{
  "type": "Feature",
  "properties": {
    "addr:full":"4298 Huron St RR 5 Stratford ON N5A 6S6",
    "addr:housenumber":"4298;5",
    "addr:postcode":"n5a 6s6",
    "addr:street":"Huron St Rr",
    "iso:country":"CA",
    "sg:address":"4298 Huron St RR 5",
    "sg:city":"Stratford",
    "sg:classifiers":[
        {
            "category":"Retail",
            "subcategory":"Auto Repair",
            "type":"Services"
        }
    ],
    "sg:phone":"+1 519 393 6164",
    "sg:postcode":"N5A 6S6",
    "sg:province":"ON",
    "sg:tags":[
        "body",
        "automobile",
        "painting"
    ],
    "wof:name":"Al's Auto Body",
    "wof:placetype":"venue"
},
  "geometry": {"coordinates":[-80.98192596440001,43.370136261],"type":"Point"}
}