{
  "type": "Feature",
  "properties": {
    "iso:country":"CA",
    "sg:address":"5485 Boul Jean-Xxiii",
    "sg:city":"Trois-Rivieres-Ouest",
    "sg:classifiers":[
        {
            "category":"Retail",
            "subcategory":"Auto Repair",
            "type":"Services"
        }
    ],
    "sg:phone":"+1 819 374 8433",
    "sg:postcode":"G8Z 4A8",
    "sg:province":"QC",
    "sg:tags":[
        "repairing",
        "automobile",
        "muffler",
        "exhaust"
    ],
    "wof:name":"Beauchesne Alignement",
    "wof:placetype":"venue"
},
  "geometry": {"coordinates":[-72.5897979736,46.3352737427],"type":"Point"}
}