{
  "type": "Feature",
  "properties": {
    "addr:full":"Hope BC V0X 1L0",
    "addr:postcode":"v0x 1l0",
    "iso:country":"CA",
    "sg:city":"Hope",
    "sg:classifiers":[
        {
            "category":"Restaurant",
            "type":"Food & Drink"
        }
    ],
    "sg:phone":"+1 604 869 3354",
    "sg:postcode":"V0X 1L0",
    "sg:province":"BC",
    "sg:tags":[
        "delicatessen"
    ],
    "wof:name":"Sharon's Deli & Lunch Bar",
    "wof:placetype":"venue"
},
  "geometry": {"coordinates":[-121.440651,49.37973],"type":"Point"}
}