{
  "type": "Feature",
  "properties": {
    "addr:full":"1435 Rue City Councillors Montreal QC H3A 2E4",
    "addr:housenumber":"1435",
    "addr:postcode":"h3a 2e4",
    "addr:street":"Rue City Councillors",
    "iso:country":"CA",
    "sg:address":"1435 Rue City Councillors",
    "sg:city":"Montreal",
    "sg:classifiers":[
        {
            "category":"Organizations",
            "subcategory":"Religious Organization",
            "type":"Services"
        }
    ],
    "sg:phone":"+1 514 282 1449",
    "sg:postcode":"H3A 2E4",
    "sg:province":"QC",
    "wof:name":"Communaute Culturel",
    "wof:placetype":"venue"
},
  "geometry": {"coordinates":[-73.568642,45.505146],"type":"Point"}
}