{
  "type": "Feature",
  "properties": {
    "addr:full":"901 Boul Lachapelle Saint-Jerome QC J7Z 7M4",
    "addr:housenumber":"901",
    "addr:postcode":"j7z 7m4",
    "addr:street":"Boul Lachapelle Saint-Jerome",
    "iso:country":"CA",
    "sg:address":"901 Boul Lachapelle",
    "sg:city":"Saint-Jerome",
    "sg:classifiers":[
        {
            "category":"Retail",
            "subcategory":"Repair Shop",
            "type":"Services"
        }
    ],
    "sg:phone":"+1 450 438 8623",
    "sg:postcode":"J7Z 7M4",
    "sg:province":"QC",
    "sg:tags":[
        "lock",
        "locksmith"
    ],
    "wof:name":"Decoration Paquette & Fils Inc",
    "wof:placetype":"venue"
},
  "geometry": {"coordinates":[-73.98233,45.764427],"type":"Point"}
}