{
  "type": "Feature",
  "properties": {
    "addr:full":"24 Centennial Dr Seaforth ON N0K 1W0",
    "addr:housenumber":"24",
    "addr:postcode":"n0k 1w0",
    "addr:street":"Centennial Dr",
    "iso:country":"CA",
    "sg:address":"24 Centennial Dr",
    "sg:city":"Seaforth",
    "sg:classifiers":[
        {
            "category":"Health Services",
            "subcategory":"Hospital",
            "type":"Services"
        }
    ],
    "sg:phone":"+1 519 527 1650",
    "sg:postcode":"N0K 1W0",
    "sg:province":"ON",
    "wof:name":"Seaforth Community Hospital",
    "wof:placetype":"venue"
},
  "geometry": {"coordinates":[-81.38640599999999,43.550598],"type":"Point"}
}