{
  "type": "Feature",
  "properties": {
    "addr:full":"385 Rue Saint-Etienne LA Malbaie QC G5A 1S8",
    "addr:housenumber":"385",
    "addr:postcode":"g5a 1s8",
    "addr:street":"Rue Saint-Etienne",
    "iso:country":"CA",
    "sg:address":"385 Rue Saint-Etienne",
    "sg:city":"LA Malbaie",
    "sg:classifiers":[
        {
            "category":"Social Services",
            "type":"Services"
        }
    ],
    "sg:phone":"+1 418 665 3981",
    "sg:postcode":"G5A 1S8",
    "sg:province":"QC",
    "sg:tags":[
        "organization",
        "welfare"
    ],
    "wof:name":"Centre Jeunesse DE Quebec",
    "wof:placetype":"venue"
},
  "geometry": {"coordinates":[-70.1495437622,47.6536254883],"type":"Point"}
}