{
  "type": "Feature",
  "properties": {
    "iso:country":"CA",
    "sg:address":"1732 Rue Paul-Broca",
    "sg:city":"Laval",
    "sg:classifiers":[
        {
            "category":"Building & Trades",
            "subcategory":"Construction",
            "type":"Services"
        }
    ],
    "sg:phone":"+1 450 662 1146",
    "sg:postcode":"H7M 6B1",
    "sg:province":"QC",
    "sg:tags":[
        "resurfacing",
        "laying",
        "refinishing",
        "floor"
    ],
    "wof:name":"Entreprises B Lambert Enr",
    "wof:placetype":"venue"
},
  "geometry": {"coordinates":[-73.7021408081,45.6077651978],"type":"Point"}
}