{
  "type": "Feature",
  "properties": {
    "addr:full":"3017 Carriage Rd Delaware ON N0L 1E0",
    "addr:housenumber":"3017",
    "addr:postcode":"n0l 1e0",
    "addr:street":"Carriage Rd",
    "iso:country":"CA",
    "sg:address":"3017 Carriage Rd",
    "sg:city":"Delaware",
    "sg:classifiers":[
        {
            "category":"Travel",
            "subcategory":"Hotels & Motels",
            "type":"Entertainment"
        }
    ],
    "sg:phone":"+1 519 471 3799",
    "sg:postcode":"N0L 1E0",
    "sg:province":"ON",
    "sg:tags":[
        "resort",
        "skiing",
        "center",
        "stable"
    ],
    "wof:name":"Circle R Ranch",
    "wof:placetype":"venue"
},
  "geometry": {"coordinates":[-81.399612,42.924232],"type":"Point"}
}