{
  "type": "Feature",
  "properties": {
    "addr:full":"Milton ON L9T 5E3",
    "addr:postcode":"l9t 5e3",
    "iso:country":"CA",
    "sg:city":"Milton",
    "sg:classifiers":[
        {
            "category":"Professional",
            "subcategory":"Management & Consulting",
            "type":"Services"
        }
    ],
    "sg:phone":"+1 905 875 0023",
    "sg:postcode":"L9T 5E3",
    "sg:province":"ON",
    "sg:tags":[
        "consultant",
        "freight"
    ],
    "wof:name":"Expedite Plus",
    "wof:placetype":"venue"
},
  "geometry": {"coordinates":[-79.86312103269999,43.5237426758],"type":"Point"}
}