{
  "type": "Feature",
  "properties": {
    "addr:full":"51 Rue Frontenac Saint-Jean-Sur-Richelieu QC J3B 2Y3",
    "addr:housenumber":"51",
    "addr:postcode":"j3b 2y3",
    "addr:street":"Rue Frontenac",
    "iso:country":"CA",
    "sg:address":"51 Rue Frontenac",
    "sg:city":"Saint-Jean-Sur-Richelieu",
    "sg:classifiers":[
        {
            "category":"Social Services",
            "subcategory":"Child Care",
            "type":"Services"
        }
    ],
    "sg:phone":"+1 450 346 5312",
    "sg:postcode":"J3B 2Y3",
    "sg:province":"QC",
    "sg:tags":[
        "school"
    ],
    "wof:name":"Centre DE LA Petite Enfance",
    "wof:placetype":"venue"
},
  "geometry": {"coordinates":[-73.255234,45.302944],"type":"Point"}
}