{
  "type": "Feature",
  "properties": {
    "addr:full":"798 Bank St Ottawa ON K1S 3V8",
    "addr:housenumber":"798",
    "addr:postcode":"k1s 3v8",
    "addr:street":"Bank St",
    "iso:country":"CA",
    "sg:address":"798 Bank St",
    "sg:city":"Ottawa",
    "sg:classifiers":[
        {
            "category":"Food & Beverages",
            "subcategory":"Candy",
            "type":"Retail Goods"
        }
    ],
    "sg:phone":"+1 613 236 1095",
    "sg:postcode":"K1S 3V8",
    "sg:province":"ON",
    "sg:tags":[
        "parlor",
        "ice",
        "cream"
    ],
    "wof:name":"Purple Cow Fudge & Candy CO",
    "wof:placetype":"venue"
},
  "geometry": {"coordinates":[-75.688446,45.402836],"type":"Point"}
}