{
  "type": "Feature",
  "properties": {
    "addr:full":"Pointe-Claire QC H9R 1E9",
    "addr:postcode":"h9r 1e9",
    "iso:country":"CA",
    "sg:city":"Pointe-Claire",
    "sg:classifiers":[
        {
            "category":"Food & Beverages",
            "subcategory":"Bakery",
            "type":"Retail Goods"
        }
    ],
    "sg:phone":"+1 514 426 0787",
    "sg:postcode":"H9R 1E9",
    "sg:province":"QC",
    "sg:tags":[
        "doughnut"
    ],
    "wof:name":"Tim Hortons",
    "wof:placetype":"venue"
},
  "geometry": {"coordinates":[-73.8176498413,45.4615135193],"type":"Point"}
}