{
  "type": "Feature",
  "properties": {
    "addr:full":"Toronto ON M4S 1C1",
    "addr:postcode":"m4s 1c1",
    "iso:country":"CA",
    "sg:city":"Toronto",
    "sg:classifiers":[
        {
            "category":"Personal",
            "subcategory":"Beauty Salon",
            "type":"Services"
        }
    ],
    "sg:phone":"+1 416 487 8869",
    "sg:postcode":"M4S 1C1",
    "sg:province":"ON",
    "wof:name":"Siinardi Hair Design",
    "wof:placetype":"venue"
},
  "geometry": {"coordinates":[-79.395362854,43.6977272034],"type":"Point"}
}