{
  "type": "Feature",
  "properties": {
    "addr:full":"25 Campus Dr Saskatoon SK S7N 5A7",
    "addr:housenumber":"25",
    "addr:postcode":"s7n 5a7",
    "addr:street":"Campus Dr",
    "iso:country":"CA",
    "sg:address":"25 Campus Dr",
    "sg:city":"Saskatoon",
    "sg:classifiers":[
        {
            "category":"Professional",
            "subcategory":"Management & Consulting",
            "type":"Services"
        }
    ],
    "sg:phone":"+1 306 966 8686",
    "sg:postcode":"S7N 5A7",
    "sg:province":"SK",
    "sg:tags":[
        "consultant",
        "business"
    ],
    "wof:name":"Business Advisory Svc",
    "wof:placetype":"venue"
},
  "geometry": {"coordinates":[-106.638870239,52.1332626343],"type":"Point"}
}