{
  "type": "Feature",
  "properties": {
    "addr:full":"Trois-Rivieres-Ouest QC G8Y 6S6",
    "addr:postcode":"g8y 6s6",
    "iso:country":"CA",
    "sg:city":"Trois-Rivieres-Ouest",
    "sg:classifiers":[
        {
            "category":"Real Estate",
            "subcategory":"Real Estate Agent",
            "type":"Services"
        }
    ],
    "sg:phone":"+1 819 374 4136",
    "sg:postcode":"G8Y 6S6",
    "sg:province":"QC",
    "sg:tags":[
        "appraiser"
    ],
    "wof:name":"Jean-Louis Hannis Inc",
    "wof:placetype":"venue"
},
  "geometry": {"coordinates":[-72.608124,46.338287],"type":"Point"}
}