{
  "type": "Feature",
  "properties": {
    "addr:full":"5550 Rue Saint-Patrick Montreal QC H4E 1A9",
    "addr:housenumber":"5550",
    "addr:postcode":"h4e 1a9",
    "addr:street":"Rue Saint-Patrick",
    "iso:country":"CA",
    "sg:address":"5550 Rue Saint-Patrick",
    "sg:city":"Montreal",
    "sg:classifiers":[
        {
            "category":"Manufacturing",
            "subcategory":"Printing",
            "type":"Manufacturing & Wholesale Goods"
        }
    ],
    "sg:phone":"+1 514 761 5577",
    "sg:postcode":"H4E 1A9",
    "sg:province":"QC",
    "sg:tags":[
        "printer"
    ],
    "wof:name":"Imprimerie & Envoi Automatique",
    "wof:placetype":"venue"
},
  "geometry": {"coordinates":[-73.59716796879999,45.46301651],"type":"Point"}
}