{
  "type": "Feature",
  "properties": {
    "addr:full":"2795 Rue Du Camping Sainte-Julienne QC J0K 2T0",
    "addr:housenumber":"2795",
    "addr:postcode":"j0k 2t0",
    "addr:street":"Rue Du Camping",
    "iso:country":"CA",
    "sg:address":"2795 Rue Du Camping",
    "sg:city":"Sainte-Julienne",
    "sg:classifiers":[
        {
            "category":"Travel",
            "subcategory":"Campground",
            "type":"Entertainment"
        }
    ],
    "sg:phone":"+1 450 831 2422",
    "sg:postcode":"J0K 2T0",
    "sg:province":"QC",
    "wof:name":"Camping Kelly Enr",
    "wof:placetype":"venue"
},
  "geometry": {"coordinates":[-73.7079238892,45.9627075195],"type":"Point"}
}