{
  "type": "Feature",
  "properties": {
    "addr:full":"361 Rue Gingras # 361 Sainte-Foy QC G1X 4H4",
    "addr:housenumber":"361",
    "addr:postcode":"g1x 4h4",
    "addr:street":"Rue Gingras # 361 Sainte-Foy",
    "iso:country":"CA",
    "sg:address":"361 Rue Gingras # 361",
    "sg:city":"Sainte-Foy",
    "sg:classifiers":[
        {
            "category":"Restaurant",
            "type":"Food & Drink"
        }
    ],
    "sg:phone":"+1 418 653 3092",
    "sg:postcode":"G1X 4H4",
    "sg:province":"QC",
    "sg:tags":[
        "caterer"
    ],
    "wof:name":"Services Alimentaire-Gourmet",
    "wof:placetype":"venue"
},
  "geometry": {"coordinates":[-71.3358306885,46.7655220032],"type":"Point"}
}