{
  "type": "Feature",
  "properties": {
    "iso:country":"CA",
    "sg:city":"Waterloo",
    "sg:classifiers":[
        {
            "category":"Building & Trades",
            "subcategory":"Plumbing",
            "type":"Services"
        }
    ],
    "sg:phone":"+1 519 885 5513",
    "sg:postcode":"N2L 5V4",
    "sg:province":"ON",
    "sg:tags":[
        "control",
        "air",
        "pollution"
    ],
    "wof:name":"Turbosonic Inc",
    "wof:placetype":"venue"
},
  "geometry": {"coordinates":[-80.5443115234,43.493396759],"type":"Point"}
}