{
  "type": "Feature",
  "properties": {
    "addr:full":"Cambridge ON N1R 6B3",
    "addr:postcode":"n1r 6b3",
    "iso:country":"CA",
    "sg:city":"Cambridge",
    "sg:classifiers":[
        {
            "category":"Manufacturing",
            "subcategory":"Printing",
            "type":"Manufacturing & Wholesale Goods"
        }
    ],
    "sg:phone":"+1 519 623 9588",
    "sg:postcode":"N1R 6B3",
    "sg:province":"ON",
    "sg:tags":[
        "printer"
    ],
    "wof:name":"Print Three",
    "wof:placetype":"venue"
},
  "geometry": {"coordinates":[-80.32270050050001,43.3920707703],"type":"Point"}
}