{
  "type": "Feature",
  "properties": {
    "addr:full":"7077 Boul Newman Lasalle QC H8N 1X1",
    "addr:housenumber":"7077",
    "addr:postcode":"h8n 1x1",
    "addr:street":"Boul Newman",
    "iso:country":"CA",
    "sg:address":"7077 Boul Newman",
    "sg:city":"Lasalle",
    "sg:classifiers":[
        {
            "category":"Food & Beverages",
            "subcategory":"Dairy",
            "type":"Retail Goods"
        }
    ],
    "sg:phone":"+1 514 367 4498",
    "sg:postcode":"H8N 1X1",
    "sg:province":"QC",
    "sg:tags":[
        "yogurt"
    ],
    "wof:name":"Yogen Fruz Frozen Yogurt",
    "wof:placetype":"venue"
},
  "geometry": {"coordinates":[-73.6108169556,45.4471321106],"type":"Point"}
}