{
  "type": "Feature",
  "properties": {
    "iso:country":"CA",
    "sg:city":"Saskatoon",
    "sg:classifiers":[
        {
            "category":"Shopping",
            "subcategory":"Music",
            "type":"Retail Goods"
        }
    ],
    "sg:phone":"+1 306 244 7640",
    "sg:postcode":"S7N 1A9",
    "sg:province":"SK",
    "sg:tags":[
        "compact",
        "record",
        "disc",
        "tape"
    ],
    "wof:name":"Vinyl Diner C D's & Records",
    "wof:placetype":"venue"
},
  "geometry": {"coordinates":[-106.657066345,52.1194801331],"type":"Point"}
}