{
  "type": "Feature",
  "properties": {
    "addr:full":"Edmonton AB T6J 6B7",
    "addr:postcode":"t6j 6b7",
    "iso:country":"CA",
    "sg:city":"Edmonton",
    "sg:classifiers":[
        {
            "category":"Health Services",
            "subcategory":"Medical Lab",
            "type":"Services"
        }
    ],
    "sg:phone":"+1 780 436 7386",
    "sg:postcode":"T6J 6B7",
    "sg:province":"AB",
    "sg:tags":[
        "laboratory"
    ],
    "wof:name":"Heritage Dental Lab Ltd",
    "wof:placetype":"venue"
},
  "geometry": {"coordinates":[-113.509635925,53.4592933655],"type":"Point"}
}