{
  "type": "Feature",
  "properties": {
    "addr:full":"33651 Busby Rd Abbotsford BC V2S 1V2",
    "addr:housenumber":"33651",
    "addr:postcode":"v2s 1v2",
    "addr:street":"Busby Rd",
    "iso:country":"CA",
    "sg:address":"33651 Busby Rd",
    "sg:city":"Abbotsford",
    "sg:classifiers":[
        {
            "category":"Organizations",
            "subcategory":"Religious Organization",
            "type":"Services"
        }
    ],
    "sg:phone":"+1 604 853 5821",
    "sg:postcode":"V2S 1V2",
    "sg:province":"BC",
    "sg:tags":[
        "church"
    ],
    "wof:name":"Abbotsford Baptist Church",
    "wof:placetype":"venue"
},
  "geometry": {"coordinates":[-122.292252,49.043526],"type":"Point"}
}