{
  "type": "Feature",
  "properties": {
    "addr:full":"Richmond Hill ON L4C 3C7",
    "addr:postcode":"l4c 3c7",
    "iso:country":"CA",
    "sg:city":"Richmond Hill",
    "sg:classifiers":[
        {
            "category":"Shopping",
            "type":"Retail Goods"
        }
    ],
    "sg:phone":"+1 905 737 4758",
    "sg:postcode":"L4C 3C7",
    "sg:province":"ON",
    "sg:tags":[
        "photographer",
        "wedding",
        "supply"
    ],
    "wof:name":"Sooter Portrait Studios",
    "wof:placetype":"venue"
},
  "geometry": {"coordinates":[-79.44036865229999,43.883972168],"type":"Point"}
}