{
  "type": "Feature",
  "properties": {
    "addr:full":"1303 Docliddle Rd Comox BC V9M 2R4",
    "addr:housenumber":"1303",
    "addr:postcode":"v9m 2r4",
    "addr:street":"Docliddle Rd",
    "iso:country":"CA",
    "sg:address":"1303 Docliddle Rd",
    "sg:city":"Comox",
    "sg:classifiers":[
        {
            "category":"Building & Trades",
            "subcategory":"Landscaping Services",
            "type":"Services"
        }
    ],
    "sg:phone":"+1 250 338 0348",
    "sg:postcode":"V9M 2R4",
    "sg:province":"BC",
    "sg:tags":[
        "landscape",
        "contractor"
    ],
    "wof:name":"Island Yard Svc",
    "wof:placetype":"venue"
},
  "geometry": {"coordinates":[-124.92681899999999,49.673538],"type":"Point"}
}