{
  "type": "Feature",
  "properties": {
    "iso:country":"CA",
    "sg:city":"Surrey",
    "sg:classifiers":[
        {
            "category":"Professional",
            "subcategory":"Accounting & Tax Preparation",
            "type":"Services"
        }
    ],
    "sg:phone":"+1 604 536 4373",
    "sg:postcode":"V4A 5A4",
    "sg:province":"BC",
    "sg:tags":[
        "accountant"
    ],
    "wof:name":"Karvellas, Helen E CA",
    "wof:placetype":"venue"
},
  "geometry": {"coordinates":[-122.793343,49.045158],"type":"Point"}
}