{
  "type": "Feature",
  "properties": {
    "addr:full":"104 Citadel Hills Green NW Calgary AB T3G 3T6",
    "addr:housenumber":"104",
    "addr:postcode":"t3g 3t6",
    "addr:street":"Citadel Hills Green Nw",
    "iso:country":"CA",
    "sg:address":"104 Citadel Hills Green NW",
    "sg:city":"Calgary",
    "sg:classifiers":[
        {
            "category":"Wholesale",
            "subcategory":"Non-durable Goods",
            "type":"Manufacturing & Wholesale Goods"
        }
    ],
    "sg:phone":"+1 403 241 3214",
    "sg:postcode":"T3G 3T6",
    "sg:province":"AB",
    "sg:tags":[
        "advertising"
    ],
    "wof:name":"Citadel Promotional Sales Inc",
    "wof:placetype":"venue"
},
  "geometry": {"coordinates":[-114.174538,51.138699],"type":"Point"}
}