{
  "type": "Feature",
  "properties": {
    "iso:country":"CA",
    "sg:address":"455 Av Lafleur",
    "sg:city":"Lasalle",
    "sg:classifiers":[
        {
            "category":"Restaurant",
            "type":"Food & Drink"
        }
    ],
    "sg:phone":"+1 514 366 3234",
    "sg:postcode":"H8R 3H8",
    "sg:province":"QC",
    "wof:name":"Serano Restaurant",
    "wof:placetype":"venue"
},
  "geometry": {"coordinates":[-73.6459655762,45.4331169128],"type":"Point"}
}