{
  "type": "Feature",
  "properties": {
    "addr:full":"165 Boul Canam S Saint-Gedeon-DE-Beauce QC G0M 1T0",
    "addr:housenumber":"165",
    "addr:postcode":"g0m 1t0",
    "addr:street":"Boul Canam S Saint-Gedeon-De-Beauce",
    "iso:country":"CA",
    "sg:address":"165 Boul Canam S",
    "sg:city":"Saint-Gedeon-DE-Beauce",
    "sg:classifiers":[
        {
            "category":"Building & Trades",
            "subcategory":"Construction",
            "type":"Services"
        }
    ],
    "sg:phone":"+1 418 582 3006",
    "sg:postcode":"G0M 1T0",
    "sg:province":"QC",
    "sg:tags":[
        "general",
        "contractor"
    ],
    "wof:name":"G-Mar-Tec Inc",
    "wof:placetype":"venue"
},
  "geometry": {"coordinates":[-70.635712,45.851536],"type":"Point"}
}