{
  "type": "Feature",
  "properties": {
    "addr:full":"Richmond BC V7C 5J8",
    "addr:postcode":"v7c 5j8",
    "iso:country":"CA",
    "sg:city":"Richmond",
    "sg:classifiers":[
        {
            "category":"Wholesale",
            "subcategory":"Durable Goods & Equipment",
            "type":"Manufacturing & Wholesale Goods"
        }
    ],
    "sg:phone":"+1 604 278 7221",
    "sg:postcode":"V7C 5J8",
    "sg:province":"BC",
    "sg:tags":[
        "exporter"
    ],
    "wof:name":"Upper Creek Exporting",
    "wof:placetype":"venue"
},
  "geometry": {"coordinates":[-123.136512756,49.1631736755],"type":"Point"}
}