{
  "type": "Feature",
  "properties": {
    "addr:full":"1199 Badger Cres Pincher Creek AB T0K 1W0",
    "addr:housenumber":"1199",
    "addr:postcode":"t0k 1w0",
    "addr:street":"Badger Cres",
    "iso:country":"CA",
    "sg:address":"1199 Badger Cres",
    "sg:city":"Pincher Creek",
    "sg:classifiers":[
        {
            "category":"Building & Trades",
            "subcategory":"Construction",
            "type":"Services"
        }
    ],
    "sg:phone":"+1 403 627 2264",
    "sg:postcode":"T0K 1W0",
    "sg:province":"AB",
    "sg:tags":[
        "concrete",
        "contractor"
    ],
    "wof:name":"Reg O'Sullivan Construction CO",
    "wof:placetype":"venue"
},
  "geometry": {"coordinates":[-113.929580688,49.4882774353],"type":"Point"}
}