{
  "type": "Feature",
  "properties": {
    "addr:full":"8559 Boul Pie-Ix Montreal QC H1Z 3T9",
    "addr:housenumber":"8559",
    "addr:postcode":"h1z 3t9",
    "addr:street":"Boul Pie-Ix",
    "iso:country":"CA",
    "sg:address":"8559 Boul Pie-Ix",
    "sg:city":"Montreal",
    "sg:classifiers":[
        {
            "category":"Banks & Credit Unions",
            "subcategory":"Bank",
            "type":"Services"
        }
    ],
    "sg:phone":"+1 514 323 7622",
    "sg:postcode":"H1Z 3T9",
    "sg:province":"QC",
    "sg:tags":[
        "banking",
        "market",
        "system",
        "analysis",
        "research"
    ],
    "wof:name":"Soca Transfer Inc",
    "wof:placetype":"venue"
},
  "geometry": {"coordinates":[-73.6112442017,45.5755348206],"type":"Point"}
}