{
  "type": "Feature",
  "properties": {
    "addr:full":"Lethbridge AB T1J 4L9",
    "addr:postcode":"t1j 4l9",
    "iso:country":"CA",
    "sg:city":"Lethbridge",
    "sg:classifiers":[
        {
            "category":"Restaurant",
            "type":"Food & Drink"
        }
    ],
    "sg:phone":"+1 403 320 1646",
    "sg:postcode":"T1J 4L9",
    "sg:province":"AB",
    "wof:name":"Smitty's Pancake House",
    "wof:placetype":"venue"
},
  "geometry": {"coordinates":[-112.840377808,49.6980628967],"type":"Point"}
}