{
  "type": "Feature",
  "properties": {
    "addr:full":"111 Charles St E Ingersoll ON N5C 1J9",
    "addr:housenumber":"111",
    "addr:postcode":"n5c 1j9",
    "addr:street":"Charles St E",
    "iso:country":"CA",
    "sg:address":"111 Charles St E",
    "sg:city":"Ingersoll",
    "sg:classifiers":[
        {
            "category":"Retail",
            "subcategory":"Photofinishing",
            "type":"Services"
        }
    ],
    "sg:phone":"+1 519 485 0203",
    "sg:postcode":"N5C 1J9",
    "sg:province":"ON",
    "sg:tags":[
        "photo",
        "finishing"
    ],
    "wof:name":"Carman's Foto Source",
    "wof:placetype":"venue"
},
  "geometry": {"coordinates":[-80.88016500000001,43.041317],"type":"Point"}
}