{
  "type": "Feature",
  "properties": {
    "addr:full":"6561 Rue Beaubien E Montreal QC H1M 1B1",
    "addr:housenumber":"6561",
    "addr:postcode":"h1m 1b1",
    "addr:street":"Rue Beaubien E",
    "iso:country":"CA",
    "sg:address":"6561 Rue Beaubien E",
    "sg:city":"Montreal",
    "sg:classifiers":[
        {
            "category":"Food & Beverages",
            "subcategory":"Bakery",
            "type":"Retail Goods"
        }
    ],
    "sg:phone":"+1 514 259 2545",
    "sg:postcode":"H1M 1B1",
    "sg:province":"QC",
    "sg:tags":[
        "baker"
    ],
    "wof:name":"Boulangerie Patisserie",
    "wof:placetype":"venue"
},
  "geometry": {"coordinates":[-73.56104999999999,45.587883],"type":"Point"}
}