{
  "type": "Feature",
  "properties": {
    "addr:full":"180 Lake Nosbonsing Rd Callander ON P0H 1H0",
    "addr:housenumber":"180",
    "addr:postcode":"p0h 1h0",
    "addr:street":"Lake Nosbonsing Rd",
    "iso:country":"CA",
    "sg:address":"180 Lake Nosbonsing Rd",
    "sg:city":"Callander",
    "sg:classifiers":[
        {
            "category":"Autos & Motor Vehicles",
            "subcategory":"Recreational Vehicle Sales",
            "type":"Retail Goods"
        }
    ],
    "sg:phone":"+1 705 752 3554",
    "sg:postcode":"P0H 1H0",
    "sg:province":"ON",
    "wof:name":"Delorme's Recreational Vehicle",
    "wof:placetype":"venue"
},
  "geometry": {"coordinates":[-79.35128,46.19397],"type":"Point"}
}