{
  "type": "Feature",
  "properties": {
    "iso:country":"CA",
    "sg:city":"Clearwater",
    "sg:classifiers":[
        {
            "category":"Retail",
            "subcategory":"Self-service Laundry",
            "type":"Services"
        }
    ],
    "sg:phone":"+1 250 674 2567",
    "sg:postcode":"V0E 1N0",
    "sg:province":"BC",
    "wof:name":"Loonie Plus Variety Store",
    "wof:placetype":"venue"
},
  "geometry": {"coordinates":[-120.034812927,51.6509208679],"type":"Point"}
}