{
  "type": "Feature",
  "properties": {
    "addr:full":"329 Main St S St Lazare MB R0M 1Y0",
    "addr:housenumber":"329",
    "addr:postcode":"r0m 1y0",
    "addr:street":"Main St S St Lazare",
    "iso:country":"CA",
    "sg:address":"329 Main St S",
    "sg:city":"St Lazare",
    "sg:classifiers":[
        {
            "category":"Shopping",
            "subcategory":"Florist",
            "type":"Retail Goods"
        }
    ],
    "sg:phone":"+1 204 683 2356",
    "sg:postcode":"R0M 1Y0",
    "sg:province":"MB",
    "wof:name":"Bird's Boutique",
    "wof:placetype":"venue"
},
  "geometry": {"coordinates":[-101.303253,50.448906],"type":"Point"}
}