{
  "type": "Feature",
  "properties": {
    "addr:full":"Lethbridge AB T1J 0P6",
    "addr:postcode":"t1j 0p6",
    "iso:country":"CA",
    "sg:city":"Lethbridge",
    "sg:classifiers":[
        {
            "category":"Government",
            "subcategory":"Office",
            "type":"Public Place"
        }
    ],
    "sg:phone":"+1 403 320 3020",
    "sg:postcode":"T1J 0P6",
    "sg:province":"AB",
    "sg:tags":[
        "village"
    ],
    "wof:name":"Lethbridge Leisure Svc",
    "wof:placetype":"venue"
},
  "geometry": {"coordinates":[-112.833518982,49.6944580078],"type":"Point"}
}