{
  "type": "Feature",
  "properties": {
    "iso:country":"CA",
    "sg:address":"1250 Boul Rene-Levesque O",
    "sg:city":"Montreal",
    "sg:classifiers":[
        {
            "category":"Restaurant",
            "type":"Food & Drink"
        }
    ],
    "sg:phone":"+1 514 933 1104",
    "sg:postcode":"H3B 4W8",
    "sg:province":"QC",
    "wof:name":"Treats Coffee Emporium",
    "wof:placetype":"venue"
},
  "geometry": {"coordinates":[-73.553131,45.517662],"type":"Point"}
}