{
  "type": "Feature",
  "properties": {
    "addr:full":"415 Rue Jean-Talon O Montreal QC H3N 1P9",
    "addr:housenumber":"415",
    "addr:postcode":"h3n 1p9",
    "addr:street":"Rue Jean-Talon O",
    "iso:country":"CA",
    "sg:address":"415 Rue Jean-Talon O",
    "sg:city":"Montreal",
    "sg:classifiers":[
        {
            "category":"Shopping",
            "subcategory":"Jewelry",
            "type":"Retail Goods"
        }
    ],
    "sg:phone":"+1 514 278 6600",
    "sg:postcode":"H3N 1P9",
    "sg:province":"QC",
    "wof:name":"Bijouterie Kalina",
    "wof:placetype":"venue"
},
  "geometry": {"coordinates":[-73.61451,45.538517],"type":"Point"}
}