{
  "type": "Feature",
  "properties": {
    "addr:full":"700 Pembina Hwy Winnipeg MB R3M 2M6",
    "addr:housenumber":"700",
    "addr:postcode":"r3m 2m6",
    "addr:street":"Pembina Hwy",
    "iso:country":"CA",
    "sg:address":"700 Pembina Hwy",
    "sg:city":"Winnipeg",
    "sg:classifiers":[
        {
            "category":"Retail",
            "subcategory":"Auto Repair",
            "type":"Services"
        }
    ],
    "sg:phone":"+1 204 475 6161",
    "sg:postcode":"R3M 2M6",
    "sg:province":"MB",
    "sg:tags":[
        "transmission"
    ],
    "wof:name":"Bob's Transmissions",
    "wof:placetype":"venue"
},
  "geometry": {"coordinates":[-97.149399,49.860847],"type":"Point"}
}