{
  "type": "Feature",
  "properties": {
    "addr:full":"RR 1 Cherhill AB T0E 0J0",
    "addr:postcode":"t0e 0j0",
    "addr:street":"Rr 1 Cherhill",
    "iso:country":"CA",
    "sg:address":"RR 1",
    "sg:city":"Cherhill",
    "sg:classifiers":[
        {
            "category":"Wholesale",
            "subcategory":"Machinery & Supplies",
            "type":"Manufacturing & Wholesale Goods"
        }
    ],
    "sg:phone":"+1 780 785 2187",
    "sg:postcode":"T0E 0J0",
    "sg:province":"AB",
    "sg:tags":[
        "trailer"
    ],
    "wof:name":"Flying L Trailer Sales",
    "wof:placetype":"venue"
},
  "geometry": {"coordinates":[-114.68444061300001,53.820400238],"type":"Point"}
}