{
  "type": "Feature",
  "properties": {
    "addr:full":"481 Sammon Ave East York ON M4J 2B3",
    "addr:housenumber":"481",
    "addr:postcode":"m4j 2b3",
    "addr:street":"Sammon Ave",
    "iso:country":"CA",
    "sg:address":"481 Sammon Ave",
    "sg:city":"East York",
    "sg:classifiers":[
        {
            "category":"Autos & Motor Vehicles",
            "subcategory":"Automobile Sales",
            "type":"Retail Goods"
        }
    ],
    "sg:phone":"+1 416 462 1992",
    "sg:postcode":"M4J 2B3",
    "sg:province":"ON",
    "sg:tags":[
        "classic"
    ],
    "wof:name":"A & R Motor Cars Intl Inc",
    "wof:placetype":"venue"
},
  "geometry": {"coordinates":[-79.3287734985,43.688041687],"type":"Point"}
}