{
  "type": "Feature",
  "properties": {
    "addr:full":"715 Milner Ave Scarborough ON M1B 2K8",
    "addr:housenumber":"715",
    "addr:postcode":"m1b 2k8",
    "addr:street":"Milner Ave",
    "iso:country":"CA",
    "sg:address":"715 Milner Ave",
    "sg:city":"Scarborough",
    "sg:classifiers":[
        {
            "category":"Autos & Motor Vehicles",
            "subcategory":"Automobile Sales",
            "type":"Retail Goods"
        }
    ],
    "sg:phone":"+1 416 284 8110",
    "sg:postcode":"M1B 2K8",
    "sg:province":"ON",
    "sg:tags":[
        "car",
        "dealer"
    ],
    "wof:name":"Acura",
    "wof:placetype":"venue"
},
  "geometry": {"coordinates":[-79.2080001831,43.7963981628],"type":"Point"}
}