{
  "type": "Feature",
  "properties": {
    "addr:full":"920 Clark Dr Vancouver BC V5L 3J8",
    "addr:housenumber":"920",
    "addr:postcode":"v5l 3j8",
    "addr:street":"Clark Dr",
    "iso:country":"CA",
    "sg:address":"920 Clark Dr",
    "sg:city":"Vancouver",
    "sg:classifiers":[
        {
            "category":"Manufacturing",
            "subcategory":"Metals",
            "type":"Manufacturing & Wholesale Goods"
        }
    ],
    "sg:phone":"+1 604 255 3227",
    "sg:postcode":"V5L 3J8",
    "sg:province":"BC",
    "sg:tags":[
        "ornamental",
        "work",
        "bronze"
    ],
    "wof:name":"Custom Bronze Foundry Ltd",
    "wof:placetype":"venue"
},
  "geometry": {"coordinates":[-123.077041626,49.2765426636],"type":"Point"}
}