{
  "type": "Feature",
  "properties": {
    "addr:full":"Dildo NL A0B 1P0",
    "addr:postcode":"a0b 1p0",
    "iso:country":"CA",
    "sg:city":"Dildo",
    "sg:classifiers":[
        {
            "category":"Retail",
            "subcategory":"Funeral Services",
            "type":"Services"
        }
    ],
    "sg:phone":"+1 709 582 3118",
    "sg:postcode":"A0B 1P0",
    "sg:province":"NL",
    "sg:tags":[
        "director"
    ],
    "wof:name":"Warren's Funeral Home",
    "wof:placetype":"venue"
},
  "geometry": {"coordinates":[-53.5485687256,47.5628089905],"type":"Point"}
}