{
  "type": "Feature",
  "properties": {
    "iso:country":"CA",
    "sg:city":"Saskatoon",
    "sg:classifiers":[
        {
            "category":"Personal",
            "subcategory":"Beauty Salon",
            "type":"Services"
        }
    ],
    "sg:phone":"+1 306 652 5300",
    "sg:postcode":"S7K 7A9",
    "sg:province":"SK",
    "wof:name":"Hallmark Hair Gallery",
    "wof:placetype":"venue"
},
  "geometry": {"coordinates":[-106.65561676,52.1309356689],"type":"Point"}
}