{
  "type": "Feature",
  "properties": {
    "addr:full":"253 Finholm St N Parksville BC V9P 1H3",
    "addr:housenumber":"253",
    "addr:postcode":"v9p 1h3",
    "addr:street":"Finholm St N",
    "iso:country":"CA",
    "sg:address":"253 Finholm St N",
    "sg:city":"Parksville",
    "sg:classifiers":[
        {
            "category":"Building & Trades",
            "subcategory":"Construction",
            "type":"Services"
        }
    ],
    "sg:phone":"+1 250 954 1440",
    "sg:postcode":"V9P 1H3",
    "sg:province":"BC",
    "sg:tags":[
        "painter"
    ],
    "wof:name":"Done-Right Painting",
    "wof:placetype":"venue"
},
  "geometry": {"coordinates":[-124.32873499999999,49.324257],"type":"Point"}
}