{
  "type": "Feature",
  "properties": {
    "addr:full":"1097 56 St Delta BC V4L 2A2",
    "addr:housenumber":"1097",
    "addr:postcode":"v4l 2a2",
    "addr:street":"56 St",
    "iso:country":"CA",
    "sg:address":"1097 56 St",
    "sg:city":"Delta",
    "sg:classifiers":[
        {
            "category":"Restaurant",
            "type":"Food & Drink"
        }
    ],
    "sg:phone":"+1 604 943 7471",
    "sg:postcode":"V4L 2A2",
    "sg:province":"BC",
    "wof:name":"Alfa Greco Roman Cuisine",
    "wof:placetype":"venue"
},
  "geometry": {"coordinates":[-123.068847656,49.0230712891],"type":"Point"}
}