{
  "type": "Feature",
  "properties": {
    "iso:country":"CA",
    "sg:address":"10429 124 St NW",
    "sg:city":"Edmonton",
    "sg:classifiers":[
        {
            "category":"Shopping",
            "subcategory":"Bicycles & Sporting Goods",
            "type":"Retail Goods"
        }
    ],
    "sg:phone":"+1 780 482 5636",
    "sg:postcode":"T5N 1R7",
    "sg:province":"AB",
    "wof:name":"Western Cycle",
    "wof:placetype":"venue"
},
  "geometry": {"coordinates":[-113.53569,53.547043],"type":"Point"}
}