{
  "type": "Feature",
  "properties": {
    "addr:full":"Tring-Jonction QC G0N 1X0",
    "addr:postcode":"g0n 1x0",
    "iso:country":"CA",
    "sg:city":"Tring-Jonction",
    "sg:classifiers":[
        {
            "category":"Government",
            "subcategory":"Office",
            "type":"Public Place"
        }
    ],
    "sg:phone":"+1 418 426 2497",
    "sg:postcode":"G0N 1X0",
    "sg:province":"QC",
    "sg:tags":[
        "municipality"
    ],
    "wof:name":"Tring Jonction Municipalite",
    "wof:placetype":"venue"
},
  "geometry": {"coordinates":[-70.9949798584,46.2710723877],"type":"Point"}
}