{
  "type": "Feature",
  "properties": {
    "iso:country":"CA",
    "sg:city":"Calgary",
    "sg:classifiers":[
        {
            "category":"Personal",
            "subcategory":"Beauty Salon",
            "type":"Services"
        }
    ],
    "sg:phone":"+1 403 236 0303",
    "sg:postcode":"T2C 1Y1",
    "sg:province":"AB",
    "wof:name":"Clip & Curl",
    "wof:placetype":"venue"
},
  "geometry": {"coordinates":[-114.01567840600001,50.9907913208],"type":"Point"}
}