{
  "type": "Feature",
  "properties": {
    "addr:full":"West Shore Rd Owen Sound ON N4K 5P3",
    "addr:postcode":"n4k 5p3",
    "addr:street":"West Shore Rd",
    "iso:country":"CA",
    "sg:address":"West Shore Rd",
    "sg:city":"Owen Sound",
    "sg:classifiers":[
        {
            "category":"Sports & Exercise",
            "subcategory":"Golf",
            "type":"Entertainment"
        }
    ],
    "sg:phone":"+1 519 376 2784",
    "sg:postcode":"N4K 5P3",
    "sg:province":"ON",
    "sg:tags":[
        "course"
    ],
    "wof:name":"Owen Sound Golf & Country Club",
    "wof:placetype":"venue"
},
  "geometry": {"coordinates":[-80.942604,44.564877],"type":"Point"}
}