{
  "type": "Feature",
  "properties": {
    "addr:full":"General Delivery Hillgrade NL A0G 2S0",
    "addr:postcode":"a0g 2s0",
    "iso:country":"CA",
    "sg:address":"General Delivery",
    "sg:city":"Hillgrade",
    "sg:classifiers":[
        {
            "category":"Manufacturing",
            "subcategory":"Food",
            "type":"Manufacturing & Wholesale Goods"
        }
    ],
    "sg:phone":"+1 709 628 7818",
    "sg:postcode":"A0G 2S0",
    "sg:province":"NL",
    "sg:tags":[
        "packer",
        "fish"
    ],
    "wof:name":"Summerville Fisheries",
    "wof:placetype":"venue"
},
  "geometry": {"coordinates":[-54.688522,49.573715],"type":"Point"}
}