{
  "type": "Feature",
  "properties": {
    "addr:full":"751 Sq Victoria Montreal QC H2Y 2J3",
    "addr:housenumber":"751",
    "addr:postcode":"h2y 2j3",
    "addr:street":"Sq Victoria",
    "iso:country":"CA",
    "sg:address":"751 Sq Victoria",
    "sg:city":"Montreal",
    "sg:classifiers":[
        {
            "category":"Banks & Credit Unions",
            "subcategory":"Investment Brokerage",
            "type":"Services"
        }
    ],
    "sg:phone":"+1 514 286 7444",
    "sg:postcode":"H2Y 2J3",
    "sg:province":"QC",
    "sg:tags":[
        "company",
        "broadcasting",
        "radio"
    ],
    "wof:name":"Power Technology Investments",
    "wof:placetype":"venue"
},
  "geometry": {"coordinates":[-73.560585,45.501518],"type":"Point"}
}