{
  "type": "Feature",
  "properties": {
    "addr:full":"243 Perth St Brockville ON K6V 5E7",
    "addr:housenumber":"243",
    "addr:postcode":"k6v 5e7",
    "addr:street":"Perth St",
    "iso:country":"CA",
    "sg:address":"243 Perth St",
    "sg:city":"Brockville",
    "sg:classifiers":[
        {
            "category":"Government",
            "subcategory":"Office",
            "type":"Public Place"
        }
    ],
    "sg:phone":"+1 613 342 9522",
    "sg:postcode":"K6V 5E7",
    "sg:province":"ON",
    "wof:name":"Runciman, Robert",
    "wof:placetype":"venue"
},
  "geometry": {"coordinates":[-75.695724,44.5952],"type":"Point"}
}