{
  "type": "Feature",
  "properties": {
    "iso:country":"CA",
    "sg:city":"Montreal",
    "sg:classifiers":[
        {
            "category":"Health Services",
            "subcategory":"Doctor",
            "type":"Services"
        }
    ],
    "sg:phone":"+1 514 738 5000",
    "sg:postcode":"H3V 1J1",
    "sg:province":"QC",
    "sg:tags":[
        "dentist"
    ],
    "wof:name":"St Germain, Philippe DDS",
    "wof:placetype":"venue"
},
  "geometry": {"coordinates":[-73.616249,45.495903],"type":"Point"}
}