{
  "type": "Feature",
  "properties": {
    "iso:country":"CA",
    "sg:address":"5515 Duffus St",
    "sg:city":"Halifax",
    "sg:classifiers":[
        {
            "category":"Shopping",
            "subcategory":"Pharmacy",
            "type":"Retail Goods"
        }
    ],
    "sg:phone":"+1 902 454 7471",
    "sg:postcode":"B3K 2M5",
    "sg:province":"NS",
    "wof:name":"Lawton's Drugs",
    "wof:placetype":"venue"
},
  "geometry": {"coordinates":[-63.6065177917,44.6673355103],"type":"Point"}
}