{
  "type": "Feature",
  "properties": {
    "addr:full":"3201 Kingsway Vancouver BC V5R 5K3",
    "addr:housenumber":"3201",
    "addr:postcode":"v5r 5k3",
    "addr:street":"Kingsway",
    "iso:country":"CA",
    "sg:address":"3201 Kingsway",
    "sg:city":"Vancouver",
    "sg:classifiers":[
        {
            "category":"Wholesale",
            "subcategory":"Machinery & Supplies",
            "type":"Manufacturing & Wholesale Goods"
        }
    ],
    "sg:phone":"+1 604 438 6303",
    "sg:postcode":"V5R 5K3",
    "sg:province":"BC",
    "sg:tags":[
        "equipment",
        "safety",
        "clothing"
    ],
    "wof:name":"Carleton Rescue Equipment",
    "wof:placetype":"venue"
},
  "geometry": {"coordinates":[-123.037811279,49.2351074219],"type":"Point"}
}