{
  "type": "Feature",
  "properties": {
    "addr:full":"Dollard-Des-Ormeaux QC H9B 2Y1",
    "addr:postcode":"h9b 2y1",
    "iso:country":"CA",
    "sg:city":"Dollard-Des-Ormeaux",
    "sg:classifiers":[
        {
            "category":"Health Services",
            "subcategory":"Doctor",
            "type":"Services"
        }
    ],
    "sg:phone":"+1 514 683 2010",
    "sg:postcode":"H9B 2Y1",
    "sg:province":"QC",
    "sg:tags":[
        "dentist"
    ],
    "wof:name":"Dr Mike Tenembaum",
    "wof:placetype":"venue"
},
  "geometry": {"coordinates":[-73.799774,45.484539],"type":"Point"}
}