{
  "type": "Feature",
  "properties": {
    "addr:full":"833 9 St SW High River AB T1V 1C3",
    "addr:housenumber":"833 9",
    "addr:postcode":"t1v 1c3",
    "addr:street":"St Sw",
    "iso:country":"CA",
    "sg:address":"833 9 St SW",
    "sg:city":"High River",
    "sg:classifiers":[
        {
            "category":"Social Services",
            "subcategory":"Adult Care",
            "type":"Services"
        }
    ],
    "sg:phone":"+1 403 652 8600",
    "sg:postcode":"T1V 1C3",
    "sg:province":"AB",
    "sg:tags":[
        "senior",
        "apartment",
        "housing",
        "citizen"
    ],
    "wof:name":"Foothills Foundation",
    "wof:placetype":"venue"
},
  "geometry": {"coordinates":[-113.885223389,50.5760803223],"type":"Point"}
}