{
  "type": "Feature",
  "properties": {
    "iso:country":"CA",
    "sg:address":"15 Balsam St S",
    "sg:city":"Timmins",
    "sg:classifiers":[
        {
            "category":"Professional",
            "subcategory":"Lawyer & Legal Services",
            "type":"Services"
        }
    ],
    "sg:phone":"+1 705 264 2385",
    "sg:postcode":"P4N 2C7",
    "sg:province":"ON",
    "sg:tags":[
        "attorney"
    ],
    "wof:name":"Racicot Maisonneuve Labelle",
    "wof:placetype":"venue"
},
  "geometry": {"coordinates":[-81.3310165405,48.4757347107],"type":"Point"}
}