{
  "type": "Feature",
  "properties": {
    "iso:country":"CA",
    "sg:address":"409 Bayfield St",
    "sg:city":"Barrie",
    "sg:classifiers":[
        {
            "category":"Retail",
            "subcategory":"Laundry & Dry Cleaning",
            "type":"Services"
        }
    ],
    "sg:phone":"+1 705 737 9335",
    "sg:postcode":"L4M 6E5",
    "sg:province":"ON",
    "sg:tags":[
        "cleaners"
    ],
    "wof:name":"Capital M Dry Cleaning",
    "wof:placetype":"venue"
},
  "geometry": {"coordinates":[-79.706558,44.408455],"type":"Point"}
}