{
  "type": "Feature",
  "properties": {
    "addr:full":"Chicoutimi QC G7H 6P3",
    "addr:postcode":"g7h 6p3",
    "iso:country":"CA",
    "sg:city":"Chicoutimi",
    "sg:classifiers":[
        {
            "category":"Insurance",
            "subcategory":"Insurance Agent",
            "type":"Services"
        }
    ],
    "sg:phone":"+1 418 543 7791",
    "sg:postcode":"G7H 6P3",
    "sg:province":"QC",
    "wof:name":"Wawanesa Cie Mutuelle-Assrnce",
    "wof:placetype":"venue"
},
  "geometry": {"coordinates":[-71.051605,48.405853],"type":"Point"}
}