{
  "type": "Feature",
  "properties": {
    "addr:full":"61 Lansdowne Ave Sault Ste Marie ON P6B 1K5",
    "addr:housenumber":"61",
    "addr:postcode":"p6b 1k5",
    "addr:street":"Lansdowne Ave",
    "iso:country":"CA",
    "sg:address":"61 Lansdowne Ave",
    "sg:city":"Sault Ste Marie",
    "sg:classifiers":[
        {
            "category":"Travel",
            "subcategory":"Hotels & Motels",
            "type":"Entertainment"
        }
    ],
    "sg:phone":"+1 705 256 9623",
    "sg:postcode":"P6B 1K5",
    "sg:province":"ON",
    "sg:tags":[
        "breakfast",
        "accommodation",
        "bed"
    ],
    "wof:name":"Knight Home B & B",
    "wof:placetype":"venue"
},
  "geometry": {"coordinates":[-84.326736,46.518589],"type":"Point"}
}