{
  "type": "Feature",
  "properties": {
    "addr:full":"Halifax NS B3L 4P1",
    "addr:postcode":"b3l 4p1",
    "iso:country":"CA",
    "sg:city":"Halifax",
    "sg:classifiers":[
        {
            "category":"Wholesale",
            "subcategory":"Electrical",
            "type":"Manufacturing & Wholesale Goods"
        }
    ],
    "sg:phone":"+1 902 453 4498",
    "sg:postcode":"B3L 4P1",
    "sg:province":"NS",
    "sg:tags":[
        "control"
    ],
    "wof:name":"Advanced Energy Mgmt Ltd",
    "wof:placetype":"venue"
},
  "geometry": {"coordinates":[-63.61763,44.646454],"type":"Point"}
}