{
  "type": "Feature",
  "properties": {
    "addr:full":"5410 Hwy 97 Falkland BC V0E 1W0",
    "addr:housenumber":"5410",
    "addr:postcode":"v0e 1w0",
    "addr:street":"Hwy 97",
    "iso:country":"CA",
    "sg:address":"5410 Hwy 97",
    "sg:city":"Falkland",
    "sg:classifiers":[
        {
            "category":"Organizations",
            "subcategory":"Religious Organization",
            "type":"Services"
        }
    ],
    "sg:phone":"+1 250 379 2155",
    "sg:postcode":"V0E 1W0",
    "sg:province":"BC",
    "sg:tags":[
        "church"
    ],
    "wof:name":"Jehovah's Witnesses",
    "wof:placetype":"venue"
},
  "geometry": {"coordinates":[-119.55400848399999,50.5002708435],"type":"Point"}
}