{
  "type": "Feature",
  "properties": {
    "iso:country":"CA",
    "sg:address":"1575 the Queensway",
    "sg:city":"Etobicoke",
    "sg:classifiers":[
        {
            "category":"Autos & Motor Vehicles",
            "subcategory":"Automobile Sales",
            "type":"Retail Goods"
        }
    ],
    "sg:phone":"+1 416 521 7001",
    "sg:postcode":"M8Z 1T9",
    "sg:province":"ON",
    "sg:tags":[
        "truck"
    ],
    "wof:name":"Sterling Trucks of Toronto",
    "wof:placetype":"venue"
},
  "geometry": {"coordinates":[-79.540085,43.617786],"type":"Point"}
}