{
  "type": "Feature",
  "properties": {
    "addr:full":"2175 Blackwater Rd Quesnel BC V2J 7C3",
    "addr:housenumber":"2175",
    "addr:postcode":"v2j 7c3",
    "addr:street":"Blackwater Rd",
    "iso:country":"CA",
    "sg:address":"2175 Blackwater Rd",
    "sg:city":"Quesnel",
    "sg:classifiers":[
        {
            "category":"Retail",
            "subcategory":"Auto Repair",
            "type":"Services"
        }
    ],
    "sg:phone":"+1 250 992 5100",
    "sg:postcode":"V2J 7C3",
    "sg:province":"BC",
    "sg:tags":[
        "repairing",
        "automobile",
        "pump"
    ],
    "wof:name":"Rob's Pumps",
    "wof:placetype":"venue"
},
  "geometry": {"coordinates":[-122.498245239,52.9781188965],"type":"Point"}
}