{
  "type": "Feature",
  "properties": {
    "addr:full":"2179 Danforth Ave Toronto ON M4C 1K4",
    "addr:housenumber":"2179",
    "addr:postcode":"m4c 1k4",
    "addr:street":"Danforth Ave",
    "iso:country":"CA",
    "sg:address":"2179 Danforth Ave",
    "sg:city":"Toronto",
    "sg:classifiers":[
        {
            "category":"Professional",
            "subcategory":"Management & Consulting",
            "type":"Services"
        }
    ],
    "sg:phone":"+1 416 693 4778",
    "sg:postcode":"M4C 1K4",
    "sg:province":"ON",
    "sg:tags":[
        "consultant",
        "business"
    ],
    "wof:name":"First Choice Business Cnsltng",
    "wof:placetype":"venue"
},
  "geometry": {"coordinates":[-79.3100891113,43.6861495972],"type":"Point"}
}