{
  "type": "Feature",
  "properties": {
    "addr:full":"2311 Faithfull Ave Saskatoon SK S7K 1T9",
    "addr:housenumber":"2311",
    "addr:postcode":"s7k 1t9",
    "addr:street":"Faithfull Ave",
    "iso:country":"CA",
    "sg:address":"2311 Faithfull Ave",
    "sg:city":"Saskatoon",
    "sg:classifiers":[
        {
            "category":"Wholesale",
            "subcategory":"Electrical",
            "type":"Manufacturing & Wholesale Goods"
        }
    ],
    "sg:phone":"+1 306 931 0001",
    "sg:postcode":"S7K 1T9",
    "sg:province":"SK",
    "sg:tags":[
        "control",
        "security",
        "system"
    ],
    "wof:name":"Infiniti Hardware",
    "wof:placetype":"venue"
},
  "geometry": {"coordinates":[-106.665115356,52.1619758606],"type":"Point"}
}