{
  "type": "Feature",
  "properties": {
    "addr:full":"189 Main St Lucan ON N0M 2J0",
    "addr:housenumber":"189",
    "addr:postcode":"n0m 2j0",
    "addr:street":"Main St",
    "iso:country":"CA",
    "sg:address":"189 Main St",
    "sg:city":"Lucan",
    "sg:classifiers":[
        {
            "category":"Organizations",
            "subcategory":"Religious Organization",
            "type":"Services"
        }
    ],
    "sg:phone":"+1 519 227 1740",
    "sg:postcode":"N0M 2J0",
    "sg:province":"ON",
    "sg:tags":[
        "church"
    ],
    "wof:name":"Holy Trinity Anglican Church",
    "wof:placetype":"venue"
},
  "geometry": {"coordinates":[-81.405518,43.188747],"type":"Point"}
}