{
  "type": "Feature",
  "properties": {
    "iso:country":"CA",
    "sg:address":"5500 Dixie Rd",
    "sg:city":"Mississauga",
    "sg:classifiers":[
        {
            "category":"Autos & Motor Vehicles",
            "subcategory":"Automobile Sales",
            "type":"Retail Goods"
        }
    ],
    "sg:phone":"+1 905 629 5337",
    "sg:postcode":"L4W 4N3",
    "sg:province":"ON",
    "sg:tags":[
        "car",
        "dealer"
    ],
    "wof:name":"Team Chrysler Jeep Dodge Inc",
    "wof:placetype":"venue"
},
  "geometry": {"coordinates":[-79.6335525513,43.6448059082],"type":"Point"}
}