{
  "type": "Feature",
  "properties": {
    "iso:country":"CA",
    "sg:city":"Trois-Rivieres-Ouest",
    "sg:classifiers":[
        {
            "category":"Health Services",
            "subcategory":"Doctor",
            "type":"Services"
        }
    ],
    "sg:phone":"+1 819 376 1144",
    "sg:postcode":"G8Z 4A8",
    "sg:province":"QC",
    "sg:tags":[
        "physician",
        "surgeon"
    ],
    "wof:name":"Gagnon, Jean MD",
    "wof:placetype":"venue"
},
  "geometry": {"coordinates":[-72.58989,46.335194],"type":"Point"}
}