{
  "type": "Feature",
  "properties": {
    "addr:full":"Vancouver BC V6M 2A3",
    "addr:postcode":"v6m 2a3",
    "iso:country":"CA",
    "sg:city":"Vancouver",
    "sg:classifiers":[
        {
            "category":"Professional",
            "subcategory":"Lawyer & Legal Services",
            "type":"Services"
        }
    ],
    "sg:phone":"+1 604 269 2544",
    "sg:postcode":"V6M 2A3",
    "sg:province":"BC",
    "sg:tags":[
        "attorney"
    ],
    "wof:name":"Goossen, Erv",
    "wof:placetype":"venue"
},
  "geometry": {"coordinates":[-123.160644531,49.2347755432],"type":"Point"}
}