{
  "type": "Feature",
  "properties": {
    "addr:full":"22 Birch St N Timmins ON P4N 6C7",
    "addr:housenumber":"22",
    "addr:postcode":"p4n 6c7",
    "addr:street":"Birch St N",
    "iso:country":"CA",
    "sg:address":"22 Birch St N",
    "sg:city":"Timmins",
    "sg:classifiers":[
        {
            "category":"Banks & Credit Unions",
            "subcategory":"Bank",
            "type":"Services"
        }
    ],
    "sg:phone":"+1 705 360 1116",
    "sg:postcode":"P4N 6C7",
    "sg:province":"ON",
    "sg:tags":[
        "financing"
    ],
    "wof:name":"Global Outreaches",
    "wof:placetype":"venue"
},
  "geometry": {"coordinates":[-81.33186340330001,48.476474762],"type":"Point"}
}