{
  "type": "Feature",
  "properties": {
    "addr:full":"141 Torbay Rd St. John's NL A1A 2H1",
    "addr:housenumber":"141",
    "addr:postcode":"a1a 2h1",
    "addr:street":"Torbay Rd",
    "iso:country":"CA",
    "sg:address":"141 Torbay Rd",
    "sg:city":"St. John's",
    "sg:classifiers":[
        {
            "category":"Shopping",
            "subcategory":"Pharmacy",
            "type":"Retail Goods"
        }
    ],
    "sg:phone":"+1 709 722 6270",
    "sg:postcode":"A1A 2H1",
    "sg:province":"NL",
    "wof:name":"Shoppers Drug Mart",
    "wof:placetype":"venue"
},
  "geometry": {"coordinates":[-52.7098617554,47.58984375],"type":"Point"}
}