{
  "type": "Feature",
  "properties": {
    "addr:full":"2320 Smith St Regina SK S4P 2P6",
    "addr:housenumber":"2320",
    "addr:postcode":"s4p 2p6",
    "addr:street":"Smith St",
    "iso:country":"CA",
    "sg:address":"2320 Smith St",
    "sg:city":"Regina",
    "sg:classifiers":[
        {
            "category":"Insurance",
            "subcategory":"Insurance Agent",
            "type":"Services"
        }
    ],
    "sg:phone":"+1 306 585 0030",
    "sg:postcode":"S4P 2P6",
    "sg:province":"SK",
    "wof:name":"Milleker Financial Inc",
    "wof:placetype":"venue"
},
  "geometry": {"coordinates":[-104.615341187,50.4420204163],"type":"Point"}
}