{
  "type": "Feature",
  "properties": {
    "iso:country":"CA",
    "sg:city":"Elk Lake",
    "sg:classifiers":[
        {
            "category":"Travel",
            "subcategory":"Hotels & Motels",
            "type":"Entertainment"
        }
    ],
    "sg:phone":"+1 705 624 2419",
    "sg:postcode":"P0J 1G0",
    "sg:province":"ON",
    "sg:tags":[
        "tourist",
        "accommodation"
    ],
    "wof:name":"Long Point Lodge",
    "wof:placetype":"venue"
},
  "geometry": {"coordinates":[-80.33020019529999,47.7312278748],"type":"Point"}
}