{
  "type": "Feature",
  "properties": {
    "addr:full":"Scarborough ON M1V 5J1",
    "addr:postcode":"m1v 5j1",
    "iso:country":"CA",
    "sg:city":"Scarborough",
    "sg:classifiers":[
        {
            "category":"Manufacturing",
            "subcategory":"Metals",
            "type":"Manufacturing & Wholesale Goods"
        }
    ],
    "sg:phone":"+1 416 609 9670",
    "sg:postcode":"M1V 5J1",
    "sg:province":"ON",
    "sg:tags":[
        "plumbing",
        "fixture",
        "supply"
    ],
    "wof:name":"E T Industries Inc",
    "wof:placetype":"venue"
},
  "geometry": {"coordinates":[-79.2595443726,43.8186988831],"type":"Point"}
}