{
  "type": "Feature",
  "properties": {
    "addr:full":"3160 Peter St Windsor ON N9C 1H3",
    "addr:housenumber":"3160",
    "addr:postcode":"n9c 1h3",
    "addr:street":"Peter St",
    "iso:country":"CA",
    "sg:address":"3160 Peter St",
    "sg:city":"Windsor",
    "sg:classifiers":[
        {
            "category":"Real Estate",
            "subcategory":"Real Estate Operator",
            "type":"Services"
        }
    ],
    "sg:phone":"+1 519 258 6150",
    "sg:postcode":"N9C 1H3",
    "sg:province":"ON",
    "sg:tags":[
        "apartment"
    ],
    "wof:name":"Sandiland Tower",
    "wof:placetype":"venue"
},
  "geometry": {"coordinates":[-83.0736236572,42.302444458],"type":"Point"}
}