{
  "type": "Feature",
  "properties": {
    "addr:full":"961 Boul Saint-Joseph Hull QC J8Z 1W8",
    "addr:housenumber":"961",
    "addr:postcode":"j8z 1w8",
    "addr:street":"Boul Saint-Joseph",
    "iso:country":"CA",
    "sg:address":"961 Boul Saint-Joseph",
    "sg:city":"Hull",
    "sg:classifiers":[
        {
            "category":"Autos & Motor Vehicles",
            "subcategory":"Automobile Sales",
            "type":"Retail Goods"
        }
    ],
    "sg:phone":"+1 819 776 6700",
    "sg:postcode":"J8Z 1W8",
    "sg:province":"QC",
    "sg:tags":[
        "car",
        "dealer"
    ],
    "wof:name":"Argus Mazda",
    "wof:placetype":"venue"
},
  "geometry": {"coordinates":[-75.73814400000001,45.468063],"type":"Point"}
}