{
  "type": "Feature",
  "properties": {
    "addr:full":"81 Duke St Dryden ON P8N 1G2",
    "addr:housenumber":"81",
    "addr:postcode":"p8n 1g2",
    "addr:street":"Duke St",
    "iso:country":"CA",
    "sg:address":"81 Duke St",
    "sg:city":"Dryden",
    "sg:classifiers":[
        {
            "category":"Government",
            "subcategory":"Office",
            "type":"Public Place"
        }
    ],
    "sg:phone":"+1 807 223 5505",
    "sg:postcode":"P8N 1G2",
    "sg:province":"ON",
    "wof:name":"Nault, Robert",
    "wof:placetype":"venue"
},
  "geometry": {"coordinates":[-92.836037,49.782257],"type":"Point"}
}