{
  "type": "Feature",
  "properties": {
    "addr:full":"183 Rue Saint-Eustache Saint-Eustache QC J7R 2L5",
    "addr:housenumber":"183",
    "addr:postcode":"j7r 2l5",
    "addr:street":"Rue Saint-Eustache",
    "iso:country":"CA",
    "sg:address":"183 Rue Saint-Eustache",
    "sg:city":"Saint-Eustache",
    "sg:classifiers":[
        {
            "category":"Health Services",
            "subcategory":"Clinic",
            "type":"Services"
        }
    ],
    "sg:phone":"+1 450 472 8815",
    "sg:postcode":"J7R 2L5",
    "sg:province":"QC",
    "sg:tags":[
        "hearing",
        "equipment",
        "supply",
        "impaired"
    ],
    "wof:name":"Audioprothesiste Guy Martin",
    "wof:placetype":"venue"
},
  "geometry": {"coordinates":[-73.8940048218,45.5585479736],"type":"Point"}
}