{
  "type": "Feature",
  "properties": {
    "iso:country":"CA",
    "sg:address":"904 Talbot St",
    "sg:city":"St Thomas",
    "sg:classifiers":[
        {
            "category":"Retail",
            "subcategory":"Auto Repair",
            "type":"Services"
        }
    ],
    "sg:phone":"+1 519 631 7050",
    "sg:postcode":"N5P 1E7",
    "sg:province":"ON",
    "sg:tags":[
        "repairing",
        "automobile",
        "muffler",
        "system",
        "exhaust"
    ],
    "wof:name":"Mufflerman",
    "wof:placetype":"venue"
},
  "geometry": {"coordinates":[-81.1823959351,42.7787017822],"type":"Point"}
}