{
  "type": "Feature",
  "properties": {
    "addr:full":"1891 Cornwall Ave Vancouver BC V6J 1C6",
    "addr:housenumber":"1891",
    "addr:postcode":"v6j 1c6",
    "addr:street":"Cornwall Ave",
    "iso:country":"CA",
    "sg:address":"1891 Cornwall Ave",
    "sg:city":"Vancouver",
    "sg:classifiers":[
        {
            "category":"Health Services",
            "subcategory":"Doctor",
            "type":"Services"
        }
    ],
    "sg:phone":"+1 604 737 2101",
    "sg:postcode":"V6J 1C6",
    "sg:province":"BC",
    "sg:tags":[
        "dentist"
    ],
    "wof:name":"Kits Point Dental Group",
    "wof:placetype":"venue"
},
  "geometry": {"coordinates":[-123.147575,49.272564],"type":"Point"}
}