{
  "type": "Feature",
  "properties": {
    "addr:full":"475 Boul DE L'Avenir Laval QC H7N 5H9",
    "addr:housenumber":"475",
    "addr:postcode":"h7n 5h9",
    "addr:street":"Boul De L'Avenir",
    "iso:country":"CA",
    "sg:address":"475 Boul DE L'Avenir",
    "sg:city":"Laval",
    "sg:classifiers":[
        {
            "category":"Organizations",
            "subcategory":"Professional Association",
            "type":"Services"
        }
    ],
    "sg:phone":"+1 450 668 1344",
    "sg:postcode":"H7N 5H9",
    "sg:province":"QC",
    "wof:name":"Syndicat Des Enseignants",
    "wof:placetype":"venue"
},
  "geometry": {"coordinates":[-73.72286224370001,45.5618209839],"type":"Point"}
}