{
  "type": "Feature",
  "properties": {
    "addr:full":"396 Rue Brodeur Saint-Eustache QC J7R 4Z8",
    "addr:housenumber":"396",
    "addr:postcode":"j7r 4z8",
    "addr:street":"Rue Brodeur",
    "iso:country":"CA",
    "sg:address":"396 Rue Brodeur",
    "sg:city":"Saint-Eustache",
    "sg:classifiers":[
        {
            "category":"Building & Trades",
            "subcategory":"Construction",
            "type":"Services"
        }
    ],
    "sg:phone":"+1 450 473 7732",
    "sg:postcode":"J7R 4Z8",
    "sg:province":"QC",
    "sg:tags":[
        "general",
        "contractor"
    ],
    "wof:name":"Habitations Jp Labelle Inc",
    "wof:placetype":"venue"
},
  "geometry": {"coordinates":[-73.908226,45.561146],"type":"Point"}
}