{
  "type": "Feature",
  "properties": {
    "iso:country":"CA",
    "sg:address":"1010 Dawson Rd",
    "sg:city":"Thunder Bay",
    "sg:classifiers":[
        {
            "category":"Bars & Pubs",
            "type":"Food & Drink"
        }
    ],
    "sg:phone":"+1 807 767 8271",
    "sg:postcode":"P7B 5J4",
    "sg:province":"ON",
    "sg:tags":[
        "lounge",
        "cocktail"
    ],
    "wof:name":"Donny's Den & Sports Lounge",
    "wof:placetype":"venue"
},
  "geometry": {"coordinates":[-89.252075,48.451019],"type":"Point"}
}