{
  "type": "Feature",
  "properties": {
    "addr:full":"32085 Holiday Ave Mission BC V2V 2M9",
    "addr:housenumber":"32085",
    "addr:postcode":"v2v 2m9",
    "addr:street":"Holiday Ave",
    "iso:country":"CA",
    "sg:address":"32085 Holiday Ave",
    "sg:city":"Mission",
    "sg:classifiers":[
        {
            "category":"Building & Trades",
            "subcategory":"Plumbing",
            "type":"Services"
        }
    ],
    "sg:phone":"+1 604 826 4210",
    "sg:postcode":"V2V 2M9",
    "sg:province":"BC",
    "sg:tags":[
        "contractor"
    ],
    "wof:name":"Dan Plumbing",
    "wof:placetype":"venue"
},
  "geometry": {"coordinates":[-122.336067,49.144859],"type":"Point"}
}