{
  "type": "Feature",
  "properties": {
    "addr:full":"7700 Av DE Gaspe Montreal QC H2R 2A4",
    "addr:housenumber":"7700",
    "addr:postcode":"h2r 2a4",
    "addr:street":"Av De Gaspe",
    "iso:country":"CA",
    "sg:address":"7700 Av DE Gaspe",
    "sg:city":"Montreal",
    "sg:classifiers":[
        {
            "category":"Food & Beverages",
            "subcategory":"Groceries & Convenience Stores",
            "type":"Retail Goods"
        }
    ],
    "sg:phone":"+1 514 948 4235",
    "sg:postcode":"H2R 2A4",
    "sg:province":"QC",
    "wof:name":"Alimentation Yireh",
    "wof:placetype":"venue"
},
  "geometry": {"coordinates":[-73.62445099999999,45.538895],"type":"Point"}
}