{
  "type": "Feature",
  "properties": {
    "iso:country":"CA",
    "sg:address":"7700 Av DE Gaspe",
    "sg:city":"Montreal",
    "sg:classifiers":[
        {
            "category":"Food & Beverages",
            "subcategory":"Groceries & Convenience Stores",
            "type":"Retail Goods"
        }
    ],
    "sg:phone":"+1 514 948 4235",
    "sg:postcode":"H2R 2A4",
    "sg:province":"QC",
    "wof:name":"Alimentation Yireh",
    "wof:placetype":"venue"
},
  "geometry": {"coordinates":[-73.624451,45.538895],"type":"Point"}
}