{
  "type": "Feature",
  "properties": {
    "addr:full":"Schomberg ON L0G 1T0",
    "addr:postcode":"l0g 1t0",
    "iso:country":"CA",
    "sg:city":"Schomberg",
    "sg:classifiers":[
        {
            "category":"Food & Beverages",
            "subcategory":"Groceries & Convenience Stores",
            "type":"Retail Goods"
        }
    ],
    "sg:phone":"+1 905 939 7372",
    "sg:postcode":"L0G 1T0",
    "sg:province":"ON",
    "sg:tags":[
        "grocer"
    ],
    "wof:name":"Schomberg Iga",
    "wof:placetype":"venue"
},
  "geometry": {"coordinates":[-79.68695831300001,44.0048103333],"type":"Point"}
}