{
  "type": "Feature",
  "properties": {
    "addr:full":"875 Big Bay Point Rd Barrie ON L4M 4S6",
    "addr:housenumber":"875",
    "addr:postcode":"l4m 4s6",
    "addr:street":"Big Bay Point Rd",
    "iso:country":"CA",
    "sg:address":"875 Big Bay Point Rd",
    "sg:city":"Barrie",
    "sg:classifiers":[
        {
            "category":"Building & Trades",
            "subcategory":"Landscaping Services",
            "type":"Services"
        }
    ],
    "sg:phone":"+1 705 722 4800",
    "sg:postcode":"L4M 4S6",
    "sg:province":"ON",
    "sg:tags":[
        "tree"
    ],
    "wof:name":"Lakeside Tree Experts",
    "wof:placetype":"venue"
},
  "geometry": {"coordinates":[-79.61273956300001,44.3647232056],"type":"Point"}
}