{
  "type": "Feature",
  "properties": {
    "addr:full":"475 Sackville Dr Lower Sackville NS B4C 2S1",
    "addr:housenumber":"475",
    "addr:postcode":"b4c 2s1",
    "addr:street":"Sackville Dr",
    "iso:country":"CA",
    "sg:address":"475 Sackville Dr",
    "sg:city":"Lower Sackville",
    "sg:classifiers":[
        {
            "category":"Building & Trades",
            "subcategory":"Construction",
            "type":"Services"
        }
    ],
    "sg:phone":"+1 902 865 4373",
    "sg:postcode":"B4C 2S1",
    "sg:province":"NS",
    "sg:tags":[
        "designer",
        "dealer",
        "pool",
        "swimming"
    ],
    "wof:name":"R F Levy Pools Ltd",
    "wof:placetype":"venue"
},
  "geometry": {"coordinates":[-63.680096,44.765591],"type":"Point"}
}