{
  "type": "Feature",
  "properties": {
    "addr:full":"56 Sprucewood Dr New Maryland NB E3C 1C7",
    "addr:housenumber":"56",
    "addr:postcode":"e3c 1c7",
    "addr:street":"Sprucewood Dr",
    "iso:country":"CA",
    "sg:address":"56 Sprucewood Dr",
    "sg:city":"New Maryland",
    "sg:classifiers":[
        {
            "category":"Insurance",
            "subcategory":"Insurance Agent",
            "type":"Services"
        }
    ],
    "sg:phone":"+1 506 457 6046",
    "sg:postcode":"E3C 1C7",
    "sg:province":"NB",
    "wof:name":"Brent Richardson Insurance",
    "wof:placetype":"venue"
},
  "geometry": {"coordinates":[-66.68919372560001,45.8972015381],"type":"Point"}
}