{
  "type": "Feature",
  "properties": {
    "iso:country":"CA",
    "sg:address":"707 Mount Pleasant Rd",
    "sg:city":"Toronto",
    "sg:classifiers":[
        {
            "category":"Shopping",
            "type":"Retail Goods"
        }
    ],
    "sg:phone":"+1 416 920 3779",
    "sg:postcode":"M4S 2N4",
    "sg:province":"ON",
    "sg:tags":[
        "art",
        "gallery",
        "dealer"
    ],
    "wof:name":"Willow Gallery",
    "wof:placetype":"venue"
},
  "geometry": {"coordinates":[-79.389289856,43.7066802979],"type":"Point"}
}