{
  "type": "Feature",
  "properties": {
    "addr:full":"Mississauga ON L5B 4A2",
    "addr:postcode":"l5b 4a2",
    "iso:country":"CA",
    "sg:city":"Mississauga",
    "sg:classifiers":[
        {
            "category":"Health Services",
            "subcategory":"Doctor",
            "type":"Services"
        }
    ],
    "sg:phone":"+1 905 273 9793",
    "sg:postcode":"L5B 4A2",
    "sg:province":"ON",
    "sg:tags":[
        "physician",
        "surgeon"
    ],
    "wof:name":"Choi, David MD",
    "wof:placetype":"venue"
},
  "geometry": {"coordinates":[-79.615509,43.577759],"type":"Point"}
}