{
  "type": "Feature",
  "properties": {
    "addr:full":"40 Rue Du Moulin Warwick QC J0A 1M0",
    "addr:housenumber":"40",
    "addr:postcode":"j0a 1m0",
    "addr:street":"Rue Du Moulin",
    "iso:country":"CA",
    "sg:address":"40 Rue Du Moulin",
    "sg:city":"Warwick",
    "sg:classifiers":[
        {
            "category":"Manufacturing",
            "subcategory":"Food",
            "type":"Manufacturing & Wholesale Goods"
        }
    ],
    "sg:phone":"+1 819 358 3600",
    "sg:postcode":"J0A 1M0",
    "sg:province":"QC",
    "sg:tags":[
        "chips"
    ],
    "wof:name":"Yum Yum Croustilles Enr",
    "wof:placetype":"venue"
},
  "geometry": {"coordinates":[-71.98123931879999,45.9353294373],"type":"Point"}
}