{
  "type": "Feature",
  "properties": {
    "addr:full":"2950 Marleau Ave Cornwall ON K6H 6B5",
    "addr:housenumber":"2950",
    "addr:postcode":"k6h 6b5",
    "addr:street":"Marleau Ave",
    "iso:country":"CA",
    "sg:address":"2950 Marleau Ave",
    "sg:city":"Cornwall",
    "sg:classifiers":[
        {
            "category":"Manufacturing",
            "subcategory":"Rubber & Plastics",
            "type":"Manufacturing & Wholesale Goods"
        }
    ],
    "sg:phone":"+1 613 938 8099",
    "sg:postcode":"K6H 6B5",
    "sg:province":"ON",
    "wof:name":"Spartech Plastics",
    "wof:placetype":"venue"
},
  "geometry": {"coordinates":[-74.691399,45.044151],"type":"Point"}
}