{
  "type": "Feature",
  "properties": {
    "addr:full":"323 Main St Lemberg SK S0A 2B0",
    "addr:housenumber":"323",
    "addr:postcode":"s0a 2b0",
    "addr:street":"Main St",
    "iso:country":"CA",
    "sg:address":"323 Main St",
    "sg:city":"Lemberg",
    "sg:classifiers":[
        {
            "category":"Food & Beverages",
            "subcategory":"Groceries & Convenience Stores",
            "type":"Retail Goods"
        }
    ],
    "sg:phone":"+1 306 335 2461",
    "sg:postcode":"S0A 2B0",
    "sg:province":"SK",
    "sg:tags":[
        "grocer"
    ],
    "wof:name":"Prairie CO-Operatives Ltd",
    "wof:placetype":"venue"
},
  "geometry": {"coordinates":[-103.20283499999999,50.727901],"type":"Point"}
}