{
  "type": "Feature",
  "properties": {
    "addr:full":"3 Northrup Cres St Catharines ON L2M 7M3",
    "addr:housenumber":"3",
    "addr:postcode":"l2m 7m3",
    "addr:street":"Northrup Cres",
    "iso:country":"CA",
    "sg:address":"3 Northrup Cres",
    "sg:city":"St Catharines",
    "sg:classifiers":[
        {
            "category":"Professional",
            "subcategory":"Business Services",
            "type":"Services"
        }
    ],
    "sg:phone":"+1 905 646 7371",
    "sg:postcode":"L2M 7M3",
    "sg:province":"ON",
    "sg:tags":[
        "engraver"
    ],
    "wof:name":"Ident Systems",
    "wof:placetype":"venue"
},
  "geometry": {"coordinates":[-79.2033233643,43.2237892151],"type":"Point"}
}