{
  "type": "Feature",
  "properties": {
    "addr:full":"7 Creekstone Pl Port Moody BC V3H 4L7",
    "addr:housenumber":"7",
    "addr:postcode":"v3h 4l7",
    "addr:street":"Creekstone Pl",
    "iso:country":"CA",
    "sg:address":"7 Creekstone Pl",
    "sg:city":"Port Moody",
    "sg:classifiers":[
        {
            "category":"Building & Trades",
            "subcategory":"Construction",
            "type":"Services"
        }
    ],
    "sg:phone":"+1 604 461 6590",
    "sg:postcode":"V3H 4L7",
    "sg:province":"BC",
    "sg:tags":[
        "contractor"
    ],
    "wof:name":"Richardson Bros Developments",
    "wof:placetype":"venue"
},
  "geometry": {"coordinates":[-122.82872,49.291203],"type":"Point"}
}