{
  "type": "Feature",
  "properties": {
    "addr:full":"874 3E Rue Chibougamau QC G8P 1P9",
    "addr:housenumber":"874",
    "addr:postcode":"g8p 1p9",
    "addr:street":"3E Rue",
    "iso:country":"CA",
    "sg:address":"874 3E Rue",
    "sg:city":"Chibougamau",
    "sg:classifiers":[
        {
            "category":"Wholesale",
            "subcategory":"Machinery & Supplies",
            "type":"Manufacturing & Wholesale Goods"
        }
    ],
    "sg:phone":"+1 418 748 7674",
    "sg:postcode":"G8P 1P9",
    "sg:province":"QC",
    "sg:tags":[
        "equipment",
        "industrial"
    ],
    "wof:name":"Mas Chibougamau Inc",
    "wof:placetype":"venue"
},
  "geometry": {"coordinates":[-74.3813781738,49.9134292603],"type":"Point"}
}