{
  "type": "Feature",
  "properties": {
    "addr:full":"1401 Ch DE Chambly Longueuil QC J4J 3X6",
    "addr:housenumber":"1401",
    "addr:postcode":"j4j 3x6",
    "addr:street":"Ch De Chambly",
    "iso:country":"CA",
    "sg:address":"1401 Ch DE Chambly",
    "sg:city":"Longueuil",
    "sg:classifiers":[
        {
            "category":"Retail",
            "subcategory":"Animal Services",
            "type":"Services"
        }
    ],
    "sg:phone":"+1 450 679 9779",
    "sg:postcode":"J4J 3X6",
    "sg:province":"QC",
    "sg:tags":[
        "pet",
        "grooming",
        "washing"
    ],
    "wof:name":"Salon DE Toilettage Spooky",
    "wof:placetype":"venue"
},
  "geometry": {"coordinates":[-73.485039,45.530922],"type":"Point"}
}