{
  "type": "Feature",
  "properties": {
    "addr:full":"301 Rue Principale O Magog QC J1X 2B1",
    "addr:housenumber":"301",
    "addr:postcode":"j1x 2b1",
    "addr:street":"Rue Principale O",
    "iso:country":"CA",
    "sg:address":"301 Rue Principale O",
    "sg:city":"Magog",
    "sg:classifiers":[
        {
            "category":"Restaurant",
            "type":"Food & Drink"
        }
    ],
    "sg:phone":"+1 819 868 3857",
    "sg:postcode":"J1X 2B1",
    "sg:province":"QC",
    "wof:name":"Brasserie Jessie Enr",
    "wof:placetype":"venue"
},
  "geometry": {"coordinates":[-72.138718,45.262661],"type":"Point"}
}