{
  "type": "Feature",
  "properties": {
    "addr:full":"5000 Rue Saint-Roch N Drummondville QC J2E 1A1",
    "addr:housenumber":"5000",
    "addr:postcode":"j2e 1a1",
    "addr:street":"Rue Saint-Roch N",
    "iso:country":"CA",
    "sg:address":"5000 Rue Saint-Roch N",
    "sg:city":"Drummondville",
    "sg:classifiers":[
        {
            "category":"Autos & Motor Vehicles",
            "subcategory":"Fuel & Gas Station",
            "type":"Retail Goods"
        }
    ],
    "sg:phone":"+1 819 478 8168",
    "sg:postcode":"J2E 1A1",
    "sg:province":"QC",
    "sg:tags":[
        "oil"
    ],
    "wof:name":"Station Petro-T Route 20",
    "wof:placetype":"venue"
},
  "geometry": {"coordinates":[-72.5256729126,45.905166626],"type":"Point"}
}