{
  "type": "Feature",
  "properties": {
    "addr:full":"2045 Rue Berlier Laval QC H7L 3M9",
    "addr:housenumber":"2045",
    "addr:postcode":"h7l 3m9",
    "addr:street":"Rue Berlier",
    "iso:country":"CA",
    "sg:address":"2045 Rue Berlier",
    "sg:city":"Laval",
    "sg:classifiers":[
        {
            "category":"Manufacturing",
            "subcategory":"Printing",
            "type":"Manufacturing & Wholesale Goods"
        }
    ],
    "sg:phone":"+1 450 686 2866",
    "sg:postcode":"H7L 3M9",
    "sg:province":"QC",
    "sg:tags":[
        "equipment",
        "loose",
        "leaf"
    ],
    "wof:name":"Systeme DE Classement",
    "wof:placetype":"venue"
},
  "geometry": {"coordinates":[-73.749664,45.581032],"type":"Point"}
}