{
  "type": "Feature",
  "properties": {
    "addr:full":"Chetwynd BC V0C 1J0",
    "addr:postcode":"bc v0c 1j0",
    "iso:country":"CA",
    "sg:city":"Chetwynd",
    "sg:classifiers":[
        {
            "category":"Government",
            "subcategory":"Office",
            "type":"Public Place"
        }
    ],
    "sg:phone":"+1 250 788 1066",
    "sg:postcode":"V0C 1J0",
    "sg:province":"BC",
    "sg:tags":[
        "village"
    ],
    "wof:name":"Chetwynd Landfills",
    "wof:placetype":"venue"
},
  "geometry": {"coordinates":[-121.627746582,55.6975326538],"type":"Point"}
}