{
  "type": "Feature",
  "properties": {
    "addr:full":"875 Rue Des Calfats Levis QC G6V 9E7",
    "addr:housenumber":"875",
    "addr:postcode":"g6v 9e7",
    "addr:street":"Rue Des Calfats",
    "iso:country":"CA",
    "sg:address":"875 Rue Des Calfats",
    "sg:city":"Levis",
    "sg:classifiers":[
        {
            "category":"Building & Trades",
            "subcategory":"Construction",
            "type":"Services"
        }
    ],
    "sg:phone":"+1 418 837 4333",
    "sg:postcode":"G6V 9E7",
    "sg:province":"QC",
    "sg:tags":[
        "excavating",
        "contractor",
        "snow",
        "removal"
    ],
    "wof:name":"Terrassement Robert Letourneau",
    "wof:placetype":"venue"
},
  "geometry": {"coordinates":[-71.12400100000001,46.819782],"type":"Point"}
}