{
  "type": "Feature",
  "properties": {
    "iso:country":"CA",
    "sg:address":"242 Robie St",
    "sg:city":"Truro",
    "sg:classifiers":[
        {
            "category":"Restaurant",
            "type":"Food & Drink"
        }
    ],
    "sg:phone":"+1 902 895 2101",
    "sg:postcode":"B2N 1L1",
    "sg:province":"NS",
    "sg:tags":[
        "out"
    ],
    "wof:name":"Kfc",
    "wof:placetype":"venue"
},
  "geometry": {"coordinates":[-63.302341,45.369202],"type":"Point"}
}