{
  "type": "Feature",
  "properties": {
    "addr:full":"11621 147 St NW Edmonton AB T5M 1W3",
    "addr:housenumber":"11621",
    "addr:postcode":"t5m 1w3",
    "addr:street":"147 St Nw",
    "iso:country":"CA",
    "sg:address":"11621 147 St NW",
    "sg:city":"Edmonton",
    "sg:classifiers":[
        {
            "category":"Wholesale",
            "subcategory":"Seafood",
            "type":"Manufacturing & Wholesale Goods"
        }
    ],
    "sg:phone":"+1 780 451 0223",
    "sg:postcode":"T5M 1W3",
    "sg:province":"AB",
    "wof:name":"Wayne Wood Fresh Fish Ltd",
    "wof:placetype":"venue"
},
  "geometry": {"coordinates":[-113.573677,53.568085],"type":"Point"}
}