{
  "type": "Feature",
  "properties": {
    "iso:country":"CA",
    "sg:city":"Victoria",
    "sg:classifiers":[
        {
            "category":"Health Services",
            "subcategory":"Doctor",
            "type":"Services"
        }
    ],
    "sg:phone":"+1 250 418 8878",
    "sg:postcode":"V9A 7N6",
    "sg:province":"BC",
    "sg:tags":[
        "physician",
        "surgeon"
    ],
    "wof:name":"Hepburn, David MD",
    "wof:placetype":"venue"
},
  "geometry": {"coordinates":[-123.38154602,48.4327545166],"type":"Point"}
}