{
  "type": "Feature",
  "properties": {
    "addr:full":"162 Rue Cadillac Val-D'Or QC J9P 2J4",
    "addr:housenumber":"162",
    "addr:postcode":"j9p 2j4",
    "addr:street":"Rue Cadillac",
    "iso:country":"CA",
    "sg:address":"162 Rue Cadillac",
    "sg:city":"Val-D'Or",
    "sg:classifiers":[
        {
            "category":"Building & Trades",
            "subcategory":"Construction",
            "type":"Services"
        }
    ],
    "sg:phone":"+1 819 825 9315",
    "sg:postcode":"J9P 2J4",
    "sg:province":"QC",
    "sg:tags":[
        "excavating",
        "contractor",
        "general"
    ],
    "wof:name":"Construction Christian Bouchrd",
    "wof:placetype":"venue"
},
  "geometry": {"coordinates":[-71.0033187866,45.3835067749],"type":"Point"}
}