{
  "type": "Feature",
  "properties": {
    "addr:full":"308 Main St N Moose Jaw SK S6H 3J9",
    "addr:housenumber":"308",
    "addr:postcode":"s6h 3j9",
    "addr:street":"Main St N",
    "iso:country":"CA",
    "sg:address":"308 Main St N",
    "sg:city":"Moose Jaw",
    "sg:classifiers":[
        {
            "category":"Manufacturing",
            "subcategory":"Printing",
            "type":"Manufacturing & Wholesale Goods"
        }
    ],
    "sg:phone":"+1 306 693 7111",
    "sg:postcode":"S6H 3J9",
    "sg:province":"SK",
    "sg:tags":[
        "newspaper"
    ],
    "wof:name":"Players Newstand",
    "wof:placetype":"venue"
},
  "geometry": {"coordinates":[-105.534965515,50.3927268982],"type":"Point"}
}