{
  "type": "Feature",
  "properties": {
    "addr:full":"408053 Grey Rd 4 Maxwell ON N0C 1J0",
    "addr:housenumber":"408053",
    "addr:postcode":"n0c 1j0",
    "addr:street":"Grey Rd 4",
    "iso:country":"CA",
    "sg:address":"408053 Grey Rd 4",
    "sg:city":"Maxwell",
    "sg:classifiers":[
        {
            "category":"Social Services",
            "subcategory":"Child Care",
            "type":"Services"
        }
    ],
    "sg:phone":"+1 519 922 2333",
    "sg:postcode":"N0C 1J0",
    "sg:province":"ON",
    "wof:name":"Osprey Kid's N US Day Care Ctr",
    "wof:placetype":"venue"
},
  "geometry": {"coordinates":[-80.397003,44.309956],"type":"Point"}
}