{
  "type": "Feature",
  "properties": {
    "addr:full":"Winkler MB R6W 4B9",
    "addr:postcode":"r6w 4b9",
    "iso:country":"CA",
    "sg:city":"Winkler",
    "sg:classifiers":[
        {
            "category":"Food & Beverages",
            "subcategory":"Fruits & Vegetables",
            "type":"Retail Goods"
        }
    ],
    "sg:phone":"+1 204 325 9004",
    "sg:postcode":"R6W 4B9",
    "sg:province":"MB",
    "sg:tags":[
        "produce"
    ],
    "wof:name":"Vanden Berg Vegetables",
    "wof:placetype":"venue"
},
  "geometry": {"coordinates":[-97.93928527830001,49.1923484802],"type":"Point"}
}