{
  "type": "Feature",
  "properties": {
    "iso:country":"CA",
    "sg:city":"Vaudreuil-Dorion",
    "sg:classifiers":[
        {
            "category":"Autos & Motor Vehicles",
            "subcategory":"Automobile Sales",
            "type":"Retail Goods"
        }
    ],
    "sg:phone":"+1 450 455 5701",
    "sg:postcode":"J7V 8P2",
    "sg:province":"QC",
    "sg:tags":[
        "car",
        "dealer"
    ],
    "wof:name":"Reno Auto Parts Inc",
    "wof:placetype":"venue"
},
  "geometry": {"coordinates":[-74.0383682251,45.3704605103],"type":"Point"}
}