{
  "type": "Feature",
  "properties": {
    "iso:country":"CA",
    "sg:address":"7065 Tranmere Dr",
    "sg:city":"Mississauga",
    "sg:classifiers":[
        {
            "category":"Wholesale",
            "subcategory":"Office Equipment",
            "type":"Manufacturing & Wholesale Goods"
        }
    ],
    "sg:phone":"+1 905 673 9333",
    "sg:postcode":"L5S 1M2",
    "sg:province":"ON",
    "sg:tags":[
        "scanning",
        "code",
        "bar"
    ],
    "wof:name":"Intermec Technologies Canada",
    "wof:placetype":"venue"
},
  "geometry": {"coordinates":[-79.666855,43.683918],"type":"Point"}
}