{
  "type": "Feature",
  "properties": {
    "iso:country":"CA",
    "sg:address":"548 Rue Marquis",
    "sg:city":"Repentigny",
    "sg:classifiers":[
        {
            "category":"Building & Trades",
            "subcategory":"Construction",
            "type":"Services"
        }
    ],
    "sg:phone":"+1 450 654 2735",
    "sg:postcode":"J6A 7J2",
    "sg:province":"QC",
    "sg:tags":[
        "excavating",
        "contractor"
    ],
    "wof:name":"Repentigny Excavation Inc",
    "wof:placetype":"venue"
},
  "geometry": {"coordinates":[-73.460052,45.749462],"type":"Point"}
}