{
  "type": "Feature",
  "properties": {
    "addr:full":"2205 Boul Wilfrid-Hamel Quebec QC G1P 2H8",
    "addr:housenumber":"2205",
    "addr:postcode":"g1p 2h8",
    "addr:street":"Boul Wilfrid-Hamel",
    "iso:country":"CA",
    "sg:address":"2205 Boul Wilfrid-Hamel",
    "sg:city":"Quebec",
    "sg:classifiers":[
        {
            "category":"Retail",
            "subcategory":"Auto Repair",
            "type":"Services"
        }
    ],
    "sg:phone":"+1 418 683 5873",
    "sg:postcode":"G1P 2H8",
    "sg:province":"QC",
    "sg:tags":[
        "repairing",
        "automobile"
    ],
    "wof:name":"Clinique DE L'Auto Mm Inc",
    "wof:placetype":"venue"
},
  "geometry": {"coordinates":[-71.29177900000001,46.806377],"type":"Point"}
}