{
  "type": "Feature",
  "properties": {
    "iso:country":"CA",
    "sg:address":"8841 Highway 99",
    "sg:city":"Whistler",
    "sg:classifiers":[
        {
            "category":"Travel",
            "subcategory":"Hotels & Motels",
            "type":"Entertainment"
        }
    ],
    "sg:phone":"+1 604 932 0688",
    "sg:postcode":"V0N 1B0",
    "sg:province":"BC",
    "sg:tags":[
        "resort"
    ],
    "wof:name":"Edgewater",
    "wof:placetype":"venue"
},
  "geometry": {"coordinates":[-122.954086304,50.1195716858],"type":"Point"}
}