{
  "type": "Feature",
  "properties": {
    "addr:full":"Vernon BC V1T 3R4",
    "addr:postcode":"v1t 3r4",
    "iso:country":"CA",
    "sg:city":"Vernon",
    "sg:classifiers":[
        {
            "category":"Social Services",
            "type":"Services"
        }
    ],
    "sg:phone":"+1 250 542 6151",
    "sg:postcode":"V1T 3R4",
    "sg:province":"BC",
    "sg:tags":[
        "info",
        "drug",
        "abuse",
        "treatment",
        "welfare",
        "organization",
        "addiction"
    ],
    "wof:name":"Vernon Treatment Ctr",
    "wof:placetype":"venue"
},
  "geometry": {"coordinates":[-119.268295288,50.2818374634],"type":"Point"}
}