{
  "type": "Feature",
  "properties": {
    "iso:country":"CA",
    "sg:city":"Winnipeg",
    "sg:classifiers":[
        {
            "category":"Restaurant",
            "type":"Food & Drink"
        }
    ],
    "sg:phone":"+1 204 474 0908",
    "sg:postcode":"R3L 1Y5",
    "sg:province":"MB",
    "wof:name":"Bangkok Thai Restaurant",
    "wof:placetype":"venue"
},
  "geometry": {"coordinates":[-97.146095,49.879086],"type":"Point"}
}