{
  "type": "Feature",
  "properties": {
    "addr:full":"2201 Logan Ave Winnipeg MB R2R 0J3",
    "addr:housenumber":"2201",
    "addr:postcode":"r2r 0j3",
    "addr:street":"Logan Ave",
    "iso:country":"CA",
    "sg:address":"2201 Logan Ave",
    "sg:city":"Winnipeg",
    "sg:classifiers":[
        {
            "category":"Manufacturing",
            "subcategory":"Lumber",
            "type":"Manufacturing & Wholesale Goods"
        }
    ],
    "sg:phone":"+1 204 697 8191",
    "sg:postcode":"R2R 0J3",
    "sg:province":"MB",
    "sg:tags":[
        "pallet",
        "skid"
    ],
    "wof:name":"Pa D'Or Mfg Inc",
    "wof:placetype":"venue"
},
  "geometry": {"coordinates":[-97.217468,49.925781],"type":"Point"}
}