{
  "type": "Feature",
  "properties": {
    "addr:full":"2900 Warden Ave Scarborough ON M1W 2S8",
    "addr:housenumber":"2900",
    "addr:postcode":"m1w 2s8",
    "addr:street":"Warden Ave",
    "iso:country":"CA",
    "sg:address":"2900 Warden Ave",
    "sg:city":"Scarborough",
    "sg:classifiers":[
        {
            "category":"Wholesale",
            "subcategory":"Non-durable Goods",
            "type":"Manufacturing & Wholesale Goods"
        }
    ],
    "sg:phone":"+1 416 498 6695",
    "sg:postcode":"M1W 2S8",
    "sg:province":"ON",
    "sg:tags":[
        "advertising"
    ],
    "wof:name":"Bullseye Design",
    "wof:placetype":"venue"
},
  "geometry": {"coordinates":[-79.31596399999999,43.796898],"type":"Point"}
}