{
  "type": "Feature",
  "properties": {
    "addr:full":"Hwy 18 W Oxbow SK S0C 2B0",
    "addr:postcode":"s0c 2b0",
    "addr:street":"Hwy 18 W Oxbow",
    "iso:country":"CA",
    "sg:address":"Hwy 18 W",
    "sg:city":"Oxbow",
    "sg:classifiers":[
        {
            "category":"Wholesale",
            "subcategory":"Machinery & Supplies",
            "type":"Manufacturing & Wholesale Goods"
        }
    ],
    "sg:phone":"+1 306 483 5115",
    "sg:postcode":"S0C 2B0",
    "sg:province":"SK",
    "sg:tags":[
        "agricultural",
        "implement"
    ],
    "wof:name":"Kosior Tractor Ltd",
    "wof:placetype":"venue"
},
  "geometry": {"coordinates":[-102.18023700000001,49.230194],"type":"Point"}
}