{
  "type": "Feature",
  "properties": {
    "addr:full":"280 Rue Denison E Granby QC J2H 2R6",
    "addr:housenumber":"280",
    "addr:postcode":"j2h 2r6",
    "addr:street":"Rue Denison E",
    "iso:country":"CA",
    "sg:address":"280 Rue Denison E",
    "sg:city":"Granby",
    "sg:classifiers":[
        {
            "category":"Health Services",
            "subcategory":"Nursing And Care Facility",
            "type":"Services"
        }
    ],
    "sg:phone":"+1 450 375 4684",
    "sg:postcode":"J2H 2R6",
    "sg:province":"QC",
    "sg:tags":[
        "home",
        "retirement",
        "community"
    ],
    "wof:name":"Residence Du Mont Enrg",
    "wof:placetype":"venue"
},
  "geometry": {"coordinates":[-72.70575714109999,45.3943138123],"type":"Point"}
}