{
  "type": "Feature",
  "properties": {
    "addr:full":"1420 Rue Legendre E Montreal QC H2M 1H5",
    "addr:housenumber":"1420",
    "addr:postcode":"h2m 1h5",
    "addr:street":"Rue Legendre E",
    "iso:country":"CA",
    "sg:address":"1420 Rue Legendre E",
    "sg:city":"Montreal",
    "sg:classifiers":[
        {
            "category":"Personal",
            "subcategory":"Beauty Salon",
            "type":"Services"
        }
    ],
    "sg:phone":"+1 514 383 5289",
    "sg:postcode":"H2M 1H5",
    "sg:province":"QC",
    "wof:name":"Salon Philo Inc",
    "wof:placetype":"venue"
},
  "geometry": {"coordinates":[-73.63793200000001,45.558594],"type":"Point"}
}