{
  "type": "Feature",
  "properties": {
    "addr:full":"32374 Cassidy Ailsa Craig ON N0M 1A0",
    "addr:housenumber":"32374",
    "addr:postcode":"n0m 1a0",
    "addr:street":"Cassidy Ailsa",
    "iso:country":"CA",
    "sg:address":"32374 Cassidy",
    "sg:city":"Ailsa Craig",
    "sg:classifiers":[
        {
            "category":"Freight",
            "type":"Transportation"
        }
    ],
    "sg:phone":"+1 519 232 1111",
    "sg:postcode":"N0M 1A0",
    "sg:province":"ON",
    "sg:tags":[
        "trucking"
    ],
    "wof:name":"Cgf Transportation Svc Inc",
    "wof:placetype":"venue"
},
  "geometry": {"coordinates":[-81.567421,43.121258],"type":"Point"}
}