{
  "type": "Feature",
  "properties": {
    "addr:full":"354 Marcotte Cres Saskatoon SK S7K 7N8",
    "addr:housenumber":"354",
    "addr:postcode":"s7k 7n8",
    "addr:street":"Marcotte Cres",
    "iso:country":"CA",
    "sg:address":"354 Marcotte Cres",
    "sg:city":"Saskatoon",
    "sg:classifiers":[
        {
            "category":"Wholesale",
            "subcategory":"Durable Goods & Equipment",
            "type":"Manufacturing & Wholesale Goods"
        }
    ],
    "sg:phone":"+1 306 668 2823",
    "sg:postcode":"S7K 7N8",
    "sg:province":"SK",
    "sg:tags":[
        "representative",
        "manufacturer"
    ],
    "wof:name":"Sherwood & Assoc",
    "wof:placetype":"venue"
},
  "geometry": {"coordinates":[-106.636192322,52.1843643188],"type":"Point"}
}