{
  "type": "Feature",
  "properties": {
    "addr:full":"3685 Rue Lemire Saint-Cyrille-DE-Wendover QC J1Z 1V3",
    "addr:housenumber":"3685",
    "addr:postcode":"j1z 1v3",
    "addr:street":"Rue Lemire",
    "iso:country":"CA",
    "sg:address":"3685 Rue Lemire",
    "sg:city":"Saint-Cyrille-DE-Wendover",
    "sg:classifiers":[
        {
            "category":"Retail",
            "subcategory":"Auto Repair",
            "type":"Services"
        }
    ],
    "sg:phone":"+1 819 397 5097",
    "sg:postcode":"J1Z 1V3",
    "sg:province":"QC",
    "sg:tags":[
        "body",
        "automobile",
        "painting"
    ],
    "wof:name":"Garage Peinture Thomas Enr",
    "wof:placetype":"venue"
},
  "geometry": {"coordinates":[-72.432365,45.927345],"type":"Point"}
}