{
  "type": "Feature",
  "properties": {
    "iso:country":"CA",
    "sg:address":"554 Boul DE Mortagne",
    "sg:city":"Boucherville",
    "sg:classifiers":[
        {
            "category":"Travel",
            "subcategory":"Travel Agent",
            "type":"Entertainment"
        }
    ],
    "sg:phone":"+1 450 655 2055",
    "sg:postcode":"J4B 5E4",
    "sg:province":"QC",
    "sg:tags":[
        "agency",
        "bureau"
    ],
    "wof:name":"Voyages Performa Inc",
    "wof:placetype":"venue"
},
  "geometry": {"coordinates":[-73.4340133667,45.5930747986],"type":"Point"}
}