{
  "type": "Feature",
  "properties": {
    "addr:full":"151 Richmond St Sydney NS B1P 2V1",
    "addr:housenumber":"151",
    "addr:postcode":"b1p 2v1",
    "addr:street":"Richmond St",
    "iso:country":"CA",
    "sg:address":"151 Richmond St",
    "sg:city":"Sydney",
    "sg:classifiers":[
        {
            "category":"Retail",
            "subcategory":"Auto Repair",
            "type":"Services"
        }
    ],
    "sg:phone":"+1 902 562 3254",
    "sg:postcode":"B1P 2V1",
    "sg:province":"NS",
    "sg:tags":[
        "truck"
    ],
    "wof:name":"H G Mac Neil Truck Parts & Svc",
    "wof:placetype":"venue"
},
  "geometry": {"coordinates":[-60.17868,46.14642],"type":"Point"}
}