{
  "type": "Feature",
  "properties": {
    "iso:country":"CA",
    "sg:city":"Westmount",
    "sg:classifiers":[
        {
            "category":"Wholesale",
            "subcategory":"Groceries",
            "type":"Manufacturing & Wholesale Goods"
        }
    ],
    "sg:phone":"+1 514 481 0247",
    "sg:postcode":"H3Z 1N1",
    "sg:province":"QC",
    "sg:tags":[
        "food",
        "broker"
    ],
    "wof:name":"G Vankam Trading CO",
    "wof:placetype":"venue"
},
  "geometry": {"coordinates":[-73.6012496948,45.4764556885],"type":"Point"}
}