{
  "type": "Feature",
  "properties": {
    "addr:full":"2935 Outlet Rd Lansdowne ON K0E 1L0",
    "addr:housenumber":"2935",
    "addr:postcode":"k0e 1l0",
    "addr:street":"Outlet Rd",
    "iso:country":"CA",
    "sg:address":"2935 Outlet Rd",
    "sg:city":"Lansdowne",
    "sg:classifiers":[
        {
            "category":"Retail",
            "subcategory":"Repair Shop",
            "type":"Services"
        }
    ],
    "sg:phone":"+1 613 659 2945",
    "sg:postcode":"K0E 1L0",
    "sg:province":"ON",
    "sg:tags":[
        "craft",
        "caning",
        "supply"
    ],
    "wof:name":"Wiltse Creek Studio",
    "wof:placetype":"venue"
},
  "geometry": {"coordinates":[-76.020737,44.42873],"type":"Point"}
}