{
  "type": "Feature",
  "properties": {
    "addr:full":"163 Rosedale Heights Dr Toronto ON M4T 1C7",
    "addr:housenumber":"163",
    "addr:postcode":"m4t 1c7",
    "addr:street":"Rosedale Heights Dr",
    "iso:country":"CA",
    "sg:address":"163 Rosedale Heights Dr",
    "sg:city":"Toronto",
    "sg:classifiers":[
        {
            "category":"Professional",
            "subcategory":"Business Services",
            "type":"Services"
        }
    ],
    "sg:phone":"+1 416 483 4189",
    "sg:postcode":"M4T 1C7",
    "sg:province":"ON",
    "wof:name":"D C Wine Merchants",
    "wof:placetype":"venue"
},
  "geometry": {"coordinates":[-79.3760223389,43.687915802],"type":"Point"}
}