{
  "type": "Feature",
  "properties": {
    "addr:full":"6497 Chukar Dr Kamloops BC V2C 4T9",
    "addr:housenumber":"6497",
    "addr:postcode":"bc v2c 4t9",
    "addr:street":"Chukar Dr",
    "iso:country":"CA",
    "sg:address":"6497 Chukar Dr",
    "sg:city":"Kamloops",
    "sg:classifiers":[
        {
            "category":"Building & Trades",
            "subcategory":"Construction",
            "type":"Services"
        }
    ],
    "sg:phone":"+1 250 573 2929",
    "sg:postcode":"V2C 4T9",
    "sg:province":"BC",
    "sg:tags":[
        "siding",
        "contractor"
    ],
    "wof:name":"Arctic Renovations",
    "wof:placetype":"venue"
},
  "geometry": {"coordinates":[-120.151412964,50.6697540283],"type":"Point"}
}