{
  "type": "Feature",
  "properties": {
    "addr:full":"3861 Campbell Rd Orillia ON L3V 1J1",
    "addr:housenumber":"3861",
    "addr:postcode":"l3v 1j1",
    "addr:street":"Campbell Rd",
    "iso:country":"CA",
    "sg:address":"3861 Campbell Rd",
    "sg:city":"Orillia",
    "sg:classifiers":[
        {
            "category":"Freight",
            "type":"Transportation"
        }
    ],
    "sg:phone":"+1 705 722 7691",
    "sg:postcode":"L3V 1J1",
    "sg:province":"ON",
    "sg:tags":[
        "mover"
    ],
    "wof:name":"Gary's Moving Svc",
    "wof:placetype":"venue"
},
  "geometry": {"coordinates":[-79.41822814939999,44.606590271],"type":"Point"}
}