{
  "type": "Feature",
  "properties": {
    "iso:country":"CA",
    "sg:address":"8075 22 St NE",
    "sg:city":"Calgary",
    "sg:classifiers":[
        {
            "category":"Airport",
            "type":"Transportation"
        }
    ],
    "sg:phone":"+1 403 291 0965",
    "sg:postcode":"T2E 7Z6",
    "sg:province":"AB",
    "sg:tags":[
        "aircraft",
        "maintenance"
    ],
    "wof:name":"Airport Terminal Svc Canadian",
    "wof:placetype":"venue"
},
  "geometry": {"coordinates":[-114.006393,51.124962],"type":"Point"}
}