{
  "type": "Feature",
  "properties": {
    "addr:full":"1346 Rue Des Fondateurs Paquetville NB E8R 1A4",
    "addr:housenumber":"1346",
    "addr:postcode":"e8r 1a4",
    "addr:street":"Rue Des Fondateurs",
    "iso:country":"CA",
    "sg:address":"1346 Rue Des Fondateurs",
    "sg:city":"Paquetville",
    "sg:classifiers":[
        {
            "category":"Personal",
            "subcategory":"Beauty Salon",
            "type":"Services"
        }
    ],
    "sg:phone":"+1 506 764 5299",
    "sg:postcode":"E8R 1A4",
    "sg:province":"NB",
    "wof:name":"Salon DE Coiffure Chez Dodo",
    "wof:placetype":"venue"
},
  "geometry": {"coordinates":[-65.118088,47.665775],"type":"Point"}
}