{
  "type": "Feature",
  "properties": {
    "addr:full":"1 Dairy Ave Napanee ON K7R 1M4",
    "addr:housenumber":"1",
    "addr:postcode":"k7r 1m4",
    "addr:street":"Dairy Ave",
    "iso:country":"CA",
    "sg:address":"1 Dairy Ave",
    "sg:city":"Napanee",
    "sg:classifiers":[
        {
            "category":"Wholesale",
            "subcategory":"Farm Supplies",
            "type":"Manufacturing & Wholesale Goods"
        }
    ],
    "sg:phone":"+1 613 354 4424",
    "sg:postcode":"K7R 1M4",
    "sg:province":"ON",
    "sg:tags":[
        "feed"
    ],
    "wof:name":"O'Neill's Farm Supply Ltd",
    "wof:placetype":"venue"
},
  "geometry": {"coordinates":[-76.9565124512,44.2547683716],"type":"Point"}
}