{
  "type": "Feature",
  "properties": {
    "addr:full":"1026 Rue Saint-Jean #203 Quebec QC G1R 1R7",
    "addr:housenumber":"1026;203",
    "addr:postcode":"g1r 1r7",
    "addr:street":"Rue Saint-Jean #",
    "iso:country":"CA",
    "sg:address":"1026 Rue Saint-Jean #203",
    "sg:city":"Quebec",
    "sg:classifiers":[
        {
            "category":"Building & Trades",
            "subcategory":"Equipment Rental",
            "type":"Services"
        }
    ],
    "sg:phone":"+1 418 692 3134",
    "sg:postcode":"G1R 1R7",
    "sg:province":"QC",
    "sg:tags":[
        "leasing",
        "camping"
    ],
    "wof:name":"Supervision Andre Duchesne Inc",
    "wof:placetype":"venue"
},
  "geometry": {"coordinates":[-71.212357,46.813046],"type":"Point"}
}