{
  "type": "Feature",
  "properties": {
    "addr:full":"Barrie ON L4M 1G8",
    "addr:postcode":"l4m 1g8",
    "iso:country":"CA",
    "sg:city":"Barrie",
    "sg:classifiers":[
        {
            "category":"Professional",
            "subcategory":"Research",
            "type":"Services"
        }
    ],
    "sg:phone":"+1 705 792 5750",
    "sg:postcode":"L4M 1G8",
    "sg:province":"ON",
    "sg:tags":[
        "environmental",
        "ecological"
    ],
    "wof:name":"Vicinia Corp",
    "wof:placetype":"venue"
},
  "geometry": {"coordinates":[-79.68678300000001,44.390549],"type":"Point"}
}