{
  "type": "Feature",
  "properties": {
    "iso:country":"CA",
    "sg:city":"Barrie",
    "sg:classifiers":[
        {
            "category":"Professional",
            "subcategory":"Research",
            "type":"Services"
        }
    ],
    "sg:phone":"+1 705 792 5750",
    "sg:postcode":"L4M 1G8",
    "sg:province":"ON",
    "sg:tags":[
        "environmental",
        "ecological"
    ],
    "wof:name":"Vicinia Corp",
    "wof:placetype":"venue"
},
  "geometry": {"coordinates":[-79.686783,44.390549],"type":"Point"}
}