{
  "type": "Feature",
  "properties": {
    "addr:full":"10741 Third Line RR 5 Milton ON L9T 2X9",
    "addr:housenumber":"10741",
    "addr:postcode":"l9t 2x9",
    "addr:street":"Third Line Rr 5",
    "iso:country":"CA",
    "sg:address":"10741 Third Line RR 5",
    "sg:city":"Milton",
    "sg:classifiers":[
        {
            "category":"Building & Trades",
            "subcategory":"Electrical",
            "type":"Services"
        }
    ],
    "sg:phone":"+1 905 876 4480",
    "sg:postcode":"L9T 2X9",
    "sg:province":"ON",
    "sg:tags":[
        "electric",
        "contractor"
    ],
    "wof:name":"Deerhurst Contractors",
    "wof:placetype":"venue"
},
  "geometry": {"coordinates":[-79.8838882446,43.5110359192],"type":"Point"}
}