{
  "type": "Feature",
  "properties": {
    "iso:country":"CA",
    "sg:address":"149 Rue Maltais",
    "sg:city":"Sept-Iles",
    "sg:classifiers":[
        {
            "category":"Freight",
            "type":"Transportation"
        }
    ],
    "sg:phone":"+1 418 962 3639",
    "sg:postcode":"G4R 3J8",
    "sg:province":"QC",
    "sg:tags":[
        "trucking"
    ],
    "wof:name":"Tessier Limitee",
    "wof:placetype":"venue"
},
  "geometry": {"coordinates":[-66.3673782349,50.2102813721],"type":"Point"}
}