{
  "type": "Feature",
  "properties": {
    "addr:full":"Montreal QC H4N 3H5",
    "addr:postcode":"h4n 3h5",
    "iso:country":"CA",
    "sg:city":"Montreal",
    "sg:classifiers":[
        {
            "category":"Banks & Credit Unions",
            "subcategory":"Investment Brokerage",
            "type":"Services"
        }
    ],
    "sg:phone":"+1 514 385 9001",
    "sg:postcode":"H4N 3H5",
    "sg:province":"QC",
    "sg:tags":[
        "advisory",
        "financial"
    ],
    "wof:name":"Allard Allard & Assoc",
    "wof:placetype":"venue"
},
  "geometry": {"coordinates":[-73.63369,45.581413],"type":"Point"}
}