{
  "type": "Feature",
  "properties": {
    "addr:full":"1905 Ogden Ave Vancouver BC V6J 1A3",
    "addr:housenumber":"1905",
    "addr:postcode":"v6j 1a3",
    "addr:street":"Ogden Ave",
    "iso:country":"CA",
    "sg:address":"1905 Ogden Ave",
    "sg:city":"Vancouver",
    "sg:classifiers":[
        {
            "category":"Museum",
            "type":"Entertainment"
        }
    ],
    "sg:phone":"+1 604 257 8300",
    "sg:postcode":"V6J 1A3",
    "sg:province":"BC",
    "wof:name":"Vancouver Maritime Museum",
    "wof:placetype":"venue"
},
  "geometry": {"coordinates":[-123.147781372,49.2769546509],"type":"Point"}
}