{
  "type": "Feature",
  "properties": {
    "addr:full":"395 Mountain Rd Moncton NB E1C 2M8",
    "addr:housenumber":"395",
    "addr:postcode":"e1c 2m8",
    "addr:street":"Mountain Rd",
    "iso:country":"CA",
    "sg:address":"395 Mountain Rd",
    "sg:city":"Moncton",
    "sg:classifiers":[
        {
            "category":"Retail",
            "subcategory":"Auto Repair",
            "type":"Services"
        }
    ],
    "sg:phone":"+1 506 853 1999",
    "sg:postcode":"E1C 2M8",
    "sg:province":"NB",
    "sg:tags":[
        "repairing",
        "automobile"
    ],
    "wof:name":"Westmount Service Ctr",
    "wof:placetype":"venue"
},
  "geometry": {"coordinates":[-64.79296100000001,46.096611],"type":"Point"}
}