{
  "type": "Feature",
  "properties": {
    "addr:full":"6146 80 St NW Edmonton AB T6E 4Y7",
    "addr:housenumber":"6146",
    "addr:postcode":"t6e 4y7",
    "addr:street":"80 St Nw",
    "iso:country":"CA",
    "sg:address":"6146 80 St NW",
    "sg:city":"Edmonton",
    "sg:classifiers":[
        {
            "category":"Cinema",
            "subcategory":"Movie Rental",
            "type":"Entertainment"
        }
    ],
    "sg:phone":"+1 780 465 5160",
    "sg:postcode":"T6E 4Y7",
    "sg:province":"AB",
    "sg:tags":[
        "video",
        "game",
        "leasing"
    ],
    "wof:name":"Simple Jet Technology CO Ltd",
    "wof:placetype":"venue"
},
  "geometry": {"coordinates":[-113.448494,53.498234],"type":"Point"}
}