{
  "type": "Feature",
  "properties": {
    "addr:full":"1750 Rue Notre-Dame Lachine QC H8S 2E7",
    "addr:housenumber":"1750",
    "addr:postcode":"h8s 2e7",
    "addr:street":"Rue Notre-Dame",
    "iso:country":"CA",
    "sg:address":"1750 Rue Notre-Dame",
    "sg:city":"Lachine",
    "sg:classifiers":[
        {
            "category":"Retail",
            "subcategory":"Funeral Services",
            "type":"Services"
        }
    ],
    "sg:phone":"+1 514 639 8360",
    "sg:postcode":"H8S 2E7",
    "sg:province":"QC",
    "sg:tags":[
        "director"
    ],
    "wof:name":"Urgel Bourgie Ltee",
    "wof:placetype":"venue"
},
  "geometry": {"coordinates":[-73.679726,45.435265],"type":"Point"}
}