{
  "type": "Feature",
  "properties": {
    "addr:full":"65 Av Duluth E Montreal QC H2W 1G9",
    "addr:postcode":"h2w 1g9",
    "addr:street":"65 Av Duluth E",
    "iso:country":"CA",
    "sg:address":"65 Av Duluth E",
    "sg:city":"Montreal",
    "sg:classifiers":[
        {
            "category":"Restaurant",
            "type":"Food & Drink"
        }
    ],
    "sg:phone":"+1 514 289 9972",
    "sg:postcode":"H2W 1G9",
    "sg:province":"QC",
    "wof:name":"Restaurant L'Harmonie D'Asie",
    "wof:placetype":"venue"
},
  "geometry": {"coordinates":[-73.578964,45.517689],"type":"Point"}
}