{
  "type": "Feature",
  "properties": {
    "iso:country":"CA",
    "sg:city":"Winterton",
    "sg:classifiers":[
        {
            "category":"Government",
            "subcategory":"Office",
            "type":"Public Place"
        }
    ],
    "sg:phone":"+1 709 583 2349",
    "sg:postcode":"A0B 3M0",
    "sg:province":"NL",
    "sg:tags":[
        "village"
    ],
    "wof:name":"Winterton Town Dump",
    "wof:placetype":"venue"
},
  "geometry": {"coordinates":[-53.3295555115,47.9556732178],"type":"Point"}
}