{
  "type": "Feature",
  "properties": {
    "addr:full":"19 Av DE LA Gare # K St-Sauveur-Des-Monts QC J0R 1R0",
    "addr:postcode":"j0r 1r0",
    "addr:street":"19 Av De La Gare # K St-Sauveur-Des-Monts",
    "iso:country":"CA",
    "sg:address":"19 Av DE LA Gare # K",
    "sg:city":"St-Sauveur-Des-Monts",
    "sg:classifiers":[
        {
            "category":"Building & Trades",
            "subcategory":"Plumbing",
            "type":"Services"
        }
    ],
    "sg:phone":"+1 450 227 6767",
    "sg:postcode":"J0R 1R0",
    "sg:province":"QC",
    "sg:tags":[
        "conditioning",
        "air",
        "system",
        "contractor"
    ],
    "wof:name":"Air DE Inc",
    "wof:placetype":"venue"
},
  "geometry": {"coordinates":[-74.157043,45.893936],"type":"Point"}
}