{
  "type": "Feature",
  "properties": {
    "addr:full":"6496 January Dr Niagara Falls ON L2J 4J4",
    "addr:housenumber":"6496",
    "addr:postcode":"l2j 4j4",
    "addr:street":"January Dr",
    "iso:country":"CA",
    "sg:address":"6496 January Dr",
    "sg:city":"Niagara Falls",
    "sg:classifiers":[
        {
            "category":"Building & Trades",
            "subcategory":"Construction",
            "type":"Services"
        }
    ],
    "sg:phone":"+1 905 356 7270",
    "sg:postcode":"L2J 4J4",
    "sg:province":"ON",
    "sg:tags":[
        "contractor",
        "general"
    ],
    "wof:name":"Frank Costantino Construction",
    "wof:placetype":"venue"
},
  "geometry": {"coordinates":[-79.105087,43.137985],"type":"Point"}
}