{
  "type": "Feature",
  "properties": {
    "addr:full":"Mccarthy Parent QC G0X 3P0",
    "addr:postcode":"g0x 3p0",
    "iso:country":"CA",
    "sg:address":"Mccarthy",
    "sg:city":"Parent",
    "sg:classifiers":[
        {
            "category":"Travel",
            "subcategory":"Campground",
            "type":"Entertainment"
        }
    ],
    "sg:phone":"+1 819 667 2556",
    "sg:postcode":"G0X 3P0",
    "sg:province":"QC",
    "sg:tags":[
        "camp"
    ],
    "wof:name":"Simard Fishing & Hunting Camp",
    "wof:placetype":"venue"
},
  "geometry": {"coordinates":[-74.624588,47.920414],"type":"Point"}
}