{
  "type": "Feature",
  "properties": {
    "addr:full":"642 the Queensway Etobicoke ON M8Y 1K5",
    "addr:housenumber":"642",
    "addr:postcode":"m8y 1k5",
    "addr:street":"The Queensway",
    "iso:country":"CA",
    "sg:address":"642 the Queensway",
    "sg:city":"Etobicoke",
    "sg:classifiers":[
        {
            "category":"Professional",
            "subcategory":"Business Services",
            "type":"Services"
        }
    ],
    "sg:phone":"+1 416 253 5508",
    "sg:postcode":"M8Y 1K5",
    "sg:province":"ON",
    "wof:name":"Schiralli Saverio Agencies Ltd",
    "wof:placetype":"venue"
},
  "geometry": {"coordinates":[-79.49719238279999,43.6275863647],"type":"Point"}
}