{
  "type": "Feature",
  "properties": {
    "addr:full":"Baie-Comeau QC G4Z 2Z1",
    "addr:postcode":"g4z 2z1",
    "iso:country":"CA",
    "sg:city":"Baie-Comeau",
    "sg:classifiers":[
        {
            "category":"Real Estate",
            "subcategory":"Real Estate Agent",
            "type":"Services"
        }
    ],
    "sg:phone":"+1 418 296 4444",
    "sg:postcode":"G4Z 2Z1",
    "sg:province":"QC",
    "wof:name":"Immeubles Re-Max",
    "wof:placetype":"venue"
},
  "geometry": {"coordinates":[-68.19207,49.214771],"type":"Point"}
}