{
  "type": "Feature",
  "properties": {
    "addr:full":"3860 Legion St Niagara Falls ON L2G 6C9",
    "addr:housenumber":"3860",
    "addr:postcode":"l2g 6c9",
    "addr:street":"Legion St",
    "iso:country":"CA",
    "sg:address":"3860 Legion St",
    "sg:city":"Niagara Falls",
    "sg:classifiers":[
        {
            "category":"Organizations",
            "subcategory":"Professional Association",
            "type":"Services"
        }
    ],
    "sg:phone":"+1 905 295 4451",
    "sg:postcode":"L2G 6C9",
    "sg:province":"ON",
    "wof:name":"Royal Canadian Legion",
    "wof:placetype":"venue"
},
  "geometry": {"coordinates":[-79.0560836792,43.060585022],"type":"Point"}
}