{
  "type": "Feature",
  "properties": {
    "addr:full":"3773 Boul DE LA Cote-Vertu # 350 Saint-Laurent QC H4R 2M3",
    "addr:housenumber":"3773",
    "addr:postcode":"h4r 2m3",
    "addr:street":"Boul De La Cote-Vertu # 350",
    "iso:country":"CA",
    "sg:address":"3773 Boul DE LA Cote-Vertu # 350",
    "sg:city":"Saint-Laurent",
    "sg:classifiers":[
        {
            "category":"Wholesale",
            "subcategory":"Office Equipment",
            "type":"Manufacturing & Wholesale Goods"
        }
    ],
    "sg:phone":"+1 514 744 9218",
    "sg:postcode":"H4R 2M3",
    "sg:province":"QC",
    "sg:tags":[
        "credit",
        "furniture"
    ],
    "wof:name":"Caplo Limitee",
    "wof:placetype":"venue"
},
  "geometry": {"coordinates":[-73.71006800000001,45.492832],"type":"Point"}
}