{
  "type": "Feature",
  "properties": {
    "iso:country":"CA",
    "sg:address":"3773 Boul DE LA Cote-Vertu # 350",
    "sg:city":"Saint-Laurent",
    "sg:classifiers":[
        {
            "category":"Wholesale",
            "subcategory":"Office Equipment",
            "type":"Manufacturing & Wholesale Goods"
        }
    ],
    "sg:phone":"+1 514 744 9218",
    "sg:postcode":"H4R 2M3",
    "sg:province":"QC",
    "sg:tags":[
        "credit",
        "furniture"
    ],
    "wof:name":"Caplo Limitee",
    "wof:placetype":"venue"
},
  "geometry": {"coordinates":[-73.710068,45.492832],"type":"Point"}
}