{
  "type": "Feature",
  "properties": {
    "addr:full":"Burnaby BC V5H 4L9",
    "addr:postcode":"v5h 4l9",
    "iso:country":"CA",
    "sg:city":"Burnaby",
    "sg:classifiers":[
        {
            "category":"Restaurant",
            "type":"Food & Drink"
        }
    ],
    "sg:phone":"+1 604 438 2288",
    "sg:postcode":"V5H 4L9",
    "sg:province":"BC",
    "wof:name":"Thai House Restaurant Ltd",
    "wof:placetype":"venue"
},
  "geometry": {"coordinates":[-123.002479553,49.2293434143],"type":"Point"}
}