{
  "type": "Feature",
  "properties": {
    "iso:country":"CA",
    "sg:address":"186 Principale",
    "sg:city":"Lac-Bouchette",
    "sg:classifiers":[
        {
            "category":"Government",
            "subcategory":"Office",
            "type":"Public Place"
        }
    ],
    "sg:phone":"+1 418 348 6306",
    "sg:postcode":"G0W 1V0",
    "sg:province":"QC",
    "sg:tags":[
        "village"
    ],
    "wof:name":"Lac Bouchette Secretaire Trsr",
    "wof:placetype":"venue"
},
  "geometry": {"coordinates":[-72.1817321777,48.263004303],"type":"Point"}
}