{
  "type": "Feature",
  "properties": {
    "iso:country":"CA",
    "sg:address":"3984 Spring Creek Rd",
    "sg:city":"Vineland",
    "sg:classifiers":[
        {
            "category":"Retail",
            "subcategory":"Auto Repair",
            "type":"Services"
        }
    ],
    "sg:phone":"+1 905 563 7961",
    "sg:postcode":"L0R 2C0",
    "sg:province":"ON",
    "sg:tags":[
        "repairing",
        "automobile"
    ],
    "wof:name":"Tintern Automotive",
    "wof:placetype":"venue"
},
  "geometry": {"coordinates":[-79.3944015503,43.159954071],"type":"Point"}
}