{
  "type": "Feature",
  "properties": {
    "addr:full":"77 Leighton Ave Winnipeg MB R2K 0J1",
    "addr:housenumber":"77",
    "addr:postcode":"r2k 0j1",
    "addr:street":"Leighton Ave",
    "iso:country":"CA",
    "sg:address":"77 Leighton Ave",
    "sg:city":"Winnipeg",
    "sg:classifiers":[
        {
            "category":"Wholesale",
            "subcategory":"Chemicals & Plastics",
            "type":"Manufacturing & Wholesale Goods"
        }
    ],
    "sg:phone":"+1 204 654 1225",
    "sg:postcode":"R2K 0J1",
    "sg:province":"MB",
    "sg:tags":[
        "adhesive",
        "glue"
    ],
    "wof:name":"Loctite Canada Inc",
    "wof:placetype":"venue"
},
  "geometry": {"coordinates":[-97.104752,49.935032],"type":"Point"}
}