{
  "type": "Feature",
  "properties": {
    "addr:full":"480 Gardiners Rd Kingston ON K7M 7W8",
    "addr:housenumber":"480",
    "addr:postcode":"k7m 7w8",
    "addr:street":"Gardiners Rd",
    "iso:country":"CA",
    "sg:address":"480 Gardiners Rd",
    "sg:city":"Kingston",
    "sg:classifiers":[
        {
            "category":"Personal",
            "subcategory":"Beauty Salon",
            "type":"Services"
        }
    ],
    "sg:phone":"+1 613 384 7057",
    "sg:postcode":"K7M 7W8",
    "sg:province":"ON",
    "wof:name":"First Choice Haircutters",
    "wof:placetype":"venue"
},
  "geometry": {"coordinates":[-76.56746699999999,44.236683],"type":"Point"}
}