{
  "type": "Feature",
  "properties": {
    "addr:full":"2202 Enderby Mabel Lake Rd Enderby BC V0E 1V5",
    "addr:housenumber":"2202",
    "addr:postcode":"v0e 1v5",
    "addr:street":"Mabel Lake Rd",
    "iso:country":"CA",
    "sg:address":"2202 Enderby Mabel Lake Rd",
    "sg:city":"Enderby",
    "sg:classifiers":[
        {
            "category":"Travel",
            "subcategory":"Hotels & Motels",
            "type":"Entertainment"
        }
    ],
    "sg:phone":"+1 250 838 6100",
    "sg:postcode":"V0E 1V5",
    "sg:province":"BC",
    "sg:tags":[
        "resort"
    ],
    "wof:name":"Shuswap Falls Rv Resort",
    "wof:placetype":"venue"
},
  "geometry": {"coordinates":[-119.140159607,50.5507011414],"type":"Point"}
}