{
  "type": "Feature",
  "properties": {
    "addr:full":"33 Cabot Dr Moncton NB E1A 5K8",
    "addr:housenumber":"33",
    "addr:postcode":"e1a 5k8",
    "addr:street":"Cabot Dr",
    "iso:country":"CA",
    "sg:address":"33 Cabot Dr",
    "sg:city":"Moncton",
    "sg:classifiers":[
        {
            "category":"Shopping",
            "type":"Retail Goods"
        }
    ],
    "sg:phone":"+1 506 856 9303",
    "sg:postcode":"E1A 5K8",
    "sg:province":"NB",
    "sg:tags":[
        "trophy",
        "medal",
        "award"
    ],
    "wof:name":"East Coast Trophies",
    "wof:placetype":"venue"
},
  "geometry": {"coordinates":[-64.7859344482,46.1235046387],"type":"Point"}
}