{
  "type": "Feature",
  "properties": {
    "addr:full":"37 Third Ave N Yorkton SK S3N 1C1",
    "addr:housenumber":"37",
    "addr:postcode":"s3n 1c1",
    "addr:street":"Third Ave N",
    "iso:country":"CA",
    "sg:address":"37 Third Ave N",
    "sg:city":"Yorkton",
    "sg:classifiers":[
        {
            "category":"Government",
            "subcategory":"Office",
            "type":"Public Place"
        }
    ],
    "sg:phone":"+1 306 786 1714",
    "sg:postcode":"S3N 1C1",
    "sg:province":"SK",
    "sg:tags":[
        "village"
    ],
    "wof:name":"City of Yorkton Taxation",
    "wof:placetype":"venue"
},
  "geometry": {"coordinates":[-102.45974699999999,51.211246],"type":"Point"}
}