{
  "type": "Feature",
  "properties": {
    "addr:full":"13651 72 Ave Surrey BC V3W 2P2",
    "addr:housenumber":"13651",
    "addr:postcode":"v3w 2p2",
    "addr:street":"72 Ave",
    "iso:country":"CA",
    "sg:address":"13651 72 Ave",
    "sg:city":"Surrey",
    "sg:classifiers":[
        {
            "category":"Restaurant",
            "type":"Food & Drink"
        }
    ],
    "sg:phone":"+1 604 592 2883",
    "sg:postcode":"V3W 2P2",
    "sg:province":"BC",
    "wof:name":"Kyotyo Sushi",
    "wof:placetype":"venue"
},
  "geometry": {"coordinates":[-122.844238,49.133766],"type":"Point"}
}