{
  "type": "Feature",
  "properties": {
    "addr:full":"57 Rue Girouard Victoriaville QC G6P 5T2",
    "addr:housenumber":"57",
    "addr:postcode":"g6p 5t2",
    "addr:street":"Rue Girouard",
    "iso:country":"CA",
    "sg:address":"57 Rue Girouard",
    "sg:city":"Victoriaville",
    "sg:classifiers":[
        {
            "category":"Wholesale",
            "subcategory":"Meat",
            "type":"Manufacturing & Wholesale Goods"
        }
    ],
    "sg:phone":"+1 819 357 5045",
    "sg:postcode":"G6P 5T2",
    "sg:province":"QC",
    "sg:tags":[
        "butchering"
    ],
    "wof:name":"Boucherie Houle & Guevin Enr",
    "wof:placetype":"venue"
},
  "geometry": {"coordinates":[-71.9322128296,46.0497283936],"type":"Point"}
}