{
  "type": "Feature",
  "properties": {
    "addr:full":"North York ON M2M 3W2",
    "addr:postcode":"m2m 3w2",
    "iso:country":"CA",
    "sg:city":"North York",
    "sg:classifiers":[
        {
            "category":"Professional",
            "subcategory":"Computer Services",
            "type":"Services"
        }
    ],
    "sg:phone":"+1 416 730 0313",
    "sg:postcode":"M2M 3W2",
    "sg:province":"ON",
    "wof:name":"Dawson Networks Inc",
    "wof:placetype":"venue"
},
  "geometry": {"coordinates":[-79.41767120359999,43.7891960144],"type":"Point"}
}