{
  "type": "Feature",
  "properties": {
    "addr:full":"409 Main St Liverpool NS B0T 1K0",
    "addr:housenumber":"409",
    "addr:postcode":"b0t 1k0",
    "addr:street":"Main St",
    "iso:country":"CA",
    "sg:address":"409 Main St",
    "sg:city":"Liverpool",
    "sg:classifiers":[
        {
            "category":"Organizations",
            "subcategory":"Religious Organization",
            "type":"Services"
        }
    ],
    "sg:phone":"+1 902 354 5851",
    "sg:postcode":"B0T 1K0",
    "sg:province":"NS",
    "sg:tags":[
        "church"
    ],
    "wof:name":"Zion United Church",
    "wof:placetype":"venue"
},
  "geometry": {"coordinates":[-64.72068,44.035763],"type":"Point"}
}