{
  "type": "Feature",
  "properties": {
    "addr:full":"3840 Rue Georges-Corbeil Terrebonne QC J6X 4J4",
    "addr:housenumber":"3840",
    "addr:postcode":"j6x 4j4",
    "addr:street":"Rue Georges-Corbeil",
    "iso:country":"CA",
    "sg:address":"3840 Rue Georges-Corbeil",
    "sg:city":"Terrebonne",
    "sg:classifiers":[
        {
            "category":"Home & Garden",
            "subcategory":"Building Materials",
            "type":"Retail Goods"
        }
    ],
    "sg:phone":"+1 450 990 1522",
    "sg:postcode":"J6X 4J4",
    "sg:province":"QC",
    "sg:tags":[
        "windows",
        "door"
    ],
    "wof:name":"Fabelta Aluminium Inc",
    "wof:placetype":"venue"
},
  "geometry": {"coordinates":[-73.674843,45.728798],"type":"Point"}
}