{
  "type": "Feature",
  "properties": {
    "addr:full":"888 Meadowlands Dr # 9 Ottawa ON K2C 3R2",
    "addr:housenumber":"888",
    "addr:postcode":"k2c 3r2",
    "addr:street":"Meadowlands Dr # 9",
    "iso:country":"CA",
    "sg:address":"888 Meadowlands Dr # 9",
    "sg:city":"Ottawa",
    "sg:classifiers":[
        {
            "category":"Health Services",
            "subcategory":"Doctor",
            "type":"Services"
        }
    ],
    "sg:phone":"+1 613 225 0225",
    "sg:postcode":"K2C 3R2",
    "sg:province":"ON",
    "sg:tags":[
        "dentist"
    ],
    "wof:name":"Locke, Peter T DDS",
    "wof:placetype":"venue"
},
  "geometry": {"coordinates":[-75.7014083862,45.3681793213],"type":"Point"}
}