{
  "type": "Feature",
  "properties": {
    "iso:country":"CA",
    "sg:city":"Langley",
    "sg:classifiers":[
        {
            "category":"Personal",
            "subcategory":"Tattoo Parlor",
            "type":"Services"
        }
    ],
    "sg:phone":"+1 604 514 9432",
    "sg:postcode":"V3A 4L9",
    "sg:province":"BC",
    "sg:tags":[
        "tattooing"
    ],
    "wof:name":"Ace Tattoo",
    "wof:placetype":"venue"
},
  "geometry": {"coordinates":[-122.658073425,49.1077957153],"type":"Point"}
}