{
  "type": "Feature",
  "properties": {
    "addr:full":"135 Main St Trenton NS B0K 1X0",
    "addr:housenumber":"135",
    "addr:postcode":"b0k 1x0",
    "addr:street":"Main St",
    "iso:country":"CA",
    "sg:address":"135 Main St",
    "sg:city":"Trenton",
    "sg:classifiers":[
        {
            "category":"Food & Beverages",
            "subcategory":"Groceries & Convenience Stores",
            "type":"Retail Goods"
        }
    ],
    "sg:phone":"+1 902 755 5655",
    "sg:postcode":"B0K 1X0",
    "sg:province":"NS",
    "wof:name":"Needs",
    "wof:placetype":"venue"
},
  "geometry": {"coordinates":[-62.639523,45.610336],"type":"Point"}
}