{
  "type": "Feature",
  "properties": {
    "iso:country":"CA",
    "sg:address":"29 Eaton St",
    "sg:city":"Georgetown",
    "sg:classifiers":[
        {
            "category":"Autos & Motor Vehicles",
            "subcategory":"Auto Supplies",
            "type":"Retail Goods"
        }
    ],
    "sg:phone":"+1 905 877 6303",
    "sg:postcode":"L7G 5L4",
    "sg:province":"ON",
    "sg:tags":[
        "automobile",
        "parts"
    ],
    "wof:name":"Kerr Machine Shop Group",
    "wof:placetype":"venue"
},
  "geometry": {"coordinates":[-79.88632202150001,43.6336364746],"type":"Point"}
}