{
  "type": "Feature",
  "properties": {
    "addr:full":"640 Queen St E Sault Ste Marie ON P6A 2A4",
    "addr:housenumber":"640",
    "addr:postcode":"p6a 2a4",
    "addr:street":"Queen St E",
    "iso:country":"CA",
    "sg:address":"640 Queen St E",
    "sg:city":"Sault Ste Marie",
    "sg:classifiers":[
        {
            "category":"Personal",
            "subcategory":"Beauty Salon",
            "type":"Services"
        }
    ],
    "sg:phone":"+1 705 254 5381",
    "sg:postcode":"P6A 2A4",
    "sg:province":"ON",
    "wof:name":"Continental Hair Stylists",
    "wof:placetype":"venue"
},
  "geometry": {"coordinates":[-84.328903,46.50869],"type":"Point"}
}