{
  "type": "Feature",
  "properties": {
    "addr:full":"577 Hamilton Rd London ON N5Z 1S5",
    "addr:housenumber":"577",
    "addr:postcode":"n5z 1s5",
    "addr:street":"Hamilton Rd",
    "iso:country":"CA",
    "sg:address":"577 Hamilton Rd",
    "sg:city":"London",
    "sg:classifiers":[
        {
            "category":"Food & Beverages",
            "subcategory":"Groceries & Convenience Stores",
            "type":"Retail Goods"
        }
    ],
    "sg:phone":"+1 519 439 8829",
    "sg:postcode":"N5Z 1S5",
    "sg:province":"ON",
    "sg:tags":[
        "grocer"
    ],
    "wof:name":"Asia Chinese Food Supplier",
    "wof:placetype":"venue"
},
  "geometry": {"coordinates":[-81.21369199999999,42.980186],"type":"Point"}
}