{
  "type": "Feature",
  "properties": {
    "iso:country":"CA",
    "sg:address":"577 Hamilton Rd",
    "sg:city":"London",
    "sg:classifiers":[
        {
            "category":"Food & Beverages",
            "subcategory":"Groceries & Convenience Stores",
            "type":"Retail Goods"
        }
    ],
    "sg:phone":"+1 519 439 8829",
    "sg:postcode":"N5Z 1S5",
    "sg:province":"ON",
    "sg:tags":[
        "grocer"
    ],
    "wof:name":"Asia Chinese Food Supplier",
    "wof:placetype":"venue"
},
  "geometry": {"coordinates":[-81.213692,42.980186],"type":"Point"}
}