{
  "type": "Feature",
  "properties": {
    "iso:country":"CA",
    "sg:address":"57 Pontiac St",
    "sg:city":"Eganville",
    "sg:classifiers":[
        {
            "category":"Organizations",
            "subcategory":"Professional Association",
            "type":"Services"
        }
    ],
    "sg:phone":"+1 613 628 2802",
    "sg:postcode":"K0J 1T0",
    "sg:province":"ON",
    "wof:name":"Royal Canadian Legion Branch",
    "wof:placetype":"venue"
},
  "geometry": {"coordinates":[-77.1005325317,45.5377044678],"type":"Point"}
}