{
  "type": "Feature",
  "properties": {
    "addr:full":"53 5E Av Saint-Gabriel-DE-Valcartier QC G0A 4S0",
    "addr:housenumber":"53",
    "addr:postcode":"g0a 4s0",
    "addr:street":"5E Av",
    "iso:country":"CA",
    "sg:address":"53 5E Av",
    "sg:city":"Saint-Gabriel-DE-Valcartier",
    "sg:classifiers":[
        {
            "category":"Travel",
            "subcategory":"Hotels & Motels",
            "type":"Entertainment"
        }
    ],
    "sg:phone":"+1 418 844 3166",
    "sg:postcode":"G0A 4S0",
    "sg:province":"QC",
    "wof:name":"Auberge LA Seigneurie",
    "wof:placetype":"venue"
},
  "geometry": {"coordinates":[-71.466667,46.949444],"type":"Point"}
}