{
  "type": "Feature",
  "properties": {
    "addr:full":"280 Montee DE Liesse Saint-Laurent QC H4T 1N8",
    "addr:housenumber":"280",
    "addr:postcode":"h4t 1n8",
    "addr:street":"Montee De Liesse",
    "iso:country":"CA",
    "sg:address":"280 Montee DE Liesse",
    "sg:city":"Saint-Laurent",
    "sg:classifiers":[
        {
            "category":"Freight",
            "type":"Transportation"
        }
    ],
    "sg:phone":"+1 514 341 5666",
    "sg:postcode":"H4T 1N8",
    "sg:province":"QC",
    "sg:tags":[
        "trucking"
    ],
    "wof:name":"Laurentien Transport",
    "wof:placetype":"venue"
},
  "geometry": {"coordinates":[-73.705871582,45.4786224365],"type":"Point"}
}