{
  "type": "Feature",
  "properties": {
    "addr:full":"Winnipeg MB R3C 2E6",
    "addr:postcode":"r3c 2e6",
    "iso:country":"CA",
    "sg:city":"Winnipeg",
    "sg:classifiers":[
        {
            "category":"Wholesale",
            "subcategory":"Machinery & Supplies",
            "type":"Manufacturing & Wholesale Goods"
        }
    ],
    "sg:phone":"+1 204 694 4085",
    "sg:postcode":"R3C 2E6",
    "sg:province":"MB",
    "sg:tags":[
        "equipment",
        "livestock"
    ],
    "wof:name":"Weiller & Williams",
    "wof:placetype":"venue"
},
  "geometry": {"coordinates":[-97.321243,49.990147],"type":"Point"}
}