{
  "type": "Feature",
  "properties": {
    "addr:full":"352 Rue Laurent Saint-Simeon QC G0T 1X0",
    "addr:housenumber":"352",
    "addr:postcode":"g0t 1x0",
    "addr:street":"Rue Laurent Saint-Simeon",
    "iso:country":"CA",
    "sg:address":"352 Rue Laurent",
    "sg:city":"Saint-Simeon",
    "sg:classifiers":[
        {
            "category":"Food & Beverages",
            "subcategory":"Groceries & Convenience Stores",
            "type":"Retail Goods"
        }
    ],
    "sg:phone":"+1 418 638 5338",
    "sg:postcode":"G0T 1X0",
    "sg:province":"QC",
    "sg:tags":[
        "grocer"
    ],
    "wof:name":"Alimentation Hjm Inc",
    "wof:placetype":"venue"
},
  "geometry": {"coordinates":[-69.87902832029999,47.8436012268],"type":"Point"}
}