{
  "type": "Feature",
  "properties": {
    "addr:full":"North Vancouver BC V7N 4M2",
    "addr:postcode":"v7n 4m2",
    "iso:country":"CA",
    "sg:city":"North Vancouver",
    "sg:classifiers":[
        {
            "category":"Health Services",
            "subcategory":"Optometrist",
            "type":"Services"
        }
    ],
    "sg:phone":"+1 604 980 5367",
    "sg:postcode":"V7N 4M2",
    "sg:province":"BC",
    "wof:name":"Westview Optometry",
    "wof:placetype":"venue"
},
  "geometry": {"coordinates":[-123.088348,49.333393],"type":"Point"}
}