{
  "type": "Feature",
  "properties": {
    "addr:full":"94 Main St S Hagersville ON N0A 1H0",
    "addr:housenumber":"94",
    "addr:postcode":"n0a 1h0",
    "addr:street":"Main St S",
    "iso:country":"CA",
    "sg:address":"94 Main St S",
    "sg:city":"Hagersville",
    "sg:classifiers":[
        {
            "category":"Organizations",
            "subcategory":"Religious Organization",
            "type":"Services"
        }
    ],
    "sg:phone":"+1 905 768 5726",
    "sg:postcode":"N0A 1H0",
    "sg:province":"ON",
    "sg:tags":[
        "church"
    ],
    "wof:name":"St Mary's Church",
    "wof:placetype":"venue"
},
  "geometry": {"coordinates":[-80.0567474365,42.9567108154],"type":"Point"}
}