{
  "type": "Feature",
  "properties": {
    "addr:full":"Saint-Nicolas QC G7A 4X6",
    "addr:postcode":"g7a 4x6",
    "iso:country":"CA",
    "sg:city":"Saint-Nicolas",
    "sg:classifiers":[
        {
            "category":"Building & Trades",
            "subcategory":"Construction",
            "type":"Services"
        }
    ],
    "sg:phone":"+1 418 831 1330",
    "sg:postcode":"G7A 4X6",
    "sg:province":"QC",
    "sg:tags":[
        "builder",
        "patio",
        "deck"
    ],
    "wof:name":"Rampes Gardex Inc",
    "wof:placetype":"venue"
},
  "geometry": {"coordinates":[-71.337852478,46.6727600098],"type":"Point"}
}