{
  "type": "Feature",
  "properties": {
    "addr:full":"37 Rue Saint-Pierre Saint-Constant QC J5A 1B9",
    "addr:housenumber":"37",
    "addr:postcode":"j5a 1b9",
    "addr:street":"Rue Saint-Pierre",
    "iso:country":"CA",
    "sg:address":"37 Rue Saint-Pierre",
    "sg:city":"Saint-Constant",
    "sg:classifiers":[
        {
            "category":"Health Services",
            "subcategory":"Doctor",
            "type":"Services"
        }
    ],
    "sg:phone":"+1 450 632 8231",
    "sg:postcode":"J5A 1B9",
    "sg:province":"QC",
    "sg:tags":[
        "clinic",
        "veterinarian"
    ],
    "wof:name":"Hopital Vet St-Constant Enr",
    "wof:placetype":"venue"
},
  "geometry": {"coordinates":[-73.560256958,45.3824768066],"type":"Point"}
}