{
  "type": "Feature",
  "properties": {
    "addr:full":"129 Main St N Milk River AB T0K 1M0",
    "addr:housenumber":"129",
    "addr:postcode":"t0k 1m0",
    "addr:street":"Main St N Milk",
    "iso:country":"CA",
    "sg:address":"129 Main St N",
    "sg:city":"Milk River",
    "sg:classifiers":[
        {
            "category":"Building & Trades",
            "subcategory":"Electrical",
            "type":"Services"
        }
    ],
    "sg:phone":"+1 403 647 3966",
    "sg:postcode":"T0K 1M0",
    "sg:province":"AB",
    "sg:tags":[
        "electric",
        "contractor"
    ],
    "wof:name":"Clark's Electric",
    "wof:placetype":"venue"
},
  "geometry": {"coordinates":[-112.086868286,49.1485366821],"type":"Point"}
}