{
  "type": "Feature",
  "properties": {
    "addr:full":"314 Stanley Ave Hamilton ON L8P 2L6",
    "addr:housenumber":"314",
    "addr:postcode":"l8p 2l6",
    "addr:street":"Stanley Ave",
    "iso:country":"CA",
    "sg:address":"314 Stanley Ave",
    "sg:city":"Hamilton",
    "sg:classifiers":[
        {
            "category":"Freight",
            "type":"Transportation"
        }
    ],
    "sg:phone":"+1 905 526 1601",
    "sg:postcode":"L8P 2L6",
    "sg:province":"ON",
    "sg:tags":[
        "piano",
        "mover"
    ],
    "wof:name":"Ivory Touch Piano CO",
    "wof:placetype":"venue"
},
  "geometry": {"coordinates":[-79.8950805664,43.2537574768],"type":"Point"}
}