{
  "type": "Feature",
  "properties": {
    "addr:full":"10047 80 Ave NW Edmonton AB T6E 1T4",
    "addr:housenumber":"10047",
    "addr:postcode":"t6e 1t4",
    "addr:street":"80 Ave Nw",
    "iso:country":"CA",
    "sg:address":"10047 80 Ave NW",
    "sg:city":"Edmonton",
    "sg:classifiers":[
        {
            "category":"Shopping",
            "subcategory":"Bicycles & Sporting Goods",
            "type":"Retail Goods"
        }
    ],
    "sg:phone":"+1 780 433 2453",
    "sg:postcode":"T6E 1T4",
    "sg:province":"AB",
    "wof:name":"Edmonton Bicycle Commuters",
    "wof:placetype":"venue"
},
  "geometry": {"coordinates":[-113.489944458,53.5158843994],"type":"Point"}
}