{
  "type": "Feature",
  "properties": {
    "addr:full":"4462 Frances St Burnaby BC V5C 2R4",
    "addr:housenumber":"4462",
    "addr:postcode":"v5c 2r4",
    "addr:street":"Frances St",
    "iso:country":"CA",
    "sg:address":"4462 Frances St",
    "sg:city":"Burnaby",
    "sg:classifiers":[
        {
            "category":"Manufacturing",
            "subcategory":"Signs",
            "type":"Manufacturing & Wholesale Goods"
        }
    ],
    "sg:phone":"+1 604 299 2901",
    "sg:postcode":"V5C 2R4",
    "sg:province":"BC",
    "wof:name":"Burnaby Signs",
    "wof:placetype":"venue"
},
  "geometry": {"coordinates":[-123.004272,49.279076],"type":"Point"}
}