{
  "type": "Feature",
  "properties": {
    "iso:country":"CA",
    "sg:address":"27 Beech St E",
    "sg:city":"Chapleau",
    "sg:classifiers":[
        {
            "category":"Autos & Motor Vehicles",
            "subcategory":"Boat Sales",
            "type":"Retail Goods"
        }
    ],
    "sg:phone":"+1 705 864 0739",
    "sg:postcode":"P0M 1K0",
    "sg:province":"ON",
    "sg:tags":[
        "outboard"
    ],
    "wof:name":"Robitaille Camille Svc",
    "wof:placetype":"venue"
},
  "geometry": {"coordinates":[-83.4021453857,47.8438034058],"type":"Point"}
}