{
  "type": "Feature",
  "properties": {
    "iso:country":"CA",
    "sg:city":"Orleans",
    "sg:classifiers":[
        {
            "category":"Social Services",
            "type":"Services"
        }
    ],
    "sg:phone":"+1 613 837 9868",
    "sg:postcode":"K1C 1E9",
    "sg:province":"ON",
    "sg:tags":[
        "counselor",
        "marriage",
        "family"
    ],
    "wof:name":"Orleans Centre For Marriage",
    "wof:placetype":"venue"
},
  "geometry": {"coordinates":[-75.527961731,45.4697952271],"type":"Point"}
}