{
  "type": "Feature",
  "properties": {
    "addr:full":"9523 163 St NW Edmonton AB T5P 3M6",
    "addr:housenumber":"9523",
    "addr:postcode":"t5p 3m6",
    "addr:street":"163 St Nw",
    "iso:country":"CA",
    "sg:address":"9523 163 St NW",
    "sg:city":"Edmonton",
    "sg:classifiers":[
        {
            "category":"Real Estate",
            "subcategory":"Real Estate Agent",
            "type":"Services"
        }
    ],
    "sg:phone":"+1 780 413 8880",
    "sg:postcode":"T5P 3M6",
    "sg:province":"AB",
    "sg:tags":[
        "management"
    ],
    "wof:name":"Prosperitas Management Ltd",
    "wof:placetype":"venue"
},
  "geometry": {"coordinates":[-113.602295,53.532135],"type":"Point"}
}