{
  "type": "Feature",
  "properties": {
    "iso:country":"CA",
    "sg:address":"3 Canal St E",
    "sg:city":"Bobcaygeon",
    "sg:classifiers":[
        {
            "category":"Travel",
            "subcategory":"Hotels & Motels",
            "type":"Entertainment"
        }
    ],
    "sg:phone":"+1 705 738 4300",
    "sg:postcode":"K0M 1A0",
    "sg:province":"ON",
    "wof:name":"New Rockland Motel",
    "wof:placetype":"venue"
},
  "geometry": {"coordinates":[-78.5443649292,44.5377044678],"type":"Point"}
}