{
  "type": "Feature",
  "properties": {
    "iso:country":"CA",
    "sg:city":"Mississauga",
    "sg:classifiers":[
        {
            "category":"Manufacturing",
            "subcategory":"Food",
            "type":"Manufacturing & Wholesale Goods"
        }
    ],
    "sg:phone":"+1 905 275 7400",
    "sg:postcode":"L4Y 3Y3",
    "sg:province":"ON",
    "sg:tags":[
        "frozen",
        "processor"
    ],
    "wof:name":"Molinaro Fine Italian Foods",
    "wof:placetype":"venue"
},
  "geometry": {"coordinates":[-79.5830154419,43.5984535217],"type":"Point"}
}