{
  "type": "Feature",
  "properties": {
    "addr:full":"740 Rue Saint-Edouard Saint-Urbain-DE-Charlevoix QC G0A 4K0",
    "addr:housenumber":"740",
    "addr:postcode":"g0a 4k0",
    "addr:street":"Rue Saint-Edouard Saint-Urbain-De-Charlevoix",
    "iso:country":"CA",
    "sg:address":"740 Rue Saint-Edouard",
    "sg:city":"Saint-Urbain-DE-Charlevoix",
    "sg:classifiers":[
        {
            "category":"Retail",
            "subcategory":"Auto Repair",
            "type":"Services"
        }
    ],
    "sg:phone":"+1 418 639 2971",
    "sg:postcode":"G0A 4K0",
    "sg:province":"QC",
    "sg:tags":[
        "repairing",
        "automobile"
    ],
    "wof:name":"Garage Jr Fortin & Fils Inc",
    "wof:placetype":"venue"
},
  "geometry": {"coordinates":[-70.54526519780001,47.5604400635],"type":"Point"}
}