{
  "type": "Feature",
  "properties": {
    "addr:full":"6 Cameron St E Cannington ON L0E 1E0",
    "addr:housenumber":"6",
    "addr:postcode":"l0e 1e0",
    "addr:street":"Cameron St E",
    "iso:country":"CA",
    "sg:address":"6 Cameron St E",
    "sg:city":"Cannington",
    "sg:classifiers":[
        {
            "category":"Shopping",
            "subcategory":"Pharmacy",
            "type":"Retail Goods"
        }
    ],
    "sg:phone":"+1 705 432 2644",
    "sg:postcode":"L0E 1E0",
    "sg:province":"ON",
    "wof:name":"Ben's Pharmacy",
    "wof:placetype":"venue"
},
  "geometry": {"coordinates":[-79.038383,44.350403],"type":"Point"}
}