{
  "type": "Feature",
  "properties": {
    "addr:full":"730 Wilson Ave North York ON M3K 1E2",
    "addr:housenumber":"730",
    "addr:postcode":"m3k 1e2",
    "addr:street":"Wilson Ave",
    "iso:country":"CA",
    "sg:address":"730 Wilson Ave",
    "sg:city":"North York",
    "sg:classifiers":[
        {
            "category":"Retail",
            "subcategory":"Portrait Studio",
            "type":"Services"
        }
    ],
    "sg:phone":"+1 416 638 7080",
    "sg:postcode":"M3K 1E2",
    "sg:province":"ON",
    "sg:tags":[
        "photographer"
    ],
    "wof:name":"S & K Photography",
    "wof:placetype":"venue"
},
  "geometry": {"coordinates":[-79.463638,43.731503],"type":"Point"}
}