{
  "type": "Feature",
  "properties": {
    "iso:country":"CA",
    "sg:address":"50 Lancaster St W",
    "sg:city":"Kitchener",
    "sg:classifiers":[
        {
            "category":"Autos & Motor Vehicles",
            "subcategory":"Auto Supplies",
            "type":"Retail Goods"
        }
    ],
    "sg:phone":"+1 519 745 6441",
    "sg:postcode":"N2H 4T2",
    "sg:province":"ON",
    "sg:tags":[
        "tire"
    ],
    "wof:name":"Woodside Tire",
    "wof:placetype":"venue"
},
  "geometry": {"coordinates":[-80.4830780029,43.4604225159],"type":"Point"}
}