{
  "type": "Feature",
  "properties": {
    "iso:country":"CA",
    "sg:address":"134 London St S",
    "sg:city":"Hamilton",
    "sg:classifiers":[
        {
            "category":"Shopping",
            "subcategory":"Florist",
            "type":"Retail Goods"
        }
    ],
    "sg:phone":"+1 905 545 2910",
    "sg:postcode":"L8K 2G5",
    "sg:province":"ON",
    "wof:name":"Mimi's House of Flowers & Gift",
    "wof:placetype":"venue"
},
  "geometry": {"coordinates":[-79.8204879761,43.2383918762],"type":"Point"}
}