{
  "type": "Feature",
  "properties": {
    "addr:full":"30 Peartree Cres Guelph ON N1H 8J2",
    "addr:housenumber":"30",
    "addr:postcode":"n1h 8j2",
    "addr:street":"Peartree Cres",
    "iso:country":"CA",
    "sg:address":"30 Peartree Cres",
    "sg:city":"Guelph",
    "sg:classifiers":[
        {
            "category":"Personal",
            "subcategory":"Beauty Salon",
            "type":"Services"
        }
    ],
    "sg:phone":"+1 519 763 0864",
    "sg:postcode":"N1H 8J2",
    "sg:province":"ON",
    "wof:name":"Carissima Aesthetics",
    "wof:placetype":"venue"
},
  "geometry": {"coordinates":[-80.3013916016,43.5295562744],"type":"Point"}
}