{
  "type": "Feature",
  "properties": {
    "iso:country":"CA",
    "sg:address":"266 Sherbrook St",
    "sg:city":"Winnipeg",
    "sg:classifiers":[
        {
            "category":"Building & Trades",
            "subcategory":"Electrical",
            "type":"Services"
        }
    ],
    "sg:phone":"+1 204 475 1202",
    "sg:postcode":"R3C 2B9",
    "sg:province":"MB",
    "sg:tags":[
        "plumbing",
        "electric",
        "contractor"
    ],
    "wof:name":"Parsons Plumbing & Heating CO",
    "wof:placetype":"venue"
},
  "geometry": {"coordinates":[-97.1593780518,49.886844635],"type":"Point"}
}