{
  "type": "Feature",
  "properties": {
    "addr:full":"449 Logan Ave Winnipeg MB R3A 0R6",
    "addr:housenumber":"449",
    "addr:postcode":"r3a 0r6",
    "addr:street":"Logan Ave",
    "iso:country":"CA",
    "sg:address":"449 Logan Ave",
    "sg:city":"Winnipeg",
    "sg:classifiers":[
        {
            "category":"Retail",
            "subcategory":"Car Wash",
            "type":"Services"
        }
    ],
    "sg:phone":"+1 204 956 2322",
    "sg:postcode":"R3A 0R6",
    "sg:province":"MB",
    "sg:tags":[
        "polishing",
        "washing"
    ],
    "wof:name":"Coin Wash",
    "wof:placetype":"venue"
},
  "geometry": {"coordinates":[-97.1443328857,49.9054527283],"type":"Point"}
}