{
  "type": "Feature",
  "properties": {
    "addr:full":"18 Rue Principale E Sainte-Agathe-Des-Monts QC J8C 1J4",
    "addr:housenumber":"18",
    "addr:postcode":"j8c 1j4",
    "addr:street":"Rue Principale E Sainte-Agathe-Des-Monts",
    "iso:country":"CA",
    "sg:address":"18 Rue Principale E",
    "sg:city":"Sainte-Agathe-Des-Monts",
    "sg:classifiers":[
        {
            "category":"Shopping",
            "subcategory":"Books",
            "type":"Retail Goods"
        }
    ],
    "sg:phone":"+1 819 326 2950",
    "sg:postcode":"J8C 1J4",
    "sg:province":"QC",
    "sg:tags":[
        "dealer"
    ],
    "wof:name":"Libraire Ste Marie Inc",
    "wof:placetype":"venue"
},
  "geometry": {"coordinates":[-74.287178,46.047089],"type":"Point"}
}