{
  "type": "Feature",
  "properties": {
    "addr:full":"1420 Dundas St W Toronto ON M6J 1Y5",
    "addr:housenumber":"1420",
    "addr:postcode":"m6j 1y5",
    "addr:street":"Dundas St W",
    "iso:country":"CA",
    "sg:address":"1420 Dundas St W",
    "sg:city":"Toronto",
    "sg:classifiers":[
        {
            "category":"Personal",
            "subcategory":"Beauty Salon",
            "type":"Services"
        }
    ],
    "sg:phone":"+1 416 538 1633",
    "sg:postcode":"M6J 1Y5",
    "sg:province":"ON",
    "wof:name":"Christina's Hair Studio",
    "wof:placetype":"venue"
},
  "geometry": {"coordinates":[-79.429337,43.649704],"type":"Point"}
}