{
  "type": "Feature",
  "properties": {
    "addr:full":"5107 Doyle Ave Donnelly AB T0H 1G0",
    "addr:housenumber":"5107",
    "addr:postcode":"t0h 1g0",
    "addr:street":"Doyle Ave",
    "iso:country":"CA",
    "sg:address":"5107 Doyle Ave",
    "sg:city":"Donnelly",
    "sg:classifiers":[
        {
            "category":"Retail",
            "subcategory":"Auto Repair",
            "type":"Services"
        }
    ],
    "sg:phone":"+1 780 925 3998",
    "sg:postcode":"T0H 1G0",
    "sg:province":"AB",
    "sg:tags":[
        "repairing",
        "automobile"
    ],
    "wof:name":"Charlie's Auto Repair",
    "wof:placetype":"venue"
},
  "geometry": {"coordinates":[-117.101921081,55.7253761292],"type":"Point"}
}