{
  "type": "Feature",
  "properties": {
    "addr:full":"10 Parkhill Rd Halifax NS B3P 1R3",
    "addr:housenumber":"10",
    "addr:postcode":"b3p 1r3",
    "addr:street":"Parkhill Rd",
    "iso:country":"CA",
    "sg:address":"10 Parkhill Rd",
    "sg:city":"Halifax",
    "sg:classifiers":[
        {
            "category":"Organizations",
            "subcategory":"Religious Organization",
            "type":"Services"
        }
    ],
    "sg:phone":"+1 902 477 0008",
    "sg:postcode":"B3P 1R3",
    "sg:province":"NS",
    "sg:tags":[
        "church"
    ],
    "wof:name":"Maritime Sikh Society",
    "wof:placetype":"venue"
},
  "geometry": {"coordinates":[-63.600834,44.62447],"type":"Point"}
}