{
  "type": "Feature",
  "properties": {
    "iso:country":"CA",
    "sg:city":"Delta",
    "sg:classifiers":[
        {
            "category":"Personal",
            "subcategory":"Beauty Salon",
            "type":"Services"
        }
    ],
    "sg:phone":"+1 604 591 7414",
    "sg:postcode":"V4C 2K4",
    "sg:province":"BC",
    "wof:name":"Alberto's Unisex Hairdesign",
    "wof:placetype":"venue"
},
  "geometry": {"coordinates":[-122.91368866000001,49.156211853],"type":"Point"}
}