{
  "type": "Feature",
  "properties": {
    "addr:full":"401 George St N Peterborough ON K9H 3R4",
    "addr:housenumber":"401",
    "addr:postcode":"k9h 3r4",
    "addr:street":"George St N",
    "iso:country":"CA",
    "sg:address":"401 George St N",
    "sg:city":"Peterborough",
    "sg:classifiers":[
        {
            "category":"Banks & Credit Unions",
            "subcategory":"Bank",
            "type":"Services"
        }
    ],
    "sg:phone":"+1 705 876 3520",
    "sg:postcode":"K9H 3R4",
    "sg:province":"ON",
    "wof:name":"Royal Bank Financial Group",
    "wof:placetype":"venue"
},
  "geometry": {"coordinates":[-78.320251,44.306034],"type":"Point"}
}