{
  "type": "Feature",
  "properties": {
    "addr:full":"Waterloo QC J0E 2N0",
    "addr:postcode":"j0e 2n0",
    "iso:country":"CA",
    "sg:city":"Waterloo",
    "sg:classifiers":[
        {
            "category":"Organizations",
            "subcategory":"Religious Organization",
            "type":"Services"
        }
    ],
    "sg:phone":"+1 450 539 2078",
    "sg:postcode":"J0E 2N0",
    "sg:province":"QC",
    "sg:tags":[
        "church"
    ],
    "wof:name":"St Luke's Anglican Church",
    "wof:placetype":"venue"
},
  "geometry": {"coordinates":[-72.5160980225,45.3435668945],"type":"Point"}
}