{
  "type": "Feature",
  "properties": {
    "addr:full":"4107 Portage Rd Niagara Falls ON L2E 6A2",
    "addr:housenumber":"4107",
    "addr:postcode":"l2e 6a2",
    "addr:street":"Portage Rd",
    "iso:country":"CA",
    "sg:address":"4107 Portage Rd",
    "sg:city":"Niagara Falls",
    "sg:classifiers":[
        {
            "category":"Health Services",
            "subcategory":"Medical Lab",
            "type":"Services"
        }
    ],
    "sg:phone":"+1 905 356 2535",
    "sg:postcode":"L2E 6A2",
    "sg:province":"ON",
    "wof:name":"Stamford Dentures",
    "wof:placetype":"venue"
},
  "geometry": {"coordinates":[-79.098732,43.114498],"type":"Point"}
}