{
  "type": "Feature",
  "properties": {
    "addr:full":"Waterford ON N0E 1Y0",
    "addr:postcode":"n0e 1y0",
    "iso:country":"CA",
    "sg:city":"Waterford",
    "sg:classifiers":[
        {
            "category":"Building & Trades",
            "subcategory":"Plumbing",
            "type":"Services"
        }
    ],
    "sg:phone":"+1 519 443 7936",
    "sg:postcode":"N0E 1Y0",
    "sg:province":"ON",
    "sg:tags":[
        "conditioning",
        "air",
        "system",
        "contractor"
    ],
    "wof:name":"Keith A Hutchinson Heating Ltd",
    "wof:placetype":"venue"
},
  "geometry": {"coordinates":[-80.288605,42.925114],"type":"Point"}
}