{
  "type": "Feature",
  "properties": {
    "addr:full":"21979 8 Ave Langley BC V2Z 1R4",
    "addr:housenumber":"21979",
    "addr:postcode":"v2z 1r4",
    "addr:street":"8 Ave",
    "iso:country":"CA",
    "sg:address":"21979 8 Ave",
    "sg:city":"Langley",
    "sg:classifiers":[
        {
            "category":"Shopping",
            "subcategory":"Jewelry",
            "type":"Retail Goods"
        }
    ],
    "sg:phone":"+1 604 534 6790",
    "sg:postcode":"V2Z 1R4",
    "sg:province":"BC",
    "sg:tags":[
        "designer",
        "jeweler"
    ],
    "wof:name":"Country Goldsmith Ltd",
    "wof:placetype":"venue"
},
  "geometry": {"coordinates":[-122.61599699999999,49.016865],"type":"Point"}
}