{
  "type": "Feature",
  "properties": {
    "iso:country":"CA",
    "sg:address":"59 Roy Blvd",
    "sg:city":"Brantford",
    "sg:classifiers":[
        {
            "category":"Freight",
            "type":"Transportation"
        }
    ],
    "sg:phone":"+1 519 754 0962",
    "sg:postcode":"N3R 7K1",
    "sg:province":"ON",
    "sg:tags":[
        "machinery",
        "trucking"
    ],
    "wof:name":"Lmt Transportation Svc",
    "wof:placetype":"venue"
},
  "geometry": {"coordinates":[-80.22737121580001,43.1720428467],"type":"Point"}
}