{
  "type": "Feature",
  "properties": {
    "addr:full":"4307 200 St Langley BC V3A 1L2",
    "addr:housenumber":"4307",
    "addr:postcode":"v3a 1l2",
    "addr:street":"200 St",
    "iso:country":"CA",
    "sg:address":"4307 200 St",
    "sg:city":"Langley",
    "sg:classifiers":[
        {
            "category":"Arts & Performance",
            "subcategory":"Theater",
            "type":"Entertainment"
        }
    ],
    "sg:phone":"+1 604 534 7469",
    "sg:postcode":"V3A 1L2",
    "sg:province":"BC",
    "wof:name":"Langley Players Drama Club",
    "wof:placetype":"venue"
},
  "geometry": {"coordinates":[-122.669433594,49.0803451538],"type":"Point"}
}