{
  "type": "Feature",
  "properties": {
    "addr:full":"5111 New St Burlington ON L7L 1V2",
    "addr:housenumber":"5111",
    "addr:postcode":"l7l 1v2",
    "addr:street":"New St",
    "iso:country":"CA",
    "sg:address":"5111 New St",
    "sg:city":"Burlington",
    "sg:classifiers":[
        {
            "category":"Shopping",
            "subcategory":"Pharmacy",
            "type":"Retail Goods"
        }
    ],
    "sg:phone":"+1 905 637 2331",
    "sg:postcode":"L7L 1V2",
    "sg:province":"ON",
    "sg:tags":[
        "cosmetic",
        "perfume"
    ],
    "wof:name":"Pharma Plus Drugmart",
    "wof:placetype":"venue"
},
  "geometry": {"coordinates":[-79.751724,43.36911],"type":"Point"}
}