{
  "type": "Feature",
  "properties": {
    "addr:full":"2817 Riverside Dr Ottawa ON K1V 8N4",
    "addr:housenumber":"2817",
    "addr:postcode":"k1v 8n4",
    "addr:street":"Riverside Dr",
    "iso:country":"CA",
    "sg:address":"2817 Riverside Dr",
    "sg:city":"Ottawa",
    "sg:classifiers":[
        {
            "category":"Shopping",
            "subcategory":"Computers & Home Electronics",
            "type":"Retail Goods"
        }
    ],
    "sg:phone":"+1 613 733 6868",
    "sg:postcode":"K1V 8N4",
    "sg:province":"ON",
    "sg:tags":[
        "equipment",
        "dealer",
        "internet"
    ],
    "wof:name":"Global Mart Intl",
    "wof:placetype":"venue"
},
  "geometry": {"coordinates":[-75.69046,45.371811],"type":"Point"}
}