{
  "type": "Feature",
  "properties": {
    "addr:full":"5001 Aut Transcanadienne Pointe-Claire QC H9R 1B8",
    "addr:postcode":"5001;h9r 1b8",
    "addr:street":"Transcanadienne",
    "iso:country":"CA",
    "sg:address":"5001 Aut Transcanadienne",
    "sg:city":"Pointe-Claire",
    "sg:classifiers":[
        {
            "category":"Wholesale",
            "subcategory":"Machinery & Supplies",
            "type":"Manufacturing & Wholesale Goods"
        }
    ],
    "sg:phone":"+1 514 426 1024",
    "sg:postcode":"H9R 1B8",
    "sg:province":"QC",
    "sg:tags":[
        "agency",
        "rental",
        "contractor"
    ],
    "wof:name":"Hewitt Equipement Ltee",
    "wof:placetype":"venue"
},
  "geometry": {"coordinates":[-73.838219,45.457832],"type":"Point"}
}