{
  "type": "Feature",
  "properties": {
    "iso:country":"CA",
    "sg:address":"8732 61 Ave NW",
    "sg:city":"Edmonton",
    "sg:classifiers":[
        {
            "category":"Professional",
            "subcategory":"Business Services",
            "type":"Services"
        }
    ],
    "sg:phone":"+1 780 469 7890",
    "sg:postcode":"T6E 5P6",
    "sg:province":"AB",
    "sg:tags":[
        "paper",
        "lamination"
    ],
    "wof:name":"Custom Laminating Svc",
    "wof:placetype":"venue"
},
  "geometry": {"coordinates":[-113.458992,53.497005],"type":"Point"}
}