{
  "type": "Feature",
  "properties": {
    "addr:full":"Saskatoon SK S7H 5J6",
    "addr:postcode":"s7h 5j6",
    "iso:country":"CA",
    "sg:city":"Saskatoon",
    "sg:classifiers":[
        {
            "category":"Retail",
            "subcategory":"Veterinary Services",
            "type":"Services"
        }
    ],
    "sg:phone":"+1 306 373 3500",
    "sg:postcode":"S7H 5J6",
    "sg:province":"SK",
    "sg:tags":[
        "veterinarian"
    ],
    "wof:name":"Chotowetz, T DVM",
    "wof:placetype":"venue"
},
  "geometry": {"coordinates":[-106.63481903100001,52.1150779724],"type":"Point"}
}