{
  "type": "Feature",
  "properties": {
    "addr:full":"14 Poplar Dr Richmond Hill ON L4E 2X6",
    "addr:housenumber":"14",
    "addr:postcode":"l4e 2x6",
    "addr:street":"Poplar Dr",
    "iso:country":"CA",
    "sg:address":"14 Poplar Dr",
    "sg:city":"Richmond Hill",
    "sg:classifiers":[
        {
            "category":"Building & Trades",
            "subcategory":"Landscaping Services",
            "type":"Services"
        }
    ],
    "sg:phone":"+1 905 773 1598",
    "sg:postcode":"L4E 2X6",
    "sg:province":"ON",
    "sg:tags":[
        "landscape",
        "contractor"
    ],
    "wof:name":"Magic Garden CO",
    "wof:placetype":"venue"
},
  "geometry": {"coordinates":[-79.46674299999999,43.944187],"type":"Point"}
}