{
  "type": "Feature",
  "properties": {
    "addr:full":"2945 Colonial Rd Sarsfield ON K0A 3E0",
    "addr:housenumber":"2945",
    "addr:postcode":"k0a 3e0",
    "addr:street":"Colonial Rd",
    "iso:country":"CA",
    "sg:address":"2945 Colonial Rd",
    "sg:city":"Sarsfield",
    "sg:classifiers":[
        {
            "category":"Banks & Credit Unions",
            "subcategory":"Bank",
            "type":"Services"
        }
    ],
    "sg:phone":"+1 613 835 2191",
    "sg:postcode":"K0A 3E0",
    "sg:province":"ON",
    "wof:name":"Caisse Populaire DE Sarsfield",
    "wof:placetype":"venue"
},
  "geometry": {"coordinates":[-75.34317799999999,45.442093],"type":"Point"}
}