{
  "type": "Feature",
  "properties": {
    "addr:full":"1391 101st St North Battleford SK S9A 0Z9",
    "addr:housenumber":"1391",
    "addr:postcode":"s9a 0z9",
    "addr:street":"101St St",
    "iso:country":"CA",
    "sg:address":"1391 101st St",
    "sg:city":"North Battleford",
    "sg:classifiers":[
        {
            "category":"Professional",
            "subcategory":"Lawyer & Legal Services",
            "type":"Services"
        }
    ],
    "sg:phone":"+1 306 445 4436",
    "sg:postcode":"S9A 0Z9",
    "sg:province":"SK",
    "sg:tags":[
        "attorney"
    ],
    "wof:name":"Greenwood, Murray E",
    "wof:placetype":"venue"
},
  "geometry": {"coordinates":[-108.29776,52.777794],"type":"Point"}
}