{
  "type": "Feature",
  "properties": {
    "addr:full":"Mount Elgin ON N0J 1N0",
    "addr:postcode":"n0j 1n0",
    "iso:country":"CA",
    "sg:city":"Mount Elgin",
    "sg:classifiers":[
        {
            "category":"Wholesale",
            "subcategory":"Farm Supplies",
            "type":"Manufacturing & Wholesale Goods"
        }
    ],
    "sg:phone":"+1 519 485 1523",
    "sg:postcode":"N0J 1N0",
    "sg:province":"ON",
    "sg:tags":[
        "livestock"
    ],
    "wof:name":"Mount Elgin Pork Assembly Yard",
    "wof:placetype":"venue"
},
  "geometry": {"coordinates":[-76.2204284668,44.6089019775],"type":"Point"}
}