{
  "type": "Feature",
  "properties": {
    "addr:full":"787 Trunk Rd Sault Ste Marie ON P6A 3T3",
    "addr:housenumber":"787",
    "addr:postcode":"p6a 3t3",
    "addr:street":"Trunk Rd",
    "iso:country":"CA",
    "sg:address":"787 Trunk Rd",
    "sg:city":"Sault Ste Marie",
    "sg:classifiers":[
        {
            "category":"Retail",
            "subcategory":"Veterinary Services",
            "type":"Services"
        }
    ],
    "sg:phone":"+1 705 759 4555",
    "sg:postcode":"P6A 3T3",
    "sg:province":"ON",
    "sg:tags":[
        "veterinarian"
    ],
    "wof:name":"Animal Health Clinic",
    "wof:placetype":"venue"
},
  "geometry": {"coordinates":[-84.26720400000001,46.524597],"type":"Point"}
}