{
  "type": "Feature",
  "properties": {
    "iso:country":"CA",
    "sg:address":"787 Trunk Rd",
    "sg:city":"Sault Ste Marie",
    "sg:classifiers":[
        {
            "category":"Retail",
            "subcategory":"Veterinary Services",
            "type":"Services"
        }
    ],
    "sg:phone":"+1 705 759 4555",
    "sg:postcode":"P6A 3T3",
    "sg:province":"ON",
    "sg:tags":[
        "veterinarian"
    ],
    "wof:name":"Animal Health Clinic",
    "wof:placetype":"venue"
},
  "geometry": {"coordinates":[-84.267204,46.524597],"type":"Point"}
}