{
  "type": "Feature",
  "properties": {
    "addr:full":"17720 100 Ave NW Edmonton AB T5S 1S9",
    "addr:housenumber":"17720",
    "addr:postcode":"t5s 1s9",
    "addr:street":"100 Ave Nw",
    "iso:country":"CA",
    "sg:address":"17720 100 Ave NW",
    "sg:city":"Edmonton",
    "sg:classifiers":[
        {
            "category":"Restaurant",
            "type":"Food & Drink"
        }
    ],
    "sg:phone":"+1 780 414 8395",
    "sg:postcode":"T5S 1S9",
    "sg:province":"AB",
    "wof:name":"Mc Donald's",
    "wof:placetype":"venue"
},
  "geometry": {"coordinates":[-113.625198,53.538136],"type":"Point"}
}