{
  "type": "Feature",
  "properties": {
    "addr:full":"4555 Dunbar St Vancouver BC V6S 2G7",
    "addr:housenumber":"4555",
    "addr:postcode":"v6s 2g7",
    "addr:street":"Dunbar St",
    "iso:country":"CA",
    "sg:address":"4555 Dunbar St",
    "sg:city":"Vancouver",
    "sg:classifiers":[
        {
            "category":"Cinema",
            "subcategory":"Movie Theater",
            "type":"Entertainment"
        }
    ],
    "sg:phone":"+1 604 222 2991",
    "sg:postcode":"V6S 2G7",
    "sg:province":"BC",
    "wof:name":"First Run Theatre",
    "wof:placetype":"venue"
},
  "geometry": {"coordinates":[-123.185440063,49.2456741333],"type":"Point"}
}