{
  "type": "Feature",
  "properties": {
    "iso:country":"CA",
    "sg:address":"2648 Don St",
    "sg:city":"Ottawa",
    "sg:classifiers":[
        {
            "category":"Taxi",
            "type":"Transportation"
        }
    ],
    "sg:phone":"+1 613 248 3558",
    "sg:postcode":"K2B 6Y3",
    "sg:province":"ON",
    "sg:tags":[
        "taxicab",
        "limousine"
    ],
    "wof:name":"Executive Cabs",
    "wof:placetype":"venue"
},
  "geometry": {"coordinates":[-75.791916,45.364628],"type":"Point"}
}