{
  "type": "Feature",
  "properties": {
    "addr:full":"2648 Don St Ottawa ON K2B 6Y3",
    "addr:housenumber":"2648",
    "addr:postcode":"k2b 6y3",
    "addr:street":"Don St",
    "iso:country":"CA",
    "sg:address":"2648 Don St",
    "sg:city":"Ottawa",
    "sg:classifiers":[
        {
            "category":"Taxi",
            "type":"Transportation"
        }
    ],
    "sg:phone":"+1 613 248 3558",
    "sg:postcode":"K2B 6Y3",
    "sg:province":"ON",
    "sg:tags":[
        "taxicab",
        "limousine"
    ],
    "wof:name":"Executive Cabs",
    "wof:placetype":"venue"
},
  "geometry": {"coordinates":[-75.791916,45.364628],"type":"Point"}
}