{
  "type": "Feature",
  "properties": {
    "addr:full":"5331 Nauvoo Rd Watford ON N0M 2S0",
    "addr:housenumber":"5331",
    "addr:postcode":"n0m 2s0",
    "addr:street":"Nauvoo Rd",
    "iso:country":"CA",
    "sg:address":"5331 Nauvoo Rd",
    "sg:city":"Watford",
    "sg:classifiers":[
        {
            "category":"Organizations",
            "subcategory":"Religious Organization",
            "type":"Services"
        }
    ],
    "sg:phone":"+1 519 876 3824",
    "sg:postcode":"N0M 2S0",
    "sg:province":"ON",
    "sg:tags":[
        "church"
    ],
    "wof:name":"Trinity Anglican Church",
    "wof:placetype":"venue"
},
  "geometry": {"coordinates":[-81.8801116943,42.9500846863],"type":"Point"}
}