{
  "type": "Feature",
  "properties": {
    "addr:full":"311 Brock St N Whitby ON L1N 4H8",
    "addr:housenumber":"311",
    "addr:postcode":"l1n 4h8",
    "addr:street":"Brock St N",
    "iso:country":"CA",
    "sg:address":"311 Brock St N",
    "sg:city":"Whitby",
    "sg:classifiers":[
        {
            "category":"Shopping",
            "subcategory":"Used Merchandise",
            "type":"Retail Goods"
        }
    ],
    "sg:phone":"+1 905 666 0868",
    "sg:postcode":"L1N 4H8",
    "sg:province":"ON",
    "sg:tags":[
        "second",
        "store",
        "hand"
    ],
    "wof:name":"Salvation Army Thrift Store",
    "wof:placetype":"venue"
},
  "geometry": {"coordinates":[-78.943268,43.883163],"type":"Point"}
}