{
  "type": "Feature",
  "properties": {
    "iso:country":"CA",
    "sg:address":"105 George St",
    "sg:city":"Brantford",
    "sg:classifiers":[
        {
            "category":"Insurance",
            "subcategory":"Insurance Agent",
            "type":"Services"
        }
    ],
    "sg:phone":"+1 519 752 3155",
    "sg:postcode":"N3T 2Y5",
    "sg:province":"ON",
    "sg:tags":[
        "consultant",
        "planning",
        "financial"
    ],
    "wof:name":"Assante Capital Management Ltd",
    "wof:placetype":"venue"
},
  "geometry": {"coordinates":[-80.2625961304,43.1424674988],"type":"Point"}
}