{
  "type": "Feature",
  "properties": {
    "addr:full":"130 Oakland Ave London ON N5W 4H6",
    "addr:housenumber":"130",
    "addr:postcode":"n5w 4h6",
    "addr:street":"Oakland Ave",
    "iso:country":"CA",
    "sg:address":"130 Oakland Ave",
    "sg:city":"London",
    "sg:classifiers":[
        {
            "category":"Professional",
            "subcategory":"Computer Services",
            "type":"Services"
        }
    ],
    "sg:phone":"+1 519 453 8806",
    "sg:postcode":"N5W 4H6",
    "sg:province":"ON",
    "wof:name":"Newell Networking Svc",
    "wof:placetype":"venue"
},
  "geometry": {"coordinates":[-81.20160675050001,42.9864006042],"type":"Point"}
}