{
  "type": "Feature",
  "properties": {
    "addr:full":"Sussex NB E4E 7H5",
    "addr:postcode":"e4e 7h5",
    "iso:country":"CA",
    "sg:city":"Sussex",
    "sg:classifiers":[
        {
            "category":"Restaurant",
            "type":"Food & Drink"
        }
    ],
    "sg:phone":"+1 506 433 3334",
    "sg:postcode":"E4E 7H5",
    "sg:province":"NB",
    "sg:tags":[
        "pizza"
    ],
    "wof:name":"Sussex Pizza Stop",
    "wof:placetype":"venue"
},
  "geometry": {"coordinates":[-65.50741600000001,45.723022],"type":"Point"}
}