{
  "type": "Feature",
  "properties": {
    "addr:full":"145 4th Ave W Cardston AB T0K 0K0",
    "addr:housenumber":"145",
    "addr:postcode":"t0k 0k0",
    "addr:street":"4Th Ave W Cardston",
    "iso:country":"CA",
    "sg:address":"145 4th Ave W",
    "sg:city":"Cardston",
    "sg:classifiers":[
        {
            "category":"Education",
            "subcategory":"School",
            "type":"Public Place"
        }
    ],
    "sg:phone":"+1 403 653 4951",
    "sg:postcode":"T0K 0K0",
    "sg:province":"AB",
    "wof:name":"Cardston High School",
    "wof:placetype":"venue"
},
  "geometry": {"coordinates":[-113.306686,49.197079],"type":"Point"}
}