{
  "type": "Feature",
  "properties": {
    "addr:full":"2515 Boul Le Corbusier Laval QC H7S 1Z4",
    "addr:housenumber":"2515",
    "addr:postcode":"h7s 1z4",
    "addr:street":"Boul Le Corbusier",
    "iso:country":"CA",
    "sg:address":"2515 Boul Le Corbusier",
    "sg:city":"Laval",
    "sg:classifiers":[
        {
            "category":"Restaurant",
            "type":"Food & Drink"
        }
    ],
    "sg:phone":"+1 450 688 5515",
    "sg:postcode":"H7S 1Z4",
    "sg:province":"QC",
    "wof:name":"Restaurant LA Mazzanina",
    "wof:placetype":"venue"
},
  "geometry": {"coordinates":[-73.742332,45.574654],"type":"Point"}
}