{
  "type": "Feature",
  "properties": {
    "iso:country":"CA",
    "sg:address":"623 20th Ave E",
    "sg:city":"Vancouver",
    "sg:classifiers":[
        {
            "category":"Building & Trades",
            "subcategory":"Electrical",
            "type":"Services"
        }
    ],
    "sg:phone":"+1 604 879 9394",
    "sg:postcode":"V5V 1M9",
    "sg:province":"BC",
    "sg:tags":[
        "electric",
        "contractor"
    ],
    "wof:name":"Perma Electric Ltd",
    "wof:placetype":"venue"
},
  "geometry": {"coordinates":[-123.091301,49.25301],"type":"Point"}
}