{
  "type": "Feature",
  "properties": {
    "addr:full":"106 Church Holstein ON N0G 2A0",
    "addr:housenumber":"106",
    "addr:postcode":"n0g 2a0",
    "addr:street":"Church Holstein",
    "iso:country":"CA",
    "sg:address":"106 Church",
    "sg:city":"Holstein",
    "sg:classifiers":[
        {
            "category":"Manufacturing",
            "subcategory":"Tools & Machinery",
            "type":"Manufacturing & Wholesale Goods"
        }
    ],
    "sg:phone":"+1 519 334 3464",
    "sg:postcode":"N0G 2A0",
    "sg:province":"ON",
    "sg:tags":[
        "machine",
        "shop"
    ],
    "wof:name":"Caudle Tool & Die",
    "wof:placetype":"venue"
},
  "geometry": {"coordinates":[-80.76067399999999,44.061241],"type":"Point"}
}