{
  "type": "Feature",
  "properties": {
    "addr:full":"15 Queen St Lakefield ON K0L 2H0",
    "addr:housenumber":"15",
    "addr:postcode":"k0l 2h0",
    "addr:street":"Queen St",
    "iso:country":"CA",
    "sg:address":"15 Queen St",
    "sg:city":"Lakefield",
    "sg:classifiers":[
        {
            "category":"Shopping",
            "subcategory":"Clothing, Apparel, & Fashions",
            "type":"Retail Goods"
        }
    ],
    "sg:phone":"+1 705 652 3891",
    "sg:postcode":"K0L 2H0",
    "sg:province":"ON",
    "wof:name":"Treasure Chest",
    "wof:placetype":"venue"
},
  "geometry": {"coordinates":[-78.2720413208,44.4225006104],"type":"Point"}
}