{
  "type": "Feature",
  "properties": {
    "iso:country":"CA",
    "sg:city":"Spruce Grove",
    "sg:classifiers":[
        {
            "category":"Retail",
            "subcategory":"Auto Repair",
            "type":"Services"
        }
    ],
    "sg:phone":"+1 780 962 1972",
    "sg:postcode":"T7X 4G2",
    "sg:province":"AB",
    "sg:tags":[
        "repairing",
        "automobile"
    ],
    "wof:name":"Fastlane Customs",
    "wof:placetype":"venue"
},
  "geometry": {"coordinates":[-113.905326843,53.5390930176],"type":"Point"}
}