{
  "type": "Feature",
  "properties": {
    "addr:full":"500 George St Sydney NS B1P 1K6",
    "addr:housenumber":"500",
    "addr:postcode":"b1p 1k6",
    "addr:street":"George St",
    "iso:country":"CA",
    "sg:address":"500 George St",
    "sg:city":"Sydney",
    "sg:classifiers":[
        {
            "category":"Government",
            "subcategory":"Office",
            "type":"Public Place"
        }
    ],
    "sg:phone":"+1 902 563 2280",
    "sg:postcode":"B1P 1K6",
    "sg:province":"NS",
    "wof:name":"N S Land Registration & Info",
    "wof:placetype":"venue"
},
  "geometry": {"coordinates":[-60.1923141479,46.1371078491],"type":"Point"}
}