{
  "type": "Feature",
  "properties": {
    "addr:full":"840 Yonge St Toronto ON M4W 2H1",
    "addr:housenumber":"840",
    "addr:postcode":"m4w 2h1",
    "addr:street":"Yonge St",
    "iso:country":"CA",
    "sg:address":"840 Yonge St",
    "sg:city":"Toronto",
    "sg:classifiers":[
        {
            "category":"Home & Garden",
            "subcategory":"Home Furnishings",
            "type":"Retail Goods"
        }
    ],
    "sg:phone":"+1 416 927 9925",
    "sg:postcode":"M4W 2H1",
    "sg:province":"ON",
    "sg:tags":[
        "utensil",
        "cooking",
        "kitchen",
        "accessory"
    ],
    "wof:name":"Kitchen & Glass Place",
    "wof:placetype":"venue"
},
  "geometry": {"coordinates":[-79.387512207,43.6715507507],"type":"Point"}
}