{
  "type": "Feature",
  "properties": {
    "addr:full":"Elliot Lake ON P5A 2M1",
    "addr:postcode":"p5a 2m1",
    "iso:country":"CA",
    "sg:city":"Elliot Lake",
    "sg:classifiers":[
        {
            "category":"Retail",
            "subcategory":"Repair Shop",
            "type":"Services"
        }
    ],
    "sg:phone":"+1 705 848 6412",
    "sg:postcode":"P5A 2M1",
    "sg:province":"ON",
    "sg:tags":[
        "lock",
        "locksmith"
    ],
    "wof:name":"Al the Locksmith",
    "wof:placetype":"venue"
},
  "geometry": {"coordinates":[-82.66580963129999,46.3769798279],"type":"Point"}
}