{
  "type": "Feature",
  "properties": {
    "addr:full":"2860 Ch Sainte-Foy Sainte-Foy QC G1V 1W2",
    "addr:postcode":"2860;g1v 1w2",
    "addr:street":"Ch Sainte-Foy",
    "iso:country":"CA",
    "sg:address":"2860 Ch Sainte-Foy",
    "sg:city":"Sainte-Foy",
    "sg:classifiers":[
        {
            "category":"Food & Beverages",
            "subcategory":"Groceries & Convenience Stores",
            "type":"Retail Goods"
        }
    ],
    "sg:phone":"+1 418 651 1963",
    "sg:postcode":"G1V 1W2",
    "sg:province":"QC",
    "sg:tags":[
        "grocer"
    ],
    "wof:name":"Alimentation Bourbeau Enr",
    "wof:placetype":"venue"
},
  "geometry": {"coordinates":[-71.291763,46.769211],"type":"Point"}
}