{
  "type": "Feature",
  "properties": {
    "iso:country":"CA",
    "sg:city":"Maple Ridge",
    "sg:classifiers":[
        {
            "category":"Shopping",
            "subcategory":"Clothing, Apparel, & Fashions",
            "type":"Retail Goods"
        }
    ],
    "sg:phone":"+1 604 463 7397",
    "sg:postcode":"V2X 2V5",
    "sg:province":"BC",
    "sg:tags":[
        "accessory"
    ],
    "wof:name":"Prime Collection",
    "wof:placetype":"venue"
},
  "geometry": {"coordinates":[-122.593353,49.217049],"type":"Point"}
}