{
  "type": "Feature",
  "properties": {
    "addr:full":"1144 Main St Dartmouth NS B2Z 1A8",
    "addr:housenumber":"1144",
    "addr:postcode":"b2z 1a8",
    "addr:street":"Main St",
    "iso:country":"CA",
    "sg:address":"1144 Main St",
    "sg:city":"Dartmouth",
    "sg:classifiers":[
        {
            "category":"Professional",
            "subcategory":"Management & Consulting",
            "type":"Services"
        }
    ],
    "sg:phone":"+1 902 435 4648",
    "sg:postcode":"B2Z 1A8",
    "sg:province":"NS",
    "sg:tags":[
        "development",
        "economic",
        "agency"
    ],
    "wof:name":"Watershed Association Dev Ltd",
    "wof:placetype":"venue"
},
  "geometry": {"coordinates":[-63.47163,44.702595],"type":"Point"}
}