{
  "type": "Feature",
  "properties": {
    "addr:full":"1481 Rue Sainte-Catherine E Montreal QC H2L 2H9",
    "addr:housenumber":"1481",
    "addr:postcode":"h2l 2h9",
    "addr:street":"Rue Sainte-Catherine E",
    "iso:country":"CA",
    "sg:address":"1481 Rue Sainte-Catherine E",
    "sg:city":"Montreal",
    "sg:classifiers":[
        {
            "category":"Banks & Credit Unions",
            "subcategory":"Bank",
            "type":"Services"
        }
    ],
    "sg:phone":"+1 514 522 2211",
    "sg:postcode":"H2L 2H9",
    "sg:province":"QC",
    "sg:tags":[
        "cashing",
        "check"
    ],
    "wof:name":"Insta-Cheques",
    "wof:placetype":"venue"
},
  "geometry": {"coordinates":[-73.5539474487,45.5209236145],"type":"Point"}
}