{
  "type": "Feature",
  "properties": {
    "addr:full":"1133 Hastings St E Vancouver BC V6A 1S3",
    "addr:housenumber":"1133",
    "addr:postcode":"v6a 1s3",
    "addr:street":"Hastings St E",
    "iso:country":"CA",
    "sg:address":"1133 Hastings St E",
    "sg:city":"Vancouver",
    "sg:classifiers":[
        {
            "category":"Wholesale",
            "subcategory":"Non-durable Goods",
            "type":"Manufacturing & Wholesale Goods"
        }
    ],
    "sg:phone":"+1 604 255 6949",
    "sg:postcode":"V6A 1S3",
    "sg:province":"BC",
    "sg:tags":[
        "souvenir"
    ],
    "wof:name":"Northwest Trading Ltd",
    "wof:placetype":"venue"
},
  "geometry": {"coordinates":[-123.08049011200001,49.2811965942],"type":"Point"}
}