{
  "type": "Feature",
  "properties": {
    "addr:full":"3268 Broadway W Vancouver BC V6K 2H4",
    "addr:housenumber":"3268",
    "addr:postcode":"v6k 2h4",
    "addr:street":"Broadway W",
    "iso:country":"CA",
    "sg:address":"3268 Broadway W",
    "sg:city":"Vancouver",
    "sg:classifiers":[
        {
            "category":"Personal",
            "subcategory":"Beauty Salon",
            "type":"Services"
        }
    ],
    "sg:phone":"+1 604 731 2510",
    "sg:postcode":"V6K 2H4",
    "sg:province":"BC",
    "wof:name":"Seville Unisex",
    "wof:placetype":"venue"
},
  "geometry": {"coordinates":[-123.177032,49.264065],"type":"Point"}
}