{
  "type": "Feature",
  "properties": {
    "addr:full":"5217 Av Des Generations Charny QC G6X 2G6",
    "addr:housenumber":"5217",
    "addr:postcode":"g6x 2g6",
    "addr:street":"Av Des Generations",
    "iso:country":"CA",
    "sg:address":"5217 Av Des Generations",
    "sg:city":"Charny",
    "sg:classifiers":[
        {
            "category":"Manufacturing",
            "subcategory":"Printing",
            "type":"Manufacturing & Wholesale Goods"
        }
    ],
    "sg:phone":"+1 418 832 8300",
    "sg:postcode":"G6X 2G6",
    "sg:province":"QC",
    "sg:tags":[
        "printer"
    ],
    "wof:name":"Imprimerie Des Chutes Enr",
    "wof:placetype":"venue"
},
  "geometry": {"coordinates":[-71.2636795044,46.7151374817],"type":"Point"}
}