{
  "type": "Feature",
  "properties": {
    "addr:full":"2353 Rue Saint-Dominique Jonquiere QC G7X 6L9",
    "addr:housenumber":"2353",
    "addr:postcode":"g7x 6l9",
    "addr:street":"Rue Saint-Dominique",
    "iso:country":"CA",
    "sg:address":"2353 Rue Saint-Dominique",
    "sg:city":"Jonquiere",
    "sg:classifiers":[
        {
            "category":"Recreation",
            "type":"Entertainment"
        }
    ],
    "sg:phone":"+1 418 547 8894",
    "sg:postcode":"G7X 6L9",
    "sg:province":"QC",
    "sg:tags":[
        "martial",
        "arts",
        "instruction"
    ],
    "wof:name":"Club DE Karate Oyama",
    "wof:placetype":"venue"
},
  "geometry": {"coordinates":[-71.253525,48.414143],"type":"Point"}
}