{
  "type": "Feature",
  "properties": {
    "addr:full":"56 Rte 132 E Sayabec QC G0J 3K0",
    "addr:housenumber":"56",
    "addr:postcode":"g0j 3k0",
    "addr:street":"Rte 132 E",
    "iso:country":"CA",
    "sg:address":"56 Rte 132 E",
    "sg:city":"Sayabec",
    "sg:classifiers":[
        {
            "category":"Autos & Motor Vehicles",
            "subcategory":"Auto Supplies",
            "type":"Retail Goods"
        }
    ],
    "sg:phone":"+1 418 536 3515",
    "sg:postcode":"G0J 3K0",
    "sg:province":"QC",
    "sg:tags":[
        "automobile",
        "parts"
    ],
    "wof:name":"Antoine Pelletier Auto Ctr Inc",
    "wof:placetype":"venue"
},
  "geometry": {"coordinates":[-67.6638183594,48.5655021667],"type":"Point"}
}