{
  "type": "Feature",
  "properties": {
    "addr:full":"278 Conception Bay Hwy Bay Roberts NL A0A 1G0",
    "addr:housenumber":"278",
    "addr:postcode":"a0a 1g0",
    "addr:street":"Conception Bay Hwy Bay",
    "iso:country":"CA",
    "sg:address":"278 Conception Bay Hwy",
    "sg:city":"Bay Roberts",
    "sg:classifiers":[
        {
            "category":"Autos & Motor Vehicles",
            "subcategory":"Fuel & Gas Station",
            "type":"Retail Goods"
        }
    ],
    "sg:phone":"+1 709 786 7479",
    "sg:postcode":"A0A 1G0",
    "sg:province":"NL",
    "sg:tags":[
        "oil"
    ],
    "wof:name":"Bartlett's Irving",
    "wof:placetype":"venue"
},
  "geometry": {"coordinates":[-53.285278,47.574436],"type":"Point"}
}