{
  "type": "Feature",
  "properties": {
    "addr:full":"486 Rathgar Ave Winnipeg MB R3L 1G3",
    "addr:housenumber":"486",
    "addr:postcode":"r3l 1g3",
    "addr:street":"Rathgar Ave",
    "iso:country":"CA",
    "sg:address":"486 Rathgar Ave",
    "sg:city":"Winnipeg",
    "sg:classifiers":[
        {
            "category":"Education",
            "subcategory":"Dance Studio",
            "type":"Public Place"
        }
    ],
    "sg:phone":"+1 204 452 9417",
    "sg:postcode":"R3L 1G3",
    "sg:province":"MB",
    "sg:tags":[
        "instruction",
        "dancing"
    ],
    "wof:name":"Osborne Street Dance Club",
    "wof:placetype":"venue"
},
  "geometry": {"coordinates":[-97.1341629028,49.8613586426],"type":"Point"}
}