{
  "type": "Feature",
  "properties": {
    "addr:full":"1180 Henderson Hwy Winnipeg MB R2G 1L6",
    "addr:housenumber":"1180",
    "addr:postcode":"r2g 1l6",
    "addr:street":"Henderson Hwy",
    "iso:country":"CA",
    "sg:address":"1180 Henderson Hwy",
    "sg:city":"Winnipeg",
    "sg:classifiers":[
        {
            "category":"Professional",
            "subcategory":"Computer Services",
            "type":"Services"
        }
    ],
    "sg:phone":"+1 204 339 5260",
    "sg:postcode":"R2G 1L6",
    "sg:province":"MB",
    "sg:tags":[
        "repair"
    ],
    "wof:name":"Edps Computing",
    "wof:placetype":"venue"
},
  "geometry": {"coordinates":[-97.091843,49.939411],"type":"Point"}
}