{
  "type": "Feature",
  "properties": {
    "iso:country":"CA",
    "sg:address":"5 Oblate St",
    "sg:city":"St Catharines",
    "sg:classifiers":[
        {
            "category":"Organizations",
            "subcategory":"Religious Organization",
            "type":"Services"
        }
    ],
    "sg:phone":"+1 905 937 4230",
    "sg:postcode":"L2M 5C5",
    "sg:province":"ON",
    "sg:tags":[
        "church"
    ],
    "wof:name":"Our Lady of Perpetual Help Ch",
    "wof:placetype":"venue"
},
  "geometry": {"coordinates":[-79.224106,43.178986],"type":"Point"}
}