{
  "type": "Feature",
  "properties": {
    "addr:full":"2100 Rue Ontario E Montreal QC H2K 1V5",
    "addr:housenumber":"2100",
    "addr:postcode":"h2k 1v5",
    "addr:street":"Rue Ontario E",
    "iso:country":"CA",
    "sg:address":"2100 Rue Ontario E",
    "sg:city":"Montreal",
    "sg:classifiers":[
        {
            "category":"Professional",
            "type":"Services"
        }
    ],
    "sg:phone":"+1 514 527 2226",
    "sg:postcode":"H2K 1V5",
    "sg:province":"QC",
    "sg:tags":[
        "equipment",
        "hydroponics",
        "supply"
    ],
    "wof:name":"Univert 4 Saisons",
    "wof:placetype":"venue"
},
  "geometry": {"coordinates":[-73.5572433472,45.5281028748],"type":"Point"}
}