{
  "type": "Feature",
  "properties": {
    "iso:country":"CA",
    "sg:address":"614 Humboldt St",
    "sg:city":"Victoria",
    "sg:classifiers":[
        {
            "category":"Government",
            "subcategory":"Office",
            "type":"Public Place"
        }
    ],
    "sg:phone":"+1 250 387 6485",
    "sg:postcode":"V8W 1A4",
    "sg:province":"BC",
    "wof:name":"BC Social Svc Ministry Comm",
    "wof:placetype":"venue"
},
  "geometry": {"coordinates":[-123.367744446,48.4227638245],"type":"Point"}
}