{
  "type": "Feature",
  "properties": {
    "addr:full":"276 Sunset Blvd Stouffville ON L4A 3R1",
    "addr:housenumber":"276",
    "addr:postcode":"l4a 3r1",
    "addr:street":"Sunset Blvd",
    "iso:country":"CA",
    "sg:address":"276 Sunset Blvd",
    "sg:city":"Stouffville",
    "sg:classifiers":[
        {
            "category":"Education",
            "subcategory":"School",
            "type":"Public Place"
        }
    ],
    "sg:phone":"+1 905 640 3552",
    "sg:postcode":"L4A 3R1",
    "sg:province":"ON",
    "wof:name":"Orchard Park Public School",
    "wof:placetype":"venue"
},
  "geometry": {"coordinates":[-79.254822,43.967525],"type":"Point"}
}