{
  "type": "Feature",
  "properties": {
    "addr:full":"156 Houlton Rd Woodstock NB E7M 1Z1",
    "addr:housenumber":"156",
    "addr:postcode":"e7m 1z1",
    "addr:street":"Houlton Rd",
    "iso:country":"CA",
    "sg:address":"156 Houlton Rd",
    "sg:city":"Woodstock",
    "sg:classifiers":[
        {
            "category":"Autos & Motor Vehicles",
            "subcategory":"Automobile Sales",
            "type":"Retail Goods"
        }
    ],
    "sg:phone":"+1 506 328 3318",
    "sg:postcode":"E7M 1Z1",
    "sg:province":"NB",
    "sg:tags":[
        "car",
        "dealer"
    ],
    "wof:name":"L G Wilson Motors Ltd",
    "wof:placetype":"venue"
},
  "geometry": {"coordinates":[-67.58670043950001,46.1446495056],"type":"Point"}
}