{
  "type": "Feature",
  "properties": {
    "iso:country":"CA",
    "sg:address":"203 Ch Du Roi",
    "sg:city":"L'Isle-Aux-Grues",
    "sg:classifiers":[
        {
            "category":"Food & Beverages",
            "subcategory":"Groceries & Convenience Stores",
            "type":"Retail Goods"
        }
    ],
    "sg:phone":"+1 418 248 2466",
    "sg:postcode":"G0R 1P0",
    "sg:province":"QC",
    "sg:tags":[
        "grocer"
    ],
    "wof:name":"Epicerie Michel Gagne",
    "wof:placetype":"venue"
},
  "geometry": {"coordinates":[-70.555015564,47.0566520691],"type":"Point"}
}