{
  "type": "Feature",
  "properties": {
    "addr:full":"3410 Semenyk Crt Mississauga ON L5C 4P8",
    "addr:housenumber":"3410",
    "addr:postcode":"l5c 4p8",
    "addr:street":"Semenyk Crt",
    "iso:country":"CA",
    "sg:address":"3410 Semenyk Crt",
    "sg:city":"Mississauga",
    "sg:classifiers":[
        {
            "category":"Manufacturing",
            "subcategory":"Printing",
            "type":"Manufacturing & Wholesale Goods"
        }
    ],
    "sg:phone":"+1 905 272 7200",
    "sg:postcode":"L5C 4P8",
    "sg:province":"ON",
    "sg:tags":[
        "multimedia"
    ],
    "wof:name":"Aim New Media Inc",
    "wof:placetype":"venue"
},
  "geometry": {"coordinates":[-79.652382,43.567772],"type":"Point"}
}