{
  "type": "Feature",
  "properties": {
    "addr:full":"210 Furry Creek Dr Furry Creek BC V0N 3Z2",
    "addr:housenumber":"210",
    "addr:postcode":"v0n 3z2",
    "addr:street":"Furry Creek Dr Furry",
    "iso:country":"CA",
    "sg:address":"210 Furry Creek Dr",
    "sg:city":"Furry Creek",
    "sg:classifiers":[
        {
            "category":"Insurance",
            "subcategory":"Insurance Agent",
            "type":"Services"
        }
    ],
    "sg:phone":"+1 604 896 1552",
    "sg:postcode":"V0N 3Z2",
    "sg:province":"BC",
    "wof:name":"Clarica Life Insurance CO",
    "wof:placetype":"venue"
},
  "geometry": {"coordinates":[-123.22496032700001,49.5745925903],"type":"Point"}
}