{
  "type": "Feature",
  "properties": {
    "iso:country":"CA",
    "sg:address":"849 Automall Dr",
    "sg:city":"North Vancouver",
    "sg:classifiers":[
        {
            "category":"Autos & Motor Vehicles",
            "subcategory":"Automobile Sales",
            "type":"Retail Goods"
        }
    ],
    "sg:phone":"+1 604 985 0591",
    "sg:postcode":"V7P 3R8",
    "sg:province":"BC",
    "sg:tags":[
        "car",
        "dealer"
    ],
    "wof:name":"Jim Pattison Toyota",
    "wof:placetype":"venue"
},
  "geometry": {"coordinates":[-123.096275,49.315773],"type":"Point"}
}