{
  "type": "Feature",
  "properties": {
    "addr:full":"194 Main St Unionville ON L3R 2G9",
    "addr:housenumber":"194",
    "addr:postcode":"l3r 2g9",
    "addr:street":"Main St",
    "iso:country":"CA",
    "sg:address":"194 Main St",
    "sg:city":"Unionville",
    "sg:classifiers":[
        {
            "category":"Restaurant",
            "type":"Food & Drink"
        }
    ],
    "sg:phone":"+1 905 479 3834",
    "sg:postcode":"L3R 2G9",
    "sg:province":"ON",
    "sg:tags":[
        "parlor",
        "ice",
        "cream"
    ],
    "wof:name":"Polar Bar",
    "wof:placetype":"venue"
},
  "geometry": {"coordinates":[-79.3123474121,43.8679924011],"type":"Point"}
}