{
  "type": "Feature",
  "properties": {
    "addr:full":"Vancouver BC V6H 3W1",
    "addr:postcode":"v6h 3w1",
    "iso:country":"CA",
    "sg:city":"Vancouver",
    "sg:classifiers":[
        {
            "category":"Real Estate",
            "subcategory":"Real Estate Agent",
            "type":"Services"
        }
    ],
    "sg:phone":"+1 604 731 7336",
    "sg:postcode":"V6H 3W1",
    "sg:province":"BC",
    "sg:tags":[
        "cooperative"
    ],
    "wof:name":"Twin Rainbows Housing CO-OP",
    "wof:placetype":"venue"
},
  "geometry": {"coordinates":[-123.113937378,49.2604484558],"type":"Point"}
}