{
  "type": "Feature",
  "properties": {
    "addr:full":"114 Rue Sicard Buckingham QC J8L 3E9",
    "addr:housenumber":"114",
    "addr:postcode":"j8l 3e9",
    "addr:street":"Rue Sicard",
    "iso:country":"CA",
    "sg:address":"114 Rue Sicard",
    "sg:city":"Buckingham",
    "sg:classifiers":[
        {
            "category":"Building & Trades",
            "subcategory":"Construction",
            "type":"Services"
        }
    ],
    "sg:phone":"+1 819 986 3898",
    "sg:postcode":"J8L 3E9",
    "sg:province":"QC",
    "sg:tags":[
        "general",
        "contractor"
    ],
    "wof:name":"Charlebois Arsene Constr Ltee",
    "wof:placetype":"venue"
},
  "geometry": {"coordinates":[-75.39250199999999,45.586323],"type":"Point"}
}