{
  "type": "Feature",
  "properties": {
    "addr:full":"255 Scott St Fort Frances ON P9A 1G8",
    "addr:housenumber":"255",
    "addr:postcode":"p9a 1g8",
    "addr:street":"Scott St",
    "iso:country":"CA",
    "sg:address":"255 Scott St",
    "sg:city":"Fort Frances",
    "sg:classifiers":[
        {
            "category":"Shopping",
            "subcategory":"Jewelry",
            "type":"Retail Goods"
        }
    ],
    "sg:phone":"+1 807 274 3934",
    "sg:postcode":"P9A 1G8",
    "sg:province":"ON",
    "sg:tags":[
        "jeweler"
    ],
    "wof:name":"Brockie's Jewellers",
    "wof:placetype":"venue"
},
  "geometry": {"coordinates":[-93.397003,48.609852],"type":"Point"}
}