{
  "type": "Feature",
  "properties": {
    "addr:full":"4175 222 Rte Saint-Denis-DE-Brompton QC J0B 2P0",
    "addr:housenumber":"4175",
    "addr:postcode":"j0b 2p0",
    "addr:street":"222 Rte Saint-Denis-De-Brompton",
    "iso:country":"CA",
    "sg:address":"4175 222 Rte",
    "sg:city":"Saint-Denis-DE-Brompton",
    "sg:classifiers":[
        {
            "category":"Wholesale",
            "subcategory":"Electrical",
            "type":"Manufacturing & Wholesale Goods"
        }
    ],
    "sg:phone":"+1 819 846 6032",
    "sg:postcode":"J0B 2P0",
    "sg:province":"QC",
    "sg:tags":[
        "generator"
    ],
    "wof:name":"Generatrices Bm Inc",
    "wof:placetype":"venue"
},
  "geometry": {"coordinates":[-72.08098602290001,45.4581336975],"type":"Point"}
}