{
  "type": "Feature",
  "properties": {
    "addr:full":"2 Hardy Ave Grand Falls-Windsor NL A2A 2P9",
    "addr:housenumber":"2",
    "addr:postcode":"a2a 2p9",
    "addr:street":"Hardy Ave",
    "iso:country":"CA",
    "sg:address":"2 Hardy Ave",
    "sg:city":"Grand Falls-Windsor",
    "sg:classifiers":[
        {
            "category":"Shopping",
            "subcategory":"Department Store",
            "type":"Retail Goods"
        }
    ],
    "sg:phone":"+1 709 489 5631",
    "sg:postcode":"A2A 2P9",
    "sg:province":"NL",
    "wof:name":"Riff's Limited",
    "wof:placetype":"venue"
},
  "geometry": {"coordinates":[-55.622589,48.953819],"type":"Point"}
}