{
  "type": "Feature",
  "properties": {
    "addr:full":"Calgary AB T2X 1M2",
    "addr:postcode":"t2x 1m2",
    "iso:country":"CA",
    "sg:city":"Calgary",
    "sg:classifiers":[
        {
            "category":"Shopping",
            "subcategory":"Computers & Home Electronics",
            "type":"Retail Goods"
        }
    ],
    "sg:phone":"+1 403 256 5699",
    "sg:postcode":"T2X 1M2",
    "sg:province":"AB",
    "sg:tags":[
        "software"
    ],
    "wof:name":"Ciphersoft Inc",
    "wof:placetype":"venue"
},
  "geometry": {"coordinates":[-114.06350707999999,50.9104995728],"type":"Point"}
}