{
  "type": "Feature",
  "properties": {
    "iso:country":"CA",
    "sg:address":"2735 Rue Jules-Vachon",
    "sg:city":"Trois-Rivieres",
    "sg:classifiers":[
        {
            "category":"Manufacturing",
            "subcategory":"Metals",
            "type":"Manufacturing & Wholesale Goods"
        }
    ],
    "sg:phone":"+1 819 691 4244",
    "sg:postcode":"G9A 5E1",
    "sg:province":"QC",
    "sg:tags":[
        "plating"
    ],
    "wof:name":"Cr3X Inc",
    "wof:placetype":"venue"
},
  "geometry": {"coordinates":[-72.656189,46.378529],"type":"Point"}
}