{
  "type": "Feature",
  "properties": {
    "addr:full":"5130 50 Ave Barrhead AB T7N 1L1",
    "addr:housenumber":"5130",
    "addr:postcode":"t7n 1l1",
    "addr:street":"50 Ave",
    "iso:country":"CA",
    "sg:address":"5130 50 Ave",
    "sg:city":"Barrhead",
    "sg:classifiers":[
        {
            "category":"Shopping",
            "subcategory":"Used Merchandise",
            "type":"Retail Goods"
        }
    ],
    "sg:phone":"+1 780 674 4041",
    "sg:postcode":"T7N 1L1",
    "sg:province":"AB",
    "sg:tags":[
        "clothing"
    ],
    "wof:name":"Blue Heron Support Svc Assn",
    "wof:placetype":"venue"
},
  "geometry": {"coordinates":[-114.406951904,54.1196746826],"type":"Point"}
}