{
  "type": "Feature",
  "properties": {
    "addr:full":"2080 Columbia Ave Rossland BC V0G 1Y0",
    "addr:housenumber":"2080",
    "addr:postcode":"v0g 1y0",
    "addr:street":"Columbia Ave",
    "iso:country":"CA",
    "sg:address":"2080 Columbia Ave",
    "sg:city":"Rossland",
    "sg:classifiers":[
        {
            "category":"Insurance",
            "subcategory":"Insurance Agent",
            "type":"Services"
        }
    ],
    "sg:phone":"+1 250 362 7337",
    "sg:postcode":"V0G 1Y0",
    "sg:province":"BC",
    "wof:name":"Curriers Insurance",
    "wof:placetype":"venue"
},
  "geometry": {"coordinates":[-117.798904419,49.0770454407],"type":"Point"}
}