{
  "type": "Feature",
  "properties": {
    "iso:country":"CA",
    "sg:address":"133 Regina Rd # 3",
    "sg:city":"Woodbridge",
    "sg:classifiers":[
        {
            "category":"Manufacturing",
            "subcategory":"Tools & Machinery",
            "type":"Manufacturing & Wholesale Goods"
        }
    ],
    "sg:phone":"+1 905 850 4652",
    "sg:postcode":"L4L 8L9",
    "sg:province":"ON",
    "sg:tags":[
        "die",
        "fixture",
        "maker",
        "jig"
    ],
    "wof:name":"J P Jig Boring Inc",
    "wof:placetype":"venue"
},
  "geometry": {"coordinates":[-79.611984,43.771439],"type":"Point"}
}