{
  "type": "Feature",
  "properties": {
    "addr:full":"Vancouver BC V6Z 2M3",
    "addr:postcode":"v6z 2m3",
    "iso:country":"CA",
    "sg:city":"Vancouver",
    "sg:classifiers":[
        {
            "category":"Personal",
            "subcategory":"Beauty Salon",
            "type":"Services"
        }
    ],
    "sg:phone":"+1 604 681 9595",
    "sg:postcode":"V6Z 2M3",
    "sg:province":"BC",
    "sg:tags":[
        "consultant",
        "health"
    ],
    "wof:name":"D C Skincare Clinic Inc",
    "wof:placetype":"venue"
},
  "geometry": {"coordinates":[-123.133736,49.274818],"type":"Point"}
}