{
  "type": "Feature",
  "properties": {
    "iso:country":"CA",
    "sg:address":"333 Grande Allee E",
    "sg:city":"Quebec",
    "sg:classifiers":[
        {
            "category":"Personal",
            "subcategory":"Beauty Salon",
            "type":"Services"
        }
    ],
    "sg:phone":"+1 418 522 3333",
    "sg:postcode":"G1R 2H8",
    "sg:province":"QC",
    "wof:name":"Institut St-Laurent",
    "wof:placetype":"venue"
},
  "geometry": {"coordinates":[-71.2202301025,46.8040237427],"type":"Point"}
}