{
  "type": "Feature",
  "properties": {
    "addr:full":"LA Pocatiere QC G0R 1Z0",
    "addr:postcode":"g0r 1z0",
    "iso:country":"CA",
    "sg:city":"LA Pocatiere",
    "sg:classifiers":[
        {
            "category":"Real Estate",
            "subcategory":"Real Estate Agent",
            "type":"Services"
        }
    ],
    "sg:phone":"+1 418 856 1352",
    "sg:postcode":"G0R 1Z0",
    "sg:province":"QC",
    "wof:name":"Immeubles Re/Max",
    "wof:placetype":"venue"
},
  "geometry": {"coordinates":[-70.3518066406,47.1060943604],"type":"Point"}
}