{
  "type": "Feature",
  "properties": {
    "iso:country":"CA",
    "sg:address":"331 Bayfield St",
    "sg:city":"Barrie",
    "sg:classifiers":[
        {
            "category":"Social Services",
            "type":"Services"
        }
    ],
    "sg:phone":"+1 705 721 7727",
    "sg:postcode":"L4M 3C2",
    "sg:province":"ON",
    "sg:tags":[
        "counselor",
        "marriage",
        "family"
    ],
    "wof:name":"Carter, Paula K",
    "wof:placetype":"venue"
},
  "geometry": {"coordinates":[-79.701195,44.402344],"type":"Point"}
}