{
  "type": "Feature",
  "properties": {
    "addr:full":"Coquitlam BC V3B 1B9",
    "addr:postcode":"v3b 1b9",
    "iso:country":"CA",
    "sg:city":"Coquitlam",
    "sg:classifiers":[
        {
            "category":"Retail",
            "subcategory":"Auto Repair",
            "type":"Services"
        }
    ],
    "sg:phone":"+1 604 464 2515",
    "sg:postcode":"V3B 1B9",
    "sg:province":"BC",
    "sg:tags":[
        "repairing",
        "automobile"
    ],
    "wof:name":"Speedy Auto Svc",
    "wof:placetype":"venue"
},
  "geometry": {"coordinates":[-122.803307,49.277267],"type":"Point"}
}