{
  "type": "Feature",
  "properties": {
    "addr:full":"3680 Rue DE LA Montagne Montreal QC H3G 2A8",
    "addr:housenumber":"3680",
    "addr:postcode":"h3g 2a8",
    "addr:street":"Rue De La Montagne",
    "iso:country":"CA",
    "sg:address":"3680 Rue DE LA Montagne",
    "sg:city":"Montreal",
    "sg:classifiers":[
        {
            "category":"Professional",
            "subcategory":"Business Services",
            "type":"Services"
        }
    ],
    "sg:phone":"+1 514 289 8614",
    "sg:postcode":"H3G 2A8",
    "sg:province":"QC",
    "sg:tags":[
        "arbitration"
    ],
    "wof:name":"Groupe Interlex Du Canada Inc",
    "wof:placetype":"venue"
},
  "geometry": {"coordinates":[-73.5828170776,45.5014762878],"type":"Point"}
}