{
  "type": "Feature",
  "properties": {
    "iso:country":"CA",
    "sg:address":"1691 Pender St E",
    "sg:city":"Vancouver",
    "sg:classifiers":[
        {
            "category":"Social Services",
            "subcategory":"Job Training",
            "type":"Services"
        }
    ],
    "sg:phone":"+1 604 215 4344",
    "sg:postcode":"V5L 1W2",
    "sg:province":"BC",
    "sg:tags":[
        "career",
        "counseling",
        "vocational"
    ],
    "wof:name":"Newstart",
    "wof:placetype":"venue"
},
  "geometry": {"coordinates":[-123.070755,49.280567],"type":"Point"}
}