{
  "type": "Feature",
  "properties": {
    "addr:full":"Burnaby BC V3N 4R7",
    "addr:postcode":"v3n 4r7",
    "iso:country":"CA",
    "sg:city":"Burnaby",
    "sg:classifiers":[
        {
            "category":"Health Services",
            "subcategory":"Doctor",
            "type":"Services"
        }
    ],
    "sg:phone":"+1 604 444 5155",
    "sg:postcode":"V3N 4R7",
    "sg:province":"BC",
    "sg:tags":[
        "dentist"
    ],
    "wof:name":"Four Seasons Dental Clinic",
    "wof:placetype":"venue"
},
  "geometry": {"coordinates":[-122.892814636,49.2442359924],"type":"Point"}
}