{
  "type": "Feature",
  "properties": {
    "addr:full":"55 Rue Ouimet Vaudreuil-Dorion QC J7V 8B7",
    "addr:housenumber":"55",
    "addr:postcode":"j7v 8b7",
    "addr:street":"Rue Ouimet",
    "iso:country":"CA",
    "sg:address":"55 Rue Ouimet",
    "sg:city":"Vaudreuil-Dorion",
    "sg:classifiers":[
        {
            "category":"Personal",
            "subcategory":"Beauty Salon",
            "type":"Services"
        }
    ],
    "sg:phone":"+1 450 424 3500",
    "sg:postcode":"J7V 8B7",
    "sg:province":"QC",
    "wof:name":"Salon L'Hote Coiffure",
    "wof:placetype":"venue"
},
  "geometry": {"coordinates":[-74.03601074220001,45.3958816528],"type":"Point"}
}