{
  "type": "Feature",
  "properties": {
    "addr:full":"765 Conc 3 Wheatley ON N0P 2P0",
    "addr:housenumber":"765;3",
    "addr:postcode":"n0p 2p0",
    "addr:street":"Conc",
    "iso:country":"CA",
    "sg:address":"765 Conc 3",
    "sg:city":"Wheatley",
    "sg:classifiers":[
        {
            "category":"Freight",
            "type":"Transportation"
        }
    ],
    "sg:phone":"+1 519 825 7441",
    "sg:postcode":"N0P 2P0",
    "sg:province":"ON",
    "sg:tags":[
        "warehouse",
        "storage"
    ],
    "wof:name":"Taylor Cold Storage Inc",
    "wof:placetype":"venue"
},
  "geometry": {"coordinates":[-82.444229126,42.1174812317],"type":"Point"}
}