{
  "type": "Feature",
  "properties": {
    "addr:full":"1 Rideau St Ottawa ON K1N 8S7",
    "addr:housenumber":"1",
    "addr:postcode":"k1n 8s7",
    "addr:street":"Rideau St",
    "iso:country":"CA",
    "sg:address":"1 Rideau St",
    "sg:city":"Ottawa",
    "sg:classifiers":[
        {
            "category":"Professional",
            "subcategory":"Secretarial Services",
            "type":"Services"
        }
    ],
    "sg:phone":"+1 613 562 0601",
    "sg:postcode":"K1N 8S7",
    "sg:province":"ON",
    "sg:tags":[
        "reporting",
        "court"
    ],
    "wof:name":"Anderson Group",
    "wof:placetype":"venue"
},
  "geometry": {"coordinates":[-75.692307,45.444412],"type":"Point"}
}