{
  "type": "Feature",
  "properties": {
    "addr:full":"92 Rue Des Pins Magog QC J1X 2H7",
    "addr:housenumber":"92",
    "addr:postcode":"j1x 2h7",
    "addr:street":"Rue Des Pins",
    "iso:country":"CA",
    "sg:address":"92 Rue Des Pins",
    "sg:city":"Magog",
    "sg:classifiers":[
        {
            "category":"Personal",
            "subcategory":"Tanning Parlor",
            "type":"Services"
        }
    ],
    "sg:phone":"+1 819 843 4110",
    "sg:postcode":"J1X 2H7",
    "sg:province":"QC",
    "sg:tags":[
        "salon"
    ],
    "wof:name":"Bronzage Etc",
    "wof:placetype":"venue"
},
  "geometry": {"coordinates":[-72.15271,45.267242],"type":"Point"}
}