{
  "type": "Feature",
  "properties": {
    "addr:full":"Yorkton SK S3N 4E7",
    "addr:postcode":"s3n 4e7",
    "iso:country":"CA",
    "sg:city":"Yorkton",
    "sg:classifiers":[
        {
            "category":"Taxi",
            "type":"Transportation"
        }
    ],
    "sg:phone":"+1 306 783 1010",
    "sg:postcode":"S3N 4E7",
    "sg:province":"SK",
    "sg:tags":[
        "taxicab"
    ],
    "wof:name":"Redline Taxi",
    "wof:placetype":"venue"
},
  "geometry": {"coordinates":[-102.457473755,51.2241592407],"type":"Point"}
}