{
  "type": "Feature",
  "properties": {
    "iso:country":"CA",
    "sg:address":"111 Ch Martin",
    "sg:city":"Sainte-Anne-DE-Madawaska",
    "sg:classifiers":[
        {
            "category":"Restaurant",
            "type":"Food & Drink"
        }
    ],
    "sg:phone":"+1 506 445 2242",
    "sg:postcode":"E7E 1G4",
    "sg:province":"NB",
    "sg:tags":[
        "grocer"
    ],
    "wof:name":"Y Ringuette Garage-Gas Bar",
    "wof:placetype":"venue"
},
  "geometry": {"coordinates":[-68.1537017822,47.6347541809],"type":"Point"}
}