{
  "type": "Feature",
  "properties": {
    "addr:full":"1330 Boul Roland-Therrien Longueuil QC J4J 4L8",
    "addr:housenumber":"1330",
    "addr:postcode":"j4j 4l8",
    "addr:street":"Boul Roland-Therrien",
    "iso:country":"CA",
    "sg:address":"1330 Boul Roland-Therrien",
    "sg:city":"Longueuil",
    "sg:classifiers":[
        {
            "category":"Personal",
            "type":"Services"
        }
    ],
    "sg:phone":"+1 450 928 1330",
    "sg:postcode":"J4J 4L8",
    "sg:province":"QC",
    "sg:tags":[
        "therapist",
        "massage"
    ],
    "wof:name":"Massotherapie Andree Royer",
    "wof:placetype":"venue"
},
  "geometry": {"coordinates":[-73.48111,45.538254],"type":"Point"}
}