{
  "type": "Feature",
  "properties": {
    "addr:full":"300 Commercial St Saltcoats SK S0A 3R0",
    "addr:housenumber":"300",
    "addr:postcode":"s0a 3r0",
    "addr:street":"Commercial St",
    "iso:country":"CA",
    "sg:address":"300 Commercial St",
    "sg:city":"Saltcoats",
    "sg:classifiers":[
        {
            "category":"Farming",
            "subcategory":"Farm & Veterinary Services",
            "type":"Manufacturing & Wholesale Goods"
        }
    ],
    "sg:phone":"+1 306 744 2998",
    "sg:postcode":"S0A 3R0",
    "sg:province":"SK",
    "sg:tags":[
        "insemination"
    ],
    "wof:name":"Mc Callum's Ai Svc",
    "wof:placetype":"venue"
},
  "geometry": {"coordinates":[-102.169204712,51.041229248],"type":"Point"}
}