{
  "type": "Feature",
  "properties": {
    "addr:full":"5555 Burrill St Shawinigan QC G9N 6W3",
    "addr:housenumber":"5555",
    "addr:postcode":"g9n 6w3",
    "addr:street":"Burrill St",
    "iso:country":"CA",
    "sg:address":"5555 Burrill St",
    "sg:city":"Shawinigan",
    "sg:classifiers":[
        {
            "category":"Wholesale",
            "subcategory":"Metals & Minerals",
            "type":"Manufacturing & Wholesale Goods"
        }
    ],
    "sg:phone":"+1 819 539 1250",
    "sg:postcode":"G9N 6W3",
    "sg:province":"QC",
    "sg:tags":[
        "fabricator",
        "aluminum"
    ],
    "wof:name":"Alcan Usine Saint-Maurice",
    "wof:placetype":"venue"
},
  "geometry": {"coordinates":[-72.78323399999999,46.572872],"type":"Point"}
}