{
  "type": "Feature",
  "properties": {
    "addr:full":"Montreal QC H3A 1B9",
    "addr:postcode":"h3a 1b9",
    "iso:country":"CA",
    "sg:city":"Montreal",
    "sg:classifiers":[
        {
            "category":"Health Services",
            "subcategory":"Clinic",
            "type":"Services"
        }
    ],
    "sg:phone":"+1 514 842 4801",
    "sg:postcode":"H3A 1B9",
    "sg:province":"QC",
    "sg:tags":[
        "aid",
        "first"
    ],
    "wof:name":"Ambulance Saint-Jean",
    "wof:placetype":"venue"
},
  "geometry": {"coordinates":[-73.56658899999999,45.518375],"type":"Point"}
}