{
  "type": "Feature",
  "properties": {
    "addr:full":"6852 Merritt Ave Burnaby BC V5J 4R6",
    "addr:housenumber":"6852",
    "addr:postcode":"v5j 4r6",
    "addr:street":"Merritt Ave",
    "iso:country":"CA",
    "sg:address":"6852 Merritt Ave",
    "sg:city":"Burnaby",
    "sg:classifiers":[
        {
            "category":"Professional",
            "subcategory":"Computer Services",
            "type":"Services"
        }
    ],
    "sg:phone":"+1 604 435 5259",
    "sg:postcode":"V5J 4R6",
    "sg:province":"BC",
    "sg:tags":[
        "repair"
    ],
    "wof:name":"Multitech Microsystems Ltd",
    "wof:placetype":"venue"
},
  "geometry": {"coordinates":[-122.980034,49.22134],"type":"Point"}
}