{
  "type": "Feature",
  "properties": {
    "addr:full":"Trout River NL A0K 5P0",
    "addr:postcode":"a0k 5p0",
    "iso:country":"CA",
    "sg:city":"Trout River",
    "sg:classifiers":[
        {
            "category":"Travel",
            "subcategory":"Hotels & Motels",
            "type":"Entertainment"
        }
    ],
    "sg:phone":"+1 709 451 3236",
    "sg:postcode":"A0K 5P0",
    "sg:province":"NL",
    "sg:tags":[
        "tourist",
        "accommodation"
    ],
    "wof:name":"Crocker Cabins",
    "wof:placetype":"venue"
},
  "geometry": {"coordinates":[-58.1267700195,49.4806594849],"type":"Point"}
}