{
  "type": "Feature",
  "properties": {
    "addr:full":"330 River Rd St Andrews MB R1A 2X2",
    "addr:housenumber":"330",
    "addr:postcode":"r1a 2x2",
    "addr:street":"River Rd",
    "iso:country":"CA",
    "sg:address":"330 River Rd",
    "sg:city":"St Andrews",
    "sg:classifiers":[
        {
            "category":"Building & Trades",
            "subcategory":"Construction",
            "type":"Services"
        }
    ],
    "sg:phone":"+1 204 338 1500",
    "sg:postcode":"R1A 2X2",
    "sg:province":"MB",
    "sg:tags":[
        "builder",
        "stair"
    ],
    "wof:name":"Spirals By Ron",
    "wof:placetype":"venue"
},
  "geometry": {"coordinates":[-97.026596,50.036961],"type":"Point"}
}