{
  "type": "Feature",
  "properties": {
    "addr:full":"PO Box 218 Ile-A-LA-Crosse SK S0M 1C0",
    "addr:housenumber":"po",
    "addr:postcode":"s0m 1c0",
    "addr:street":"Box 218",
    "iso:country":"CA",
    "sg:address":"PO Box 218",
    "sg:city":"Ile-A-LA-Crosse",
    "sg:classifiers":[
        {
            "category":"Organizations",
            "subcategory":"Professional Association",
            "type":"Services"
        }
    ],
    "sg:phone":"+1 306 833 2626",
    "sg:postcode":"S0M 1C0",
    "sg:province":"SK",
    "wof:name":"Preschool Program",
    "wof:placetype":"venue"
},
  "geometry": {"coordinates":[-107.906257629,55.4523468018],"type":"Point"}
}