{
  "type": "Feature",
  "properties": {
    "addr:full":"Edmonton AB T5N 1R2",
    "addr:postcode":"t5n 1r2",
    "iso:country":"CA",
    "sg:city":"Edmonton",
    "sg:classifiers":[
        {
            "category":"Government",
            "subcategory":"Office",
            "type":"Public Place"
        }
    ],
    "sg:phone":"+1 780 447 1177",
    "sg:postcode":"T5N 1R2",
    "sg:province":"AB",
    "sg:tags":[
        "federal",
        "affairs"
    ],
    "wof:name":"Consulate General of Bolivia",
    "wof:placetype":"venue"
},
  "geometry": {"coordinates":[-113.53613281200001,53.5449867249],"type":"Point"}
}