{
  "type": "Feature",
  "properties": {
    "addr:full":"643 6th St Courtenay BC V9N 1M7",
    "addr:housenumber":"643",
    "addr:postcode":"v9n 1m7",
    "addr:street":"6Th St",
    "iso:country":"CA",
    "sg:address":"643 6th St",
    "sg:city":"Courtenay",
    "sg:classifiers":[
        {
            "category":"Health Services",
            "subcategory":"Doctor",
            "type":"Services"
        }
    ],
    "sg:phone":"+1 250 334 4172",
    "sg:postcode":"V9N 1M7",
    "sg:province":"BC",
    "sg:tags":[
        "physician",
        "surgeon"
    ],
    "wof:name":"Jenkins, Donald MD",
    "wof:placetype":"venue"
},
  "geometry": {"coordinates":[-125.003822,49.688335],"type":"Point"}
}