{
  "type": "Feature",
  "properties": {
    "addr:full":"8600 100 St Fort St John BC V1J 3W8",
    "addr:housenumber":"8600",
    "addr:postcode":"v1j 3w8",
    "addr:street":"100 St",
    "iso:country":"CA",
    "sg:address":"8600 100 St",
    "sg:city":"Fort St John",
    "sg:classifiers":[
        {
            "category":"Wholesale",
            "subcategory":"Machinery & Supplies",
            "type":"Manufacturing & Wholesale Goods"
        }
    ],
    "sg:phone":"+1 250 785 8161",
    "sg:postcode":"V1J 3W8",
    "sg:province":"BC",
    "sg:tags":[
        "contractor"
    ],
    "wof:name":"Coneco Equipment Inc",
    "wof:placetype":"venue"
},
  "geometry": {"coordinates":[-120.847595215,56.2327613831],"type":"Point"}
}