{
  "type": "Feature",
  "properties": {
    "addr:full":"1399 Rue Du Mont-Plaisant Prevost QC J0R 1T0",
    "addr:housenumber":"1399",
    "addr:postcode":"j0r 1t0",
    "addr:street":"Rue Du Mont-Plaisant Prevost",
    "iso:country":"CA",
    "sg:address":"1399 Rue Du Mont-Plaisant",
    "sg:city":"Prevost",
    "sg:classifiers":[
        {
            "category":"Retail",
            "subcategory":"Animal Services",
            "type":"Services"
        }
    ],
    "sg:phone":"+1 450 224 7820",
    "sg:postcode":"J0R 1T0",
    "sg:province":"QC",
    "sg:tags":[
        "pet",
        "grooming",
        "washing"
    ],
    "wof:name":"Salon DE Toilettage Puppy Enr",
    "wof:placetype":"venue"
},
  "geometry": {"coordinates":[-74.0118637085,45.8789672852],"type":"Point"}
}