{
  "type": "Feature",
  "properties": {
    "addr:full":"4945 Boul Rosemont Montreal QC H1T 2E6",
    "addr:housenumber":"4945",
    "addr:postcode":"h1t 2e6",
    "addr:street":"Boul Rosemont",
    "iso:country":"CA",
    "sg:address":"4945 Boul Rosemont",
    "sg:city":"Montreal",
    "sg:classifiers":[
        {
            "category":"Food & Beverages",
            "subcategory":"Groceries & Convenience Stores",
            "type":"Retail Goods"
        }
    ],
    "sg:phone":"+1 514 252 9397",
    "sg:postcode":"H1T 2E6",
    "sg:province":"QC",
    "sg:tags":[
        "grocer"
    ],
    "wof:name":"Depanneur Rosemont Enr",
    "wof:placetype":"venue"
},
  "geometry": {"coordinates":[-73.5665512085,45.5691719055],"type":"Point"}
}