{
  "type": "Feature",
  "properties": {
    "addr:full":"7493 Kimbel St Mississauga ON L5S 1A7",
    "addr:housenumber":"7493",
    "addr:postcode":"l5s 1a7",
    "addr:street":"Kimbel St",
    "iso:country":"CA",
    "sg:address":"7493 Kimbel St",
    "sg:city":"Mississauga",
    "sg:classifiers":[
        {
            "category":"Retail",
            "subcategory":"Repair Shop",
            "type":"Services"
        }
    ],
    "sg:phone":"+1 905 673 0936",
    "sg:postcode":"L5S 1A7",
    "sg:province":"ON",
    "sg:tags":[
        "welding"
    ],
    "wof:name":"Triangle Welding & Fabricating",
    "wof:placetype":"venue"
},
  "geometry": {"coordinates":[-79.6646728516,43.7002868652],"type":"Point"}
}