{
  "type": "Feature",
  "properties": {
    "addr:full":"2085 Lawrence Ave E #6 Scarborough ON M1R 2Z4",
    "addr:housenumber":"2085",
    "addr:postcode":"m1r 2z4",
    "addr:street":"Lawrence Ave E # 6",
    "iso:country":"CA",
    "sg:address":"2085 Lawrence Ave E #6",
    "sg:city":"Scarborough",
    "sg:classifiers":[
        {
            "category":"Health Services",
            "subcategory":"Doctor",
            "type":"Services"
        }
    ],
    "sg:phone":"+1 416 751 8400",
    "sg:postcode":"M1R 2Z4",
    "sg:province":"ON",
    "sg:tags":[
        "dentist"
    ],
    "wof:name":"Tasios, Chris DDS",
    "wof:placetype":"venue"
},
  "geometry": {"coordinates":[-79.2928771973,43.7456321716],"type":"Point"}
}