{
  "type": "Feature",
  "properties": {
    "iso:country":"CA",
    "sg:address":"986 Av Dupuis",
    "sg:city":"Mascouche",
    "sg:classifiers":[
        {
            "category":"Building & Trades",
            "subcategory":"Electrical",
            "type":"Services"
        }
    ],
    "sg:phone":"+1 450 966 9916",
    "sg:postcode":"J7K 3P7",
    "sg:province":"QC",
    "sg:tags":[
        "electric",
        "contractor"
    ],
    "wof:name":"Micro Electrique Inc",
    "wof:placetype":"venue"
},
  "geometry": {"coordinates":[-73.596207,45.745552],"type":"Point"}
}