{
  "type": "Feature",
  "properties": {
    "addr:full":"2189 Av Larue Beauport QC G1C 4Z3",
    "addr:housenumber":"2189",
    "addr:postcode":"qc g1c 4z3",
    "addr:street":"Av Larue",
    "iso:country":"CA",
    "sg:address":"2189 Av Larue",
    "sg:city":"Beauport",
    "sg:classifiers":[
        {
            "category":"Retail",
            "subcategory":"Laundry & Dry Cleaning",
            "type":"Services"
        }
    ],
    "sg:phone":"+1 418 667 1316",
    "sg:postcode":"G1C 4Z3",
    "sg:province":"QC",
    "sg:tags":[
        "cleaners"
    ],
    "wof:name":"Nettoyeur Miranet Enr",
    "wof:placetype":"venue"
},
  "geometry": {"coordinates":[-71.168678,46.888229],"type":"Point"}
}