{
  "type": "Feature",
  "properties": {
    "addr:full":"York ON M6B 4J3",
    "addr:postcode":"m6b 4j3",
    "iso:country":"CA",
    "sg:city":"York",
    "sg:classifiers":[
        {
            "category":"Food & Beverages",
            "subcategory":"Bakery",
            "type":"Retail Goods"
        }
    ],
    "sg:phone":"+1 416 256 4813",
    "sg:postcode":"M6B 4J3",
    "sg:province":"ON",
    "sg:tags":[
        "doughnut"
    ],
    "wof:name":"Tim Hortons",
    "wof:placetype":"venue"
},
  "geometry": {"coordinates":[-79.4521865845,43.701877594],"type":"Point"}
}