{
  "type": "Feature",
  "properties": {
    "addr:full":"150 King St W Toronto ON M5H 1J9",
    "addr:housenumber":"150",
    "addr:postcode":"m5h 1j9",
    "addr:street":"King St W",
    "iso:country":"CA",
    "sg:address":"150 King St W",
    "sg:city":"Toronto",
    "sg:classifiers":[
        {
            "category":"Shopping",
            "subcategory":"Stationery & Office Supplies",
            "type":"Retail Goods"
        }
    ],
    "sg:phone":"+1 416 595 5111",
    "sg:postcode":"M5H 1J9",
    "sg:province":"ON",
    "sg:tags":[
        "stationer"
    ],
    "wof:name":"Carlton Cards",
    "wof:placetype":"venue"
},
  "geometry": {"coordinates":[-79.38372039790001,43.6479721069],"type":"Point"}
}