{
  "type": "Feature",
  "properties": {
    "addr:full":"334 Yonge St Toronto ON M5B 1R8",
    "addr:housenumber":"334",
    "addr:postcode":"m5b 1r8",
    "addr:street":"Yonge St",
    "iso:country":"CA",
    "sg:address":"334 Yonge St",
    "sg:city":"Toronto",
    "sg:classifiers":[
        {
            "category":"Professional",
            "subcategory":"Lawyer & Legal Services",
            "type":"Services"
        }
    ],
    "sg:phone":"+1 416 597 0502",
    "sg:postcode":"M5B 1R8",
    "sg:province":"ON",
    "sg:tags":[
        "attorney"
    ],
    "wof:name":"Funland Arcades",
    "wof:placetype":"venue"
},
  "geometry": {"coordinates":[-79.3814697266,43.657459259],"type":"Point"}
}