{
  "type": "Feature",
  "properties": {
    "iso:country":"CA",
    "sg:city":"North Vancouver",
    "sg:classifiers":[
        {
            "category":"Health Services",
            "subcategory":"Optometrist",
            "type":"Services"
        }
    ],
    "sg:phone":"+1 604 988 4455",
    "sg:postcode":"V7M 3J9",
    "sg:province":"BC",
    "wof:name":"Quayside Optometry Clinic",
    "wof:placetype":"venue"
},
  "geometry": {"coordinates":[-123.08181762700001,49.3119316101],"type":"Point"}
}