{
  "type": "Feature",
  "properties": {
    "addr:full":"4300 Steeles Ave E # CA Markham ON L3R 0Y5",
    "addr:housenumber":"4300",
    "addr:postcode":"l3r 0y5",
    "addr:street":"Steeles Ave E #",
    "iso:country":"CA",
    "sg:address":"4300 Steeles Ave E # CA",
    "sg:city":"Markham",
    "sg:classifiers":[
        {
            "category":"Shopping",
            "subcategory":"Clothing, Apparel, & Fashions",
            "type":"Retail Goods"
        }
    ],
    "sg:phone":"+1 905 415 1000",
    "sg:postcode":"L3R 0Y5",
    "sg:province":"ON",
    "sg:tags":[
        "infant",
        "wear"
    ],
    "wof:name":"Tweety Kids Fashion",
    "wof:placetype":"venue"
},
  "geometry": {"coordinates":[-79.3067321777,43.8238983154],"type":"Point"}
}