{
  "type": "Feature",
  "properties": {
    "addr:full":"630 Ch DE LA Grande-Carriere Louiseville QC J5V 2L4",
    "addr:housenumber":"630",
    "addr:postcode":"j5v 2l4",
    "addr:street":"Ch De La Grande-Carriere",
    "iso:country":"CA",
    "sg:address":"630 Ch DE LA Grande-Carriere",
    "sg:city":"Louiseville",
    "sg:classifiers":[
        {
            "category":"Autos & Motor Vehicles",
            "subcategory":"Motorcycle Sales",
            "type":"Retail Goods"
        }
    ],
    "sg:phone":"+1 819 228 5267",
    "sg:postcode":"J5V 2L4",
    "sg:province":"QC",
    "sg:tags":[
        "scooter"
    ],
    "wof:name":"Clement Motors Inc",
    "wof:placetype":"venue"
},
  "geometry": {"coordinates":[-72.98234600000001,46.266876],"type":"Point"}
}