{
  "type": "Feature",
  "properties": {
    "addr:full":"4529 Eleniak Rd NW Edmonton AB T6B 2N1",
    "addr:housenumber":"4529",
    "addr:postcode":"t6b 2n1",
    "addr:street":"Eleniak Rd Nw",
    "iso:country":"CA",
    "sg:address":"4529 Eleniak Rd NW",
    "sg:city":"Edmonton",
    "sg:classifiers":[
        {
            "category":"Freight",
            "type":"Transportation"
        }
    ],
    "sg:phone":"+1 780 468 5244",
    "sg:postcode":"T6B 2N1",
    "sg:province":"AB",
    "sg:tags":[
        "mover"
    ],
    "wof:name":"Al's Piano & Furniture Moving",
    "wof:placetype":"venue"
},
  "geometry": {"coordinates":[-113.411491394,53.5026741028],"type":"Point"}
}