{
  "type": "Feature",
  "properties": {
    "addr:full":"112 Rue Durand Saint-Pierre-Les-Becquets QC G0X 2Z0",
    "addr:housenumber":"112",
    "addr:postcode":"g0x 2z0",
    "addr:street":"Rue Durand",
    "iso:country":"CA",
    "sg:address":"112 Rue Durand",
    "sg:city":"Saint-Pierre-Les-Becquets",
    "sg:classifiers":[
        {
            "category":"Personal",
            "subcategory":"Beauty Salon",
            "type":"Services"
        }
    ],
    "sg:phone":"+1 819 263 2349",
    "sg:postcode":"G0X 2Z0",
    "sg:province":"QC",
    "wof:name":"Salon Esthetique L'Etincelle",
    "wof:placetype":"venue"
},
  "geometry": {"coordinates":[-72.218231,46.463989],"type":"Point"}
}