{
  "type": "Feature",
  "properties": {
    "addr:full":"126 Weber St W Kitchener ON N2H 3Z9",
    "addr:housenumber":"126",
    "addr:postcode":"n2h 3z9",
    "addr:street":"Weber St W",
    "iso:country":"CA",
    "sg:address":"126 Weber St W",
    "sg:city":"Kitchener",
    "sg:classifiers":[
        {
            "category":"Railroad",
            "type":"Transportation"
        }
    ],
    "sg:phone":"+1 519 749 8000",
    "sg:postcode":"N2H 3Z9",
    "sg:province":"ON",
    "wof:name":"Goderich Exeter Railway CO Ltd",
    "wof:placetype":"venue"
},
  "geometry": {"coordinates":[-80.494263,43.45591],"type":"Point"}
}