{
  "type": "Feature",
  "properties": {
    "iso:country":"CA",
    "sg:city":"Dunnville",
    "sg:classifiers":[
        {
            "category":"Health Services",
            "subcategory":"Doctor",
            "type":"Services"
        }
    ],
    "sg:phone":"+1 905 774 7503",
    "sg:postcode":"N1A 2P7",
    "sg:province":"ON",
    "sg:tags":[
        "physician",
        "clinic",
        "surgeon"
    ],
    "wof:name":"Scallan, Frank J MD",
    "wof:placetype":"venue"
},
  "geometry": {"coordinates":[-79.6250991821,42.9050941467],"type":"Point"}
}