{
  "type": "Feature",
  "properties": {
    "addr:full":"5 St Anne St St Albert AB T8N 3Z9",
    "addr:housenumber":"5",
    "addr:postcode":"t8n 3z9",
    "addr:street":"St Anne St",
    "iso:country":"CA",
    "sg:address":"5 St Anne St",
    "sg:city":"St Albert",
    "sg:classifiers":[
        {
            "category":"Government",
            "subcategory":"Office",
            "type":"Public Place"
        }
    ],
    "sg:phone":"+1 780 459 1523",
    "sg:postcode":"T8N 3Z9",
    "sg:province":"AB",
    "sg:tags":[
        "village"
    ],
    "wof:name":"St Albert Accounts Receivable",
    "wof:placetype":"venue"
},
  "geometry": {"coordinates":[-113.627571,53.633484],"type":"Point"}
}