{
  "type": "Feature",
  "properties": {
    "iso:country":"CA",
    "sg:address":"949 Commercial Dr",
    "sg:city":"Vancouver",
    "sg:classifiers":[
        {
            "category":"Restaurant",
            "type":"Food & Drink"
        }
    ],
    "sg:phone":"+1 604 251 2411",
    "sg:postcode":"V5L 3W8",
    "sg:province":"BC",
    "wof:name":"Sunrise Pizza & Steak House",
    "wof:placetype":"venue"
},
  "geometry": {"coordinates":[-123.069747925,49.2762374878],"type":"Point"}
}