{
  "type": "Feature",
  "properties": {
    "iso:country":"CA",
    "sg:address":"5 Assiniboia Ave",
    "sg:city":"Yorkton",
    "sg:classifiers":[
        {
            "category":"Building & Trades",
            "subcategory":"Plumbing",
            "type":"Services"
        }
    ],
    "sg:phone":"+1 306 782 1577",
    "sg:postcode":"S3N 1N5",
    "sg:province":"SK",
    "sg:tags":[
        "conditioning",
        "air",
        "system",
        "contractor"
    ],
    "wof:name":"Penguin Refrigeration CO Ltd",
    "wof:placetype":"venue"
},
  "geometry": {"coordinates":[-102.449874878,51.2040557861],"type":"Point"}
}