{
  "type": "Feature",
  "properties": {
    "addr:full":"10004 105 Ave Grande Prairie AB T8V 1H1",
    "addr:housenumber":"10004",
    "addr:postcode":"t8v 1h1",
    "addr:street":"105 Ave",
    "iso:country":"CA",
    "sg:address":"10004 105 Ave",
    "sg:city":"Grande Prairie",
    "sg:classifiers":[
        {
            "category":"Restaurant",
            "type":"Food & Drink"
        }
    ],
    "sg:phone":"+1 780 532 2007",
    "sg:postcode":"T8V 1H1",
    "sg:province":"AB",
    "sg:tags":[
        "parlor",
        "ice",
        "cream"
    ],
    "wof:name":"Dairy Queen",
    "wof:placetype":"venue"
},
  "geometry": {"coordinates":[-118.795303,55.175526],"type":"Point"}
}