{
  "type": "Feature",
  "properties": {
    "addr:full":"6515 Boul LA Fayette Laval QC H7C 1M5",
    "addr:housenumber":"6515",
    "addr:postcode":"h7c 1m5",
    "addr:street":"Boul La Fayette",
    "iso:country":"CA",
    "sg:address":"6515 Boul LA Fayette",
    "sg:city":"Laval",
    "sg:classifiers":[
        {
            "category":"Wholesale",
            "subcategory":"Auto Parts",
            "type":"Manufacturing & Wholesale Goods"
        }
    ],
    "sg:phone":"+1 450 661 3364",
    "sg:postcode":"H7C 1M5",
    "sg:province":"QC",
    "sg:tags":[
        "automobile",
        "rebuilt"
    ],
    "wof:name":"Recyclage Automobiles Svp",
    "wof:placetype":"venue"
},
  "geometry": {"coordinates":[-73.63581848139999,45.6344985962],"type":"Point"}
}