{
  "type": "Feature",
  "properties": {
    "addr:full":"8405 Rue Desormeaux Becancour QC G9H 2X3",
    "addr:housenumber":"8405",
    "addr:postcode":"g9h 2x3",
    "addr:street":"Rue Desormeaux Becancour",
    "iso:country":"CA",
    "sg:address":"8405 Rue Desormeaux",
    "sg:city":"Becancour",
    "sg:classifiers":[
        {
            "category":"Professional",
            "subcategory":"Management & Consulting",
            "type":"Services"
        }
    ],
    "sg:phone":"+1 819 294 2999",
    "sg:postcode":"G9H 2X3",
    "sg:province":"QC",
    "sg:tags":[
        "consultant",
        "waste"
    ],
    "wof:name":"Regie Des Dechets Becancour",
    "wof:placetype":"venue"
},
  "geometry": {"coordinates":[-72.435051,46.339317],"type":"Point"}
}