{
  "type": "Feature",
  "properties": {
    "addr:full":"200 Route 236 Saint-Stanislas-DE-Kostka QC J0S 1W0",
    "addr:housenumber":"200",
    "addr:postcode":"j0s 1w0",
    "addr:street":"Route 236",
    "iso:country":"CA",
    "sg:address":"200 Route 236",
    "sg:city":"Saint-Stanislas-DE-Kostka",
    "sg:classifiers":[
        {
            "category":"Building & Trades",
            "subcategory":"Construction",
            "type":"Services"
        }
    ],
    "sg:phone":"+1 450 373 2088",
    "sg:postcode":"J0S 1W0",
    "sg:province":"QC",
    "sg:tags":[
        "contractor"
    ],
    "wof:name":"Construction & Fndtn D Vachon",
    "wof:placetype":"venue"
},
  "geometry": {"coordinates":[-74.12661,45.180672],"type":"Point"}
}