{
  "type": "Feature",
  "properties": {
    "addr:full":"10200 8 St Dawson Creek BC V1G 3P8",
    "addr:housenumber":"10200",
    "addr:postcode":"v1g 3p8",
    "addr:street":"8 St",
    "iso:country":"CA",
    "sg:address":"10200 8 St",
    "sg:city":"Dawson Creek",
    "sg:classifiers":[
        {
            "category":"Real Estate",
            "subcategory":"Real Estate Agent",
            "type":"Services"
        }
    ],
    "sg:phone":"+1 250 782 4858",
    "sg:postcode":"V1G 3P8",
    "sg:province":"BC",
    "sg:tags":[
        "cooperative"
    ],
    "wof:name":"Dawson CO-OP Union",
    "wof:placetype":"venue"
},
  "geometry": {"coordinates":[-120.224388,55.757347],"type":"Point"}
}