{
  "type": "Feature",
  "properties": {
    "addr:full":"43 King St E Colborne ON K0K 1S0",
    "addr:housenumber":"43",
    "addr:postcode":"k0k 1s0",
    "addr:street":"King St E Colborne",
    "iso:country":"CA",
    "sg:address":"43 King St E",
    "sg:city":"Colborne",
    "sg:classifiers":[
        {
            "category":"Professional",
            "subcategory":"Lawyer & Legal Services",
            "type":"Services"
        }
    ],
    "sg:phone":"+1 905 355 2525",
    "sg:postcode":"K0K 1S0",
    "sg:province":"ON",
    "sg:tags":[
        "attorney"
    ],
    "wof:name":"Hustler, Peter A",
    "wof:placetype":"venue"
},
  "geometry": {"coordinates":[-77.886368,44.005589],"type":"Point"}
}