{
  "type": "Feature",
  "properties": {
    "addr:full":"Vancouver BC V6P 6G5",
    "addr:postcode":"v6p 6g5",
    "iso:country":"CA",
    "sg:city":"Vancouver",
    "sg:classifiers":[
        {
            "category":"Professional",
            "subcategory":"Credit Reporting & Collection",
            "type":"Services"
        }
    ],
    "sg:phone":"+1 604 606 3200",
    "sg:postcode":"V6P 6G5",
    "sg:province":"BC",
    "sg:tags":[
        "agency"
    ],
    "wof:name":"Allied International Credit",
    "wof:placetype":"venue"
},
  "geometry": {"coordinates":[-123.13324,49.204262],"type":"Point"}
}