{
  "type": "Feature",
  "properties": {
    "addr:full":"163 Rue Principale E Saint-Aubert QC G0R 2R0",
    "addr:housenumber":"163",
    "addr:postcode":"g0r 2r0",
    "addr:street":"Rue Principale E Saint-Aubert",
    "iso:country":"CA",
    "sg:address":"163 Rue Principale E",
    "sg:city":"Saint-Aubert",
    "sg:classifiers":[
        {
            "category":"Wholesale",
            "subcategory":"Construction Materials",
            "type":"Manufacturing & Wholesale Goods"
        }
    ],
    "sg:phone":"+1 418 598 6497",
    "sg:postcode":"G0R 2R0",
    "sg:province":"QC",
    "sg:tags":[
        "limestone",
        "lime"
    ],
    "wof:name":"Fortin & Fournier",
    "wof:placetype":"venue"
},
  "geometry": {"coordinates":[-70.200821,47.198193],"type":"Point"}
}