{
  "type": "Feature",
  "properties": {
    "iso:country":"CA",
    "sg:address":"2058 Logan Ave",
    "sg:city":"Winnipeg",
    "sg:classifiers":[
        {
            "category":"Wholesale",
            "subcategory":"Auto Parts",
            "type":"Manufacturing & Wholesale Goods"
        }
    ],
    "sg:phone":"+1 204 694 3000",
    "sg:postcode":"R2R 0H9",
    "sg:province":"MB",
    "sg:tags":[
        "equipment",
        "truck"
    ],
    "wof:name":"Freightliner Manitoba Ltd",
    "wof:placetype":"venue"
},
  "geometry": {"coordinates":[-97.2092666626,49.9255142212],"type":"Point"}
}