{
  "type": "Feature",
  "properties": {
    "addr:full":"1106 Walker Rd Windsor ON N8Y 2N7",
    "addr:housenumber":"1106",
    "addr:postcode":"n8y 2n7",
    "addr:street":"Walker Rd",
    "iso:country":"CA",
    "sg:address":"1106 Walker Rd",
    "sg:city":"Windsor",
    "sg:classifiers":[
        {
            "category":"Manufacturing",
            "subcategory":"Chemicals & Compounds",
            "type":"Manufacturing & Wholesale Goods"
        }
    ],
    "sg:phone":"+1 519 252 7275",
    "sg:postcode":"N8Y 2N7",
    "sg:province":"ON",
    "sg:tags":[
        "paint"
    ],
    "wof:name":"Mac Donald & White Varnish CO",
    "wof:placetype":"venue"
},
  "geometry": {"coordinates":[-83.0040054321,42.3174591064],"type":"Point"}
}