{
  "type": "Feature",
  "properties": {
    "addr:full":"Saskatoon SK S7H 0W5",
    "addr:postcode":"s7h 0w5",
    "iso:country":"CA",
    "sg:city":"Saskatoon",
    "sg:classifiers":[
        {
            "category":"Professional",
            "subcategory":"Management & Consulting",
            "type":"Services"
        }
    ],
    "sg:phone":"+1 306 665 6900",
    "sg:postcode":"S7H 0W5",
    "sg:province":"SK",
    "sg:tags":[
        "consultant",
        "business"
    ],
    "wof:name":"Bmg Business Management Group",
    "wof:placetype":"venue"
},
  "geometry": {"coordinates":[-106.597084045,52.114906311],"type":"Point"}
}