{
  "type": "Feature",
  "properties": {
    "addr:full":"3432 Rue Metcalfe Rawdon QC J0K 1S0",
    "addr:housenumber":"3432",
    "addr:postcode":"j0k 1s0",
    "addr:street":"Rue Metcalfe",
    "iso:country":"CA",
    "sg:address":"3432 Rue Metcalfe",
    "sg:city":"Rawdon",
    "sg:classifiers":[
        {
            "category":"Shopping",
            "subcategory":"Florist",
            "type":"Retail Goods"
        }
    ],
    "sg:phone":"+1 450 834 4000",
    "sg:postcode":"J0K 1S0",
    "sg:province":"QC",
    "wof:name":"Fleurs D'Elysee",
    "wof:placetype":"venue"
},
  "geometry": {"coordinates":[-73.69635,46.038933],"type":"Point"}
}