{
  "type": "Feature",
  "properties": {
    "addr:full":"200 Iroquois St E Moose Jaw SK S6H 4T3",
    "addr:housenumber":"200",
    "addr:postcode":"s6h 4t3",
    "addr:street":"Iroquois St E",
    "iso:country":"CA",
    "sg:address":"200 Iroquois St E",
    "sg:city":"Moose Jaw",
    "sg:classifiers":[
        {
            "category":"Health Services",
            "subcategory":"Nursing And Care Facility",
            "type":"Services"
        }
    ],
    "sg:phone":"+1 306 692 4882",
    "sg:postcode":"S6H 4T3",
    "sg:province":"SK",
    "sg:tags":[
        "personal",
        "home",
        "senior",
        "citizen"
    ],
    "wof:name":"Ina Grafton Gage Home-Seniors",
    "wof:placetype":"venue"
},
  "geometry": {"coordinates":[-105.529319763,50.3831367493],"type":"Point"}
}