{
  "type": "Feature",
  "properties": {
    "addr:full":"726 Poplar Bay Portage LA Prairie MB R1N 3K8",
    "addr:housenumber":"726",
    "addr:postcode":"r1n 3k8",
    "addr:street":"Poplar Bay",
    "iso:country":"CA",
    "sg:address":"726 Poplar Bay",
    "sg:city":"Portage LA Prairie",
    "sg:classifiers":[
        {
            "category":"Personal",
            "subcategory":"Barber",
            "type":"Services"
        }
    ],
    "sg:phone":"+1 204 857 7651",
    "sg:postcode":"R1N 3K8",
    "sg:province":"MB",
    "wof:name":"Bev's Hairstyling",
    "wof:placetype":"venue"
},
  "geometry": {"coordinates":[-98.281319,49.982895],"type":"Point"}
}