{
  "type": "Feature",
  "properties": {
    "addr:full":"1560 Brebber Rd Nanaimo BC V9X 1P4",
    "addr:housenumber":"1560",
    "addr:postcode":"v9x 1p4",
    "addr:street":"Brebber Rd",
    "iso:country":"CA",
    "sg:address":"1560 Brebber Rd",
    "sg:city":"Nanaimo",
    "sg:classifiers":[
        {
            "category":"Autos & Motor Vehicles",
            "subcategory":"Boat Sales",
            "type":"Retail Goods"
        }
    ],
    "sg:phone":"+1 250 722 3683",
    "sg:postcode":"V9X 1P4",
    "sg:province":"BC",
    "sg:tags":[
        "tours",
        "dealer",
        "sightseeing"
    ],
    "wof:name":"Wild Heart Adventures",
    "wof:placetype":"venue"
},
  "geometry": {"coordinates":[-123.93615699999999,49.164268],"type":"Point"}
}