{
  "type": "Feature",
  "properties": {
    "addr:full":"800 Centre St Espanola ON P5E 1J3",
    "addr:housenumber":"800",
    "addr:postcode":"p5e 1j3",
    "addr:street":"Centre St",
    "iso:country":"CA",
    "sg:address":"800 Centre St",
    "sg:city":"Espanola",
    "sg:classifiers":[
        {
            "category":"Health Services",
            "subcategory":"Doctor",
            "type":"Services"
        }
    ],
    "sg:phone":"+1 705 869 0880",
    "sg:postcode":"P5E 1J3",
    "sg:province":"ON",
    "sg:tags":[
        "dentist"
    ],
    "wof:name":"D'Aloisio, David R DDS",
    "wof:placetype":"venue"
},
  "geometry": {"coordinates":[-81.75806427000001,46.247795105],"type":"Point"}
}