{
  "type": "Feature",
  "properties": {
    "addr:full":"259 Traders Blvd E Mississauga ON L4Z 2E5",
    "addr:housenumber":"259",
    "addr:postcode":"l4z 2e5",
    "addr:street":"Traders Blvd E",
    "iso:country":"CA",
    "sg:address":"259 Traders Blvd E",
    "sg:city":"Mississauga",
    "sg:classifiers":[
        {
            "category":"Professional",
            "subcategory":"Research",
            "type":"Services"
        }
    ],
    "sg:phone":"+1 905 507 6244",
    "sg:postcode":"L4Z 2E5",
    "sg:province":"ON",
    "sg:tags":[
        "development",
        "laboratory"
    ],
    "wof:name":"Tis Technologies Inc",
    "wof:placetype":"venue"
},
  "geometry": {"coordinates":[-79.66889999999999,43.628059],"type":"Point"}
}