{
  "type": "Feature",
  "properties": {
    "addr:full":"Sudbury ON P3E 4Z6",
    "addr:postcode":"p3e 4z6",
    "iso:country":"CA",
    "sg:city":"Sudbury",
    "sg:classifiers":[
        {
            "category":"Retail",
            "subcategory":"Auto Repair",
            "type":"Services"
        }
    ],
    "sg:phone":"+1 705 523 8200",
    "sg:postcode":"P3E 4Z6",
    "sg:province":"ON",
    "sg:tags":[
        "repairing",
        "automobile",
        "radiator"
    ],
    "wof:name":"Enterprise Radiators & Gas",
    "wof:placetype":"venue"
},
  "geometry": {"coordinates":[-80.99569702150001,46.4437217712],"type":"Point"}
}