{
  "type": "Feature",
  "properties": {
    "addr:full":"158 Shoemaker St Kitchener ON N2E 3E1",
    "addr:housenumber":"158",
    "addr:postcode":"n2e 3e1",
    "addr:street":"Shoemaker St",
    "iso:country":"CA",
    "sg:address":"158 Shoemaker St",
    "sg:city":"Kitchener",
    "sg:classifiers":[
        {
            "category":"Manufacturing",
            "subcategory":"Metals",
            "type":"Manufacturing & Wholesale Goods"
        }
    ],
    "sg:phone":"+1 519 748 6002",
    "sg:postcode":"N2E 3E1",
    "sg:province":"ON",
    "sg:tags":[
        "steel"
    ],
    "wof:name":"K S Welding Ltd",
    "wof:placetype":"venue"
},
  "geometry": {"coordinates":[-80.46893300000001,43.407249],"type":"Point"}
}