{
  "type": "Feature",
  "properties": {
    "iso:country":"CA",
    "sg:address":"10013 106 Ave NW",
    "sg:city":"Edmonton",
    "sg:classifiers":[
        {
            "category":"Restaurant",
            "type":"Food & Drink"
        }
    ],
    "sg:phone":"+1 780 423 3743",
    "sg:postcode":"T5H 0N8",
    "sg:province":"AB",
    "wof:name":"Wokking Restaurant Ltd",
    "wof:placetype":"venue"
},
  "geometry": {"coordinates":[-113.492248535,53.5497360229],"type":"Point"}
}