{
  "type": "Feature",
  "properties": {
    "addr:full":"5801 Ch Upper Lachine Montreal QC H4A 2B6",
    "addr:housenumber":"5801",
    "addr:postcode":"h4a 2b6",
    "addr:street":"Ch Upper",
    "iso:country":"CA",
    "sg:address":"5801 Ch Upper Lachine",
    "sg:city":"Montreal",
    "sg:classifiers":[
        {
            "category":"Food & Beverages",
            "subcategory":"Bakery",
            "type":"Retail Goods"
        }
    ],
    "sg:phone":"+1 514 481 4215",
    "sg:postcode":"H4A 2B6",
    "sg:province":"QC",
    "sg:tags":[
        "baker"
    ],
    "wof:name":"Boulangerie Ndg",
    "wof:placetype":"venue"
},
  "geometry": {"coordinates":[-73.61187,45.467426],"type":"Point"}
}