{
  "type": "Feature",
  "properties": {
    "addr:full":"1550 Nottinghill Gate Oakville ON L6M 1X7",
    "addr:housenumber":"1550",
    "addr:postcode":"l6m 1x7",
    "addr:street":"Nottinghill Gate",
    "iso:country":"CA",
    "sg:address":"1550 Nottinghill Gate",
    "sg:city":"Oakville",
    "sg:classifiers":[
        {
            "category":"Education",
            "subcategory":"School",
            "type":"Public Place"
        }
    ],
    "sg:phone":"+1 905 847 0595",
    "sg:postcode":"L6M 1X7",
    "sg:province":"ON",
    "wof:name":"St Ignatius of Loyola Scndry",
    "wof:placetype":"venue"
},
  "geometry": {"coordinates":[-79.733124,43.445576],"type":"Point"}
}