{
  "type": "Feature",
  "properties": {
    "addr:full":"384 5th St Courtenay BC V9N 1K1",
    "addr:housenumber":"384",
    "addr:postcode":"v9n 1k1",
    "addr:street":"5Th St",
    "iso:country":"CA",
    "sg:address":"384 5th St",
    "sg:city":"Courtenay",
    "sg:classifiers":[
        {
            "category":"Restaurant",
            "type":"Food & Drink"
        }
    ],
    "sg:phone":"+1 250 338 0939",
    "sg:postcode":"V9N 1K1",
    "sg:province":"BC",
    "sg:tags":[
        "shop",
        "coffee"
    ],
    "wof:name":"Mudsharks Coffee Bar",
    "wof:placetype":"venue"
},
  "geometry": {"coordinates":[-124.999664,49.690453],"type":"Point"}
}