{
  "type": "Feature",
  "properties": {
    "addr:full":"192 Caithness St W Caledonia ON N3W 1B2",
    "addr:housenumber":"192",
    "addr:postcode":"n3w 1b2",
    "addr:street":"Caithness St W",
    "iso:country":"CA",
    "sg:address":"192 Caithness St W",
    "sg:city":"Caledonia",
    "sg:classifiers":[
        {
            "category":"Shopping",
            "subcategory":"Bicycles & Sporting Goods",
            "type":"Retail Goods"
        }
    ],
    "sg:phone":"+1 905 765 3215",
    "sg:postcode":"N3W 1B2",
    "sg:province":"ON",
    "sg:tags":[
        "tackle",
        "bait",
        "fishing"
    ],
    "wof:name":"Caledonia Bait & Tackle",
    "wof:placetype":"venue"
},
  "geometry": {"coordinates":[-79.958778,43.075066],"type":"Point"}
}