{
  "type": "Feature",
  "properties": {
    "addr:full":"431 George St S Peterborough ON K9J 3E2",
    "addr:housenumber":"431",
    "addr:postcode":"k9j 3e2",
    "addr:street":"George St S",
    "iso:country":"CA",
    "sg:address":"431 George St S",
    "sg:city":"Peterborough",
    "sg:classifiers":[
        {
            "category":"Retail",
            "subcategory":"Funeral Services",
            "type":"Services"
        }
    ],
    "sg:phone":"+1 705 745 4612",
    "sg:postcode":"K9J 3E2",
    "sg:province":"ON",
    "sg:tags":[
        "director"
    ],
    "wof:name":"Duffus Funeral Home",
    "wof:placetype":"venue"
},
  "geometry": {"coordinates":[-78.318916,44.291458],"type":"Point"}
}