{
  "type": "Feature",
  "properties": {
    "addr:full":"6934 Kinsman Crt Niagara Falls ON L2E 6S5",
    "addr:housenumber":"6934",
    "addr:postcode":"l2e 6s5",
    "addr:street":"Kinsman Crt",
    "iso:country":"CA",
    "sg:address":"6934 Kinsman Crt",
    "sg:city":"Niagara Falls",
    "sg:classifiers":[
        {
            "category":"Wholesale",
            "subcategory":"Machinery & Supplies",
            "type":"Manufacturing & Wholesale Goods"
        }
    ],
    "sg:phone":"+1 905 356 1531",
    "sg:postcode":"L2E 6S5",
    "sg:province":"ON",
    "sg:tags":[
        "carpet",
        "cleaning",
        "rug"
    ],
    "wof:name":"Bissell Limited",
    "wof:placetype":"venue"
},
  "geometry": {"coordinates":[-79.12262699999999,43.075195],"type":"Point"}
}