{
  "type": "Feature",
  "properties": {
    "addr:full":"12 Main St N Hagersville ON N0A 1H0",
    "addr:housenumber":"12",
    "addr:postcode":"n0a 1h0",
    "addr:street":"Main St N",
    "iso:country":"CA",
    "sg:address":"12 Main St N",
    "sg:city":"Hagersville",
    "sg:classifiers":[
        {
            "category":"Restaurant",
            "type":"Food & Drink"
        }
    ],
    "sg:phone":"+1 905 768 1466",
    "sg:postcode":"N0A 1H0",
    "sg:province":"ON",
    "wof:name":"Princess Submarine & Rstrnt",
    "wof:placetype":"venue"
},
  "geometry": {"coordinates":[-80.05117799999999,42.962353],"type":"Point"}
}