{
  "type": "Feature",
  "properties": {
    "addr:full":"Schreiber ON P0T 2S0",
    "addr:postcode":"p0t 2s0",
    "iso:country":"CA",
    "sg:city":"Schreiber",
    "sg:classifiers":[
        {
            "category":"Banks & Credit Unions",
            "subcategory":"Bank",
            "type":"Services"
        }
    ],
    "sg:phone":"+1 807 824 2500",
    "sg:postcode":"P0T 2S0",
    "sg:province":"ON",
    "wof:name":"Superior Credit Union Ltd",
    "wof:placetype":"venue"
},
  "geometry": {"coordinates":[-87.26683800000001,48.80785],"type":"Point"}
}