{
  "type": "Feature",
  "properties": {
    "addr:full":"Saint-Andre-Avellin QC J0V 1W0",
    "addr:postcode":"j0v 1w0",
    "iso:country":"CA",
    "sg:city":"Saint-Andre-Avellin",
    "sg:classifiers":[
        {
            "category":"Sports & Exercise",
            "subcategory":"Bowling",
            "type":"Entertainment"
        }
    ],
    "sg:phone":"+1 819 983 2666",
    "sg:postcode":"J0V 1W0",
    "sg:province":"QC",
    "sg:tags":[
        "center"
    ],
    "wof:name":"Salle Quilles LA Petite Nation",
    "wof:placetype":"venue"
},
  "geometry": {"coordinates":[-75.054253,45.724167],"type":"Point"}
}