{
  "type": "Feature",
  "properties": {
    "addr:full":"1740 Richmond St London ON N5X 4E9",
    "addr:housenumber":"1740",
    "addr:postcode":"n5x 4e9",
    "addr:street":"Richmond St",
    "iso:country":"CA",
    "sg:address":"1740 Richmond St",
    "sg:city":"London",
    "sg:classifiers":[
        {
            "category":"Wholesale",
            "subcategory":"Groceries",
            "type":"Manufacturing & Wholesale Goods"
        }
    ],
    "sg:phone":"+1 519 679 4055",
    "sg:postcode":"N5X 4E9",
    "sg:province":"ON",
    "sg:tags":[
        "cocoa",
        "chocolate"
    ],
    "wof:name":"Sugar & Spice Chocolate London",
    "wof:placetype":"venue"
},
  "geometry": {"coordinates":[-81.283379,43.028454],"type":"Point"}
}