{
  "type": "Feature",
  "properties": {
    "iso:country":"CA",
    "sg:address":"1900 Dundas St E # 203",
    "sg:city":"Mississauga",
    "sg:classifiers":[
        {
            "category":"Personal",
            "subcategory":"Beauty Salon",
            "type":"Services"
        }
    ],
    "sg:phone":"+1 905 277 5706",
    "sg:postcode":"L4X 2Z4",
    "sg:province":"ON",
    "wof:name":"Chellsey Institute Aesthetics",
    "wof:placetype":"venue"
},
  "geometry": {"coordinates":[-79.571526,43.620567],"type":"Point"}
}