{
  "type": "Feature",
  "properties": {
    "addr:full":"145 Roland Michener Dr Kanata ON K2T 1G7",
    "addr:housenumber":"145",
    "addr:postcode":"k2t 1g7",
    "addr:street":"Roland Michener Dr",
    "iso:country":"CA",
    "sg:address":"145 Roland Michener Dr",
    "sg:city":"Kanata",
    "sg:classifiers":[
        {
            "category":"Shopping",
            "type":"Retail Goods"
        }
    ],
    "sg:phone":"+1 613 592 2822",
    "sg:postcode":"K2T 1G7",
    "sg:province":"ON",
    "sg:tags":[
        "pet",
        "shop",
        "aquarium"
    ],
    "wof:name":"Aquarium Services Warehouse",
    "wof:placetype":"venue"
},
  "geometry": {"coordinates":[-75.91280399999999,45.308483],"type":"Point"}
}