{
  "type": "Feature",
  "properties": {
    "addr:full":"50 Trail's End Collingwood ON L9Y 5B2",
    "addr:housenumber":"50",
    "addr:postcode":"l9y 5b2",
    "addr:street":"Trail'S End",
    "iso:country":"CA",
    "sg:address":"50 Trail's End",
    "sg:city":"Collingwood",
    "sg:classifiers":[
        {
            "category":"Professional",
            "subcategory":"Engineering",
            "type":"Services"
        }
    ],
    "sg:phone":"+1 705 445 4905",
    "sg:postcode":"L9Y 5B2",
    "sg:province":"ON",
    "sg:tags":[
        "engineer"
    ],
    "wof:name":"Barill Engineering Ltd",
    "wof:placetype":"venue"
},
  "geometry": {"coordinates":[-80.281311,44.496838],"type":"Point"}
}