{
  "type": "Feature",
  "properties": {
    "iso:country":"CA",
    "sg:address":"1405 Morningside Ave",
    "sg:city":"Scarborough",
    "sg:classifiers":[
        {
            "category":"Manufacturing",
            "subcategory":"Jewelry",
            "type":"Manufacturing & Wholesale Goods"
        }
    ],
    "sg:phone":"+1 416 281 0382",
    "sg:postcode":"M1B 3J1",
    "sg:province":"ON",
    "wof:name":"A & A Jewellers Ltd",
    "wof:placetype":"venue"
},
  "geometry": {"coordinates":[-79.203125,43.8104057312],"type":"Point"}
}