{
  "type": "Feature",
  "properties": {
    "iso:country":"CA",
    "sg:address":"237 Rue Des Tulipes",
    "sg:city":"Saint-Redempteur",
    "sg:classifiers":[
        {
            "category":"Building & Trades",
            "subcategory":"Cleaning & Sanitation",
            "type":"Services"
        }
    ],
    "sg:phone":"+1 418 836 5267",
    "sg:postcode":"G6K 1J2",
    "sg:province":"QC",
    "sg:tags":[
        "snow",
        "removal"
    ],
    "wof:name":"Groupe Theco",
    "wof:placetype":"venue"
},
  "geometry": {"coordinates":[-71.2834320068,46.6926078796],"type":"Point"}
}