{
  "type": "Feature",
  "properties": {
    "addr:full":"Sainte-Martine QC J0S 1V0",
    "addr:postcode":"j0s 1v0",
    "iso:country":"CA",
    "sg:city":"Sainte-Martine",
    "sg:classifiers":[
        {
            "category":"Wholesale",
            "subcategory":"Farm Supplies",
            "type":"Manufacturing & Wholesale Goods"
        }
    ],
    "sg:phone":"+1 450 427 2003",
    "sg:postcode":"J0S 1V0",
    "sg:province":"QC",
    "sg:tags":[
        "feed"
    ],
    "wof:name":"Coop Des Frontieres Coop",
    "wof:placetype":"venue"
},
  "geometry": {"coordinates":[-73.79852294920001,45.2501220703],"type":"Point"}
}