{
  "type": "Feature",
  "properties": {
    "addr:full":"70 Drewry Ave North York ON M2M 1C8",
    "addr:housenumber":"70",
    "addr:postcode":"m2m 1c8",
    "addr:street":"Drewry Ave",
    "iso:country":"CA",
    "sg:address":"70 Drewry Ave",
    "sg:city":"North York",
    "sg:classifiers":[
        {
            "category":"Education",
            "subcategory":"School",
            "type":"Public Place"
        }
    ],
    "sg:phone":"+1 416 395 3262",
    "sg:postcode":"M2M 1C8",
    "sg:province":"ON",
    "wof:name":"Drewry Secondary School",
    "wof:placetype":"venue"
},
  "geometry": {"coordinates":[-79.421227,43.786404],"type":"Point"}
}