{
  "type": "Feature",
  "properties": {
    "addr:full":"180 Industrial Pky N Aurora ON L4G 4C3",
    "addr:housenumber":"180",
    "addr:postcode":"l4g 4c3",
    "addr:street":"Industrial Pky N",
    "iso:country":"CA",
    "sg:address":"180 Industrial Pky N",
    "sg:city":"Aurora",
    "sg:classifiers":[
        {
            "category":"Wholesale",
            "subcategory":"Sporting Goods",
            "type":"Manufacturing & Wholesale Goods"
        }
    ],
    "sg:phone":"+1 905 841 4001",
    "sg:postcode":"L4G 4C3",
    "sg:province":"ON",
    "sg:tags":[
        "skiing"
    ],
    "wof:name":"Uvex Toko Canada Ltd",
    "wof:placetype":"venue"
},
  "geometry": {"coordinates":[-79.46161651609999,44.0105056763],"type":"Point"}
}