{
  "type": "Feature",
  "properties": {
    "iso:country":"CA",
    "sg:address":"685 Elgin St N",
    "sg:city":"Cambridge",
    "sg:classifiers":[
        {
            "category":"Education",
            "subcategory":"School",
            "type":"Public Place"
        }
    ],
    "sg:phone":"+1 519 622 0611",
    "sg:postcode":"N1R 7W6",
    "sg:province":"ON",
    "wof:name":"Elgin Street Public School",
    "wof:placetype":"venue"
},
  "geometry": {"coordinates":[-80.3128356934,43.3852348328],"type":"Point"}
}