{
  "type": "Feature",
  "properties": {
    "addr:full":"561 Rue Saint-Patrick Thetford Mines QC G6G 5W1",
    "addr:housenumber":"561",
    "addr:postcode":"g6g 5w1",
    "addr:street":"Rue Saint-Patrick",
    "iso:country":"CA",
    "sg:address":"561 Rue Saint-Patrick",
    "sg:city":"Thetford Mines",
    "sg:classifiers":[
        {
            "category":"Education",
            "subcategory":"School",
            "type":"Public Place"
        }
    ],
    "sg:phone":"+1 418 338 7831",
    "sg:postcode":"G6G 5W1",
    "sg:province":"QC",
    "wof:name":"Ecole Secondaire Joseph-Fectea",
    "wof:placetype":"venue"
},
  "geometry": {"coordinates":[-71.292534,46.087433],"type":"Point"}
}