{
  "type": "Feature",
  "properties": {
    "addr:full":"Surrey BC V3S 9S4",
    "addr:postcode":"v3s 9s4",
    "iso:country":"CA",
    "sg:city":"Surrey",
    "sg:classifiers":[
        {
            "category":"Freight",
            "type":"Transportation"
        }
    ],
    "sg:phone":"+1 604 535 7255",
    "sg:postcode":"V3S 9S4",
    "sg:province":"BC",
    "sg:tags":[
        "trucking"
    ],
    "wof:name":"Sea-Tac Transportation Svc Inc",
    "wof:placetype":"venue"
},
  "geometry": {"coordinates":[-122.735527,49.004883],"type":"Point"}
}