{
  "type": "Feature",
  "properties": {
    "addr:full":"Elphinstone MB R0J 0N0",
    "addr:postcode":"r0j 0n0",
    "iso:country":"CA",
    "sg:city":"Elphinstone",
    "sg:classifiers":[
        {
            "category":"Organizations",
            "subcategory":"Professional Association",
            "type":"Services"
        }
    ],
    "sg:phone":"+1 204 625 2062",
    "sg:postcode":"R0J 0N0",
    "sg:province":"MB",
    "sg:tags":[
        "native"
    ],
    "wof:name":"Keesee School",
    "wof:placetype":"venue"
},
  "geometry": {"coordinates":[-100.323059082,50.5326385498],"type":"Point"}
}