{
  "type": "Feature",
  "properties": {
    "addr:full":"Saskatoon SK S7K 4A7",
    "addr:postcode":"s7k 4a7",
    "iso:country":"CA",
    "sg:city":"Saskatoon",
    "sg:classifiers":[
        {
            "category":"Social Services",
            "type":"Services"
        }
    ],
    "sg:phone":"+1 306 867 1819",
    "sg:postcode":"S7K 4A7",
    "sg:province":"SK",
    "sg:tags":[
        "crisis",
        "center"
    ],
    "wof:name":"Crisis Line",
    "wof:placetype":"venue"
},
  "geometry": {"coordinates":[-106.65616607699999,52.1326751709],"type":"Point"}
}