{
  "type": "Feature",
  "properties": {
    "addr:full":"592 Rue Houde Saint-Celestin QC J0C 1G0",
    "addr:housenumber":"592",
    "addr:postcode":"j0c 1g0",
    "addr:street":"Rue Houde Saint-Celestin",
    "iso:country":"CA",
    "sg:address":"592 Rue Houde",
    "sg:city":"Saint-Celestin",
    "sg:classifiers":[
        {
            "category":"Autos & Motor Vehicles",
            "subcategory":"Recreational Vehicle Sales",
            "type":"Retail Goods"
        }
    ],
    "sg:phone":"+1 819 229 2204",
    "sg:postcode":"J0C 1G0",
    "sg:province":"QC",
    "sg:tags":[
        "parts",
        "trailer"
    ],
    "wof:name":"A M Pinard & Fils Inc",
    "wof:placetype":"venue"
},
  "geometry": {"coordinates":[-72.4342041016,46.2125473022],"type":"Point"}
}