{
  "type": "Feature",
  "properties": {
    "addr:full":"1420 Finlayson St LA Ronge SK S0J 1L0",
    "addr:housenumber":"1420",
    "addr:postcode":"s0j 1l0",
    "addr:street":"Finlayson St",
    "iso:country":"CA",
    "sg:address":"1420 Finlayson St",
    "sg:city":"LA Ronge",
    "sg:classifiers":[
        {
            "category":"Building & Trades",
            "subcategory":"Construction",
            "type":"Services"
        }
    ],
    "sg:phone":"+1 306 425 6840",
    "sg:postcode":"S0J 1L0",
    "sg:province":"SK",
    "sg:tags":[
        "excavating",
        "contractor"
    ],
    "wof:name":"Lee's Construction",
    "wof:placetype":"venue"
},
  "geometry": {"coordinates":[-105.295326233,55.1124954224],"type":"Point"}
}