{
  "type": "Feature",
  "properties": {
    "iso:country":"CA",
    "sg:address":"951 Regent St",
    "sg:city":"Fredericton",
    "sg:classifiers":[
        {
            "category":"Real Estate",
            "subcategory":"Real Estate Operator",
            "type":"Services"
        }
    ],
    "sg:phone":"+1 506 452 1056",
    "sg:postcode":"E3B 6Z2",
    "sg:province":"NB",
    "sg:tags":[
        "apartment"
    ],
    "wof:name":"Preferred Properties Ltd",
    "wof:placetype":"venue"
},
  "geometry": {"coordinates":[-66.653107,45.94471],"type":"Point"}
}