{
  "type": "Feature",
  "properties": {
    "addr:full":"7670 Tecumseh Rd E Windsor ON N8T 1E9",
    "addr:housenumber":"7670",
    "addr:postcode":"n8t 1e9",
    "addr:street":"Tecumseh Rd E",
    "iso:country":"CA",
    "sg:address":"7670 Tecumseh Rd E",
    "sg:city":"Windsor",
    "sg:classifiers":[
        {
            "category":"Personal",
            "type":"Services"
        }
    ],
    "sg:phone":"+1 519 974 6518",
    "sg:postcode":"N8T 1E9",
    "sg:province":"ON",
    "sg:tags":[
        "program",
        "physical",
        "exercise",
        "fitness"
    ],
    "wof:name":"Good Life Fitness Clubs",
    "wof:placetype":"venue"
},
  "geometry": {"coordinates":[-82.9347915649,42.3138198853],"type":"Point"}
}