{
  "type": "Feature",
  "properties": {
    "addr:full":"Orillia ON L3V 5X8",
    "addr:postcode":"l3v 5x8",
    "iso:country":"CA",
    "sg:city":"Orillia",
    "sg:classifiers":[
        {
            "category":"Food & Beverages",
            "subcategory":"Bakery",
            "type":"Retail Goods"
        }
    ],
    "sg:phone":"+1 705 325 6644",
    "sg:postcode":"L3V 5X8",
    "sg:province":"ON",
    "sg:tags":[
        "doughnut"
    ],
    "wof:name":"Donut Line",
    "wof:placetype":"venue"
},
  "geometry": {"coordinates":[-79.42436218260001,44.5976676941],"type":"Point"}
}