{
  "type": "Feature",
  "properties": {
    "addr:full":"North York ON M3A 1B2",
    "addr:postcode":"m3a 1b2",
    "iso:country":"CA",
    "sg:city":"North York",
    "sg:classifiers":[
        {
            "category":"Wholesale",
            "subcategory":"Construction Materials",
            "type":"Manufacturing & Wholesale Goods"
        }
    ],
    "sg:phone":"+1 416 445 2093",
    "sg:postcode":"M3A 1B2",
    "sg:province":"ON",
    "sg:tags":[
        "marble"
    ],
    "wof:name":"Marble Renewal",
    "wof:placetype":"venue"
},
  "geometry": {"coordinates":[-79.324715,43.735634],"type":"Point"}
}