{
  "type": "Feature",
  "properties": {
    "addr:full":"2773 5th Ave E Vancouver BC V5M 1N3",
    "addr:housenumber":"2773",
    "addr:postcode":"v5m 1n3",
    "addr:street":"5Th Ave E",
    "iso:country":"CA",
    "sg:address":"2773 5th Ave E",
    "sg:city":"Vancouver",
    "sg:classifiers":[
        {
            "category":"Retail",
            "subcategory":"Repair Shop",
            "type":"Services"
        }
    ],
    "sg:phone":"+1 604 254 8729",
    "sg:postcode":"V5M 1N3",
    "sg:province":"BC",
    "sg:tags":[
        "appliance"
    ],
    "wof:name":"Standard Refrigeration Appl",
    "wof:placetype":"venue"
},
  "geometry": {"coordinates":[-123.047790527,49.2659301758],"type":"Point"}
}