{
  "type": "Feature",
  "properties": {
    "addr:full":"6421 Boul Saint-Laurent Montreal QC H2S 3C3",
    "addr:housenumber":"6421",
    "addr:postcode":"h2s 3c3",
    "addr:street":"Boul Saint-Laurent",
    "iso:country":"CA",
    "sg:address":"6421 Boul Saint-Laurent",
    "sg:city":"Montreal",
    "sg:classifiers":[
        {
            "category":"Shopping",
            "subcategory":"Gifts & Souvenirs",
            "type":"Retail Goods"
        }
    ],
    "sg:phone":"+1 514 270 4141",
    "sg:postcode":"H2S 3C3",
    "sg:province":"QC",
    "sg:tags":[
        "party",
        "supply",
        "furniture"
    ],
    "wof:name":"Meubles Santini Inc",
    "wof:placetype":"venue"
},
  "geometry": {"coordinates":[-73.60810089109999,45.5302047729],"type":"Point"}
}