{
  "type": "Feature",
  "properties": {
    "addr:full":"470 Edmonton Ave Penticton BC V2A 2H2",
    "addr:housenumber":"470",
    "addr:postcode":"v2a 2h2",
    "addr:street":"Edmonton Ave",
    "iso:country":"CA",
    "sg:address":"470 Edmonton Ave",
    "sg:city":"Penticton",
    "sg:classifiers":[
        {
            "category":"Social Services",
            "subcategory":"Child Care",
            "type":"Services"
        }
    ],
    "sg:phone":"+1 250 492 4616",
    "sg:postcode":"V2A 2H2",
    "sg:province":"BC",
    "wof:name":"Penticton After-School Program",
    "wof:placetype":"venue"
},
  "geometry": {"coordinates":[-119.582237244,49.4901924133],"type":"Point"}
}