{
  "type": "Feature",
  "properties": {
    "addr:full":"904 Ontario Rd Welland ON L3B 5E3",
    "addr:housenumber":"904",
    "addr:postcode":"l3b 5e3",
    "addr:street":"Ontario Rd",
    "iso:country":"CA",
    "sg:address":"904 Ontario Rd",
    "sg:city":"Welland",
    "sg:classifiers":[
        {
            "category":"Restaurant",
            "type":"Food & Drink"
        }
    ],
    "sg:phone":"+1 905 735 6221",
    "sg:postcode":"L3B 5E3",
    "sg:province":"ON",
    "wof:name":"Canton House",
    "wof:placetype":"venue"
},
  "geometry": {"coordinates":[-79.23786200000001,42.974464],"type":"Point"}
}