{
  "type": "Feature",
  "properties": {
    "addr:full":"370 Mooney Ave Thunder Bay ON P7B 5R4",
    "addr:housenumber":"370",
    "addr:postcode":"p7b 5r4",
    "addr:street":"Mooney Ave",
    "iso:country":"CA",
    "sg:address":"370 Mooney Ave",
    "sg:city":"Thunder Bay",
    "sg:classifiers":[
        {
            "category":"Manufacturing",
            "subcategory":"Rubber & Plastics",
            "type":"Manufacturing & Wholesale Goods"
        }
    ],
    "sg:phone":"+1 807 345 2549",
    "sg:postcode":"P7B 5R4",
    "sg:province":"ON",
    "sg:tags":[
        "conveying",
        "conveyor",
        "equipment"
    ],
    "wof:name":"Rematech Industries",
    "wof:placetype":"venue"
},
  "geometry": {"coordinates":[-89.2386169434,48.4085006714],"type":"Point"}
}