{
  "type": "Feature",
  "properties": {
    "iso:country":"CA",
    "sg:city":"Prime Brook",
    "sg:classifiers":[
        {
            "category":"Retail",
            "subcategory":"Repair Shop",
            "type":"Services"
        }
    ],
    "sg:phone":"+1 902 562 0902",
    "sg:postcode":"B1L 1G1",
    "sg:province":"NS",
    "sg:tags":[
        "sharpening"
    ],
    "wof:name":"Pride Sharpening Ctr",
    "wof:placetype":"venue"
},
  "geometry": {"coordinates":[-60.200848,46.099579],"type":"Point"}
}