{
  "type": "Feature",
  "properties": {
    "addr:full":"946 Brunette Ave Coquitlam BC V3K 1C9",
    "addr:housenumber":"946",
    "addr:postcode":"v3k 1c9",
    "addr:street":"Brunette Ave",
    "iso:country":"CA",
    "sg:address":"946 Brunette Ave",
    "sg:city":"Coquitlam",
    "sg:classifiers":[
        {
            "category":"Restaurant",
            "type":"Food & Drink"
        }
    ],
    "sg:phone":"+1 604 525 5351",
    "sg:postcode":"V3K 1C9",
    "sg:province":"BC",
    "wof:name":"Mr Greek Taverna",
    "wof:placetype":"venue"
},
  "geometry": {"coordinates":[-122.869499,49.237122],"type":"Point"}
}