{
  "type": "Feature",
  "properties": {
    "iso:country":"CA",
    "sg:address":"54 Grafton St",
    "sg:city":"Charlottetown",
    "sg:classifiers":[
        {
            "category":"Personal",
            "subcategory":"Beauty Salon",
            "type":"Services"
        }
    ],
    "sg:phone":"+1 902 566 9776",
    "sg:postcode":"C1A 1K7",
    "sg:province":"PE",
    "wof:name":"Vitality Hair & Esthetics",
    "wof:placetype":"venue"
},
  "geometry": {"coordinates":[-63.1292152405,46.2335510254],"type":"Point"}
}