{
  "type": "Feature",
  "properties": {
    "addr:full":"Sault Ste Marie ON P6A 5X8",
    "addr:postcode":"p6a 5x8",
    "iso:country":"CA",
    "sg:city":"Sault Ste Marie",
    "sg:classifiers":[
        {
            "category":"Health Services",
            "subcategory":"Doctor",
            "type":"Services"
        }
    ],
    "sg:phone":"+1 705 759 3339",
    "sg:postcode":"P6A 5X8",
    "sg:province":"ON",
    "sg:tags":[
        "dentist"
    ],
    "wof:name":"Nanne, Michael J DDS",
    "wof:placetype":"venue"
},
  "geometry": {"coordinates":[-84.3371124268,46.5149383545],"type":"Point"}
}