{
  "type": "Feature",
  "properties": {
    "addr:full":"Burnaby BC V5H 3P2",
    "addr:postcode":"v5h 3p2",
    "iso:country":"CA",
    "sg:city":"Burnaby",
    "sg:classifiers":[
        {
            "category":"Health Services",
            "subcategory":"Doctor",
            "type":"Services"
        }
    ],
    "sg:phone":"+1 604 482 6100",
    "sg:postcode":"V5H 3P2",
    "sg:province":"BC",
    "sg:tags":[
        "physician",
        "surgeon"
    ],
    "wof:name":"Jones, David W MD",
    "wof:placetype":"venue"
},
  "geometry": {"coordinates":[-122.988747,49.225719],"type":"Point"}
}