{
  "type": "Feature",
  "properties": {
    "iso:country":"CA",
    "sg:address":"1584 Broughton Blvd",
    "sg:city":"Port Mcneill",
    "sg:classifiers":[
        {
            "category":"Shopping",
            "subcategory":"Pharmacy",
            "type":"Retail Goods"
        }
    ],
    "sg:phone":"+1 250 956 3126",
    "sg:postcode":"V0N 2R0",
    "sg:province":"BC",
    "wof:name":"Peoples Drug Mart",
    "wof:placetype":"venue"
},
  "geometry": {"coordinates":[-127.08678436300001,50.5895767212],"type":"Point"}
}