{
  "type": "Feature",
  "properties": {
    "iso:country":"CA",
    "sg:address":"17 Rue Sainte-Catherine E",
    "sg:city":"Montreal",
    "sg:classifiers":[
        {
            "category":"Shopping",
            "subcategory":"Clothing, Apparel, & Fashions",
            "type":"Retail Goods"
        }
    ],
    "sg:phone":"+1 514 842 9559",
    "sg:postcode":"H2X 1K3",
    "sg:province":"QC",
    "sg:tags":[
        "poster"
    ],
    "wof:name":"Rock",
    "wof:placetype":"venue"
},
  "geometry": {"coordinates":[-73.563812,45.510117],"type":"Point"}
}