{
  "type": "Feature",
  "properties": {
    "addr:full":"Belleville ON K8N 4Z5",
    "addr:postcode":"k8n 4z5",
    "iso:country":"CA",
    "sg:city":"Belleville",
    "sg:phone":"+1 613 968 2900",
    "sg:postcode":"K8N 4Z5",
    "sg:province":"ON",
    "sg:tags":[
        "oil"
    ],
    "wof:name":"Stan Fergusson Fuels Ltd",
    "wof:placetype":"venue"
},
  "geometry": {"coordinates":[-77.436066,44.157688],"type":"Point"}
}