{
  "type": "Feature",
  "properties": {
    "addr:full":"Chilliwack BC V2R 3N4",
    "addr:postcode":"v2r 3n4",
    "iso:country":"CA",
    "sg:city":"Chilliwack",
    "sg:classifiers":[
        {
            "category":"Personal",
            "subcategory":"Tanning Parlor",
            "type":"Services"
        }
    ],
    "sg:phone":"+1 604 858 8400",
    "sg:postcode":"V2R 3N4",
    "sg:province":"BC",
    "sg:tags":[
        "salon"
    ],
    "wof:name":"Tropicana Tanning Studios Ltd",
    "wof:placetype":"venue"
},
  "geometry": {"coordinates":[-121.960472,49.106617],"type":"Point"}
}