{
  "type": "Feature",
  "properties": {
    "addr:full":"242 Manitoba Ave Selkirk MB R1A 0Y5",
    "addr:housenumber":"242",
    "addr:postcode":"r1a 0y5",
    "addr:street":"Manitoba Ave",
    "iso:country":"CA",
    "sg:address":"242 Manitoba Ave",
    "sg:city":"Selkirk",
    "sg:classifiers":[
        {
            "category":"Social Services",
            "type":"Services"
        }
    ],
    "sg:phone":"+1 204 482 3536",
    "sg:postcode":"R1A 0Y5",
    "sg:province":"MB",
    "sg:tags":[
        "counselor",
        "marriage",
        "family"
    ],
    "wof:name":"Selkirk & Interlake Mental",
    "wof:placetype":"venue"
},
  "geometry": {"coordinates":[-96.870789,50.144199],"type":"Point"}
}