{
  "type": "Feature",
  "properties": {
    "addr:full":"North York ON M6M 5G3",
    "addr:postcode":"m6m 5g3",
    "iso:country":"CA",
    "sg:city":"North York",
    "sg:classifiers":[
        {
            "category":"Building & Trades",
            "subcategory":"Construction",
            "type":"Services"
        }
    ],
    "sg:phone":"+1 416 769 6545",
    "sg:postcode":"M6M 5G3",
    "sg:province":"ON",
    "sg:tags":[
        "general",
        "contractor"
    ],
    "wof:name":"Bemocon Contracting Ltd",
    "wof:placetype":"venue"
},
  "geometry": {"coordinates":[-79.4936904907,43.6939125061],"type":"Point"}
}