{
  "type": "Feature",
  "properties": {
    "addr:full":"60 Rue Des Pionniers Saint-Charles-Borromee QC J6E 7Y8",
    "addr:housenumber":"60",
    "addr:postcode":"j6e 7y8",
    "addr:street":"Rue Des Pionniers Saint-Charles-Borromee",
    "iso:country":"CA",
    "sg:address":"60 Rue Des Pionniers",
    "sg:city":"Saint-Charles-Borromee",
    "sg:classifiers":[
        {
            "category":"Retail",
            "subcategory":"Veterinary Services",
            "type":"Services"
        }
    ],
    "sg:phone":"+1 450 759 2635",
    "sg:postcode":"J6E 7Y8",
    "sg:province":"QC",
    "sg:tags":[
        "veterinarian"
    ],
    "wof:name":"Clinique Veterinaire Delorme",
    "wof:placetype":"venue"
},
  "geometry": {"coordinates":[-73.475440979,46.0682106018],"type":"Point"}
}