{
  "type": "Feature",
  "properties": {
    "addr:full":"1805 8th Ave # 100 Regina SK S4R 1E8",
    "addr:housenumber":"1805",
    "addr:postcode":"s4r 1e8",
    "addr:street":"8Th Ave # 100",
    "iso:country":"CA",
    "sg:address":"1805 8th Ave # 100",
    "sg:city":"Regina",
    "sg:classifiers":[
        {
            "category":"Organizations",
            "subcategory":"Professional Association",
            "type":"Services"
        }
    ],
    "sg:phone":"+1 306 780 9412",
    "sg:postcode":"S4R 1E8",
    "sg:province":"SK",
    "wof:name":"Bowling Fdrtn of Saskatchewan",
    "wof:placetype":"venue"
},
  "geometry": {"coordinates":[-104.606827,50.456619],"type":"Point"}
}