{
  "type": "Feature",
  "properties": {
    "addr:full":"441 Rolla Rd Rolla BC V0C 2G0",
    "addr:housenumber":"441",
    "addr:postcode":"bc v0c 2g0",
    "addr:street":"Rolla Rd",
    "iso:country":"CA",
    "sg:address":"441 Rolla Rd",
    "sg:city":"Rolla",
    "sg:classifiers":[
        {
            "category":"Recreation",
            "type":"Entertainment"
        }
    ],
    "sg:phone":"+1 250 759 4710",
    "sg:postcode":"V0C 2G0",
    "sg:province":"BC",
    "sg:tags":[
        "hall",
        "auditorium"
    ],
    "wof:name":"Doe River Community Hall",
    "wof:placetype":"venue"
},
  "geometry": {"coordinates":[-120.14048,55.897495],"type":"Point"}
}