{
  "type": "Feature",
  "properties": {
    "addr:full":"12200 1st Ave Richmond BC V7E 3M2",
    "addr:housenumber":"12200",
    "addr:postcode":"v7e 3m2",
    "addr:street":"1St Ave",
    "iso:country":"CA",
    "sg:address":"12200 1st Ave",
    "sg:city":"Richmond",
    "sg:classifiers":[
        {
            "category":"Wholesale",
            "subcategory":"Hardware",
            "type":"Manufacturing & Wholesale Goods"
        }
    ],
    "sg:phone":"+1 604 271 9222",
    "sg:postcode":"V7E 3M2",
    "sg:province":"BC",
    "sg:tags":[
        "dust",
        "collecting",
        "system"
    ],
    "wof:name":"NU-Tech Systems Ltd",
    "wof:placetype":"venue"
},
  "geometry": {"coordinates":[-123.182571411,49.1247406006],"type":"Point"}
}