{
  "type": "Feature",
  "properties": {
    "addr:full":"11739 83 St NW Edmonton AB T5B 2Z1",
    "addr:housenumber":"11739",
    "addr:postcode":"t5b 2z1",
    "addr:street":"83 St Nw",
    "iso:country":"CA",
    "sg:address":"11739 83 St NW",
    "sg:city":"Edmonton",
    "sg:classifiers":[
        {
            "category":"Restaurant",
            "type":"Food & Drink"
        }
    ],
    "sg:phone":"+1 780 474 4059",
    "sg:postcode":"T5B 2Z1",
    "sg:province":"AB",
    "wof:name":"Maria's Place",
    "wof:placetype":"venue"
},
  "geometry": {"coordinates":[-113.468582153,53.5695152283],"type":"Point"}
}