{
  "type": "Feature",
  "properties": {
    "iso:country":"CA",
    "sg:address":"7920 18E Av",
    "sg:city":"Montreal",
    "sg:classifiers":[
        {
            "category":"Retail",
            "subcategory":"Auto Repair",
            "type":"Services"
        }
    ],
    "sg:phone":"+1 514 728 6621",
    "sg:postcode":"H1Z 3R8",
    "sg:province":"QC",
    "sg:tags":[
        "repairing",
        "automobile"
    ],
    "wof:name":"Garage Quatre Saisons",
    "wof:placetype":"venue"
},
  "geometry": {"coordinates":[-73.6036148071,45.5681533813],"type":"Point"}
}