{
  "type": "Feature",
  "properties": {
    "addr:full":"Burnaby BC V5E 4M7",
    "addr:postcode":"v5e 4m7",
    "iso:country":"CA",
    "sg:city":"Burnaby",
    "sg:classifiers":[
        {
            "category":"Recreation",
            "type":"Entertainment"
        }
    ],
    "sg:phone":"+1 604 777 7200",
    "sg:postcode":"V5E 4M7",
    "sg:province":"BC",
    "sg:tags":[
        "center"
    ],
    "wof:name":"Intercultural Action Society",
    "wof:placetype":"venue"
},
  "geometry": {"coordinates":[-122.964614868,49.2178840637],"type":"Point"}
}