{
  "type": "Feature",
  "properties": {
    "addr:full":"New Minas NS B4N 3N2",
    "addr:postcode":"b4n 3n2",
    "iso:country":"CA",
    "sg:city":"New Minas",
    "sg:classifiers":[
        {
            "category":"Health Services",
            "subcategory":"Health Practitioner",
            "type":"Services"
        }
    ],
    "sg:phone":"+1 902 681 0235",
    "sg:postcode":"B4N 3N2",
    "sg:province":"NS",
    "sg:tags":[
        "psychologist"
    ],
    "wof:name":"Boyd & Pick Psychological Svc",
    "wof:placetype":"venue"
},
  "geometry": {"coordinates":[-64.449913,45.068405],"type":"Point"}
}