{
  "type": "Feature",
  "properties": {
    "iso:country":"CA",
    "sg:address":"3001 Rue Sherbrooke O # 103",
    "sg:city":"Montreal",
    "sg:classifiers":[
        {
            "category":"Real Estate",
            "subcategory":"Real Estate Operator",
            "type":"Services"
        }
    ],
    "sg:phone":"+1 514 939 1990",
    "sg:postcode":"H3Z 2X8",
    "sg:province":"QC",
    "sg:tags":[
        "condominium"
    ],
    "wof:name":"Condominium Le Barat",
    "wof:placetype":"venue"
},
  "geometry": {"coordinates":[-73.5586929321,45.5412559509],"type":"Point"}
}