{
  "type": "Feature",
  "properties": {
    "addr:full":"80 Cottage Lane Harvey York CO NB E6K 3H5",
    "addr:housenumber":"80",
    "addr:postcode":"e6k 3h5",
    "addr:street":"Cottage Lane Harvey",
    "iso:country":"CA",
    "sg:address":"80 Cottage Lane",
    "sg:city":"Harvey York CO",
    "sg:classifiers":[
        {
            "category":"Building & Trades",
            "subcategory":"Construction",
            "type":"Services"
        }
    ],
    "sg:phone":"+1 506 260 3366",
    "sg:postcode":"E6K 3H5",
    "sg:province":"NB",
    "sg:tags":[
        "roofing",
        "contractor",
        "general"
    ],
    "wof:name":"Roof Doctor",
    "wof:placetype":"venue"
},
  "geometry": {"coordinates":[-66.61339599999999,46.13475],"type":"Point"}
}