{
  "type": "Feature",
  "properties": {
    "addr:full":"Kelowna BC V1Y 9S9",
    "addr:postcode":"v1y 9s9",
    "iso:country":"CA",
    "sg:city":"Kelowna",
    "sg:classifiers":[
        {
            "category":"Health Services",
            "subcategory":"Doctor",
            "type":"Services"
        }
    ],
    "sg:phone":"+1 250 868 0700",
    "sg:postcode":"V1Y 9S9",
    "sg:province":"BC",
    "sg:tags":[
        "physician",
        "clinic",
        "surgeon"
    ],
    "wof:name":"Millcreek Family Medicine",
    "wof:placetype":"venue"
},
  "geometry": {"coordinates":[-119.453186035,49.8842887878],"type":"Point"}
}