{
  "type": "Feature",
  "properties": {
    "addr:full":"1310 Railway Ave Canmore AB T1W 1P6",
    "addr:housenumber":"1310",
    "addr:postcode":"t1w 1p6",
    "addr:street":"Railway Ave",
    "iso:country":"CA",
    "sg:address":"1310 Railway Ave",
    "sg:city":"Canmore",
    "sg:classifiers":[
        {
            "category":"Home & Garden",
            "subcategory":"Furniture",
            "type":"Retail Goods"
        }
    ],
    "sg:phone":"+1 403 678 6037",
    "sg:postcode":"T1W 1P6",
    "sg:province":"AB",
    "wof:name":"Castle Mountain Home Frnshngs",
    "wof:placetype":"venue"
},
  "geometry": {"coordinates":[-115.358436584,51.0933303833],"type":"Point"}
}