{
  "type": "Feature",
  "properties": {
    "addr:full":"Chilliwack BC V2P 4P3",
    "addr:postcode":"v2p 4p3",
    "iso:country":"CA",
    "sg:city":"Chilliwack",
    "sg:classifiers":[
        {
            "category":"Education",
            "subcategory":"Special Training",
            "type":"Public Place"
        }
    ],
    "sg:phone":"+1 604 795 2205",
    "sg:postcode":"V2P 4P3",
    "sg:province":"BC",
    "sg:tags":[
        "school",
        "instruction",
        "driving"
    ],
    "wof:name":"Young Drivers of Canada",
    "wof:placetype":"venue"
},
  "geometry": {"coordinates":[-121.952575684,49.1592941284],"type":"Point"}
}