{
  "type": "Feature",
  "properties": {
    "iso:country":"CA",
    "sg:address":"34 Roy's Sq",
    "sg:city":"Toronto",
    "sg:classifiers":[
        {
            "category":"Restaurant",
            "type":"Food & Drink"
        }
    ],
    "sg:phone":"+1 416 920 9127",
    "sg:postcode":"M4Y 2W2",
    "sg:province":"ON",
    "wof:name":"Roy's Garden",
    "wof:placetype":"venue"
},
  "geometry": {"coordinates":[-79.38591003419999,43.6699333191],"type":"Point"}
}