{
  "type": "Feature",
  "properties": {
    "addr:full":"3111 Dufferin St North York ON M6A 2S7",
    "addr:housenumber":"3111",
    "addr:postcode":"m6a 2s7",
    "addr:street":"Dufferin St",
    "iso:country":"CA",
    "sg:address":"3111 Dufferin St",
    "sg:city":"North York",
    "sg:classifiers":[
        {
            "category":"Shopping",
            "subcategory":"Computers & Home Electronics",
            "type":"Retail Goods"
        }
    ],
    "sg:phone":"+1 416 781 6103",
    "sg:postcode":"M6A 2S7",
    "sg:province":"ON",
    "sg:tags":[
        "television",
        "radio"
    ],
    "wof:name":"Stewart Tv & Video",
    "wof:placetype":"venue"
},
  "geometry": {"coordinates":[-79.45491800000001,43.716],"type":"Point"}
}