{
  "type": "Feature",
  "properties": {
    "addr:full":"New Westminster BC V3M 1X2",
    "addr:postcode":"v3m 1x2",
    "iso:country":"CA",
    "sg:city":"New Westminster",
    "sg:classifiers":[
        {
            "category":"Social Services",
            "subcategory":"Child Care",
            "type":"Services"
        }
    ],
    "sg:phone":"+1 604 540 1122",
    "sg:postcode":"V3M 1X2",
    "sg:province":"BC",
    "wof:name":"Size Small Child Care Ctr",
    "wof:placetype":"venue"
},
  "geometry": {"coordinates":[-122.929749,49.20462],"type":"Point"}
}