{
  "type": "Feature",
  "properties": {
    "addr:full":"Richmond BC V6X 2R2",
    "addr:postcode":"v6x 2r2",
    "iso:country":"CA",
    "sg:city":"Richmond",
    "sg:classifiers":[
        {
            "category":"Building & Trades",
            "subcategory":"Construction",
            "type":"Services"
        }
    ],
    "sg:phone":"+1 604 279 8838",
    "sg:postcode":"V6X 2R2",
    "sg:province":"BC",
    "sg:tags":[
        "repairing",
        "remodeling",
        "contractor"
    ],
    "wof:name":"Elegant Flooring",
    "wof:placetype":"venue"
},
  "geometry": {"coordinates":[-123.099174499,49.1960868835],"type":"Point"}
}