{
  "type": "Feature",
  "properties": {
    "addr:full":"Castor AB T0C 0X0",
    "addr:postcode":"t0c 0x0",
    "iso:country":"CA",
    "sg:city":"Castor",
    "sg:classifiers":[
        {
            "category":"Health Services",
            "subcategory":"Doctor",
            "type":"Services"
        }
    ],
    "sg:phone":"+1 403 882 3320",
    "sg:postcode":"T0C 0X0",
    "sg:province":"AB",
    "sg:tags":[
        "dentist"
    ],
    "wof:name":"Simpson, Karen M DDS",
    "wof:placetype":"venue"
},
  "geometry": {"coordinates":[-111.904037476,52.2185440063],"type":"Point"}
}