{
  "type": "Feature",
  "properties": {
    "addr:full":"8203 Boul Montreal-Toronto Montreal-Ouest QC H4X 1N1",
    "addr:housenumber":"8203",
    "addr:postcode":"h4x 1n1",
    "addr:street":"Boul Montreal-Toronto Montreal-Ouest",
    "iso:country":"CA",
    "sg:address":"8203 Boul Montreal-Toronto",
    "sg:city":"Montreal-Ouest",
    "sg:classifiers":[
        {
            "category":"Shopping",
            "subcategory":"Stationery & Office Supplies",
            "type":"Retail Goods"
        }
    ],
    "sg:phone":"+1 514 368 8641",
    "sg:postcode":"H4X 1N1",
    "sg:province":"QC",
    "wof:name":"Crites & Riddell Inc",
    "wof:placetype":"venue"
},
  "geometry": {"coordinates":[-73.638687,45.448154],"type":"Point"}
}