{
  "type": "Feature",
  "properties": {
    "addr:full":"9653 Ch Cote-DE-Liesse Dorval QC H9P 1A3",
    "addr:postcode":"9653;h9p 1a3",
    "addr:street":"Ch Cote-De-Liesse",
    "iso:country":"CA",
    "sg:address":"9653 Ch Cote-DE-Liesse",
    "sg:city":"Dorval",
    "sg:classifiers":[
        {
            "category":"Manufacturing",
            "subcategory":"Paper Products",
            "type":"Manufacturing & Wholesale Goods"
        }
    ],
    "sg:phone":"+1 514 631 5600",
    "sg:postcode":"H9P 1A3",
    "sg:province":"QC",
    "sg:tags":[
        "packaging",
        "material"
    ],
    "wof:name":"Emballages Esquire Canada Inc",
    "wof:placetype":"venue"
},
  "geometry": {"coordinates":[-73.7137145996,45.4695358276],"type":"Point"}
}