{
  "type": "Feature",
  "properties": {
    "iso:country":"CA",
    "sg:address":"1 Sawmill Rd",
    "sg:city":"Geraldton",
    "sg:classifiers":[
        {
            "category":"Retail",
            "subcategory":"Auto Repair",
            "type":"Services"
        }
    ],
    "sg:phone":"+1 807 854 0484",
    "sg:postcode":"P0T 1M0",
    "sg:province":"ON",
    "sg:tags":[
        "wrecker"
    ],
    "wof:name":"Larry's 24 Hour Towing & Rprs",
    "wof:placetype":"venue"
},
  "geometry": {"coordinates":[-86.9500198364,49.719581604],"type":"Point"}
}