{
  "type": "Feature",
  "properties": {
    "iso:country":"CA",
    "sg:address":"285 Duke St",
    "sg:city":"Miramichi",
    "sg:classifiers":[
        {
            "category":"Home & Garden",
            "subcategory":"Household Appliances",
            "type":"Retail Goods"
        }
    ],
    "sg:phone":"+1 506 773 3389",
    "sg:postcode":"E1N 1J9",
    "sg:province":"NB",
    "wof:name":"J & J Appliance Sales & Svc",
    "wof:placetype":"venue"
},
  "geometry": {"coordinates":[-65.46105957029999,47.0356445312],"type":"Point"}
}