{
  "type": "Feature",
  "properties": {
    "addr:full":"1140 155E Rue Saint-Georges QC G5Y 7W2",
    "addr:housenumber":"1140",
    "addr:postcode":"g5y 7w2",
    "addr:street":"155E Rue",
    "iso:country":"CA",
    "sg:address":"1140 155E Rue",
    "sg:city":"Saint-Georges",
    "sg:classifiers":[
        {
            "category":"Personal",
            "subcategory":"Beauty Salon",
            "type":"Services"
        }
    ],
    "sg:phone":"+1 418 227 4420",
    "sg:postcode":"G5Y 7W2",
    "sg:province":"QC",
    "wof:name":"Salon D'Esthetique H Paquet",
    "wof:placetype":"venue"
},
  "geometry": {"coordinates":[-70.67115020750001,46.1233482361],"type":"Point"}
}