{
  "type": "Feature",
  "properties": {
    "addr:full":"Scarborough ON M1V 4P2",
    "addr:postcode":"m1v 4p2",
    "iso:country":"CA",
    "sg:city":"Scarborough",
    "sg:classifiers":[
        {
            "category":"Shopping",
            "type":"Retail Goods"
        }
    ],
    "sg:phone":"+1 416 299 9296",
    "sg:postcode":"M1V 4P2",
    "sg:province":"ON",
    "sg:tags":[
        "cosmetic",
        "perfume"
    ],
    "wof:name":"My's Health & Beauty",
    "wof:placetype":"venue"
},
  "geometry": {"coordinates":[-79.27699279789999,43.826625824],"type":"Point"}
}