{
  "type": "Feature",
  "properties": {
    "addr:full":"402 Richards St W Nelson BC V1L 3K3",
    "addr:housenumber":"402",
    "addr:postcode":"bc v1l 3k3",
    "addr:street":"Richards St W",
    "iso:country":"CA",
    "sg:address":"402 Richards St W",
    "sg:city":"Nelson",
    "sg:classifiers":[
        {
            "category":"Organizations",
            "subcategory":"Religious Organization",
            "type":"Services"
        }
    ],
    "sg:phone":"+1 250 352 6921",
    "sg:postcode":"V1L 3K3",
    "sg:province":"BC",
    "sg:tags":[
        "church"
    ],
    "wof:name":"Chancery Office",
    "wof:placetype":"venue"
},
  "geometry": {"coordinates":[-117.296753,49.480297],"type":"Point"}
}