{
  "type": "Feature",
  "properties": {
    "addr:full":"47 Av Plamondon Drummondville QC J2C 3V7",
    "addr:postcode":"j2c 3v7",
    "addr:street":"47 Av Plamondon",
    "iso:country":"CA",
    "sg:address":"47 Av Plamondon",
    "sg:city":"Drummondville",
    "sg:classifiers":[
        {
            "category":"Professional",
            "subcategory":"Business Services",
            "type":"Services"
        }
    ],
    "sg:phone":"+1 819 472 5615",
    "sg:postcode":"J2C 3V7",
    "sg:province":"QC",
    "sg:tags":[
        "notary"
    ],
    "wof:name":"Sylvestre, Andre",
    "wof:placetype":"venue"
},
  "geometry": {"coordinates":[-72.49957999999999,45.887787],"type":"Point"}
}