{
  "type": "Feature",
  "properties": {
    "addr:full":"Sechelt BC V0N 3A1",
    "addr:postcode":"v0n 3a1",
    "iso:country":"CA",
    "sg:city":"Sechelt",
    "sg:classifiers":[
        {
            "category":"Wholesale",
            "subcategory":"Electrical",
            "type":"Manufacturing & Wholesale Goods"
        }
    ],
    "sg:phone":"+1 604 740 8855",
    "sg:postcode":"V0N 3A1",
    "sg:province":"BC",
    "sg:tags":[
        "equipment",
        "electric",
        "supply"
    ],
    "wof:name":"Eecol Electric Inc",
    "wof:placetype":"venue"
},
  "geometry": {"coordinates":[-123.711197,49.449326],"type":"Point"}
}