{
  "type": "Feature",
  "properties": {
    "addr:full":"750 Oklahoma Dr Pickering ON L1W 3G9",
    "addr:housenumber":"750",
    "addr:postcode":"l1w 3g9",
    "addr:street":"Oklahoma Dr",
    "iso:country":"CA",
    "sg:address":"750 Oklahoma Dr",
    "sg:city":"Pickering",
    "sg:classifiers":[
        {
            "category":"Banks & Credit Unions",
            "subcategory":"Bank",
            "type":"Services"
        }
    ],
    "sg:phone":"+1 905 420 8855",
    "sg:postcode":"L1W 3G9",
    "sg:province":"ON",
    "wof:name":"Td Canada Trust",
    "wof:placetype":"venue"
},
  "geometry": {"coordinates":[-79.11029052729999,43.8123168945],"type":"Point"}
}