{
  "type": "Feature",
  "properties": {
    "addr:full":"140 Allstate Pky Markham ON L3R 5Y8",
    "addr:housenumber":"140",
    "addr:postcode":"l3r 5y8",
    "addr:street":"Allstate Pky",
    "iso:country":"CA",
    "sg:address":"140 Allstate Pky",
    "sg:city":"Markham",
    "sg:classifiers":[
        {
            "category":"Insurance",
            "subcategory":"Insurance Agent",
            "type":"Services"
        }
    ],
    "sg:phone":"+1 905 470 1414",
    "sg:postcode":"L3R 5Y8",
    "sg:province":"ON",
    "wof:name":"Avemco Insurance CO",
    "wof:placetype":"venue"
},
  "geometry": {"coordinates":[-79.3687591553,43.8554039001],"type":"Point"}
}