{
  "type": "Feature",
  "properties": {
    "addr:full":"1548 Strasburg Rd Kitchener ON N2R 1E9",
    "addr:housenumber":"1548",
    "addr:postcode":"n2r 1e9",
    "addr:street":"Strasburg Rd",
    "iso:country":"CA",
    "sg:address":"1548 Strasburg Rd",
    "sg:city":"Kitchener",
    "sg:classifiers":[
        {
            "category":"Home & Garden",
            "subcategory":"Furniture",
            "type":"Retail Goods"
        }
    ],
    "sg:phone":"+1 519 748 4928",
    "sg:postcode":"N2R 1E9",
    "sg:province":"ON",
    "sg:tags":[
        "equipment",
        "kitchen",
        "cabinet"
    ],
    "wof:name":"Formatop Manufacturing CO Ltd",
    "wof:placetype":"venue"
},
  "geometry": {"coordinates":[-80.4677734375,43.3999900818],"type":"Point"}
}