{
  "type": "Feature",
  "properties": {
    "addr:full":"Castlegar BC V1N 2K6",
    "addr:postcode":"v1n 2k6",
    "iso:country":"CA",
    "sg:city":"Castlegar",
    "sg:classifiers":[
        {
            "category":"Manufacturing",
            "subcategory":"Lumber",
            "type":"Manufacturing & Wholesale Goods"
        }
    ],
    "sg:phone":"+1 250 365 1181",
    "sg:postcode":"V1N 2K6",
    "sg:province":"BC",
    "sg:tags":[
        "forester"
    ],
    "wof:name":"Aurora Resource Consulting Ltd",
    "wof:placetype":"venue"
},
  "geometry": {"coordinates":[-117.659729,49.310329],"type":"Point"}
}