{
  "type": "Feature",
  "properties": {
    "iso:country":"CA",
    "sg:city":"Kamloops",
    "sg:classifiers":[
        {
            "category":"Shopping",
            "subcategory":"Shoes",
            "type":"Retail Goods"
        }
    ],
    "sg:phone":"+1 250 377 4055",
    "sg:postcode":"V2E 2R7",
    "sg:province":"BC",
    "wof:name":"Runners' Sole",
    "wof:placetype":"venue"
},
  "geometry": {"coordinates":[-120.377082825,50.6544952393],"type":"Point"}
}