{
  "type": "Feature",
  "properties": {
    "addr:full":"1161 Route 776 Grand Manan NB E5G 4E9",
    "addr:housenumber":"1161",
    "addr:postcode":"e5g 4e9",
    "addr:street":"Route 776",
    "iso:country":"CA",
    "sg:address":"1161 Route 776",
    "sg:city":"Grand Manan",
    "sg:classifiers":[
        {
            "category":"Home & Garden",
            "subcategory":"Hardware",
            "type":"Retail Goods"
        }
    ],
    "sg:phone":"+1 506 662 8441",
    "sg:postcode":"E5G 4E9",
    "sg:province":"NB",
    "wof:name":"Home Hardware",
    "wof:placetype":"venue"
},
  "geometry": {"coordinates":[-66.84721374510001,44.6484527588],"type":"Point"}
}