{
  "type": "Feature",
  "properties": {
    "addr:full":"Victoria BC V8R 2L8",
    "addr:postcode":"v8r 2l8",
    "iso:country":"CA",
    "sg:city":"Victoria",
    "sg:classifiers":[
        {
            "category":"Real Estate",
            "subcategory":"Real Estate Agent",
            "type":"Services"
        }
    ],
    "sg:phone":"+1 250 595 2181",
    "sg:postcode":"V8R 2L8",
    "sg:province":"BC",
    "sg:tags":[
        "management"
    ],
    "wof:name":"Traveller's Inn",
    "wof:placetype":"venue"
},
  "geometry": {"coordinates":[-123.32876586899999,48.4359207153],"type":"Point"}
}