{
  "type": "Feature",
  "properties": {
    "addr:full":"47 King St N Waterloo ON N2J 2W9",
    "addr:housenumber":"47",
    "addr:postcode":"n2j 2w9",
    "addr:street":"King St N",
    "iso:country":"CA",
    "sg:address":"47 King St N",
    "sg:city":"Waterloo",
    "sg:classifiers":[
        {
            "category":"Wholesale",
            "subcategory":"Jewelry",
            "type":"Manufacturing & Wholesale Goods"
        }
    ],
    "sg:phone":"+1 519 888 1771",
    "sg:postcode":"N2J 2W9",
    "sg:province":"ON",
    "sg:tags":[
        "beads"
    ],
    "wof:name":"Bead Bazaar",
    "wof:placetype":"venue"
},
  "geometry": {"coordinates":[-80.52291099999999,43.466461],"type":"Point"}
}