{
  "type": "Feature",
  "properties": {
    "iso:country":"CA",
    "sg:address":"152 Cree Rd",
    "sg:city":"Sherwood Park",
    "sg:classifiers":[
        {
            "category":"Wholesale",
            "subcategory":"Groceries",
            "type":"Manufacturing & Wholesale Goods"
        }
    ],
    "sg:phone":"+1 780 464 0303",
    "sg:postcode":"T8A 3X8",
    "sg:province":"AB",
    "sg:tags":[
        "baker"
    ],
    "wof:name":"Wow Factor Desserts Ltd",
    "wof:placetype":"venue"
},
  "geometry": {"coordinates":[-113.32939148,53.5374259949],"type":"Point"}
}