{
  "type": "Feature",
  "properties": {
    "addr:full":"1249 West Riverside Dr Perth-Andover NB E7H 5G8",
    "addr:housenumber":"1249",
    "addr:postcode":"e7h 5g8",
    "addr:street":"West Riverside Dr",
    "iso:country":"CA",
    "sg:address":"1249 West Riverside Dr",
    "sg:city":"Perth-Andover",
    "sg:classifiers":[
        {
            "category":"Manufacturing",
            "subcategory":"Tools & Machinery",
            "type":"Manufacturing & Wholesale Goods"
        }
    ],
    "sg:phone":"+1 506 273 3870",
    "sg:postcode":"E7H 5G8",
    "sg:province":"NB",
    "sg:tags":[
        "potato"
    ],
    "wof:name":"Haines New Brunswick Inc",
    "wof:placetype":"venue"
},
  "geometry": {"coordinates":[-67.6969070435,46.7484512329],"type":"Point"}
}