{
  "type": "Feature",
  "properties": {
    "iso:country":"CA",
    "sg:address":"400 Rue Norman",
    "sg:city":"Lachine",
    "sg:classifiers":[
        {
            "category":"Freight",
            "type":"Transportation"
        }
    ],
    "sg:phone":"+1 514 485 3636",
    "sg:postcode":"H8R 1A1",
    "sg:province":"QC",
    "sg:tags":[
        "trucking"
    ],
    "wof:name":"Transport Trans-Action Inc",
    "wof:placetype":"venue"
},
  "geometry": {"coordinates":[-73.663948,45.447857],"type":"Point"}
}