{
  "type": "Feature",
  "properties": {
    "addr:full":"11201 95 St NW Edmonton AB T5G 1K8",
    "addr:housenumber":"11201",
    "addr:postcode":"t5g 1k8",
    "addr:street":"95 St Nw",
    "iso:country":"CA",
    "sg:address":"11201 95 St NW",
    "sg:city":"Edmonton",
    "sg:classifiers":[
        {
            "category":"Restaurant",
            "type":"Food & Drink"
        }
    ],
    "sg:phone":"+1 780 477 3415",
    "sg:postcode":"T5G 1K8",
    "sg:province":"AB",
    "sg:tags":[
        "club"
    ],
    "wof:name":"Odd Fellows Temple",
    "wof:placetype":"venue"
},
  "geometry": {"coordinates":[-113.486908,53.56123],"type":"Point"}
}