{
  "type": "Feature",
  "properties": {
    "addr:full":"10610 Bayview Ave Richmond Hill ON L4C 3N8",
    "addr:housenumber":"10610",
    "addr:postcode":"l4c 3n8",
    "addr:street":"Bayview Ave",
    "iso:country":"CA",
    "sg:address":"10610 Bayview Ave",
    "sg:city":"Richmond Hill",
    "sg:classifiers":[
        {
            "category":"Restaurant",
            "type":"Food & Drink"
        }
    ],
    "sg:phone":"+1 905 787 1177",
    "sg:postcode":"L4C 3N8",
    "sg:province":"ON",
    "sg:tags":[
        "pizza"
    ],
    "wof:name":"Little Caesars Pizza",
    "wof:placetype":"venue"
},
  "geometry": {"coordinates":[-79.419144,43.890228],"type":"Point"}
}