{
  "type": "Feature",
  "properties": {
    "addr:full":"112 3rd St E North Vancouver BC V7L 1E6",
    "addr:housenumber":"112",
    "addr:postcode":"v7l 1e6",
    "addr:street":"3Rd St E",
    "iso:country":"CA",
    "sg:address":"112 3rd St E",
    "sg:city":"North Vancouver",
    "sg:classifiers":[
        {
            "category":"Government",
            "subcategory":"Office",
            "type":"Public Place"
        }
    ],
    "sg:phone":"+1 604 990 7465",
    "sg:postcode":"V7L 1E6",
    "sg:province":"BC",
    "sg:tags":[
        "village"
    ],
    "wof:name":"North Vancouver Lower Lonsdale",
    "wof:placetype":"venue"
},
  "geometry": {"coordinates":[-123.076263428,49.3132896423],"type":"Point"}
}