{
  "type": "Feature",
  "properties": {
    "addr:full":"Princeton BC V0X 1W0",
    "addr:postcode":"v0x 1w0",
    "iso:country":"CA",
    "sg:city":"Princeton",
    "sg:classifiers":[
        {
            "category":"Mining & Drilling",
            "type":"Manufacturing & Wholesale Goods"
        }
    ],
    "sg:phone":"+1 250 295 3376",
    "sg:postcode":"V0X 1W0",
    "sg:province":"BC",
    "sg:tags":[
        "contractor"
    ],
    "wof:name":"Adam Diamond Drilling Ltd",
    "wof:placetype":"venue"
},
  "geometry": {"coordinates":[-120.518707275,49.4529876709],"type":"Point"}
}