{
  "type": "Feature",
  "properties": {
    "addr:full":"236 Clark Dr Vancouver BC V5L 3H3",
    "addr:housenumber":"236",
    "addr:postcode":"v5l 3h3",
    "addr:street":"Clark Dr",
    "iso:country":"CA",
    "sg:address":"236 Clark Dr",
    "sg:city":"Vancouver",
    "sg:classifiers":[
        {
            "category":"Manufacturing",
            "subcategory":"Metals",
            "type":"Manufacturing & Wholesale Goods"
        }
    ],
    "sg:phone":"+1 604 253 2811",
    "sg:postcode":"V5L 3H3",
    "sg:province":"BC",
    "sg:tags":[
        "brass",
        "foundry",
        "bronze"
    ],
    "wof:name":"Hastings Brass Foundry Ltd",
    "wof:placetype":"venue"
},
  "geometry": {"coordinates":[-123.07673645,49.282787323],"type":"Point"}
}