{
  "type": "Feature",
  "properties": {
    "iso:country":"CA",
    "sg:address":"9734 Chemainus Rd",
    "sg:city":"Chemainus",
    "sg:classifiers":[
        {
            "category":"Restaurant",
            "type":"Food & Drink"
        }
    ],
    "sg:phone":"+1 250 246 1101",
    "sg:postcode":"V0R 1K0",
    "sg:province":"BC",
    "wof:name":"Subway Sandwiches & Salads",
    "wof:placetype":"venue"
},
  "geometry": {"coordinates":[-123.71733856199999,48.9208374023],"type":"Point"}
}