{
  "type": "Feature",
  "properties": {
    "iso:country":"CA",
    "sg:address":"9719 384th Ave",
    "sg:city":"Oliver",
    "sg:classifiers":[
        {
            "category":"Education",
            "subcategory":"Special Training",
            "type":"Public Place"
        }
    ],
    "sg:phone":"+1 250 498 6861",
    "sg:postcode":"V0H 1T0",
    "sg:province":"BC",
    "sg:tags":[
        "instruction",
        "driving"
    ],
    "wof:name":"South Okanagan Driving School",
    "wof:placetype":"venue"
},
  "geometry": {"coordinates":[-119.55046081499999,49.182598114],"type":"Point"}
}