{
  "type": "Feature",
  "properties": {
    "addr:full":"75 West St Stephenville NL A2N 1E5",
    "addr:housenumber":"75",
    "addr:postcode":"a2n 1e5",
    "addr:street":"West St",
    "iso:country":"CA",
    "sg:address":"75 West St",
    "sg:city":"Stephenville",
    "sg:classifiers":[
        {
            "category":"Restaurant",
            "type":"Food & Drink"
        }
    ],
    "sg:phone":"+1 709 643 4411",
    "sg:postcode":"A2N 1E5",
    "sg:province":"NL",
    "wof:name":"Golden G Dairy Bar",
    "wof:placetype":"venue"
},
  "geometry": {"coordinates":[-58.591282,48.546555],"type":"Point"}
}