{
  "type": "Feature",
  "properties": {
    "addr:full":"1001 20th Ave Prince George BC V2L 5K2",
    "addr:housenumber":"1001",
    "addr:postcode":"v2l 5k2",
    "addr:street":"20Th Ave",
    "iso:country":"CA",
    "sg:address":"1001 20th Ave",
    "sg:city":"Prince George",
    "sg:classifiers":[
        {
            "category":"Autos & Motor Vehicles",
            "subcategory":"Motorcycle Sales",
            "type":"Retail Goods"
        }
    ],
    "sg:phone":"+1 250 562 4151",
    "sg:postcode":"V2L 5K2",
    "sg:province":"BC",
    "sg:tags":[
        "all",
        "terrain",
        "scooter"
    ],
    "wof:name":"Prince George Yamaha",
    "wof:placetype":"venue"
},
  "geometry": {"coordinates":[-122.742362976,53.9053344727],"type":"Point"}
}