{
  "type": "Feature",
  "properties": {
    "addr:full":"938 Twelfth St New Westminster BC V3M 4K6",
    "addr:housenumber":"938",
    "addr:postcode":"v3m 4k6",
    "addr:street":"Twelfth St",
    "iso:country":"CA",
    "sg:address":"938 Twelfth St",
    "sg:city":"New Westminster",
    "sg:classifiers":[
        {
            "category":"Restaurant",
            "type":"Food & Drink"
        }
    ],
    "sg:phone":"+1 604 526 4432",
    "sg:postcode":"V3M 4K6",
    "sg:province":"BC",
    "wof:name":"Donair House",
    "wof:placetype":"venue"
},
  "geometry": {"coordinates":[-122.937263489,49.2127723694],"type":"Point"}
}