{
  "type": "Feature",
  "properties": {
    "addr:full":"12335 Av Edger Montreal-Nord QC H1G 5A8",
    "addr:postcode":"h1g 5a8",
    "addr:street":"Av Edger",
    "iso:country":"CA",
    "sg:address":"12335 Av Edger",
    "sg:city":"Montreal-Nord",
    "sg:classifiers":[
        {
            "category":"Building & Trades",
            "subcategory":"Construction",
            "type":"Services"
        }
    ],
    "sg:phone":"+1 514 327 1211",
    "sg:postcode":"H1G 5A8",
    "sg:province":"QC",
    "sg:tags":[
        "tile",
        "dealer"
    ],
    "wof:name":"Ceramique Pie Ix Inc",
    "wof:placetype":"venue"
},
  "geometry": {"coordinates":[-73.6349945068,45.6114654541],"type":"Point"}
}