{
  "type": "Feature",
  "properties": {
    "iso:country":"CA",
    "sg:address":"13103 Keele St",
    "sg:city":"King City",
    "sg:classifiers":[
        {
            "category":"Personal",
            "type":"Services"
        }
    ],
    "sg:phone":"+1 905 833 3300",
    "sg:postcode":"L7B 1G1",
    "sg:province":"ON",
    "sg:tags":[
        "therapist",
        "chiropractor",
        "massage"
    ],
    "wof:name":"King Chiropractic Clinic",
    "wof:placetype":"venue"
},
  "geometry": {"coordinates":[-79.5285873413,43.9308395386],"type":"Point"}
}