{
  "type": "Feature",
  "properties": {
    "addr:full":"11221 143 St NW Edmonton AB T5M 3P8",
    "addr:housenumber":"11221",
    "addr:postcode":"t5m 3p8",
    "addr:street":"143 St Nw",
    "iso:country":"CA",
    "sg:address":"11221 143 St NW",
    "sg:city":"Edmonton",
    "sg:classifiers":[
        {
            "category":"Building & Trades",
            "subcategory":"Construction",
            "type":"Services"
        }
    ],
    "sg:phone":"+1 780 482 6470",
    "sg:postcode":"T5M 3P8",
    "sg:province":"AB",
    "sg:tags":[
        "painter"
    ],
    "wof:name":"Mario Painting Ltd",
    "wof:placetype":"venue"
},
  "geometry": {"coordinates":[-113.567245,53.560905],"type":"Point"}
}