{
  "type": "Feature",
  "properties": {
    "iso:country":"CA",
    "sg:address":"660 Richmond St",
    "sg:city":"London",
    "sg:classifiers":[
        {
            "category":"Food & Beverages",
            "subcategory":"Specialty",
            "type":"Retail Goods"
        }
    ],
    "sg:phone":"+1 519 645 2202",
    "sg:postcode":"N6A 3G8",
    "sg:province":"ON",
    "sg:tags":[
        "health",
        "diet"
    ],
    "wof:name":"AAA Sport Nutrition Depot",
    "wof:placetype":"venue"
},
  "geometry": {"coordinates":[-81.251495,42.992607],"type":"Point"}
}