{
  "type": "Feature",
  "properties": {
    "addr:full":"660 Richmond St London ON N6A 3G8",
    "addr:housenumber":"660",
    "addr:postcode":"n6a 3g8",
    "addr:street":"Richmond St",
    "iso:country":"CA",
    "sg:address":"660 Richmond St",
    "sg:city":"London",
    "sg:classifiers":[
        {
            "category":"Food & Beverages",
            "subcategory":"Specialty",
            "type":"Retail Goods"
        }
    ],
    "sg:phone":"+1 519 645 2202",
    "sg:postcode":"N6A 3G8",
    "sg:province":"ON",
    "sg:tags":[
        "health",
        "diet"
    ],
    "wof:name":"AAA Sport Nutrition Depot",
    "wof:placetype":"venue"
},
  "geometry": {"coordinates":[-81.25149500000001,42.992607],"type":"Point"}
}