{
  "type": "Feature",
  "properties": {
    "addr:full":"5 Ellen St Mississauga ON L5M 1R8",
    "addr:housenumber":"5",
    "addr:postcode":"l5m 1r8",
    "addr:street":"Ellen St",
    "iso:country":"CA",
    "sg:address":"5 Ellen St",
    "sg:city":"Mississauga",
    "sg:classifiers":[
        {
            "category":"Building & Trades",
            "subcategory":"Construction",
            "type":"Services"
        }
    ],
    "sg:phone":"+1 905 542 7660",
    "sg:postcode":"L5M 1R8",
    "sg:province":"ON",
    "sg:tags":[
        "general",
        "contractor"
    ],
    "wof:name":"W C Graham Construction",
    "wof:placetype":"venue"
},
  "geometry": {"coordinates":[-79.7192,43.586117],"type":"Point"}
}