{
  "type": "Feature",
  "properties": {
    "iso:country":"CA",
    "sg:address":"181 Thames St",
    "sg:city":"Chatham",
    "sg:classifiers":[
        {
            "category":"Shopping",
            "subcategory":"Bicycles & Sporting Goods",
            "type":"Retail Goods"
        }
    ],
    "sg:phone":"+1 519 351 5588",
    "sg:postcode":"N7L 2Z2",
    "sg:province":"ON",
    "wof:name":"Smith Cycle & More",
    "wof:placetype":"venue"
},
  "geometry": {"coordinates":[-82.1855163574,42.4098358154],"type":"Point"}
}