{
  "type": "Feature",
  "properties": {
    "addr:full":"930 St Clair Ave W Toronto ON M6C 1C8",
    "addr:housenumber":"930",
    "addr:postcode":"m6c 1c8",
    "addr:street":"St Clair Ave W",
    "iso:country":"CA",
    "sg:address":"930 St Clair Ave W",
    "sg:city":"Toronto",
    "sg:classifiers":[
        {
            "category":"Food & Beverages",
            "subcategory":"Groceries & Convenience Stores",
            "type":"Retail Goods"
        }
    ],
    "sg:phone":"+1 416 652 1201",
    "sg:postcode":"M6C 1C8",
    "sg:province":"ON",
    "wof:name":"Bina Convenience Stores",
    "wof:placetype":"venue"
},
  "geometry": {"coordinates":[-79.4348526001,43.6798782349],"type":"Point"}
}