{
  "type": "Feature",
  "properties": {
    "addr:full":"530 Talbot St E Aylmer ON N5H 2W2",
    "addr:housenumber":"530",
    "addr:postcode":"n5h 2w2",
    "addr:street":"Talbot St E",
    "iso:country":"CA",
    "sg:address":"530 Talbot St E",
    "sg:city":"Aylmer",
    "sg:classifiers":[
        {
            "category":"Shopping",
            "subcategory":"Hobbies, Toys, & Games",
            "type":"Retail Goods"
        }
    ],
    "sg:phone":"+1 519 765 3550",
    "sg:postcode":"N5H 2W2",
    "sg:province":"ON",
    "sg:tags":[
        "craft",
        "supply"
    ],
    "wof:name":"Spare Moments Crafts & Supply",
    "wof:placetype":"venue"
},
  "geometry": {"coordinates":[-80.9697570801,42.7703018188],"type":"Point"}
}