{
  "type": "Feature",
  "properties": {
    "addr:full":"3075 14th Ave # 218 Markham ON L3R 0G9",
    "addr:housenumber":"3075",
    "addr:postcode":"l3r 0g9",
    "addr:street":"14Th Ave # 218",
    "iso:country":"CA",
    "sg:address":"3075 14th Ave # 218",
    "sg:city":"Markham",
    "sg:classifiers":[
        {
            "category":"Shopping",
            "subcategory":"Computers & Home Electronics",
            "type":"Retail Goods"
        }
    ],
    "sg:phone":"+1 905 475 8050",
    "sg:postcode":"L3R 0G9",
    "sg:province":"ON",
    "sg:tags":[
        "software"
    ],
    "wof:name":"Heron Technology Corp",
    "wof:placetype":"venue"
},
  "geometry": {"coordinates":[-79.3506774902,43.8321876526],"type":"Point"}
}