{
  "type": "Feature",
  "properties": {
    "addr:full":"130 Advance Blvd Brampton ON L6T 4J4",
    "addr:housenumber":"130",
    "addr:postcode":"l6t 4j4",
    "addr:street":"Advance Blvd",
    "iso:country":"CA",
    "sg:address":"130 Advance Blvd",
    "sg:city":"Brampton",
    "sg:classifiers":[
        {
            "category":"Wholesale",
            "subcategory":"Durable Goods & Equipment",
            "type":"Manufacturing & Wholesale Goods"
        }
    ],
    "sg:phone":"+1 905 458 8840",
    "sg:postcode":"L6T 4J4",
    "sg:province":"ON",
    "sg:tags":[
        "exporter"
    ],
    "wof:name":"Bassi Trading CO",
    "wof:placetype":"venue"
},
  "geometry": {"coordinates":[-79.69266500000001,43.694324],"type":"Point"}
}