{
  "type": "Feature",
  "properties": {
    "addr:full":"127 Rue Proulx Amqui QC G5J 3H3",
    "addr:housenumber":"127",
    "addr:postcode":"g5j 3h3",
    "addr:street":"Rue Proulx",
    "iso:country":"CA",
    "sg:address":"127 Rue Proulx",
    "sg:city":"Amqui",
    "sg:classifiers":[
        {
            "category":"Local Transit",
            "type":"Transportation"
        }
    ],
    "sg:phone":"+1 418 629 4567",
    "sg:postcode":"G5J 3H3",
    "sg:province":"QC",
    "sg:tags":[
        "bus",
        "line"
    ],
    "wof:name":"Autobus Bouchard & Filles Inc",
    "wof:placetype":"venue"
},
  "geometry": {"coordinates":[-67.4404144287,48.4696884155],"type":"Point"}
}