{
  "type": "Feature",
  "properties": {
    "addr:full":"Blackfalds AB T0M 0J0",
    "addr:postcode":"t0m 0j0",
    "iso:country":"CA",
    "sg:city":"Blackfalds",
    "sg:classifiers":[
        {
            "category":"Professional",
            "subcategory":"Business Services",
            "type":"Services"
        }
    ],
    "sg:phone":"+1 403 885 4510",
    "sg:postcode":"T0M 0J0",
    "sg:province":"AB",
    "sg:tags":[
        "auctioneer"
    ],
    "wof:name":"Rick Horn Auctions",
    "wof:placetype":"venue"
},
  "geometry": {"coordinates":[-113.795601,52.380409],"type":"Point"}
}