{
  "type": "Feature",
  "properties": {
    "addr:full":"Labelle QC J0T 1H0",
    "addr:postcode":"j0t 1h0",
    "iso:country":"CA",
    "sg:city":"Labelle",
    "sg:classifiers":[
        {
            "category":"Building & Trades",
            "subcategory":"Construction",
            "type":"Services"
        }
    ],
    "sg:phone":"+1 819 686 3199",
    "sg:postcode":"J0T 1H0",
    "sg:province":"QC",
    "sg:tags":[
        "excavating",
        "contractor"
    ],
    "wof:name":"Doris Nadon Excavation",
    "wof:placetype":"venue"
},
  "geometry": {"coordinates":[-74.795799,46.278313],"type":"Point"}
}