{
  "type": "Feature",
  "properties": {
    "addr:full":"54 Bridge E Campbellford ON K0L 1L0",
    "addr:housenumber":"54",
    "addr:postcode":"k0l 1l0",
    "addr:street":"Bridge E Campbellford",
    "iso:country":"CA",
    "sg:address":"54 Bridge E",
    "sg:city":"Campbellford",
    "sg:classifiers":[
        {
            "category":"Cinema",
            "subcategory":"Movie Theater",
            "type":"Entertainment"
        }
    ],
    "sg:phone":"+1 705 653 3390",
    "sg:postcode":"K0L 1L0",
    "sg:province":"ON",
    "wof:name":"Aron Cinema",
    "wof:placetype":"venue"
},
  "geometry": {"coordinates":[-77.7967,44.308247],"type":"Point"}
}