{
  "type": "Feature",
  "properties": {
    "addr:full":"Nicolet QC J3T 1Z9",
    "addr:postcode":"j3t 1z9",
    "iso:country":"CA",
    "sg:city":"Nicolet",
    "sg:classifiers":[
        {
            "category":"Organizations",
            "subcategory":"Professional Association",
            "type":"Services"
        }
    ],
    "sg:phone":"+1 819 293 5838",
    "sg:postcode":"J3T 1Z9",
    "sg:province":"QC",
    "wof:name":"Upa Du Centre-Du-Quebec",
    "wof:placetype":"venue"
},
  "geometry": {"coordinates":[-72.5933761597,46.2523384094],"type":"Point"}
}