{
  "type": "Feature",
  "properties": {
    "addr:full":"59 Main Ave Glenwood AB T0K 2R0",
    "addr:housenumber":"59",
    "addr:postcode":"t0k 2r0",
    "addr:street":"Main Ave",
    "iso:country":"CA",
    "sg:address":"59 Main Ave",
    "sg:city":"Glenwood",
    "sg:classifiers":[
        {
            "category":"Government",
            "subcategory":"Office",
            "type":"Public Place"
        }
    ],
    "sg:phone":"+1 403 626 3233",
    "sg:postcode":"T0K 2R0",
    "sg:province":"AB",
    "sg:tags":[
        "village"
    ],
    "wof:name":"Glenwood Village Office",
    "wof:placetype":"venue"
},
  "geometry": {"coordinates":[-113.521866,49.36628],"type":"Point"}
}