{
  "type": "Feature",
  "properties": {
    "iso:country":"CA",
    "sg:address":"340 St George St",
    "sg:city":"Annapolis Royal",
    "sg:classifiers":[
        {
            "category":"Organizations",
            "subcategory":"Religious Organization",
            "type":"Services"
        }
    ],
    "sg:phone":"+1 902 532 0913",
    "sg:postcode":"B0S 1A0",
    "sg:province":"NS",
    "wof:name":"St Lukes Church Hall",
    "wof:placetype":"venue"
},
  "geometry": {"coordinates":[-65.51727294920001,44.7423362732],"type":"Point"}
}