{
  "type": "Feature",
  "properties": {
    "addr:full":"4915 50 Ave Bonnyville AB T9N 2G4",
    "addr:housenumber":"4915",
    "addr:postcode":"t9n 2g4",
    "addr:street":"50 Ave",
    "iso:country":"CA",
    "sg:address":"4915 50 Ave",
    "sg:city":"Bonnyville",
    "sg:classifiers":[
        {
            "category":"Insurance",
            "subcategory":"Insurance Agent",
            "type":"Services"
        }
    ],
    "sg:phone":"+1 780 826 3147",
    "sg:postcode":"T9N 2G4",
    "sg:province":"AB",
    "wof:name":"Trans West Insurance Brokers",
    "wof:placetype":"venue"
},
  "geometry": {"coordinates":[-110.737785,54.2682],"type":"Point"}
}