{
  "type": "Feature",
  "properties": {
    "addr:full":"Slave Lake AB T0G 2A3",
    "addr:postcode":"t0g 2a3",
    "iso:country":"CA",
    "sg:city":"Slave Lake",
    "sg:classifiers":[
        {
            "category":"Building & Trades",
            "subcategory":"Construction",
            "type":"Services"
        }
    ],
    "sg:phone":"+1 780 849 2009",
    "sg:postcode":"T0G 2A3",
    "sg:province":"AB",
    "sg:tags":[
        "excavating",
        "contractor"
    ],
    "wof:name":"Ted Conrad Construction",
    "wof:placetype":"venue"
},
  "geometry": {"coordinates":[-114.770500183,55.2736816406],"type":"Point"}
}