{
  "type": "Feature",
  "properties": {
    "addr:full":"Hamilton ON L9B 1K3",
    "addr:postcode":"l9b 1k3",
    "iso:country":"CA",
    "sg:city":"Hamilton",
    "sg:classifiers":[
        {
            "category":"Insurance",
            "subcategory":"Insurance Agent",
            "type":"Services"
        }
    ],
    "sg:phone":"+1 905 318 8000",
    "sg:postcode":"L9B 1K3",
    "sg:province":"ON",
    "wof:name":"Ruhl, Stan",
    "wof:placetype":"venue"
},
  "geometry": {"coordinates":[-79.89015999999999,43.209335],"type":"Point"}
}