{
  "type": "Feature",
  "properties": {
    "iso:country":"CA",
    "sg:address":"450 6E Av",
    "sg:city":"Grand-Mere",
    "sg:classifiers":[
        {
            "category":"Personal",
            "type":"Services"
        }
    ],
    "sg:phone":"+1 819 533 7190",
    "sg:postcode":"G9T 2H2",
    "sg:province":"QC",
    "sg:tags":[
        "electrolysis"
    ],
    "wof:name":"Salon D'Esthetique L Grenon",
    "wof:placetype":"venue"
},
  "geometry": {"coordinates":[-72.690353,46.615986],"type":"Point"}
}