{
  "type": "Feature",
  "properties": {
    "iso:country":"CA",
    "sg:address":"15 Purcell's Cove Rd",
    "sg:city":"Halifax",
    "sg:classifiers":[
        {
            "category":"Autos & Motor Vehicles",
            "subcategory":"Boat Sales",
            "type":"Retail Goods"
        }
    ],
    "sg:phone":"+1 902 477 6464",
    "sg:postcode":"B3N 1R2",
    "sg:province":"NS",
    "sg:tags":[
        "equipment",
        "marine",
        "supply"
    ],
    "wof:name":"Binnacle Navigation Instrmnts",
    "wof:placetype":"venue"
},
  "geometry": {"coordinates":[-63.5739212036,44.6461601257],"type":"Point"}
}