{
  "type": "Feature",
  "properties": {
    "iso:country":"CA",
    "sg:address":"200 Rue Principale",
    "sg:city":"Leeds Village",
    "sg:classifiers":[
        {
            "category":"Banks & Credit Unions",
            "subcategory":"Bank",
            "type":"Services"
        }
    ],
    "sg:phone":"+1 418 338 6021",
    "sg:postcode":"G0N 1J0",
    "sg:province":"QC",
    "wof:name":"Caisses Desjardins",
    "wof:placetype":"venue"
},
  "geometry": {"coordinates":[-71.3382110596,46.2879104614],"type":"Point"}
}