{
  "type": "Feature",
  "properties": {
    "addr:full":"Toronto ON M6G 1B9",
    "addr:postcode":"m6g 1b9",
    "iso:country":"CA",
    "sg:city":"Toronto",
    "sg:classifiers":[
        {
            "category":"Professional",
            "subcategory":"Accounting & Tax Preparation",
            "type":"Services"
        }
    ],
    "sg:phone":"+1 416 651 1900",
    "sg:postcode":"M6G 1B9",
    "sg:province":"ON",
    "sg:tags":[
        "accountant"
    ],
    "wof:name":"Irefino & Assoc Ltd",
    "wof:placetype":"venue"
},
  "geometry": {"coordinates":[-79.41774700000001,43.655121],"type":"Point"}
}