{
  "type": "Feature",
  "properties": {
    "addr:full":"6101 6 St SE Calgary AB T2H 1L9",
    "addr:housenumber":"6101 6",
    "addr:postcode":"t2h 1l9",
    "addr:street":"St Se",
    "iso:country":"CA",
    "sg:address":"6101 6 St SE",
    "sg:city":"Calgary",
    "sg:classifiers":[
        {
            "category":"Shopping",
            "type":"Retail Goods"
        }
    ],
    "sg:phone":"+1 403 347 8811",
    "sg:postcode":"T2H 1L9",
    "sg:province":"AB",
    "sg:tags":[
        "equipment",
        "telephone",
        "supply"
    ],
    "wof:name":"Delphi Solutions Corp",
    "wof:placetype":"venue"
},
  "geometry": {"coordinates":[-114.051033,50.997299],"type":"Point"}
}