{
  "type": "Feature",
  "properties": {
    "iso:country":"CA",
    "sg:address":"275 Macpherson Ave",
    "sg:city":"Toronto",
    "sg:classifiers":[
        {
            "category":"Professional",
            "subcategory":"Management & Consulting",
            "type":"Services"
        }
    ],
    "sg:phone":"+1 416 964 8887",
    "sg:postcode":"M4V 1A4",
    "sg:province":"ON",
    "sg:tags":[
        "consultant",
        "business"
    ],
    "wof:name":"Inspired Pathways",
    "wof:placetype":"venue"
},
  "geometry": {"coordinates":[-79.4007797241,43.6771888733],"type":"Point"}
}