{
  "type": "Feature",
  "properties": {
    "addr:full":"74 Pearltown Rd St. John's NL A1G 1P3",
    "addr:housenumber":"74",
    "addr:postcode":"a1g 1p3",
    "addr:street":"Pearltown Rd",
    "iso:country":"CA",
    "sg:address":"74 Pearltown Rd",
    "sg:city":"St. John's",
    "sg:classifiers":[
        {
            "category":"Retail",
            "subcategory":"Animal Services",
            "type":"Services"
        }
    ],
    "sg:phone":"+1 709 747 5466",
    "sg:postcode":"A1G 1P3",
    "sg:province":"NL",
    "sg:tags":[
        "pet",
        "boarding",
        "sitting"
    ],
    "wof:name":"Markwin Country Pet Resort",
    "wof:placetype":"venue"
},
  "geometry": {"coordinates":[-52.773811,47.506535],"type":"Point"}
}