{
  "type": "Feature",
  "properties": {
    "addr:full":"116 Woodlawn Ave Winnipeg MB R2M 2P4",
    "addr:housenumber":"116",
    "addr:postcode":"r2m 2p4",
    "addr:street":"Woodlawn Ave",
    "iso:country":"CA",
    "sg:address":"116 Woodlawn Ave",
    "sg:city":"Winnipeg",
    "sg:classifiers":[
        {
            "category":"Building & Trades",
            "subcategory":"Construction",
            "type":"Services"
        }
    ],
    "sg:phone":"+1 204 253 8549",
    "sg:postcode":"R2M 2P4",
    "sg:province":"MB",
    "sg:tags":[
        "woodworker"
    ],
    "wof:name":"Lou-Mig Custom Woodwork",
    "wof:placetype":"venue"
},
  "geometry": {"coordinates":[-97.12406900000001,49.820122],"type":"Point"}
}