{
  "type": "Feature",
  "properties": {
    "addr:full":"4515 Chesswood Dr North York ON M3J 2V6",
    "addr:housenumber":"4515",
    "addr:postcode":"m3j 2v6",
    "addr:street":"Chesswood Dr",
    "iso:country":"CA",
    "sg:address":"4515 Chesswood Dr",
    "sg:city":"North York",
    "sg:classifiers":[
        {
            "category":"Wholesale",
            "subcategory":"Durable Goods & Equipment",
            "type":"Manufacturing & Wholesale Goods"
        }
    ],
    "sg:phone":"+1 416 638 0952",
    "sg:postcode":"M3J 2V6",
    "sg:province":"ON",
    "sg:tags":[
        "importer"
    ],
    "wof:name":"Advance Trading CO",
    "wof:placetype":"venue"
},
  "geometry": {"coordinates":[-79.476662,43.764961],"type":"Point"}
}