{
  "type": "Feature",
  "properties": {
    "iso:country":"CA",
    "sg:address":"12858 Old Yale Rd",
    "sg:city":"Surrey",
    "sg:classifiers":[
        {
            "category":"Building & Trades",
            "subcategory":"Electrical",
            "type":"Services"
        }
    ],
    "sg:phone":"+1 604 581 2590",
    "sg:postcode":"V3T 3B5",
    "sg:province":"BC",
    "sg:tags":[
        "electric",
        "contractor"
    ],
    "wof:name":"Hiram Electric Ltd",
    "wof:placetype":"venue"
},
  "geometry": {"coordinates":[-122.863441467,49.1916885376],"type":"Point"}
}