{
  "type": "Feature",
  "properties": {
    "addr:full":"119 105th St E Saskatoon SK S7N 1Z2",
    "addr:housenumber":"119",
    "addr:postcode":"s7n 1z2",
    "addr:street":"105Th St E",
    "iso:country":"CA",
    "sg:address":"119 105th St E",
    "sg:city":"Saskatoon",
    "sg:classifiers":[
        {
            "category":"Sports & Exercise",
            "subcategory":"Gym",
            "type":"Entertainment"
        }
    ],
    "sg:phone":"+1 306 477 4273",
    "sg:postcode":"S7N 1Z2",
    "sg:province":"SK",
    "sg:tags":[
        "club",
        "health",
        "studio",
        "gymnasium"
    ],
    "wof:name":"Mawson Health & Fitness",
    "wof:placetype":"venue"
},
  "geometry": {"coordinates":[-106.596901,52.133476],"type":"Point"}
}