{
  "type": "Feature",
  "properties": {
    "addr:full":"331 Sheldon Dr Cambridge ON N1T 1B1",
    "addr:housenumber":"331",
    "addr:postcode":"n1t 1b1",
    "addr:street":"Sheldon Dr",
    "iso:country":"CA",
    "sg:address":"331 Sheldon Dr",
    "sg:city":"Cambridge",
    "sg:classifiers":[
        {
            "category":"Building & Trades",
            "subcategory":"Construction",
            "type":"Services"
        }
    ],
    "sg:phone":"+1 519 763 4733",
    "sg:postcode":"N1T 1B1",
    "sg:province":"ON",
    "sg:tags":[
        "roofing",
        "contractor"
    ],
    "wof:name":"Conestoga Roofing & Sheet Mtl",
    "wof:placetype":"venue"
},
  "geometry": {"coordinates":[-80.29953,43.407379],"type":"Point"}
}