{
  "type": "Feature",
  "properties": {
    "addr:full":"5266 Ch Queen-Mary Montreal QC H3W 1X5",
    "addr:housenumber":"5266",
    "addr:postcode":"h3w 1x5",
    "addr:street":"Ch Queen-Mary",
    "iso:country":"CA",
    "sg:address":"5266 Ch Queen-Mary",
    "sg:city":"Montreal",
    "sg:classifiers":[
        {
            "category":"Shopping",
            "subcategory":"Clothing, Apparel, & Fashions",
            "type":"Retail Goods"
        }
    ],
    "sg:phone":"+1 514 484 2911",
    "sg:postcode":"H3W 1X5",
    "sg:province":"QC",
    "wof:name":"Match Boutique",
    "wof:placetype":"venue"
},
  "geometry": {"coordinates":[-73.628578186,45.4839515686],"type":"Point"}
}