{
  "type": "Feature",
  "properties": {
    "addr:full":"173 Montreal Rd Cornwall ON K6H 1B2",
    "addr:housenumber":"173",
    "addr:postcode":"k6h 1b2",
    "addr:street":"Montreal Rd",
    "iso:country":"CA",
    "sg:address":"173 Montreal Rd",
    "sg:city":"Cornwall",
    "sg:classifiers":[
        {
            "category":"Shopping",
            "subcategory":"Pharmacy",
            "type":"Retail Goods"
        }
    ],
    "sg:phone":"+1 613 932 6501",
    "sg:postcode":"K6H 1B2",
    "sg:province":"ON",
    "wof:name":"Medical Arts Pharmacy",
    "wof:placetype":"venue"
},
  "geometry": {"coordinates":[-74.71358499999999,45.018402],"type":"Point"}
}