{
  "type": "Feature",
  "properties": {
    "addr:full":"Les Boules QC G0J 1S0",
    "addr:postcode":"g0j 1s0",
    "iso:country":"CA",
    "sg:city":"Les Boules",
    "sg:classifiers":[
        {
            "category":"Food & Beverages",
            "subcategory":"Groceries & Convenience Stores",
            "type":"Retail Goods"
        }
    ],
    "sg:phone":"+1 418 936 3366",
    "sg:postcode":"G0J 1S0",
    "sg:province":"QC",
    "sg:tags":[
        "grocer"
    ],
    "wof:name":"Epicerie Andre Ratte Inc",
    "wof:placetype":"venue"
},
  "geometry": {"coordinates":[-67.9632568359,48.6840400696],"type":"Point"}
}