{
  "type": "Feature",
  "properties": {
    "addr:full":"311 King St Cranbrook BC V1C 4E2",
    "addr:housenumber":"311",
    "addr:postcode":"bc v1c 4e2",
    "addr:street":"King St",
    "iso:country":"CA",
    "sg:address":"311 King St",
    "sg:city":"Cranbrook",
    "sg:classifiers":[
        {
            "category":"Retail",
            "subcategory":"Repair Shop",
            "type":"Services"
        }
    ],
    "sg:phone":"+1 250 489 2700",
    "sg:postcode":"V1C 4E2",
    "sg:province":"BC",
    "sg:tags":[
        "television",
        "radio"
    ],
    "wof:name":"See's Tv Repair",
    "wof:placetype":"venue"
},
  "geometry": {"coordinates":[-115.77021000000001,49.513336],"type":"Point"}
}