{
  "type": "Feature",
  "properties": {
    "addr:full":"Phantom Lake Creighton SK S0P 0A0",
    "addr:postcode":"s0p 0a0",
    "addr:street":"Phantom;Creighton",
    "iso:country":"CA",
    "sg:address":"Phantom Lake",
    "sg:city":"Creighton",
    "sg:classifiers":[
        {
            "category":"Sports & Exercise",
            "subcategory":"Golf",
            "type":"Entertainment"
        }
    ],
    "sg:phone":"+1 306 688 5555",
    "sg:postcode":"S0P 0A0",
    "sg:province":"SK",
    "sg:tags":[
        "course"
    ],
    "wof:name":"Phantom Lake Golf Club",
    "wof:placetype":"venue"
},
  "geometry": {"coordinates":[-101.872169,54.755569],"type":"Point"}
}