{
  "type": "Feature",
  "properties": {
    "addr:full":"830 43rd St E Saskatoon SK S7K 3V1",
    "addr:housenumber":"830",
    "addr:postcode":"s7k 3v1",
    "addr:street":"43Rd St E",
    "iso:country":"CA",
    "sg:address":"830 43rd St E",
    "sg:city":"Saskatoon",
    "sg:classifiers":[
        {
            "category":"Wholesale",
            "subcategory":"Vending Machines",
            "type":"Manufacturing & Wholesale Goods"
        }
    ],
    "sg:phone":"+1 306 652 8030",
    "sg:postcode":"S7K 3V1",
    "sg:province":"SK",
    "wof:name":"Pepsi Bottling Group",
    "wof:placetype":"venue"
},
  "geometry": {"coordinates":[-106.652489,52.160442],"type":"Point"}
}