{
  "type": "Feature",
  "properties": {
    "addr:full":"2987 Pandosy St Kelowna BC V1Y 1W1",
    "addr:housenumber":"2987",
    "addr:postcode":"v1y 1w1",
    "addr:street":"Pandosy St",
    "iso:country":"CA",
    "sg:address":"2987 Pandosy St",
    "sg:city":"Kelowna",
    "sg:classifiers":[
        {
            "category":"Shopping",
            "subcategory":"Used Merchandise",
            "type":"Retail Goods"
        }
    ],
    "sg:phone":"+1 250 763 6668",
    "sg:postcode":"V1Y 1W1",
    "sg:province":"BC",
    "sg:tags":[
        "shop",
        "consignment"
    ],
    "wof:name":"Wardrobe Quality Consignment",
    "wof:placetype":"venue"
},
  "geometry": {"coordinates":[-119.491035461,49.863483429],"type":"Point"}
}