{
  "type": "Feature",
  "properties": {
    "iso:country":"CA",
    "sg:city":"Spalding",
    "sg:classifiers":[
        {
            "category":"Sports & Exercise",
            "subcategory":"Bowling",
            "type":"Entertainment"
        }
    ],
    "sg:phone":"+1 306 872 2115",
    "sg:postcode":"S0K 4C0",
    "sg:province":"SK",
    "sg:tags":[
        "center"
    ],
    "wof:name":"Spalding Bowling Alley",
    "wof:placetype":"venue"
},
  "geometry": {"coordinates":[-104.496582031,52.3327331543],"type":"Point"}
}