{
  "type": "Feature",
  "properties": {
    "addr:full":"572 Eglinton Ave W Toronto ON M5N 1B7",
    "addr:housenumber":"572",
    "addr:postcode":"m5n 1b7",
    "addr:street":"Eglinton Ave W",
    "iso:country":"CA",
    "sg:address":"572 Eglinton Ave W",
    "sg:city":"Toronto",
    "sg:classifiers":[
        {
            "category":"Health Services",
            "subcategory":"Doctor",
            "type":"Services"
        }
    ],
    "sg:phone":"+1 416 481 0661",
    "sg:postcode":"M5N 1B7",
    "sg:province":"ON",
    "sg:tags":[
        "physician",
        "surgeon"
    ],
    "wof:name":"Keltz, M MD",
    "wof:placetype":"venue"
},
  "geometry": {"coordinates":[-79.41709899999999,43.702904],"type":"Point"}
}