{
  "type": "Feature",
  "properties": {
    "addr:full":"1251 Northside Rd Burlington ON L7M 1H7",
    "addr:housenumber":"1251",
    "addr:postcode":"l7m 1h7",
    "addr:street":"Northside Rd",
    "iso:country":"CA",
    "sg:address":"1251 Northside Rd",
    "sg:city":"Burlington",
    "sg:classifiers":[
        {
            "category":"Wholesale",
            "subcategory":"Books, Periodicals, & Newspapers",
            "type":"Manufacturing & Wholesale Goods"
        }
    ],
    "sg:phone":"+1 905 336 4003",
    "sg:postcode":"L7M 1H7",
    "sg:province":"ON",
    "sg:tags":[
        "dealer"
    ],
    "wof:name":"Minnow Books",
    "wof:placetype":"venue"
},
  "geometry": {"coordinates":[-79.80748,43.36264],"type":"Point"}
}