{
  "type": "Feature",
  "properties": {
    "iso:country":"CA",
    "sg:address":"939 3rd Ave",
    "sg:city":"Prince George",
    "sg:classifiers":[
        {
            "category":"Home & Garden",
            "subcategory":"Furniture",
            "type":"Retail Goods"
        }
    ],
    "sg:phone":"+1 250 562 3995",
    "sg:postcode":"V2L 3E1",
    "sg:province":"BC",
    "sg:tags":[
        "equipment",
        "kitchen",
        "cabinet"
    ],
    "wof:name":"Cabinet Doors Plus",
    "wof:placetype":"venue"
},
  "geometry": {"coordinates":[-122.74018096899999,53.9151954651],"type":"Point"}
}