{
  "type": "Feature",
  "properties": {
    "addr:full":"Hwy 16 Radisson SK S0K 3L0",
    "addr:postcode":"s0k 3l0",
    "addr:street":"Hwy 16 Radisson",
    "iso:country":"CA",
    "sg:address":"Hwy 16",
    "sg:city":"Radisson",
    "sg:classifiers":[
        {
            "category":"Restaurant",
            "type":"Food & Drink"
        }
    ],
    "sg:phone":"+1 306 827 4414",
    "sg:postcode":"S0K 3L0",
    "sg:province":"SK",
    "wof:name":"Red Bull Family Restaurant",
    "wof:placetype":"venue"
},
  "geometry": {"coordinates":[-107.39627075200001,52.468547821],"type":"Point"}
}