{
  "type": "Feature",
  "properties": {
    "addr:full":"2757 Norland Ave Burnaby BC V5B 3A9",
    "addr:housenumber":"2757",
    "addr:postcode":"v5b 3a9",
    "addr:street":"Norland Ave",
    "iso:country":"CA",
    "sg:address":"2757 Norland Ave",
    "sg:city":"Burnaby",
    "sg:classifiers":[
        {
            "category":"Wholesale",
            "subcategory":"Machinery & Supplies",
            "type":"Manufacturing & Wholesale Goods"
        }
    ],
    "sg:phone":"+1 604 299 4011",
    "sg:postcode":"V5B 3A9",
    "sg:province":"BC",
    "sg:tags":[
        "equipment",
        "baker"
    ],
    "wof:name":"Lockwood Manufacturing Inc",
    "wof:placetype":"venue"
},
  "geometry": {"coordinates":[-122.98204,49.25914],"type":"Point"}
}