{
  "type": "Feature",
  "properties": {
    "addr:full":"5329 Beechwood Rd Niagara Falls ON L2E 6S4",
    "addr:housenumber":"5329",
    "addr:postcode":"l2e 6s4",
    "addr:street":"Beechwood Rd",
    "iso:country":"CA",
    "sg:address":"5329 Beechwood Rd",
    "sg:city":"Niagara Falls",
    "sg:classifiers":[
        {
            "category":"Organizations",
            "subcategory":"Religious Organization",
            "type":"Services"
        }
    ],
    "sg:phone":"+1 905 356 7717",
    "sg:postcode":"L2E 6S4",
    "sg:province":"ON",
    "sg:tags":[
        "church"
    ],
    "wof:name":"Bible Baptist Church",
    "wof:placetype":"venue"
},
  "geometry": {"coordinates":[-79.162567,43.09766],"type":"Point"}
}