{
  "type": "Feature",
  "properties": {
    "addr:full":"65 Wickware Gate #8 Scarborough ON M1P 4Z1",
    "addr:housenumber":"65;# 8",
    "addr:postcode":"m1p 4z1",
    "addr:street":"Wickware Gate",
    "iso:country":"CA",
    "sg:address":"65 Wickware Gate #8",
    "sg:city":"Scarborough",
    "sg:classifiers":[
        {
            "category":"Shopping",
            "subcategory":"Computers & Home Electronics",
            "type":"Retail Goods"
        }
    ],
    "sg:phone":"+1 416 288 9996",
    "sg:postcode":"M1P 4Z1",
    "sg:province":"ON",
    "sg:tags":[
        "equipment",
        "electronic",
        "supply"
    ],
    "wof:name":"Payless Electronic 2000 Inc",
    "wof:placetype":"venue"
},
  "geometry": {"coordinates":[-79.27415499999999,43.753513],"type":"Point"}
}