{
  "type": "Feature",
  "properties": {
    "iso:country":"CA",
    "sg:address":"10 Herald Ave",
    "sg:city":"Corner Brook",
    "sg:classifiers":[
        {
            "category":"Bars & Pubs",
            "type":"Food & Drink"
        }
    ],
    "sg:phone":"+1 709 639 1041",
    "sg:postcode":"A2H 4B4",
    "sg:province":"NL",
    "sg:tags":[
        "lounge",
        "cocktail"
    ],
    "wof:name":"Padarnic Lounge",
    "wof:placetype":"venue"
},
  "geometry": {"coordinates":[-57.9546127319,48.9516067505],"type":"Point"}
}