{
  "type": "Feature",
  "properties": {
    "iso:country":"CA",
    "sg:city":"Woodbridge",
    "sg:classifiers":[
        {
            "category":"Shopping",
            "type":"Retail Goods"
        }
    ],
    "sg:phone":"+1 905 851 4538",
    "sg:postcode":"L4L 4Y5",
    "sg:province":"ON",
    "sg:tags":[
        "wedding",
        "supply"
    ],
    "wof:name":"1268231 Ontario Inc",
    "wof:placetype":"venue"
},
  "geometry": {"coordinates":[-79.552521,43.769196],"type":"Point"}
}