{
  "type": "Feature",
  "properties": {
    "addr:full":"6687 Longwood Rd Melbourne ON N0L 1T0",
    "addr:housenumber":"6687",
    "addr:postcode":"n0l 1t0",
    "addr:street":"Longwood Rd",
    "iso:country":"CA",
    "sg:address":"6687 Longwood Rd",
    "sg:city":"Melbourne",
    "sg:classifiers":[
        {
            "category":"Wholesale",
            "subcategory":"Machinery & Supplies",
            "type":"Manufacturing & Wholesale Goods"
        }
    ],
    "sg:phone":"+1 519 289 5256",
    "sg:postcode":"N0L 1T0",
    "sg:province":"ON",
    "sg:tags":[
        "farm",
        "equipment"
    ],
    "wof:name":"Melbourne Farm Automation",
    "wof:placetype":"venue"
},
  "geometry": {"coordinates":[-81.54652400000001,42.821533],"type":"Point"}
}