{
  "type": "Feature",
  "properties": {
    "iso:country":"CA",
    "sg:address":"434 Milltown Blvd",
    "sg:city":"St Stephen",
    "sg:classifiers":[
        {
            "category":"Education",
            "subcategory":"School",
            "type":"Public Place"
        }
    ],
    "sg:phone":"+1 506 466 7315",
    "sg:postcode":"E3L 1J8",
    "sg:province":"NB",
    "wof:name":"Milltown Elementary School",
    "wof:placetype":"venue"
},
  "geometry": {"coordinates":[-67.29624938960001,45.1747245789],"type":"Point"}
}