{
  "type": "Feature",
  "properties": {
    "addr:full":"107 Kennedy Rd S Brampton ON L6W 3G3",
    "addr:housenumber":"107",
    "addr:postcode":"l6w 3g3",
    "addr:street":"Kennedy Rd S",
    "iso:country":"CA",
    "sg:address":"107 Kennedy Rd S",
    "sg:city":"Brampton",
    "sg:classifiers":[
        {
            "category":"Food & Beverages",
            "subcategory":"Groceries & Convenience Stores",
            "type":"Retail Goods"
        }
    ],
    "sg:phone":"+1 905 453 4435",
    "sg:postcode":"L6W 3G3",
    "sg:province":"ON",
    "wof:name":"Goodies",
    "wof:placetype":"venue"
},
  "geometry": {"coordinates":[-79.737487793,43.6865119934],"type":"Point"}
}