{
  "type": "Feature",
  "properties": {
    "addr:full":"52119 Misener Rd Wainfleet ON L0S 1V0",
    "addr:housenumber":"52119",
    "addr:postcode":"l0s 1v0",
    "addr:street":"Misener Rd",
    "iso:country":"CA",
    "sg:address":"52119 Misener Rd",
    "sg:city":"Wainfleet",
    "sg:classifiers":[
        {
            "category":"Wholesale",
            "subcategory":"Farm Supplies",
            "type":"Manufacturing & Wholesale Goods"
        }
    ],
    "sg:phone":"+1 905 899 1559",
    "sg:postcode":"L0S 1V0",
    "sg:province":"ON",
    "sg:tags":[
        "livestock"
    ],
    "wof:name":"Niagara Livestock Sales Ltd",
    "wof:placetype":"venue"
},
  "geometry": {"coordinates":[-79.38865699999999,42.948257],"type":"Point"}
}