{
  "type": "Feature",
  "properties": {
    "iso:country":"CA",
    "sg:address":"554 Rue Dufferin",
    "sg:city":"Sherbrooke",
    "sg:classifiers":[
        {
            "category":"Health Services",
            "subcategory":"Clinic",
            "type":"Services"
        }
    ],
    "sg:phone":"+1 819 823 0093",
    "sg:postcode":"J1H 4N1",
    "sg:province":"QC",
    "sg:tags":[
        "home",
        "cleaning",
        "house"
    ],
    "wof:name":"Cooperative DE Svc A Domicile",
    "wof:placetype":"venue"
},
  "geometry": {"coordinates":[-71.897041,45.408138],"type":"Point"}
}