{
  "type": "Feature",
  "properties": {
    "addr:full":"792 Elizabeth Ave Sarnia ON N7S 2V3",
    "addr:housenumber":"792",
    "addr:postcode":"n7s 2v3",
    "addr:street":"Elizabeth Ave",
    "iso:country":"CA",
    "sg:address":"792 Elizabeth Ave",
    "sg:city":"Sarnia",
    "sg:classifiers":[
        {
            "category":"Building & Trades",
            "subcategory":"Construction",
            "type":"Services"
        }
    ],
    "sg:phone":"+1 519 336 7576",
    "sg:postcode":"N7S 2V3",
    "sg:province":"ON",
    "sg:tags":[
        "resurfacing",
        "laying",
        "refinishing",
        "floor"
    ],
    "wof:name":"Rene's Flooring",
    "wof:placetype":"venue"
},
  "geometry": {"coordinates":[-82.3698959351,42.9845046997],"type":"Point"}
}