{
  "type": "Feature",
  "properties": {
    "addr:full":"2691 Markham Rd # 13 Scarborough ON M1X 1L4",
    "addr:housenumber":"2691",
    "addr:postcode":"m1x 1l4",
    "addr:street":"Markham Rd # 13",
    "iso:country":"CA",
    "sg:address":"2691 Markham Rd # 13",
    "sg:city":"Scarborough",
    "sg:classifiers":[
        {
            "category":"Wholesale",
            "subcategory":"Groceries",
            "type":"Manufacturing & Wholesale Goods"
        }
    ],
    "sg:phone":"+1 416 291 4564",
    "sg:postcode":"M1X 1L4",
    "sg:province":"ON",
    "sg:tags":[
        "food",
        "grocer",
        "product"
    ],
    "wof:name":"Wah Season CO",
    "wof:placetype":"venue"
},
  "geometry": {"coordinates":[-79.245544,43.819458],"type":"Point"}
}