{
  "type": "Feature",
  "properties": {
    "addr:full":"Langley BC V3A 7N3",
    "addr:postcode":"v3a 7n3",
    "iso:country":"CA",
    "sg:city":"Langley",
    "sg:classifiers":[
        {
            "category":"Home & Garden",
            "subcategory":"Furniture",
            "type":"Retail Goods"
        }
    ],
    "sg:phone":"+1 604 530 6015",
    "sg:postcode":"V3A 7N3",
    "sg:province":"BC",
    "sg:tags":[
        "equipment",
        "kitchen",
        "cabinet"
    ],
    "wof:name":"Ray-Mar Ind Inc",
    "wof:placetype":"venue"
},
  "geometry": {"coordinates":[-122.659606934,49.1097145081],"type":"Point"}
}