{
  "type": "Feature",
  "properties": {
    "addr:full":"223 Northlake Dr Waterloo ON N2V 1A6",
    "addr:housenumber":"223",
    "addr:postcode":"n2v 1a6",
    "addr:street":"Northlake Dr",
    "iso:country":"CA",
    "sg:address":"223 Northlake Dr",
    "sg:city":"Waterloo",
    "sg:classifiers":[
        {
            "category":"Retail",
            "subcategory":"Repair Shop",
            "type":"Services"
        }
    ],
    "sg:phone":"+1 519 888 0631",
    "sg:postcode":"N2V 1A6",
    "sg:province":"ON",
    "sg:tags":[
        "sharpening"
    ],
    "wof:name":"Precision Tool Sharpening",
    "wof:placetype":"venue"
},
  "geometry": {"coordinates":[-80.55415344239999,43.4947853088],"type":"Point"}
}