{
  "type": "Feature",
  "properties": {
    "iso:country":"CA",
    "sg:address":"85 Renfrew Dr",
    "sg:city":"Markham",
    "sg:classifiers":[
        {
            "category":"Real Estate",
            "subcategory":"Real Estate Agent",
            "type":"Services"
        }
    ],
    "sg:phone":"+1 905 948 1770",
    "sg:postcode":"L3R 0N9",
    "sg:province":"ON",
    "wof:name":"Rainbow Allstar Realty Inc",
    "wof:placetype":"venue"
},
  "geometry": {"coordinates":[-79.362236,43.858505],"type":"Point"}
}