{
  "type": "Feature",
  "properties": {
    "addr:full":"85 Renfrew Dr Markham ON L3R 0N9",
    "addr:housenumber":"85",
    "addr:postcode":"l3r 0n9",
    "addr:street":"Renfrew Dr",
    "iso:country":"CA",
    "sg:address":"85 Renfrew Dr",
    "sg:city":"Markham",
    "sg:classifiers":[
        {
            "category":"Real Estate",
            "subcategory":"Real Estate Agent",
            "type":"Services"
        }
    ],
    "sg:phone":"+1 905 948 1770",
    "sg:postcode":"L3R 0N9",
    "sg:province":"ON",
    "wof:name":"Rainbow Allstar Realty Inc",
    "wof:placetype":"venue"
},
  "geometry": {"coordinates":[-79.362236,43.858505],"type":"Point"}
}