{
  "type": "Feature",
  "properties": {
    "addr:full":"101 Amber St # 9 Markham ON L3R 3B2",
    "addr:housenumber":"101",
    "addr:postcode":"l3r 3b2",
    "addr:street":"Amber St # 9",
    "iso:country":"CA",
    "sg:address":"101 Amber St # 9",
    "sg:city":"Markham",
    "sg:classifiers":[
        {
            "category":"Shopping",
            "subcategory":"Jewelry",
            "type":"Retail Goods"
        }
    ],
    "sg:phone":"+1 905 477 7572",
    "sg:postcode":"L3R 3B2",
    "sg:province":"ON",
    "sg:tags":[
        "watch"
    ],
    "wof:name":"Gucci Timepieces Canada Inc",
    "wof:placetype":"venue"
},
  "geometry": {"coordinates":[-79.331337,43.828079],"type":"Point"}
}