{
  "type": "Feature",
  "properties": {
    "addr:full":"Joliette QC J6E 4T2",
    "addr:postcode":"j6e 4t2",
    "iso:country":"CA",
    "sg:city":"Joliette",
    "sg:classifiers":[
        {
            "category":"Restaurant",
            "type":"Food & Drink"
        }
    ],
    "sg:phone":"+1 450 759 8969",
    "sg:postcode":"J6E 4T2",
    "sg:province":"QC",
    "wof:name":"Harvey's",
    "wof:placetype":"venue"
},
  "geometry": {"coordinates":[-73.43718,46.023853],"type":"Point"}
}