{
  "type": "Feature",
  "properties": {
    "iso:country":"CA",
    "sg:address":"8369 Island Hwy",
    "sg:city":"Black Creek",
    "sg:classifiers":[
        {
            "category":"Organizations",
            "subcategory":"Professional Association",
            "type":"Services"
        }
    ],
    "sg:phone":"+1 250 337 5388",
    "sg:postcode":"V9J 1H2",
    "sg:province":"BC",
    "sg:tags":[
        "club"
    ],
    "wof:name":"Black Creek Oapo",
    "wof:placetype":"venue"
},
  "geometry": {"coordinates":[-125.132919312,49.8385772705],"type":"Point"}
}