{
  "type": "Feature",
  "properties": {
    "addr:full":"5114 50 Ave Wetaskiwin AB T9A 0S6",
    "addr:housenumber":"5114",
    "addr:postcode":"t9a 0s6",
    "addr:street":"50 Ave",
    "iso:country":"CA",
    "sg:address":"5114 50 Ave",
    "sg:city":"Wetaskiwin",
    "sg:classifiers":[
        {
            "category":"Health Services",
            "subcategory":"Medical Lab",
            "type":"Services"
        }
    ],
    "sg:phone":"+1 780 352 4343",
    "sg:postcode":"T9A 0S6",
    "sg:province":"AB",
    "wof:name":"Wetaskiwin Denture Clinic",
    "wof:placetype":"venue"
},
  "geometry": {"coordinates":[-113.376625061,52.9699935913],"type":"Point"}
}