{
  "type": "Feature",
  "properties": {
    "addr:full":"279 Boul Rene-A.-Robert Sainte-Therese QC J7E 1W2",
    "addr:housenumber":"279",
    "addr:postcode":"j7e 1w2",
    "addr:street":"Boul Rene-A.-Robert Sainte-Therese",
    "iso:country":"CA",
    "sg:address":"279 Boul Rene-A.-Robert",
    "sg:city":"Sainte-Therese",
    "sg:classifiers":[
        {
            "category":"Building & Trades",
            "subcategory":"Landscaping Services",
            "type":"Services"
        }
    ],
    "sg:phone":"+1 450 435 4755",
    "sg:postcode":"J7E 1W2",
    "sg:province":"QC",
    "sg:tags":[
        "sod",
        "sodding"
    ],
    "wof:name":"Gazons Gl Lebeau Inc",
    "wof:placetype":"venue"
},
  "geometry": {"coordinates":[-73.814476,45.640503],"type":"Point"}
}