{
  "type": "Feature",
  "properties": {
    "addr:full":"20 Rue Principale N Saint-Jean-DE-Dieu QC G0L 3M0",
    "addr:housenumber":"20",
    "addr:postcode":"g0l 3m0",
    "addr:street":"Rue Principale N",
    "iso:country":"CA",
    "sg:address":"20 Rue Principale N",
    "sg:city":"Saint-Jean-DE-Dieu",
    "sg:classifiers":[
        {
            "category":"Home & Garden",
            "subcategory":"Hardware",
            "type":"Retail Goods"
        }
    ],
    "sg:phone":"+1 418 963 2568",
    "sg:postcode":"G0L 3M0",
    "sg:province":"QC",
    "wof:name":"Quincaillerie Coop",
    "wof:placetype":"venue"
},
  "geometry": {"coordinates":[-69.0462722778,48.0038795471],"type":"Point"}
}