{
  "type": "Feature",
  "properties": {
    "addr:full":"449 E Island Hwy Parksville BC V9P 2G5",
    "addr:housenumber":"449",
    "addr:postcode":"v9p 2g5",
    "addr:street":"E Island Hwy",
    "iso:country":"CA",
    "sg:address":"449 E Island Hwy",
    "sg:city":"Parksville",
    "sg:classifiers":[
        {
            "category":"Manufacturing",
            "subcategory":"Petroleum Products",
            "type":"Manufacturing & Wholesale Goods"
        }
    ],
    "sg:phone":"+1 250 248 0585",
    "sg:postcode":"V9P 2G5",
    "sg:province":"BC",
    "sg:tags":[
        "repairing",
        "lubricating",
        "oil",
        "grease",
        "automobile"
    ],
    "wof:name":"Great Canadian Oil Change",
    "wof:placetype":"venue"
},
  "geometry": {"coordinates":[-124.29827899999999,49.318398],"type":"Point"}
}