{
  "type": "Feature",
  "properties": {
    "addr:full":"211 Simms St Courtenay BC V9N 1J6",
    "addr:housenumber":"211",
    "addr:postcode":"v9n 1j6",
    "addr:street":"Simms St",
    "iso:country":"CA",
    "sg:address":"211 Simms St",
    "sg:city":"Courtenay",
    "sg:classifiers":[
        {
            "category":"Shopping",
            "subcategory":"Music",
            "type":"Retail Goods"
        }
    ],
    "sg:phone":"+1 250 338 6621",
    "sg:postcode":"V9N 1J6",
    "sg:province":"BC",
    "sg:tags":[
        "compact",
        "record",
        "disc",
        "tape"
    ],
    "wof:name":"Bop City Records",
    "wof:placetype":"venue"
},
  "geometry": {"coordinates":[-124.99314099999999,49.686722],"type":"Point"}
}