{
  "type": "Feature",
  "properties": {
    "iso:country":"CA",
    "sg:address":"5121 Av Connaught",
    "sg:city":"Montreal",
    "sg:classifiers":[
        {
            "category":"Professional",
            "subcategory":"Business Services",
            "type":"Services"
        }
    ],
    "sg:phone":"+1 514 481 7657",
    "sg:postcode":"H4V 1X5",
    "sg:province":"QC",
    "wof:name":"Saseco Inc",
    "wof:placetype":"venue"
},
  "geometry": {"coordinates":[-73.6516799927,45.4577484131],"type":"Point"}
}