{
  "type": "Feature",
  "properties": {
    "iso:country":"CA",
    "sg:city":"Exshaw",
    "sg:classifiers":[
        {
            "category":"Organizations",
            "subcategory":"Community Association",
            "type":"Services"
        }
    ],
    "sg:phone":"+1 403 673 3522",
    "sg:postcode":"T0L 2C0",
    "sg:province":"AB",
    "sg:tags":[
        "club"
    ],
    "wof:name":"Royal Canadian Legion 179",
    "wof:placetype":"venue"
},
  "geometry": {"coordinates":[-115.162658691,51.0591773987],"type":"Point"}
}