{
  "type": "Feature",
  "properties": {
    "addr:full":"443 Route 309 Val-Des-Bois QC J0X 3C0",
    "addr:housenumber":"443",
    "addr:postcode":"j0x 3c0",
    "addr:street":"Route 309",
    "iso:country":"CA",
    "sg:address":"443 Route 309",
    "sg:city":"Val-Des-Bois",
    "sg:classifiers":[
        {
            "category":"Travel",
            "subcategory":"Hotels & Motels",
            "type":"Entertainment"
        }
    ],
    "sg:phone":"+1 819 454 2011",
    "sg:postcode":"J0X 3C0",
    "sg:province":"QC",
    "sg:tags":[
        "outing",
        "camp",
        "fishing",
        "facility"
    ],
    "wof:name":"Reserve Faunique Papineau",
    "wof:placetype":"venue"
},
  "geometry": {"coordinates":[-75.606606,45.894405],"type":"Point"}
}