{
  "type": "Feature",
  "properties": {
    "addr:full":"36 Hardy Ave Grand Falls-Windsor NL A2A 2J3",
    "addr:housenumber":"36",
    "addr:postcode":"a2a 2j3",
    "addr:street":"Hardy Ave",
    "iso:country":"CA",
    "sg:address":"36 Hardy Ave",
    "sg:city":"Grand Falls-Windsor",
    "sg:classifiers":[
        {
            "category":"Retail",
            "subcategory":"Auto Rental",
            "type":"Services"
        }
    ],
    "sg:phone":"+1 709 489 5716",
    "sg:postcode":"A2A 2J3",
    "sg:province":"NL",
    "sg:tags":[
        "renting",
        "truck",
        "leasing"
    ],
    "wof:name":"U-Haul CO Ltd",
    "wof:placetype":"venue"
},
  "geometry": {"coordinates":[-55.6466751099,48.951423645],"type":"Point"}
}