{
  "type": "Feature",
  "properties": {
    "iso:country":"CA",
    "sg:city":"Ottawa",
    "sg:classifiers":[
        {
            "category":"Recreation",
            "type":"Entertainment"
        }
    ],
    "sg:phone":"+1 613 737 3200",
    "sg:postcode":"K1V 9A3",
    "sg:province":"ON",
    "sg:tags":[
        "center",
        "association"
    ],
    "wof:name":"Hunt Club Rec Ctr",
    "wof:placetype":"venue"
},
  "geometry": {"coordinates":[-75.664390564,45.3478775024],"type":"Point"}
}