{
  "type": "Feature",
  "properties": {
    "addr:full":"4710 17 Ave SE Calgary AB T2A 0V1",
    "addr:housenumber":"4710",
    "addr:postcode":"t2a 0v1",
    "addr:street":"17 Ave Se",
    "iso:country":"CA",
    "sg:address":"4710 17 Ave SE",
    "sg:city":"Calgary",
    "sg:classifiers":[
        {
            "category":"Retail",
            "subcategory":"Auto Repair",
            "type":"Services"
        }
    ],
    "sg:phone":"+1 403 273 6005",
    "sg:postcode":"T2A 0V1",
    "sg:province":"AB",
    "sg:tags":[
        "repairing",
        "automobile",
        "muffler",
        "exhaust"
    ],
    "wof:name":"Apollo Muffler",
    "wof:placetype":"venue"
},
  "geometry": {"coordinates":[-113.967033,51.037991],"type":"Point"}
}