{
  "type": "Feature",
  "properties": {
    "addr:full":"Mattawa ON P0H 1V0",
    "addr:postcode":"p0h 1v0",
    "iso:country":"CA",
    "sg:city":"Mattawa",
    "sg:classifiers":[
        {
            "category":"Restaurant",
            "type":"Food & Drink"
        }
    ],
    "sg:phone":"+1 705 744 2880",
    "sg:postcode":"P0H 1V0",
    "sg:province":"ON",
    "wof:name":"Dixie Lee Restaurant",
    "wof:placetype":"venue"
},
  "geometry": {"coordinates":[-78.7045135498,46.312412262],"type":"Point"}
}