{
  "type": "Feature",
  "properties": {
    "addr:full":"Chateauguay QC J6K 3C3",
    "addr:postcode":"j6k 3c3",
    "iso:country":"CA",
    "sg:city":"Chateauguay",
    "sg:classifiers":[
        {
            "category":"Shopping",
            "type":"Retail Goods"
        }
    ],
    "sg:phone":"+1 450 699 1913",
    "sg:postcode":"J6K 3C3",
    "sg:province":"QC",
    "sg:tags":[
        "picture",
        "frame",
        "material",
        "artist",
        "supply"
    ],
    "wof:name":"Cadrexpert Inc",
    "wof:placetype":"venue"
},
  "geometry": {"coordinates":[-73.72265625,45.347858429],"type":"Point"}
}