{
  "type": "Feature",
  "properties": {
    "addr:full":"Saskatoon SK S7N 3A4",
    "addr:postcode":"s7n 3a4",
    "iso:country":"CA",
    "sg:city":"Saskatoon",
    "sg:classifiers":[
        {
            "category":"Personal",
            "subcategory":"Beauty Salon",
            "type":"Services"
        }
    ],
    "sg:phone":"+1 306 373 6112",
    "sg:postcode":"S7N 3A4",
    "sg:province":"SK",
    "wof:name":"J R's Barber Stylists",
    "wof:placetype":"venue"
},
  "geometry": {"coordinates":[-106.59891500000001,52.136169],"type":"Point"}
}