{
  "type": "Feature",
  "properties": {
    "addr:full":"345 Van Horne St S Cranbrook BC V1C 1Z6",
    "addr:housenumber":"345",
    "addr:postcode":"v1c 1z6",
    "addr:street":"Van Horne St S",
    "iso:country":"CA",
    "sg:address":"345 Van Horne St S",
    "sg:city":"Cranbrook",
    "sg:classifiers":[
        {
            "category":"Farming",
            "subcategory":"Nursery",
            "type":"Manufacturing & Wholesale Goods"
        }
    ],
    "sg:phone":"+1 250 489 3328",
    "sg:postcode":"V1C 1Z6",
    "sg:province":"BC",
    "sg:tags":[
        "greenhouse"
    ],
    "wof:name":"Columbia Valley Greenhouses",
    "wof:placetype":"venue"
},
  "geometry": {"coordinates":[-115.782623,49.506004],"type":"Point"}
}