{
  "type": "Feature",
  "properties": {
    "addr:full":"220 Humberline Dr Etobicoke ON M9W 5Y4",
    "addr:housenumber":"220",
    "addr:postcode":"m9w 5y4",
    "addr:street":"Humberline Dr",
    "iso:country":"CA",
    "sg:address":"220 Humberline Dr",
    "sg:city":"Etobicoke",
    "sg:classifiers":[
        {
            "category":"Arts & Performance",
            "subcategory":"Theater",
            "type":"Entertainment"
        }
    ],
    "sg:phone":"+1 416 738 3535",
    "sg:postcode":"M9W 5Y4",
    "sg:province":"ON",
    "sg:tags":[
        "live",
        "music"
    ],
    "wof:name":"Lasting Impressions Disc",
    "wof:placetype":"venue"
},
  "geometry": {"coordinates":[-79.617966,43.735474],"type":"Point"}
}