{
  "type": "Feature",
  "properties": {
    "iso:country":"CA",
    "sg:address":"4573 Boul Bourque",
    "sg:city":"Rock Forest",
    "sg:classifiers":[
        {
            "category":"Building & Trades",
            "subcategory":"Plumbing",
            "type":"Services"
        }
    ],
    "sg:phone":"+1 819 569 6676",
    "sg:postcode":"J1N 2G6",
    "sg:province":"QC",
    "sg:tags":[
        "contractor"
    ],
    "wof:name":"Andre Lapierre Svc Enr",
    "wof:placetype":"venue"
},
  "geometry": {"coordinates":[-71.980225,45.37608],"type":"Point"}
}