{
  "type": "Feature",
  "properties": {
    "addr:full":"2610 Glenayr Dr Nanaimo BC V9S 3S3",
    "addr:housenumber":"2610",
    "addr:postcode":"v9s 3s3",
    "addr:street":"Glenayr Dr",
    "iso:country":"CA",
    "sg:address":"2610 Glenayr Dr",
    "sg:city":"Nanaimo",
    "sg:classifiers":[
        {
            "category":"Home & Garden",
            "subcategory":"Building Materials",
            "type":"Retail Goods"
        }
    ],
    "sg:phone":"+1 250 758 8022",
    "sg:postcode":"V9S 3S3",
    "sg:province":"BC",
    "sg:tags":[
        "windows",
        "glass"
    ],
    "wof:name":"Windecker Windows Ltd",
    "wof:placetype":"venue"
},
  "geometry": {"coordinates":[-123.97604370099999,49.2022018433],"type":"Point"}
}