{
  "type": "Feature",
  "properties": {
    "addr:full":"Toronto ON M6G 1A4",
    "addr:postcode":"m6g 1a4",
    "iso:country":"CA",
    "sg:city":"Toronto",
    "sg:classifiers":[
        {
            "category":"Restaurant",
            "type":"Food & Drink"
        }
    ],
    "sg:phone":"+1 416 968 6431",
    "sg:postcode":"M6G 1A4",
    "sg:province":"ON",
    "sg:tags":[
        "shop",
        "coffee"
    ],
    "wof:name":"Simon's Coffee Shop",
    "wof:placetype":"venue"
},
  "geometry": {"coordinates":[-79.40924072270001,43.6563415527],"type":"Point"}
}