{
  "type": "Feature",
  "properties": {
    "addr:full":"Rougemont QC J0L 1M0",
    "addr:postcode":"j0l 1m0",
    "iso:country":"CA",
    "sg:city":"Rougemont",
    "sg:classifiers":[
        {
            "category":"Manufacturing",
            "subcategory":"Metals",
            "type":"Manufacturing & Wholesale Goods"
        }
    ],
    "sg:phone":"+1 450 469 4674",
    "sg:postcode":"J0L 1M0",
    "sg:province":"QC",
    "sg:tags":[
        "solder"
    ],
    "wof:name":"Soudure Mobile Rm Inc",
    "wof:placetype":"venue"
},
  "geometry": {"coordinates":[-73.076561,45.44244],"type":"Point"}
}