{
  "type": "Feature",
  "properties": {
    "addr:full":"Rawdon QC J0K 1S0",
    "addr:postcode":"j0k 1s0",
    "iso:country":"CA",
    "sg:city":"Rawdon",
    "sg:classifiers":[
        {
            "category":"Building & Trades",
            "subcategory":"Plumbing",
            "type":"Services"
        }
    ],
    "sg:phone":"+1 450 834 6040",
    "sg:postcode":"J0K 1S0",
    "sg:province":"QC",
    "sg:tags":[
        "contractor"
    ],
    "wof:name":"Plomberie Cascades",
    "wof:placetype":"venue"
},
  "geometry": {"coordinates":[-73.7073669434,46.0426101685],"type":"Point"}
}