{
  "type": "Feature",
  "properties": {
    "addr:full":"Mississauga ON L4Z 1V9",
    "addr:postcode":"l4z 1v9",
    "iso:country":"CA",
    "sg:city":"Mississauga",
    "sg:classifiers":[
        {
            "category":"Professional",
            "subcategory":"Engineering",
            "type":"Services"
        }
    ],
    "sg:phone":"+1 905 896 1346",
    "sg:postcode":"L4Z 1V9",
    "sg:province":"ON",
    "sg:tags":[
        "engineer"
    ],
    "wof:name":"Mc Ewen & Assoc Ltd",
    "wof:placetype":"venue"
},
  "geometry": {"coordinates":[-79.641029,43.600811],"type":"Point"}
}