{
  "type": "Feature",
  "properties": {
    "iso:country":"CA",
    "sg:address":"2225 Preston Ave",
    "sg:city":"Saskatoon",
    "sg:classifiers":[
        {
            "category":"Health Services",
            "subcategory":"Nursing And Care Facility",
            "type":"Services"
        }
    ],
    "sg:phone":"+1 306 374 2242",
    "sg:postcode":"S7J 2E7",
    "sg:province":"SK",
    "sg:tags":[
        "home",
        "convalescent"
    ],
    "wof:name":"Extendicare/Preston",
    "wof:placetype":"venue"
},
  "geometry": {"coordinates":[-106.622383118,52.1035652161],"type":"Point"}
}