{
  "type": "Feature",
  "properties": {
    "addr:full":"Barrie ON L4N 8K8",
    "addr:postcode":"l4n 8k8",
    "iso:country":"CA",
    "sg:city":"Barrie",
    "sg:classifiers":[
        {
            "category":"Health Services",
            "subcategory":"Doctor",
            "type":"Services"
        }
    ],
    "sg:phone":"+1 705 726 0966",
    "sg:postcode":"L4N 8K8",
    "sg:province":"ON",
    "sg:tags":[
        "physician",
        "surgeon"
    ],
    "wof:name":"Mozaffari, Bob MD",
    "wof:placetype":"venue"
},
  "geometry": {"coordinates":[-79.649773,44.365829],"type":"Point"}
}