{
  "type": "Feature",
  "properties": {
    "addr:full":"378 Rue Montpellier Beauport QC G1C 6X6",
    "addr:housenumber":"378",
    "addr:postcode":"qc g1c 6x6",
    "addr:street":"Rue Montpellier",
    "iso:country":"CA",
    "sg:address":"378 Rue Montpellier",
    "sg:city":"Beauport",
    "sg:classifiers":[
        {
            "category":"Food & Beverages",
            "subcategory":"Groceries & Convenience Stores",
            "type":"Retail Goods"
        }
    ],
    "sg:phone":"+1 418 664 1327",
    "sg:postcode":"G1C 6X6",
    "sg:province":"QC",
    "wof:name":"Depanneur Montpellier",
    "wof:placetype":"venue"
},
  "geometry": {"coordinates":[-71.216202,46.879223],"type":"Point"}
}