{
  "type": "Feature",
  "properties": {
    "addr:full":"275 Queen St W Toronto ON M5V 1Z9",
    "addr:housenumber":"275",
    "addr:postcode":"m5v 1z9",
    "addr:street":"Queen St W",
    "iso:country":"CA",
    "sg:address":"275 Queen St W",
    "sg:city":"Toronto",
    "sg:classifiers":[
        {
            "category":"Shopping",
            "subcategory":"Bicycles & Sporting Goods",
            "type":"Retail Goods"
        }
    ],
    "sg:phone":"+1 416 971 6479",
    "sg:postcode":"M5V 1Z9",
    "sg:province":"ON",
    "sg:tags":[
        "clothing"
    ],
    "wof:name":"Noise",
    "wof:placetype":"venue"
},
  "geometry": {"coordinates":[-79.38980865480001,43.6501045227],"type":"Point"}
}