{
  "type": "Feature",
  "properties": {
    "addr:full":"4913 Rue Lionel-Groulx Saint-Augustin-DE-Desmaures QC G3A 1V1",
    "addr:housenumber":"4913",
    "addr:postcode":"g3a 1v1",
    "addr:street":"Rue Lionel-Groulx",
    "iso:country":"CA",
    "sg:address":"4913 Rue Lionel-Groulx",
    "sg:city":"Saint-Augustin-DE-Desmaures",
    "sg:classifiers":[
        {
            "category":"Professional",
            "subcategory":"Management & Consulting",
            "type":"Services"
        }
    ],
    "sg:phone":"+1 418 872 6989",
    "sg:postcode":"G3A 1V1",
    "sg:province":"QC",
    "sg:tags":[
        "food",
        "facility"
    ],
    "wof:name":"Sanilogik Technologies",
    "wof:placetype":"venue"
},
  "geometry": {"coordinates":[-71.384613,46.737419],"type":"Point"}
}