{
  "type": "Feature",
  "properties": {
    "addr:full":"1125 Talbot St St Thomas ON N5P 3W7",
    "addr:housenumber":"1125",
    "addr:postcode":"n5p 3w7",
    "addr:street":"Talbot St",
    "iso:country":"CA",
    "sg:address":"1125 Talbot St",
    "sg:city":"St Thomas",
    "sg:classifiers":[
        {
            "category":"Wholesale",
            "subcategory":"Non-durable Goods",
            "type":"Manufacturing & Wholesale Goods"
        }
    ],
    "sg:phone":"+1 519 631 7660",
    "sg:postcode":"N5P 3W7",
    "sg:province":"ON",
    "sg:tags":[
        "pet",
        "shop",
        "supply"
    ],
    "wof:name":"Hartz Canada Inc",
    "wof:placetype":"venue"
},
  "geometry": {"coordinates":[-81.16651153559999,42.7788276672],"type":"Point"}
}