{
  "type": "Feature",
  "properties": {
    "iso:country":"CA",
    "sg:address":"1464 St. Paul St",
    "sg:city":"Kelowna",
    "sg:classifiers":[
        {
            "category":"Health Services",
            "subcategory":"Clinic",
            "type":"Services"
        }
    ],
    "sg:phone":"+1 250 762 3125",
    "sg:postcode":"V1Y 2E6",
    "sg:province":"BC",
    "wof:name":"Boisselle, Eugene R",
    "wof:placetype":"venue"
},
  "geometry": {"coordinates":[-119.492095947,49.8873252869],"type":"Point"}
}