{
  "type": "Feature",
  "properties": {
    "addr:full":"Edmonton AB T5H 2X6",
    "addr:postcode":"t5h 2x6",
    "iso:country":"CA",
    "sg:city":"Edmonton",
    "sg:classifiers":[
        {
            "category":"Manufacturing",
            "subcategory":"Printing",
            "type":"Manufacturing & Wholesale Goods"
        }
    ],
    "sg:phone":"+1 780 429 1073",
    "sg:postcode":"T5H 2X6",
    "sg:province":"AB",
    "sg:tags":[
        "publication"
    ],
    "wof:name":"Canada A-Z Oil Gas Mining",
    "wof:placetype":"venue"
},
  "geometry": {"coordinates":[-113.503044,53.548702],"type":"Point"}
}