{
  "type": "Feature",
  "properties": {
    "addr:full":"4424 Colonel Talbot Rd London ON N6P 1P9",
    "addr:housenumber":"4424",
    "addr:postcode":"n6p 1p9",
    "addr:street":"Colonel Talbot Rd",
    "iso:country":"CA",
    "sg:address":"4424 Colonel Talbot Rd",
    "sg:city":"London",
    "sg:classifiers":[
        {
            "category":"Travel",
            "subcategory":"Travel Agent",
            "type":"Entertainment"
        }
    ],
    "sg:phone":"+1 519 652 2052",
    "sg:postcode":"N6P 1P9",
    "sg:province":"ON",
    "sg:tags":[
        "agency",
        "bureau"
    ],
    "wof:name":"Travel Express",
    "wof:placetype":"venue"
},
  "geometry": {"coordinates":[-81.2983703613,42.906452179],"type":"Point"}
}