{
  "type": "Feature",
  "properties": {
    "addr:full":"Oakville ON L6J 1J5",
    "addr:postcode":"l6j 1j5",
    "iso:country":"CA",
    "sg:city":"Oakville",
    "sg:classifiers":[
        {
            "category":"Health Services",
            "subcategory":"Doctor",
            "type":"Services"
        }
    ],
    "sg:phone":"+1 905 338 2311",
    "sg:postcode":"L6J 1J5",
    "sg:province":"ON",
    "sg:tags":[
        "physician",
        "surgeon"
    ],
    "wof:name":"Mac Gregor, Todd MD",
    "wof:placetype":"venue"
},
  "geometry": {"coordinates":[-79.6652755737,43.4487419128],"type":"Point"}
}