{
  "type": "Feature",
  "properties": {
    "addr:full":"Blainville QC J7C 2N5",
    "addr:postcode":"j7c 2n5",
    "iso:country":"CA",
    "sg:city":"Blainville",
    "sg:classifiers":[
        {
            "category":"Home & Garden",
            "subcategory":"Building Materials",
            "type":"Retail Goods"
        }
    ],
    "sg:phone":"+1 450 430 2918",
    "sg:postcode":"J7C 2N5",
    "sg:province":"QC",
    "sg:tags":[
        "siding",
        "door",
        "contractor"
    ],
    "wof:name":"J P Lauzon & Fils Ltee",
    "wof:placetype":"venue"
},
  "geometry": {"coordinates":[-73.895325,45.683174],"type":"Point"}
}