{
  "type": "Feature",
  "properties": {
    "addr:full":"Orleans ON K1E 3E6",
    "addr:postcode":"k1e 3e6",
    "iso:country":"CA",
    "sg:city":"Orleans",
    "sg:classifiers":[
        {
            "category":"Personal",
            "subcategory":"Tanning Parlor",
            "type":"Services"
        }
    ],
    "sg:phone":"+1 613 841 0342",
    "sg:postcode":"K1E 3E6",
    "sg:province":"ON",
    "sg:tags":[
        "salon"
    ],
    "wof:name":"Sunsplash Tanning",
    "wof:placetype":"venue"
},
  "geometry": {"coordinates":[-75.4953155518,45.4659347534],"type":"Point"}
}