{
  "type": "Feature",
  "properties": {
    "addr:full":"Surrey BC V3S 6J8",
    "addr:postcode":"v3s 6j8",
    "iso:country":"CA",
    "sg:city":"Surrey",
    "sg:classifiers":[
        {
            "category":"Retail",
            "subcategory":"Auto Repair",
            "type":"Services"
        }
    ],
    "sg:phone":"+1 604 534 0411",
    "sg:postcode":"V3S 6J8",
    "sg:province":"BC",
    "sg:tags":[
        "truck"
    ],
    "wof:name":"T & G Mobile Truck Repair Ltd",
    "wof:placetype":"venue"
},
  "geometry": {"coordinates":[-122.687866,49.107986],"type":"Point"}
}