{
  "type": "Feature",
  "properties": {
    "addr:full":"1000 Stevenson Rd N Oshawa ON L1J 5P5",
    "addr:housenumber":"1000",
    "addr:postcode":"l1j 5p5",
    "addr:street":"Stevenson Rd N",
    "iso:country":"CA",
    "sg:address":"1000 Stevenson Rd N",
    "sg:city":"Oshawa",
    "sg:classifiers":[
        {
            "category":"Organizations",
            "subcategory":"Professional Association",
            "type":"Services"
        }
    ],
    "sg:phone":"+1 905 728 6199",
    "sg:postcode":"L1J 5P5",
    "sg:province":"ON",
    "wof:name":"Ontario Regiment Museum Ferret",
    "wof:placetype":"venue"
},
  "geometry": {"coordinates":[-78.894897,43.91692],"type":"Point"}
}