{
  "type": "Feature",
  "properties": {
    "iso:country":"CA",
    "sg:city":"Brampton",
    "sg:classifiers":[
        {
            "category":"Restaurant",
            "type":"Food & Drink"
        }
    ],
    "sg:phone":"+1 905 457 5557",
    "sg:postcode":"L6Y 4M3",
    "sg:province":"ON",
    "sg:tags":[
        "pizza"
    ],
    "wof:name":"City South Pizza Inc",
    "wof:placetype":"venue"
},
  "geometry": {"coordinates":[-79.725601,43.660057],"type":"Point"}
}