{
  "type": "Feature",
  "properties": {
    "addr:full":"756 Dundas St Woodstock ON N4S 1E9",
    "addr:housenumber":"756",
    "addr:postcode":"n4s 1e9",
    "addr:street":"Dundas St",
    "iso:country":"CA",
    "sg:address":"756 Dundas St",
    "sg:city":"Woodstock",
    "sg:classifiers":[
        {
            "category":"Autos & Motor Vehicles",
            "subcategory":"Fuel & Gas Station",
            "type":"Retail Goods"
        }
    ],
    "sg:phone":"+1 519 421 0558",
    "sg:postcode":"N4S 1E9",
    "sg:province":"ON",
    "sg:tags":[
        "oil"
    ],
    "wof:name":"Maple Leaf Gas & Fuels Ltd",
    "wof:placetype":"venue"
},
  "geometry": {"coordinates":[-80.744789,43.131687],"type":"Point"}
}