{
  "type": "Feature",
  "properties": {
    "addr:full":"Etobicoke ON M9W 6X9",
    "addr:postcode":"m9w 6x9",
    "iso:country":"CA",
    "sg:city":"Etobicoke",
    "sg:classifiers":[
        {
            "category":"Building & Trades",
            "subcategory":"Construction",
            "type":"Services"
        }
    ],
    "sg:phone":"+1 416 213 0558",
    "sg:postcode":"M9W 6X9",
    "sg:province":"ON",
    "sg:tags":[
        "roofing",
        "contractor"
    ],
    "wof:name":"Aseal Roofing & Sheet Metal",
    "wof:placetype":"venue"
},
  "geometry": {"coordinates":[-79.5896224976,43.7032546997],"type":"Point"}
}