{
  "type": "Feature",
  "properties": {
    "iso:country":"CA",
    "sg:address":"888 Meadowlands Dr",
    "sg:city":"Ottawa",
    "sg:classifiers":[
        {
            "category":"Restaurant",
            "type":"Food & Drink"
        }
    ],
    "sg:phone":"+1 613 226 2261",
    "sg:postcode":"K2C 3R2",
    "sg:province":"ON",
    "wof:name":"Mc Donald's",
    "wof:placetype":"venue"
},
  "geometry": {"coordinates":[-75.7014083862,45.3681793213],"type":"Point"}
}