{
  "type": "Feature",
  "properties": {
    "addr:full":"3570 Dutch Village Rd # A Halifax NS B3N 2S2",
    "addr:housenumber":"3570",
    "addr:postcode":"b3n 2s2",
    "addr:street":"Dutch Village Rd # A",
    "iso:country":"CA",
    "sg:address":"3570 Dutch Village Rd # A",
    "sg:city":"Halifax",
    "sg:classifiers":[
        {
            "category":"Professional",
            "subcategory":"Accounting & Tax Preparation",
            "type":"Services"
        }
    ],
    "sg:phone":"+1 902 443 3100",
    "sg:postcode":"B3N 2S2",
    "sg:province":"NS",
    "sg:tags":[
        "return",
        "filing"
    ],
    "wof:name":"A Plus Accounting & Tax Svc",
    "wof:placetype":"venue"
},
  "geometry": {"coordinates":[-63.6322822571,44.6569633484],"type":"Point"}
}