{
  "type": "Feature",
  "properties": {
    "iso:country":"CA",
    "sg:address":"170 the Donway W # 122",
    "sg:city":"North York",
    "sg:classifiers":[
        {
            "category":"Shopping",
            "subcategory":"Clothing, Apparel, & Fashions",
            "type":"Retail Goods"
        }
    ],
    "sg:phone":"+1 416 383 0137",
    "sg:postcode":"M3C 2G3",
    "sg:province":"ON",
    "wof:name":"Casual Nonsense",
    "wof:placetype":"venue"
},
  "geometry": {"coordinates":[-79.34838104249999,43.7346992493],"type":"Point"}
}