{
  "type": "Feature",
  "properties": {
    "addr:full":"Hearst ON P0L 1N0",
    "addr:postcode":"p0l 1n0",
    "iso:country":"CA",
    "sg:city":"Hearst",
    "sg:classifiers":[
        {
            "category":"Health Services",
            "subcategory":"Optometrist",
            "type":"Services"
        }
    ],
    "sg:phone":"+1 705 362 4247",
    "sg:postcode":"P0L 1N0",
    "sg:province":"ON",
    "wof:name":"Guindon, J L OD",
    "wof:placetype":"venue"
},
  "geometry": {"coordinates":[-83.681175,49.690174],"type":"Point"}
}