{
  "type": "Feature",
  "properties": {
    "iso:country":"CA",
    "sg:address":"17 Mary St",
    "sg:city":"Aurora",
    "sg:classifiers":[
        {
            "category":"Retail",
            "subcategory":"Repair Shop",
            "type":"Services"
        }
    ],
    "sg:phone":"+1 905 841 8444",
    "sg:postcode":"L4G 1G1",
    "sg:province":"ON",
    "sg:tags":[
        "upholsterer"
    ],
    "wof:name":"Morra Custom Upholstery Ltd",
    "wof:placetype":"venue"
},
  "geometry": {"coordinates":[-79.456146,43.998779],"type":"Point"}
}