{
  "type": "Feature",
  "properties": {
    "iso:country":"CA",
    "sg:address":"9515 93 St",
    "sg:city":"Sexsmith",
    "sg:classifiers":[
        {
            "category":"Organizations",
            "subcategory":"Religious Organization",
            "type":"Services"
        }
    ],
    "sg:phone":"+1 780 568 4360",
    "sg:postcode":"T0H 3C0",
    "sg:province":"AB",
    "sg:tags":[
        "church"
    ],
    "wof:name":"Grace Bible Fellowship Church",
    "wof:placetype":"venue"
},
  "geometry": {"coordinates":[-118.774299622,55.3506889343],"type":"Point"}
}