{
  "type": "Feature",
  "properties": {
    "addr:full":"1101 Prince of Wales Dr Ottawa ON K2C 3W7",
    "addr:housenumber":"1101",
    "addr:postcode":"k2c 3w7",
    "addr:street":"Prince Of Wales Dr",
    "iso:country":"CA",
    "sg:address":"1101 Prince of Wales Dr",
    "sg:city":"Ottawa",
    "sg:classifiers":[
        {
            "category":"Social Services",
            "subcategory":"Job Training",
            "type":"Services"
        }
    ],
    "sg:phone":"+1 613 723 1033",
    "sg:postcode":"K2C 3W7",
    "sg:province":"ON",
    "sg:tags":[
        "rehabilitation",
        "association"
    ],
    "wof:name":"Canadian Paraplegic Assn",
    "wof:placetype":"venue"
},
  "geometry": {"coordinates":[-75.70591,45.377338],"type":"Point"}
}