{
  "type": "Feature",
  "properties": {
    "addr:full":"64 Mission Rd Wawa ON P0S 1K0",
    "addr:housenumber":"64",
    "addr:postcode":"p0s 1k0",
    "addr:street":"Mission Rd",
    "iso:country":"CA",
    "sg:address":"64 Mission Rd",
    "sg:city":"Wawa",
    "sg:classifiers":[
        {
            "category":"Travel",
            "subcategory":"Hotels & Motels",
            "type":"Entertainment"
        }
    ],
    "sg:phone":"+1 705 856 2294",
    "sg:postcode":"P0S 1K0",
    "sg:province":"ON",
    "wof:name":"Beaver Motel",
    "wof:placetype":"venue"
},
  "geometry": {"coordinates":[-84.778419,47.987602],"type":"Point"}
}