{
  "type": "Feature",
  "properties": {
    "addr:full":"692 Rue Daigle Thetford Mines QC G6G 7W6",
    "addr:housenumber":"692",
    "addr:postcode":"g6g 7w6",
    "addr:street":"Rue Daigle",
    "iso:country":"CA",
    "sg:address":"692 Rue Daigle",
    "sg:city":"Thetford Mines",
    "sg:classifiers":[
        {
            "category":"Personal",
            "subcategory":"Beauty Salon",
            "type":"Services"
        }
    ],
    "sg:phone":"+1 418 338 2399",
    "sg:postcode":"G6G 7W6",
    "sg:province":"QC",
    "wof:name":"Salon Nuance Coiffure Enr",
    "wof:placetype":"venue"
},
  "geometry": {"coordinates":[-71.3001327515,46.1054763794],"type":"Point"}
}