{
  "type": "Feature",
  "properties": {
    "addr:full":"7733 Boul Newman Lasalle QC H8N 1X7",
    "addr:housenumber":"7733",
    "addr:postcode":"h8n 1x7",
    "addr:street":"Boul Newman",
    "iso:country":"CA",
    "sg:address":"7733 Boul Newman",
    "sg:city":"Lasalle",
    "sg:classifiers":[
        {
            "category":"Freight",
            "type":"Transportation"
        }
    ],
    "sg:phone":"+1 514 366 0303",
    "sg:postcode":"H8N 1X7",
    "sg:province":"QC",
    "sg:tags":[
        "trucking"
    ],
    "wof:name":"Imperial Logistics Inc",
    "wof:placetype":"venue"
},
  "geometry": {"coordinates":[-73.623916626,45.4382247925],"type":"Point"}
}