{
  "type": "Feature",
  "properties": {
    "iso:country":"CA",
    "sg:address":"50 Grosvenor Blvd",
    "sg:city":"St Albert",
    "sg:classifiers":[
        {
            "category":"Education",
            "subcategory":"School",
            "type":"Public Place"
        }
    ],
    "sg:phone":"+1 780 459 4456",
    "sg:postcode":"T8N 0X6",
    "sg:province":"AB",
    "wof:name":"Sir George Simpson School",
    "wof:placetype":"venue"
},
  "geometry": {"coordinates":[-113.623497009,53.6204452515],"type":"Point"}
}