{
  "type": "Feature",
  "properties": {
    "iso:country":"CA",
    "sg:address":"235 32nd Ave E",
    "sg:city":"Vancouver",
    "sg:classifiers":[
        {
            "category":"Wholesale",
            "subcategory":"Medical Equipment & Supplies",
            "type":"Manufacturing & Wholesale Goods"
        }
    ],
    "sg:phone":"+1 604 876 4133",
    "sg:postcode":"V5V 2Y2",
    "sg:province":"BC",
    "sg:tags":[
        "physician",
        "surgeon"
    ],
    "wof:name":"Chair Stuff",
    "wof:placetype":"venue"
},
  "geometry": {"coordinates":[-123.100334167,49.2424316406],"type":"Point"}
}