{
  "type": "Feature",
  "properties": {
    "iso:country":"CA",
    "sg:city":"Montreal",
    "sg:classifiers":[
        {
            "category":"Wholesale",
            "subcategory":"Apparel",
            "type":"Manufacturing & Wholesale Goods"
        }
    ],
    "sg:phone":"+1 514 383 5279",
    "sg:postcode":"H2N 1B6",
    "sg:province":"QC",
    "sg:tags":[
        "manufacturer"
    ],
    "wof:name":"Agence Michel Cadorette",
    "wof:placetype":"venue"
},
  "geometry": {"coordinates":[-73.6513671875,45.5496635437],"type":"Point"}
}