{
  "type": "Feature",
  "properties": {
    "addr:full":"203 5th Ave N Swan River MB R0L 1Z0",
    "addr:housenumber":"203",
    "addr:postcode":"r0l 1z0",
    "addr:street":"5Th Ave N",
    "iso:country":"CA",
    "sg:address":"203 5th Ave N",
    "sg:city":"Swan River",
    "sg:classifiers":[
        {
            "category":"Health Services",
            "subcategory":"Chiropractor",
            "type":"Services"
        }
    ],
    "sg:phone":"+1 204 734 3840",
    "sg:postcode":"R0L 1Z0",
    "sg:province":"MB",
    "wof:name":"John M Borley Chiropractic Cln",
    "wof:placetype":"venue"
},
  "geometry": {"coordinates":[-101.26877594,52.1045799255],"type":"Point"}
}