{
  "type": "Feature",
  "properties": {
    "iso:country":"CA",
    "sg:city":"Brampton",
    "sg:classifiers":[
        {
            "category":"Health Services",
            "subcategory":"Doctor",
            "type":"Services"
        }
    ],
    "sg:phone":"+1 905 793 8177",
    "sg:postcode":"L6T 3R5",
    "sg:province":"ON",
    "sg:tags":[
        "dentist"
    ],
    "wof:name":"Bram Care Dental Ctr",
    "wof:placetype":"venue"
},
  "geometry": {"coordinates":[-79.723366,43.717297],"type":"Point"}
}