{
  "type": "Feature",
  "properties": {
    "iso:country":"CA",
    "sg:city":"Waterloo",
    "sg:classifiers":[
        {
            "category":"Food & Beverages",
            "subcategory":"Specialty",
            "type":"Retail Goods"
        }
    ],
    "sg:phone":"+1 519 886 5178",
    "sg:postcode":"N2J 4R8",
    "sg:province":"ON",
    "sg:tags":[
        "health",
        "diet"
    ],
    "wof:name":"Nature's Pharm",
    "wof:placetype":"venue"
},
  "geometry": {"coordinates":[-80.518166,43.485786],"type":"Point"}
}