{
  "type": "Feature",
  "properties": {
    "addr:full":"3934 Gordon Rd Regina SK S4S 6Y3",
    "addr:housenumber":"3934",
    "addr:postcode":"s4s 6y3",
    "addr:street":"Gordon Rd",
    "iso:country":"CA",
    "sg:address":"3934 Gordon Rd",
    "sg:city":"Regina",
    "sg:classifiers":[
        {
            "category":"Professional",
            "subcategory":"Accounting & Tax Preparation",
            "type":"Services"
        }
    ],
    "sg:phone":"+1 306 584 9702",
    "sg:postcode":"S4S 6Y3",
    "sg:province":"SK",
    "sg:tags":[
        "accountant"
    ],
    "wof:name":"Catton & Emery",
    "wof:placetype":"venue"
},
  "geometry": {"coordinates":[-104.637687683,50.4056243896],"type":"Point"}
}