{
  "type": "Feature",
  "properties": {
    "addr:full":"5386 Imperial St Burnaby BC V5J 1E6",
    "addr:housenumber":"5386",
    "addr:postcode":"v5j 1e6",
    "addr:street":"Imperial St",
    "iso:country":"CA",
    "sg:address":"5386 Imperial St",
    "sg:city":"Burnaby",
    "sg:classifiers":[
        {
            "category":"Wholesale",
            "subcategory":"Construction Materials",
            "type":"Manufacturing & Wholesale Goods"
        }
    ],
    "sg:phone":"+1 604 431 8900",
    "sg:postcode":"V5J 1E6",
    "sg:province":"BC",
    "sg:tags":[
        "building"
    ],
    "wof:name":"Lpc Metal Spindles & Casting",
    "wof:placetype":"venue"
},
  "geometry": {"coordinates":[-122.985984802,49.2217025757],"type":"Point"}
}