{
  "type": "Feature",
  "properties": {
    "iso:country":"CA",
    "sg:address":"1501 Moraine Rd NE",
    "sg:city":"Calgary",
    "sg:classifiers":[
        {
            "category":"Manufacturing",
            "subcategory":"Petroleum Products",
            "type":"Manufacturing & Wholesale Goods"
        }
    ],
    "sg:phone":"+1 403 207 1616",
    "sg:postcode":"T2A 2P5",
    "sg:province":"AB",
    "sg:tags":[
        "lubricating",
        "oil",
        "grease"
    ],
    "wof:name":"Chris Page & Assoc",
    "wof:placetype":"venue"
},
  "geometry": {"coordinates":[-113.99546814,51.0651855469],"type":"Point"}
}