{
  "type": "Feature",
  "properties": {
    "iso:country":"CA",
    "sg:city":"London",
    "sg:classifiers":[
        {
            "category":"Manufacturing",
            "subcategory":"Printing",
            "type":"Manufacturing & Wholesale Goods"
        }
    ],
    "sg:phone":"+1 519 668 7480",
    "sg:postcode":"N5Z 3M5",
    "sg:province":"ON",
    "sg:tags":[
        "screen"
    ],
    "wof:name":"Tnt Shirts",
    "wof:placetype":"venue"
},
  "geometry": {"coordinates":[-81.214355,42.961491],"type":"Point"}
}