{
  "type": "Feature",
  "properties": {
    "addr:full":"2703 Meighen Rd Windsor ON N8W 4C7",
    "addr:housenumber":"2703",
    "addr:postcode":"n8w 4c7",
    "addr:street":"Meighen Rd",
    "iso:country":"CA",
    "sg:address":"2703 Meighen Rd",
    "sg:city":"Windsor",
    "sg:classifiers":[
        {
            "category":"Manufacturing",
            "subcategory":"Glass & Minerals",
            "type":"Manufacturing & Wholesale Goods"
        }
    ],
    "sg:phone":"+1 519 945 5573",
    "sg:postcode":"N8W 4C7",
    "sg:province":"ON",
    "sg:tags":[
        "granite",
        "mantel"
    ],
    "wof:name":"Lebcan Marble & Granite Ltd",
    "wof:placetype":"venue"
},
  "geometry": {"coordinates":[-82.9781417847,42.2939224243],"type":"Point"}
}