{
  "type": "Feature",
  "properties": {
    "addr:full":"2121 Nathaway Dr Youngs Point ON K0L 3G0",
    "addr:housenumber":"2121",
    "addr:postcode":"k0l 3g0",
    "addr:street":"Nathaway Dr Youngs",
    "iso:country":"CA",
    "sg:address":"2121 Nathaway Dr",
    "sg:city":"Youngs Point",
    "sg:classifiers":[
        {
            "category":"Recreation",
            "subcategory":"Marina",
            "type":"Entertainment"
        }
    ],
    "sg:phone":"+1 705 652 8563",
    "sg:postcode":"K0L 3G0",
    "sg:province":"ON",
    "wof:name":"Young's Point Marina",
    "wof:placetype":"venue"
},
  "geometry": {"coordinates":[-78.234489,44.489426],"type":"Point"}
}