{
  "type": "Feature",
  "properties": {
    "addr:full":"48 Point St. Mark Dr #A Kingston ON K7K 6L4",
    "addr:housenumber":"48",
    "addr:postcode":"k7k 6l4",
    "addr:street":"Point St. Mark Dr # A",
    "iso:country":"CA",
    "sg:address":"48 Point St. Mark Dr #A",
    "sg:city":"Kingston",
    "sg:classifiers":[
        {
            "category":"Recreation",
            "subcategory":"Marina",
            "type":"Entertainment"
        }
    ],
    "sg:phone":"+1 613 546 6234",
    "sg:postcode":"K7K 6L4",
    "sg:province":"ON",
    "wof:name":"Rideau Marina",
    "wof:placetype":"venue"
},
  "geometry": {"coordinates":[-76.464844,44.253952],"type":"Point"}
}