{
  "type": "Feature",
  "properties": {
    "addr:full":"100 Cheapside St London ON N6A 1Z8",
    "addr:housenumber":"100",
    "addr:postcode":"n6a 1z8",
    "addr:street":"Cheapside St",
    "iso:country":"CA",
    "sg:address":"100 Cheapside St",
    "sg:city":"London",
    "sg:classifiers":[
        {
            "category":"Organizations",
            "subcategory":"Professional Association",
            "type":"Services"
        }
    ],
    "sg:phone":"+1 519 667 0050",
    "sg:postcode":"N6A 1Z8",
    "sg:province":"ON",
    "wof:name":"Kappa Alpha Theta",
    "wof:placetype":"venue"
},
  "geometry": {"coordinates":[-81.2583312988,43.0012702942],"type":"Point"}
}