{
  "type": "Feature",
  "properties": {
    "addr:full":"2238 Ch Gascon Terrebonne QC J6X 3A1",
    "addr:housenumber":"2238",
    "addr:postcode":"j6x 3a1",
    "addr:street":"Ch Gascon",
    "iso:country":"CA",
    "sg:address":"2238 Ch Gascon",
    "sg:city":"Terrebonne",
    "sg:classifiers":[
        {
            "category":"Restaurant",
            "type":"Food & Drink"
        }
    ],
    "sg:phone":"+1 450 471 6606",
    "sg:postcode":"J6X 3A1",
    "sg:province":"QC",
    "wof:name":"Joe Le Roi Du Sous-Marin Inc",
    "wof:placetype":"venue"
},
  "geometry": {"coordinates":[-73.6633758545,45.7225952148],"type":"Point"}
}