{
  "type": "Feature",
  "properties": {
    "addr:full":"Scarborough ON M1B 4Y5",
    "addr:postcode":"m1b 4y5",
    "iso:country":"CA",
    "sg:city":"Scarborough",
    "sg:classifiers":[
        {
            "category":"Manufacturing",
            "subcategory":"Metals",
            "type":"Manufacturing & Wholesale Goods"
        }
    ],
    "sg:phone":"+1 416 282 7277",
    "sg:postcode":"M1B 4Y5",
    "sg:province":"ON",
    "sg:tags":[
        "brass",
        "product"
    ],
    "wof:name":"Adag Creative Metal Ltd",
    "wof:placetype":"venue"
},
  "geometry": {"coordinates":[-79.20178199999999,43.807579],"type":"Point"}
}