{
  "type": "Feature",
  "properties": {
    "iso:country":"CA",
    "sg:address":"312 Pine St",
    "sg:city":"Ignace",
    "sg:classifiers":[
        {
            "category":"Social Services",
            "subcategory":"Child Care",
            "type":"Services"
        }
    ],
    "sg:phone":"+1 807 934 6696",
    "sg:postcode":"P0T 1T0",
    "sg:province":"ON",
    "wof:name":"Ignace Nursery School",
    "wof:placetype":"venue"
},
  "geometry": {"coordinates":[-91.6588134766,49.417678833],"type":"Point"}
}