{
  "type": "Feature",
  "properties": {
    "addr:full":"194 Cranwell Close SE Calgary AB T3M 1A9",
    "addr:housenumber":"194",
    "addr:postcode":"t3m 1a9",
    "addr:street":"Cranwell Close Se",
    "iso:country":"CA",
    "sg:address":"194 Cranwell Close SE",
    "sg:city":"Calgary",
    "sg:classifiers":[
        {
            "category":"Professional",
            "type":"Services"
        }
    ],
    "sg:phone":"+1 403 289 6332",
    "sg:postcode":"T3M 1A9",
    "sg:province":"AB",
    "sg:tags":[
        "geophysical"
    ],
    "wof:name":"Techo Geophysical Svc Ltd",
    "wof:placetype":"venue"
},
  "geometry": {"coordinates":[-113.98535156200001,50.8894615173],"type":"Point"}
}