{
  "type": "Feature",
  "properties": {
    "addr:full":"1876 Kennedy Rd Scarborough ON M1P 2L8",
    "addr:housenumber":"1876",
    "addr:postcode":"m1p 2l8",
    "addr:street":"Kennedy Rd",
    "iso:country":"CA",
    "sg:address":"1876 Kennedy Rd",
    "sg:city":"Scarborough",
    "sg:classifiers":[
        {
            "category":"Restaurant",
            "type":"Food & Drink"
        }
    ],
    "sg:phone":"+1 416 291 3553",
    "sg:postcode":"M1P 2L8",
    "sg:province":"ON",
    "wof:name":"Chinese Hut Restaurant",
    "wof:placetype":"venue"
},
  "geometry": {"coordinates":[-79.2813796997,43.7662849426],"type":"Point"}
}