{
  "type": "Feature",
  "properties": {
    "addr:full":"480 Rang Brule Saint-Thomas QC J0K 3L0",
    "addr:housenumber":"480",
    "addr:postcode":"j0k 3l0",
    "addr:street":"Rang Brule",
    "iso:country":"CA",
    "sg:address":"480 Rang Brule",
    "sg:city":"Saint-Thomas",
    "sg:classifiers":[
        {
            "category":"Wholesale",
            "subcategory":"Machinery & Supplies",
            "type":"Manufacturing & Wholesale Goods"
        }
    ],
    "sg:phone":"+1 450 759 9547",
    "sg:postcode":"J0K 3L0",
    "sg:province":"QC",
    "sg:tags":[
        "farm",
        "equipment"
    ],
    "wof:name":"Machineries Del-Mont-Guay Inc",
    "wof:placetype":"venue"
},
  "geometry": {"coordinates":[-73.332207,46.007835],"type":"Point"}
}