{
  "type": "Feature",
  "properties": {
    "iso:country":"CA",
    "sg:address":"1102 9th Ave W",
    "sg:city":"Kindersley",
    "sg:classifiers":[
        {
            "category":"Building & Trades",
            "subcategory":"Construction",
            "type":"Services"
        }
    ],
    "sg:phone":"+1 306 463 6309",
    "sg:postcode":"S0L 1S0",
    "sg:province":"SK",
    "sg:tags":[
        "sandblasting"
    ],
    "wof:name":"Braeco Industrial",
    "wof:placetype":"venue"
},
  "geometry": {"coordinates":[-109.17011261,51.4728431702],"type":"Point"}
}