{
  "type": "Feature",
  "properties": {
    "addr:full":"2545 Chrysler Ctr Windsor ON N8W 5M4",
    "addr:housenumber":"2545",
    "addr:postcode":"n8w 5m4",
    "addr:street":"Chrysler Ctr",
    "iso:country":"CA",
    "sg:address":"2545 Chrysler Ctr",
    "sg:city":"Windsor",
    "sg:classifiers":[
        {
            "category":"Professional",
            "subcategory":"Management & Consulting",
            "type":"Services"
        }
    ],
    "sg:phone":"+1 519 977 0777",
    "sg:postcode":"N8W 5M4",
    "sg:province":"ON",
    "sg:tags":[
        "food"
    ],
    "wof:name":"Compass Group Canada",
    "wof:placetype":"venue"
},
  "geometry": {"coordinates":[-82.9839019775,42.2959403992],"type":"Point"}
}