{
  "type": "Feature",
  "properties": {
    "addr:full":"461 Rue Principale Pohenegamook QC G0L 1J0",
    "addr:housenumber":"461",
    "addr:postcode":"g0l 1j0",
    "addr:street":"Rue Principale",
    "iso:country":"CA",
    "sg:address":"461 Rue Principale",
    "sg:city":"Pohenegamook",
    "sg:classifiers":[
        {
            "category":"Shopping",
            "subcategory":"Bicycles & Sporting Goods",
            "type":"Retail Goods"
        }
    ],
    "sg:phone":"+1 418 893 5332",
    "sg:postcode":"G0L 1J0",
    "sg:province":"QC",
    "wof:name":"Marcel Cossette Ltee",
    "wof:placetype":"venue"
},
  "geometry": {"coordinates":[-69.158249,47.457333],"type":"Point"}
}