{
  "type": "Feature",
  "properties": {
    "addr:full":"1640 Av Diesel Quebec QC G1P 4J5",
    "addr:housenumber":"1640",
    "addr:postcode":"g1p 4j5",
    "addr:street":"Av Diesel",
    "iso:country":"CA",
    "sg:address":"1640 Av Diesel",
    "sg:city":"Quebec",
    "sg:classifiers":[
        {
            "category":"Manufacturing",
            "subcategory":"Metals",
            "type":"Manufacturing & Wholesale Goods"
        }
    ],
    "sg:phone":"+1 418 687 4141",
    "sg:postcode":"G1P 4J5",
    "sg:province":"QC",
    "sg:tags":[
        "steel"
    ],
    "wof:name":"Metal Inc",
    "wof:placetype":"venue"
},
  "geometry": {"coordinates":[-71.2963485718,46.8052444458],"type":"Point"}
}