{
  "type": "Feature",
  "properties": {
    "addr:full":"2 Railway Ave Glendon AB T0A 1P0",
    "addr:housenumber":"2",
    "addr:postcode":"t0a 1p0",
    "addr:street":"Railway Ave",
    "iso:country":"CA",
    "sg:address":"2 Railway Ave",
    "sg:city":"Glendon",
    "sg:classifiers":[
        {
            "category":"Food & Beverages",
            "subcategory":"Liquor & Beverages",
            "type":"Retail Goods"
        }
    ],
    "sg:phone":"+1 780 635 3944",
    "sg:postcode":"T0A 1P0",
    "sg:province":"AB",
    "sg:tags":[
        "store"
    ],
    "wof:name":"Glendon Liquor Store",
    "wof:placetype":"venue"
},
  "geometry": {"coordinates":[-111.155975342,54.2511291504],"type":"Point"}
}