{
  "type": "Feature",
  "properties": {
    "addr:full":"24 Huron St W Exeter ON N0M 1S2",
    "addr:housenumber":"24",
    "addr:postcode":"n0m 1s2",
    "addr:street":"Huron St W",
    "iso:country":"CA",
    "sg:address":"24 Huron St W",
    "sg:city":"Exeter",
    "sg:classifiers":[
        {
            "category":"Social Services",
            "type":"Services"
        }
    ],
    "sg:phone":"+1 519 235 2510",
    "sg:postcode":"N0M 1S2",
    "sg:province":"ON",
    "sg:tags":[
        "organization",
        "welfare"
    ],
    "wof:name":"Von Palliative Care Program",
    "wof:placetype":"venue"
},
  "geometry": {"coordinates":[-81.48077392579999,43.3436088562],"type":"Point"}
}