{
  "type": "Feature",
  "properties": {
    "addr:full":"Waterloo QC J0E 2N0",
    "addr:postcode":"j0e 2n0",
    "iso:country":"CA",
    "sg:city":"Waterloo",
    "sg:classifiers":[
        {
            "category":"Freight",
            "type":"Transportation"
        }
    ],
    "sg:phone":"+1 450 539 0348",
    "sg:postcode":"J0E 2N0",
    "sg:province":"QC",
    "sg:tags":[
        "trucking"
    ],
    "wof:name":"Michael Duff Inc",
    "wof:placetype":"venue"
},
  "geometry": {"coordinates":[-72.53435500000001,45.356873],"type":"Point"}
}