{
  "type": "Feature",
  "properties": {
    "addr:full":"595 Mount Pleasant Rd Toronto ON M4S 2M5",
    "addr:housenumber":"595",
    "addr:postcode":"m4s 2m5",
    "addr:street":"Mount Pleasant Rd",
    "iso:country":"CA",
    "sg:address":"595 Mount Pleasant Rd",
    "sg:city":"Toronto",
    "sg:classifiers":[
        {
            "category":"Home & Garden",
            "subcategory":"Home Furnishings",
            "type":"Retail Goods"
        }
    ],
    "sg:phone":"+1 416 487 1047",
    "sg:postcode":"M4S 2M5",
    "sg:province":"ON",
    "sg:tags":[
        "quilting"
    ],
    "wof:name":"Quilters' Quarters",
    "wof:placetype":"venue"
},
  "geometry": {"coordinates":[-79.3881072998,43.7037353516],"type":"Point"}
}