{
  "type": "Feature",
  "properties": {
    "addr:full":"128 Leland Rd London ON N6K 1T3",
    "addr:housenumber":"128",
    "addr:postcode":"n6k 1t3",
    "addr:street":"Leland Rd",
    "iso:country":"CA",
    "sg:address":"128 Leland Rd",
    "sg:city":"London",
    "sg:classifiers":[
        {
            "category":"Building & Trades",
            "subcategory":"Landscaping Services",
            "type":"Services"
        }
    ],
    "sg:phone":"+1 519 471 3300",
    "sg:postcode":"N6K 1T3",
    "sg:province":"ON",
    "sg:tags":[
        "lawn",
        "maintenance",
        "grounds"
    ],
    "wof:name":"Mc Kinley Horticultural Svc",
    "wof:placetype":"venue"
},
  "geometry": {"coordinates":[-81.29888916020001,42.9473609924],"type":"Point"}
}