{
  "type": "Feature",
  "properties": {
    "addr:full":"75 Boul Kirkland Kirkland QC H9J 1N5",
    "addr:housenumber":"75",
    "addr:postcode":"h9j 1n5",
    "addr:street":"Boul Kirkland",
    "iso:country":"CA",
    "sg:address":"75 Boul Kirkland",
    "sg:city":"Kirkland",
    "sg:classifiers":[
        {
            "category":"Organizations",
            "subcategory":"Religious Organization",
            "type":"Services"
        }
    ],
    "sg:phone":"+1 514 695 6812",
    "sg:postcode":"H9J 1N5",
    "sg:province":"QC",
    "sg:tags":[
        "church"
    ],
    "wof:name":"St-Mary's Anglican Church",
    "wof:placetype":"venue"
},
  "geometry": {"coordinates":[-73.859695,45.442493],"type":"Point"}
}