{
  "type": "Feature",
  "properties": {
    "addr:full":"1945 55E Av Dorval QC H9P 1G9",
    "addr:housenumber":"1945",
    "addr:postcode":"h9p 1g9",
    "addr:street":"55E Av",
    "iso:country":"CA",
    "sg:address":"1945 55E Av",
    "sg:city":"Dorval",
    "sg:classifiers":[
        {
            "category":"Wholesale",
            "subcategory":"Machinery & Supplies",
            "type":"Manufacturing & Wholesale Goods"
        }
    ],
    "sg:phone":"+1 514 636 4950",
    "sg:postcode":"H9P 1G9",
    "sg:province":"QC",
    "sg:tags":[
        "contractor"
    ],
    "wof:name":"Equipement Federal Quebec Ltee",
    "wof:placetype":"venue"
},
  "geometry": {"coordinates":[-73.7236862183,45.4578704834],"type":"Point"}
}