{
  "type": "Feature",
  "properties": {
    "addr:full":"Calgary AB T2E 2S6",
    "addr:postcode":"t2e 2s6",
    "iso:country":"CA",
    "sg:city":"Calgary",
    "sg:classifiers":[
        {
            "category":"Personal",
            "subcategory":"Beauty Salon",
            "type":"Services"
        }
    ],
    "sg:phone":"+1 403 276 1130",
    "sg:postcode":"T2E 2S6",
    "sg:province":"AB",
    "wof:name":"Supercuts",
    "wof:placetype":"venue"
},
  "geometry": {"coordinates":[-114.062309265,51.0680809021],"type":"Point"}
}