{
  "type": "Feature",
  "properties": {
    "addr:full":"Mississauga ON L5B 1N1",
    "addr:postcode":"l5b 1n1",
    "iso:country":"CA",
    "sg:city":"Mississauga",
    "sg:classifiers":[
        {
            "category":"Health Services",
            "subcategory":"Doctor",
            "type":"Services"
        }
    ],
    "sg:phone":"+1 905 270 4700",
    "sg:postcode":"L5B 1N1",
    "sg:province":"ON",
    "sg:tags":[
        "dentist"
    ],
    "wof:name":"Andrews, Paul DDS",
    "wof:placetype":"venue"
},
  "geometry": {"coordinates":[-79.609177,43.575005],"type":"Point"}
}