{
  "type": "Feature",
  "properties": {
    "addr:full":"107 Stanley St Cupar SK S0G 0Y0",
    "addr:housenumber":"107",
    "addr:postcode":"s0g 0y0",
    "addr:street":"Stanley St",
    "iso:country":"CA",
    "sg:address":"107 Stanley St",
    "sg:city":"Cupar",
    "sg:classifiers":[
        {
            "category":"Home & Garden",
            "subcategory":"Hardware",
            "type":"Retail Goods"
        }
    ],
    "sg:phone":"+1 306 723 4355",
    "sg:postcode":"S0G 0Y0",
    "sg:province":"SK",
    "wof:name":"Mac Leod's Family Shopping Ctr",
    "wof:placetype":"venue"
},
  "geometry": {"coordinates":[-104.211624145,50.9502906799],"type":"Point"}
}