{
  "type": "Feature",
  "properties": {
    "addr:full":"254 Erie St S Leamington ON N8H 3C3",
    "addr:housenumber":"254",
    "addr:postcode":"n8h 3c3",
    "addr:street":"Erie St S",
    "iso:country":"CA",
    "sg:address":"254 Erie St S",
    "sg:city":"Leamington",
    "sg:classifiers":[
        {
            "category":"Travel",
            "subcategory":"Travel Agent",
            "type":"Entertainment"
        }
    ],
    "sg:phone":"+1 519 326 2675",
    "sg:postcode":"N8H 3C3",
    "sg:province":"ON",
    "sg:tags":[
        "agency",
        "bureau"
    ],
    "wof:name":"Travel Pro's",
    "wof:placetype":"venue"
},
  "geometry": {"coordinates":[-82.600548,42.039394],"type":"Point"}
}