{
  "type": "Feature",
  "properties": {
    "addr:full":"3229 Boul Saint-Jean-Baptiste Chicoutimi QC G7H 7V5",
    "addr:housenumber":"3229",
    "addr:postcode":"g7h 7v5",
    "addr:street":"Boul Saint-Jean-Baptiste",
    "iso:country":"CA",
    "sg:address":"3229 Boul Saint-Jean-Baptiste",
    "sg:city":"Chicoutimi",
    "sg:classifiers":[
        {
            "category":"Manufacturing",
            "subcategory":"Furniture",
            "type":"Manufacturing & Wholesale Goods"
        }
    ],
    "sg:phone":"+1 418 549 5466",
    "sg:postcode":"G7H 7V5",
    "sg:province":"QC",
    "sg:tags":[
        "maker",
        "mattress"
    ],
    "wof:name":"Matelas Lion D'Or",
    "wof:placetype":"venue"
},
  "geometry": {"coordinates":[-70.9740142822,48.3871116638],"type":"Point"}
}