{
  "type": "Feature",
  "properties": {
    "addr:full":"1250 Brant St # 301 Burlington ON L7P 1X8",
    "addr:housenumber":"1250",
    "addr:postcode":"l7p 1x8",
    "addr:street":"Brant St # 301",
    "iso:country":"CA",
    "sg:address":"1250 Brant St # 301",
    "sg:city":"Burlington",
    "sg:classifiers":[
        {
            "category":"Restaurant",
            "type":"Food & Drink"
        }
    ],
    "sg:phone":"+1 905 315 8423",
    "sg:postcode":"L7P 1X8",
    "sg:province":"ON",
    "sg:tags":[
        "health",
        "diet"
    ],
    "wof:name":"Booster Juice",
    "wof:placetype":"venue"
},
  "geometry": {"coordinates":[-79.8267211914,43.3448066711],"type":"Point"}
}