{
  "type": "Feature",
  "properties": {
    "addr:full":"163 Idema Rd Markham ON L3R 1A9",
    "addr:housenumber":"163",
    "addr:postcode":"l3r 1a9",
    "addr:street":"Idema Rd",
    "iso:country":"CA",
    "sg:address":"163 Idema Rd",
    "sg:city":"Markham",
    "sg:classifiers":[
        {
            "category":"Professional",
            "subcategory":"Engineering",
            "type":"Services"
        }
    ],
    "sg:phone":"+1 905 474 0800",
    "sg:postcode":"L3R 1A9",
    "sg:province":"ON",
    "sg:tags":[
        "engineer"
    ],
    "wof:name":"Haronitis & Assoc Ltd",
    "wof:placetype":"venue"
},
  "geometry": {"coordinates":[-79.3539657593,43.8154258728],"type":"Point"}
}