{
  "type": "Feature",
  "properties": {
    "iso:country":"CA",
    "sg:city":"Brampton",
    "sg:classifiers":[
        {
            "category":"Education",
            "subcategory":"Special Training",
            "type":"Public Place"
        }
    ],
    "sg:phone":"+1 905 453 1400",
    "sg:postcode":"L6T 4W8",
    "sg:province":"ON",
    "sg:tags":[
        "instruction",
        "driving"
    ],
    "wof:name":"United Truck Training Svc Ltd",
    "wof:placetype":"venue"
},
  "geometry": {"coordinates":[-79.6982345581,43.6906051636],"type":"Point"}
}