{
  "type": "Feature",
  "properties": {
    "addr:full":"1438 148 Rte O Campbell's Bay QC J0X 1K0",
    "addr:housenumber":"1438",
    "addr:postcode":"j0x 1k0",
    "addr:street":"148 Rte O",
    "iso:country":"CA",
    "sg:address":"1438 148 Rte O",
    "sg:city":"Campbell's Bay",
    "sg:classifiers":[
        {
            "category":"Wholesale",
            "subcategory":"Auto Parts",
            "type":"Manufacturing & Wholesale Goods"
        }
    ],
    "sg:phone":"+1 819 648 5570",
    "sg:postcode":"J0X 1K0",
    "sg:province":"QC",
    "sg:tags":[
        "automobile",
        "scooter",
        "motorcycle",
        "motor"
    ],
    "wof:name":"Cpm Ltee",
    "wof:placetype":"venue"
},
  "geometry": {"coordinates":[-65.95812225340001,48.3070640564],"type":"Point"}
}