{
  "type": "Feature",
  "properties": {
    "iso:country":"CA",
    "sg:address":"4664 Yonge St",
    "sg:city":"North York",
    "sg:classifiers":[
        {
            "category":"Shopping",
            "subcategory":"Florist",
            "type":"Retail Goods"
        }
    ],
    "sg:phone":"+1 416 227 1600",
    "sg:postcode":"M2N 5M1",
    "sg:province":"ON",
    "wof:name":"Orchard's Florists",
    "wof:placetype":"venue"
},
  "geometry": {"coordinates":[-79.4102630615,43.7580108643],"type":"Point"}
}