{
  "type": "Feature",
  "properties": {
    "addr:full":"98 Ashwarren Rd North York ON M3J 2S6",
    "addr:housenumber":"98",
    "addr:postcode":"m3j 2s6",
    "addr:street":"Ashwarren Rd",
    "iso:country":"CA",
    "sg:address":"98 Ashwarren Rd",
    "sg:city":"North York",
    "sg:classifiers":[
        {
            "category":"Autos & Motor Vehicles",
            "subcategory":"Automobile Sales",
            "type":"Retail Goods"
        }
    ],
    "sg:phone":"+1 416 630 0007",
    "sg:postcode":"M3J 2S6",
    "sg:province":"ON",
    "sg:tags":[
        "car",
        "dealer"
    ],
    "wof:name":"Autobella Inc",
    "wof:placetype":"venue"
},
  "geometry": {"coordinates":[-79.48420715330001,43.75756073],"type":"Point"}
}