{
  "type": "Feature",
  "properties": {
    "addr:full":"1120 Caledonia Rd #12 North York ON M6A 2W5",
    "addr:housenumber":"1120",
    "addr:postcode":"m6a 2w5",
    "addr:street":"Caledonia Rd # 12",
    "iso:country":"CA",
    "sg:address":"1120 Caledonia Rd #12",
    "sg:city":"North York",
    "sg:classifiers":[
        {
            "category":"Retail",
            "subcategory":"Repair Shop",
            "type":"Services"
        }
    ],
    "sg:phone":"+1 416 256 7222",
    "sg:postcode":"M6A 2W5",
    "sg:province":"ON",
    "sg:tags":[
        "lock",
        "locksmith"
    ],
    "wof:name":"Reilly Lock",
    "wof:placetype":"venue"
},
  "geometry": {"coordinates":[-79.467224,43.713348],"type":"Point"}
}