{
  "type": "Feature",
  "properties": {
    "addr:full":"652 Norfolk St S Simcoe ON N3Y 4K1",
    "addr:housenumber":"652",
    "addr:postcode":"n3y 4k1",
    "addr:street":"Norfolk St S",
    "iso:country":"CA",
    "sg:address":"652 Norfolk St S",
    "sg:city":"Simcoe",
    "sg:classifiers":[
        {
            "category":"Shopping",
            "subcategory":"Florist",
            "type":"Retail Goods"
        }
    ],
    "sg:phone":"+1 519 426 3190",
    "sg:postcode":"N3Y 4K1",
    "sg:province":"ON",
    "sg:tags":[
        "garden",
        "center"
    ],
    "wof:name":"King Flower & Garden Ctr",
    "wof:placetype":"venue"
},
  "geometry": {"coordinates":[-80.2954940796,42.8133163452],"type":"Point"}
}