{
  "type": "Feature",
  "properties": {
    "addr:full":"124 Walsh Cres NW Edmonton AB T5T 5L7",
    "addr:housenumber":"124",
    "addr:postcode":"t5t 5l7",
    "addr:street":"Walsh Cres Nw",
    "iso:country":"CA",
    "sg:address":"124 Walsh Cres NW",
    "sg:city":"Edmonton",
    "sg:classifiers":[
        {
            "category":"Wholesale",
            "subcategory":"Construction Materials",
            "type":"Manufacturing & Wholesale Goods"
        }
    ],
    "sg:phone":"+1 780 486 5273",
    "sg:postcode":"T5T 5L7",
    "sg:province":"AB",
    "sg:tags":[
        "sand",
        "gravel"
    ],
    "wof:name":"Lynch, Fred",
    "wof:placetype":"venue"
},
  "geometry": {"coordinates":[-113.612625122,53.5055160522],"type":"Point"}
}