{
  "type": "Feature",
  "properties": {
    "addr:full":"7925 East Saanich Rd Saanichton BC V8M 1T4",
    "addr:housenumber":"7925",
    "addr:postcode":"v8m 1t4",
    "addr:street":"East Saanich Rd",
    "iso:country":"CA",
    "sg:address":"7925 East Saanich Rd",
    "sg:city":"Saanichton",
    "sg:classifiers":[
        {
            "category":"Organizations",
            "subcategory":"Religious Organization",
            "type":"Services"
        }
    ],
    "sg:phone":"+1 250 544 0005",
    "sg:postcode":"V8M 1T4",
    "sg:province":"BC",
    "sg:tags":[
        "church"
    ],
    "wof:name":"Centre For Self-Awareness",
    "wof:placetype":"venue"
},
  "geometry": {"coordinates":[-123.416595,48.597878],"type":"Point"}
}