{
  "type": "Feature",
  "properties": {
    "addr:full":"151 Boul DE Mortagne Boucherville QC J4B 6G4",
    "addr:housenumber":"151",
    "addr:postcode":"j4b 6g4",
    "addr:street":"Boul De Mortagne",
    "iso:country":"CA",
    "sg:address":"151 Boul DE Mortagne",
    "sg:city":"Boucherville",
    "sg:classifiers":[
        {
            "category":"Professional",
            "subcategory":"Business Services",
            "type":"Services"
        }
    ],
    "sg:phone":"+1 450 641 1153",
    "sg:postcode":"J4B 6G4",
    "sg:province":"QC",
    "sg:tags":[
        "notary"
    ],
    "wof:name":"Perreault, Alain",
    "wof:placetype":"venue"
},
  "geometry": {"coordinates":[-73.447014,45.577713],"type":"Point"}
}