{
  "type": "Feature",
  "properties": {
    "addr:full":"15 Paultiel Dr North York ON M2M 3P4",
    "addr:housenumber":"15",
    "addr:postcode":"m2m 3p4",
    "addr:street":"Paultiel Dr",
    "iso:country":"CA",
    "sg:address":"15 Paultiel Dr",
    "sg:city":"North York",
    "sg:classifiers":[
        {
            "category":"Wholesale",
            "subcategory":"Machinery & Supplies",
            "type":"Manufacturing & Wholesale Goods"
        }
    ],
    "sg:phone":"+1 416 250 7596",
    "sg:postcode":"M2M 3P4",
    "sg:province":"ON",
    "sg:tags":[
        "compressor",
        "gas"
    ],
    "wof:name":"Anac Machine & Tool Ltd",
    "wof:placetype":"venue"
},
  "geometry": {"coordinates":[-79.39806400000001,43.796974],"type":"Point"}
}