{
  "type": "Feature",
  "properties": {
    "addr:full":"821 17th Ave W Vancouver BC V5Z 1V3",
    "addr:housenumber":"821",
    "addr:postcode":"v5z 1v3",
    "addr:street":"17Th Ave W",
    "iso:country":"CA",
    "sg:address":"821 17th Ave W",
    "sg:city":"Vancouver",
    "sg:classifiers":[
        {
            "category":"Professional",
            "subcategory":"Computer Services",
            "type":"Services"
        }
    ],
    "sg:phone":"+1 604 871 9811",
    "sg:postcode":"V5Z 1V3",
    "sg:province":"BC",
    "sg:tags":[
        "internet"
    ],
    "wof:name":"Electric Playground Web",
    "wof:placetype":"venue"
},
  "geometry": {"coordinates":[-123.122597,49.256344],"type":"Point"}
}