{
  "type": "Feature",
  "properties": {
    "iso:country":"CA",
    "sg:address":"RR 1",
    "sg:city":"Hepworth",
    "sg:classifiers":[
        {
            "category":"Government",
            "subcategory":"Office",
            "type":"Public Place"
        }
    ],
    "sg:phone":"+1 519 935 2145",
    "sg:postcode":"N0H 1P0",
    "sg:province":"ON",
    "wof:name":"Ontario Patrol Yard",
    "wof:placetype":"venue"
},
  "geometry": {"coordinates":[-81.131187439,44.6337928772],"type":"Point"}
}