{
  "type": "Feature",
  "properties": {
    "addr:full":"776 Boul Maloney E Gatineau QC J8P 1G6",
    "addr:housenumber":"776",
    "addr:postcode":"j8p 1g6",
    "addr:street":"Boul Maloney E",
    "iso:country":"CA",
    "sg:address":"776 Boul Maloney E",
    "sg:city":"Gatineau",
    "sg:classifiers":[
        {
            "category":"Autos & Motor Vehicles",
            "subcategory":"Boat Sales",
            "type":"Retail Goods"
        }
    ],
    "sg:phone":"+1 819 663 2526",
    "sg:postcode":"J8P 1G6",
    "sg:province":"QC",
    "sg:tags":[
        "dealer"
    ],
    "wof:name":"Brabant & Fils Equipements",
    "wof:placetype":"venue"
},
  "geometry": {"coordinates":[-75.617012,45.48251],"type":"Point"}
}