{
  "type": "Feature",
  "properties": {
    "addr:full":"5865 Boul Henri-Bourassa E Montreal-Nord QC H1G 2V1",
    "addr:housenumber":"5865",
    "addr:postcode":"h1g 2v1",
    "addr:street":"Boul Henri-Bourassa E",
    "iso:country":"CA",
    "sg:address":"5865 Boul Henri-Bourassa E",
    "sg:city":"Montreal-Nord",
    "sg:classifiers":[
        {
            "category":"Food & Beverages",
            "subcategory":"Groceries & Convenience Stores",
            "type":"Retail Goods"
        }
    ],
    "sg:phone":"+1 514 327 1432",
    "sg:postcode":"H1G 2V1",
    "sg:province":"QC",
    "sg:tags":[
        "grocer"
    ],
    "wof:name":"Depanur 7 Jours",
    "wof:placetype":"venue"
},
  "geometry": {"coordinates":[-73.6184310913,45.6074028015],"type":"Point"}
}