{
  "type": "Feature",
  "properties": {
    "addr:full":"76 Hoka St Winnipeg MB R2C 3N2",
    "addr:housenumber":"76",
    "addr:postcode":"r2c 3n2",
    "addr:street":"Hoka St",
    "iso:country":"CA",
    "sg:address":"76 Hoka St",
    "sg:city":"Winnipeg",
    "sg:classifiers":[
        {
            "category":"Wholesale",
            "subcategory":"Scrap",
            "type":"Manufacturing & Wholesale Goods"
        }
    ],
    "sg:phone":"+1 204 222 5096",
    "sg:postcode":"R2C 3N2",
    "sg:province":"MB",
    "sg:tags":[
        "recycling",
        "center"
    ],
    "wof:name":"Phoenix Recycling Inc",
    "wof:placetype":"venue"
},
  "geometry": {"coordinates":[-97.015884,49.890743],"type":"Point"}
}