{
  "type": "Feature",
  "properties": {
    "addr:full":"275 Av Du Ruisseau Lac-Etchemin QC G0R 1S0",
    "addr:postcode":"g0r 1s0",
    "addr:street":"275 Av Du Ruisseau",
    "iso:country":"CA",
    "sg:address":"275 Av Du Ruisseau",
    "sg:city":"Lac-Etchemin",
    "sg:classifiers":[
        {
            "category":"Building & Trades",
            "subcategory":"Construction",
            "type":"Services"
        }
    ],
    "sg:phone":"+1 418 625 3373",
    "sg:postcode":"G0R 1S0",
    "sg:province":"QC",
    "sg:tags":[
        "contractor",
        "general"
    ],
    "wof:name":"Constructions Marc Rancourt",
    "wof:placetype":"venue"
},
  "geometry": {"coordinates":[-70.5266494751,46.4061965942],"type":"Point"}
}