{
  "type": "Feature",
  "properties": {
    "addr:full":"16 Ballycastle Cres Brampton ON L6Z 2V5",
    "addr:housenumber":"16",
    "addr:postcode":"l6z 2v5",
    "addr:street":"Ballycastle Cres",
    "iso:country":"CA",
    "sg:address":"16 Ballycastle Cres",
    "sg:city":"Brampton",
    "sg:classifiers":[
        {
            "category":"Wholesale",
            "subcategory":"Construction Materials",
            "type":"Manufacturing & Wholesale Goods"
        }
    ],
    "sg:phone":"+1 905 846 7132",
    "sg:postcode":"L6Z 2V5",
    "sg:province":"ON",
    "sg:tags":[
        "fence"
    ],
    "wof:name":"B D Fence & Deck",
    "wof:placetype":"venue"
},
  "geometry": {"coordinates":[-79.785225,43.713547],"type":"Point"}
}