{
  "type": "Feature",
  "properties": {
    "iso:country":"CA",
    "sg:address":"888 Rue Sainte-Catherine O",
    "sg:city":"Montreal",
    "sg:classifiers":[
        {
            "category":"Restaurant",
            "type":"Food & Drink"
        }
    ],
    "sg:phone":"+1 514 861 1255",
    "sg:postcode":"H3B 1E2",
    "sg:province":"QC",
    "wof:name":"Reuben's Restaurant Deli",
    "wof:placetype":"venue"
},
  "geometry": {"coordinates":[-73.558014,45.516171],"type":"Point"}
}