{
  "type": "Feature",
  "properties": {
    "iso:country":"CA",
    "sg:address":"520 Silverstone Dr",
    "sg:city":"Etobicoke",
    "sg:classifiers":[
        {
            "category":"Social Services",
            "subcategory":"Child Care",
            "type":"Services"
        }
    ],
    "sg:phone":"+1 416 741 0414",
    "sg:postcode":"M9V 3L5",
    "sg:province":"ON",
    "wof:name":"Silverstone Learning Ctr",
    "wof:placetype":"venue"
},
  "geometry": {"coordinates":[-79.595627,43.738071],"type":"Point"}
}