{
  "type": "Feature",
  "properties": {
    "addr:full":"6345 Dixie Rd # 1A Mississauga ON L5T 2E6",
    "addr:housenumber":"6345",
    "addr:postcode":"l5t 2e6",
    "addr:street":"Dixie Rd # 1A",
    "iso:country":"CA",
    "sg:address":"6345 Dixie Rd # 1A",
    "sg:city":"Mississauga",
    "sg:classifiers":[
        {
            "category":"Restaurant",
            "type":"Food & Drink"
        }
    ],
    "sg:phone":"+1 905 670 5249",
    "sg:postcode":"L5T 2E6",
    "sg:province":"ON",
    "wof:name":"Druxy's Famous Deli Sandwiches",
    "wof:placetype":"venue"
},
  "geometry": {"coordinates":[-79.65645600000001,43.662277],"type":"Point"}
}