{
  "type": "Feature",
  "properties": {
    "addr:full":"60 Fern Rd Lake Cowichan BC V0R 2G0",
    "addr:housenumber":"60",
    "addr:postcode":"v0r 2g0",
    "addr:street":"Fern Rd",
    "iso:country":"CA",
    "sg:address":"60 Fern Rd",
    "sg:city":"Lake Cowichan",
    "sg:classifiers":[
        {
            "category":"Organizations",
            "subcategory":"Religious Organization",
            "type":"Services"
        }
    ],
    "sg:phone":"+1 250 749 4103",
    "sg:postcode":"V0R 2G0",
    "sg:province":"BC",
    "sg:tags":[
        "church"
    ],
    "wof:name":"St Louis DE Montfort Catholic",
    "wof:placetype":"venue"
},
  "geometry": {"coordinates":[-124.05986799999999,48.820427],"type":"Point"}
}