{
  "type": "Feature",
  "properties": {
    "iso:country":"CA",
    "sg:address":"4887 Rue Sherbrooke O",
    "sg:city":"Westmount",
    "sg:classifiers":[
        {
            "category":"Shopping",
            "subcategory":"Stationery & Office Supplies",
            "type":"Retail Goods"
        }
    ],
    "sg:phone":"+1 514 481 2575",
    "sg:postcode":"H3Z 1G9",
    "sg:province":"QC",
    "sg:tags":[
        "stationer"
    ],
    "wof:name":"Westmount Stationery Inc",
    "wof:placetype":"venue"
},
  "geometry": {"coordinates":[-73.604225,45.478512],"type":"Point"}
}