{
  "type": "Feature",
  "properties": {
    "addr:full":"Red Deer AB T4N 4A4",
    "addr:postcode":"t4n 4a4",
    "iso:country":"CA",
    "sg:city":"Red Deer",
    "sg:classifiers":[
        {
            "category":"Health Services",
            "subcategory":"Podiatrist",
            "type":"Services"
        }
    ],
    "sg:phone":"+1 403 340 3343",
    "sg:postcode":"T4N 4A4",
    "sg:province":"AB",
    "wof:name":"Smith, Scott L DPM",
    "wof:placetype":"venue"
},
  "geometry": {"coordinates":[-113.814278,52.26796],"type":"Point"}
}