{
  "type": "Feature",
  "properties": {
    "addr:full":"242 Main St Palmerston ON N0G 2P0",
    "addr:housenumber":"242",
    "addr:postcode":"n0g 2p0",
    "addr:street":"Main St",
    "iso:country":"CA",
    "sg:address":"242 Main St",
    "sg:city":"Palmerston",
    "sg:classifiers":[
        {
            "category":"Real Estate",
            "subcategory":"Real Estate Agent",
            "type":"Services"
        }
    ],
    "sg:phone":"+1 519 343 3619",
    "sg:postcode":"N0G 2P0",
    "sg:province":"ON",
    "wof:name":"Peak Results Realty",
    "wof:placetype":"venue"
},
  "geometry": {"coordinates":[-80.846352,43.834438],"type":"Point"}
}