{
  "type": "Feature",
  "properties": {
    "iso:country":"CA",
    "sg:address":"300 Rue Saint-Louis",
    "sg:city":"Saint-Jean-Sur-Richelieu",
    "sg:classifiers":[
        {
            "category":"Wholesale",
            "subcategory":"Home Furnishings",
            "type":"Manufacturing & Wholesale Goods"
        }
    ],
    "sg:phone":"+1 450 348 4843",
    "sg:postcode":"J3B 1Y4",
    "sg:province":"QC",
    "sg:tags":[
        "rug",
        "carpet"
    ],
    "wof:name":"Lanart Sales Inc",
    "wof:placetype":"venue"
},
  "geometry": {"coordinates":[-73.2671890259,45.3126106262],"type":"Point"}
}