{
  "type": "Feature",
  "properties": {
    "addr:full":"121 Marica Ave Oshawa ON L1G 3G9",
    "addr:housenumber":"121",
    "addr:postcode":"l1g 3g9",
    "addr:street":"Marica Ave",
    "iso:country":"CA",
    "sg:address":"121 Marica Ave",
    "sg:city":"Oshawa",
    "sg:classifiers":[
        {
            "category":"Real Estate",
            "subcategory":"Developer",
            "type":"Services"
        }
    ],
    "sg:phone":"+1 905 723 7711",
    "sg:postcode":"L1G 3G9",
    "sg:province":"ON",
    "sg:tags":[
        "company",
        "land"
    ],
    "wof:name":"William Tonno Construction Ltd",
    "wof:placetype":"venue"
},
  "geometry": {"coordinates":[-78.870583,43.925327],"type":"Point"}
}