{
  "type": "Feature",
  "properties": {
    "addr:full":"808 Alpine 108 Mile Ranch BC V0K 2Z0",
    "addr:housenumber":"808;108",
    "addr:postcode":"v0k 2z0",
    "addr:street":"Alpine;Mile Ranch",
    "iso:country":"CA",
    "sg:address":"808 Alpine",
    "sg:city":"108 Mile Ranch",
    "sg:classifiers":[
        {
            "category":"Shopping",
            "subcategory":"Computers & Home Electronics",
            "type":"Retail Goods"
        }
    ],
    "sg:phone":"+1 250 395 4008",
    "sg:postcode":"V0K 2Z0",
    "sg:province":"BC",
    "sg:tags":[
        "equipment",
        "dealer"
    ],
    "wof:name":"100 Mile House Cyber Site",
    "wof:placetype":"venue"
},
  "geometry": {"coordinates":[-121.34844207800001,51.7511444092],"type":"Point"}
}