{
  "type": "Feature",
  "properties": {
    "iso:country":"CA",
    "sg:city":"London",
    "sg:classifiers":[
        {
            "category":"Health Services",
            "subcategory":"Doctor",
            "type":"Services"
        }
    ],
    "sg:phone":"+1 519 434 5403",
    "sg:postcode":"N6A 5B5",
    "sg:province":"ON",
    "sg:tags":[
        "physician",
        "surgeon"
    ],
    "wof:name":"Sussman, H Leonard MD",
    "wof:placetype":"venue"
},
  "geometry": {"coordinates":[-81.24462127690001,42.9841003418],"type":"Point"}
}