{
  "type": "Feature",
  "properties": {
    "addr:full":"Vancouver BC V5M 3H9",
    "addr:postcode":"v5m 3h9",
    "iso:country":"CA",
    "sg:city":"Vancouver",
    "sg:classifiers":[
        {
            "category":"Professional",
            "subcategory":"Business Services",
            "type":"Services"
        }
    ],
    "sg:phone":"+1 604 215 1762",
    "sg:postcode":"V5M 3H9",
    "sg:province":"BC",
    "sg:tags":[
        "water",
        "treatment"
    ],
    "wof:name":"Tri-Y Enterprises Ltd",
    "wof:placetype":"venue"
},
  "geometry": {"coordinates":[-123.044006,49.268269],"type":"Point"}
}