{
  "type": "Feature",
  "properties": {
    "iso:country":"CA",
    "sg:address":"1555 Regent Ave W",
    "sg:city":"Winnipeg",
    "sg:classifiers":[
        {
            "category":"Restaurant",
            "type":"Food & Drink"
        }
    ],
    "sg:phone":"+1 204 661 5922",
    "sg:postcode":"R2C 4J2",
    "sg:province":"MB",
    "sg:tags":[
        "shop",
        "tea",
        "coffee"
    ],
    "wof:name":"Second Cup",
    "wof:placetype":"venue"
},
  "geometry": {"coordinates":[-97.061829,49.897278],"type":"Point"}
}