{
  "type": "Feature",
  "properties": {
    "addr:full":"907 Michigan Ave Point Edward ON N7V 1H2",
    "addr:housenumber":"907",
    "addr:postcode":"n7v 1h2",
    "addr:street":"Michigan Ave",
    "iso:country":"CA",
    "sg:address":"907 Michigan Ave",
    "sg:city":"Point Edward",
    "sg:classifiers":[
        {
            "category":"Manufacturing",
            "subcategory":"Metals",
            "type":"Manufacturing & Wholesale Goods"
        }
    ],
    "sg:phone":"+1 519 344 4300",
    "sg:postcode":"N7V 1H2",
    "sg:province":"ON",
    "sg:tags":[
        "valve"
    ],
    "wof:name":"Contro Valve Inc",
    "wof:placetype":"venue"
},
  "geometry": {"coordinates":[-82.4009857178,42.9974327087],"type":"Point"}
}