{
  "type": "Feature",
  "properties": {
    "addr:full":"2279 Prince of Wales Dr Nepean ON K2E 6Z8",
    "addr:housenumber":"2279",
    "addr:postcode":"k2e 6z8",
    "addr:street":"Prince Of Wales Dr",
    "iso:country":"CA",
    "sg:address":"2279 Prince of Wales Dr",
    "sg:city":"Nepean",
    "sg:classifiers":[
        {
            "category":"Travel",
            "subcategory":"Hotels & Motels",
            "type":"Entertainment"
        }
    ],
    "sg:phone":"+1 613 226 5312",
    "sg:postcode":"K2E 6Z8",
    "sg:province":"ON",
    "wof:name":"New Highway Inn Motel Inc",
    "wof:placetype":"venue"
},
  "geometry": {"coordinates":[-75.701797,45.326637],"type":"Point"}
}