{
  "type": "Feature",
  "properties": {
    "addr:full":"26 Laidlaw Blvd Markham ON L3P 1W7",
    "addr:housenumber":"26",
    "addr:postcode":"l3p 1w7",
    "addr:street":"Laidlaw Blvd",
    "iso:country":"CA",
    "sg:address":"26 Laidlaw Blvd",
    "sg:city":"Markham",
    "sg:classifiers":[
        {
            "category":"Manufacturing",
            "subcategory":"Food",
            "type":"Manufacturing & Wholesale Goods"
        }
    ],
    "sg:phone":"+1 905 294 7775",
    "sg:postcode":"L3P 1W7",
    "sg:province":"ON",
    "sg:tags":[
        "grocer",
        "product",
        "manufacturer"
    ],
    "wof:name":"Ocean Chinese Food Products",
    "wof:placetype":"venue"
},
  "geometry": {"coordinates":[-79.2786026001,43.8716773987],"type":"Point"}
}