{
  "type": "Feature",
  "properties": {
    "addr:full":"Waterloo ON N2L 3Y2",
    "addr:postcode":"n2l 3y2",
    "iso:country":"CA",
    "sg:city":"Waterloo",
    "sg:classifiers":[
        {
            "category":"Building & Trades",
            "subcategory":"Electrical",
            "type":"Services"
        }
    ],
    "sg:phone":"+1 519 746 5955",
    "sg:postcode":"N2L 3Y2",
    "sg:province":"ON",
    "sg:tags":[
        "electric",
        "contractor"
    ],
    "wof:name":"Shantz & Brubacher Electric",
    "wof:placetype":"venue"
},
  "geometry": {"coordinates":[-80.5322647095,43.4815177917],"type":"Point"}
}