{
  "type": "Feature",
  "properties": {
    "addr:full":"303 Princess St Shallow Lake ON N0H 2K0",
    "addr:housenumber":"303",
    "addr:postcode":"n0h 2k0",
    "addr:street":"Princess St",
    "iso:country":"CA",
    "sg:address":"303 Princess St",
    "sg:city":"Shallow Lake",
    "sg:classifiers":[
        {
            "category":"Manufacturing",
            "subcategory":"Motor Vehicles & Parts",
            "type":"Manufacturing & Wholesale Goods"
        }
    ],
    "sg:phone":"+1 519 935 2146",
    "sg:postcode":"N0H 2K0",
    "sg:province":"ON",
    "sg:tags":[
        "body",
        "equipment",
        "truck"
    ],
    "wof:name":"R Noble & Sons",
    "wof:placetype":"venue"
},
  "geometry": {"coordinates":[-81.08663900000001,44.615009],"type":"Point"}
}