{
  "type": "Feature",
  "properties": {
    "addr:full":"163 Rue Laurier Maniwaki QC J9E 2K6",
    "addr:housenumber":"163",
    "addr:postcode":"j9e 2k6",
    "addr:street":"Rue Laurier",
    "iso:country":"CA",
    "sg:address":"163 Rue Laurier",
    "sg:city":"Maniwaki",
    "sg:classifiers":[
        {
            "category":"Communications",
            "subcategory":"Radio Station",
            "type":"Services"
        }
    ],
    "sg:phone":"+1 819 449 3959",
    "sg:postcode":"J9E 2K6",
    "sg:province":"QC",
    "sg:tags":[
        "company",
        "broadcasting"
    ],
    "wof:name":"Chga",
    "wof:placetype":"venue"
},
  "geometry": {"coordinates":[-75.9763412476,46.3747673035],"type":"Point"}
}