{
  "type": "Feature",
  "properties": {
    "addr:full":"7989 Hoskins St Delta BC V4G 1M4",
    "addr:housenumber":"7989",
    "addr:postcode":"v4g 1m4",
    "addr:street":"Hoskins St",
    "iso:country":"CA",
    "sg:address":"7989 Hoskins St",
    "sg:city":"Delta",
    "sg:classifiers":[
        {
            "category":"Freight",
            "type":"Transportation"
        }
    ],
    "sg:phone":"+1 604 940 2323",
    "sg:postcode":"V4G 1M4",
    "sg:province":"BC",
    "sg:tags":[
        "trucking"
    ],
    "wof:name":"Squamish Freightways Ltd",
    "wof:placetype":"venue"
},
  "geometry": {"coordinates":[-122.999801636,49.1457176208],"type":"Point"}
}