{
  "type": "Feature",
  "properties": {
    "addr:full":"1295 Boul Des Forges Trois-Rivieres QC G8Z 1T7",
    "addr:housenumber":"1295",
    "addr:postcode":"g8z 1t7",
    "addr:street":"Boul Des Forges Trois-Rivieres",
    "iso:country":"CA",
    "sg:address":"1295 Boul Des Forges",
    "sg:city":"Trois-Rivieres",
    "sg:classifiers":[
        {
            "category":"Organizations",
            "subcategory":"Professional Association",
            "type":"Services"
        }
    ],
    "sg:phone":"+1 819 374 5541",
    "sg:postcode":"G8Z 1T7",
    "sg:province":"QC",
    "wof:name":"Parents-Secours Du Quebec Inc",
    "wof:placetype":"venue"
},
  "geometry": {"coordinates":[-72.5545425415,46.3442878723],"type":"Point"}
}