{
  "type": "Feature",
  "properties": {
    "addr:full":"33790 Essendene Ave Abbotsford BC V2S 2H2",
    "addr:housenumber":"33790",
    "addr:postcode":"v2s 2h2",
    "addr:street":"Essendene Ave",
    "iso:country":"CA",
    "sg:address":"33790 Essendene Ave",
    "sg:city":"Abbotsford",
    "sg:classifiers":[
        {
            "category":"Travel",
            "subcategory":"Hotels & Motels",
            "type":"Entertainment"
        }
    ],
    "sg:phone":"+1 604 853 3307",
    "sg:postcode":"V2S 2H2",
    "sg:province":"BC",
    "wof:name":"Fraser Valley Inn",
    "wof:placetype":"venue"
},
  "geometry": {"coordinates":[-122.28929100000001,49.048805],"type":"Point"}
}