{
  "type": "Feature",
  "properties": {
    "addr:full":"651 Boul Saint-Jean-Baptiste Mercier QC J6R 2A3",
    "addr:housenumber":"651",
    "addr:postcode":"j6r 2a3",
    "addr:street":"Boul Saint-Jean-Baptiste",
    "iso:country":"CA",
    "sg:address":"651 Boul Saint-Jean-Baptiste",
    "sg:city":"Mercier",
    "sg:classifiers":[
        {
            "category":"Autos & Motor Vehicles",
            "subcategory":"Fuel & Gas Station",
            "type":"Retail Goods"
        }
    ],
    "sg:phone":"+1 450 698 1411",
    "sg:postcode":"J6R 2A3",
    "sg:province":"QC",
    "sg:tags":[
        "oil"
    ],
    "wof:name":"Petro Canada",
    "wof:placetype":"venue"
},
  "geometry": {"coordinates":[-73.739112854,45.321105957],"type":"Point"}
}