{
  "type": "Feature",
  "properties": {
    "addr:full":"2985 Dougall Ave Windsor ON N9E 1S1",
    "addr:postcode":"2985;n9e 1s1",
    "addr:street":"Dougall Ave",
    "iso:country":"CA",
    "sg:address":"2985 Dougall Ave",
    "sg:city":"Windsor",
    "sg:classifiers":[
        {
            "category":"Real Estate",
            "subcategory":"Real Estate Agent",
            "type":"Services"
        }
    ],
    "sg:phone":"+1 519 966 7777",
    "sg:postcode":"N9E 1S1",
    "sg:province":"ON",
    "wof:name":"Remo Valente Real Estate Ltd",
    "wof:placetype":"venue"
},
  "geometry": {"coordinates":[-83.0144500732,42.2735328674],"type":"Point"}
}