{
  "type": "Feature",
  "properties": {
    "addr:full":"Vancouver BC V6B 1R8",
    "addr:postcode":"v6b 1r8",
    "iso:country":"CA",
    "sg:city":"Vancouver",
    "sg:classifiers":[
        {
            "category":"Arts & Performance",
            "subcategory":"Theater",
            "type":"Entertainment"
        }
    ],
    "sg:phone":"+1 604 685 0345",
    "sg:postcode":"V6B 1R8",
    "sg:province":"BC",
    "sg:tags":[
        "talent",
        "agency",
        "casting"
    ],
    "wof:name":"Lucas Talent",
    "wof:placetype":"venue"
},
  "geometry": {"coordinates":[-123.10779599999999,49.281048],"type":"Point"}
}