{
  "type": "Feature",
  "properties": {
    "addr:full":"10611 109 St NW Edmonton AB T5H 3B5",
    "addr:housenumber":"10611",
    "addr:postcode":"t5h 3b5",
    "addr:street":"109 St Nw",
    "iso:country":"CA",
    "sg:address":"10611 109 St NW",
    "sg:city":"Edmonton",
    "sg:classifiers":[
        {
            "category":"Building & Trades",
            "subcategory":"Construction",
            "type":"Services"
        }
    ],
    "sg:phone":"+1 780 428 9100",
    "sg:postcode":"T5H 3B5",
    "sg:province":"AB",
    "sg:tags":[
        "general",
        "contractor"
    ],
    "wof:name":"Genex Construction Ltd",
    "wof:placetype":"venue"
},
  "geometry": {"coordinates":[-113.50829299999999,53.550102],"type":"Point"}
}