{
  "type": "Feature",
  "properties": {
    "iso:country":"CA",
    "sg:address":"127 Peter St N",
    "sg:city":"Orillia",
    "sg:classifiers":[
        {
            "category":"Health Services",
            "subcategory":"Nursing And Care Facility",
            "type":"Services"
        }
    ],
    "sg:phone":"+1 705 325 8383",
    "sg:postcode":"L3V 4Z4",
    "sg:province":"ON",
    "sg:tags":[
        "home",
        "retirement",
        "convalescent",
        "community"
    ],
    "wof:name":"Tudhope Manor",
    "wof:placetype":"venue"
},
  "geometry": {"coordinates":[-79.42087554930001,44.6126899719],"type":"Point"}
}