{
  "type": "Feature",
  "properties": {
    "addr:full":"529 Vaughan Rd York ON M6C 2R1",
    "addr:housenumber":"529",
    "addr:postcode":"m6c 2r1",
    "addr:street":"Vaughan Rd",
    "iso:country":"CA",
    "sg:address":"529 Vaughan Rd",
    "sg:city":"York",
    "sg:classifiers":[
        {
            "category":"Social Services",
            "subcategory":"Child Care",
            "type":"Services"
        }
    ],
    "sg:phone":"+1 416 658 1874",
    "sg:postcode":"M6C 2R1",
    "sg:province":"ON",
    "wof:name":"Vaughan Road Infant & Tdlr Ctr",
    "wof:placetype":"venue"
},
  "geometry": {"coordinates":[-79.43612670900001,43.6902656555],"type":"Point"}
}