{
  "type": "Feature",
  "properties": {
    "iso:country":"CA",
    "sg:city":"Mississauga",
    "sg:classifiers":[
        {
            "category":"Professional",
            "subcategory":"Management & Consulting",
            "type":"Services"
        }
    ],
    "sg:phone":"+1 905 819 1600",
    "sg:postcode":"L5N 6S2",
    "sg:province":"ON",
    "sg:tags":[
        "roofing",
        "consultant"
    ],
    "wof:name":"Premier /Levaque Inc",
    "wof:placetype":"venue"
},
  "geometry": {"coordinates":[-79.7734909058,43.6038017273],"type":"Point"}
}