{
  "type": "Feature",
  "properties": {
    "addr:full":"2447 Candace St Saint John NB E2J 2Z8",
    "addr:housenumber":"2447",
    "addr:postcode":"nb e2j 2z8",
    "addr:street":"Candace St",
    "iso:country":"CA",
    "sg:address":"2447 Candace St",
    "sg:city":"Saint John",
    "sg:classifiers":[
        {
            "category":"Retail",
            "subcategory":"Repair Shop",
            "type":"Services"
        }
    ],
    "sg:phone":"+1 506 696 8168",
    "sg:postcode":"E2J 2Z8",
    "sg:province":"NB",
    "sg:tags":[
        "lock",
        "locksmith"
    ],
    "wof:name":"Mr Deadbolt",
    "wof:placetype":"venue"
},
  "geometry": {"coordinates":[-65.99968,45.31078],"type":"Point"}
}