{
  "type": "Feature",
  "properties": {
    "iso:country":"CA",
    "sg:city":"Kelowna",
    "sg:classifiers":[
        {
            "category":"Building & Trades",
            "subcategory":"Construction",
            "type":"Services"
        }
    ],
    "sg:phone":"+1 250 491 5818",
    "sg:postcode":"V1X 1W7",
    "sg:province":"BC",
    "sg:tags":[
        "insulation",
        "heat",
        "contractor"
    ],
    "wof:name":"Okanagan Insulation Svc Ltd",
    "wof:placetype":"venue"
},
  "geometry": {"coordinates":[-119.387771606,49.8881721497],"type":"Point"}
}