{
  "type": "Feature",
  "properties": {
    "iso:country":"CA",
    "sg:address":"24 Emerald St S",
    "sg:city":"Hamilton",
    "sg:classifiers":[
        {
            "category":"Social Services",
            "type":"Services"
        }
    ],
    "sg:phone":"+1 905 529 8494",
    "sg:postcode":"L8N 2V2",
    "sg:province":"ON",
    "sg:tags":[
        "organization",
        "welfare"
    ],
    "wof:name":"St Leonard's Treatment Ctr",
    "wof:placetype":"venue"
},
  "geometry": {"coordinates":[-79.8547592163,43.2524185181],"type":"Point"}
}