{
  "type": "Feature",
  "properties": {
    "addr:full":"1550 Lake Trail Rd Courtenay BC V9N 9C2",
    "addr:housenumber":"1550",
    "addr:postcode":"v9n 9c2",
    "addr:street":"Lake Trail Rd",
    "iso:country":"CA",
    "sg:address":"1550 Lake Trail Rd",
    "sg:city":"Courtenay",
    "sg:classifiers":[
        {
            "category":"Social Services",
            "type":"Services"
        }
    ],
    "sg:phone":"+1 250 338 2700",
    "sg:postcode":"V9N 9C2",
    "sg:province":"BC",
    "sg:tags":[
        "counselor",
        "marriage",
        "family"
    ],
    "wof:name":"Pacific Therapy & Consulting",
    "wof:placetype":"venue"
},
  "geometry": {"coordinates":[-125.010383606,49.6803207397],"type":"Point"}
}