{
  "type": "Feature",
  "properties": {
    "iso:country":"CA",
    "sg:address":"6824 Boul Joseph-Renaud",
    "sg:city":"Anjou",
    "sg:classifiers":[
        {
            "category":"Personal",
            "subcategory":"Beauty Salon",
            "type":"Services"
        }
    ],
    "sg:phone":"+1 514 351 3364",
    "sg:postcode":"H1K 3V4",
    "sg:province":"QC",
    "sg:tags":[
        "manicuring"
    ],
    "wof:name":"Ongles Dt",
    "wof:placetype":"venue"
},
  "geometry": {"coordinates":[-73.55275726319999,45.6051101685],"type":"Point"}
}