{
  "type": "Feature",
  "properties": {
    "addr:full":"12850 87 Ave Surrey BC V3W 3H9",
    "addr:housenumber":"12850",
    "addr:postcode":"v3w 3h9",
    "addr:street":"87 Ave",
    "iso:country":"CA",
    "sg:address":"12850 87 Ave",
    "sg:city":"Surrey",
    "sg:classifiers":[
        {
            "category":"Manufacturing",
            "subcategory":"Metals",
            "type":"Manufacturing & Wholesale Goods"
        }
    ],
    "sg:phone":"+1 604 594 5404",
    "sg:postcode":"V3W 3H9",
    "sg:province":"BC",
    "sg:tags":[
        "valve"
    ],
    "wof:name":"Singer Valve",
    "wof:placetype":"venue"
},
  "geometry": {"coordinates":[-122.867271,49.160671],"type":"Point"}
}