{
  "type": "Feature",
  "properties": {
    "addr:full":"6604 Rama Rd Orillia ON L3V 6H6",
    "addr:housenumber":"6604",
    "addr:postcode":"l3v 6h6",
    "addr:street":"Rama Rd",
    "iso:country":"CA",
    "sg:address":"6604 Rama Rd",
    "sg:city":"Orillia",
    "sg:classifiers":[
        {
            "category":"Social Services",
            "type":"Services"
        }
    ],
    "sg:phone":"+1 705 325 2253",
    "sg:postcode":"L3V 6H6",
    "sg:province":"ON",
    "sg:tags":[
        "center",
        "facility",
        "youth",
        "convention",
        "organization",
        "meeting"
    ],
    "wof:name":"Ymca Geneva Park Conference",
    "wof:placetype":"venue"
},
  "geometry": {"coordinates":[-79.41822814939999,44.606590271],"type":"Point"}
}