{
  "type": "Feature",
  "properties": {
    "addr:full":"Medicine Hat AB T1A 0G9",
    "addr:postcode":"t1a 0g9",
    "iso:country":"CA",
    "sg:city":"Medicine Hat",
    "sg:classifiers":[
        {
            "category":"Mining & Drilling",
            "type":"Manufacturing & Wholesale Goods"
        }
    ],
    "sg:phone":"+1 403 504 4078",
    "sg:postcode":"T1A 0G9",
    "sg:province":"AB",
    "sg:tags":[
        "consultant",
        "oil",
        "gas"
    ],
    "wof:name":"Echo Environmental",
    "wof:placetype":"venue"
},
  "geometry": {"coordinates":[-110.679283142,50.0383644104],"type":"Point"}
}