{
  "type": "Feature",
  "properties": {
    "addr:full":"4304 41 Ave NW Edmonton AB T6L 5Y6",
    "addr:housenumber":"4304",
    "addr:postcode":"t6l 5y6",
    "addr:street":"41 Ave Nw",
    "iso:country":"CA",
    "sg:address":"4304 41 Ave NW",
    "sg:city":"Edmonton",
    "sg:classifiers":[
        {
            "category":"Education",
            "subcategory":"School",
            "type":"Public Place"
        }
    ],
    "sg:phone":"+1 780 462 4622",
    "sg:postcode":"T6L 5Y6",
    "sg:province":"AB",
    "wof:name":"Julia Kiniski School",
    "wof:placetype":"venue"
},
  "geometry": {"coordinates":[-113.405998,53.477161],"type":"Point"}
}