{
  "type": "Feature",
  "properties": {
    "iso:country":"CA",
    "sg:city":"Gold Bridge",
    "sg:classifiers":[
        {
            "category":"Mining & Drilling",
            "type":"Manufacturing & Wholesale Goods"
        }
    ],
    "sg:phone":"+1 250 238 2273",
    "sg:postcode":"V0K 1P0",
    "sg:province":"BC",
    "sg:tags":[
        "contractor"
    ],
    "wof:name":"Oniva International Svc Corp",
    "wof:placetype":"venue"
},
  "geometry": {"coordinates":[-122.84909820599999,50.851360321],"type":"Point"}
}