{
  "type": "Feature",
  "properties": {
    "addr:full":"4807 50th Ave Gibbons AB T0A 1N0",
    "addr:housenumber":"4807",
    "addr:postcode":"t0a 1n0",
    "addr:street":"50Th Ave",
    "iso:country":"CA",
    "sg:address":"4807 50th Ave",
    "sg:city":"Gibbons",
    "sg:classifiers":[
        {
            "category":"Education",
            "subcategory":"Library",
            "type":"Public Place"
        }
    ],
    "sg:phone":"+1 780 923 2004",
    "sg:postcode":"T0A 1N0",
    "sg:province":"AB",
    "wof:name":"Gibbons Public Library",
    "wof:placetype":"venue"
},
  "geometry": {"coordinates":[-113.326874,53.828068],"type":"Point"}
}