{
  "type": "Feature",
  "properties": {
    "addr:full":"2101 32 St Vernon BC V1T 5L2",
    "addr:housenumber":"2101",
    "addr:postcode":"v1t 5l2",
    "addr:street":"32 St",
    "iso:country":"CA",
    "sg:address":"2101 32 St",
    "sg:city":"Vernon",
    "sg:classifiers":[
        {
            "category":"Government",
            "subcategory":"Office",
            "type":"Public Place"
        }
    ],
    "sg:phone":"+1 250 558 1323",
    "sg:postcode":"V1T 5L2",
    "sg:province":"BC",
    "wof:name":"Polson Special",
    "wof:placetype":"venue"
},
  "geometry": {"coordinates":[-119.273697,50.256924],"type":"Point"}
}