{
  "type": "Feature",
  "properties": {
    "addr:full":"62 John St Orangeville ON L9W 2P5",
    "addr:housenumber":"62",
    "addr:postcode":"l9w 2p5",
    "addr:street":"John St",
    "iso:country":"CA",
    "sg:address":"62 John St",
    "sg:city":"Orangeville",
    "sg:classifiers":[
        {
            "category":"Building & Trades",
            "subcategory":"Construction",
            "type":"Services"
        }
    ],
    "sg:phone":"+1 519 941 4605",
    "sg:postcode":"L9W 2P5",
    "sg:province":"ON",
    "sg:tags":[
        "painter"
    ],
    "wof:name":"Rod Alexander Enterprises",
    "wof:placetype":"venue"
},
  "geometry": {"coordinates":[-80.09418487550001,43.9138717651],"type":"Point"}
}