{
  "type": "Feature",
  "properties": {
    "addr:full":"Blainville QC J7C 2H1",
    "addr:postcode":"j7c 2h1",
    "iso:country":"CA",
    "sg:city":"Blainville",
    "sg:classifiers":[
        {
            "category":"Food & Beverages",
            "subcategory":"Groceries & Convenience Stores",
            "type":"Retail Goods"
        }
    ],
    "sg:phone":"+1 450 430 6570",
    "sg:postcode":"J7C 2H1",
    "sg:province":"QC",
    "wof:name":"Provi-Soir Couche-Tard",
    "wof:placetype":"venue"
},
  "geometry": {"coordinates":[-73.845741,45.651474],"type":"Point"}
}