{
  "type": "Feature",
  "properties": {
    "addr:full":"12 Ch Melvie L'Ange-Gardien QC J8L 2W7",
    "addr:housenumber":"12",
    "addr:postcode":"j8l 2w7",
    "addr:street":"Ch Melvie",
    "iso:country":"CA",
    "sg:address":"12 Ch Melvie",
    "sg:city":"L'Ange-Gardien",
    "sg:classifiers":[
        {
            "category":"Building & Trades",
            "subcategory":"Construction",
            "type":"Services"
        }
    ],
    "sg:phone":"+1 819 281 5252",
    "sg:postcode":"J8L 2W7",
    "sg:province":"QC",
    "sg:tags":[
        "general",
        "contractor"
    ],
    "wof:name":"Entreprises Alfa Enr",
    "wof:placetype":"venue"
},
  "geometry": {"coordinates":[-75.51779174799999,45.5689430237],"type":"Point"}
}