{
  "type": "Feature",
  "properties": {
    "addr:full":"Scarborough ON M1V 4Z7",
    "addr:postcode":"m1v 4z7",
    "iso:country":"CA",
    "sg:city":"Scarborough",
    "sg:classifiers":[
        {
            "category":"Manufacturing",
            "subcategory":"Apparel",
            "type":"Manufacturing & Wholesale Goods"
        }
    ],
    "sg:phone":"+1 416 297 7525",
    "sg:postcode":"M1V 4Z7",
    "sg:province":"ON",
    "sg:tags":[
        "textile",
        "manufacturer"
    ],
    "wof:name":"Fab Knit Textiles Inc",
    "wof:placetype":"venue"
},
  "geometry": {"coordinates":[-79.2630996704,43.8234786987],"type":"Point"}
}