{
  "type": "Feature",
  "properties": {
    "addr:full":"155 Mcnicoll Ave North York ON M2H 2C1",
    "addr:housenumber":"155",
    "addr:postcode":"m2h 2c1",
    "addr:street":"Mcnicoll Ave",
    "iso:country":"CA",
    "sg:address":"155 Mcnicoll Ave",
    "sg:city":"North York",
    "sg:classifiers":[
        {
            "category":"Social Services",
            "subcategory":"Child Care",
            "type":"Services"
        }
    ],
    "sg:phone":"+1 416 499 9743",
    "sg:postcode":"M2H 2C1",
    "sg:province":"ON",
    "wof:name":"Mc Nicoll Avenue Child Care",
    "wof:placetype":"venue"
},
  "geometry": {"coordinates":[-79.357849,43.79924],"type":"Point"}
}