{
  "type": "Feature",
  "properties": {
    "addr:full":"RR 1 STN Main Airdrie AB T4B 2A3",
    "addr:postcode":"t4b 2a3",
    "addr:street":"Rr 1 Stn Main",
    "iso:country":"CA",
    "sg:address":"RR 1 STN Main",
    "sg:city":"Airdrie",
    "sg:classifiers":[
        {
            "category":"Wholesale",
            "subcategory":"Machinery & Supplies",
            "type":"Manufacturing & Wholesale Goods"
        }
    ],
    "sg:phone":"+1 403 948 5678",
    "sg:postcode":"T4B 2A3",
    "sg:province":"AB",
    "sg:tags":[
        "trailer"
    ],
    "wof:name":"Airdrie Trailer Sales",
    "wof:placetype":"venue"
},
  "geometry": {"coordinates":[-114.013428,51.288055],"type":"Point"}
}