{
  "type": "Feature",
  "properties": {
    "addr:full":"Shellbrook SK S0J 2E0",
    "addr:postcode":"s0j 2e0",
    "iso:country":"CA",
    "sg:city":"Shellbrook",
    "sg:classifiers":[
        {
            "category":"Farming",
            "subcategory":"Nursery",
            "type":"Manufacturing & Wholesale Goods"
        }
    ],
    "sg:phone":"+1 306 747 2829",
    "sg:postcode":"S0J 2E0",
    "sg:province":"SK",
    "sg:tags":[
        "greenhouse"
    ],
    "wof:name":"K-5 Market Enterprise",
    "wof:placetype":"venue"
},
  "geometry": {"coordinates":[-106.390968323,53.2259750366],"type":"Point"}
}