{
  "type": "Feature",
  "properties": {
    "iso:country":"CA",
    "sg:address":"3090 Bathurst St",
    "sg:city":"North York",
    "sg:classifiers":[
        {
            "category":"Recreation",
            "type":"Entertainment"
        }
    ],
    "sg:phone":"+1 416 783 3877",
    "sg:postcode":"M6A 2A1",
    "sg:province":"ON",
    "sg:tags":[
        "martial",
        "arts",
        "instruction"
    ],
    "wof:name":"Summit Karate Schools Inc",
    "wof:placetype":"venue"
},
  "geometry": {"coordinates":[-79.43002300000001,43.719582],"type":"Point"}
}