{
  "type": "Feature",
  "properties": {
    "addr:full":"4150 Westminster Pl Mississauga ON L4W 3Z7",
    "addr:housenumber":"4150",
    "addr:postcode":"l4w 3z7",
    "addr:street":"Westminster Pl",
    "iso:country":"CA",
    "sg:address":"4150 Westminster Pl",
    "sg:city":"Mississauga",
    "sg:classifiers":[
        {
            "category":"Health Services",
            "subcategory":"Nursing And Care Facility",
            "type":"Services"
        }
    ],
    "sg:phone":"+1 905 273 3676",
    "sg:postcode":"L4W 3Z7",
    "sg:province":"ON",
    "sg:tags":[
        "home",
        "rest"
    ],
    "wof:name":"Westminister Court",
    "wof:placetype":"venue"
},
  "geometry": {"coordinates":[-79.6186676025,43.61536026],"type":"Point"}
}