{
  "type": "Feature",
  "properties": {
    "addr:full":"1610 Boul Wallberg Dolbeau-Mistassini QC G8L 1H4",
    "addr:housenumber":"1610",
    "addr:postcode":"g8l 1h4",
    "addr:street":"Boul Wallberg",
    "iso:country":"CA",
    "sg:address":"1610 Boul Wallberg",
    "sg:city":"Dolbeau-Mistassini",
    "sg:classifiers":[
        {
            "category":"Travel",
            "subcategory":"Hotels & Motels",
            "type":"Entertainment"
        }
    ],
    "sg:phone":"+1 418 276 8207",
    "sg:postcode":"G8L 1H4",
    "sg:province":"QC",
    "wof:name":"Hotel Du Boulevard",
    "wof:placetype":"venue"
},
  "geometry": {"coordinates":[-72.2300796509,48.8800888062],"type":"Point"}
}