{
  "type": "Feature",
  "properties": {
    "addr:full":"5319 Av Notre-Dame-DE-Grace Montreal QC H4A 1L2",
    "addr:housenumber":"5319",
    "addr:postcode":"h4a 1l2",
    "addr:street":"Av Notre-Dame-De-Grace",
    "iso:country":"CA",
    "sg:address":"5319 Av Notre-Dame-DE-Grace",
    "sg:city":"Montreal",
    "sg:classifiers":[
        {
            "category":"Organizations",
            "subcategory":"Professional Association",
            "type":"Services"
        }
    ],
    "sg:phone":"+1 514 489 6567",
    "sg:postcode":"H4A 1L2",
    "sg:province":"QC",
    "wof:name":"Prevention Ndg Inc",
    "wof:placetype":"venue"
},
  "geometry": {"coordinates":[-73.615685,45.477123],"type":"Point"}
}