{
  "type": "Feature",
  "properties": {
    "addr:full":"11 Prospect Ave Oxbow SK S0C 2B0",
    "addr:housenumber":"11",
    "addr:postcode":"s0c 2b0",
    "addr:street":"Prospect Ave",
    "iso:country":"CA",
    "sg:address":"11 Prospect Ave",
    "sg:city":"Oxbow",
    "sg:classifiers":[
        {
            "category":"Home & Garden",
            "subcategory":"Building Materials",
            "type":"Retail Goods"
        }
    ],
    "sg:phone":"+1 306 483 2707",
    "sg:postcode":"S0C 2B0",
    "sg:province":"SK",
    "wof:name":"Smith's Lumber Yards Ltd",
    "wof:placetype":"venue"
},
  "geometry": {"coordinates":[-102.17251586899999,49.2280731201],"type":"Point"}
}