{
  "type": "Feature",
  "properties": {
    "iso:country":"CA",
    "sg:city":"Surrey",
    "sg:classifiers":[
        {
            "category":"Manufacturing",
            "subcategory":"Buildings",
            "type":"Manufacturing & Wholesale Goods"
        }
    ],
    "sg:phone":"+1 604 594 1777",
    "sg:postcode":"V3S 1X6",
    "sg:province":"BC",
    "sg:tags":[
        "prefab"
    ],
    "wof:name":"Double S Cedar Homes",
    "wof:placetype":"venue"
},
  "geometry": {"coordinates":[-122.813117981,49.1192474365],"type":"Point"}
}