{
  "type": "Feature",
  "properties": {
    "addr:full":"4533 Av DE Lorimier Montreal QC H2H 2B4",
    "addr:housenumber":"4533",
    "addr:postcode":"h2h 2b4",
    "addr:street":"Av De Lorimier",
    "iso:country":"CA",
    "sg:address":"4533 Av DE Lorimier",
    "sg:city":"Montreal",
    "sg:classifiers":[
        {
            "category":"Organizations",
            "subcategory":"Professional Association",
            "type":"Services"
        }
    ],
    "sg:phone":"+1 514 527 3661",
    "sg:postcode":"H2H 2B4",
    "sg:province":"QC",
    "wof:name":"Union Des Travailleurs",
    "wof:placetype":"venue"
},
  "geometry": {"coordinates":[-73.5732727051,45.5357475281],"type":"Point"}
}