{
  "type": "Feature",
  "properties": {
    "addr:full":"2765 Innes Rd Gloucester ON K1B 3J7",
    "addr:housenumber":"2765",
    "addr:postcode":"k1b 3j7",
    "addr:street":"Innes Rd",
    "iso:country":"CA",
    "sg:address":"2765 Innes Rd",
    "sg:city":"Gloucester",
    "sg:classifiers":[
        {
            "category":"Real Estate",
            "subcategory":"Real Estate Operator",
            "type":"Services"
        }
    ],
    "sg:phone":"+1 613 830 5493",
    "sg:postcode":"K1B 3J7",
    "sg:province":"ON",
    "sg:tags":[
        "apartment"
    ],
    "wof:name":"Innes Park Complex",
    "wof:placetype":"venue"
},
  "geometry": {"coordinates":[-75.55805206300001,45.4344673157],"type":"Point"}
}