{
  "type": "Feature",
  "properties": {
    "addr:full":"L'Ange-Gardien QC J8L 2W7",
    "addr:postcode":"j8l 2w7",
    "iso:country":"CA",
    "sg:city":"L'Ange-Gardien",
    "sg:classifiers":[
        {
            "category":"Health Services",
            "subcategory":"Nursing And Care Facility",
            "type":"Services"
        }
    ],
    "sg:phone":"+1 819 281 4524",
    "sg:postcode":"J8L 2W7",
    "sg:province":"QC",
    "sg:tags":[
        "home",
        "retirement",
        "community"
    ],
    "wof:name":"Villa Des Aine DE Buckingham",
    "wof:placetype":"venue"
},
  "geometry": {"coordinates":[-75.46645355219999,45.5717811584],"type":"Point"}
}