{
  "type": "Feature",
  "properties": {
    "iso:country":"CA",
    "sg:city":"Elm Creek",
    "sg:classifiers":[
        {
            "category":"Sports & Exercise",
            "subcategory":"Golf",
            "type":"Entertainment"
        }
    ],
    "sg:phone":"+1 204 436 2600",
    "sg:postcode":"R0G 0N0",
    "sg:province":"MB",
    "sg:tags":[
        "course"
    ],
    "wof:name":"Scotswood Links Ltd",
    "wof:placetype":"venue"
},
  "geometry": {"coordinates":[-97.99304199220001,49.6755638123],"type":"Point"}
}