{
  "type": "Feature",
  "properties": {
    "iso:country":"CA",
    "sg:address":"237 Lancaster St E",
    "sg:city":"Kitchener",
    "sg:classifiers":[
        {
            "category":"Shopping",
            "subcategory":"Discount & Variety Stores",
            "type":"Retail Goods"
        }
    ],
    "sg:phone":"+1 519 745 2030",
    "sg:postcode":"N2H 1N5",
    "sg:province":"ON",
    "wof:name":"Three Point Variety",
    "wof:placetype":"venue"
},
  "geometry": {"coordinates":[-80.4817810059,43.4497413635],"type":"Point"}
}