{
  "type": "Feature",
  "properties": {
    "iso:country":"CA",
    "sg:city":"Montreal",
    "sg:classifiers":[
        {
            "category":"Bus Charters",
            "type":"Transportation"
        }
    ],
    "sg:phone":"+1 514 990 9236",
    "sg:postcode":"H2Y 2K7",
    "sg:province":"QC",
    "sg:tags":[
        "rental"
    ],
    "wof:name":"Autobus Nolises Symphony Inc",
    "wof:placetype":"venue"
},
  "geometry": {"coordinates":[-73.558197,45.501122],"type":"Point"}
}