{
  "type": "Feature",
  "properties": {
    "addr:full":"20008 Colonization Rd Arnes MB R0C 0C0",
    "addr:postcode":"20008;r0c 0c0",
    "addr:street":"Colonization Rd",
    "iso:country":"CA",
    "sg:address":"20008 Colonization Rd",
    "sg:city":"Arnes",
    "sg:classifiers":[
        {
            "category":"Home & Garden",
            "subcategory":"Building Materials",
            "type":"Retail Goods"
        }
    ],
    "sg:phone":"+1 204 642 8672",
    "sg:postcode":"R0C 0C0",
    "sg:province":"MB",
    "sg:tags":[
        "lumber"
    ],
    "wof:name":"Phoenix Lumber",
    "wof:placetype":"venue"
},
  "geometry": {"coordinates":[-96.994247,50.802204],"type":"Point"}
}