{
  "type": "Feature",
  "properties": {
    "addr:full":"2519 Edmonton Trail NE Calgary AB T2E 3M9",
    "addr:housenumber":"2519",
    "addr:postcode":"t2e 3m9",
    "addr:street":"Edmonton Trail Ne",
    "iso:country":"CA",
    "sg:address":"2519 Edmonton Trail NE",
    "sg:city":"Calgary",
    "sg:classifiers":[
        {
            "category":"Organizations",
            "subcategory":"Religious Organization",
            "type":"Services"
        }
    ],
    "sg:phone":"+1 403 277 7228",
    "sg:postcode":"T2E 3M9",
    "sg:province":"AB",
    "sg:tags":[
        "church"
    ],
    "wof:name":"Our Lady of Guadalupe Parish",
    "wof:placetype":"venue"
},
  "geometry": {"coordinates":[-114.05641199999999,51.074512],"type":"Point"}
}