{
  "type": "Feature",
  "properties": {
    "addr:full":"810 Canyon St Creston BC V0B 1G3",
    "addr:housenumber":"810",
    "addr:postcode":"bc v0b 1g3",
    "addr:street":"Canyon St",
    "iso:country":"CA",
    "sg:address":"810 Canyon St",
    "sg:city":"Creston",
    "sg:classifiers":[
        {
            "category":"Organizations",
            "subcategory":"Professional Association",
            "type":"Services"
        }
    ],
    "sg:phone":"+1 250 428 2511",
    "sg:postcode":"V0B 1G3",
    "sg:province":"BC",
    "sg:tags":[
        "club"
    ],
    "wof:name":"Senior Citizens",
    "wof:placetype":"venue"
},
  "geometry": {"coordinates":[-116.51348900000001,49.09547],"type":"Point"}
}