{
  "type": "Feature",
  "properties": {
    "addr:full":"474 Rue Des Etudiants Pohenegamook QC G0L 1J0",
    "addr:housenumber":"474",
    "addr:postcode":"g0l 1j0",
    "addr:street":"Rue Des Etudiants Pohenegamook",
    "iso:country":"CA",
    "sg:address":"474 Rue Des Etudiants",
    "sg:city":"Pohenegamook",
    "sg:classifiers":[
        {
            "category":"Social Services",
            "type":"Services"
        }
    ],
    "sg:phone":"+1 418 893 5389",
    "sg:postcode":"G0L 1J0",
    "sg:province":"QC",
    "sg:tags":[
        "organization",
        "welfare"
    ],
    "wof:name":"Regroupement Acti-Familles",
    "wof:placetype":"venue"
},
  "geometry": {"coordinates":[-69.152298,47.45657],"type":"Point"}
}