{
  "type": "Feature",
  "properties": {
    "addr:full":"1124 Rue Saint-Pierre LA Baie QC G7B 2Y3",
    "addr:housenumber":"1124",
    "addr:postcode":"g7b 2y3",
    "addr:street":"Rue Saint-Pierre",
    "iso:country":"CA",
    "sg:address":"1124 Rue Saint-Pierre",
    "sg:city":"LA Baie",
    "sg:classifiers":[
        {
            "category":"Health Services",
            "subcategory":"Chiropractor",
            "type":"Services"
        }
    ],
    "sg:phone":"+1 418 544 3832",
    "sg:postcode":"G7B 2Y3",
    "sg:province":"QC",
    "wof:name":"Renaud, Denis DC",
    "wof:placetype":"venue"
},
  "geometry": {"coordinates":[-70.8837356567,48.3460845947],"type":"Point"}
}