{
  "type": "Feature",
  "properties": {
    "addr:full":"463 Rue DE Boischatel Saint-Nicolas QC G7A 1P1",
    "addr:housenumber":"463",
    "addr:postcode":"g7a 1p1",
    "addr:street":"Rue De Boischatel",
    "iso:country":"CA",
    "sg:address":"463 Rue DE Boischatel",
    "sg:city":"Saint-Nicolas",
    "sg:classifiers":[
        {
            "category":"Building & Trades",
            "subcategory":"Construction",
            "type":"Services"
        }
    ],
    "sg:phone":"+1 418 836 1750",
    "sg:postcode":"G7A 1P1",
    "sg:province":"QC",
    "sg:tags":[
        "contractor",
        "general"
    ],
    "wof:name":"Constructions Mont Chateau Inc",
    "wof:placetype":"venue"
},
  "geometry": {"coordinates":[-71.398293,46.700764],"type":"Point"}
}