{
  "type": "Feature",
  "properties": {
    "iso:country":"CA",
    "sg:address":"2369 Rue Principale",
    "sg:city":"Saint-Jean-Des-Piles",
    "sg:classifiers":[
        {
            "category":"Travel",
            "subcategory":"Hotels & Motels",
            "type":"Entertainment"
        }
    ],
    "sg:phone":"+1 819 538 2112",
    "sg:postcode":"G0X 2V0",
    "sg:province":"QC",
    "wof:name":"Aux Berges Du St-Maurice Inc",
    "wof:placetype":"venue"
},
  "geometry": {"coordinates":[-72.7625961304,46.7089729309],"type":"Point"}
}