{
  "type": "Feature",
  "properties": {
    "iso:country":"CA",
    "sg:address":"1161 Cyrville Rd",
    "sg:city":"Gloucester",
    "sg:classifiers":[
        {
            "category":"Professional",
            "subcategory":"Management & Consulting",
            "type":"Services"
        }
    ],
    "sg:phone":"+1 613 747 0300",
    "sg:postcode":"K1J 7S6",
    "sg:province":"ON",
    "sg:tags":[
        "project",
        "consultant",
        "telecommunication"
    ],
    "wof:name":"Kevin Orr Assoc Canada Inc",
    "wof:placetype":"venue"
},
  "geometry": {"coordinates":[-75.631683,45.423908],"type":"Point"}
}