{
  "type": "Feature",
  "properties": {
    "addr:full":"160 Rue Saint-Joseph E Quebec QC G1K 3A7",
    "addr:housenumber":"160",
    "addr:postcode":"g1k 3a7",
    "addr:street":"Rue Saint-Joseph E",
    "iso:country":"CA",
    "sg:address":"160 Rue Saint-Joseph E",
    "sg:city":"Quebec",
    "sg:classifiers":[
        {
            "category":"Health Services",
            "subcategory":"Hospital",
            "type":"Services"
        }
    ],
    "sg:phone":"+1 418 640 5253",
    "sg:postcode":"G1K 3A7",
    "sg:province":"QC",
    "sg:tags":[
        "mental"
    ],
    "wof:name":"Regroupement Des Ressources",
    "wof:placetype":"venue"
},
  "geometry": {"coordinates":[-71.2291183472,46.8129196167],"type":"Point"}
}