{
  "type": "Feature",
  "properties": {
    "addr:full":"Edmonton AB T5N 3Z1",
    "addr:postcode":"t5n 3z1",
    "iso:country":"CA",
    "sg:city":"Edmonton",
    "sg:classifiers":[
        {
            "category":"Professional",
            "subcategory":"Accounting & Tax Preparation",
            "type":"Services"
        }
    ],
    "sg:phone":"+1 780 482 2358",
    "sg:postcode":"T5N 3Z1",
    "sg:province":"AB",
    "sg:tags":[
        "accountant",
        "architect"
    ],
    "wof:name":"C W Tse Architects Ltd",
    "wof:placetype":"venue"
},
  "geometry": {"coordinates":[-113.532669067,53.5494804382],"type":"Point"}
}