{
  "type": "Feature",
  "properties": {
    "addr:full":"1010 Merivale Rd Ottawa ON K1Z 6A5",
    "addr:housenumber":"1010",
    "addr:postcode":"k1z 6a5",
    "addr:street":"Merivale Rd",
    "iso:country":"CA",
    "sg:address":"1010 Merivale Rd",
    "sg:city":"Ottawa",
    "sg:classifiers":[
        {
            "category":"Personal",
            "subcategory":"Beauty Salon",
            "type":"Services"
        }
    ],
    "sg:phone":"+1 613 798 0029",
    "sg:postcode":"K1Z 6A5",
    "sg:province":"ON",
    "wof:name":"Vera's Hair Studio",
    "wof:placetype":"venue"
},
  "geometry": {"coordinates":[-75.73346710209999,45.3796234131],"type":"Point"}
}