{
  "type": "Feature",
  "properties": {
    "iso:country":"CA",
    "sg:address":"144 Rue Saint-Denis",
    "sg:city":"Chateauguay",
    "sg:classifiers":[
        {
            "category":"Professional",
            "type":"Services"
        }
    ],
    "sg:phone":"+1 450 699 8767",
    "sg:postcode":"J6K 2C6",
    "sg:province":"QC",
    "sg:tags":[
        "establishment",
        "engineer"
    ],
    "wof:name":"Services Techniques Duminy",
    "wof:placetype":"venue"
},
  "geometry": {"coordinates":[-73.767899,45.353878],"type":"Point"}
}