{
  "type": "Feature",
  "properties": {
    "addr:full":"477 Dupont St Toronto ON M6G 1Y6",
    "addr:housenumber":"477",
    "addr:postcode":"m6g 1y6",
    "addr:street":"Dupont St",
    "iso:country":"CA",
    "sg:address":"477 Dupont St",
    "sg:city":"Toronto",
    "sg:classifiers":[
        {
            "category":"Home & Garden",
            "subcategory":"Home Furnishings",
            "type":"Retail Goods"
        }
    ],
    "sg:phone":"+1 416 533 9337",
    "sg:postcode":"M6G 1Y6",
    "sg:province":"ON",
    "sg:tags":[
        "pottery"
    ],
    "wof:name":"Kaolin Designs",
    "wof:placetype":"venue"
},
  "geometry": {"coordinates":[-79.4148406982,43.6729240417],"type":"Point"}
}