{
  "type": "Feature",
  "properties": {
    "addr:full":"5020 Rue Saint-Ambroise Montreal QC H4C 2G1",
    "addr:housenumber":"5020",
    "addr:postcode":"h4c 2g1",
    "addr:street":"Rue Saint-Ambroise",
    "iso:country":"CA",
    "sg:address":"5020 Rue Saint-Ambroise",
    "sg:city":"Montreal",
    "sg:classifiers":[
        {
            "category":"Building & Trades",
            "subcategory":"Construction",
            "type":"Services"
        }
    ],
    "sg:phone":"+1 514 766 8606",
    "sg:postcode":"H4C 2G1",
    "sg:province":"QC",
    "sg:tags":[
        "roofing",
        "contractor"
    ],
    "wof:name":"Jules & Henri Couvreurs Ltee",
    "wof:placetype":"venue"
},
  "geometry": {"coordinates":[-73.589378,45.469067],"type":"Point"}
}