{
  "type": "Feature",
  "properties": {
    "addr:full":"4162 Ganaraska Rd Campbellcroft ON L0A 1B0",
    "addr:housenumber":"4162",
    "addr:postcode":"l0a 1b0",
    "addr:street":"Ganaraska Rd",
    "iso:country":"CA",
    "sg:address":"4162 Ganaraska Rd",
    "sg:city":"Campbellcroft",
    "sg:classifiers":[
        {
            "category":"Arts & Performance",
            "subcategory":"Theater",
            "type":"Entertainment"
        }
    ],
    "sg:phone":"+1 905 797 2936",
    "sg:postcode":"L0A 1B0",
    "sg:province":"ON",
    "sg:tags":[
        "live",
        "music"
    ],
    "wof:name":"One of A Kind Disc Jockey Svc",
    "wof:placetype":"venue"
},
  "geometry": {"coordinates":[-78.39548492430001,44.0592002869],"type":"Point"}
}