{
  "type": "Feature",
  "properties": {
    "addr:full":"550 Somerset St Saint John NB E2K 2Y7",
    "addr:housenumber":"550",
    "addr:postcode":"e2k 2y7",
    "addr:street":"Somerset St",
    "iso:country":"CA",
    "sg:address":"550 Somerset St",
    "sg:city":"Saint John",
    "sg:classifiers":[
        {
            "category":"Building & Trades",
            "subcategory":"Construction",
            "type":"Services"
        }
    ],
    "sg:phone":"+1 506 632 0025",
    "sg:postcode":"E2K 2Y7",
    "sg:province":"NB",
    "sg:tags":[
        "insulation",
        "heat",
        "contractor"
    ],
    "wof:name":"City Fibreglass Insulation Ltd",
    "wof:placetype":"venue"
},
  "geometry": {"coordinates":[-66.08195495610001,45.2883491516],"type":"Point"}
}