{
  "type": "Feature",
  "properties": {
    "addr:full":"333 Ch Du Canal Lachine QC H8S 2P6",
    "addr:housenumber":"333",
    "addr:postcode":"h8s 2p6",
    "addr:street":"Ch Du Canal",
    "iso:country":"CA",
    "sg:address":"333 Ch Du Canal",
    "sg:city":"Lachine",
    "sg:classifiers":[
        {
            "category":"Wholesale",
            "subcategory":"Machinery & Supplies",
            "type":"Manufacturing & Wholesale Goods"
        }
    ],
    "sg:phone":"+1 514 367 0021",
    "sg:postcode":"H8S 2P6",
    "sg:province":"QC",
    "sg:tags":[
        "bearing"
    ],
    "wof:name":"Syncrodrive Limitee",
    "wof:placetype":"venue"
},
  "geometry": {"coordinates":[-73.66934999999999,45.429413],"type":"Point"}
}