{
  "type": "Feature",
  "properties": {
    "addr:full":"2581 Rue Saint-Zotique E Montreal QC H1Y 1C8",
    "addr:housenumber":"2581",
    "addr:postcode":"h1y 1c8",
    "addr:street":"Rue Saint-Zotique E",
    "iso:country":"CA",
    "sg:address":"2581 Rue Saint-Zotique E",
    "sg:city":"Montreal",
    "sg:classifiers":[
        {
            "category":"Health Services",
            "subcategory":"Doctor",
            "type":"Services"
        }
    ],
    "sg:phone":"+1 514 990 2302",
    "sg:postcode":"H1Y 1C8",
    "sg:province":"QC",
    "sg:tags":[
        "psychoanalyst"
    ],
    "wof:name":"Pigeon, Martin",
    "wof:placetype":"venue"
},
  "geometry": {"coordinates":[-73.59498596189999,45.550579071],"type":"Point"}
}