{
  "type": "Feature",
  "properties": {
    "iso:country":"CA",
    "sg:address":"645 Victoria St N",
    "sg:city":"Kitchener",
    "sg:classifiers":[
        {
            "category":"Shopping",
            "subcategory":"Computers & Home Electronics",
            "type":"Retail Goods"
        }
    ],
    "sg:phone":"+1 519 744 3111",
    "sg:postcode":"N2H 5G3",
    "sg:province":"ON",
    "sg:tags":[
        "stereo",
        "automobile",
        "high",
        "stereophonic",
        "radio",
        "fidelity"
    ],
    "wof:name":"Natural Sound",
    "wof:placetype":"venue"
},
  "geometry": {"coordinates":[-80.473793,43.461082],"type":"Point"}
}