{
  "type": "Feature",
  "properties": {
    "addr:full":"1525 Dundas St London ON N5W 3B8",
    "addr:housenumber":"1525",
    "addr:postcode":"n5w 3b8",
    "addr:street":"Dundas St",
    "iso:country":"CA",
    "sg:address":"1525 Dundas St",
    "sg:city":"London",
    "sg:classifiers":[
        {
            "category":"Retail",
            "subcategory":"Auto Repair",
            "type":"Services"
        }
    ],
    "sg:phone":"+1 519 453 0460",
    "sg:postcode":"N5W 3B8",
    "sg:province":"ON",
    "sg:tags":[
        "repairing",
        "automobile",
        "tire"
    ],
    "wof:name":"Bob Williams Tire & Auto Ctr",
    "wof:placetype":"venue"
},
  "geometry": {"coordinates":[-81.195663,42.999004],"type":"Point"}
}