{
  "type": "Feature",
  "properties": {
    "addr:full":"12 Grace Ave Orillia ON L3V 2K2",
    "addr:housenumber":"12",
    "addr:postcode":"l3v 2k2",
    "addr:street":"Grace Ave",
    "iso:country":"CA",
    "sg:address":"12 Grace Ave",
    "sg:city":"Orillia",
    "sg:classifiers":[
        {
            "category":"Organizations",
            "subcategory":"Professional Association",
            "type":"Services"
        }
    ],
    "sg:phone":"+1 705 329 0909",
    "sg:postcode":"L3V 2K2",
    "sg:province":"ON",
    "wof:name":"Alzheimer Society of Orillia",
    "wof:placetype":"venue"
},
  "geometry": {"coordinates":[-79.426064,44.628178],"type":"Point"}
}