{
  "type": "Feature",
  "properties": {
    "iso:country":"CA",
    "sg:address":"4543 Southclark Pl #2",
    "sg:city":"Gloucester",
    "sg:classifiers":[
        {
            "category":"Manufacturing",
            "subcategory":"Metals",
            "type":"Manufacturing & Wholesale Goods"
        }
    ],
    "sg:phone":"+1 613 822 0276",
    "sg:postcode":"K1T 3V2",
    "sg:province":"ON",
    "sg:tags":[
        "plating"
    ],
    "wof:name":"Reliable Plating & Finishing",
    "wof:placetype":"venue"
},
  "geometry": {"coordinates":[-75.61782100000001,45.320793],"type":"Point"}
}