{
  "type": "Feature",
  "properties": {
    "iso:country":"CA",
    "sg:address":"985 Rue Bernard-Pilon",
    "sg:city":"Beloeil",
    "sg:classifiers":[
        {
            "category":"Food & Beverages",
            "subcategory":"Groceries & Convenience Stores",
            "type":"Retail Goods"
        }
    ],
    "sg:phone":"+1 450 464 2466",
    "sg:postcode":"J3G 1V7",
    "sg:province":"QC",
    "wof:name":"Couche-Tard",
    "wof:placetype":"venue"
},
  "geometry": {"coordinates":[-73.230713,45.557308],"type":"Point"}
}