{
  "type": "Feature",
  "properties": {
    "iso:country":"CA",
    "sg:address":"7 Spectacle Lake Dr",
    "sg:city":"Dartmouth",
    "sg:classifiers":[
        {
            "category":"Insurance",
            "subcategory":"Insurance Agent",
            "type":"Services"
        }
    ],
    "sg:phone":"+1 902 496 6624",
    "sg:postcode":"B3B 1X7",
    "sg:province":"NS",
    "wof:name":"Atlantic Blue Cross Care Inc",
    "wof:placetype":"venue"
},
  "geometry": {"coordinates":[-63.5800018311,44.7007484436],"type":"Point"}
}