{
  "type": "Feature",
  "properties": {
    "addr:full":"7304 Buller Ave Burnaby BC V5J 4S5",
    "addr:housenumber":"7304",
    "addr:postcode":"v5j 4s5",
    "addr:street":"Buller Ave",
    "iso:country":"CA",
    "sg:address":"7304 Buller Ave",
    "sg:city":"Burnaby",
    "sg:classifiers":[
        {
            "category":"Freight",
            "type":"Transportation"
        }
    ],
    "sg:phone":"+1 604 324 3333",
    "sg:postcode":"V5J 4S5",
    "sg:province":"BC",
    "sg:tags":[
        "mover"
    ],
    "wof:name":"Two Small Men With Big Hearts",
    "wof:placetype":"venue"
},
  "geometry": {"coordinates":[-122.97731,49.217216],"type":"Point"}
}