{
  "type": "Feature",
  "properties": {
    "addr:full":"118 Killarney Rd Killarney Road NB E3A 9E2",
    "addr:housenumber":"118",
    "addr:postcode":"e3a 9e2",
    "addr:street":"Killarney Rd",
    "iso:country":"CA",
    "sg:address":"118 Killarney Rd",
    "sg:city":"Killarney Road",
    "sg:classifiers":[
        {
            "category":"Wholesale",
            "subcategory":"Meat",
            "type":"Manufacturing & Wholesale Goods"
        }
    ],
    "sg:phone":"+1 506 452 7772",
    "sg:postcode":"E3A 9E2",
    "sg:province":"NB",
    "sg:tags":[
        "packer"
    ],
    "wof:name":"Custom Meat Cutting",
    "wof:placetype":"venue"
},
  "geometry": {"coordinates":[-66.62990570069999,46.0177650452],"type":"Point"}
}