{
  "type": "Feature",
  "properties": {
    "iso:country":"CA",
    "sg:address":"106 Michaud St",
    "sg:city":"Sturgeon Falls",
    "sg:classifiers":[
        {
            "category":"Health Services",
            "subcategory":"Nursing And Care Facility",
            "type":"Services"
        }
    ],
    "sg:phone":"+1 705 753 1550",
    "sg:postcode":"P2B 2Z3",
    "sg:province":"ON",
    "sg:tags":[
        "home",
        "rest"
    ],
    "wof:name":"Au Chateau",
    "wof:placetype":"venue"
},
  "geometry": {"coordinates":[-79.9207229614,46.3720283508],"type":"Point"}
}