{
  "type": "Feature",
  "properties": {
    "addr:full":"Richmond BC V6X 2P9",
    "addr:postcode":"v6x 2p9",
    "iso:country":"CA",
    "sg:city":"Richmond",
    "sg:classifiers":[
        {
            "category":"Wholesale",
            "subcategory":"Electrical",
            "type":"Manufacturing & Wholesale Goods"
        }
    ],
    "sg:phone":"+1 604 270 1050",
    "sg:postcode":"V6X 2P9",
    "sg:province":"BC",
    "sg:tags":[
        "video",
        "disc",
        "tape"
    ],
    "wof:name":"Cana Wholesalers",
    "wof:placetype":"venue"
},
  "geometry": {"coordinates":[-123.098907,49.197113],"type":"Point"}
}