{
  "type": "Feature",
  "properties": {
    "addr:full":"570 Rue Du Roi Quebec QC G1K 2X2",
    "addr:housenumber":"570",
    "addr:postcode":"g1k 2x2",
    "addr:street":"Rue Du Roi",
    "iso:country":"CA",
    "sg:address":"570 Rue Du Roi",
    "sg:city":"Quebec",
    "sg:classifiers":[
        {
            "category":"Organizations",
            "subcategory":"Professional Association",
            "type":"Services"
        }
    ],
    "sg:phone":"+1 418 522 1568",
    "sg:postcode":"G1K 2X2",
    "sg:province":"QC",
    "wof:name":"Assn Cooperative D'Economie",
    "wof:placetype":"venue"
},
  "geometry": {"coordinates":[-71.2229385376,46.8156814575],"type":"Point"}
}