{
  "type": "Feature",
  "properties": {
    "addr:full":"Main St Smeaton SK S0J 2J0",
    "addr:postcode":"s0j 2j0",
    "addr:street":"Main St",
    "iso:country":"CA",
    "sg:address":"Main St",
    "sg:city":"Smeaton",
    "sg:classifiers":[
        {
            "category":"Food & Beverages",
            "subcategory":"Liquor & Beverages",
            "type":"Retail Goods"
        }
    ],
    "sg:phone":"+1 306 426 2010",
    "sg:postcode":"S0J 2J0",
    "sg:province":"SK",
    "sg:tags":[
        "grocer"
    ],
    "wof:name":"Smeaton CO-OP",
    "wof:placetype":"venue"
},
  "geometry": {"coordinates":[-104.806282,53.491917],"type":"Point"}
}