{
  "type": "Feature",
  "properties": {
    "iso:country":"CA",
    "sg:address":"2331 Vauxhall Pl",
    "sg:city":"Richmond",
    "sg:classifiers":[
        {
            "category":"Manufacturing",
            "subcategory":"Building Materials",
            "type":"Manufacturing & Wholesale Goods"
        }
    ],
    "sg:phone":"+1 604 278 4111",
    "sg:postcode":"V6V 1Z5",
    "sg:province":"BC",
    "wof:name":"Bennic Contr & Millwork Ltd",
    "wof:placetype":"venue"
},
  "geometry": {"coordinates":[-123.087318,49.196663],"type":"Point"}
}