{
  "type": "Feature",
  "properties": {
    "addr:full":"646 Dundas St London ON N5W 2Y8",
    "addr:housenumber":"646",
    "addr:postcode":"n5w 2y8",
    "addr:street":"Dundas St",
    "iso:country":"CA",
    "sg:address":"646 Dundas St",
    "sg:city":"London",
    "sg:classifiers":[
        {
            "category":"Restaurant",
            "type":"Food & Drink"
        }
    ],
    "sg:phone":"+1 519 439 6471",
    "sg:postcode":"N5W 2Y8",
    "sg:province":"ON",
    "wof:name":"Melody Restaurant & Tavern",
    "wof:placetype":"venue"
},
  "geometry": {"coordinates":[-81.23028600000001,42.989349],"type":"Point"}
}