{
  "type": "Feature",
  "properties": {
    "iso:country":"CA",
    "sg:address":"646 Dundas St",
    "sg:city":"London",
    "sg:classifiers":[
        {
            "category":"Restaurant",
            "type":"Food & Drink"
        }
    ],
    "sg:phone":"+1 519 439 6471",
    "sg:postcode":"N5W 2Y8",
    "sg:province":"ON",
    "wof:name":"Melody Restaurant & Tavern",
    "wof:placetype":"venue"
},
  "geometry": {"coordinates":[-81.230286,42.989349],"type":"Point"}
}