{
  "type": "Feature",
  "properties": {
    "iso:country":"CA",
    "sg:address":"354 Rue Charles-Marchand",
    "sg:city":"Le Gardeur",
    "sg:classifiers":[
        {
            "category":"Building & Trades",
            "subcategory":"Construction",
            "type":"Services"
        }
    ],
    "sg:phone":"+1 450 585 7155",
    "sg:postcode":"J5Z 4P1",
    "sg:province":"QC",
    "sg:tags":[
        "concrete",
        "pumping"
    ],
    "wof:name":"Beton Le Gardeur Inc",
    "wof:placetype":"venue"
},
  "geometry": {"coordinates":[-73.484795,45.758102],"type":"Point"}
}