{
  "type": "Feature",
  "properties": {
    "addr:full":"6300 Av Du Parc Montreal QC H2V 4H8",
    "addr:housenumber":"6300",
    "addr:postcode":"h2v 4h8",
    "addr:street":"Av Du Parc",
    "iso:country":"CA",
    "sg:address":"6300 Av Du Parc",
    "sg:city":"Montreal",
    "sg:classifiers":[
        {
            "category":"Wholesale",
            "subcategory":"Apparel",
            "type":"Manufacturing & Wholesale Goods"
        }
    ],
    "sg:phone":"+1 514 948 0193",
    "sg:postcode":"H2V 4H8",
    "sg:province":"QC",
    "sg:tags":[
        "clothing"
    ],
    "wof:name":"Nadya Toto Inc",
    "wof:placetype":"venue"
},
  "geometry": {"coordinates":[-73.61243399999999,45.526707],"type":"Point"}
}