{
  "type": "Feature",
  "properties": {
    "addr:full":"5325 Boul Decarie Montreal QC H3W 3C4",
    "addr:housenumber":"5325",
    "addr:postcode":"h3w 3c4",
    "addr:street":"Boul Decarie",
    "iso:country":"CA",
    "sg:address":"5325 Boul Decarie",
    "sg:city":"Montreal",
    "sg:classifiers":[
        {
            "category":"Retail",
            "subcategory":"Animal Services",
            "type":"Services"
        }
    ],
    "sg:phone":"+1 514 483 2275",
    "sg:postcode":"H3W 3C4",
    "sg:province":"QC",
    "sg:tags":[
        "pet",
        "grooming",
        "washing"
    ],
    "wof:name":"Barks & Parks",
    "wof:placetype":"venue"
},
  "geometry": {"coordinates":[-73.632462,45.485516],"type":"Point"}
}