{
  "type": "Feature",
  "properties": {
    "addr:full":"98 Main St Grand Falls-Windsor NL A2B 1J7",
    "addr:housenumber":"98",
    "addr:postcode":"a2b 1j7",
    "addr:street":"Main St",
    "iso:country":"CA",
    "sg:address":"98 Main St",
    "sg:city":"Grand Falls-Windsor",
    "sg:classifiers":[
        {
            "category":"Restaurant",
            "type":"Food & Drink"
        }
    ],
    "sg:phone":"+1 709 489 8988",
    "sg:postcode":"A2B 1J7",
    "sg:province":"NL",
    "wof:name":"Sun's Take Out",
    "wof:placetype":"venue"
},
  "geometry": {"coordinates":[-55.65987,48.950115],"type":"Point"}
}