{
  "type": "Feature",
  "properties": {
    "addr:full":"925 Av Newton Quebec QC G1P 4C4",
    "addr:housenumber":"925",
    "addr:postcode":"g1p 4c4",
    "addr:street":"Av Newton",
    "iso:country":"CA",
    "sg:address":"925 Av Newton",
    "sg:city":"Quebec",
    "sg:classifiers":[
        {
            "category":"Wholesale",
            "subcategory":"Electrical",
            "type":"Manufacturing & Wholesale Goods"
        }
    ],
    "sg:phone":"+1 418 877 4069",
    "sg:postcode":"G1P 4C4",
    "sg:province":"QC",
    "sg:tags":[
        "sound",
        "equipment",
        "system"
    ],
    "wof:name":"Carden Audio Enr",
    "wof:placetype":"venue"
},
  "geometry": {"coordinates":[-71.3031997681,46.803943634],"type":"Point"}
}