{
  "type": "Feature",
  "properties": {
    "addr:full":"81 Rue Leduc Hull QC J8X 3A7",
    "addr:housenumber":"81",
    "addr:postcode":"j8x 3a7",
    "addr:street":"Rue Leduc",
    "iso:country":"CA",
    "sg:address":"81 Rue Leduc",
    "sg:city":"Hull",
    "sg:classifiers":[
        {
            "category":"Professional",
            "subcategory":"Art Services",
            "type":"Services"
        }
    ],
    "sg:phone":"+1 819 771 4754",
    "sg:postcode":"J8X 3A7",
    "sg:province":"QC",
    "sg:tags":[
        "graphic",
        "designer"
    ],
    "wof:name":"Publicom Inc",
    "wof:placetype":"venue"
},
  "geometry": {"coordinates":[-75.718491,45.42844],"type":"Point"}
}