{
  "type": "Feature",
  "properties": {
    "addr:full":"826 51st St E Saskatoon SK S7K 5C7",
    "addr:housenumber":"826",
    "addr:postcode":"s7k 5c7",
    "addr:street":"51St St E",
    "iso:country":"CA",
    "sg:address":"826 51st St E",
    "sg:city":"Saskatoon",
    "sg:classifiers":[
        {
            "category":"Restaurant",
            "type":"Food & Drink"
        }
    ],
    "sg:phone":"+1 306 934 7603",
    "sg:postcode":"S7K 5C7",
    "sg:province":"SK",
    "wof:name":"Boston Pizza",
    "wof:placetype":"venue"
},
  "geometry": {"coordinates":[-106.65038300000001,52.173084],"type":"Point"}
}