{
  "type": "Feature",
  "properties": {
    "iso:country":"CA",
    "sg:address":"826 51st St E",
    "sg:city":"Saskatoon",
    "sg:classifiers":[
        {
            "category":"Restaurant",
            "type":"Food & Drink"
        }
    ],
    "sg:phone":"+1 306 934 7603",
    "sg:postcode":"S7K 5C7",
    "sg:province":"SK",
    "wof:name":"Boston Pizza",
    "wof:placetype":"venue"
},
  "geometry": {"coordinates":[-106.650383,52.173084],"type":"Point"}
}