{
  "type": "Feature",
  "properties": {
    "iso:country":"CA",
    "sg:address":"175 Goulard Rd",
    "sg:city":"Sturgeon Falls",
    "sg:classifiers":[
        {
            "category":"Manufacturing",
            "subcategory":"Lumber",
            "type":"Manufacturing & Wholesale Goods"
        }
    ],
    "sg:phone":"+1 705 753 2220",
    "sg:postcode":"P2B 2R9",
    "sg:province":"ON",
    "sg:tags":[
        "sawmill"
    ],
    "wof:name":"Goulard Lumber Ltd",
    "wof:placetype":"venue"
},
  "geometry": {"coordinates":[-79.9063568115,46.3784065247],"type":"Point"}
}