{
  "type": "Feature",
  "properties": {
    "addr:full":"2057 Rue Du Parc-Gomin Sillery QC G1T 1A6",
    "addr:housenumber":"2057",
    "addr:postcode":"g1t 1a6",
    "addr:street":"Rue Du Parc-Gomin",
    "iso:country":"CA",
    "sg:address":"2057 Rue Du Parc-Gomin",
    "sg:city":"Sillery",
    "sg:classifiers":[
        {
            "category":"Professional",
            "subcategory":"Business Services",
            "type":"Services"
        }
    ],
    "sg:phone":"+1 418 261 0999",
    "sg:postcode":"G1T 1A6",
    "sg:province":"QC",
    "sg:tags":[
        "drafting"
    ],
    "wof:name":"Icoss Inc",
    "wof:placetype":"venue"
},
  "geometry": {"coordinates":[-71.26061199999999,46.783916],"type":"Point"}
}