{
  "type": "Feature",
  "properties": {
    "iso:country":"CA",
    "sg:address":"1431 Boul Du Royaume O",
    "sg:city":"Chicoutimi",
    "sg:classifiers":[
        {
            "category":"Home & Garden",
            "subcategory":"Mobile Homes",
            "type":"Retail Goods"
        }
    ],
    "sg:phone":"+1 418 696 2515",
    "sg:postcode":"G7H 5B1",
    "sg:province":"QC",
    "sg:tags":[
        "commercial",
        "unit"
    ],
    "wof:name":"Bureau Mobile Saglac Inc",
    "wof:placetype":"venue"
},
  "geometry": {"coordinates":[-71.11702,48.388405],"type":"Point"}
}