{
  "type": "Feature",
  "properties": {
    "addr:full":"4 Janedale Cres Whitby ON L1N 6Z5",
    "addr:housenumber":"4",
    "addr:postcode":"l1n 6z5",
    "addr:street":"Janedale Cres",
    "iso:country":"CA",
    "sg:address":"4 Janedale Cres",
    "sg:city":"Whitby",
    "sg:classifiers":[
        {
            "category":"Retail",
            "subcategory":"Portrait Studio",
            "type":"Services"
        }
    ],
    "sg:phone":"+1 905 571 5008",
    "sg:postcode":"L1N 6Z5",
    "sg:province":"ON",
    "sg:tags":[
        "photographer"
    ],
    "wof:name":"Fashion Photos",
    "wof:placetype":"venue"
},
  "geometry": {"coordinates":[-78.9040222168,43.8850631714],"type":"Point"}
}