{
  "type": "Feature",
  "properties": {
    "addr:full":"7355 Morley St Burnaby BC V5E 2K1",
    "addr:housenumber":"7355",
    "addr:postcode":"v5e 2k1",
    "addr:street":"Morley St",
    "iso:country":"CA",
    "sg:address":"7355 Morley St",
    "sg:city":"Burnaby",
    "sg:classifiers":[
        {
            "category":"Education",
            "subcategory":"School",
            "type":"Public Place"
        }
    ],
    "sg:phone":"+1 604 664 8774",
    "sg:postcode":"V5E 2K1",
    "sg:province":"BC",
    "wof:name":"Morley Elementary School",
    "wof:placetype":"venue"
},
  "geometry": {"coordinates":[-122.958068848,49.2257461548],"type":"Point"}
}