{
  "type": "Feature",
  "properties": {
    "addr:full":"Boucherville QC J4B 4T3",
    "addr:postcode":"j4b 4t3",
    "iso:country":"CA",
    "sg:city":"Boucherville",
    "sg:classifiers":[
        {
            "category":"Personal",
            "type":"Services"
        }
    ],
    "sg:phone":"+1 450 641 2999",
    "sg:postcode":"J4B 4T3",
    "sg:province":"QC",
    "sg:tags":[
        "electrolysis"
    ],
    "wof:name":"Electrolyse Micheline Enr",
    "wof:placetype":"venue"
},
  "geometry": {"coordinates":[-73.45263671879999,45.6151313782],"type":"Point"}
}