{
  "type": "Feature",
  "properties": {
    "addr:full":"1014 Prescott Dr Sarnia ON N7T 7H3",
    "addr:housenumber":"1014",
    "addr:postcode":"n7t 7h3",
    "addr:street":"Prescott Dr",
    "iso:country":"CA",
    "sg:address":"1014 Prescott Dr",
    "sg:city":"Sarnia",
    "sg:classifiers":[
        {
            "category":"Building & Trades",
            "subcategory":"Electrical",
            "type":"Services"
        }
    ],
    "sg:phone":"+1 519 332 8120",
    "sg:postcode":"N7T 7H3",
    "sg:province":"ON",
    "sg:tags":[
        "electric",
        "contractor"
    ],
    "wof:name":"Tee Jay Instrumentation Svc",
    "wof:placetype":"venue"
},
  "geometry": {"coordinates":[-82.347847,42.942207],"type":"Point"}
}