{
  "type": "Feature",
  "properties": {
    "addr:full":"12010 Boul Albert-Hudon Montreal-Nord QC H1G 3K7",
    "addr:housenumber":"12010",
    "addr:postcode":"h1g 3k7",
    "addr:street":"Boul Albert-Hudon",
    "iso:country":"CA",
    "sg:address":"12010 Boul Albert-Hudon",
    "sg:city":"Montreal-Nord",
    "sg:classifiers":[
        {
            "category":"Autos & Motor Vehicles",
            "subcategory":"Auto Supplies",
            "type":"Retail Goods"
        }
    ],
    "sg:phone":"+1 514 323 4630",
    "sg:postcode":"H1G 3K7",
    "sg:province":"QC",
    "sg:tags":[
        "tire"
    ],
    "wof:name":"Pneus Metropolitains Inc",
    "wof:placetype":"venue"
},
  "geometry": {"coordinates":[-73.615211,45.620724],"type":"Point"}
}