{
  "type": "Feature",
  "properties": {
    "iso:country":"CA",
    "sg:address":"320 Boul Saint-Benoit O",
    "sg:city":"Amqui",
    "sg:classifiers":[
        {
            "category":"Restaurant",
            "type":"Food & Drink"
        }
    ],
    "sg:phone":"+1 418 629 3535",
    "sg:postcode":"G5J 2G2",
    "sg:province":"QC",
    "wof:name":"Cantine Fortier",
    "wof:placetype":"venue"
},
  "geometry": {"coordinates":[-67.4387893677,48.4700584412],"type":"Point"}
}