{
  "type": "Feature",
  "properties": {
    "addr:full":"Calgary AB T1Y 6Z1",
    "addr:postcode":"t1y 6z1",
    "iso:country":"CA",
    "sg:city":"Calgary",
    "sg:classifiers":[
        {
            "category":"Real Estate",
            "subcategory":"Real Estate Agent",
            "type":"Services"
        }
    ],
    "sg:phone":"+1 403 250 2981",
    "sg:postcode":"T1Y 6Z1",
    "sg:province":"AB",
    "wof:name":"Intelligent Realty Inc",
    "wof:placetype":"venue"
},
  "geometry": {"coordinates":[-113.998024,51.080544],"type":"Point"}
}