{
  "type": "Feature",
  "properties": {
    "addr:full":"320 Bridge St W Napanee ON K7R 3S7",
    "addr:housenumber":"320",
    "addr:postcode":"k7r 3s7",
    "addr:street":"Bridge St W",
    "iso:country":"CA",
    "sg:address":"320 Bridge St W",
    "sg:city":"Napanee",
    "sg:classifiers":[
        {
            "category":"Education",
            "subcategory":"School",
            "type":"Public Place"
        }
    ],
    "sg:phone":"+1 613 354 2354",
    "sg:postcode":"K7R 3S7",
    "sg:province":"ON",
    "wof:name":"Cornerstone Christian Academy",
    "wof:placetype":"venue"
},
  "geometry": {"coordinates":[-76.97197723390001,44.2390823364],"type":"Point"}
}