{
  "type": "Feature",
  "properties": {
    "iso:country":"CA",
    "sg:address":"20 Wellington Rd 23",
    "sg:city":"Erin",
    "sg:classifiers":[
        {
            "category":"Home & Garden",
            "subcategory":"Furniture",
            "type":"Retail Goods"
        }
    ],
    "sg:phone":"+1 519 833 9694",
    "sg:postcode":"N0B 1T0",
    "sg:province":"ON",
    "sg:tags":[
        "builder",
        "custom"
    ],
    "wof:name":"Neilson Cabinet Works",
    "wof:placetype":"venue"
},
  "geometry": {"coordinates":[-80.1332397461,43.7835388184],"type":"Point"}
}