{
  "type": "Feature",
  "properties": {
    "addr:full":"1421 Elgin St Burlington ON L7S 1E6",
    "addr:housenumber":"1421",
    "addr:postcode":"l7s 1e6",
    "addr:street":"Elgin St",
    "iso:country":"CA",
    "sg:address":"1421 Elgin St",
    "sg:city":"Burlington",
    "sg:classifiers":[
        {
            "category":"Real Estate",
            "subcategory":"Real Estate Operator",
            "type":"Services"
        }
    ],
    "sg:phone":"+1 905 681 7113",
    "sg:postcode":"L7S 1E6",
    "sg:province":"ON",
    "sg:tags":[
        "apartment"
    ],
    "wof:name":"St Luke's Close of Burlington",
    "wof:placetype":"venue"
},
  "geometry": {"coordinates":[-79.799797,43.323967],"type":"Point"}
}