{
  "type": "Feature",
  "properties": {
    "addr:full":"600 Bowles St Cartwright MB R0K 0L0",
    "addr:housenumber":"600",
    "addr:postcode":"r0k 0l0",
    "addr:street":"Bowles St",
    "iso:country":"CA",
    "sg:address":"600 Bowles St",
    "sg:city":"Cartwright",
    "sg:classifiers":[
        {
            "category":"Insurance",
            "subcategory":"Insurance Agent",
            "type":"Services"
        }
    ],
    "sg:phone":"+1 204 529 2283",
    "sg:postcode":"R0K 0L0",
    "sg:province":"MB",
    "wof:name":"J K Insurance",
    "wof:placetype":"venue"
},
  "geometry": {"coordinates":[-99.3453674316,49.0949668884],"type":"Point"}
}