{
  "type": "Feature",
  "properties": {
    "addr:full":"422 Railway St Vancouver BC V6A 1B1",
    "addr:housenumber":"422",
    "addr:postcode":"v6a 1b1",
    "addr:street":"Railway St",
    "iso:country":"CA",
    "sg:address":"422 Railway St",
    "sg:city":"Vancouver",
    "sg:classifiers":[
        {
            "category":"Wholesale",
            "subcategory":"Groceries",
            "type":"Manufacturing & Wholesale Goods"
        }
    ],
    "sg:phone":"+1 604 254 7223",
    "sg:postcode":"V6A 1B1",
    "sg:province":"BC",
    "sg:tags":[
        "grocer"
    ],
    "wof:name":"Kwong Fung Food Processing",
    "wof:placetype":"venue"
},
  "geometry": {"coordinates":[-123.094612122,49.2847824097],"type":"Point"}
}