{
  "type": "Feature",
  "properties": {
    "addr:full":"227 Roncesvalles Ave Toronto ON M6R 2L6",
    "addr:housenumber":"227",
    "addr:postcode":"m6r 2l6",
    "addr:street":"Roncesvalles Ave",
    "iso:country":"CA",
    "sg:address":"227 Roncesvalles Ave",
    "sg:city":"Toronto",
    "sg:classifiers":[
        {
            "category":"Shopping",
            "subcategory":"Discount & Variety Stores",
            "type":"Retail Goods"
        }
    ],
    "sg:phone":"+1 416 533 9991",
    "sg:postcode":"M6R 2L6",
    "sg:province":"ON",
    "wof:name":"Metro Lottery",
    "wof:placetype":"venue"
},
  "geometry": {"coordinates":[-79.448669,43.645863],"type":"Point"}
}