{
  "type": "Feature",
  "properties": {
    "iso:country":"CA",
    "sg:address":"22 College St",
    "sg:city":"Toronto",
    "sg:classifiers":[
        {
            "category":"Travel",
            "subcategory":"Travel Agent",
            "type":"Entertainment"
        }
    ],
    "sg:phone":"+1 416 964 8881",
    "sg:postcode":"M5G 1K2",
    "sg:province":"ON",
    "sg:tags":[
        "agency",
        "bureau"
    ],
    "wof:name":"Super World Wide Tours Inc",
    "wof:placetype":"venue"
},
  "geometry": {"coordinates":[-79.384361,43.661232],"type":"Point"}
}