{
  "type": "Feature",
  "properties": {
    "addr:full":"7630 Rue Trudeau Brossard QC J4W 2M3",
    "addr:housenumber":"7630",
    "addr:postcode":"j4w 2m3",
    "addr:street":"Rue Trudeau",
    "iso:country":"CA",
    "sg:address":"7630 Rue Trudeau",
    "sg:city":"Brossard",
    "sg:classifiers":[
        {
            "category":"Local Transit",
            "type":"Transportation"
        }
    ],
    "sg:phone":"+1 514 990 2222",
    "sg:postcode":"J4W 2M3",
    "sg:province":"QC",
    "sg:tags":[
        "limousine"
    ],
    "wof:name":"Air Limo",
    "wof:placetype":"venue"
},
  "geometry": {"coordinates":[-73.48030853269999,45.4595069885],"type":"Point"}
}