{
  "type": "Feature",
  "properties": {
    "addr:full":"Hamilton ON L8S 1B4",
    "addr:postcode":"l8s 1b4",
    "iso:country":"CA",
    "sg:city":"Hamilton",
    "sg:classifiers":[
        {
            "category":"Professional",
            "subcategory":"Accounting & Tax Preparation",
            "type":"Services"
        }
    ],
    "sg:phone":"+1 905 577 6999",
    "sg:postcode":"L8S 1B4",
    "sg:province":"ON",
    "sg:tags":[
        "accountant"
    ],
    "wof:name":"Somer & Clewley",
    "wof:placetype":"venue"
},
  "geometry": {"coordinates":[-79.908936,43.258404],"type":"Point"}
}