{
  "type": "Feature",
  "properties": {
    "addr:full":"867 Tower Rd Halifax NS B3H 2Y1",
    "addr:housenumber":"867",
    "addr:postcode":"b3h 2y1",
    "addr:street":"Tower Rd",
    "iso:country":"CA",
    "sg:address":"867 Tower Rd",
    "sg:city":"Halifax",
    "sg:classifiers":[
        {
            "category":"Wholesale",
            "subcategory":"Seafood",
            "type":"Manufacturing & Wholesale Goods"
        }
    ],
    "sg:phone":"+1 902 482 0288",
    "sg:postcode":"B3H 2Y1",
    "sg:province":"NS",
    "sg:tags":[
        "fish"
    ],
    "wof:name":"Middle Africa Eagle Resource",
    "wof:placetype":"venue"
},
  "geometry": {"coordinates":[-63.577572,44.631046],"type":"Point"}
}