{
  "type": "Feature",
  "properties": {
    "addr:full":"517 Eastern Ave Toronto ON M4M 1C6",
    "addr:housenumber":"517",
    "addr:postcode":"m4m 1c6",
    "addr:street":"Eastern Ave",
    "iso:country":"CA",
    "sg:address":"517 Eastern Ave",
    "sg:city":"Toronto",
    "sg:classifiers":[
        {
            "category":"Retail",
            "subcategory":"Auto Repair",
            "type":"Services"
        }
    ],
    "sg:phone":"+1 416 461 5505",
    "sg:postcode":"M4M 1C6",
    "sg:province":"ON",
    "sg:tags":[
        "repairing",
        "automobile"
    ],
    "wof:name":"Mike's Garage",
    "wof:placetype":"venue"
},
  "geometry": {"coordinates":[-79.33970600000001,43.658085],"type":"Point"}
}