{
  "type": "Feature",
  "properties": {
    "addr:full":"14945 South Branch Rd Cornwall ON K6H 5R6",
    "addr:housenumber":"14945",
    "addr:postcode":"k6h 5r6",
    "addr:street":"South Branch Rd",
    "iso:country":"CA",
    "sg:address":"14945 South Branch Rd",
    "sg:city":"Cornwall",
    "sg:classifiers":[
        {
            "category":"Real Estate",
            "subcategory":"Developer",
            "type":"Services"
        }
    ],
    "sg:phone":"+1 613 933 4331",
    "sg:postcode":"K6H 5R6",
    "sg:province":"ON",
    "sg:tags":[
        "cemetery"
    ],
    "wof:name":"Notre Dame Cemetery",
    "wof:placetype":"venue"
},
  "geometry": {"coordinates":[-74.76435089109999,45.0628204346],"type":"Point"}
}