{
  "type": "Feature",
  "properties": {
    "addr:full":"160 2nd Ave S Saskatoon SK S7K 1K5",
    "addr:housenumber":"160",
    "addr:postcode":"s7k 1k5",
    "addr:street":"2Nd Ave S",
    "iso:country":"CA",
    "sg:address":"160 2nd Ave S",
    "sg:city":"Saskatoon",
    "sg:classifiers":[
        {
            "category":"Shopping",
            "subcategory":"Music",
            "type":"Retail Goods"
        }
    ],
    "sg:phone":"+1 306 652 7175",
    "sg:postcode":"S7K 1K5",
    "sg:province":"SK",
    "sg:tags":[
        "compact",
        "record",
        "disc",
        "tape"
    ],
    "wof:name":"Tramp's 2nd Ave",
    "wof:placetype":"venue"
},
  "geometry": {"coordinates":[-106.664093018,52.1278076172],"type":"Point"}
}