{
  "type": "Feature",
  "properties": {
    "addr:full":"875 Av Sainte-Anne Saint-Hyacinthe QC J2S 5G6",
    "addr:postcode":"j2s 5g6",
    "addr:street":"875 Av Sainte-Anne",
    "iso:country":"CA",
    "sg:address":"875 Av Sainte-Anne",
    "sg:city":"Saint-Hyacinthe",
    "sg:classifiers":[
        {
            "category":"Organizations",
            "subcategory":"Religious Organization",
            "type":"Services"
        }
    ],
    "sg:phone":"+1 450 778 7044",
    "sg:postcode":"J2S 5G6",
    "sg:province":"QC",
    "sg:tags":[
        "home",
        "retirement",
        "community",
        "retreat",
        "house"
    ],
    "wof:name":"Manoir Ste-Anne",
    "wof:placetype":"venue"
},
  "geometry": {"coordinates":[-72.9482879639,45.6251220703],"type":"Point"}
}