{
  "type": "Feature",
  "properties": {
    "addr:full":"900 Rue Laviolette Saint-Jerome QC J7Y 2W4",
    "addr:housenumber":"900",
    "addr:postcode":"j7y 2w4",
    "addr:street":"Rue Laviolette",
    "iso:country":"CA",
    "sg:address":"900 Rue Laviolette",
    "sg:city":"Saint-Jerome",
    "sg:classifiers":[
        {
            "category":"Personal",
            "subcategory":"Beauty Salon",
            "type":"Services"
        }
    ],
    "sg:phone":"+1 450 436 7476",
    "sg:postcode":"J7Y 2W4",
    "sg:province":"QC",
    "wof:name":"Coiffure Au Reflet D'Or Enr",
    "wof:placetype":"venue"
},
  "geometry": {"coordinates":[-74.013367,45.794674],"type":"Point"}
}