{
  "type": "Feature",
  "properties": {
    "addr:full":"341 Freshwater Rd St. John's NL A1B 1C4",
    "addr:housenumber":"341",
    "addr:postcode":"a1b 1c4",
    "addr:street":"Freshwater Rd",
    "iso:country":"CA",
    "sg:address":"341 Freshwater Rd",
    "sg:city":"St. John's",
    "sg:classifiers":[
        {
            "category":"Banks & Credit Unions",
            "subcategory":"Bank",
            "type":"Services"
        }
    ],
    "sg:phone":"+1 709 754 2630",
    "sg:postcode":"A1B 1C4",
    "sg:province":"NL",
    "wof:name":"Newfoundland & Labrador Credit",
    "wof:placetype":"venue"
},
  "geometry": {"coordinates":[-52.745223999,47.5614700317],"type":"Point"}
}