{
  "type": "Feature",
  "properties": {
    "addr:full":"4303 Albert St # 300 Regina SK S4S 3R6",
    "addr:housenumber":"4303",
    "addr:postcode":"s4s 3r6",
    "addr:street":"Albert St # 300",
    "iso:country":"CA",
    "sg:address":"4303 Albert St # 300",
    "sg:city":"Regina",
    "sg:classifiers":[
        {
            "category":"Health Services",
            "subcategory":"Doctor",
            "type":"Services"
        }
    ],
    "sg:phone":"+1 306 586 5015",
    "sg:postcode":"S4S 3R6",
    "sg:province":"SK",
    "sg:tags":[
        "dentist"
    ],
    "wof:name":"Albert South Dental Office",
    "wof:placetype":"venue"
},
  "geometry": {"coordinates":[-104.61779,50.411205],"type":"Point"}
}