{
  "type": "Feature",
  "properties": {
    "addr:full":"Perth ON K7H 3E2",
    "addr:postcode":"k7h 3e2",
    "iso:country":"CA",
    "sg:city":"Perth",
    "sg:classifiers":[
        {
            "category":"Retail",
            "subcategory":"Auto Repair",
            "type":"Services"
        }
    ],
    "sg:phone":"+1 613 267 2901",
    "sg:postcode":"K7H 3E2",
    "sg:province":"ON",
    "sg:tags":[
        "repairing",
        "automobile"
    ],
    "wof:name":"Perth Motors",
    "wof:placetype":"venue"
},
  "geometry": {"coordinates":[-76.270599,44.906071],"type":"Point"}
}