{
  "type": "Feature",
  "properties": {
    "addr:full":"219 Main St E Hawkesbury ON K6A 1A1",
    "addr:housenumber":"219",
    "addr:postcode":"k6a 1a1",
    "addr:street":"Main St E",
    "iso:country":"CA",
    "sg:address":"219 Main St E",
    "sg:city":"Hawkesbury",
    "sg:classifiers":[
        {
            "category":"Health Services",
            "subcategory":"Doctor",
            "type":"Services"
        }
    ],
    "sg:phone":"+1 613 632 8811",
    "sg:postcode":"K6A 1A1",
    "sg:province":"ON",
    "sg:tags":[
        "physician",
        "surgeon"
    ],
    "wof:name":"Therapedia Clinic",
    "wof:placetype":"venue"
},
  "geometry": {"coordinates":[-74.60893249510001,45.609992981],"type":"Point"}
}