{
  "type": "Feature",
  "properties": {
    "addr:full":"2441 Rue Holt Montreal QC H2G 1Y2",
    "addr:housenumber":"2441",
    "addr:postcode":"h2g 1y2",
    "addr:street":"Rue Holt",
    "iso:country":"CA",
    "sg:address":"2441 Rue Holt",
    "sg:city":"Montreal",
    "sg:classifiers":[
        {
            "category":"Wholesale",
            "subcategory":"Auto Parts",
            "type":"Manufacturing & Wholesale Goods"
        }
    ],
    "sg:phone":"+1 514 271 7047",
    "sg:postcode":"H2G 1Y2",
    "sg:province":"QC",
    "sg:tags":[
        "tire"
    ],
    "wof:name":"Pneus Bennett",
    "wof:placetype":"venue"
},
  "geometry": {"coordinates":[-73.583679,45.544777],"type":"Point"}
}