{
  "type": "Feature",
  "properties": {
    "addr:full":"47 1st Ave S Chesley ON N0G 1L0",
    "addr:housenumber":"47",
    "addr:postcode":"n0g 1l0",
    "addr:street":"1St Ave S Chesley",
    "iso:country":"CA",
    "sg:address":"47 1st Ave S",
    "sg:city":"Chesley",
    "sg:classifiers":[
        {
            "category":"Banks & Credit Unions",
            "subcategory":"Bank",
            "type":"Services"
        }
    ],
    "sg:phone":"+1 519 363 3512",
    "sg:postcode":"N0G 1L0",
    "sg:province":"ON",
    "wof:name":"Cibc",
    "wof:placetype":"venue"
},
  "geometry": {"coordinates":[-81.095337,44.299061],"type":"Point"}
}