{
  "type": "Feature",
  "properties": {
    "iso:country":"CA",
    "sg:address":"605 Rue Boisvert",
    "sg:city":"Saint-Jean-Sur-Richelieu",
    "sg:classifiers":[
        {
            "category":"Personal",
            "subcategory":"Beauty Salon",
            "type":"Services"
        }
    ],
    "sg:phone":"+1 450 346 5210",
    "sg:postcode":"J3B 2X7",
    "sg:province":"QC",
    "wof:name":"Salon Pierret",
    "wof:placetype":"venue"
},
  "geometry": {"coordinates":[-73.2851104736,45.3043823242],"type":"Point"}
}