{
  "type": "Feature",
  "properties": {
    "addr:full":"797 Rue Des Erables Mascouche QC J7L 3H2",
    "addr:housenumber":"797",
    "addr:postcode":"j7l 3h2",
    "addr:street":"Rue Des Erables",
    "iso:country":"CA",
    "sg:address":"797 Rue Des Erables",
    "sg:city":"Mascouche",
    "sg:classifiers":[
        {
            "category":"Shopping",
            "subcategory":"Computers & Home Electronics",
            "type":"Retail Goods"
        }
    ],
    "sg:phone":"+1 450 477 1321",
    "sg:postcode":"J7L 3H2",
    "sg:province":"QC",
    "sg:tags":[
        "equipment",
        "dealer"
    ],
    "wof:name":"Centre Electronique Rive Nord",
    "wof:placetype":"venue"
},
  "geometry": {"coordinates":[-73.65242000000001,45.746487],"type":"Point"}
}