{
  "type": "Feature",
  "properties": {
    "iso:country":"CA",
    "sg:address":"8245 Boul Taschereau",
    "sg:city":"Brossard",
    "sg:classifiers":[
        {
            "category":"Retail",
            "subcategory":"Laundry & Dry Cleaning",
            "type":"Services"
        }
    ],
    "sg:phone":"+1 450 676 3528",
    "sg:postcode":"J4Y 1A4",
    "sg:province":"QC",
    "sg:tags":[
        "cleaners"
    ],
    "wof:name":"Nettoyeurs Chatel Inc",
    "wof:placetype":"venue"
},
  "geometry": {"coordinates":[-73.46979522709999,45.4470252991],"type":"Point"}
}