{
  "type": "Feature",
  "properties": {
    "addr:full":"35 Larkin Dr Nepean ON K2J 2T2",
    "addr:housenumber":"35",
    "addr:postcode":"k2j 2t2",
    "addr:street":"Larkin Dr",
    "iso:country":"CA",
    "sg:address":"35 Larkin Dr",
    "sg:city":"Nepean",
    "sg:classifiers":[
        {
            "category":"Health Services",
            "subcategory":"Doctor",
            "type":"Services"
        }
    ],
    "sg:phone":"+1 613 825 8548",
    "sg:postcode":"K2J 2T2",
    "sg:province":"ON",
    "sg:tags":[
        "physiotherapist",
        "clinic"
    ],
    "wof:name":"Barrhaven Physiotherapy Clinic",
    "wof:placetype":"venue"
},
  "geometry": {"coordinates":[-75.7570571899,45.285774231],"type":"Point"}
}