{
  "type": "Feature",
  "properties": {
    "addr:full":"130 Clarence St Lanark ON K0G 1K0",
    "addr:housenumber":"130",
    "addr:postcode":"k0g 1k0",
    "addr:street":"Clarence St",
    "iso:country":"CA",
    "sg:address":"130 Clarence St",
    "sg:city":"Lanark",
    "sg:classifiers":[
        {
            "category":"Retail",
            "subcategory":"Funeral Services",
            "type":"Services"
        }
    ],
    "sg:phone":"+1 613 259 2872",
    "sg:postcode":"K0G 1K0",
    "sg:province":"ON",
    "sg:tags":[
        "director"
    ],
    "wof:name":"Young's Funeral Svc",
    "wof:placetype":"venue"
},
  "geometry": {"coordinates":[-76.367065,45.016747],"type":"Point"}
}