{
  "type": "Feature",
  "properties": {
    "addr:full":"64 Elizabeth St Brighton ON K0K 1H0",
    "addr:housenumber":"64",
    "addr:postcode":"k0k 1h0",
    "addr:street":"Elizabeth St",
    "iso:country":"CA",
    "sg:address":"64 Elizabeth St",
    "sg:city":"Brighton",
    "sg:classifiers":[
        {
            "category":"Retail",
            "subcategory":"Self-service Laundry",
            "type":"Services"
        }
    ],
    "sg:phone":"+1 613 475 2939",
    "sg:postcode":"K0K 1H0",
    "sg:province":"ON",
    "wof:name":"Brighton Laundromat",
    "wof:placetype":"venue"
},
  "geometry": {"coordinates":[-77.73062896730001,44.0431938171],"type":"Point"}
}