{
  "type": "Feature",
  "properties": {
    "addr:full":"Hwy 43 Rochfort Bridge AB T0E 1Y0",
    "addr:postcode":"t0e 1y0",
    "addr:street":"Hwy 43",
    "iso:country":"CA",
    "sg:address":"Hwy 43",
    "sg:city":"Rochfort Bridge",
    "sg:classifiers":[
        {
            "category":"Sports & Exercise",
            "subcategory":"Golf",
            "type":"Entertainment"
        }
    ],
    "sg:phone":"+1 780 785 3467",
    "sg:postcode":"T0E 1Y0",
    "sg:province":"AB",
    "sg:tags":[
        "course"
    ],
    "wof:name":"Rochfort Bridge Trading Post",
    "wof:placetype":"venue"
},
  "geometry": {"coordinates":[-115.053833,53.918785],"type":"Point"}
}