{
  "type": "Feature",
  "properties": {
    "addr:full":"1303 Route 776 Grand Manan NB E5G 1G4",
    "addr:housenumber":"1303",
    "addr:postcode":"e5g 1g4",
    "addr:street":"Route 776",
    "iso:country":"CA",
    "sg:address":"1303 Route 776",
    "sg:city":"Grand Manan",
    "sg:classifiers":[
        {
            "category":"Restaurant",
            "type":"Food & Drink"
        }
    ],
    "sg:phone":"+1 506 662 8341",
    "sg:postcode":"E5G 1G4",
    "sg:province":"NB",
    "wof:name":"Fundy House",
    "wof:placetype":"venue"
},
  "geometry": {"coordinates":[-66.84721399999999,44.648453],"type":"Point"}
}