{
  "type": "Feature",
  "properties": {
    "addr:full":"Surrey BC V3T 5T3",
    "addr:postcode":"v3t 5t3",
    "iso:country":"CA",
    "sg:city":"Surrey",
    "sg:classifiers":[
        {
            "category":"Professional",
            "subcategory":"Lawyer & Legal Services",
            "type":"Services"
        }
    ],
    "sg:phone":"+1 604 581 4677",
    "sg:postcode":"V3T 5T3",
    "sg:province":"BC",
    "sg:tags":[
        "attorney"
    ],
    "wof:name":"Strickland, G Brent",
    "wof:placetype":"venue"
},
  "geometry": {"coordinates":[-122.834121704,49.198841095],"type":"Point"}
}