{
  "type": "Feature",
  "properties": {
    "iso:country":"CA",
    "sg:address":"1118 Concession Rd",
    "sg:city":"Fort Erie",
    "sg:classifiers":[
        {
            "category":"Organizations",
            "subcategory":"Professional Association",
            "type":"Services"
        }
    ],
    "sg:phone":"+1 905 871 1271",
    "sg:postcode":"L2A 6R2",
    "sg:province":"ON",
    "wof:name":"Fort Erie LA France Assoc",
    "wof:placetype":"venue"
},
  "geometry": {"coordinates":[-78.927772522,42.9069519043],"type":"Point"}
}