{
  "type": "Feature",
  "properties": {
    "addr:full":"3851 Rue Masson Montreal QC H1X 1S9",
    "addr:housenumber":"3851",
    "addr:postcode":"h1x 1s9",
    "addr:street":"Rue Masson",
    "iso:country":"CA",
    "sg:address":"3851 Rue Masson",
    "sg:city":"Montreal",
    "sg:classifiers":[
        {
            "category":"Retail",
            "subcategory":"Laundry & Dry Cleaning",
            "type":"Services"
        }
    ],
    "sg:phone":"+1 514 721 6767",
    "sg:postcode":"H1X 1S9",
    "sg:province":"QC",
    "sg:tags":[
        "cleaners",
        "steam"
    ],
    "wof:name":"Nettoyeur Masson Enrg",
    "wof:placetype":"venue"
},
  "geometry": {"coordinates":[-73.57025899999999,45.556549],"type":"Point"}
}