{
  "type": "Feature",
  "properties": {
    "addr:full":"1671 Av Laurier E Montreal QC H2J 1J3",
    "addr:housenumber":"1671",
    "addr:postcode":"h2j 1j3",
    "addr:street":"Av Laurier E",
    "iso:country":"CA",
    "sg:address":"1671 Av Laurier E",
    "sg:city":"Montreal",
    "sg:classifiers":[
        {
            "category":"Personal",
            "subcategory":"Shoe Repair & Shine",
            "type":"Services"
        }
    ],
    "sg:phone":"+1 514 524 8252",
    "sg:postcode":"H2J 1J3",
    "sg:province":"QC",
    "sg:tags":[
        "repairing",
        "boot"
    ],
    "wof:name":"Cordonnerie Micho Enr",
    "wof:placetype":"venue"
},
  "geometry": {"coordinates":[-73.58205413819999,45.5355529785],"type":"Point"}
}