{
  "type": "Feature",
  "properties": {
    "addr:full":"2569 Midland Ave Scarborough ON M1S 1R3",
    "addr:housenumber":"2569",
    "addr:postcode":"m1s 1r3",
    "addr:street":"Midland Ave",
    "iso:country":"CA",
    "sg:address":"2569 Midland Ave",
    "sg:city":"Scarborough",
    "sg:classifiers":[
        {
            "category":"Organizations",
            "subcategory":"Religious Organization",
            "type":"Services"
        }
    ],
    "sg:phone":"+1 416 293 4424",
    "sg:postcode":"M1S 1R3",
    "sg:province":"ON",
    "sg:tags":[
        "church"
    ],
    "wof:name":"Knox United Church",
    "wof:placetype":"venue"
},
  "geometry": {"coordinates":[-79.278648,43.786076],"type":"Point"}
}