{
  "type": "Feature",
  "properties": {
    "iso:country":"CA",
    "sg:address":"132 St. Andrews St",
    "sg:city":"Woodstock",
    "sg:classifiers":[
        {
            "category":"Sports & Exercise",
            "subcategory":"Golf",
            "type":"Entertainment"
        }
    ],
    "sg:phone":"+1 506 328 2386",
    "sg:postcode":"E7M 2S5",
    "sg:province":"NB",
    "sg:tags":[
        "course"
    ],
    "wof:name":"Woodstock Golf & Curling Club",
    "wof:placetype":"venue"
},
  "geometry": {"coordinates":[-67.5761566162,46.1572723389],"type":"Point"}
}