{
  "type": "Feature",
  "properties": {
    "addr:full":"Calgary AB T3E 3A4",
    "addr:postcode":"t3e 3a4",
    "iso:country":"CA",
    "sg:city":"Calgary",
    "sg:classifiers":[
        {
            "category":"Banks & Credit Unions",
            "subcategory":"Bank",
            "type":"Services"
        }
    ],
    "sg:phone":"+1 403 686 7825",
    "sg:postcode":"T3E 3A4",
    "sg:province":"AB",
    "sg:tags":[
        "cashing",
        "loan",
        "check"
    ],
    "wof:name":"Instaloans",
    "wof:placetype":"venue"
},
  "geometry": {"coordinates":[-114.14137268099999,51.037197113],"type":"Point"}
}