{
  "type": "Feature",
  "properties": {
    "addr:full":"Quebec QC G1R 4X5",
    "addr:postcode":"g1r 4x5",
    "iso:country":"CA",
    "sg:city":"Quebec",
    "sg:classifiers":[
        {
            "category":"Shopping",
            "subcategory":"Clothing, Apparel, & Fashions",
            "type":"Retail Goods"
        }
    ],
    "sg:phone":"+1 418 529 2848",
    "sg:postcode":"G1R 4X5",
    "sg:province":"QC",
    "wof:name":"Boutique Revue Inc",
    "wof:placetype":"venue"
},
  "geometry": {"coordinates":[-71.217293,46.826565],"type":"Point"}
}