{
  "type": "Feature",
  "properties": {
    "addr:full":"10303 100 Ave Fort Saskatchewan AB T8L 1Y9",
    "addr:housenumber":"10303",
    "addr:postcode":"t8l 1y9",
    "addr:street":"100 Ave",
    "iso:country":"CA",
    "sg:address":"10303 100 Ave",
    "sg:city":"Fort Saskatchewan",
    "sg:classifiers":[
        {
            "category":"Shopping",
            "subcategory":"Hobbies, Toys, & Games",
            "type":"Retail Goods"
        }
    ],
    "sg:phone":"+1 780 998 9864",
    "sg:postcode":"T8L 1Y9",
    "sg:province":"AB",
    "sg:tags":[
        "craft",
        "supply"
    ],
    "wof:name":"Pastimes Craft Supplies & Gift",
    "wof:placetype":"venue"
},
  "geometry": {"coordinates":[-113.212280273,53.7126502991],"type":"Point"}
}