{
  "type": "Feature",
  "properties": {
    "addr:full":"Port Coquitlam BC V3C 2B2",
    "addr:postcode":"v3c 2b2",
    "iso:country":"CA",
    "sg:city":"Port Coquitlam",
    "sg:classifiers":[
        {
            "category":"Personal",
            "subcategory":"Beauty Salon",
            "type":"Services"
        }
    ],
    "sg:phone":"+1 604 945 1833",
    "sg:postcode":"V3C 2B2",
    "sg:province":"BC",
    "sg:tags":[
        "school",
        "manicuring"
    ],
    "wof:name":"Nails in Fashion Studio Ctr",
    "wof:placetype":"venue"
},
  "geometry": {"coordinates":[-122.780052185,49.2633895874],"type":"Point"}
}