{
  "type": "Feature",
  "properties": {
    "addr:full":"RR 3 STN Main Rocky Mountain House AB T4T 2A3",
    "addr:postcode":"t4t 2a3",
    "addr:street":"Rr 3 Stn Main",
    "iso:country":"CA",
    "sg:address":"RR 3 STN Main",
    "sg:city":"Rocky Mountain House",
    "sg:classifiers":[
        {
            "category":"Retail",
            "subcategory":"Animal Services",
            "type":"Services"
        }
    ],
    "sg:phone":"+1 403 845 7033",
    "sg:postcode":"T4T 2A3",
    "sg:province":"AB",
    "sg:tags":[
        "pet",
        "grooming",
        "washing"
    ],
    "wof:name":"K-9 Grooming",
    "wof:placetype":"venue"
},
  "geometry": {"coordinates":[-114.931236267,52.3775901794],"type":"Point"}
}