{
  "type": "Feature",
  "properties": {
    "addr:full":"Claresholm AB T0L 0T0",
    "addr:postcode":"t0l 0t0",
    "iso:country":"CA",
    "sg:city":"Claresholm",
    "sg:classifiers":[
        {
            "category":"Home & Garden",
            "subcategory":"Building Materials",
            "type":"Retail Goods"
        }
    ],
    "sg:phone":"+1 403 625 4224",
    "sg:postcode":"T0L 0T0",
    "sg:province":"AB",
    "sg:tags":[
        "glass",
        "window",
        "plate"
    ],
    "wof:name":"Claresholm Glass",
    "wof:placetype":"venue"
},
  "geometry": {"coordinates":[-113.57553900000001,50.017784],"type":"Point"}
}