{
  "type": "Feature",
  "properties": {
    "addr:full":"182 3rd Ave W Melville SK S0A 2P0",
    "addr:housenumber":"182",
    "addr:postcode":"s0a 2p0",
    "addr:street":"3Rd Ave W",
    "iso:country":"CA",
    "sg:address":"182 3rd Ave W",
    "sg:city":"Melville",
    "sg:classifiers":[
        {
            "category":"Home & Garden",
            "subcategory":"Building Materials",
            "type":"Retail Goods"
        }
    ],
    "sg:phone":"+1 306 728 5032",
    "sg:postcode":"S0A 2P0",
    "sg:province":"SK",
    "sg:tags":[
        "lumber"
    ],
    "wof:name":"North American Lumber Ltd",
    "wof:placetype":"venue"
},
  "geometry": {"coordinates":[-102.81609344500001,50.9311256409],"type":"Point"}
}