{
  "type": "Feature",
  "properties": {
    "iso:country":"CA",
    "sg:address":"168 Humber Rd",
    "sg:city":"Corner Brook",
    "sg:classifiers":[
        {
            "category":"Travel",
            "subcategory":"Hotels & Motels",
            "type":"Entertainment"
        }
    ],
    "sg:phone":"+1 709 639 9795",
    "sg:postcode":"A2H 1G8",
    "sg:province":"NL",
    "sg:tags":[
        "tourist",
        "accommodation"
    ],
    "wof:name":"Bayview Haven",
    "wof:placetype":"venue"
},
  "geometry": {"coordinates":[-57.9231834412,48.9641838074],"type":"Point"}
}