{
  "type": "Feature",
  "properties": {
    "addr:full":"510 6 St NE Calgary AB T2E 3Y6",
    "addr:housenumber":"510 6",
    "addr:postcode":"t2e 3y6",
    "addr:street":"St Ne",
    "iso:country":"CA",
    "sg:address":"510 6 St NE",
    "sg:city":"Calgary",
    "sg:classifiers":[
        {
            "category":"Building & Trades",
            "subcategory":"Construction",
            "type":"Services"
        }
    ],
    "sg:phone":"+1 403 269 2893",
    "sg:postcode":"T2E 3Y6",
    "sg:province":"AB",
    "sg:tags":[
        "tile",
        "dealer"
    ],
    "wof:name":"A-1 Marble & Tile Ltd",
    "wof:placetype":"venue"
},
  "geometry": {"coordinates":[-114.048149,51.056339],"type":"Point"}
}