{
  "type": "Feature",
  "properties": {
    "addr:full":"Toronto ON M5T 3A3",
    "addr:postcode":"m5t 3a3",
    "iso:country":"CA",
    "sg:city":"Toronto",
    "sg:classifiers":[
        {
            "category":"Professional",
            "subcategory":"Lawyer & Legal Services",
            "type":"Services"
        }
    ],
    "sg:phone":"+1 416 591 1131",
    "sg:postcode":"M5T 3A3",
    "sg:province":"ON",
    "sg:tags":[
        "attorney"
    ],
    "wof:name":"Martin, Donald G QC",
    "wof:placetype":"venue"
},
  "geometry": {"coordinates":[-79.3891983032,43.651309967],"type":"Point"}
}