{
  "type": "Feature",
  "properties": {
    "iso:country":"CA",
    "sg:city":"Cambridge",
    "sg:classifiers":[
        {
            "category":"Manufacturing",
            "subcategory":"Signs",
            "type":"Manufacturing & Wholesale Goods"
        }
    ],
    "sg:phone":"+1 519 624 1177",
    "sg:postcode":"N1R 7W4",
    "sg:province":"ON",
    "wof:name":"1 Hour Signs",
    "wof:placetype":"venue"
},
  "geometry": {"coordinates":[-80.3053359985,43.4019317627],"type":"Point"}
}