{
  "type": "Feature",
  "properties": {
    "iso:country":"CA",
    "sg:address":"11940 47 St NW",
    "sg:city":"Edmonton",
    "sg:classifiers":[
        {
            "category":"Organizations",
            "subcategory":"Religious Organization",
            "type":"Services"
        }
    ],
    "sg:phone":"+1 780 474 4924",
    "sg:postcode":"T5W 2X1",
    "sg:province":"AB",
    "sg:tags":[
        "church"
    ],
    "wof:name":"Beverley Foursquare Church",
    "wof:placetype":"venue"
},
  "geometry": {"coordinates":[-113.413917541,53.5725898743],"type":"Point"}
}