{
  "type": "Feature",
  "properties": {
    "addr:full":"Sundridge ON P0A 1Z0",
    "addr:postcode":"p0a 1z0",
    "iso:country":"CA",
    "sg:city":"Sundridge",
    "sg:classifiers":[
        {
            "category":"Wholesale",
            "subcategory":"Auto Parts",
            "type":"Manufacturing & Wholesale Goods"
        }
    ],
    "sg:phone":"+1 705 384 5318",
    "sg:postcode":"P0A 1Z0",
    "sg:province":"ON",
    "sg:tags":[
        "automobile",
        "supply"
    ],
    "wof:name":"Almaguin Automotive Ltd",
    "wof:placetype":"venue"
},
  "geometry": {"coordinates":[-79.38999200000001,45.771523],"type":"Point"}
}