{
  "type": "Feature",
  "properties": {
    "addr:full":"Calgary AB T2L 0E6",
    "addr:postcode":"t2l 0e6",
    "iso:country":"CA",
    "sg:city":"Calgary",
    "sg:classifiers":[
        {
            "category":"Restaurant",
            "type":"Food & Drink"
        }
    ],
    "sg:phone":"+1 403 220 0290",
    "sg:postcode":"T2L 0E6",
    "sg:province":"AB",
    "wof:name":"Gondola Incomparable Pizza",
    "wof:placetype":"venue"
},
  "geometry": {"coordinates":[-114.128349,51.092991],"type":"Point"}
}