{
  "type": "Feature",
  "properties": {
    "addr:full":"2444 Eglinton Ave E Scarborough ON M1K 2P7",
    "addr:housenumber":"2444",
    "addr:postcode":"m1k 2p7",
    "addr:street":"Eglinton Ave E",
    "iso:country":"CA",
    "sg:address":"2444 Eglinton Ave E",
    "sg:city":"Scarborough",
    "sg:classifiers":[
        {
            "category":"Retail",
            "subcategory":"Auto Repair",
            "type":"Services"
        }
    ],
    "sg:phone":"+1 416 264 4119",
    "sg:postcode":"M1K 2P7",
    "sg:province":"ON",
    "sg:tags":[
        "repairing",
        "automobile"
    ],
    "wof:name":"Car Court Auto Clinic",
    "wof:placetype":"venue"
},
  "geometry": {"coordinates":[-79.26467100000001,43.733395],"type":"Point"}
}