{
  "type": "Feature",
  "properties": {
    "iso:country":"CA",
    "sg:address":"9 Fenmar Dr",
    "sg:city":"North York",
    "sg:classifiers":[
        {
            "category":"Wholesale",
            "subcategory":"Machinery & Supplies",
            "type":"Manufacturing & Wholesale Goods"
        }
    ],
    "sg:phone":"+1 416 743 4417",
    "sg:postcode":"M9L 1L4",
    "sg:province":"ON",
    "sg:tags":[
        "machine",
        "equipment",
        "grinding",
        "shop"
    ],
    "wof:name":"Donlee Precision",
    "wof:placetype":"venue"
},
  "geometry": {"coordinates":[-79.534477,43.759289],"type":"Point"}
}