{
  "type": "Feature",
  "properties": {
    "addr:full":"PO Box 280 Catalina NL A0C 1J0",
    "addr:housenumber":"po",
    "addr:postcode":"a0c 1j0",
    "addr:street":"Box 280",
    "iso:country":"CA",
    "sg:address":"PO Box 280",
    "sg:city":"Catalina",
    "sg:classifiers":[
        {
            "category":"Health Services",
            "subcategory":"Doctor",
            "type":"Services"
        }
    ],
    "sg:phone":"+1 709 469 2222",
    "sg:postcode":"A0C 1J0",
    "sg:province":"NL",
    "sg:tags":[
        "clinic"
    ],
    "wof:name":"Norman, Jabez",
    "wof:placetype":"venue"
},
  "geometry": {"coordinates":[-53.077618,48.517845],"type":"Point"}
}