{
  "type": "Feature",
  "properties": {
    "addr:full":"190 Rte Quintal Saint-Liboire QC J0H 1R0",
    "addr:housenumber":"190",
    "addr:postcode":"j0h 1r0",
    "addr:street":"Rte Quintal",
    "iso:country":"CA",
    "sg:address":"190 Rte Quintal",
    "sg:city":"Saint-Liboire",
    "sg:classifiers":[
        {
            "category":"Building & Trades",
            "subcategory":"Construction",
            "type":"Services"
        }
    ],
    "sg:phone":"+1 450 793 2247",
    "sg:postcode":"J0H 1R0",
    "sg:province":"QC",
    "sg:tags":[
        "equipment",
        "kitchen",
        "maker",
        "cabinet"
    ],
    "wof:name":"Ebenisterie Germain",
    "wof:placetype":"venue"
},
  "geometry": {"coordinates":[-72.750298,45.662346],"type":"Point"}
}