{
  "type": "Feature",
  "properties": {
    "addr:full":"5485 Ferry St Niagara Falls ON L2G 1S3",
    "addr:housenumber":"5485",
    "addr:postcode":"l2g 1s3",
    "addr:street":"Ferry St",
    "iso:country":"CA",
    "sg:address":"5485 Ferry St",
    "sg:city":"Niagara Falls",
    "sg:classifiers":[
        {
            "category":"Restaurant",
            "type":"Food & Drink"
        }
    ],
    "sg:phone":"+1 905 356 3345",
    "sg:postcode":"L2G 1S3",
    "sg:province":"ON",
    "sg:tags":[
        "pizza"
    ],
    "wof:name":"Napoli Pizzeria",
    "wof:placetype":"venue"
},
  "geometry": {"coordinates":[-79.087059021,43.0896568298],"type":"Point"}
}