{
  "type": "Feature",
  "properties": {
    "iso:country":"CA",
    "sg:address":"387 Reid St",
    "sg:city":"Quesnel",
    "sg:classifiers":[
        {
            "category":"Shopping",
            "subcategory":"Clothing, Apparel, & Fashions",
            "type":"Retail Goods"
        }
    ],
    "sg:phone":"+1 250 992 7028",
    "sg:postcode":"V2J 2M5",
    "sg:province":"BC",
    "wof:name":"Pearl's Fashions Ltd",
    "wof:placetype":"venue"
},
  "geometry": {"coordinates":[-122.497085571,52.9786605835],"type":"Point"}
}