{
  "type": "Feature",
  "properties": {
    "iso:country":"CA",
    "sg:address":"322 Rte 138",
    "sg:city":"Les Escoumins",
    "sg:classifiers":[
        {
            "category":"Restaurant",
            "type":"Food & Drink"
        }
    ],
    "sg:phone":"+1 418 233 2809",
    "sg:postcode":"G0T 1K0",
    "sg:province":"QC",
    "wof:name":"Cantine Monic",
    "wof:placetype":"venue"
},
  "geometry": {"coordinates":[-69.40325927729999,48.3541679382],"type":"Point"}
}