{
  "type": "Feature",
  "properties": {
    "addr:full":"PO Box 36 Sonningdale SK S0K 4B0",
    "addr:housenumber":"po box 36",
    "addr:postcode":"s0k 4b0",
    "iso:country":"CA",
    "sg:address":"PO Box 36",
    "sg:city":"Sonningdale",
    "sg:classifiers":[
        {
            "category":"Shopping",
            "subcategory":"Hobbies, Toys, & Games",
            "type":"Retail Goods"
        }
    ],
    "sg:phone":"+1 306 237 4885",
    "sg:postcode":"S0K 4B0",
    "sg:province":"SK",
    "sg:tags":[
        "craft"
    ],
    "wof:name":"Prairie Cottage Crafts",
    "wof:placetype":"venue"
},
  "geometry": {"coordinates":[-107.683334351,52.3880653381],"type":"Point"}
}