{
  "type": "Feature",
  "properties": {
    "iso:country":"CA",
    "sg:address":"940 Belfast Rd # 215",
    "sg:city":"Ottawa",
    "sg:classifiers":[
        {
            "category":"Professional",
            "subcategory":"Art Services",
            "type":"Services"
        }
    ],
    "sg:phone":"+1 613 239 3838",
    "sg:postcode":"K1G 4A2",
    "sg:province":"ON",
    "sg:tags":[
        "production",
        "layout",
        "advertising"
    ],
    "wof:name":"Monte Cristo Productions",
    "wof:placetype":"venue"
},
  "geometry": {"coordinates":[-75.6343612671,45.4117622375],"type":"Point"}
}