{
  "type": "Feature",
  "properties": {
    "iso:country":"CA",
    "sg:address":"373 Poulin Ave",
    "sg:city":"Ottawa",
    "sg:classifiers":[
        {
            "category":"Shopping",
            "subcategory":"Computers & Home Electronics",
            "type":"Retail Goods"
        }
    ],
    "sg:phone":"+1 613 230 3923",
    "sg:postcode":"K2B 5V2",
    "sg:province":"ON",
    "sg:tags":[
        "equipment",
        "dealer"
    ],
    "wof:name":"Workshift Systems Corp",
    "wof:placetype":"venue"
},
  "geometry": {"coordinates":[-75.79168701170001,45.3626098633],"type":"Point"}
}