{
  "type": "Feature",
  "properties": {
    "addr:full":"711 Mariner Way Parksville BC V9P 1S4",
    "addr:housenumber":"711",
    "addr:postcode":"v9p 1s4",
    "addr:street":"Mariner Way",
    "iso:country":"CA",
    "sg:address":"711 Mariner Way",
    "sg:city":"Parksville",
    "sg:classifiers":[
        {
            "category":"Shopping",
            "type":"Retail Goods"
        }
    ],
    "sg:phone":"+1 250 248 7372",
    "sg:postcode":"V9P 1S4",
    "sg:province":"BC",
    "sg:tags":[
        "art",
        "gallery",
        "dealer"
    ],
    "wof:name":"Englishman River Gallery Ltd",
    "wof:placetype":"venue"
},
  "geometry": {"coordinates":[-124.31364440900001,49.3196907043],"type":"Point"}
}