{
  "type": "Feature",
  "properties": {
    "addr:full":"79 Edgebrook Close NW Calgary AB T3A 4W6",
    "addr:housenumber":"79",
    "addr:postcode":"t3a 4w6",
    "addr:street":"Edgebrook Close Nw",
    "iso:country":"CA",
    "sg:address":"79 Edgebrook Close NW",
    "sg:city":"Calgary",
    "sg:classifiers":[
        {
            "category":"Home & Garden",
            "subcategory":"Home Furnishings",
            "type":"Retail Goods"
        }
    ],
    "sg:phone":"+1 403 241 2399",
    "sg:postcode":"T3A 4W6",
    "sg:province":"AB",
    "sg:tags":[
        "curtain",
        "made",
        "drapery"
    ],
    "wof:name":"Great Shades",
    "wof:placetype":"venue"
},
  "geometry": {"coordinates":[-114.131263733,51.1295852661],"type":"Point"}
}