{
  "type": "Feature",
  "properties": {
    "addr:full":"Richmond BC V6X 3A3",
    "addr:postcode":"v6x 3a3",
    "iso:country":"CA",
    "sg:city":"Richmond",
    "sg:classifiers":[
        {
            "category":"Recreation",
            "subcategory":"Marina",
            "type":"Entertainment"
        }
    ],
    "sg:phone":"+1 604 273 6568",
    "sg:postcode":"V6X 3A3",
    "sg:province":"BC",
    "sg:tags":[
        "repairing",
        "boat"
    ],
    "wof:name":"Kwik Boat Repair & Towing Ltd",
    "wof:placetype":"venue"
},
  "geometry": {"coordinates":[-123.135154724,49.1893043518],"type":"Point"}
}