{
  "type": "Feature",
  "properties": {
    "addr:full":"Edmonton AB T5H 0X6",
    "addr:postcode":"t5h 0x6",
    "iso:country":"CA",
    "sg:city":"Edmonton",
    "sg:classifiers":[
        {
            "category":"Personal",
            "subcategory":"Barber",
            "type":"Services"
        }
    ],
    "sg:phone":"+1 780 426 2766",
    "sg:postcode":"T5H 0X6",
    "sg:province":"AB",
    "wof:name":"Sweeny Todd's Barber Stylists",
    "wof:placetype":"venue"
},
  "geometry": {"coordinates":[-113.51062,53.551273],"type":"Point"}
}