{
  "type": "Feature",
  "properties": {
    "addr:full":"1052 Deep Cove Rd North Vancouver BC V7G 1S3",
    "addr:housenumber":"1052",
    "addr:postcode":"v7g 1s3",
    "addr:street":"Deep Cove Rd",
    "iso:country":"CA",
    "sg:address":"1052 Deep Cove Rd",
    "sg:city":"North Vancouver",
    "sg:classifiers":[
        {
            "category":"Restaurant",
            "type":"Food & Drink"
        }
    ],
    "sg:phone":"+1 604 929 3834",
    "sg:postcode":"V7G 1S3",
    "sg:province":"BC",
    "wof:name":"Raven Neighbourhood Pub",
    "wof:placetype":"venue"
},
  "geometry": {"coordinates":[-122.95339199999999,49.316311],"type":"Point"}
}