{
  "type": "Feature",
  "properties": {
    "addr:full":"50 Rue Garneau Quebec QC G1R 3V5",
    "addr:housenumber":"50",
    "addr:postcode":"g1r 3v5",
    "addr:street":"Rue Garneau",
    "iso:country":"CA",
    "sg:address":"50 Rue Garneau",
    "sg:city":"Quebec",
    "sg:classifiers":[
        {
            "category":"Restaurant",
            "type":"Food & Drink"
        }
    ],
    "sg:phone":"+1 418 692 4215",
    "sg:postcode":"G1R 3V5",
    "sg:province":"QC",
    "wof:name":"Croissant Plus",
    "wof:placetype":"venue"
},
  "geometry": {"coordinates":[-71.20826,46.814777],"type":"Point"}
}