{
  "type": "Feature",
  "properties": {
    "iso:country":"CA",
    "sg:address":"93 Woodstream Blvd",
    "sg:city":"Woodbridge",
    "sg:classifiers":[
        {
            "category":"Wholesale",
            "subcategory":"Non-durable Goods",
            "type":"Manufacturing & Wholesale Goods"
        }
    ],
    "sg:phone":"+1 905 856 5120",
    "sg:postcode":"L4L 7Y7",
    "sg:province":"ON",
    "sg:tags":[
        "advertising"
    ],
    "wof:name":"Integrated Marketing Solutions",
    "wof:placetype":"venue"
},
  "geometry": {"coordinates":[-79.60377502439999,43.7746543884],"type":"Point"}
}