{
  "type": "Feature",
  "properties": {
    "addr:full":"976 Rue Honore-Mercier Iberville QC J2X 5A5",
    "addr:housenumber":"976",
    "addr:postcode":"j2x 5a5",
    "addr:street":"Rue Honore-Mercier",
    "iso:country":"CA",
    "sg:address":"976 Rue Honore-Mercier",
    "sg:city":"Iberville",
    "sg:classifiers":[
        {
            "category":"Education",
            "subcategory":"School",
            "type":"Public Place"
        }
    ],
    "sg:phone":"+1 450 347 1327",
    "sg:postcode":"J2X 5A5",
    "sg:province":"QC",
    "wof:name":"Ecole Chabanel",
    "wof:placetype":"venue"
},
  "geometry": {"coordinates":[-73.2362289429,45.2990226746],"type":"Point"}
}