{
  "type": "Feature",
  "properties": {
    "addr:full":"206 Victoria Ave Fort Frances ON P9A 2B9",
    "addr:housenumber":"206",
    "addr:postcode":"p9a 2b9",
    "addr:street":"Victoria Ave",
    "iso:country":"CA",
    "sg:address":"206 Victoria Ave",
    "sg:city":"Fort Frances",
    "sg:classifiers":[
        {
            "category":"Organizations",
            "subcategory":"Religious Organization",
            "type":"Services"
        }
    ],
    "sg:phone":"+1 807 274 5233",
    "sg:postcode":"P9A 2B9",
    "sg:province":"ON",
    "sg:tags":[
        "church"
    ],
    "wof:name":"St Mary's Church",
    "wof:placetype":"venue"
},
  "geometry": {"coordinates":[-93.392494,48.606915],"type":"Point"}
}