{
  "type": "Feature",
  "properties": {
    "addr:full":"2750 Jefferson Blvd Windsor ON N8T 3C7",
    "addr:housenumber":"2750",
    "addr:postcode":"n8t 3c7",
    "addr:street":"Jefferson Blvd",
    "iso:country":"CA",
    "sg:address":"2750 Jefferson Blvd",
    "sg:city":"Windsor",
    "sg:classifiers":[
        {
            "category":"Building & Trades",
            "subcategory":"Equipment Rental",
            "type":"Services"
        }
    ],
    "sg:phone":"+1 519 974 8800",
    "sg:postcode":"N8T 3C7",
    "sg:province":"ON",
    "sg:tags":[
        "yard",
        "contractor"
    ],
    "wof:name":"Sunrise Equipment Rental & Sls",
    "wof:placetype":"venue"
},
  "geometry": {"coordinates":[-82.94742599999999,42.303707],"type":"Point"}
}