{
  "type": "Feature",
  "properties": {
    "addr:full":"414 Lake Dr S Keswick ON L4P 1P4",
    "addr:housenumber":"414",
    "addr:postcode":"l4p 1p4",
    "addr:street":"Lake Dr S",
    "iso:country":"CA",
    "sg:address":"414 Lake Dr S",
    "sg:city":"Keswick",
    "sg:classifiers":[
        {
            "category":"Building & Trades",
            "subcategory":"Plumbing",
            "type":"Services"
        }
    ],
    "sg:phone":"+1 905 476 2236",
    "sg:postcode":"L4P 1P4",
    "sg:province":"ON",
    "sg:tags":[
        "contractor"
    ],
    "wof:name":"Bedford Plumbing & Heating",
    "wof:placetype":"venue"
},
  "geometry": {"coordinates":[-79.47272491459999,44.2140769958],"type":"Point"}
}