{
  "type": "Feature",
  "properties": {
    "addr:full":"1003 Buckskin Way Orleans ON K1C 2Y7",
    "addr:housenumber":"1003",
    "addr:postcode":"k1c 2y7",
    "addr:street":"Buckskin Way",
    "iso:country":"CA",
    "sg:address":"1003 Buckskin Way",
    "sg:city":"Orleans",
    "sg:classifiers":[
        {
            "category":"Professional",
            "subcategory":"Computer Services",
            "type":"Services"
        }
    ],
    "sg:phone":"+1 613 837 1578",
    "sg:postcode":"K1C 2Y7",
    "sg:province":"ON",
    "sg:tags":[
        "consultant"
    ],
    "wof:name":"Danara Software Systems Inc",
    "wof:placetype":"venue"
},
  "geometry": {"coordinates":[-75.544411,45.479702],"type":"Point"}
}