{
  "type": "Feature",
  "properties": {
    "addr:full":"175 Grenoble Dr North York ON M3C 3E7",
    "addr:housenumber":"175",
    "addr:postcode":"m3c 3e7",
    "addr:street":"Grenoble Dr",
    "iso:country":"CA",
    "sg:address":"175 Grenoble Dr",
    "sg:city":"North York",
    "sg:classifiers":[
        {
            "category":"Education",
            "subcategory":"School",
            "type":"Public Place"
        }
    ],
    "sg:phone":"+1 416 393 5348",
    "sg:postcode":"M3C 3E7",
    "sg:province":"ON",
    "wof:name":"John Xxiii School",
    "wof:placetype":"venue"
},
  "geometry": {"coordinates":[-79.3294372559,43.7122764587],"type":"Point"}
}