{
  "type": "Feature",
  "properties": {
    "iso:country":"CA",
    "sg:address":"295 St. George St",
    "sg:city":"Moncton",
    "sg:classifiers":[
        {
            "category":"Retail",
            "subcategory":"Auto Rental",
            "type":"Services"
        }
    ],
    "sg:phone":"+1 506 852 9337",
    "sg:postcode":"E1C 1W7",
    "sg:province":"NB",
    "sg:tags":[
        "renting",
        "automobile"
    ],
    "wof:name":"Sears Car & Truck Rental",
    "wof:placetype":"venue"
},
  "geometry": {"coordinates":[-64.78545379640001,46.0907554626],"type":"Point"}
}