{
  "type": "Feature",
  "properties": {
    "addr:full":"11319 101 St Grande Prairie AB T8V 2R8",
    "addr:housenumber":"11319",
    "addr:postcode":"t8v 2r8",
    "addr:street":"101 St",
    "iso:country":"CA",
    "sg:address":"11319 101 St",
    "sg:city":"Grande Prairie",
    "sg:classifiers":[
        {
            "category":"Professional",
            "subcategory":"Research",
            "type":"Services"
        }
    ],
    "sg:phone":"+1 780 538 3838",
    "sg:postcode":"T8V 2R8",
    "sg:province":"AB",
    "sg:tags":[
        "environmental",
        "ecological"
    ],
    "wof:name":"G P Petroleum Maintenance Ltd",
    "wof:placetype":"venue"
},
  "geometry": {"coordinates":[-118.797485352,55.182762146],"type":"Point"}
}