{
  "type": "Feature",
  "properties": {
    "iso:country":"CA",
    "sg:address":"684 Elizabeth Rd",
    "sg:city":"Winnipeg",
    "sg:classifiers":[
        {
            "category":"Retail",
            "subcategory":"Animal Services",
            "type":"Services"
        }
    ],
    "sg:phone":"+1 204 255 3611",
    "sg:postcode":"R2J 1A4",
    "sg:province":"MB",
    "sg:tags":[
        "pet",
        "grooming",
        "washing"
    ],
    "wof:name":"Dog Grooming By Darci",
    "wof:placetype":"venue"
},
  "geometry": {"coordinates":[-97.0888214111,49.8708534241],"type":"Point"}
}