{
  "type": "Feature",
  "properties": {
    "addr:full":"Kitchener ON N2H 5Z2",
    "addr:postcode":"n2h 5z2",
    "iso:country":"CA",
    "sg:city":"Kitchener",
    "sg:classifiers":[
        {
            "category":"Freight",
            "type":"Transportation"
        }
    ],
    "sg:phone":"+1 519 743 8844",
    "sg:postcode":"N2H 5Z2",
    "sg:province":"ON",
    "sg:tags":[
        "warehouse",
        "commercial"
    ],
    "wof:name":"Woodside Industrial Ctr",
    "wof:placetype":"venue"
},
  "geometry": {"coordinates":[-80.4785308838,43.4668159485],"type":"Point"}
}