{
  "type": "Feature",
  "properties": {
    "addr:full":"Timmins ON P4N 4C7",
    "addr:postcode":"p4n 4c7",
    "iso:country":"CA",
    "sg:city":"Timmins",
    "sg:classifiers":[
        {
            "category":"Manufacturing",
            "subcategory":"Tools & Machinery",
            "type":"Manufacturing & Wholesale Goods"
        }
    ],
    "sg:phone":"+1 705 264 4577",
    "sg:postcode":"P4N 4C7",
    "sg:province":"ON",
    "sg:tags":[
        "alternator",
        "starter"
    ],
    "wof:name":"Alternate Starts",
    "wof:placetype":"venue"
},
  "geometry": {"coordinates":[-81.1708679199,48.4939308167],"type":"Point"}
}