{
  "type": "Feature",
  "properties": {
    "addr:full":"1585 Liberty St Winnipeg MB R3S 1A5",
    "addr:housenumber":"1585",
    "addr:postcode":"r3s 1a5",
    "addr:street":"Liberty St",
    "iso:country":"CA",
    "sg:address":"1585 Liberty St",
    "sg:city":"Winnipeg",
    "sg:classifiers":[
        {
            "category":"Building & Trades",
            "subcategory":"Construction",
            "type":"Services"
        }
    ],
    "sg:phone":"+1 204 888 1651",
    "sg:postcode":"R3S 1A5",
    "sg:province":"MB",
    "sg:tags":[
        "painter"
    ],
    "wof:name":"Tuscany Decorating Svc",
    "wof:placetype":"venue"
},
  "geometry": {"coordinates":[-97.261566,49.828941],"type":"Point"}
}