{
  "type": "Feature",
  "properties": {
    "addr:full":"1093 Boul Saint-Felicien Saint-Felicien QC G8K 1G2",
    "addr:housenumber":"1093",
    "addr:postcode":"g8k 1g2",
    "addr:street":"Boul Saint-Felicien Saint-Felicien",
    "iso:country":"CA",
    "sg:address":"1093 Boul Saint-Felicien",
    "sg:city":"Saint-Felicien",
    "sg:classifiers":[
        {
            "category":"Autos & Motor Vehicles",
            "subcategory":"Fuel & Gas Station",
            "type":"Retail Goods"
        }
    ],
    "sg:phone":"+1 418 679 0166",
    "sg:postcode":"G8K 1G2",
    "sg:province":"QC",
    "sg:tags":[
        "oil"
    ],
    "wof:name":"Ultramar",
    "wof:placetype":"venue"
},
  "geometry": {"coordinates":[-72.450737,48.657654],"type":"Point"}
}