{
  "type": "Feature",
  "properties": {
    "addr:full":"200 Bay St # 204 Toronto ON M5J 2J6",
    "addr:housenumber":"200",
    "addr:postcode":"m5j 2j6",
    "addr:street":"Bay St # 204",
    "iso:country":"CA",
    "sg:address":"200 Bay St # 204",
    "sg:city":"Toronto",
    "sg:classifiers":[
        {
            "category":"Retail",
            "subcategory":"Portrait Studio",
            "type":"Services"
        }
    ],
    "sg:phone":"+1 416 367 2882",
    "sg:postcode":"M5J 2J6",
    "sg:province":"ON",
    "sg:tags":[
        "photographer"
    ],
    "wof:name":"Sooter's",
    "wof:placetype":"venue"
},
  "geometry": {"coordinates":[-79.3797988892,43.6471252441],"type":"Point"}
}