{
  "type": "Feature",
  "properties": {
    "addr:full":"2138 Av Poulin Beauport QC G1E 3T2",
    "addr:housenumber":"2138",
    "addr:postcode":"qc g1e 3t2",
    "addr:street":"Av Poulin",
    "iso:country":"CA",
    "sg:address":"2138 Av Poulin",
    "sg:city":"Beauport",
    "sg:classifiers":[
        {
            "category":"Building & Trades",
            "subcategory":"Equipment Rental",
            "type":"Services"
        }
    ],
    "sg:phone":"+1 418 666 5336",
    "sg:postcode":"G1E 3T2",
    "sg:province":"QC",
    "sg:tags":[
        "camping"
    ],
    "wof:name":"Rene Bertrand Tentes",
    "wof:placetype":"venue"
},
  "geometry": {"coordinates":[-71.2134857178,46.8491706848],"type":"Point"}
}