{
  "type": "Feature",
  "properties": {
    "addr:full":"971 Boul Monseigneur-DE Laval Baie-Saint-Paul QC G3Z 2W3",
    "addr:housenumber":"971",
    "addr:postcode":"g3z 2w3",
    "addr:street":"Boul Monseigneur-De Laval",
    "iso:country":"CA",
    "sg:address":"971 Boul Monseigneur-DE Laval",
    "sg:city":"Baie-Saint-Paul",
    "sg:classifiers":[
        {
            "category":"Retail",
            "subcategory":"Auto Repair",
            "type":"Services"
        }
    ],
    "sg:phone":"+1 418 435 6611",
    "sg:postcode":"G3Z 2W3",
    "sg:province":"QC",
    "sg:tags":[
        "repairing",
        "automobile",
        "body"
    ],
    "wof:name":"Atelier Debosselage E Turcotte",
    "wof:placetype":"venue"
},
  "geometry": {"coordinates":[-70.5180435181,47.4477767944],"type":"Point"}
}