{
  "type": "Feature",
  "properties": {
    "iso:country":"CA",
    "sg:city":"Burlington",
    "sg:classifiers":[
        {
            "category":"Retail",
            "subcategory":"Veterinary Services",
            "type":"Services"
        }
    ],
    "sg:phone":"+1 905 331 1870",
    "sg:postcode":"L7M 4E4",
    "sg:province":"ON",
    "sg:tags":[
        "veterinarian"
    ],
    "wof:name":"Tansley Woods Veterinary Svc",
    "wof:placetype":"venue"
},
  "geometry": {"coordinates":[-79.7985534668,43.3261604309],"type":"Point"}
}