{
  "type": "Feature",
  "properties": {
    "addr:full":"North York ON M2J 4Z2",
    "addr:postcode":"m2j 4z2",
    "iso:country":"CA",
    "sg:city":"North York",
    "sg:classifiers":[
        {
            "category":"Restaurant",
            "type":"Food & Drink"
        }
    ],
    "sg:phone":"+1 416 494 9464",
    "sg:postcode":"M2J 4Z2",
    "sg:province":"ON",
    "wof:name":"Mega Wraps",
    "wof:placetype":"venue"
},
  "geometry": {"coordinates":[-79.32403600000001,43.771275],"type":"Point"}
}