{
  "type": "Feature",
  "properties": {
    "addr:full":"Toronto ON M4T 2V7",
    "addr:postcode":"m4t 2v7",
    "iso:country":"CA",
    "sg:city":"Toronto",
    "sg:classifiers":[
        {
            "category":"Professional",
            "subcategory":"Advertising",
            "type":"Services"
        }
    ],
    "sg:phone":"+1 416 966 4564",
    "sg:postcode":"M4T 2V7",
    "sg:province":"ON",
    "sg:tags":[
        "counselor"
    ],
    "wof:name":"Padulo Advertising Inc",
    "wof:placetype":"venue"
},
  "geometry": {"coordinates":[-79.3938674927,43.6879920959],"type":"Point"}
}