{
  "type": "Feature",
  "properties": {
    "addr:full":"621 Boul Wilfrid-Hamel Quebec QC G1M 2T4",
    "addr:housenumber":"621",
    "addr:postcode":"g1m 2t4",
    "addr:street":"Boul Wilfrid-Hamel",
    "iso:country":"CA",
    "sg:address":"621 Boul Wilfrid-Hamel",
    "sg:city":"Quebec",
    "sg:classifiers":[
        {
            "category":"Personal",
            "subcategory":"Beauty Salon",
            "type":"Services"
        }
    ],
    "sg:phone":"+1 418 687 1919",
    "sg:postcode":"G1M 2T4",
    "sg:province":"QC",
    "wof:name":"Coiffe Image",
    "wof:placetype":"venue"
},
  "geometry": {"coordinates":[-71.251617,46.815369],"type":"Point"}
}