{
  "type": "Feature",
  "properties": {
    "iso:country":"CA",
    "sg:address":"215 King St E",
    "sg:city":"Hamilton",
    "sg:classifiers":[
        {
            "category":"Restaurant",
            "type":"Food & Drink"
        }
    ],
    "sg:phone":"+1 905 527 4823",
    "sg:postcode":"L8N 1B6",
    "sg:province":"ON",
    "wof:name":"Tony's Corner",
    "wof:placetype":"venue"
},
  "geometry": {"coordinates":[-79.86260223390001,43.254699707],"type":"Point"}
}