{
  "type": "Feature",
  "properties": {
    "iso:country":"CA",
    "sg:address":"102 Fraser St",
    "sg:city":"Kingston",
    "sg:classifiers":[
        {
            "category":"Retail",
            "subcategory":"Laundry & Dry Cleaning",
            "type":"Services"
        }
    ],
    "sg:phone":"+1 613 549 3509",
    "sg:postcode":"K7K 2J2",
    "sg:province":"ON",
    "sg:tags":[
        "linen",
        "supply",
        "rental",
        "uniform"
    ],
    "wof:name":"Canadian Linen & Uniform Svc",
    "wof:placetype":"venue"
},
  "geometry": {"coordinates":[-76.49137878419999,44.2460327148],"type":"Point"}
}