{
  "type": "Feature",
  "properties": {
    "addr:full":"160 Douglas St Sudbury ON P3E 1G1",
    "addr:housenumber":"160",
    "addr:postcode":"p3e 1g1",
    "addr:street":"Douglas St",
    "iso:country":"CA",
    "sg:address":"160 Douglas St",
    "sg:city":"Sudbury",
    "sg:classifiers":[
        {
            "category":"Building & Trades",
            "subcategory":"Construction",
            "type":"Services"
        }
    ],
    "sg:phone":"+1 705 673 5822",
    "sg:postcode":"P3E 1G1",
    "sg:province":"ON",
    "sg:tags":[
        "general",
        "contractor"
    ],
    "wof:name":"Prime Corp Construction Svc",
    "wof:placetype":"venue"
},
  "geometry": {"coordinates":[-81.001938,46.486034],"type":"Point"}
}