{
  "type": "Feature",
  "properties": {
    "addr:full":"2621 170 Rte Laterriere QC G7N 1A6",
    "addr:housenumber":"2621",
    "addr:postcode":"g7n 1a6",
    "addr:street":"170 Rte Laterriere",
    "iso:country":"CA",
    "sg:address":"2621 170 Rte",
    "sg:city":"Laterriere",
    "sg:classifiers":[
        {
            "category":"Retail",
            "subcategory":"Auto Repair",
            "type":"Services"
        }
    ],
    "sg:phone":"+1 418 678 1257",
    "sg:postcode":"G7N 1A6",
    "sg:province":"QC",
    "sg:tags":[
        "transmission"
    ],
    "wof:name":"Transmission Sttic Inc",
    "wof:placetype":"venue"
},
  "geometry": {"coordinates":[-71.1181335449,48.3027496338],"type":"Point"}
}