{
  "type": "Feature",
  "properties": {
    "addr:full":"Kelowna BC V1Y 8K5",
    "addr:postcode":"v1y 8k5",
    "iso:country":"CA",
    "sg:city":"Kelowna",
    "sg:classifiers":[
        {
            "category":"Shopping",
            "subcategory":"Computers & Home Electronics",
            "type":"Retail Goods"
        }
    ],
    "sg:phone":"+1 250 763 2492",
    "sg:postcode":"V1Y 8K5",
    "sg:province":"BC",
    "sg:tags":[
        "equipment",
        "dealer"
    ],
    "wof:name":"National Computer Resource",
    "wof:placetype":"venue"
},
  "geometry": {"coordinates":[-119.44348100000001,49.87899],"type":"Point"}
}