{
  "type": "Feature",
  "properties": {
    "iso:country":"CA",
    "sg:address":"108 Queen St",
    "sg:city":"Flin Flon",
    "sg:classifiers":[
        {
            "category":"Travel",
            "subcategory":"Campground",
            "type":"Entertainment"
        }
    ],
    "sg:phone":"+1 204 687 8109",
    "sg:postcode":"R8A 0M5",
    "sg:province":"MB",
    "sg:tags":[
        "camp",
        "fishing"
    ],
    "wof:name":"Phelps Lake Camp Inc",
    "wof:placetype":"venue"
},
  "geometry": {"coordinates":[-101.85376739500001,54.7841186523],"type":"Point"}
}