{
  "type": "Feature",
  "properties": {
    "addr:full":"236 King George Rd Brantford ON N3R 5L4",
    "addr:housenumber":"236",
    "addr:postcode":"n3r 5l4",
    "addr:street":"King George Rd",
    "iso:country":"CA",
    "sg:address":"236 King George Rd",
    "sg:city":"Brantford",
    "sg:classifiers":[
        {
            "category":"Autos & Motor Vehicles",
            "subcategory":"Fuel & Gas Station",
            "type":"Retail Goods"
        }
    ],
    "sg:phone":"+1 519 751 1522",
    "sg:postcode":"N3R 5L4",
    "sg:province":"ON",
    "sg:tags":[
        "oil"
    ],
    "wof:name":"Esso",
    "wof:placetype":"venue"
},
  "geometry": {"coordinates":[-80.278915,43.17654],"type":"Point"}
}