{
  "type": "Feature",
  "properties": {
    "addr:full":"North York ON M3J 2H2",
    "addr:postcode":"m3j 2h2",
    "iso:country":"CA",
    "sg:city":"North York",
    "sg:classifiers":[
        {
            "category":"Freight",
            "type":"Transportation"
        }
    ],
    "sg:phone":"+1 416 739 8600",
    "sg:postcode":"M3J 2H2",
    "sg:province":"ON",
    "sg:tags":[
        "courier"
    ],
    "wof:name":"Westminster Courier Svc",
    "wof:placetype":"venue"
},
  "geometry": {"coordinates":[-79.472649,43.773022],"type":"Point"}
}