{
  "type": "Feature",
  "properties": {
    "addr:full":"8695 Rue Hochelaga Montreal QC H1L 6J5",
    "addr:housenumber":"8695",
    "addr:postcode":"h1l 6j5",
    "addr:street":"Rue Hochelaga",
    "iso:country":"CA",
    "sg:address":"8695 Rue Hochelaga",
    "sg:city":"Montreal",
    "sg:classifiers":[
        {
            "category":"Wholesale",
            "subcategory":"Drugs",
            "type":"Manufacturing & Wholesale Goods"
        }
    ],
    "sg:phone":"+1 514 493 3711",
    "sg:postcode":"H1L 6J5",
    "sg:province":"QC",
    "sg:tags":[
        "pharmaceutical",
        "exporter"
    ],
    "wof:name":"First Monitor Canada Inc",
    "wof:placetype":"venue"
},
  "geometry": {"coordinates":[-73.52002,45.601433],"type":"Point"}
}