{
  "type": "Feature",
  "properties": {
    "addr:full":"6800 Azure Rd Richmond BC V7C 2S8",
    "addr:housenumber":"6800",
    "addr:postcode":"bc v7c 2s8",
    "addr:street":"Azure Rd",
    "iso:country":"CA",
    "sg:address":"6800 Azure Rd",
    "sg:city":"Richmond",
    "sg:classifiers":[
        {
            "category":"Social Services",
            "subcategory":"Child Care",
            "type":"Services"
        }
    ],
    "sg:phone":"+1 604 241 2511",
    "sg:postcode":"V7C 2S8",
    "sg:province":"BC",
    "wof:name":"Butterfly Progressive",
    "wof:placetype":"venue"
},
  "geometry": {"coordinates":[-123.14982605,49.1660614014],"type":"Point"}
}