{
  "type": "Feature",
  "properties": {
    "addr:full":"75 Simcoe Rd Long Sault ON K0C 1P0",
    "addr:housenumber":"75",
    "addr:postcode":"k0c 1p0",
    "addr:street":"Simcoe Rd",
    "iso:country":"CA",
    "sg:address":"75 Simcoe Rd",
    "sg:city":"Long Sault",
    "sg:classifiers":[
        {
            "category":"Recreation",
            "type":"Entertainment"
        }
    ],
    "sg:phone":"+1 613 534 3832",
    "sg:postcode":"K0C 1P0",
    "sg:province":"ON",
    "sg:tags":[
        "pool",
        "swimming"
    ],
    "wof:name":"Long Sault Wading Pool",
    "wof:placetype":"venue"
},
  "geometry": {"coordinates":[-74.89495100000001,45.029812],"type":"Point"}
}