{
  "type": "Feature",
  "properties": {
    "addr:full":"Courtenay BC V9N 1J4",
    "addr:postcode":"v9n 1j4",
    "iso:country":"CA",
    "sg:city":"Courtenay",
    "sg:classifiers":[
        {
            "category":"Shopping",
            "type":"Retail Goods"
        }
    ],
    "sg:phone":"+1 250 334 4613",
    "sg:postcode":"V9N 1J4",
    "sg:province":"BC",
    "sg:tags":[
        "pottery",
        "art",
        "gallery",
        "dealer"
    ],
    "wof:name":"Potter's Place",
    "wof:placetype":"venue"
},
  "geometry": {"coordinates":[-124.996819,49.69146],"type":"Point"}
}