{
  "type": "Feature",
  "properties": {
    "addr:full":"11212 102 Ave NW Edmonton AB T5K 0P4",
    "addr:housenumber":"11212",
    "addr:postcode":"t5k 0p4",
    "addr:street":"102 Ave Nw",
    "iso:country":"CA",
    "sg:address":"11212 102 Ave NW",
    "sg:city":"Edmonton",
    "sg:classifiers":[
        {
            "category":"Real Estate",
            "subcategory":"Real Estate Operator",
            "type":"Services"
        }
    ],
    "sg:phone":"+1 780 497 7936",
    "sg:postcode":"T5K 0P4",
    "sg:province":"AB",
    "sg:tags":[
        "apartment"
    ],
    "wof:name":"Central Court Apartments",
    "wof:placetype":"venue"
},
  "geometry": {"coordinates":[-113.514313,53.543137],"type":"Point"}
}