{
  "type": "Feature",
  "properties": {
    "addr:full":"Toronto ON M5R 2A5",
    "addr:postcode":"m5r 2a5",
    "iso:country":"CA",
    "sg:city":"Toronto",
    "sg:classifiers":[
        {
            "category":"Shopping",
            "subcategory":"Computers & Home Electronics",
            "type":"Retail Goods"
        }
    ],
    "sg:phone":"+1 416 640 5627",
    "sg:postcode":"M5R 2A5",
    "sg:province":"ON",
    "sg:tags":[
        "software"
    ],
    "wof:name":"Kenception Technologies Inc",
    "wof:placetype":"venue"
},
  "geometry": {"coordinates":[-79.38962554930001,43.6697387695],"type":"Point"}
}