{
  "type": "Feature",
  "properties": {
    "iso:country":"CA",
    "sg:address":"170 Carson Ave",
    "sg:city":"Quesnel",
    "sg:classifiers":[
        {
            "category":"Shopping",
            "subcategory":"Used Merchandise",
            "type":"Retail Goods"
        }
    ],
    "sg:phone":"+1 250 992 2755",
    "sg:postcode":"V2J 2A8",
    "sg:province":"BC",
    "sg:tags":[
        "shop",
        "thrift"
    ],
    "wof:name":"Dorothy's Duds For You",
    "wof:placetype":"venue"
},
  "geometry": {"coordinates":[-122.496894836,52.9756126404],"type":"Point"}
}