{
  "type": "Feature",
  "properties": {
    "addr:full":"829 Watt St Winnipeg MB R2K 2T3",
    "addr:housenumber":"829",
    "addr:postcode":"r2k 2t3",
    "addr:street":"Watt St",
    "iso:country":"CA",
    "sg:address":"829 Watt St",
    "sg:city":"Winnipeg",
    "sg:classifiers":[
        {
            "category":"Social Services",
            "subcategory":"Child Care",
            "type":"Services"
        }
    ],
    "sg:phone":"+1 204 669 0436",
    "sg:postcode":"R2K 2T3",
    "sg:province":"MB",
    "wof:name":"Care-A-Lot Day Care Ctr Inc",
    "wof:placetype":"venue"
},
  "geometry": {"coordinates":[-97.08907318120001,49.9258117676],"type":"Point"}
}