{
  "type": "Feature",
  "properties": {
    "iso:country":"CA",
    "sg:address":"165 Rue Principale",
    "sg:city":"Warden",
    "sg:classifiers":[
        {
            "category":"Education",
            "subcategory":"Special Training",
            "type":"Public Place"
        }
    ],
    "sg:phone":"+1 450 539 2561",
    "sg:postcode":"J0E 2M0",
    "sg:province":"QC",
    "sg:tags":[
        "educ",
        "school",
        "instruction",
        "music",
        "vocational"
    ],
    "wof:name":"Ecole DE Musique Josee Fortin",
    "wof:placetype":"venue"
},
  "geometry": {"coordinates":[-72.5051956177,45.3770828247],"type":"Point"}
}