{
  "type": "Feature",
  "properties": {
    "addr:full":"2200 Boul Industriel Magog QC J1X 5T3",
    "addr:housenumber":"2200",
    "addr:postcode":"j1x 5t3",
    "addr:street":"Boul Industriel",
    "iso:country":"CA",
    "sg:address":"2200 Boul Industriel",
    "sg:city":"Magog",
    "sg:classifiers":[
        {
            "category":"Freight",
            "type":"Transportation"
        }
    ],
    "sg:phone":"+1 819 868 4441",
    "sg:postcode":"J1X 5T3",
    "sg:province":"QC",
    "sg:tags":[
        "warehouse",
        "self",
        "storage"
    ],
    "wof:name":"Entreposage Maska Ltee",
    "wof:placetype":"venue"
},
  "geometry": {"coordinates":[-72.114616,45.277172],"type":"Point"}
}