{
  "type": "Feature",
  "properties": {
    "addr:full":"1415 Rue Notre-Dame N Sainte-Marie QC G6E 2L9",
    "addr:housenumber":"1415",
    "addr:postcode":"g6e 2l9",
    "addr:street":"Rue Notre-Dame N",
    "iso:country":"CA",
    "sg:address":"1415 Rue Notre-Dame N",
    "sg:city":"Sainte-Marie",
    "sg:classifiers":[
        {
            "category":"Personal",
            "type":"Services"
        }
    ],
    "sg:phone":"+1 418 387 3291",
    "sg:postcode":"G6E 2L9",
    "sg:province":"QC",
    "sg:tags":[
        "therapist",
        "massage"
    ],
    "wof:name":"Sante Relaxe Claudine Mathieu",
    "wof:placetype":"venue"
},
  "geometry": {"coordinates":[-71.049156189,46.4601020813],"type":"Point"}
}