{
  "type": "Feature",
  "properties": {
    "iso:country":"CA",
    "sg:city":"North York",
    "sg:classifiers":[
        {
            "category":"Health Services",
            "subcategory":"Medical Lab",
            "type":"Services"
        }
    ],
    "sg:phone":"+1 416 421 1212",
    "sg:postcode":"M3C 3A1",
    "sg:province":"ON",
    "sg:tags":[
        "laboratory"
    ],
    "wof:name":"Young Dental Lab",
    "wof:placetype":"venue"
},
  "geometry": {"coordinates":[-79.3332519531,43.7101593018],"type":"Point"}
}