{
  "type": "Feature",
  "properties": {
    "addr:full":"11808 104 Ave NW Edmonton AB T5K 2T8",
    "addr:housenumber":"11808",
    "addr:postcode":"t5k 2t8",
    "addr:street":"104 Ave Nw",
    "iso:country":"CA",
    "sg:address":"11808 104 Ave NW",
    "sg:city":"Edmonton",
    "sg:classifiers":[
        {
            "category":"Shopping",
            "subcategory":"Stationery & Office Supplies",
            "type":"Retail Goods"
        }
    ],
    "sg:phone":"+1 780 482 3663",
    "sg:postcode":"T5K 2T8",
    "sg:province":"AB",
    "sg:tags":[
        "equipment",
        "computer",
        "dealer"
    ],
    "wof:name":"Office Depot",
    "wof:placetype":"venue"
},
  "geometry": {"coordinates":[-113.52520800000001,53.546387],"type":"Point"}
}