{
  "type": "Feature",
  "properties": {
    "addr:full":"536 Carlton St St Catharines ON L2M 6Z4",
    "addr:housenumber":"536",
    "addr:postcode":"l2m 6z4",
    "addr:street":"Carlton St",
    "iso:country":"CA",
    "sg:address":"536 Carlton St",
    "sg:city":"St Catharines",
    "sg:classifiers":[
        {
            "category":"Retail",
            "subcategory":"Auto Repair",
            "type":"Services"
        }
    ],
    "sg:phone":"+1 905 935 1910",
    "sg:postcode":"L2M 6Z4",
    "sg:province":"ON",
    "sg:tags":[
        "repairing",
        "automobile"
    ],
    "wof:name":"Tom Trivieri Svc Station",
    "wof:placetype":"venue"
},
  "geometry": {"coordinates":[-79.2151107788,43.1840782166],"type":"Point"}
}