{
  "type": "Feature",
  "properties": {
    "iso:country":"CA",
    "sg:address":"431 Welland Ave",
    "sg:city":"St Catharines",
    "sg:classifiers":[
        {
            "category":"Food & Beverages",
            "subcategory":"Groceries & Convenience Stores",
            "type":"Retail Goods"
        }
    ],
    "sg:phone":"+1 905 685 4979",
    "sg:postcode":"L2M 5V2",
    "sg:province":"ON",
    "wof:name":"Avondale Stores Ltd",
    "wof:placetype":"venue"
},
  "geometry": {"coordinates":[-79.219833,43.173168],"type":"Point"}
}