{
  "type": "Feature",
  "properties": {
    "addr:full":"16 Fitzgerald Rd Nepean ON K2H 8R6",
    "addr:housenumber":"16",
    "addr:postcode":"k2h 8r6",
    "addr:street":"Fitzgerald Rd",
    "iso:country":"CA",
    "sg:address":"16 Fitzgerald Rd",
    "sg:city":"Nepean",
    "sg:classifiers":[
        {
            "category":"Professional",
            "subcategory":"Business Services",
            "type":"Services"
        }
    ],
    "sg:phone":"+1 613 721 5200",
    "sg:postcode":"K2H 8R6",
    "sg:province":"ON",
    "wof:name":"Dewar & CO Law Clerks",
    "wof:placetype":"venue"
},
  "geometry": {"coordinates":[-75.836624,45.324585],"type":"Point"}
}