{
  "type": "Feature",
  "properties": {
    "addr:full":"1179 133 Rte Sabrevois QC J0J 2G0",
    "addr:housenumber":"1179",
    "addr:postcode":"j0j 2g0",
    "addr:street":"133 Rte Sabrevois",
    "iso:country":"CA",
    "sg:address":"1179 133 Rte",
    "sg:city":"Sabrevois",
    "sg:classifiers":[
        {
            "category":"Shopping",
            "subcategory":"Used Merchandise",
            "type":"Retail Goods"
        }
    ],
    "sg:phone":"+1 450 358 4351",
    "sg:postcode":"J0J 2G0",
    "sg:province":"QC",
    "sg:tags":[
        "antique"
    ],
    "wof:name":"Chez Mon Oncle Enr",
    "wof:placetype":"venue"
},
  "geometry": {"coordinates":[-73.2304992676,45.2063903809],"type":"Point"}
}