{
  "type": "Feature",
  "properties": {
    "addr:full":"50 Juniper St Truro NS B2N 5Z8",
    "addr:housenumber":"50",
    "addr:postcode":"b2n 5z8",
    "addr:street":"Juniper St",
    "iso:country":"CA",
    "sg:address":"50 Juniper St",
    "sg:city":"Truro",
    "sg:classifiers":[
        {
            "category":"Recreation",
            "type":"Entertainment"
        }
    ],
    "sg:phone":"+1 902 893 0322",
    "sg:postcode":"B2N 5Z8",
    "sg:province":"NS",
    "sg:tags":[
        "parlor",
        "billiard"
    ],
    "wof:name":"Dooly's Billiard Room",
    "wof:placetype":"venue"
},
  "geometry": {"coordinates":[-63.299145,45.36784],"type":"Point"}
}