{
  "type": "Feature",
  "properties": {
    "addr:full":"170 Boul Fiset Sorel-Tracy QC J3P 3P4",
    "addr:housenumber":"170",
    "addr:postcode":"j3p 3p4",
    "addr:street":"Boul Fiset",
    "iso:country":"CA",
    "sg:address":"170 Boul Fiset",
    "sg:city":"Sorel-Tracy",
    "sg:classifiers":[
        {
            "category":"Food & Beverages",
            "subcategory":"Bakery",
            "type":"Retail Goods"
        }
    ],
    "sg:phone":"+1 450 742 8295",
    "sg:postcode":"J3P 3P4",
    "sg:province":"QC",
    "sg:tags":[
        "doughnut"
    ],
    "wof:name":"Dunkin' Donuts",
    "wof:placetype":"venue"
},
  "geometry": {"coordinates":[-73.102661,46.042366],"type":"Point"}
}