{
  "type": "Feature",
  "properties": {
    "addr:full":"7 Blair Dr Brampton ON L6T 2H4",
    "addr:housenumber":"7",
    "addr:postcode":"l6t 2h4",
    "addr:street":"Blair Dr",
    "iso:country":"CA",
    "sg:address":"7 Blair Dr",
    "sg:city":"Brampton",
    "sg:classifiers":[
        {
            "category":"Wholesale",
            "subcategory":"Metals & Minerals",
            "type":"Manufacturing & Wholesale Goods"
        }
    ],
    "sg:phone":"+1 905 457 5230",
    "sg:postcode":"L6T 2H4",
    "sg:province":"ON",
    "sg:tags":[
        "steel",
        "warehouse"
    ],
    "wof:name":"Debro Steel",
    "wof:placetype":"venue"
},
  "geometry": {"coordinates":[-79.7170333862,43.6931266785],"type":"Point"}
}