{
  "type": "Feature",
  "properties": {
    "addr:full":"2493 Rue Notre-Dame O Montreal QC H3J 1N6",
    "addr:housenumber":"2493",
    "addr:postcode":"h3j 1n6",
    "addr:street":"Rue Notre-Dame O",
    "iso:country":"CA",
    "sg:address":"2493 Rue Notre-Dame O",
    "sg:city":"Montreal",
    "sg:classifiers":[
        {
            "category":"Building & Trades",
            "subcategory":"Cleaning & Sanitation",
            "type":"Services"
        }
    ],
    "sg:phone":"+1 514 833 4335",
    "sg:postcode":"H3J 1N6",
    "sg:province":"QC",
    "sg:tags":[
        "house",
        "janitor"
    ],
    "wof:name":"France Andrea Marie-Josee Asso",
    "wof:placetype":"venue"
},
  "geometry": {"coordinates":[-73.5446853638,45.5291175842],"type":"Point"}
}