{
  "type": "Feature",
  "properties": {
    "addr:full":"12914 97 St NW Edmonton AB T5E 4C3",
    "addr:housenumber":"12914",
    "addr:postcode":"t5e 4c3",
    "addr:street":"97 St Nw",
    "iso:country":"CA",
    "sg:address":"12914 97 St NW",
    "sg:city":"Edmonton",
    "sg:classifiers":[
        {
            "category":"Banks & Credit Unions",
            "subcategory":"Bank",
            "type":"Services"
        }
    ],
    "sg:phone":"+1 780 413 6672",
    "sg:postcode":"T5E 4C3",
    "sg:province":"AB",
    "sg:tags":[
        "cashing",
        "loan",
        "check"
    ],
    "wof:name":"Instaloans Financial Solution",
    "wof:placetype":"venue"
},
  "geometry": {"coordinates":[-113.492111206,53.5880203247],"type":"Point"}
}