{
  "type": "Feature",
  "properties": {
    "addr:full":"Langley BC V3A 8H4",
    "addr:postcode":"v3a 8h4",
    "iso:country":"CA",
    "sg:city":"Langley",
    "sg:classifiers":[
        {
            "category":"Government",
            "subcategory":"Office",
            "type":"Public Place"
        }
    ],
    "sg:phone":"+1 604 532 3666",
    "sg:postcode":"V3A 8H4",
    "sg:province":"BC",
    "wof:name":"B C Human Resources Ministry",
    "wof:placetype":"venue"
},
  "geometry": {"coordinates":[-122.65175600000001,49.107594],"type":"Point"}
}