{
  "type": "Feature",
  "properties": {
    "iso:country":"CA",
    "sg:address":"1115 Rue Sherbrooke O # 1103",
    "sg:city":"Montreal",
    "sg:classifiers":[
        {
            "category":"Professional",
            "subcategory":"Testing Lab",
            "type":"Services"
        }
    ],
    "sg:phone":"+1 514 286 2449",
    "sg:postcode":"H3A 1H3",
    "sg:province":"QC",
    "sg:tags":[
        "laboratory"
    ],
    "wof:name":"Techmat Inc",
    "wof:placetype":"venue"
},
  "geometry": {"coordinates":[-73.5657501221,45.5215873718],"type":"Point"}
}