{
  "type": "Feature",
  "properties": {
    "addr:full":"1115 Rue Sherbrooke O # 1103 Montreal QC H3A 1H3",
    "addr:housenumber":"1115",
    "addr:postcode":"h3a 1h3",
    "addr:street":"Rue Sherbrooke O # 1103",
    "iso:country":"CA",
    "sg:address":"1115 Rue Sherbrooke O # 1103",
    "sg:city":"Montreal",
    "sg:classifiers":[
        {
            "category":"Professional",
            "subcategory":"Testing Lab",
            "type":"Services"
        }
    ],
    "sg:phone":"+1 514 286 2449",
    "sg:postcode":"H3A 1H3",
    "sg:province":"QC",
    "sg:tags":[
        "laboratory"
    ],
    "wof:name":"Techmat Inc",
    "wof:placetype":"venue"
},
  "geometry": {"coordinates":[-73.5657501221,45.5215873718],"type":"Point"}
}