{
  "type": "Feature",
  "properties": {
    "addr:full":"2283 Whyte Ave Port Coquitlam BC V3C 5Y3",
    "addr:housenumber":"2283",
    "addr:postcode":"v3c 5y3",
    "addr:street":"Whyte Ave",
    "iso:country":"CA",
    "sg:address":"2283 Whyte Ave",
    "sg:city":"Port Coquitlam",
    "sg:classifiers":[
        {
            "category":"Personal",
            "subcategory":"Piercing",
            "type":"Services"
        }
    ],
    "sg:phone":"+1 604 942 9995",
    "sg:postcode":"V3C 5Y3",
    "sg:province":"BC",
    "sg:tags":[
        "body",
        "consultant",
        "health",
        "beauty"
    ],
    "wof:name":"Seabreeze Skin Care Studio",
    "wof:placetype":"venue"
},
  "geometry": {"coordinates":[-122.781693,49.262081],"type":"Point"}
}