{
  "type": "Feature",
  "properties": {
    "addr:full":"7227 Lantzville Rd Lantzville BC V0R 2H0",
    "addr:housenumber":"7227",
    "addr:postcode":"v0r 2h0",
    "addr:street":"Lantzville Rd",
    "iso:country":"CA",
    "sg:address":"7227 Lantzville Rd",
    "sg:city":"Lantzville",
    "sg:classifiers":[
        {
            "category":"Organizations",
            "subcategory":"Community Association",
            "type":"Services"
        }
    ],
    "sg:phone":"+1 250 390 2841",
    "sg:postcode":"V0R 2H0",
    "sg:province":"BC",
    "sg:tags":[
        "fraternal"
    ],
    "wof:name":"Royal Canadian Legion Branch",
    "wof:placetype":"venue"
},
  "geometry": {"coordinates":[-124.074738,49.250286],"type":"Point"}
}