{
  "type": "Feature",
  "properties": {
    "addr:full":"993 Rue Dufferin Canton-DE-Granby QC J2G 9H8",
    "addr:housenumber":"993",
    "addr:postcode":"j2g 9h8",
    "addr:street":"Rue Dufferin Canton-De-Granby",
    "iso:country":"CA",
    "sg:address":"993 Rue Dufferin",
    "sg:city":"Canton-DE-Granby",
    "sg:classifiers":[
        {
            "category":"Building & Trades",
            "subcategory":"Construction",
            "type":"Services"
        }
    ],
    "sg:phone":"+1 450 375 1171",
    "sg:postcode":"J2G 9H8",
    "sg:province":"QC",
    "sg:tags":[
        "refinishing",
        "floor",
        "laying",
        "cabinet",
        "resurfacing",
        "maker"
    ],
    "wof:name":"Ebeniste Pierre Desilets",
    "wof:placetype":"venue"
},
  "geometry": {"coordinates":[-72.7217712402,45.3979949951],"type":"Point"}
}