{
  "type": "Feature",
  "properties": {
    "addr:full":"58 Alexander St Vancouver BC V6A 1B4",
    "addr:housenumber":"58",
    "addr:postcode":"v6a 1b4",
    "addr:street":"Alexander St",
    "iso:country":"CA",
    "sg:address":"58 Alexander St",
    "sg:city":"Vancouver",
    "sg:classifiers":[
        {
            "category":"Government",
            "subcategory":"Office",
            "type":"Public Place"
        }
    ],
    "sg:phone":"+1 604 665 3093",
    "sg:postcode":"V6A 1B4",
    "sg:province":"BC",
    "sg:tags":[
        "village"
    ],
    "wof:name":"Alexander Residence",
    "wof:placetype":"venue"
},
  "geometry": {"coordinates":[-123.10297393800001,49.2835006714],"type":"Point"}
}