{
  "type": "Feature",
  "properties": {
    "iso:country":"CA",
    "sg:address":"440 Av Des Laurentides",
    "sg:city":"Beauport",
    "sg:classifiers":[
        {
            "category":"Wholesale",
            "subcategory":"Electrical",
            "type":"Manufacturing & Wholesale Goods"
        }
    ],
    "sg:phone":"+1 418 664 0900",
    "sg:postcode":"G1C 5C4",
    "sg:province":"QC",
    "sg:tags":[
        "lighting",
        "fixture"
    ],
    "wof:name":"Eclairages Std Inc",
    "wof:placetype":"venue"
},
  "geometry": {"coordinates":[-71.1990203857,46.8781700134],"type":"Point"}
}