{
  "type": "Feature",
  "properties": {
    "iso:country":"CA",
    "sg:address":"42 Colborne St",
    "sg:city":"Fenelon Falls",
    "sg:classifiers":[
        {
            "category":"Personal",
            "subcategory":"Barber",
            "type":"Services"
        }
    ],
    "sg:phone":"+1 705 887 2905",
    "sg:postcode":"K0M 1N0",
    "sg:province":"ON",
    "wof:name":"J & B Village Barber Shop",
    "wof:placetype":"venue"
},
  "geometry": {"coordinates":[-78.73621368409999,44.5368804932],"type":"Point"}
}