{
  "type": "Feature",
  "properties": {
    "addr:full":"167 Main St S Newmarket ON L3Y 3Y9",
    "addr:housenumber":"167",
    "addr:postcode":"l3y 3y9",
    "addr:street":"Main St S",
    "iso:country":"CA",
    "sg:address":"167 Main St S",
    "sg:city":"Newmarket",
    "sg:classifiers":[
        {
            "category":"Restaurant",
            "type":"Food & Drink"
        }
    ],
    "sg:phone":"+1 905 898 1500",
    "sg:postcode":"L3Y 3Y9",
    "sg:province":"ON",
    "wof:name":"Four Seasons Chinese Food",
    "wof:placetype":"venue"
},
  "geometry": {"coordinates":[-79.4578781128,44.0541191101],"type":"Point"}
}