{
  "type": "Feature",
  "properties": {
    "addr:full":"5250 Dundas St W Etobicoke ON M9B 1A9",
    "addr:housenumber":"5250",
    "addr:postcode":"m9b 1a9",
    "addr:street":"Dundas St W",
    "iso:country":"CA",
    "sg:address":"5250 Dundas St W",
    "sg:city":"Etobicoke",
    "sg:classifiers":[
        {
            "category":"Restaurant",
            "type":"Food & Drink"
        }
    ],
    "sg:phone":"+1 416 234 8666",
    "sg:postcode":"M9B 1A9",
    "sg:province":"ON",
    "wof:name":"Wendy's",
    "wof:placetype":"venue"
},
  "geometry": {"coordinates":[-79.53846,43.638226],"type":"Point"}
}