{
  "type": "Feature",
  "properties": {
    "addr:full":"6855 Rue Jean-Talon E Saint-Leonard QC H1S 1N2",
    "addr:housenumber":"6855",
    "addr:postcode":"h1s 1n2",
    "addr:street":"Rue Jean-Talon E",
    "iso:country":"CA",
    "sg:address":"6855 Rue Jean-Talon E",
    "sg:city":"Saint-Leonard",
    "sg:classifiers":[
        {
            "category":"Home & Garden",
            "subcategory":"Furniture",
            "type":"Retail Goods"
        }
    ],
    "sg:phone":"+1 514 253 1070",
    "sg:postcode":"H1S 1N2",
    "sg:province":"QC",
    "wof:name":"Mobilia Ltee",
    "wof:placetype":"venue"
},
  "geometry": {"coordinates":[-73.5719985962,45.5957870483],"type":"Point"}
}