{
  "type": "Feature",
  "properties": {
    "addr:full":"19368 Fraser Hwy Surrey BC V3S 6K6",
    "addr:housenumber":"19368",
    "addr:postcode":"v3s 6k6",
    "addr:street":"Fraser Hwy",
    "iso:country":"CA",
    "sg:address":"19368 Fraser Hwy",
    "sg:city":"Surrey",
    "sg:classifiers":[
        {
            "category":"Shopping",
            "subcategory":"Florist",
            "type":"Retail Goods"
        }
    ],
    "sg:phone":"+1 604 534 3278",
    "sg:postcode":"V3S 6K6",
    "sg:province":"BC",
    "wof:name":"Flowers Fast Fres 'N' Fancy",
    "wof:placetype":"venue"
},
  "geometry": {"coordinates":[-122.686066,49.116535],"type":"Point"}
}