{
  "type": "Feature",
  "properties": {
    "iso:country":"CA",
    "sg:address":"205 Condon Rd",
    "sg:city":"Berwick",
    "sg:classifiers":[
        {
            "category":"Retail",
            "subcategory":"Car Wash",
            "type":"Services"
        }
    ],
    "sg:phone":"+1 902 538 9098",
    "sg:postcode":"B0P 1E0",
    "sg:province":"NS",
    "sg:tags":[
        "truck",
        "cleaning"
    ],
    "wof:name":"Valley Mobile Wash",
    "wof:placetype":"venue"
},
  "geometry": {"coordinates":[-64.7377243042,45.0498161316],"type":"Point"}
}