{
  "type": "Feature",
  "properties": {
    "addr:full":"31 Michael Ave Hanwell NB E3C 2A5",
    "addr:housenumber":"31",
    "addr:postcode":"e3c 2a5",
    "addr:street":"Michael Ave",
    "iso:country":"CA",
    "sg:address":"31 Michael Ave",
    "sg:city":"Hanwell",
    "sg:classifiers":[
        {
            "category":"Health Services",
            "subcategory":"Nursing And Care Facility",
            "type":"Services"
        }
    ],
    "sg:phone":"+1 506 451 9880",
    "sg:postcode":"E3C 2A5",
    "sg:province":"NB",
    "sg:tags":[
        "home",
        "rest"
    ],
    "wof:name":"Southampton House",
    "wof:placetype":"venue"
},
  "geometry": {"coordinates":[-66.7954406738,45.8684844971],"type":"Point"}
}