{
  "type": "Feature",
  "properties": {
    "addr:full":"12250 Rue DE L'Entreprise Sorel-Tracy QC J3P 5N3",
    "addr:housenumber":"12250",
    "addr:postcode":"j3p 5n3",
    "addr:street":"Rue De L'Entreprise",
    "iso:country":"CA",
    "sg:address":"12250 Rue DE L'Entreprise",
    "sg:city":"Sorel-Tracy",
    "sg:classifiers":[
        {
            "category":"Manufacturing",
            "subcategory":"Metals",
            "type":"Manufacturing & Wholesale Goods"
        }
    ],
    "sg:phone":"+1 450 742 2301",
    "sg:postcode":"J3P 5N3",
    "sg:province":"QC",
    "sg:tags":[
        "steel"
    ],
    "wof:name":"Lamt Inc",
    "wof:placetype":"venue"
},
  "geometry": {"coordinates":[-73.112633,46.042389],"type":"Point"}
}