{
  "type": "Feature",
  "properties": {
    "addr:full":"1750 Boul Chomedey Laval QC H7T 2W3",
    "addr:housenumber":"1750",
    "addr:postcode":"h7t 2w3",
    "addr:street":"Boul Chomedey",
    "iso:country":"CA",
    "sg:address":"1750 Boul Chomedey",
    "sg:city":"Laval",
    "sg:classifiers":[
        {
            "category":"Autos & Motor Vehicles",
            "subcategory":"Automobile Sales",
            "type":"Retail Goods"
        }
    ],
    "sg:phone":"+1 450 682 4000",
    "sg:postcode":"H7T 2W3",
    "sg:province":"QC",
    "sg:tags":[
        "car",
        "dealer"
    ],
    "wof:name":"Suzuki DE Laval",
    "wof:placetype":"venue"
},
  "geometry": {"coordinates":[-73.75308990480001,45.5573616028],"type":"Point"}
}