{
  "type": "Feature",
  "properties": {
    "iso:country":"CA",
    "sg:address":"1211 Denison St",
    "sg:city":"Markham",
    "sg:classifiers":[
        {
            "category":"Manufacturing",
            "subcategory":"Tools & Machinery",
            "type":"Manufacturing & Wholesale Goods"
        }
    ],
    "sg:phone":"+1 905 475 6730",
    "sg:postcode":"L3R 4B3",
    "sg:province":"ON",
    "sg:tags":[
        "adhesive",
        "gluing",
        "equipment"
    ],
    "wof:name":"Nordson Canada Ltd",
    "wof:placetype":"venue"
},
  "geometry": {"coordinates":[-79.322609,43.830765],"type":"Point"}
}