{
  "type": "Feature",
  "properties": {
    "addr:full":"159 Richmond St Amherstburg ON N9V 1G6",
    "addr:housenumber":"159",
    "addr:postcode":"n9v 1g6",
    "addr:street":"Richmond St",
    "iso:country":"CA",
    "sg:address":"159 Richmond St",
    "sg:city":"Amherstburg",
    "sg:classifiers":[
        {
            "category":"Personal",
            "subcategory":"Beauty Salon",
            "type":"Services"
        }
    ],
    "sg:phone":"+1 519 736 0556",
    "sg:postcode":"N9V 1G6",
    "sg:province":"ON",
    "wof:name":"Theresa & CO Unisex Hair Std",
    "wof:placetype":"venue"
},
  "geometry": {"coordinates":[-83.10776519780001,42.1034088135],"type":"Point"}
}