{
  "type": "Feature",
  "properties": {
    "iso:country":"CA",
    "sg:address":"412 5th Ave",
    "sg:city":"Matheson",
    "sg:classifiers":[
        {
            "category":"Food & Beverages",
            "subcategory":"Groceries & Convenience Stores",
            "type":"Retail Goods"
        }
    ],
    "sg:phone":"+1 705 273 2293",
    "sg:postcode":"P0K 1N0",
    "sg:province":"ON",
    "wof:name":"D & L Confectionery",
    "wof:placetype":"venue"
},
  "geometry": {"coordinates":[-80.4654464722,48.5354194641],"type":"Point"}
}