{
  "type": "Feature",
  "properties": {
    "addr:full":"15890 Av Pouliot Saint-Hyacinthe QC J2T 4C6",
    "addr:postcode":"j2t 4c6",
    "addr:street":"Av Pouliot",
    "iso:country":"CA",
    "sg:address":"15890 Av Pouliot",
    "sg:city":"Saint-Hyacinthe",
    "sg:classifiers":[
        {
            "category":"Building & Trades",
            "subcategory":"Construction",
            "type":"Services"
        }
    ],
    "sg:phone":"+1 450 773 2698",
    "sg:postcode":"J2T 4C6",
    "sg:province":"QC",
    "sg:tags":[
        "general",
        "painter",
        "contractor"
    ],
    "wof:name":"Construction Yves Giard Inc",
    "wof:placetype":"venue"
},
  "geometry": {"coordinates":[-72.93141900000001,45.628136],"type":"Point"}
}