{
  "type": "Feature",
  "properties": {
    "addr:full":"453 Bank St Ottawa ON K2P 1Y9",
    "addr:housenumber":"453",
    "addr:postcode":"k2p 1y9",
    "addr:street":"Bank St",
    "iso:country":"CA",
    "sg:address":"453 Bank St",
    "sg:city":"Ottawa",
    "sg:classifiers":[
        {
            "category":"Organizations",
            "subcategory":"Religious Organization",
            "type":"Services"
        }
    ],
    "sg:phone":"+1 613 238 8182",
    "sg:postcode":"K2P 1Y9",
    "sg:province":"ON",
    "sg:tags":[
        "church"
    ],
    "wof:name":"Metropolitan Bible Church",
    "wof:placetype":"venue"
},
  "geometry": {"coordinates":[-75.69317599999999,45.411613],"type":"Point"}
}