{
  "type": "Feature",
  "properties": {
    "addr:full":"Montreal QC H3G 1Y4",
    "addr:postcode":"h3g 1y4",
    "iso:country":"CA",
    "sg:city":"Montreal",
    "sg:classifiers":[
        {
            "category":"Professional",
            "subcategory":"Lawyer & Legal Services",
            "type":"Services"
        }
    ],
    "sg:phone":"+1 514 849 4134",
    "sg:postcode":"H3G 1Y4",
    "sg:province":"QC",
    "sg:tags":[
        "attorney"
    ],
    "wof:name":"Malcolm, Tr Anthony",
    "wof:placetype":"venue"
},
  "geometry": {"coordinates":[-73.5801696777,45.5013542175],"type":"Point"}
}