{
  "type": "Feature",
  "properties": {
    "addr:full":"Patterson St Bay Roberts NL A0A 1G0",
    "addr:postcode":"a0a 1g0",
    "addr:street":"Patterson St",
    "iso:country":"CA",
    "sg:address":"Patterson St",
    "sg:city":"Bay Roberts",
    "sg:classifiers":[
        {
            "category":"Organizations",
            "subcategory":"Religious Organization",
            "type":"Services"
        }
    ],
    "sg:phone":"+1 709 786 0740",
    "sg:postcode":"A0A 1G0",
    "sg:province":"NL",
    "sg:tags":[
        "church"
    ],
    "wof:name":"Helping Hand",
    "wof:placetype":"venue"
},
  "geometry": {"coordinates":[-53.256924,47.596329],"type":"Point"}
}