{
  "type": "Feature",
  "properties": {
    "addr:full":"502 Laurier East Angus QC J0B 1R0",
    "addr:housenumber":"502",
    "addr:postcode":"j0b 1r0",
    "addr:street":"Laurier",
    "iso:country":"CA",
    "sg:address":"502 Laurier",
    "sg:city":"East Angus",
    "sg:classifiers":[
        {
            "category":"Organizations",
            "subcategory":"Labor Organization",
            "type":"Services"
        }
    ],
    "sg:phone":"+1 819 832 2673",
    "sg:postcode":"J0B 1R0",
    "sg:province":"QC",
    "wof:name":"Syndicat Travailleurs",
    "wof:placetype":"venue"
},
  "geometry": {"coordinates":[-71.6597900391,45.4853096008],"type":"Point"}
}