{
  "type": "Feature",
  "properties": {
    "addr:full":"86 Rte 108 E Saint-Ephrem-DE-Beauce QC G0M 1R0",
    "addr:housenumber":"86",
    "addr:postcode":"g0m 1r0",
    "addr:street":"Rte 108 E Saint-Ephrem-De-Beauce",
    "iso:country":"CA",
    "sg:address":"86 Rte 108 E",
    "sg:city":"Saint-Ephrem-DE-Beauce",
    "sg:classifiers":[
        {
            "category":"Insurance",
            "subcategory":"Insurance Agent",
            "type":"Services"
        }
    ],
    "sg:phone":"+1 418 484 5641",
    "sg:postcode":"G0M 1R0",
    "sg:province":"QC",
    "wof:name":"Assurance Rodrigue & Roy",
    "wof:placetype":"venue"
},
  "geometry": {"coordinates":[-70.9533462524,46.0646095276],"type":"Point"}
}