{
  "type": "Feature",
  "properties": {
    "addr:full":"Elrose SK S0L 0Z0",
    "addr:postcode":"s0l 0z0",
    "addr:street":"Elrose",
    "iso:country":"CA",
    "sg:city":"Elrose",
    "sg:classifiers":[
        {
            "category":"Government",
            "subcategory":"Office",
            "type":"Public Place"
        }
    ],
    "sg:phone":"+1 306 378 2725",
    "sg:postcode":"S0L 0Z0",
    "sg:province":"SK",
    "wof:name":"Canada Fairview Community Past",
    "wof:placetype":"venue"
},
  "geometry": {"coordinates":[-108.02725982699999,51.2012863159],"type":"Point"}
}