{
  "type": "Feature",
  "properties": {
    "iso:country":"CA",
    "sg:city":"Sainte-Foy",
    "sg:classifiers":[
        {
            "category":"Health Services",
            "subcategory":"Health Practitioner",
            "type":"Services"
        }
    ],
    "sg:phone":"+1 418 688 9099",
    "sg:postcode":"G1N 4P4",
    "sg:province":"QC",
    "sg:tags":[
        "psychologist"
    ],
    "wof:name":"Centre DE Psychologie Humanist",
    "wof:placetype":"venue"
},
  "geometry": {"coordinates":[-71.2882156372,46.7913017273],"type":"Point"}
}