{
  "type": "Feature",
  "properties": {
    "addr:full":"5 Place Ville-Marie # 400 Montreal QC H3B 5E7",
    "addr:housenumber":"5",
    "addr:postcode":"h3b 5e7",
    "addr:street":"Place Ville-Marie # 400",
    "iso:country":"CA",
    "sg:address":"5 Place Ville-Marie # 400",
    "sg:city":"Montreal",
    "sg:classifiers":[
        {
            "category":"Banks & Credit Unions",
            "subcategory":"Bank",
            "type":"Services"
        }
    ],
    "sg:phone":"+1 514 283 5904",
    "sg:postcode":"H3B 5E7",
    "sg:province":"QC",
    "sg:tags":[
        "government"
    ],
    "wof:name":"Federal Business Dev Bank",
    "wof:placetype":"venue"
},
  "geometry": {"coordinates":[-73.56914500000001,45.500343],"type":"Point"}
}