{
  "type": "Feature",
  "properties": {
    "addr:full":"424 Mountain Ave Neepawa MB R0J 1H0",
    "addr:housenumber":"424",
    "addr:postcode":"r0j 1h0",
    "addr:street":"Mountain Ave",
    "iso:country":"CA",
    "sg:address":"424 Mountain Ave",
    "sg:city":"Neepawa",
    "sg:classifiers":[
        {
            "category":"Health Services",
            "subcategory":"Clinic",
            "type":"Services"
        }
    ],
    "sg:phone":"+1 204 476 3157",
    "sg:postcode":"R0J 1H0",
    "sg:province":"MB",
    "sg:tags":[
        "home"
    ],
    "wof:name":"Harris Pharmacy Ltd Home Hlth",
    "wof:placetype":"venue"
},
  "geometry": {"coordinates":[-99.466606,50.229046],"type":"Point"}
}