{
  "type": "Feature",
  "properties": {
    "iso:country":"CA",
    "sg:address":"18114 107 Ave NW",
    "sg:city":"Edmonton",
    "sg:classifiers":[
        {
            "category":"Building & Trades",
            "subcategory":"Construction",
            "type":"Services"
        }
    ],
    "sg:phone":"+1 780 448 7303",
    "sg:postcode":"T5S 1K5",
    "sg:province":"AB",
    "sg:tags":[
        "millwright"
    ],
    "wof:name":"Align-Tech Ind Inc",
    "wof:placetype":"venue"
},
  "geometry": {"coordinates":[-113.633872986,53.5534858704],"type":"Point"}
}