{
  "type": "Feature",
  "properties": {
    "addr:full":"6024 Rue Sherbrooke O Montreal QC H4A 1X9",
    "addr:housenumber":"6024",
    "addr:postcode":"h4a 1x9",
    "addr:street":"Rue Sherbrooke O",
    "iso:country":"CA",
    "sg:address":"6024 Rue Sherbrooke O",
    "sg:city":"Montreal",
    "sg:classifiers":[
        {
            "category":"Shopping",
            "subcategory":"Clothing, Apparel, & Fashions",
            "type":"Retail Goods"
        }
    ],
    "sg:phone":"+1 514 486 8450",
    "sg:postcode":"H4A 1X9",
    "sg:province":"QC",
    "sg:tags":[
        "item",
        "boutique"
    ],
    "wof:name":"Boutique Fancy Fit",
    "wof:placetype":"venue"
},
  "geometry": {"coordinates":[-73.5462646484,45.5770454407],"type":"Point"}
}