{
  "type": "Feature",
  "properties": {
    "addr:full":"1 St. Catherine St Grand Falls-Windsor NL A2A 1V7",
    "addr:housenumber":"1",
    "addr:postcode":"a2a 1v7",
    "addr:street":"St. Catherine St",
    "iso:country":"CA",
    "sg:address":"1 St. Catherine St",
    "sg:city":"Grand Falls-Windsor",
    "sg:classifiers":[
        {
            "category":"Education",
            "subcategory":"School",
            "type":"Public Place"
        }
    ],
    "sg:phone":"+1 709 489 3805",
    "sg:postcode":"A2A 1V7",
    "sg:province":"NL",
    "wof:name":"Millcrest Academy",
    "wof:placetype":"venue"
},
  "geometry": {"coordinates":[-55.6606407166,48.9397468567],"type":"Point"}
}