{
  "type": "Feature",
  "properties": {
    "addr:full":"30 Washburn Way Scarborough ON M1B 1H3",
    "addr:housenumber":"30",
    "addr:postcode":"m1b 1h3",
    "addr:street":"Washburn Way",
    "iso:country":"CA",
    "sg:address":"30 Washburn Way",
    "sg:city":"Scarborough",
    "sg:classifiers":[
        {
            "category":"Education",
            "subcategory":"School",
            "type":"Public Place"
        }
    ],
    "sg:phone":"+1 416 393 5351",
    "sg:postcode":"M1B 1H3",
    "sg:province":"ON",
    "wof:name":"Saint Barnabas",
    "wof:placetype":"venue"
},
  "geometry": {"coordinates":[-79.2279968262,43.7968482971],"type":"Point"}
}