{
  "type": "Feature",
  "properties": {
    "iso:country":"CA",
    "sg:address":"33 King St W",
    "sg:city":"Oshawa",
    "sg:classifiers":[
        {
            "category":"Government",
            "subcategory":"Office",
            "type":"Public Place"
        }
    ],
    "sg:phone":"+1 905 433 6500",
    "sg:postcode":"L1H 1A1",
    "sg:province":"ON",
    "wof:name":"Ontario Corporations Tax",
    "wof:placetype":"venue"
},
  "geometry": {"coordinates":[-78.86475372309999,43.8971862793],"type":"Point"}
}