{
  "type": "Feature",
  "properties": {
    "addr:full":"1122 Brydges St London ON N5W 2B7",
    "addr:housenumber":"1122",
    "addr:postcode":"n5w 2b7",
    "addr:street":"Brydges St",
    "iso:country":"CA",
    "sg:address":"1122 Brydges St",
    "sg:city":"London",
    "sg:classifiers":[
        {
            "category":"Manufacturing",
            "subcategory":"Tools & Machinery",
            "type":"Manufacturing & Wholesale Goods"
        }
    ],
    "sg:phone":"+1 519 453 3235",
    "sg:postcode":"N5W 2B7",
    "sg:province":"ON",
    "sg:tags":[
        "alternator",
        "starter"
    ],
    "wof:name":"A & N Auto Electric",
    "wof:placetype":"venue"
},
  "geometry": {"coordinates":[-81.20932769780001,42.986869812],"type":"Point"}
}