{
  "type": "Feature",
  "properties": {
    "iso:country":"CA",
    "sg:address":"5 Boul D'Youville",
    "sg:city":"Chateauguay",
    "sg:classifiers":[
        {
            "category":"Government",
            "subcategory":"Office",
            "type":"Public Place"
        }
    ],
    "sg:phone":"+1 450 698 3250",
    "sg:postcode":"J6J 2P8",
    "sg:province":"QC",
    "sg:tags":[
        "village"
    ],
    "wof:name":"Chateauguay Evaluation",
    "wof:placetype":"venue"
},
  "geometry": {"coordinates":[-73.7498474121,45.3612518311],"type":"Point"}
}