{
  "type": "Feature",
  "properties": {
    "addr:full":"Shannon QC G0A 4N0",
    "addr:postcode":"g0a 4n0",
    "iso:country":"CA",
    "sg:city":"Shannon",
    "sg:classifiers":[
        {
            "category":"Recreation",
            "type":"Entertainment"
        }
    ],
    "sg:phone":"+1 418 844 1210",
    "sg:postcode":"G0A 4N0",
    "sg:province":"QC",
    "sg:tags":[
        "provincial",
        "parks",
        "government"
    ],
    "wof:name":"Shannon Parc",
    "wof:placetype":"venue"
},
  "geometry": {"coordinates":[-71.51738,46.885967],"type":"Point"}
}