{
  "type": "Feature",
  "properties": {
    "iso:country":"CA",
    "sg:city":"Winfield",
    "sg:classifiers":[
        {
            "category":"Health Services",
            "subcategory":"Nursing And Care Facility",
            "type":"Services"
        }
    ],
    "sg:phone":"+1 250 766 3121",
    "sg:postcode":"V4V 2M2",
    "sg:province":"BC",
    "sg:tags":[
        "home",
        "convalescent",
        "community"
    ],
    "wof:name":"Lake Country Lodge",
    "wof:placetype":"venue"
},
  "geometry": {"coordinates":[-119.398727417,50.0290336609],"type":"Point"}
}