{
  "type": "Feature",
  "properties": {
    "addr:full":"17 Millbrook Cres Toronto ON M4K 1H2",
    "addr:housenumber":"17",
    "addr:postcode":"m4k 1h2",
    "addr:street":"Millbrook Cres",
    "iso:country":"CA",
    "sg:address":"17 Millbrook Cres",
    "sg:city":"Toronto",
    "sg:classifiers":[
        {
            "category":"Professional",
            "subcategory":"Management & Consulting",
            "type":"Services"
        }
    ],
    "sg:phone":"+1 416 466 7284",
    "sg:postcode":"M4K 1H2",
    "sg:province":"ON",
    "sg:tags":[
        "consultant",
        "business"
    ],
    "wof:name":"Mcc Workplace Solutions",
    "wof:placetype":"venue"
},
  "geometry": {"coordinates":[-79.353187561,43.6721763611],"type":"Point"}
}