{
  "type": "Feature",
  "properties": {
    "addr:full":"3822 Rue Dandurand Montreal QC H1X 1P2",
    "addr:housenumber":"3822",
    "addr:postcode":"h1x 1p2",
    "addr:street":"Rue Dandurand",
    "iso:country":"CA",
    "sg:address":"3822 Rue Dandurand",
    "sg:city":"Montreal",
    "sg:classifiers":[
        {
            "category":"Taxi",
            "type":"Transportation"
        }
    ],
    "sg:phone":"+1 514 725 9885",
    "sg:postcode":"H1X 1P2",
    "sg:province":"QC",
    "sg:tags":[
        "taxicab"
    ],
    "wof:name":"Coop DE Taxi DE Montreal",
    "wof:placetype":"venue"
},
  "geometry": {"coordinates":[-73.57284545900001,45.5571022034],"type":"Point"}
}