{
  "type": "Feature",
  "properties": {
    "addr:full":"Vancouver BC V6B 1G8",
    "addr:postcode":"v6b 1g8",
    "iso:country":"CA",
    "sg:city":"Vancouver",
    "sg:classifiers":[
        {
            "category":"Real Estate",
            "subcategory":"Real Estate Operator",
            "type":"Services"
        }
    ],
    "sg:phone":"+1 604 681 3728",
    "sg:postcode":"V6B 1G8",
    "sg:province":"BC",
    "sg:tags":[
        "boarding",
        "house"
    ],
    "wof:name":"Argyll House",
    "wof:placetype":"venue"
},
  "geometry": {"coordinates":[-123.107643127,49.2819366455],"type":"Point"}
}