{
  "type": "Feature",
  "properties": {
    "addr:full":"65 Spencer St Ottawa ON K1Y 4W8",
    "addr:housenumber":"65",
    "addr:postcode":"k1y 4w8",
    "addr:street":"Spencer St",
    "iso:country":"CA",
    "sg:address":"65 Spencer St",
    "sg:city":"Ottawa",
    "sg:classifiers":[
        {
            "category":"Personal",
            "subcategory":"Beauty Salon",
            "type":"Services"
        }
    ],
    "sg:phone":"+1 613 759 8177",
    "sg:postcode":"K1Y 4W8",
    "sg:province":"ON",
    "sg:tags":[
        "aromatherapy",
        "holistic",
        "practitioner"
    ],
    "wof:name":"Lortie, Lynn",
    "wof:placetype":"venue"
},
  "geometry": {"coordinates":[-75.7324295044,45.4020576477],"type":"Point"}
}