{
  "type": "Feature",
  "properties": {
    "addr:full":"46 Salme Dr Winnipeg MB R2M 1Y7",
    "addr:housenumber":"46",
    "addr:postcode":"r2m 1y7",
    "addr:street":"Salme Dr",
    "iso:country":"CA",
    "sg:address":"46 Salme Dr",
    "sg:city":"Winnipeg",
    "sg:classifiers":[
        {
            "category":"Professional",
            "subcategory":"Accounting & Tax Preparation",
            "type":"Services"
        }
    ],
    "sg:phone":"+1 204 255 5626",
    "sg:postcode":"R2M 1Y7",
    "sg:province":"MB",
    "sg:tags":[
        "accountant"
    ],
    "wof:name":"Krahn-Matthewson, Jeanne CA",
    "wof:placetype":"venue"
},
  "geometry": {"coordinates":[-97.123878479,49.8395233154],"type":"Point"}
}