{
  "type": "Feature",
  "properties": {
    "addr:full":"340 Simonston Blvd Thornhill ON L3T 4T5",
    "addr:housenumber":"340",
    "addr:postcode":"l3t 4t5",
    "addr:street":"Simonston Blvd",
    "iso:country":"CA",
    "sg:address":"340 Simonston Blvd",
    "sg:city":"Thornhill",
    "sg:classifiers":[
        {
            "category":"Wholesale",
            "subcategory":"Non-durable Goods",
            "type":"Manufacturing & Wholesale Goods"
        }
    ],
    "sg:phone":"+1 905 881 8798",
    "sg:postcode":"L3T 4T5",
    "sg:province":"ON",
    "sg:tags":[
        "advertising"
    ],
    "wof:name":"Serkin Promotions",
    "wof:placetype":"venue"
},
  "geometry": {"coordinates":[-79.3600769043,43.8161010742],"type":"Point"}
}