{
  "type": "Feature",
  "properties": {
    "addr:full":"Abbotsford BC V2S 1Y9",
    "addr:postcode":"v2s 1y9",
    "iso:country":"CA",
    "sg:city":"Abbotsford",
    "sg:classifiers":[
        {
            "category":"Real Estate",
            "subcategory":"Real Estate Operator",
            "type":"Services"
        }
    ],
    "sg:phone":"+1 604 853 0333",
    "sg:postcode":"V2S 1Y9",
    "sg:province":"BC",
    "sg:tags":[
        "apartment"
    ],
    "wof:name":"Park View Villa Apartments",
    "wof:placetype":"venue"
},
  "geometry": {"coordinates":[-122.297211,49.047714],"type":"Point"}
}