{
  "type": "Feature",
  "properties": {
    "addr:full":"Scotstown QC J0B 3B0",
    "addr:postcode":"j0b 3b0",
    "iso:country":"CA",
    "sg:city":"Scotstown",
    "sg:classifiers":[
        {
            "category":"Government",
            "subcategory":"Office",
            "type":"Public Place"
        }
    ],
    "sg:phone":"+1 819 657 2925",
    "sg:postcode":"J0B 3B0",
    "sg:province":"QC",
    "sg:tags":[
        "village"
    ],
    "wof:name":"Scotstown Garage Municipal",
    "wof:placetype":"venue"
},
  "geometry": {"coordinates":[-71.275428772,45.5262908936],"type":"Point"}
}