{
  "type": "Feature",
  "properties": {
    "addr:full":"860 Rue Longpre Sherbrooke QC J1G 5B9",
    "addr:housenumber":"860",
    "addr:postcode":"j1g 5b9",
    "addr:street":"Rue Longpre",
    "iso:country":"CA",
    "sg:address":"860 Rue Longpre",
    "sg:city":"Sherbrooke",
    "sg:classifiers":[
        {
            "category":"Freight",
            "type":"Transportation"
        }
    ],
    "sg:phone":"+1 819 346 0007",
    "sg:postcode":"J1G 5B9",
    "sg:province":"QC",
    "sg:tags":[
        "trucking"
    ],
    "wof:name":"Gsk Entreprises Inc",
    "wof:placetype":"venue"
},
  "geometry": {"coordinates":[-71.85850499999999,45.394859],"type":"Point"}
}