{
  "type": "Feature",
  "properties": {
    "addr:full":"909 Rte Lagueux Saint-Etienne-DE-Lauzon QC G6J 1A4",
    "addr:housenumber":"909",
    "addr:postcode":"g6j 1a4",
    "addr:street":"Rte Lagueux Saint-Etienne-De-Lauzon",
    "iso:country":"CA",
    "sg:address":"909 Rte Lagueux",
    "sg:city":"Saint-Etienne-DE-Lauzon",
    "sg:classifiers":[
        {
            "category":"Wholesale",
            "subcategory":"Meat",
            "type":"Manufacturing & Wholesale Goods"
        }
    ],
    "sg:phone":"+1 418 831 2835",
    "sg:postcode":"G6J 1A4",
    "sg:province":"QC",
    "sg:tags":[
        "butchering"
    ],
    "wof:name":"Boucherie Cote Pierre",
    "wof:placetype":"venue"
},
  "geometry": {"coordinates":[-71.32231899999999,46.658787],"type":"Point"}
}