{
  "type": "Feature",
  "properties": {
    "iso:country":"CA",
    "sg:address":"9724 Yonge St",
    "sg:city":"Richmond Hill",
    "sg:classifiers":[
        {
            "category":"Restaurant",
            "type":"Food & Drink"
        }
    ],
    "sg:phone":"+1 905 508 2770",
    "sg:postcode":"L4C 1V9",
    "sg:province":"ON",
    "wof:name":"London Pub CO",
    "wof:placetype":"venue"
},
  "geometry": {"coordinates":[-79.4359054565,43.86460495],"type":"Point"}
}