{
  "type": "Feature",
  "properties": {
    "iso:country":"CA",
    "sg:address":"3323 Rue Felix-Leclerc",
    "sg:city":"Vaudreuil-Dorion",
    "sg:classifiers":[
        {
            "category":"Professional",
            "subcategory":"Accounting & Tax Preparation",
            "type":"Services"
        }
    ],
    "sg:phone":"+1 450 424 7000",
    "sg:postcode":"J7V 8W5",
    "sg:province":"QC",
    "sg:tags":[
        "accountant"
    ],
    "wof:name":"Bourassa Boyer",
    "wof:placetype":"venue"
},
  "geometry": {"coordinates":[-74.1982955933,45.4432373047],"type":"Point"}
}