{
  "type": "Feature",
  "properties": {
    "iso:country":"CA",
    "sg:address":"1230 16 Ave NW",
    "sg:city":"Calgary",
    "sg:classifiers":[
        {
            "category":"Retail",
            "subcategory":"Auto Repair",
            "type":"Services"
        }
    ],
    "sg:phone":"+1 403 282 6661",
    "sg:postcode":"T2M 0K9",
    "sg:province":"AB",
    "sg:tags":[
        "automobile",
        "lubrication"
    ],
    "wof:name":"Nikkon Fast Lube",
    "wof:placetype":"venue"
},
  "geometry": {"coordinates":[-114.088127136,51.067073822],"type":"Point"}
}