{
  "type": "Feature",
  "properties": {
    "addr:full":"Mississauga ON L5L 5Y7",
    "addr:postcode":"l5l 5y7",
    "iso:country":"CA",
    "sg:city":"Mississauga",
    "sg:classifiers":[
        {
            "category":"Wholesale",
            "subcategory":"Apparel",
            "type":"Manufacturing & Wholesale Goods"
        }
    ],
    "sg:phone":"+1 905 828 8800",
    "sg:postcode":"L5L 5Y7",
    "sg:province":"ON",
    "sg:tags":[
        "textile",
        "broker"
    ],
    "wof:name":"Adam & Adams Inc",
    "wof:placetype":"venue"
},
  "geometry": {"coordinates":[-79.69927199999999,43.517517],"type":"Point"}
}