{
  "type": "Feature",
  "properties": {
    "addr:full":"Brampton ON L6V 4H4",
    "addr:postcode":"l6v 4h4",
    "iso:country":"CA",
    "sg:city":"Brampton",
    "sg:classifiers":[
        {
            "category":"Shopping",
            "type":"Retail Goods"
        }
    ],
    "sg:phone":"+1 905 874 1170",
    "sg:postcode":"L6V 4H4",
    "sg:province":"ON",
    "sg:tags":[
        "hearing",
        "equipment",
        "supply",
        "impaired"
    ],
    "wof:name":"Brampton Audiology",
    "wof:placetype":"venue"
},
  "geometry": {"coordinates":[-79.767883,43.694546],"type":"Point"}
}