{
  "type": "Feature",
  "properties": {
    "addr:full":"5032 51 Ave Whitecourt AB T7S 1P4",
    "addr:housenumber":"5032",
    "addr:postcode":"t7s 1p4",
    "addr:street":"51 Ave",
    "iso:country":"CA",
    "sg:address":"5032 51 Ave",
    "sg:city":"Whitecourt",
    "sg:classifiers":[
        {
            "category":"Health Services",
            "subcategory":"Chiropractor",
            "type":"Services"
        }
    ],
    "sg:phone":"+1 780 778 2674",
    "sg:postcode":"T7S 1P4",
    "sg:province":"AB",
    "wof:name":"Whitecourt Chiropractic Office",
    "wof:placetype":"venue"
},
  "geometry": {"coordinates":[-115.685539246,54.1415863037],"type":"Point"}
}