{
  "type": "Feature",
  "properties": {
    "addr:full":"9315 Alaska Rd Fort St John BC V1J 1A3",
    "addr:housenumber":"9315",
    "addr:postcode":"v1j 1a3",
    "addr:street":"Alaska Rd",
    "iso:country":"CA",
    "sg:address":"9315 Alaska Rd",
    "sg:city":"Fort St John",
    "sg:classifiers":[
        {
            "category":"Professional",
            "subcategory":"Research",
            "type":"Services"
        }
    ],
    "sg:phone":"+1 250 787 0010",
    "sg:postcode":"V1J 1A3",
    "sg:province":"BC",
    "sg:tags":[
        "environmental",
        "ecological"
    ],
    "wof:name":"Alpine Environmental",
    "wof:placetype":"venue"
},
  "geometry": {"coordinates":[-120.834159851,56.2318382263],"type":"Point"}
}