{
  "type": "Feature",
  "properties": {
    "addr:full":"PO Box 628 Wabasca AB T0G 2K0",
    "addr:housenumber":"po",
    "addr:postcode":"t0g 2k0",
    "addr:street":"Box 628 Wabasca",
    "iso:country":"CA",
    "sg:address":"PO Box 628",
    "sg:city":"Wabasca",
    "sg:classifiers":[
        {
            "category":"Travel",
            "subcategory":"Hotels & Motels",
            "type":"Entertainment"
        }
    ],
    "sg:phone":"+1 780 891 2267",
    "sg:postcode":"T0G 2K0",
    "sg:province":"AB",
    "sg:tags":[
        "resort"
    ],
    "wof:name":"Jennifer's Open Camp & Resort",
    "wof:placetype":"venue"
},
  "geometry": {"coordinates":[-113.823402,55.948551],"type":"Point"}
}