{
  "type": "Feature",
  "properties": {
    "addr:full":"622 Emmeline Rd Saskatoon SK S7J 5G8",
    "addr:housenumber":"622",
    "addr:postcode":"s7j 5g8",
    "addr:street":"Emmeline Rd",
    "iso:country":"CA",
    "sg:address":"622 Emmeline Rd",
    "sg:city":"Saskatoon",
    "sg:classifiers":[
        {
            "category":"Building & Trades",
            "subcategory":"Plumbing",
            "type":"Services"
        }
    ],
    "sg:phone":"+1 306 343 1414",
    "sg:postcode":"S7J 5G8",
    "sg:province":"SK",
    "sg:tags":[
        "balancing",
        "air"
    ],
    "wof:name":"Centre West Air",
    "wof:placetype":"venue"
},
  "geometry": {"coordinates":[-106.57290649399999,52.0946960449],"type":"Point"}
}