{
  "type": "Feature",
  "properties": {
    "addr:full":"210 Talbot St St Thomas ON N5P 1A9",
    "addr:housenumber":"210",
    "addr:postcode":"n5p 1a9",
    "addr:street":"Talbot St",
    "iso:country":"CA",
    "sg:address":"210 Talbot St",
    "sg:city":"St Thomas",
    "sg:classifiers":[
        {
            "category":"Retail",
            "subcategory":"Auto Repair",
            "type":"Services"
        }
    ],
    "sg:phone":"+1 519 633 3630",
    "sg:postcode":"N5P 1A9",
    "sg:province":"ON",
    "sg:tags":[
        "repairing",
        "automobile"
    ],
    "wof:name":"Factory Muffler",
    "wof:placetype":"venue"
},
  "geometry": {"coordinates":[-81.203362,42.779045],"type":"Point"}
}