{
  "type": "Feature",
  "properties": {
    "addr:full":"Oliver BC V0H 1T0",
    "addr:postcode":"bc v0h 1t0",
    "iso:country":"CA",
    "sg:city":"Oliver",
    "sg:classifiers":[
        {
            "category":"Health Services",
            "subcategory":"Doctor",
            "type":"Services"
        }
    ],
    "sg:phone":"+1 250 498 2646",
    "sg:postcode":"V0H 1T0",
    "sg:province":"BC",
    "sg:tags":[
        "dentist"
    ],
    "wof:name":"Daniel Ng Inc",
    "wof:placetype":"venue"
},
  "geometry": {"coordinates":[-119.55141399999999,49.179852],"type":"Point"}
}