{
  "type": "Feature",
  "properties": {
    "iso:country":"CA",
    "sg:address":"7725 85 St NW",
    "sg:city":"Edmonton",
    "sg:classifiers":[
        {
            "category":"Personal",
            "subcategory":"Barber",
            "type":"Services"
        }
    ],
    "sg:phone":"+1 780 466 3503",
    "sg:postcode":"T6C 3B4",
    "sg:province":"AB",
    "wof:name":"Ricci's Stylists Barber Shop",
    "wof:placetype":"venue"
},
  "geometry": {"coordinates":[-113.457923889,53.5140228271],"type":"Point"}
}