{
  "type": "Feature",
  "properties": {
    "addr:full":"2188 132 Rte E Le Bic QC G0L 1B0",
    "addr:housenumber":"2188",
    "addr:postcode":"g0l 1b0",
    "addr:street":"132 Rte E Le Bic",
    "iso:country":"CA",
    "sg:address":"2188 132 Rte E",
    "sg:city":"Le Bic",
    "sg:classifiers":[
        {
            "category":"Wholesale",
            "subcategory":"Meat",
            "type":"Manufacturing & Wholesale Goods"
        }
    ],
    "sg:phone":"+1 418 736 4323",
    "sg:postcode":"G0L 1B0",
    "sg:province":"QC",
    "wof:name":"Distribution Alimentaire Rt",
    "wof:placetype":"venue"
},
  "geometry": {"coordinates":[-68.7056427002,48.3731918335],"type":"Point"}
}