{
  "type": "Feature",
  "properties": {
    "iso:country":"CA",
    "sg:address":"30 Main St S",
    "sg:city":"Brampton",
    "sg:classifiers":[
        {
            "category":"Organizations",
            "subcategory":"Religious Organization",
            "type":"Services"
        }
    ],
    "sg:phone":"+1 905 451 1405",
    "sg:postcode":"L6W 2C4",
    "sg:province":"ON",
    "sg:tags":[
        "church"
    ],
    "wof:name":"St Paul's United Church",
    "wof:placetype":"venue"
},
  "geometry": {"coordinates":[-79.7585678101,43.6850585938],"type":"Point"}
}