{
  "type": "Feature",
  "properties": {
    "addr:full":"108 Route 255 Dsl DE Saint-Andre NB E3Y 3P8",
    "addr:housenumber":"108",
    "addr:postcode":"e3y 3p8",
    "addr:street":"Route 255 Dsl De Saint-Andre",
    "iso:country":"CA",
    "sg:address":"108 Route 255",
    "sg:city":"Dsl DE Saint-Andre",
    "sg:classifiers":[
        {
            "category":"Wholesale",
            "subcategory":"Groceries",
            "type":"Manufacturing & Wholesale Goods"
        }
    ],
    "sg:phone":"+1 506 473 6250",
    "sg:postcode":"E3Y 3P8",
    "sg:province":"NB",
    "sg:tags":[
        "grocer"
    ],
    "wof:name":"Grand Falls Central Bakery",
    "wof:placetype":"venue"
},
  "geometry": {"coordinates":[-67.75946044920001,47.105758667],"type":"Point"}
}