{
  "type": "Feature",
  "properties": {
    "addr:full":"Barriere BC V0E 1E0",
    "addr:postcode":"v0e 1e0",
    "iso:country":"CA",
    "sg:city":"Barriere",
    "sg:classifiers":[
        {
            "category":"Travel",
            "subcategory":"Campground",
            "type":"Entertainment"
        }
    ],
    "sg:phone":"+1 250 672 5685",
    "sg:postcode":"V0E 1E0",
    "sg:province":"BC",
    "wof:name":"Dee Jay Rv Park & Campground",
    "wof:placetype":"venue"
},
  "geometry": {"coordinates":[-120.12648799999999,51.168125],"type":"Point"}
}