{
  "type": "Feature",
  "properties": {
    "addr:full":"2065 Henry Ave Sidney BC V8L 5Z6",
    "addr:housenumber":"2065",
    "addr:postcode":"v8l 5z6",
    "addr:street":"Henry Ave",
    "iso:country":"CA",
    "sg:address":"2065 Henry Ave",
    "sg:city":"Sidney",
    "sg:classifiers":[
        {
            "category":"Manufacturing",
            "subcategory":"Rubber & Plastics",
            "type":"Manufacturing & Wholesale Goods"
        }
    ],
    "sg:phone":"+1 250 656 8102",
    "sg:postcode":"V8L 5Z6",
    "sg:province":"BC",
    "sg:tags":[
        "mold",
        "maker"
    ],
    "wof:name":"Scott Plastics Ltd",
    "wof:placetype":"venue"
},
  "geometry": {"coordinates":[-123.414055,48.653088],"type":"Point"}
}