{
  "type": "Feature",
  "properties": {
    "addr:full":"6455 Macleod Trail SW Calgary AB T2H 0K8",
    "addr:housenumber":"6455",
    "addr:postcode":"t2h 0k8",
    "addr:street":"Macleod Trail Sw",
    "iso:country":"CA",
    "sg:address":"6455 Macleod Trail SW",
    "sg:city":"Calgary",
    "sg:classifiers":[
        {
            "category":"Shopping",
            "subcategory":"Pharmacy",
            "type":"Retail Goods"
        }
    ],
    "sg:phone":"+1 403 255 5115",
    "sg:postcode":"T2H 0K8",
    "sg:province":"AB",
    "wof:name":"Zellers Pharmacy",
    "wof:placetype":"venue"
},
  "geometry": {"coordinates":[-114.071831,50.996162],"type":"Point"}
}