{
  "type": "Feature",
  "properties": {
    "iso:country":"CA",
    "sg:address":"2021 Lakeshore Rd",
    "sg:city":"Burlington",
    "sg:classifiers":[
        {
            "category":"Building & Trades",
            "subcategory":"Construction",
            "type":"Services"
        }
    ],
    "sg:phone":"+1 905 634 9981",
    "sg:postcode":"L7R 1A2",
    "sg:province":"ON",
    "sg:tags":[
        "concrete",
        "paving",
        "contractor"
    ],
    "wof:name":"Triple F Paving CO Ltd",
    "wof:placetype":"venue"
},
  "geometry": {"coordinates":[-79.7952957153,43.3248748779],"type":"Point"}
}