{
  "type": "Feature",
  "properties": {
    "addr:full":"503 Ch Chute Cookshire QC J0B 1M0",
    "addr:housenumber":"503",
    "addr:postcode":"j0b 1m0",
    "addr:street":"Ch Chute Cookshire",
    "iso:country":"CA",
    "sg:address":"503 Ch Chute",
    "sg:city":"Cookshire",
    "sg:classifiers":[
        {
            "category":"Retail",
            "subcategory":"Repair Shop",
            "type":"Services"
        }
    ],
    "sg:phone":"+1 819 875 3574",
    "sg:postcode":"J0B 1M0",
    "sg:province":"QC",
    "sg:tags":[
        "sharpening"
    ],
    "wof:name":"Aiguisage General Enr",
    "wof:placetype":"venue"
},
  "geometry": {"coordinates":[-71.654854,45.37381],"type":"Point"}
}