{
  "type": "Feature",
  "properties": {
    "addr:full":"736 Tyee Rd Victoria BC V9A 6X3",
    "addr:housenumber":"736",
    "addr:postcode":"v9a 6x3",
    "addr:street":"Tyee Rd",
    "iso:country":"CA",
    "sg:address":"736 Tyee Rd",
    "sg:city":"Victoria",
    "sg:classifiers":[
        {
            "category":"Home & Garden",
            "subcategory":"Building Materials",
            "type":"Retail Goods"
        }
    ],
    "sg:phone":"+1 250 383 2795",
    "sg:postcode":"V9A 6X3",
    "sg:province":"BC",
    "sg:tags":[
        "door"
    ],
    "wof:name":"Action Door Svc Inc",
    "wof:placetype":"venue"
},
  "geometry": {"coordinates":[-123.382041931,48.4351577759],"type":"Point"}
}