{
  "type": "Feature",
  "properties": {
    "addr:full":"724 Caledonia Rd York ON M6B 3X7",
    "addr:housenumber":"724",
    "addr:postcode":"m6b 3x7",
    "addr:street":"Caledonia Rd",
    "iso:country":"CA",
    "sg:address":"724 Caledonia Rd",
    "sg:city":"York",
    "sg:classifiers":[
        {
            "category":"Manufacturing",
            "subcategory":"Apparel",
            "type":"Manufacturing & Wholesale Goods"
        }
    ],
    "sg:phone":"+1 416 781 5440",
    "sg:postcode":"M6B 3X7",
    "sg:province":"ON",
    "sg:tags":[
        "textile",
        "bedding",
        "manufacturer"
    ],
    "wof:name":"Hollander Canada Home Fashions",
    "wof:placetype":"venue"
},
  "geometry": {"coordinates":[-79.46380600000001,43.698917],"type":"Point"}
}