{
  "type": "Feature",
  "properties": {
    "addr:full":"Farm Strongfield SK S0H 3Z0",
    "addr:postcode":"s0h 3z0",
    "iso:country":"CA",
    "sg:address":"Farm",
    "sg:city":"Strongfield",
    "sg:classifiers":[
        {
            "category":"Freight",
            "type":"Transportation"
        }
    ],
    "sg:phone":"+1 306 857 2033",
    "sg:postcode":"S0H 3Z0",
    "sg:province":"SK",
    "sg:tags":[
        "trucking"
    ],
    "wof:name":"Norrish Trucking",
    "wof:placetype":"venue"
},
  "geometry": {"coordinates":[-106.590012,51.330769],"type":"Point"}
}