{
  "type": "Feature",
  "properties": {
    "addr:full":"220 68 St NE Calgary AB T2A 6P7",
    "addr:postcode":"220 68;t2a 6p7",
    "addr:street":"St Ne",
    "iso:country":"CA",
    "sg:address":"220 68 St NE",
    "sg:city":"Calgary",
    "sg:classifiers":[
        {
            "category":"Autos & Motor Vehicles",
            "subcategory":"Fuel & Gas Station",
            "type":"Retail Goods"
        }
    ],
    "sg:phone":"+1 403 272 4868",
    "sg:postcode":"T2A 6P7",
    "sg:province":"AB",
    "sg:tags":[
        "oil"
    ],
    "wof:name":"Abbeydale Esso",
    "wof:placetype":"venue"
},
  "geometry": {"coordinates":[-113.93489099999999,51.053013],"type":"Point"}
}