{
  "type": "Feature",
  "properties": {
    "addr:full":"7 Carl St Moncton NB E1A 3R6",
    "addr:housenumber":"7",
    "addr:postcode":"e1a 3r6",
    "addr:street":"Carl St",
    "iso:country":"CA",
    "sg:address":"7 Carl St",
    "sg:city":"Moncton",
    "sg:classifiers":[
        {
            "category":"Freight",
            "type":"Transportation"
        }
    ],
    "sg:phone":"+1 506 383 1144",
    "sg:postcode":"E1A 3R6",
    "sg:province":"NB",
    "sg:tags":[
        "delivery"
    ],
    "wof:name":"Ike's Light Delivery",
    "wof:placetype":"venue"
},
  "geometry": {"coordinates":[-64.7866973877,46.1198616028],"type":"Point"}
}