{
  "type": "Feature",
  "properties": {
    "addr:full":"Vancouver BC V6J 1G5",
    "addr:postcode":"v6j 1g5",
    "iso:country":"CA",
    "sg:city":"Vancouver",
    "sg:classifiers":[
        {
            "category":"Personal",
            "subcategory":"Beauty Salon",
            "type":"Services"
        }
    ],
    "sg:phone":"+1 604 731 3171",
    "sg:postcode":"V6J 1G5",
    "sg:province":"BC",
    "wof:name":"David Charles Hair Salon",
    "wof:placetype":"venue"
},
  "geometry": {"coordinates":[-123.147247315,49.2704429626],"type":"Point"}
}