{
  "type": "Feature",
  "properties": {
    "addr:full":"42294 Highland Dr Chilliwack BC V2R 5H2",
    "addr:housenumber":"42294",
    "addr:postcode":"v2r 5h2",
    "addr:street":"Highland Dr",
    "iso:country":"CA",
    "sg:address":"42294 Highland Dr",
    "sg:city":"Chilliwack",
    "sg:classifiers":[
        {
            "category":"Building & Trades",
            "subcategory":"Construction",
            "type":"Services"
        }
    ],
    "sg:phone":"+1 604 946 6350",
    "sg:postcode":"V2R 5H2",
    "sg:province":"BC",
    "sg:tags":[
        "designer",
        "dealer",
        "pool",
        "swimming"
    ],
    "wof:name":"Sparkle Pools",
    "wof:placetype":"venue"
},
  "geometry": {"coordinates":[-122.05278778100001,49.0720596313],"type":"Point"}
}