{
  "type": "Feature",
  "properties": {
    "addr:full":"38 Parkside Dr Newmarket ON L3Y 8J9",
    "addr:housenumber":"38",
    "addr:postcode":"l3y 8j9",
    "addr:street":"Parkside Dr",
    "iso:country":"CA",
    "sg:address":"38 Parkside Dr",
    "sg:city":"Newmarket",
    "sg:classifiers":[
        {
            "category":"Insurance",
            "subcategory":"Insurance Agent",
            "type":"Services"
        }
    ],
    "sg:phone":"+1 905 898 0008",
    "sg:postcode":"L3Y 8J9",
    "sg:province":"ON",
    "sg:tags":[
        "adjuster"
    ],
    "wof:name":"Crawford Adjusters Canada Inc",
    "wof:placetype":"venue"
},
  "geometry": {"coordinates":[-79.47272491459999,44.0550537109],"type":"Point"}
}