{
  "type": "Feature",
  "properties": {
    "addr:full":"PO Box 78 Wellington Station PE C0B 2E0",
    "addr:housenumber":"po box 78",
    "addr:postcode":"c0b 2e0",
    "addr:street":"Wellington",
    "iso:country":"CA",
    "sg:address":"PO Box 78",
    "sg:city":"Wellington Station",
    "sg:classifiers":[
        {
            "category":"Health Services",
            "subcategory":"Doctor",
            "type":"Services"
        }
    ],
    "sg:phone":"+1 902 854 2017",
    "sg:postcode":"C0B 2E0",
    "sg:province":"PE",
    "sg:tags":[
        "clinic"
    ],
    "wof:name":"Wellington Medical Ctr",
    "wof:placetype":"venue"
},
  "geometry": {"coordinates":[-64.00045,46.449951],"type":"Point"}
}