{
  "type": "Feature",
  "properties": {
    "addr:full":"Montreal QC H2Y 3C3",
    "addr:postcode":"h2y 3c3",
    "iso:country":"CA",
    "sg:city":"Montreal",
    "sg:classifiers":[
        {
            "category":"Restaurant",
            "type":"Food & Drink"
        }
    ],
    "sg:phone":"+1 514 849 3535",
    "sg:postcode":"H2Y 3C3",
    "sg:province":"QC",
    "wof:name":"Filles Du Roy",
    "wof:placetype":"venue"
},
  "geometry": {"coordinates":[-73.5515213013,45.5099868774],"type":"Point"}
}