{
  "type": "Feature",
  "properties": {
    "addr:full":"Brampton ON L6S 5N4",
    "addr:postcode":"l6s 5n4",
    "iso:country":"CA",
    "sg:city":"Brampton",
    "sg:classifiers":[
        {
            "category":"Manufacturing",
            "subcategory":"Tools & Machinery",
            "type":"Manufacturing & Wholesale Goods"
        }
    ],
    "sg:phone":"+1 416 803 8665",
    "sg:postcode":"L6S 5N4",
    "sg:province":"ON",
    "sg:tags":[
        "die",
        "maker"
    ],
    "wof:name":"Pas Tooling Inc",
    "wof:placetype":"venue"
},
  "geometry": {"coordinates":[-79.70816000000001,43.755219],"type":"Point"}
}