{
  "type": "Feature",
  "properties": {
    "iso:country":"CA",
    "sg:city":"Rouyn-Noranda",
    "sg:classifiers":[
        {
            "category":"Wholesale",
            "subcategory":"Office Equipment",
            "type":"Manufacturing & Wholesale Goods"
        }
    ],
    "sg:phone":"+1 819 797 4354",
    "sg:postcode":"J9X 4P1",
    "sg:province":"QC",
    "sg:tags":[
        "accounting",
        "bookkeeping",
        "system"
    ],
    "wof:name":"Gestion Jacques Levesque",
    "wof:placetype":"venue"
},
  "geometry": {"coordinates":[-79.01979064939999,48.240562439],"type":"Point"}
}