{
  "type": "Feature",
  "properties": {
    "addr:full":"1294 Balmoral St Thunder Bay ON P7B 5Z5",
    "addr:housenumber":"1294",
    "addr:postcode":"p7b 5z5",
    "addr:street":"Balmoral St",
    "iso:country":"CA",
    "sg:address":"1294 Balmoral St",
    "sg:city":"Thunder Bay",
    "sg:classifiers":[
        {
            "category":"Professional",
            "subcategory":"Management & Consulting",
            "type":"Services"
        }
    ],
    "sg:phone":"+1 807 768 6682",
    "sg:postcode":"P7B 5Z5",
    "sg:province":"ON",
    "sg:tags":[
        "consultant",
        "business"
    ],
    "wof:name":"Northwestern Ontario Tech",
    "wof:placetype":"venue"
},
  "geometry": {"coordinates":[-89.25653800000001,48.419201],"type":"Point"}
}