{
  "type": "Feature",
  "properties": {
    "addr:full":"Oakville ON L6L 5G8",
    "addr:postcode":"l6l 5g8",
    "iso:country":"CA",
    "sg:city":"Oakville",
    "sg:classifiers":[
        {
            "category":"Health Services",
            "subcategory":"Doctor",
            "type":"Services"
        }
    ],
    "sg:phone":"+1 905 827 6102",
    "sg:postcode":"L6L 5G8",
    "sg:province":"ON",
    "sg:tags":[
        "dentist"
    ],
    "wof:name":"Brown, Grant DDS",
    "wof:placetype":"venue"
},
  "geometry": {"coordinates":[-79.70552062989999,43.4114265442],"type":"Point"}
}