{
  "type": "Feature",
  "properties": {
    "addr:full":"299 Norfinch Dr North York ON M3N 1Y7",
    "addr:housenumber":"299",
    "addr:postcode":"m3n 1y7",
    "addr:street":"Norfinch Dr",
    "iso:country":"CA",
    "sg:address":"299 Norfinch Dr",
    "sg:city":"North York",
    "sg:classifiers":[
        {
            "category":"Manufacturing",
            "subcategory":"Building Materials",
            "type":"Manufacturing & Wholesale Goods"
        }
    ],
    "sg:phone":"+1 416 665 7474",
    "sg:postcode":"M3N 1Y7",
    "sg:province":"ON",
    "sg:tags":[
        "molding"
    ],
    "wof:name":"Canadian Coral Inc",
    "wof:placetype":"venue"
},
  "geometry": {"coordinates":[-79.52959442140001,43.7637481689],"type":"Point"}
}