{
  "type": "Feature",
  "properties": {
    "iso:country":"CA",
    "sg:city":"Surrey",
    "sg:classifiers":[
        {
            "category":"Food & Beverages",
            "subcategory":"Candy",
            "type":"Retail Goods"
        }
    ],
    "sg:phone":"+1 604 531 6777",
    "sg:postcode":"V4A 2H9",
    "sg:province":"BC",
    "sg:tags":[
        "confectionery"
    ],
    "wof:name":"Chocolaterie Bernard Callebaut",
    "wof:placetype":"venue"
},
  "geometry": {"coordinates":[-122.797424316,49.045791626],"type":"Point"}
}