{
  "type": "Feature",
  "properties": {
    "iso:country":"CA",
    "sg:address":"33 Rue Blainville O",
    "sg:city":"Sainte-Therese",
    "sg:classifiers":[
        {
            "category":"Real Estate",
            "subcategory":"Architect",
            "type":"Services"
        }
    ],
    "sg:phone":"+1 450 430 2112",
    "sg:postcode":"J7E 1X1",
    "sg:province":"QC",
    "wof:name":"Berthiaume & Assoc",
    "wof:placetype":"venue"
},
  "geometry": {"coordinates":[-73.839104,45.639145],"type":"Point"}
}