{
  "type": "Feature",
  "properties": {
    "addr:full":"Cookstown ON L0L 1L0",
    "addr:postcode":"l0l 1l0",
    "iso:country":"CA",
    "sg:city":"Cookstown",
    "sg:classifiers":[
        {
            "category":"Wholesale",
            "subcategory":"Auto Parts",
            "type":"Manufacturing & Wholesale Goods"
        }
    ],
    "sg:phone":"+1 705 428 3410",
    "sg:postcode":"L0L 1L0",
    "sg:province":"ON",
    "sg:tags":[
        "automobile",
        "rebuilt"
    ],
    "wof:name":"Cookstown Auto Ctr Ltd",
    "wof:placetype":"venue"
},
  "geometry": {"coordinates":[-79.702797,44.189636],"type":"Point"}
}