{
  "type": "Feature",
  "properties": {
    "addr:full":"350 Bayfield Rd Goderich ON N7A 3G7",
    "addr:housenumber":"350",
    "addr:postcode":"n7a 3g7",
    "addr:street":"Bayfield Rd",
    "iso:country":"CA",
    "sg:address":"350 Bayfield Rd",
    "sg:city":"Goderich",
    "sg:classifiers":[
        {
            "category":"Restaurant",
            "type":"Food & Drink"
        }
    ],
    "sg:phone":"+1 519 524 7711",
    "sg:postcode":"N7A 3G7",
    "sg:province":"ON",
    "wof:name":"Candlelight Restaurant & Tvrn",
    "wof:placetype":"venue"
},
  "geometry": {"coordinates":[-81.706085,43.731907],"type":"Point"}
}