{
  "type": "Feature",
  "properties": {
    "iso:country":"CA",
    "sg:address":"950 Wharf St",
    "sg:city":"Victoria",
    "sg:classifiers":[
        {
            "category":"Airline",
            "type":"Transportation"
        }
    ],
    "sg:phone":"+1 250 414 4223",
    "sg:postcode":"V8W 1T3",
    "sg:province":"BC",
    "sg:tags":[
        "cargo",
        "company",
        "air"
    ],
    "wof:name":"Harbour Air Seaplanes Freight",
    "wof:placetype":"venue"
},
  "geometry": {"coordinates":[-123.369888,48.424023],"type":"Point"}
}