{
  "type": "Feature",
  "properties": {
    "addr:full":"130 Rue Saint-Maurice Cap-DE-LA-Madeleine QC G8T 8T2",
    "addr:housenumber":"130",
    "addr:postcode":"g8t 8t2",
    "addr:street":"Rue Saint-Maurice",
    "iso:country":"CA",
    "sg:address":"130 Rue Saint-Maurice",
    "sg:city":"Cap-DE-LA-Madeleine",
    "sg:classifiers":[
        {
            "category":"Food & Beverages",
            "subcategory":"Groceries & Convenience Stores",
            "type":"Retail Goods"
        }
    ],
    "sg:phone":"+1 819 376 2801",
    "sg:postcode":"G8T 8T2",
    "sg:province":"QC",
    "sg:tags":[
        "grocer"
    ],
    "wof:name":"Depanneur Jaco",
    "wof:placetype":"venue"
},
  "geometry": {"coordinates":[-72.5031051636,46.3730354309],"type":"Point"}
}