{
  "type": "Feature",
  "properties": {
    "addr:full":"32 Wall St Brockville ON K6V 4R9",
    "addr:housenumber":"32",
    "addr:postcode":"k6v 4r9",
    "addr:street":"Wall St",
    "iso:country":"CA",
    "sg:address":"32 Wall St",
    "sg:city":"Brockville",
    "sg:classifiers":[
        {
            "category":"Government",
            "subcategory":"Office",
            "type":"Public Place"
        }
    ],
    "sg:phone":"+1 613 342 3840",
    "sg:postcode":"K6V 4R9",
    "sg:province":"ON",
    "sg:tags":[
        "village"
    ],
    "wof:name":"Leeds & Grenville Adminstrat",
    "wof:placetype":"venue"
},
  "geometry": {"coordinates":[-75.6860046387,44.5916252136],"type":"Point"}
}