{
  "type": "Feature",
  "properties": {
    "iso:country":"CA",
    "sg:address":"1408 Deer Run Rd",
    "sg:city":"Leamington",
    "sg:classifiers":[
        {
            "category":"Organizations",
            "subcategory":"Religious Organization",
            "type":"Services"
        }
    ],
    "sg:phone":"+1 519 326 9734",
    "sg:postcode":"N8H 3V7",
    "sg:province":"ON",
    "sg:tags":[
        "church"
    ],
    "wof:name":"Emmc Church",
    "wof:placetype":"venue"
},
  "geometry": {"coordinates":[-82.549659729,42.0473175049],"type":"Point"}
}