{
  "type": "Feature",
  "properties": {
    "addr:full":"872 Queen St W Toronto ON M6J 1G3",
    "addr:housenumber":"872",
    "addr:postcode":"m6j 1g3",
    "addr:street":"Queen St W",
    "iso:country":"CA",
    "sg:address":"872 Queen St W",
    "sg:city":"Toronto",
    "sg:classifiers":[
        {
            "category":"Restaurant",
            "type":"Food & Drink"
        }
    ],
    "sg:phone":"+1 416 534 3432",
    "sg:postcode":"M6J 1G3",
    "sg:province":"ON",
    "sg:tags":[
        "caterer"
    ],
    "wof:name":"Oyster Boy",
    "wof:placetype":"venue"
},
  "geometry": {"coordinates":[-79.41431427000001,43.6452217102],"type":"Point"}
}