{
  "type": "Feature",
  "properties": {
    "addr:full":"31 Rue Octave Inkerman NB E8P 1B4",
    "addr:housenumber":"31",
    "addr:postcode":"e8p 1b4",
    "addr:street":"Rue Octave Inkerman",
    "iso:country":"CA",
    "sg:address":"31 Rue Octave",
    "sg:city":"Inkerman",
    "sg:classifiers":[
        {
            "category":"Social Services",
            "subcategory":"Adult Care",
            "type":"Services"
        }
    ],
    "sg:phone":"+1 506 336 8257",
    "sg:postcode":"E8P 1B4",
    "sg:province":"NB",
    "sg:tags":[
        "home",
        "residential"
    ],
    "wof:name":"Pavillion Hache",
    "wof:placetype":"venue"
},
  "geometry": {"coordinates":[-64.832077,47.669628],"type":"Point"}
}