{
  "type": "Feature",
  "properties": {
    "addr:full":"45 Hempstead Dr Hamilton ON L8W 2Y6",
    "addr:housenumber":"45",
    "addr:postcode":"l8w 2y6",
    "addr:street":"Hempstead Dr",
    "iso:country":"CA",
    "sg:address":"45 Hempstead Dr",
    "sg:city":"Hamilton",
    "sg:classifiers":[
        {
            "category":"Recreation",
            "type":"Entertainment"
        }
    ],
    "sg:phone":"+1 905 575 5836",
    "sg:postcode":"L8W 2Y6",
    "sg:province":"ON",
    "sg:tags":[
        "martial",
        "arts",
        "instruction"
    ],
    "wof:name":"Kawasaki's Rendoakan Judo Acad",
    "wof:placetype":"venue"
},
  "geometry": {"coordinates":[-79.839493,43.19548],"type":"Point"}
}