{
  "type": "Feature",
  "properties": {
    "iso:country":"CA",
    "sg:city":"Mississauga",
    "sg:classifiers":[
        {
            "category":"Manufacturing",
            "subcategory":"Tools & Machinery",
            "type":"Manufacturing & Wholesale Goods"
        }
    ],
    "sg:phone":"+1 905 820 0272",
    "sg:postcode":"L5L 5T1",
    "sg:province":"ON",
    "sg:tags":[
        "water",
        "cutting",
        "jet"
    ],
    "wof:name":"Waterjet Workshop",
    "wof:placetype":"venue"
},
  "geometry": {"coordinates":[-79.7191390991,43.5300788879],"type":"Point"}
}