{
  "type": "Feature",
  "properties": {
    "addr:full":"9354 49 St NW Edmonton AB T6B 2L7",
    "addr:housenumber":"9354",
    "addr:postcode":"t6b 2l7",
    "addr:street":"49 St Nw",
    "iso:country":"CA",
    "sg:address":"9354 49 St NW",
    "sg:city":"Edmonton",
    "sg:classifiers":[
        {
            "category":"Manufacturing",
            "subcategory":"Metals",
            "type":"Manufacturing & Wholesale Goods"
        }
    ],
    "sg:phone":"+1 780 415 5670",
    "sg:postcode":"T6B 2L7",
    "sg:province":"AB",
    "sg:tags":[
        "steel"
    ],
    "wof:name":"Keller Kustom Metal Ltd",
    "wof:placetype":"venue"
},
  "geometry": {"coordinates":[-113.415092,53.531822],"type":"Point"}
}