{
  "type": "Feature",
  "properties": {
    "iso:country":"CA",
    "sg:address":"Lot 14 Conc 10 Ross Twp",
    "sg:city":"Foresters Falls",
    "sg:classifiers":[
        {
            "category":"Restaurant",
            "type":"Food & Drink"
        }
    ],
    "sg:phone":"+1 613 646 2241",
    "sg:postcode":"K0J 1V0",
    "sg:province":"ON",
    "wof:name":"Rafters Restaurant",
    "wof:placetype":"venue"
},
  "geometry": {"coordinates":[-76.78359985349999,45.6780586243],"type":"Point"}
}