{
  "type": "Feature",
  "properties": {
    "addr:full":"8650 Boul DE LA Rive-Sud Levis QC G6V 9G9",
    "addr:housenumber":"8650",
    "addr:postcode":"g6v 9g9",
    "addr:street":"Boul De La Rive-Sud",
    "iso:country":"CA",
    "sg:address":"8650 Boul DE LA Rive-Sud",
    "sg:city":"Levis",
    "sg:classifiers":[
        {
            "category":"Manufacturing",
            "subcategory":"Rubber & Plastics",
            "type":"Manufacturing & Wholesale Goods"
        }
    ],
    "sg:phone":"+1 418 833 3231",
    "sg:postcode":"G6V 9G9",
    "sg:province":"QC",
    "wof:name":"P H Tech Inc",
    "wof:placetype":"venue"
},
  "geometry": {"coordinates":[-71.129532,46.821106],"type":"Point"}
}