{
  "type": "Feature",
  "properties": {
    "addr:full":"1660 Av DE L'Energie Alma QC G8C 1M6",
    "addr:housenumber":"1660",
    "addr:postcode":"g8c 1m6",
    "addr:street":"Av De L'Energie",
    "iso:country":"CA",
    "sg:address":"1660 Av DE L'Energie",
    "sg:city":"Alma",
    "sg:classifiers":[
        {
            "category":"Manufacturing",
            "subcategory":"Lumber",
            "type":"Manufacturing & Wholesale Goods"
        }
    ],
    "sg:phone":"+1 418 662 8333",
    "sg:postcode":"G8C 1M6",
    "sg:province":"QC",
    "sg:tags":[
        "forester"
    ],
    "wof:name":"Rctf Inc",
    "wof:placetype":"venue"
},
  "geometry": {"coordinates":[-71.66120910639999,48.5256347656],"type":"Point"}
}