{
  "type": "Feature",
  "properties": {
    "addr:full":"5526 118 Ave NW Edmonton AB T5W 1C7",
    "addr:housenumber":"5526",
    "addr:postcode":"t5w 1c7",
    "addr:street":"118 Ave Nw",
    "iso:country":"CA",
    "sg:address":"5526 118 Ave NW",
    "sg:city":"Edmonton",
    "sg:classifiers":[
        {
            "category":"Recreation",
            "type":"Entertainment"
        }
    ],
    "sg:phone":"+1 780 474 0007",
    "sg:postcode":"T5W 1C7",
    "sg:province":"AB",
    "sg:tags":[
        "hall",
        "auditorium"
    ],
    "wof:name":"Highlands Masonic Hall Ltd",
    "wof:placetype":"venue"
},
  "geometry": {"coordinates":[-113.42659,53.570545],"type":"Point"}
}