{
  "type": "Feature",
  "properties": {
    "addr:full":"100 Wingold Ave North York ON M6B 4K7",
    "addr:housenumber":"100",
    "addr:postcode":"m6b 4k7",
    "addr:street":"Wingold Ave",
    "iso:country":"CA",
    "sg:address":"100 Wingold Ave",
    "sg:city":"North York",
    "sg:classifiers":[
        {
            "category":"Home & Garden",
            "subcategory":"Home Furnishings",
            "type":"Retail Goods"
        }
    ],
    "sg:phone":"+1 416 781 4417",
    "sg:postcode":"M6B 4K7",
    "sg:province":"ON",
    "sg:tags":[
        "fashion",
        "fireplace",
        "designer"
    ],
    "wof:name":"Siena Design Inc",
    "wof:placetype":"venue"
},
  "geometry": {"coordinates":[-79.4595718384,43.7023048401],"type":"Point"}
}