{
  "type": "Feature",
  "properties": {
    "addr:full":"321 Rue DE LA Commune O # 200 Montreal QC H2Y 2E1",
    "addr:housenumber":"321",
    "addr:postcode":"h2y 2e1",
    "addr:street":"Rue De La Commune O # 200",
    "iso:country":"CA",
    "sg:address":"321 Rue DE LA Commune O # 200",
    "sg:city":"Montreal",
    "sg:classifiers":[
        {
            "category":"Organizations",
            "subcategory":"Professional Association",
            "type":"Services"
        }
    ],
    "sg:phone":"+1 514 848 9885",
    "sg:postcode":"H2Y 2E1",
    "sg:province":"QC",
    "wof:name":"Centre D'Expertise-Recherche",
    "wof:placetype":"venue"
},
  "geometry": {"coordinates":[-73.55159,45.50856],"type":"Point"}
}