{
  "type": "Feature",
  "properties": {
    "addr:full":"104 Rue DE Martigny O Saint-Jerome QC J7Y 2G1",
    "addr:housenumber":"104",
    "addr:postcode":"j7y 2g1",
    "addr:street":"Rue De Martigny O Saint-Jerome",
    "iso:country":"CA",
    "sg:address":"104 Rue DE Martigny O",
    "sg:city":"Saint-Jerome",
    "sg:classifiers":[
        {
            "category":"Professional",
            "subcategory":"Lawyer & Legal Services",
            "type":"Services"
        }
    ],
    "sg:phone":"+1 450 431 7752",
    "sg:postcode":"J7Y 2G1",
    "sg:province":"QC",
    "sg:tags":[
        "attorney"
    ],
    "wof:name":"Dubreuil, Francois",
    "wof:placetype":"venue"
},
  "geometry": {"coordinates":[-74.010811,45.780064],"type":"Point"}
}