{
  "type": "Feature",
  "properties": {
    "addr:full":"248 18E Av Deux-Montagnes QC J7R 4B1",
    "addr:housenumber":"248",
    "addr:postcode":"j7r 4b1",
    "addr:street":"18E Av Deux-Montagnes",
    "iso:country":"CA",
    "sg:address":"248 18E Av",
    "sg:city":"Deux-Montagnes",
    "sg:classifiers":[
        {
            "category":"Organizations",
            "subcategory":"Religious Organization",
            "type":"Services"
        }
    ],
    "sg:phone":"+1 450 473 9541",
    "sg:postcode":"J7R 4B1",
    "sg:province":"QC",
    "sg:tags":[
        "church"
    ],
    "wof:name":"All Saints Church",
    "wof:placetype":"venue"
},
  "geometry": {"coordinates":[-73.90239,45.537453],"type":"Point"}
}