{
  "type": "Feature",
  "properties": {
    "addr:full":"257 Reserve St Glace Bay NS B1A 4W3",
    "addr:housenumber":"257",
    "addr:postcode":"b1a 4w3",
    "addr:street":"Reserve St",
    "iso:country":"CA",
    "sg:address":"257 Reserve St",
    "sg:city":"Glace Bay",
    "sg:classifiers":[
        {
            "category":"Organizations",
            "subcategory":"Religious Organization",
            "type":"Services"
        }
    ],
    "sg:phone":"+1 902 849 4783",
    "sg:postcode":"B1A 4W3",
    "sg:province":"NS",
    "sg:tags":[
        "church"
    ],
    "wof:name":"Kingdom Hall-Jehovahs Witness",
    "wof:placetype":"venue"
},
  "geometry": {"coordinates":[-59.9873313904,46.1899375916],"type":"Point"}
}