{
  "type": "Feature",
  "properties": {
    "addr:full":"617 Belmont St New Westminster BC V3M 5Z8",
    "addr:housenumber":"617",
    "addr:postcode":"v3m 5z8",
    "addr:street":"Belmont St",
    "iso:country":"CA",
    "sg:address":"617 Belmont St",
    "sg:city":"New Westminster",
    "sg:classifiers":[
        {
            "category":"Government",
            "subcategory":"Post Office",
            "type":"Public Place"
        }
    ],
    "sg:phone":"+1 604 527 7874",
    "sg:postcode":"V3M 5Z8",
    "sg:province":"BC",
    "wof:name":"Belmont Market Postal & Ticket",
    "wof:placetype":"venue"
},
  "geometry": {"coordinates":[-122.919922,49.212326],"type":"Point"}
}