{
  "type": "Feature",
  "properties": {
    "iso:country":"CA",
    "sg:address":"105 Shade St",
    "sg:city":"Cambridge",
    "sg:classifiers":[
        {
            "category":"Personal",
            "type":"Services"
        }
    ],
    "sg:phone":"+1 519 621 9826",
    "sg:postcode":"N1R 4J7",
    "sg:province":"ON",
    "sg:tags":[
        "wear",
        "formal"
    ],
    "wof:name":"Andre's Bridal Ctr",
    "wof:placetype":"venue"
},
  "geometry": {"coordinates":[-80.306709,43.361816],"type":"Point"}
}