{
  "type": "Feature",
  "properties": {
    "addr:full":"13 Owen Dr Etobicoke ON M8W 1W8",
    "addr:housenumber":"13",
    "addr:postcode":"m8w 1w8",
    "addr:street":"Owen Dr",
    "iso:country":"CA",
    "sg:address":"13 Owen Dr",
    "sg:city":"Etobicoke",
    "sg:classifiers":[
        {
            "category":"Building & Trades",
            "subcategory":"Electrical",
            "type":"Services"
        }
    ],
    "sg:phone":"+1 416 259 8071",
    "sg:postcode":"M8W 1W8",
    "sg:province":"ON",
    "sg:tags":[
        "electric",
        "contractor"
    ],
    "wof:name":"Brown's Line Electrical & Mech",
    "wof:placetype":"venue"
},
  "geometry": {"coordinates":[-79.5436706543,43.5970878601],"type":"Point"}
}