{
  "type": "Feature",
  "properties": {
    "addr:full":"821 Av DE L'Industrie Amos QC J9T 4L6",
    "addr:postcode":"j9t 4l6",
    "addr:street":"821 Av De L'Industrie",
    "iso:country":"CA",
    "sg:address":"821 Av DE L'Industrie",
    "sg:city":"Amos",
    "sg:classifiers":[
        {
            "category":"Manufacturing",
            "subcategory":"Signs",
            "type":"Manufacturing & Wholesale Goods"
        }
    ],
    "sg:phone":"+1 819 727 9818",
    "sg:postcode":"J9T 4L6",
    "sg:province":"QC",
    "wof:name":"Zip Lignes",
    "wof:placetype":"venue"
},
  "geometry": {"coordinates":[-78.1251525879,48.5630111694],"type":"Point"}
}