{
  "type": "Feature",
  "properties": {
    "addr:full":"25 Rue Du College L'Assomption QC J5W 1L8",
    "addr:housenumber":"25",
    "addr:postcode":"j5w 1l8",
    "addr:street":"Rue Du College",
    "iso:country":"CA",
    "sg:address":"25 Rue Du College",
    "sg:city":"L'Assomption",
    "sg:classifiers":[
        {
            "category":"Taxi",
            "type":"Transportation"
        }
    ],
    "sg:phone":"+1 450 589 0971",
    "sg:postcode":"J5W 1L8",
    "sg:province":"QC",
    "sg:tags":[
        "taxicab"
    ],
    "wof:name":"Taxi Ville DE L'Assomption",
    "wof:placetype":"venue"
},
  "geometry": {"coordinates":[-73.4216995239,45.8310775757],"type":"Point"}
}