{
  "type": "Feature",
  "properties": {
    "addr:full":"1387 Grand Marais Rd W Windsor ON N9E 1E2",
    "addr:housenumber":"1387",
    "addr:postcode":"n9e 1e2",
    "addr:street":"Grand Marais Rd W",
    "iso:country":"CA",
    "sg:address":"1387 Grand Marais Rd W",
    "sg:city":"Windsor",
    "sg:classifiers":[
        {
            "category":"Food & Beverages",
            "subcategory":"Bakery",
            "type":"Retail Goods"
        }
    ],
    "sg:phone":"+1 519 969 7080",
    "sg:postcode":"N9E 1E2",
    "sg:province":"ON",
    "sg:tags":[
        "baker"
    ],
    "wof:name":"Deb's Place",
    "wof:placetype":"venue"
},
  "geometry": {"coordinates":[-83.027237,42.267353],"type":"Point"}
}