{
  "type": "Feature",
  "properties": {
    "addr:full":"1033 Pine St London ON N5Z 2J7",
    "addr:housenumber":"1033",
    "addr:postcode":"n5z 2j7",
    "addr:street":"Pine St",
    "iso:country":"CA",
    "sg:address":"1033 Pine St",
    "sg:city":"London",
    "sg:classifiers":[
        {
            "category":"Manufacturing",
            "subcategory":"Metals",
            "type":"Manufacturing & Wholesale Goods"
        }
    ],
    "sg:phone":"+1 519 451 0344",
    "sg:postcode":"N5Z 2J7",
    "sg:province":"ON",
    "sg:tags":[
        "welding"
    ],
    "wof:name":"S & S Steel Product Ltd",
    "wof:placetype":"venue"
},
  "geometry": {"coordinates":[-81.213066,42.984879],"type":"Point"}
}