{
  "type": "Feature",
  "properties": {
    "addr:full":"2311 2nd Ave Fort Macleod AB T0L 0Z0",
    "addr:housenumber":"2311",
    "addr:postcode":"t0l 0z0",
    "addr:street":"2Nd Ave Fort",
    "iso:country":"CA",
    "sg:address":"2311 2nd Ave",
    "sg:city":"Fort Macleod",
    "sg:classifiers":[
        {
            "category":"Real Estate",
            "subcategory":"Real Estate Agent",
            "type":"Services"
        }
    ],
    "sg:phone":"+1 403 553 3576",
    "sg:postcode":"T0L 0Z0",
    "sg:province":"AB",
    "wof:name":"Royal Le Page South Country",
    "wof:placetype":"venue"
},
  "geometry": {"coordinates":[-113.408836365,49.7248306274],"type":"Point"}
}