{
  "type": "Feature",
  "properties": {
    "addr:full":"808 York Rd Guelph ON N1E 6A6",
    "addr:housenumber":"808",
    "addr:postcode":"n1e 6a6",
    "addr:street":"York Rd",
    "iso:country":"CA",
    "sg:address":"808 York Rd",
    "sg:city":"Guelph",
    "sg:classifiers":[
        {
            "category":"Shopping",
            "subcategory":"Used Merchandise",
            "type":"Retail Goods"
        }
    ],
    "sg:phone":"+1 519 837 0980",
    "sg:postcode":"N1E 6A6",
    "sg:province":"ON",
    "sg:tags":[
        "furniture"
    ],
    "wof:name":"Gramma's Attic",
    "wof:placetype":"venue"
},
  "geometry": {"coordinates":[-80.2139511108,43.5593452454],"type":"Point"}
}