{
  "type": "Feature",
  "properties": {
    "addr:full":"217 Jessop Ave Saskatoon SK S7N 1Y3",
    "addr:housenumber":"217",
    "addr:postcode":"s7n 1y3",
    "addr:street":"Jessop Ave",
    "iso:country":"CA",
    "sg:address":"217 Jessop Ave",
    "sg:city":"Saskatoon",
    "sg:classifiers":[
        {
            "category":"Manufacturing",
            "subcategory":"Printing",
            "type":"Manufacturing & Wholesale Goods"
        }
    ],
    "sg:phone":"+1 306 955 3373",
    "sg:postcode":"S7N 1Y3",
    "sg:province":"SK",
    "sg:tags":[
        "printer"
    ],
    "wof:name":"Globe Printers",
    "wof:placetype":"venue"
},
  "geometry": {"coordinates":[-106.593727,52.128685],"type":"Point"}
}