{
  "type": "Feature",
  "properties": {
    "addr:full":"11 9 St Hearst ON P0L 1N0",
    "addr:postcode":"p0l 1n0",
    "addr:street":"11 9",
    "iso:country":"CA",
    "sg:address":"11 9 St",
    "sg:city":"Hearst",
    "sg:classifiers":[
        {
            "category":"Health Services",
            "subcategory":"Chiropractor",
            "type":"Services"
        }
    ],
    "sg:phone":"+1 705 362 8255",
    "sg:postcode":"P0L 1N0",
    "sg:province":"ON",
    "wof:name":"Oldaker, Ken DC",
    "wof:placetype":"venue"
},
  "geometry": {"coordinates":[-83.6648635864,49.6887512207],"type":"Point"}
}