{
  "type": "Feature",
  "properties": {
    "addr:full":"731 Broadview Ave Toronto ON M4K 2P6",
    "addr:housenumber":"731",
    "addr:postcode":"m4k 2p6",
    "addr:street":"Broadview Ave",
    "iso:country":"CA",
    "sg:address":"731 Broadview Ave",
    "sg:city":"Toronto",
    "sg:classifiers":[
        {
            "category":"Food & Beverages",
            "subcategory":"Bakery",
            "type":"Retail Goods"
        }
    ],
    "sg:phone":"+1 416 469 0712",
    "sg:postcode":"M4K 2P6",
    "sg:province":"ON",
    "sg:tags":[
        "tea",
        "coffee",
        "doughnut"
    ],
    "wof:name":"Coffee Time Donuts",
    "wof:placetype":"venue"
},
  "geometry": {"coordinates":[-79.358047,43.675533],"type":"Point"}
}