{
  "type": "Feature",
  "properties": {
    "addr:full":"61 Robinson St Simcoe ON N3Y 1W5",
    "addr:housenumber":"61",
    "addr:postcode":"n3y 1w5",
    "addr:street":"Robinson St",
    "iso:country":"CA",
    "sg:address":"61 Robinson St",
    "sg:city":"Simcoe",
    "sg:classifiers":[
        {
            "category":"Banks & Credit Unions",
            "subcategory":"Investment Brokerage",
            "type":"Services"
        }
    ],
    "sg:phone":"+1 519 426 3416",
    "sg:postcode":"N3Y 1W5",
    "sg:province":"ON",
    "wof:name":"Rbc Dominion Securities Inc",
    "wof:placetype":"venue"
},
  "geometry": {"coordinates":[-80.305969,42.837063],"type":"Point"}
}