{
  "type": "Feature",
  "properties": {
    "iso:country":"CA",
    "sg:address":"11 Lowrey Ave S",
    "sg:city":"Cambridge",
    "sg:classifiers":[
        {
            "category":"Personal",
            "type":"Services"
        }
    ],
    "sg:phone":"+1 519 740 8903",
    "sg:postcode":"N1R 4Z2",
    "sg:province":"ON",
    "sg:tags":[
        "therapist",
        "massage"
    ],
    "wof:name":"Tree of Life Massage Therapy",
    "wof:placetype":"venue"
},
  "geometry": {"coordinates":[-80.2996292114,43.3551559448],"type":"Point"}
}