{
  "type": "Feature",
  "properties": {
    "addr:full":"313 Husky Ave Air Ronge SK S0J 3G0",
    "addr:housenumber":"313",
    "addr:postcode":"s0j 3g0",
    "addr:street":"Husky Ave",
    "iso:country":"CA",
    "sg:address":"313 Husky Ave",
    "sg:city":"Air Ronge",
    "sg:classifiers":[
        {
            "category":"Retail",
            "subcategory":"Auto Repair",
            "type":"Services"
        }
    ],
    "sg:phone":"+1 306 425 3996",
    "sg:postcode":"S0J 3G0",
    "sg:province":"SK",
    "sg:tags":[
        "truck"
    ],
    "wof:name":"Nash Bay Equipment Ltd",
    "wof:placetype":"venue"
},
  "geometry": {"coordinates":[-105.318794,55.082458],"type":"Point"}
}