{
  "type": "Feature",
  "properties": {
    "addr:full":"220 Grande Allee E # 100 Quebec QC G1R 2J1",
    "addr:housenumber":"220",
    "addr:postcode":"g1r 2j1",
    "addr:street":"Grande Allee E # 100",
    "iso:country":"CA",
    "sg:address":"220 Grande Allee E # 100",
    "sg:city":"Quebec",
    "sg:classifiers":[
        {
            "category":"Professional",
            "subcategory":"Lawyer & Legal Services",
            "type":"Services"
        }
    ],
    "sg:phone":"+1 418 640 1773",
    "sg:postcode":"G1R 2J1",
    "sg:province":"QC",
    "sg:tags":[
        "attorney"
    ],
    "wof:name":"Seney, Sylvain",
    "wof:placetype":"venue"
},
  "geometry": {"coordinates":[-71.221222,46.803799],"type":"Point"}
}