{
  "type": "Feature",
  "properties": {
    "addr:full":"Surrey BC V4N 4C4",
    "addr:postcode":"v4n 4c4",
    "iso:country":"CA",
    "sg:city":"Surrey",
    "sg:classifiers":[
        {
            "category":"Building & Trades",
            "subcategory":"Construction",
            "type":"Services"
        }
    ],
    "sg:phone":"+1 604 888 8818",
    "sg:postcode":"V4N 4C4",
    "sg:province":"BC",
    "sg:tags":[
        "grouting",
        "contractor"
    ],
    "wof:name":"Dywidag Systems Intl Canada",
    "wof:placetype":"venue"
},
  "geometry": {"coordinates":[-122.68411999999999,49.177151],"type":"Point"}
}