{
  "type": "Feature",
  "properties": {
    "addr:full":"Blainville QC J7C 2K8",
    "addr:postcode":"j7c 2k8",
    "iso:country":"CA",
    "sg:city":"Blainville",
    "sg:classifiers":[
        {
            "category":"Autos & Motor Vehicles",
            "subcategory":"Motorcycle Sales",
            "type":"Retail Goods"
        }
    ],
    "sg:phone":"+1 450 434 6154",
    "sg:postcode":"J7C 2K8",
    "sg:province":"QC",
    "sg:tags":[
        "dealer",
        "boat"
    ],
    "wof:name":"Christian Laurin Sports Inc",
    "wof:placetype":"venue"
},
  "geometry": {"coordinates":[-73.87316131590001,45.6688842773],"type":"Point"}
}