{
  "type": "Feature",
  "properties": {
    "addr:full":"11461 95 St NW Edmonton AB T5G 1L3",
    "addr:housenumber":"11461",
    "addr:postcode":"t5g 1l3",
    "addr:street":"95 St Nw",
    "iso:country":"CA",
    "sg:address":"11461 95 St NW",
    "sg:city":"Edmonton",
    "sg:classifiers":[
        {
            "category":"Organizations",
            "subcategory":"Religious Organization",
            "type":"Services"
        }
    ],
    "sg:phone":"+1 780 477 3341",
    "sg:postcode":"T5G 1L3",
    "sg:province":"AB",
    "sg:tags":[
        "church"
    ],
    "wof:name":"Bethel Gospel Chapel",
    "wof:placetype":"venue"
},
  "geometry": {"coordinates":[-113.486946106,53.565158844],"type":"Point"}
}