{
  "type": "Feature",
  "properties": {
    "addr:full":"1898 Baseline Rd W Bowmanville ON L1C 3K3",
    "addr:housenumber":"1898",
    "addr:postcode":"l1c 3k3",
    "addr:street":"Baseline Rd W",
    "iso:country":"CA",
    "sg:address":"1898 Baseline Rd W",
    "sg:city":"Bowmanville",
    "sg:classifiers":[
        {
            "category":"Autos & Motor Vehicles",
            "subcategory":"Motorcycle Sales",
            "type":"Retail Goods"
        }
    ],
    "sg:phone":"+1 905 433 0042",
    "sg:postcode":"L1C 3K3",
    "sg:province":"ON",
    "sg:tags":[
        "all",
        "terrain",
        "snowmobile"
    ],
    "wof:name":"Used Parts Plus",
    "wof:placetype":"venue"
},
  "geometry": {"coordinates":[-78.69568599999999,43.896679],"type":"Point"}
}