{
  "type": "Feature",
  "properties": {
    "addr:full":"37 Rue Des Marianistes Saint-Anselme QC G0R 2N0",
    "addr:housenumber":"37",
    "addr:postcode":"g0r 2n0",
    "addr:street":"Rue Des Marianistes",
    "iso:country":"CA",
    "sg:address":"37 Rue Des Marianistes",
    "sg:city":"Saint-Anselme",
    "sg:classifiers":[
        {
            "category":"Professional",
            "subcategory":"Business Services",
            "type":"Services"
        }
    ],
    "sg:phone":"+1 418 885 8185",
    "sg:postcode":"G0R 2N0",
    "sg:province":"QC",
    "sg:tags":[
        "trade",
        "exposition",
        "fair",
        "show"
    ],
    "wof:name":"Expo Bbq",
    "wof:placetype":"venue"
},
  "geometry": {"coordinates":[-70.9640426636,46.6291122437],"type":"Point"}
}