{
  "type": "Feature",
  "properties": {
    "iso:country":"CA",
    "sg:address":"2120 Oak Bay Ave",
    "sg:city":"Victoria",
    "sg:classifiers":[
        {
            "category":"Personal",
            "subcategory":"Beauty Salon",
            "type":"Services"
        }
    ],
    "sg:phone":"+1 250 598 2922",
    "sg:postcode":"V8R 1E7",
    "sg:province":"BC",
    "wof:name":"Lorraine's Salon",
    "wof:placetype":"venue"
},
  "geometry": {"coordinates":[-123.322669983,48.4264183044],"type":"Point"}
}