{
  "type": "Feature",
  "properties": {
    "iso:country":"CA",
    "sg:address":"2101 43 St",
    "sg:city":"Vernon",
    "sg:classifiers":[
        {
            "category":"Freight",
            "type":"Transportation"
        }
    ],
    "sg:phone":"+1 250 542 4254",
    "sg:postcode":"V1T 6K7",
    "sg:province":"BC",
    "sg:tags":[
        "mover"
    ],
    "wof:name":"Cidel Moving & Storage Ltd",
    "wof:placetype":"venue"
},
  "geometry": {"coordinates":[-119.29818725600001,50.2564277649],"type":"Point"}
}