{
  "type": "Feature",
  "properties": {
    "addr:full":"200 Barclay Parade SW # 149 Calgary AB T2P 4R5",
    "addr:housenumber":"200",
    "addr:postcode":"t2p 4r5",
    "addr:street":"Barclay Parade Sw # 149",
    "iso:country":"CA",
    "sg:address":"200 Barclay Parade SW # 149",
    "sg:city":"Calgary",
    "sg:classifiers":[
        {
            "category":"Shopping",
            "subcategory":"Gifts & Souvenirs",
            "type":"Retail Goods"
        }
    ],
    "sg:phone":"+1 403 261 1845",
    "sg:postcode":"T2P 4R5",
    "sg:province":"AB",
    "sg:tags":[
        "shop"
    ],
    "wof:name":"Son of the Pharaoh",
    "wof:placetype":"venue"
},
  "geometry": {"coordinates":[-114.06905399999999,51.052784],"type":"Point"}
}