{
  "type": "Feature",
  "properties": {
    "addr:full":"6450 Young St Halifax NS B3L 2A3",
    "addr:housenumber":"6450",
    "addr:postcode":"b3l 2a3",
    "addr:street":"Young St",
    "iso:country":"CA",
    "sg:address":"6450 Young St",
    "sg:city":"Halifax",
    "sg:classifiers":[
        {
            "category":"Professional",
            "subcategory":"Art Services",
            "type":"Services"
        }
    ],
    "sg:phone":"+1 902 455 0133",
    "sg:postcode":"B3L 2A3",
    "sg:province":"NS",
    "sg:tags":[
        "graphic",
        "designer"
    ],
    "wof:name":"Semaphor Design CO",
    "wof:placetype":"venue"
},
  "geometry": {"coordinates":[-63.6104125977,44.6535301208],"type":"Point"}
}