{
  "type": "Feature",
  "properties": {
    "addr:full":"Welland ON L3B 3W3",
    "addr:postcode":"l3b 3w3",
    "iso:country":"CA",
    "sg:city":"Welland",
    "sg:classifiers":[
        {
            "category":"Organizations",
            "subcategory":"Professional Association",
            "type":"Services"
        }
    ],
    "sg:phone":"+1 905 732 7515",
    "sg:postcode":"L3B 3W3",
    "sg:province":"ON",
    "wof:name":"Welland Pelham Chamber of Comm",
    "wof:placetype":"venue"
},
  "geometry": {"coordinates":[-79.249763,42.99197],"type":"Point"}
}