{
  "type": "Feature",
  "properties": {
    "iso:country":"CA",
    "sg:address":"680 Old Harwood Ave",
    "sg:city":"Ajax",
    "sg:classifiers":[
        {
            "category":"Personal",
            "subcategory":"Beauty Salon",
            "type":"Services"
        }
    ],
    "sg:phone":"+1 416 703 6489",
    "sg:postcode":"L1T 3M2",
    "sg:province":"ON",
    "sg:tags":[
        "school"
    ],
    "wof:name":"Mistique Beauty Clinic & Spa",
    "wof:placetype":"venue"
},
  "geometry": {"coordinates":[-79.0312347412,43.873298645],"type":"Point"}
}