{
  "type": "Feature",
  "properties": {
    "addr:full":"341 Montee Industrielle-Et-Com Rimouski QC G5M 1A7",
    "addr:housenumber":"341",
    "addr:postcode":"g5m 1a7",
    "addr:street":"Montee Industrielle-Et-Com",
    "iso:country":"CA",
    "sg:address":"341 Montee Industrielle-Et-Com",
    "sg:city":"Rimouski",
    "sg:classifiers":[
        {
            "category":"Home & Garden",
            "subcategory":"Building Materials",
            "type":"Retail Goods"
        }
    ],
    "sg:phone":"+1 418 724 5990",
    "sg:postcode":"G5M 1A7",
    "sg:province":"QC",
    "sg:tags":[
        "door"
    ],
    "wof:name":"Centre DE Portes & Fenetres",
    "wof:placetype":"venue"
},
  "geometry": {"coordinates":[-68.50057200000001,48.460007],"type":"Point"}
}