{
  "type": "Feature",
  "properties": {
    "addr:full":"329 Ch Des Iles Levis QC G6V 7M5",
    "addr:housenumber":"329",
    "addr:postcode":"g6v 7m5",
    "addr:street":"Ch Des Iles",
    "iso:country":"CA",
    "sg:address":"329 Ch Des Iles",
    "sg:city":"Levis",
    "sg:classifiers":[
        {
            "category":"Retail",
            "subcategory":"Repair Shop",
            "type":"Services"
        }
    ],
    "sg:phone":"+1 418 837 4736",
    "sg:postcode":"G6V 7M5",
    "sg:province":"QC",
    "sg:tags":[
        "sharpening",
        "saw"
    ],
    "wof:name":"Scies & Outils Technov",
    "wof:placetype":"venue"
},
  "geometry": {"coordinates":[-71.171127,46.748245],"type":"Point"}
}