{
  "type": "Feature",
  "properties": {
    "addr:full":"7983 Lickman Rd Chilliwack BC V2R 3Z9",
    "addr:housenumber":"7983",
    "addr:postcode":"v2r 3z9",
    "addr:street":"Lickman Rd",
    "iso:country":"CA",
    "sg:address":"7983 Lickman Rd",
    "sg:city":"Chilliwack",
    "sg:classifiers":[
        {
            "category":"Retail",
            "subcategory":"Car Wash",
            "type":"Services"
        }
    ],
    "sg:phone":"+1 604 702 0442",
    "sg:postcode":"V2R 3Z9",
    "sg:province":"BC",
    "sg:tags":[
        "truck",
        "cleaning"
    ],
    "wof:name":"Pro-Shine Truck Care Ltd",
    "wof:placetype":"venue"
},
  "geometry": {"coordinates":[-122.007156372,49.1475830078],"type":"Point"}
}