{
  "type": "Feature",
  "properties": {
    "addr:full":"817 Prospect St Fredericton NB E3B 5Y4",
    "addr:housenumber":"817",
    "addr:postcode":"e3b 5y4",
    "addr:street":"Prospect St",
    "iso:country":"CA",
    "sg:address":"817 Prospect St",
    "sg:city":"Fredericton",
    "sg:classifiers":[
        {
            "category":"Retail",
            "subcategory":"Auto Rental",
            "type":"Services"
        }
    ],
    "sg:phone":"+1 506 453 1700",
    "sg:postcode":"E3B 5Y4",
    "sg:province":"NB",
    "sg:tags":[
        "renting",
        "automobile"
    ],
    "wof:name":"National Car & Truck Rental",
    "wof:placetype":"venue"
},
  "geometry": {"coordinates":[-66.67850494379999,45.9464492798],"type":"Point"}
}