{
  "type": "Feature",
  "properties": {
    "addr:full":"Toronto ON M5E 1G4",
    "addr:postcode":"m5e 1g4",
    "iso:country":"CA",
    "sg:city":"Toronto",
    "sg:classifiers":[
        {
            "category":"Professional",
            "subcategory":"Art Services",
            "type":"Services"
        }
    ],
    "sg:phone":"+1 416 361 0195",
    "sg:postcode":"M5E 1G4",
    "sg:province":"ON",
    "sg:tags":[
        "graphic",
        "designer"
    ],
    "wof:name":"Design Direct",
    "wof:placetype":"venue"
},
  "geometry": {"coordinates":[-79.3768615723,43.6471099854],"type":"Point"}
}