{
  "type": "Feature",
  "properties": {
    "addr:full":"112 King St Palmerston ON N0G 2P0",
    "addr:housenumber":"112",
    "addr:postcode":"n0g 2p0",
    "addr:street":"King St",
    "iso:country":"CA",
    "sg:address":"112 King St",
    "sg:city":"Palmerston",
    "sg:classifiers":[
        {
            "category":"Travel",
            "subcategory":"Hotels & Motels",
            "type":"Entertainment"
        }
    ],
    "sg:phone":"+1 519 343 3838",
    "sg:postcode":"N0G 2P0",
    "sg:province":"ON",
    "wof:name":"King Hotel & Restaurant",
    "wof:placetype":"venue"
},
  "geometry": {"coordinates":[-80.857941,43.832439],"type":"Point"}
}