{
  "type": "Feature",
  "properties": {
    "addr:full":"2054 Rue Saint-Hubert Jonquiere QC G7X 5R4",
    "addr:housenumber":"2054",
    "addr:postcode":"g7x 5r4",
    "addr:street":"Rue Saint-Hubert",
    "iso:country":"CA",
    "sg:address":"2054 Rue Saint-Hubert",
    "sg:city":"Jonquiere",
    "sg:classifiers":[
        {
            "category":"Home & Garden",
            "subcategory":"Building Materials",
            "type":"Retail Goods"
        }
    ],
    "sg:phone":"+1 418 695 9898",
    "sg:postcode":"G7X 5R4",
    "sg:province":"QC",
    "sg:tags":[
        "windows",
        "plate",
        "window"
    ],
    "wof:name":"Vitrerie Abg Inc",
    "wof:placetype":"venue"
},
  "geometry": {"coordinates":[-71.24216461180001,48.4214019775],"type":"Point"}
}