{
  "type": "Feature",
  "properties": {
    "addr:full":"757 Lake Bonavista Dr SE Calgary AB T2J 0N2",
    "addr:housenumber":"757",
    "addr:postcode":"t2j 0n2",
    "addr:street":"Lake Bonavista Dr Se",
    "iso:country":"CA",
    "sg:address":"757 Lake Bonavista Dr SE",
    "sg:city":"Calgary",
    "sg:classifiers":[
        {
            "category":"Organizations",
            "subcategory":"Professional Association",
            "type":"Services"
        }
    ],
    "sg:phone":"+1 403 271 3333",
    "sg:postcode":"T2J 0N2",
    "sg:province":"AB",
    "wof:name":"Lake Bonavista Hm Owners Assn",
    "wof:placetype":"venue"
},
  "geometry": {"coordinates":[-114.048096,50.943596],"type":"Point"}
}