{
  "type": "Feature",
  "properties": {
    "addr:full":"738 Arlington Park Pl Kingston ON K7M 8H9",
    "addr:housenumber":"738",
    "addr:postcode":"k7m 8h9",
    "addr:street":"Arlington Park Pl",
    "iso:country":"CA",
    "sg:address":"738 Arlington Park Pl",
    "sg:city":"Kingston",
    "sg:classifiers":[
        {
            "category":"Professional",
            "subcategory":"Lawyer & Legal Services",
            "type":"Services"
        }
    ],
    "sg:phone":"+1 613 389 4404",
    "sg:postcode":"K7M 8H9",
    "sg:province":"ON",
    "sg:tags":[
        "attorney"
    ],
    "wof:name":"Wilson & Wilson",
    "wof:placetype":"venue"
},
  "geometry": {"coordinates":[-76.571594,44.249268],"type":"Point"}
}