{
  "type": "Feature",
  "properties": {
    "addr:full":"77 E Nelson Lake Cowichan BC V0R 2G0",
    "addr:housenumber":"77",
    "addr:postcode":"v0r 2g0",
    "addr:street":"E Nelson",
    "iso:country":"CA",
    "sg:address":"77 E Nelson",
    "sg:city":"Lake Cowichan",
    "sg:classifiers":[
        {
            "category":"Travel",
            "subcategory":"Hotels & Motels",
            "type":"Entertainment"
        }
    ],
    "sg:phone":"+1 250 749 3524",
    "sg:postcode":"V0R 2G0",
    "sg:province":"BC",
    "sg:tags":[
        "resort"
    ],
    "wof:name":"Pallies Place-Motel",
    "wof:placetype":"venue"
},
  "geometry": {"coordinates":[-124.051643,48.823936],"type":"Point"}
}