{
  "type": "Feature",
  "properties": {
    "iso:country":"CA",
    "sg:address":"809 2nd St E",
    "sg:city":"Cornwall",
    "sg:classifiers":[
        {
            "category":"Health Services",
            "subcategory":"Doctor",
            "type":"Services"
        }
    ],
    "sg:phone":"+1 613 938 8484",
    "sg:postcode":"K6H 2A4",
    "sg:province":"ON",
    "sg:tags":[
        "dentist"
    ],
    "wof:name":"Fournier, Simon DDS",
    "wof:placetype":"venue"
},
  "geometry": {"coordinates":[-74.71275300000001,45.022705],"type":"Point"}
}