{
  "type": "Feature",
  "properties": {
    "addr:full":"55 Albert St Stratford ON N5A 3K2",
    "addr:housenumber":"55",
    "addr:postcode":"n5a 3k2",
    "addr:street":"Albert St",
    "iso:country":"CA",
    "sg:address":"55 Albert St",
    "sg:city":"Stratford",
    "sg:classifiers":[
        {
            "category":"Food & Beverages",
            "subcategory":"Candy",
            "type":"Retail Goods"
        }
    ],
    "sg:phone":"+1 519 271 6910",
    "sg:postcode":"N5A 3K2",
    "sg:province":"ON",
    "sg:tags":[
        "confectionery"
    ],
    "wof:name":"Rheo Thompson Candies",
    "wof:placetype":"venue"
},
  "geometry": {"coordinates":[-80.9808959961,43.3703842163],"type":"Point"}
}