{
  "type": "Feature",
  "properties": {
    "addr:full":"465 Rue Saint-Jean Montreal QC H2Y 2R6",
    "addr:housenumber":"465",
    "addr:postcode":"h2y 2r6",
    "addr:street":"Rue Saint-Jean",
    "iso:country":"CA",
    "sg:address":"465 Rue Saint-Jean",
    "sg:city":"Montreal",
    "sg:classifiers":[
        {
            "category":"Professional",
            "subcategory":"Computer Services",
            "type":"Services"
        }
    ],
    "sg:phone":"+1 514 982 0678",
    "sg:postcode":"H2Y 2R6",
    "sg:province":"QC",
    "sg:tags":[
        "internet"
    ],
    "wof:name":"Secure Ops Inc",
    "wof:placetype":"venue"
},
  "geometry": {"coordinates":[-73.557259,45.502762],"type":"Point"}
}