{
  "type": "Feature",
  "properties": {
    "iso:country":"CA",
    "sg:address":"5675 Av Christophe-Colomb",
    "sg:city":"Montreal",
    "sg:classifiers":[
        {
            "category":"Manufacturing",
            "subcategory":"Apparel",
            "type":"Manufacturing & Wholesale Goods"
        }
    ],
    "sg:phone":"+1 514 271 5107",
    "sg:postcode":"H2S 2E8",
    "sg:province":"QC",
    "sg:tags":[
        "clothing"
    ],
    "wof:name":"Town & Country Uniformes Inc",
    "wof:placetype":"venue"
},
  "geometry": {"coordinates":[-73.592896,45.534302],"type":"Point"}
}