{
  "type": "Feature",
  "properties": {
    "iso:country":"CA",
    "sg:address":"40 Cokato Rd",
    "sg:city":"Fernie",
    "sg:classifiers":[
        {
            "category":"Building & Trades",
            "subcategory":"Construction",
            "type":"Services"
        }
    ],
    "sg:phone":"+1 250 423 6613",
    "sg:postcode":"V0B 1M4",
    "sg:province":"BC",
    "sg:tags":[
        "excavating",
        "contractor"
    ],
    "wof:name":"Cameron Enterprises",
    "wof:placetype":"venue"
},
  "geometry": {"coordinates":[-115.065788269,49.4912490845],"type":"Point"}
}