{
  "type": "Feature",
  "properties": {
    "addr:full":"29 Boul Saint-Francis Chateauguay QC J6J 1Y2",
    "addr:housenumber":"29",
    "addr:postcode":"j6j 1y2",
    "addr:street":"Boul Saint-Francis",
    "iso:country":"CA",
    "sg:address":"29 Boul Saint-Francis",
    "sg:city":"Chateauguay",
    "sg:classifiers":[
        {
            "category":"Communications",
            "subcategory":"Television Station",
            "type":"Services"
        }
    ],
    "sg:phone":"+1 450 692 3398",
    "sg:postcode":"J6J 1Y2",
    "sg:province":"QC",
    "sg:tags":[
        "broadcasting",
        "co"
    ],
    "wof:name":"Ctgc Tv",
    "wof:placetype":"venue"
},
  "geometry": {"coordinates":[-73.747253,45.369015],"type":"Point"}
}