{
  "type": "Feature",
  "properties": {
    "addr:full":"Pickering ON L1W 3R2",
    "addr:postcode":"l1w 3r2",
    "iso:country":"CA",
    "sg:city":"Pickering",
    "sg:classifiers":[
        {
            "category":"Organizations",
            "subcategory":"Professional Association",
            "type":"Services"
        }
    ],
    "sg:phone":"+1 905 831 1757",
    "sg:postcode":"L1W 3R2",
    "sg:province":"ON",
    "wof:name":"Ontario Curling Assn",
    "wof:placetype":"venue"
},
  "geometry": {"coordinates":[-79.0816040039,43.830078125],"type":"Point"}
}