{
  "type": "Feature",
  "properties": {
    "addr:full":"219 University Ave Charlottetown PE C1A 4L6",
    "addr:housenumber":"219",
    "addr:postcode":"c1a 4l6",
    "addr:street":"University Ave",
    "iso:country":"CA",
    "sg:address":"219 University Ave",
    "sg:city":"Charlottetown",
    "sg:classifiers":[
        {
            "category":"Real Estate",
            "subcategory":"Real Estate Agent",
            "type":"Services"
        }
    ],
    "sg:phone":"+1 902 566 9943",
    "sg:postcode":"C1A 4L6",
    "sg:province":"PE",
    "wof:name":"Spud Isle Realty Inc",
    "wof:placetype":"venue"
},
  "geometry": {"coordinates":[-63.1300125122,46.2381324768],"type":"Point"}
}