{
  "type": "Feature",
  "properties": {
    "iso:country":"CA",
    "sg:address":"2131 Broad St",
    "sg:city":"Regina",
    "sg:classifiers":[
        {
            "category":"Real Estate",
            "subcategory":"Real Estate Operator",
            "type":"Services"
        }
    ],
    "sg:phone":"+1 306 522 3766",
    "sg:postcode":"S4P 1Y6",
    "sg:province":"SK",
    "sg:tags":[
        "apartment"
    ],
    "wof:name":"Centre Point Plaza",
    "wof:placetype":"venue"
},
  "geometry": {"coordinates":[-104.60621643099999,50.4449729919],"type":"Point"}
}