{
  "type": "Feature",
  "properties": {
    "addr:full":"Toronto ON M4P 1E4",
    "addr:postcode":"m4p 1e4",
    "iso:country":"CA",
    "sg:city":"Toronto",
    "sg:classifiers":[
        {
            "category":"Personal",
            "type":"Services"
        }
    ],
    "sg:phone":"+1 416 322 6506",
    "sg:postcode":"M4P 1E4",
    "sg:province":"ON",
    "sg:tags":[
        "therapist",
        "massage"
    ],
    "wof:name":"Coulter Clinic",
    "wof:placetype":"venue"
},
  "geometry": {"coordinates":[-79.39866600000001,43.707237],"type":"Point"}
}