{
  "type": "Feature",
  "properties": {
    "addr:full":"245 Hardy Rd Brantford ON N3T 5L8",
    "addr:housenumber":"245",
    "addr:postcode":"n3t 5l8",
    "addr:street":"Hardy Rd",
    "iso:country":"CA",
    "sg:address":"245 Hardy Rd",
    "sg:city":"Brantford",
    "sg:classifiers":[
        {
            "category":"Building & Trades",
            "subcategory":"Construction",
            "type":"Services"
        }
    ],
    "sg:phone":"+1 519 753 4612",
    "sg:postcode":"N3T 5L8",
    "sg:province":"ON",
    "sg:tags":[
        "home",
        "improvement",
        "maker",
        "cabinet"
    ],
    "wof:name":"C & J Custom Carpentry",
    "wof:placetype":"venue"
},
  "geometry": {"coordinates":[-80.304276,43.163139],"type":"Point"}
}