{
  "type": "Feature",
  "properties": {
    "addr:full":"Airdrie AB T4B 2B8",
    "addr:postcode":"t4b 2b8",
    "iso:country":"CA",
    "sg:city":"Airdrie",
    "sg:classifiers":[
        {
            "category":"Personal",
            "subcategory":"Beauty Salon",
            "type":"Services"
        }
    ],
    "sg:phone":"+1 403 948 0642",
    "sg:postcode":"T4B 2B8",
    "sg:province":"AB",
    "wof:name":"Great Clips For Hair",
    "wof:placetype":"venue"
},
  "geometry": {"coordinates":[-114.01348900000001,51.28698],"type":"Point"}
}