{
  "type": "Feature",
  "properties": {
    "addr:full":"427 Williams Ave Killarney MB R0K 1G0",
    "addr:housenumber":"427",
    "addr:postcode":"r0k 1g0",
    "addr:street":"Williams Ave",
    "iso:country":"CA",
    "sg:address":"427 Williams Ave",
    "sg:city":"Killarney",
    "sg:classifiers":[
        {
            "category":"Restaurant",
            "type":"Food & Drink"
        }
    ],
    "sg:phone":"+1 204 523 4659",
    "sg:postcode":"R0K 1G0",
    "sg:province":"MB",
    "sg:tags":[
        "motel",
        "hotel"
    ],
    "wof:name":"Killarney Motor Hotel",
    "wof:placetype":"venue"
},
  "geometry": {"coordinates":[-99.666313,49.18264],"type":"Point"}
}