{
  "type": "Feature",
  "properties": {
    "addr:full":"Ottawa ON K1R 7S8",
    "addr:postcode":"k1r 7s8",
    "iso:country":"CA",
    "sg:city":"Ottawa",
    "sg:classifiers":[
        {
            "category":"Professional",
            "subcategory":"Research",
            "type":"Services"
        }
    ],
    "sg:phone":"+1 613 594 8282",
    "sg:postcode":"K1R 7S8",
    "sg:province":"ON",
    "sg:tags":[
        "market",
        "analysis"
    ],
    "wof:name":"Vision Research Inc",
    "wof:placetype":"venue"
},
  "geometry": {"coordinates":[-75.705719,45.419121],"type":"Point"}
}