{
  "type": "Feature",
  "properties": {
    "iso:country":"CA",
    "sg:address":"12 Underwood Rd",
    "sg:city":"Ingersoll",
    "sg:classifiers":[
        {
            "category":"Wholesale",
            "subcategory":"Hardware",
            "type":"Manufacturing & Wholesale Goods"
        }
    ],
    "sg:phone":"+1 519 485 1050",
    "sg:postcode":"N5C 3K1",
    "sg:province":"ON",
    "sg:tags":[
        "fastener"
    ],
    "wof:name":"Nifast Canada Corp",
    "wof:placetype":"venue"
},
  "geometry": {"coordinates":[-80.8819656372,43.017742157],"type":"Point"}
}