{
  "type": "Feature",
  "properties": {
    "addr:full":"1632 Rue Fleury E Montreal QC H2C 1S8",
    "addr:housenumber":"1632",
    "addr:postcode":"h2c 1s8",
    "addr:street":"Rue Fleury E",
    "iso:country":"CA",
    "sg:address":"1632 Rue Fleury E",
    "sg:city":"Montreal",
    "sg:classifiers":[
        {
            "category":"Professional",
            "subcategory":"Accounting & Tax Preparation",
            "type":"Services"
        }
    ],
    "sg:phone":"+1 514 385 6515",
    "sg:postcode":"H2C 1S8",
    "sg:province":"QC",
    "sg:tags":[
        "return",
        "filing"
    ],
    "wof:name":"Taillefer Jean Luc Fiscaliste",
    "wof:placetype":"venue"
},
  "geometry": {"coordinates":[-73.65534210209999,45.5643043518],"type":"Point"}
}