{
  "type": "Feature",
  "properties": {
    "addr:full":"9048 138 Ave NW Edmonton AB T5E 2A9",
    "addr:housenumber":"9048",
    "addr:postcode":"t5e 2a9",
    "addr:street":"138 Ave Nw",
    "iso:country":"CA",
    "sg:address":"9048 138 Ave NW",
    "sg:city":"Edmonton",
    "sg:classifiers":[
        {
            "category":"Building & Trades",
            "subcategory":"Pest Control",
            "type":"Services"
        }
    ],
    "sg:phone":"+1 780 476 8886",
    "sg:postcode":"T5E 2A9",
    "sg:province":"AB",
    "wof:name":"Ernst Fumigators",
    "wof:placetype":"venue"
},
  "geometry": {"coordinates":[-113.481437683,53.6008377075],"type":"Point"}
}