{
  "type": "Feature",
  "properties": {
    "addr:full":"Scarborough ON M1V 1E7",
    "addr:postcode":"m1v 1e7",
    "iso:country":"CA",
    "sg:city":"Scarborough",
    "sg:classifiers":[
        {
            "category":"Insurance",
            "subcategory":"Insurance Agent",
            "type":"Services"
        }
    ],
    "sg:phone":"+1 416 291 5521",
    "sg:postcode":"M1V 1E7",
    "sg:province":"ON",
    "wof:name":"Bst Insurance Brokers Ltd",
    "wof:placetype":"venue"
},
  "geometry": {"coordinates":[-79.299744,43.807762],"type":"Point"}
}