{
  "type": "Feature",
  "properties": {
    "addr:full":"44 Britannia Rd E Mississauga ON L4Z 3W7",
    "addr:housenumber":"44",
    "addr:postcode":"l4z 3w7",
    "addr:street":"Britannia Rd E",
    "iso:country":"CA",
    "sg:address":"44 Britannia Rd E",
    "sg:city":"Mississauga",
    "sg:classifiers":[
        {
            "category":"Restaurant",
            "type":"Food & Drink"
        }
    ],
    "sg:phone":"+1 905 712 4312",
    "sg:postcode":"L4Z 3W7",
    "sg:province":"ON",
    "wof:name":"Wendy's",
    "wof:placetype":"venue"
},
  "geometry": {"coordinates":[-79.678459,43.62709],"type":"Point"}
}