{
  "type": "Feature",
  "properties": {
    "iso:country":"CA",
    "sg:address":"76 Combe Ave",
    "sg:city":"North York",
    "sg:classifiers":[
        {
            "category":"Building & Trades",
            "subcategory":"Construction",
            "type":"Services"
        }
    ],
    "sg:phone":"+1 416 633 8411",
    "sg:postcode":"M3H 4J7",
    "sg:province":"ON",
    "sg:tags":[
        "resurfacing",
        "laying",
        "refinishing",
        "floor"
    ],
    "wof:name":"D B Flooring",
    "wof:placetype":"venue"
},
  "geometry": {"coordinates":[-79.451698,43.760624],"type":"Point"}
}