{
  "type": "Feature",
  "properties": {
    "addr:full":"Montreal QC H2N 1R2",
    "addr:postcode":"h2n 1r2",
    "iso:country":"CA",
    "sg:city":"Montreal",
    "sg:classifiers":[
        {
            "category":"Wholesale",
            "subcategory":"Home Furnishings",
            "type":"Manufacturing & Wholesale Goods"
        }
    ],
    "sg:phone":"+1 514 381 9137",
    "sg:postcode":"H2N 1R2",
    "sg:province":"QC",
    "sg:tags":[
        "curtain",
        "drapery"
    ],
    "wof:name":"Tissus Decoratifs Starlite Inc",
    "wof:placetype":"venue"
},
  "geometry": {"coordinates":[-73.655846,45.545666],"type":"Point"}
}