{
  "type": "Feature",
  "properties": {
    "addr:full":"1395 Route 46 Fabre QC J0Z 1Z0",
    "addr:housenumber":"1395",
    "addr:postcode":"j0z 1z0",
    "addr:street":"Route 46 Fabre",
    "iso:country":"CA",
    "sg:address":"1395 Route 46",
    "sg:city":"Fabre",
    "sg:classifiers":[
        {
            "category":"Freight",
            "type":"Transportation"
        }
    ],
    "sg:phone":"+1 819 634 5461",
    "sg:postcode":"J0Z 1Z0",
    "sg:province":"QC",
    "sg:tags":[
        "trucking"
    ],
    "wof:name":"Transport B Derochers Inc",
    "wof:placetype":"venue"
},
  "geometry": {"coordinates":[-79.36739300000001,47.199329],"type":"Point"}
}