{
  "type": "Feature",
  "properties": {
    "addr:full":"Laporte Pump STN Eatonia SK S0L 0Y0",
    "addr:postcode":"s0l 0y0",
    "addr:street":"Eatonia",
    "iso:country":"CA",
    "sg:address":"Laporte Pump STN",
    "sg:city":"Eatonia",
    "sg:classifiers":[
        {
            "category":"Mining & Drilling",
            "type":"Manufacturing & Wholesale Goods"
        }
    ],
    "sg:phone":"+1 306 967 2888",
    "sg:postcode":"S0L 0Y0",
    "sg:province":"SK",
    "sg:tags":[
        "company",
        "oil"
    ],
    "wof:name":"Bp Canada Energy CO",
    "wof:placetype":"venue"
},
  "geometry": {"coordinates":[-109.389267,51.221149],"type":"Point"}
}