{
  "type": "Feature",
  "properties": {
    "iso:country":"CA",
    "sg:address":"Cassburn Rd",
    "sg:city":"L'Orignal",
    "sg:classifiers":[
        {
            "category":"Organizations",
            "subcategory":"Religious Organization",
            "type":"Services"
        }
    ],
    "sg:phone":"+1 613 675 4487",
    "sg:postcode":"K0B 1K0",
    "sg:province":"ON",
    "sg:tags":[
        "church"
    ],
    "wof:name":"Cassburn United Church",
    "wof:placetype":"venue"
},
  "geometry": {"coordinates":[-74.6980209351,45.6091194153],"type":"Point"}
}