{
  "type": "Feature",
  "properties": {
    "addr:full":"7381 Boul Du Cure-Labelle Labelle QC J0T 1H0",
    "addr:housenumber":"7381",
    "addr:postcode":"j0t 1h0",
    "addr:street":"Boul Du Cure-Labelle",
    "iso:country":"CA",
    "sg:address":"7381 Boul Du Cure-Labelle",
    "sg:city":"Labelle",
    "sg:classifiers":[
        {
            "category":"Insurance",
            "subcategory":"Insurance Agent",
            "type":"Services"
        }
    ],
    "sg:phone":"+1 819 686 5353",
    "sg:postcode":"J0T 1H0",
    "sg:province":"QC",
    "wof:name":"Promutuel L'Abitibienne",
    "wof:placetype":"venue"
},
  "geometry": {"coordinates":[-74.734093,46.280285],"type":"Point"}
}