{
  "type": "Feature",
  "properties": {
    "addr:full":"21 Linda Limoges ON K0A 2M0",
    "addr:housenumber":"21",
    "addr:postcode":"k0a 2m0",
    "addr:street":"Linda Limoges",
    "iso:country":"CA",
    "sg:address":"21 Linda",
    "sg:city":"Limoges",
    "sg:classifiers":[
        {
            "category":"Building & Trades",
            "subcategory":"Construction",
            "type":"Services"
        }
    ],
    "sg:phone":"+1 613 443 3341",
    "sg:postcode":"K0A 2M0",
    "sg:province":"ON",
    "sg:tags":[
        "downspouts",
        "gutter"
    ],
    "wof:name":"Maurice Laforest Eavestrough",
    "wof:placetype":"venue"
},
  "geometry": {"coordinates":[-75.2473831177,45.3251228333],"type":"Point"}
}