{
  "type": "Feature",
  "properties": {
    "addr:full":"164 Rang Mississipi St-Germain QC G0L 3G0",
    "addr:housenumber":"164",
    "addr:postcode":"g0l 3g0",
    "addr:street":"Rang Mississipi St-Germain",
    "iso:country":"CA",
    "sg:address":"164 Rang Mississipi",
    "sg:city":"St-Germain",
    "sg:classifiers":[
        {
            "category":"Farming",
            "subcategory":"Farm",
            "type":"Manufacturing & Wholesale Goods"
        }
    ],
    "sg:phone":"+1 418 492 1541",
    "sg:postcode":"G0L 3G0",
    "sg:province":"QC",
    "wof:name":"Ferme FM Levesque",
    "wof:placetype":"venue"
},
  "geometry": {"coordinates":[-69.775566,47.606148],"type":"Point"}
}