{
  "type": "Feature",
  "properties": {
    "addr:full":"85 Clarence St Ottawa ON K1N 5P5",
    "addr:housenumber":"85",
    "addr:postcode":"k1n 5p5",
    "addr:street":"Clarence St",
    "iso:country":"CA",
    "sg:address":"85 Clarence St",
    "sg:city":"Ottawa",
    "sg:classifiers":[
        {
            "category":"Restaurant",
            "type":"Food & Drink"
        }
    ],
    "sg:phone":"+1 613 789 7934",
    "sg:postcode":"K1N 5P5",
    "sg:province":"ON",
    "wof:name":"Saigon Restaurant",
    "wof:placetype":"venue"
},
  "geometry": {"coordinates":[-75.6929702759,45.4292678833],"type":"Point"}
}