{
  "type": "Feature",
  "properties": {
    "addr:full":"115 Clarence St Ottawa ON K1N 5P5",
    "addr:housenumber":"115",
    "addr:postcode":"k1n 5p5",
    "addr:street":"Clarence St",
    "iso:country":"CA",
    "sg:address":"115 Clarence St",
    "sg:city":"Ottawa",
    "sg:classifiers":[
        {
            "category":"Home & Garden",
            "subcategory":"Carpets & Floor Coverings",
            "type":"Retail Goods"
        }
    ],
    "sg:phone":"+1 613 789 9139",
    "sg:postcode":"K1N 5P5",
    "sg:province":"ON",
    "sg:tags":[
        "dealer",
        "rug"
    ],
    "wof:name":"Canadian Rug Traders",
    "wof:placetype":"venue"
},
  "geometry": {"coordinates":[-75.69230651860001,45.4295539856],"type":"Point"}
}