{
  "type": "Feature",
  "properties": {
    "addr:full":"330 Alexander NE # 103 Salmon Arm BC V1E 4N7",
    "addr:housenumber":"330",
    "addr:postcode":"v1e 4n7",
    "addr:street":"Alexander Ne # 103",
    "iso:country":"CA",
    "sg:address":"330 Alexander NE # 103",
    "sg:city":"Salmon Arm",
    "sg:classifiers":[
        {
            "category":"Health Services",
            "subcategory":"Medical Lab",
            "type":"Services"
        }
    ],
    "sg:phone":"+1 250 833 1500",
    "sg:postcode":"V1E 4N7",
    "sg:province":"BC",
    "wof:name":"Salmon Arm Denture Clinic",
    "wof:placetype":"venue"
},
  "geometry": {"coordinates":[-119.28272247300001,50.7020454407],"type":"Point"}
}