{
  "type": "Feature",
  "properties": {
    "addr:full":"732 Queen St Kincardine ON N2Z 1Z8",
    "addr:housenumber":"732",
    "addr:postcode":"n2z 1z8",
    "addr:street":"Queen St",
    "iso:country":"CA",
    "sg:address":"732 Queen St",
    "sg:city":"Kincardine",
    "sg:classifiers":[
        {
            "category":"Personal",
            "subcategory":"Tattoo Parlor",
            "type":"Services"
        }
    ],
    "sg:phone":"+1 519 396 8282",
    "sg:postcode":"N2Z 1Z8",
    "sg:province":"ON",
    "sg:tags":[
        "tattooing"
    ],
    "wof:name":"Sugar Shack Tattoo",
    "wof:placetype":"venue"
},
  "geometry": {"coordinates":[-81.6362991333,44.1759147644],"type":"Point"}
}