{
  "type": "Feature",
  "properties": {
    "iso:country":"CA",
    "sg:address":"503 Clothier St W",
    "sg:city":"Kemptville",
    "sg:classifiers":[
        {
            "category":"Organizations",
            "subcategory":"Religious Organization",
            "type":"Services"
        }
    ],
    "sg:phone":"+1 613 258 3377",
    "sg:postcode":"K0G 1J0",
    "sg:province":"ON",
    "sg:tags":[
        "church"
    ],
    "wof:name":"Holy Cross Church",
    "wof:placetype":"venue"
},
  "geometry": {"coordinates":[-75.653191,45.012257],"type":"Point"}
}