{
  "type": "Feature",
  "properties": {
    "addr:full":"Millbrook ON L0A 1G0",
    "addr:postcode":"l0a 1g0",
    "iso:country":"CA",
    "sg:city":"Millbrook",
    "sg:classifiers":[
        {
            "category":"Organizations",
            "subcategory":"Religious Organization",
            "type":"Services"
        }
    ],
    "sg:phone":"+1 705 932 2186",
    "sg:postcode":"L0A 1G0",
    "sg:province":"ON",
    "sg:tags":[
        "church"
    ],
    "wof:name":"Cavan St Andrews United Church",
    "wof:placetype":"venue"
},
  "geometry": {"coordinates":[-78.447456,44.150921],"type":"Point"}
}