{
  "type": "Feature",
  "properties": {
    "addr:full":"2128 Rue Saint-Mathieu Montreal QC H3H 2J4",
    "addr:housenumber":"2128",
    "addr:postcode":"h3h 2j4",
    "addr:street":"Rue Saint-Mathieu",
    "iso:country":"CA",
    "sg:address":"2128 Rue Saint-Mathieu",
    "sg:city":"Montreal",
    "sg:classifiers":[
        {
            "category":"Personal",
            "subcategory":"Beauty Salon",
            "type":"Services"
        }
    ],
    "sg:phone":"+1 514 932 8194",
    "sg:postcode":"H3H 2J4",
    "sg:province":"QC",
    "wof:name":"Beauty Salon Sharon",
    "wof:placetype":"venue"
},
  "geometry": {"coordinates":[-73.58117675779999,45.4947662354],"type":"Point"}
}