{
  "type": "Feature",
  "properties": {
    "addr:full":"St-Sauveur-Des-Monts QC J0R 1R0",
    "addr:postcode":"j0r 1r0",
    "iso:country":"CA",
    "sg:city":"St-Sauveur-Des-Monts",
    "sg:classifiers":[
        {
            "category":"Personal",
            "subcategory":"Beauty Salon",
            "type":"Services"
        }
    ],
    "sg:phone":"+1 450 227 6434",
    "sg:postcode":"J0R 1R0",
    "sg:province":"QC",
    "wof:name":"Salon En Tete Enr",
    "wof:placetype":"venue"
},
  "geometry": {"coordinates":[-74.1579818726,45.8936195374],"type":"Point"}
}