{
  "type": "Feature",
  "properties": {
    "addr:full":"Toronto ON M4P 1E8",
    "addr:postcode":"m4p 1e8",
    "iso:country":"CA",
    "sg:city":"Toronto",
    "sg:classifiers":[
        {
            "category":"Government",
            "subcategory":"Office",
            "type":"Public Place"
        }
    ],
    "sg:phone":"+1 416 397 1800",
    "sg:postcode":"M4P 1E8",
    "sg:province":"ON",
    "sg:tags":[
        "village"
    ],
    "wof:name":"Toronto Social Assistance Ofc",
    "wof:placetype":"venue"
},
  "geometry": {"coordinates":[-79.3938827515,43.7077941895],"type":"Point"}
}