{
  "type": "Feature",
  "properties": {
    "iso:country":"CA",
    "sg:city":"Mississauga",
    "sg:classifiers":[
        {
            "category":"Food & Beverages",
            "subcategory":"Groceries & Convenience Stores",
            "type":"Retail Goods"
        }
    ],
    "sg:phone":"+1 905 896 4263",
    "sg:postcode":"L5A 4E1",
    "sg:province":"ON",
    "sg:tags":[
        "grocer"
    ],
    "wof:name":"Han Yang Oriental Supermarket",
    "wof:placetype":"venue"
},
  "geometry": {"coordinates":[-79.614021,43.580406],"type":"Point"}
}