{
  "type": "Feature",
  "properties": {
    "addr:full":"179 Sheppard Ave E North York ON M2N 3A6",
    "addr:housenumber":"179",
    "addr:postcode":"m2n 3a6",
    "addr:street":"Sheppard Ave E",
    "iso:country":"CA",
    "sg:address":"179 Sheppard Ave E",
    "sg:city":"North York",
    "sg:classifiers":[
        {
            "category":"Food & Beverages",
            "subcategory":"Liquor & Beverages",
            "type":"Retail Goods"
        }
    ],
    "sg:phone":"+1 416 225 3013",
    "sg:postcode":"M2N 3A6",
    "sg:province":"ON",
    "sg:tags":[
        "beer",
        "ale"
    ],
    "wof:name":"Beer Store",
    "wof:placetype":"venue"
},
  "geometry": {"coordinates":[-79.4000320435,43.7637825012],"type":"Point"}
}