{
  "type": "Feature",
  "properties": {
    "addr:full":"46 Edgecombe Ave North York ON M5N 2X3",
    "addr:housenumber":"46",
    "addr:postcode":"m5n 2x3",
    "addr:street":"Edgecombe Ave",
    "iso:country":"CA",
    "sg:address":"46 Edgecombe Ave",
    "sg:city":"North York",
    "sg:classifiers":[
        {
            "category":"Professional",
            "subcategory":"Management & Consulting",
            "type":"Services"
        }
    ],
    "sg:phone":"+1 416 783 3020",
    "sg:postcode":"M5N 2X3",
    "sg:province":"ON",
    "sg:tags":[
        "consultant",
        "business"
    ],
    "wof:name":"Shareyt Managements Inc",
    "wof:placetype":"venue"
},
  "geometry": {"coordinates":[-79.416687,43.72089],"type":"Point"}
}