{
  "type": "Feature",
  "properties": {
    "addr:full":"Trois-Rivieres QC G9A 5R6",
    "addr:postcode":"g9a 5r6",
    "iso:country":"CA",
    "sg:city":"Trois-Rivieres",
    "sg:classifiers":[
        {
            "category":"Wholesale",
            "subcategory":"Office Equipment",
            "type":"Manufacturing & Wholesale Goods"
        }
    ],
    "sg:phone":"+1 819 373 0112",
    "sg:postcode":"G9A 5R6",
    "sg:province":"QC",
    "sg:tags":[
        "supply",
        "register",
        "system",
        "cash",
        "time",
        "recorder"
    ],
    "wof:name":"Dijitec Inc",
    "wof:placetype":"venue"
},
  "geometry": {"coordinates":[-72.559235,46.334686],"type":"Point"}
}