{
  "type": "Feature",
  "properties": {
    "addr:full":"34979 Everett Dr Abbotsford BC V2S 7R9",
    "addr:housenumber":"34979",
    "addr:postcode":"v2s 7r9",
    "addr:street":"Everett Dr",
    "iso:country":"CA",
    "sg:address":"34979 Everett Dr",
    "sg:city":"Abbotsford",
    "sg:classifiers":[
        {
            "category":"Shopping",
            "type":"Retail Goods"
        }
    ],
    "sg:phone":"+1 604 852 8004",
    "sg:postcode":"V2S 7R9",
    "sg:province":"BC",
    "sg:tags":[
        "skin",
        "treatment",
        "cosmetic"
    ],
    "wof:name":"Mary Kay Cosmetics",
    "wof:placetype":"venue"
},
  "geometry": {"coordinates":[-122.255256653,49.041683197],"type":"Point"}
}