{
  "type": "Feature",
  "properties": {
    "addr:full":"285 William St Arborg MB R0C 0A0",
    "addr:housenumber":"285",
    "addr:postcode":"r0c 0a0",
    "addr:street":"William St",
    "iso:country":"CA",
    "sg:address":"285 William St",
    "sg:city":"Arborg",
    "sg:classifiers":[
        {
            "category":"Autos & Motor Vehicles",
            "subcategory":"Automobile Sales",
            "type":"Retail Goods"
        }
    ],
    "sg:phone":"+1 204 376 2263",
    "sg:postcode":"R0C 0A0",
    "sg:province":"MB",
    "sg:tags":[
        "car",
        "dealer"
    ],
    "wof:name":"Chyzy Sales & Svc Inc",
    "wof:placetype":"venue"
},
  "geometry": {"coordinates":[-97.22210699999999,50.913399],"type":"Point"}
}