{
  "type": "Feature",
  "properties": {
    "addr:full":"1426 Rue Bagot LA Baie QC G7B 2P5",
    "addr:housenumber":"1426",
    "addr:postcode":"g7b 2p5",
    "addr:street":"Rue Bagot",
    "iso:country":"CA",
    "sg:address":"1426 Rue Bagot",
    "sg:city":"LA Baie",
    "sg:classifiers":[
        {
            "category":"Insurance",
            "subcategory":"Insurance Agent",
            "type":"Services"
        }
    ],
    "sg:phone":"+1 418 544 9375",
    "sg:postcode":"G7B 2P5",
    "sg:province":"QC",
    "wof:name":"Promutuel Du Lac Au Fjord",
    "wof:placetype":"venue"
},
  "geometry": {"coordinates":[-70.886909,48.337498],"type":"Point"}
}