{
  "type": "Feature",
  "properties": {
    "addr:full":"633 Main St N Sauble Beach ON N0H 2G0",
    "addr:housenumber":"633",
    "addr:postcode":"n0h 2g0",
    "addr:street":"Main St N",
    "iso:country":"CA",
    "sg:address":"633 Main St N",
    "sg:city":"Sauble Beach",
    "sg:classifiers":[
        {
            "category":"Home & Garden",
            "subcategory":"Household Appliances",
            "type":"Retail Goods"
        }
    ],
    "sg:phone":"+1 519 422 2831",
    "sg:postcode":"N0H 2G0",
    "sg:province":"ON",
    "wof:name":"Longland's Appliance Sales",
    "wof:placetype":"venue"
},
  "geometry": {"coordinates":[-81.2607421875,44.6298675537],"type":"Point"}
}