{
  "type": "Feature",
  "properties": {
    "iso:country":"CA",
    "sg:address":"211 Martindale Rd",
    "sg:city":"St Catharines",
    "sg:classifiers":[
        {
            "category":"Organizations",
            "subcategory":"Professional Association",
            "type":"Services"
        }
    ],
    "sg:phone":"+1 905 688 0022",
    "sg:postcode":"L2S 3V7",
    "sg:province":"ON",
    "sg:tags":[
        "social",
        "welfare"
    ],
    "wof:name":"Canadian Natl Institute Blind",
    "wof:placetype":"venue"
},
  "geometry": {"coordinates":[-79.273209,43.172161],"type":"Point"}
}