{
  "type": "Feature",
  "properties": {
    "addr:full":"Quebec QC G2K 2G4",
    "addr:postcode":"g2k 2g4",
    "iso:country":"CA",
    "sg:city":"Quebec",
    "sg:classifiers":[
        {
            "category":"Real Estate",
            "subcategory":"Real Estate Agent",
            "type":"Services"
        }
    ],
    "sg:phone":"+1 418 626 5500",
    "sg:postcode":"G2K 2G4",
    "sg:province":"QC",
    "sg:tags":[
        "management"
    ],
    "wof:name":"Gestion Immobiliere Lafrance",
    "wof:placetype":"venue"
},
  "geometry": {"coordinates":[-71.2951889038,46.836227417],"type":"Point"}
}