{
  "type": "Feature",
  "properties": {
    "addr:full":"Montreal QC H2Y 3B1",
    "addr:postcode":"h2y 3b1",
    "iso:country":"CA",
    "sg:city":"Montreal",
    "sg:classifiers":[
        {
            "category":"Real Estate",
            "subcategory":"Real Estate Agent",
            "type":"Services"
        }
    ],
    "sg:phone":"+1 514 861 1001",
    "sg:postcode":"H2Y 3B1",
    "sg:province":"QC",
    "sg:tags":[
        "management"
    ],
    "wof:name":"Cdn Mgmt",
    "wof:placetype":"venue"
},
  "geometry": {"coordinates":[-73.55280303959999,45.5080375671],"type":"Point"}
}