{
  "type": "Feature",
  "properties": {
    "addr:full":"1162 Osler St Regina SK S4R 5G9",
    "addr:housenumber":"1162",
    "addr:postcode":"s4r 5g9",
    "addr:street":"Osler St",
    "iso:country":"CA",
    "sg:address":"1162 Osler St",
    "sg:city":"Regina",
    "sg:classifiers":[
        {
            "category":"Manufacturing",
            "subcategory":"Tools & Machinery",
            "type":"Manufacturing & Wholesale Goods"
        }
    ],
    "sg:phone":"+1 306 757 5678",
    "sg:postcode":"S4R 5G9",
    "sg:province":"SK",
    "sg:tags":[
        "machine",
        "copying",
        "furniture"
    ],
    "wof:name":"Brennan Office Plus",
    "wof:placetype":"venue"
},
  "geometry": {"coordinates":[-104.605125,50.460457],"type":"Point"}
}