{
  "type": "Feature",
  "properties": {
    "addr:full":"35 Lorne Ave Kettleby ON L0G 1J0",
    "addr:housenumber":"35",
    "addr:postcode":"l0g 1j0",
    "addr:street":"Lorne Ave",
    "iso:country":"CA",
    "sg:address":"35 Lorne Ave",
    "sg:city":"Kettleby",
    "sg:classifiers":[
        {
            "category":"Professional",
            "subcategory":"Management & Consulting",
            "type":"Services"
        }
    ],
    "sg:phone":"+1 905 726 1666",
    "sg:postcode":"L0G 1J0",
    "sg:province":"ON",
    "sg:tags":[
        "consultant",
        "business"
    ],
    "wof:name":"Harvard Group",
    "wof:placetype":"venue"
},
  "geometry": {"coordinates":[-79.566536,44.009487],"type":"Point"}
}