{
  "type": "Feature",
  "properties": {
    "addr:full":"99 Young St W Harriston ON N0G 1Z0",
    "addr:housenumber":"99",
    "addr:postcode":"n0g 1z0",
    "addr:street":"Young St W",
    "iso:country":"CA",
    "sg:address":"99 Young St W",
    "sg:city":"Harriston",
    "sg:classifiers":[
        {
            "category":"Organizations",
            "subcategory":"Religious Organization",
            "type":"Services"
        }
    ],
    "sg:phone":"+1 519 338 5581",
    "sg:postcode":"N0G 1Z0",
    "sg:province":"ON",
    "sg:tags":[
        "church"
    ],
    "wof:name":"Crossroads Community Church",
    "wof:placetype":"venue"
},
  "geometry": {"coordinates":[-80.86944580079999,43.9089813232],"type":"Point"}
}