{
  "type": "Feature",
  "properties": {
    "addr:full":"69 Hawkview Blvd Woodbridge ON L4H 2E2",
    "addr:housenumber":"69",
    "addr:postcode":"l4h 2e2",
    "addr:street":"Hawkview Blvd",
    "iso:country":"CA",
    "sg:address":"69 Hawkview Blvd",
    "sg:city":"Woodbridge",
    "sg:classifiers":[
        {
            "category":"Shopping",
            "subcategory":"Clothing, Apparel, & Fashions",
            "type":"Retail Goods"
        }
    ],
    "sg:phone":"+1 905 832 0024",
    "sg:postcode":"L4H 2E2",
    "sg:province":"ON",
    "sg:tags":[
        "dressmaker"
    ],
    "wof:name":"Jenran Exclusive Designs",
    "wof:placetype":"venue"
},
  "geometry": {"coordinates":[-79.55445899999999,43.828171],"type":"Point"}
}