{
  "type": "Feature",
  "properties": {
    "addr:full":"211 12E Av Saint-Eustache QC J7P 2S7",
    "addr:housenumber":"211",
    "addr:postcode":"j7p 2s7",
    "addr:street":"12E Av Saint-Eustache",
    "iso:country":"CA",
    "sg:address":"211 12E Av",
    "sg:city":"Saint-Eustache",
    "sg:classifiers":[
        {
            "category":"Manufacturing",
            "subcategory":"Glass & Minerals",
            "type":"Manufacturing & Wholesale Goods"
        }
    ],
    "sg:phone":"+1 450 623 0052",
    "sg:postcode":"J7P 2S7",
    "sg:province":"QC",
    "sg:tags":[
        "marble"
    ],
    "wof:name":"Onixmar Inc",
    "wof:placetype":"venue"
},
  "geometry": {"coordinates":[-73.8889007568,45.5580482483],"type":"Point"}
}