{
  "type": "Feature",
  "properties": {
    "addr:full":"181 138 Rte Saint-Augustin-DE-Desmaures QC G3A 1W7",
    "addr:housenumber":"138",
    "addr:postcode":"g3a 1w7",
    "addr:street":"Rte Saint-Augustin-De-Desmaures",
    "iso:country":"CA",
    "sg:address":"181 138 Rte",
    "sg:city":"Saint-Augustin-DE-Desmaures",
    "sg:classifiers":[
        {
            "category":"Retail",
            "subcategory":"Auto Repair",
            "type":"Services"
        }
    ],
    "sg:phone":"+1 418 878 3028",
    "sg:postcode":"G3A 1W7",
    "sg:province":"QC",
    "sg:tags":[
        "repairing",
        "automobile"
    ],
    "wof:name":"Station DE Svc Mar-and Inc",
    "wof:placetype":"venue"
},
  "geometry": {"coordinates":[-71.4315414429,46.7510871887],"type":"Point"}
}