{
  "type": "Feature",
  "properties": {
    "addr:full":"3600 Rue Richelieu Saint-Hubert QC J3Y 7B1",
    "addr:housenumber":"3600",
    "addr:postcode":"j3y 7b1",
    "addr:street":"Rue Richelieu",
    "iso:country":"CA",
    "sg:address":"3600 Rue Richelieu",
    "sg:city":"Saint-Hubert",
    "sg:classifiers":[
        {
            "category":"Home & Garden",
            "subcategory":"Home Furnishings",
            "type":"Retail Goods"
        }
    ],
    "sg:phone":"+1 450 678 9221",
    "sg:postcode":"J3Y 7B1",
    "sg:province":"QC",
    "sg:tags":[
        "door",
        "supply",
        "bath",
        "shower",
        "equipment",
        "enclosure"
    ],
    "wof:name":"Aciflex Industries Inc",
    "wof:placetype":"venue"
},
  "geometry": {"coordinates":[-73.44548,45.501408],"type":"Point"}
}