{
  "type": "Feature",
  "properties": {
    "iso:country":"CA",
    "sg:city":"Canmore",
    "sg:classifiers":[
        {
            "category":"Health Services",
            "subcategory":"Doctor",
            "type":"Services"
        }
    ],
    "sg:phone":"+1 403 609 2136",
    "sg:postcode":"T1W 1P5",
    "sg:province":"AB",
    "sg:tags":[
        "physician",
        "surgeon"
    ],
    "wof:name":"Bryson, Wally MD",
    "wof:placetype":"venue"
},
  "geometry": {"coordinates":[-115.35058593799999,51.0909805298],"type":"Point"}
}