{
  "type": "Feature",
  "properties": {
    "addr:full":"17075 Leslie St #33 Newmarket ON L3Y 8E1",
    "addr:housenumber":"17075;33",
    "addr:postcode":"l3y 8e1",
    "addr:street":"Leslie St #",
    "iso:country":"CA",
    "sg:address":"17075 Leslie St #33",
    "sg:city":"Newmarket",
    "sg:classifiers":[
        {
            "category":"Retail",
            "subcategory":"Auto Repair",
            "type":"Services"
        }
    ],
    "sg:phone":"+1 905 830 1828",
    "sg:postcode":"L3Y 8E1",
    "sg:province":"ON",
    "sg:tags":[
        "repairing",
        "automobile",
        "lubrication"
    ],
    "wof:name":"Pennzoil 10 Minute Oil Change",
    "wof:placetype":"venue"
},
  "geometry": {"coordinates":[-79.4296569824,44.0577201843],"type":"Point"}
}