{
  "type": "Feature",
  "properties": {
    "addr:full":"8 Mayhurst Ave Hamilton ON L8K 3M8",
    "addr:housenumber":"8",
    "addr:postcode":"l8k 3m8",
    "addr:street":"Mayhurst Ave",
    "iso:country":"CA",
    "sg:address":"8 Mayhurst Ave",
    "sg:city":"Hamilton",
    "sg:classifiers":[
        {
            "category":"Organizations",
            "subcategory":"Religious Organization",
            "type":"Services"
        }
    ],
    "sg:phone":"+1 905 549 2711",
    "sg:postcode":"L8K 3M8",
    "sg:province":"ON",
    "sg:tags":[
        "church"
    ],
    "wof:name":"St Mary Armenian Church",
    "wof:placetype":"venue"
},
  "geometry": {"coordinates":[-79.7979431152,43.2298164368],"type":"Point"}
}