{
  "type": "Feature",
  "properties": {
    "addr:full":"1680 Rue DE Malapart Trois-Rivieres QC G8Y 4V7",
    "addr:housenumber":"1680",
    "addr:postcode":"g8y 4v7",
    "addr:street":"Rue De Malapart Trois-Rivieres",
    "iso:country":"CA",
    "sg:address":"1680 Rue DE Malapart",
    "sg:city":"Trois-Rivieres",
    "sg:classifiers":[
        {
            "category":"Personal",
            "subcategory":"Beauty Salon",
            "type":"Services"
        }
    ],
    "sg:phone":"+1 819 691 0880",
    "sg:postcode":"G8Y 4V7",
    "sg:province":"QC",
    "wof:name":"Claude Saint-Louis Coiffure",
    "wof:placetype":"venue"
},
  "geometry": {"coordinates":[-72.58493804930001,46.3534049988],"type":"Point"}
}