{
  "type": "Feature",
  "properties": {
    "addr:full":"Saint John NB E2L 1G3",
    "addr:postcode":"e2l 1g3",
    "iso:country":"CA",
    "sg:city":"Saint John",
    "sg:classifiers":[
        {
            "category":"Professional",
            "subcategory":"Lawyer & Legal Services",
            "type":"Services"
        }
    ],
    "sg:phone":"+1 506 633 8588",
    "sg:postcode":"E2L 1G3",
    "sg:province":"NB",
    "sg:tags":[
        "attorney"
    ],
    "wof:name":"Shannon Bishop Mc Phee",
    "wof:placetype":"venue"
},
  "geometry": {"coordinates":[-66.0610656738,45.2729377747],"type":"Point"}
}