{
  "type": "Feature",
  "properties": {
    "iso:country":"CA",
    "sg:city":"Winnipeg",
    "sg:classifiers":[
        {
            "category":"Freight",
            "type":"Transportation"
        }
    ],
    "sg:phone":"+1 204 953 0210",
    "sg:postcode":"R3B 0X3",
    "sg:province":"MB",
    "sg:tags":[
        "broker",
        "agent"
    ],
    "wof:name":"Seaway Marine Transport",
    "wof:placetype":"venue"
},
  "geometry": {"coordinates":[-97.137184,49.89566],"type":"Point"}
}