{
  "type": "Feature",
  "properties": {
    "iso:country":"CA",
    "sg:city":"St Catharines",
    "sg:classifiers":[
        {
            "category":"Home & Garden",
            "subcategory":"Furniture",
            "type":"Retail Goods"
        }
    ],
    "sg:phone":"+1 905 641 5295",
    "sg:postcode":"L2R 6P9",
    "sg:province":"ON",
    "sg:tags":[
        "mattress"
    ],
    "wof:name":"Sleep Country Canada",
    "wof:placetype":"venue"
},
  "geometry": {"coordinates":[-79.27034759519999,43.1526374817],"type":"Point"}
}