{
  "type": "Feature",
  "properties": {
    "addr:full":"204 5 Ave W Bow Island AB T0K 0G0",
    "addr:housenumber":"204",
    "addr:postcode":"t0k 0g0",
    "addr:street":"5 Ave W Bow Island",
    "iso:country":"CA",
    "sg:address":"204 5 Ave W",
    "sg:city":"Bow Island",
    "sg:classifiers":[
        {
            "category":"Banks & Credit Unions",
            "subcategory":"Bank",
            "type":"Services"
        }
    ],
    "sg:phone":"+1 403 545 2282",
    "sg:postcode":"T0K 0G0",
    "sg:province":"AB",
    "wof:name":"Community Credit Union",
    "wof:placetype":"venue"
},
  "geometry": {"coordinates":[-111.38310199999999,49.869598],"type":"Point"}
}