{
  "type": "Feature",
  "properties": {
    "addr:full":"2590 Av Watt Sainte-Foy QC G1P 4S2",
    "addr:housenumber":"2590",
    "addr:postcode":"g1p 4s2",
    "addr:street":"Av Watt",
    "iso:country":"CA",
    "sg:address":"2590 Av Watt",
    "sg:city":"Sainte-Foy",
    "sg:classifiers":[
        {
            "category":"Manufacturing",
            "subcategory":"Paper Products",
            "type":"Manufacturing & Wholesale Goods"
        }
    ],
    "sg:phone":"+1 418 653 8456",
    "sg:postcode":"G1P 4S2",
    "sg:province":"QC",
    "sg:tags":[
        "equipment",
        "agency",
        "rental",
        "caterer"
    ],
    "wof:name":"Location Castel Laval",
    "wof:placetype":"venue"
},
  "geometry": {"coordinates":[-71.30233764650001,46.7886619568],"type":"Point"}
}