{
  "type": "Feature",
  "properties": {
    "addr:full":"Palmerston ON N0G 2P0",
    "addr:postcode":"n0g 2p0",
    "iso:country":"CA",
    "sg:city":"Palmerston",
    "sg:classifiers":[
        {
            "category":"Government",
            "subcategory":"Fire Station",
            "type":"Public Place"
        }
    ],
    "sg:phone":"+1 519 343 3735",
    "sg:postcode":"N0G 2P0",
    "sg:province":"ON",
    "sg:tags":[
        "department"
    ],
    "wof:name":"Palmerston Fire Hall",
    "wof:placetype":"venue"
},
  "geometry": {"coordinates":[-80.8475570679,43.8344345093],"type":"Point"}
}