{
  "type": "Feature",
  "properties": {
    "addr:full":"2212 Rue Saint-Germain Montreal QC H1W 2T7",
    "addr:housenumber":"2212",
    "addr:postcode":"h1w 2t7",
    "addr:street":"Rue Saint-Germain",
    "iso:country":"CA",
    "sg:address":"2212 Rue Saint-Germain",
    "sg:city":"Montreal",
    "sg:classifiers":[
        {
            "category":"Restaurant",
            "type":"Food & Drink"
        }
    ],
    "sg:phone":"+1 514 598 1234",
    "sg:postcode":"H1W 2T7",
    "sg:province":"QC",
    "wof:name":"Restaurant Cafe Tex-Mex",
    "wof:placetype":"venue"
},
  "geometry": {"coordinates":[-73.549316,45.542259],"type":"Point"}
}