{
  "type": "Feature",
  "properties": {
    "addr:full":"Brandon MB R7B 2P7",
    "addr:postcode":"r7b 2p7",
    "iso:country":"CA",
    "sg:city":"Brandon",
    "sg:classifiers":[
        {
            "category":"Real Estate",
            "subcategory":"Real Estate Operator",
            "type":"Services"
        }
    ],
    "sg:phone":"+1 204 728 2584",
    "sg:postcode":"R7B 2P7",
    "sg:province":"MB",
    "sg:tags":[
        "apartment"
    ],
    "wof:name":"Boreham Park Apartments",
    "wof:placetype":"venue"
},
  "geometry": {"coordinates":[-99.9859619141,49.8449440002],"type":"Point"}
}