{
  "type": "Feature",
  "properties": {
    "addr:full":"2100 Ellesmere Rd Scarborough ON M1H 3B7",
    "addr:housenumber":"2100",
    "addr:postcode":"m1h 3b7",
    "addr:street":"Ellesmere Rd",
    "iso:country":"CA",
    "sg:address":"2100 Ellesmere Rd",
    "sg:city":"Scarborough",
    "sg:classifiers":[
        {
            "category":"Health Services",
            "subcategory":"Doctor",
            "type":"Services"
        }
    ],
    "sg:phone":"+1 416 438 8517",
    "sg:postcode":"M1H 3B7",
    "sg:province":"ON",
    "sg:tags":[
        "physician",
        "surgeon"
    ],
    "wof:name":"2100 Medical Ctr",
    "wof:placetype":"venue"
},
  "geometry": {"coordinates":[-79.2321548462,43.7764701843],"type":"Point"}
}