{
  "type": "Feature",
  "properties": {
    "addr:full":"Calgary AB T2B 1N5",
    "addr:postcode":"t2b 1n5",
    "iso:country":"CA",
    "sg:city":"Calgary",
    "sg:classifiers":[
        {
            "category":"Building & Trades",
            "subcategory":"Plumbing",
            "type":"Services"
        }
    ],
    "sg:phone":"+1 403 288 1111",
    "sg:postcode":"T2B 1N5",
    "sg:province":"AB",
    "sg:tags":[
        "contractor"
    ],
    "wof:name":"Action Auger Canada Inc",
    "wof:placetype":"venue"
},
  "geometry": {"coordinates":[-113.955772,51.037071],"type":"Point"}
}