{
  "type": "Feature",
  "properties": {
    "iso:country":"CA",
    "sg:address":"4473 Orkney Beach Rd",
    "sg:city":"Orillia",
    "sg:classifiers":[
        {
            "category":"Education",
            "subcategory":"School",
            "type":"Public Place"
        }
    ],
    "sg:phone":"+1 705 325 2073",
    "sg:postcode":"L3V 6H7",
    "sg:province":"ON",
    "wof:name":"Bright Horizons Montessori",
    "wof:placetype":"venue"
},
  "geometry": {"coordinates":[-79.418228,44.60659],"type":"Point"}
}