{
  "type": "Feature",
  "properties": {
    "addr:full":"912 Hwy 11 Pinewood ON P0W 1K0",
    "addr:housenumber":"912",
    "addr:postcode":"p0w 1k0",
    "addr:street":"Hwy 11",
    "iso:country":"CA",
    "sg:address":"912 Hwy 11",
    "sg:city":"Pinewood",
    "sg:classifiers":[
        {
            "category":"Building & Trades",
            "subcategory":"Construction",
            "type":"Services"
        }
    ],
    "sg:phone":"+1 807 483 5823",
    "sg:postcode":"P0W 1K0",
    "sg:province":"ON",
    "sg:tags":[
        "excavating",
        "contractor"
    ],
    "wof:name":"Armor Construction",
    "wof:placetype":"venue"
},
  "geometry": {"coordinates":[-94.2829818726,48.7085952759],"type":"Point"}
}