{
  "type": "Feature",
  "properties": {
    "addr:full":"18 Dacotah St St Catharines ON L2R 1Z4",
    "addr:housenumber":"18",
    "addr:postcode":"l2r 1z4",
    "addr:street":"Dacotah St",
    "iso:country":"CA",
    "sg:address":"18 Dacotah St",
    "sg:city":"St Catharines",
    "sg:classifiers":[
        {
            "category":"Personal",
            "subcategory":"Beauty Salon",
            "type":"Services"
        }
    ],
    "sg:phone":"+1 905 684 6833",
    "sg:postcode":"L2R 1Z4",
    "sg:province":"ON",
    "wof:name":"Fulvia's Coiffure",
    "wof:placetype":"venue"
},
  "geometry": {"coordinates":[-79.238838,43.168415],"type":"Point"}
}