{
  "type": "Feature",
  "properties": {
    "addr:full":"3405 Boul Losch Saint-Hubert QC J3Y 5T7",
    "addr:housenumber":"3405",
    "addr:postcode":"j3y 5t7",
    "addr:street":"Boul Losch",
    "iso:country":"CA",
    "sg:address":"3405 Boul Losch",
    "sg:city":"Saint-Hubert",
    "sg:classifiers":[
        {
            "category":"Professional",
            "subcategory":"Business Services",
            "type":"Services"
        }
    ],
    "sg:phone":"+1 450 445 3266",
    "sg:postcode":"J3Y 5T7",
    "sg:province":"QC",
    "sg:tags":[
        "event"
    ],
    "wof:name":"Lettrage Scripsit",
    "wof:placetype":"venue"
},
  "geometry": {"coordinates":[-73.44306899999999,45.500603],"type":"Point"}
}