{
  "type": "Feature",
  "properties": {
    "addr:full":"109 Washington Ave Davidson SK S0G 1A0",
    "addr:housenumber":"109",
    "addr:postcode":"s0g 1a0",
    "addr:street":"Washington Ave",
    "iso:country":"CA",
    "sg:address":"109 Washington Ave",
    "sg:city":"Davidson",
    "sg:classifiers":[
        {
            "category":"Shopping",
            "subcategory":"Jewelry",
            "type":"Retail Goods"
        }
    ],
    "sg:phone":"+1 306 567 2077",
    "sg:postcode":"S0G 1A0",
    "sg:province":"SK",
    "sg:tags":[
        "jeweler"
    ],
    "wof:name":"Golden Image Jewellery",
    "wof:placetype":"venue"
},
  "geometry": {"coordinates":[-105.995986938,51.267364502],"type":"Point"}
}