{
  "type": "Feature",
  "properties": {
    "addr:full":"50 Denton Ave Tillsonburg ON N4G 3W6",
    "addr:housenumber":"50",
    "addr:postcode":"n4g 3w6",
    "addr:street":"Denton Ave",
    "iso:country":"CA",
    "sg:address":"50 Denton Ave",
    "sg:city":"Tillsonburg",
    "sg:classifiers":[
        {
            "category":"Shopping",
            "subcategory":"Clothing, Apparel, & Fashions",
            "type":"Retail Goods"
        }
    ],
    "sg:phone":"+1 519 842 2699",
    "sg:postcode":"N4G 3W6",
    "sg:province":"ON",
    "sg:tags":[
        "dressmaker"
    ],
    "wof:name":"Irene's Sewing Shop",
    "wof:placetype":"venue"
},
  "geometry": {"coordinates":[-80.73394,42.868019],"type":"Point"}
}