{
  "type": "Feature",
  "properties": {
    "addr:full":"1300 6E Av Grand-Mere QC G9T 2J6",
    "addr:housenumber":"1300",
    "addr:postcode":"g9t 2j6",
    "addr:street":"6E Av Grand-Mere",
    "iso:country":"CA",
    "sg:address":"1300 6E Av",
    "sg:city":"Grand-Mere",
    "sg:classifiers":[
        {
            "category":"Retail",
            "subcategory":"Auto Repair",
            "type":"Services"
        }
    ],
    "sg:phone":"+1 819 538 6358",
    "sg:postcode":"G9T 2J6",
    "sg:province":"QC",
    "sg:tags":[
        "repairing",
        "automobile"
    ],
    "wof:name":"Garage Rs Auto Enr",
    "wof:placetype":"venue"
},
  "geometry": {"coordinates":[-72.70066799999999,46.609024],"type":"Point"}
}