{
  "type": "Feature",
  "properties": {
    "addr:full":"1376 Rue Marie-Gendron Carignan QC J3L 3P9",
    "addr:housenumber":"1376",
    "addr:postcode":"j3l 3p9",
    "addr:street":"Rue Marie-Gendron",
    "iso:country":"CA",
    "sg:address":"1376 Rue Marie-Gendron",
    "sg:city":"Carignan",
    "sg:classifiers":[
        {
            "category":"Building & Trades",
            "subcategory":"Landscaping Services",
            "type":"Services"
        }
    ],
    "sg:phone":"+1 450 447 6383",
    "sg:postcode":"J3L 3P9",
    "sg:province":"QC",
    "sg:tags":[
        "landscape",
        "contractor"
    ],
    "wof:name":"Amenagement Distingue Enr",
    "wof:placetype":"venue"
},
  "geometry": {"coordinates":[-73.36655399999999,45.432789],"type":"Point"}
}