{
  "type": "Feature",
  "properties": {
    "addr:full":"292 15th Ave E Prince Albert SK S6V 2N7",
    "addr:housenumber":"292",
    "addr:postcode":"s6v 2n7",
    "addr:street":"15Th Ave E",
    "iso:country":"CA",
    "sg:address":"292 15th Ave E",
    "sg:city":"Prince Albert",
    "sg:classifiers":[
        {
            "category":"Organizations",
            "subcategory":"Community Association",
            "type":"Services"
        }
    ],
    "sg:phone":"+1 306 922 6566",
    "sg:postcode":"S6V 2N7",
    "sg:province":"SK",
    "sg:tags":[
        "fraternal"
    ],
    "wof:name":"Masonic Temple",
    "wof:placetype":"venue"
},
  "geometry": {"coordinates":[-105.705063,53.206875],"type":"Point"}
}