{
  "type": "Feature",
  "properties": {
    "addr:full":"North York ON M2N 5N5",
    "addr:postcode":"m2n 5n5",
    "iso:country":"CA",
    "sg:city":"North York",
    "sg:classifiers":[
        {
            "category":"Professional",
            "subcategory":"Business Services",
            "type":"Services"
        }
    ],
    "sg:phone":"+1 416 221 7777",
    "sg:postcode":"M2N 5N5",
    "sg:province":"ON",
    "sg:tags":[
        "paralegal"
    ],
    "wof:name":"Tickets Traffic Court Defense",
    "wof:placetype":"venue"
},
  "geometry": {"coordinates":[-79.41175800000001,43.764114],"type":"Point"}
}