{
  "type": "Feature",
  "properties": {
    "iso:country":"CA",
    "sg:address":"390 Rue Notre-Dame O # 400",
    "sg:city":"Montreal",
    "sg:classifiers":[
        {
            "category":"Professional",
            "subcategory":"Lawyer & Legal Services",
            "type":"Services"
        }
    ],
    "sg:phone":"+1 514 982 9584",
    "sg:postcode":"H2Y 1T9",
    "sg:province":"QC",
    "sg:tags":[
        "naturalization",
        "immigration"
    ],
    "wof:name":"Dalma Export-Import Ltee",
    "wof:placetype":"venue"
},
  "geometry": {"coordinates":[-73.5524978638,45.5098838806],"type":"Point"}
}