{
  "type": "Feature",
  "properties": {
    "iso:country":"CA",
    "sg:address":"115 Healey Rd",
    "sg:city":"Bolton",
    "sg:classifiers":[
        {
            "category":"Manufacturing",
            "subcategory":"Furniture",
            "type":"Manufacturing & Wholesale Goods"
        }
    ],
    "sg:phone":"+1 905 857 3424",
    "sg:postcode":"L7E 5R3",
    "sg:province":"ON",
    "wof:name":"Trimco Woods Inc",
    "wof:placetype":"venue"
},
  "geometry": {"coordinates":[-79.724541,43.865437],"type":"Point"}
}