{
  "type": "Feature",
  "properties": {
    "addr:full":"4146 Tyndall Ave Victoria BC V8N 3R8",
    "addr:housenumber":"4146",
    "addr:postcode":"v8n 3r8",
    "addr:street":"Tyndall Ave",
    "iso:country":"CA",
    "sg:address":"4146 Tyndall Ave",
    "sg:city":"Victoria",
    "sg:classifiers":[
        {
            "category":"Recreation",
            "type":"Entertainment"
        }
    ],
    "sg:phone":"+1 250 477 0154",
    "sg:postcode":"V8N 3R8",
    "sg:province":"BC",
    "sg:tags":[
        "hall",
        "auditorium"
    ],
    "wof:name":"Gordon Head Community Hall",
    "wof:placetype":"venue"
},
  "geometry": {"coordinates":[-123.364517212,48.428314209],"type":"Point"}
}