{
  "type": "Feature",
  "properties": {
    "addr:full":"226 Murray Rd Ellerslie PE C0B 1J0",
    "addr:housenumber":"226",
    "addr:postcode":"c0b 1j0",
    "addr:street":"Murray Rd",
    "iso:country":"CA",
    "sg:address":"226 Murray Rd",
    "sg:city":"Ellerslie",
    "sg:classifiers":[
        {
            "category":"Professional",
            "subcategory":"Employment Agencies",
            "type":"Services"
        }
    ],
    "sg:phone":"+1 902 831 2202",
    "sg:postcode":"C0B 1J0",
    "sg:province":"PE",
    "sg:tags":[
        "opportunity"
    ],
    "wof:name":"Atlantic Career Advancements",
    "wof:placetype":"venue"
},
  "geometry": {"coordinates":[-63.949745,46.602455],"type":"Point"}
}