{
  "type": "Feature",
  "properties": {
    "addr:full":"2223 Kingston Rd Scarborough ON M1N 1T8",
    "addr:housenumber":"2223",
    "addr:postcode":"m1n 1t8",
    "addr:street":"Kingston Rd",
    "iso:country":"CA",
    "sg:address":"2223 Kingston Rd",
    "sg:city":"Scarborough",
    "sg:classifiers":[
        {
            "category":"Restaurant",
            "type":"Food & Drink"
        }
    ],
    "sg:phone":"+1 416 261 6027",
    "sg:postcode":"M1N 1T8",
    "sg:province":"ON",
    "sg:tags":[
        "shop",
        "coffee",
        "cafe"
    ],
    "wof:name":"Coffee Dome",
    "wof:placetype":"venue"
},
  "geometry": {"coordinates":[-79.2523727417,43.7041816711],"type":"Point"}
}