{
  "type": "Feature",
  "properties": {
    "addr:full":"2161 Gottingen St Halifax NS B3K 3B5",
    "addr:housenumber":"2161",
    "addr:postcode":"b3k 3b5",
    "addr:street":"Gottingen St",
    "iso:country":"CA",
    "sg:address":"2161 Gottingen St",
    "sg:city":"Halifax",
    "sg:classifiers":[
        {
            "category":"Social Services",
            "subcategory":"Child Care",
            "type":"Services"
        }
    ],
    "sg:phone":"+1 902 422 7850",
    "sg:postcode":"B3K 3B5",
    "sg:province":"NS",
    "wof:name":"Mi'Kmaq Child Development Ctr",
    "wof:placetype":"venue"
},
  "geometry": {"coordinates":[-63.5843238831,44.6528511047],"type":"Point"}
}