{
  "type": "Feature",
  "properties": {
    "addr:full":"255 Matchedash St N Orillia ON L3V 4V8",
    "addr:housenumber":"255",
    "addr:postcode":"l3v 4v8",
    "addr:street":"Matchedash St N",
    "iso:country":"CA",
    "sg:address":"255 Matchedash St N",
    "sg:city":"Orillia",
    "sg:classifiers":[
        {
            "category":"Education",
            "subcategory":"School",
            "type":"Public Place"
        }
    ],
    "sg:phone":"+1 705 325 5031",
    "sg:postcode":"L3V 4V8",
    "sg:province":"ON",
    "wof:name":"Hillcrest School",
    "wof:placetype":"venue"
},
  "geometry": {"coordinates":[-79.421829,44.616978],"type":"Point"}
}