{
  "type": "Feature",
  "properties": {
    "addr:full":"16650 Av Bourdages S Saint-Hyacinthe QC J2T 4J9",
    "addr:housenumber":"16650",
    "addr:postcode":"j2t 4j9",
    "addr:street":"Av Bourdages S",
    "iso:country":"CA",
    "sg:address":"16650 Av Bourdages S",
    "sg:city":"Saint-Hyacinthe",
    "sg:classifiers":[
        {
            "category":"Health Services",
            "subcategory":"Nursing And Care Facility",
            "type":"Services"
        }
    ],
    "sg:phone":"+1 450 778 5595",
    "sg:postcode":"J2T 4J9",
    "sg:province":"QC",
    "sg:tags":[
        "home",
        "retirement",
        "community"
    ],
    "wof:name":"Pavillon Marie-Luce-Labossiere",
    "wof:placetype":"venue"
},
  "geometry": {"coordinates":[-72.941467,45.61541],"type":"Point"}
}