{
  "type": "Feature",
  "properties": {
    "addr:full":"Hwy 28 Bancroft ON K0L 1C0",
    "addr:postcode":"k0l 1c0",
    "addr:street":"Hwy 28",
    "iso:country":"CA",
    "sg:address":"Hwy 28",
    "sg:city":"Bancroft",
    "sg:classifiers":[
        {
            "category":"Government",
            "subcategory":"Office",
            "type":"Public Place"
        }
    ],
    "sg:phone":"+1 613 332 3940",
    "sg:postcode":"K0L 1C0",
    "sg:province":"ON",
    "wof:name":"Ontario Natural Resources",
    "wof:placetype":"venue"
},
  "geometry": {"coordinates":[-77.73743399999999,45.066822],"type":"Point"}
}