{
  "type": "Feature",
  "properties": {
    "addr:full":"1114 Mohawk Rd Ancaster ON L9G 3K9",
    "addr:housenumber":"1114",
    "addr:postcode":"l9g 3k9",
    "addr:street":"Mohawk Rd",
    "iso:country":"CA",
    "sg:address":"1114 Mohawk Rd",
    "sg:city":"Ancaster",
    "sg:classifiers":[
        {
            "category":"Organizations",
            "subcategory":"Religious Organization",
            "type":"Services"
        }
    ],
    "sg:phone":"+1 905 648 4943",
    "sg:postcode":"L9G 3K9",
    "sg:province":"ON",
    "sg:tags":[
        "church"
    ],
    "wof:name":"Free Reformed Church Hamilton",
    "wof:placetype":"venue"
},
  "geometry": {"coordinates":[-79.939888,43.232006],"type":"Point"}
}