{
  "type": "Feature",
  "properties": {
    "addr:full":"5666 12 Ave Delta BC V4L 1C4",
    "addr:housenumber":"5666",
    "addr:postcode":"v4l 1c4",
    "addr:street":"12 Ave",
    "iso:country":"CA",
    "sg:address":"5666 12 Ave",
    "sg:city":"Delta",
    "sg:classifiers":[
        {
            "category":"Building & Trades",
            "subcategory":"Equipment Rental",
            "type":"Services"
        }
    ],
    "sg:phone":"+1 604 943 4211",
    "sg:postcode":"V4L 1C4",
    "sg:province":"BC",
    "sg:tags":[
        "party"
    ],
    "wof:name":"12th Avenue Party Rentals",
    "wof:placetype":"venue"
},
  "geometry": {"coordinates":[-123.067078,49.024532],"type":"Point"}
}