{
  "type": "Feature",
  "properties": {
    "addr:full":"139 Rue Saint-Germain E Rimouski QC G5L 1A9",
    "addr:housenumber":"139",
    "addr:postcode":"g5l 1a9",
    "addr:street":"Rue Saint-Germain E",
    "iso:country":"CA",
    "sg:address":"139 Rue Saint-Germain E",
    "sg:city":"Rimouski",
    "sg:classifiers":[
        {
            "category":"Organizations",
            "subcategory":"Professional Association",
            "type":"Services"
        }
    ],
    "sg:phone":"+1 418 723 2843",
    "sg:postcode":"G5L 1A9",
    "sg:province":"QC",
    "wof:name":"Chevaliers DE Colomb",
    "wof:placetype":"venue"
},
  "geometry": {"coordinates":[-68.52146148680001,48.4537200928],"type":"Point"}
}