{
  "type": "Feature",
  "properties": {
    "addr:full":"1551 100th St North Battleford SK S9A 0W3",
    "addr:housenumber":"1551",
    "addr:postcode":"s9a 0w3",
    "addr:street":"100Th St",
    "iso:country":"CA",
    "sg:address":"1551 100th St",
    "sg:city":"North Battleford",
    "sg:classifiers":[
        {
            "category":"Shopping",
            "type":"Retail Goods"
        }
    ],
    "sg:phone":"+1 306 446 1588",
    "sg:postcode":"S9A 0W3",
    "sg:province":"SK",
    "sg:tags":[
        "trophy",
        "medal",
        "award"
    ],
    "wof:name":"Arrow Trophies",
    "wof:placetype":"venue"
},
  "geometry": {"coordinates":[-108.299255,52.780407],"type":"Point"}
}