{
  "type": "Feature",
  "properties": {
    "addr:full":"1740 Commercial Dr Vancouver BC V5N 4A3",
    "addr:housenumber":"1740",
    "addr:postcode":"v5n 4a3",
    "addr:street":"Commercial Dr",
    "iso:country":"CA",
    "sg:address":"1740 Commercial Dr",
    "sg:city":"Vancouver",
    "sg:classifiers":[
        {
            "category":"Personal",
            "subcategory":"Tanning Parlor",
            "type":"Services"
        }
    ],
    "sg:phone":"+1 604 215 2792",
    "sg:postcode":"V5N 4A3",
    "sg:province":"BC",
    "sg:tags":[
        "salon"
    ],
    "wof:name":"Pacific Sun CO",
    "wof:placetype":"venue"
},
  "geometry": {"coordinates":[-123.069489,49.269215],"type":"Point"}
}