{
  "type": "Feature",
  "properties": {
    "addr:full":"69 Dundas St E Napanee ON K7R 1J1",
    "addr:housenumber":"69",
    "addr:postcode":"k7r 1j1",
    "addr:street":"Dundas St",
    "iso:country":"CA",
    "sg:address":"69 Dundas St E",
    "sg:city":"Napanee",
    "sg:classifiers":[
        {
            "category":"Autos & Motor Vehicles",
            "subcategory":"Automobile Sales",
            "type":"Retail Goods"
        }
    ],
    "sg:phone":"+1 613 354 3387",
    "sg:postcode":"K7R 1J1",
    "sg:province":"ON",
    "sg:tags":[
        "car",
        "dealer"
    ],
    "wof:name":"George Lyons Motors Ltd",
    "wof:placetype":"venue"
},
  "geometry": {"coordinates":[-76.9480209351,44.2488136292],"type":"Point"}
}