{
  "type": "Feature",
  "properties": {
    "addr:full":"2918 Bloor St W Etobicoke ON M8X 1B6",
    "addr:housenumber":"2918",
    "addr:postcode":"m8x 1b6",
    "addr:street":"Bloor St W",
    "iso:country":"CA",
    "sg:address":"2918 Bloor St W",
    "sg:city":"Etobicoke",
    "sg:classifiers":[
        {
            "category":"Shopping",
            "subcategory":"Florist",
            "type":"Retail Goods"
        }
    ],
    "sg:phone":"+1 416 232 1731",
    "sg:postcode":"M8X 1B6",
    "sg:province":"ON",
    "wof:name":"Green Garden",
    "wof:placetype":"venue"
},
  "geometry": {"coordinates":[-79.50711099999999,43.648468],"type":"Point"}
}