{
  "type": "Feature",
  "properties": {
    "iso:country":"CA",
    "sg:address":"10 Erie St S",
    "sg:city":"Ridgetown",
    "sg:classifiers":[
        {
            "category":"Restaurant",
            "type":"Food & Drink"
        }
    ],
    "sg:phone":"+1 519 674 1068",
    "sg:postcode":"N0P 2C0",
    "sg:province":"ON",
    "sg:tags":[
        "sandwich"
    ],
    "wof:name":"Subway Sandwiches & Salads",
    "wof:placetype":"venue"
},
  "geometry": {"coordinates":[-81.88622283940001,42.4387359619],"type":"Point"}
}