{
  "type": "Feature",
  "properties": {
    "addr:full":"399 Rue Saint-Jean Quebec QC G1R 1N8",
    "addr:housenumber":"399",
    "addr:postcode":"g1r 1n8",
    "addr:street":"Rue Saint-Jean",
    "iso:country":"CA",
    "sg:address":"399 Rue Saint-Jean",
    "sg:city":"Quebec",
    "sg:classifiers":[
        {
            "category":"Restaurant",
            "type":"Food & Drink"
        }
    ],
    "sg:phone":"+1 418 529 0576",
    "sg:postcode":"G1R 1N8",
    "sg:province":"QC",
    "wof:name":"Restaurant Carthage",
    "wof:placetype":"venue"
},
  "geometry": {"coordinates":[-71.2223892212,46.8089408875],"type":"Point"}
}