{
  "type": "Feature",
  "properties": {
    "addr:full":"6 King St W Havelock ON K0L 1Z0",
    "addr:housenumber":"6",
    "addr:postcode":"k0l 1z0",
    "addr:street":"King St W",
    "iso:country":"CA",
    "sg:address":"6 King St W",
    "sg:city":"Havelock",
    "sg:classifiers":[
        {
            "category":"Home & Garden",
            "subcategory":"Garden Supply",
            "type":"Retail Goods"
        }
    ],
    "sg:phone":"+1 705 778 2233",
    "sg:postcode":"K0L 1Z0",
    "sg:province":"ON",
    "sg:tags":[
        "lawn",
        "mower"
    ],
    "wof:name":"Small Engines Plus",
    "wof:placetype":"venue"
},
  "geometry": {"coordinates":[-77.8861541748,44.4361839294],"type":"Point"}
}