{
  "type": "Feature",
  "properties": {
    "addr:full":"195 West Brown's Rd Huntsville ON P1H 1S2",
    "addr:housenumber":"195",
    "addr:postcode":"p1h 1s2",
    "addr:street":"West Brown'S Rd",
    "iso:country":"CA",
    "sg:address":"195 West Brown's Rd",
    "sg:city":"Huntsville",
    "sg:classifiers":[
        {
            "category":"Building & Trades",
            "subcategory":"Plumbing",
            "type":"Services"
        }
    ],
    "sg:phone":"+1 705 788 1718",
    "sg:postcode":"P1H 1S2",
    "sg:province":"ON",
    "sg:tags":[
        "conditioning",
        "air",
        "system",
        "refrigerating",
        "contractor"
    ],
    "wof:name":"Huntsville Refrigeration",
    "wof:placetype":"venue"
},
  "geometry": {"coordinates":[-79.19369500000001,45.304153],"type":"Point"}
}