{
  "type": "Feature",
  "properties": {
    "addr:full":"Sainte-Foy QC G1V 4M6",
    "addr:postcode":"g1v 4m6",
    "iso:country":"CA",
    "sg:city":"Sainte-Foy",
    "sg:classifiers":[
        {
            "category":"Wholesale",
            "subcategory":"Construction Materials",
            "type":"Manufacturing & Wholesale Goods"
        }
    ],
    "sg:phone":"+1 418 657 5115",
    "sg:postcode":"G1V 4M6",
    "sg:province":"QC",
    "sg:tags":[
        "lumber"
    ],
    "wof:name":"Miradas Produits Forestiers",
    "wof:placetype":"venue"
},
  "geometry": {"coordinates":[-71.281059,46.771248],"type":"Point"}
}