{
  "type": "Feature",
  "properties": {
    "addr:full":"42 Pepper Vine Way North York ON M2J 4J8",
    "addr:housenumber":"42",
    "addr:postcode":"m2j 4j8",
    "addr:street":"Pepper Vine Way",
    "iso:country":"CA",
    "sg:address":"42 Pepper Vine Way",
    "sg:city":"North York",
    "sg:classifiers":[
        {
            "category":"Building & Trades",
            "subcategory":"Cleaning & Sanitation",
            "type":"Services"
        }
    ],
    "sg:phone":"+1 416 498 7505",
    "sg:postcode":"M2J 4J8",
    "sg:province":"ON",
    "sg:tags":[
        "janitor"
    ],
    "wof:name":"Corporate Janitorial Svc",
    "wof:placetype":"venue"
},
  "geometry": {"coordinates":[-79.3690338135,43.7867050171],"type":"Point"}
}