{
  "type": "Feature",
  "properties": {
    "addr:full":"Brampton ON L6S 5N1",
    "addr:postcode":"l6s 5n1",
    "iso:country":"CA",
    "sg:city":"Brampton",
    "sg:classifiers":[
        {
            "category":"Manufacturing",
            "subcategory":"Metals",
            "type":"Manufacturing & Wholesale Goods"
        }
    ],
    "sg:phone":"+1 905 790 2655",
    "sg:postcode":"L6S 5N1",
    "sg:province":"ON",
    "sg:tags":[
        "coating"
    ],
    "wof:name":"R S Coatings Ltd",
    "wof:placetype":"venue"
},
  "geometry": {"coordinates":[-79.706199646,43.7553596497],"type":"Point"}
}