{
  "type": "Feature",
  "properties": {
    "addr:full":"1766 Boul Gaboury Mont-Joli QC G5H 3J2",
    "addr:housenumber":"1766",
    "addr:postcode":"g5h 3j2",
    "addr:street":"Boul Gaboury",
    "iso:country":"CA",
    "sg:address":"1766 Boul Gaboury",
    "sg:city":"Mont-Joli",
    "sg:classifiers":[
        {
            "category":"Food & Beverages",
            "subcategory":"Groceries & Convenience Stores",
            "type":"Retail Goods"
        }
    ],
    "sg:phone":"+1 418 775 2802",
    "sg:postcode":"G5H 3J2",
    "sg:province":"QC",
    "wof:name":"Accommodation 7-23",
    "wof:placetype":"venue"
},
  "geometry": {"coordinates":[-68.1865768433,48.5807037354],"type":"Point"}
}