{
  "type": "Feature",
  "properties": {
    "addr:full":"Dundas ON L9H 6X4",
    "addr:postcode":"l9h 6x4",
    "iso:country":"CA",
    "sg:city":"Dundas",
    "sg:classifiers":[
        {
            "category":"Personal",
            "subcategory":"Beauty Salon",
            "type":"Services"
        }
    ],
    "sg:phone":"+1 905 627 7892",
    "sg:postcode":"L9H 6X4",
    "sg:province":"ON",
    "wof:name":"Haircrafters",
    "wof:placetype":"venue"
},
  "geometry": {"coordinates":[-79.941696167,43.2590065002],"type":"Point"}
}