{
  "type": "Feature",
  "properties": {
    "iso:country":"CA",
    "sg:address":"340 Blake St",
    "sg:city":"Barrie",
    "sg:classifiers":[
        {
            "category":"Health Services",
            "subcategory":"Nursing And Care Facility",
            "type":"Services"
        }
    ],
    "sg:phone":"+1 705 722 3611",
    "sg:postcode":"L4M 1L3",
    "sg:province":"ON",
    "sg:tags":[
        "home",
        "retirement",
        "community"
    ],
    "wof:name":"Barrie Manor",
    "wof:placetype":"venue"
},
  "geometry": {"coordinates":[-79.65564,44.397778],"type":"Point"}
}