{
  "type": "Feature",
  "properties": {
    "addr:full":"Orleans ON K1C 6Z7",
    "addr:postcode":"k1c 6z7",
    "iso:country":"CA",
    "sg:city":"Orleans",
    "sg:classifiers":[
        {
            "category":"Food & Beverages",
            "subcategory":"Liquor & Beverages",
            "type":"Retail Goods"
        }
    ],
    "sg:phone":"+1 613 830 6154",
    "sg:postcode":"K1C 6Z7",
    "sg:province":"ON",
    "sg:tags":[
        "equipment",
        "wine",
        "supply"
    ],
    "wof:name":"Brewers Select",
    "wof:placetype":"venue"
},
  "geometry": {"coordinates":[-75.5487747192,45.4649238586],"type":"Point"}
}