{
  "type": "Feature",
  "properties": {
    "addr:full":"655 Bay St Toronto ON M5G 2K4",
    "addr:housenumber":"655",
    "addr:postcode":"m5g 2k4",
    "addr:street":"Bay St",
    "iso:country":"CA",
    "sg:address":"655 Bay St",
    "sg:city":"Toronto",
    "sg:classifiers":[
        {
            "category":"Real Estate",
            "subcategory":"Real Estate Agent",
            "type":"Services"
        }
    ],
    "sg:phone":"+1 416 977 8838",
    "sg:postcode":"M5G 2K4",
    "sg:province":"ON",
    "wof:name":"Minto Advisors Inc",
    "wof:placetype":"venue"
},
  "geometry": {"coordinates":[-79.38426971440001,43.657459259],"type":"Point"}
}