{
  "type": "Feature",
  "properties": {
    "iso:country":"CA",
    "sg:city":"Sherbrooke",
    "sg:classifiers":[
        {
            "category":"Shopping",
            "subcategory":"Computers & Home Electronics",
            "type":"Retail Goods"
        }
    ],
    "sg:phone":"+1 819 565 3844",
    "sg:postcode":"J1L 1K1",
    "sg:province":"QC",
    "sg:tags":[
        "game",
        "video"
    ],
    "wof:name":"Boutique Eb",
    "wof:placetype":"venue"
},
  "geometry": {"coordinates":[-71.948082,45.403381],"type":"Point"}
}