{
  "type": "Feature",
  "properties": {
    "addr:full":"Nanaimo BC V9R 1T3",
    "addr:postcode":"v9r 1t3",
    "iso:country":"CA",
    "sg:city":"Nanaimo",
    "sg:classifiers":[
        {
            "category":"Retail",
            "subcategory":"Laundry & Dry Cleaning",
            "type":"Services"
        }
    ],
    "sg:phone":"+1 250 754 7344",
    "sg:postcode":"V9R 1T3",
    "sg:province":"BC",
    "sg:tags":[
        "cleaners"
    ],
    "wof:name":"Mr One Hour Cleaners",
    "wof:placetype":"venue"
},
  "geometry": {"coordinates":[-123.94973,49.158817],"type":"Point"}
}