{
  "type": "Feature",
  "properties": {
    "iso:country":"CA",
    "sg:city":"Concord",
    "sg:classifiers":[
        {
            "category":"Autos & Motor Vehicles",
            "subcategory":"Fuel & Gas Station",
            "type":"Retail Goods"
        }
    ],
    "sg:phone":"+1 905 669 2550",
    "sg:postcode":"L4K 1V7",
    "sg:province":"ON",
    "sg:tags":[
        "oil"
    ],
    "wof:name":"Shell Gas Bar",
    "wof:placetype":"venue"
},
  "geometry": {"coordinates":[-79.507179,43.798237],"type":"Point"}
}