{
  "type": "Feature",
  "properties": {
    "iso:country":"CA",
    "sg:address":"427 Bank St",
    "sg:city":"Ottawa",
    "sg:classifiers":[
        {
            "category":"Personal",
            "subcategory":"Shoe Repair & Shine",
            "type":"Services"
        }
    ],
    "sg:phone":"+1 613 232 4700",
    "sg:postcode":"K2P 1Y7",
    "sg:province":"ON",
    "sg:tags":[
        "repairing",
        "boot"
    ],
    "wof:name":"Hackett the Shoemakers",
    "wof:placetype":"venue"
},
  "geometry": {"coordinates":[-75.6936035156,45.4124107361],"type":"Point"}
}