{
  "type": "Feature",
  "properties": {
    "addr:full":"34 Rang Grande Ligne Sainte-Angele-DE-Monnoir QC J0L 1P0",
    "addr:housenumber":"34",
    "addr:postcode":"j0l 1p0",
    "addr:street":"Rang Grande Ligne Sainte-Angele-De-Monnoir",
    "iso:country":"CA",
    "sg:address":"34 Rang Grande Ligne",
    "sg:city":"Sainte-Angele-DE-Monnoir",
    "sg:classifiers":[
        {
            "category":"Restaurant",
            "type":"Food & Drink"
        }
    ],
    "sg:phone":"+1 450 460 4117",
    "sg:postcode":"J0L 1P0",
    "sg:province":"QC",
    "wof:name":"Resto Monic",
    "wof:placetype":"venue"
},
  "geometry": {"coordinates":[-73.1004867554,45.3943710327],"type":"Point"}
}