{
  "type": "Feature",
  "properties": {
    "iso:country":"CA",
    "sg:address":"4290 Boul Wilfrid-Hamel",
    "sg:city":"Quebec",
    "sg:classifiers":[
        {
            "category":"Autos & Motor Vehicles",
            "subcategory":"Fuel & Gas Station",
            "type":"Retail Goods"
        }
    ],
    "sg:phone":"+1 418 872 5996",
    "sg:postcode":"G1P 2J8",
    "sg:province":"QC",
    "sg:tags":[
        "oil"
    ],
    "wof:name":"Olco",
    "wof:placetype":"venue"
},
  "geometry": {"coordinates":[-71.3204650879,46.8062667847],"type":"Point"}
}