{
  "type": "Feature",
  "properties": {
    "addr:full":"2350 Rue Saint-Dominique Jonquiere QC G7X 6L8",
    "addr:housenumber":"2350",
    "addr:postcode":"g7x 6l8",
    "addr:street":"Rue Saint-Dominique",
    "iso:country":"CA",
    "sg:address":"2350 Rue Saint-Dominique",
    "sg:city":"Jonquiere",
    "sg:classifiers":[
        {
            "category":"Restaurant",
            "type":"Food & Drink"
        }
    ],
    "sg:phone":"+1 418 542 0400",
    "sg:postcode":"G7X 6L8",
    "sg:province":"QC",
    "wof:name":"Restaurant Les 400 Coups",
    "wof:placetype":"venue"
},
  "geometry": {"coordinates":[-71.25391399999999,48.414207],"type":"Point"}
}