{
  "type": "Feature",
  "properties": {
    "iso:country":"CA",
    "sg:address":"2350 Rue Saint-Dominique",
    "sg:city":"Jonquiere",
    "sg:classifiers":[
        {
            "category":"Restaurant",
            "type":"Food & Drink"
        }
    ],
    "sg:phone":"+1 418 542 0400",
    "sg:postcode":"G7X 6L8",
    "sg:province":"QC",
    "wof:name":"Restaurant Les 400 Coups",
    "wof:placetype":"venue"
},
  "geometry": {"coordinates":[-71.253914,48.414207],"type":"Point"}
}