{
  "type": "Feature",
  "properties": {
    "addr:full":"Kamloops BC V2C 5X6",
    "addr:postcode":"bc v2c 5x6",
    "iso:country":"CA",
    "sg:city":"Kamloops",
    "sg:classifiers":[
        {
            "category":"Organizations",
            "subcategory":"Professional Association",
            "type":"Services"
        }
    ],
    "sg:phone":"+1 250 828 2231",
    "sg:postcode":"V2C 5X6",
    "sg:province":"BC",
    "wof:name":"Kamloops Masonic Temple Assn",
    "wof:placetype":"venue"
},
  "geometry": {"coordinates":[-120.333328247,50.672077179],"type":"Point"}
}