{
  "type": "Feature",
  "properties": {
    "addr:full":"520 Whitmore Ave E Dauphin MB R7N 2V5",
    "addr:housenumber":"520",
    "addr:postcode":"r7n 2v5",
    "addr:street":"Whitmore Ave E Dauphin",
    "iso:country":"CA",
    "sg:address":"520 Whitmore Ave E",
    "sg:city":"Dauphin",
    "sg:classifiers":[
        {
            "category":"Education",
            "subcategory":"College",
            "type":"Public Place"
        }
    ],
    "sg:phone":"+1 204 622 2023",
    "sg:postcode":"R7N 2V5",
    "sg:province":"MB",
    "sg:tags":[
        "academic",
        "school"
    ],
    "wof:name":"Assiniboine Community College",
    "wof:placetype":"venue"
},
  "geometry": {"coordinates":[-100.041618,51.140472],"type":"Point"}
}