{
  "type": "Feature",
  "properties": {
    "addr:full":"Edmonton AB T5L 4X5",
    "addr:postcode":"t5l 4x5",
    "iso:country":"CA",
    "sg:city":"Edmonton",
    "sg:classifiers":[
        {
            "category":"Restaurant",
            "type":"Food & Drink"
        }
    ],
    "sg:phone":"+1 780 473 5639",
    "sg:postcode":"T5L 4X5",
    "sg:province":"AB",
    "wof:name":"Joey's Only Seafood Restaurant",
    "wof:placetype":"venue"
},
  "geometry": {"coordinates":[-113.532264709,53.59973526],"type":"Point"}
}