{
  "type": "Feature",
  "properties": {
    "addr:full":"North York ON M2M 3X7",
    "addr:postcode":"m2m 3x7",
    "iso:country":"CA",
    "sg:city":"North York",
    "sg:classifiers":[
        {
            "category":"Shopping",
            "subcategory":"Optical Goods",
            "type":"Retail Goods"
        }
    ],
    "sg:phone":"+1 416 222 6002",
    "sg:postcode":"M2M 3X7",
    "sg:province":"ON",
    "sg:tags":[
        "optician"
    ],
    "wof:name":"United Optical",
    "wof:placetype":"venue"
},
  "geometry": {"coordinates":[-79.4194564819,43.7962036133],"type":"Point"}
}