{
  "type": "Feature",
  "properties": {
    "addr:full":"818 Park Ave Beausejour MB R0E 0C0",
    "addr:housenumber":"818",
    "addr:postcode":"r0e 0c0",
    "addr:street":"Park Ave",
    "iso:country":"CA",
    "sg:address":"818 Park Ave",
    "sg:city":"Beausejour",
    "sg:classifiers":[
        {
            "category":"Restaurant",
            "type":"Food & Drink"
        }
    ],
    "sg:phone":"+1 204 268 2697",
    "sg:postcode":"R0E 0C0",
    "sg:province":"MB",
    "wof:name":"Subway Sandwiches & Salads",
    "wof:placetype":"venue"
},
  "geometry": {"coordinates":[-96.509697,50.061779],"type":"Point"}
}