{
  "type": "Feature",
  "properties": {
    "addr:full":"511 Royal Ave New Westminster BC V3L 1H9",
    "addr:housenumber":"511",
    "addr:postcode":"v3l 1h9",
    "addr:street":"Royal Ave",
    "iso:country":"CA",
    "sg:address":"511 Royal Ave",
    "sg:city":"New Westminster",
    "sg:classifiers":[
        {
            "category":"Government",
            "subcategory":"Office",
            "type":"Public Place"
        }
    ],
    "sg:phone":"+1 604 521 3711",
    "sg:postcode":"V3L 1H9",
    "sg:province":"BC",
    "sg:tags":[
        "village"
    ],
    "wof:name":"New Westminster City Hall",
    "wof:placetype":"venue"
},
  "geometry": {"coordinates":[-122.909813,49.206383],"type":"Point"}
}