{
  "type": "Feature",
  "properties": {
    "addr:full":"Prince Rupert BC V8J 1L9",
    "addr:postcode":"v8j 1l9",
    "iso:country":"CA",
    "sg:city":"Prince Rupert",
    "sg:classifiers":[
        {
            "category":"Health Services",
            "subcategory":"Doctor",
            "type":"Services"
        }
    ],
    "sg:phone":"+1 250 622 2811",
    "sg:postcode":"V8J 1L9",
    "sg:province":"BC",
    "sg:tags":[
        "physician",
        "surgeon"
    ],
    "wof:name":"Ryeburn, Michael MD",
    "wof:placetype":"venue"
},
  "geometry": {"coordinates":[-130.32575988799999,54.311958313],"type":"Point"}
}