{
  "type": "Feature",
  "properties": {
    "addr:full":"78 Glenwood Dr Barrie ON L4N 1R4",
    "addr:housenumber":"78",
    "addr:postcode":"l4n 1r4",
    "addr:street":"Glenwood Dr",
    "iso:country":"CA",
    "sg:address":"78 Glenwood Dr",
    "sg:city":"Barrie",
    "sg:classifiers":[
        {
            "category":"Building & Trades",
            "subcategory":"Plumbing",
            "type":"Services"
        }
    ],
    "sg:phone":"+1 705 728 9395",
    "sg:postcode":"L4N 1R4",
    "sg:province":"ON",
    "sg:tags":[
        "contractor"
    ],
    "wof:name":"Action Rooter",
    "wof:placetype":"venue"
},
  "geometry": {"coordinates":[-79.704933,44.4039],"type":"Point"}
}