{
  "type": "Feature",
  "properties": {
    "addr:full":"2504 Bristol Cir Oakville ON L6H 5S1",
    "addr:housenumber":"2504",
    "addr:postcode":"l6h 5s1",
    "addr:street":"Bristol Cir",
    "iso:country":"CA",
    "sg:address":"2504 Bristol Cir",
    "sg:city":"Oakville",
    "sg:classifiers":[
        {
            "category":"Manufacturing",
            "subcategory":"Glass & Minerals",
            "type":"Manufacturing & Wholesale Goods"
        }
    ],
    "sg:phone":"+1 416 740 7932",
    "sg:postcode":"L6H 5S1",
    "sg:province":"ON",
    "sg:tags":[
        "mirror"
    ],
    "wof:name":"Mirror Interiors",
    "wof:placetype":"venue"
},
  "geometry": {"coordinates":[-79.681725,43.519333],"type":"Point"}
}