{
  "type": "Feature",
  "properties": {
    "addr:full":"747 Wedgeport Rd Arcadia NS B0W 1B0",
    "addr:housenumber":"747",
    "addr:postcode":"b0w 1b0",
    "addr:street":"Wedgeport Rd",
    "iso:country":"CA",
    "sg:address":"747 Wedgeport Rd",
    "sg:city":"Arcadia",
    "sg:classifiers":[
        {
            "category":"Shopping",
            "subcategory":"Bicycles & Sporting Goods",
            "type":"Retail Goods"
        }
    ],
    "sg:phone":"+1 902 663 4466",
    "sg:postcode":"B0W 1B0",
    "sg:province":"NS",
    "sg:tags":[
        "tackle",
        "fishing"
    ],
    "wof:name":"Fundy Twine Ltd",
    "wof:placetype":"venue"
},
  "geometry": {"coordinates":[-66.0688323975,43.8255081177],"type":"Point"}
}