{
  "type": "Feature",
  "properties": {
    "addr:full":"38 Av Parent Port-Cartier QC G5B 2G5",
    "addr:postcode":"g5b 2g5",
    "addr:street":"38 Av Parent",
    "iso:country":"CA",
    "sg:address":"38 Av Parent",
    "sg:city":"Port-Cartier",
    "sg:classifiers":[
        {
            "category":"Organizations",
            "subcategory":"Religious Organization",
            "type":"Services"
        }
    ],
    "sg:phone":"+1 418 766 2471",
    "sg:postcode":"G5B 2G5",
    "sg:province":"QC",
    "sg:tags":[
        "church"
    ],
    "wof:name":"Presbytere Sacre-Coeur",
    "wof:placetype":"venue"
},
  "geometry": {"coordinates":[-66.87558,50.019859],"type":"Point"}
}