{
  "type": "Feature",
  "properties": {
    "addr:full":"114 Eagle Dr Delta BC V4M 4G4",
    "addr:housenumber":"114",
    "addr:postcode":"v4m 4g4",
    "addr:street":"Eagle Dr",
    "iso:country":"CA",
    "sg:address":"114 Eagle Dr",
    "sg:city":"Delta",
    "sg:classifiers":[
        {
            "category":"Shopping",
            "subcategory":"Gifts & Souvenirs",
            "type":"Retail Goods"
        }
    ],
    "sg:phone":"+1 604 943 6474",
    "sg:postcode":"V4M 4G4",
    "sg:province":"BC",
    "sg:tags":[
        "indian",
        "art",
        "gallery",
        "dealer"
    ],
    "wof:name":"Qway-Aathia's Native Art Gllry",
    "wof:placetype":"venue"
},
  "geometry": {"coordinates":[-123.096961975,49.0316467285],"type":"Point"}
}