{
  "type": "Feature",
  "properties": {
    "addr:full":"Brian St Limerick SK S0H 2P0",
    "addr:postcode":"s0h 2p0",
    "addr:street":"Brian St",
    "iso:country":"CA",
    "sg:address":"Brian St",
    "sg:city":"Limerick",
    "sg:classifiers":[
        {
            "category":"Education",
            "subcategory":"School",
            "type":"Public Place"
        }
    ],
    "sg:phone":"+1 306 263 2122",
    "sg:postcode":"S0H 2P0",
    "sg:province":"SK",
    "wof:name":"Limerick Public School",
    "wof:placetype":"venue"
},
  "geometry": {"coordinates":[-106.271156,49.652695],"type":"Point"}
}