{
  "type": "Feature",
  "properties": {
    "addr:full":"5131 53rd Ave Sangudo AB T0E 2A0",
    "addr:housenumber":"5131",
    "addr:postcode":"t0e 2a0",
    "addr:street":"53Rd Ave",
    "iso:country":"CA",
    "sg:address":"5131 53rd Ave",
    "sg:city":"Sangudo",
    "sg:classifiers":[
        {
            "category":"Education",
            "subcategory":"School",
            "type":"Public Place"
        }
    ],
    "sg:phone":"+1 780 785 3431",
    "sg:postcode":"T0E 2A0",
    "sg:province":"AB",
    "wof:name":"Sangudo High School",
    "wof:placetype":"venue"
},
  "geometry": {"coordinates":[-114.90612793,53.8896179199],"type":"Point"}
}