{
  "type": "Feature",
  "properties": {
    "addr:full":"140 Rue Saint-Jean-Baptiste E Montmagny QC G5V 1K6",
    "addr:housenumber":"140",
    "addr:postcode":"g5v 1k6",
    "addr:street":"Rue Saint-Jean-Baptiste E",
    "iso:country":"CA",
    "sg:address":"140 Rue Saint-Jean-Baptiste E",
    "sg:city":"Montmagny",
    "sg:classifiers":[
        {
            "category":"Organizations",
            "subcategory":"Religious Organization",
            "type":"Services"
        }
    ],
    "sg:phone":"+1 418 248 3663",
    "sg:postcode":"G5V 1K6",
    "sg:province":"QC",
    "sg:tags":[
        "church"
    ],
    "wof:name":"Fabrique St-Thomas",
    "wof:placetype":"venue"
},
  "geometry": {"coordinates":[-70.556831,46.981117],"type":"Point"}
}