{
  "type": "Feature",
  "properties": {
    "addr:full":"12019 Av Alexis-Carrel Montreal QC H1E 4B8",
    "addr:housenumber":"12019",
    "addr:postcode":"h1e 4b8",
    "addr:street":"Av Alexis-Carrel",
    "iso:country":"CA",
    "sg:address":"12019 Av Alexis-Carrel",
    "sg:city":"Montreal",
    "sg:classifiers":[
        {
            "category":"Shopping",
            "subcategory":"Gifts & Souvenirs",
            "type":"Retail Goods"
        }
    ],
    "sg:phone":"+1 514 881 1609",
    "sg:postcode":"H1E 4B8",
    "sg:province":"QC",
    "sg:tags":[
        "shop"
    ],
    "wof:name":"Cadeaux Eleganza",
    "wof:placetype":"venue"
},
  "geometry": {"coordinates":[-73.58065795900001,45.6391601562],"type":"Point"}
}