{
  "type": "Feature",
  "properties": {
    "addr:full":"220 Goulding Ave North York ON M2R 2P5",
    "addr:housenumber":"220",
    "addr:postcode":"m2r 2p5",
    "addr:street":"Goulding Ave",
    "iso:country":"CA",
    "sg:address":"220 Goulding Ave",
    "sg:city":"North York",
    "sg:classifiers":[
        {
            "category":"Professional",
            "subcategory":"Art Services",
            "type":"Services"
        }
    ],
    "sg:phone":"+1 416 225 6476",
    "sg:postcode":"M2R 2P5",
    "sg:province":"ON",
    "sg:tags":[
        "artist"
    ],
    "wof:name":"Michel Socha Art Studio",
    "wof:placetype":"venue"
},
  "geometry": {"coordinates":[-79.436325,43.788254],"type":"Point"}
}