{
  "type": "Feature",
  "properties": {
    "addr:full":"Surrey BC V4A 9E3",
    "addr:postcode":"v4a 9e3",
    "iso:country":"CA",
    "sg:city":"Surrey",
    "sg:classifiers":[
        {
            "category":"Retail",
            "subcategory":"Laundry & Dry Cleaning",
            "type":"Services"
        }
    ],
    "sg:phone":"+1 604 538 8231",
    "sg:postcode":"V4A 9E3",
    "sg:province":"BC",
    "sg:tags":[
        "cleaners"
    ],
    "wof:name":"Courtesy Cleaners",
    "wof:placetype":"venue"
},
  "geometry": {"coordinates":[-122.80136899999999,49.037582],"type":"Point"}
}