{
  "type": "Feature",
  "properties": {
    "iso:country":"CA",
    "sg:address":"212 17 Ave NE",
    "sg:city":"Calgary",
    "sg:classifiers":[
        {
            "category":"Real Estate",
            "subcategory":"Real Estate Agent",
            "type":"Services"
        }
    ],
    "sg:phone":"+1 403 276 7653",
    "sg:postcode":"T2E 1L8",
    "sg:province":"AB",
    "wof:name":"Bob Dawe Real Estate",
    "wof:placetype":"venue"
},
  "geometry": {"coordinates":[-114.059319,51.06802],"type":"Point"}
}