{
  "type": "Feature",
  "properties": {
    "addr:full":"93 Rue Du College Pont-Rouge QC G3H 3A7",
    "addr:housenumber":"93",
    "addr:postcode":"g3h 3a7",
    "addr:street":"Rue Du College",
    "iso:country":"CA",
    "sg:address":"93 Rue Du College",
    "sg:city":"Pont-Rouge",
    "sg:classifiers":[
        {
            "category":"Home & Garden",
            "subcategory":"Building Materials",
            "type":"Retail Goods"
        }
    ],
    "sg:phone":"+1 418 873 3626",
    "sg:postcode":"G3H 3A7",
    "sg:province":"QC",
    "sg:tags":[
        "plate",
        "window",
        "glazier"
    ],
    "wof:name":"Vitrerie Du College Enr",
    "wof:placetype":"venue"
},
  "geometry": {"coordinates":[-71.694962,46.748722],"type":"Point"}
}