{
  "type": "Feature",
  "properties": {
    "iso:country":"CA",
    "sg:address":"15171 Yonge St",
    "sg:city":"Aurora",
    "sg:classifiers":[
        {
            "category":"Restaurant",
            "type":"Food & Drink"
        }
    ],
    "sg:phone":"+1 905 727 4073",
    "sg:postcode":"L4G 1M1",
    "sg:province":"ON",
    "wof:name":"Trio Steakhouse & Tavern",
    "wof:placetype":"venue"
},
  "geometry": {"coordinates":[-79.466988,43.997898],"type":"Point"}
}