{
  "type": "Feature",
  "properties": {
    "addr:full":"1000 Central Ave Saskatoon SK S7N 2G9",
    "addr:housenumber":"1000",
    "addr:postcode":"s7n 2g9",
    "addr:street":"Central Ave",
    "iso:country":"CA",
    "sg:address":"1000 Central Ave",
    "sg:city":"Saskatoon",
    "sg:classifiers":[
        {
            "category":"Insurance",
            "subcategory":"Insurance Agent",
            "type":"Services"
        }
    ],
    "sg:phone":"+1 306 373 0663",
    "sg:postcode":"S7N 2G9",
    "sg:province":"SK",
    "wof:name":"Rayner Agencies Ltd",
    "wof:placetype":"venue"
},
  "geometry": {"coordinates":[-106.599082947,52.138759613],"type":"Point"}
}