{
  "type": "Feature",
  "properties": {
    "addr:full":"15 Rue Saint-Charles Sainte-Therese QC J7E 2A3",
    "addr:housenumber":"15",
    "addr:postcode":"j7e 2a3",
    "addr:street":"Rue Saint-Charles",
    "iso:country":"CA",
    "sg:address":"15 Rue Saint-Charles",
    "sg:city":"Sainte-Therese",
    "sg:classifiers":[
        {
            "category":"Health Services",
            "subcategory":"Doctor",
            "type":"Services"
        }
    ],
    "sg:phone":"+1 514 235 6253",
    "sg:postcode":"J7E 2A3",
    "sg:province":"QC",
    "sg:tags":[
        "physician",
        "surgeon"
    ],
    "wof:name":"Milot, Jean-Claude DO",
    "wof:placetype":"venue"
},
  "geometry": {"coordinates":[-73.844894,45.640686],"type":"Point"}
}