{
  "type": "Feature",
  "properties": {
    "addr:full":"5480 Av Victoria Montreal QC H3W 2P8",
    "addr:housenumber":"5480",
    "addr:postcode":"h3w 2p8",
    "addr:street":"Av Victoria",
    "iso:country":"CA",
    "sg:address":"5480 Av Victoria",
    "sg:city":"Montreal",
    "sg:classifiers":[
        {
            "category":"Shopping",
            "subcategory":"Pharmacy",
            "type":"Retail Goods"
        }
    ],
    "sg:phone":"+1 514 735 1383",
    "sg:postcode":"H3W 2P8",
    "sg:province":"QC",
    "wof:name":"Pharmacie Vu-Bien Pham",
    "wof:placetype":"venue"
},
  "geometry": {"coordinates":[-73.6309967041,45.4913253784],"type":"Point"}
}