{
  "type": "Feature",
  "properties": {
    "addr:full":"5012 49 Ave Alberta Beach AB T0E 0A0",
    "addr:housenumber":"5012",
    "addr:postcode":"t0e 0a0",
    "addr:street":"49 Ave",
    "iso:country":"CA",
    "sg:address":"5012 49 Ave",
    "sg:city":"Alberta Beach",
    "sg:classifiers":[
        {
            "category":"Organizations",
            "subcategory":"Community Association",
            "type":"Services"
        }
    ],
    "sg:phone":"+1 780 924 3636",
    "sg:postcode":"T0E 0A0",
    "sg:province":"AB",
    "sg:tags":[
        "club"
    ],
    "wof:name":"Alberta Beach & District",
    "wof:placetype":"venue"
},
  "geometry": {"coordinates":[-114.356956,53.673321],"type":"Point"}
}