{
  "type": "Feature",
  "properties": {
    "addr:full":"1515 Rue Marie-Victorin Saint-Bruno QC J3V 6B7",
    "addr:housenumber":"1515",
    "addr:postcode":"j3v 6b7",
    "addr:street":"Rue Marie-Victorin",
    "iso:country":"CA",
    "sg:address":"1515 Rue Marie-Victorin",
    "sg:city":"Saint-Bruno",
    "sg:classifiers":[
        {
            "category":"Bus Charters",
            "type":"Transportation"
        }
    ],
    "sg:phone":"+1 450 653 2040",
    "sg:postcode":"J3V 6B7",
    "sg:province":"QC",
    "sg:tags":[
        "rental"
    ],
    "wof:name":"Grise Transport Inc",
    "wof:placetype":"venue"
},
  "geometry": {"coordinates":[-71.675522,48.471771],"type":"Point"}
}