{
  "type": "Feature",
  "properties": {
    "addr:full":"124 Pugwash Point Rd Pugwash NS B0K 1L0",
    "addr:housenumber":"124",
    "addr:postcode":"b0k 1l0",
    "addr:street":"Pugwash Point Rd",
    "iso:country":"CA",
    "sg:address":"124 Pugwash Point Rd",
    "sg:city":"Pugwash",
    "sg:classifiers":[
        {
            "category":"Utilities",
            "subcategory":"Fuel Oil & Lpg",
            "type":"Services"
        }
    ],
    "sg:phone":"+1 902 243 2286",
    "sg:postcode":"B0K 1L0",
    "sg:province":"NS",
    "sg:tags":[
        "propane",
        "gas"
    ],
    "wof:name":"Eldon F Mundle Propane Gas",
    "wof:placetype":"venue"
},
  "geometry": {"coordinates":[-63.661335,45.849506],"type":"Point"}
}