{
  "type": "Feature",
  "properties": {
    "iso:country":"CA",
    "sg:city":"Harbour Grace",
    "sg:classifiers":[
        {
            "category":"Government",
            "subcategory":"Office",
            "type":"Public Place"
        }
    ],
    "sg:phone":"+1 709 945 3016",
    "sg:postcode":"A0A 2M0",
    "sg:province":"NL",
    "wof:name":"Newfoundland Driver Exam Ofc",
    "wof:placetype":"venue"
},
  "geometry": {"coordinates":[-53.24401474,47.6816673279],"type":"Point"}
}