{
  "type": "Feature",
  "properties": {
    "iso:country":"CA",
    "sg:city":"Saint-Jean-D'Orleans",
    "sg:classifiers":[
        {
            "category":"Retail",
            "subcategory":"Auto Repair",
            "type":"Services"
        }
    ],
    "sg:phone":"+1 418 829 2775",
    "sg:postcode":"G0A 3W0",
    "sg:province":"QC",
    "sg:tags":[
        "repairing",
        "automobile"
    ],
    "wof:name":"Garage Picard",
    "wof:placetype":"venue"
},
  "geometry": {"coordinates":[-72.54965199999999,46.334076],"type":"Point"}
}