{
  "type": "Feature",
  "properties": {
    "iso:country":"CA",
    "sg:address":"4276 Rue Jean-Talon E",
    "sg:city":"Saint-Leonard",
    "sg:classifiers":[
        {
            "category":"Shopping",
            "subcategory":"Clothing, Apparel, & Fashions",
            "type":"Retail Goods"
        }
    ],
    "sg:phone":"+1 514 593 8736",
    "sg:postcode":"H1S 1J7",
    "sg:province":"QC",
    "sg:tags":[
        "lingerie"
    ],
    "wof:name":"Lingerie LA Perla",
    "wof:placetype":"venue"
},
  "geometry": {"coordinates":[-73.595856,45.586124],"type":"Point"}
}