{
  "type": "Feature",
  "properties": {
    "addr:full":"2117 Westville Rd RR 3 New Glasgow NS B2H 5C6",
    "addr:housenumber":"2117",
    "addr:postcode":"b2h 5c6",
    "addr:street":"Westville Rd",
    "iso:country":"CA",
    "sg:address":"2117 Westville Rd RR 3",
    "sg:city":"New Glasgow",
    "sg:classifiers":[
        {
            "category":"Retail",
            "subcategory":"Car Wash",
            "type":"Services"
        }
    ],
    "sg:phone":"+1 902 755 6610",
    "sg:postcode":"B2H 5C6",
    "sg:province":"NS",
    "sg:tags":[
        "polishing",
        "washing"
    ],
    "wof:name":"Kevin's Service Ctr",
    "wof:placetype":"venue"
},
  "geometry": {"coordinates":[-62.6434135437,45.5918388367],"type":"Point"}
}