{
  "type": "Feature",
  "properties": {
    "addr:full":"Surrey BC V3T 2X3",
    "addr:postcode":"v3t 2x3",
    "iso:country":"CA",
    "sg:city":"Surrey",
    "sg:classifiers":[
        {
            "category":"Shopping",
            "subcategory":"Gifts & Souvenirs",
            "type":"Retail Goods"
        }
    ],
    "sg:phone":"+1 604 582 3944",
    "sg:postcode":"V3T 2X3",
    "sg:province":"BC",
    "sg:tags":[
        "shop"
    ],
    "wof:name":"Ukrainian Baba's Gifts & Crfts",
    "wof:placetype":"venue"
},
  "geometry": {"coordinates":[-122.84529113799999,49.1916389465],"type":"Point"}
}