{
  "type": "Feature",
  "properties": {
    "addr:full":"Kitchener ON N2G 4L1",
    "addr:postcode":"n2g 4l1",
    "iso:country":"CA",
    "sg:city":"Kitchener",
    "sg:classifiers":[
        {
            "category":"Food & Beverages",
            "subcategory":"Groceries & Convenience Stores",
            "type":"Retail Goods"
        }
    ],
    "sg:phone":"+1 519 745 5961",
    "sg:postcode":"N2G 4L1",
    "sg:province":"ON",
    "sg:tags":[
        "grocer"
    ],
    "wof:name":"Southwood Mini Mart",
    "wof:placetype":"venue"
},
  "geometry": {"coordinates":[-80.486389,43.439056],"type":"Point"}
}