{
  "type": "Feature",
  "properties": {
    "iso:country":"CA",
    "sg:address":"140 Rue Brassard",
    "sg:city":"Magog",
    "sg:classifiers":[
        {
            "category":"Retail",
            "subcategory":"Auto Repair",
            "type":"Services"
        }
    ],
    "sg:phone":"+1 819 868 1552",
    "sg:postcode":"J1X 1P9",
    "sg:province":"QC",
    "sg:tags":[
        "body",
        "automobile",
        "painting"
    ],
    "wof:name":"Debosselage Orford Inc",
    "wof:placetype":"venue"
},
  "geometry": {"coordinates":[-72.1407546997,45.2671546936],"type":"Point"}
}