{
  "type": "Feature",
  "properties": {
    "addr:full":"5380 Woodwards Rd Richmond BC V7E 1H1",
    "addr:housenumber":"5380",
    "addr:postcode":"v7e 1h1",
    "addr:street":"Woodwards Rd",
    "iso:country":"CA",
    "sg:address":"5380 Woodwards Rd",
    "sg:city":"Richmond",
    "sg:classifiers":[
        {
            "category":"Education",
            "subcategory":"School",
            "type":"Public Place"
        }
    ],
    "sg:phone":"+1 604 668 6198",
    "sg:postcode":"V7E 1H1",
    "sg:province":"BC",
    "wof:name":"Jessie Wowk Elementary School",
    "wof:placetype":"venue"
},
  "geometry": {"coordinates":[-123.16484069800001,49.1438102722],"type":"Point"}
}