{
  "type": "Feature",
  "properties": {
    "iso:country":"CA",
    "sg:address":"539 Jevlan Dr",
    "sg:city":"Woodbridge",
    "sg:classifiers":[
        {
            "category":"Restaurant",
            "type":"Food & Drink"
        }
    ],
    "sg:phone":"+1 905 850 2832",
    "sg:postcode":"L4L 8W1",
    "sg:province":"ON",
    "wof:name":"Alta Rossa",
    "wof:placetype":"venue"
},
  "geometry": {"coordinates":[-79.5492553711,43.8065795898],"type":"Point"}
}