{
  "type": "Feature",
  "properties": {
    "addr:full":"11 Sackville Dr SW Calgary AB T2W 0W3",
    "addr:housenumber":"11",
    "addr:postcode":"t2w 0w3",
    "addr:street":"Sackville Dr Sw",
    "iso:country":"CA",
    "sg:address":"11 Sackville Dr SW",
    "sg:city":"Calgary",
    "sg:classifiers":[
        {
            "category":"Organizations",
            "subcategory":"Professional Association",
            "type":"Services"
        }
    ],
    "sg:phone":"+1 403 255 5922",
    "sg:postcode":"T2W 0W3",
    "sg:province":"AB",
    "wof:name":"Royal Canadian Air Cadets 52",
    "wof:placetype":"venue"
},
  "geometry": {"coordinates":[-114.086174011,50.9583053589],"type":"Point"}
}