{
  "type": "Feature",
  "properties": {
    "addr:full":"Kelowna BC V1Y 9G6",
    "addr:postcode":"v1y 9g6",
    "iso:country":"CA",
    "sg:city":"Kelowna",
    "sg:classifiers":[
        {
            "category":"Professional",
            "subcategory":"Engineering",
            "type":"Services"
        }
    ],
    "sg:phone":"+1 250 762 9993",
    "sg:postcode":"V1Y 9G6",
    "sg:province":"BC",
    "sg:tags":[
        "engineer"
    ],
    "wof:name":"Falcon Engineering Ltd",
    "wof:placetype":"venue"
},
  "geometry": {"coordinates":[-119.46029663100001,49.8805198669],"type":"Point"}
}