{
  "type": "Feature",
  "properties": {
    "addr:full":"Woodbridge ON L4L 9P1",
    "addr:postcode":"l4l 9p1",
    "iso:country":"CA",
    "sg:city":"Woodbridge",
    "sg:classifiers":[
        {
            "category":"Communications",
            "subcategory":"Film & Video Production",
            "type":"Services"
        }
    ],
    "sg:phone":"+1 905 850 6270",
    "sg:postcode":"L4L 9P1",
    "sg:province":"ON",
    "sg:tags":[
        "taping"
    ],
    "wof:name":"Memory Video Productions",
    "wof:placetype":"venue"
},
  "geometry": {"coordinates":[-79.55239899999999,43.810978],"type":"Point"}
}