{
  "type": "Feature",
  "properties": {
    "addr:full":"873 Rue Principale Saint-Valentin QC J0J 2E0",
    "addr:housenumber":"873",
    "addr:postcode":"j0j 2e0",
    "addr:street":"Rue Principale",
    "iso:country":"CA",
    "sg:address":"873 Rue Principale",
    "sg:city":"Saint-Valentin",
    "sg:classifiers":[
        {
            "category":"Freight",
            "type":"Transportation"
        }
    ],
    "sg:phone":"+1 450 291 5128",
    "sg:postcode":"J0J 2E0",
    "sg:province":"QC",
    "sg:tags":[
        "building",
        "house",
        "mover"
    ],
    "wof:name":"Fernand Fallon Transport",
    "wof:placetype":"venue"
},
  "geometry": {"coordinates":[-73.324791,45.128841],"type":"Point"}
}