{
  "type": "Feature",
  "properties": {
    "addr:full":"9941 Rue DE Belle-Riviere Mirabel QC J7N 2X7",
    "addr:housenumber":"9941",
    "addr:postcode":"j7n 2x7",
    "addr:street":"Rue De Belle-Riviere",
    "iso:country":"CA",
    "sg:address":"9941 Rue DE Belle-Riviere",
    "sg:city":"Mirabel",
    "sg:classifiers":[
        {
            "category":"Organizations",
            "subcategory":"Professional Association",
            "type":"Services"
        }
    ],
    "sg:phone":"+1 450 258 3311",
    "sg:postcode":"J7N 2X7",
    "sg:province":"QC",
    "wof:name":"Sclerose En Plaques Section",
    "wof:placetype":"venue"
},
  "geometry": {"coordinates":[-74.09034,45.651325],"type":"Point"}
}