{
  "type": "Feature",
  "properties": {
    "addr:full":"101 Murray St Ottawa ON K1N 5M5",
    "addr:housenumber":"101",
    "addr:postcode":"k1n 5m5",
    "addr:street":"Murray St",
    "iso:country":"CA",
    "sg:address":"101 Murray St",
    "sg:city":"Ottawa",
    "sg:classifiers":[
        {
            "category":"Personal",
            "subcategory":"Beauty Salon",
            "type":"Services"
        }
    ],
    "sg:phone":"+1 613 241 4807",
    "sg:postcode":"K1N 5M5",
    "sg:province":"ON",
    "wof:name":"Scissors Hair Studio",
    "wof:placetype":"venue"
},
  "geometry": {"coordinates":[-75.693123,45.430058],"type":"Point"}
}