{
  "type": "Feature",
  "properties": {
    "addr:full":"Hamilton ON L8W 2E5",
    "addr:postcode":"l8w 2e5",
    "iso:country":"CA",
    "sg:city":"Hamilton",
    "sg:classifiers":[
        {
            "category":"Building & Trades",
            "subcategory":"Landscaping Services",
            "type":"Services"
        }
    ],
    "sg:phone":"+1 905 388 5251",
    "sg:postcode":"L8W 2E5",
    "sg:province":"ON",
    "sg:tags":[
        "landscape",
        "contractor"
    ],
    "wof:name":"Greentario Landscaping Ltd",
    "wof:placetype":"venue"
},
  "geometry": {"coordinates":[-79.832787,43.194668],"type":"Point"}
}