{
  "type": "Feature",
  "properties": {
    "addr:full":"Edmonton AB T5J 1C9",
    "addr:postcode":"t5j 1c9",
    "iso:country":"CA",
    "sg:city":"Edmonton",
    "sg:classifiers":[
        {
            "category":"Organizations",
            "subcategory":"Membership Organization",
            "type":"Services"
        }
    ],
    "sg:phone":"+1 780 425 1050",
    "sg:postcode":"T5J 1C9",
    "sg:province":"AB",
    "sg:tags":[
        "meditation",
        "instruction"
    ],
    "wof:name":"Brahma Kumaris Mediation Ctr",
    "wof:placetype":"venue"
},
  "geometry": {"coordinates":[-113.501289368,53.5416908264],"type":"Point"}
}