{
  "type": "Feature",
  "properties": {
    "iso:country":"CA",
    "sg:city":"Saskatoon",
    "sg:classifiers":[
        {
            "category":"Wholesale",
            "subcategory":"Hardware",
            "type":"Manufacturing & Wholesale Goods"
        }
    ],
    "sg:phone":"+1 306 244 2440",
    "sg:postcode":"S7L 5X1",
    "sg:province":"SK",
    "sg:tags":[
        "steam",
        "specialty"
    ],
    "wof:name":"General Equipment Ltd",
    "wof:placetype":"venue"
},
  "geometry": {"coordinates":[-106.67897,52.164074],"type":"Point"}
}