{
  "type": "Feature",
  "properties": {
    "addr:full":"Mississauga ON L4Y 1Y6",
    "addr:postcode":"l4y 1y6",
    "iso:country":"CA",
    "sg:city":"Mississauga",
    "sg:classifiers":[
        {
            "category":"Autos & Motor Vehicles",
            "subcategory":"Auto Supplies",
            "type":"Retail Goods"
        }
    ],
    "sg:phone":"+1 905 275 8864",
    "sg:postcode":"L4Y 1Y6",
    "sg:province":"ON",
    "sg:tags":[
        "automobile",
        "stereo",
        "radio"
    ],
    "wof:name":"Avn Electronics",
    "wof:placetype":"venue"
},
  "geometry": {"coordinates":[-79.591843,43.593868],"type":"Point"}
}