{
  "type": "Feature",
  "properties": {
    "iso:country":"CA",
    "sg:address":"440 Rue Collard O",
    "sg:city":"Alma",
    "sg:classifiers":[
        {
            "category":"Shopping",
            "subcategory":"Computers & Home Electronics",
            "type":"Retail Goods"
        }
    ],
    "sg:phone":"+1 418 668 4591",
    "sg:postcode":"G8B 1N2",
    "sg:province":"QC",
    "sg:tags":[
        "equipment",
        "dealer"
    ],
    "wof:name":"Megaburo Inc",
    "wof:placetype":"venue"
},
  "geometry": {"coordinates":[-71.6494140625,48.5481414795],"type":"Point"}
}