{
  "type": "Feature",
  "properties": {
    "iso:country":"CA",
    "sg:address":"130 George St",
    "sg:city":"New Glasgow",
    "sg:classifiers":[
        {
            "category":"Restaurant",
            "type":"Food & Drink"
        }
    ],
    "sg:phone":"+1 902 752 0884",
    "sg:postcode":"B2H 2K6",
    "sg:province":"NS",
    "wof:name":"Dock Food Spirits & Ales",
    "wof:placetype":"venue"
},
  "geometry": {"coordinates":[-62.6450119019,45.5895271301],"type":"Point"}
}