{
  "type": "Feature",
  "properties": {
    "iso:country":"CA",
    "sg:city":"North Vancouver",
    "sg:classifiers":[
        {
            "category":"Government",
            "subcategory":"Post Office",
            "type":"Public Place"
        }
    ],
    "sg:phone":"+1 604 982 0272",
    "sg:postcode":"V7J 3V3",
    "sg:province":"BC",
    "wof:name":"Office Services Etc",
    "wof:placetype":"venue"
},
  "geometry": {"coordinates":[-123.032257,49.306],"type":"Point"}
}