{
  "type": "Feature",
  "properties": {
    "addr:full":"930 Quesnel Rd Sturgeon Falls ON P2B 2W3",
    "addr:housenumber":"930",
    "addr:postcode":"p2b 2w3",
    "addr:street":"Quesnel Rd",
    "iso:country":"CA",
    "sg:address":"930 Quesnel Rd",
    "sg:city":"Sturgeon Falls",
    "sg:classifiers":[
        {
            "category":"Travel",
            "subcategory":"Hotels & Motels",
            "type":"Entertainment"
        }
    ],
    "sg:phone":"+1 705 753 2280",
    "sg:postcode":"P2B 2W3",
    "sg:province":"ON",
    "sg:tags":[
        "tourist",
        "accommodation"
    ],
    "wof:name":"Sea Gull Lodge",
    "wof:placetype":"venue"
},
  "geometry": {"coordinates":[-79.94525146479999,46.3495559692],"type":"Point"}
}