{
  "type": "Feature",
  "properties": {
    "addr:full":"14 Tolte Rd Marystown NL A0E 2M0",
    "addr:housenumber":"14",
    "addr:postcode":"a0e 2m0",
    "addr:street":"Tolte Rd",
    "iso:country":"CA",
    "sg:address":"14 Tolte Rd",
    "sg:city":"Marystown",
    "sg:classifiers":[
        {
            "category":"Freight",
            "type":"Transportation"
        }
    ],
    "sg:phone":"+1 709 279 5301",
    "sg:postcode":"A0E 2M0",
    "sg:province":"NL",
    "sg:tags":[
        "septic",
        "trucking"
    ],
    "wof:name":"Mallay's Industrial Svc",
    "wof:placetype":"venue"
},
  "geometry": {"coordinates":[-55.157001,47.16375],"type":"Point"}
}