{
  "type": "Feature",
  "properties": {
    "addr:full":"73 Rue Soucy LA Redemption QC G0J 1P0",
    "addr:housenumber":"73",
    "addr:postcode":"g0j 1p0",
    "addr:street":"Rue Soucy La",
    "iso:country":"CA",
    "sg:address":"73 Rue Soucy",
    "sg:city":"LA Redemption",
    "sg:classifiers":[
        {
            "category":"Organizations",
            "subcategory":"Professional Association",
            "type":"Services"
        }
    ],
    "sg:phone":"+1 418 776 5237",
    "sg:postcode":"G0J 1P0",
    "sg:province":"QC",
    "wof:name":"Otj DE LA Redemption",
    "wof:placetype":"venue"
},
  "geometry": {"coordinates":[-67.87872299999999,48.444546],"type":"Point"}
}