{
  "type": "Feature",
  "properties": {
    "addr:full":"357 Bartos Dr Oakville ON L6K 3E5",
    "addr:housenumber":"357",
    "addr:postcode":"l6k 3e5",
    "addr:street":"Bartos Dr",
    "iso:country":"CA",
    "sg:address":"357 Bartos Dr",
    "sg:city":"Oakville",
    "sg:classifiers":[
        {
            "category":"Education",
            "subcategory":"School",
            "type":"Public Place"
        }
    ],
    "sg:phone":"+1 905 845 0412",
    "sg:postcode":"L6K 3E5",
    "sg:province":"ON",
    "wof:name":"Oakwood Elementary School",
    "wof:placetype":"venue"
},
  "geometry": {"coordinates":[-79.683464,43.446167],"type":"Point"}
}