{
  "type": "Feature",
  "properties": {
    "addr:full":"PO Box 180 Warner AB T0K 2L0",
    "addr:housenumber":"po",
    "addr:postcode":"t0k 2l0",
    "addr:street":"Box 180",
    "iso:country":"CA",
    "sg:address":"PO Box 180",
    "sg:city":"Warner",
    "sg:classifiers":[
        {
            "category":"Education",
            "subcategory":"School",
            "type":"Public Place"
        }
    ],
    "sg:phone":"+1 403 642 2294",
    "sg:postcode":"T0K 2L0",
    "sg:province":"AB",
    "wof:name":"Sunnysite Colony School",
    "wof:placetype":"venue"
},
  "geometry": {"coordinates":[-112.207138,49.288326],"type":"Point"}
}