{
  "type": "Feature",
  "properties": {
    "addr:full":"Etobicoke ON M9V 4J8",
    "addr:postcode":"m9v 4j8",
    "iso:country":"CA",
    "sg:city":"Etobicoke",
    "sg:classifiers":[
        {
            "category":"Manufacturing",
            "subcategory":"Printing",
            "type":"Manufacturing & Wholesale Goods"
        }
    ],
    "sg:phone":"+1 416 741 2228",
    "sg:postcode":"M9V 4J8",
    "sg:province":"ON",
    "sg:tags":[
        "printer"
    ],
    "wof:name":"Sana Printing & Copy",
    "wof:placetype":"venue"
},
  "geometry": {"coordinates":[-79.6052932739,43.7440261841],"type":"Point"}
}