{
  "type": "Feature",
  "properties": {
    "addr:full":"415 Athabasca St E Moose Jaw SK S6H 0L9",
    "addr:housenumber":"415",
    "addr:postcode":"s6h 0l9",
    "addr:street":"Athabasca St E",
    "iso:country":"CA",
    "sg:address":"415 Athabasca St E",
    "sg:city":"Moose Jaw",
    "sg:classifiers":[
        {
            "category":"Food & Beverages",
            "subcategory":"Meat & Fish",
            "type":"Retail Goods"
        }
    ],
    "sg:phone":"+1 306 692 8833",
    "sg:postcode":"S6H 0L9",
    "sg:province":"SK",
    "wof:name":"Fellinger & Sons Meats",
    "wof:placetype":"venue"
},
  "geometry": {"coordinates":[-105.52417755099999,50.3954734802],"type":"Point"}
}