{
  "type": "Feature",
  "properties": {
    "addr:full":"1950 Place Arthur-Buies Montreal QC H1L 3G3",
    "addr:housenumber":"1950",
    "addr:postcode":"h1l 3g3",
    "addr:street":"Place Arthur-Buies",
    "iso:country":"CA",
    "sg:address":"1950 Place Arthur-Buies",
    "sg:city":"Montreal",
    "sg:classifiers":[
        {
            "category":"Building & Trades",
            "subcategory":"Electrical",
            "type":"Services"
        }
    ],
    "sg:phone":"+1 514 354 0578",
    "sg:postcode":"H1L 3G3",
    "sg:province":"QC",
    "sg:tags":[
        "electric",
        "contractor"
    ],
    "wof:name":"Orange Electrique Inc",
    "wof:placetype":"venue"
},
  "geometry": {"coordinates":[-73.51438903810001,45.5920639038],"type":"Point"}
}