{
  "type": "Feature",
  "properties": {
    "addr:full":"SE 35 6 7E LA Broquerie MB R0A 0W0",
    "addr:housenumber":"35 6 7e",
    "addr:postcode":"r0a 0w0",
    "addr:street":"Se",
    "iso:country":"CA",
    "sg:address":"SE 35 6 7E",
    "sg:city":"LA Broquerie",
    "sg:classifiers":[
        {
            "category":"Farming",
            "subcategory":"Farm",
            "type":"Manufacturing & Wholesale Goods"
        }
    ],
    "sg:phone":"+1 204 424 5410",
    "sg:postcode":"R0A 0W0",
    "sg:province":"MB",
    "wof:name":"Albert Vielfaure & Sons Ltd",
    "wof:placetype":"venue"
},
  "geometry": {"coordinates":[-96.51056699999999,49.480671],"type":"Point"}
}