{
  "type": "Feature",
  "properties": {
    "addr:full":"Carstairs AB T0M 0N0",
    "addr:postcode":"t0m 0n0",
    "iso:country":"CA",
    "sg:city":"Carstairs",
    "sg:classifiers":[
        {
            "category":"Building & Trades",
            "subcategory":"Landscaping Services",
            "type":"Services"
        }
    ],
    "sg:phone":"+1 403 337 3119",
    "sg:postcode":"T0M 0N0",
    "sg:province":"AB",
    "sg:tags":[
        "excavating",
        "landscape",
        "contractor"
    ],
    "wof:name":"Carstairs Landscaping & Bobcat",
    "wof:placetype":"venue"
},
  "geometry": {"coordinates":[-114.099838257,51.5645103455],"type":"Point"}
}