{
  "type": "Feature",
  "properties": {
    "iso:country":"CA",
    "sg:address":"141 Larche Ave E",
    "sg:city":"Winnipeg",
    "sg:classifiers":[
        {
            "category":"Retail",
            "subcategory":"Laundry & Dry Cleaning",
            "type":"Services"
        }
    ],
    "sg:phone":"+1 204 224 5882",
    "sg:postcode":"R2C 1A5",
    "sg:province":"MB",
    "wof:name":"B I Baxter Inc",
    "wof:placetype":"venue"
},
  "geometry": {"coordinates":[-97.00053405760001,49.9079055786],"type":"Point"}
}