{
  "type": "Feature",
  "properties": {
    "addr:full":"50 Hastings St E Vancouver BC V6A 1N1",
    "addr:housenumber":"50",
    "addr:postcode":"v6a 1n1",
    "addr:street":"Hastings St E",
    "iso:country":"CA",
    "sg:address":"50 Hastings St E",
    "sg:city":"Vancouver",
    "sg:classifiers":[
        {
            "category":"Shopping",
            "subcategory":"Pharmacy",
            "type":"Retail Goods"
        }
    ],
    "sg:phone":"+1 604 669 5990",
    "sg:postcode":"V6A 1N1",
    "sg:province":"BC",
    "wof:name":"Vancouver Pharmacy",
    "wof:placetype":"venue"
},
  "geometry": {"coordinates":[-123.103347778,49.2812805176],"type":"Point"}
}