{
  "type": "Feature",
  "properties": {
    "iso:country":"CA",
    "sg:address":"3285 Rue Achim",
    "sg:city":"Saint-Laurent",
    "sg:classifiers":[
        {
            "category":"Building & Trades",
            "subcategory":"Construction",
            "type":"Services"
        }
    ],
    "sg:phone":"+1 514 336 3383",
    "sg:postcode":"H4K 1V5",
    "sg:province":"QC",
    "sg:tags":[
        "painter"
    ],
    "wof:name":"K C Painting & Decorating",
    "wof:placetype":"venue"
},
  "geometry": {"coordinates":[-73.7251739502,45.520198822],"type":"Point"}
}