{
  "type": "Feature",
  "properties": {
    "addr:full":"3302 Senkler Rd Belcarra BC V3H 4S3",
    "addr:housenumber":"3302",
    "addr:postcode":"v3h 4s3",
    "addr:street":"Senkler Rd",
    "iso:country":"CA",
    "sg:address":"3302 Senkler Rd",
    "sg:city":"Belcarra",
    "sg:classifiers":[
        {
            "category":"Travel",
            "subcategory":"Campground",
            "type":"Entertainment"
        }
    ],
    "sg:phone":"+1 604 939 2268",
    "sg:postcode":"V3H 4S3",
    "sg:province":"BC",
    "sg:tags":[
        "camp"
    ],
    "wof:name":"Sasamat Outdoor Ctr",
    "wof:placetype":"venue"
},
  "geometry": {"coordinates":[-122.89990997300001,49.3237113953],"type":"Point"}
}