{
  "type": "Feature",
  "properties": {
    "addr:full":"17844 Leslie St Newmarket ON L3Y 3E5",
    "addr:housenumber":"17844",
    "addr:postcode":"l3y 3e5",
    "addr:street":"Leslie St",
    "iso:country":"CA",
    "sg:address":"17844 Leslie St",
    "sg:city":"Newmarket",
    "sg:classifiers":[
        {
            "category":"Retail",
            "subcategory":"Auto Repair",
            "type":"Services"
        }
    ],
    "sg:phone":"+1 905 895 5661",
    "sg:postcode":"L3Y 3E5",
    "sg:province":"ON",
    "sg:tags":[
        "repairing",
        "automobile"
    ],
    "wof:name":"Jim's Autopro",
    "wof:placetype":"venue"
},
  "geometry": {"coordinates":[-79.434181,44.074081],"type":"Point"}
}