{
  "type": "Feature",
  "properties": {
    "addr:full":"Lloydminster SK S9V 0T6",
    "addr:postcode":"s9v 0t6",
    "iso:country":"CA",
    "sg:city":"Lloydminster",
    "sg:classifiers":[
        {
            "category":"Shopping",
            "subcategory":"Computers & Home Electronics",
            "type":"Retail Goods"
        }
    ],
    "sg:phone":"+1 306 825 4555",
    "sg:postcode":"S9V 0T6",
    "sg:province":"SK",
    "sg:tags":[
        "equipment",
        "dealer"
    ],
    "wof:name":"L K Computer Systems",
    "wof:placetype":"venue"
},
  "geometry": {"coordinates":[-104.617043,50.432056],"type":"Point"}
}