{
  "type": "Feature",
  "properties": {
    "addr:full":"75 Rue DE LA Gare #14 St-Sauveur-Des-Monts QC J0R 1R6",
    "addr:housenumber":"75",
    "addr:postcode":"j0r 1r6",
    "addr:street":"Rue De La Gare # 14 St-Sauveur-Des-Monts",
    "iso:country":"CA",
    "sg:address":"75 Rue DE LA Gare #14",
    "sg:city":"St-Sauveur-Des-Monts",
    "sg:classifiers":[
        {
            "category":"Health Services",
            "subcategory":"Optometrist",
            "type":"Services"
        }
    ],
    "sg:phone":"+1 450 227 4141",
    "sg:postcode":"J0R 1R6",
    "sg:province":"QC",
    "wof:name":"Optique St-Sauveur",
    "wof:placetype":"venue"
},
  "geometry": {"coordinates":[-74.1544494629,45.8920631409],"type":"Point"}
}