{
  "type": "Feature",
  "properties": {
    "addr:full":"186 University Park Dr Regina SK S4V 1A3",
    "addr:housenumber":"186",
    "addr:postcode":"s4v 1a3",
    "addr:street":"University Park Dr",
    "iso:country":"CA",
    "sg:address":"186 University Park Dr",
    "sg:city":"Regina",
    "sg:classifiers":[
        {
            "category":"Personal",
            "subcategory":"Beauty Salon",
            "type":"Services"
        }
    ],
    "sg:phone":"+1 306 789 9077",
    "sg:postcode":"S4V 1A3",
    "sg:province":"SK",
    "wof:name":"Shears 2000",
    "wof:placetype":"venue"
},
  "geometry": {"coordinates":[-104.558083,50.432018],"type":"Point"}
}