{
  "type": "Feature",
  "properties": {
    "addr:full":"545 Rue Mcdougall Trois-Rivieres QC G9A 2T2",
    "addr:housenumber":"545",
    "addr:postcode":"g9a 2t2",
    "addr:street":"Rue Mcdougall Trois-Rivieres",
    "iso:country":"CA",
    "sg:address":"545 Rue Mcdougall",
    "sg:city":"Trois-Rivieres",
    "sg:classifiers":[
        {
            "category":"Wholesale",
            "subcategory":"Auto Parts",
            "type":"Manufacturing & Wholesale Goods"
        }
    ],
    "sg:phone":"+1 819 374 5545",
    "sg:postcode":"G9A 2T2",
    "sg:province":"QC",
    "sg:tags":[
        "automobile",
        "supply"
    ],
    "wof:name":"Accessoires D'Auto M Baril",
    "wof:placetype":"venue"
},
  "geometry": {"coordinates":[-72.54892,46.336918],"type":"Point"}
}