{
  "type": "Feature",
  "properties": {
    "addr:full":"SW 7 22 5W Eriksdale MB R0C 0W0",
    "addr:housenumber":"22 5w eriksdale",
    "addr:postcode":"r0c 0w0",
    "addr:street":"Sw 7",
    "iso:country":"CA",
    "sg:address":"SW 7 22 5W",
    "sg:city":"Eriksdale",
    "sg:classifiers":[
        {
            "category":"Retail",
            "subcategory":"Auto Repair",
            "type":"Services"
        }
    ],
    "sg:phone":"+1 204 739 5458",
    "sg:postcode":"R0C 0W0",
    "sg:province":"MB",
    "sg:tags":[
        "repairing",
        "automobile"
    ],
    "wof:name":"R & B Auto Svc",
    "wof:placetype":"venue"
},
  "geometry": {"coordinates":[-98.122299,50.860088],"type":"Point"}
}