{
  "type": "Feature",
  "properties": {
    "addr:full":"1202 St Clair Ave W Toronto ON M6E 1B4",
    "addr:housenumber":"1202",
    "addr:postcode":"m6e 1b4",
    "addr:street":"St Clair Ave W",
    "iso:country":"CA",
    "sg:address":"1202 St Clair Ave W",
    "sg:city":"Toronto",
    "sg:classifiers":[
        {
            "category":"Shopping",
            "subcategory":"Clothing, Apparel, & Fashions",
            "type":"Retail Goods"
        }
    ],
    "sg:phone":"+1 416 652 8080",
    "sg:postcode":"M6E 1B4",
    "sg:province":"ON",
    "sg:tags":[
        "shop",
        "bridal"
    ],
    "wof:name":"Belle Rykiss",
    "wof:placetype":"venue"
},
  "geometry": {"coordinates":[-79.444267,43.677811],"type":"Point"}
}