{
  "type": "Feature",
  "properties": {
    "addr:full":"15203 156 St NW Edmonton AB T6V 1J1",
    "addr:housenumber":"15203",
    "addr:postcode":"t6v 1j1",
    "addr:street":"156 St Nw",
    "iso:country":"CA",
    "sg:address":"15203 156 St NW",
    "sg:city":"Edmonton",
    "sg:classifiers":[
        {
            "category":"Real Estate",
            "subcategory":"Developer",
            "type":"Services"
        }
    ],
    "sg:phone":"+1 780 496 6983",
    "sg:postcode":"T6V 1J1",
    "sg:province":"AB",
    "sg:tags":[
        "cemetery",
        "government"
    ],
    "wof:name":"Northern Lights Cemetery",
    "wof:placetype":"venue"
},
  "geometry": {"coordinates":[-113.59131600000001,53.609879],"type":"Point"}
}