{
  "type": "Feature",
  "properties": {
    "addr:full":"656 Imperial Rd N Guelph ON N1H 7M3",
    "addr:housenumber":"656",
    "addr:postcode":"n1h 7m3",
    "addr:street":"Imperial Rd N",
    "iso:country":"CA",
    "sg:address":"656 Imperial Rd N",
    "sg:city":"Guelph",
    "sg:classifiers":[
        {
            "category":"Building & Trades",
            "subcategory":"Plumbing",
            "type":"Services"
        }
    ],
    "sg:phone":"+1 519 821 4130",
    "sg:postcode":"N1H 7M3",
    "sg:province":"ON",
    "sg:tags":[
        "conditioning",
        "air",
        "system",
        "contractor"
    ],
    "wof:name":"Wellington Comfort Systems Ltd",
    "wof:placetype":"venue"
},
  "geometry": {"coordinates":[-80.30615997309999,43.5435791016],"type":"Point"}
}