{
  "type": "Feature",
  "properties": {
    "addr:full":"Calgary AB T2G 5P6",
    "addr:postcode":"t2g 5p6",
    "iso:country":"CA",
    "sg:city":"Calgary",
    "sg:classifiers":[
        {
            "category":"Professional",
            "subcategory":"Printing & Photocopies",
            "type":"Services"
        }
    ],
    "sg:phone":"+1 403 537 6860",
    "sg:postcode":"T2G 5P6",
    "sg:province":"AB",
    "sg:tags":[
        "duplicating",
        "copying"
    ],
    "wof:name":"Executive Express",
    "wof:placetype":"venue"
},
  "geometry": {"coordinates":[-114.062934876,51.0463447571],"type":"Point"}
}