{
  "type": "Feature",
  "properties": {
    "addr:full":"Saint-Lazare QC J7T 2J1",
    "addr:postcode":"j7t 2j1",
    "iso:country":"CA",
    "sg:city":"Saint-Lazare",
    "sg:classifiers":[
        {
            "category":"Freight",
            "type":"Transportation"
        }
    ],
    "sg:phone":"+1 450 458 4857",
    "sg:postcode":"J7T 2J1",
    "sg:province":"QC",
    "sg:tags":[
        "mover"
    ],
    "wof:name":"Demenagement P Enos Moving",
    "wof:placetype":"venue"
},
  "geometry": {"coordinates":[-74.17693300000001,45.429504],"type":"Point"}
}