{
  "type": "Feature",
  "properties": {
    "addr:full":"27 William St St Catharines ON L2R 5H9",
    "addr:housenumber":"27",
    "addr:postcode":"l2r 5h9",
    "addr:street":"William St",
    "iso:country":"CA",
    "sg:address":"27 William St",
    "sg:city":"St Catharines",
    "sg:classifiers":[
        {
            "category":"Professional",
            "subcategory":"Advertising",
            "type":"Services"
        }
    ],
    "sg:phone":"+1 905 641 3059",
    "sg:postcode":"L2R 5H9",
    "sg:province":"ON",
    "sg:tags":[
        "counselor"
    ],
    "wof:name":"Sure Stroke Advertising Inc",
    "wof:placetype":"venue"
},
  "geometry": {"coordinates":[-79.24821472169999,43.15675354],"type":"Point"}
}