{
  "type": "Feature",
  "properties": {
    "addr:full":"113 Boulder Cres Canmore AB T1W 1L4",
    "addr:housenumber":"113",
    "addr:postcode":"t1w 1l4",
    "addr:street":"Boulder Cres",
    "iso:country":"CA",
    "sg:address":"113 Boulder Cres",
    "sg:city":"Canmore",
    "sg:classifiers":[
        {
            "category":"Home & Garden",
            "subcategory":"Building Materials",
            "type":"Retail Goods"
        }
    ],
    "sg:phone":"+1 403 678 2111",
    "sg:postcode":"T1W 1L4",
    "sg:province":"AB",
    "sg:tags":[
        "mixed",
        "concrete"
    ],
    "wof:name":"Lafarge Construction Materials",
    "wof:placetype":"venue"
},
  "geometry": {"coordinates":[-115.32519531200001,51.0762786865],"type":"Point"}
}