{
  "type": "Feature",
  "properties": {
    "addr:full":"16 Kimberly Dr Kapuskasing ON P5N 1L5",
    "addr:housenumber":"16",
    "addr:postcode":"p5n 1l5",
    "addr:street":"Kimberly Dr",
    "iso:country":"CA",
    "sg:address":"16 Kimberly Dr",
    "sg:city":"Kapuskasing",
    "sg:classifiers":[
        {
            "category":"Personal",
            "subcategory":"Beauty Salon",
            "type":"Services"
        }
    ],
    "sg:phone":"+1 705 337 1088",
    "sg:postcode":"P5N 1L5",
    "sg:province":"ON",
    "wof:name":"Hair Studio By Liza",
    "wof:placetype":"venue"
},
  "geometry": {"coordinates":[-82.434128,49.424103],"type":"Point"}
}