{
  "type": "Feature",
  "properties": {
    "addr:full":"136528 County Rd 40 Chatsworth ON N0H 1G0",
    "addr:housenumber":"136528;40",
    "addr:postcode":"n0h 1g0",
    "addr:street":"County Rd",
    "iso:country":"CA",
    "sg:address":"136528 County Rd 40",
    "sg:city":"Chatsworth",
    "sg:classifiers":[
        {
            "category":"Wholesale",
            "subcategory":"Farm Supplies",
            "type":"Manufacturing & Wholesale Goods"
        }
    ],
    "sg:phone":"+1 519 794 2940",
    "sg:postcode":"N0H 1G0",
    "sg:province":"ON",
    "wof:name":"Pringle Quality Feeds",
    "wof:placetype":"venue"
},
  "geometry": {"coordinates":[-80.8974075317,44.4536552429],"type":"Point"}
}