{
  "type": "Feature",
  "properties": {
    "iso:country":"CA",
    "sg:city":"Toronto",
    "sg:classifiers":[
        {
            "category":"Organizations",
            "subcategory":"Religious Organization",
            "type":"Services"
        }
    ],
    "sg:phone":"+1 416 481 7242",
    "sg:postcode":"M6G 3K8",
    "sg:province":"ON",
    "wof:name":"Sai Baba Book & Info Ctr",
    "wof:placetype":"venue"
},
  "geometry": {"coordinates":[-79.4282608032,43.6792106628],"type":"Point"}
}