{
  "type": "Feature",
  "properties": {
    "iso:country":"CA",
    "sg:address":"73 Centre St S",
    "sg:city":"Oshawa",
    "sg:classifiers":[
        {
            "category":"Professional",
            "subcategory":"Credit Reporting & Collection",
            "type":"Services"
        }
    ],
    "sg:phone":"+1 905 434 6186",
    "sg:postcode":"L1H 4A1",
    "sg:province":"ON",
    "sg:tags":[
        "agency"
    ],
    "wof:name":"Collection Recovery Systems",
    "wof:placetype":"venue"
},
  "geometry": {"coordinates":[-78.864471,43.895077],"type":"Point"}
}