{
  "type": "Feature",
  "properties": {
    "addr:full":"30 Livingston Rd Scarborough ON M1E 1K6",
    "addr:housenumber":"30",
    "addr:postcode":"m1e 1k6",
    "addr:street":"Livingston Rd",
    "iso:country":"CA",
    "sg:address":"30 Livingston Rd",
    "sg:city":"Scarborough",
    "sg:classifiers":[
        {
            "category":"Building & Trades",
            "subcategory":"Construction",
            "type":"Services"
        }
    ],
    "sg:phone":"+1 416 265 8523",
    "sg:postcode":"M1E 1K6",
    "sg:province":"ON",
    "sg:tags":[
        "roofing",
        "contractor"
    ],
    "wof:name":"Red Dog Roofing",
    "wof:placetype":"venue"
},
  "geometry": {"coordinates":[-79.19770812989999,43.7420501709],"type":"Point"}
}