{
  "type": "Feature",
  "properties": {
    "addr:full":"Hamilton ON L8P 4S1",
    "addr:postcode":"l8p 4s1",
    "iso:country":"CA",
    "sg:city":"Hamilton",
    "sg:classifiers":[
        {
            "category":"Food & Beverages",
            "subcategory":"Groceries & Convenience Stores",
            "type":"Retail Goods"
        }
    ],
    "sg:phone":"+1 905 523 4252",
    "sg:postcode":"L8P 4S1",
    "sg:province":"ON",
    "wof:name":"Daisy Mart",
    "wof:placetype":"venue"
},
  "geometry": {"coordinates":[-79.877335,43.257092],"type":"Point"}
}