{
  "type": "Feature",
  "properties": {
    "addr:full":"498 Rue Ste-Elisabeth Saint-Hugues QC J0H 1N0",
    "addr:housenumber":"498",
    "addr:postcode":"j0h 1n0",
    "addr:street":"Rue Ste-Elisabeth",
    "iso:country":"CA",
    "sg:address":"498 Rue Ste-Elisabeth",
    "sg:city":"Saint-Hugues",
    "sg:classifiers":[
        {
            "category":"Bars & Pubs",
            "type":"Food & Drink"
        }
    ],
    "sg:phone":"+1 450 794 2818",
    "sg:postcode":"J0H 1N0",
    "sg:province":"QC",
    "sg:tags":[
        "lounge",
        "cocktail"
    ],
    "wof:name":"Resto-Pub Du Village",
    "wof:placetype":"venue"
},
  "geometry": {"coordinates":[-72.85945129389999,45.7938270569],"type":"Point"}
}