{
  "type": "Feature",
  "properties": {
    "addr:full":"1129 Queens Ave Brandon MB R7A 1L9",
    "addr:housenumber":"1129",
    "addr:postcode":"r7a 1l9",
    "addr:street":"Queens Ave",
    "iso:country":"CA",
    "sg:address":"1129 Queens Ave",
    "sg:city":"Brandon",
    "sg:classifiers":[
        {
            "category":"Government",
            "subcategory":"Office",
            "type":"Public Place"
        }
    ],
    "sg:phone":"+1 204 726 6969",
    "sg:postcode":"R7A 1L9",
    "sg:province":"MB",
    "wof:name":"Land Stewardship Specialist",
    "wof:placetype":"venue"
},
  "geometry": {"coordinates":[-99.9522476196,49.830329895],"type":"Point"}
}