{
  "type": "Feature",
  "properties": {
    "addr:full":"3812 Macleod Trail SE Calgary AB T2G 2R2",
    "addr:housenumber":"3812",
    "addr:postcode":"t2g 2r2",
    "addr:street":"Macleod Trail Se",
    "iso:country":"CA",
    "sg:address":"3812 Macleod Trail SE",
    "sg:city":"Calgary",
    "sg:classifiers":[
        {
            "category":"Shopping",
            "subcategory":"Clothing, Apparel, & Fashions",
            "type":"Retail Goods"
        }
    ],
    "sg:phone":"+1 403 287 3100",
    "sg:postcode":"T2G 2R2",
    "sg:province":"AB",
    "sg:tags":[
        "lingerie"
    ],
    "wof:name":"Adam & Eve's Exotic Boutique",
    "wof:placetype":"venue"
},
  "geometry": {"coordinates":[-114.06060791,51.0210418701],"type":"Point"}
}