{
  "type": "Feature",
  "properties": {
    "addr:full":"Campbell River BC V9W 6K6",
    "addr:postcode":"v9w 6k6",
    "iso:country":"CA",
    "sg:city":"Campbell River",
    "sg:classifiers":[
        {
            "category":"Retail",
            "subcategory":"Veterinary Services",
            "type":"Services"
        }
    ],
    "sg:phone":"+1 250 287 2007",
    "sg:postcode":"V9W 6K6",
    "sg:province":"BC",
    "sg:tags":[
        "veterinarian"
    ],
    "wof:name":"Merecroft Veterinary Clinic",
    "wof:placetype":"venue"
},
  "geometry": {"coordinates":[-125.24716949499999,50.0001869202],"type":"Point"}
}