{
  "type": "Feature",
  "properties": {
    "addr:full":"3737 Av Van Horne Montreal QC H3S 1R9",
    "addr:housenumber":"3737",
    "addr:postcode":"h3s 1r9",
    "addr:street":"Av Van Horne",
    "iso:country":"CA",
    "sg:address":"3737 Av Van Horne",
    "sg:city":"Montreal",
    "sg:classifiers":[
        {
            "category":"Education",
            "subcategory":"School",
            "type":"Public Place"
        }
    ],
    "sg:phone":"+1 514 735 2255",
    "sg:postcode":"H3S 1R9",
    "sg:province":"QC",
    "wof:name":"Free Hebrew For Juniors",
    "wof:placetype":"venue"
},
  "geometry": {"coordinates":[-73.6327056885,45.5003509521],"type":"Point"}
}