{
  "type": "Feature",
  "properties": {
    "addr:full":"15856 Central Ave Inverness NS B0E 1N0",
    "addr:postcode":"15856;b0e 1n0",
    "addr:street":"Central Ave",
    "iso:country":"CA",
    "sg:address":"15856 Central Ave",
    "sg:city":"Inverness",
    "sg:classifiers":[
        {
            "category":"Food & Beverages",
            "subcategory":"Groceries & Convenience Stores",
            "type":"Retail Goods"
        }
    ],
    "sg:phone":"+1 902 258 2789",
    "sg:postcode":"B0E 1N0",
    "sg:province":"NS",
    "sg:tags":[
        "grocer"
    ],
    "wof:name":"Shean CO-OP Ltd",
    "wof:placetype":"venue"
},
  "geometry": {"coordinates":[-61.3062095642,46.2300186157],"type":"Point"}
}