{
  "type": "Feature",
  "properties": {
    "iso:country":"CA",
    "sg:address":"301 Ch Du Ruisseau-Saint-Louis # 227",
    "sg:city":"Marieville",
    "sg:classifiers":[
        {
            "category":"Retail",
            "subcategory":"Veterinary Services",
            "type":"Services"
        }
    ],
    "sg:phone":"+1 450 460 4884",
    "sg:postcode":"J3M 1P1",
    "sg:province":"QC",
    "sg:tags":[
        "veterinarian"
    ],
    "wof:name":"Clinique Vet DE Marieville",
    "wof:placetype":"venue"
},
  "geometry": {"coordinates":[-73.1761398315,45.4524383545],"type":"Point"}
}