{
  "type": "Feature",
  "properties": {
    "iso:country":"CA",
    "sg:address":"105 132 Rte W",
    "sg:city":"Cacouna",
    "sg:classifiers":[
        {
            "category":"Manufacturing",
            "subcategory":"Furniture",
            "type":"Manufacturing & Wholesale Goods"
        }
    ],
    "sg:phone":"+1 418 867 1294",
    "sg:postcode":"G0L 1G0",
    "sg:province":"QC",
    "sg:tags":[
        "equipment",
        "kitchen",
        "cabinet"
    ],
    "wof:name":"Atelier Du Bois & Melamine Enr",
    "wof:placetype":"venue"
},
  "geometry": {"coordinates":[-69.50769805909999,47.909614563],"type":"Point"}
}