{
  "type": "Feature",
  "properties": {
    "addr:full":"18 Front St Pictou NS B0K 1H0",
    "addr:housenumber":"18",
    "addr:postcode":"b0k 1h0",
    "addr:street":"Front St",
    "iso:country":"CA",
    "sg:address":"18 Front St",
    "sg:city":"Pictou",
    "sg:classifiers":[
        {
            "category":"Shopping",
            "subcategory":"Pharmacy",
            "type":"Retail Goods"
        }
    ],
    "sg:phone":"+1 902 485 1600",
    "sg:postcode":"B0K 1H0",
    "sg:province":"NS",
    "wof:name":"Fulmore Pharma Choice",
    "wof:placetype":"venue"
},
  "geometry": {"coordinates":[-62.7084236145,45.6759338379],"type":"Point"}
}