{
  "type": "Feature",
  "properties": {
    "addr:full":"8543 Commerce Crt Burnaby BC V5A 4N4",
    "addr:housenumber":"8543",
    "addr:postcode":"v5a 4n4",
    "addr:street":"Commerce Crt",
    "iso:country":"CA",
    "sg:address":"8543 Commerce Crt",
    "sg:city":"Burnaby",
    "sg:classifiers":[
        {
            "category":"Banks & Credit Unions",
            "subcategory":"Bank",
            "type":"Services"
        }
    ],
    "sg:phone":"+1 604 420 5117",
    "sg:postcode":"V5A 4N4",
    "sg:province":"BC",
    "sg:tags":[
        "machine",
        "business",
        "teller",
        "automated"
    ],
    "wof:name":"DE LA Rue Cash Systems Inc",
    "wof:placetype":"venue"
},
  "geometry": {"coordinates":[-122.916481,49.254871],"type":"Point"}
}