{
  "type": "Feature",
  "properties": {
    "addr:full":"Chilliwack BC V2P 2N9",
    "addr:postcode":"v2p 2n9",
    "iso:country":"CA",
    "sg:city":"Chilliwack",
    "sg:classifiers":[
        {
            "category":"Retail",
            "subcategory":"Self-service Laundry",
            "type":"Services"
        }
    ],
    "sg:phone":"+1 604 795 6595",
    "sg:postcode":"V2P 2N9",
    "sg:province":"BC",
    "wof:name":"Ultra Wash Laundry Ctr",
    "wof:placetype":"venue"
},
  "geometry": {"coordinates":[-121.958748,49.164902],"type":"Point"}
}