{
  "type": "Feature",
  "properties": {
    "iso:country":"CA",
    "sg:address":"200 Ch Riviere Bras Du Nord",
    "sg:city":"Falardeau",
    "sg:classifiers":[
        {
            "category":"Travel",
            "subcategory":"Hotels & Motels",
            "type":"Entertainment"
        }
    ],
    "sg:phone":"+1 418 673 6455",
    "sg:postcode":"G0V 1C0",
    "sg:province":"QC",
    "sg:tags":[
        "organization",
        "skiing",
        "resort"
    ],
    "wof:name":"Station DE Ski Valinouet",
    "wof:placetype":"venue"
},
  "geometry": {"coordinates":[-71.1103363037,48.6209449768],"type":"Point"}
}