{
  "type": "Feature",
  "properties": {
    "addr:full":"16400 Av DE LA Concorde S Saint-Hyacinthe QC J2T 3K9",
    "addr:postcode":"j2t 3k9",
    "addr:street":"Av De La Concorde S",
    "iso:country":"CA",
    "sg:address":"16400 Av DE LA Concorde S",
    "sg:city":"Saint-Hyacinthe",
    "sg:classifiers":[
        {
            "category":"Food & Beverages",
            "subcategory":"Groceries & Convenience Stores",
            "type":"Retail Goods"
        }
    ],
    "sg:phone":"+1 450 774 6298",
    "sg:postcode":"J2T 3K9",
    "sg:province":"QC",
    "wof:name":"Depanneur Lamoureaux Enr",
    "wof:placetype":"venue"
},
  "geometry": {"coordinates":[-72.9359283447,45.6210174561],"type":"Point"}
}