{
  "type": "Feature",
  "properties": {
    "addr:full":"115 Glenmorris St Cambridge ON N1S 2Y8",
    "addr:housenumber":"115",
    "addr:postcode":"n1s 2y8",
    "addr:street":"Glenmorris St",
    "iso:country":"CA",
    "sg:address":"115 Glenmorris St",
    "sg:city":"Cambridge",
    "sg:classifiers":[
        {
            "category":"Recreation",
            "type":"Entertainment"
        }
    ],
    "sg:phone":"+1 519 740 7178",
    "sg:postcode":"N1S 2Y8",
    "sg:province":"ON",
    "sg:tags":[
        "pool",
        "swimming"
    ],
    "wof:name":"George Hancock Pool",
    "wof:placetype":"venue"
},
  "geometry": {"coordinates":[-80.321579,43.346992],"type":"Point"}
}