{
  "type": "Feature",
  "properties": {
    "addr:full":"5215 49 Ave Wetaskiwin AB T9A 0R1",
    "addr:housenumber":"5215",
    "addr:postcode":"t9a 0r1",
    "addr:street":"49 Ave",
    "iso:country":"CA",
    "sg:address":"5215 49 Ave",
    "sg:city":"Wetaskiwin",
    "sg:classifiers":[
        {
            "category":"Health Services",
            "subcategory":"Doctor",
            "type":"Services"
        }
    ],
    "sg:phone":"+1 780 352 7157",
    "sg:postcode":"T9A 0R1",
    "sg:province":"AB",
    "sg:tags":[
        "physician",
        "surgeon"
    ],
    "wof:name":"Jeffery, D A MD",
    "wof:placetype":"venue"
},
  "geometry": {"coordinates":[-113.37912,52.969051],"type":"Point"}
}