{
  "type": "Feature",
  "properties": {
    "addr:full":"PO Box 353 Bay Roberts NL A0A 1G0",
    "addr:housenumber":"po;353",
    "addr:postcode":"a0a 1g0",
    "addr:street":"Box;Bay Roberts",
    "iso:country":"CA",
    "sg:address":"PO Box 353",
    "sg:city":"Bay Roberts",
    "sg:classifiers":[
        {
            "category":"Bus Charters",
            "type":"Transportation"
        }
    ],
    "sg:phone":"+1 709 786 3869",
    "sg:postcode":"A0A 1G0",
    "sg:province":"NL",
    "sg:tags":[
        "rental"
    ],
    "wof:name":"Ed Sullivan Transportation Ltd",
    "wof:placetype":"venue"
},
  "geometry": {"coordinates":[-53.281509,47.583984],"type":"Point"}
}