{
  "type": "Feature",
  "properties": {
    "iso:country":"CA",
    "sg:address":"1172 56 St",
    "sg:city":"Delta",
    "sg:classifiers":[
        {
            "category":"Social Services",
            "subcategory":"Child Care",
            "type":"Services"
        }
    ],
    "sg:phone":"+1 604 943 6331",
    "sg:postcode":"V4L 2A3",
    "sg:province":"BC",
    "wof:name":"Secret Garden Pre-School",
    "wof:placetype":"venue"
},
  "geometry": {"coordinates":[-123.068450928,49.0240287781],"type":"Point"}
}