{
  "type": "Feature",
  "properties": {
    "addr:full":"177 Rue Jean-Juneau Saint-Augustin-DE-Desmaures QC G3A 2W1",
    "addr:housenumber":"177",
    "addr:postcode":"g3a 2w1",
    "addr:street":"Rue Jean-Juneau",
    "iso:country":"CA",
    "sg:address":"177 Rue Jean-Juneau",
    "sg:city":"Saint-Augustin-DE-Desmaures",
    "sg:classifiers":[
        {
            "category":"Retail",
            "subcategory":"Animal Services",
            "type":"Services"
        }
    ],
    "sg:phone":"+1 418 878 5553",
    "sg:postcode":"G3A 2W1",
    "sg:province":"QC",
    "sg:tags":[
        "pet",
        "shop",
        "grooming",
        "washing"
    ],
    "wof:name":"Centre Canin Annie Levesque",
    "wof:placetype":"venue"
},
  "geometry": {"coordinates":[-71.45179748539999,46.7408676147],"type":"Point"}
}