{
  "type": "Feature",
  "properties": {
    "addr:full":"Vancouver BC V6E 4H2",
    "addr:postcode":"v6e 4h2",
    "iso:country":"CA",
    "sg:city":"Vancouver",
    "sg:classifiers":[
        {
            "category":"Real Estate",
            "subcategory":"Real Estate Agent",
            "type":"Services"
        }
    ],
    "sg:phone":"+1 604 687 0605",
    "sg:postcode":"V6E 4H2",
    "sg:province":"BC",
    "sg:tags":[
        "cooperative"
    ],
    "wof:name":"Amicae Housing CO-Operative",
    "wof:placetype":"venue"
},
  "geometry": {"coordinates":[-123.125801,49.282597],"type":"Point"}
}