{
  "type": "Feature",
  "properties": {
    "addr:full":"Richmond BC V6Y 2B6",
    "addr:postcode":"v6y 2b6",
    "iso:country":"CA",
    "sg:city":"Richmond",
    "sg:classifiers":[
        {
            "category":"Home & Garden",
            "subcategory":"Furniture",
            "type":"Retail Goods"
        }
    ],
    "sg:phone":"+1 604 279 0027",
    "sg:postcode":"V6Y 2B6",
    "sg:province":"BC",
    "wof:name":"Bombay CO",
    "wof:placetype":"venue"
},
  "geometry": {"coordinates":[-123.136658,49.166374],"type":"Point"}
}