{
  "type": "Feature",
  "properties": {
    "addr:full":"148 Walby Dr Oakville ON L6L 4E2",
    "addr:housenumber":"148",
    "addr:postcode":"l6l 4e2",
    "addr:street":"Walby Dr",
    "iso:country":"CA",
    "sg:address":"148 Walby Dr",
    "sg:city":"Oakville",
    "sg:classifiers":[
        {
            "category":"Building & Trades",
            "subcategory":"Plumbing",
            "type":"Services"
        }
    ],
    "sg:phone":"+1 905 847 8080",
    "sg:postcode":"L6L 4E2",
    "sg:province":"ON",
    "sg:tags":[
        "refrigeration",
        "contractor"
    ],
    "wof:name":"Thermo Well Systems Inc",
    "wof:placetype":"venue"
},
  "geometry": {"coordinates":[-79.69863100000001,43.409279],"type":"Point"}
}