{
  "type": "Feature",
  "properties": {
    "addr:full":"31 Shortt St York ON M6E 3X6",
    "addr:housenumber":"31",
    "addr:postcode":"m6e 3x6",
    "addr:street":"Shortt St",
    "iso:country":"CA",
    "sg:address":"31 Shortt St",
    "sg:city":"York",
    "sg:classifiers":[
        {
            "category":"Organizations",
            "subcategory":"Professional Association",
            "type":"Services"
        }
    ],
    "sg:phone":"+1 416 783 1350",
    "sg:postcode":"M6E 3X6",
    "sg:province":"ON",
    "wof:name":"Royal Canadian Legion",
    "wof:placetype":"venue"
},
  "geometry": {"coordinates":[-79.45159099999999,43.695827],"type":"Point"}
}