{
  "type": "Feature",
  "properties": {
    "addr:full":"210 Main St S Kenora ON P9N 1T2",
    "addr:housenumber":"210",
    "addr:postcode":"p9n 1t2",
    "addr:street":"Main St S",
    "iso:country":"CA",
    "sg:address":"210 Main St S",
    "sg:city":"Kenora",
    "sg:classifiers":[
        {
            "category":"Shopping",
            "subcategory":"Jewelry",
            "type":"Retail Goods"
        }
    ],
    "sg:phone":"+1 807 468 7922",
    "sg:postcode":"P9N 1T2",
    "sg:province":"ON",
    "sg:tags":[
        "jeweler"
    ],
    "wof:name":"Brennan's Jewellers Ltd",
    "wof:placetype":"venue"
},
  "geometry": {"coordinates":[-94.4912261963,49.766292572],"type":"Point"}
}