{
  "type": "Feature",
  "properties": {
    "addr:full":"4359 Route 640 Harvey York CO NB E6K 2Y1",
    "addr:housenumber":"4359",
    "addr:postcode":"e6k 2y1",
    "addr:street":"Route 640 Harvey",
    "iso:country":"CA",
    "sg:address":"4359 Route 640",
    "sg:city":"Harvey York CO",
    "sg:classifiers":[
        {
            "category":"Building & Trades",
            "subcategory":"Construction",
            "type":"Services"
        }
    ],
    "sg:phone":"+1 506 366 3244",
    "sg:postcode":"E6K 2Y1",
    "sg:province":"NB",
    "sg:tags":[
        "concrete",
        "masonry",
        "contractor"
    ],
    "wof:name":"Jones Masonry Ltd",
    "wof:placetype":"venue"
},
  "geometry": {"coordinates":[-67.014488,45.737919],"type":"Point"}
}