{
  "type": "Feature",
  "properties": {
    "addr:full":"54 3E Av O Sainte-Anne-Des-Monts QC G4V 1J6",
    "addr:housenumber":"54",
    "addr:postcode":"g4v 1j6",
    "addr:street":"3E Av O",
    "iso:country":"CA",
    "sg:address":"54 3E Av O",
    "sg:city":"Sainte-Anne-Des-Monts",
    "sg:classifiers":[
        {
            "category":"Organizations",
            "subcategory":"Professional Association",
            "type":"Services"
        }
    ],
    "sg:phone":"+1 418 763 5909",
    "sg:postcode":"G4V 1J6",
    "sg:province":"QC",
    "wof:name":"Corporation Action Jeunes",
    "wof:placetype":"venue"
},
  "geometry": {"coordinates":[-66.48639678959999,49.1292152405],"type":"Point"}
}