{
  "type": "Feature",
  "properties": {
    "addr:full":"139 Ordze Ave Sherwood Park AB T8B 1M6",
    "addr:housenumber":"139",
    "addr:postcode":"t8b 1m6",
    "addr:street":"Ordze Ave",
    "iso:country":"CA",
    "sg:address":"139 Ordze Ave",
    "sg:city":"Sherwood Park",
    "sg:classifiers":[
        {
            "category":"Banks & Credit Unions",
            "subcategory":"Bank",
            "type":"Services"
        }
    ],
    "sg:phone":"+1 780 449 1612",
    "sg:postcode":"T8B 1M6",
    "sg:province":"AB",
    "wof:name":"Td Canada Trust",
    "wof:placetype":"venue"
},
  "geometry": {"coordinates":[-113.326904297,53.5116195679],"type":"Point"}
}