{
  "type": "Feature",
  "properties": {
    "iso:country":"CA",
    "sg:address":"2300 Yonge St",
    "sg:city":"Toronto",
    "sg:classifiers":[
        {
            "category":"Shopping",
            "subcategory":"Hobbies, Toys, & Games",
            "type":"Retail Goods"
        }
    ],
    "sg:phone":"+1 416 483 3764",
    "sg:postcode":"M4P 1E4",
    "sg:province":"ON",
    "sg:tags":[
        "supply"
    ],
    "wof:name":"Crazy Frog Inc",
    "wof:placetype":"venue"
},
  "geometry": {"coordinates":[-79.3986663818,43.7072372437],"type":"Point"}
}