{
  "type": "Feature",
  "properties": {
    "addr:full":"Blainville QC J7C 3P5",
    "addr:postcode":"j7c 3p5",
    "iso:country":"CA",
    "sg:city":"Blainville",
    "sg:classifiers":[
        {
            "category":"Home & Garden",
            "subcategory":"Home Furnishings",
            "type":"Retail Goods"
        }
    ],
    "sg:phone":"+1 450 979 6650",
    "sg:postcode":"J7C 3P5",
    "sg:province":"QC",
    "sg:tags":[
        "fireplace"
    ],
    "wof:name":"Foyer Design Inc",
    "wof:placetype":"venue"
},
  "geometry": {"coordinates":[-73.871582,45.667793],"type":"Point"}
}