{
  "type": "Feature",
  "properties": {
    "iso:country":"CA",
    "sg:city":"Coquitlam",
    "sg:classifiers":[
        {
            "category":"Travel",
            "subcategory":"Travel Agent",
            "type":"Entertainment"
        }
    ],
    "sg:phone":"+1 604 927 2555",
    "sg:postcode":"V3B 5R5",
    "sg:province":"BC",
    "sg:tags":[
        "agency",
        "bureau"
    ],
    "wof:name":"Sears Travel Svc",
    "wof:placetype":"venue"
},
  "geometry": {"coordinates":[-122.800247,49.277153],"type":"Point"}
}