{
  "type": "Feature",
  "properties": {
    "addr:full":"509 20 Ave SW Calgary AB T2S 0E7",
    "addr:postcode":"t2s 0e7",
    "addr:street":"509 20 Ave Sw",
    "iso:country":"CA",
    "sg:address":"509 20 Ave SW",
    "sg:city":"Calgary",
    "sg:classifiers":[
        {
            "category":"Professional",
            "subcategory":"Lawyer & Legal Services",
            "type":"Services"
        }
    ],
    "sg:phone":"+1 403 228 6666",
    "sg:postcode":"T2S 0E7",
    "sg:province":"AB",
    "sg:tags":[
        "attorney"
    ],
    "wof:name":"Mac Lachlan, L J",
    "wof:placetype":"venue"
},
  "geometry": {"coordinates":[-114.07196,51.035],"type":"Point"}
}