{
  "type": "Feature",
  "properties": {
    "addr:full":"151 Main St Wellington ON K0K 3L0",
    "addr:housenumber":"151",
    "addr:postcode":"k0k 3l0",
    "addr:street":"Main St",
    "iso:country":"CA",
    "sg:address":"151 Main St",
    "sg:city":"Wellington",
    "sg:classifiers":[
        {
            "category":"Shopping",
            "subcategory":"Bicycles & Sporting Goods",
            "type":"Retail Goods"
        }
    ],
    "sg:phone":"+1 613 399 3649",
    "sg:postcode":"K0K 3L0",
    "sg:province":"ON",
    "wof:name":"Reel Thing Fishing Pro Shop",
    "wof:placetype":"venue"
},
  "geometry": {"coordinates":[-77.338013,43.952106],"type":"Point"}
}