{
  "type": "Feature",
  "properties": {
    "iso:country":"CA",
    "sg:address":"703 3rd Ave E",
    "sg:city":"Meadow Lake",
    "sg:classifiers":[
        {
            "category":"Wholesale",
            "subcategory":"Scrap",
            "type":"Manufacturing & Wholesale Goods"
        }
    ],
    "sg:phone":"+1 306 236 4420",
    "sg:postcode":"S9X 1H9",
    "sg:province":"SK",
    "sg:tags":[
        "recycling",
        "center"
    ],
    "wof:name":"Sarcan Recycling",
    "wof:placetype":"venue"
},
  "geometry": {"coordinates":[-108.419624,54.132416],"type":"Point"}
}