{
  "type": "Feature",
  "properties": {
    "addr:full":"370 Old Kingston Rd Scarborough ON M1C 1B6",
    "addr:housenumber":"370",
    "addr:postcode":"m1c 1b6",
    "addr:street":"Old Kingston Rd",
    "iso:country":"CA",
    "sg:address":"370 Old Kingston Rd",
    "sg:city":"Scarborough",
    "sg:classifiers":[
        {
            "category":"Travel",
            "subcategory":"Travel Agent",
            "type":"Entertainment"
        }
    ],
    "sg:phone":"+1 416 281 5300",
    "sg:postcode":"M1C 1B6",
    "sg:province":"ON",
    "sg:tags":[
        "agency",
        "bureau"
    ],
    "wof:name":"Graham's Travel",
    "wof:placetype":"venue"
},
  "geometry": {"coordinates":[-79.17008972169999,43.78383255],"type":"Point"}
}