{
  "type": "Feature",
  "properties": {
    "addr:full":"Greys Rd Belle River PE C0A 1B0",
    "addr:postcode":"c0a 1b0",
    "addr:street":"Greys Rd",
    "iso:country":"CA",
    "sg:address":"Greys Rd",
    "sg:city":"Belle River",
    "sg:classifiers":[
        {
            "category":"Farming",
            "subcategory":"Farm",
            "type":"Manufacturing & Wholesale Goods"
        }
    ],
    "sg:phone":"+1 902 962 3386",
    "sg:postcode":"C0A 1B0",
    "sg:province":"PE",
    "wof:name":"A & R Farms Ltd",
    "wof:placetype":"venue"
},
  "geometry": {"coordinates":[-62.8234634399,45.9816436768],"type":"Point"}
}