{
  "type": "Feature",
  "properties": {
    "addr:full":"206 3rd Ave Warner AB T0K 2L0",
    "addr:housenumber":"206",
    "addr:postcode":"t0k 2l0",
    "addr:street":"3Rd Ave",
    "iso:country":"CA",
    "sg:address":"206 3rd Ave",
    "sg:city":"Warner",
    "sg:classifiers":[
        {
            "category":"Education",
            "subcategory":"Library",
            "type":"Public Place"
        }
    ],
    "sg:phone":"+1 403 642 3988",
    "sg:postcode":"T0K 2L0",
    "sg:province":"AB",
    "wof:name":"Warner Memorial Library",
    "wof:placetype":"venue"
},
  "geometry": {"coordinates":[-112.205696,49.281891],"type":"Point"}
}