{
  "type": "Feature",
  "properties": {
    "addr:full":"1500 Highbury Ave N London ON N5Y 5N7",
    "addr:housenumber":"1500",
    "addr:postcode":"n5y 5n7",
    "addr:street":"Highbury Ave N",
    "iso:country":"CA",
    "sg:address":"1500 Highbury Ave N",
    "sg:city":"London",
    "sg:classifiers":[
        {
            "category":"Building & Trades",
            "subcategory":"Plumbing",
            "type":"Services"
        }
    ],
    "sg:phone":"+1 519 659 4211",
    "sg:postcode":"N5Y 5N7",
    "sg:province":"ON",
    "sg:tags":[
        "conditioning",
        "air",
        "refrigeration",
        "system",
        "contractor"
    ],
    "wof:name":"Cool Zone Svc",
    "wof:placetype":"venue"
},
  "geometry": {"coordinates":[-81.221321,43.031929],"type":"Point"}
}