{
  "type": "Feature",
  "properties": {
    "addr:full":"409 Helicopter Dr St Andrews MB R1A 3P7",
    "addr:housenumber":"409",
    "addr:postcode":"r1a 3p7",
    "addr:street":"Helicopter Dr",
    "iso:country":"CA",
    "sg:address":"409 Helicopter Dr",
    "sg:city":"St Andrews",
    "sg:classifiers":[
        {
            "category":"Airport",
            "type":"Transportation"
        }
    ],
    "sg:phone":"+1 204 338 3630",
    "sg:postcode":"R1A 3P7",
    "sg:province":"MB",
    "sg:tags":[
        "aircraft",
        "maintenance"
    ],
    "wof:name":"Olekson Enterprises",
    "wof:placetype":"venue"
},
  "geometry": {"coordinates":[-97.03271484379999,50.3881454468],"type":"Point"}
}