{
  "type": "Feature",
  "properties": {
    "iso:country":"CA",
    "sg:address":"60 LA Costa Fairway Close",
    "sg:city":"Stony Plain",
    "sg:classifiers":[
        {
            "category":"Shopping",
            "subcategory":"Bicycles & Sporting Goods",
            "type":"Retail Goods"
        }
    ],
    "sg:phone":"+1 780 968 3008",
    "sg:postcode":"T7Z 2A5",
    "sg:province":"AB",
    "wof:name":"Asi Golf",
    "wof:placetype":"venue"
},
  "geometry": {"coordinates":[-113.96099100000001,53.527554],"type":"Point"}
}