{
  "type": "Feature",
  "properties": {
    "addr:full":"Calgary AB T2N 1V8",
    "addr:postcode":"t2n 1v8",
    "iso:country":"CA",
    "sg:city":"Calgary",
    "sg:classifiers":[
        {
            "category":"Health Services",
            "subcategory":"Doctor",
            "type":"Services"
        }
    ],
    "sg:phone":"+1 403 270 3600",
    "sg:postcode":"T2N 1V8",
    "sg:province":"AB",
    "sg:tags":[
        "dentist"
    ],
    "wof:name":"Kensington Dental Care",
    "wof:placetype":"venue"
},
  "geometry": {"coordinates":[-114.08570899999999,51.054478],"type":"Point"}
}