{
  "type": "Feature",
  "properties": {
    "addr:full":"Delta BC V4C 6S3",
    "addr:postcode":"v4c 6s3",
    "iso:country":"CA",
    "sg:city":"Delta",
    "sg:classifiers":[
        {
            "category":"Travel",
            "subcategory":"Travel Agent",
            "type":"Entertainment"
        }
    ],
    "sg:phone":"+1 604 582 0668",
    "sg:postcode":"V4C 6S3",
    "sg:province":"BC",
    "sg:tags":[
        "agency",
        "bureau",
        "promoter"
    ],
    "wof:name":"Royal Heights Tours & Travel",
    "wof:placetype":"venue"
},
  "geometry": {"coordinates":[-122.890365601,49.1757621765],"type":"Point"}
}