{
  "type": "Feature",
  "properties": {
    "addr:full":"3945 Lawrence Ave E Scarborough ON M1G 1R9",
    "addr:housenumber":"3945",
    "addr:postcode":"m1g 1r9",
    "addr:street":"Lawrence Ave E",
    "iso:country":"CA",
    "sg:address":"3945 Lawrence Ave E",
    "sg:city":"Scarborough",
    "sg:classifiers":[
        {
            "category":"Shopping",
            "subcategory":"Clothing, Apparel, & Fashions",
            "type":"Retail Goods"
        }
    ],
    "sg:phone":"+1 416 439 7056",
    "sg:postcode":"M1G 1R9",
    "sg:province":"ON",
    "wof:name":"U & Me Fashion",
    "wof:placetype":"venue"
},
  "geometry": {"coordinates":[-79.203789,43.764339],"type":"Point"}
}