{
  "type": "Feature",
  "properties": {
    "addr:full":"5590 200 St Langley BC V3A 1M5",
    "addr:housenumber":"5590",
    "addr:postcode":"v3a 1m5",
    "addr:street":"200 St",
    "iso:country":"CA",
    "sg:address":"5590 200 St",
    "sg:city":"Langley",
    "sg:classifiers":[
        {
            "category":"Autos & Motor Vehicles",
            "subcategory":"Fuel & Gas Station",
            "type":"Retail Goods"
        }
    ],
    "sg:phone":"+1 604 533 5434",
    "sg:postcode":"V3A 1M5",
    "sg:province":"BC",
    "sg:tags":[
        "oil"
    ],
    "wof:name":"Langley Carwash",
    "wof:placetype":"venue"
},
  "geometry": {"coordinates":[-122.66860200000001,49.104149],"type":"Point"}
}