{
  "type": "Feature",
  "properties": {
    "addr:full":"99 Phillips Rd Port Hope ON L1A 2J6",
    "addr:housenumber":"99",
    "addr:postcode":"l1a 2j6",
    "addr:street":"Phillips Rd",
    "iso:country":"CA",
    "sg:address":"99 Phillips Rd",
    "sg:city":"Port Hope",
    "sg:classifiers":[
        {
            "category":"Real Estate",
            "subcategory":"Real Estate Operator",
            "type":"Services"
        }
    ],
    "sg:phone":"+1 905 885 2017",
    "sg:postcode":"L1A 2J6",
    "sg:province":"ON",
    "sg:tags":[
        "apartment"
    ],
    "wof:name":"Concord Apartments",
    "wof:placetype":"venue"
},
  "geometry": {"coordinates":[-78.287254,43.967476],"type":"Point"}
}