{
  "type": "Feature",
  "properties": {
    "addr:full":"Montreal QC H4A 1E1",
    "addr:postcode":"h4a 1e1",
    "iso:country":"CA",
    "sg:city":"Montreal",
    "sg:classifiers":[
        {
            "category":"Professional",
            "subcategory":"Business Services",
            "type":"Services"
        }
    ],
    "sg:phone":"+1 514 481 6699",
    "sg:postcode":"H4A 1E1",
    "sg:province":"QC",
    "sg:tags":[
        "notary"
    ],
    "wof:name":"Silverstone, Joseph",
    "wof:placetype":"venue"
},
  "geometry": {"coordinates":[-73.622688,45.475964],"type":"Point"}
}