{
  "type": "Feature",
  "properties": {
    "addr:full":"1601 Ellesmere Rd Scarborough ON M1P 2Y3",
    "addr:housenumber":"1601",
    "addr:postcode":"m1p 2y3",
    "addr:street":"Ellesmere Rd",
    "iso:country":"CA",
    "sg:address":"1601 Ellesmere Rd",
    "sg:city":"Scarborough",
    "sg:classifiers":[
        {
            "category":"Food & Beverages",
            "subcategory":"Bakery",
            "type":"Retail Goods"
        }
    ],
    "sg:phone":"+1 416 438 4214",
    "sg:postcode":"M1P 2Y3",
    "sg:province":"ON",
    "sg:tags":[
        "butchering"
    ],
    "wof:name":"But N' Ben Butchers",
    "wof:placetype":"venue"
},
  "geometry": {"coordinates":[-79.25256299999999,43.771744],"type":"Point"}
}