{
  "type": "Feature",
  "properties": {
    "addr:full":"2250 Rang Saint-Mathieu E Shawinigan-Sud QC G9N 6T5",
    "addr:housenumber":"2250",
    "addr:postcode":"g9n 6t5",
    "addr:street":"Rang Saint-Mathieu E Shawinigan-Sud",
    "iso:country":"CA",
    "sg:address":"2250 Rang Saint-Mathieu E",
    "sg:city":"Shawinigan-Sud",
    "sg:classifiers":[
        {
            "category":"Professional",
            "subcategory":"Advertising",
            "type":"Services"
        }
    ],
    "sg:phone":"+1 819 537 9172",
    "sg:postcode":"G9N 6T5",
    "sg:province":"QC",
    "sg:tags":[
        "distributing",
        "sample"
    ],
    "wof:name":"Distribution Clap",
    "wof:placetype":"venue"
},
  "geometry": {"coordinates":[-72.71563,46.537495],"type":"Point"}
}