{
  "type": "Feature",
  "properties": {
    "addr:full":"225 Railway Ave E # C Fox Valley SK S0N 0V0",
    "addr:housenumber":"225",
    "addr:postcode":"s0n 0v0",
    "addr:street":"Railway Ave E # C Fox",
    "iso:country":"CA",
    "sg:address":"225 Railway Ave E # C",
    "sg:city":"Fox Valley",
    "sg:classifiers":[
        {
            "category":"Freight",
            "type":"Transportation"
        }
    ],
    "sg:phone":"+1 306 666 3010",
    "sg:postcode":"S0N 0V0",
    "sg:province":"SK",
    "sg:tags":[
        "grain",
        "elevator"
    ],
    "wof:name":"N M Paterson & Sons Ltd",
    "wof:placetype":"venue"
},
  "geometry": {"coordinates":[-109.48082700000001,50.463871],"type":"Point"}
}