{
  "type": "Feature",
  "properties": {
    "addr:full":"7621 Macdonald Rd Delta BC V4G 1N3",
    "addr:housenumber":"7621",
    "addr:postcode":"v4g 1n3",
    "addr:street":"Macdonald Rd",
    "iso:country":"CA",
    "sg:address":"7621 Macdonald Rd",
    "sg:city":"Delta",
    "sg:classifiers":[
        {
            "category":"Manufacturing",
            "subcategory":"Tools & Machinery",
            "type":"Manufacturing & Wholesale Goods"
        }
    ],
    "sg:phone":"+1 604 940 2233",
    "sg:postcode":"V4G 1N3",
    "sg:province":"BC",
    "sg:tags":[
        "equipment",
        "baker"
    ],
    "wof:name":"Unifiller Systems Inc",
    "wof:placetype":"venue"
},
  "geometry": {"coordinates":[-123.037910461,49.1377983093],"type":"Point"}
}