{
  "type": "Feature",
  "properties": {
    "addr:full":"700 Priestman St Fredericton NB E3B 3B7",
    "addr:housenumber":"700",
    "addr:postcode":"e3b 3b7",
    "addr:street":"Priestman St",
    "iso:country":"CA",
    "sg:address":"700 Priestman St",
    "sg:city":"Fredericton",
    "sg:classifiers":[
        {
            "category":"Health Services",
            "subcategory":"Hospital",
            "type":"Services"
        }
    ],
    "sg:phone":"+1 506 452 5400",
    "sg:postcode":"E3B 3B7",
    "sg:province":"NB",
    "wof:name":"Dr Everett Chalmers Hospital",
    "wof:placetype":"venue"
},
  "geometry": {"coordinates":[-66.652641,45.939346],"type":"Point"}
}