{
  "type": "Feature",
  "properties": {
    "iso:country":"CA",
    "sg:city":"Calgary",
    "sg:classifiers":[
        {
            "category":"Manufacturing",
            "subcategory":"Musical Instruments",
            "type":"Manufacturing & Wholesale Goods"
        }
    ],
    "sg:phone":"+1 403 291 4222",
    "sg:postcode":"T2E 7T1",
    "sg:province":"AB",
    "wof:name":"Adam Shaper Tips Ltd",
    "wof:placetype":"venue"
},
  "geometry": {"coordinates":[-114.009315491,51.0784568787],"type":"Point"}
}