{
  "type": "Feature",
  "properties": {
    "addr:full":"444 Milltown Blvd St Stephen NB E3L 1J8",
    "addr:housenumber":"444",
    "addr:postcode":"e3l 1j8",
    "addr:street":"Milltown Blvd",
    "iso:country":"CA",
    "sg:address":"444 Milltown Blvd",
    "sg:city":"St Stephen",
    "sg:classifiers":[
        {
            "category":"Organizations",
            "subcategory":"Community Association",
            "type":"Services"
        }
    ],
    "sg:phone":"+1 506 466 9022",
    "sg:postcode":"E3L 1J8",
    "sg:province":"NB",
    "sg:tags":[
        "club"
    ],
    "wof:name":"Royal Canadian Legion Br 48",
    "wof:placetype":"venue"
},
  "geometry": {"coordinates":[-67.2964096069,45.1740036011],"type":"Point"}
}