{
  "type": "Feature",
  "properties": {
    "addr:full":"Vancouver BC V6E 2C2",
    "addr:postcode":"v6e 2c2",
    "iso:country":"CA",
    "sg:city":"Vancouver",
    "sg:classifiers":[
        {
            "category":"Banks & Credit Unions",
            "subcategory":"Investment Brokerage",
            "type":"Services"
        }
    ],
    "sg:phone":"+1 604 682 6418",
    "sg:postcode":"V6E 2C2",
    "sg:province":"BC",
    "sg:tags":[
        "stock",
        "broker",
        "bond"
    ],
    "wof:name":"Hot Stocks",
    "wof:placetype":"venue"
},
  "geometry": {"coordinates":[-123.13339999999999,49.284042],"type":"Point"}
}