{
  "type": "Feature",
  "properties": {
    "iso:country":"CA",
    "sg:address":"1280 Rue Des Cascades O",
    "sg:city":"Saint-Hyacinthe",
    "sg:classifiers":[
        {
            "category":"Manufacturing",
            "subcategory":"Tools & Machinery",
            "type":"Manufacturing & Wholesale Goods"
        }
    ],
    "sg:phone":"+1 450 774 7188",
    "sg:postcode":"J2S 3H1",
    "sg:province":"QC",
    "sg:tags":[
        "optical"
    ],
    "wof:name":"Lunetterie New Look Inc",
    "wof:placetype":"venue"
},
  "geometry": {"coordinates":[-72.944405,45.625645],"type":"Point"}
}