{
  "type": "Feature",
  "properties": {
    "addr:full":"127 Richhill Ave W Elkhorn MB R0M 0N0",
    "addr:housenumber":"127",
    "addr:postcode":"r0m 0n0",
    "addr:street":"Richhill Ave W",
    "iso:country":"CA",
    "sg:address":"127 Richhill Ave W",
    "sg:city":"Elkhorn",
    "sg:classifiers":[
        {
            "category":"Farming",
            "subcategory":"Farm & Veterinary Services",
            "type":"Manufacturing & Wholesale Goods"
        }
    ],
    "sg:phone":"+1 204 845 2070",
    "sg:postcode":"R0M 0N0",
    "sg:province":"MB",
    "sg:tags":[
        "seed",
        "grain",
        "cleaning"
    ],
    "wof:name":"Elkhorn Seeds & Supplies",
    "wof:placetype":"venue"
},
  "geometry": {"coordinates":[-101.230705,49.977234],"type":"Point"}
}