{
  "type": "Feature",
  "properties": {
    "addr:full":"Sleeman ON P0W 1M0",
    "addr:postcode":"p0w 1m0",
    "iso:country":"CA",
    "sg:city":"Sleeman",
    "sg:classifiers":[
        {
            "category":"Building & Trades",
            "subcategory":"Construction",
            "type":"Services"
        }
    ],
    "sg:phone":"+1 807 488 5526",
    "sg:postcode":"P0W 1M0",
    "sg:province":"ON",
    "sg:tags":[
        "contractor",
        "general"
    ],
    "wof:name":"Larsen Construction",
    "wof:placetype":"venue"
},
  "geometry": {"coordinates":[-94.4399185181,48.7221412659],"type":"Point"}
}