{
  "type": "Feature",
  "properties": {
    "iso:country":"CA",
    "sg:address":"1910 Old Prescott Rd",
    "sg:city":"Greely",
    "sg:classifiers":[
        {
            "category":"Wholesale",
            "subcategory":"Construction Materials",
            "type":"Manufacturing & Wholesale Goods"
        }
    ],
    "sg:phone":"+1 613 821 6090",
    "sg:postcode":"K4P 1L4",
    "sg:province":"ON",
    "sg:tags":[
        "sand",
        "gravel"
    ],
    "wof:name":"D & G Landscaping Sand Pit",
    "wof:placetype":"venue"
},
  "geometry": {"coordinates":[-75.5612792969,45.2363548279],"type":"Point"}
}