{
  "type": "Feature",
  "properties": {
    "addr:full":"304 Elizabeth St Guelph ON N1E 2X7",
    "addr:housenumber":"304",
    "addr:postcode":"n1e 2x7",
    "addr:street":"Elizabeth St",
    "iso:country":"CA",
    "sg:address":"304 Elizabeth St",
    "sg:city":"Guelph",
    "sg:classifiers":[
        {
            "category":"Retail",
            "subcategory":"Auto Repair",
            "type":"Services"
        }
    ],
    "sg:phone":"+1 519 824 6281",
    "sg:postcode":"N1E 2X7",
    "sg:province":"ON",
    "sg:tags":[
        "repairing",
        "automobile"
    ],
    "wof:name":"Frank's Custom Auto Repair",
    "wof:placetype":"venue"
},
  "geometry": {"coordinates":[-80.23284099999999,43.554836],"type":"Point"}
}