{
  "type": "Feature",
  "properties": {
    "addr:full":"509 Rue DE L'Ecole Saint-Narcisse-DE-Beaurivage QC G0S 1W0",
    "addr:housenumber":"509",
    "addr:postcode":"g0s 1w0",
    "addr:street":"Rue De L'Ecole",
    "iso:country":"CA",
    "sg:address":"509 Rue DE L'Ecole",
    "sg:city":"Saint-Narcisse-DE-Beaurivage",
    "sg:classifiers":[
        {
            "category":"Organizations",
            "subcategory":"Religious Organization",
            "type":"Services"
        }
    ],
    "sg:phone":"+1 418 475 4067",
    "sg:postcode":"G0S 1W0",
    "sg:province":"QC",
    "sg:tags":[
        "house",
        "retreat"
    ],
    "wof:name":"Villa Maria",
    "wof:placetype":"venue"
},
  "geometry": {"coordinates":[-71.2321395874,46.4821357727],"type":"Point"}
}