{
  "type": "Feature",
  "properties": {
    "addr:full":"Winnipeg MB R3T 4J5",
    "addr:postcode":"r3t 4j5",
    "iso:country":"CA",
    "sg:city":"Winnipeg",
    "sg:classifiers":[
        {
            "category":"Real Estate",
            "subcategory":"Real Estate Operator",
            "type":"Services"
        }
    ],
    "sg:phone":"+1 204 269 8148",
    "sg:postcode":"R3T 4J5",
    "sg:province":"MB",
    "sg:tags":[
        "apartment"
    ],
    "wof:name":"Armadale Hollows",
    "wof:placetype":"venue"
},
  "geometry": {"coordinates":[-97.152092,49.826294],"type":"Point"}
}