{
  "type": "Feature",
  "properties": {
    "addr:full":"Waterloo ON N2V 1B4",
    "addr:postcode":"n2v 1b4",
    "iso:country":"CA",
    "sg:city":"Waterloo",
    "sg:classifiers":[
        {
            "category":"Autos & Motor Vehicles",
            "subcategory":"Auto Supplies",
            "type":"Retail Goods"
        }
    ],
    "sg:phone":"+1 519 746 0880",
    "sg:postcode":"N2V 1B4",
    "sg:province":"ON",
    "sg:tags":[
        "equipment",
        "racing",
        "car",
        "automobile"
    ],
    "wof:name":"Racer's Edge",
    "wof:placetype":"venue"
},
  "geometry": {"coordinates":[-80.5390319824,43.5050888062],"type":"Point"}
}