{
  "type": "Feature",
  "properties": {
    "addr:full":"4609 50 Ave Valleyview AB T0H 3N0",
    "addr:housenumber":"4609",
    "addr:postcode":"ab t0h 3n0",
    "addr:street":"50 Ave",
    "iso:country":"CA",
    "sg:address":"4609 50 Ave",
    "sg:city":"Valleyview",
    "sg:classifiers":[
        {
            "category":"Restaurant",
            "type":"Food & Drink"
        }
    ],
    "sg:phone":"+1 780 524 2177",
    "sg:postcode":"T0H 3N0",
    "sg:province":"AB",
    "wof:name":"Burger Baron",
    "wof:placetype":"venue"
},
  "geometry": {"coordinates":[-117.272041321,55.0683822632],"type":"Point"}
}