{
  "type": "Feature",
  "properties": {
    "addr:full":"Edmonton AB T5A 4X1",
    "addr:postcode":"t5a 4x1",
    "iso:country":"CA",
    "sg:city":"Edmonton",
    "sg:classifiers":[
        {
            "category":"Real Estate",
            "subcategory":"Real Estate Agent",
            "type":"Services"
        }
    ],
    "sg:phone":"+1 780 478 7791",
    "sg:postcode":"T5A 4X1",
    "sg:province":"AB",
    "wof:name":"Ranger Realty CO Ltd",
    "wof:placetype":"venue"
},
  "geometry": {"coordinates":[-113.430504,53.586838],"type":"Point"}
}