{
  "type": "Feature",
  "properties": {
    "addr:full":"4239 Bow Trail SW Calgary AB T3C 2G1",
    "addr:housenumber":"4239",
    "addr:postcode":"t3c 2g1",
    "addr:street":"Bow Trail Sw",
    "iso:country":"CA",
    "sg:address":"4239 Bow Trail SW",
    "sg:city":"Calgary",
    "sg:classifiers":[
        {
            "category":"Retail",
            "subcategory":"Animal Services",
            "type":"Services"
        }
    ],
    "sg:phone":"+1 403 217 2221",
    "sg:postcode":"T3C 2G1",
    "sg:province":"AB",
    "sg:tags":[
        "pet",
        "grooming",
        "washing"
    ],
    "wof:name":"Doggie Style",
    "wof:placetype":"venue"
},
  "geometry": {"coordinates":[-114.147606,51.047016],"type":"Point"}
}