{
  "type": "Feature",
  "properties": {
    "addr:full":"65 Fox St Lunenburg NS B0J 2C0",
    "addr:housenumber":"65",
    "addr:postcode":"b0j 2c0",
    "addr:street":"Fox St",
    "iso:country":"CA",
    "sg:address":"65 Fox St",
    "sg:city":"Lunenburg",
    "sg:classifiers":[
        {
            "category":"Organizations",
            "subcategory":"Religious Organization",
            "type":"Services"
        }
    ],
    "sg:phone":"+1 902 634 4383",
    "sg:postcode":"B0J 2C0",
    "sg:province":"NS",
    "sg:tags":[
        "church"
    ],
    "wof:name":"Zion Ev Lutheran Church",
    "wof:placetype":"venue"
},
  "geometry": {"coordinates":[-64.312141,44.378979],"type":"Point"}
}