{
  "type": "Feature",
  "properties": {
    "iso:country":"CA",
    "sg:address":"767 Memorial Ave",
    "sg:city":"Thunder Bay",
    "sg:classifiers":[
        {
            "category":"Shopping",
            "subcategory":"Stationery & Office Supplies",
            "type":"Retail Goods"
        }
    ],
    "sg:phone":"+1 807 343 2506",
    "sg:postcode":"P7B 3Z7",
    "sg:province":"ON",
    "wof:name":"Staples Business Depot",
    "wof:placetype":"venue"
},
  "geometry": {"coordinates":[-89.243019104,48.4141693115],"type":"Point"}
}