{
  "type": "Feature",
  "properties": {
    "addr:full":"37 Advance Ave Napanee ON K7R 3Y5",
    "addr:housenumber":"37",
    "addr:postcode":"k7r 3y5",
    "addr:street":"Advance Ave",
    "iso:country":"CA",
    "sg:address":"37 Advance Ave",
    "sg:city":"Napanee",
    "sg:classifiers":[
        {
            "category":"Home & Garden",
            "subcategory":"Carpets & Floor Coverings",
            "type":"Retail Goods"
        }
    ],
    "sg:phone":"+1 613 354 5252",
    "sg:postcode":"K7R 3Y5",
    "sg:province":"ON",
    "sg:tags":[
        "dealer",
        "rug"
    ],
    "wof:name":"Napanee Flooring",
    "wof:placetype":"venue"
},
  "geometry": {"coordinates":[-76.95635223390001,44.2556114197],"type":"Point"}
}