{
  "type": "Feature",
  "properties": {
    "addr:full":"76 Davenport Rd Toronto ON M5R 1H3",
    "addr:housenumber":"76",
    "addr:postcode":"m5r 1h3",
    "addr:street":"Davenport Rd",
    "iso:country":"CA",
    "sg:address":"76 Davenport Rd",
    "sg:city":"Toronto",
    "sg:classifiers":[
        {
            "category":"Health Services",
            "subcategory":"Chiropractor",
            "type":"Services"
        }
    ],
    "sg:phone":"+1 416 515 1999",
    "sg:postcode":"M5R 1H3",
    "sg:province":"ON",
    "wof:name":"Physio Med Davenport",
    "wof:placetype":"venue"
},
  "geometry": {"coordinates":[-79.39020499999999,43.673126],"type":"Point"}
}