{
  "type": "Feature",
  "properties": {
    "addr:full":"10103 Churchill Dr Lac LA Biche AB T0A 2C0",
    "addr:housenumber":"10103",
    "addr:postcode":"t0a 2c0",
    "addr:street":"Churchill Dr",
    "iso:country":"CA",
    "sg:address":"10103 Churchill Dr",
    "sg:city":"Lac LA Biche",
    "sg:classifiers":[
        {
            "category":"Organizations",
            "subcategory":"Religious Organization",
            "type":"Services"
        }
    ],
    "sg:phone":"+1 780 623 2531",
    "sg:postcode":"T0A 2C0",
    "sg:province":"AB",
    "sg:tags":[
        "church"
    ],
    "wof:name":"Anglican Church",
    "wof:placetype":"venue"
},
  "geometry": {"coordinates":[-111.980102539,54.7728385925],"type":"Point"}
}