{
  "type": "Feature",
  "properties": {
    "addr:full":"133 Main St Melita MB R0M 1L0",
    "addr:housenumber":"133",
    "addr:postcode":"r0m 1l0",
    "addr:street":"Main St",
    "iso:country":"CA",
    "sg:address":"133 Main St",
    "sg:city":"Melita",
    "sg:classifiers":[
        {
            "category":"Professional",
            "subcategory":"Accounting & Tax Preparation",
            "type":"Services"
        }
    ],
    "sg:phone":"+1 204 522 3333",
    "sg:postcode":"R0M 1L0",
    "sg:province":"MB",
    "sg:tags":[
        "accountant"
    ],
    "wof:name":"Meyers Norris Penny Llp",
    "wof:placetype":"venue"
},
  "geometry": {"coordinates":[-100.99102020300001,49.2701072693],"type":"Point"}
}