{
  "type": "Feature",
  "properties": {
    "addr:full":"352 Sheppard Ave E North York ON M2N 3B4",
    "addr:housenumber":"352",
    "addr:postcode":"m2n 3b4",
    "addr:street":"Sheppard Ave E",
    "iso:country":"CA",
    "sg:address":"352 Sheppard Ave E",
    "sg:city":"North York",
    "sg:classifiers":[
        {
            "category":"Real Estate",
            "subcategory":"Real Estate Agent",
            "type":"Services"
        }
    ],
    "sg:phone":"+1 416 250 9000",
    "sg:postcode":"M2N 3B4",
    "sg:province":"ON",
    "wof:name":"Coldwell Banker Case",
    "wof:placetype":"venue"
},
  "geometry": {"coordinates":[-79.39501953120001,43.7651596069],"type":"Point"}
}