{
  "type": "Feature",
  "properties": {
    "addr:full":"84 Broadway St W Nakusp BC V0G 1R0",
    "addr:housenumber":"84",
    "addr:postcode":"v0g 1r0",
    "addr:street":"Broadway St W",
    "iso:country":"CA",
    "sg:address":"84 Broadway St W",
    "sg:city":"Nakusp",
    "sg:classifiers":[
        {
            "category":"Sports & Exercise",
            "subcategory":"Gym",
            "type":"Entertainment"
        }
    ],
    "sg:phone":"+1 250 265 4554",
    "sg:postcode":"V0G 1R0",
    "sg:province":"BC",
    "sg:tags":[
        "club",
        "health",
        "studio",
        "gymnasium"
    ],
    "wof:name":"Alley Health and Fitness",
    "wof:placetype":"venue"
},
  "geometry": {"coordinates":[-117.798461914,50.2383422852],"type":"Point"}
}