{
  "type": "Feature",
  "properties": {
    "addr:full":"183 Thames St S Ingersoll ON N5C 2T6",
    "addr:housenumber":"183",
    "addr:postcode":"n5c 2t6",
    "addr:street":"Thames St S",
    "iso:country":"CA",
    "sg:address":"183 Thames St S",
    "sg:city":"Ingersoll",
    "sg:classifiers":[
        {
            "category":"Professional",
            "subcategory":"Lawyer & Legal Services",
            "type":"Services"
        }
    ],
    "sg:phone":"+1 519 485 5651",
    "sg:postcode":"N5C 2T6",
    "sg:province":"ON",
    "sg:tags":[
        "attorney"
    ],
    "wof:name":"Nesbitt Coulter Llp",
    "wof:placetype":"venue"
},
  "geometry": {"coordinates":[-80.881416,43.037315],"type":"Point"}
}