{
  "type": "Feature",
  "properties": {
    "iso:country":"CA",
    "sg:address":"540 High St S",
    "sg:city":"Thunder Bay",
    "sg:classifiers":[
        {
            "category":"Recreation",
            "type":"Entertainment"
        }
    ],
    "sg:phone":"+1 807 344 7490",
    "sg:postcode":"P7B 3M5",
    "sg:province":"ON",
    "sg:tags":[
        "hall",
        "association",
        "auditorium"
    ],
    "wof:name":"Port Arthur Ukrainian Prosvita",
    "wof:placetype":"venue"
},
  "geometry": {"coordinates":[-89.238609314,48.4181442261],"type":"Point"}
}