{
  "type": "Feature",
  "properties": {
    "addr:full":"1525 Rue DE Bromont Terrebonne QC J6W 4H9",
    "addr:housenumber":"1525",
    "addr:postcode":"j6w 4h9",
    "addr:street":"Rue De Bromont",
    "iso:country":"CA",
    "sg:address":"1525 Rue DE Bromont",
    "sg:city":"Terrebonne",
    "sg:classifiers":[
        {
            "category":"Manufacturing",
            "subcategory":"Rubber & Plastics",
            "type":"Manufacturing & Wholesale Goods"
        }
    ],
    "sg:phone":"+1 450 471 2772",
    "sg:postcode":"J6W 4H9",
    "sg:province":"QC",
    "wof:name":"Agrico Plastiques Ltee",
    "wof:placetype":"venue"
},
  "geometry": {"coordinates":[-73.65261099999999,45.705727],"type":"Point"}
}