{
  "type": "Feature",
  "properties": {
    "addr:full":"4050 Whistler Way Whistler BC V0N 1B4",
    "addr:housenumber":"4050",
    "addr:postcode":"v0n 1b4",
    "addr:street":"Whistler Way",
    "iso:country":"CA",
    "sg:address":"4050 Whistler Way",
    "sg:city":"Whistler",
    "sg:classifiers":[
        {
            "category":"Bars & Pubs",
            "type":"Food & Drink"
        }
    ],
    "sg:phone":"+1 604 932 1982",
    "sg:postcode":"V0N 1B4",
    "sg:province":"BC",
    "sg:tags":[
        "club",
        "night"
    ],
    "wof:name":"Cinnamon Bear Bar",
    "wof:placetype":"venue"
},
  "geometry": {"coordinates":[-122.956642,50.113087],"type":"Point"}
}