{
  "type": "Feature",
  "properties": {
    "addr:full":"Vancouver BC V6C 1V5",
    "addr:postcode":"v6c 1v5",
    "iso:country":"CA",
    "sg:city":"Vancouver",
    "sg:classifiers":[
        {
            "category":"Mining & Drilling",
            "type":"Manufacturing & Wholesale Goods"
        }
    ],
    "sg:phone":"+1 604 662 3598",
    "sg:postcode":"V6C 1V5",
    "sg:province":"BC",
    "sg:tags":[
        "contractor"
    ],
    "wof:name":"New Guinea Gold Corp",
    "wof:placetype":"venue"
},
  "geometry": {"coordinates":[-123.114273,49.284771],"type":"Point"}
}