{
  "type": "Feature",
  "properties": {
    "iso:country":"CA",
    "sg:address":"930 Richmond St",
    "sg:city":"Chatham",
    "sg:classifiers":[
        {
            "category":"Manufacturing",
            "subcategory":"Tools & Machinery",
            "type":"Manufacturing & Wholesale Goods"
        }
    ],
    "sg:phone":"+1 519 354 0788",
    "sg:postcode":"N7M 5J5",
    "sg:province":"ON",
    "sg:tags":[
        "machine",
        "shop"
    ],
    "wof:name":"County Machine Shop",
    "wof:placetype":"venue"
},
  "geometry": {"coordinates":[-82.21179199220001,42.3828163147],"type":"Point"}
}