{
  "type": "Feature",
  "properties": {
    "addr:full":"1114 Wilson Ave North York ON M3M 1G7",
    "addr:housenumber":"1114",
    "addr:postcode":"m3m 1g7",
    "addr:street":"Wilson Ave",
    "iso:country":"CA",
    "sg:address":"1114 Wilson Ave",
    "sg:city":"North York",
    "sg:classifiers":[
        {
            "category":"Personal",
            "subcategory":"Beauty Salon",
            "type":"Services"
        }
    ],
    "sg:phone":"+1 416 638 0174",
    "sg:postcode":"M3M 1G7",
    "sg:province":"ON",
    "wof:name":"Stephen's Men's Hair Styling",
    "wof:placetype":"venue"
},
  "geometry": {"coordinates":[-79.483124,43.726574],"type":"Point"}
}