{
  "type": "Feature",
  "properties": {
    "addr:full":"Saint-Jean-Sur-Richelieu QC J3B 6L7",
    "addr:postcode":"j3b 6l7",
    "iso:country":"CA",
    "sg:city":"Saint-Jean-Sur-Richelieu",
    "sg:classifiers":[
        {
            "category":"Manufacturing",
            "subcategory":"Metals",
            "type":"Manufacturing & Wholesale Goods"
        }
    ],
    "sg:phone":"+1 450 349 4745",
    "sg:postcode":"J3B 6L7",
    "sg:province":"QC",
    "sg:tags":[
        "plate",
        "tin"
    ],
    "wof:name":"Ventilation J Hebert Inc",
    "wof:placetype":"venue"
},
  "geometry": {"coordinates":[-73.25675964360001,45.3138771057],"type":"Point"}
}