{
  "type": "Feature",
  "properties": {
    "addr:full":"400 Rue DE Bigarre Victoriaville QC G6P 4Z2",
    "addr:housenumber":"400",
    "addr:postcode":"g6p 4z2",
    "addr:street":"Rue De Bigarre",
    "iso:country":"CA",
    "sg:address":"400 Rue DE Bigarre",
    "sg:city":"Victoriaville",
    "sg:classifiers":[
        {
            "category":"Government",
            "subcategory":"Office",
            "type":"Public Place"
        }
    ],
    "sg:phone":"+1 819 758 0651",
    "sg:postcode":"G6P 4Z2",
    "sg:province":"QC",
    "sg:tags":[
        "village"
    ],
    "wof:name":"Victoriaville Bureau-L'Ingr",
    "wof:placetype":"venue"
},
  "geometry": {"coordinates":[-71.951736,46.06403],"type":"Point"}
}