{
  "type": "Feature",
  "properties": {
    "addr:full":"210 Ferguson Rd Gravenhurst ON P1P 1P7",
    "addr:housenumber":"210",
    "addr:postcode":"p1p 1p7",
    "addr:street":"Ferguson Rd",
    "iso:country":"CA",
    "sg:address":"210 Ferguson Rd",
    "sg:city":"Gravenhurst",
    "sg:classifiers":[
        {
            "category":"Building & Trades",
            "subcategory":"Construction",
            "type":"Services"
        }
    ],
    "sg:phone":"+1 705 687 3302",
    "sg:postcode":"P1P 1P7",
    "sg:province":"ON",
    "sg:tags":[
        "general",
        "contractor"
    ],
    "wof:name":"Sheppard Construction",
    "wof:placetype":"venue"
},
  "geometry": {"coordinates":[-79.367363,44.929531],"type":"Point"}
}