{
  "type": "Feature",
  "properties": {
    "addr:full":"1942 Coulter Rd Campbell River BC V9W 7M1",
    "addr:housenumber":"1942",
    "addr:postcode":"v9w 7m1",
    "addr:street":"Coulter Rd",
    "iso:country":"CA",
    "sg:address":"1942 Coulter Rd",
    "sg:city":"Campbell River",
    "sg:classifiers":[
        {
            "category":"Wholesale",
            "subcategory":"Scrap",
            "type":"Manufacturing & Wholesale Goods"
        }
    ],
    "sg:phone":"+1 250 286 4572",
    "sg:postcode":"V9W 7M1",
    "sg:province":"BC",
    "sg:tags":[
        "recycling",
        "center"
    ],
    "wof:name":"Harper's Recycling",
    "wof:placetype":"venue"
},
  "geometry": {"coordinates":[-125.27091217,50.0452308655],"type":"Point"}
}