{
  "type": "Feature",
  "properties": {
    "addr:full":"Wellington ON K0K 3L0",
    "addr:postcode":"k0k 3l0",
    "iso:country":"CA",
    "sg:city":"Wellington",
    "sg:classifiers":[
        {
            "category":"Shopping",
            "subcategory":"Gifts & Souvenirs",
            "type":"Retail Goods"
        }
    ],
    "sg:phone":"+1 613 399 2000",
    "sg:postcode":"K0K 3L0",
    "sg:province":"ON",
    "sg:tags":[
        "shop"
    ],
    "wof:name":"Once Upon A Time",
    "wof:placetype":"venue"
},
  "geometry": {"coordinates":[-77.34921300000001,43.951168],"type":"Point"}
}