{
  "type": "Feature",
  "properties": {
    "addr:full":"Winnipeg MB R2J 3E6",
    "addr:postcode":"r2j 3e6",
    "iso:country":"CA",
    "sg:city":"Winnipeg",
    "sg:classifiers":[
        {
            "category":"Personal",
            "type":"Services"
        }
    ],
    "sg:phone":"+1 204 257 7435",
    "sg:postcode":"R2J 3E6",
    "sg:province":"MB",
    "sg:tags":[
        "miscellaneous"
    ],
    "wof:name":"Customized Marriages",
    "wof:placetype":"venue"
},
  "geometry": {"coordinates":[-97.08203125,49.8471946716],"type":"Point"}
}