{
  "type": "Feature",
  "properties": {
    "addr:full":"NE 24-8-23W Souris MB R0K 2C0",
    "addr:postcode":"r0k 2c0",
    "addr:street":"Ne 24-8-23W",
    "iso:country":"CA",
    "sg:address":"NE 24-8-23W",
    "sg:city":"Souris",
    "sg:classifiers":[
        {
            "category":"Shopping",
            "subcategory":"Bicycles & Sporting Goods",
            "type":"Retail Goods"
        }
    ],
    "sg:phone":"+1 204 483 3311",
    "sg:postcode":"R0K 2C0",
    "sg:province":"MB",
    "sg:tags":[
        "gun",
        "gunsmith"
    ],
    "wof:name":"D 5 Gunsmith Shop",
    "wof:placetype":"venue"
},
  "geometry": {"coordinates":[-100.258865,49.620834],"type":"Point"}
}