{
  "type": "Feature",
  "properties": {
    "addr:full":"Surrey BC V4N 4W7",
    "addr:postcode":"v4n 4w7",
    "iso:country":"CA",
    "sg:city":"Surrey",
    "sg:classifiers":[
        {
            "category":"Manufacturing",
            "subcategory":"Metals",
            "type":"Manufacturing & Wholesale Goods"
        }
    ],
    "sg:phone":"+1 604 888 3682",
    "sg:postcode":"V4N 4W7",
    "sg:province":"BC",
    "sg:tags":[
        "machine",
        "shop"
    ],
    "wof:name":"Charger Engineering Ltd",
    "wof:placetype":"venue"
},
  "geometry": {"coordinates":[-122.698791504,49.1755561829],"type":"Point"}
}