{
  "type": "Feature",
  "properties": {
    "iso:country":"CA",
    "sg:address":"388 Champlain St",
    "sg:city":"Dieppe",
    "sg:classifiers":[
        {
            "category":"Professional",
            "subcategory":"Lawyer & Legal Services",
            "type":"Services"
        }
    ],
    "sg:phone":"+1 506 857 1820",
    "sg:postcode":"E1A 1P3",
    "sg:province":"NB",
    "sg:tags":[
        "attorney"
    ],
    "wof:name":"Finn, Pierre",
    "wof:placetype":"venue"
},
  "geometry": {"coordinates":[-64.7400436401,46.097038269],"type":"Point"}
}