{
  "type": "Feature",
  "properties": {
    "addr:full":"11417 89 Ave Grande Prairie AB T8V 7M9",
    "addr:housenumber":"11417",
    "addr:postcode":"t8v 7m9",
    "addr:street":"89 Ave",
    "iso:country":"CA",
    "sg:address":"11417 89 Ave",
    "sg:city":"Grande Prairie",
    "sg:classifiers":[
        {
            "category":"Mining & Drilling",
            "type":"Manufacturing & Wholesale Goods"
        }
    ],
    "sg:phone":"+1 780 539 3440",
    "sg:postcode":"T8V 7M9",
    "sg:province":"AB",
    "sg:tags":[
        "field",
        "oil"
    ],
    "wof:name":"Quinn Well Control Ltd",
    "wof:placetype":"venue"
},
  "geometry": {"coordinates":[-118.84095000000001,55.158905],"type":"Point"}
}