{
  "type": "Feature",
  "properties": {
    "addr:full":"380 Princes St S Kincardine ON N2Z 2T6",
    "addr:housenumber":"380",
    "addr:postcode":"n2z 2t6",
    "addr:street":"Princes St S",
    "iso:country":"CA",
    "sg:address":"380 Princes St S",
    "sg:city":"Kincardine",
    "sg:classifiers":[
        {
            "category":"Building & Trades",
            "subcategory":"Electrical",
            "type":"Services"
        }
    ],
    "sg:phone":"+1 519 396 7141",
    "sg:postcode":"N2Z 2T6",
    "sg:province":"ON",
    "sg:tags":[
        "electric",
        "contractor"
    ],
    "wof:name":"K L Petrie Heating Elec Ltd",
    "wof:placetype":"venue"
},
  "geometry": {"coordinates":[-81.6413574219,44.16639328],"type":"Point"}
}