{
  "type": "Feature",
  "properties": {
    "iso:country":"CA",
    "sg:address":"2412 King George Hwy",
    "sg:city":"Surrey",
    "sg:classifiers":[
        {
            "category":"Building & Trades",
            "subcategory":"Equipment Rental",
            "type":"Services"
        }
    ],
    "sg:phone":"+1 604 531 1491",
    "sg:postcode":"V4P 1H5",
    "sg:province":"BC",
    "wof:name":"United Rentals Inc",
    "wof:placetype":"venue"
},
  "geometry": {"coordinates":[-122.79394531200001,49.0460777283],"type":"Point"}
}