{
  "type": "Feature",
  "properties": {
    "addr:full":"335 Rue DE Champs Boucherville QC J4B 6E4",
    "addr:housenumber":"335",
    "addr:postcode":"j4b 6e4",
    "addr:street":"Rue De Champs",
    "iso:country":"CA",
    "sg:address":"335 Rue DE Champs",
    "sg:city":"Boucherville",
    "sg:classifiers":[
        {
            "category":"Professional",
            "subcategory":"Accounting & Tax Preparation",
            "type":"Services"
        }
    ],
    "sg:phone":"+1 450 449 1727",
    "sg:postcode":"J4B 6E4",
    "sg:province":"QC",
    "sg:tags":[
        "return",
        "filing"
    ],
    "wof:name":"Gestion Privel",
    "wof:placetype":"venue"
},
  "geometry": {"coordinates":[-73.4374465942,45.5764503479],"type":"Point"}
}