{
  "type": "Feature",
  "properties": {
    "addr:full":"Vancouver BC V5T 4S8",
    "addr:postcode":"v5t 4s8",
    "iso:country":"CA",
    "sg:city":"Vancouver",
    "sg:classifiers":[
        {
            "category":"Recreation",
            "type":"Entertainment"
        }
    ],
    "sg:phone":"+1 604 718 1888",
    "sg:postcode":"V5T 4S8",
    "sg:province":"BC",
    "sg:tags":[
        "publisher",
        "hall",
        "auditorium"
    ],
    "wof:name":"Annick Press",
    "wof:placetype":"venue"
},
  "geometry": {"coordinates":[-123.099174,49.2635],"type":"Point"}
}