{
  "type": "Feature",
  "properties": {
    "iso:country":"CA",
    "sg:address":"870 Av Du Moulin #A",
    "sg:city":"Saint-Joseph-DE-Beauce",
    "sg:classifiers":[
        {
            "category":"Taxi",
            "type":"Transportation"
        }
    ],
    "sg:phone":"+1 418 397 4444",
    "sg:postcode":"G0S 2V0",
    "sg:province":"QC",
    "sg:tags":[
        "taxicab"
    ],
    "wof:name":"Taxi Karine Verreault",
    "wof:placetype":"venue"
},
  "geometry": {"coordinates":[-70.87948608400001,46.3060531616],"type":"Point"}
}