{
  "type": "Feature",
  "properties": {
    "iso:country":"CA",
    "sg:address":"861 Mackenzie Ave S",
    "sg:city":"Williams Lake",
    "sg:classifiers":[
        {
            "category":"Autos & Motor Vehicles",
            "subcategory":"Auto Supplies",
            "type":"Retail Goods"
        }
    ],
    "sg:phone":"+1 250 392 3306",
    "sg:postcode":"V2G 3X8",
    "sg:province":"BC",
    "sg:tags":[
        "automobile",
        "parts"
    ],
    "wof:name":"Chuck's Auto Supply Ltd",
    "wof:placetype":"venue"
},
  "geometry": {"coordinates":[-122.13053893999999,52.1233177185],"type":"Point"}
}