{
  "type": "Feature",
  "properties": {
    "addr:full":"Mississauga ON L5R 3K6",
    "addr:postcode":"l5r 3k6",
    "iso:country":"CA",
    "sg:city":"Mississauga",
    "sg:classifiers":[
        {
            "category":"Professional",
            "subcategory":"Management & Consulting",
            "type":"Services"
        }
    ],
    "sg:phone":"+1 905 568 8888",
    "sg:postcode":"L5R 3K6",
    "sg:province":"ON",
    "sg:tags":[
        "town",
        "city",
        "regional",
        "planner"
    ],
    "wof:name":"Glen Schnarr & Assoc",
    "wof:placetype":"venue"
},
  "geometry": {"coordinates":[-79.64924600000001,43.603615],"type":"Point"}
}