{
  "type": "Feature",
  "properties": {
    "addr:full":"238 Algonquin Ave North Bay ON P1B 4V9",
    "addr:housenumber":"238",
    "addr:postcode":"p1b 4v9",
    "addr:street":"Algonquin Ave",
    "iso:country":"CA",
    "sg:address":"238 Algonquin Ave",
    "sg:city":"North Bay",
    "sg:classifiers":[
        {
            "category":"Social Services",
            "type":"Services"
        }
    ],
    "sg:phone":"+1 705 472 8650",
    "sg:postcode":"P1B 4V9",
    "sg:province":"ON",
    "sg:tags":[
        "organization",
        "welfare"
    ],
    "wof:name":"Royal Canadian Legion Svc Bur",
    "wof:placetype":"venue"
},
  "geometry": {"coordinates":[-79.46589660639999,46.3131332397],"type":"Point"}
}