{
  "type": "Feature",
  "properties": {
    "iso:country":"CA",
    "sg:address":"3368 Ch Bois-Clair",
    "sg:city":"Saint-Antoine-DE-Tilly",
    "sg:classifiers":[
        {
            "category":"Farming",
            "subcategory":"Farm & Veterinary Services",
            "type":"Manufacturing & Wholesale Goods"
        }
    ],
    "sg:phone":"+1 418 886 2314",
    "sg:postcode":"G0S 2C0",
    "sg:province":"QC",
    "sg:tags":[
        "breeder",
        "livestock"
    ],
    "wof:name":"Genest Paul-Emile & Fils Inc",
    "wof:placetype":"venue"
},
  "geometry": {"coordinates":[-71.5175857544,46.6545295715],"type":"Point"}
}