{
  "type": "Feature",
  "properties": {
    "addr:full":"Vancouver BC V6K 4M1",
    "addr:postcode":"v6k 4m1",
    "iso:country":"CA",
    "sg:city":"Vancouver",
    "sg:classifiers":[
        {
            "category":"Health Services",
            "subcategory":"Doctor",
            "type":"Services"
        }
    ],
    "sg:phone":"+1 604 732 6333",
    "sg:postcode":"V6K 4M1",
    "sg:province":"BC",
    "sg:tags":[
        "dentist"
    ],
    "wof:name":"Fastlicht, Sandra DDS",
    "wof:placetype":"venue"
},
  "geometry": {"coordinates":[-123.167510986,49.2575187683],"type":"Point"}
}