{
  "type": "Feature",
  "properties": {
    "addr:full":"1185 Youghall Dr Bathurst NB E2A 4Y3",
    "addr:housenumber":"1185",
    "addr:postcode":"e2a 4y3",
    "addr:street":"Youghall Dr",
    "iso:country":"CA",
    "sg:address":"1185 Youghall Dr",
    "sg:city":"Bathurst",
    "sg:classifiers":[
        {
            "category":"Building & Trades",
            "subcategory":"Construction",
            "type":"Services"
        }
    ],
    "sg:phone":"+1 506 548 9271",
    "sg:postcode":"E2A 4Y3",
    "sg:province":"NB",
    "sg:tags":[
        "excavating",
        "contractor"
    ],
    "wof:name":"Bradley Jenks Excavation Ltd",
    "wof:placetype":"venue"
},
  "geometry": {"coordinates":[-65.6393280029,47.6620483398],"type":"Point"}
}