{
  "type": "Feature",
  "properties": {
    "addr:full":"555 King St W Prescott ON K0E 1T0",
    "addr:housenumber":"555",
    "addr:postcode":"k0e 1t0",
    "addr:street":"King St W",
    "iso:country":"CA",
    "sg:address":"555 King St W",
    "sg:city":"Prescott",
    "sg:classifiers":[
        {
            "category":"Health Services",
            "subcategory":"Doctor",
            "type":"Services"
        }
    ],
    "sg:phone":"+1 613 925 5977",
    "sg:postcode":"K0E 1T0",
    "sg:province":"ON",
    "sg:tags":[
        "physician",
        "surgeon"
    ],
    "wof:name":"Kellam, G W MD",
    "wof:placetype":"venue"
},
  "geometry": {"coordinates":[-75.5201797485,44.7057952881],"type":"Point"}
}