{
  "type": "Feature",
  "properties": {
    "addr:full":"PO Box 168 Ryley AB T0B 4A0",
    "addr:housenumber":"po",
    "addr:postcode":"t0b 4a0",
    "addr:street":"Box 168 Ryley",
    "iso:country":"CA",
    "sg:address":"PO Box 168",
    "sg:city":"Ryley",
    "sg:classifiers":[
        {
            "category":"Organizations",
            "subcategory":"Religious Organization",
            "type":"Services"
        }
    ],
    "sg:phone":"+1 780 663 3767",
    "sg:postcode":"T0B 4A0",
    "sg:province":"AB",
    "sg:tags":[
        "church"
    ],
    "wof:name":"Ryley Seventh-Day Adventist",
    "wof:placetype":"venue"
},
  "geometry": {"coordinates":[-112.42781100000001,53.289848],"type":"Point"}
}