{
  "type": "Feature",
  "properties": {
    "addr:full":"2406 Milliner Rd Roberts Creek BC V0N 2W6",
    "addr:postcode":"2406;v0n 2w6",
    "addr:street":"Milliner Rd",
    "iso:country":"CA",
    "sg:address":"2406 Milliner Rd",
    "sg:city":"Roberts Creek",
    "sg:classifiers":[
        {
            "category":"Building & Trades",
            "subcategory":"Construction",
            "type":"Services"
        }
    ],
    "sg:phone":"+1 604 886 8900",
    "sg:postcode":"V0N 2W6",
    "sg:province":"BC",
    "sg:tags":[
        "contractor"
    ],
    "wof:name":"Pomfret Construction Ltd",
    "wof:placetype":"venue"
},
  "geometry": {"coordinates":[-123.607498169,49.4122810364],"type":"Point"}
}