{
  "type": "Feature",
  "properties": {
    "iso:country":"CA",
    "sg:address":"5165 Rue Sherbrooke O",
    "sg:city":"Montreal",
    "sg:classifiers":[
        {
            "category":"Health Services",
            "subcategory":"Doctor",
            "type":"Services"
        }
    ],
    "sg:phone":"+1 514 369 1555",
    "sg:postcode":"H4A 1T6",
    "sg:province":"QC",
    "sg:tags":[
        "psychoanalyst"
    ],
    "wof:name":"Walker Sandford",
    "wof:placetype":"venue"
},
  "geometry": {"coordinates":[-73.5530548096,45.567905426],"type":"Point"}
}