{
  "type": "Feature",
  "properties": {
    "iso:country":"CA",
    "sg:address":"6435 Highway 89",
    "sg:city":"Alliston",
    "sg:classifiers":[
        {
            "category":"Home & Garden",
            "subcategory":"Furniture",
            "type":"Retail Goods"
        }
    ],
    "sg:phone":"+1 705 435 5674",
    "sg:postcode":"L9R 1V2",
    "sg:province":"ON",
    "wof:name":"Lifetime Pine & Oak",
    "wof:placetype":"venue"
},
  "geometry": {"coordinates":[-79.8681259155,44.1542167664],"type":"Point"}
}