{
  "type": "Feature",
  "properties": {
    "addr:full":"12451 97 St NW Edmonton AB T5G 1Z6",
    "addr:housenumber":"12451",
    "addr:postcode":"t5g 1z6",
    "addr:street":"97 St Nw",
    "iso:country":"CA",
    "sg:address":"12451 97 St NW",
    "sg:city":"Edmonton",
    "sg:classifiers":[
        {
            "category":"Shopping",
            "subcategory":"Clothing, Apparel, & Fashions",
            "type":"Retail Goods"
        }
    ],
    "sg:phone":"+1 780 471 2230",
    "sg:postcode":"T5G 1Z6",
    "sg:province":"AB",
    "sg:tags":[
        "lingerie"
    ],
    "wof:name":"Love Stop",
    "wof:placetype":"venue"
},
  "geometry": {"coordinates":[-113.491623,53.580235],"type":"Point"}
}