{
  "type": "Feature",
  "properties": {
    "addr:full":"1135 Vantassell St Bathurst NB E2A 4C7",
    "addr:housenumber":"1135",
    "addr:postcode":"e2a 4c7",
    "addr:street":"Vantassell St",
    "iso:country":"CA",
    "sg:address":"1135 Vantassell St",
    "sg:city":"Bathurst",
    "sg:classifiers":[
        {
            "category":"Wholesale",
            "subcategory":"Machinery & Supplies",
            "type":"Manufacturing & Wholesale Goods"
        }
    ],
    "sg:phone":"+1 506 548 3854",
    "sg:postcode":"E2A 4C7",
    "sg:province":"NB",
    "sg:tags":[
        "product",
        "paper",
        "janitor"
    ],
    "wof:name":"Drift Hand Cleaner Ltd",
    "wof:placetype":"venue"
},
  "geometry": {"coordinates":[-65.696083,47.634621],"type":"Point"}
}