{
  "type": "Feature",
  "properties": {
    "addr:full":"10380 Tecumseh Rd E Windsor ON N8R 1A7",
    "addr:housenumber":"10380",
    "addr:postcode":"n8r 1a7",
    "addr:street":"Tecumseh Rd E",
    "iso:country":"CA",
    "sg:address":"10380 Tecumseh Rd E",
    "sg:city":"Windsor",
    "sg:classifiers":[
        {
            "category":"Autos & Motor Vehicles",
            "subcategory":"Automobile Sales",
            "type":"Retail Goods"
        }
    ],
    "sg:phone":"+1 519 979 9900",
    "sg:postcode":"N8R 1A7",
    "sg:province":"ON",
    "sg:tags":[
        "car",
        "dealer"
    ],
    "wof:name":"Windsor Chrysler Jeep Eagle",
    "wof:placetype":"venue"
},
  "geometry": {"coordinates":[-82.913223,42.314003],"type":"Point"}
}