{
  "type": "Feature",
  "properties": {
    "addr:full":"9472 Martin Park Dr Black Creek BC V9J 1C3",
    "addr:housenumber":"9472",
    "addr:postcode":"v9j 1c3",
    "addr:street":"Martin Park Dr",
    "iso:country":"CA",
    "sg:address":"9472 Martin Park Dr",
    "sg:city":"Black Creek",
    "sg:classifiers":[
        {
            "category":"Building & Trades",
            "subcategory":"Construction",
            "type":"Services"
        }
    ],
    "sg:phone":"+1 250 897 7779",
    "sg:postcode":"V9J 1C3",
    "sg:province":"BC",
    "sg:tags":[
        "contractor"
    ],
    "wof:name":"Ed Bell Construction",
    "wof:placetype":"venue"
},
  "geometry": {"coordinates":[-125.135002136,49.843006134],"type":"Point"}
}