{
  "type": "Feature",
  "properties": {
    "addr:full":"2025 County Road 21 Spencerville ON K0E 1X0",
    "addr:housenumber":"2025",
    "addr:postcode":"k0e 1x0",
    "addr:street":"County Road 21",
    "iso:country":"CA",
    "sg:address":"2025 County Road 21",
    "sg:city":"Spencerville",
    "sg:classifiers":[
        {
            "category":"Building & Trades",
            "subcategory":"Construction",
            "type":"Services"
        }
    ],
    "sg:phone":"+1 613 658 2209",
    "sg:postcode":"K0E 1X0",
    "sg:province":"ON",
    "sg:tags":[
        "home",
        "general",
        "improvement",
        "contractor"
    ],
    "wof:name":"L J Home Improvement",
    "wof:placetype":"venue"
},
  "geometry": {"coordinates":[-75.5466842651,44.8430595398],"type":"Point"}
}