{
  "type": "Feature",
  "properties": {
    "iso:country":"CA",
    "sg:address":"91 2E Rue E",
    "sg:city":"Amos",
    "sg:classifiers":[
        {
            "category":"Real Estate",
            "subcategory":"Surveying",
            "type":"Services"
        }
    ],
    "sg:phone":"+1 819 732 8315",
    "sg:postcode":"J9T 3W8",
    "sg:province":"QC",
    "sg:tags":[
        "surveyor"
    ],
    "wof:name":"Descarreaux Dube",
    "wof:placetype":"venue"
},
  "geometry": {"coordinates":[-78.1110534668,48.5624198914],"type":"Point"}
}