{
  "type": "Feature",
  "properties": {
    "addr:full":"4285 Ch Vincent-Massey Rawdon QC J0K 1S0",
    "addr:housenumber":"4285",
    "addr:postcode":"j0k 1s0",
    "addr:street":"Ch Vincent-Massey",
    "iso:country":"CA",
    "sg:address":"4285 Ch Vincent-Massey",
    "sg:city":"Rawdon",
    "sg:classifiers":[
        {
            "category":"Manufacturing",
            "subcategory":"Glass & Minerals",
            "type":"Manufacturing & Wholesale Goods"
        }
    ],
    "sg:phone":"+1 450 834 2571",
    "sg:postcode":"J0K 1S0",
    "sg:province":"QC",
    "sg:tags":[
        "building",
        "brick",
        "material"
    ],
    "wof:name":"Rawdon Produits DE Ciment Cie",
    "wof:placetype":"venue"
},
  "geometry": {"coordinates":[-73.733223,46.035908],"type":"Point"}
}