{
  "type": "Feature",
  "properties": {
    "addr:full":"Laval QC H7L 4C3",
    "addr:postcode":"h7l 4c3",
    "iso:country":"CA",
    "sg:city":"Laval",
    "sg:classifiers":[
        {
            "category":"Restaurant",
            "type":"Food & Drink"
        }
    ],
    "sg:phone":"+1 450 978 0505",
    "sg:postcode":"H7L 4C3",
    "sg:province":"QC",
    "sg:tags":[
        "baker"
    ],
    "wof:name":"Saint Cinnamon",
    "wof:placetype":"venue"
},
  "geometry": {"coordinates":[-73.752396,45.585976],"type":"Point"}
}