{
  "type": "Feature",
  "properties": {
    "addr:full":"Delta BC V4E 2A8",
    "addr:postcode":"v4e 2a8",
    "iso:country":"CA",
    "sg:city":"Delta",
    "sg:classifiers":[
        {
            "category":"Health Services",
            "subcategory":"Doctor",
            "type":"Services"
        }
    ],
    "sg:phone":"+1 604 599 5600",
    "sg:postcode":"V4E 2A8",
    "sg:province":"BC",
    "sg:tags":[
        "dentist"
    ],
    "wof:name":"Robert Holditch Inc",
    "wof:placetype":"venue"
},
  "geometry": {"coordinates":[-122.890488,49.129025],"type":"Point"}
}