{
  "type": "Feature",
  "properties": {
    "addr:full":"355 South Park Rd Thornhill ON L3T 7W2",
    "addr:housenumber":"355",
    "addr:postcode":"l3t 7w2",
    "addr:street":"South Park Rd",
    "iso:country":"CA",
    "sg:address":"355 South Park Rd",
    "sg:city":"Thornhill",
    "sg:classifiers":[
        {
            "category":"Travel",
            "subcategory":"Hotels & Motels",
            "type":"Entertainment"
        }
    ],
    "sg:phone":"+1 905 771 9333",
    "sg:postcode":"L3T 7W2",
    "sg:province":"ON",
    "wof:name":"Staybridge Suites Hotel",
    "wof:placetype":"venue"
},
  "geometry": {"coordinates":[-79.3876419067,43.838218689],"type":"Point"}
}