{
  "type": "Feature",
  "properties": {
    "addr:full":"New Liskeard ON P0J 1P0",
    "addr:postcode":"p0j 1p0",
    "iso:country":"CA",
    "sg:city":"New Liskeard",
    "sg:classifiers":[
        {
            "category":"Government",
            "subcategory":"Office",
            "type":"Public Place"
        }
    ],
    "sg:phone":"+1 705 647 7447",
    "sg:postcode":"P0J 1P0",
    "sg:province":"ON",
    "sg:tags":[
        "organization",
        "social",
        "welfare"
    ],
    "wof:name":"Ontario Social Svc Dept",
    "wof:placetype":"venue"
},
  "geometry": {"coordinates":[-79.671836853,47.5153198242],"type":"Point"}
}