{
  "type": "Feature",
  "properties": {
    "addr:full":"Calgary AB T2R 1M7",
    "addr:postcode":"t2r 1m7",
    "iso:country":"CA",
    "sg:city":"Calgary",
    "sg:classifiers":[
        {
            "category":"Manufacturing",
            "subcategory":"Metals",
            "type":"Manufacturing & Wholesale Goods"
        }
    ],
    "sg:phone":"+1 403 266 7070",
    "sg:postcode":"T2R 1M7",
    "sg:province":"AB",
    "sg:tags":[
        "field",
        "oil"
    ],
    "wof:name":"Pillar Oilfield Projects Ltd",
    "wof:placetype":"venue"
},
  "geometry": {"coordinates":[-114.07278442400001,51.0427856445],"type":"Point"}
}