{
  "type": "Feature",
  "properties": {
    "addr:full":"169 Hiram St Bracebridge ON P1L 2C1",
    "addr:housenumber":"169",
    "addr:postcode":"p1l 2c1",
    "addr:street":"Hiram St",
    "iso:country":"CA",
    "sg:address":"169 Hiram St",
    "sg:city":"Bracebridge",
    "sg:classifiers":[
        {
            "category":"Health Services",
            "subcategory":"Doctor",
            "type":"Services"
        }
    ],
    "sg:phone":"+1 705 646 1221",
    "sg:postcode":"P1L 2C1",
    "sg:province":"ON",
    "sg:tags":[
        "physician",
        "surgeon"
    ],
    "wof:name":"Moran, Keith MD",
    "wof:placetype":"venue"
},
  "geometry": {"coordinates":[-79.3139343262,45.0452194214],"type":"Point"}
}