{
  "type": "Feature",
  "properties": {
    "addr:full":"13391 Cedar Rd Ladysmith BC V9G 1H6",
    "addr:housenumber":"13391",
    "addr:postcode":"v9g 1h6",
    "addr:street":"Cedar Rd",
    "iso:country":"CA",
    "sg:address":"13391 Cedar Rd",
    "sg:city":"Ladysmith",
    "sg:classifiers":[
        {
            "category":"Retail",
            "subcategory":"Auto Repair",
            "type":"Services"
        }
    ],
    "sg:phone":"+1 250 245 2795",
    "sg:postcode":"V9G 1H6",
    "sg:province":"BC",
    "sg:tags":[
        "repairing",
        "automobile"
    ],
    "wof:name":"Larry's Automotive Repair",
    "wof:placetype":"venue"
},
  "geometry": {"coordinates":[-123.820541382,48.9973564148],"type":"Point"}
}