{
  "type": "Feature",
  "properties": {
    "iso:country":"CA",
    "sg:city":"Mississauga",
    "sg:classifiers":[
        {
            "category":"Professional",
            "subcategory":"Management & Consulting",
            "type":"Services"
        }
    ],
    "sg:phone":"+1 905 238 8445",
    "sg:postcode":"L4W 4J9",
    "sg:province":"ON",
    "sg:tags":[
        "promotion",
        "sales"
    ],
    "wof:name":"Reward Connections Inc",
    "wof:placetype":"venue"
},
  "geometry": {"coordinates":[-79.6406784058,43.6339950562],"type":"Point"}
}