{
  "type": "Feature",
  "properties": {
    "addr:full":"97 Arthur Ave Barrie ON L4M 6H6",
    "addr:housenumber":"97",
    "addr:postcode":"l4m 6h6",
    "addr:street":"Arthur Ave",
    "iso:country":"CA",
    "sg:address":"97 Arthur Ave",
    "sg:city":"Barrie",
    "sg:classifiers":[
        {
            "category":"Real Estate",
            "subcategory":"Real Estate Agent",
            "type":"Services"
        }
    ],
    "sg:phone":"+1 705 734 0455",
    "sg:postcode":"L4M 6H6",
    "sg:province":"ON",
    "sg:tags":[
        "management"
    ],
    "wof:name":"Anmar Property Management",
    "wof:placetype":"venue"
},
  "geometry": {"coordinates":[-79.6568908691,44.4027290344],"type":"Point"}
}