{
  "type": "Feature",
  "properties": {
    "addr:full":"109 10 Ave SE Calgary AB T2G 0V8",
    "addr:postcode":"t2g 0v8",
    "addr:street":"109 10 Ave Se",
    "iso:country":"CA",
    "sg:address":"109 10 Ave SE",
    "sg:city":"Calgary",
    "sg:classifiers":[
        {
            "category":"Travel",
            "subcategory":"Travel Agent",
            "type":"Entertainment"
        }
    ],
    "sg:phone":"+1 403 290 0007",
    "sg:postcode":"T2G 0V8",
    "sg:province":"AB",
    "sg:tags":[
        "agency",
        "bureau"
    ],
    "wof:name":"Koreana Travel",
    "wof:placetype":"venue"
},
  "geometry": {"coordinates":[-114.062782,51.043163],"type":"Point"}
}