{
  "type": "Feature",
  "properties": {
    "addr:full":"Truro NS B2N 5N6",
    "addr:postcode":"b2n 5n6",
    "iso:country":"CA",
    "sg:city":"Truro",
    "sg:classifiers":[
        {
            "category":"Home & Garden",
            "subcategory":"Household Appliances",
            "type":"Retail Goods"
        }
    ],
    "sg:phone":"+1 902 893 1101",
    "sg:postcode":"B2N 5N6",
    "sg:province":"NS",
    "sg:tags":[
        "department",
        "store"
    ],
    "wof:name":"Sears Canada Inc",
    "wof:placetype":"venue"
},
  "geometry": {"coordinates":[-63.303237915,45.3695487976],"type":"Point"}
}