{
  "type": "Feature",
  "properties": {
    "addr:full":"915 9 Ave SE Calgary AB T2G 0S5",
    "addr:housenumber":"915",
    "addr:postcode":"t2g 0s5",
    "addr:street":"9 Ave Se",
    "iso:country":"CA",
    "sg:address":"915 9 Ave SE",
    "sg:city":"Calgary",
    "sg:classifiers":[
        {
            "category":"Organizations",
            "subcategory":"Religious Organization",
            "type":"Services"
        }
    ],
    "sg:phone":"+1 403 264 8465",
    "sg:postcode":"T2G 0S5",
    "sg:province":"AB",
    "sg:tags":[
        "church"
    ],
    "wof:name":"Grace Vineyard Christian Flshp",
    "wof:placetype":"venue"
},
  "geometry": {"coordinates":[-114.041084,51.043121],"type":"Point"}
}