{
  "type": "Feature",
  "properties": {
    "addr:full":"Edmonton AB T6L 6W6",
    "addr:postcode":"t6l 6w6",
    "iso:country":"CA",
    "sg:city":"Edmonton",
    "sg:classifiers":[
        {
            "category":"Health Services",
            "subcategory":"Doctor",
            "type":"Services"
        }
    ],
    "sg:phone":"+1 780 450 3335",
    "sg:postcode":"T6L 6W6",
    "sg:province":"AB",
    "sg:tags":[
        "physician",
        "surgeon"
    ],
    "wof:name":"Buski Eye Ctr & Surgical Suite",
    "wof:placetype":"venue"
},
  "geometry": {"coordinates":[-113.427933,53.458012],"type":"Point"}
}