{
  "type": "Feature",
  "properties": {
    "addr:full":"209 St George St Annapolis Royal NS B0S 1A0",
    "addr:housenumber":"209",
    "addr:postcode":"b0s 1a0",
    "addr:street":"St George St",
    "iso:country":"CA",
    "sg:address":"209 St George St",
    "sg:city":"Annapolis Royal",
    "sg:classifiers":[
        {
            "category":"Cinema",
            "subcategory":"Movie Theater",
            "type":"Entertainment"
        }
    ],
    "sg:phone":"+1 902 532 7704",
    "sg:postcode":"B0S 1A0",
    "sg:province":"NS",
    "wof:name":"Kings Theatre",
    "wof:placetype":"venue"
},
  "geometry": {"coordinates":[-65.51902,44.745144],"type":"Point"}
}