{
  "type": "Feature",
  "properties": {
    "addr:full":"Vancouver BC V6E 1T7",
    "addr:postcode":"v6e 1t7",
    "iso:country":"CA",
    "sg:city":"Vancouver",
    "sg:classifiers":[
        {
            "category":"Social Services",
            "type":"Services"
        }
    ],
    "sg:phone":"+1 604 685 5621",
    "sg:postcode":"V6E 1T7",
    "sg:province":"BC",
    "sg:tags":[
        "counselor",
        "marriage",
        "family"
    ],
    "wof:name":"Joel Grymaloski & Assoc",
    "wof:placetype":"venue"
},
  "geometry": {"coordinates":[-123.134002685,49.2760543823],"type":"Point"}
}