{
  "type": "Feature",
  "properties": {
    "iso:country":"CA",
    "sg:address":"440 Av Du Mont-Royal E",
    "sg:city":"Montreal",
    "sg:classifiers":[
        {
            "category":"Restaurant",
            "type":"Food & Drink"
        }
    ],
    "sg:phone":"+1 514 845 5445",
    "sg:postcode":"H2J 1W1",
    "sg:province":"QC",
    "sg:tags":[
        "shop",
        "coffee",
        "cafe"
    ],
    "wof:name":"Cafe Noir",
    "wof:placetype":"venue"
},
  "geometry": {"coordinates":[-73.582336,45.524338],"type":"Point"}
}