{
  "type": "Feature",
  "properties": {
    "addr:full":"9416 Rue Main Richibucto NB E4W 4E2",
    "addr:housenumber":"9416",
    "addr:postcode":"e4w 4e2",
    "addr:street":"Rue Main",
    "iso:country":"CA",
    "sg:address":"9416 Rue Main",
    "sg:city":"Richibucto",
    "sg:classifiers":[
        {
            "category":"Shopping",
            "subcategory":"Florist",
            "type":"Retail Goods"
        }
    ],
    "sg:phone":"+1 506 523 7114",
    "sg:postcode":"E4W 4E2",
    "sg:province":"NB",
    "wof:name":"Aline Flower Boutique & Craft",
    "wof:placetype":"venue"
},
  "geometry": {"coordinates":[-64.8620223999,46.6849555969],"type":"Point"}
}