{
  "type": "Feature",
  "properties": {
    "addr:full":"80 Elizabeth Ave St. John's NL A1A 1W7",
    "addr:housenumber":"80",
    "addr:postcode":"a1a 1w7",
    "addr:street":"Elizabeth Ave",
    "iso:country":"CA",
    "sg:address":"80 Elizabeth Ave",
    "sg:city":"St. John's",
    "sg:classifiers":[
        {
            "category":"Wholesale",
            "subcategory":"Groceries",
            "type":"Manufacturing & Wholesale Goods"
        }
    ],
    "sg:phone":"+1 709 753 6655",
    "sg:postcode":"A1A 1W7",
    "sg:province":"NL",
    "sg:tags":[
        "food",
        "grocer",
        "product"
    ],
    "wof:name":"Arts Foundation",
    "wof:placetype":"venue"
},
  "geometry": {"coordinates":[-58.576462,48.554306],"type":"Point"}
}