{
  "type": "Feature",
  "properties": {
    "addr:full":"15 Riverside St New Glasgow NS B2H 2N2",
    "addr:housenumber":"15",
    "addr:postcode":"b2h 2n2",
    "addr:street":"Riverside St",
    "iso:country":"CA",
    "sg:address":"15 Riverside St",
    "sg:city":"New Glasgow",
    "sg:classifiers":[
        {
            "category":"Recreation",
            "subcategory":"Marina",
            "type":"Entertainment"
        }
    ],
    "sg:phone":"+1 902 755 3018",
    "sg:postcode":"B2H 2N2",
    "sg:province":"NS",
    "wof:name":"Riverfront Marina",
    "wof:placetype":"venue"
},
  "geometry": {"coordinates":[-62.644794,45.590412],"type":"Point"}
}