{
  "type": "Feature",
  "properties": {
    "addr:full":"517 Main St Sicamous BC V0E 2V0",
    "addr:housenumber":"517",
    "addr:postcode":"v0e 2v0",
    "addr:street":"Main St",
    "iso:country":"CA",
    "sg:address":"517 Main St",
    "sg:city":"Sicamous",
    "sg:classifiers":[
        {
            "category":"Travel",
            "subcategory":"Hotels & Motels",
            "type":"Entertainment"
        }
    ],
    "sg:phone":"+1 250 836 2525",
    "sg:postcode":"V0E 2V0",
    "sg:province":"BC",
    "wof:name":"Paradise Motel",
    "wof:placetype":"venue"
},
  "geometry": {"coordinates":[-118.97657775899999,50.8374633789],"type":"Point"}
}