{
  "type": "Feature",
  "properties": {
    "iso:country":"CA",
    "sg:address":"4576 Bowness Ave",
    "sg:city":"Powell River",
    "sg:classifiers":[
        {
            "category":"Building & Trades",
            "subcategory":"Construction",
            "type":"Services"
        }
    ],
    "sg:phone":"+1 604 485 6582",
    "sg:postcode":"V8A 3S1",
    "sg:province":"BC",
    "sg:tags":[
        "contractor"
    ],
    "wof:name":"Missio Construction Ltd",
    "wof:placetype":"venue"
},
  "geometry": {"coordinates":[-124.506462097,49.8392333984],"type":"Point"}
}