{
  "type": "Feature",
  "properties": {
    "addr:full":"235 36 St N Lethbridge AB T1H 5R8",
    "addr:housenumber":"235 36",
    "addr:postcode":"t1h 5r8",
    "addr:street":"St N",
    "iso:country":"CA",
    "sg:address":"235 36 St N",
    "sg:city":"Lethbridge",
    "sg:classifiers":[
        {
            "category":"Professional",
            "type":"Services"
        }
    ],
    "sg:phone":"+1 403 329 4462",
    "sg:postcode":"T1H 5R8",
    "sg:province":"AB",
    "sg:tags":[
        "poultry",
        "bedding",
        "establishment"
    ],
    "wof:name":"Cargill Nutrena Feeds Ltd",
    "wof:placetype":"venue"
},
  "geometry": {"coordinates":[-112.787766,49.701927],"type":"Point"}
}