{
  "type": "Feature",
  "properties": {
    "addr:full":"8388 Capstan Way # 1268 Richmond BC V7B 1K8",
    "addr:housenumber":"8388",
    "addr:postcode":"v7b 1k8",
    "addr:street":"Capstan Way # 1268",
    "iso:country":"CA",
    "sg:address":"8388 Capstan Way # 1268",
    "sg:city":"Richmond",
    "sg:classifiers":[
        {
            "category":"Real Estate",
            "subcategory":"Real Estate Operator",
            "type":"Services"
        }
    ],
    "sg:phone":"+1 604 207 0792",
    "sg:postcode":"V7B 1K8",
    "sg:province":"BC",
    "sg:tags":[
        "mall",
        "shopping",
        "center"
    ],
    "wof:name":"Union Square Shopping Ctr",
    "wof:placetype":"venue"
},
  "geometry": {"coordinates":[-123.13020299999999,49.187851],"type":"Point"}
}