{
  "type": "Feature",
  "properties": {
    "addr:full":"2002 Airport Dr Saskatoon SK S7L 6M4",
    "addr:housenumber":"2002",
    "addr:postcode":"s7l 6m4",
    "addr:street":"Airport Dr",
    "iso:country":"CA",
    "sg:address":"2002 Airport Dr",
    "sg:city":"Saskatoon",
    "sg:classifiers":[
        {
            "category":"Shopping",
            "subcategory":"Gifts & Souvenirs",
            "type":"Retail Goods"
        }
    ],
    "sg:phone":"+1 306 244 8830",
    "sg:postcode":"S7L 6M4",
    "sg:province":"SK",
    "sg:tags":[
        "shop"
    ],
    "wof:name":"Stevens Gift Shop",
    "wof:placetype":"venue"
},
  "geometry": {"coordinates":[-106.683296,52.155357],"type":"Point"}
}