{
  "type": "Feature",
  "properties": {
    "addr:full":"211 Provost St New Glasgow NS B2H 2R2",
    "addr:housenumber":"211",
    "addr:postcode":"b2h 2r2",
    "addr:street":"Provost St",
    "iso:country":"CA",
    "sg:address":"211 Provost St",
    "sg:city":"New Glasgow",
    "sg:classifiers":[
        {
            "category":"Restaurant",
            "type":"Food & Drink"
        }
    ],
    "sg:phone":"+1 902 752 4102",
    "sg:postcode":"B2H 2R2",
    "sg:province":"NS",
    "wof:name":"Ming's Restaurant",
    "wof:placetype":"venue"
},
  "geometry": {"coordinates":[-62.645638,45.5863],"type":"Point"}
}