{
  "type": "Feature",
  "properties": {
    "addr:full":"2512 Rue Lapierre Lasalle QC H8N 2W9",
    "addr:housenumber":"2512",
    "addr:postcode":"h8n 2w9",
    "addr:street":"Rue Lapierre",
    "iso:country":"CA",
    "sg:address":"2512 Rue Lapierre",
    "sg:city":"Lasalle",
    "sg:classifiers":[
        {
            "category":"Professional",
            "subcategory":"Art Services",
            "type":"Services"
        }
    ],
    "sg:phone":"+1 514 367 0483",
    "sg:postcode":"H8N 2W9",
    "sg:province":"QC",
    "sg:tags":[
        "graphic",
        "designer"
    ],
    "wof:name":"Andre Seguin Design Inc",
    "wof:placetype":"venue"
},
  "geometry": {"coordinates":[-73.629677,45.442665],"type":"Point"}
}