{
  "type": "Feature",
  "properties": {
    "addr:full":"Kelowna BC V1Y 2H5",
    "addr:postcode":"v1y 2h5",
    "iso:country":"CA",
    "sg:city":"Kelowna",
    "sg:classifiers":[
        {
            "category":"Health Services",
            "subcategory":"Doctor",
            "type":"Services"
        }
    ],
    "sg:phone":"+1 250 763 7701",
    "sg:postcode":"V1Y 2H5",
    "sg:province":"BC",
    "sg:tags":[
        "physician",
        "surgeon"
    ],
    "wof:name":"K A Canning Inc",
    "wof:placetype":"venue"
},
  "geometry": {"coordinates":[-119.489936829,49.8627281189],"type":"Point"}
}