{
  "type": "Feature",
  "properties": {
    "iso:country":"CA",
    "sg:address":"215 Av Bloomfield",
    "sg:city":"Outremont",
    "sg:classifiers":[
        {
            "category":"Education",
            "subcategory":"School",
            "type":"Public Place"
        }
    ],
    "sg:phone":"+1 514 272 7887",
    "sg:postcode":"H2V 3R6",
    "sg:province":"QC",
    "wof:name":"Nouvelle-Querbes Ecole",
    "wof:placetype":"venue"
},
  "geometry": {"coordinates":[-73.6009063721,45.5175971985],"type":"Point"}
}