{
  "type": "Feature",
  "properties": {
    "addr:full":"10214 100 Ave Fort Saskatchewan AB T8L 1Y8",
    "addr:housenumber":"10214",
    "addr:postcode":"t8l 1y8",
    "addr:street":"100 Ave",
    "iso:country":"CA",
    "sg:address":"10214 100 Ave",
    "sg:city":"Fort Saskatchewan",
    "sg:classifiers":[
        {
            "category":"Insurance",
            "subcategory":"Insurance Agent",
            "type":"Services"
        }
    ],
    "sg:phone":"+1 780 998 9888",
    "sg:postcode":"T8L 1Y8",
    "sg:province":"AB",
    "wof:name":"CO-Operators General Insurance",
    "wof:placetype":"venue"
},
  "geometry": {"coordinates":[-113.213486,53.71249],"type":"Point"}
}