{
  "type": "Feature",
  "properties": {
    "addr:full":"965 Boul Cure-Labelle # 014A Laval QC H7V 2V7",
    "addr:housenumber":"965",
    "addr:postcode":"h7v 2v7",
    "addr:street":"Boul Cure-Labelle # 014A",
    "iso:country":"CA",
    "sg:address":"965 Boul Cure-Labelle # 014A",
    "sg:city":"Laval",
    "sg:classifiers":[
        {
            "category":"Personal",
            "subcategory":"Shoe Repair & Shine",
            "type":"Services"
        }
    ],
    "sg:phone":"+1 450 682 8467",
    "sg:postcode":"H7V 2V7",
    "sg:province":"QC",
    "sg:tags":[
        "repairing",
        "boot"
    ],
    "wof:name":"Cordonnerie St Martin",
    "wof:placetype":"venue"
},
  "geometry": {"coordinates":[-73.749207,45.542011],"type":"Point"}
}