{
  "type": "Feature",
  "properties": {
    "addr:full":"105 Rue Guindon #1 St-Sauveur-Des-Monts QC J0R 1R6",
    "addr:housenumber":"105",
    "addr:postcode":"j0r 1r6",
    "addr:street":"Rue Guindon # 1 St-Sauveur-Des-Monts",
    "iso:country":"CA",
    "sg:address":"105 Rue Guindon #1",
    "sg:city":"St-Sauveur-Des-Monts",
    "sg:classifiers":[
        {
            "category":"Food & Beverages",
            "subcategory":"Specialty",
            "type":"Retail Goods"
        }
    ],
    "sg:phone":"+1 450 227 3343",
    "sg:postcode":"J0R 1R6",
    "sg:province":"QC",
    "wof:name":"Rachelle-Bery Epicerie-Sante",
    "wof:placetype":"venue"
},
  "geometry": {"coordinates":[-74.147835,45.892536],"type":"Point"}
}