{
  "type": "Feature",
  "properties": {
    "addr:full":"401 Coventry Rd Ottawa ON K1K 2C5",
    "addr:housenumber":"401",
    "addr:postcode":"k1k 2c5",
    "addr:street":"Coventry Rd",
    "iso:country":"CA",
    "sg:address":"401 Coventry Rd",
    "sg:city":"Ottawa",
    "sg:classifiers":[
        {
            "category":"Retail",
            "subcategory":"Auto Repair",
            "type":"Services"
        }
    ],
    "sg:phone":"+1 613 749 4891",
    "sg:postcode":"K1K 2C5",
    "sg:province":"ON",
    "sg:tags":[
        "repairing",
        "automobile"
    ],
    "wof:name":"Lecavalier G Parts & Svc",
    "wof:placetype":"venue"
},
  "geometry": {"coordinates":[-75.647614,45.421577],"type":"Point"}
}