{
  "type": "Feature",
  "properties": {
    "addr:full":"6455 Rue Jean-Talon E Saint-Leonard QC H1S 3E8",
    "addr:housenumber":"6455",
    "addr:postcode":"h1s 3e8",
    "addr:street":"Rue Jean-Talon E",
    "iso:country":"CA",
    "sg:address":"6455 Rue Jean-Talon E",
    "sg:city":"Saint-Leonard",
    "sg:classifiers":[
        {
            "category":"Professional",
            "subcategory":"Accounting & Tax Preparation",
            "type":"Services"
        }
    ],
    "sg:phone":"+1 514 251 2252",
    "sg:postcode":"H1S 3E8",
    "sg:province":"QC",
    "sg:tags":[
        "accountant"
    ],
    "wof:name":"Brooks Di Santo Inc",
    "wof:placetype":"venue"
},
  "geometry": {"coordinates":[-73.5754852295,45.5918083191],"type":"Point"}
}