{
  "type": "Feature",
  "properties": {
    "iso:country":"CA",
    "sg:address":"300 Killaly St W",
    "sg:city":"Port Colborne",
    "sg:classifiers":[
        {
            "category":"Manufacturing",
            "subcategory":"Signs",
            "type":"Manufacturing & Wholesale Goods"
        }
    ],
    "sg:phone":"+1 905 834 5180",
    "sg:postcode":"L3K 6A6",
    "sg:province":"ON",
    "wof:name":"Newport Signs",
    "wof:placetype":"venue"
},
  "geometry": {"coordinates":[-79.26345825200001,42.8914909363],"type":"Point"}
}