{
  "type": "Feature",
  "properties": {
    "addr:full":"365 Victoria St Clinton ON N0M 1L0",
    "addr:housenumber":"365",
    "addr:postcode":"n0m 1l0",
    "addr:street":"Victoria St",
    "iso:country":"CA",
    "sg:address":"365 Victoria St",
    "sg:city":"Clinton",
    "sg:classifiers":[
        {
            "category":"Autos & Motor Vehicles",
            "subcategory":"Automobile Sales",
            "type":"Retail Goods"
        }
    ],
    "sg:phone":"+1 519 482 7051",
    "sg:postcode":"N0M 1L0",
    "sg:province":"ON",
    "sg:tags":[
        "car",
        "dealer"
    ],
    "wof:name":"P J Goldsworthy Motor Sales",
    "wof:placetype":"venue"
},
  "geometry": {"coordinates":[-81.53510300000001,43.608288],"type":"Point"}
}