{
  "type": "Feature",
  "properties": {
    "addr:full":"Red Deer AB T4P 1T5",
    "addr:postcode":"t4p 1t5",
    "iso:country":"CA",
    "sg:city":"Red Deer",
    "sg:classifiers":[
        {
            "category":"Manufacturing",
            "subcategory":"Printing",
            "type":"Manufacturing & Wholesale Goods"
        }
    ],
    "sg:phone":"+1 403 343 2404",
    "sg:postcode":"T4P 1T5",
    "sg:province":"AB",
    "sg:tags":[
        "printer"
    ],
    "wof:name":"Kindopp's Digital Printing",
    "wof:placetype":"venue"
},
  "geometry": {"coordinates":[-113.813728,52.303146],"type":"Point"}
}