{
  "type": "Feature",
  "properties": {
    "addr:full":"Hamilton ON L8K 5W9",
    "addr:postcode":"l8k 5w9",
    "iso:country":"CA",
    "sg:city":"Hamilton",
    "sg:classifiers":[
        {
            "category":"Retail",
            "subcategory":"Laundry & Dry Cleaning",
            "type":"Services"
        }
    ],
    "sg:phone":"+1 905 561 2611",
    "sg:postcode":"L8K 5W9",
    "sg:province":"ON",
    "sg:tags":[
        "cleaners"
    ],
    "wof:name":"White Tower Dry Cleaners",
    "wof:placetype":"venue"
},
  "geometry": {"coordinates":[-79.7866516113,43.2097396851],"type":"Point"}
}