{
  "type": "Feature",
  "properties": {
    "addr:full":"224 Toryork Dr North York ON M9L 1Y1",
    "addr:housenumber":"224",
    "addr:postcode":"m9l 1y1",
    "addr:street":"Toryork Dr",
    "iso:country":"CA",
    "sg:address":"224 Toryork Dr",
    "sg:city":"North York",
    "sg:classifiers":[
        {
            "category":"Shopping",
            "type":"Retail Goods"
        }
    ],
    "sg:phone":"+1 416 749 6811",
    "sg:postcode":"M9L 1Y1",
    "sg:province":"ON",
    "sg:tags":[
        "awning",
        "canopy"
    ],
    "wof:name":"Continental Aluminum Awning CO",
    "wof:placetype":"venue"
},
  "geometry": {"coordinates":[-79.560829,43.761284],"type":"Point"}
}