{
  "type": "Feature",
  "properties": {
    "addr:full":"Boileau QC J0T 1G0",
    "addr:postcode":"j0t 1g0",
    "iso:country":"CA",
    "sg:city":"Boileau",
    "sg:classifiers":[
        {
            "category":"Travel",
            "subcategory":"Campground",
            "type":"Entertainment"
        }
    ],
    "sg:phone":"+1 819 687 9111",
    "sg:postcode":"J0T 1G0",
    "sg:province":"QC",
    "sg:tags":[
        "camp",
        "fishing"
    ],
    "wof:name":"Laurentian Wildlife Estate Inc",
    "wof:placetype":"venue"
},
  "geometry": {"coordinates":[-74.7133178711,45.9516067505],"type":"Point"}
}