{
  "type": "Feature",
  "properties": {
    "addr:full":"Trans Canada Hwy Rte 1 Crapaud PE C0A 1J0",
    "addr:postcode":"c0a 1j0",
    "addr:street":"Trans Canada Hwy Rte 1",
    "iso:country":"CA",
    "sg:address":"Trans Canada Hwy Rte 1",
    "sg:city":"Crapaud",
    "sg:classifiers":[
        {
            "category":"Organizations",
            "subcategory":"Religious Organization",
            "type":"Services"
        }
    ],
    "sg:phone":"+1 902 658 2109",
    "sg:postcode":"C0A 1J0",
    "sg:province":"PE",
    "sg:tags":[
        "church"
    ],
    "wof:name":"St John's Anglican Church Hall",
    "wof:placetype":"venue"
},
  "geometry": {"coordinates":[-63.499989,46.238556],"type":"Point"}
}