{
  "type": "Feature",
  "properties": {
    "addr:full":"Conception Bay South NL A1W 2B7",
    "addr:postcode":"a1w 2b7",
    "iso:country":"CA",
    "sg:city":"Conception Bay South",
    "sg:classifiers":[
        {
            "category":"Building & Trades",
            "subcategory":"Construction",
            "type":"Services"
        }
    ],
    "sg:phone":"+1 709 781 2111",
    "sg:postcode":"A1W 2B7",
    "sg:province":"NL",
    "sg:tags":[
        "dry wall",
        "contractor"
    ],
    "wof:name":"Ronald White Acoustical Clngs",
    "wof:placetype":"venue"
},
  "geometry": {"coordinates":[-52.968876,47.512619],"type":"Point"}
}