{
  "type": "Feature",
  "properties": {
    "addr:full":"1570 18th St N Brandon MB R7C 1A5",
    "addr:housenumber":"1570",
    "addr:postcode":"r7c 1a5",
    "addr:street":"18Th St N",
    "iso:country":"CA",
    "sg:address":"1570 18th St N",
    "sg:city":"Brandon",
    "sg:classifiers":[
        {
            "category":"Shopping",
            "subcategory":"Shoes",
            "type":"Retail Goods"
        }
    ],
    "sg:phone":"+1 204 727 1453",
    "sg:postcode":"R7C 1A5",
    "sg:province":"MB",
    "wof:name":"Payless Shoe Source",
    "wof:placetype":"venue"
},
  "geometry": {"coordinates":[-99.962097168,49.8760261536],"type":"Point"}
}