{
  "type": "Feature",
  "properties": {
    "addr:full":"16 Cedar St S Timmins ON P4N 2G4",
    "addr:housenumber":"16",
    "addr:postcode":"p4n 2g4",
    "addr:street":"Cedar St S",
    "iso:country":"CA",
    "sg:address":"16 Cedar St S",
    "sg:city":"Timmins",
    "sg:classifiers":[
        {
            "category":"Health Services",
            "subcategory":"Doctor",
            "type":"Services"
        }
    ],
    "sg:phone":"+1 705 264 1259",
    "sg:postcode":"P4N 2G4",
    "sg:province":"ON",
    "sg:tags":[
        "dentist"
    ],
    "wof:name":"Humphreys, David A DDS",
    "wof:placetype":"venue"
},
  "geometry": {"coordinates":[-81.32944488530001,48.4757499695],"type":"Point"}
}