{
  "type": "Feature",
  "properties": {
    "addr:full":"51 Broadway St Tillsonburg ON N4G 3P4",
    "addr:housenumber":"51",
    "addr:postcode":"n4g 3p4",
    "addr:street":"Broadway St",
    "iso:country":"CA",
    "sg:address":"51 Broadway St",
    "sg:city":"Tillsonburg",
    "sg:classifiers":[
        {
            "category":"Sports & Exercise",
            "subcategory":"Bowling",
            "type":"Entertainment"
        }
    ],
    "sg:phone":"+1 519 842 5711",
    "sg:postcode":"N4G 3P4",
    "sg:province":"ON",
    "sg:tags":[
        "center"
    ],
    "wof:name":"Broadway Lanes",
    "wof:placetype":"venue"
},
  "geometry": {"coordinates":[-80.7259521484,42.8586387634],"type":"Point"}
}