{
  "type": "Feature",
  "properties": {
    "addr:full":"317 Speedvale Ave E # 4 Guelph ON N1E 1N3",
    "addr:housenumber":"317",
    "addr:postcode":"n1e 1n3",
    "addr:street":"Speedvale Ave E # 4",
    "iso:country":"CA",
    "sg:address":"317 Speedvale Ave E # 4",
    "sg:city":"Guelph",
    "sg:classifiers":[
        {
            "category":"Banks & Credit Unions",
            "subcategory":"Investment Brokerage",
            "type":"Services"
        }
    ],
    "sg:phone":"+1 519 836 2550",
    "sg:postcode":"N1E 1N3",
    "sg:province":"ON",
    "sg:tags":[
        "consultant",
        "financing",
        "planning",
        "financial"
    ],
    "wof:name":"Investment Planning Counsel",
    "wof:placetype":"venue"
},
  "geometry": {"coordinates":[-80.25897999999999,43.565006],"type":"Point"}
}