{
  "type": "Feature",
  "properties": {
    "addr:full":"525 North Park Dr Brampton ON L6S 5X4",
    "addr:housenumber":"525",
    "addr:postcode":"l6s 5x4",
    "addr:street":"North Park Dr",
    "iso:country":"CA",
    "sg:address":"525 North Park Dr",
    "sg:city":"Brampton",
    "sg:classifiers":[
        {
            "category":"Organizations",
            "subcategory":"Religious Organization",
            "type":"Services"
        }
    ],
    "sg:phone":"+1 905 450 8504",
    "sg:postcode":"L6S 5X4",
    "sg:province":"ON",
    "wof:name":"Aga Khan Coucil For Ontario",
    "wof:placetype":"venue"
},
  "geometry": {"coordinates":[-79.753654,43.727013],"type":"Point"}
}