{
  "type": "Feature",
  "properties": {
    "addr:full":"280 43E Av Pointe-Calumet QC J0N 1G2",
    "addr:housenumber":"280",
    "addr:postcode":"j0n 1g2",
    "addr:street":"43E Av Pointe-Calumet",
    "iso:country":"CA",
    "sg:address":"280 43E Av",
    "sg:city":"Pointe-Calumet",
    "sg:classifiers":[
        {
            "category":"Personal",
            "subcategory":"Beauty Salon",
            "type":"Services"
        }
    ],
    "sg:phone":"+1 450 473 4846",
    "sg:postcode":"J0N 1G2",
    "sg:province":"QC",
    "wof:name":"Salon DE Coiffure Stephane",
    "wof:placetype":"venue"
},
  "geometry": {"coordinates":[-73.9733200073,45.4984016418],"type":"Point"}
}