{
  "type": "Feature",
  "properties": {
    "addr:full":"5 Rue Saint-Jacques S Causapscal QC G0J 1J0",
    "addr:housenumber":"5",
    "addr:postcode":"g0j 1j0",
    "addr:street":"Rue Saint-Jacques S",
    "iso:country":"CA",
    "sg:address":"5 Rue Saint-Jacques S",
    "sg:city":"Causapscal",
    "sg:classifiers":[
        {
            "category":"Organizations",
            "subcategory":"Professional Association",
            "type":"Services"
        }
    ],
    "sg:phone":"+1 418 756 6048",
    "sg:postcode":"G0J 1J0",
    "sg:province":"QC",
    "sg:tags":[
        "government"
    ],
    "wof:name":"Chambre DE Commerce Kiosque",
    "wof:placetype":"venue"
},
  "geometry": {"coordinates":[-67.221436,48.353817],"type":"Point"}
}