{
  "type": "Feature",
  "properties": {
    "addr:full":"Ottawa ON K1G 5A3",
    "addr:postcode":"k1g 5a3",
    "iso:country":"CA",
    "sg:city":"Ottawa",
    "sg:classifiers":[
        {
            "category":"Museum",
            "type":"Entertainment"
        }
    ],
    "sg:phone":"+1 613 991 3044",
    "sg:postcode":"K1G 5A3",
    "sg:province":"ON",
    "wof:name":"Canada Agriculture Museum",
    "wof:placetype":"venue"
},
  "geometry": {"coordinates":[-75.6247253418,45.4023475647],"type":"Point"}
}