{
  "type": "Feature",
  "properties": {
    "addr:full":"17 Wellington St N New Liskeard ON P0J 1P0",
    "addr:housenumber":"17",
    "addr:postcode":"p0j 1p0",
    "addr:street":"Wellington St N New",
    "iso:country":"CA",
    "sg:address":"17 Wellington St N",
    "sg:city":"New Liskeard",
    "sg:classifiers":[
        {
            "category":"Social Services",
            "type":"Services"
        }
    ],
    "sg:phone":"+1 705 647 8558",
    "sg:postcode":"P0J 1P0",
    "sg:province":"ON",
    "sg:tags":[
        "organization",
        "welfare"
    ],
    "wof:name":"Children's Treatment Ctr",
    "wof:placetype":"venue"
},
  "geometry": {"coordinates":[-79.67274500000001,47.508926],"type":"Point"}
}