{
  "type": "Feature",
  "properties": {
    "iso:country":"CA",
    "sg:address":"120 White Oak Dr E",
    "sg:city":"Sault Ste Marie",
    "sg:classifiers":[
        {
            "category":"Retail",
            "subcategory":"Auto Repair",
            "type":"Services"
        }
    ],
    "sg:phone":"+1 705 949 2886",
    "sg:postcode":"P6B 4J8",
    "sg:province":"ON",
    "sg:tags":[
        "machine",
        "automobile",
        "shop"
    ],
    "wof:name":"Paul's Engine Rebuilding Inc",
    "wof:placetype":"venue"
},
  "geometry": {"coordinates":[-84.33191680909999,46.5374031067],"type":"Point"}
}