{
  "type": "Feature",
  "properties": {
    "addr:full":"333 Wilson Ave North York ON M3H 1T2",
    "addr:housenumber":"333",
    "addr:postcode":"m3h 1t2",
    "addr:street":"Wilson Ave",
    "iso:country":"CA",
    "sg:address":"333 Wilson Ave",
    "sg:city":"North York",
    "sg:classifiers":[
        {
            "category":"Professional",
            "subcategory":"Business Services",
            "type":"Services"
        }
    ],
    "sg:phone":"+1 416 635 1699",
    "sg:postcode":"M3H 1T2",
    "sg:province":"ON",
    "wof:name":"Jinkholm International Inc",
    "wof:placetype":"venue"
},
  "geometry": {"coordinates":[-79.4360580444,43.736831665],"type":"Point"}
}