{
  "type": "Feature",
  "properties": {
    "iso:country":"CA",
    "sg:address":"5857 12 St SE",
    "sg:city":"Calgary",
    "sg:classifiers":[
        {
            "category":"Wholesale",
            "subcategory":"Scrap",
            "type":"Manufacturing & Wholesale Goods"
        }
    ],
    "sg:phone":"+1 403 252 7787",
    "sg:postcode":"T2H 2X9",
    "sg:province":"AB",
    "sg:tags":[
        "salvage",
        "merchandise",
        "metal",
        "surplus",
        "iron"
    ],
    "wof:name":"Navajo Metals",
    "wof:placetype":"venue"
},
  "geometry": {"coordinates":[-114.033035278,51.0012016296],"type":"Point"}
}