{
  "type": "Feature",
  "properties": {
    "iso:country":"CA",
    "sg:address":"307 Main St",
    "sg:city":"Watrous",
    "sg:classifiers":[
        {
            "category":"Utilities",
            "subcategory":"Mobile Phone",
            "type":"Services"
        }
    ],
    "sg:phone":"+1 306 946 3542",
    "sg:postcode":"S0K 4T0",
    "sg:province":"SK",
    "sg:tags":[
        "telephone",
        "cellular",
        "furniture"
    ],
    "wof:name":"Watrous Furniture & Appliances",
    "wof:placetype":"venue"
},
  "geometry": {"coordinates":[-105.46733856199999,51.6740036011],"type":"Point"}
}