{
  "type": "Feature",
  "properties": {
    "addr:full":"2340 Industrial St Burlington ON L7P 1A1",
    "addr:housenumber":"2340",
    "addr:postcode":"l7p 1a1",
    "addr:street":"Industrial St",
    "iso:country":"CA",
    "sg:address":"2340 Industrial St",
    "sg:city":"Burlington",
    "sg:classifiers":[
        {
            "category":"Retail",
            "subcategory":"Auto Repair",
            "type":"Services"
        }
    ],
    "sg:phone":"+1 905 335 4167",
    "sg:postcode":"L7P 1A1",
    "sg:province":"ON",
    "sg:tags":[
        "transmission"
    ],
    "wof:name":"Mainway Service Ctr",
    "wof:placetype":"venue"
},
  "geometry": {"coordinates":[-79.812325,43.349606],"type":"Point"}
}