{
  "type": "Feature",
  "properties": {
    "addr:full":"Farm Melville SK S0A 2P0",
    "addr:postcode":"s0a 2p0",
    "iso:country":"CA",
    "sg:address":"Farm",
    "sg:city":"Melville",
    "sg:classifiers":[
        {
            "category":"Retail",
            "subcategory":"Repair Shop",
            "type":"Services"
        }
    ],
    "sg:phone":"+1 306 728 3416",
    "sg:postcode":"S0A 2P0",
    "sg:province":"SK",
    "sg:tags":[
        "welding"
    ],
    "wof:name":"Bucsis Mobile Welding & Fabs",
    "wof:placetype":"venue"
},
  "geometry": {"coordinates":[-102.818237,50.93169],"type":"Point"}
}