{
  "type": "Feature",
  "properties": {
    "addr:full":"Vancouver BC V5Z 3A7",
    "addr:postcode":"v5z 3a7",
    "iso:country":"CA",
    "sg:city":"Vancouver",
    "sg:classifiers":[
        {
            "category":"Health Services",
            "subcategory":"Health Practitioner",
            "type":"Services"
        }
    ],
    "sg:phone":"+1 604 325 7666",
    "sg:postcode":"V5Z 3A7",
    "sg:province":"BC",
    "sg:tags":[
        "acupuncture"
    ],
    "wof:name":"Acumedic Centre",
    "wof:placetype":"venue"
},
  "geometry": {"coordinates":[-123.115891,49.232815],"type":"Point"}
}