{
  "type": "Feature",
  "properties": {
    "addr:full":"3279 Rue Legendre E Montreal QC H1Z 1P3",
    "addr:housenumber":"3279",
    "addr:postcode":"h1z 1p3",
    "addr:street":"Rue Legendre E",
    "iso:country":"CA",
    "sg:address":"3279 Rue Legendre E",
    "sg:city":"Montreal",
    "sg:classifiers":[
        {
            "category":"Personal",
            "subcategory":"Beauty Salon",
            "type":"Services"
        }
    ],
    "sg:phone":"+1 514 385 1003",
    "sg:postcode":"H1Z 1P3",
    "sg:province":"QC",
    "wof:name":"Salon Coupe-Mode",
    "wof:placetype":"venue"
},
  "geometry": {"coordinates":[-73.62641143800001,45.5729484558],"type":"Point"}
}