{
  "type": "Feature",
  "properties": {
    "addr:full":"19 Ch Brazeau St-Sauveur QC J0R 1R7",
    "addr:housenumber":"19",
    "addr:postcode":"j0r 1r7",
    "addr:street":"Ch Brazeau St-Sauveur",
    "iso:country":"CA",
    "sg:address":"19 Ch Brazeau",
    "sg:city":"St-Sauveur",
    "sg:classifiers":[
        {
            "category":"Professional",
            "subcategory":"Accounting & Tax Preparation",
            "type":"Services"
        }
    ],
    "sg:phone":"+1 450 965 8166",
    "sg:postcode":"J0R 1R7",
    "sg:province":"QC",
    "sg:tags":[
        "accountant",
        "inventory"
    ],
    "wof:name":"Comptec Sg Inc",
    "wof:placetype":"venue"
},
  "geometry": {"coordinates":[-74.157623,45.913925],"type":"Point"}
}