{
  "type": "Feature",
  "properties": {
    "addr:full":"1028 2nd Ave E Owen Sound ON N4K 2H7",
    "addr:housenumber":"1028",
    "addr:postcode":"n4k 2h7",
    "addr:street":"2Nd Ave E",
    "iso:country":"CA",
    "sg:address":"1028 2nd Ave E",
    "sg:city":"Owen Sound",
    "sg:classifiers":[
        {
            "category":"Shopping",
            "subcategory":"Used Merchandise",
            "type":"Retail Goods"
        }
    ],
    "sg:phone":"+1 519 371 4991",
    "sg:postcode":"N4K 2H7",
    "sg:province":"ON",
    "sg:tags":[
        "book",
        "rare",
        "dealer"
    ],
    "wof:name":"Mike's Book Store",
    "wof:placetype":"venue"
},
  "geometry": {"coordinates":[-80.94300800000001,44.568596],"type":"Point"}
}