{
  "type": "Feature",
  "properties": {
    "addr:full":"53 Duke St Elmira ON N3B 2X6",
    "addr:housenumber":"53",
    "addr:postcode":"n3b 2x6",
    "addr:street":"Duke St",
    "iso:country":"CA",
    "sg:address":"53 Duke St",
    "sg:city":"Elmira",
    "sg:classifiers":[
        {
            "category":"Personal",
            "subcategory":"Beauty Salon",
            "type":"Services"
        }
    ],
    "sg:phone":"+1 519 669 3924",
    "sg:postcode":"N3B 2X6",
    "sg:province":"ON",
    "wof:name":"Marjorie's Hairstyling",
    "wof:placetype":"venue"
},
  "geometry": {"coordinates":[-80.5569076538,43.5934944153],"type":"Point"}
}