{
  "type": "Feature",
  "properties": {
    "iso:country":"CA",
    "sg:address":"2555 Av Du Havre-Des-Iles",
    "sg:city":"Laval",
    "sg:classifiers":[
        {
            "category":"Education",
            "subcategory":"Special Training",
            "type":"Public Place"
        }
    ],
    "sg:phone":"+1 450 687 2081",
    "sg:postcode":"H7W 4R4",
    "sg:province":"QC",
    "sg:tags":[
        "school",
        "language"
    ],
    "wof:name":"Anglais Rapide",
    "wof:placetype":"venue"
},
  "geometry": {"coordinates":[-73.75546264650001,45.5229454041],"type":"Point"}
}