{
  "type": "Feature",
  "properties": {
    "iso:country":"CA",
    "sg:address":"2111 Rue Dick-Irvin",
    "sg:city":"Montreal",
    "sg:classifiers":[
        {
            "category":"Real Estate",
            "subcategory":"Real Estate Agent",
            "type":"Services"
        }
    ],
    "sg:phone":"+1 514 931 3158",
    "sg:postcode":"H3K 3K1",
    "sg:province":"QC",
    "sg:tags":[
        "cooperative"
    ],
    "wof:name":"Cooperative Le Parchemin",
    "wof:placetype":"venue"
},
  "geometry": {"coordinates":[-73.550331,45.478249],"type":"Point"}
}