{
  "type": "Feature",
  "properties": {
    "iso:country":"CA",
    "sg:address":"3402 Otter Bay Rd",
    "sg:city":"Pender Island",
    "sg:classifiers":[
        {
            "category":"Building & Trades",
            "subcategory":"Construction",
            "type":"Services"
        }
    ],
    "sg:phone":"+1 250 629 2019",
    "sg:postcode":"V0N 2M1",
    "sg:province":"BC",
    "sg:tags":[
        "contractor"
    ],
    "wof:name":"Salish Construction CO Ltd",
    "wof:placetype":"venue"
},
  "geometry": {"coordinates":[-123.301170349,48.7998123169],"type":"Point"}
}