{
  "type": "Feature",
  "properties": {
    "addr:full":"608 Rue Saint-Georges Saint-Jerome QC J7Z 5B8",
    "addr:housenumber":"608",
    "addr:postcode":"j7z 5b8",
    "addr:street":"Rue Saint-Georges Saint-Jerome",
    "iso:country":"CA",
    "sg:address":"608 Rue Saint-Georges",
    "sg:city":"Saint-Jerome",
    "sg:classifiers":[
        {
            "category":"Wholesale",
            "subcategory":"Groceries",
            "type":"Manufacturing & Wholesale Goods"
        }
    ],
    "sg:phone":"+1 450 432 2034",
    "sg:postcode":"J7Z 5B8",
    "sg:province":"QC",
    "sg:tags":[
        "cocoa",
        "chocolate"
    ],
    "wof:name":"Boutique Leonidas",
    "wof:placetype":"venue"
},
  "geometry": {"coordinates":[-74.001717,45.784077],"type":"Point"}
}