{
  "type": "Feature",
  "properties": {
    "iso:country":"CA",
    "sg:address":"3018 Rue DE LA Retraite",
    "sg:city":"Sainte-Foy",
    "sg:classifiers":[
        {
            "category":"Health Services",
            "subcategory":"Health Practitioner",
            "type":"Services"
        }
    ],
    "sg:phone":"+1 418 650 0218",
    "sg:postcode":"G1W 2H2",
    "sg:province":"QC",
    "sg:tags":[
        "psychologist"
    ],
    "wof:name":"Services Psychologiques",
    "wof:placetype":"venue"
},
  "geometry": {"coordinates":[-71.2844238281,46.7540092468],"type":"Point"}
}