{
  "type": "Feature",
  "properties": {
    "addr:full":"2131 Airport Dr Saskatoon SK S7L 7E1",
    "addr:housenumber":"2131",
    "addr:postcode":"s7l 7e1",
    "addr:street":"Airport Dr",
    "iso:country":"CA",
    "sg:address":"2131 Airport Dr",
    "sg:city":"Saskatoon",
    "sg:classifiers":[
        {
            "category":"Wholesale",
            "subcategory":"Machinery & Supplies",
            "type":"Manufacturing & Wholesale Goods"
        }
    ],
    "sg:phone":"+1 306 933 8585",
    "sg:postcode":"S7L 7E1",
    "sg:province":"SK",
    "sg:tags":[
        "agricultural",
        "implement"
    ],
    "wof:name":"Morris Industries Ltd",
    "wof:placetype":"venue"
},
  "geometry": {"coordinates":[-106.68711853000001,52.1567726135],"type":"Point"}
}