{
  "type": "Feature",
  "properties": {
    "addr:full":"3 Westmount Car Westmount QC H3Z 2S5",
    "addr:housenumber":"3",
    "addr:postcode":"h3z 2s5",
    "addr:street":"Westmount",
    "iso:country":"CA",
    "sg:address":"3 Westmount Car",
    "sg:city":"Westmount",
    "sg:classifiers":[
        {
            "category":"Real Estate",
            "subcategory":"Real Estate Agent",
            "type":"Services"
        }
    ],
    "sg:phone":"+1 514 369 5857",
    "sg:postcode":"H3Z 2S5",
    "sg:province":"QC",
    "wof:name":"Brentwood Properties Inc",
    "wof:placetype":"venue"
},
  "geometry": {"coordinates":[-73.596558,45.484959],"type":"Point"}
}