{
  "type": "Feature",
  "properties": {
    "addr:full":"300 Ottawa St N Hamilton ON L8H 3Z9",
    "addr:housenumber":"300",
    "addr:postcode":"l8h 3z9",
    "addr:street":"Ottawa St N",
    "iso:country":"CA",
    "sg:address":"300 Ottawa St N",
    "sg:city":"Hamilton",
    "sg:classifiers":[
        {
            "category":"Shopping",
            "subcategory":"Clothing, Apparel, & Fashions",
            "type":"Retail Goods"
        }
    ],
    "sg:phone":"+1 905 549 4041",
    "sg:postcode":"L8H 3Z9",
    "sg:province":"ON",
    "sg:tags":[
        "shop",
        "bridal"
    ],
    "wof:name":"Textile Centre",
    "wof:placetype":"venue"
},
  "geometry": {"coordinates":[-79.8163986206,43.2503547668],"type":"Point"}
}