{
  "type": "Feature",
  "properties": {
    "iso:country":"CA",
    "sg:address":"6574 Hastings St",
    "sg:city":"Burnaby",
    "sg:classifiers":[
        {
            "category":"Restaurant",
            "type":"Food & Drink"
        }
    ],
    "sg:phone":"+1 604 291 1323",
    "sg:postcode":"V5B 1S2",
    "sg:province":"BC",
    "wof:name":"Cockney Kings Fish & Chips",
    "wof:placetype":"venue"
},
  "geometry": {"coordinates":[-122.967567444,49.2801361084],"type":"Point"}
}