{
  "type": "Feature",
  "properties": {
    "iso:country":"CA",
    "sg:address":"4974 Main St",
    "sg:city":"Dorchester",
    "sg:classifiers":[
        {
            "category":"Museum",
            "type":"Entertainment"
        }
    ],
    "sg:phone":"+1 506 379 6633",
    "sg:postcode":"E4K 2Z1",
    "sg:province":"NB",
    "wof:name":"Keillor House",
    "wof:placetype":"venue"
},
  "geometry": {"coordinates":[-64.5167770386,45.9006576538],"type":"Point"}
}