{
  "type": "Feature",
  "properties": {
    "addr:full":"Grand-Mere QC G9T 2H2",
    "addr:postcode":"g9t 2h2",
    "iso:country":"CA",
    "sg:city":"Grand-Mere",
    "sg:classifiers":[
        {
            "category":"Professional",
            "subcategory":"Lawyer & Legal Services",
            "type":"Services"
        }
    ],
    "sg:phone":"+1 819 538 7696",
    "sg:postcode":"G9T 2H2",
    "sg:province":"QC",
    "sg:tags":[
        "notary",
        "plan"
    ],
    "wof:name":"Bourbeau, Lucie",
    "wof:placetype":"venue"
},
  "geometry": {"coordinates":[-72.690376,46.615971],"type":"Point"}
}