{
  "type": "Feature",
  "properties": {
    "addr:full":"191 Glenbush St Winnipeg MB R3R 0N8",
    "addr:housenumber":"191",
    "addr:postcode":"r3r 0n8",
    "addr:street":"Glenbush St",
    "iso:country":"CA",
    "sg:address":"191 Glenbush St",
    "sg:city":"Winnipeg",
    "sg:classifiers":[
        {
            "category":"Manufacturing",
            "subcategory":"Signs",
            "type":"Manufacturing & Wholesale Goods"
        }
    ],
    "sg:phone":"+1 204 831 8076",
    "sg:postcode":"R3R 0N8",
    "sg:province":"MB",
    "wof:name":"Lighthouse Mobile Signs",
    "wof:placetype":"venue"
},
  "geometry": {"coordinates":[-97.2902832031,49.8466262817],"type":"Point"}
}