{
  "type": "Feature",
  "properties": {
    "iso:country":"CA",
    "sg:address":"106 Kent St",
    "sg:city":"London",
    "sg:classifiers":[
        {
            "category":"Organizations",
            "subcategory":"Membership Organization",
            "type":"Services"
        }
    ],
    "sg:phone":"+1 519 438 3218",
    "sg:postcode":"N6A 1L1",
    "sg:province":"ON",
    "wof:name":"Islamic Call Society of London",
    "wof:placetype":"venue"
},
  "geometry": {"coordinates":[-81.254265,42.987217],"type":"Point"}
}