{
  "type": "Feature",
  "properties": {
    "addr:full":"658 Main St W Port Colborne ON L3K 5V4",
    "addr:housenumber":"658",
    "addr:postcode":"l3k 5v4",
    "addr:street":"Main St W",
    "iso:country":"CA",
    "sg:address":"658 Main St W",
    "sg:city":"Port Colborne",
    "sg:classifiers":[
        {
            "category":"Autos & Motor Vehicles",
            "subcategory":"Auto Supplies",
            "type":"Retail Goods"
        }
    ],
    "sg:phone":"+1 905 835 8120",
    "sg:postcode":"L3K 5V4",
    "sg:province":"ON",
    "sg:tags":[
        "automobile",
        "parts"
    ],
    "wof:name":"Young Automotive Professionals",
    "wof:placetype":"venue"
},
  "geometry": {"coordinates":[-79.2714538574,42.8932113647],"type":"Point"}
}