{
  "type": "Feature",
  "properties": {
    "addr:full":"Richmond Hill ON L4C 7A2",
    "addr:postcode":"l4c 7a2",
    "iso:country":"CA",
    "sg:city":"Richmond Hill",
    "sg:classifiers":[
        {
            "category":"Personal",
            "subcategory":"Tanning Parlor",
            "type":"Services"
        }
    ],
    "sg:phone":"+1 905 707 0406",
    "sg:postcode":"L4C 7A2",
    "sg:province":"ON",
    "sg:tags":[
        "salon"
    ],
    "wof:name":"California Waves Tanning",
    "wof:placetype":"venue"
},
  "geometry": {"coordinates":[-79.43293,43.851902],"type":"Point"}
}