{
  "type": "Feature",
  "properties": {
    "iso:country":"CA",
    "sg:address":"130 Center St",
    "sg:city":"Dashwood",
    "sg:classifiers":[
        {
            "category":"Retail",
            "subcategory":"Auto Repair",
            "type":"Services"
        }
    ],
    "sg:phone":"+1 519 237 3322",
    "sg:postcode":"N0M 1N0",
    "sg:province":"ON",
    "sg:tags":[
        "repairing",
        "automobile"
    ],
    "wof:name":"Brian's Service Ctr",
    "wof:placetype":"venue"
},
  "geometry": {"coordinates":[-81.6351547241,43.3464584351],"type":"Point"}
}