{
  "type": "Feature",
  "properties": {
    "addr:full":"130 Center St Dashwood ON N0M 1N0",
    "addr:housenumber":"130",
    "addr:postcode":"n0m 1n0",
    "addr:street":"Center St",
    "iso:country":"CA",
    "sg:address":"130 Center St",
    "sg:city":"Dashwood",
    "sg:classifiers":[
        {
            "category":"Retail",
            "subcategory":"Auto Repair",
            "type":"Services"
        }
    ],
    "sg:phone":"+1 519 237 3322",
    "sg:postcode":"N0M 1N0",
    "sg:province":"ON",
    "sg:tags":[
        "repairing",
        "automobile"
    ],
    "wof:name":"Brian's Service Ctr",
    "wof:placetype":"venue"
},
  "geometry": {"coordinates":[-81.6351547241,43.3464584351],"type":"Point"}
}