{
  "type": "Feature",
  "properties": {
    "addr:full":"Medicine Hat AB T1A 0B5",
    "addr:postcode":"t1a 0b5",
    "iso:country":"CA",
    "sg:city":"Medicine Hat",
    "sg:classifiers":[
        {
            "category":"Manufacturing",
            "subcategory":"Metals",
            "type":"Manufacturing & Wholesale Goods"
        }
    ],
    "sg:phone":"+1 403 526 3342",
    "sg:postcode":"T1A 0B5",
    "sg:province":"AB",
    "sg:tags":[
        "steel"
    ],
    "wof:name":"Metal Mart Ltd",
    "wof:placetype":"venue"
},
  "geometry": {"coordinates":[-110.705963,50.024513],"type":"Point"}
}