{
  "type": "Feature",
  "properties": {
    "iso:country":"CA",
    "sg:address":"6857 Dale Rd",
    "sg:city":"Port Hope",
    "sg:classifiers":[
        {
            "category":"Freight",
            "type":"Transportation"
        }
    ],
    "sg:phone":"+1 905 885 1787",
    "sg:postcode":"L1A 3V6",
    "sg:province":"ON",
    "sg:tags":[
        "commercial",
        "storage"
    ],
    "wof:name":"Dale Corners Storage",
    "wof:placetype":"venue"
},
  "geometry": {"coordinates":[-78.2863235474,43.9889564514],"type":"Point"}
}