{
  "type": "Feature",
  "properties": {
    "addr:full":"Kelowna BC V1Z 2S9",
    "addr:postcode":"v1z 2s9",
    "iso:country":"CA",
    "sg:city":"Kelowna",
    "sg:classifiers":[
        {
            "category":"Manufacturing",
            "subcategory":"Tools & Machinery",
            "type":"Manufacturing & Wholesale Goods"
        }
    ],
    "sg:phone":"+1 250 769 7240",
    "sg:postcode":"V1Z 2S9",
    "sg:province":"BC",
    "sg:tags":[
        "steel",
        "machine",
        "shop"
    ],
    "wof:name":"Pendulum Services",
    "wof:placetype":"venue"
},
  "geometry": {"coordinates":[-119.571182251,49.8662071228],"type":"Point"}
}