{
  "type": "Feature",
  "properties": {
    "addr:full":"407 Hilson Ave Ottawa ON K1Z 6B9",
    "addr:housenumber":"407",
    "addr:postcode":"k1z 6b9",
    "addr:street":"Hilson Ave",
    "iso:country":"CA",
    "sg:address":"407 Hilson Ave",
    "sg:city":"Ottawa",
    "sg:classifiers":[
        {
            "category":"Education",
            "subcategory":"School",
            "type":"Public Place"
        }
    ],
    "sg:phone":"+1 613 728 4607",
    "sg:postcode":"K1Z 6B9",
    "sg:province":"ON",
    "wof:name":"Hilson Avenue School",
    "wof:placetype":"venue"
},
  "geometry": {"coordinates":[-75.7450637817,45.3951454163],"type":"Point"}
}