{
  "type": "Feature",
  "properties": {
    "addr:full":"5269 Highway 3 Shelburne NS B0T 1W0",
    "addr:housenumber":"5269",
    "addr:postcode":"b0t 1w0",
    "addr:street":"Highway 3",
    "iso:country":"CA",
    "sg:address":"5269 Highway 3",
    "sg:city":"Shelburne",
    "sg:classifiers":[
        {
            "category":"Freight",
            "type":"Transportation"
        }
    ],
    "sg:phone":"+1 902 723 1300",
    "sg:postcode":"B0T 1W0",
    "sg:province":"NS",
    "sg:tags":[
        "trucking"
    ],
    "wof:name":"R A D'Eon Transport Ltd",
    "wof:placetype":"venue"
},
  "geometry": {"coordinates":[-65.31564331049999,43.7656593323],"type":"Point"}
}