{
  "type": "Feature",
  "properties": {
    "addr:full":"11925 1E Av # 104 Saint-Georges QC G5Y 2C9",
    "addr:housenumber":"11925",
    "addr:postcode":"g5y 2c9",
    "addr:street":"1E Av # 104",
    "iso:country":"CA",
    "sg:address":"11925 1E Av # 104",
    "sg:city":"Saint-Georges",
    "sg:classifiers":[
        {
            "category":"Insurance",
            "subcategory":"Insurance Agent",
            "type":"Services"
        }
    ],
    "sg:phone":"+1 418 227 5335",
    "sg:postcode":"G5Y 2C9",
    "sg:province":"QC",
    "wof:name":"Harvey Hermann Assurance Inc",
    "wof:placetype":"venue"
},
  "geometry": {"coordinates":[-70.67115020750001,46.1233482361],"type":"Point"}
}