{
  "type": "Feature",
  "properties": {
    "iso:country":"CA",
    "sg:city":"Winnipeg",
    "sg:classifiers":[
        {
            "category":"Food & Beverages",
            "subcategory":"Specialty",
            "type":"Retail Goods"
        }
    ],
    "sg:phone":"+1 204 477 0187",
    "sg:postcode":"R3T 2G6",
    "sg:province":"MB",
    "sg:tags":[
        "water",
        "bulk",
        "company"
    ],
    "wof:name":"World of Water",
    "wof:placetype":"venue"
},
  "geometry": {"coordinates":[-97.152664,49.826881],"type":"Point"}
}