{
  "type": "Feature",
  "properties": {
    "addr:full":"14425 118 Ave NW Edmonton AB T5L 2M7",
    "addr:housenumber":"14425",
    "addr:postcode":"t5l 2m7",
    "addr:street":"118 Ave Nw",
    "iso:country":"CA",
    "sg:address":"14425 118 Ave NW",
    "sg:city":"Edmonton",
    "sg:classifiers":[
        {
            "category":"Home & Garden",
            "subcategory":"Building Materials",
            "type":"Retail Goods"
        }
    ],
    "sg:phone":"+1 780 454 1455",
    "sg:postcode":"T5L 2M7",
    "sg:province":"AB",
    "sg:tags":[
        "hardware",
        "door"
    ],
    "wof:name":"Wsi Doors Ltd",
    "wof:placetype":"venue"
},
  "geometry": {"coordinates":[-113.56956481900001,53.5701828003],"type":"Point"}
}