{
  "type": "Feature",
  "properties": {
    "addr:full":"206 Washington Ave Davidson SK S0G 1A0",
    "addr:housenumber":"206",
    "addr:postcode":"s0g 1a0",
    "addr:street":"Washington Ave",
    "iso:country":"CA",
    "sg:address":"206 Washington Ave",
    "sg:city":"Davidson",
    "sg:classifiers":[
        {
            "category":"Government",
            "subcategory":"Office",
            "type":"Public Place"
        }
    ],
    "sg:phone":"+1 306 567 2040",
    "sg:postcode":"S0G 1A0",
    "sg:province":"SK",
    "sg:tags":[
        "municipality"
    ],
    "wof:name":"Davidson City Offices",
    "wof:placetype":"venue"
},
  "geometry": {"coordinates":[-105.995987,51.267365],"type":"Point"}
}