{
  "type": "Feature",
  "properties": {
    "addr:full":"Vancouver BC V7X 1M8",
    "addr:postcode":"v7x 1m8",
    "iso:country":"CA",
    "sg:city":"Vancouver",
    "sg:classifiers":[
        {
            "category":"Professional",
            "subcategory":"Lawyer & Legal Services",
            "type":"Services"
        }
    ],
    "sg:phone":"+1 604 893 7069",
    "sg:postcode":"V7X 1M8",
    "sg:province":"BC",
    "sg:tags":[
        "naturalization",
        "immigration"
    ],
    "wof:name":"Cigi",
    "wof:placetype":"venue"
},
  "geometry": {"coordinates":[-123.118812561,49.2860794067],"type":"Point"}
}