{
  "type": "Feature",
  "properties": {
    "addr:full":"4142 Lakeshore Rd Beamsville ON L0R 1B1",
    "addr:housenumber":"4142",
    "addr:postcode":"l0r 1b1",
    "addr:street":"Lakeshore Rd",
    "iso:country":"CA",
    "sg:address":"4142 Lakeshore Rd",
    "sg:city":"Beamsville",
    "sg:classifiers":[
        {
            "category":"Building & Trades",
            "subcategory":"Construction",
            "type":"Services"
        }
    ],
    "sg:phone":"+1 905 563 4050",
    "sg:postcode":"L0R 1B1",
    "sg:province":"ON",
    "sg:tags":[
        "maker",
        "cabinet"
    ],
    "wof:name":"Cam Watson Woodworking",
    "wof:placetype":"venue"
},
  "geometry": {"coordinates":[-79.4726104736,43.1885528564],"type":"Point"}
}