{
  "type": "Feature",
  "properties": {
    "addr:full":"4830 Rue Rene-Emard Pierrefonds QC H9A 2Y1",
    "addr:housenumber":"4830",
    "addr:postcode":"h9a 2y1",
    "addr:street":"Rue Rene-Emard",
    "iso:country":"CA",
    "sg:address":"4830 Rue Rene-Emard",
    "sg:city":"Pierrefonds",
    "sg:classifiers":[
        {
            "category":"Home & Garden",
            "subcategory":"Building Materials",
            "type":"Retail Goods"
        }
    ],
    "sg:phone":"+1 514 620 6333",
    "sg:postcode":"H9A 2Y1",
    "sg:province":"QC",
    "sg:tags":[
        "glass",
        "window",
        "plate"
    ],
    "wof:name":"Vitrerie Gouin Auto Glass Inc",
    "wof:placetype":"venue"
},
  "geometry": {"coordinates":[-73.84675598139999,45.4898605347],"type":"Point"}
}