{
  "type": "Feature",
  "properties": {
    "iso:country":"CA",
    "sg:address":"3374 Queen Mary Rd",
    "sg:city":"Montreal",
    "sg:classifiers":[
        {
            "category":"Social Services",
            "type":"Services"
        }
    ],
    "sg:phone":"+1 514 279 5485",
    "sg:postcode":"H3V 1A6",
    "sg:province":"QC",
    "sg:tags":[
        "organization",
        "welfare"
    ],
    "wof:name":"Mouvement Salut Terre",
    "wof:placetype":"venue"
},
  "geometry": {"coordinates":[-73.617980957,45.4958305359],"type":"Point"}
}