{
  "type": "Feature",
  "properties": {
    "addr:full":"1755 St Laurent Blvd Ottawa ON K1G 3V4",
    "addr:housenumber":"1755",
    "addr:postcode":"k1g 3v4",
    "addr:street":"St Laurent Blvd",
    "iso:country":"CA",
    "sg:address":"1755 St Laurent Blvd",
    "sg:city":"Ottawa",
    "sg:classifiers":[
        {
            "category":"Restaurant",
            "type":"Food & Drink"
        }
    ],
    "sg:phone":"+1 613 521 9168",
    "sg:postcode":"K1G 3V4",
    "sg:province":"ON",
    "wof:name":"Cathay Restaurants",
    "wof:placetype":"venue"
},
  "geometry": {"coordinates":[-75.62628173829999,45.4050064087],"type":"Point"}
}