{
  "type": "Feature",
  "properties": {
    "addr:full":"200 Rte 132 Price QC G0J 1Z0",
    "addr:housenumber":"200",
    "addr:postcode":"g0j 1z0",
    "addr:street":"Rte 132",
    "iso:country":"CA",
    "sg:address":"200 Rte 132",
    "sg:city":"Price",
    "sg:classifiers":[
        {
            "category":"Home & Garden",
            "subcategory":"Garden Supply",
            "type":"Retail Goods"
        }
    ],
    "sg:phone":"+1 418 775 2222",
    "sg:postcode":"G0J 1Z0",
    "sg:province":"QC",
    "sg:tags":[
        "lawn",
        "botanical"
    ],
    "wof:name":"Jardins DE Metis Inc",
    "wof:placetype":"venue"
},
  "geometry": {"coordinates":[-68.12481699999999,48.602852],"type":"Point"}
}