{
  "type": "Feature",
  "properties": {
    "addr:full":"1550 Douglas St Merritt BC V1K 1E2",
    "addr:housenumber":"1550",
    "addr:postcode":"v1k 1e2",
    "addr:street":"Douglas St",
    "iso:country":"CA",
    "sg:address":"1550 Douglas St",
    "sg:city":"Merritt",
    "sg:classifiers":[
        {
            "category":"Building & Trades",
            "subcategory":"Construction",
            "type":"Services"
        }
    ],
    "sg:phone":"+1 250 378 2779",
    "sg:postcode":"V1K 1E2",
    "sg:province":"BC",
    "sg:tags":[
        "painter"
    ],
    "wof:name":"R & R Painting",
    "wof:placetype":"venue"
},
  "geometry": {"coordinates":[-120.774520874,50.1030807495],"type":"Point"}
}