{
  "type": "Feature",
  "properties": {
    "addr:full":"861 York Mills Rd North York ON M3B 1Y2",
    "addr:housenumber":"861",
    "addr:postcode":"m3b 1y2",
    "addr:street":"York Mills Rd",
    "iso:country":"CA",
    "sg:address":"861 York Mills Rd",
    "sg:city":"North York",
    "sg:classifiers":[
        {
            "category":"Food & Beverages",
            "subcategory":"Bakery",
            "type":"Retail Goods"
        }
    ],
    "sg:phone":"+1 416 385 8878",
    "sg:postcode":"M3B 1Y2",
    "sg:province":"ON",
    "sg:tags":[
        "cafe"
    ],
    "wof:name":"Dayberries Bakery Cafe",
    "wof:placetype":"venue"
},
  "geometry": {"coordinates":[-79.3516159058,43.7546348572],"type":"Point"}
}