{
  "type": "Feature",
  "properties": {
    "addr:full":"1020 Johnson's Lane # B2 Mississauga ON L5J 2P7",
    "addr:housenumber":"1020",
    "addr:postcode":"l5j 2p7",
    "addr:street":"Johnson'S Lane # B2",
    "iso:country":"CA",
    "sg:address":"1020 Johnson's Lane # B2",
    "sg:city":"Mississauga",
    "sg:classifiers":[
        {
            "category":"Health Services",
            "subcategory":"Doctor",
            "type":"Services"
        }
    ],
    "sg:phone":"+1 905 403 8118",
    "sg:postcode":"L5J 2P7",
    "sg:province":"ON",
    "sg:tags":[
        "dentist"
    ],
    "wof:name":"Dental Centre",
    "wof:placetype":"venue"
},
  "geometry": {"coordinates":[-79.684685,43.575413],"type":"Point"}
}