{
  "type": "Feature",
  "properties": {
    "addr:full":"2450 Ch Saint-Roch Sorel-Tracy QC J3R 3L6",
    "addr:postcode":"2450;j3r 3l6",
    "addr:street":"Ch Saint-Roch",
    "iso:country":"CA",
    "sg:address":"2450 Ch Saint-Roch",
    "sg:city":"Sorel-Tracy",
    "sg:classifiers":[
        {
            "category":"Restaurant",
            "type":"Food & Drink"
        }
    ],
    "sg:phone":"+1 450 746 8680",
    "sg:postcode":"J3R 3L6",
    "sg:province":"QC",
    "wof:name":"Restaurant Philippe DE Lyon",
    "wof:placetype":"venue"
},
  "geometry": {"coordinates":[-73.13133999999999,46.032898],"type":"Point"}
}