{
  "type": "Feature",
  "properties": {
    "iso:country":"CA",
    "sg:city":"Waterloo",
    "sg:classifiers":[
        {
            "category":"Real Estate",
            "subcategory":"Real Estate Agent",
            "type":"Services"
        }
    ],
    "sg:phone":"+1 519 746 5761",
    "sg:postcode":"N2L 6B6",
    "sg:province":"ON",
    "sg:tags":[
        "management"
    ],
    "wof:name":"Cbs Property Management",
    "wof:placetype":"venue"
},
  "geometry": {"coordinates":[-80.53774261469999,43.4742965698],"type":"Point"}
}