{
  "type": "Feature",
  "properties": {
    "iso:country":"CA",
    "sg:address":"24 Colquhoun",
    "sg:city":"Ayr",
    "sg:classifiers":[
        {
            "category":"Wholesale",
            "subcategory":"Durable Goods & Equipment",
            "type":"Manufacturing & Wholesale Goods"
        }
    ],
    "sg:phone":"+1 519 632 8240",
    "sg:postcode":"N0B 1E0",
    "sg:province":"ON",
    "sg:tags":[
        "representative",
        "manufacturer"
    ],
    "wof:name":"R & B Distribution",
    "wof:placetype":"venue"
},
  "geometry": {"coordinates":[-80.45220947270001,43.2902603149],"type":"Point"}
}