{
  "type": "Feature",
  "properties": {
    "addr:full":"2136 54 Ave SW Calgary AB T3E 1L7",
    "addr:housenumber":"2136",
    "addr:postcode":"t3e 1l7",
    "addr:street":"54 Ave Sw",
    "iso:country":"CA",
    "sg:address":"2136 54 Ave SW",
    "sg:city":"Calgary",
    "sg:classifiers":[
        {
            "category":"Wholesale",
            "subcategory":"Machinery & Supplies",
            "type":"Manufacturing & Wholesale Goods"
        }
    ],
    "sg:phone":"+1 403 212 1909",
    "sg:postcode":"T3E 1L7",
    "sg:province":"AB",
    "sg:tags":[
        "engraving",
        "equipment"
    ],
    "wof:name":"Can-Fax Logos Inc",
    "wof:placetype":"venue"
},
  "geometry": {"coordinates":[-114.11028289799999,51.0052452087],"type":"Point"}
}