{
  "type": "Feature",
  "properties": {
    "addr:full":"311 Neill St # 101 Tofino BC V0R 2Z0",
    "addr:housenumber":"311",
    "addr:postcode":"v0r 2z0",
    "addr:street":"Neill St # 101",
    "iso:country":"CA",
    "sg:address":"311 Neill St # 101",
    "sg:city":"Tofino",
    "sg:classifiers":[
        {
            "category":"Insurance",
            "subcategory":"Insurance Agent",
            "type":"Services"
        }
    ],
    "sg:phone":"+1 250 725 3346",
    "sg:postcode":"V0R 2Z0",
    "sg:province":"BC",
    "wof:name":"Peninsula & Bay Lands Ltd",
    "wof:placetype":"venue"
},
  "geometry": {"coordinates":[-125.895599,49.149815],"type":"Point"}
}