{
  "type": "Feature",
  "properties": {
    "addr:full":"506 3rd Ave E Meadow Lake SK S9X 1H5",
    "addr:housenumber":"506",
    "addr:postcode":"s9x 1h5",
    "addr:street":"3Rd Ave E;Lake",
    "iso:country":"CA",
    "sg:address":"506 3rd Ave E",
    "sg:city":"Meadow Lake",
    "sg:classifiers":[
        {
            "category":"Organizations",
            "subcategory":"Religious Organization",
            "type":"Services"
        }
    ],
    "sg:phone":"+1 306 236 5333",
    "sg:postcode":"S9X 1H5",
    "sg:province":"SK",
    "sg:tags":[
        "church"
    ],
    "wof:name":"Catholic Church Hall",
    "wof:placetype":"venue"
},
  "geometry": {"coordinates":[-108.419624,54.132416],"type":"Point"}
}