{
  "type": "Feature",
  "properties": {
    "addr:full":"11832 Av Bellevois Montreal-Nord QC H1H 3G1",
    "addr:postcode":"h1h 3g1",
    "addr:street":"Av Bellevois",
    "iso:country":"CA",
    "sg:address":"11832 Av Bellevois",
    "sg:city":"Montreal-Nord",
    "sg:classifiers":[
        {
            "category":"Organizations",
            "subcategory":"Membership Organization",
            "type":"Services"
        }
    ],
    "sg:phone":"+1 514 329 2800",
    "sg:postcode":"H1H 3G1",
    "sg:province":"QC",
    "wof:name":"Fondation DE LA Visite",
    "wof:placetype":"venue"
},
  "geometry": {"coordinates":[-73.637871,45.603165],"type":"Point"}
}