{
  "type": "Feature",
  "properties": {
    "addr:full":"361 Guelph St Georgetown ON L7G 4B6",
    "addr:housenumber":"361",
    "addr:postcode":"l7g 4b6",
    "addr:street":"Guelph St",
    "iso:country":"CA",
    "sg:address":"361 Guelph St",
    "sg:city":"Georgetown",
    "sg:classifiers":[
        {
            "category":"Autos & Motor Vehicles",
            "subcategory":"Automobile Sales",
            "type":"Retail Goods"
        }
    ],
    "sg:phone":"+1 905 873 1626",
    "sg:postcode":"L7G 4B6",
    "sg:province":"ON",
    "sg:tags":[
        "car",
        "dealer"
    ],
    "wof:name":"Concept Ford Lincoln Inc",
    "wof:placetype":"venue"
},
  "geometry": {"coordinates":[-79.88123299999999,43.649208],"type":"Point"}
}