{
  "type": "Feature",
  "properties": {
    "addr:full":"60 Thornhill Dr Dartmouth NS B3B 1S1",
    "addr:housenumber":"60",
    "addr:postcode":"b3b 1s1",
    "addr:street":"Thornhill Dr",
    "iso:country":"CA",
    "sg:address":"60 Thornhill Dr",
    "sg:city":"Dartmouth",
    "sg:classifiers":[
        {
            "category":"Manufacturing",
            "subcategory":"Tools & Machinery",
            "type":"Manufacturing & Wholesale Goods"
        }
    ],
    "sg:phone":"+1 902 468 2971",
    "sg:postcode":"B3B 1S1",
    "sg:province":"NS",
    "sg:tags":[
        "pump"
    ],
    "wof:name":"Pumps Plus Ltd",
    "wof:placetype":"venue"
},
  "geometry": {"coordinates":[-63.589939,44.698055],"type":"Point"}
}