{
  "type": "Feature",
  "properties": {
    "iso:country":"CA",
    "sg:address":"14907 45 Ave NW",
    "sg:city":"Edmonton",
    "sg:classifiers":[
        {
            "category":"Organizations",
            "subcategory":"Religious Organization",
            "type":"Services"
        }
    ],
    "sg:phone":"+1 780 430 7275",
    "sg:postcode":"T6H 5K8",
    "sg:province":"AB",
    "sg:tags":[
        "church"
    ],
    "wof:name":"Riverbend United Church",
    "wof:placetype":"venue"
},
  "geometry": {"coordinates":[-113.579246521,53.4835777283],"type":"Point"}
}