{
  "type": "Feature",
  "properties": {
    "addr:full":"906 Adelaide St N London ON N5Y 2M7",
    "addr:housenumber":"906",
    "addr:postcode":"n5y 2m7",
    "addr:street":"Adelaide St N",
    "iso:country":"CA",
    "sg:address":"906 Adelaide St N",
    "sg:city":"London",
    "sg:classifiers":[
        {
            "category":"Health Services",
            "subcategory":"Optometrist",
            "type":"Services"
        }
    ],
    "sg:phone":"+1 519 432 6142",
    "sg:postcode":"N5Y 2M7",
    "sg:province":"ON",
    "wof:name":"Adelaide Eye Care Ctr",
    "wof:placetype":"venue"
},
  "geometry": {"coordinates":[-81.2395858765,43.0052909851],"type":"Point"}
}