{
  "type": "Feature",
  "properties": {
    "addr:full":"14825 123 Ave NW Edmonton AB T5L 2Y7",
    "addr:housenumber":"14825",
    "addr:postcode":"t5l 2y7",
    "addr:street":"123 Ave Nw",
    "iso:country":"CA",
    "sg:address":"14825 123 Ave NW",
    "sg:city":"Edmonton",
    "sg:classifiers":[
        {
            "category":"Building & Trades",
            "subcategory":"Construction",
            "type":"Services"
        }
    ],
    "sg:phone":"+1 780 454 7153",
    "sg:postcode":"T5L 2Y7",
    "sg:province":"AB",
    "sg:tags":[
        "sandblasting"
    ],
    "wof:name":"Keith's Auto Sandblasting Ltd",
    "wof:placetype":"venue"
},
  "geometry": {"coordinates":[-113.576461792,53.5766181946],"type":"Point"}
}