{
  "type": "Feature",
  "properties": {
    "addr:full":"31 Rue King O Sherbrooke QC J1H 1N5",
    "addr:housenumber":"31",
    "addr:postcode":"j1h 1n5",
    "addr:street":"Rue King O",
    "iso:country":"CA",
    "sg:address":"31 Rue King O",
    "sg:city":"Sherbrooke",
    "sg:classifiers":[
        {
            "category":"Professional",
            "subcategory":"Business Services",
            "type":"Services"
        }
    ],
    "sg:phone":"+1 819 823 1666",
    "sg:postcode":"J1H 1N5",
    "sg:province":"QC",
    "wof:name":"France, Denis",
    "wof:placetype":"venue"
},
  "geometry": {"coordinates":[-71.88603999999999,45.403671],"type":"Point"}
}