{
  "type": "Feature",
  "properties": {
    "addr:full":"2000 Eglinton Ave E Scarborough ON M1L 2M7",
    "addr:housenumber":"2000",
    "addr:postcode":"m1l 2m7",
    "addr:street":"Eglinton Ave E",
    "iso:country":"CA",
    "sg:address":"2000 Eglinton Ave E",
    "sg:city":"Scarborough",
    "sg:classifiers":[
        {
            "category":"Retail",
            "subcategory":"Auto Rental",
            "type":"Services"
        }
    ],
    "sg:phone":"+1 416 751 4892",
    "sg:postcode":"M1L 2M7",
    "sg:province":"ON",
    "sg:tags":[
        "renting",
        "automobile",
        "leasing"
    ],
    "wof:name":"Natco Leasing",
    "wof:placetype":"venue"
},
  "geometry": {"coordinates":[-79.283531,43.728897],"type":"Point"}
}