{
  "type": "Feature",
  "properties": {
    "addr:full":"1467 Northdale St Gloucester ON K1B 4G7",
    "addr:housenumber":"1467",
    "addr:postcode":"k1b 4g7",
    "addr:street":"Northdale St",
    "iso:country":"CA",
    "sg:address":"1467 Northdale St",
    "sg:city":"Gloucester",
    "sg:classifiers":[
        {
            "category":"Wholesale",
            "subcategory":"Stationery",
            "type":"Manufacturing & Wholesale Goods"
        }
    ],
    "sg:phone":"+1 613 746 4848",
    "sg:postcode":"K1B 4G7",
    "sg:province":"ON",
    "sg:tags":[
        "printer",
        "business",
        "form",
        "system"
    ],
    "wof:name":"Superior Business Forms Inc",
    "wof:placetype":"venue"
},
  "geometry": {"coordinates":[-75.6063,45.42215],"type":"Point"}
}