{
  "type": "Feature",
  "properties": {
    "addr:full":"Saskatoon SK S7K 5M5",
    "addr:postcode":"s7k 5m5",
    "iso:country":"CA",
    "sg:city":"Saskatoon",
    "sg:classifiers":[
        {
            "category":"Mining & Drilling",
            "type":"Manufacturing & Wholesale Goods"
        }
    ],
    "sg:phone":"+1 306 664 4626",
    "sg:postcode":"S7K 5M5",
    "sg:province":"SK",
    "sg:tags":[
        "development",
        "gas",
        "oil",
        "exploration"
    ],
    "wof:name":"Bec International Corp",
    "wof:placetype":"venue"
},
  "geometry": {"coordinates":[-106.661171,52.12606],"type":"Point"}
}