{
  "type": "Feature",
  "properties": {
    "addr:full":"42 John St E Wingham ON N0G 2W0",
    "addr:housenumber":"42",
    "addr:postcode":"n0g 2w0",
    "addr:street":"John St E",
    "iso:country":"CA",
    "sg:address":"42 John St E",
    "sg:city":"Wingham",
    "sg:classifiers":[
        {
            "category":"Building & Trades",
            "subcategory":"Construction",
            "type":"Services"
        }
    ],
    "sg:phone":"+1 519 357 3172",
    "sg:postcode":"N0G 2W0",
    "sg:province":"ON",
    "sg:tags":[
        "resurfacing",
        "laying",
        "refinishing",
        "floor"
    ],
    "wof:name":"Paul Rintoul Construction",
    "wof:placetype":"venue"
},
  "geometry": {"coordinates":[-81.311706543,43.8855705261],"type":"Point"}
}