{
  "type": "Feature",
  "properties": {
    "addr:full":"PO Box 1777 STN Main Stittsville ON K2S 1B4",
    "addr:housenumber":"po",
    "addr:postcode":"1777;k2s 1b4",
    "addr:street":"Box;Stn Main",
    "iso:country":"CA",
    "sg:address":"PO Box 1777 STN Main",
    "sg:city":"Stittsville",
    "sg:classifiers":[
        {
            "category":"Building & Trades",
            "subcategory":"Landscaping Services",
            "type":"Services"
        }
    ],
    "sg:phone":"+1 613 836 6324",
    "sg:postcode":"K2S 1B4",
    "sg:province":"ON",
    "sg:tags":[
        "lawn",
        "maintenance",
        "grounds"
    ],
    "wof:name":"Clean Cut Lawn & Lot Mntnc",
    "wof:placetype":"venue"
},
  "geometry": {"coordinates":[-75.927216,45.263855],"type":"Point"}
}