{
  "type": "Feature",
  "properties": {
    "iso:country":"CA",
    "sg:city":"Langley",
    "sg:classifiers":[
        {
            "category":"Retail",
            "subcategory":"Auto Repair",
            "type":"Services"
        }
    ],
    "sg:phone":"+1 604 532 8923",
    "sg:postcode":"V3A 4K7",
    "sg:province":"BC",
    "sg:tags":[
        "automobile",
        "top",
        "upholstery"
    ],
    "wof:name":"Happy Ho's Upholstery Ltd",
    "wof:placetype":"venue"
},
  "geometry": {"coordinates":[-122.666969299,49.1093635559],"type":"Point"}
}