{
  "type": "Feature",
  "properties": {
    "addr:full":"26 Hastings St E Vancouver BC V6A 1N1",
    "addr:housenumber":"26",
    "addr:postcode":"v6a 1n1",
    "addr:street":"Hastings St E",
    "iso:country":"CA",
    "sg:address":"26 Hastings St E",
    "sg:city":"Vancouver",
    "sg:classifiers":[
        {
            "category":"Organizations",
            "subcategory":"Community Association",
            "type":"Services"
        }
    ],
    "sg:phone":"+1 604 681 7933",
    "sg:postcode":"V6A 1N1",
    "sg:province":"BC",
    "sg:tags":[
        "club"
    ],
    "wof:name":"Logger's Recreation Club",
    "wof:placetype":"venue"
},
  "geometry": {"coordinates":[-123.103775024,49.281288147],"type":"Point"}
}