{
  "type": "Feature",
  "properties": {
    "iso:country":"CA",
    "sg:address":"2103 Boul Edouard # 101",
    "sg:city":"Saint-Hubert",
    "sg:classifiers":[
        {
            "category":"Professional",
            "subcategory":"Business Services",
            "type":"Services"
        }
    ],
    "sg:phone":"+1 450 671 0194",
    "sg:postcode":"J4T 2A2",
    "sg:province":"QC",
    "sg:tags":[
        "notary"
    ],
    "wof:name":"Prudhomme Fontaine Dolan",
    "wof:placetype":"venue"
},
  "geometry": {"coordinates":[-73.4810791016,45.4961547852],"type":"Point"}
}