{
  "type": "Feature",
  "properties": {
    "addr:full":"22 Frank St Strathroy ON N7G 3X3",
    "addr:housenumber":"22",
    "addr:postcode":"n7g 3x3",
    "addr:street":"Frank St",
    "iso:country":"CA",
    "sg:address":"22 Frank St",
    "sg:city":"Strathroy",
    "sg:classifiers":[
        {
            "category":"Health Services",
            "subcategory":"Optometrist",
            "type":"Services"
        }
    ],
    "sg:phone":"+1 519 245 2000",
    "sg:postcode":"N7G 3X3",
    "sg:province":"ON",
    "wof:name":"Mc Gugan, Janet OD",
    "wof:placetype":"venue"
},
  "geometry": {"coordinates":[-81.6237335205,42.9557228088],"type":"Point"}
}