{
  "type": "Feature",
  "properties": {
    "iso:country":"CA",
    "sg:address":"1008 Bridge St",
    "sg:city":"Manotick",
    "sg:classifiers":[
        {
            "category":"Health Services",
            "subcategory":"Doctor",
            "type":"Services"
        }
    ],
    "sg:phone":"+1 613 692 4432",
    "sg:postcode":"K4M 1K4",
    "sg:province":"ON",
    "sg:tags":[
        "dentist"
    ],
    "wof:name":"Joseph, Jolieann DDS",
    "wof:placetype":"venue"
},
  "geometry": {"coordinates":[-75.67682600000001,45.233482],"type":"Point"}
}