{
  "type": "Feature",
  "properties": {
    "addr:full":"888 Rue Saint-Jean Quebec QC G1R 5H6",
    "addr:housenumber":"888",
    "addr:postcode":"g1r 5h6",
    "addr:street":"Rue Saint-Jean",
    "iso:country":"CA",
    "sg:address":"888 Rue Saint-Jean",
    "sg:city":"Quebec",
    "sg:classifiers":[
        {
            "category":"Food & Beverages",
            "subcategory":"Liquor & Beverages",
            "type":"Retail Goods"
        }
    ],
    "sg:phone":"+1 418 643 4337",
    "sg:postcode":"G1R 5H6",
    "sg:province":"QC",
    "sg:tags":[
        "store"
    ],
    "wof:name":"Saq",
    "wof:placetype":"venue"
},
  "geometry": {"coordinates":[-71.21607971189999,46.8119850159],"type":"Point"}
}