{
  "type": "Feature",
  "properties": {
    "iso:country":"CA",
    "sg:address":"817 Victoria Ave",
    "sg:city":"Regina",
    "sg:classifiers":[
        {
            "category":"Restaurant",
            "type":"Food & Drink"
        }
    ],
    "sg:phone":"+1 306 525 5222",
    "sg:postcode":"S4N 0R5",
    "sg:province":"SK",
    "wof:name":"Little Saigon Restaurant",
    "wof:placetype":"venue"
},
  "geometry": {"coordinates":[-104.59263610799999,50.4469795227],"type":"Point"}
}