{
  "type": "Feature",
  "properties": {
    "addr:full":"7311 152A Ave NW Edmonton AB T5C 2Z5",
    "addr:housenumber":"7311",
    "addr:postcode":"t5c 2z5",
    "addr:street":"152A Ave Nw",
    "iso:country":"CA",
    "sg:address":"7311 152A Ave NW",
    "sg:city":"Edmonton",
    "sg:classifiers":[
        {
            "category":"Professional",
            "subcategory":"Management & Consulting",
            "type":"Services"
        }
    ],
    "sg:phone":"+1 780 413 9667",
    "sg:postcode":"T5C 2Z5",
    "sg:province":"AB",
    "sg:tags":[
        "consultant",
        "business"
    ],
    "wof:name":"Chosyn Business Support Svc",
    "wof:placetype":"venue"
},
  "geometry": {"coordinates":[-113.453484,53.613422],"type":"Point"}
}