{
  "type": "Feature",
  "properties": {
    "addr:full":"2082 Kipling Ave Etobicoke ON M9W 4J9",
    "addr:housenumber":"2082",
    "addr:postcode":"m9w 4j9",
    "addr:street":"Kipling Ave",
    "iso:country":"CA",
    "sg:address":"2082 Kipling Ave",
    "sg:city":"Etobicoke",
    "sg:classifiers":[
        {
            "category":"Autos & Motor Vehicles",
            "subcategory":"Auto Supplies",
            "type":"Retail Goods"
        }
    ],
    "sg:phone":"+1 416 744 3444",
    "sg:postcode":"M9W 4J9",
    "sg:province":"ON",
    "sg:tags":[
        "tire"
    ],
    "wof:name":"Active Green & Ross",
    "wof:placetype":"venue"
},
  "geometry": {"coordinates":[-79.56879425050001,43.7156829834],"type":"Point"}
}