{
  "type": "Feature",
  "properties": {
    "addr:full":"351 Yellowhead Hwy Barriere BC V0E 1E0",
    "addr:housenumber":"351",
    "addr:postcode":"bc v0e 1e0",
    "addr:street":"Yellowhead Hwy",
    "iso:country":"CA",
    "sg:address":"351 Yellowhead Hwy",
    "sg:city":"Barriere",
    "sg:classifiers":[
        {
            "category":"Autos & Motor Vehicles",
            "subcategory":"Fuel & Gas Station",
            "type":"Retail Goods"
        }
    ],
    "sg:phone":"+1 250 672 9233",
    "sg:postcode":"V0E 1E0",
    "sg:province":"BC",
    "sg:tags":[
        "oil"
    ],
    "wof:name":"Barriere Esso",
    "wof:placetype":"venue"
},
  "geometry": {"coordinates":[-120.12648799999999,51.168125],"type":"Point"}
}