{
  "type": "Feature",
  "properties": {
    "addr:full":"2180 Rue Ward Saint-Laurent QC H4M 1T7",
    "addr:housenumber":"2180",
    "addr:postcode":"h4m 1t7",
    "addr:street":"Rue Ward",
    "iso:country":"CA",
    "sg:address":"2180 Rue Ward",
    "sg:city":"Saint-Laurent",
    "sg:classifiers":[
        {
            "category":"Organizations",
            "subcategory":"Religious Organization",
            "type":"Services"
        }
    ],
    "sg:phone":"+1 514 748 2798",
    "sg:postcode":"H4M 1T7",
    "sg:province":"QC",
    "sg:tags":[
        "synagogue"
    ],
    "wof:name":"Netivot Haim Inc",
    "wof:placetype":"venue"
},
  "geometry": {"coordinates":[-73.678619,45.498295],"type":"Point"}
}