{
  "type": "Feature",
  "properties": {
    "addr:full":"3400 Douglas St Victoria BC V8Z 3L5",
    "addr:housenumber":"3400",
    "addr:postcode":"v8z 3l5",
    "addr:street":"Douglas St",
    "iso:country":"CA",
    "sg:address":"3400 Douglas St",
    "sg:city":"Victoria",
    "sg:classifiers":[
        {
            "category":"Home & Garden",
            "subcategory":"Home Furnishings",
            "type":"Retail Goods"
        }
    ],
    "sg:phone":"+1 250 475 2561",
    "sg:postcode":"V8Z 3L5",
    "sg:province":"BC",
    "sg:tags":[
        "lighting",
        "fixture"
    ],
    "wof:name":"Mc Laren Electric Ltd",
    "wof:placetype":"venue"
},
  "geometry": {"coordinates":[-123.372329712,48.4476699829],"type":"Point"}
}