{
  "type": "Feature",
  "properties": {
    "addr:full":"150 Berry Rd # 12 Etobicoke ON M8Y 1W3",
    "addr:housenumber":"150",
    "addr:postcode":"m8y 1w3",
    "addr:street":"Berry Rd # 12",
    "iso:country":"CA",
    "sg:address":"150 Berry Rd # 12",
    "sg:city":"Etobicoke",
    "sg:classifiers":[
        {
            "category":"Food & Beverages",
            "subcategory":"Groceries & Convenience Stores",
            "type":"Retail Goods"
        }
    ],
    "sg:phone":"+1 416 236 0801",
    "sg:postcode":"M8Y 1W3",
    "sg:province":"ON",
    "sg:tags":[
        "grocer"
    ],
    "wof:name":"Hasty Market",
    "wof:placetype":"venue"
},
  "geometry": {"coordinates":[-79.488106,43.637447],"type":"Point"}
}