{
  "type": "Feature",
  "properties": {
    "addr:full":"274 Colborne St Brantford ON N3T 2H5",
    "addr:housenumber":"274",
    "addr:postcode":"n3t 2h5",
    "addr:street":"Colborne St",
    "iso:country":"CA",
    "sg:address":"274 Colborne St",
    "sg:city":"Brantford",
    "sg:classifiers":[
        {
            "category":"Government",
            "subcategory":"Office",
            "type":"Public Place"
        }
    ],
    "sg:phone":"+1 519 759 7752",
    "sg:postcode":"N3T 2H5",
    "sg:province":"ON",
    "sg:tags":[
        "home",
        "health",
        "village"
    ],
    "wof:name":"Brant Community Care Access",
    "wof:placetype":"venue"
},
  "geometry": {"coordinates":[-80.25934599999999,43.138847],"type":"Point"}
}