{
  "type": "Feature",
  "properties": {
    "addr:full":"Compton QC J0B 1L0",
    "addr:postcode":"j0b 1l0",
    "iso:country":"CA",
    "sg:city":"Compton",
    "sg:classifiers":[
        {
            "category":"Travel",
            "subcategory":"Hotels & Motels",
            "type":"Entertainment"
        }
    ],
    "sg:phone":"+1 819 835 0403",
    "sg:postcode":"J0B 1L0",
    "sg:province":"QC",
    "sg:tags":[
        "inn"
    ],
    "wof:name":"Auberge Des Grands Jardins",
    "wof:placetype":"venue"
},
  "geometry": {"coordinates":[-71.85086099999999,45.221638],"type":"Point"}
}