{
  "type": "Feature",
  "properties": {
    "addr:full":"PO Box 494 STN Main Parksville BC V9P 2G6",
    "addr:housenumber":"po",
    "addr:postcode":"v9p 2g6",
    "addr:street":"Box 494 Stn Main",
    "iso:country":"CA",
    "sg:address":"PO Box 494 STN Main",
    "sg:city":"Parksville",
    "sg:classifiers":[
        {
            "category":"Organizations",
            "subcategory":"Religious Organization",
            "type":"Services"
        }
    ],
    "sg:phone":"+1 604 248 5333",
    "sg:postcode":"V9P 2G6",
    "sg:province":"BC",
    "sg:tags":[
        "church"
    ],
    "wof:name":"Parksville Pent Assembly",
    "wof:placetype":"venue"
},
  "geometry": {"coordinates":[-124.313644,49.319691],"type":"Point"}
}