{
  "type": "Feature",
  "properties": {
    "addr:full":"Hwy 20 S Humboldt SK S0K 2A0",
    "addr:postcode":"s0k 2a0",
    "addr:street":"Hwy 20 S",
    "iso:country":"CA",
    "sg:address":"Hwy 20 S",
    "sg:city":"Humboldt",
    "sg:classifiers":[
        {
            "category":"Manufacturing",
            "subcategory":"Building Materials",
            "type":"Manufacturing & Wholesale Goods"
        }
    ],
    "sg:phone":"+1 306 682 5044",
    "sg:postcode":"S0K 2A0",
    "sg:province":"SK",
    "wof:name":"Holzmeister Millwork",
    "wof:placetype":"venue"
},
  "geometry": {"coordinates":[-105.122940063,52.1973686218],"type":"Point"}
}