{
  "type": "Feature",
  "properties": {
    "addr:full":"199 Rue Lindsay Drummondville QC J2C 1N8",
    "addr:housenumber":"199",
    "addr:postcode":"j2c 1n8",
    "addr:street":"Rue Lindsay",
    "iso:country":"CA",
    "sg:address":"199 Rue Lindsay",
    "sg:city":"Drummondville",
    "sg:classifiers":[
        {
            "category":"Health Services",
            "subcategory":"Optometrist",
            "type":"Services"
        }
    ],
    "sg:phone":"+1 819 477 8970",
    "sg:postcode":"J2C 1N8",
    "sg:province":"QC",
    "wof:name":"Laramee, Dominic OD",
    "wof:placetype":"venue"
},
  "geometry": {"coordinates":[-72.490471,45.884163],"type":"Point"}
}