{
  "type": "Feature",
  "properties": {
    "addr:full":"315 Place d'Youville Suite 188 Montreal H2Y0A4",
    "addr:housenumber":"315",
    "addr:postcode":"h2y0a4",
    "addr:street":"Place D'Youville Suite 188",
    "iso:country":"CA",
    "sg:address":"315 Place d'Youville Suite 188",
    "sg:city":"Montreal",
    "sg:classifiers":[
        {
            "category":"Professional",
            "subcategory":"Computer Services",
            "type":"Services"
        }
    ],
    "sg:postcode":"H2Y0A4",
    "sg:tags":[
        "twtpoll",
        "twtsurvey",
        "twtvite",
        "twtaway",
        "twtbizcard",
        "twtqpon",
        "twtfaq",
        "twtjobs",
        "twttrip"
    ],
    "sg:website":"http://twtapps.com",
    "wof:name":"Twtapps",
    "wof:placetype":"venue"
},
  "geometry": {"coordinates":[-73.5825418,45.4928591],"type":"Point"}
}