{
  "type": "Feature",
  "properties": {
    "addr:full":"1135 56 St Delta BC V4L 2A2",
    "addr:housenumber":"1135",
    "addr:postcode":"v4l 2a2",
    "addr:street":"56 St",
    "iso:country":"CA",
    "sg:address":"1135 56 St",
    "sg:city":"Delta",
    "sg:classifiers":[
        {
            "category":"Wholesale",
            "subcategory":"Painting Supplies",
            "type":"Manufacturing & Wholesale Goods"
        }
    ],
    "sg:phone":"+1 604 943 5515",
    "sg:postcode":"V4L 2A2",
    "sg:province":"BC",
    "sg:tags":[
        "paint"
    ],
    "wof:name":"Mills Paint Sales Ltd",
    "wof:placetype":"venue"
},
  "geometry": {"coordinates":[-123.068855,49.023594],"type":"Point"}
}