{
  "type": "Feature",
  "properties": {
    "addr:full":"812 Pitt Cornwall ON K6J 5R1",
    "addr:housenumber":"812",
    "addr:postcode":"k6j 5r1",
    "addr:street":"Pitt Cornwall",
    "iso:country":"CA",
    "sg:address":"812 Pitt",
    "sg:city":"Cornwall",
    "sg:classifiers":[
        {
            "category":"Organizations",
            "subcategory":"Non-profit Organization",
            "type":"Services"
        }
    ],
    "sg:phone":"+1 613 937 0536",
    "sg:postcode":"K6J 5R1",
    "sg:province":"ON",
    "sg:tags":[
        "alternative",
        "abortion"
    ],
    "wof:name":"Pro Life Cornwall Pro Vie",
    "wof:placetype":"venue"
},
  "geometry": {"coordinates":[-74.734161,45.027481],"type":"Point"}
}