{
  "type": "Feature",
  "properties": {
    "iso:country":"CA",
    "sg:city":"Kelowna",
    "sg:classifiers":[
        {
            "category":"Wholesale",
            "subcategory":"Sporting Goods",
            "type":"Manufacturing & Wholesale Goods"
        }
    ],
    "sg:phone":"+1 250 769 4644",
    "sg:postcode":"V1Z 3Z4",
    "sg:province":"BC",
    "sg:tags":[
        "salon",
        "tanning",
        "supply"
    ],
    "wof:name":"Sunwest Distributions",
    "wof:placetype":"venue"
},
  "geometry": {"coordinates":[-119.592185974,49.8610610962],"type":"Point"}
}