{
  "type": "Feature",
  "properties": {
    "addr:full":"619 11th St E North Vancouver BC V7L 2H7",
    "addr:housenumber":"619",
    "addr:postcode":"v7l 2h7",
    "addr:street":"11Th St E",
    "iso:country":"CA",
    "sg:address":"619 11th St E",
    "sg:city":"North Vancouver",
    "sg:classifiers":[
        {
            "category":"Building & Trades",
            "subcategory":"Construction",
            "type":"Services"
        }
    ],
    "sg:phone":"+1 604 987 3000",
    "sg:postcode":"V7L 2H7",
    "sg:province":"BC",
    "sg:tags":[
        "excavating",
        "contractor"
    ],
    "wof:name":"Jones Brothers Excavating",
    "wof:placetype":"venue"
},
  "geometry": {"coordinates":[-123.056007385,49.3175926208],"type":"Point"}
}