{
  "type": "Feature",
  "properties": {
    "iso:country":"CA",
    "sg:address":"201 Broadway St",
    "sg:city":"Moncton",
    "sg:classifiers":[
        {
            "category":"Wholesale",
            "subcategory":"Durable Goods & Equipment",
            "type":"Manufacturing & Wholesale Goods"
        }
    ],
    "sg:phone":"+1 506 857 0777",
    "sg:postcode":"E1A 3Y3",
    "sg:province":"NB",
    "sg:tags":[
        "fire",
        "extinguisher"
    ],
    "wof:name":"National Fire & Safety Ltd",
    "wof:placetype":"venue"
},
  "geometry": {"coordinates":[-64.7731933594,46.1091461182],"type":"Point"}
}