{
  "type": "Feature",
  "properties": {
    "addr:full":"15450 20 Ave Surrey BC V4A 2A5",
    "addr:housenumber":"15450",
    "addr:postcode":"v4a 2a5",
    "addr:street":"20 Ave",
    "iso:country":"CA",
    "sg:address":"15450 20 Ave",
    "sg:city":"Surrey",
    "sg:classifiers":[
        {
            "category":"Organizations",
            "subcategory":"Religious Organization",
            "type":"Services"
        }
    ],
    "sg:phone":"+1 604 531 5911",
    "sg:postcode":"V4A 2A5",
    "sg:province":"BC",
    "sg:tags":[
        "church"
    ],
    "wof:name":"Church of Jesus Christ-Lds",
    "wof:placetype":"venue"
},
  "geometry": {"coordinates":[-122.79422,49.038155],"type":"Point"}
}