{
  "type": "Feature",
  "properties": {
    "addr:full":"117 Ringwood Dr Stouffville ON L4A 8C1",
    "addr:housenumber":"117",
    "addr:postcode":"l4a 8c1",
    "addr:street":"Ringwood Dr",
    "iso:country":"CA",
    "sg:address":"117 Ringwood Dr",
    "sg:city":"Stouffville",
    "sg:classifiers":[
        {
            "category":"Personal",
            "subcategory":"Beauty Salon",
            "type":"Services"
        }
    ],
    "sg:phone":"+1 905 642 2169",
    "sg:postcode":"L4A 8C1",
    "sg:province":"ON",
    "wof:name":"Magicuts",
    "wof:placetype":"venue"
},
  "geometry": {"coordinates":[-79.27411651609999,43.9631385803],"type":"Point"}
}