{
  "type": "Feature",
  "properties": {
    "addr:full":"Lacombe AB T4L 2A1",
    "addr:postcode":"t4l 2a1",
    "iso:country":"CA",
    "sg:city":"Lacombe",
    "sg:classifiers":[
        {
            "category":"Food & Beverages",
            "subcategory":"Specialty",
            "type":"Retail Goods"
        }
    ],
    "sg:phone":"+1 403 782 5888",
    "sg:postcode":"T4L 2A1",
    "sg:province":"AB",
    "sg:tags":[
        "health",
        "diet"
    ],
    "wof:name":"Lacombe Health Hut",
    "wof:placetype":"venue"
},
  "geometry": {"coordinates":[-113.723412,52.466988],"type":"Point"}
}