{
  "type": "Feature",
  "properties": {
    "addr:full":"Chicoutimi QC G7H 6K9",
    "addr:postcode":"g7h 6k9",
    "iso:country":"CA",
    "sg:city":"Chicoutimi",
    "sg:classifiers":[
        {
            "category":"Health Services",
            "subcategory":"Doctor",
            "type":"Services"
        }
    ],
    "sg:phone":"+1 418 549 8009",
    "sg:postcode":"G7H 6K9",
    "sg:province":"QC",
    "sg:tags":[
        "physiotherapist",
        "clinic"
    ],
    "wof:name":"Clinique DE Physiotherapie",
    "wof:placetype":"venue"
},
  "geometry": {"coordinates":[-71.06107299999999,48.403706],"type":"Point"}
}