{
  "type": "Feature",
  "properties": {
    "addr:full":"28 Mudcat Rd Foxboro ON K0K 2B0",
    "addr:housenumber":"28",
    "addr:postcode":"k0k 2b0",
    "addr:street":"Mudcat Rd",
    "iso:country":"CA",
    "sg:address":"28 Mudcat Rd",
    "sg:city":"Foxboro",
    "sg:classifiers":[
        {
            "category":"Retail",
            "subcategory":"Auto Repair",
            "type":"Services"
        }
    ],
    "sg:phone":"+1 613 962 2215",
    "sg:postcode":"K0K 2B0",
    "sg:province":"ON",
    "sg:tags":[
        "repairing",
        "automobile"
    ],
    "wof:name":"Eric Emerson Garage",
    "wof:placetype":"venue"
},
  "geometry": {"coordinates":[-77.439133,44.251259],"type":"Point"}
}