{
  "type": "Feature",
  "properties": {
    "addr:full":"165 Amherst Ave North Vancouver BC V7H 1S5",
    "addr:housenumber":"165",
    "addr:postcode":"v7h 1s5",
    "addr:street":"Amherst Ave",
    "iso:country":"CA",
    "sg:address":"165 Amherst Ave",
    "sg:city":"North Vancouver",
    "sg:classifiers":[
        {
            "category":"Retail",
            "subcategory":"Auto Repair",
            "type":"Services"
        }
    ],
    "sg:phone":"+1 604 929 1323",
    "sg:postcode":"V7H 1S5",
    "sg:province":"BC",
    "sg:tags":[
        "truck"
    ],
    "wof:name":"W H Groundwater Ltd",
    "wof:placetype":"venue"
},
  "geometry": {"coordinates":[-123.018844605,49.3047828674],"type":"Point"}
}