{
  "type": "Feature",
  "properties": {
    "addr:full":"598 Bay St Toronto ON M5G 1M5",
    "addr:housenumber":"598",
    "addr:postcode":"m5g 1m5",
    "addr:street":"Bay St",
    "iso:country":"CA",
    "sg:address":"598 Bay St",
    "sg:city":"Toronto",
    "sg:classifiers":[
        {
            "category":"Shopping",
            "subcategory":"Department Store",
            "type":"Retail Goods"
        }
    ],
    "sg:phone":"+1 416 586 0537",
    "sg:postcode":"M5G 1M5",
    "sg:province":"ON",
    "sg:tags":[
        "shop",
        "establishment"
    ],
    "wof:name":"Discounts on Bay",
    "wof:placetype":"venue"
},
  "geometry": {"coordinates":[-79.3840179443,43.6559104919],"type":"Point"}
}