{
  "type": "Feature",
  "properties": {
    "addr:full":"49 Whitewood Ave New Liskeard ON P0J 1P0",
    "addr:housenumber":"49",
    "addr:postcode":"p0j 1p0",
    "addr:street":"Whitewood Ave",
    "iso:country":"CA",
    "sg:address":"49 Whitewood Ave",
    "sg:city":"New Liskeard",
    "sg:classifiers":[
        {
            "category":"Shopping",
            "subcategory":"Jewelry",
            "type":"Retail Goods"
        }
    ],
    "sg:phone":"+1 705 647 5561",
    "sg:postcode":"P0J 1P0",
    "sg:province":"ON",
    "sg:tags":[
        "jeweler"
    ],
    "wof:name":"Spencer Jewellers Ltd",
    "wof:placetype":"venue"
},
  "geometry": {"coordinates":[-79.669945,47.508652],"type":"Point"}
}