{
  "type": "Feature",
  "properties": {
    "addr:full":"118 Rue Acadie Richibucto NB E4W 3V9",
    "addr:housenumber":"118",
    "addr:postcode":"e4w 3v9",
    "addr:street":"Rue Acadie",
    "iso:country":"CA",
    "sg:address":"118 Rue Acadie",
    "sg:city":"Richibucto",
    "sg:classifiers":[
        {
            "category":"Retail",
            "subcategory":"Veterinary Services",
            "type":"Services"
        }
    ],
    "sg:phone":"+1 506 523 1818",
    "sg:postcode":"E4W 3V9",
    "sg:province":"NB",
    "sg:tags":[
        "veterinarian"
    ],
    "wof:name":"Hopital Veterinaire DE Kent",
    "wof:placetype":"venue"
},
  "geometry": {"coordinates":[-64.86389200000001,46.683285],"type":"Point"}
}