{
  "type": "Feature",
  "properties": {
    "addr:full":"490 Rue Main O Coaticook QC J1A 1P9",
    "addr:housenumber":"490",
    "addr:postcode":"j1a 1p9",
    "addr:street":"Rue Main O",
    "iso:country":"CA",
    "sg:address":"490 Rue Main O",
    "sg:city":"Coaticook",
    "sg:classifiers":[
        {
            "category":"Retail",
            "subcategory":"Veterinary Services",
            "type":"Services"
        }
    ],
    "sg:phone":"+1 819 849 4865",
    "sg:postcode":"J1A 1P9",
    "sg:province":"QC",
    "sg:tags":[
        "veterinarian"
    ],
    "wof:name":"Clinique Veterinaire-Coaticook",
    "wof:placetype":"venue"
},
  "geometry": {"coordinates":[-71.794411,45.132668],"type":"Point"}
}