{
  "type": "Feature",
  "properties": {
    "iso:country":"CA",
    "sg:address":"620 Dennis St",
    "sg:city":"Brandon",
    "sg:classifiers":[
        {
            "category":"Health Services",
            "subcategory":"Doctor",
            "type":"Services"
        }
    ],
    "sg:phone":"+1 204 728 4440",
    "sg:postcode":"R7A 5E7",
    "sg:province":"MB",
    "sg:tags":[
        "physician",
        "surgeon"
    ],
    "wof:name":"Brandon Clinic",
    "wof:placetype":"venue"
},
  "geometry": {"coordinates":[-99.9378662109,49.8402137756],"type":"Point"}
}