{
  "type": "Feature",
  "properties": {
    "addr:full":"215 Av Redfern Westmount QC H3Z 3L5",
    "addr:housenumber":"215",
    "addr:postcode":"h3z 3l5",
    "addr:street":"Av Redfern",
    "iso:country":"CA",
    "sg:address":"215 Av Redfern",
    "sg:city":"Westmount",
    "sg:classifiers":[
        {
            "category":"Professional",
            "subcategory":"Business Services",
            "type":"Services"
        }
    ],
    "sg:phone":"+1 514 288 9241",
    "sg:postcode":"H3Z 3L5",
    "sg:province":"QC",
    "sg:tags":[
        "notary"
    ],
    "wof:name":"Paquette, Michel",
    "wof:placetype":"venue"
},
  "geometry": {"coordinates":[-73.5911407471,45.483543396],"type":"Point"}
}