{
  "type": "Feature",
  "properties": {
    "addr:full":"4186 Boul Du Royaume # 4 Jonquiere QC G7X 7W8",
    "addr:housenumber":"4186",
    "addr:postcode":"g7x 7w8",
    "addr:street":"Boul Du Royaume # 4",
    "iso:country":"CA",
    "sg:address":"4186 Boul Du Royaume # 4",
    "sg:city":"Jonquiere",
    "sg:classifiers":[
        {
            "category":"Building & Trades",
            "subcategory":"Construction",
            "type":"Services"
        }
    ],
    "sg:phone":"+1 418 542 7511",
    "sg:postcode":"G7X 7W8",
    "sg:province":"QC",
    "sg:tags":[
        "general",
        "contractor"
    ],
    "wof:name":"Entrepreneurs Lapointe/Gagnon",
    "wof:placetype":"venue"
},
  "geometry": {"coordinates":[-71.2746582031,48.423614502],"type":"Point"}
}