{
  "type": "Feature",
  "properties": {
    "addr:full":"504 Boul Roland-Therrien Longueuil QC J4H 3V9",
    "addr:housenumber":"504",
    "addr:postcode":"j4h 3v9",
    "addr:street":"Boul Roland-Therrien",
    "iso:country":"CA",
    "sg:address":"504 Boul Roland-Therrien",
    "sg:city":"Longueuil",
    "sg:classifiers":[
        {
            "category":"Cinema",
            "subcategory":"Movie Rental",
            "type":"Entertainment"
        }
    ],
    "sg:phone":"+1 450 677 0720",
    "sg:postcode":"J4H 3V9",
    "sg:province":"QC",
    "sg:tags":[
        "leasing",
        "video",
        "disc",
        "tape"
    ],
    "wof:name":"Video Bellerive",
    "wof:placetype":"venue"
},
  "geometry": {"coordinates":[-73.493225,45.546028],"type":"Point"}
}