{
  "type": "Feature",
  "properties": {
    "addr:full":"265 King George Hwy Miramichi NB E1V 1L1",
    "addr:housenumber":"265",
    "addr:postcode":"e1v 1l1",
    "addr:street":"King George Hwy",
    "iso:country":"CA",
    "sg:address":"265 King George Hwy",
    "sg:city":"Miramichi",
    "sg:classifiers":[
        {
            "category":"Shopping",
            "subcategory":"Computers & Home Electronics",
            "type":"Retail Goods"
        }
    ],
    "sg:phone":"+1 506 773 4450",
    "sg:postcode":"E1V 1L1",
    "sg:province":"NB",
    "sg:tags":[
        "equipment",
        "dealer"
    ],
    "wof:name":"True Tronic Computers",
    "wof:placetype":"venue"
},
  "geometry": {"coordinates":[-65.58122299999999,46.982746],"type":"Point"}
}