{
  "type": "Feature",
  "properties": {
    "iso:country":"CA",
    "sg:city":"Vancouver",
    "sg:classifiers":[
        {
            "category":"Organizations",
            "subcategory":"Religious Organization",
            "type":"Services"
        }
    ],
    "sg:phone":"+1 604 251 4808",
    "sg:postcode":"V5N 1A9",
    "sg:province":"BC",
    "sg:tags":[
        "church"
    ],
    "wof:name":"Chan Quang Temple",
    "wof:placetype":"venue"
},
  "geometry": {"coordinates":[-123.069077,49.269722],"type":"Point"}
}