{
  "type": "Feature",
  "properties": {
    "addr:full":"Vancouver BC V5N 1A9",
    "addr:postcode":"v5n 1a9",
    "iso:country":"CA",
    "sg:city":"Vancouver",
    "sg:classifiers":[
        {
            "category":"Organizations",
            "subcategory":"Religious Organization",
            "type":"Services"
        }
    ],
    "sg:phone":"+1 604 251 4808",
    "sg:postcode":"V5N 1A9",
    "sg:province":"BC",
    "sg:tags":[
        "church"
    ],
    "wof:name":"Chan Quang Temple",
    "wof:placetype":"venue"
},
  "geometry": {"coordinates":[-123.06907699999999,49.269722],"type":"Point"}
}