{
  "type": "Feature",
  "properties": {
    "addr:full":"612 Notre Dame Belle River ON N0R 1A0",
    "addr:housenumber":"612",
    "addr:postcode":"n0r 1a0",
    "addr:street":"Notre Dame",
    "iso:country":"CA",
    "sg:address":"612 Notre Dame",
    "sg:city":"Belle River",
    "sg:classifiers":[
        {
            "category":"Shopping",
            "subcategory":"Gifts & Souvenirs",
            "type":"Retail Goods"
        }
    ],
    "sg:phone":"+1 519 728 1333",
    "sg:postcode":"N0R 1A0",
    "sg:province":"ON",
    "sg:tags":[
        "shop"
    ],
    "wof:name":"Home Stuffings",
    "wof:placetype":"venue"
},
  "geometry": {"coordinates":[-82.710953,42.293098],"type":"Point"}
}