{
  "type": "Feature",
  "properties": {
    "addr:full":"2203 Robin Dr Mississauga ON L5K 2L5",
    "addr:housenumber":"2203",
    "addr:postcode":"l5k 2l5",
    "addr:street":"Robin Dr",
    "iso:country":"CA",
    "sg:address":"2203 Robin Dr",
    "sg:city":"Mississauga",
    "sg:classifiers":[
        {
            "category":"Wholesale",
            "subcategory":"Stationery",
            "type":"Manufacturing & Wholesale Goods"
        }
    ],
    "sg:phone":"+1 905 822 8708",
    "sg:postcode":"L5K 2L5",
    "sg:province":"ON",
    "sg:tags":[
        "packaging",
        "material"
    ],
    "wof:name":"Jdp Sales",
    "wof:placetype":"venue"
},
  "geometry": {"coordinates":[-79.649445,43.531914],"type":"Point"}
}