{
  "type": "Feature",
  "properties": {
    "addr:full":"Halifax NS B3L 2H8",
    "addr:postcode":"b3l 2h8",
    "iso:country":"CA",
    "sg:city":"Halifax",
    "sg:classifiers":[
        {
            "category":"Home & Garden",
            "subcategory":"Home Furnishings",
            "type":"Retail Goods"
        }
    ],
    "sg:phone":"+1 902 455 0445",
    "sg:postcode":"B3L 2H8",
    "sg:province":"NS",
    "sg:tags":[
        "glassware",
        "chinaware"
    ],
    "wof:name":"Rob Mc Intosh China & Crystal",
    "wof:placetype":"venue"
},
  "geometry": {"coordinates":[-63.6196632385,44.6477851868],"type":"Point"}
}