{
  "type": "Feature",
  "properties": {
    "addr:full":"90 Boul Notre-Dame Clermont QC G4A 1C7",
    "addr:housenumber":"90",
    "addr:postcode":"g4a 1c7",
    "addr:street":"Boul Notre-Dame",
    "iso:country":"CA",
    "sg:address":"90 Boul Notre-Dame",
    "sg:city":"Clermont",
    "sg:classifiers":[
        {
            "category":"Retail",
            "subcategory":"Funeral Services",
            "type":"Services"
        }
    ],
    "sg:phone":"+1 418 439 2828",
    "sg:postcode":"G4A 1C7",
    "sg:province":"QC",
    "sg:tags":[
        "director",
        "plan"
    ],
    "wof:name":"Cooperative Funeraire Chrlvsn",
    "wof:placetype":"venue"
},
  "geometry": {"coordinates":[-70.221031,47.690563],"type":"Point"}
}