{
  "type": "Feature",
  "properties": {
    "addr:full":"356 Rue Raymond Vaudreuil-Dorion QC J7V 6N1",
    "addr:housenumber":"356",
    "addr:postcode":"j7v 6n1",
    "addr:street":"Rue Raymond",
    "iso:country":"CA",
    "sg:address":"356 Rue Raymond",
    "sg:city":"Vaudreuil-Dorion",
    "sg:classifiers":[
        {
            "category":"Personal",
            "subcategory":"Beauty Salon",
            "type":"Services"
        }
    ],
    "sg:phone":"+1 450 455 9717",
    "sg:postcode":"J7V 6N1",
    "sg:province":"QC",
    "wof:name":"Salon Lise",
    "wof:placetype":"venue"
},
  "geometry": {"coordinates":[-74.02178192140001,45.3906211853],"type":"Point"}
}