{
  "type": "Feature",
  "properties": {
    "addr:full":"1482 Johnston Rd White Rock BC V4B 3Z5",
    "addr:housenumber":"1482",
    "addr:postcode":"v4b 3z5",
    "addr:street":"Johnston Rd",
    "iso:country":"CA",
    "sg:address":"1482 Johnston Rd",
    "sg:city":"White Rock",
    "sg:classifiers":[
        {
            "category":"Shopping",
            "subcategory":"Used Merchandise",
            "type":"Retail Goods"
        }
    ],
    "sg:phone":"+1 604 538 8332",
    "sg:postcode":"V4B 3Z5",
    "sg:province":"BC",
    "sg:tags":[
        "compact",
        "record",
        "pawnbroker",
        "tape",
        "disc"
    ],
    "wof:name":"Seashore Gold & Music",
    "wof:placetype":"venue"
},
  "geometry": {"coordinates":[-122.800964355,49.028968811],"type":"Point"}
}