{
  "type": "Feature",
  "properties": {
    "addr:full":"4 Rue DE L'Eglise Notre-Dame-Du-Laus QC J0X 2M0",
    "addr:housenumber":"4",
    "addr:postcode":"j0x 2m0",
    "addr:street":"Rue De L'Eglise",
    "iso:country":"CA",
    "sg:address":"4 Rue DE L'Eglise",
    "sg:city":"Notre-Dame-Du-Laus",
    "sg:classifiers":[
        {
            "category":"Social Services",
            "type":"Services"
        }
    ],
    "sg:phone":"+1 819 767 2312",
    "sg:postcode":"J0X 2M0",
    "sg:province":"QC",
    "sg:tags":[
        "youth",
        "organization",
        "jean",
        "center"
    ],
    "wof:name":"Centre Ressources Jeunesse",
    "wof:placetype":"venue"
},
  "geometry": {"coordinates":[-75.6223068237,46.087928772],"type":"Point"}
}