{
  "type": "Feature",
  "properties": {
    "iso:country":"CA",
    "sg:address":"2937 Rue Masson",
    "sg:city":"Montreal",
    "sg:classifiers":[
        {
            "category":"Banks & Credit Unions",
            "subcategory":"Bank",
            "type":"Services"
        }
    ],
    "sg:phone":"+1 514 522 1846",
    "sg:postcode":"H1Y 1X5",
    "sg:province":"QC",
    "wof:name":"Banque Laurentienne Du Canada",
    "wof:placetype":"venue"
},
  "geometry": {"coordinates":[-73.5749206543,45.5484008789],"type":"Point"}
}