{
  "type": "Feature",
  "properties": {
    "addr:full":"Rocky Mountain House AB T4T 1G4",
    "addr:postcode":"t4t 1g4",
    "iso:country":"CA",
    "sg:city":"Rocky Mountain House",
    "sg:classifiers":[
        {
            "category":"Retail",
            "subcategory":"Laundry & Dry Cleaning",
            "type":"Services"
        }
    ],
    "sg:phone":"+1 403 845 2246",
    "sg:postcode":"T4T 1G4",
    "sg:province":"AB",
    "sg:tags":[
        "cleaners",
        "rug",
        "carpet"
    ],
    "wof:name":"Master Interiors Carpet",
    "wof:placetype":"venue"
},
  "geometry": {"coordinates":[-114.931236,52.37759],"type":"Point"}
}