{
  "type": "Feature",
  "properties": {
    "addr:full":"10611 150 St Surrey BC V3R 4B8",
    "addr:housenumber":"10611",
    "addr:postcode":"v3r 4b8",
    "addr:street":"150 St",
    "iso:country":"CA",
    "sg:address":"10611 150 St",
    "sg:city":"Surrey",
    "sg:classifiers":[
        {
            "category":"Real Estate",
            "subcategory":"Real Estate Operator",
            "type":"Services"
        }
    ],
    "sg:phone":"+1 604 581 9455",
    "sg:postcode":"V3R 4B8",
    "sg:province":"BC",
    "sg:tags":[
        "apartment"
    ],
    "wof:name":"Maple Place Apartments",
    "wof:placetype":"venue"
},
  "geometry": {"coordinates":[-122.80650300000001,49.19545],"type":"Point"}
}