{
  "type": "Feature",
  "properties": {
    "addr:full":"PO Box 36 Bow Island AB T0K 0G0",
    "addr:housenumber":"po box 36",
    "addr:postcode":"t0k 0g0",
    "addr:street":"Bow Island",
    "iso:country":"CA",
    "sg:address":"PO Box 36",
    "sg:city":"Bow Island",
    "sg:classifiers":[
        {
            "category":"Organizations",
            "subcategory":"Religious Organization",
            "type":"Services"
        }
    ],
    "sg:phone":"+1 403 545 2085",
    "sg:postcode":"T0K 0G0",
    "sg:province":"AB",
    "sg:tags":[
        "church"
    ],
    "wof:name":"Burdett United Church",
    "wof:placetype":"venue"
},
  "geometry": {"coordinates":[-111.36265564,49.8704719543],"type":"Point"}
}