{
  "type": "Feature",
  "properties": {
    "addr:full":"Victoria BC V9B 2W3",
    "addr:postcode":"v9b 2w3",
    "iso:country":"CA",
    "sg:city":"Victoria",
    "sg:classifiers":[
        {
            "category":"Health Services",
            "subcategory":"Medical Lab",
            "type":"Services"
        }
    ],
    "sg:phone":"+1 250 478 6813",
    "sg:postcode":"V9B 2W3",
    "sg:province":"BC",
    "sg:tags":[
        "laboratory"
    ],
    "wof:name":"NU-Pacific Dental Labs Ltd",
    "wof:placetype":"venue"
},
  "geometry": {"coordinates":[-123.470901489,48.4426574707],"type":"Point"}
}