{
  "type": "Feature",
  "properties": {
    "addr:full":"1756 Mattawa Ave Mississauga ON L4X 1K1",
    "addr:housenumber":"1756",
    "addr:postcode":"l4x 1k1",
    "addr:street":"Mattawa Ave",
    "iso:country":"CA",
    "sg:address":"1756 Mattawa Ave",
    "sg:city":"Mississauga",
    "sg:classifiers":[
        {
            "category":"Building & Trades",
            "subcategory":"Construction",
            "type":"Services"
        }
    ],
    "sg:phone":"+1 905 615 8203",
    "sg:postcode":"L4X 1K1",
    "sg:province":"ON",
    "sg:tags":[
        "resurfacing",
        "laying",
        "refinishing",
        "floor"
    ],
    "wof:name":"Diamond Line Inc",
    "wof:placetype":"venue"
},
  "geometry": {"coordinates":[-79.571175,43.61422],"type":"Point"}
}