{
  "type": "Feature",
  "properties": {
    "addr:full":"Quebec QC G1N 4E2",
    "addr:postcode":"g1n 4e2",
    "iso:country":"CA",
    "sg:city":"Quebec",
    "sg:phone":"+1 418 682 8085",
    "sg:postcode":"G1N 4E2",
    "sg:province":"QC",
    "sg:tags":[
        "shelving",
        "fixture",
        "store"
    ],
    "wof:name":"Etageres Quebec",
    "wof:placetype":"venue"
},
  "geometry": {"coordinates":[-71.27961000000001,46.804016],"type":"Point"}
}