{
  "type": "Feature",
  "properties": {
    "addr:full":"2605 64 St Delta BC V4L 2N7",
    "addr:housenumber":"2605",
    "addr:postcode":"v4l 2n7",
    "addr:street":"64 St",
    "iso:country":"CA",
    "sg:address":"2605 64 St",
    "sg:city":"Delta",
    "sg:classifiers":[
        {
            "category":"Real Estate",
            "subcategory":"Developer",
            "type":"Services"
        }
    ],
    "sg:phone":"+1 604 952 7001",
    "sg:postcode":"V4L 2N7",
    "sg:province":"BC",
    "sg:tags":[
        "company",
        "land"
    ],
    "wof:name":"Bardi Holdings Ltd",
    "wof:placetype":"venue"
},
  "geometry": {"coordinates":[-123.046356,49.05373],"type":"Point"}
}