{
  "type": "Feature",
  "properties": {
    "addr:full":"101 South Bay Rd Elliot Lake ON P5A 2S9",
    "addr:housenumber":"101",
    "addr:postcode":"p5a 2s9",
    "addr:street":"South Bay Rd",
    "iso:country":"CA",
    "sg:address":"101 South Bay Rd",
    "sg:city":"Elliot Lake",
    "sg:classifiers":[
        {
            "category":"Travel",
            "subcategory":"Campground",
            "type":"Entertainment"
        }
    ],
    "sg:phone":"+1 705 848 2804",
    "sg:postcode":"P5A 2S9",
    "sg:province":"ON",
    "wof:name":"South Bay Park",
    "wof:placetype":"venue"
},
  "geometry": {"coordinates":[-82.6519775391,46.379863739],"type":"Point"}
}