{
  "type": "Feature",
  "properties": {
    "addr:full":"Lloydminster AB T9V 2X2",
    "addr:postcode":"t9v 2x2",
    "iso:country":"CA",
    "sg:city":"Lloydminster",
    "sg:classifiers":[
        {
            "category":"Shopping",
            "subcategory":"Clothing, Apparel, & Fashions",
            "type":"Retail Goods"
        }
    ],
    "sg:phone":"+1 780 875 1221",
    "sg:postcode":"T9V 2X2",
    "sg:province":"AB",
    "wof:name":"Mark's Work Wearhouse Ltd",
    "wof:placetype":"venue"
},
  "geometry": {"coordinates":[-110.047905,53.276901],"type":"Point"}
}