{
  "type": "Feature",
  "properties": {
    "addr:full":"106 Mcgonigal St W Arnprior ON K7S 1M4",
    "addr:housenumber":"106",
    "addr:postcode":"k7s 1m4",
    "addr:street":"Mcgonigal St W",
    "iso:country":"CA",
    "sg:address":"106 Mcgonigal St W",
    "sg:city":"Arnprior",
    "sg:classifiers":[
        {
            "category":"Shopping",
            "type":"Retail Goods"
        }
    ],
    "sg:phone":"+1 613 623 0210",
    "sg:postcode":"K7S 1M4",
    "sg:province":"ON",
    "sg:tags":[
        "equipment",
        "liquor",
        "wine",
        "store",
        "supply"
    ],
    "wof:name":"Valley Brewmaster",
    "wof:placetype":"venue"
},
  "geometry": {"coordinates":[-76.35778000000001,45.434326],"type":"Point"}
}