{
  "type": "Feature",
  "properties": {
    "addr:full":"431 Richmond St E Toronto ON M5A 1R1",
    "addr:housenumber":"431",
    "addr:postcode":"m5a 1r1",
    "addr:street":"Richmond St E",
    "iso:country":"CA",
    "sg:address":"431 Richmond St E",
    "sg:city":"Toronto",
    "sg:classifiers":[
        {
            "category":"Communications",
            "subcategory":"Film & Video Production",
            "type":"Services"
        }
    ],
    "sg:phone":"+1 416 360 7500",
    "sg:postcode":"M5A 1R1",
    "sg:province":"ON",
    "sg:tags":[
        "motion",
        "picture",
        "studio",
        "producer"
    ],
    "wof:name":"Videogenic Corp",
    "wof:placetype":"venue"
},
  "geometry": {"coordinates":[-79.36646270750001,43.6538352966],"type":"Point"}
}