{
  "type": "Feature",
  "properties": {
    "addr:full":"485 Speedvale Ave E Guelph ON N1E 6J2",
    "addr:housenumber":"485",
    "addr:postcode":"n1e 6j2",
    "addr:street":"Speedvale Ave E",
    "iso:country":"CA",
    "sg:address":"485 Speedvale Ave E",
    "sg:city":"Guelph",
    "sg:classifiers":[
        {
            "category":"Food & Beverages",
            "subcategory":"Bakery",
            "type":"Retail Goods"
        }
    ],
    "sg:phone":"+1 519 836 6840",
    "sg:postcode":"N1E 6J2",
    "sg:province":"ON",
    "sg:tags":[
        "doughnut"
    ],
    "wof:name":"Coffee Stop Cafe",
    "wof:placetype":"venue"
},
  "geometry": {"coordinates":[-80.251648,43.570297],"type":"Point"}
}