{
  "type": "Feature",
  "properties": {
    "addr:full":"2363 133 Rte Saint-Jean-Sur-Richelieu QC J2X 5V2",
    "addr:housenumber":"2363",
    "addr:postcode":"j2x 5v2",
    "addr:street":"133 Rte",
    "iso:country":"CA",
    "sg:address":"2363 133 Rte",
    "sg:city":"Saint-Jean-Sur-Richelieu",
    "sg:classifiers":[
        {
            "category":"Food & Beverages",
            "subcategory":"Groceries & Convenience Stores",
            "type":"Retail Goods"
        }
    ],
    "sg:phone":"+1 450 542 9532",
    "sg:postcode":"J2X 5V2",
    "sg:province":"QC",
    "wof:name":"Depanneur 2000 Enr",
    "wof:placetype":"venue"
},
  "geometry": {"coordinates":[-73.24575,45.43996],"type":"Point"}
}