{
  "type": "Feature",
  "properties": {
    "iso:country":"CA",
    "sg:address":"138 Brickyard Rd",
    "sg:city":"Albert Bridge",
    "sg:classifiers":[
        {
            "category":"Education",
            "subcategory":"Special Training",
            "type":"Public Place"
        }
    ],
    "sg:phone":"+1 902 567 6677",
    "sg:postcode":"B1K 2R4",
    "sg:province":"NS",
    "sg:tags":[
        "instruction",
        "music"
    ],
    "wof:name":"Raylene's School of Music",
    "wof:placetype":"venue"
},
  "geometry": {"coordinates":[-60.0584373474,46.0203132629],"type":"Point"}
}