{
  "type": "Feature",
  "properties": {
    "iso:country":"CA",
    "sg:address":"Tolmies Corners Rd",
    "sg:city":"Moose Creek",
    "sg:classifiers":[
        {
            "category":"Government",
            "subcategory":"Office",
            "type":"Public Place"
        }
    ],
    "sg:phone":"+1 613 538 2399",
    "sg:postcode":"K0C 1W0",
    "sg:province":"ON",
    "sg:tags":[
        "village"
    ],
    "wof:name":"North Stromont Road Garage",
    "wof:placetype":"venue"
},
  "geometry": {"coordinates":[-74.9556808472,45.2436790466],"type":"Point"}
}