{
  "type": "Feature",
  "properties": {
    "addr:full":"32 Rue Notre Dame E LA Patrie QC J0B 1Y0",
    "addr:housenumber":"32",
    "addr:postcode":"j0b 1y0",
    "addr:street":"Rue Notre Dame E La Patrie",
    "iso:country":"CA",
    "sg:address":"32 Rue Notre Dame E",
    "sg:city":"LA Patrie",
    "sg:classifiers":[
        {
            "category":"Freight",
            "type":"Transportation"
        }
    ],
    "sg:phone":"+1 819 888 2450",
    "sg:postcode":"J0B 1Y0",
    "sg:province":"QC",
    "sg:tags":[
        "trucking"
    ],
    "wof:name":"Transport Armand Prevost",
    "wof:placetype":"venue"
},
  "geometry": {"coordinates":[-71.2439651489,45.4020309448],"type":"Point"}
}