{
  "type": "Feature",
  "properties": {
    "addr:full":"777 Hyde Park Rd London ON N6H 3S2",
    "addr:housenumber":"777",
    "addr:postcode":"n6h 3s2",
    "addr:street":"Hyde Park Rd",
    "iso:country":"CA",
    "sg:address":"777 Hyde Park Rd",
    "sg:city":"London",
    "sg:classifiers":[
        {
            "category":"Autos & Motor Vehicles",
            "subcategory":"Fuel & Gas Station",
            "type":"Retail Goods"
        }
    ],
    "sg:phone":"+1 519 641 0472",
    "sg:postcode":"N6H 3S2",
    "sg:province":"ON",
    "sg:tags":[
        "oil"
    ],
    "wof:name":"Sunoco",
    "wof:placetype":"venue"
},
  "geometry": {"coordinates":[-81.32140350340001,42.9780883789],"type":"Point"}
}