{
  "type": "Feature",
  "properties": {
    "addr:full":"4492 Rue Sherbrooke O Westmount QC H3Z 1E6",
    "addr:housenumber":"4492",
    "addr:postcode":"h3z 1e6",
    "addr:street":"Rue Sherbrooke O",
    "iso:country":"CA",
    "sg:address":"4492 Rue Sherbrooke O",
    "sg:city":"Westmount",
    "sg:classifiers":[
        {
            "category":"Health Services",
            "subcategory":"Doctor",
            "type":"Services"
        }
    ],
    "sg:phone":"+1 514 935 7144",
    "sg:postcode":"H3Z 1E6",
    "sg:province":"QC",
    "sg:tags":[
        "physician",
        "surgeon"
    ],
    "wof:name":"Shannon, J D MD",
    "wof:placetype":"venue"
},
  "geometry": {"coordinates":[-73.59815979,45.4833755493],"type":"Point"}
}