{
  "type": "Feature",
  "properties": {
    "addr:full":"38 Oliver Cres New Maryland NB E3C 1E2",
    "addr:housenumber":"38",
    "addr:postcode":"e3c 1e2",
    "addr:street":"Oliver Cres",
    "iso:country":"CA",
    "sg:address":"38 Oliver Cres",
    "sg:city":"New Maryland",
    "sg:classifiers":[
        {
            "category":"Professional",
            "subcategory":"Business Services",
            "type":"Services"
        }
    ],
    "sg:phone":"+1 506 459 7337",
    "sg:postcode":"E3C 1E2",
    "sg:province":"NB",
    "sg:tags":[
        "drafting"
    ],
    "wof:name":"H P Home Plans Inc",
    "wof:placetype":"venue"
},
  "geometry": {"coordinates":[-66.68356300000001,45.896561],"type":"Point"}
}