{
  "type": "Feature",
  "properties": {
    "addr:full":"4417 Rue Des Lierres Charlesbourg QC G1G 1S2",
    "addr:housenumber":"4417",
    "addr:postcode":"g1g 1s2",
    "addr:street":"Rue Des Lierres",
    "iso:country":"CA",
    "sg:address":"4417 Rue Des Lierres",
    "sg:city":"Charlesbourg",
    "sg:classifiers":[
        {
            "category":"Government",
            "subcategory":"Office",
            "type":"Public Place"
        }
    ],
    "sg:phone":"+1 418 626 3598",
    "sg:postcode":"G1G 1S2",
    "sg:province":"QC",
    "sg:tags":[
        "village"
    ],
    "wof:name":"Lac St-Joseph Ville",
    "wof:placetype":"venue"
},
  "geometry": {"coordinates":[-71.281471,46.882374],"type":"Point"}
}