{
  "type": "Feature",
  "properties": {
    "addr:full":"155 Queen St N Hamilton ON L8R 2V6",
    "addr:housenumber":"155",
    "addr:postcode":"l8r 2v6",
    "addr:street":"Queen St N",
    "iso:country":"CA",
    "sg:address":"155 Queen St N",
    "sg:city":"Hamilton",
    "sg:classifiers":[
        {
            "category":"Social Services",
            "type":"Services"
        }
    ],
    "sg:phone":"+1 905 527 0221",
    "sg:postcode":"L8R 2V6",
    "sg:province":"ON",
    "sg:tags":[
        "housing",
        "assistance"
    ],
    "wof:name":"Victoria Park Community Homes",
    "wof:placetype":"venue"
},
  "geometry": {"coordinates":[-79.876892,43.26421],"type":"Point"}
}