{
  "type": "Feature",
  "properties": {
    "iso:country":"CA",
    "sg:address":"775 John St",
    "sg:city":"Thunder Bay",
    "sg:classifiers":[
        {
            "category":"Education",
            "subcategory":"School",
            "type":"Public Place"
        }
    ],
    "sg:phone":"+1 807 767 3052",
    "sg:postcode":"P7B 1Z7",
    "sg:province":"ON",
    "wof:name":"E Q Jennings School",
    "wof:placetype":"venue"
},
  "geometry": {"coordinates":[-89.2560958862,48.4360084534],"type":"Point"}
}