{
  "type": "Feature",
  "properties": {
    "addr:full":"65 Enterprise Rd Etobicoke ON M9W 1C4",
    "addr:housenumber":"65",
    "addr:postcode":"m9w 1c4",
    "addr:street":"Enterprise Rd",
    "iso:country":"CA",
    "sg:address":"65 Enterprise Rd",
    "sg:city":"Etobicoke",
    "sg:classifiers":[
        {
            "category":"Building & Trades",
            "subcategory":"Construction",
            "type":"Services"
        }
    ],
    "sg:phone":"+1 416 248 5697",
    "sg:postcode":"M9W 1C4",
    "sg:province":"ON",
    "sg:tags":[
        "general",
        "contractor"
    ],
    "wof:name":"J M Fuller Ltd",
    "wof:placetype":"venue"
},
  "geometry": {"coordinates":[-79.570786,43.696964],"type":"Point"}
}