{
  "type": "Feature",
  "properties": {
    "addr:full":"Mississauga ON L4V 1W9",
    "addr:postcode":"l4v 1w9",
    "iso:country":"CA",
    "sg:city":"Mississauga",
    "sg:classifiers":[
        {
            "category":"Freight",
            "type":"Transportation"
        }
    ],
    "sg:phone":"+1 905 612 0888",
    "sg:postcode":"L4V 1W9",
    "sg:province":"ON",
    "sg:tags":[
        "trucking"
    ],
    "wof:name":"Care Transportation Svc",
    "wof:placetype":"venue"
},
  "geometry": {"coordinates":[-79.61586761469999,43.6954231262],"type":"Point"}
}