{
  "type": "Feature",
  "properties": {
    "addr:full":"121 Woodbridge Ave # 228 Woodbridge ON L4L 9E3",
    "addr:housenumber":"121",
    "addr:postcode":"l4l 9e3",
    "addr:street":"Woodbridge Ave # 228",
    "iso:country":"CA",
    "sg:address":"121 Woodbridge Ave # 228",
    "sg:city":"Woodbridge",
    "sg:classifiers":[
        {
            "category":"Real Estate",
            "subcategory":"Real Estate Operator",
            "type":"Services"
        }
    ],
    "sg:phone":"+1 905 264 9497",
    "sg:postcode":"L4L 9E3",
    "sg:province":"ON",
    "sg:tags":[
        "condominium"
    ],
    "wof:name":"Terraces of Woodbridge",
    "wof:placetype":"venue"
},
  "geometry": {"coordinates":[-79.592461,43.784821],"type":"Point"}
}