{
  "type": "Feature",
  "properties": {
    "addr:full":"1893 Boul Dagenais O Laval QC H7L 5A3",
    "addr:housenumber":"1893",
    "addr:postcode":"h7l 5a3",
    "addr:street":"Boul Dagenais O",
    "iso:country":"CA",
    "sg:address":"1893 Boul Dagenais O",
    "sg:city":"Laval",
    "sg:classifiers":[
        {
            "category":"Home & Garden",
            "subcategory":"Carpets & Floor Coverings",
            "type":"Retail Goods"
        }
    ],
    "sg:phone":"+1 450 628 6868",
    "sg:postcode":"H7L 5A3",
    "sg:province":"QC",
    "sg:tags":[
        "consultant"
    ],
    "wof:name":"Couvre-Planchers Labrosse Inc",
    "wof:placetype":"venue"
},
  "geometry": {"coordinates":[-73.7592544556,45.592590332],"type":"Point"}
}