{
  "type": "Feature",
  "properties": {
    "addr:full":"15 Salt Dock Rd Parry Sound ON P2A 2X2",
    "addr:housenumber":"15",
    "addr:postcode":"p2a 2x2",
    "addr:street":"Salt Dock Rd",
    "iso:country":"CA",
    "sg:address":"15 Salt Dock Rd",
    "sg:city":"Parry Sound",
    "sg:classifiers":[
        {
            "category":"Wholesale",
            "subcategory":"Groceries",
            "type":"Manufacturing & Wholesale Goods"
        }
    ],
    "sg:phone":"+1 705 746 2165",
    "sg:postcode":"P2A 2X2",
    "sg:province":"ON",
    "sg:tags":[
        "salt"
    ],
    "wof:name":"Sifto Salt",
    "wof:placetype":"venue"
},
  "geometry": {"coordinates":[-80.04692799999999,45.350731],"type":"Point"}
}