{
  "type": "Feature",
  "properties": {
    "addr:full":"Walkerton ON N0G 2V0",
    "addr:postcode":"n0g 2v0",
    "addr:street":"Walkerton",
    "iso:country":"CA",
    "sg:city":"Walkerton",
    "sg:classifiers":[
        {
            "category":"Professional",
            "subcategory":"Business Services",
            "type":"Services"
        }
    ],
    "sg:phone":"+1 519 881 4878",
    "sg:postcode":"N0G 2V0",
    "sg:province":"ON",
    "sg:tags":[
        "appraiser"
    ],
    "wof:name":"Lipskie Appraisal Svc",
    "wof:placetype":"venue"
},
  "geometry": {"coordinates":[-81.14720199999999,44.13303],"type":"Point"}
}