{
  "type": "Feature",
  "properties": {
    "addr:full":"RR 2 Hawkestone ON L0L 1T0",
    "addr:postcode":"l0l 1t0",
    "addr:street":"Rr 2",
    "iso:country":"CA",
    "sg:address":"RR 2",
    "sg:city":"Hawkestone",
    "sg:classifiers":[
        {
            "category":"Professional",
            "subcategory":"Business Services",
            "type":"Services"
        }
    ],
    "sg:phone":"+1 705 487 1618",
    "sg:postcode":"L0L 1T0",
    "sg:province":"ON",
    "sg:tags":[
        "interior",
        "consultant",
        "design",
        "decorator"
    ],
    "wof:name":"Andrew Mc Intyre Design & Drft",
    "wof:placetype":"venue"
},
  "geometry": {"coordinates":[-79.467873,44.497467],"type":"Point"}
}