{
  "type": "Feature",
  "properties": {
    "addr:full":"Innisfil ON L9S 1Y8",
    "addr:postcode":"l9s 1y8",
    "iso:country":"CA",
    "sg:city":"Innisfil",
    "sg:classifiers":[
        {
            "category":"Shopping",
            "subcategory":"Pharmacy",
            "type":"Retail Goods"
        }
    ],
    "sg:phone":"+1 705 436 2874",
    "sg:postcode":"L9S 1Y8",
    "sg:province":"ON",
    "wof:name":"Shoppers Drug Mart",
    "wof:placetype":"venue"
},
  "geometry": {"coordinates":[-79.54220581049999,44.316028595],"type":"Point"}
}