{
  "type": "Feature",
  "properties": {
    "addr:full":"PO Box 238 Dildo NL A0B 1P0",
    "addr:housenumber":"po",
    "addr:postcode":"a0b 1p0",
    "addr:street":"Box 238",
    "iso:country":"CA",
    "sg:address":"PO Box 238",
    "sg:city":"Dildo",
    "sg:classifiers":[
        {
            "category":"Building & Trades",
            "subcategory":"Construction",
            "type":"Services"
        }
    ],
    "sg:phone":"+1 709 582 2628",
    "sg:postcode":"A0B 1P0",
    "sg:province":"NL",
    "sg:tags":[
        "excavating",
        "contractor",
        "topsoil"
    ],
    "wof:name":"Hobb's Construction Ltd",
    "wof:placetype":"venue"
},
  "geometry": {"coordinates":[-53.5485725403,47.5628204346],"type":"Point"}
}