{
  "type": "Feature",
  "properties": {
    "addr:full":"176 Farnham Rd Belleville ON K8N 4Z5",
    "addr:housenumber":"176",
    "addr:postcode":"k8n 4z5",
    "addr:street":"Farnham Rd",
    "iso:country":"CA",
    "sg:address":"176 Farnham Rd",
    "sg:city":"Belleville",
    "sg:classifiers":[
        {
            "category":"Building & Trades",
            "subcategory":"Construction",
            "type":"Services"
        }
    ],
    "sg:phone":"+1 613 969 1818",
    "sg:postcode":"K8N 4Z5",
    "sg:province":"ON",
    "sg:tags":[
        "dock",
        "designer",
        "marine",
        "contractor"
    ],
    "wof:name":"Quinte Boatdocks",
    "wof:placetype":"venue"
},
  "geometry": {"coordinates":[-77.402519,44.217289],"type":"Point"}
}