{
  "type": "Feature",
  "properties": {
    "addr:full":"451 Tecumseh Rd W Windsor ON N8X 1G8",
    "addr:housenumber":"451",
    "addr:postcode":"n8x 1g8",
    "addr:street":"Tecumseh Rd W",
    "iso:country":"CA",
    "sg:address":"451 Tecumseh Rd W",
    "sg:city":"Windsor",
    "sg:classifiers":[
        {
            "category":"Retail",
            "subcategory":"Auto Repair",
            "type":"Services"
        }
    ],
    "sg:phone":"+1 519 256 4488",
    "sg:postcode":"N8X 1G8",
    "sg:province":"ON",
    "sg:tags":[
        "automobile",
        "rustproofing",
        "undercoating"
    ],
    "wof:name":"Oil Gard Canada",
    "wof:placetype":"venue"
},
  "geometry": {"coordinates":[-83.030418396,42.2953567505],"type":"Point"}
}