{
  "type": "Feature",
  "properties": {
    "addr:full":"Edmonton AB T6E 0A2",
    "addr:postcode":"t6e 0a2",
    "iso:country":"CA",
    "sg:city":"Edmonton",
    "sg:classifiers":[
        {
            "category":"Building & Trades",
            "subcategory":"Electrical",
            "type":"Services"
        }
    ],
    "sg:phone":"+1 780 466 9292",
    "sg:postcode":"T6E 0A2",
    "sg:province":"AB",
    "sg:tags":[
        "electric",
        "contractor"
    ],
    "wof:name":"Charger Installations",
    "wof:placetype":"venue"
},
  "geometry": {"coordinates":[-113.484848023,53.4763183594],"type":"Point"}
}