{
  "type": "Feature",
  "properties": {
    "iso:country":"CA",
    "sg:address":"448 Welland Ave # 6",
    "sg:city":"St Catharines",
    "sg:classifiers":[
        {
            "category":"Personal",
            "subcategory":"Tanning Parlor",
            "type":"Services"
        }
    ],
    "sg:phone":"+1 905 704 0513",
    "sg:postcode":"L2M 7V3",
    "sg:province":"ON",
    "sg:tags":[
        "salon"
    ],
    "wof:name":"Surround Sun Tanning CO Inc",
    "wof:placetype":"venue"
},
  "geometry": {"coordinates":[-79.218513,43.173351],"type":"Point"}
}