{
  "type": "Feature",
  "properties": {
    "iso:country":"CA",
    "sg:address":"PO Box 481",
    "sg:city":"Esterhazy",
    "sg:classifiers":[
        {
            "category":"Building & Trades",
            "subcategory":"Plumbing",
            "type":"Services"
        }
    ],
    "sg:phone":"+1 306 745 2700",
    "sg:postcode":"S0A 0X0",
    "sg:province":"SK",
    "sg:tags":[
        "furnace",
        "cleaning"
    ],
    "wof:name":"Professional Vac & Septic Svc",
    "wof:placetype":"venue"
},
  "geometry": {"coordinates":[-102.075698852,50.6538963318],"type":"Point"}
}