{
  "type": "Feature",
  "properties": {
    "addr:full":"582 Main St Sussex NB E4E 7H8",
    "addr:housenumber":"582",
    "addr:postcode":"e4e 7h8",
    "addr:street":"Main St",
    "iso:country":"CA",
    "sg:address":"582 Main St",
    "sg:city":"Sussex",
    "sg:classifiers":[
        {
            "category":"Banks & Credit Unions",
            "subcategory":"Bank",
            "type":"Services"
        }
    ],
    "sg:phone":"+1 506 433 5005",
    "sg:postcode":"E4E 7H8",
    "sg:province":"NB",
    "wof:name":"Bayview Credit Union",
    "wof:placetype":"venue"
},
  "geometry": {"coordinates":[-65.508568,45.723343],"type":"Point"}
}