{
  "type": "Feature",
  "properties": {
    "addr:full":"695 Scarlett Rd Etobicoke ON M9P 2T3",
    "addr:housenumber":"695",
    "addr:postcode":"m9p 2t3",
    "addr:street":"Scarlett Rd",
    "iso:country":"CA",
    "sg:address":"695 Scarlett Rd",
    "sg:city":"Etobicoke",
    "sg:classifiers":[
        {
            "category":"Organizations",
            "subcategory":"Religious Organization",
            "type":"Services"
        }
    ],
    "sg:phone":"+1 416 537 7861",
    "sg:postcode":"M9P 2T3",
    "sg:province":"ON",
    "sg:tags":[
        "church"
    ],
    "wof:name":"Christadelphian's",
    "wof:placetype":"venue"
},
  "geometry": {"coordinates":[-79.519524,43.695095],"type":"Point"}
}