{
  "type": "Feature",
  "properties": {
    "addr:full":"26 Rue Gamble E Rouyn-Noranda QC J9X 3B7",
    "addr:housenumber":"26",
    "addr:postcode":"j9x 3b7",
    "addr:street":"Rue Gamble E",
    "iso:country":"CA",
    "sg:address":"26 Rue Gamble E",
    "sg:city":"Rouyn-Noranda",
    "sg:classifiers":[
        {
            "category":"Shopping",
            "subcategory":"Crafts & Fabrics",
            "type":"Retail Goods"
        }
    ],
    "sg:phone":"+1 819 762 1104",
    "sg:postcode":"J9X 3B7",
    "sg:province":"QC",
    "sg:tags":[
        "shop",
        "curtain",
        "drapery"
    ],
    "wof:name":"Fabricville",
    "wof:placetype":"venue"
},
  "geometry": {"coordinates":[-79.01945495610001,48.2397994995],"type":"Point"}
}