{
  "type": "Feature",
  "properties": {
    "iso:country":"CA",
    "sg:city":"Quebec",
    "sg:classifiers":[
        {
            "category":"Professional",
            "subcategory":"Computer Services",
            "type":"Services"
        }
    ],
    "sg:phone":"+1 418 687 7333",
    "sg:postcode":"G1S 2N2",
    "sg:province":"QC",
    "sg:tags":[
        "internet"
    ],
    "wof:name":"Internet Vip Inc",
    "wof:placetype":"venue"
},
  "geometry": {"coordinates":[-71.2551193237,46.7941856384],"type":"Point"}
}