{
  "type": "Feature",
  "properties": {
    "addr:full":"Kingston ON K7K 5W7",
    "addr:postcode":"k7k 5w7",
    "iso:country":"CA",
    "sg:city":"Kingston",
    "sg:classifiers":[
        {
            "category":"Organizations",
            "subcategory":"Non-profit Organization",
            "type":"Services"
        }
    ],
    "sg:phone":"+1 613 546 1758",
    "sg:postcode":"K7K 5W7",
    "sg:province":"ON",
    "sg:tags":[
        "addiction",
        "treatment",
        "center"
    ],
    "wof:name":"Kingston Gambling Info & Couns",
    "wof:placetype":"venue"
},
  "geometry": {"coordinates":[-76.48393249510001,44.2321815491],"type":"Point"}
}