{
  "type": "Feature",
  "properties": {
    "addr:full":"Waterloo ON N2J 4V2",
    "addr:postcode":"n2j 4v2",
    "iso:country":"CA",
    "sg:city":"Waterloo",
    "sg:classifiers":[
        {
            "category":"Health Services",
            "subcategory":"Doctor",
            "type":"Services"
        }
    ],
    "sg:phone":"+1 519 888 6313",
    "sg:postcode":"N2J 4V2",
    "sg:province":"ON",
    "sg:tags":[
        "dentist"
    ],
    "wof:name":"Costigane, Robert DDS",
    "wof:placetype":"venue"
},
  "geometry": {"coordinates":[-80.52526899999999,43.47665],"type":"Point"}
}