{
  "type": "Feature",
  "properties": {
    "iso:country":"CA",
    "sg:address":"4809 South Access Rd",
    "sg:city":"Chetwynd",
    "sg:classifiers":[
        {
            "category":"Autos & Motor Vehicles",
            "subcategory":"Auto Supplies",
            "type":"Retail Goods"
        }
    ],
    "sg:phone":"+1 250 788 2067",
    "sg:postcode":"V0C 1J0",
    "sg:province":"BC",
    "sg:tags":[
        "tire"
    ],
    "wof:name":"Kal Tire",
    "wof:placetype":"venue"
},
  "geometry": {"coordinates":[-121.626274,55.696804],"type":"Point"}
}