{
  "type": "Feature",
  "properties": {
    "iso:country":"CA",
    "sg:address":"12 Lighthouse Rd",
    "sg:city":"Callander",
    "sg:classifiers":[
        {
            "category":"Shopping",
            "subcategory":"Bicycles & Sporting Goods",
            "type":"Retail Goods"
        }
    ],
    "sg:phone":"+1 705 752 1650",
    "sg:postcode":"P0H 1H0",
    "sg:province":"ON",
    "sg:tags":[
        "lawn",
        "garden",
        "supply"
    ],
    "wof:name":"South Shore Outdoor Sports",
    "wof:placetype":"venue"
},
  "geometry": {"coordinates":[-79.4101257324,46.1894493103],"type":"Point"}
}