{
  "type": "Feature",
  "properties": {
    "addr:full":"55 Regalcrest Crt Woodbridge ON L4L 8P3",
    "addr:housenumber":"55",
    "addr:postcode":"l4l 8p3",
    "addr:street":"Regalcrest Crt",
    "iso:country":"CA",
    "sg:address":"55 Regalcrest Crt",
    "sg:city":"Woodbridge",
    "sg:classifiers":[
        {
            "category":"Manufacturing",
            "subcategory":"Rubber & Plastics",
            "type":"Manufacturing & Wholesale Goods"
        }
    ],
    "sg:phone":"+1 905 850 6020",
    "sg:postcode":"L4L 8P3",
    "sg:province":"ON",
    "wof:name":"Royal Group Resources",
    "wof:placetype":"venue"
},
  "geometry": {"coordinates":[-79.6180725098,43.7688179016],"type":"Point"}
}