{
  "type": "Feature",
  "properties": {
    "addr:full":"Spruce Grove AB T7Y 1E3",
    "addr:postcode":"t7y 1e3",
    "iso:country":"CA",
    "sg:city":"Spruce Grove",
    "sg:classifiers":[
        {
            "category":"Building & Trades",
            "subcategory":"Construction",
            "type":"Services"
        }
    ],
    "sg:phone":"+1 780 470 0040",
    "sg:postcode":"T7Y 1E3",
    "sg:province":"AB",
    "sg:tags":[
        "builder",
        "stair"
    ],
    "wof:name":"Meier Railing",
    "wof:placetype":"venue"
},
  "geometry": {"coordinates":[-113.901855,53.544636],"type":"Point"}
}