{
  "type": "Feature",
  "properties": {
    "addr:full":"North York ON M2J 5C9",
    "addr:postcode":"m2j 5c9",
    "iso:country":"CA",
    "sg:city":"North York",
    "sg:classifiers":[
        {
            "category":"Retail",
            "subcategory":"Portrait Studio",
            "type":"Services"
        }
    ],
    "sg:phone":"+1 416 495 9219",
    "sg:postcode":"M2J 5C9",
    "sg:province":"ON",
    "sg:tags":[
        "photographer"
    ],
    "wof:name":"Ideas To Images",
    "wof:placetype":"venue"
},
  "geometry": {"coordinates":[-79.33521270750001,43.7729759216],"type":"Point"}
}