{
  "type": "Feature",
  "properties": {
    "addr:full":"124 Rue Saint-Vincent Sainte-Agathe-Des-Monts QC J8C 2B1",
    "addr:housenumber":"124",
    "addr:postcode":"j8c 2b1",
    "addr:street":"Rue Saint-Vincent",
    "iso:country":"CA",
    "sg:address":"124 Rue Saint-Vincent",
    "sg:city":"Sainte-Agathe-Des-Monts",
    "sg:classifiers":[
        {
            "category":"Banks & Credit Unions",
            "subcategory":"Financial Services",
            "type":"Services"
        }
    ],
    "sg:phone":"+1 819 321 2844",
    "sg:postcode":"J8C 2B1",
    "sg:province":"QC",
    "sg:tags":[
        "bankruptcy",
        "trustee"
    ],
    "wof:name":"Aberback Lapointe & Assoc Inc",
    "wof:placetype":"venue"
},
  "geometry": {"coordinates":[-74.28834500000001,46.050453],"type":"Point"}
}