{
  "type": "Feature",
  "properties": {
    "addr:full":"900 Maple Ave Burlington ON L7S 2J8",
    "addr:housenumber":"900",
    "addr:postcode":"l7s 2j8",
    "addr:street":"Maple Ave",
    "iso:country":"CA",
    "sg:address":"900 Maple Ave",
    "sg:city":"Burlington",
    "sg:classifiers":[
        {
            "category":"Shopping",
            "subcategory":"Clothing, Apparel, & Fashions",
            "type":"Retail Goods"
        }
    ],
    "sg:phone":"+1 905 631 3300",
    "sg:postcode":"L7S 2J8",
    "sg:province":"ON",
    "sg:tags":[
        "leather"
    ],
    "wof:name":"Danier Leather",
    "wof:placetype":"venue"
},
  "geometry": {"coordinates":[-79.81972500000001,43.327824],"type":"Point"}
}