{
  "type": "Feature",
  "properties": {
    "iso:country":"CA",
    "sg:address":"41 Jena Cres",
    "sg:city":"London",
    "sg:classifiers":[
        {
            "category":"Professional",
            "subcategory":"Advertising",
            "type":"Services"
        }
    ],
    "sg:phone":"+1 519 452 3215",
    "sg:postcode":"N5V 1L3",
    "sg:province":"ON",
    "sg:tags":[
        "mailing",
        "list"
    ],
    "wof:name":"Stuffer's Plus",
    "wof:placetype":"venue"
},
  "geometry": {"coordinates":[-81.15924835209999,43.0009918213],"type":"Point"}
}