{
  "type": "Feature",
  "properties": {
    "addr:full":"263 Guildwood Dr Hamilton ON L9C 6W7",
    "addr:housenumber":"263",
    "addr:postcode":"l9c 6w7",
    "addr:street":"Guildwood Dr",
    "iso:country":"CA",
    "sg:address":"263 Guildwood Dr",
    "sg:city":"Hamilton",
    "sg:classifiers":[
        {
            "category":"Wholesale",
            "subcategory":"Electrical",
            "type":"Manufacturing & Wholesale Goods"
        }
    ],
    "sg:phone":"+1 905 383 3111",
    "sg:postcode":"L9C 6W7",
    "sg:province":"ON",
    "sg:tags":[
        "equipment",
        "electric",
        "supply"
    ],
    "wof:name":"Smc Sales Agency",
    "wof:placetype":"venue"
},
  "geometry": {"coordinates":[-79.92469024659999,43.2261924744],"type":"Point"}
}