{
  "type": "Feature",
  "properties": {
    "addr:full":"1021 329 Rte Lantier QC J0T 1V0",
    "addr:housenumber":"1021",
    "addr:postcode":"j0t 1v0",
    "addr:street":"329 Rte Lantier",
    "iso:country":"CA",
    "sg:address":"1021 329 Rte",
    "sg:city":"Lantier",
    "sg:classifiers":[
        {
            "category":"Organizations",
            "subcategory":"Religious Organization",
            "type":"Services"
        }
    ],
    "sg:phone":"+1 819 326 2907",
    "sg:postcode":"J0T 1V0",
    "sg:province":"QC",
    "sg:tags":[
        "church"
    ],
    "wof:name":"Presbyteres Eglise",
    "wof:placetype":"venue"
},
  "geometry": {"coordinates":[-74.2505950928,46.1489257812],"type":"Point"}
}