{
  "type": "Feature",
  "properties": {
    "addr:full":"135 Selkirk Ave Winnipeg MB R2W 2L1",
    "addr:housenumber":"135",
    "addr:postcode":"r2w 2l1",
    "addr:street":"Selkirk Ave",
    "iso:country":"CA",
    "sg:address":"135 Selkirk Ave",
    "sg:city":"Winnipeg",
    "sg:classifiers":[
        {
            "category":"Building & Trades",
            "subcategory":"Construction",
            "type":"Services"
        }
    ],
    "sg:phone":"+1 204 582 7765",
    "sg:postcode":"R2W 2L1",
    "sg:province":"MB",
    "sg:tags":[
        "general",
        "contractor"
    ],
    "wof:name":"Mar-Jess Construction Inc",
    "wof:placetype":"venue"
},
  "geometry": {"coordinates":[-97.129738,49.912056],"type":"Point"}
}