{
  "type": "Feature",
  "properties": {
    "addr:full":"144 Boul DE Gaspe Gaspe QC G4X 1A9",
    "addr:housenumber":"144",
    "addr:postcode":"g4x 1a9",
    "addr:street":"Boul De Gaspe",
    "iso:country":"CA",
    "sg:address":"144 Boul DE Gaspe",
    "sg:city":"Gaspe",
    "sg:classifiers":[
        {
            "category":"Organizations",
            "subcategory":"Professional Association",
            "type":"Services"
        }
    ],
    "sg:phone":"+1 418 368 2349",
    "sg:postcode":"G4X 1A9",
    "sg:province":"QC",
    "wof:name":"Regie Regionale DE LA Sante",
    "wof:placetype":"venue"
},
  "geometry": {"coordinates":[-64.478607,48.838581],"type":"Point"}
}