{
  "type": "Feature",
  "properties": {
    "addr:full":"50 Tenth St # 3 Nanaimo BC V9R 6L1",
    "addr:housenumber":"50",
    "addr:postcode":"v9r 6l1",
    "addr:street":"Tenth St # 3",
    "iso:country":"CA",
    "sg:address":"50 Tenth St # 3",
    "sg:city":"Nanaimo",
    "sg:classifiers":[
        {
            "category":"Restaurant",
            "type":"Food & Drink"
        }
    ],
    "sg:phone":"+1 250 753 6433",
    "sg:postcode":"V9R 6L1",
    "sg:province":"BC",
    "wof:name":"Southgate Restaurant",
    "wof:placetype":"venue"
},
  "geometry": {"coordinates":[-123.923393,49.130981],"type":"Point"}
}