{
  "type": "Feature",
  "properties": {
    "addr:full":"1105 Wellington Rd # 965 London ON N6E 1V4",
    "addr:housenumber":"1105",
    "addr:postcode":"n6e 1v4",
    "addr:street":"Wellington Rd # 965",
    "iso:country":"CA",
    "sg:address":"1105 Wellington Rd # 965",
    "sg:city":"London",
    "sg:classifiers":[
        {
            "category":"Shopping",
            "subcategory":"Optical Goods",
            "type":"Retail Goods"
        }
    ],
    "sg:phone":"+1 519 649 2377",
    "sg:postcode":"N6E 1V4",
    "sg:province":"ON",
    "sg:tags":[
        "optician"
    ],
    "wof:name":"Lenscrafters",
    "wof:placetype":"venue"
},
  "geometry": {"coordinates":[-81.2216415405,42.9316215515],"type":"Point"}
}