{
  "type": "Feature",
  "properties": {
    "addr:full":"299 Waverley St Thunder Bay ON P7B 5Z7",
    "addr:housenumber":"299",
    "addr:postcode":"p7b 5z7",
    "addr:street":"Waverley St",
    "iso:country":"CA",
    "sg:address":"299 Waverley St",
    "sg:city":"Thunder Bay",
    "sg:classifiers":[
        {
            "category":"Retail",
            "subcategory":"Funeral Services",
            "type":"Services"
        }
    ],
    "sg:phone":"+1 807 344 1121",
    "sg:postcode":"P7B 5Z7",
    "sg:province":"ON",
    "sg:tags":[
        "director"
    ],
    "wof:name":"Everest of Thunder Bay",
    "wof:placetype":"venue"
},
  "geometry": {"coordinates":[-89.22416687010001,48.4363937378],"type":"Point"}
}