{
  "type": "Feature",
  "properties": {
    "iso:country":"CA",
    "sg:address":"741 Third St",
    "sg:city":"Nanaimo",
    "sg:classifiers":[
        {
            "category":"Recreation",
            "type":"Entertainment"
        }
    ],
    "sg:phone":"+1 250 756 5200",
    "sg:postcode":"V9R 7B2",
    "sg:province":"BC",
    "sg:tags":[
        "provincial",
        "parks",
        "swimming"
    ],
    "wof:name":"Nanaimo Aquatic Ctr",
    "wof:placetype":"venue"
},
  "geometry": {"coordinates":[-123.96408081,49.1625747681],"type":"Point"}
}