{
  "type": "Feature",
  "properties": {
    "addr:full":"Sainte-Therese-DE-Gaspe QC G0C 3B0",
    "addr:postcode":"g0c 3b0",
    "iso:country":"CA",
    "sg:city":"Sainte-Therese-DE-Gaspe",
    "sg:classifiers":[
        {
            "category":"Local Transit",
            "type":"Transportation"
        }
    ],
    "sg:phone":"+1 418 385 2017",
    "sg:postcode":"G0C 3B0",
    "sg:province":"QC",
    "sg:tags":[
        "bus",
        "line"
    ],
    "wof:name":"Couture Madeleine",
    "wof:placetype":"venue"
},
  "geometry": {"coordinates":[-64.43322000000001,48.454998],"type":"Point"}
}