{
  "type": "Feature",
  "properties": {
    "addr:full":"6630 Av Papineau Montreal QC H2G 2X2",
    "addr:housenumber":"6630",
    "addr:postcode":"h2g 2x2",
    "addr:street":"Av Papineau",
    "iso:country":"CA",
    "sg:address":"6630 Av Papineau",
    "sg:city":"Montreal",
    "sg:classifiers":[
        {
            "category":"Organizations",
            "subcategory":"Labor Organization",
            "type":"Services"
        }
    ],
    "sg:phone":"+1 514 728 6565",
    "sg:postcode":"H2G 2X2",
    "sg:province":"QC",
    "wof:name":"Retaq",
    "wof:placetype":"venue"
},
  "geometry": {"coordinates":[-73.5988998413,45.5440444946],"type":"Point"}
}