{
  "type": "Feature",
  "properties": {
    "addr:full":"278 Rte LA Vallee Memramcook NB E4K 3E3",
    "addr:housenumber":"278",
    "addr:postcode":"e4k 3e3",
    "addr:street":"Rte La Vallee",
    "iso:country":"CA",
    "sg:address":"278 Rte LA Vallee",
    "sg:city":"Memramcook",
    "sg:classifiers":[
        {
            "category":"Restaurant",
            "type":"Food & Drink"
        }
    ],
    "sg:phone":"+1 506 758 2885",
    "sg:postcode":"E4K 3E3",
    "sg:province":"NB",
    "wof:name":"China Place",
    "wof:placetype":"venue"
},
  "geometry": {"coordinates":[-64.586952,46.003716],"type":"Point"}
}