{
  "type": "Feature",
  "properties": {
    "addr:full":"2353 49E Rue Shawinigan QC G9N 8R3",
    "addr:housenumber":"2353",
    "addr:postcode":"g9n 8r3",
    "addr:street":"49E Rue",
    "iso:country":"CA",
    "sg:address":"2353 49E Rue",
    "sg:city":"Shawinigan",
    "sg:classifiers":[
        {
            "category":"Health Services",
            "subcategory":"Nursing And Care Facility",
            "type":"Services"
        }
    ],
    "sg:phone":"+1 819 539 6152",
    "sg:postcode":"G9N 8R3",
    "sg:province":"QC",
    "sg:tags":[
        "home",
        "rest"
    ],
    "wof:name":"Residence Les Chutes Inc",
    "wof:placetype":"venue"
},
  "geometry": {"coordinates":[-72.7345504761,46.5731239319],"type":"Point"}
}