{
  "type": "Feature",
  "properties": {
    "addr:full":"274 Main St S Alexandria ON K0C 1A0",
    "addr:housenumber":"274",
    "addr:postcode":"k0c 1a0",
    "addr:street":"Main St S",
    "iso:country":"CA",
    "sg:address":"274 Main St S",
    "sg:city":"Alexandria",
    "sg:classifiers":[
        {
            "category":"Professional",
            "subcategory":"Accounting & Tax Preparation",
            "type":"Services"
        }
    ],
    "sg:phone":"+1 613 525 5222",
    "sg:postcode":"K0C 1A0",
    "sg:province":"ON",
    "sg:tags":[
        "accountant"
    ],
    "wof:name":"Boyer, Guy",
    "wof:placetype":"venue"
},
  "geometry": {"coordinates":[-74.630653,45.303577],"type":"Point"}
}