{
  "type": "Feature",
  "properties": {
    "addr:full":"445 Northumberland St Fredericton NB E3B 3K3",
    "addr:housenumber":"445",
    "addr:postcode":"e3b 3k3",
    "addr:street":"Northumberland St",
    "iso:country":"CA",
    "sg:address":"445 Northumberland St",
    "sg:city":"Fredericton",
    "sg:classifiers":[
        {
            "category":"Professional",
            "subcategory":"Business Services",
            "type":"Services"
        }
    ],
    "sg:phone":"+1 506 455 9941",
    "sg:postcode":"E3B 3K3",
    "sg:province":"NB",
    "sg:tags":[
        "paralegal"
    ],
    "wof:name":"Ley Legal Support Svc",
    "wof:placetype":"venue"
},
  "geometry": {"coordinates":[-66.653938,45.957859],"type":"Point"}
}