{
  "type": "Feature",
  "properties": {
    "addr:full":"1521 Jasmine Cres Oakville ON L6H 3H2",
    "addr:housenumber":"1521",
    "addr:postcode":"l6h 3h2",
    "addr:street":"Jasmine Cres",
    "iso:country":"CA",
    "sg:address":"1521 Jasmine Cres",
    "sg:city":"Oakville",
    "sg:classifiers":[
        {
            "category":"Freight",
            "type":"Transportation"
        }
    ],
    "sg:phone":"+1 905 845 9961",
    "sg:postcode":"L6H 3H2",
    "sg:province":"ON",
    "sg:tags":[
        "courier"
    ],
    "wof:name":"Anmar Courier",
    "wof:placetype":"venue"
},
  "geometry": {"coordinates":[-79.695763,43.47961],"type":"Point"}
}