{
  "type": "Feature",
  "properties": {
    "addr:full":"1215 Meyerside Dr Mississauga ON L5T 1H3",
    "addr:housenumber":"1215",
    "addr:postcode":"l5t 1h3",
    "addr:street":"Meyerside Dr",
    "iso:country":"CA",
    "sg:address":"1215 Meyerside Dr",
    "sg:city":"Mississauga",
    "sg:classifiers":[
        {
            "category":"Professional",
            "subcategory":"Business Services",
            "type":"Services"
        }
    ],
    "sg:phone":"+1 905 564 2601",
    "sg:postcode":"L5T 1H3",
    "sg:province":"ON",
    "sg:tags":[
        "paper",
        "lamination"
    ],
    "wof:name":"Seal Craft Laminating",
    "wof:placetype":"venue"
},
  "geometry": {"coordinates":[-79.6599578857,43.6552963257],"type":"Point"}
}