{
  "type": "Feature",
  "properties": {
    "addr:full":"2281 Rue Saint-Hubert Jonquiere QC G7X 5N8",
    "addr:housenumber":"2281",
    "addr:postcode":"g7x 5n8",
    "addr:street":"Rue Saint-Hubert",
    "iso:country":"CA",
    "sg:address":"2281 Rue Saint-Hubert",
    "sg:city":"Jonquiere",
    "sg:classifiers":[
        {
            "category":"Health Services",
            "subcategory":"Medical Lab",
            "type":"Services"
        }
    ],
    "sg:phone":"+1 418 542 3551",
    "sg:postcode":"G7X 5N8",
    "sg:province":"QC",
    "wof:name":"Clinique-Denturologie Morency",
    "wof:placetype":"venue"
},
  "geometry": {"coordinates":[-71.245216,48.415844],"type":"Point"}
}