{
  "type": "Feature",
  "properties": {
    "addr:full":"2670 Rue DE Salaberry Montreal QC H3M 1L3",
    "addr:housenumber":"2670",
    "addr:postcode":"h3m 1l3",
    "addr:street":"Rue De Salaberry",
    "iso:country":"CA",
    "sg:address":"2670 Rue DE Salaberry",
    "sg:city":"Montreal",
    "sg:classifiers":[
        {
            "category":"Shopping",
            "subcategory":"Bicycles & Sporting Goods",
            "type":"Retail Goods"
        }
    ],
    "sg:phone":"+1 514 331 3340",
    "sg:postcode":"H3M 1L3",
    "sg:province":"QC",
    "wof:name":"Baron Sports",
    "wof:placetype":"venue"
},
  "geometry": {"coordinates":[-73.6995925903,45.5375862122],"type":"Point"}
}