{
  "type": "Feature",
  "properties": {
    "addr:full":"1031 Rue DE Nogent Boucherville QC J4B 2R4",
    "addr:housenumber":"1031",
    "addr:postcode":"j4b 2r4",
    "addr:street":"Rue De Nogent",
    "iso:country":"CA",
    "sg:address":"1031 Rue DE Nogent",
    "sg:city":"Boucherville",
    "sg:classifiers":[
        {
            "category":"Shopping",
            "subcategory":"Crafts & Fabrics",
            "type":"Retail Goods"
        }
    ],
    "sg:phone":"+1 450 449 7575",
    "sg:postcode":"J4B 2R4",
    "sg:province":"QC",
    "sg:tags":[
        "embroidery"
    ],
    "wof:name":"Broderies Raoul Vennat",
    "wof:placetype":"venue"
},
  "geometry": {"coordinates":[-73.4415969849,45.5831336975],"type":"Point"}
}