{
  "type": "Feature",
  "properties": {
    "addr:full":"26 Carlisle Rd Freelton ON L0R 1K0",
    "addr:housenumber":"26",
    "addr:postcode":"l0r 1k0",
    "addr:street":"Carlisle Rd",
    "iso:country":"CA",
    "sg:address":"26 Carlisle Rd",
    "sg:city":"Freelton",
    "sg:classifiers":[
        {
            "category":"Shopping",
            "type":"Retail Goods"
        }
    ],
    "sg:phone":"+1 905 689 1976",
    "sg:postcode":"L0R 1K0",
    "sg:province":"ON",
    "sg:tags":[
        "picture",
        "frame"
    ],
    "wof:name":"Corby Custom Framing",
    "wof:placetype":"venue"
},
  "geometry": {"coordinates":[-80.0391464233,43.4004554749],"type":"Point"}
}