{
  "type": "Feature",
  "properties": {
    "addr:full":"66 Government Rd W Kirkland Lake ON P2N 2E4",
    "addr:housenumber":"66",
    "addr:postcode":"p2n 2e4",
    "addr:street":"Rd W",
    "iso:country":"CA",
    "sg:address":"66 Government Rd W",
    "sg:city":"Kirkland Lake",
    "sg:classifiers":[
        {
            "category":"Sports & Exercise",
            "subcategory":"Bowling",
            "type":"Entertainment"
        }
    ],
    "sg:phone":"+1 705 567 7384",
    "sg:postcode":"P2N 2E4",
    "sg:province":"ON",
    "sg:tags":[
        "center"
    ],
    "wof:name":"Uptown Bowl",
    "wof:placetype":"venue"
},
  "geometry": {"coordinates":[-80.0375213623,48.1494102478],"type":"Point"}
}