{
  "type": "Feature",
  "properties": {
    "addr:full":"Victoria BC V8W 3M4",
    "addr:postcode":"v8w 3m4",
    "iso:country":"CA",
    "sg:city":"Victoria",
    "sg:classifiers":[
        {
            "category":"Government",
            "subcategory":"Office",
            "type":"Public Place"
        }
    ],
    "sg:phone":"+1 250 363 6910",
    "sg:postcode":"V8W 3M4",
    "sg:province":"BC",
    "wof:name":"Canada Federal Treaty Ngtns",
    "wof:placetype":"venue"
},
  "geometry": {"coordinates":[-123.367813,48.426094],"type":"Point"}
}