{
  "type": "Feature",
  "properties": {
    "addr:full":"8 Codeco Crt North York ON M3A 1A2",
    "addr:housenumber":"8",
    "addr:postcode":"m3a 1a2",
    "addr:street":"Codeco Crt",
    "iso:country":"CA",
    "sg:address":"8 Codeco Crt",
    "sg:city":"North York",
    "sg:classifiers":[
        {
            "category":"Organizations",
            "subcategory":"Religious Organization",
            "type":"Services"
        }
    ],
    "sg:phone":"+1 416 444 1716",
    "sg:postcode":"M3A 1A2",
    "sg:province":"ON",
    "wof:name":"Korean Philadelphia Church",
    "wof:placetype":"venue"
},
  "geometry": {"coordinates":[-79.3274612427,43.7359924316],"type":"Point"}
}