{
  "type": "Feature",
  "properties": {
    "iso:country":"CA",
    "sg:address":"355 Wellington St",
    "sg:city":"London",
    "sg:classifiers":[
        {
            "category":"Food & Beverages",
            "subcategory":"Groceries & Convenience Stores",
            "type":"Retail Goods"
        }
    ],
    "sg:phone":"+1 519 433 4315",
    "sg:postcode":"N6A 3N7",
    "sg:province":"ON",
    "sg:tags":[
        "product"
    ],
    "wof:name":"Bulk Barrel",
    "wof:placetype":"venue"
},
  "geometry": {"coordinates":[-81.2445678711,42.9831962585],"type":"Point"}
}