{
  "type": "Feature",
  "properties": {
    "addr:full":"St Jacobs ON N0B 2N0",
    "addr:postcode":"n0b 2n0",
    "addr:street":"St",
    "iso:country":"CA",
    "sg:city":"St Jacobs",
    "sg:classifiers":[
        {
            "category":"Professional",
            "subcategory":"Accounting & Tax Preparation",
            "type":"Services"
        }
    ],
    "sg:phone":"+1 519 664 2206",
    "sg:postcode":"N0B 2N0",
    "sg:province":"ON",
    "sg:tags":[
        "accountant"
    ],
    "wof:name":"Martin's Tax Svc",
    "wof:placetype":"venue"
},
  "geometry": {"coordinates":[-80.553237915,43.550403595],"type":"Point"}
}