{
  "type": "Feature",
  "properties": {
    "addr:full":"45 Hardy Ave Tillsonburg ON N4G 3W9",
    "addr:housenumber":"45",
    "addr:postcode":"n4g 3w9",
    "addr:street":"Hardy Ave",
    "iso:country":"CA",
    "sg:address":"45 Hardy Ave",
    "sg:city":"Tillsonburg",
    "sg:classifiers":[
        {
            "category":"Social Services",
            "type":"Services"
        }
    ],
    "sg:phone":"+1 519 842 6474",
    "sg:postcode":"N4G 3W9",
    "sg:province":"ON",
    "sg:tags":[
        "organization",
        "welfare"
    ],
    "wof:name":"Rotary Phone Check",
    "wof:placetype":"venue"
},
  "geometry": {"coordinates":[-80.7357788086,42.8714981079],"type":"Point"}
}