{
  "type": "Feature",
  "properties": {
    "addr:full":"847 Notre Dame Dr London ON N6J 3C3",
    "addr:housenumber":"847",
    "addr:postcode":"n6j 3c3",
    "addr:street":"Notre Dame Dr",
    "iso:country":"CA",
    "sg:address":"847 Notre Dame Dr",
    "sg:city":"London",
    "sg:classifiers":[
        {
            "category":"Shopping",
            "subcategory":"Bicycles & Sporting Goods",
            "type":"Retail Goods"
        }
    ],
    "sg:phone":"+1 519 685 5703",
    "sg:postcode":"N6J 3C3",
    "sg:province":"ON",
    "sg:tags":[
        "equipment",
        "arts",
        "supply",
        "martial"
    ],
    "wof:name":"London Southwestern Ontario",
    "wof:placetype":"venue"
},
  "geometry": {"coordinates":[-81.26731872560001,42.94323349],"type":"Point"}
}