{
  "type": "Feature",
  "properties": {
    "iso:country":"CA",
    "sg:address":"110 Eastview Trailer Crt",
    "sg:city":"Prince Albert",
    "sg:classifiers":[
        {
            "category":"Building & Trades",
            "subcategory":"Construction",
            "type":"Services"
        }
    ],
    "sg:phone":"+1 306 763 3369",
    "sg:postcode":"S6V 5P9",
    "sg:province":"SK",
    "sg:tags":[
        "painter"
    ],
    "wof:name":"Huser Painting",
    "wof:placetype":"venue"
},
  "geometry": {"coordinates":[-105.752876282,53.1994400024],"type":"Point"}
}