{
  "type": "Feature",
  "properties": {
    "addr:full":"198 Sandwich St N Amherstburg ON N9V 2V3",
    "addr:housenumber":"198",
    "addr:postcode":"n9v 2v3",
    "addr:street":"Sandwich St N",
    "iso:country":"CA",
    "sg:address":"198 Sandwich St N",
    "sg:city":"Amherstburg",
    "sg:classifiers":[
        {
            "category":"Recreation",
            "subcategory":"Marina",
            "type":"Entertainment"
        }
    ],
    "sg:phone":"+1 519 736 3663",
    "sg:postcode":"N9V 2V3",
    "sg:province":"ON",
    "wof:name":"Duff's Marina",
    "wof:placetype":"venue"
},
  "geometry": {"coordinates":[-83.111397,42.117039],"type":"Point"}
}