{
  "type": "Feature",
  "properties": {
    "addr:full":"7242 Colonel Talbot Rd London ON N6L 1H8",
    "addr:housenumber":"7242",
    "addr:postcode":"n6l 1h8",
    "addr:street":"Colonel Talbot Rd",
    "iso:country":"CA",
    "sg:address":"7242 Colonel Talbot Rd",
    "sg:city":"London",
    "sg:classifiers":[
        {
            "category":"Professional",
            "subcategory":"Engineering",
            "type":"Services"
        }
    ],
    "sg:phone":"+1 519 652 5047",
    "sg:postcode":"N6L 1H8",
    "sg:province":"ON",
    "sg:tags":[
        "engineer"
    ],
    "wof:name":"Vanderwesten & Rutherford Ltd",
    "wof:placetype":"venue"
},
  "geometry": {"coordinates":[-81.2682342529,42.8369636536],"type":"Point"}
}