{
  "type": "Feature",
  "properties": {
    "addr:full":"1511 Ross Ave E Regina SK S4N 7E5",
    "addr:housenumber":"1511",
    "addr:postcode":"s4n 7e5",
    "addr:street":"Ross Ave E",
    "iso:country":"CA",
    "sg:address":"1511 Ross Ave E",
    "sg:city":"Regina",
    "sg:phone":"+1 306 721 2222",
    "sg:postcode":"S4N 7E5",
    "sg:province":"SK",
    "sg:tags":[
        "oil"
    ],
    "wof:name":"Nistor's Farm Svc",
    "wof:placetype":"venue"
},
  "geometry": {"coordinates":[-104.56483459499999,50.4653778076],"type":"Point"}
}