{
  "type": "Feature",
  "properties": {
    "addr:full":"2379 Ogilvie Rd Gloucester ON K1J 7N4",
    "addr:housenumber":"2379",
    "addr:postcode":"k1j 7n4",
    "addr:street":"Ogilvie Rd",
    "iso:country":"CA",
    "sg:address":"2379 Ogilvie Rd",
    "sg:city":"Gloucester",
    "sg:classifiers":[
        {
            "category":"Social Services",
            "subcategory":"Child Care",
            "type":"Services"
        }
    ],
    "sg:phone":"+1 613 741 3422",
    "sg:postcode":"K1J 7N4",
    "sg:province":"ON",
    "wof:name":"Beacon Learning Ctr",
    "wof:placetype":"venue"
},
  "geometry": {"coordinates":[-75.598991394,45.4557113647],"type":"Point"}
}