{
  "type": "Feature",
  "properties": {
    "addr:full":"1769 Chiefswood Rd Ohsweken ON N0A 1M0",
    "addr:housenumber":"1769",
    "addr:postcode":"n0a 1m0",
    "addr:street":"Chiefswood Rd",
    "iso:country":"CA",
    "sg:address":"1769 Chiefswood Rd",
    "sg:city":"Ohsweken",
    "sg:classifiers":[
        {
            "category":"Shopping",
            "subcategory":"Pharmacy",
            "type":"Retail Goods"
        }
    ],
    "sg:phone":"+1 519 445 4471",
    "sg:postcode":"N0A 1M0",
    "sg:province":"ON",
    "wof:name":"Ohsweken Pharmasave",
    "wof:placetype":"venue"
},
  "geometry": {"coordinates":[-80.115219,43.073338],"type":"Point"}
}