{
  "type": "Feature",
  "properties": {
    "addr:full":"115 10th St NE Portage LA Prairie MB R1N 1B6",
    "addr:housenumber":"115",
    "addr:postcode":"r1n 1b6",
    "addr:street":"10Th St Ne",
    "iso:country":"CA",
    "sg:address":"115 10th St NE",
    "sg:city":"Portage LA Prairie",
    "sg:classifiers":[
        {
            "category":"Manufacturing",
            "subcategory":"Tools & Machinery",
            "type":"Manufacturing & Wholesale Goods"
        }
    ],
    "sg:phone":"+1 204 857 3115",
    "sg:postcode":"R1N 1B6",
    "sg:province":"MB",
    "sg:tags":[
        "machine",
        "shop"
    ],
    "wof:name":"Gray's Welding Ltd",
    "wof:placetype":"venue"
},
  "geometry": {"coordinates":[-98.2763214111,49.9749641418],"type":"Point"}
}