{
  "type": "Feature",
  "properties": {
    "addr:full":"1334 King St E Kitchener ON N2G 2N7",
    "addr:housenumber":"1334",
    "addr:postcode":"n2g 2n7",
    "addr:street":"King St E",
    "iso:country":"CA",
    "sg:address":"1334 King St E",
    "sg:city":"Kitchener",
    "sg:classifiers":[
        {
            "category":"Wholesale",
            "subcategory":"Office Equipment",
            "type":"Manufacturing & Wholesale Goods"
        }
    ],
    "sg:phone":"+1 519 744 2797",
    "sg:postcode":"N2G 2N7",
    "sg:province":"ON",
    "sg:tags":[
        "machine",
        "computer",
        "duplicating",
        "copying",
        "dealer"
    ],
    "wof:name":"Centra Office Products Group",
    "wof:placetype":"venue"
},
  "geometry": {"coordinates":[-80.4675750732,43.4403419495],"type":"Point"}
}