{
  "type": "Feature",
  "properties": {
    "addr:full":"1328 24th St Didsbury AB T0M 0W0",
    "addr:housenumber":"1328",
    "addr:postcode":"t0m 0w0",
    "addr:street":"24Th St",
    "iso:country":"CA",
    "sg:address":"1328 24th St",
    "sg:city":"Didsbury",
    "sg:classifiers":[
        {
            "category":"Building & Trades",
            "subcategory":"Construction",
            "type":"Services"
        }
    ],
    "sg:phone":"+1 403 335 3355",
    "sg:postcode":"T0M 0W0",
    "sg:province":"AB",
    "sg:tags":[
        "glass"
    ],
    "wof:name":"Crosstown Glass Svc",
    "wof:placetype":"venue"
},
  "geometry": {"coordinates":[-114.14527099999999,51.654972],"type":"Point"}
}