{
  "type": "Feature",
  "properties": {
    "addr:full":"Regina SK S4P 3J8",
    "addr:postcode":"s4p 3j8",
    "iso:country":"CA",
    "sg:city":"Regina",
    "sg:classifiers":[
        {
            "category":"Building & Trades",
            "subcategory":"Construction",
            "type":"Services"
        }
    ],
    "sg:phone":"+1 306 545 5050",
    "sg:postcode":"S4P 3J8",
    "sg:province":"SK",
    "sg:tags":[
        "pile",
        "driving"
    ],
    "wof:name":"North American Caission Ltd",
    "wof:placetype":"venue"
},
  "geometry": {"coordinates":[-104.59517700000001,50.448013],"type":"Point"}
}