{
  "type": "Feature",
  "properties": {
    "iso:country":"CA",
    "sg:city":"Vilna",
    "sg:classifiers":[
        {
            "category":"Restaurant",
            "type":"Food & Drink"
        }
    ],
    "sg:phone":"+1 780 636 3961",
    "sg:postcode":"T0A 3L0",
    "sg:province":"AB",
    "wof:name":"Family Corner Drive-In",
    "wof:placetype":"venue"
},
  "geometry": {"coordinates":[-111.919090271,54.1140289307],"type":"Point"}
}