{
  "type": "Feature",
  "properties": {
    "addr:full":"311 Woodvale Road West NW Edmonton AB T6L 3Z7",
    "addr:housenumber":"311",
    "addr:postcode":"t6l 3z7",
    "addr:street":"Woodvale Road West Nw",
    "iso:country":"CA",
    "sg:address":"311 Woodvale Road West NW",
    "sg:city":"Edmonton",
    "sg:classifiers":[
        {
            "category":"Restaurant",
            "type":"Food & Drink"
        }
    ],
    "sg:phone":"+1 780 462 0468",
    "sg:postcode":"T6L 3Z7",
    "sg:province":"AB",
    "sg:tags":[
        "pizza"
    ],
    "wof:name":"Woodvale Pizza & Steak",
    "wof:placetype":"venue"
},
  "geometry": {"coordinates":[-113.43130499999999,53.467644],"type":"Point"}
}