{
  "type": "Feature",
  "properties": {
    "iso:country":"CA",
    "sg:address":"1893 Bonhill Rd",
    "sg:city":"Mississauga",
    "sg:classifiers":[
        {
            "category":"Manufacturing",
            "subcategory":"Metals",
            "type":"Manufacturing & Wholesale Goods"
        }
    ],
    "sg:phone":"+1 905 564 9333",
    "sg:postcode":"L5T 1C1",
    "sg:province":"ON",
    "sg:tags":[
        "coating"
    ],
    "wof:name":"Briken Coatings",
    "wof:placetype":"venue"
},
  "geometry": {"coordinates":[-79.6476898193,43.6698951721],"type":"Point"}
}