{
  "type": "Feature",
  "properties": {
    "iso:country":"CA",
    "sg:address":"SE 14 61 4 W 4",
    "sg:city":"Ardmore",
    "sg:classifiers":[
        {
            "category":"Wholesale",
            "subcategory":"Groceries",
            "type":"Manufacturing & Wholesale Goods"
        }
    ],
    "sg:phone":"+1 780 826 6013",
    "sg:postcode":"T0A 0B0",
    "sg:province":"AB",
    "sg:tags":[
        "honey"
    ],
    "wof:name":"T 'N' T Apiaries",
    "wof:placetype":"venue"
},
  "geometry": {"coordinates":[-110.480232239,54.3330192566],"type":"Point"}
}