{
  "type": "Feature",
  "properties": {
    "addr:full":"13731 Mayfield Pl Richmond BC V6V 2G9",
    "addr:housenumber":"13731",
    "addr:postcode":"v6v 2g9",
    "addr:street":"Mayfield Pl",
    "iso:country":"CA",
    "sg:address":"13731 Mayfield Pl",
    "sg:city":"Richmond",
    "sg:classifiers":[
        {
            "category":"Manufacturing",
            "subcategory":"Chemicals & Compounds",
            "type":"Manufacturing & Wholesale Goods"
        }
    ],
    "sg:phone":"+1 604 273 5265",
    "sg:postcode":"V6V 2G9",
    "sg:province":"BC",
    "wof:name":"Xypex Chemical Corp",
    "wof:placetype":"venue"
},
  "geometry": {"coordinates":[-123.072441,49.181908],"type":"Point"}
}