{
  "type": "Feature",
  "properties": {
    "iso:country":"CA",
    "sg:address":"443 Rue Principale",
    "sg:city":"Sainte-Rose-DE-Watford",
    "sg:classifiers":[
        {
            "category":"Retail",
            "subcategory":"Auto Repair",
            "type":"Services"
        }
    ],
    "sg:phone":"+1 418 267 5492",
    "sg:postcode":"G0R 4G0",
    "sg:province":"QC",
    "sg:tags":[
        "repairing",
        "automobile"
    ],
    "wof:name":"Garage Jacques Bedard",
    "wof:placetype":"venue"
},
  "geometry": {"coordinates":[-70.4302902222,46.3181533813],"type":"Point"}
}