{
  "type": "Feature",
  "properties": {
    "addr:full":"520 36E Av Saint-Jerome QC J7Z 6A5",
    "addr:housenumber":"520",
    "addr:postcode":"j7z 6a5",
    "addr:street":"36E Av Saint-Jerome",
    "iso:country":"CA",
    "sg:address":"520 36E Av",
    "sg:city":"Saint-Jerome",
    "sg:classifiers":[
        {
            "category":"Food & Beverages",
            "subcategory":"Groceries & Convenience Stores",
            "type":"Retail Goods"
        }
    ],
    "sg:phone":"+1 450 438 5529",
    "sg:postcode":"J7Z 6A5",
    "sg:province":"QC",
    "sg:tags":[
        "grocer"
    ],
    "wof:name":"Depanneur Couche-Tard",
    "wof:placetype":"venue"
},
  "geometry": {"coordinates":[-73.9808578491,45.7750473022],"type":"Point"}
}