{
  "type": "Feature",
  "properties": {
    "addr:full":"338 King St W Oshawa ON L1J 2J9",
    "addr:housenumber":"338",
    "addr:postcode":"l1j 2j9",
    "addr:street":"King St W",
    "iso:country":"CA",
    "sg:address":"338 King St W",
    "sg:city":"Oshawa",
    "sg:classifiers":[
        {
            "category":"Restaurant",
            "type":"Food & Drink"
        }
    ],
    "sg:phone":"+1 905 571 2334",
    "sg:postcode":"L1J 2J9",
    "sg:province":"ON",
    "wof:name":"Burger King",
    "wof:placetype":"venue"
},
  "geometry": {"coordinates":[-78.8758926392,43.8949012756],"type":"Point"}
}