{
  "type": "Feature",
  "properties": {
    "addr:full":"24 Emerick Ave Fort Erie ON L2A 2W3",
    "addr:housenumber":"24",
    "addr:postcode":"l2a 2w3",
    "addr:street":"Emerick Ave",
    "iso:country":"CA",
    "sg:address":"24 Emerick Ave",
    "sg:city":"Fort Erie",
    "sg:classifiers":[
        {
            "category":"Health Services",
            "subcategory":"Medical Lab",
            "type":"Services"
        }
    ],
    "sg:phone":"+1 905 991 0684",
    "sg:postcode":"L2A 2W3",
    "sg:province":"ON",
    "sg:tags":[
        "laboratory"
    ],
    "wof:name":"Smile Science",
    "wof:placetype":"venue"
},
  "geometry": {"coordinates":[-78.917412,42.933151],"type":"Point"}
}