{
  "type": "Feature",
  "properties": {
    "addr:full":"616 17 Ave SW Calgary AB T2S 0B4",
    "addr:postcode":"t2s 0b4",
    "addr:street":"616 17 Ave Sw",
    "iso:country":"CA",
    "sg:address":"616 17 Ave SW",
    "sg:city":"Calgary",
    "sg:classifiers":[
        {
            "category":"Shopping",
            "subcategory":"Bicycles & Sporting Goods",
            "type":"Retail Goods"
        }
    ],
    "sg:phone":"+1 403 270 7669",
    "sg:postcode":"T2S 0B4",
    "sg:province":"AB",
    "sg:tags":[
        "snowboard"
    ],
    "wof:name":"Mission Skateboards & Snwbrds",
    "wof:placetype":"venue"
},
  "geometry": {"coordinates":[-114.075256348,51.0380134583],"type":"Point"}
}