{
  "type": "Feature",
  "properties": {
    "addr:full":"Lac LA Biche AB T0A 2C0",
    "addr:postcode":"t0a 2c0",
    "iso:country":"CA",
    "sg:city":"Lac LA Biche",
    "sg:classifiers":[
        {
            "category":"Mining & Drilling",
            "type":"Manufacturing & Wholesale Goods"
        }
    ],
    "sg:phone":"+1 780 623 3393",
    "sg:postcode":"T0A 2C0",
    "sg:province":"AB",
    "sg:tags":[
        "field",
        "oil"
    ],
    "wof:name":"Ken Mc Donald Contracting Ltd",
    "wof:placetype":"venue"
},
  "geometry": {"coordinates":[-111.97445678699999,54.77110672],"type":"Point"}
}