{
  "type": "Feature",
  "properties": {
    "addr:full":"510 Patricia St Jasper AB T0E 1E0",
    "addr:housenumber":"510",
    "addr:postcode":"t0e 1e0",
    "addr:street":"Patricia St",
    "iso:country":"CA",
    "sg:address":"510 Patricia St",
    "sg:city":"Jasper",
    "sg:classifiers":[
        {
            "category":"Travel",
            "subcategory":"Hotels & Motels",
            "type":"Entertainment"
        }
    ],
    "sg:phone":"+1 780 852 3386",
    "sg:postcode":"T0E 1E0",
    "sg:province":"AB",
    "wof:name":"Athabasca Hotel",
    "wof:placetype":"venue"
},
  "geometry": {"coordinates":[-118.081261,52.877232],"type":"Point"}
}