{
  "type": "Feature",
  "properties": {
    "addr:full":"Loretteville QC G2A 1G5",
    "addr:postcode":"g2a 1g5",
    "iso:country":"CA",
    "sg:city":"Loretteville",
    "sg:classifiers":[
        {
            "category":"Health Services",
            "subcategory":"Nursing And Care Facility",
            "type":"Services"
        }
    ],
    "sg:phone":"+1 418 845 4244",
    "sg:postcode":"G2A 1G5",
    "sg:province":"QC",
    "sg:tags":[
        "home",
        "retirement",
        "community"
    ],
    "wof:name":"Villa LA Source",
    "wof:placetype":"venue"
},
  "geometry": {"coordinates":[-71.3763504028,46.8550567627],"type":"Point"}
}