{
  "type": "Feature",
  "properties": {
    "addr:full":"2 Gower St East York ON M4B 1E2",
    "addr:housenumber":"2",
    "addr:postcode":"m4b 1e2",
    "addr:street":"Gower St",
    "iso:country":"CA",
    "sg:address":"2 Gower St",
    "sg:city":"East York",
    "sg:classifiers":[
        {
            "category":"Social Services",
            "type":"Services"
        }
    ],
    "sg:phone":"+1 416 752 0101",
    "sg:postcode":"M4B 1E2",
    "sg:province":"ON",
    "sg:tags":[
        "organization",
        "welfare"
    ],
    "wof:name":"Harmony Hall Ctr For Seniors",
    "wof:placetype":"venue"
},
  "geometry": {"coordinates":[-79.298698,43.702019],"type":"Point"}
}