{
  "type": "Feature",
  "properties": {
    "addr:full":"791 16th Ave W Vancouver BC V5Z 1S8",
    "addr:housenumber":"791",
    "addr:postcode":"v5z 1s8",
    "addr:street":"16Th Ave W",
    "iso:country":"CA",
    "sg:address":"791 16th Ave W",
    "sg:city":"Vancouver",
    "sg:classifiers":[
        {
            "category":"Personal",
            "subcategory":"Beauty Salon",
            "type":"Services"
        }
    ],
    "sg:phone":"+1 604 873 5641",
    "sg:postcode":"V5Z 1S8",
    "sg:province":"BC",
    "wof:name":"Caron For Your Hair",
    "wof:placetype":"venue"
},
  "geometry": {"coordinates":[-123.121582,49.257229],"type":"Point"}
}