{
  "type": "Feature",
  "properties": {
    "addr:full":"7787 Hudson St Vancouver BC V6P 4L7",
    "addr:housenumber":"7787",
    "addr:postcode":"v6p 4l7",
    "addr:street":"Hudson St",
    "iso:country":"CA",
    "sg:address":"7787 Hudson St",
    "sg:city":"Vancouver",
    "sg:classifiers":[
        {
            "category":"Professional",
            "subcategory":"Engineering",
            "type":"Services"
        }
    ],
    "sg:phone":"+1 604 266 2818",
    "sg:postcode":"V6P 4L7",
    "sg:province":"BC",
    "sg:tags":[
        "engineer"
    ],
    "wof:name":"R A Spence Engineering Inc",
    "wof:placetype":"venue"
},
  "geometry": {"coordinates":[-123.13413199999999,49.215137],"type":"Point"}
}