{
  "type": "Feature",
  "properties": {
    "addr:full":"4040 7 St SE Calgary AB T2G 2Y8",
    "addr:housenumber":"4040 7",
    "addr:postcode":"t2g 2y8",
    "addr:street":"St Se",
    "iso:country":"CA",
    "sg:address":"4040 7 St SE",
    "sg:city":"Calgary",
    "sg:classifiers":[
        {
            "category":"Building & Trades",
            "subcategory":"Construction",
            "type":"Services"
        }
    ],
    "sg:phone":"+1 403 234 7274",
    "sg:postcode":"T2G 2Y8",
    "sg:province":"AB",
    "sg:tags":[
        "tile",
        "dealer"
    ],
    "wof:name":"Stone Tile West Ltd",
    "wof:placetype":"venue"
},
  "geometry": {"coordinates":[-114.04568500000001,51.018528],"type":"Point"}
}