{
  "type": "Feature",
  "properties": {
    "addr:full":"Saint-Georges QC G5Y 5P4",
    "addr:postcode":"g5y 5p4",
    "iso:country":"CA",
    "sg:city":"Saint-Georges",
    "sg:classifiers":[
        {
            "category":"Organizations",
            "subcategory":"Labor Organization",
            "type":"Services"
        }
    ],
    "sg:phone":"+1 418 227 3347",
    "sg:postcode":"G5Y 5P4",
    "sg:province":"QC",
    "wof:name":"Conseil Central DE Quebec",
    "wof:placetype":"venue"
},
  "geometry": {"coordinates":[-70.694298,46.130489],"type":"Point"}
}