{
  "type": "Feature",
  "properties": {
    "addr:full":"Woodbridge ON L4L 8N1",
    "addr:postcode":"l4l 8n1",
    "iso:country":"CA",
    "sg:city":"Woodbridge",
    "sg:classifiers":[
        {
            "category":"Bars & Pubs",
            "type":"Food & Drink"
        }
    ],
    "sg:phone":"+1 905 850 2546",
    "sg:postcode":"L4L 8N1",
    "sg:province":"ON",
    "wof:name":"Kappa Sports Bar & Grill",
    "wof:placetype":"venue"
},
  "geometry": {"coordinates":[-79.612297,43.771214],"type":"Point"}
}