{
  "type": "Feature",
  "properties": {
    "addr:full":"1357 Lonsdale Ave North Vancouver BC V7M 2H7",
    "addr:housenumber":"1357",
    "addr:postcode":"v7m 2h7",
    "addr:street":"Lonsdale Ave",
    "iso:country":"CA",
    "sg:address":"1357 Lonsdale Ave",
    "sg:city":"North Vancouver",
    "sg:classifiers":[
        {
            "category":"Banks & Credit Unions",
            "subcategory":"Bank",
            "type":"Services"
        }
    ],
    "sg:phone":"+1 604 981 7500",
    "sg:postcode":"V7M 2H7",
    "sg:province":"BC",
    "wof:name":"Scotia Bank & Trust",
    "wof:placetype":"venue"
},
  "geometry": {"coordinates":[-123.07257842999999,49.3205833435],"type":"Point"}
}