{
  "type": "Feature",
  "properties": {
    "addr:full":"1605 29th St W Saskatoon SK S7L 0N6",
    "addr:housenumber":"1605",
    "addr:postcode":"s7l 0n6",
    "addr:street":"29Th St W",
    "iso:country":"CA",
    "sg:address":"1605 29th St W",
    "sg:city":"Saskatoon",
    "sg:classifiers":[
        {
            "category":"Restaurant",
            "type":"Food & Drink"
        }
    ],
    "sg:phone":"+1 306 384 6155",
    "sg:postcode":"S7L 0N6",
    "sg:province":"SK",
    "wof:name":"Mount Royal Restaurant",
    "wof:placetype":"venue"
},
  "geometry": {"coordinates":[-106.694389,52.136826],"type":"Point"}
}