{
  "type": "Feature",
  "properties": {
    "addr:full":"1364 Regent Ave W Winnipeg MB R2C 3A8",
    "addr:housenumber":"1364",
    "addr:postcode":"r2c 3a8",
    "addr:street":"Regent Ave W",
    "iso:country":"CA",
    "sg:address":"1364 Regent Ave W",
    "sg:city":"Winnipeg",
    "sg:classifiers":[
        {
            "category":"Autos & Motor Vehicles",
            "subcategory":"Automobile Sales",
            "type":"Retail Goods"
        }
    ],
    "sg:phone":"+1 204 661 5110",
    "sg:postcode":"R2C 3A8",
    "sg:province":"MB",
    "sg:tags":[
        "car",
        "dealer"
    ],
    "wof:name":"Saturn Isuzu of Regent",
    "wof:placetype":"venue"
},
  "geometry": {"coordinates":[-97.04129,49.895096],"type":"Point"}
}