{
  "type": "Feature",
  "properties": {
    "addr:full":"105 1st Ave E Kindersley SK S0L 1S0",
    "addr:housenumber":"105",
    "addr:postcode":"s0l 1s0",
    "addr:street":"1St Ave E Kindersley",
    "iso:country":"CA",
    "sg:address":"105 1st Ave E",
    "sg:city":"Kindersley",
    "sg:classifiers":[
        {
            "category":"Restaurant",
            "type":"Food & Drink"
        }
    ],
    "sg:phone":"+1 306 463 2599",
    "sg:postcode":"S0L 1S0",
    "sg:province":"SK",
    "wof:name":"Silver Dragon",
    "wof:placetype":"venue"
},
  "geometry": {"coordinates":[-109.150711,51.468269],"type":"Point"}
}