{
  "type": "Feature",
  "properties": {
    "addr:full":"Calgary AB T2E 6R7",
    "addr:postcode":"t2e 6r7",
    "iso:country":"CA",
    "sg:city":"Calgary",
    "sg:classifiers":[
        {
            "category":"Building & Trades",
            "subcategory":"Construction",
            "type":"Services"
        }
    ],
    "sg:phone":"+1 403 250 1869",
    "sg:postcode":"T2E 6R7",
    "sg:province":"AB",
    "sg:tags":[
        "general",
        "contractor"
    ],
    "wof:name":"Dyce Consulting",
    "wof:placetype":"venue"
},
  "geometry": {"coordinates":[-114.009811,51.088207],"type":"Point"}
}