{
  "type": "Feature",
  "properties": {
    "iso:country":"CA",
    "sg:city":"Calgary",
    "sg:classifiers":[
        {
            "category":"Shopping",
            "subcategory":"Tobacco",
            "type":"Retail Goods"
        }
    ],
    "sg:phone":"+1 403 291 3772",
    "sg:postcode":"T2E 6Z8",
    "sg:province":"AB",
    "sg:tags":[
        "cigarette",
        "cigar",
        "dealer"
    ],
    "wof:name":"United Cigar Store",
    "wof:placetype":"venue"
},
  "geometry": {"coordinates":[-114.010597,51.134121],"type":"Point"}
}