{
  "type": "Feature",
  "properties": {
    "addr:full":"Saskatoon SK S7K 5W1",
    "addr:postcode":"s7k 5w1",
    "iso:country":"CA",
    "sg:city":"Saskatoon",
    "sg:classifiers":[
        {
            "category":"Health Services",
            "subcategory":"Optometrist",
            "type":"Services"
        }
    ],
    "sg:phone":"+1 306 242 4186",
    "sg:postcode":"S7K 5W1",
    "sg:province":"SK",
    "wof:name":"Pinehouse Optometric Group",
    "wof:placetype":"venue"
},
  "geometry": {"coordinates":[-106.63223266599999,52.1692314148],"type":"Point"}
}