{
  "type": "Feature",
  "properties": {
    "addr:full":"Nanaimo BC V9T 4T7",
    "addr:postcode":"v9t 4t7",
    "iso:country":"CA",
    "sg:city":"Nanaimo",
    "sg:classifiers":[
        {
            "category":"Wholesale",
            "subcategory":"Groceries",
            "type":"Manufacturing & Wholesale Goods"
        }
    ],
    "sg:phone":"+1 250 390 1560",
    "sg:postcode":"V9T 4T7",
    "sg:province":"BC",
    "sg:tags":[
        "cocoa",
        "chocolate"
    ],
    "wof:name":"Bernard Callebaut Chocolaterie",
    "wof:placetype":"venue"
},
  "geometry": {"coordinates":[-124.046379,49.236401],"type":"Point"}
}