{
  "type": "Feature",
  "properties": {
    "iso:country":"CA",
    "sg:address":"98 Rue Brunelle",
    "sg:city":"Cap-DE-LA-Madeleine",
    "sg:classifiers":[
        {
            "category":"Food & Beverages",
            "subcategory":"Groceries & Convenience Stores",
            "type":"Retail Goods"
        }
    ],
    "sg:phone":"+1 819 374 5189",
    "sg:postcode":"G8T 6A2",
    "sg:province":"QC",
    "sg:tags":[
        "grocer"
    ],
    "wof:name":"Depanneur C Pitre Enr",
    "wof:placetype":"venue"
},
  "geometry": {"coordinates":[-72.5112991333,46.3630714417],"type":"Point"}
}