{
  "type": "Feature",
  "properties": {
    "addr:full":"3371 Rue Griffith Saint-Laurent QC H4T 1W5",
    "addr:housenumber":"3371",
    "addr:postcode":"h4t 1w5",
    "addr:street":"Rue Griffith",
    "iso:country":"CA",
    "sg:address":"3371 Rue Griffith",
    "sg:city":"Saint-Laurent",
    "sg:classifiers":[
        {
            "category":"Shopping",
            "subcategory":"Computers & Home Electronics",
            "type":"Retail Goods"
        }
    ],
    "sg:phone":"+1 514 739 1238",
    "sg:postcode":"H4T 1W5",
    "sg:province":"QC",
    "sg:tags":[
        "equipment",
        "dealer"
    ],
    "wof:name":"Frontier Info-Max",
    "wof:placetype":"venue"
},
  "geometry": {"coordinates":[-73.693878,45.488991],"type":"Point"}
}