{
  "type": "Feature",
  "properties": {
    "iso:country":"CA",
    "sg:address":"404 Ch Des Patriotes",
    "sg:city":"Saint-Mathias-Sur-Richelieu",
    "sg:classifiers":[
        {
            "category":"Retail",
            "subcategory":"Auto Repair",
            "type":"Services"
        }
    ],
    "sg:phone":"+1 450 658 9438",
    "sg:postcode":"J3L 6C4",
    "sg:province":"QC",
    "sg:tags":[
        "automobile",
        "electric"
    ],
    "wof:name":"Jacques Dulac Auto Electrique",
    "wof:placetype":"venue"
},
  "geometry": {"coordinates":[-73.2640380859,45.4854011536],"type":"Point"}
}