{
  "type": "Feature",
  "properties": {
    "addr:full":"Sainte-Julie QC J3E 1W1",
    "addr:postcode":"j3e 1w1",
    "iso:country":"CA",
    "sg:city":"Sainte-Julie",
    "sg:classifiers":[
        {
            "category":"Retail",
            "subcategory":"Animal Services",
            "type":"Services"
        }
    ],
    "sg:phone":"+1 450 922 2557",
    "sg:postcode":"J3E 1W1",
    "sg:province":"QC",
    "sg:tags":[
        "pet",
        "grooming",
        "washing"
    ],
    "wof:name":"Tropicazoo Saint-Julie",
    "wof:placetype":"venue"
},
  "geometry": {"coordinates":[-73.347374,45.588169],"type":"Point"}
}