{
  "type": "Feature",
  "properties": {
    "addr:full":"1021 Coxwell Ave East York ON M4C 3G4",
    "addr:housenumber":"1021",
    "addr:postcode":"m4c 3g4",
    "addr:street":"Coxwell Ave",
    "iso:country":"CA",
    "sg:address":"1021 Coxwell Ave",
    "sg:city":"East York",
    "sg:classifiers":[
        {
            "category":"Shopping",
            "subcategory":"Discount & Variety Stores",
            "type":"Retail Goods"
        }
    ],
    "sg:phone":"+1 416 422 3121",
    "sg:postcode":"M4C 3G4",
    "sg:province":"ON",
    "wof:name":"Yang's Variety Store",
    "wof:placetype":"venue"
},
  "geometry": {"coordinates":[-79.3289031982,43.6967849731],"type":"Point"}
}