{
  "type": "Feature",
  "properties": {
    "addr:full":"9445 Airport Rd Brampton ON L6S 4J3",
    "addr:housenumber":"9445",
    "addr:postcode":"l6s 4j3",
    "addr:street":"Airport Rd",
    "iso:country":"CA",
    "sg:address":"9445 Airport Rd",
    "sg:city":"Brampton",
    "sg:classifiers":[
        {
            "category":"Manufacturing",
            "subcategory":"Aerospace",
            "type":"Manufacturing & Wholesale Goods"
        }
    ],
    "sg:phone":"+1 905 790 2800",
    "sg:postcode":"L6S 4J3",
    "sg:province":"ON",
    "sg:tags":[
        "component",
        "system",
        "space"
    ],
    "wof:name":"Mac Donald Dettwiler Space",
    "wof:placetype":"venue"
},
  "geometry": {"coordinates":[-79.7063903809,43.7517471313],"type":"Point"}
}