{
  "type": "Feature",
  "properties": {
    "addr:full":"1939 Weston Rd York ON M9N 1W8",
    "addr:housenumber":"1939",
    "addr:postcode":"m9n 1w8",
    "addr:street":"Weston Rd",
    "iso:country":"CA",
    "sg:address":"1939 Weston Rd",
    "sg:city":"York",
    "sg:classifiers":[
        {
            "category":"Banks & Credit Unions",
            "subcategory":"Bank",
            "type":"Services"
        }
    ],
    "sg:phone":"+1 416 249 3387",
    "sg:postcode":"M9N 1W8",
    "sg:province":"ON",
    "wof:name":"Bank of Montreal",
    "wof:placetype":"venue"
},
  "geometry": {"coordinates":[-79.5179138184,43.7007751465],"type":"Point"}
}