{
  "type": "Feature",
  "properties": {
    "addr:full":"11 Lakeshore Blvd N Sauble Beach ON N0H 2G0",
    "addr:housenumber":"11",
    "addr:postcode":"n0h 2g0",
    "addr:street":"Lakeshore Blvd N",
    "iso:country":"CA",
    "sg:address":"11 Lakeshore Blvd N",
    "sg:city":"Sauble Beach",
    "sg:classifiers":[
        {
            "category":"Shopping",
            "subcategory":"Clothing, Apparel, & Fashions",
            "type":"Retail Goods"
        }
    ],
    "sg:phone":"+1 519 422 3787",
    "sg:postcode":"N0H 2G0",
    "sg:province":"ON",
    "sg:tags":[
        "accessory"
    ],
    "wof:name":"Island Beach CO",
    "wof:placetype":"venue"
},
  "geometry": {"coordinates":[-81.27024841310001,44.6296424866],"type":"Point"}
}