{
  "type": "Feature",
  "properties": {
    "iso:country":"CA",
    "sg:address":"146 Rose Glen Rd",
    "sg:city":"Port Hope",
    "sg:classifiers":[
        {
            "category":"Retail",
            "subcategory":"Veterinary Services",
            "type":"Services"
        }
    ],
    "sg:phone":"+1 905 885 8151",
    "sg:postcode":"L1A 3V6",
    "sg:province":"ON",
    "sg:tags":[
        "veterinarian"
    ],
    "wof:name":"Ganaraska Animal Clinic",
    "wof:placetype":"venue"
},
  "geometry": {"coordinates":[-78.2855224609,43.9686355591],"type":"Point"}
}