{
  "type": "Feature",
  "properties": {
    "addr:full":"216 Chitek Lake Dr Chitek Lake SK S0J 0L0",
    "addr:housenumber":"216",
    "addr:postcode":"s0j 0l0",
    "addr:street":"Chitek Lake Dr Chitek",
    "iso:country":"CA",
    "sg:address":"216 Chitek Lake Dr",
    "sg:city":"Chitek Lake",
    "sg:classifiers":[
        {
            "category":"Shopping",
            "subcategory":"Discount & Variety Stores",
            "type":"Retail Goods"
        }
    ],
    "sg:phone":"+1 306 984 2324",
    "sg:postcode":"S0J 0L0",
    "sg:province":"SK",
    "sg:tags":[
        "merchandise",
        "general"
    ],
    "wof:name":"Surprenant's General Store",
    "wof:placetype":"venue"
},
  "geometry": {"coordinates":[-107.732224,53.752579],"type":"Point"}
}