{
  "type": "Feature",
  "properties": {
    "addr:full":"Calgary AB T2E 2R8",
    "addr:postcode":"t2e 2r8",
    "iso:country":"CA",
    "sg:city":"Calgary",
    "sg:classifiers":[
        {
            "category":"Restaurant",
            "type":"Food & Drink"
        }
    ],
    "sg:phone":"+1 403 230 8890",
    "sg:postcode":"T2E 2R8",
    "sg:province":"AB",
    "wof:name":"Sun Chui Kee Restaurant",
    "wof:placetype":"venue"
},
  "geometry": {"coordinates":[-114.06398799999999,51.064571],"type":"Point"}
}