{
  "type": "Feature",
  "properties": {
    "addr:full":"85 Nantucket Blvd Scarborough ON M1P 2N7",
    "addr:housenumber":"85",
    "addr:postcode":"m1p 2n7",
    "addr:street":"Nantucket Blvd",
    "iso:country":"CA",
    "sg:address":"85 Nantucket Blvd",
    "sg:city":"Scarborough",
    "sg:classifiers":[
        {
            "category":"Manufacturing",
            "subcategory":"Metals",
            "type":"Manufacturing & Wholesale Goods"
        }
    ],
    "sg:phone":"+1 416 751 7427",
    "sg:postcode":"M1P 2N7",
    "sg:province":"ON",
    "sg:tags":[
        "stamping"
    ],
    "wof:name":"Metal Enclosures Ltd",
    "wof:placetype":"venue"
},
  "geometry": {"coordinates":[-79.2733306885,43.7547912598],"type":"Point"}
}