{
  "type": "Feature",
  "properties": {
    "addr:full":"77 Erie St N Leamington ON N8H 2Z7",
    "addr:housenumber":"77",
    "addr:postcode":"n8h 2z7",
    "addr:street":"Erie St N",
    "iso:country":"CA",
    "sg:address":"77 Erie St N",
    "sg:city":"Leamington",
    "sg:classifiers":[
        {
            "category":"Shopping",
            "subcategory":"Discount & Variety Stores",
            "type":"Retail Goods"
        }
    ],
    "sg:phone":"+1 519 326 4822",
    "sg:postcode":"N8H 2Z7",
    "sg:province":"ON",
    "wof:name":"Blondes Confectionery",
    "wof:placetype":"venue"
},
  "geometry": {"coordinates":[-82.59974699999999,42.055611],"type":"Point"}
}