{
  "type": "Feature",
  "properties": {
    "addr:full":"415 Willow St Truro NS B2N 6T2",
    "addr:housenumber":"415",
    "addr:postcode":"b2n 6t2",
    "addr:street":"Willow St",
    "iso:country":"CA",
    "sg:address":"415 Willow St",
    "sg:city":"Truro",
    "sg:classifiers":[
        {
            "category":"Wholesale",
            "subcategory":"Machinery & Supplies",
            "type":"Manufacturing & Wholesale Goods"
        }
    ],
    "sg:phone":"+1 902 895 1535",
    "sg:postcode":"B2N 6T2",
    "sg:province":"NS",
    "sg:tags":[
        "equipment",
        "laundry"
    ],
    "wof:name":"Eldis Inc",
    "wof:placetype":"venue"
},
  "geometry": {"coordinates":[-63.2934265137,45.3501434326],"type":"Point"}
}