{
  "type": "Feature",
  "properties": {
    "addr:full":"4731 Rue DE Castille Montreal-Nord QC H1H 1Y8",
    "addr:housenumber":"4731",
    "addr:postcode":"h1h 1y8",
    "addr:street":"Rue De Castille",
    "iso:country":"CA",
    "sg:address":"4731 Rue DE Castille",
    "sg:city":"Montreal-Nord",
    "sg:classifiers":[
        {
            "category":"Food & Beverages",
            "subcategory":"Groceries & Convenience Stores",
            "type":"Retail Goods"
        }
    ],
    "sg:phone":"+1 514 323 3084",
    "sg:postcode":"H1H 1Y8",
    "sg:province":"QC",
    "wof:name":"Depanneur Jean Rene",
    "wof:placetype":"venue"
},
  "geometry": {"coordinates":[-73.629829,45.594936],"type":"Point"}
}