{
  "type": "Feature",
  "properties": {
    "addr:full":"187 Boul Cure-Labelle Sainte-Rose QC H7L 2Z9",
    "addr:housenumber":"187",
    "addr:postcode":"h7l 2z9",
    "addr:street":"Boul Cure-Labelle",
    "iso:country":"CA",
    "sg:address":"187 Boul Cure-Labelle",
    "sg:city":"Sainte-Rose",
    "sg:classifiers":[
        {
            "category":"Professional",
            "subcategory":"Computer Services",
            "type":"Services"
        }
    ],
    "sg:phone":"+1 450 963 4233",
    "sg:postcode":"H7L 2Z9",
    "sg:province":"QC",
    "sg:tags":[
        "equipment",
        "dealer"
    ],
    "wof:name":"Microspec Inc",
    "wof:placetype":"venue"
},
  "geometry": {"coordinates":[-73.7907333374,45.6049232483],"type":"Point"}
}