{
  "type": "Feature",
  "properties": {
    "addr:full":"801 St Clair St Chatham ON N7M 5J7",
    "addr:housenumber":"801",
    "addr:postcode":"n7m 5j7",
    "addr:street":"St Clair St",
    "iso:country":"CA",
    "sg:address":"801 St Clair St",
    "sg:city":"Chatham",
    "sg:classifiers":[
        {
            "category":"Shopping",
            "subcategory":"Clothing, Apparel, & Fashions",
            "type":"Retail Goods"
        }
    ],
    "sg:phone":"+1 519 351 6562",
    "sg:postcode":"N7M 5J7",
    "sg:province":"ON",
    "wof:name":"Winners Apparel Store",
    "wof:placetype":"venue"
},
  "geometry": {"coordinates":[-82.21925400000001,42.430878],"type":"Point"}
}