{
  "type": "Feature",
  "properties": {
    "addr:full":"598 Boul Du Seminaire N Saint-Jean-Sur-Richelieu QC J3B 7B4",
    "addr:housenumber":"598",
    "addr:postcode":"j3b 7b4",
    "addr:street":"Boul Du Seminaire N",
    "iso:country":"CA",
    "sg:address":"598 Boul Du Seminaire N",
    "sg:city":"Saint-Jean-Sur-Richelieu",
    "sg:classifiers":[
        {
            "category":"Health Services",
            "subcategory":"Doctor",
            "type":"Services"
        }
    ],
    "sg:phone":"+1 450 359 6181",
    "sg:postcode":"J3B 7B4",
    "sg:province":"QC",
    "sg:tags":[
        "podiatrist",
        "clinic"
    ],
    "wof:name":"Noiseux & Champagne",
    "wof:placetype":"venue"
},
  "geometry": {"coordinates":[-73.26432800000001,45.318501],"type":"Point"}
}