{
  "type": "Feature",
  "properties": {
    "addr:full":"135 North St Hinton AB T7V 1S8",
    "addr:housenumber":"135",
    "addr:postcode":"t7v 1s8",
    "addr:street":"North St",
    "iso:country":"CA",
    "sg:address":"135 North St",
    "sg:city":"Hinton",
    "sg:classifiers":[
        {
            "category":"Building & Trades",
            "subcategory":"Electrical",
            "type":"Services"
        }
    ],
    "sg:phone":"+1 780 865 2504",
    "sg:postcode":"T7V 1S8",
    "sg:province":"AB",
    "sg:tags":[
        "electric",
        "contractor"
    ],
    "wof:name":"Reyn-Felt Electric Ltd",
    "wof:placetype":"venue"
},
  "geometry": {"coordinates":[-117.60667419400001,53.3944091797],"type":"Point"}
}