{
  "type": "Feature",
  "properties": {
    "addr:full":"870 Boul Du Cure-Boivin Boisbriand QC J7G 2A7",
    "addr:housenumber":"870",
    "addr:postcode":"j7g 2a7",
    "addr:street":"Boul Du Cure-Boivin",
    "iso:country":"CA",
    "sg:address":"870 Boul Du Cure-Boivin",
    "sg:city":"Boisbriand",
    "sg:classifiers":[
        {
            "category":"Building & Trades",
            "subcategory":"Construction",
            "type":"Services"
        }
    ],
    "sg:phone":"+1 450 437 0123",
    "sg:postcode":"J7G 2A7",
    "sg:province":"QC",
    "sg:tags":[
        "insulation",
        "heat"
    ],
    "wof:name":"Demilec Inc",
    "wof:placetype":"venue"
},
  "geometry": {"coordinates":[-73.8321762085,45.6245117188],"type":"Point"}
}