{
  "type": "Feature",
  "properties": {
    "iso:country":"CA",
    "sg:address":"1485 Portage Ave",
    "sg:city":"Winnipeg",
    "sg:classifiers":[
        {
            "category":"Travel",
            "subcategory":"Travel Agent",
            "type":"Entertainment"
        }
    ],
    "sg:phone":"+1 204 784 1340",
    "sg:postcode":"R3G 0W7",
    "sg:province":"MB",
    "sg:tags":[
        "agency",
        "bureau"
    ],
    "wof:name":"Sears Travel Svc",
    "wof:placetype":"venue"
},
  "geometry": {"coordinates":[-97.19825,49.88102],"type":"Point"}
}