{
  "type": "Feature",
  "properties": {
    "addr:full":"500 Berry St Winnipeg MB R3J 1N9",
    "addr:housenumber":"500",
    "addr:postcode":"r3j 1n9",
    "addr:street":"Berry St",
    "iso:country":"CA",
    "sg:address":"500 Berry St",
    "sg:city":"Winnipeg",
    "sg:classifiers":[
        {
            "category":"Home & Garden",
            "subcategory":"Garden Supply",
            "type":"Retail Goods"
        }
    ],
    "sg:phone":"+1 204 775 4555",
    "sg:postcode":"R3J 1N9",
    "sg:province":"MB",
    "sg:tags":[
        "equipment",
        "lawn",
        "mower",
        "snow",
        "removal"
    ],
    "wof:name":"Ideal Sharpening Ltd",
    "wof:placetype":"venue"
},
  "geometry": {"coordinates":[-97.21054077150001,49.8904533386],"type":"Point"}
}