{
  "type": "Feature",
  "properties": {
    "addr:full":"Newburgh ON K0K 2S0",
    "addr:postcode":"k0k 2s0",
    "iso:country":"CA",
    "sg:city":"Newburgh",
    "sg:classifiers":[
        {
            "category":"Government",
            "subcategory":"Fire Station",
            "type":"Public Place"
        }
    ],
    "sg:phone":"+1 613 378 2211",
    "sg:postcode":"K0K 2S0",
    "sg:province":"ON",
    "sg:tags":[
        "department"
    ],
    "wof:name":"Newburgh Fire Dept",
    "wof:placetype":"venue"
},
  "geometry": {"coordinates":[-76.8775405884,44.3259811401],"type":"Point"}
}