{
  "type": "Feature",
  "properties": {
    "addr:full":"1714 Vincent Massey Dr Cornwall ON K6H 5R6",
    "addr:housenumber":"1714",
    "addr:postcode":"k6h 5r6",
    "addr:street":"Vincent Massey Dr",
    "iso:country":"CA",
    "sg:address":"1714 Vincent Massey Dr",
    "sg:city":"Cornwall",
    "sg:classifiers":[
        {
            "category":"Autos & Motor Vehicles",
            "subcategory":"Automobile Sales",
            "type":"Retail Goods"
        }
    ],
    "sg:phone":"+1 613 933 2449",
    "sg:postcode":"K6H 5R6",
    "sg:province":"ON",
    "sg:tags":[
        "car",
        "dealer"
    ],
    "wof:name":"Midway Motors",
    "wof:placetype":"venue"
},
  "geometry": {"coordinates":[-74.7696228027,45.0312538147],"type":"Point"}
}