{
  "type": "Feature",
  "properties": {
    "addr:full":"North York ON M2N 3G1",
    "addr:postcode":"m2n 3g1",
    "iso:country":"CA",
    "sg:city":"North York",
    "sg:classifiers":[
        {
            "category":"Travel",
            "subcategory":"Travel Agent",
            "type":"Entertainment"
        }
    ],
    "sg:phone":"+1 416 730 0101",
    "sg:postcode":"M2N 3G1",
    "sg:province":"ON",
    "sg:tags":[
        "agency",
        "bureau"
    ],
    "wof:name":"Hana Travel Agency",
    "wof:placetype":"venue"
},
  "geometry": {"coordinates":[-79.40947,43.764633],"type":"Point"}
}