{
  "type": "Feature",
  "properties": {
    "addr:full":"Markdale ON N0C 1H0",
    "addr:postcode":"n0c 1h0",
    "iso:country":"CA",
    "sg:city":"Markdale",
    "sg:classifiers":[
        {
            "category":"Arena",
            "subcategory":"Sports Club",
            "type":"Entertainment"
        }
    ],
    "sg:phone":"+1 519 986 3301",
    "sg:postcode":"N0C 1H0",
    "sg:province":"ON",
    "sg:tags":[
        "athletic",
        "fields",
        "stadium",
        "government"
    ],
    "wof:name":"Markdale Public Arena",
    "wof:placetype":"venue"
},
  "geometry": {"coordinates":[-80.6475982666,44.3190460205],"type":"Point"}
}