{
  "type": "Feature",
  "properties": {
    "iso:country":"CA",
    "sg:address":"4300 Steeles Ave E # B88",
    "sg:city":"Markham",
    "sg:classifiers":[
        {
            "category":"Banks & Credit Unions",
            "subcategory":"Bank",
            "type":"Services"
        }
    ],
    "sg:phone":"+1 905 940 2218",
    "sg:postcode":"L3R 0Y5",
    "sg:province":"ON",
    "wof:name":"Bank of East Asia",
    "wof:placetype":"venue"
},
  "geometry": {"coordinates":[-79.3067321777,43.8238983154],"type":"Point"}
}