{
  "type": "Feature",
  "properties": {
    "addr:full":"150 Government Rd W Kirkland Lake ON P2N 2E9",
    "addr:housenumber":"150",
    "addr:postcode":"p2n 2e9",
    "addr:street":"Government Rd W",
    "iso:country":"CA",
    "sg:address":"150 Government Rd W",
    "sg:city":"Kirkland Lake",
    "sg:classifiers":[
        {
            "category":"Professional",
            "subcategory":"Management & Consulting",
            "type":"Services"
        }
    ],
    "sg:phone":"+1 705 568 8656",
    "sg:postcode":"P2N 2E9",
    "sg:province":"ON",
    "sg:tags":[
        "consultant",
        "mall",
        "shopping",
        "center",
        "business"
    ],
    "wof:name":"Kirkland Lake Shopping Ctr",
    "wof:placetype":"venue"
},
  "geometry": {"coordinates":[-80.04669199999999,48.147308],"type":"Point"}
}