{
  "type": "Feature",
  "properties": {
    "iso:country":"CA",
    "sg:address":"43 Rue Green",
    "sg:city":"Saint-Lambert",
    "sg:classifiers":[
        {
            "category":"Travel",
            "subcategory":"Travel Agent",
            "type":"Entertainment"
        }
    ],
    "sg:phone":"+1 450 465 6666",
    "sg:postcode":"J4P 1S3",
    "sg:province":"QC",
    "sg:tags":[
        "agency",
        "bureau"
    ],
    "wof:name":"G W Clark & Cie Inc",
    "wof:placetype":"venue"
},
  "geometry": {"coordinates":[-73.510811,45.501801],"type":"Point"}
}