{
  "type": "Feature",
  "properties": {
    "iso:country":"CA",
    "sg:address":"9055 63 Ave NW",
    "sg:city":"Edmonton",
    "sg:classifiers":[
        {
            "category":"Autos & Motor Vehicles",
            "subcategory":"Motorcycle Sales",
            "type":"Retail Goods"
        }
    ],
    "sg:phone":"+1 780 438 4443",
    "sg:postcode":"T6E 0E9",
    "sg:province":"AB",
    "sg:tags":[
        "all",
        "terrain"
    ],
    "wof:name":"Argo Distributor",
    "wof:placetype":"venue"
},
  "geometry": {"coordinates":[-113.466026306,53.4995994568],"type":"Point"}
}