{
  "type": "Feature",
  "properties": {
    "iso:country":"CA",
    "sg:address":"2090 Boul DE Tadoussac",
    "sg:city":"Chicoutimi",
    "sg:classifiers":[
        {
            "category":"Education",
            "subcategory":"School",
            "type":"Public Place"
        }
    ],
    "sg:phone":"+1 418 543 6067",
    "sg:postcode":"G7G 1K9",
    "sg:province":"QC",
    "wof:name":"Ecole Notre-Dame-Du-Rosaire",
    "wof:placetype":"venue"
},
  "geometry": {"coordinates":[-71.061096,48.439835],"type":"Point"}
}