{
  "type": "Feature",
  "properties": {
    "addr:full":"3883 Boul Saint-Jean # 110 Dollard-Des-Ormeaux QC H9G 3B9",
    "addr:housenumber":"3883",
    "addr:postcode":"h9g 3b9",
    "addr:street":"Boul Saint-Jean # 110",
    "iso:country":"CA",
    "sg:address":"3883 Boul Saint-Jean # 110",
    "sg:city":"Dollard-Des-Ormeaux",
    "sg:classifiers":[
        {
            "category":"Health Services",
            "subcategory":"Doctor",
            "type":"Services"
        }
    ],
    "sg:phone":"+1 514 624 8888",
    "sg:postcode":"H9G 3B9",
    "sg:province":"QC",
    "sg:tags":[
        "dentist"
    ],
    "wof:name":"Turkewicz, Jack DDS",
    "wof:placetype":"venue"
},
  "geometry": {"coordinates":[-73.83670043950001,45.4753799438],"type":"Point"}
}