{
  "type": "Feature",
  "properties": {
    "iso:country":"CA",
    "sg:address":"2865 Scharf Rd",
    "sg:city":"Westbank",
    "sg:classifiers":[
        {
            "category":"Restaurant",
            "type":"Food & Drink"
        }
    ],
    "sg:phone":"+1 250 768 5763",
    "sg:postcode":"V4T 2B5",
    "sg:province":"BC",
    "sg:tags":[
        "caterer"
    ],
    "wof:name":"Happy-Tizers Unlimited",
    "wof:placetype":"venue"
},
  "geometry": {"coordinates":[-119.649772644,49.8421058655],"type":"Point"}
}