{
  "type": "Feature",
  "properties": {
    "addr:full":"4503 45 St Leduc AB T9E 7K4",
    "addr:housenumber":"4503",
    "addr:postcode":"t9e 7k4",
    "addr:street":"45 St",
    "iso:country":"CA",
    "sg:address":"4503 45 St",
    "sg:city":"Leduc",
    "sg:classifiers":[
        {
            "category":"Education",
            "subcategory":"School",
            "type":"Public Place"
        }
    ],
    "sg:phone":"+1 780 986 8421",
    "sg:postcode":"T9E 7K4",
    "sg:province":"AB",
    "wof:name":"East Elementary School",
    "wof:placetype":"venue"
},
  "geometry": {"coordinates":[-113.540252685,53.259563446],"type":"Point"}
}