{
  "type": "Feature",
  "properties": {
    "iso:country":"CA",
    "sg:city":"Tete-A-LA-Baleine",
    "sg:classifiers":[
        {
            "category":"Organizations",
            "subcategory":"Professional Association",
            "type":"Services"
        }
    ],
    "sg:phone":"+1 418 242 2156",
    "sg:postcode":"G0G 2W0",
    "sg:province":"QC",
    "wof:name":"Comite Des Pecheurs",
    "wof:placetype":"venue"
},
  "geometry": {"coordinates":[-59.3561439514,50.6865501404],"type":"Point"}
}