{
  "type": "Feature",
  "properties": {
    "addr:full":"Magnum St E Gravelbourg SK S0H 1X0",
    "addr:postcode":"s0h 1x0",
    "addr:street":"Magnum St E Gravelbourg",
    "iso:country":"CA",
    "sg:address":"Magnum St E",
    "sg:city":"Gravelbourg",
    "sg:classifiers":[
        {
            "category":"Recreation",
            "type":"Entertainment"
        }
    ],
    "sg:phone":"+1 306 648 2225",
    "sg:postcode":"S0H 1X0",
    "sg:province":"SK",
    "sg:tags":[
        "center"
    ],
    "wof:name":"Gravelbourg Recreation Assn",
    "wof:placetype":"venue"
},
  "geometry": {"coordinates":[-106.554451,49.873363],"type":"Point"}
}