{
  "type": "Feature",
  "properties": {
    "addr:full":"Huntsville ON P1H 1C2",
    "addr:postcode":"p1h 1c2",
    "iso:country":"CA",
    "sg:city":"Huntsville",
    "sg:classifiers":[
        {
            "category":"Home & Garden",
            "subcategory":"Furniture",
            "type":"Retail Goods"
        }
    ],
    "sg:phone":"+1 705 789 0439",
    "sg:postcode":"P1H 1C2",
    "sg:province":"ON",
    "wof:name":"Kelly's Home Furniture",
    "wof:placetype":"venue"
},
  "geometry": {"coordinates":[-79.197334,45.338196],"type":"Point"}
}