{
  "type": "Feature",
  "properties": {
    "addr:full":"260 262 Harvey St Harbour Grace NL A0A 2M0",
    "addr:housenumber":"262",
    "addr:postcode":"a0a 2m0",
    "addr:street":"Harvey St",
    "iso:country":"CA",
    "sg:address":"260 262 Harvey St",
    "sg:city":"Harbour Grace",
    "sg:classifiers":[
        {
            "category":"Personal",
            "subcategory":"Beauty Salon",
            "type":"Services"
        }
    ],
    "sg:phone":"+1 709 596 3600",
    "sg:postcode":"A0A 2M0",
    "sg:province":"NL",
    "wof:name":"Hair 4U",
    "wof:placetype":"venue"
},
  "geometry": {"coordinates":[-53.24401474,47.6816673279],"type":"Point"}
}