{
  "type": "Feature",
  "properties": {
    "addr:full":"Victoria BC V8T 2C8",
    "addr:postcode":"v8t 2c8",
    "iso:country":"CA",
    "sg:city":"Victoria",
    "sg:classifiers":[
        {
            "category":"Professional",
            "subcategory":"Computer Services",
            "type":"Services"
        }
    ],
    "sg:phone":"+1 250 360 1990",
    "sg:postcode":"V8T 2C8",
    "sg:province":"BC",
    "sg:tags":[
        "repair"
    ],
    "wof:name":"Bsl Business Systems Lustre",
    "wof:placetype":"venue"
},
  "geometry": {"coordinates":[-123.371421814,48.4383201599],"type":"Point"}
}