{
  "type": "Feature",
  "properties": {
    "addr:full":"860 Rue Gauthier O Alma QC G8B 2H8",
    "addr:housenumber":"860",
    "addr:postcode":"g8b 2h8",
    "addr:street":"Rue Gauthier O",
    "iso:country":"CA",
    "sg:address":"860 Rue Gauthier O",
    "sg:city":"Alma",
    "sg:classifiers":[
        {
            "category":"Wholesale",
            "subcategory":"Chemicals & Plastics",
            "type":"Manufacturing & Wholesale Goods"
        }
    ],
    "sg:phone":"+1 418 662 9902",
    "sg:postcode":"G8B 2H8",
    "sg:province":"QC",
    "sg:tags":[
        "sanitary",
        "product",
        "compound",
        "cleaning",
        "supply"
    ],
    "wof:name":"Fortin, Errold",
    "wof:placetype":"venue"
},
  "geometry": {"coordinates":[-71.65873000000001,48.542385],"type":"Point"}
}