{
  "type": "Feature",
  "properties": {
    "iso:country":"CA",
    "sg:address":"1526 Ch Des Patriotes",
    "sg:city":"Sainte-Victoire-DE-Sorel",
    "sg:classifiers":[
        {
            "category":"Personal",
            "type":"Services"
        }
    ],
    "sg:phone":"+1 450 742 2200",
    "sg:postcode":"J0G 1T0",
    "sg:province":"QC",
    "sg:tags":[
        "therapist",
        "massage"
    ],
    "wof:name":"Clinique DE Massotherapie",
    "wof:placetype":"venue"
},
  "geometry": {"coordinates":[-73.13659667970001,45.9888267517],"type":"Point"}
}