{
  "type": "Feature",
  "properties": {
    "addr:full":"1808 Eglinton Ave W York ON M6E 2H6",
    "addr:housenumber":"1808",
    "addr:postcode":"m6e 2h6",
    "addr:street":"Eglinton Ave W",
    "iso:country":"CA",
    "sg:address":"1808 Eglinton Ave W",
    "sg:city":"York",
    "sg:classifiers":[
        {
            "category":"Restaurant",
            "type":"Food & Drink"
        }
    ],
    "sg:phone":"+1 416 782 3334",
    "sg:postcode":"M6E 2H6",
    "sg:province":"ON",
    "wof:name":"Best Food Grill",
    "wof:placetype":"venue"
},
  "geometry": {"coordinates":[-79.449539,43.69598],"type":"Point"}
}