{
  "type": "Feature",
  "properties": {
    "addr:full":"Bolton Centre QC J0E 1G0",
    "addr:postcode":"j0e 1g0",
    "iso:country":"CA",
    "sg:city":"Bolton Centre",
    "sg:classifiers":[
        {
            "category":"Manufacturing",
            "subcategory":"Buildings",
            "type":"Manufacturing & Wholesale Goods"
        }
    ],
    "sg:phone":"+1 450 297 4234",
    "sg:postcode":"J0E 1G0",
    "sg:province":"QC",
    "sg:tags":[
        "prefab",
        "company",
        "land"
    ],
    "wof:name":"Aux Environs DE Bolton Dev",
    "wof:placetype":"venue"
},
  "geometry": {"coordinates":[-72.35470581049999,45.2086296082],"type":"Point"}
}