{
  "type": "Feature",
  "properties": {
    "addr:full":"67 Lankin Blvd East York ON M4J 4W9",
    "addr:housenumber":"67",
    "addr:postcode":"m4j 4w9",
    "addr:street":"Lankin Blvd",
    "iso:country":"CA",
    "sg:address":"67 Lankin Blvd",
    "sg:city":"East York",
    "sg:classifiers":[
        {
            "category":"Retail",
            "subcategory":"Repair Shop",
            "type":"Services"
        }
    ],
    "sg:phone":"+1 416 425 7560",
    "sg:postcode":"M4J 4W9",
    "sg:province":"ON",
    "sg:tags":[
        "appliance"
    ],
    "wof:name":"Dan's Services",
    "wof:placetype":"venue"
},
  "geometry": {"coordinates":[-79.329353,43.695091],"type":"Point"}
}