{
  "type": "Feature",
  "properties": {
    "addr:full":"1201 Cypress St Campbell River BC V9W 2Z3",
    "addr:housenumber":"1201",
    "addr:postcode":"v9w 2z3",
    "addr:street":"Cypress St",
    "iso:country":"CA",
    "sg:address":"1201 Cypress St",
    "sg:city":"Campbell River",
    "sg:classifiers":[
        {
            "category":"Organizations",
            "subcategory":"Religious Organization",
            "type":"Services"
        }
    ],
    "sg:phone":"+1 250 287 8786",
    "sg:postcode":"V9W 2Z3",
    "sg:province":"BC",
    "sg:tags":[
        "church"
    ],
    "wof:name":"Discovery Community Church",
    "wof:placetype":"venue"
},
  "geometry": {"coordinates":[-125.248336792,50.0270500183],"type":"Point"}
}