{
  "type": "Feature",
  "properties": {
    "addr:full":"840 Walker St Prescott ON K0E 1T0",
    "addr:housenumber":"840",
    "addr:postcode":"k0e 1t0",
    "addr:street":"Walker St",
    "iso:country":"CA",
    "sg:address":"840 Walker St",
    "sg:city":"Prescott",
    "sg:classifiers":[
        {
            "category":"Shopping",
            "type":"Retail Goods"
        }
    ],
    "sg:phone":"+1 613 925 4242",
    "sg:postcode":"K0E 1T0",
    "sg:province":"ON",
    "sg:tags":[
        "factory",
        "outlet"
    ],
    "wof:name":"Portolano Products Inc",
    "wof:placetype":"venue"
},
  "geometry": {"coordinates":[-75.520927,44.713009],"type":"Point"}
}