{
  "type": "Feature",
  "properties": {
    "addr:full":"284 King St E Toronto ON M5A 1K4",
    "addr:housenumber":"284",
    "addr:postcode":"m5a 1k4",
    "addr:street":"King St E",
    "iso:country":"CA",
    "sg:address":"284 King St E",
    "sg:city":"Toronto",
    "sg:classifiers":[
        {
            "category":"Professional",
            "subcategory":"Management & Consulting",
            "type":"Services"
        }
    ],
    "sg:phone":"+1 416 366 5172",
    "sg:postcode":"M5A 1K4",
    "sg:province":"ON",
    "sg:tags":[
        "development",
        "image",
        "corporate"
    ],
    "wof:name":"Tudhope Associates Inc",
    "wof:placetype":"venue"
},
  "geometry": {"coordinates":[-79.3656539917,43.6519813538],"type":"Point"}
}