{
  "type": "Feature",
  "properties": {
    "addr:full":"26518 28B Ave Aldergrove BC V4W 3B1",
    "addr:housenumber":"26518",
    "addr:postcode":"v4w 3b1",
    "addr:street":"28B Ave",
    "iso:country":"CA",
    "sg:address":"26518 28B Ave",
    "sg:city":"Aldergrove",
    "sg:classifiers":[
        {
            "category":"Building & Trades",
            "subcategory":"Plumbing",
            "type":"Services"
        }
    ],
    "sg:phone":"+1 604 607 3808",
    "sg:postcode":"V4W 3B1",
    "sg:province":"BC",
    "sg:tags":[
        "contractor"
    ],
    "wof:name":"Brookswood Plumbing",
    "wof:placetype":"venue"
},
  "geometry": {"coordinates":[-122.489052,49.052883],"type":"Point"}
}