{
  "type": "Feature",
  "properties": {
    "addr:full":"Quebec QC G1K 7M1",
    "addr:postcode":"g1k 7m1",
    "iso:country":"CA",
    "sg:city":"Quebec",
    "sg:classifiers":[
        {
            "category":"Autos & Motor Vehicles",
            "subcategory":"Boat Sales",
            "type":"Retail Goods"
        }
    ],
    "sg:phone":"+1 418 821 4377",
    "sg:postcode":"G1K 7M1",
    "sg:province":"QC",
    "sg:tags":[
        "equipment",
        "supply"
    ],
    "wof:name":"Equipements DE Survie Maritime",
    "wof:placetype":"venue"
},
  "geometry": {"coordinates":[-71.2193603516,46.8127479553],"type":"Point"}
}