{
  "type": "Feature",
  "properties": {
    "addr:full":"7805 Telephone Rd Cobourg ON K9A 4J7",
    "addr:housenumber":"7805",
    "addr:postcode":"k9a 4j7",
    "addr:street":"Telephone Rd",
    "iso:country":"CA",
    "sg:address":"7805 Telephone Rd",
    "sg:city":"Cobourg",
    "sg:classifiers":[
        {
            "category":"Communications",
            "subcategory":"Radio Station",
            "type":"Services"
        }
    ],
    "sg:phone":"+1 905 372 5401",
    "sg:postcode":"K9A 4J7",
    "sg:province":"ON",
    "sg:tags":[
        "company",
        "broadcasting"
    ],
    "wof:name":"Chuc",
    "wof:placetype":"venue"
},
  "geometry": {"coordinates":[-78.167778,43.959606],"type":"Point"}
}