{
  "type": "Feature",
  "properties": {
    "addr:full":"1281 Kingsway Vancouver BC V5V 3E2",
    "addr:housenumber":"1281",
    "addr:postcode":"v5v 3e2",
    "addr:street":"Kingsway",
    "iso:country":"CA",
    "sg:address":"1281 Kingsway",
    "sg:city":"Vancouver",
    "sg:classifiers":[
        {
            "category":"Retail",
            "subcategory":"Repair Shop",
            "type":"Services"
        }
    ],
    "sg:phone":"+1 604 876 2692",
    "sg:postcode":"V5V 3E2",
    "sg:province":"BC",
    "sg:tags":[
        "television",
        "radio"
    ],
    "wof:name":"Luc Tv Electronics",
    "wof:placetype":"venue"
},
  "geometry": {"coordinates":[-123.078262,49.251453],"type":"Point"}
}