{
  "type": "Feature",
  "properties": {
    "addr:full":"543 Main St Montague PE C0A 1R0",
    "addr:housenumber":"543",
    "addr:postcode":"c0a 1r0",
    "addr:street":"Main St",
    "iso:country":"CA",
    "sg:address":"543 Main St",
    "sg:city":"Montague",
    "sg:classifiers":[
        {
            "category":"Insurance",
            "subcategory":"Insurance Agent",
            "type":"Services"
        }
    ],
    "sg:phone":"+1 902 838 2231",
    "sg:postcode":"C0A 1R0",
    "sg:province":"PE",
    "wof:name":"Concorde Insurance Brokers Ltd",
    "wof:placetype":"venue"
},
  "geometry": {"coordinates":[-62.649261,46.166222],"type":"Point"}
}