{
  "type": "Feature",
  "properties": {
    "addr:full":"Scarborough ON M1S 3L1",
    "addr:postcode":"m1s 3l1",
    "iso:country":"CA",
    "sg:city":"Scarborough",
    "sg:classifiers":[
        {
            "category":"Education",
            "subcategory":"Special Training",
            "type":"Public Place"
        }
    ],
    "sg:phone":"+1 416 299 9956",
    "sg:postcode":"M1S 3L1",
    "sg:province":"ON",
    "sg:tags":[
        "instruction",
        "driving"
    ],
    "wof:name":"Amb Driving School Inc",
    "wof:placetype":"venue"
},
  "geometry": {"coordinates":[-79.25784299999999,43.792336],"type":"Point"}
}