{
  "type": "Feature",
  "properties": {
    "addr:full":"845 Jane St York ON M6N 4C4",
    "addr:housenumber":"845",
    "addr:postcode":"m6n 4c4",
    "addr:street":"Jane St",
    "iso:country":"CA",
    "sg:address":"845 Jane St",
    "sg:city":"York",
    "sg:classifiers":[
        {
            "category":"Retail",
            "subcategory":"Photofinishing",
            "type":"Services"
        }
    ],
    "sg:phone":"+1 416 766 5073",
    "sg:postcode":"M6N 4C4",
    "sg:province":"ON",
    "sg:tags":[
        "photo",
        "finishing"
    ],
    "wof:name":"Colortone",
    "wof:placetype":"venue"
},
  "geometry": {"coordinates":[-79.495583,43.676437],"type":"Point"}
}