{
  "type": "Feature",
  "properties": {
    "addr:full":"Calgary AB T2W 4N4",
    "addr:postcode":"t2w 4n4",
    "iso:country":"CA",
    "sg:city":"Calgary",
    "sg:classifiers":[
        {
            "category":"Food & Beverages",
            "subcategory":"Specialty",
            "type":"Retail Goods"
        }
    ],
    "sg:phone":"+1 403 281 5582",
    "sg:postcode":"T2W 4N4",
    "sg:province":"AB",
    "sg:tags":[
        "health",
        "diet"
    ],
    "wof:name":"Trinity Health Foods",
    "wof:placetype":"venue"
},
  "geometry": {"coordinates":[-114.119499206,50.9409751892],"type":"Point"}
}