{
  "type": "Feature",
  "properties": {
    "addr:full":"Frog Creek Rd Fort Frances ON P9A 3M2",
    "addr:postcode":"p9a 3m2",
    "addr:street":"Frog Creek Rd",
    "iso:country":"CA",
    "sg:address":"Frog Creek Rd",
    "sg:city":"Fort Frances",
    "sg:classifiers":[
        {
            "category":"Retail",
            "subcategory":"Animal Services",
            "type":"Services"
        }
    ],
    "sg:phone":"+1 807 274 6050",
    "sg:postcode":"P9A 3M2",
    "sg:province":"ON",
    "sg:tags":[
        "pet",
        "boarding",
        "sitting"
    ],
    "wof:name":"Galusha's Boarding Kennels",
    "wof:placetype":"venue"
},
  "geometry": {"coordinates":[-93.439911,48.648998],"type":"Point"}
}