{
  "type": "Feature",
  "properties": {
    "addr:full":"118 Main St Invermay SK S0A 1M0",
    "addr:housenumber":"118",
    "addr:postcode":"s0a 1m0",
    "addr:street":"Main St",
    "iso:country":"CA",
    "sg:address":"118 Main St",
    "sg:city":"Invermay",
    "sg:classifiers":[
        {
            "category":"Restaurant",
            "type":"Food & Drink"
        }
    ],
    "sg:phone":"+1 306 593 2055",
    "sg:postcode":"S0A 1M0",
    "sg:province":"SK",
    "wof:name":"Benny's Restaurant",
    "wof:placetype":"venue"
},
  "geometry": {"coordinates":[-103.153221,51.805794],"type":"Point"}
}