{
  "type": "Feature",
  "properties": {
    "addr:full":"Winnipeg MB R2M 3S9",
    "addr:postcode":"r2m 3s9",
    "iso:country":"CA",
    "sg:city":"Winnipeg",
    "sg:classifiers":[
        {
            "category":"Professional",
            "subcategory":"Engineering",
            "type":"Services"
        }
    ],
    "sg:phone":"+1 204 253 3400",
    "sg:postcode":"R2M 3S9",
    "sg:province":"MB",
    "sg:tags":[
        "engineer"
    ],
    "wof:name":"M2 Engineering Electrical",
    "wof:placetype":"venue"
},
  "geometry": {"coordinates":[-97.11260223390001,49.8378753662],"type":"Point"}
}