{
  "type": "Feature",
  "properties": {
    "addr:full":"Regina SK S4P 0K6",
    "addr:postcode":"s4p 0k6",
    "iso:country":"CA",
    "sg:city":"Regina",
    "sg:classifiers":[
        {
            "category":"Manufacturing",
            "subcategory":"Printing",
            "type":"Manufacturing & Wholesale Goods"
        }
    ],
    "sg:phone":"+1 306 525 4900",
    "sg:postcode":"S4P 0K6",
    "sg:province":"SK",
    "sg:tags":[
        "printer"
    ],
    "wof:name":"L M Publication Svc Ltd",
    "wof:placetype":"venue"
},
  "geometry": {"coordinates":[-104.616752624,50.4502906799],"type":"Point"}
}