{
  "type": "Feature",
  "properties": {
    "iso:country":"CA",
    "sg:address":"3990 Boul Industriel",
    "sg:city":"Sherbrooke",
    "sg:classifiers":[
        {
            "category":"Building & Trades",
            "subcategory":"Construction",
            "type":"Services"
        }
    ],
    "sg:phone":"+1 819 820 2220",
    "sg:postcode":"J1L 2T8",
    "sg:province":"QC",
    "sg:tags":[
        "general",
        "contractor"
    ],
    "wof:name":"Comco Construction Inc",
    "wof:placetype":"venue"
},
  "geometry": {"coordinates":[-71.96328,45.39761],"type":"Point"}
}