{
  "type": "Feature",
  "properties": {
    "addr:full":"Toronto ON M6R 2A3",
    "addr:postcode":"m6r 2a3",
    "iso:country":"CA",
    "sg:city":"Toronto",
    "sg:classifiers":[
        {
            "category":"Professional",
            "subcategory":"Computer Services",
            "type":"Services"
        }
    ],
    "sg:phone":"+1 416 532 9943",
    "sg:postcode":"M6R 2A3",
    "sg:province":"ON",
    "sg:tags":[
        "graphics"
    ],
    "wof:name":"Ovation Digital",
    "wof:placetype":"venue"
},
  "geometry": {"coordinates":[-79.43785099999999,43.640667],"type":"Point"}
}