{
  "type": "Feature",
  "properties": {
    "iso:country":"CA",
    "sg:address":"899 Ch Benoit",
    "sg:city":"Mont-Saint-Hilaire",
    "sg:classifiers":[
        {
            "category":"Manufacturing",
            "subcategory":"Lumber",
            "type":"Manufacturing & Wholesale Goods"
        }
    ],
    "sg:phone":"+1 450 464 8016",
    "sg:postcode":"J3G 4S6",
    "sg:province":"QC",
    "wof:name":"Exulon Inc",
    "wof:placetype":"venue"
},
  "geometry": {"coordinates":[-73.145164,45.585163],"type":"Point"}
}