{
  "type": "Feature",
  "properties": {
    "addr:full":"1126 Princess Ave Brandon MB R7A 0P9",
    "addr:housenumber":"1126",
    "addr:postcode":"r7a 0p9",
    "addr:street":"Princess Ave",
    "iso:country":"CA",
    "sg:address":"1126 Princess Ave",
    "sg:city":"Brandon",
    "sg:classifiers":[
        {
            "category":"Retail",
            "subcategory":"Auto Repair",
            "type":"Services"
        }
    ],
    "sg:phone":"+1 204 727 2250",
    "sg:postcode":"R7A 0P9",
    "sg:province":"MB",
    "sg:tags":[
        "repairing",
        "automobile",
        "muffler",
        "system",
        "exhaust"
    ],
    "wof:name":"Midas Auto Svc Experts",
    "wof:placetype":"venue"
},
  "geometry": {"coordinates":[-99.95324707029999,49.8467216492],"type":"Point"}
}