{
  "type": "Feature",
  "properties": {
    "addr:full":"55 Rue Castonguay Saint-Jerome QC J7Y 2H9",
    "addr:housenumber":"55",
    "addr:postcode":"j7y 2h9",
    "addr:street":"Rue Castonguay Saint-Jerome",
    "iso:country":"CA",
    "sg:address":"55 Rue Castonguay",
    "sg:city":"Saint-Jerome",
    "sg:classifiers":[
        {
            "category":"Government",
            "subcategory":"Office",
            "type":"Public Place"
        }
    ],
    "sg:phone":"+1 450 569 7575",
    "sg:postcode":"J7Y 2H9",
    "sg:province":"QC",
    "wof:name":"Quebec Solidarite Sociale",
    "wof:placetype":"venue"
},
  "geometry": {"coordinates":[-74.00670599999999,45.776741],"type":"Point"}
}