{
  "type": "Feature",
  "properties": {
    "addr:full":"295 Rue Dequen Saint-Gedeon QC G0W 2P0",
    "addr:housenumber":"295",
    "addr:postcode":"g0w 2p0",
    "addr:street":"Rue Dequen Saint-Gedeon",
    "iso:country":"CA",
    "sg:address":"295 Rue Dequen",
    "sg:city":"Saint-Gedeon",
    "sg:classifiers":[
        {
            "category":"Wholesale",
            "subcategory":"Fruits & Vegetables",
            "type":"Manufacturing & Wholesale Goods"
        }
    ],
    "sg:phone":"+1 418 345 8334",
    "sg:postcode":"G0W 2P0",
    "sg:province":"QC",
    "sg:tags":[
        "shipper"
    ],
    "wof:name":"Legunord Inc",
    "wof:placetype":"venue"
},
  "geometry": {"coordinates":[-71.77376599999999,48.497849],"type":"Point"}
}