{
  "type": "Feature",
  "properties": {
    "addr:full":"280 Cordova St E Vancouver BC V6A 1L3",
    "addr:housenumber":"280",
    "addr:postcode":"v6a 1l3",
    "addr:street":"Cordova St E",
    "iso:country":"CA",
    "sg:address":"280 Cordova St E",
    "sg:city":"Vancouver",
    "sg:classifiers":[
        {
            "category":"Arts & Performance",
            "subcategory":"Theater",
            "type":"Entertainment"
        }
    ],
    "sg:phone":"+1 604 689 0926",
    "sg:postcode":"V6A 1L3",
    "sg:province":"BC",
    "wof:name":"Firehall Arts Ctr",
    "wof:placetype":"venue"
},
  "geometry": {"coordinates":[-123.098083,49.282124],"type":"Point"}
}