{
  "type": "Feature",
  "properties": {
    "iso:country":"CA",
    "sg:address":"2824 Main St",
    "sg:city":"Shubenacadie",
    "sg:classifiers":[
        {
            "category":"Banks & Credit Unions",
            "subcategory":"Bank",
            "type":"Services"
        }
    ],
    "sg:phone":"+1 902 758 2295",
    "sg:postcode":"B0N 2H0",
    "sg:province":"NS",
    "wof:name":"Royal Bank Financial Group",
    "wof:placetype":"venue"
},
  "geometry": {"coordinates":[-63.4078598022,45.0872917175],"type":"Point"}
}