{
  "type": "Feature",
  "properties": {
    "addr:full":"2495 2E Rue Sainte-Sophie QC J5J 1N6",
    "addr:housenumber":"2495",
    "addr:postcode":"j5j 1n6",
    "addr:street":"2E Rue",
    "iso:country":"CA",
    "sg:address":"2495 2E Rue",
    "sg:city":"Sainte-Sophie",
    "sg:classifiers":[
        {
            "category":"Farming",
            "subcategory":"Farm",
            "type":"Manufacturing & Wholesale Goods"
        }
    ],
    "sg:phone":"+1 450 565 5722",
    "sg:postcode":"J5J 1N6",
    "sg:province":"QC",
    "wof:name":"Ferme H3B Ltee",
    "wof:placetype":"venue"
},
  "geometry": {"coordinates":[-73.89660600000001,45.819359],"type":"Point"}
}