{
  "type": "Feature",
  "properties": {
    "addr:full":"15 Gidley St E Exeter ON N0M 1S7",
    "addr:housenumber":"15",
    "addr:postcode":"n0m 1s7",
    "addr:street":"Gidley St E",
    "iso:country":"CA",
    "sg:address":"15 Gidley St E",
    "sg:city":"Exeter",
    "sg:classifiers":[
        {
            "category":"Professional",
            "subcategory":"Business Services",
            "type":"Services"
        }
    ],
    "sg:phone":"+1 519 235 1010",
    "sg:postcode":"N0M 1S7",
    "sg:province":"ON",
    "sg:tags":[
        "interior",
        "consultant",
        "design",
        "decorator",
        "paint"
    ],
    "wof:name":"Exeter Decor Ctr",
    "wof:placetype":"venue"
},
  "geometry": {"coordinates":[-81.48028600000001,43.348995],"type":"Point"}
}