{
  "type": "Feature",
  "properties": {
    "iso:country":"CA",
    "sg:address":"10 Birch St",
    "sg:city":"Digby",
    "sg:classifiers":[
        {
            "category":"Organizations",
            "subcategory":"Religious Organization",
            "type":"Services"
        }
    ],
    "sg:phone":"+1 902 245 2350",
    "sg:postcode":"B0V 1A0",
    "sg:province":"NS",
    "sg:tags":[
        "church"
    ],
    "wof:name":"Sisters of Charity/Immclte Con",
    "wof:placetype":"venue"
},
  "geometry": {"coordinates":[-65.75671386720001,44.6267166138],"type":"Point"}
}