{
  "type": "Feature",
  "properties": {
    "addr:full":"1755 Rue Du Ruisseau Sainte-Madeleine QC J0H 1S0",
    "addr:housenumber":"1755",
    "addr:postcode":"j0h 1s0",
    "addr:street":"Rue Du Ruisseau",
    "iso:country":"CA",
    "sg:address":"1755 Rue Du Ruisseau",
    "sg:city":"Sainte-Madeleine",
    "sg:classifiers":[
        {
            "category":"Building & Trades",
            "subcategory":"Construction",
            "type":"Services"
        }
    ],
    "sg:phone":"+1 450 795 6454",
    "sg:postcode":"J0H 1S0",
    "sg:province":"QC",
    "sg:tags":[
        "maker",
        "cabinet"
    ],
    "wof:name":"Charlemagne, Rabot",
    "wof:placetype":"venue"
},
  "geometry": {"coordinates":[-73.10176800000001,45.586006],"type":"Point"}
}