{
  "type": "Feature",
  "properties": {
    "addr:full":"Toronto ON M5H 3M7",
    "addr:postcode":"m5h 3m7",
    "iso:country":"CA",
    "sg:city":"Toronto",
    "sg:classifiers":[
        {
            "category":"Government",
            "subcategory":"Office",
            "type":"Public Place"
        }
    ],
    "sg:phone":"+1 416 861 0000",
    "sg:postcode":"M5H 3M7",
    "sg:province":"ON",
    "sg:tags":[
        "commission",
        "trade"
    ],
    "wof:name":"Jetro Toronto",
    "wof:placetype":"venue"
},
  "geometry": {"coordinates":[-79.3854141235,43.6490478516],"type":"Point"}
}