{
  "type": "Feature",
  "properties": {
    "addr:full":"6430 Av Victoria Montreal QC H3W 2S6",
    "addr:housenumber":"6430",
    "addr:postcode":"h3w 2s6",
    "addr:street":"Av Victoria",
    "iso:country":"CA",
    "sg:address":"6430 Av Victoria",
    "sg:city":"Montreal",
    "sg:classifiers":[
        {
            "category":"Food & Beverages",
            "subcategory":"Groceries & Convenience Stores",
            "type":"Retail Goods"
        }
    ],
    "sg:phone":"+1 514 345 1827",
    "sg:postcode":"H3W 2S6",
    "sg:province":"QC",
    "sg:tags":[
        "video",
        "grocer",
        "disc",
        "tape"
    ],
    "wof:name":"Marche Duc-Thanh Enr",
    "wof:placetype":"venue"
},
  "geometry": {"coordinates":[-73.640007,45.495285],"type":"Point"}
}