{
  "type": "Feature",
  "properties": {
    "addr:full":"350 Garyray Dr North York ON M9L 1P5",
    "addr:housenumber":"350",
    "addr:postcode":"m9l 1p5",
    "addr:street":"Garyray Dr",
    "iso:country":"CA",
    "sg:address":"350 Garyray Dr",
    "sg:city":"North York",
    "sg:classifiers":[
        {
            "category":"Wholesale",
            "subcategory":"Meat",
            "type":"Manufacturing & Wholesale Goods"
        }
    ],
    "sg:phone":"+1 416 743 2021",
    "sg:postcode":"M9L 1P5",
    "sg:province":"ON",
    "sg:tags":[
        "packer"
    ],
    "wof:name":"Filicetti Foods Inc",
    "wof:placetype":"venue"
},
  "geometry": {"coordinates":[-79.543571,43.768299],"type":"Point"}
}