{
  "type": "Feature",
  "properties": {
    "iso:country":"CA",
    "sg:address":"4789 Riverside Dr E # 1203",
    "sg:city":"Windsor",
    "sg:classifiers":[
        {
            "category":"Building & Trades",
            "subcategory":"Construction",
            "type":"Services"
        }
    ],
    "sg:phone":"+1 519 945 3725",
    "sg:postcode":"N8Y 5A2",
    "sg:province":"ON",
    "sg:tags":[
        "painter"
    ],
    "wof:name":"R J's Wall Visions",
    "wof:placetype":"venue"
},
  "geometry": {"coordinates":[-82.98025512700001,42.3284454346],"type":"Point"}
}