{
  "type": "Feature",
  "properties": {
    "addr:full":"834 Fairford St E Moose Jaw SK S6H 0G4",
    "addr:housenumber":"834",
    "addr:postcode":"s6h 0g4",
    "addr:street":"Fairford St E",
    "iso:country":"CA",
    "sg:address":"834 Fairford St E",
    "sg:city":"Moose Jaw",
    "sg:classifiers":[
        {
            "category":"Freight",
            "type":"Transportation"
        }
    ],
    "sg:phone":"+1 306 692 6161",
    "sg:postcode":"S6H 0G4",
    "sg:province":"SK",
    "sg:tags":[
        "delivery"
    ],
    "wof:name":"Speed's Delivery",
    "wof:placetype":"venue"
},
  "geometry": {"coordinates":[-105.513763428,50.3924293518],"type":"Point"}
}