{
  "type": "Feature",
  "properties": {
    "addr:full":"955 Eglinton Ave W York ON M6C 2C4",
    "addr:housenumber":"955",
    "addr:postcode":"m6c 2c4",
    "addr:street":"Eglinton Ave W",
    "iso:country":"CA",
    "sg:address":"955 Eglinton Ave W",
    "sg:city":"York",
    "sg:classifiers":[
        {
            "category":"Restaurant",
            "type":"Food & Drink"
        }
    ],
    "sg:phone":"+1 416 783 6494",
    "sg:postcode":"M6C 2C4",
    "sg:province":"ON",
    "wof:name":"Jerusalem Restaurant",
    "wof:placetype":"venue"
},
  "geometry": {"coordinates":[-79.4289398193,43.7001533508],"type":"Point"}
}