{
  "type": "Feature",
  "properties": {
    "addr:full":"122 Main St S Carberry MB R0K 0H0",
    "addr:housenumber":"122",
    "addr:postcode":"r0k 0h0",
    "addr:street":"Main St S Carberry",
    "iso:country":"CA",
    "sg:address":"122 Main St S",
    "sg:city":"Carberry",
    "sg:classifiers":[
        {
            "category":"Organizations",
            "subcategory":"Professional Association",
            "type":"Services"
        }
    ],
    "sg:phone":"+1 204 834 6617",
    "sg:postcode":"R0K 0H0",
    "sg:province":"MB",
    "wof:name":"Carberry Plains Arts Council",
    "wof:placetype":"venue"
},
  "geometry": {"coordinates":[-99.359093,49.868328],"type":"Point"}
}