{
  "type": "Feature",
  "properties": {
    "addr:full":"50 Atlantic Ave Toronto ON M6K 1X8",
    "addr:housenumber":"50",
    "addr:postcode":"m6k 1x8",
    "addr:street":"Atlantic Ave",
    "iso:country":"CA",
    "sg:address":"50 Atlantic Ave",
    "sg:city":"Toronto",
    "sg:classifiers":[
        {
            "category":"Retail",
            "subcategory":"Repair Shop",
            "type":"Services"
        }
    ],
    "sg:phone":"+1 416 530 0680",
    "sg:postcode":"M6K 1X8",
    "sg:province":"ON",
    "sg:tags":[
        "welding"
    ],
    "wof:name":"Cad Welding",
    "wof:placetype":"venue"
},
  "geometry": {"coordinates":[-79.42063903810001,43.6380233765],"type":"Point"}
}