{
  "type": "Feature",
  "properties": {
    "addr:full":"3200 Pharmacy Ave Scarborough ON M1W 3J5",
    "addr:housenumber":"3200",
    "addr:postcode":"m1w 3j5",
    "addr:street":"Pharmacy Ave",
    "iso:country":"CA",
    "sg:address":"3200 Pharmacy Ave",
    "sg:city":"Scarborough",
    "sg:classifiers":[
        {
            "category":"Organizations",
            "subcategory":"Religious Organization",
            "type":"Services"
        }
    ],
    "sg:phone":"+1 416 499 2196",
    "sg:postcode":"M1W 3J5",
    "sg:province":"ON",
    "sg:tags":[
        "church"
    ],
    "wof:name":"Epiphany of Our Lord Church",
    "wof:placetype":"venue"
},
  "geometry": {"coordinates":[-79.3285980225,43.7990455627],"type":"Point"}
}