{
  "type": "Feature",
  "properties": {
    "addr:full":"381 Kent St # 4000 Ottawa ON K2P 2A8",
    "addr:housenumber":"381",
    "addr:postcode":"k2p 2a8",
    "addr:street":"Kent St # 4000",
    "iso:country":"CA",
    "sg:address":"381 Kent St # 4000",
    "sg:city":"Ottawa",
    "sg:classifiers":[
        {
            "category":"Real Estate",
            "subcategory":"Real Estate Agent",
            "type":"Services"
        }
    ],
    "sg:phone":"+1 613 241 6380",
    "sg:postcode":"K2P 2A8",
    "sg:province":"ON",
    "sg:tags":[
        "management"
    ],
    "wof:name":"Toth Equity Ltd",
    "wof:placetype":"venue"
},
  "geometry": {"coordinates":[-75.69696044920001,45.4128265381],"type":"Point"}
}