{
  "type": "Feature",
  "properties": {
    "addr:full":"5455 Yonge St North York ON M2N 5S1",
    "addr:housenumber":"5455",
    "addr:postcode":"m2n 5s1",
    "addr:street":"Yonge St",
    "iso:country":"CA",
    "sg:address":"5455 Yonge St",
    "sg:city":"North York",
    "sg:classifiers":[
        {
            "category":"Professional",
            "subcategory":"Employment Agencies",
            "type":"Services"
        }
    ],
    "sg:phone":"+1 416 222 0871",
    "sg:postcode":"M2N 5S1",
    "sg:province":"ON",
    "sg:tags":[
        "opportunity"
    ],
    "wof:name":"Temp Industrial Consulting CO",
    "wof:placetype":"venue"
},
  "geometry": {"coordinates":[-79.414688,43.777195],"type":"Point"}
}