{
  "type": "Feature",
  "properties": {
    "addr:full":"19442 Hwy 2 Summerstown ON K0C 2E0",
    "addr:housenumber":"19442",
    "addr:postcode":"k0c 2e0",
    "addr:street":"Hwy 2",
    "iso:country":"CA",
    "sg:address":"19442 Hwy 2",
    "sg:city":"Summerstown",
    "sg:classifiers":[
        {
            "category":"Recreation",
            "subcategory":"Marina",
            "type":"Entertainment"
        }
    ],
    "sg:phone":"+1 613 931 1443",
    "sg:postcode":"K0C 2E0",
    "sg:province":"ON",
    "wof:name":"Roger's Marina",
    "wof:placetype":"venue"
},
  "geometry": {"coordinates":[-74.54180100000001,45.072445],"type":"Point"}
}