{
  "type": "Feature",
  "properties": {
    "iso:country":"CA",
    "sg:address":"6500 Gottardo Crt",
    "sg:city":"Mississauga",
    "sg:classifiers":[
        {
            "category":"Wholesale",
            "subcategory":"Machinery & Supplies",
            "type":"Manufacturing & Wholesale Goods"
        }
    ],
    "sg:phone":"+1 905 795 1946",
    "sg:postcode":"L5T 2A2",
    "sg:province":"ON",
    "sg:tags":[
        "operated",
        "laundry"
    ],
    "wof:name":"Coinamatic Canada Inc",
    "wof:placetype":"venue"
},
  "geometry": {"coordinates":[-79.672996521,43.6544761658],"type":"Point"}
}