{
  "type": "Feature",
  "properties": {
    "addr:full":"123 3rd St St Louis SK S0J 2C0",
    "addr:housenumber":"123",
    "addr:postcode":"s0j 2c0",
    "addr:street":"3Rd St",
    "iso:country":"CA",
    "sg:address":"123 3rd St",
    "sg:city":"St Louis",
    "sg:classifiers":[
        {
            "category":"Recreation",
            "type":"Entertainment"
        }
    ],
    "sg:phone":"+1 306 422 8216",
    "sg:postcode":"S0J 2C0",
    "sg:province":"SK",
    "sg:tags":[
        "club",
        "curling"
    ],
    "wof:name":"St Louis Curling Rink",
    "wof:placetype":"venue"
},
  "geometry": {"coordinates":[-105.811576843,52.920211792],"type":"Point"}
}