{
  "type": "Feature",
  "properties": {
    "addr:full":"5935 Rue Louis-Hemon Montreal QC H2G 2K5",
    "addr:housenumber":"5935",
    "addr:postcode":"h2g 2k5",
    "addr:street":"Rue Louis-Hemon",
    "iso:country":"CA",
    "sg:address":"5935 Rue Louis-Hemon",
    "sg:city":"Montreal",
    "sg:classifiers":[
        {
            "category":"Personal",
            "subcategory":"Beauty Salon",
            "type":"Services"
        }
    ],
    "sg:phone":"+1 514 722 5302",
    "sg:postcode":"H2G 2K5",
    "sg:province":"QC",
    "sg:tags":[
        "school"
    ],
    "wof:name":"Institut DE Beaute Danielle",
    "wof:placetype":"venue"
},
  "geometry": {"coordinates":[-73.5882568359,45.5447654724],"type":"Point"}
}