{
  "type": "Feature",
  "properties": {
    "addr:full":"3025 Cote Rosemont Trois-Rivieres-Ouest QC G8Y 4R9",
    "addr:housenumber":"3025",
    "addr:postcode":"g8y 4r9",
    "addr:street":"Cote Rosemont",
    "iso:country":"CA",
    "sg:address":"3025 Cote Rosemont",
    "sg:city":"Trois-Rivieres-Ouest",
    "sg:classifiers":[
        {
            "category":"Retail",
            "subcategory":"Repair Shop",
            "type":"Services"
        }
    ],
    "sg:phone":"+1 819 370 8343",
    "sg:postcode":"G8Y 4R9",
    "sg:province":"QC",
    "sg:tags":[
        "jeweler"
    ],
    "wof:name":"Bijouterie L'Heure Juste",
    "wof:placetype":"venue"
},
  "geometry": {"coordinates":[-72.59326934809999,46.3322525024],"type":"Point"}
}