{
  "type": "Feature",
  "properties": {
    "addr:full":"2846 Highway 6 Lions Head ON N0H 1W0",
    "addr:housenumber":"2846",
    "addr:postcode":"n0h 1w0",
    "addr:street":"Highway 6 Lions Head",
    "iso:country":"CA",
    "sg:address":"2846 Highway 6",
    "sg:city":"Lions Head",
    "sg:classifiers":[
        {
            "category":"Building & Trades",
            "subcategory":"Plumbing",
            "type":"Services"
        }
    ],
    "sg:phone":"+1 519 793 3636",
    "sg:postcode":"N0H 1W0",
    "sg:province":"ON",
    "sg:tags":[
        "heating",
        "contractor"
    ],
    "wof:name":"Robert Martel Heating & Coolng",
    "wof:placetype":"venue"
},
  "geometry": {"coordinates":[-81.254204,44.98658],"type":"Point"}
}