{
  "type": "Feature",
  "properties": {
    "addr:full":"350 Legion Dr Quesnel BC V2J 2A3",
    "addr:housenumber":"350",
    "addr:postcode":"v2j 2a3",
    "addr:street":"Legion Dr",
    "iso:country":"CA",
    "sg:address":"350 Legion Dr",
    "sg:city":"Quesnel",
    "sg:classifiers":[
        {
            "category":"Wholesale",
            "subcategory":"Auto Parts",
            "type":"Manufacturing & Wholesale Goods"
        }
    ],
    "sg:phone":"+1 250 992 8474",
    "sg:postcode":"V2J 2A3",
    "sg:province":"BC",
    "sg:tags":[
        "equipment",
        "truck"
    ],
    "wof:name":"Johnston Equipment",
    "wof:placetype":"venue"
},
  "geometry": {"coordinates":[-122.49449199999999,52.974136],"type":"Point"}
}