{
  "type": "Feature",
  "properties": {
    "addr:full":"955 Lydiard Rd Centreville NS B0P 1J0",
    "addr:housenumber":"955",
    "addr:postcode":"b0p 1j0",
    "addr:street":"Lydiard Rd",
    "iso:country":"CA",
    "sg:address":"955 Lydiard Rd",
    "sg:city":"Centreville",
    "sg:classifiers":[
        {
            "category":"Food & Beverages",
            "subcategory":"Groceries & Convenience Stores",
            "type":"Retail Goods"
        }
    ],
    "sg:phone":"+1 902 678 6473",
    "sg:postcode":"B0P 1J0",
    "sg:province":"NS",
    "wof:name":"Centreville Kwik-Way",
    "wof:placetype":"venue"
},
  "geometry": {"coordinates":[-64.52295700000001,45.131042],"type":"Point"}
}