{
  "type": "Feature",
  "properties": {
    "addr:full":"460 Latimore Lake Rd Saint John NB E2N 1X3",
    "addr:housenumber":"460",
    "addr:postcode":"e2n 1x3",
    "addr:street":"Latimore Lake Rd",
    "iso:country":"CA",
    "sg:address":"460 Latimore Lake Rd",
    "sg:city":"Saint John",
    "sg:classifiers":[
        {
            "category":"Wholesale",
            "subcategory":"Construction Materials",
            "type":"Manufacturing & Wholesale Goods"
        }
    ],
    "sg:phone":"+1 506 696 6080",
    "sg:postcode":"E2N 1X3",
    "sg:province":"NB",
    "sg:tags":[
        "sand",
        "gravel"
    ],
    "wof:name":"Fundy Bay Sand & Gravel",
    "wof:placetype":"venue"
},
  "geometry": {"coordinates":[-65.94725800000001,45.301514],"type":"Point"}
}