{
  "type": "Feature",
  "properties": {
    "addr:full":"550 Boul Wilfrid-Hamel Quebec QC G1M 2S6",
    "addr:housenumber":"550",
    "addr:postcode":"g1m 2s6",
    "addr:street":"Boul Wilfrid-Hamel",
    "iso:country":"CA",
    "sg:address":"550 Boul Wilfrid-Hamel",
    "sg:city":"Quebec",
    "sg:classifiers":[
        {
            "category":"Wholesale",
            "subcategory":"Drugs",
            "type":"Manufacturing & Wholesale Goods"
        }
    ],
    "sg:phone":"+1 418 648 1919",
    "sg:postcode":"G1M 2S6",
    "sg:province":"QC",
    "sg:tags":[
        "preparation",
        "toilet"
    ],
    "wof:name":"Body Reform",
    "wof:placetype":"venue"
},
  "geometry": {"coordinates":[-71.24894,46.820374],"type":"Point"}
}