{
  "type": "Feature",
  "properties": {
    "iso:country":"CA",
    "sg:address":"5165 Yonge St",
    "sg:city":"North York",
    "sg:classifiers":[
        {
            "category":"Shopping",
            "subcategory":"Music",
            "type":"Retail Goods"
        }
    ],
    "sg:phone":"+1 416 222 2004",
    "sg:postcode":"M2N 5P5",
    "sg:province":"ON",
    "sg:tags":[
        "compact",
        "record",
        "disc",
        "tape"
    ],
    "wof:name":"Sonic Temple Compact Disc",
    "wof:placetype":"venue"
},
  "geometry": {"coordinates":[-79.412827,43.769703],"type":"Point"}
}