{
  "type": "Feature",
  "properties": {
    "addr:full":"372 Blyth Park Rd Colborne ON K0K 1S0",
    "addr:housenumber":"372",
    "addr:postcode":"k0k 1s0",
    "addr:street":"Blyth Park Rd",
    "iso:country":"CA",
    "sg:address":"372 Blyth Park Rd",
    "sg:city":"Colborne",
    "sg:classifiers":[
        {
            "category":"Autos & Motor Vehicles",
            "subcategory":"Automobile Sales",
            "type":"Retail Goods"
        }
    ],
    "sg:phone":"+1 905 355 3601",
    "sg:postcode":"K0K 1S0",
    "sg:province":"ON",
    "sg:tags":[
        "car",
        "dealer"
    ],
    "wof:name":"Gary's Place",
    "wof:placetype":"venue"
},
  "geometry": {"coordinates":[-77.83563995359999,44.0089035034],"type":"Point"}
}