{
  "type": "Feature",
  "properties": {
    "addr:full":"10122 100 St Peace River AB T8S 1S7",
    "addr:housenumber":"10122",
    "addr:postcode":"t8s 1s7",
    "addr:street":"100 St",
    "iso:country":"CA",
    "sg:address":"10122 100 St",
    "sg:city":"Peace River",
    "sg:classifiers":[
        {
            "category":"Shopping",
            "subcategory":"Books",
            "type":"Retail Goods"
        }
    ],
    "sg:phone":"+1 780 624 2489",
    "sg:postcode":"T8S 1S7",
    "sg:province":"AB",
    "sg:tags":[
        "dealer"
    ],
    "wof:name":"City Music Book World",
    "wof:placetype":"venue"
},
  "geometry": {"coordinates":[-117.290474,56.231987],"type":"Point"}
}