{
  "type": "Feature",
  "properties": {
    "iso:country":"CA",
    "sg:city":"Red Deer",
    "sg:classifiers":[
        {
            "category":"Health Services",
            "subcategory":"Optometrist",
            "type":"Services"
        }
    ],
    "sg:phone":"+1 403 343 2020",
    "sg:postcode":"T4N 3Y5",
    "sg:province":"AB",
    "wof:name":"Checkmate Optometry Clinic",
    "wof:placetype":"venue"
},
  "geometry": {"coordinates":[-113.813377,52.256485],"type":"Point"}
}