{
  "type": "Feature",
  "properties": {
    "addr:full":"160 Baseline Rd E Bowmanville ON L1C 1A2",
    "addr:housenumber":"160",
    "addr:postcode":"l1c 1a2",
    "addr:street":"Baseline Rd E",
    "iso:country":"CA",
    "sg:address":"160 Baseline Rd E",
    "sg:city":"Bowmanville",
    "sg:classifiers":[
        {
            "category":"Banks & Credit Unions",
            "subcategory":"Investment Brokerage",
            "type":"Services"
        }
    ],
    "sg:phone":"+1 905 623 5030",
    "sg:postcode":"L1C 1A2",
    "sg:province":"ON",
    "sg:tags":[
        "consultant",
        "planning",
        "financial"
    ],
    "wof:name":"E T Financial Svc Ltd",
    "wof:placetype":"venue"
},
  "geometry": {"coordinates":[-78.668442,43.903],"type":"Point"}
}