{
  "type": "Feature",
  "properties": {
    "addr:full":"Burnaby BC V5H 4L9",
    "addr:postcode":"v5h 4l9",
    "iso:country":"CA",
    "sg:city":"Burnaby",
    "sg:classifiers":[
        {
            "category":"Home & Garden",
            "subcategory":"Furniture",
            "type":"Retail Goods"
        }
    ],
    "sg:phone":"+1 604 434 1185",
    "sg:postcode":"V5H 4L9",
    "sg:province":"BC",
    "sg:tags":[
        "mattress"
    ],
    "wof:name":"Sleep Country Canada",
    "wof:placetype":"venue"
},
  "geometry": {"coordinates":[-122.999908447,49.2284431458],"type":"Point"}
}