{
  "type": "Feature",
  "properties": {
    "addr:full":"Scarborough ON M1C 3B2",
    "addr:postcode":"m1c 3b2",
    "iso:country":"CA",
    "sg:city":"Scarborough",
    "sg:classifiers":[
        {
            "category":"Health Services",
            "subcategory":"Doctor",
            "type":"Services"
        }
    ],
    "sg:phone":"+1 416 283 3700",
    "sg:postcode":"M1C 3B2",
    "sg:province":"ON",
    "sg:tags":[
        "physician",
        "surgeon"
    ],
    "wof:name":"Port Union Medical Ctr",
    "wof:placetype":"venue"
},
  "geometry": {"coordinates":[-79.13880899999999,43.779247],"type":"Point"}
}