{
  "type": "Feature",
  "properties": {
    "iso:country":"CA",
    "sg:city":"Vancouver",
    "sg:classifiers":[
        {
            "category":"Personal",
            "subcategory":"Beauty Salon",
            "type":"Services"
        }
    ],
    "sg:phone":"+1 604 681 7400",
    "sg:postcode":"V6C 2T6",
    "sg:province":"BC",
    "wof:name":"Jason-David Hair Studio",
    "wof:placetype":"venue"
},
  "geometry": {"coordinates":[-123.11795,49.284016],"type":"Point"}
}