{
  "type": "Feature",
  "properties": {
    "addr:full":"109 Carleton St Woodstock NB E7M 1E3",
    "addr:housenumber":"109",
    "addr:postcode":"e7m 1e3",
    "addr:street":"Carleton St",
    "iso:country":"CA",
    "sg:address":"109 Carleton St",
    "sg:city":"Woodstock",
    "sg:classifiers":[
        {
            "category":"Organizations",
            "subcategory":"Community Association",
            "type":"Services"
        }
    ],
    "sg:phone":"+1 506 328 2368",
    "sg:postcode":"E7M 1E3",
    "sg:province":"NB",
    "sg:tags":[
        "club"
    ],
    "wof:name":"Royal Canadian Legion",
    "wof:placetype":"venue"
},
  "geometry": {"coordinates":[-67.571198,46.1502],"type":"Point"}
}