{
  "type": "Feature",
  "properties": {
    "addr:full":"Beaverton ON L0K 1A0",
    "addr:postcode":"l0k 1a0",
    "iso:country":"CA",
    "sg:city":"Beaverton",
    "sg:classifiers":[
        {
            "category":"Building & Trades",
            "subcategory":"Construction",
            "type":"Services"
        }
    ],
    "sg:phone":"+1 705 426 7067",
    "sg:postcode":"L0K 1A0",
    "sg:province":"ON",
    "sg:tags":[
        "excavating",
        "contractor"
    ],
    "wof:name":"Vieveen's Landscaping Constr",
    "wof:placetype":"venue"
},
  "geometry": {"coordinates":[-79.1363372803,44.4384269714],"type":"Point"}
}