{
  "type": "Feature",
  "properties": {
    "addr:full":"463 Nightingale Ave London ON N5W 4C4",
    "addr:housenumber":"463",
    "addr:postcode":"n5w 4c4",
    "addr:street":"Nightingale Ave",
    "iso:country":"CA",
    "sg:address":"463 Nightingale Ave",
    "sg:city":"London",
    "sg:classifiers":[
        {
            "category":"Manufacturing",
            "subcategory":"Metals",
            "type":"Manufacturing & Wholesale Goods"
        }
    ],
    "sg:phone":"+1 519 457 0603",
    "sg:postcode":"N5W 4C4",
    "sg:province":"ON",
    "sg:tags":[
        "steel"
    ],
    "wof:name":"West Metal Fabricators Ltd",
    "wof:placetype":"venue"
},
  "geometry": {"coordinates":[-81.2130279541,42.995426178],"type":"Point"}
}