{
  "type": "Feature",
  "properties": {
    "addr:full":"50 Delong Dr Moncton NB E1E 4G3",
    "addr:housenumber":"50",
    "addr:postcode":"e1e 4g3",
    "addr:street":"Delong Dr",
    "iso:country":"CA",
    "sg:address":"50 Delong Dr",
    "sg:city":"Moncton",
    "sg:classifiers":[
        {
            "category":"Manufacturing",
            "subcategory":"Tools & Machinery",
            "type":"Manufacturing & Wholesale Goods"
        }
    ],
    "sg:phone":"+1 506 859 1680",
    "sg:postcode":"E1E 4G3",
    "sg:province":"NB",
    "sg:tags":[
        "equipment",
        "hydraulic",
        "supply"
    ],
    "wof:name":"Hydrostatic Services Ltd",
    "wof:placetype":"venue"
},
  "geometry": {"coordinates":[-64.8407897949,46.0858268738],"type":"Point"}
}