{
  "type": "Feature",
  "properties": {
    "addr:full":"PO Box 3964 STN D Edmonton AB T5L 4K1",
    "addr:housenumber":"po",
    "addr:postcode":"t5l 4k1",
    "addr:street":"Box 3964 Stn D",
    "iso:country":"CA",
    "sg:address":"PO Box 3964 STN D",
    "sg:city":"Edmonton",
    "sg:classifiers":[
        {
            "category":"Building & Trades",
            "subcategory":"Electrical",
            "type":"Services"
        }
    ],
    "sg:phone":"+1 780 963 0922",
    "sg:postcode":"T5L 4K1",
    "sg:province":"AB",
    "sg:tags":[
        "electric",
        "contractor"
    ],
    "wof:name":"Tamber Electric Ltd",
    "wof:placetype":"venue"
},
  "geometry": {"coordinates":[-113.490371704,53.5462188721],"type":"Point"}
}