{
  "type": "Feature",
  "properties": {
    "addr:full":"Saint-Timothee QC J6S 1E4",
    "addr:postcode":"j6s 1e4",
    "iso:country":"CA",
    "sg:city":"Saint-Timothee",
    "sg:classifiers":[
        {
            "category":"Wholesale",
            "subcategory":"Groceries",
            "type":"Manufacturing & Wholesale Goods"
        }
    ],
    "sg:phone":"+1 450 373 5141",
    "sg:postcode":"J6S 1E4",
    "sg:province":"QC",
    "sg:tags":[
        "grocer"
    ],
    "wof:name":"Presto Epiceries Ltee",
    "wof:placetype":"venue"
},
  "geometry": {"coordinates":[-74.0979919434,45.2720298767],"type":"Point"}
}