{
  "type": "Feature",
  "properties": {
    "addr:full":"Calgary AB T2H 2K6",
    "addr:postcode":"t2h 2k6",
    "iso:country":"CA",
    "sg:city":"Calgary",
    "sg:classifiers":[
        {
            "category":"Building & Trades",
            "subcategory":"Construction",
            "type":"Services"
        }
    ],
    "sg:phone":"+1 403 685 2284",
    "sg:postcode":"T2H 2K6",
    "sg:province":"AB",
    "sg:tags":[
        "repairing",
        "remodeling",
        "contractor"
    ],
    "wof:name":"Suite Life",
    "wof:placetype":"venue"
},
  "geometry": {"coordinates":[-114.07189200000001,50.991219],"type":"Point"}
}