{
  "type": "Feature",
  "properties": {
    "iso:country":"CA",
    "sg:city":"Alma",
    "sg:classifiers":[
        {
            "category":"Government",
            "subcategory":"Office",
            "type":"Public Place"
        }
    ],
    "sg:phone":"+1 418 668 6149",
    "sg:postcode":"G8B 7A6",
    "sg:province":"QC",
    "wof:name":"Quebec Deputes Provinciaux",
    "wof:placetype":"venue"
},
  "geometry": {"coordinates":[-71.6523513794,48.5499267578],"type":"Point"}
}