{
  "type": "Feature",
  "properties": {
    "addr:full":"Highway 14 Perdue SK S0K 3C0",
    "addr:postcode":"s0k 3c0",
    "addr:street":"Highway 14 Perdue",
    "iso:country":"CA",
    "sg:address":"Highway 14",
    "sg:city":"Perdue",
    "sg:classifiers":[
        {
            "category":"Wholesale",
            "subcategory":"Machinery & Supplies",
            "type":"Manufacturing & Wholesale Goods"
        }
    ],
    "sg:phone":"+1 306 237 4272",
    "sg:postcode":"S0K 3C0",
    "sg:province":"SK",
    "sg:tags":[
        "engine"
    ],
    "wof:name":"Moody's Equipment Ltd",
    "wof:placetype":"venue"
},
  "geometry": {"coordinates":[-107.542266846,52.0555114746],"type":"Point"}
}