{
  "type": "Feature",
  "properties": {
    "iso:country":"CA",
    "sg:address":"SE 9-20-1W",
    "sg:city":"Inwood",
    "sg:classifiers":[
        {
            "category":"Government",
            "subcategory":"Office",
            "type":"Public Place"
        }
    ],
    "sg:phone":"+1 204 278 3445",
    "sg:postcode":"R0C 1P0",
    "sg:province":"MB",
    "wof:name":"Canada Community Pastures",
    "wof:placetype":"venue"
},
  "geometry": {"coordinates":[-97.497444,50.507839],"type":"Point"}
}