{
  "type": "Feature",
  "properties": {
    "addr:full":"5583 Ch DE L'Aeroport Valcourt QC J0E 2L0",
    "addr:postcode":"5583;j0e 2l0",
    "addr:street":"Ch De L'Aeroport",
    "iso:country":"CA",
    "sg:address":"5583 Ch DE L'Aeroport",
    "sg:city":"Valcourt",
    "sg:classifiers":[
        {
            "category":"Shopping",
            "subcategory":"Bicycles & Sporting Goods",
            "type":"Retail Goods"
        }
    ],
    "sg:phone":"+1 450 532 2945",
    "sg:postcode":"J0E 2L0",
    "sg:province":"QC",
    "sg:tags":[
        "parachute"
    ],
    "wof:name":"Sea-Bow Intl Inc",
    "wof:placetype":"venue"
},
  "geometry": {"coordinates":[-72.3921508789,45.027431488],"type":"Point"}
}