{
  "type": "Feature",
  "properties": {
    "addr:full":"100 Cameron St Moncton NB E1C 5Y6",
    "addr:housenumber":"100",
    "addr:postcode":"e1c 5y6",
    "addr:street":"Cameron St",
    "iso:country":"CA",
    "sg:address":"100 Cameron St",
    "sg:city":"Moncton",
    "sg:classifiers":[
        {
            "category":"Professional",
            "subcategory":"Accounting & Tax Preparation",
            "type":"Services"
        }
    ],
    "sg:phone":"+1 506 862 1991",
    "sg:postcode":"E1C 5Y6",
    "sg:province":"NB",
    "sg:tags":[
        "accountant"
    ],
    "wof:name":"Close, David A CA",
    "wof:placetype":"venue"
},
  "geometry": {"coordinates":[-64.788864,46.0881],"type":"Point"}
}