{
  "type": "Feature",
  "properties": {
    "addr:full":"196 Mckenzie Ave Moncton NB E1C 7Z3",
    "addr:housenumber":"196",
    "addr:postcode":"e1c 7z3",
    "addr:street":"Mckenzie Ave",
    "iso:country":"CA",
    "sg:address":"196 Mckenzie Ave",
    "sg:city":"Moncton",
    "sg:classifiers":[
        {
            "category":"Wholesale",
            "subcategory":"Machinery & Supplies",
            "type":"Manufacturing & Wholesale Goods"
        }
    ],
    "sg:phone":"+1 506 384 6186",
    "sg:postcode":"E1C 7Z3",
    "sg:province":"NB",
    "sg:tags":[
        "machine",
        "sewing"
    ],
    "wof:name":"Bourque Sewing Machines",
    "wof:placetype":"venue"
},
  "geometry": {"coordinates":[-64.824455,46.102734],"type":"Point"}
}