{
  "type": "Feature",
  "properties": {
    "addr:full":"7475 Rue Sherbrooke O Montreal QC H4B 1S3",
    "addr:housenumber":"7475",
    "addr:postcode":"h4b 1s3",
    "addr:street":"Rue Sherbrooke O",
    "iso:country":"CA",
    "sg:address":"7475 Rue Sherbrooke O",
    "sg:city":"Montreal",
    "sg:classifiers":[
        {
            "category":"Education",
            "subcategory":"School",
            "type":"Public Place"
        }
    ],
    "sg:phone":"+1 514 489 7287",
    "sg:postcode":"H4B 1S3",
    "sg:province":"QC",
    "wof:name":"College Prep Intl",
    "wof:placetype":"venue"
},
  "geometry": {"coordinates":[-73.538772583,45.5907249451],"type":"Point"}
}