{
  "type": "Feature",
  "properties": {
    "iso:country":"CA",
    "sg:address":"1067 Hwy 1",
    "sg:city":"Mount Uniacke",
    "sg:classifiers":[
        {
            "category":"Building & Trades",
            "subcategory":"Construction",
            "type":"Services"
        }
    ],
    "sg:phone":"+1 902 866 1300",
    "sg:postcode":"B0N 1Z0",
    "sg:province":"NS",
    "sg:tags":[
        "maker",
        "cabinet"
    ],
    "wof:name":"Custom Millwork Atlantic Inc",
    "wof:placetype":"venue"
},
  "geometry": {"coordinates":[-63.8340301514,44.8959693909],"type":"Point"}
}