{
  "type": "Feature",
  "properties": {
    "iso:country":"CA",
    "sg:address":"496 Brant St",
    "sg:city":"Burlington",
    "sg:classifiers":[
        {
            "category":"Manufacturing",
            "subcategory":"Textiles",
            "type":"Manufacturing & Wholesale Goods"
        }
    ],
    "sg:phone":"+1 905 632 5197",
    "sg:postcode":"L7R 2G4",
    "sg:province":"ON",
    "sg:tags":[
        "upholsterer",
        "mattress"
    ],
    "wof:name":"Fiberglass & Foam Supply CO",
    "wof:placetype":"venue"
},
  "geometry": {"coordinates":[-79.8005065918,43.3273658752],"type":"Point"}
}