{
  "type": "Feature",
  "properties": {
    "addr:full":"115 Rue Fortier Sainte-Sabine QC J0J 2B0",
    "addr:housenumber":"115",
    "addr:postcode":"j0j 2b0",
    "addr:street":"Rue Fortier",
    "iso:country":"CA",
    "sg:address":"115 Rue Fortier",
    "sg:city":"Sainte-Sabine",
    "sg:classifiers":[
        {
            "category":"Professional",
            "subcategory":"Business Services",
            "type":"Services"
        }
    ],
    "sg:phone":"+1 450 293 5019",
    "sg:postcode":"J0J 2B0",
    "sg:province":"QC",
    "sg:tags":[
        "water",
        "treatment"
    ],
    "wof:name":"Groupe Guerin Inc",
    "wof:placetype":"venue"
},
  "geometry": {"coordinates":[-72.99048614500001,45.2511291504],"type":"Point"}
}