{
  "type": "Feature",
  "properties": {
    "iso:country":"CA",
    "sg:address":"525 1 Rang E",
    "sg:city":"Saint-Joachim-DE-Shefford",
    "sg:classifiers":[
        {
            "category":"Manufacturing",
            "subcategory":"Tools & Machinery",
            "type":"Manufacturing & Wholesale Goods"
        }
    ],
    "sg:phone":"+1 450 539 0250",
    "sg:postcode":"J0E 2G0",
    "sg:province":"QC",
    "sg:tags":[
        "machine",
        "shop"
    ],
    "wof:name":"Mecanifab Enr",
    "wof:placetype":"venue"
},
  "geometry": {"coordinates":[-72.51805877690001,45.4514198303],"type":"Point"}
}