{
  "type": "Feature",
  "properties": {
    "addr:full":"412 1st Ave Field BC V0A 1G0",
    "addr:housenumber":"412",
    "addr:postcode":"v0a 1g0",
    "addr:street":"1St Ave",
    "iso:country":"CA",
    "sg:address":"412 1st Ave",
    "sg:city":"Field",
    "sg:classifiers":[
        {
            "category":"Building & Trades",
            "subcategory":"Landscaping Services",
            "type":"Services"
        }
    ],
    "sg:phone":"+1 250 343 6366",
    "sg:postcode":"V0A 1G0",
    "sg:province":"BC",
    "sg:tags":[
        "landscape",
        "contractor"
    ],
    "wof:name":"High Country Landscaping",
    "wof:placetype":"venue"
},
  "geometry": {"coordinates":[-116.481658935,51.4040222168],"type":"Point"}
}