{
  "type": "Feature",
  "properties": {
    "addr:full":"Riviere-Du-Loup QC G5R 1G9",
    "addr:postcode":"g5r 1g9",
    "iso:country":"CA",
    "sg:city":"Riviere-Du-Loup",
    "sg:classifiers":[
        {
            "category":"Manufacturing",
            "subcategory":"Metals",
            "type":"Manufacturing & Wholesale Goods"
        }
    ],
    "sg:phone":"+1 418 862 2457",
    "sg:postcode":"G5R 1G9",
    "sg:province":"QC",
    "sg:tags":[
        "supply",
        "equipment",
        "fiber",
        "system",
        "telephone"
    ],
    "wof:name":"Inter-Select Inc",
    "wof:placetype":"venue"
},
  "geometry": {"coordinates":[-69.5392074585,47.838142395],"type":"Point"}
}