{
  "type": "Feature",
  "properties": {
    "addr:full":"2459 Dundas St W Toronto ON M6P 1X3",
    "addr:housenumber":"2459",
    "addr:postcode":"m6p 1x3",
    "addr:street":"Dundas St W",
    "iso:country":"CA",
    "sg:address":"2459 Dundas St W",
    "sg:city":"Toronto",
    "sg:classifiers":[
        {
            "category":"Organizations",
            "subcategory":"Professional Association",
            "type":"Services"
        }
    ],
    "sg:phone":"+1 416 539 9928",
    "sg:postcode":"M6P 1X3",
    "sg:province":"ON",
    "wof:name":"Zumunta Cultural Assn",
    "wof:placetype":"venue"
},
  "geometry": {"coordinates":[-79.45362900000001,43.659389],"type":"Point"}
}