{
  "type": "Feature",
  "properties": {
    "iso:country":"CA",
    "sg:address":"1340 Kingston Rd",
    "sg:city":"Pickering",
    "sg:classifiers":[
        {
            "category":"Personal",
            "subcategory":"Beauty Salon",
            "type":"Services"
        }
    ],
    "sg:phone":"+1 905 831 3800",
    "sg:postcode":"L1V 3M9",
    "sg:province":"ON",
    "wof:name":"Topcuts",
    "wof:placetype":"venue"
},
  "geometry": {"coordinates":[-79.0884017944,43.8374862671],"type":"Point"}
}