{
  "type": "Feature",
  "properties": {
    "addr:full":"Vanier QC G1M 3R1",
    "addr:postcode":"g1m 3r1",
    "iso:country":"CA",
    "sg:city":"Vanier",
    "sg:classifiers":[
        {
            "category":"Travel",
            "subcategory":"Hotels & Motels",
            "type":"Entertainment"
        }
    ],
    "sg:phone":"+1 418 688 3888",
    "sg:postcode":"G1M 3R1",
    "sg:province":"QC",
    "wof:name":"Hotel Le Dauphin Quebec",
    "wof:placetype":"venue"
},
  "geometry": {"coordinates":[-71.282692,46.828094],"type":"Point"}
}