{
  "type": "Feature",
  "properties": {
    "addr:full":"1603 Rue Ontario E Montreal QC H2L 1S6",
    "addr:housenumber":"1603",
    "addr:postcode":"h2l 1s6",
    "addr:street":"Rue Ontario E",
    "iso:country":"CA",
    "sg:address":"1603 Rue Ontario E",
    "sg:city":"Montreal",
    "sg:classifiers":[
        {
            "category":"Bars & Pubs",
            "type":"Food & Drink"
        }
    ],
    "sg:phone":"+1 514 525 4251",
    "sg:postcode":"H2L 1S6",
    "sg:province":"QC",
    "sg:tags":[
        "lounge",
        "cocktail"
    ],
    "wof:name":"Citi Bar",
    "wof:placetype":"venue"
},
  "geometry": {"coordinates":[-73.5600891113,45.5250205994],"type":"Point"}
}