{
  "type": "Feature",
  "properties": {
    "iso:country":"CA",
    "sg:address":"1285 Erie St E",
    "sg:city":"Windsor",
    "sg:classifiers":[
        {
            "category":"Professional",
            "subcategory":"Accounting & Tax Preparation",
            "type":"Services"
        }
    ],
    "sg:phone":"+1 519 985 1117",
    "sg:postcode":"N9A 3Z6",
    "sg:province":"ON",
    "sg:tags":[
        "return",
        "filing"
    ],
    "wof:name":"Nizam Accounting & Tax Svc",
    "wof:placetype":"venue"
},
  "geometry": {"coordinates":[-83.01583099370001,42.3151245117],"type":"Point"}
}