{
  "type": "Feature",
  "properties": {
    "addr:full":"120 Boul Harbourview Bathurst NB E2A 7R2",
    "addr:housenumber":"120",
    "addr:postcode":"e2a 7r2",
    "addr:street":"Boul Harbourview",
    "iso:country":"CA",
    "sg:address":"120 Boul Harbourview",
    "sg:city":"Bathurst",
    "sg:classifiers":[
        {
            "category":"Government",
            "subcategory":"Office",
            "type":"Public Place"
        }
    ],
    "sg:phone":"+1 506 548 7186",
    "sg:postcode":"E2A 7R2",
    "sg:province":"NB",
    "wof:name":"Canada Emploi",
    "wof:placetype":"venue"
},
  "geometry": {"coordinates":[-65.657326,47.621529],"type":"Point"}
}