{
  "type": "Feature",
  "properties": {
    "addr:full":"853 Kebir Pl Winnipeg MB R3T 1X1",
    "addr:housenumber":"853",
    "addr:postcode":"r3t 1x1",
    "addr:street":"Kebir Pl",
    "iso:country":"CA",
    "sg:address":"853 Kebir Pl",
    "sg:city":"Winnipeg",
    "sg:classifiers":[
        {
            "category":"Autos & Motor Vehicles",
            "subcategory":"Boat Sales",
            "type":"Retail Goods"
        }
    ],
    "sg:phone":"+1 204 795 6967",
    "sg:postcode":"R3T 1X1",
    "sg:province":"MB",
    "sg:tags":[
        "outboard"
    ],
    "wof:name":"Putt Putt Parts",
    "wof:placetype":"venue"
},
  "geometry": {"coordinates":[-97.1441955566,49.8345756531],"type":"Point"}
}