{
  "type": "Feature",
  "properties": {
    "iso:country":"CA",
    "sg:city":"Vancouver",
    "sg:classifiers":[
        {
            "category":"Food & Beverages",
            "subcategory":"Bakery",
            "type":"Retail Goods"
        }
    ],
    "sg:phone":"+1 604 872 5212",
    "sg:postcode":"V5Z 3X7",
    "sg:province":"BC",
    "sg:tags":[
        "baker"
    ],
    "wof:name":"Cinnzeo",
    "wof:placetype":"venue"
},
  "geometry": {"coordinates":[-123.11640167199999,49.2606010437],"type":"Point"}
}