{
  "type": "Feature",
  "properties": {
    "addr:full":"214 Quebec St Schreiber ON P0T 2S0",
    "addr:housenumber":"214",
    "addr:postcode":"p0t 2s0",
    "addr:street":"Quebec St",
    "iso:country":"CA",
    "sg:address":"214 Quebec St",
    "sg:city":"Schreiber",
    "sg:classifiers":[
        {
            "category":"Home & Garden",
            "subcategory":"Building Materials",
            "type":"Retail Goods"
        }
    ],
    "sg:phone":"+1 807 824 2639",
    "sg:postcode":"P0T 2S0",
    "sg:province":"ON",
    "sg:tags":[
        "glass",
        "window",
        "plate"
    ],
    "wof:name":"Zap's Auto Glass",
    "wof:placetype":"venue"
},
  "geometry": {"coordinates":[-87.26290899999999,48.809139],"type":"Point"}
}