{
  "type": "Feature",
  "properties": {
    "addr:full":"1185 Robson St Vancouver BC V6E 1B5",
    "addr:housenumber":"1185",
    "addr:postcode":"v6e 1b5",
    "addr:street":"Robson St",
    "iso:country":"CA",
    "sg:address":"1185 Robson St",
    "sg:city":"Vancouver",
    "sg:classifiers":[
        {
            "category":"Restaurant",
            "type":"Food & Drink"
        }
    ],
    "sg:phone":"+1 604 669 0020",
    "sg:postcode":"V6E 1B5",
    "sg:province":"BC",
    "wof:name":"Earl's Restaurant",
    "wof:placetype":"venue"
},
  "geometry": {"coordinates":[-123.12637329099999,49.2858009338],"type":"Point"}
}