{
  "type": "Feature",
  "properties": {
    "iso:country":"CA",
    "sg:address":"1700 Av Emile-Legrand",
    "sg:city":"Montreal",
    "sg:classifiers":[
        {
            "category":"Manufacturing",
            "subcategory":"Retail Goods",
            "type":"Manufacturing & Wholesale Goods"
        }
    ],
    "sg:phone":"+1 514 257 9197",
    "sg:postcode":"H1N 3H4",
    "sg:province":"QC",
    "sg:tags":[
        "assembly",
        "fabricating"
    ],
    "wof:name":"Gdl Electro",
    "wof:placetype":"venue"
},
  "geometry": {"coordinates":[-73.518318,45.579857],"type":"Point"}
}