{
  "type": "Feature",
  "properties": {
    "addr:full":"8740 Boul Pie-Ix Montreal QC H1Z 3V1",
    "addr:housenumber":"8740",
    "addr:postcode":"h1z 3v1",
    "addr:street":"Boul Pie-Ix",
    "iso:country":"CA",
    "sg:address":"8740 Boul Pie-Ix",
    "sg:city":"Montreal",
    "sg:classifiers":[
        {
            "category":"Professional",
            "subcategory":"Management & Consulting",
            "type":"Services"
        }
    ],
    "sg:phone":"+1 514 593 5755",
    "sg:postcode":"H1Z 3V1",
    "sg:province":"QC",
    "sg:tags":[
        "control",
        "consultant",
        "quality"
    ],
    "wof:name":"Laboratoire D'Essair Mqltch",
    "wof:placetype":"venue"
},
  "geometry": {"coordinates":[-73.613831,45.576237],"type":"Point"}
}