{
  "type": "Feature",
  "properties": {
    "addr:full":"5025 Rue Ramsay Saint-Hubert QC J3Y 2S3",
    "addr:housenumber":"5025",
    "addr:postcode":"j3y 2s3",
    "addr:street":"Rue Ramsay",
    "iso:country":"CA",
    "sg:address":"5025 Rue Ramsay",
    "sg:city":"Saint-Hubert",
    "sg:classifiers":[
        {
            "category":"Wholesale",
            "subcategory":"Machinery & Supplies",
            "type":"Manufacturing & Wholesale Goods"
        }
    ],
    "sg:phone":"+1 450 445 0050",
    "sg:postcode":"J3Y 2S3",
    "sg:province":"QC",
    "sg:tags":[
        "steel",
        "equipment",
        "pile",
        "driving"
    ],
    "wof:name":"Tuyaux & Material DE Fondation",
    "wof:placetype":"venue"
},
  "geometry": {"coordinates":[-73.42199707029999,45.4711303711],"type":"Point"}
}