{
  "type": "Feature",
  "properties": {
    "iso:country":"CA",
    "sg:address":"1000 Rue Saint-Jacques",
    "sg:city":"Montreal",
    "sg:classifiers":[
        {
            "category":"Recreation",
            "type":"Entertainment"
        }
    ],
    "sg:phone":"+1 514 872 4530",
    "sg:postcode":"H3C 1G7",
    "sg:province":"QC",
    "sg:tags":[
        "provincial",
        "pool",
        "parks",
        "swimming"
    ],
    "wof:name":"Montreal Planetarium",
    "wof:placetype":"venue"
},
  "geometry": {"coordinates":[-73.564667,45.496803],"type":"Point"}
}