{
  "type": "Feature",
  "properties": {
    "iso:country":"CA",
    "sg:address":"15 Louis St",
    "sg:city":"Brockville",
    "sg:classifiers":[
        {
            "category":"Travel",
            "subcategory":"Travel Agent",
            "type":"Entertainment"
        }
    ],
    "sg:phone":"+1 613 342 4791",
    "sg:postcode":"K6V 6E7",
    "sg:province":"ON",
    "sg:tags":[
        "agency",
        "bureau"
    ],
    "wof:name":"Howard Travel",
    "wof:placetype":"venue"
},
  "geometry": {"coordinates":[-75.6894226074,44.5946807861],"type":"Point"}
}