{
  "type": "Feature",
  "properties": {
    "addr:full":"2000 Hartley Ave Coquitlam BC V3K 6W5",
    "addr:housenumber":"2000",
    "addr:postcode":"v3k 6w5",
    "addr:street":"Hartley Ave",
    "iso:country":"CA",
    "sg:address":"2000 Hartley Ave",
    "sg:city":"Coquitlam",
    "sg:classifiers":[
        {
            "category":"Manufacturing",
            "subcategory":"Wood Products",
            "type":"Manufacturing & Wholesale Goods"
        }
    ],
    "sg:phone":"+1 604 525 3900",
    "sg:postcode":"V3K 6W5",
    "sg:province":"BC",
    "sg:tags":[
        "picture",
        "frame"
    ],
    "wof:name":"Art in Motion",
    "wof:placetype":"venue"
},
  "geometry": {"coordinates":[-122.83955400000001,49.225952],"type":"Point"}
}