{
  "type": "Feature",
  "properties": {
    "addr:full":"303 York Mills Rd North York ON M2L 1L3",
    "addr:housenumber":"303",
    "addr:postcode":"m2l 1l3",
    "addr:street":"York Mills Rd",
    "iso:country":"CA",
    "sg:address":"303 York Mills Rd",
    "sg:city":"North York",
    "sg:classifiers":[
        {
            "category":"Wholesale",
            "subcategory":"Meat",
            "type":"Manufacturing & Wholesale Goods"
        }
    ],
    "sg:phone":"+1 416 447 0310",
    "sg:postcode":"M2L 1L3",
    "sg:province":"ON",
    "sg:tags":[
        "butchering"
    ],
    "wof:name":"Nortown Foods Ltd",
    "wof:placetype":"venue"
},
  "geometry": {"coordinates":[-79.38458300000001,43.747803],"type":"Point"}
}