{
  "type": "Feature",
  "properties": {
    "iso:country":"CA",
    "sg:address":"27 Buell St",
    "sg:city":"Brockville",
    "sg:classifiers":[
        {
            "category":"Restaurant",
            "type":"Food & Drink"
        }
    ],
    "sg:phone":"+1 613 345 2623",
    "sg:postcode":"K6V 4Y1",
    "sg:province":"ON",
    "wof:name":"Buell St Bistro",
    "wof:placetype":"venue"
},
  "geometry": {"coordinates":[-75.6867904663,44.5895614624],"type":"Point"}
}