{
  "type": "Feature",
  "properties": {
    "addr:full":"98 Geikie St Jasper AB T0E 1E0",
    "addr:housenumber":"98",
    "addr:postcode":"t0e 1e0",
    "addr:street":"Geikie St",
    "iso:country":"CA",
    "sg:address":"98 Geikie St",
    "sg:city":"Jasper",
    "sg:classifiers":[
        {
            "category":"Restaurant",
            "type":"Food & Drink"
        }
    ],
    "sg:phone":"+1 780 852 3232",
    "sg:postcode":"T0E 1E0",
    "sg:province":"AB",
    "wof:name":"Inn Restaurant",
    "wof:placetype":"venue"
},
  "geometry": {"coordinates":[-118.080528,52.884892],"type":"Point"}
}