{
  "type": "Feature",
  "properties": {
    "addr:full":"7191 Horne St Mission BC V2V 3X9",
    "addr:housenumber":"7191",
    "addr:postcode":"v2v 3x9",
    "addr:street":"Horne St",
    "iso:country":"CA",
    "sg:address":"7191 Horne St",
    "sg:city":"Mission",
    "sg:classifiers":[
        {
            "category":"Autos & Motor Vehicles",
            "subcategory":"Automobile Sales",
            "type":"Retail Goods"
        }
    ],
    "sg:phone":"+1 604 826 9936",
    "sg:postcode":"V2V 3X9",
    "sg:province":"BC",
    "sg:tags":[
        "car",
        "dealer"
    ],
    "wof:name":"Mission Bridge Motors",
    "wof:placetype":"venue"
},
  "geometry": {"coordinates":[-122.301223755,49.1322975159],"type":"Point"}
}