{
  "type": "Feature",
  "properties": {
    "addr:full":"5918 50 St Taber AB T1G 1J6",
    "addr:housenumber":"5918",
    "addr:postcode":"t1g 1j6",
    "addr:street":"50 St",
    "iso:country":"CA",
    "sg:address":"5918 50 St",
    "sg:city":"Taber",
    "sg:classifiers":[
        {
            "category":"Shopping",
            "type":"Retail Goods"
        }
    ],
    "sg:phone":"+1 403 223 2575",
    "sg:postcode":"T1G 1J6",
    "sg:province":"AB",
    "sg:tags":[
        "trophy",
        "sporting",
        "medal",
        "award"
    ],
    "wof:name":"Harding's Sporting Goods",
    "wof:placetype":"venue"
},
  "geometry": {"coordinates":[-112.14981842,49.7954940796],"type":"Point"}
}