{
  "type": "Feature",
  "properties": {
    "iso:country":"CA",
    "sg:address":"87-95 West",
    "sg:city":"St Anthony",
    "sg:classifiers":[
        {
            "category":"Government",
            "subcategory":"Office",
            "type":"Public Place"
        }
    ],
    "sg:phone":"+1 709 454 3453",
    "sg:postcode":"A0K 4S0",
    "sg:province":"NL",
    "sg:tags":[
        "village"
    ],
    "wof:name":"St Anthony Town Council",
    "wof:placetype":"venue"
},
  "geometry": {"coordinates":[-55.5950393677,51.3686218262],"type":"Point"}
}