{
  "type": "Feature",
  "properties": {
    "addr:full":"Scarborough ON M1B 4Y7",
    "addr:postcode":"m1b 4y7",
    "iso:country":"CA",
    "sg:city":"Scarborough",
    "sg:classifiers":[
        {
            "category":"Health Services",
            "subcategory":"Doctor",
            "type":"Services"
        }
    ],
    "sg:phone":"+1 416 297 5513",
    "sg:postcode":"M1B 4Y7",
    "sg:province":"ON",
    "sg:tags":[
        "dentist"
    ],
    "wof:name":"Jandoo, Ken DDS",
    "wof:placetype":"venue"
},
  "geometry": {"coordinates":[-79.22133599999999,43.805531],"type":"Point"}
}