{
  "type": "Feature",
  "properties": {
    "addr:full":"Vancouver BC V6G 1R8",
    "addr:postcode":"v6g 1r8",
    "iso:country":"CA",
    "sg:city":"Vancouver",
    "sg:classifiers":[
        {
            "category":"Professional",
            "subcategory":"Management & Consulting",
            "type":"Services"
        }
    ],
    "sg:phone":"+1 604 692 0888",
    "sg:postcode":"V6G 1R8",
    "sg:province":"BC",
    "sg:tags":[
        "consultant",
        "business"
    ],
    "wof:name":"Kyosei Consulting Intl",
    "wof:placetype":"venue"
},
  "geometry": {"coordinates":[-123.14389038100001,49.2912139893],"type":"Point"}
}