{
  "type": "Feature",
  "properties": {
    "addr:full":"Mississauga ON L5A 3K6",
    "addr:postcode":"l5a 3k6",
    "iso:country":"CA",
    "sg:city":"Mississauga",
    "sg:classifiers":[
        {
            "category":"Banks & Credit Unions",
            "subcategory":"Investment Brokerage",
            "type":"Services"
        }
    ],
    "sg:phone":"+1 905 275 5250",
    "sg:postcode":"L5A 3K6",
    "sg:province":"ON",
    "wof:name":"Mig Inc",
    "wof:placetype":"venue"
},
  "geometry": {"coordinates":[-79.59586334230001,43.5916213989],"type":"Point"}
}