{
  "type": "Feature",
  "properties": {
    "addr:full":"20 Simcoe St N Oshawa ON L1G 4R8",
    "addr:housenumber":"20",
    "addr:postcode":"l1g 4r8",
    "addr:street":"Simcoe St N",
    "iso:country":"CA",
    "sg:address":"20 Simcoe St N",
    "sg:city":"Oshawa",
    "sg:classifiers":[
        {
            "category":"Shopping",
            "subcategory":"Gifts & Souvenirs",
            "type":"Retail Goods"
        }
    ],
    "sg:phone":"+1 905 438 0421",
    "sg:postcode":"L1G 4R8",
    "sg:province":"ON",
    "sg:tags":[
        "shop",
        "jeweler"
    ],
    "wof:name":"Tribal Voices",
    "wof:placetype":"venue"
},
  "geometry": {"coordinates":[-78.86406700000001,43.898052],"type":"Point"}
}