{
  "type": "Feature",
  "properties": {
    "iso:country":"CA",
    "sg:address":"61 Crawford Dr",
    "sg:city":"Ajax",
    "sg:classifiers":[
        {
            "category":"Wholesale",
            "subcategory":"Vending Machines",
            "type":"Manufacturing & Wholesale Goods"
        }
    ],
    "sg:phone":"+1 905 619 2722",
    "sg:postcode":"L1S 3A9",
    "sg:province":"ON",
    "wof:name":"A 1 Quality Vending",
    "wof:placetype":"venue"
},
  "geometry": {"coordinates":[-79.004181,43.825825],"type":"Point"}
}