{
  "type": "Feature",
  "properties": {
    "addr:full":"Etobicoke ON M9W 4P2",
    "addr:postcode":"m9w 4p2",
    "iso:country":"CA",
    "sg:city":"Etobicoke",
    "sg:classifiers":[
        {
            "category":"Building & Trades",
            "subcategory":"Plumbing",
            "type":"Services"
        }
    ],
    "sg:phone":"+1 905 452 0145",
    "sg:postcode":"M9W 4P2",
    "sg:province":"ON",
    "sg:tags":[
        "conditioning",
        "air",
        "system",
        "contractor"
    ],
    "wof:name":"Dael Thermal Group Inc",
    "wof:placetype":"venue"
},
  "geometry": {"coordinates":[-79.575813,43.720421],"type":"Point"}
}