{
  "type": "Feature",
  "properties": {
    "addr:full":"Le Bic QC G0L 1B0",
    "addr:postcode":"g0l 1b0",
    "iso:country":"CA",
    "sg:city":"Le Bic",
    "sg:classifiers":[
        {
            "category":"Building & Trades",
            "subcategory":"Construction",
            "type":"Services"
        }
    ],
    "sg:phone":"+1 418 736 5181",
    "sg:postcode":"G0L 1B0",
    "sg:province":"QC",
    "sg:tags":[
        "masonry",
        "contractor"
    ],
    "wof:name":"Groupe Des Francs Macons",
    "wof:placetype":"venue"
},
  "geometry": {"coordinates":[-68.71374511720001,48.3688468933],"type":"Point"}
}