{
  "type": "Feature",
  "properties": {
    "addr:full":"11601 82 Ave Delta BC V4C 2C3",
    "addr:housenumber":"11601",
    "addr:postcode":"v4c 2c3",
    "addr:street":"82 Ave",
    "iso:country":"CA",
    "sg:address":"11601 82 Ave",
    "sg:city":"Delta",
    "sg:classifiers":[
        {
            "category":"Organizations",
            "subcategory":"Religious Organization",
            "type":"Services"
        }
    ],
    "sg:phone":"+1 604 594 8822",
    "sg:postcode":"V4C 2C3",
    "sg:province":"BC",
    "sg:tags":[
        "church"
    ],
    "wof:name":"St Cuthbert Anglican Church",
    "wof:placetype":"venue"
},
  "geometry": {"coordinates":[-122.90117600000001,49.152386],"type":"Point"}
}