{
  "type": "Feature",
  "properties": {
    "addr:full":"Blue Sea QC J0X 1C0",
    "addr:postcode":"j0x 1c0",
    "iso:country":"CA",
    "sg:city":"Blue Sea",
    "sg:classifiers":[
        {
            "category":"Organizations",
            "subcategory":"Religious Organization",
            "type":"Services"
        }
    ],
    "sg:phone":"+1 819 463 4329",
    "sg:postcode":"J0X 1C0",
    "sg:province":"QC",
    "sg:tags":[
        "church"
    ],
    "wof:name":"Paroisse DE Lac Blue Sea",
    "wof:placetype":"venue"
},
  "geometry": {"coordinates":[-76.06062300000001,46.18248],"type":"Point"}
}