{
  "type": "Feature",
  "properties": {
    "addr:full":"61 Crocus Rd Rossburn MB R0J 1V0",
    "addr:housenumber":"61",
    "addr:postcode":"r0j 1v0",
    "addr:street":"Crocus Rd",
    "iso:country":"CA",
    "sg:address":"61 Crocus Rd",
    "sg:city":"Rossburn",
    "sg:classifiers":[
        {
            "category":"Freight",
            "type":"Transportation"
        }
    ],
    "sg:phone":"+1 204 859 2031",
    "sg:postcode":"R0J 1V0",
    "sg:province":"MB",
    "sg:tags":[
        "grain",
        "elevator"
    ],
    "wof:name":"Rossburn Grain Handlers",
    "wof:placetype":"venue"
},
  "geometry": {"coordinates":[-100.81082916299999,50.6689682007],"type":"Point"}
}