{
  "type": "Feature",
  "properties": {
    "addr:full":"4945 Boul Henri-Bourassa E Montreal-Nord QC H1G 2R4",
    "addr:housenumber":"4945",
    "addr:postcode":"h1g 2r4",
    "addr:street":"Boul Henri-Bourassa E",
    "iso:country":"CA",
    "sg:address":"4945 Boul Henri-Bourassa E",
    "sg:city":"Montreal-Nord",
    "sg:classifiers":[
        {
            "category":"Retail",
            "subcategory":"Veterinary Services",
            "type":"Services"
        }
    ],
    "sg:phone":"+1 514 324 9872",
    "sg:postcode":"H1G 2R4",
    "sg:province":"QC",
    "sg:tags":[
        "veterinarian"
    ],
    "wof:name":"Clinique Veterinaire Benoit",
    "wof:placetype":"venue"
},
  "geometry": {"coordinates":[-73.633415,45.602329],"type":"Point"}
}