{
  "type": "Feature",
  "properties": {
    "iso:country":"CA",
    "sg:address":"2100 Oak Dr",
    "sg:city":"Revelstoke",
    "sg:classifiers":[
        {
            "category":"Travel",
            "subcategory":"Hotels & Motels",
            "type":"Entertainment"
        }
    ],
    "sg:phone":"+1 250 837 3322",
    "sg:postcode":"V0E 2S0",
    "sg:province":"BC",
    "wof:name":"Hillcrest Resort Hotel",
    "wof:placetype":"venue"
},
  "geometry": {"coordinates":[-118.165054321,50.9976501465],"type":"Point"}
}