{
  "type": "Feature",
  "properties": {
    "addr:full":"Victoria BC V9A 3P4",
    "addr:postcode":"v9a 3p4",
    "iso:country":"CA",
    "sg:city":"Victoria",
    "sg:classifiers":[
        {
            "category":"Banks & Credit Unions",
            "subcategory":"Bank",
            "type":"Services"
        }
    ],
    "sg:phone":"+1 250 386 2274",
    "sg:postcode":"V9A 3P4",
    "sg:province":"BC",
    "sg:tags":[
        "loan"
    ],
    "wof:name":"Loans 'Til Payday",
    "wof:placetype":"venue"
},
  "geometry": {"coordinates":[-123.372276,48.427959],"type":"Point"}
}