{
  "type": "Feature",
  "properties": {
    "iso:country":"CA",
    "sg:address":"25223 Valleyview Dr",
    "sg:city":"Sutton West",
    "sg:classifiers":[
        {
            "category":"Autos & Motor Vehicles",
            "subcategory":"Boat Sales",
            "type":"Retail Goods"
        }
    ],
    "sg:phone":"+1 905 722 7767",
    "sg:postcode":"L0E 1R0",
    "sg:province":"ON",
    "sg:tags":[
        "propeller"
    ],
    "wof:name":"Simcoe Prop Repair",
    "wof:placetype":"venue"
},
  "geometry": {"coordinates":[-79.3574523926,44.2845993042],"type":"Point"}
}