{
  "type": "Feature",
  "properties": {
    "addr:full":"Delta BC V4G 1K8",
    "addr:postcode":"v4g 1k8",
    "iso:country":"CA",
    "sg:city":"Delta",
    "sg:classifiers":[
        {
            "category":"Arts & Performance",
            "subcategory":"Theater",
            "type":"Entertainment"
        }
    ],
    "sg:phone":"+1 604 940 9507",
    "sg:postcode":"V4G 1K8",
    "sg:province":"BC",
    "sg:tags":[
        "musician"
    ],
    "wof:name":"Bossa Boys",
    "wof:placetype":"venue"
},
  "geometry": {"coordinates":[-123.024338,49.133514],"type":"Point"}
}