{
  "type": "Feature",
  "properties": {
    "addr:full":"Calgary AB T1Y 5E4",
    "addr:postcode":"t1y 5e4",
    "iso:country":"CA",
    "sg:city":"Calgary",
    "sg:classifiers":[
        {
            "category":"Manufacturing",
            "subcategory":"Building Materials",
            "type":"Manufacturing & Wholesale Goods"
        }
    ],
    "sg:phone":"+1 403 735 6051",
    "sg:postcode":"T1Y 5E4",
    "sg:province":"AB",
    "wof:name":"Able Woodwork Ltd",
    "wof:placetype":"venue"
},
  "geometry": {"coordinates":[-113.99503300000001,51.083824],"type":"Point"}
}