{
  "type": "Feature",
  "properties": {
    "iso:country":"CA",
    "sg:address":"48 Rue Moreau",
    "sg:city":"Saint-Luc",
    "sg:classifiers":[
        {
            "category":"Professional",
            "subcategory":"Business Services",
            "type":"Services"
        }
    ],
    "sg:phone":"+1 450 348 8852",
    "sg:postcode":"J2W 1H9",
    "sg:province":"QC",
    "sg:tags":[
        "interior",
        "consultant",
        "design",
        "decorator"
    ],
    "wof:name":"Decor St-Luc",
    "wof:placetype":"venue"
},
  "geometry": {"coordinates":[-73.289368,45.346214],"type":"Point"}
}