{
  "type": "Feature",
  "properties": {
    "addr:full":"754 Rue Saint-Jacques Granby QC J2G 3R4",
    "addr:housenumber":"754",
    "addr:postcode":"j2g 3r4",
    "addr:street":"Rue Saint-Jacques",
    "iso:country":"CA",
    "sg:address":"754 Rue Saint-Jacques",
    "sg:city":"Granby",
    "sg:classifiers":[
        {
            "category":"Retail",
            "subcategory":"Laundry & Dry Cleaning",
            "type":"Services"
        }
    ],
    "sg:phone":"+1 450 375 0232",
    "sg:postcode":"J2G 3R4",
    "sg:province":"QC",
    "sg:tags":[
        "cleaners"
    ],
    "wof:name":"Nettoyeur St-Jacques",
    "wof:placetype":"venue"
},
  "geometry": {"coordinates":[-72.75176999999999,45.396622],"type":"Point"}
}