{
  "type": "Feature",
  "properties": {
    "addr:full":"Arnes MB R0C 0C0",
    "addr:postcode":"r0c 0c0",
    "iso:country":"CA",
    "sg:city":"Arnes",
    "sg:classifiers":[
        {
            "category":"Recreation",
            "type":"Entertainment"
        }
    ],
    "sg:phone":"+1 204 642 4653",
    "sg:postcode":"R0C 0C0",
    "sg:province":"MB",
    "sg:tags":[
        "course",
        "golf"
    ],
    "wof:name":"Northernaire Golf & Cntry Club",
    "wof:placetype":"venue"
},
  "geometry": {"coordinates":[-96.994247,50.802204],"type":"Point"}
}