{
  "type": "Feature",
  "properties": {
    "addr:full":"3 Sinclair St Etobicoke ON M8Z 1M7",
    "addr:housenumber":"3",
    "addr:postcode":"m8z 1m7",
    "addr:street":"Sinclair St",
    "iso:country":"CA",
    "sg:address":"3 Sinclair St",
    "sg:city":"Etobicoke",
    "sg:classifiers":[
        {
            "category":"Retail",
            "subcategory":"Auto Repair",
            "type":"Services"
        }
    ],
    "sg:phone":"+1 416 201 9667",
    "sg:postcode":"M8Z 1M7",
    "sg:province":"ON",
    "sg:tags":[
        "body",
        "automobile",
        "painting"
    ],
    "wof:name":"Royal York Collision & Svc",
    "wof:placetype":"venue"
},
  "geometry": {"coordinates":[-79.5021286011,43.6242904663],"type":"Point"}
}