{
  "type": "Feature",
  "properties": {
    "addr:full":"Ajax ON L1S 7G8",
    "addr:postcode":"l1s 7g8",
    "iso:country":"CA",
    "sg:city":"Ajax",
    "sg:classifiers":[
        {
            "category":"Autos & Motor Vehicles",
            "subcategory":"Auto Supplies",
            "type":"Retail Goods"
        }
    ],
    "sg:phone":"+1 905 686 3303",
    "sg:postcode":"L1S 7G8",
    "sg:province":"ON",
    "sg:tags":[
        "equipment",
        "racing",
        "car",
        "automobile"
    ],
    "wof:name":"Turn 6 Turning & Design",
    "wof:placetype":"venue"
},
  "geometry": {"coordinates":[-79.032501,43.835239],"type":"Point"}
}