{
  "type": "Feature",
  "properties": {
    "addr:full":"Courtenay BC V9N 2L8",
    "addr:postcode":"v9n 2l8",
    "iso:country":"CA",
    "sg:city":"Courtenay",
    "sg:classifiers":[
        {
            "category":"Personal",
            "subcategory":"Beauty Salon",
            "type":"Services"
        }
    ],
    "sg:phone":"+1 250 338 7342",
    "sg:postcode":"V9N 2L8",
    "sg:province":"BC",
    "wof:name":"Faces & Shear Design",
    "wof:placetype":"venue"
},
  "geometry": {"coordinates":[-124.98133900000001,49.673447],"type":"Point"}
}