{
  "type": "Feature",
  "properties": {
    "iso:country":"CA",
    "sg:address":"212 Av Saint-Jacques",
    "sg:city":"Saint-Raymond",
    "sg:classifiers":[
        {
            "category":"Shopping",
            "subcategory":"Pharmacy",
            "type":"Retail Goods"
        }
    ],
    "sg:phone":"+1 418 337 3030",
    "sg:postcode":"G3L 3Y8",
    "sg:province":"QC",
    "wof:name":"Pharmacie Associee Au Groupe",
    "wof:placetype":"venue"
},
  "geometry": {"coordinates":[-71.8363265991,46.8893585205],"type":"Point"}
}