{
  "type": "Feature",
  "properties": {
    "addr:full":"1921 10 Ave S Lethbridge AB T1K 0B8",
    "addr:housenumber":"1921",
    "addr:postcode":"t1k 0b8",
    "addr:street":"10 Ave S",
    "iso:country":"CA",
    "sg:address":"1921 10 Ave S",
    "sg:city":"Lethbridge",
    "sg:classifiers":[
        {
            "category":"Health Services",
            "subcategory":"Doctor",
            "type":"Services"
        }
    ],
    "sg:phone":"+1 403 380 4777",
    "sg:postcode":"T1K 0B8",
    "sg:province":"AB",
    "sg:tags":[
        "physician",
        "surgeon"
    ],
    "wof:name":"Hebert, R J MD",
    "wof:placetype":"venue"
},
  "geometry": {"coordinates":[-112.814002991,49.6839065552],"type":"Point"}
}