{
  "type": "Feature",
  "properties": {
    "addr:full":"Hwy 42 Dinsmore SK S0L 0T0",
    "addr:postcode":"s0l 0t0",
    "addr:street":"Hwy 42",
    "iso:country":"CA",
    "sg:address":"Hwy 42",
    "sg:city":"Dinsmore",
    "sg:classifiers":[
        {
            "category":"Wholesale",
            "subcategory":"Farm Supplies",
            "type":"Manufacturing & Wholesale Goods"
        }
    ],
    "sg:phone":"+1 306 846 2122",
    "sg:postcode":"S0L 0T0",
    "sg:province":"SK",
    "sg:tags":[
        "fertilizer",
        "oil"
    ],
    "wof:name":"Imperial Oil Sales Agent",
    "wof:placetype":"venue"
},
  "geometry": {"coordinates":[-107.454987,51.329079],"type":"Point"}
}