{
  "type": "Feature",
  "properties": {
    "iso:country":"CA",
    "sg:address":"107 Ainslie St N",
    "sg:city":"Cambridge",
    "sg:classifiers":[
        {
            "category":"Insurance",
            "subcategory":"Insurance Agent",
            "type":"Services"
        }
    ],
    "sg:phone":"+1 519 621 9121",
    "sg:postcode":"N1R 3P2",
    "sg:province":"ON",
    "wof:name":"Peter G Hallman Insurance",
    "wof:placetype":"venue"
},
  "geometry": {"coordinates":[-80.31372833250001,43.3623428345],"type":"Point"}
}