{
  "type": "Feature",
  "properties": {
    "addr:full":"1300 Broadway E Vancouver BC V5N 1V6",
    "addr:housenumber":"1300",
    "addr:postcode":"v5n 1v6",
    "addr:street":"Broadway E",
    "iso:country":"CA",
    "sg:address":"1300 Broadway E",
    "sg:city":"Vancouver",
    "sg:classifiers":[
        {
            "category":"Education",
            "subcategory":"School",
            "type":"Public Place"
        }
    ],
    "sg:phone":"+1 604 713 4599",
    "sg:postcode":"V5N 1V6",
    "sg:province":"BC",
    "wof:name":"Queen Alexandra Elementary",
    "wof:placetype":"venue"
},
  "geometry": {"coordinates":[-123.077293,49.262272],"type":"Point"}
}