{
  "type": "Feature",
  "properties": {
    "addr:full":"36 Crockford Blvd Scarborough ON M1R 3C2",
    "addr:housenumber":"36",
    "addr:postcode":"m1r 3c2",
    "addr:street":"Crockford Blvd",
    "iso:country":"CA",
    "sg:address":"36 Crockford Blvd",
    "sg:city":"Scarborough",
    "sg:classifiers":[
        {
            "category":"Professional",
            "subcategory":"Detective & Security Services",
            "type":"Services"
        }
    ],
    "sg:phone":"+1 416 285 5233",
    "sg:postcode":"M1R 3C2",
    "sg:province":"ON",
    "sg:tags":[
        "guard",
        "patrol"
    ],
    "wof:name":"Nemesis Security Svc",
    "wof:placetype":"venue"
},
  "geometry": {"coordinates":[-79.2876586914,43.7374649048],"type":"Point"}
}