{
  "type": "Feature",
  "properties": {
    "addr:full":"717 Rue Du Precieux-Sang Joliette QC J6E 2M8",
    "addr:housenumber":"717",
    "addr:postcode":"j6e 2m8",
    "addr:street":"Rue Du Precieux-Sang",
    "iso:country":"CA",
    "sg:address":"717 Rue Du Precieux-Sang",
    "sg:city":"Joliette",
    "sg:classifiers":[
        {
            "category":"Real Estate",
            "subcategory":"Real Estate Agent",
            "type":"Services"
        }
    ],
    "sg:phone":"+1 450 755 4705",
    "sg:postcode":"J6E 2M8",
    "sg:province":"QC",
    "wof:name":"Immeubles Lanaudiere",
    "wof:placetype":"venue"
},
  "geometry": {"coordinates":[-73.452202,46.027653],"type":"Point"}
}