{
  "type": "Feature",
  "properties": {
    "addr:full":"148 Boul Broadway Grand-Sault/Grand Falls NB E3Z 2J9",
    "addr:housenumber":"148",
    "addr:postcode":"e3z 2j9",
    "addr:street":"Boul Broadway",
    "iso:country":"CA",
    "sg:address":"148 Boul Broadway",
    "sg:city":"Grand-Sault/Grand Falls",
    "sg:classifiers":[
        {
            "category":"Health Services",
            "subcategory":"Doctor",
            "type":"Services"
        }
    ],
    "sg:phone":"+1 506 473 3042",
    "sg:postcode":"E3Z 2J9",
    "sg:province":"NB",
    "sg:tags":[
        "dentist"
    ],
    "wof:name":"Theriault, Michel DDS",
    "wof:placetype":"venue"
},
  "geometry": {"coordinates":[-67.7386550903,47.0489311218],"type":"Point"}
}