{
  "type": "Feature",
  "properties": {
    "addr:full":"Burnaby BC V5C 5M8",
    "addr:postcode":"v5c 5m8",
    "iso:country":"CA",
    "sg:city":"Burnaby",
    "sg:classifiers":[
        {
            "category":"Building & Trades",
            "subcategory":"Equipment Rental",
            "type":"Services"
        }
    ],
    "sg:phone":"+1 604 294 3400",
    "sg:postcode":"V5C 5M8",
    "sg:province":"BC",
    "wof:name":"United Scaffold Supply CO Inc",
    "wof:placetype":"venue"
},
  "geometry": {"coordinates":[-122.997406,49.263836],"type":"Point"}
}