{
  "type": "Feature",
  "properties": {
    "addr:full":"70 Silton Rd Woodbridge ON L4L 8B9",
    "addr:housenumber":"70",
    "addr:postcode":"l4l 8b9",
    "addr:street":"Silton Rd",
    "iso:country":"CA",
    "sg:address":"70 Silton Rd",
    "sg:city":"Woodbridge",
    "sg:classifiers":[
        {
            "category":"Wholesale",
            "subcategory":"Stationery",
            "type":"Manufacturing & Wholesale Goods"
        }
    ],
    "sg:phone":"+1 905 264 1292",
    "sg:postcode":"L4L 8B9",
    "sg:province":"ON",
    "sg:tags":[
        "box"
    ],
    "wof:name":"Conray Engineered Products",
    "wof:placetype":"venue"
},
  "geometry": {"coordinates":[-79.5462188721,43.8023338318],"type":"Point"}
}