{
  "type": "Feature",
  "properties": {
    "iso:country":"CA",
    "sg:address":"64 Salter St",
    "sg:city":"Winnipeg",
    "sg:classifiers":[
        {
            "category":"Retail",
            "subcategory":"Auto Repair",
            "type":"Services"
        }
    ],
    "sg:phone":"+1 204 586 8321",
    "sg:postcode":"R2W 4J6",
    "sg:province":"MB",
    "sg:tags":[
        "body",
        "automobile",
        "painting"
    ],
    "wof:name":"AAA Nepon Auto Body",
    "wof:placetype":"venue"
},
  "geometry": {"coordinates":[-97.143166,49.912449],"type":"Point"}
}