{
  "type": "Feature",
  "properties": {
    "addr:full":"65 Dawson Cres Georgetown ON L7G 1H3",
    "addr:housenumber":"65",
    "addr:postcode":"l7g 1h3",
    "addr:street":"Dawson Cres",
    "iso:country":"CA",
    "sg:address":"65 Dawson Cres",
    "sg:city":"Georgetown",
    "sg:classifiers":[
        {
            "category":"Professional",
            "subcategory":"Art Services",
            "type":"Services"
        }
    ],
    "sg:phone":"+1 905 702 7881",
    "sg:postcode":"L7G 1H3",
    "sg:province":"ON",
    "sg:tags":[
        "graphic",
        "designer"
    ],
    "wof:name":"Cdh Design",
    "wof:placetype":"venue"
},
  "geometry": {"coordinates":[-79.897171,43.641243],"type":"Point"}
}