{
  "type": "Feature",
  "properties": {
    "addr:full":"10 Greengage Rd New Lowell ON L0M 1N0",
    "addr:housenumber":"10",
    "addr:postcode":"l0m 1n0",
    "addr:street":"Greengage Rd",
    "iso:country":"CA",
    "sg:address":"10 Greengage Rd",
    "sg:city":"New Lowell",
    "sg:classifiers":[
        {
            "category":"Retail",
            "subcategory":"Repair Shop",
            "type":"Services"
        }
    ],
    "sg:phone":"+1 705 424 9381",
    "sg:postcode":"L0M 1N0",
    "sg:province":"ON",
    "sg:tags":[
        "ironwork"
    ],
    "wof:name":"Wrought Iron of New Lowell Inc",
    "wof:placetype":"venue"
},
  "geometry": {"coordinates":[-79.97593688960001,44.3618812561],"type":"Point"}
}