{
  "type": "Feature",
  "properties": {
    "addr:full":"2920 111 Rte E Amos QC J9T 3A1",
    "addr:housenumber":"2920",
    "addr:postcode":"j9t 3a1",
    "addr:street":"111 Rte E Amos",
    "iso:country":"CA",
    "sg:address":"2920 111 Rte E",
    "sg:city":"Amos",
    "sg:classifiers":[
        {
            "category":"Utilities",
            "subcategory":"Fuel Oil & Lpg",
            "type":"Services"
        }
    ],
    "sg:phone":"+1 819 732 2076",
    "sg:postcode":"J9T 3A1",
    "sg:province":"QC",
    "wof:name":"Produits Petrolieres Harricana",
    "wof:placetype":"venue"
},
  "geometry": {"coordinates":[-78.1567,48.599545],"type":"Point"}
}