{
  "type": "Feature",
  "properties": {
    "iso:country":"CA",
    "sg:city":"Hull",
    "sg:classifiers":[
        {
            "category":"Education",
            "subcategory":"Special Training",
            "type":"Public Place"
        }
    ],
    "sg:phone":"+1 819 772 2542",
    "sg:postcode":"J8Y 2V5",
    "sg:province":"QC",
    "sg:tags":[
        "tutoring"
    ],
    "wof:name":"Centre DE Langues Intl",
    "wof:placetype":"venue"
},
  "geometry": {"coordinates":[-75.733315,45.435268],"type":"Point"}
}