{
  "type": "Feature",
  "properties": {
    "addr:full":"RR 1 Gads Hill Station ON N0K 1J0",
    "addr:postcode":"n0k 1j0",
    "addr:street":"Rr 1 Gads Hill Station",
    "iso:country":"CA",
    "sg:address":"RR 1",
    "sg:city":"Gads Hill Station",
    "sg:classifiers":[
        {
            "category":"Retail",
            "subcategory":"Animal Services",
            "type":"Services"
        }
    ],
    "sg:phone":"+1 519 273 7869",
    "sg:postcode":"N0K 1J0",
    "sg:province":"ON",
    "sg:tags":[
        "pet",
        "boarding",
        "sitting"
    ],
    "wof:name":"Schamber Kennels",
    "wof:placetype":"venue"
},
  "geometry": {"coordinates":[-80.922492981,43.4451255798],"type":"Point"}
}