{
  "type": "Feature",
  "properties": {
    "addr:full":"819 Bathurst St Toronto ON M5R 3G2",
    "addr:housenumber":"819",
    "addr:postcode":"m5r 3g2",
    "addr:street":"Bathurst St",
    "iso:country":"CA",
    "sg:address":"819 Bathurst St",
    "sg:city":"Toronto",
    "sg:classifiers":[
        {
            "category":"Food & Beverages",
            "subcategory":"Groceries & Convenience Stores",
            "type":"Retail Goods"
        }
    ],
    "sg:phone":"+1 416 533 5468",
    "sg:postcode":"M5R 3G2",
    "sg:province":"ON",
    "sg:tags":[
        "grocer"
    ],
    "wof:name":"Thuvass Enterprise",
    "wof:placetype":"venue"
},
  "geometry": {"coordinates":[-79.41130065919999,43.6658630371],"type":"Point"}
}