{
  "type": "Feature",
  "properties": {
    "addr:full":"2088 Rue Des Roses Carignan QC J3L 5C9",
    "addr:housenumber":"2088",
    "addr:postcode":"j3l 5c9",
    "addr:street":"Rue Des Roses",
    "iso:country":"CA",
    "sg:address":"2088 Rue Des Roses",
    "sg:city":"Carignan",
    "sg:classifiers":[
        {
            "category":"Building & Trades",
            "subcategory":"Construction",
            "type":"Services"
        }
    ],
    "sg:phone":"+1 450 658 3392",
    "sg:postcode":"J3L 5C9",
    "sg:province":"QC",
    "sg:tags":[
        "roofing",
        "contractor"
    ],
    "wof:name":"Couverture Landry",
    "wof:placetype":"venue"
},
  "geometry": {"coordinates":[-73.280327,45.471924],"type":"Point"}
}