{
  "type": "Feature",
  "properties": {
    "addr:full":"639 5 Ave SW Calgary AB T2P 0M9",
    "addr:housenumber":"639",
    "addr:postcode":"t2p 0m9",
    "addr:street":"5 Ave Sw",
    "iso:country":"CA",
    "sg:address":"639 5 Ave SW",
    "sg:city":"Calgary",
    "sg:classifiers":[
        {
            "category":"Personal",
            "subcategory":"Barber",
            "type":"Services"
        }
    ],
    "sg:phone":"+1 403 265 6260",
    "sg:postcode":"T2P 0M9",
    "sg:province":"AB",
    "wof:name":"Gentleman's Choice",
    "wof:placetype":"venue"
},
  "geometry": {"coordinates":[-114.074646,51.048569],"type":"Point"}
}