{
  "type": "Feature",
  "properties": {
    "addr:full":"9909 96 Ave Peace River AB T8S 1H5",
    "addr:housenumber":"9909",
    "addr:postcode":"t8s 1h5",
    "addr:street":"96 Ave",
    "iso:country":"CA",
    "sg:address":"9909 96 Ave",
    "sg:city":"Peace River",
    "sg:classifiers":[
        {
            "category":"Professional",
            "subcategory":"Business Services",
            "type":"Services"
        }
    ],
    "sg:phone":"+1 780 624 4050",
    "sg:postcode":"T8S 1H5",
    "sg:province":"AB",
    "sg:tags":[
        "plumbing",
        "water",
        "fixture",
        "treatment",
        "supply"
    ],
    "wof:name":"Bartle & Gibson CO Ltd",
    "wof:placetype":"venue"
},
  "geometry": {"coordinates":[-117.29059600799999,56.2371902466],"type":"Point"}
}