{
  "type": "Feature",
  "properties": {
    "addr:full":"Huntsville ON P1H 1J4",
    "addr:postcode":"p1h 1j4",
    "iso:country":"CA",
    "sg:city":"Huntsville",
    "sg:classifiers":[
        {
            "category":"Health Services",
            "subcategory":"Doctor",
            "type":"Services"
        }
    ],
    "sg:phone":"+1 705 789 1747",
    "sg:postcode":"P1H 1J4",
    "sg:province":"ON",
    "sg:tags":[
        "dentist"
    ],
    "wof:name":"Gemmell, Warren DDS",
    "wof:placetype":"venue"
},
  "geometry": {"coordinates":[-79.21403503419999,45.3313713074],"type":"Point"}
}