{
  "type": "Feature",
  "properties": {
    "addr:full":"44 Paddington Ave London ON N6J 2S6",
    "addr:housenumber":"44",
    "addr:postcode":"n6j 2s6",
    "addr:street":"Paddington Ave",
    "iso:country":"CA",
    "sg:address":"44 Paddington Ave",
    "sg:city":"London",
    "sg:classifiers":[
        {
            "category":"Building & Trades",
            "subcategory":"Construction",
            "type":"Services"
        }
    ],
    "sg:phone":"+1 519 433 8181",
    "sg:postcode":"N6J 2S6",
    "sg:province":"ON",
    "sg:tags":[
        "coating",
        "painter"
    ],
    "wof:name":"Paramount Painting & Decortng",
    "wof:placetype":"venue"
},
  "geometry": {"coordinates":[-81.263092,42.963371],"type":"Point"}
}