{
  "type": "Feature",
  "properties": {
    "addr:full":"2615 Faithfull Ave Saskatoon SK S7K 5W2",
    "addr:housenumber":"2615",
    "addr:postcode":"s7k 5w2",
    "addr:street":"Faithfull Ave",
    "iso:country":"CA",
    "sg:address":"2615 Faithfull Ave",
    "sg:city":"Saskatoon",
    "sg:classifiers":[
        {
            "category":"Autos & Motor Vehicles",
            "subcategory":"Auto Supplies",
            "type":"Retail Goods"
        }
    ],
    "sg:phone":"+1 306 242 6212",
    "sg:postcode":"S7K 5W2",
    "sg:province":"SK",
    "sg:tags":[
        "tire"
    ],
    "wof:name":"Can-am Rubber Inc",
    "wof:placetype":"venue"
},
  "geometry": {"coordinates":[-106.665084839,52.1686096191],"type":"Point"}
}