{
  "type": "Feature",
  "properties": {
    "addr:full":"Vancouver BC V6Z 2Y6",
    "addr:postcode":"v6z 2y6",
    "iso:country":"CA",
    "sg:city":"Vancouver",
    "sg:classifiers":[
        {
            "category":"Insurance",
            "subcategory":"Insurance Agent",
            "type":"Services"
        }
    ],
    "sg:phone":"+1 604 669 3212",
    "sg:postcode":"V6Z 2Y6",
    "sg:province":"BC",
    "wof:name":"Aviva Insurance CO of Canada",
    "wof:placetype":"venue"
},
  "geometry": {"coordinates":[-123.126152039,49.2785987854],"type":"Point"}
}