{
  "type": "Feature",
  "properties": {
    "addr:full":"3930 Boul Wilfrid-Hamel Quebec QC G1P 2J2",
    "addr:housenumber":"3930",
    "addr:postcode":"g1p 2j2",
    "addr:street":"Boul Wilfrid-Hamel",
    "iso:country":"CA",
    "sg:address":"3930 Boul Wilfrid-Hamel",
    "sg:city":"Quebec",
    "sg:classifiers":[
        {
            "category":"Restaurant",
            "type":"Food & Drink"
        }
    ],
    "sg:phone":"+1 418 877 5865",
    "sg:postcode":"G1P 2J2",
    "sg:province":"QC",
    "wof:name":"Subway Sandwiches & Salads",
    "wof:placetype":"venue"
},
  "geometry": {"coordinates":[-71.314865,46.806374],"type":"Point"}
}