{
  "type": "Feature",
  "properties": {
    "iso:country":"CA",
    "sg:address":"3930 Boul Wilfrid-Hamel",
    "sg:city":"Quebec",
    "sg:classifiers":[
        {
            "category":"Restaurant",
            "type":"Food & Drink"
        }
    ],
    "sg:phone":"+1 418 877 5865",
    "sg:postcode":"G1P 2J2",
    "sg:province":"QC",
    "wof:name":"Subway Sandwiches & Salads",
    "wof:placetype":"venue"
},
  "geometry": {"coordinates":[-71.314865,46.806374],"type":"Point"}
}