{
  "type": "Feature",
  "properties": {
    "addr:full":"71 Rue Bernier Victoriaville QC G6P 2P3",
    "addr:housenumber":"71",
    "addr:postcode":"g6p 2p3",
    "addr:street":"Rue Bernier",
    "iso:country":"CA",
    "sg:address":"71 Rue Bernier",
    "sg:city":"Victoriaville",
    "sg:classifiers":[
        {
            "category":"Wholesale",
            "subcategory":"Hardware",
            "type":"Manufacturing & Wholesale Goods"
        }
    ],
    "sg:phone":"+1 819 795 4924",
    "sg:postcode":"G6P 2P3",
    "sg:province":"QC",
    "sg:tags":[
        "used",
        "boiler"
    ],
    "wof:name":"CO-Breyne Inc",
    "wof:placetype":"venue"
},
  "geometry": {"coordinates":[-71.969093,46.044048],"type":"Point"}
}