{
  "type": "Feature",
  "properties": {
    "addr:full":"9091 Rue Hochelaga Montreal QC H1L 2P2",
    "addr:housenumber":"9091",
    "addr:postcode":"h1l 2p2",
    "addr:street":"Rue Hochelaga",
    "iso:country":"CA",
    "sg:address":"9091 Rue Hochelaga",
    "sg:city":"Montreal",
    "sg:classifiers":[
        {
            "category":"Shopping",
            "subcategory":"Bicycles & Sporting Goods",
            "type":"Retail Goods"
        }
    ],
    "sg:phone":"+1 514 351 3370",
    "sg:postcode":"H1L 2P2",
    "sg:province":"QC",
    "wof:name":"Tetreaultville Bicycle & Sport",
    "wof:placetype":"venue"
},
  "geometry": {"coordinates":[-73.51750199999999,45.605824],"type":"Point"}
}