{
  "type": "Feature",
  "properties": {
    "addr:full":"548 4th Ave W Owen Sound ON N4K 4V4",
    "addr:housenumber":"548",
    "addr:postcode":"n4k 4v4",
    "addr:street":"4Th Ave W",
    "iso:country":"CA",
    "sg:address":"548 4th Ave W",
    "sg:city":"Owen Sound",
    "sg:classifiers":[
        {
            "category":"Organizations",
            "subcategory":"Religious Organization",
            "type":"Services"
        }
    ],
    "sg:phone":"+1 519 371 3647",
    "sg:postcode":"N4K 4V4",
    "sg:province":"ON",
    "sg:tags":[
        "church"
    ],
    "wof:name":"Trinity Christian Church",
    "wof:placetype":"venue"
},
  "geometry": {"coordinates":[-80.9477233887,44.5587043762],"type":"Point"}
}