{
  "type": "Feature",
  "properties": {
    "addr:full":"162 Medana St Victoria BC V8V 2H5",
    "addr:housenumber":"162",
    "addr:postcode":"v8v 2h5",
    "addr:street":"Medana St",
    "iso:country":"CA",
    "sg:address":"162 Medana St",
    "sg:city":"Victoria",
    "sg:classifiers":[
        {
            "category":"Travel",
            "subcategory":"Hotels & Motels",
            "type":"Entertainment"
        }
    ],
    "sg:phone":"+1 250 389 0437",
    "sg:postcode":"V8V 2H5",
    "sg:province":"BC",
    "sg:tags":[
        "breakfast",
        "accommodation",
        "bed"
    ],
    "wof:name":"Medana Grove Bed & Breakfast",
    "wof:placetype":"venue"
},
  "geometry": {"coordinates":[-123.374016,48.414471],"type":"Point"}
}