{
  "type": "Feature",
  "properties": {
    "addr:full":"407 Pido Rd Peterborough ON K9J 6X7",
    "addr:housenumber":"407",
    "addr:postcode":"k9j 6x7",
    "addr:street":"Pido Rd",
    "iso:country":"CA",
    "sg:address":"407 Pido Rd",
    "sg:city":"Peterborough",
    "sg:classifiers":[
        {
            "category":"Building & Trades",
            "subcategory":"Plumbing",
            "type":"Services"
        }
    ],
    "sg:phone":"+1 705 745 5751",
    "sg:postcode":"K9J 6X7",
    "sg:province":"ON",
    "sg:tags":[
        "mechanical",
        "contractor"
    ],
    "wof:name":"Adamson & Dobbin Ltd",
    "wof:placetype":"venue"
},
  "geometry": {"coordinates":[-78.2935638428,44.2768707275],"type":"Point"}
}