{
  "type": "Feature",
  "properties": {
    "addr:full":"360 10th St Brandon MB R7A 4G1",
    "addr:housenumber":"360",
    "addr:postcode":"r7a 4g1",
    "addr:street":"10Th St",
    "iso:country":"CA",
    "sg:address":"360 10th St",
    "sg:city":"Brandon",
    "sg:classifiers":[
        {
            "category":"Restaurant",
            "type":"Food & Drink"
        }
    ],
    "sg:phone":"+1 204 727 0442",
    "sg:postcode":"R7A 4G1",
    "sg:province":"MB",
    "sg:tags":[
        "pizza"
    ],
    "wof:name":"Pizza Express",
    "wof:placetype":"venue"
},
  "geometry": {"coordinates":[-99.951576,49.844402],"type":"Point"}
}