{
  "type": "Feature",
  "properties": {
    "addr:full":"Rainy River ON P0W 1L0",
    "addr:postcode":"p0w 1l0",
    "iso:country":"CA",
    "sg:city":"Rainy River",
    "sg:classifiers":[
        {
            "category":"Education",
            "subcategory":"School",
            "type":"Public Place"
        }
    ],
    "sg:phone":"+1 807 852 3561",
    "sg:postcode":"P0W 1L0",
    "sg:province":"ON",
    "wof:name":"Riverview Elementary School",
    "wof:placetype":"venue"
},
  "geometry": {"coordinates":[-94.567719,48.717243],"type":"Point"}
}