{
  "type": "Feature",
  "properties": {
    "addr:full":"199 Rue Saint-Patrice E Magog QC J1X 1T7",
    "addr:housenumber":"199",
    "addr:postcode":"j1x 1t7",
    "addr:street":"Rue Saint-Patrice E",
    "iso:country":"CA",
    "sg:address":"199 Rue Saint-Patrice E",
    "sg:city":"Magog",
    "sg:classifiers":[
        {
            "category":"Recreation",
            "type":"Entertainment"
        }
    ],
    "sg:phone":"+1 819 847 1191",
    "sg:postcode":"J1X 1T7",
    "sg:province":"QC",
    "sg:tags":[
        "martial",
        "arts",
        "instruction"
    ],
    "wof:name":"Club Karate Magog",
    "wof:placetype":"venue"
},
  "geometry": {"coordinates":[-72.140488,45.264736],"type":"Point"}
}