{
  "type": "Feature",
  "properties": {
    "addr:full":"103 Bluewater Rd Bedford NS B4B 1H2",
    "addr:housenumber":"103",
    "addr:postcode":"b4b 1h2",
    "addr:street":"Bluewater Rd",
    "iso:country":"CA",
    "sg:address":"103 Bluewater Rd",
    "sg:city":"Bedford",
    "sg:classifiers":[
        {
            "category":"Manufacturing",
            "subcategory":"Glass & Minerals",
            "type":"Manufacturing & Wholesale Goods"
        }
    ],
    "sg:phone":"+1 902 835 7483",
    "sg:postcode":"B4B 1H2",
    "sg:province":"NS",
    "sg:tags":[
        "decoration",
        "glassware"
    ],
    "wof:name":"Jym Line Products Ltd",
    "wof:placetype":"venue"
},
  "geometry": {"coordinates":[-63.709843,44.723137],"type":"Point"}
}