{
  "type": "Feature",
  "properties": {
    "iso:country":"CA",
    "sg:city":"East Selkirk",
    "sg:classifiers":[
        {
            "category":"Recreation",
            "type":"Entertainment"
        }
    ],
    "sg:phone":"+1 204 482 6555",
    "sg:postcode":"R0E 0M0",
    "sg:province":"MB",
    "sg:tags":[
        "riding",
        "academy",
        "stable"
    ],
    "wof:name":"Prairie Grass Trails",
    "wof:placetype":"venue"
},
  "geometry": {"coordinates":[-96.87390899659999,50.1457252502],"type":"Point"}
}