{
  "type": "Feature",
  "properties": {
    "addr:full":"1391 Rue Principale Saint-Etienne-Des-Gres QC G0X 2P0",
    "addr:housenumber":"1391",
    "addr:postcode":"g0x 2p0",
    "addr:street":"Rue Principale",
    "iso:country":"CA",
    "sg:address":"1391 Rue Principale",
    "sg:city":"Saint-Etienne-Des-Gres",
    "sg:classifiers":[
        {
            "category":"Personal",
            "subcategory":"Beauty Salon",
            "type":"Services"
        }
    ],
    "sg:phone":"+1 819 535 3332",
    "sg:postcode":"G0X 2P0",
    "sg:province":"QC",
    "wof:name":"Salon DE Coiffure Jo-Litete",
    "wof:placetype":"venue"
},
  "geometry": {"coordinates":[-72.77545166020001,46.4416694641],"type":"Point"}
}