{
  "type": "Feature",
  "properties": {
    "addr:full":"1525 1st St N Brandon MB R7C 1B5",
    "addr:housenumber":"1525",
    "addr:postcode":"r7c 1b5",
    "addr:street":"1St St N",
    "iso:country":"CA",
    "sg:address":"1525 1st St N",
    "sg:city":"Brandon",
    "sg:classifiers":[
        {
            "category":"Government",
            "subcategory":"Office",
            "type":"Public Place"
        }
    ],
    "sg:phone":"+1 204 726 6800",
    "sg:postcode":"R7C 1B5",
    "sg:province":"MB",
    "wof:name":"Manitoba Highways & Trans",
    "wof:placetype":"venue"
},
  "geometry": {"coordinates":[-99.93881988530001,49.8764648438],"type":"Point"}
}