{
  "type": "Feature",
  "properties": {
    "addr:full":"Ajax ON L1S 2C9",
    "addr:postcode":"l1s 2c9",
    "iso:country":"CA",
    "sg:city":"Ajax",
    "sg:classifiers":[
        {
            "category":"Retail",
            "subcategory":"Auto Rental",
            "type":"Services"
        }
    ],
    "sg:phone":"+1 905 427 4664",
    "sg:postcode":"L1S 2C9",
    "sg:province":"ON",
    "sg:tags":[
        "renting",
        "automobile"
    ],
    "wof:name":"Advantage Car & Truck Rentals",
    "wof:placetype":"venue"
},
  "geometry": {"coordinates":[-79.0365905762,43.8439369202],"type":"Point"}
}