{
  "type": "Feature",
  "properties": {
    "addr:full":"525 2nd Ave W Prince Rupert BC V8J 1G9",
    "addr:housenumber":"525",
    "addr:postcode":"v8j 1g9",
    "addr:street":"2Nd Ave W",
    "iso:country":"CA",
    "sg:address":"525 2nd Ave W",
    "sg:city":"Prince Rupert",
    "sg:classifiers":[
        {
            "category":"Cinema",
            "subcategory":"Movie Theater",
            "type":"Entertainment"
        }
    ],
    "sg:phone":"+1 250 624 6770",
    "sg:postcode":"V8J 1G9",
    "sg:province":"BC",
    "wof:name":"Prince Rupert Cinemas",
    "wof:placetype":"venue"
},
  "geometry": {"coordinates":[-130.326843,54.312473],"type":"Point"}
}