{
  "type": "Feature",
  "properties": {
    "addr:full":"Surrey BC V4P 3K1",
    "addr:postcode":"v4p 3k1",
    "iso:country":"CA",
    "sg:city":"Surrey",
    "sg:classifiers":[
        {
            "category":"Personal",
            "subcategory":"Beauty Salon",
            "type":"Services"
        }
    ],
    "sg:phone":"+1 604 531 8709",
    "sg:postcode":"V4P 3K1",
    "sg:province":"BC",
    "wof:name":"Great Clips For Hair",
    "wof:placetype":"venue"
},
  "geometry": {"coordinates":[-122.801346,49.056671],"type":"Point"}
}