{
  "type": "Feature",
  "properties": {
    "iso:country":"CA",
    "sg:address":"2 Ross Dr",
    "sg:city":"Fort Saskatchewan",
    "sg:classifiers":[
        {
            "category":"Restaurant",
            "type":"Food & Drink"
        }
    ],
    "sg:phone":"+1 780 998 2390",
    "sg:postcode":"T8L 2M8",
    "sg:province":"AB",
    "sg:tags":[
        "caterer"
    ],
    "wof:name":"Royal Catering",
    "wof:placetype":"venue"
},
  "geometry": {"coordinates":[-113.204055786,53.710018158],"type":"Point"}
}