{
  "type": "Feature",
  "properties": {
    "addr:full":"714 May St N Thunder Bay ON P7C 3R9",
    "addr:housenumber":"714",
    "addr:postcode":"p7c 3r9",
    "addr:street":"May St N",
    "iso:country":"CA",
    "sg:address":"714 May St N",
    "sg:city":"Thunder Bay",
    "sg:classifiers":[
        {
            "category":"Shopping",
            "subcategory":"Florist",
            "type":"Retail Goods"
        }
    ],
    "sg:phone":"+1 807 474 5353",
    "sg:postcode":"P7C 3R9",
    "sg:province":"ON",
    "wof:name":"Flower Shed",
    "wof:placetype":"venue"
},
  "geometry": {"coordinates":[-89.245338,48.396484],"type":"Point"}
}