{
  "type": "Feature",
  "properties": {
    "addr:full":"7230 67 St NW Edmonton AB T6B 3E7",
    "addr:housenumber":"7230",
    "addr:postcode":"t6b 3e7",
    "addr:street":"67 St Nw",
    "iso:country":"CA",
    "sg:address":"7230 67 St NW",
    "sg:city":"Edmonton",
    "sg:classifiers":[
        {
            "category":"Building & Trades",
            "subcategory":"Cleaning & Sanitation",
            "type":"Services"
        }
    ],
    "sg:phone":"+1 780 468 6446",
    "sg:postcode":"T6B 3E7",
    "sg:province":"AB",
    "sg:tags":[
        "sand",
        "gravel",
        "snow",
        "removal"
    ],
    "wof:name":"Sprague Transport Ltd",
    "wof:placetype":"venue"
},
  "geometry": {"coordinates":[-113.430786133,53.5090370178],"type":"Point"}
}