{
  "type": "Feature",
  "properties": {
    "addr:full":"83 Rue Saint-Paul O Montreal QC H2Y 1Z1",
    "addr:housenumber":"83",
    "addr:postcode":"h2y 1z1",
    "addr:street":"Rue Saint-Paul O",
    "iso:country":"CA",
    "sg:address":"83 Rue Saint-Paul O",
    "sg:city":"Montreal",
    "sg:classifiers":[
        {
            "category":"Professional",
            "subcategory":"Lawyer & Legal Services",
            "type":"Services"
        }
    ],
    "sg:phone":"+1 514 288 1086",
    "sg:postcode":"H2Y 1Z1",
    "sg:province":"QC",
    "sg:tags":[
        "attorney"
    ],
    "wof:name":"David & David",
    "wof:placetype":"venue"
},
  "geometry": {"coordinates":[-73.55326100000001,45.506538],"type":"Point"}
}