{
  "type": "Feature",
  "properties": {
    "addr:full":"2411 Eagle St N Cambridge ON N3H 4R7",
    "addr:housenumber":"2411",
    "addr:postcode":"n3h 4r7",
    "addr:street":"Eagle St N",
    "iso:country":"CA",
    "sg:address":"2411 Eagle St N",
    "sg:city":"Cambridge",
    "sg:classifiers":[
        {
            "category":"Manufacturing",
            "subcategory":"Tools & Machinery",
            "type":"Manufacturing & Wholesale Goods"
        }
    ],
    "sg:phone":"+1 519 653 5923",
    "sg:postcode":"N3H 4R7",
    "sg:province":"ON",
    "sg:tags":[
        "cutting",
        "gear"
    ],
    "wof:name":"Variable Propulsion Systems",
    "wof:placetype":"venue"
},
  "geometry": {"coordinates":[-80.33209228520001,43.4071884155],"type":"Point"}
}