{
  "type": "Feature",
  "properties": {
    "addr:full":"145 Main St N Mount Forest ON N0G 2L0",
    "addr:housenumber":"145",
    "addr:postcode":"n0g 2l0",
    "addr:street":"Main St N",
    "iso:country":"CA",
    "sg:address":"145 Main St N",
    "sg:city":"Mount Forest",
    "sg:classifiers":[
        {
            "category":"Professional",
            "subcategory":"Accounting & Tax Preparation",
            "type":"Services"
        }
    ],
    "sg:phone":"+1 519 323 1212",
    "sg:postcode":"N0G 2L0",
    "sg:province":"ON",
    "sg:tags":[
        "return",
        "filing"
    ],
    "wof:name":"H & R Block Canada Inc",
    "wof:placetype":"venue"
},
  "geometry": {"coordinates":[-80.7364654541,43.9822158813],"type":"Point"}
}