{
  "type": "Feature",
  "properties": {
    "iso:country":"CA",
    "sg:address":"625 Simcoe St N",
    "sg:city":"Oshawa",
    "sg:classifiers":[
        {
            "category":"Education",
            "subcategory":"School",
            "type":"Public Place"
        }
    ],
    "sg:phone":"+1 905 725 4232",
    "sg:postcode":"L1G 4V5",
    "sg:province":"ON",
    "wof:name":"S J Phillips Public School",
    "wof:placetype":"venue"
},
  "geometry": {"coordinates":[-78.8706893921,43.9141159058],"type":"Point"}
}