{
  "type": "Feature",
  "properties": {
    "addr:full":"1305 Boul Saint-Antoine Saint-Jerome QC J7Z 7M1",
    "addr:housenumber":"1305",
    "addr:postcode":"j7z 7m1",
    "addr:street":"Boul Saint-Antoine",
    "iso:country":"CA",
    "sg:address":"1305 Boul Saint-Antoine",
    "sg:city":"Saint-Jerome",
    "sg:classifiers":[
        {
            "category":"Autos & Motor Vehicles",
            "subcategory":"Automobile Sales",
            "type":"Retail Goods"
        }
    ],
    "sg:phone":"+1 450 436 9937",
    "sg:postcode":"J7Z 7M1",
    "sg:province":"QC",
    "sg:tags":[
        "car",
        "dealer"
    ],
    "wof:name":"Automobiles Pv",
    "wof:placetype":"venue"
},
  "geometry": {"coordinates":[-73.9745178223,45.7696151733],"type":"Point"}
}