{
  "type": "Feature",
  "properties": {
    "addr:full":"304 Caribou St Banff AB T1L 1B7",
    "addr:housenumber":"304",
    "addr:postcode":"t1l 1b7",
    "addr:street":"Caribou St",
    "iso:country":"CA",
    "sg:address":"304 Caribou St",
    "sg:city":"Banff",
    "sg:classifiers":[
        {
            "category":"Restaurant",
            "type":"Food & Drink"
        }
    ],
    "sg:phone":"+1 403 762 4353",
    "sg:postcode":"T1L 1B7",
    "sg:province":"AB",
    "wof:name":"Sushi House Banff",
    "wof:placetype":"venue"
},
  "geometry": {"coordinates":[-115.57060199999999,51.176594],"type":"Point"}
}