{
  "type": "Feature",
  "properties": {
    "addr:full":"Vancouver BC V6G 2Y1",
    "addr:postcode":"v6g 2y1",
    "iso:country":"CA",
    "sg:city":"Vancouver",
    "sg:classifiers":[
        {
            "category":"Social Services",
            "type":"Services"
        }
    ],
    "sg:phone":"+1 604 688 1615",
    "sg:postcode":"V6G 2Y1",
    "sg:province":"BC",
    "sg:tags":[
        "senior",
        "citizen"
    ],
    "wof:name":"Sunset Towers Advocacy",
    "wof:placetype":"venue"
},
  "geometry": {"coordinates":[-123.135262,49.288704],"type":"Point"}
}