{
  "type": "Feature",
  "properties": {
    "addr:full":"PO Box 120 Plum Point NL A0K 4A0",
    "addr:housenumber":"po",
    "addr:postcode":"a0k 4a0",
    "addr:street":"Box 120",
    "iso:country":"CA",
    "sg:address":"PO Box 120",
    "sg:city":"Plum Point",
    "sg:classifiers":[
        {
            "category":"Professional",
            "subcategory":"Management & Consulting",
            "type":"Services"
        }
    ],
    "sg:phone":"+1 709 247 2354",
    "sg:postcode":"A0K 4A0",
    "sg:province":"NL",
    "sg:tags":[
        "consultant",
        "business"
    ],
    "wof:name":"Great Northern Peninsula Dev",
    "wof:placetype":"venue"
},
  "geometry": {"coordinates":[-56.8771934509,51.0777702332],"type":"Point"}
}