{
  "type": "Feature",
  "properties": {
    "addr:full":"Huntsville ON P1H 1B5",
    "addr:postcode":"p1h 1b5",
    "iso:country":"CA",
    "sg:city":"Huntsville",
    "sg:classifiers":[
        {
            "category":"Recreation",
            "subcategory":"Marina",
            "type":"Entertainment"
        }
    ],
    "sg:phone":"+1 705 789 5522",
    "sg:postcode":"P1H 1B5",
    "sg:province":"ON",
    "sg:tags":[
        "dealer",
        "boat",
        "sales"
    ],
    "wof:name":"Huntsville Marine & Recreation",
    "wof:placetype":"venue"
},
  "geometry": {"coordinates":[-79.218002,45.326565],"type":"Point"}
}