{
  "type": "Feature",
  "properties": {
    "addr:full":"Calgary AB T2P 2X6",
    "addr:postcode":"t2p 2x6",
    "iso:country":"CA",
    "sg:city":"Calgary",
    "sg:classifiers":[
        {
            "category":"Utilities",
            "subcategory":"Mobile Phone",
            "type":"Services"
        }
    ],
    "sg:phone":"+1 403 539 0003",
    "sg:postcode":"T2P 2X6",
    "sg:province":"AB",
    "sg:tags":[
        "telephone",
        "cellular"
    ],
    "wof:name":"Rogers Wireless Alberta Inc",
    "wof:placetype":"venue"
},
  "geometry": {"coordinates":[-114.07665299999999,51.048634],"type":"Point"}
}