{
  "type": "Feature",
  "properties": {
    "addr:full":"250 Scott St Fort Frances ON P9A 1G7",
    "addr:housenumber":"250",
    "addr:postcode":"p9a 1g7",
    "addr:street":"Scott St",
    "iso:country":"CA",
    "sg:address":"250 Scott St",
    "sg:city":"Fort Frances",
    "sg:classifiers":[
        {
            "category":"Insurance",
            "subcategory":"Insurance Agent",
            "type":"Services"
        }
    ],
    "sg:phone":"+1 807 274 9891",
    "sg:postcode":"P9A 1G7",
    "sg:province":"ON",
    "wof:name":"Cousineau Brokers Inc",
    "wof:placetype":"venue"
},
  "geometry": {"coordinates":[-93.39710998539999,48.610118866],"type":"Point"}
}