{
  "type": "Feature",
  "properties": {
    "addr:full":"1724 Ch DE LA Sauvagine Saint-Faustin-Lac-Carre QC J0T 1J2",
    "addr:postcode":"1724;j0t 1j2",
    "addr:street":"Ch De La Sauvagine",
    "iso:country":"CA",
    "sg:address":"1724 Ch DE LA Sauvagine",
    "sg:city":"Saint-Faustin-Lac-Carre",
    "sg:classifiers":[
        {
            "category":"Farming",
            "subcategory":"Farm",
            "type":"Manufacturing & Wholesale Goods"
        }
    ],
    "sg:phone":"+1 819 425 5688",
    "sg:postcode":"J0T 1J2",
    "sg:province":"QC",
    "sg:tags":[
        "breakfast",
        "accommodation",
        "bed"
    ],
    "wof:name":"Ferme DE LA Butte Magique",
    "wof:placetype":"venue"
},
  "geometry": {"coordinates":[-74.538704,46.074646],"type":"Point"}
}