{
  "type": "Feature",
  "properties": {
    "iso:country":"CA",
    "sg:city":"North York",
    "sg:classifiers":[
        {
            "category":"Shopping",
            "subcategory":"Computers & Home Electronics",
            "type":"Retail Goods"
        }
    ],
    "sg:phone":"+1 416 447 8770",
    "sg:postcode":"M3B 3N7",
    "sg:province":"ON",
    "sg:tags":[
        "software"
    ],
    "wof:name":"Roberts Browne Ltd",
    "wof:placetype":"venue"
},
  "geometry": {"coordinates":[-79.34624481199999,43.7471199036],"type":"Point"}
}