{
  "type": "Feature",
  "properties": {
    "addr:full":"4212 Petrolia St Petrolia ON N0N 1R0",
    "addr:housenumber":"4212",
    "addr:postcode":"n0n 1r0",
    "addr:street":"Petrolia St",
    "iso:country":"CA",
    "sg:address":"4212 Petrolia St",
    "sg:city":"Petrolia",
    "sg:classifiers":[
        {
            "category":"Shopping",
            "type":"Retail Goods"
        }
    ],
    "sg:phone":"+1 519 882 1234",
    "sg:postcode":"N0N 1R0",
    "sg:province":"ON",
    "sg:tags":[
        "picture",
        "frame"
    ],
    "wof:name":"Creekside Picture Framing CO",
    "wof:placetype":"venue"
},
  "geometry": {"coordinates":[-82.14561500000001,42.882011],"type":"Point"}
}