{
  "type": "Feature",
  "properties": {
    "addr:full":"Nanaimo BC V9T 5V9",
    "addr:postcode":"v9t 5v9",
    "iso:country":"CA",
    "sg:city":"Nanaimo",
    "sg:classifiers":[
        {
            "category":"Shopping",
            "subcategory":"Bicycles & Sporting Goods",
            "type":"Retail Goods"
        }
    ],
    "sg:phone":"+1 250 751 7625",
    "sg:postcode":"V9T 5V9",
    "sg:province":"BC",
    "sg:tags":[
        "club",
        "health",
        "studio",
        "gymnasium",
        "backpacking"
    ],
    "wof:name":"Romper Room Indoor Climbing",
    "wof:placetype":"venue"
},
  "geometry": {"coordinates":[-124.036018,49.208546],"type":"Point"}
}