{
  "type": "Feature",
  "properties": {
    "addr:full":"3081 3rd Ave Whitehorse YT Y1A 4Z7",
    "addr:housenumber":"3081",
    "addr:postcode":"y1a 4z7",
    "addr:street":"3Rd Ave",
    "iso:country":"CA",
    "sg:address":"3081 3rd Ave",
    "sg:city":"Whitehorse",
    "sg:classifiers":[
        {
            "category":"Professional",
            "subcategory":"Lawyer & Legal Services",
            "type":"Services"
        }
    ],
    "sg:phone":"+1 867 668 4405",
    "sg:postcode":"Y1A 4Z7",
    "sg:province":"YT",
    "sg:tags":[
        "attorney"
    ],
    "wof:name":"Austring Fendrick Fairman",
    "wof:placetype":"venue"
},
  "geometry": {"coordinates":[-135.05229199999999,60.717175],"type":"Point"}
}