{
  "type": "Feature",
  "properties": {
    "addr:full":"3330 Rue DE Miniac Saint-Laurent QC H4S 1Y4",
    "addr:housenumber":"3330",
    "addr:postcode":"h4s 1y4",
    "addr:street":"Rue De Miniac",
    "iso:country":"CA",
    "sg:address":"3330 Rue DE Miniac",
    "sg:city":"Saint-Laurent",
    "sg:classifiers":[
        {
            "category":"Freight",
            "type":"Transportation"
        }
    ],
    "sg:phone":"+1 514 333 0888",
    "sg:postcode":"H4S 1Y4",
    "sg:province":"QC",
    "sg:tags":[
        "advertising",
        "trucking"
    ],
    "wof:name":"Alstom Transport Telecite",
    "wof:placetype":"venue"
},
  "geometry": {"coordinates":[-73.7535934448,45.4967918396],"type":"Point"}
}