{
  "type": "Feature",
  "properties": {
    "addr:full":"195 the West Mall Etobicoke ON M9C 5K1",
    "addr:housenumber":"195",
    "addr:postcode":"m9c 5k1",
    "addr:street":"The West Mall",
    "iso:country":"CA",
    "sg:address":"195 the West Mall",
    "sg:city":"Etobicoke",
    "sg:classifiers":[
        {
            "category":"Real Estate",
            "subcategory":"Real Estate Agent",
            "type":"Services"
        }
    ],
    "sg:phone":"+1 416 622 9510",
    "sg:postcode":"M9C 5K1",
    "sg:province":"ON",
    "sg:tags":[
        "management"
    ],
    "wof:name":"Parklane Management Svc Inc",
    "wof:placetype":"venue"
},
  "geometry": {"coordinates":[-79.558769,43.626701],"type":"Point"}
}