{
  "type": "Feature",
  "properties": {
    "addr:full":"Montreal QC H3A 3L8",
    "addr:postcode":"h3a 3l8",
    "iso:country":"CA",
    "sg:city":"Montreal",
    "sg:classifiers":[
        {
            "category":"Professional",
            "subcategory":"Business Services",
            "type":"Services"
        }
    ],
    "sg:phone":"+1 514 287 1070",
    "sg:postcode":"H3A 3L8",
    "sg:province":"QC",
    "sg:tags":[
        "convention",
        "meeting",
        "facility"
    ],
    "wof:name":"Jpdl Multi Management Inc",
    "wof:placetype":"venue"
},
  "geometry": {"coordinates":[-73.574196,45.50082],"type":"Point"}
}