{
  "type": "Feature",
  "properties": {
    "addr:full":"347 Wood St New Westminster BC V3M 5K6",
    "addr:housenumber":"347",
    "addr:postcode":"v3m 5k6",
    "addr:street":"Wood St",
    "iso:country":"CA",
    "sg:address":"347 Wood St",
    "sg:city":"New Westminster",
    "sg:classifiers":[
        {
            "category":"Organizations",
            "subcategory":"Religious Organization",
            "type":"Services"
        }
    ],
    "sg:phone":"+1 604 521 6933",
    "sg:postcode":"V3M 5K6",
    "sg:province":"BC",
    "sg:tags":[
        "church"
    ],
    "wof:name":"Sikh Temple Sukhsagar",
    "wof:placetype":"venue"
},
  "geometry": {"coordinates":[-122.941146851,49.1915016174],"type":"Point"}
}