{
  "type": "Feature",
  "properties": {
    "addr:full":"701 Park Cres New Westminster BC V3L 5V4",
    "addr:housenumber":"701",
    "addr:postcode":"v3l 5v4",
    "addr:street":"Park Cres",
    "iso:country":"CA",
    "sg:address":"701 Park Cres",
    "sg:city":"New Westminster",
    "sg:classifiers":[
        {
            "category":"Education",
            "subcategory":"School",
            "type":"Public Place"
        }
    ],
    "sg:phone":"+1 604 517 5940",
    "sg:postcode":"V3L 5V4",
    "sg:province":"BC",
    "wof:name":"Glenbrook Middle School",
    "wof:placetype":"venue"
},
  "geometry": {"coordinates":[-122.911445618,49.2204055786],"type":"Point"}
}