{
  "type": "Feature",
  "properties": {
    "addr:full":"833 Avenue P N Saskatoon SK S7L 2W5",
    "addr:housenumber":"833",
    "addr:postcode":"s7l 2w5",
    "addr:street":"Avenue;N",
    "iso:country":"CA",
    "sg:address":"833 Avenue P N",
    "sg:city":"Saskatoon",
    "sg:classifiers":[
        {
            "category":"Recreation",
            "type":"Entertainment"
        }
    ],
    "sg:phone":"+1 306 975 3318",
    "sg:postcode":"S7L 2W5",
    "sg:province":"SK",
    "sg:tags":[
        "skating",
        "rink"
    ],
    "wof:name":"Clarence Downey Speed Skating",
    "wof:placetype":"venue"
},
  "geometry": {"coordinates":[-106.694320679,52.1375923157],"type":"Point"}
}