{
  "type": "Feature",
  "properties": {
    "addr:full":"4200 10 St NE Calgary AB T2E 6K3",
    "addr:housenumber":"4200",
    "addr:postcode":"t2e 6k3",
    "addr:street":"10 St Ne",
    "iso:country":"CA",
    "sg:address":"4200 10 St NE",
    "sg:city":"Calgary",
    "sg:classifiers":[
        {
            "category":"Building & Trades",
            "subcategory":"Construction",
            "type":"Services"
        }
    ],
    "sg:phone":"+1 403 250 3818",
    "sg:postcode":"T2E 6K3",
    "sg:province":"AB",
    "sg:tags":[
        "general",
        "contractor"
    ],
    "wof:name":"Lear Construction Svc Ltd",
    "wof:placetype":"venue"
},
  "geometry": {"coordinates":[-114.037682,51.089676],"type":"Point"}
}