{
  "type": "Feature",
  "properties": {
    "addr:full":"66 Shanley St Kitchener ON N2H 5N9",
    "addr:housenumber":"66",
    "addr:postcode":"n2h 5n9",
    "addr:street":"Shanley St",
    "iso:country":"CA",
    "sg:address":"66 Shanley St",
    "sg:city":"Kitchener",
    "sg:classifiers":[
        {
            "category":"Organizations",
            "subcategory":"Religious Organization",
            "type":"Services"
        }
    ],
    "sg:phone":"+1 519 742 5831",
    "sg:postcode":"N2H 5N9",
    "sg:province":"ON",
    "sg:tags":[
        "church"
    ],
    "wof:name":"Sacred Heart Parish",
    "wof:placetype":"venue"
},
  "geometry": {"coordinates":[-80.50266999999999,43.456596],"type":"Point"}
}