{
  "type": "Feature",
  "properties": {
    "addr:full":"3817 Rue Saint-Denis Montreal QC H2W 2M4",
    "addr:housenumber":"3817",
    "addr:postcode":"h2w 2m4",
    "addr:street":"Rue Saint-Denis",
    "iso:country":"CA",
    "sg:address":"3817 Rue Saint-Denis",
    "sg:city":"Montreal",
    "sg:classifiers":[
        {
            "category":"Restaurant",
            "type":"Food & Drink"
        }
    ],
    "sg:phone":"+1 514 840 9011",
    "sg:postcode":"H2W 2M4",
    "sg:province":"QC",
    "wof:name":"Restaurant Cafe Fruits Folie",
    "wof:placetype":"venue"
},
  "geometry": {"coordinates":[-73.5729141235,45.5196037292],"type":"Point"}
}