{
  "type": "Feature",
  "properties": {
    "addr:full":"8676 Rue Sainte-Claire Montreal QC H1L 1Y2",
    "addr:housenumber":"8676",
    "addr:postcode":"h1l 1y2",
    "addr:street":"Rue Sainte-Claire",
    "iso:country":"CA",
    "sg:address":"8676 Rue Sainte-Claire",
    "sg:city":"Montreal",
    "sg:classifiers":[
        {
            "category":"Food & Beverages",
            "subcategory":"Bakery",
            "type":"Retail Goods"
        }
    ],
    "sg:phone":"+1 514 351 3307",
    "sg:postcode":"H1L 1Y2",
    "sg:province":"QC",
    "sg:tags":[
        "baker"
    ],
    "wof:name":"Patisserie Ste Claire",
    "wof:placetype":"venue"
},
  "geometry": {"coordinates":[-73.523949,45.602409],"type":"Point"}
}