{
  "type": "Feature",
  "properties": {
    "addr:full":"2723 Greenwood Rd Nelson BC V1L 6L1",
    "addr:housenumber":"2723",
    "addr:postcode":"bc v1l 6l1",
    "addr:street":"Greenwood Rd",
    "iso:country":"CA",
    "sg:address":"2723 Greenwood Rd",
    "sg:city":"Nelson",
    "sg:classifiers":[
        {
            "category":"Bars & Pubs",
            "type":"Food & Drink"
        }
    ],
    "sg:phone":"+1 250 825 4464",
    "sg:postcode":"V1L 6L1",
    "sg:province":"BC",
    "wof:name":"Chillers Neighbourhood Pub",
    "wof:placetype":"venue"
},
  "geometry": {"coordinates":[-117.288811,49.49754],"type":"Point"}
}