{
  "type": "Feature",
  "properties": {
    "iso:country":"CA",
    "sg:address":"177 Rue Bernard O",
    "sg:city":"Montreal",
    "sg:classifiers":[
        {
            "category":"Restaurant",
            "type":"Food & Drink"
        }
    ],
    "sg:phone":"+1 514 274 1464",
    "sg:postcode":"H2T 2K3",
    "sg:province":"QC",
    "wof:name":"Restaurant Senzala",
    "wof:placetype":"venue"
},
  "geometry": {"coordinates":[-73.5993804932,45.5285453796],"type":"Point"}
}