{
  "type": "Feature",
  "properties": {
    "addr:full":"Chilliwack BC V2R 4G7",
    "addr:postcode":"v2r 4g7",
    "iso:country":"CA",
    "sg:city":"Chilliwack",
    "sg:classifiers":[
        {
            "category":"Manufacturing",
            "subcategory":"Food",
            "type":"Manufacturing & Wholesale Goods"
        }
    ],
    "sg:phone":"+1 604 824 8686",
    "sg:postcode":"V2R 4G7",
    "sg:province":"BC",
    "sg:tags":[
        "winery"
    ],
    "wof:name":"Vine To Wine CO",
    "wof:placetype":"venue"
},
  "geometry": {"coordinates":[-121.960136414,49.1412010193],"type":"Point"}
}