{
  "type": "Feature",
  "properties": {
    "addr:full":"17600 Yonge St # B8 Newmarket ON L3Y 4Z1",
    "addr:housenumber":"17600;b8",
    "addr:postcode":"l3y 4z1",
    "addr:street":"Yonge St #",
    "iso:country":"CA",
    "sg:address":"17600 Yonge St # B8",
    "sg:city":"Newmarket",
    "sg:classifiers":[
        {
            "category":"Shopping",
            "subcategory":"Clothing, Apparel, & Fashions",
            "type":"Retail Goods"
        }
    ],
    "sg:phone":"+1 905 836 9555",
    "sg:postcode":"L3Y 4Z1",
    "sg:province":"ON",
    "sg:tags":[
        "leather"
    ],
    "wof:name":"Roots Canada Ltd",
    "wof:placetype":"venue"
},
  "geometry": {"coordinates":[-79.4811096191,44.057056427],"type":"Point"}
}