{
  "type": "Feature",
  "properties": {
    "iso:country":"CA",
    "sg:city":"Vercheres",
    "sg:classifiers":[
        {
            "category":"Cinema",
            "subcategory":"Movie Rental",
            "type":"Entertainment"
        }
    ],
    "sg:phone":"+1 450 583 3572",
    "sg:postcode":"J0L 2R0",
    "sg:province":"QC",
    "sg:tags":[
        "leasing",
        "video",
        "disc",
        "tape"
    ],
    "wof:name":"Club Video Vercheres",
    "wof:placetype":"venue"
},
  "geometry": {"coordinates":[-73.3601074219,45.7750816345],"type":"Point"}
}