{
  "type": "Feature",
  "properties": {
    "addr:full":"2687 Rue Wellington Montreal QC H3K 1X8",
    "addr:housenumber":"2687",
    "addr:postcode":"h3k 1x8",
    "addr:street":"Rue Wellington",
    "iso:country":"CA",
    "sg:address":"2687 Rue Wellington",
    "sg:city":"Montreal",
    "sg:classifiers":[
        {
            "category":"Bars & Pubs",
            "type":"Food & Drink"
        }
    ],
    "sg:phone":"+1 514 935 5969",
    "sg:postcode":"H3K 1X8",
    "sg:province":"QC",
    "sg:tags":[
        "lounge",
        "cocktail"
    ],
    "wof:name":"Pub St Charles",
    "wof:placetype":"venue"
},
  "geometry": {"coordinates":[-73.56257600000001,45.47311],"type":"Point"}
}