{
  "type": "Feature",
  "properties": {
    "addr:full":"1527 St Marys Rd W Montague PE C0A 1R0",
    "addr:housenumber":"1527",
    "addr:postcode":"c0a 1r0",
    "addr:street":"St Marys Rd W",
    "iso:country":"CA",
    "sg:address":"1527 St Marys Rd W",
    "sg:city":"Montague",
    "sg:classifiers":[
        {
            "category":"Building & Trades",
            "subcategory":"Construction",
            "type":"Services"
        }
    ],
    "sg:phone":"+1 902 962 3643",
    "sg:postcode":"C0A 1R0",
    "sg:province":"PE",
    "sg:tags":[
        "masonry",
        "contractor"
    ],
    "wof:name":"Gormley's Masonry Inc",
    "wof:placetype":"venue"
},
  "geometry": {"coordinates":[-62.649719,46.167164],"type":"Point"}
}