{
  "type": "Feature",
  "properties": {
    "addr:full":"York ON M9N 2S4",
    "addr:postcode":"m9n 2s4",
    "iso:country":"CA",
    "sg:city":"York",
    "sg:classifiers":[
        {
            "category":"Education",
            "subcategory":"Special Training",
            "type":"Public Place"
        }
    ],
    "sg:phone":"+1 416 245 2812",
    "sg:postcode":"M9N 2S4",
    "sg:province":"ON",
    "sg:tags":[
        "instruction",
        "driving"
    ],
    "wof:name":"Brisa Driving School",
    "wof:placetype":"venue"
},
  "geometry": {"coordinates":[-79.5040054321,43.703037262],"type":"Point"}
}