{
  "type": "Feature",
  "properties": {
    "addr:full":"Toronto ON M5G 2E9",
    "addr:postcode":"m5g 2e9",
    "iso:country":"CA",
    "sg:city":"Toronto",
    "sg:classifiers":[
        {
            "category":"Professional",
            "subcategory":"Lawyer & Legal Services",
            "type":"Services"
        }
    ],
    "sg:phone":"+1 416 977 7786",
    "sg:postcode":"M5G 2E9",
    "sg:province":"ON",
    "sg:tags":[
        "attorney"
    ],
    "wof:name":"Weingust, John QC",
    "wof:placetype":"venue"
},
  "geometry": {"coordinates":[-79.3881530762,43.6552429199],"type":"Point"}
}