{
  "type": "Feature",
  "properties": {
    "addr:full":"40 Dussek St Belleville ON K8N 5R8",
    "addr:housenumber":"40",
    "addr:postcode":"k8n 5r8",
    "addr:street":"Dussek St",
    "iso:country":"CA",
    "sg:address":"40 Dussek St",
    "sg:city":"Belleville",
    "sg:classifiers":[
        {
            "category":"Shopping",
            "subcategory":"Clothing, Apparel, & Fashions",
            "type":"Retail Goods"
        }
    ],
    "sg:phone":"+1 613 966 0062",
    "sg:postcode":"K8N 5R8",
    "sg:province":"ON",
    "sg:tags":[
        "industrial",
        "glove"
    ],
    "wof:name":"Impacto Protective Products",
    "wof:placetype":"venue"
},
  "geometry": {"coordinates":[-77.368385,44.179329],"type":"Point"}
}