{
  "type": "Feature",
  "properties": {
    "addr:full":"Bedford NS B4A 2X9",
    "addr:postcode":"b4a 2x9",
    "iso:country":"CA",
    "sg:city":"Bedford",
    "sg:classifiers":[
        {
            "category":"Shopping",
            "subcategory":"Clothing, Apparel, & Fashions",
            "type":"Retail Goods"
        }
    ],
    "sg:phone":"+1 902 835 2848",
    "sg:postcode":"B4A 2X9",
    "sg:province":"NS",
    "wof:name":"Suzy Shier",
    "wof:placetype":"venue"
},
  "geometry": {"coordinates":[-63.654804,44.736401],"type":"Point"}
}