{
  "type": "Feature",
  "properties": {
    "iso:country":"CA",
    "sg:address":"766 Ch Trudeau",
    "sg:city":"Saint-Mathieu-DE-Beloeil",
    "sg:classifiers":[
        {
            "category":"Health Services",
            "subcategory":"Medical Lab",
            "type":"Services"
        }
    ],
    "sg:phone":"+1 450 464 4388",
    "sg:postcode":"J3G 4S5",
    "sg:province":"QC",
    "wof:name":"Baril Lavallee, Denise",
    "wof:placetype":"venue"
},
  "geometry": {"coordinates":[-73.235878,45.583401],"type":"Point"}
}