{
  "type": "Feature",
  "properties": {
    "addr:full":"220 Rue Rochette Saint-Pascal QC G0L 3Y0",
    "addr:housenumber":"220",
    "addr:postcode":"g0l 3y0",
    "addr:street":"Rue Rochette",
    "iso:country":"CA",
    "sg:address":"220 Rue Rochette",
    "sg:city":"Saint-Pascal",
    "sg:classifiers":[
        {
            "category":"Wholesale",
            "subcategory":"Machinery & Supplies",
            "type":"Manufacturing & Wholesale Goods"
        }
    ],
    "sg:phone":"+1 418 492 6852",
    "sg:postcode":"G0L 3Y0",
    "sg:province":"QC",
    "sg:tags":[
        "farm",
        "equipment"
    ],
    "wof:name":"Equipements Jpl Inc",
    "wof:placetype":"venue"
},
  "geometry": {"coordinates":[-69.81954193120001,47.5289382935],"type":"Point"}
}