{
  "type": "Feature",
  "properties": {
    "addr:full":"74 1st St E The Pas MB R9A 1L7",
    "addr:housenumber":"74",
    "addr:postcode":"r9a 1l7",
    "addr:street":"1St St E",
    "iso:country":"CA",
    "sg:address":"74 1st St E",
    "sg:city":"The Pas",
    "sg:classifiers":[
        {
            "category":"Recreation",
            "type":"Entertainment"
        }
    ],
    "sg:phone":"+1 204 623 3837",
    "sg:postcode":"R9A 1L7",
    "sg:province":"MB",
    "sg:tags":[
        "hall",
        "auditorium"
    ],
    "wof:name":"Norlite Hall",
    "wof:placetype":"venue"
},
  "geometry": {"coordinates":[-101.25035099999999,53.813435],"type":"Point"}
}