{
  "type": "Feature",
  "properties": {
    "iso:country":"CA",
    "sg:address":"1414 Route 275",
    "sg:city":"Saint-Arthur",
    "sg:classifiers":[
        {
            "category":"Food & Beverages",
            "subcategory":"Groceries & Convenience Stores",
            "type":"Retail Goods"
        }
    ],
    "sg:phone":"+1 506 759 7931",
    "sg:postcode":"E3N 5R6",
    "sg:province":"NB",
    "sg:tags":[
        "grocer"
    ],
    "wof:name":"Depanneur Diane",
    "wof:placetype":"venue"
},
  "geometry": {"coordinates":[-66.73748000000001,47.889404],"type":"Point"}
}