{
  "type": "Feature",
  "properties": {
    "addr:full":"141 Water St Charlottetown PE C1A 1A8",
    "addr:housenumber":"141",
    "addr:postcode":"c1a 1a8",
    "addr:street":"Water St",
    "iso:country":"CA",
    "sg:address":"141 Water St",
    "sg:city":"Charlottetown",
    "sg:classifiers":[
        {
            "category":"Food & Beverages",
            "subcategory":"Meat & Fish",
            "type":"Retail Goods"
        }
    ],
    "sg:phone":"+1 902 368 3212",
    "sg:postcode":"C1A 1A8",
    "sg:province":"PE",
    "sg:tags":[
        "seafood"
    ],
    "wof:name":"Water Prince Corner Shop",
    "wof:placetype":"venue"
},
  "geometry": {"coordinates":[-63.122379,46.233791],"type":"Point"}
}