{
  "type": "Feature",
  "properties": {
    "addr:full":"5550 St Peters Hwy St-Peters Bay PE C0A 2A0",
    "addr:housenumber":"5550",
    "addr:postcode":"c0a 2a0",
    "addr:street":"St Peters Hwy St-Peters",
    "iso:country":"CA",
    "sg:address":"5550 St Peters Hwy",
    "sg:city":"St-Peters Bay",
    "sg:classifiers":[
        {
            "category":"Travel",
            "subcategory":"Hotels & Motels",
            "type":"Entertainment"
        }
    ],
    "sg:phone":"+1 902 961 3496",
    "sg:postcode":"C0A 2A0",
    "sg:province":"PE",
    "wof:name":"Greenwich Gate Lodge",
    "wof:placetype":"venue"
},
  "geometry": {"coordinates":[-62.582474,46.418121],"type":"Point"}
}