{
  "type": "Feature",
  "properties": {
    "addr:full":"Mississauga ON L5T 1N9",
    "addr:postcode":"l5t 1n9",
    "iso:country":"CA",
    "sg:city":"Mississauga",
    "sg:classifiers":[
        {
            "category":"Retail",
            "subcategory":"Repair Shop",
            "type":"Services"
        }
    ],
    "sg:phone":"+1 905 564 0760",
    "sg:postcode":"L5T 1N9",
    "sg:province":"ON",
    "sg:tags":[
        "equipment",
        "electronic",
        "supply"
    ],
    "wof:name":"Argo Electronics Ltd",
    "wof:placetype":"venue"
},
  "geometry": {"coordinates":[-79.65062,43.658497],"type":"Point"}
}