{
  "type": "Feature",
  "properties": {
    "addr:full":"PO Box 31702 Pitt Meadows BC V3Y 2H1",
    "addr:housenumber":"po box",
    "addr:postcode":"31702;v3y 2h1",
    "iso:country":"CA",
    "sg:address":"PO Box 31702",
    "sg:city":"Pitt Meadows",
    "sg:classifiers":[
        {
            "category":"Recreation",
            "type":"Entertainment"
        }
    ],
    "sg:phone":"+1 604 460 8660",
    "sg:postcode":"V3Y 2H1",
    "sg:province":"BC",
    "sg:tags":[
        "supply",
        "equipment",
        "instruction",
        "boat",
        "boating"
    ],
    "wof:name":"Agonic Marine Inc",
    "wof:placetype":"venue"
},
  "geometry": {"coordinates":[-122.689621,49.220718],"type":"Point"}
}