{
  "type": "Feature",
  "properties": {
    "iso:country":"CA",
    "sg:address":"50 Rue Western",
    "sg:city":"Sutton",
    "sg:classifiers":[
        {
            "category":"Health Services",
            "subcategory":"Nursing And Care Facility",
            "type":"Services"
        }
    ],
    "sg:phone":"+1 450 538 3332",
    "sg:postcode":"J0E 2K0",
    "sg:province":"QC",
    "sg:tags":[
        "home",
        "rest"
    ],
    "wof:name":"Foyer Sutton",
    "wof:placetype":"venue"
},
  "geometry": {"coordinates":[-72.61808776860001,45.1070213318],"type":"Point"}
}