{
  "type": "Feature",
  "properties": {
    "addr:full":"1130 3E Av Quebec QC G1L 2X6",
    "addr:housenumber":"1130",
    "addr:postcode":"g1l 2x6",
    "addr:street":"3E Av",
    "iso:country":"CA",
    "sg:address":"1130 3E Av",
    "sg:city":"Quebec",
    "sg:classifiers":[
        {
            "category":"Professional",
            "subcategory":"Lawyer & Legal Services",
            "type":"Services"
        }
    ],
    "sg:phone":"+1 418 640 0123",
    "sg:postcode":"G1L 2X6",
    "sg:province":"QC",
    "sg:tags":[
        "attorney"
    ],
    "wof:name":"Sirois, Philippe",
    "wof:placetype":"venue"
},
  "geometry": {"coordinates":[-71.230476,46.82745],"type":"Point"}
}