{
  "type": "Feature",
  "properties": {
    "addr:full":"440 Rue Saint-Michel Saint-Jean-Sur-Richelieu QC J3B 1T4",
    "addr:housenumber":"440",
    "addr:postcode":"j3b 1t4",
    "addr:street":"Rue Saint-Michel",
    "iso:country":"CA",
    "sg:address":"440 Rue Saint-Michel",
    "sg:city":"Saint-Jean-Sur-Richelieu",
    "sg:classifiers":[
        {
            "category":"Manufacturing",
            "subcategory":"Rubber & Plastics",
            "type":"Manufacturing & Wholesale Goods"
        }
    ],
    "sg:phone":"+1 450 348 4918",
    "sg:postcode":"J3B 1T4",
    "sg:province":"QC",
    "sg:tags":[
        "mold",
        "maker"
    ],
    "wof:name":"Groupe Glp hi-Tech Inc",
    "wof:placetype":"venue"
},
  "geometry": {"coordinates":[-73.27220199999999,45.315029],"type":"Point"}
}