{
  "type": "Feature",
  "properties": {
    "addr:full":"3246 Shaughnessy St Port Coquitlam BC V3B 4L5",
    "addr:housenumber":"3246",
    "addr:postcode":"v3b 4l5",
    "addr:street":"Shaughnessy St",
    "iso:country":"CA",
    "sg:address":"3246 Shaughnessy St",
    "sg:city":"Port Coquitlam",
    "sg:classifiers":[
        {
            "category":"Retail",
            "subcategory":"Portrait Studio",
            "type":"Services"
        }
    ],
    "sg:phone":"+1 604 524 4546",
    "sg:postcode":"V3B 4L5",
    "sg:province":"BC",
    "sg:tags":[
        "photographer"
    ],
    "wof:name":"Triad Photographic",
    "wof:placetype":"venue"
},
  "geometry": {"coordinates":[-122.775047302,49.2717933655],"type":"Point"}
}