{
  "type": "Feature",
  "properties": {
    "iso:country":"CA",
    "sg:address":"377 Rue Principale",
    "sg:city":"St-Sauveur-Des-Monts",
    "sg:classifiers":[
        {
            "category":"Food & Beverages",
            "subcategory":"Groceries & Convenience Stores",
            "type":"Retail Goods"
        }
    ],
    "sg:phone":"+1 450 227 2141",
    "sg:postcode":"J0R 1R0",
    "sg:province":"QC",
    "sg:tags":[
        "grocer"
    ],
    "wof:name":"Marche Real Chartier",
    "wof:placetype":"venue"
},
  "geometry": {"coordinates":[-74.16278839109999,45.8908576965],"type":"Point"}
}