{
  "type": "Feature",
  "properties": {
    "iso:country":"CA",
    "sg:address":"1061 Rue DE Liege O",
    "sg:city":"Montreal",
    "sg:classifiers":[
        {
            "category":"Banks & Credit Unions",
            "subcategory":"Investment Brokerage",
            "type":"Services"
        }
    ],
    "sg:phone":"+1 514 272 8706",
    "sg:postcode":"H3N 1B9",
    "sg:province":"QC",
    "sg:tags":[
        "consultant",
        "financing"
    ],
    "wof:name":"Professionnel Inc",
    "wof:placetype":"venue"
},
  "geometry": {"coordinates":[-73.631073,45.549492],"type":"Point"}
}