{
  "type": "Feature",
  "properties": {
    "iso:country":"CA",
    "sg:address":"439 Rue Barkoff",
    "sg:city":"Cap-DE-LA-Madeleine",
    "sg:classifiers":[
        {
            "category":"Insurance",
            "subcategory":"Insurance Agent",
            "type":"Services"
        }
    ],
    "sg:phone":"+1 819 374 4117",
    "sg:postcode":"G8T 2A5",
    "sg:province":"QC",
    "wof:name":"Promutuel Port Neuf Champlain",
    "wof:placetype":"venue"
},
  "geometry": {"coordinates":[-72.554359,46.374039],"type":"Point"}
}