{
  "type": "Feature",
  "properties": {
    "iso:country":"CA",
    "sg:address":"480 Berkley Cres NW",
    "sg:city":"Calgary",
    "sg:classifiers":[
        {
            "category":"Building & Trades",
            "subcategory":"Construction",
            "type":"Services"
        }
    ],
    "sg:phone":"+1 403 274 7690",
    "sg:postcode":"T3K 1A8",
    "sg:province":"AB",
    "sg:tags":[
        "masonry",
        "contractor"
    ],
    "wof:name":"Profeta Construction",
    "wof:placetype":"venue"
},
  "geometry": {"coordinates":[-114.081581116,51.1254730225],"type":"Point"}
}