{
  "type": "Feature",
  "properties": {
    "addr:full":"800 Boul DE Maisonneuve E # 500 Montreal QC H2L 4L8",
    "addr:housenumber":"800",
    "addr:postcode":"h2l 4l8",
    "addr:street":"Boul De Maisonneuve E # 500",
    "iso:country":"CA",
    "sg:address":"800 Boul DE Maisonneuve E # 500",
    "sg:city":"Montreal",
    "sg:classifiers":[
        {
            "category":"Education",
            "subcategory":"College",
            "type":"Public Place"
        }
    ],
    "sg:phone":"+1 514 932 1122",
    "sg:postcode":"H2L 4L8",
    "sg:province":"QC",
    "sg:tags":[
        "academic",
        "school"
    ],
    "wof:name":"College Superieur DE Mtl Inc",
    "wof:placetype":"venue"
},
  "geometry": {"coordinates":[-73.56023399999999,45.516155],"type":"Point"}
}