{
  "type": "Feature",
  "properties": {
    "addr:full":"42 Rue Sainte-Anne Ville-Marie QC J9V 2B7",
    "addr:housenumber":"42",
    "addr:postcode":"j9v 2b7",
    "addr:street":"Rue Sainte-Anne",
    "iso:country":"CA",
    "sg:address":"42 Rue Sainte-Anne",
    "sg:city":"Ville-Marie",
    "sg:classifiers":[
        {
            "category":"Museum",
            "type":"Entertainment"
        }
    ],
    "sg:phone":"+1 819 622 1362",
    "sg:postcode":"J9V 2B7",
    "sg:province":"QC",
    "sg:tags":[
        "organization",
        "recreation",
        "arts",
        "amusement",
        "information"
    ],
    "wof:name":"Salle Augustin-Chenier",
    "wof:placetype":"venue"
},
  "geometry": {"coordinates":[-79.43860599999999,47.331264],"type":"Point"}
}