{
  "type": "Feature",
  "properties": {
    "iso:country":"CA",
    "sg:address":"150 Boul Tache O",
    "sg:city":"Montmagny",
    "sg:classifiers":[
        {
            "category":"Autos & Motor Vehicles",
            "subcategory":"Automobile Sales",
            "type":"Retail Goods"
        }
    ],
    "sg:phone":"+1 418 248 7877",
    "sg:postcode":"G5V 3A5",
    "sg:province":"QC",
    "sg:tags":[
        "car",
        "dealer"
    ],
    "wof:name":"Montmagny Hyundai",
    "wof:placetype":"venue"
},
  "geometry": {"coordinates":[-70.5561828613,46.9840698242],"type":"Point"}
}