{
  "type": "Feature",
  "properties": {
    "iso:country":"CA",
    "sg:city":"Brooks",
    "sg:classifiers":[
        {
            "category":"Building & Trades",
            "subcategory":"Construction",
            "type":"Services"
        }
    ],
    "sg:phone":"+1 403 362 5243",
    "sg:postcode":"T1R 1C7",
    "sg:province":"AB",
    "sg:tags":[
        "excavating",
        "contractor",
        "trucking"
    ],
    "wof:name":"Blue Line Truck Svc Ltd",
    "wof:placetype":"venue"
},
  "geometry": {"coordinates":[-111.89849090600001,50.5658531189],"type":"Point"}
}