{
  "type": "Feature",
  "properties": {
    "addr:full":"3003 Danforth Ave # 46 East York ON M4C 1M9",
    "addr:housenumber":"3003",
    "addr:postcode":"m4c 1m9",
    "addr:street":"Danforth Ave # 46",
    "iso:country":"CA",
    "sg:address":"3003 Danforth Ave # 46",
    "sg:city":"East York",
    "sg:classifiers":[
        {
            "category":"Shopping",
            "type":"Retail Goods"
        }
    ],
    "sg:phone":"+1 416 693 0196",
    "sg:postcode":"M4C 1M9",
    "sg:province":"ON",
    "sg:tags":[
        "pet",
        "food",
        "supply"
    ],
    "wof:name":"Pet Valu Discount Pet Foods",
    "wof:placetype":"venue"
},
  "geometry": {"coordinates":[-79.2915725708,43.6903800964],"type":"Point"}
}