{
  "type": "Feature",
  "properties": {
    "addr:full":"985 Rue Jean-Talon O Montreal QC H3N 1S9",
    "addr:housenumber":"985",
    "addr:postcode":"h3n 1s9",
    "addr:street":"Rue Jean-Talon O",
    "iso:country":"CA",
    "sg:address":"985 Rue Jean-Talon O",
    "sg:city":"Montreal",
    "sg:classifiers":[
        {
            "category":"Shopping",
            "subcategory":"Crafts & Fabrics",
            "type":"Retail Goods"
        }
    ],
    "sg:phone":"+1 514 278 6632",
    "sg:postcode":"H3N 1S9",
    "sg:province":"QC",
    "sg:tags":[
        "shop"
    ],
    "wof:name":"Sandhu Textiles",
    "wof:placetype":"venue"
},
  "geometry": {"coordinates":[-73.612846,45.541588],"type":"Point"}
}