{
  "type": "Feature",
  "properties": {
    "addr:full":"Red Deer AB T4N 2R2",
    "addr:postcode":"t4n 2r2",
    "iso:country":"CA",
    "sg:city":"Red Deer",
    "sg:classifiers":[
        {
            "category":"Home & Garden",
            "subcategory":"Building Materials",
            "type":"Retail Goods"
        }
    ],
    "sg:phone":"+1 403 346 5189",
    "sg:postcode":"T4N 2R2",
    "sg:province":"AB",
    "sg:tags":[
        "door"
    ],
    "wof:name":"Cwd Windows & Doors",
    "wof:placetype":"venue"
},
  "geometry": {"coordinates":[-113.804108,52.28376],"type":"Point"}
}