{
  "type": "Feature",
  "properties": {
    "iso:country":"CA",
    "sg:address":"2214 Boul Rene-Levesque O # 200",
    "sg:city":"Montreal",
    "sg:classifiers":[
        {
            "category":"Real Estate",
            "subcategory":"Real Estate Agent",
            "type":"Services"
        }
    ],
    "sg:phone":"+1 514 933 8040",
    "sg:postcode":"H3H 1R6",
    "sg:province":"QC",
    "sg:tags":[
        "management"
    ],
    "wof:name":"Braxo Enterprises Inc",
    "wof:placetype":"venue"
},
  "geometry": {"coordinates":[-73.581093,45.488651],"type":"Point"}
}