{
  "type": "Feature",
  "properties": {
    "addr:full":"Wyoming ON N0N 1T0",
    "addr:postcode":"n0n 1t0",
    "iso:country":"CA",
    "sg:city":"Wyoming",
    "sg:classifiers":[
        {
            "category":"Food & Beverages",
            "subcategory":"Candy",
            "type":"Retail Goods"
        }
    ],
    "sg:phone":"+1 519 845 0620",
    "sg:postcode":"N0N 1T0",
    "sg:province":"ON",
    "sg:tags":[
        "making",
        "supply"
    ],
    "wof:name":"Isn't Life Sweet Cakes Candies",
    "wof:placetype":"venue"
},
  "geometry": {"coordinates":[-82.12188,42.979679],"type":"Point"}
}