{
  "type": "Feature",
  "properties": {
    "addr:full":"Stanbridge Station QC J0J 2J0",
    "addr:postcode":"j0j 2j0",
    "iso:country":"CA",
    "sg:city":"Stanbridge Station",
    "sg:classifiers":[
        {
            "category":"Retail",
            "subcategory":"Auto Repair",
            "type":"Services"
        }
    ],
    "sg:phone":"+1 450 248 2482",
    "sg:postcode":"J0J 2J0",
    "sg:province":"QC",
    "sg:tags":[
        "body",
        "automobile",
        "painting"
    ],
    "wof:name":"R Cadieux Debosselage & Pntr",
    "wof:placetype":"venue"
},
  "geometry": {"coordinates":[-73.03389,45.122604],"type":"Point"}
}