{
  "type": "Feature",
  "properties": {
    "iso:country":"CA",
    "sg:city":"Dartmouth",
    "sg:classifiers":[
        {
            "category":"Shopping",
            "subcategory":"Computers & Home Electronics",
            "type":"Retail Goods"
        }
    ],
    "sg:phone":"+1 902 468 2671",
    "sg:postcode":"B3B 1T4",
    "sg:province":"NS",
    "sg:tags":[
        "equipment",
        "dealer"
    ],
    "wof:name":"Toshiba of Canada Ltd",
    "wof:placetype":"venue"
},
  "geometry": {"coordinates":[-63.5878334045,44.7030715942],"type":"Point"}
}