{
  "type": "Feature",
  "properties": {
    "addr:full":"1230 17 Ave SW Calgary AB T2T 0B8",
    "addr:housenumber":"1230",
    "addr:postcode":"t2t 0b8",
    "addr:street":"17 Ave Sw",
    "iso:country":"CA",
    "sg:address":"1230 17 Ave SW",
    "sg:city":"Calgary",
    "sg:classifiers":[
        {
            "category":"Social Services",
            "type":"Services"
        }
    ],
    "sg:phone":"+1 403 605 3274",
    "sg:postcode":"T2T 0B8",
    "sg:province":"AB",
    "sg:tags":[
        "counseling"
    ],
    "wof:name":"Bow River Counselling",
    "wof:placetype":"venue"
},
  "geometry": {"coordinates":[-114.090515137,51.0380249023],"type":"Point"}
}