{
  "type": "Feature",
  "properties": {
    "iso:country":"CA",
    "sg:address":"1167 Route 3",
    "sg:city":"Harvey York CO",
    "sg:classifiers":[
        {
            "category":"Health Services",
            "subcategory":"Health Practitioner",
            "type":"Services"
        }
    ],
    "sg:phone":"+1 506 366 2882",
    "sg:postcode":"E6K 2S3",
    "sg:province":"NB",
    "sg:tags":[
        "psychologist"
    ],
    "wof:name":"Smerdon Psychological Svc",
    "wof:placetype":"venue"
},
  "geometry": {"coordinates":[-67.3256225586,45.5988044739],"type":"Point"}
}