{
  "type": "Feature",
  "properties": {
    "addr:full":"1 Rue Principale N Saint-Jean-DE-Dieu QC G0L 3M0",
    "addr:housenumber":"1",
    "addr:postcode":"g0l 3m0",
    "addr:street":"Rue Principale N",
    "iso:country":"CA",
    "sg:address":"1 Rue Principale N",
    "sg:city":"Saint-Jean-DE-Dieu",
    "sg:classifiers":[
        {
            "category":"Shopping",
            "subcategory":"Clothing, Apparel, & Fashions",
            "type":"Retail Goods"
        }
    ],
    "sg:phone":"+1 418 963 2027",
    "sg:postcode":"G0L 3M0",
    "sg:province":"QC",
    "sg:tags":[
        "item",
        "boutique"
    ],
    "wof:name":"Boutique Emmanuelle Inc",
    "wof:placetype":"venue"
},
  "geometry": {"coordinates":[-69.04615020750001,48.0036239624],"type":"Point"}
}