{
  "type": "Feature",
  "properties": {
    "addr:full":"3755 Rue Sainte-Catherine E Montreal QC H1W 2E9",
    "addr:housenumber":"3755",
    "addr:postcode":"h1w 2e9",
    "addr:street":"Rue Sainte-Catherine E",
    "iso:country":"CA",
    "sg:address":"3755 Rue Sainte-Catherine E",
    "sg:city":"Montreal",
    "sg:classifiers":[
        {
            "category":"Restaurant",
            "type":"Food & Drink"
        }
    ],
    "sg:phone":"+1 514 340 1483",
    "sg:postcode":"H1W 2E9",
    "sg:province":"QC",
    "sg:tags":[
        "shop",
        "coffee"
    ],
    "wof:name":"Second Cup",
    "wof:placetype":"venue"
},
  "geometry": {"coordinates":[-73.53789500000001,45.544758],"type":"Point"}
}