{
  "type": "Feature",
  "properties": {
    "addr:full":"15244 Russell Ave White Rock BC V4B 2P6",
    "addr:housenumber":"15244",
    "addr:postcode":"v4b 2p6",
    "addr:street":"Russell Ave",
    "iso:country":"CA",
    "sg:address":"15244 Russell Ave",
    "sg:city":"White Rock",
    "sg:classifiers":[
        {
            "category":"Travel",
            "subcategory":"Travel Agent",
            "type":"Entertainment"
        }
    ],
    "sg:phone":"+1 604 536 7674",
    "sg:postcode":"V4B 2P6",
    "sg:province":"BC",
    "sg:tags":[
        "agency",
        "bureau"
    ],
    "wof:name":"Posh Travel & Cruises Ltd",
    "wof:placetype":"venue"
},
  "geometry": {"coordinates":[-122.799438477,49.0292510986],"type":"Point"}
}