{
  "type": "Feature",
  "properties": {
    "addr:full":"28 Lankin Blvd Orillia ON L3V 6T2",
    "addr:housenumber":"28",
    "addr:postcode":"l3v 6t2",
    "addr:street":"Lankin Blvd",
    "iso:country":"CA",
    "sg:address":"28 Lankin Blvd",
    "sg:city":"Orillia",
    "sg:classifiers":[
        {
            "category":"Building & Trades",
            "subcategory":"Construction",
            "type":"Services"
        }
    ],
    "sg:phone":"+1 705 327 1504",
    "sg:postcode":"L3V 6T2",
    "sg:province":"ON",
    "sg:tags":[
        "home",
        "improvement"
    ],
    "wof:name":"Builder's Choice",
    "wof:placetype":"venue"
},
  "geometry": {"coordinates":[-79.39506530760001,44.5963821411],"type":"Point"}
}