{
  "type": "Feature",
  "properties": {
    "addr:full":"82 Marr Rd Rothesay NB E2E 3J9",
    "addr:housenumber":"82",
    "addr:postcode":"e2e 3j9",
    "addr:street":"Marr Rd",
    "iso:country":"CA",
    "sg:address":"82 Marr Rd",
    "sg:city":"Rothesay",
    "sg:classifiers":[
        {
            "category":"Autos & Motor Vehicles",
            "subcategory":"Motorcycle Sales",
            "type":"Retail Goods"
        }
    ],
    "sg:phone":"+1 506 849 8899",
    "sg:postcode":"E2E 3J9",
    "sg:province":"NB",
    "sg:tags":[
        "all",
        "terrain"
    ],
    "wof:name":"All Star Recreation",
    "wof:placetype":"venue"
},
  "geometry": {"coordinates":[-65.9693145752,45.3906555176],"type":"Point"}
}