{
  "type": "Feature",
  "properties": {
    "addr:full":"Saint-Lambert QC J4P 2J4",
    "addr:postcode":"j4p 2j4",
    "iso:country":"CA",
    "sg:city":"Saint-Lambert",
    "sg:classifiers":[
        {
            "category":"Freight",
            "type":"Transportation"
        }
    ],
    "sg:phone":"+1 450 466 7266",
    "sg:postcode":"J4P 2J4",
    "sg:province":"QC",
    "sg:tags":[
        "broker",
        "trucking"
    ],
    "wof:name":"Entreprises Ppt",
    "wof:placetype":"venue"
},
  "geometry": {"coordinates":[-73.511551,45.501659],"type":"Point"}
}