{
  "type": "Feature",
  "properties": {
    "addr:full":"Mississauga ON L4Z 2H7",
    "addr:postcode":"l4z 2h7",
    "iso:country":"CA",
    "sg:city":"Mississauga",
    "sg:classifiers":[
        {
            "category":"Restaurant",
            "type":"Food & Drink"
        }
    ],
    "sg:phone":"+1 905 890 6222",
    "sg:postcode":"L4Z 2H7",
    "sg:province":"ON",
    "wof:name":"C J Restaurant",
    "wof:placetype":"venue"
},
  "geometry": {"coordinates":[-79.6709823608,43.6257400513],"type":"Point"}
}