{
  "type": "Feature",
  "properties": {
    "addr:full":"749 Redwood Dr Qualicum Beach BC V9K 2J2",
    "addr:housenumber":"749",
    "addr:postcode":"v9k 2j2",
    "addr:street":"Redwood Dr",
    "iso:country":"CA",
    "sg:address":"749 Redwood Dr",
    "sg:city":"Qualicum Beach",
    "sg:classifiers":[
        {
            "category":"Social Services",
            "type":"Services"
        }
    ],
    "sg:phone":"+1 250 752 0054",
    "sg:postcode":"V9K 2J2",
    "sg:province":"BC",
    "sg:tags":[
        "counselor",
        "marriage",
        "family"
    ],
    "wof:name":"Josiah's Place of Family",
    "wof:placetype":"venue"
},
  "geometry": {"coordinates":[-124.41142273,49.3501586914],"type":"Point"}
}