{
  "type": "Feature",
  "properties": {
    "addr:full":"22 Rue Brigantine Kirkland QC H9H 5A7",
    "addr:housenumber":"22",
    "addr:postcode":"h9h 5a7",
    "addr:street":"Rue Brigantine",
    "iso:country":"CA",
    "sg:address":"22 Rue Brigantine",
    "sg:city":"Kirkland",
    "sg:classifiers":[
        {
            "category":"Manufacturing",
            "subcategory":"Tools & Machinery",
            "type":"Manufacturing & Wholesale Goods"
        }
    ],
    "sg:phone":"+1 514 695 9000",
    "sg:postcode":"H9H 5A7",
    "sg:province":"QC",
    "sg:tags":[
        "equipment",
        "sawmill",
        "kiln",
        "supply"
    ],
    "wof:name":"Secovac International",
    "wof:placetype":"venue"
},
  "geometry": {"coordinates":[-73.8520736694,45.4596061707],"type":"Point"}
}