{
  "type": "Feature",
  "properties": {
    "iso:country":"CA",
    "sg:city":"Richmond",
    "sg:classifiers":[
        {
            "category":"Health Services",
            "subcategory":"Health Practitioner",
            "type":"Services"
        }
    ],
    "sg:phone":"+1 604 273 2863",
    "sg:postcode":"V6X 4E4",
    "sg:province":"BC",
    "sg:tags":[
        "acupuncture"
    ],
    "wof:name":"Natural Life Herbs",
    "wof:placetype":"venue"
},
  "geometry": {"coordinates":[-123.136512756,49.1631584167],"type":"Point"}
}