{
  "type": "Feature",
  "properties": {
    "addr:full":"230 Montee Saint-Regis Saint-Constant QC J5A 2E7",
    "addr:housenumber":"230",
    "addr:postcode":"j5a 2e7",
    "addr:street":"Montee Saint-Regis",
    "iso:country":"CA",
    "sg:address":"230 Montee Saint-Regis",
    "sg:city":"Saint-Constant",
    "sg:classifiers":[
        {
            "category":"Home & Garden",
            "subcategory":"Building Materials",
            "type":"Retail Goods"
        }
    ],
    "sg:phone":"+1 450 638 2265",
    "sg:postcode":"J5A 2E7",
    "sg:province":"QC",
    "sg:tags":[
        "glass",
        "window",
        "plate"
    ],
    "wof:name":"Vitrerie Lemieux",
    "wof:placetype":"venue"
},
  "geometry": {"coordinates":[-73.590546,45.371181],"type":"Point"}
}