{
  "type": "Feature",
  "properties": {
    "addr:full":"1330 Rang DE LA Riviere S Sainte-Elisabeth QC J0K 2J0",
    "addr:housenumber":"1330",
    "addr:postcode":"j0k 2j0",
    "addr:street":"Rang De La Riviere S Sainte-Elisabeth",
    "iso:country":"CA",
    "sg:address":"1330 Rang DE LA Riviere S",
    "sg:city":"Sainte-Elisabeth",
    "sg:classifiers":[
        {
            "category":"Health Services",
            "subcategory":"Health Practitioner",
            "type":"Services"
        }
    ],
    "sg:phone":"+1 450 759 0752",
    "sg:postcode":"J0K 2J0",
    "sg:province":"QC",
    "sg:tags":[
        "psychologist"
    ],
    "wof:name":"Girard, Yvon",
    "wof:placetype":"venue"
},
  "geometry": {"coordinates":[-73.287094,46.097416],"type":"Point"}
}