{
  "type": "Feature",
  "properties": {
    "addr:full":"Williams Lake BC V2G 1J1",
    "addr:postcode":"bc v2g 1j1",
    "iso:country":"CA",
    "sg:city":"Williams Lake",
    "sg:classifiers":[
        {
            "category":"Government",
            "subcategory":"Office",
            "type":"Public Place"
        }
    ],
    "sg:phone":"+1 250 392 2626",
    "sg:postcode":"V2G 1J1",
    "sg:province":"BC",
    "wof:name":"Members of Parliament",
    "wof:placetype":"venue"
},
  "geometry": {"coordinates":[-122.14254800000001,52.127232],"type":"Point"}
}