{
  "type": "Feature",
  "properties": {
    "addr:full":"46 Mcnevin St Providence Bay ON P0P 1T0",
    "addr:housenumber":"46",
    "addr:postcode":"p0p 1t0",
    "addr:street":"Mcnevin St",
    "iso:country":"CA",
    "sg:address":"46 Mcnevin St",
    "sg:city":"Providence Bay",
    "sg:classifiers":[
        {
            "category":"Restaurant",
            "type":"Food & Drink"
        }
    ],
    "sg:phone":"+1 705 377 4055",
    "sg:postcode":"P0P 1T0",
    "sg:province":"ON",
    "wof:name":"School House",
    "wof:placetype":"venue"
},
  "geometry": {"coordinates":[-82.26438903810001,45.6640815735],"type":"Point"}
}