{
  "type": "Feature",
  "properties": {
    "addr:full":"2869 Melbourne Rd Arcadia NS B0W 1B0",
    "addr:housenumber":"2869",
    "addr:postcode":"b0w 1b0",
    "addr:street":"Melbourne Rd",
    "iso:country":"CA",
    "sg:address":"2869 Melbourne Rd",
    "sg:city":"Arcadia",
    "sg:classifiers":[
        {
            "category":"Food & Beverages",
            "subcategory":"Meat & Fish",
            "type":"Retail Goods"
        }
    ],
    "sg:phone":"+1 902 742 2271",
    "sg:postcode":"B0W 1B0",
    "sg:province":"NS",
    "sg:tags":[
        "lobster"
    ],
    "wof:name":"Estrela Domar Fisheries Ltd",
    "wof:placetype":"venue"
},
  "geometry": {"coordinates":[-66.068832,43.825508],"type":"Point"}
}