{
  "type": "Feature",
  "properties": {
    "addr:full":"150 First St Collingwood ON L9Y 1A4",
    "addr:housenumber":"150",
    "addr:postcode":"l9y 1a4",
    "addr:street":"First St",
    "iso:country":"CA",
    "sg:address":"150 First St",
    "sg:city":"Collingwood",
    "sg:classifiers":[
        {
            "category":"Sports & Exercise",
            "subcategory":"Gym",
            "type":"Entertainment"
        }
    ],
    "sg:phone":"+1 705 444 0001",
    "sg:postcode":"L9Y 1A4",
    "sg:province":"ON",
    "sg:tags":[
        "club",
        "gymnasium",
        "program",
        "health",
        "fitness",
        "studio",
        "physical"
    ],
    "wof:name":"Curves For Women",
    "wof:placetype":"venue"
},
  "geometry": {"coordinates":[-80.2216873169,44.502281189],"type":"Point"}
}