{
  "type": "Feature",
  "properties": {
    "addr:full":"St-Peters Bay PE C0A 2A0",
    "addr:postcode":"c0a 2a0",
    "iso:country":"CA",
    "sg:city":"St-Peters Bay",
    "sg:classifiers":[
        {
            "category":"Organizations",
            "subcategory":"Religious Organization",
            "type":"Services"
        }
    ],
    "sg:phone":"+1 902 961 2936",
    "sg:postcode":"C0A 2A0",
    "sg:province":"PE",
    "sg:tags":[
        "church"
    ],
    "wof:name":"Upton Gospel Chapel",
    "wof:placetype":"venue"
},
  "geometry": {"coordinates":[-62.5824737549,46.4181213379],"type":"Point"}
}