{
  "type": "Feature",
  "properties": {
    "addr:full":"2nd St Dock Kenora ON P9N 3X7",
    "addr:postcode":"p9n 3x7",
    "addr:street":"2Nd St Dock",
    "iso:country":"CA",
    "sg:address":"2nd St Dock",
    "sg:city":"Kenora",
    "sg:classifiers":[
        {
            "category":"Building & Trades",
            "subcategory":"Equipment Rental",
            "type":"Services"
        }
    ],
    "sg:phone":"+1 807 468 9818",
    "sg:postcode":"P9N 3X7",
    "sg:province":"ON",
    "sg:tags":[
        "aircraft",
        "charter",
        "leasing",
        "company",
        "airline"
    ],
    "wof:name":"Kenora Air Svc Ltd",
    "wof:placetype":"venue"
},
  "geometry": {"coordinates":[-94.489311,49.770626],"type":"Point"}
}