{
  "type": "Feature",
  "properties": {
    "iso:country":"CA",
    "sg:address":"18386 Rue Joseph-Wilson",
    "sg:city":"Pierrefonds",
    "sg:classifiers":[
        {
            "category":"Manufacturing",
            "subcategory":"Printing",
            "type":"Manufacturing & Wholesale Goods"
        }
    ],
    "sg:phone":"+1 514 620 6176",
    "sg:postcode":"H9K 1H2",
    "sg:province":"QC",
    "sg:tags":[
        "printer"
    ],
    "wof:name":"Impressions By Daria Inc",
    "wof:placetype":"venue"
},
  "geometry": {"coordinates":[-73.892784,45.460873],"type":"Point"}
}