{
  "type": "Feature",
  "properties": {
    "addr:full":"270 Rue Bouchard L'Assomption QC J5W 1J4",
    "addr:housenumber":"270",
    "addr:postcode":"j5w 1j4",
    "addr:street":"Rue Bouchard",
    "iso:country":"CA",
    "sg:address":"270 Rue Bouchard",
    "sg:city":"L'Assomption",
    "sg:classifiers":[
        {
            "category":"Freight",
            "type":"Transportation"
        }
    ],
    "sg:phone":"+1 450 589 6886",
    "sg:postcode":"J5W 1J4",
    "sg:province":"QC",
    "sg:tags":[
        "trucking"
    ],
    "wof:name":"Archambault, Marcel",
    "wof:placetype":"venue"
},
  "geometry": {"coordinates":[-73.441025,45.824905],"type":"Point"}
}