{
  "type": "Feature",
  "properties": {
    "addr:full":"3265 Mountbatten Cres Regina SK S4V 0R5",
    "addr:housenumber":"3265",
    "addr:postcode":"s4v 0r5",
    "addr:street":"Mountbatten Cres",
    "iso:country":"CA",
    "sg:address":"3265 Mountbatten Cres",
    "sg:city":"Regina",
    "sg:classifiers":[
        {
            "category":"Personal",
            "type":"Services"
        }
    ],
    "sg:phone":"+1 306 586 6013",
    "sg:postcode":"S4V 0R5",
    "sg:province":"SK",
    "sg:tags":[
        "welcoming",
        "newcomer",
        "for"
    ],
    "wof:name":"Welcome Wagon",
    "wof:placetype":"venue"
},
  "geometry": {"coordinates":[-104.549995,50.425816],"type":"Point"}
}