{
  "type": "Feature",
  "properties": {
    "iso:country":"CA",
    "sg:address":"25 Museum Dr",
    "sg:city":"Orillia",
    "sg:classifiers":[
        {
            "category":"Health Services",
            "subcategory":"Nursing And Care Facility",
            "type":"Services"
        }
    ],
    "sg:phone":"+1 705 325 9181",
    "sg:postcode":"L3V 7T9",
    "sg:province":"ON",
    "sg:tags":[
        "home",
        "convalescent"
    ],
    "wof:name":"Leacock Care Ctr",
    "wof:placetype":"venue"
},
  "geometry": {"coordinates":[-79.396049,44.60701],"type":"Point"}
}