{
  "type": "Feature",
  "properties": {
    "addr:full":"9 Patterson Rd Orillia ON L3V 6H1",
    "addr:housenumber":"9",
    "addr:postcode":"l3v 6h1",
    "addr:street":"Patterson Rd",
    "iso:country":"CA",
    "sg:address":"9 Patterson Rd",
    "sg:city":"Orillia",
    "sg:classifiers":[
        {
            "category":"Building & Trades",
            "subcategory":"Landscaping Services",
            "type":"Services"
        }
    ],
    "sg:phone":"+1 705 325 8064",
    "sg:postcode":"L3V 6H1",
    "sg:province":"ON",
    "sg:tags":[
        "landscape",
        "contractor"
    ],
    "wof:name":"Shoreline Construction",
    "wof:placetype":"venue"
},
  "geometry": {"coordinates":[-79.418228,44.60659],"type":"Point"}
}