{
  "type": "Feature",
  "properties": {
    "addr:full":"4710 Slocan St Vancouver BC V5R 2A1",
    "addr:housenumber":"4710",
    "addr:postcode":"v5r 2a1",
    "addr:street":"Slocan St",
    "iso:country":"CA",
    "sg:address":"4710 Slocan St",
    "sg:city":"Vancouver",
    "sg:classifiers":[
        {
            "category":"Education",
            "subcategory":"School",
            "type":"Public Place"
        }
    ],
    "sg:phone":"+1 604 713 4666",
    "sg:postcode":"V5R 2A1",
    "sg:province":"BC",
    "wof:name":"John Norquay Elementary School",
    "wof:placetype":"venue"
},
  "geometry": {"coordinates":[-123.051636,49.242199],"type":"Point"}
}