{
  "type": "Feature",
  "properties": {
    "addr:full":"115 Select Ave Scarborough ON M1V 4A5",
    "addr:housenumber":"115",
    "addr:postcode":"m1v 4a5",
    "addr:street":"Select Ave",
    "iso:country":"CA",
    "sg:address":"115 Select Ave",
    "sg:city":"Scarborough",
    "sg:classifiers":[
        {
            "category":"Wholesale",
            "subcategory":"Electrical",
            "type":"Manufacturing & Wholesale Goods"
        }
    ],
    "sg:phone":"+1 416 754 7539",
    "sg:postcode":"M1V 4A5",
    "sg:province":"ON",
    "sg:tags":[
        "printer"
    ],
    "wof:name":"Electro Circuit Inc",
    "wof:placetype":"venue"
},
  "geometry": {"coordinates":[-79.25862884519999,43.8311882019],"type":"Point"}
}