{
  "type": "Feature",
  "properties": {
    "addr:full":"2052 St Joseph Blvd Orleans ON K1C 1E6",
    "addr:housenumber":"2052",
    "addr:postcode":"k1c 1e6",
    "addr:street":"St Joseph Blvd",
    "iso:country":"CA",
    "sg:address":"2052 St Joseph Blvd",
    "sg:city":"Orleans",
    "sg:classifiers":[
        {
            "category":"Professional",
            "subcategory":"Accounting & Tax Preparation",
            "type":"Services"
        }
    ],
    "sg:phone":"+1 613 837 8858",
    "sg:postcode":"K1C 1E6",
    "sg:province":"ON",
    "sg:tags":[
        "accountant"
    ],
    "wof:name":"Consultation Roger Millette",
    "wof:placetype":"venue"
},
  "geometry": {"coordinates":[-75.536789,45.465519],"type":"Point"}
}