{
  "type": "Feature",
  "properties": {
    "addr:full":"6336 Av Papineau Montreal QC H2G 2W9",
    "addr:housenumber":"6336",
    "addr:postcode":"h2g 2w9",
    "addr:street":"Av Papineau",
    "iso:country":"CA",
    "sg:address":"6336 Av Papineau",
    "sg:city":"Montreal",
    "sg:classifiers":[
        {
            "category":"Personal",
            "subcategory":"Beauty Salon",
            "type":"Services"
        }
    ],
    "sg:phone":"+1 514 495 1804",
    "sg:postcode":"H2G 2W9",
    "sg:province":"QC",
    "wof:name":"Salon Sylvia Enr",
    "wof:placetype":"venue"
},
  "geometry": {"coordinates":[-73.5949249268,45.5422096252],"type":"Point"}
}