{
  "type": "Feature",
  "properties": {
    "iso:country":"CA",
    "sg:address":"208 Mackenzie Ave",
    "sg:city":"Revelstoke",
    "sg:classifiers":[
        {
            "category":"Shopping",
            "subcategory":"Books",
            "type":"Retail Goods"
        }
    ],
    "sg:phone":"+1 250 837 6185",
    "sg:postcode":"V0E 2S0",
    "sg:province":"BC",
    "sg:tags":[
        "dealer"
    ],
    "wof:name":"Grizzly Book & Serendipity",
    "wof:placetype":"venue"
},
  "geometry": {"coordinates":[-118.195274353,50.9985694885],"type":"Point"}
}