{
  "type": "Feature",
  "properties": {
    "iso:country":"CA",
    "sg:address":"3338 Rue Principale",
    "sg:city":"Saint-Simon-Les-Mines",
    "sg:classifiers":[
        {
            "category":"Banks & Credit Unions",
            "subcategory":"Bank",
            "type":"Services"
        }
    ],
    "sg:phone":"+1 418 228 8824",
    "sg:postcode":"G0M 1K0",
    "sg:province":"QC",
    "wof:name":"Caisses Desjardins",
    "wof:placetype":"venue"
},
  "geometry": {"coordinates":[-70.6794052124,46.2092590332],"type":"Point"}
}