{
  "type": "Feature",
  "properties": {
    "iso:country":"CA",
    "sg:address":"35 West Deane Park Dr",
    "sg:city":"Etobicoke",
    "sg:classifiers":[
        {
            "category":"Education",
            "subcategory":"School",
            "type":"Public Place"
        }
    ],
    "sg:phone":"+1 416 393 5413",
    "sg:postcode":"M9B 2R5",
    "sg:province":"ON",
    "wof:name":"Josyf Cardinal Slipyj",
    "wof:placetype":"venue"
},
  "geometry": {"coordinates":[-79.564758,43.659534],"type":"Point"}
}