{
  "type": "Feature",
  "properties": {
    "iso:country":"CA",
    "sg:address":"80 Industrial Court A",
    "sg:city":"Sault Ste Marie",
    "sg:classifiers":[
        {
            "category":"Home & Garden",
            "subcategory":"Building Materials",
            "type":"Retail Goods"
        }
    ],
    "sg:phone":"+1 705 942 0627",
    "sg:postcode":"P6B 5W6",
    "sg:province":"ON",
    "sg:tags":[
        "mixed",
        "concrete"
    ],
    "wof:name":"Lafarge Construction Materials",
    "wof:placetype":"venue"
},
  "geometry": {"coordinates":[-84.3274383545,46.5487442017],"type":"Point"}
}