{
  "type": "Feature",
  "properties": {
    "iso:country":"CA",
    "sg:address":"4402 42 Ave",
    "sg:city":"Stettler",
    "sg:classifiers":[
        {
            "category":"Autos & Motor Vehicles",
            "subcategory":"Automobile Sales",
            "type":"Retail Goods"
        }
    ],
    "sg:phone":"+1 403 742 4477",
    "sg:postcode":"T0C 2L1",
    "sg:province":"AB",
    "sg:tags":[
        "car",
        "dealer"
    ],
    "wof:name":"Swallow Ford Sales Ltd",
    "wof:placetype":"venue"
},
  "geometry": {"coordinates":[-112.692009,52.318199],"type":"Point"}
}