{
  "type": "Feature",
  "properties": {
    "addr:full":"7575 Rte Transcanadienne # 500 Saint-Laurent QC H4T 1V6",
    "addr:housenumber":"7575",
    "addr:postcode":"h4t 1v6",
    "addr:street":"Rte Transcanadienne # 500",
    "iso:country":"CA",
    "sg:address":"7575 Rte Transcanadienne # 500",
    "sg:city":"Saint-Laurent",
    "sg:classifiers":[
        {
            "category":"Professional",
            "subcategory":"Credit Reporting & Collection",
            "type":"Services"
        }
    ],
    "sg:phone":"+1 514 337 9091",
    "sg:postcode":"H4T 1V6",
    "sg:province":"QC",
    "sg:tags":[
        "agency"
    ],
    "wof:name":"Agence DE Recouvrement Com",
    "wof:placetype":"venue"
},
  "geometry": {"coordinates":[-73.710876,45.489342],"type":"Point"}
}