{
  "type": "Feature",
  "properties": {
    "addr:full":"Truro NS B2N 2K3",
    "addr:postcode":"b2n 2k3",
    "iso:country":"CA",
    "sg:city":"Truro",
    "sg:classifiers":[
        {
            "category":"Building & Trades",
            "subcategory":"Equipment Rental",
            "type":"Services"
        }
    ],
    "sg:phone":"+1 902 897 0700",
    "sg:postcode":"B2N 2K3",
    "sg:province":"NS",
    "sg:tags":[
        "leasing"
    ],
    "wof:name":"Truro Centre Ltd",
    "wof:placetype":"venue"
},
  "geometry": {"coordinates":[-63.2762451172,45.3627166748],"type":"Point"}
}