{
  "type": "Feature",
  "properties": {
    "addr:full":"5770 Place Kubota Drummondville QC J2B 6V4",
    "addr:housenumber":"5770",
    "addr:postcode":"j2b 6v4",
    "addr:street":"Place Kubota",
    "iso:country":"CA",
    "sg:address":"5770 Place Kubota",
    "sg:city":"Drummondville",
    "sg:classifiers":[
        {
            "category":"Autos & Motor Vehicles",
            "subcategory":"Automobile Sales",
            "type":"Retail Goods"
        }
    ],
    "sg:phone":"+1 819 474 2264",
    "sg:postcode":"J2B 6V4",
    "sg:province":"QC",
    "sg:tags":[
        "truck"
    ],
    "wof:name":"Camions Bl Freightliner Enr",
    "wof:placetype":"venue"
},
  "geometry": {"coordinates":[-72.53800964360001,45.8934402466],"type":"Point"}
}