{
  "type": "Feature",
  "properties": {
    "addr:full":"Montreal QC H3W 2S7",
    "addr:postcode":"h3w 2s7",
    "iso:country":"CA",
    "sg:city":"Montreal",
    "sg:classifiers":[
        {
            "category":"Shopping",
            "subcategory":"Pharmacy",
            "type":"Retail Goods"
        }
    ],
    "sg:phone":"+1 514 733 9586",
    "sg:postcode":"H3W 2S7",
    "sg:province":"QC",
    "wof:name":"Pharmacie N Lethi",
    "wof:placetype":"venue"
},
  "geometry": {"coordinates":[-73.639931,45.495255],"type":"Point"}
}