{
  "type": "Feature",
  "properties": {
    "iso:country":"CA",
    "sg:address":"63 Church St",
    "sg:city":"St Catharines",
    "sg:classifiers":[
        {
            "category":"Ferry",
            "type":"Transportation"
        }
    ],
    "sg:phone":"+1 905 687 7838",
    "sg:postcode":"L2R 3C4",
    "sg:province":"ON",
    "sg:tags":[
        "company",
        "steamship"
    ],
    "wof:name":"Algoma Tankers",
    "wof:placetype":"venue"
},
  "geometry": {"coordinates":[-79.2468261719,43.1603507996],"type":"Point"}
}