{
  "type": "Feature",
  "properties": {
    "addr:full":"33447 Dewdney Trunk Rd Mission BC V2V 6Y3",
    "addr:housenumber":"33447",
    "addr:postcode":"v2v 6y3",
    "addr:street":"Dewdney Trunk Rd",
    "iso:country":"CA",
    "sg:address":"33447 Dewdney Trunk Rd",
    "sg:city":"Mission",
    "sg:classifiers":[
        {
            "category":"Social Services",
            "subcategory":"Child Care",
            "type":"Services"
        }
    ],
    "sg:phone":"+1 604 820 4997",
    "sg:postcode":"V2V 6Y3",
    "sg:province":"BC",
    "wof:name":"Mission Montessori Preschool",
    "wof:placetype":"venue"
},
  "geometry": {"coordinates":[-122.29814910899999,49.1584358215],"type":"Point"}
}