{
  "type": "Feature",
  "properties": {
    "addr:full":"150 Armstrong Ave Georgetown ON L7G 5G8",
    "addr:housenumber":"150",
    "addr:postcode":"l7g 5g8",
    "addr:street":"Armstrong Ave",
    "iso:country":"CA",
    "sg:address":"150 Armstrong Ave",
    "sg:city":"Georgetown",
    "sg:classifiers":[
        {
            "category":"Manufacturing",
            "subcategory":"Tools & Machinery",
            "type":"Manufacturing & Wholesale Goods"
        }
    ],
    "sg:phone":"+1 905 873 8739",
    "sg:postcode":"L7G 5G8",
    "sg:province":"ON",
    "sg:tags":[
        "die",
        "maker"
    ],
    "wof:name":"Jzs Precision Machine",
    "wof:placetype":"venue"
},
  "geometry": {"coordinates":[-79.8896408081,43.6557998657],"type":"Point"}
}