{
  "type": "Feature",
  "properties": {
    "addr:full":"44 Easton Ave Midland ON L4R 4K3",
    "addr:housenumber":"44",
    "addr:postcode":"l4r 4k3",
    "addr:street":"Easton Ave",
    "iso:country":"CA",
    "sg:address":"44 Easton Ave",
    "sg:city":"Midland",
    "sg:classifiers":[
        {
            "category":"Building & Trades",
            "subcategory":"Construction",
            "type":"Services"
        }
    ],
    "sg:phone":"+1 705 534 4038",
    "sg:postcode":"L4R 4K3",
    "sg:province":"ON",
    "sg:tags":[
        "tile",
        "dealer"
    ],
    "wof:name":"Daniel Hayes Ceramic Tile",
    "wof:placetype":"venue"
},
  "geometry": {"coordinates":[-79.88851200000001,44.749905],"type":"Point"}
}