{
  "type": "Feature",
  "properties": {
    "addr:full":"21817 Prospect Hill Rd Thorndale ON N0M 2P0",
    "addr:housenumber":"21817",
    "addr:postcode":"n0m 2p0",
    "addr:street":"Prospect Hill Rd",
    "iso:country":"CA",
    "sg:address":"21817 Prospect Hill Rd",
    "sg:city":"Thorndale",
    "sg:classifiers":[
        {
            "category":"Wholesale",
            "subcategory":"Farm Supplies",
            "type":"Manufacturing & Wholesale Goods"
        }
    ],
    "sg:phone":"+1 519 461 1981",
    "sg:postcode":"N0M 2P0",
    "sg:province":"ON",
    "sg:tags":[
        "feed"
    ],
    "wof:name":"Tribasics Agra Inc",
    "wof:placetype":"venue"
},
  "geometry": {"coordinates":[-81.110603,43.11816],"type":"Point"}
}