{
  "type": "Feature",
  "properties": {
    "addr:full":"703 Ch Du Village Laforce QC J0Z 2J0",
    "addr:housenumber":"703",
    "addr:postcode":"j0z 2j0",
    "addr:street":"Ch Du Village",
    "iso:country":"CA",
    "sg:address":"703 Ch Du Village",
    "sg:city":"Laforce",
    "sg:classifiers":[
        {
            "category":"Government",
            "subcategory":"Office",
            "type":"Public Place"
        }
    ],
    "sg:phone":"+1 819 722 2461",
    "sg:postcode":"J0Z 2J0",
    "sg:province":"QC",
    "sg:tags":[
        "village"
    ],
    "wof:name":"Laforce Municipalite",
    "wof:placetype":"venue"
},
  "geometry": {"coordinates":[-78.702072,47.536224],"type":"Point"}
}