{
  "type": "Feature",
  "properties": {
    "addr:full":"2 Water St N Cambridge ON N1R 3B1",
    "addr:housenumber":"2",
    "addr:postcode":"n1r 3b1",
    "addr:street":"Water St N",
    "iso:country":"CA",
    "sg:address":"2 Water St N",
    "sg:city":"Cambridge",
    "sg:classifiers":[
        {
            "category":"Professional",
            "subcategory":"Lawyer & Legal Services",
            "type":"Services"
        }
    ],
    "sg:phone":"+1 519 621 9850",
    "sg:postcode":"N1R 3B1",
    "sg:province":"ON",
    "sg:tags":[
        "notary",
        "attorney"
    ],
    "wof:name":"Thompson, Donald A",
    "wof:placetype":"venue"
},
  "geometry": {"coordinates":[-80.31546,43.359051],"type":"Point"}
}