{
  "type": "Feature",
  "properties": {
    "addr:full":"135 Spring Gate Blvd Thornhill ON L4J 3B2",
    "addr:housenumber":"135",
    "addr:postcode":"l4j 3b2",
    "addr:street":"Spring Gate Blvd",
    "iso:country":"CA",
    "sg:address":"135 Spring Gate Blvd",
    "sg:city":"Thornhill",
    "sg:classifiers":[
        {
            "category":"Professional",
            "subcategory":"Accounting & Tax Preparation",
            "type":"Services"
        }
    ],
    "sg:phone":"+1 905 886 3942",
    "sg:postcode":"L4J 3B2",
    "sg:province":"ON",
    "sg:tags":[
        "accountant"
    ],
    "wof:name":"Reynolds, Mary",
    "wof:placetype":"venue"
},
  "geometry": {"coordinates":[-79.43158,43.808758],"type":"Point"}
}