{
  "type": "Feature",
  "properties": {
    "addr:full":"Farm Luseland SK S0L 2A0",
    "addr:postcode":"s0l 2a0",
    "addr:street":"Luseland",
    "iso:country":"CA",
    "sg:address":"Farm",
    "sg:city":"Luseland",
    "sg:classifiers":[
        {
            "category":"Retail",
            "subcategory":"Auto Repair",
            "type":"Services"
        }
    ],
    "sg:phone":"+1 306 834 2820",
    "sg:postcode":"S0L 2A0",
    "sg:province":"SK",
    "sg:tags":[
        "repairing",
        "automobile"
    ],
    "wof:name":"Murphy Auto",
    "wof:placetype":"venue"
},
  "geometry": {"coordinates":[-109.38346900000001,52.079491],"type":"Point"}
}