{
  "type": "Feature",
  "properties": {
    "iso:country":"CA",
    "sg:address":"320 Toronto St",
    "sg:city":"Winnipeg",
    "sg:classifiers":[
        {
            "category":"Retail",
            "subcategory":"Laundry & Dry Cleaning",
            "type":"Services"
        }
    ],
    "sg:phone":"+1 204 775 2654",
    "sg:postcode":"R3G 1S2",
    "sg:province":"MB",
    "sg:tags":[
        "cleaners",
        "rug",
        "carpet"
    ],
    "wof:name":"Steam Team",
    "wof:placetype":"venue"
},
  "geometry": {"coordinates":[-97.16469600000001,49.889347],"type":"Point"}
}