{
  "type": "Feature",
  "properties": {
    "addr:full":"Saint-Chrysostome QC J0S 1R0",
    "addr:postcode":"j0s 1r0",
    "iso:country":"CA",
    "sg:city":"Saint-Chrysostome",
    "sg:classifiers":[
        {
            "category":"Professional",
            "subcategory":"Business Services",
            "type":"Services"
        }
    ],
    "sg:phone":"+1 450 826 3639",
    "sg:postcode":"J0S 1R0",
    "sg:province":"QC",
    "sg:tags":[
        "notary"
    ],
    "wof:name":"Marcil, Arthur",
    "wof:placetype":"venue"
},
  "geometry": {"coordinates":[-73.75862121580001,45.1040763855],"type":"Point"}
}