{
  "type": "Feature",
  "properties": {
    "iso:country":"CA",
    "sg:address":"459 Pembroke St W",
    "sg:city":"Pembroke",
    "sg:classifiers":[
        {
            "category":"Manufacturing",
            "subcategory":"Musical Instruments",
            "type":"Manufacturing & Wholesale Goods"
        }
    ],
    "sg:phone":"+1 613 732 3531",
    "sg:postcode":"K8A 5N8",
    "sg:province":"ON",
    "sg:tags":[
        "violin",
        "maker"
    ],
    "wof:name":"Dojczman Violin Rentals & Rpr",
    "wof:placetype":"venue"
},
  "geometry": {"coordinates":[-77.12386322019999,45.8241424561],"type":"Point"}
}