{
  "type": "Feature",
  "properties": {
    "addr:full":"9415 27 Ave NW Edmonton AB T6N 1C9",
    "addr:housenumber":"9415",
    "addr:postcode":"t6n 1c9",
    "addr:street":"27 Ave Nw",
    "iso:country":"CA",
    "sg:address":"9415 27 Ave NW",
    "sg:city":"Edmonton",
    "sg:classifiers":[
        {
            "category":"Mining & Drilling",
            "type":"Manufacturing & Wholesale Goods"
        }
    ],
    "sg:phone":"+1 780 448 0074",
    "sg:postcode":"T6N 1C9",
    "sg:province":"AB",
    "sg:tags":[
        "field",
        "oil"
    ],
    "wof:name":"Hamdon Wellsite Solutions Ltd",
    "wof:placetype":"venue"
},
  "geometry": {"coordinates":[-113.473274,53.456779],"type":"Point"}
}