{
  "type": "Feature",
  "properties": {
    "addr:full":"45763 Yale Rd Chilliwack BC V2P 2N5",
    "addr:housenumber":"45763",
    "addr:postcode":"v2p 2n5",
    "addr:street":"Yale Rd",
    "iso:country":"CA",
    "sg:address":"45763 Yale Rd",
    "sg:city":"Chilliwack",
    "sg:classifiers":[
        {
            "category":"Retail",
            "subcategory":"Auto Repair",
            "type":"Services"
        }
    ],
    "sg:phone":"+1 604 792 0760",
    "sg:postcode":"V2P 2N5",
    "sg:province":"BC",
    "sg:tags":[
        "repairing",
        "automobile"
    ],
    "wof:name":"Pro Autocare Ltd",
    "wof:placetype":"venue"
},
  "geometry": {"coordinates":[-121.959060669,49.1615829468],"type":"Point"}
}