{
  "type": "Feature",
  "properties": {
    "addr:full":"108 Broadway Ave Holland MB R0G 0X0",
    "addr:housenumber":"108",
    "addr:postcode":"r0g 0x0",
    "addr:street":"Broadway Ave",
    "iso:country":"CA",
    "sg:address":"108 Broadway Ave",
    "sg:city":"Holland",
    "sg:classifiers":[
        {
            "category":"Home & Garden",
            "subcategory":"Hardware",
            "type":"Retail Goods"
        }
    ],
    "sg:phone":"+1 204 526 2349",
    "sg:postcode":"R0G 0X0",
    "sg:province":"MB",
    "wof:name":"Pittet's Hardware",
    "wof:placetype":"venue"
},
  "geometry": {"coordinates":[-98.878967,49.5975],"type":"Point"}
}