{
  "type": "Feature",
  "properties": {
    "addr:full":"East York ON M4H 1H2",
    "addr:postcode":"m4h 1h2",
    "iso:country":"CA",
    "sg:city":"East York",
    "sg:classifiers":[
        {
            "category":"Manufacturing",
            "subcategory":"Printing",
            "type":"Manufacturing & Wholesale Goods"
        }
    ],
    "sg:phone":"+1 416 467 1517",
    "sg:postcode":"M4H 1H2",
    "sg:province":"ON",
    "sg:tags":[
        "printer"
    ],
    "wof:name":"Shawn Graphics",
    "wof:placetype":"venue"
},
  "geometry": {"coordinates":[-79.3509674072,43.705821991],"type":"Point"}
}