{
  "type": "Feature",
  "properties": {
    "addr:full":"Carleton Place ON K7C 3H4",
    "addr:postcode":"k7c 3h4",
    "iso:country":"CA",
    "sg:city":"Carleton Place",
    "sg:classifiers":[
        {
            "category":"Shopping",
            "subcategory":"Computers & Home Electronics",
            "type":"Retail Goods"
        }
    ],
    "sg:phone":"+1 613 253 0677",
    "sg:postcode":"K7C 3H4",
    "sg:province":"ON",
    "sg:tags":[
        "equipment",
        "metal",
        "locating"
    ],
    "wof:name":"Detect Enterprises Canadian",
    "wof:placetype":"venue"
},
  "geometry": {"coordinates":[-76.1489639282,45.1419792175],"type":"Point"}
}