{
  "type": "Feature",
  "properties": {
    "iso:country":"CA",
    "sg:address":"447 Montrose Dr",
    "sg:city":"Beaconsfield",
    "sg:classifiers":[
        {
            "category":"Professional",
            "subcategory":"Management & Consulting",
            "type":"Services"
        }
    ],
    "sg:phone":"+1 514 426 3286",
    "sg:postcode":"H9W 1H4",
    "sg:province":"QC",
    "sg:tags":[
        "consultant",
        "business"
    ],
    "wof:name":"Groupe Cjm",
    "wof:placetype":"venue"
},
  "geometry": {"coordinates":[-73.88037109379999,45.4333190918],"type":"Point"}
}