{
  "type": "Feature",
  "properties": {
    "addr:full":"802 16 Ave NE Calgary AB T2E 1K8",
    "addr:housenumber":"802",
    "addr:postcode":"t2e 1k8",
    "addr:street":"16 Ave Ne",
    "iso:country":"CA",
    "sg:address":"802 16 Ave NE",
    "sg:city":"Calgary",
    "sg:classifiers":[
        {
            "category":"Restaurant",
            "type":"Food & Drink"
        }
    ],
    "sg:phone":"+1 403 230 5430",
    "sg:postcode":"T2E 1K8",
    "sg:province":"AB",
    "wof:name":"Amber's Family Restaurant",
    "wof:placetype":"venue"
},
  "geometry": {"coordinates":[-114.04534149200001,51.0670852661],"type":"Point"}
}