{
  "type": "Feature",
  "properties": {
    "addr:full":"6173 Perth St Richmond ON K0A 2Z0",
    "addr:housenumber":"6173",
    "addr:postcode":"k0a 2z0",
    "addr:street":"Perth St",
    "iso:country":"CA",
    "sg:address":"6173 Perth St",
    "sg:city":"Richmond",
    "sg:classifiers":[
        {
            "category":"Restaurant",
            "type":"Food & Drink"
        }
    ],
    "sg:phone":"+1 613 838 2118",
    "sg:postcode":"K0A 2Z0",
    "sg:province":"ON",
    "wof:name":"Chipper",
    "wof:placetype":"venue"
},
  "geometry": {"coordinates":[-75.8411331177,45.1931266785],"type":"Point"}
}