{
  "type": "Feature",
  "properties": {
    "iso:country":"CA",
    "sg:city":"Chapeau",
    "sg:classifiers":[
        {
            "category":"Travel",
            "subcategory":"Hotels & Motels",
            "type":"Entertainment"
        }
    ],
    "sg:phone":"+1 819 689 2762",
    "sg:postcode":"J0X 1M0",
    "sg:province":"QC",
    "wof:name":"Fred's Hotel",
    "wof:placetype":"venue"
},
  "geometry": {"coordinates":[-77.1936035156,45.9464187622],"type":"Point"}
}