{
  "type": "Feature",
  "properties": {
    "addr:full":"914 Sherwood Ave Coquitlam BC V3K 1A6",
    "addr:housenumber":"914",
    "addr:postcode":"v3k 1a6",
    "addr:street":"Sherwood Ave",
    "iso:country":"CA",
    "sg:address":"914 Sherwood Ave",
    "sg:city":"Coquitlam",
    "sg:classifiers":[
        {
            "category":"Wholesale",
            "subcategory":"Groceries",
            "type":"Manufacturing & Wholesale Goods"
        }
    ],
    "sg:phone":"+1 604 540 0123",
    "sg:postcode":"V3K 1A6",
    "sg:province":"BC",
    "sg:tags":[
        "food",
        "broker"
    ],
    "wof:name":"New Venture Sales",
    "wof:placetype":"venue"
},
  "geometry": {"coordinates":[-122.872269,49.235653],"type":"Point"}
}