{
  "type": "Feature",
  "properties": {
    "addr:full":"8073 Timber Lane Whistler BC V0N 1B8",
    "addr:housenumber":"8073",
    "addr:postcode":"v0n 1b8",
    "addr:street":"Timber Lane",
    "iso:country":"CA",
    "sg:address":"8073 Timber Lane",
    "sg:city":"Whistler",
    "sg:classifiers":[
        {
            "category":"Professional",
            "subcategory":"Engineering",
            "type":"Services"
        }
    ],
    "sg:phone":"+1 604 932 5976",
    "sg:postcode":"V0N 1B8",
    "sg:province":"BC",
    "sg:tags":[
        "engineer"
    ],
    "wof:name":"Ecosign Mountain Resort Plnnrs",
    "wof:placetype":"venue"
},
  "geometry": {"coordinates":[-122.961456,50.14603],"type":"Point"}
}