{
  "type": "Feature",
  "properties": {
    "iso:country":"CA",
    "sg:address":"690 Rowntree Dairy Rd",
    "sg:city":"Woodbridge",
    "sg:classifiers":[
        {
            "category":"Wholesale",
            "subcategory":"Hardware",
            "type":"Manufacturing & Wholesale Goods"
        }
    ],
    "sg:phone":"+1 905 856 4455",
    "sg:postcode":"L4L 5T7",
    "sg:province":"ON",
    "sg:tags":[
        "plumbing",
        "fixture",
        "supply"
    ],
    "wof:name":"Penmar Plumbing",
    "wof:placetype":"venue"
},
  "geometry": {"coordinates":[-79.567032,43.777683],"type":"Point"}
}