{
  "type": "Feature",
  "properties": {
    "addr:full":"Victoria Park & Spadina Cres Saskatoon SK S7M 2J5",
    "addr:postcode":"s7m 2j5",
    "addr:street":"Cres",
    "iso:country":"CA",
    "sg:address":"Victoria Park & Spadina Cres",
    "sg:city":"Saskatoon",
    "sg:classifiers":[
        {
            "category":"Recreation",
            "type":"Entertainment"
        }
    ],
    "sg:phone":"+1 306 242 5584",
    "sg:postcode":"S7M 2J5",
    "sg:province":"SK",
    "sg:tags":[
        "club",
        "sport"
    ],
    "wof:name":"Riverside Badminton & Tennis",
    "wof:placetype":"venue"
},
  "geometry": {"coordinates":[-106.664039612,52.1231002808],"type":"Point"}
}