{
  "type": "Feature",
  "properties": {
    "iso:country":"CA",
    "sg:address":"2 Chudd's Corner",
    "sg:city":"Gimli",
    "sg:classifiers":[
        {
            "category":"Real Estate",
            "subcategory":"Real Estate Agent",
            "type":"Services"
        }
    ],
    "sg:phone":"+1 204 642 8145",
    "sg:postcode":"R0C 1B0",
    "sg:province":"MB",
    "wof:name":"Four Seasons Realty",
    "wof:placetype":"venue"
},
  "geometry": {"coordinates":[-96.9941864014,50.6368598938],"type":"Point"}
}