{
  "type": "Feature",
  "properties": {
    "iso:country":"CA",
    "sg:address":"PO Box 5270 STN Main",
    "sg:city":"Edson",
    "sg:classifiers":[
        {
            "category":"Manufacturing",
            "subcategory":"Metals",
            "type":"Manufacturing & Wholesale Goods"
        }
    ],
    "sg:phone":"+1 780 723 3448",
    "sg:postcode":"T7E 1T5",
    "sg:province":"AB",
    "sg:tags":[
        "tongs"
    ],
    "wof:name":"Bitz Power Tongs Ltd",
    "wof:placetype":"venue"
},
  "geometry": {"coordinates":[-116.43409729,53.5821304321],"type":"Point"}
}