{
  "type": "Feature",
  "properties": {
    "addr:full":"654 York St London ON N5W 2S7",
    "addr:housenumber":"654",
    "addr:postcode":"n5w 2s7",
    "addr:street":"York St",
    "iso:country":"CA",
    "sg:address":"654 York St",
    "sg:city":"London",
    "sg:classifiers":[
        {
            "category":"Retail",
            "subcategory":"Auto Repair",
            "type":"Services"
        }
    ],
    "sg:phone":"+1 519 438 2303",
    "sg:postcode":"N5W 2S7",
    "sg:province":"ON",
    "sg:tags":[
        "transmission"
    ],
    "wof:name":"Murray's Automatic Trans Ctr",
    "wof:placetype":"venue"
},
  "geometry": {"coordinates":[-81.22895050050001,42.9868392944],"type":"Point"}
}