{
  "type": "Feature",
  "properties": {
    "addr:full":"6361 6E Av Montreal QC H1Y 2R7",
    "addr:housenumber":"6361",
    "addr:postcode":"h1y 2r7",
    "addr:street":"6E Av",
    "iso:country":"CA",
    "sg:address":"6361 6E Av",
    "sg:city":"Montreal",
    "sg:classifiers":[
        {
            "category":"Education",
            "subcategory":"School",
            "type":"Public Place"
        }
    ],
    "sg:phone":"+1 514 374 8490",
    "sg:postcode":"H1Y 2R7",
    "sg:province":"QC",
    "sg:tags":[
        "academic",
        "special"
    ],
    "wof:name":"Centre D'Integration Scolaire",
    "wof:placetype":"venue"
},
  "geometry": {"coordinates":[-73.5872955322,45.5520324707],"type":"Point"}
}