{
  "type": "Feature",
  "properties": {
    "addr:full":"48 Ste-Catherine Rue RR 1 Saint-Polycarpe QC J0P 1X0",
    "addr:housenumber":"48",
    "addr:postcode":"j0p 1x0",
    "addr:street":"Rue Rr 1 Saint-Polycarpe",
    "iso:country":"CA",
    "sg:address":"48 Ste-Catherine Rue RR 1",
    "sg:city":"Saint-Polycarpe",
    "sg:classifiers":[
        {
            "category":"Social Services",
            "type":"Services"
        }
    ],
    "sg:phone":"+1 450 265 3672",
    "sg:postcode":"J0P 1X0",
    "sg:province":"QC",
    "sg:tags":[
        "organization",
        "welfare"
    ],
    "wof:name":"Jonathans DE Soulanges Inc",
    "wof:placetype":"venue"
},
  "geometry": {"coordinates":[-74.3069534302,45.3005218506],"type":"Point"}
}