{
  "type": "Feature",
  "properties": {
    "addr:full":"105 2nd Ave W Hanna AB T0J 1P0",
    "addr:housenumber":"105",
    "addr:postcode":"t0j 1p0",
    "addr:street":"2Nd Ave W",
    "iso:country":"CA",
    "sg:address":"105 2nd Ave W",
    "sg:city":"Hanna",
    "sg:classifiers":[
        {
            "category":"Shopping",
            "subcategory":"Computers & Home Electronics",
            "type":"Retail Goods"
        }
    ],
    "sg:phone":"+1 403 854 4600",
    "sg:postcode":"T0J 1P0",
    "sg:province":"AB",
    "sg:tags":[
        "equipment",
        "dealer"
    ],
    "wof:name":"Paragon Computer Solutions",
    "wof:placetype":"venue"
},
  "geometry": {"coordinates":[-111.926125,51.643299],"type":"Point"}
}