{
  "type": "Feature",
  "properties": {
    "addr:full":"2093 2nd Ave Whitehorse YT Y1A 1B5",
    "addr:housenumber":"2093",
    "addr:postcode":"y1a 1b5",
    "addr:street":"2Nd Ave",
    "iso:country":"CA",
    "sg:address":"2093 2nd Ave",
    "sg:city":"Whitehorse",
    "sg:classifiers":[
        {
            "category":"Manufacturing",
            "subcategory":"Tools & Machinery",
            "type":"Manufacturing & Wholesale Goods"
        }
    ],
    "sg:phone":"+1 867 667 4001",
    "sg:postcode":"Y1A 1B5",
    "sg:province":"YT",
    "sg:tags":[
        "laboratory",
        "optical"
    ],
    "wof:name":"Wing Optical Laboratories",
    "wof:placetype":"venue"
},
  "geometry": {"coordinates":[-135.051086,60.718403],"type":"Point"}
}