{
  "type": "Feature",
  "properties": {
    "iso:country":"CA",
    "sg:address":"7035 W Island Hwy",
    "sg:city":"Bowser",
    "sg:classifiers":[
        {
            "category":"Organizations",
            "subcategory":"Community Association",
            "type":"Services"
        }
    ],
    "sg:phone":"+1 250 757 9222",
    "sg:postcode":"V0R 1G0",
    "sg:province":"BC",
    "sg:tags":[
        "fraternal"
    ],
    "wof:name":"Royal Canadian Legion Br 211",
    "wof:placetype":"venue"
},
  "geometry": {"coordinates":[-124.686485291,49.4392242432],"type":"Point"}
}