{
  "type": "Feature",
  "properties": {
    "iso:country":"CA",
    "sg:address":"6740 Marshall Rd",
    "sg:city":"Port Robinson",
    "sg:classifiers":[
        {
            "category":"Wholesale",
            "subcategory":"Auto Parts",
            "type":"Manufacturing & Wholesale Goods"
        }
    ],
    "sg:phone":"+1 905 295 4316",
    "sg:postcode":"L0S 1K0",
    "sg:province":"ON",
    "sg:tags":[
        "automobile",
        "rebuilt"
    ],
    "wof:name":"Queensway Auto Parts & Rcyclng",
    "wof:placetype":"venue"
},
  "geometry": {"coordinates":[-79.2100982666,43.0383987427],"type":"Point"}
}