{
  "type": "Feature",
  "properties": {
    "addr:full":"10924 Sunset Rd Talbotville Royal ON N0L 2K0",
    "addr:housenumber":"10924",
    "addr:postcode":"n0l 2k0",
    "addr:street":"Sunset Rd",
    "iso:country":"CA",
    "sg:address":"10924 Sunset Rd",
    "sg:city":"Talbotville Royal",
    "sg:classifiers":[
        {
            "category":"Shopping",
            "subcategory":"Used Merchandise",
            "type":"Retail Goods"
        }
    ],
    "sg:phone":"+1 519 631 0535",
    "sg:postcode":"N0L 2K0",
    "sg:province":"ON",
    "sg:tags":[
        "antique"
    ],
    "wof:name":"House of Glass Antiques & Gfts",
    "wof:placetype":"venue"
},
  "geometry": {"coordinates":[-81.25569900000001,42.809837],"type":"Point"}
}