{
  "type": "Feature",
  "properties": {
    "addr:full":"1 Valleywood Dr Markham ON L3R 5L9",
    "addr:housenumber":"1",
    "addr:postcode":"l3r 5l9",
    "addr:street":"Valleywood Dr",
    "iso:country":"CA",
    "sg:address":"1 Valleywood Dr",
    "sg:city":"Markham",
    "sg:classifiers":[
        {
            "category":"Professional",
            "subcategory":"Computer Services",
            "type":"Services"
        }
    ],
    "sg:phone":"+1 905 475 6161",
    "sg:postcode":"L3R 5L9",
    "sg:province":"ON",
    "sg:tags":[
        "consultant"
    ],
    "wof:name":"Kerr Vayne Systems Ltd",
    "wof:placetype":"venue"
},
  "geometry": {"coordinates":[-79.360069,43.85667],"type":"Point"}
}