{
  "type": "Feature",
  "properties": {
    "addr:full":"Glencairn ON L0M 1K0",
    "addr:postcode":"l0m 1k0",
    "iso:country":"CA",
    "sg:city":"Glencairn",
    "sg:classifiers":[
        {
            "category":"Building & Trades",
            "subcategory":"Electrical",
            "type":"Services"
        }
    ],
    "sg:phone":"+1 705 424 8889",
    "sg:postcode":"L0M 1K0",
    "sg:province":"ON",
    "sg:tags":[
        "electric",
        "contractor"
    ],
    "wof:name":"Pridham Electrical",
    "wof:placetype":"venue"
},
  "geometry": {"coordinates":[-80.0016326904,44.305431366],"type":"Point"}
}