{
  "type": "Feature",
  "properties": {
    "addr:full":"30 East Wilmot St Richmond Hill ON L4B 1A4",
    "addr:housenumber":"30",
    "addr:postcode":"l4b 1a4",
    "addr:street":"East Wilmot St",
    "iso:country":"CA",
    "sg:address":"30 East Wilmot St",
    "sg:city":"Richmond Hill",
    "sg:classifiers":[
        {
            "category":"Wholesale",
            "subcategory":"Durable Goods & Equipment",
            "type":"Manufacturing & Wholesale Goods"
        }
    ],
    "sg:phone":"+1 905 886 3566",
    "sg:postcode":"L4B 1A4",
    "sg:province":"ON",
    "sg:tags":[
        "importer"
    ],
    "wof:name":"Splash International",
    "wof:placetype":"venue"
},
  "geometry": {"coordinates":[-79.3815689087,43.8535308838],"type":"Point"}
}