{
  "type": "Feature",
  "properties": {
    "addr:full":"101 Glen Manor Dr Toronto ON M4E 3V3",
    "addr:housenumber":"101",
    "addr:postcode":"m4e 3v3",
    "addr:street":"Glen Manor Dr",
    "iso:country":"CA",
    "sg:address":"101 Glen Manor Dr",
    "sg:city":"Toronto",
    "sg:classifiers":[
        {
            "category":"Building & Trades",
            "subcategory":"Construction",
            "type":"Services"
        }
    ],
    "sg:phone":"+1 416 699 0341",
    "sg:postcode":"M4E 3V3",
    "sg:province":"ON",
    "sg:tags":[
        "general",
        "contractor"
    ],
    "wof:name":"Centor Project Management",
    "wof:placetype":"venue"
},
  "geometry": {"coordinates":[-79.29225158689999,43.6713943481],"type":"Point"}
}