{
  "type": "Feature",
  "properties": {
    "addr:full":"Saint-Laurent QC H4R 1V4",
    "addr:postcode":"h4r 1v4",
    "iso:country":"CA",
    "sg:city":"Saint-Laurent",
    "sg:classifiers":[
        {
            "category":"Manufacturing",
            "subcategory":"Tools & Machinery",
            "type":"Manufacturing & Wholesale Goods"
        }
    ],
    "sg:phone":"+1 514 331 2773",
    "sg:postcode":"H4R 1V4",
    "sg:province":"QC",
    "sg:tags":[
        "equipment",
        "electric"
    ],
    "wof:name":"Crouse-Hinds",
    "wof:placetype":"venue"
},
  "geometry": {"coordinates":[-73.71077699999999,45.491646],"type":"Point"}
}