{
  "type": "Feature",
  "properties": {
    "addr:full":"870 Somerset St W Ottawa ON K1R 6R7",
    "addr:housenumber":"870",
    "addr:postcode":"k1r 6r7",
    "addr:street":"Somerset St W",
    "iso:country":"CA",
    "sg:address":"870 Somerset St W",
    "sg:city":"Ottawa",
    "sg:classifiers":[
        {
            "category":"Restaurant",
            "type":"Food & Drink"
        }
    ],
    "sg:phone":"+1 613 567 2122",
    "sg:postcode":"K1R 6R7",
    "sg:province":"ON",
    "wof:name":"Northern 2 Restaurant",
    "wof:placetype":"venue"
},
  "geometry": {"coordinates":[-75.713257,45.40852],"type":"Point"}
}