{
  "type": "Feature",
  "properties": {
    "addr:full":"1699 Ch Du Mont-Gabriel Sainte-Adele QC J8B 1A5",
    "addr:housenumber":"1699",
    "addr:postcode":"j8b 1a5",
    "addr:street":"Ch Du Mont-Gabriel Sainte-Adele",
    "iso:country":"CA",
    "sg:address":"1699 Ch Du Mont-Gabriel",
    "sg:city":"Sainte-Adele",
    "sg:classifiers":[
        {
            "category":"Travel",
            "subcategory":"Hotels & Motels",
            "type":"Entertainment"
        }
    ],
    "sg:phone":"+1 450 229 3547",
    "sg:postcode":"J8B 1A5",
    "sg:province":"QC",
    "sg:tags":[
        "course",
        "golf"
    ],
    "wof:name":"Club DE Golf Mont Gabriel",
    "wof:placetype":"venue"
},
  "geometry": {"coordinates":[-74.1626205444,45.9194068909],"type":"Point"}
}