{
  "type": "Feature",
  "properties": {
    "addr:full":"2700 30 Ave Vernon BC V1T 2B6",
    "addr:housenumber":"2700",
    "addr:postcode":"v1t 2b6",
    "addr:street":"30 Ave",
    "iso:country":"CA",
    "sg:address":"2700 30 Ave",
    "sg:city":"Vernon",
    "sg:classifiers":[
        {
            "category":"Retail",
            "subcategory":"Veterinary Services",
            "type":"Services"
        }
    ],
    "sg:phone":"+1 250 549 0402",
    "sg:postcode":"V1T 2B6",
    "sg:province":"BC",
    "sg:tags":[
        "veterinarian"
    ],
    "wof:name":"Central Animal Hospital",
    "wof:placetype":"venue"
},
  "geometry": {"coordinates":[-119.266807556,50.2636795044],"type":"Point"}
}