{
  "type": "Feature",
  "properties": {
    "addr:full":"541 Boul Sainte-Madeleine Cap-DE-LA-Madeleine QC G8T 3P8",
    "addr:housenumber":"541",
    "addr:postcode":"g8t 3p8",
    "addr:street":"Boul Sainte-Madeleine",
    "iso:country":"CA",
    "sg:address":"541 Boul Sainte-Madeleine",
    "sg:city":"Cap-DE-LA-Madeleine",
    "sg:classifiers":[
        {
            "category":"Real Estate",
            "subcategory":"Real Estate Agent",
            "type":"Services"
        }
    ],
    "sg:phone":"+1 819 372 0399",
    "sg:postcode":"G8T 3P8",
    "sg:province":"QC",
    "sg:tags":[
        "agency",
        "rental"
    ],
    "wof:name":"Major Mini Moteur Inc",
    "wof:placetype":"venue"
},
  "geometry": {"coordinates":[-72.49737500000001,46.374252],"type":"Point"}
}