{
  "type": "Feature",
  "properties": {
    "iso:country":"CA",
    "sg:address":"4901 7 Line",
    "sg:city":"Ballinafad",
    "sg:classifiers":[
        {
            "category":"Food & Beverages",
            "subcategory":"Groceries & Convenience Stores",
            "type":"Retail Goods"
        }
    ],
    "sg:phone":"+1 905 877 6639",
    "sg:postcode":"N0B 1H0",
    "sg:province":"ON",
    "sg:tags":[
        "apparel",
        "riding",
        "equipment"
    ],
    "wof:name":"Ballinafad General Store",
    "wof:placetype":"venue"
},
  "geometry": {"coordinates":[-80.0111618042,43.6965751648],"type":"Point"}
}