{
  "type": "Feature",
  "properties": {
    "addr:full":"209 Queen St Charlottetown PE C1A 4B7",
    "addr:housenumber":"209",
    "addr:postcode":"c1a 4b7",
    "addr:street":"Queen St",
    "iso:country":"CA",
    "sg:address":"209 Queen St",
    "sg:city":"Charlottetown",
    "sg:classifiers":[
        {
            "category":"Organizations",
            "subcategory":"Non-profit Organization",
            "type":"Services"
        }
    ],
    "sg:phone":"+1 902 894 5473",
    "sg:postcode":"C1A 4B7",
    "sg:province":"PE",
    "sg:tags":[
        "charitable",
        "institution"
    ],
    "wof:name":"Pei Right To Life Assoc",
    "wof:placetype":"venue"
},
  "geometry": {"coordinates":[-63.129646,46.235428],"type":"Point"}
}