{
  "type": "Feature",
  "properties": {
    "iso:country":"CA",
    "sg:address":"2398 Yonge St",
    "sg:city":"Toronto",
    "sg:classifiers":[
        {
            "category":"Health Services",
            "subcategory":"Doctor",
            "type":"Services"
        }
    ],
    "sg:phone":"+1 416 486 8666",
    "sg:postcode":"M4P 2H4",
    "sg:province":"ON",
    "sg:tags":[
        "clinic"
    ],
    "wof:name":"Anne Johnston Health Station",
    "wof:placetype":"venue"
},
  "geometry": {"coordinates":[-79.399178,43.70974],"type":"Point"}
}