{
  "type": "Feature",
  "properties": {
    "addr:full":"815 Boul DE LA Cote-Vertu Saint-Laurent QC H4L 1Y6",
    "addr:housenumber":"815",
    "addr:postcode":"h4l 1y6",
    "addr:street":"Boul De La Cote-Vertu",
    "iso:country":"CA",
    "sg:address":"815 Boul DE LA Cote-Vertu",
    "sg:city":"Saint-Laurent",
    "sg:classifiers":[
        {
            "category":"Shopping",
            "subcategory":"Pharmacy",
            "type":"Retail Goods"
        }
    ],
    "sg:phone":"+1 514 747 8489",
    "sg:postcode":"H4L 1Y6",
    "sg:province":"QC",
    "wof:name":"Pharmacie Lynda Fortin",
    "wof:placetype":"venue"
},
  "geometry": {"coordinates":[-73.67540700000001,45.520126],"type":"Point"}
}