{
  "type": "Feature",
  "properties": {
    "iso:country":"CA",
    "sg:address":"5917 Main St",
    "sg:city":"Stouffville",
    "sg:classifiers":[
        {
            "category":"Restaurant",
            "type":"Food & Drink"
        }
    ],
    "sg:phone":"+1 905 642 1344",
    "sg:postcode":"L4A 2Z9",
    "sg:province":"ON",
    "wof:name":"Lion of Stouffville",
    "wof:placetype":"venue"
},
  "geometry": {"coordinates":[-79.259369,43.968407],"type":"Point"}
}