{
  "type": "Feature",
  "properties": {
    "addr:full":"1061 Linden Way Sarnia ON N7S 2C7",
    "addr:housenumber":"1061",
    "addr:postcode":"n7s 2c7",
    "addr:street":"Linden Way",
    "iso:country":"CA",
    "sg:address":"1061 Linden Way",
    "sg:city":"Sarnia",
    "sg:classifiers":[
        {
            "category":"Building & Trades",
            "subcategory":"Construction",
            "type":"Services"
        }
    ],
    "sg:phone":"+1 519 542 0033",
    "sg:postcode":"N7S 2C7",
    "sg:province":"ON",
    "sg:tags":[
        "painter"
    ],
    "wof:name":"Victorian Painters",
    "wof:placetype":"venue"
},
  "geometry": {"coordinates":[-82.368736,43.002419],"type":"Point"}
}