{
  "type": "Feature",
  "properties": {
    "addr:full":"26 Rue DE L'Eglise Sainte-Marie-Saint-Raphael NB E8T 1N8",
    "addr:housenumber":"26",
    "addr:postcode":"e8t 1n8",
    "addr:street":"Rue De L'Eglise Sainte-Marie-Saint-Raphael",
    "iso:country":"CA",
    "sg:address":"26 Rue DE L'Eglise",
    "sg:city":"Sainte-Marie-Saint-Raphael",
    "sg:classifiers":[
        {
            "category":"Organizations",
            "subcategory":"Religious Organization",
            "type":"Services"
        }
    ],
    "sg:phone":"+1 506 344 8212",
    "sg:postcode":"E8T 1N8",
    "sg:province":"NB",
    "sg:tags":[
        "church"
    ],
    "wof:name":"St Pie X Catholic Church",
    "wof:placetype":"venue"
},
  "geometry": {"coordinates":[-64.5725021362,47.7918586731],"type":"Point"}
}