{
  "type": "Feature",
  "properties": {
    "iso:country":"CA",
    "sg:address":"71 Wharncliffe Rd S",
    "sg:city":"London",
    "sg:classifiers":[
        {
            "category":"Travel",
            "subcategory":"Travel Agent",
            "type":"Entertainment"
        }
    ],
    "sg:phone":"+1 519 432 4133",
    "sg:postcode":"N6J 2J8",
    "sg:province":"ON",
    "sg:tags":[
        "agency",
        "bureau"
    ],
    "wof:name":"Ruppe Travel Bureau Inc",
    "wof:placetype":"venue"
},
  "geometry": {"coordinates":[-81.2623596191,42.976272583],"type":"Point"}
}