{
  "type": "Feature",
  "properties": {
    "addr:full":"212 Edmonton Trail SE Airdrie AB T4B 1S2",
    "addr:housenumber":"212",
    "addr:postcode":"t4b 1s2",
    "addr:street":"Edmonton Trail Se",
    "iso:country":"CA",
    "sg:address":"212 Edmonton Trail SE",
    "sg:city":"Airdrie",
    "sg:classifiers":[
        {
            "category":"Autos & Motor Vehicles",
            "subcategory":"Auto Supplies",
            "type":"Retail Goods"
        }
    ],
    "sg:phone":"+1 403 948 6050",
    "sg:postcode":"T4B 1S2",
    "sg:province":"AB",
    "sg:tags":[
        "automobile",
        "parts"
    ],
    "wof:name":"Napa Auto Parts",
    "wof:placetype":"venue"
},
  "geometry": {"coordinates":[-114.001152,51.289829],"type":"Point"}
}