{
  "type": "Feature",
  "properties": {
    "addr:full":"514 Mount Pleasant Rd Toronto ON M4S 2M2",
    "addr:housenumber":"514",
    "addr:postcode":"m4s 2m2",
    "addr:street":"Mount Pleasant Rd",
    "iso:country":"CA",
    "sg:address":"514 Mount Pleasant Rd",
    "sg:city":"Toronto",
    "sg:classifiers":[
        {
            "category":"Shopping",
            "subcategory":"Used Merchandise",
            "type":"Retail Goods"
        }
    ],
    "sg:phone":"+1 416 481 4924",
    "sg:postcode":"M4S 2M2",
    "sg:province":"ON",
    "sg:tags":[
        "shop",
        "consignment"
    ],
    "wof:name":"Second Nature Boutique",
    "wof:placetype":"venue"
},
  "geometry": {"coordinates":[-79.387749,43.701839],"type":"Point"}
}