{
  "type": "Feature",
  "properties": {
    "iso:country":"CA",
    "sg:address":"5500 North Service Rd # 200",
    "sg:city":"Burlington",
    "sg:classifiers":[
        {
            "category":"Banks & Credit Unions",
            "subcategory":"Bank",
            "type":"Services"
        }
    ],
    "sg:phone":"+1 905 332 4338",
    "sg:postcode":"L7L 6W6",
    "sg:province":"ON",
    "wof:name":"National Bank of Canada",
    "wof:placetype":"venue"
},
  "geometry": {"coordinates":[-79.76113891599999,43.3953742981],"type":"Point"}
}