{
  "type": "Feature",
  "properties": {
    "addr:full":"38 Glenwood Dr Chatham ON N7L 3X2",
    "addr:housenumber":"38",
    "addr:postcode":"n7l 3x2",
    "addr:street":"Glenwood Dr",
    "iso:country":"CA",
    "sg:address":"38 Glenwood Dr",
    "sg:city":"Chatham",
    "sg:classifiers":[
        {
            "category":"Real Estate",
            "subcategory":"Real Estate Operator",
            "type":"Services"
        }
    ],
    "sg:phone":"+1 519 436 2448",
    "sg:postcode":"N7L 3X2",
    "sg:province":"ON",
    "sg:tags":[
        "apartment"
    ],
    "wof:name":"Fisher Apartments Ltd",
    "wof:placetype":"venue"
},
  "geometry": {"coordinates":[-82.200378,42.417469],"type":"Point"}
}