{
  "type": "Feature",
  "properties": {
    "addr:full":"3171 Broadway W Vancouver BC V6K 2H2",
    "addr:housenumber":"3171",
    "addr:postcode":"v6k 2h2",
    "addr:street":"Broadway W",
    "iso:country":"CA",
    "sg:address":"3171 Broadway W",
    "sg:city":"Vancouver",
    "sg:classifiers":[
        {
            "category":"Food & Beverages",
            "subcategory":"Specialty",
            "type":"Retail Goods"
        }
    ],
    "sg:phone":"+1 604 738 0905",
    "sg:postcode":"V6K 2H2",
    "sg:province":"BC",
    "sg:tags":[
        "tea",
        "coffee"
    ],
    "wof:name":"Yoka's Coffee & Honey",
    "wof:placetype":"venue"
},
  "geometry": {"coordinates":[-123.17512499999999,49.264301],"type":"Point"}
}