{
  "type": "Feature",
  "properties": {
    "addr:full":"Mississauga ON L5N 2Y1",
    "addr:postcode":"l5n 2y1",
    "iso:country":"CA",
    "sg:city":"Mississauga",
    "sg:classifiers":[
        {
            "category":"Professional",
            "subcategory":"Management & Consulting",
            "type":"Services"
        }
    ],
    "sg:phone":"+1 905 826 6042",
    "sg:postcode":"L5N 2Y1",
    "sg:province":"ON",
    "sg:tags":[
        "consultant",
        "educational",
        "psycho"
    ],
    "wof:name":"Neurodevelopmental & Education",
    "wof:placetype":"venue"
},
  "geometry": {"coordinates":[-79.75865899999999,43.58445],"type":"Point"}
}