{
  "type": "Feature",
  "properties": {
    "addr:full":"2655 Main St Vancouver BC V5T 3E7",
    "addr:housenumber":"2655",
    "addr:postcode":"v5t 3e7",
    "addr:street":"Main St",
    "iso:country":"CA",
    "sg:address":"2655 Main St",
    "sg:city":"Vancouver",
    "sg:classifiers":[
        {
            "category":"Organizations",
            "subcategory":"Community Association",
            "type":"Services"
        }
    ],
    "sg:phone":"+1 604 879 3551",
    "sg:postcode":"V5T 3E7",
    "sg:province":"BC",
    "sg:tags":[
        "fraternal"
    ],
    "wof:name":"Royal Canadian Legion 177",
    "wof:placetype":"venue"
},
  "geometry": {"coordinates":[-123.101135,49.261597],"type":"Point"}
}