{
  "type": "Feature",
  "properties": {
    "addr:full":"Abbotsford BC V2T 6K3",
    "addr:postcode":"v2t 6k3",
    "iso:country":"CA",
    "sg:city":"Abbotsford",
    "sg:classifiers":[
        {
            "category":"Building & Trades",
            "subcategory":"Electrical",
            "type":"Services"
        }
    ],
    "sg:phone":"+1 604 850 9173",
    "sg:postcode":"V2T 6K3",
    "sg:province":"BC",
    "sg:tags":[
        "electric",
        "contractor"
    ],
    "wof:name":"Moss Electric Ltd",
    "wof:placetype":"venue"
},
  "geometry": {"coordinates":[-122.36592899999999,49.046238],"type":"Point"}
}