{
  "type": "Feature",
  "properties": {
    "addr:full":"325 Main St Kentville NS B4N 1K5",
    "addr:housenumber":"325",
    "addr:postcode":"b4n 1k5",
    "addr:street":"Main St",
    "iso:country":"CA",
    "sg:address":"325 Main St",
    "sg:city":"Kentville",
    "sg:classifiers":[
        {
            "category":"Bars & Pubs",
            "type":"Food & Drink"
        }
    ],
    "sg:phone":"+1 902 678 3474",
    "sg:postcode":"B4N 1K5",
    "sg:province":"NS",
    "wof:name":"Old English Tavern",
    "wof:placetype":"venue"
},
  "geometry": {"coordinates":[-64.4905166626,45.075756073],"type":"Point"}
}