{
  "type": "Feature",
  "properties": {
    "addr:full":"Lindsay ON K9V 4R4",
    "addr:postcode":"k9v 4r4",
    "iso:country":"CA",
    "sg:city":"Lindsay",
    "sg:classifiers":[
        {
            "category":"Building & Trades",
            "subcategory":"Plumbing",
            "type":"Services"
        }
    ],
    "sg:phone":"+1 705 878 0447",
    "sg:postcode":"K9V 4R4",
    "sg:province":"ON",
    "sg:tags":[
        "heating",
        "contractor"
    ],
    "wof:name":"G R Howie Heating",
    "wof:placetype":"venue"
},
  "geometry": {"coordinates":[-78.74006652830001,44.3542785645],"type":"Point"}
}