{
  "type": "Feature",
  "properties": {
    "addr:full":"2087 Okanagan St Armstrong BC V0E 1B1",
    "addr:housenumber":"2087",
    "addr:postcode":"v0e 1b1",
    "addr:street":"Okanagan St",
    "iso:country":"CA",
    "sg:address":"2087 Okanagan St",
    "sg:city":"Armstrong",
    "sg:classifiers":[
        {
            "category":"Building & Trades",
            "subcategory":"Plumbing",
            "type":"Services"
        }
    ],
    "sg:phone":"+1 250 546 6070",
    "sg:postcode":"V0E 1B1",
    "sg:province":"BC",
    "sg:tags":[
        "contractor"
    ],
    "wof:name":"North Okanagan Plumbing & Htg",
    "wof:placetype":"venue"
},
  "geometry": {"coordinates":[-119.191391,50.433601],"type":"Point"}
}