{
  "type": "Feature",
  "properties": {
    "addr:full":"152 MT Robson Cir SE Calgary AB T2Z 2C1",
    "addr:housenumber":"152",
    "addr:postcode":"t2z 2c1",
    "addr:street":"Mt Robson Cir Se",
    "iso:country":"CA",
    "sg:address":"152 MT Robson Cir SE",
    "sg:city":"Calgary",
    "sg:classifiers":[
        {
            "category":"Professional",
            "subcategory":"Management & Consulting",
            "type":"Services"
        }
    ],
    "sg:phone":"+1 403 257 5823",
    "sg:postcode":"T2Z 2C1",
    "sg:province":"AB",
    "sg:tags":[
        "consultant",
        "construction"
    ],
    "wof:name":"Showcase Projects Ltd",
    "wof:placetype":"venue"
},
  "geometry": {"coordinates":[-113.989830017,50.9101219177],"type":"Point"}
}