{
  "type": "Feature",
  "properties": {
    "addr:full":"430 Pioneer Dr Regina SK S4T 6L8",
    "addr:housenumber":"430",
    "addr:postcode":"s4t 6l8",
    "addr:street":"Pioneer Dr",
    "iso:country":"CA",
    "sg:address":"430 Pioneer Dr",
    "sg:city":"Regina",
    "sg:classifiers":[
        {
            "category":"Recreation",
            "type":"Entertainment"
        }
    ],
    "sg:phone":"+1 306 757 5646",
    "sg:postcode":"S4T 6L8",
    "sg:province":"SK",
    "sg:tags":[
        "home",
        "convalescent",
        "auditorium",
        "nursing",
        "hall"
    ],
    "wof:name":"Regina Pioneer Village Ltd",
    "wof:placetype":"venue"
},
  "geometry": {"coordinates":[-104.64598100000001,50.453533],"type":"Point"}
}