{
  "type": "Feature",
  "properties": {
    "addr:full":"710 10th Ave E Vancouver BC V5T 2A7",
    "addr:housenumber":"710",
    "addr:postcode":"v5t 2a7",
    "addr:street":"10Th Ave E",
    "iso:country":"CA",
    "sg:address":"710 10th Ave E",
    "sg:city":"Vancouver",
    "sg:classifiers":[
        {
            "category":"Organizations",
            "subcategory":"Religious Organization",
            "type":"Services"
        }
    ],
    "sg:phone":"+1 604 872 1614",
    "sg:postcode":"V5T 2A7",
    "sg:province":"BC",
    "sg:tags":[
        "synagogue"
    ],
    "wof:name":"Or Shalom",
    "wof:placetype":"venue"
},
  "geometry": {"coordinates":[-123.088745117,49.2614631653],"type":"Point"}
}