{
  "type": "Feature",
  "properties": {
    "addr:full":"1247 Wyandotte St E Windsor ON N9A 3K6",
    "addr:housenumber":"1247",
    "addr:postcode":"n9a 3k6",
    "addr:street":"Wyandotte St E",
    "iso:country":"CA",
    "sg:address":"1247 Wyandotte St E",
    "sg:city":"Windsor",
    "sg:classifiers":[
        {
            "category":"Shopping",
            "subcategory":"Clothing, Apparel, & Fashions",
            "type":"Retail Goods"
        }
    ],
    "sg:phone":"+1 519 253 4751",
    "sg:postcode":"N9A 3K6",
    "sg:province":"ON",
    "sg:tags":[
        "uniform"
    ],
    "wof:name":"Windsor Uniforms",
    "wof:placetype":"venue"
},
  "geometry": {"coordinates":[-83.019516,42.320141],"type":"Point"}
}