{
  "type": "Feature",
  "properties": {
    "iso:country":"CA",
    "sg:city":"Winnipeg",
    "sg:classifiers":[
        {
            "category":"Professional",
            "subcategory":"Advertising",
            "type":"Services"
        }
    ],
    "sg:phone":"+1 204 925 4321",
    "sg:postcode":"R3B 2N8",
    "sg:province":"MB",
    "sg:tags":[
        "counselor"
    ],
    "wof:name":"Fusion Communications Group",
    "wof:placetype":"venue"
},
  "geometry": {"coordinates":[-97.149879,49.891621],"type":"Point"}
}