{
  "type": "Feature",
  "properties": {
    "addr:full":"Boisbriand QC J7G 2J7",
    "addr:postcode":"j7g 2j7",
    "iso:country":"CA",
    "sg:city":"Boisbriand",
    "sg:classifiers":[
        {
            "category":"Health Services",
            "subcategory":"Doctor",
            "type":"Services"
        }
    ],
    "sg:phone":"+1 450 433 9440",
    "sg:postcode":"J7G 2J7",
    "sg:province":"QC",
    "sg:tags":[
        "dentist"
    ],
    "wof:name":"Gilbert, Liliane DDS",
    "wof:placetype":"venue"
},
  "geometry": {"coordinates":[-73.83863100000001,45.612564],"type":"Point"}
}