{
  "type": "Feature",
  "properties": {
    "iso:country":"CA",
    "sg:city":"Markham",
    "sg:classifiers":[
        {
            "category":"Manufacturing",
            "subcategory":"Apparel",
            "type":"Manufacturing & Wholesale Goods"
        }
    ],
    "sg:phone":"+1 905 294 5578",
    "sg:postcode":"L6E 1A6",
    "sg:province":"ON",
    "sg:tags":[
        "bridal",
        "supply"
    ],
    "wof:name":"Mitchell Accessories Ltd",
    "wof:placetype":"venue"
},
  "geometry": {"coordinates":[-79.26458,43.901894],"type":"Point"}
}