{
  "type": "Feature",
  "properties": {
    "addr:full":"Grand Falls-Windsor NL A2A 2G8",
    "addr:postcode":"a2a 2g8",
    "iso:country":"CA",
    "sg:city":"Grand Falls-Windsor",
    "sg:classifiers":[
        {
            "category":"Organizations",
            "subcategory":"Professional Association",
            "type":"Services"
        }
    ],
    "sg:phone":"+1 709 489 6515",
    "sg:postcode":"A2A 2G8",
    "sg:province":"NL",
    "wof:name":"Canadian National Inst-Blind",
    "wof:placetype":"venue"
},
  "geometry": {"coordinates":[-55.641449,48.931629],"type":"Point"}
}