{
  "type": "Feature",
  "properties": {
    "addr:full":"114 Av DE Gaspe E Saint-Jean-Port-Joli QC G0R 3G0",
    "addr:postcode":"g0r 3g0",
    "addr:street":"114 Av De Gaspe E",
    "iso:country":"CA",
    "sg:address":"114 Av DE Gaspe E",
    "sg:city":"Saint-Jean-Port-Joli",
    "sg:classifiers":[
        {
            "category":"Professional",
            "subcategory":"Accounting & Tax Preparation",
            "type":"Services"
        }
    ],
    "sg:phone":"+1 418 598 3331",
    "sg:postcode":"G0R 3G0",
    "sg:province":"QC",
    "sg:tags":[
        "accountant"
    ],
    "wof:name":"Raymond Chabot Grant Thornton",
    "wof:placetype":"venue"
},
  "geometry": {"coordinates":[-70.26187899999999,47.219551],"type":"Point"}
}