{
  "type": "Feature",
  "properties": {
    "addr:full":"1275 Rue Blanchette Saint-Hyacinthe QC J2S 1J9",
    "addr:housenumber":"1275",
    "addr:postcode":"j2s 1j9",
    "addr:street":"Rue Blanchette",
    "iso:country":"CA",
    "sg:address":"1275 Rue Blanchette",
    "sg:city":"Saint-Hyacinthe",
    "sg:classifiers":[
        {
            "category":"Health Services",
            "subcategory":"Chiropractor",
            "type":"Services"
        }
    ],
    "sg:phone":"+1 450 774 6855",
    "sg:postcode":"J2S 1J9",
    "sg:province":"QC",
    "wof:name":"Chiro-Clinique Daniel",
    "wof:placetype":"venue"
},
  "geometry": {"coordinates":[-72.958229,45.633659],"type":"Point"}
}