{
  "type": "Feature",
  "properties": {
    "addr:full":"11400 1E Av Saint-Georges QC G5Y 5S4",
    "addr:housenumber":"11400",
    "addr:postcode":"g5y 5s4",
    "addr:street":"1E Av",
    "iso:country":"CA",
    "sg:address":"11400 1E Av",
    "sg:city":"Saint-Georges",
    "sg:classifiers":[
        {
            "category":"Personal",
            "subcategory":"Beauty Salon",
            "type":"Services"
        }
    ],
    "sg:phone":"+1 418 227 2882",
    "sg:postcode":"G5Y 5S4",
    "sg:province":"QC",
    "wof:name":"Salon D'Esthetique Illusion",
    "wof:placetype":"venue"
},
  "geometry": {"coordinates":[-70.67115,46.123348],"type":"Point"}
}