{
  "type": "Feature",
  "properties": {
    "addr:full":"1551 4th Ave Regina SK S4R 8P9",
    "addr:housenumber":"1551",
    "addr:postcode":"s4r 8p9",
    "addr:street":"4Th Ave",
    "iso:country":"CA",
    "sg:address":"1551 4th Ave",
    "sg:city":"Regina",
    "sg:classifiers":[
        {
            "category":"Retail",
            "subcategory":"Auto Repair",
            "type":"Services"
        }
    ],
    "sg:phone":"+1 306 359 1955",
    "sg:postcode":"S4R 8P9",
    "sg:province":"SK",
    "sg:tags":[
        "wheel",
        "alignment",
        "axle"
    ],
    "wof:name":"Western Wheel Alignment & Brke",
    "wof:placetype":"venue"
},
  "geometry": {"coordinates":[-104.60154,50.462799],"type":"Point"}
}