{
  "type": "Feature",
  "properties": {
    "addr:full":"5 Broadway Corner Brook NL A2H 4C2",
    "addr:housenumber":"5",
    "addr:postcode":"a2h 4c2",
    "addr:street":"Broadway",
    "iso:country":"CA",
    "sg:address":"5 Broadway",
    "sg:city":"Corner Brook",
    "sg:classifiers":[
        {
            "category":"Shopping",
            "subcategory":"Computers & Home Electronics",
            "type":"Retail Goods"
        }
    ],
    "sg:phone":"+1 709 639 7515",
    "sg:postcode":"A2H 4C2",
    "sg:province":"NL",
    "sg:tags":[
        "high",
        "equipment",
        "fidelity",
        "stereophonic",
        "electronic"
    ],
    "wof:name":"Mad Man Murphy's",
    "wof:placetype":"venue"
},
  "geometry": {"coordinates":[-57.951744,48.951485],"type":"Point"}
}