{
  "type": "Feature",
  "properties": {
    "iso:country":"CA",
    "sg:address":"12774 115 St NW",
    "sg:city":"Edmonton",
    "sg:classifiers":[
        {
            "category":"Home & Garden",
            "subcategory":"Building Materials",
            "type":"Retail Goods"
        }
    ],
    "sg:phone":"+1 780 452 2124",
    "sg:postcode":"T5E 5E8",
    "sg:province":"AB",
    "sg:tags":[
        "glass",
        "window",
        "plate"
    ],
    "wof:name":"April Glass & Mirror Ltd",
    "wof:placetype":"venue"
},
  "geometry": {"coordinates":[-113.520103455,53.5860900879],"type":"Point"}
}