{
  "type": "Feature",
  "properties": {
    "addr:full":"4547 Queen St Niagara Falls ON L2E 2L4",
    "addr:housenumber":"4547",
    "addr:postcode":"l2e 2l4",
    "addr:street":"Queen St",
    "iso:country":"CA",
    "sg:address":"4547 Queen St",
    "sg:city":"Niagara Falls",
    "sg:classifiers":[
        {
            "category":"Shopping",
            "subcategory":"Bicycles & Sporting Goods",
            "type":"Retail Goods"
        }
    ],
    "sg:phone":"+1 905 357 1273",
    "sg:postcode":"L2E 2L4",
    "sg:province":"ON",
    "wof:name":"Pedlar Bicycle Shop",
    "wof:placetype":"venue"
},
  "geometry": {"coordinates":[-79.068085,43.106747],"type":"Point"}
}