{
  "type": "Feature",
  "properties": {
    "addr:full":"9261 34 Ave NW # 18 Edmonton AB T6E 5T5",
    "addr:housenumber":"9261;18",
    "addr:postcode":"t6e 5t5",
    "addr:street":"34 Ave Nw #",
    "iso:country":"CA",
    "sg:address":"9261 34 Ave NW # 18",
    "sg:city":"Edmonton",
    "sg:classifiers":[
        {
            "category":"Shopping",
            "subcategory":"Crafts & Fabrics",
            "type":"Retail Goods"
        }
    ],
    "sg:phone":"+1 780 413 1722",
    "sg:postcode":"T6E 5T5",
    "sg:province":"AB",
    "sg:tags":[
        "shop"
    ],
    "wof:name":"Libaas Fashion & Fabric Ltd",
    "wof:placetype":"venue"
},
  "geometry": {"coordinates":[-113.473144531,53.4652862549],"type":"Point"}
}