{
  "type": "Feature",
  "properties": {
    "iso:country":"CA",
    "sg:address":"799 Bloor St W",
    "sg:city":"Oshawa",
    "sg:classifiers":[
        {
            "category":"Autos & Motor Vehicles",
            "subcategory":"Automobile Sales",
            "type":"Retail Goods"
        }
    ],
    "sg:phone":"+1 905 686 1642",
    "sg:postcode":"L1J 5Y6",
    "sg:province":"ON",
    "sg:tags":[
        "car",
        "dealer"
    ],
    "wof:name":"Durham Dodge Chrysler",
    "wof:placetype":"venue"
},
  "geometry": {"coordinates":[-78.88265228269999,43.8739051819],"type":"Point"}
}