{
  "type": "Feature",
  "properties": {
    "iso:country":"CA",
    "sg:address":"441 Clark Ave W",
    "sg:city":"Thornhill",
    "sg:classifiers":[
        {
            "category":"Health Services",
            "subcategory":"Optometrist",
            "type":"Services"
        }
    ],
    "sg:phone":"+1 905 889 2940",
    "sg:postcode":"L4J 6W7",
    "sg:province":"ON",
    "wof:name":"Shaul, Brenda OD",
    "wof:placetype":"venue"
},
  "geometry": {"coordinates":[-79.438354,43.805225],"type":"Point"}
}