{
  "type": "Feature",
  "properties": {
    "addr:full":"9000 Aut Transcanadienne Pointe-Claire QC H9R 5Z8",
    "addr:postcode":"9000;h9r 5z8",
    "addr:street":"Transcanadienne",
    "iso:country":"CA",
    "sg:address":"9000 Aut Transcanadienne",
    "sg:city":"Pointe-Claire",
    "sg:classifiers":[
        {
            "category":"Building & Trades",
            "subcategory":"Electrical",
            "type":"Services"
        }
    ],
    "sg:phone":"+1 514 694 9000",
    "sg:postcode":"H9R 5Z8",
    "sg:province":"QC",
    "sg:tags":[
        "equipment",
        "telecommunication"
    ],
    "wof:name":"Mitec Telecom Inc",
    "wof:placetype":"venue"
},
  "geometry": {"coordinates":[-73.838219,45.457832],"type":"Point"}
}