{
  "type": "Feature",
  "properties": {
    "iso:country":"CA",
    "sg:address":"60 St Clair Ave E # 901",
    "sg:city":"Toronto",
    "sg:classifiers":[
        {
            "category":"Banks & Credit Unions",
            "subcategory":"Investment Brokerage",
            "type":"Services"
        }
    ],
    "sg:phone":"+1 416 925 1615",
    "sg:postcode":"M4T 1N5",
    "sg:province":"ON",
    "wof:name":"M Shier & Assoc Ltd",
    "wof:placetype":"venue"
},
  "geometry": {"coordinates":[-79.39130401609999,43.6887931824],"type":"Point"}
}