{
  "type": "Feature",
  "properties": {
    "iso:country":"CA",
    "sg:address":"897 Adelaide St N",
    "sg:city":"London",
    "sg:classifiers":[
        {
            "category":"Health Services",
            "subcategory":"Health Practitioner",
            "type":"Services"
        }
    ],
    "sg:phone":"+1 519 642 2096",
    "sg:postcode":"N5Y 2M4",
    "sg:province":"ON",
    "sg:tags":[
        "acupuncture"
    ],
    "wof:name":"Alternate Pain Mgmt Clinic",
    "wof:placetype":"venue"
},
  "geometry": {"coordinates":[-81.2396697998,43.0048065186],"type":"Point"}
}