{
  "type": "Feature",
  "properties": {
    "addr:full":"3671 Boul Saint-Charles Kirkland QC H9H 4M2",
    "addr:housenumber":"3671",
    "addr:postcode":"h9h 4m2",
    "addr:street":"Boul Saint-Charles",
    "iso:country":"CA",
    "sg:address":"3671 Boul Saint-Charles",
    "sg:city":"Kirkland",
    "sg:classifiers":[
        {
            "category":"Autos & Motor Vehicles",
            "subcategory":"Fuel & Gas Station",
            "type":"Retail Goods"
        }
    ],
    "sg:phone":"+1 514 697 0666",
    "sg:postcode":"H9H 4M2",
    "sg:province":"QC",
    "sg:tags":[
        "oil"
    ],
    "wof:name":"Ultramar",
    "wof:placetype":"venue"
},
  "geometry": {"coordinates":[-73.864029,45.458252],"type":"Point"}
}