{
  "type": "Feature",
  "properties": {
    "iso:country":"CA",
    "sg:address":"1308 Centre St NE",
    "sg:city":"Calgary",
    "sg:classifiers":[
        {
            "category":"Retail",
            "subcategory":"Repair Shop",
            "type":"Services"
        }
    ],
    "sg:phone":"+1 403 230 5625",
    "sg:postcode":"T2E 2R7",
    "sg:province":"AB",
    "sg:tags":[
        "lock",
        "locksmith"
    ],
    "wof:name":"Aboe Lockworks Ltd",
    "wof:placetype":"venue"
},
  "geometry": {"coordinates":[-114.03327179,51.0524406433],"type":"Point"}
}