{
  "type": "Feature",
  "properties": {
    "addr:full":"Surrey BC V3W 8J9",
    "addr:postcode":"v3w 8j9",
    "iso:country":"CA",
    "sg:city":"Surrey",
    "sg:classifiers":[
        {
            "category":"Manufacturing",
            "subcategory":"Metals",
            "type":"Manufacturing & Wholesale Goods"
        }
    ],
    "sg:phone":"+1 604 572 7382",
    "sg:postcode":"V3W 8J9",
    "sg:province":"BC",
    "sg:tags":[
        "anodizing"
    ],
    "wof:name":"Spectral Finishing Inc",
    "wof:placetype":"venue"
},
  "geometry": {"coordinates":[-122.861969,49.153439],"type":"Point"}
}