{
  "type": "Feature",
  "properties": {
    "addr:full":"354 Cloverdale Rd Rockcliffe ON K1M 0X3",
    "addr:housenumber":"354",
    "addr:postcode":"k1m 0x3",
    "addr:street":"Cloverdale Rd",
    "iso:country":"CA",
    "sg:address":"354 Cloverdale Rd",
    "sg:city":"Rockcliffe",
    "sg:classifiers":[
        {
            "category":"Real Estate",
            "subcategory":"Real Estate Agent",
            "type":"Services"
        }
    ],
    "sg:phone":"+1 613 749 6930",
    "sg:postcode":"K1M 0X3",
    "sg:province":"ON",
    "sg:tags":[
        "consultant"
    ],
    "wof:name":"Trisen Corp",
    "wof:placetype":"venue"
},
  "geometry": {"coordinates":[-75.673538208,45.4507026672],"type":"Point"}
}