{
  "type": "Feature",
  "properties": {
    "addr:full":"1298 Pine Ave Trail BC V1R 4E4",
    "addr:housenumber":"1298",
    "addr:postcode":"bc v1r 4e4",
    "addr:street":"Pine Ave Trail",
    "iso:country":"CA",
    "sg:address":"1298 Pine Ave",
    "sg:city":"Trail",
    "sg:classifiers":[
        {
            "category":"Retail",
            "subcategory":"Funeral Services",
            "type":"Services"
        }
    ],
    "sg:phone":"+1 250 364 1211",
    "sg:postcode":"V1R 4E4",
    "sg:province":"BC",
    "sg:tags":[
        "director"
    ],
    "wof:name":"Carberry's Funeral Home",
    "wof:placetype":"venue"
},
  "geometry": {"coordinates":[-117.710220337,49.0952682495],"type":"Point"}
}