{
  "type": "Feature",
  "properties": {
    "addr:full":"3829 Sunset St Burnaby BC V5G 1T4",
    "addr:housenumber":"3829",
    "addr:postcode":"v5g 1t4",
    "addr:street":"Sunset St",
    "iso:country":"CA",
    "sg:address":"3829 Sunset St",
    "sg:city":"Burnaby",
    "sg:classifiers":[
        {
            "category":"Personal",
            "subcategory":"Beauty Salon",
            "type":"Services"
        }
    ],
    "sg:phone":"+1 604 433 8855",
    "sg:postcode":"V5G 1T4",
    "sg:province":"BC",
    "wof:name":"High-Crest Beauty Salon",
    "wof:placetype":"venue"
},
  "geometry": {"coordinates":[-123.019051,49.249886],"type":"Point"}
}