{
  "type": "Feature",
  "properties": {
    "addr:full":"1316 Pembroke St W Pembroke ON K8A 7A2",
    "addr:housenumber":"1316",
    "addr:postcode":"k8a 7a2",
    "addr:street":"Pembroke St W",
    "iso:country":"CA",
    "sg:address":"1316 Pembroke St W",
    "sg:city":"Pembroke",
    "sg:classifiers":[
        {
            "category":"Insurance",
            "subcategory":"Insurance Agent",
            "type":"Services"
        }
    ],
    "sg:phone":"+1 613 735 0608",
    "sg:postcode":"K8A 7A2",
    "sg:province":"ON",
    "wof:name":"David Minns Insurance Ltd",
    "wof:placetype":"venue"
},
  "geometry": {"coordinates":[-77.1524429321,45.8342666626],"type":"Point"}
}