{
  "type": "Feature",
  "properties": {
    "iso:country":"CA",
    "sg:address":"6 Av Edison",
    "sg:city":"Saint-Lambert",
    "sg:classifiers":[
        {
            "category":"Real Estate",
            "subcategory":"Real Estate Agent",
            "type":"Services"
        }
    ],
    "sg:phone":"+1 450 672 1731",
    "sg:postcode":"J4R 2P2",
    "sg:province":"QC",
    "wof:name":"Stuart Immeubles Inc",
    "wof:placetype":"venue"
},
  "geometry": {"coordinates":[-73.51354980470001,45.4967346191],"type":"Point"}
}