{
  "type": "Feature",
  "properties": {
    "addr:full":"89 University Ave W Windsor ON N9A 5N8",
    "addr:housenumber":"89",
    "addr:postcode":"n9a 5n8",
    "addr:street":"University Ave W",
    "iso:country":"CA",
    "sg:address":"89 University Ave W",
    "sg:city":"Windsor",
    "sg:classifiers":[
        {
            "category":"Bars & Pubs",
            "type":"Food & Drink"
        }
    ],
    "sg:phone":"+1 519 977 6400",
    "sg:postcode":"N9A 5N8",
    "sg:province":"ON",
    "wof:name":"Aardvark Blues Cafe",
    "wof:placetype":"venue"
},
  "geometry": {"coordinates":[-83.039818,42.317268],"type":"Point"}
}