{
  "type": "Feature",
  "properties": {
    "iso:country":"CA",
    "sg:address":"2 Westney Rd N",
    "sg:city":"Ajax",
    "sg:classifiers":[
        {
            "category":"Real Estate",
            "subcategory":"Real Estate Operator",
            "type":"Services"
        }
    ],
    "sg:phone":"+1 905 428 7162",
    "sg:postcode":"L1T 3H3",
    "sg:province":"ON",
    "sg:tags":[
        "apartment"
    ],
    "wof:name":"Top of Westney",
    "wof:placetype":"venue"
},
  "geometry": {"coordinates":[-79.041969,43.857914],"type":"Point"}
}