{
  "type": "Feature",
  "properties": {
    "addr:full":"Peterborough ON K9J 6X7",
    "addr:postcode":"k9j 6x7",
    "iso:country":"CA",
    "sg:city":"Peterborough",
    "sg:phone":"+1 705 745 2488",
    "sg:postcode":"K9J 6X7",
    "sg:province":"ON",
    "sg:tags":[
        "scale"
    ],
    "wof:name":"Masstec Weighing Systems",
    "wof:placetype":"venue"
},
  "geometry": {"coordinates":[-78.292946,44.275517],"type":"Point"}
}