{
  "type": "Feature",
  "properties": {
    "iso:country":"CA",
    "sg:city":"Norwood",
    "sg:classifiers":[
        {
            "category":"Education",
            "subcategory":"Library",
            "type":"Public Place"
        }
    ],
    "sg:phone":"+1 705 639 2228",
    "sg:postcode":"K0L 2V0",
    "sg:province":"ON",
    "sg:tags":[
        "government"
    ],
    "wof:name":"Norwood Public Library",
    "wof:placetype":"venue"
},
  "geometry": {"coordinates":[-77.979133606,44.3830337524],"type":"Point"}
}