{
  "type": "Feature",
  "properties": {
    "iso:country":"CA",
    "sg:address":"2855 Dalton Rd",
    "sg:city":"Timmins",
    "sg:classifiers":[
        {
            "category":"Manufacturing",
            "subcategory":"Lumber",
            "type":"Manufacturing & Wholesale Goods"
        }
    ],
    "sg:phone":"+1 705 264 8231",
    "sg:postcode":"P4N 7C2",
    "sg:province":"ON",
    "sg:tags":[
        "company",
        "logging",
        "landscape",
        "contractor"
    ],
    "wof:name":"Boreal Forestree Svc",
    "wof:placetype":"venue"
},
  "geometry": {"coordinates":[-81.4263305664,48.4187088013],"type":"Point"}
}