{
  "type": "Feature",
  "properties": {
    "addr:full":"11 Cleary Dr Dartmouth NS B2Y 3X3",
    "addr:housenumber":"11",
    "addr:postcode":"b2y 3x3",
    "addr:street":"Cleary Dr",
    "iso:country":"CA",
    "sg:address":"11 Cleary Dr",
    "sg:city":"Dartmouth",
    "sg:classifiers":[
        {
            "category":"Building & Trades",
            "subcategory":"Construction",
            "type":"Services"
        }
    ],
    "sg:phone":"+1 902 465 5360",
    "sg:postcode":"B2Y 3X3",
    "sg:province":"NS",
    "sg:tags":[
        "general",
        "contractor"
    ],
    "wof:name":"Classic Roofing & Siding Ltd",
    "wof:placetype":"venue"
},
  "geometry": {"coordinates":[-63.539074,44.66605],"type":"Point"}
}