{
  "type": "Feature",
  "properties": {
    "addr:full":"4 Water St Saint John NB E2L 2A5",
    "addr:housenumber":"4",
    "addr:postcode":"e2l 2a5",
    "addr:street":"Water St",
    "iso:country":"CA",
    "sg:address":"4 Water St",
    "sg:city":"Saint John",
    "sg:classifiers":[
        {
            "category":"Retail",
            "subcategory":"Auto Rental",
            "type":"Services"
        }
    ],
    "sg:phone":"+1 506 634 7750",
    "sg:postcode":"E2L 2A5",
    "sg:province":"NB",
    "sg:tags":[
        "renting",
        "automobile"
    ],
    "wof:name":"Avis Rent A Car",
    "wof:placetype":"venue"
},
  "geometry": {"coordinates":[-66.06293487550001,45.2728004456],"type":"Point"}
}