{
  "type": "Feature",
  "properties": {
    "addr:full":"2508 Lakeshore Rd W Oakville ON L6L 1H8",
    "addr:housenumber":"2508",
    "addr:postcode":"l6l 1h8",
    "addr:street":"Lakeshore Rd W",
    "iso:country":"CA",
    "sg:address":"2508 Lakeshore Rd W",
    "sg:city":"Oakville",
    "sg:classifiers":[
        {
            "category":"Autos & Motor Vehicles",
            "subcategory":"Boat Sales",
            "type":"Retail Goods"
        }
    ],
    "sg:phone":"+1 905 825 0561",
    "sg:postcode":"L6L 1H8",
    "sg:province":"ON",
    "sg:tags":[
        "dealer"
    ],
    "wof:name":"G & B Sports Marine Ltd",
    "wof:placetype":"venue"
},
  "geometry": {"coordinates":[-79.712928772,43.3930892944],"type":"Point"}
}