{
  "type": "Feature",
  "properties": {
    "addr:full":"183 Rue Du Roi Sorel-Tracy QC J3P 4N6",
    "addr:housenumber":"183",
    "addr:postcode":"j3p 4n6",
    "addr:street":"Rue Du Roi",
    "iso:country":"CA",
    "sg:address":"183 Rue Du Roi",
    "sg:city":"Sorel-Tracy",
    "sg:classifiers":[
        {
            "category":"Professional",
            "subcategory":"Accounting & Tax Preparation",
            "type":"Services"
        }
    ],
    "sg:phone":"+1 450 730 0000",
    "sg:postcode":"J3P 4N6",
    "sg:province":"QC",
    "sg:tags":[
        "return",
        "filing"
    ],
    "wof:name":"A 1 Impot",
    "wof:placetype":"venue"
},
  "geometry": {"coordinates":[-73.1140289307,46.0395202637],"type":"Point"}
}