{
  "type": "Feature",
  "properties": {
    "iso:country":"CA",
    "sg:address":"6075 Ch DE Chambly",
    "sg:city":"Saint-Hubert",
    "sg:classifiers":[
        {
            "category":"Personal",
            "subcategory":"Beauty Salon",
            "type":"Services"
        }
    ],
    "sg:phone":"+1 450 443 0258",
    "sg:postcode":"J3Y 3R6",
    "sg:province":"QC",
    "wof:name":"Salon Dynastie Enr",
    "wof:placetype":"venue"
},
  "geometry": {"coordinates":[-73.405663,45.497757],"type":"Point"}
}