{
  "type": "Feature",
  "properties": {
    "iso:country":"CA",
    "sg:address":"47 Main St S",
    "sg:city":"Georgetown",
    "sg:classifiers":[
        {
            "category":"Manufacturing",
            "subcategory":"Tools & Machinery",
            "type":"Manufacturing & Wholesale Goods"
        }
    ],
    "sg:phone":"+1 905 877 2711",
    "sg:postcode":"L7G 3G2",
    "sg:province":"ON",
    "sg:tags":[
        "equipment",
        "hospital",
        "pharmacy"
    ],
    "wof:name":"Young's Pharmacy & Homecare",
    "wof:placetype":"venue"
},
  "geometry": {"coordinates":[-79.926826,43.650173],"type":"Point"}
}