{
  "type": "Feature",
  "properties": {
    "addr:full":"47 Main St S Georgetown ON L7G 3G2",
    "addr:housenumber":"47",
    "addr:postcode":"l7g 3g2",
    "addr:street":"Main St S",
    "iso:country":"CA",
    "sg:address":"47 Main St S",
    "sg:city":"Georgetown",
    "sg:classifiers":[
        {
            "category":"Manufacturing",
            "subcategory":"Tools & Machinery",
            "type":"Manufacturing & Wholesale Goods"
        }
    ],
    "sg:phone":"+1 905 877 2711",
    "sg:postcode":"L7G 3G2",
    "sg:province":"ON",
    "sg:tags":[
        "equipment",
        "hospital",
        "pharmacy"
    ],
    "wof:name":"Young's Pharmacy & Homecare",
    "wof:placetype":"venue"
},
  "geometry": {"coordinates":[-79.92682600000001,43.650173],"type":"Point"}
}