{
  "type": "Feature",
  "properties": {
    "addr:full":"1107 Webbwood Dr Sudbury ON P3C 3B6",
    "addr:housenumber":"1107",
    "addr:postcode":"p3c 3b6",
    "addr:street":"Webbwood Dr",
    "iso:country":"CA",
    "sg:address":"1107 Webbwood Dr",
    "sg:city":"Sudbury",
    "sg:classifiers":[
        {
            "category":"Retail",
            "subcategory":"Car Wash",
            "type":"Services"
        }
    ],
    "sg:phone":"+1 705 671 2927",
    "sg:postcode":"P3C 3B6",
    "sg:province":"ON",
    "sg:tags":[
        "polishing",
        "washing"
    ],
    "wof:name":"Corrosion Free",
    "wof:placetype":"venue"
},
  "geometry": {"coordinates":[-81.027817,46.471947],"type":"Point"}
}