{
  "type": "Feature",
  "properties": {
    "addr:full":"300 138 Rte Saint-Tite-Des-Caps QC G0A 4J0",
    "addr:housenumber":"138",
    "addr:postcode":"g0a 4j0",
    "addr:street":"Rte Saint-Tite-Des-Caps",
    "iso:country":"CA",
    "sg:address":"300 138 Rte",
    "sg:city":"Saint-Tite-Des-Caps",
    "sg:classifiers":[
        {
            "category":"Retail",
            "subcategory":"Auto Repair",
            "type":"Services"
        }
    ],
    "sg:phone":"+1 418 823 2040",
    "sg:postcode":"G0A 4J0",
    "sg:province":"QC",
    "sg:tags":[
        "repairing",
        "automobile"
    ],
    "wof:name":"Simeon Ferland Inc",
    "wof:placetype":"venue"
},
  "geometry": {"coordinates":[-70.768593,47.142159],"type":"Point"}
}