{
  "type": "Feature",
  "properties": {
    "addr:full":"Victoria BC V8N 4P6",
    "addr:postcode":"v8n 4p6",
    "iso:country":"CA",
    "sg:city":"Victoria",
    "sg:classifiers":[
        {
            "category":"Professional",
            "subcategory":"Accounting & Tax Preparation",
            "type":"Services"
        }
    ],
    "sg:phone":"+1 250 477 1423",
    "sg:postcode":"V8N 4P6",
    "sg:province":"BC",
    "sg:tags":[
        "accountant"
    ],
    "wof:name":"Frank M Lee Accounting",
    "wof:placetype":"venue"
},
  "geometry": {"coordinates":[-123.333237,48.448151],"type":"Point"}
}