{
  "type": "Feature",
  "properties": {
    "addr:full":"1030 Des Cedres St Chute A Blondeau ON K0B 1B0",
    "addr:housenumber":"1030",
    "addr:postcode":"k0b 1b0",
    "addr:street":"Des Cedres St;A Blondeau",
    "iso:country":"CA",
    "sg:address":"1030 Des Cedres St",
    "sg:city":"Chute A Blondeau",
    "sg:classifiers":[
        {
            "category":"Personal",
            "subcategory":"Beauty Salon",
            "type":"Services"
        }
    ],
    "sg:phone":"+1 613 632 0524",
    "sg:postcode":"K0B 1B0",
    "sg:province":"ON",
    "wof:name":"Salon Du Village",
    "wof:placetype":"venue"
},
  "geometry": {"coordinates":[-74.470161,45.587406],"type":"Point"}
}