{
  "type": "Feature",
  "properties": {
    "iso:country":"CA",
    "sg:address":"NW 19 2 7W",
    "sg:city":"Darlingford",
    "sg:classifiers":[
        {
            "category":"Farming",
            "subcategory":"Farm",
            "type":"Manufacturing & Wholesale Goods"
        }
    ],
    "sg:phone":"+1 204 246 2182",
    "sg:postcode":"R0G 0L0",
    "sg:province":"MB",
    "wof:name":"Pembina Colony",
    "wof:placetype":"venue"
},
  "geometry": {"coordinates":[-98.377663,49.204361],"type":"Point"}
}