{
  "type": "Feature",
  "properties": {
    "addr:full":"3033 Rue Daemen Shawinigan QC G9N 6A9",
    "addr:housenumber":"3033",
    "addr:postcode":"g9n 6a9",
    "addr:street":"Rue Daemen",
    "iso:country":"CA",
    "sg:address":"3033 Rue Daemen",
    "sg:city":"Shawinigan",
    "sg:classifiers":[
        {
            "category":"Building & Trades",
            "subcategory":"Construction",
            "type":"Services"
        }
    ],
    "sg:phone":"+1 819 539 6851",
    "sg:postcode":"G9N 6A9",
    "sg:province":"QC",
    "sg:tags":[
        "general",
        "contractor"
    ],
    "wof:name":"Construction Denis Rousseau",
    "wof:placetype":"venue"
},
  "geometry": {"coordinates":[-72.74559783940001,46.5724983215],"type":"Point"}
}