{
  "type": "Feature",
  "properties": {
    "addr:full":"2 Rue Querry Saint-Quentin NB E8A 1Z1",
    "addr:housenumber":"2",
    "addr:postcode":"e8a 1z1",
    "addr:street":"Rue Querry",
    "iso:country":"CA",
    "sg:address":"2 Rue Querry",
    "sg:city":"Saint-Quentin",
    "sg:classifiers":[
        {
            "category":"Retail",
            "subcategory":"Auto Repair",
            "type":"Services"
        }
    ],
    "sg:phone":"+1 506 235 2218",
    "sg:postcode":"E8A 1Z1",
    "sg:province":"NB",
    "sg:tags":[
        "lining",
        "parts",
        "brake",
        "truck",
        "equipment"
    ],
    "wof:name":"Yvan Brake & Clutch Ind Parts",
    "wof:placetype":"venue"
},
  "geometry": {"coordinates":[-67.3915939331,47.520275116],"type":"Point"}
}