{
  "type": "Feature",
  "properties": {
    "addr:full":"171 Rue Notre-Dame Mont-Carmel QC G0L 1W0",
    "addr:housenumber":"171",
    "addr:postcode":"g0l 1w0",
    "addr:street":"Rue Notre-Dame",
    "iso:country":"CA",
    "sg:address":"171 Rue Notre-Dame",
    "sg:city":"Mont-Carmel",
    "sg:classifiers":[
        {
            "category":"Farming",
            "subcategory":"Farm",
            "type":"Manufacturing & Wholesale Goods"
        }
    ],
    "sg:phone":"+1 418 498 2011",
    "sg:postcode":"G0L 1W0",
    "sg:province":"QC",
    "wof:name":"Gena & Fils Inc",
    "wof:placetype":"venue"
},
  "geometry": {"coordinates":[-69.84418487550001,47.450466156],"type":"Point"}
}