{
  "type": "Feature",
  "properties": {
    "addr:full":"20 Patterson Blvd SW Calgary AB T3H 1W9",
    "addr:housenumber":"20",
    "addr:postcode":"t3h 1w9",
    "addr:street":"Patterson Blvd Sw",
    "iso:country":"CA",
    "sg:address":"20 Patterson Blvd SW",
    "sg:city":"Calgary",
    "sg:classifiers":[
        {
            "category":"Real Estate",
            "subcategory":"Real Estate Operator",
            "type":"Services"
        }
    ],
    "sg:phone":"+1 403 249 4440",
    "sg:postcode":"T3H 1W9",
    "sg:province":"AB",
    "sg:tags":[
        "apartment"
    ],
    "wof:name":"Coachman House",
    "wof:placetype":"venue"
},
  "geometry": {"coordinates":[-114.178574,51.060558],"type":"Point"}
}