{
  "type": "Feature",
  "properties": {
    "addr:full":"1870 St Clair Ave W Toronto ON M6N 1J8",
    "addr:housenumber":"1870",
    "addr:postcode":"m6n 1j8",
    "addr:street":"St Clair Ave W",
    "iso:country":"CA",
    "sg:address":"1870 St Clair Ave W",
    "sg:city":"Toronto",
    "sg:classifiers":[
        {
            "category":"Manufacturing",
            "subcategory":"Printing",
            "type":"Manufacturing & Wholesale Goods"
        }
    ],
    "sg:phone":"+1 416 656 3311",
    "sg:postcode":"M6N 1J8",
    "sg:province":"ON",
    "sg:tags":[
        "printer"
    ],
    "wof:name":"Royal Printing CO",
    "wof:placetype":"venue"
},
  "geometry": {"coordinates":[-79.4644775391,43.6733551025],"type":"Point"}
}