{
  "type": "Feature",
  "properties": {
    "addr:full":"524 Main St Montague PE C0A 1R0",
    "addr:housenumber":"524",
    "addr:postcode":"c0a 1r0",
    "addr:street":"Main St",
    "iso:country":"CA",
    "sg:address":"524 Main St",
    "sg:city":"Montague",
    "sg:classifiers":[
        {
            "category":"Banks & Credit Unions",
            "subcategory":"Bank",
            "type":"Services"
        }
    ],
    "sg:phone":"+1 902 838 3636",
    "sg:postcode":"C0A 1R0",
    "sg:province":"PE",
    "wof:name":"Montague Credit Union",
    "wof:placetype":"venue"
},
  "geometry": {"coordinates":[-62.649918,46.168205],"type":"Point"}
}