{
  "type": "Feature",
  "properties": {
    "iso:country":"CA",
    "sg:address":"2446 Bank St #118",
    "sg:city":"Ottawa",
    "sg:classifiers":[
        {
            "category":"Shopping",
            "subcategory":"News",
            "type":"Retail Goods"
        }
    ],
    "sg:phone":"+1 613 247 6397",
    "sg:postcode":"K1V 1A4",
    "sg:province":"ON",
    "sg:tags":[
        "magazine"
    ],
    "wof:name":"Towngate News",
    "wof:placetype":"venue"
},
  "geometry": {"coordinates":[-75.6464920044,45.3534927368],"type":"Point"}
}