{
  "type": "Feature",
  "properties": {
    "addr:full":"10435 142 St NW Edmonton AB T5N 2P4",
    "addr:housenumber":"10435",
    "addr:postcode":"t5n 2p4",
    "addr:street":"142 St Nw",
    "iso:country":"CA",
    "sg:address":"10435 142 St NW",
    "sg:city":"Edmonton",
    "sg:classifiers":[
        {
            "category":"Professional",
            "subcategory":"Lawyer & Legal Services",
            "type":"Services"
        }
    ],
    "sg:phone":"+1 780 451 7889",
    "sg:postcode":"T5N 2P4",
    "sg:province":"AB",
    "sg:tags":[
        "attorney"
    ],
    "wof:name":"Furman, Michael L",
    "wof:placetype":"venue"
},
  "geometry": {"coordinates":[-113.565338,53.547287],"type":"Point"}
}