{
  "type": "Feature",
  "properties": {
    "addr:full":"999 Cameron St Hawkesbury ON K6A 2B8",
    "addr:housenumber":"999",
    "addr:postcode":"k6a 2b8",
    "addr:street":"Cameron St",
    "iso:country":"CA",
    "sg:address":"999 Cameron St",
    "sg:city":"Hawkesbury",
    "sg:classifiers":[
        {
            "category":"Home & Garden",
            "subcategory":"Building Materials",
            "type":"Retail Goods"
        }
    ],
    "sg:phone":"+1 613 632 3427",
    "sg:postcode":"K6A 2B8",
    "sg:province":"ON",
    "sg:tags":[
        "carpet",
        "dealer",
        "rug"
    ],
    "wof:name":"Robillard Carpet Ctr",
    "wof:placetype":"venue"
},
  "geometry": {"coordinates":[-74.5969009399,45.5996398926],"type":"Point"}
}