{
  "type": "Feature",
  "properties": {
    "iso:country":"CA",
    "sg:address":"5010 106 Ave NW",
    "sg:city":"Edmonton",
    "sg:classifiers":[
        {
            "category":"Restaurant",
            "type":"Food & Drink"
        }
    ],
    "sg:phone":"+1 780 490 6759",
    "sg:postcode":"T6A 1E9",
    "sg:province":"AB",
    "sg:tags":[
        "shop",
        "coffee"
    ],
    "wof:name":"Blues Java Bar",
    "wof:placetype":"venue"
},
  "geometry": {"coordinates":[-113.42076110799999,53.5511894226],"type":"Point"}
}