{
  "type": "Feature",
  "properties": {
    "addr:full":"4 Rue Du Parc Kedgwick NB E8B 1E3",
    "addr:housenumber":"4",
    "addr:postcode":"e8b 1e3",
    "addr:street":"Rue Du Parc",
    "iso:country":"CA",
    "sg:address":"4 Rue Du Parc",
    "sg:city":"Kedgwick",
    "sg:classifiers":[
        {
            "category":"Shopping",
            "subcategory":"Florist",
            "type":"Retail Goods"
        }
    ],
    "sg:phone":"+1 506 284 2589",
    "sg:postcode":"E8B 1E3",
    "sg:province":"NB",
    "wof:name":"Fleuriste LA Jacinthe",
    "wof:placetype":"venue"
},
  "geometry": {"coordinates":[-67.34198000000001,47.64782],"type":"Point"}
}