{
  "type": "Feature",
  "properties": {
    "addr:full":"Scarborough ON M1R 2S9",
    "addr:postcode":"m1r 2s9",
    "iso:country":"CA",
    "sg:city":"Scarborough",
    "sg:classifiers":[
        {
            "category":"Retail",
            "subcategory":"Auto Repair",
            "type":"Services"
        }
    ],
    "sg:phone":"+1 416 335 8378",
    "sg:postcode":"M1R 2S9",
    "sg:province":"ON",
    "sg:tags":[
        "automobile",
        "testing",
        "emission"
    ],
    "wof:name":"Emission Check",
    "wof:placetype":"venue"
},
  "geometry": {"coordinates":[-79.301132,43.763702],"type":"Point"}
}