{
  "type": "Feature",
  "properties": {
    "addr:full":"Whitehorse YT Y1A 2C5",
    "addr:postcode":"y1a 2c5",
    "iso:country":"CA",
    "sg:city":"Whitehorse",
    "sg:classifiers":[
        {
            "category":"Organizations",
            "subcategory":"Professional Association",
            "type":"Services"
        }
    ],
    "sg:phone":"+1 867 668 6864",
    "sg:postcode":"Y1A 2C5",
    "sg:province":"YT",
    "wof:name":"Yukon Agricultural Assn",
    "wof:placetype":"venue"
},
  "geometry": {"coordinates":[-135.05517599999999,60.720158],"type":"Point"}
}