{
  "type": "Feature",
  "properties": {
    "addr:full":"520 King St #840 Fredericton NB E3B 6G3",
    "addr:housenumber":"520",
    "addr:postcode":"e3b 6g3",
    "addr:street":"King St # 840",
    "iso:country":"CA",
    "sg:address":"520 King St #840",
    "sg:city":"Fredericton",
    "sg:classifiers":[
        {
            "category":"Food & Beverages",
            "subcategory":"Groceries & Convenience Stores",
            "type":"Retail Goods"
        }
    ],
    "sg:phone":"+1 506 454 1180",
    "sg:postcode":"E3B 6G3",
    "sg:province":"NB",
    "sg:tags":[
        "magazine"
    ],
    "wof:name":"Carleton News Stop Ltd",
    "wof:placetype":"venue"
},
  "geometry": {"coordinates":[-66.6416320801,45.9608840942],"type":"Point"}
}