{
  "type": "Feature",
  "properties": {
    "addr:full":"Bridgetown NS B0S 1C0",
    "addr:postcode":"b0s 1c0",
    "iso:country":"CA",
    "sg:city":"Bridgetown",
    "sg:classifiers":[
        {
            "category":"Government",
            "subcategory":"Office",
            "type":"Public Place"
        }
    ],
    "sg:phone":"+1 902 665 4083",
    "sg:postcode":"B0S 1C0",
    "sg:province":"NS",
    "wof:name":"Western Valley Development",
    "wof:placetype":"venue"
},
  "geometry": {"coordinates":[-65.295975,44.843369],"type":"Point"}
}