{
  "type": "Feature",
  "properties": {
    "iso:country":"CA",
    "sg:address":"960 Queen St",
    "sg:city":"Kincardine",
    "sg:classifiers":[
        {
            "category":"Food & Beverages",
            "subcategory":"Groceries & Convenience Stores",
            "type":"Retail Goods"
        }
    ],
    "sg:phone":"+1 519 396 2134",
    "sg:postcode":"N2Z 2Y2",
    "sg:province":"ON",
    "wof:name":"Mac's Convenience Stores Ltd",
    "wof:placetype":"venue"
},
  "geometry": {"coordinates":[-81.63259887700001,44.180770874],"type":"Point"}
}