{
  "type": "Feature",
  "properties": {
    "addr:full":"614 Frederica St W Thunder Bay ON P7E 3X1",
    "addr:housenumber":"614",
    "addr:postcode":"p7e 3x1",
    "addr:street":"Frederica St W",
    "iso:country":"CA",
    "sg:address":"614 Frederica St W",
    "sg:city":"Thunder Bay",
    "sg:classifiers":[
        {
            "category":"Shopping",
            "subcategory":"Bicycles & Sporting Goods",
            "type":"Retail Goods"
        }
    ],
    "sg:phone":"+1 807 577 9801",
    "sg:postcode":"P7E 3X1",
    "sg:province":"ON",
    "sg:tags":[
        "bait",
        "fishing"
    ],
    "wof:name":"Sunshine Baits",
    "wof:placetype":"venue"
},
  "geometry": {"coordinates":[-89.291168,48.364887],"type":"Point"}
}