{
  "type": "Feature",
  "properties": {
    "addr:full":"3 Mcgloin St Fredericton NB E3A 4J9",
    "addr:housenumber":"3",
    "addr:postcode":"e3a 4j9",
    "addr:street":"Mcgloin St",
    "iso:country":"CA",
    "sg:address":"3 Mcgloin St",
    "sg:city":"Fredericton",
    "sg:classifiers":[
        {
            "category":"Home & Garden",
            "subcategory":"Building Materials",
            "type":"Retail Goods"
        }
    ],
    "sg:phone":"+1 506 453 1318",
    "sg:postcode":"E3A 4J9",
    "sg:province":"NB",
    "sg:tags":[
        "glass",
        "leaded"
    ],
    "wof:name":"Shades of Light Ltd",
    "wof:placetype":"venue"
},
  "geometry": {"coordinates":[-66.5888290405,45.9759368896],"type":"Point"}
}