{
  "type": "Feature",
  "properties": {
    "iso:country":"CA",
    "sg:address":"RR 4 STN Main",
    "sg:city":"Perth",
    "sg:classifiers":[
        {
            "category":"Travel",
            "subcategory":"Campground",
            "type":"Entertainment"
        }
    ],
    "sg:phone":"+1 613 267 3955",
    "sg:postcode":"K7H 3C6",
    "sg:province":"ON",
    "wof:name":"Tay River Tent & Trailer Park",
    "wof:placetype":"venue"
},
  "geometry": {"coordinates":[-76.2483291626,44.8989448547],"type":"Point"}
}