{
  "type": "Feature",
  "properties": {
    "iso:country":"CA",
    "sg:address":"78 Milltown Blvd",
    "sg:city":"St Stephen",
    "sg:classifiers":[
        {
            "category":"Food & Beverages",
            "subcategory":"Groceries & Convenience Stores",
            "type":"Retail Goods"
        }
    ],
    "sg:phone":"+1 506 466 2520",
    "sg:postcode":"E3L 1G6",
    "sg:province":"NB",
    "wof:name":"Miss D's Convenience Ctr Ltd",
    "wof:placetype":"venue"
},
  "geometry": {"coordinates":[-67.2782287598,45.1924362183],"type":"Point"}
}