{
  "type": "Feature",
  "properties": {
    "addr:full":"215 Crescent St Peterborough ON K9J 2G5",
    "addr:housenumber":"215",
    "addr:postcode":"k9j 2g5",
    "addr:street":"Crescent St",
    "iso:country":"CA",
    "sg:address":"215 Crescent St",
    "sg:city":"Peterborough",
    "sg:classifiers":[
        {
            "category":"Building & Trades",
            "subcategory":"Electrical",
            "type":"Services"
        }
    ],
    "sg:phone":"+1 705 876 9100",
    "sg:postcode":"K9J 2G5",
    "sg:province":"ON",
    "sg:tags":[
        "electric",
        "contractor"
    ],
    "wof:name":"H & M Electric",
    "wof:placetype":"venue"
},
  "geometry": {"coordinates":[-78.318085,44.293816],"type":"Point"}
}