{
  "type": "Feature",
  "properties": {
    "addr:full":"492 Rue Lamoureux Sainte-Julie QC J3E 1G9",
    "addr:housenumber":"492",
    "addr:postcode":"j3e 1g9",
    "addr:street":"Rue Lamoureux",
    "iso:country":"CA",
    "sg:address":"492 Rue Lamoureux",
    "sg:city":"Sainte-Julie",
    "sg:classifiers":[
        {
            "category":"Shopping",
            "subcategory":"Bicycles & Sporting Goods",
            "type":"Retail Goods"
        }
    ],
    "sg:phone":"+1 450 922 1835",
    "sg:postcode":"J3E 1G9",
    "sg:province":"QC",
    "wof:name":"Exclusivite Chasse & Peche Ste",
    "wof:placetype":"venue"
},
  "geometry": {"coordinates":[-73.33575399999999,45.592453],"type":"Point"}
}