{
  "type": "Feature",
  "properties": {
    "iso:country":"CA",
    "sg:city":"Mallorytown",
    "sg:classifiers":[
        {
            "category":"Travel",
            "subcategory":"Hotels & Motels",
            "type":"Entertainment"
        }
    ],
    "sg:phone":"+1 613 923 5339",
    "sg:postcode":"K0E 1R0",
    "sg:province":"ON",
    "sg:tags":[
        "campground",
        "tourist",
        "accommodation"
    ],
    "wof:name":"Thousand Islands Koa Camping",
    "wof:placetype":"venue"
},
  "geometry": {"coordinates":[-75.8799362183,44.4781455994],"type":"Point"}
}