{
  "type": "Feature",
  "properties": {
    "addr:full":"Fort Nelson BC V0C 1R0",
    "addr:postcode":"bc v0c 1r0",
    "iso:country":"CA",
    "sg:city":"Fort Nelson",
    "sg:classifiers":[
        {
            "category":"Manufacturing",
            "subcategory":"Signs",
            "type":"Manufacturing & Wholesale Goods"
        }
    ],
    "sg:phone":"+1 250 774 7689",
    "sg:postcode":"V0C 1R0",
    "sg:province":"BC",
    "wof:name":"Image Tech",
    "wof:placetype":"venue"
},
  "geometry": {"coordinates":[-122.68596599999999,58.803211],"type":"Point"}
}