{
  "type": "Feature",
  "properties": {
    "addr:full":"Winnipeg MB R3C 4J5",
    "addr:postcode":"r3c 4j5",
    "iso:country":"CA",
    "sg:city":"Winnipeg",
    "sg:classifiers":[
        {
            "category":"Health Services",
            "subcategory":"Doctor",
            "type":"Services"
        }
    ],
    "sg:phone":"+1 204 942 7744",
    "sg:postcode":"R3C 4J5",
    "sg:province":"MB",
    "sg:tags":[
        "physician",
        "surgeon"
    ],
    "wof:name":"Mac Kay, M J MD",
    "wof:placetype":"venue"
},
  "geometry": {"coordinates":[-97.1371,49.887741],"type":"Point"}
}