{
  "type": "Feature",
  "properties": {
    "iso:country":"CA",
    "sg:city":"Mission",
    "sg:classifiers":[
        {
            "category":"Health Services",
            "subcategory":"Doctor",
            "type":"Services"
        }
    ],
    "sg:phone":"+1 604 820 2477",
    "sg:postcode":"V2V 6M7",
    "sg:province":"BC",
    "sg:tags":[
        "dentist"
    ],
    "wof:name":"Mission Junction Dental Clinic",
    "wof:placetype":"venue"
},
  "geometry": {"coordinates":[-122.317642212,49.1289710999],"type":"Point"}
}