{
  "type": "Feature",
  "properties": {
    "addr:full":"3986 Chesswood Dr North York ON M3J 2W6",
    "addr:housenumber":"3986",
    "addr:postcode":"m3j 2w6",
    "addr:street":"Chesswood Dr",
    "iso:country":"CA",
    "sg:address":"3986 Chesswood Dr",
    "sg:city":"North York",
    "sg:classifiers":[
        {
            "category":"Building & Trades",
            "subcategory":"Cleaning & Sanitation",
            "type":"Services"
        }
    ],
    "sg:phone":"+1 416 635 9595",
    "sg:postcode":"M3J 2W6",
    "sg:province":"ON",
    "sg:tags":[
        "window"
    ],
    "wof:name":"Beaver Integrated Svc",
    "wof:placetype":"venue"
},
  "geometry": {"coordinates":[-79.47505200000001,43.756935],"type":"Point"}
}