{
  "type": "Feature",
  "properties": {
    "iso:country":"CA",
    "sg:address":"194 Mitton St N",
    "sg:city":"Sarnia",
    "sg:classifiers":[
        {
            "category":"Autos & Motor Vehicles",
            "subcategory":"Auto Supplies",
            "type":"Retail Goods"
        }
    ],
    "sg:phone":"+1 519 337 2331",
    "sg:postcode":"N7T 6H4",
    "sg:province":"ON",
    "sg:tags":[
        "automobile",
        "parts"
    ],
    "wof:name":"Sarnia Auto Parts",
    "wof:placetype":"venue"
},
  "geometry": {"coordinates":[-82.398056,42.9739],"type":"Point"}
}