{
  "type": "Feature",
  "properties": {
    "addr:full":"42 Boul Rene-Levesque O Quebec QC G1R 2A4",
    "addr:housenumber":"42",
    "addr:postcode":"g1r 2a4",
    "addr:street":"Boul Rene-Levesque O",
    "iso:country":"CA",
    "sg:address":"42 Boul Rene-Levesque O",
    "sg:city":"Quebec",
    "sg:classifiers":[
        {
            "category":"Wholesale",
            "subcategory":"Groceries",
            "type":"Manufacturing & Wholesale Goods"
        }
    ],
    "sg:phone":"+1 418 529 8999",
    "sg:postcode":"G1R 2A4",
    "sg:province":"QC",
    "sg:tags":[
        "pasta",
        "gourmet",
        "shop"
    ],
    "wof:name":"Pates A Tout Inc",
    "wof:placetype":"venue"
},
  "geometry": {"coordinates":[-71.225021,46.805408],"type":"Point"}
}