{
  "type": "Feature",
  "properties": {
    "addr:full":"1095 Cliffe Ave Courtenay BC V9N 2J9",
    "addr:housenumber":"1095",
    "addr:postcode":"v9n 2j9",
    "addr:street":"Cliffe Ave",
    "iso:country":"CA",
    "sg:address":"1095 Cliffe Ave",
    "sg:city":"Courtenay",
    "sg:classifiers":[
        {
            "category":"Manufacturing",
            "subcategory":"Apparel",
            "type":"Manufacturing & Wholesale Goods"
        }
    ],
    "sg:phone":"+1 250 334 1778",
    "sg:postcode":"V9N 2J9",
    "sg:province":"BC",
    "sg:tags":[
        "sewing",
        "contractor"
    ],
    "wof:name":"Euro Tailoring",
    "wof:placetype":"venue"
},
  "geometry": {"coordinates":[-124.994888,49.68795],"type":"Point"}
}