{
  "type": "Feature",
  "properties": {
    "iso:country":"CA",
    "sg:address":"181 Boul Laurier",
    "sg:city":"Mcmasterville",
    "sg:classifiers":[
        {
            "category":"Shopping",
            "subcategory":"Used Merchandise",
            "type":"Retail Goods"
        }
    ],
    "sg:phone":"+1 450 464 7888",
    "sg:postcode":"J3G 1P9",
    "sg:province":"QC",
    "sg:tags":[
        "furniture"
    ],
    "wof:name":"Meubletout",
    "wof:placetype":"venue"
},
  "geometry": {"coordinates":[-73.224937,45.548149],"type":"Point"}
}