{
  "type": "Feature",
  "properties": {
    "addr:full":"181 Boul Laurier Mcmasterville QC J3G 1P9",
    "addr:housenumber":"181",
    "addr:postcode":"j3g 1p9",
    "addr:street":"Boul Laurier",
    "iso:country":"CA",
    "sg:address":"181 Boul Laurier",
    "sg:city":"Mcmasterville",
    "sg:classifiers":[
        {
            "category":"Shopping",
            "subcategory":"Used Merchandise",
            "type":"Retail Goods"
        }
    ],
    "sg:phone":"+1 450 464 7888",
    "sg:postcode":"J3G 1P9",
    "sg:province":"QC",
    "sg:tags":[
        "furniture"
    ],
    "wof:name":"Meubletout",
    "wof:placetype":"venue"
},
  "geometry": {"coordinates":[-73.224937,45.548149],"type":"Point"}
}