{
  "type": "Feature",
  "properties": {
    "iso:country":"CA",
    "sg:address":"160 76E Rue E",
    "sg:city":"Charlesbourg",
    "sg:classifiers":[
        {
            "category":"Government",
            "subcategory":"Office",
            "type":"Public Place"
        }
    ],
    "sg:phone":"+1 418 641 6226",
    "sg:postcode":"G1H 7H6",
    "sg:province":"QC",
    "sg:tags":[
        "village"
    ],
    "wof:name":"Arrondissements 4-5 & 7",
    "wof:placetype":"venue"
},
  "geometry": {"coordinates":[-71.25119,46.845703],"type":"Point"}
}