{
  "type": "Feature",
  "properties": {
    "iso:country":"CA",
    "sg:city":"Kelowna",
    "sg:classifiers":[
        {
            "category":"Professional",
            "subcategory":"Engineering",
            "type":"Services"
        }
    ],
    "sg:phone":"+1 250 860 8424",
    "sg:postcode":"V1Y 5V5",
    "sg:province":"BC",
    "sg:tags":[
        "engineer"
    ],
    "wof:name":"Golder Associates Ltd",
    "wof:placetype":"venue"
},
  "geometry": {"coordinates":[-119.45778656,49.8767356873],"type":"Point"}
}