{
  "type": "Feature",
  "properties": {
    "iso:country":"CA",
    "sg:city":"Newmarket",
    "sg:classifiers":[
        {
            "category":"Shopping",
            "subcategory":"Clothing, Apparel, & Fashions",
            "type":"Retail Goods"
        }
    ],
    "sg:phone":"+1 905 895 4336",
    "sg:postcode":"L3Y 4Z1",
    "sg:province":"ON",
    "sg:tags":[
        "item",
        "boutique"
    ],
    "wof:name":"Fruits & Passion",
    "wof:placetype":"venue"
},
  "geometry": {"coordinates":[-79.481071,44.057091],"type":"Point"}
}