{
  "type": "Feature",
  "properties": {
    "iso:country":"CA",
    "sg:address":"75 Boul Saint-Luc O",
    "sg:city":"Alma",
    "sg:classifiers":[
        {
            "category":"Real Estate",
            "subcategory":"Real Estate Agent",
            "type":"Services"
        }
    ],
    "sg:phone":"+1 418 662 4000",
    "sg:postcode":"G8B 6W7",
    "sg:province":"QC",
    "wof:name":"Immeubles Contact",
    "wof:placetype":"venue"
},
  "geometry": {"coordinates":[-71.64948272709999,48.534702301],"type":"Point"}
}