{
  "type": "Feature",
  "properties": {
    "iso:country":"CA",
    "sg:city":"Alfred",
    "sg:classifiers":[
        {
            "category":"Food & Beverages",
            "subcategory":"Groceries & Convenience Stores",
            "type":"Retail Goods"
        }
    ],
    "sg:phone":"+1 613 679 0920",
    "sg:postcode":"K0B 1A0",
    "sg:province":"ON",
    "wof:name":"Depanneur Guillaume Rozon",
    "wof:placetype":"venue"
},
  "geometry": {"coordinates":[-74.8840255737,45.5575218201],"type":"Point"}
}