{
  "type": "Feature",
  "properties": {
    "addr:full":"25 Rue Levasseur O Alma QC G8B 2C5",
    "addr:housenumber":"25",
    "addr:postcode":"g8b 2c5",
    "addr:street":"Rue Levasseur O",
    "iso:country":"CA",
    "sg:address":"25 Rue Levasseur O",
    "sg:city":"Alma",
    "sg:classifiers":[
        {
            "category":"Health Services",
            "subcategory":"Health Practitioner",
            "type":"Services"
        }
    ],
    "sg:phone":"+1 418 668 3470",
    "sg:postcode":"G8B 2C5",
    "sg:province":"QC",
    "sg:tags":[
        "psychologist"
    ],
    "wof:name":"Bureau DE Consultation Psych",
    "wof:placetype":"venue"
},
  "geometry": {"coordinates":[-71.645905,48.541851],"type":"Point"}
}