{
  "type": "Feature",
  "properties": {
    "addr:full":"9460 Charles St Chilliwack BC V2P 5K1",
    "addr:housenumber":"9460",
    "addr:postcode":"v2p 5k1",
    "addr:street":"Charles St",
    "iso:country":"CA",
    "sg:address":"9460 Charles St",
    "sg:city":"Chilliwack",
    "sg:classifiers":[
        {
            "category":"Organizations",
            "subcategory":"Religious Organization",
            "type":"Services"
        }
    ],
    "sg:phone":"+1 604 795 3864",
    "sg:postcode":"V2P 5K1",
    "sg:province":"BC",
    "sg:tags":[
        "church"
    ],
    "wof:name":"Christ Lutheran Church",
    "wof:placetype":"venue"
},
  "geometry": {"coordinates":[-121.942466736,49.173789978],"type":"Point"}
}