{
  "type": "Feature",
  "properties": {
    "addr:full":"87 Grafton St S Macgregor MB R0H 0R0",
    "addr:housenumber":"87",
    "addr:postcode":"r0h 0r0",
    "addr:street":"Grafton St S",
    "iso:country":"CA",
    "sg:address":"87 Grafton St S",
    "sg:city":"Macgregor",
    "sg:classifiers":[
        {
            "category":"Health Services",
            "subcategory":"Hospital",
            "type":"Services"
        }
    ],
    "sg:phone":"+1 204 685 2850",
    "sg:postcode":"R0H 0R0",
    "sg:province":"MB",
    "wof:name":"Mac Gregor Health Ctr",
    "wof:placetype":"venue"
},
  "geometry": {"coordinates":[-98.779297,49.965221],"type":"Point"}
}