{
  "type": "Feature",
  "properties": {
    "addr:full":"180 Duncan Mill Rd North York ON M3B 1Z6",
    "addr:housenumber":"180",
    "addr:postcode":"m3b 1z6",
    "addr:street":"Duncan Mill Rd",
    "iso:country":"CA",
    "sg:address":"180 Duncan Mill Rd",
    "sg:city":"North York",
    "sg:classifiers":[
        {
            "category":"Restaurant",
            "type":"Food & Drink"
        }
    ],
    "sg:phone":"+1 416 443 3450",
    "sg:postcode":"M3B 1Z6",
    "sg:province":"ON",
    "sg:tags":[
        "cafe"
    ],
    "wof:name":"Delimark Cafe",
    "wof:placetype":"venue"
},
  "geometry": {"coordinates":[-79.354218,43.762131],"type":"Point"}
}