{
  "type": "Feature",
  "properties": {
    "iso:country":"CA",
    "sg:address":"185 Av Plante",
    "sg:city":"Vanier",
    "sg:classifiers":[
        {
            "category":"Bars & Pubs",
            "type":"Food & Drink"
        }
    ],
    "sg:phone":"+1 418 681 6454",
    "sg:postcode":"G1M 1S2",
    "sg:province":"QC",
    "sg:tags":[
        "lounge",
        "cocktail"
    ],
    "wof:name":"Bar LA Gamelle",
    "wof:placetype":"venue"
},
  "geometry": {"coordinates":[-71.2556686401,46.8175010681],"type":"Point"}
}