{
  "type": "Feature",
  "properties": {
    "addr:full":"2323 Oakmoor Dr SW Calgary AB T2V 4T2",
    "addr:housenumber":"2323",
    "addr:postcode":"t2v 4t2",
    "addr:street":"Oakmoor Dr Sw",
    "iso:country":"CA",
    "sg:address":"2323 Oakmoor Dr SW",
    "sg:city":"Calgary",
    "sg:classifiers":[
        {
            "category":"Insurance",
            "subcategory":"Insurance Agent",
            "type":"Services"
        }
    ],
    "sg:phone":"+1 403 560 7775",
    "sg:postcode":"T2V 4T2",
    "sg:province":"AB",
    "wof:name":"Hamlin Insurance & Financial",
    "wof:placetype":"venue"
},
  "geometry": {"coordinates":[-114.116257,50.962875],"type":"Point"}
}