{
  "type": "Feature",
  "properties": {
    "addr:full":"106 3rd Ave E Drumheller AB T0J 0Y0",
    "addr:housenumber":"106",
    "addr:postcode":"t0j 0y0",
    "addr:street":"3Rd Ave E",
    "iso:country":"CA",
    "sg:address":"106 3rd Ave E",
    "sg:city":"Drumheller",
    "sg:classifiers":[
        {
            "category":"Shopping",
            "subcategory":"Used Merchandise",
            "type":"Retail Goods"
        }
    ],
    "sg:phone":"+1 403 823 3704",
    "sg:postcode":"T0J 0Y0",
    "sg:province":"AB",
    "sg:tags":[
        "shop",
        "consignment"
    ],
    "wof:name":"Just You & I",
    "wof:placetype":"venue"
},
  "geometry": {"coordinates":[-112.706566,51.463966],"type":"Point"}
}