{
  "type": "Feature",
  "properties": {
    "addr:full":"195 Eagle Dr Winnipeg MB R2R 1V4",
    "addr:housenumber":"195",
    "addr:postcode":"r2r 1v4",
    "addr:street":"Eagle Dr",
    "iso:country":"CA",
    "sg:address":"195 Eagle Dr",
    "sg:city":"Winnipeg",
    "sg:classifiers":[
        {
            "category":"Building & Trades",
            "subcategory":"Equipment Rental",
            "type":"Services"
        }
    ],
    "sg:phone":"+1 204 788 1121",
    "sg:postcode":"R2R 1V4",
    "sg:province":"MB",
    "sg:tags":[
        "crane",
        "material",
        "handling"
    ],
    "wof:name":"Kaverit Steel & Crane",
    "wof:placetype":"venue"
},
  "geometry": {"coordinates":[-97.225601,49.93351],"type":"Point"}
}