{
  "type": "Feature",
  "properties": {
    "addr:full":"392 Broadway St W # B Yorkton SK S3N 0P1",
    "addr:housenumber":"392",
    "addr:postcode":"s3n 0p1",
    "addr:street":"Broadway St W # B",
    "iso:country":"CA",
    "sg:address":"392 Broadway St W # B",
    "sg:city":"Yorkton",
    "sg:classifiers":[
        {
            "category":"Sports & Exercise",
            "subcategory":"Golf",
            "type":"Entertainment"
        }
    ],
    "sg:phone":"+1 306 786 4653",
    "sg:postcode":"S3N 0P1",
    "sg:province":"SK",
    "sg:tags":[
        "course"
    ],
    "wof:name":"Bunkers Indoor Golf Ltd",
    "wof:placetype":"venue"
},
  "geometry": {"coordinates":[-102.48716,51.209953],"type":"Point"}
}