{
  "type": "Feature",
  "properties": {
    "addr:full":"18 Hunter St South River ON P0A 1X0",
    "addr:housenumber":"18",
    "addr:postcode":"p0a 1x0",
    "addr:street":"Hunter St",
    "iso:country":"CA",
    "sg:address":"18 Hunter St",
    "sg:city":"South River",
    "sg:classifiers":[
        {
            "category":"Retail",
            "subcategory":"Funeral Services",
            "type":"Services"
        }
    ],
    "sg:phone":"+1 705 386 2624",
    "sg:postcode":"P0A 1X0",
    "sg:province":"ON",
    "sg:tags":[
        "director"
    ],
    "wof:name":"Raney Funeral Chapel",
    "wof:placetype":"venue"
},
  "geometry": {"coordinates":[-79.377937,45.841393],"type":"Point"}
}