{
  "type": "Feature",
  "properties": {
    "iso:country":"CA",
    "sg:city":"Richmond",
    "sg:classifiers":[
        {
            "category":"Building & Trades",
            "subcategory":"Construction",
            "type":"Services"
        }
    ],
    "sg:phone":"+1 604 231 8120",
    "sg:postcode":"V6X 1T2",
    "sg:province":"BC",
    "sg:tags":[
        "resurfacing",
        "laying",
        "refinishing",
        "floor"
    ],
    "wof:name":"Rmd Hardwood Floors",
    "wof:placetype":"venue"
},
  "geometry": {"coordinates":[-123.097854614,49.191860199],"type":"Point"}
}