{
  "type": "Feature",
  "properties": {
    "addr:full":"Scarborough ON M1B 4Z9",
    "addr:postcode":"m1b 4z9",
    "iso:country":"CA",
    "sg:city":"Scarborough",
    "sg:classifiers":[
        {
            "category":"Wholesale",
            "subcategory":"Office Equipment",
            "type":"Manufacturing & Wholesale Goods"
        }
    ],
    "sg:phone":"+1 416 291 0015",
    "sg:postcode":"M1B 4Z9",
    "sg:province":"ON",
    "sg:tags":[
        "accounting",
        "bookkeeping",
        "system"
    ],
    "wof:name":"Baig Accounting & Tax Svc",
    "wof:placetype":"venue"
},
  "geometry": {"coordinates":[-79.239807,43.795971],"type":"Point"}
}