{
  "type": "Feature",
  "properties": {
    "iso:country":"CA",
    "sg:address":"4261 Highway 7 # 202",
    "sg:city":"Markham",
    "sg:classifiers":[
        {
            "category":"Insurance",
            "subcategory":"Insurance Agent",
            "type":"Services"
        }
    ],
    "sg:phone":"+1 905 474 3286",
    "sg:postcode":"L3R 9W6",
    "sg:province":"ON",
    "wof:name":"Hung, Amy",
    "wof:placetype":"venue"
},
  "geometry": {"coordinates":[-79.339943,43.856033],"type":"Point"}
}