{
  "type": "Feature",
  "properties": {
    "addr:full":"592 4E Rue Shawinigan QC G9N 1G8",
    "addr:housenumber":"592",
    "addr:postcode":"g9n 1g8",
    "addr:street":"4E Rue",
    "iso:country":"CA",
    "sg:address":"592 4E Rue",
    "sg:city":"Shawinigan",
    "sg:classifiers":[
        {
            "category":"Manufacturing",
            "subcategory":"Printing",
            "type":"Manufacturing & Wholesale Goods"
        }
    ],
    "sg:phone":"+1 819 537 0311",
    "sg:postcode":"G9N 1G8",
    "sg:province":"QC",
    "sg:tags":[
        "printer",
        "duplicating",
        "copying"
    ],
    "wof:name":"Copie Service Cd 1999 Inc",
    "wof:placetype":"venue"
},
  "geometry": {"coordinates":[-72.74917600000001,46.539928],"type":"Point"}
}