{
  "type": "Feature",
  "properties": {
    "addr:full":"1384 Barton St E Hamilton ON L8H 2W5",
    "addr:housenumber":"1384",
    "addr:postcode":"l8h 2w5",
    "addr:street":"Barton St E",
    "iso:country":"CA",
    "sg:address":"1384 Barton St E",
    "sg:city":"Hamilton",
    "sg:classifiers":[
        {
            "category":"Shopping",
            "subcategory":"Computers & Home Electronics",
            "type":"Retail Goods"
        }
    ],
    "sg:phone":"+1 905 545 8952",
    "sg:postcode":"L8H 2W5",
    "sg:province":"ON",
    "sg:tags":[
        "radio",
        "television",
        "video",
        "equipment"
    ],
    "wof:name":"Brankos Audio & Video Ltd",
    "wof:placetype":"venue"
},
  "geometry": {"coordinates":[-79.803612,43.248474],"type":"Point"}
}