{
  "type": "Feature",
  "properties": {
    "iso:country":"CA",
    "sg:address":"PO Box 120",
    "sg:city":"Turin",
    "sg:classifiers":[
        {
            "category":"Building & Trades",
            "subcategory":"Construction",
            "type":"Services"
        }
    ],
    "sg:phone":"+1 403 308 1212",
    "sg:postcode":"T0K 2H0",
    "sg:province":"AB",
    "sg:tags":[
        "excavating",
        "contractor"
    ],
    "wof:name":"Dutchie Dirt-Moving Ltd",
    "wof:placetype":"venue"
},
  "geometry": {"coordinates":[-112.520462036,49.9682388306],"type":"Point"}
}