{
  "type": "Feature",
  "properties": {
    "addr:full":"12001 Boul DE Salaberry Dollard-Des-Ormeaux QC H9B 2A7",
    "addr:housenumber":"12001",
    "addr:postcode":"h9b 2a7",
    "addr:street":"Boul De Salaberry",
    "iso:country":"CA",
    "sg:address":"12001 Boul DE Salaberry",
    "sg:city":"Dollard-Des-Ormeaux",
    "sg:classifiers":[
        {
            "category":"Shopping",
            "subcategory":"Bicycles & Sporting Goods",
            "type":"Retail Goods"
        }
    ],
    "sg:phone":"+1 514 421 1330",
    "sg:postcode":"H9B 2A7",
    "sg:province":"QC",
    "wof:name":"J R Sailesh Patel Sports",
    "wof:placetype":"venue"
},
  "geometry": {"coordinates":[-73.80956999999999,45.482807],"type":"Point"}
}