{
  "type": "Feature",
  "properties": {
    "addr:full":"241 Rue Saint-Felix Saint-Germain-DE-Grantham QC J0C 1K0",
    "addr:housenumber":"241",
    "addr:postcode":"j0c 1k0",
    "addr:street":"Rue Saint-Felix",
    "iso:country":"CA",
    "sg:address":"241 Rue Saint-Felix",
    "sg:city":"Saint-Germain-DE-Grantham",
    "sg:classifiers":[
        {
            "category":"Building & Trades",
            "subcategory":"Construction",
            "type":"Services"
        }
    ],
    "sg:phone":"+1 819 395 4033",
    "sg:postcode":"J0C 1K0",
    "sg:province":"QC",
    "sg:tags":[
        "general",
        "contractor"
    ],
    "wof:name":"Construction A Mathieu Inc",
    "wof:placetype":"venue"
},
  "geometry": {"coordinates":[-72.572693,45.836098],"type":"Point"}
}