{
  "type": "Feature",
  "properties": {
    "addr:full":"16 Grand Rd Campbellford ON K0L 1L0",
    "addr:housenumber":"16",
    "addr:postcode":"k0l 1l0",
    "addr:street":"Grand Rd",
    "iso:country":"CA",
    "sg:address":"16 Grand Rd",
    "sg:city":"Campbellford",
    "sg:classifiers":[
        {
            "category":"Shopping",
            "subcategory":"Pharmacy",
            "type":"Retail Goods"
        }
    ],
    "sg:phone":"+1 705 653 1881",
    "sg:postcode":"K0L 1L0",
    "sg:province":"ON",
    "wof:name":"Economy Fair Rexall",
    "wof:placetype":"venue"
},
  "geometry": {"coordinates":[-77.800674,44.308056],"type":"Point"}
}