{
  "type": "Feature",
  "properties": {
    "iso:country":"CA",
    "sg:address":"7238 Boul Maurice-Duplessis",
    "sg:city":"Montreal",
    "sg:classifiers":[
        {
            "category":"Recreation",
            "type":"Entertainment"
        }
    ],
    "sg:phone":"+1 514 881 1013",
    "sg:postcode":"H1E 4A7",
    "sg:province":"QC",
    "sg:tags":[
        "martial",
        "arts",
        "instruction",
        "boxing"
    ],
    "wof:name":"Club DE Defense Expert Inc",
    "wof:placetype":"venue"
},
  "geometry": {"coordinates":[-73.60218,45.623585],"type":"Point"}
}