{
  "type": "Feature",
  "properties": {
    "addr:full":"11391 West Saanich Rd North Saanich BC V8L 5L1",
    "addr:housenumber":"11391",
    "addr:postcode":"v8l 5l1",
    "addr:street":"West Saanich Rd",
    "iso:country":"CA",
    "sg:address":"11391 West Saanich Rd",
    "sg:city":"North Saanich",
    "sg:classifiers":[
        {
            "category":"Professional",
            "subcategory":"Computer Services",
            "type":"Services"
        }
    ],
    "sg:phone":"+1 250 656 1033",
    "sg:postcode":"V8L 5L1",
    "sg:province":"BC",
    "sg:tags":[
        "consultant",
        "designer"
    ],
    "wof:name":"Price Book Svc",
    "wof:placetype":"venue"
},
  "geometry": {"coordinates":[-123.45753499999999,48.691174],"type":"Point"}
}