{
  "type": "Feature",
  "properties": {
    "addr:full":"2700 College Ave Regina SK S4T 1V1",
    "addr:housenumber":"2700",
    "addr:postcode":"s4t 1v1",
    "addr:street":"College Ave",
    "iso:country":"CA",
    "sg:address":"2700 College Ave",
    "sg:city":"Regina",
    "sg:classifiers":[
        {
            "category":"Organizations",
            "subcategory":"Religious Organization",
            "type":"Services"
        }
    ],
    "sg:phone":"+1 306 522 1133",
    "sg:postcode":"S4T 1V1",
    "sg:province":"SK",
    "sg:tags":[
        "church"
    ],
    "wof:name":"First Ch of Christ Scientist",
    "wof:placetype":"venue"
},
  "geometry": {"coordinates":[-104.61979700000001,50.44091],"type":"Point"}
}