{
  "type": "Feature",
  "properties": {
    "addr:full":"862 Bathurst St Toronto ON M5R 3G3",
    "addr:housenumber":"862",
    "addr:postcode":"m5r 3g3",
    "addr:street":"Bathurst St",
    "iso:country":"CA",
    "sg:address":"862 Bathurst St",
    "sg:city":"Toronto",
    "sg:classifiers":[
        {
            "category":"Wholesale",
            "subcategory":"Machinery & Supplies",
            "type":"Manufacturing & Wholesale Goods"
        }
    ],
    "sg:phone":"+1 416 533 6033",
    "sg:postcode":"M5R 3G3",
    "sg:province":"ON",
    "sg:tags":[
        "salon",
        "beauty"
    ],
    "wof:name":"West Indian Golden Beauty Supl",
    "wof:placetype":"venue"
},
  "geometry": {"coordinates":[-79.4121017456,43.6668968201],"type":"Point"}
}