{
  "type": "Feature",
  "properties": {
    "iso:country":"CA",
    "sg:address":"1487 Rue Provancher",
    "sg:city":"Cap-Rouge",
    "sg:classifiers":[
        {
            "category":"Restaurant",
            "type":"Food & Drink"
        }
    ],
    "sg:phone":"+1 418 658 0013",
    "sg:postcode":"G1Y 1S2",
    "sg:province":"QC",
    "wof:name":"Restaurant O Tracel",
    "wof:placetype":"venue"
},
  "geometry": {"coordinates":[-71.342438,46.749771],"type":"Point"}
}