{
  "type": "Feature",
  "properties": {
    "iso:country":"CA",
    "sg:address":"706 Rue DE LA Paix",
    "sg:city":"Saint-Alphonse-Rodriguez",
    "sg:classifiers":[
        {
            "category":"Social Services",
            "type":"Services"
        }
    ],
    "sg:phone":"+1 450 883 3446",
    "sg:postcode":"J0K 1W0",
    "sg:province":"QC",
    "sg:tags":[
        "info",
        "drug",
        "abuse",
        "treatment",
        "welfare",
        "organization",
        "addiction"
    ],
    "wof:name":"Villa DE LA Paix II Enr",
    "wof:placetype":"venue"
},
  "geometry": {"coordinates":[-73.6997756958,46.1801605225],"type":"Point"}
}