{
  "type": "Feature",
  "properties": {
    "addr:full":"29 Boul Kirouac Warwick QC J0A 1M0",
    "addr:housenumber":"29",
    "addr:postcode":"j0a 1m0",
    "addr:street":"Boul Kirouac",
    "iso:country":"CA",
    "sg:address":"29 Boul Kirouac",
    "sg:city":"Warwick",
    "sg:classifiers":[
        {
            "category":"Personal",
            "subcategory":"Beauty Salon",
            "type":"Services"
        }
    ],
    "sg:phone":"+1 819 358 2977",
    "sg:postcode":"J0A 1M0",
    "sg:province":"QC",
    "wof:name":"Salon Suzie",
    "wof:placetype":"venue"
},
  "geometry": {"coordinates":[-71.99174499510001,45.9428253174],"type":"Point"}
}