{
  "type": "Feature",
  "properties": {
    "addr:full":"9 Rue Des Prairies Clermont QC G4A 1H2",
    "addr:housenumber":"9",
    "addr:postcode":"g4a 1h2",
    "addr:street":"Rue Des Prairies",
    "iso:country":"CA",
    "sg:address":"9 Rue Des Prairies",
    "sg:city":"Clermont",
    "sg:classifiers":[
        {
            "category":"Travel",
            "subcategory":"Hotels & Motels",
            "type":"Entertainment"
        }
    ],
    "sg:phone":"+1 418 439 3695",
    "sg:postcode":"G4A 1H2",
    "sg:province":"QC",
    "sg:tags":[
        "cottage",
        "cabin"
    ],
    "wof:name":"Pourvoirie Du Lac Moreau",
    "wof:placetype":"venue"
},
  "geometry": {"coordinates":[-70.226997,47.693413],"type":"Point"}
}