{
  "type": "Feature",
  "properties": {
    "addr:full":"Mississauga ON L5T 1P1",
    "addr:postcode":"l5t 1p1",
    "iso:country":"CA",
    "sg:city":"Mississauga",
    "sg:classifiers":[
        {
            "category":"Building & Trades",
            "subcategory":"Construction",
            "type":"Services"
        }
    ],
    "sg:phone":"+1 905 670 5994",
    "sg:postcode":"L5T 1P1",
    "sg:province":"ON",
    "sg:tags":[
        "general",
        "contractor"
    ],
    "wof:name":"Conin Construction CO Ltd",
    "wof:placetype":"venue"
},
  "geometry": {"coordinates":[-79.66579400000001,43.654106],"type":"Point"}
}