{
  "type": "Feature",
  "properties": {
    "addr:full":"540 Route 105 Maugerville NB E3A 8G4",
    "addr:housenumber":"540",
    "addr:postcode":"e3a 8g4",
    "addr:street":"Route 105",
    "iso:country":"CA",
    "sg:address":"540 Route 105",
    "sg:city":"Maugerville",
    "sg:classifiers":[
        {
            "category":"Retail",
            "subcategory":"Repair Shop",
            "type":"Services"
        }
    ],
    "sg:phone":"+1 506 459 4416",
    "sg:postcode":"E3A 8G4",
    "sg:province":"NB",
    "sg:tags":[
        "restoring",
        "furniture"
    ],
    "wof:name":"Trevor Smith Furniture Rstrtn",
    "wof:placetype":"venue"
},
  "geometry": {"coordinates":[-66.53613300000001,45.898785],"type":"Point"}
}