{
  "type": "Feature",
  "properties": {
    "addr:full":"2755 Dundas St W Toronto ON M6P 1Y4",
    "addr:housenumber":"2755",
    "addr:postcode":"m6p 1y4",
    "addr:street":"Dundas St W",
    "iso:country":"CA",
    "sg:address":"2755 Dundas St W",
    "sg:city":"Toronto",
    "sg:classifiers":[
        {
            "category":"Food & Beverages",
            "subcategory":"Groceries & Convenience Stores",
            "type":"Retail Goods"
        }
    ],
    "sg:phone":"+1 416 762 9469",
    "sg:postcode":"M6P 1Y4",
    "sg:province":"ON",
    "sg:tags":[
        "grocer"
    ],
    "wof:name":"Five Star Market",
    "wof:placetype":"venue"
},
  "geometry": {"coordinates":[-79.461235,43.665131],"type":"Point"}
}