{
  "type": "Feature",
  "properties": {
    "addr:full":"North Vancouver BC V7L 2N4",
    "addr:postcode":"v7l 2n4",
    "iso:country":"CA",
    "sg:city":"North Vancouver",
    "sg:classifiers":[
        {
            "category":"Health Services",
            "subcategory":"Doctor",
            "type":"Services"
        }
    ],
    "sg:phone":"+1 604 988 1914",
    "sg:postcode":"V7L 2N4",
    "sg:province":"BC",
    "sg:tags":[
        "dentist"
    ],
    "wof:name":"Cheung, Raymond DDS",
    "wof:placetype":"venue"
},
  "geometry": {"coordinates":[-123.070930481,49.3208961487],"type":"Point"}
}