{
  "type": "Feature",
  "properties": {
    "addr:full":"463 Church St Toronto ON M4Y 2C5",
    "addr:housenumber":"463",
    "addr:postcode":"m4y 2c5",
    "addr:street":"Church St",
    "iso:country":"CA",
    "sg:address":"463 Church St",
    "sg:city":"Toronto",
    "sg:classifiers":[
        {
            "category":"Restaurant",
            "type":"Food & Drink"
        }
    ],
    "sg:phone":"+1 416 922 9594",
    "sg:postcode":"M4Y 2C5",
    "sg:province":"ON",
    "wof:name":"Bigliardi's Steak Seafood",
    "wof:placetype":"venue"
},
  "geometry": {"coordinates":[-79.38014200000001,43.664299],"type":"Point"}
}