{
  "type": "Feature",
  "properties": {
    "iso:country":"CA",
    "sg:address":"5050 Rue Bannantyne",
    "sg:city":"Verdun",
    "sg:classifiers":[
        {
            "category":"Autos & Motor Vehicles",
            "subcategory":"Fuel & Gas Station",
            "type":"Retail Goods"
        }
    ],
    "sg:phone":"+1 514 761 4220",
    "sg:postcode":"H4G 1G3",
    "sg:province":"QC",
    "sg:tags":[
        "oil"
    ],
    "wof:name":"Entreprises Fernand Turpin",
    "wof:placetype":"venue"
},
  "geometry": {"coordinates":[-73.57619476319999,45.4561004639],"type":"Point"}
}