{
  "type": "Feature",
  "properties": {
    "addr:full":"2117 20th St Nanton AB T0L 1R0",
    "addr:housenumber":"2117",
    "addr:postcode":"t0l 1r0",
    "addr:street":"20Th St",
    "iso:country":"CA",
    "sg:address":"2117 20th St",
    "sg:city":"Nanton",
    "sg:classifiers":[
        {
            "category":"Shopping",
            "subcategory":"Used Merchandise",
            "type":"Retail Goods"
        }
    ],
    "sg:phone":"+1 403 646 0056",
    "sg:postcode":"T0L 1R0",
    "sg:province":"AB",
    "sg:tags":[
        "shop",
        "gift"
    ],
    "wof:name":"Edwards & CO",
    "wof:placetype":"venue"
},
  "geometry": {"coordinates":[-113.77172899999999,50.348419],"type":"Point"}
}