{
  "type": "Feature",
  "properties": {
    "addr:full":"Saint-Ferdinand QC G0N 1N0",
    "addr:postcode":"g0n 1n0",
    "iso:country":"CA",
    "sg:city":"Saint-Ferdinand",
    "sg:classifiers":[
        {
            "category":"Social Services",
            "subcategory":"Child Care",
            "type":"Services"
        }
    ],
    "sg:phone":"+1 418 428 9390",
    "sg:postcode":"G0N 1N0",
    "sg:province":"QC",
    "wof:name":"Cpe LA Marmaillerie",
    "wof:placetype":"venue"
},
  "geometry": {"coordinates":[-71.5731964111,46.1151733398],"type":"Point"}
}