{
  "type": "Feature",
  "properties": {
    "addr:full":"6600 Aut Transcanadienne Pointe-Claire QC H9R 4S2",
    "addr:postcode":"6600;h9r 4s2",
    "addr:street":"Transcanadienne",
    "iso:country":"CA",
    "sg:address":"6600 Aut Transcanadienne",
    "sg:city":"Pointe-Claire",
    "sg:classifiers":[
        {
            "category":"Real Estate",
            "subcategory":"Real Estate Operator",
            "type":"Services"
        }
    ],
    "sg:phone":"+1 514 694 1342",
    "sg:postcode":"H9R 4S2",
    "sg:province":"QC",
    "sg:tags":[
        "building",
        "parks"
    ],
    "wof:name":"Pointe Claire Commerce Ctr",
    "wof:placetype":"venue"
},
  "geometry": {"coordinates":[-73.838218689,45.4578323364],"type":"Point"}
}