{
  "type": "Feature",
  "properties": {
    "addr:full":"Morrin AB T0J 2B0",
    "addr:postcode":"t0j 2b0",
    "iso:country":"CA",
    "sg:city":"Morrin",
    "sg:classifiers":[
        {
            "category":"Retail",
            "subcategory":"Animal Services",
            "type":"Services"
        }
    ],
    "sg:phone":"+1 403 772 2207",
    "sg:postcode":"T0J 2B0",
    "sg:province":"AB",
    "sg:tags":[
        "pet",
        "boarding",
        "sitting"
    ],
    "wof:name":"Cole's Pet Resort",
    "wof:placetype":"venue"
},
  "geometry": {"coordinates":[-112.756355286,51.64894104],"type":"Point"}
}