{
  "type": "Feature",
  "properties": {
    "addr:full":"6740 Meadowvale Town Centre Ci Mississauga ON L5N 4B7",
    "addr:housenumber":"6740",
    "addr:postcode":"l5n 4b7",
    "addr:street":"Meadowvale Town Centre Ci",
    "iso:country":"CA",
    "sg:address":"6740 Meadowvale Town Centre Ci",
    "sg:city":"Mississauga",
    "sg:classifiers":[
        {
            "category":"Cinema",
            "subcategory":"Movie Rental",
            "type":"Entertainment"
        }
    ],
    "sg:phone":"+1 905 821 7620",
    "sg:postcode":"L5N 4B7",
    "sg:province":"ON",
    "sg:tags":[
        "leasing",
        "video",
        "disc",
        "tape"
    ],
    "wof:name":"Blockbuster Video",
    "wof:placetype":"venue"
},
  "geometry": {"coordinates":[-79.761612,43.583206],"type":"Point"}
}