{
  "type": "Feature",
  "properties": {
    "addr:full":"5871 Tyson Rd Chilliwack BC V2R 3R6",
    "addr:housenumber":"5871",
    "addr:postcode":"v2r 3r6",
    "addr:street":"Tyson Rd",
    "iso:country":"CA",
    "sg:address":"5871 Tyson Rd",
    "sg:city":"Chilliwack",
    "sg:classifiers":[
        {
            "category":"Education",
            "subcategory":"School",
            "type":"Public Place"
        }
    ],
    "sg:phone":"+1 604 824 7481",
    "sg:postcode":"V2R 3R6",
    "sg:province":"BC",
    "wof:name":"Mount Slesse Middle School",
    "wof:placetype":"venue"
},
  "geometry": {"coordinates":[-121.97677612299999,49.1087417603],"type":"Point"}
}