{
  "type": "Feature",
  "properties": {
    "addr:full":"Winnipeg MB R2V 3E1",
    "addr:postcode":"r2v 3e1",
    "iso:country":"CA",
    "sg:city":"Winnipeg",
    "sg:classifiers":[
        {
            "category":"Shopping",
            "subcategory":"Clothing, Apparel, & Fashions",
            "type":"Retail Goods"
        }
    ],
    "sg:phone":"+1 204 334 1169",
    "sg:postcode":"R2V 3E1",
    "sg:province":"MB",
    "wof:name":"Cotton Ginny Ltd",
    "wof:placetype":"venue"
},
  "geometry": {"coordinates":[-97.147614,49.95306],"type":"Point"}
}