{
  "type": "Feature",
  "properties": {
    "addr:full":"170 Grand Trunk Ave Dryden ON P8N 2W6",
    "addr:housenumber":"170",
    "addr:postcode":"p8n 2w6",
    "addr:street":"Grand Trunk Ave",
    "iso:country":"CA",
    "sg:address":"170 Grand Trunk Ave",
    "sg:city":"Dryden",
    "sg:classifiers":[
        {
            "category":"Retail",
            "subcategory":"Self-service Laundry",
            "type":"Services"
        }
    ],
    "sg:phone":"+1 807 223 3722",
    "sg:postcode":"P8N 2W6",
    "sg:province":"ON",
    "wof:name":"Highway Laundromat",
    "wof:placetype":"venue"
},
  "geometry": {"coordinates":[-92.8474731445,49.7900543213],"type":"Point"}
}