{
  "type": "Feature",
  "properties": {
    "addr:full":"863 Fenmar Dr North York ON M9L 1C8",
    "addr:housenumber":"863",
    "addr:postcode":"m9l 1c8",
    "addr:street":"Fenmar Dr",
    "iso:country":"CA",
    "sg:address":"863 Fenmar Dr",
    "sg:city":"North York",
    "sg:classifiers":[
        {
            "category":"Manufacturing",
            "subcategory":"Tools & Machinery",
            "type":"Manufacturing & Wholesale Goods"
        }
    ],
    "sg:phone":"+1 416 749 8225",
    "sg:postcode":"M9L 1C8",
    "sg:province":"ON",
    "sg:tags":[
        "woodworking"
    ],
    "wof:name":"Auto V Grooving Inc",
    "wof:placetype":"venue"
},
  "geometry": {"coordinates":[-79.564125,43.765667],"type":"Point"}
}