{
  "type": "Feature",
  "properties": {
    "addr:full":"505 Consumers Rd # 8 North York ON M2J 4V8",
    "addr:housenumber":"505",
    "addr:postcode":"m2j 4v8",
    "addr:street":"Consumers Rd # 8",
    "iso:country":"CA",
    "sg:address":"505 Consumers Rd # 8",
    "sg:city":"North York",
    "sg:classifiers":[
        {
            "category":"Professional",
            "subcategory":"Employment Agencies",
            "type":"Services"
        }
    ],
    "sg:phone":"+1 905 940 6789",
    "sg:postcode":"M2J 4V8",
    "sg:province":"ON",
    "sg:tags":[
        "help",
        "contractor"
    ],
    "wof:name":"Todays Staffing",
    "wof:placetype":"venue"
},
  "geometry": {"coordinates":[-79.324234,43.771141],"type":"Point"}
}