{
  "type": "Feature",
  "properties": {
    "addr:full":"1050 Islington Ave Etobicoke ON M8Z 4R6",
    "addr:housenumber":"1050",
    "addr:postcode":"m8z 4r6",
    "addr:street":"Islington Ave",
    "iso:country":"CA",
    "sg:address":"1050 Islington Ave",
    "sg:city":"Etobicoke",
    "sg:classifiers":[
        {
            "category":"Restaurant",
            "type":"Food & Drink"
        }
    ],
    "sg:phone":"+1 416 231 9632",
    "sg:postcode":"M8Z 4R6",
    "sg:province":"ON",
    "wof:name":"Kfc",
    "wof:placetype":"venue"
},
  "geometry": {"coordinates":[-79.5193557739,43.6343460083],"type":"Point"}
}