{
  "type": "Feature",
  "properties": {
    "addr:full":"218 Strand Ave Thunder Bay ON P7B 5H9",
    "addr:housenumber":"218",
    "addr:postcode":"p7b 5h9",
    "addr:street":"Strand Ave",
    "iso:country":"CA",
    "sg:address":"218 Strand Ave",
    "sg:city":"Thunder Bay",
    "sg:classifiers":[
        {
            "category":"Professional",
            "subcategory":"Accounting & Tax Preparation",
            "type":"Services"
        }
    ],
    "sg:phone":"+1 807 767 0686",
    "sg:postcode":"P7B 5H9",
    "sg:province":"ON",
    "sg:tags":[
        "return",
        "filing"
    ],
    "wof:name":"Office Assistant",
    "wof:placetype":"venue"
},
  "geometry": {"coordinates":[-89.256317,48.450516],"type":"Point"}
}