{
  "type": "Feature",
  "properties": {
    "iso:country":"CA",
    "sg:address":"11 Rue O'Reilly",
    "sg:city":"Verdun",
    "sg:classifiers":[
        {
            "category":"Professional",
            "subcategory":"Management & Consulting",
            "type":"Services"
        }
    ],
    "sg:phone":"+1 514 768 8111",
    "sg:postcode":"H3E 1T6",
    "sg:province":"QC",
    "sg:tags":[
        "consultant",
        "business"
    ],
    "wof:name":"Matte Bourbonnais & Assoc",
    "wof:placetype":"venue"
},
  "geometry": {"coordinates":[-73.5407791138,45.4624099731],"type":"Point"}
}