{
  "type": "Feature",
  "properties": {
    "addr:full":"33 Station St Bancroft ON K0L 1C0",
    "addr:housenumber":"33",
    "addr:postcode":"k0l 1c0",
    "addr:street":"Station St",
    "iso:country":"CA",
    "sg:address":"33 Station St",
    "sg:city":"Bancroft",
    "sg:classifiers":[
        {
            "category":"Food & Beverages",
            "subcategory":"Groceries & Convenience Stores",
            "type":"Retail Goods"
        }
    ],
    "sg:phone":"+1 613 332 4334",
    "sg:postcode":"K0L 1C0",
    "sg:province":"ON",
    "sg:tags":[
        "product"
    ],
    "wof:name":"Harvest Moon Whole Foods",
    "wof:placetype":"venue"
},
  "geometry": {"coordinates":[-77.8589859009,45.0586624146],"type":"Point"}
}