{
  "type": "Feature",
  "properties": {
    "addr:full":"457 Rue Winchester Granby QC J2G 6Y8",
    "addr:housenumber":"457",
    "addr:postcode":"j2g 6y8",
    "addr:street":"Rue Winchester",
    "iso:country":"CA",
    "sg:address":"457 Rue Winchester",
    "sg:city":"Granby",
    "sg:classifiers":[
        {
            "category":"Shopping",
            "subcategory":"Computers & Home Electronics",
            "type":"Retail Goods"
        }
    ],
    "sg:phone":"+1 450 378 7273",
    "sg:postcode":"J2G 6Y8",
    "sg:province":"QC",
    "sg:tags":[
        "television",
        "radio"
    ],
    "wof:name":"Paul Lamothe Cine-Tv Enr",
    "wof:placetype":"venue"
},
  "geometry": {"coordinates":[-72.734505,45.386082],"type":"Point"}
}