{
  "type": "Feature",
  "properties": {
    "addr:full":"Hannon ON L0R 1P0",
    "addr:postcode":"l0r 1p0",
    "iso:country":"CA",
    "sg:city":"Hannon",
    "sg:classifiers":[
        {
            "category":"Building & Trades",
            "subcategory":"Construction",
            "type":"Services"
        }
    ],
    "sg:phone":"+1 905 389 6000",
    "sg:postcode":"L0R 1P0",
    "sg:province":"ON",
    "sg:tags":[
        "roofing",
        "contractor"
    ],
    "wof:name":"C M Whiteside Roofing Svc",
    "wof:placetype":"venue"
},
  "geometry": {"coordinates":[-79.8377,43.198528],"type":"Point"}
}