{
  "type": "Feature",
  "properties": {
    "addr:full":"23063 125A Ave Maple Ridge BC V2X 0S2",
    "addr:housenumber":"23063",
    "addr:postcode":"v2x 0s2",
    "addr:street":"125A Ave",
    "iso:country":"CA",
    "sg:address":"23063 125A Ave",
    "sg:city":"Maple Ridge",
    "sg:classifiers":[
        {
            "category":"Building & Trades",
            "subcategory":"Construction",
            "type":"Services"
        }
    ],
    "sg:phone":"+1 604 463 7344",
    "sg:postcode":"V2X 0S2",
    "sg:province":"BC",
    "sg:tags":[
        "repairing",
        "siding",
        "remodeling",
        "contractor"
    ],
    "wof:name":"Brooks Vinyl CO Ltd",
    "wof:placetype":"venue"
},
  "geometry": {"coordinates":[-122.605827331,49.2168464661],"type":"Point"}
}