{
  "type": "Feature",
  "properties": {
    "addr:full":"2529 Shaughnessy St Port Coquitlam BC V3C 3G1",
    "addr:postcode":"2529;v3c 3g1",
    "addr:street":"Shaughnessy St",
    "iso:country":"CA",
    "sg:address":"2529 Shaughnessy St",
    "sg:city":"Port Coquitlam",
    "sg:classifiers":[
        {
            "category":"Shopping",
            "subcategory":"Pharmacy",
            "type":"Retail Goods"
        }
    ],
    "sg:phone":"+1 604 941 2413",
    "sg:postcode":"V3C 3G1",
    "sg:province":"BC",
    "wof:name":"Peoples Drug Mart",
    "wof:placetype":"venue"
},
  "geometry": {"coordinates":[-122.78263092,49.2614974976],"type":"Point"}
}