{
  "type": "Feature",
  "properties": {
    "addr:full":"1321 Commercial Dr Vancouver BC V5L 3X5",
    "addr:housenumber":"1321",
    "addr:postcode":"v5l 3x5",
    "addr:street":"Commercial Dr",
    "iso:country":"CA",
    "sg:address":"1321 Commercial Dr",
    "sg:city":"Vancouver",
    "sg:classifiers":[
        {
            "category":"Restaurant",
            "type":"Food & Drink"
        }
    ],
    "sg:phone":"+1 604 254 2641",
    "sg:postcode":"V5L 3X5",
    "sg:province":"BC",
    "sg:tags":[
        "shop",
        "coffee"
    ],
    "wof:name":"Abruzzo Cappuccino Bar",
    "wof:placetype":"venue"
},
  "geometry": {"coordinates":[-123.069839,49.272766],"type":"Point"}
}