{
  "type": "Feature",
  "properties": {
    "iso:country":"CA",
    "sg:address":"2233 Hurontario St # 2233",
    "sg:city":"Mississauga",
    "sg:classifiers":[
        {
            "category":"Real Estate",
            "subcategory":"Real Estate Operator",
            "type":"Services"
        }
    ],
    "sg:phone":"+1 905 848 0002",
    "sg:postcode":"L5A 2E9",
    "sg:province":"ON",
    "sg:tags":[
        "apartment"
    ],
    "wof:name":"Promenade Court Apartments",
    "wof:placetype":"venue"
},
  "geometry": {"coordinates":[-79.605225,43.572643],"type":"Point"}
}