{
  "type": "Feature",
  "properties": {
    "addr:full":"Mississauga ON L5K 2L8",
    "addr:postcode":"l5k 2l8",
    "iso:country":"CA",
    "sg:city":"Mississauga",
    "sg:classifiers":[
        {
            "category":"Recreation",
            "type":"Entertainment"
        }
    ],
    "sg:phone":"+1 905 828 6149",
    "sg:postcode":"L5K 2L8",
    "sg:province":"ON",
    "sg:tags":[
        "parlor",
        "billiard"
    ],
    "wof:name":"Classic Q Billiards",
    "wof:placetype":"venue"
},
  "geometry": {"coordinates":[-79.67190600000001,43.531918],"type":"Point"}
}