{
  "type": "Feature",
  "properties": {
    "addr:full":"376 Sackville Dr Lower Sackville NS B4C 2R8",
    "addr:housenumber":"376",
    "addr:postcode":"b4c 2r8",
    "addr:street":"Sackville Dr",
    "iso:country":"CA",
    "sg:address":"376 Sackville Dr",
    "sg:city":"Lower Sackville",
    "sg:classifiers":[
        {
            "category":"Professional",
            "subcategory":"Business Services",
            "type":"Services"
        }
    ],
    "sg:phone":"+1 902 865 8650",
    "sg:postcode":"B4C 2R8",
    "sg:province":"NS",
    "sg:tags":[
        "auctioneer"
    ],
    "wof:name":"Auction City Inc",
    "wof:placetype":"venue"
},
  "geometry": {"coordinates":[-63.675579,44.76355],"type":"Point"}
}