{
  "type": "Feature",
  "properties": {
    "addr:full":"16 Balsam Ave Bragg Creek AB T0L 0K0",
    "addr:housenumber":"16",
    "addr:postcode":"t0l 0k0",
    "addr:street":"Balsam Ave",
    "iso:country":"CA",
    "sg:address":"16 Balsam Ave",
    "sg:city":"Bragg Creek",
    "sg:classifiers":[
        {
            "category":"Retail",
            "subcategory":"Veterinary Services",
            "type":"Services"
        }
    ],
    "sg:phone":"+1 403 949 2650",
    "sg:postcode":"T0L 0K0",
    "sg:province":"AB",
    "sg:tags":[
        "veterinarian"
    ],
    "wof:name":"Bragg Creek Animal Hospital",
    "wof:placetype":"venue"
},
  "geometry": {"coordinates":[-114.56089799999999,50.952564],"type":"Point"}
}