{
  "type": "Feature",
  "properties": {
    "addr:full":"353 Kelsey Blvd Churchill MB R0B 0E0",
    "addr:housenumber":"353",
    "addr:postcode":"r0b 0e0",
    "addr:street":"Kelsey Blvd",
    "iso:country":"CA",
    "sg:address":"353 Kelsey Blvd",
    "sg:city":"Churchill",
    "sg:classifiers":[
        {
            "category":"Building & Trades",
            "subcategory":"Construction",
            "type":"Services"
        }
    ],
    "sg:phone":"+1 204 675 2006",
    "sg:postcode":"R0B 0E0",
    "sg:province":"MB",
    "sg:tags":[
        "layer",
        "carpet"
    ],
    "wof:name":"Tamarack Flooring",
    "wof:placetype":"venue"
},
  "geometry": {"coordinates":[-94.167953,58.769119],"type":"Point"}
}