{
  "type": "Feature",
  "properties": {
    "addr:full":"327 Elm St Sudbury ON P3C 1V7",
    "addr:housenumber":"327",
    "addr:postcode":"p3c 1v7",
    "addr:street":"Elm St",
    "iso:country":"CA",
    "sg:address":"327 Elm St",
    "sg:city":"Sudbury",
    "sg:classifiers":[
        {
            "category":"Education",
            "subcategory":"Dance Studio",
            "type":"Public Place"
        }
    ],
    "sg:phone":"+1 705 673 1184",
    "sg:postcode":"P3C 1V7",
    "sg:province":"ON",
    "sg:tags":[
        "instruction",
        "dancing"
    ],
    "wof:name":"Gauvreau School",
    "wof:placetype":"venue"
},
  "geometry": {"coordinates":[-81.007378,46.493004],"type":"Point"}
}