{
  "type": "Feature",
  "properties": {
    "addr:full":"41 Main St N Hagersville ON N0A 1H0",
    "addr:housenumber":"41",
    "addr:postcode":"n0a 1h0",
    "addr:street":"Main St N",
    "iso:country":"CA",
    "sg:address":"41 Main St N",
    "sg:city":"Hagersville",
    "sg:classifiers":[
        {
            "category":"Organizations",
            "subcategory":"Religious Organization",
            "type":"Services"
        }
    ],
    "sg:phone":"+1 519 768 3056",
    "sg:postcode":"N0A 1H0",
    "sg:province":"ON",
    "sg:tags":[
        "church"
    ],
    "wof:name":"Rural Life Mission",
    "wof:placetype":"venue"
},
  "geometry": {"coordinates":[-80.05059799999999,42.96349],"type":"Point"}
}