{
  "type": "Feature",
  "properties": {
    "addr:full":"191 John St Barrie ON L4N 2L4",
    "addr:housenumber":"191",
    "addr:postcode":"l4n 2l4",
    "addr:street":"John St",
    "iso:country":"CA",
    "sg:address":"191 John St",
    "sg:city":"Barrie",
    "sg:classifiers":[
        {
            "category":"Professional",
            "subcategory":"Advertising",
            "type":"Services"
        }
    ],
    "sg:phone":"+1 705 722 3092",
    "sg:postcode":"L4N 2L4",
    "sg:province":"ON",
    "sg:tags":[
        "designer",
        "display",
        "producer"
    ],
    "wof:name":"Moore Display & Design",
    "wof:placetype":"venue"
},
  "geometry": {"coordinates":[-79.70515441889999,44.3757705688],"type":"Point"}
}