{
  "type": "Feature",
  "properties": {
    "iso:country":"CA",
    "sg:address":"8833 County Rd 45",
    "sg:city":"Roseneath",
    "sg:classifiers":[
        {
            "category":"Shopping",
            "subcategory":"Discount & Variety Stores",
            "type":"Retail Goods"
        }
    ],
    "sg:phone":"+1 905 352 2751",
    "sg:postcode":"K0K 2X0",
    "sg:province":"ON",
    "sg:tags":[
        "merchandise",
        "general"
    ],
    "wof:name":"Lloyd's General Store",
    "wof:placetype":"venue"
},
  "geometry": {"coordinates":[-78.0572357178,44.1935386658],"type":"Point"}
}