{
  "type": "Feature",
  "properties": {
    "addr:full":"2175 Whitfield Rd Port Perry ON L9L 1B2",
    "addr:housenumber":"2175",
    "addr:postcode":"l9l 1b2",
    "addr:street":"Whitfield Rd",
    "iso:country":"CA",
    "sg:address":"2175 Whitfield Rd",
    "sg:city":"Port Perry",
    "sg:classifiers":[
        {
            "category":"Recreation",
            "subcategory":"Marina",
            "type":"Entertainment"
        }
    ],
    "sg:phone":"+1 905 985 2658",
    "sg:postcode":"L9L 1B2",
    "sg:province":"ON",
    "wof:name":"West Shore Marine",
    "wof:placetype":"venue"
},
  "geometry": {"coordinates":[-78.937355,44.142277],"type":"Point"}
}