{
  "type": "Feature",
  "properties": {
    "iso:country":"CA",
    "sg:address":"100 Rte Rousseau",
    "sg:city":"Montauban",
    "sg:classifiers":[
        {
            "category":"Bars & Pubs",
            "type":"Food & Drink"
        }
    ],
    "sg:phone":"+1 418 336 2008",
    "sg:postcode":"G0X 1W0",
    "sg:province":"QC",
    "sg:tags":[
        "lounge",
        "cocktail"
    ],
    "wof:name":"Bar Du Cinq Dollars Enr",
    "wof:placetype":"venue"
},
  "geometry": {"coordinates":[-72.30912780760001,46.8770103455],"type":"Point"}
}