{
  "type": "Feature",
  "properties": {
    "addr:full":"201 Francis St Viscount SK S0K 4M0",
    "addr:housenumber":"201",
    "addr:postcode":"s0k 4m0",
    "addr:street":"Francis St",
    "iso:country":"CA",
    "sg:address":"201 Francis St",
    "sg:city":"Viscount",
    "sg:classifiers":[
        {
            "category":"Education",
            "subcategory":"School",
            "type":"Public Place"
        }
    ],
    "sg:phone":"+1 306 944 2064",
    "sg:postcode":"S0K 4M0",
    "sg:province":"SK",
    "wof:name":"St Alphonse School",
    "wof:placetype":"venue"
},
  "geometry": {"coordinates":[-105.640693665,51.9491539001],"type":"Point"}
}