{
  "type": "Feature",
  "properties": {
    "addr:full":"615 Mount Paul Way Kamloops BC V2H 1A9",
    "addr:housenumber":"615",
    "addr:postcode":"bc v2h 1a9",
    "addr:street":"Mount Paul Way",
    "iso:country":"CA",
    "sg:address":"615 Mount Paul Way",
    "sg:city":"Kamloops",
    "sg:classifiers":[
        {
            "category":"Sports & Exercise",
            "subcategory":"Golf",
            "type":"Entertainment"
        }
    ],
    "sg:phone":"+1 250 374 4653",
    "sg:postcode":"V2H 1A9",
    "sg:province":"BC",
    "sg:tags":[
        "course"
    ],
    "wof:name":"MT Paul Golf Course & Driving",
    "wof:placetype":"venue"
},
  "geometry": {"coordinates":[-120.321968079,50.6881141663],"type":"Point"}
}