{
  "type": "Feature",
  "properties": {
    "addr:full":"17100 Boul Hymus Kirkland QC H9J 2W2",
    "addr:housenumber":"17100",
    "addr:postcode":"h9j 2w2",
    "addr:street":"Boul Hymus",
    "iso:country":"CA",
    "sg:address":"17100 Boul Hymus",
    "sg:city":"Kirkland",
    "sg:classifiers":[
        {
            "category":"Government",
            "subcategory":"Office",
            "type":"Public Place"
        }
    ],
    "sg:phone":"+1 514 630 2726",
    "sg:postcode":"H9J 2W2",
    "sg:province":"QC",
    "sg:tags":[
        "village"
    ],
    "wof:name":"Kirkland Bibliotheque",
    "wof:placetype":"venue"
},
  "geometry": {"coordinates":[-73.856987,45.448738],"type":"Point"}
}