{
  "type": "Feature",
  "properties": {
    "addr:full":"4131 Rue Sherbrooke O Westmount QC H3Z 1B7",
    "addr:housenumber":"4131",
    "addr:postcode":"h3z 1b7",
    "addr:street":"Rue Sherbrooke O",
    "iso:country":"CA",
    "sg:address":"4131 Rue Sherbrooke O",
    "sg:city":"Westmount",
    "sg:classifiers":[
        {
            "category":"Health Services",
            "subcategory":"Doctor",
            "type":"Services"
        }
    ],
    "sg:phone":"+1 514 933 2353",
    "sg:postcode":"H3Z 1B7",
    "sg:province":"QC",
    "sg:tags":[
        "physician",
        "surgeon"
    ],
    "wof:name":"Papa-Swift",
    "wof:placetype":"venue"
},
  "geometry": {"coordinates":[-73.5911941528,45.4884757996],"type":"Point"}
}