{
  "type": "Feature",
  "properties": {
    "addr:full":"19 King St St Catharines ON L2R 3H1",
    "addr:housenumber":"19",
    "addr:postcode":"l2r 3h1",
    "addr:street":"King St",
    "iso:country":"CA",
    "sg:address":"19 King St",
    "sg:city":"St Catharines",
    "sg:classifiers":[
        {
            "category":"Restaurant",
            "type":"Food & Drink"
        }
    ],
    "sg:phone":"+1 905 984 5872",
    "sg:postcode":"L2R 3H1",
    "sg:province":"ON",
    "sg:tags":[
        "cafe"
    ],
    "wof:name":"Strega",
    "wof:placetype":"venue"
},
  "geometry": {"coordinates":[-79.2475814819,43.1571350098],"type":"Point"}
}