{
  "type": "Feature",
  "properties": {
    "addr:full":"5029 50 Ave Lacombe AB T4L 1K4",
    "addr:housenumber":"5029",
    "addr:postcode":"t4l 1k4",
    "addr:street":"50 Ave",
    "iso:country":"CA",
    "sg:address":"5029 50 Ave",
    "sg:city":"Lacombe",
    "sg:classifiers":[
        {
            "category":"Personal",
            "subcategory":"Beauty Salon",
            "type":"Services"
        }
    ],
    "sg:phone":"+1 403 782 5800",
    "sg:postcode":"T4L 1K4",
    "sg:province":"AB",
    "wof:name":"Head Hunters",
    "wof:placetype":"venue"
},
  "geometry": {"coordinates":[-113.731583,52.463036],"type":"Point"}
}