{
  "type": "Feature",
  "properties": {
    "addr:full":"10888 Rue Berri Montreal QC H3L 2H5",
    "addr:housenumber":"10888",
    "addr:postcode":"h3l 2h5",
    "addr:street":"Rue Berri",
    "iso:country":"CA",
    "sg:address":"10888 Rue Berri",
    "sg:city":"Montreal",
    "sg:classifiers":[
        {
            "category":"Social Services",
            "type":"Services"
        }
    ],
    "sg:phone":"+1 514 382 9182",
    "sg:postcode":"H3L 2H5",
    "sg:province":"QC",
    "sg:tags":[
        "organization",
        "welfare"
    ],
    "wof:name":"Semaine Quebecoise Des Famille",
    "wof:placetype":"venue"
},
  "geometry": {"coordinates":[-73.671272,45.555103],"type":"Point"}
}