{
  "type": "Feature",
  "properties": {
    "iso:country":"CA",
    "sg:address":"300 Esna Park Dr",
    "sg:city":"Markham",
    "sg:classifiers":[
        {
            "category":"Professional",
            "type":"Services"
        }
    ],
    "sg:phone":"+1 905 415 8144",
    "sg:postcode":"L3R 1H3",
    "sg:province":"ON",
    "sg:tags":[
        "establishment",
        "telephone",
        "cellular"
    ],
    "wof:name":"Nectiv.net",
    "wof:placetype":"venue"
},
  "geometry": {"coordinates":[-79.33657073969999,43.8239517212],"type":"Point"}
}