{
  "type": "Feature",
  "properties": {
    "iso:country":"CA",
    "sg:address":"1993 Rue Michelin",
    "sg:city":"Laval",
    "sg:classifiers":[
        {
            "category":"Wholesale",
            "subcategory":"Durable Goods & Equipment",
            "type":"Manufacturing & Wholesale Goods"
        }
    ],
    "sg:phone":"+1 450 681 5779",
    "sg:postcode":"H7L 5B7",
    "sg:province":"QC",
    "sg:tags":[
        "importer"
    ],
    "wof:name":"Importations Euromode Inc",
    "wof:placetype":"venue"
},
  "geometry": {"coordinates":[-73.755264,45.585815],"type":"Point"}
}