{
  "type": "Feature",
  "properties": {
    "addr:full":"373 Av DE LA Cathedrale Rimouski QC G5L 5K8",
    "addr:postcode":"g5l 5k8",
    "addr:street":"373 Av De La Cathedrale",
    "iso:country":"CA",
    "sg:address":"373 Av DE LA Cathedrale",
    "sg:city":"Rimouski",
    "sg:classifiers":[
        {
            "category":"Organizations",
            "subcategory":"Religious Organization",
            "type":"Services"
        }
    ],
    "sg:phone":"+1 418 723 6951",
    "sg:postcode":"G5L 5K8",
    "sg:province":"QC",
    "sg:tags":[
        "church"
    ],
    "wof:name":"Presbytere St-Pie-X",
    "wof:placetype":"venue"
},
  "geometry": {"coordinates":[-68.51610599999999,48.443745],"type":"Point"}
}