{
  "type": "Feature",
  "properties": {
    "addr:full":"174 Rue Saint-Etienne LA Malbaie QC G5A 1T2",
    "addr:housenumber":"174",
    "addr:postcode":"g5a 1t2",
    "addr:street":"Rue Saint-Etienne",
    "iso:country":"CA",
    "sg:address":"174 Rue Saint-Etienne",
    "sg:city":"LA Malbaie",
    "sg:classifiers":[
        {
            "category":"Shopping",
            "subcategory":"Clothing, Apparel, & Fashions",
            "type":"Retail Goods"
        }
    ],
    "sg:phone":"+1 418 665 7639",
    "sg:postcode":"G5A 1T2",
    "sg:province":"QC",
    "sg:tags":[
        "boutique"
    ],
    "wof:name":"Boutik Ariel Enr",
    "wof:placetype":"venue"
},
  "geometry": {"coordinates":[-70.1543273926,47.6576576233],"type":"Point"}
}