{
  "type": "Feature",
  "properties": {
    "addr:full":"1012 Glenlea Rd Glenlea MB R0G 0S0",
    "addr:housenumber":"1012",
    "addr:postcode":"r0g 0s0",
    "addr:street":"Glenlea Rd",
    "iso:country":"CA",
    "sg:address":"1012 Glenlea Rd",
    "sg:city":"Glenlea",
    "sg:classifiers":[
        {
            "category":"Organizations",
            "subcategory":"Religious Organization",
            "type":"Services"
        }
    ],
    "sg:phone":"+1 204 883 2471",
    "sg:postcode":"R0G 0S0",
    "sg:province":"MB",
    "sg:tags":[
        "church"
    ],
    "wof:name":"Glenlea Mennonite Church",
    "wof:placetype":"venue"
},
  "geometry": {"coordinates":[-97.133247,49.641773],"type":"Point"}
}