{
  "type": "Feature",
  "properties": {
    "addr:full":"84 Conner Rd Sault Ste Marie ON P6A 6J8",
    "addr:housenumber":"84",
    "addr:postcode":"p6a 6j8",
    "addr:street":"Conner Rd",
    "iso:country":"CA",
    "sg:address":"84 Conner Rd",
    "sg:city":"Sault Ste Marie",
    "sg:classifiers":[
        {
            "category":"Retail",
            "subcategory":"Repair Shop",
            "type":"Services"
        }
    ],
    "sg:phone":"+1 705 949 9297",
    "sg:postcode":"P6A 6J8",
    "sg:province":"ON",
    "sg:tags":[
        "upholsterer"
    ],
    "wof:name":"Arts Upholstering",
    "wof:placetype":"venue"
},
  "geometry": {"coordinates":[-84.275589,46.595337],"type":"Point"}
}