{
  "type": "Feature",
  "properties": {
    "addr:full":"1801 Eglinton Ave W York ON M6E 2H8",
    "addr:housenumber":"1801",
    "addr:postcode":"m6e 2h8",
    "addr:street":"Eglinton Ave W",
    "iso:country":"CA",
    "sg:address":"1801 Eglinton Ave W",
    "sg:city":"York",
    "sg:classifiers":[
        {
            "category":"Shopping",
            "subcategory":"Pharmacy",
            "type":"Retail Goods"
        }
    ],
    "sg:phone":"+1 416 789 1859",
    "sg:postcode":"M6E 2H8",
    "sg:province":"ON",
    "wof:name":"Ayda Pharmacy Inc",
    "wof:placetype":"venue"
},
  "geometry": {"coordinates":[-79.449265,43.695759],"type":"Point"}
}