{
  "type": "Feature",
  "properties": {
    "addr:full":"30 Faulkner St Dartmouth NS B3A 3A5",
    "addr:housenumber":"30",
    "addr:postcode":"b3a 3a5",
    "addr:street":"Faulkner St",
    "iso:country":"CA",
    "sg:address":"30 Faulkner St",
    "sg:city":"Dartmouth",
    "sg:classifiers":[
        {
            "category":"Food & Beverages",
            "subcategory":"Liquor & Beverages",
            "type":"Retail Goods"
        }
    ],
    "sg:phone":"+1 902 466 2240",
    "sg:postcode":"B3A 3A5",
    "sg:province":"NS",
    "sg:tags":[
        "store"
    ],
    "wof:name":"Nova Scotia Liquor Store",
    "wof:placetype":"venue"
},
  "geometry": {"coordinates":[-63.579410553,44.6699981689],"type":"Point"}
}