{
  "type": "Feature",
  "properties": {
    "iso:country":"CA",
    "sg:address":"365 Rue Compton E",
    "sg:city":"Waterville",
    "sg:classifiers":[
        {
            "category":"Education",
            "subcategory":"College",
            "type":"Public Place"
        }
    ],
    "sg:phone":"+1 819 837 2433",
    "sg:postcode":"J0B 3H0",
    "sg:province":"QC",
    "sg:tags":[
        "academic",
        "school"
    ],
    "wof:name":"College Francois Delaplace",
    "wof:placetype":"venue"
},
  "geometry": {"coordinates":[-71.88679504389999,45.2763519287],"type":"Point"}
}