{
  "type": "Feature",
  "properties": {
    "addr:full":"80 Boul DE LA Seigneurie O Blainville QC J7C 5M3",
    "addr:housenumber":"80",
    "addr:postcode":"j7c 5m3",
    "addr:street":"Boul De La Seigneurie O",
    "iso:country":"CA",
    "sg:address":"80 Boul DE LA Seigneurie O",
    "sg:city":"Blainville",
    "sg:classifiers":[
        {
            "category":"Restaurant",
            "type":"Food & Drink"
        }
    ],
    "sg:phone":"+1 450 979 7766",
    "sg:postcode":"J7C 5M3",
    "sg:province":"QC",
    "wof:name":"Subway Sandwiches & Salads",
    "wof:placetype":"venue"
},
  "geometry": {"coordinates":[-73.8613128662,45.674118042],"type":"Point"}
}