{
  "type": "Feature",
  "properties": {
    "addr:full":"Edmonton AB T6E 4Z8",
    "addr:postcode":"t6e 4z8",
    "iso:country":"CA",
    "sg:city":"Edmonton",
    "sg:classifiers":[
        {
            "category":"Shopping",
            "subcategory":"Used Merchandise",
            "type":"Retail Goods"
        }
    ],
    "sg:phone":"+1 780 433 0398",
    "sg:postcode":"T6E 4Z8",
    "sg:province":"AB",
    "sg:tags":[
        "antique"
    ],
    "wof:name":"Strathcona Antique Mall",
    "wof:placetype":"venue"
},
  "geometry": {"coordinates":[-113.494796753,53.5126533508],"type":"Point"}
}