{
  "type": "Feature",
  "properties": {
    "iso:country":"CA",
    "sg:address":"795 Ryan Rd",
    "sg:city":"Courtenay",
    "sg:classifiers":[
        {
            "category":"Shopping",
            "subcategory":"Shoes",
            "type":"Retail Goods"
        }
    ],
    "sg:phone":"+1 250 703 0077",
    "sg:postcode":"V9N 3R6",
    "sg:province":"BC",
    "wof:name":"Shoe Warehouse",
    "wof:placetype":"venue"
},
  "geometry": {"coordinates":[-124.987388611,49.6986656189],"type":"Point"}
}