{
  "type": "Feature",
  "properties": {
    "addr:full":"8662 Commerce Crt Burnaby BC V5A 4N7",
    "addr:housenumber":"8662",
    "addr:postcode":"v5a 4n7",
    "addr:street":"Commerce Crt",
    "iso:country":"CA",
    "sg:address":"8662 Commerce Crt",
    "sg:city":"Burnaby",
    "sg:classifiers":[
        {
            "category":"Restaurant",
            "type":"Food & Drink"
        }
    ],
    "sg:phone":"+1 604 421 0407",
    "sg:postcode":"V5A 4N7",
    "sg:province":"BC",
    "wof:name":"Sandwich Tree",
    "wof:placetype":"venue"
},
  "geometry": {"coordinates":[-122.915786743,49.254322052],"type":"Point"}
}