{
  "type": "Feature",
  "properties": {
    "addr:full":"34 Ch Cornwall Shediac NB E4P 1P1",
    "addr:housenumber":"34",
    "addr:postcode":"e4p 1p1",
    "addr:street":"Ch Cornwall",
    "iso:country":"CA",
    "sg:address":"34 Ch Cornwall",
    "sg:city":"Shediac",
    "sg:classifiers":[
        {
            "category":"Building & Trades",
            "subcategory":"Construction",
            "type":"Services"
        }
    ],
    "sg:phone":"+1 506 532 5924",
    "sg:postcode":"E4P 1P1",
    "sg:province":"NB",
    "sg:tags":[
        "masonry",
        "contractor"
    ],
    "wof:name":"Westmorland Masonry Ltd",
    "wof:placetype":"venue"
},
  "geometry": {"coordinates":[-64.56461334230001,46.2158813477],"type":"Point"}
}