{
  "type": "Feature",
  "properties": {
    "addr:full":"922 North Park Dr Brampton ON L6S 3Y5",
    "addr:housenumber":"922",
    "addr:postcode":"l6s 3y5",
    "addr:street":"North Park Dr",
    "iso:country":"CA",
    "sg:address":"922 North Park Dr",
    "sg:city":"Brampton",
    "sg:classifiers":[
        {
            "category":"Recreation",
            "type":"Entertainment"
        }
    ],
    "sg:phone":"+1 905 791 4811",
    "sg:postcode":"L6S 3Y5",
    "sg:province":"ON",
    "sg:tags":[
        "center"
    ],
    "wof:name":"Ellen Mitchell Recreation Ctr",
    "wof:placetype":"venue"
},
  "geometry": {"coordinates":[-79.743492,43.73386],"type":"Point"}
}