{
  "type": "Feature",
  "properties": {
    "iso:country":"CA",
    "sg:address":"235 Guelph St",
    "sg:city":"Georgetown",
    "sg:classifiers":[
        {
            "category":"Cinema",
            "subcategory":"Movie Theater",
            "type":"Entertainment"
        }
    ],
    "sg:phone":"+1 905 873 1999",
    "sg:postcode":"L7G 4A8",
    "sg:province":"ON",
    "wof:name":"Georgetown Cinemas",
    "wof:placetype":"venue"
},
  "geometry": {"coordinates":[-79.894905,43.649872],"type":"Point"}
}