{
  "type": "Feature",
  "properties": {
    "addr:full":"4 Rue Alie Hull QC J8Z 1M8",
    "addr:housenumber":"4",
    "addr:postcode":"j8z 1m8",
    "addr:street":"Rue Alie",
    "iso:country":"CA",
    "sg:address":"4 Rue Alie",
    "sg:city":"Hull",
    "sg:classifiers":[
        {
            "category":"Health Services",
            "subcategory":"Doctor",
            "type":"Services"
        }
    ],
    "sg:phone":"+1 819 770 1787",
    "sg:postcode":"J8Z 1M8",
    "sg:province":"QC",
    "sg:tags":[
        "dentist"
    ],
    "wof:name":"Clinique Dentaire",
    "wof:placetype":"venue"
},
  "geometry": {"coordinates":[-75.760796,45.46349],"type":"Point"}
}