{
  "type": "Feature",
  "properties": {
    "addr:full":"1 Banting Pl St. John's NL A1E 2C4",
    "addr:housenumber":"1",
    "addr:postcode":"a1e 2c4",
    "addr:street":"Banting Pl",
    "iso:country":"CA",
    "sg:address":"1 Banting Pl",
    "sg:city":"St. John's",
    "sg:classifiers":[
        {
            "category":"Personal",
            "type":"Services"
        }
    ],
    "sg:phone":"+1 709 747 7766",
    "sg:postcode":"A1E 2C4",
    "sg:province":"NL",
    "sg:tags":[
        "therapist",
        "massage"
    ],
    "wof:name":"Pro Motion Therapeutic Massage",
    "wof:placetype":"venue"
},
  "geometry": {"coordinates":[-52.7550125122,47.5308609009],"type":"Point"}
}