{
  "type": "Feature",
  "properties": {
    "addr:full":"2105 Rue Coulombe Dolbeau-Mistassini QC G8L 3L6",
    "addr:housenumber":"2105",
    "addr:postcode":"g8l 3l6",
    "addr:street":"Rue Coulombe",
    "iso:country":"CA",
    "sg:address":"2105 Rue Coulombe",
    "sg:city":"Dolbeau-Mistassini",
    "sg:classifiers":[
        {
            "category":"Personal",
            "type":"Services"
        }
    ],
    "sg:phone":"+1 418 276 4226",
    "sg:postcode":"G8L 3L6",
    "sg:province":"QC",
    "sg:tags":[
        "clinic",
        "therapist",
        "massage"
    ],
    "wof:name":"Deschesnes Lisette Massotherap",
    "wof:placetype":"venue"
},
  "geometry": {"coordinates":[-72.24983978269999,48.8867721558],"type":"Point"}
}