{
  "type": "Feature",
  "properties": {
    "iso:country":"CA",
    "sg:address":"435 Donwood Dr",
    "sg:city":"Winnipeg",
    "sg:classifiers":[
        {
            "category":"Building & Trades",
            "subcategory":"Construction",
            "type":"Services"
        }
    ],
    "sg:phone":"+1 204 668 5067",
    "sg:postcode":"R2G 0X5",
    "sg:province":"MB",
    "sg:tags":[
        "tile",
        "dealer"
    ],
    "wof:name":"J & L Tile CO Ltd",
    "wof:placetype":"venue"
},
  "geometry": {"coordinates":[-97.065269,49.940678],"type":"Point"}
}