{
  "type": "Feature",
  "properties": {
    "addr:full":"334 Simcoe St Beaverton ON L0K 1A0",
    "addr:housenumber":"334",
    "addr:postcode":"l0k 1a0",
    "addr:street":"Simcoe St",
    "iso:country":"CA",
    "sg:address":"334 Simcoe St",
    "sg:city":"Beaverton",
    "sg:classifiers":[
        {
            "category":"Restaurant",
            "type":"Food & Drink"
        }
    ],
    "sg:phone":"+1 705 426 7950",
    "sg:postcode":"L0K 1A0",
    "sg:province":"ON",
    "sg:tags":[
        "health",
        "diet"
    ],
    "wof:name":"Farmer's Kitchen",
    "wof:placetype":"venue"
},
  "geometry": {"coordinates":[-79.15413700000001,44.429817],"type":"Point"}
}