{
  "type": "Feature",
  "properties": {
    "addr:full":"427 1st St Kamsack SK S0A 1S0",
    "addr:housenumber":"427",
    "addr:postcode":"s0a 1s0",
    "addr:street":"1St St",
    "iso:country":"CA",
    "sg:address":"427 1st St",
    "sg:city":"Kamsack",
    "sg:classifiers":[
        {
            "category":"Shopping",
            "subcategory":"Jewelry",
            "type":"Retail Goods"
        }
    ],
    "sg:phone":"+1 306 542 4422",
    "sg:postcode":"S0A 1S0",
    "sg:province":"SK",
    "sg:tags":[
        "jeweler"
    ],
    "wof:name":"Glass Door Jewellery",
    "wof:placetype":"venue"
},
  "geometry": {"coordinates":[-101.90431213399999,51.5642051697],"type":"Point"}
}