{
  "type": "Feature",
  "properties": {
    "addr:full":"147 Hamelin St Winnipeg MB R3T 3Z1",
    "addr:housenumber":"147",
    "addr:postcode":"r3t 3z1",
    "addr:street":"Hamelin St",
    "iso:country":"CA",
    "sg:address":"147 Hamelin St",
    "sg:city":"Winnipeg",
    "sg:classifiers":[
        {
            "category":"Professional",
            "subcategory":"Research",
            "type":"Services"
        }
    ],
    "sg:phone":"+1 204 478 1023",
    "sg:postcode":"R3T 3Z1",
    "sg:province":"MB",
    "sg:tags":[
        "development",
        "laboratory"
    ],
    "wof:name":"Viventia Biotech Inc",
    "wof:placetype":"venue"
},
  "geometry": {"coordinates":[-97.1694717407,49.8311958313],"type":"Point"}
}