{
  "type": "Feature",
  "properties": {
    "addr:full":"32 Rue Saint-Paul Saint-Jean-Sur-Richelieu QC J3B 1Y7",
    "addr:housenumber":"32",
    "addr:postcode":"j3b 1y7",
    "addr:street":"Rue Saint-Paul",
    "iso:country":"CA",
    "sg:address":"32 Rue Saint-Paul",
    "sg:city":"Saint-Jean-Sur-Richelieu",
    "sg:classifiers":[
        {
            "category":"Shopping",
            "subcategory":"Jewelry",
            "type":"Retail Goods"
        }
    ],
    "sg:phone":"+1 450 348 5696",
    "sg:postcode":"J3B 1Y7",
    "sg:province":"QC",
    "sg:tags":[
        "watch"
    ],
    "wof:name":"Horlogerie Richelieu Enr",
    "wof:placetype":"venue"
},
  "geometry": {"coordinates":[-73.2531738281,45.311050415],"type":"Point"}
}