{
  "type": "Feature",
  "properties": {
    "iso:country":"CA",
    "sg:address":"2504 Rang St Joseph",
    "sg:city":"Sainte-Perpetue",
    "sg:classifiers":[
        {
            "category":"Education",
            "subcategory":"School",
            "type":"Public Place"
        }
    ],
    "sg:phone":"+1 819 336 6623",
    "sg:postcode":"J0C 1R0",
    "sg:province":"QC",
    "wof:name":"Ecole LA Jeunesse",
    "wof:placetype":"venue"
},
  "geometry": {"coordinates":[-72.4610290527,46.0786781311],"type":"Point"}
}