{
  "type": "Feature",
  "properties": {
    "addr:full":"Quebec QC G2K 1N4",
    "addr:postcode":"g2k 1n4",
    "iso:country":"CA",
    "sg:city":"Quebec",
    "sg:classifiers":[
        {
            "category":"Shopping",
            "subcategory":"Clothing, Apparel, & Fashions",
            "type":"Retail Goods"
        }
    ],
    "sg:phone":"+1 418 627 3156",
    "sg:postcode":"G2K 1N4",
    "sg:province":"QC",
    "sg:tags":[
        "tailor"
    ],
    "wof:name":"Abraham Tailleur Enr",
    "wof:placetype":"venue"
},
  "geometry": {"coordinates":[-71.295677,46.831238],"type":"Point"}
}