{
  "type": "Feature",
  "properties": {
    "addr:full":"Thornhill BC V8G 4Z8",
    "addr:postcode":"v8g 4z8",
    "iso:country":"CA",
    "sg:city":"Thornhill",
    "sg:classifiers":[
        {
            "category":"Building & Trades",
            "subcategory":"Construction",
            "type":"Services"
        }
    ],
    "sg:phone":"+1 250 638 1822",
    "sg:postcode":"V8G 4Z8",
    "sg:province":"BC",
    "sg:tags":[
        "dry wall",
        "contractor"
    ],
    "wof:name":"Gunnar's Drywall",
    "wof:placetype":"venue"
},
  "geometry": {"coordinates":[-128.517303,54.513466],"type":"Point"}
}