{
  "type": "Feature",
  "properties": {
    "addr:full":"Brampton ON L6T 5B1",
    "addr:postcode":"l6t 5b1",
    "iso:country":"CA",
    "sg:city":"Brampton",
    "sg:classifiers":[
        {
            "category":"Manufacturing",
            "subcategory":"Tools & Machinery",
            "type":"Manufacturing & Wholesale Goods"
        }
    ],
    "sg:phone":"+1 905 455 3116",
    "sg:postcode":"L6T 5B1",
    "sg:province":"ON",
    "sg:tags":[
        "built",
        "designed"
    ],
    "wof:name":"Apex Manufacturing",
    "wof:placetype":"venue"
},
  "geometry": {"coordinates":[-79.7040100098,43.6899299622],"type":"Point"}
}