{
  "type": "Feature",
  "properties": {
    "addr:full":"320 Harwell Rd Nanaimo BC V9R 6V2",
    "addr:housenumber":"320",
    "addr:postcode":"v9r 6v2",
    "addr:street":"Harwell Rd",
    "iso:country":"CA",
    "sg:address":"320 Harwell Rd",
    "sg:city":"Nanaimo",
    "sg:classifiers":[
        {
            "category":"Personal",
            "subcategory":"Beauty Salon",
            "type":"Services"
        }
    ],
    "sg:phone":"+1 250 754 1000",
    "sg:postcode":"V9R 6V2",
    "sg:province":"BC",
    "sg:tags":[
        "manicuring"
    ],
    "wof:name":"Classic Tips Nail Design",
    "wof:placetype":"venue"
},
  "geometry": {"coordinates":[-123.98925800000001,49.166035],"type":"Point"}
}