{
  "type": "Feature",
  "properties": {
    "addr:full":"1391 Boul Rene-Levesque E Montreal QC H2L 2M1",
    "addr:housenumber":"1391",
    "addr:postcode":"h2l 2m1",
    "addr:street":"Boul Rene-Levesque E",
    "iso:country":"CA",
    "sg:address":"1391 Boul Rene-Levesque E",
    "sg:city":"Montreal",
    "sg:classifiers":[
        {
            "category":"Building & Trades",
            "subcategory":"Construction",
            "type":"Services"
        }
    ],
    "sg:phone":"+1 514 731 0402",
    "sg:postcode":"H2L 2M1",
    "sg:province":"QC",
    "sg:tags":[
        "general",
        "contractor"
    ],
    "wof:name":"Taya Contractors Inc",
    "wof:placetype":"venue"
},
  "geometry": {"coordinates":[-73.552071,45.519348],"type":"Point"}
}