{
  "type": "Feature",
  "properties": {
    "addr:full":"1230 Boul Cure-Poirier O Longueuil QC J4K 4Z3",
    "addr:housenumber":"1230",
    "addr:postcode":"j4k 4z3",
    "addr:street":"Boul Cure-Poirier O",
    "iso:country":"CA",
    "sg:address":"1230 Boul Cure-Poirier O",
    "sg:city":"Longueuil",
    "sg:classifiers":[
        {
            "category":"Food & Beverages",
            "subcategory":"Groceries & Convenience Stores",
            "type":"Retail Goods"
        }
    ],
    "sg:phone":"+1 450 463 3190",
    "sg:postcode":"J4K 4Z3",
    "sg:province":"QC",
    "sg:tags":[
        "grocer"
    ],
    "wof:name":"Couche-Tard",
    "wof:placetype":"venue"
},
  "geometry": {"coordinates":[-73.468834,45.543282],"type":"Point"}
}