{
  "type": "Feature",
  "properties": {
    "addr:full":"1473 Rue Fleury E Montreal QC H2C 1S3",
    "addr:housenumber":"1473",
    "addr:postcode":"h2c 1s3",
    "addr:street":"Rue Fleury E",
    "iso:country":"CA",
    "sg:address":"1473 Rue Fleury E",
    "sg:city":"Montreal",
    "sg:classifiers":[
        {
            "category":"Real Estate",
            "subcategory":"Real Estate Operator",
            "type":"Services"
        }
    ],
    "sg:phone":"+1 514 387 0022",
    "sg:postcode":"H2C 1S3",
    "sg:province":"QC",
    "sg:tags":[
        "mall",
        "shopping",
        "center"
    ],
    "wof:name":"Promenade Fleury",
    "wof:placetype":"venue"
},
  "geometry": {"coordinates":[-73.65692901609999,45.56224823],"type":"Point"}
}