{
  "type": "Feature",
  "properties": {
    "iso:country":"CA",
    "sg:address":"245 Carnegie Dr",
    "sg:city":"St Albert",
    "sg:classifiers":[
        {
            "category":"Freight",
            "type":"Transportation"
        }
    ],
    "sg:phone":"+1 780 460 1234",
    "sg:postcode":"T8N 5A7",
    "sg:province":"AB",
    "sg:tags":[
        "commercial",
        "storage"
    ],
    "wof:name":"St Albert Self Storage Ltd",
    "wof:placetype":"venue"
},
  "geometry": {"coordinates":[-113.57608795199999,53.639125824],"type":"Point"}
}