{
  "type": "Feature",
  "properties": {
    "addr:full":"89 Rue Glinel Beauport QC G1B 3G2",
    "addr:housenumber":"89",
    "addr:postcode":"g1b 3g2",
    "addr:street":"Rue Glinel",
    "iso:country":"CA",
    "sg:address":"89 Rue Glinel",
    "sg:city":"Beauport",
    "sg:classifiers":[
        {
            "category":"Building & Trades",
            "subcategory":"Construction",
            "type":"Services"
        }
    ],
    "sg:phone":"+1 418 808 7303",
    "sg:postcode":"G1B 3G2",
    "sg:province":"QC",
    "sg:tags":[
        "elevator"
    ],
    "wof:name":"Ascenseur Universel Inc",
    "wof:placetype":"venue"
},
  "geometry": {"coordinates":[-71.221062,46.893093],"type":"Point"}
}