{
  "type": "Feature",
  "properties": {
    "addr:full":"486 Parliament St Toronto ON M4X 1P2",
    "addr:housenumber":"486",
    "addr:postcode":"m4x 1p2",
    "addr:street":"Parliament St",
    "iso:country":"CA",
    "sg:address":"486 Parliament St",
    "sg:city":"Toronto",
    "sg:classifiers":[
        {
            "category":"Retail",
            "subcategory":"Laundry & Dry Cleaning",
            "type":"Services"
        }
    ],
    "sg:phone":"+1 416 924 8376",
    "sg:postcode":"M4X 1P2",
    "sg:province":"ON",
    "wof:name":"Cabbagetown Laundromat",
    "wof:placetype":"venue"
},
  "geometry": {"coordinates":[-79.368332,43.66468],"type":"Point"}
}