{
  "type": "Feature",
  "properties": {
    "addr:full":"250 2E Av Quebec QC G1L 3A7",
    "addr:housenumber":"250",
    "addr:postcode":"g1l 3a7",
    "addr:street":"2E Av",
    "iso:country":"CA",
    "sg:address":"250 2E Av",
    "sg:city":"Quebec",
    "sg:classifiers":[
        {
            "category":"Manufacturing",
            "subcategory":"Motor Vehicles & Parts",
            "type":"Manufacturing & Wholesale Goods"
        }
    ],
    "sg:phone":"+1 418 522 8222",
    "sg:postcode":"G1L 3A7",
    "sg:province":"QC",
    "sg:tags":[
        "equipment",
        "designer",
        "hydraulic",
        "supply"
    ],
    "wof:name":"Phil Larochelle Equipement Inc",
    "wof:placetype":"venue"
},
  "geometry": {"coordinates":[-71.2269744873,46.8210945129],"type":"Point"}
}