{
  "type": "Feature",
  "properties": {
    "addr:full":"Hamilton ON L8R 3H6",
    "addr:postcode":"l8r 3h6",
    "iso:country":"CA",
    "sg:city":"Hamilton",
    "sg:classifiers":[
        {
            "category":"Real Estate",
            "subcategory":"Real Estate Operator",
            "type":"Services"
        }
    ],
    "sg:phone":"+1 905 529 9401",
    "sg:postcode":"L8R 3H6",
    "sg:province":"ON",
    "sg:tags":[
        "apartment"
    ],
    "wof:name":"Marketeer",
    "wof:placetype":"venue"
},
  "geometry": {"coordinates":[-79.87631988530001,43.2597923279],"type":"Point"}
}