{
  "type": "Feature",
  "properties": {
    "addr:full":"1616 Rue DE Salaberry Montreal QC H3M 1K2",
    "addr:housenumber":"1616",
    "addr:postcode":"h3m 1k2",
    "addr:street":"Rue De Salaberry",
    "iso:country":"CA",
    "sg:address":"1616 Rue DE Salaberry",
    "sg:city":"Montreal",
    "sg:classifiers":[
        {
            "category":"Personal",
            "subcategory":"Beauty Salon",
            "type":"Services"
        }
    ],
    "sg:phone":"+1 514 956 9448",
    "sg:postcode":"H3M 1K2",
    "sg:province":"QC",
    "wof:name":"Lady Godiva Coiffure",
    "wof:placetype":"venue"
},
  "geometry": {"coordinates":[-73.6946258545,45.5419845581],"type":"Point"}
}