{
  "type": "Feature",
  "properties": {
    "addr:full":"8321 Willard St Burnaby BC V3N 2X3",
    "addr:housenumber":"8321",
    "addr:postcode":"v3n 2x3",
    "addr:street":"Willard St",
    "iso:country":"CA",
    "sg:address":"8321 Willard St",
    "sg:city":"Burnaby",
    "sg:classifiers":[
        {
            "category":"Manufacturing",
            "subcategory":"Chemicals & Compounds",
            "type":"Manufacturing & Wholesale Goods"
        }
    ],
    "sg:phone":"+1 604 520 6211",
    "sg:postcode":"V3N 2X3",
    "sg:province":"BC",
    "wof:name":"Pace Chemicals Ltd",
    "wof:placetype":"venue"
},
  "geometry": {"coordinates":[-122.95732099999999,49.19368],"type":"Point"}
}