{
  "type": "Feature",
  "properties": {
    "addr:full":"2905 14th Ave W Vancouver BC V6K 2X5",
    "addr:housenumber":"2905",
    "addr:postcode":"v6k 2x5",
    "addr:street":"14Th Ave W",
    "iso:country":"CA",
    "sg:address":"2905 14th Ave W",
    "sg:city":"Vancouver",
    "sg:classifiers":[
        {
            "category":"Real Estate",
            "subcategory":"Architect",
            "type":"Services"
        }
    ],
    "sg:phone":"+1 604 688 3600",
    "sg:postcode":"V6K 2X5",
    "sg:province":"BC",
    "wof:name":"Faibish, Jory C",
    "wof:placetype":"venue"
},
  "geometry": {"coordinates":[-123.170433,49.259781],"type":"Point"}
}