{
  "type": "Feature",
  "properties": {
    "addr:full":"3022 Bloor St W Etobicoke ON M8X 1C4",
    "addr:housenumber":"3022",
    "addr:postcode":"m8x 1c4",
    "addr:street":"Bloor St W",
    "iso:country":"CA",
    "sg:address":"3022 Bloor St W",
    "sg:city":"Etobicoke",
    "sg:classifiers":[
        {
            "category":"Banks & Credit Unions",
            "subcategory":"Bank",
            "type":"Services"
        }
    ],
    "sg:phone":"+1 416 231 2255",
    "sg:postcode":"M8X 1C4",
    "sg:province":"ON",
    "wof:name":"Bank of Montreal",
    "wof:placetype":"venue"
},
  "geometry": {"coordinates":[-79.51178,43.647404],"type":"Point"}
}