{
  "type": "Feature",
  "properties": {
    "addr:full":"PO Box 1072 Rpo Main Clair NB E7A 2J5",
    "addr:housenumber":"po",
    "addr:postcode":"e7a 2j5",
    "addr:street":"Box 1072 Rpo Main",
    "iso:country":"CA",
    "sg:address":"PO Box 1072 Rpo Main",
    "sg:city":"Clair",
    "sg:classifiers":[
        {
            "category":"Social Services",
            "type":"Services"
        }
    ],
    "sg:phone":"+1 506 992 2820",
    "sg:postcode":"E7A 2J5",
    "sg:province":"NB",
    "sg:tags":[
        "organization",
        "welfare"
    ],
    "wof:name":"Escadrille DE L'Air 836",
    "wof:placetype":"venue"
},
  "geometry": {"coordinates":[-68.604477,47.251747],"type":"Point"}
}