{
  "type": "Feature",
  "properties": {
    "addr:full":"1517 Sieveright Rd Gloucester ON K1T 1M5",
    "addr:housenumber":"1517",
    "addr:postcode":"k1t 1m5",
    "addr:street":"Sieveright Rd",
    "iso:country":"CA",
    "sg:address":"1517 Sieveright Rd",
    "sg:city":"Gloucester",
    "sg:classifiers":[
        {
            "category":"Utilities",
            "subcategory":"Natural Gas",
            "type":"Services"
        }
    ],
    "sg:phone":"+1 613 733 6292",
    "sg:postcode":"K1T 1M5",
    "sg:province":"ON",
    "sg:tags":[
        "repairing",
        "automobile",
        "company"
    ],
    "wof:name":"J & J Auto Svc Ltd",
    "wof:placetype":"venue"
},
  "geometry": {"coordinates":[-75.636658,45.355816],"type":"Point"}
}