{
  "type": "Feature",
  "properties": {
    "addr:full":"Saint-Hyacinthe QC J2S 2Z8",
    "addr:postcode":"j2s 2z8",
    "iso:country":"CA",
    "sg:city":"Saint-Hyacinthe",
    "sg:classifiers":[
        {
            "category":"Professional",
            "subcategory":"Lawyer & Legal Services",
            "type":"Services"
        }
    ],
    "sg:phone":"+1 514 866 8445",
    "sg:postcode":"J2S 2Z8",
    "sg:province":"QC",
    "sg:tags":[
        "attorney"
    ],
    "wof:name":"Sylvestre & Assoc",
    "wof:placetype":"venue"
},
  "geometry": {"coordinates":[-72.9399032593,45.6413726807],"type":"Point"}
}