{
  "type": "Feature",
  "properties": {
    "addr:full":"RR 2 STN Main Pembroke ON K8A 6W3",
    "addr:postcode":"k8a 6w3",
    "addr:street":"Rr 2 Stn Main",
    "iso:country":"CA",
    "sg:address":"RR 2 STN Main",
    "sg:city":"Pembroke",
    "sg:classifiers":[
        {
            "category":"Shopping",
            "subcategory":"Used Merchandise",
            "type":"Retail Goods"
        }
    ],
    "sg:phone":"+1 613 638 5160",
    "sg:postcode":"K8A 6W3",
    "sg:province":"ON",
    "sg:tags":[
        "antique"
    ],
    "wof:name":"Ray's Antique Shop",
    "wof:placetype":"venue"
},
  "geometry": {"coordinates":[-77.1122131348,45.8264808655],"type":"Point"}
}