{
  "type": "Feature",
  "properties": {
    "addr:full":"224 10th St Hanover ON N4N 1N9",
    "addr:housenumber":"224",
    "addr:postcode":"n4n 1n9",
    "addr:street":"10Th St",
    "iso:country":"CA",
    "sg:address":"224 10th St",
    "sg:city":"Hanover",
    "sg:classifiers":[
        {
            "category":"Personal",
            "subcategory":"Beauty Salon",
            "type":"Services"
        }
    ],
    "sg:phone":"+1 519 364 3710",
    "sg:postcode":"N4N 1N9",
    "sg:province":"ON",
    "wof:name":"Val's Hair Design",
    "wof:placetype":"venue"
},
  "geometry": {"coordinates":[-81.0305862427,44.1517753601],"type":"Point"}
}