{
  "type": "Feature",
  "properties": {
    "addr:full":"104 Church St Woodstock NB E7M 5Z7",
    "addr:housenumber":"104",
    "addr:postcode":"e7m 5z7",
    "addr:street":"Church St",
    "iso:country":"CA",
    "sg:address":"104 Church St",
    "sg:city":"Woodstock",
    "sg:classifiers":[
        {
            "category":"Organizations",
            "subcategory":"Religious Organization",
            "type":"Services"
        }
    ],
    "sg:phone":"+1 506 328 4304",
    "sg:postcode":"E7M 5Z7",
    "sg:province":"NB",
    "sg:tags":[
        "church"
    ],
    "wof:name":"Anglican Church of Canada",
    "wof:placetype":"venue"
},
  "geometry": {"coordinates":[-67.572281,46.151653],"type":"Point"}
}