{
  "type": "Feature",
  "properties": {
    "addr:full":"4458 Rue Sainte-Catherine O Westmount QC H3Z 1R7",
    "addr:housenumber":"4458",
    "addr:postcode":"h3z 1r7",
    "addr:street":"Rue Sainte-Catherine O",
    "iso:country":"CA",
    "sg:address":"4458 Rue Sainte-Catherine O",
    "sg:city":"Westmount",
    "sg:classifiers":[
        {
            "category":"Restaurant",
            "type":"Food & Drink"
        }
    ],
    "sg:phone":"+1 514 989 8580",
    "sg:postcode":"H3Z 1R7",
    "sg:province":"QC",
    "wof:name":"Restaurant Copoli-2",
    "wof:placetype":"venue"
},
  "geometry": {"coordinates":[-73.592606,45.481522],"type":"Point"}
}