{
  "type": "Feature",
  "properties": {
    "addr:full":"325 Prince St Sydney NS B1P 5K6",
    "addr:housenumber":"325",
    "addr:postcode":"b1p 5k6",
    "addr:street":"Prince St",
    "iso:country":"CA",
    "sg:address":"325 Prince St",
    "sg:city":"Sydney",
    "sg:classifiers":[
        {
            "category":"Banks & Credit Unions",
            "subcategory":"Bank",
            "type":"Services"
        }
    ],
    "sg:phone":"+1 902 567 8570",
    "sg:postcode":"B1P 5K6",
    "sg:province":"NS",
    "wof:name":"Royal Bank Financial Group",
    "wof:placetype":"venue"
},
  "geometry": {"coordinates":[-60.1846885681,46.1397361755],"type":"Point"}
}