{
  "type": "Feature",
  "properties": {
    "iso:country":"CA",
    "sg:city":"New Westminster",
    "sg:classifiers":[
        {
            "category":"Real Estate",
            "subcategory":"Real Estate Operator",
            "type":"Services"
        }
    ],
    "sg:phone":"+1 604 524 5082",
    "sg:postcode":"V3M 5Z6",
    "sg:province":"BC",
    "sg:tags":[
        "apartment"
    ],
    "wof:name":"London Place",
    "wof:placetype":"venue"
},
  "geometry": {"coordinates":[-122.93687439,49.2124290466],"type":"Point"}
}