{
  "type": "Feature",
  "properties": {
    "addr:full":"117 Scenic Ridge Cres NW Calgary AB T3L 1V3",
    "addr:housenumber":"117",
    "addr:postcode":"t3l 1v3",
    "addr:street":"Scenic Ridge Cres Nw",
    "iso:country":"CA",
    "sg:address":"117 Scenic Ridge Cres NW",
    "sg:city":"Calgary",
    "sg:classifiers":[
        {
            "category":"Education",
            "subcategory":"Special Training",
            "type":"Public Place"
        }
    ],
    "sg:phone":"+1 403 547 9243",
    "sg:postcode":"T3L 1V3",
    "sg:province":"AB",
    "sg:tags":[
        "tutoring"
    ],
    "wof:name":"Access Tutoring",
    "wof:placetype":"venue"
},
  "geometry": {"coordinates":[-114.219604492,51.1088142395],"type":"Point"}
}