{
  "type": "Feature",
  "properties": {
    "addr:full":"2740 Boul Laurier Sainte-Foy QC G1V 4P7",
    "addr:housenumber":"2740",
    "addr:postcode":"g1v 4p7",
    "addr:street":"Boul Laurier",
    "iso:country":"CA",
    "sg:address":"2740 Boul Laurier",
    "sg:city":"Sainte-Foy",
    "sg:classifiers":[
        {
            "category":"Shopping",
            "subcategory":"Department Store",
            "type":"Retail Goods"
        }
    ],
    "sg:phone":"+1 418 627 5959",
    "sg:postcode":"G1V 4P7",
    "sg:province":"QC",
    "wof:name":"Baie",
    "wof:placetype":"venue"
},
  "geometry": {"coordinates":[-71.2851257324,46.7691421509],"type":"Point"}
}