{
  "type": "Feature",
  "properties": {
    "addr:full":"612 Front St Atikokan ON P0T 1C0",
    "addr:housenumber":"612",
    "addr:postcode":"p0t 1c0",
    "addr:street":"Front St",
    "iso:country":"CA",
    "sg:address":"612 Front St",
    "sg:city":"Atikokan",
    "sg:classifiers":[
        {
            "category":"Building & Trades",
            "subcategory":"Electrical",
            "type":"Services"
        }
    ],
    "sg:phone":"+1 807 597 2307",
    "sg:postcode":"P0T 1C0",
    "sg:province":"ON",
    "sg:tags":[
        "electric",
        "contractor"
    ],
    "wof:name":"Pierce Electric Contracting",
    "wof:placetype":"venue"
},
  "geometry": {"coordinates":[-91.63464399999999,48.753948],"type":"Point"}
}