{
  "type": "Feature",
  "properties": {
    "iso:country":"CA",
    "sg:address":"6855 Av DE L'Epee # 102",
    "sg:city":"Montreal",
    "sg:classifiers":[
        {
            "category":"Wholesale",
            "subcategory":"Office Equipment",
            "type":"Manufacturing & Wholesale Goods"
        }
    ],
    "sg:phone":"+1 514 733 3773",
    "sg:postcode":"H3N 2C7",
    "sg:province":"QC",
    "sg:tags":[
        "register",
        "cash",
        "supply"
    ],
    "wof:name":"Azbar",
    "wof:placetype":"venue"
},
  "geometry": {"coordinates":[-73.621887,45.527435],"type":"Point"}
}