{
  "type": "Feature",
  "properties": {
    "addr:full":"1265 Rue Tellier Laval QC H7C 2H1",
    "addr:housenumber":"1265",
    "addr:postcode":"h7c 2h1",
    "addr:street":"Rue Tellier",
    "iso:country":"CA",
    "sg:address":"1265 Rue Tellier",
    "sg:city":"Laval",
    "sg:classifiers":[
        {
            "category":"Manufacturing",
            "subcategory":"Chemicals & Compounds",
            "type":"Manufacturing & Wholesale Goods"
        }
    ],
    "sg:phone":"+1 450 664 0163",
    "sg:postcode":"H7C 2H1",
    "sg:province":"QC",
    "sg:tags":[
        "paint"
    ],
    "wof:name":"Laknord Enr",
    "wof:placetype":"venue"
},
  "geometry": {"coordinates":[-73.658585,45.616207],"type":"Point"}
}