{
  "type": "Feature",
  "properties": {
    "addr:full":"179493 County Rd 17 Wiarton ON N0H 2T0",
    "addr:housenumber":"179493;17",
    "addr:postcode":"n0h 2t0",
    "addr:street":"County Rd",
    "iso:country":"CA",
    "sg:address":"179493 County Rd 17",
    "sg:city":"Wiarton",
    "sg:classifiers":[
        {
            "category":"Building & Trades",
            "subcategory":"Plumbing",
            "type":"Services"
        }
    ],
    "sg:phone":"+1 519 534 5933",
    "sg:postcode":"N0H 2T0",
    "sg:province":"ON",
    "sg:tags":[
        "contractor"
    ],
    "wof:name":"Al Joyce Plumbing & Mechanical",
    "wof:placetype":"venue"
},
  "geometry": {"coordinates":[-81.1397857666,44.7401351929],"type":"Point"}
}