{
  "type": "Feature",
  "properties": {
    "addr:full":"Ottawa ON K1Y 2Y9",
    "addr:postcode":"k1y 2y9",
    "iso:country":"CA",
    "sg:city":"Ottawa",
    "sg:classifiers":[
        {
            "category":"Personal",
            "subcategory":"Beauty Salon",
            "type":"Services"
        }
    ],
    "sg:phone":"+1 613 729 6813",
    "sg:postcode":"K1Y 2Y9",
    "sg:province":"ON",
    "wof:name":"Stella Beauty Salon",
    "wof:placetype":"venue"
},
  "geometry": {"coordinates":[-75.7289352417,45.4009857178],"type":"Point"}
}