{
  "type": "Feature",
  "properties": {
    "iso:country":"CA",
    "sg:address":"9 Barn Rd",
    "sg:city":"St Anthony",
    "sg:classifiers":[
        {
            "category":"Bars & Pubs",
            "type":"Food & Drink"
        }
    ],
    "sg:phone":"+1 709 454 3220",
    "sg:postcode":"A0K 4S0",
    "sg:province":"NL",
    "sg:tags":[
        "club",
        "night"
    ],
    "wof:name":"Carson Lounge",
    "wof:placetype":"venue"
},
  "geometry": {"coordinates":[-55.6133537292,51.3665618896],"type":"Point"}
}