{
  "type": "Feature",
  "properties": {
    "addr:full":"Saint-Laurent QC H4T 1G7",
    "addr:postcode":"h4t 1g7",
    "iso:country":"CA",
    "sg:city":"Saint-Laurent",
    "sg:classifiers":[
        {
            "category":"Wholesale",
            "subcategory":"Stationery",
            "type":"Manufacturing & Wholesale Goods"
        }
    ],
    "sg:phone":"+1 514 731 3713",
    "sg:postcode":"H4T 1G7",
    "sg:province":"QC",
    "sg:tags":[
        "packaging"
    ],
    "wof:name":"Emballages Festival Inc",
    "wof:placetype":"venue"
},
  "geometry": {"coordinates":[-73.704185,45.475864],"type":"Point"}
}