{
  "type": "Feature",
  "properties": {
    "iso:country":"CA",
    "sg:address":"610 27 St N",
    "sg:city":"Lethbridge",
    "sg:classifiers":[
        {
            "category":"Shopping",
            "type":"Retail Goods"
        }
    ],
    "sg:phone":"+1 403 329 0273",
    "sg:postcode":"T1H 3W7",
    "sg:province":"AB",
    "sg:tags":[
        "coin",
        "dealer",
        "supply"
    ],
    "wof:name":"Chinook Stamp & Coin Shop",
    "wof:placetype":"venue"
},
  "geometry": {"coordinates":[-112.804397583,49.7071113586],"type":"Point"}
}