{
  "type": "Feature",
  "properties": {
    "addr:full":"28 Common St Sydney NS B1P 3L1",
    "addr:housenumber":"28",
    "addr:postcode":"b1p 3l1",
    "addr:street":"Common St",
    "iso:country":"CA",
    "sg:address":"28 Common St",
    "sg:city":"Sydney",
    "sg:classifiers":[
        {
            "category":"Building & Trades",
            "subcategory":"Construction",
            "type":"Services"
        }
    ],
    "sg:phone":"+1 902 562 3528",
    "sg:postcode":"B1P 3L1",
    "sg:province":"NS",
    "sg:tags":[
        "surveyor",
        "general",
        "contractor"
    ],
    "wof:name":"Wayne D Hardy Nsls Cls",
    "wof:placetype":"venue"
},
  "geometry": {"coordinates":[-60.1764526367,46.1237297058],"type":"Point"}
}