{
  "type": "Feature",
  "properties": {
    "addr:full":"490 Av Michel-Jasmin Dorval QC H9P 1C3",
    "addr:housenumber":"490",
    "addr:postcode":"h9p 1c3",
    "addr:street":"Av Michel-Jasmin",
    "iso:country":"CA",
    "sg:address":"490 Av Michel-Jasmin",
    "sg:city":"Dorval",
    "sg:classifiers":[
        {
            "category":"Restaurant",
            "type":"Food & Drink"
        }
    ],
    "sg:phone":"+1 514 420 0075",
    "sg:postcode":"H9P 1C3",
    "sg:province":"QC",
    "wof:name":"Restaurant Bar Focaccio",
    "wof:placetype":"venue"
},
  "geometry": {"coordinates":[-73.73558,45.453056],"type":"Point"}
}