{
  "type": "Feature",
  "properties": {
    "addr:full":"292 Main St Carman MB R0G 0J0",
    "addr:housenumber":"292",
    "addr:postcode":"r0g 0j0",
    "addr:street":"Main St",
    "iso:country":"CA",
    "sg:address":"292 Main St",
    "sg:city":"Carman",
    "sg:classifiers":[
        {
            "category":"Professional",
            "subcategory":"Art Services",
            "type":"Services"
        }
    ],
    "sg:phone":"+1 204 745 2221",
    "sg:postcode":"R0G 0J0",
    "sg:province":"MB",
    "sg:tags":[
        "photographer"
    ],
    "wof:name":"Yourview Aerial Scenics",
    "wof:placetype":"venue"
},
  "geometry": {"coordinates":[-98.00185399999999,49.497223],"type":"Point"}
}