{
  "type": "Feature",
  "properties": {
    "addr:full":"205695 Hwy 26 Meaford ON N4L 1W5",
    "addr:housenumber":"205695",
    "addr:postcode":"n4l 1w5",
    "addr:street":"Hwy 26",
    "iso:country":"CA",
    "sg:address":"205695 Hwy 26",
    "sg:city":"Meaford",
    "sg:classifiers":[
        {
            "category":"Retail",
            "subcategory":"Auto Repair",
            "type":"Services"
        }
    ],
    "sg:phone":"+1 519 538 2422",
    "sg:postcode":"N4L 1W5",
    "sg:province":"ON",
    "sg:tags":[
        "repairing",
        "automobile"
    ],
    "wof:name":"Stan's Repair Svc",
    "wof:placetype":"venue"
},
  "geometry": {"coordinates":[-80.6447143555,44.6110649109],"type":"Point"}
}