{
  "type": "Feature",
  "properties": {
    "addr:full":"12447 Riverside Dr E Windsor ON N8N 1A5",
    "addr:housenumber":"12447",
    "addr:postcode":"n8n 1a5",
    "addr:street":"Riverside Dr E",
    "iso:country":"CA",
    "sg:address":"12447 Riverside Dr E",
    "sg:city":"Windsor",
    "sg:classifiers":[
        {
            "category":"Professional",
            "subcategory":"Management & Consulting",
            "type":"Services"
        }
    ],
    "sg:phone":"+1 519 735 2761",
    "sg:postcode":"N8N 1A5",
    "sg:province":"ON",
    "sg:tags":[
        "consultant",
        "business"
    ],
    "wof:name":"Business Operating Systems",
    "wof:placetype":"venue"
},
  "geometry": {"coordinates":[-82.895996,42.332741],"type":"Point"}
}