{
  "type": "Feature",
  "properties": {
    "addr:full":"Mississauga ON L4W 1V5",
    "addr:postcode":"l4w 1v5",
    "iso:country":"CA",
    "sg:city":"Mississauga",
    "sg:classifiers":[
        {
            "category":"Food & Beverages",
            "subcategory":"Specialty",
            "type":"Retail Goods"
        }
    ],
    "sg:phone":"+1 905 206 9050",
    "sg:postcode":"L4W 1V5",
    "sg:province":"ON",
    "sg:tags":[
        "herb"
    ],
    "wof:name":"Ginsengg Herbs",
    "wof:placetype":"venue"
},
  "geometry": {"coordinates":[-79.605644,43.625027],"type":"Point"}
}