{
  "type": "Feature",
  "properties": {
    "addr:full":"396 Rue Main O Coaticook QC J1A 1P7",
    "addr:housenumber":"396",
    "addr:postcode":"j1a 1p7",
    "addr:street":"Rue Main O",
    "iso:country":"CA",
    "sg:address":"396 Rue Main O",
    "sg:city":"Coaticook",
    "sg:classifiers":[
        {
            "category":"Retail",
            "subcategory":"Auto Repair",
            "type":"Services"
        }
    ],
    "sg:phone":"+1 819 849 2776",
    "sg:postcode":"J1A 1P7",
    "sg:province":"QC",
    "sg:tags":[
        "repairing",
        "automobile"
    ],
    "wof:name":"Lamoureux Pontiac Buick Inc",
    "wof:placetype":"venue"
},
  "geometry": {"coordinates":[-71.797096,45.132507],"type":"Point"}
}