{
  "type": "Feature",
  "properties": {
    "iso:country":"CA",
    "sg:address":"3608 Line 9 N",
    "sg:city":"Coldwater",
    "sg:classifiers":[
        {
            "category":"Wholesale",
            "subcategory":"Fruits & Vegetables",
            "type":"Manufacturing & Wholesale Goods"
        }
    ],
    "sg:phone":"+1 705 835 3124",
    "sg:postcode":"L0K 1E0",
    "sg:province":"ON",
    "sg:tags":[
        "shipper"
    ],
    "wof:name":"Ego's Berry Farm",
    "wof:placetype":"venue"
},
  "geometry": {"coordinates":[-79.644363,44.710224],"type":"Point"}
}