{
  "type": "Feature",
  "properties": {
    "addr:full":"243 Boul Bourque Omerville QC J1X 4E7",
    "addr:housenumber":"243",
    "addr:postcode":"j1x 4e7",
    "addr:street":"Boul Bourque",
    "iso:country":"CA",
    "sg:address":"243 Boul Bourque",
    "sg:city":"Omerville",
    "sg:classifiers":[
        {
            "category":"Building & Trades",
            "subcategory":"Construction",
            "type":"Services"
        }
    ],
    "sg:phone":"+1 819 843 7246",
    "sg:postcode":"J1X 4E7",
    "sg:province":"QC",
    "sg:tags":[
        "woodworker"
    ],
    "wof:name":"Cuisines al Enr",
    "wof:placetype":"venue"
},
  "geometry": {"coordinates":[-72.115402,45.288113],"type":"Point"}
}