{
  "type": "Feature",
  "properties": {
    "addr:full":"8150 Rue Rousselot Montreal QC H2E 1Z6",
    "addr:housenumber":"8150",
    "addr:postcode":"h2e 1z6",
    "addr:street":"Rue Rousselot",
    "iso:country":"CA",
    "sg:address":"8150 Rue Rousselot",
    "sg:city":"Montreal",
    "sg:classifiers":[
        {
            "category":"Education",
            "subcategory":"School",
            "type":"Public Place"
        }
    ],
    "sg:phone":"+1 514 596 4400",
    "sg:postcode":"H2E 1Z6",
    "sg:province":"QC",
    "wof:name":"Henri-Julien Ecole",
    "wof:placetype":"venue"
},
  "geometry": {"coordinates":[-73.6221084595,45.5512084961],"type":"Point"}
}