{
  "type": "Feature",
  "properties": {
    "addr:full":"7483 50 Ave #9B Red Deer AB T4P 1M5",
    "addr:housenumber":"7483",
    "addr:postcode":"t4p 1m5",
    "addr:street":"50 Ave # 9B",
    "iso:country":"CA",
    "sg:address":"7483 50 Ave #9B",
    "sg:city":"Red Deer",
    "sg:classifiers":[
        {
            "category":"Building & Trades",
            "subcategory":"Electrical",
            "type":"Services"
        }
    ],
    "sg:phone":"+1 403 346 2147",
    "sg:postcode":"T4P 1M5",
    "sg:province":"AB",
    "sg:tags":[
        "electric",
        "contractor"
    ],
    "wof:name":"Sid's Electric Ltd",
    "wof:placetype":"venue"
},
  "geometry": {"coordinates":[-113.81323999999999,52.301098],"type":"Point"}
}