{
  "type": "Feature",
  "properties": {
    "iso:country":"CA",
    "sg:address":"Monroe St",
    "sg:city":"Moose Creek",
    "sg:classifiers":[
        {
            "category":"Organizations",
            "subcategory":"Professional Association",
            "type":"Services"
        }
    ],
    "sg:phone":"+1 613 538 2828",
    "sg:postcode":"K0C 1W0",
    "sg:province":"ON",
    "sg:tags":[
        "club"
    ],
    "wof:name":"Moose Creek Recreation Club",
    "wof:placetype":"venue"
},
  "geometry": {"coordinates":[-74.9752731323,45.2581100464],"type":"Point"}
}