{
  "type": "Feature",
  "properties": {
    "iso:country":"CA",
    "sg:address":"3826 115 Ave NW",
    "sg:city":"Edmonton",
    "sg:classifiers":[
        {
            "category":"Professional",
            "subcategory":"Business Services",
            "type":"Services"
        }
    ],
    "sg:phone":"+1 780 675 3422",
    "sg:postcode":"T5W 0V3",
    "sg:province":"AB",
    "sg:tags":[
        "water",
        "treatment"
    ],
    "wof:name":"Enviro-Clear Water Systems Inc",
    "wof:placetype":"venue"
},
  "geometry": {"coordinates":[-113.400917053,53.5679168701],"type":"Point"}
}