{
  "type": "Feature",
  "properties": {
    "addr:full":"67 Beachview Cres Toronto ON M4E 2L7",
    "addr:housenumber":"67",
    "addr:postcode":"m4e 2l7",
    "addr:street":"Beachview Cres",
    "iso:country":"CA",
    "sg:address":"67 Beachview Cres",
    "sg:city":"Toronto",
    "sg:classifiers":[
        {
            "category":"Building & Trades",
            "subcategory":"Construction",
            "type":"Services"
        }
    ],
    "sg:phone":"+1 416 691 3471",
    "sg:postcode":"M4E 2L7",
    "sg:province":"ON",
    "sg:tags":[
        "general",
        "contractor"
    ],
    "wof:name":"Braunstein & Braunstein Constr",
    "wof:placetype":"venue"
},
  "geometry": {"coordinates":[-79.307678,43.682362],"type":"Point"}
}