{
  "type": "Feature",
  "properties": {
    "iso:country":"CA",
    "sg:address":"138 Rue Richelieu",
    "sg:city":"Beloeil",
    "sg:classifiers":[
        {
            "category":"Health Services",
            "subcategory":"Nursing And Care Facility",
            "type":"Services"
        }
    ],
    "sg:phone":"+1 450 446 4949",
    "sg:postcode":"J3G 4N9",
    "sg:province":"QC",
    "sg:tags":[
        "home",
        "retirement",
        "community"
    ],
    "wof:name":"Residence Ensoleillee-Beloeil",
    "wof:placetype":"venue"
},
  "geometry": {"coordinates":[-73.21216583250001,45.5485649109],"type":"Point"}
}