{
  "type": "Feature",
  "properties": {
    "iso:country":"CA",
    "sg:city":"Newmarket",
    "sg:classifiers":[
        {
            "category":"Shopping",
            "type":"Retail Goods"
        }
    ],
    "sg:phone":"+1 905 830 9176",
    "sg:postcode":"L3Y 2M9",
    "sg:province":"ON",
    "sg:tags":[
        "miscellaneous",
        "store"
    ],
    "wof:name":"Adult Movie Warehouse",
    "wof:placetype":"venue"
},
  "geometry": {"coordinates":[-79.4759140015,44.0559463501],"type":"Point"}
}