{
  "type": "Feature",
  "properties": {
    "addr:full":"630 56th St E Saskatoon SK S7K 8G5",
    "addr:housenumber":"630",
    "addr:postcode":"s7k 8g5",
    "addr:street":"56Th St E",
    "iso:country":"CA",
    "sg:address":"630 56th St E",
    "sg:city":"Saskatoon",
    "sg:classifiers":[
        {
            "category":"Wholesale",
            "subcategory":"Machinery & Supplies",
            "type":"Manufacturing & Wholesale Goods"
        }
    ],
    "sg:phone":"+1 306 242 4466",
    "sg:postcode":"S7K 8G5",
    "sg:province":"SK",
    "sg:tags":[
        "room",
        "shipping"
    ],
    "wof:name":"General Fasteners Ltd",
    "wof:placetype":"venue"
},
  "geometry": {"coordinates":[-106.659934998,52.1807403564],"type":"Point"}
}