{
  "type": "Feature",
  "properties": {
    "addr:full":"133 Av Garnier Roberval QC G8H 1L3",
    "addr:postcode":"g8h 1l3",
    "addr:street":"133 Av Garnier",
    "iso:country":"CA",
    "sg:address":"133 Av Garnier",
    "sg:city":"Roberval",
    "sg:classifiers":[
        {
            "category":"Professional",
            "subcategory":"Accounting & Tax Preparation",
            "type":"Services"
        }
    ],
    "sg:phone":"+1 418 275 5791",
    "sg:postcode":"G8H 1L3",
    "sg:province":"QC",
    "sg:tags":[
        "bookkeeping",
        "return",
        "system",
        "filing"
    ],
    "wof:name":"Gestion Lisanne Tremblay Inc",
    "wof:placetype":"venue"
},
  "geometry": {"coordinates":[-72.223473,48.519653],"type":"Point"}
}