{
  "type": "Feature",
  "properties": {
    "iso:country":"CA",
    "sg:address":"222 Ridgeway",
    "sg:city":"Crystal Beach",
    "sg:classifiers":[
        {
            "category":"Building & Trades",
            "subcategory":"Construction",
            "type":"Services"
        }
    ],
    "sg:phone":"+1 905 894 1585",
    "sg:postcode":"L0S 1B0",
    "sg:province":"ON",
    "sg:tags":[
        "general",
        "contractor"
    ],
    "wof:name":"Schoenrath Directional Drillin",
    "wof:placetype":"venue"
},
  "geometry": {"coordinates":[-79.0588150024,42.8696022034],"type":"Point"}
}