{
  "type": "Feature",
  "properties": {
    "iso:country":"CA",
    "sg:address":"101 Queen St S",
    "sg:city":"Mississauga",
    "sg:classifiers":[
        {
            "category":"Professional",
            "subcategory":"Management & Consulting",
            "type":"Services"
        }
    ],
    "sg:phone":"+1 905 542 7114",
    "sg:postcode":"L5M 1K7",
    "sg:province":"ON",
    "sg:tags":[
        "consultant",
        "telecommunication"
    ],
    "wof:name":"Graycom Analysis",
    "wof:placetype":"venue"
},
  "geometry": {"coordinates":[-79.596809,43.546326],"type":"Point"}
}