{
  "type": "Feature",
  "properties": {
    "iso:country":"CA",
    "sg:address":"4720 26 Ave SW",
    "sg:city":"Calgary",
    "sg:classifiers":[
        {
            "category":"Building & Trades",
            "subcategory":"Construction",
            "type":"Services"
        }
    ],
    "sg:phone":"+1 403 250 8339",
    "sg:postcode":"T3E 0R2",
    "sg:province":"AB",
    "sg:tags":[
        "sewer",
        "landscape",
        "contractor"
    ],
    "wof:name":"Parkside Contractors",
    "wof:placetype":"venue"
},
  "geometry": {"coordinates":[-114.15341949499999,51.0306472778],"type":"Point"}
}