{
  "type": "Feature",
  "properties": {
    "addr:full":"94 Cannon St W # 1 Hamilton ON L8R 2B6",
    "addr:housenumber":"94",
    "addr:postcode":"l8r 2b6",
    "addr:street":"Cannon St W # 1",
    "iso:country":"CA",
    "sg:address":"94 Cannon St W # 1",
    "sg:city":"Hamilton",
    "sg:classifiers":[
        {
            "category":"Manufacturing",
            "subcategory":"Printing",
            "type":"Manufacturing & Wholesale Goods"
        }
    ],
    "sg:phone":"+1 905 528 7365",
    "sg:postcode":"L8R 2B6",
    "sg:province":"ON",
    "sg:tags":[
        "printer",
        "business",
        "form",
        "system"
    ],
    "wof:name":"Impressive Printing & Insert",
    "wof:placetype":"venue"
},
  "geometry": {"coordinates":[-79.8716812134,43.2619018555],"type":"Point"}
}