{
  "type": "Feature",
  "properties": {
    "addr:full":"7132 Rue DE Nogent Saint-Leonard QC H1S 2S1",
    "addr:housenumber":"7132",
    "addr:postcode":"h1s 2s1",
    "addr:street":"Rue De Nogent",
    "iso:country":"CA",
    "sg:address":"7132 Rue DE Nogent",
    "sg:city":"Saint-Leonard",
    "sg:classifiers":[
        {
            "category":"Wholesale",
            "subcategory":"Electrical",
            "type":"Manufacturing & Wholesale Goods"
        }
    ],
    "sg:phone":"+1 514 237 4047",
    "sg:postcode":"H1S 2S1",
    "sg:province":"QC",
    "sg:tags":[
        "intercommunication"
    ],
    "wof:name":"Abl Communications",
    "wof:placetype":"venue"
},
  "geometry": {"coordinates":[-73.586853,45.570065],"type":"Point"}
}