{
  "type": "Feature",
  "properties": {
    "iso:country":"CA",
    "sg:address":"180 Riverton Ave",
    "sg:city":"Winnipeg",
    "sg:classifiers":[
        {
            "category":"Education",
            "subcategory":"School",
            "type":"Public Place"
        }
    ],
    "sg:phone":"+1 204 667 8210",
    "sg:postcode":"R2L 2E8",
    "sg:province":"MB",
    "wof:name":"Mennonite Brethren Collegiate",
    "wof:placetype":"venue"
},
  "geometry": {"coordinates":[-97.117088,49.909718],"type":"Point"}
}