{
  "type": "Feature",
  "properties": {
    "addr:full":"92 Sanford Ave N Hamilton ON L8L 5Z2",
    "addr:housenumber":"92",
    "addr:postcode":"l8l 5z2",
    "addr:street":"Sanford Ave N",
    "iso:country":"CA",
    "sg:address":"92 Sanford Ave N",
    "sg:city":"Hamilton",
    "sg:classifiers":[
        {
            "category":"Autos & Motor Vehicles",
            "subcategory":"Automobile Sales",
            "type":"Retail Goods"
        }
    ],
    "sg:phone":"+1 905 545 6606",
    "sg:postcode":"L8L 5Z2",
    "sg:province":"ON",
    "sg:tags":[
        "car",
        "dealer"
    ],
    "wof:name":"Munro Auto Body",
    "wof:placetype":"venue"
},
  "geometry": {"coordinates":[-79.8451156616,43.2541923523],"type":"Point"}
}