{
  "type": "Feature",
  "properties": {
    "iso:country":"CA",
    "sg:city":"Saint-Didace",
    "sg:classifiers":[
        {
            "category":"Farming",
            "subcategory":"Farm",
            "type":"Manufacturing & Wholesale Goods"
        }
    ],
    "sg:phone":"+1 450 835 1435",
    "sg:postcode":"J0K 2G0",
    "sg:province":"QC",
    "wof:name":"Ferme Davi",
    "wof:placetype":"venue"
},
  "geometry": {"coordinates":[-73.31163787840001,46.3366317749],"type":"Point"}
}