{
  "type": "Feature",
  "properties": {
    "addr:full":"701 Ontario St Sarnia ON N7T 1M3",
    "addr:housenumber":"701",
    "addr:postcode":"n7t 1m3",
    "addr:street":"Ontario St",
    "iso:country":"CA",
    "sg:address":"701 Ontario St",
    "sg:city":"Sarnia",
    "sg:classifiers":[
        {
            "category":"Health Services",
            "subcategory":"Clinic",
            "type":"Services"
        }
    ],
    "sg:phone":"+1 519 736 9218",
    "sg:postcode":"N7T 1M3",
    "sg:province":"ON",
    "sg:tags":[
        "aid",
        "first"
    ],
    "wof:name":"St John Ambulance",
    "wof:placetype":"venue"
},
  "geometry": {"coordinates":[-82.3869400024,42.9622688293],"type":"Point"}
}