{
  "type": "Feature",
  "properties": {
    "addr:full":"Scarborough ON M1P 3C3",
    "addr:postcode":"m1p 3c3",
    "iso:country":"CA",
    "sg:city":"Scarborough",
    "sg:classifiers":[
        {
            "category":"Retail",
            "subcategory":"Auto Repair",
            "type":"Services"
        }
    ],
    "sg:phone":"+1 416 285 9816",
    "sg:postcode":"M1P 3C3",
    "sg:province":"ON",
    "sg:tags":[
        "repairing",
        "automobile"
    ],
    "wof:name":"Alfa Auto Clinic",
    "wof:placetype":"venue"
},
  "geometry": {"coordinates":[-79.266502,43.755005],"type":"Point"}
}