{
  "type": "Feature",
  "properties": {
    "addr:full":"664 Annette St Toronto ON M6S 2C8",
    "addr:housenumber":"664",
    "addr:postcode":"m6s 2c8",
    "addr:street":"Annette St",
    "iso:country":"CA",
    "sg:address":"664 Annette St",
    "sg:city":"Toronto",
    "sg:classifiers":[
        {
            "category":"Home & Garden",
            "subcategory":"Garden Supply",
            "type":"Retail Goods"
        }
    ],
    "sg:phone":"+1 416 766 1960",
    "sg:postcode":"M6S 2C8",
    "sg:province":"ON",
    "sg:tags":[
        "lawn",
        "center"
    ],
    "wof:name":"Windergarden",
    "wof:placetype":"venue"
},
  "geometry": {"coordinates":[-79.48406199999999,43.659225],"type":"Point"}
}