{
  "type": "Feature",
  "properties": {
    "iso:country":"CA",
    "sg:address":"5404 Hwy 3 Exit 9",
    "sg:city":"Chester Basin",
    "sg:classifiers":[
        {
            "category":"Autos & Motor Vehicles",
            "subcategory":"Fuel & Gas Station",
            "type":"Retail Goods"
        }
    ],
    "sg:phone":"+1 902 275 5388",
    "sg:postcode":"B0J 1K0",
    "sg:province":"NS",
    "sg:tags":[
        "oil"
    ],
    "wof:name":"Chester Basin Petro-Canada Svc",
    "wof:placetype":"venue"
},
  "geometry": {"coordinates":[-64.3093338013,44.5633621216],"type":"Point"}
}