{
  "type": "Feature",
  "properties": {
    "addr:full":"101 Water St W Brockville ON K6V 3M1",
    "addr:housenumber":"101",
    "addr:postcode":"k6v 3m1",
    "addr:street":"Water St W",
    "iso:country":"CA",
    "sg:address":"101 Water St W",
    "sg:city":"Brockville",
    "sg:classifiers":[
        {
            "category":"Building & Trades",
            "subcategory":"Electrical",
            "type":"Services"
        }
    ],
    "sg:phone":"+1 613 342 9652",
    "sg:postcode":"K6V 3M1",
    "sg:province":"ON",
    "sg:tags":[
        "equipment",
        "telecommunication"
    ],
    "wof:name":"Eastern Independent Telecom",
    "wof:placetype":"venue"
},
  "geometry": {"coordinates":[-75.686325,44.586548],"type":"Point"}
}