{
  "type": "Feature",
  "properties": {
    "addr:full":"Vancouver BC V6B 2K4",
    "addr:postcode":"v6b 2k4",
    "iso:country":"CA",
    "sg:city":"Vancouver",
    "sg:classifiers":[
        {
            "category":"Travel",
            "subcategory":"Travel Agent",
            "type":"Entertainment"
        }
    ],
    "sg:phone":"+1 604 408 1099",
    "sg:postcode":"V6B 2K4",
    "sg:province":"BC",
    "sg:tags":[
        "bureau",
        "agency",
        "tours"
    ],
    "wof:name":"Entree Canada",
    "wof:placetype":"venue"
},
  "geometry": {"coordinates":[-123.10610200000001,49.284122],"type":"Point"}
}