{
  "type": "Feature",
  "properties": {
    "addr:full":"647 Rue Principale Saint-Etienne-DE-Lauzon QC G6J 1H3",
    "addr:housenumber":"647",
    "addr:postcode":"g6j 1h3",
    "addr:street":"Rue Principale",
    "iso:country":"CA",
    "sg:address":"647 Rue Principale",
    "sg:city":"Saint-Etienne-DE-Lauzon",
    "sg:classifiers":[
        {
            "category":"Social Services",
            "type":"Services"
        }
    ],
    "sg:phone":"+1 418 836 0468",
    "sg:postcode":"G6J 1H3",
    "sg:province":"QC",
    "sg:tags":[
        "organization",
        "welfare"
    ],
    "wof:name":"Service D'Entraide St-Etienne",
    "wof:placetype":"venue"
},
  "geometry": {"coordinates":[-71.297501,46.652561],"type":"Point"}
}