{
  "type": "Feature",
  "properties": {
    "iso:country":"CA",
    "sg:address":"9 Swansea Rd",
    "sg:city":"Markham",
    "sg:classifiers":[
        {
            "category":"Retail",
            "subcategory":"Repair Shop",
            "type":"Services"
        }
    ],
    "sg:phone":"+1 905 477 6346",
    "sg:postcode":"L3R 8Y4",
    "sg:province":"ON",
    "sg:tags":[
        "upholsterer"
    ],
    "wof:name":"Gus Interiors",
    "wof:placetype":"venue"
},
  "geometry": {"coordinates":[-79.29741668699999,43.8610877991],"type":"Point"}
}