{
  "type": "Feature",
  "properties": {
    "addr:full":"2287 Rue King O Sherbrooke QC J1J 2G2",
    "addr:housenumber":"2287",
    "addr:postcode":"j1j 2g2",
    "addr:street":"Rue King O",
    "iso:country":"CA",
    "sg:address":"2287 Rue King O",
    "sg:city":"Sherbrooke",
    "sg:classifiers":[
        {
            "category":"Shopping",
            "subcategory":"Shoes",
            "type":"Retail Goods"
        }
    ],
    "sg:phone":"+1 819 562 2244",
    "sg:postcode":"J1J 2G2",
    "sg:province":"QC",
    "wof:name":"Chaussures Gregoire Inc",
    "wof:placetype":"venue"
},
  "geometry": {"coordinates":[-71.928963,45.39856],"type":"Point"}
}