{
  "type": "Feature",
  "properties": {
    "addr:full":"181 Andrew St Newcastle ON L1B 1J9",
    "addr:housenumber":"181",
    "addr:postcode":"l1b 1j9",
    "addr:street":"Andrew St",
    "iso:country":"CA",
    "sg:address":"181 Andrew St",
    "sg:city":"Newcastle",
    "sg:classifiers":[
        {
            "category":"Autos & Motor Vehicles",
            "subcategory":"Auto Supplies",
            "type":"Retail Goods"
        }
    ],
    "sg:phone":"+1 905 987 2224",
    "sg:postcode":"L1B 1J9",
    "sg:province":"ON",
    "sg:tags":[
        "filter",
        "gas"
    ],
    "wof:name":"Filtakleen",
    "wof:placetype":"venue"
},
  "geometry": {"coordinates":[-78.5828704834,43.9220848083],"type":"Point"}
}