{
  "type": "Feature",
  "properties": {
    "addr:full":"Yellowknife NT X1A 3R9",
    "addr:postcode":"x1a 3r9",
    "iso:country":"CA",
    "sg:city":"Yellowknife",
    "sg:classifiers":[
        {
            "category":"Shopping",
            "subcategory":"Optical Goods",
            "type":"Retail Goods"
        }
    ],
    "sg:phone":"+1 867 669 2088",
    "sg:postcode":"X1A 3R9",
    "sg:province":"NT",
    "sg:tags":[
        "optician"
    ],
    "wof:name":"Family Vision Ctr",
    "wof:placetype":"venue"
},
  "geometry": {"coordinates":[-114.41168999999999,62.445244],"type":"Point"}
}