{
  "type": "Feature",
  "properties": {
    "addr:full":"15 Akins Dr St Albert AB T8N 2H6",
    "addr:housenumber":"15",
    "addr:postcode":"t8n 2h6",
    "addr:street":"Akins Dr",
    "iso:country":"CA",
    "sg:address":"15 Akins Dr",
    "sg:city":"St Albert",
    "sg:classifiers":[
        {
            "category":"Real Estate",
            "subcategory":"Real Estate Agent",
            "type":"Services"
        }
    ],
    "sg:phone":"+1 780 458 9168",
    "sg:postcode":"T8N 2H6",
    "sg:province":"AB",
    "sg:tags":[
        "inspection"
    ],
    "wof:name":"Madsen Technical Svc Inc",
    "wof:placetype":"venue"
},
  "geometry": {"coordinates":[-113.595207214,53.6308250427],"type":"Point"}
}