{
  "type": "Feature",
  "properties": {
    "addr:full":"2424 Industrial St Burlington ON L7P 1A5",
    "addr:housenumber":"2424",
    "addr:postcode":"l7p 1a5",
    "addr:street":"Industrial St",
    "iso:country":"CA",
    "sg:address":"2424 Industrial St",
    "sg:city":"Burlington",
    "sg:classifiers":[
        {
            "category":"Government",
            "subcategory":"Office",
            "type":"Public Place"
        }
    ],
    "sg:phone":"+1 905 335 3030",
    "sg:postcode":"L7P 1A5",
    "sg:province":"ON",
    "sg:tags":[
        "village"
    ],
    "wof:name":"Burlington Animal Shelter",
    "wof:placetype":"venue"
},
  "geometry": {"coordinates":[-79.8101654053,43.3517494202],"type":"Point"}
}