{
  "type": "Feature",
  "properties": {
    "addr:full":"3375 Dunmore Rd SE Medicine Hat AB T1B 3R2",
    "addr:housenumber":"3375",
    "addr:postcode":"t1b 3r2",
    "addr:street":"Dunmore Rd Se",
    "iso:country":"CA",
    "sg:address":"3375 Dunmore Rd SE",
    "sg:city":"Medicine Hat",
    "sg:classifiers":[
        {
            "category":"Restaurant",
            "type":"Food & Drink"
        }
    ],
    "sg:phone":"+1 403 529 2002",
    "sg:postcode":"T1B 3R2",
    "sg:province":"AB",
    "wof:name":"Mc Donald's",
    "wof:placetype":"venue"
},
  "geometry": {"coordinates":[-110.64323400000001,50.004967],"type":"Point"}
}