{
  "type": "Feature",
  "properties": {
    "addr:full":"Dartmouth NS B2Y 2K2",
    "addr:postcode":"b2y 2k2",
    "iso:country":"CA",
    "sg:city":"Dartmouth",
    "sg:classifiers":[
        {
            "category":"Personal",
            "subcategory":"Beauty Salon",
            "type":"Services"
        }
    ],
    "sg:phone":"+1 902 464 9390",
    "sg:postcode":"B2Y 2K2",
    "sg:province":"NS",
    "wof:name":"Inclination Hair Design",
    "wof:placetype":"venue"
},
  "geometry": {"coordinates":[-63.551651001,44.6612701416],"type":"Point"}
}