{
  "type": "Feature",
  "properties": {
    "iso:country":"CA",
    "sg:city":"Kitchener",
    "sg:classifiers":[
        {
            "category":"Health Services",
            "subcategory":"Doctor",
            "type":"Services"
        }
    ],
    "sg:phone":"+1 519 579 2020",
    "sg:postcode":"N2M 5N6",
    "sg:province":"ON",
    "sg:tags":[
        "physician",
        "surgeon"
    ],
    "wof:name":"Jellie, Hugh MD",
    "wof:placetype":"venue"
},
  "geometry": {"coordinates":[-80.51509094239999,43.44921875],"type":"Point"}
}