{
  "type": "Feature",
  "properties": {
    "addr:full":"350 Lodge Ave Winnipeg MB R3J 0S4",
    "addr:housenumber":"350",
    "addr:postcode":"r3j 0s4",
    "addr:street":"Lodge Ave",
    "iso:country":"CA",
    "sg:address":"350 Lodge Ave",
    "sg:city":"Winnipeg",
    "sg:classifiers":[
        {
            "category":"Education",
            "subcategory":"School",
            "type":"Public Place"
        }
    ],
    "sg:phone":"+1 204 837 1321",
    "sg:postcode":"R3J 0S4",
    "sg:province":"MB",
    "wof:name":"Silver Heights Collegiate",
    "wof:placetype":"venue"
},
  "geometry": {"coordinates":[-97.259079,49.879787],"type":"Point"}
}