{
  "type": "Feature",
  "properties": {
    "addr:full":"704 Osborne St Winnipeg MB R3L 2B9",
    "addr:housenumber":"704",
    "addr:postcode":"r3l 2b9",
    "addr:street":"Osborne St",
    "iso:country":"CA",
    "sg:address":"704 Osborne St",
    "sg:city":"Winnipeg",
    "sg:classifiers":[
        {
            "category":"Health Services",
            "subcategory":"Doctor",
            "type":"Services"
        }
    ],
    "sg:phone":"+1 204 474 1424",
    "sg:postcode":"R3L 2B9",
    "sg:province":"MB",
    "sg:tags":[
        "dentist"
    ],
    "wof:name":"Cooke, William DDS",
    "wof:placetype":"venue"
},
  "geometry": {"coordinates":[-97.13179,49.862114],"type":"Point"}
}