{
  "type": "Feature",
  "properties": {
    "addr:full":"154 Main St W Listowel ON N4W 1A1",
    "addr:housenumber":"154",
    "addr:postcode":"n4w 1a1",
    "addr:street":"Main St W",
    "iso:country":"CA",
    "sg:address":"154 Main St W",
    "sg:city":"Listowel",
    "sg:classifiers":[
        {
            "category":"Shopping",
            "subcategory":"Used Merchandise",
            "type":"Retail Goods"
        }
    ],
    "sg:phone":"+1 519 291 9292",
    "sg:postcode":"N4W 1A1",
    "sg:province":"ON",
    "sg:tags":[
        "shop",
        "consignment"
    ],
    "wof:name":"Clothing Loft",
    "wof:placetype":"venue"
},
  "geometry": {"coordinates":[-80.95391100000001,43.731712],"type":"Point"}
}