{
  "type": "Feature",
  "properties": {
    "iso:country":"CA",
    "sg:address":"2146 Queen St E",
    "sg:city":"Toronto",
    "sg:classifiers":[
        {
            "category":"Retail",
            "subcategory":"Laundry & Dry Cleaning",
            "type":"Services"
        }
    ],
    "sg:phone":"+1 416 690 7977",
    "sg:postcode":"M4E 1E3",
    "sg:province":"ON",
    "sg:tags":[
        "cleaners"
    ],
    "wof:name":"Metro Cleaners",
    "wof:placetype":"venue"
},
  "geometry": {"coordinates":[-79.2930221558,43.671672821],"type":"Point"}
}