{
  "type": "Feature",
  "properties": {
    "addr:full":"7583 Edmonds St Burnaby BC V3N 1B5",
    "addr:housenumber":"7583",
    "addr:postcode":"v3n 1b5",
    "addr:street":"Edmonds St",
    "iso:country":"CA",
    "sg:address":"7583 Edmonds St",
    "sg:city":"Burnaby",
    "sg:classifiers":[
        {
            "category":"Retail",
            "subcategory":"Laundry & Dry Cleaning",
            "type":"Services"
        }
    ],
    "sg:phone":"+1 604 524 5624",
    "sg:postcode":"V3N 1B5",
    "sg:province":"BC",
    "sg:tags":[
        "cleaners"
    ],
    "wof:name":"Tuesdays Drycleaners",
    "wof:placetype":"venue"
},
  "geometry": {"coordinates":[-122.94355,49.222855],"type":"Point"}
}