{
  "type": "Feature",
  "properties": {
    "addr:full":"Edmonton AB T5J 2Y2",
    "addr:postcode":"t5j 2y2",
    "iso:country":"CA",
    "sg:city":"Edmonton",
    "sg:classifiers":[
        {
            "category":"Professional",
            "subcategory":"Accounting & Tax Preparation",
            "type":"Services"
        }
    ],
    "sg:phone":"+1 780 423 4272",
    "sg:postcode":"T5J 2Y2",
    "sg:province":"AB",
    "sg:tags":[
        "accountant"
    ],
    "wof:name":"Hodge, Gordon E",
    "wof:placetype":"venue"
},
  "geometry": {"coordinates":[-113.502685547,53.5399627686],"type":"Point"}
}