{
  "type": "Feature",
  "properties": {
    "addr:full":"6 Main St Fife Lake SK S0H 1N0",
    "addr:housenumber":"6",
    "addr:postcode":"s0h 1n0",
    "addr:street":"Main St",
    "iso:country":"CA",
    "sg:address":"6 Main St",
    "sg:city":"Fife Lake",
    "sg:classifiers":[
        {
            "category":"Travel",
            "subcategory":"Hotels & Motels",
            "type":"Entertainment"
        }
    ],
    "sg:phone":"+1 306 476 2605",
    "sg:postcode":"S0H 1N0",
    "sg:province":"SK",
    "wof:name":"Fife Lake Hotel",
    "wof:placetype":"venue"
},
  "geometry": {"coordinates":[-105.72783699999999,49.192696],"type":"Point"}
}