{
  "type": "Feature",
  "properties": {
    "addr:full":"816 George St Hearst ON P0L 1N0",
    "addr:housenumber":"816",
    "addr:postcode":"p0l 1n0",
    "addr:street":"George St",
    "iso:country":"CA",
    "sg:address":"816 George St",
    "sg:city":"Hearst",
    "sg:classifiers":[
        {
            "category":"Shopping",
            "subcategory":"Computers & Home Electronics",
            "type":"Retail Goods"
        }
    ],
    "sg:phone":"+1 705 362 5250",
    "sg:postcode":"P0L 1N0",
    "sg:province":"ON",
    "sg:tags":[
        "equipment",
        "video"
    ],
    "wof:name":"Video Plus",
    "wof:placetype":"venue"
},
  "geometry": {"coordinates":[-83.6630783081,49.6889419556],"type":"Point"}
}