{
  "type": "Feature",
  "properties": {
    "addr:full":"273 Boul Des Bois-Francs S Victoriaville QC G6P 4S9",
    "addr:housenumber":"273",
    "addr:postcode":"g6p 4s9",
    "addr:street":"Boul Des Bois-Francs S",
    "iso:country":"CA",
    "sg:address":"273 Boul Des Bois-Francs S",
    "sg:city":"Victoriaville",
    "sg:classifiers":[
        {
            "category":"Professional",
            "subcategory":"Computer Services",
            "type":"Services"
        }
    ],
    "sg:phone":"+1 819 752 7171",
    "sg:postcode":"G6P 4S9",
    "sg:province":"QC",
    "sg:tags":[
        "consultant"
    ],
    "wof:name":"Equipements Mm",
    "wof:placetype":"venue"
},
  "geometry": {"coordinates":[-71.944473,46.055],"type":"Point"}
}