{
  "type": "Feature",
  "properties": {
    "iso:country":"CA",
    "sg:address":"159 Rue Principale",
    "sg:city":"Saint-Benoit-Labre",
    "sg:classifiers":[
        {
            "category":"Food & Beverages",
            "subcategory":"Groceries & Convenience Stores",
            "type":"Retail Goods"
        }
    ],
    "sg:phone":"+1 418 228 9633",
    "sg:postcode":"G0M 1P0",
    "sg:province":"QC",
    "wof:name":"Robert Cloutier Enr",
    "wof:placetype":"venue"
},
  "geometry": {"coordinates":[-70.7910003662,46.0685539246],"type":"Point"}
}