{
  "type": "Feature",
  "properties": {
    "addr:full":"833 219 Rte Hemmingford QC J0L 1H0",
    "addr:housenumber":"219",
    "addr:postcode":"j0l 1h0",
    "addr:street":"Rte",
    "iso:country":"CA",
    "sg:address":"833 219 Rte",
    "sg:city":"Hemmingford",
    "sg:classifiers":[
        {
            "category":"Retail",
            "subcategory":"Auto Repair",
            "type":"Services"
        }
    ],
    "sg:phone":"+1 450 247 2232",
    "sg:postcode":"J0L 1H0",
    "sg:province":"QC",
    "sg:tags":[
        "body",
        "automobile",
        "painting"
    ],
    "wof:name":"St-Hilaire Benoit",
    "wof:placetype":"venue"
},
  "geometry": {"coordinates":[-73.580765,45.099941],"type":"Point"}
}