{
  "type": "Feature",
  "properties": {
    "addr:full":"107 Baxter St Langham SK S0K 2L0",
    "addr:housenumber":"107",
    "addr:postcode":"s0k 2l0",
    "addr:street":"Baxter St",
    "iso:country":"CA",
    "sg:address":"107 Baxter St",
    "sg:city":"Langham",
    "sg:classifiers":[
        {
            "category":"Building & Trades",
            "subcategory":"Construction",
            "type":"Services"
        }
    ],
    "sg:phone":"+1 306 283 4818",
    "sg:postcode":"S0K 2L0",
    "sg:province":"SK",
    "sg:tags":[
        "general",
        "road",
        "contractor"
    ],
    "wof:name":"Nemanishen Contracting Ltd",
    "wof:placetype":"venue"
},
  "geometry": {"coordinates":[-106.958190918,52.3611793518],"type":"Point"}
}