{
  "type": "Feature",
  "properties": {
    "addr:full":"1389 Quartz Rd Cache Creek BC V0K 1H0",
    "addr:housenumber":"1389",
    "addr:postcode":"v0k 1h0",
    "addr:street":"Quartz Rd",
    "iso:country":"CA",
    "sg:address":"1389 Quartz Rd",
    "sg:city":"Cache Creek",
    "sg:classifiers":[
        {
            "category":"Government",
            "subcategory":"Office",
            "type":"Public Place"
        }
    ],
    "sg:phone":"+1 250 457 6237",
    "sg:postcode":"V0K 1H0",
    "sg:province":"BC",
    "sg:tags":[
        "village"
    ],
    "wof:name":"Cache Creek Village Clerk",
    "wof:placetype":"venue"
},
  "geometry": {"coordinates":[-121.322975,50.811008],"type":"Point"}
}