{
  "type": "Feature",
  "properties": {
    "addr:full":"101 Rue Oliver Cowansville QC J2K 1H7",
    "addr:housenumber":"101",
    "addr:postcode":"j2k 1h7",
    "addr:street":"Rue Oliver",
    "iso:country":"CA",
    "sg:address":"101 Rue Oliver",
    "sg:city":"Cowansville",
    "sg:classifiers":[
        {
            "category":"Retail",
            "subcategory":"Laundry & Dry Cleaning",
            "type":"Services"
        }
    ],
    "sg:phone":"+1 450 263 1198",
    "sg:postcode":"J2K 1H7",
    "sg:province":"QC",
    "sg:tags":[
        "cleaners"
    ],
    "wof:name":"Nettoyeur A Sec Houle",
    "wof:placetype":"venue"
},
  "geometry": {"coordinates":[-72.7497177124,45.208694458],"type":"Point"}
}