{
  "type": "Feature",
  "properties": {
    "addr:full":"1400 Av DE Dieppe Alma QC G8C 1J3",
    "addr:housenumber":"1400",
    "addr:postcode":"g8c 1j3",
    "addr:street":"Av De Dieppe",
    "iso:country":"CA",
    "sg:address":"1400 Av DE Dieppe",
    "sg:city":"Alma",
    "sg:classifiers":[
        {
            "category":"Wholesale",
            "subcategory":"Electrical",
            "type":"Manufacturing & Wholesale Goods"
        }
    ],
    "sg:phone":"+1 418 480 2915",
    "sg:postcode":"G8C 1J3",
    "sg:province":"QC",
    "sg:tags":[
        "communication",
        "radio",
        "system"
    ],
    "wof:name":"Communication Provincial 2000",
    "wof:placetype":"venue"
},
  "geometry": {"coordinates":[-71.6413116455,48.5273628235],"type":"Point"}
}