{
  "type": "Feature",
  "properties": {
    "addr:full":"774 Rue Cowie Granby QC J2G 3Y1",
    "addr:housenumber":"774",
    "addr:postcode":"j2g 3y1",
    "addr:street":"Rue Cowie",
    "iso:country":"CA",
    "sg:address":"774 Rue Cowie",
    "sg:city":"Granby",
    "sg:classifiers":[
        {
            "category":"Professional",
            "subcategory":"Business Services",
            "type":"Services"
        }
    ],
    "sg:phone":"+1 450 378 5518",
    "sg:postcode":"J2G 3Y1",
    "sg:province":"QC",
    "sg:tags":[
        "water",
        "treatment"
    ],
    "wof:name":"Pompes Caron Inc",
    "wof:placetype":"venue"
},
  "geometry": {"coordinates":[-72.7537689209,45.3943214417],"type":"Point"}
}