{
  "type": "Feature",
  "properties": {
    "addr:full":"8181 Cambie Rd Richmond BC V6X 3X9",
    "addr:housenumber":"8181",
    "addr:postcode":"v6x 3x9",
    "addr:street":"Cambie Rd",
    "iso:country":"CA",
    "sg:address":"8181 Cambie Rd",
    "sg:city":"Richmond",
    "sg:classifiers":[
        {
            "category":"Professional",
            "subcategory":"Business Services",
            "type":"Services"
        }
    ],
    "sg:phone":"+1 604 276 8181",
    "sg:postcode":"V6X 3X9",
    "sg:province":"BC",
    "sg:tags":[
        "conference",
        "motel",
        "hotel",
        "center"
    ],
    "wof:name":"Radisson President Hotel",
    "wof:placetype":"venue"
},
  "geometry": {"coordinates":[-123.13400300000001,49.184811],"type":"Point"}
}