{
  "type": "Feature",
  "properties": {
    "addr:full":"15884 112 Ave Surrey BC V4N 1J1",
    "addr:housenumber":"15884",
    "addr:postcode":"v4n 1j1",
    "addr:street":"112 Ave",
    "iso:country":"CA",
    "sg:address":"15884 112 Ave",
    "sg:city":"Surrey",
    "sg:classifiers":[
        {
            "category":"Building & Trades",
            "subcategory":"Construction",
            "type":"Services"
        }
    ],
    "sg:phone":"+1 604 583 2400",
    "sg:postcode":"V4N 1J1",
    "sg:province":"BC",
    "sg:tags":[
        "repairing",
        "remodeling",
        "contractor"
    ],
    "wof:name":"Korecki Fiberglass Contracting",
    "wof:placetype":"venue"
},
  "geometry": {"coordinates":[-122.781784,49.20594],"type":"Point"}
}