{
  "type": "Feature",
  "properties": {
    "iso:country":"CA",
    "sg:address":"RR 7 STN Main",
    "sg:city":"St Marys",
    "sg:classifiers":[
        {
            "category":"Building & Trades",
            "subcategory":"Electrical",
            "type":"Services"
        }
    ],
    "sg:phone":"+1 519 284 1125",
    "sg:postcode":"N4X 1C9",
    "sg:province":"ON",
    "sg:tags":[
        "electric",
        "contractor"
    ],
    "wof:name":"Cubberley Electric",
    "wof:placetype":"venue"
},
  "geometry": {"coordinates":[-81.1414260864,43.2594947815],"type":"Point"}
}