{
  "type": "Feature",
  "properties": {
    "addr:full":"7132 Kerr St Vancouver BC V5S 4W2",
    "addr:housenumber":"7132",
    "addr:postcode":"v5s 4w2",
    "addr:street":"Kerr St",
    "iso:country":"CA",
    "sg:address":"7132 Kerr St",
    "sg:city":"Vancouver",
    "sg:classifiers":[
        {
            "category":"Retail",
            "subcategory":"Laundry & Dry Cleaning",
            "type":"Services"
        }
    ],
    "sg:phone":"+1 604 435 9748",
    "sg:postcode":"V5S 4W2",
    "sg:province":"BC",
    "sg:tags":[
        "cleaners"
    ],
    "wof:name":"Champlain Mall Cleaners",
    "wof:placetype":"venue"
},
  "geometry": {"coordinates":[-123.041183,49.218838],"type":"Point"}
}