{
  "type": "Feature",
  "properties": {
    "addr:full":"1424 Clarke Rd London ON N5V 5B9",
    "addr:housenumber":"1424",
    "addr:postcode":"n5v 5b9",
    "addr:street":"Clarke Rd",
    "iso:country":"CA",
    "sg:address":"1424 Clarke Rd",
    "sg:city":"London",
    "sg:classifiers":[
        {
            "category":"Government",
            "subcategory":"Office",
            "type":"Public Place"
        }
    ],
    "sg:phone":"+1 519 451 2800",
    "sg:postcode":"N5V 5B9",
    "sg:province":"ON",
    "sg:tags":[
        "village"
    ],
    "wof:name":"Upper Thames River Cnsrvtn",
    "wof:placetype":"venue"
},
  "geometry": {"coordinates":[-81.19096374510001,43.0346832275],"type":"Point"}
}