{
  "type": "Feature",
  "properties": {
    "addr:full":"1225 Rue DE Conde Montreal QC H3K 2E4",
    "addr:housenumber":"1225",
    "addr:postcode":"h3k 2e4",
    "addr:street":"Rue De Conde",
    "iso:country":"CA",
    "sg:address":"1225 Rue DE Conde",
    "sg:city":"Montreal",
    "sg:classifiers":[
        {
            "category":"Manufacturing",
            "subcategory":"Food",
            "type":"Manufacturing & Wholesale Goods"
        }
    ],
    "sg:phone":"+1 514 935 8887",
    "sg:postcode":"H3K 2E4",
    "sg:province":"QC",
    "sg:tags":[
        "cocoa",
        "chocolate"
    ],
    "wof:name":"Chocolats Privilege Inc",
    "wof:placetype":"venue"
},
  "geometry": {"coordinates":[-73.558655,45.48555],"type":"Point"}
}