{
  "type": "Feature",
  "properties": {
    "iso:country":"CA",
    "sg:address":"63 Hillsdale Ave E",
    "sg:city":"Toronto",
    "sg:classifiers":[
        {
            "category":"Health Services",
            "subcategory":"Health Practitioner",
            "type":"Services"
        }
    ],
    "sg:phone":"+1 416 486 1788",
    "sg:postcode":"M4S 1T4",
    "sg:province":"ON",
    "sg:tags":[
        "psychotherapist",
        "surgeon",
        "physician"
    ],
    "wof:name":"Dowsling, J L MD",
    "wof:placetype":"venue"
},
  "geometry": {"coordinates":[-79.39557647709999,43.7036781311],"type":"Point"}
}