{
  "type": "Feature",
  "properties": {
    "addr:full":"430 Boul Gouin Saint-Jean-Sur-Richelieu QC J3B 3E6",
    "addr:housenumber":"430",
    "addr:postcode":"j3b 3e6",
    "addr:street":"Boul Gouin",
    "iso:country":"CA",
    "sg:address":"430 Boul Gouin",
    "sg:city":"Saint-Jean-Sur-Richelieu",
    "sg:classifiers":[
        {
            "category":"Government",
            "subcategory":"Office",
            "type":"Public Place"
        }
    ],
    "sg:phone":"+1 450 346 4494",
    "sg:postcode":"J3B 3E6",
    "sg:province":"QC",
    "wof:name":"Canada Agriculture Canada",
    "wof:placetype":"venue"
},
  "geometry": {"coordinates":[-73.2730636597,45.3013267517],"type":"Point"}
}