{
  "type": "Feature",
  "properties": {
    "iso:country":"CA",
    "sg:address":"1143 Ivanhill Rd",
    "sg:city":"London",
    "sg:classifiers":[
        {
            "category":"Real Estate",
            "subcategory":"Real Estate Agent",
            "type":"Services"
        }
    ],
    "sg:phone":"+1 519 471 7249",
    "sg:postcode":"N6H 4B9",
    "sg:province":"ON",
    "wof:name":"Crystal Realty Corp",
    "wof:placetype":"venue"
},
  "geometry": {"coordinates":[-81.323837,42.98101],"type":"Point"}
}