{
  "type": "Feature",
  "properties": {
    "addr:full":"80 Rue Principale N #B Windsor QC J1S 2C6",
    "addr:housenumber":"80",
    "addr:postcode":"j1s 2c6",
    "addr:street":"Rue Principale N # B",
    "iso:country":"CA",
    "sg:address":"80 Rue Principale N #B",
    "sg:city":"Windsor",
    "sg:classifiers":[
        {
            "category":"Taxi",
            "type":"Transportation"
        }
    ],
    "sg:phone":"+1 819 845 2929",
    "sg:postcode":"J1S 2C6",
    "sg:province":"QC",
    "sg:tags":[
        "taxicab"
    ],
    "wof:name":"Taxi Windsor",
    "wof:placetype":"venue"
},
  "geometry": {"coordinates":[-72.006912,45.570187],"type":"Point"}
}