{
  "type": "Feature",
  "properties": {
    "addr:full":"403 Fletcher St Killarney MB R0K 1G0",
    "addr:housenumber":"403",
    "addr:postcode":"r0k 1g0",
    "addr:street":"Fletcher St",
    "iso:country":"CA",
    "sg:address":"403 Fletcher St",
    "sg:city":"Killarney",
    "sg:classifiers":[
        {
            "category":"Recreation",
            "type":"Entertainment"
        }
    ],
    "sg:phone":"+1 204 523 8372",
    "sg:postcode":"R0K 1G0",
    "sg:province":"MB",
    "sg:tags":[
        "hall",
        "auditorium"
    ],
    "wof:name":"Elk's Lodge Hall",
    "wof:placetype":"venue"
},
  "geometry": {"coordinates":[-99.669128,49.18277],"type":"Point"}
}