{
  "type": "Feature",
  "properties": {
    "addr:full":"1088 Kennedy Rue N Saint-Come-Liniere QC G0M 1J0",
    "addr:housenumber":"1088",
    "addr:postcode":"g0m 1j0",
    "addr:street":"Kennedy Rue N",
    "iso:country":"CA",
    "sg:address":"1088 Kennedy Rue N",
    "sg:city":"Saint-Come-Liniere",
    "sg:classifiers":[
        {
            "category":"Wholesale",
            "subcategory":"Machinery & Supplies",
            "type":"Manufacturing & Wholesale Goods"
        }
    ],
    "sg:phone":"+1 418 685 3982",
    "sg:postcode":"G0M 1J0",
    "sg:province":"QC",
    "sg:tags":[
        "heavy",
        "equipment",
        "repairing"
    ],
    "wof:name":"Bernard Diezel Inc",
    "wof:placetype":"venue"
},
  "geometry": {"coordinates":[-70.54650100000001,46.060261],"type":"Point"}
}