{
  "type": "Feature",
  "properties": {
    "addr:full":"5520 Calgary Trail NW Edmonton AB T6H 4K1",
    "addr:housenumber":"5520",
    "addr:postcode":"t6h 4k1",
    "addr:street":"Calgary Trail Nw",
    "iso:country":"CA",
    "sg:address":"5520 Calgary Trail NW",
    "sg:city":"Edmonton",
    "sg:classifiers":[
        {
            "category":"Autos & Motor Vehicles",
            "subcategory":"Fuel & Gas Station",
            "type":"Retail Goods"
        }
    ],
    "sg:phone":"+1 780 435 2611",
    "sg:postcode":"T6H 4K1",
    "sg:province":"AB",
    "sg:tags":[
        "oil"
    ],
    "wof:name":"Canadian Insta-Tune Ltd",
    "wof:placetype":"venue"
},
  "geometry": {"coordinates":[-113.496948,53.492493],"type":"Point"}
}