{
  "type": "Feature",
  "properties": {
    "addr:full":"143 Great Northern Rd # 202A Sault Ste Marie ON P6B 4Y9",
    "addr:housenumber":"143",
    "addr:postcode":"p6b 4y9",
    "addr:street":"Great Northern Rd # 202A",
    "iso:country":"CA",
    "sg:address":"143 Great Northern Rd # 202A",
    "sg:city":"Sault Ste Marie",
    "sg:classifiers":[
        {
            "category":"Wholesale",
            "subcategory":"Office Equipment",
            "type":"Manufacturing & Wholesale Goods"
        }
    ],
    "sg:phone":"+1 705 256 7144",
    "sg:postcode":"P6B 4Y9",
    "sg:province":"ON",
    "sg:tags":[
        "machine",
        "duplicating",
        "copying"
    ],
    "wof:name":"Superior Digital Solutions",
    "wof:placetype":"venue"
},
  "geometry": {"coordinates":[-84.319641,46.529755],"type":"Point"}
}