{
  "type": "Feature",
  "properties": {
    "addr:full":"16225 Stony Plain Rd NW Edmonton AB T5P 4A3",
    "addr:housenumber":"16225",
    "addr:postcode":"t5p 4a3",
    "addr:street":"Stony Plain Rd Nw",
    "iso:country":"CA",
    "sg:address":"16225 Stony Plain Rd NW",
    "sg:city":"Edmonton",
    "sg:classifiers":[
        {
            "category":"Shopping",
            "subcategory":"Florist",
            "type":"Retail Goods"
        }
    ],
    "sg:phone":"+1 780 489 6616",
    "sg:postcode":"T5P 4A3",
    "sg:province":"AB",
    "wof:name":"Flowers By Western",
    "wof:placetype":"venue"
},
  "geometry": {"coordinates":[-113.6014328,53.5411643982],"type":"Point"}
}