{
  "type": "Feature",
  "properties": {
    "addr:full":"933 Topsail Rd Mount Pearl NL A1N 3K1",
    "addr:housenumber":"933",
    "addr:postcode":"a1n 3k1",
    "addr:street":"Topsail Rd",
    "iso:country":"CA",
    "sg:address":"933 Topsail Rd",
    "sg:city":"Mount Pearl",
    "sg:classifiers":[
        {
            "category":"Autos & Motor Vehicles",
            "subcategory":"Automobile Sales",
            "type":"Retail Goods"
        }
    ],
    "sg:phone":"+1 709 368 2298",
    "sg:postcode":"A1N 3K1",
    "sg:province":"NL",
    "sg:tags":[
        "car",
        "dealer"
    ],
    "wof:name":"Car Max Used Cars & Trucks",
    "wof:placetype":"venue"
},
  "geometry": {"coordinates":[-52.8007469177,47.5233535767],"type":"Point"}
}