{
  "type": "Feature",
  "properties": {
    "addr:full":"Port Coquitlam BC V3C 2B2",
    "addr:postcode":"v3c 2b2",
    "iso:country":"CA",
    "sg:city":"Port Coquitlam",
    "sg:classifiers":[
        {
            "category":"Personal",
            "subcategory":"Barber",
            "type":"Services"
        }
    ],
    "sg:phone":"+1 604 941 6017",
    "sg:postcode":"V3C 2B2",
    "sg:province":"BC",
    "wof:name":"Prestige Barbers",
    "wof:placetype":"venue"
},
  "geometry": {"coordinates":[-122.779998779,49.2633666992],"type":"Point"}
}