{
  "type": "Feature",
  "properties": {
    "iso:country":"CA",
    "sg:address":"6488 Bay St",
    "sg:city":"West Vancouver",
    "sg:classifiers":[
        {
            "category":"Real Estate",
            "subcategory":"Architect",
            "type":"Services"
        }
    ],
    "sg:phone":"+1 604 921 8313",
    "sg:postcode":"V7W 2H1",
    "sg:province":"BC",
    "wof:name":"Weiser, David",
    "wof:placetype":"venue"
},
  "geometry": {"coordinates":[-123.276016235,49.3751144409],"type":"Point"}
}