{
  "type": "Feature",
  "properties": {
    "addr:full":"79 Boul Rene-Levesque E Quebec QC G1R 5N5",
    "addr:housenumber":"79",
    "addr:postcode":"g1r 5n5",
    "addr:street":"Boul Rene-Levesque E",
    "iso:country":"CA",
    "sg:address":"79 Boul Rene-Levesque E",
    "sg:city":"Quebec",
    "sg:classifiers":[
        {
            "category":"Professional",
            "subcategory":"Computer Services",
            "type":"Services"
        }
    ],
    "sg:phone":"+1 418 266 2900",
    "sg:postcode":"G1R 5N5",
    "sg:province":"QC",
    "sg:tags":[
        "processing",
        "datum"
    ],
    "wof:name":"Oracle Corporation Canada Inc",
    "wof:placetype":"venue"
},
  "geometry": {"coordinates":[-71.224442,46.805389],"type":"Point"}
}