{
  "type": "Feature",
  "properties": {
    "addr:full":"485 Washington St Elora ON N0B 1S0",
    "addr:housenumber":"485",
    "addr:postcode":"n0b 1s0",
    "addr:street":"Washington St",
    "iso:country":"CA",
    "sg:address":"485 Washington St",
    "sg:city":"Elora",
    "sg:classifiers":[
        {
            "category":"Wholesale",
            "subcategory":"Fruits & Vegetables",
            "type":"Manufacturing & Wholesale Goods"
        }
    ],
    "sg:phone":"+1 519 846 5553",
    "sg:postcode":"N0B 1S0",
    "sg:province":"ON",
    "sg:tags":[
        "shipper"
    ],
    "wof:name":"Ontario Potato Board",
    "wof:placetype":"venue"
},
  "geometry": {"coordinates":[-80.4463882446,43.6946029663],"type":"Point"}
}