{
  "type": "Feature",
  "properties": {
    "addr:full":"Burnaby BC V5H 4M2",
    "addr:postcode":"v5h 4m2",
    "iso:country":"CA",
    "sg:city":"Burnaby",
    "sg:classifiers":[
        {
            "category":"Professional",
            "subcategory":"Lawyer & Legal Services",
            "type":"Services"
        }
    ],
    "sg:phone":"+1 604 437 6611",
    "sg:postcode":"V5H 4M2",
    "sg:province":"BC",
    "sg:tags":[
        "attorney"
    ],
    "wof:name":"Mc Lean, Brent A",
    "wof:placetype":"venue"
},
  "geometry": {"coordinates":[-122.998886,49.228115],"type":"Point"}
}