{
  "type": "Feature",
  "properties": {
    "addr:full":"Oshawa ON L1H 8R3",
    "addr:postcode":"l1h 8r3",
    "iso:country":"CA",
    "sg:city":"Oshawa",
    "sg:classifiers":[
        {
            "category":"Building & Trades",
            "subcategory":"Landscaping Services",
            "type":"Services"
        }
    ],
    "sg:phone":"+1 905 579 9767",
    "sg:postcode":"L1H 8R3",
    "sg:province":"ON",
    "sg:tags":[
        "landscape",
        "contractor"
    ],
    "wof:name":"Jrc Groundskeeping",
    "wof:placetype":"venue"
},
  "geometry": {"coordinates":[-78.83543400000001,43.882641],"type":"Point"}
}