{
  "type": "Feature",
  "properties": {
    "addr:full":"325 Penniac Rd Penniac NB E3A 9B6",
    "addr:housenumber":"325",
    "addr:postcode":"e3a 9b6",
    "addr:street":"Penniac Rd",
    "iso:country":"CA",
    "sg:address":"325 Penniac Rd",
    "sg:city":"Penniac",
    "sg:classifiers":[
        {
            "category":"Manufacturing",
            "subcategory":"Printing",
            "type":"Manufacturing & Wholesale Goods"
        }
    ],
    "sg:phone":"+1 506 472 2086",
    "sg:postcode":"E3A 9B6",
    "sg:province":"NB",
    "sg:tags":[
        "printer"
    ],
    "wof:name":"Atlantic Gold Printing Ltd",
    "wof:placetype":"venue"
},
  "geometry": {"coordinates":[-66.56353799999999,46.03875],"type":"Point"}
}