{
  "type": "Feature",
  "properties": {
    "addr:full":"Bonnyville AB T9N 2H8",
    "addr:postcode":"t9n 2h8",
    "iso:country":"CA",
    "sg:city":"Bonnyville",
    "sg:classifiers":[
        {
            "category":"Real Estate",
            "subcategory":"Developer",
            "type":"Services"
        }
    ],
    "sg:phone":"+1 780 826 5340",
    "sg:postcode":"T9N 2H8",
    "sg:province":"AB",
    "sg:tags":[
        "mobile",
        "home"
    ],
    "wof:name":"Country Home Trailer Park",
    "wof:placetype":"venue"
},
  "geometry": {"coordinates":[-110.75366200000001,54.267956],"type":"Point"}
}