{
  "type": "Feature",
  "properties": {
    "iso:country":"CA",
    "sg:address":"484 Indian Meal Line",
    "sg:city":"Torbay",
    "sg:classifiers":[
        {
            "category":"Building & Trades",
            "subcategory":"Construction",
            "type":"Services"
        }
    ],
    "sg:phone":"+1 709 437 1878",
    "sg:postcode":"A1K 1G4",
    "sg:province":"NL",
    "sg:tags":[
        "roofing",
        "contractor"
    ],
    "wof:name":"New Tech Roofing Ltd",
    "wof:placetype":"venue"
},
  "geometry": {"coordinates":[-52.7766609192,47.6434936523],"type":"Point"}
}