{
  "type": "Feature",
  "properties": {
    "addr:full":"37 Mager Dr W Winnipeg MB R2M 0R9",
    "addr:housenumber":"37",
    "addr:postcode":"r2m 0r9",
    "addr:street":"Mager Dr W",
    "iso:country":"CA",
    "sg:address":"37 Mager Dr W",
    "sg:city":"Winnipeg",
    "sg:classifiers":[
        {
            "category":"Building & Trades",
            "subcategory":"Construction",
            "type":"Services"
        }
    ],
    "sg:phone":"+1 204 944 8521",
    "sg:postcode":"R2M 0R9",
    "sg:province":"MB",
    "sg:tags":[
        "layer",
        "carpet"
    ],
    "wof:name":"Masters Floor Covering Svc",
    "wof:placetype":"venue"
},
  "geometry": {"coordinates":[-97.1139678955,49.8604393005],"type":"Point"}
}