{
  "type": "Feature",
  "properties": {
    "addr:full":"19 Rue Paiement Sainte-Genevieve QC H9H 2S6",
    "addr:housenumber":"19",
    "addr:postcode":"h9h 2s6",
    "addr:street":"Rue Paiement",
    "iso:country":"CA",
    "sg:address":"19 Rue Paiement",
    "sg:city":"Sainte-Genevieve",
    "sg:classifiers":[
        {
            "category":"Shopping",
            "subcategory":"Computers & Home Electronics",
            "type":"Retail Goods"
        }
    ],
    "sg:phone":"+1 514 624 2925",
    "sg:postcode":"H9H 2S6",
    "sg:province":"QC",
    "sg:tags":[
        "software"
    ],
    "wof:name":"Systemes Informatiques Lars",
    "wof:placetype":"venue"
},
  "geometry": {"coordinates":[-73.866798,45.483135],"type":"Point"}
}