{
  "type": "Feature",
  "properties": {
    "addr:full":"1 Ch Tache O Saint-Hubert-Riviere-Du-Loup QC G0L 3L0",
    "addr:housenumber":"1",
    "addr:postcode":"g0l 3l0",
    "addr:street":"Ch Tache O Saint-Hubert-Riviere-Du-Loup",
    "iso:country":"CA",
    "sg:address":"1 Ch Tache O",
    "sg:city":"Saint-Hubert-Riviere-Du-Loup",
    "sg:classifiers":[
        {
            "category":"Organizations",
            "subcategory":"Religious Organization",
            "type":"Services"
        }
    ],
    "sg:phone":"+1 418 497 3530",
    "sg:postcode":"G0L 3L0",
    "sg:province":"QC",
    "sg:tags":[
        "church"
    ],
    "wof:name":"Presbytere St-Hubert",
    "wof:placetype":"venue"
},
  "geometry": {"coordinates":[-69.14767456049999,47.8149337769],"type":"Point"}
}