{
  "type": "Feature",
  "properties": {
    "addr:full":"Waterford ON N0E 1Y0",
    "addr:postcode":"n0e 1y0",
    "iso:country":"CA",
    "sg:city":"Waterford",
    "sg:classifiers":[
        {
            "category":"Autos & Motor Vehicles",
            "subcategory":"Recreational Vehicle Sales",
            "type":"Retail Goods"
        }
    ],
    "sg:phone":"+1 519 443 0291",
    "sg:postcode":"N0E 1Y0",
    "sg:province":"ON",
    "wof:name":"Adventure Rv Ctr",
    "wof:placetype":"venue"
},
  "geometry": {"coordinates":[-80.288605,42.925114],"type":"Point"}
}