{
  "type": "Feature",
  "properties": {
    "addr:full":"817 Rue Principale Cowansville QC J2K 1J8",
    "addr:housenumber":"817",
    "addr:postcode":"j2k 1j8",
    "addr:street":"Rue Principale",
    "iso:country":"CA",
    "sg:address":"817 Rue Principale",
    "sg:city":"Cowansville",
    "sg:classifiers":[
        {
            "category":"Travel",
            "subcategory":"Travel Agent",
            "type":"Entertainment"
        }
    ],
    "sg:phone":"+1 450 263 6531",
    "sg:postcode":"J2K 1J8",
    "sg:province":"QC",
    "sg:tags":[
        "agency",
        "bureau"
    ],
    "wof:name":"Agence DE Voyage Airtour Inc",
    "wof:placetype":"venue"
},
  "geometry": {"coordinates":[-72.721481,45.208862],"type":"Point"}
}