{
  "type": "Feature",
  "properties": {
    "addr:full":"2576 Rue Hochelaga Montreal QC H2K 1J6",
    "addr:housenumber":"2576",
    "addr:postcode":"h2k 1j6",
    "addr:street":"Rue Hochelaga",
    "iso:country":"CA",
    "sg:address":"2576 Rue Hochelaga",
    "sg:city":"Montreal",
    "sg:classifiers":[
        {
            "category":"Wholesale",
            "subcategory":"Electrical",
            "type":"Manufacturing & Wholesale Goods"
        }
    ],
    "sg:phone":"+1 514 526 8787",
    "sg:postcode":"H2K 1J6",
    "sg:province":"QC",
    "sg:tags":[
        "sound",
        "equipment",
        "system"
    ],
    "wof:name":"Sonomarc",
    "wof:placetype":"venue"
},
  "geometry": {"coordinates":[-73.558266,45.53561],"type":"Point"}
}