{
  "type": "Feature",
  "properties": {
    "iso:country":"CA",
    "sg:address":"2110 Highway 1",
    "sg:city":"Auburn",
    "sg:classifiers":[
        {
            "category":"Real Estate",
            "subcategory":"Real Estate Agent",
            "type":"Services"
        }
    ],
    "sg:phone":"+1 902 847 9336",
    "sg:postcode":"B0P 1A0",
    "sg:province":"NS",
    "wof:name":"Annapolis Valley Real Estate",
    "wof:placetype":"venue"
},
  "geometry": {"coordinates":[-64.863243103,45.0173187256],"type":"Point"}
}