{
  "type": "Feature",
  "properties": {
    "addr:full":"600 Welland Ave St Catharines ON L2M 5V6",
    "addr:housenumber":"600",
    "addr:postcode":"l2m 5v6",
    "addr:street":"Welland Ave",
    "iso:country":"CA",
    "sg:address":"600 Welland Ave",
    "sg:city":"St Catharines",
    "sg:classifiers":[
        {
            "category":"Real Estate",
            "subcategory":"Real Estate Agent",
            "type":"Services"
        }
    ],
    "sg:phone":"+1 905 646 4622",
    "sg:postcode":"L2M 5V6",
    "sg:province":"ON",
    "sg:tags":[
        "management"
    ],
    "wof:name":"I J Siegert Real Estate",
    "wof:placetype":"venue"
},
  "geometry": {"coordinates":[-79.20708500000001,43.177483],"type":"Point"}
}