{
  "type": "Feature",
  "properties": {
    "iso:country":"CA",
    "sg:city":"Castlegar",
    "sg:classifiers":[
        {
            "category":"Health Services",
            "subcategory":"Doctor",
            "type":"Services"
        }
    ],
    "sg:phone":"+1 250 365 7717",
    "sg:postcode":"V1N 2A1",
    "sg:province":"BC",
    "sg:tags":[
        "physician",
        "surgeon"
    ],
    "wof:name":"Vasil, L MD",
    "wof:placetype":"venue"
},
  "geometry": {"coordinates":[-117.664352417,49.3265533447],"type":"Point"}
}