{
  "type": "Feature",
  "properties": {
    "addr:full":"834 Baie DE Kipawa Kipawa QC J0Z 2H0",
    "addr:housenumber":"834",
    "addr:postcode":"j0z 2h0",
    "addr:street":"Baie De Kipawa",
    "iso:country":"CA",
    "sg:address":"834 Baie DE Kipawa",
    "sg:city":"Kipawa",
    "sg:classifiers":[
        {
            "category":"Travel",
            "subcategory":"Hotels & Motels",
            "type":"Entertainment"
        }
    ],
    "sg:phone":"+1 819 627 3722",
    "sg:postcode":"J0Z 2H0",
    "sg:province":"QC",
    "sg:tags":[
        "tourist",
        "boat",
        "accommodation"
    ],
    "wof:name":"Kipawa Outpost Houseboat Rntls",
    "wof:placetype":"venue"
},
  "geometry": {"coordinates":[-78.9880981445,46.7844276428],"type":"Point"}
}