{
  "type": "Feature",
  "properties": {
    "addr:full":"112 Main St Lintlaw SK S0A 2H0",
    "addr:housenumber":"112",
    "addr:postcode":"s0a 2h0",
    "addr:street":"Main St",
    "iso:country":"CA",
    "sg:address":"112 Main St",
    "sg:city":"Lintlaw",
    "sg:classifiers":[
        {
            "category":"Restaurant",
            "type":"Food & Drink"
        }
    ],
    "sg:phone":"+1 306 325 4610",
    "sg:postcode":"S0A 2H0",
    "sg:province":"SK",
    "wof:name":"Rocky Acres Store",
    "wof:placetype":"venue"
},
  "geometry": {"coordinates":[-103.247246,52.066792],"type":"Point"}
}