{
  "type": "Feature",
  "properties": {
    "iso:country":"CA",
    "sg:city":"Burnaby",
    "sg:classifiers":[
        {
            "category":"Professional",
            "subcategory":"Research",
            "type":"Services"
        }
    ],
    "sg:phone":"+1 604 435 5486",
    "sg:postcode":"V5J 4J2",
    "sg:province":"BC",
    "sg:tags":[
        "development",
        "laboratory"
    ],
    "wof:name":"Crrs Culture Regeneration",
    "wof:placetype":"venue"
},
  "geometry": {"coordinates":[-122.98841095,49.2204055786],"type":"Point"}
}