{
  "type": "Feature",
  "properties": {
    "addr:full":"50 Erie Blvd Port Rowan ON N0E 1M0",
    "addr:housenumber":"50",
    "addr:postcode":"n0e 1m0",
    "addr:street":"Erie Blvd",
    "iso:country":"CA",
    "sg:address":"50 Erie Blvd",
    "sg:city":"Port Rowan",
    "sg:classifiers":[
        {
            "category":"Travel",
            "subcategory":"Hotels & Motels",
            "type":"Entertainment"
        }
    ],
    "sg:phone":"+1 519 586 2301",
    "sg:postcode":"N0E 1M0",
    "sg:province":"ON",
    "wof:name":"Harbour Resort",
    "wof:placetype":"venue"
},
  "geometry": {"coordinates":[-80.4370498657,42.5783729553],"type":"Point"}
}