{
  "type": "Feature",
  "properties": {
    "addr:full":"4711 50 St Athabasca AB T9S 1A3",
    "addr:housenumber":"4711",
    "addr:postcode":"t9s 1a3",
    "addr:street":"50 St",
    "iso:country":"CA",
    "sg:address":"4711 50 St",
    "sg:city":"Athabasca",
    "sg:classifiers":[
        {
            "category":"Autos & Motor Vehicles",
            "subcategory":"Fuel & Gas Station",
            "type":"Retail Goods"
        }
    ],
    "sg:phone":"+1 780 675 4492",
    "sg:postcode":"T9S 1A3",
    "sg:province":"AB",
    "sg:tags":[
        "oil"
    ],
    "wof:name":"Fas Gas",
    "wof:placetype":"venue"
},
  "geometry": {"coordinates":[-113.286460877,54.7170295715],"type":"Point"}
}