{
  "type": "Feature",
  "properties": {
    "iso:country":"CA",
    "sg:city":"Toronto",
    "sg:classifiers":[
        {
            "category":"Professional",
            "subcategory":"Art Services",
            "type":"Services"
        }
    ],
    "sg:phone":"+1 416 588 1772",
    "sg:postcode":"M6P 4H3",
    "sg:province":"ON",
    "sg:tags":[
        "photographer"
    ],
    "wof:name":"B Mac Donald & Assoc",
    "wof:placetype":"venue"
},
  "geometry": {"coordinates":[-79.44841,43.666466],"type":"Point"}
}