{
  "type": "Feature",
  "properties": {
    "addr:full":"Montreal-Nord QC H1G 6L6",
    "addr:postcode":"h1g 6l6",
    "iso:country":"CA",
    "sg:city":"Montreal-Nord",
    "sg:classifiers":[
        {
            "category":"Health Services",
            "subcategory":"Doctor",
            "type":"Services"
        }
    ],
    "sg:phone":"+1 514 322 4790",
    "sg:postcode":"H1G 6L6",
    "sg:province":"QC",
    "sg:tags":[
        "dentist"
    ],
    "wof:name":"Centre Dentaire Gladu",
    "wof:placetype":"venue"
},
  "geometry": {"coordinates":[-73.62896000000001,45.598045],"type":"Point"}
}