{
  "type": "Feature",
  "properties": {
    "addr:full":"11733 87 Ave NW Edmonton AB T6G 0Y4",
    "addr:housenumber":"11733",
    "addr:postcode":"t6g 0y4",
    "addr:street":"87 Ave Nw",
    "iso:country":"CA",
    "sg:address":"11733 87 Ave NW",
    "sg:city":"Edmonton",
    "sg:classifiers":[
        {
            "category":"Organizations",
            "subcategory":"Religious Organization",
            "type":"Services"
        }
    ],
    "sg:phone":"+1 780 439 1470",
    "sg:postcode":"T6G 0Y4",
    "sg:province":"AB",
    "sg:tags":[
        "church"
    ],
    "wof:name":"St George's Anglican Church",
    "wof:placetype":"venue"
},
  "geometry": {"coordinates":[-113.53314209,53.522605896],"type":"Point"}
}