{
  "type": "Feature",
  "properties": {
    "addr:full":"3848 Rue Saint-Dominique Montreal QC H2W 2A3",
    "addr:housenumber":"3848",
    "addr:postcode":"h2w 2a3",
    "addr:street":"Rue Saint-Dominique",
    "iso:country":"CA",
    "sg:address":"3848 Rue Saint-Dominique",
    "sg:city":"Montreal",
    "sg:classifiers":[
        {
            "category":"Organizations",
            "subcategory":"Non-profit Organization",
            "type":"Services"
        }
    ],
    "sg:phone":"+1 514 849 0131",
    "sg:postcode":"H2W 2A3",
    "sg:province":"QC",
    "sg:tags":[
        "information",
        "treatment",
        "center",
        "smoker"
    ],
    "wof:name":"Nicotine Anonyme",
    "wof:placetype":"venue"
},
  "geometry": {"coordinates":[-73.5762023926,45.5160522461],"type":"Point"}
}