{
  "type": "Feature",
  "properties": {
    "iso:country":"CA",
    "sg:city":"Montreal",
    "sg:classifiers":[
        {
            "category":"Building & Trades",
            "subcategory":"Construction",
            "type":"Services"
        }
    ],
    "sg:phone":"+1 514 286 9228",
    "sg:postcode":"H3M 3E2",
    "sg:province":"QC",
    "sg:tags":[
        "excavating",
        "contractor"
    ],
    "wof:name":"Info-Excavation",
    "wof:placetype":"venue"
},
  "geometry": {"coordinates":[-73.678719,45.5368],"type":"Point"}
}