{
  "type": "Feature",
  "properties": {
    "iso:country":"CA",
    "sg:address":"20 Ch Des Iles-Yale",
    "sg:city":"Saint-Eustache",
    "sg:classifiers":[
        {
            "category":"Health Services",
            "subcategory":"Nursing And Care Facility",
            "type":"Services"
        }
    ],
    "sg:phone":"+1 450 472 0263",
    "sg:postcode":"J7P 5M6",
    "sg:province":"QC",
    "sg:tags":[
        "home",
        "convalescent",
        "rest"
    ],
    "wof:name":"Maison DE L'Ile Ctr DE",
    "wof:placetype":"venue"
},
  "geometry": {"coordinates":[-73.8526687622,45.5781364441],"type":"Point"}
}