{
  "type": "Feature",
  "properties": {
    "addr:full":"4500 Boul DE Port-Royal Becancour QC G9H 1Z4",
    "addr:housenumber":"4500",
    "addr:postcode":"g9h 1z4",
    "addr:street":"Boul De Port-Royal Becancour",
    "iso:country":"CA",
    "sg:address":"4500 Boul DE Port-Royal",
    "sg:city":"Becancour",
    "sg:classifiers":[
        {
            "category":"Shopping",
            "subcategory":"Jewelry",
            "type":"Retail Goods"
        }
    ],
    "sg:phone":"+1 819 233 2348",
    "sg:postcode":"G9H 1Z4",
    "sg:province":"QC",
    "sg:tags":[
        "jeweler"
    ],
    "wof:name":"Bijouterie Capri",
    "wof:placetype":"venue"
},
  "geometry": {"coordinates":[-72.51067399999999,46.270935],"type":"Point"}
}