{
  "type": "Feature",
  "properties": {
    "addr:full":"Scarborough ON M1H 2V9",
    "addr:postcode":"m1h 2v9",
    "iso:country":"CA",
    "sg:city":"Scarborough",
    "sg:classifiers":[
        {
            "category":"Building & Trades",
            "subcategory":"Construction",
            "type":"Services"
        }
    ],
    "sg:phone":"+1 416 438 6389",
    "sg:postcode":"M1H 2V9",
    "sg:province":"ON",
    "sg:tags":[
        "painter"
    ],
    "wof:name":"Precise Finishers Ltd",
    "wof:placetype":"venue"
},
  "geometry": {"coordinates":[-79.2383117676,43.7751655579],"type":"Point"}
}