{
  "type": "Feature",
  "properties": {
    "addr:full":"145 Rue Saint-Paul Quebec QC G1K 3V8",
    "addr:housenumber":"145",
    "addr:postcode":"g1k 3v8",
    "addr:street":"Rue Saint-Paul",
    "iso:country":"CA",
    "sg:address":"145 Rue Saint-Paul",
    "sg:city":"Quebec",
    "sg:classifiers":[
        {
            "category":"Shopping",
            "subcategory":"Used Merchandise",
            "type":"Retail Goods"
        }
    ],
    "sg:phone":"+1 418 692 5318",
    "sg:postcode":"G1K 3V8",
    "sg:province":"QC",
    "sg:tags":[
        "antique"
    ],
    "wof:name":"Boutique A LA Capucine",
    "wof:placetype":"venue"
},
  "geometry": {"coordinates":[-71.2059555054,46.8164176941],"type":"Point"}
}