{
  "type": "Feature",
  "properties": {
    "iso:country":"CA",
    "sg:address":"1800 Saskatchewan Ave E",
    "sg:city":"Portage LA Prairie",
    "sg:classifiers":[
        {
            "category":"Building & Trades",
            "subcategory":"Plumbing",
            "type":"Services"
        }
    ],
    "sg:phone":"+1 204 857 6833",
    "sg:postcode":"R1N 0N9",
    "sg:province":"MB",
    "sg:tags":[
        "contractor"
    ],
    "wof:name":"Cobbe's Plumbing & Heating Ltd",
    "wof:placetype":"venue"
},
  "geometry": {"coordinates":[-98.3134384155,49.9718742371],"type":"Point"}
}