{
  "type": "Feature",
  "properties": {
    "addr:full":"85 Albert St #100 Ottawa ON K1P 6A4",
    "addr:housenumber":"85",
    "addr:postcode":"k1p 6a4",
    "addr:street":"Albert St # 100",
    "iso:country":"CA",
    "sg:address":"85 Albert St #100",
    "sg:city":"Ottawa",
    "sg:classifiers":[
        {
            "category":"Shopping",
            "subcategory":"Computers & Home Electronics",
            "type":"Retail Goods"
        }
    ],
    "sg:phone":"+1 613 235 6740",
    "sg:postcode":"K1P 6A4",
    "sg:province":"ON",
    "sg:tags":[
        "software"
    ],
    "wof:name":"Autoskill International Inc",
    "wof:placetype":"venue"
},
  "geometry": {"coordinates":[-75.695908,45.422001],"type":"Point"}
}