{
  "type": "Feature",
  "properties": {
    "addr:full":"491 Madison St Winnipeg MB R3J 1J2",
    "addr:housenumber":"491",
    "addr:postcode":"r3j 1j2",
    "addr:street":"Madison St",
    "iso:country":"CA",
    "sg:address":"491 Madison St",
    "sg:city":"Winnipeg",
    "sg:classifiers":[
        {
            "category":"Professional",
            "subcategory":"Advertising",
            "type":"Services"
        }
    ],
    "sg:phone":"+1 204 786 8828",
    "sg:postcode":"R3J 1J2",
    "sg:province":"MB",
    "sg:tags":[
        "designer",
        "lamination",
        "display",
        "producer"
    ],
    "wof:name":"Posters on Board Inc",
    "wof:placetype":"venue"
},
  "geometry": {"coordinates":[-97.203255,49.889999],"type":"Point"}
}