{
  "type": "Feature",
  "properties": {
    "iso:country":"CA",
    "sg:city":"Mississauga",
    "sg:classifiers":[
        {
            "category":"Wholesale",
            "subcategory":"Metals & Minerals",
            "type":"Manufacturing & Wholesale Goods"
        }
    ],
    "sg:phone":"+1 905 795 1860",
    "sg:postcode":"L5T 2G4",
    "sg:province":"ON",
    "sg:tags":[
        "roofing",
        "aluminum",
        "contractor"
    ],
    "wof:name":"Columbus Aluminum Roofing Ltd",
    "wof:placetype":"venue"
},
  "geometry": {"coordinates":[-79.669921875,43.6693305969],"type":"Point"}
}