{
  "type": "Feature",
  "properties": {
    "addr:full":"310 Prairie Pl Dalmeny SK S0K 1E0",
    "addr:housenumber":"310",
    "addr:postcode":"s0k 1e0",
    "addr:street":"Prairie Pl",
    "iso:country":"CA",
    "sg:address":"310 Prairie Pl",
    "sg:city":"Dalmeny",
    "sg:classifiers":[
        {
            "category":"Professional",
            "subcategory":"Engineering",
            "type":"Services"
        }
    ],
    "sg:phone":"+1 306 254 4956",
    "sg:postcode":"S0K 1E0",
    "sg:province":"SK",
    "sg:tags":[
        "engineer"
    ],
    "wof:name":"Kba Consultants Inc",
    "wof:placetype":"venue"
},
  "geometry": {"coordinates":[-106.776634,52.339287],"type":"Point"}
}