{
  "type": "Feature",
  "properties": {
    "addr:full":"Hwy 14 W Saskatoon SK S7K 3K1",
    "addr:postcode":"s7k 3k1",
    "addr:street":"Hwy 14 W",
    "iso:country":"CA",
    "sg:address":"Hwy 14 W",
    "sg:city":"Saskatoon",
    "sg:classifiers":[
        {
            "category":"Retail",
            "subcategory":"Veterinary Services",
            "type":"Services"
        }
    ],
    "sg:phone":"+1 306 384 7676",
    "sg:postcode":"S7K 3K1",
    "sg:province":"SK",
    "sg:tags":[
        "veterinarian"
    ],
    "wof:name":"Corman Park & District Vet Svc",
    "wof:placetype":"venue"
},
  "geometry": {"coordinates":[-106.750381,52.128056],"type":"Point"}
}