{
  "type": "Feature",
  "properties": {
    "addr:full":"882 Tungsten St Thunder Bay ON P7B 6J3",
    "addr:housenumber":"882",
    "addr:postcode":"p7b 6j3",
    "addr:street":"Tungsten St",
    "iso:country":"CA",
    "sg:address":"882 Tungsten St",
    "sg:city":"Thunder Bay",
    "sg:classifiers":[
        {
            "category":"Home & Garden",
            "subcategory":"Building Materials",
            "type":"Retail Goods"
        }
    ],
    "sg:phone":"+1 807 623 5459",
    "sg:postcode":"P7B 6J3",
    "sg:province":"ON",
    "sg:tags":[
        "siding"
    ],
    "wof:name":"Boncor Building Products CO",
    "wof:placetype":"venue"
},
  "geometry": {"coordinates":[-89.254822,48.413525],"type":"Point"}
}