{
  "type": "Feature",
  "properties": {
    "addr:full":"883 Jane St York ON M6N 4C4",
    "addr:housenumber":"883",
    "addr:postcode":"m6n 4c4",
    "addr:street":"Jane St",
    "iso:country":"CA",
    "sg:address":"883 Jane St",
    "sg:city":"York",
    "sg:classifiers":[
        {
            "category":"Health Services",
            "subcategory":"Doctor",
            "type":"Services"
        }
    ],
    "sg:phone":"+1 416 767 6591",
    "sg:postcode":"M6N 4C4",
    "sg:province":"ON",
    "sg:tags":[
        "dentist"
    ],
    "wof:name":"Zimmerman, Daniel DDS",
    "wof:placetype":"venue"
},
  "geometry": {"coordinates":[-79.495803833,43.6769485474],"type":"Point"}
}