{
  "type": "Feature",
  "properties": {
    "addr:full":"1565 Bayview Ave East York ON M4G 3B5",
    "addr:housenumber":"1565",
    "addr:postcode":"m4g 3b5",
    "addr:street":"Bayview Ave",
    "iso:country":"CA",
    "sg:address":"1565 Bayview Ave",
    "sg:city":"East York",
    "sg:classifiers":[
        {
            "category":"Shopping",
            "subcategory":"Clothing, Apparel, & Fashions",
            "type":"Retail Goods"
        }
    ],
    "sg:phone":"+1 416 489 8877",
    "sg:postcode":"M4G 3B5",
    "sg:province":"ON",
    "sg:tags":[
        "tailor"
    ],
    "wof:name":"Norman Cleaners & Tailors",
    "wof:placetype":"venue"
},
  "geometry": {"coordinates":[-79.374931,43.705666],"type":"Point"}
}