{
  "type": "Feature",
  "properties": {
    "addr:full":"5054 222 Rte Valcourt QC J0E 2L0",
    "addr:housenumber":"5054",
    "addr:postcode":"j0e 2l0",
    "addr:street":"222 Rte Valcourt",
    "iso:country":"CA",
    "sg:address":"5054 222 Rte",
    "sg:city":"Valcourt",
    "sg:classifiers":[
        {
            "category":"Farming",
            "subcategory":"Farm",
            "type":"Manufacturing & Wholesale Goods"
        }
    ],
    "sg:phone":"+1 450 532 2610",
    "sg:postcode":"J0E 2L0",
    "sg:province":"QC",
    "wof:name":"Ferme Dlo",
    "wof:placetype":"venue"
},
  "geometry": {"coordinates":[-72.31495700000001,45.493382],"type":"Point"}
}