{
  "type": "Feature",
  "properties": {
    "addr:full":"460 St. George St Moncton NB E1C 1Y1",
    "addr:housenumber":"460",
    "addr:postcode":"e1c 1y1",
    "addr:street":"St. George St",
    "iso:country":"CA",
    "sg:address":"460 St. George St",
    "sg:city":"Moncton",
    "sg:classifiers":[
        {
            "category":"Food & Beverages",
            "subcategory":"Groceries & Convenience Stores",
            "type":"Retail Goods"
        }
    ],
    "sg:phone":"+1 506 857 9360",
    "sg:postcode":"E1C 1Y1",
    "sg:province":"NB",
    "wof:name":"Greg's Coffee & Convenience",
    "wof:placetype":"venue"
},
  "geometry": {"coordinates":[-64.792686,46.089062],"type":"Point"}
}