{
  "type": "Feature",
  "properties": {
    "addr:full":"59 Country Lane E Kanata ON K2L 1H9",
    "addr:housenumber":"59",
    "addr:postcode":"k2l 1h9",
    "addr:street":"Country Lane E",
    "iso:country":"CA",
    "sg:address":"59 Country Lane E",
    "sg:city":"Kanata",
    "sg:classifiers":[
        {
            "category":"Shopping",
            "type":"Retail Goods"
        }
    ],
    "sg:phone":"+1 613 836 1625",
    "sg:postcode":"K2L 1H9",
    "sg:province":"ON",
    "sg:tags":[
        "equipment",
        "telephone",
        "supply"
    ],
    "wof:name":"Murdoch Headsets Inc",
    "wof:placetype":"venue"
},
  "geometry": {"coordinates":[-75.876114,45.299522],"type":"Point"}
}