{
  "type": "Feature",
  "properties": {
    "addr:full":"Domain MB R0G 0M0",
    "addr:postcode":"r0g 0m0",
    "iso:country":"CA",
    "sg:city":"Domain",
    "sg:classifiers":[
        {
            "category":"Education",
            "subcategory":"School",
            "type":"Public Place"
        }
    ],
    "sg:phone":"+1 204 736 4083",
    "sg:postcode":"R0G 0M0",
    "sg:province":"MB",
    "wof:name":"Domain Elementary School",
    "wof:placetype":"venue"
},
  "geometry": {"coordinates":[-97.322113,49.617016],"type":"Point"}
}