{
  "type": "Feature",
  "properties": {
    "addr:full":"93 Harris Rd Pictou NS B0K 1H0",
    "addr:housenumber":"93",
    "addr:postcode":"b0k 1h0",
    "addr:street":"Harris Rd",
    "iso:country":"CA",
    "sg:address":"93 Harris Rd",
    "sg:city":"Pictou",
    "sg:classifiers":[
        {
            "category":"Autos & Motor Vehicles",
            "subcategory":"Automobile Sales",
            "type":"Retail Goods"
        }
    ],
    "sg:phone":"+1 902 485 6348",
    "sg:postcode":"B0K 1H0",
    "sg:province":"NS",
    "sg:tags":[
        "body",
        "car"
    ],
    "wof:name":"Perry's Auto Body",
    "wof:placetype":"venue"
},
  "geometry": {"coordinates":[-62.7070732117,45.6781806946],"type":"Point"}
}