{
  "type": "Feature",
  "properties": {
    "addr:full":"102 Rte 138 O Baie-Trinite QC G0H 1A0",
    "addr:housenumber":"102",
    "addr:postcode":"g0h 1a0",
    "addr:street":"Rte 138 O Baie-Trinite",
    "iso:country":"CA",
    "sg:address":"102 Rte 138 O",
    "sg:city":"Baie-Trinite",
    "sg:classifiers":[
        {
            "category":"Retail",
            "subcategory":"Auto Repair",
            "type":"Services"
        }
    ],
    "sg:phone":"+1 418 939 2272",
    "sg:postcode":"G0H 1A0",
    "sg:province":"QC",
    "sg:tags":[
        "repairing",
        "automobile"
    ],
    "wof:name":"Garage Georges Ringuette Svc",
    "wof:placetype":"venue"
},
  "geometry": {"coordinates":[-67.27578,49.434856],"type":"Point"}
}