{
  "type": "Feature",
  "properties": {
    "addr:full":"Farmers Market Rd Waterloo ON N2J 4G8",
    "addr:postcode":"n2j 4g8",
    "addr:street":"Rd",
    "iso:country":"CA",
    "sg:address":"Farmers Market Rd",
    "sg:city":"Waterloo",
    "sg:classifiers":[
        {
            "category":"Home & Garden",
            "subcategory":"Home Furnishings",
            "type":"Retail Goods"
        }
    ],
    "sg:phone":"+1 519 884 2938",
    "sg:postcode":"N2J 4G8",
    "sg:province":"ON",
    "sg:tags":[
        "blanket",
        "quilt"
    ],
    "wof:name":"Quilted Heirlooms",
    "wof:placetype":"venue"
},
  "geometry": {"coordinates":[-80.520690918,43.4631385803],"type":"Point"}
}