{
  "type": "Feature",
  "properties": {
    "addr:full":"165 Dundas St W Mississauga ON L5B 2N6",
    "addr:housenumber":"165",
    "addr:postcode":"l5b 2n6",
    "addr:street":"Dundas St W",
    "iso:country":"CA",
    "sg:address":"165 Dundas St W",
    "sg:city":"Mississauga",
    "sg:classifiers":[
        {
            "category":"Professional",
            "type":"Services"
        }
    ],
    "sg:phone":"+1 905 306 2816",
    "sg:postcode":"L5B 2N6",
    "sg:province":"ON",
    "sg:tags":[
        "establishment",
        "advertising"
    ],
    "wof:name":"Phunkie Gifts & Bombonieres",
    "wof:placetype":"venue"
},
  "geometry": {"coordinates":[-79.6207733154,43.5766410828],"type":"Point"}
}