{
  "type": "Feature",
  "properties": {
    "addr:full":"5523 Sunshine Coast Hwy 101 Sechelt BC V0N 3A0",
    "addr:housenumber":"5523",
    "addr:postcode":"v0n 3a0",
    "addr:street":"Sunshine Coast Hwy 101",
    "iso:country":"CA",
    "sg:address":"5523 Sunshine Coast Hwy 101",
    "sg:city":"Sechelt",
    "sg:classifiers":[
        {
            "category":"Building & Trades",
            "subcategory":"Construction",
            "type":"Services"
        }
    ],
    "sg:phone":"+1 604 740 8819",
    "sg:postcode":"V0N 3A0",
    "sg:province":"BC",
    "sg:tags":[
        "excavating",
        "contractor"
    ],
    "wof:name":"Salish Land Development Inc",
    "wof:placetype":"venue"
},
  "geometry": {"coordinates":[-123.75483699999999,49.473251],"type":"Point"}
}