{
  "type": "Feature",
  "properties": {
    "addr:full":"Winnipeg MB R2M 5L5",
    "addr:postcode":"r2m 5l5",
    "iso:country":"CA",
    "sg:city":"Winnipeg",
    "sg:classifiers":[
        {
            "category":"Manufacturing",
            "subcategory":"Metals",
            "type":"Manufacturing & Wholesale Goods"
        }
    ],
    "sg:phone":"+1 204 255 2334",
    "sg:postcode":"R2M 5L5",
    "sg:province":"MB",
    "sg:tags":[
        "engraver"
    ],
    "wof:name":"Key Man Engravables",
    "wof:placetype":"venue"
},
  "geometry": {"coordinates":[-97.136482,49.891891],"type":"Point"}
}