{
  "type": "Feature",
  "properties": {
    "addr:full":"60 Rue Prudent Cloutier Mont-Saint-Pierre QC G0E 1V0",
    "addr:housenumber":"60",
    "addr:postcode":"g0e 1v0",
    "addr:street":"Rue Prudent Cloutier",
    "iso:country":"CA",
    "sg:address":"60 Rue Prudent Cloutier",
    "sg:city":"Mont-Saint-Pierre",
    "sg:classifiers":[
        {
            "category":"Travel",
            "subcategory":"Hotels & Motels",
            "type":"Entertainment"
        }
    ],
    "sg:phone":"+1 418 797 2202",
    "sg:postcode":"G0E 1V0",
    "sg:province":"QC",
    "wof:name":"Hotel Motel Mont St-Pierre",
    "wof:placetype":"venue"
},
  "geometry": {"coordinates":[-65.805557251,49.222454071],"type":"Point"}
}