{
  "type": "Feature",
  "properties": {
    "addr:full":"1132 15th St W North Vancouver BC V7P 1M9",
    "addr:housenumber":"1132",
    "addr:postcode":"v7p 1m9",
    "addr:street":"15Th St W",
    "iso:country":"CA",
    "sg:address":"1132 15th St W",
    "sg:city":"North Vancouver",
    "sg:classifiers":[
        {
            "category":"Wholesale",
            "subcategory":"Non-durable Goods",
            "type":"Manufacturing & Wholesale Goods"
        }
    ],
    "sg:phone":"+1 604 986 0365",
    "sg:postcode":"V7P 1M9",
    "sg:province":"BC",
    "wof:name":"D H Ussher Ltd",
    "wof:placetype":"venue"
},
  "geometry": {"coordinates":[-123.097015,49.322041],"type":"Point"}
}