{
  "type": "Feature",
  "properties": {
    "addr:full":"Etobicoke ON M9C 2Z4",
    "addr:postcode":"m9c 2z4",
    "iso:country":"CA",
    "sg:city":"Etobicoke",
    "sg:classifiers":[
        {
            "category":"Shopping",
            "subcategory":"Jewelry",
            "type":"Retail Goods"
        }
    ],
    "sg:phone":"+1 416 620 9881",
    "sg:postcode":"M9C 2Z4",
    "sg:province":"ON",
    "sg:tags":[
        "jeweler"
    ],
    "wof:name":"Pot of Gold Jewellers",
    "wof:placetype":"venue"
},
  "geometry": {"coordinates":[-79.57719400000001,43.642151],"type":"Point"}
}