{
  "type": "Feature",
  "properties": {
    "addr:full":"350 Place Royale Montreal QC H2Y 3Y5",
    "addr:housenumber":"350",
    "addr:postcode":"h2y 3y5",
    "addr:street":"Place",
    "iso:country":"CA",
    "sg:address":"350 Place Royale",
    "sg:city":"Montreal",
    "sg:classifiers":[
        {
            "category":"Restaurant",
            "type":"Food & Drink"
        }
    ],
    "sg:phone":"+1 514 842 6914",
    "sg:postcode":"H2Y 3Y5",
    "sg:province":"QC",
    "wof:name":"L'Arrivage",
    "wof:placetype":"venue"
},
  "geometry": {"coordinates":[-73.554749,45.503429],"type":"Point"}
}