{
  "type": "Feature",
  "properties": {
    "addr:full":"31 John Savage Ave Dartmouth NS B3B 2C9",
    "addr:housenumber":"31",
    "addr:postcode":"b3b 2c9",
    "addr:street":"John Savage Ave",
    "iso:country":"CA",
    "sg:address":"31 John Savage Ave",
    "sg:city":"Dartmouth",
    "sg:classifiers":[
        {
            "category":"Freight",
            "type":"Transportation"
        }
    ],
    "sg:phone":"+1 902 468 5424",
    "sg:postcode":"B3B 2C9",
    "sg:province":"NS",
    "sg:tags":[
        "mover"
    ],
    "wof:name":"Moffatt Moving & Storage",
    "wof:placetype":"venue"
},
  "geometry": {"coordinates":[-63.580296,44.716202],"type":"Point"}
}