{
  "type": "Feature",
  "properties": {
    "addr:full":"690 Fairford St W Moose Jaw SK S6H 7W9",
    "addr:housenumber":"690",
    "addr:postcode":"s6h 7w9",
    "addr:street":"Fairford St W",
    "iso:country":"CA",
    "sg:address":"690 Fairford St W",
    "sg:city":"Moose Jaw",
    "sg:classifiers":[
        {
            "category":"Building & Trades",
            "subcategory":"Equipment Rental",
            "type":"Services"
        }
    ],
    "sg:phone":"+1 306 692 3300",
    "sg:postcode":"S6H 7W9",
    "sg:province":"SK",
    "sg:tags":[
        "crane"
    ],
    "wof:name":"B & T Crane Svc Ltd",
    "wof:placetype":"venue"
},
  "geometry": {"coordinates":[-105.551254,50.392708],"type":"Point"}
}