{
  "type": "Feature",
  "properties": {
    "iso:country":"CA",
    "sg:address":"624 Main St",
    "sg:city":"Moosomin",
    "sg:classifiers":[
        {
            "category":"Manufacturing",
            "subcategory":"Printing",
            "type":"Manufacturing & Wholesale Goods"
        }
    ],
    "sg:phone":"+1 306 435 2445",
    "sg:postcode":"S0G 3N0",
    "sg:province":"SK",
    "sg:tags":[
        "newspaper"
    ],
    "wof:name":"World Spectator",
    "wof:placetype":"venue"
},
  "geometry": {"coordinates":[-101.666572571,50.1443710327],"type":"Point"}
}