{
  "type": "Feature",
  "properties": {
    "iso:country":"CA",
    "sg:address":"16135 99 St NW",
    "sg:city":"Edmonton",
    "sg:classifiers":[
        {
            "category":"Professional",
            "subcategory":"Business Services",
            "type":"Services"
        }
    ],
    "sg:phone":"+1 780 456 1210",
    "sg:postcode":"T5X 4R5",
    "sg:province":"AB",
    "sg:tags":[
        "auctioneer"
    ],
    "wof:name":"Dennis J Andruchow Auctions",
    "wof:placetype":"venue"
},
  "geometry": {"coordinates":[-113.494636536,53.6224441528],"type":"Point"}
}