{
  "type": "Feature",
  "properties": {
    "addr:full":"30 Frazee Ave Dartmouth NS B3B 1X4",
    "addr:housenumber":"30",
    "addr:postcode":"b3b 1x4",
    "addr:street":"Frazee Ave",
    "iso:country":"CA",
    "sg:address":"30 Frazee Ave",
    "sg:city":"Dartmouth",
    "sg:classifiers":[
        {
            "category":"Organizations",
            "subcategory":"Labor Organization",
            "type":"Services"
        }
    ],
    "sg:phone":"+1 902 469 1474",
    "sg:postcode":"B3B 1X4",
    "sg:province":"NS",
    "wof:name":"Nova Scotia Nurses Union",
    "wof:placetype":"venue"
},
  "geometry": {"coordinates":[-63.583240509,44.7134170532],"type":"Point"}
}