{
  "type": "Feature",
  "properties": {
    "addr:full":"76 Church St Wellington NS B2T 1A2",
    "addr:housenumber":"76",
    "addr:postcode":"b2t 1a2",
    "addr:street":"Church St",
    "iso:country":"CA",
    "sg:address":"76 Church St",
    "sg:city":"Wellington",
    "sg:classifiers":[
        {
            "category":"Organizations",
            "subcategory":"Religious Organization",
            "type":"Services"
        }
    ],
    "sg:phone":"+1 902 861 1956",
    "sg:postcode":"B2T 1A2",
    "sg:province":"NS",
    "sg:tags":[
        "church"
    ],
    "wof:name":"Wellington United Church",
    "wof:placetype":"venue"
},
  "geometry": {"coordinates":[-63.615681,44.866291],"type":"Point"}
}