{
  "type": "Feature",
  "properties": {
    "addr:full":"1810 Rue Principale E Farnham QC J2N 1N4",
    "addr:housenumber":"1810",
    "addr:postcode":"j2n 1n4",
    "addr:street":"Rue Principale E",
    "iso:country":"CA",
    "sg:address":"1810 Rue Principale E",
    "sg:city":"Farnham",
    "sg:classifiers":[
        {
            "category":"Government",
            "subcategory":"Office",
            "type":"Public Place"
        }
    ],
    "sg:phone":"+1 450 293 7378",
    "sg:postcode":"J2N 1N4",
    "sg:province":"QC",
    "sg:tags":[
        "village"
    ],
    "wof:name":"Rainville Centre DE Loisirs",
    "wof:placetype":"venue"
},
  "geometry": {"coordinates":[-72.956383,45.273045],"type":"Point"}
}