{
  "type": "Feature",
  "properties": {
    "addr:full":"2225 15 St SE Calgary AB T2G 3M3",
    "addr:housenumber":"2225",
    "addr:postcode":"t2g 3m3",
    "addr:street":"15 St Se",
    "iso:country":"CA",
    "sg:address":"2225 15 St SE",
    "sg:city":"Calgary",
    "sg:classifiers":[
        {
            "category":"Shopping",
            "type":"Retail Goods"
        }
    ],
    "sg:phone":"+1 403 294 9448",
    "sg:postcode":"T2G 3M3",
    "sg:province":"AB",
    "sg:tags":[
        "art",
        "gallery",
        "dealer"
    ],
    "wof:name":"Simply Metal Studio",
    "wof:placetype":"venue"
},
  "geometry": {"coordinates":[-114.02533721899999,51.0354270935],"type":"Point"}
}