{
  "type": "Feature",
  "properties": {
    "iso:country":"CA",
    "sg:address":"243 Ch DE LA Beauce",
    "sg:city":"Beauharnois",
    "sg:classifiers":[
        {
            "category":"Retail",
            "subcategory":"Auto Repair",
            "type":"Services"
        }
    ],
    "sg:phone":"+1 450 429 5727",
    "sg:postcode":"J6N 2N5",
    "sg:province":"QC",
    "sg:tags":[
        "body",
        "automobile",
        "painting"
    ],
    "wof:name":"Garage Peladeau",
    "wof:placetype":"venue"
},
  "geometry": {"coordinates":[-73.861618042,45.3082351685],"type":"Point"}
}