{
  "type": "Feature",
  "properties": {
    "addr:full":"Saint-Zotique QC J0P 1Z0",
    "addr:postcode":"j0p 1z0",
    "iso:country":"CA",
    "sg:city":"Saint-Zotique",
    "sg:classifiers":[
        {
            "category":"Autos & Motor Vehicles",
            "subcategory":"Fuel & Gas Station",
            "type":"Retail Goods"
        }
    ],
    "sg:phone":"+1 450 267 9807",
    "sg:postcode":"J0P 1Z0",
    "sg:province":"QC",
    "sg:tags":[
        "oil"
    ],
    "wof:name":"Produits Petroliers Real Ltee",
    "wof:placetype":"venue"
},
  "geometry": {"coordinates":[-74.24887099999999,45.241421],"type":"Point"}
}