{
  "type": "Feature",
  "properties": {
    "iso:country":"CA",
    "sg:city":"Newmarket",
    "sg:classifiers":[
        {
            "category":"Health Services",
            "subcategory":"Doctor",
            "type":"Services"
        }
    ],
    "sg:phone":"+1 905 895 8695",
    "sg:postcode":"L3Y 2P7",
    "sg:province":"ON",
    "sg:tags":[
        "dentist"
    ],
    "wof:name":"Medical Sciences",
    "wof:placetype":"venue"
},
  "geometry": {"coordinates":[-79.452873,44.061138],"type":"Point"}
}