{
  "type": "Feature",
  "properties": {
    "iso:country":"CA",
    "sg:city":"Woodbridge",
    "sg:classifiers":[
        {
            "category":"Health Services",
            "subcategory":"Doctor",
            "type":"Services"
        }
    ],
    "sg:phone":"+1 905 856 6060",
    "sg:postcode":"L4L 8B7",
    "sg:province":"ON",
    "sg:tags":[
        "dentist"
    ],
    "wof:name":"Woodbridge Sq Dental Clinic",
    "wof:placetype":"venue"
},
  "geometry": {"coordinates":[-79.54734,43.787727],"type":"Point"}
}