{
  "type": "Feature",
  "properties": {
    "addr:full":"162 Main St S Mount Forest ON N0G 2L0",
    "addr:housenumber":"162",
    "addr:postcode":"n0g 2l0",
    "addr:street":"Main St S Mount",
    "iso:country":"CA",
    "sg:address":"162 Main St S",
    "sg:city":"Mount Forest",
    "sg:classifiers":[
        {
            "category":"Shopping",
            "subcategory":"Clothing, Apparel, & Fashions",
            "type":"Retail Goods"
        }
    ],
    "sg:phone":"+1 519 323 4789",
    "sg:postcode":"N0G 2L0",
    "sg:province":"ON",
    "wof:name":"Cynthia & CO",
    "wof:placetype":"venue"
},
  "geometry": {"coordinates":[-80.73645,43.982582],"type":"Point"}
}