{
  "type": "Feature",
  "properties": {
    "iso:country":"CA",
    "sg:address":"15675 16 Ave",
    "sg:city":"Surrey",
    "sg:classifiers":[
        {
            "category":"Building & Trades",
            "subcategory":"Construction",
            "type":"Services"
        }
    ],
    "sg:phone":"+1 604 535 1619",
    "sg:postcode":"V4A 1R9",
    "sg:province":"BC",
    "sg:tags":[
        "roofing",
        "contractor"
    ],
    "wof:name":"Priority Roofing Ltd",
    "wof:placetype":"venue"
},
  "geometry": {"coordinates":[-122.78805542000001,49.0313453674],"type":"Point"}
}