{
  "type": "Feature",
  "properties": {
    "addr:full":"1657 Bayview Ave East York ON M4G 3C1",
    "addr:housenumber":"1657",
    "addr:postcode":"m4g 3c1",
    "addr:street":"Bayview Ave",
    "iso:country":"CA",
    "sg:address":"1657 Bayview Ave",
    "sg:city":"East York",
    "sg:classifiers":[
        {
            "category":"Home & Garden",
            "subcategory":"Furniture",
            "type":"Retail Goods"
        }
    ],
    "sg:phone":"+1 416 322 8883",
    "sg:postcode":"M4G 3C1",
    "sg:province":"ON",
    "wof:name":"Country Store",
    "wof:placetype":"venue"
},
  "geometry": {"coordinates":[-79.3755493164,43.7072906494],"type":"Point"}
}