{
  "type": "Feature",
  "properties": {
    "addr:full":"425 Boul DE Maisonneuve O # B06 Montreal QC H3A 3G5",
    "addr:housenumber":"425",
    "addr:postcode":"h3a 3g5",
    "addr:street":"Boul De Maisonneuve O # B06",
    "iso:country":"CA",
    "sg:address":"425 Boul DE Maisonneuve O # B06",
    "sg:city":"Montreal",
    "sg:classifiers":[
        {
            "category":"Restaurant",
            "type":"Food & Drink"
        }
    ],
    "sg:phone":"+1 514 284 2332",
    "sg:postcode":"H3A 3G5",
    "sg:province":"QC",
    "wof:name":"Fontaine Sante DE Maisonneuve",
    "wof:placetype":"venue"
},
  "geometry": {"coordinates":[-73.5617218018,45.5147743225],"type":"Point"}
}