{
  "type": "Feature",
  "properties": {
    "addr:full":"5175 Av Papineau Montreal QC H2H 1W1",
    "addr:housenumber":"5175",
    "addr:postcode":"h2h 1w1",
    "addr:street":"Av Papineau",
    "iso:country":"CA",
    "sg:address":"5175 Av Papineau",
    "sg:city":"Montreal",
    "sg:classifiers":[
        {
            "category":"Shopping",
            "subcategory":"Computers & Home Electronics",
            "type":"Retail Goods"
        }
    ],
    "sg:phone":"+1 514 521 0902",
    "sg:postcode":"H2H 1W1",
    "sg:province":"QC",
    "sg:tags":[
        "television",
        "radio"
    ],
    "wof:name":"Concordia Tv Enr",
    "wof:placetype":"venue"
},
  "geometry": {"coordinates":[-73.581413269,45.5362014771],"type":"Point"}
}