{
  "type": "Feature",
  "properties": {
    "iso:country":"CA",
    "sg:address":"237 Huron Rd",
    "sg:city":"Sebringville",
    "sg:classifiers":[
        {
            "category":"Home & Garden",
            "subcategory":"Household Appliances",
            "type":"Retail Goods"
        }
    ],
    "sg:phone":"+1 519 393 6181",
    "sg:postcode":"N0K 1X0",
    "sg:province":"ON",
    "wof:name":"Phelans Place Furniture Appl",
    "wof:placetype":"venue"
},
  "geometry": {"coordinates":[-81.05661773680001,43.4049072266],"type":"Point"}
}