{
  "type": "Feature",
  "properties": {
    "addr:full":"11580 4E Av Montreal QC H1E 3B3",
    "addr:housenumber":"11580",
    "addr:postcode":"h1e 3b3",
    "addr:street":"4E Av",
    "iso:country":"CA",
    "sg:address":"11580 4E Av",
    "sg:city":"Montreal",
    "sg:classifiers":[
        {
            "category":"Building & Trades",
            "subcategory":"Construction",
            "type":"Services"
        }
    ],
    "sg:phone":"+1 514 494 2151",
    "sg:postcode":"H1E 3B3",
    "sg:province":"QC",
    "sg:tags":[
        "product",
        "paving",
        "asphalt",
        "contractor"
    ],
    "wof:name":"Asphalte Tms Inc",
    "wof:placetype":"venue"
},
  "geometry": {"coordinates":[-73.5996017456,45.6199378967],"type":"Point"}
}