{
  "type": "Feature",
  "properties": {
    "addr:full":"139 Spring St Sault Ste Marie ON P6A 3A2",
    "addr:housenumber":"139",
    "addr:postcode":"p6a 3a2",
    "addr:street":"Spring St",
    "iso:country":"CA",
    "sg:address":"139 Spring St",
    "sg:city":"Sault Ste Marie",
    "sg:classifiers":[
        {
            "category":"Personal",
            "subcategory":"Beauty Salon",
            "type":"Services"
        }
    ],
    "sg:phone":"+1 705 254 7992",
    "sg:postcode":"P6A 3A2",
    "sg:province":"ON",
    "sg:tags":[
        "school"
    ],
    "wof:name":"Ultimate Touch",
    "wof:placetype":"venue"
},
  "geometry": {"coordinates":[-84.330444,46.51091],"type":"Point"}
}