{
  "type": "Feature",
  "properties": {
    "addr:full":"Calgary AB T2Z 1K4",
    "addr:postcode":"t2z 1k4",
    "iso:country":"CA",
    "sg:city":"Calgary",
    "sg:classifiers":[
        {
            "category":"Shopping",
            "subcategory":"Pharmacy",
            "type":"Retail Goods"
        }
    ],
    "sg:phone":"+1 403 279 3837",
    "sg:postcode":"T2Z 1K4",
    "sg:province":"AB",
    "wof:name":"Douglasdale Pharmacy Inc",
    "wof:placetype":"venue"
},
  "geometry": {"coordinates":[-114.002419,50.943367],"type":"Point"}
}