{
  "type": "Feature",
  "properties": {
    "addr:full":"893 Prince St Truro NS B2N 1H2",
    "addr:housenumber":"893",
    "addr:postcode":"b2n 1h2",
    "addr:street":"Prince St",
    "iso:country":"CA",
    "sg:address":"893 Prince St",
    "sg:city":"Truro",
    "sg:classifiers":[
        {
            "category":"Personal",
            "subcategory":"Beauty Salon",
            "type":"Services"
        }
    ],
    "sg:phone":"+1 902 895 1063",
    "sg:postcode":"B2N 1H2",
    "sg:province":"NS",
    "wof:name":"Marie's Beauty Salon",
    "wof:placetype":"venue"
},
  "geometry": {"coordinates":[-63.274544,45.364548],"type":"Point"}
}