{
  "type": "Feature",
  "properties": {
    "iso:country":"CA",
    "sg:address":"167 Medora St",
    "sg:city":"Port Carling",
    "sg:classifiers":[
        {
            "category":"Personal",
            "subcategory":"Barber",
            "type":"Services"
        }
    ],
    "sg:phone":"+1 705 706 1113",
    "sg:postcode":"P0B 1J0",
    "sg:province":"ON",
    "wof:name":"Courtyard Barber Shop",
    "wof:placetype":"venue"
},
  "geometry": {"coordinates":[-79.5886001587,45.1117515564],"type":"Point"}
}