{
  "type": "Feature",
  "properties": {
    "iso:country":"CA",
    "sg:city":"Plessisville",
    "sg:classifiers":[
        {
            "category":"Social Services",
            "type":"Services"
        }
    ],
    "sg:phone":"+1 819 362 3473",
    "sg:postcode":"G6L 1P6",
    "sg:province":"QC",
    "sg:tags":[
        "organization",
        "welfare"
    ],
    "wof:name":"Cdc",
    "wof:placetype":"venue"
},
  "geometry": {"coordinates":[-71.77517700200001,46.2169723511],"type":"Point"}
}