{
  "type": "Feature",
  "properties": {
    "iso:country":"CA",
    "sg:address":"5295 Lakeshore Rd",
    "sg:city":"Burlington",
    "sg:classifiers":[
        {
            "category":"Shopping",
            "subcategory":"Discount & Variety Stores",
            "type":"Retail Goods"
        }
    ],
    "sg:phone":"+1 905 637 9308",
    "sg:postcode":"L7L 1C7",
    "sg:province":"ON",
    "wof:name":"Ted's Variety",
    "wof:placetype":"venue"
},
  "geometry": {"coordinates":[-79.734413,43.366344],"type":"Point"}
}