{
  "type": "Feature",
  "properties": {
    "iso:country":"CA",
    "sg:address":"35 Cedar Pointe Dr #14",
    "sg:city":"Barrie",
    "sg:classifiers":[
        {
            "category":"Home & Garden",
            "subcategory":"Furniture",
            "type":"Retail Goods"
        }
    ],
    "sg:phone":"+1 705 739 0026",
    "sg:postcode":"L4N 5R7",
    "sg:province":"ON",
    "wof:name":"Waterbed Gallery",
    "wof:placetype":"venue"
},
  "geometry": {"coordinates":[-79.712486,44.380886],"type":"Point"}
}