{
  "type": "Feature",
  "properties": {
    "addr:full":"215 Industrial Pky S Aurora ON L4G 3V5",
    "addr:housenumber":"215",
    "addr:postcode":"l4g 3v5",
    "addr:street":"Industrial Pky",
    "iso:country":"CA",
    "sg:address":"215 Industrial Pky S",
    "sg:city":"Aurora",
    "sg:classifiers":[
        {
            "category":"Government",
            "subcategory":"Office",
            "type":"Public Place"
        }
    ],
    "sg:phone":"+1 905 727 4612",
    "sg:postcode":"L4G 3V5",
    "sg:province":"ON",
    "sg:tags":[
        "village"
    ],
    "wof:name":"Aurora Hydro Commission Ofc",
    "wof:placetype":"venue"
},
  "geometry": {"coordinates":[-79.454285,43.992298],"type":"Point"}
}