{
  "type": "Feature",
  "properties": {
    "addr:full":"4904 Argyle St Port Alberni BC V9Y 1V7",
    "addr:housenumber":"4904",
    "addr:postcode":"v9y 1v7",
    "addr:street":"Argyle St",
    "iso:country":"CA",
    "sg:address":"4904 Argyle St",
    "sg:city":"Port Alberni",
    "sg:classifiers":[
        {
            "category":"Arts & Performance",
            "subcategory":"Theater",
            "type":"Entertainment"
        }
    ],
    "sg:phone":"+1 250 723 1195",
    "sg:postcode":"V9Y 1V7",
    "sg:province":"BC",
    "wof:name":"Portal Players Dramatic Soc",
    "wof:placetype":"venue"
},
  "geometry": {"coordinates":[-124.806313,49.234455],"type":"Point"}
}