{
  "type": "Feature",
  "properties": {
    "addr:full":"4081 Dufferin St North York ON M3H 5R8",
    "addr:housenumber":"4081",
    "addr:postcode":"m3h 5r8",
    "addr:street":"Dufferin St",
    "iso:country":"CA",
    "sg:address":"4081 Dufferin St",
    "sg:city":"North York",
    "sg:classifiers":[
        {
            "category":"Organizations",
            "subcategory":"Professional Association",
            "type":"Services"
        }
    ],
    "sg:phone":"+1 416 636 6677",
    "sg:postcode":"M3H 5R8",
    "sg:province":"ON",
    "wof:name":"Mesjid, AL Sabur",
    "wof:placetype":"venue"
},
  "geometry": {"coordinates":[-79.4645233154,43.7585754395],"type":"Point"}
}