{
  "type": "Feature",
  "properties": {
    "addr:full":"2100 Bloor St W Toronto ON M6S 1M7",
    "addr:housenumber":"2100",
    "addr:postcode":"m6s 1m7",
    "addr:street":"Bloor St W",
    "iso:country":"CA",
    "sg:address":"2100 Bloor St W",
    "sg:city":"Toronto",
    "sg:classifiers":[
        {
            "category":"Real Estate",
            "subcategory":"Real Estate Agent",
            "type":"Services"
        }
    ],
    "sg:phone":"+1 416 656 0036",
    "sg:postcode":"M6S 1M7",
    "sg:province":"ON",
    "sg:tags":[
        "consultant"
    ],
    "wof:name":"Haffwood Services Ltd",
    "wof:placetype":"venue"
},
  "geometry": {"coordinates":[-79.4706497192,43.6525115967],"type":"Point"}
}