{
  "type": "Feature",
  "properties": {
    "addr:full":"63 3rd St Weyburn SK S4H 0W1",
    "addr:housenumber":"63",
    "addr:postcode":"s4h 0w1",
    "addr:street":"3Rd St",
    "iso:country":"CA",
    "sg:address":"63 3rd St",
    "sg:city":"Weyburn",
    "sg:classifiers":[
        {
            "category":"Shopping",
            "subcategory":"Bicycles & Sporting Goods",
            "type":"Retail Goods"
        }
    ],
    "sg:phone":"+1 306 842 1711",
    "sg:postcode":"S4H 0W1",
    "sg:province":"SK",
    "wof:name":"Hoium's Mvp Sports",
    "wof:placetype":"venue"
},
  "geometry": {"coordinates":[-103.854141,49.661221],"type":"Point"}
}