{
  "type": "Feature",
  "properties": {
    "addr:full":"Bonaventure QC G0C 1E0",
    "addr:postcode":"g0c 1e0",
    "iso:country":"CA",
    "sg:city":"Bonaventure",
    "sg:classifiers":[
        {
            "category":"Government",
            "subcategory":"Office",
            "type":"Public Place"
        }
    ],
    "sg:phone":"+1 418 534 4431",
    "sg:postcode":"G0C 1E0",
    "sg:province":"QC",
    "wof:name":"Quebec Affaires Culturelles",
    "wof:placetype":"venue"
},
  "geometry": {"coordinates":[-65.485191,48.048817],"type":"Point"}
}