{
  "type": "Feature",
  "properties": {
    "addr:full":"330 6th Ave Ladysmith BC V9G 1A2",
    "addr:housenumber":"330",
    "addr:postcode":"v9g 1a2",
    "addr:street":"6Th Ave",
    "iso:country":"CA",
    "sg:address":"330 6th Ave",
    "sg:city":"Ladysmith",
    "sg:classifiers":[
        {
            "category":"Government",
            "subcategory":"Office",
            "type":"Public Place"
        }
    ],
    "sg:phone":"+1 250 245 6400",
    "sg:postcode":"V9G 1A2",
    "sg:province":"BC",
    "sg:tags":[
        "village"
    ],
    "wof:name":"Ladysmith Public Works",
    "wof:placetype":"venue"
},
  "geometry": {"coordinates":[-123.822754,48.988106],"type":"Point"}
}