{
  "type": "Feature",
  "properties": {
    "iso:country":"CA",
    "sg:address":"2777 6th Ave W",
    "sg:city":"Prince Albert",
    "sg:classifiers":[
        {
            "category":"Organizations",
            "subcategory":"Religious Organization",
            "type":"Services"
        }
    ],
    "sg:phone":"+1 306 763 3771",
    "sg:postcode":"S6V 5L4",
    "sg:province":"SK",
    "sg:tags":[
        "church"
    ],
    "wof:name":"Alliance Church",
    "wof:placetype":"venue"
},
  "geometry": {"coordinates":[-105.76992799999999,53.187805],"type":"Point"}
}