{
  "type": "Feature",
  "properties": {
    "addr:full":"375 Cliffe Ave Courtenay BC V9N 2J1",
    "addr:housenumber":"375",
    "addr:postcode":"v9n 2j1",
    "addr:street":"Cliffe Ave",
    "iso:country":"CA",
    "sg:address":"375 Cliffe Ave",
    "sg:city":"Courtenay",
    "sg:classifiers":[
        {
            "category":"Government",
            "subcategory":"Office",
            "type":"Public Place"
        }
    ],
    "sg:phone":"+1 250 334 3424",
    "sg:postcode":"V9N 2J1",
    "sg:province":"BC",
    "wof:name":"Canada Revenue",
    "wof:placetype":"venue"
},
  "geometry": {"coordinates":[-124.99820699999999,49.692318],"type":"Point"}
}