{
  "type": "Feature",
  "properties": {
    "addr:full":"661 Edinburgh Rd S Guelph ON N1G 4H6",
    "addr:housenumber":"661",
    "addr:postcode":"n1g 4h6",
    "addr:street":"Edinburgh Rd",
    "iso:country":"CA",
    "sg:address":"661 Edinburgh Rd S",
    "sg:city":"Guelph",
    "sg:classifiers":[
        {
            "category":"Social Services",
            "subcategory":"Child Care",
            "type":"Services"
        }
    ],
    "sg:phone":"+1 519 763 4679",
    "sg:postcode":"N1G 4H6",
    "sg:province":"ON",
    "wof:name":"Teddy Bear's Picnic Child Care",
    "wof:placetype":"venue"
},
  "geometry": {"coordinates":[-80.224754,43.515827],"type":"Point"}
}