{
  "type": "Feature",
  "properties": {
    "addr:full":"2628 Rue Bernard-Pilon Saint-Mathieu-DE-Beloeil QC J3G 4S5",
    "addr:housenumber":"2628",
    "addr:postcode":"j3g 4s5",
    "addr:street":"Rue Bernard-Pilon",
    "iso:country":"CA",
    "sg:address":"2628 Rue Bernard-Pilon",
    "sg:city":"Saint-Mathieu-DE-Beloeil",
    "sg:classifiers":[
        {
            "category":"Manufacturing",
            "subcategory":"Electronics",
            "type":"Manufacturing & Wholesale Goods"
        }
    ],
    "sg:phone":"+1 450 464 4220",
    "sg:postcode":"J3G 4S5",
    "sg:province":"QC",
    "sg:tags":[
        "equipment",
        "electronic",
        "supply"
    ],
    "wof:name":"Instruments Controle Jgg Inc",
    "wof:placetype":"venue"
},
  "geometry": {"coordinates":[-73.255585,45.574917],"type":"Point"}
}