{
  "type": "Feature",
  "properties": {
    "addr:full":"300 Rue Des Bouleaux Charlemagne QC J5Z 4A7",
    "addr:housenumber":"300",
    "addr:postcode":"j5z 4a7",
    "addr:street":"Rue Des Bouleaux",
    "iso:country":"CA",
    "sg:address":"300 Rue Des Bouleaux",
    "sg:city":"Charlemagne",
    "sg:classifiers":[
        {
            "category":"Organizations",
            "subcategory":"Non-profit Organization",
            "type":"Services"
        }
    ],
    "sg:phone":"+1 450 654 3871",
    "sg:postcode":"J5Z 4A7",
    "sg:province":"QC",
    "sg:tags":[
        "charitable",
        "institution"
    ],
    "wof:name":"Fin A LA Faim",
    "wof:placetype":"venue"
},
  "geometry": {"coordinates":[-73.497177124,45.7341003418],"type":"Point"}
}