{
  "type": "Feature",
  "properties": {
    "addr:full":"3891 Chatham St Richmond BC V7E 2Z6",
    "addr:housenumber":"3891",
    "addr:postcode":"v7e 2z6",
    "addr:street":"Chatham St",
    "iso:country":"CA",
    "sg:address":"3891 Chatham St",
    "sg:city":"Richmond",
    "sg:classifiers":[
        {
            "category":"Shopping",
            "subcategory":"Gifts & Souvenirs",
            "type":"Retail Goods"
        }
    ],
    "sg:phone":"+1 604 448 1867",
    "sg:postcode":"V7E 2Z6",
    "sg:province":"BC",
    "sg:tags":[
        "shop",
        "picture",
        "frame"
    ],
    "wof:name":"Phoenix Coastal Art CO",
    "wof:placetype":"venue"
},
  "geometry": {"coordinates":[-123.18203699999999,49.126545],"type":"Point"}
}