{
  "type": "Feature",
  "properties": {
    "iso:country":"CA",
    "sg:address":"9919 Prince Philip St",
    "sg:city":"Thedford",
    "sg:classifiers":[
        {
            "category":"Manufacturing",
            "subcategory":"Signs",
            "type":"Manufacturing & Wholesale Goods"
        }
    ],
    "sg:phone":"+1 519 243 3910",
    "sg:postcode":"N0M 2N0",
    "sg:province":"ON",
    "wof:name":"Tella Sign",
    "wof:placetype":"venue"
},
  "geometry": {"coordinates":[-81.8614730835,43.2169837952],"type":"Point"}
}