{
  "type": "Feature",
  "properties": {
    "iso:country":"CA",
    "sg:address":"6693 Boul Thimens",
    "sg:city":"Saint-Laurent",
    "sg:classifiers":[
        {
            "category":"Professional",
            "subcategory":"Management & Consulting",
            "type":"Services"
        }
    ],
    "sg:phone":"+1 514 694 7589",
    "sg:postcode":"H4S 1W2",
    "sg:province":"QC",
    "sg:tags":[
        "marketing",
        "consultant"
    ],
    "wof:name":"Lbc Consulting Svc",
    "wof:placetype":"venue"
},
  "geometry": {"coordinates":[-73.7393569946,45.5047874451],"type":"Point"}
}