{
  "type": "Feature",
  "properties": {
    "addr:full":"1999 Ch Val-Doucet Val-Doucet NB E8R 1Z5",
    "addr:housenumber":"1999",
    "addr:postcode":"e8r 1z5",
    "addr:street":"Ch Val-Doucet Val-Doucet",
    "iso:country":"CA",
    "sg:address":"1999 Ch Val-Doucet",
    "sg:city":"Val-Doucet",
    "sg:classifiers":[
        {
            "category":"Freight",
            "type":"Transportation"
        }
    ],
    "sg:phone":"+1 506 764 8004",
    "sg:postcode":"E8R 1Z5",
    "sg:province":"NB",
    "sg:tags":[
        "repairing",
        "automobile",
        "trucking"
    ],
    "wof:name":"Bbt Transport",
    "wof:placetype":"venue"
},
  "geometry": {"coordinates":[-65.220268,47.610355],"type":"Point"}
}