{
  "type": "Feature",
  "properties": {
    "addr:full":"1300 Boul Saint-Jean-Baptiste Pointe-Aux-Trembles QC H1B 4A4",
    "addr:housenumber":"1300",
    "addr:postcode":"h1b 4a4",
    "addr:street":"Boul Saint-Jean-Baptiste",
    "iso:country":"CA",
    "sg:address":"1300 Boul Saint-Jean-Baptiste",
    "sg:city":"Pointe-Aux-Trembles",
    "sg:classifiers":[
        {
            "category":"Restaurant",
            "type":"Food & Drink"
        }
    ],
    "sg:phone":"+1 514 645 1481",
    "sg:postcode":"H1B 4A4",
    "sg:province":"QC",
    "wof:name":"Restaurant LA Belle Province",
    "wof:placetype":"venue"
},
  "geometry": {"coordinates":[-73.5019989014,45.6417427063],"type":"Point"}
}