{
  "type": "Feature",
  "properties": {
    "addr:full":"116 Rue Lois Hull QC J8Y 3R7",
    "addr:housenumber":"116",
    "addr:postcode":"j8y 3r7",
    "addr:street":"Rue Lois",
    "iso:country":"CA",
    "sg:address":"116 Rue Lois",
    "sg:city":"Hull",
    "sg:classifiers":[
        {
            "category":"Building & Trades",
            "subcategory":"Construction",
            "type":"Services"
        }
    ],
    "sg:phone":"+1 819 770 3038",
    "sg:postcode":"J8Y 3R7",
    "sg:province":"QC",
    "sg:tags":[
        "general",
        "contractor"
    ],
    "wof:name":"Joseph Pelletier Ltee",
    "wof:placetype":"venue"
},
  "geometry": {"coordinates":[-75.7318649292,45.43592453],"type":"Point"}
}