{
  "type": "Feature",
  "properties": {
    "addr:full":"539 Grand Valley Dr Cambridge ON N3H 2S2",
    "addr:housenumber":"539",
    "addr:postcode":"n3h 2s2",
    "addr:street":"Grand Valley Dr",
    "iso:country":"CA",
    "sg:address":"539 Grand Valley Dr",
    "sg:city":"Cambridge",
    "sg:classifiers":[
        {
            "category":"Professional",
            "subcategory":"Computer Services",
            "type":"Services"
        }
    ],
    "sg:phone":"+1 519 650 0660",
    "sg:postcode":"N3H 2S2",
    "sg:province":"ON",
    "sg:tags":[
        "consultant"
    ],
    "wof:name":"A J Lill Consultants",
    "wof:placetype":"venue"
},
  "geometry": {"coordinates":[-80.339478,43.389381],"type":"Point"}
}