{
  "type": "Feature",
  "properties": {
    "addr:full":"General Delivery Tehkummah ON P0P 2C0",
    "addr:postcode":"p0p 2c0",
    "iso:country":"CA",
    "sg:address":"General Delivery",
    "sg:city":"Tehkummah",
    "sg:classifiers":[
        {
            "category":"Building & Trades",
            "subcategory":"Plumbing",
            "type":"Services"
        }
    ],
    "sg:phone":"+1 705 859 3774",
    "sg:postcode":"P0P 2C0",
    "sg:province":"ON",
    "sg:tags":[
        "sheet",
        "work",
        "metal",
        "heating",
        "contractor"
    ],
    "wof:name":"Scott's Plumbing Htg & Elec",
    "wof:placetype":"venue"
},
  "geometry": {"coordinates":[-82.003494,45.649555],"type":"Point"}
}