{
  "type": "Feature",
  "properties": {
    "addr:full":"982 Rue DE L'Eglise Saint-Jean-Chrysostome QC G6Z 3H7",
    "addr:housenumber":"982",
    "addr:postcode":"g6z 3h7",
    "addr:street":"Rue De L'Eglise Saint-Jean-Chrysostome",
    "iso:country":"CA",
    "sg:address":"982 Rue DE L'Eglise",
    "sg:city":"Saint-Jean-Chrysostome",
    "sg:classifiers":[
        {
            "category":"Health Services",
            "subcategory":"Nursing And Care Facility",
            "type":"Services"
        }
    ],
    "sg:phone":"+1 418 839 2260",
    "sg:postcode":"G6Z 3H7",
    "sg:province":"QC",
    "sg:tags":[
        "home",
        "retirement",
        "community"
    ],
    "wof:name":"Villa St-Jean",
    "wof:placetype":"venue"
},
  "geometry": {"coordinates":[-71.1913909912,46.7214393616],"type":"Point"}
}