{
  "type": "Feature",
  "properties": {
    "iso:country":"CA",
    "sg:address":"489 Main St E",
    "sg:city":"Cambridge",
    "sg:classifiers":[
        {
            "category":"Retail",
            "subcategory":"Veterinary Services",
            "type":"Services"
        }
    ],
    "sg:phone":"+1 519 622 6988",
    "sg:postcode":"N1R 5S7",
    "sg:province":"ON",
    "sg:tags":[
        "veterinarian"
    ],
    "wof:name":"Rich, Peter DVM",
    "wof:placetype":"venue"
},
  "geometry": {"coordinates":[-80.2895812988,43.3576889038],"type":"Point"}
}