{
  "type": "Feature",
  "properties": {
    "addr:full":"14300 Entertainment Blvd Richmond BC V6W 1K3",
    "addr:housenumber":"14300",
    "addr:postcode":"v6w 1k3",
    "addr:street":"Entertainment Blvd",
    "iso:country":"CA",
    "sg:address":"14300 Entertainment Blvd",
    "sg:city":"Richmond",
    "sg:classifiers":[
        {
            "category":"Recreation",
            "type":"Entertainment"
        }
    ],
    "sg:phone":"+1 604 448 5353",
    "sg:postcode":"V6W 1K3",
    "sg:province":"BC",
    "sg:tags":[
        "pool",
        "swimming"
    ],
    "wof:name":"Watermania",
    "wof:placetype":"venue"
},
  "geometry": {"coordinates":[-123.064156,49.135185],"type":"Point"}
}