{
  "type": "Feature",
  "properties": {
    "iso:country":"CA",
    "sg:address":"390 Rue DE Bernieres",
    "sg:city":"Quebec",
    "sg:classifiers":[
        {
            "category":"Government",
            "subcategory":"Office",
            "type":"Public Place"
        }
    ],
    "sg:phone":"+1 418 648 3506",
    "sg:postcode":"G1R 2L7",
    "sg:province":"QC",
    "wof:name":"Canada National Battlefields",
    "wof:placetype":"venue"
},
  "geometry": {"coordinates":[-71.218575,46.803169],"type":"Point"}
}