{
  "type": "Feature",
  "properties": {
    "iso:country":"CA",
    "sg:city":"Edmonton",
    "sg:classifiers":[
        {
            "category":"Real Estate",
            "subcategory":"Real Estate Operator",
            "type":"Services"
        }
    ],
    "sg:phone":"+1 780 428 6488",
    "sg:postcode":"T5K 0Y6",
    "sg:province":"AB",
    "sg:tags":[
        "apartment"
    ],
    "wof:name":"Rowand House",
    "wof:placetype":"venue"
},
  "geometry": {"coordinates":[-113.499015808,53.5348396301],"type":"Point"}
}