{
  "type": "Feature",
  "properties": {
    "addr:full":"Tavistock ON N0B 2R0",
    "addr:postcode":"n0b 2r0",
    "iso:country":"CA",
    "sg:city":"Tavistock",
    "sg:classifiers":[
        {
            "category":"Retail",
            "subcategory":"Repair Shop",
            "type":"Services"
        }
    ],
    "sg:phone":"+1 519 462 2121",
    "sg:postcode":"N0B 2R0",
    "sg:province":"ON",
    "sg:tags":[
        "welding"
    ],
    "wof:name":"Jrw Custom Welding",
    "wof:placetype":"venue"
},
  "geometry": {"coordinates":[-80.83616600000001,43.321362],"type":"Point"}
}