{
  "type": "Feature",
  "properties": {
    "addr:full":"Richmond BC V6V 1Z4",
    "addr:postcode":"v6v 1z4",
    "iso:country":"CA",
    "sg:city":"Richmond",
    "sg:classifiers":[
        {
            "category":"Manufacturing",
            "subcategory":"Electronics",
            "type":"Manufacturing & Wholesale Goods"
        }
    ],
    "sg:phone":"+1 604 276 9717",
    "sg:postcode":"V6V 1Z4",
    "sg:province":"BC",
    "sg:tags":[
        "printed",
        "circuit",
        "etched"
    ],
    "wof:name":"Omni Graphics Ltd",
    "wof:placetype":"venue"
},
  "geometry": {"coordinates":[-123.083724976,49.1890144348],"type":"Point"}
}