{
  "type": "Feature",
  "properties": {
    "addr:full":"8 Shawinigan Manitouwadge ON P0T 2C0",
    "addr:housenumber":"8",
    "addr:postcode":"p0t 2c0",
    "iso:country":"CA",
    "sg:address":"8 Shawinigan",
    "sg:city":"Manitouwadge",
    "sg:classifiers":[
        {
            "category":"Organizations",
            "subcategory":"Religious Organization",
            "type":"Services"
        }
    ],
    "sg:phone":"+1 807 826 3897",
    "sg:postcode":"P0T 2C0",
    "sg:province":"ON",
    "sg:tags":[
        "church"
    ],
    "wof:name":"St Paul's United Church",
    "wof:placetype":"venue"
},
  "geometry": {"coordinates":[-85.83766900000001,49.126881],"type":"Point"}
}