{
  "type": "Feature",
  "properties": {
    "addr:full":"1095 Murray Dr Williams Lake BC V2G 4K8",
    "addr:housenumber":"1095",
    "addr:postcode":"v2g 4k8",
    "addr:street":"Murray Dr",
    "iso:country":"CA",
    "sg:address":"1095 Murray Dr",
    "sg:city":"Williams Lake",
    "sg:classifiers":[
        {
            "category":"Freight",
            "type":"Transportation"
        }
    ],
    "sg:phone":"+1 250 398 5585",
    "sg:postcode":"V2G 4K8",
    "sg:province":"BC",
    "sg:tags":[
        "courier"
    ],
    "wof:name":"Canpar Transport Ltd",
    "wof:placetype":"venue"
},
  "geometry": {"coordinates":[-122.16023300000001,52.141632],"type":"Point"}
}