{
  "type": "Feature",
  "properties": {
    "iso:country":"CA",
    "sg:address":"340 Dosco Dr",
    "sg:city":"Stoney Creek",
    "sg:classifiers":[
        {
            "category":"Building & Trades",
            "subcategory":"Construction",
            "type":"Services"
        }
    ],
    "sg:phone":"+1 905 662 3353",
    "sg:postcode":"L8E 2N5",
    "sg:province":"ON",
    "sg:tags":[
        "machine",
        "shop",
        "balancing"
    ],
    "wof:name":"R & S Technical Svc Ltd",
    "wof:placetype":"venue"
},
  "geometry": {"coordinates":[-79.7202529907,43.2295265198],"type":"Point"}
}