{
  "type": "Feature",
  "properties": {
    "iso:country":"CA",
    "sg:city":"Orleans",
    "sg:classifiers":[
        {
            "category":"Health Services",
            "subcategory":"Health Practitioner",
            "type":"Services"
        }
    ],
    "sg:phone":"+1 613 834 6508",
    "sg:postcode":"K1C 6Z7",
    "sg:province":"ON",
    "sg:tags":[
        "nurse",
        "registry"
    ],
    "wof:name":"Continental Health Care Svc",
    "wof:placetype":"venue"
},
  "geometry": {"coordinates":[-75.5487747192,45.4649238586],"type":"Point"}
}