{
  "type": "Feature",
  "properties": {
    "addr:full":"North York ON M9M 2Z3",
    "addr:postcode":"m9m 2z3",
    "iso:country":"CA",
    "sg:city":"North York",
    "sg:classifiers":[
        {
            "category":"Organizations",
            "subcategory":"Professional Association",
            "type":"Services"
        }
    ],
    "sg:phone":"+1 416 744 9289",
    "sg:postcode":"M9M 2Z3",
    "sg:province":"ON",
    "wof:name":"Afghan Association of Ontario",
    "wof:placetype":"venue"
},
  "geometry": {"coordinates":[-79.532089,43.749355],"type":"Point"}
}