{
  "type": "Feature",
  "properties": {
    "addr:full":"1895 Boul DE Comporte LA Malbaie QC G5A 1N9",
    "addr:housenumber":"1895",
    "addr:postcode":"g5a 1n9",
    "addr:street":"Boul De Comporte",
    "iso:country":"CA",
    "sg:address":"1895 Boul DE Comporte",
    "sg:city":"LA Malbaie",
    "sg:classifiers":[
        {
            "category":"Manufacturing",
            "subcategory":"Tools & Machinery",
            "type":"Manufacturing & Wholesale Goods"
        }
    ],
    "sg:phone":"+1 418 665 7551",
    "sg:postcode":"G5A 1N9",
    "sg:province":"QC",
    "sg:tags":[
        "machine",
        "shop"
    ],
    "wof:name":"Usinages DE LA Malbaie",
    "wof:placetype":"venue"
},
  "geometry": {"coordinates":[-70.177322,47.674122],"type":"Point"}
}