{
  "type": "Feature",
  "properties": {
    "addr:full":"Canmore AB T1W 1P5",
    "addr:postcode":"t1w 1p5",
    "iso:country":"CA",
    "sg:city":"Canmore",
    "sg:classifiers":[
        {
            "category":"Personal",
            "subcategory":"Beauty Salon",
            "type":"Services"
        }
    ],
    "sg:phone":"+1 403 678 9388",
    "sg:postcode":"T1W 1P5",
    "sg:province":"AB",
    "wof:name":"Satori Day Spa",
    "wof:placetype":"venue"
},
  "geometry": {"coordinates":[-115.35058600000001,51.090981],"type":"Point"}
}