{
  "type": "Feature",
  "properties": {
    "iso:country":"CA",
    "sg:city":"Edmonton",
    "sg:classifiers":[
        {
            "category":"Health Services",
            "subcategory":"Clinic",
            "type":"Services"
        }
    ],
    "sg:phone":"+1 780 488 7282",
    "sg:postcode":"T5K 2J1",
    "sg:province":"AB",
    "sg:tags":[
        "home",
        "nurse",
        "registry"
    ],
    "wof:name":"Edmonton Home Svc Ltd",
    "wof:placetype":"venue"
},
  "geometry": {"coordinates":[-113.514167786,53.5399055481],"type":"Point"}
}