{
  "type": "Feature",
  "properties": {
    "addr:full":"Hull QC J8Y 6M1",
    "addr:postcode":"j8y 6m1",
    "iso:country":"CA",
    "sg:city":"Hull",
    "sg:classifiers":[
        {
            "category":"Real Estate",
            "subcategory":"Real Estate Operator",
            "type":"Services"
        }
    ],
    "sg:phone":"+1 819 770 9730",
    "sg:postcode":"J8Y 6M1",
    "sg:province":"QC",
    "sg:tags":[
        "apartment"
    ],
    "wof:name":"Altitude",
    "wof:placetype":"venue"
},
  "geometry": {"coordinates":[-75.75369999999999,45.448425],"type":"Point"}
}