{
  "type": "Feature",
  "properties": {
    "addr:full":"2397 Fairview St Burlington ON L7R 2E3",
    "addr:housenumber":"2397",
    "addr:postcode":"l7r 2e3",
    "addr:street":"Fairview St",
    "iso:country":"CA",
    "sg:address":"2397 Fairview St",
    "sg:city":"Burlington",
    "sg:classifiers":[
        {
            "category":"Retail",
            "subcategory":"Auto Repair",
            "type":"Services"
        }
    ],
    "sg:phone":"+1 905 634 7711",
    "sg:postcode":"L7R 2E3",
    "sg:province":"ON",
    "sg:tags":[
        "muffler",
        "exhaust",
        "system"
    ],
    "wof:name":"Carline Muffler",
    "wof:placetype":"venue"
},
  "geometry": {"coordinates":[-79.80085800000001,43.344826],"type":"Point"}
}