{
  "type": "Feature",
  "properties": {
    "addr:full":"Fort Vermilion AB T0H 1N0",
    "addr:postcode":"t0h 1n0",
    "addr:street":"Fort",
    "iso:country":"CA",
    "sg:city":"Fort Vermilion",
    "sg:classifiers":[
        {
            "category":"Government",
            "subcategory":"Office",
            "type":"Public Place"
        }
    ],
    "sg:phone":"+1 780 927 3253",
    "sg:postcode":"T0H 1N0",
    "sg:province":"AB",
    "wof:name":"Canada Agriculture & Agri-Food",
    "wof:placetype":"venue"
},
  "geometry": {"coordinates":[-116.018112,58.387356],"type":"Point"}
}