{
  "type": "Feature",
  "properties": {
    "addr:full":"7790 Ch DE LA Cote-DE-Liesse Saint-Laurent QC H4T 1E7",
    "addr:postcode":"7790;h4t 1e7",
    "addr:street":"Ch De La Cote-De-Liesse",
    "iso:country":"CA",
    "sg:address":"7790 Ch DE LA Cote-DE-Liesse",
    "sg:city":"Saint-Laurent",
    "sg:classifiers":[
        {
            "category":"Manufacturing",
            "subcategory":"Rubber & Plastics",
            "type":"Manufacturing & Wholesale Goods"
        }
    ],
    "sg:phone":"+1 514 737 4718",
    "sg:postcode":"H4T 1E7",
    "sg:province":"QC",
    "sg:tags":[
        "forming"
    ],
    "wof:name":"Perry Mukri",
    "wof:placetype":"venue"
},
  "geometry": {"coordinates":[-73.701317,45.478031],"type":"Point"}
}