{
  "type": "Feature",
  "properties": {
    "addr:full":"2805 Boul DE LA Concorde E Laval QC H7E 2B5",
    "addr:housenumber":"2805",
    "addr:postcode":"h7e 2b5",
    "addr:street":"Boul De La Concorde E",
    "iso:country":"CA",
    "sg:address":"2805 Boul DE LA Concorde E",
    "sg:city":"Laval",
    "sg:classifiers":[
        {
            "category":"Personal",
            "subcategory":"Beauty Salon",
            "type":"Services"
        }
    ],
    "sg:phone":"+1 450 664 3366",
    "sg:postcode":"H7E 2B5",
    "sg:province":"QC",
    "wof:name":"Romanza Soins Capillaires",
    "wof:placetype":"venue"
},
  "geometry": {"coordinates":[-73.670807,45.590439],"type":"Point"}
}