{
  "type": "Feature",
  "properties": {
    "addr:full":"517 Rideau St Ottawa ON K1N 5Z5",
    "addr:housenumber":"517",
    "addr:postcode":"k1n 5z5",
    "addr:street":"Rideau St",
    "iso:country":"CA",
    "sg:address":"517 Rideau St",
    "sg:city":"Ottawa",
    "sg:classifiers":[
        {
            "category":"Shopping",
            "subcategory":"Bicycles & Sporting Goods",
            "type":"Retail Goods"
        }
    ],
    "sg:phone":"+1 613 562 2453",
    "sg:postcode":"K1N 5Z5",
    "sg:province":"ON",
    "wof:name":"Unchained Independent Cycles",
    "wof:placetype":"venue"
},
  "geometry": {"coordinates":[-75.67868,45.431873],"type":"Point"}
}