{
  "type": "Feature",
  "properties": {
    "addr:full":"3717 Sideroad 10 Bradford ON L3Z 2A5",
    "addr:housenumber":"3717",
    "addr:postcode":"l3z 2a5",
    "addr:street":"Sideroad 10",
    "iso:country":"CA",
    "sg:address":"3717 Sideroad 10",
    "sg:city":"Bradford",
    "sg:classifiers":[
        {
            "category":"Building & Trades",
            "subcategory":"Construction",
            "type":"Services"
        }
    ],
    "sg:phone":"+1 905 775 2851",
    "sg:postcode":"L3Z 2A5",
    "sg:province":"ON",
    "sg:tags":[
        "general",
        "contractor"
    ],
    "wof:name":"Hoving Construction",
    "wof:placetype":"venue"
},
  "geometry": {"coordinates":[-79.563659668,44.1145515442],"type":"Point"}
}