{
  "type": "Feature",
  "properties": {
    "iso:country":"CA",
    "sg:address":"111 5E Rue",
    "sg:city":"New Richmond",
    "sg:classifiers":[
        {
            "category":"Organizations",
            "subcategory":"Religious Organization",
            "type":"Services"
        }
    ],
    "sg:phone":"+1 418 392 6316",
    "sg:postcode":"G0C 2B0",
    "sg:province":"QC",
    "sg:tags":[
        "church"
    ],
    "wof:name":"Eglise Baptiste Evangelique",
    "wof:placetype":"venue"
},
  "geometry": {"coordinates":[-65.861885,48.163696],"type":"Point"}
}