{
  "type": "Feature",
  "properties": {
    "addr:full":"14410 96 Ave NW Edmonton AB T5N 0C7",
    "addr:housenumber":"14410",
    "addr:postcode":"t5n 0c7",
    "addr:street":"96 Ave Nw",
    "iso:country":"CA",
    "sg:address":"14410 96 Ave NW",
    "sg:city":"Edmonton",
    "sg:classifiers":[
        {
            "category":"Education",
            "subcategory":"School",
            "type":"Public Place"
        }
    ],
    "sg:phone":"+1 780 452 1510",
    "sg:postcode":"T5N 0C7",
    "sg:province":"AB",
    "wof:name":"St Paul Catholic Elementary",
    "wof:placetype":"venue"
},
  "geometry": {"coordinates":[-113.571365356,53.5332489014],"type":"Point"}
}