{
  "type": "Feature",
  "properties": {
    "addr:full":"1301 Bay Ave Trail BC V1R 4A7",
    "addr:housenumber":"1301",
    "addr:postcode":"bc v1r 4a7",
    "addr:street":"Bay Ave Trail",
    "iso:country":"CA",
    "sg:address":"1301 Bay Ave",
    "sg:city":"Trail",
    "sg:classifiers":[
        {
            "category":"Banks & Credit Unions",
            "subcategory":"Bank",
            "type":"Services"
        }
    ],
    "sg:phone":"+1 250 368 5505",
    "sg:postcode":"V1R 4A7",
    "sg:province":"BC",
    "sg:tags":[
        "loan",
        "real estate"
    ],
    "wof:name":"Citi Financial",
    "wof:placetype":"venue"
},
  "geometry": {"coordinates":[-117.70790100000001,49.096176],"type":"Point"}
}