{
  "type": "Feature",
  "properties": {
    "addr:full":"122 3rd Ave N Swan River MB R0L 1Z0",
    "addr:housenumber":"122",
    "addr:postcode":"r0l 1z0",
    "addr:street":"3Rd Ave N",
    "iso:country":"CA",
    "sg:address":"122 3rd Ave N",
    "sg:city":"Swan River",
    "sg:classifiers":[
        {
            "category":"Building & Trades",
            "subcategory":"Plumbing",
            "type":"Services"
        }
    ],
    "sg:phone":"+1 204 734 2188",
    "sg:postcode":"R0L 1Z0",
    "sg:province":"MB",
    "sg:tags":[
        "contractor"
    ],
    "wof:name":"Valley Plumbing & Heating",
    "wof:placetype":"venue"
},
  "geometry": {"coordinates":[-101.267944336,52.092918396],"type":"Point"}
}