{
  "type": "Feature",
  "properties": {
    "addr:full":"102 Bay Bulls Rd St. John's NL A1G 1A7",
    "addr:housenumber":"102",
    "addr:postcode":"a1g 1a7",
    "addr:street":"Bay Bulls Rd",
    "iso:country":"CA",
    "sg:address":"102 Bay Bulls Rd",
    "sg:city":"St. John's",
    "sg:classifiers":[
        {
            "category":"Food & Beverages",
            "subcategory":"Groceries & Convenience Stores",
            "type":"Retail Goods"
        }
    ],
    "sg:phone":"+1 709 364 2464",
    "sg:postcode":"A1G 1A7",
    "sg:province":"NL",
    "sg:tags":[
        "grocer"
    ],
    "wof:name":"Kilbride Ultramar",
    "wof:placetype":"venue"
},
  "geometry": {"coordinates":[-52.8186,47.317009],"type":"Point"}
}