{
  "type": "Feature",
  "properties": {
    "addr:full":"6420 Rue Beaubien E Montreal QC H1M 2Y1",
    "addr:housenumber":"6420",
    "addr:postcode":"h1m 2y1",
    "addr:street":"Rue Beaubien E",
    "iso:country":"CA",
    "sg:address":"6420 Rue Beaubien E",
    "sg:city":"Montreal",
    "sg:classifiers":[
        {
            "category":"Restaurant",
            "type":"Food & Drink"
        }
    ],
    "sg:phone":"+1 514 259 1282",
    "sg:postcode":"H1M 2Y1",
    "sg:province":"QC",
    "wof:name":"Pfk",
    "wof:placetype":"venue"
},
  "geometry": {"coordinates":[-73.5619354248,45.5857887268],"type":"Point"}
}