{
  "type": "Feature",
  "properties": {
    "addr:full":"210 Chain Lake Dr Halifax NS B3S 1C5",
    "addr:housenumber":"210",
    "addr:postcode":"b3s 1c5",
    "addr:street":"Chain Lake Dr",
    "iso:country":"CA",
    "sg:address":"210 Chain Lake Dr",
    "sg:city":"Halifax",
    "sg:classifiers":[
        {
            "category":"Food & Beverages",
            "subcategory":"Groceries & Convenience Stores",
            "type":"Retail Goods"
        }
    ],
    "sg:phone":"+1 902 450 5317",
    "sg:postcode":"B3S 1C5",
    "sg:province":"NS",
    "sg:tags":[
        "grocer"
    ],
    "wof:name":"Atlantic Superstore",
    "wof:placetype":"venue"
},
  "geometry": {"coordinates":[-63.6753768921,44.6502761841],"type":"Point"}
}