{
  "type": "Feature",
  "properties": {
    "addr:full":"75 Rue Daudelin Kirkland QC H9J 2J4",
    "addr:housenumber":"75",
    "addr:postcode":"h9j 2j4",
    "addr:street":"Rue Daudelin",
    "iso:country":"CA",
    "sg:address":"75 Rue Daudelin",
    "sg:city":"Kirkland",
    "sg:classifiers":[
        {
            "category":"Building & Trades",
            "subcategory":"Plumbing",
            "type":"Services"
        }
    ],
    "sg:phone":"+1 514 697 9365",
    "sg:postcode":"H9J 2J4",
    "sg:province":"QC",
    "sg:tags":[
        "conditioning",
        "air",
        "system",
        "contractor"
    ],
    "wof:name":"Lee Air Conditioning Reg'd",
    "wof:placetype":"venue"
},
  "geometry": {"coordinates":[-73.86841583250001,45.4506149292],"type":"Point"}
}