{
  "type": "Feature",
  "properties": {
    "addr:full":"306 Darrell Rd Ayr ON N0B 1E0",
    "addr:housenumber":"306",
    "addr:postcode":"n0b 1e0",
    "addr:street":"Darrell Rd",
    "iso:country":"CA",
    "sg:address":"306 Darrell Rd",
    "sg:city":"Ayr",
    "sg:classifiers":[
        {
            "category":"Manufacturing",
            "subcategory":"Furniture",
            "type":"Manufacturing & Wholesale Goods"
        }
    ],
    "sg:phone":"+1 519 622 4763",
    "sg:postcode":"N0B 1E0",
    "sg:province":"ON",
    "wof:name":"Galt Furniture Ltd",
    "wof:placetype":"venue"
},
  "geometry": {"coordinates":[-80.449997,43.285656],"type":"Point"}
}