{
  "type": "Feature",
  "properties": {
    "addr:full":"1008 Rue Achille-Fortier Boucherville QC J4B 8G7",
    "addr:housenumber":"1008",
    "addr:postcode":"j4b 8g7",
    "addr:street":"Rue Achille-Fortier",
    "iso:country":"CA",
    "sg:address":"1008 Rue Achille-Fortier",
    "sg:city":"Boucherville",
    "sg:classifiers":[
        {
            "category":"Marine",
            "type":"Transportation"
        }
    ],
    "sg:phone":"+1 450 449 2433",
    "sg:postcode":"J4B 8G7",
    "sg:province":"QC",
    "sg:tags":[
        "surveyor"
    ],
    "wof:name":"Polaris Inspection Inc",
    "wof:placetype":"venue"
},
  "geometry": {"coordinates":[-73.42622375489999,45.596912384],"type":"Point"}
}