{
  "type": "Feature",
  "properties": {
    "iso:country":"CA",
    "sg:address":"2819 Centre St NW",
    "sg:city":"Calgary",
    "sg:classifiers":[
        {
            "category":"Travel",
            "subcategory":"Travel Agent",
            "type":"Entertainment"
        }
    ],
    "sg:phone":"+1 403 283 1131",
    "sg:postcode":"T2E 2V7",
    "sg:province":"AB",
    "sg:tags":[
        "agency",
        "bureau"
    ],
    "wof:name":"Canada West Tours & Adventures",
    "wof:placetype":"venue"
},
  "geometry": {"coordinates":[-114.062721252,51.0771789551],"type":"Point"}
}