{
  "type": "Feature",
  "properties": {
    "addr:full":"7846 Boul Sainte-Anne E Chateau-Richer QC G0A 1N0",
    "addr:housenumber":"7846",
    "addr:postcode":"g0a 1n0",
    "addr:street":"Boul Sainte-Anne E Chateau-Richer",
    "iso:country":"CA",
    "sg:address":"7846 Boul Sainte-Anne E",
    "sg:city":"Chateau-Richer",
    "sg:classifiers":[
        {
            "category":"Manufacturing",
            "subcategory":"Building Materials",
            "type":"Manufacturing & Wholesale Goods"
        }
    ],
    "sg:phone":"+1 418 824 9374",
    "sg:postcode":"G0A 1N0",
    "sg:province":"QC",
    "sg:tags":[
        "molding"
    ],
    "wof:name":"Boiseries Ornementales Dpl",
    "wof:placetype":"venue"
},
  "geometry": {"coordinates":[-71.021889,46.966682],"type":"Point"}
}