{
  "type": "Feature",
  "properties": {
    "addr:full":"2750 Centre Rd St Catharines ON L2R 6P7",
    "addr:housenumber":"2750",
    "addr:postcode":"l2r 6p7",
    "addr:street":"Centre Rd",
    "iso:country":"CA",
    "sg:address":"2750 Centre Rd",
    "sg:city":"St Catharines",
    "sg:classifiers":[
        {
            "category":"Shopping",
            "subcategory":"Bicycles & Sporting Goods",
            "type":"Retail Goods"
        }
    ],
    "sg:phone":"+1 905 646 1381",
    "sg:postcode":"L2R 6P7",
    "sg:province":"ON",
    "sg:tags":[
        "gun",
        "gunsmith"
    ],
    "wof:name":"Firearms Education School",
    "wof:placetype":"venue"
},
  "geometry": {"coordinates":[-79.24011230470001,43.1624794006],"type":"Point"}
}