{
  "type": "Feature",
  "properties": {
    "addr:full":"722 Bank St Ottawa ON K1S 3V2",
    "addr:housenumber":"722",
    "addr:postcode":"k1s 3v2",
    "addr:street":"Bank St",
    "iso:country":"CA",
    "sg:address":"722 Bank St",
    "sg:city":"Ottawa",
    "sg:classifiers":[
        {
            "category":"Shopping",
            "subcategory":"Clothing, Apparel, & Fashions",
            "type":"Retail Goods"
        }
    ],
    "sg:phone":"+1 613 238 2020",
    "sg:postcode":"K1S 3V2",
    "sg:province":"ON",
    "wof:name":"Bucklands Fine Clothing",
    "wof:placetype":"venue"
},
  "geometry": {"coordinates":[-75.6893081665,45.4045028687],"type":"Point"}
}