{
  "type": "Feature",
  "properties": {
    "addr:full":"Radisson QC J0Y 2X0",
    "addr:postcode":"j0y 2x0",
    "iso:country":"CA",
    "sg:city":"Radisson",
    "sg:classifiers":[
        {
            "category":"Airport",
            "type":"Transportation"
        }
    ],
    "sg:phone":"+1 819 638 3426",
    "sg:postcode":"J0Y 2X0",
    "sg:province":"QC",
    "sg:tags":[
        "aircraft",
        "maintenance"
    ],
    "wof:name":"Valpiro Inc",
    "wof:placetype":"venue"
},
  "geometry": {"coordinates":[-77.66571,53.730625],"type":"Point"}
}