{
  "type": "Feature",
  "properties": {
    "addr:full":"442 Boul Saint-Joseph Hull QC J8Y 3Y7",
    "addr:housenumber":"442",
    "addr:postcode":"j8y 3y7",
    "addr:street":"Boul Saint-Joseph",
    "iso:country":"CA",
    "sg:address":"442 Boul Saint-Joseph",
    "sg:city":"Hull",
    "sg:classifiers":[
        {
            "category":"Shopping",
            "subcategory":"Clothing, Apparel, & Fashions",
            "type":"Retail Goods"
        }
    ],
    "sg:phone":"+1 819 770 2001",
    "sg:postcode":"J8Y 3Y7",
    "sg:province":"QC",
    "wof:name":"Chatelaine Corsetiere Inc",
    "wof:placetype":"venue"
},
  "geometry": {"coordinates":[-75.732483,45.445824],"type":"Point"}
}