{
  "type": "Feature",
  "properties": {
    "addr:full":"1011 Rue Hebert Desbiens QC G0W 1N0",
    "addr:housenumber":"1011",
    "addr:postcode":"g0w 1n0",
    "addr:street":"Rue Hebert",
    "iso:country":"CA",
    "sg:address":"1011 Rue Hebert",
    "sg:city":"Desbiens",
    "sg:classifiers":[
        {
            "category":"Food & Beverages",
            "subcategory":"Groceries & Convenience Stores",
            "type":"Retail Goods"
        }
    ],
    "sg:phone":"+1 418 346 5335",
    "sg:postcode":"G0W 1N0",
    "sg:province":"QC",
    "sg:tags":[
        "grocer"
    ],
    "wof:name":"Magasin CO-OP DE Desbiens",
    "wof:placetype":"venue"
},
  "geometry": {"coordinates":[-71.948418,48.417828],"type":"Point"}
}