{
  "type": "Feature",
  "properties": {
    "iso:country":"CA",
    "sg:city":"Guelph",
    "sg:classifiers":[
        {
            "category":"Freight",
            "type":"Transportation"
        }
    ],
    "sg:phone":"+1 519 763 3704",
    "sg:postcode":"N1E 6V8",
    "sg:province":"ON",
    "sg:tags":[
        "trucking",
        "welding"
    ],
    "wof:name":"Choice Transportation Svc Inc",
    "wof:placetype":"venue"
},
  "geometry": {"coordinates":[-80.231689,43.54982],"type":"Point"}
}