{
  "type": "Feature",
  "properties": {
    "addr:full":"Campbell River BC V9W 3N7",
    "addr:postcode":"v9w 3n7",
    "iso:country":"CA",
    "sg:city":"Campbell River",
    "sg:classifiers":[
        {
            "category":"Shopping",
            "subcategory":"Crafts & Fabrics",
            "type":"Retail Goods"
        }
    ],
    "sg:phone":"+1 250 286 3600",
    "sg:postcode":"V9W 3N7",
    "sg:province":"BC",
    "sg:tags":[
        "shop"
    ],
    "wof:name":"Fabricland",
    "wof:placetype":"venue"
},
  "geometry": {"coordinates":[-125.258605957,50.0234794617],"type":"Point"}
}