{
  "type": "Feature",
  "properties": {
    "addr:full":"276 Ste Agathe St Ste Agathe MB R0G 1Y0",
    "addr:housenumber":"276",
    "addr:postcode":"r0g 1y0",
    "addr:street":"Ste Agathe St Ste Agathe",
    "iso:country":"CA",
    "sg:address":"276 Ste Agathe St",
    "sg:city":"Ste Agathe",
    "sg:classifiers":[
        {
            "category":"Arena",
            "subcategory":"Sports Club",
            "type":"Entertainment"
        }
    ],
    "sg:phone":"+1 204 882 2440",
    "sg:postcode":"R0G 1Y0",
    "sg:province":"MB",
    "sg:tags":[
        "athletic",
        "fields",
        "stadium"
    ],
    "wof:name":"Ste Agathe Arena",
    "wof:placetype":"venue"
},
  "geometry": {"coordinates":[-97.1465911865,49.6004867554],"type":"Point"}
}