{
  "type": "Feature",
  "properties": {
    "addr:full":"Calgary AB T2P 4K1",
    "addr:postcode":"t2p 4k1",
    "iso:country":"CA",
    "sg:city":"Calgary",
    "sg:classifiers":[
        {
            "category":"Mining & Drilling",
            "type":"Manufacturing & Wholesale Goods"
        }
    ],
    "sg:phone":"+1 403 274 2718",
    "sg:postcode":"T2P 4K1",
    "sg:province":"AB",
    "sg:tags":[
        "consultant",
        "oil",
        "gas"
    ],
    "wof:name":"Drillpro Engineering Corp",
    "wof:placetype":"venue"
},
  "geometry": {"coordinates":[-114.068489075,51.0455627441],"type":"Point"}
}