{
  "type": "Feature",
  "properties": {
    "iso:country":"CA",
    "sg:address":"155 Signet Dr",
    "sg:city":"North York",
    "sg:classifiers":[
        {
            "category":"Professional",
            "subcategory":"Business Services",
            "type":"Services"
        }
    ],
    "sg:phone":"+1 416 746 0616",
    "sg:postcode":"M9L 1V1",
    "sg:province":"ON",
    "sg:tags":[
        "paper",
        "lamination"
    ],
    "wof:name":"Laminated Textiles Ltd",
    "wof:placetype":"venue"
},
  "geometry": {"coordinates":[-79.540314,43.764042],"type":"Point"}
}