{
  "type": "Feature",
  "properties": {
    "addr:full":"51 Durham Madoc ON K0K 2K0",
    "addr:housenumber":"51",
    "addr:postcode":"k0k 2k0",
    "addr:street":"Durham",
    "iso:country":"CA",
    "sg:address":"51 Durham",
    "sg:city":"Madoc",
    "sg:classifiers":[
        {
            "category":"Organizations",
            "subcategory":"Professional Association",
            "type":"Services"
        }
    ],
    "sg:phone":"+1 613 473 4697",
    "sg:postcode":"K0K 2K0",
    "sg:province":"ON",
    "wof:name":"Madoc Odd Fellows & Rebeccas",
    "wof:placetype":"venue"
},
  "geometry": {"coordinates":[-77.472786,44.505997],"type":"Point"}
}