{
  "type": "Feature",
  "properties": {
    "iso:country":"CA",
    "sg:address":"1006 Wellington St",
    "sg:city":"London",
    "sg:classifiers":[
        {
            "category":"Shopping",
            "subcategory":"Musical Instruments",
            "type":"Retail Goods"
        }
    ],
    "sg:phone":"+1 519 438 7340",
    "sg:postcode":"N6A 3T4",
    "sg:province":"ON",
    "sg:tags":[
        "photographer"
    ],
    "wof:name":"Gabriel Kney Photography",
    "wof:placetype":"venue"
},
  "geometry": {"coordinates":[-81.2561798096,43.0066146851],"type":"Point"}
}