{
  "type": "Feature",
  "properties": {
    "iso:country":"CA",
    "sg:address":"5036 49 St",
    "sg:city":"Provost",
    "sg:classifiers":[
        {
            "category":"Cinema",
            "subcategory":"Movie Theater",
            "type":"Entertainment"
        }
    ],
    "sg:phone":"+1 780 753 8044",
    "sg:postcode":"T0B 3S0",
    "sg:province":"AB",
    "wof:name":"Reel Entertainment",
    "wof:placetype":"venue"
},
  "geometry": {"coordinates":[-110.26319122300001,52.3523788452],"type":"Point"}
}