{
  "type": "Feature",
  "properties": {
    "addr:full":"208 Midpark Way SE Calgary AB T2X 1J6",
    "addr:housenumber":"208",
    "addr:postcode":"t2x 1j6",
    "addr:street":"Midpark Way Se",
    "iso:country":"CA",
    "sg:address":"208 Midpark Way SE",
    "sg:city":"Calgary",
    "sg:classifiers":[
        {
            "category":"Restaurant",
            "type":"Food & Drink"
        }
    ],
    "sg:phone":"+1 403 256 5199",
    "sg:postcode":"T2X 1J6",
    "sg:province":"AB",
    "sg:tags":[
        "pizza"
    ],
    "wof:name":"Little Caesars Pizza",
    "wof:placetype":"venue"
},
  "geometry": {"coordinates":[-114.062393,50.912983],"type":"Point"}
}