{
  "type": "Feature",
  "properties": {
    "addr:full":"333 Edwards Ave The Pas MB R9A 1L7",
    "addr:housenumber":"333",
    "addr:postcode":"r9a 1l7",
    "addr:street":"Edwards Ave",
    "iso:country":"CA",
    "sg:address":"333 Edwards Ave",
    "sg:city":"The Pas",
    "sg:classifiers":[
        {
            "category":"Home & Garden",
            "subcategory":"Hardware",
            "type":"Retail Goods"
        }
    ],
    "sg:phone":"+1 204 623 6454",
    "sg:postcode":"R9A 1L7",
    "sg:province":"MB",
    "wof:name":"True Value",
    "wof:placetype":"venue"
},
  "geometry": {"coordinates":[-101.250587,53.823448],"type":"Point"}
}