{
  "type": "Feature",
  "properties": {
    "addr:full":"1925 Merivale Rd Nepean ON K2G 1E7",
    "addr:housenumber":"1925",
    "addr:postcode":"k2g 1e7",
    "addr:street":"Merivale Rd",
    "iso:country":"CA",
    "sg:address":"1925 Merivale Rd",
    "sg:city":"Nepean",
    "sg:classifiers":[
        {
            "category":"Autos & Motor Vehicles",
            "subcategory":"Fuel & Gas Station",
            "type":"Retail Goods"
        }
    ],
    "sg:phone":"+1 613 228 7226",
    "sg:postcode":"K2G 1E7",
    "sg:province":"ON",
    "sg:tags":[
        "propane",
        "oil"
    ],
    "wof:name":"Drummond's Gas",
    "wof:placetype":"venue"
},
  "geometry": {"coordinates":[-75.720726,45.329342],"type":"Point"}
}