{
  "type": "Feature",
  "properties": {
    "addr:full":"423 Mountain Ave Neepawa MB R0J 1H0",
    "addr:housenumber":"423",
    "addr:postcode":"r0j 1h0",
    "addr:street":"Mountain Ave",
    "iso:country":"CA",
    "sg:address":"423 Mountain Ave",
    "sg:city":"Neepawa",
    "sg:classifiers":[
        {
            "category":"Manufacturing",
            "subcategory":"Printing",
            "type":"Manufacturing & Wholesale Goods"
        }
    ],
    "sg:phone":"+1 204 476 2309",
    "sg:postcode":"R0J 1H0",
    "sg:province":"MB",
    "sg:tags":[
        "printer"
    ],
    "wof:name":"Neepawa Press Printing",
    "wof:placetype":"venue"
},
  "geometry": {"coordinates":[-99.466301,50.22757],"type":"Point"}
}