{
  "type": "Feature",
  "properties": {
    "iso:country":"CA",
    "sg:city":"Langley",
    "sg:classifiers":[
        {
            "category":"Shopping",
            "subcategory":"Musical Instruments",
            "type":"Retail Goods"
        }
    ],
    "sg:phone":"+1 604 530 8704",
    "sg:postcode":"V2Y 1A2",
    "sg:province":"BC",
    "sg:tags":[
        "music",
        "dealer"
    ],
    "wof:name":"Ward Music Ltd",
    "wof:placetype":"venue"
},
  "geometry": {"coordinates":[-122.66874694800001,49.1179466248],"type":"Point"}
}