{
  "type": "Feature",
  "properties": {
    "addr:full":"33746 Lincoln Rd Abbotsford BC V2S 1R9",
    "addr:housenumber":"33746",
    "addr:postcode":"v2s 1r9",
    "addr:street":"Lincoln Rd",
    "iso:country":"CA",
    "sg:address":"33746 Lincoln Rd",
    "sg:city":"Abbotsford",
    "sg:classifiers":[
        {
            "category":"Building & Trades",
            "subcategory":"Electrical",
            "type":"Services"
        }
    ],
    "sg:phone":"+1 604 852 2177",
    "sg:postcode":"V2S 1R9",
    "sg:province":"BC",
    "sg:tags":[
        "electric",
        "contractor"
    ],
    "wof:name":"West Star Electric Ltd",
    "wof:placetype":"venue"
},
  "geometry": {"coordinates":[-122.28990899999999,49.040783],"type":"Point"}
}