{
  "type": "Feature",
  "properties": {
    "addr:full":"42 10E Rue L'Isletville QC G0R 2C0",
    "addr:housenumber":"42",
    "addr:postcode":"g0r 2c0",
    "addr:street":"10E Rue L'Isletville",
    "iso:country":"CA",
    "sg:address":"42 10E Rue",
    "sg:city":"L'Isletville",
    "sg:classifiers":[
        {
            "category":"Personal",
            "subcategory":"Beauty Salon",
            "type":"Services"
        }
    ],
    "sg:phone":"+1 418 247 7907",
    "sg:postcode":"G0R 2C0",
    "sg:province":"QC",
    "wof:name":"Salon Le Figaro",
    "wof:placetype":"venue"
},
  "geometry": {"coordinates":[-70.33503,47.11459],"type":"Point"}
}