{
  "type": "Feature",
  "properties": {
    "addr:full":"Victoria BC V9A 4T5",
    "addr:postcode":"v9a 4t5",
    "iso:country":"CA",
    "sg:city":"Victoria",
    "sg:classifiers":[
        {
            "category":"Restaurant",
            "type":"Food & Drink"
        }
    ],
    "sg:phone":"+1 250 383 2822",
    "sg:postcode":"V9A 4T5",
    "sg:province":"BC",
    "wof:name":"Romeo's Place Warehouse",
    "wof:placetype":"venue"
},
  "geometry": {"coordinates":[-123.364517212,48.428314209],"type":"Point"}
}