{
  "type": "Feature",
  "properties": {
    "addr:full":"Block 22 -1Conc 5 Hearst ON P0L 1N0",
    "addr:housenumber":"5",
    "addr:postcode":"p0l 1n0",
    "iso:country":"CA",
    "sg:address":"Block 22 -1Conc 5",
    "sg:city":"Hearst",
    "sg:classifiers":[
        {
            "category":"Retail",
            "subcategory":"Auto Repair",
            "type":"Services"
        }
    ],
    "sg:phone":"+1 705 372 5474",
    "sg:postcode":"P0L 1N0",
    "sg:province":"ON",
    "sg:tags":[
        "repairing",
        "automobile"
    ],
    "wof:name":"Bill's Auto Repair & Solar",
    "wof:placetype":"venue"
},
  "geometry": {"coordinates":[-83.664948,49.689316],"type":"Point"}
}