{
  "type": "Feature",
  "properties": {
    "addr:full":"4140A Sladeview Cres #6 Mississauga ON L5L 6A1",
    "addr:housenumber":"4140a",
    "addr:postcode":"l5l 6a1",
    "addr:street":"Sladeview Cres # 6",
    "iso:country":"CA",
    "sg:address":"4140A Sladeview Cres #6",
    "sg:city":"Mississauga",
    "sg:classifiers":[
        {
            "category":"Wholesale",
            "subcategory":"Metals & Minerals",
            "type":"Manufacturing & Wholesale Goods"
        }
    ],
    "sg:phone":"+1 905 607 7700",
    "sg:postcode":"L5L 6A1",
    "sg:province":"ON",
    "sg:tags":[
        "wire"
    ],
    "wof:name":"Ontario Wire & Cable Inc",
    "wof:placetype":"venue"
},
  "geometry": {"coordinates":[-79.71962000000001,43.528416],"type":"Point"}
}