{
  "type": "Feature",
  "properties": {
    "addr:full":"Bashaw AB T0B 0H0",
    "addr:postcode":"t0b 0h0",
    "iso:country":"CA",
    "sg:city":"Bashaw",
    "sg:classifiers":[
        {
            "category":"Mining & Drilling",
            "type":"Manufacturing & Wholesale Goods"
        }
    ],
    "sg:phone":"+1 780 372 4062",
    "sg:postcode":"T0B 0H0",
    "sg:province":"AB",
    "sg:tags":[
        "company",
        "oil"
    ],
    "wof:name":"Enermark Inc",
    "wof:placetype":"venue"
},
  "geometry": {"coordinates":[-112.970878601,52.5837783813],"type":"Point"}
}