{
  "type": "Feature",
  "properties": {
    "addr:full":"723 9E Rue Saint-Jerome QC J7Z 2Z6",
    "addr:housenumber":"723",
    "addr:postcode":"j7z 2z6",
    "addr:street":"9E Rue Saint-Jerome",
    "iso:country":"CA",
    "sg:address":"723 9E Rue",
    "sg:city":"Saint-Jerome",
    "sg:classifiers":[
        {
            "category":"Shopping",
            "subcategory":"Florist",
            "type":"Retail Goods"
        }
    ],
    "sg:phone":"+1 450 436 3351",
    "sg:postcode":"J7Z 2Z6",
    "sg:province":"QC",
    "wof:name":"Fleuriste Jardin Laurentien",
    "wof:placetype":"venue"
},
  "geometry": {"coordinates":[-74.00351000000001,45.775009],"type":"Point"}
}