{
  "type": "Feature",
  "properties": {
    "addr:full":"1104 22nd St W Saskatoon SK S7M 0S5",
    "addr:housenumber":"1104",
    "addr:postcode":"s7m 0s5",
    "addr:street":"22Nd St W",
    "iso:country":"CA",
    "sg:address":"1104 22nd St W",
    "sg:city":"Saskatoon",
    "sg:classifiers":[
        {
            "category":"Retail",
            "subcategory":"Auto Repair",
            "type":"Services"
        }
    ],
    "sg:phone":"+1 306 374 5594",
    "sg:postcode":"S7M 0S5",
    "sg:province":"SK",
    "sg:tags":[
        "repairing",
        "automobile"
    ],
    "wof:name":"Saskatoon Auto Ctr",
    "wof:placetype":"venue"
},
  "geometry": {"coordinates":[-106.686012268,52.129486084],"type":"Point"}
}