{
  "type": "Feature",
  "properties": {
    "addr:full":"100 Penn Dr North York ON M9L 2A9",
    "addr:housenumber":"100",
    "addr:postcode":"m9l 2a9",
    "addr:street":"Penn Dr",
    "iso:country":"CA",
    "sg:address":"100 Penn Dr",
    "sg:city":"North York",
    "sg:classifiers":[
        {
            "category":"Manufacturing",
            "subcategory":"Leather Goods",
            "type":"Manufacturing & Wholesale Goods"
        }
    ],
    "sg:phone":"+1 416 747 9686",
    "sg:postcode":"M9L 2A9",
    "sg:province":"ON",
    "wof:name":"Aquarian Leather Products Inc",
    "wof:placetype":"venue"
},
  "geometry": {"coordinates":[-79.558525,43.75452],"type":"Point"}
}