{
  "type": "Feature",
  "properties": {
    "addr:full":"8810 Meadowlark Rd NW Edmonton AB T5R 5W6",
    "addr:housenumber":"8810",
    "addr:postcode":"t5r 5w6",
    "addr:street":"Meadowlark Rd Nw",
    "iso:country":"CA",
    "sg:address":"8810 Meadowlark Rd NW",
    "sg:city":"Edmonton",
    "sg:classifiers":[
        {
            "category":"Organizations",
            "subcategory":"Religious Organization",
            "type":"Services"
        }
    ],
    "sg:phone":"+1 780 489 0860",
    "sg:postcode":"T5R 5W6",
    "sg:province":"AB",
    "sg:tags":[
        "church"
    ],
    "wof:name":"Trinity United Church-Canada",
    "wof:placetype":"venue"
},
  "geometry": {"coordinates":[-113.59564209,53.521774292],"type":"Point"}
}