{
  "type": "Feature",
  "properties": {
    "addr:full":"Winnipeg MB R2M 0Y7",
    "addr:postcode":"r2m 0y7",
    "iso:country":"CA",
    "sg:city":"Winnipeg",
    "sg:classifiers":[
        {
            "category":"Real Estate",
            "subcategory":"Real Estate Operator",
            "type":"Services"
        }
    ],
    "sg:phone":"+1 204 255 9293",
    "sg:postcode":"R2M 0Y7",
    "sg:province":"MB",
    "sg:tags":[
        "apartment"
    ],
    "wof:name":"Niakwa Green",
    "wof:placetype":"venue"
},
  "geometry": {"coordinates":[-97.100838,49.854641],"type":"Point"}
}