{
  "type": "Feature",
  "properties": {
    "iso:country":"CA",
    "sg:address":"490 Main St",
    "sg:city":"Alberton",
    "sg:classifiers":[
        {
            "category":"Restaurant",
            "type":"Food & Drink"
        }
    ],
    "sg:phone":"+1 902 853 3277",
    "sg:postcode":"C0B 1B0",
    "sg:province":"PE",
    "wof:name":"Kings Restaurant",
    "wof:placetype":"venue"
},
  "geometry": {"coordinates":[-64.06452899999999,46.812496],"type":"Point"}
}