{
  "type": "Feature",
  "properties": {
    "addr:full":"110 Advance Blvd Brampton ON L6T 4J4",
    "addr:housenumber":"110",
    "addr:postcode":"l6t 4j4",
    "addr:street":"Advance Blvd",
    "iso:country":"CA",
    "sg:address":"110 Advance Blvd",
    "sg:city":"Brampton",
    "sg:classifiers":[
        {
            "category":"Retail",
            "subcategory":"Auto Repair",
            "type":"Services"
        }
    ],
    "sg:phone":"+1 905 792 7900",
    "sg:postcode":"L6T 4J4",
    "sg:province":"ON",
    "sg:tags":[
        "wrecker"
    ],
    "wof:name":"Sci Towing",
    "wof:placetype":"venue"
},
  "geometry": {"coordinates":[-79.693085,43.694942],"type":"Point"}
}