{
  "type": "Feature",
  "properties": {
    "addr:full":"8610 Horton Rd SW Calgary AB T2V 2X4",
    "addr:housenumber":"8610",
    "addr:postcode":"t2v 2x4",
    "addr:street":"Horton Rd Sw",
    "iso:country":"CA",
    "sg:address":"8610 Horton Rd SW",
    "sg:city":"Calgary",
    "sg:classifiers":[
        {
            "category":"Retail",
            "subcategory":"Auto Repair",
            "type":"Services"
        }
    ],
    "sg:phone":"+1 403 640 1040",
    "sg:postcode":"T2V 2X4",
    "sg:province":"AB",
    "sg:tags":[
        "repairing",
        "automobile"
    ],
    "wof:name":"Cortech Automotive Industries",
    "wof:placetype":"venue"
},
  "geometry": {"coordinates":[-114.074424744,50.9749488831],"type":"Point"}
}