{
  "type": "Feature",
  "properties": {
    "addr:full":"5605 Richmond Rd Nepean ON K2R 1G4",
    "addr:housenumber":"5605",
    "addr:postcode":"k2r 1g4",
    "addr:street":"Richmond Rd",
    "iso:country":"CA",
    "sg:address":"5605 Richmond Rd",
    "sg:city":"Nepean",
    "sg:classifiers":[
        {
            "category":"Building & Trades",
            "subcategory":"Landscaping Services",
            "type":"Services"
        }
    ],
    "sg:phone":"+1 613 591 1517",
    "sg:postcode":"K2R 1G4",
    "sg:province":"ON",
    "sg:tags":[
        "landscape",
        "contractor"
    ],
    "wof:name":"Greenstar Landscaping Inc",
    "wof:placetype":"venue"
},
  "geometry": {"coordinates":[-75.8283920288,45.2644233704],"type":"Point"}
}