{
  "type": "Feature",
  "properties": {
    "iso:country":"CA",
    "sg:address":"50 Mc Pherson Ave",
    "sg:city":"Kapuskasing",
    "sg:classifiers":[
        {
            "category":"Home & Garden",
            "subcategory":"Carpets & Floor Coverings",
            "type":"Retail Goods"
        }
    ],
    "sg:phone":"+1 705 335 4735",
    "sg:postcode":"P5N 1V2",
    "sg:province":"ON",
    "sg:tags":[
        "dealer",
        "rug"
    ],
    "wof:name":"Tapisrido Centre",
    "wof:placetype":"venue"
},
  "geometry": {"coordinates":[-82.4249954224,49.4164199829],"type":"Point"}
}