{
  "type": "Feature",
  "properties": {
    "addr:full":"473 St. George St Moncton NB E1C 1Y2",
    "addr:housenumber":"473",
    "addr:postcode":"e1c 1y2",
    "addr:street":"St. George St",
    "iso:country":"CA",
    "sg:address":"473 St. George St",
    "sg:city":"Moncton",
    "sg:classifiers":[
        {
            "category":"Banks & Credit Unions",
            "subcategory":"Bank",
            "type":"Services"
        }
    ],
    "sg:phone":"+1 506 382 1663",
    "sg:postcode":"E1C 1Y2",
    "sg:province":"NB",
    "wof:name":"Moncton Civic Credit Union Ltd",
    "wof:placetype":"venue"
},
  "geometry": {"coordinates":[-64.793037,46.08918],"type":"Point"}
}