{
  "type": "Feature",
  "properties": {
    "addr:full":"900 Sunshine Coast Hwy # 33 Gibsons BC V0N 1V0",
    "addr:housenumber":"900",
    "addr:postcode":"v0n 1v0",
    "addr:street":"Sunshine Coast Hwy # 33",
    "iso:country":"CA",
    "sg:address":"900 Sunshine Coast Hwy # 33",
    "sg:city":"Gibsons",
    "sg:classifiers":[
        {
            "category":"Banks & Credit Unions",
            "subcategory":"Bank",
            "type":"Services"
        }
    ],
    "sg:phone":"+1 604 886 5400",
    "sg:postcode":"V0N 1V0",
    "sg:province":"BC",
    "wof:name":"Royal Bank Financial Group",
    "wof:placetype":"venue"
},
  "geometry": {"coordinates":[-123.51907300000001,49.406822],"type":"Point"}
}