{
  "type": "Feature",
  "properties": {
    "addr:full":"10 Rue Des Bouleaux Kingsey Falls QC J0A 1B0",
    "addr:housenumber":"10",
    "addr:postcode":"j0a 1b0",
    "addr:street":"Rue Des Bouleaux",
    "iso:country":"CA",
    "sg:address":"10 Rue Des Bouleaux",
    "sg:city":"Kingsey Falls",
    "sg:classifiers":[
        {
            "category":"Personal",
            "subcategory":"Beauty Salon",
            "type":"Services"
        }
    ],
    "sg:phone":"+1 819 363 2926",
    "sg:postcode":"J0A 1B0",
    "sg:province":"QC",
    "wof:name":"Salon Nathalie Enr",
    "wof:placetype":"venue"
},
  "geometry": {"coordinates":[-72.064735,45.854187],"type":"Point"}
}