{
  "type": "Feature",
  "properties": {
    "iso:country":"CA",
    "sg:address":"509 Commissioners Rd W",
    "sg:city":"London",
    "sg:classifiers":[
        {
            "category":"Food & Beverages",
            "subcategory":"Bakery",
            "type":"Retail Goods"
        }
    ],
    "sg:phone":"+1 519 657 4772",
    "sg:postcode":"N6J 1Y5",
    "sg:province":"ON",
    "sg:tags":[
        "baker"
    ],
    "wof:name":"Great Canadian Bagel",
    "wof:placetype":"venue"
},
  "geometry": {"coordinates":[-81.2893981934,42.954536438],"type":"Point"}
}