{
  "type": "Feature",
  "properties": {
    "addr:full":"10001 Rue Mirabeau Anjou QC H1J 1T7",
    "addr:housenumber":"10001",
    "addr:postcode":"h1j 1t7",
    "addr:street":"Rue Mirabeau",
    "iso:country":"CA",
    "sg:address":"10001 Rue Mirabeau",
    "sg:city":"Anjou",
    "sg:classifiers":[
        {
            "category":"Autos & Motor Vehicles",
            "subcategory":"Automobile Sales",
            "type":"Retail Goods"
        }
    ],
    "sg:phone":"+1 514 353 9105",
    "sg:postcode":"H1J 1T7",
    "sg:province":"QC",
    "sg:tags":[
        "car",
        "dealer"
    ],
    "wof:name":"Oscar Auto",
    "wof:placetype":"venue"
},
  "geometry": {"coordinates":[-73.578613,45.615124],"type":"Point"}
}