{
  "type": "Feature",
  "properties": {
    "addr:full":"1227 Rue Notre-Dame Repentigny QC J5Y 3H2",
    "addr:housenumber":"1227",
    "addr:postcode":"j5y 3h2",
    "addr:street":"Rue Notre-Dame",
    "iso:country":"CA",
    "sg:address":"1227 Rue Notre-Dame",
    "sg:city":"Repentigny",
    "sg:classifiers":[
        {
            "category":"Education",
            "subcategory":"College",
            "type":"Public Place"
        }
    ],
    "sg:phone":"+1 450 582 2020",
    "sg:postcode":"J5Y 3H2",
    "sg:province":"QC",
    "sg:tags":[
        "academic",
        "school"
    ],
    "wof:name":"Academie Francois-Labelle",
    "wof:placetype":"venue"
},
  "geometry": {"coordinates":[-73.40759300000001,45.778038],"type":"Point"}
}