{
  "type": "Feature",
  "properties": {
    "iso:country":"CA",
    "sg:address":"39031 97th St",
    "sg:city":"Oliver",
    "sg:classifiers":[
        {
            "category":"Travel",
            "subcategory":"Campground",
            "type":"Entertainment"
        }
    ],
    "sg:phone":"+1 250 498 3358",
    "sg:postcode":"V0H 1T0",
    "sg:province":"BC",
    "wof:name":"Gallagher Lake Koa Campground",
    "wof:placetype":"venue"
},
  "geometry": {"coordinates":[-119.552261352,49.1897506714],"type":"Point"}
}