{
  "type": "Feature",
  "properties": {
    "addr:full":"375 Thomas St Ingersoll ON N5C 3K1",
    "addr:housenumber":"375",
    "addr:postcode":"n5c 3k1",
    "addr:street":"Thomas St",
    "iso:country":"CA",
    "sg:address":"375 Thomas St",
    "sg:city":"Ingersoll",
    "sg:classifiers":[
        {
            "category":"Manufacturing",
            "subcategory":"Rubber & Plastics",
            "type":"Manufacturing & Wholesale Goods"
        }
    ],
    "sg:phone":"+1 519 425 0996",
    "sg:postcode":"N5C 3K1",
    "sg:province":"ON",
    "sg:tags":[
        "mold",
        "maker"
    ],
    "wof:name":"T & H Plastics Inc",
    "wof:placetype":"venue"
},
  "geometry": {"coordinates":[-80.89321099999999,43.027237],"type":"Point"}
}