{
  "type": "Feature",
  "properties": {
    "iso:country":"CA",
    "sg:address":"8407 Boul Viau",
    "sg:city":"Saint-Leonard",
    "sg:classifiers":[
        {
            "category":"Personal",
            "subcategory":"Beauty Salon",
            "type":"Services"
        }
    ],
    "sg:phone":"+1 514 322 5218",
    "sg:postcode":"H1R 2T6",
    "sg:province":"QC",
    "wof:name":"Salon LA Coiff Inc",
    "wof:placetype":"venue"
},
  "geometry": {"coordinates":[-73.6022109985,45.5805282593],"type":"Point"}
}