{
  "type": "Feature",
  "properties": {
    "addr:full":"17 Rue Garnier Fermont QC G0G 1J0",
    "addr:housenumber":"17",
    "addr:postcode":"g0g 1j0",
    "addr:street":"Rue Garnier",
    "iso:country":"CA",
    "sg:address":"17 Rue Garnier",
    "sg:city":"Fermont",
    "sg:classifiers":[
        {
            "category":"Travel",
            "subcategory":"Campground",
            "type":"Entertainment"
        }
    ],
    "sg:phone":"+1 418 287 5668",
    "sg:postcode":"G0G 1J0",
    "sg:province":"QC",
    "sg:tags":[
        "camp",
        "fishing"
    ],
    "wof:name":"Club Peche Du Lac LA Justone",
    "wof:placetype":"venue"
},
  "geometry": {"coordinates":[-67.100128,52.792542],"type":"Point"}
}