{
  "type": "Feature",
  "properties": {
    "iso:country":"CA",
    "sg:address":"PO Box 7477 STN Main",
    "sg:city":"Edson",
    "sg:classifiers":[
        {
            "category":"Mining & Drilling",
            "type":"Manufacturing & Wholesale Goods"
        }
    ],
    "sg:phone":"+1 780 622 3636",
    "sg:postcode":"T7E 1V6",
    "sg:province":"AB",
    "wof:name":"Enersul Operations",
    "wof:placetype":"venue"
},
  "geometry": {"coordinates":[-116.43409729,53.5821304321],"type":"Point"}
}