{
  "type": "Feature",
  "properties": {
    "addr:full":"Springhill NS B0M 1X0",
    "addr:postcode":"b0m 1x0",
    "iso:country":"CA",
    "sg:city":"Springhill",
    "sg:classifiers":[
        {
            "category":"Health Services",
            "subcategory":"Doctor",
            "type":"Services"
        }
    ],
    "sg:phone":"+1 902 597 3727",
    "sg:postcode":"B0M 1X0",
    "sg:province":"NS",
    "sg:tags":[
        "physician",
        "surgeon"
    ],
    "wof:name":"Gintowt, Barbara MD",
    "wof:placetype":"venue"
},
  "geometry": {"coordinates":[-64.0573501587,45.650554657],"type":"Point"}
}