{
  "type": "Feature",
  "properties": {
    "addr:full":"700 8 Ave SW Calgary AB T2P 1H2",
    "addr:housenumber":"700",
    "addr:postcode":"t2p 1h2",
    "addr:street":"8 Ave Sw",
    "iso:country":"CA",
    "sg:address":"700 8 Ave SW",
    "sg:city":"Calgary",
    "sg:classifiers":[
        {
            "category":"Personal",
            "subcategory":"Beauty Salon",
            "type":"Services"
        }
    ],
    "sg:phone":"+1 403 234 9495",
    "sg:postcode":"T2P 1H2",
    "sg:province":"AB",
    "wof:name":"Stephen's Off Stephen's Hair",
    "wof:placetype":"venue"
},
  "geometry": {"coordinates":[-114.076584,51.04607],"type":"Point"}
}