{
  "type": "Feature",
  "properties": {
    "iso:country":"CA",
    "sg:address":"415 Main St W",
    "sg:city":"Hamilton",
    "sg:classifiers":[
        {
            "category":"Restaurant",
            "type":"Food & Drink"
        }
    ],
    "sg:phone":"+1 905 521 8653",
    "sg:postcode":"L8P 1K5",
    "sg:province":"ON",
    "sg:tags":[
        "parlor",
        "ice",
        "cream"
    ],
    "wof:name":"Dairy Queen",
    "wof:placetype":"venue"
},
  "geometry": {"coordinates":[-79.886719,43.259155],"type":"Point"}
}