{
  "type": "Feature",
  "properties": {
    "addr:full":"3 Anne Pickle Lake ON P0V 3A0",
    "addr:housenumber":"3",
    "addr:postcode":"p0v 3a0",
    "addr:street":"Anne Pickle",
    "iso:country":"CA",
    "sg:address":"3 Anne",
    "sg:city":"Pickle Lake",
    "sg:classifiers":[
        {
            "category":"Social Services",
            "type":"Services"
        }
    ],
    "sg:phone":"+1 807 928 2234",
    "sg:postcode":"P0V 3A0",
    "sg:province":"ON",
    "sg:tags":[
        "organization",
        "welfare"
    ],
    "wof:name":"Northwestern Health Unit",
    "wof:placetype":"venue"
},
  "geometry": {"coordinates":[-90.1605377197,51.4813728333],"type":"Point"}
}