{
  "type": "Feature",
  "properties": {
    "addr:full":"Toronto ON M5L 1G2",
    "addr:postcode":"m5l 1g2",
    "iso:country":"CA",
    "sg:city":"Toronto",
    "sg:classifiers":[
        {
            "category":"Organizations",
            "subcategory":"Professional Association",
            "type":"Services"
        }
    ],
    "sg:phone":"+1 416 362 6092",
    "sg:postcode":"M5L 1G2",
    "sg:province":"ON",
    "wof:name":"Canadian Bankers Assn",
    "wof:placetype":"venue"
},
  "geometry": {"coordinates":[-79.533241,43.603634],"type":"Point"}
}