{
  "type": "Feature",
  "properties": {
    "iso:country":"CA",
    "sg:address":"130 Seal Point Rd",
    "sg:city":"Upper Port LA Tour",
    "sg:classifiers":[
        {
            "category":"Manufacturing",
            "subcategory":"Food",
            "type":"Manufacturing & Wholesale Goods"
        }
    ],
    "sg:phone":"+1 902 768 2478",
    "sg:postcode":"B0W 3N0",
    "sg:province":"NS",
    "sg:tags":[
        "product",
        "seafood",
        "fish",
        "prepared"
    ],
    "wof:name":"K & N Fisheries Ltd",
    "wof:placetype":"venue"
},
  "geometry": {"coordinates":[-65.4689025879,43.5086975098],"type":"Point"}
}