{
  "type": "Feature",
  "properties": {
    "iso:country":"CA",
    "sg:address":"PO Box 27",
    "sg:city":"Fort Mcpherson",
    "sg:classifiers":[
        {
            "category":"Travel",
            "subcategory":"Hotels & Motels",
            "type":"Entertainment"
        }
    ],
    "sg:phone":"+1 867 952 2094",
    "sg:postcode":"X0E 0J0",
    "sg:province":"NT",
    "sg:tags":[
        "resort"
    ],
    "wof:name":"Peel River Inn",
    "wof:placetype":"venue"
},
  "geometry": {"coordinates":[-134.76582300000001,67.45753499999999],"type":"Point"}
}