{
  "type": "Feature",
  "properties": {
    "iso:country":"CA",
    "sg:city":"Scarborough",
    "sg:classifiers":[
        {
            "category":"Real Estate",
            "subcategory":"Real Estate Agent",
            "type":"Services"
        }
    ],
    "sg:phone":"+1 416 609 2642",
    "sg:postcode":"M1B 4Z9",
    "sg:province":"ON",
    "sg:tags":[
        "management"
    ],
    "wof:name":"Miracle Medical Ctr",
    "wof:placetype":"venue"
},
  "geometry": {"coordinates":[-79.2398071289,43.7959709167],"type":"Point"}
}