{
  "type": "Feature",
  "properties": {
    "addr:full":"555 Fisgard St Victoria BC V8W 1R5",
    "addr:housenumber":"555",
    "addr:postcode":"v8w 1r5",
    "addr:street":"Fisgard St",
    "iso:country":"CA",
    "sg:address":"555 Fisgard St",
    "sg:city":"Victoria",
    "sg:classifiers":[
        {
            "category":"Food & Beverages",
            "subcategory":"Specialty",
            "type":"Retail Goods"
        }
    ],
    "sg:phone":"+1 250 386 8888",
    "sg:postcode":"V8W 1R5",
    "sg:province":"BC",
    "sg:tags":[
        "oriental"
    ],
    "wof:name":"Jan K Market",
    "wof:placetype":"venue"
},
  "geometry": {"coordinates":[-123.36771400000001,48.429199],"type":"Point"}
}