{
  "type": "Feature",
  "properties": {
    "addr:full":"Warren ON P0H 2N0",
    "addr:postcode":"p0h 2n0",
    "iso:country":"CA",
    "sg:city":"Warren",
    "sg:classifiers":[
        {
            "category":"Manufacturing",
            "subcategory":"Lumber",
            "type":"Manufacturing & Wholesale Goods"
        }
    ],
    "sg:phone":"+1 705 967 0531",
    "sg:postcode":"P0H 2N0",
    "sg:province":"ON",
    "sg:tags":[
        "company",
        "logging"
    ],
    "wof:name":"Jean Brunet Logging Ltd",
    "wof:placetype":"venue"
},
  "geometry": {"coordinates":[-80.310745,46.442421],"type":"Point"}
}