{
  "type": "Feature",
  "properties": {
    "addr:full":"9734 201 St Langley BC V1M 3E8",
    "addr:housenumber":"9734",
    "addr:postcode":"v1m 3e8",
    "addr:street":"201 St",
    "iso:country":"CA",
    "sg:address":"9734 201 St",
    "sg:city":"Langley",
    "sg:classifiers":[
        {
            "category":"Building & Trades",
            "subcategory":"Construction",
            "type":"Services"
        }
    ],
    "sg:phone":"+1 604 882 9734",
    "sg:postcode":"V1M 3E8",
    "sg:province":"BC",
    "sg:tags":[
        "roofing",
        "contractor"
    ],
    "wof:name":"Roofing Contractors Assn-BC",
    "wof:placetype":"venue"
},
  "geometry": {"coordinates":[-122.66410827599999,49.1801338196],"type":"Point"}
}