{
  "type": "Feature",
  "properties": {
    "addr:full":"126 Superior Ave Wawa ON P0S 1K0",
    "addr:housenumber":"126",
    "addr:postcode":"p0s 1k0",
    "addr:street":"Superior Ave",
    "iso:country":"CA",
    "sg:address":"126 Superior Ave",
    "sg:city":"Wawa",
    "sg:classifiers":[
        {
            "category":"Building & Trades",
            "subcategory":"Construction",
            "type":"Services"
        }
    ],
    "sg:phone":"+1 705 856 7550",
    "sg:postcode":"P0S 1K0",
    "sg:province":"ON",
    "sg:tags":[
        "home",
        "spa",
        "hot",
        "tub",
        "improvement"
    ],
    "wof:name":"Paul's Masonry",
    "wof:placetype":"venue"
},
  "geometry": {"coordinates":[-84.78306600000001,47.993874],"type":"Point"}
}