{
  "type": "Feature",
  "properties": {
    "addr:full":"201 Georgian Dr Barrie ON L4M 6M2",
    "addr:housenumber":"201",
    "addr:postcode":"l4m 6m2",
    "addr:street":"Georgian Dr",
    "iso:country":"CA",
    "sg:address":"201 Georgian Dr",
    "sg:city":"Barrie",
    "sg:classifiers":[
        {
            "category":"Shopping",
            "type":"Retail Goods"
        }
    ],
    "sg:phone":"+1 705 739 5625",
    "sg:postcode":"L4M 6M2",
    "sg:province":"ON",
    "sg:tags":[
        "hearing",
        "equipment",
        "supply",
        "impaired"
    ],
    "wof:name":"Hearing Aid Dispensing",
    "wof:placetype":"venue"
},
  "geometry": {"coordinates":[-79.66512299999999,44.415379],"type":"Point"}
}