{
  "type": "Feature",
  "properties": {
    "addr:full":"250 Lakewood Blvd Winnipeg MB R2J 3A2",
    "addr:housenumber":"250",
    "addr:postcode":"r2j 3a2",
    "addr:street":"Lakewood Blvd",
    "iso:country":"CA",
    "sg:address":"250 Lakewood Blvd",
    "sg:city":"Winnipeg",
    "sg:classifiers":[
        {
            "category":"Education",
            "subcategory":"School",
            "type":"Public Place"
        }
    ],
    "sg:phone":"+1 204 257 2928",
    "sg:postcode":"R2J 3A2",
    "sg:province":"MB",
    "wof:name":"J H Bruns Collegiate",
    "wof:placetype":"venue"
},
  "geometry": {"coordinates":[-97.0771865845,49.8477401733],"type":"Point"}
}