{
  "type": "Feature",
  "properties": {
    "addr:full":"3115 48 Ave # 300 Vernon BC V1T 3R5",
    "addr:housenumber":"3115",
    "addr:postcode":"v1t 3r5",
    "addr:street":"48 Ave # 300",
    "iso:country":"CA",
    "sg:address":"3115 48 Ave # 300",
    "sg:city":"Vernon",
    "sg:classifiers":[
        {
            "category":"Banks & Credit Unions",
            "subcategory":"Investment Brokerage",
            "type":"Services"
        }
    ],
    "sg:phone":"+1 250 545 9766",
    "sg:postcode":"V1T 3R5",
    "sg:province":"BC",
    "wof:name":"Edward Jones",
    "wof:placetype":"venue"
},
  "geometry": {"coordinates":[-119.272255,50.282139],"type":"Point"}
}