{
  "type": "Feature",
  "properties": {
    "addr:full":"174 Rue Richelieu Quebec QC G1R 1J5",
    "addr:housenumber":"174",
    "addr:postcode":"g1r 1j5",
    "addr:street":"Rue Richelieu",
    "iso:country":"CA",
    "sg:address":"174 Rue Richelieu",
    "sg:city":"Quebec",
    "sg:classifiers":[
        {
            "category":"Shopping",
            "subcategory":"Bicycles & Sporting Goods",
            "type":"Retail Goods"
        }
    ],
    "sg:phone":"+1 418 648 6022",
    "sg:postcode":"G1R 1J5",
    "sg:province":"QC",
    "wof:name":"Bicycles Falardeau Enr",
    "wof:placetype":"venue"
},
  "geometry": {"coordinates":[-71.226151,46.808411],"type":"Point"}
}