{
  "type": "Feature",
  "properties": {
    "iso:country":"CA",
    "sg:city":"Langley",
    "sg:classifiers":[
        {
            "category":"Shopping",
            "subcategory":"Optical Goods",
            "type":"Retail Goods"
        }
    ],
    "sg:phone":"+1 604 514 3919",
    "sg:postcode":"V3A 3N5",
    "sg:province":"BC",
    "sg:tags":[
        "optician"
    ],
    "wof:name":"Visual Eyes Opticians Ltd",
    "wof:placetype":"venue"
},
  "geometry": {"coordinates":[-122.60858917199999,49.0891838074],"type":"Point"}
}