{
  "type": "Feature",
  "properties": {
    "iso:country":"CA",
    "sg:address":"61 Rue King O",
    "sg:city":"Sherbrooke",
    "sg:classifiers":[
        {
            "category":"Restaurant",
            "type":"Food & Drink"
        }
    ],
    "sg:phone":"+1 819 562 1029",
    "sg:postcode":"J1H 1P1",
    "sg:province":"QC",
    "wof:name":"Restaurant Pizzicato",
    "wof:placetype":"venue"
},
  "geometry": {"coordinates":[-71.885658,45.403893],"type":"Point"}
}