{
  "type": "Feature",
  "properties": {
    "addr:full":"189 Bruce St Sault Ste Marie ON P6A 2Y1",
    "addr:housenumber":"189",
    "addr:postcode":"p6a 2y1",
    "addr:street":"Bruce St",
    "iso:country":"CA",
    "sg:address":"189 Bruce St",
    "sg:city":"Sault Ste Marie",
    "sg:classifiers":[
        {
            "category":"Insurance",
            "subcategory":"Insurance Agent",
            "type":"Services"
        }
    ],
    "sg:phone":"+1 705 253 4302",
    "sg:postcode":"P6A 2Y1",
    "sg:province":"ON",
    "wof:name":"Marchand, Ralph",
    "wof:placetype":"venue"
},
  "geometry": {"coordinates":[-84.333527,46.515301],"type":"Point"}
}