{
  "type": "Feature",
  "properties": {
    "addr:full":"178 Reach Industrial Park Rd Port Perry ON L9L 1B2",
    "addr:housenumber":"178",
    "addr:postcode":"l9l 1b2",
    "addr:street":"Reach Industrial Park Rd",
    "iso:country":"CA",
    "sg:address":"178 Reach Industrial Park Rd",
    "sg:city":"Port Perry",
    "sg:classifiers":[
        {
            "category":"Building & Trades",
            "subcategory":"Construction",
            "type":"Services"
        }
    ],
    "sg:phone":"+1 905 985 5205",
    "sg:postcode":"L9L 1B2",
    "sg:province":"ON",
    "sg:tags":[
        "maker",
        "cabinet"
    ],
    "wof:name":"J Thaeter Custom Cabinetry",
    "wof:placetype":"venue"
},
  "geometry": {"coordinates":[-78.98468,44.103874],"type":"Point"}
}