{
  "type": "Feature",
  "properties": {
    "addr:full":"3181 Walker Rd # 1 Windsor ON N8W 3R6",
    "addr:housenumber":"3181",
    "addr:postcode":"n8w 3r6",
    "addr:street":"Walker Rd # 1",
    "iso:country":"CA",
    "sg:address":"3181 Walker Rd # 1",
    "sg:city":"Windsor",
    "sg:classifiers":[
        {
            "category":"Manufacturing",
            "subcategory":"Tools & Machinery",
            "type":"Manufacturing & Wholesale Goods"
        }
    ],
    "sg:phone":"+1 519 966 1000",
    "sg:postcode":"N8W 3R6",
    "sg:province":"ON",
    "sg:tags":[
        "alternator",
        "automobile",
        "parts",
        "supply"
    ],
    "wof:name":"Walker Road Automotive Ltd",
    "wof:placetype":"venue"
},
  "geometry": {"coordinates":[-82.980934,42.281132],"type":"Point"}
}