{
  "type": "Feature",
  "properties": {
    "addr:full":"3560 Rue Principale Tracadie-Sheila NB E1X 1C9",
    "addr:housenumber":"3560",
    "addr:postcode":"e1x 1c9",
    "addr:street":"Rue Principale",
    "iso:country":"CA",
    "sg:address":"3560 Rue Principale",
    "sg:city":"Tracadie-Sheila",
    "sg:classifiers":[
        {
            "category":"Health Services",
            "subcategory":"Doctor",
            "type":"Services"
        }
    ],
    "sg:phone":"+1 506 395 3307",
    "sg:postcode":"E1X 1C9",
    "sg:province":"NB",
    "sg:tags":[
        "physician",
        "surgeon"
    ],
    "wof:name":"Louis, Carlyle MD",
    "wof:placetype":"venue"
},
  "geometry": {"coordinates":[-64.9176864624,47.4913406372],"type":"Point"}
}