{
  "type": "Feature",
  "properties": {
    "addr:full":"560 Rue Principale Lachute QC J8H 1Y7",
    "addr:housenumber":"560",
    "addr:postcode":"j8h 1y7",
    "addr:street":"Rue Principale",
    "iso:country":"CA",
    "sg:address":"560 Rue Principale",
    "sg:city":"Lachute",
    "sg:classifiers":[
        {
            "category":"Health Services",
            "subcategory":"Optometrist",
            "type":"Services"
        }
    ],
    "sg:phone":"+1 450 562 8897",
    "sg:postcode":"J8H 1Y7",
    "sg:province":"QC",
    "wof:name":"Vision Expert",
    "wof:placetype":"venue"
},
  "geometry": {"coordinates":[-74.333206,45.656975],"type":"Point"}
}