{
  "type": "Feature",
  "properties": {
    "addr:full":"6024 Quinpool Rd Halifax NS B3L 1A1",
    "addr:housenumber":"6024",
    "addr:postcode":"b3l 1a1",
    "addr:street":"Quinpool Rd",
    "iso:country":"CA",
    "sg:address":"6024 Quinpool Rd",
    "sg:city":"Halifax",
    "sg:classifiers":[
        {
            "category":"Cinema",
            "subcategory":"Movie Rental",
            "type":"Entertainment"
        }
    ],
    "sg:phone":"+1 902 422 7365",
    "sg:postcode":"B3L 1A1",
    "sg:province":"NS",
    "sg:tags":[
        "leasing",
        "video",
        "disc",
        "tape"
    ],
    "wof:name":"Blockbuster Video",
    "wof:placetype":"venue"
},
  "geometry": {"coordinates":[-63.591091,44.646896],"type":"Point"}
}