{
  "type": "Feature",
  "properties": {
    "addr:full":"Lethbridge AB T1J 4M7",
    "addr:postcode":"t1j 4m7",
    "iso:country":"CA",
    "sg:city":"Lethbridge",
    "sg:classifiers":[
        {
            "category":"Restaurant",
            "type":"Food & Drink"
        }
    ],
    "sg:phone":"+1 403 327 4548",
    "sg:postcode":"T1J 4M7",
    "sg:province":"AB",
    "wof:name":"Boston Pizza",
    "wof:placetype":"venue"
},
  "geometry": {"coordinates":[-112.833229,49.698223],"type":"Point"}
}