{
  "type": "Feature",
  "properties": {
    "addr:full":"7014 Rue Saint-Hubert Montreal QC H2S 2M9",
    "addr:housenumber":"7014",
    "addr:postcode":"h2s 2m9",
    "addr:street":"Rue Saint-Hubert",
    "iso:country":"CA",
    "sg:address":"7014 Rue Saint-Hubert",
    "sg:city":"Montreal",
    "sg:classifiers":[
        {
            "category":"Shopping",
            "subcategory":"Clothing, Apparel, & Fashions",
            "type":"Retail Goods"
        }
    ],
    "sg:phone":"+1 514 272 8284",
    "sg:postcode":"H2S 2M9",
    "sg:province":"QC",
    "wof:name":"Boutique Sonu",
    "wof:placetype":"venue"
},
  "geometry": {"coordinates":[-73.611221,45.539673],"type":"Point"}
}