{
  "type": "Feature",
  "properties": {
    "iso:country":"CA",
    "sg:address":"444 14th Ave W",
    "sg:city":"Vancouver",
    "sg:classifiers":[
        {
            "category":"Travel",
            "subcategory":"Hotels & Motels",
            "type":"Entertainment"
        }
    ],
    "sg:phone":"+1 604 876 8177",
    "sg:postcode":"V5Y 1X6",
    "sg:province":"BC",
    "sg:tags":[
        "breakfast",
        "accommodation",
        "bed"
    ],
    "wof:name":"Bed & Breakfast By Stan's",
    "wof:placetype":"venue"
},
  "geometry": {"coordinates":[-123.11391399999999,49.258629],"type":"Point"}
}