{
  "type": "Feature",
  "properties": {
    "addr:full":"631 Montreal Rd Ottawa ON K1K 0T4",
    "addr:housenumber":"631",
    "addr:postcode":"k1k 0t4",
    "addr:street":"Montreal Rd",
    "iso:country":"CA",
    "sg:address":"631 Montreal Rd",
    "sg:city":"Ottawa",
    "sg:classifiers":[
        {
            "category":"Shopping",
            "type":"Retail Goods"
        }
    ],
    "sg:phone":"+1 613 745 3173",
    "sg:postcode":"K1K 0T4",
    "sg:province":"ON",
    "sg:tags":[
        "orthopedic",
        "appliance"
    ],
    "wof:name":"Ampos Orthopaedics",
    "wof:placetype":"venue"
},
  "geometry": {"coordinates":[-75.641891,45.442783],"type":"Point"}
}