{
  "type": "Feature",
  "properties": {
    "iso:country":"CA",
    "sg:city":"Warwick",
    "sg:classifiers":[
        {
            "category":"Health Services",
            "subcategory":"Doctor",
            "type":"Services"
        }
    ],
    "sg:phone":"+1 819 358 4600",
    "sg:postcode":"J0A 1M0",
    "sg:province":"QC",
    "sg:tags":[
        "clinic"
    ],
    "wof:name":"Clinique Medicale DE Warwick",
    "wof:placetype":"venue"
},
  "geometry": {"coordinates":[-71.9884567261,45.9447250366],"type":"Point"}
}