{
  "type": "Feature",
  "properties": {
    "addr:full":"1570 119E Rue Shawinigan-Sud QC G9P 3J3",
    "addr:housenumber":"1570",
    "addr:postcode":"g9p 3j3",
    "addr:street":"119E Rue Shawinigan-Sud",
    "iso:country":"CA",
    "sg:address":"1570 119E Rue",
    "sg:city":"Shawinigan-Sud",
    "sg:classifiers":[
        {
            "category":"Professional",
            "subcategory":"Business Services",
            "type":"Services"
        }
    ],
    "sg:phone":"+1 819 537 1996",
    "sg:postcode":"G9P 3J3",
    "sg:province":"QC",
    "sg:tags":[
        "engraver"
    ],
    "wof:name":"Gravure Provinciale Inc",
    "wof:placetype":"venue"
},
  "geometry": {"coordinates":[-72.7542419434,46.5164909363],"type":"Point"}
}