{
  "type": "Feature",
  "properties": {
    "addr:full":"Vancouver BC V6K 2E1",
    "addr:postcode":"v6k 2e1",
    "iso:country":"CA",
    "sg:city":"Vancouver",
    "sg:classifiers":[
        {
            "category":"Health Services",
            "subcategory":"Doctor",
            "type":"Services"
        }
    ],
    "sg:phone":"+1 604 736 6441",
    "sg:postcode":"V6K 2E1",
    "sg:province":"BC",
    "sg:tags":[
        "physician",
        "surgeon"
    ],
    "wof:name":"Qrsecg & Exercise Testing",
    "wof:placetype":"venue"
},
  "geometry": {"coordinates":[-123.154732,49.263744],"type":"Point"}
}