{
  "type": "Feature",
  "properties": {
    "addr:full":"215 Isabel St Winnipeg MB R3A 1R5",
    "addr:housenumber":"215",
    "addr:postcode":"r3a 1r5",
    "addr:street":"Isabel St",
    "iso:country":"CA",
    "sg:address":"215 Isabel St",
    "sg:city":"Winnipeg",
    "sg:classifiers":[
        {
            "category":"Social Services",
            "subcategory":"Child Care",
            "type":"Services"
        }
    ],
    "sg:phone":"+1 204 943 1969",
    "sg:postcode":"R3A 1R5",
    "sg:province":"MB",
    "wof:name":"Freighthouse Day Nursery Inc",
    "wof:placetype":"venue"
},
  "geometry": {"coordinates":[-97.147819519,49.9041442871],"type":"Point"}
}