{
  "type": "Feature",
  "properties": {
    "addr:full":"11103 76 Ave NW Edmonton AB T6G 0J9",
    "addr:housenumber":"11103",
    "addr:postcode":"t6g 0j9",
    "addr:street":"76 Ave Nw",
    "iso:country":"CA",
    "sg:address":"11103 76 Ave NW",
    "sg:city":"Edmonton",
    "sg:classifiers":[
        {
            "category":"Organizations",
            "subcategory":"Religious Organization",
            "type":"Services"
        }
    ],
    "sg:phone":"+1 780 436 0611",
    "sg:postcode":"T6G 0J9",
    "sg:province":"AB",
    "sg:tags":[
        "church"
    ],
    "wof:name":"Mc Kernan Baptist Church",
    "wof:placetype":"venue"
},
  "geometry": {"coordinates":[-113.516907,53.512142],"type":"Point"}
}