{
  "type": "Feature",
  "properties": {
    "iso:country":"CA",
    "sg:city":"Winnipeg",
    "sg:classifiers":[
        {
            "category":"Banks & Credit Unions",
            "subcategory":"Investment Brokerage",
            "type":"Services"
        }
    ],
    "sg:phone":"+1 204 925 2401",
    "sg:postcode":"R3B 3P2",
    "sg:province":"MB",
    "wof:name":"Crocus Investment Fund",
    "wof:placetype":"venue"
},
  "geometry": {"coordinates":[-97.139359,49.897987],"type":"Point"}
}