{
  "type": "Feature",
  "properties": {
    "addr:full":"1840 Carrigan Dr Orleans ON K4A 2V2",
    "addr:housenumber":"1840",
    "addr:postcode":"k4a 2v2",
    "addr:street":"Carrigan Dr",
    "iso:country":"CA",
    "sg:address":"1840 Carrigan Dr",
    "sg:city":"Orleans",
    "sg:classifiers":[
        {
            "category":"Freight",
            "type":"Transportation"
        }
    ],
    "sg:phone":"+1 613 837 6025",
    "sg:postcode":"K4A 2V2",
    "sg:province":"ON",
    "sg:tags":[
        "trucking"
    ],
    "wof:name":"Certified Logistics Systems",
    "wof:placetype":"venue"
},
  "geometry": {"coordinates":[-75.47923278810001,45.4732704163],"type":"Point"}
}