{
  "type": "Feature",
  "properties": {
    "addr:full":"416 Main St Gravelbourg SK S0H 1X0",
    "addr:housenumber":"416",
    "addr:postcode":"s0h 1x0",
    "addr:street":"Main St",
    "iso:country":"CA",
    "sg:address":"416 Main St",
    "sg:city":"Gravelbourg",
    "sg:classifiers":[
        {
            "category":"Real Estate",
            "subcategory":"Real Estate Operator",
            "type":"Services"
        }
    ],
    "sg:phone":"+1 306 648 2263",
    "sg:postcode":"S0H 1X0",
    "sg:province":"SK",
    "sg:tags":[
        "mall",
        "shopping",
        "center"
    ],
    "wof:name":"Minnie's Mall",
    "wof:placetype":"venue"
},
  "geometry": {"coordinates":[-106.557113648,49.875869751],"type":"Point"}
}