{
  "type": "Feature",
  "properties": {
    "addr:full":"Hwy 16 W Lanigan SK S0K 2M0",
    "addr:postcode":"s0k 2m0",
    "addr:street":"Hwy 16 W Lanigan",
    "iso:country":"CA",
    "sg:address":"Hwy 16 W",
    "sg:city":"Lanigan",
    "sg:classifiers":[
        {
            "category":"Retail",
            "subcategory":"Auto Repair",
            "type":"Services"
        }
    ],
    "sg:phone":"+1 306 365 4209",
    "sg:postcode":"S0K 2M0",
    "sg:province":"SK",
    "sg:tags":[
        "body",
        "automobile",
        "painting"
    ],
    "wof:name":"Lanigan Auto Wrecking Ltd",
    "wof:placetype":"venue"
},
  "geometry": {"coordinates":[-105.01026899999999,51.840866],"type":"Point"}
}