{
  "type": "Feature",
  "properties": {
    "addr:full":"Calgary AB T3E 0C3",
    "addr:postcode":"t3e 0c3",
    "iso:country":"CA",
    "sg:city":"Calgary",
    "sg:classifiers":[
        {
            "category":"Autos & Motor Vehicles",
            "subcategory":"Auto Supplies",
            "type":"Retail Goods"
        }
    ],
    "sg:phone":"+1 403 249 2469",
    "sg:postcode":"T3E 0C3",
    "sg:province":"AB",
    "sg:tags":[
        "automobile",
        "parts"
    ],
    "wof:name":"Auto Value Parts Stores",
    "wof:placetype":"venue"
},
  "geometry": {"coordinates":[-114.141563416,51.0376396179],"type":"Point"}
}