{
  "type": "Feature",
  "properties": {
    "addr:full":"340 Coach Ridge Rise SW Calgary AB T3H 1G1",
    "addr:housenumber":"340",
    "addr:postcode":"t3h 1g1",
    "addr:street":"Coach Ridge Rise Sw",
    "iso:country":"CA",
    "sg:address":"340 Coach Ridge Rise SW",
    "sg:city":"Calgary",
    "sg:classifiers":[
        {
            "category":"Mining & Drilling",
            "type":"Manufacturing & Wholesale Goods"
        }
    ],
    "sg:phone":"+1 403 221 8000",
    "sg:postcode":"T3H 1G1",
    "sg:province":"AB",
    "sg:tags":[
        "field",
        "oil"
    ],
    "wof:name":"Waterflood Service & Sales Ltd",
    "wof:placetype":"venue"
},
  "geometry": {"coordinates":[-114.18523399999999,51.055058],"type":"Point"}
}