{
  "type": "Feature",
  "properties": {
    "addr:full":"5990 14th Ave Markham ON L3S 4M4",
    "addr:housenumber":"5990",
    "addr:postcode":"l3s 4m4",
    "addr:street":"14Th Ave",
    "iso:country":"CA",
    "sg:address":"5990 14th Ave",
    "sg:city":"Markham",
    "sg:classifiers":[
        {
            "category":"Home & Garden",
            "subcategory":"Building Materials",
            "type":"Retail Goods"
        }
    ],
    "sg:phone":"+1 905 201 7885",
    "sg:postcode":"L3S 4M4",
    "sg:province":"ON",
    "sg:tags":[
        "windows"
    ],
    "wof:name":"Ostaco 2000 Windoor Ltd",
    "wof:placetype":"venue"
},
  "geometry": {"coordinates":[-79.2565536499,43.8559265137],"type":"Point"}
}