{
  "type": "Feature",
  "properties": {
    "addr:full":"1105 Albion Rd Etobicoke ON M9V 1A9",
    "addr:housenumber":"1105",
    "addr:postcode":"m9v 1a9",
    "addr:street":"Albion Rd",
    "iso:country":"CA",
    "sg:address":"1105 Albion Rd",
    "sg:city":"Etobicoke",
    "sg:classifiers":[
        {
            "category":"Shopping",
            "subcategory":"Jewelry",
            "type":"Retail Goods"
        }
    ],
    "sg:phone":"+1 416 746 8088",
    "sg:postcode":"M9V 1A9",
    "sg:province":"ON",
    "sg:tags":[
        "jeweler"
    ],
    "wof:name":"Patel's Fine Jewellery",
    "wof:placetype":"venue"
},
  "geometry": {"coordinates":[-79.56560500000001,43.73716],"type":"Point"}
}