{
  "type": "Feature",
  "properties": {
    "addr:full":"231 Main St N Bothwell ON N0P 1C0",
    "addr:housenumber":"231",
    "addr:postcode":"n0p 1c0",
    "addr:street":"Main St N",
    "iso:country":"CA",
    "sg:address":"231 Main St N",
    "sg:city":"Bothwell",
    "sg:classifiers":[
        {
            "category":"Shopping",
            "subcategory":"Pharmacy",
            "type":"Retail Goods"
        }
    ],
    "sg:phone":"+1 519 695 2723",
    "sg:postcode":"N0P 1C0",
    "sg:province":"ON",
    "wof:name":"Bothwell Pharmacy Ida",
    "wof:placetype":"venue"
},
  "geometry": {"coordinates":[-81.87027,42.63031],"type":"Point"}
}