{
  "type": "Feature",
  "properties": {
    "addr:full":"55 Ranchero Green NW Calgary AB T3G 1C5",
    "addr:housenumber":"55",
    "addr:postcode":"t3g 1c5",
    "addr:street":"Ranchero Green Nw",
    "iso:country":"CA",
    "sg:address":"55 Ranchero Green NW",
    "sg:city":"Calgary",
    "sg:classifiers":[
        {
            "category":"Manufacturing",
            "subcategory":"Pottery",
            "type":"Manufacturing & Wholesale Goods"
        }
    ],
    "sg:phone":"+1 403 241 0989",
    "sg:postcode":"T3G 1C5",
    "sg:province":"AB",
    "wof:name":"Studio 55",
    "wof:placetype":"venue"
},
  "geometry": {"coordinates":[-114.189430237,51.1191864014],"type":"Point"}
}