{
  "type": "Feature",
  "properties": {
    "addr:full":"11927 203 St Maple Ridge BC V2X 4V2",
    "addr:housenumber":"11927",
    "addr:postcode":"v2x 4v2",
    "addr:street":"203 St",
    "iso:country":"CA",
    "sg:address":"11927 203 St",
    "sg:city":"Maple Ridge",
    "sg:classifiers":[
        {
            "category":"Retail",
            "subcategory":"Auto Repair",
            "type":"Services"
        }
    ],
    "sg:phone":"+1 604 465 1750",
    "sg:postcode":"V2X 4V2",
    "sg:province":"BC",
    "sg:tags":[
        "body",
        "automobile",
        "painting"
    ],
    "wof:name":"Craftsman Collision",
    "wof:placetype":"venue"
},
  "geometry": {"coordinates":[-122.657524,49.219944],"type":"Point"}
}