{
  "type": "Feature",
  "properties": {
    "addr:full":"Lloydminster AB T9V 1V7",
    "addr:postcode":"t9v 1v7",
    "iso:country":"CA",
    "sg:city":"Lloydminster",
    "sg:classifiers":[
        {
            "category":"Freight",
            "type":"Transportation"
        }
    ],
    "sg:phone":"+1 780 875 3207",
    "sg:postcode":"T9V 1V7",
    "sg:province":"AB",
    "sg:tags":[
        "trucking"
    ],
    "wof:name":"Roberge Transport Inc",
    "wof:placetype":"venue"
},
  "geometry": {"coordinates":[-110.030334,53.278179],"type":"Point"}
}