{
  "type": "Feature",
  "properties": {
    "addr:full":"3381 Gershaw Dr SW Medicine Hat AB T1B 3N2",
    "addr:housenumber":"3381",
    "addr:postcode":"t1b 3n2",
    "addr:street":"Gershaw Dr Sw",
    "iso:country":"CA",
    "sg:address":"3381 Gershaw Dr SW",
    "sg:city":"Medicine Hat",
    "sg:classifiers":[
        {
            "category":"Wholesale",
            "subcategory":"Farm Supplies",
            "type":"Manufacturing & Wholesale Goods"
        }
    ],
    "sg:phone":"+1 403 526 7561",
    "sg:postcode":"T1B 3N2",
    "sg:province":"AB",
    "sg:tags":[
        "livestock"
    ],
    "wof:name":"Lang Livestock Alta Ltd",
    "wof:placetype":"venue"
},
  "geometry": {"coordinates":[-110.732201,50.00716],"type":"Point"}
}