{
  "type": "Feature",
  "properties": {
    "addr:full":"47 Ch DE LA Rabastaliere E Saint-Bruno QC J3V 2A4",
    "addr:housenumber":"47",
    "addr:postcode":"j3v 2a4",
    "addr:street":"Ch De La Rabastaliere E Saint-Bruno",
    "iso:country":"CA",
    "sg:address":"47 Ch DE LA Rabastaliere E",
    "sg:city":"Saint-Bruno",
    "sg:classifiers":[
        {
            "category":"Professional",
            "subcategory":"Business Services",
            "type":"Services"
        }
    ],
    "sg:phone":"+1 450 653 1333",
    "sg:postcode":"J3V 2A4",
    "sg:province":"QC",
    "sg:tags":[
        "interior",
        "consultant",
        "design",
        "decorator"
    ],
    "wof:name":"Egglefield Grant Marchand",
    "wof:placetype":"venue"
},
  "geometry": {"coordinates":[-71.67552185060001,48.4717712402],"type":"Point"}
}