{
  "type": "Feature",
  "properties": {
    "addr:full":"Toronto ON M5V 3K8",
    "addr:postcode":"m5v 3k8",
    "iso:country":"CA",
    "sg:city":"Toronto",
    "sg:classifiers":[
        {
            "category":"Professional",
            "subcategory":"Art Services",
            "type":"Services"
        }
    ],
    "sg:phone":"+1 416 595 9823",
    "sg:postcode":"M5V 3K8",
    "sg:province":"ON",
    "sg:tags":[
        "graphic",
        "designer"
    ],
    "wof:name":"Genesys Creative",
    "wof:placetype":"venue"
},
  "geometry": {"coordinates":[-79.39473,43.637455],"type":"Point"}
}