{
  "type": "Feature",
  "properties": {
    "addr:full":"658 Jadel Dr Victoria BC V9C 2L4",
    "addr:housenumber":"658",
    "addr:postcode":"bc v9c 2l4",
    "addr:street":"Jadel Dr",
    "iso:country":"CA",
    "sg:address":"658 Jadel Dr",
    "sg:city":"Victoria",
    "sg:classifiers":[
        {
            "category":"Retail",
            "subcategory":"Animal Services",
            "type":"Services"
        }
    ],
    "sg:phone":"+1 250 474 0551",
    "sg:postcode":"V9C 2L4",
    "sg:province":"BC",
    "sg:tags":[
        "pet"
    ],
    "wof:name":"Walking Dog Daycare",
    "wof:placetype":"venue"
},
  "geometry": {"coordinates":[-123.36451700000001,48.428314],"type":"Point"}
}