{
  "type": "Feature",
  "properties": {
    "iso:country":"CA",
    "sg:city":"Abbotsford",
    "sg:classifiers":[
        {
            "category":"Personal",
            "type":"Services"
        }
    ],
    "sg:phone":"+1 604 855 6645",
    "sg:postcode":"V2S 6A4",
    "sg:province":"BC",
    "sg:tags":[
        "therapist",
        "massage"
    ],
    "wof:name":"Bodykneads Massage Therapy",
    "wof:placetype":"venue"
},
  "geometry": {"coordinates":[-122.310089111,49.0525856018],"type":"Point"}
}