{
  "type": "Feature",
  "properties": {
    "addr:full":"Calgary AB T3H 2Y3",
    "addr:postcode":"t3h 2y3",
    "iso:country":"CA",
    "sg:city":"Calgary",
    "sg:classifiers":[
        {
            "category":"Restaurant",
            "type":"Food & Drink"
        }
    ],
    "sg:phone":"+1 403 246 5353",
    "sg:postcode":"T3H 2Y3",
    "sg:province":"AB",
    "wof:name":"Sorrentino's Bistro-Bar",
    "wof:placetype":"venue"
},
  "geometry": {"coordinates":[-114.16712951700001,51.0356826782],"type":"Point"}
}