{
  "type": "Feature",
  "properties": {
    "addr:full":"141 Av Laval Laval QC H7N 3V6",
    "addr:postcode":"h7n 3v6",
    "addr:street":"141 Av Laval",
    "iso:country":"CA",
    "sg:address":"141 Av Laval",
    "sg:city":"Laval",
    "sg:classifiers":[
        {
            "category":"Food & Beverages",
            "subcategory":"Groceries & Convenience Stores",
            "type":"Retail Goods"
        }
    ],
    "sg:phone":"+1 450 668 9089",
    "sg:postcode":"H7N 3V6",
    "sg:province":"QC",
    "wof:name":"Depanneur Et",
    "wof:placetype":"venue"
},
  "geometry": {"coordinates":[-73.706985,45.553379],"type":"Point"}
}