{
  "type": "Feature",
  "properties": {
    "addr:full":"1200 Rue Des Riveurs Levis QC G6V 9G2",
    "addr:housenumber":"1200",
    "addr:postcode":"g6v 9g2",
    "addr:street":"Rue Des Riveurs",
    "iso:country":"CA",
    "sg:address":"1200 Rue Des Riveurs",
    "sg:city":"Levis",
    "sg:classifiers":[
        {
            "category":"Professional",
            "subcategory":"Business Services",
            "type":"Services"
        }
    ],
    "sg:phone":"+1 418 833 0421",
    "sg:postcode":"G6V 9G2",
    "sg:province":"QC",
    "sg:tags":[
        "recycling",
        "center"
    ],
    "wof:name":"Societe Via Inc",
    "wof:placetype":"venue"
},
  "geometry": {"coordinates":[-71.1253356934,46.8173027039],"type":"Point"}
}