{
  "type": "Feature",
  "properties": {
    "addr:full":"5101 50th Ave Castor AB T0C 0X0",
    "addr:housenumber":"5101",
    "addr:postcode":"t0c 0x0",
    "addr:street":"50Th Ave",
    "iso:country":"CA",
    "sg:address":"5101 50th Ave",
    "sg:city":"Castor",
    "sg:classifiers":[
        {
            "category":"Restaurant",
            "type":"Food & Drink"
        }
    ],
    "sg:phone":"+1 403 882 3232",
    "sg:postcode":"T0C 0X0",
    "sg:province":"AB",
    "wof:name":"Golden Crown",
    "wof:placetype":"venue"
},
  "geometry": {"coordinates":[-111.90418243400001,52.218547821],"type":"Point"}
}