{
  "type": "Feature",
  "properties": {
    "addr:full":"350 Creditstone Rd Concord ON L4K 3Z2",
    "addr:housenumber":"350",
    "addr:postcode":"l4k 3z2",
    "addr:street":"Creditstone Rd",
    "iso:country":"CA",
    "sg:address":"350 Creditstone Rd",
    "sg:city":"Concord",
    "sg:classifiers":[
        {
            "category":"Manufacturing",
            "subcategory":"Metals",
            "type":"Manufacturing & Wholesale Goods"
        }
    ],
    "sg:phone":"+1 905 660 9050",
    "sg:postcode":"L4K 3Z2",
    "sg:province":"ON",
    "sg:tags":[
        "door"
    ],
    "wof:name":"Arrow 2000 Window & Door",
    "wof:placetype":"venue"
},
  "geometry": {"coordinates":[-79.5186080933,43.7981796265],"type":"Point"}
}