{
  "type": "Feature",
  "properties": {
    "addr:full":"Carp ON K0A 1L0",
    "addr:postcode":"k0a 1l0",
    "iso:country":"CA",
    "sg:city":"Carp",
    "sg:classifiers":[
        {
            "category":"Wholesale",
            "subcategory":"Farm Supplies",
            "type":"Manufacturing & Wholesale Goods"
        }
    ],
    "sg:phone":"+1 613 839 2802",
    "sg:postcode":"K0A 1L0",
    "sg:province":"ON",
    "sg:tags":[
        "feed"
    ],
    "wof:name":"Carp Flour Mills Feed Store",
    "wof:placetype":"venue"
},
  "geometry": {"coordinates":[-76.034042,45.344028],"type":"Point"}
}