{
  "type": "Feature",
  "properties": {
    "addr:full":"499 Hot Springs Harrison Hot Springs BC V0M 1K0",
    "addr:housenumber":"499",
    "addr:postcode":"v0m 1k0",
    "addr:street":"Hot Springs",
    "iso:country":"CA",
    "sg:address":"499 Hot Springs",
    "sg:city":"Harrison Hot Springs",
    "sg:classifiers":[
        {
            "category":"Government",
            "subcategory":"Office",
            "type":"Public Place"
        }
    ],
    "sg:phone":"+1 604 796 2913",
    "sg:postcode":"V0M 1K0",
    "sg:province":"BC",
    "sg:tags":[
        "village"
    ],
    "wof:name":"Harrison Hot Springs Shop",
    "wof:placetype":"venue"
},
  "geometry": {"coordinates":[-121.784554,49.29834],"type":"Point"}
}