{
  "type": "Feature",
  "properties": {
    "addr:full":"61 Charles St Oshawa ON L1H 4X8",
    "addr:housenumber":"61",
    "addr:postcode":"l1h 4x8",
    "addr:street":"Charles St",
    "iso:country":"CA",
    "sg:address":"61 Charles St",
    "sg:city":"Oshawa",
    "sg:classifiers":[
        {
            "category":"Freight",
            "type":"Transportation"
        }
    ],
    "sg:phone":"+1 905 721 9777",
    "sg:postcode":"L1H 4X8",
    "sg:province":"ON",
    "sg:tags":[
        "commercial",
        "storage"
    ],
    "wof:name":"Durham Storage Inc",
    "wof:placetype":"venue"
},
  "geometry": {"coordinates":[-78.858101,43.897182],"type":"Point"}
}