{
  "type": "Feature",
  "properties": {
    "addr:full":"617 Belmont St New Westminster BC V3M 5Z8",
    "addr:housenumber":"617",
    "addr:postcode":"v3m 5z8",
    "addr:street":"Belmont St",
    "iso:country":"CA",
    "sg:address":"617 Belmont St",
    "sg:city":"New Westminster",
    "sg:classifiers":[
        {
            "category":"Social Services",
            "subcategory":"Child Care",
            "type":"Services"
        }
    ],
    "sg:phone":"+1 604 526 1153",
    "sg:postcode":"V3M 5Z8",
    "sg:province":"BC",
    "wof:name":"Queens Park Preschool Society",
    "wof:placetype":"venue"
},
  "geometry": {"coordinates":[-122.919921875,49.2123260498],"type":"Point"}
}