{
  "type": "Feature",
  "properties": {
    "iso:country":"CA",
    "sg:address":"22051 Fraser Hwy",
    "sg:city":"Langley",
    "sg:classifiers":[
        {
            "category":"Health Services",
            "subcategory":"Hospital",
            "type":"Services"
        }
    ],
    "sg:phone":"+1 604 534 4121",
    "sg:postcode":"V3A 4H4",
    "sg:province":"BC",
    "wof:name":"Langley Memorial Hospital",
    "wof:placetype":"venue"
},
  "geometry": {"coordinates":[-122.613891602,49.0932998657],"type":"Point"}
}