{
  "type": "Feature",
  "properties": {
    "addr:full":"16 102 St Hay River NT X0E 0R9",
    "addr:housenumber":"102",
    "addr:postcode":"x0e 0r9",
    "addr:street":"16;St",
    "iso:country":"CA",
    "sg:address":"16 102 St",
    "sg:city":"Hay River",
    "sg:classifiers":[
        {
            "category":"Freight",
            "type":"Transportation"
        }
    ],
    "sg:phone":"+1 867 874 2566",
    "sg:postcode":"X0E 0R9",
    "sg:province":"NT",
    "sg:tags":[
        "bus",
        "courier"
    ],
    "wof:name":"Frontier Coachlines",
    "wof:placetype":"venue"
},
  "geometry": {"coordinates":[-115.738830566,60.8545379639],"type":"Point"}
}