{
  "type": "Feature",
  "properties": {
    "addr:full":"3790 Wheeler Line Tilbury ON N0P 2L0",
    "addr:housenumber":"3790",
    "addr:postcode":"n0p 2l0",
    "addr:street":"Wheeler Line",
    "iso:country":"CA",
    "sg:address":"3790 Wheeler Line",
    "sg:city":"Tilbury",
    "sg:classifiers":[
        {
            "category":"Manufacturing",
            "subcategory":"Printing",
            "type":"Manufacturing & Wholesale Goods"
        }
    ],
    "sg:phone":"+1 519 682 0170",
    "sg:postcode":"N0P 2L0",
    "sg:province":"ON",
    "sg:tags":[
        "hot",
        "stamping",
        "gold"
    ],
    "wof:name":"Imprint Technologies Inc",
    "wof:placetype":"venue"
},
  "geometry": {"coordinates":[-82.4106826782,42.2714347839],"type":"Point"}
}