{
  "type": "Feature",
  "properties": {
    "addr:full":"16 Grant Blvd Dundas ON L9H 4L6",
    "addr:housenumber":"16",
    "addr:postcode":"l9h 4l6",
    "addr:street":"Grant Blvd",
    "iso:country":"CA",
    "sg:address":"16 Grant Blvd",
    "sg:city":"Dundas",
    "sg:classifiers":[
        {
            "category":"Shopping",
            "type":"Retail Goods"
        }
    ],
    "sg:phone":"+1 905 628 3754",
    "sg:postcode":"L9H 4L6",
    "sg:province":"ON",
    "sg:tags":[
        "orthopedic",
        "appliance"
    ],
    "wof:name":"Orthomed Canada",
    "wof:placetype":"venue"
},
  "geometry": {"coordinates":[-79.9400939941,43.2595825195],"type":"Point"}
}