{
  "type": "Feature",
  "properties": {
    "addr:full":"13020 Delf Pl Richmond BC V6V 2A2",
    "addr:housenumber":"13020",
    "addr:postcode":"v6v 2a2",
    "addr:street":"Delf Pl",
    "iso:country":"CA",
    "sg:address":"13020 Delf Pl",
    "sg:city":"Richmond",
    "sg:classifiers":[
        {
            "category":"Restaurant",
            "type":"Food & Drink"
        }
    ],
    "sg:phone":"+1 604 207 1221",
    "sg:postcode":"V6V 2A2",
    "sg:province":"BC",
    "sg:tags":[
        "caterer"
    ],
    "wof:name":"Tiffaney's Catering Ltd",
    "wof:placetype":"venue"
},
  "geometry": {"coordinates":[-123.079926,49.180714],"type":"Point"}
}