{
  "type": "Feature",
  "properties": {
    "addr:full":"1686 Jalna Blvd London ON N6E 3P6",
    "addr:housenumber":"1686",
    "addr:postcode":"n6e 3p6",
    "addr:street":"Jalna Blvd",
    "iso:country":"CA",
    "sg:address":"1686 Jalna Blvd",
    "sg:city":"London",
    "sg:classifiers":[
        {
            "category":"Home & Garden",
            "subcategory":"Household Appliances",
            "type":"Retail Goods"
        }
    ],
    "sg:phone":"+1 519 668 3744",
    "sg:postcode":"N6E 3P6",
    "sg:province":"ON",
    "wof:name":"Tom Evanski Appliance Svc Spec",
    "wof:placetype":"venue"
},
  "geometry": {"coordinates":[-81.2450332642,42.9343643188],"type":"Point"}
}