{
  "type": "Feature",
  "properties": {
    "addr:full":"1011 53 Ave NE Calgary AB T2E 6X9",
    "addr:housenumber":"1011",
    "addr:postcode":"t2e 6x9",
    "addr:street":"53 Ave Ne",
    "iso:country":"CA",
    "sg:address":"1011 53 Ave NE",
    "sg:city":"Calgary",
    "sg:classifiers":[
        {
            "category":"Wholesale",
            "subcategory":"Machinery & Supplies",
            "type":"Manufacturing & Wholesale Goods"
        }
    ],
    "sg:phone":"+1 403 275 3601",
    "sg:postcode":"T2E 6X9",
    "sg:province":"AB",
    "sg:tags":[
        "equipment",
        "pump",
        "dairy"
    ],
    "wof:name":"Jadler Industries Ltd",
    "wof:placetype":"venue"
},
  "geometry": {"coordinates":[-114.04050445599999,51.0998878479],"type":"Point"}
}