{
  "type": "Feature",
  "properties": {
    "iso:country":"CA",
    "sg:address":"2787 Dunmark Rd",
    "sg:city":"Alberton",
    "sg:classifiers":[
        {
            "category":"Recreation",
            "type":"Entertainment"
        }
    ],
    "sg:phone":"+1 905 304 1414",
    "sg:postcode":"L0R 1A0",
    "sg:province":"ON",
    "sg:tags":[
        "course",
        "golf"
    ],
    "wof:name":"Heron Point Golf Links",
    "wof:placetype":"venue"
},
  "geometry": {"coordinates":[-80.0677490234,43.1776847839],"type":"Point"}
}