{
  "type": "Feature",
  "properties": {
    "addr:full":"3219 Dufferin St North York ON M6A 2T2",
    "addr:housenumber":"3219",
    "addr:postcode":"m6a 2t2",
    "addr:street":"Dufferin St",
    "iso:country":"CA",
    "sg:address":"3219 Dufferin St",
    "sg:city":"North York",
    "sg:classifiers":[
        {
            "category":"Local Transit",
            "type":"Transportation"
        }
    ],
    "sg:phone":"+1 416 787 0200",
    "sg:postcode":"M6A 2T2",
    "sg:province":"ON",
    "sg:tags":[
        "limousine"
    ],
    "wof:name":"Bright Star Limousine Svc",
    "wof:placetype":"venue"
},
  "geometry": {"coordinates":[-79.4556274414,43.7190971375],"type":"Point"}
}