{
  "type": "Feature",
  "properties": {
    "addr:full":"10660 156 St NW Edmonton AB T5P 2R9",
    "addr:housenumber":"10660",
    "addr:postcode":"t5p 2r9",
    "addr:street":"156 St Nw",
    "iso:country":"CA",
    "sg:address":"10660 156 St NW",
    "sg:city":"Edmonton",
    "sg:classifiers":[
        {
            "category":"Health Services",
            "subcategory":"Chiropractor",
            "type":"Services"
        }
    ],
    "sg:phone":"+1 780 486 2755",
    "sg:postcode":"T5P 2R9",
    "sg:province":"AB",
    "wof:name":"Anderson, Anders DC",
    "wof:placetype":"venue"
},
  "geometry": {"coordinates":[-113.590599,53.550388],"type":"Point"}
}