{
  "type": "Feature",
  "properties": {
    "addr:full":"7315 Rue Saint-Jacques Montreal QC H4B 1W2",
    "addr:housenumber":"7315",
    "addr:postcode":"h4b 1w2",
    "addr:street":"Rue Saint-Jacques",
    "iso:country":"CA",
    "sg:address":"7315 Rue Saint-Jacques",
    "sg:city":"Montreal",
    "sg:classifiers":[
        {
            "category":"Restaurant",
            "type":"Food & Drink"
        }
    ],
    "sg:phone":"+1 514 488 7952",
    "sg:postcode":"H4B 1W2",
    "sg:province":"QC",
    "wof:name":"Chez Timothee",
    "wof:placetype":"venue"
},
  "geometry": {"coordinates":[-73.63459,45.45433],"type":"Point"}
}