{
  "type": "Feature",
  "properties": {
    "iso:country":"CA",
    "sg:city":"Taber",
    "sg:classifiers":[
        {
            "category":"Wholesale",
            "subcategory":"Machinery & Supplies",
            "type":"Manufacturing & Wholesale Goods"
        }
    ],
    "sg:phone":"+1 403 223 8744",
    "sg:postcode":"T1G 1W7",
    "sg:province":"AB",
    "sg:tags":[
        "farm",
        "equipment"
    ],
    "wof:name":"Geeraert Mechanical Svc",
    "wof:placetype":"venue"
},
  "geometry": {"coordinates":[-112.13375854500001,49.786113739],"type":"Point"}
}