{
  "type": "Feature",
  "properties": {
    "addr:full":"15 Fugere Evain QC J0Z 1Y0",
    "addr:housenumber":"15",
    "addr:postcode":"j0z 1y0",
    "addr:street":"Fugere Evain",
    "iso:country":"CA",
    "sg:address":"15 Fugere",
    "sg:city":"Evain",
    "sg:classifiers":[
        {
            "category":"Government",
            "subcategory":"Office",
            "type":"Public Place"
        }
    ],
    "sg:phone":"+1 819 279 2241",
    "sg:postcode":"J0Z 1Y0",
    "sg:province":"QC",
    "sg:tags":[
        "village"
    ],
    "wof:name":"Arntfield Municipalite",
    "wof:placetype":"venue"
},
  "geometry": {"coordinates":[-79.230698,48.322769],"type":"Point"}
}