{
  "type": "Feature",
  "properties": {
    "iso:country":"CA",
    "sg:address":"5700 Ch DE LA Cote-DE-Liesse",
    "sg:city":"Mont-Royal",
    "sg:classifiers":[
        {
            "category":"Manufacturing",
            "subcategory":"Metals",
            "type":"Manufacturing & Wholesale Goods"
        }
    ],
    "sg:phone":"+1 514 735 5671",
    "sg:postcode":"H4T 1B1",
    "sg:province":"QC",
    "sg:tags":[
        "pipe",
        "thermometer"
    ],
    "wof:name":"Bowtemp Inc",
    "wof:placetype":"venue"
},
  "geometry": {"coordinates":[-73.67628479,45.4951019287],"type":"Point"}
}