{
  "type": "Feature",
  "properties": {
    "addr:full":"Sept-Iles QC G4R 4S6",
    "addr:postcode":"g4r 4s6",
    "iso:country":"CA",
    "sg:city":"Sept-Iles",
    "sg:classifiers":[
        {
            "category":"Shopping",
            "subcategory":"Gifts & Souvenirs",
            "type":"Retail Goods"
        }
    ],
    "sg:phone":"+1 418 962 9394",
    "sg:postcode":"G4R 4S6",
    "sg:province":"QC",
    "sg:tags":[
        "shop"
    ],
    "wof:name":"Boutique Aux Sentiments",
    "wof:placetype":"venue"
},
  "geometry": {"coordinates":[-66.391808,50.227005],"type":"Point"}
}