{
  "type": "Feature",
  "properties": {
    "addr:full":"12244 Rue Ranger Montreal QC H4J 2L2",
    "addr:housenumber":"12244",
    "addr:postcode":"h4j 2l2",
    "addr:street":"Rue Ranger",
    "iso:country":"CA",
    "sg:address":"12244 Rue Ranger",
    "sg:city":"Montreal",
    "sg:classifiers":[
        {
            "category":"Restaurant",
            "type":"Food & Drink"
        }
    ],
    "sg:phone":"+1 514 331 4945",
    "sg:postcode":"H4J 2L2",
    "sg:province":"QC",
    "wof:name":"Pen Castel",
    "wof:placetype":"venue"
},
  "geometry": {"coordinates":[-73.7198562622,45.5308151245],"type":"Point"}
}