{
  "type": "Feature",
  "properties": {
    "addr:full":"3845 Gladwin Rd Abbotsford BC V2S 7A1",
    "addr:housenumber":"3845",
    "addr:postcode":"v2s 7a1",
    "addr:street":"Gladwin Rd",
    "iso:country":"CA",
    "sg:address":"3845 Gladwin Rd",
    "sg:city":"Abbotsford",
    "sg:classifiers":[
        {
            "category":"Organizations",
            "subcategory":"Religious Organization",
            "type":"Services"
        }
    ],
    "sg:phone":"+1 604 853 3227",
    "sg:postcode":"V2S 7A1",
    "sg:province":"BC",
    "sg:tags":[
        "church"
    ],
    "wof:name":"Trinity Lutheran Church",
    "wof:placetype":"venue"
},
  "geometry": {"coordinates":[-122.316338,49.071453],"type":"Point"}
}