{
  "type": "Feature",
  "properties": {
    "addr:full":"4493 Rue Sherbrooke O Westmount QC H3Z 1E7",
    "addr:housenumber":"4493",
    "addr:postcode":"h3z 1e7",
    "addr:street":"Rue Sherbrooke O",
    "iso:country":"CA",
    "sg:address":"4493 Rue Sherbrooke O",
    "sg:city":"Westmount",
    "sg:classifiers":[
        {
            "category":"Professional",
            "subcategory":"Lawyer & Legal Services",
            "type":"Services"
        }
    ],
    "sg:phone":"+1 514 939 3993",
    "sg:postcode":"H3Z 1E7",
    "sg:province":"QC",
    "sg:tags":[
        "attorney"
    ],
    "wof:name":"Gruszczynski Romoff",
    "wof:placetype":"venue"
},
  "geometry": {"coordinates":[-73.598534,45.483471],"type":"Point"}
}