{
  "type": "Feature",
  "properties": {
    "addr:full":"920 Boul Du Seminaire N Saint-Jean-Sur-Richelieu QC J3A 1B7",
    "addr:housenumber":"920",
    "addr:postcode":"j3a 1b7",
    "addr:street":"Boul Du Seminaire N",
    "iso:country":"CA",
    "sg:address":"920 Boul Du Seminaire N",
    "sg:city":"Saint-Jean-Sur-Richelieu",
    "sg:classifiers":[
        {
            "category":"Health Services",
            "subcategory":"Hospital",
            "type":"Services"
        }
    ],
    "sg:phone":"+1 450 359 5000",
    "sg:postcode":"J3A 1B7",
    "sg:province":"QC",
    "wof:name":"Hopital Du Haut-Richelieu",
    "wof:placetype":"venue"
},
  "geometry": {"coordinates":[-73.2680892944,45.3328132629],"type":"Point"}
}