{
  "type": "Feature",
  "properties": {
    "addr:full":"755 Main St E North Bay ON P1B 1C2",
    "addr:housenumber":"755",
    "addr:postcode":"p1b 1c2",
    "addr:street":"Main St E",
    "iso:country":"CA",
    "sg:address":"755 Main St E",
    "sg:city":"North Bay",
    "sg:classifiers":[
        {
            "category":"Shopping",
            "subcategory":"Musical Instruments",
            "type":"Retail Goods"
        }
    ],
    "sg:phone":"+1 705 472 0070",
    "sg:postcode":"P1B 1C2",
    "sg:province":"ON",
    "sg:tags":[
        "sales",
        "live",
        "music",
        "karaoke",
        "entertainment"
    ],
    "wof:name":"Acclaim Sound & Lighting",
    "wof:placetype":"venue"
},
  "geometry": {"coordinates":[-79.45649,46.30162],"type":"Point"}
}