{
  "type": "Feature",
  "properties": {
    "addr:full":"180 Boul Du Mont-Bleu Hull QC J8Z 3J5",
    "addr:housenumber":"180",
    "addr:postcode":"j8z 3j5",
    "addr:street":"Boul Du Mont-Bleu",
    "iso:country":"CA",
    "sg:address":"180 Boul Du Mont-Bleu",
    "sg:city":"Hull",
    "sg:classifiers":[
        {
            "category":"Insurance",
            "subcategory":"Insurance Agent",
            "type":"Services"
        }
    ],
    "sg:phone":"+1 819 595 0708",
    "sg:postcode":"J8Z 3J5",
    "sg:province":"QC",
    "wof:name":"Mutuelle D'Aglise DE L'Inter",
    "wof:placetype":"venue"
},
  "geometry": {"coordinates":[-75.762497,45.46122],"type":"Point"}
}