{
  "type": "Feature",
  "properties": {
    "addr:full":"32 Mill St Aurora ON L4G 2R9",
    "addr:housenumber":"32",
    "addr:postcode":"l4g 2r9",
    "addr:street":"Mill St",
    "iso:country":"CA",
    "sg:address":"32 Mill St",
    "sg:city":"Aurora",
    "sg:classifiers":[
        {
            "category":"Health Services",
            "subcategory":"Nursing And Care Facility",
            "type":"Services"
        }
    ],
    "sg:phone":"+1 905 727 1939",
    "sg:postcode":"L4G 2R9",
    "sg:province":"ON",
    "sg:tags":[
        "home",
        "convalescent"
    ],
    "wof:name":"Aurora Resthaven",
    "wof:placetype":"venue"
},
  "geometry": {"coordinates":[-79.4704742432,43.9983139038],"type":"Point"}
}