{
  "type": "Feature",
  "properties": {
    "addr:full":"Cranbrook BC V1C 7G3",
    "addr:postcode":"v1c 7g3",
    "iso:country":"CA",
    "sg:city":"Cranbrook",
    "sg:classifiers":[
        {
            "category":"Retail",
            "subcategory":"Auto Repair",
            "type":"Services"
        }
    ],
    "sg:phone":"+1 250 426 3233",
    "sg:postcode":"V1C 7G3",
    "sg:province":"BC",
    "sg:tags":[
        "repairing",
        "automobile"
    ],
    "wof:name":"Cranbrook Auto Repair & Svc",
    "wof:placetype":"venue"
},
  "geometry": {"coordinates":[-115.755928,49.526302],"type":"Point"}
}