{
  "type": "Feature",
  "properties": {
    "addr:full":"48 Pheasant Run Dr Guelph ON N1C 1E7",
    "addr:housenumber":"48",
    "addr:postcode":"n1c 1e7",
    "addr:street":"Pheasant Run Dr",
    "iso:country":"CA",
    "sg:address":"48 Pheasant Run Dr",
    "sg:city":"Guelph",
    "sg:classifiers":[
        {
            "category":"Building & Trades",
            "subcategory":"Construction",
            "type":"Services"
        }
    ],
    "sg:phone":"+1 519 821 6061",
    "sg:postcode":"N1C 1E7",
    "sg:province":"ON",
    "sg:tags":[
        "painter"
    ],
    "wof:name":"Jack Obiala's Painting",
    "wof:placetype":"venue"
},
  "geometry": {"coordinates":[-80.23825100000001,43.495747],"type":"Point"}
}