{
  "type": "Feature",
  "properties": {
    "addr:full":"44 Rue Parent Saint-Liboire QC J0H 1R0",
    "addr:housenumber":"44",
    "addr:postcode":"j0h 1r0",
    "addr:street":"Rue Parent",
    "iso:country":"CA",
    "sg:address":"44 Rue Parent",
    "sg:city":"Saint-Liboire",
    "sg:classifiers":[
        {
            "category":"Building & Trades",
            "subcategory":"Construction",
            "type":"Services"
        }
    ],
    "sg:phone":"+1 450 793 2340",
    "sg:postcode":"J0H 1R0",
    "sg:province":"QC",
    "sg:tags":[
        "excavating",
        "contractor"
    ],
    "wof:name":"Laflamme, Daniel",
    "wof:placetype":"venue"
},
  "geometry": {"coordinates":[-72.761314,45.650681],"type":"Point"}
}