{
  "type": "Feature",
  "properties": {
    "addr:full":"295 Queenston Rd Hamilton ON L8K 1H2",
    "addr:housenumber":"295",
    "addr:postcode":"l8k 1h2",
    "addr:street":"Queenston Rd",
    "iso:country":"CA",
    "sg:address":"295 Queenston Rd",
    "sg:city":"Hamilton",
    "sg:classifiers":[
        {
            "category":"Education",
            "subcategory":"School",
            "type":"Public Place"
        }
    ],
    "sg:phone":"+1 905 547 8862",
    "sg:postcode":"L8K 1H2",
    "sg:province":"ON",
    "sg:tags":[
        "academic",
        "instruction",
        "music",
        "special"
    ],
    "wof:name":"Agnes Viola School of Music",
    "wof:placetype":"venue"
},
  "geometry": {"coordinates":[-79.791267,43.234203],"type":"Point"}
}