{
  "type": "Feature",
  "properties": {
    "addr:full":"171 Railway Ave Komoka ON N0L 1R0",
    "addr:housenumber":"171",
    "addr:postcode":"n0l 1r0",
    "addr:street":"Railway Ave",
    "iso:country":"CA",
    "sg:address":"171 Railway Ave",
    "sg:city":"Komoka",
    "sg:classifiers":[
        {
            "category":"Wholesale",
            "subcategory":"Farm Supplies",
            "type":"Manufacturing & Wholesale Goods"
        }
    ],
    "sg:phone":"+1 519 657 1744",
    "sg:postcode":"N0L 1R0",
    "sg:province":"ON",
    "sg:tags":[
        "feed"
    ],
    "wof:name":"Superfeeder Services",
    "wof:placetype":"venue"
},
  "geometry": {"coordinates":[-81.427109,42.95475],"type":"Point"}
}