{
  "type": "Feature",
  "properties": {
    "addr:full":"RR 2 STN Main Olds AB T4H 1P3",
    "addr:postcode":"t4h 1p3",
    "addr:street":"Rr 2 Stn Main",
    "iso:country":"CA",
    "sg:address":"RR 2 STN Main",
    "sg:city":"Olds",
    "sg:classifiers":[
        {
            "category":"Farming",
            "subcategory":"Nursery",
            "type":"Manufacturing & Wholesale Goods"
        }
    ],
    "sg:phone":"+1 403 556 7733",
    "sg:postcode":"T4H 1P3",
    "sg:province":"AB",
    "sg:tags":[
        "greenhouse"
    ],
    "wof:name":"Room Outside",
    "wof:placetype":"venue"
},
  "geometry": {"coordinates":[-114.11061100000001,51.791626],"type":"Point"}
}