{
  "type": "Feature",
  "properties": {
    "addr:full":"5141 Steeles Ave W North York ON M9L 1R5",
    "addr:housenumber":"5141",
    "addr:postcode":"m9l 1r5",
    "addr:street":"Steeles Ave W",
    "iso:country":"CA",
    "sg:address":"5141 Steeles Ave W",
    "sg:city":"North York",
    "sg:classifiers":[
        {
            "category":"Wholesale",
            "subcategory":"Construction Materials",
            "type":"Manufacturing & Wholesale Goods"
        }
    ],
    "sg:phone":"+1 416 743 4227",
    "sg:postcode":"M9L 1R5",
    "sg:province":"ON",
    "sg:tags":[
        "marble"
    ],
    "wof:name":"New Way Marble & Tile Ltd",
    "wof:placetype":"venue"
},
  "geometry": {"coordinates":[-79.5505142212,43.7693138123],"type":"Point"}
}