{
  "type": "Feature",
  "properties": {
    "iso:country":"CA",
    "sg:address":"11 Baldwin St",
    "sg:city":"Riverview",
    "sg:classifiers":[
        {
            "category":"Building & Trades",
            "subcategory":"Construction",
            "type":"Services"
        }
    ],
    "sg:phone":"+1 506 386 5276",
    "sg:postcode":"E1B 3C9",
    "sg:province":"NB",
    "sg:tags":[
        "designer",
        "dealer",
        "pool",
        "swimming"
    ],
    "wof:name":"Eric Douthwright Swimming Pool",
    "wof:placetype":"venue"
},
  "geometry": {"coordinates":[-64.8056182861,46.054019928],"type":"Point"}
}