{
  "type": "Feature",
  "properties": {
    "addr:full":"755 St. Peter Ave Bathurst NB E2A 2Y9",
    "addr:housenumber":"755",
    "addr:postcode":"e2a 2y9",
    "addr:street":"St. Peter Ave",
    "iso:country":"CA",
    "sg:address":"755 St. Peter Ave",
    "sg:city":"Bathurst",
    "sg:classifiers":[
        {
            "category":"Restaurant",
            "type":"Food & Drink"
        }
    ],
    "sg:phone":"+1 506 548 9860",
    "sg:postcode":"E2A 2Y9",
    "sg:province":"NB",
    "wof:name":"Wendy's",
    "wof:placetype":"venue"
},
  "geometry": {"coordinates":[-65.66928900000001,47.632107],"type":"Point"}
}