{
  "type": "Feature",
  "properties": {
    "addr:full":"800 112 Rte Saint-Cesaire QC J0L 1T0",
    "addr:housenumber":"112",
    "addr:postcode":"j0l 1t0",
    "addr:street":"Rte Saint-Cesaire",
    "iso:country":"CA",
    "sg:address":"800 112 Rte",
    "sg:city":"Saint-Cesaire",
    "sg:classifiers":[
        {
            "category":"Autos & Motor Vehicles",
            "subcategory":"Motorcycle Sales",
            "type":"Retail Goods"
        }
    ],
    "sg:phone":"+1 450 469 2733",
    "sg:postcode":"J0L 1T0",
    "sg:province":"QC",
    "sg:tags":[
        "scooter"
    ],
    "wof:name":"St-Cesaire Moto Sports Inc",
    "wof:placetype":"venue"
},
  "geometry": {"coordinates":[-72.996689,45.413181],"type":"Point"}
}