{
  "type": "Feature",
  "properties": {
    "addr:full":"Hwy 41 W Melfort SK S0E 1A0",
    "addr:postcode":"s0e 1a0",
    "addr:street":"Hwy 41 W Melfort",
    "iso:country":"CA",
    "sg:address":"Hwy 41 W",
    "sg:city":"Melfort",
    "sg:classifiers":[
        {
            "category":"Freight",
            "type":"Transportation"
        }
    ],
    "sg:phone":"+1 306 752 9073",
    "sg:postcode":"S0E 1A0",
    "sg:province":"SK",
    "sg:tags":[
        "grain",
        "elevator"
    ],
    "wof:name":"Pioneer Grain CO Ltd",
    "wof:placetype":"venue"
},
  "geometry": {"coordinates":[-104.59774,52.84177],"type":"Point"}
}