{
  "type": "Feature",
  "properties": {
    "addr:full":"9711 Fifth St Sidney BC V8L 2W9",
    "addr:housenumber":"9711",
    "addr:postcode":"v8l 2w9",
    "addr:street":"Fifth St",
    "iso:country":"CA",
    "sg:address":"9711 Fifth St",
    "sg:city":"Sidney",
    "sg:classifiers":[
        {
            "category":"Shopping",
            "subcategory":"Crafts & Fabrics",
            "type":"Retail Goods"
        }
    ],
    "sg:phone":"+1 250 656 2499",
    "sg:postcode":"V8L 2W9",
    "sg:province":"BC",
    "sg:tags":[
        "woolen",
        "needlework"
    ],
    "wof:name":"In Sheep's Clothing Wool Shop",
    "wof:placetype":"venue"
},
  "geometry": {"coordinates":[-123.400093,48.647026],"type":"Point"}
}