{
  "type": "Feature",
  "properties": {
    "addr:full":"967 Rue Maurice Canton-DE-Granby QC J2G 9J1",
    "addr:housenumber":"967",
    "addr:postcode":"j2g 9j1",
    "addr:street":"Rue Maurice Canton-De-Granby",
    "iso:country":"CA",
    "sg:address":"967 Rue Maurice",
    "sg:city":"Canton-DE-Granby",
    "sg:classifiers":[
        {
            "category":"Building & Trades",
            "subcategory":"Construction",
            "type":"Services"
        }
    ],
    "sg:phone":"+1 450 372 9223",
    "sg:postcode":"J2G 9J1",
    "sg:province":"QC",
    "sg:tags":[
        "contractor"
    ],
    "wof:name":"Construction Yj Tremblay Inc",
    "wof:placetype":"venue"
},
  "geometry": {"coordinates":[-72.7217712402,45.3979949951],"type":"Point"}
}