{
  "type": "Feature",
  "properties": {
    "addr:full":"Chilliwack BC V2R 5S3",
    "addr:postcode":"v2r 5s3",
    "iso:country":"CA",
    "sg:city":"Chilliwack",
    "sg:classifiers":[
        {
            "category":"Building & Trades",
            "subcategory":"Construction",
            "type":"Services"
        }
    ],
    "sg:phone":"+1 604 847 0700",
    "sg:postcode":"V2R 5S3",
    "sg:province":"BC",
    "sg:tags":[
        "general",
        "contractor"
    ],
    "wof:name":"Van Maren Construction CO Ltd",
    "wof:placetype":"venue"
},
  "geometry": {"coordinates":[-121.95787799999999,49.14307],"type":"Point"}
}