{
  "type": "Feature",
  "properties": {
    "addr:full":"301 Manitoba St Schreiber ON P0T 2S0",
    "addr:housenumber":"301",
    "addr:postcode":"p0t 2s0",
    "addr:street":"Manitoba St",
    "iso:country":"CA",
    "sg:address":"301 Manitoba St",
    "sg:city":"Schreiber",
    "sg:classifiers":[
        {
            "category":"Food & Beverages",
            "subcategory":"Groceries & Convenience Stores",
            "type":"Retail Goods"
        }
    ],
    "sg:phone":"+1 807 824 3383",
    "sg:postcode":"P0T 2S0",
    "sg:province":"ON",
    "sg:tags":[
        "grocer"
    ],
    "wof:name":"Skale Foods Ltd",
    "wof:placetype":"venue"
},
  "geometry": {"coordinates":[-87.2659378052,48.8085517883],"type":"Point"}
}