{
  "type": "Feature",
  "properties": {
    "addr:full":"2625 Av Dalton Sainte-Foy QC G1P 3S9",
    "addr:housenumber":"2625",
    "addr:postcode":"g1p 3s9",
    "addr:street":"Av Dalton",
    "iso:country":"CA",
    "sg:address":"2625 Av Dalton",
    "sg:city":"Sainte-Foy",
    "sg:classifiers":[
        {
            "category":"Manufacturing",
            "subcategory":"Electronics",
            "type":"Manufacturing & Wholesale Goods"
        }
    ],
    "sg:phone":"+1 418 651 8001",
    "sg:postcode":"G1P 3S9",
    "sg:province":"QC",
    "sg:tags":[
        "equipment",
        "electronic",
        "supply"
    ],
    "wof:name":"Gentec Inc",
    "wof:placetype":"venue"
},
  "geometry": {"coordinates":[-71.305519104,46.789981842],"type":"Point"}
}