{
  "type": "Feature",
  "properties": {
    "addr:full":"717 Mount Pleasant Rd # A Toronto ON M4S 2N4",
    "addr:housenumber":"717",
    "addr:postcode":"m4s 2n4",
    "addr:street":"Mount Pleasant Rd # A",
    "iso:country":"CA",
    "sg:address":"717 Mount Pleasant Rd # A",
    "sg:city":"Toronto",
    "sg:classifiers":[
        {
            "category":"Building & Trades",
            "subcategory":"Plumbing",
            "type":"Services"
        }
    ],
    "sg:phone":"+1 416 481 7215",
    "sg:postcode":"M4S 2N4",
    "sg:province":"ON",
    "sg:tags":[
        "contractor"
    ],
    "wof:name":"A G Shanks Plumbing & Heating",
    "wof:placetype":"venue"
},
  "geometry": {"coordinates":[-79.389381,43.706898],"type":"Point"}
}