{
  "type": "Feature",
  "properties": {
    "addr:full":"Saskatoon SK S7M 4A8",
    "addr:postcode":"s7m 4a8",
    "iso:country":"CA",
    "sg:city":"Saskatoon",
    "sg:classifiers":[
        {
            "category":"Retail",
            "subcategory":"Auto Repair",
            "type":"Services"
        }
    ],
    "sg:phone":"+1 306 244 6322",
    "sg:postcode":"S7M 4A8",
    "sg:province":"SK",
    "sg:tags":[
        "repairing",
        "automobile",
        "painting"
    ],
    "wof:name":"Autocolor Collision Ctr Ltd",
    "wof:placetype":"venue"
},
  "geometry": {"coordinates":[-106.694237,52.12244],"type":"Point"}
}