{
  "type": "Feature",
  "properties": {
    "addr:full":"Calgary AB T2E 6K5",
    "addr:postcode":"t2e 6k5",
    "iso:country":"CA",
    "sg:city":"Calgary",
    "sg:classifiers":[
        {
            "category":"Banks & Credit Unions",
            "subcategory":"Financial Services",
            "type":"Services"
        }
    ],
    "sg:phone":"+1 403 277 9156",
    "sg:postcode":"T2E 6K5",
    "sg:province":"AB",
    "sg:tags":[
        "company",
        "holding"
    ],
    "wof:name":"Teramo Holdings Ltd",
    "wof:placetype":"venue"
},
  "geometry": {"coordinates":[-114.04811859100001,51.0850868225],"type":"Point"}
}