{
  "type": "Feature",
  "properties": {
    "addr:full":"27 Primrose Ave Toronto ON M6H 3V1",
    "addr:housenumber":"27",
    "addr:postcode":"m6h 3v1",
    "addr:street":"Primrose Ave",
    "iso:country":"CA",
    "sg:address":"27 Primrose Ave",
    "sg:city":"Toronto",
    "sg:classifiers":[
        {
            "category":"Communications",
            "subcategory":"Film & Video Production",
            "type":"Services"
        }
    ],
    "sg:phone":"+1 416 538 6342",
    "sg:postcode":"M6H 3V1",
    "sg:province":"ON",
    "sg:tags":[
        "motion",
        "picture",
        "studio",
        "producer"
    ],
    "wof:name":"Primrose Studios",
    "wof:placetype":"venue"
},
  "geometry": {"coordinates":[-79.444603,43.668785],"type":"Point"}
}