{
  "type": "Feature",
  "properties": {
    "addr:full":"Hamilton ON L8N 2C3",
    "addr:postcode":"l8n 2c3",
    "iso:country":"CA",
    "sg:city":"Hamilton",
    "sg:classifiers":[
        {
            "category":"Social Services",
            "type":"Services"
        }
    ],
    "sg:phone":"+1 905 527 8919",
    "sg:postcode":"L8N 2C3",
    "sg:province":"ON",
    "sg:tags":[
        "organization",
        "welfare"
    ],
    "wof:name":"Hamilton Midwives",
    "wof:placetype":"venue"
},
  "geometry": {"coordinates":[-79.86797300000001,43.252426],"type":"Point"}
}