{
  "type": "Feature",
  "properties": {
    "addr:full":"210 Rue York Granby QC J2G 2B8",
    "addr:housenumber":"210",
    "addr:postcode":"j2g 2b8",
    "addr:street":"Rue York",
    "iso:country":"CA",
    "sg:address":"210 Rue York",
    "sg:city":"Granby",
    "sg:classifiers":[
        {
            "category":"Shopping",
            "subcategory":"Florist",
            "type":"Retail Goods"
        }
    ],
    "sg:phone":"+1 450 372 3925",
    "sg:postcode":"J2G 2B8",
    "sg:province":"QC",
    "wof:name":"A LA Maison Montcalm",
    "wof:placetype":"venue"
},
  "geometry": {"coordinates":[-72.724281,45.406281],"type":"Point"}
}