{
  "type": "Feature",
  "properties": {
    "addr:full":"5933 Hazeldean Rd Stittsville ON K2S 1B9",
    "addr:housenumber":"5933",
    "addr:postcode":"k2s 1b9",
    "addr:street":"Hazeldean Rd",
    "iso:country":"CA",
    "sg:address":"5933 Hazeldean Rd",
    "sg:city":"Stittsville",
    "sg:classifiers":[
        {
            "category":"Retail",
            "subcategory":"Repair Shop",
            "type":"Services"
        }
    ],
    "sg:phone":"+1 613 836 3541",
    "sg:postcode":"K2S 1B9",
    "sg:province":"ON",
    "sg:tags":[
        "upholsterer"
    ],
    "wof:name":"Frank Cantusci Upholstery",
    "wof:placetype":"venue"
},
  "geometry": {"coordinates":[-75.92248499999999,45.276619],"type":"Point"}
}