{
  "type": "Feature",
  "properties": {
    "addr:full":"1860 Robson St Vancouver BC V6G 3C1",
    "addr:housenumber":"1860",
    "addr:postcode":"v6g 3c1",
    "addr:street":"Robson St",
    "iso:country":"CA",
    "sg:address":"1860 Robson St",
    "sg:city":"Vancouver",
    "sg:classifiers":[
        {
            "category":"Real Estate",
            "subcategory":"Real Estate Operator",
            "type":"Services"
        }
    ],
    "sg:phone":"+1 604 683 5120",
    "sg:postcode":"V6G 3C1",
    "sg:province":"BC",
    "sg:tags":[
        "condominium"
    ],
    "wof:name":"Stanley Park Place",
    "wof:placetype":"venue"
},
  "geometry": {"coordinates":[-123.136566,49.291985],"type":"Point"}
}