{
  "type": "Feature",
  "properties": {
    "addr:full":"270 Rue Brunet Mont-Saint-Hilaire QC J3G 4S6",
    "addr:housenumber":"270",
    "addr:postcode":"j3g 4s6",
    "addr:street":"Rue Brunet",
    "iso:country":"CA",
    "sg:address":"270 Rue Brunet",
    "sg:city":"Mont-Saint-Hilaire",
    "sg:classifiers":[
        {
            "category":"Building & Trades",
            "subcategory":"Construction",
            "type":"Services"
        }
    ],
    "sg:phone":"+1 450 446 8144",
    "sg:postcode":"J3G 4S6",
    "sg:province":"QC",
    "sg:tags":[
        "well",
        "drilling"
    ],
    "wof:name":"Foraction Inc",
    "wof:placetype":"venue"
},
  "geometry": {"coordinates":[-73.173042,45.594215],"type":"Point"}
}