{
  "type": "Feature",
  "properties": {
    "addr:full":"124 Main Rd Wareham-Centreville NL A0G 4P0",
    "addr:housenumber":"124",
    "addr:postcode":"a0g 4p0",
    "addr:street":"Main Rd",
    "iso:country":"CA",
    "sg:address":"124 Main Rd",
    "sg:city":"Wareham-Centreville",
    "sg:classifiers":[
        {
            "category":"Taxi",
            "type":"Transportation"
        }
    ],
    "sg:phone":"+1 709 678 2360",
    "sg:postcode":"A0G 4P0",
    "sg:province":"NL",
    "sg:tags":[
        "taxicab"
    ],
    "wof:name":"Jim Hunt Taxi",
    "wof:placetype":"venue"
},
  "geometry": {"coordinates":[-53.888969,49.012432],"type":"Point"}
}