{
  "type": "Feature",
  "properties": {
    "addr:full":"1789 Lawrence Ave W North York ON M6L 1E3",
    "addr:housenumber":"1789",
    "addr:postcode":"m6l 1e3",
    "addr:street":"Lawrence Ave W",
    "iso:country":"CA",
    "sg:address":"1789 Lawrence Ave W",
    "sg:city":"North York",
    "sg:classifiers":[
        {
            "category":"Organizations",
            "subcategory":"Religious Organization",
            "type":"Services"
        }
    ],
    "sg:phone":"+1 416 241 6738",
    "sg:postcode":"M6L 1E3",
    "sg:province":"ON",
    "sg:tags":[
        "church"
    ],
    "wof:name":"St Bernard Church",
    "wof:placetype":"venue"
},
  "geometry": {"coordinates":[-79.500587,43.703339],"type":"Point"}
}