{
  "type": "Feature",
  "properties": {
    "addr:full":"718 Railway Ave Rosthern SK S0K 3R0",
    "addr:housenumber":"718",
    "addr:postcode":"s0k 3r0",
    "addr:street":"Railway Ave",
    "iso:country":"CA",
    "sg:address":"718 Railway Ave",
    "sg:city":"Rosthern",
    "sg:classifiers":[
        {
            "category":"Professional",
            "subcategory":"Lawyer & Legal Services",
            "type":"Services"
        }
    ],
    "sg:phone":"+1 306 232 4482",
    "sg:postcode":"S0K 3R0",
    "sg:province":"SK",
    "sg:tags":[
        "attorney"
    ],
    "wof:name":"Parchomchuk, Ronald G",
    "wof:placetype":"venue"
},
  "geometry": {"coordinates":[-106.33169599999999,52.657753],"type":"Point"}
}