{
  "type": "Feature",
  "properties": {
    "addr:full":"Georgetown ON L7G 5B5",
    "addr:postcode":"l7g 5b5",
    "iso:country":"CA",
    "sg:city":"Georgetown",
    "sg:classifiers":[
        {
            "category":"Insurance",
            "subcategory":"Insurance Agent",
            "type":"Services"
        }
    ],
    "sg:phone":"+1 905 873 1615",
    "sg:postcode":"L7G 5B5",
    "sg:province":"ON",
    "wof:name":"State Farm Insurance CO",
    "wof:placetype":"venue"
},
  "geometry": {"coordinates":[-79.9011764526,43.6502761841],"type":"Point"}
}