{
  "type": "Feature",
  "properties": {
    "addr:full":"8080 Edgar Industrial Cres Red Deer AB T4P 3R3",
    "addr:housenumber":"8080",
    "addr:postcode":"t4p 3r3",
    "addr:street":"Edgar Industrial Cres",
    "iso:country":"CA",
    "sg:address":"8080 Edgar Industrial Cres",
    "sg:city":"Red Deer",
    "sg:classifiers":[
        {
            "category":"Mining & Drilling",
            "type":"Manufacturing & Wholesale Goods"
        }
    ],
    "sg:phone":"+1 403 347 9727",
    "sg:postcode":"T4P 3R3",
    "sg:province":"AB",
    "sg:tags":[
        "field",
        "oil"
    ],
    "wof:name":"Lonkar Services Ltd",
    "wof:placetype":"venue"
},
  "geometry": {"coordinates":[-113.85458374,52.31615448],"type":"Point"}
}