{
  "type": "Feature",
  "properties": {
    "addr:full":"24A Timber Rd Elliot Lake ON P5A 2T1",
    "addr:housenumber":"24a",
    "addr:postcode":"p5a 2t1",
    "addr:street":"Timber Rd",
    "iso:country":"CA",
    "sg:address":"24A Timber Rd",
    "sg:city":"Elliot Lake",
    "sg:classifiers":[
        {
            "category":"Retail",
            "subcategory":"Auto Repair",
            "type":"Services"
        }
    ],
    "sg:phone":"+1 705 848 8860",
    "sg:postcode":"P5A 2T1",
    "sg:province":"ON",
    "sg:tags":[
        "transmission",
        "automobile",
        "repairing"
    ],
    "wof:name":"Auto Works",
    "wof:placetype":"venue"
},
  "geometry": {"coordinates":[-82.6689071655,46.4013557434],"type":"Point"}
}