{
  "type": "Feature",
  "properties": {
    "addr:full":"13450 65A Ave Surrey BC V3W 1Z6",
    "addr:housenumber":"13450",
    "addr:postcode":"v3w 1z6",
    "addr:street":"65A Ave",
    "iso:country":"CA",
    "sg:address":"13450 65A Ave",
    "sg:city":"Surrey",
    "sg:classifiers":[
        {
            "category":"Retail",
            "subcategory":"Repair Shop",
            "type":"Services"
        }
    ],
    "sg:phone":"+1 604 590 8623",
    "sg:postcode":"V3W 1Z6",
    "sg:province":"BC",
    "sg:tags":[
        "welding"
    ],
    "wof:name":"Dale Fulton Contractors",
    "wof:placetype":"venue"
},
  "geometry": {"coordinates":[-122.830215454,49.105178833],"type":"Point"}
}