{
  "type": "Feature",
  "properties": {
    "addr:full":"Toronto ON M5J 2G2",
    "addr:postcode":"m5j 2g2",
    "iso:country":"CA",
    "sg:city":"Toronto",
    "sg:classifiers":[
        {
            "category":"Banks & Credit Unions",
            "subcategory":"Bank",
            "type":"Services"
        }
    ],
    "sg:phone":"+1 416 363 0574",
    "sg:postcode":"M5J 2G2",
    "sg:province":"ON",
    "sg:tags":[
        "advisory",
        "financial"
    ],
    "wof:name":"Mac Donald Bancorp",
    "wof:placetype":"venue"
},
  "geometry": {"coordinates":[-79.37716674799999,43.640827179],"type":"Point"}
}