{
  "type": "Feature",
  "properties": {
    "addr:full":"7720 108 St NW Edmonton AB T6E 5E1",
    "addr:housenumber":"7720",
    "addr:postcode":"t6e 5e1",
    "addr:street":"108 St Nw",
    "iso:country":"CA",
    "sg:address":"7720 108 St NW",
    "sg:city":"Edmonton",
    "sg:classifiers":[
        {
            "category":"Restaurant",
            "type":"Food & Drink"
        }
    ],
    "sg:phone":"+1 780 432 2648",
    "sg:postcode":"T6E 5E1",
    "sg:province":"AB",
    "sg:tags":[
        "caterer"
    ],
    "wof:name":"Anna Maria's Kitchen",
    "wof:placetype":"venue"
},
  "geometry": {"coordinates":[-113.50957489,53.5134773254],"type":"Point"}
}