{
  "type": "Feature",
  "properties": {
    "addr:full":"1002 Rue Vanasse Rouyn-Noranda QC J9X 3V6",
    "addr:housenumber":"1002",
    "addr:postcode":"j9x 3v6",
    "addr:street":"Rue Vanasse",
    "iso:country":"CA",
    "sg:address":"1002 Rue Vanasse",
    "sg:city":"Rouyn-Noranda",
    "sg:classifiers":[
        {
            "category":"Professional",
            "subcategory":"Business Services",
            "type":"Services"
        }
    ],
    "sg:phone":"+1 819 762 7350",
    "sg:postcode":"J9X 3V6",
    "sg:province":"QC",
    "sg:tags":[
        "water",
        "treatment"
    ],
    "wof:name":"Distribution H2Odl Enr",
    "wof:placetype":"venue"
},
  "geometry": {"coordinates":[-79.000748,48.224262],"type":"Point"}
}