{
  "type": "Feature",
  "properties": {
    "addr:full":"1827 Rue Galt Montreal QC H4E 1J5",
    "addr:housenumber":"1827",
    "addr:postcode":"h4e 1j5",
    "addr:street":"Rue Galt",
    "iso:country":"CA",
    "sg:address":"1827 Rue Galt",
    "sg:city":"Montreal",
    "sg:classifiers":[
        {
            "category":"Building & Trades",
            "subcategory":"Construction",
            "type":"Services"
        }
    ],
    "sg:phone":"+1 514 767 4062",
    "sg:postcode":"H4E 1J5",
    "sg:province":"QC",
    "sg:tags":[
        "resurfacing",
        "laying",
        "refinishing",
        "floor"
    ],
    "wof:name":"Plancher Gadoury & Fils",
    "wof:placetype":"venue"
},
  "geometry": {"coordinates":[-73.5884170532,45.4629821777],"type":"Point"}
}