{
  "type": "Feature",
  "properties": {
    "addr:full":"Nanaimo BC V9S 1G9",
    "addr:postcode":"v9s 1g9",
    "iso:country":"CA",
    "sg:city":"Nanaimo",
    "sg:classifiers":[
        {
            "category":"Shopping",
            "type":"Retail Goods"
        }
    ],
    "sg:phone":"+1 250 753 0315",
    "sg:postcode":"V9S 1G9",
    "sg:province":"BC",
    "sg:tags":[
        "orthopedic",
        "appliance"
    ],
    "wof:name":"Orthoti Care Clinics Inc",
    "wof:placetype":"venue"
},
  "geometry": {"coordinates":[-123.978347778,49.1809196472],"type":"Point"}
}