{
  "type": "Feature",
  "properties": {
    "addr:full":"4335 Water St Miramichi NB E1N 4L9",
    "addr:housenumber":"4335",
    "addr:postcode":"e1n 4l9",
    "addr:street":"Water St",
    "iso:country":"CA",
    "sg:address":"4335 Water St",
    "sg:city":"Miramichi",
    "sg:classifiers":[
        {
            "category":"Building & Trades",
            "subcategory":"Plumbing",
            "type":"Services"
        }
    ],
    "sg:phone":"+1 506 773 4369",
    "sg:postcode":"E1N 4L9",
    "sg:province":"NB",
    "sg:tags":[
        "conditioning",
        "air",
        "system",
        "contractor"
    ],
    "wof:name":"2-Cool Refrigeration",
    "wof:placetype":"venue"
},
  "geometry": {"coordinates":[-65.385696,47.072247],"type":"Point"}
}