{
  "type": "Feature",
  "properties": {
    "addr:full":"Surrey BC V3W 8J9",
    "addr:postcode":"v3w 8j9",
    "iso:country":"CA",
    "sg:city":"Surrey",
    "sg:classifiers":[
        {
            "category":"Manufacturing",
            "subcategory":"Toys & Sporting Goods",
            "type":"Manufacturing & Wholesale Goods"
        }
    ],
    "sg:phone":"+1 604 590 9211",
    "sg:postcode":"V3W 8J9",
    "sg:province":"BC",
    "sg:tags":[
        "athletic"
    ],
    "wof:name":"Big Kahuna Sport CO",
    "wof:placetype":"venue"
},
  "geometry": {"coordinates":[-122.86196099999999,49.154053],"type":"Point"}
}