{
  "type": "Feature",
  "properties": {
    "addr:full":"7520 Macleod Trail SE Calgary AB T2H 0L9",
    "addr:housenumber":"7520",
    "addr:postcode":"t2h 0l9",
    "addr:street":"Macleod Trail Se",
    "iso:country":"CA",
    "sg:address":"7520 Macleod Trail SE",
    "sg:city":"Calgary",
    "sg:classifiers":[
        {
            "category":"Recreation",
            "type":"Entertainment"
        }
    ],
    "sg:phone":"+1 403 252 0146",
    "sg:postcode":"T2H 0L9",
    "sg:province":"AB",
    "sg:tags":[
        "skating",
        "center",
        "rink"
    ],
    "wof:name":"Lloyd's Recreation Ltd",
    "wof:placetype":"venue"
},
  "geometry": {"coordinates":[-114.07094600000001,50.985706],"type":"Point"}
}