{
  "type": "Feature",
  "properties": {
    "addr:full":"Edmonton AB T5N 3Z1",
    "addr:postcode":"t5n 3z1",
    "iso:country":"CA",
    "sg:city":"Edmonton",
    "sg:classifiers":[
        {
            "category":"Professional",
            "subcategory":"Accounting & Tax Preparation",
            "type":"Services"
        }
    ],
    "sg:phone":"+1 780 428 6890",
    "sg:postcode":"T5N 3Z1",
    "sg:province":"AB",
    "sg:tags":[
        "accountant"
    ],
    "wof:name":"Mah, Donald F M CA",
    "wof:placetype":"venue"
},
  "geometry": {"coordinates":[-113.532669,53.54948],"type":"Point"}
}