{
  "type": "Feature",
  "properties": {
    "addr:full":"Windsor ON N8W 5K8",
    "addr:postcode":"n8w 5k8",
    "iso:country":"CA",
    "sg:city":"Windsor",
    "sg:classifiers":[
        {
            "category":"Professional",
            "subcategory":"Research",
            "type":"Services"
        }
    ],
    "sg:phone":"+1 519 948 5000",
    "sg:postcode":"N8W 5K8",
    "sg:province":"ON",
    "sg:tags":[
        "environmental",
        "ecological",
        "engineer"
    ],
    "wof:name":"Dillon Consulting Ltd",
    "wof:placetype":"venue"
},
  "geometry": {"coordinates":[-82.969902,42.282017],"type":"Point"}
}