{
  "type": "Feature",
  "properties": {
    "addr:full":"10 Villeneuve Crt Sturgeon Falls ON P2B 3G8",
    "addr:housenumber":"10",
    "addr:postcode":"p2b 3g8",
    "addr:street":"Villeneuve Crt",
    "iso:country":"CA",
    "sg:address":"10 Villeneuve Crt",
    "sg:city":"Sturgeon Falls",
    "sg:classifiers":[
        {
            "category":"Shopping",
            "type":"Retail Goods"
        }
    ],
    "sg:phone":"+1 705 753 4348",
    "sg:postcode":"P2B 3G8",
    "sg:province":"ON",
    "sg:tags":[
        "cosmetic",
        "perfume"
    ],
    "wof:name":"Aloette Cosmetics",
    "wof:placetype":"venue"
},
  "geometry": {"coordinates":[-79.943657,46.362885],"type":"Point"}
}