{
  "type": "Feature",
  "properties": {
    "addr:full":"19 Winnett Ave York ON M6C 3L2",
    "addr:housenumber":"19",
    "addr:postcode":"m6c 3l2",
    "addr:street":"Winnett Ave",
    "iso:country":"CA",
    "sg:address":"19 Winnett Ave",
    "sg:city":"York",
    "sg:classifiers":[
        {
            "category":"Building & Trades",
            "subcategory":"Plumbing",
            "type":"Services"
        }
    ],
    "sg:phone":"+1 416 656 4765",
    "sg:postcode":"M6C 3L2",
    "sg:province":"ON",
    "sg:tags":[
        "contractor"
    ],
    "wof:name":"Atlantis Plumbing & Heating",
    "wof:placetype":"venue"
},
  "geometry": {"coordinates":[-79.430908,43.6842],"type":"Point"}
}