{
  "type": "Feature",
  "properties": {
    "addr:full":"Laval QC H7V 2V3",
    "addr:postcode":"h7v 2v3",
    "iso:country":"CA",
    "sg:city":"Laval",
    "sg:classifiers":[
        {
            "category":"Personal",
            "subcategory":"Beauty Salon",
            "type":"Services"
        }
    ],
    "sg:phone":"+1 450 686 4776",
    "sg:postcode":"H7V 2V3",
    "sg:province":"QC",
    "wof:name":"Salon Ligue",
    "wof:placetype":"venue"
},
  "geometry": {"coordinates":[-73.74755096440001,45.5398292542],"type":"Point"}
}