{
  "type": "Feature",
  "properties": {
    "addr:full":"1341 Upper James St Hamilton ON L9C 3B3",
    "addr:housenumber":"1341",
    "addr:postcode":"l9c 3b3",
    "addr:street":"Upper James St",
    "iso:country":"CA",
    "sg:address":"1341 Upper James St",
    "sg:city":"Hamilton",
    "sg:classifiers":[
        {
            "category":"Autos & Motor Vehicles",
            "subcategory":"Fuel & Gas Station",
            "type":"Retail Goods"
        }
    ],
    "sg:phone":"+1 905 318 9832",
    "sg:postcode":"L9C 3B3",
    "sg:province":"ON",
    "sg:tags":[
        "oil"
    ],
    "wof:name":"Rainbow Gas & Convenience Str",
    "wof:placetype":"venue"
},
  "geometry": {"coordinates":[-79.88888549799999,43.2113037109],"type":"Point"}
}