{
  "type": "Feature",
  "properties": {
    "addr:full":"2241 Speers Ave Saskatoon SK S7L 5X6",
    "addr:housenumber":"2241",
    "addr:postcode":"s7l 5x6",
    "addr:street":"Speers Ave",
    "iso:country":"CA",
    "sg:address":"2241 Speers Ave",
    "sg:city":"Saskatoon",
    "sg:classifiers":[
        {
            "category":"Food & Beverages",
            "subcategory":"Specialty",
            "type":"Retail Goods"
        }
    ],
    "sg:phone":"+1 306 934 6477",
    "sg:postcode":"S7L 5X6",
    "sg:province":"SK",
    "sg:tags":[
        "salt"
    ],
    "wof:name":"Nsc Minerals Inc",
    "wof:placetype":"venue"
},
  "geometry": {"coordinates":[-106.676437378,52.1603355408],"type":"Point"}
}