{
  "type": "Feature",
  "properties": {
    "addr:full":"6110 144 Ave NW Edmonton AB T5A 1K5",
    "addr:housenumber":"6110",
    "addr:postcode":"t5a 1k5",
    "addr:street":"144 Ave Nw",
    "iso:country":"CA",
    "sg:address":"6110 144 Ave NW",
    "sg:city":"Edmonton",
    "sg:classifiers":[
        {
            "category":"Education",
            "subcategory":"School",
            "type":"Public Place"
        }
    ],
    "sg:phone":"+1 780 475 3730",
    "sg:postcode":"T5A 1K5",
    "sg:province":"AB",
    "wof:name":"J J Bowlen Catholic Jr High",
    "wof:placetype":"venue"
},
  "geometry": {"coordinates":[-113.436165,53.60511],"type":"Point"}
}