{
  "type": "Feature",
  "properties": {
    "addr:full":"5181 Boul Decarie Montreal QC H3W 3C2",
    "addr:housenumber":"5181",
    "addr:postcode":"h3w 3c2",
    "addr:street":"Boul Decarie",
    "iso:country":"CA",
    "sg:address":"5181 Boul Decarie",
    "sg:city":"Montreal",
    "sg:classifiers":[
        {
            "category":"Shopping",
            "subcategory":"Books",
            "type":"Retail Goods"
        }
    ],
    "sg:phone":"+1 514 484 2008",
    "sg:postcode":"H3W 3C2",
    "sg:province":"QC",
    "sg:tags":[
        "dealer"
    ],
    "wof:name":"Gazeta Inc",
    "wof:placetype":"venue"
},
  "geometry": {"coordinates":[-73.63031768800001,45.4845542908],"type":"Point"}
}