{
  "type": "Feature",
  "properties": {
    "addr:full":"315 Ross St NE Salmon Arm BC V1E 4N8",
    "addr:housenumber":"315",
    "addr:postcode":"v1e 4n8",
    "addr:street":"Ross St Ne",
    "iso:country":"CA",
    "sg:address":"315 Ross St NE",
    "sg:city":"Salmon Arm",
    "sg:classifiers":[
        {
            "category":"Health Services",
            "subcategory":"Optometrist",
            "type":"Services"
        }
    ],
    "sg:phone":"+1 250 832 6206",
    "sg:postcode":"V1E 4N8",
    "sg:province":"BC",
    "wof:name":"Shuswap Optometric Ctr",
    "wof:placetype":"venue"
},
  "geometry": {"coordinates":[-119.281425476,50.701877594],"type":"Point"}
}