{
  "type": "Feature",
  "properties": {
    "iso:country":"CA",
    "sg:city":"Newmarket",
    "sg:classifiers":[
        {
            "category":"Retail",
            "subcategory":"Veterinary Services",
            "type":"Services"
        }
    ],
    "sg:phone":"+1 905 895 2512",
    "sg:postcode":"L3Y 7M9",
    "sg:province":"ON",
    "sg:tags":[
        "veterinarian"
    ],
    "wof:name":"Newmarket Animal Hospital",
    "wof:placetype":"venue"
},
  "geometry": {"coordinates":[-79.485306,44.05312],"type":"Point"}
}