{
  "type": "Feature",
  "properties": {
    "iso:country":"CA",
    "sg:city":"North York",
    "sg:classifiers":[
        {
            "category":"Education",
            "subcategory":"Special Training",
            "type":"Public Place"
        }
    ],
    "sg:phone":"+1 416 665 2310",
    "sg:postcode":"M3J 2N8",
    "sg:province":"ON",
    "sg:tags":[
        "academic",
        "school",
        "tutoring"
    ],
    "wof:name":"Math Lab Tutorials",
    "wof:placetype":"venue"
},
  "geometry": {"coordinates":[-79.49364471440001,43.7750930786],"type":"Point"}
}