{
  "type": "Feature",
  "properties": {
    "addr:full":"Gibsons BC V0N 1V0",
    "addr:postcode":"v0n 1v0",
    "iso:country":"CA",
    "sg:city":"Gibsons",
    "sg:classifiers":[
        {
            "category":"Shopping",
            "subcategory":"Books",
            "type":"Retail Goods"
        }
    ],
    "sg:phone":"+1 604 886 7744",
    "sg:postcode":"V0N 1V0",
    "sg:province":"BC",
    "sg:tags":[
        "dealer"
    ],
    "wof:name":"Coast Books",
    "wof:placetype":"venue"
},
  "geometry": {"coordinates":[-123.50531768800001,49.4022064209],"type":"Point"}
}