{
  "type": "Feature",
  "properties": {
    "addr:full":"Sainte-Cecile-DE-Masham QC J0X 2W0",
    "addr:postcode":"j0x 2w0",
    "iso:country":"CA",
    "sg:city":"Sainte-Cecile-DE-Masham",
    "sg:classifiers":[
        {
            "category":"Retail",
            "subcategory":"Auto Repair",
            "type":"Services"
        }
    ],
    "sg:phone":"+1 819 456 3027",
    "sg:postcode":"J0X 2W0",
    "sg:province":"QC",
    "sg:tags":[
        "repairing",
        "automobile"
    ],
    "wof:name":"Garage Beaudoin & Renaud",
    "wof:placetype":"venue"
},
  "geometry": {"coordinates":[-76.028397,45.643173],"type":"Point"}
}