{
  "type": "Feature",
  "properties": {
    "addr:full":"1151 Richmond St London ON N6A 3K7",
    "addr:housenumber":"1151",
    "addr:postcode":"n6a 3k7",
    "addr:street":"Richmond St",
    "iso:country":"CA",
    "sg:address":"1151 Richmond St",
    "sg:city":"London",
    "sg:classifiers":[
        {
            "category":"Professional",
            "subcategory":"Management & Consulting",
            "type":"Services"
        }
    ],
    "sg:phone":"+1 519 661 3717",
    "sg:postcode":"N6A 3K7",
    "sg:province":"ON",
    "sg:tags":[
        "consultant",
        "business"
    ],
    "wof:name":"Ivey Business Consulting Group",
    "wof:placetype":"venue"
},
  "geometry": {"coordinates":[-81.261757,43.009296],"type":"Point"}
}