{
  "type": "Feature",
  "properties": {
    "addr:full":"Sainte-Ursule QC J0K 3M0",
    "addr:postcode":"j0k 3m0",
    "iso:country":"CA",
    "sg:city":"Sainte-Ursule",
    "sg:classifiers":[
        {
            "category":"Government",
            "subcategory":"Office",
            "type":"Public Place"
        }
    ],
    "sg:phone":"+1 819 228 4345",
    "sg:postcode":"J0K 3M0",
    "sg:province":"QC",
    "sg:tags":[
        "village"
    ],
    "wof:name":"Ste-Ursule Ofc",
    "wof:placetype":"venue"
},
  "geometry": {"coordinates":[-73.0296325684,46.289806366],"type":"Point"}
}