{
  "type": "Feature",
  "properties": {
    "iso:country":"CA",
    "sg:address":"94 Saunders Rd",
    "sg:city":"Barrie",
    "sg:classifiers":[
        {
            "category":"Building & Trades",
            "subcategory":"Construction",
            "type":"Services"
        }
    ],
    "sg:phone":"+1 705 722 4421",
    "sg:postcode":"L4N 9A8",
    "sg:province":"ON",
    "sg:tags":[
        "maker",
        "cabinet"
    ],
    "wof:name":"Norcab Kitchen & Millwork CO",
    "wof:placetype":"venue"
},
  "geometry": {"coordinates":[-79.680923,44.329762],"type":"Point"}
}