{
  "type": "Feature",
  "properties": {
    "addr:full":"605 Main St Doaktown NB E9C 1Y3",
    "addr:housenumber":"605",
    "addr:postcode":"e9c 1y3",
    "addr:street":"Main St",
    "iso:country":"CA",
    "sg:address":"605 Main St",
    "sg:city":"Doaktown",
    "sg:classifiers":[
        {
            "category":"Retail",
            "subcategory":"Auto Repair",
            "type":"Services"
        }
    ],
    "sg:phone":"+1 506 365 4667",
    "sg:postcode":"E9C 1Y3",
    "sg:province":"NB",
    "sg:tags":[
        "repairing",
        "automobile"
    ],
    "wof:name":"Stewart Service Station",
    "wof:placetype":"venue"
},
  "geometry": {"coordinates":[-66.1276092529,46.5560951233],"type":"Point"}
}