{
  "type": "Feature",
  "properties": {
    "addr:full":"12950 Silvercreek Dr Georgetown ON L7G 4S4",
    "addr:housenumber":"12950",
    "addr:postcode":"l7g 4s4",
    "addr:street":"Silvercreek Dr",
    "iso:country":"CA",
    "sg:address":"12950 Silvercreek Dr",
    "sg:city":"Georgetown",
    "sg:classifiers":[
        {
            "category":"Shopping",
            "type":"Retail Goods"
        }
    ],
    "sg:phone":"+1 905 702 1042",
    "sg:postcode":"L7G 4S4",
    "sg:province":"ON",
    "sg:tags":[
        "candle"
    ],
    "wof:name":"Island Scentations",
    "wof:placetype":"venue"
},
  "geometry": {"coordinates":[-79.98477200000001,43.674545],"type":"Point"}
}