{
  "type": "Feature",
  "properties": {
    "addr:full":"3034 Av Du Pont N Alma QC G8E 1R9",
    "addr:housenumber":"3034",
    "addr:postcode":"g8e 1r9",
    "addr:street":"Av Du Pont N",
    "iso:country":"CA",
    "sg:address":"3034 Av Du Pont N",
    "sg:city":"Alma",
    "sg:classifiers":[
        {
            "category":"Home & Garden",
            "subcategory":"Building Materials",
            "type":"Retail Goods"
        }
    ],
    "sg:phone":"+1 418 480 3553",
    "sg:postcode":"G8E 1R9",
    "sg:province":"QC",
    "sg:tags":[
        "door"
    ],
    "wof:name":"Portes DE Garages Du Lac",
    "wof:placetype":"venue"
},
  "geometry": {"coordinates":[-71.62112399999999,48.603546],"type":"Point"}
}