{
  "type": "Feature",
  "properties": {
    "addr:full":"2192 Floradale Rd Floradale ON N0B 1V0",
    "addr:housenumber":"2192",
    "addr:postcode":"n0b 1v0",
    "addr:street":"Floradale Rd",
    "iso:country":"CA",
    "sg:address":"2192 Floradale Rd",
    "sg:city":"Floradale",
    "sg:classifiers":[
        {
            "category":"Food & Beverages",
            "subcategory":"Bakery",
            "type":"Retail Goods"
        }
    ],
    "sg:phone":"+1 519 669 1381",
    "sg:postcode":"N0B 1V0",
    "sg:province":"ON",
    "sg:tags":[
        "baker"
    ],
    "wof:name":"Hillcrest Home Baking",
    "wof:placetype":"venue"
},
  "geometry": {"coordinates":[-80.58091,43.631241],"type":"Point"}
}