{
  "type": "Feature",
  "properties": {
    "addr:full":"855 A Trillium Dr Kitchener ON N2R 1J9",
    "addr:housenumber":"855",
    "addr:postcode":"n2r 1j9",
    "addr:street":"A Trillium Dr",
    "iso:country":"CA",
    "sg:address":"855 A Trillium Dr",
    "sg:city":"Kitchener",
    "sg:classifiers":[
        {
            "category":"Manufacturing",
            "subcategory":"Tools & Machinery",
            "type":"Manufacturing & Wholesale Goods"
        }
    ],
    "sg:phone":"+1 519 893 1433",
    "sg:postcode":"N2R 1J9",
    "sg:province":"ON",
    "sg:tags":[
        "industry",
        "aerospace"
    ],
    "wof:name":"Dals Logistics & Defense Div",
    "wof:placetype":"venue"
},
  "geometry": {"coordinates":[-80.484664917,43.3997573853],"type":"Point"}
}