{
  "type": "Feature",
  "properties": {
    "addr:full":"Westbank BC V4T 1V3",
    "addr:postcode":"v4t 1v3",
    "iso:country":"CA",
    "sg:city":"Westbank",
    "sg:classifiers":[
        {
            "category":"Building & Trades",
            "subcategory":"Construction",
            "type":"Services"
        }
    ],
    "sg:phone":"+1 250 768 7597",
    "sg:postcode":"V4T 1V3",
    "sg:province":"BC",
    "sg:tags":[
        "general",
        "contractor"
    ],
    "wof:name":"Hohn Construction",
    "wof:placetype":"venue"
},
  "geometry": {"coordinates":[-119.604530334,49.8462715149],"type":"Point"}
}