{
  "type": "Feature",
  "properties": {
    "addr:full":"6853 Highway 17 E Coniston ON P0M 1M0",
    "addr:housenumber":"6853",
    "addr:postcode":"p0m 1m0",
    "addr:street":"Highway 17 E",
    "iso:country":"CA",
    "sg:address":"6853 Highway 17 E",
    "sg:city":"Coniston",
    "sg:classifiers":[
        {
            "category":"Autos & Motor Vehicles",
            "subcategory":"Automobile Sales",
            "type":"Retail Goods"
        }
    ],
    "sg:phone":"+1 705 694 6617",
    "sg:postcode":"P0M 1M0",
    "sg:province":"ON",
    "sg:tags":[
        "car",
        "dealer"
    ],
    "wof:name":"High Tech Auto Sales",
    "wof:placetype":"venue"
},
  "geometry": {"coordinates":[-80.848511,46.486622],"type":"Point"}
}