{
  "type": "Feature",
  "properties": {
    "addr:full":"1 Jaffray St New Liskeard ON P0J 1P0",
    "addr:housenumber":"1",
    "addr:postcode":"p0j 1p0",
    "addr:street":"Jaffray St",
    "iso:country":"CA",
    "sg:address":"1 Jaffray St",
    "sg:city":"New Liskeard",
    "sg:classifiers":[
        {
            "category":"Freight",
            "type":"Transportation"
        }
    ],
    "sg:phone":"+1 705 647 4061",
    "sg:postcode":"P0J 1P0",
    "sg:province":"ON",
    "sg:tags":[
        "courier"
    ],
    "wof:name":"Ontario Northland",
    "wof:placetype":"venue"
},
  "geometry": {"coordinates":[-79.685211,47.514458],"type":"Point"}
}