{
  "type": "Feature",
  "properties": {
    "iso:country":"CA",
    "sg:address":"146 Pond Mills Rd",
    "sg:city":"London",
    "sg:classifiers":[
        {
            "category":"Building & Trades",
            "subcategory":"Construction",
            "type":"Services"
        }
    ],
    "sg:phone":"+1 519 685 3739",
    "sg:postcode":"N5Z 3X2",
    "sg:province":"ON",
    "sg:tags":[
        "home",
        "general",
        "improvement",
        "contractor"
    ],
    "wof:name":"Wasa Construction",
    "wof:placetype":"venue"
},
  "geometry": {"coordinates":[-81.202507,42.969387],"type":"Point"}
}