{
  "type": "Feature",
  "properties": {
    "addr:full":"815 Grafton Bowen Island BC V0N 1G0",
    "addr:housenumber":"815",
    "addr:postcode":"v0n 1g0",
    "addr:street":"Grafton",
    "iso:country":"CA",
    "sg:address":"815 Grafton",
    "sg:city":"Bowen Island",
    "sg:classifiers":[
        {
            "category":"Sports & Exercise",
            "subcategory":"Gym",
            "type":"Entertainment"
        }
    ],
    "sg:phone":"+1 604 947 0982",
    "sg:postcode":"V0N 1G0",
    "sg:province":"BC",
    "sg:tags":[
        "club",
        "health",
        "studio",
        "gymnasium"
    ],
    "wof:name":"Bowen Island Fitness Club",
    "wof:placetype":"venue"
},
  "geometry": {"coordinates":[-123.3592453,49.3733634949],"type":"Point"}
}