{
  "type": "Feature",
  "properties": {
    "addr:full":"371 Amirault St Dieppe NB E1A 1G1",
    "addr:housenumber":"371",
    "addr:postcode":"e1a 1g1",
    "addr:street":"Amirault St",
    "iso:country":"CA",
    "sg:address":"371 Amirault St",
    "sg:city":"Dieppe",
    "sg:classifiers":[
        {
            "category":"Health Services",
            "subcategory":"Nursing And Care Facility",
            "type":"Services"
        }
    ],
    "sg:phone":"+1 506 858 1318",
    "sg:postcode":"E1A 1G1",
    "sg:province":"NB",
    "sg:tags":[
        "home",
        "rest"
    ],
    "wof:name":"Residence Du Marais",
    "wof:placetype":"venue"
},
  "geometry": {"coordinates":[-64.732178,46.082809],"type":"Point"}
}