{
  "type": "Feature",
  "properties": {
    "iso:country":"CA",
    "sg:city":"Montreal",
    "sg:classifiers":[
        {
            "category":"Social Services",
            "subcategory":"Job Training",
            "type":"Services"
        }
    ],
    "sg:phone":"+1 514 286 9595",
    "sg:postcode":"H3A 1B9",
    "sg:province":"QC",
    "sg:tags":[
        "consultant",
        "instructional",
        "employment"
    ],
    "wof:name":"Club DE Recherche D'Emploi",
    "wof:placetype":"venue"
},
  "geometry": {"coordinates":[-73.5665893555,45.5183753967],"type":"Point"}
}