{
  "type": "Feature",
  "properties": {
    "addr:full":"6311 Wagner Rd NW Edmonton AB T6E 4N4",
    "addr:housenumber":"6311",
    "addr:postcode":"t6e 4n4",
    "addr:street":"Wagner Rd Nw",
    "iso:country":"CA",
    "sg:address":"6311 Wagner Rd NW",
    "sg:city":"Edmonton",
    "sg:classifiers":[
        {
            "category":"Manufacturing",
            "subcategory":"Food",
            "type":"Manufacturing & Wholesale Goods"
        }
    ],
    "sg:phone":"+1 780 465 8085",
    "sg:postcode":"T6E 4N4",
    "sg:province":"AB",
    "sg:tags":[
        "confectionery",
        "candy"
    ],
    "wof:name":"Riddle's Sweet Impressions",
    "wof:placetype":"venue"
},
  "geometry": {"coordinates":[-113.448356628,53.5002708435],"type":"Point"}
}