{
  "type": "Feature",
  "properties": {
    "iso:country":"CA",
    "sg:address":"70 King St W",
    "sg:city":"Stoney Creek",
    "sg:classifiers":[
        {
            "category":"Personal",
            "subcategory":"Beauty Salon",
            "type":"Services"
        }
    ],
    "sg:phone":"+1 905 664 5622",
    "sg:postcode":"L8G 1H8",
    "sg:province":"ON",
    "wof:name":"Rosa's Day Spa",
    "wof:placetype":"venue"
},
  "geometry": {"coordinates":[-79.764297,43.218399],"type":"Point"}
}