{
  "type": "Feature",
  "properties": {
    "addr:full":"9519 Boul Gouin O Pierrefonds QC H8Y 1T7",
    "addr:housenumber":"9519",
    "addr:postcode":"h8y 1t7",
    "addr:street":"Boul Gouin O",
    "iso:country":"CA",
    "sg:address":"9519 Boul Gouin O",
    "sg:city":"Pierrefonds",
    "sg:classifiers":[
        {
            "category":"Building & Trades",
            "subcategory":"Landscaping Services",
            "type":"Services"
        }
    ],
    "sg:phone":"+1 514 684 0297",
    "sg:postcode":"H8Y 1T7",
    "sg:province":"QC",
    "sg:tags":[
        "center",
        "garden",
        "landscape",
        "contractor"
    ],
    "wof:name":"Pepiniere Pauls",
    "wof:placetype":"venue"
},
  "geometry": {"coordinates":[-73.777023,45.505219],"type":"Point"}
}