{
  "type": "Feature",
  "properties": {
    "addr:full":"12 Rue Saint-Donat Sainte-Agathe-Des-Monts QC J8C 1P5",
    "addr:housenumber":"12",
    "addr:postcode":"j8c 1p5",
    "addr:street":"Rue Saint-Donat",
    "iso:country":"CA",
    "sg:address":"12 Rue Saint-Donat",
    "sg:city":"Sainte-Agathe-Des-Monts",
    "sg:classifiers":[
        {
            "category":"Social Services",
            "type":"Services"
        }
    ],
    "sg:phone":"+1 819 324 2261",
    "sg:postcode":"J8C 1P5",
    "sg:province":"QC",
    "sg:tags":[
        "organization",
        "welfare"
    ],
    "wof:name":"Tangage Des Laurentides",
    "wof:placetype":"venue"
},
  "geometry": {"coordinates":[-74.287537,46.048771],"type":"Point"}
}