{
  "type": "Feature",
  "properties": {
    "addr:full":"212 1st St Morden MB R6M 1P4",
    "addr:housenumber":"212",
    "addr:postcode":"r6m 1p4",
    "addr:street":"1St St",
    "iso:country":"CA",
    "sg:address":"212 1st St",
    "sg:city":"Morden",
    "sg:classifiers":[
        {
            "category":"Travel",
            "subcategory":"Hotels & Motels",
            "type":"Entertainment"
        }
    ],
    "sg:phone":"+1 204 822 4494",
    "sg:postcode":"R6M 1P4",
    "sg:province":"MB",
    "wof:name":"Star Motel & Restaurant",
    "wof:placetype":"venue"
},
  "geometry": {"coordinates":[-98.09178900000001,49.179585],"type":"Point"}
}