{
  "type": "Feature",
  "properties": {
    "addr:full":"85 Ch Siegas No 1 Siegas NB E7E 1T6",
    "addr:housenumber":"85",
    "addr:postcode":"e7e 1t6",
    "addr:street":"Ch Siegas No 1 Siegas",
    "iso:country":"CA",
    "sg:address":"85 Ch Siegas No 1",
    "sg:city":"Siegas",
    "sg:classifiers":[
        {
            "category":"Food & Beverages",
            "subcategory":"Groceries & Convenience Stores",
            "type":"Retail Goods"
        }
    ],
    "sg:phone":"+1 506 445 2471",
    "sg:postcode":"E7E 1T6",
    "sg:province":"NB",
    "sg:tags":[
        "grocer"
    ],
    "wof:name":"Larry's Grocery",
    "wof:placetype":"venue"
},
  "geometry": {"coordinates":[-67.9938201904,47.2220802307],"type":"Point"}
}