{
  "type": "Feature",
  "properties": {
    "iso:country":"CA",
    "sg:address":"27 Woodstock St S",
    "sg:city":"Tavistock",
    "sg:classifiers":[
        {
            "category":"Insurance",
            "subcategory":"Insurance Agent",
            "type":"Services"
        }
    ],
    "sg:phone":"+1 519 655 2277",
    "sg:postcode":"N0B 2R0",
    "sg:province":"ON",
    "wof:name":"Mc Farlan Rowlands Insurance",
    "wof:placetype":"venue"
},
  "geometry": {"coordinates":[-80.8367156982,43.3202209473],"type":"Point"}
}