{
  "type": "Feature",
  "properties": {
    "addr:full":"925 Boul Decarie Saint-Laurent QC H4L 3M3",
    "addr:housenumber":"925",
    "addr:postcode":"h4l 3m3",
    "addr:street":"Boul Decarie",
    "iso:country":"CA",
    "sg:address":"925 Boul Decarie",
    "sg:city":"Saint-Laurent",
    "sg:classifiers":[
        {
            "category":"Restaurant",
            "type":"Food & Drink"
        }
    ],
    "sg:phone":"+1 514 747 7251",
    "sg:postcode":"H4L 3M3",
    "sg:province":"QC",
    "wof:name":"Diogenis Restaurant",
    "wof:placetype":"venue"
},
  "geometry": {"coordinates":[-73.6808853149,45.5133132935],"type":"Point"}
}