{
  "type": "Feature",
  "properties": {
    "addr:full":"9 James St S Forest ON N0N 1J0",
    "addr:housenumber":"9",
    "addr:postcode":"n0n 1j0",
    "addr:street":"James St S",
    "iso:country":"CA",
    "sg:address":"9 James St S",
    "sg:city":"Forest",
    "sg:classifiers":[
        {
            "category":"Retail",
            "subcategory":"Funeral Services",
            "type":"Services"
        }
    ],
    "sg:phone":"+1 519 786 2401",
    "sg:postcode":"N0N 1J0",
    "sg:province":"ON",
    "sg:tags":[
        "director"
    ],
    "wof:name":"Ronn E Dodge Funeral Directors",
    "wof:placetype":"venue"
},
  "geometry": {"coordinates":[-82.001831,43.095284],"type":"Point"}
}