{
  "type": "Feature",
  "properties": {
    "iso:country":"CA",
    "sg:address":"678 Cooper St",
    "sg:city":"Campbell River",
    "sg:classifiers":[
        {
            "category":"Building & Trades",
            "subcategory":"Electrical",
            "type":"Services"
        }
    ],
    "sg:phone":"+1 250 923 4494",
    "sg:postcode":"V9H 1S8",
    "sg:province":"BC",
    "sg:tags":[
        "electric",
        "contractor"
    ],
    "wof:name":"Regal Electric Ltd",
    "wof:placetype":"venue"
},
  "geometry": {"coordinates":[-125.228981,49.965393],"type":"Point"}
}