{
  "type": "Feature",
  "properties": {
    "addr:full":"2466 Eglinton Ave E #9 Scarborough ON M1K 5J8",
    "addr:housenumber":"2466",
    "addr:postcode":"m1k 5j8",
    "addr:street":"Eglinton Ave E # 9",
    "iso:country":"CA",
    "sg:address":"2466 Eglinton Ave E #9",
    "sg:city":"Scarborough",
    "sg:classifiers":[
        {
            "category":"Retail",
            "subcategory":"Laundry & Dry Cleaning",
            "type":"Services"
        }
    ],
    "sg:phone":"+1 416 266 4562",
    "sg:postcode":"M1K 5J8",
    "sg:province":"ON",
    "sg:tags":[
        "cleaners"
    ],
    "wof:name":"Agape Cleaners",
    "wof:placetype":"venue"
},
  "geometry": {"coordinates":[-79.2609634399,43.7343254089],"type":"Point"}
}