{
  "type": "Feature",
  "properties": {
    "addr:full":"275 Rue Saint-Georges Windsor QC J1S 1K3",
    "addr:housenumber":"275",
    "addr:postcode":"j1s 1k3",
    "addr:street":"Rue Saint-Georges",
    "iso:country":"CA",
    "sg:address":"275 Rue Saint-Georges",
    "sg:city":"Windsor",
    "sg:classifiers":[
        {
            "category":"Restaurant",
            "type":"Food & Drink"
        }
    ],
    "sg:phone":"+1 819 845 3399",
    "sg:postcode":"J1S 1K3",
    "sg:province":"QC",
    "wof:name":"Pizzeria Le Tournesol",
    "wof:placetype":"venue"
},
  "geometry": {"coordinates":[-71.995338,45.575954],"type":"Point"}
}