{
  "type": "Feature",
  "properties": {
    "addr:full":"55 Northland Rd Waterloo ON N2V 1Y8",
    "addr:housenumber":"55",
    "addr:postcode":"n2v 1y8",
    "addr:street":"Northland Rd",
    "iso:country":"CA",
    "sg:address":"55 Northland Rd",
    "sg:city":"Waterloo",
    "sg:classifiers":[
        {
            "category":"Manufacturing",
            "subcategory":"Metals",
            "type":"Manufacturing & Wholesale Goods"
        }
    ],
    "sg:phone":"+1 519 884 8650",
    "sg:postcode":"N2V 1Y8",
    "sg:province":"ON",
    "sg:tags":[
        "stamping"
    ],
    "wof:name":"J Gerth Custom Toolage Inc",
    "wof:placetype":"venue"
},
  "geometry": {"coordinates":[-80.53318,43.507099],"type":"Point"}
}