{
  "type": "Feature",
  "properties": {
    "addr:full":"Calgary AB T2Y 2Z7",
    "addr:postcode":"t2y 2z7",
    "iso:country":"CA",
    "sg:city":"Calgary",
    "sg:classifiers":[
        {
            "category":"Shopping",
            "subcategory":"Pharmacy",
            "type":"Retail Goods"
        }
    ],
    "sg:phone":"+1 403 299 4439",
    "sg:postcode":"T2Y 2Z7",
    "sg:province":"AB",
    "wof:name":"Calgary CO-OP Pharmacy",
    "wof:placetype":"venue"
},
  "geometry": {"coordinates":[-114.065102,50.903107],"type":"Point"}
}