{
  "type": "Feature",
  "properties": {
    "addr:full":"168 Major St Toronto ON M5S 2L3",
    "addr:housenumber":"168",
    "addr:postcode":"m5s 2l3",
    "addr:street":"Major St",
    "iso:country":"CA",
    "sg:address":"168 Major St",
    "sg:city":"Toronto",
    "sg:classifiers":[
        {
            "category":"Shopping",
            "subcategory":"Florist",
            "type":"Retail Goods"
        }
    ],
    "sg:phone":"+1 416 928 1478",
    "sg:postcode":"M5S 2L3",
    "sg:province":"ON",
    "sg:tags":[
        "store",
        "variety"
    ],
    "wof:name":"Harbord Variety & Gift",
    "wof:placetype":"venue"
},
  "geometry": {"coordinates":[-79.40506000000001,43.662666],"type":"Point"}
}