{
  "type": "Feature",
  "properties": {
    "iso:country":"CA",
    "sg:address":"4860 Rue Fisher",
    "sg:city":"Saint-Laurent",
    "sg:classifiers":[
        {
            "category":"Wholesale",
            "subcategory":"Stationery",
            "type":"Manufacturing & Wholesale Goods"
        }
    ],
    "sg:phone":"+1 514 340 1888",
    "sg:postcode":"H4T 1J5",
    "sg:province":"QC",
    "sg:tags":[
        "die",
        "cutting",
        "cardboard"
    ],
    "wof:name":"Graphic Finishers Inc",
    "wof:placetype":"venue"
},
  "geometry": {"coordinates":[-73.6979751587,45.4698867798],"type":"Point"}
}