{
  "type": "Feature",
  "properties": {
    "addr:full":"Saint-Isidore NB E8M 1S3",
    "addr:postcode":"e8m 1s3",
    "iso:country":"CA",
    "sg:city":"Saint-Isidore",
    "sg:classifiers":[
        {
            "category":"Food & Beverages",
            "subcategory":"Groceries & Convenience Stores",
            "type":"Retail Goods"
        }
    ],
    "sg:phone":"+1 506 358 2276",
    "sg:postcode":"E8M 1S3",
    "sg:province":"NB",
    "sg:tags":[
        "grocer"
    ],
    "wof:name":"Epicerie St Isidore Ltee",
    "wof:placetype":"venue"
},
  "geometry": {"coordinates":[-65.06047821040001,47.5519752502],"type":"Point"}
}