{
  "type": "Feature",
  "properties": {
    "iso:country":"CA",
    "sg:address":"2079 Rue Thierry",
    "sg:city":"Lasalle",
    "sg:classifiers":[
        {
            "category":"Food & Beverages",
            "subcategory":"Groceries & Convenience Stores",
            "type":"Retail Goods"
        }
    ],
    "sg:phone":"+1 514 365 5378",
    "sg:postcode":"H8N 2J2",
    "sg:province":"QC",
    "wof:name":"Varietes San Remo Handy Store",
    "wof:placetype":"venue"
},
  "geometry": {"coordinates":[-73.62637329099999,45.4370956421],"type":"Point"}
}