{
  "type": "Feature",
  "properties": {
    "iso:country":"CA",
    "sg:city":"Montreal",
    "sg:classifiers":[
        {
            "category":"Food & Beverages",
            "subcategory":"Groceries & Convenience Stores",
            "type":"Retail Goods"
        }
    ],
    "sg:phone":"+1 514 846 1632",
    "sg:postcode":"H3G 1C1",
    "sg:province":"QC",
    "wof:name":"Depanneur Dynamix",
    "wof:placetype":"venue"
},
  "geometry": {"coordinates":[-73.5851516724,45.4979057312],"type":"Point"}
}