{
  "type": "Feature",
  "properties": {
    "iso:country":"CA",
    "sg:city":"Scarborough",
    "sg:classifiers":[
        {
            "category":"Social Services",
            "type":"Services"
        }
    ],
    "sg:phone":"+1 416 757 9956",
    "sg:postcode":"M1L 2L6",
    "sg:province":"ON",
    "sg:tags":[
        "organization",
        "welfare"
    ],
    "wof:name":"Toronto Bail Program",
    "wof:placetype":"venue"
},
  "geometry": {"coordinates":[-79.2907791138,43.727016449],"type":"Point"}
}