{
  "type": "Feature",
  "properties": {
    "addr:full":"5155 Baldwin St S Whitby ON L1M 1T4",
    "addr:housenumber":"5155",
    "addr:postcode":"l1m 1t4",
    "addr:street":"Baldwin St S",
    "iso:country":"CA",
    "sg:address":"5155 Baldwin St S",
    "sg:city":"Whitby",
    "sg:classifiers":[
        {
            "category":"Real Estate",
            "subcategory":"Developer",
            "type":"Services"
        }
    ],
    "sg:phone":"+1 905 655 3493",
    "sg:postcode":"L1M 1T4",
    "sg:province":"ON",
    "sg:tags":[
        "cemetery",
        "government"
    ],
    "wof:name":"Groveside Municipal Cemetery",
    "wof:placetype":"venue"
},
  "geometry": {"coordinates":[-78.961227417,43.93516922],"type":"Point"}
}