{
  "type": "Feature",
  "properties": {
    "addr:full":"Kelowna BC V1Y 2M5",
    "addr:postcode":"v1y 2m5",
    "iso:country":"CA",
    "sg:city":"Kelowna",
    "sg:classifiers":[
        {
            "category":"Retail",
            "subcategory":"Auto Repair",
            "type":"Services"
        }
    ],
    "sg:phone":"+1 250 869 4020",
    "sg:postcode":"V1Y 2M5",
    "sg:province":"BC",
    "sg:tags":[
        "repairing",
        "automobile"
    ],
    "wof:name":"Great Canadian Oil Change",
    "wof:placetype":"venue"
},
  "geometry": {"coordinates":[-119.488288879,49.8829841614],"type":"Point"}
}