{
  "type": "Feature",
  "properties": {
    "iso:country":"CA",
    "sg:address":"1459 Rue Crescent",
    "sg:city":"Montreal",
    "sg:classifiers":[
        {
            "category":"Bars & Pubs",
            "type":"Food & Drink"
        }
    ],
    "sg:phone":"+1 514 288 0616",
    "sg:postcode":"H3G 2B2",
    "sg:province":"QC",
    "sg:tags":[
        "lounge",
        "cocktail"
    ],
    "wof:name":"Karina",
    "wof:placetype":"venue"
},
  "geometry": {"coordinates":[-73.5769271851,45.4978637695],"type":"Point"}
}