{
  "type": "Feature",
  "properties": {
    "addr:full":"154 Route 776 Grand Manan NB E5G 1A3",
    "addr:housenumber":"154",
    "addr:postcode":"e5g 1a3",
    "addr:street":"Route 776",
    "iso:country":"CA",
    "sg:address":"154 Route 776",
    "sg:city":"Grand Manan",
    "sg:classifiers":[
        {
            "category":"Home & Garden",
            "subcategory":"Household Appliances",
            "type":"Retail Goods"
        }
    ],
    "sg:phone":"+1 506 662 3156",
    "sg:postcode":"E5G 1A3",
    "sg:province":"NB",
    "wof:name":"Barn Workshop",
    "wof:placetype":"venue"
},
  "geometry": {"coordinates":[-66.84721399999999,44.648453],"type":"Point"}
}