{
  "type": "Feature",
  "properties": {
    "addr:full":"Richmond BC V6V 2L4",
    "addr:postcode":"v6v 2l4",
    "iso:country":"CA",
    "sg:city":"Richmond",
    "sg:classifiers":[
        {
            "category":"Wholesale",
            "subcategory":"Electrical",
            "type":"Manufacturing & Wholesale Goods"
        }
    ],
    "sg:phone":"+1 604 270 0450",
    "sg:postcode":"V6V 2L4",
    "sg:province":"BC",
    "sg:tags":[
        "equipment",
        "electric",
        "motor"
    ],
    "wof:name":"Westburne Electric Supply Ltd",
    "wof:placetype":"venue"
},
  "geometry": {"coordinates":[-123.0730896,49.1840629578],"type":"Point"}
}