{
  "type": "Feature",
  "properties": {
    "iso:country":"CA",
    "sg:address":"484 132 Rte",
    "sg:city":"Cloridorme",
    "sg:classifiers":[
        {
            "category":"Food & Beverages",
            "subcategory":"Groceries & Convenience Stores",
            "type":"Retail Goods"
        }
    ],
    "sg:phone":"+1 418 395 2811",
    "sg:postcode":"G0E 1G0",
    "sg:province":"QC",
    "sg:tags":[
        "grocer"
    ],
    "wof:name":"Boucherie Le Rouge Enr",
    "wof:placetype":"venue"
},
  "geometry": {"coordinates":[-64.85288199999999,49.185135],"type":"Point"}
}