{
  "type": "Feature",
  "properties": {
    "addr:full":"Hwy 1A W Portage LA Prairie MB R1N 3B7",
    "addr:postcode":"r1n 3b7",
    "addr:street":"Hwy 1A W",
    "iso:country":"CA",
    "sg:address":"Hwy 1A W",
    "sg:city":"Portage LA Prairie",
    "sg:classifiers":[
        {
            "category":"Autos & Motor Vehicles",
            "subcategory":"Auto Supplies",
            "type":"Retail Goods"
        }
    ],
    "sg:phone":"+1 204 857 6828",
    "sg:postcode":"R1N 3B7",
    "sg:province":"MB",
    "sg:tags":[
        "tire"
    ],
    "wof:name":"Sene-Boy Tirecraft",
    "wof:placetype":"venue"
},
  "geometry": {"coordinates":[-98.32972700000001,49.973728],"type":"Point"}
}