{
  "type": "Feature",
  "properties": {
    "addr:full":"285 Cummer Ave North York ON M2M 2G1",
    "addr:housenumber":"285",
    "addr:postcode":"m2m 2g1",
    "addr:street":"Cummer Ave",
    "iso:country":"CA",
    "sg:address":"285 Cummer Ave",
    "sg:city":"North York",
    "sg:classifiers":[
        {
            "category":"Health Services",
            "subcategory":"Hospital",
            "type":"Services"
        }
    ],
    "sg:phone":"+1 416 226 6780",
    "sg:postcode":"M2M 2G1",
    "sg:province":"ON",
    "wof:name":"St John's Rehabilitation Hosp",
    "wof:placetype":"venue"
},
  "geometry": {"coordinates":[-79.404800415,43.7896232605],"type":"Point"}
}