{
  "type": "Feature",
  "properties": {
    "addr:full":"25 Ruth Ave Brampton ON L6Z 3X3",
    "addr:housenumber":"25",
    "addr:postcode":"l6z 3x3",
    "addr:street":"Ruth Ave",
    "iso:country":"CA",
    "sg:address":"25 Ruth Ave",
    "sg:city":"Brampton",
    "sg:classifiers":[
        {
            "category":"Organizations",
            "subcategory":"Religious Organization",
            "type":"Services"
        }
    ],
    "sg:phone":"+1 905 846 6657",
    "sg:postcode":"L6Z 3X3",
    "sg:province":"ON",
    "sg:tags":[
        "church"
    ],
    "wof:name":"Heart Lake Presbyterian Church",
    "wof:placetype":"venue"
},
  "geometry": {"coordinates":[-79.787437439,43.7220458984],"type":"Point"}
}