{
  "type": "Feature",
  "properties": {
    "iso:country":"CA",
    "sg:address":"2104 6 St",
    "sg:city":"Nisku",
    "sg:classifiers":[
        {
            "category":"Mining & Drilling",
            "type":"Manufacturing & Wholesale Goods"
        }
    ],
    "sg:phone":"+1 780 955 2424",
    "sg:postcode":"T9E 7X5",
    "sg:province":"AB",
    "sg:tags":[
        "field",
        "oil",
        "valve"
    ],
    "wof:name":"Cana West Valve Ltd",
    "wof:placetype":"venue"
},
  "geometry": {"coordinates":[-113.52747345,53.3397865295],"type":"Point"}
}