{
  "type": "Feature",
  "properties": {
    "addr:full":"Calgary AB T2J 3V1",
    "addr:postcode":"t2j 3v1",
    "iso:country":"CA",
    "sg:city":"Calgary",
    "sg:classifiers":[
        {
            "category":"Shopping",
            "subcategory":"Optical Goods",
            "type":"Retail Goods"
        }
    ],
    "sg:phone":"+1 403 278 2722",
    "sg:postcode":"T2J 3V1",
    "sg:province":"AB",
    "sg:tags":[
        "optician"
    ],
    "wof:name":"Lenscrafters",
    "wof:placetype":"venue"
},
  "geometry": {"coordinates":[-114.06149292000001,50.9497756958],"type":"Point"}
}