{
  "type": "Feature",
  "properties": {
    "addr:full":"Rothesay NB E2E 5B6",
    "addr:postcode":"e2e 5b6",
    "iso:country":"CA",
    "sg:city":"Rothesay",
    "sg:classifiers":[
        {
            "category":"Building & Trades",
            "subcategory":"Construction",
            "type":"Services"
        }
    ],
    "sg:phone":"+1 506 847 8487",
    "sg:postcode":"E2E 5B6",
    "sg:province":"NB",
    "sg:tags":[
        "excavating",
        "contractor"
    ],
    "wof:name":"M & R Carpenter Excavating Ltd",
    "wof:placetype":"venue"
},
  "geometry": {"coordinates":[-65.979767,45.380653],"type":"Point"}
}