{
  "type": "Feature",
  "properties": {
    "addr:full":"5226 Boul Saint-Joseph Saint-Nicephore QC J2A 3V9",
    "addr:housenumber":"5226",
    "addr:postcode":"j2a 3v9",
    "addr:street":"Boul Saint-Joseph Saint-Nicephore",
    "iso:country":"CA",
    "sg:address":"5226 Boul Saint-Joseph",
    "sg:city":"Saint-Nicephore",
    "sg:classifiers":[
        {
            "category":"Professional",
            "subcategory":"Business Services",
            "type":"Services"
        }
    ],
    "sg:phone":"+1 819 472 6757",
    "sg:postcode":"J2A 3V9",
    "sg:province":"QC",
    "sg:tags":[
        "advertising",
        "embroidery"
    ],
    "wof:name":"Spax",
    "wof:placetype":"venue"
},
  "geometry": {"coordinates":[-72.398033,45.819351],"type":"Point"}
}