{
  "type": "Feature",
  "properties": {
    "iso:country":"CA",
    "sg:address":"2251 Rue Guenette",
    "sg:city":"Saint-Laurent",
    "sg:phone":"+1 514 334 7161",
    "sg:postcode":"H4R 2E9",
    "sg:province":"QC",
    "sg:tags":[
        "fixture",
        "store"
    ],
    "wof:name":"Presentoirs Hpr",
    "wof:placetype":"venue"
},
  "geometry": {"coordinates":[-73.72556304930001,45.4984779358],"type":"Point"}
}