{
  "type": "Feature",
  "properties": {
    "addr:full":"1935 Avenue B N Saskatoon SK S7L 4K9",
    "addr:housenumber":"1935",
    "addr:postcode":"s7l 4k9",
    "addr:street":"Avenue B N",
    "iso:country":"CA",
    "sg:address":"1935 Avenue B N",
    "sg:city":"Saskatoon",
    "sg:classifiers":[
        {
            "category":"Retail",
            "subcategory":"Auto Repair",
            "type":"Services"
        }
    ],
    "sg:phone":"+1 306 242 4212",
    "sg:postcode":"S7L 4K9",
    "sg:province":"SK",
    "sg:tags":[
        "automobile",
        "rustproofing",
        "undercoating"
    ],
    "wof:name":"Rust Check",
    "wof:placetype":"venue"
},
  "geometry": {"coordinates":[-106.671966553,52.1556510925],"type":"Point"}
}