{
  "type": "Feature",
  "properties": {
    "addr:full":"77 Rue Rondeau Kirkland QC H9H 4J2",
    "addr:housenumber":"77",
    "addr:postcode":"h9h 4j2",
    "addr:street":"Rue Rondeau",
    "iso:country":"CA",
    "sg:address":"77 Rue Rondeau",
    "sg:city":"Kirkland",
    "sg:classifiers":[
        {
            "category":"Wholesale",
            "subcategory":"Machinery & Supplies",
            "type":"Manufacturing & Wholesale Goods"
        }
    ],
    "sg:phone":"+1 514 426 0219",
    "sg:postcode":"H9H 4J2",
    "sg:province":"QC",
    "sg:tags":[
        "equipment",
        "cover",
        "marine",
        "dock"
    ],
    "wof:name":"Penta Lift Equipment Corp",
    "wof:placetype":"venue"
},
  "geometry": {"coordinates":[-73.84206399999999,45.44664],"type":"Point"}
}