{
  "type": "Feature",
  "properties": {
    "addr:full":"507 18 Ave SW Calgary AB T2S 0C6",
    "addr:postcode":"t2s 0c6",
    "addr:street":"507 18 Ave Sw",
    "iso:country":"CA",
    "sg:address":"507 18 Ave SW",
    "sg:city":"Calgary",
    "sg:classifiers":[
        {
            "category":"Personal",
            "subcategory":"Massage",
            "type":"Services"
        }
    ],
    "sg:phone":"+1 403 228 9877",
    "sg:postcode":"T2S 0C6",
    "sg:province":"AB",
    "wof:name":"Mirage Massage Studio",
    "wof:placetype":"venue"
},
  "geometry": {"coordinates":[-114.07191467299999,51.0368080139],"type":"Point"}
}