{
  "type": "Feature",
  "properties": {
    "addr:full":"4522 Fenwick Jaffray BC V0B 1T0",
    "addr:housenumber":"4522",
    "addr:postcode":"bc v0b 1t0",
    "addr:street":"Fenwick",
    "iso:country":"CA",
    "sg:address":"4522 Fenwick",
    "sg:city":"Jaffray",
    "sg:classifiers":[
        {
            "category":"Government",
            "subcategory":"Office",
            "type":"Public Place"
        }
    ],
    "sg:phone":"+1 250 429 3214",
    "sg:postcode":"V0B 1T0",
    "sg:province":"BC",
    "wof:name":"BC Fisheries",
    "wof:placetype":"venue"
},
  "geometry": {"coordinates":[-115.297241,49.37674],"type":"Point"}
}