{
  "type": "Feature",
  "properties": {
    "iso:country":"CA",
    "sg:address":"8217 Franklin Ave",
    "sg:city":"Fort Mcmurray",
    "sg:classifiers":[
        {
            "category":"Freight",
            "type":"Transportation"
        }
    ],
    "sg:phone":"+1 780 791 2990",
    "sg:postcode":"T9H 4P4",
    "sg:province":"AB",
    "sg:tags":[
        "delivery"
    ],
    "wof:name":"Red Arrow",
    "wof:placetype":"venue"
},
  "geometry": {"coordinates":[-111.351722717,56.7158813477],"type":"Point"}
}