{
  "type": "Feature",
  "properties": {
    "iso:country":"CA",
    "sg:address":"2127 Mer Bleue Rd",
    "sg:city":"Orleans",
    "sg:classifiers":[
        {
            "category":"Recreation",
            "type":"Entertainment"
        }
    ],
    "sg:phone":"+1 613 837 7746",
    "sg:postcode":"K4A 3T9",
    "sg:province":"ON",
    "sg:tags":[
        "range",
        "practice",
        "golf"
    ],
    "wof:name":"Orleans Golf Ctr",
    "wof:placetype":"venue"
},
  "geometry": {"coordinates":[-75.511414,45.480122],"type":"Point"}
}