{
  "type": "Feature",
  "properties": {
    "addr:full":"Concord ON L4K 2Y7",
    "addr:postcode":"l4k 2y7",
    "iso:country":"CA",
    "sg:city":"Concord",
    "sg:classifiers":[
        {
            "category":"Retail",
            "subcategory":"Repair Shop",
            "type":"Services"
        }
    ],
    "sg:phone":"+1 905 669 6406",
    "sg:postcode":"L4K 2Y7",
    "sg:province":"ON",
    "sg:tags":[
        "audio",
        "photographic"
    ],
    "wof:name":"Sun Camera Svc Ltd",
    "wof:placetype":"venue"
},
  "geometry": {"coordinates":[-79.49185199999999,43.782303],"type":"Point"}
}