{
  "type": "Feature",
  "properties": {
    "iso:country":"CA",
    "sg:address":"9852 33 Ave NW",
    "sg:city":"Edmonton",
    "sg:classifiers":[
        {
            "category":"Freight",
            "type":"Transportation"
        }
    ],
    "sg:phone":"+1 780 436 5931",
    "sg:postcode":"T6N 1C6",
    "sg:province":"AB",
    "sg:tags":[
        "field",
        "oil"
    ],
    "wof:name":"Trans Carrier Ltd",
    "wof:placetype":"venue"
},
  "geometry": {"coordinates":[-113.483482361,53.4660568237],"type":"Point"}
}