{
  "type": "Feature",
  "properties": {
    "addr:full":"Kitchener ON N2G 2E4",
    "addr:postcode":"n2g 2e4",
    "iso:country":"CA",
    "sg:city":"Kitchener",
    "sg:classifiers":[
        {
            "category":"Manufacturing",
            "subcategory":"Glass & Minerals",
            "type":"Manufacturing & Wholesale Goods"
        }
    ],
    "sg:phone":"+1 519 571 7567",
    "sg:postcode":"N2G 2E4",
    "sg:province":"ON",
    "sg:tags":[
        "marble"
    ],
    "wof:name":"Marble Tradition",
    "wof:placetype":"venue"
},
  "geometry": {"coordinates":[-80.50412799999999,43.451534],"type":"Point"}
}