{
  "type": "Feature",
  "properties": {
    "iso:country":"CA",
    "sg:address":"1496 Bedford Hwy",
    "sg:city":"Bedford",
    "sg:classifiers":[
        {
            "category":"Government",
            "subcategory":"Office",
            "type":"Public Place"
        }
    ],
    "sg:phone":"+1 902 426 9090",
    "sg:postcode":"B4A 1E5",
    "sg:province":"NS",
    "wof:name":"Canada Atmospheric Environment",
    "wof:placetype":"venue"
},
  "geometry": {"coordinates":[-63.6597633362,44.7313652039],"type":"Point"}
}