{
  "type": "Feature",
  "properties": {
    "iso:country":"CA",
    "sg:address":"301 Oak St",
    "sg:city":"Sudbury",
    "sg:classifiers":[
        {
            "category":"Shopping",
            "subcategory":"Computers & Home Electronics",
            "type":"Retail Goods"
        }
    ],
    "sg:phone":"+1 705 675 2021",
    "sg:postcode":"P3C 1N1",
    "sg:province":"ON",
    "sg:tags":[
        "consultant",
        "software"
    ],
    "wof:name":"Lloyd Research Group Inc",
    "wof:placetype":"venue"
},
  "geometry": {"coordinates":[-81.00559997560001,46.4908332825],"type":"Point"}
}