{
  "type": "Feature",
  "properties": {
    "addr:full":"769 Bethune St Peterborough ON K9H 4A5",
    "addr:housenumber":"769",
    "addr:postcode":"k9h 4a5",
    "addr:street":"Bethune St",
    "iso:country":"CA",
    "sg:address":"769 Bethune St",
    "sg:city":"Peterborough",
    "sg:classifiers":[
        {
            "category":"Building & Trades",
            "subcategory":"Electrical",
            "type":"Services"
        }
    ],
    "sg:phone":"+1 705 745 3391",
    "sg:postcode":"K9H 4A5",
    "sg:province":"ON",
    "sg:tags":[
        "equipment",
        "disability",
        "telecommunication"
    ],
    "wof:name":"Ultimate Communications",
    "wof:placetype":"venue"
},
  "geometry": {"coordinates":[-78.3269958496,44.316318512],"type":"Point"}
}