{
  "type": "Feature",
  "properties": {
    "iso:country":"CA",
    "sg:address":"736 13 St N",
    "sg:city":"Lethbridge",
    "sg:classifiers":[
        {
            "category":"Shopping",
            "subcategory":"Clothing, Apparel, & Fashions",
            "type":"Retail Goods"
        }
    ],
    "sg:phone":"+1 403 328 6229",
    "sg:postcode":"T1H 2T1",
    "sg:province":"AB",
    "sg:tags":[
        "baby",
        "accessory"
    ],
    "wof:name":"Pelican's Pouch",
    "wof:placetype":"venue"
},
  "geometry": {"coordinates":[-112.824325562,49.7099227905],"type":"Point"}
}