{
  "type": "Feature",
  "properties": {
    "addr:full":"713 Switzer Dr # 89 Hinton AB T7V 1H1",
    "addr:housenumber":"713",
    "addr:postcode":"t7v 1h1",
    "addr:street":"Switzer Dr # 89",
    "iso:country":"CA",
    "sg:address":"713 Switzer Dr # 89",
    "sg:city":"Hinton",
    "sg:classifiers":[
        {
            "category":"Autos & Motor Vehicles",
            "subcategory":"Auto Supplies",
            "type":"Retail Goods"
        }
    ],
    "sg:phone":"+1 780 865 4547",
    "sg:postcode":"T7V 1H1",
    "sg:province":"AB",
    "sg:tags":[
        "tire"
    ],
    "wof:name":"Kal Tire",
    "wof:placetype":"venue"
},
  "geometry": {"coordinates":[-117.56102752699999,53.416267395],"type":"Point"}
}