{
  "type": "Feature",
  "properties": {
    "iso:country":"CA",
    "sg:address":"7035 Arbutus Cres",
    "sg:city":"Lantzville",
    "sg:classifiers":[
        {
            "category":"Building & Trades",
            "subcategory":"Construction",
            "type":"Services"
        }
    ],
    "sg:phone":"+1 250 390 3702",
    "sg:postcode":"V0R 2H0",
    "sg:province":"BC",
    "sg:tags":[
        "excavating",
        "contractor"
    ],
    "wof:name":"Cliff's Contracting",
    "wof:placetype":"venue"
},
  "geometry": {"coordinates":[-124.066238403,49.2352256775],"type":"Point"}
}