{
  "type": "Feature",
  "properties": {
    "addr:full":"Notre-Dame-Du-Nord QC J0Z 3B0",
    "addr:postcode":"j0z 3b0",
    "iso:country":"CA",
    "sg:city":"Notre-Dame-Du-Nord",
    "sg:classifiers":[
        {
            "category":"Museum",
            "type":"Entertainment"
        }
    ],
    "sg:phone":"+1 819 723 2500",
    "sg:postcode":"J0Z 3B0",
    "sg:province":"QC",
    "wof:name":"Centre Thematique Fossiliere",
    "wof:placetype":"venue"
},
  "geometry": {"coordinates":[-79.483643,47.592857],"type":"Point"}
}