{
  "type": "Feature",
  "properties": {
    "addr:full":"2015 Park Royal S West Vancouver BC V7T 2W4",
    "addr:housenumber":"2015",
    "addr:postcode":"v7t 2w4",
    "addr:street":"Park Royal S West",
    "iso:country":"CA",
    "sg:address":"2015 Park Royal S",
    "sg:city":"West Vancouver",
    "sg:classifiers":[
        {
            "category":"Shopping",
            "subcategory":"Shoes",
            "type":"Retail Goods"
        }
    ],
    "sg:phone":"+1 604 925 0058",
    "sg:postcode":"V7T 2W4",
    "sg:province":"BC",
    "wof:name":"Wear Else",
    "wof:placetype":"venue"
},
  "geometry": {"coordinates":[-123.140091,49.324432],"type":"Point"}
}