{
  "type": "Feature",
  "properties": {
    "iso:country":"CA",
    "sg:city":"Burlington",
    "sg:classifiers":[
        {
            "category":"Professional",
            "subcategory":"Lawyer & Legal Services",
            "type":"Services"
        }
    ],
    "sg:phone":"+1 905 681 1521",
    "sg:postcode":"L7R 4B6",
    "sg:province":"ON",
    "sg:tags":[
        "attorney"
    ],
    "wof:name":"Simpson & Rich",
    "wof:placetype":"venue"
},
  "geometry": {"coordinates":[-79.799583,43.326729],"type":"Point"}
}