{
  "type": "Feature",
  "properties": {
    "iso:country":"CA",
    "sg:address":"1919 St Mary's Rd",
    "sg:city":"Winnipeg",
    "sg:classifiers":[
        {
            "category":"Autos & Motor Vehicles",
            "subcategory":"Fuel & Gas Station",
            "type":"Retail Goods"
        }
    ],
    "sg:phone":"+1 204 255 4196",
    "sg:postcode":"R2N 2H6",
    "sg:province":"MB",
    "sg:tags":[
        "repairing",
        "automobile",
        "oil"
    ],
    "wof:name":"River Park Husky",
    "wof:placetype":"venue"
},
  "geometry": {"coordinates":[-97.112099,49.815174],"type":"Point"}
}