{
  "type": "Feature",
  "properties": {
    "iso:country":"CA",
    "sg:address":"65 Kings Cres",
    "sg:city":"Ajax",
    "sg:classifiers":[
        {
            "category":"Social Services",
            "subcategory":"Child Care",
            "type":"Services"
        }
    ],
    "sg:phone":"+1 905 427 6744",
    "sg:postcode":"L1S 2M4",
    "sg:province":"ON",
    "sg:tags":[
        "school"
    ],
    "wof:name":"Sunshine Nursery School",
    "wof:placetype":"venue"
},
  "geometry": {"coordinates":[-79.014793,43.850292],"type":"Point"}
}