{
  "type": "Feature",
  "properties": {
    "addr:full":"32 Central St Waterloo ON N2L 3A6",
    "addr:housenumber":"32",
    "addr:postcode":"n2l 3a6",
    "addr:street":"Central St",
    "iso:country":"CA",
    "sg:address":"32 Central St",
    "sg:city":"Waterloo",
    "sg:classifiers":[
        {
            "category":"Education",
            "subcategory":"School",
            "type":"Public Place"
        }
    ],
    "sg:phone":"+1 519 885 6200",
    "sg:postcode":"N2L 3A6",
    "sg:province":"ON",
    "wof:name":"Mac Gregor Public School",
    "wof:placetype":"venue"
},
  "geometry": {"coordinates":[-80.525848,43.470036],"type":"Point"}
}