{
  "type": "Feature",
  "properties": {
    "addr:full":"1445 Boul Ducharme LA Tuque QC G9X 4R7",
    "addr:housenumber":"1445",
    "addr:postcode":"g9x 4r7",
    "addr:street":"Boul Ducharme",
    "iso:country":"CA",
    "sg:address":"1445 Boul Ducharme",
    "sg:city":"LA Tuque",
    "sg:classifiers":[
        {
            "category":"Autos & Motor Vehicles",
            "subcategory":"Automobile Sales",
            "type":"Retail Goods"
        }
    ],
    "sg:phone":"+1 819 523 6144",
    "sg:postcode":"G9X 4R7",
    "sg:province":"QC",
    "sg:tags":[
        "car",
        "dealer"
    ],
    "wof:name":"St-Onge Ford Inc",
    "wof:placetype":"venue"
},
  "geometry": {"coordinates":[-72.78546900000001,47.410263],"type":"Point"}
}