{
  "type": "Feature",
  "properties": {
    "addr:full":"7 Monaghan St Miscouche PE C0B 1T0",
    "addr:housenumber":"7",
    "addr:postcode":"c0b 1t0",
    "addr:street":"Monaghan St",
    "iso:country":"CA",
    "sg:address":"7 Monaghan St",
    "sg:city":"Miscouche",
    "sg:classifiers":[
        {
            "category":"Home & Garden",
            "subcategory":"Garden Supply",
            "type":"Retail Goods"
        }
    ],
    "sg:phone":"+1 902 436 5528",
    "sg:postcode":"C0B 1T0",
    "sg:province":"PE",
    "sg:tags":[
        "lawn",
        "mower"
    ],
    "wof:name":"Small Engine Clinic Ltd",
    "wof:placetype":"venue"
},
  "geometry": {"coordinates":[-63.860699,46.430012],"type":"Point"}
}