{
  "type": "Feature",
  "properties": {
    "addr:full":"2158 Rue Rachel E Montreal QC H2H 1R2",
    "addr:housenumber":"2158",
    "addr:postcode":"h2h 1r2",
    "addr:street":"Rue Rachel E",
    "iso:country":"CA",
    "sg:address":"2158 Rue Rachel E",
    "sg:city":"Montreal",
    "sg:classifiers":[
        {
            "category":"Food & Beverages",
            "subcategory":"Groceries & Convenience Stores",
            "type":"Retail Goods"
        }
    ],
    "sg:phone":"+1 514 525 5577",
    "sg:postcode":"H2H 1R2",
    "sg:province":"QC",
    "sg:tags":[
        "grocer"
    ],
    "wof:name":"Depanneur Lafrance",
    "wof:placetype":"venue"
},
  "geometry": {"coordinates":[-73.56640625,45.5335273743],"type":"Point"}
}