{
  "type": "Feature",
  "properties": {
    "addr:full":"6 Forwell Rd Kitchener ON N2B 3E7",
    "addr:housenumber":"6",
    "addr:postcode":"n2b 3e7",
    "addr:street":"Forwell Rd",
    "iso:country":"CA",
    "sg:address":"6 Forwell Rd",
    "sg:city":"Kitchener",
    "sg:classifiers":[
        {
            "category":"Building & Trades",
            "subcategory":"Construction",
            "type":"Services"
        }
    ],
    "sg:phone":"+1 519 743 2712",
    "sg:postcode":"N2B 3E7",
    "sg:province":"ON",
    "sg:tags":[
        "excavating",
        "contractor"
    ],
    "wof:name":"Rooney Brothers Gradall Svc",
    "wof:placetype":"venue"
},
  "geometry": {"coordinates":[-80.4361495972,43.4723930359],"type":"Point"}
}