{
  "type": "Feature",
  "properties": {
    "addr:full":"2016 Bathurst St York ON M5P 3L1",
    "addr:housenumber":"2016",
    "addr:postcode":"m5p 3l1",
    "addr:street":"Bathurst St",
    "iso:country":"CA",
    "sg:address":"2016 Bathurst St",
    "sg:city":"York",
    "sg:classifiers":[
        {
            "category":"Shopping",
            "subcategory":"Florist",
            "type":"Retail Goods"
        }
    ],
    "sg:phone":"+1 416 782 3195",
    "sg:postcode":"M5P 3L1",
    "sg:province":"ON",
    "wof:name":"Eglinton Greenhouse",
    "wof:placetype":"venue"
},
  "geometry": {"coordinates":[-79.4256057739,43.7008476257],"type":"Point"}
}