{
  "type": "Feature",
  "properties": {
    "addr:full":"225 Henry St Brantford ON N3S 7R4",
    "addr:housenumber":"225",
    "addr:postcode":"n3s 7r4",
    "addr:street":"Henry St",
    "iso:country":"CA",
    "sg:address":"225 Henry St",
    "sg:city":"Brantford",
    "sg:classifiers":[
        {
            "category":"Food & Beverages",
            "subcategory":"Bakery",
            "type":"Retail Goods"
        }
    ],
    "sg:phone":"+1 519 753 4816",
    "sg:postcode":"N3S 7R4",
    "sg:province":"ON",
    "sg:tags":[
        "tea",
        "coffee",
        "doughnut"
    ],
    "wof:name":"Tim Hortons",
    "wof:placetype":"venue"
},
  "geometry": {"coordinates":[-80.236412,43.155727],"type":"Point"}
}