{
  "type": "Feature",
  "properties": {
    "addr:full":"193 Ontario St Burks Falls ON P0A 1C0",
    "addr:housenumber":"193",
    "addr:postcode":"p0a 1c0",
    "addr:street":"Ontario St",
    "iso:country":"CA",
    "sg:address":"193 Ontario St",
    "sg:city":"Burks Falls",
    "sg:classifiers":[
        {
            "category":"Shopping",
            "subcategory":"Pharmacy",
            "type":"Retail Goods"
        }
    ],
    "sg:phone":"+1 705 382 3220",
    "sg:postcode":"P0A 1C0",
    "sg:province":"ON",
    "wof:name":"Bishop's Pharmacy",
    "wof:placetype":"venue"
},
  "geometry": {"coordinates":[-83.564178,46.256901],"type":"Point"}
}