{
  "type": "Feature",
  "properties": {
    "iso:country":"CA",
    "sg:address":"57 King St",
    "sg:city":"Chester",
    "sg:classifiers":[
        {
            "category":"Health Services",
            "subcategory":"Doctor",
            "type":"Services"
        }
    ],
    "sg:phone":"+1 902 275 3529",
    "sg:postcode":"B0J 1J0",
    "sg:province":"NS",
    "sg:tags":[
        "physician",
        "surgeon"
    ],
    "wof:name":"Chester Clinic",
    "wof:placetype":"venue"
},
  "geometry": {"coordinates":[-63.292175293,45.713394165],"type":"Point"}
}