{
  "type": "Feature",
  "properties": {
    "addr:full":"Saskatoon SK S7K 5S6",
    "addr:postcode":"s7k 5s6",
    "iso:country":"CA",
    "sg:city":"Saskatoon",
    "sg:classifiers":[
        {
            "category":"Shopping",
            "subcategory":"Clothing, Apparel, & Fashions",
            "type":"Retail Goods"
        }
    ],
    "sg:phone":"+1 306 933 0006",
    "sg:postcode":"S7K 5S6",
    "sg:province":"SK",
    "wof:name":"Suzy Shier",
    "wof:placetype":"venue"
},
  "geometry": {"coordinates":[-106.640457,52.167423],"type":"Point"}
}