{
  "type": "Feature",
  "properties": {
    "addr:full":"5127 Cherryhill Cres # 406 Burlington ON L7L 4B8",
    "addr:housenumber":"5127",
    "addr:postcode":"l7l 4b8",
    "addr:street":"Cherryhill Cres # 406",
    "iso:country":"CA",
    "sg:address":"5127 Cherryhill Cres # 406",
    "sg:city":"Burlington",
    "sg:classifiers":[
        {
            "category":"Professional",
            "subcategory":"Computer Services",
            "type":"Services"
        }
    ],
    "sg:phone":"+1 905 633 8556",
    "sg:postcode":"L7L 4B8",
    "sg:province":"ON",
    "sg:tags":[
        "internet"
    ],
    "wof:name":"Marshall Forbes & Assoc",
    "wof:placetype":"venue"
},
  "geometry": {"coordinates":[-79.74953499999999,43.369236],"type":"Point"}
}