{
  "type": "Feature",
  "properties": {
    "iso:country":"CA",
    "sg:city":"Mississauga",
    "sg:classifiers":[
        {
            "category":"Health Services",
            "subcategory":"Doctor",
            "type":"Services"
        }
    ],
    "sg:phone":"+1 905 569 8978",
    "sg:postcode":"L5L 3E5",
    "sg:province":"ON",
    "sg:tags":[
        "dentist"
    ],
    "wof:name":"Schellenberg, Teresa DDS",
    "wof:placetype":"venue"
},
  "geometry": {"coordinates":[-79.704704,43.540154],"type":"Point"}
}