{
  "type": "Feature",
  "properties": {
    "addr:full":"Mississauga ON L5L 3E5",
    "addr:postcode":"l5l 3e5",
    "iso:country":"CA",
    "sg:city":"Mississauga",
    "sg:classifiers":[
        {
            "category":"Health Services",
            "subcategory":"Doctor",
            "type":"Services"
        }
    ],
    "sg:phone":"+1 905 569 8978",
    "sg:postcode":"L5L 3E5",
    "sg:province":"ON",
    "sg:tags":[
        "dentist"
    ],
    "wof:name":"Schellenberg, Teresa DDS",
    "wof:placetype":"venue"
},
  "geometry": {"coordinates":[-79.70470400000001,43.540154],"type":"Point"}
}