{
  "type": "Feature",
  "properties": {
    "iso:country":"CA",
    "sg:address":"11330 Lakeside Dr",
    "sg:city":"Prince George",
    "sg:classifiers":[
        {
            "category":"Professional",
            "subcategory":"Detective & Security Services",
            "type":"Services"
        }
    ],
    "sg:phone":"+1 250 967 4838",
    "sg:postcode":"V2K 5M6",
    "sg:province":"BC",
    "sg:tags":[
        "investigator"
    ],
    "wof:name":"Secure Active Svc",
    "wof:placetype":"venue"
},
  "geometry": {"coordinates":[-122.74508667000001,53.9123497009],"type":"Point"}
}