{
  "type": "Feature",
  "properties": {
    "addr:full":"Elizabethtown ON K6T 1A8",
    "addr:postcode":"k6t 1a8",
    "iso:country":"CA",
    "sg:city":"Elizabethtown",
    "sg:classifiers":[
        {
            "category":"Home & Garden",
            "subcategory":"Garden Supply",
            "type":"Retail Goods"
        }
    ],
    "sg:phone":"+1 613 342 3835",
    "sg:postcode":"K6T 1A8",
    "sg:province":"ON",
    "sg:tags":[
        "lawn",
        "mower"
    ],
    "wof:name":"Potter's Small Engine Sales",
    "wof:placetype":"venue"
},
  "geometry": {"coordinates":[-75.766823,44.621803],"type":"Point"}
}