{
  "type": "Feature",
  "properties": {
    "addr:full":"90 Stone St S Gananoque ON K7G 1Z8",
    "addr:housenumber":"90",
    "addr:postcode":"k7g 1z8",
    "addr:street":"Stone St S",
    "iso:country":"CA",
    "sg:address":"90 Stone St S",
    "sg:city":"Gananoque",
    "sg:classifiers":[
        {
            "category":"Travel",
            "subcategory":"Hotels & Motels",
            "type":"Entertainment"
        }
    ],
    "sg:phone":"+1 613 382 8383",
    "sg:postcode":"K7G 1Z8",
    "sg:province":"ON",
    "sg:tags":[
        "breakfast",
        "accommodation",
        "bed"
    ],
    "wof:name":"Trinity House Inn",
    "wof:placetype":"venue"
},
  "geometry": {"coordinates":[-76.162048,44.329056],"type":"Point"}
}