{
  "type": "Feature",
  "properties": {
    "addr:full":"225 Boul Antonio-Barrette Notre-Dame-Des-Prairies QC J6E 1E7",
    "addr:housenumber":"225",
    "addr:postcode":"j6e 1e7",
    "addr:street":"Boul Antonio-Barrette",
    "iso:country":"CA",
    "sg:address":"225 Boul Antonio-Barrette",
    "sg:city":"Notre-Dame-Des-Prairies",
    "sg:classifiers":[
        {
            "category":"Government",
            "subcategory":"Office",
            "type":"Public Place"
        }
    ],
    "sg:phone":"+1 450 759 7741",
    "sg:postcode":"J6E 1E7",
    "sg:province":"QC",
    "sg:tags":[
        "village"
    ],
    "wof:name":"Notre-Dame-Des-Prairies Inspct",
    "wof:placetype":"venue"
},
  "geometry": {"coordinates":[-73.4308395386,46.0439071655],"type":"Point"}
}