{
  "type": "Feature",
  "properties": {
    "addr:full":"533 Alder St Campbell River BC V9W 2N9",
    "addr:housenumber":"533",
    "addr:postcode":"v9w 2n9",
    "addr:street":"Alder St",
    "iso:country":"CA",
    "sg:address":"533 Alder St",
    "sg:city":"Campbell River",
    "sg:classifiers":[
        {
            "category":"Building & Trades",
            "subcategory":"Construction",
            "type":"Services"
        }
    ],
    "sg:phone":"+1 250 830 0435",
    "sg:postcode":"V9W 2N9",
    "sg:province":"BC",
    "sg:tags":[
        "painter"
    ],
    "wof:name":"Brian Dent's Painting & Decor",
    "wof:placetype":"venue"
},
  "geometry": {"coordinates":[-125.239761,50.017132],"type":"Point"}
}