{
  "type": "Feature",
  "properties": {
    "addr:full":"4048 Tolmie Rd Abbotsford BC V3G 2V3",
    "addr:housenumber":"4048",
    "addr:postcode":"v3g 2v3",
    "addr:street":"Tolmie Rd",
    "iso:country":"CA",
    "sg:address":"4048 Tolmie Rd",
    "sg:city":"Abbotsford",
    "sg:classifiers":[
        {
            "category":"Freight",
            "type":"Transportation"
        }
    ],
    "sg:phone":"+1 604 823 0298",
    "sg:postcode":"V3G 2V3",
    "sg:province":"BC",
    "sg:tags":[
        "trucking"
    ],
    "wof:name":"Agri-Trans Svc",
    "wof:placetype":"venue"
},
  "geometry": {"coordinates":[-122.094994,49.077042],"type":"Point"}
}