{
  "type": "Feature",
  "properties": {
    "addr:full":"2315 Aut Transcanadienne Pointe-Claire QC H9R 5Z5",
    "addr:postcode":"2315;h9r 5z5",
    "addr:street":"Transcanadienne",
    "iso:country":"CA",
    "sg:address":"2315 Aut Transcanadienne",
    "sg:city":"Pointe-Claire",
    "sg:classifiers":[
        {
            "category":"Home & Garden",
            "subcategory":"Furniture",
            "type":"Retail Goods"
        }
    ],
    "sg:phone":"+1 514 426 2386",
    "sg:postcode":"H9R 5Z5",
    "sg:province":"QC",
    "wof:name":"Structube",
    "wof:placetype":"venue"
},
  "geometry": {"coordinates":[-73.838218689,45.4578323364],"type":"Point"}
}