{
  "type": "Feature",
  "properties": {
    "addr:full":"Concord ON L4K 4C9",
    "addr:postcode":"l4k 4c9",
    "iso:country":"CA",
    "sg:city":"Concord",
    "sg:classifiers":[
        {
            "category":"Building & Trades",
            "subcategory":"Construction",
            "type":"Services"
        }
    ],
    "sg:phone":"+1 905 660 4924",
    "sg:postcode":"L4K 4C9",
    "sg:province":"ON",
    "sg:tags":[
        "masonry",
        "contractor"
    ],
    "wof:name":"Denham Masonry Ltd",
    "wof:placetype":"venue"
},
  "geometry": {"coordinates":[-79.4920043945,43.8282241821],"type":"Point"}
}