{
  "type": "Feature",
  "properties": {
    "addr:full":"190 Stirling Ave N Kitchener ON N2H 3H2",
    "addr:housenumber":"190",
    "addr:postcode":"n2h 3h2",
    "addr:street":"Stirling Ave N",
    "iso:country":"CA",
    "sg:address":"190 Stirling Ave N",
    "sg:city":"Kitchener",
    "sg:classifiers":[
        {
            "category":"Building & Trades",
            "subcategory":"Construction",
            "type":"Services"
        }
    ],
    "sg:phone":"+1 519 893 6171",
    "sg:postcode":"N2H 3H2",
    "sg:province":"ON",
    "sg:tags":[
        "marking",
        "maintenance",
        "parking"
    ],
    "wof:name":"Imperial Pavement Marking Inc",
    "wof:placetype":"venue"
},
  "geometry": {"coordinates":[-80.471199,43.448483],"type":"Point"}
}