{
  "type": "Feature",
  "properties": {
    "addr:full":"103 Worthington Way Kingston ON K7K 5C6",
    "addr:housenumber":"103",
    "addr:postcode":"k7k 5c6",
    "addr:street":"Worthington Way",
    "iso:country":"CA",
    "sg:address":"103 Worthington Way",
    "sg:city":"Kingston",
    "sg:classifiers":[
        {
            "category":"Real Estate",
            "subcategory":"Real Estate Operator",
            "type":"Services"
        }
    ],
    "sg:phone":"+1 613 542 2800",
    "sg:postcode":"K7K 5C6",
    "sg:province":"ON",
    "sg:tags":[
        "mobile",
        "home",
        "community"
    ],
    "wof:name":"Worthington Park Mobile Homes",
    "wof:placetype":"venue"
},
  "geometry": {"coordinates":[-76.49202,44.260338],"type":"Point"}
}