{
  "type": "Feature",
  "properties": {
    "addr:full":"731 Runnymede Rd Toronto ON M6N 3V7",
    "addr:housenumber":"731",
    "addr:postcode":"m6n 3v7",
    "addr:street":"Runnymede Rd",
    "iso:country":"CA",
    "sg:address":"731 Runnymede Rd",
    "sg:city":"Toronto",
    "sg:classifiers":[
        {
            "category":"Home & Garden",
            "subcategory":"Furniture",
            "type":"Retail Goods"
        }
    ],
    "sg:phone":"+1 416 763 0790",
    "sg:postcode":"M6N 3V7",
    "sg:province":"ON",
    "wof:name":"Early Canadian Furniture",
    "wof:placetype":"venue"
},
  "geometry": {"coordinates":[-79.48300170900001,43.668170929],"type":"Point"}
}