{
  "type": "Feature",
  "properties": {
    "addr:full":"835 Seymour Cres Regina SK S4X 2B6",
    "addr:housenumber":"835",
    "addr:postcode":"s4x 2b6",
    "addr:street":"Seymour Cres",
    "iso:country":"CA",
    "sg:address":"835 Seymour Cres",
    "sg:city":"Regina",
    "sg:phone":"+1 306 721 6555",
    "sg:postcode":"S4X 2B6",
    "sg:province":"SK",
    "sg:tags":[
        "equipment",
        "station"
    ],
    "wof:name":"Wayne Dresser Di Canada Inc",
    "wof:placetype":"venue"
},
  "geometry": {"coordinates":[-104.66894499999999,50.49041],"type":"Point"}
}