{
  "type": "Feature",
  "properties": {
    "addr:full":"Surrey BC V3W 4N6",
    "addr:postcode":"v3w 4n6",
    "iso:country":"CA",
    "sg:city":"Surrey",
    "sg:classifiers":[
        {
            "category":"Manufacturing",
            "subcategory":"Tools & Machinery",
            "type":"Manufacturing & Wholesale Goods"
        }
    ],
    "sg:phone":"+1 604 590 1667",
    "sg:postcode":"V3W 4N6",
    "sg:province":"BC",
    "sg:tags":[
        "electric",
        "motor"
    ],
    "wof:name":"Soper's Supply Ltd",
    "wof:placetype":"venue"
},
  "geometry": {"coordinates":[-122.856994629,49.1533966064],"type":"Point"}
}