{
  "type": "Feature",
  "properties": {
    "addr:full":"1727 Division Rd N Kingsville ON N9Y 2H1",
    "addr:housenumber":"1727",
    "addr:postcode":"n9y 2h1",
    "addr:street":"Division Rd N",
    "iso:country":"CA",
    "sg:address":"1727 Division Rd N",
    "sg:city":"Kingsville",
    "sg:classifiers":[
        {
            "category":"Restaurant",
            "type":"Food & Drink"
        }
    ],
    "sg:phone":"+1 519 733 4040",
    "sg:postcode":"N9Y 2H1",
    "sg:province":"ON",
    "wof:name":"Rosabelle's Restaurant",
    "wof:placetype":"venue"
},
  "geometry": {"coordinates":[-82.738831,42.050137],"type":"Point"}
}