{
  "type": "Feature",
  "properties": {
    "addr:full":"341 Witney Ave S Saskatoon SK S7M 3K4",
    "addr:housenumber":"341",
    "addr:postcode":"s7m 3k4",
    "addr:street":"Witney Ave S",
    "iso:country":"CA",
    "sg:address":"341 Witney Ave S",
    "sg:city":"Saskatoon",
    "sg:classifiers":[
        {
            "category":"Building & Trades",
            "subcategory":"Plumbing",
            "type":"Services"
        }
    ],
    "sg:phone":"+1 306 242 9870",
    "sg:postcode":"S7M 3K4",
    "sg:province":"SK",
    "sg:tags":[
        "contractor"
    ],
    "wof:name":"Stanley's Plumbing & Rpr Svc",
    "wof:placetype":"venue"
},
  "geometry": {"coordinates":[-106.710548401,52.1252632141],"type":"Point"}
}