{
  "type": "Feature",
  "properties": {
    "addr:full":"147 Wyndham St N Guelph ON N1H 4E9",
    "addr:housenumber":"147",
    "addr:postcode":"n1h 4e9",
    "addr:street":"Wyndham St N",
    "iso:country":"CA",
    "sg:address":"147 Wyndham St N",
    "sg:city":"Guelph",
    "sg:classifiers":[
        {
            "category":"Government",
            "subcategory":"Office",
            "type":"Public Place"
        }
    ],
    "sg:phone":"+1 519 826 2222",
    "sg:postcode":"N1H 4E9",
    "sg:province":"ON",
    "wof:name":"Canada Human Resources Ctr",
    "wof:placetype":"venue"
},
  "geometry": {"coordinates":[-80.2500534058,43.5471305847],"type":"Point"}
}