{
  "type": "Feature",
  "properties": {
    "iso:country":"CA",
    "sg:address":"57 Colinization Rd",
    "sg:city":"Emo",
    "sg:classifiers":[
        {
            "category":"Education",
            "subcategory":"School",
            "type":"Public Place"
        }
    ],
    "sg:phone":"+1 807 482 2271",
    "sg:postcode":"P0W 1E0",
    "sg:province":"ON",
    "wof:name":"Donald Young Elementary School",
    "wof:placetype":"venue"
},
  "geometry": {"coordinates":[-93.83782958979999,48.633140564],"type":"Point"}
}