{
  "type": "Feature",
  "properties": {
    "addr:full":"26 Rue Durocher Lachute QC J8H 2V7",
    "addr:housenumber":"26",
    "addr:postcode":"j8h 2v7",
    "addr:street":"Rue Durocher",
    "iso:country":"CA",
    "sg:address":"26 Rue Durocher",
    "sg:city":"Lachute",
    "sg:classifiers":[
        {
            "category":"Restaurant",
            "type":"Food & Drink"
        }
    ],
    "sg:phone":"+1 450 562 6326",
    "sg:postcode":"J8H 2V7",
    "sg:province":"QC",
    "sg:tags":[
        "caterer"
    ],
    "wof:name":"Campbell Reception",
    "wof:placetype":"venue"
},
  "geometry": {"coordinates":[-74.3548202515,45.6484642029],"type":"Point"}
}