{
  "type": "Feature",
  "properties": {
    "addr:full":"630 Thornhill St Morden MB R6M 1E8",
    "addr:housenumber":"630",
    "addr:postcode":"r6m 1e8",
    "addr:street":"Thornhill St",
    "iso:country":"CA",
    "sg:address":"630 Thornhill St",
    "sg:city":"Morden",
    "sg:classifiers":[
        {
            "category":"Restaurant",
            "type":"Food & Drink"
        }
    ],
    "sg:phone":"+1 204 822 1400",
    "sg:postcode":"R6M 1E8",
    "sg:province":"MB",
    "sg:tags":[
        "shop",
        "coffee"
    ],
    "wof:name":"Java Junktion",
    "wof:placetype":"venue"
},
  "geometry": {"coordinates":[-98.09973144529999,49.1921615601],"type":"Point"}
}