{
  "type": "Feature",
  "properties": {
    "addr:full":"Saskatoon SK S7K 5S6",
    "addr:postcode":"s7k 5s6",
    "iso:country":"CA",
    "sg:city":"Saskatoon",
    "sg:classifiers":[
        {
            "category":"Home & Garden",
            "subcategory":"Home Furnishings",
            "type":"Retail Goods"
        }
    ],
    "sg:phone":"+1 306 242 3226",
    "sg:postcode":"S7K 5S6",
    "sg:province":"SK",
    "sg:tags":[
        "kitchen",
        "accessory"
    ],
    "wof:name":"Peppers Kitchen",
    "wof:placetype":"venue"
},
  "geometry": {"coordinates":[-106.64041137700001,52.1674613953],"type":"Point"}
}