{
  "type": "Feature",
  "properties": {
    "iso:country":"CA",
    "sg:address":"1080 Boul Des Recollets",
    "sg:city":"Trois-Rivieres",
    "sg:classifiers":[
        {
            "category":"Restaurant",
            "type":"Food & Drink"
        }
    ],
    "sg:phone":"+1 819 379 4510",
    "sg:postcode":"G8Z 3X1",
    "sg:province":"QC",
    "wof:name":"Kfc",
    "wof:placetype":"venue"
},
  "geometry": {"coordinates":[-72.573776,46.35725],"type":"Point"}
}