{
  "type": "Feature",
  "properties": {
    "addr:full":"1080 Boul Des Recollets Trois-Rivieres QC G8Z 3X1",
    "addr:housenumber":"1080",
    "addr:postcode":"g8z 3x1",
    "addr:street":"Boul Des Recollets Trois-Rivieres",
    "iso:country":"CA",
    "sg:address":"1080 Boul Des Recollets",
    "sg:city":"Trois-Rivieres",
    "sg:classifiers":[
        {
            "category":"Restaurant",
            "type":"Food & Drink"
        }
    ],
    "sg:phone":"+1 819 379 4510",
    "sg:postcode":"G8Z 3X1",
    "sg:province":"QC",
    "wof:name":"Kfc",
    "wof:placetype":"venue"
},
  "geometry": {"coordinates":[-72.573776,46.35725],"type":"Point"}
}