{
  "type": "Feature",
  "properties": {
    "addr:full":"378 Ch DE LA Grande-Cote Boisbriand QC J7G 1B1",
    "addr:housenumber":"378",
    "addr:postcode":"j7g 1b1",
    "addr:street":"Ch De La Grande-Cote",
    "iso:country":"CA",
    "sg:address":"378 Ch DE LA Grande-Cote",
    "sg:city":"Boisbriand",
    "sg:classifiers":[
        {
            "category":"Food & Beverages",
            "subcategory":"Liquor & Beverages",
            "type":"Retail Goods"
        }
    ],
    "sg:phone":"+1 450 437 4772",
    "sg:postcode":"J7G 1B1",
    "sg:province":"QC",
    "sg:tags":[
        "store"
    ],
    "wof:name":"Saq",
    "wof:placetype":"venue"
},
  "geometry": {"coordinates":[-73.8341140747,45.6064338684],"type":"Point"}
}