{
  "type": "Feature",
  "properties": {
    "addr:full":"Rimouski QC G5L 4J2",
    "addr:postcode":"g5l 4j2",
    "iso:country":"CA",
    "sg:city":"Rimouski",
    "sg:classifiers":[
        {
            "category":"Organizations",
            "subcategory":"Professional Association",
            "type":"Services"
        }
    ],
    "sg:phone":"+1 418 721 4421",
    "sg:postcode":"G5L 4J2",
    "sg:province":"QC",
    "wof:name":"Fondation Canadienne Des",
    "wof:placetype":"venue"
},
  "geometry": {"coordinates":[-68.5246887207,48.4472312927],"type":"Point"}
}