{
  "type": "Feature",
  "properties": {
    "addr:full":"North York ON M3A 3R3",
    "addr:postcode":"m3a 3r3",
    "iso:country":"CA",
    "sg:city":"North York",
    "sg:classifiers":[
        {
            "category":"Insurance",
            "subcategory":"Insurance Agent",
            "type":"Services"
        }
    ],
    "sg:phone":"+1 416 447 2018",
    "sg:postcode":"M3A 3R3",
    "sg:province":"ON",
    "wof:name":"State Farm Insurance CO",
    "wof:placetype":"venue"
},
  "geometry": {"coordinates":[-79.32184599999999,43.740879],"type":"Point"}
}