{
  "type": "Feature",
  "properties": {
    "addr:full":"70 West Beaver Creek Rd Richmond Hill ON L4B 1G5",
    "addr:housenumber":"70",
    "addr:postcode":"l4b 1g5",
    "addr:street":"West Beaver Creek Rd",
    "iso:country":"CA",
    "sg:address":"70 West Beaver Creek Rd",
    "sg:city":"Richmond Hill",
    "sg:classifiers":[
        {
            "category":"Wholesale",
            "subcategory":"Electrical",
            "type":"Manufacturing & Wholesale Goods"
        }
    ],
    "sg:phone":"+1 905 709 2396",
    "sg:postcode":"L4B 1G5",
    "sg:province":"ON",
    "sg:tags":[
        "electric",
        "motor"
    ],
    "wof:name":"Herma Motor Svc",
    "wof:placetype":"venue"
},
  "geometry": {"coordinates":[-79.3935165405,43.8548583984],"type":"Point"}
}