{
  "type": "Feature",
  "properties": {
    "addr:full":"5711 Atlantic Dr Mississauga ON L4W 1H3",
    "addr:housenumber":"5711",
    "addr:postcode":"l4w 1h3",
    "addr:street":"Atlantic Dr",
    "iso:country":"CA",
    "sg:address":"5711 Atlantic Dr",
    "sg:city":"Mississauga",
    "sg:classifiers":[
        {
            "category":"Manufacturing",
            "subcategory":"Paper Products",
            "type":"Manufacturing & Wholesale Goods"
        }
    ],
    "sg:phone":"+1 905 670 0301",
    "sg:postcode":"L4W 1H3",
    "sg:province":"ON",
    "sg:tags":[
        "corrugated",
        "solid",
        "fiber",
        "box"
    ],
    "wof:name":"Atlantic Packaging Products",
    "wof:placetype":"venue"
},
  "geometry": {"coordinates":[-79.63552856450001,43.6539802551],"type":"Point"}
}