{
  "type": "Feature",
  "properties": {
    "iso:country":"CA",
    "sg:city":"Amqui",
    "sg:classifiers":[
        {
            "category":"Professional",
            "subcategory":"Lawyer & Legal Services",
            "type":"Services"
        }
    ],
    "sg:phone":"+1 418 629 4404",
    "sg:postcode":"G5J 3G2",
    "sg:province":"QC",
    "sg:tags":[
        "attorney"
    ],
    "wof:name":"Aide Juridique D'Amqui",
    "wof:placetype":"venue"
},
  "geometry": {"coordinates":[-67.43380737299999,48.4641952515],"type":"Point"}
}