{
  "type": "Feature",
  "properties": {
    "addr:full":"210 Saunders St Stayner ON L0M 1S0",
    "addr:housenumber":"210",
    "addr:postcode":"l0m 1s0",
    "addr:street":"Saunders St",
    "iso:country":"CA",
    "sg:address":"210 Saunders St",
    "sg:city":"Stayner",
    "sg:classifiers":[
        {
            "category":"Retail",
            "subcategory":"Portrait Studio",
            "type":"Services"
        }
    ],
    "sg:phone":"+1 705 428 3537",
    "sg:postcode":"L0M 1S0",
    "sg:province":"ON",
    "sg:tags":[
        "photographer"
    ],
    "wof:name":"Jeff Parton Photography",
    "wof:placetype":"venue"
},
  "geometry": {"coordinates":[-80.08889000000001,44.422859],"type":"Point"}
}