{
  "type": "Feature",
  "properties": {
    "addr:full":"2395 Boul Levesque E Laval QC H7E 2N3",
    "addr:housenumber":"2395",
    "addr:postcode":"h7e 2n3",
    "addr:street":"Boul Levesque E",
    "iso:country":"CA",
    "sg:address":"2395 Boul Levesque E",
    "sg:city":"Laval",
    "sg:classifiers":[
        {
            "category":"Autos & Motor Vehicles",
            "subcategory":"Automobile Sales",
            "type":"Retail Goods"
        }
    ],
    "sg:phone":"+1 450 662 0000",
    "sg:postcode":"H7E 2N3",
    "sg:province":"QC",
    "sg:tags":[
        "car",
        "dealer"
    ],
    "wof:name":"Rojo Entreprises Inc",
    "wof:placetype":"venue"
},
  "geometry": {"coordinates":[-73.6679763794,45.5810699463],"type":"Point"}
}