{
  "type": "Feature",
  "properties": {
    "addr:full":"Fredericton NB E3B 6Z6",
    "addr:postcode":"e3b 6z6",
    "iso:country":"CA",
    "sg:city":"Fredericton",
    "sg:classifiers":[
        {
            "category":"Banks & Credit Unions",
            "subcategory":"Bank",
            "type":"Services"
        }
    ],
    "sg:phone":"+1 506 452 3030",
    "sg:postcode":"E3B 6Z6",
    "sg:province":"NB",
    "wof:name":"Business Development Bank",
    "wof:placetype":"venue"
},
  "geometry": {"coordinates":[-66.639526,45.961315],"type":"Point"}
}