{
  "type": "Feature",
  "properties": {
    "addr:full":"3454 17 Ave SE Calgary AB T2A 0R4",
    "addr:housenumber":"3454",
    "addr:postcode":"t2a 0r4",
    "addr:street":"17 Ave Se",
    "iso:country":"CA",
    "sg:address":"3454 17 Ave SE",
    "sg:city":"Calgary",
    "sg:classifiers":[
        {
            "category":"Banks & Credit Unions",
            "subcategory":"Bank",
            "type":"Services"
        }
    ],
    "sg:phone":"+1 403 273 1552",
    "sg:postcode":"T2A 0R4",
    "sg:province":"AB",
    "sg:tags":[
        "cashing",
        "loan",
        "check"
    ],
    "wof:name":"Money Mart",
    "wof:placetype":"venue"
},
  "geometry": {"coordinates":[-113.98556499999999,51.03804],"type":"Point"}
}