{
  "type": "Feature",
  "properties": {
    "addr:full":"3100 Boul Saint-Michel Trois-Rivieres QC G9A 5E1",
    "addr:housenumber":"3100",
    "addr:postcode":"g9a 5e1",
    "addr:street":"Boul Saint-Michel Trois-Rivieres",
    "iso:country":"CA",
    "sg:address":"3100 Boul Saint-Michel",
    "sg:city":"Trois-Rivieres",
    "sg:classifiers":[
        {
            "category":"Retail",
            "subcategory":"Repair Shop",
            "type":"Services"
        }
    ],
    "sg:phone":"+1 819 376 3685",
    "sg:postcode":"G9A 5E1",
    "sg:province":"QC",
    "sg:tags":[
        "ironwork"
    ],
    "wof:name":"Maurice Milette & Fils Enr",
    "wof:placetype":"venue"
},
  "geometry": {"coordinates":[-72.669601,46.381172],"type":"Point"}
}