{
  "type": "Feature",
  "properties": {
    "iso:country":"CA",
    "sg:address":"3505 Maplewood Rd",
    "sg:city":"Victoria",
    "sg:classifiers":[
        {
            "category":"Retail",
            "subcategory":"Animal Services",
            "type":"Services"
        }
    ],
    "sg:phone":"+1 250 383 7387",
    "sg:postcode":"V8P 3N6",
    "sg:province":"BC",
    "sg:tags":[
        "pet",
        "grooming",
        "washing"
    ],
    "wof:name":"Fairfield Grooming House Ltd",
    "wof:placetype":"venue"
},
  "geometry": {"coordinates":[-123.364517,48.428314],"type":"Point"}
}