{
  "type": "Feature",
  "properties": {
    "addr:full":"Swift Current SK S9H 3X6",
    "addr:postcode":"s9h 3x6",
    "iso:country":"CA",
    "sg:city":"Swift Current",
    "sg:classifiers":[
        {
            "category":"Shopping",
            "subcategory":"Florist",
            "type":"Retail Goods"
        }
    ],
    "sg:phone":"+1 306 773 4421",
    "sg:postcode":"S9H 3X6",
    "sg:province":"SK",
    "sg:tags":[
        "apparel"
    ],
    "wof:name":"Grower Direct/Soulstis Flowers",
    "wof:placetype":"venue"
},
  "geometry": {"coordinates":[-107.781051636,50.3051147461],"type":"Point"}
}