{
  "type": "Feature",
  "properties": {
    "iso:country":"CA",
    "sg:city":"Calgary",
    "sg:classifiers":[
        {
            "category":"Professional",
            "subcategory":"Accounting & Tax Preparation",
            "type":"Services"
        }
    ],
    "sg:phone":"+1 403 277 7172",
    "sg:postcode":"T2E 2P8",
    "sg:province":"AB",
    "sg:tags":[
        "accountant"
    ],
    "wof:name":"James Yee & CO",
    "wof:placetype":"venue"
},
  "geometry": {"coordinates":[-114.06275177000001,51.0608825684],"type":"Point"}
}