{
  "type": "Feature",
  "properties": {
    "addr:full":"Calgary AB T2S 2S7",
    "addr:postcode":"t2s 2s7",
    "iso:country":"CA",
    "sg:city":"Calgary",
    "sg:classifiers":[
        {
            "category":"Shopping",
            "type":"Retail Goods"
        }
    ],
    "sg:phone":"+1 403 228 4124",
    "sg:postcode":"T2S 2S7",
    "sg:province":"AB",
    "sg:tags":[
        "hearing",
        "equipment",
        "supply",
        "impaired"
    ],
    "wof:name":"Apex Hearing Systems Ltd",
    "wof:placetype":"venue"
},
  "geometry": {"coordinates":[-114.07164,51.032356],"type":"Point"}
}