{
  "type": "Feature",
  "properties": {
    "addr:full":"2140 Rue Crescent Montreal QC H3G 2B8",
    "addr:housenumber":"2140",
    "addr:postcode":"h3g 2b8",
    "addr:street":"Rue Crescent",
    "iso:country":"CA",
    "sg:address":"2140 Rue Crescent",
    "sg:city":"Montreal",
    "sg:classifiers":[
        {
            "category":"Shopping",
            "subcategory":"Clothing, Apparel, & Fashions",
            "type":"Retail Goods"
        }
    ],
    "sg:phone":"+1 514 842 0020",
    "sg:postcode":"H3G 2B8",
    "sg:province":"QC",
    "sg:tags":[
        "item",
        "boutique"
    ],
    "wof:name":"Blue Willi's",
    "wof:placetype":"venue"
},
  "geometry": {"coordinates":[-73.5784912109,45.4984016418],"type":"Point"}
}