{
  "type": "Feature",
  "properties": {
    "iso:country":"CA",
    "sg:address":"5655 Rue Philippe-Turcot",
    "sg:city":"Montreal",
    "sg:classifiers":[
        {
            "category":"Manufacturing",
            "subcategory":"Rubber & Plastics",
            "type":"Manufacturing & Wholesale Goods"
        }
    ],
    "sg:phone":"+1 514 932 7821",
    "sg:postcode":"H4C 3K8",
    "sg:province":"QC",
    "sg:tags":[
        "mold",
        "maker"
    ],
    "wof:name":"Plastique Caduna Inc",
    "wof:placetype":"venue"
},
  "geometry": {"coordinates":[-73.599525,45.464317],"type":"Point"}
}