{
  "type": "Feature",
  "properties": {
    "addr:full":"2148 Carling Ave Ottawa ON K2A 1H1",
    "addr:housenumber":"2148",
    "addr:postcode":"k2a 1h1",
    "addr:street":"Carling Ave",
    "iso:country":"CA",
    "sg:address":"2148 Carling Ave",
    "sg:city":"Ottawa",
    "sg:classifiers":[
        {
            "category":"Food & Beverages",
            "subcategory":"Groceries & Convenience Stores",
            "type":"Retail Goods"
        }
    ],
    "sg:phone":"+1 613 725 1128",
    "sg:postcode":"K2A 1H1",
    "sg:province":"ON",
    "sg:tags":[
        "grocer"
    ],
    "wof:name":"Fairlawn Your Independent Groc",
    "wof:placetype":"venue"
},
  "geometry": {"coordinates":[-75.7692871094,45.3704948425],"type":"Point"}
}