{
  "type": "Feature",
  "properties": {
    "addr:full":"41 Woodisland Hill Montague PE C0A 1R0",
    "addr:housenumber":"41",
    "addr:postcode":"c0a 1r0",
    "addr:street":"Woodisland Hill",
    "iso:country":"CA",
    "sg:address":"41 Woodisland Hill",
    "sg:city":"Montague",
    "sg:classifiers":[
        {
            "category":"Government",
            "subcategory":"Office",
            "type":"Public Place"
        }
    ],
    "sg:phone":"+1 902 838 0708",
    "sg:postcode":"C0A 1R0",
    "sg:province":"PE",
    "wof:name":"P E Child Abuse Reporting",
    "wof:placetype":"venue"
},
  "geometry": {"coordinates":[-62.649719,46.167164],"type":"Point"}
}