{
  "type": "Feature",
  "properties": {
    "addr:full":"161 Danforth Ave Toronto ON M4K 1N2",
    "addr:housenumber":"161",
    "addr:postcode":"m4k 1n2",
    "addr:street":"Danforth Ave",
    "iso:country":"CA",
    "sg:address":"161 Danforth Ave",
    "sg:city":"Toronto",
    "sg:classifiers":[
        {
            "category":"Manufacturing",
            "subcategory":"Apparel",
            "type":"Manufacturing & Wholesale Goods"
        }
    ],
    "sg:phone":"+1 416 516 4545",
    "sg:postcode":"M4K 1N2",
    "sg:province":"ON",
    "sg:tags":[
        "leather"
    ],
    "wof:name":"Negash Design Inc",
    "wof:placetype":"venue"
},
  "geometry": {"coordinates":[-79.3566360474,43.6764640808],"type":"Point"}
}