{
  "type": "Feature",
  "properties": {
    "addr:full":"1517 Lawson Ave West Vancouver BC V7V 2C8",
    "addr:housenumber":"1517",
    "addr:postcode":"v7v 2c8",
    "addr:street":"Lawson Ave",
    "iso:country":"CA",
    "sg:address":"1517 Lawson Ave",
    "sg:city":"West Vancouver",
    "sg:classifiers":[
        {
            "category":"Banks & Credit Unions",
            "subcategory":"Bank",
            "type":"Services"
        }
    ],
    "sg:phone":"+1 604 922 9300",
    "sg:postcode":"V7V 2C8",
    "sg:province":"BC",
    "sg:tags":[
        "financing"
    ],
    "wof:name":"Interface International",
    "wof:placetype":"venue"
},
  "geometry": {"coordinates":[-123.157387,49.337406],"type":"Point"}
}