{
  "type": "Feature",
  "properties": {
    "addr:full":"67 Rue Des Forges Victoriaville QC G6P 1N9",
    "addr:housenumber":"67",
    "addr:postcode":"g6p 1n9",
    "addr:street":"Rue Des Forges",
    "iso:country":"CA",
    "sg:address":"67 Rue Des Forges",
    "sg:city":"Victoriaville",
    "sg:classifiers":[
        {
            "category":"Professional",
            "subcategory":"Business Services",
            "type":"Services"
        }
    ],
    "sg:phone":"+1 819 758 9911",
    "sg:postcode":"G6P 1N9",
    "sg:province":"QC",
    "sg:tags":[
        "adjuster",
        "insurance",
        "appraiser"
    ],
    "wof:name":"Sinotte & Assoc",
    "wof:placetype":"venue"
},
  "geometry": {"coordinates":[-71.961777,46.056],"type":"Point"}
}