{
  "type": "Feature",
  "properties": {
    "addr:full":"655 32E Av Lachine QC H8T 3G6",
    "addr:housenumber":"655",
    "addr:postcode":"h8t 3g6",
    "addr:street":"32E Av",
    "iso:country":"CA",
    "sg:address":"655 32E Av",
    "sg:city":"Lachine",
    "sg:classifiers":[
        {
            "category":"Professional",
            "subcategory":"Management & Consulting",
            "type":"Services"
        }
    ],
    "sg:phone":"+1 514 634 3434",
    "sg:postcode":"H8T 3G6",
    "sg:province":"QC",
    "sg:tags":[
        "consultant",
        "business"
    ],
    "wof:name":"Pador Associations Mgmt Group",
    "wof:placetype":"venue"
},
  "geometry": {"coordinates":[-73.6927490234,45.4408683777],"type":"Point"}
}