{
  "type": "Feature",
  "properties": {
    "addr:full":"46 Bankfield Dr Etobicoke ON M9V 2P8",
    "addr:housenumber":"46",
    "addr:postcode":"m9v 2p8",
    "addr:street":"Bankfield Dr",
    "iso:country":"CA",
    "sg:address":"46 Bankfield Dr",
    "sg:city":"Etobicoke",
    "sg:classifiers":[
        {
            "category":"Shopping",
            "subcategory":"Stationery & Office Supplies",
            "type":"Retail Goods"
        }
    ],
    "sg:phone":"+1 416 741 2440",
    "sg:postcode":"M9V 2P8",
    "sg:province":"ON",
    "wof:name":"Porter Business Products Inc",
    "wof:placetype":"venue"
},
  "geometry": {"coordinates":[-79.55502300000001,43.734848],"type":"Point"}
}