{
  "type": "Feature",
  "properties": {
    "addr:full":"Medicine Hat AB T1A 2W3",
    "addr:postcode":"t1a 2w3",
    "iso:country":"CA",
    "sg:city":"Medicine Hat",
    "sg:classifiers":[
        {
            "category":"Building & Trades",
            "subcategory":"Plumbing",
            "type":"Services"
        }
    ],
    "sg:phone":"+1 403 526 8341",
    "sg:postcode":"T1A 2W3",
    "sg:province":"AB",
    "sg:tags":[
        "contractor"
    ],
    "wof:name":"Rob Stroh's Plumbing & Heating",
    "wof:placetype":"venue"
},
  "geometry": {"coordinates":[-110.663162,50.031448],"type":"Point"}
}