{
  "type": "Feature",
  "properties": {
    "iso:country":"CA",
    "sg:address":"8760 Ch DE LA Cote-DE-Liesse",
    "sg:city":"Saint-Laurent",
    "sg:classifiers":[
        {
            "category":"Freight",
            "type":"Transportation"
        }
    ],
    "sg:phone":"+1 514 633 2050",
    "sg:postcode":"H4T 1H2",
    "sg:province":"QC",
    "sg:tags":[
        "trucking"
    ],
    "wof:name":"Journey Freight Intl",
    "wof:placetype":"venue"
},
  "geometry": {"coordinates":[-73.706741,45.473904],"type":"Point"}
}