{
  "type": "Feature",
  "properties": {
    "addr:full":"1061 Boul Base-DE-Roc Joliette QC J6E 5P3",
    "addr:housenumber":"1061",
    "addr:postcode":"j6e 5p3",
    "addr:street":"Boul Base-De-Roc",
    "iso:country":"CA",
    "sg:address":"1061 Boul Base-DE-Roc",
    "sg:city":"Joliette",
    "sg:classifiers":[
        {
            "category":"Food & Beverages",
            "subcategory":"Groceries & Convenience Stores",
            "type":"Retail Goods"
        }
    ],
    "sg:phone":"+1 450 759 8448",
    "sg:postcode":"J6E 5P3",
    "sg:province":"QC",
    "wof:name":"Depanneur Marcil",
    "wof:placetype":"venue"
},
  "geometry": {"coordinates":[-73.423103,46.010925],"type":"Point"}
}