{
  "type": "Feature",
  "properties": {
    "addr:full":"1122 Henderson Hwy Winnipeg MB R2G 1L1",
    "addr:housenumber":"1122",
    "addr:postcode":"r2g 1l1",
    "addr:street":"Henderson Hwy",
    "iso:country":"CA",
    "sg:address":"1122 Henderson Hwy",
    "sg:city":"Winnipeg",
    "sg:classifiers":[
        {
            "category":"Government",
            "subcategory":"Office",
            "type":"Public Place"
        }
    ],
    "sg:phone":"+1 204 983 6168",
    "sg:postcode":"R2G 1L1",
    "sg:province":"MB",
    "wof:name":"Canada Employment Ctr",
    "wof:placetype":"venue"
},
  "geometry": {"coordinates":[-97.09242248539999,49.9386901855],"type":"Point"}
}