{
  "type": "Feature",
  "properties": {
    "addr:full":"891 Glencairn Ave North York ON M6B 2A6",
    "addr:housenumber":"891",
    "addr:postcode":"m6b 2a6",
    "addr:street":"Glencairn Ave",
    "iso:country":"CA",
    "sg:address":"891 Glencairn Ave",
    "sg:city":"North York",
    "sg:classifiers":[
        {
            "category":"Home & Garden",
            "subcategory":"Home Furnishings",
            "type":"Retail Goods"
        }
    ],
    "sg:phone":"+1 416 787 8510",
    "sg:postcode":"M6B 2A6",
    "sg:province":"ON",
    "sg:tags":[
        "curtain",
        "made",
        "drapery"
    ],
    "wof:name":"Venezia Drapery",
    "wof:placetype":"venue"
},
  "geometry": {"coordinates":[-79.4470291138,43.7081680298],"type":"Point"}
}