{
  "type": "Feature",
  "properties": {
    "iso:country":"CA",
    "sg:city":"Rabbit Lake",
    "sg:classifiers":[
        {
            "category":"Travel",
            "subcategory":"Hotels & Motels",
            "type":"Entertainment"
        }
    ],
    "sg:phone":"+1 306 824 4812",
    "sg:postcode":"S0M 2L0",
    "sg:province":"SK",
    "sg:tags":[
        "resort"
    ],
    "wof:name":"Meeting Lake Regional Park",
    "wof:placetype":"venue"
},
  "geometry": {"coordinates":[-107.770141602,53.1422309875],"type":"Point"}
}