{
  "type": "Feature",
  "properties": {
    "addr:full":"1697 Lakeshore Rd W Mississauga ON L5J 1J4",
    "addr:housenumber":"1697",
    "addr:postcode":"l5j 1j4",
    "addr:street":"Lakeshore Rd W",
    "iso:country":"CA",
    "sg:address":"1697 Lakeshore Rd W",
    "sg:city":"Mississauga",
    "sg:classifiers":[
        {
            "category":"Shopping",
            "type":"Retail Goods"
        }
    ],
    "sg:phone":"+1 905 822 5495",
    "sg:postcode":"L5J 1J4",
    "sg:province":"ON",
    "sg:tags":[
        "art",
        "gallery",
        "dealer"
    ],
    "wof:name":"Harbour Gallery",
    "wof:placetype":"venue"
},
  "geometry": {"coordinates":[-79.622208,43.518356],"type":"Point"}
}