{
  "type": "Feature",
  "properties": {
    "addr:full":"201 Arlington Ave Ottawa ON K1R 5S8",
    "addr:housenumber":"201",
    "addr:postcode":"k1r 5s8",
    "addr:street":"Arlington Ave",
    "iso:country":"CA",
    "sg:address":"201 Arlington Ave",
    "sg:city":"Ottawa",
    "sg:classifiers":[
        {
            "category":"Freight",
            "type":"Transportation"
        }
    ],
    "sg:phone":"+1 613 235 3244",
    "sg:postcode":"K1R 5S8",
    "sg:province":"ON",
    "sg:tags":[
        "mover"
    ],
    "wof:name":"Gerry's Moving Ltd",
    "wof:placetype":"venue"
},
  "geometry": {"coordinates":[-75.698792,45.407707],"type":"Point"}
}