{
  "type": "Feature",
  "properties": {
    "addr:full":"218 Industrial Dr Mount Forest ON N0G 2L1",
    "addr:housenumber":"218",
    "addr:postcode":"n0g 2l1",
    "addr:street":"Industrial Dr",
    "iso:country":"CA",
    "sg:address":"218 Industrial Dr",
    "sg:city":"Mount Forest",
    "sg:classifiers":[
        {
            "category":"Manufacturing",
            "subcategory":"Tools & Machinery",
            "type":"Manufacturing & Wholesale Goods"
        }
    ],
    "sg:phone":"+1 519 323 2420",
    "sg:postcode":"N0G 2L1",
    "sg:province":"ON",
    "sg:tags":[
        "machine",
        "shop"
    ],
    "wof:name":"Wellington North Machine",
    "wof:placetype":"venue"
},
  "geometry": {"coordinates":[-80.74635314939999,43.9860153198],"type":"Point"}
}