{
  "type": "Feature",
  "properties": {
    "addr:full":"11941 72 St NW Edmonton AB T5B 1Y4",
    "addr:housenumber":"11941",
    "addr:postcode":"t5b 1y4",
    "addr:street":"72 St Nw",
    "iso:country":"CA",
    "sg:address":"11941 72 St NW",
    "sg:city":"Edmonton",
    "sg:classifiers":[
        {
            "category":"Restaurant",
            "type":"Food & Drink"
        }
    ],
    "sg:phone":"+1 780 414 0248",
    "sg:postcode":"T5B 1Y4",
    "sg:province":"AB",
    "sg:tags":[
        "parlor",
        "ice",
        "cream"
    ],
    "wof:name":"Tara's Treats",
    "wof:placetype":"venue"
},
  "geometry": {"coordinates":[-113.451668,53.56815],"type":"Point"}
}