{
  "type": "Feature",
  "properties": {
    "iso:country":"CA",
    "sg:city":"Hinton",
    "sg:classifiers":[
        {
            "category":"Real Estate",
            "subcategory":"Real Estate Operator",
            "type":"Services"
        }
    ],
    "sg:phone":"+1 780 865 1999",
    "sg:postcode":"T7V 1Y6",
    "sg:province":"AB",
    "sg:tags":[
        "mall",
        "shopping",
        "center"
    ],
    "wof:name":"Parks West Mall",
    "wof:placetype":"venue"
},
  "geometry": {"coordinates":[-117.626403809,53.3810844421],"type":"Point"}
}