{
  "type": "Feature",
  "properties": {
    "addr:full":"904 Portage Ave Winnipeg MB R3G 0P4",
    "addr:housenumber":"904",
    "addr:postcode":"r3g 0p4",
    "addr:street":"Portage Ave",
    "iso:country":"CA",
    "sg:address":"904 Portage Ave",
    "sg:city":"Winnipeg",
    "sg:classifiers":[
        {
            "category":"Restaurant",
            "type":"Food & Drink"
        }
    ],
    "sg:phone":"+1 204 779 1136",
    "sg:postcode":"R3G 0P4",
    "sg:province":"MB",
    "wof:name":"George's Burgers & Subs",
    "wof:placetype":"venue"
},
  "geometry": {"coordinates":[-97.1700210571,49.8852386475],"type":"Point"}
}