{
  "type": "Feature",
  "properties": {
    "addr:full":"2000 Boul Rene-Levesque Verdun QC H3E 1Z7",
    "addr:housenumber":"2000",
    "addr:postcode":"h3e 1z7",
    "addr:street":"Boul Rene-Levesque",
    "iso:country":"CA",
    "sg:address":"2000 Boul Rene-Levesque",
    "sg:city":"Verdun",
    "sg:classifiers":[
        {
            "category":"Shopping",
            "subcategory":"Pharmacy",
            "type":"Retail Goods"
        }
    ],
    "sg:phone":"+1 514 761 4448",
    "sg:postcode":"H3E 1Z7",
    "sg:province":"QC",
    "wof:name":"Jean Coutu",
    "wof:placetype":"venue"
},
  "geometry": {"coordinates":[-73.571762085,45.4590187073],"type":"Point"}
}