{
  "type": "Feature",
  "properties": {
    "addr:full":"2236 Av Larue Beauport QC G1C 1J7",
    "addr:housenumber":"2236",
    "addr:postcode":"qc g1c 1j7",
    "addr:street":"Av Larue",
    "iso:country":"CA",
    "sg:address":"2236 Av Larue",
    "sg:city":"Beauport",
    "sg:classifiers":[
        {
            "category":"Food & Beverages",
            "subcategory":"Groceries & Convenience Stores",
            "type":"Retail Goods"
        }
    ],
    "sg:phone":"+1 418 663 2110",
    "sg:postcode":"G1C 1J7",
    "sg:province":"QC",
    "sg:tags":[
        "grocer"
    ],
    "wof:name":"Eko",
    "wof:placetype":"venue"
},
  "geometry": {"coordinates":[-71.1653518677,46.8882598877],"type":"Point"}
}