{
  "type": "Feature",
  "properties": {
    "addr:full":"Brantford ON N3R 6B8",
    "addr:postcode":"n3r 6b8",
    "iso:country":"CA",
    "sg:city":"Brantford",
    "sg:classifiers":[
        {
            "category":"Restaurant",
            "type":"Food & Drink"
        }
    ],
    "sg:phone":"+1 519 753 6361",
    "sg:postcode":"N3R 6B8",
    "sg:province":"ON",
    "wof:name":"A & W Family Restaurant",
    "wof:placetype":"venue"
},
  "geometry": {"coordinates":[-80.243782,43.172901],"type":"Point"}
}