{
  "type": "Feature",
  "properties": {
    "addr:full":"300 Giles Blvd E Windsor ON N9A 4C4",
    "addr:housenumber":"300",
    "addr:postcode":"n9a 4c4",
    "addr:street":"Giles Blvd E",
    "iso:country":"CA",
    "sg:address":"300 Giles Blvd E",
    "sg:city":"Windsor",
    "sg:classifiers":[
        {
            "category":"Health Services",
            "subcategory":"Doctor",
            "type":"Services"
        }
    ],
    "sg:phone":"+1 519 252 4049",
    "sg:postcode":"N9A 4C4",
    "sg:province":"ON",
    "sg:tags":[
        "physician",
        "surgeon"
    ],
    "wof:name":"Parashar, R K MD",
    "wof:placetype":"venue"
},
  "geometry": {"coordinates":[-83.02703099999999,42.30724],"type":"Point"}
}