{
  "type": "Feature",
  "properties": {
    "addr:full":"115 Queen St E St Marys ON N4X 1B7",
    "addr:housenumber":"115",
    "addr:postcode":"n4x 1b7",
    "addr:street":"Queen St E",
    "iso:country":"CA",
    "sg:address":"115 Queen St E",
    "sg:city":"St Marys",
    "sg:classifiers":[
        {
            "category":"Manufacturing",
            "subcategory":"Printing",
            "type":"Manufacturing & Wholesale Goods"
        }
    ],
    "sg:phone":"+1 519 284 2440",
    "sg:postcode":"N4X 1B7",
    "sg:province":"ON",
    "sg:tags":[
        "newspaper"
    ],
    "wof:name":"Journal Argus",
    "wof:placetype":"venue"
},
  "geometry": {"coordinates":[-81.14244100000001,43.259518],"type":"Point"}
}