{
  "type": "Feature",
  "properties": {
    "addr:full":"Grande-Vallee QC G0E 1K0",
    "addr:postcode":"g0e 1k0",
    "iso:country":"CA",
    "sg:city":"Grande-Vallee",
    "sg:classifiers":[
        {
            "category":"Food & Beverages",
            "subcategory":"Groceries & Convenience Stores",
            "type":"Retail Goods"
        }
    ],
    "sg:phone":"+1 418 393 2010",
    "sg:postcode":"G0E 1K0",
    "sg:province":"QC",
    "sg:tags":[
        "grocer"
    ],
    "wof:name":"Super Marche Grande Vallee Inc",
    "wof:placetype":"venue"
},
  "geometry": {"coordinates":[-65.12631988530001,49.2252960205],"type":"Point"}
}