{
  "type": "Feature",
  "properties": {
    "addr:full":"Tisdale SK S0E 1T0",
    "addr:postcode":"s0e 1t0",
    "addr:street":"Tisdale",
    "iso:country":"CA",
    "sg:city":"Tisdale",
    "sg:classifiers":[
        {
            "category":"Real Estate",
            "subcategory":"Real Estate Agent",
            "type":"Services"
        }
    ],
    "sg:phone":"+1 306 873 2412",
    "sg:postcode":"S0E 1T0",
    "sg:province":"SK",
    "sg:tags":[
        "authorities",
        "housing"
    ],
    "wof:name":"Tisdale Housing Authority",
    "wof:placetype":"venue"
},
  "geometry": {"coordinates":[-104.057678223,52.8521156311],"type":"Point"}
}