{
  "type": "Feature",
  "properties": {
    "addr:full":"Waterton Park AB T0K 2M0",
    "addr:postcode":"t0k 2m0",
    "addr:street":"Waterton",
    "iso:country":"CA",
    "sg:city":"Waterton Park",
    "sg:classifiers":[
        {
            "category":"Travel",
            "subcategory":"Travel Agent",
            "type":"Entertainment"
        }
    ],
    "sg:phone":"+1 403 859 2663",
    "sg:postcode":"T0K 2M0",
    "sg:province":"AB",
    "sg:tags":[
        "information",
        "tourist"
    ],
    "wof:name":"Trail of the Great Bear",
    "wof:placetype":"venue"
},
  "geometry": {"coordinates":[-113.907051,49.049835],"type":"Point"}
}