{
  "type": "Feature",
  "properties": {
    "addr:full":"Winkler MB R6W 4B5",
    "addr:postcode":"r6w 4b5",
    "iso:country":"CA",
    "sg:city":"Winkler",
    "sg:classifiers":[
        {
            "category":"Autos & Motor Vehicles",
            "subcategory":"Automobile Sales",
            "type":"Retail Goods"
        }
    ],
    "sg:phone":"+1 204 325 9511",
    "sg:postcode":"R6W 4B5",
    "sg:province":"MB",
    "sg:tags":[
        "car",
        "dealer"
    ],
    "wof:name":"Janzen Pontiac Buick Gmc Ltd",
    "wof:placetype":"venue"
},
  "geometry": {"coordinates":[-97.9384,49.177704],"type":"Point"}
}