{
  "type": "Feature",
  "properties": {
    "iso:country":"CA",
    "sg:city":"Sherbrooke",
    "sg:classifiers":[
        {
            "category":"Shopping",
            "subcategory":"Computers & Home Electronics",
            "type":"Retail Goods"
        }
    ],
    "sg:phone":"+1 819 564 1534",
    "sg:postcode":"J1L 2G4",
    "sg:province":"QC",
    "sg:tags":[
        "equipment",
        "dealer"
    ],
    "wof:name":"Nexinnovations",
    "wof:placetype":"venue"
},
  "geometry": {"coordinates":[-71.937927,45.398396],"type":"Point"}
}