{
  "type": "Feature",
  "properties": {
    "addr:full":"Farm Rd Leslie SK S0A 2E0",
    "addr:postcode":"s0a 2e0",
    "addr:street":"Farm Rd",
    "iso:country":"CA",
    "sg:address":"Farm Rd",
    "sg:city":"Leslie",
    "sg:classifiers":[
        {
            "category":"Farming",
            "subcategory":"Nursery",
            "type":"Manufacturing & Wholesale Goods"
        }
    ],
    "sg:phone":"+1 306 272 4624",
    "sg:postcode":"S0A 2E0",
    "sg:province":"SK",
    "sg:tags":[
        "seed"
    ],
    "wof:name":"B W Seeds",
    "wof:placetype":"venue"
},
  "geometry": {"coordinates":[-103.71627807599999,51.6946983337],"type":"Point"}
}