{
  "type": "Feature",
  "properties": {
    "addr:full":"3702 6 St NE Calgary AB T2E 6K5",
    "addr:housenumber":"3702 6",
    "addr:postcode":"t2e 6k5",
    "addr:street":"St Ne",
    "iso:country":"CA",
    "sg:address":"3702 6 St NE",
    "sg:city":"Calgary",
    "sg:classifiers":[
        {
            "category":"Freight",
            "type":"Transportation"
        }
    ],
    "sg:phone":"+1 403 264 6305",
    "sg:postcode":"T2E 6K5",
    "sg:province":"AB",
    "sg:tags":[
        "commercial",
        "trailer"
    ],
    "wof:name":"Cambrian Trailer Rentals Ltd",
    "wof:placetype":"venue"
},
  "geometry": {"coordinates":[-114.048171997,51.0850791931],"type":"Point"}
}