{
  "type": "Feature",
  "properties": {
    "addr:full":"51 Stover St S Norwich ON N0J 1P0",
    "addr:housenumber":"51",
    "addr:postcode":"n0j 1p0",
    "addr:street":"Stover St S",
    "iso:country":"CA",
    "sg:address":"51 Stover St S",
    "sg:city":"Norwich",
    "sg:classifiers":[
        {
            "category":"Retail",
            "subcategory":"Veterinary Services",
            "type":"Services"
        }
    ],
    "sg:phone":"+1 519 863 3836",
    "sg:postcode":"N0J 1P0",
    "sg:province":"ON",
    "sg:tags":[
        "veterinarian"
    ],
    "wof:name":"Kirby, Kathi DVM",
    "wof:placetype":"venue"
},
  "geometry": {"coordinates":[-80.59554300000001,42.981468],"type":"Point"}
}