{
  "type": "Feature",
  "properties": {
    "addr:full":"157 George St Arthur ON N0G 1A0",
    "addr:housenumber":"157",
    "addr:postcode":"n0g 1a0",
    "addr:street":"George St",
    "iso:country":"CA",
    "sg:address":"157 George St",
    "sg:city":"Arthur",
    "sg:classifiers":[
        {
            "category":"Government",
            "subcategory":"Office",
            "type":"Public Place"
        }
    ],
    "sg:phone":"+1 519 848 2113",
    "sg:postcode":"N0G 1A0",
    "sg:province":"ON",
    "wof:name":"Ontario Driver & Vehicle Lcnc",
    "wof:placetype":"venue"
},
  "geometry": {"coordinates":[-80.536385,43.831657],"type":"Point"}
}