{
  "type": "Feature",
  "properties": {
    "addr:full":"825 King Ave E Newcastle ON L1B 1K8",
    "addr:housenumber":"825",
    "addr:postcode":"l1b 1k8",
    "addr:street":"King Ave E",
    "iso:country":"CA",
    "sg:address":"825 King Ave E",
    "sg:city":"Newcastle",
    "sg:classifiers":[
        {
            "category":"Building & Trades",
            "subcategory":"Construction",
            "type":"Services"
        }
    ],
    "sg:phone":"+1 905 987 9925",
    "sg:postcode":"L1B 1K8",
    "sg:province":"ON",
    "sg:tags":[
        "home",
        "improvement"
    ],
    "wof:name":"Taxis Contracting Ltd",
    "wof:placetype":"venue"
},
  "geometry": {"coordinates":[-78.575615,43.920483],"type":"Point"}
}