{
  "type": "Feature",
  "properties": {
    "addr:full":"2780 Yonge St Toronto ON M4N 2J2",
    "addr:housenumber":"2780",
    "addr:postcode":"m4n 2j2",
    "addr:street":"Yonge St",
    "iso:country":"CA",
    "sg:address":"2780 Yonge St",
    "sg:city":"Toronto",
    "sg:classifiers":[
        {
            "category":"Shopping",
            "subcategory":"Discount & Variety Stores",
            "type":"Retail Goods"
        }
    ],
    "sg:phone":"+1 416 932 2988",
    "sg:postcode":"M4N 2J2",
    "sg:province":"ON",
    "wof:name":"Urban Market",
    "wof:placetype":"venue"
},
  "geometry": {"coordinates":[-79.40116119379999,43.7190895081],"type":"Point"}
}