{
  "type": "Feature",
  "properties": {
    "addr:full":"3015 62 St Edmonton AB T6L 5X8",
    "addr:housenumber":"3015",
    "addr:postcode":"t6l 5x8",
    "addr:street":"62 St",
    "iso:country":"CA",
    "sg:address":"3015 62 St",
    "sg:city":"Edmonton",
    "sg:classifiers":[
        {
            "category":"Health Services",
            "subcategory":"Hospital",
            "type":"Services"
        }
    ],
    "sg:phone":"+1 780 450 7000",
    "sg:postcode":"T6L 5X8",
    "sg:province":"AB",
    "wof:name":"Grey Nuns Community Hospital",
    "wof:placetype":"venue"
},
  "geometry": {"coordinates":[-113.433570862,53.4743804932],"type":"Point"}
}