{
  "type": "Feature",
  "properties": {
    "addr:full":"Terrace BC V8G 3B4",
    "addr:postcode":"v8g 3b4",
    "iso:country":"CA",
    "sg:city":"Terrace",
    "sg:classifiers":[
        {
            "category":"Real Estate",
            "subcategory":"Real Estate Operator",
            "type":"Services"
        }
    ],
    "sg:phone":"+1 250 635 5030",
    "sg:postcode":"V8G 3B4",
    "sg:province":"BC",
    "sg:tags":[
        "apartment"
    ],
    "wof:name":"Munroe Manor",
    "wof:placetype":"venue"
},
  "geometry": {"coordinates":[-128.605392456,54.5170440674],"type":"Point"}
}