{
  "type": "Feature",
  "properties": {
    "addr:full":"1000 Lewes Blvd Whitehorse YT Y1A 3H9",
    "addr:housenumber":"1000",
    "addr:postcode":"y1a 3h9",
    "addr:street":"Lewes Blvd",
    "iso:country":"CA",
    "sg:address":"1000 Lewes Blvd",
    "sg:city":"Whitehorse",
    "sg:classifiers":[
        {
            "category":"Social Services",
            "subcategory":"Child Care",
            "type":"Services"
        }
    ],
    "sg:phone":"+1 867 456 8182",
    "sg:postcode":"Y1A 3H9",
    "sg:province":"YT",
    "sg:tags":[
        "kindergarten",
        "academic",
        "school"
    ],
    "wof:name":"Child Development Ctr",
    "wof:placetype":"venue"
},
  "geometry": {"coordinates":[-135.02505493199999,60.7032623291],"type":"Point"}
}