{
  "type": "Feature",
  "properties": {
    "addr:full":"99 Maitland St Harriston ON N0G 1Z0",
    "addr:housenumber":"99",
    "addr:postcode":"n0g 1z0",
    "addr:street":"Maitland St",
    "iso:country":"CA",
    "sg:address":"99 Maitland St",
    "sg:city":"Harriston",
    "sg:classifiers":[
        {
            "category":"Home & Garden",
            "subcategory":"Building Materials",
            "type":"Retail Goods"
        }
    ],
    "sg:phone":"+1 519 338 2074",
    "sg:postcode":"N0G 1Z0",
    "sg:province":"ON",
    "sg:tags":[
        "windows",
        "contractor"
    ],
    "wof:name":"Franshaw Construction",
    "wof:placetype":"venue"
},
  "geometry": {"coordinates":[-80.86803399999999,43.915123],"type":"Point"}
}