{
  "type": "Feature",
  "properties": {
    "addr:full":"Quebec QC G1S 1T5",
    "addr:postcode":"g1s 1t5",
    "iso:country":"CA",
    "sg:city":"Quebec",
    "sg:classifiers":[
        {
            "category":"Real Estate",
            "subcategory":"Real Estate Agent",
            "type":"Services"
        }
    ],
    "sg:phone":"+1 418 681 5222",
    "sg:postcode":"G1S 1T5",
    "sg:province":"QC",
    "wof:name":"Gendron & Assoc Courtier",
    "wof:placetype":"venue"
},
  "geometry": {"coordinates":[-71.21470600000001,46.809952],"type":"Point"}
}