{
  "type": "Feature",
  "properties": {
    "iso:country":"CA",
    "sg:city":"Fredericton",
    "sg:classifiers":[
        {
            "category":"Shopping",
            "subcategory":"Clothing, Apparel, & Fashions",
            "type":"Retail Goods"
        }
    ],
    "sg:phone":"+1 506 451 8981",
    "sg:postcode":"E3A 8V4",
    "sg:province":"NB",
    "wof:name":"Dorlene",
    "wof:placetype":"venue"
},
  "geometry": {"coordinates":[-66.65033,45.992214],"type":"Point"}
}