{
  "type": "Feature",
  "properties": {
    "iso:country":"CA",
    "sg:address":"651 Cottesmore Ave N",
    "sg:city":"Cobourg",
    "sg:classifiers":[
        {
            "category":"Building & Trades",
            "subcategory":"Construction",
            "type":"Services"
        }
    ],
    "sg:phone":"+1 905 372 9308",
    "sg:postcode":"K9A 4K8",
    "sg:province":"ON",
    "sg:tags":[
        "contractor"
    ],
    "wof:name":"Benz Brothers",
    "wof:placetype":"venue"
},
  "geometry": {"coordinates":[-78.1557312012,43.9708976746],"type":"Point"}
}