{
  "type": "Feature",
  "properties": {
    "addr:full":"2 Wyndenfog Lane East Lawrencetown NS B2Z 1P7",
    "addr:housenumber":"2",
    "addr:postcode":"b2z 1p7",
    "addr:street":"Wyndenfog Lane",
    "iso:country":"CA",
    "sg:address":"2 Wyndenfog Lane",
    "sg:city":"East Lawrencetown",
    "sg:classifiers":[
        {
            "category":"Travel",
            "subcategory":"Hotels & Motels",
            "type":"Entertainment"
        }
    ],
    "sg:phone":"+1 902 827 2712",
    "sg:postcode":"B2Z 1P7",
    "sg:province":"NS",
    "sg:tags":[
        "breakfast",
        "accommodation",
        "bed"
    ],
    "wof:name":"Moonlight Beach Inn",
    "wof:placetype":"venue"
},
  "geometry": {"coordinates":[-63.3298110962,44.6439819336],"type":"Point"}
}