{
  "type": "Feature",
  "properties": {
    "addr:full":"Newmarket ON L3X 1N6",
    "addr:postcode":"l3x 1n6",
    "iso:country":"CA",
    "sg:city":"Newmarket",
    "sg:classifiers":[
        {
            "category":"Food & Beverages",
            "subcategory":"Groceries & Convenience Stores",
            "type":"Retail Goods"
        }
    ],
    "sg:phone":"+1 905 895 0095",
    "sg:postcode":"L3X 1N6",
    "sg:province":"ON",
    "wof:name":"Shalom Convenience Store",
    "wof:placetype":"venue"
},
  "geometry": {"coordinates":[-79.4302749634,44.041469574],"type":"Point"}
}