{
  "type": "Feature",
  "properties": {
    "addr:full":"Scarborough ON M1T 3P6",
    "addr:postcode":"m1t 3p6",
    "iso:country":"CA",
    "sg:city":"Scarborough",
    "sg:classifiers":[
        {
            "category":"Social Services",
            "type":"Services"
        }
    ],
    "sg:phone":"+1 416 291 1800",
    "sg:postcode":"M1T 3P6",
    "sg:province":"ON",
    "sg:tags":[
        "organization",
        "welfare"
    ],
    "wof:name":"Carefirst Seniors & Comm Svc",
    "wof:placetype":"venue"
},
  "geometry": {"coordinates":[-79.2922668457,43.7822380066],"type":"Point"}
}