{
  "type": "Feature",
  "properties": {
    "addr:full":"Saint-Michel-DE-Bellechasse QC G0R 3S0",
    "addr:postcode":"g0r 3s0",
    "iso:country":"CA",
    "sg:city":"Saint-Michel-DE-Bellechasse",
    "sg:classifiers":[
        {
            "category":"Education",
            "subcategory":"Library",
            "type":"Public Place"
        }
    ],
    "sg:phone":"+1 418 884 2766",
    "sg:postcode":"G0R 3S0",
    "sg:province":"QC",
    "wof:name":"Bibliotheque Benoit Lacroix",
    "wof:placetype":"venue"
},
  "geometry": {"coordinates":[-70.91185760499999,46.8715324402],"type":"Point"}
}