{
  "type": "Feature",
  "properties": {
    "addr:full":"347 Hwy 16 Burns Lake BC V0J 1E0",
    "addr:housenumber":"347",
    "addr:postcode":"v0j 1e0",
    "addr:street":"Hwy 16 Burns",
    "iso:country":"CA",
    "sg:address":"347 Hwy 16",
    "sg:city":"Burns Lake",
    "sg:classifiers":[
        {
            "category":"Professional",
            "subcategory":"Lawyer & Legal Services",
            "type":"Services"
        }
    ],
    "sg:phone":"+1 250 692 7688",
    "sg:postcode":"V0J 1E0",
    "sg:province":"BC",
    "sg:tags":[
        "attorney"
    ],
    "wof:name":"Laura Lee Grant Law Office",
    "wof:placetype":"venue"
},
  "geometry": {"coordinates":[-125.76282501199999,54.2285766602],"type":"Point"}
}