{
  "type": "Feature",
  "properties": {
    "addr:full":"417 Wellington St St Thomas ON N5R 5J5",
    "addr:housenumber":"417",
    "addr:postcode":"n5r 5j5",
    "addr:street":"Wellington St",
    "iso:country":"CA",
    "sg:address":"417 Wellington St",
    "sg:city":"St Thomas",
    "sg:classifiers":[
        {
            "category":"Recreation",
            "type":"Entertainment"
        }
    ],
    "sg:phone":"+1 519 633 0392",
    "sg:postcode":"N5R 5J5",
    "sg:province":"ON",
    "sg:tags":[
        "convenience",
        "lottery",
        "store",
        "agent"
    ],
    "wof:name":"Cnib Corner Store",
    "wof:placetype":"venue"
},
  "geometry": {"coordinates":[-81.1623840332,42.7747917175],"type":"Point"}
}