{
  "type": "Feature",
  "properties": {
    "addr:full":"4681 Ch Royal Sainte-Famille QC G0A 3P0",
    "addr:postcode":"4681;g0a 3p0",
    "addr:street":"Ch Royal",
    "iso:country":"CA",
    "sg:address":"4681 Ch Royal",
    "sg:city":"Sainte-Famille",
    "sg:classifiers":[
        {
            "category":"Retail",
            "subcategory":"Auto Repair",
            "type":"Services"
        }
    ],
    "sg:phone":"+1 418 829 2879",
    "sg:postcode":"G0A 3P0",
    "sg:province":"QC",
    "sg:tags":[
        "repairing",
        "automobile"
    ],
    "wof:name":"Garage Rejean Deblois Inc",
    "wof:placetype":"venue"
},
  "geometry": {"coordinates":[-70.90876,46.99881],"type":"Point"}
}