{
  "type": "Feature",
  "properties": {
    "iso:country":"CA",
    "sg:address":"1245 Oxford St",
    "sg:city":"Victoria",
    "sg:classifiers":[
        {
            "category":"Education",
            "subcategory":"Special Training",
            "type":"Public Place"
        }
    ],
    "sg:phone":"+1 250 384 1783",
    "sg:postcode":"V8V 2V6",
    "sg:province":"BC",
    "sg:tags":[
        "school",
        "instruction",
        "art"
    ],
    "wof:name":"Oxford Street Art School",
    "wof:placetype":"venue"
},
  "geometry": {"coordinates":[-123.35105133099999,48.413356781],"type":"Point"}
}