{
  "type": "Feature",
  "properties": {
    "addr:full":"5025 Route 1 Pennfield NB E5H 1Y4",
    "addr:housenumber":"5025",
    "addr:postcode":"e5h 1y4",
    "addr:street":"Route 1",
    "iso:country":"CA",
    "sg:address":"5025 Route 1",
    "sg:city":"Pennfield",
    "sg:classifiers":[
        {
            "category":"Restaurant",
            "type":"Food & Drink"
        }
    ],
    "sg:phone":"+1 506 755 3011",
    "sg:postcode":"E5H 1Y4",
    "sg:province":"NB",
    "wof:name":"Comeau's Seafood Restaurant",
    "wof:placetype":"venue"
},
  "geometry": {"coordinates":[-66.731995,45.113235],"type":"Point"}
}