{
  "type": "Feature",
  "properties": {
    "addr:full":"5252 Hwy 60 Douglas ON K0J 1S0",
    "addr:housenumber":"5252",
    "addr:postcode":"k0j 1s0",
    "addr:street":"Hwy 60",
    "iso:country":"CA",
    "sg:address":"5252 Hwy 60",
    "sg:city":"Douglas",
    "sg:classifiers":[
        {
            "category":"Wholesale",
            "subcategory":"Machinery & Supplies",
            "type":"Manufacturing & Wholesale Goods"
        }
    ],
    "sg:phone":"+1 613 649 2457",
    "sg:postcode":"K0J 1S0",
    "sg:province":"ON",
    "sg:tags":[
        "farm",
        "equipment"
    ],
    "wof:name":"Bromley Farm Supply Ltd",
    "wof:placetype":"venue"
},
  "geometry": {"coordinates":[-76.94107099999999,45.510883],"type":"Point"}
}