{
  "type": "Feature",
  "properties": {
    "addr:full":"475 Rue Principale Granby QC J2G 2W9",
    "addr:housenumber":"475",
    "addr:postcode":"j2g 2w9",
    "addr:street":"Rue Principale",
    "iso:country":"CA",
    "sg:address":"475 Rue Principale",
    "sg:city":"Granby",
    "sg:classifiers":[
        {
            "category":"Shopping",
            "type":"Retail Goods"
        }
    ],
    "sg:phone":"+1 450 378 3514",
    "sg:postcode":"J2G 2W9",
    "sg:province":"QC",
    "sg:tags":[
        "lace"
    ],
    "wof:name":"Decoration Ouellet",
    "wof:placetype":"venue"
},
  "geometry": {"coordinates":[-72.735794,45.404442],"type":"Point"}
}