{
  "type": "Feature",
  "properties": {
    "addr:full":"Scarborough ON M1B 3E9",
    "addr:postcode":"m1b 3e9",
    "iso:country":"CA",
    "sg:city":"Scarborough",
    "sg:classifiers":[
        {
            "category":"Manufacturing",
            "subcategory":"Furniture",
            "type":"Manufacturing & Wholesale Goods"
        }
    ],
    "sg:phone":"+1 416 754 0090",
    "sg:postcode":"M1B 3E9",
    "sg:province":"ON",
    "sg:tags":[
        "material",
        "fixture",
        "display"
    ],
    "wof:name":"Exhibit Store",
    "wof:placetype":"venue"
},
  "geometry": {"coordinates":[-79.2346572876,43.8022766113],"type":"Point"}
}