{
  "type": "Feature",
  "properties": {
    "addr:full":"176 Rue Simard Saint-Ambroise QC G7P 2R7",
    "addr:housenumber":"176",
    "addr:postcode":"g7p 2r7",
    "addr:street":"Rue Simard",
    "iso:country":"CA",
    "sg:address":"176 Rue Simard",
    "sg:city":"Saint-Ambroise",
    "sg:classifiers":[
        {
            "category":"Manufacturing",
            "subcategory":"Furniture",
            "type":"Manufacturing & Wholesale Goods"
        }
    ],
    "sg:phone":"+1 418 672 2155",
    "sg:postcode":"G7P 2R7",
    "sg:province":"QC",
    "sg:tags":[
        "exposition",
        "stand"
    ],
    "wof:name":"Kiliex Enr",
    "wof:placetype":"venue"
},
  "geometry": {"coordinates":[-71.322823,48.550369],"type":"Point"}
}