{
  "type": "Feature",
  "properties": {
    "addr:full":"32 Queen St Ripley ON N0G 2R0",
    "addr:housenumber":"32",
    "addr:postcode":"n0g 2r0",
    "addr:street":"Queen St",
    "iso:country":"CA",
    "sg:address":"32 Queen St",
    "sg:city":"Ripley",
    "sg:classifiers":[
        {
            "category":"Restaurant",
            "type":"Food & Drink"
        }
    ],
    "sg:phone":"+1 519 395 4455",
    "sg:postcode":"N0G 2R0",
    "sg:province":"ON",
    "wof:name":"Liddle's Family Restaurant",
    "wof:placetype":"venue"
},
  "geometry": {"coordinates":[-81.579414,44.071621],"type":"Point"}
}