{
  "type": "Feature",
  "properties": {
    "iso:country":"CA",
    "sg:city":"Kingston",
    "sg:classifiers":[
        {
            "category":"Health Services",
            "subcategory":"Medical Lab",
            "type":"Services"
        }
    ],
    "sg:phone":"+1 613 634 4391",
    "sg:postcode":"K7P 1T5",
    "sg:province":"ON",
    "sg:tags":[
        "laboratory"
    ],
    "wof:name":"Central Dental Laboratories",
    "wof:placetype":"venue"
},
  "geometry": {"coordinates":[-76.5890884399,44.2520294189],"type":"Point"}
}