{
  "type": "Feature",
  "properties": {
    "addr:full":"Hwy 12 Coldwater ON L0K 1E0",
    "addr:postcode":"l0k 1e0",
    "addr:street":"Hwy 12",
    "iso:country":"CA",
    "sg:address":"Hwy 12",
    "sg:city":"Coldwater",
    "sg:classifiers":[
        {
            "category":"Home & Garden",
            "subcategory":"Garden Supply",
            "type":"Retail Goods"
        }
    ],
    "sg:phone":"+1 705 686 3387",
    "sg:postcode":"L0K 1E0",
    "sg:province":"ON",
    "sg:tags":[
        "center"
    ],
    "wof:name":"Fesserton Precast Concrete",
    "wof:placetype":"venue"
},
  "geometry": {"coordinates":[-79.6289520264,44.6861991882],"type":"Point"}
}