{
  "type": "Feature",
  "properties": {
    "addr:full":"5655 King Rd Nobleton ON L0G 1N0",
    "addr:housenumber":"5655",
    "addr:postcode":"l0g 1n0",
    "addr:street":"King Rd",
    "iso:country":"CA",
    "sg:address":"5655 King Rd",
    "sg:city":"Nobleton",
    "sg:classifiers":[
        {
            "category":"Retail",
            "subcategory":"Auto Repair",
            "type":"Services"
        }
    ],
    "sg:phone":"+1 905 859 3848",
    "sg:postcode":"L0G 1N0",
    "sg:province":"ON",
    "sg:tags":[
        "repairing",
        "automobile"
    ],
    "wof:name":"Cosmocare Service & Collision",
    "wof:placetype":"venue"
},
  "geometry": {"coordinates":[-79.6410140991,43.9039268494],"type":"Point"}
}