{
  "type": "Feature",
  "properties": {
    "addr:full":"210 Claude St Wolseley SK S0G 5H0",
    "addr:housenumber":"210",
    "addr:postcode":"s0g 5h0",
    "addr:street":"Claude St",
    "iso:country":"CA",
    "sg:address":"210 Claude St",
    "sg:city":"Wolseley",
    "sg:classifiers":[
        {
            "category":"Retail",
            "subcategory":"Funeral Services",
            "type":"Services"
        }
    ],
    "sg:phone":"+1 306 698 2557",
    "sg:postcode":"S0G 5H0",
    "sg:province":"SK",
    "sg:tags":[
        "director"
    ],
    "wof:name":"Tubman Funeral Home",
    "wof:placetype":"venue"
},
  "geometry": {"coordinates":[-103.27891540500001,50.4196395874],"type":"Point"}
}