{
  "type": "Feature",
  "properties": {
    "addr:full":"14 Division St Bowmanville ON L1C 2Z1",
    "addr:housenumber":"14",
    "addr:postcode":"l1c 2z1",
    "addr:street":"Division St",
    "iso:country":"CA",
    "sg:address":"14 Division St",
    "sg:city":"Bowmanville",
    "sg:classifiers":[
        {
            "category":"Personal",
            "subcategory":"Beauty Salon",
            "type":"Services"
        }
    ],
    "sg:phone":"+1 905 623 0113",
    "sg:postcode":"L1C 2Z1",
    "sg:province":"ON",
    "wof:name":"Total Aspects",
    "wof:placetype":"venue"
},
  "geometry": {"coordinates":[-78.68804168699999,43.9114265442],"type":"Point"}
}