{
  "type": "Feature",
  "properties": {
    "addr:full":"2035 Rue Sauriol E Montreal QC H2B 1E4",
    "addr:housenumber":"2035",
    "addr:postcode":"h2b 1e4",
    "addr:street":"Rue Sauriol E",
    "iso:country":"CA",
    "sg:address":"2035 Rue Sauriol E",
    "sg:city":"Montreal",
    "sg:classifiers":[
        {
            "category":"Insurance",
            "subcategory":"Hazard Insurance",
            "type":"Services"
        }
    ],
    "sg:phone":"+1 514 388 2324",
    "sg:postcode":"H2B 1E4",
    "sg:province":"QC",
    "wof:name":"Societe DE Cautionnement",
    "wof:placetype":"venue"
},
  "geometry": {"coordinates":[-73.6491241455,45.5692405701],"type":"Point"}
}