{
  "type": "Feature",
  "properties": {
    "addr:full":"9822 101 Ave Fort St John BC V1J 2B2",
    "addr:housenumber":"9822",
    "addr:postcode":"v1j 2b2",
    "addr:street":"101 Ave",
    "iso:country":"CA",
    "sg:address":"9822 101 Ave",
    "sg:city":"Fort St John",
    "sg:classifiers":[
        {
            "category":"Professional",
            "subcategory":"Accounting & Tax Preparation",
            "type":"Services"
        }
    ],
    "sg:phone":"+1 250 787 7522",
    "sg:postcode":"V1J 2B2",
    "sg:province":"BC",
    "sg:tags":[
        "bookkeeping",
        "general"
    ],
    "wof:name":"First Choice Bookkeeping",
    "wof:placetype":"venue"
},
  "geometry": {"coordinates":[-120.844711,56.247593],"type":"Point"}
}