{
  "type": "Feature",
  "properties": {
    "addr:full":"5415 56 Ave SE Calgary AB T2C 3X6",
    "addr:housenumber":"5415",
    "addr:postcode":"t2c 3x6",
    "addr:street":"56 Ave Se",
    "iso:country":"CA",
    "sg:address":"5415 56 Ave SE",
    "sg:city":"Calgary",
    "sg:classifiers":[
        {
            "category":"Building & Trades",
            "subcategory":"Construction",
            "type":"Services"
        }
    ],
    "sg:phone":"+1 403 236 3478",
    "sg:postcode":"T2C 3X6",
    "sg:province":"AB",
    "sg:tags":[
        "contractor",
        "road",
        "general"
    ],
    "wof:name":"Top Notch Construction Ltd",
    "wof:placetype":"venue"
},
  "geometry": {"coordinates":[-113.955658,51.001987],"type":"Point"}
}