{
  "type": "Feature",
  "properties": {
    "iso:country":"CA",
    "sg:city":"Sherwood Park",
    "sg:classifiers":[
        {
            "category":"Professional",
            "subcategory":"Lawyer & Legal Services",
            "type":"Services"
        }
    ],
    "sg:phone":"+1 780 464 7477",
    "sg:postcode":"T8A 4W6",
    "sg:province":"AB",
    "sg:tags":[
        "attorney"
    ],
    "wof:name":"Ahlstrom Wright Oliver Cooper",
    "wof:placetype":"venue"
},
  "geometry": {"coordinates":[-113.32476043699999,53.5357818604],"type":"Point"}
}