{
  "type": "Feature",
  "properties": {
    "addr:full":"40 Dundas St W Toronto ON M5G 2C2",
    "addr:housenumber":"40",
    "addr:postcode":"m5g 2c2",
    "addr:street":"Dundas St W",
    "iso:country":"CA",
    "sg:address":"40 Dundas St W",
    "sg:city":"Toronto",
    "sg:classifiers":[
        {
            "category":"Health Services",
            "subcategory":"Health Practitioner",
            "type":"Services"
        }
    ],
    "sg:phone":"+1 416 599 7232",
    "sg:postcode":"M5G 2C2",
    "sg:province":"ON",
    "sg:tags":[
        "nurse",
        "registry"
    ],
    "wof:name":"Exclusive Care Svc",
    "wof:placetype":"venue"
},
  "geometry": {"coordinates":[-79.3828430176,43.6560401917],"type":"Point"}
}