{
  "type": "Feature",
  "properties": {
    "addr:full":"Montreal QC H3B 5E9",
    "addr:postcode":"h3b 5e9",
    "iso:country":"CA",
    "sg:city":"Montreal",
    "sg:classifiers":[
        {
            "category":"Professional",
            "subcategory":"Lawyer & Legal Services",
            "type":"Services"
        }
    ],
    "sg:phone":"+1 514 925 6300",
    "sg:postcode":"H3B 5E9",
    "sg:province":"QC",
    "sg:tags":[
        "attorney"
    ],
    "wof:name":"Lapointe Rosenstein",
    "wof:placetype":"venue"
},
  "geometry": {"coordinates":[-73.55313099999999,45.517662],"type":"Point"}
}