{
  "type": "Feature",
  "properties": {
    "addr:full":"3050 Boys Rd Duncan BC V9L 6W4",
    "addr:housenumber":"3050",
    "addr:postcode":"v9l 6w4",
    "addr:street":"Boys Rd",
    "iso:country":"CA",
    "sg:address":"3050 Boys Rd",
    "sg:city":"Duncan",
    "sg:classifiers":[
        {
            "category":"Retail",
            "subcategory":"Auto Repair",
            "type":"Services"
        }
    ],
    "sg:phone":"+1 250 748 5514",
    "sg:postcode":"V9L 6W4",
    "sg:province":"BC",
    "sg:tags":[
        "body",
        "automobile",
        "painting"
    ],
    "wof:name":"G T Collision Ctr Ltd",
    "wof:placetype":"venue"
},
  "geometry": {"coordinates":[-123.70738220200001,48.779094696],"type":"Point"}
}