{
  "type": "Feature",
  "properties": {
    "iso:country":"CA",
    "sg:address":"28 Crowfoot Cir NW",
    "sg:city":"Calgary",
    "sg:classifiers":[
        {
            "category":"Restaurant",
            "type":"Food & Drink"
        }
    ],
    "sg:phone":"+1 403 241 1772",
    "sg:postcode":"T3G 2T3",
    "sg:province":"AB",
    "wof:name":"Swiss Chalet Rotisserie/Grill",
    "wof:placetype":"venue"
},
  "geometry": {"coordinates":[-114.203430176,51.1229553223],"type":"Point"}
}