{
  "type": "Feature",
  "properties": {
    "addr:full":"Jasper ON K0G 1G0",
    "addr:postcode":"k0g 1g0",
    "iso:country":"CA",
    "sg:city":"Jasper",
    "sg:classifiers":[
        {
            "category":"Wholesale",
            "subcategory":"Auto Parts",
            "type":"Manufacturing & Wholesale Goods"
        }
    ],
    "sg:phone":"+1 613 283 4794",
    "sg:postcode":"K0G 1G0",
    "sg:province":"ON",
    "sg:tags":[
        "automobile",
        "rebuilt"
    ],
    "wof:name":"Mc Dougall Auto Recyclers Ltd",
    "wof:placetype":"venue"
},
  "geometry": {"coordinates":[-75.94136,44.825916],"type":"Point"}
}