{
  "type": "Feature",
  "properties": {
    "iso:country":"CA",
    "sg:address":"4111 Rossland Cres",
    "sg:city":"Mississauga",
    "sg:classifiers":[
        {
            "category":"Professional",
            "subcategory":"Business Services",
            "type":"Services"
        }
    ],
    "sg:phone":"+1 905 820 7530",
    "sg:postcode":"L5L 4B8",
    "sg:province":"ON",
    "sg:tags":[
        "pool",
        "swimming"
    ],
    "wof:name":"Jaf Pool Svc Limited",
    "wof:placetype":"venue"
},
  "geometry": {"coordinates":[-79.7109069824,43.5330963135],"type":"Point"}
}