{
  "type": "Feature",
  "properties": {
    "addr:full":"151 Esna Park Dr # 16 Markham ON L3R 3B1",
    "addr:housenumber":"151",
    "addr:postcode":"l3r 3b1",
    "addr:street":"Esna Park Dr # 16",
    "iso:country":"CA",
    "sg:address":"151 Esna Park Dr # 16",
    "sg:city":"Markham",
    "sg:classifiers":[
        {
            "category":"Professional",
            "subcategory":"Management & Consulting",
            "type":"Services"
        }
    ],
    "sg:phone":"+1 905 305 7441",
    "sg:postcode":"L3R 3B1",
    "sg:province":"ON",
    "sg:tags":[
        "marketing",
        "consultant"
    ],
    "wof:name":"York Overseas",
    "wof:placetype":"venue"
},
  "geometry": {"coordinates":[-79.3391418457,43.8266716003],"type":"Point"}
}