{
  "type": "Feature",
  "properties": {
    "addr:full":"210 Clarence St Brampton ON L6W 1T4",
    "addr:housenumber":"210",
    "addr:postcode":"l6w 1t4",
    "addr:street":"Clarence St",
    "iso:country":"CA",
    "sg:address":"210 Clarence St",
    "sg:city":"Brampton",
    "sg:classifiers":[
        {
            "category":"Home & Garden",
            "subcategory":"Home Furnishings",
            "type":"Retail Goods"
        }
    ],
    "sg:phone":"+1 905 453 6403",
    "sg:postcode":"L6W 1T4",
    "sg:province":"ON",
    "sg:tags":[
        "lighting",
        "fixture"
    ],
    "wof:name":"Lando Lighting Inc",
    "wof:placetype":"venue"
},
  "geometry": {"coordinates":[-79.739395,43.690758],"type":"Point"}
}