{
  "type": "Feature",
  "properties": {
    "addr:full":"9944 35 Ave NW Edmonton AB T6E 6B2",
    "addr:housenumber":"9944",
    "addr:postcode":"t6e 6b2",
    "addr:street":"35 Ave Nw",
    "iso:country":"CA",
    "sg:address":"9944 35 Ave NW",
    "sg:city":"Edmonton",
    "sg:classifiers":[
        {
            "category":"Retail",
            "subcategory":"Car Wash",
            "type":"Services"
        }
    ],
    "sg:phone":"+1 780 444 4040",
    "sg:postcode":"T6E 6B2",
    "sg:province":"AB",
    "sg:tags":[
        "polishing",
        "washing"
    ],
    "wof:name":"Hughes Petroleum Ltd",
    "wof:placetype":"venue"
},
  "geometry": {"coordinates":[-113.4868927,53.4691047668],"type":"Point"}
}