{
  "type": "Feature",
  "properties": {
    "iso:country":"CA",
    "sg:address":"2910 Glenmore Rd N",
    "sg:city":"Kelowna",
    "sg:classifiers":[
        {
            "category":"Wholesale",
            "subcategory":"Groceries",
            "type":"Manufacturing & Wholesale Goods"
        }
    ],
    "sg:phone":"+1 250 762 8156",
    "sg:postcode":"V1V 2B6",
    "sg:province":"BC",
    "sg:tags":[
        "honey"
    ],
    "wof:name":"Bill's Honey Farm",
    "wof:placetype":"venue"
},
  "geometry": {"coordinates":[-119.423606873,49.9757537842],"type":"Point"}
}