{
  "type": "Feature",
  "properties": {
    "addr:full":"2105 Richardson Rd Saskatoon SK S7L 4B9",
    "addr:housenumber":"2105",
    "addr:postcode":"s7l 4b9",
    "addr:street":"Richardson Rd",
    "iso:country":"CA",
    "sg:address":"2105 Richardson Rd",
    "sg:city":"Saskatoon",
    "sg:classifiers":[
        {
            "category":"Building & Trades",
            "subcategory":"Construction",
            "type":"Services"
        }
    ],
    "sg:phone":"+1 306 382 4306",
    "sg:postcode":"S7L 4B9",
    "sg:province":"SK",
    "sg:tags":[
        "painter"
    ],
    "wof:name":"Golden West Painting & Dcrtng",
    "wof:placetype":"venue"
},
  "geometry": {"coordinates":[-106.701286,52.147053],"type":"Point"}
}