{
  "type": "Feature",
  "properties": {
    "iso:country":"CA",
    "sg:address":"2105 Richardson Rd",
    "sg:city":"Saskatoon",
    "sg:classifiers":[
        {
            "category":"Building & Trades",
            "subcategory":"Construction",
            "type":"Services"
        }
    ],
    "sg:phone":"+1 306 382 4306",
    "sg:postcode":"S7L 4B9",
    "sg:province":"SK",
    "sg:tags":[
        "painter"
    ],
    "wof:name":"Golden West Painting & Dcrtng",
    "wof:placetype":"venue"
},
  "geometry": {"coordinates":[-106.701286,52.147053],"type":"Point"}
}