{
  "type": "Feature",
  "properties": {
    "addr:full":"384 Old Val D'Amour Rd # 16 Atholville NB E3N 4E3",
    "addr:housenumber":"384",
    "addr:postcode":"e3n 4e3",
    "addr:street":"Old Val D'Amour Rd # 16",
    "iso:country":"CA",
    "sg:address":"384 Old Val D'Amour Rd # 16",
    "sg:city":"Atholville",
    "sg:classifiers":[
        {
            "category":"Autos & Motor Vehicles",
            "subcategory":"Auto Supplies",
            "type":"Retail Goods"
        }
    ],
    "sg:phone":"+1 506 789 0222",
    "sg:postcode":"E3N 4E3",
    "sg:province":"NB",
    "sg:tags":[
        "automobile",
        "parts"
    ],
    "wof:name":"Canadian Tire",
    "wof:placetype":"venue"
},
  "geometry": {"coordinates":[-66.714119,47.99308],"type":"Point"}
}