{
  "type": "Feature",
  "properties": {
    "iso:country":"CA",
    "sg:address":"3786 Hwy 2",
    "sg:city":"Debert",
    "sg:classifiers":[
        {
            "category":"Building & Trades",
            "subcategory":"Plumbing",
            "type":"Services"
        }
    ],
    "sg:phone":"+1 902 662 4050",
    "sg:postcode":"B0M 1G0",
    "sg:province":"NS",
    "sg:tags":[
        "contractor"
    ],
    "wof:name":"Archibald's Plumbing & Heating",
    "wof:placetype":"venue"
},
  "geometry": {"coordinates":[-63.4477386475,45.430480957],"type":"Point"}
}