{
  "type": "Feature",
  "properties": {
    "addr:full":"1554 Johnston Rd White Rock BC V4B 3Z7",
    "addr:housenumber":"1554",
    "addr:postcode":"v4b 3z7",
    "addr:street":"Johnston Rd",
    "iso:country":"CA",
    "sg:address":"1554 Johnston Rd",
    "sg:city":"White Rock",
    "sg:classifiers":[
        {
            "category":"Wholesale",
            "subcategory":"Meat",
            "type":"Manufacturing & Wholesale Goods"
        }
    ],
    "sg:phone":"+1 604 531 1447",
    "sg:postcode":"V4B 3Z7",
    "sg:province":"BC",
    "wof:name":"Penguin Meat Supply Ltd",
    "wof:placetype":"venue"
},
  "geometry": {"coordinates":[-122.80096399999999,49.03038],"type":"Point"}
}