{
  "type": "Feature",
  "properties": {
    "addr:full":"3650 Lobsinger Line St Clements ON N0B 2M0",
    "addr:housenumber":"3650",
    "addr:postcode":"n0b 2m0",
    "addr:street":"Lobsinger Line St Clements",
    "iso:country":"CA",
    "sg:address":"3650 Lobsinger Line",
    "sg:city":"St Clements",
    "sg:classifiers":[
        {
            "category":"Autos & Motor Vehicles",
            "subcategory":"Fuel & Gas Station",
            "type":"Retail Goods"
        }
    ],
    "sg:phone":"+1 519 699 6211",
    "sg:postcode":"N0B 2M0",
    "sg:province":"ON",
    "sg:tags":[
        "oil"
    ],
    "wof:name":"St Clements Plaza Shell Inc",
    "wof:placetype":"venue"
},
  "geometry": {"coordinates":[-80.65539550779999,43.523223877],"type":"Point"}
}