{
  "type": "Feature",
  "properties": {
    "iso:country":"CA",
    "sg:address":"52405 Yale Rd",
    "sg:city":"Rosedale",
    "sg:classifiers":[
        {
            "category":"Wholesale",
            "subcategory":"Construction Materials",
            "type":"Manufacturing & Wholesale Goods"
        }
    ],
    "sg:phone":"+1 604 794 7488",
    "sg:postcode":"V0X 1X0",
    "sg:province":"BC",
    "sg:tags":[
        "sand",
        "gravel"
    ],
    "wof:name":"Armstrong Sand & Gravel Ltd",
    "wof:placetype":"venue"
},
  "geometry": {"coordinates":[-121.783111572,49.1838607788],"type":"Point"}
}