{
  "type": "Feature",
  "properties": {
    "addr:full":"PO Box 1225 STN Main Cold Lake AB T9M 1P3",
    "addr:housenumber":"po",
    "addr:postcode":"t9m 1p3",
    "addr:street":"Box 1225 Stn Main",
    "iso:country":"CA",
    "sg:address":"PO Box 1225 STN Main",
    "sg:city":"Cold Lake",
    "sg:classifiers":[
        {
            "category":"Building & Trades",
            "subcategory":"Construction",
            "type":"Services"
        }
    ],
    "sg:phone":"+1 780 639 3997",
    "sg:postcode":"T9M 1P3",
    "sg:province":"AB",
    "sg:tags":[
        "builder",
        "deck"
    ],
    "wof:name":"Deck-Aids Western Ltd",
    "wof:placetype":"venue"
},
  "geometry": {"coordinates":[-110.17379,54.465027],"type":"Point"}
}