{
  "type": "Feature",
  "properties": {
    "iso:country":"CA",
    "sg:address":"250 Wincott Dr",
    "sg:city":"Etobicoke",
    "sg:classifiers":[
        {
            "category":"Personal",
            "subcategory":"Beauty Salon",
            "type":"Services"
        }
    ],
    "sg:phone":"+1 416 244 6775",
    "sg:postcode":"M9R 2R5",
    "sg:province":"ON",
    "wof:name":"Kingsway Beauty & Skin Care",
    "wof:placetype":"venue"
},
  "geometry": {"coordinates":[-79.5455780029,43.6796951294],"type":"Point"}
}