{
  "type": "Feature",
  "properties": {
    "addr:full":"1698 75th Ave W Vancouver BC V6P 6G2",
    "addr:housenumber":"1698",
    "addr:postcode":"v6p 6g2",
    "addr:street":"75Th Ave W",
    "iso:country":"CA",
    "sg:address":"1698 75th Ave W",
    "sg:city":"Vancouver",
    "sg:classifiers":[
        {
            "category":"Manufacturing",
            "subcategory":"Rubber & Plastics",
            "type":"Manufacturing & Wholesale Goods"
        }
    ],
    "sg:phone":"+1 604 263 1562",
    "sg:postcode":"V6P 6G2",
    "sg:province":"BC",
    "sg:tags":[
        "grease",
        "seal"
    ],
    "wof:name":"Progressive Sealing Inc",
    "wof:placetype":"venue"
},
  "geometry": {"coordinates":[-123.146919251,49.2061653137],"type":"Point"}
}