{
  "type": "Feature",
  "properties": {
    "addr:full":"925 Lena Ave Windsor ON N9C 3K1",
    "addr:housenumber":"925",
    "addr:postcode":"n9c 3k1",
    "addr:street":"Lena Ave",
    "iso:country":"CA",
    "sg:address":"925 Lena Ave",
    "sg:city":"Windsor",
    "sg:classifiers":[
        {
            "category":"Social Services",
            "type":"Services"
        }
    ],
    "sg:phone":"+1 519 971 9489",
    "sg:postcode":"N9C 3K1",
    "sg:province":"ON",
    "sg:tags":[
        "counselor",
        "marriage",
        "family"
    ],
    "wof:name":"Gallant, Wilf PhD",
    "wof:placetype":"venue"
},
  "geometry": {"coordinates":[-83.0674133301,42.2968482971],"type":"Point"}
}