{
  "type": "Feature",
  "properties": {
    "addr:full":"Brampton ON L6V 1P8",
    "addr:postcode":"l6v 1p8",
    "iso:country":"CA",
    "sg:city":"Brampton",
    "sg:classifiers":[
        {
            "category":"Social Services",
            "subcategory":"Job Training",
            "type":"Services"
        }
    ],
    "sg:phone":"+1 905 457 7475",
    "sg:postcode":"L6V 1P8",
    "sg:province":"ON",
    "sg:tags":[
        "physiotherapist",
        "rehabilitation"
    ],
    "wof:name":"Action Physiotherapy Clinic",
    "wof:placetype":"venue"
},
  "geometry": {"coordinates":[-79.76988220210001,43.6935157776],"type":"Point"}
}