{
  "type": "Feature",
  "properties": {
    "iso:country":"CA",
    "sg:address":"9000 Boul Ray-Lawson",
    "sg:city":"Anjou",
    "sg:classifiers":[
        {
            "category":"Professional",
            "subcategory":"Computer Services",
            "type":"Services"
        }
    ],
    "sg:phone":"+1 514 356 3456",
    "sg:postcode":"H1J 1K8",
    "sg:province":"QC",
    "sg:tags":[
        "consultant"
    ],
    "wof:name":"Ordinateurs Pour Les Ecoles",
    "wof:placetype":"venue"
},
  "geometry": {"coordinates":[-73.5634460449,45.6170578003],"type":"Point"}
}