{
  "type": "Feature",
  "properties": {
    "addr:full":"Fredericton NB E3C 1A2",
    "addr:postcode":"e3c 1a2",
    "iso:country":"CA",
    "sg:city":"Fredericton",
    "sg:classifiers":[
        {
            "category":"Shopping",
            "subcategory":"Computers & Home Electronics",
            "type":"Retail Goods"
        }
    ],
    "sg:phone":"+1 506 450 1188",
    "sg:postcode":"E3C 1A2",
    "sg:province":"NB",
    "sg:tags":[
        "high",
        "television",
        "stereophonic",
        "fidelity"
    ],
    "wof:name":"Sony Store",
    "wof:placetype":"venue"
},
  "geometry": {"coordinates":[-66.66302490229999,45.9331932068],"type":"Point"}
}