{
  "type": "Feature",
  "properties": {
    "addr:full":"Mont-Saint-Hilaire QC J3H 3N4",
    "addr:postcode":"j3h 3n4",
    "iso:country":"CA",
    "sg:city":"Mont-Saint-Hilaire",
    "sg:classifiers":[
        {
            "category":"Travel",
            "subcategory":"Hotels & Motels",
            "type":"Entertainment"
        }
    ],
    "sg:phone":"+1 450 467 2891",
    "sg:postcode":"J3H 3N4",
    "sg:province":"QC",
    "wof:name":"Motel St Hilaire Engr",
    "wof:placetype":"venue"
},
  "geometry": {"coordinates":[-73.1951751709,45.562915802],"type":"Point"}
}