{
  "type": "Feature",
  "properties": {
    "addr:full":"95 Rue Sherbrooke Magog QC J1X 2R3",
    "addr:housenumber":"95",
    "addr:postcode":"j1x 2r3",
    "addr:street":"Rue Sherbrooke",
    "iso:country":"CA",
    "sg:address":"95 Rue Sherbrooke",
    "sg:city":"Magog",
    "sg:classifiers":[
        {
            "category":"Retail",
            "subcategory":"Auto Repair",
            "type":"Services"
        }
    ],
    "sg:phone":"+1 819 843 3588",
    "sg:postcode":"J1X 2R3",
    "sg:province":"QC",
    "sg:tags":[
        "repairing",
        "automobile"
    ],
    "wof:name":"Garage Lagrandeur & Fils Inc",
    "wof:placetype":"venue"
},
  "geometry": {"coordinates":[-72.14653800000001,45.265953],"type":"Point"}
}