{
  "type": "Feature",
  "properties": {
    "addr:full":"4206 Bloor St W Etobicoke ON M9C 1Z4",
    "addr:housenumber":"4206",
    "addr:postcode":"m9c 1z4",
    "addr:street":"Bloor St W",
    "iso:country":"CA",
    "sg:address":"4206 Bloor St W",
    "sg:city":"Etobicoke",
    "sg:classifiers":[
        {
            "category":"Health Services",
            "subcategory":"Medical Lab",
            "type":"Services"
        }
    ],
    "sg:phone":"+1 416 626 1432",
    "sg:postcode":"M9C 1Z4",
    "sg:province":"ON",
    "wof:name":"Bloor West Denture Clinic",
    "wof:placetype":"venue"
},
  "geometry": {"coordinates":[-79.5627670288,43.6356544495],"type":"Point"}
}