{
  "type": "Feature",
  "properties": {
    "addr:full":"22736 28 Ave Langley BC V2Z 3B2",
    "addr:housenumber":"22736",
    "addr:postcode":"v2z 3b2",
    "addr:street":"28 Ave",
    "iso:country":"CA",
    "sg:address":"22736 28 Ave",
    "sg:city":"Langley",
    "sg:classifiers":[
        {
            "category":"Autos & Motor Vehicles",
            "subcategory":"Auto Supplies",
            "type":"Retail Goods"
        }
    ],
    "sg:phone":"+1 604 530 3970",
    "sg:postcode":"V2Z 3B2",
    "sg:province":"BC",
    "sg:tags":[
        "tire"
    ],
    "wof:name":"Transpo Tire Distr Inc",
    "wof:placetype":"venue"
},
  "geometry": {"coordinates":[-122.595535,49.052555],"type":"Point"}
}