{
  "type": "Feature",
  "properties": {
    "addr:full":"Nelson BC V1L 4B6",
    "addr:postcode":"bc v1l 4b6",
    "iso:country":"CA",
    "sg:city":"Nelson",
    "sg:classifiers":[
        {
            "category":"Shopping",
            "subcategory":"Clothing, Apparel, & Fashions",
            "type":"Retail Goods"
        }
    ],
    "sg:phone":"+1 250 352 2501",
    "sg:postcode":"V1L 4B6",
    "sg:province":"BC",
    "wof:name":"Strutter's Styles Ltd",
    "wof:placetype":"venue"
},
  "geometry": {"coordinates":[-117.294486999,49.4946708679],"type":"Point"}
}