{
  "type": "Feature",
  "properties": {
    "iso:country":"CA",
    "sg:address":"142 Cross Ave",
    "sg:city":"Oakville",
    "sg:classifiers":[
        {
            "category":"Retail",
            "subcategory":"Auto Repair",
            "type":"Services"
        }
    ],
    "sg:phone":"+1 905 845 0666",
    "sg:postcode":"L6J 2W6",
    "sg:province":"ON",
    "sg:tags":[
        "repairing",
        "automobile"
    ],
    "wof:name":"Cross Avenue Auto",
    "wof:placetype":"venue"
},
  "geometry": {"coordinates":[-79.685516,43.45462],"type":"Point"}
}