{
  "type": "Feature",
  "properties": {
    "addr:full":"2929 Av Jeanne-D'Arc Montreal QC H1W 3W2",
    "addr:housenumber":"2929",
    "addr:postcode":"h1w 3w2",
    "addr:street":"Av Jeanne-D'Arc",
    "iso:country":"CA",
    "sg:address":"2929 Av Jeanne-D'Arc",
    "sg:city":"Montreal",
    "sg:classifiers":[
        {
            "category":"Organizations",
            "subcategory":"Professional Association",
            "type":"Services"
        }
    ],
    "sg:phone":"+1 514 899 9979",
    "sg:postcode":"H1W 3W2",
    "sg:province":"QC",
    "wof:name":"Atelier D'Histoire Hochelaga",
    "wof:placetype":"venue"
},
  "geometry": {"coordinates":[-73.5533905029,45.5534286499],"type":"Point"}
}