{
  "type": "Feature",
  "properties": {
    "addr:full":"406 Lakeshore Dr North Bay ON P1A 2C6",
    "addr:housenumber":"406",
    "addr:postcode":"p1a 2c6",
    "addr:street":"Lakeshore Dr",
    "iso:country":"CA",
    "sg:address":"406 Lakeshore Dr",
    "sg:city":"North Bay",
    "sg:classifiers":[
        {
            "category":"Shopping",
            "type":"Retail Goods"
        }
    ],
    "sg:phone":"+1 705 472 2698",
    "sg:postcode":"P1A 2C6",
    "sg:province":"ON",
    "sg:tags":[
        "pet",
        "food",
        "supply"
    ],
    "wof:name":"Global Pet Foods",
    "wof:placetype":"venue"
},
  "geometry": {"coordinates":[-79.445679,46.277725],"type":"Point"}
}