{
  "type": "Feature",
  "properties": {
    "addr:full":"10943 84 Ave NW Edmonton AB T6G 0V5",
    "addr:housenumber":"10943",
    "addr:postcode":"t6g 0v5",
    "addr:street":"84 Ave Nw",
    "iso:country":"CA",
    "sg:address":"10943 84 Ave NW",
    "sg:city":"Edmonton",
    "sg:classifiers":[
        {
            "category":"Shopping",
            "type":"Retail Goods"
        }
    ],
    "sg:phone":"+1 780 496 6955",
    "sg:postcode":"T6G 0V5",
    "sg:province":"AB",
    "sg:tags":[
        "government",
        "art",
        "dealer",
        "gallery"
    ],
    "wof:name":"Edmonton City Arts Ctr",
    "wof:placetype":"venue"
},
  "geometry": {"coordinates":[-113.513778687,53.5198936462],"type":"Point"}
}