{
  "type": "Feature",
  "properties": {
    "iso:country":"CA",
    "sg:address":"151 230 Rte",
    "sg:city":"LA Pocatiere",
    "sg:classifiers":[
        {
            "category":"Retail",
            "subcategory":"Auto Repair",
            "type":"Services"
        }
    ],
    "sg:phone":"+1 418 856 6323",
    "sg:postcode":"G0R 1Z0",
    "sg:province":"QC",
    "sg:tags":[
        "repairing",
        "glass",
        "automobile"
    ],
    "wof:name":"Centre Du Pare-Brise Ml",
    "wof:placetype":"venue"
},
  "geometry": {"coordinates":[-70.0480499268,47.3597450256],"type":"Point"}
}