{
  "type": "Feature",
  "properties": {
    "addr:full":"NW 14 8 1E Sanford MB R0G 2J0",
    "addr:housenumber":"8",
    "addr:postcode":"r0g 2j0",
    "addr:street":"Nw 14",
    "iso:country":"CA",
    "sg:address":"NW 14 8 1E",
    "sg:city":"Sanford",
    "sg:classifiers":[
        {
            "category":"Education",
            "subcategory":"School",
            "type":"Public Place"
        }
    ],
    "sg:phone":"+1 204 736 4223",
    "sg:postcode":"R0G 2J0",
    "sg:province":"MB",
    "wof:name":"Vermillion School",
    "wof:placetype":"venue"
},
  "geometry": {"coordinates":[-97.4463729858,49.6804656982],"type":"Point"}
}