{
  "type": "Feature",
  "properties": {
    "addr:full":"4 Paget Rd Brampton ON L6T 5G3",
    "addr:housenumber":"4",
    "addr:postcode":"l6t 5g3",
    "addr:street":"Paget Rd",
    "iso:country":"CA",
    "sg:address":"4 Paget Rd",
    "sg:city":"Brampton",
    "sg:classifiers":[
        {
            "category":"Wholesale",
            "subcategory":"Electrical",
            "type":"Manufacturing & Wholesale Goods"
        }
    ],
    "sg:phone":"+1 905 791 9977",
    "sg:postcode":"L6T 5G3",
    "sg:province":"ON",
    "sg:tags":[
        "equipment",
        "electronic",
        "supply"
    ],
    "wof:name":"Mektronix Systems Corp",
    "wof:placetype":"venue"
},
  "geometry": {"coordinates":[-79.65570099999999,43.734631],"type":"Point"}
}