{
  "type": "Feature",
  "properties": {
    "addr:full":"11651 71 St NW Edmonton AB T5B 1W3",
    "addr:housenumber":"11651",
    "addr:postcode":"t5b 1w3",
    "addr:street":"71 St Nw",
    "iso:country":"CA",
    "sg:address":"11651 71 St NW",
    "sg:city":"Edmonton",
    "sg:classifiers":[
        {
            "category":"Building & Trades",
            "subcategory":"Cleaning & Sanitation",
            "type":"Services"
        }
    ],
    "sg:phone":"+1 780 477 3311",
    "sg:postcode":"T5B 1W3",
    "sg:province":"AB",
    "sg:tags":[
        "janitor"
    ],
    "wof:name":"Scandinavian Building Svc Ltd",
    "wof:placetype":"venue"
},
  "geometry": {"coordinates":[-113.450676,53.569492],"type":"Point"}
}