{
  "type": "Feature",
  "properties": {
    "addr:full":"Cambridge ON N1R 8K9",
    "addr:postcode":"n1r 8k9",
    "iso:country":"CA",
    "sg:city":"Cambridge",
    "sg:classifiers":[
        {
            "category":"Wholesale",
            "subcategory":"Machinery & Supplies",
            "type":"Manufacturing & Wholesale Goods"
        }
    ],
    "sg:phone":"+1 519 624 6888",
    "sg:postcode":"N1R 8K9",
    "sg:province":"ON",
    "sg:tags":[
        "compressor",
        "gas"
    ],
    "wof:name":"Delta Compressor CO",
    "wof:placetype":"venue"
},
  "geometry": {"coordinates":[-80.29389999999999,43.359959],"type":"Point"}
}