{
  "type": "Feature",
  "properties": {
    "addr:full":"Saint-Jean-Sur-Richelieu QC J3B 8J3",
    "addr:postcode":"j3b 8j3",
    "iso:country":"CA",
    "sg:city":"Saint-Jean-Sur-Richelieu",
    "sg:classifiers":[
        {
            "category":"Professional",
            "subcategory":"Lawyer & Legal Services",
            "type":"Services"
        }
    ],
    "sg:phone":"+1 450 348 1994",
    "sg:postcode":"J3B 8J3",
    "sg:province":"QC",
    "sg:tags":[
        "attorney"
    ],
    "wof:name":"Gagne, Carole",
    "wof:placetype":"venue"
},
  "geometry": {"coordinates":[-73.26406860349999,45.3254966736],"type":"Point"}
}