{
  "type": "Feature",
  "properties": {
    "addr:full":"4917 50th St Forestburg AB T0B 1N0",
    "addr:housenumber":"4917",
    "addr:postcode":"t0b 1n0",
    "addr:street":"50Th St",
    "iso:country":"CA",
    "sg:address":"4917 50th St",
    "sg:city":"Forestburg",
    "sg:classifiers":[
        {
            "category":"Retail",
            "subcategory":"Auto Repair",
            "type":"Services"
        }
    ],
    "sg:phone":"+1 780 582 3530",
    "sg:postcode":"T0B 1N0",
    "sg:province":"AB",
    "sg:tags":[
        "body",
        "automobile",
        "painting"
    ],
    "wof:name":"Ross' Body Shop",
    "wof:placetype":"venue"
},
  "geometry": {"coordinates":[-112.0625,52.5837135315],"type":"Point"}
}