{
  "type": "Feature",
  "properties": {
    "addr:full":"Huntsville ON P1H 2J6",
    "addr:postcode":"p1h 2j6",
    "iso:country":"CA",
    "sg:city":"Huntsville",
    "sg:classifiers":[
        {
            "category":"Building & Trades",
            "subcategory":"Construction",
            "type":"Services"
        }
    ],
    "sg:phone":"+1 705 789 8231",
    "sg:postcode":"P1H 2J6",
    "sg:province":"ON",
    "sg:tags":[
        "general",
        "contractor"
    ],
    "wof:name":"J M Construction",
    "wof:placetype":"venue"
},
  "geometry": {"coordinates":[-79.218002,45.326565],"type":"Point"}
}