{
  "type": "Feature",
  "properties": {
    "addr:full":"133 Cedar St S Timmins ON P4N 2G9",
    "addr:housenumber":"133",
    "addr:postcode":"p4n 2g9",
    "addr:street":"Cedar St S",
    "iso:country":"CA",
    "sg:address":"133 Cedar St S",
    "sg:city":"Timmins",
    "sg:classifiers":[
        {
            "category":"Government",
            "subcategory":"Office",
            "type":"Public Place"
        }
    ],
    "sg:phone":"+1 ",
    "sg:postcode":"P4N 2G9",
    "sg:province":"ON",
    "sg:tags":[
        "fire",
        "department",
        "village"
    ],
    "wof:name":"Timmins Fire Department",
    "wof:placetype":"venue"
},
  "geometry": {"coordinates":[-81.329758,48.473541],"type":"Point"}
}