{
  "type": "Feature",
  "properties": {
    "iso:country":"CA",
    "sg:address":"7135 Pacific Cir",
    "sg:city":"Mississauga",
    "sg:classifiers":[
        {
            "category":"Wholesale",
            "subcategory":"Hardware",
            "type":"Manufacturing & Wholesale Goods"
        }
    ],
    "sg:phone":"+1 905 670 7920",
    "sg:postcode":"L5T 2A8",
    "sg:province":"ON",
    "wof:name":"Blum Canada Ltd",
    "wof:placetype":"venue"
},
  "geometry": {"coordinates":[-79.68353271479999,43.6594238281],"type":"Point"}
}