{
  "type": "Feature",
  "properties": {
    "addr:full":"3646 Av Des Eglises Charny QC G6X 1X4",
    "addr:housenumber":"3646",
    "addr:postcode":"g6x 1x4",
    "addr:street":"Av Des Eglises",
    "iso:country":"CA",
    "sg:address":"3646 Av Des Eglises",
    "sg:city":"Charny",
    "sg:classifiers":[
        {
            "category":"Shopping",
            "subcategory":"Bicycles & Sporting Goods",
            "type":"Retail Goods"
        }
    ],
    "sg:phone":"+1 418 832 6455",
    "sg:postcode":"G6X 1X4",
    "sg:province":"QC",
    "wof:name":"Centre Du Bicycle Rive-Sud",
    "wof:placetype":"venue"
},
  "geometry": {"coordinates":[-71.2678070068,46.7186889648],"type":"Point"}
}