{
  "type": "Feature",
  "properties": {
    "addr:full":"23 Boul Perron O Caplan QC G0C 1H0",
    "addr:housenumber":"23",
    "addr:postcode":"g0c 1h0",
    "addr:street":"Boul Perron O",
    "iso:country":"CA",
    "sg:address":"23 Boul Perron O",
    "sg:city":"Caplan",
    "sg:classifiers":[
        {
            "category":"Professional",
            "subcategory":"Business Services",
            "type":"Services"
        }
    ],
    "sg:phone":"+1 418 388 5225",
    "sg:postcode":"G0C 1H0",
    "sg:province":"QC",
    "sg:tags":[
        "notary"
    ],
    "wof:name":"Tremblay Barriault",
    "wof:placetype":"venue"
},
  "geometry": {"coordinates":[-65.6791687012,48.1013031006],"type":"Point"}
}