{
  "type": "Feature",
  "properties": {
    "addr:full":"64 Miller St Toronto ON M6N 2Z9",
    "addr:housenumber":"64",
    "addr:postcode":"m6n 2z9",
    "addr:street":"Miller St",
    "iso:country":"CA",
    "sg:address":"64 Miller St",
    "sg:city":"Toronto",
    "sg:classifiers":[
        {
            "category":"Building & Trades",
            "subcategory":"Construction",
            "type":"Services"
        }
    ],
    "sg:phone":"+1 416 656 9554",
    "sg:postcode":"M6N 2Z9",
    "sg:province":"ON",
    "sg:tags":[
        "woodworker"
    ],
    "wof:name":"David Forster Fine Woodworking",
    "wof:placetype":"venue"
},
  "geometry": {"coordinates":[-79.46021270750001,43.6688613892],"type":"Point"}
}