{
  "type": "Feature",
  "properties": {
    "iso:country":"CA",
    "sg:address":"255 Av Evangeline",
    "sg:city":"Sept-Iles",
    "sg:classifiers":[
        {
            "category":"Retail",
            "subcategory":"Veterinary Services",
            "type":"Services"
        }
    ],
    "sg:phone":"+1 418 968 5841",
    "sg:postcode":"G4R 2N1",
    "sg:province":"QC",
    "sg:tags":[
        "veterinarian"
    ],
    "wof:name":"Clinique Veterinaire Cote-Nord",
    "wof:placetype":"venue"
},
  "geometry": {"coordinates":[-66.3765792847,50.203578949],"type":"Point"}
}