{
  "type": "Feature",
  "properties": {
    "addr:full":"RR 2 STN Main Namao AB T0A 2N0",
    "addr:postcode":"t0a 2n0",
    "addr:street":"Rr 2 Stn Main",
    "iso:country":"CA",
    "sg:address":"RR 2 STN Main",
    "sg:city":"Namao",
    "sg:classifiers":[
        {
            "category":"Retail",
            "subcategory":"Repair Shop",
            "type":"Services"
        }
    ],
    "sg:phone":"+1 780 973 6963",
    "sg:postcode":"T0A 2N0",
    "sg:province":"AB",
    "sg:tags":[
        "equipment",
        "laundry"
    ],
    "wof:name":"Belvedere Technical Svc",
    "wof:placetype":"venue"
},
  "geometry": {"coordinates":[-113.450356,53.686771],"type":"Point"}
}