{
  "type": "Feature",
  "properties": {
    "addr:full":"Winnipeg MB R2J 4A9",
    "addr:postcode":"r2j 4a9",
    "iso:country":"CA",
    "sg:city":"Winnipeg",
    "sg:classifiers":[
        {
            "category":"Food & Beverages",
            "subcategory":"Bakery",
            "type":"Retail Goods"
        }
    ],
    "sg:phone":"+1 204 257 2590",
    "sg:postcode":"R2J 4A9",
    "sg:province":"MB",
    "sg:tags":[
        "baker"
    ],
    "wof:name":"Mc Gavin's Bread Baskets",
    "wof:placetype":"venue"
},
  "geometry": {"coordinates":[-97.0712890625,49.854259491],"type":"Point"}
}