{
  "type": "Feature",
  "properties": {
    "addr:full":"10714 124 St NW Edmonton AB T5M 0H1",
    "addr:housenumber":"10714",
    "addr:postcode":"t5m 0h1",
    "addr:street":"124 St Nw",
    "iso:country":"CA",
    "sg:address":"10714 124 St NW",
    "sg:city":"Edmonton",
    "sg:classifiers":[
        {
            "category":"Shopping",
            "subcategory":"Used Merchandise",
            "type":"Retail Goods"
        }
    ],
    "sg:phone":"+1 780 448 2787",
    "sg:postcode":"T5M 0H1",
    "sg:province":"AB",
    "sg:tags":[
        "pawnbroker"
    ],
    "wof:name":"Dan's Exchange",
    "wof:placetype":"venue"
},
  "geometry": {"coordinates":[-113.536109924,53.5513000488],"type":"Point"}
}