{
  "type": "Feature",
  "properties": {
    "addr:full":"162 Houlton Rd Woodstock NB E7M 1Z1",
    "addr:housenumber":"162",
    "addr:postcode":"e7m 1z1",
    "addr:street":"Houlton Rd",
    "iso:country":"CA",
    "sg:address":"162 Houlton Rd",
    "sg:city":"Woodstock",
    "sg:classifiers":[
        {
            "category":"Shopping",
            "subcategory":"Used Merchandise",
            "type":"Retail Goods"
        }
    ],
    "sg:phone":"+1 506 324 9810",
    "sg:postcode":"E7M 1Z1",
    "sg:province":"NB",
    "sg:tags":[
        "second",
        "store",
        "hand"
    ],
    "wof:name":"Global Textile",
    "wof:placetype":"venue"
},
  "geometry": {"coordinates":[-67.587272644,46.1449813843],"type":"Point"}
}