{
  "type": "Feature",
  "properties": {
    "addr:full":"Blainville QC J7C 2K5",
    "addr:postcode":"j7c 2k5",
    "iso:country":"CA",
    "sg:city":"Blainville",
    "sg:classifiers":[
        {
            "category":"Professional",
            "subcategory":"Business Services",
            "type":"Services"
        }
    ],
    "sg:phone":"+1 450 434 1061",
    "sg:postcode":"J7C 2K5",
    "sg:province":"QC",
    "sg:tags":[
        "interior",
        "consultant",
        "design",
        "decorator"
    ],
    "wof:name":"Vertisoleil Inc",
    "wof:placetype":"venue"
},
  "geometry": {"coordinates":[-73.8688659668,45.6665611267],"type":"Point"}
}