{
  "type": "Feature",
  "properties": {
    "addr:full":"10832 Rue Saint-Urbain Montreal QC H3L 2V3",
    "addr:housenumber":"10832",
    "addr:postcode":"h3l 2v3",
    "addr:street":"Rue Saint-Urbain",
    "iso:country":"CA",
    "sg:address":"10832 Rue Saint-Urbain",
    "sg:city":"Montreal",
    "sg:classifiers":[
        {
            "category":"Wholesale",
            "subcategory":"Durable Goods & Equipment",
            "type":"Manufacturing & Wholesale Goods"
        }
    ],
    "sg:phone":"+1 514 332 2274",
    "sg:postcode":"H3L 2V3",
    "sg:province":"QC",
    "sg:tags":[
        "representative",
        "manufacturer"
    ],
    "wof:name":"Agence Celine Chrusten",
    "wof:placetype":"venue"
},
  "geometry": {"coordinates":[-73.673912,45.549297],"type":"Point"}
}