{
  "type": "Feature",
  "properties": {
    "iso:country":"CA",
    "sg:address":"10 Coulter St #3",
    "sg:city":"Barrie",
    "sg:classifiers":[
        {
            "category":"Real Estate",
            "subcategory":"Real Estate Operator",
            "type":"Services"
        }
    ],
    "sg:phone":"+1 705 721 9194",
    "sg:postcode":"L4N 6S2",
    "sg:province":"ON",
    "sg:tags":[
        "condominium"
    ],
    "wof:name":"Sunnidale Terrace Condominiums",
    "wof:placetype":"venue"
},
  "geometry": {"coordinates":[-79.70117999999999,44.399281],"type":"Point"}
}