{
  "type": "Feature",
  "properties": {
    "addr:full":"121 Pettingill Rd Quispamsis NB E2E 2T8",
    "addr:housenumber":"121",
    "addr:postcode":"e2e 2t8",
    "addr:street":"Pettingill Rd",
    "iso:country":"CA",
    "sg:address":"121 Pettingill Rd",
    "sg:city":"Quispamsis",
    "sg:classifiers":[
        {
            "category":"Retail",
            "subcategory":"Auto Repair",
            "type":"Services"
        }
    ],
    "sg:phone":"+1 506 652 9960",
    "sg:postcode":"E2E 2T8",
    "sg:province":"NB",
    "sg:tags":[
        "wrecker"
    ],
    "wof:name":"Cmv Towing & Recovery Ltd",
    "wof:placetype":"venue"
},
  "geometry": {"coordinates":[-65.970947,45.419434],"type":"Point"}
}