{
  "type": "Feature",
  "properties": {
    "addr:full":"420 2E Av Iberville QC J2X 2B8",
    "addr:housenumber":"420",
    "addr:postcode":"j2x 2b8",
    "addr:street":"2E Av",
    "iso:country":"CA",
    "sg:address":"420 2E Av",
    "sg:city":"Iberville",
    "sg:classifiers":[
        {
            "category":"Personal",
            "subcategory":"Beauty Salon",
            "type":"Services"
        }
    ],
    "sg:phone":"+1 450 358 4777",
    "sg:postcode":"J2X 2B8",
    "sg:province":"QC",
    "wof:name":"Salon Lancelot",
    "wof:placetype":"venue"
},
  "geometry": {"coordinates":[-73.2292480469,45.3042602539],"type":"Point"}
}