{
  "type": "Feature",
  "properties": {
    "iso:country":"CA",
    "sg:address":"2150 Maple St",
    "sg:city":"Vancouver",
    "sg:classifiers":[
        {
            "category":"Organizations",
            "subcategory":"Professional Association",
            "type":"Services"
        }
    ],
    "sg:phone":"+1 604 874 0649",
    "sg:postcode":"V6J 3T3",
    "sg:province":"BC",
    "wof:name":"Vancouver Committee-Domestic",
    "wof:placetype":"venue"
},
  "geometry": {"coordinates":[-123.150146,49.26683],"type":"Point"}
}