{
  "type": "Feature",
  "properties": {
    "addr:full":"5121 Hwy 10 New Germany NS B0R 1E0",
    "addr:housenumber":"5121",
    "addr:postcode":"b0r 1e0",
    "addr:street":"Hwy 10",
    "iso:country":"CA",
    "sg:address":"5121 Hwy 10",
    "sg:city":"New Germany",
    "sg:classifiers":[
        {
            "category":"Home & Garden",
            "subcategory":"Household Appliances",
            "type":"Retail Goods"
        }
    ],
    "sg:phone":"+1 902 644 2330",
    "sg:postcode":"B0R 1E0",
    "sg:province":"NS",
    "wof:name":"Ritcey's Electric Appliances",
    "wof:placetype":"venue"
},
  "geometry": {"coordinates":[-64.71772,44.544041],"type":"Point"}
}