{
  "type": "Feature",
  "properties": {
    "addr:full":"Farm Govan SK S0G 1Z0",
    "addr:postcode":"s0g 1z0",
    "iso:country":"CA",
    "sg:address":"Farm",
    "sg:city":"Govan",
    "sg:classifiers":[
        {
            "category":"Farming",
            "subcategory":"Farm & Veterinary Services",
            "type":"Manufacturing & Wholesale Goods"
        }
    ],
    "sg:phone":"+1 306 484 2010",
    "sg:postcode":"S0G 1Z0",
    "sg:province":"SK",
    "sg:tags":[
        "seed",
        "grain",
        "cleaning"
    ],
    "wof:name":"Sundwall Seed Svc",
    "wof:placetype":"venue"
},
  "geometry": {"coordinates":[-104.991844,51.311275],"type":"Point"}
}