{
  "type": "Feature",
  "properties": {
    "addr:full":"245 Edinburgh Rd N Guelph ON N1H 5S2",
    "addr:housenumber":"245",
    "addr:postcode":"n1h 5s2",
    "addr:street":"Edinburgh Rd N",
    "iso:country":"CA",
    "sg:address":"245 Edinburgh Rd N",
    "sg:city":"Guelph",
    "sg:classifiers":[
        {
            "category":"Retail",
            "subcategory":"Car Wash",
            "type":"Services"
        }
    ],
    "sg:phone":"+1 519 836 3240",
    "sg:postcode":"N1H 5S2",
    "sg:province":"ON",
    "sg:tags":[
        "polishing",
        "washing"
    ],
    "wof:name":"Rainbow Car Wash & Gas Bar",
    "wof:placetype":"venue"
},
  "geometry": {"coordinates":[-80.26778411870001,43.5446815491],"type":"Point"}
}