{
  "type": "Feature",
  "properties": {
    "addr:full":"411 Cooper St Ottawa ON K2P 0H1",
    "addr:housenumber":"411",
    "addr:postcode":"k2p 0h1",
    "addr:street":"Cooper St",
    "iso:country":"CA",
    "sg:address":"411 Cooper St",
    "sg:city":"Ottawa",
    "sg:classifiers":[
        {
            "category":"Shopping",
            "subcategory":"Music",
            "type":"Retail Goods"
        }
    ],
    "sg:phone":"+1 613 230 4586",
    "sg:postcode":"K2P 0H1",
    "sg:province":"ON",
    "sg:tags":[
        "compact",
        "record",
        "disc",
        "tape"
    ],
    "wof:name":"Turning Point",
    "wof:placetype":"venue"
},
  "geometry": {"coordinates":[-75.697571,45.415958],"type":"Point"}
}