{
  "type": "Feature",
  "properties": {
    "addr:full":"254 271 Rte Saint-Benoit-Labre QC G0M 1P0",
    "addr:housenumber":"271",
    "addr:postcode":"g0m 1p0",
    "addr:street":"Rte Saint-Benoit-Labre",
    "iso:country":"CA",
    "sg:address":"254 271 Rte",
    "sg:city":"Saint-Benoit-Labre",
    "sg:classifiers":[
        {
            "category":"Personal",
            "subcategory":"Beauty Salon",
            "type":"Services"
        }
    ],
    "sg:phone":"+1 418 228 4313",
    "sg:postcode":"G0M 1P0",
    "sg:province":"QC",
    "wof:name":"Salon Claudette",
    "wof:placetype":"venue"
},
  "geometry": {"coordinates":[-70.791039,46.0704],"type":"Point"}
}