{
  "type": "Feature",
  "properties": {
    "addr:full":"170 6E Ave Senneterre QC J0Y 2M0",
    "addr:housenumber":"170",
    "addr:postcode":"j0y 2m0",
    "addr:street":"6E Ave",
    "iso:country":"CA",
    "sg:address":"170 6E Ave",
    "sg:city":"Senneterre",
    "sg:classifiers":[
        {
            "category":"Government",
            "subcategory":"Office",
            "type":"Public Place"
        }
    ],
    "sg:phone":"+1 819 737 3223",
    "sg:postcode":"J0Y 2M0",
    "sg:province":"QC",
    "sg:tags":[
        "village"
    ],
    "wof:name":"Senneterre Batiment Technique",
    "wof:placetype":"venue"
},
  "geometry": {"coordinates":[-77.222565,48.385616],"type":"Point"}
}