{
  "type": "Feature",
  "properties": {
    "addr:full":"454 Locust St Burlington ON L7S 1V1",
    "addr:housenumber":"454",
    "addr:postcode":"l7s 1v1",
    "addr:street":"Locust St",
    "iso:country":"CA",
    "sg:address":"454 Locust St",
    "sg:city":"Burlington",
    "sg:classifiers":[
        {
            "category":"Personal",
            "subcategory":"Beauty Salon",
            "type":"Services"
        }
    ],
    "sg:phone":"+1 905 333 0449",
    "sg:postcode":"L7S 1V1",
    "sg:province":"ON",
    "sg:tags":[
        "manicuring"
    ],
    "wof:name":"Erlene's Nail Design",
    "wof:placetype":"venue"
},
  "geometry": {"coordinates":[-79.7989730835,43.3250045776],"type":"Point"}
}