{
  "type": "Feature",
  "properties": {
    "addr:full":"Vilna AB T0A 3L0",
    "addr:postcode":"t0a 3l0",
    "iso:country":"CA",
    "sg:city":"Vilna",
    "sg:classifiers":[
        {
            "category":"Restaurant",
            "type":"Food & Drink"
        }
    ],
    "sg:phone":"+1 780 636 2726",
    "sg:postcode":"T0A 3L0",
    "sg:province":"AB",
    "wof:name":"Z Side Street Cafe",
    "wof:placetype":"venue"
},
  "geometry": {"coordinates":[-111.92166137700001,54.1162605286],"type":"Point"}
}