{
  "type": "Feature",
  "properties": {
    "iso:country":"CA",
    "sg:address":"990 Copeland St",
    "sg:city":"North Bay",
    "sg:classifiers":[
        {
            "category":"Building & Trades",
            "subcategory":"Construction",
            "type":"Services"
        }
    ],
    "sg:phone":"+1 705 474 8741",
    "sg:postcode":"P1B 3E4",
    "sg:province":"ON",
    "sg:tags":[
        "carpenter",
        "contractor"
    ],
    "wof:name":"Precision Woodworks",
    "wof:placetype":"venue"
},
  "geometry": {"coordinates":[-79.474609375,46.320690155],"type":"Point"}
}