{
  "type": "Feature",
  "properties": {
    "addr:full":"168 Mcdougald St Sault Ste Marie ON P6A 3A8",
    "addr:housenumber":"168",
    "addr:postcode":"p6a 3a8",
    "addr:street":"Mcdougald St",
    "iso:country":"CA",
    "sg:address":"168 Mcdougald St",
    "sg:city":"Sault Ste Marie",
    "sg:classifiers":[
        {
            "category":"Organizations",
            "subcategory":"Professional Association",
            "type":"Services"
        }
    ],
    "sg:phone":"+1 705 759 6653",
    "sg:postcode":"P6A 3A8",
    "sg:province":"ON",
    "wof:name":"Ontario Secondary School Tchrs",
    "wof:placetype":"venue"
},
  "geometry": {"coordinates":[-84.328148,46.511063],"type":"Point"}
}