{
  "type": "Feature",
  "properties": {
    "iso:country":"CA",
    "sg:address":"891 Rue Saint-Francois-Xavier",
    "sg:city":"Terrebonne",
    "sg:classifiers":[
        {
            "category":"Health Services",
            "subcategory":"Health Practitioner",
            "type":"Services"
        }
    ],
    "sg:phone":"+1 450 964 6841",
    "sg:postcode":"J6W 1H1",
    "sg:province":"QC",
    "sg:tags":[
        "psychologist"
    ],
    "wof:name":"Fortier, Francine",
    "wof:placetype":"venue"
},
  "geometry": {"coordinates":[-73.6369552612,45.6933326721],"type":"Point"}
}