{
  "type": "Feature",
  "properties": {
    "addr:full":"272 Michel Cir Vanier ON K1L 7P3",
    "addr:housenumber":"272",
    "addr:postcode":"k1l 7p3",
    "addr:street":"Michel Cir",
    "iso:country":"CA",
    "sg:address":"272 Michel Cir",
    "sg:city":"Vanier",
    "sg:classifiers":[
        {
            "category":"Wholesale",
            "subcategory":"Non-durable Goods",
            "type":"Manufacturing & Wholesale Goods"
        }
    ],
    "sg:phone":"+1 613 749 5272",
    "sg:postcode":"K1L 7P3",
    "sg:province":"ON",
    "sg:tags":[
        "advertising"
    ],
    "wof:name":"J C Marketing",
    "wof:placetype":"venue"
},
  "geometry": {"coordinates":[-75.665047,45.444061],"type":"Point"}
}