{
  "type": "Feature",
  "properties": {
    "addr:full":"1002 Rue Deschaillons Sherbrooke QC J1G 1X7",
    "addr:housenumber":"1002",
    "addr:postcode":"j1g 1x7",
    "addr:street":"Rue Deschaillons",
    "iso:country":"CA",
    "sg:address":"1002 Rue Deschaillons",
    "sg:city":"Sherbrooke",
    "sg:classifiers":[
        {
            "category":"Building & Trades",
            "subcategory":"Construction",
            "type":"Services"
        }
    ],
    "sg:phone":"+1 819 562 8667",
    "sg:postcode":"J1G 1X7",
    "sg:province":"QC",
    "sg:tags":[
        "acoustical",
        "contractor"
    ],
    "wof:name":"Experts Acoustique Inc",
    "wof:placetype":"venue"
},
  "geometry": {"coordinates":[-71.866631,45.398476],"type":"Point"}
}