{
  "type": "Feature",
  "properties": {
    "addr:full":"3625 Shaganappi Trail NW Calgary AB T3A 0E2",
    "addr:housenumber":"3625",
    "addr:postcode":"t3a 0e2",
    "addr:street":"Shaganappi Trail Nw",
    "iso:country":"CA",
    "sg:address":"3625 Shaganappi Trail NW",
    "sg:city":"Calgary",
    "sg:classifiers":[
        {
            "category":"Shopping",
            "subcategory":"Hobbies, Toys, & Games",
            "type":"Retail Goods"
        }
    ],
    "sg:phone":"+1 403 974 8683",
    "sg:postcode":"T3A 0E2",
    "sg:province":"AB",
    "wof:name":"Toys R US",
    "wof:placetype":"venue"
},
  "geometry": {"coordinates":[-114.153137207,51.0852966309],"type":"Point"}
}