{
  "type": "Feature",
  "properties": {
    "addr:full":"2325 Cambie St Vancouver BC V5Z 2T9",
    "addr:housenumber":"2325",
    "addr:postcode":"v5z 2t9",
    "addr:street":"Cambie St",
    "iso:country":"CA",
    "sg:address":"2325 Cambie St",
    "sg:city":"Vancouver",
    "sg:classifiers":[
        {
            "category":"Restaurant",
            "type":"Food & Drink"
        }
    ],
    "sg:phone":"+1 604 732 3939",
    "sg:postcode":"V5Z 2T9",
    "sg:province":"BC",
    "wof:name":"Chao Phraya Thai Restaurant",
    "wof:placetype":"venue"
},
  "geometry": {"coordinates":[-123.114952,49.264679],"type":"Point"}
}