{
  "type": "Feature",
  "properties": {
    "addr:full":"24 Cavehill Cres Scarborough ON M1R 4P9",
    "addr:housenumber":"24",
    "addr:postcode":"m1r 4p9",
    "addr:street":"Cavehill Cres",
    "iso:country":"CA",
    "sg:address":"24 Cavehill Cres",
    "sg:city":"Scarborough",
    "sg:classifiers":[
        {
            "category":"Professional",
            "subcategory":"Advertising",
            "type":"Services"
        }
    ],
    "sg:phone":"+1 416 447 6646",
    "sg:postcode":"M1R 4P9",
    "sg:province":"ON",
    "sg:tags":[
        "mail"
    ],
    "wof:name":"Toronto Advertising",
    "wof:placetype":"venue"
},
  "geometry": {"coordinates":[-79.3103179932,43.7667732239],"type":"Point"}
}