{
  "type": "Feature",
  "properties": {
    "addr:full":"5620 Timberlea Blvd Mississauga ON L4W 4M6",
    "addr:housenumber":"5620",
    "addr:postcode":"l4w 4m6",
    "addr:street":"Timberlea Blvd",
    "iso:country":"CA",
    "sg:address":"5620 Timberlea Blvd",
    "sg:city":"Mississauga",
    "sg:classifiers":[
        {
            "category":"Wholesale",
            "subcategory":"Machinery & Supplies",
            "type":"Manufacturing & Wholesale Goods"
        }
    ],
    "sg:phone":"+1 905 890 3231",
    "sg:postcode":"L4W 4M6",
    "sg:province":"ON",
    "sg:tags":[
        "machine",
        "tool"
    ],
    "wof:name":"Ferro Technique Ltd",
    "wof:placetype":"venue"
},
  "geometry": {"coordinates":[-79.65046691889999,43.6363487244],"type":"Point"}
}