{
  "type": "Feature",
  "properties": {
    "addr:full":"251 Schoolhouse St Coquitlam BC V3K 4Y1",
    "addr:housenumber":"251",
    "addr:postcode":"v3k 4y1",
    "addr:street":"Schoolhouse St",
    "iso:country":"CA",
    "sg:address":"251 Schoolhouse St",
    "sg:city":"Coquitlam",
    "sg:classifiers":[
        {
            "category":"Manufacturing",
            "subcategory":"Metals",
            "type":"Manufacturing & Wholesale Goods"
        }
    ],
    "sg:phone":"+1 604 525 2673",
    "sg:postcode":"V3K 4Y1",
    "sg:province":"BC",
    "sg:tags":[
        "fence"
    ],
    "wof:name":"Steelguard Fence Ltd",
    "wof:placetype":"venue"
},
  "geometry": {"coordinates":[-122.852287,49.238117],"type":"Point"}
}