{
  "type": "Feature",
  "properties": {
    "addr:full":"1835 4th Ave W Vancouver BC V6J 1M4",
    "addr:housenumber":"1835",
    "addr:postcode":"v6j 1m4",
    "addr:street":"4Th Ave W",
    "iso:country":"CA",
    "sg:address":"1835 4th Ave W",
    "sg:city":"Vancouver",
    "sg:classifiers":[
        {
            "category":"Restaurant",
            "type":"Food & Drink"
        }
    ],
    "sg:phone":"+1 604 734 5777",
    "sg:postcode":"V6J 1M4",
    "sg:province":"BC",
    "wof:name":"India Grill Restaurant",
    "wof:placetype":"venue"
},
  "geometry": {"coordinates":[-123.146476746,49.2682571411],"type":"Point"}
}