{
  "type": "Feature",
  "properties": {
    "addr:full":"3725 Webster Cres Maidstone ON N0R 1K0",
    "addr:housenumber":"3725",
    "addr:postcode":"n0r 1k0",
    "addr:street":"Webster Cres",
    "iso:country":"CA",
    "sg:address":"3725 Webster Cres",
    "sg:city":"Maidstone",
    "sg:classifiers":[
        {
            "category":"Wholesale",
            "subcategory":"Auto Parts",
            "type":"Manufacturing & Wholesale Goods"
        }
    ],
    "sg:phone":"+1 519 737 7995",
    "sg:postcode":"N0R 1K0",
    "sg:province":"ON",
    "sg:tags":[
        "equipment",
        "truck"
    ],
    "wof:name":"Traction",
    "wof:placetype":"venue"
},
  "geometry": {"coordinates":[-82.890511,42.210068],"type":"Point"}
}