{
  "type": "Feature",
  "properties": {
    "addr:full":"588 Sargent Ave Winnipeg MB R3E 0A1",
    "addr:housenumber":"588",
    "addr:postcode":"r3e 0a1",
    "addr:street":"Sargent Ave",
    "iso:country":"CA",
    "sg:address":"588 Sargent Ave",
    "sg:city":"Winnipeg",
    "sg:classifiers":[
        {
            "category":"Banks & Credit Unions",
            "subcategory":"Bank",
            "type":"Services"
        }
    ],
    "sg:phone":"+1 204 988 6370",
    "sg:postcode":"R3E 0A1",
    "sg:province":"MB",
    "wof:name":"Royal Bank Financial Group",
    "wof:placetype":"venue"
},
  "geometry": {"coordinates":[-97.1587142944,49.8964729309],"type":"Point"}
}