{
  "type": "Feature",
  "properties": {
    "addr:full":"5810 Rue Sherbrooke E Montreal QC H1N 1B2",
    "addr:housenumber":"5810",
    "addr:postcode":"h1n 1b2",
    "addr:street":"Rue Sherbrooke E",
    "iso:country":"CA",
    "sg:address":"5810 Rue Sherbrooke E",
    "sg:city":"Montreal",
    "sg:classifiers":[
        {
            "category":"Social Services",
            "type":"Services"
        }
    ],
    "sg:phone":"+1 514 255 2365",
    "sg:postcode":"H1N 1B2",
    "sg:province":"QC",
    "sg:tags":[
        "organization",
        "welfare"
    ],
    "wof:name":"Clsc Olivier-Guimond",
    "wof:placetype":"venue"
},
  "geometry": {"coordinates":[-73.547744751,45.5748291016],"type":"Point"}
}