{
  "type": "Feature",
  "properties": {
    "addr:full":"Rouyn-Noranda QC J9X 4P1",
    "addr:postcode":"j9x 4p1",
    "iso:country":"CA",
    "sg:city":"Rouyn-Noranda",
    "sg:classifiers":[
        {
            "category":"Food & Beverages",
            "subcategory":"Groceries & Convenience Stores",
            "type":"Retail Goods"
        }
    ],
    "sg:phone":"+1 819 797 8927",
    "sg:postcode":"J9X 4P1",
    "sg:province":"QC",
    "wof:name":"Variete Depanneur Centre-Ville",
    "wof:placetype":"venue"
},
  "geometry": {"coordinates":[-79.0198135376,48.2408180237],"type":"Point"}
}