{
  "type": "Feature",
  "properties": {
    "addr:full":"417 Rue St Laurent Saint-Simeon QC G0T 1X0",
    "addr:housenumber":"417",
    "addr:postcode":"g0t 1x0",
    "addr:street":"Rue St Laurent Saint-Simeon",
    "iso:country":"CA",
    "sg:address":"417 Rue St Laurent",
    "sg:city":"Saint-Simeon",
    "sg:classifiers":[
        {
            "category":"Banks & Credit Unions",
            "subcategory":"Bank",
            "type":"Services"
        }
    ],
    "sg:phone":"+1 418 638 2493",
    "sg:postcode":"G0T 1X0",
    "sg:province":"QC",
    "wof:name":"Caisse Desjardins",
    "wof:placetype":"venue"
},
  "geometry": {"coordinates":[-69.8806610107,47.8410835266],"type":"Point"}
}