{
  "type": "Feature",
  "properties": {
    "addr:full":"7783 Wiltshire Blvd Delta BC V4C 4B2",
    "addr:housenumber":"7783",
    "addr:postcode":"v4c 4b2",
    "addr:street":"Wiltshire Blvd",
    "iso:country":"CA",
    "sg:address":"7783 Wiltshire Blvd",
    "sg:city":"Delta",
    "sg:classifiers":[
        {
            "category":"Building & Trades",
            "subcategory":"Plumbing",
            "type":"Services"
        }
    ],
    "sg:phone":"+1 604 594 1719",
    "sg:postcode":"V4C 4B2",
    "sg:province":"BC",
    "sg:tags":[
        "mechanical",
        "contractor"
    ],
    "wof:name":"Essex Mechanical Systems Ltd",
    "wof:placetype":"venue"
},
  "geometry": {"coordinates":[-122.92472100000001,49.145096],"type":"Point"}
}