{
  "type": "Feature",
  "properties": {
    "addr:full":"7217 Girard Rd NW Edmonton AB T6B 2C5",
    "addr:housenumber":"7217",
    "addr:postcode":"t6b 2c5",
    "addr:street":"Girard Rd Nw",
    "iso:country":"CA",
    "sg:address":"7217 Girard Rd NW",
    "sg:city":"Edmonton",
    "sg:classifiers":[
        {
            "category":"Manufacturing",
            "subcategory":"Tools & Machinery",
            "type":"Manufacturing & Wholesale Goods"
        }
    ],
    "sg:phone":"+1 780 463 0026",
    "sg:postcode":"T6B 2C5",
    "sg:province":"AB",
    "sg:tags":[
        "material",
        "handling",
        "scale"
    ],
    "wof:name":"Precision Giant Systems Inc",
    "wof:placetype":"venue"
},
  "geometry": {"coordinates":[-113.43950700000001,53.508453],"type":"Point"}
}