{
  "type": "Feature",
  "properties": {
    "addr:full":"870 Danforth Ave Toronto ON M4J 1L7",
    "addr:housenumber":"870",
    "addr:postcode":"m4j 1l7",
    "addr:street":"Danforth Ave",
    "iso:country":"CA",
    "sg:address":"870 Danforth Ave",
    "sg:city":"Toronto",
    "sg:classifiers":[
        {
            "category":"Professional",
            "subcategory":"Lawyer & Legal Services",
            "type":"Services"
        }
    ],
    "sg:phone":"+1 416 469 5355",
    "sg:postcode":"M4J 1L7",
    "sg:province":"ON",
    "sg:tags":[
        "attorney"
    ],
    "wof:name":"Pantazis, Demetrius",
    "wof:placetype":"venue"
},
  "geometry": {"coordinates":[-79.3399505615,43.6800117493],"type":"Point"}
}