{
  "type": "Feature",
  "properties": {
    "addr:full":"9368 120 St Surrey BC V3V 4B9",
    "addr:housenumber":"9368",
    "addr:postcode":"v3v 4b9",
    "addr:street":"120 St",
    "iso:country":"CA",
    "sg:address":"9368 120 St",
    "sg:city":"Surrey",
    "sg:classifiers":[
        {
            "category":"Banks & Credit Unions",
            "subcategory":"Bank",
            "type":"Services"
        }
    ],
    "sg:phone":"+1 604 583 3363",
    "sg:postcode":"V3V 4B9",
    "sg:province":"BC",
    "wof:name":"State Bank of India Canada",
    "wof:placetype":"venue"
},
  "geometry": {"coordinates":[-122.89003,49.173363],"type":"Point"}
}