{
  "type": "Feature",
  "properties": {
    "iso:country":"CA",
    "sg:address":"1171 Ambleside Dr",
    "sg:city":"Ottawa",
    "sg:classifiers":[
        {
            "category":"Real Estate",
            "subcategory":"Real Estate Operator",
            "type":"Services"
        }
    ],
    "sg:phone":"+1 613 828 7838",
    "sg:postcode":"K2B 8E1",
    "sg:province":"ON",
    "sg:tags":[
        "condominium"
    ],
    "wof:name":"Ambleside Two",
    "wof:placetype":"venue"
},
  "geometry": {"coordinates":[-75.7820358276,45.3723754883],"type":"Point"}
}