{
  "type": "Feature",
  "properties": {
    "iso:country":"CA",
    "sg:address":"595 Toronto St",
    "sg:city":"Palmerston",
    "sg:classifiers":[
        {
            "category":"Manufacturing",
            "subcategory":"Tools & Machinery",
            "type":"Manufacturing & Wholesale Goods"
        }
    ],
    "sg:phone":"+1 519 343 2503",
    "sg:postcode":"N0G 2P0",
    "sg:province":"ON",
    "sg:tags":[
        "filtering",
        "material",
        "supply"
    ],
    "wof:name":"Skj Mfg Ltd",
    "wof:placetype":"venue"
},
  "geometry": {"coordinates":[-80.842628479,43.827041626],"type":"Point"}
}