{
  "type": "Feature",
  "properties": {
    "addr:full":"170 East St # 203S Sault Ste Marie ON P6A 3C6",
    "addr:housenumber":"170",
    "addr:postcode":"p6a 3c6",
    "addr:street":"East St # 203S",
    "iso:country":"CA",
    "sg:address":"170 East St # 203S",
    "sg:city":"Sault Ste Marie",
    "sg:classifiers":[
        {
            "category":"Health Services",
            "subcategory":"Doctor",
            "type":"Services"
        }
    ],
    "sg:phone":"+1 705 759 3388",
    "sg:postcode":"P6A 3C6",
    "sg:province":"ON",
    "sg:tags":[
        "physician",
        "surgeon"
    ],
    "wof:name":"Mossing, M S MD",
    "wof:placetype":"venue"
},
  "geometry": {"coordinates":[-84.325821,46.508862],"type":"Point"}
}