{
  "type": "Feature",
  "properties": {
    "addr:full":"12 Goodyear Ave Grand Falls-Windsor NL A2A 1H8",
    "addr:housenumber":"12",
    "addr:postcode":"a2a 1h8",
    "addr:street":"Goodyear Ave",
    "iso:country":"CA",
    "sg:address":"12 Goodyear Ave",
    "sg:city":"Grand Falls-Windsor",
    "sg:classifiers":[
        {
            "category":"Personal",
            "subcategory":"Beauty Salon",
            "type":"Services"
        }
    ],
    "sg:phone":"+1 709 489 4646",
    "sg:postcode":"A2A 1H8",
    "sg:province":"NL",
    "wof:name":"Sheila's Beauty Salon",
    "wof:placetype":"venue"
},
  "geometry": {"coordinates":[-55.641166687,48.9342765808],"type":"Point"}
}