{
  "type": "Feature",
  "properties": {
    "iso:country":"CA",
    "sg:address":"1 Sandcliffe Terr",
    "sg:city":"Nepean",
    "sg:classifiers":[
        {
            "category":"Professional",
            "subcategory":"Art Services",
            "type":"Services"
        }
    ],
    "sg:phone":"+1 613 723 3400",
    "sg:postcode":"K2G 5X1",
    "sg:province":"ON",
    "sg:tags":[
        "photographer"
    ],
    "wof:name":"Teckles Photography Inc",
    "wof:placetype":"venue"
},
  "geometry": {"coordinates":[-75.768776,45.338806],"type":"Point"}
}