{
  "type": "Feature",
  "properties": {
    "iso:country":"CA",
    "sg:city":"New Westminster",
    "sg:classifiers":[
        {
            "category":"Health Services",
            "subcategory":"Doctor",
            "type":"Services"
        }
    ],
    "sg:phone":"+1 604 522 3121",
    "sg:postcode":"V3L 3C4",
    "sg:province":"BC",
    "sg:tags":[
        "dentist"
    ],
    "wof:name":"Staines, Robert L DDS",
    "wof:placetype":"venue"
},
  "geometry": {"coordinates":[-122.921326,49.213745],"type":"Point"}
}