{
  "type": "Feature",
  "properties": {
    "iso:country":"CA",
    "sg:city":"Wadena",
    "sg:classifiers":[
        {
            "category":"Organizations",
            "subcategory":"Religious Organization",
            "type":"Services"
        }
    ],
    "sg:phone":"+1 306 338 2423",
    "sg:postcode":"S0A 4J0",
    "sg:province":"SK",
    "sg:tags":[
        "church"
    ],
    "wof:name":"St Paul Lutheran Church",
    "wof:placetype":"venue"
},
  "geometry": {"coordinates":[-103.803031921,51.9453659058],"type":"Point"}
}