{
  "type": "Feature",
  "properties": {
    "addr:full":"119 Simmonds Dr Dartmouth NS B3B 1N7",
    "addr:housenumber":"119",
    "addr:postcode":"b3b 1n7",
    "addr:street":"Simmonds Dr",
    "iso:country":"CA",
    "sg:address":"119 Simmonds Dr",
    "sg:city":"Dartmouth",
    "sg:classifiers":[
        {
            "category":"Wholesale",
            "subcategory":"Machinery & Supplies",
            "type":"Manufacturing & Wholesale Goods"
        }
    ],
    "sg:phone":"+1 902 468 6636",
    "sg:postcode":"B3B 1N7",
    "sg:province":"NS",
    "sg:tags":[
        "equipment",
        "material",
        "truck",
        "handling"
    ],
    "wof:name":"S & B Hydraulics",
    "wof:placetype":"venue"
},
  "geometry": {"coordinates":[-63.6018981934,44.7160797119],"type":"Point"}
}