{
  "type": "Feature",
  "properties": {
    "addr:full":"545 Wilson Ave North York ON M3H 1V2",
    "addr:housenumber":"545",
    "addr:postcode":"m3h 1v2",
    "addr:street":"Wilson Ave",
    "iso:country":"CA",
    "sg:address":"545 Wilson Ave",
    "sg:city":"North York",
    "sg:classifiers":[
        {
            "category":"Social Services",
            "subcategory":"Job Training",
            "type":"Services"
        }
    ],
    "sg:phone":"+1 416 633 6383",
    "sg:postcode":"M3H 1V2",
    "sg:province":"ON",
    "sg:tags":[
        "rehabilitation"
    ],
    "wof:name":"New Age Recovery & Wellness",
    "wof:placetype":"venue"
},
  "geometry": {"coordinates":[-79.44760100000001,43.734352],"type":"Point"}
}