{
  "type": "Feature",
  "properties": {
    "addr:full":"Cornwall PE C0A 1H0",
    "addr:postcode":"c0a 1h0",
    "iso:country":"CA",
    "sg:city":"Cornwall",
    "sg:classifiers":[
        {
            "category":"Professional",
            "subcategory":"Lawyer & Legal Services",
            "type":"Services"
        }
    ],
    "sg:phone":"+1 902 675 2359",
    "sg:postcode":"C0A 1H0",
    "sg:province":"PE",
    "sg:tags":[
        "attorney"
    ],
    "wof:name":"Robert Mac Arthur Law Office",
    "wof:placetype":"venue"
},
  "geometry": {"coordinates":[-63.218075,46.22768],"type":"Point"}
}