{
  "type": "Feature",
  "properties": {
    "iso:country":"CA",
    "sg:address":"2882 Douglas St",
    "sg:city":"Victoria",
    "sg:classifiers":[
        {
            "category":"Retail",
            "subcategory":"Auto Repair",
            "type":"Services"
        }
    ],
    "sg:phone":"+1 250 383 3353",
    "sg:postcode":"V8T 4M9",
    "sg:province":"BC",
    "sg:tags":[
        "wheel",
        "axle",
        "tire"
    ],
    "wof:name":"Scotia Automotive-At Firestone",
    "wof:placetype":"venue"
},
  "geometry": {"coordinates":[-123.368629,48.441174],"type":"Point"}
}