{
  "type": "Feature",
  "properties": {
    "addr:full":"Chesterfield Inlet NU X0C 0B0",
    "addr:postcode":"x0c 0b0",
    "addr:street":"Chesterfield Inlet",
    "iso:country":"CA",
    "sg:city":"Chesterfield Inlet",
    "sg:classifiers":[
        {
            "category":"Government",
            "subcategory":"Office",
            "type":"Public Place"
        }
    ],
    "sg:phone":"+1 867 898 9131",
    "sg:postcode":"X0C 0B0",
    "sg:province":"NU",
    "wof:name":"N T Social Svc",
    "wof:placetype":"venue"
},
  "geometry": {"coordinates":[-90.70715332029999,63.339641571],"type":"Point"}
}