{
  "type": "Feature",
  "properties": {
    "addr:full":"Prince Albert SK S6V 2N2",
    "addr:postcode":"s6v 2n2",
    "iso:country":"CA",
    "sg:city":"Prince Albert",
    "sg:classifiers":[
        {
            "category":"Personal",
            "subcategory":"Beauty Salon",
            "type":"Services"
        }
    ],
    "sg:phone":"+1 306 763 6718",
    "sg:postcode":"S6V 2N2",
    "sg:province":"SK",
    "wof:name":"Cassy's",
    "wof:placetype":"venue"
},
  "geometry": {"coordinates":[-105.711929,53.207348],"type":"Point"}
}