{
  "type": "Feature",
  "properties": {
    "addr:full":"34660 103rd St Oliver BC V0H 1T0",
    "addr:housenumber":"34660",
    "addr:postcode":"bc v0h 1t0",
    "addr:street":"103Rd St",
    "iso:country":"CA",
    "sg:address":"34660 103rd St",
    "sg:city":"Oliver",
    "sg:classifiers":[
        {
            "category":"Organizations",
            "subcategory":"Religious Organization",
            "type":"Services"
        }
    ],
    "sg:phone":"+1 250 498 2559",
    "sg:postcode":"V0H 1T0",
    "sg:province":"BC",
    "sg:tags":[
        "church"
    ],
    "wof:name":"St Edwards Anglican Church",
    "wof:placetype":"venue"
},
  "geometry": {"coordinates":[-119.555419922,49.1791381836],"type":"Point"}
}