{
  "type": "Feature",
  "properties": {
    "iso:country":"CA",
    "sg:address":"9224 82 St NW",
    "sg:city":"Edmonton",
    "sg:classifiers":[
        {
            "category":"Organizations",
            "subcategory":"Religious Organization",
            "type":"Services"
        }
    ],
    "sg:phone":"+1 780 469 2404",
    "sg:postcode":"T6C 2X3",
    "sg:province":"AB",
    "sg:tags":[
        "church"
    ],
    "wof:name":"First Church of God",
    "wof:placetype":"venue"
},
  "geometry": {"coordinates":[-113.453590393,53.5271186829],"type":"Point"}
}