{
  "type": "Feature",
  "properties": {
    "addr:full":"419 Rue Principale Lachute QC J8H 1Y1",
    "addr:housenumber":"419",
    "addr:postcode":"j8h 1y1",
    "addr:street":"Rue Principale",
    "iso:country":"CA",
    "sg:address":"419 Rue Principale",
    "sg:city":"Lachute",
    "sg:classifiers":[
        {
            "category":"Food & Beverages",
            "subcategory":"Groceries & Convenience Stores",
            "type":"Retail Goods"
        }
    ],
    "sg:phone":"+1 450 562 3613",
    "sg:postcode":"J8H 1Y1",
    "sg:province":"QC",
    "wof:name":"Depan-Escompte Couche-Tard",
    "wof:placetype":"venue"
},
  "geometry": {"coordinates":[-74.3375167847,45.6564559937],"type":"Point"}
}