{
  "type": "Feature",
  "properties": {
    "addr:full":"8120 Boul Decarie Montreal QC H4P 2S8",
    "addr:housenumber":"8120",
    "addr:postcode":"h4p 2s8",
    "addr:street":"Boul Decarie",
    "iso:country":"CA",
    "sg:address":"8120 Boul Decarie",
    "sg:city":"Montreal",
    "sg:classifiers":[
        {
            "category":"Wholesale",
            "subcategory":"Construction Materials",
            "type":"Manufacturing & Wholesale Goods"
        }
    ],
    "sg:phone":"+1 514 733 9925",
    "sg:postcode":"H4P 2S8",
    "sg:province":"QC",
    "sg:tags":[
        "tile"
    ],
    "wof:name":"Ardesia Carreaux",
    "wof:placetype":"venue"
},
  "geometry": {"coordinates":[-73.6597747803,45.4980392456],"type":"Point"}
}