{
  "type": "Feature",
  "properties": {
    "addr:full":"Centennial Sq Mount Pearl NL A1N 2C1",
    "addr:postcode":"a1n 2c1",
    "addr:street":"Centennial Sq",
    "iso:country":"CA",
    "sg:address":"Centennial Sq",
    "sg:city":"Mount Pearl",
    "sg:classifiers":[
        {
            "category":"Banks & Credit Unions",
            "subcategory":"Bank",
            "type":"Services"
        }
    ],
    "sg:phone":"+1 709 576 7796",
    "sg:postcode":"A1N 2C1",
    "sg:province":"NL",
    "wof:name":"Scotiabank",
    "wof:placetype":"venue"
},
  "geometry": {"coordinates":[-52.819725,47.516403],"type":"Point"}
}