{
  "type": "Feature",
  "properties": {
    "addr:full":"3007 Bathurst St North York ON M6B 3B3",
    "addr:housenumber":"3007",
    "addr:postcode":"m6b 3b3",
    "addr:street":"Bathurst St",
    "iso:country":"CA",
    "sg:address":"3007 Bathurst St",
    "sg:city":"North York",
    "sg:classifiers":[
        {
            "category":"Shopping",
            "type":"Retail Goods"
        }
    ],
    "sg:phone":"+1 416 781 8261",
    "sg:postcode":"M6B 3B3",
    "sg:province":"ON",
    "sg:tags":[
        "religious"
    ],
    "wof:name":"Miriam's Fine Judaica",
    "wof:placetype":"venue"
},
  "geometry": {"coordinates":[-79.4291687012,43.7174835205],"type":"Point"}
}