{
  "type": "Feature",
  "properties": {
    "addr:full":"1844 142 St Surrey BC V4A 7C3",
    "addr:housenumber":"1844",
    "addr:postcode":"v4a 7c3",
    "addr:street":"142 St",
    "iso:country":"CA",
    "sg:address":"1844 142 St",
    "sg:city":"Surrey",
    "sg:classifiers":[
        {
            "category":"Wholesale",
            "subcategory":"Durable Goods & Equipment",
            "type":"Manufacturing & Wholesale Goods"
        }
    ],
    "sg:phone":"+1 604 535 8118",
    "sg:postcode":"V4A 7C3",
    "sg:province":"BC",
    "sg:tags":[
        "representative",
        "manufacturer"
    ],
    "wof:name":"George Boon & Assoc",
    "wof:placetype":"venue"
},
  "geometry": {"coordinates":[-122.82976499999999,49.035515],"type":"Point"}
}