{
  "type": "Feature",
  "properties": {
    "addr:full":"2122 Conc 12 Ripley ON N0G 2R0",
    "addr:housenumber":"2122;12",
    "addr:postcode":"n0g 2r0",
    "addr:street":"Conc",
    "iso:country":"CA",
    "sg:address":"2122 Conc 12",
    "sg:city":"Ripley",
    "sg:classifiers":[
        {
            "category":"Wholesale",
            "subcategory":"Farm Supplies",
            "type":"Manufacturing & Wholesale Goods"
        }
    ],
    "sg:phone":"+1 519 395 2605",
    "sg:postcode":"N0G 2R0",
    "sg:province":"ON",
    "sg:tags":[
        "fertilizer"
    ],
    "wof:name":"Bluewater Agromart Ltd",
    "wof:placetype":"venue"
},
  "geometry": {"coordinates":[-81.577789,44.071129],"type":"Point"}
}