{
  "type": "Feature",
  "properties": {
    "addr:full":"1383 Coast Meridian Rd Port Coquitlam BC V3C 6L1",
    "addr:housenumber":"1383",
    "addr:postcode":"v3c 6l1",
    "addr:street":"Coast Meridian Rd",
    "iso:country":"CA",
    "sg:address":"1383 Coast Meridian Rd",
    "sg:city":"Port Coquitlam",
    "sg:classifiers":[
        {
            "category":"Building & Trades",
            "subcategory":"Construction",
            "type":"Services"
        }
    ],
    "sg:phone":"+1 604 941 9115",
    "sg:postcode":"V3C 6L1",
    "sg:province":"BC",
    "sg:tags":[
        "front",
        "store"
    ],
    "wof:name":"Glastech Contracting Ltd",
    "wof:placetype":"venue"
},
  "geometry": {"coordinates":[-122.754486,49.24197],"type":"Point"}
}