{
  "type": "Feature",
  "properties": {
    "addr:full":"139 Sheppard Ave E North York ON M2N 3A6",
    "addr:housenumber":"139",
    "addr:postcode":"m2n 3a6",
    "addr:street":"Sheppard Ave E",
    "iso:country":"CA",
    "sg:address":"139 Sheppard Ave E",
    "sg:city":"North York",
    "sg:classifiers":[
        {
            "category":"Health Services",
            "subcategory":"Clinic",
            "type":"Services"
        }
    ],
    "sg:phone":"+1 905 842 5584",
    "sg:postcode":"M2N 3A6",
    "sg:province":"ON",
    "sg:tags":[
        "home"
    ],
    "wof:name":"Selectacare Limited",
    "wof:placetype":"venue"
},
  "geometry": {"coordinates":[-79.40184021,43.7633781433],"type":"Point"}
}