{
  "type": "Feature",
  "properties": {
    "addr:full":"2500 County Rd 35 Pointe Aux Roches ON N0R 1N0",
    "addr:housenumber":"2500;35",
    "addr:postcode":"n0r 1n0",
    "addr:street":"County Rd;Aux Roches",
    "iso:country":"CA",
    "sg:address":"2500 County Rd 35",
    "sg:city":"Pointe Aux Roches",
    "sg:classifiers":[
        {
            "category":"Manufacturing",
            "subcategory":"Food",
            "type":"Manufacturing & Wholesale Goods"
        }
    ],
    "sg:phone":"+1 519 798 3025",
    "sg:postcode":"N0R 1N0",
    "sg:province":"ON",
    "sg:tags":[
        "canning"
    ],
    "wof:name":"Countryside Canners CO Ltd",
    "wof:placetype":"venue"
},
  "geometry": {"coordinates":[-82.5517120361,42.3142814636],"type":"Point"}
}