{
  "type": "Feature",
  "properties": {
    "addr:full":"Toronto ON M5T 2E3",
    "addr:postcode":"m5t 2e3",
    "iso:country":"CA",
    "sg:city":"Toronto",
    "sg:classifiers":[
        {
            "category":"Shopping",
            "subcategory":"Gifts & Souvenirs",
            "type":"Retail Goods"
        }
    ],
    "sg:phone":"+1 416 596 7978",
    "sg:postcode":"M5T 2E3",
    "sg:province":"ON",
    "sg:tags":[
        "shop"
    ],
    "wof:name":"Dragon Seed Ltd",
    "wof:placetype":"venue"
},
  "geometry": {"coordinates":[-79.397415,43.652134],"type":"Point"}
}