{
  "type": "Feature",
  "properties": {
    "addr:full":"243 Loch Lomond Rd Saint John NB E2J 1Y6",
    "addr:housenumber":"243",
    "addr:postcode":"e2j 1y6",
    "addr:street":"Loch Lomond Rd",
    "iso:country":"CA",
    "sg:address":"243 Loch Lomond Rd",
    "sg:city":"Saint John",
    "sg:classifiers":[
        {
            "category":"Health Services",
            "subcategory":"Doctor",
            "type":"Services"
        }
    ],
    "sg:phone":"+1 506 648 0606",
    "sg:postcode":"E2J 1Y6",
    "sg:province":"NB",
    "sg:tags":[
        "physician",
        "surgeon"
    ],
    "wof:name":"Acupuncture Clinic",
    "wof:placetype":"venue"
},
  "geometry": {"coordinates":[-66.0264663696,45.2911071777],"type":"Point"}
}