{
  "type": "Feature",
  "properties": {
    "addr:full":"Coquitlam BC V3E 3J7",
    "addr:postcode":"v3e 3j7",
    "iso:country":"CA",
    "sg:city":"Coquitlam",
    "sg:classifiers":[
        {
            "category":"Manufacturing",
            "subcategory":"Food",
            "type":"Manufacturing & Wholesale Goods"
        }
    ],
    "sg:phone":"+1 604 464 5009",
    "sg:postcode":"V3E 3J7",
    "sg:province":"BC",
    "sg:tags":[
        "winery",
        "wine"
    ],
    "wof:name":"Carol's Wine Inc",
    "wof:placetype":"venue"
},
  "geometry": {"coordinates":[-122.80304717999999,49.2968902588],"type":"Point"}
}