{
  "type": "Feature",
  "properties": {
    "addr:full":"PO Box 456 STN Main Cold Lake AB T9M 1P1",
    "addr:housenumber":"po",
    "addr:postcode":"t9m 1p1",
    "addr:street":"Box 456 Stn Main",
    "iso:country":"CA",
    "sg:address":"PO Box 456 STN Main",
    "sg:city":"Cold Lake",
    "sg:classifiers":[
        {
            "category":"Organizations",
            "subcategory":"Religious Organization",
            "type":"Services"
        }
    ],
    "sg:phone":"+1 403 639 2375",
    "sg:postcode":"T9M 1P1",
    "sg:province":"AB",
    "sg:tags":[
        "church"
    ],
    "wof:name":"Lakeland Lutheran Church",
    "wof:placetype":"venue"
},
  "geometry": {"coordinates":[-110.173789978,54.4650268555],"type":"Point"}
}