{
  "type": "Feature",
  "properties": {
    "addr:full":"Sioux Lookout ON P8T 1A1",
    "addr:postcode":"p8t 1a1",
    "iso:country":"CA",
    "sg:city":"Sioux Lookout",
    "sg:classifiers":[
        {
            "category":"Insurance",
            "subcategory":"Insurance Agent",
            "type":"Services"
        }
    ],
    "sg:phone":"+1 807 737 2550",
    "sg:postcode":"P8T 1A1",
    "sg:province":"ON",
    "wof:name":"Standard Insurance Brokers",
    "wof:placetype":"venue"
},
  "geometry": {"coordinates":[-91.9178161621,50.098941803],"type":"Point"}
}