{
  "type": "Feature",
  "properties": {
    "addr:full":"416 28 St NE Calgary AB T2A 6T3",
    "addr:postcode":"416 28;t2a 6t3",
    "addr:street":"St Ne",
    "iso:country":"CA",
    "sg:address":"416 28 St NE",
    "sg:city":"Calgary",
    "sg:classifiers":[
        {
            "category":"Wholesale",
            "subcategory":"Machinery & Supplies",
            "type":"Manufacturing & Wholesale Goods"
        }
    ],
    "sg:phone":"+1 403 273 8253",
    "sg:postcode":"T2A 6T3",
    "sg:province":"AB",
    "sg:tags":[
        "janitor"
    ],
    "wof:name":"Amclean Industrial Cleaning",
    "wof:placetype":"venue"
},
  "geometry": {"coordinates":[-113.993087769,51.0549621582],"type":"Point"}
}