{
  "type": "Feature",
  "properties": {
    "addr:full":"1941 Highway 69 N Val Caron ON P3N 1M1",
    "addr:housenumber":"1941",
    "addr:postcode":"p3n 1m1",
    "addr:street":"Highway 69 N",
    "iso:country":"CA",
    "sg:address":"1941 Highway 69 N",
    "sg:city":"Val Caron",
    "sg:classifiers":[
        {
            "category":"Building & Trades",
            "subcategory":"Landscaping Services",
            "type":"Services"
        }
    ],
    "sg:phone":"+1 705 897 5952",
    "sg:postcode":"P3N 1M1",
    "sg:province":"ON",
    "sg:tags":[
        "tree"
    ],
    "wof:name":"Complete Yard Care",
    "wof:placetype":"venue"
},
  "geometry": {"coordinates":[-81.008644,46.610432],"type":"Point"}
}