{
  "type": "Feature",
  "properties": {
    "addr:full":"10875 Av Moisan Montreal-Nord QC H1G 4N6",
    "addr:postcode":"h1g 4n6",
    "addr:street":"Av Moisan",
    "iso:country":"CA",
    "sg:address":"10875 Av Moisan",
    "sg:city":"Montreal-Nord",
    "sg:classifiers":[
        {
            "category":"Manufacturing",
            "subcategory":"Tools & Machinery",
            "type":"Manufacturing & Wholesale Goods"
        }
    ],
    "sg:phone":"+1 514 323 4841",
    "sg:postcode":"H1G 4N6",
    "sg:province":"QC",
    "sg:tags":[
        "machine",
        "shop"
    ],
    "wof:name":"Astro Machine Shop Ltd",
    "wof:placetype":"venue"
},
  "geometry": {"coordinates":[-73.616501,45.601921],"type":"Point"}
}