{
  "type": "Feature",
  "properties": {
    "iso:country":"CA",
    "sg:address":"6625 Airport Rd",
    "sg:city":"Mississauga",
    "sg:classifiers":[
        {
            "category":"Autos & Motor Vehicles",
            "subcategory":"Fuel & Gas Station",
            "type":"Retail Goods"
        }
    ],
    "sg:phone":"+1 905 677 5815",
    "sg:postcode":"L4V 1Y1",
    "sg:province":"ON",
    "sg:tags":[
        "polishing",
        "car",
        "oil",
        "washing"
    ],
    "wof:name":"Trillium Car Wash",
    "wof:placetype":"venue"
},
  "geometry": {"coordinates":[-79.6320571899,43.6962623596],"type":"Point"}
}