{
  "type": "Feature",
  "properties": {
    "addr:full":"Trois-Rivieres QC G9A 4M3",
    "addr:postcode":"g9a 4m3",
    "iso:country":"CA",
    "sg:city":"Trois-Rivieres",
    "sg:classifiers":[
        {
            "category":"Professional",
            "subcategory":"Management & Consulting",
            "type":"Services"
        }
    ],
    "sg:phone":"+1 819 691 3075",
    "sg:postcode":"G9A 4M3",
    "sg:province":"QC",
    "sg:tags":[
        "consultant",
        "business"
    ],
    "wof:name":"Urls DE LA Mauricie",
    "wof:placetype":"venue"
},
  "geometry": {"coordinates":[-72.556152,46.330292],"type":"Point"}
}