{
  "type": "Feature",
  "properties": {
    "addr:full":"London ON N6L 1G4",
    "addr:postcode":"n6l 1g4",
    "iso:country":"CA",
    "sg:city":"London",
    "sg:classifiers":[
        {
            "category":"Manufacturing",
            "subcategory":"Furniture",
            "type":"Manufacturing & Wholesale Goods"
        }
    ],
    "sg:phone":"+1 519 652 0184",
    "sg:postcode":"N6L 1G4",
    "sg:province":"ON",
    "sg:tags":[
        "upholsterer"
    ],
    "wof:name":"Schueneman's Design Systems",
    "wof:placetype":"venue"
},
  "geometry": {"coordinates":[-81.266312,42.919498],"type":"Point"}
}