{
  "type": "Feature",
  "properties": {
    "addr:full":"1270 Rue Brassard # A Longueuil QC J4M 1S8",
    "addr:housenumber":"1270",
    "addr:postcode":"j4m 1s8",
    "addr:street":"Rue Brassard # A",
    "iso:country":"CA",
    "sg:address":"1270 Rue Brassard # A",
    "sg:city":"Longueuil",
    "sg:classifiers":[
        {
            "category":"Professional",
            "subcategory":"Management & Consulting",
            "type":"Services"
        }
    ],
    "sg:phone":"+1 450 647 0094",
    "sg:postcode":"J4M 1S8",
    "sg:province":"QC",
    "sg:tags":[
        "marketing",
        "consultant"
    ],
    "wof:name":"Communications Pif Enr",
    "wof:placetype":"venue"
},
  "geometry": {"coordinates":[-73.44547271730001,45.5294532776],"type":"Point"}
}