{
  "type": "Feature",
  "properties": {
    "addr:full":"Morin-Heights QC J0R 1H0",
    "addr:postcode":"j0r 1h0",
    "iso:country":"CA",
    "sg:city":"Morin-Heights",
    "sg:classifiers":[
        {
            "category":"Shopping",
            "subcategory":"Computers & Home Electronics",
            "type":"Retail Goods"
        }
    ],
    "sg:phone":"+1 450 226 8865",
    "sg:postcode":"J0R 1H0",
    "sg:province":"QC",
    "sg:tags":[
        "equipment",
        "dealer"
    ],
    "wof:name":"Electronique Des Monts",
    "wof:placetype":"venue"
},
  "geometry": {"coordinates":[-74.25042000000001,45.902679],"type":"Point"}
}