{
  "type": "Feature",
  "properties": {
    "iso:country":"CA",
    "sg:address":"470 Boul Du Seminaire N",
    "sg:city":"Saint-Jean-Sur-Richelieu",
    "sg:classifiers":[
        {
            "category":"Retail",
            "subcategory":"Car Wash",
            "type":"Services"
        }
    ],
    "sg:phone":"+1 450 359 1777",
    "sg:postcode":"J3B 5L3",
    "sg:province":"QC",
    "sg:tags":[
        "polishing",
        "washing"
    ],
    "wof:name":"Salon DE L'Auto Enr",
    "wof:placetype":"venue"
},
  "geometry": {"coordinates":[-73.265015,45.314388],"type":"Point"}
}