{
  "type": "Feature",
  "properties": {
    "addr:full":"Saint-Marc-Du-Lac-Long QC G0L 1T0",
    "addr:postcode":"g0l 1t0",
    "iso:country":"CA",
    "sg:city":"Saint-Marc-Du-Lac-Long",
    "sg:classifiers":[
        {
            "category":"Food & Beverages",
            "subcategory":"Groceries & Convenience Stores",
            "type":"Retail Goods"
        }
    ],
    "sg:phone":"+1 418 893 2539",
    "sg:postcode":"G0L 1T0",
    "sg:province":"QC",
    "sg:tags":[
        "grocer"
    ],
    "wof:name":"Epicerie Cassistat",
    "wof:placetype":"venue"
},
  "geometry": {"coordinates":[-68.8972702026,47.3897628784],"type":"Point"}
}