{
  "type": "Feature",
  "properties": {
    "iso:country":"CA",
    "sg:city":"Windsor",
    "sg:classifiers":[
        {
            "category":"Freight",
            "type":"Transportation"
        }
    ],
    "sg:phone":"+1 519 977 9844",
    "sg:postcode":"N8T 1C1",
    "sg:province":"ON",
    "sg:tags":[
        "delivery",
        "mover"
    ],
    "wof:name":"A J Jackson's Movers",
    "wof:placetype":"venue"
},
  "geometry": {"coordinates":[-82.96418,42.308235],"type":"Point"}
}