{
  "type": "Feature",
  "properties": {
    "iso:country":"CA",
    "sg:city":"Brandon",
    "sg:classifiers":[
        {
            "category":"Government",
            "subcategory":"Office",
            "type":"Public Place"
        }
    ],
    "sg:phone":"+1 204 726 7665",
    "sg:postcode":"R7A 3X8",
    "sg:province":"MB",
    "wof:name":"Canadian Grain Commission",
    "wof:placetype":"venue"
},
  "geometry": {"coordinates":[-99.94853973390001,49.8413009644],"type":"Point"}
}