{
  "type": "Feature",
  "properties": {
    "addr:full":"Saint-Laurent QC H4R 2A8",
    "addr:postcode":"h4r 2a8",
    "iso:country":"CA",
    "sg:city":"Saint-Laurent",
    "sg:classifiers":[
        {
            "category":"Real Estate",
            "subcategory":"Real Estate Agent",
            "type":"Services"
        }
    ],
    "sg:phone":"+1 514 334 3755",
    "sg:postcode":"H4R 2A8",
    "sg:province":"QC",
    "sg:tags":[
        "management"
    ],
    "wof:name":"Enebrina Corporation",
    "wof:placetype":"venue"
},
  "geometry": {"coordinates":[-73.7010879517,45.5050735474],"type":"Point"}
}