{
  "type": "Feature",
  "properties": {
    "addr:full":"Abbotsford BC V2T 4C3",
    "addr:postcode":"v2t 4c3",
    "iso:country":"CA",
    "sg:city":"Abbotsford",
    "sg:classifiers":[
        {
            "category":"Building & Trades",
            "subcategory":"Construction",
            "type":"Services"
        }
    ],
    "sg:phone":"+1 604 850 0435",
    "sg:postcode":"V2T 4C3",
    "sg:province":"BC",
    "sg:tags":[
        "dry wall",
        "contractor"
    ],
    "wof:name":"Mid-Valley",
    "wof:placetype":"venue"
},
  "geometry": {"coordinates":[-122.33927199999999,49.040203],"type":"Point"}
}