{
  "type": "Feature",
  "properties": {
    "addr:full":"5 Gander Bay Rd Gander NL A1V 1W1",
    "addr:housenumber":"5",
    "addr:postcode":"a1v 1w1",
    "addr:street":"Gander Bay Rd",
    "iso:country":"CA",
    "sg:address":"5 Gander Bay Rd",
    "sg:city":"Gander",
    "sg:classifiers":[
        {
            "category":"Education",
            "subcategory":"School",
            "type":"Public Place"
        }
    ],
    "sg:phone":"+1 709 256 8404",
    "sg:postcode":"A1V 1W1",
    "sg:province":"NL",
    "wof:name":"St Paul's Intermediate School",
    "wof:placetype":"venue"
},
  "geometry": {"coordinates":[-54.633663,48.959717],"type":"Point"}
}