{
  "type": "Feature",
  "properties": {
    "addr:full":"Brandon MB R7A 0L8",
    "addr:postcode":"r7a 0l8",
    "iso:country":"CA",
    "sg:city":"Brandon",
    "sg:classifiers":[
        {
            "category":"Insurance",
            "subcategory":"Insurance Agent",
            "type":"Services"
        }
    ],
    "sg:phone":"+1 204 727 0709",
    "sg:postcode":"R7A 0L8",
    "sg:province":"MB",
    "wof:name":"Phillips Insurance Ltd",
    "wof:placetype":"venue"
},
  "geometry": {"coordinates":[-99.95320100000001,49.848629],"type":"Point"}
}