{
  "type": "Feature",
  "properties": {
    "addr:full":"804 6E Rue O Chibougamau QC G8P 2W1",
    "addr:housenumber":"804",
    "addr:postcode":"g8p 2w1",
    "addr:street":"6E Rue O",
    "iso:country":"CA",
    "sg:address":"804 6E Rue O",
    "sg:city":"Chibougamau",
    "sg:classifiers":[
        {
            "category":"Building & Trades",
            "subcategory":"Cleaning & Sanitation",
            "type":"Services"
        }
    ],
    "sg:phone":"+1 418 748 6227",
    "sg:postcode":"G8P 2W1",
    "sg:province":"QC",
    "sg:tags":[
        "ventilating",
        "contractor"
    ],
    "wof:name":"Entreprises Bon-Air",
    "wof:placetype":"venue"
},
  "geometry": {"coordinates":[-74.360428,49.910748],"type":"Point"}
}