{
  "type": "Feature",
  "properties": {
    "addr:full":"2400 Fulton Rd Vernon BC V1H 1S3",
    "addr:housenumber":"2400",
    "addr:postcode":"v1h 1s3",
    "addr:street":"Fulton Rd",
    "iso:country":"CA",
    "sg:address":"2400 Fulton Rd",
    "sg:city":"Vernon",
    "sg:classifiers":[
        {
            "category":"Education",
            "subcategory":"School",
            "type":"Public Place"
        }
    ],
    "sg:phone":"+1 250 260 4176",
    "sg:postcode":"V1H 1S3",
    "sg:province":"BC",
    "wof:name":"Ellison Elementary",
    "wof:placetype":"venue"
},
  "geometry": {"coordinates":[-119.311157227,50.2489891052],"type":"Point"}
}