{
  "type": "Feature",
  "properties": {
    "addr:full":"Red Deer County AB T4E 1B4",
    "addr:postcode":"t4e 1b4",
    "iso:country":"CA",
    "sg:city":"Red Deer County",
    "sg:classifiers":[
        {
            "category":"Building & Trades",
            "subcategory":"Construction",
            "type":"Services"
        }
    ],
    "sg:phone":"+1 403 340 3535",
    "sg:postcode":"T4E 1B4",
    "sg:province":"AB",
    "sg:tags":[
        "pipe",
        "line",
        "contractor"
    ],
    "wof:name":"Corvet Construction Ltd",
    "wof:placetype":"venue"
},
  "geometry": {"coordinates":[-113.93549299999999,52.022137],"type":"Point"}
}