{
  "type": "Feature",
  "properties": {
    "iso:country":"CA",
    "sg:address":"44 Cote Du Palais",
    "sg:city":"Quebec",
    "sg:classifiers":[
        {
            "category":"Health Services",
            "subcategory":"Doctor",
            "type":"Services"
        }
    ],
    "sg:phone":"+1 418 692 4230",
    "sg:postcode":"G1R 4H8",
    "sg:province":"QC",
    "sg:tags":[
        "physician",
        "surgeon"
    ],
    "wof:name":"Demers, Georges MD",
    "wof:placetype":"venue"
},
  "geometry": {"coordinates":[-71.21067,46.81461],"type":"Point"}
}