{
  "type": "Feature",
  "properties": {
    "addr:full":"3228 Cedartree Cres Mississauga ON L4Y 3G4",
    "addr:housenumber":"3228",
    "addr:postcode":"l4y 3g4",
    "addr:street":"Cedartree Cres",
    "iso:country":"CA",
    "sg:address":"3228 Cedartree Cres",
    "sg:city":"Mississauga",
    "sg:classifiers":[
        {
            "category":"Wholesale",
            "subcategory":"Groceries",
            "type":"Manufacturing & Wholesale Goods"
        }
    ],
    "sg:phone":"+1 905 629 4838",
    "sg:postcode":"L4Y 3G4",
    "sg:province":"ON",
    "sg:tags":[
        "food",
        "broker"
    ],
    "wof:name":"Ron Boyko & Assoc",
    "wof:placetype":"venue"
},
  "geometry": {"coordinates":[-79.591904,43.611309],"type":"Point"}
}