{
  "type": "Feature",
  "properties": {
    "addr:full":"710 Elmwood Dr Moncton NB E1A 2X7",
    "addr:housenumber":"710",
    "addr:postcode":"e1a 2x7",
    "addr:street":"Elmwood Dr",
    "iso:country":"CA",
    "sg:address":"710 Elmwood Dr",
    "sg:city":"Moncton",
    "sg:classifiers":[
        {
            "category":"Health Services",
            "subcategory":"Doctor",
            "type":"Services"
        }
    ],
    "sg:phone":"+1 506 858 0212",
    "sg:postcode":"E1A 2X7",
    "sg:province":"NB",
    "sg:tags":[
        "dentist"
    ],
    "wof:name":"Mc Laughlin, Wallace DDS",
    "wof:placetype":"venue"
},
  "geometry": {"coordinates":[-64.770416,46.129536],"type":"Point"}
}