{
  "type": "Feature",
  "properties": {
    "addr:full":"17 Rue Gault Salaberry-DE-Valleyfield QC J6S 3R4",
    "addr:housenumber":"17",
    "addr:postcode":"j6s 3r4",
    "addr:street":"Rue Gault",
    "iso:country":"CA",
    "sg:address":"17 Rue Gault",
    "sg:city":"Salaberry-DE-Valleyfield",
    "sg:classifiers":[
        {
            "category":"Education",
            "subcategory":"School",
            "type":"Public Place"
        }
    ],
    "sg:phone":"+1 450 373 6922",
    "sg:postcode":"J6S 3R4",
    "sg:province":"QC",
    "wof:name":"Gault Institute",
    "wof:placetype":"venue"
},
  "geometry": {"coordinates":[-74.13074493409999,45.2622642517],"type":"Point"}
}