{
  "type": "Feature",
  "properties": {
    "addr:full":"14 Glendale Dr Tillsonburg ON N4G 1J2",
    "addr:housenumber":"14",
    "addr:postcode":"n4g 1j2",
    "addr:street":"Glendale Dr",
    "iso:country":"CA",
    "sg:address":"14 Glendale Dr",
    "sg:city":"Tillsonburg",
    "sg:classifiers":[
        {
            "category":"Organizations",
            "subcategory":"Religious Organization",
            "type":"Services"
        }
    ],
    "sg:phone":"+1 519 842 8331",
    "sg:postcode":"N4G 1J2",
    "sg:province":"ON",
    "sg:tags":[
        "church"
    ],
    "wof:name":"St Luke's Lutheran Church",
    "wof:placetype":"venue"
},
  "geometry": {"coordinates":[-80.7397079468,42.8696479797],"type":"Point"}
}