{
  "type": "Feature",
  "properties": {
    "addr:full":"105 Main St E #1505 Hamilton ON L8N 1G6",
    "addr:housenumber":"105",
    "addr:postcode":"l8n 1g6",
    "addr:street":"Main St E # 1505",
    "iso:country":"CA",
    "sg:address":"105 Main St E #1505",
    "sg:city":"Hamilton",
    "sg:classifiers":[
        {
            "category":"Health Services",
            "subcategory":"Doctor",
            "type":"Services"
        }
    ],
    "sg:phone":"+1 905 528 3855",
    "sg:postcode":"L8N 1G6",
    "sg:province":"ON",
    "sg:tags":[
        "physician",
        "surgeon"
    ],
    "wof:name":"Allergy Clinic",
    "wof:placetype":"venue"
},
  "geometry": {"coordinates":[-79.865326,43.254452],"type":"Point"}
}