{
  "type": "Feature",
  "properties": {
    "addr:full":"Provincial Rd 307 Seven Sisters Falls MB R0E 1Y0",
    "addr:housenumber":"307",
    "addr:postcode":"r0e 1y0",
    "addr:street":"Provincial Rd;Seven Sisters",
    "iso:country":"CA",
    "sg:address":"Provincial Rd 307",
    "sg:city":"Seven Sisters Falls",
    "sg:classifiers":[
        {
            "category":"Shopping",
            "subcategory":"Discount & Variety Stores",
            "type":"Retail Goods"
        }
    ],
    "sg:phone":"+1 204 348 2957",
    "sg:postcode":"R0E 1Y0",
    "sg:province":"MB",
    "sg:tags":[
        "merchandise",
        "general"
    ],
    "wof:name":"Seven Sisters General Store",
    "wof:placetype":"venue"
},
  "geometry": {"coordinates":[-96.029701,50.105354],"type":"Point"}
}