{
  "type": "Feature",
  "properties": {
    "addr:full":"Welland ON L3B 3L2",
    "addr:postcode":"l3b 3l2",
    "iso:country":"CA",
    "sg:city":"Welland",
    "sg:classifiers":[
        {
            "category":"Health Services",
            "subcategory":"Doctor",
            "type":"Services"
        }
    ],
    "sg:phone":"+1 905 732 1121",
    "sg:postcode":"L3B 3L2",
    "sg:province":"ON",
    "sg:tags":[
        "dentist"
    ],
    "wof:name":"Mullins, Eric DDS",
    "wof:placetype":"venue"
},
  "geometry": {"coordinates":[-79.251114,42.97839],"type":"Point"}
}