{
  "type": "Feature",
  "properties": {
    "addr:full":"2450 Boul Laurier Sainte-Foy QC G1V 2L1",
    "addr:housenumber":"2450",
    "addr:postcode":"g1v 2l1",
    "addr:street":"Boul Laurier",
    "iso:country":"CA",
    "sg:address":"2450 Boul Laurier",
    "sg:city":"Sainte-Foy",
    "sg:classifiers":[
        {
            "category":"Shopping",
            "subcategory":"Clothing, Apparel, & Fashions",
            "type":"Retail Goods"
        }
    ],
    "sg:phone":"+1 418 652 7811",
    "sg:postcode":"G1V 2L1",
    "sg:province":"QC",
    "wof:name":"Georges Rech Boutique",
    "wof:placetype":"venue"
},
  "geometry": {"coordinates":[-71.2763137817,46.7736816406],"type":"Point"}
}