{
  "type": "Feature",
  "properties": {
    "addr:full":"1275 7th St E Prince Albert SK S6V 0T8",
    "addr:housenumber":"1275",
    "addr:postcode":"s6v 0t8",
    "addr:street":"7Th St",
    "iso:country":"CA",
    "sg:address":"1275 7th St E",
    "sg:city":"Prince Albert",
    "sg:classifiers":[
        {
            "category":"Freight",
            "type":"Transportation"
        }
    ],
    "sg:phone":"+1 306 763 0044",
    "sg:postcode":"S6V 0T8",
    "sg:province":"SK",
    "sg:tags":[
        "trucking"
    ],
    "wof:name":"Ted Ruszkowski Trucking",
    "wof:placetype":"venue"
},
  "geometry": {"coordinates":[-105.71442399999999,53.203697],"type":"Point"}
}