{
  "type": "Feature",
  "properties": {
    "addr:full":"Fort Macleod AB T0L 0Z0",
    "addr:postcode":"t0l 0z0",
    "addr:street":"Fort",
    "iso:country":"CA",
    "sg:city":"Fort Macleod",
    "sg:classifiers":[
        {
            "category":"Social Services",
            "type":"Services"
        }
    ],
    "sg:phone":"+1 403 553 4849",
    "sg:postcode":"T0L 0Z0",
    "sg:province":"AB",
    "sg:tags":[
        "organization",
        "welfare"
    ],
    "wof:name":"Salvation Army",
    "wof:placetype":"venue"
},
  "geometry": {"coordinates":[-113.395584106,49.7260742188],"type":"Point"}
}