{
  "type": "Feature",
  "properties": {
    "addr:full":"859 Hornby St Vancouver BC V6Z 1T9",
    "addr:housenumber":"859",
    "addr:postcode":"v6z 1t9",
    "addr:street":"Hornby St",
    "iso:country":"CA",
    "sg:address":"859 Hornby St",
    "sg:city":"Vancouver",
    "sg:classifiers":[
        {
            "category":"Restaurant",
            "type":"Food & Drink"
        }
    ],
    "sg:phone":"+1 604 684 4445",
    "sg:postcode":"V6Z 1T9",
    "sg:province":"BC",
    "wof:name":"Presto Panini Cafe",
    "wof:placetype":"venue"
},
  "geometry": {"coordinates":[-123.12285614,49.2820701599],"type":"Point"}
}