{
  "type": "Feature",
  "properties": {
    "addr:full":"270 1st St E North Vancouver BC V7L 1B3",
    "addr:housenumber":"270",
    "addr:postcode":"v7l 1b3",
    "addr:street":"1St St E",
    "iso:country":"CA",
    "sg:address":"270 1st St E",
    "sg:city":"North Vancouver",
    "sg:classifiers":[
        {
            "category":"Retail",
            "subcategory":"Auto Repair",
            "type":"Services"
        }
    ],
    "sg:phone":"+1 604 986 0102",
    "sg:postcode":"V7L 1B3",
    "sg:province":"BC",
    "sg:tags":[
        "automobile",
        "restoration",
        "painting"
    ],
    "wof:name":"R X Autoworks",
    "wof:placetype":"venue"
},
  "geometry": {"coordinates":[-123.07343299999999,49.30978],"type":"Point"}
}