{
  "type": "Feature",
  "properties": {
    "addr:full":"Foleyet ON P0M 1T0",
    "addr:postcode":"p0m 1t0",
    "iso:country":"CA",
    "sg:city":"Foleyet",
    "sg:classifiers":[
        {
            "category":"Travel",
            "subcategory":"Hotels & Motels",
            "type":"Entertainment"
        }
    ],
    "sg:phone":"+1 705 899 2300",
    "sg:postcode":"P0M 1T0",
    "sg:province":"ON",
    "sg:tags":[
        "tourist",
        "accommodation"
    ],
    "wof:name":"Moose Land Resort",
    "wof:placetype":"venue"
},
  "geometry": {"coordinates":[-82.44074999999999,48.243862],"type":"Point"}
}