{
  "type": "Feature",
  "properties": {
    "addr:full":"Little Current ON P0P 1K0",
    "addr:postcode":"p0p 1k0",
    "iso:country":"CA",
    "sg:city":"Little Current",
    "sg:classifiers":[
        {
            "category":"Wholesale",
            "subcategory":"Machinery & Supplies",
            "type":"Manufacturing & Wholesale Goods"
        }
    ],
    "sg:phone":"+1 705 368 0163",
    "sg:postcode":"P0P 1K0",
    "sg:province":"ON",
    "sg:tags":[
        "contractor"
    ],
    "wof:name":"Joly's Equipment Svc & Supply",
    "wof:placetype":"venue"
},
  "geometry": {"coordinates":[-81.9230957031,45.9775123596],"type":"Point"}
}