{
  "type": "Feature",
  "properties": {
    "addr:full":"Kaministiquia ON P0T 1X0",
    "addr:postcode":"p0t 1x0",
    "iso:country":"CA",
    "sg:city":"Kaministiquia",
    "sg:classifiers":[
        {
            "category":"Manufacturing",
            "subcategory":"Metals",
            "type":"Manufacturing & Wholesale Goods"
        }
    ],
    "sg:phone":"+1 807 767 4440",
    "sg:postcode":"P0T 1X0",
    "sg:province":"ON",
    "sg:tags":[
        "door"
    ],
    "wof:name":"Lakehead Aluminum Ltd",
    "wof:placetype":"venue"
},
  "geometry": {"coordinates":[-89.6157,48.532066],"type":"Point"}
}