{
  "type": "Feature",
  "properties": {
    "iso:country":"CA",
    "sg:address":"700 York St",
    "sg:city":"London",
    "sg:classifiers":[
        {
            "category":"Insurance",
            "subcategory":"Insurance Agent",
            "type":"Services"
        }
    ],
    "sg:phone":"+1 519 672 3962",
    "sg:postcode":"N5W 2S8",
    "sg:province":"ON",
    "wof:name":"Woodland Insurance Ltd",
    "wof:placetype":"venue"
},
  "geometry": {"coordinates":[-81.227333,42.987289],"type":"Point"}
}