{
  "type": "Feature",
  "properties": {
    "iso:country":"CA",
    "sg:address":"6 Lincoln St",
    "sg:city":"Ajax",
    "sg:classifiers":[
        {
            "category":"Retail",
            "subcategory":"Laundry & Dry Cleaning",
            "type":"Services"
        }
    ],
    "sg:phone":"+1 905 683 3391",
    "sg:postcode":"L1S 6C8",
    "sg:province":"ON",
    "sg:tags":[
        "cleaners"
    ],
    "wof:name":"Pickering Cleaners",
    "wof:placetype":"venue"
},
  "geometry": {"coordinates":[-79.0543670654,43.8529853821],"type":"Point"}
}