{
  "type": "Feature",
  "properties": {
    "iso:country":"CA",
    "sg:address":"5189 Rue Saint-Denis",
    "sg:city":"Montreal",
    "sg:classifiers":[
        {
            "category":"Communications",
            "subcategory":"Film & Video Production",
            "type":"Services"
        }
    ],
    "sg:phone":"+1 514 606 6768",
    "sg:postcode":"H2J 2M1",
    "sg:province":"QC",
    "sg:tags":[
        "motion",
        "picture",
        "studio",
        "producer"
    ],
    "wof:name":"Productions Du Regard Inc",
    "wof:placetype":"venue"
},
  "geometry": {"coordinates":[-73.59056854249999,45.5275878906],"type":"Point"}
}