{
  "type": "Feature",
  "properties": {
    "addr:full":"3115 Skaha Lake Rd # 101 Penticton BC V2A 6G5",
    "addr:housenumber":"3115",
    "addr:postcode":"v2a 6g5",
    "addr:street":"Skaha Lake Rd # 101",
    "iso:country":"CA",
    "sg:address":"3115 Skaha Lake Rd # 101",
    "sg:city":"Penticton",
    "sg:classifiers":[
        {
            "category":"Real Estate",
            "subcategory":"Real Estate Agent",
            "type":"Services"
        }
    ],
    "sg:phone":"+1 250 493 5072",
    "sg:postcode":"V2A 6G5",
    "sg:province":"BC",
    "sg:tags":[
        "management"
    ],
    "wof:name":"Stanmar Manufactured Homes Svc",
    "wof:placetype":"venue"
},
  "geometry": {"coordinates":[-119.588753,49.460518],"type":"Point"}
}