{
  "type": "Feature",
  "properties": {
    "addr:full":"350 Main St Yarmouth NS B5A 1E6",
    "addr:housenumber":"350",
    "addr:postcode":"b5a 1e6",
    "addr:street":"Main St",
    "iso:country":"CA",
    "sg:address":"350 Main St",
    "sg:city":"Yarmouth",
    "sg:classifiers":[
        {
            "category":"Home & Garden",
            "subcategory":"Building Materials",
            "type":"Retail Goods"
        }
    ],
    "sg:phone":"+1 902 742 0108",
    "sg:postcode":"B5A 1E6",
    "sg:province":"NS",
    "sg:tags":[
        "shop",
        "gift"
    ],
    "wof:name":"Home Sweet Home Decor & Gifts",
    "wof:placetype":"venue"
},
  "geometry": {"coordinates":[-66.120148,43.836433],"type":"Point"}
}