{
  "type": "Feature",
  "properties": {
    "addr:full":"403 Regent St Fredericton NB E3B 3X6",
    "addr:housenumber":"403",
    "addr:postcode":"e3b 3x6",
    "addr:street":"Regent St",
    "iso:country":"CA",
    "sg:address":"403 Regent St",
    "sg:city":"Fredericton",
    "sg:classifiers":[
        {
            "category":"Real Estate",
            "subcategory":"Real Estate Agent",
            "type":"Services"
        }
    ],
    "sg:phone":"+1 506 450 2016",
    "sg:postcode":"E3B 3X6",
    "sg:province":"NB",
    "sg:tags":[
        "appraiser"
    ],
    "wof:name":"New Brunswick Assn-Rl Est Appr",
    "wof:placetype":"venue"
},
  "geometry": {"coordinates":[-66.6444244385,45.9546775818],"type":"Point"}
}