{
  "type": "Feature",
  "properties": {
    "addr:full":"1846 Guildford Town Ctr Surrey BC V3R 7B8",
    "addr:housenumber":"1846",
    "addr:postcode":"v3r 7b8",
    "addr:street":"Guildford Town Ctr",
    "iso:country":"CA",
    "sg:address":"1846 Guildford Town Ctr",
    "sg:city":"Surrey",
    "sg:classifiers":[
        {
            "category":"Home & Garden",
            "subcategory":"Furniture",
            "type":"Retail Goods"
        }
    ],
    "sg:phone":"+1 604 584 4662",
    "sg:postcode":"V3R 7B8",
    "sg:province":"BC",
    "sg:tags":[
        "linen",
        "bedding"
    ],
    "wof:name":"Daniadown Quilts Ltd",
    "wof:placetype":"venue"
},
  "geometry": {"coordinates":[-122.803161621,49.1889343262],"type":"Point"}
}