{
  "type": "Feature",
  "properties": {
    "addr:full":"210 Rue Saint-Jean-Baptiste S Princeville QC G6L 5A6",
    "addr:housenumber":"210",
    "addr:postcode":"g6l 5a6",
    "addr:street":"Rue Saint-Jean-Baptiste S",
    "iso:country":"CA",
    "sg:address":"210 Rue Saint-Jean-Baptiste S",
    "sg:city":"Princeville",
    "sg:classifiers":[
        {
            "category":"Professional",
            "subcategory":"Management & Consulting",
            "type":"Services"
        }
    ],
    "sg:phone":"+1 819 364 5718",
    "sg:postcode":"G6L 5A6",
    "sg:province":"QC",
    "sg:tags":[
        "forestry",
        "consultant",
        "instructional",
        "timber"
    ],
    "wof:name":"Scp Drummond",
    "wof:placetype":"venue"
},
  "geometry": {"coordinates":[-71.8727264404,46.1702613831],"type":"Point"}
}