{
  "type": "Feature",
  "properties": {
    "addr:full":"4806 Bank St Gloucester ON K1X 1G6",
    "addr:housenumber":"4806",
    "addr:postcode":"k1x 1g6",
    "addr:street":"Bank St",
    "iso:country":"CA",
    "sg:address":"4806 Bank St",
    "sg:city":"Gloucester",
    "sg:classifiers":[
        {
            "category":"Building & Trades",
            "subcategory":"Construction",
            "type":"Services"
        }
    ],
    "sg:phone":"+1 613 822 3467",
    "sg:postcode":"K1X 1G6",
    "sg:province":"ON",
    "sg:tags":[
        "resurfacing",
        "laying",
        "refinishing",
        "floor"
    ],
    "wof:name":"Provincial Wood",
    "wof:placetype":"venue"
},
  "geometry": {"coordinates":[-75.589012,45.311943],"type":"Point"}
}