{
  "type": "Feature",
  "properties": {
    "addr:full":"70 James St Parry Sound ON P2A 1T5",
    "addr:housenumber":"70",
    "addr:postcode":"p2a 1t5",
    "addr:street":"James St",
    "iso:country":"CA",
    "sg:address":"70 James St",
    "sg:city":"Parry Sound",
    "sg:classifiers":[
        {
            "category":"Banks & Credit Unions",
            "subcategory":"Investment Brokerage",
            "type":"Services"
        }
    ],
    "sg:phone":"+1 705 774 9444",
    "sg:postcode":"P2A 1T5",
    "sg:province":"ON",
    "wof:name":"Edward Jones",
    "wof:placetype":"venue"
},
  "geometry": {"coordinates":[-80.03396606450001,45.345249176],"type":"Point"}
}