{
  "type": "Feature",
  "properties": {
    "addr:full":"Laval QC H7N 1H8",
    "addr:postcode":"h7n 1h8",
    "iso:country":"CA",
    "sg:city":"Laval",
    "sg:classifiers":[
        {
            "category":"Personal",
            "type":"Services"
        }
    ],
    "sg:phone":"+1 450 967 5557",
    "sg:postcode":"H7N 1H8",
    "sg:province":"QC",
    "sg:tags":[
        "electrolysis"
    ],
    "wof:name":"Institut Brigitte Chayer Enr",
    "wof:placetype":"venue"
},
  "geometry": {"coordinates":[-73.6987,45.567009],"type":"Point"}
}