{
  "type": "Feature",
  "properties": {
    "iso:country":"CA",
    "sg:address":"3655 Rue Marquette",
    "sg:city":"Lac-Megantic",
    "sg:classifiers":[
        {
            "category":"Building & Trades",
            "subcategory":"Construction",
            "type":"Services"
        }
    ],
    "sg:phone":"+1 819 583 1309",
    "sg:postcode":"G6B 1N5",
    "sg:province":"QC",
    "sg:tags":[
        "excavating",
        "contractor"
    ],
    "wof:name":"Excavation Emile Rheaume",
    "wof:placetype":"venue"
},
  "geometry": {"coordinates":[-70.89459228520001,45.5841217041],"type":"Point"}
}