{
  "type": "Feature",
  "properties": {
    "addr:full":"1397 Shoppers Park Mall Grande Cache AB T0E 0Y0",
    "addr:housenumber":"1397",
    "addr:postcode":"t0e 0y0",
    "addr:street":"Shoppers Park Mall Grande",
    "iso:country":"CA",
    "sg:address":"1397 Shoppers Park Mall",
    "sg:city":"Grande Cache",
    "sg:classifiers":[
        {
            "category":"Personal",
            "subcategory":"Beauty Salon",
            "type":"Services"
        }
    ],
    "sg:phone":"+1 780 827 5220",
    "sg:postcode":"T0E 0Y0",
    "sg:province":"AB",
    "wof:name":"Eurotech Hair Design",
    "wof:placetype":"venue"
},
  "geometry": {"coordinates":[-119.11524199999999,53.889915],"type":"Point"}
}