{
  "type": "Feature",
  "properties": {
    "addr:full":"133 Rue Principale Saint-Anselme QC G0R 2N0",
    "addr:housenumber":"133",
    "addr:postcode":"g0r 2n0",
    "addr:street":"Rue Principale",
    "iso:country":"CA",
    "sg:address":"133 Rue Principale",
    "sg:city":"Saint-Anselme",
    "sg:classifiers":[
        {
            "category":"Banks & Credit Unions",
            "subcategory":"Bank",
            "type":"Services"
        }
    ],
    "sg:phone":"+1 418 885 4445",
    "sg:postcode":"G0R 2N0",
    "sg:province":"QC",
    "wof:name":"Banque Nationale Du Canada",
    "wof:placetype":"venue"
},
  "geometry": {"coordinates":[-70.971214,46.628208],"type":"Point"}
}