{
  "type": "Feature",
  "properties": {
    "addr:full":"4520 2nd Ave N Regina SK S4R 0Y4",
    "addr:housenumber":"4520",
    "addr:postcode":"s4r 0y4",
    "addr:street":"2Nd Ave N",
    "iso:country":"CA",
    "sg:address":"4520 2nd Ave N",
    "sg:city":"Regina",
    "sg:classifiers":[
        {
            "category":"Building & Trades",
            "subcategory":"Landscaping Services",
            "type":"Services"
        }
    ],
    "sg:phone":"+1 306 789 2268",
    "sg:postcode":"S4R 0Y4",
    "sg:province":"SK",
    "sg:tags":[
        "landscape",
        "contractor"
    ],
    "wof:name":"Aloha Landscaping Contractors",
    "wof:placetype":"venue"
},
  "geometry": {"coordinates":[-104.64569854699999,50.472530365],"type":"Point"}
}