{
  "type": "Feature",
  "properties": {
    "addr:full":"Rodney ON N0L 2C0",
    "addr:postcode":"n0l 2c0",
    "iso:country":"CA",
    "sg:city":"Rodney",
    "sg:classifiers":[
        {
            "category":"Building & Trades",
            "subcategory":"Landscaping Services",
            "type":"Services"
        }
    ],
    "sg:phone":"+1 519 785 2138",
    "sg:postcode":"N0L 2C0",
    "sg:province":"ON",
    "sg:tags":[
        "landscape",
        "contractor"
    ],
    "wof:name":"Green Street Landscaping",
    "wof:placetype":"venue"
},
  "geometry": {"coordinates":[-81.68309021,42.5680351257],"type":"Point"}
}