{
  "type": "Feature",
  "properties": {
    "iso:country":"CA",
    "sg:address":"5 Fieldstone Pl",
    "sg:city":"Spruce Grove",
    "sg:classifiers":[
        {
            "category":"Professional",
            "subcategory":"Management & Consulting",
            "type":"Services"
        }
    ],
    "sg:phone":"+1 780 962 2494",
    "sg:postcode":"T7X 2Z4",
    "sg:province":"AB",
    "sg:tags":[
        "consultant",
        "business"
    ],
    "wof:name":"Sfp Energy & Government Rltn",
    "wof:placetype":"venue"
},
  "geometry": {"coordinates":[-113.90766143800001,53.5610618591],"type":"Point"}
}