{
  "type": "Feature",
  "properties": {
    "addr:full":"8395 St Lawrence Pl Prince George BC V2N 5G9",
    "addr:housenumber":"8395",
    "addr:postcode":"v2n 5g9",
    "addr:street":"St Lawrence Pl",
    "iso:country":"CA",
    "sg:address":"8395 St Lawrence Pl",
    "sg:city":"Prince George",
    "sg:classifiers":[
        {
            "category":"Professional",
            "subcategory":"Research",
            "type":"Services"
        }
    ],
    "sg:phone":"+1 250 564 9010",
    "sg:postcode":"V2N 5G9",
    "sg:province":"BC",
    "sg:tags":[
        "environmental",
        "ecological"
    ],
    "wof:name":"Geotech Drilling Svc",
    "wof:placetype":"venue"
},
  "geometry": {"coordinates":[-122.780654907,53.8541641235],"type":"Point"}
}