{
  "type": "Feature",
  "properties": {
    "addr:full":"132 South Railway Ave LA Riviere MB R0G 1A0",
    "addr:housenumber":"132",
    "addr:postcode":"r0g 1a0",
    "addr:street":"South Railway Ave",
    "iso:country":"CA",
    "sg:address":"132 South Railway Ave",
    "sg:city":"LA Riviere",
    "sg:classifiers":[
        {
            "category":"Personal",
            "subcategory":"Beauty Salon",
            "type":"Services"
        }
    ],
    "sg:phone":"+1 204 242 2872",
    "sg:postcode":"R0G 1A0",
    "sg:province":"MB",
    "wof:name":"Christine's Cuts & Curls",
    "wof:placetype":"venue"
},
  "geometry": {"coordinates":[-98.68032100000001,49.238739],"type":"Point"}
}