{
  "type": "Feature",
  "properties": {
    "iso:country":"CA",
    "sg:address":"3242 Beverley Cres",
    "sg:city":"Abbotsford",
    "sg:classifiers":[
        {
            "category":"Professional",
            "subcategory":"Business Services",
            "type":"Services"
        }
    ],
    "sg:phone":"+1 604 854 8175",
    "sg:postcode":"V2S 4M5",
    "sg:province":"BC",
    "sg:tags":[
        "drafting"
    ],
    "wof:name":"D & D Design",
    "wof:placetype":"venue"
},
  "geometry": {"coordinates":[-122.26255798299999,49.0605278015],"type":"Point"}
}