{
  "type": "Feature",
  "properties": {
    "addr:full":"Calgary AB T2M 2A8",
    "addr:postcode":"t2m 2a8",
    "iso:country":"CA",
    "sg:city":"Calgary",
    "sg:classifiers":[
        {
            "category":"Food & Beverages",
            "subcategory":"Bakery",
            "type":"Retail Goods"
        }
    ],
    "sg:phone":"+1 403 282 0788",
    "sg:postcode":"T2M 2A8",
    "sg:province":"AB",
    "sg:tags":[
        "baker"
    ],
    "wof:name":"Eiffel Tower Bakery",
    "wof:placetype":"venue"
},
  "geometry": {"coordinates":[-114.0718,51.075283],"type":"Point"}
}