{
  "type": "Feature",
  "properties": {
    "iso:country":"CA",
    "sg:address":"75 Queen Alexandra Close SE",
    "sg:city":"Calgary",
    "sg:classifiers":[
        {
            "category":"Manufacturing",
            "subcategory":"Building Materials",
            "type":"Manufacturing & Wholesale Goods"
        }
    ],
    "sg:phone":"+1 403 225 2170",
    "sg:postcode":"T2J 3P9",
    "sg:province":"AB",
    "sg:tags":[
        "fastener"
    ],
    "wof:name":"Revoe Manufacturing Ltd",
    "wof:placetype":"venue"
},
  "geometry": {"coordinates":[-114.03120422400001,50.9358139038],"type":"Point"}
}