{
  "type": "Feature",
  "properties": {
    "iso:country":"CA",
    "sg:address":"11437 Hwy 17",
    "sg:city":"Wabigoon",
    "sg:classifiers":[
        {
            "category":"Travel",
            "subcategory":"Hotels & Motels",
            "type":"Entertainment"
        }
    ],
    "sg:phone":"+1 807 938 6543",
    "sg:postcode":"P0V 2W0",
    "sg:province":"ON",
    "sg:tags":[
        "tourist",
        "accommodation"
    ],
    "wof:name":"Pine Grove Camping & Motel",
    "wof:placetype":"venue"
},
  "geometry": {"coordinates":[-92.58558654789999,49.7077598572],"type":"Point"}
}