{
  "type": "Feature",
  "properties": {
    "addr:full":"402 1st Ave St Brieux SK S0K 3V0",
    "addr:housenumber":"402",
    "addr:postcode":"s0k 3v0",
    "addr:street":"1St Ave St",
    "iso:country":"CA",
    "sg:address":"402 1st Ave",
    "sg:city":"St Brieux",
    "sg:classifiers":[
        {
            "category":"Food & Beverages",
            "subcategory":"Meat & Fish",
            "type":"Retail Goods"
        }
    ],
    "sg:phone":"+1 306 275 2009",
    "sg:postcode":"S0K 3V0",
    "sg:province":"SK",
    "wof:name":"E & A Meat Market Ltd",
    "wof:placetype":"venue"
},
  "geometry": {"coordinates":[-104.892776,52.634571],"type":"Point"}
}