{
  "type": "Feature",
  "properties": {
    "addr:full":"250 Rodney St Headingley MB R4J 1A8",
    "addr:housenumber":"250",
    "addr:postcode":"r4j 1a8",
    "addr:street":"Rodney St",
    "iso:country":"CA",
    "sg:address":"250 Rodney St",
    "sg:city":"Headingley",
    "sg:classifiers":[
        {
            "category":"Food & Beverages",
            "subcategory":"Fruits & Vegetables",
            "type":"Retail Goods"
        }
    ],
    "sg:phone":"+1 204 888 8839",
    "sg:postcode":"R4J 1A8",
    "sg:province":"MB",
    "sg:tags":[
        "produce"
    ],
    "wof:name":"Miinan-Wild Blueberries",
    "wof:placetype":"venue"
},
  "geometry": {"coordinates":[-97.41394805909999,49.8613777161],"type":"Point"}
}