{
  "type": "Feature",
  "properties": {
    "addr:full":"2911 Eglinton Ave E Scarborough ON M1J 2E5",
    "addr:housenumber":"2911",
    "addr:postcode":"m1j 2e5",
    "addr:street":"Eglinton Ave E",
    "iso:country":"CA",
    "sg:address":"2911 Eglinton Ave E",
    "sg:city":"Scarborough",
    "sg:classifiers":[
        {
            "category":"Restaurant",
            "type":"Food & Drink"
        }
    ],
    "sg:phone":"+1 416 431 7437",
    "sg:postcode":"M1J 2E5",
    "sg:province":"ON",
    "wof:name":"Harvey's",
    "wof:placetype":"venue"
},
  "geometry": {"coordinates":[-79.2371063232,43.7390174866],"type":"Point"}
}