{
  "type": "Feature",
  "properties": {
    "addr:full":"Brampton ON L6W 3P3",
    "addr:postcode":"l6w 3p3",
    "iso:country":"CA",
    "sg:city":"Brampton",
    "sg:classifiers":[
        {
            "category":"Professional",
            "subcategory":"Employment Agencies",
            "type":"Services"
        }
    ],
    "sg:phone":"+1 905 799 1177",
    "sg:postcode":"L6W 3P3",
    "sg:province":"ON",
    "sg:tags":[
        "opportunity"
    ],
    "wof:name":"Mmmi Employment Solutions",
    "wof:placetype":"venue"
},
  "geometry": {"coordinates":[-79.74082900000001,43.688988],"type":"Point"}
}