{
  "type": "Feature",
  "properties": {
    "addr:full":"7 Aurora Ave Kapuskasing ON P5N 1J6",
    "addr:housenumber":"7",
    "addr:postcode":"p5n 1j6",
    "addr:street":"Aurora Ave",
    "iso:country":"CA",
    "sg:address":"7 Aurora Ave",
    "sg:city":"Kapuskasing",
    "sg:classifiers":[
        {
            "category":"Social Services",
            "type":"Services"
        }
    ],
    "sg:phone":"+1 705 335 4122",
    "sg:postcode":"P5N 1J6",
    "sg:province":"ON",
    "sg:tags":[
        "organization",
        "welfare"
    ],
    "wof:name":"Cochrane Temiskaming Resource",
    "wof:placetype":"venue"
},
  "geometry": {"coordinates":[-82.43013000000001,49.419361],"type":"Point"}
}