{
  "type": "Feature",
  "properties": {
    "addr:full":"504 Parks St Whitewood SK S0G 5C0",
    "addr:housenumber":"504",
    "addr:postcode":"s0g 5c0",
    "addr:street":"Parks St",
    "iso:country":"CA",
    "sg:address":"504 Parks St",
    "sg:city":"Whitewood",
    "sg:classifiers":[
        {
            "category":"Recreation",
            "type":"Entertainment"
        }
    ],
    "sg:phone":"+1 306 735 2640",
    "sg:postcode":"S0G 5C0",
    "sg:province":"SK",
    "sg:tags":[
        "club",
        "curling"
    ],
    "wof:name":"Whitewood Curling Club",
    "wof:placetype":"venue"
},
  "geometry": {"coordinates":[-102.274338,50.331406],"type":"Point"}
}