{
  "type": "Feature",
  "properties": {
    "addr:full":"627 Shawcliffe Gate SW Calgary AB T2Y 1W1",
    "addr:housenumber":"627",
    "addr:postcode":"ab t2y 1w1",
    "addr:street":"Shawcliffe Gate Sw",
    "iso:country":"CA",
    "sg:address":"627 Shawcliffe Gate SW",
    "sg:city":"Calgary",
    "sg:classifiers":[
        {
            "category":"Restaurant",
            "type":"Food & Drink"
        }
    ],
    "sg:phone":"+1 403 254 1688",
    "sg:postcode":"T2Y 1W1",
    "sg:province":"AB",
    "wof:name":"Oriental Ginger Beef House Ltd",
    "wof:placetype":"venue"
},
  "geometry": {"coordinates":[-114.074714661,50.9113693237],"type":"Point"}
}