{
  "type": "Feature",
  "properties": {
    "addr:full":"1502 Mountain Rd Dauphin MB R7N 0K5",
    "addr:housenumber":"1502",
    "addr:postcode":"r7n 0k5",
    "addr:street":"Mountain Rd",
    "iso:country":"CA",
    "sg:address":"1502 Mountain Rd",
    "sg:city":"Dauphin",
    "sg:classifiers":[
        {
            "category":"Food & Beverages",
            "subcategory":"Groceries & Convenience Stores",
            "type":"Retail Goods"
        }
    ],
    "sg:phone":"+1 204 638 5015",
    "sg:postcode":"R7N 0K5",
    "sg:province":"MB",
    "wof:name":"Mr T's",
    "wof:placetype":"venue"
},
  "geometry": {"coordinates":[-100.03969574,51.1580162048],"type":"Point"}
}