{
  "type": "Feature",
  "properties": {
    "addr:full":"705 Ch Saint-Fereol Les Cedres QC J7T 1M9",
    "addr:housenumber":"705",
    "addr:postcode":"j7t 1m9",
    "addr:street":"Ch Saint-Fereol",
    "iso:country":"CA",
    "sg:address":"705 Ch Saint-Fereol",
    "sg:city":"Les Cedres",
    "sg:classifiers":[
        {
            "category":"Food & Beverages",
            "subcategory":"Groceries & Convenience Stores",
            "type":"Retail Goods"
        }
    ],
    "sg:phone":"+1 450 452 2440",
    "sg:postcode":"J7T 1M9",
    "sg:province":"QC",
    "wof:name":"Depanneur St-Feroel Enr",
    "wof:placetype":"venue"
},
  "geometry": {"coordinates":[-74.08020019529999,45.3349914551],"type":"Point"}
}