{
  "type": "Feature",
  "properties": {
    "iso:country":"CA",
    "sg:address":"1253 Av Mcgill College # 655",
    "sg:city":"Montreal",
    "sg:classifiers":[
        {
            "category":"Professional",
            "subcategory":"Business Services",
            "type":"Services"
        }
    ],
    "sg:phone":"+1 514 397 1182",
    "sg:postcode":"H3B 2Y5",
    "sg:province":"QC",
    "sg:tags":[
        "information",
        "referral"
    ],
    "wof:name":"Office National Du Tourisme",
    "wof:placetype":"venue"
},
  "geometry": {"coordinates":[-73.5704574585,45.5019378662],"type":"Point"}
}