{
  "type": "Feature",
  "properties": {
    "addr:full":"810 Main St Smith AB T0G 2B0",
    "addr:housenumber":"810",
    "addr:postcode":"t0g 2b0",
    "addr:street":"Main St",
    "iso:country":"CA",
    "sg:address":"810 Main St",
    "sg:city":"Smith",
    "sg:classifiers":[
        {
            "category":"Shopping",
            "subcategory":"Used Merchandise",
            "type":"Retail Goods"
        }
    ],
    "sg:phone":"+1 780 829 2929",
    "sg:postcode":"T0G 2B0",
    "sg:province":"AB",
    "sg:tags":[
        "antique"
    ],
    "wof:name":"Needful Things Inc",
    "wof:placetype":"venue"
},
  "geometry": {"coordinates":[-114.02030944800001,55.1507873535],"type":"Point"}
}