{
  "type": "Feature",
  "properties": {
    "addr:full":"1890 Rue Girouard O Saint-Hyacinthe QC J2S 3A3",
    "addr:housenumber":"1890",
    "addr:postcode":"j2s 3a3",
    "addr:street":"Rue Girouard O",
    "iso:country":"CA",
    "sg:address":"1890 Rue Girouard O",
    "sg:city":"Saint-Hyacinthe",
    "sg:classifiers":[
        {
            "category":"Government",
            "subcategory":"Office",
            "type":"Public Place"
        }
    ],
    "sg:phone":"+1 450 799 5838",
    "sg:postcode":"J2S 3A3",
    "sg:province":"QC",
    "sg:tags":[
        "village"
    ],
    "wof:name":"Saint-Hyacinthe Usine",
    "wof:placetype":"venue"
},
  "geometry": {"coordinates":[-72.9425201416,45.6458244324],"type":"Point"}
}