{
  "type": "Feature",
  "properties": {
    "addr:full":"1584 Huron Church Rd Windsor ON N9C 2L1",
    "addr:housenumber":"1584",
    "addr:postcode":"n9c 2l1",
    "addr:street":"Huron Church Rd",
    "iso:country":"CA",
    "sg:address":"1584 Huron Church Rd",
    "sg:city":"Windsor",
    "sg:classifiers":[
        {
            "category":"Banks & Credit Unions",
            "subcategory":"Bank",
            "type":"Services"
        }
    ],
    "sg:phone":"+1 519 256 2274",
    "sg:postcode":"N9C 2L1",
    "sg:province":"ON",
    "sg:tags":[
        "cashing",
        "money",
        "check",
        "order"
    ],
    "wof:name":"Money Mart Cheque Cashing Ctr",
    "wof:placetype":"venue"
},
  "geometry": {"coordinates":[-83.05817399999999,42.288147],"type":"Point"}
}