{
  "type": "Feature",
  "properties": {
    "addr:full":"2206 Boul Des Chenaux Trois-Rivieres QC G9A 1A1",
    "addr:housenumber":"2206",
    "addr:postcode":"g9a 1a1",
    "addr:street":"Boul Des Chenaux Trois-Rivieres",
    "iso:country":"CA",
    "sg:address":"2206 Boul Des Chenaux",
    "sg:city":"Trois-Rivieres",
    "sg:classifiers":[
        {
            "category":"Shopping",
            "subcategory":"Bicycles & Sporting Goods",
            "type":"Retail Goods"
        }
    ],
    "sg:phone":"+1 819 694 7010",
    "sg:postcode":"G9A 1A1",
    "sg:province":"QC",
    "sg:tags":[
        "camp"
    ],
    "wof:name":"Camp DE Base Maikan Radisson",
    "wof:placetype":"venue"
},
  "geometry": {"coordinates":[-72.55545043950001,46.3646430969],"type":"Point"}
}