{
  "type": "Feature",
  "properties": {
    "addr:full":"9200 Holding Rd Chase BC V0E 1M0",
    "addr:postcode":"9200;v0e 1m0",
    "addr:street":"Holding Rd",
    "iso:country":"CA",
    "sg:address":"9200 Holding Rd",
    "sg:city":"Chase",
    "sg:classifiers":[
        {
            "category":"Manufacturing",
            "subcategory":"Lumber",
            "type":"Manufacturing & Wholesale Goods"
        }
    ],
    "sg:phone":"+1 250 679 3234",
    "sg:postcode":"V0E 1M0",
    "sg:province":"BC",
    "wof:name":"Adams Lake Lumber",
    "wof:placetype":"venue"
},
  "geometry": {"coordinates":[-119.68430328399999,50.8160667419],"type":"Point"}
}