{
  "type": "Feature",
  "properties": {
    "addr:full":"103 Rue James Cowansville QC J2K 2L1",
    "addr:housenumber":"103",
    "addr:postcode":"j2k 2l1",
    "addr:street":"Rue James",
    "iso:country":"CA",
    "sg:address":"103 Rue James",
    "sg:city":"Cowansville",
    "sg:classifiers":[
        {
            "category":"Personal",
            "subcategory":"Beauty Salon",
            "type":"Services"
        }
    ],
    "sg:phone":"+1 450 263 3493",
    "sg:postcode":"J2K 2L1",
    "sg:province":"QC",
    "wof:name":"Salon Elegance Enrg",
    "wof:placetype":"venue"
},
  "geometry": {"coordinates":[-72.73989105219999,45.2084274292],"type":"Point"}
}