{
  "type": "Feature",
  "properties": {
    "addr:full":"17 Avonlea Crt Fredericton NB E3C 1N8",
    "addr:housenumber":"17",
    "addr:postcode":"e3c 1n8",
    "addr:street":"Avonlea Crt",
    "iso:country":"CA",
    "sg:address":"17 Avonlea Crt",
    "sg:city":"Fredericton",
    "sg:classifiers":[
        {
            "category":"Retail",
            "subcategory":"Auto Repair",
            "type":"Services"
        }
    ],
    "sg:phone":"+1 506 453 1953",
    "sg:postcode":"E3C 1N8",
    "sg:province":"NB",
    "sg:tags":[
        "repairing",
        "automobile"
    ],
    "wof:name":"York Auto Svc",
    "wof:placetype":"venue"
},
  "geometry": {"coordinates":[-66.689735,45.945499],"type":"Point"}
}