{
  "type": "Feature",
  "properties": {
    "iso:country":"CA",
    "sg:address":"400 Mackenzie Beach Rd",
    "sg:city":"Tofino",
    "sg:classifiers":[
        {
            "category":"Travel",
            "subcategory":"Hotels & Motels",
            "type":"Entertainment"
        }
    ],
    "sg:phone":"+1 250 725 2900",
    "sg:postcode":"V0R 2Z0",
    "sg:province":"BC",
    "sg:tags":[
        "resort"
    ],
    "wof:name":"Middle Beach Lodge",
    "wof:placetype":"venue"
},
  "geometry": {"coordinates":[-125.901092529,49.1325454712],"type":"Point"}
}