{
  "type": "Feature",
  "properties": {
    "addr:full":"2915 Hwy 3 Creston BC V0B 1G1",
    "addr:housenumber":"2915",
    "addr:postcode":"bc v0b 1g1",
    "addr:street":"Hwy 3",
    "iso:country":"CA",
    "sg:address":"2915 Hwy 3",
    "sg:city":"Creston",
    "sg:classifiers":[
        {
            "category":"Home & Garden",
            "subcategory":"Garden Supply",
            "type":"Retail Goods"
        }
    ],
    "sg:phone":"+1 250 428 2062",
    "sg:postcode":"V0B 1G1",
    "sg:province":"BC",
    "sg:tags":[
        "nurseryman"
    ],
    "wof:name":"Beltane Nursery",
    "wof:placetype":"venue"
},
  "geometry": {"coordinates":[-116.49185199999999,49.095421],"type":"Point"}
}