{
  "type": "Feature",
  "properties": {
    "addr:full":"221 Timber Dr London ON N6K 4B6",
    "addr:housenumber":"221",
    "addr:postcode":"n6k 4b6",
    "addr:street":"Timber Dr",
    "iso:country":"CA",
    "sg:address":"221 Timber Dr",
    "sg:city":"London",
    "sg:classifiers":[
        {
            "category":"Wholesale",
            "subcategory":"Durable Goods & Equipment",
            "type":"Manufacturing & Wholesale Goods"
        }
    ],
    "sg:phone":"+1 519 473 1953",
    "sg:postcode":"N6K 4B6",
    "sg:province":"ON",
    "sg:tags":[
        "laboratory",
        "supply"
    ],
    "wof:name":"Cambridge Environmental Prods",
    "wof:placetype":"venue"
},
  "geometry": {"coordinates":[-81.346558,42.952801],"type":"Point"}
}