{
  "type": "Feature",
  "properties": {
    "addr:full":"High Level AB T0H 1Z0",
    "addr:postcode":"t0h 1z0",
    "iso:country":"CA",
    "sg:city":"High Level",
    "sg:classifiers":[
        {
            "category":"Building & Trades",
            "subcategory":"Equipment Rental",
            "type":"Services"
        }
    ],
    "sg:phone":"+1 780 926 2133",
    "sg:postcode":"T0H 1Z0",
    "sg:province":"AB",
    "sg:tags":[
        "oil",
        "well",
        "supply"
    ],
    "wof:name":"Parma Ventures Inc",
    "wof:placetype":"venue"
},
  "geometry": {"coordinates":[-117.134331,58.504742],"type":"Point"}
}