{
  "type": "Feature",
  "properties": {
    "iso:country":"CA",
    "sg:address":"Rl 36 River Rd",
    "sg:city":"Emerson",
    "sg:classifiers":[
        {
            "category":"Farming",
            "subcategory":"Farm & Veterinary Services",
            "type":"Manufacturing & Wholesale Goods"
        }
    ],
    "sg:phone":"+1 204 373 2911",
    "sg:postcode":"R0A 0L0",
    "sg:province":"MB",
    "sg:tags":[
        "seed",
        "grain",
        "cleaning"
    ],
    "wof:name":"South Central Seed Cleaning",
    "wof:placetype":"venue"
},
  "geometry": {"coordinates":[-97.2047576904,49.0089759827],"type":"Point"}
}