{
  "type": "Feature",
  "properties": {
    "addr:full":"Calgary AB T2H 2J7",
    "addr:postcode":"t2h 2j7",
    "iso:country":"CA",
    "sg:city":"Calgary",
    "sg:classifiers":[
        {
            "category":"Wholesale",
            "subcategory":"Machinery & Supplies",
            "type":"Manufacturing & Wholesale Goods"
        }
    ],
    "sg:phone":"+1 403 299 0260",
    "sg:postcode":"T2H 2J7",
    "sg:province":"AB",
    "sg:tags":[
        "dyer",
        "equipment",
        "laundry",
        "cleaners"
    ],
    "wof:name":"Prairie Distributors Inc",
    "wof:placetype":"venue"
},
  "geometry": {"coordinates":[-114.03993199999999,50.995235],"type":"Point"}
}