{
  "type": "Feature",
  "properties": {
    "addr:full":"14 Ash St Kapuskasing ON P5N 2C8",
    "addr:housenumber":"14",
    "addr:postcode":"p5n 2c8",
    "addr:street":"Ash St",
    "iso:country":"CA",
    "sg:address":"14 Ash St",
    "sg:city":"Kapuskasing",
    "sg:classifiers":[
        {
            "category":"Building & Trades",
            "subcategory":"Plumbing",
            "type":"Services"
        }
    ],
    "sg:phone":"+1 705 335 3243",
    "sg:postcode":"P5N 2C8",
    "sg:province":"ON",
    "sg:tags":[
        "equipment",
        "refrigeration",
        "contractor"
    ],
    "wof:name":"G T Plumbing & Heating",
    "wof:placetype":"venue"
},
  "geometry": {"coordinates":[-82.4173660278,49.4222717285],"type":"Point"}
}