{
  "type": "Feature",
  "properties": {
    "addr:full":"315 Fairview Dr Brantford ON N3R 2X3",
    "addr:housenumber":"315",
    "addr:postcode":"n3r 2x3",
    "addr:street":"Fairview Dr",
    "iso:country":"CA",
    "sg:address":"315 Fairview Dr",
    "sg:city":"Brantford",
    "sg:classifiers":[
        {
            "category":"Retail",
            "subcategory":"Laundry & Dry Cleaning",
            "type":"Services"
        }
    ],
    "sg:phone":"+1 519 752 1923",
    "sg:postcode":"N3R 2X3",
    "sg:province":"ON",
    "sg:tags":[
        "cleaners"
    ],
    "wof:name":"Burtol Cleaners",
    "wof:placetype":"venue"
},
  "geometry": {"coordinates":[-80.258095,43.17083],"type":"Point"}
}