{
  "type": "Feature",
  "properties": {
    "addr:full":"1220 Broadway W Vancouver BC V6H 1G6",
    "addr:housenumber":"1220",
    "addr:postcode":"v6h 1g6",
    "addr:street":"Broadway W",
    "iso:country":"CA",
    "sg:address":"1220 Broadway W",
    "sg:city":"Vancouver",
    "sg:classifiers":[
        {
            "category":"Shopping",
            "subcategory":"Computers & Home Electronics",
            "type":"Retail Goods"
        }
    ],
    "sg:phone":"+1 604 734 8688",
    "sg:postcode":"V6H 1G6",
    "sg:province":"BC",
    "sg:tags":[
        "parts",
        "supply"
    ],
    "wof:name":"Save on Cartridge Plus",
    "wof:placetype":"venue"
},
  "geometry": {"coordinates":[-123.13201100000001,49.263367],"type":"Point"}
}