{
  "type": "Feature",
  "properties": {
    "addr:full":"289 Boul DE LA Concorde E Laval QC H7G 2E5",
    "addr:housenumber":"289",
    "addr:postcode":"qc h7g 2e5",
    "addr:street":"Boul De La Concorde E",
    "iso:country":"CA",
    "sg:address":"289 Boul DE LA Concorde E",
    "sg:city":"Laval",
    "sg:classifiers":[
        {
            "category":"Personal",
            "subcategory":"Beauty Salon",
            "type":"Services"
        }
    ],
    "sg:phone":"+1 450 629 2648",
    "sg:postcode":"H7G 2E5",
    "sg:province":"QC",
    "wof:name":"Salon DE Coiffure Creatif Pour",
    "wof:placetype":"venue"
},
  "geometry": {"coordinates":[-73.6810760498,45.5770988464],"type":"Point"}
}