{
  "type": "Feature",
  "properties": {
    "addr:full":"Oakville ON L6J 6J3",
    "addr:postcode":"l6j 6j3",
    "iso:country":"CA",
    "sg:city":"Oakville",
    "sg:classifiers":[
        {
            "category":"Professional",
            "subcategory":"Management & Consulting",
            "type":"Services"
        }
    ],
    "sg:phone":"+1 905 339 3222",
    "sg:postcode":"L6J 6J3",
    "sg:province":"ON",
    "sg:tags":[
        "consultant",
        "business"
    ],
    "wof:name":"Perforex",
    "wof:placetype":"venue"
},
  "geometry": {"coordinates":[-79.66677900000001,43.447311],"type":"Point"}
}