{
  "type": "Feature",
  "properties": {
    "iso:country":"CA",
    "sg:address":"1 Young St #312A",
    "sg:city":"Hamilton",
    "sg:classifiers":[
        {
            "category":"Health Services",
            "subcategory":"Health Practitioner",
            "type":"Services"
        }
    ],
    "sg:phone":"+1 905 529 7269",
    "sg:postcode":"L8N 1T8",
    "sg:province":"ON",
    "sg:tags":[
        "psychologist"
    ],
    "wof:name":"Burt, D B",
    "wof:placetype":"venue"
},
  "geometry": {"coordinates":[-79.87117,43.251408],"type":"Point"}
}