{
  "type": "Feature",
  "properties": {
    "iso:country":"CA",
    "sg:address":"2180 Rue Lesperance",
    "sg:city":"Montreal",
    "sg:classifiers":[
        {
            "category":"Wholesale",
            "subcategory":"Construction Materials",
            "type":"Manufacturing & Wholesale Goods"
        }
    ],
    "sg:phone":"+1 514 527 3419",
    "sg:postcode":"H2K 2N9",
    "sg:province":"QC",
    "sg:tags":[
        "glass",
        "fiber"
    ],
    "wof:name":"H L Platso Ind Ltee",
    "wof:placetype":"venue"
},
  "geometry": {"coordinates":[-73.551865,45.538364],"type":"Point"}
}