{
  "type": "Feature",
  "properties": {
    "addr:full":"Rosthern SK S0K 3R0",
    "addr:postcode":"s0k 3r0",
    "iso:country":"CA",
    "sg:city":"Rosthern",
    "sg:classifiers":[
        {
            "category":"Wholesale",
            "subcategory":"Farm Supplies",
            "type":"Manufacturing & Wholesale Goods"
        }
    ],
    "sg:phone":"+1 306 232 4223",
    "sg:postcode":"S0K 3R0",
    "sg:province":"SK",
    "sg:tags":[
        "fertilizer"
    ],
    "wof:name":"Wendland Ag Svc",
    "wof:placetype":"venue"
},
  "geometry": {"coordinates":[-106.331695557,52.6577529907],"type":"Point"}
}