{
  "type": "Feature",
  "properties": {
    "addr:full":"4 Alta Dr Stouffville ON L4A 7X4",
    "addr:housenumber":"4",
    "addr:postcode":"l4a 7x4",
    "addr:street":"Alta Dr",
    "iso:country":"CA",
    "sg:address":"4 Alta Dr",
    "sg:city":"Stouffville",
    "sg:classifiers":[
        {
            "category":"Shopping",
            "subcategory":"Florist",
            "type":"Retail Goods"
        }
    ],
    "sg:phone":"+1 905 642 2970",
    "sg:postcode":"L4A 7X4",
    "sg:province":"ON",
    "sg:tags":[
        "plant"
    ],
    "wof:name":"Blackwood & CO Interior Lndscp",
    "wof:placetype":"venue"
},
  "geometry": {"coordinates":[-79.248024,43.971085],"type":"Point"}
}