{
  "type": "Feature",
  "properties": {
    "addr:full":"Nelson BC V1L 1W7",
    "addr:postcode":"bc v1l 1w7",
    "iso:country":"CA",
    "sg:city":"Nelson",
    "sg:classifiers":[
        {
            "category":"Shopping",
            "subcategory":"Clothing, Apparel, & Fashions",
            "type":"Retail Goods"
        }
    ],
    "sg:phone":"+1 250 354 4660",
    "sg:postcode":"V1L 1W7",
    "sg:province":"BC",
    "wof:name":"Sensations Klothes Shoppe",
    "wof:placetype":"venue"
},
  "geometry": {"coordinates":[-117.291969299,49.491558075],"type":"Point"}
}