{
  "type": "Feature",
  "properties": {
    "addr:full":"Main St Cumberland House SK S0E 0S0",
    "addr:postcode":"s0e 0s0",
    "addr:street":"Main St",
    "iso:country":"CA",
    "sg:address":"Main St",
    "sg:city":"Cumberland House",
    "sg:classifiers":[
        {
            "category":"Shopping",
            "subcategory":"Discount & Variety Stores",
            "type":"Retail Goods"
        }
    ],
    "sg:phone":"+1 306 888 2265",
    "sg:postcode":"S0E 0S0",
    "sg:province":"SK",
    "sg:tags":[
        "merchandise",
        "general"
    ],
    "wof:name":"H & M Gas Bar Ltd",
    "wof:placetype":"venue"
},
  "geometry": {"coordinates":[-102.267616272,53.955329895],"type":"Point"}
}