{
  "type": "Feature",
  "properties": {
    "addr:full":"PO Box 5570 STN Main Fort Mcmurray AB T9H 3G5",
    "addr:housenumber":"po",
    "addr:postcode":"5570;t9h 3g5",
    "addr:street":"Box;Stn Main",
    "iso:country":"CA",
    "sg:address":"PO Box 5570 STN Main",
    "sg:city":"Fort Mcmurray",
    "sg:classifiers":[
        {
            "category":"Building & Trades",
            "subcategory":"Construction",
            "type":"Services"
        }
    ],
    "sg:phone":"+1 780 791 0654",
    "sg:postcode":"T9H 3G5",
    "sg:province":"AB",
    "sg:tags":[
        "excavating",
        "contractor",
        "general"
    ],
    "wof:name":"Neegan Dev Corp Ltd",
    "wof:placetype":"venue"
},
  "geometry": {"coordinates":[-111.380302,56.727188],"type":"Point"}
}