{
  "type": "Feature",
  "properties": {
    "addr:full":"Calgary AB T2H 0H9",
    "addr:postcode":"t2h 0h9",
    "iso:country":"CA",
    "sg:city":"Calgary",
    "sg:classifiers":[
        {
            "category":"Personal",
            "subcategory":"Beauty Salon",
            "type":"Services"
        }
    ],
    "sg:phone":"+1 403 255 4199",
    "sg:postcode":"T2H 0H9",
    "sg:province":"AB",
    "wof:name":"Hairdoo's",
    "wof:placetype":"venue"
},
  "geometry": {"coordinates":[-114.06933593799999,50.999671936],"type":"Point"}
}