{
  "type": "Feature",
  "properties": {
    "iso:country":"CA",
    "sg:city":"Toronto",
    "sg:classifiers":[
        {
            "category":"Real Estate",
            "subcategory":"Real Estate Agent",
            "type":"Services"
        }
    ],
    "sg:phone":"+1 416 531 6687",
    "sg:postcode":"M6K 2Z1",
    "sg:province":"ON",
    "wof:name":"Apartment Property Management",
    "wof:placetype":"venue"
},
  "geometry": {"coordinates":[-79.4365158081,43.6379890442],"type":"Point"}
}