{
  "type": "Feature",
  "properties": {
    "addr:full":"1000 Ch Du Lac Longueuil QC J4J 1W3",
    "addr:postcode":"1000;j4j 1w3",
    "addr:street":"Ch Du Lac",
    "iso:country":"CA",
    "sg:address":"1000 Ch Du Lac",
    "sg:city":"Longueuil",
    "sg:classifiers":[
        {
            "category":"Education",
            "subcategory":"School",
            "type":"Public Place"
        }
    ],
    "sg:phone":"+1 450 468 1247",
    "sg:postcode":"J4J 1W3",
    "sg:province":"QC",
    "wof:name":"Ecole Joseph DE Serigny",
    "wof:placetype":"venue"
},
  "geometry": {"coordinates":[-73.4754333496,45.5415534973],"type":"Point"}
}