{
  "type": "Feature",
  "properties": {
    "addr:full":"7870 Rue Louis-Vanier Saint-Leonard QC H1P 2K8",
    "addr:housenumber":"7870",
    "addr:postcode":"h1p 2k8",
    "addr:street":"Rue Louis-Vanier",
    "iso:country":"CA",
    "sg:address":"7870 Rue Louis-Vanier",
    "sg:city":"Saint-Leonard",
    "sg:classifiers":[
        {
            "category":"Wholesale",
            "subcategory":"Hardware",
            "type":"Manufacturing & Wholesale Goods"
        }
    ],
    "sg:phone":"+1 514 329 9999",
    "sg:postcode":"H1P 2K8",
    "sg:province":"QC",
    "sg:tags":[
        "machine",
        "making",
        "ice",
        "equipment"
    ],
    "wof:name":"Groupe Master Ltee",
    "wof:placetype":"venue"
},
  "geometry": {"coordinates":[-73.5847702026,45.5889511108],"type":"Point"}
}