{
  "type": "Feature",
  "properties": {
    "addr:full":"Coral Harbour Airport Coral Harbour NU X0C 0C0",
    "addr:postcode":"x0c 0c0",
    "iso:country":"CA",
    "sg:address":"Coral Harbour Airport",
    "sg:city":"Coral Harbour",
    "sg:classifiers":[
        {
            "category":"Airline",
            "type":"Transportation"
        }
    ],
    "sg:phone":"+1 867 925 8474",
    "sg:postcode":"X0C 0C0",
    "sg:province":"NU",
    "sg:tags":[
        "company"
    ],
    "wof:name":"Keewatin Air",
    "wof:placetype":"venue"
},
  "geometry": {"coordinates":[-83.366699,64.199997],"type":"Point"}
}