{
  "type": "Feature",
  "properties": {
    "addr:full":"Calgary AB T2E 7T1",
    "addr:postcode":"t2e 7t1",
    "iso:country":"CA",
    "sg:city":"Calgary",
    "sg:classifiers":[
        {
            "category":"Health Services",
            "subcategory":"Health Practitioner",
            "type":"Services"
        }
    ],
    "sg:phone":"+1 403 264 1130",
    "sg:postcode":"T2E 7T1",
    "sg:province":"AB",
    "sg:tags":[
        "audiologists"
    ],
    "wof:name":"Thm Industrial Audiology Ltd",
    "wof:placetype":"venue"
},
  "geometry": {"coordinates":[-114.009315491,51.0784568787],"type":"Point"}
}