{
  "type": "Feature",
  "properties": {
    "addr:full":"491 Lawrence Ave W North York ON M5M 1C7",
    "addr:housenumber":"491",
    "addr:postcode":"m5m 1c7",
    "addr:street":"Lawrence Ave W",
    "iso:country":"CA",
    "sg:address":"491 Lawrence Ave W",
    "sg:city":"North York",
    "sg:classifiers":[
        {
            "category":"Shopping",
            "subcategory":"Pharmacy",
            "type":"Retail Goods"
        }
    ],
    "sg:phone":"+1 416 781 5683",
    "sg:postcode":"M5M 1C7",
    "sg:province":"ON",
    "wof:name":"Peoples Drug Mart",
    "wof:placetype":"venue"
},
  "geometry": {"coordinates":[-79.429214,43.719257],"type":"Point"}
}