{
  "type": "Feature",
  "properties": {
    "addr:full":"9514 Rue Main Richibucto NB E4W 4E4",
    "addr:housenumber":"9514",
    "addr:postcode":"e4w 4e4",
    "addr:street":"Rue Main",
    "iso:country":"CA",
    "sg:address":"9514 Rue Main",
    "sg:city":"Richibucto",
    "sg:classifiers":[
        {
            "category":"Autos & Motor Vehicles",
            "subcategory":"Auto Supplies",
            "type":"Retail Goods"
        }
    ],
    "sg:phone":"+1 506 523 6779",
    "sg:postcode":"E4W 4E4",
    "sg:province":"NB",
    "sg:tags":[
        "automobile",
        "parts"
    ],
    "wof:name":"Mazerolle Auto Parts",
    "wof:placetype":"venue"
},
  "geometry": {"coordinates":[-64.867569,46.692108],"type":"Point"}
}