{
  "type": "Feature",
  "properties": {
    "addr:full":"8913 8E Av Montreal QC H1Z 2X9",
    "addr:housenumber":"8913",
    "addr:postcode":"h1z 2x9",
    "addr:street":"8E Av",
    "iso:country":"CA",
    "sg:address":"8913 8E Av",
    "sg:city":"Montreal",
    "sg:classifiers":[
        {
            "category":"Food & Beverages",
            "subcategory":"Bakery",
            "type":"Retail Goods"
        }
    ],
    "sg:phone":"+1 514 727 9555",
    "sg:postcode":"H1Z 2X9",
    "sg:province":"QC",
    "sg:tags":[
        "baker"
    ],
    "wof:name":"Boulangerie Multi-Marques Inc",
    "wof:placetype":"venue"
},
  "geometry": {"coordinates":[-73.62545799999999,45.568642],"type":"Point"}
}