{
  "type": "Feature",
  "properties": {
    "iso:country":"CA",
    "sg:address":"298 Archibald St",
    "sg:city":"Winnipeg",
    "sg:classifiers":[
        {
            "category":"Manufacturing",
            "subcategory":"Printing",
            "type":"Manufacturing & Wholesale Goods"
        }
    ],
    "sg:phone":"+1 204 233 7119",
    "sg:postcode":"R2J 3M4",
    "sg:province":"MB",
    "sg:tags":[
        "bookbinder",
        "loose",
        "leaf",
        "equipment"
    ],
    "wof:name":"Phil-Mar Trade Bindery Ltd",
    "wof:placetype":"venue"
},
  "geometry": {"coordinates":[-97.103546,49.892452],"type":"Point"}
}