{
  "type": "Feature",
  "properties": {
    "addr:full":"298 Archibald St Winnipeg MB R2J 3M4",
    "addr:housenumber":"298",
    "addr:postcode":"r2j 3m4",
    "addr:street":"Archibald St",
    "iso:country":"CA",
    "sg:address":"298 Archibald St",
    "sg:city":"Winnipeg",
    "sg:classifiers":[
        {
            "category":"Manufacturing",
            "subcategory":"Printing",
            "type":"Manufacturing & Wholesale Goods"
        }
    ],
    "sg:phone":"+1 204 233 7119",
    "sg:postcode":"R2J 3M4",
    "sg:province":"MB",
    "sg:tags":[
        "bookbinder",
        "loose",
        "leaf",
        "equipment"
    ],
    "wof:name":"Phil-Mar Trade Bindery Ltd",
    "wof:placetype":"venue"
},
  "geometry": {"coordinates":[-97.10354599999999,49.892452],"type":"Point"}
}