{
  "type": "Feature",
  "properties": {
    "addr:full":"Principale St Harrington Harbour QC G0G 1N0",
    "addr:postcode":"g0g 1n0",
    "addr:street":"Principale St",
    "iso:country":"CA",
    "sg:address":"Principale St",
    "sg:city":"Harrington Harbour",
    "sg:classifiers":[
        {
            "category":"Education",
            "subcategory":"School",
            "type":"Public Place"
        }
    ],
    "sg:phone":"+1 418 229 2450",
    "sg:postcode":"G0G 1N0",
    "sg:province":"QC",
    "wof:name":"Ecole Olamen",
    "wof:placetype":"venue"
},
  "geometry": {"coordinates":[-59.478401,50.497078],"type":"Point"}
}