{
  "type": "Feature",
  "properties": {
    "addr:full":"158 Maclaren St Ottawa ON K2P 0K9",
    "addr:housenumber":"158",
    "addr:postcode":"k2p 0k9",
    "addr:street":"Maclaren St",
    "iso:country":"CA",
    "sg:address":"158 Maclaren St",
    "sg:city":"Ottawa",
    "sg:classifiers":[
        {
            "category":"Health Services",
            "subcategory":"Medical Lab",
            "type":"Services"
        }
    ],
    "sg:phone":"+1 613 230 1527",
    "sg:postcode":"K2P 0K9",
    "sg:province":"ON",
    "wof:name":"H D Alvarez Denture Clinic",
    "wof:placetype":"venue"
},
  "geometry": {"coordinates":[-75.688744,45.417503],"type":"Point"}
}