{
  "type": "Feature",
  "properties": {
    "addr:full":"10138 79 St NW Edmonton AB T6A 3G3",
    "addr:housenumber":"10138",
    "addr:postcode":"t6a 3g3",
    "addr:street":"79 St Nw",
    "iso:country":"CA",
    "sg:address":"10138 79 St NW",
    "sg:city":"Edmonton",
    "sg:classifiers":[
        {
            "category":"Personal",
            "subcategory":"Beauty Salon",
            "type":"Services"
        }
    ],
    "sg:phone":"+1 780 466 5110",
    "sg:postcode":"T6A 3G3",
    "sg:province":"AB",
    "sg:tags":[
        "tanning"
    ],
    "wof:name":"Beach Bumms Tanning Studio Ltd",
    "wof:placetype":"venue"
},
  "geometry": {"coordinates":[-113.449524,53.542],"type":"Point"}
}