{
  "type": "Feature",
  "properties": {
    "addr:full":"9711 42 Ave NW Edmonton AB T6E 5P8",
    "addr:housenumber":"9711",
    "addr:postcode":"t6e 5p8",
    "addr:street":"42 Ave Nw",
    "iso:country":"CA",
    "sg:address":"9711 42 Ave NW",
    "sg:city":"Edmonton",
    "sg:classifiers":[
        {
            "category":"Building & Trades",
            "subcategory":"Construction",
            "type":"Services"
        }
    ],
    "sg:phone":"+1 780 463 9711",
    "sg:postcode":"T6E 5P8",
    "sg:province":"AB",
    "sg:tags":[
        "general",
        "contractor"
    ],
    "wof:name":"Vetsch Brothers Ltd",
    "wof:placetype":"venue"
},
  "geometry": {"coordinates":[-113.47995758099999,53.478603363],"type":"Point"}
}