{
  "type": "Feature",
  "properties": {
    "iso:country":"CA",
    "sg:address":"94 Brockport Dr",
    "sg:city":"Etobicoke",
    "sg:classifiers":[
        {
            "category":"Professional",
            "type":"Services"
        }
    ],
    "sg:phone":"+1 416 675 3933",
    "sg:postcode":"M9W 5C5",
    "sg:province":"ON",
    "sg:tags":[
        "printing",
        "establishment",
        "supply"
    ],
    "wof:name":"A B Dick CO of Canada Ltd",
    "wof:placetype":"venue"
},
  "geometry": {"coordinates":[-79.5863571167,43.6964263916],"type":"Point"}
}