{
  "type": "Feature",
  "properties": {
    "addr:full":"851 Rue Terrill Sherbrooke QC J1E 1M2",
    "addr:housenumber":"851",
    "addr:postcode":"j1e 1m2",
    "addr:street":"Rue Terrill",
    "iso:country":"CA",
    "sg:address":"851 Rue Terrill",
    "sg:city":"Sherbrooke",
    "sg:classifiers":[
        {
            "category":"Food & Beverages",
            "subcategory":"Groceries & Convenience Stores",
            "type":"Retail Goods"
        }
    ],
    "sg:phone":"+1 819 569 7770",
    "sg:postcode":"J1E 1M2",
    "sg:province":"QC",
    "wof:name":"Couche-Tard",
    "wof:placetype":"venue"
},
  "geometry": {"coordinates":[-71.87247499999999,45.416672],"type":"Point"}
}