{
  "type": "Feature",
  "properties": {
    "iso:country":"CA",
    "sg:address":"851 Rue Terrill",
    "sg:city":"Sherbrooke",
    "sg:classifiers":[
        {
            "category":"Food & Beverages",
            "subcategory":"Groceries & Convenience Stores",
            "type":"Retail Goods"
        }
    ],
    "sg:phone":"+1 819 569 7770",
    "sg:postcode":"J1E 1M2",
    "sg:province":"QC",
    "wof:name":"Couche-Tard",
    "wof:placetype":"venue"
},
  "geometry": {"coordinates":[-71.872475,45.416672],"type":"Point"}
}