{
  "type": "Feature",
  "properties": {
    "addr:full":"749 King St W Kitchener ON N2G 1E4",
    "addr:housenumber":"749",
    "addr:postcode":"n2g 1e4",
    "addr:street":"King St W",
    "iso:country":"CA",
    "sg:address":"749 King St W",
    "sg:city":"Kitchener",
    "sg:classifiers":[
        {
            "category":"Real Estate",
            "subcategory":"Real Estate Agent",
            "type":"Services"
        }
    ],
    "sg:phone":"+1 519 744 3581",
    "sg:postcode":"N2G 1E4",
    "sg:province":"ON",
    "sg:tags":[
        "physician",
        "surgeon",
        "management"
    ],
    "wof:name":"Central Medical Building",
    "wof:placetype":"venue"
},
  "geometry": {"coordinates":[-80.507233,43.455578],"type":"Point"}
}