{
  "type": "Feature",
  "properties": {
    "iso:country":"CA",
    "sg:address":"191 Rue Empire",
    "sg:city":"Granby",
    "sg:classifiers":[
        {
            "category":"Professional",
            "subcategory":"Lawyer & Legal Services",
            "type":"Services"
        }
    ],
    "sg:phone":"+1 450 372 9892",
    "sg:postcode":"J2G 3B3",
    "sg:province":"QC",
    "sg:tags":[
        "attorney"
    ],
    "wof:name":"Huppe, Martin",
    "wof:placetype":"venue"
},
  "geometry": {"coordinates":[-72.72821807859999,45.3988075256],"type":"Point"}
}