{
  "type": "Feature",
  "properties": {
    "iso:country":"CA",
    "sg:city":"Kitchener",
    "sg:classifiers":[
        {
            "category":"Shopping",
            "type":"Retail Goods"
        }
    ],
    "sg:phone":"+1 519 742 5414",
    "sg:postcode":"N2B 1L3",
    "sg:province":"ON",
    "sg:tags":[
        "pet",
        "shop",
        "supply"
    ],
    "wof:name":"Animal Den",
    "wof:placetype":"venue"
},
  "geometry": {"coordinates":[-80.461906,43.45644],"type":"Point"}
}