{
  "type": "Feature",
  "properties": {
    "addr:full":"455 Av Bechard Vanier QC G1M 2G1",
    "addr:postcode":"g1m 2g1",
    "addr:street":"455 Av Bechard",
    "iso:country":"CA",
    "sg:address":"455 Av Bechard",
    "sg:city":"Vanier",
    "sg:classifiers":[
        {
            "category":"Shopping",
            "type":"Retail Goods"
        }
    ],
    "sg:phone":"+1 418 683 2388",
    "sg:postcode":"G1M 2G1",
    "sg:province":"QC",
    "sg:tags":[
        "dry",
        "oxygen",
        "ice"
    ],
    "wof:name":"Praxair",
    "wof:placetype":"venue"
},
  "geometry": {"coordinates":[-71.268944,46.816536],"type":"Point"}
}