{
  "type": "Feature",
  "properties": {
    "addr:full":"3204 Av Francis-Hughes Laval QC H7L 5A7",
    "addr:housenumber":"3204",
    "addr:postcode":"h7l 5a7",
    "addr:street":"Av Francis-Hughes",
    "iso:country":"CA",
    "sg:address":"3204 Av Francis-Hughes",
    "sg:city":"Laval",
    "sg:classifiers":[
        {
            "category":"Professional",
            "subcategory":"Computer Services",
            "type":"Services"
        }
    ],
    "sg:phone":"+1 450 668 4780",
    "sg:postcode":"H7L 5A7",
    "sg:province":"QC",
    "wof:name":"Ecmor",
    "wof:placetype":"venue"
},
  "geometry": {"coordinates":[-73.737991333,45.5932731628],"type":"Point"}
}