{
  "type": "Feature",
  "properties": {
    "addr:full":"97 Keewatin St Winnipeg MB R3E 3J1",
    "addr:housenumber":"97",
    "addr:postcode":"r3e 3j1",
    "addr:street":"Keewatin St",
    "iso:country":"CA",
    "sg:address":"97 Keewatin St",
    "sg:city":"Winnipeg",
    "sg:classifiers":[
        {
            "category":"Health Services",
            "subcategory":"Nursing And Care Facility",
            "type":"Services"
        }
    ],
    "sg:phone":"+1 204 632 0194",
    "sg:postcode":"R3E 3J1",
    "sg:province":"MB",
    "sg:tags":[
        "home",
        "retirement",
        "community"
    ],
    "wof:name":"Bluebird Lodge Senior Home",
    "wof:placetype":"venue"
},
  "geometry": {"coordinates":[-97.1948623657,49.9203491211],"type":"Point"}
}