{
  "type": "Feature",
  "properties": {
    "addr:full":"2959 Baker Rd Stevensville ON L0S 1S0",
    "addr:housenumber":"2959",
    "addr:postcode":"l0s 1s0",
    "addr:street":"Baker Rd",
    "iso:country":"CA",
    "sg:address":"2959 Baker Rd",
    "sg:city":"Stevensville",
    "sg:classifiers":[
        {
            "category":"Recreation",
            "type":"Entertainment"
        }
    ],
    "sg:phone":"+1 905 382 2306",
    "sg:postcode":"L0S 1S0",
    "sg:province":"ON",
    "sg:tags":[
        "center"
    ],
    "wof:name":"Black Creek Community Assoc",
    "wof:placetype":"venue"
},
  "geometry": {"coordinates":[-79.054672,42.943707],"type":"Point"}
}