{
  "type": "Feature",
  "properties": {
    "addr:full":"Cayuga ON N0A 1E0",
    "addr:postcode":"n0a 1e0",
    "iso:country":"CA",
    "sg:city":"Cayuga",
    "sg:classifiers":[
        {
            "category":"Wholesale",
            "subcategory":"Machinery & Supplies",
            "type":"Manufacturing & Wholesale Goods"
        }
    ],
    "sg:phone":"+1 905 772 1717",
    "sg:postcode":"N0A 1E0",
    "sg:province":"ON",
    "sg:tags":[
        "pump"
    ],
    "wof:name":"Cozy Heating & Water Systems",
    "wof:placetype":"venue"
},
  "geometry": {"coordinates":[-79.8601,42.949505],"type":"Point"}
}