{
  "type": "Feature",
  "properties": {
    "iso:country":"CA",
    "sg:address":"522 Lake St",
    "sg:city":"St Catharines",
    "sg:classifiers":[
        {
            "category":"Personal",
            "subcategory":"Beauty Salon",
            "type":"Services"
        }
    ],
    "sg:phone":"+1 905 935 6191",
    "sg:postcode":"L2N 4H4",
    "sg:province":"ON",
    "wof:name":"Susan's Hairstyles",
    "wof:placetype":"venue"
},
  "geometry": {"coordinates":[-79.2518615723,43.1903991699],"type":"Point"}
}