{
  "type": "Feature",
  "properties": {
    "addr:full":"Sainte-Martine QC J0S 1V0",
    "addr:postcode":"j0s 1v0",
    "iso:country":"CA",
    "sg:city":"Sainte-Martine",
    "sg:classifiers":[
        {
            "category":"Banks & Credit Unions",
            "subcategory":"Bank",
            "type":"Services"
        }
    ],
    "sg:phone":"+1 450 427 2015",
    "sg:postcode":"J0S 1V0",
    "sg:province":"QC",
    "wof:name":"Banque Nationale Du Canada",
    "wof:placetype":"venue"
},
  "geometry": {"coordinates":[-73.79866800000001,45.251141],"type":"Point"}
}