{
  "type": "Feature",
  "properties": {
    "iso:country":"CA",
    "sg:address":"88 Rue Hebert",
    "sg:city":"Sorel-Tracy",
    "sg:classifiers":[
        {
            "category":"Manufacturing",
            "subcategory":"Toys & Sporting Goods",
            "type":"Manufacturing & Wholesale Goods"
        }
    ],
    "sg:phone":"+1 450 743 3810",
    "sg:postcode":"J3P 4Z1",
    "sg:province":"QC",
    "sg:tags":[
        "equipment",
        "designer",
        "dealer",
        "pool",
        "swimming"
    ],
    "wof:name":"Piscines Rdr Enr",
    "wof:placetype":"venue"
},
  "geometry": {"coordinates":[-73.11595916749999,46.0238227844],"type":"Point"}
}