{
  "type": "Feature",
  "properties": {
    "addr:full":"1500 Church Ave Winnipeg MB R2X 1G6",
    "addr:housenumber":"1500",
    "addr:postcode":"r2x 1g6",
    "addr:street":"Church Ave",
    "iso:country":"CA",
    "sg:address":"1500 Church Ave",
    "sg:city":"Winnipeg",
    "sg:classifiers":[
        {
            "category":"Home & Garden",
            "subcategory":"Building Materials",
            "type":"Retail Goods"
        }
    ],
    "sg:phone":"+1 204 694 0101",
    "sg:postcode":"R2X 1G6",
    "sg:province":"MB",
    "sg:tags":[
        "door"
    ],
    "wof:name":"Inkster Park Millwork Ltd",
    "wof:placetype":"venue"
},
  "geometry": {"coordinates":[-97.1799545288,49.9391746521],"type":"Point"}
}