{
  "type": "Feature",
  "properties": {
    "iso:country":"CA",
    "sg:address":"275 Boul Samson",
    "sg:city":"Laval",
    "sg:classifiers":[
        {
            "category":"Personal",
            "subcategory":"Beauty Salon",
            "type":"Services"
        }
    ],
    "sg:phone":"+1 450 689 7624",
    "sg:postcode":"H7X 2Z7",
    "sg:province":"QC",
    "wof:name":"Haute Coiffure Sandra",
    "wof:placetype":"venue"
},
  "geometry": {"coordinates":[-73.800957,45.522785],"type":"Point"}
}