{
  "type": "Feature",
  "properties": {
    "addr:full":"129 Kenyon St W Alexandria ON K0C 1A0",
    "addr:housenumber":"129",
    "addr:postcode":"k0c 1a0",
    "addr:street":"Kenyon St W",
    "iso:country":"CA",
    "sg:address":"129 Kenyon St W",
    "sg:city":"Alexandria",
    "sg:classifiers":[
        {
            "category":"Retail",
            "subcategory":"Auto Repair",
            "type":"Services"
        }
    ],
    "sg:phone":"+1 613 525 4309",
    "sg:postcode":"K0C 1A0",
    "sg:province":"ON",
    "sg:tags":[
        "repairing",
        "automobile"
    ],
    "wof:name":"Yves Lamoureux Svc Station",
    "wof:placetype":"venue"
},
  "geometry": {"coordinates":[-74.64166259770001,45.3090324402],"type":"Point"}
}