{
  "type": "Feature",
  "properties": {
    "addr:full":"PO Box 68 Cumberland House SK S0E 0S0",
    "addr:housenumber":"po box 68",
    "addr:postcode":"s0e 0s0",
    "iso:country":"CA",
    "sg:address":"PO Box 68",
    "sg:city":"Cumberland House",
    "sg:classifiers":[
        {
            "category":"Organizations",
            "subcategory":"Religious Organization",
            "type":"Services"
        }
    ],
    "sg:phone":"+1 306 888 2050",
    "sg:postcode":"S0E 0S0",
    "sg:province":"SK",
    "sg:tags":[
        "church"
    ],
    "wof:name":"Christian Fellowship Ctr",
    "wof:placetype":"venue"
},
  "geometry": {"coordinates":[-102.267616,53.95533],"type":"Point"}
}