{
  "type": "Feature",
  "properties": {
    "addr:full":"248 Whiteridge Pl NE Calgary AB T1Y 4K3",
    "addr:housenumber":"248",
    "addr:postcode":"t1y 4k3",
    "addr:street":"Whiteridge Pl Ne",
    "iso:country":"CA",
    "sg:address":"248 Whiteridge Pl NE",
    "sg:city":"Calgary",
    "sg:classifiers":[
        {
            "category":"Wholesale",
            "subcategory":"Electrical",
            "type":"Manufacturing & Wholesale Goods"
        }
    ],
    "sg:phone":"+1 403 293 1159",
    "sg:postcode":"T1Y 4K3",
    "sg:province":"AB",
    "sg:tags":[
        "equipment",
        "electric"
    ],
    "wof:name":"Bel-Cor Agencies",
    "wof:placetype":"venue"
},
  "geometry": {"coordinates":[-113.96395099999999,51.089153],"type":"Point"}
}