{
  "type": "Feature",
  "properties": {
    "addr:full":"North Wiltshire PE C0A 1Y0",
    "addr:postcode":"c0a 1y0",
    "iso:country":"CA",
    "sg:city":"North Wiltshire",
    "sg:classifiers":[
        {
            "category":"Farming",
            "subcategory":"Dairy Farm",
            "type":"Manufacturing & Wholesale Goods"
        }
    ],
    "sg:phone":"+1 902 621 0225",
    "sg:postcode":"C0A 1Y0",
    "sg:province":"PE",
    "wof:name":"Wiltshire Dairying CO Ltd",
    "wof:placetype":"venue"
},
  "geometry": {"coordinates":[-63.335064,46.302067],"type":"Point"}
}