{
  "type": "Feature",
  "properties": {
    "addr:full":"56 Fire 33 Rd Havelock ON K0L 1Z0",
    "addr:housenumber":"56;33",
    "addr:postcode":"k0l 1z0",
    "addr:street":"Fire;Rd",
    "iso:country":"CA",
    "sg:address":"56 Fire 33 Rd",
    "sg:city":"Havelock",
    "sg:classifiers":[
        {
            "category":"Recreation",
            "subcategory":"Marina",
            "type":"Entertainment"
        }
    ],
    "sg:phone":"+1 705 778 2366",
    "sg:postcode":"K0L 1Z0",
    "sg:province":"ON",
    "wof:name":"Belmont Lake Marina",
    "wof:placetype":"venue"
},
  "geometry": {"coordinates":[-77.886383,44.433201],"type":"Point"}
}