{
  "type": "Feature",
  "properties": {
    "addr:full":"Hwy 2A High Prairie AB T0G 1E0",
    "addr:postcode":"t0g 1e0",
    "addr:street":"Hwy 2A",
    "iso:country":"CA",
    "sg:address":"Hwy 2A",
    "sg:city":"High Prairie",
    "sg:classifiers":[
        {
            "category":"Travel",
            "subcategory":"Hotels & Motels",
            "type":"Entertainment"
        }
    ],
    "sg:phone":"+1 780 523 5789",
    "sg:postcode":"T0G 1E0",
    "sg:province":"AB",
    "wof:name":"Sunset Cottage Guesthouse",
    "wof:placetype":"venue"
},
  "geometry": {"coordinates":[-116.477050781,55.4328651428],"type":"Point"}
}