{
  "type": "Feature",
  "properties": {
    "addr:full":"1494 Rue Du Meleze Baie-Comeau QC G5C 3P7",
    "addr:housenumber":"1494",
    "addr:postcode":"g5c 3p7",
    "addr:street":"Rue Du Meleze",
    "iso:country":"CA",
    "sg:address":"1494 Rue Du Meleze",
    "sg:city":"Baie-Comeau",
    "sg:classifiers":[
        {
            "category":"Building & Trades",
            "subcategory":"Construction",
            "type":"Services"
        }
    ],
    "sg:phone":"+1 418 295 2160",
    "sg:postcode":"G5C 3P7",
    "sg:province":"QC",
    "sg:tags":[
        "designer"
    ],
    "wof:name":"Dessins Cadxpert Enr",
    "wof:placetype":"venue"
},
  "geometry": {"coordinates":[-68.2668228149,49.2012710571],"type":"Point"}
}