{
  "type": "Feature",
  "properties": {
    "addr:full":"7040 Edwards Blvd Mississauga ON L5S 1Z1",
    "addr:housenumber":"7040",
    "addr:postcode":"l5s 1z1",
    "addr:street":"Edwards Blvd",
    "iso:country":"CA",
    "sg:address":"7040 Edwards Blvd",
    "sg:city":"Mississauga",
    "sg:classifiers":[
        {
            "category":"Travel",
            "subcategory":"Hotels & Motels",
            "type":"Entertainment"
        }
    ],
    "sg:phone":"+1 905 564 2122",
    "sg:postcode":"L5S 1Z1",
    "sg:province":"ON",
    "wof:name":"Hampton Inn",
    "wof:placetype":"venue"
},
  "geometry": {"coordinates":[-79.704674,43.649334],"type":"Point"}
}