{
  "type": "Feature",
  "properties": {
    "addr:full":"825 Rue Principale E Parisville QC G0S 1X0",
    "addr:housenumber":"825",
    "addr:postcode":"g0s 1x0",
    "addr:street":"Rue Principale E",
    "iso:country":"CA",
    "sg:address":"825 Rue Principale E",
    "sg:city":"Parisville",
    "sg:classifiers":[
        {
            "category":"Building & Trades",
            "subcategory":"Cleaning & Sanitation",
            "type":"Services"
        }
    ],
    "sg:phone":"+1 819 292 2174",
    "sg:postcode":"G0S 1X0",
    "sg:province":"QC",
    "sg:tags":[
        "snow",
        "removal"
    ],
    "wof:name":"Entreprises Jacques Beaudet",
    "wof:placetype":"venue"
},
  "geometry": {"coordinates":[-72.05680847169999,46.5220413208],"type":"Point"}
}