{
  "type": "Feature",
  "properties": {
    "addr:full":"75 Unsworth Dr Hamilton ON L8W 2T7",
    "addr:housenumber":"75",
    "addr:postcode":"l8w 2t7",
    "addr:street":"Unsworth Dr",
    "iso:country":"CA",
    "sg:address":"75 Unsworth Dr",
    "sg:city":"Hamilton",
    "sg:classifiers":[
        {
            "category":"Wholesale",
            "subcategory":"Machinery & Supplies",
            "type":"Manufacturing & Wholesale Goods"
        }
    ],
    "sg:phone":"+1 905 318 4051",
    "sg:postcode":"L8W 2T7",
    "sg:province":"ON",
    "sg:tags":[
        "salon",
        "beauty"
    ],
    "wof:name":"Radiant Beauty Supplies",
    "wof:placetype":"venue"
},
  "geometry": {"coordinates":[-79.8405075073,43.1945304871],"type":"Point"}
}