{
  "type": "Feature",
  "properties": {
    "addr:full":"4375 Macdonald Rd Armstrong BC V0E 1B5",
    "addr:housenumber":"4375",
    "addr:postcode":"v0e 1b5",
    "addr:street":"Macdonald Rd",
    "iso:country":"CA",
    "sg:address":"4375 Macdonald Rd",
    "sg:city":"Armstrong",
    "sg:classifiers":[
        {
            "category":"Home & Garden",
            "subcategory":"Building Materials",
            "type":"Retail Goods"
        }
    ],
    "sg:phone":"+1 250 546 2966",
    "sg:postcode":"V0E 1B5",
    "sg:province":"BC",
    "sg:tags":[
        "windows"
    ],
    "wof:name":"Westwood Custom Windows-Doors",
    "wof:placetype":"venue"
},
  "geometry": {"coordinates":[-119.183700562,50.4418182373],"type":"Point"}
}