{
  "type": "Feature",
  "properties": {
    "addr:full":"491 Berkley Cres NW Calgary AB T3K 1A9",
    "addr:housenumber":"491",
    "addr:postcode":"t3k 1a9",
    "addr:street":"Berkley Cres Nw",
    "iso:country":"CA",
    "sg:address":"491 Berkley Cres NW",
    "sg:city":"Calgary",
    "sg:classifiers":[
        {
            "category":"Building & Trades",
            "subcategory":"Cleaning & Sanitation",
            "type":"Services"
        }
    ],
    "sg:phone":"+1 403 274 6900",
    "sg:postcode":"T3K 1A9",
    "sg:province":"AB",
    "sg:tags":[
        "window",
        "janitor"
    ],
    "wof:name":"Skyline Window Cleaning Ltd",
    "wof:placetype":"venue"
},
  "geometry": {"coordinates":[-114.081841,51.12574],"type":"Point"}
}