{
  "type": "Feature",
  "properties": {
    "addr:full":"5839 Boul Davis Saint-Hubert QC J3Y 8G4",
    "addr:housenumber":"5839",
    "addr:postcode":"j3y 8g4",
    "addr:street":"Boul Davis",
    "iso:country":"CA",
    "sg:address":"5839 Boul Davis",
    "sg:city":"Saint-Hubert",
    "sg:classifiers":[
        {
            "category":"Personal",
            "type":"Services"
        }
    ],
    "sg:phone":"+1 450 445 0800",
    "sg:postcode":"J3Y 8G4",
    "sg:province":"QC",
    "sg:tags":[
        "electrolysis"
    ],
    "wof:name":"Electrolyse & Epilation",
    "wof:placetype":"venue"
},
  "geometry": {"coordinates":[-73.41778600000001,45.490414],"type":"Point"}
}