{
  "type": "Feature",
  "properties": {
    "iso:country":"CA",
    "sg:address":"10121 Glendon Dr",
    "sg:city":"Komoka",
    "sg:classifiers":[
        {
            "category":"Personal",
            "type":"Services"
        }
    ],
    "sg:phone":"+1 519 472 0991",
    "sg:postcode":"N0L 1R0",
    "sg:province":"ON",
    "sg:tags":[
        "therapist",
        "massage"
    ],
    "wof:name":"Komoka Massage Therapy",
    "wof:placetype":"venue"
},
  "geometry": {"coordinates":[-81.4240722656,42.9502105713],"type":"Point"}
}