{
  "type": "Feature",
  "properties": {
    "addr:full":"10757 95 St NW Edmonton AB T5H 2E1",
    "addr:housenumber":"10757",
    "addr:postcode":"edmonton ab t5h 2e1",
    "addr:street":"95 St Nw",
    "iso:country":"CA",
    "sg:address":"10757 95 St NW",
    "sg:city":"Edmonton",
    "sg:classifiers":[
        {
            "category":"Food & Beverages",
            "subcategory":"Meat & Fish",
            "type":"Retail Goods"
        }
    ],
    "sg:phone":"+1 780 422 6473",
    "sg:postcode":"T5H 2E1",
    "sg:province":"AB",
    "wof:name":"Italian Canadian Meats Ltd",
    "wof:placetype":"venue"
},
  "geometry": {"coordinates":[-113.48350499999999,53.554241],"type":"Point"}
}