{
  "type": "Feature",
  "properties": {
    "addr:full":"Richmond Hill ON L4C 9Y7",
    "addr:postcode":"l4c 9y7",
    "iso:country":"CA",
    "sg:city":"Richmond Hill",
    "sg:classifiers":[
        {
            "category":"Building & Trades",
            "subcategory":"Construction",
            "type":"Services"
        }
    ],
    "sg:phone":"+1 905 737 5617",
    "sg:postcode":"L4C 9Y7",
    "sg:province":"ON",
    "sg:tags":[
        "general",
        "contractor"
    ],
    "wof:name":"Classicon Trades Inc",
    "wof:placetype":"venue"
},
  "geometry": {"coordinates":[-79.42938232420001,43.8975753784],"type":"Point"}
}