{
  "type": "Feature",
  "properties": {
    "iso:country":"CA",
    "sg:address":"273 Vaughan Rd",
    "sg:city":"York",
    "sg:classifiers":[
        {
            "category":"Organizations",
            "subcategory":"Religious Organization",
            "type":"Services"
        }
    ],
    "sg:phone":"+1 416 652 6209",
    "sg:postcode":"M6C 2N2",
    "sg:province":"ON",
    "sg:tags":[
        "church"
    ],
    "wof:name":"Church of Jesus Christ",
    "wof:placetype":"venue"
},
  "geometry": {"coordinates":[-79.426605,43.688885],"type":"Point"}
}