{
  "type": "Feature",
  "properties": {
    "addr:full":"453 Av DE LA Sabliere Sainte-Marie QC G6E 3E9",
    "addr:postcode":"g6e 3e9",
    "addr:street":"453 Av De La Sabliere",
    "iso:country":"CA",
    "sg:address":"453 Av DE LA Sabliere",
    "sg:city":"Sainte-Marie",
    "sg:classifiers":[
        {
            "category":"Personal",
            "subcategory":"Beauty Salon",
            "type":"Services"
        }
    ],
    "sg:phone":"+1 418 387 8053",
    "sg:postcode":"G6E 3E9",
    "sg:province":"QC",
    "wof:name":"Salon D'Electrolyse Follicule",
    "wof:placetype":"venue"
},
  "geometry": {"coordinates":[-71.0418395996,46.4682655334],"type":"Point"}
}