{
  "type": "Feature",
  "properties": {
    "iso:country":"CA",
    "sg:address":"234 Wellington St",
    "sg:city":"West Lorne",
    "sg:classifiers":[
        {
            "category":"Retail",
            "subcategory":"Laundry & Dry Cleaning",
            "type":"Services"
        }
    ],
    "sg:phone":"+1 519 768 2620",
    "sg:postcode":"N0L 2P0",
    "sg:province":"ON",
    "sg:tags":[
        "cleaners",
        "rug",
        "carpet"
    ],
    "wof:name":"Labadies' Professional Carpet",
    "wof:placetype":"venue"
},
  "geometry": {"coordinates":[-81.6112747192,42.6010055542],"type":"Point"}
}