{
  "type": "Feature",
  "properties": {
    "iso:country":"CA",
    "sg:address":"4801 51 Ave",
    "sg:city":"Camrose",
    "sg:classifiers":[
        {
            "category":"Autos & Motor Vehicles",
            "subcategory":"Fuel & Gas Station",
            "type":"Retail Goods"
        }
    ],
    "sg:phone":"+1 780 672 2925",
    "sg:postcode":"T4V 0V4",
    "sg:province":"AB",
    "sg:tags":[
        "oil"
    ],
    "wof:name":"J & M Svc",
    "wof:placetype":"venue"
},
  "geometry": {"coordinates":[-112.821640015,53.0234184265],"type":"Point"}
}