{
  "type": "Feature",
  "properties": {
    "iso:country":"CA",
    "sg:city":"Vonda",
    "sg:classifiers":[
        {
            "category":"Wholesale",
            "subcategory":"Machinery & Supplies",
            "type":"Manufacturing & Wholesale Goods"
        }
    ],
    "sg:phone":"+1 306 258 2175",
    "sg:postcode":"S0K 4N0",
    "sg:province":"SK",
    "sg:tags":[
        "equipment",
        "implement",
        "spraying",
        "agricultural"
    ],
    "wof:name":"Spray-Tech Systems Ltd",
    "wof:placetype":"venue"
},
  "geometry": {"coordinates":[-106.099868774,52.3182601929],"type":"Point"}
}