{
  "type": "Feature",
  "properties": {
    "iso:country":"CA",
    "sg:address":"151 Bentley Ave",
    "sg:city":"Nepean",
    "sg:classifiers":[
        {
            "category":"Manufacturing",
            "subcategory":"Tools & Machinery",
            "type":"Manufacturing & Wholesale Goods"
        }
    ],
    "sg:phone":"+1 613 723 3445",
    "sg:postcode":"K2E 6T7",
    "sg:province":"ON",
    "sg:tags":[
        "machine",
        "shop"
    ],
    "wof:name":"Fresa Precision Machining",
    "wof:placetype":"venue"
},
  "geometry": {"coordinates":[-75.71144104,45.3364944458],"type":"Point"}
}