{
  "type": "Feature",
  "properties": {
    "iso:country":"CA",
    "sg:address":"220 Av Des Lacasse",
    "sg:city":"Laval",
    "sg:classifiers":[
        {
            "category":"Retail",
            "subcategory":"Repair Shop",
            "type":"Services"
        }
    ],
    "sg:phone":"+1 450 625 9388",
    "sg:postcode":"H7K 1J1",
    "sg:province":"QC",
    "sg:tags":[
        "welding"
    ],
    "wof:name":"Soudure Generale L Bouchard",
    "wof:placetype":"venue"
},
  "geometry": {"coordinates":[-73.742638,45.620667],"type":"Point"}
}