{
  "type": "Feature",
  "properties": {
    "addr:full":"27 Medulla Ave Etobicoke ON M8Z 5L6",
    "addr:housenumber":"27",
    "addr:postcode":"m8z 5l6",
    "addr:street":"Medulla Ave",
    "iso:country":"CA",
    "sg:address":"27 Medulla Ave",
    "sg:city":"Etobicoke",
    "sg:classifiers":[
        {
            "category":"Retail",
            "subcategory":"Auto Repair",
            "type":"Services"
        }
    ],
    "sg:phone":"+1 416 239 0088",
    "sg:postcode":"M8Z 5L6",
    "sg:province":"ON",
    "sg:tags":[
        "truck"
    ],
    "wof:name":"Diesel Truck Svc Ltd",
    "wof:placetype":"venue"
},
  "geometry": {"coordinates":[-79.5458450317,43.6227722168],"type":"Point"}
}