{
  "type": "Feature",
  "properties": {
    "iso:country":"CA",
    "sg:address":"28 Pallo Close",
    "sg:city":"Red Deer",
    "sg:classifiers":[
        {
            "category":"Mining & Drilling",
            "type":"Manufacturing & Wholesale Goods"
        }
    ],
    "sg:phone":"+1 403 346 1012",
    "sg:postcode":"T4P 1J3",
    "sg:province":"AB",
    "sg:tags":[
        "field",
        "oil"
    ],
    "wof:name":"Pamoco Petroleum Ltd",
    "wof:placetype":"venue"
},
  "geometry": {"coordinates":[-113.806381226,52.2906837463],"type":"Point"}
}