{
  "type": "Feature",
  "properties": {
    "addr:full":"255 Rue Celanese Drummondville QC J2B 5J7",
    "addr:housenumber":"255",
    "addr:postcode":"j2b 5j7",
    "addr:street":"Rue Celanese",
    "iso:country":"CA",
    "sg:address":"255 Rue Celanese",
    "sg:city":"Drummondville",
    "sg:classifiers":[
        {
            "category":"Personal",
            "subcategory":"Beauty Salon",
            "type":"Services"
        }
    ],
    "sg:phone":"+1 819 474 6868",
    "sg:postcode":"J2B 5J7",
    "sg:province":"QC",
    "wof:name":"Tribu Coiffure",
    "wof:placetype":"venue"
},
  "geometry": {"coordinates":[-72.47686,45.87434],"type":"Point"}
}