{
  "type": "Feature",
  "properties": {
    "addr:full":"2110 Skeena St Vancouver BC V5M 3Y3",
    "addr:housenumber":"2110",
    "addr:postcode":"v5m 3y3",
    "addr:street":"Skeena St",
    "iso:country":"CA",
    "sg:address":"2110 Skeena St",
    "sg:city":"Vancouver",
    "sg:classifiers":[
        {
            "category":"Manufacturing",
            "subcategory":"Glass & Minerals",
            "type":"Manufacturing & Wholesale Goods"
        }
    ],
    "sg:phone":"+1 604 299 7301",
    "sg:postcode":"V5M 3Y3",
    "sg:province":"BC",
    "sg:tags":[
        "tile",
        "granite"
    ],
    "wof:name":"Att Stoneworks Ltd",
    "wof:placetype":"venue"
},
  "geometry": {"coordinates":[-123.028313,49.265354],"type":"Point"}
}