{
  "type": "Feature",
  "properties": {
    "addr:full":"1657 Barrington St Halifax NS B3J 2A1",
    "addr:housenumber":"1657",
    "addr:postcode":"ns b3j 2a1",
    "addr:street":"Barrington St",
    "iso:country":"CA",
    "sg:address":"1657 Barrington St",
    "sg:city":"Halifax",
    "sg:classifiers":[
        {
            "category":"Education",
            "subcategory":"Special Training",
            "type":"Public Place"
        }
    ],
    "sg:phone":"+1 902 422 7648",
    "sg:postcode":"B3J 2A1",
    "sg:province":"NS",
    "sg:tags":[
        "reading",
        "instruction",
        "improvement"
    ],
    "wof:name":"Halifax Community Learning",
    "wof:placetype":"venue"
},
  "geometry": {"coordinates":[-63.5736541748,44.6468544006],"type":"Point"}
}