{
  "type": "Feature",
  "properties": {
    "addr:full":"3 Cote Dinan Quebec QC G1K 3V5",
    "addr:housenumber":"3",
    "addr:postcode":"g1k 3v5",
    "addr:street":"Cote Dinan",
    "iso:country":"CA",
    "sg:address":"3 Cote Dinan",
    "sg:city":"Quebec",
    "sg:classifiers":[
        {
            "category":"Real Estate",
            "subcategory":"Architect",
            "type":"Services"
        }
    ],
    "sg:phone":"+1 418 692 4610",
    "sg:postcode":"G1K 3V5",
    "sg:province":"QC",
    "wof:name":"Amiot & Bergeron",
    "wof:placetype":"venue"
},
  "geometry": {"coordinates":[-71.20980072019999,46.8165435791],"type":"Point"}
}