{
  "type": "Feature",
  "properties": {
    "addr:full":"8767 132 St Surrey BC V3W 4P1",
    "addr:housenumber":"8767",
    "addr:postcode":"v3w 4p1",
    "addr:street":"132 St",
    "iso:country":"CA",
    "sg:address":"8767 132 St",
    "sg:city":"Surrey",
    "sg:classifiers":[
        {
            "category":"Government",
            "subcategory":"Fire Station",
            "type":"Public Place"
        }
    ],
    "sg:phone":"+1 604 543 6700",
    "sg:postcode":"V3W 4P1",
    "sg:province":"BC",
    "sg:tags":[
        "department"
    ],
    "wof:name":"Surrey Fire Dept",
    "wof:placetype":"venue"
},
  "geometry": {"coordinates":[-122.857063294,49.162021637],"type":"Point"}
}