{
  "type": "Feature",
  "properties": {
    "addr:full":"Edmonton AB T5S 1R5",
    "addr:postcode":"t5s 1r5",
    "iso:country":"CA",
    "sg:city":"Edmonton",
    "sg:classifiers":[
        {
            "category":"Social Services",
            "subcategory":"Child Care",
            "type":"Services"
        }
    ],
    "sg:phone":"+1 780 489 2626",
    "sg:postcode":"T5S 1R5",
    "sg:province":"AB",
    "wof:name":"It's A Child's World Family",
    "wof:placetype":"venue"
},
  "geometry": {"coordinates":[-113.627151489,53.546081543],"type":"Point"}
}