{
  "type": "Feature",
  "properties": {
    "addr:full":"319 Still's Lane Oakville ON L6J 5Y5",
    "addr:housenumber":"319",
    "addr:postcode":"l6j 5y5",
    "addr:street":"Still'S Lane",
    "iso:country":"CA",
    "sg:address":"319 Still's Lane",
    "sg:city":"Oakville",
    "sg:classifiers":[
        {
            "category":"Real Estate",
            "subcategory":"Real Estate Agent",
            "type":"Services"
        }
    ],
    "sg:phone":"+1 905 338 8080",
    "sg:postcode":"L6J 5Y5",
    "sg:province":"ON",
    "wof:name":"Procomm Realty Corp",
    "wof:placetype":"venue"
},
  "geometry": {"coordinates":[-79.68956756590001,43.4661903381],"type":"Point"}
}