{
  "type": "Feature",
  "properties": {
    "addr:full":"6772 14th Ave Markham ON L6B 1A8",
    "addr:housenumber":"6772",
    "addr:postcode":"l6b 1a8",
    "addr:street":"14Th Ave",
    "iso:country":"CA",
    "sg:address":"6772 14th Ave",
    "sg:city":"Markham",
    "sg:classifiers":[
        {
            "category":"Building & Trades",
            "subcategory":"Construction",
            "type":"Services"
        }
    ],
    "sg:phone":"+1 905 294 7090",
    "sg:postcode":"L6B 1A8",
    "sg:province":"ON",
    "sg:tags":[
        "painter"
    ],
    "wof:name":"Glover & Assoc Painting Ltd",
    "wof:placetype":"venue"
},
  "geometry": {"coordinates":[-79.228973,43.860043],"type":"Point"}
}