{
  "type": "Feature",
  "properties": {
    "iso:country":"CA",
    "sg:address":"3035 Osler St",
    "sg:city":"London",
    "sg:classifiers":[
        {
            "category":"Retail",
            "subcategory":"Auto Repair",
            "type":"Services"
        }
    ],
    "sg:phone":"+1 519 455 8430",
    "sg:postcode":"N5V 1V4",
    "sg:province":"ON",
    "sg:tags":[
        "repairing",
        "automobile",
        "boot",
        "shoe"
    ],
    "wof:name":"Country Repair",
    "wof:placetype":"venue"
},
  "geometry": {"coordinates":[-81.15836334230001,43.0116500854],"type":"Point"}
}