{
  "type": "Feature",
  "properties": {
    "addr:full":"Grande Prairie AB T8V 0R9",
    "addr:postcode":"t8v 0r9",
    "iso:country":"CA",
    "sg:city":"Grande Prairie",
    "sg:classifiers":[
        {
            "category":"Restaurant",
            "type":"Food & Drink"
        }
    ],
    "sg:phone":"+1 780 538 4644",
    "sg:postcode":"T8V 0R9",
    "sg:province":"AB",
    "wof:name":"Subway Sandwiches & Salads",
    "wof:placetype":"venue"
},
  "geometry": {"coordinates":[-118.79531900000001,55.169907],"type":"Point"}
}