{
  "type": "Feature",
  "properties": {
    "addr:full":"495 Main St W North Bay ON P1B 2V3",
    "addr:housenumber":"495",
    "addr:postcode":"p1b 2v3",
    "addr:street":"Main St W",
    "iso:country":"CA",
    "sg:address":"495 Main St W",
    "sg:city":"North Bay",
    "sg:classifiers":[
        {
            "category":"Professional",
            "subcategory":"Lawyer & Legal Services",
            "type":"Services"
        }
    ],
    "sg:phone":"+1 705 495 1334",
    "sg:postcode":"P1B 2V3",
    "sg:province":"ON",
    "sg:tags":[
        "attorney"
    ],
    "wof:name":"Sinicrope, Joseph",
    "wof:placetype":"venue"
},
  "geometry": {"coordinates":[-79.468369,46.315067],"type":"Point"}
}