{
  "type": "Feature",
  "properties": {
    "addr:full":"Scarborough ON M1J 2E9",
    "addr:postcode":"m1j 2e9",
    "iso:country":"CA",
    "sg:city":"Scarborough",
    "sg:classifiers":[
        {
            "category":"Restaurant",
            "type":"Food & Drink"
        }
    ],
    "sg:phone":"+1 416 265 7373",
    "sg:postcode":"M1J 2E9",
    "sg:province":"ON",
    "wof:name":"Gramps & Elaine Roti Place",
    "wof:placetype":"venue"
},
  "geometry": {"coordinates":[-79.22554,43.741611],"type":"Point"}
}