{
  "type": "Feature",
  "properties": {
    "addr:full":"1153 Fir St White Rock BC V4B 4A8",
    "addr:housenumber":"1153",
    "addr:postcode":"v4b 4a8",
    "addr:street":"Fir St",
    "iso:country":"CA",
    "sg:address":"1153 Fir St",
    "sg:city":"White Rock",
    "sg:classifiers":[
        {
            "category":"Organizations",
            "subcategory":"Religious Organization",
            "type":"Services"
        }
    ],
    "sg:phone":"+1 604 531 5739",
    "sg:postcode":"V4B 4A8",
    "sg:province":"BC",
    "sg:tags":[
        "church"
    ],
    "wof:name":"Star of the Sea Church",
    "wof:placetype":"venue"
},
  "geometry": {"coordinates":[-122.79951477,49.0229644775],"type":"Point"}
}