{
  "type": "Feature",
  "properties": {
    "addr:full":"3505 57 St Camrose AB T4V 4Y4",
    "addr:housenumber":"3505",
    "addr:postcode":"t4v 4y4",
    "addr:street":"57 St",
    "iso:country":"CA",
    "sg:address":"3505 57 St",
    "sg:city":"Camrose",
    "sg:classifiers":[
        {
            "category":"Building & Trades",
            "subcategory":"Cleaning & Sanitation",
            "type":"Services"
        }
    ],
    "sg:phone":"+1 780 672 1201",
    "sg:postcode":"T4V 4Y4",
    "sg:province":"AB",
    "sg:tags":[
        "janitor"
    ],
    "wof:name":"North Star Janitorial Svc",
    "wof:placetype":"venue"
},
  "geometry": {"coordinates":[-112.842567444,53.0000305176],"type":"Point"}
}