{
  "type": "Feature",
  "properties": {
    "addr:full":"112 28 St SE Calgary AB T2A 6J9",
    "addr:housenumber":"112 28",
    "addr:postcode":"t2a 6j9",
    "addr:street":"St Se",
    "iso:country":"CA",
    "sg:address":"112 28 St SE",
    "sg:city":"Calgary",
    "sg:classifiers":[
        {
            "category":"Health Services",
            "subcategory":"Health Practitioner",
            "type":"Services"
        }
    ],
    "sg:phone":"+1 403 569 2000",
    "sg:postcode":"T2A 6J9",
    "sg:province":"AB",
    "sg:tags":[
        "speech",
        "audiologists",
        "therapy",
        "hearing"
    ],
    "wof:name":"Calgary Health Region",
    "wof:placetype":"venue"
},
  "geometry": {"coordinates":[-113.993057251,51.0520706177],"type":"Point"}
}