{
  "type": "Feature",
  "properties": {
    "addr:full":"10213 112 Ave High Level AB T0H 1Z0",
    "addr:housenumber":"10213",
    "addr:postcode":"t0h 1z0",
    "addr:street":"112 Ave",
    "iso:country":"CA",
    "sg:address":"10213 112 Ave",
    "sg:city":"High Level",
    "sg:classifiers":[
        {
            "category":"Wholesale",
            "subcategory":"Machinery & Supplies",
            "type":"Manufacturing & Wholesale Goods"
        }
    ],
    "sg:phone":"+1 780 926 3845",
    "sg:postcode":"T0H 1Z0",
    "sg:province":"AB",
    "sg:tags":[
        "contractor"
    ],
    "wof:name":"Dezzco",
    "wof:placetype":"venue"
},
  "geometry": {"coordinates":[-117.146522522,58.5107727051],"type":"Point"}
}