{
  "type": "Feature",
  "properties": {
    "addr:full":"2148 Pyott Rd Armstrong BC V0E 1B4",
    "addr:housenumber":"2148",
    "addr:postcode":"v0e 1b4",
    "addr:street":"Pyott Rd",
    "iso:country":"CA",
    "sg:address":"2148 Pyott Rd",
    "sg:city":"Armstrong",
    "sg:classifiers":[
        {
            "category":"Building & Trades",
            "subcategory":"Construction",
            "type":"Services"
        }
    ],
    "sg:phone":"+1 250 546 6276",
    "sg:postcode":"V0E 1B4",
    "sg:province":"BC",
    "sg:tags":[
        "contractor"
    ],
    "wof:name":"Huxley Construction Ltd",
    "wof:placetype":"venue"
},
  "geometry": {"coordinates":[-119.183701,50.441818],"type":"Point"}
}