{
  "type": "Feature",
  "properties": {
    "addr:full":"128 Richmond St Charlottetown PE C1A 1H9",
    "addr:housenumber":"128",
    "addr:postcode":"c1a 1h9",
    "addr:street":"Richmond St",
    "iso:country":"CA",
    "sg:address":"128 Richmond St",
    "sg:city":"Charlottetown",
    "sg:classifiers":[
        {
            "category":"Restaurant",
            "type":"Food & Drink"
        }
    ],
    "sg:phone":"+1 902 892 0494",
    "sg:postcode":"C1A 1H9",
    "sg:province":"PE",
    "sg:tags":[
        "shop",
        "coffee"
    ],
    "wof:name":"Cafe Diem",
    "wof:placetype":"venue"
},
  "geometry": {"coordinates":[-63.1264801025,46.2338638306],"type":"Point"}
}