{
  "type": "Feature",
  "properties": {
    "addr:full":"Delta BC V4L 2A2",
    "addr:postcode":"v4l 2a2",
    "iso:country":"CA",
    "sg:city":"Delta",
    "sg:classifiers":[
        {
            "category":"Shopping",
            "subcategory":"Gifts & Souvenirs",
            "type":"Retail Goods"
        }
    ],
    "sg:phone":"+1 604 948 9315",
    "sg:postcode":"V4L 2A2",
    "sg:province":"BC",
    "sg:tags":[
        "shop"
    ],
    "wof:name":"Ambiente",
    "wof:placetype":"venue"
},
  "geometry": {"coordinates":[-123.06887054400001,49.0241966248],"type":"Point"}
}