{
  "type": "Feature",
  "properties": {
    "addr:full":"99 Duncan Norrie Dr Winnipeg MB R3P 2K2",
    "addr:housenumber":"99",
    "addr:postcode":"r3p 2k2",
    "addr:street":"Duncan Norrie Dr",
    "iso:country":"CA",
    "sg:address":"99 Duncan Norrie Dr",
    "sg:city":"Winnipeg",
    "sg:classifiers":[
        {
            "category":"Professional",
            "subcategory":"Computer Services",
            "type":"Services"
        }
    ],
    "sg:phone":"+1 204 488 3129",
    "sg:postcode":"R3P 2K2",
    "sg:province":"MB",
    "sg:tags":[
        "consultant"
    ],
    "wof:name":"Alitra Inc",
    "wof:placetype":"venue"
},
  "geometry": {"coordinates":[-97.192375,49.836754],"type":"Point"}
}