{
  "type": "Feature",
  "properties": {
    "addr:full":"Burlington ON L7L 6G4",
    "addr:postcode":"l7l 6g4",
    "iso:country":"CA",
    "sg:city":"Burlington",
    "sg:classifiers":[
        {
            "category":"Building & Trades",
            "subcategory":"Equipment Rental",
            "type":"Services"
        }
    ],
    "sg:phone":"+1 905 331 2000",
    "sg:postcode":"L7L 6G4",
    "sg:province":"ON",
    "sg:tags":[
        "leasing"
    ],
    "wof:name":"Abn Amro Leasing",
    "wof:placetype":"venue"
},
  "geometry": {"coordinates":[-79.7617721558,43.3954124451],"type":"Point"}
}