{
  "type": "Feature",
  "properties": {
    "addr:full":"1104 Rue DE LA Manic Chicoutimi QC G7K 1A2",
    "addr:housenumber":"1104",
    "addr:postcode":"g7k 1a2",
    "addr:street":"Rue De La Manic",
    "iso:country":"CA",
    "sg:address":"1104 Rue DE LA Manic",
    "sg:city":"Chicoutimi",
    "sg:classifiers":[
        {
            "category":"Wholesale",
            "subcategory":"Machinery & Supplies",
            "type":"Manufacturing & Wholesale Goods"
        }
    ],
    "sg:phone":"+1 418 696 9759",
    "sg:postcode":"G7K 1A2",
    "sg:province":"QC",
    "sg:tags":[
        "chains",
        "sling"
    ],
    "wof:name":"Industries Lam-E",
    "wof:placetype":"venue"
},
  "geometry": {"coordinates":[-71.109116,48.396812],"type":"Point"}
}