{
  "type": "Feature",
  "properties": {
    "iso:country":"CA",
    "sg:address":"31 Stewart Rd",
    "sg:city":"Collingwood",
    "sg:classifiers":[
        {
            "category":"Professional",
            "subcategory":"Engineering",
            "type":"Services"
        }
    ],
    "sg:phone":"+1 705 444 5678",
    "sg:postcode":"L9Y 4M7",
    "sg:province":"ON",
    "sg:tags":[
        "contractor",
        "sewer",
        "engineer"
    ],
    "wof:name":"Tectonic Infrastructure Inc",
    "wof:placetype":"venue"
},
  "geometry": {"coordinates":[-80.23658752439999,44.4942398071],"type":"Point"}
}