{
  "type": "Feature",
  "properties": {
    "addr:full":"Cardston AB T0K 0K0",
    "addr:postcode":"t0k 0k0",
    "iso:country":"CA",
    "sg:city":"Cardston",
    "sg:classifiers":[
        {
            "category":"Organizations",
            "subcategory":"Religious Organization",
            "type":"Services"
        }
    ],
    "sg:phone":"+1 403 653 4044",
    "sg:postcode":"T0K 0K0",
    "sg:province":"AB",
    "sg:tags":[
        "church"
    ],
    "wof:name":"Church of Jesus Christ of Lds",
    "wof:placetype":"venue"
},
  "geometry": {"coordinates":[-113.310684204,49.1985816956],"type":"Point"}
}