{
  "type": "Feature",
  "properties": {
    "iso:country":"CA",
    "sg:address":"218 Ottawa St N",
    "sg:city":"Hamilton",
    "sg:classifiers":[
        {
            "category":"Restaurant",
            "type":"Food & Drink"
        }
    ],
    "sg:phone":"+1 905 547 3672",
    "sg:postcode":"L8H 3Z6",
    "sg:province":"ON",
    "sg:tags":[
        "caterer"
    ],
    "wof:name":"Dora's Delicatessen & Catering",
    "wof:placetype":"venue"
},
  "geometry": {"coordinates":[-79.81713104249999,43.2485313416],"type":"Point"}
}