{
  "type": "Feature",
  "properties": {
    "iso:country":"CA",
    "sg:address":"1330 Rue Saint-Georges",
    "sg:city":"Saint-Cesaire",
    "sg:classifiers":[
        {
            "category":"Organizations",
            "subcategory":"Religious Organization",
            "type":"Services"
        }
    ],
    "sg:phone":"+1 450 469 4572",
    "sg:postcode":"J0L 1T0",
    "sg:province":"QC",
    "sg:tags":[
        "house",
        "retreat"
    ],
    "wof:name":"Ambassade Du 3Ieme Age",
    "wof:placetype":"venue"
},
  "geometry": {"coordinates":[-73.0053024292,45.4099121094],"type":"Point"}
}