{
  "type": "Feature",
  "properties": {
    "addr:full":"245 Belleville Rd Napanee ON K7R 3M7",
    "addr:housenumber":"245",
    "addr:postcode":"k7r 3m7",
    "addr:street":"Belleville Rd",
    "iso:country":"CA",
    "sg:address":"245 Belleville Rd",
    "sg:city":"Napanee",
    "sg:classifiers":[
        {
            "category":"Education",
            "subcategory":"School",
            "type":"Public Place"
        }
    ],
    "sg:phone":"+1 613 354 3381",
    "sg:postcode":"K7R 3M7",
    "sg:province":"ON",
    "wof:name":"Napanee Dist Secondary School",
    "wof:placetype":"venue"
},
  "geometry": {"coordinates":[-76.959915,44.248562],"type":"Point"}
}