{
  "type": "Feature",
  "properties": {
    "iso:country":"CA",
    "sg:address":"7405 Boul Decarie",
    "sg:city":"Montreal",
    "sg:classifiers":[
        {
            "category":"Shopping",
            "subcategory":"Tobacco",
            "type":"Retail Goods"
        }
    ],
    "sg:phone":"+1 514 733 8519",
    "sg:postcode":"H4P 2G9",
    "sg:province":"QC",
    "sg:tags":[
        "cigarette",
        "cigar",
        "dealer"
    ],
    "wof:name":"Kiosque A Journaux Makoukji",
    "wof:placetype":"venue"
},
  "geometry": {"coordinates":[-73.65313,45.494953],"type":"Point"}
}