{
  "type": "Feature",
  "properties": {
    "iso:country":"CA",
    "sg:city":"Mont-Royal",
    "sg:classifiers":[
        {
            "category":"Restaurant",
            "type":"Food & Drink"
        }
    ],
    "sg:phone":"+1 514 739 5953",
    "sg:postcode":"H3P 3E9",
    "sg:province":"QC",
    "wof:name":"Rockland Souvlaki Inc",
    "wof:placetype":"venue"
},
  "geometry": {"coordinates":[-73.6484832764,45.5267295837],"type":"Point"}
}