{
  "type": "Feature",
  "properties": {
    "addr:full":"810 Boul Taschereau LA Prairie QC J5R 1V9",
    "addr:housenumber":"810",
    "addr:postcode":"j5r 1v9",
    "addr:street":"Boul Taschereau",
    "iso:country":"CA",
    "sg:address":"810 Boul Taschereau",
    "sg:city":"LA Prairie",
    "sg:classifiers":[
        {
            "category":"Personal",
            "subcategory":"Beauty Salon",
            "type":"Services"
        }
    ],
    "sg:phone":"+1 450 659 1733",
    "sg:postcode":"J5R 1V9",
    "sg:province":"QC",
    "wof:name":"Salon Gigi",
    "wof:placetype":"venue"
},
  "geometry": {"coordinates":[-73.495842,45.409309],"type":"Point"}
}