{
  "type": "Feature",
  "properties": {
    "addr:full":"350 Rue Principale Saint-Zotique QC J0P 1Z0",
    "addr:housenumber":"350",
    "addr:postcode":"j0p 1z0",
    "addr:street":"Rue Principale",
    "iso:country":"CA",
    "sg:address":"350 Rue Principale",
    "sg:city":"Saint-Zotique",
    "sg:classifiers":[
        {
            "category":"Food & Beverages",
            "subcategory":"Groceries & Convenience Stores",
            "type":"Retail Goods"
        }
    ],
    "sg:phone":"+1 450 267 3343",
    "sg:postcode":"J0P 1Z0",
    "sg:province":"QC",
    "sg:tags":[
        "grocer"
    ],
    "wof:name":"Marche Metro Fordham",
    "wof:placetype":"venue"
},
  "geometry": {"coordinates":[-74.22611999999999,45.252903],"type":"Point"}
}