{
  "type": "Feature",
  "properties": {
    "addr:full":"317 Rue Racine Granby QC J2G 3B6",
    "addr:housenumber":"317",
    "addr:postcode":"j2g 3b6",
    "addr:street":"Rue Racine",
    "iso:country":"CA",
    "sg:address":"317 Rue Racine",
    "sg:city":"Granby",
    "sg:classifiers":[
        {
            "category":"Professional",
            "subcategory":"Accounting & Tax Preparation",
            "type":"Services"
        }
    ],
    "sg:phone":"+1 450 372 8742",
    "sg:postcode":"J2G 3B6",
    "sg:province":"QC",
    "sg:tags":[
        "accountant"
    ],
    "wof:name":"Dumas, Jean-Pierre",
    "wof:placetype":"venue"
},
  "geometry": {"coordinates":[-72.731590271,45.4007034302],"type":"Point"}
}