{
  "type": "Feature",
  "properties": {
    "addr:full":"15 Everett St Moncton NB E1C 3Z6",
    "addr:housenumber":"15",
    "addr:postcode":"e1c 3z6",
    "addr:street":"Everett St",
    "iso:country":"CA",
    "sg:address":"15 Everett St",
    "sg:city":"Moncton",
    "sg:classifiers":[
        {
            "category":"Social Services",
            "subcategory":"Child Care",
            "type":"Services"
        }
    ],
    "sg:phone":"+1 506 858 0949",
    "sg:postcode":"E1C 3Z6",
    "sg:province":"NB",
    "sg:tags":[
        "youth",
        "organization",
        "center"
    ],
    "wof:name":"Moncton Boys' & Girls' Club",
    "wof:placetype":"venue"
},
  "geometry": {"coordinates":[-64.814285,46.104076],"type":"Point"}
}