{
  "type": "Feature",
  "properties": {
    "addr:full":"32 Rue Saint-Jude S # 1 Canton-DE-Granby QC J2J 2N4",
    "addr:housenumber":"32",
    "addr:postcode":"j2j 2n4",
    "addr:street":"Rue Saint-Jude S # 1 Canton-De-Granby",
    "iso:country":"CA",
    "sg:address":"32 Rue Saint-Jude S # 1",
    "sg:city":"Canton-DE-Granby",
    "sg:classifiers":[
        {
            "category":"Wholesale",
            "subcategory":"Metals & Minerals",
            "type":"Manufacturing & Wholesale Goods"
        }
    ],
    "sg:phone":"+1 450 372 7105",
    "sg:postcode":"J2J 2N4",
    "sg:province":"QC",
    "sg:tags":[
        "repairing",
        "remodeling",
        "aluminum",
        "contractor"
    ],
    "wof:name":"Aluminium Goulet & Fils Inc",
    "wof:placetype":"venue"
},
  "geometry": {"coordinates":[-72.7592544556,45.4134559631],"type":"Point"}
}