{
  "type": "Feature",
  "properties": {
    "addr:full":"Thornhill ON L3T 4S1",
    "addr:postcode":"l3t 4s1",
    "iso:country":"CA",
    "sg:city":"Thornhill",
    "sg:classifiers":[
        {
            "category":"Professional",
            "subcategory":"Management & Consulting",
            "type":"Services"
        }
    ],
    "sg:phone":"+1 905 881 8499",
    "sg:postcode":"L3T 4S1",
    "sg:province":"ON",
    "sg:tags":[
        "party",
        "planning"
    ],
    "wof:name":"Wonderkids Sports Ctr",
    "wof:placetype":"venue"
},
  "geometry": {"coordinates":[-79.41810599999999,43.803036],"type":"Point"}
}