{
  "type": "Feature",
  "properties": {
    "addr:full":"Prince Albert SK S6V 7J4",
    "addr:postcode":"s6v 7j4",
    "iso:country":"CA",
    "sg:city":"Prince Albert",
    "sg:classifiers":[
        {
            "category":"Shopping",
            "subcategory":"Clothing, Apparel, & Fashions",
            "type":"Retail Goods"
        }
    ],
    "sg:phone":"+1 306 922 4644",
    "sg:postcode":"S6V 7J4",
    "sg:province":"SK",
    "wof:name":"Bootlegger",
    "wof:placetype":"venue"
},
  "geometry": {"coordinates":[-105.754501343,53.1999282837],"type":"Point"}
}