{
  "type": "Feature",
  "properties": {
    "addr:full":"7 Mill Rd Grand Falls-Windsor NL A2A 1B8",
    "addr:housenumber":"7",
    "addr:postcode":"a2a 1b8",
    "addr:street":"Mill Rd",
    "iso:country":"CA",
    "sg:address":"7 Mill Rd",
    "sg:city":"Grand Falls-Windsor",
    "sg:classifiers":[
        {
            "category":"Manufacturing",
            "subcategory":"Paper Products",
            "type":"Manufacturing & Wholesale Goods"
        }
    ],
    "sg:phone":"+1 709 292 3230",
    "sg:postcode":"A2A 1B8",
    "sg:province":"NL",
    "wof:name":"Abitibi-Consolidated Inc",
    "wof:placetype":"venue"
},
  "geometry": {"coordinates":[-55.661137,48.927185],"type":"Point"}
}