{
  "type": "Feature",
  "properties": {
    "addr:full":"4307 Rue Sainte-Catherine E Montreal QC H1V 1Y1",
    "addr:housenumber":"4307",
    "addr:postcode":"h1v 1y1",
    "addr:street":"Rue Sainte-Catherine E",
    "iso:country":"CA",
    "sg:address":"4307 Rue Sainte-Catherine E",
    "sg:city":"Montreal",
    "sg:classifiers":[
        {
            "category":"Personal",
            "subcategory":"Beauty Salon",
            "type":"Services"
        }
    ],
    "sg:phone":"+1 514 253 2026",
    "sg:postcode":"H1V 1Y1",
    "sg:province":"QC",
    "wof:name":"Bernard Beaulieu Hair Dresser",
    "wof:placetype":"venue"
},
  "geometry": {"coordinates":[-73.5341796875,45.5508842468],"type":"Point"}
}