{
  "type": "Feature",
  "properties": {
    "iso:country":"CA",
    "sg:address":"3584 Rue Queen",
    "sg:city":"Rawdon",
    "sg:classifiers":[
        {
            "category":"Utilities",
            "subcategory":"Fuel Oil & Lpg",
            "type":"Services"
        }
    ],
    "sg:phone":"+1 450 834 2457",
    "sg:postcode":"J0K 1S0",
    "sg:province":"QC",
    "sg:tags":[
        "propane",
        "gas"
    ],
    "wof:name":"J Mainville Inc",
    "wof:placetype":"venue"
},
  "geometry": {"coordinates":[-73.7049255371,46.0411186218],"type":"Point"}
}