{
  "type": "Feature",
  "properties": {
    "addr:full":"404 King Rd Richmond Hill ON L4E 2X4",
    "addr:housenumber":"404",
    "addr:postcode":"l4e 2x4",
    "addr:street":"King Rd",
    "iso:country":"CA",
    "sg:address":"404 King Rd",
    "sg:city":"Richmond Hill",
    "sg:classifiers":[
        {
            "category":"Professional",
            "subcategory":"Business Services",
            "type":"Services"
        }
    ],
    "sg:phone":"+1 905 773 9893",
    "sg:postcode":"L4E 2X4",
    "sg:province":"ON",
    "sg:tags":[
        "orthopedic",
        "appliance",
        "made"
    ],
    "wof:name":"Shoemate Orthotics",
    "wof:placetype":"venue"
},
  "geometry": {"coordinates":[-79.4699249268,43.9415283203],"type":"Point"}
}