{
  "type": "Feature",
  "properties": {
    "addr:full":"Kelowna BC V1W 4B6",
    "addr:postcode":"v1w 4b6",
    "iso:country":"CA",
    "sg:city":"Kelowna",
    "sg:classifiers":[
        {
            "category":"Retail",
            "subcategory":"Repair Shop",
            "type":"Services"
        }
    ],
    "sg:phone":"+1 250 763 8660",
    "sg:postcode":"V1W 4B6",
    "sg:province":"BC",
    "sg:tags":[
        "sharpening"
    ],
    "wof:name":"Apex Saw Sharpening",
    "wof:placetype":"venue"
},
  "geometry": {"coordinates":[-119.418556213,49.8320617676],"type":"Point"}
}