{
  "type": "Feature",
  "properties": {
    "addr:full":"33 Edward St Stouffville ON L4A 1A4",
    "addr:housenumber":"33",
    "addr:postcode":"l4a 1a4",
    "addr:street":"Edward St",
    "iso:country":"CA",
    "sg:address":"33 Edward St",
    "sg:city":"Stouffville",
    "sg:classifiers":[
        {
            "category":"Building & Trades",
            "subcategory":"Construction",
            "type":"Services"
        }
    ],
    "sg:phone":"+1 905 640 3440",
    "sg:postcode":"L4A 1A4",
    "sg:province":"ON",
    "sg:tags":[
        "lumber",
        "contractor"
    ],
    "wof:name":"Schell Lumber Ltd",
    "wof:placetype":"venue"
},
  "geometry": {"coordinates":[-79.2509841919,43.9715766907],"type":"Point"}
}