{
  "type": "Feature",
  "properties": {
    "addr:full":"Saint-Hubert QC J4T 2R4",
    "addr:postcode":"j4t 2r4",
    "iso:country":"CA",
    "sg:city":"Saint-Hubert",
    "sg:classifiers":[
        {
            "category":"Wholesale",
            "subcategory":"Chemicals & Plastics",
            "type":"Manufacturing & Wholesale Goods"
        }
    ],
    "sg:phone":"+1 450 465 2233",
    "sg:postcode":"J4T 2R4",
    "sg:province":"QC",
    "sg:tags":[
        "concrete",
        "additive"
    ],
    "wof:name":"Adjuvants Euclid Canada Inc",
    "wof:placetype":"venue"
},
  "geometry": {"coordinates":[-73.483315,45.501472],"type":"Point"}
}