{
  "type": "Feature",
  "properties": {
    "addr:full":"1420 King St Bowmanville ON L1C 3K2",
    "addr:housenumber":"1420",
    "addr:postcode":"l1c 3k2",
    "addr:street":"King St",
    "iso:country":"CA",
    "sg:address":"1420 King St",
    "sg:city":"Bowmanville",
    "sg:classifiers":[
        {
            "category":"Travel",
            "subcategory":"Travel Agent",
            "type":"Entertainment"
        }
    ],
    "sg:phone":"+1 905 404 0061",
    "sg:postcode":"L1C 3K2",
    "sg:province":"ON",
    "sg:tags":[
        "agency",
        "bureau"
    ],
    "wof:name":"Grant Morris Cruise & Travel",
    "wof:placetype":"venue"
},
  "geometry": {"coordinates":[-78.66449737550001,43.912311554],"type":"Point"}
}