{
  "type": "Feature",
  "properties": {
    "addr:full":"1900 Guildford Town Ctr Surrey BC V3R 7B8",
    "addr:housenumber":"1900",
    "addr:postcode":"v3r 7b8",
    "addr:street":"Guildford Town Ctr",
    "iso:country":"CA",
    "sg:address":"1900 Guildford Town Ctr",
    "sg:city":"Surrey",
    "sg:classifiers":[
        {
            "category":"Home & Garden",
            "subcategory":"Furniture",
            "type":"Retail Goods"
        }
    ],
    "sg:phone":"+1 604 588 6622",
    "sg:postcode":"V3R 7B8",
    "sg:province":"BC",
    "wof:name":"In Style Home Furnishings",
    "wof:placetype":"venue"
},
  "geometry": {"coordinates":[-122.803291,49.188934],"type":"Point"}
}