{
  "type": "Feature",
  "properties": {
    "addr:full":"Calgary AB T2E 2S6",
    "addr:postcode":"t2e 2s6",
    "iso:country":"CA",
    "sg:city":"Calgary",
    "sg:classifiers":[
        {
            "category":"Banks & Credit Unions",
            "subcategory":"Bank",
            "type":"Services"
        }
    ],
    "sg:phone":"+1 403 503 5530",
    "sg:postcode":"T2E 2S6",
    "sg:province":"AB",
    "wof:name":"Bank of Montreal",
    "wof:placetype":"venue"
},
  "geometry": {"coordinates":[-114.062309,51.068081],"type":"Point"}
}