{
  "type": "Feature",
  "properties": {
    "addr:full":"Toronto ON M4N 3M5",
    "addr:postcode":"m4n 3m5",
    "iso:country":"CA",
    "sg:city":"Toronto",
    "sg:classifiers":[
        {
            "category":"Health Services",
            "subcategory":"Doctor",
            "type":"Services"
        }
    ],
    "sg:phone":"+1 416 480 4932",
    "sg:postcode":"M4N 3M5",
    "sg:province":"ON",
    "sg:tags":[
        "physician",
        "surgeon"
    ],
    "wof:name":"Charles, J MD",
    "wof:placetype":"venue"
},
  "geometry": {"coordinates":[-79.37876900000001,43.721176],"type":"Point"}
}