{
  "type": "Feature",
  "properties": {
    "iso:country":"CA",
    "sg:address":"204 Rue DE LA Riviere",
    "sg:city":"Cowansville",
    "sg:classifiers":[
        {
            "category":"Restaurant",
            "type":"Food & Drink"
        }
    ],
    "sg:phone":"+1 450 263 9033",
    "sg:postcode":"J2K 1M8",
    "sg:province":"QC",
    "sg:tags":[
        "pub"
    ],
    "wof:name":"Brasserie DE LA Riviere",
    "wof:placetype":"venue"
},
  "geometry": {"coordinates":[-72.7514877319,45.2055587769],"type":"Point"}
}