{
  "type": "Feature",
  "properties": {
    "addr:full":"3230 Salmon Rd Westbank BC V4T 1A7",
    "addr:housenumber":"3230",
    "addr:postcode":"v4t 1a7",
    "addr:street":"Salmon Rd",
    "iso:country":"CA",
    "sg:address":"3230 Salmon Rd",
    "sg:city":"Westbank",
    "sg:classifiers":[
        {
            "category":"Education",
            "subcategory":"School",
            "type":"Public Place"
        }
    ],
    "sg:phone":"+1 250 768 7250",
    "sg:postcode":"V4T 1A7",
    "sg:province":"BC",
    "wof:name":"Helen Gorman Elementary",
    "wof:placetype":"venue"
},
  "geometry": {"coordinates":[-119.671288,49.84584],"type":"Point"}
}