{
  "type": "Feature",
  "properties": {
    "addr:full":"9445 Rue Hochelaga Montreal QC H1L 2P7",
    "addr:housenumber":"9445",
    "addr:postcode":"h1l 2p7",
    "addr:street":"Rue Hochelaga",
    "iso:country":"CA",
    "sg:address":"9445 Rue Hochelaga",
    "sg:city":"Montreal",
    "sg:classifiers":[
        {
            "category":"Education",
            "subcategory":"School",
            "type":"Public Place"
        }
    ],
    "sg:phone":"+1 514 353 5937",
    "sg:postcode":"H1L 2P7",
    "sg:province":"QC",
    "sg:tags":[
        "academic",
        "special"
    ],
    "wof:name":"Ecoles Peter Hall",
    "wof:placetype":"venue"
},
  "geometry": {"coordinates":[-73.5160446167,45.6089515686],"type":"Point"}
}