{
  "type": "Feature",
  "properties": {
    "addr:full":"36 Rue Ste Catherine Saint-Polycarpe QC J0P 1X0",
    "addr:housenumber":"36",
    "addr:postcode":"j0p 1x0",
    "addr:street":"Rue Ste Catherine",
    "iso:country":"CA",
    "sg:address":"36 Rue Ste Catherine",
    "sg:city":"Saint-Polycarpe",
    "sg:classifiers":[
        {
            "category":"Professional",
            "subcategory":"Business Services",
            "type":"Services"
        }
    ],
    "sg:phone":"+1 450 265 3779",
    "sg:postcode":"J0P 1X0",
    "sg:province":"QC",
    "sg:tags":[
        "notary"
    ],
    "wof:name":"Pharand, Jean Claude",
    "wof:placetype":"venue"
},
  "geometry": {"coordinates":[-74.30638885499999,45.3008918762],"type":"Point"}
}