{
  "type": "Feature",
  "properties": {
    "addr:full":"588 Division St Kingston ON K7K 4B6",
    "addr:housenumber":"588",
    "addr:postcode":"k7k 4b6",
    "addr:street":"Division St",
    "iso:country":"CA",
    "sg:address":"588 Division St",
    "sg:city":"Kingston",
    "sg:classifiers":[
        {
            "category":"Organizations",
            "subcategory":"Religious Organization",
            "type":"Services"
        }
    ],
    "sg:phone":"+1 613 546 5011",
    "sg:postcode":"K7K 4B6",
    "sg:province":"ON",
    "sg:tags":[
        "church"
    ],
    "wof:name":"Our Lady of Fatima Parish",
    "wof:placetype":"venue"
},
  "geometry": {"coordinates":[-76.4958572388,44.2463645935],"type":"Point"}
}