{
  "type": "Feature",
  "properties": {
    "addr:full":"29 Rue Victoria Saint-Jean-Sur-Richelieu QC J3B 2W8",
    "addr:housenumber":"29",
    "addr:postcode":"j3b 2w8",
    "addr:street":"Rue Victoria",
    "iso:country":"CA",
    "sg:address":"29 Rue Victoria",
    "sg:city":"Saint-Jean-Sur-Richelieu",
    "sg:classifiers":[
        {
            "category":"Sports & Exercise",
            "subcategory":"Bowling",
            "type":"Entertainment"
        }
    ],
    "sg:phone":"+1 450 346 3566",
    "sg:postcode":"J3B 2W8",
    "sg:province":"QC",
    "sg:tags":[
        "center"
    ],
    "wof:name":"Salle DE Quilles Au Royaume",
    "wof:placetype":"venue"
},
  "geometry": {"coordinates":[-73.25355500000001,45.303581],"type":"Point"}
}