{
  "type": "Feature",
  "properties": {
    "addr:full":"3504 Rubens Crt Burlington ON L7N 3K4",
    "addr:housenumber":"3504",
    "addr:postcode":"l7n 3k4",
    "addr:street":"Rubens Crt",
    "iso:country":"CA",
    "sg:address":"3504 Rubens Crt",
    "sg:city":"Burlington",
    "sg:classifiers":[
        {
            "category":"Health Services",
            "subcategory":"Health Practitioner",
            "type":"Services"
        }
    ],
    "sg:phone":"+1 905 333 3190",
    "sg:postcode":"L7N 3K4",
    "sg:province":"ON",
    "sg:tags":[
        "physiotherapist"
    ],
    "wof:name":"Therapy Visions Inc",
    "wof:placetype":"venue"
},
  "geometry": {"coordinates":[-79.7704162598,43.3508262634],"type":"Point"}
}