{
  "type": "Feature",
  "properties": {
    "addr:full":"303 Ch Grande-Cote Rosemere QC J7A 1J7",
    "addr:housenumber":"303",
    "addr:postcode":"j7a 1j7",
    "addr:street":"Ch Grande-Cote Rosemere",
    "iso:country":"CA",
    "sg:address":"303 Ch Grande-Cote",
    "sg:city":"Rosemere",
    "sg:classifiers":[
        {
            "category":"Health Services",
            "subcategory":"Doctor",
            "type":"Services"
        }
    ],
    "sg:phone":"+1 450 621 0623",
    "sg:postcode":"J7A 1J7",
    "sg:province":"QC",
    "sg:tags":[
        "physician",
        "surgeon"
    ],
    "wof:name":"Clinique Ortho Sante pm",
    "wof:placetype":"venue"
},
  "geometry": {"coordinates":[-73.79443359379999,45.634929657],"type":"Point"}
}