{
  "type": "Feature",
  "properties": {
    "addr:full":"Maniwaki QC J9E 3L4",
    "addr:postcode":"j9e 3l4",
    "iso:country":"CA",
    "sg:city":"Maniwaki",
    "sg:classifiers":[
        {
            "category":"Restaurant",
            "type":"Food & Drink"
        }
    ],
    "sg:phone":"+1 819 449 4499",
    "sg:postcode":"J9E 3L4",
    "sg:province":"QC",
    "wof:name":"Cafe Cristina",
    "wof:placetype":"venue"
},
  "geometry": {"coordinates":[-75.98198699949999,46.3759117126],"type":"Point"}
}