{
  "type": "Feature",
  "properties": {
    "addr:full":"Squatec QC G0L 4H0",
    "addr:postcode":"g0l 4h0",
    "iso:country":"CA",
    "sg:city":"Squatec",
    "sg:classifiers":[
        {
            "category":"Personal",
            "subcategory":"Beauty Salon",
            "type":"Services"
        }
    ],
    "sg:phone":"+1 418 855 5353",
    "sg:postcode":"G0L 4H0",
    "sg:province":"QC",
    "wof:name":"Coiffure Nouvel Hair",
    "wof:placetype":"venue"
},
  "geometry": {"coordinates":[-68.723145,47.881096],"type":"Point"}
}