{
  "type": "Feature",
  "properties": {
    "iso:country":"CA",
    "sg:address":"200 Rue Bosse",
    "sg:city":"Chicoutimi",
    "sg:classifiers":[
        {
            "category":"Shopping",
            "subcategory":"Shoes",
            "type":"Retail Goods"
        }
    ],
    "sg:phone":"+1 418 543 5634",
    "sg:postcode":"G7J 1L6",
    "sg:province":"QC",
    "wof:name":"J X Tremblay Enr",
    "wof:placetype":"venue"
},
  "geometry": {"coordinates":[-71.0749053955,48.4243202209],"type":"Point"}
}