{
  "type": "Feature",
  "properties": {
    "addr:full":"1447 Vieux Chemin Pohenegamook QC G0L 1J0",
    "addr:housenumber":"1447",
    "addr:postcode":"g0l 1j0",
    "addr:street":"Vieux Chemin Pohenegamook",
    "iso:country":"CA",
    "sg:address":"1447 Vieux Chemin",
    "sg:city":"Pohenegamook",
    "sg:classifiers":[
        {
            "category":"Retail",
            "subcategory":"Auto Repair",
            "type":"Services"
        }
    ],
    "sg:phone":"+1 418 859 1233",
    "sg:postcode":"G0L 1J0",
    "sg:province":"QC",
    "sg:tags":[
        "body",
        "automobile",
        "painting"
    ],
    "wof:name":"Carrossiers Desbiens",
    "wof:placetype":"venue"
},
  "geometry": {"coordinates":[-69.249207,47.463158],"type":"Point"}
}