{
  "type": "Feature",
  "properties": {
    "addr:full":"5887 Rue Sherbrooke O Montreal QC H4A 1X6",
    "addr:housenumber":"5887",
    "addr:postcode":"h4a 1x6",
    "addr:street":"Rue Sherbrooke O",
    "iso:country":"CA",
    "sg:address":"5887 Rue Sherbrooke O",
    "sg:city":"Montreal",
    "sg:classifiers":[
        {
            "category":"Shopping",
            "subcategory":"Computers & Home Electronics",
            "type":"Retail Goods"
        }
    ],
    "sg:phone":"+1 514 488 3363",
    "sg:postcode":"H4A 1X6",
    "sg:province":"QC",
    "sg:tags":[
        "television",
        "radio"
    ],
    "wof:name":"R-C Leon Svc Inc",
    "wof:placetype":"venue"
},
  "geometry": {"coordinates":[-73.547676,45.575871],"type":"Point"}
}