{
  "type": "Feature",
  "properties": {
    "addr:full":"279 Rang Des Mines Saint-Augustin-DE-Desmaures QC G3A 1W8",
    "addr:housenumber":"279",
    "addr:postcode":"g3a 1w8",
    "addr:street":"Rang Des Mines",
    "iso:country":"CA",
    "sg:address":"279 Rang Des Mines",
    "sg:city":"Saint-Augustin-DE-Desmaures",
    "sg:classifiers":[
        {
            "category":"Building & Trades",
            "subcategory":"Landscaping Services",
            "type":"Services"
        }
    ],
    "sg:phone":"+1 418 878 5545",
    "sg:postcode":"G3A 1W8",
    "sg:province":"QC",
    "sg:tags":[
        "landscape",
        "contractor"
    ],
    "wof:name":"A G Kerr Productions",
    "wof:placetype":"venue"
},
  "geometry": {"coordinates":[-71.47936199999999,46.765148],"type":"Point"}
}