{
  "type": "Feature",
  "properties": {
    "addr:full":"2583 Pembina Hwy Winnipeg MB R3T 2H5",
    "addr:housenumber":"2583",
    "addr:postcode":"r3t 2h5",
    "addr:street":"Pembina Hwy",
    "iso:country":"CA",
    "sg:address":"2583 Pembina Hwy",
    "sg:city":"Winnipeg",
    "sg:classifiers":[
        {
            "category":"Travel",
            "subcategory":"Hotels & Motels",
            "type":"Entertainment"
        }
    ],
    "sg:phone":"+1 204 269 2526",
    "sg:postcode":"R3T 2H5",
    "sg:province":"MB",
    "wof:name":"Palomino Plains Motor Inn",
    "wof:placetype":"venue"
},
  "geometry": {"coordinates":[-97.15754699999999,49.798393],"type":"Point"}
}