{
  "type": "Feature",
  "properties": {
    "iso:country":"CA",
    "sg:address":"85 Kingston Rd E",
    "sg:city":"Ajax",
    "sg:classifiers":[
        {
            "category":"Personal",
            "subcategory":"Tanning Parlor",
            "type":"Services"
        }
    ],
    "sg:phone":"+1 905 426 1482",
    "sg:postcode":"L1S 7J4",
    "sg:province":"ON",
    "sg:tags":[
        "salon"
    ],
    "wof:name":"Palm Beach Mega Tan",
    "wof:placetype":"venue"
},
  "geometry": {"coordinates":[-79.021202,43.862049],"type":"Point"}
}