{
  "type": "Feature",
  "properties": {
    "addr:full":"Hopewell NS B0K 1C0",
    "addr:postcode":"b0k 1c0",
    "iso:country":"CA",
    "sg:city":"Hopewell",
    "sg:classifiers":[
        {
            "category":"Organizations",
            "subcategory":"Religious Organization",
            "type":"Services"
        }
    ],
    "sg:phone":"+1 902 923 2457",
    "sg:postcode":"B0K 1C0",
    "sg:province":"NS",
    "sg:tags":[
        "church"
    ],
    "wof:name":"Presbyterian Church Hall",
    "wof:placetype":"venue"
},
  "geometry": {"coordinates":[-62.6975784302,45.4827003479],"type":"Point"}
}