{
  "type": "Feature",
  "properties": {
    "addr:full":"1314 Upper Wentworth St # 3 Hamilton ON L9A 4W2",
    "addr:housenumber":"1314",
    "addr:postcode":"l9a 4w2",
    "addr:street":"Upper Wentworth St # 3",
    "iso:country":"CA",
    "sg:address":"1314 Upper Wentworth St # 3",
    "sg:city":"Hamilton",
    "sg:classifiers":[
        {
            "category":"Health Services",
            "subcategory":"Doctor",
            "type":"Services"
        }
    ],
    "sg:phone":"+1 905 574 2222",
    "sg:postcode":"L9A 4W2",
    "sg:province":"ON",
    "sg:tags":[
        "dentist"
    ],
    "wof:name":"Bommarito & Staff",
    "wof:placetype":"venue"
},
  "geometry": {"coordinates":[-79.869415,43.206532],"type":"Point"}
}