{
  "type": "Feature",
  "properties": {
    "addr:full":"Chambly QC J3L 4C3",
    "addr:postcode":"j3l 4c3",
    "iso:country":"CA",
    "sg:city":"Chambly",
    "sg:classifiers":[
        {
            "category":"Shopping",
            "type":"Retail Goods"
        }
    ],
    "sg:phone":"+1 450 447 9816",
    "sg:postcode":"J3L 4C3",
    "sg:province":"QC",
    "sg:tags":[
        "wheel",
        "chair",
        "orthopedic",
        "appliance",
        "scooter"
    ],
    "wof:name":"Equimed",
    "wof:placetype":"venue"
},
  "geometry": {"coordinates":[-73.276473999,45.4432983398],"type":"Point"}
}