{
  "type": "Feature",
  "properties": {
    "addr:full":"Salaberry-DE-Valleyfield QC J6T 1W4",
    "addr:postcode":"j6t 1w4",
    "iso:country":"CA",
    "sg:city":"Salaberry-DE-Valleyfield",
    "sg:classifiers":[
        {
            "category":"Government",
            "subcategory":"Office",
            "type":"Public Place"
        }
    ],
    "sg:phone":"+1 450 370 3027",
    "sg:postcode":"J6T 1W4",
    "sg:province":"QC",
    "wof:name":"Quebec Centre Local D'Emploi",
    "wof:placetype":"venue"
},
  "geometry": {"coordinates":[-74.128242,45.255371],"type":"Point"}
}