{
  "type": "Feature",
  "properties": {
    "addr:full":"635 Broadway St Wyoming ON N0N 1T0",
    "addr:housenumber":"635",
    "addr:postcode":"n0n 1t0",
    "addr:street":"Broadway St",
    "iso:country":"CA",
    "sg:address":"635 Broadway St",
    "sg:city":"Wyoming",
    "sg:classifiers":[
        {
            "category":"Wholesale",
            "subcategory":"Meat",
            "type":"Manufacturing & Wholesale Goods"
        }
    ],
    "sg:phone":"+1 519 845 0255",
    "sg:postcode":"N0N 1T0",
    "sg:province":"ON",
    "sg:tags":[
        "butchering"
    ],
    "wof:name":"Tony's Meat Market",
    "wof:placetype":"venue"
},
  "geometry": {"coordinates":[-82.118561,42.950466],"type":"Point"}
}