{
  "type": "Feature",
  "properties": {
    "addr:full":"119 4th Ave N Three Hills AB T0M 2A0",
    "addr:housenumber":"119",
    "addr:postcode":"t0m 2a0",
    "addr:street":"4Th Ave N Three",
    "iso:country":"CA",
    "sg:address":"119 4th Ave N",
    "sg:city":"Three Hills",
    "sg:classifiers":[
        {
            "category":"Food & Beverages",
            "subcategory":"Groceries & Convenience Stores",
            "type":"Retail Goods"
        }
    ],
    "sg:phone":"+1 403 443 5022",
    "sg:postcode":"T0M 2A0",
    "sg:province":"AB",
    "sg:tags":[
        "grocer"
    ],
    "wof:name":"Three Hills Iga",
    "wof:placetype":"venue"
},
  "geometry": {"coordinates":[-113.26815000000001,51.70438],"type":"Point"}
}