{
  "type": "Feature",
  "properties": {
    "addr:full":"2910 1E Av Quebec QC G1L 3P3",
    "addr:housenumber":"2910",
    "addr:postcode":"g1l 3p3",
    "addr:street":"1E Av",
    "iso:country":"CA",
    "sg:address":"2910 1E Av",
    "sg:city":"Quebec",
    "sg:classifiers":[
        {
            "category":"Social Services",
            "type":"Services"
        }
    ],
    "sg:phone":"+1 418 684 0266",
    "sg:postcode":"G1L 3P3",
    "sg:province":"QC",
    "sg:tags":[
        "organization",
        "suicide",
        "prevention",
        "welfare"
    ],
    "wof:name":"Sos Suicide Jeunesse",
    "wof:placetype":"venue"
},
  "geometry": {"coordinates":[-71.24464399999999,46.837704],"type":"Point"}
}