{
  "type": "Feature",
  "properties": {
    "addr:full":"78 Spring Garden Ave North York ON M2N 3G3",
    "addr:housenumber":"78",
    "addr:postcode":"m2n 3g3",
    "addr:street":"Spring Garden Ave",
    "iso:country":"CA",
    "sg:address":"78 Spring Garden Ave",
    "sg:city":"North York",
    "sg:classifiers":[
        {
            "category":"Banks & Credit Unions",
            "subcategory":"Investment Brokerage",
            "type":"Services"
        }
    ],
    "sg:phone":"+1 416 221 1564",
    "sg:postcode":"M2N 3G3",
    "sg:province":"ON",
    "sg:tags":[
        "consultant",
        "planning",
        "financial"
    ],
    "wof:name":"Ioct Financial",
    "wof:placetype":"venue"
},
  "geometry": {"coordinates":[-79.40812699999999,43.765156],"type":"Point"}
}