{
  "type": "Feature",
  "properties": {
    "iso:country":"CA",
    "sg:address":"505 Rue Sainte-Catherine E",
    "sg:city":"Montreal",
    "sg:classifiers":[
        {
            "category":"Shopping",
            "subcategory":"Jewelry",
            "type":"Retail Goods"
        }
    ],
    "sg:phone":"+1 514 845 5243",
    "sg:postcode":"H2L 2C9",
    "sg:province":"QC",
    "sg:tags":[
        "book",
        "dealer"
    ],
    "wof:name":"Parchemin Librairie Agree",
    "wof:placetype":"venue"
},
  "geometry": {"coordinates":[-73.559631,45.51479],"type":"Point"}
}