{
  "type": "Feature",
  "properties": {
    "addr:full":"1355 Boul Des Laurentides Vimont QC H7M 2Y2",
    "addr:housenumber":"1355",
    "addr:postcode":"h7m 2y2",
    "addr:street":"Boul Des Laurentides",
    "iso:country":"CA",
    "sg:address":"1355 Boul Des Laurentides",
    "sg:city":"Vimont",
    "sg:classifiers":[
        {
            "category":"Shopping",
            "subcategory":"Bicycles & Sporting Goods",
            "type":"Retail Goods"
        }
    ],
    "sg:phone":"+1 450 667 4656",
    "sg:postcode":"H7M 2Y2",
    "sg:province":"QC",
    "sg:tags":[
        "equipment",
        "diver",
        "supply"
    ],
    "wof:name":"Boutique Du Plongeur",
    "wof:placetype":"venue"
},
  "geometry": {"coordinates":[-73.71066999999999,45.586906],"type":"Point"}
}