{
  "type": "Feature",
  "properties": {
    "addr:full":"851 King St E Kitchener ON N2G 2M7",
    "addr:housenumber":"851",
    "addr:postcode":"n2g 2m7",
    "addr:street":"King St E",
    "iso:country":"CA",
    "sg:address":"851 King St E",
    "sg:city":"Kitchener",
    "sg:classifiers":[
        {
            "category":"Autos & Motor Vehicles",
            "subcategory":"Fuel & Gas Station",
            "type":"Retail Goods"
        }
    ],
    "sg:phone":"+1 519 745 0480",
    "sg:postcode":"N2G 2M7",
    "sg:province":"ON",
    "sg:tags":[
        "oil"
    ],
    "wof:name":"Cango Petroleums",
    "wof:placetype":"venue"
},
  "geometry": {"coordinates":[-80.47566999999999,43.443504],"type":"Point"}
}