{
  "type": "Feature",
  "properties": {
    "addr:full":"131 Old Onondaga Rd E Brantford ON N3T 5L4",
    "addr:housenumber":"131",
    "addr:postcode":"n3t 5l4",
    "addr:street":"Old Onondaga Rd E",
    "iso:country":"CA",
    "sg:address":"131 Old Onondaga Rd E",
    "sg:city":"Brantford",
    "sg:classifiers":[
        {
            "category":"Building & Trades",
            "subcategory":"Construction",
            "type":"Services"
        }
    ],
    "sg:phone":"+1 519 752 9698",
    "sg:postcode":"N3T 5L4",
    "sg:province":"ON",
    "sg:tags":[
        "masonry",
        "contractor"
    ],
    "wof:name":"D & D Masonry Ltd",
    "wof:placetype":"venue"
},
  "geometry": {"coordinates":[-80.26174163819999,43.1413612366],"type":"Point"}
}