{
  "type": "Feature",
  "properties": {
    "iso:country":"CA",
    "sg:city":"Grand Falls-Windsor",
    "sg:classifiers":[
        {
            "category":"Social Services",
            "subcategory":"Child Care",
            "type":"Services"
        }
    ],
    "sg:phone":"+1 709 489 0811",
    "sg:postcode":"A2A 1L2",
    "sg:province":"NL",
    "wof:name":"Discovery Daycare",
    "wof:placetype":"venue"
},
  "geometry": {"coordinates":[-55.654499054,48.9309310913],"type":"Point"}
}