{
  "type": "Feature",
  "properties": {
    "iso:country":"CA",
    "sg:address":"Ivanhoe Lake",
    "sg:city":"Foleyet",
    "sg:classifiers":[
        {
            "category":"Travel",
            "subcategory":"Campground",
            "type":"Entertainment"
        }
    ],
    "sg:phone":"+1 705 899 2875",
    "sg:postcode":"P0M 1T0",
    "sg:province":"ON",
    "sg:tags":[
        "camp",
        "fishing"
    ],
    "wof:name":"Red Pine Lodge",
    "wof:placetype":"venue"
},
  "geometry": {"coordinates":[-82.4386672974,48.2442245483],"type":"Point"}
}