{
  "type": "Feature",
  "properties": {
    "addr:full":"Toronto ON M5H 2G4",
    "addr:postcode":"m5h 2g4",
    "iso:country":"CA",
    "sg:city":"Toronto",
    "sg:classifiers":[
        {
            "category":"Personal",
            "subcategory":"Barber",
            "type":"Services"
        }
    ],
    "sg:phone":"+1 416 860 9200",
    "sg:postcode":"M5H 2G4",
    "sg:province":"ON",
    "wof:name":"Frank's Barber Shop",
    "wof:placetype":"venue"
},
  "geometry": {"coordinates":[-79.3838348389,43.6504745483],"type":"Point"}
}