{
  "type": "Feature",
  "properties": {
    "iso:country":"CA",
    "sg:city":"Vancouver",
    "sg:classifiers":[
        {
            "category":"Professional",
            "subcategory":"Accounting & Tax Preparation",
            "type":"Services"
        }
    ],
    "sg:phone":"+1 604 685 0564",
    "sg:postcode":"V6E 3B9",
    "sg:province":"BC",
    "sg:tags":[
        "accountant"
    ],
    "wof:name":"Collins Barrow",
    "wof:placetype":"venue"
},
  "geometry": {"coordinates":[-123.12184906,49.2847557068],"type":"Point"}
}