{
  "type": "Feature",
  "properties": {
    "addr:full":"Kitchener ON N2M 2K5",
    "addr:postcode":"n2m 2k5",
    "iso:country":"CA",
    "sg:city":"Kitchener",
    "sg:classifiers":[
        {
            "category":"Food & Beverages",
            "subcategory":"Groceries & Convenience Stores",
            "type":"Retail Goods"
        }
    ],
    "sg:phone":"+1 519 743 2593",
    "sg:postcode":"N2M 2K5",
    "sg:province":"ON",
    "wof:name":"Farah's Food Mart",
    "wof:placetype":"venue"
},
  "geometry": {"coordinates":[-80.5238037109,43.4463615417],"type":"Point"}
}