{
  "type": "Feature",
  "properties": {
    "addr:full":"242 Ontario St St Catharines ON L2R 5L4",
    "addr:housenumber":"242",
    "addr:postcode":"l2r 5l4",
    "addr:street":"Ontario St",
    "iso:country":"CA",
    "sg:address":"242 Ontario St",
    "sg:city":"St Catharines",
    "sg:classifiers":[
        {
            "category":"Retail",
            "subcategory":"Auto Repair",
            "type":"Services"
        }
    ],
    "sg:phone":"+1 905 684 8622",
    "sg:postcode":"L2R 5L4",
    "sg:province":"ON",
    "sg:tags":[
        "repairing",
        "automobile"
    ],
    "wof:name":"Ontario Street Svc Ctr",
    "wof:placetype":"venue"
},
  "geometry": {"coordinates":[-79.259529,43.163902],"type":"Point"}
}