{
  "type": "Feature",
  "properties": {
    "addr:full":"Saint-Jean-Sur-Richelieu QC J3B 8H7",
    "addr:postcode":"j3b 8h7",
    "iso:country":"CA",
    "sg:city":"Saint-Jean-Sur-Richelieu",
    "sg:classifiers":[
        {
            "category":"Manufacturing",
            "subcategory":"Furniture",
            "type":"Manufacturing & Wholesale Goods"
        }
    ],
    "sg:phone":"+1 450 359 0035",
    "sg:postcode":"J3B 8H7",
    "sg:province":"QC",
    "sg:tags":[
        "equipment",
        "kitchen",
        "cabinet"
    ],
    "wof:name":"Ebenisterie Luc Besner",
    "wof:placetype":"venue"
},
  "geometry": {"coordinates":[-73.296829,45.326485],"type":"Point"}
}