{
  "type": "Feature",
  "properties": {
    "addr:full":"Sherwood Park AB T8A 4E3",
    "addr:postcode":"t8a 4e3",
    "iso:country":"CA",
    "sg:city":"Sherwood Park",
    "sg:classifiers":[
        {
            "category":"Professional",
            "subcategory":"Accounting & Tax Preparation",
            "type":"Services"
        }
    ],
    "sg:phone":"+1 780 467 6805",
    "sg:postcode":"T8A 4E3",
    "sg:province":"AB",
    "sg:tags":[
        "accountant"
    ],
    "wof:name":"Hedstrom, Bruce",
    "wof:placetype":"venue"
},
  "geometry": {"coordinates":[-113.320564,53.53656],"type":"Point"}
}