{
  "type": "Feature",
  "properties": {
    "addr:full":"305 16th Ave E Vancouver BC V5T 2T7",
    "addr:housenumber":"305",
    "addr:postcode":"v5t 2t7",
    "addr:street":"16Th Ave E",
    "iso:country":"CA",
    "sg:address":"305 16th Ave E",
    "sg:city":"Vancouver",
    "sg:classifiers":[
        {
            "category":"Organizations",
            "subcategory":"Religious Organization",
            "type":"Services"
        }
    ],
    "sg:phone":"+1 604 879 8116",
    "sg:postcode":"V5T 2T7",
    "sg:province":"BC",
    "sg:tags":[
        "church"
    ],
    "wof:name":"Seicho-No-Ie Vancouver Church",
    "wof:placetype":"venue"
},
  "geometry": {"coordinates":[-123.098061,49.256721],"type":"Point"}
}