{
  "type": "Feature",
  "properties": {
    "addr:full":"Sudbury ON P3E 1H5",
    "addr:postcode":"p3e 1h5",
    "iso:country":"CA",
    "sg:city":"Sudbury",
    "sg:classifiers":[
        {
            "category":"Organizations",
            "subcategory":"Professional Association",
            "type":"Services"
        }
    ],
    "sg:phone":"+1 705 671 6099",
    "sg:postcode":"P3E 1H5",
    "sg:province":"ON",
    "wof:name":"Sudbury & District Home Bldrs",
    "wof:placetype":"venue"
},
  "geometry": {"coordinates":[-81.005951,46.482643],"type":"Point"}
}