{
  "type": "Feature",
  "properties": {
    "addr:full":"274 Barton St Stoney Creek ON L8E 2K5",
    "addr:housenumber":"274",
    "addr:postcode":"l8e 2k5",
    "addr:street":"Barton St",
    "iso:country":"CA",
    "sg:address":"274 Barton St",
    "sg:city":"Stoney Creek",
    "sg:classifiers":[
        {
            "category":"Shopping",
            "subcategory":"Discount & Variety Stores",
            "type":"Retail Goods"
        }
    ],
    "sg:phone":"+1 905 662 3501",
    "sg:postcode":"L8E 2K5",
    "sg:province":"ON",
    "wof:name":"Green's Variety",
    "wof:placetype":"venue"
},
  "geometry": {"coordinates":[-79.729973,43.229885],"type":"Point"}
}