{
  "type": "Feature",
  "properties": {
    "addr:full":"Vancouver BC V5X 3J3",
    "addr:postcode":"v5x 3j3",
    "iso:country":"CA",
    "sg:city":"Vancouver",
    "sg:classifiers":[
        {
            "category":"Home & Garden",
            "subcategory":"Home Furnishings",
            "type":"Retail Goods"
        }
    ],
    "sg:phone":"+1 604 325 6090",
    "sg:postcode":"V5X 3J3",
    "sg:province":"BC",
    "sg:tags":[
        "curtain",
        "made",
        "drapery"
    ],
    "wof:name":"Shan Drapery & Blinds Ltd",
    "wof:placetype":"venue"
},
  "geometry": {"coordinates":[-123.10206599999999,49.21909],"type":"Point"}
}