{
  "type": "Feature",
  "properties": {
    "iso:country":"CA",
    "sg:address":"880 Av Ogilvy",
    "sg:city":"Montreal",
    "sg:classifiers":[
        {
            "category":"Social Services",
            "subcategory":"Child Care",
            "type":"Services"
        }
    ],
    "sg:phone":"+1 514 271 6343",
    "sg:postcode":"H3N 1P1",
    "sg:province":"QC",
    "wof:name":"Garderie Le Monde DE L'Enfant",
    "wof:placetype":"venue"
},
  "geometry": {"coordinates":[-73.626846,45.526043],"type":"Point"}
}