{
  "type": "Feature",
  "properties": {
    "addr:full":"Parish Rd Houston BC V0J 1Z0",
    "addr:postcode":"v0j 1z0",
    "addr:street":"Parish Rd",
    "iso:country":"CA",
    "sg:address":"Parish Rd",
    "sg:city":"Houston",
    "sg:classifiers":[
        {
            "category":"Travel",
            "subcategory":"Campground",
            "type":"Entertainment"
        }
    ],
    "sg:phone":"+1 250 845 7155",
    "sg:postcode":"V0J 1Z0",
    "sg:province":"BC",
    "sg:tags":[
        "camp"
    ],
    "wof:name":"Rough Acres Bible Camp",
    "wof:placetype":"venue"
},
  "geometry": {"coordinates":[-126.650428772,54.391040802],"type":"Point"}
}