{
  "type": "Feature",
  "properties": {
    "addr:full":"255 Cornwall Dr Fort Mcmurray AB T9K 1G7",
    "addr:housenumber":"255",
    "addr:postcode":"t9k 1g7",
    "addr:street":"Cornwall Dr",
    "iso:country":"CA",
    "sg:address":"255 Cornwall Dr",
    "sg:city":"Fort Mcmurray",
    "sg:classifiers":[
        {
            "category":"Organizations",
            "subcategory":"Religious Organization",
            "type":"Services"
        }
    ],
    "sg:phone":"+1 780 743 5754",
    "sg:postcode":"T9K 1G7",
    "sg:province":"AB",
    "sg:tags":[
        "church"
    ],
    "wof:name":"Faith Presbyterian Church",
    "wof:placetype":"venue"
},
  "geometry": {"coordinates":[-111.45136261,56.7365951538],"type":"Point"}
}