{
  "type": "Feature",
  "properties": {
    "addr:full":"260 Hearst Way Kanata ON K2L 3H1",
    "addr:housenumber":"260",
    "addr:postcode":"k2l 3h1",
    "addr:street":"Hearst Way",
    "iso:country":"CA",
    "sg:address":"260 Hearst Way",
    "sg:city":"Kanata",
    "sg:classifiers":[
        {
            "category":"Restaurant",
            "type":"Food & Drink"
        }
    ],
    "sg:phone":"+1 613 592 0442",
    "sg:postcode":"K2L 3H1",
    "sg:province":"ON",
    "wof:name":"Tommy's Dining Lounge",
    "wof:placetype":"venue"
},
  "geometry": {"coordinates":[-75.893387,45.314774],"type":"Point"}
}