{
  "type": "Feature",
  "properties": {
    "addr:full":"75 Rue St-Francois Edmundston NB E3V 1E5",
    "addr:housenumber":"75",
    "addr:postcode":"e3v 1e5",
    "addr:street":"Rue St-Francois",
    "iso:country":"CA",
    "sg:address":"75 Rue St-Francois",
    "sg:city":"Edmundston",
    "sg:classifiers":[
        {
            "category":"Real Estate",
            "subcategory":"Architect",
            "type":"Services"
        }
    ],
    "sg:phone":"+1 506 735 7181",
    "sg:postcode":"E3V 1E5",
    "sg:province":"NB",
    "wof:name":"Ronald Lapointe Architecte Inc",
    "wof:placetype":"venue"
},
  "geometry": {"coordinates":[-68.32988,47.362129],"type":"Point"}
}