{
  "type": "Feature",
  "properties": {
    "iso:country":"CA",
    "sg:address":"3683 4th Ave W",
    "sg:city":"Vancouver",
    "sg:classifiers":[
        {
            "category":"Restaurant",
            "type":"Food & Drink"
        }
    ],
    "sg:phone":"+1 604 437 8676",
    "sg:postcode":"V6R 1P2",
    "sg:province":"BC",
    "wof:name":"Let's Go For Dinner",
    "wof:placetype":"venue"
},
  "geometry": {"coordinates":[-123.185157776,49.2687568665],"type":"Point"}
}