{
  "type": "Feature",
  "properties": {
    "addr:full":"201 Cowan Ave Toronto ON M6K 2N7",
    "addr:housenumber":"201",
    "addr:postcode":"m6k 2n7",
    "addr:street":"Cowan Ave",
    "iso:country":"CA",
    "sg:address":"201 Cowan Ave",
    "sg:city":"Toronto",
    "sg:classifiers":[
        {
            "category":"Organizations",
            "subcategory":"Religious Organization",
            "type":"Services"
        }
    ],
    "sg:phone":"+1 416 535 8240",
    "sg:postcode":"M6K 2N7",
    "sg:province":"ON",
    "sg:tags":[
        "church"
    ],
    "wof:name":"Church of the Epiphany St Mark",
    "wof:placetype":"venue"
},
  "geometry": {"coordinates":[-79.432396,43.640118],"type":"Point"}
}