{
  "type": "Feature",
  "properties": {
    "addr:full":"Toronto ON M5H 1S3",
    "addr:postcode":"m5h 1s3",
    "iso:country":"CA",
    "sg:city":"Toronto",
    "sg:classifiers":[
        {
            "category":"Professional",
            "subcategory":"Lawyer & Legal Services",
            "type":"Services"
        }
    ],
    "sg:phone":"+1 416 956 9655",
    "sg:postcode":"M5H 1S3",
    "sg:province":"ON",
    "sg:tags":[
        "attorney"
    ],
    "wof:name":"Brian Cintosun & Ibrahim",
    "wof:placetype":"venue"
},
  "geometry": {"coordinates":[-79.382423,43.649673],"type":"Point"}
}