{
  "type": "Feature",
  "properties": {
    "addr:full":"293 Rue Des Jacinthes Gatineau QC J8R 1L9",
    "addr:housenumber":"293",
    "addr:postcode":"j8r 1l9",
    "addr:street":"Rue Des Jacinthes",
    "iso:country":"CA",
    "sg:address":"293 Rue Des Jacinthes",
    "sg:city":"Gatineau",
    "sg:classifiers":[
        {
            "category":"Professional",
            "subcategory":"Computer Services",
            "type":"Services"
        }
    ],
    "sg:phone":"+1 819 663 6962",
    "sg:postcode":"J8R 1L9",
    "sg:province":"QC",
    "sg:tags":[
        "information",
        "consultant",
        "system",
        "internet"
    ],
    "wof:name":"Ciber",
    "wof:placetype":"venue"
},
  "geometry": {"coordinates":[-75.601921,45.504364],"type":"Point"}
}