{
  "type": "Feature",
  "properties": {
    "addr:full":"Fredericton NB E3B 3L3",
    "addr:postcode":"e3b 3l3",
    "iso:country":"CA",
    "sg:city":"Fredericton",
    "sg:classifiers":[
        {
            "category":"Government",
            "subcategory":"Office",
            "type":"Public Place"
        }
    ],
    "sg:phone":"+1 506 452 3016",
    "sg:postcode":"E3B 3L3",
    "sg:province":"NB",
    "wof:name":"Federal Court of Canada",
    "wof:placetype":"venue"
},
  "geometry": {"coordinates":[-66.6457824707,45.9631500244],"type":"Point"}
}