{
  "type": "Feature",
  "properties": {
    "addr:full":"Vaudreuil-Dorion QC J7V 1Y5",
    "addr:postcode":"j7v 1y5",
    "iso:country":"CA",
    "sg:city":"Vaudreuil-Dorion",
    "sg:classifiers":[
        {
            "category":"Banks & Credit Unions",
            "subcategory":"Investment Brokerage",
            "type":"Services"
        }
    ],
    "sg:phone":"+1 450 424 1335",
    "sg:postcode":"J7V 1Y5",
    "sg:province":"QC",
    "sg:tags":[
        "consultant",
        "planning",
        "financial"
    ],
    "wof:name":"Bar Zebrah",
    "wof:placetype":"venue"
},
  "geometry": {"coordinates":[-74.016785,45.380383],"type":"Point"}
}