{
  "type": "Feature",
  "properties": {
    "addr:full":"1110 Idylwyld Dr N Saskatoon SK S7L 4J7",
    "addr:housenumber":"1110",
    "addr:postcode":"s7l 4j7",
    "addr:street":"Idylwyld Dr N",
    "iso:country":"CA",
    "sg:address":"1110 Idylwyld Dr N",
    "sg:city":"Saskatoon",
    "sg:classifiers":[
        {
            "category":"Recreation",
            "type":"Entertainment"
        }
    ],
    "sg:phone":"+1 306 975 3321",
    "sg:postcode":"S7L 4J7",
    "sg:province":"SK",
    "sg:tags":[
        "pool",
        "swimming"
    ],
    "wof:name":"Harry Bailey Aquatic Ctr",
    "wof:placetype":"venue"
},
  "geometry": {"coordinates":[-106.669899,52.142296],"type":"Point"}
}