{
  "type": "Feature",
  "properties": {
    "addr:full":"Winkler MB R6W 1G3",
    "addr:postcode":"r6w 1g3",
    "iso:country":"CA",
    "sg:city":"Winkler",
    "sg:classifiers":[
        {
            "category":"Health Services",
            "subcategory":"Chiropractor",
            "type":"Services"
        }
    ],
    "sg:phone":"+1 204 325 9604",
    "sg:postcode":"R6W 1G3",
    "sg:province":"MB",
    "wof:name":"Winkler Chiropractic Office",
    "wof:placetype":"venue"
},
  "geometry": {"coordinates":[-97.939087,49.186558],"type":"Point"}
}