{
  "type": "Feature",
  "properties": {
    "iso:country":"CA",
    "sg:address":"2368 Lakeshore Rd W",
    "sg:city":"Oakville",
    "sg:classifiers":[
        {
            "category":"Personal",
            "subcategory":"Beauty Salon",
            "type":"Services"
        }
    ],
    "sg:phone":"+1 905 469 0344",
    "sg:postcode":"L6L 1H5",
    "sg:province":"ON",
    "wof:name":"Hair Studio 1",
    "wof:placetype":"venue"
},
  "geometry": {"coordinates":[-79.70916,43.396545],"type":"Point"}
}