{
  "type": "Feature",
  "properties": {
    "addr:full":"1400 Boul DE LA Grande-Allee # 201 Boisbriand QC J7G 2Z8",
    "addr:housenumber":"1400",
    "addr:postcode":"j7g 2z8",
    "addr:street":"Boul De La Grande-Allee # 201",
    "iso:country":"CA",
    "sg:address":"1400 Boul DE LA Grande-Allee # 201",
    "sg:city":"Boisbriand",
    "sg:classifiers":[
        {
            "category":"Insurance",
            "subcategory":"Insurance Agent",
            "type":"Services"
        }
    ],
    "sg:phone":"+1 450 434 1132",
    "sg:postcode":"J7G 2Z8",
    "sg:province":"QC",
    "wof:name":"Groupe Lyras",
    "wof:placetype":"venue"
},
  "geometry": {"coordinates":[-73.84196472169999,45.6174125671],"type":"Point"}
}