{
  "type": "Feature",
  "properties": {
    "iso:country":"CA",
    "sg:address":"780 Boul Des Seigneurs",
    "sg:city":"Terrebonne",
    "sg:classifiers":[
        {
            "category":"Personal",
            "subcategory":"Beauty Salon",
            "type":"Services"
        }
    ],
    "sg:phone":"+1 450 471 8606",
    "sg:postcode":"J6W 1T7",
    "sg:province":"QC",
    "wof:name":"Studio-Beaute-Quatre Saisons",
    "wof:placetype":"venue"
},
  "geometry": {"coordinates":[-73.6381149292,45.7025299072],"type":"Point"}
}