{
  "type": "Feature",
  "properties": {
    "addr:full":"451 Boul Cure-Labelle Fabreville QC H7P 2P3",
    "addr:housenumber":"451",
    "addr:postcode":"h7p 2p3",
    "addr:street":"Boul Cure-Labelle",
    "iso:country":"CA",
    "sg:address":"451 Boul Cure-Labelle",
    "sg:city":"Fabreville",
    "sg:classifiers":[
        {
            "category":"Restaurant",
            "type":"Food & Drink"
        }
    ],
    "sg:phone":"+1 450 625 0707",
    "sg:postcode":"H7P 2P3",
    "sg:province":"QC",
    "wof:name":"Restaurant Ste-Rose Diner Inc",
    "wof:placetype":"venue"
},
  "geometry": {"coordinates":[-73.78852081300001,45.578502655],"type":"Point"}
}