{
  "type": "Feature",
  "properties": {
    "addr:full":"Ajax ON L1T 1P5",
    "addr:postcode":"l1t 1p5",
    "iso:country":"CA",
    "sg:city":"Ajax",
    "sg:classifiers":[
        {
            "category":"Retail",
            "subcategory":"Veterinary Services",
            "type":"Services"
        }
    ],
    "sg:phone":"+1 905 683 8087",
    "sg:postcode":"L1T 1P5",
    "sg:province":"ON",
    "sg:tags":[
        "veterinarian"
    ],
    "wof:name":"Donovan, P DVM",
    "wof:placetype":"venue"
},
  "geometry": {"coordinates":[-79.0414352417,43.8588485718],"type":"Point"}
}