{
  "type": "Feature",
  "properties": {
    "addr:full":"612 Main St Sussex NB E4E 7H8",
    "addr:housenumber":"612",
    "addr:postcode":"e4e 7h8",
    "addr:street":"Main St",
    "iso:country":"CA",
    "sg:address":"612 Main St",
    "sg:city":"Sussex",
    "sg:classifiers":[
        {
            "category":"Restaurant",
            "type":"Food & Drink"
        }
    ],
    "sg:phone":"+1 506 433 4007",
    "sg:postcode":"E4E 7H8",
    "sg:province":"NB",
    "wof:name":"Cathy's Chinese Restaurant",
    "wof:placetype":"venue"
},
  "geometry": {"coordinates":[-65.5077819824,45.723274231],"type":"Point"}
}