{
  "type": "Feature",
  "properties": {
    "addr:full":"3574 Irwin Crt Mississauga ON L5L 4W3",
    "addr:housenumber":"3574",
    "addr:postcode":"l5l 4w3",
    "addr:street":"Irwin Crt",
    "iso:country":"CA",
    "sg:address":"3574 Irwin Crt",
    "sg:city":"Mississauga",
    "sg:classifiers":[
        {
            "category":"Professional",
            "subcategory":"Management & Consulting",
            "type":"Services"
        }
    ],
    "sg:phone":"+1 905 820 0830",
    "sg:postcode":"L5L 4W3",
    "sg:province":"ON",
    "sg:tags":[
        "training",
        "sales"
    ],
    "wof:name":"Training Makes Cents Inc",
    "wof:placetype":"venue"
},
  "geometry": {"coordinates":[-79.698425,43.530045],"type":"Point"}
}