{
  "type": "Feature",
  "properties": {
    "addr:full":"6370 Rue Pelletier Laval QC H7H 2P7",
    "addr:housenumber":"6370",
    "addr:postcode":"h7h 2p7",
    "addr:street":"Rue Pelletier",
    "iso:country":"CA",
    "sg:address":"6370 Rue Pelletier",
    "sg:city":"Laval",
    "sg:classifiers":[
        {
            "category":"Home & Garden",
            "subcategory":"Household Appliances",
            "type":"Retail Goods"
        }
    ],
    "sg:phone":"+1 450 963 7727",
    "sg:postcode":"H7H 2P7",
    "sg:province":"QC",
    "wof:name":"Appareil Electromax",
    "wof:placetype":"venue"
},
  "geometry": {"coordinates":[-73.75309753419999,45.6413764954],"type":"Point"}
}