{
  "type": "Feature",
  "properties": {
    "addr:full":"122 Ch Trudel Huberdeau QC J0T 1G0",
    "addr:housenumber":"122",
    "addr:postcode":"j0t 1g0",
    "addr:street":"Ch Trudel",
    "iso:country":"CA",
    "sg:address":"122 Ch Trudel",
    "sg:city":"Huberdeau",
    "sg:classifiers":[
        {
            "category":"Travel",
            "subcategory":"Hotels & Motels",
            "type":"Entertainment"
        }
    ],
    "sg:phone":"+1 819 687 8888",
    "sg:postcode":"J0T 1G0",
    "sg:province":"QC",
    "sg:tags":[
        "inn"
    ],
    "wof:name":"Auberge Du Lac A LA Loutre",
    "wof:placetype":"venue"
},
  "geometry": {"coordinates":[-74.65757000000001,45.999004],"type":"Point"}
}