{
  "type": "Feature",
  "properties": {
    "addr:full":"100 Abegweit Blvd Port Borden PE C0B 1X0",
    "addr:housenumber":"100",
    "addr:postcode":"c0b 1x0",
    "addr:street":"Abegweit Blvd",
    "iso:country":"CA",
    "sg:address":"100 Abegweit Blvd",
    "sg:city":"Port Borden",
    "sg:classifiers":[
        {
            "category":"Government",
            "subcategory":"Office",
            "type":"Public Place"
        }
    ],
    "sg:phone":"+1 902 437 8570",
    "sg:postcode":"C0B 1X0",
    "sg:province":"PE",
    "sg:tags":[
        "information",
        "tourist"
    ],
    "wof:name":"Pei Visitor Information Ctr",
    "wof:placetype":"venue"
},
  "geometry": {"coordinates":[-63.6951904297,46.2549057007],"type":"Point"}
}