{
  "type": "Feature",
  "properties": {
    "addr:full":"Bonavista Bay Kings Cove NL A0C 1S0",
    "addr:postcode":"a0c 1s0",
    "addr:street":"Bonavista Bay Kings Cove",
    "iso:country":"CA",
    "sg:address":"Bonavista Bay",
    "sg:city":"Kings Cove",
    "sg:classifiers":[
        {
            "category":"Organizations",
            "subcategory":"Professional Association",
            "type":"Services"
        }
    ],
    "sg:phone":"+1 709 447 2100",
    "sg:postcode":"A0C 1S0",
    "sg:province":"NL",
    "wof:name":"Knights of Columbus",
    "wof:placetype":"venue"
},
  "geometry": {"coordinates":[-57.961231,48.949078],"type":"Point"}
}