{
  "type": "Feature",
  "properties": {
    "addr:full":"200 Grand River Ave Brantford ON N3T 4X9",
    "addr:housenumber":"200",
    "addr:postcode":"n3t 4x9",
    "addr:street":"Grand River Ave",
    "iso:country":"CA",
    "sg:address":"200 Grand River Ave",
    "sg:city":"Brantford",
    "sg:classifiers":[
        {
            "category":"Restaurant",
            "type":"Food & Drink"
        }
    ],
    "sg:phone":"+1 519 756 8431",
    "sg:postcode":"N3T 4X9",
    "sg:province":"ON",
    "wof:name":"Wendcorp Holdings",
    "wof:placetype":"venue"
},
  "geometry": {"coordinates":[-80.2841873169,43.1413383484],"type":"Point"}
}