{
  "type": "Feature",
  "properties": {
    "addr:full":"211 Harmony Rd N Oshawa ON L1G 6L4",
    "addr:housenumber":"211",
    "addr:postcode":"l1g 6l4",
    "addr:street":"Harmony Rd N",
    "iso:country":"CA",
    "sg:address":"211 Harmony Rd N",
    "sg:city":"Oshawa",
    "sg:classifiers":[
        {
            "category":"Education",
            "subcategory":"School",
            "type":"Public Place"
        }
    ],
    "sg:phone":"+1 905 728 0681",
    "sg:postcode":"L1G 6L4",
    "sg:province":"ON",
    "wof:name":"Vincent Massey Public School",
    "wof:placetype":"venue"
},
  "geometry": {"coordinates":[-78.8365020752,43.9102554321],"type":"Point"}
}