{
  "type": "Feature",
  "properties": {
    "addr:full":"6025 Bronze Rd Port Hardy BC V0N 2P0",
    "addr:housenumber":"6025",
    "addr:postcode":"v0n 2p0",
    "addr:street":"Bronze Rd",
    "iso:country":"CA",
    "sg:address":"6025 Bronze Rd",
    "sg:city":"Port Hardy",
    "sg:classifiers":[
        {
            "category":"Building & Trades",
            "subcategory":"Electrical",
            "type":"Services"
        }
    ],
    "sg:phone":"+1 250 949 8133",
    "sg:postcode":"V0N 2P0",
    "sg:province":"BC",
    "sg:tags":[
        "electric",
        "contractor"
    ],
    "wof:name":"K & K Electric Ltd",
    "wof:placetype":"venue"
},
  "geometry": {"coordinates":[-127.431442261,50.6851348877],"type":"Point"}
}