{
  "type": "Feature",
  "properties": {
    "addr:full":"Cranbrook BC V1C 2P3",
    "addr:postcode":"v1c 2p3",
    "iso:country":"CA",
    "sg:city":"Cranbrook",
    "sg:classifiers":[
        {
            "category":"Government",
            "subcategory":"Office",
            "type":"Public Place"
        }
    ],
    "sg:phone":"+1 250 426 1631",
    "sg:postcode":"V1C 2P3",
    "sg:province":"BC",
    "wof:name":"British Columbia Youth Justice",
    "wof:placetype":"venue"
},
  "geometry": {"coordinates":[-115.765991,49.510059],"type":"Point"}
}