{
  "type": "Feature",
  "properties": {
    "addr:full":"25 Beaty Ave Toronto ON M6K 3B3",
    "addr:housenumber":"25",
    "addr:postcode":"m6k 3b3",
    "addr:street":"Beaty Ave",
    "iso:country":"CA",
    "sg:address":"25 Beaty Ave",
    "sg:city":"Toronto",
    "sg:classifiers":[
        {
            "category":"Arts & Performance",
            "subcategory":"Theater",
            "type":"Entertainment"
        }
    ],
    "sg:phone":"+1 416 533 8848",
    "sg:postcode":"M6K 3B3",
    "sg:province":"ON",
    "wof:name":"Little Red Theatre",
    "wof:placetype":"venue"
},
  "geometry": {"coordinates":[-79.44010900000001,43.637444],"type":"Point"}
}