{
  "type": "Feature",
  "properties": {
    "addr:full":"Toronto ON M5H 1T1",
    "addr:postcode":"m5h 1t1",
    "iso:country":"CA",
    "sg:city":"Toronto",
    "sg:classifiers":[
        {
            "category":"Restaurant",
            "type":"Food & Drink"
        }
    ],
    "sg:phone":"+1 416 214 0070",
    "sg:postcode":"M5H 1T1",
    "sg:province":"ON",
    "wof:name":"Fit For Life Fresh Food",
    "wof:placetype":"venue"
},
  "geometry": {"coordinates":[-79.38343811039999,43.6494560242],"type":"Point"}
}