{
  "type": "Feature",
  "properties": {
    "addr:full":"Esterhazy SK S0A 0X0",
    "addr:postcode":"s0a 0x0",
    "addr:street":"Esterhazy",
    "iso:country":"CA",
    "sg:city":"Esterhazy",
    "sg:classifiers":[
        {
            "category":"Retail",
            "subcategory":"Auto Repair",
            "type":"Services"
        }
    ],
    "sg:phone":"+1 306 745 6233",
    "sg:postcode":"S0A 0X0",
    "sg:province":"SK",
    "sg:tags":[
        "body",
        "automobile",
        "painting"
    ],
    "wof:name":"Towne Autobody Ltd",
    "wof:placetype":"venue"
},
  "geometry": {"coordinates":[-102.086921692,50.6497802734],"type":"Point"}
}