{
  "type": "Feature",
  "properties": {
    "addr:full":"Ottawa ON K2P 0Z8",
    "addr:postcode":"k2p 0z8",
    "iso:country":"CA",
    "sg:city":"Ottawa",
    "sg:classifiers":[
        {
            "category":"Social Services",
            "type":"Services"
        }
    ],
    "sg:phone":"+1 613 563 4400",
    "sg:postcode":"K2P 0Z8",
    "sg:province":"ON",
    "sg:tags":[
        "counselor",
        "marriage",
        "family"
    ],
    "wof:name":"Bleecker, Sally",
    "wof:placetype":"venue"
},
  "geometry": {"coordinates":[-75.6887664795,45.4135284424],"type":"Point"}
}