{
  "type": "Feature",
  "properties": {
    "addr:full":"1750 Rue Du Perigord Charlesbourg QC G1G 5X3",
    "addr:housenumber":"1750",
    "addr:postcode":"g1g 5x3",
    "addr:street":"Rue Du Perigord",
    "iso:country":"CA",
    "sg:address":"1750 Rue Du Perigord",
    "sg:city":"Charlesbourg",
    "sg:classifiers":[
        {
            "category":"Government",
            "subcategory":"Office",
            "type":"Public Place"
        }
    ],
    "sg:phone":"+1 418 643 7620",
    "sg:postcode":"G1G 5X3",
    "sg:province":"QC",
    "wof:name":"Quebec Societe Assurance Auto",
    "wof:placetype":"venue"
},
  "geometry": {"coordinates":[-71.2897949219,46.8677101135],"type":"Point"}
}