{
  "type": "Feature",
  "properties": {
    "addr:full":"814 Queen St E Sault Ste Marie ON P6A 2B1",
    "addr:housenumber":"814",
    "addr:postcode":"p6a 2b1",
    "addr:street":"Queen St E",
    "iso:country":"CA",
    "sg:address":"814 Queen St E",
    "sg:city":"Sault Ste Marie",
    "sg:classifiers":[
        {
            "category":"Food & Beverages",
            "subcategory":"Groceries & Convenience Stores",
            "type":"Retail Goods"
        }
    ],
    "sg:phone":"+1 705 256 2271",
    "sg:postcode":"P6A 2B1",
    "sg:province":"ON",
    "sg:tags":[
        "grocer"
    ],
    "wof:name":"City Meat Market",
    "wof:placetype":"venue"
},
  "geometry": {"coordinates":[-84.325012207,46.506942749],"type":"Point"}
}