{
  "type": "Feature",
  "properties": {
    "addr:full":"1397 Commercial Dr Vancouver BC V5L 3X5",
    "addr:housenumber":"1397",
    "addr:postcode":"v5l 3x5",
    "addr:street":"Commercial Dr",
    "iso:country":"CA",
    "sg:address":"1397 Commercial Dr",
    "sg:city":"Vancouver",
    "sg:classifiers":[
        {
            "category":"Health Services",
            "subcategory":"Chiropractor",
            "type":"Services"
        }
    ],
    "sg:phone":"+1 604 253 2515",
    "sg:postcode":"V5L 3X5",
    "sg:province":"BC",
    "wof:name":"Beaton, K C DC",
    "wof:placetype":"venue"
},
  "geometry": {"coordinates":[-123.069786072,49.2721710205],"type":"Point"}
}