{
  "type": "Feature",
  "properties": {
    "addr:full":"1997 Danforth Ave Toronto ON M4C 1J7",
    "addr:housenumber":"1997",
    "addr:postcode":"m4c 1j7",
    "addr:street":"Danforth Ave",
    "iso:country":"CA",
    "sg:address":"1997 Danforth Ave",
    "sg:city":"Toronto",
    "sg:classifiers":[
        {
            "category":"Banks & Credit Unions",
            "subcategory":"Bank",
            "type":"Services"
        }
    ],
    "sg:phone":"+1 416 693 8630",
    "sg:postcode":"M4C 1J7",
    "sg:province":"ON",
    "sg:tags":[
        "financing"
    ],
    "wof:name":"Atlantic Hs Financial Corp",
    "wof:placetype":"venue"
},
  "geometry": {"coordinates":[-79.314575,43.685146],"type":"Point"}
}