{
  "type": "Feature",
  "properties": {
    "addr:full":"NE 16 6 5E Kleefeld MB R0A 0V0",
    "addr:housenumber":"6",
    "addr:postcode":"r0a 0v0",
    "addr:street":"Ne 16",
    "iso:country":"CA",
    "sg:address":"NE 16 6 5E",
    "sg:city":"Kleefeld",
    "sg:classifiers":[
        {
            "category":"Education",
            "subcategory":"School",
            "type":"Public Place"
        }
    ],
    "sg:phone":"+1 204 377 4204",
    "sg:postcode":"R0A 0V0",
    "sg:province":"MB",
    "wof:name":"New Hope Christian School",
    "wof:placetype":"venue"
},
  "geometry": {"coordinates":[-96.872681,49.502579],"type":"Point"}
}