{
  "type": "Feature",
  "properties": {
    "addr:full":"Saint-Hyacinthe QC J2S 5W7",
    "addr:postcode":"j2s 5w7",
    "iso:country":"CA",
    "sg:city":"Saint-Hyacinthe",
    "sg:classifiers":[
        {
            "category":"Health Services",
            "subcategory":"Doctor",
            "type":"Services"
        }
    ],
    "sg:phone":"+1 450 774 2002",
    "sg:postcode":"J2S 5W7",
    "sg:province":"QC",
    "sg:tags":[
        "physician",
        "surgeon"
    ],
    "wof:name":"Osteopathie-Physiotherapie",
    "wof:placetype":"venue"
},
  "geometry": {"coordinates":[-72.9628753662,45.6318435669],"type":"Point"}
}