{
  "type": "Feature",
  "properties": {
    "addr:full":"18 Meadowpoint Dr Hamilton ON L9B 2T4",
    "addr:housenumber":"18",
    "addr:postcode":"l9b 2t4",
    "addr:street":"Meadowpoint Dr",
    "iso:country":"CA",
    "sg:address":"18 Meadowpoint Dr",
    "sg:city":"Hamilton",
    "sg:classifiers":[
        {
            "category":"Professional",
            "subcategory":"Management & Consulting",
            "type":"Services"
        }
    ],
    "sg:phone":"+1 905 388 0842",
    "sg:postcode":"L9B 2T4",
    "sg:province":"ON",
    "sg:tags":[
        "control",
        "consultant",
        "quality"
    ],
    "wof:name":"Iso Assist",
    "wof:placetype":"venue"
},
  "geometry": {"coordinates":[-79.885857,43.196922],"type":"Point"}
}