{
  "type": "Feature",
  "properties": {
    "addr:full":"Hamilton ON L8R 3K2",
    "addr:postcode":"l8r 3k2",
    "iso:country":"CA",
    "sg:city":"Hamilton",
    "sg:classifiers":[
        {
            "category":"Real Estate",
            "subcategory":"Real Estate Operator",
            "type":"Services"
        }
    ],
    "sg:phone":"+1 905 523 5700",
    "sg:postcode":"L8R 3K2",
    "sg:province":"ON",
    "sg:tags":[
        "apartment"
    ],
    "wof:name":"Market Street Apartments",
    "wof:placetype":"venue"
},
  "geometry": {"coordinates":[-79.874527,43.258999],"type":"Point"}
}