{
  "type": "Feature",
  "properties": {
    "iso:country":"CA",
    "sg:city":"Longueuil",
    "sg:classifiers":[
        {
            "category":"Professional",
            "subcategory":"Lawyer & Legal Services",
            "type":"Services"
        }
    ],
    "sg:phone":"+1 450 928 7666",
    "sg:postcode":"J4J 3X5",
    "sg:province":"QC",
    "sg:tags":[
        "attorney"
    ],
    "wof:name":"Aide Juridique",
    "wof:placetype":"venue"
},
  "geometry": {"coordinates":[-73.484062,45.530308],"type":"Point"}
}