{
  "type": "Feature",
  "properties": {
    "addr:full":"1991 River Rd Prince George BC V2L 5S8",
    "addr:housenumber":"1991",
    "addr:postcode":"v2l 5s8",
    "addr:street":"River Rd",
    "iso:country":"CA",
    "sg:address":"1991 River Rd",
    "sg:city":"Prince George",
    "sg:classifiers":[
        {
            "category":"Autos & Motor Vehicles",
            "subcategory":"Fuel & Gas Station",
            "type":"Retail Goods"
        }
    ],
    "sg:phone":"+1 250 561 1233",
    "sg:postcode":"V2L 5S8",
    "sg:province":"BC",
    "sg:tags":[
        "company",
        "oil"
    ],
    "wof:name":"Esso",
    "wof:placetype":"venue"
},
  "geometry": {"coordinates":[-122.76007799999999,53.925995],"type":"Point"}
}