{
  "type": "Feature",
  "properties": {
    "iso:country":"CA",
    "sg:address":"1462 Storyland Rd",
    "sg:city":"Haley Station",
    "sg:classifiers":[
        {
            "category":"Restaurant",
            "type":"Food & Drink"
        }
    ],
    "sg:phone":"+1 613 432 1244",
    "sg:postcode":"K0J 1Y0",
    "sg:province":"ON",
    "wof:name":"Sunshine Cafe & Gas Bar",
    "wof:placetype":"venue"
},
  "geometry": {"coordinates":[-76.777756,45.562916],"type":"Point"}
}