{
  "type": "Feature",
  "properties": {
    "iso:country":"CA",
    "sg:address":"180 Av D'Iberia",
    "sg:city":"Candiac",
    "sg:classifiers":[
        {
            "category":"Manufacturing",
            "subcategory":"Printing",
            "type":"Manufacturing & Wholesale Goods"
        }
    ],
    "sg:phone":"+1 450 619 0991",
    "sg:postcode":"J5R 6A7",
    "sg:province":"QC",
    "sg:tags":[
        "printer"
    ],
    "wof:name":"Wilco Inc",
    "wof:placetype":"venue"
},
  "geometry": {"coordinates":[-73.5122756958,45.3997459412],"type":"Point"}
}