{
  "type": "Feature",
  "properties": {
    "iso:country":"CA",
    "sg:address":"9596 Oakland Rd SW",
    "sg:city":"Calgary",
    "sg:classifiers":[
        {
            "category":"Professional",
            "subcategory":"Computer Services",
            "type":"Services"
        }
    ],
    "sg:phone":"+1 403 251 4402",
    "sg:postcode":"T2V 4C1",
    "sg:province":"AB",
    "wof:name":"Frontier Solutions Inc",
    "wof:placetype":"venue"
},
  "geometry": {"coordinates":[-114.13518524200001,50.9684143066],"type":"Point"}
}