{
  "type": "Feature",
  "properties": {
    "addr:full":"295 Rue Peel Montreal QC H3C 3R9",
    "addr:housenumber":"295",
    "addr:postcode":"h3c 3r9",
    "addr:street":"Rue Peel",
    "iso:country":"CA",
    "sg:address":"295 Rue Peel",
    "sg:city":"Montreal",
    "sg:classifiers":[
        {
            "category":"Professional",
            "subcategory":"Computer Services",
            "type":"Services"
        }
    ],
    "sg:phone":"+1 514 933 4455",
    "sg:postcode":"H3C 3R9",
    "sg:province":"QC",
    "wof:name":"Compuservice",
    "wof:placetype":"venue"
},
  "geometry": {"coordinates":[-73.559731,45.494343],"type":"Point"}
}