{
  "type": "Feature",
  "properties": {
    "addr:full":"2159 Pickeral & Jack Lake Burks Falls ON P0A 1C0",
    "addr:housenumber":"2159",
    "addr:postcode":"p0a 1c0",
    "addr:street":"Pickeral & Jack Lake Burks",
    "iso:country":"CA",
    "sg:address":"2159 Pickeral & Jack Lake",
    "sg:city":"Burks Falls",
    "sg:classifiers":[
        {
            "category":"Travel",
            "subcategory":"Hotels & Motels",
            "type":"Entertainment"
        }
    ],
    "sg:phone":"+1 705 382 2025",
    "sg:postcode":"P0A 1C0",
    "sg:province":"ON",
    "sg:tags":[
        "resort"
    ],
    "wof:name":"Pickerel Lake Lodge Ltd",
    "wof:placetype":"venue"
},
  "geometry": {"coordinates":[-78.083015,44.751575],"type":"Point"}
}