{
  "type": "Feature",
  "properties": {
    "addr:full":"3545 45th Ave E Vancouver BC V5R 3G2",
    "addr:housenumber":"3545",
    "addr:postcode":"v5r 3g2",
    "addr:street":"45Th Ave E",
    "iso:country":"CA",
    "sg:address":"3545 45th Ave E",
    "sg:city":"Vancouver",
    "sg:classifiers":[
        {
            "category":"Building & Trades",
            "subcategory":"Construction",
            "type":"Services"
        }
    ],
    "sg:phone":"+1 604 436 6229",
    "sg:postcode":"V5R 3G2",
    "sg:province":"BC",
    "sg:tags":[
        "dry wall",
        "contractor"
    ],
    "wof:name":"National Drywall Ltd",
    "wof:placetype":"venue"
},
  "geometry": {"coordinates":[-123.02814499999999,49.229465],"type":"Point"}
}