{
  "type": "Feature",
  "properties": {
    "addr:full":"209 Rue Papineau Hull QC J8X 1W4",
    "addr:housenumber":"209",
    "addr:postcode":"j8x 1w4",
    "addr:street":"Rue Papineau",
    "iso:country":"CA",
    "sg:address":"209 Rue Papineau",
    "sg:city":"Hull",
    "sg:classifiers":[
        {
            "category":"Shopping",
            "subcategory":"Used Merchandise",
            "type":"Retail Goods"
        }
    ],
    "sg:phone":"+1 819 771 9550",
    "sg:postcode":"J8X 1W4",
    "sg:province":"QC",
    "sg:tags":[
        "antique"
    ],
    "wof:name":"Antiquites Du Portage",
    "wof:placetype":"venue"
},
  "geometry": {"coordinates":[-75.7139511108,45.4300384521],"type":"Point"}
}