{
  "type": "Feature",
  "properties": {
    "iso:country":"CA",
    "sg:city":"Langley",
    "sg:classifiers":[
        {
            "category":"Health Services",
            "subcategory":"Health Practitioner",
            "type":"Services"
        }
    ],
    "sg:phone":"+1 604 534 3248",
    "sg:postcode":"V2Y 2T2",
    "sg:province":"BC",
    "sg:tags":[
        "midwife"
    ],
    "wof:name":"Carlson-Rink, C",
    "wof:placetype":"venue"
},
  "geometry": {"coordinates":[-122.677375794,49.085849762],"type":"Point"}
}