{
  "type": "Feature",
  "properties": {
    "addr:full":"5033 Regent St Burnaby BC V5C 4H4",
    "addr:housenumber":"5033",
    "addr:postcode":"v5c 4h4",
    "addr:street":"Regent St",
    "iso:country":"CA",
    "sg:address":"5033 Regent St",
    "sg:city":"Burnaby",
    "sg:classifiers":[
        {
            "category":"Building & Trades",
            "subcategory":"Construction",
            "type":"Services"
        }
    ],
    "sg:phone":"+1 604 298 5943",
    "sg:postcode":"V5C 4H4",
    "sg:province":"BC",
    "sg:tags":[
        "boring",
        "drilling",
        "contractor"
    ],
    "wof:name":"Dynamic Drilling Inc",
    "wof:placetype":"venue"
},
  "geometry": {"coordinates":[-122.98983,49.258514],"type":"Point"}
}