{
  "type": "Feature",
  "properties": {
    "addr:full":"Langley BC V3A 4Y1",
    "addr:postcode":"v3a 4y1",
    "iso:country":"CA",
    "sg:city":"Langley",
    "sg:classifiers":[
        {
            "category":"Manufacturing",
            "subcategory":"Wood Products",
            "type":"Manufacturing & Wholesale Goods"
        }
    ],
    "sg:phone":"+1 604 534 9870",
    "sg:postcode":"V3A 4Y1",
    "sg:province":"BC",
    "sg:tags":[
        "picture",
        "frame"
    ],
    "wof:name":"Frame Warehouse",
    "wof:placetype":"venue"
},
  "geometry": {"coordinates":[-122.672233581,49.1130828857],"type":"Point"}
}