{
  "type": "Feature",
  "properties": {
    "addr:full":"St Albert AB T8N 1G3",
    "addr:postcode":"t8n 1g3",
    "iso:country":"CA",
    "sg:city":"St Albert",
    "sg:classifiers":[
        {
            "category":"Building & Trades",
            "subcategory":"Plumbing",
            "type":"Services"
        }
    ],
    "sg:phone":"+1 780 460 6075",
    "sg:postcode":"T8N 1G3",
    "sg:province":"AB",
    "sg:tags":[
        "conditioning",
        "air",
        "fireplace",
        "system",
        "contractor"
    ],
    "wof:name":"Fire Shoppe Ltd",
    "wof:placetype":"venue"
},
  "geometry": {"coordinates":[-113.62531300000001,53.638664],"type":"Point"}
}