{
  "type": "Feature",
  "properties": {
    "iso:country":"CA",
    "sg:address":"534 Rue DE Lanaudiere",
    "sg:city":"Joliette",
    "sg:classifiers":[
        {
            "category":"Shopping",
            "type":"Retail Goods"
        }
    ],
    "sg:phone":"+1 450 759 9977",
    "sg:postcode":"J6E 3M4",
    "sg:province":"QC",
    "sg:tags":[
        "trophy",
        "engraver",
        "medal",
        "award"
    ],
    "wof:name":"Trophees Jlm",
    "wof:placetype":"venue"
},
  "geometry": {"coordinates":[-73.43859100340001,46.0227203369],"type":"Point"}
}