{
  "type": "Feature",
  "properties": {
    "iso:country":"CA",
    "sg:address":"3350 2nd St E",
    "sg:city":"Cornwall",
    "sg:classifiers":[
        {
            "category":"Wholesale",
            "subcategory":"Chemicals & Plastics",
            "type":"Manufacturing & Wholesale Goods"
        }
    ],
    "sg:phone":"+1 613 932 3370",
    "sg:postcode":"K6H 6C6",
    "sg:province":"ON",
    "sg:tags":[
        "oxygen"
    ],
    "wof:name":"Air Liquide Canada Inc",
    "wof:placetype":"venue"
},
  "geometry": {"coordinates":[-74.6766586304,45.0383491516],"type":"Point"}
}