{
  "type": "Feature",
  "properties": {
    "addr:full":"344 Boul DE LA Marine Varennes QC J3X 1Z4",
    "addr:housenumber":"344",
    "addr:postcode":"j3x 1z4",
    "addr:street":"Boul De La Marine",
    "iso:country":"CA",
    "sg:address":"344 Boul DE LA Marine",
    "sg:city":"Varennes",
    "sg:classifiers":[
        {
            "category":"Restaurant",
            "type":"Food & Drink"
        }
    ],
    "sg:phone":"+1 450 929 9999",
    "sg:postcode":"J3X 1Z4",
    "sg:province":"QC",
    "wof:name":"Petit Quebec",
    "wof:placetype":"venue"
},
  "geometry": {"coordinates":[-73.421913,45.655899],"type":"Point"}
}