{
  "type": "Feature",
  "properties": {
    "addr:full":"5035 49 St # 1 Innisfail AB T4G 1V3",
    "addr:housenumber":"5035",
    "addr:postcode":"t4g 1v3",
    "addr:street":"49 St # 1",
    "iso:country":"CA",
    "sg:address":"5035 49 St # 1",
    "sg:city":"Innisfail",
    "sg:classifiers":[
        {
            "category":"Professional",
            "subcategory":"Lawyer & Legal Services",
            "type":"Services"
        }
    ],
    "sg:phone":"+1 403 227 3361",
    "sg:postcode":"T4G 1V3",
    "sg:province":"AB",
    "sg:tags":[
        "attorney"
    ],
    "wof:name":"Miller Lehane & Wild",
    "wof:placetype":"venue"
},
  "geometry": {"coordinates":[-113.950958,52.026386],"type":"Point"}
}