{
  "type": "Feature",
  "properties": {
    "addr:full":"1718 Boul Saint-Joseph Lachine QC H8S 2N2",
    "addr:housenumber":"1718",
    "addr:postcode":"h8s 2n2",
    "addr:street":"Boul Saint-Joseph",
    "iso:country":"CA",
    "sg:address":"1718 Boul Saint-Joseph",
    "sg:city":"Lachine",
    "sg:classifiers":[
        {
            "category":"Restaurant",
            "type":"Food & Drink"
        }
    ],
    "sg:phone":"+1 514 634 3400",
    "sg:postcode":"H8S 2N2",
    "sg:province":"QC",
    "wof:name":"Restaurant Pasta Andrea Inc",
    "wof:placetype":"venue"
},
  "geometry": {"coordinates":[-73.67997,45.432838],"type":"Point"}
}