{
  "type": "Feature",
  "properties": {
    "iso:country":"CA",
    "sg:address":"81 Kean Rd",
    "sg:city":"Saint John",
    "sg:classifiers":[
        {
            "category":"Professional",
            "subcategory":"Accounting & Tax Preparation",
            "type":"Services"
        }
    ],
    "sg:phone":"+1 506 672 4364",
    "sg:postcode":"E2M 4Y5",
    "sg:province":"NB",
    "sg:tags":[
        "accountant"
    ],
    "wof:name":"Vihvelin, Cynthia J",
    "wof:placetype":"venue"
},
  "geometry": {"coordinates":[-66.0967712402,45.2418632507],"type":"Point"}
}