{
  "type": "Feature",
  "properties": {
    "iso:country":"CA",
    "sg:city":"Montreal",
    "sg:classifiers":[
        {
            "category":"Real Estate",
            "subcategory":"Architect",
            "type":"Services"
        }
    ],
    "sg:phone":"+1 514 861 5122",
    "sg:postcode":"H3C 2N3",
    "sg:province":"QC",
    "wof:name":"Rubin & Rotman Assoc",
    "wof:placetype":"venue"
},
  "geometry": {"coordinates":[-73.557755,45.497662],"type":"Point"}
}