{
  "type": "Feature",
  "properties": {
    "iso:country":"CA",
    "sg:city":"North York",
    "sg:classifiers":[
        {
            "category":"Real Estate",
            "subcategory":"Real Estate Agent",
            "type":"Services"
        }
    ],
    "sg:phone":"+1 416 445 4286",
    "sg:postcode":"M3B 2M3",
    "sg:province":"ON",
    "sg:tags":[
        "management"
    ],
    "wof:name":"Great Spaces Property Mgmt",
    "wof:placetype":"venue"
},
  "geometry": {"coordinates":[-79.36028289790001,43.7551002502],"type":"Point"}
}