{
  "type": "Feature",
  "properties": {
    "addr:full":"PO Box 95 Darwell AB T0E 0L0",
    "addr:housenumber":"po box 95",
    "addr:postcode":"t0e 0l0",
    "addr:street":"Darwell Ab",
    "iso:country":"CA",
    "sg:address":"PO Box 95",
    "sg:city":"Darwell",
    "sg:classifiers":[
        {
            "category":"Recreation",
            "type":"Entertainment"
        }
    ],
    "sg:phone":"+1 780 892 3199",
    "sg:postcode":"T0E 0L0",
    "sg:province":"AB",
    "sg:tags":[
        "hall",
        "auditorium"
    ],
    "wof:name":"Darwell District Recreation",
    "wof:placetype":"venue"
},
  "geometry": {"coordinates":[-114.591492,53.669456],"type":"Point"}
}