{
  "type": "Feature",
  "properties": {
    "addr:full":"605 Rue Notre-Dame E Victoriaville QC G6P 6Y9",
    "addr:housenumber":"605",
    "addr:postcode":"g6p 6y9",
    "addr:street":"Rue Notre-Dame E",
    "iso:country":"CA",
    "sg:address":"605 Rue Notre-Dame E",
    "sg:city":"Victoriaville",
    "sg:classifiers":[
        {
            "category":"Education",
            "subcategory":"Special Training",
            "type":"Public Place"
        }
    ],
    "sg:phone":"+1 819 758 1084",
    "sg:postcode":"G6P 6Y9",
    "sg:province":"QC",
    "sg:tags":[
        "instruction",
        "music"
    ],
    "wof:name":"Harmonie L'Inspiration",
    "wof:placetype":"venue"
},
  "geometry": {"coordinates":[-71.94258880620001,46.062538147],"type":"Point"}
}