{
  "type": "Feature",
  "properties": {
    "addr:full":"1868 Dundas St E Mississauga ON L4X 1L9",
    "addr:housenumber":"1868",
    "addr:postcode":"l4x 1l9",
    "addr:street":"Dundas St E",
    "iso:country":"CA",
    "sg:address":"1868 Dundas St E",
    "sg:city":"Mississauga",
    "sg:classifiers":[
        {
            "category":"Building & Trades",
            "subcategory":"Construction",
            "type":"Services"
        }
    ],
    "sg:phone":"+1 416 233 7470",
    "sg:postcode":"L4X 1L9",
    "sg:province":"ON",
    "sg:tags":[
        "skylight"
    ],
    "wof:name":"Solatube",
    "wof:placetype":"venue"
},
  "geometry": {"coordinates":[-79.57203699999999,43.620083],"type":"Point"}
}