{
  "type": "Feature",
  "properties": {
    "addr:full":"7240 Rue Saint-Hubert Montreal QC H2R 2N1",
    "addr:housenumber":"7240",
    "addr:postcode":"h2r 2n1",
    "addr:street":"Rue Saint-Hubert",
    "iso:country":"CA",
    "sg:address":"7240 Rue Saint-Hubert",
    "sg:city":"Montreal",
    "sg:classifiers":[
        {
            "category":"Shopping",
            "subcategory":"Jewelry",
            "type":"Retail Goods"
        }
    ],
    "sg:phone":"+1 514 279 3939",
    "sg:postcode":"H2R 2N1",
    "sg:province":"QC",
    "sg:tags":[
        "jeweler"
    ],
    "wof:name":"Bijouterie DE Bruxelles",
    "wof:placetype":"venue"
},
  "geometry": {"coordinates":[-73.61438800000001,45.541134],"type":"Point"}
}