{
  "type": "Feature",
  "properties": {
    "addr:full":"Vancouver BC V6H 1E2",
    "addr:postcode":"v6h 1e2",
    "iso:country":"CA",
    "sg:city":"Vancouver",
    "sg:classifiers":[
        {
            "category":"Real Estate",
            "subcategory":"Real Estate Agent",
            "type":"Services"
        }
    ],
    "sg:phone":"+1 604 738 0188",
    "sg:postcode":"V6H 1E2",
    "sg:province":"BC",
    "sg:tags":[
        "notary"
    ],
    "wof:name":"Jang, Pauline",
    "wof:placetype":"venue"
},
  "geometry": {"coordinates":[-123.12789917000001,49.2635726929],"type":"Point"}
}