{
  "type": "Feature",
  "properties": {
    "addr:full":"344 Rue Saint-Roch #210 Quebec QC G1K 6S2",
    "addr:housenumber":"344;210",
    "addr:postcode":"g1k 6s2",
    "addr:street":"Rue Saint-Roch #",
    "iso:country":"CA",
    "sg:address":"344 Rue Saint-Roch #210",
    "sg:city":"Quebec",
    "sg:classifiers":[
        {
            "category":"Shopping",
            "type":"Retail Goods"
        }
    ],
    "sg:phone":"+1 418 524 6060",
    "sg:postcode":"G1K 6S2",
    "sg:province":"QC",
    "sg:tags":[
        "equipment",
        "telephone",
        "supply"
    ],
    "wof:name":"Versatel Communications Inc",
    "wof:placetype":"venue"
},
  "geometry": {"coordinates":[-71.218086,46.817955],"type":"Point"}
}