{
  "type": "Feature",
  "properties": {
    "iso:country":"CA",
    "sg:address":"39 Court St",
    "sg:city":"St Catharines",
    "sg:classifiers":[
        {
            "category":"Retail",
            "subcategory":"Funeral Services",
            "type":"Services"
        }
    ],
    "sg:phone":"+1 905 685 6584",
    "sg:postcode":"L2R 4R8",
    "sg:province":"ON",
    "sg:tags":[
        "director"
    ],
    "wof:name":"A Patrick Darte Funeral Chapel",
    "wof:placetype":"venue"
},
  "geometry": {"coordinates":[-79.242577,43.16214],"type":"Point"}
}