{
  "type": "Feature",
  "properties": {
    "iso:country":"CA",
    "sg:city":"Brandon",
    "sg:classifiers":[
        {
            "category":"Professional",
            "subcategory":"Credit Reporting & Collection",
            "type":"Services"
        }
    ],
    "sg:phone":"+1 204 726 0813",
    "sg:postcode":"R7A 4E8",
    "sg:province":"MB",
    "sg:tags":[
        "agency"
    ],
    "wof:name":"Trend Collection & Bailiff Svc",
    "wof:placetype":"venue"
},
  "geometry": {"coordinates":[-99.9516448975,49.845905304],"type":"Point"}
}