{
  "type": "Feature",
  "properties": {
    "addr:full":"80 S 1 St W Magrath AB T0K 1J0",
    "addr:housenumber":"80;1",
    "addr:postcode":"t0k 1j0",
    "addr:street":"S;St W Magrath",
    "iso:country":"CA",
    "sg:address":"80 S 1 St W",
    "sg:city":"Magrath",
    "sg:classifiers":[
        {
            "category":"Shopping",
            "subcategory":"Pharmacy",
            "type":"Retail Goods"
        }
    ],
    "sg:phone":"+1 403 758 3001",
    "sg:postcode":"T0K 1J0",
    "sg:province":"AB",
    "wof:name":"Magrath Pharmacy Ltd",
    "wof:placetype":"venue"
},
  "geometry": {"coordinates":[-112.862213135,49.4185371399],"type":"Point"}
}