{
  "type": "Feature",
  "properties": {
    "addr:full":"544 Rue Desormeaux Saint-Donat-DE-Montcalm QC J0T 2C0",
    "addr:housenumber":"544",
    "addr:postcode":"j0t 2c0",
    "addr:street":"Rue Desormeaux",
    "iso:country":"CA",
    "sg:address":"544 Rue Desormeaux",
    "sg:city":"Saint-Donat-DE-Montcalm",
    "sg:classifiers":[
        {
            "category":"Social Services",
            "type":"Services"
        }
    ],
    "sg:phone":"+1 819 424 3811",
    "sg:postcode":"J0T 2C0",
    "sg:province":"QC",
    "sg:tags":[
        "youth",
        "organization",
        "center"
    ],
    "wof:name":"Maison Des Jeunes DE St-Donat",
    "wof:placetype":"venue"
},
  "geometry": {"coordinates":[-74.218903,46.316792],"type":"Point"}
}