{
  "type": "Feature",
  "properties": {
    "addr:full":"16725 Jane St Kettleby ON L0G 1J0",
    "addr:housenumber":"16725",
    "addr:postcode":"l0g 1j0",
    "addr:street":"Jane St",
    "iso:country":"CA",
    "sg:address":"16725 Jane St",
    "sg:city":"Kettleby",
    "sg:classifiers":[
        {
            "category":"Building & Trades",
            "subcategory":"Landscaping Services",
            "type":"Services"
        }
    ],
    "sg:phone":"+1 905 727 0710",
    "sg:postcode":"L0G 1J0",
    "sg:province":"ON",
    "sg:tags":[
        "tree"
    ],
    "wof:name":"Tree Depot Inc",
    "wof:placetype":"venue"
},
  "geometry": {"coordinates":[-79.57502746580001,44.0130882263],"type":"Point"}
}