{
  "type": "Feature",
  "properties": {
    "addr:full":"4714 48th Ave Clive AB T0C 0Y0",
    "addr:housenumber":"4714",
    "addr:postcode":"t0c 0y0",
    "addr:street":"48Th Ave",
    "iso:country":"CA",
    "sg:address":"4714 48th Ave",
    "sg:city":"Clive",
    "sg:classifiers":[
        {
            "category":"Building & Trades",
            "subcategory":"Construction",
            "type":"Services"
        }
    ],
    "sg:phone":"+1 403 784 3439",
    "sg:postcode":"T0C 0Y0",
    "sg:province":"AB",
    "sg:tags":[
        "excavating",
        "contractor"
    ],
    "wof:name":"Dale's Ditching & Excavating",
    "wof:placetype":"venue"
},
  "geometry": {"coordinates":[-113.44423675500001,52.4733505249],"type":"Point"}
}