{
  "type": "Feature",
  "properties": {
    "addr:full":"Richmond BC V6V 1Y3",
    "addr:postcode":"v6v 1y3",
    "iso:country":"CA",
    "sg:city":"Richmond",
    "sg:classifiers":[
        {
            "category":"Home & Garden",
            "subcategory":"Building Materials",
            "type":"Retail Goods"
        }
    ],
    "sg:phone":"+1 604 278 6386",
    "sg:postcode":"V6V 1Y3",
    "sg:province":"BC",
    "sg:tags":[
        "windows"
    ],
    "wof:name":"Full Arts Ltd",
    "wof:placetype":"venue"
},
  "geometry": {"coordinates":[-123.06186700000001,49.199829],"type":"Point"}
}