{
  "type": "Feature",
  "properties": {
    "addr:full":"11 11E Rue Roxboro QC H8Y 1K6",
    "addr:housenumber":"11",
    "addr:postcode":"h8y 1k6",
    "addr:street":"11E Rue",
    "iso:country":"CA",
    "sg:address":"11 11E Rue",
    "sg:city":"Roxboro",
    "sg:classifiers":[
        {
            "category":"Social Services",
            "subcategory":"Child Care",
            "type":"Services"
        }
    ],
    "sg:phone":"+1 514 684 8699",
    "sg:postcode":"H8Y 1K6",
    "sg:province":"QC",
    "wof:name":"Cpe Hellenique Ilios",
    "wof:placetype":"venue"
},
  "geometry": {"coordinates":[-73.80342899999999,45.504761],"type":"Point"}
}