{
  "type": "Feature",
  "properties": {
    "addr:full":"2325 Rue Girard Trois-Rivieres QC G8Z 2M3",
    "addr:housenumber":"2325",
    "addr:postcode":"g8z 2m3",
    "addr:street":"Rue Girard",
    "iso:country":"CA",
    "sg:address":"2325 Rue Girard",
    "sg:city":"Trois-Rivieres",
    "sg:classifiers":[
        {
            "category":"Wholesale",
            "subcategory":"Electrical",
            "type":"Manufacturing & Wholesale Goods"
        }
    ],
    "sg:phone":"+1 819 378 4071",
    "sg:postcode":"G8Z 2M3",
    "sg:province":"QC",
    "sg:tags":[
        "equipment",
        "electric",
        "supply"
    ],
    "wof:name":"Westburne Quebec Inc",
    "wof:placetype":"venue"
},
  "geometry": {"coordinates":[-72.568634,46.337856],"type":"Point"}
}