{
  "type": "Feature",
  "properties": {
    "iso:country":"CA",
    "sg:address":"370 Rue Jean-Talon E",
    "sg:city":"Montreal",
    "sg:classifiers":[
        {
            "category":"Bars & Pubs",
            "type":"Food & Drink"
        }
    ],
    "sg:phone":"+1 514 279 6899",
    "sg:postcode":"H2R 1T3",
    "sg:province":"QC",
    "sg:tags":[
        "lounge",
        "cocktail"
    ],
    "wof:name":"Bar Pho Dem",
    "wof:placetype":"venue"
},
  "geometry": {"coordinates":[-73.614609,45.537891],"type":"Point"}
}