{
  "type": "Feature",
  "properties": {
    "addr:full":"9125 Boul Pie-Ix Montreal QC H1Z 3V8",
    "addr:housenumber":"9125",
    "addr:postcode":"h1z 3v8",
    "addr:street":"Boul Pie-Ix",
    "iso:country":"CA",
    "sg:address":"9125 Boul Pie-Ix",
    "sg:city":"Montreal",
    "sg:classifiers":[
        {
            "category":"Food & Beverages",
            "subcategory":"Groceries & Convenience Stores",
            "type":"Retail Goods"
        }
    ],
    "sg:phone":"+1 514 325 1331",
    "sg:postcode":"H1Z 3V8",
    "sg:province":"QC",
    "sg:tags":[
        "grocer"
    ],
    "wof:name":"Intermarche Pie Ix",
    "wof:placetype":"venue"
},
  "geometry": {"coordinates":[-73.621185,45.579868],"type":"Point"}
}