{
  "type": "Feature",
  "properties": {
    "addr:full":"2020 10 St NW Calgary AB T2M 3M2",
    "addr:housenumber":"2020",
    "addr:postcode":"t2m 3m2",
    "addr:street":"10 St Nw",
    "iso:country":"CA",
    "sg:address":"2020 10 St NW",
    "sg:city":"Calgary",
    "sg:classifiers":[
        {
            "category":"Building & Trades",
            "subcategory":"Construction",
            "type":"Services"
        }
    ],
    "sg:phone":"+1 403 282 7120",
    "sg:postcode":"T2M 3M2",
    "sg:province":"AB",
    "sg:tags":[
        "contractor"
    ],
    "wof:name":"Assured Developments Ltd",
    "wof:placetype":"venue"
},
  "geometry": {"coordinates":[-114.08474699999999,51.069881],"type":"Point"}
}