{
  "type": "Feature",
  "properties": {
    "addr:full":"RR 1 Box 9545 Lavigne ON P0H 1R0",
    "addr:housenumber":"box",
    "addr:postcode":"9545;p0h 1r0",
    "addr:street":"Rr 1",
    "iso:country":"CA",
    "sg:address":"RR 1 Box 9545",
    "sg:city":"Lavigne",
    "sg:classifiers":[
        {
            "category":"Building & Trades",
            "subcategory":"Construction",
            "type":"Services"
        }
    ],
    "sg:phone":"+1 705 594 2682",
    "sg:postcode":"P0H 1R0",
    "sg:province":"ON",
    "sg:tags":[
        "railing"
    ],
    "wof:name":"Advance Railings Systems",
    "wof:placetype":"venue"
},
  "geometry": {"coordinates":[-80.172462,46.318356],"type":"Point"}
}