{
  "type": "Feature",
  "properties": {
    "addr:full":"63 Saint Nicholas St Toronto ON M4Y 1W6",
    "addr:housenumber":"63",
    "addr:postcode":"m4y 1w6",
    "addr:street":"Saint Nicholas St",
    "iso:country":"CA",
    "sg:address":"63 Saint Nicholas St",
    "sg:city":"Toronto",
    "sg:classifiers":[
        {
            "category":"Personal",
            "subcategory":"Beauty Salon",
            "type":"Services"
        }
    ],
    "sg:phone":"+1 416 927 0844",
    "sg:postcode":"M4Y 1W6",
    "sg:province":"ON",
    "wof:name":"Bruno Malfara Hair",
    "wof:placetype":"venue"
},
  "geometry": {"coordinates":[-79.38645200000001,43.667538],"type":"Point"}
}