{
  "type": "Feature",
  "properties": {
    "iso:country":"CA",
    "sg:address":"6811 50 St NW",
    "sg:city":"Edmonton",
    "sg:classifiers":[
        {
            "category":"Retail",
            "subcategory":"Auto Repair",
            "type":"Services"
        }
    ],
    "sg:phone":"+1 780 466 4646",
    "sg:postcode":"T6B 3B7",
    "sg:province":"AB",
    "sg:tags":[
        "automobile",
        "parts",
        "supply"
    ],
    "wof:name":"Gear Centre",
    "wof:placetype":"venue"
},
  "geometry": {"coordinates":[-113.41798400899999,53.5052452087],"type":"Point"}
}