{
  "type": "Feature",
  "properties": {
    "addr:full":"115 Rue Saint-Viateur O Montreal QC H2T 2L2",
    "addr:housenumber":"115",
    "addr:postcode":"h2t 2l2",
    "addr:street":"Rue Saint-Viateur O",
    "iso:country":"CA",
    "sg:address":"115 Rue Saint-Viateur O",
    "sg:city":"Montreal",
    "sg:classifiers":[
        {
            "category":"Restaurant",
            "type":"Food & Drink"
        }
    ],
    "sg:phone":"+1 514 948 2161",
    "sg:postcode":"H2T 2L2",
    "sg:province":"QC",
    "sg:tags":[
        "delicatessen"
    ],
    "wof:name":"Euro-Deli Batory",
    "wof:placetype":"venue"
},
  "geometry": {"coordinates":[-73.5978469849,45.5272636414],"type":"Point"}
}