{
  "type": "Feature",
  "properties": {
    "addr:full":"1651 Boul Du Royaume O Chicoutimi QC G7H 5B1",
    "addr:housenumber":"1651",
    "addr:postcode":"g7h 5b1",
    "addr:street":"Boul Du Royaume O",
    "iso:country":"CA",
    "sg:address":"1651 Boul Du Royaume O",
    "sg:city":"Chicoutimi",
    "sg:classifiers":[
        {
            "category":"Manufacturing",
            "subcategory":"Building Materials",
            "type":"Manufacturing & Wholesale Goods"
        }
    ],
    "sg:phone":"+1 418 549 7731",
    "sg:postcode":"G7H 5B1",
    "sg:province":"QC",
    "sg:tags":[
        "truss"
    ],
    "wof:name":"Charpenterie Inc",
    "wof:placetype":"venue"
},
  "geometry": {"coordinates":[-71.1236419678,48.3912734985],"type":"Point"}
}