{
  "type": "Feature",
  "properties": {
    "addr:full":"Richmond BC V7E 2K2",
    "addr:postcode":"v7e 2k2",
    "iso:country":"CA",
    "sg:city":"Richmond",
    "sg:classifiers":[
        {
            "category":"Retail",
            "subcategory":"Veterinary Services",
            "type":"Services"
        }
    ],
    "sg:phone":"+1 604 274 9938",
    "sg:postcode":"V7E 2K2",
    "sg:province":"BC",
    "sg:tags":[
        "veterinarian"
    ],
    "wof:name":"Steveston Vet Hospital Ltd",
    "wof:placetype":"venue"
},
  "geometry": {"coordinates":[-123.18235799999999,49.133595],"type":"Point"}
}