{
  "type": "Feature",
  "properties": {
    "addr:full":"506 Memquisit Rd Monetville ON P0M 2K0",
    "addr:housenumber":"506",
    "addr:postcode":"p0m 2k0",
    "addr:street":"Memquisit Rd",
    "iso:country":"CA",
    "sg:address":"506 Memquisit Rd",
    "sg:city":"Monetville",
    "sg:classifiers":[
        {
            "category":"Travel",
            "subcategory":"Hotels & Motels",
            "type":"Entertainment"
        }
    ],
    "sg:phone":"+1 705 898 2355",
    "sg:postcode":"P0M 2K0",
    "sg:province":"ON",
    "sg:tags":[
        "resort"
    ],
    "wof:name":"Memquisit Lodge",
    "wof:placetype":"venue"
},
  "geometry": {"coordinates":[-80.358566,46.162197],"type":"Point"}
}