{
  "type": "Feature",
  "properties": {
    "addr:full":"2150 Prince of Wales Dr Regina SK S4V 3A6",
    "addr:housenumber":"2150",
    "addr:postcode":"s4v 3a6",
    "addr:street":"Prince Of Wales Dr",
    "iso:country":"CA",
    "sg:address":"2150 Prince of Wales Dr",
    "sg:city":"Regina",
    "sg:classifiers":[
        {
            "category":"Shopping",
            "subcategory":"Department Store",
            "type":"Retail Goods"
        }
    ],
    "sg:phone":"+1 306 780 3700",
    "sg:postcode":"S4V 3A6",
    "sg:province":"SK",
    "wof:name":"Wal-Mart",
    "wof:placetype":"venue"
},
  "geometry": {"coordinates":[-104.53262329099999,50.4441566467],"type":"Point"}
}