{
  "type": "Feature",
  "properties": {
    "addr:full":"75 Ann St London ON N6A 1R1",
    "addr:housenumber":"75",
    "addr:postcode":"n6a 1r1",
    "addr:street":"Ann St",
    "iso:country":"CA",
    "sg:address":"75 Ann St",
    "sg:city":"London",
    "sg:classifiers":[
        {
            "category":"Wholesale",
            "subcategory":"Sporting Goods",
            "type":"Manufacturing & Wholesale Goods"
        }
    ],
    "sg:phone":"+1 819 367 3030",
    "sg:postcode":"N6A 1R1",
    "sg:province":"ON",
    "wof:name":"Rawlings Canada Inc",
    "wof:placetype":"venue"
},
  "geometry": {"coordinates":[-81.257248,42.992386],"type":"Point"}
}