{
  "type": "Feature",
  "properties": {
    "addr:full":"6237 Mississauga Rd Mississauga ON L5N 1A4",
    "addr:housenumber":"6237",
    "addr:postcode":"l5n 1a4",
    "addr:street":"Mississauga Rd",
    "iso:country":"CA",
    "sg:address":"6237 Mississauga Rd",
    "sg:city":"Mississauga",
    "sg:classifiers":[
        {
            "category":"Retail",
            "subcategory":"Auto Repair",
            "type":"Services"
        }
    ],
    "sg:phone":"+1 905 286 1426",
    "sg:postcode":"L5N 1A4",
    "sg:province":"ON",
    "sg:tags":[
        "repairing",
        "automobile"
    ],
    "wof:name":"Tony's Repair",
    "wof:placetype":"venue"
},
  "geometry": {"coordinates":[-79.7284164429,43.5927467346],"type":"Point"}
}