{
  "type": "Feature",
  "properties": {
    "addr:full":"PO Box 160 Norway House MB R0B 1B0",
    "addr:housenumber":"po",
    "addr:postcode":"r0b 1b0",
    "addr:street":"Box 160",
    "iso:country":"CA",
    "sg:address":"PO Box 160",
    "sg:city":"Norway House",
    "sg:classifiers":[
        {
            "category":"Shopping",
            "subcategory":"Department Store",
            "type":"Retail Goods"
        }
    ],
    "sg:phone":"+1 204 359 6222",
    "sg:postcode":"R0B 1B0",
    "sg:province":"MB",
    "wof:name":"Northern-Rossville",
    "wof:placetype":"venue"
},
  "geometry": {"coordinates":[-97.76863098139999,53.9951553345],"type":"Point"}
}