{
  "type": "Feature",
  "properties": {
    "addr:full":"27 Redstone Path Etobicoke ON M9C 1Y7",
    "addr:housenumber":"27",
    "addr:postcode":"m9c 1y7",
    "addr:street":"Redstone Path",
    "iso:country":"CA",
    "sg:address":"27 Redstone Path",
    "sg:city":"Etobicoke",
    "sg:classifiers":[
        {
            "category":"Manufacturing",
            "subcategory":"Tools & Machinery",
            "type":"Manufacturing & Wholesale Goods"
        }
    ],
    "sg:phone":"+1 416 620 5255",
    "sg:postcode":"M9C 1Y7",
    "sg:province":"ON",
    "sg:tags":[
        "equipment",
        "system",
        "automation"
    ],
    "wof:name":"Jantek Home Control Systems",
    "wof:placetype":"venue"
},
  "geometry": {"coordinates":[-79.586945,43.641506],"type":"Point"}
}