{
  "type": "Feature",
  "properties": {
    "addr:full":"4055 Mcconnell Dr Burnaby BC V5A 3A7",
    "addr:housenumber":"4055",
    "addr:postcode":"v5a 3a7",
    "addr:street":"Mcconnell Dr",
    "iso:country":"CA",
    "sg:address":"4055 Mcconnell Dr",
    "sg:city":"Burnaby",
    "sg:classifiers":[
        {
            "category":"Shopping",
            "subcategory":"Gifts & Souvenirs",
            "type":"Retail Goods"
        }
    ],
    "sg:phone":"+1 604 299 7511",
    "sg:postcode":"V5A 3A7",
    "sg:province":"BC",
    "sg:tags":[
        "carnival",
        "supply"
    ],
    "wof:name":"Specialty Toys Direct Inc",
    "wof:placetype":"venue"
},
  "geometry": {"coordinates":[-122.937607,49.247459],"type":"Point"}
}