{
  "type": "Feature",
  "properties": {
    "addr:full":"6243 Quinpool Rd Halifax NS B3L 1A4",
    "addr:housenumber":"6243",
    "addr:postcode":"b3l 1a4",
    "addr:street":"Quinpool Rd",
    "iso:country":"CA",
    "sg:address":"6243 Quinpool Rd",
    "sg:city":"Halifax",
    "sg:classifiers":[
        {
            "category":"Professional",
            "subcategory":"Business Services",
            "type":"Services"
        }
    ],
    "sg:phone":"+1 902 423 4915",
    "sg:postcode":"B3L 1A4",
    "sg:province":"NS",
    "sg:tags":[
        "interior",
        "consultant",
        "design",
        "decorator",
        "paint"
    ],
    "wof:name":"Acadia & Quigley's Decorating",
    "wof:placetype":"venue"
},
  "geometry": {"coordinates":[-63.5970840454,44.6455993652],"type":"Point"}
}