{
  "type": "Feature",
  "properties": {
    "addr:full":"North York ON M3H 3R8",
    "addr:postcode":"m3h 3r8",
    "iso:country":"CA",
    "sg:city":"North York",
    "sg:classifiers":[
        {
            "category":"Manufacturing",
            "subcategory":"Printing",
            "type":"Manufacturing & Wholesale Goods"
        }
    ],
    "sg:phone":"+1 416 398 5011",
    "sg:postcode":"M3H 3R8",
    "sg:province":"ON",
    "sg:tags":[
        "newspaper"
    ],
    "wof:name":"Canadian Courier Russian",
    "wof:placetype":"venue"
},
  "geometry": {"coordinates":[-79.4387054443,43.7556686401],"type":"Point"}
}