{
  "type": "Feature",
  "properties": {
    "addr:full":"Bracebridge ON P1L 2C1",
    "addr:postcode":"p1l 2c1",
    "iso:country":"CA",
    "sg:city":"Bracebridge",
    "sg:classifiers":[
        {
            "category":"Health Services",
            "subcategory":"Clinic",
            "type":"Services"
        }
    ],
    "sg:phone":"+1 705 645 6238",
    "sg:postcode":"P1L 2C1",
    "sg:province":"ON",
    "sg:tags":[
        "home"
    ],
    "wof:name":"Community Care Access Ctr",
    "wof:placetype":"venue"
},
  "geometry": {"coordinates":[-79.315819,45.046165],"type":"Point"}
}