{
  "type": "Feature",
  "properties": {
    "addr:full":"68 Scollard St Toronto ON M5R 1G2",
    "addr:housenumber":"68",
    "addr:postcode":"m5r 1g2",
    "addr:street":"Scollard St",
    "iso:country":"CA",
    "sg:address":"68 Scollard St",
    "sg:city":"Toronto",
    "sg:classifiers":[
        {
            "category":"Professional",
            "subcategory":"Management & Consulting",
            "type":"Services"
        }
    ],
    "sg:phone":"+1 416 968 3845",
    "sg:postcode":"M5R 1G2",
    "sg:province":"ON",
    "sg:tags":[
        "communications",
        "consultant"
    ],
    "wof:name":"Lewis Carroll Communications",
    "wof:placetype":"venue"
},
  "geometry": {"coordinates":[-79.391098,43.672138],"type":"Point"}
}