{
  "type": "Feature",
  "properties": {
    "addr:full":"8404 Hwy 7 Sherbrooke NS B0J 3C0",
    "addr:housenumber":"8404",
    "addr:postcode":"b0j 3c0",
    "addr:street":"Hwy 7",
    "iso:country":"CA",
    "sg:address":"8404 Hwy 7",
    "sg:city":"Sherbrooke",
    "sg:classifiers":[
        {
            "category":"Museum",
            "type":"Entertainment"
        }
    ],
    "sg:phone":"+1 902 522 2099",
    "sg:postcode":"B0J 3C0",
    "sg:province":"NS",
    "wof:name":"Saint Mary's River Assn",
    "wof:placetype":"venue"
},
  "geometry": {"coordinates":[-61.97617,45.146431],"type":"Point"}
}