{
  "type": "Feature",
  "properties": {
    "addr:full":"Calgary AB T2E 6T5",
    "addr:postcode":"t2e 6t5",
    "iso:country":"CA",
    "sg:city":"Calgary",
    "sg:classifiers":[
        {
            "category":"Manufacturing",
            "subcategory":"Apparel",
            "type":"Manufacturing & Wholesale Goods"
        }
    ],
    "sg:phone":"+1 403 250 9395",
    "sg:postcode":"T2E 6T5",
    "sg:province":"AB",
    "wof:name":"Bingo Garment Mfg Ltd",
    "wof:placetype":"venue"
},
  "geometry": {"coordinates":[-114.008850098,51.08751297],"type":"Point"}
}