{
  "type": "Feature",
  "properties": {
    "addr:full":"PO Box 127 Byemoor AB T0J 0L0",
    "addr:housenumber":"po",
    "addr:postcode":"t0j 0l0",
    "addr:street":"Box 127 Byemoor",
    "iso:country":"CA",
    "sg:address":"PO Box 127",
    "sg:city":"Byemoor",
    "sg:classifiers":[
        {
            "category":"Education",
            "subcategory":"School",
            "type":"Public Place"
        }
    ],
    "sg:phone":"+1 403 579 2293",
    "sg:postcode":"T0J 0L0",
    "sg:province":"AB",
    "wof:name":"Byemoor Colony School",
    "wof:placetype":"venue"
},
  "geometry": {"coordinates":[-112.28825399999999,51.980751],"type":"Point"}
}