{
  "type": "Feature",
  "properties": {
    "addr:full":"367 Michener Rd Guelph ON N1K 1E8",
    "addr:housenumber":"367",
    "addr:postcode":"n1k 1e8",
    "addr:street":"Michener Rd",
    "iso:country":"CA",
    "sg:address":"367 Michener Rd",
    "sg:city":"Guelph",
    "sg:classifiers":[
        {
            "category":"Manufacturing",
            "subcategory":"Tools & Machinery",
            "type":"Manufacturing & Wholesale Goods"
        }
    ],
    "sg:phone":"+1 519 836 4600",
    "sg:postcode":"N1K 1E8",
    "sg:province":"ON",
    "sg:tags":[
        "equipment",
        "automation",
        "system",
        "hydraulic",
        "supply"
    ],
    "wof:name":"Rubberline Products Ltd",
    "wof:placetype":"venue"
},
  "geometry": {"coordinates":[-80.3164367676,43.5322608948],"type":"Point"}
}