{
  "type": "Feature",
  "properties": {
    "addr:full":"80 Travail Rd # 4 Markham ON L3S 3H9",
    "addr:housenumber":"80",
    "addr:postcode":"l3s 3h9",
    "addr:street":"Travail Rd # 4",
    "iso:country":"CA",
    "sg:address":"80 Travail Rd # 4",
    "sg:city":"Markham",
    "sg:classifiers":[
        {
            "category":"Home & Garden",
            "subcategory":"Garden Supply",
            "type":"Retail Goods"
        }
    ],
    "sg:phone":"+1 905 201 1083",
    "sg:postcode":"L3S 3H9",
    "sg:province":"ON",
    "sg:tags":[
        "sprinkler"
    ],
    "wof:name":"Green Grass Lawn Sprinklers",
    "wof:placetype":"venue"
},
  "geometry": {"coordinates":[-79.26587677000001,43.8549766541],"type":"Point"}
}