{
  "type": "Feature",
  "properties": {
    "addr:full":"PO Box 216 Yarker ON K0K 3N0",
    "addr:housenumber":"po",
    "addr:postcode":"k0k 3n0",
    "addr:street":"Box 216 Yarker",
    "iso:country":"CA",
    "sg:address":"PO Box 216",
    "sg:city":"Yarker",
    "sg:classifiers":[
        {
            "category":"Building & Trades",
            "subcategory":"Construction",
            "type":"Services"
        }
    ],
    "sg:phone":"+1 613 377 1640",
    "sg:postcode":"K0K 3N0",
    "sg:province":"ON",
    "sg:tags":[
        "demolition",
        "contractor"
    ],
    "wof:name":"Westendorp Demolition",
    "wof:placetype":"venue"
},
  "geometry": {"coordinates":[-76.7711029053,44.3717460632],"type":"Point"}
}