{
  "type": "Feature",
  "properties": {
    "addr:full":"1170 St James St Winnipeg MB R3H 0K7",
    "addr:housenumber":"1170",
    "addr:postcode":"r3h 0k7",
    "addr:street":"St James St",
    "iso:country":"CA",
    "sg:address":"1170 St James St",
    "sg:city":"Winnipeg",
    "sg:classifiers":[
        {
            "category":"Home & Garden",
            "subcategory":"Furniture",
            "type":"Retail Goods"
        }
    ],
    "sg:phone":"+1 204 982 8600",
    "sg:postcode":"R3H 0K7",
    "sg:province":"MB",
    "wof:name":"Nolan's Home Furnishings",
    "wof:placetype":"venue"
},
  "geometry": {"coordinates":[-97.20040893549999,49.899230957],"type":"Point"}
}