{
  "type": "Feature",
  "properties": {
    "addr:full":"2102 11th Ave # 56 Regina SK S4P 3Y6",
    "addr:housenumber":"2102;56",
    "addr:postcode":"s4p 3y6",
    "addr:street":"11Th Ave #",
    "iso:country":"CA",
    "sg:address":"2102 11th Ave # 56",
    "sg:city":"Regina",
    "sg:classifiers":[
        {
            "category":"Wholesale",
            "subcategory":"Non-durable Goods",
            "type":"Manufacturing & Wholesale Goods"
        }
    ],
    "sg:phone":"+1 306 569 5824",
    "sg:postcode":"S4P 3Y6",
    "sg:province":"SK",
    "sg:tags":[
        "leather"
    ],
    "wof:name":"Danier Leather",
    "wof:placetype":"venue"
},
  "geometry": {"coordinates":[-104.610992,50.450562],"type":"Point"}
}