{
  "type": "Feature",
  "properties": {
    "addr:full":"33 Rue Principale Montpellier QC J0V 1M0",
    "addr:housenumber":"33",
    "addr:postcode":"j0v 1m0",
    "addr:street":"Rue Principale",
    "iso:country":"CA",
    "sg:address":"33 Rue Principale",
    "sg:city":"Montpellier",
    "sg:classifiers":[
        {
            "category":"Food & Beverages",
            "subcategory":"Groceries & Convenience Stores",
            "type":"Retail Goods"
        }
    ],
    "sg:phone":"+1 819 428 3554",
    "sg:postcode":"J0V 1M0",
    "sg:province":"QC",
    "sg:tags":[
        "grocer"
    ],
    "wof:name":"Marche Faubert Inc",
    "wof:placetype":"venue"
},
  "geometry": {"coordinates":[-75.1628112793,45.8558158875],"type":"Point"}
}