{
  "type": "Feature",
  "properties": {
    "addr:full":"682 Montee Douglas Rte 219 Napierville QC J0J 1L0",
    "addr:housenumber":"682",
    "addr:postcode":"j0j 1l0",
    "addr:street":"Montee Douglas Rte 219",
    "iso:country":"CA",
    "sg:address":"682 Montee Douglas Rte 219",
    "sg:city":"Napierville",
    "sg:classifiers":[
        {
            "category":"Wholesale",
            "subcategory":"Machinery & Supplies",
            "type":"Manufacturing & Wholesale Goods"
        }
    ],
    "sg:phone":"+1 450 245 3565",
    "sg:postcode":"J0J 1L0",
    "sg:province":"QC",
    "sg:tags":[
        "farm",
        "equipment"
    ],
    "wof:name":"Claude Joyal Inc",
    "wof:placetype":"venue"
},
  "geometry": {"coordinates":[-73.40520477290001,45.186756134],"type":"Point"}
}