{
  "type": "Feature",
  "properties": {
    "addr:full":"1599 Bayview Ave East York ON M4G 3B5",
    "addr:housenumber":"1599",
    "addr:postcode":"m4g 3b5",
    "addr:street":"Bayview Ave",
    "iso:country":"CA",
    "sg:address":"1599 Bayview Ave",
    "sg:city":"East York",
    "sg:classifiers":[
        {
            "category":"Home & Garden",
            "subcategory":"Furniture",
            "type":"Retail Goods"
        }
    ],
    "sg:phone":"+1 416 484 1203",
    "sg:postcode":"M4G 3B5",
    "sg:province":"ON",
    "wof:name":"Early Canadian Furniture",
    "wof:placetype":"venue"
},
  "geometry": {"coordinates":[-79.37513,43.706184],"type":"Point"}
}