{
  "type": "Feature",
  "properties": {
    "addr:full":"33221 Glasgow Ave Mission BC V2V 2X2",
    "addr:housenumber":"33221",
    "addr:postcode":"v2v 2x2",
    "addr:street":"Glasgow Ave",
    "iso:country":"CA",
    "sg:address":"33221 Glasgow Ave",
    "sg:city":"Mission",
    "sg:classifiers":[
        {
            "category":"Home & Garden",
            "subcategory":"Building Materials",
            "type":"Retail Goods"
        }
    ],
    "sg:phone":"+1 604 826 3637",
    "sg:postcode":"V2V 2X2",
    "sg:province":"BC",
    "sg:tags":[
        "glass",
        "window",
        "plate"
    ],
    "wof:name":"Adams Glass Ltd",
    "wof:placetype":"venue"
},
  "geometry": {"coordinates":[-122.30435199999999,49.13121],"type":"Point"}
}