{
  "type": "Feature",
  "properties": {
    "addr:full":"299 Rue Corcoran Saint-Alphonse-Rodriguez QC J0K 1W0",
    "addr:housenumber":"299",
    "addr:postcode":"j0k 1w0",
    "addr:street":"Rue Corcoran",
    "iso:country":"CA",
    "sg:address":"299 Rue Corcoran",
    "sg:city":"Saint-Alphonse-Rodriguez",
    "sg:classifiers":[
        {
            "category":"Freight",
            "type":"Transportation"
        }
    ],
    "sg:phone":"+1 450 883 6005",
    "sg:postcode":"J0K 1W0",
    "sg:province":"QC",
    "sg:tags":[
        "trucking"
    ],
    "wof:name":"Transport Marcel Perreault",
    "wof:placetype":"venue"
},
  "geometry": {"coordinates":[-73.669983,46.141956],"type":"Point"}
}