{
  "type": "Feature",
  "properties": {
    "iso:country":"CA",
    "sg:city":"North Vancouver",
    "sg:classifiers":[
        {
            "category":"Manufacturing",
            "subcategory":"Lumber",
            "type":"Manufacturing & Wholesale Goods"
        }
    ],
    "sg:phone":"+1 604 216 7766",
    "sg:postcode":"V7P 1B7",
    "sg:province":"BC",
    "sg:tags":[
        "forester"
    ],
    "wof:name":"Zanzibar Holdings Ltd",
    "wof:placetype":"venue"
},
  "geometry": {"coordinates":[-123.11862182599999,49.3175125122],"type":"Point"}
}