{
  "type": "Feature",
  "properties": {
    "addr:full":"2760 Av Barry Brossard QC J4Z 1T6",
    "addr:housenumber":"2760",
    "addr:postcode":"j4z 1t6",
    "addr:street":"Av Barry",
    "iso:country":"CA",
    "sg:address":"2760 Av Barry",
    "sg:city":"Brossard",
    "sg:classifiers":[
        {
            "category":"Social Services",
            "subcategory":"Child Care",
            "type":"Services"
        }
    ],
    "sg:phone":"+1 450 678 4990",
    "sg:postcode":"J4Z 1T6",
    "sg:province":"QC",
    "wof:name":"Cpe LA Bergerie Inc",
    "wof:placetype":"venue"
},
  "geometry": {"coordinates":[-73.45573400000001,45.469254],"type":"Point"}
}