{
  "type": "Feature",
  "properties": {
    "addr:full":"Kingston ON K7M 9B8",
    "addr:postcode":"k7m 9b8",
    "iso:country":"CA",
    "sg:city":"Kingston",
    "sg:classifiers":[
        {
            "category":"Home & Garden",
            "subcategory":"Home Furnishings",
            "type":"Retail Goods"
        }
    ],
    "sg:phone":"+1 613 384 3380",
    "sg:postcode":"K7M 9B8",
    "sg:province":"ON",
    "sg:tags":[
        "shop",
        "made",
        "fabric",
        "drapery"
    ],
    "wof:name":"Bouclair Inc",
    "wof:placetype":"venue"
},
  "geometry": {"coordinates":[-76.56764200000001,44.242989],"type":"Point"}
}