{
  "type": "Feature",
  "properties": {
    "addr:full":"171 Mill St Smithville ON L0R 2A0",
    "addr:housenumber":"171",
    "addr:postcode":"l0r 2a0",
    "addr:street":"Mill St",
    "iso:country":"CA",
    "sg:address":"171 Mill St",
    "sg:city":"Smithville",
    "sg:classifiers":[
        {
            "category":"Social Services",
            "type":"Services"
        }
    ],
    "sg:phone":"+1 905 957 2274",
    "sg:postcode":"L0R 2A0",
    "sg:province":"ON",
    "sg:tags":[
        "housing",
        "assistance"
    ],
    "wof:name":"Legion Villa",
    "wof:placetype":"venue"
},
  "geometry": {"coordinates":[-79.5442276001,43.0961074829],"type":"Point"}
}