{
  "type": "Feature",
  "properties": {
    "iso:country":"CA",
    "sg:city":"Mont-Saint-Hilaire",
    "sg:classifiers":[
        {
            "category":"Restaurant",
            "type":"Food & Drink"
        }
    ],
    "sg:phone":"+1 450 464 4447",
    "sg:postcode":"J3H 3N7",
    "sg:province":"QC",
    "wof:name":"Restaurant Jardin Du Paradis",
    "wof:placetype":"venue"
},
  "geometry": {"coordinates":[-73.188949585,45.5621871948],"type":"Point"}
}