{
  "type": "Feature",
  "properties": {
    "iso:country":"CA",
    "sg:address":"24 Harlech Crt",
    "sg:city":"Thornhill",
    "sg:classifiers":[
        {
            "category":"Retail",
            "subcategory":"Auto Repair",
            "type":"Services"
        }
    ],
    "sg:phone":"+1 905 889 5729",
    "sg:postcode":"L3T 6L5",
    "sg:province":"ON",
    "sg:tags":[
        "body",
        "automobile",
        "painting"
    ],
    "wof:name":"Active Collision Ctr",
    "wof:placetype":"venue"
},
  "geometry": {"coordinates":[-79.396896,43.825123],"type":"Point"}
}