{
  "type": "Feature",
  "properties": {
    "addr:full":"211 Rue Sainte-Anne E Alma QC G8B 3Z9",
    "addr:housenumber":"211",
    "addr:postcode":"g8b 3z9",
    "addr:street":"Rue Sainte-Anne E",
    "iso:country":"CA",
    "sg:address":"211 Rue Sainte-Anne E",
    "sg:city":"Alma",
    "sg:classifiers":[
        {
            "category":"Insurance",
            "subcategory":"Insurance Agent",
            "type":"Services"
        }
    ],
    "sg:phone":"+1 418 668 8008",
    "sg:postcode":"G8B 3Z9",
    "sg:province":"QC",
    "wof:name":"Assurances Dm",
    "wof:placetype":"venue"
},
  "geometry": {"coordinates":[-71.635704,48.550411],"type":"Point"}
}