{
  "type": "Feature",
  "properties": {
    "addr:full":"Toronto ON M5S 1R1",
    "addr:postcode":"m5s 1r1",
    "iso:country":"CA",
    "sg:city":"Toronto",
    "sg:classifiers":[
        {
            "category":"Restaurant",
            "type":"Food & Drink"
        }
    ],
    "sg:phone":"+1 416 923 3323",
    "sg:postcode":"M5S 1R1",
    "sg:province":"ON",
    "wof:name":"Dynasty",
    "wof:placetype":"venue"
},
  "geometry": {"coordinates":[-79.39203643800001,43.6690063477],"type":"Point"}
}