{
  "type": "Feature",
  "properties": {
    "addr:full":"108 Miller Lake Shore Rd Miller Lake ON N0H 1Z0",
    "addr:housenumber":"108",
    "addr:postcode":"n0h 1z0",
    "addr:street":"Miller Lake Shore Rd",
    "iso:country":"CA",
    "sg:address":"108 Miller Lake Shore Rd",
    "sg:city":"Miller Lake",
    "sg:classifiers":[
        {
            "category":"Travel",
            "subcategory":"Hotels & Motels",
            "type":"Entertainment"
        }
    ],
    "sg:phone":"+1 519 795 7750",
    "sg:postcode":"N0H 1Z0",
    "sg:province":"ON",
    "sg:tags":[
        "cottage",
        "cabin"
    ],
    "wof:name":"Miller's Family Camp",
    "wof:placetype":"venue"
},
  "geometry": {"coordinates":[-81.443108,45.10257],"type":"Point"}
}