{
  "type": "Feature",
  "properties": {
    "addr:full":"142 Truro Heights Rd Truro NS B2N 5A9",
    "addr:housenumber":"142",
    "addr:postcode":"b2n 5a9",
    "addr:street":"Truro Heights Rd",
    "iso:country":"CA",
    "sg:address":"142 Truro Heights Rd",
    "sg:city":"Truro",
    "sg:classifiers":[
        {
            "category":"Wholesale",
            "subcategory":"Machinery & Supplies",
            "type":"Manufacturing & Wholesale Goods"
        }
    ],
    "sg:phone":"+1 902 895 5393",
    "sg:postcode":"B2N 5A9",
    "sg:province":"NS",
    "sg:tags":[
        "bearing"
    ],
    "wof:name":"Canadian Bearings",
    "wof:placetype":"venue"
},
  "geometry": {"coordinates":[-63.3048095703,45.3391990662],"type":"Point"}
}