{
  "type": "Feature",
  "properties": {
    "addr:full":"Scarborough ON M1X 1A6",
    "addr:postcode":"m1x 1a6",
    "iso:country":"CA",
    "sg:city":"Scarborough",
    "sg:classifiers":[
        {
            "category":"Professional",
            "subcategory":"Computer Services",
            "type":"Services"
        }
    ],
    "sg:phone":"+1 416 293 8263",
    "sg:postcode":"M1X 1A6",
    "sg:province":"ON",
    "sg:tags":[
        "electronics"
    ],
    "wof:name":"Microsym Computers Inc",
    "wof:placetype":"venue"
},
  "geometry": {"coordinates":[-79.232635,43.818695],"type":"Point"}
}