{
  "type": "Feature",
  "properties": {
    "addr:full":"Hwy 35 N Lindsay ON K9V 4R1",
    "addr:postcode":"k9v 4r1",
    "addr:street":"Hwy 35 N",
    "iso:country":"CA",
    "sg:address":"Hwy 35 N",
    "sg:city":"Lindsay",
    "sg:classifiers":[
        {
            "category":"Autos & Motor Vehicles",
            "subcategory":"Fuel & Gas Station",
            "type":"Retail Goods"
        }
    ],
    "sg:phone":"+1 705 328 3027",
    "sg:postcode":"K9V 4R1",
    "sg:province":"ON",
    "sg:tags":[
        "oil"
    ],
    "wof:name":"Olco",
    "wof:placetype":"venue"
},
  "geometry": {"coordinates":[-78.79335,44.401161],"type":"Point"}
}