{
  "type": "Feature",
  "properties": {
    "iso:country":"CA",
    "sg:city":"Sydney",
    "sg:classifiers":[
        {
            "category":"Shopping",
            "subcategory":"Gifts & Souvenirs",
            "type":"Retail Goods"
        }
    ],
    "sg:phone":"+1 902 539 5688",
    "sg:postcode":"B1P 5K6",
    "sg:province":"NS",
    "sg:tags":[
        "shop",
        "glass"
    ],
    "wof:name":"Painted Carousel Design",
    "wof:placetype":"venue"
},
  "geometry": {"coordinates":[-60.18642,46.139217],"type":"Point"}
}