{
  "type": "Feature",
  "properties": {
    "addr:full":"4628 99 St NW Edmonton AB T6E 5H5",
    "addr:housenumber":"4628",
    "addr:postcode":"t6e 5h5",
    "addr:street":"99 St Nw",
    "iso:country":"CA",
    "sg:address":"4628 99 St NW",
    "sg:city":"Edmonton",
    "sg:classifiers":[
        {
            "category":"Shopping",
            "subcategory":"Clothing, Apparel, & Fashions",
            "type":"Retail Goods"
        }
    ],
    "sg:phone":"+1 780 434 9425",
    "sg:postcode":"T6E 5H5",
    "sg:province":"AB",
    "wof:name":"Elegance Plus Boutique",
    "wof:placetype":"venue"
},
  "geometry": {"coordinates":[-113.486435,53.484142],"type":"Point"}
}