{
  "type": "Feature",
  "properties": {
    "addr:full":"Toronto ON M5H 3T9",
    "addr:postcode":"m5h 3t9",
    "iso:country":"CA",
    "sg:city":"Toronto",
    "sg:classifiers":[
        {
            "category":"Retail",
            "subcategory":"Laundry & Dry Cleaning",
            "type":"Services"
        }
    ],
    "sg:phone":"+1 416 362 0403",
    "sg:postcode":"M5H 3T9",
    "sg:province":"ON",
    "sg:tags":[
        "cleaners"
    ],
    "wof:name":"Clover Leaf Cleaners & Shoe",
    "wof:placetype":"venue"
},
  "geometry": {"coordinates":[-79.383369,43.647835],"type":"Point"}
}