{
  "type": "Feature",
  "properties": {
    "addr:full":"1425 Ellice Ave Winnipeg MB R3G 0G3",
    "addr:housenumber":"1425",
    "addr:postcode":"r3g 0g3",
    "addr:street":"Ellice Ave",
    "iso:country":"CA",
    "sg:address":"1425 Ellice Ave",
    "sg:city":"Winnipeg",
    "sg:classifiers":[
        {
            "category":"Home & Garden",
            "subcategory":"Furniture",
            "type":"Retail Goods"
        }
    ],
    "sg:phone":"+1 204 783 8500",
    "sg:postcode":"R3G 0G3",
    "sg:province":"MB",
    "wof:name":"LA-Z-Boy Furniture Galleries",
    "wof:placetype":"venue"
},
  "geometry": {"coordinates":[-97.1983795166,49.8942947388],"type":"Point"}
}