{
  "type": "Feature",
  "properties": {
    "iso:country":"CA",
    "sg:address":"47 Harrington Crt",
    "sg:city":"Kanata",
    "sg:classifiers":[
        {
            "category":"Manufacturing",
            "subcategory":"Printing",
            "type":"Manufacturing & Wholesale Goods"
        }
    ],
    "sg:phone":"+1 613 599 4190",
    "sg:postcode":"K2K 2S6",
    "sg:province":"ON",
    "sg:tags":[
        "publisher"
    ],
    "wof:name":"Above & Beyond Ltd",
    "wof:placetype":"venue"
},
  "geometry": {"coordinates":[-75.921349,45.323929],"type":"Point"}
}