{
  "type": "Feature",
  "properties": {
    "addr:full":"Canso NS B0H 1H0",
    "addr:postcode":"b0h 1h0",
    "iso:country":"CA",
    "sg:city":"Canso",
    "sg:classifiers":[
        {
            "category":"Government",
            "subcategory":"Office",
            "type":"Public Place"
        }
    ],
    "sg:phone":"+1 902 366 2004",
    "sg:postcode":"B0H 1H0",
    "sg:province":"NS",
    "wof:name":"Canada Conservation & Protctn",
    "wof:placetype":"venue"
},
  "geometry": {"coordinates":[-60.9964866638,45.3361129761],"type":"Point"}
}