{
  "type": "Feature",
  "properties": {
    "iso:country":"CA",
    "sg:address":"House 83E",
    "sg:city":"Cross Lake",
    "sg:classifiers":[
        {
            "category":"Building & Trades",
            "subcategory":"Electrical",
            "type":"Services"
        }
    ],
    "sg:phone":"+1 204 676 2239",
    "sg:postcode":"R0B 0J0",
    "sg:province":"MB",
    "sg:tags":[
        "electric",
        "contractor"
    ],
    "wof:name":"Rjr Electric",
    "wof:placetype":"venue"
},
  "geometry": {"coordinates":[-97.745667,54.622204],"type":"Point"}
}