{
  "type": "Feature",
  "properties": {
    "addr:full":"10934 66 Ave NW Edmonton AB T6H 1Y2",
    "addr:housenumber":"10934",
    "addr:postcode":"t6h 1y2",
    "addr:street":"66 Ave Nw",
    "iso:country":"CA",
    "sg:address":"10934 66 Ave NW",
    "sg:city":"Edmonton",
    "sg:classifiers":[
        {
            "category":"Professional",
            "subcategory":"Management & Consulting",
            "type":"Services"
        }
    ],
    "sg:phone":"+1 780 437 6749",
    "sg:postcode":"T6H 1Y2",
    "sg:province":"AB",
    "sg:tags":[
        "consultant",
        "business"
    ],
    "wof:name":"J A Smith Research & Consultng",
    "wof:placetype":"venue"
},
  "geometry": {"coordinates":[-113.513084412,53.5031776428],"type":"Point"}
}