{
  "type": "Feature",
  "properties": {
    "addr:full":"1010 Boul Monseigneur-DE Laval Baie-Saint-Paul QC G3Z 2W2",
    "addr:housenumber":"1010",
    "addr:postcode":"g3z 2w2",
    "addr:street":"Boul Monseigneur-De Laval",
    "iso:country":"CA",
    "sg:address":"1010 Boul Monseigneur-DE Laval",
    "sg:city":"Baie-Saint-Paul",
    "sg:classifiers":[
        {
            "category":"Restaurant",
            "type":"Food & Drink"
        }
    ],
    "sg:phone":"+1 418 435 2330",
    "sg:postcode":"G3Z 2W2",
    "sg:province":"QC",
    "wof:name":"Mc Donald's",
    "wof:placetype":"venue"
},
  "geometry": {"coordinates":[-70.515305,47.444057],"type":"Point"}
}