{
  "type": "Feature",
  "properties": {
    "addr:full":"2175 Rue Gagnon Saint-Hubert QC J3Y 5K2",
    "addr:housenumber":"2175",
    "addr:postcode":"j3y 5k2",
    "addr:street":"Rue Gagnon",
    "iso:country":"CA",
    "sg:address":"2175 Rue Gagnon",
    "sg:city":"Saint-Hubert",
    "sg:classifiers":[
        {
            "category":"Building & Trades",
            "subcategory":"Cleaning & Sanitation",
            "type":"Services"
        }
    ],
    "sg:phone":"+1 450 447 4747",
    "sg:postcode":"J3Y 5K2",
    "sg:province":"QC",
    "sg:tags":[
        "janitor"
    ],
    "wof:name":"Aed Maintenance Enr",
    "wof:placetype":"venue"
},
  "geometry": {"coordinates":[-73.354797,45.471497],"type":"Point"}
}