{
  "type": "Feature",
  "properties": {
    "addr:full":"3 Grey St Winnipeg MB R2L 1V2",
    "addr:housenumber":"3",
    "addr:postcode":"r2l 1v2",
    "addr:street":"Grey St",
    "iso:country":"CA",
    "sg:address":"3 Grey St",
    "sg:city":"Winnipeg",
    "sg:classifiers":[
        {
            "category":"Government",
            "subcategory":"Office",
            "type":"Public Place"
        }
    ],
    "sg:phone":"+1 204 986 3222",
    "sg:postcode":"R2L 1V2",
    "sg:province":"MB",
    "sg:tags":[
        "village"
    ],
    "wof:name":"Winnipeg Insect Control",
    "wof:placetype":"venue"
},
  "geometry": {"coordinates":[-97.0962219238,49.9016036987],"type":"Point"}
}