{
  "type": "Feature",
  "properties": {
    "addr:full":"274 Kingston Rd E Ajax ON L1Z 1G1",
    "addr:housenumber":"274",
    "addr:postcode":"l1z 1g1",
    "addr:street":"Kingston Rd E",
    "iso:country":"CA",
    "sg:address":"274 Kingston Rd E",
    "sg:city":"Ajax",
    "sg:classifiers":[
        {
            "category":"Restaurant",
            "type":"Food & Drink"
        }
    ],
    "sg:phone":"+1 905 426 9947",
    "sg:postcode":"L1Z 1G1",
    "sg:province":"ON",
    "sg:tags":[
        "building",
        "contractor"
    ],
    "wof:name":"Raf Holdings Ltd",
    "wof:placetype":"venue"
},
  "geometry": {"coordinates":[-79.011681,43.864571],"type":"Point"}
}