{
  "type": "Feature",
  "properties": {
    "iso:country":"CA",
    "sg:city":"Montreal",
    "sg:classifiers":[
        {
            "category":"Organizations",
            "subcategory":"Professional Association",
            "type":"Services"
        }
    ],
    "sg:phone":"+1 514 524 0607",
    "sg:postcode":"H2K 1C3",
    "sg:province":"QC",
    "wof:name":"Center D'Assistance Et D'Accom",
    "wof:placetype":"venue"
},
  "geometry": {"coordinates":[-73.5627441406,45.5310668945],"type":"Point"}
}