{
  "type": "Feature",
  "properties": {
    "iso:country":"CA",
    "sg:address":"340 Pitt St",
    "sg:city":"Cornwall",
    "sg:classifiers":[
        {
            "category":"Government",
            "subcategory":"Office",
            "type":"Public Place"
        }
    ],
    "sg:phone":"+1 613 932 6252",
    "sg:postcode":"K6J 3P9",
    "sg:province":"ON",
    "sg:tags":[
        "village"
    ],
    "wof:name":"Cornwall Permis DE Constr",
    "wof:placetype":"venue"
},
  "geometry": {"coordinates":[-74.7300949097,45.0203361511],"type":"Point"}
}