{
  "type": "Feature",
  "properties": {
    "addr:full":"3469 Innes Rd Orleans ON K1C 1T1",
    "addr:housenumber":"3469",
    "addr:postcode":"k1c 1t1",
    "addr:street":"Innes Rd",
    "iso:country":"CA",
    "sg:address":"3469 Innes Rd",
    "sg:city":"Orleans",
    "sg:classifiers":[
        {
            "category":"Shopping",
            "subcategory":"Florist",
            "type":"Retail Goods"
        }
    ],
    "sg:phone":"+1 613 841 8552",
    "sg:postcode":"K1C 1T1",
    "sg:province":"ON",
    "wof:name":"Sweet Rose Ltd",
    "wof:placetype":"venue"
},
  "geometry": {"coordinates":[-75.5258407593,45.44739151],"type":"Point"}
}