{
  "type": "Feature",
  "properties": {
    "iso:country":"CA",
    "sg:address":"95 Harrison St",
    "sg:city":"Plaster Rock",
    "sg:classifiers":[
        {
            "category":"Retail",
            "subcategory":"Repair Shop",
            "type":"Services"
        }
    ],
    "sg:phone":"+1 506 356 2323",
    "sg:postcode":"E7G 1T2",
    "sg:province":"NB",
    "sg:tags":[
        "appliance"
    ],
    "wof:name":"Hal's Appliance Repairs",
    "wof:placetype":"venue"
},
  "geometry": {"coordinates":[-67.3897323608,46.8987808228],"type":"Point"}
}