{
  "type": "Feature",
  "properties": {
    "addr:full":"2854 Rue Legare Sainte-Foy QC G1V 2H2",
    "addr:housenumber":"2854",
    "addr:postcode":"g1v 2h2",
    "addr:street":"Rue Legare",
    "iso:country":"CA",
    "sg:address":"2854 Rue Legare",
    "sg:city":"Sainte-Foy",
    "sg:classifiers":[
        {
            "category":"Health Services",
            "subcategory":"Health Practitioner",
            "type":"Services"
        }
    ],
    "sg:phone":"+1 418 624 0447",
    "sg:postcode":"G1V 2H2",
    "sg:province":"QC",
    "sg:tags":[
        "psychologist"
    ],
    "wof:name":"Guilbault-Baril, Ginette",
    "wof:placetype":"venue"
},
  "geometry": {"coordinates":[-71.291634,46.770271],"type":"Point"}
}