{
  "type": "Feature",
  "properties": {
    "addr:full":"1033 Mcgregor St Winnipeg MB R2V 3H4",
    "addr:housenumber":"1033",
    "addr:postcode":"r2v 3h4",
    "addr:street":"Mcgregor St",
    "iso:country":"CA",
    "sg:address":"1033 Mcgregor St",
    "sg:city":"Winnipeg",
    "sg:classifiers":[
        {
            "category":"Real Estate",
            "subcategory":"Real Estate Agent",
            "type":"Services"
        }
    ],
    "sg:phone":"+1 204 339 0461",
    "sg:postcode":"R2V 3H4",
    "sg:province":"MB",
    "sg:tags":[
        "management"
    ],
    "wof:name":"Kay Four Properties Inc",
    "wof:placetype":"venue"
},
  "geometry": {"coordinates":[-97.12554900000001,49.947044],"type":"Point"}
}