{
  "type": "Feature",
  "properties": {
    "addr:full":"11850 142 St NW Edmonton AB T5L 2G7",
    "addr:housenumber":"11850",
    "addr:postcode":"t5l 2g7",
    "addr:street":"142 St Nw",
    "iso:country":"CA",
    "sg:address":"11850 142 St NW",
    "sg:city":"Edmonton",
    "sg:classifiers":[
        {
            "category":"Wholesale",
            "subcategory":"Electrical",
            "type":"Manufacturing & Wholesale Goods"
        }
    ],
    "sg:phone":"+1 780 453 6735",
    "sg:postcode":"T5L 2G7",
    "sg:province":"AB",
    "sg:tags":[
        "barbecue",
        "appliance",
        "equipment"
    ],
    "wof:name":"Reliable Parts Ltd",
    "wof:placetype":"venue"
},
  "geometry": {"coordinates":[-113.56608581499999,53.5708351135],"type":"Point"}
}