{
  "type": "Feature",
  "properties": {
    "addr:full":"165 Ontario St Kingston ON K7L 2Y6",
    "addr:housenumber":"165",
    "addr:postcode":"k7l 2y6",
    "addr:street":"Ontario St",
    "iso:country":"CA",
    "sg:address":"165 Ontario St",
    "sg:city":"Kingston",
    "sg:classifiers":[
        {
            "category":"Health Services",
            "subcategory":"Doctor",
            "type":"Services"
        }
    ],
    "sg:phone":"+1 613 546 6379",
    "sg:postcode":"K7L 2Y6",
    "sg:province":"ON",
    "sg:tags":[
        "dentist"
    ],
    "wof:name":"Cameron, Ian A DDS",
    "wof:placetype":"venue"
},
  "geometry": {"coordinates":[-76.481506,44.228088],"type":"Point"}
}