{
  "type": "Feature",
  "properties": {
    "iso:country":"CA",
    "sg:address":"305 Lakeshore Rd E",
    "sg:city":"Oakville",
    "sg:classifiers":[
        {
            "category":"Health Services",
            "subcategory":"Doctor",
            "type":"Services"
        }
    ],
    "sg:phone":"+1 905 844 4825",
    "sg:postcode":"L6J 1J3",
    "sg:province":"ON",
    "sg:tags":[
        "physician",
        "surgeon"
    ],
    "wof:name":"Bhattacharya, Ashok MD",
    "wof:placetype":"venue"
},
  "geometry": {"coordinates":[-79.6661224365,43.4479293823],"type":"Point"}
}