{
  "type": "Feature",
  "properties": {
    "addr:full":"Revelstoke BC V0E 2S0",
    "addr:postcode":"v0e 2s0",
    "iso:country":"CA",
    "sg:city":"Revelstoke",
    "sg:classifiers":[
        {
            "category":"Social Services",
            "subcategory":"Child Care",
            "type":"Services"
        }
    ],
    "sg:phone":"+1 250 837 5855",
    "sg:postcode":"V0E 2S0",
    "sg:province":"BC",
    "wof:name":"Stepping Stones Childcare",
    "wof:placetype":"venue"
},
  "geometry": {"coordinates":[-118.198753357,50.9975585938],"type":"Point"}
}