{
  "type": "Feature",
  "properties": {
    "addr:full":"9028 Nouch Frontage Rd Smithers BC V0J 2N2",
    "addr:housenumber":"9028",
    "addr:postcode":"v0j 2n2",
    "addr:street":"Nouch Frontage Rd",
    "iso:country":"CA",
    "sg:address":"9028 Nouch Frontage Rd",
    "sg:city":"Smithers",
    "sg:classifiers":[
        {
            "category":"Travel",
            "subcategory":"Campground",
            "type":"Entertainment"
        }
    ],
    "sg:phone":"+1 250 847 3961",
    "sg:postcode":"V0J 2N2",
    "sg:province":"BC",
    "wof:name":"Glacier View Rv Park",
    "wof:placetype":"venue"
},
  "geometry": {"coordinates":[-127.161514,54.778461],"type":"Point"}
}