{
  "type": "Feature",
  "properties": {
    "addr:full":"31 Main St S Waterdown ON L0R 2H0",
    "addr:housenumber":"31",
    "addr:postcode":"l0r 2h0",
    "addr:street":"Main St S",
    "iso:country":"CA",
    "sg:address":"31 Main St S",
    "sg:city":"Waterdown",
    "sg:classifiers":[
        {
            "category":"Restaurant",
            "type":"Food & Drink"
        }
    ],
    "sg:phone":"+1 905 689 4741",
    "sg:postcode":"L0R 2H0",
    "sg:province":"ON",
    "wof:name":"Pause Awhile Restaurant",
    "wof:placetype":"venue"
},
  "geometry": {"coordinates":[-79.891869,43.332748],"type":"Point"}
}