{
  "type": "Feature",
  "properties": {
    "addr:full":"69 London Rd Hensall ON N0M 1X0",
    "addr:housenumber":"69",
    "addr:postcode":"n0m 1x0",
    "addr:street":"London Rd",
    "iso:country":"CA",
    "sg:address":"69 London Rd",
    "sg:city":"Hensall",
    "sg:classifiers":[
        {
            "category":"Shopping",
            "subcategory":"Bicycles & Sporting Goods",
            "type":"Retail Goods"
        }
    ],
    "sg:phone":"+1 519 262 2615",
    "sg:postcode":"N0M 1X0",
    "sg:province":"ON",
    "sg:tags":[
        "antique"
    ],
    "wof:name":"O'Brien's Bait & Tackle",
    "wof:placetype":"venue"
},
  "geometry": {"coordinates":[-81.49886322019999,43.4366607666],"type":"Point"}
}