{
  "type": "Feature",
  "properties": {
    "addr:full":"35015 Sward Rd Mission BC V2V 7H1",
    "addr:housenumber":"35015",
    "addr:postcode":"v2v 7h1",
    "addr:street":"Sward Rd",
    "iso:country":"CA",
    "sg:address":"35015 Sward Rd",
    "sg:city":"Mission",
    "sg:classifiers":[
        {
            "category":"Building & Trades",
            "subcategory":"Landscaping Services",
            "type":"Services"
        }
    ],
    "sg:phone":"+1 604 826 9139",
    "sg:postcode":"V2V 7H1",
    "sg:province":"BC",
    "sg:tags":[
        "lawn",
        "maintenance",
        "grounds"
    ],
    "wof:name":"Greg's House & Garden Mntnc",
    "wof:placetype":"venue"
},
  "geometry": {"coordinates":[-122.28280599999999,49.159996],"type":"Point"}
}