{
  "type": "Feature",
  "properties": {
    "addr:full":"560 Rue Cambronne Beauport QC G1E 6X1",
    "addr:housenumber":"560",
    "addr:postcode":"qc g1e 6x1",
    "addr:street":"Rue Cambronne",
    "iso:country":"CA",
    "sg:address":"560 Rue Cambronne",
    "sg:city":"Beauport",
    "sg:classifiers":[
        {
            "category":"Bars & Pubs",
            "type":"Food & Drink"
        }
    ],
    "sg:phone":"+1 418 667 1656",
    "sg:postcode":"G1E 6X1",
    "sg:province":"QC",
    "sg:tags":[
        "lounge",
        "cocktail"
    ],
    "wof:name":"Bar Des Seigneurs Inc",
    "wof:placetype":"venue"
},
  "geometry": {"coordinates":[-71.196602,46.872074],"type":"Point"}
}