{
  "type": "Feature",
  "properties": {
    "iso:country":"CA",
    "sg:city":"Guelph",
    "sg:classifiers":[
        {
            "category":"Health Services",
            "subcategory":"Health Practitioner",
            "type":"Services"
        }
    ],
    "sg:phone":"+1 519 823 9785",
    "sg:postcode":"N1H 8N9",
    "sg:province":"ON",
    "sg:tags":[
        "midwife"
    ],
    "wof:name":"Guelph Midwives",
    "wof:placetype":"venue"
},
  "geometry": {"coordinates":[-80.2506942749,43.5473251343],"type":"Point"}
}