{
  "type": "Feature",
  "properties": {
    "iso:country":"CA",
    "sg:address":"34 Cowansview Rd",
    "sg:city":"Cambridge",
    "sg:classifiers":[
        {
            "category":"Manufacturing",
            "subcategory":"Metals",
            "type":"Manufacturing & Wholesale Goods"
        }
    ],
    "sg:phone":"+1 519 623 5427",
    "sg:postcode":"N1R 7N3",
    "sg:province":"ON",
    "sg:tags":[
        "treating",
        "heat"
    ],
    "wof:name":"Cambridge Heat Treating",
    "wof:placetype":"venue"
},
  "geometry": {"coordinates":[-80.306968689,43.3962554932],"type":"Point"}
}