{
  "type": "Feature",
  "properties": {
    "addr:full":"368 St Laurent Ave Quesnel BC V2J 5A3",
    "addr:housenumber":"368",
    "addr:postcode":"v2j 5a3",
    "addr:street":"St Laurent Ave",
    "iso:country":"CA",
    "sg:address":"368 St Laurent Ave",
    "sg:city":"Quesnel",
    "sg:classifiers":[
        {
            "category":"Health Services",
            "subcategory":"Medical Lab",
            "type":"Services"
        }
    ],
    "sg:phone":"+1 250 992 5766",
    "sg:postcode":"V2J 5A3",
    "sg:province":"BC",
    "wof:name":"George Walker Denture Clinic",
    "wof:placetype":"venue"
},
  "geometry": {"coordinates":[-122.49432400000001,52.979015],"type":"Point"}
}