{
  "type": "Feature",
  "properties": {
    "iso:country":"CA",
    "sg:address":"10815 Pacific Hwy 2",
    "sg:city":"Iroquois",
    "sg:classifiers":[
        {
            "category":"Travel",
            "subcategory":"Hotels & Motels",
            "type":"Entertainment"
        }
    ],
    "sg:phone":"+1 613 652 4176",
    "sg:postcode":"K0E 1K0",
    "sg:province":"ON",
    "wof:name":"Iroquois Motor Motel",
    "wof:placetype":"venue"
},
  "geometry": {"coordinates":[-75.3483963013,44.8118362427],"type":"Point"}
}