{
  "type": "Feature",
  "properties": {
    "addr:full":"Grassland AB T0A 1V0",
    "addr:postcode":"t0a 1v0",
    "iso:country":"CA",
    "sg:city":"Grassland",
    "sg:classifiers":[
        {
            "category":"Autos & Motor Vehicles",
            "subcategory":"Fuel & Gas Station",
            "type":"Retail Goods"
        }
    ],
    "sg:phone":"+1 780 525 2600",
    "sg:postcode":"T0A 1V0",
    "sg:province":"AB",
    "sg:tags":[
        "oil",
        "courier"
    ],
    "wof:name":"Greyhound Lines of Canada Ltd",
    "wof:placetype":"venue"
},
  "geometry": {"coordinates":[-112.71305099999999,54.820309],"type":"Point"}
}