{
  "type": "Feature",
  "properties": {
    "addr:full":"820 Hwy 246 Wentworth NS B0M 1Z0",
    "addr:housenumber":"820",
    "addr:postcode":"b0m 1z0",
    "addr:street":"Hwy 246",
    "iso:country":"CA",
    "sg:address":"820 Hwy 246",
    "sg:city":"Wentworth",
    "sg:classifiers":[
        {
            "category":"Retail",
            "subcategory":"Auto Repair",
            "type":"Services"
        }
    ],
    "sg:phone":"+1 902 548 2409",
    "sg:postcode":"B0M 1Z0",
    "sg:province":"NS",
    "sg:tags":[
        "body",
        "automobile",
        "painting"
    ],
    "wof:name":"Smith's Autobody",
    "wof:placetype":"venue"
},
  "geometry": {"coordinates":[-63.549278,45.657459],"type":"Point"}
}