{
  "type": "Feature",
  "properties": {
    "addr:full":"Dorval QC H9S 2B6",
    "addr:postcode":"h9s 2b6",
    "iso:country":"CA",
    "sg:city":"Dorval",
    "sg:classifiers":[
        {
            "category":"Insurance",
            "subcategory":"Insurance Agent",
            "type":"Services"
        }
    ],
    "sg:phone":"+1 514 631 1170",
    "sg:postcode":"H9S 2B6",
    "sg:province":"QC",
    "wof:name":"Sklivas & Assoc",
    "wof:placetype":"venue"
},
  "geometry": {"coordinates":[-73.77886199949999,45.4455871582],"type":"Point"}
}