{
  "type": "Feature",
  "properties": {
    "iso:country":"CA",
    "sg:city":"Calgary",
    "sg:classifiers":[
        {
            "category":"Building & Trades",
            "subcategory":"Construction",
            "type":"Services"
        }
    ],
    "sg:phone":"+1 403 250 9951",
    "sg:postcode":"T2E 6L1",
    "sg:province":"AB",
    "sg:tags":[
        "repairing",
        "remodeling",
        "contractor"
    ],
    "wof:name":"Rusco Industries Calgary Ltd",
    "wof:placetype":"venue"
},
  "geometry": {"coordinates":[-114.029732,51.088863],"type":"Point"}
}