{
  "type": "Feature",
  "properties": {
    "addr:full":"5060 Rue Frontenac Saint-Hyacinthe QC J2S 2E5",
    "addr:housenumber":"5060",
    "addr:postcode":"j2s 2e5",
    "addr:street":"Rue Frontenac",
    "iso:country":"CA",
    "sg:address":"5060 Rue Frontenac",
    "sg:city":"Saint-Hyacinthe",
    "sg:classifiers":[
        {
            "category":"Health Services",
            "subcategory":"Medical Lab",
            "type":"Services"
        }
    ],
    "sg:phone":"+1 450 773 5790",
    "sg:postcode":"J2S 2E5",
    "sg:province":"QC",
    "wof:name":"Chaput, Alain",
    "wof:placetype":"venue"
},
  "geometry": {"coordinates":[-72.970787,45.602177],"type":"Point"}
}