{
  "type": "Feature",
  "properties": {
    "addr:full":"625 Rue Sainte-Catherine O Montreal QC H3B 1B7",
    "addr:housenumber":"625",
    "addr:postcode":"h3b 1b7",
    "addr:street":"Rue Sainte-Catherine O",
    "iso:country":"CA",
    "sg:address":"625 Rue Sainte-Catherine O",
    "sg:city":"Montreal",
    "sg:classifiers":[
        {
            "category":"Organizations",
            "subcategory":"Religious Organization",
            "type":"Services"
        }
    ],
    "sg:phone":"+1 514 848 9777",
    "sg:postcode":"H3B 1B7",
    "sg:province":"QC",
    "wof:name":"Societe Biblique Canadienne",
    "wof:placetype":"venue"
},
  "geometry": {"coordinates":[-73.5592880249,45.5152549744],"type":"Point"}
}