{
  "type": "Feature",
  "properties": {
    "addr:full":"1170 Albion Rd Etobicoke ON M9V 1A8",
    "addr:housenumber":"1170",
    "addr:postcode":"m9v 1a8",
    "addr:street":"Albion Rd",
    "iso:country":"CA",
    "sg:address":"1170 Albion Rd",
    "sg:city":"Etobicoke",
    "sg:classifiers":[
        {
            "category":"Personal",
            "subcategory":"Beauty Salon",
            "type":"Services"
        }
    ],
    "sg:phone":"+1 416 742 2698",
    "sg:postcode":"M9V 1A8",
    "sg:province":"ON",
    "wof:name":"Kiran Beauty Parlour",
    "wof:placetype":"venue"
},
  "geometry": {"coordinates":[-79.568687439,43.7379646301],"type":"Point"}
}