{
  "type": "Feature",
  "properties": {
    "addr:full":"Maria QC G0C 1Y0",
    "addr:postcode":"g0c 1y0",
    "addr:street":"Maria",
    "iso:country":"CA",
    "sg:city":"Maria",
    "sg:classifiers":[
        {
            "category":"Shopping",
            "subcategory":"Gifts & Souvenirs",
            "type":"Retail Goods"
        }
    ],
    "sg:phone":"+1 418 759 5663",
    "sg:postcode":"G0C 1Y0",
    "sg:province":"QC",
    "sg:tags":[
        "shop"
    ],
    "wof:name":"Boite Aux Belles Choses Enr",
    "wof:placetype":"venue"
},
  "geometry": {"coordinates":[-65.981987,48.175045],"type":"Point"}
}