{
  "type": "Feature",
  "properties": {
    "addr:full":"240 Leighland Ave # 108 Oakville ON L6H 3H6",
    "addr:housenumber":"240",
    "addr:postcode":"l6h 3h6",
    "addr:street":"Leighland Ave # 108",
    "iso:country":"CA",
    "sg:address":"240 Leighland Ave # 108",
    "sg:city":"Oakville",
    "sg:classifiers":[
        {
            "category":"Shopping",
            "type":"Retail Goods"
        }
    ],
    "sg:phone":"+1 905 849 7353",
    "sg:postcode":"L6H 3H6",
    "sg:province":"ON",
    "sg:tags":[
        "cosmetic",
        "perfume"
    ],
    "wof:name":"Body Shop",
    "wof:placetype":"venue"
},
  "geometry": {"coordinates":[-79.688705,43.462414],"type":"Point"}
}