{
  "type": "Feature",
  "properties": {
    "addr:full":"369 Rue Principale Saint-Gabriel-DE-Rimouski QC G0K 1M0",
    "addr:housenumber":"369",
    "addr:postcode":"g0k 1m0",
    "addr:street":"Rue Principale",
    "iso:country":"CA",
    "sg:address":"369 Rue Principale",
    "sg:city":"Saint-Gabriel-DE-Rimouski",
    "sg:classifiers":[
        {
            "category":"Freight",
            "type":"Transportation"
        }
    ],
    "sg:phone":"+1 418 798 4963",
    "sg:postcode":"G0K 1M0",
    "sg:province":"QC",
    "sg:tags":[
        "trucking"
    ],
    "wof:name":"Guildo Brochu Inc",
    "wof:placetype":"venue"
},
  "geometry": {"coordinates":[-68.182281,48.416176],"type":"Point"}
}