{
  "type": "Feature",
  "properties": {
    "addr:full":"136 Waller Rd Opaskwayak MB R0B 2J0",
    "addr:housenumber":"136",
    "addr:postcode":"r0b 2j0",
    "addr:street":"Waller Rd",
    "iso:country":"CA",
    "sg:address":"136 Waller Rd",
    "sg:city":"Opaskwayak",
    "sg:classifiers":[
        {
            "category":"Education",
            "subcategory":"School",
            "type":"Public Place"
        }
    ],
    "sg:phone":"+1 204 623 4286",
    "sg:postcode":"R0B 2J0",
    "sg:province":"MB",
    "wof:name":"Joe A Ross School",
    "wof:placetype":"venue"
},
  "geometry": {"coordinates":[-95.49900100000001,54.499432],"type":"Point"}
}