{
  "type": "Feature",
  "properties": {
    "addr:full":"Vancouver BC V6J 1H3",
    "addr:postcode":"v6j 1h3",
    "iso:country":"CA",
    "sg:city":"Vancouver",
    "sg:classifiers":[
        {
            "category":"Professional",
            "subcategory":"Engineering",
            "type":"Services"
        }
    ],
    "sg:phone":"+1 604 736 9466",
    "sg:postcode":"V6J 1H3",
    "sg:province":"BC",
    "sg:tags":[
        "architect",
        "naval"
    ],
    "wof:name":"Robert Allan Ltd",
    "wof:placetype":"venue"
},
  "geometry": {"coordinates":[-123.141792,49.269859],"type":"Point"}
}