{
  "type": "Feature",
  "properties": {
    "iso:country":"CA",
    "sg:address":"8 Hammond St",
    "sg:city":"St Thomas",
    "sg:classifiers":[
        {
            "category":"Social Services",
            "subcategory":"Child Care",
            "type":"Services"
        }
    ],
    "sg:phone":"+1 519 631 1658",
    "sg:postcode":"N5P 2B5",
    "sg:province":"ON",
    "wof:name":"Robin's Nest",
    "wof:placetype":"venue"
},
  "geometry": {"coordinates":[-81.183281,42.789169],"type":"Point"}
}