{
  "type": "Feature",
  "properties": {
    "addr:full":"610 King St W Gananoque ON K7G 2H1",
    "addr:housenumber":"610",
    "addr:postcode":"k7g 2h1",
    "addr:street":"King St W",
    "iso:country":"CA",
    "sg:address":"610 King St W",
    "sg:city":"Gananoque",
    "sg:classifiers":[
        {
            "category":"Retail",
            "subcategory":"Auto Repair",
            "type":"Services"
        }
    ],
    "sg:phone":"+1 613 382 2094",
    "sg:postcode":"K7G 2H1",
    "sg:province":"ON",
    "sg:tags":[
        "repairing",
        "automobile"
    ],
    "wof:name":"Neal's Garage",
    "wof:placetype":"venue"
},
  "geometry": {"coordinates":[-76.174659729,44.3258857727],"type":"Point"}
}