{
  "type": "Feature",
  "properties": {
    "addr:full":"680 Torbay Rd St. John's NL A1A 5G9",
    "addr:housenumber":"680",
    "addr:postcode":"a1a 5g9",
    "addr:street":"Torbay Rd",
    "iso:country":"CA",
    "sg:address":"680 Torbay Rd",
    "sg:city":"St. John's",
    "sg:classifiers":[
        {
            "category":"Wholesale",
            "subcategory":"Groceries",
            "type":"Manufacturing & Wholesale Goods"
        }
    ],
    "sg:phone":"+1 709 738 3788",
    "sg:postcode":"A1A 5G9",
    "sg:province":"NL",
    "sg:tags":[
        "food",
        "grocer",
        "product"
    ],
    "wof:name":"Ziggy Peelgoods French Fries",
    "wof:placetype":"venue"
},
  "geometry": {"coordinates":[-52.722946,47.617802],"type":"Point"}
}