{
  "type": "Feature",
  "properties": {
    "addr:full":"3542 Hwy 321 Oxford NS B0M 1P0",
    "addr:housenumber":"3542",
    "addr:postcode":"b0m 1p0",
    "addr:street":"Hwy 321",
    "iso:country":"CA",
    "sg:address":"3542 Hwy 321",
    "sg:city":"Oxford",
    "sg:phone":"+1 902 447 2042",
    "sg:postcode":"B0M 1P0",
    "sg:province":"NS",
    "sg:tags":[
        "lubricant"
    ],
    "wof:name":"Power Up Lubricants",
    "wof:placetype":"venue"
},
  "geometry": {"coordinates":[-63.8797874451,45.7197341919],"type":"Point"}
}