{
  "type": "Feature",
  "properties": {
    "addr:full":"655 Hwy 3A Nelson BC V1L 6M6",
    "addr:housenumber":"655",
    "addr:postcode":"bc v1l 6m6",
    "addr:street":"Hwy 3A",
    "iso:country":"CA",
    "sg:address":"655 Hwy 3A",
    "sg:city":"Nelson",
    "sg:classifiers":[
        {
            "category":"Travel",
            "subcategory":"Hotels & Motels",
            "type":"Entertainment"
        }
    ],
    "sg:phone":"+1 250 352 5515",
    "sg:postcode":"V1L 6M6",
    "sg:province":"BC",
    "wof:name":"Villa Motel",
    "wof:placetype":"venue"
},
  "geometry": {"coordinates":[-117.292739868,49.4937553406],"type":"Point"}
}