{
  "type": "Feature",
  "properties": {
    "iso:country":"CA",
    "sg:address":"450 Ch Rheaume # A",
    "sg:city":"Saint-Michel",
    "sg:classifiers":[
        {
            "category":"Retail",
            "subcategory":"Auto Repair",
            "type":"Services"
        }
    ],
    "sg:phone":"+1 450 454 3727",
    "sg:postcode":"J0L 2J0",
    "sg:province":"QC",
    "sg:tags":[
        "truck"
    ],
    "wof:name":"Centre Du Camion 410 Inc",
    "wof:placetype":"venue"
},
  "geometry": {"coordinates":[-73.5691070557,45.2428207397],"type":"Point"}
}