{
  "type": "Feature",
  "properties": {
    "addr:full":"Grande Prairie AB T8V 2K6",
    "addr:postcode":"t8v 2k6",
    "iso:country":"CA",
    "sg:city":"Grande Prairie",
    "sg:classifiers":[
        {
            "category":"Real Estate",
            "subcategory":"Real Estate Operator",
            "type":"Services"
        }
    ],
    "sg:phone":"+1 780 532 8243",
    "sg:postcode":"T8V 2K6",
    "sg:province":"AB",
    "sg:tags":[
        "apartment"
    ],
    "wof:name":"Boardwalk Realty Ltd",
    "wof:placetype":"venue"
},
  "geometry": {"coordinates":[-118.79470825200001,55.1636543274],"type":"Point"}
}