{
  "type": "Feature",
  "properties": {
    "addr:full":"3035 Airport Rd Kamloops BC V2B 7X1",
    "addr:housenumber":"3035",
    "addr:postcode":"bc v2b 7x1",
    "addr:street":"Airport Rd",
    "iso:country":"CA",
    "sg:address":"3035 Airport Rd",
    "sg:city":"Kamloops",
    "sg:classifiers":[
        {
            "category":"Airport",
            "type":"Transportation"
        }
    ],
    "sg:phone":"+1 250 376 3613",
    "sg:postcode":"V2B 7X1",
    "sg:province":"BC",
    "wof:name":"Kamloops Airport Ltd",
    "wof:placetype":"venue"
},
  "geometry": {"coordinates":[-120.441765,50.705406],"type":"Point"}
}