{
  "type": "Feature",
  "properties": {
    "addr:full":"2579 Broadway W Vancouver BC V6K 2E9",
    "addr:housenumber":"2579",
    "addr:postcode":"v6k 2e9",
    "addr:street":"Broadway W",
    "iso:country":"CA",
    "sg:address":"2579 Broadway W",
    "sg:city":"Vancouver",
    "sg:classifiers":[
        {
            "category":"Personal",
            "subcategory":"Beauty Salon",
            "type":"Services"
        }
    ],
    "sg:phone":"+1 604 736 7761",
    "sg:postcode":"V6K 2E9",
    "sg:province":"BC",
    "sg:tags":[
        "aromatherapy"
    ],
    "wof:name":"Escents Aromatherapy Bath",
    "wof:placetype":"venue"
},
  "geometry": {"coordinates":[-123.163902283,49.2641525269],"type":"Point"}
}