{
  "type": "Feature",
  "properties": {
    "addr:full":"7 Clarence St Ottawa ON K1N 5P4",
    "addr:housenumber":"7",
    "addr:postcode":"k1n 5p4",
    "addr:street":"Clarence St",
    "iso:country":"CA",
    "sg:address":"7 Clarence St",
    "sg:city":"Ottawa",
    "sg:classifiers":[
        {
            "category":"Restaurant",
            "type":"Food & Drink"
        }
    ],
    "sg:phone":"+1 613 241 1882",
    "sg:postcode":"K1N 5P4",
    "sg:province":"ON",
    "wof:name":"Memories Restaurant",
    "wof:placetype":"venue"
},
  "geometry": {"coordinates":[-75.69538879389999,45.4281311035],"type":"Point"}
}