{
  "type": "Feature",
  "properties": {
    "iso:country":"CA",
    "sg:city":"Brossard",
    "sg:classifiers":[
        {
            "category":"Shopping",
            "subcategory":"Bicycles & Sporting Goods",
            "type":"Retail Goods"
        }
    ],
    "sg:phone":"+1 450 445 1484",
    "sg:postcode":"J4Z 1A6",
    "sg:province":"QC",
    "sg:tags":[
        "club",
        "soccer"
    ],
    "wof:name":"Evangelista Sports",
    "wof:placetype":"venue"
},
  "geometry": {"coordinates":[-73.466506958,45.4746322632],"type":"Point"}
}