{
  "type": "Feature",
  "properties": {
    "addr:full":"26 Maple Valley Rd Corner Brook NL A2H 3C2",
    "addr:housenumber":"26",
    "addr:postcode":"a2h 3c2",
    "addr:street":"Maple Valley Rd",
    "iso:country":"CA",
    "sg:address":"26 Maple Valley Rd",
    "sg:city":"Corner Brook",
    "sg:classifiers":[
        {
            "category":"Wholesale",
            "subcategory":"Electrical",
            "type":"Manufacturing & Wholesale Goods"
        }
    ],
    "sg:phone":"+1 709 634 5620",
    "sg:postcode":"A2H 3C2",
    "sg:province":"NL",
    "sg:tags":[
        "electric",
        "motor"
    ],
    "wof:name":"Power Electric Motor Sales Ltd",
    "wof:placetype":"venue"
},
  "geometry": {"coordinates":[-57.9175033569,48.9508857727],"type":"Point"}
}