{
  "type": "Feature",
  "properties": {
    "addr:full":"6206 Perth St Richmond ON K0A 2Z0",
    "addr:housenumber":"6206",
    "addr:postcode":"k0a 2z0",
    "addr:street":"Perth St",
    "iso:country":"CA",
    "sg:address":"6206 Perth St",
    "sg:city":"Richmond",
    "sg:classifiers":[
        {
            "category":"Health Services",
            "subcategory":"Doctor",
            "type":"Services"
        }
    ],
    "sg:phone":"+1 613 838 2093",
    "sg:postcode":"K0A 2Z0",
    "sg:province":"ON",
    "sg:tags":[
        "physician",
        "surgeon"
    ],
    "wof:name":"Zahab, Raymond E MD",
    "wof:placetype":"venue"
},
  "geometry": {"coordinates":[-75.842354,45.192001],"type":"Point"}
}