{
  "type": "Feature",
  "properties": {
    "addr:full":"39 Talbot St W Cayuga ON N0A 1E0",
    "addr:housenumber":"39",
    "addr:postcode":"n0a 1e0",
    "addr:street":"Talbot St W",
    "iso:country":"CA",
    "sg:address":"39 Talbot St W",
    "sg:city":"Cayuga",
    "sg:classifiers":[
        {
            "category":"Retail",
            "subcategory":"Auto Repair",
            "type":"Services"
        }
    ],
    "sg:phone":"+1 905 772 5411",
    "sg:postcode":"N0A 1E0",
    "sg:province":"ON",
    "sg:tags":[
        "repairing",
        "automobile"
    ],
    "wof:name":"Cayuga Automotive",
    "wof:placetype":"venue"
},
  "geometry": {"coordinates":[-79.85953521730001,42.9492301941],"type":"Point"}
}