{
  "type": "Feature",
  "properties": {
    "addr:full":"2100 Boul Le Corbusier Laval QC H7S 2C9",
    "addr:housenumber":"2100",
    "addr:postcode":"h7s 2c9",
    "addr:street":"Boul Le Corbusier",
    "iso:country":"CA",
    "sg:address":"2100 Boul Le Corbusier",
    "sg:city":"Laval",
    "sg:classifiers":[
        {
            "category":"Health Services",
            "subcategory":"Podiatrist",
            "type":"Services"
        }
    ],
    "sg:phone":"+1 450 681 4399",
    "sg:postcode":"H7S 2C9",
    "sg:province":"QC",
    "wof:name":"A L'Orthese Du Pied",
    "wof:placetype":"venue"
},
  "geometry": {"coordinates":[-73.73938,45.570648],"type":"Point"}
}