{
  "type": "Feature",
  "properties": {
    "addr:full":"49 Elora St S Clifford ON N0G 1M0",
    "addr:housenumber":"49",
    "addr:postcode":"n0g 1m0",
    "addr:street":"Elora St S",
    "iso:country":"CA",
    "sg:address":"49 Elora St S",
    "sg:city":"Clifford",
    "sg:classifiers":[
        {
            "category":"Wholesale",
            "subcategory":"Farm Supplies",
            "type":"Manufacturing & Wholesale Goods"
        }
    ],
    "sg:phone":"+1 519 327 8008",
    "sg:postcode":"N0G 1M0",
    "sg:province":"ON",
    "sg:tags":[
        "feed"
    ],
    "wof:name":"Nieuwland Feed & Supply Ltd",
    "wof:placetype":"venue"
},
  "geometry": {"coordinates":[-80.97539500000001,43.967728],"type":"Point"}
}