{
  "type": "Feature",
  "properties": {
    "addr:full":"1972 Peninsula St Ucluelet BC V0R 3A0",
    "addr:housenumber":"1972",
    "addr:postcode":"bc v0r 3a0",
    "addr:street":"Peninsula St",
    "iso:country":"CA",
    "sg:address":"1972 Peninsula St",
    "sg:city":"Ucluelet",
    "sg:classifiers":[
        {
            "category":"Food & Beverages",
            "subcategory":"Groceries & Convenience Stores",
            "type":"Retail Goods"
        }
    ],
    "sg:phone":"+1 250 726 4240",
    "sg:postcode":"V0R 3A0",
    "sg:province":"BC",
    "sg:tags":[
        "grocer"
    ],
    "wof:name":"Number One Market",
    "wof:placetype":"venue"
},
  "geometry": {"coordinates":[-125.54261,48.938026],"type":"Point"}
}