{
  "type": "Feature",
  "properties": {
    "addr:full":"720 Westmount Rd E Kitchener ON N2E 2M6",
    "addr:housenumber":"720",
    "addr:postcode":"n2e 2m6",
    "addr:street":"Westmount Rd E",
    "iso:country":"CA",
    "sg:address":"720 Westmount Rd E",
    "sg:city":"Kitchener",
    "sg:classifiers":[
        {
            "category":"Banks & Credit Unions",
            "subcategory":"Bank",
            "type":"Services"
        }
    ],
    "sg:phone":"+1 519 885 9285",
    "sg:postcode":"N2E 2M6",
    "sg:province":"ON",
    "wof:name":"Bank of Montreal",
    "wof:placetype":"venue"
},
  "geometry": {"coordinates":[-80.5013656616,43.418964386],"type":"Point"}
}