{
  "type": "Feature",
  "properties": {
    "addr:full":"5 Boul Archambault Gatineau QC J8T 2L7",
    "addr:housenumber":"5",
    "addr:postcode":"j8t 2l7",
    "addr:street":"Boul Archambault",
    "iso:country":"CA",
    "sg:address":"5 Boul Archambault",
    "sg:city":"Gatineau",
    "sg:classifiers":[
        {
            "category":"Home & Garden",
            "subcategory":"Building Materials",
            "type":"Retail Goods"
        }
    ],
    "sg:phone":"+1 819 246 7100",
    "sg:postcode":"J8T 2L7",
    "sg:province":"QC",
    "sg:tags":[
        "door"
    ],
    "wof:name":"Canada Trim",
    "wof:placetype":"venue"
},
  "geometry": {"coordinates":[-75.74329400000001,45.443722],"type":"Point"}
}