{
  "type": "Feature",
  "properties": {
    "iso:country":"CA",
    "sg:address":"132 Queen St",
    "sg:city":"Chatham",
    "sg:classifiers":[
        {
            "category":"Wholesale",
            "subcategory":"Office Equipment",
            "type":"Manufacturing & Wholesale Goods"
        }
    ],
    "sg:phone":"+1 519 354 5310",
    "sg:postcode":"N7M 2G6",
    "sg:province":"ON",
    "sg:tags":[
        "accounting",
        "bookkeeping",
        "system"
    ],
    "wof:name":"Easter & Assoc",
    "wof:placetype":"venue"
},
  "geometry": {"coordinates":[-82.185143,42.402763],"type":"Point"}
}