{
  "type": "Feature",
  "properties": {
    "addr:full":"11807 125 St NW Edmonton AB T5L 0S1",
    "addr:housenumber":"11807",
    "addr:postcode":"t5l 0s1",
    "addr:street":"125 St Nw",
    "iso:country":"CA",
    "sg:address":"11807 125 St NW",
    "sg:city":"Edmonton",
    "sg:classifiers":[
        {
            "category":"Manufacturing",
            "subcategory":"Printing",
            "type":"Manufacturing & Wholesale Goods"
        }
    ],
    "sg:phone":"+1 780 452 6022",
    "sg:postcode":"T5L 0S1",
    "sg:province":"AB",
    "sg:tags":[
        "printer"
    ],
    "wof:name":"Vos Printing & Design Ltd",
    "wof:placetype":"venue"
},
  "geometry": {"coordinates":[-113.537476,53.570564],"type":"Point"}
}