{
  "type": "Feature",
  "properties": {
    "addr:full":"421 Base Line Rd E London ON N6C 2P5",
    "addr:housenumber":"421",
    "addr:postcode":"n6c 2p5",
    "addr:street":"Base Line Rd E",
    "iso:country":"CA",
    "sg:address":"421 Base Line Rd E",
    "sg:city":"London",
    "sg:classifiers":[
        {
            "category":"Home & Garden",
            "subcategory":"Home Furnishings",
            "type":"Retail Goods"
        }
    ],
    "sg:phone":"+1 519 686 6343",
    "sg:postcode":"N6C 2P5",
    "sg:province":"ON",
    "sg:tags":[
        "curtain",
        "made",
        "drapery"
    ],
    "wof:name":"Fountain Custom Drapery",
    "wof:placetype":"venue"
},
  "geometry": {"coordinates":[-81.24165344239999,42.9607200623],"type":"Point"}
}