{
  "type": "Feature",
  "properties": {
    "addr:full":"168 Milltown Blvd St Stephen NB E3L 1G8",
    "addr:housenumber":"168",
    "addr:postcode":"e3l 1g8",
    "addr:street":"Milltown Blvd",
    "iso:country":"CA",
    "sg:address":"168 Milltown Blvd",
    "sg:city":"St Stephen",
    "sg:classifiers":[
        {
            "category":"Personal",
            "subcategory":"Barber",
            "type":"Services"
        }
    ],
    "sg:phone":"+1 506 465 8430",
    "sg:postcode":"E3L 1G8",
    "sg:province":"NB",
    "wof:name":"Hyland Clipper",
    "wof:placetype":"venue"
},
  "geometry": {"coordinates":[-67.282501,45.192303],"type":"Point"}
}