{
  "type": "Feature",
  "properties": {
    "addr:full":"Vernon BC V1T 5G4",
    "addr:postcode":"v1t 5g4",
    "iso:country":"CA",
    "sg:city":"Vernon",
    "sg:classifiers":[
        {
            "category":"Communications",
            "subcategory":"Television Station",
            "type":"Services"
        }
    ],
    "sg:phone":"+1 250 542 7493",
    "sg:postcode":"V1T 5G4",
    "sg:province":"BC",
    "sg:tags":[
        "broadcasting",
        "co"
    ],
    "wof:name":"Chbc Okanagan Television",
    "wof:placetype":"venue"
},
  "geometry": {"coordinates":[-119.273804,50.265686],"type":"Point"}
}