{
  "type": "Feature",
  "properties": {
    "addr:full":"12 Worthington St Little Current ON P0P 1K0",
    "addr:housenumber":"12",
    "addr:postcode":"p0p 1k0",
    "addr:street":"Worthington St",
    "iso:country":"CA",
    "sg:address":"12 Worthington St",
    "sg:city":"Little Current",
    "sg:classifiers":[
        {
            "category":"Retail",
            "subcategory":"Auto Repair",
            "type":"Services"
        }
    ],
    "sg:phone":"+1 705 368 2823",
    "sg:postcode":"P0P 1K0",
    "sg:province":"ON",
    "sg:tags":[
        "repairing",
        "automobile"
    ],
    "wof:name":"Acme Motors Manitoulin Ltd",
    "wof:placetype":"venue"
},
  "geometry": {"coordinates":[-81.9276428223,45.9804801941],"type":"Point"}
}