{
  "type": "Feature",
  "properties": {
    "addr:full":"RR 1 STN Lcd 1 Calgary AB T2P 2G4",
    "addr:housenumber":"1",
    "addr:postcode":"t2p 2g4",
    "addr:street":"Rr 1 Stn Lcd",
    "iso:country":"CA",
    "sg:address":"RR 1 STN Lcd 1",
    "sg:city":"Calgary",
    "sg:classifiers":[
        {
            "category":"Building & Trades",
            "subcategory":"Construction",
            "type":"Services"
        }
    ],
    "sg:phone":"+1 403 242 4465",
    "sg:postcode":"T2P 2G4",
    "sg:province":"AB",
    "sg:tags":[
        "repairing",
        "remodeling",
        "contractor"
    ],
    "wof:name":"Sandstone Associates",
    "wof:placetype":"venue"
},
  "geometry": {"coordinates":[-114.063194275,51.0450744629],"type":"Point"}
}