{
  "type": "Feature",
  "properties": {
    "addr:full":"Mont-Saint-Hilaire QC J3H 3N3",
    "addr:postcode":"j3h 3n3",
    "iso:country":"CA",
    "sg:city":"Mont-Saint-Hilaire",
    "sg:classifiers":[
        {
            "category":"Professional",
            "subcategory":"Business Services",
            "type":"Services"
        }
    ],
    "sg:phone":"+1 450 446 3111",
    "sg:postcode":"J3H 3N3",
    "sg:province":"QC",
    "sg:tags":[
        "made"
    ],
    "wof:name":"Flory Multicolore",
    "wof:placetype":"venue"
},
  "geometry": {"coordinates":[-73.19692999999999,45.563358],"type":"Point"}
}