{
  "type": "Feature",
  "properties": {
    "iso:country":"CA",
    "sg:address":"Hazel St",
    "sg:city":"Sidney",
    "sg:classifiers":[
        {
            "category":"Organizations",
            "subcategory":"Professional Association",
            "type":"Services"
        }
    ],
    "sg:phone":"+1 204 466 2750",
    "sg:postcode":"R0H 1L0",
    "sg:province":"MB",
    "sg:tags":[
        "club"
    ],
    "wof:name":"Sidney Community Ctr",
    "wof:placetype":"venue"
},
  "geometry": {"coordinates":[-99.0853271484,49.8994560242],"type":"Point"}
}