{
  "type": "Feature",
  "properties": {
    "iso:country":"CA",
    "sg:address":"3215 School Ave",
    "sg:city":"Vancouver",
    "sg:classifiers":[
        {
            "category":"Organizations",
            "subcategory":"Religious Organization",
            "type":"Services"
        }
    ],
    "sg:phone":"+1 604 434 8227",
    "sg:postcode":"V5R 5N2",
    "sg:province":"BC",
    "sg:tags":[
        "church"
    ],
    "wof:name":"Bethel Chinese Christian MB",
    "wof:placetype":"venue"
},
  "geometry": {"coordinates":[-123.036605835,49.2328529358],"type":"Point"}
}