{
  "type": "Feature",
  "properties": {
    "addr:full":"2476 Old Montreal Rd Cumberland ON K4C 1G6",
    "addr:housenumber":"2476",
    "addr:postcode":"k4c 1g6",
    "addr:street":"Old Montreal Rd",
    "iso:country":"CA",
    "sg:address":"2476 Old Montreal Rd",
    "sg:city":"Cumberland",
    "sg:classifiers":[
        {
            "category":"Organizations",
            "subcategory":"Religious Organization",
            "type":"Services"
        }
    ],
    "sg:phone":"+1 613 833 8326",
    "sg:postcode":"K4C 1G6",
    "sg:province":"ON",
    "sg:tags":[
        "church"
    ],
    "wof:name":"St Mark's Anglican Church",
    "wof:placetype":"venue"
},
  "geometry": {"coordinates":[-75.41213999999999,45.516022],"type":"Point"}
}