{
  "type": "Feature",
  "properties": {
    "addr:full":"7475 Boul Newman Lasalle QC H8N 1X3",
    "addr:housenumber":"7475",
    "addr:postcode":"h8n 1x3",
    "addr:street":"Boul Newman",
    "iso:country":"CA",
    "sg:address":"7475 Boul Newman",
    "sg:city":"Lasalle",
    "sg:classifiers":[
        {
            "category":"Real Estate",
            "subcategory":"Real Estate Agent",
            "type":"Services"
        }
    ],
    "sg:phone":"+1 514 363 4151",
    "sg:postcode":"H8N 1X3",
    "sg:province":"QC",
    "sg:tags":[
        "management"
    ],
    "wof:name":"Rio Can Fonds DE Placement",
    "wof:placetype":"venue"
},
  "geometry": {"coordinates":[-73.62101,45.440498],"type":"Point"}
}