{
  "type": "Feature",
  "properties": {
    "iso:country":"CA",
    "sg:address":"1224 Chaster Rd",
    "sg:city":"Gibsons",
    "sg:classifiers":[
        {
            "category":"Government",
            "subcategory":"Office",
            "type":"Public Place"
        }
    ],
    "sg:phone":"+1 604 886 0303",
    "sg:postcode":"V0N 1V4",
    "sg:province":"BC",
    "wof:name":"Sunshine Coast Frank West Hall",
    "wof:placetype":"venue"
},
  "geometry": {"coordinates":[-123.519691467,49.3922615051],"type":"Point"}
}