{
  "type": "Feature",
  "properties": {
    "addr:full":"9996 Rte 16 Guysborough NS B0H 1N0",
    "addr:housenumber":"9996",
    "addr:postcode":"b0h 1n0",
    "addr:street":"Rte 16",
    "iso:country":"CA",
    "sg:address":"9996 Rte 16",
    "sg:city":"Guysborough",
    "sg:classifiers":[
        {
            "category":"Food & Beverages",
            "subcategory":"Groceries & Convenience Stores",
            "type":"Retail Goods"
        }
    ],
    "sg:phone":"+1 902 533 4070",
    "sg:postcode":"B0H 1N0",
    "sg:province":"NS",
    "sg:tags":[
        "grocer"
    ],
    "wof:name":"Avery's Save Easy",
    "wof:placetype":"venue"
},
  "geometry": {"coordinates":[-61.503704071,45.3976325989],"type":"Point"}
}