{
  "type": "Feature",
  "properties": {
    "addr:full":"Brooks AB T1R 0M8",
    "addr:postcode":"t1r 0m8",
    "iso:country":"CA",
    "sg:city":"Brooks",
    "sg:classifiers":[
        {
            "category":"Real Estate",
            "subcategory":"Real Estate Operator",
            "type":"Services"
        }
    ],
    "sg:phone":"+1 403 362 5108",
    "sg:postcode":"T1R 0M8",
    "sg:province":"AB",
    "sg:tags":[
        "apartment"
    ],
    "wof:name":"Willowbrook Estates",
    "wof:placetype":"venue"
},
  "geometry": {"coordinates":[-111.892105102,50.5722122192],"type":"Point"}
}