{
  "type": "Feature",
  "properties": {
    "addr:full":"1659 Victoria St N # 12 Kitchener ON N2B 3E6",
    "addr:housenumber":"1659;12",
    "addr:postcode":"n2b 3e6",
    "addr:street":"Victoria St N #",
    "iso:country":"CA",
    "sg:address":"1659 Victoria St N # 12",
    "sg:city":"Kitchener",
    "sg:classifiers":[
        {
            "category":"Home & Garden",
            "subcategory":"Carpets & Floor Coverings",
            "type":"Retail Goods"
        }
    ],
    "sg:phone":"+1 519 579 5110",
    "sg:postcode":"N2B 3E6",
    "sg:province":"ON",
    "sg:tags":[
        "resurfacing",
        "laying",
        "refinishing",
        "rug"
    ],
    "wof:name":"Forever Custom Flooring Store",
    "wof:placetype":"venue"
},
  "geometry": {"coordinates":[-80.433182,43.474426],"type":"Point"}
}