{
  "type": "Feature",
  "properties": {
    "addr:full":"4904 50 St Camrose AB T4V 1R1",
    "addr:housenumber":"4904",
    "addr:postcode":"t4v 1r1",
    "addr:street":"50 St",
    "iso:country":"CA",
    "sg:address":"4904 50 St",
    "sg:city":"Camrose",
    "sg:classifiers":[
        {
            "category":"Freight",
            "type":"Transportation"
        }
    ],
    "sg:phone":"+1 780 672 9702",
    "sg:postcode":"T4V 1R1",
    "sg:province":"AB",
    "sg:tags":[
        "courier"
    ],
    "wof:name":"Camrose Purolator Depot",
    "wof:placetype":"venue"
},
  "geometry": {"coordinates":[-112.825417,53.020943],"type":"Point"}
}