{
  "type": "Feature",
  "properties": {
    "addr:full":"New Glasgow NS B2H 4Z6",
    "addr:postcode":"b2h 4z6",
    "iso:country":"CA",
    "sg:city":"New Glasgow",
    "sg:classifiers":[
        {
            "category":"Manufacturing",
            "subcategory":"Tools & Machinery",
            "type":"Manufacturing & Wholesale Goods"
        }
    ],
    "sg:phone":"+1 902 755 3000",
    "sg:postcode":"B2H 4Z6",
    "sg:province":"NS",
    "sg:tags":[
        "machine",
        "shop"
    ],
    "wof:name":"Darteg Industries",
    "wof:placetype":"venue"
},
  "geometry": {"coordinates":[-62.643409729,45.5918312073],"type":"Point"}
}