{
  "type": "Feature",
  "properties": {
    "iso:country":"CA",
    "sg:address":"160 Spruce Ave",
    "sg:city":"Elliot Lake",
    "sg:classifiers":[
        {
            "category":"Social Services",
            "subcategory":"Child Care",
            "type":"Services"
        }
    ],
    "sg:phone":"+1 705 848 4904",
    "sg:postcode":"P5A 2C5",
    "sg:province":"ON",
    "wof:name":"Little Treasures Children's",
    "wof:placetype":"venue"
},
  "geometry": {"coordinates":[-82.6590957642,46.392250061],"type":"Point"}
}