{
  "type": "Feature",
  "properties": {
    "addr:full":"2915 St Clair Ave E East York ON M4B 1N9",
    "addr:housenumber":"2915",
    "addr:postcode":"m4b 1n9",
    "addr:street":"St Clair Ave E",
    "iso:country":"CA",
    "sg:address":"2915 St Clair Ave E",
    "sg:city":"East York",
    "sg:classifiers":[
        {
            "category":"Autos & Motor Vehicles",
            "subcategory":"Fuel & Gas Station",
            "type":"Retail Goods"
        }
    ],
    "sg:phone":"+1 416 759 3257",
    "sg:postcode":"M4B 1N9",
    "sg:province":"ON",
    "sg:tags":[
        "oil"
    ],
    "wof:name":"Ultramar Gas Station",
    "wof:placetype":"venue"
},
  "geometry": {"coordinates":[-79.30027771,43.7080802917],"type":"Point"}
}