{
  "type": "Feature",
  "properties": {
    "addr:full":"4803 Saint Clair Ave Niagara Falls ON L2E 3T3",
    "addr:housenumber":"4803",
    "addr:postcode":"l2e 3t3",
    "addr:street":"Saint Clair Ave",
    "iso:country":"CA",
    "sg:address":"4803 Saint Clair Ave",
    "sg:city":"Niagara Falls",
    "sg:classifiers":[
        {
            "category":"Food & Beverages",
            "subcategory":"Groceries & Convenience Stores",
            "type":"Retail Goods"
        }
    ],
    "sg:phone":"+1 905 354 6110",
    "sg:postcode":"L2E 3T3",
    "sg:province":"ON",
    "sg:tags":[
        "grocer"
    ],
    "wof:name":"Frasers Grocery",
    "wof:placetype":"venue"
},
  "geometry": {"coordinates":[-79.06701700000001,43.104538],"type":"Point"}
}