{
  "type": "Feature",
  "properties": {
    "addr:full":"1362 Rue Sherbrooke E Montreal QC H2L 1M4",
    "addr:housenumber":"1362",
    "addr:postcode":"h2l 1m4",
    "addr:street":"Rue Sherbrooke E",
    "iso:country":"CA",
    "sg:address":"1362 Rue Sherbrooke E",
    "sg:city":"Montreal",
    "sg:classifiers":[
        {
            "category":"Health Services",
            "subcategory":"Doctor",
            "type":"Services"
        }
    ],
    "sg:phone":"+1 514 528 7555",
    "sg:postcode":"H2L 1M4",
    "sg:province":"QC",
    "sg:tags":[
        "physician",
        "surgeon"
    ],
    "wof:name":"Leclerc, Francine MD",
    "wof:placetype":"venue"
},
  "geometry": {"coordinates":[-73.5647201538,45.5248565674],"type":"Point"}
}