{
  "type": "Feature",
  "properties": {
    "addr:full":"4741 Montrose St Port Alberni BC V9Y 1M7",
    "addr:housenumber":"4741",
    "addr:postcode":"v9y 1m7",
    "addr:street":"Montrose St",
    "iso:country":"CA",
    "sg:address":"4741 Montrose St",
    "sg:city":"Port Alberni",
    "sg:classifiers":[
        {
            "category":"Organizations",
            "subcategory":"Religious Organization",
            "type":"Services"
        }
    ],
    "sg:phone":"+1 250 723 9112",
    "sg:postcode":"V9Y 1M7",
    "sg:province":"BC",
    "sg:tags":[
        "church"
    ],
    "wof:name":"Alberni Valley Gurdawara Scty",
    "wof:placetype":"venue"
},
  "geometry": {"coordinates":[-124.80394,49.230667],"type":"Point"}
}