{
  "type": "Feature",
  "properties": {
    "addr:full":"827 Danforth Pl Burlington ON L7T 1S1",
    "addr:housenumber":"827",
    "addr:postcode":"l7t 1s1",
    "addr:street":"Danforth Pl",
    "iso:country":"CA",
    "sg:address":"827 Danforth Pl",
    "sg:city":"Burlington",
    "sg:classifiers":[
        {
            "category":"Wholesale",
            "subcategory":"Chemicals & Plastics",
            "type":"Manufacturing & Wholesale Goods"
        }
    ],
    "sg:phone":"+1 905 522 7949",
    "sg:postcode":"L7T 1S1",
    "sg:province":"ON",
    "sg:tags":[
        "undercoating",
        "automobile",
        "rustproofing",
        "remover",
        "preventive",
        "rust"
    ],
    "wof:name":"Northern Shield Protective",
    "wof:placetype":"venue"
},
  "geometry": {"coordinates":[-79.85967254640001,43.2941055298],"type":"Point"}
}