{
  "type": "Feature",
  "properties": {
    "addr:full":"1001 Rang Saint-Malo Sainte-Marthe-Du-Cap QC G8V 1X4",
    "addr:housenumber":"1001",
    "addr:postcode":"g8v 1x4",
    "addr:street":"Rang Saint-Malo",
    "iso:country":"CA",
    "sg:address":"1001 Rang Saint-Malo",
    "sg:city":"Sainte-Marthe-Du-Cap",
    "sg:classifiers":[
        {
            "category":"Government",
            "subcategory":"Office",
            "type":"Public Place"
        }
    ],
    "sg:phone":"+1 819 378 5949",
    "sg:postcode":"G8V 1X4",
    "sg:province":"QC",
    "sg:tags":[
        "village"
    ],
    "wof:name":"Ville DE Ste-Marthe-Du-Cap",
    "wof:placetype":"venue"
},
  "geometry": {"coordinates":[-72.5107269287,46.3919067383],"type":"Point"}
}