{
  "type": "Feature",
  "properties": {
    "iso:country":"CA",
    "sg:address":"47 Bendingroad Cres",
    "sg:city":"St Catharines",
    "sg:classifiers":[
        {
            "category":"Building & Trades",
            "subcategory":"Electrical",
            "type":"Services"
        }
    ],
    "sg:phone":"+1 905 935 0154",
    "sg:postcode":"L2N 5R4",
    "sg:province":"ON",
    "sg:tags":[
        "electric",
        "contractor"
    ],
    "wof:name":"Bcr Electric",
    "wof:placetype":"venue"
},
  "geometry": {"coordinates":[-79.2506561279,43.1882667542],"type":"Point"}
}