{
  "type": "Feature",
  "properties": {
    "addr:full":"520 Rue Sagard Saint-Bruno QC J3V 6C2",
    "addr:housenumber":"520",
    "addr:postcode":"j3v 6c2",
    "addr:street":"Rue Sagard",
    "iso:country":"CA",
    "sg:address":"520 Rue Sagard",
    "sg:city":"Saint-Bruno",
    "sg:classifiers":[
        {
            "category":"Retail",
            "subcategory":"Auto Repair",
            "type":"Services"
        }
    ],
    "sg:phone":"+1 450 441 2893",
    "sg:postcode":"J3V 6C2",
    "sg:province":"QC",
    "sg:tags":[
        "truck"
    ],
    "wof:name":"Soudure & Suspension St-Bruno",
    "wof:placetype":"venue"
},
  "geometry": {"coordinates":[-71.67552185060001,48.4717712402],"type":"Point"}
}