{
  "type": "Feature",
  "properties": {
    "addr:full":"164 Sherbrooke St Peterborough ON K9J 2N3",
    "addr:housenumber":"164",
    "addr:postcode":"k9j 2n3",
    "addr:street":"Sherbrooke St",
    "iso:country":"CA",
    "sg:address":"164 Sherbrooke St",
    "sg:city":"Peterborough",
    "sg:classifiers":[
        {
            "category":"Social Services",
            "type":"Services"
        }
    ],
    "sg:phone":"+1 705 742 9800",
    "sg:postcode":"K9J 2N3",
    "sg:province":"ON",
    "sg:tags":[
        "organization",
        "welfare"
    ],
    "wof:name":"Good Neighbours Care Ctr",
    "wof:placetype":"venue"
},
  "geometry": {"coordinates":[-78.320183,44.300907],"type":"Point"}
}