{
  "type": "Feature",
  "properties": {
    "addr:full":"1823 11th Ave E Vancouver BC V5N 1Y9",
    "addr:housenumber":"1823",
    "addr:postcode":"v5n 1y9",
    "addr:street":"11Th Ave E",
    "iso:country":"CA",
    "sg:address":"1823 11th Ave E",
    "sg:city":"Vancouver",
    "sg:classifiers":[
        {
            "category":"Real Estate",
            "subcategory":"Real Estate Agent",
            "type":"Services"
        }
    ],
    "sg:phone":"+1 604 708 5450",
    "sg:postcode":"V5N 1Y9",
    "sg:province":"BC",
    "sg:tags":[
        "cooperative"
    ],
    "wof:name":"Victoria Gardens Housing CO-OP",
    "wof:placetype":"venue"
},
  "geometry": {"coordinates":[-123.067428589,49.2606086731],"type":"Point"}
}