{
  "type": "Feature",
  "properties": {
    "addr:full":"208 Bloor St W Toronto ON M5S 3B4",
    "addr:housenumber":"208",
    "addr:postcode":"m5s 3b4",
    "addr:street":"Bloor St W",
    "iso:country":"CA",
    "sg:address":"208 Bloor St W",
    "sg:city":"Toronto",
    "sg:classifiers":[
        {
            "category":"Restaurant",
            "type":"Food & Drink"
        }
    ],
    "sg:phone":"+1 416 922 2345",
    "sg:postcode":"M5S 3B4",
    "sg:province":"ON",
    "wof:name":"Over Easy",
    "wof:placetype":"venue"
},
  "geometry": {"coordinates":[-79.39590454099999,43.6684646606],"type":"Point"}
}