{
  "type": "Feature",
  "properties": {
    "addr:full":"Vancouver BC V6B 2P6",
    "addr:postcode":"v6b 2p6",
    "iso:country":"CA",
    "sg:city":"Vancouver",
    "sg:classifiers":[
        {
            "category":"Professional",
            "subcategory":"Business Services",
            "type":"Services"
        }
    ],
    "sg:phone":"+1 604 682 8781",
    "sg:postcode":"V6B 2P6",
    "sg:province":"BC",
    "sg:tags":[
        "interior",
        "consultant",
        "design",
        "decorator"
    ],
    "wof:name":"2112 Innerspace CO Ltd",
    "wof:placetype":"venue"
},
  "geometry": {"coordinates":[-123.116165,49.277172],"type":"Point"}
}