{
  "type": "Feature",
  "properties": {
    "addr:full":"5225 Rue DE Courcelette Trois-Rivieres-Ouest QC G8Y 4L4",
    "addr:housenumber":"5225",
    "addr:postcode":"g8y 4l4",
    "addr:street":"Rue De Courcelette Trois-Rivieres-Ouest",
    "iso:country":"CA",
    "sg:address":"5225 Rue DE Courcelette",
    "sg:city":"Trois-Rivieres-Ouest",
    "sg:classifiers":[
        {
            "category":"Organizations",
            "subcategory":"Professional Association",
            "type":"Services"
        }
    ],
    "sg:phone":"+1 819 379 9211",
    "sg:postcode":"G8Y 4L4",
    "sg:province":"QC",
    "wof:name":"Organisation Du Hockey Mineur",
    "wof:placetype":"venue"
},
  "geometry": {"coordinates":[-72.59326934809999,46.3322525024],"type":"Point"}
}