{
  "type": "Feature",
  "properties": {
    "addr:full":"Valleyview AB T0H 3N0",
    "addr:postcode":"t0h 3n0",
    "iso:country":"CA",
    "sg:city":"Valleyview",
    "sg:classifiers":[
        {
            "category":"Organizations",
            "subcategory":"Religious Organization",
            "type":"Services"
        }
    ],
    "sg:phone":"+1 780 524 3855",
    "sg:postcode":"T0H 3N0",
    "sg:province":"AB",
    "sg:tags":[
        "church"
    ],
    "wof:name":"Church of Jesus Christ-Lds",
    "wof:placetype":"venue"
},
  "geometry": {"coordinates":[-117.286293,55.068047],"type":"Point"}
}