{
  "type": "Feature",
  "properties": {
    "addr:full":"900 Boul Rene-Levesque O Quebec QC G1S 1T6",
    "addr:housenumber":"900",
    "addr:postcode":"g1s 1t6",
    "addr:street":"Boul Rene-Levesque O",
    "iso:country":"CA",
    "sg:address":"900 Boul Rene-Levesque O",
    "sg:city":"Quebec",
    "sg:classifiers":[
        {
            "category":"Food & Beverages",
            "subcategory":"Groceries & Convenience Stores",
            "type":"Retail Goods"
        }
    ],
    "sg:phone":"+1 418 527 0565",
    "sg:postcode":"G1S 1T6",
    "sg:province":"QC",
    "sg:tags":[
        "grocer"
    ],
    "wof:name":"Couche-Tard",
    "wof:placetype":"venue"
},
  "geometry": {"coordinates":[-71.2159042358,46.8097877502],"type":"Point"}
}