{
  "type": "Feature",
  "properties": {
    "addr:full":"983 Chilver Rd Windsor ON N8Y 2K6",
    "addr:housenumber":"983",
    "addr:postcode":"n8y 2k6",
    "addr:street":"Chilver Rd",
    "iso:country":"CA",
    "sg:address":"983 Chilver Rd",
    "sg:city":"Windsor",
    "sg:classifiers":[
        {
            "category":"Professional",
            "subcategory":"Accounting & Tax Preparation",
            "type":"Services"
        }
    ],
    "sg:phone":"+1 519 977 4203",
    "sg:postcode":"N8Y 2K6",
    "sg:province":"ON",
    "sg:tags":[
        "accountant"
    ],
    "wof:name":"Anderson Financial Svc",
    "wof:placetype":"venue"
},
  "geometry": {"coordinates":[-83.011185,42.317451],"type":"Point"}
}