{
  "type": "Feature",
  "properties": {
    "iso:country":"CA",
    "sg:city":"Scarborough",
    "sg:classifiers":[
        {
            "category":"Manufacturing",
            "subcategory":"Printing",
            "type":"Manufacturing & Wholesale Goods"
        }
    ],
    "sg:phone":"+1 416 298 9226",
    "sg:postcode":"M1V 5A5",
    "sg:province":"ON",
    "sg:tags":[
        "printer"
    ],
    "wof:name":"29 Print Machine",
    "wof:placetype":"venue"
},
  "geometry": {"coordinates":[-79.25174713129999,43.8236503601],"type":"Point"}
}