{
  "type": "Feature",
  "properties": {
    "addr:full":"91 Lakeshore Rd E Mississauga ON L5G 1E2",
    "addr:housenumber":"91",
    "addr:postcode":"l5g 1e2",
    "addr:street":"Lakeshore Rd E",
    "iso:country":"CA",
    "sg:address":"91 Lakeshore Rd E",
    "sg:city":"Mississauga",
    "sg:classifiers":[
        {
            "category":"Real Estate",
            "subcategory":"Real Estate Agent",
            "type":"Services"
        }
    ],
    "sg:phone":"+1 905 278 8840",
    "sg:postcode":"L5G 1E2",
    "sg:province":"ON",
    "wof:name":"Re Max",
    "wof:placetype":"venue"
},
  "geometry": {"coordinates":[-79.58390799999999,43.553089],"type":"Point"}
}