{
  "type": "Feature",
  "properties": {
    "addr:full":"5020 26 Ave NE Calgary AB T1Y 1E1",
    "addr:housenumber":"5020",
    "addr:postcode":"t1y 1e1",
    "addr:street":"26 Ave Ne",
    "iso:country":"CA",
    "sg:address":"5020 26 Ave NE",
    "sg:city":"Calgary",
    "sg:classifiers":[
        {
            "category":"Government",
            "subcategory":"Office",
            "type":"Public Place"
        }
    ],
    "sg:phone":"+1 403 268 3830",
    "sg:postcode":"T1Y 1E1",
    "sg:province":"AB",
    "sg:tags":[
        "village"
    ],
    "wof:name":"Optimist Athletic Parks",
    "wof:placetype":"venue"
},
  "geometry": {"coordinates":[-113.962677,51.07655],"type":"Point"}
}