{
  "type": "Feature",
  "properties": {
    "addr:full":"4098 Ch Forest Rawdon QC J0K 1S0",
    "addr:housenumber":"4098",
    "addr:postcode":"j0k 1s0",
    "addr:street":"Ch Forest",
    "iso:country":"CA",
    "sg:address":"4098 Ch Forest",
    "sg:city":"Rawdon",
    "sg:classifiers":[
        {
            "category":"Building & Trades",
            "subcategory":"Plumbing",
            "type":"Services"
        }
    ],
    "sg:phone":"+1 450 752 7990",
    "sg:postcode":"J0K 1S0",
    "sg:province":"QC",
    "sg:tags":[
        "conditioning",
        "air",
        "system",
        "contractor"
    ],
    "wof:name":"Climatisation Sansregret Inc",
    "wof:placetype":"venue"
},
  "geometry": {"coordinates":[-73.689995,46.065891],"type":"Point"}
}