{
  "type": "Feature",
  "properties": {
    "addr:full":"Calgary AB T2H 2K1",
    "addr:postcode":"t2h 2k1",
    "iso:country":"CA",
    "sg:city":"Calgary",
    "sg:classifiers":[
        {
            "category":"Retail",
            "subcategory":"Auto Repair",
            "type":"Services"
        }
    ],
    "sg:phone":"+1 403 258 0211",
    "sg:postcode":"T2H 2K1",
    "sg:province":"AB",
    "sg:tags":[
        "repairing",
        "engine"
    ],
    "wof:name":"Safety Seal/Wesco",
    "wof:placetype":"venue"
},
  "geometry": {"coordinates":[-114.034988,50.99876],"type":"Point"}
}