{
  "type": "Feature",
  "properties": {
    "addr:full":"230 Southgate Dr Guelph ON N1G 4P5",
    "addr:housenumber":"230",
    "addr:postcode":"n1g 4p5",
    "addr:street":"Southgate Dr",
    "iso:country":"CA",
    "sg:address":"230 Southgate Dr",
    "sg:city":"Guelph",
    "sg:classifiers":[
        {
            "category":"Manufacturing",
            "subcategory":"Tools & Machinery",
            "type":"Manufacturing & Wholesale Goods"
        }
    ],
    "sg:phone":"+1 519 763 2241",
    "sg:postcode":"N1G 4P5",
    "sg:province":"ON",
    "sg:tags":[
        "machine",
        "shop"
    ],
    "wof:name":"Miknar Machine Inc",
    "wof:placetype":"venue"
},
  "geometry": {"coordinates":[-80.21408081049999,43.5003395081],"type":"Point"}
}