{
  "type": "Feature",
  "properties": {
    "addr:full":"788 Yonge St Midland ON L4R 2E6",
    "addr:housenumber":"788",
    "addr:postcode":"l4r 2e6",
    "addr:street":"Yonge St",
    "iso:country":"CA",
    "sg:address":"788 Yonge St",
    "sg:city":"Midland",
    "sg:classifiers":[
        {
            "category":"Recreation",
            "subcategory":"Amusement Park",
            "type":"Entertainment"
        }
    ],
    "sg:phone":"+1 705 528 7077",
    "sg:postcode":"L4R 2E6",
    "sg:province":"ON",
    "wof:name":"Fun Stop",
    "wof:placetype":"venue"
},
  "geometry": {"coordinates":[-79.89474487299999,44.7419242859],"type":"Point"}
}