{
  "type": "Feature",
  "properties": {
    "addr:full":"61 Hamilton Dr Calgary AB T3R 1A2",
    "addr:housenumber":"61",
    "addr:postcode":"t3r 1a2",
    "addr:street":"Hamilton Dr",
    "iso:country":"CA",
    "sg:address":"61 Hamilton Dr",
    "sg:city":"Calgary",
    "sg:classifiers":[
        {
            "category":"Recreation",
            "type":"Entertainment"
        }
    ],
    "sg:phone":"+1 403 239 8474",
    "sg:postcode":"T3R 1A2",
    "sg:province":"AB",
    "sg:tags":[
        "course",
        "golf"
    ],
    "wof:name":"Bearspaw Country Club",
    "wof:placetype":"venue"
},
  "geometry": {"coordinates":[-114.263321,51.157333],"type":"Point"}
}