{
  "type": "Feature",
  "properties": {
    "addr:full":"821 Av Sainte-Croix Saint-Laurent QC H4L 3X9",
    "addr:postcode":"h4l 3x9",
    "addr:street":"821 Av Sainte-Croix",
    "iso:country":"CA",
    "sg:address":"821 Av Sainte-Croix",
    "sg:city":"Saint-Laurent",
    "sg:classifiers":[
        {
            "category":"Education",
            "subcategory":"College",
            "type":"Public Place"
        }
    ],
    "sg:phone":"+1 514 744 7500",
    "sg:postcode":"H4L 3X9",
    "sg:province":"QC",
    "sg:tags":[
        "academic",
        "school"
    ],
    "wof:name":"Cegep Vanier College",
    "wof:placetype":"venue"
},
  "geometry": {"coordinates":[-73.67607099999999,45.514065],"type":"Point"}
}