{
  "type": "Feature",
  "properties": {
    "iso:country":"CA",
    "sg:address":"8371 Boul Lasalle",
    "sg:city":"Lasalle",
    "sg:classifiers":[
        {
            "category":"Building & Trades",
            "subcategory":"Electrical",
            "type":"Services"
        }
    ],
    "sg:phone":"+1 514 366 8602",
    "sg:postcode":"H8P 1Y6",
    "sg:province":"QC",
    "sg:tags":[
        "electric",
        "contractor"
    ],
    "wof:name":"Providence Eletrique Inc",
    "wof:placetype":"venue"
},
  "geometry": {"coordinates":[-73.61056518549999,45.4166946411],"type":"Point"}
}