{
  "type": "Feature",
  "properties": {
    "addr:full":"Saint-Eustache QC J7R 5B7",
    "addr:postcode":"j7r 5b7",
    "iso:country":"CA",
    "sg:city":"Saint-Eustache",
    "sg:classifiers":[
        {
            "category":"Home & Garden",
            "subcategory":"Furniture",
            "type":"Retail Goods"
        }
    ],
    "sg:phone":"+1 450 491 0613",
    "sg:postcode":"J7R 5B7",
    "sg:province":"QC",
    "sg:tags":[
        "kitchen",
        "cabinet"
    ],
    "wof:name":"Ateliers St-Pierre Inc",
    "wof:placetype":"venue"
},
  "geometry": {"coordinates":[-73.9168930054,45.5698242188],"type":"Point"}
}