{
  "type": "Feature",
  "properties": {
    "iso:country":"CA",
    "sg:address":"2930 Rue Laplume",
    "sg:city":"Sorel-Tracy",
    "sg:classifiers":[
        {
            "category":"Wholesale",
            "subcategory":"Machinery & Supplies",
            "type":"Manufacturing & Wholesale Goods"
        }
    ],
    "sg:phone":"+1 450 742 8770",
    "sg:postcode":"J3R 2R1",
    "sg:province":"QC",
    "sg:tags":[
        "equipment",
        "steam",
        "cleaning"
    ],
    "wof:name":"Menage Express Enr",
    "wof:placetype":"venue"
},
  "geometry": {"coordinates":[-73.1507034302,46.0251731873],"type":"Point"}
}