{
  "type": "Feature",
  "properties": {
    "addr:full":"1177 Factory St SE Medicine Hat AB T1A 8N8",
    "addr:housenumber":"1177",
    "addr:postcode":"t1a 8n8",
    "addr:street":"Factory St Se",
    "iso:country":"CA",
    "sg:address":"1177 Factory St SE",
    "sg:city":"Medicine Hat",
    "sg:classifiers":[
        {
            "category":"Home & Garden",
            "subcategory":"Building Materials",
            "type":"Retail Goods"
        }
    ],
    "sg:phone":"+1 403 529 1786",
    "sg:postcode":"T1A 8N8",
    "sg:province":"AB",
    "sg:tags":[
        "door"
    ],
    "wof:name":"Southern Door Sales Ltd",
    "wof:placetype":"venue"
},
  "geometry": {"coordinates":[-110.656799316,50.0279350281],"type":"Point"}
}