{
  "type": "Feature",
  "properties": {
    "iso:country":"CA",
    "sg:address":"1819 Av Dollard",
    "sg:city":"Lasalle",
    "sg:classifiers":[
        {
            "category":"Health Services",
            "subcategory":"Doctor",
            "type":"Services"
        }
    ],
    "sg:phone":"+1 514 367 4597",
    "sg:postcode":"H8N 1T9",
    "sg:province":"QC",
    "sg:tags":[
        "dentist"
    ],
    "wof:name":"Clinique Dentaire Brochu",
    "wof:placetype":"venue"
},
  "geometry": {"coordinates":[-73.63231658940001,45.4295349121],"type":"Point"}
}