{
  "type": "Feature",
  "properties": {
    "addr:full":"2180 Ponderosa Ave Kamloops BC V2B 4V9",
    "addr:housenumber":"2180",
    "addr:postcode":"bc v2b 4v9",
    "addr:street":"Ponderosa Ave",
    "iso:country":"CA",
    "sg:address":"2180 Ponderosa Ave",
    "sg:city":"Kamloops",
    "sg:classifiers":[
        {
            "category":"Shopping",
            "type":"Retail Goods"
        }
    ],
    "sg:phone":"+1 250 554 2156",
    "sg:postcode":"V2B 4V9",
    "sg:province":"BC",
    "sg:tags":[
        "awning",
        "builder",
        "canopy",
        "deck"
    ],
    "wof:name":"Abco Waterproofing & Sundck",
    "wof:placetype":"venue"
},
  "geometry": {"coordinates":[-120.40660095200001,50.7066459656],"type":"Point"}
}