{
  "type": "Feature",
  "properties": {
    "iso:country":"CA",
    "sg:address":"6020 Rue Jean-Talon E",
    "sg:city":"Saint-Leonard",
    "sg:classifiers":[
        {
            "category":"Health Services",
            "subcategory":"Doctor",
            "type":"Services"
        }
    ],
    "sg:phone":"+1 514 253 2273",
    "sg:postcode":"H1S 3B1",
    "sg:province":"QC",
    "sg:tags":[
        "physician",
        "surgeon"
    ],
    "wof:name":"Feldman, Marcel MD",
    "wof:placetype":"venue"
},
  "geometry": {"coordinates":[-73.578529,45.587299],"type":"Point"}
}