{
  "type": "Feature",
  "properties": {
    "addr:full":"1195 Rte 101 N Saint-Bruno-DE-Guigues QC J0Z 2G0",
    "addr:housenumber":"1195",
    "addr:postcode":"j0z 2g0",
    "addr:street":"Rte 101 N Saint-Bruno-De-Guigues",
    "iso:country":"CA",
    "sg:address":"1195 Rte 101 N",
    "sg:city":"Saint-Bruno-DE-Guigues",
    "sg:classifiers":[
        {
            "category":"Recreation",
            "type":"Entertainment"
        }
    ],
    "sg:phone":"+1 819 728 2816",
    "sg:postcode":"J0Z 2G0",
    "sg:province":"QC",
    "sg:tags":[
        "mobile",
        "discotheque",
        "stable"
    ],
    "wof:name":"Ecurie Donleo",
    "wof:placetype":"venue"
},
  "geometry": {"coordinates":[-79.43843099999999,47.514614],"type":"Point"}
}