{
  "type": "Feature",
  "properties": {
    "addr:full":"10512 135A St Surrey BC V3T 4E1",
    "addr:housenumber":"10512",
    "addr:postcode":"v3t 4e1",
    "addr:street":"135A St",
    "iso:country":"CA",
    "sg:address":"10512 135A St",
    "sg:city":"Surrey",
    "sg:classifiers":[
        {
            "category":"Autos & Motor Vehicles",
            "subcategory":"Automobile Sales",
            "type":"Retail Goods"
        }
    ],
    "sg:phone":"+1 604 584 8555",
    "sg:postcode":"V3T 4E1",
    "sg:province":"BC",
    "sg:tags":[
        "car",
        "dealer"
    ],
    "wof:name":"Able Car & Truck Sales Ltd",
    "wof:placetype":"venue"
},
  "geometry": {"coordinates":[-122.830215454,49.105178833],"type":"Point"}
}