{
  "type": "Feature",
  "properties": {
    "addr:full":"PO Box 286 Gogama ON P0M 1W0",
    "addr:housenumber":"po;286",
    "addr:postcode":"p0m 1w0",
    "addr:street":"Box",
    "iso:country":"CA",
    "sg:address":"PO Box 286",
    "sg:city":"Gogama",
    "sg:classifiers":[
        {
            "category":"Organizations",
            "subcategory":"Religious Organization",
            "type":"Services"
        }
    ],
    "sg:phone":"+1 705 894 2140",
    "sg:postcode":"P0M 1W0",
    "sg:province":"ON",
    "sg:tags":[
        "church"
    ],
    "wof:name":"Mattagami New Covenant Church",
    "wof:placetype":"venue"
},
  "geometry": {"coordinates":[-81.7227096558,47.6751365662],"type":"Point"}
}