{
  "type": "Feature",
  "properties": {
    "addr:full":"285 Augusta Ave Toronto ON M5T 2M1",
    "addr:housenumber":"285",
    "addr:postcode":"m5t 2m1",
    "addr:street":"Augusta Ave",
    "iso:country":"CA",
    "sg:address":"285 Augusta Ave",
    "sg:city":"Toronto",
    "sg:classifiers":[
        {
            "category":"Food & Beverages",
            "subcategory":"Fruits & Vegetables",
            "type":"Retail Goods"
        }
    ],
    "sg:phone":"+1 416 597 2300",
    "sg:postcode":"M5T 2M1",
    "sg:province":"ON",
    "wof:name":"Romeo's Fruity Fruit Inc",
    "wof:placetype":"venue"
},
  "geometry": {"coordinates":[-79.40248099999999,43.656013],"type":"Point"}
}