{
  "type": "Feature",
  "properties": {
    "addr:full":"4105 Lawrence Ave E Scarborough ON M1E 5K2",
    "addr:housenumber":"4105",
    "addr:postcode":"m1e 5k2",
    "addr:street":"Lawrence Ave E",
    "iso:country":"CA",
    "sg:address":"4105 Lawrence Ave E",
    "sg:city":"Scarborough",
    "sg:classifiers":[
        {
            "category":"Social Services",
            "subcategory":"Child Care",
            "type":"Services"
        }
    ],
    "sg:phone":"+1 416 438 5989",
    "sg:postcode":"M1E 5K2",
    "sg:province":"ON",
    "wof:name":"Growing Steps",
    "wof:placetype":"venue"
},
  "geometry": {"coordinates":[-79.1951828003,43.7663078308],"type":"Point"}
}