{
  "type": "Feature",
  "properties": {
    "addr:full":"100 Main St Picton ON K0K 2T0",
    "addr:housenumber":"100",
    "addr:postcode":"k0k 2t0",
    "addr:street":"Main St",
    "iso:country":"CA",
    "sg:address":"100 Main St",
    "sg:city":"Picton",
    "sg:classifiers":[
        {
            "category":"Shopping",
            "subcategory":"Used Merchandise",
            "type":"Retail Goods"
        }
    ],
    "sg:phone":"+1 613 476 1667",
    "sg:postcode":"K0K 2T0",
    "sg:province":"ON",
    "sg:tags":[
        "antique"
    ],
    "wof:name":"Loyalist Antiques & Fine Art",
    "wof:placetype":"venue"
},
  "geometry": {"coordinates":[-77.146309,44.004997],"type":"Point"}
}