{
  "type": "Feature",
  "properties": {
    "addr:full":"8191 Jane St Concord ON L4K 5P2",
    "addr:housenumber":"8191",
    "addr:postcode":"l4k 5p2",
    "addr:street":"Jane St",
    "iso:country":"CA",
    "sg:address":"8191 Jane St",
    "sg:city":"Concord",
    "sg:classifiers":[
        {
            "category":"Building & Trades",
            "subcategory":"Cleaning & Sanitation",
            "type":"Services"
        }
    ],
    "sg:phone":"+1 905 669 6565",
    "sg:postcode":"L4K 5P2",
    "sg:province":"ON",
    "sg:tags":[
        "janitor"
    ],
    "wof:name":"Nova Services Group Inc",
    "wof:placetype":"venue"
},
  "geometry": {"coordinates":[-79.5267562866,43.805721283],"type":"Point"}
}