{
  "type": "Feature",
  "properties": {
    "addr:full":"704 King St W Kingston ON K7M 2G2",
    "addr:housenumber":"704",
    "addr:postcode":"k7m 2g2",
    "addr:street":"King St W",
    "iso:country":"CA",
    "sg:address":"704 King St W",
    "sg:city":"Kingston",
    "sg:classifiers":[
        {
            "category":"Food & Beverages",
            "subcategory":"Bakery",
            "type":"Retail Goods"
        }
    ],
    "sg:phone":"+1 613 545 1016",
    "sg:postcode":"K7M 2G2",
    "sg:province":"ON",
    "sg:tags":[
        "doughnut"
    ],
    "wof:name":"Tim Hortons",
    "wof:placetype":"venue"
},
  "geometry": {"coordinates":[-76.5209274292,44.2205352783],"type":"Point"}
}