{
  "type": "Feature",
  "properties": {
    "iso:country":"CA",
    "sg:address":"103 Rue Principale",
    "sg:city":"Aylmer",
    "sg:classifiers":[
        {
            "category":"Shopping",
            "type":"Retail Goods"
        }
    ],
    "sg:phone":"+1 819 682 6186",
    "sg:postcode":"J9H 3L9",
    "sg:province":"QC",
    "sg:tags":[
        "art",
        "gallery",
        "dealer"
    ],
    "wof:name":"Galerie D'Art Epoque",
    "wof:placetype":"venue"
},
  "geometry": {"coordinates":[-75.8457946777,45.394985199],"type":"Point"}
}