{
  "type": "Feature",
  "properties": {
    "addr:full":"1507 20 St Coaldale AB T1M 1J7",
    "addr:housenumber":"1507",
    "addr:postcode":"t1m 1j7",
    "addr:street":"20 St",
    "iso:country":"CA",
    "sg:address":"1507 20 St",
    "sg:city":"Coaldale",
    "sg:classifiers":[
        {
            "category":"Government",
            "subcategory":"Fire Station",
            "type":"Public Place"
        }
    ],
    "sg:phone":"+1 403 345 1330",
    "sg:postcode":"T1M 1J7",
    "sg:province":"AB",
    "sg:tags":[
        "department"
    ],
    "wof:name":"Coaldale Fire Dept",
    "wof:placetype":"venue"
},
  "geometry": {"coordinates":[-112.62247467,49.7330360413],"type":"Point"}
}