{
  "type": "Feature",
  "properties": {
    "addr:full":"4268 Yonge St Gilford ON L0L 1R0",
    "addr:housenumber":"4268",
    "addr:postcode":"l0l 1r0",
    "addr:street":"Yonge St",
    "iso:country":"CA",
    "sg:address":"4268 Yonge St",
    "sg:city":"Gilford",
    "sg:classifiers":[
        {
            "category":"Wholesale",
            "subcategory":"Durable Goods & Equipment",
            "type":"Manufacturing & Wholesale Goods"
        }
    ],
    "sg:phone":"+1 905 775 5805",
    "sg:postcode":"L0L 1R0",
    "sg:province":"ON",
    "sg:tags":[
        "sawdust",
        "shaving"
    ],
    "wof:name":"Reliable Wood Shavings Ltd",
    "wof:placetype":"venue"
},
  "geometry": {"coordinates":[-79.584473,44.195141],"type":"Point"}
}