{
  "type": "Feature",
  "properties": {
    "addr:full":"95 Dolomite Dr North York ON M3J 2N1",
    "addr:housenumber":"95",
    "addr:postcode":"m3j 2n1",
    "addr:street":"Dolomite Dr",
    "iso:country":"CA",
    "sg:address":"95 Dolomite Dr",
    "sg:city":"North York",
    "sg:classifiers":[
        {
            "category":"Retail",
            "subcategory":"Repair Shop",
            "type":"Services"
        }
    ],
    "sg:phone":"+1 416 665 8887",
    "sg:postcode":"M3J 2N1",
    "sg:province":"ON",
    "sg:tags":[
        "upholsterer"
    ],
    "wof:name":"Grand Dukes Design Upholstery",
    "wof:placetype":"venue"
},
  "geometry": {"coordinates":[-79.471954,43.780231],"type":"Point"}
}