{
  "type": "Feature",
  "properties": {
    "addr:full":"251 Leon Ave Kelowna BC V1Y 6J1",
    "addr:housenumber":"251",
    "addr:postcode":"v1y 6j1",
    "addr:street":"Leon Ave",
    "iso:country":"CA",
    "sg:address":"251 Leon Ave",
    "sg:city":"Kelowna",
    "sg:classifiers":[
        {
            "category":"Social Services",
            "type":"Services"
        }
    ],
    "sg:phone":"+1 250 763 3737",
    "sg:postcode":"V1Y 6J1",
    "sg:province":"BC",
    "sg:tags":[
        "organization",
        "hostel",
        "welfare"
    ],
    "wof:name":"Kelowna Gospel Mission",
    "wof:placetype":"venue"
},
  "geometry": {"coordinates":[-119.497970581,49.8843803406],"type":"Point"}
}