{
  "type": "Feature",
  "properties": {
    "addr:full":"1304 Rue Principale Saint-Dominique QC J0H 1L0",
    "addr:housenumber":"1304",
    "addr:postcode":"j0h 1l0",
    "addr:street":"Rue Principale",
    "iso:country":"CA",
    "sg:address":"1304 Rue Principale",
    "sg:city":"Saint-Dominique",
    "sg:classifiers":[
        {
            "category":"Retail",
            "subcategory":"Auto Repair",
            "type":"Services"
        }
    ],
    "sg:phone":"+1 450 773 6003",
    "sg:postcode":"J0H 1L0",
    "sg:province":"QC",
    "sg:tags":[
        "truck"
    ],
    "wof:name":"Garage Chagnon & Fils Inc",
    "wof:placetype":"venue"
},
  "geometry": {"coordinates":[-72.848274,45.560825],"type":"Point"}
}