{
  "type": "Feature",
  "properties": {
    "addr:full":"1586 Broadway W Vancouver BC V6J 5K9",
    "addr:housenumber":"1586",
    "addr:postcode":"v6j 5k9",
    "addr:street":"Broadway W",
    "iso:country":"CA",
    "sg:address":"1586 Broadway W",
    "sg:city":"Vancouver",
    "sg:classifiers":[
        {
            "category":"Insurance",
            "subcategory":"Insurance Agent",
            "type":"Services"
        }
    ],
    "sg:phone":"+1 604 734 7722",
    "sg:postcode":"V6J 5K9",
    "sg:province":"BC",
    "wof:name":"Buntain Insurance Ltd",
    "wof:placetype":"venue"
},
  "geometry": {"coordinates":[-123.140724182,49.2635307312],"type":"Point"}
}