{
  "type": "Feature",
  "properties": {
    "addr:full":"Richmond BC V6V 1W1",
    "addr:postcode":"v6v 1w1",
    "iso:country":"CA",
    "sg:city":"Richmond",
    "sg:classifiers":[
        {
            "category":"Wholesale",
            "subcategory":"Chemicals & Plastics",
            "type":"Manufacturing & Wholesale Goods"
        }
    ],
    "sg:phone":"+1 604 270 2252",
    "sg:postcode":"V6V 1W1",
    "sg:province":"BC",
    "wof:name":"Anachemia Science",
    "wof:placetype":"venue"
},
  "geometry": {"coordinates":[-123.073425293,49.1873893738],"type":"Point"}
}