{
  "type": "Feature",
  "properties": {
    "iso:country":"CA",
    "sg:address":"PO Box 415",
    "sg:city":"Trochu",
    "sg:classifiers":[
        {
            "category":"Organizations",
            "subcategory":"Religious Organization",
            "type":"Services"
        }
    ],
    "sg:phone":"+1 403 442 4363",
    "sg:postcode":"T0M 2C0",
    "sg:province":"AB",
    "sg:tags":[
        "church"
    ],
    "wof:name":"St Anne's Catholic Church",
    "wof:placetype":"venue"
},
  "geometry": {"coordinates":[-113.237632752,51.8237037659],"type":"Point"}
}