{
  "type": "Feature",
  "properties": {
    "addr:full":"Mississauga ON L4W 4Y6",
    "addr:postcode":"l4w 4y6",
    "iso:country":"CA",
    "sg:city":"Mississauga",
    "sg:classifiers":[
        {
            "category":"Wholesale",
            "subcategory":"Groceries",
            "type":"Manufacturing & Wholesale Goods"
        }
    ],
    "sg:phone":"+1 905 625 9306",
    "sg:postcode":"L4W 4Y6",
    "sg:province":"ON",
    "sg:tags":[
        "food",
        "broker"
    ],
    "wof:name":"A S May Powell Corp",
    "wof:placetype":"venue"
},
  "geometry": {"coordinates":[-79.601463,43.65593],"type":"Point"}
}