{
  "type": "Feature",
  "properties": {
    "addr:full":"1200 Plains Rd E Burlington ON L7S 1W6",
    "addr:housenumber":"1200",
    "addr:postcode":"l7s 1w6",
    "addr:street":"Plains Rd E",
    "iso:country":"CA",
    "sg:address":"1200 Plains Rd E",
    "sg:city":"Burlington",
    "sg:classifiers":[
        {
            "category":"Freight",
            "type":"Transportation"
        }
    ],
    "sg:phone":"+1 905 632 8010",
    "sg:postcode":"L7S 1W6",
    "sg:province":"ON",
    "sg:tags":[
        "mover"
    ],
    "wof:name":"A Taylor Moving & Storage Ltd",
    "wof:placetype":"venue"
},
  "geometry": {"coordinates":[-79.823166,43.331116],"type":"Point"}
}