{
  "type": "Feature",
  "properties": {
    "addr:full":"2 Robert Speck Pky # 590 Mississauga ON L4Z 1H8",
    "addr:housenumber":"2",
    "addr:postcode":"l4z 1h8",
    "addr:street":"Robert Speck Pky # 590",
    "iso:country":"CA",
    "sg:address":"2 Robert Speck Pky # 590",
    "sg:city":"Mississauga",
    "sg:classifiers":[
        {
            "category":"Professional",
            "subcategory":"Lawyer & Legal Services",
            "type":"Services"
        }
    ],
    "sg:phone":"+1 905 276 9000",
    "sg:postcode":"L4Z 1H8",
    "sg:province":"ON",
    "sg:tags":[
        "attorney"
    ],
    "wof:name":"Turkstra Mazza Reininger Assoc",
    "wof:placetype":"venue"
},
  "geometry": {"coordinates":[-79.637939,43.596294],"type":"Point"}
}