{
  "type": "Feature",
  "properties": {
    "addr:full":"5944 Perth St Richmond ON K0A 2Z0",
    "addr:housenumber":"5944",
    "addr:postcode":"k0a 2z0",
    "addr:street":"Perth St",
    "iso:country":"CA",
    "sg:address":"5944 Perth St",
    "sg:city":"Richmond",
    "sg:classifiers":[
        {
            "category":"Shopping",
            "subcategory":"Gifts & Souvenirs",
            "type":"Retail Goods"
        }
    ],
    "sg:phone":"+1 613 838 5252",
    "sg:postcode":"K0A 2Z0",
    "sg:province":"ON",
    "sg:tags":[
        "basket",
        "parcel"
    ],
    "wof:name":"Simple Pleasures",
    "wof:placetype":"venue"
},
  "geometry": {"coordinates":[-75.8302078247,45.1997680664],"type":"Point"}
}