{
  "type": "Feature",
  "properties": {
    "iso:country":"CA",
    "sg:address":"19 Jennifer Cres",
    "sg:city":"St Catharines",
    "sg:classifiers":[
        {
            "category":"Building & Trades",
            "subcategory":"Cleaning & Sanitation",
            "type":"Services"
        }
    ],
    "sg:phone":"+1 905 646 5175",
    "sg:postcode":"L2M 7Y9",
    "sg:province":"ON",
    "sg:tags":[
        "butler",
        "maid",
        "house"
    ],
    "wof:name":"Helping Hands Maid Svc",
    "wof:placetype":"venue"
},
  "geometry": {"coordinates":[-79.206245,43.184799],"type":"Point"}
}