{
  "type": "Feature",
  "properties": {
    "addr:full":"5764 176 St Surrey BC V3S 4C8",
    "addr:housenumber":"5764",
    "addr:postcode":"v3s 4c8",
    "addr:street":"176 St",
    "iso:country":"CA",
    "sg:address":"5764 176 St",
    "sg:city":"Surrey",
    "sg:classifiers":[
        {
            "category":"Shopping",
            "subcategory":"Used Merchandise",
            "type":"Retail Goods"
        }
    ],
    "sg:phone":"+1 604 576 0088",
    "sg:postcode":"V3S 4C8",
    "sg:province":"BC",
    "sg:tags":[
        "antique"
    ],
    "wof:name":"Hometown Antiques",
    "wof:placetype":"venue"
},
  "geometry": {"coordinates":[-122.734909,49.10397],"type":"Point"}
}