{
  "type": "Feature",
  "properties": {
    "addr:full":"Abbotsford BC V2T 6H5",
    "addr:postcode":"v2t 6h5",
    "iso:country":"CA",
    "sg:city":"Abbotsford",
    "sg:classifiers":[
        {
            "category":"Building & Trades",
            "subcategory":"Equipment Rental",
            "type":"Services"
        }
    ],
    "sg:phone":"+1 604 850 0262",
    "sg:postcode":"V2T 6H5",
    "sg:province":"BC",
    "sg:tags":[
        "aircraft",
        "leasing",
        "charter",
        "school"
    ],
    "wof:name":"Abbotsford Flight Ctr",
    "wof:placetype":"venue"
},
  "geometry": {"coordinates":[-122.37795300000001,49.026787],"type":"Point"}
}