{
  "type": "Feature",
  "properties": {
    "addr:full":"640 Riverbend Dr Kitchener ON N2K 3S2",
    "addr:housenumber":"640",
    "addr:postcode":"n2k 3s2",
    "addr:street":"Riverbend Dr",
    "iso:country":"CA",
    "sg:address":"640 Riverbend Dr",
    "sg:city":"Kitchener",
    "sg:classifiers":[
        {
            "category":"Professional",
            "subcategory":"Management & Consulting",
            "type":"Services"
        }
    ],
    "sg:phone":"+1 519 579 7749",
    "sg:postcode":"N2K 3S2",
    "sg:province":"ON",
    "sg:tags":[
        "sharing",
        "profit",
        "consultant",
        "benefit",
        "pension",
        "employee",
        "plan"
    ],
    "wof:name":"Corporate Benefit Analysts Inc",
    "wof:placetype":"venue"
},
  "geometry": {"coordinates":[-80.4796829224,43.4752235413],"type":"Point"}
}