{
  "type": "Feature",
  "properties": {
    "addr:full":"310 Rue Robitaille Granby QC J2G 9J6",
    "addr:housenumber":"310",
    "addr:postcode":"j2g 9j6",
    "addr:street":"Rue Robitaille",
    "iso:country":"CA",
    "sg:address":"310 Rue Robitaille",
    "sg:city":"Granby",
    "sg:classifiers":[
        {
            "category":"Travel",
            "subcategory":"Campground",
            "type":"Entertainment"
        }
    ],
    "sg:phone":"+1 450 372 6639",
    "sg:postcode":"J2G 9J6",
    "sg:province":"QC",
    "wof:name":"Camping Granby",
    "wof:placetype":"venue"
},
  "geometry": {"coordinates":[-72.68245697019999,45.3847427368],"type":"Point"}
}