{
  "type": "Feature",
  "properties": {
    "addr:full":"783 Rue Pierre-Laviolette Nicolet QC J3T 1J5",
    "addr:housenumber":"783",
    "addr:postcode":"j3t 1j5",
    "addr:street":"Rue Pierre-Laviolette",
    "iso:country":"CA",
    "sg:address":"783 Rue Pierre-Laviolette",
    "sg:city":"Nicolet",
    "sg:classifiers":[
        {
            "category":"Building & Trades",
            "subcategory":"Electrical",
            "type":"Services"
        }
    ],
    "sg:phone":"+1 819 293 5523",
    "sg:postcode":"J3T 1J5",
    "sg:province":"QC",
    "sg:tags":[
        "electric",
        "contractor"
    ],
    "wof:name":"Jean Caron & Fils Inc",
    "wof:placetype":"venue"
},
  "geometry": {"coordinates":[-72.602592,46.228065],"type":"Point"}
}