{
  "type": "Feature",
  "properties": {
    "iso:country":"CA",
    "sg:address":"596 Kingston Rd W",
    "sg:city":"Ajax",
    "sg:classifiers":[
        {
            "category":"Wholesale",
            "subcategory":"Sporting Goods",
            "type":"Manufacturing & Wholesale Goods"
        }
    ],
    "sg:phone":"+1 905 426 9900",
    "sg:postcode":"L1T 3A2",
    "sg:province":"ON",
    "sg:tags":[
        "salon",
        "tanning"
    ],
    "wof:name":"Cool Rays Tanning & Esthetics",
    "wof:placetype":"venue"
},
  "geometry": {"coordinates":[-79.0551986694,43.8547096252],"type":"Point"}
}