{
  "type": "Feature",
  "properties": {
    "addr:full":"Antigonish NS B2G 2K8",
    "addr:postcode":"b2g 2k8",
    "iso:country":"CA",
    "sg:city":"Antigonish",
    "sg:classifiers":[
        {
            "category":"Building & Trades",
            "subcategory":"Construction",
            "type":"Services"
        }
    ],
    "sg:phone":"+1 902 863 4748",
    "sg:postcode":"B2G 2K8",
    "sg:province":"NS",
    "sg:tags":[
        "general",
        "contractor"
    ],
    "wof:name":"Carsen Enterprises Ltd",
    "wof:placetype":"venue"
},
  "geometry": {"coordinates":[-61.9942703247,45.6221885681],"type":"Point"}
}