{
  "type": "Feature",
  "properties": {
    "addr:full":"5585 Av DE Monkland Montreal QC H4A 1E1",
    "addr:housenumber":"5585",
    "addr:postcode":"h4a 1e1",
    "addr:street":"Av De Monkland",
    "iso:country":"CA",
    "sg:address":"5585 Av DE Monkland",
    "sg:city":"Montreal",
    "sg:classifiers":[
        {
            "category":"Travel",
            "subcategory":"Campground",
            "type":"Entertainment"
        }
    ],
    "sg:phone":"+1 514 488 8920",
    "sg:postcode":"H4A 1E1",
    "sg:province":"QC",
    "sg:tags":[
        "camp"
    ],
    "wof:name":"Westcoast Connection Travel",
    "wof:placetype":"venue"
},
  "geometry": {"coordinates":[-73.622688,45.475964],"type":"Point"}
}