{
  "type": "Feature",
  "properties": {
    "addr:full":"Vancouver BC V6A 2V1",
    "addr:postcode":"v6a 2v1",
    "iso:country":"CA",
    "sg:city":"Vancouver",
    "sg:classifiers":[
        {
            "category":"Health Services",
            "subcategory":"Doctor",
            "type":"Services"
        }
    ],
    "sg:phone":"+1 604 684 2128",
    "sg:postcode":"V6A 2V1",
    "sg:province":"BC",
    "sg:tags":[
        "physician",
        "surgeon"
    ],
    "wof:name":"Jue, P MD",
    "wof:placetype":"venue"
},
  "geometry": {"coordinates":[-123.09992200000001,49.280014],"type":"Point"}
}