{
  "type": "Feature",
  "properties": {
    "addr:full":"34 Matheson St S Kenora ON P9N 1T6",
    "addr:housenumber":"34",
    "addr:postcode":"p9n 1t6",
    "addr:street":"Matheson St S",
    "iso:country":"CA",
    "sg:address":"34 Matheson St S",
    "sg:city":"Kenora",
    "sg:classifiers":[
        {
            "category":"Health Services",
            "subcategory":"Doctor",
            "type":"Services"
        }
    ],
    "sg:phone":"+1 807 468 6421",
    "sg:postcode":"P9N 1T6",
    "sg:province":"ON",
    "sg:tags":[
        "dentist"
    ],
    "wof:name":"Montero, Elizabeth DDS",
    "wof:placetype":"venue"
},
  "geometry": {"coordinates":[-94.48830413819999,49.7677955627],"type":"Point"}
}