{
  "type": "Feature",
  "properties": {
    "addr:full":"583 King St N # 3 Waterloo ON N2V 2E5",
    "addr:housenumber":"583",
    "addr:postcode":"n2v 2e5",
    "addr:street":"King St N # 3",
    "iso:country":"CA",
    "sg:address":"583 King St N # 3",
    "sg:city":"Waterloo",
    "sg:classifiers":[
        {
            "category":"Personal",
            "type":"Services"
        }
    ],
    "sg:phone":"+1 519 884 9518",
    "sg:postcode":"N2V 2E5",
    "sg:province":"ON",
    "sg:tags":[
        "program",
        "physical",
        "exercise",
        "fitness"
    ],
    "wof:name":"Curves For Women",
    "wof:placetype":"venue"
},
  "geometry": {"coordinates":[-80.53383636469999,43.5018997192],"type":"Point"}
}