{
  "type": "Feature",
  "properties": {
    "iso:country":"CA",
    "sg:address":"2225 41st Ave W",
    "sg:city":"Vancouver",
    "sg:classifiers":[
        {
            "category":"Shopping",
            "subcategory":"Pharmacy",
            "type":"Retail Goods"
        }
    ],
    "sg:phone":"+1 604 266 5344",
    "sg:postcode":"V6M 2A3",
    "sg:province":"BC",
    "wof:name":"Shoppers Drug Mart",
    "wof:placetype":"venue"
},
  "geometry": {"coordinates":[-123.158828735,49.2347412109],"type":"Point"}
}