{
  "type": "Feature",
  "properties": {
    "addr:full":"941 Kingston Rd Toronto ON M4E 1S8",
    "addr:housenumber":"941",
    "addr:postcode":"m4e 1s8",
    "addr:street":"Kingston Rd",
    "iso:country":"CA",
    "sg:address":"941 Kingston Rd",
    "sg:city":"Toronto",
    "sg:classifiers":[
        {
            "category":"Food & Beverages",
            "subcategory":"Bakery",
            "type":"Retail Goods"
        }
    ],
    "sg:phone":"+1 416 699 2025",
    "sg:postcode":"M4E 1S8",
    "sg:province":"ON",
    "sg:tags":[
        "baker"
    ],
    "wof:name":"Pastry Shop",
    "wof:placetype":"venue"
},
  "geometry": {"coordinates":[-79.28800964360001,43.6803627014],"type":"Point"}
}