{
  "type": "Feature",
  "properties": {
    "addr:full":"422 6th Ave New Denver BC V0G 1S0",
    "addr:housenumber":"422",
    "addr:postcode":"v0g 1s0",
    "addr:street":"6Th Ave",
    "iso:country":"CA",
    "sg:address":"422 6th Ave",
    "sg:city":"New Denver",
    "sg:classifiers":[
        {
            "category":"Shopping",
            "subcategory":"Clothing, Apparel, & Fashions",
            "type":"Retail Goods"
        }
    ],
    "sg:phone":"+1 250 358 2255",
    "sg:postcode":"V0G 1S0",
    "sg:province":"BC",
    "sg:tags":[
        "infant",
        "wear"
    ],
    "wof:name":"Carol's Corner",
    "wof:placetype":"venue"
},
  "geometry": {"coordinates":[-117.377205,49.991547],"type":"Point"}
}