{
  "type": "Feature",
  "properties": {
    "addr:full":"181 Cocksfield Ave North York ON M3H 3T4",
    "addr:housenumber":"181",
    "addr:postcode":"m3h 3t4",
    "addr:street":"Cocksfield Ave",
    "iso:country":"CA",
    "sg:address":"181 Cocksfield Ave",
    "sg:city":"North York",
    "sg:classifiers":[
        {
            "category":"Communications",
            "subcategory":"Film & Video Production",
            "type":"Services"
        }
    ],
    "sg:phone":"+1 416 916 7896",
    "sg:postcode":"M3H 3T4",
    "sg:province":"ON",
    "sg:tags":[
        "motion",
        "picture",
        "studio",
        "producer"
    ],
    "wof:name":"Libran Entertainment Corp",
    "wof:placetype":"venue"
},
  "geometry": {"coordinates":[-79.4512176514,43.7540740967],"type":"Point"}
}