{
  "type": "Feature",
  "properties": {
    "addr:full":"59 Main St E Ridgetown ON N0P 2C0",
    "addr:housenumber":"59",
    "addr:postcode":"n0p 2c0",
    "addr:street":"Main St E",
    "iso:country":"CA",
    "sg:address":"59 Main St E",
    "sg:city":"Ridgetown",
    "sg:classifiers":[
        {
            "category":"Organizations",
            "subcategory":"Religious Organization",
            "type":"Services"
        }
    ],
    "sg:phone":"+1 519 674 3487",
    "sg:postcode":"N0P 2C0",
    "sg:province":"ON",
    "sg:tags":[
        "church"
    ],
    "wof:name":"MT Zion Presbyterian Church",
    "wof:placetype":"venue"
},
  "geometry": {"coordinates":[-81.885223,42.440338],"type":"Point"}
}