{
  "type": "Feature",
  "properties": {
    "iso:country":"CA",
    "sg:address":"225 Main St N",
    "sg:city":"Vita",
    "sg:classifiers":[
        {
            "category":"Arena",
            "subcategory":"Sports Club",
            "type":"Entertainment"
        }
    ],
    "sg:phone":"+1 204 425 3189",
    "sg:postcode":"R0A 2K0",
    "sg:province":"MB",
    "sg:tags":[
        "athletic",
        "fields",
        "stadium"
    ],
    "wof:name":"Vita Arena",
    "wof:placetype":"venue"
},
  "geometry": {"coordinates":[-96.5628814697,49.1333847046],"type":"Point"}
}