{
  "type": "Feature",
  "properties": {
    "addr:full":"Etobicoke ON M9B 6J1",
    "addr:postcode":"m9b 6j1",
    "iso:country":"CA",
    "sg:city":"Etobicoke",
    "sg:classifiers":[
        {
            "category":"Health Services",
            "subcategory":"Doctor",
            "type":"Services"
        }
    ],
    "sg:phone":"+1 416 234 8060",
    "sg:postcode":"M9B 6J1",
    "sg:province":"ON",
    "sg:tags":[
        "dentist"
    ],
    "wof:name":"Yuen, Sek Lun DDS",
    "wof:placetype":"venue"
},
  "geometry": {"coordinates":[-79.552605,43.631866],"type":"Point"}
}