{
  "type": "Feature",
  "properties": {
    "addr:full":"1412 Princess St Kingston ON K7M 3E5",
    "addr:housenumber":"1412",
    "addr:postcode":"k7m 3e5",
    "addr:street":"Princess St",
    "iso:country":"CA",
    "sg:address":"1412 Princess St",
    "sg:city":"Kingston",
    "sg:classifiers":[
        {
            "category":"Social Services",
            "type":"Services"
        }
    ],
    "sg:phone":"+1 613 546 6613",
    "sg:postcode":"K7M 3E5",
    "sg:province":"ON",
    "sg:tags":[
        "organization",
        "welfare"
    ],
    "wof:name":"Community Living Kingston",
    "wof:placetype":"venue"
},
  "geometry": {"coordinates":[-76.532928,44.250935],"type":"Point"}
}