{
  "type": "Feature",
  "properties": {
    "addr:full":"Brampton ON L7A 1C5",
    "addr:postcode":"l7a 1c5",
    "iso:country":"CA",
    "sg:city":"Brampton",
    "sg:classifiers":[
        {
            "category":"Home & Garden",
            "subcategory":"Building Materials",
            "type":"Retail Goods"
        }
    ],
    "sg:phone":"+1 905 840 6906",
    "sg:postcode":"L7A 1C5",
    "sg:province":"ON",
    "sg:tags":[
        "type",
        "door"
    ],
    "wof:name":"Westwood Garage Doors Ltd",
    "wof:placetype":"venue"
},
  "geometry": {"coordinates":[-79.80255099999999,43.702389],"type":"Point"}
}