{
  "type": "Feature",
  "properties": {
    "addr:full":"Montreal QC H3G 1M8",
    "addr:postcode":"h3g 1m8",
    "iso:country":"CA",
    "sg:city":"Montreal",
    "sg:classifiers":[
        {
            "category":"Manufacturing",
            "subcategory":"Printing",
            "type":"Manufacturing & Wholesale Goods"
        }
    ],
    "sg:phone":"+1 514 848 7406",
    "sg:postcode":"H3G 1M8",
    "sg:province":"QC",
    "sg:tags":[
        "newspaper"
    ],
    "wof:name":"Link Concordia University",
    "wof:placetype":"venue"
},
  "geometry": {"coordinates":[-73.57884216310001,45.4968452454],"type":"Point"}
}