{
  "type": "Feature",
  "properties": {
    "addr:full":"815 Rue Cormier Drummondville QC J2C 6P7",
    "addr:housenumber":"815",
    "addr:postcode":"j2c 6p7",
    "addr:street":"Rue Cormier",
    "iso:country":"CA",
    "sg:address":"815 Rue Cormier",
    "sg:city":"Drummondville",
    "sg:classifiers":[
        {
            "category":"Real Estate",
            "subcategory":"Real Estate Agent",
            "type":"Services"
        }
    ],
    "sg:phone":"+1 819 477 0488",
    "sg:postcode":"J2C 6P7",
    "sg:province":"QC",
    "sg:tags":[
        "agency",
        "rental"
    ],
    "wof:name":"Motelin Inc",
    "wof:placetype":"venue"
},
  "geometry": {"coordinates":[-72.514122,45.887352],"type":"Point"}
}