{
  "type": "Feature",
  "properties": {
    "iso:country":"CA",
    "sg:address":"1430 Ottawa St",
    "sg:city":"Windsor",
    "sg:classifiers":[
        {
            "category":"Restaurant",
            "type":"Food & Drink"
        }
    ],
    "sg:phone":"+1 519 252 2615",
    "sg:postcode":"N8X 2G2",
    "sg:province":"ON",
    "wof:name":"Lee's Villa Restaurant",
    "wof:placetype":"venue"
},
  "geometry": {"coordinates":[-83.0108795166,42.3104743958],"type":"Point"}
}