{
  "type": "Feature",
  "properties": {
    "addr:full":"2200 Boul Marcel-Laurin Saint-Laurent QC H4R 1J9",
    "addr:housenumber":"2200",
    "addr:postcode":"h4r 1j9",
    "addr:street":"Boul Marcel-Laurin",
    "iso:country":"CA",
    "sg:address":"2200 Boul Marcel-Laurin",
    "sg:city":"Saint-Laurent",
    "sg:classifiers":[
        {
            "category":"Retail",
            "subcategory":"Auto Repair",
            "type":"Services"
        }
    ],
    "sg:phone":"+1 514 331 7211",
    "sg:postcode":"H4R 1J9",
    "sg:province":"QC",
    "sg:tags":[
        "repairing",
        "automobile"
    ],
    "wof:name":"Entreprises R Monaco Inc",
    "wof:placetype":"venue"
},
  "geometry": {"coordinates":[-73.703209,45.519348],"type":"Point"}
}