{
  "type": "Feature",
  "properties": {
    "iso:country":"CA",
    "sg:address":"1450 Boul Hymus",
    "sg:city":"Dorval",
    "sg:classifiers":[
        {
            "category":"Professional",
            "subcategory":"Business Services",
            "type":"Services"
        }
    ],
    "sg:phone":"+1 514 685 2611",
    "sg:postcode":"H9P 1J6",
    "sg:province":"QC",
    "sg:tags":[
        "arbitration"
    ],
    "wof:name":"Guy E Dulude & Assoc",
    "wof:placetype":"venue"
},
  "geometry": {"coordinates":[-73.77015686039999,45.4856033325],"type":"Point"}
}