{
  "type": "Feature",
  "properties": {
    "addr:full":"Brampton ON L6T 3J1",
    "addr:postcode":"l6t 3j1",
    "iso:country":"CA",
    "sg:city":"Brampton",
    "sg:classifiers":[
        {
            "category":"Social Services",
            "subcategory":"Job Training",
            "type":"Services"
        }
    ],
    "sg:phone":"+1 905 799 3200",
    "sg:postcode":"L6T 3J1",
    "sg:province":"ON",
    "sg:tags":[
        "rehabilitation"
    ],
    "wof:name":"Act Health Group Corp",
    "wof:placetype":"venue"
},
  "geometry": {"coordinates":[-79.711815,43.727352],"type":"Point"}
}