{
  "type": "Feature",
  "properties": {
    "addr:full":"293 Fountain St Winnipeg MB R3A 0Z6",
    "addr:housenumber":"293",
    "addr:postcode":"r3a 0z6",
    "addr:street":"Fountain St",
    "iso:country":"CA",
    "sg:address":"293 Fountain St",
    "sg:city":"Winnipeg",
    "sg:classifiers":[
        {
            "category":"Retail",
            "subcategory":"Repair Shop",
            "type":"Services"
        }
    ],
    "sg:phone":"+1 204 947 1823",
    "sg:postcode":"R3A 0Z6",
    "sg:province":"MB",
    "sg:tags":[
        "welding"
    ],
    "wof:name":"Superb Heli-Arc Welding",
    "wof:placetype":"venue"
},
  "geometry": {"coordinates":[-97.1414489746,49.9048500061],"type":"Point"}
}