{
  "type": "Feature",
  "properties": {
    "addr:full":"Portage LA Prairie MB R1N 0L1",
    "addr:postcode":"r1n 0l1",
    "iso:country":"CA",
    "sg:city":"Portage LA Prairie",
    "sg:classifiers":[
        {
            "category":"Shopping",
            "subcategory":"Florist",
            "type":"Retail Goods"
        }
    ],
    "sg:phone":"+1 204 857 6886",
    "sg:postcode":"R1N 0L1",
    "sg:province":"MB",
    "wof:name":"Mil-Jeanne Flowers",
    "wof:placetype":"venue"
},
  "geometry": {"coordinates":[-98.289658,49.973167],"type":"Point"}
}