{
  "type": "Feature",
  "properties": {
    "addr:full":"89 Main St Saint John NB E2K 1H2",
    "addr:housenumber":"89",
    "addr:postcode":"e2k 1h2",
    "addr:street":"Main St",
    "iso:country":"CA",
    "sg:address":"89 Main St",
    "sg:city":"Saint John",
    "sg:classifiers":[
        {
            "category":"Manufacturing",
            "subcategory":"Food",
            "type":"Manufacturing & Wholesale Goods"
        }
    ],
    "sg:phone":"+1 506 635 7000",
    "sg:postcode":"E2K 1H2",
    "sg:province":"NB",
    "sg:tags":[
        "brewer"
    ],
    "wof:name":"Moosehead Breweries Ltd",
    "wof:placetype":"venue"
},
  "geometry": {"coordinates":[-66.08563995359999,45.2751922607],"type":"Point"}
}