{
  "type": "Feature",
  "properties": {
    "addr:full":"11213 88 Ave Fort Saskatchewan AB T8L 2X4",
    "addr:housenumber":"11213",
    "addr:postcode":"t8l 2x4",
    "addr:street":"88 Ave",
    "iso:country":"CA",
    "sg:address":"11213 88 Ave",
    "sg:city":"Fort Saskatchewan",
    "sg:classifiers":[
        {
            "category":"Retail",
            "subcategory":"Auto Rental",
            "type":"Services"
        }
    ],
    "sg:phone":"+1 780 992 3123",
    "sg:postcode":"T8L 2X4",
    "sg:province":"AB",
    "sg:tags":[
        "renting",
        "truck",
        "leasing"
    ],
    "wof:name":"U-Haul CO Ltd",
    "wof:placetype":"venue"
},
  "geometry": {"coordinates":[-113.193291,53.708111],"type":"Point"}
}