{
  "type": "Feature",
  "properties": {
    "iso:country":"CA",
    "sg:city":"Montreal",
    "sg:classifiers":[
        {
            "category":"Restaurant",
            "type":"Food & Drink"
        }
    ],
    "sg:phone":"+1 514 871 1017",
    "sg:postcode":"H3B 2V6",
    "sg:province":"QC",
    "sg:tags":[
        "delicatessen"
    ],
    "wof:name":"Stecchino",
    "wof:placetype":"venue"
},
  "geometry": {"coordinates":[-73.569847,45.49968],"type":"Point"}
}