{
  "type": "Feature",
  "properties": {
    "addr:full":"Etobicoke ON M9W 6K5",
    "addr:postcode":"m9w 6k5",
    "iso:country":"CA",
    "sg:city":"Etobicoke",
    "sg:classifiers":[
        {
            "category":"Restaurant",
            "type":"Food & Drink"
        }
    ],
    "sg:phone":"+1 416 674 5584",
    "sg:postcode":"M9W 6K5",
    "sg:province":"ON",
    "wof:name":"Manchu Wok",
    "wof:placetype":"venue"
},
  "geometry": {"coordinates":[-79.596985,43.71785],"type":"Point"}
}