{
  "type": "Feature",
  "properties": {
    "addr:full":"1981 Av Mcgill College # 1600 Montreal QC H3A 2Y3",
    "addr:housenumber":"1981;#",
    "addr:postcode":"h3a 2y3",
    "addr:street":"Av Mcgill College",
    "iso:country":"CA",
    "sg:address":"1981 Av Mcgill College # 1600",
    "sg:city":"Montreal",
    "sg:classifiers":[
        {
            "category":"Professional",
            "subcategory":"Business Services",
            "type":"Services"
        }
    ],
    "sg:phone":"+1 514 849 0476",
    "sg:postcode":"H3A 2Y3",
    "sg:province":"QC",
    "sg:tags":[
        "drafting"
    ],
    "wof:name":"P Illustration B Ltee",
    "wof:placetype":"venue"
},
  "geometry": {"coordinates":[-73.57326500000001,45.5033],"type":"Point"}
}