{
  "type": "Feature",
  "properties": {
    "addr:full":"1835 Park St Regina SK S4N 2G4",
    "addr:housenumber":"1835",
    "addr:postcode":"s4n 2g4",
    "addr:street":"Park St",
    "iso:country":"CA",
    "sg:address":"1835 Park St",
    "sg:city":"Regina",
    "sg:classifiers":[
        {
            "category":"Retail",
            "subcategory":"Auto Repair",
            "type":"Services"
        }
    ],
    "sg:phone":"+1 306 352 3943",
    "sg:postcode":"S4N 2G4",
    "sg:province":"SK",
    "sg:tags":[
        "transmission",
        "automobile",
        "repairing"
    ],
    "wof:name":"Transmission Warehouse Inc",
    "wof:placetype":"venue"
},
  "geometry": {"coordinates":[-104.57197600000001,50.449791],"type":"Point"}
}