{
  "type": "Feature",
  "properties": {
    "addr:full":"69 Talbot St E Leamington ON N8H 1L1",
    "addr:housenumber":"69",
    "addr:postcode":"n8h 1l1",
    "addr:street":"Talbot St E",
    "iso:country":"CA",
    "sg:address":"69 Talbot St E",
    "sg:city":"Leamington",
    "sg:classifiers":[
        {
            "category":"Professional",
            "type":"Services"
        }
    ],
    "sg:phone":"+1 519 322 2555",
    "sg:postcode":"N8H 1L1",
    "sg:province":"ON",
    "sg:tags":[
        "automobile",
        "parts",
        "establishment",
        "supply"
    ],
    "wof:name":"Pete's Paint & Parts",
    "wof:placetype":"venue"
},
  "geometry": {"coordinates":[-82.598007,42.053623],"type":"Point"}
}