{
  "type": "Feature",
  "properties": {
    "addr:full":"900 Dufferin St #75 Toronto ON M6H 4A9",
    "addr:housenumber":"900",
    "addr:postcode":"m6h 4a9",
    "addr:street":"Dufferin St # 75",
    "iso:country":"CA",
    "sg:address":"900 Dufferin St #75",
    "sg:city":"Toronto",
    "sg:classifiers":[
        {
            "category":"Personal",
            "subcategory":"Beauty Salon",
            "type":"Services"
        }
    ],
    "sg:phone":"+1 416 531 3131",
    "sg:postcode":"M6H 4A9",
    "sg:province":"ON",
    "sg:tags":[
        "school"
    ],
    "wof:name":"Marca College of Hair",
    "wof:placetype":"venue"
},
  "geometry": {"coordinates":[-79.43435700000001,43.656773],"type":"Point"}
}