{
  "type": "Feature",
  "properties": {
    "addr:full":"2345 Bossert Ave Kamloops BC V2B 4V6",
    "addr:housenumber":"2345",
    "addr:postcode":"bc v2b 4v6",
    "addr:street":"Bossert Ave",
    "iso:country":"CA",
    "sg:address":"2345 Bossert Ave",
    "sg:city":"Kamloops",
    "sg:classifiers":[
        {
            "category":"Building & Trades",
            "subcategory":"Electrical",
            "type":"Services"
        }
    ],
    "sg:phone":"+1 250 376 8320",
    "sg:postcode":"V2B 4V6",
    "sg:province":"BC",
    "sg:tags":[
        "electric",
        "contractor"
    ],
    "wof:name":"Stead Electric",
    "wof:placetype":"venue"
},
  "geometry": {"coordinates":[-120.410973,50.706779],"type":"Point"}
}