{
  "type": "Feature",
  "properties": {
    "addr:full":"3911 57A Ave Red Deer AB T4N 4T1",
    "addr:housenumber":"3911",
    "addr:postcode":"t4n 4t1",
    "addr:street":"57A Ave",
    "iso:country":"CA",
    "sg:address":"3911 57A Ave",
    "sg:city":"Red Deer",
    "sg:classifiers":[
        {
            "category":"Education",
            "subcategory":"School",
            "type":"Public Place"
        }
    ],
    "sg:phone":"+1 403 347 5650",
    "sg:postcode":"T4N 4T1",
    "sg:province":"AB",
    "wof:name":"St Martin DE Porres School",
    "wof:placetype":"venue"
},
  "geometry": {"coordinates":[-113.830436706,52.2596282959],"type":"Point"}
}