{
  "type": "Feature",
  "properties": {
    "addr:full":"843 Red River Rd Thunder Bay ON P7B 1K3",
    "addr:housenumber":"843",
    "addr:postcode":"p7b 1k3",
    "addr:street":"Red River Rd",
    "iso:country":"CA",
    "sg:address":"843 Red River Rd",
    "sg:city":"Thunder Bay",
    "sg:classifiers":[
        {
            "category":"Restaurant",
            "type":"Food & Drink"
        }
    ],
    "sg:phone":"+1 807 767 2110",
    "sg:postcode":"P7B 1K3",
    "sg:province":"ON",
    "sg:tags":[
        "pizza"
    ],
    "wof:name":"Little Caesar's Pizza",
    "wof:placetype":"venue"
},
  "geometry": {"coordinates":[-89.24834442140001,48.4456939697],"type":"Point"}
}