{
  "type": "Feature",
  "properties": {
    "addr:full":"4982 Kingsway Burnaby BC V5H 2E2",
    "addr:housenumber":"4982",
    "addr:postcode":"v5h 2e2",
    "addr:street":"Kingsway",
    "iso:country":"CA",
    "sg:address":"4982 Kingsway",
    "sg:city":"Burnaby",
    "sg:classifiers":[
        {
            "category":"Insurance",
            "subcategory":"Insurance Agent",
            "type":"Services"
        }
    ],
    "sg:phone":"+1 604 433 9351",
    "sg:postcode":"V5H 2E2",
    "sg:province":"BC",
    "wof:name":"Johnston Meier Insurance Ltd",
    "wof:placetype":"venue"
},
  "geometry": {"coordinates":[-122.992805,49.226131],"type":"Point"}
}