{
  "type": "Feature",
  "properties": {
    "addr:full":"601 Terminal Ave Vancouver BC V6A 2M2",
    "addr:housenumber":"601",
    "addr:postcode":"v6a 2m2",
    "addr:street":"Terminal Ave",
    "iso:country":"CA",
    "sg:address":"601 Terminal Ave",
    "sg:city":"Vancouver",
    "sg:classifiers":[
        {
            "category":"Food & Beverages",
            "subcategory":"Specialty",
            "type":"Retail Goods"
        }
    ],
    "sg:phone":"+1 604 688 9333",
    "sg:postcode":"V6A 2M2",
    "sg:province":"BC",
    "sg:tags":[
        "oriental"
    ],
    "wof:name":"Hung Gay Enterprises Ltd",
    "wof:placetype":"venue"
},
  "geometry": {"coordinates":[-123.09166,49.271614],"type":"Point"}
}