{
  "type": "Feature",
  "properties": {
    "addr:full":"1941 Weston Rd York ON M9N 1W8",
    "addr:housenumber":"1941",
    "addr:postcode":"m9n 1w8",
    "addr:street":"Weston Rd",
    "iso:country":"CA",
    "sg:address":"1941 Weston Rd",
    "sg:city":"York",
    "sg:classifiers":[
        {
            "category":"Education",
            "subcategory":"Vocational School",
            "type":"Public Place"
        }
    ],
    "sg:phone":"+1 416 242 7094",
    "sg:postcode":"M9N 1W8",
    "sg:province":"ON",
    "sg:tags":[
        "training",
        "computer"
    ],
    "wof:name":"Ikm Computer Training Ctr",
    "wof:placetype":"venue"
},
  "geometry": {"coordinates":[-79.5179672241,43.7008018494],"type":"Point"}
}