{
  "type": "Feature",
  "properties": {
    "addr:full":"5800 Montevideo Rd Mississauga ON L5N 2S1",
    "addr:housenumber":"5800",
    "addr:postcode":"l5n 2s1",
    "addr:street":"Montevideo Rd",
    "iso:country":"CA",
    "sg:address":"5800 Montevideo Rd",
    "sg:city":"Mississauga",
    "sg:classifiers":[
        {
            "category":"Education",
            "subcategory":"School",
            "type":"Public Place"
        }
    ],
    "sg:phone":"+1 905 826 4947",
    "sg:postcode":"L5N 2S1",
    "sg:province":"ON",
    "wof:name":"Settler's Green Public School",
    "wof:placetype":"venue"
},
  "geometry": {"coordinates":[-79.750305,43.577888],"type":"Point"}
}