{
  "type": "Feature",
  "properties": {
    "addr:full":"150 Huron St Stratford ON N5A 5S8",
    "addr:housenumber":"150",
    "addr:postcode":"n5a 5s8",
    "addr:street":"Huron St",
    "iso:country":"CA",
    "sg:address":"150 Huron St",
    "sg:city":"Stratford",
    "sg:classifiers":[
        {
            "category":"Health Services",
            "subcategory":"Doctor",
            "type":"Services"
        }
    ],
    "sg:phone":"+1 519 272 0891",
    "sg:postcode":"N5A 5S8",
    "sg:province":"ON",
    "sg:tags":[
        "physician",
        "surgeon"
    ],
    "wof:name":"Kintanar, C MD",
    "wof:placetype":"venue"
},
  "geometry": {"coordinates":[-80.9889678955,43.37449646],"type":"Point"}
}