{
  "type": "Feature",
  "properties": {
    "addr:full":"661 Berford St Wiarton ON N0H 2T0",
    "addr:housenumber":"661",
    "addr:postcode":"n0h 2t0",
    "addr:street":"Berford St",
    "iso:country":"CA",
    "sg:address":"661 Berford St",
    "sg:city":"Wiarton",
    "sg:classifiers":[
        {
            "category":"Insurance",
            "subcategory":"Insurance Agent",
            "type":"Services"
        }
    ],
    "sg:phone":"+1 519 534 2311",
    "sg:postcode":"N0H 2T0",
    "sg:province":"ON",
    "wof:name":"Carruthers Nicol Insurance",
    "wof:placetype":"venue"
},
  "geometry": {"coordinates":[-81.1408,44.744747],"type":"Point"}
}