{
  "type": "Feature",
  "properties": {
    "iso:country":"CA",
    "sg:address":"7055 Rue Alexandra",
    "sg:city":"Montreal",
    "sg:classifiers":[
        {
            "category":"Building & Trades",
            "subcategory":"Electrical",
            "type":"Services"
        }
    ],
    "sg:phone":"+1 514 271 1559",
    "sg:postcode":"H2S 3J6",
    "sg:province":"QC",
    "sg:tags":[
        "electric",
        "contractor"
    ],
    "wof:name":"Entreprises D'Elec Tuross Inc",
    "wof:placetype":"venue"
},
  "geometry": {"coordinates":[-73.618812561,45.5319099426],"type":"Point"}
}