{
  "type": "Feature",
  "properties": {
    "iso:country":"CA",
    "sg:address":"876 Riverside Dr",
    "sg:city":"Timmins",
    "sg:classifiers":[
        {
            "category":"Shopping",
            "subcategory":"Computers & Home Electronics",
            "type":"Retail Goods"
        }
    ],
    "sg:phone":"+1 705 268 3600",
    "sg:postcode":"P4N 3W2",
    "sg:province":"ON",
    "sg:tags":[
        "equipment",
        "dealer"
    ],
    "wof:name":"Computer Support Solutions",
    "wof:placetype":"venue"
},
  "geometry": {"coordinates":[-81.36199951170001,48.4769515991],"type":"Point"}
}