{
  "type": "Feature",
  "properties": {
    "addr:full":"8004 Lundy's Lane Niagara Falls ON L2H 1H1",
    "addr:housenumber":"8004",
    "addr:postcode":"l2h 1h1",
    "addr:street":"Lundy'S Lane",
    "iso:country":"CA",
    "sg:address":"8004 Lundy's Lane",
    "sg:city":"Niagara Falls",
    "sg:classifiers":[
        {
            "category":"Travel",
            "subcategory":"Hotels & Motels",
            "type":"Entertainment"
        }
    ],
    "sg:phone":"+1 905 356 7799",
    "sg:postcode":"L2H 1H1",
    "sg:province":"ON",
    "wof:name":"Carriage House Motor Lodge",
    "wof:placetype":"venue"
},
  "geometry": {"coordinates":[-77.56536865229999,45.0424156189],"type":"Point"}
}