{
  "type": "Feature",
  "properties": {
    "addr:full":"407 St Clair St Chatham ON N7L 3K4",
    "addr:housenumber":"407",
    "addr:postcode":"n7l 3k4",
    "addr:street":"St Clair St",
    "iso:country":"CA",
    "sg:address":"407 St Clair St",
    "sg:city":"Chatham",
    "sg:classifiers":[
        {
            "category":"Restaurant",
            "type":"Food & Drink"
        }
    ],
    "sg:phone":"+1 519 352 9184",
    "sg:postcode":"N7L 3K4",
    "sg:province":"ON",
    "sg:tags":[
        "parlor",
        "ice",
        "cream"
    ],
    "wof:name":"Dairy Queen",
    "wof:placetype":"venue"
},
  "geometry": {"coordinates":[-82.2000656128,42.4152984619],"type":"Point"}
}