{
  "type": "Feature",
  "properties": {
    "iso:country":"CA",
    "sg:address":"7201 Rue Notre-Dame Ouest",
    "sg:city":"Trois-Rivieres-Ouest",
    "sg:classifiers":[
        {
            "category":"Travel",
            "subcategory":"Hotels & Motels",
            "type":"Entertainment"
        }
    ],
    "sg:phone":"+1 819 377 4747",
    "sg:postcode":"G9B 1W2",
    "sg:province":"QC",
    "wof:name":"Hotel Les Suites DE Laviolette",
    "wof:placetype":"venue"
},
  "geometry": {"coordinates":[-72.57498931879999,46.3133468628],"type":"Point"}
}