{
  "type": "Feature",
  "properties": {
    "addr:full":"Amherstburg ON N9V 3L4",
    "addr:postcode":"n9v 3l4",
    "iso:country":"CA",
    "sg:city":"Amherstburg",
    "sg:classifiers":[
        {
            "category":"Personal",
            "subcategory":"Beauty Salon",
            "type":"Services"
        }
    ],
    "sg:phone":"+1 519 736 3145",
    "sg:postcode":"N9V 3L4",
    "sg:province":"ON",
    "wof:name":"Salon 2000",
    "wof:placetype":"venue"
},
  "geometry": {"coordinates":[-83.10828399659999,42.0971336365],"type":"Point"}
}