{
  "type": "Feature",
  "properties": {
    "addr:full":"65 Ch DE LA Rabastaliere O Saint-Bruno QC J3V 1Y7",
    "addr:housenumber":"65",
    "addr:postcode":"j3v 1y7",
    "addr:street":"Ch De La Rabastaliere O",
    "iso:country":"CA",
    "sg:address":"65 Ch DE LA Rabastaliere O",
    "sg:city":"Saint-Bruno",
    "sg:classifiers":[
        {
            "category":"Professional",
            "subcategory":"Lawyer & Legal Services",
            "type":"Services"
        }
    ],
    "sg:phone":"+1 450 653 3693",
    "sg:postcode":"J3V 1Y7",
    "sg:province":"QC",
    "sg:tags":[
        "notary",
        "plan"
    ],
    "wof:name":"Leroux & Delorme",
    "wof:placetype":"venue"
},
  "geometry": {"coordinates":[-71.675522,48.471771],"type":"Point"}
}