{
  "type": "Feature",
  "properties": {
    "iso:country":"CA",
    "sg:address":"690 Rue Mandel",
    "sg:city":"Laval",
    "sg:classifiers":[
        {
            "category":"Health Services",
            "subcategory":"Nursing And Care Facility",
            "type":"Services"
        }
    ],
    "sg:phone":"+1 450 689 5844",
    "sg:postcode":"H7X 1L4",
    "sg:province":"QC",
    "sg:tags":[
        "home",
        "rest"
    ],
    "wof:name":"Foyer Sainte Dorothee",
    "wof:placetype":"venue"
},
  "geometry": {"coordinates":[-73.8163604736,45.5222663879],"type":"Point"}
}