{
  "type": "Feature",
  "properties": {
    "addr:full":"133 11th Ave S Cranbrook BC V1C 2P4",
    "addr:housenumber":"133",
    "addr:postcode":"bc v1c 2p4",
    "addr:street":"11Th Ave S",
    "iso:country":"CA",
    "sg:address":"133 11th Ave S",
    "sg:city":"Cranbrook",
    "sg:classifiers":[
        {
            "category":"Social Services",
            "subcategory":"Adult Care",
            "type":"Services"
        }
    ],
    "sg:phone":"+1 250 426 2651",
    "sg:postcode":"V1C 2P4",
    "sg:province":"BC",
    "sg:tags":[
        "community",
        "facility"
    ],
    "wof:name":"Pioneer Lodge",
    "wof:placetype":"venue"
},
  "geometry": {"coordinates":[-115.766403,49.509628],"type":"Point"}
}