{
  "type": "Feature",
  "properties": {
    "addr:full":"260 Main St Iroquois Falls ON P0K 1E0",
    "addr:housenumber":"260",
    "addr:postcode":"p0k 1e0",
    "addr:street":"Main St",
    "iso:country":"CA",
    "sg:address":"260 Main St",
    "sg:city":"Iroquois Falls",
    "sg:classifiers":[
        {
            "category":"Government",
            "subcategory":"Office",
            "type":"Public Place"
        }
    ],
    "sg:phone":"+1 705 232 4001",
    "sg:postcode":"P0K 1E0",
    "sg:province":"ON",
    "wof:name":"Government Information Ctr",
    "wof:placetype":"venue"
},
  "geometry": {"coordinates":[-80.68589019780001,48.7582893372],"type":"Point"}
}