{
  "type": "Feature",
  "properties": {
    "addr:full":"4 Baker Rd Brampton ON L6T 4E3",
    "addr:housenumber":"4",
    "addr:postcode":"l6t 4e3",
    "addr:street":"Baker Rd",
    "iso:country":"CA",
    "sg:address":"4 Baker Rd",
    "sg:city":"Brampton",
    "sg:classifiers":[
        {
            "category":"Manufacturing",
            "subcategory":"Rubber & Plastics",
            "type":"Manufacturing & Wholesale Goods"
        }
    ],
    "sg:phone":"+1 905 791 1303",
    "sg:postcode":"L6T 4E3",
    "sg:province":"ON",
    "sg:tags":[
        "closure"
    ],
    "wof:name":"Caps 'N Plugs",
    "wof:placetype":"venue"
},
  "geometry": {"coordinates":[-79.697227,43.731564],"type":"Point"}
}