{
  "type": "Feature",
  "properties": {
    "addr:full":"6440 Quinpool Rd Halifax NS B3L 1A8",
    "addr:housenumber":"6440",
    "addr:postcode":"b3l 1a8",
    "addr:street":"Quinpool Rd",
    "iso:country":"CA",
    "sg:address":"6440 Quinpool Rd",
    "sg:city":"Halifax",
    "sg:classifiers":[
        {
            "category":"Education",
            "subcategory":"Special Training",
            "type":"Public Place"
        }
    ],
    "sg:phone":"+1 902 422 7323",
    "sg:postcode":"B3L 1A8",
    "sg:province":"NS",
    "sg:tags":[
        "school",
        "tutoring"
    ],
    "wof:name":"Sylvan Learning Ctr",
    "wof:placetype":"venue"
},
  "geometry": {"coordinates":[-63.601348877,44.6441040039],"type":"Point"}
}