{
  "type": "Feature",
  "properties": {
    "addr:full":"9195 Boul Saint-Michel Montreal QC H1Z 3G6",
    "addr:housenumber":"9195",
    "addr:postcode":"h1z 3g6",
    "addr:street":"Boul Saint-Michel",
    "iso:country":"CA",
    "sg:address":"9195 Boul Saint-Michel",
    "sg:city":"Montreal",
    "sg:classifiers":[
        {
            "category":"Arts & Performance",
            "subcategory":"Theater",
            "type":"Entertainment"
        }
    ],
    "sg:phone":"+1 514 244 5532",
    "sg:postcode":"H1Z 3G6",
    "sg:province":"QC",
    "sg:tags":[
        "mobile",
        "discotheque"
    ],
    "wof:name":"Vizion Multimedia Entertain",
    "wof:placetype":"venue"
},
  "geometry": {"coordinates":[-73.62973,45.572914],"type":"Point"}
}