{
  "type": "Feature",
  "properties": {
    "addr:full":"Winnipeg MB R2R 1T9",
    "addr:postcode":"r2r 1t9",
    "iso:country":"CA",
    "sg:city":"Winnipeg",
    "sg:classifiers":[
        {
            "category":"Freight",
            "type":"Transportation"
        }
    ],
    "sg:phone":"+1 204 633 1008",
    "sg:postcode":"R2R 1T9",
    "sg:province":"MB",
    "sg:tags":[
        "renting",
        "container",
        "leasing",
        "storage",
        "trailer"
    ],
    "wof:name":"Best Storage Trailers",
    "wof:placetype":"venue"
},
  "geometry": {"coordinates":[-97.2244796753,49.9378852844],"type":"Point"}
}