{
  "type": "Feature",
  "properties": {
    "addr:full":"228 Hamel Ave Winnipeg MB R2H 0K6",
    "addr:housenumber":"228",
    "addr:postcode":"r2h 0k6",
    "addr:street":"Hamel Ave",
    "iso:country":"CA",
    "sg:address":"228 Hamel Ave",
    "sg:city":"Winnipeg",
    "sg:classifiers":[
        {
            "category":"Organizations",
            "subcategory":"Religious Organization",
            "type":"Services"
        }
    ],
    "sg:phone":"+1 204 237 4098",
    "sg:postcode":"R2H 0K6",
    "sg:province":"MB",
    "wof:name":"White Fathers",
    "wof:placetype":"venue"
},
  "geometry": {"coordinates":[-97.117980957,49.8881416321],"type":"Point"}
}