{
  "type": "Feature",
  "properties": {
    "addr:full":"Cornwall ON K6H 5R7",
    "addr:postcode":"k6h 5r7",
    "iso:country":"CA",
    "sg:city":"Cornwall",
    "sg:classifiers":[
        {
            "category":"Recreation",
            "type":"Entertainment"
        }
    ],
    "sg:phone":"+1 613 933 6794",
    "sg:postcode":"K6H 5R7",
    "sg:province":"ON",
    "sg:tags":[
        "center"
    ],
    "wof:name":"Kawehnoke Community Ctr",
    "wof:placetype":"venue"
},
  "geometry": {"coordinates":[-74.72938499999999,45.025845],"type":"Point"}
}