{
  "type": "Feature",
  "properties": {
    "addr:full":"14 Lansfield Way Nepean ON K2G 3V8",
    "addr:housenumber":"14",
    "addr:postcode":"k2g 3v8",
    "addr:street":"Lansfield Way",
    "iso:country":"CA",
    "sg:address":"14 Lansfield Way",
    "sg:city":"Nepean",
    "sg:classifiers":[
        {
            "category":"Real Estate",
            "subcategory":"Real Estate Agent",
            "type":"Services"
        }
    ],
    "sg:phone":"+1 613 224 9842",
    "sg:postcode":"K2G 3V8",
    "sg:province":"ON",
    "sg:tags":[
        "building",
        "inspection"
    ],
    "wof:name":"Abode Inspection Svc",
    "wof:placetype":"venue"
},
  "geometry": {"coordinates":[-75.74477400000001,45.332218],"type":"Point"}
}