{
  "type": "Feature",
  "properties": {
    "addr:full":"Etobicoke ON M9W 5C8",
    "addr:postcode":"m9w 5c8",
    "iso:country":"CA",
    "sg:city":"Etobicoke",
    "sg:classifiers":[
        {
            "category":"Professional",
            "subcategory":"Accounting & Tax Preparation",
            "type":"Services"
        }
    ],
    "sg:phone":"+1 416 679 0530",
    "sg:postcode":"M9W 5C8",
    "sg:province":"ON",
    "sg:tags":[
        "accountant"
    ],
    "wof:name":"A V Accounting",
    "wof:placetype":"venue"
},
  "geometry": {"coordinates":[-79.5886383057,43.7012176514],"type":"Point"}
}