{
  "type": "Feature",
  "properties": {
    "addr:full":"Winnipeg MB R3C 0B9",
    "addr:postcode":"r3c 0b9",
    "iso:country":"CA",
    "sg:city":"Winnipeg",
    "sg:classifiers":[
        {
            "category":"Education",
            "subcategory":"Vocational School",
            "type":"Public Place"
        }
    ],
    "sg:phone":"+1 204 989 2659",
    "sg:postcode":"R3C 0B9",
    "sg:province":"MB",
    "sg:tags":[
        "training",
        "computer"
    ],
    "wof:name":"Abenaki Computer Enterprises",
    "wof:placetype":"venue"
},
  "geometry": {"coordinates":[-97.14274597169999,49.893661499],"type":"Point"}
}