{
  "type": "Feature",
  "properties": {
    "addr:full":"Montreal QC H3N 2N8",
    "addr:postcode":"h3n 2n8",
    "iso:country":"CA",
    "sg:city":"Montreal",
    "sg:classifiers":[
        {
            "category":"Manufacturing",
            "subcategory":"Printing",
            "type":"Manufacturing & Wholesale Goods"
        }
    ],
    "sg:phone":"+1 514 272 6873",
    "sg:postcode":"H3N 2N8",
    "sg:province":"QC",
    "sg:tags":[
        "newspaper"
    ],
    "wof:name":"Greek Canadian Tribune Ltd",
    "wof:placetype":"venue"
},
  "geometry": {"coordinates":[-73.6326141357,45.5281867981],"type":"Point"}
}