{
  "type": "Feature",
  "properties": {
    "addr:full":"13 Quebec Havelock ON K0L 1Z0",
    "addr:housenumber":"13",
    "addr:postcode":"k0l 1z0",
    "addr:street":"Quebec",
    "iso:country":"CA",
    "sg:address":"13 Quebec",
    "sg:city":"Havelock",
    "sg:classifiers":[
        {
            "category":"Education",
            "subcategory":"Library",
            "type":"Public Place"
        }
    ],
    "sg:phone":"+1 705 778 2621",
    "sg:postcode":"K0L 1Z0",
    "sg:province":"ON",
    "sg:tags":[
        "government"
    ],
    "wof:name":"Havelock Public Library",
    "wof:placetype":"venue"
},
  "geometry": {"coordinates":[-77.887642,44.434772],"type":"Point"}
}