{
  "type": "Feature",
  "properties": {
    "addr:full":"Comox BC V9M 1R9",
    "addr:postcode":"v9m 1r9",
    "iso:country":"CA",
    "sg:city":"Comox",
    "sg:classifiers":[
        {
            "category":"Real Estate",
            "subcategory":"Real Estate Agent",
            "type":"Services"
        }
    ],
    "sg:phone":"+1 250 890 3320",
    "sg:postcode":"V9M 1R9",
    "sg:province":"BC",
    "sg:tags":[
        "appraiser"
    ],
    "wof:name":"Kutyn Property Svc",
    "wof:placetype":"venue"
},
  "geometry": {"coordinates":[-124.92771911600001,49.6731185913],"type":"Point"}
}