{
  "type": "Feature",
  "properties": {
    "addr:full":"417 Harmony Rd Ayr ON N0B 1E0",
    "addr:housenumber":"417",
    "addr:postcode":"n0b 1e0",
    "addr:street":"Harmony Rd",
    "iso:country":"CA",
    "sg:address":"417 Harmony Rd",
    "sg:city":"Ayr",
    "sg:classifiers":[
        {
            "category":"Manufacturing",
            "subcategory":"Metals",
            "type":"Manufacturing & Wholesale Goods"
        }
    ],
    "sg:phone":"+1 519 622 8811",
    "sg:postcode":"N0B 1E0",
    "sg:province":"ON",
    "sg:tags":[
        "pipe",
        "lining",
        "coating"
    ],
    "wof:name":"Ecl Engineered Coatings Ltd",
    "wof:placetype":"venue"
},
  "geometry": {"coordinates":[-80.449997,43.285656],"type":"Point"}
}