{
  "type": "Feature",
  "properties": {
    "addr:full":"3220 1Re Rue #513 Saint-Hubert QC J3Y 8Y5",
    "addr:postcode":"3220;j3y 8y5",
    "addr:street":"1Re Rue # 513",
    "iso:country":"CA",
    "sg:address":"3220 1Re Rue #513",
    "sg:city":"Saint-Hubert",
    "sg:classifiers":[
        {
            "category":"Manufacturing",
            "subcategory":"Printing",
            "type":"Manufacturing & Wholesale Goods"
        }
    ],
    "sg:phone":"+1 450 445 2049",
    "sg:postcode":"J3Y 8Y5",
    "sg:province":"QC",
    "sg:tags":[
        "screen"
    ],
    "wof:name":"Isi Serigraphie Enr",
    "wof:placetype":"venue"
},
  "geometry": {"coordinates":[-73.39111328120001,45.4780845642],"type":"Point"}
}