{
  "type": "Feature",
  "properties": {
    "iso:country":"CA",
    "sg:city":"Delta",
    "sg:classifiers":[
        {
            "category":"Autos & Motor Vehicles",
            "subcategory":"Auto Supplies",
            "type":"Retail Goods"
        }
    ],
    "sg:phone":"+1 604 946 4679",
    "sg:postcode":"V4K 2X7",
    "sg:province":"BC",
    "sg:tags":[
        "automobile",
        "parts"
    ],
    "wof:name":"Lordco Parts Ltd",
    "wof:placetype":"venue"
},
  "geometry": {"coordinates":[-123.08367157000001,49.0912017822],"type":"Point"}
}