{
  "type": "Feature",
  "properties": {
    "addr:full":"694 Rue Jean-Talon O Montreal QC H3N 1R8",
    "addr:housenumber":"694",
    "addr:postcode":"h3n 1r8",
    "addr:street":"Rue Jean-Talon O",
    "iso:country":"CA",
    "sg:address":"694 Rue Jean-Talon O",
    "sg:city":"Montreal",
    "sg:classifiers":[
        {
            "category":"Home & Garden",
            "subcategory":"Hardware",
            "type":"Retail Goods"
        }
    ],
    "sg:phone":"+1 514 277 4137",
    "sg:postcode":"H3N 1R8",
    "sg:province":"QC",
    "wof:name":"Quincaillerie Larose",
    "wof:placetype":"venue"
},
  "geometry": {"coordinates":[-73.613472,45.539925],"type":"Point"}
}