{
  "type": "Feature",
  "properties": {
    "addr:full":"Sainte-Anne-Du-Lac QC J0W 1C0",
    "addr:postcode":"j0w 1c0",
    "iso:country":"CA",
    "sg:city":"Sainte-Anne-Du-Lac",
    "sg:classifiers":[
        {
            "category":"Building & Trades",
            "subcategory":"Construction",
            "type":"Services"
        }
    ],
    "sg:phone":"+1 819 586 2801",
    "sg:postcode":"J0W 1C0",
    "sg:province":"QC",
    "sg:tags":[
        "general",
        "contractor"
    ],
    "wof:name":"Constructech Ml Inc",
    "wof:placetype":"venue"
},
  "geometry": {"coordinates":[-75.319061,46.883026],"type":"Point"}
}