{
  "type": "Feature",
  "properties": {
    "addr:full":"Surrey BC V3T 4H4",
    "addr:postcode":"v3t 4h4",
    "iso:country":"CA",
    "sg:city":"Surrey",
    "sg:classifiers":[
        {
            "category":"Health Services",
            "subcategory":"Medical Lab",
            "type":"Services"
        }
    ],
    "sg:phone":"+1 604 588 5001",
    "sg:postcode":"V3T 4H4",
    "sg:province":"BC",
    "sg:tags":[
        "laboratory"
    ],
    "wof:name":"Nova Dental Ceramics",
    "wof:placetype":"venue"
},
  "geometry": {"coordinates":[-122.84184265099999,49.1902008057],"type":"Point"}
}