{
  "type": "Feature",
  "properties": {
    "iso:country":"CA",
    "sg:city":"North Vancouver",
    "sg:classifiers":[
        {
            "category":"Restaurant",
            "type":"Food & Drink"
        }
    ],
    "sg:phone":"+1 604 986 1858",
    "sg:postcode":"V7P 3K6",
    "sg:province":"BC",
    "wof:name":"Swiss Chalet Rotisserie/Grill",
    "wof:placetype":"venue"
},
  "geometry": {"coordinates":[-123.095009,49.321091],"type":"Point"}
}