{
  "type": "Feature",
  "properties": {
    "addr:full":"2300 Fairview St Burlington ON L7R 2E4",
    "addr:housenumber":"2300",
    "addr:postcode":"l7r 2e4",
    "addr:street":"Fairview St",
    "iso:country":"CA",
    "sg:address":"2300 Fairview St",
    "sg:city":"Burlington",
    "sg:classifiers":[
        {
            "category":"Autos & Motor Vehicles",
            "subcategory":"Automobile Sales",
            "type":"Retail Goods"
        }
    ],
    "sg:phone":"+1 905 632 5371",
    "sg:postcode":"L7R 2E4",
    "sg:province":"ON",
    "sg:tags":[
        "car",
        "dealer"
    ],
    "wof:name":"Halton Honda Inc",
    "wof:placetype":"venue"
},
  "geometry": {"coordinates":[-79.80307769780001,43.3427124023],"type":"Point"}
}