{
  "type": "Feature",
  "properties": {
    "addr:full":"90129 Fordwich Line Clifford ON N0G 1M0",
    "addr:postcode":"90129;n0g 1m0",
    "addr:street":"Fordwich Line",
    "iso:country":"CA",
    "sg:address":"90129 Fordwich Line",
    "sg:city":"Clifford",
    "sg:classifiers":[
        {
            "category":"Building & Trades",
            "subcategory":"Construction",
            "type":"Services"
        }
    ],
    "sg:phone":"+1 519 327 8271",
    "sg:postcode":"N0G 1M0",
    "sg:province":"ON",
    "sg:tags":[
        "builder",
        "stair"
    ],
    "wof:name":"Blue Spruce Woodcraft",
    "wof:placetype":"venue"
},
  "geometry": {"coordinates":[-80.97931699999999,43.969601],"type":"Point"}
}