{
  "type": "Feature",
  "properties": {
    "iso:country":"CA",
    "sg:address":"6565 Rue Jean-Talon E",
    "sg:city":"Saint-Leonard",
    "sg:classifiers":[
        {
            "category":"Autos & Motor Vehicles",
            "subcategory":"Auto Supplies",
            "type":"Retail Goods"
        }
    ],
    "sg:phone":"+1 514 253 2877",
    "sg:postcode":"H1S 1N2",
    "sg:province":"QC",
    "sg:tags":[
        "repairing",
        "automobile",
        "parts"
    ],
    "wof:name":"Canadian Tire",
    "wof:placetype":"venue"
},
  "geometry": {"coordinates":[-73.5739822388,45.5935287476],"type":"Point"}
}