{
  "type": "Feature",
  "properties": {
    "iso:country":"CA",
    "sg:address":"114 Woodlawn Rd",
    "sg:city":"Dartmouth",
    "sg:classifiers":[
        {
            "category":"Cinema",
            "subcategory":"Movie Rental",
            "type":"Entertainment"
        }
    ],
    "sg:phone":"+1 902 433 0994",
    "sg:postcode":"B2W 2S7",
    "sg:province":"NS",
    "sg:tags":[
        "leasing",
        "video",
        "disc",
        "tape"
    ],
    "wof:name":"Rogers Video",
    "wof:placetype":"venue"
},
  "geometry": {"coordinates":[-63.5305709839,44.6731567383],"type":"Point"}
}