{
  "type": "Feature",
  "properties": {
    "addr:full":"RR 1 Bornholm ON N0K 1A0",
    "addr:postcode":"n0k 1a0",
    "addr:street":"Rr 1 Bornholm",
    "iso:country":"CA",
    "sg:address":"RR 1",
    "sg:city":"Bornholm",
    "sg:classifiers":[
        {
            "category":"Organizations",
            "subcategory":"Religious Organization",
            "type":"Services"
        }
    ],
    "sg:phone":"+1 519 595 4689",
    "sg:postcode":"N0K 1A0",
    "sg:province":"ON",
    "sg:tags":[
        "church"
    ],
    "wof:name":"St Peter's Lutheran Church",
    "wof:placetype":"venue"
},
  "geometry": {"coordinates":[-81.145065,43.531792],"type":"Point"}
}