{
  "type": "Feature",
  "properties": {
    "addr:full":"6021 Young St # 210 Halifax NS B3K 2A1",
    "addr:housenumber":"6021",
    "addr:postcode":"b3k 2a1",
    "addr:street":"Young St # 210",
    "iso:country":"CA",
    "sg:address":"6021 Young St # 210",
    "sg:city":"Halifax",
    "sg:classifiers":[
        {
            "category":"Professional",
            "subcategory":"Lawyer & Legal Services",
            "type":"Services"
        }
    ],
    "sg:phone":"+1 902 425 5111",
    "sg:postcode":"B3K 2A1",
    "sg:province":"NS",
    "sg:tags":[
        "attorney"
    ],
    "wof:name":"Roza, Joseph S",
    "wof:placetype":"venue"
},
  "geometry": {"coordinates":[-63.602463,44.659645],"type":"Point"}
}