{
  "type": "Feature",
  "properties": {
    "addr:full":"1004 Richard Rd Williams Lake BC V2G 3M1",
    "addr:housenumber":"1004",
    "addr:postcode":"v2g 3m1",
    "addr:street":"Richard Rd",
    "iso:country":"CA",
    "sg:address":"1004 Richard Rd",
    "sg:city":"Williams Lake",
    "sg:classifiers":[
        {
            "category":"Shopping",
            "subcategory":"Gifts & Souvenirs",
            "type":"Retail Goods"
        }
    ],
    "sg:phone":"+1 250 398 7815",
    "sg:postcode":"V2G 3M1",
    "sg:province":"BC",
    "sg:tags":[
        "basket",
        "parcel"
    ],
    "wof:name":"Piccadilly Gift Baskets",
    "wof:placetype":"venue"
},
  "geometry": {"coordinates":[-122.14108299999999,52.128651],"type":"Point"}
}