{
  "type": "Feature",
  "properties": {
    "addr:full":"571 Netherby Rd Welland ON L3B 5N7",
    "addr:housenumber":"571",
    "addr:postcode":"l3b 5n7",
    "addr:street":"Netherby Rd",
    "iso:country":"CA",
    "sg:address":"571 Netherby Rd",
    "sg:city":"Welland",
    "sg:classifiers":[
        {
            "category":"Home & Garden",
            "subcategory":"Building Materials",
            "type":"Retail Goods"
        }
    ],
    "sg:phone":"+1 905 788 2110",
    "sg:postcode":"L3B 5N7",
    "sg:province":"ON",
    "sg:tags":[
        "improvement"
    ],
    "wof:name":"Jey Home Improvements",
    "wof:placetype":"venue"
},
  "geometry": {"coordinates":[-79.19047500000001,42.962063],"type":"Point"}
}