{
  "type": "Feature",
  "properties": {
    "addr:full":"RR 2 Warren ON P0H 2N0",
    "addr:postcode":"p0h 2n0",
    "addr:street":"Rr 2",
    "iso:country":"CA",
    "sg:address":"RR 2",
    "sg:city":"Warren",
    "sg:classifiers":[
        {
            "category":"Travel",
            "subcategory":"Hotels & Motels",
            "type":"Entertainment"
        }
    ],
    "sg:phone":"+1 705 594 9143",
    "sg:postcode":"P0H 2N0",
    "sg:province":"ON",
    "sg:tags":[
        "tourist",
        "accommodation"
    ],
    "wof:name":"Deer Lake Cottages",
    "wof:placetype":"venue"
},
  "geometry": {"coordinates":[-80.310745,46.442421],"type":"Point"}
}