{
  "type": "Feature",
  "properties": {
    "addr:full":"304 5 Ave W Cochrane AB T4C 2A5",
    "addr:housenumber":"304",
    "addr:postcode":"t4c 2a5",
    "addr:street":"5 Ave W",
    "iso:country":"CA",
    "sg:address":"304 5 Ave W",
    "sg:city":"Cochrane",
    "sg:classifiers":[
        {
            "category":"Shopping",
            "subcategory":"Pharmacy",
            "type":"Retail Goods"
        }
    ],
    "sg:phone":"+1 403 851 1279",
    "sg:postcode":"T4C 2A5",
    "sg:province":"AB",
    "wof:name":"Safeway Pharmacy",
    "wof:placetype":"venue"
},
  "geometry": {"coordinates":[-114.477661,51.18457],"type":"Point"}
}