{
  "type": "Feature",
  "properties": {
    "addr:full":"302 Cedar St Nelson BC V1L 2B9",
    "addr:housenumber":"302",
    "addr:postcode":"bc v1l 2b9",
    "addr:street":"Cedar St",
    "iso:country":"CA",
    "sg:address":"302 Cedar St",
    "sg:city":"Nelson",
    "sg:classifiers":[
        {
            "category":"Recreation",
            "type":"Entertainment"
        }
    ],
    "sg:phone":"+1 250 352 7628",
    "sg:postcode":"V1L 2B9",
    "sg:province":"BC",
    "sg:tags":[
        "club",
        "curling"
    ],
    "wof:name":"Nelson Curling Club",
    "wof:placetype":"venue"
},
  "geometry": {"coordinates":[-117.290046692,49.4955215454],"type":"Point"}
}