{
  "type": "Feature",
  "properties": {
    "iso:country":"CA",
    "sg:address":"7839 Rue Foucher",
    "sg:city":"Montreal",
    "sg:classifiers":[
        {
            "category":"Health Services",
            "subcategory":"Health Practitioner",
            "type":"Services"
        }
    ],
    "sg:phone":"+1 514 278 4315",
    "sg:postcode":"H2R 2K8",
    "sg:province":"QC",
    "sg:tags":[
        "psychologist"
    ],
    "wof:name":"Forget, Elise",
    "wof:placetype":"venue"
},
  "geometry": {"coordinates":[-73.623787,45.543941],"type":"Point"}
}