{
  "type": "Feature",
  "properties": {
    "addr:full":"Scarborough ON M1S 4A9",
    "addr:postcode":"m1s 4a9",
    "iso:country":"CA",
    "sg:city":"Scarborough",
    "sg:classifiers":[
        {
            "category":"Manufacturing",
            "subcategory":"Printing",
            "type":"Manufacturing & Wholesale Goods"
        }
    ],
    "sg:phone":"+1 416 292 1477",
    "sg:postcode":"M1S 4A9",
    "sg:province":"ON",
    "sg:tags":[
        "screen"
    ],
    "wof:name":"Metro Cresting CO",
    "wof:placetype":"venue"
},
  "geometry": {"coordinates":[-79.275841,43.779411],"type":"Point"}
}