{
  "type": "Feature",
  "properties": {
    "iso:country":"CA",
    "sg:address":"1490 Battler Rd",
    "sg:city":"Kitchener",
    "sg:classifiers":[
        {
            "category":"Building & Trades",
            "subcategory":"Electrical",
            "type":"Services"
        }
    ],
    "sg:phone":"+1 519 748 6740",
    "sg:postcode":"N2R 1J6",
    "sg:province":"ON",
    "sg:tags":[
        "electric",
        "contractor"
    ],
    "wof:name":"Conestogo Electric Inc",
    "wof:placetype":"venue"
},
  "geometry": {"coordinates":[-80.46508,43.398014],"type":"Point"}
}