{
  "type": "Feature",
  "properties": {
    "addr:full":"620 Twain Ave Mississauga ON L5W 1M1",
    "addr:housenumber":"620",
    "addr:postcode":"l5w 1m1",
    "addr:street":"Twain Ave",
    "iso:country":"CA",
    "sg:address":"620 Twain Ave",
    "sg:city":"Mississauga",
    "sg:classifiers":[
        {
            "category":"Education",
            "subcategory":"School",
            "type":"Public Place"
        }
    ],
    "sg:phone":"+1 905 565 5762",
    "sg:postcode":"L5W 1M1",
    "sg:province":"ON",
    "wof:name":"Derry West Village",
    "wof:placetype":"venue"
},
  "geometry": {"coordinates":[-79.72472399999999,43.640316],"type":"Point"}
}