{
  "type": "Feature",
  "properties": {
    "iso:country":"CA",
    "sg:address":"3643 99 St NW",
    "sg:city":"Edmonton",
    "sg:classifiers":[
        {
            "category":"Home & Garden",
            "subcategory":"Furniture",
            "type":"Retail Goods"
        }
    ],
    "sg:phone":"+1 780 434 9388",
    "sg:postcode":"T6E 6K5",
    "sg:province":"AB",
    "sg:tags":[
        "mattress"
    ],
    "wof:name":"Rogers Sleep Shop Ltd",
    "wof:placetype":"venue"
},
  "geometry": {"coordinates":[-113.485794067,53.4708900452],"type":"Point"}
}