{
  "type": "Feature",
  "properties": {
    "addr:full":"1876 Huron Rd Kitchener ON N2R 1R6",
    "addr:housenumber":"1876",
    "addr:postcode":"n2r 1r6",
    "addr:street":"Huron Rd",
    "iso:country":"CA",
    "sg:address":"1876 Huron Rd",
    "sg:city":"Kitchener",
    "sg:classifiers":[
        {
            "category":"Wholesale",
            "subcategory":"Machinery & Supplies",
            "type":"Manufacturing & Wholesale Goods"
        }
    ],
    "sg:phone":"+1 519 696 2568",
    "sg:postcode":"N2R 1R6",
    "sg:province":"ON",
    "sg:tags":[
        "farm",
        "equipment"
    ],
    "wof:name":"Kitchener Tractor Ctr Inc",
    "wof:placetype":"venue"
},
  "geometry": {"coordinates":[-80.506149292,43.3790664673],"type":"Point"}
}