{
  "type": "Feature",
  "properties": {
    "addr:full":"527 James St N Hamilton ON L8L 1J6",
    "addr:housenumber":"527",
    "addr:postcode":"l8l 1j6",
    "addr:street":"James St N",
    "iso:country":"CA",
    "sg:address":"527 James St N",
    "sg:city":"Hamilton",
    "sg:classifiers":[
        {
            "category":"Shopping",
            "subcategory":"Discount & Variety Stores",
            "type":"Retail Goods"
        }
    ],
    "sg:phone":"+1 905 528 4881",
    "sg:postcode":"L8L 1J6",
    "sg:province":"ON",
    "wof:name":"James Milk",
    "wof:placetype":"venue"
},
  "geometry": {"coordinates":[-79.86302947999999,43.2707939148],"type":"Point"}
}