{
  "type": "Feature",
  "properties": {
    "addr:full":"39 High St W Moose Jaw SK S6H 1S4",
    "addr:housenumber":"39",
    "addr:postcode":"s6h 1s4",
    "addr:street":"High St W",
    "iso:country":"CA",
    "sg:address":"39 High St W",
    "sg:city":"Moose Jaw",
    "sg:classifiers":[
        {
            "category":"Professional",
            "subcategory":"Accounting & Tax Preparation",
            "type":"Services"
        }
    ],
    "sg:phone":"+1 306 693 4395",
    "sg:postcode":"S6H 1S4",
    "sg:province":"SK",
    "sg:tags":[
        "return",
        "filing"
    ],
    "wof:name":"Liberty Tax Svc",
    "wof:placetype":"venue"
},
  "geometry": {"coordinates":[-105.535774231,50.3914337158],"type":"Point"}
}