{
  "type": "Feature",
  "properties": {
    "addr:full":"119 Spadina Ave Toronto ON M5V 2L1",
    "addr:housenumber":"119",
    "addr:postcode":"m5v 2l1",
    "addr:street":"Spadina Ave",
    "iso:country":"CA",
    "sg:address":"119 Spadina Ave",
    "sg:city":"Toronto",
    "sg:classifiers":[
        {
            "category":"Government",
            "subcategory":"Post Office",
            "type":"Public Place"
        }
    ],
    "sg:phone":"+1 416 596 8040",
    "sg:postcode":"M5V 2L1",
    "sg:province":"ON",
    "wof:name":"Canada Post Corp STN B",
    "wof:placetype":"venue"
},
  "geometry": {"coordinates":[-79.39534,43.647053],"type":"Point"}
}