{
  "type": "Feature",
  "properties": {
    "addr:full":"75 Birch E Chapleau ON P0M 1K0",
    "addr:housenumber":"75",
    "addr:postcode":"p0m 1k0",
    "addr:street":"Birch E",
    "iso:country":"CA",
    "sg:address":"75 Birch E",
    "sg:city":"Chapleau",
    "sg:classifiers":[
        {
            "category":"Health Services",
            "subcategory":"Chiropractor",
            "type":"Services"
        }
    ],
    "sg:phone":"+1 705 864 1372",
    "sg:postcode":"P0M 1K0",
    "sg:province":"ON",
    "wof:name":"Mione, Angelo G DC",
    "wof:placetype":"venue"
},
  "geometry": {"coordinates":[-83.40016199999999,47.843288],"type":"Point"}
}