{
  "type": "Feature",
  "properties": {
    "addr:full":"7 Ingram Dr North York ON M6M 2L7",
    "addr:housenumber":"7",
    "addr:postcode":"m6m 2l7",
    "addr:street":"Ingram Dr",
    "iso:country":"CA",
    "sg:address":"7 Ingram Dr",
    "sg:city":"North York",
    "sg:classifiers":[
        {
            "category":"Freight",
            "type":"Transportation"
        }
    ],
    "sg:phone":"+1 416 242 8800",
    "sg:postcode":"M6M 2L7",
    "sg:province":"ON",
    "sg:tags":[
        "commercial",
        "storage"
    ],
    "wof:name":"Speedy Self Storage",
    "wof:placetype":"venue"
},
  "geometry": {"coordinates":[-79.47487599999999,43.699512],"type":"Point"}
}