{
  "type": "Feature",
  "properties": {
    "addr:full":"849 1/2 Bloor St W Toronto ON M6G 1M3",
    "addr:housenumber":"849 1 / 2",
    "addr:postcode":"m6g 1m3",
    "addr:street":"Bloor St W",
    "iso:country":"CA",
    "sg:address":"849 1/2 Bloor St W",
    "sg:city":"Toronto",
    "sg:classifiers":[
        {
            "category":"Shopping",
            "subcategory":"Musical Instruments",
            "type":"Retail Goods"
        }
    ],
    "sg:phone":"+1 416 516 6445",
    "sg:postcode":"M6G 1M3",
    "sg:province":"ON",
    "wof:name":"Ken Fornetran Woodwinds",
    "wof:placetype":"venue"
},
  "geometry": {"coordinates":[-79.42385101319999,43.6622238159],"type":"Point"}
}