{
  "type": "Feature",
  "properties": {
    "addr:full":"114 Main St Rexton NB E4W 2B3",
    "addr:housenumber":"114",
    "addr:postcode":"e4w 2b3",
    "addr:street":"Main St",
    "iso:country":"CA",
    "sg:address":"114 Main St",
    "sg:city":"Rexton",
    "sg:classifiers":[
        {
            "category":"Insurance",
            "subcategory":"Insurance Agent",
            "type":"Services"
        }
    ],
    "sg:phone":"+1 506 523 6100",
    "sg:postcode":"E4W 2B3",
    "sg:province":"NB",
    "wof:name":"Hutchinson & Warren Ins Svc",
    "wof:placetype":"venue"
},
  "geometry": {"coordinates":[-64.877174,46.649818],"type":"Point"}
}