{
  "type": "Feature",
  "properties": {
    "addr:full":"245 Hodgson Rd Williams Lake BC V2G 3P7",
    "addr:housenumber":"245",
    "addr:postcode":"v2g 3p7",
    "addr:street":"Hodgson Rd",
    "iso:country":"CA",
    "sg:address":"245 Hodgson Rd",
    "sg:city":"Williams Lake",
    "sg:classifiers":[
        {
            "category":"Home & Garden",
            "subcategory":"Building Materials",
            "type":"Retail Goods"
        }
    ],
    "sg:phone":"+1 250 392 3443",
    "sg:postcode":"V2G 3P7",
    "sg:province":"BC",
    "sg:tags":[
        "mixed",
        "concrete"
    ],
    "wof:name":"United Concrete & Gravel Ltd",
    "wof:placetype":"venue"
},
  "geometry": {"coordinates":[-122.13335418699999,52.1152381897],"type":"Point"}
}