{
  "type": "Feature",
  "properties": {
    "addr:full":"4581 Boul Gouin E Montreal-Nord QC H1H 1E6",
    "addr:housenumber":"4581",
    "addr:postcode":"h1h 1e6",
    "addr:street":"Boul Gouin E",
    "iso:country":"CA",
    "sg:address":"4581 Boul Gouin E",
    "sg:city":"Montreal-Nord",
    "sg:classifiers":[
        {
            "category":"Personal",
            "subcategory":"Beauty Salon",
            "type":"Services"
        }
    ],
    "sg:phone":"+1 514 326 2426",
    "sg:postcode":"H1H 1E6",
    "sg:province":"QC",
    "wof:name":"Univers DE LA Beaute",
    "wof:placetype":"venue"
},
  "geometry": {"coordinates":[-73.64110565190001,45.6017074585],"type":"Point"}
}