{
  "type": "Feature",
  "properties": {
    "addr:full":"861 Mcgregor St Winnipeg MB R2V 2H9",
    "addr:housenumber":"861",
    "addr:postcode":"r2v 2h9",
    "addr:street":"Mcgregor St",
    "iso:country":"CA",
    "sg:address":"861 Mcgregor St",
    "sg:city":"Winnipeg",
    "sg:classifiers":[
        {
            "category":"Shopping",
            "subcategory":"Computers & Home Electronics",
            "type":"Retail Goods"
        }
    ],
    "sg:phone":"+1 204 339 1796",
    "sg:postcode":"R2V 2H9",
    "sg:province":"MB",
    "sg:tags":[
        "equipment",
        "dealer"
    ],
    "wof:name":"First Phase Data Ltd",
    "wof:placetype":"venue"
},
  "geometry": {"coordinates":[-97.130028,49.941151],"type":"Point"}
}