{
  "type": "Feature",
  "properties": {
    "addr:full":"191 Rue Fraserville Riviere-Du-Loup QC G5R 2C7",
    "addr:housenumber":"191",
    "addr:postcode":"g5r 2c7",
    "addr:street":"Rue Fraserville Riviere-Du-Loup",
    "iso:country":"CA",
    "sg:address":"191 Rue Fraserville",
    "sg:city":"Riviere-Du-Loup",
    "sg:classifiers":[
        {
            "category":"Food & Beverages",
            "subcategory":"Groceries & Convenience Stores",
            "type":"Retail Goods"
        }
    ],
    "sg:phone":"+1 418 862 9043",
    "sg:postcode":"G5R 2C7",
    "sg:province":"QC",
    "wof:name":"Depanneur Petro Fraserville",
    "wof:placetype":"venue"
},
  "geometry": {"coordinates":[-69.534599,47.817245],"type":"Point"}
}