{
  "type": "Feature",
  "properties": {
    "addr:full":"233 King St Niagara on the Lake ON L0S 1J0",
    "addr:housenumber":"233",
    "addr:postcode":"l0s 1j0",
    "addr:street":"King St;On",
    "iso:country":"CA",
    "sg:address":"233 King St",
    "sg:city":"Niagara on the Lake",
    "sg:classifiers":[
        {
            "category":"Shopping",
            "subcategory":"Books",
            "type":"Retail Goods"
        }
    ],
    "sg:phone":"+1 905 468 2602",
    "sg:postcode":"L0S 1J0",
    "sg:province":"ON",
    "sg:tags":[
        "dealer"
    ],
    "wof:name":"Old Niagara Bookshop",
    "wof:placetype":"venue"
},
  "geometry": {"coordinates":[-79.0717544556,43.2540435791],"type":"Point"}
}