{
  "type": "Feature",
  "properties": {
    "addr:full":"282 Rue Victoria Victoriaville QC G6P 5G5",
    "addr:housenumber":"282",
    "addr:postcode":"g6p 5g5",
    "addr:street":"Rue Victoria",
    "iso:country":"CA",
    "sg:address":"282 Rue Victoria",
    "sg:city":"Victoriaville",
    "sg:classifiers":[
        {
            "category":"Personal",
            "subcategory":"Beauty Salon",
            "type":"Services"
        }
    ],
    "sg:phone":"+1 819 758 6327",
    "sg:postcode":"G6P 5G5",
    "sg:province":"QC",
    "wof:name":"Salon Johanne",
    "wof:placetype":"venue"
},
  "geometry": {"coordinates":[-71.95079800000001,46.052578],"type":"Point"}
}