{
  "type": "Feature",
  "properties": {
    "addr:full":"Calgary AB T2G 2A7",
    "addr:postcode":"t2g 2a7",
    "iso:country":"CA",
    "sg:city":"Calgary",
    "sg:classifiers":[
        {
            "category":"Professional",
            "subcategory":"Business Services",
            "type":"Services"
        }
    ],
    "sg:phone":"+1 403 243 8041",
    "sg:postcode":"T2G 2A7",
    "sg:province":"AB",
    "sg:tags":[
        "interior",
        "consultant",
        "design",
        "decorator"
    ],
    "wof:name":"Watershed Mpn Group",
    "wof:placetype":"venue"
},
  "geometry": {"coordinates":[-114.039688,51.011105],"type":"Point"}
}