{
  "type": "Feature",
  "properties": {
    "addr:full":"742 Granville St Vancouver BC V6Z 1E4",
    "addr:housenumber":"742",
    "addr:postcode":"v6z 1e4",
    "addr:street":"Granville St",
    "iso:country":"CA",
    "sg:address":"742 Granville St",
    "sg:city":"Vancouver",
    "sg:classifiers":[
        {
            "category":"Shopping",
            "subcategory":"Jewelry",
            "type":"Retail Goods"
        }
    ],
    "sg:phone":"+1 604 684 5178",
    "sg:postcode":"V6Z 1E4",
    "sg:province":"BC",
    "sg:tags":[
        "jeweler"
    ],
    "wof:name":"Ideal Jewellery",
    "wof:placetype":"venue"
},
  "geometry": {"coordinates":[-123.118576,49.281975],"type":"Point"}
}