{
  "type": "Feature",
  "properties": {
    "iso:country":"CA",
    "sg:address":"7043 Rue Saint-Hubert",
    "sg:city":"Montreal",
    "sg:classifiers":[
        {
            "category":"Shopping",
            "subcategory":"Shoes",
            "type":"Retail Goods"
        }
    ],
    "sg:phone":"+1 514 270 3910",
    "sg:postcode":"H2S 2N1",
    "sg:province":"QC",
    "wof:name":"Payless Shoe Source",
    "wof:placetype":"venue"
},
  "geometry": {"coordinates":[-73.611366,45.540062],"type":"Point"}
}