{
  "type": "Feature",
  "properties": {
    "addr:full":"1601 Cariboo Hwy Clinton BC V0K 1K0",
    "addr:housenumber":"1601",
    "addr:postcode":"v0k 1k0",
    "addr:street":"Cariboo Hwy",
    "iso:country":"CA",
    "sg:address":"1601 Cariboo Hwy",
    "sg:city":"Clinton",
    "sg:classifiers":[
        {
            "category":"Shopping",
            "subcategory":"Used Merchandise",
            "type":"Retail Goods"
        }
    ],
    "sg:phone":"+1 250 459 7792",
    "sg:postcode":"V0K 1K0",
    "sg:province":"BC",
    "sg:tags":[
        "antique"
    ],
    "wof:name":"North Road Trading Post",
    "wof:placetype":"venue"
},
  "geometry": {"coordinates":[-121.583190918,51.0937614441],"type":"Point"}
}