{
  "type": "Feature",
  "properties": {
    "addr:full":"8 John St Iroquois ON K0E 1K0",
    "addr:housenumber":"8",
    "addr:postcode":"k0e 1k0",
    "addr:street":"John St",
    "iso:country":"CA",
    "sg:address":"8 John St",
    "sg:city":"Iroquois",
    "sg:classifiers":[
        {
            "category":"Manufacturing",
            "subcategory":"Electronics",
            "type":"Manufacturing & Wholesale Goods"
        }
    ],
    "sg:phone":"+1 613 652 4886",
    "sg:postcode":"K0E 1K0",
    "sg:province":"ON",
    "sg:tags":[
        "equipment",
        "television",
        "station"
    ],
    "wof:name":"Ross Video Ltd",
    "wof:placetype":"venue"
},
  "geometry": {"coordinates":[-75.318787,44.848331],"type":"Point"}
}