{
  "type": "Feature",
  "properties": {
    "iso:country":"CA",
    "sg:address":"5008 47 Ave",
    "sg:city":"Bon Accord",
    "sg:classifiers":[
        {
            "category":"Autos & Motor Vehicles",
            "subcategory":"Fuel & Gas Station",
            "type":"Retail Goods"
        }
    ],
    "sg:phone":"+1 780 921 2280",
    "sg:postcode":"T0A 0K0",
    "sg:province":"AB",
    "sg:tags":[
        "grocer",
        "oil"
    ],
    "wof:name":"Winks Convenience Stores-Husky",
    "wof:placetype":"venue"
},
  "geometry": {"coordinates":[-113.413315,53.833099],"type":"Point"}
}