{
  "type": "Feature",
  "properties": {
    "addr:full":"50 Front St Pictou NS B0K 1H0",
    "addr:housenumber":"50",
    "addr:postcode":"b0k 1h0",
    "addr:street":"Front St",
    "iso:country":"CA",
    "sg:address":"50 Front St",
    "sg:city":"Pictou",
    "sg:classifiers":[
        {
            "category":"Insurance",
            "subcategory":"Insurance Agent",
            "type":"Services"
        }
    ],
    "sg:phone":"+1 902 485 4542",
    "sg:postcode":"B0K 1H0",
    "sg:province":"NS",
    "wof:name":"Pictou County Farmers Mutual",
    "wof:placetype":"venue"
},
  "geometry": {"coordinates":[-62.7084236145,45.6759338379],"type":"Point"}
}