{
  "type": "Feature",
  "properties": {
    "addr:full":"2151 Burrard St Vancouver BC V6J 3H7",
    "addr:housenumber":"2151",
    "addr:postcode":"v6j 3h7",
    "addr:street":"Burrard St",
    "iso:country":"CA",
    "sg:address":"2151 Burrard St",
    "sg:city":"Vancouver",
    "sg:classifiers":[
        {
            "category":"Shopping",
            "subcategory":"Bicycles & Sporting Goods",
            "type":"Retail Goods"
        }
    ],
    "sg:phone":"+1 604 739 8990",
    "sg:postcode":"V6J 3H7",
    "sg:province":"BC",
    "wof:name":"Sports Exchange",
    "wof:placetype":"venue"
},
  "geometry": {"coordinates":[-123.145858765,49.266746521],"type":"Point"}
}