{
  "type": "Feature",
  "properties": {
    "addr:full":"5110 Rue Saint-Denis Montreal QC H2J 2M2",
    "addr:housenumber":"5110",
    "addr:postcode":"h2j 2m2",
    "addr:street":"Rue Saint-Denis",
    "iso:country":"CA",
    "sg:address":"5110 Rue Saint-Denis",
    "sg:city":"Montreal",
    "sg:classifiers":[
        {
            "category":"Autos & Motor Vehicles",
            "subcategory":"Fuel & Gas Station",
            "type":"Retail Goods"
        }
    ],
    "sg:phone":"+1 514 274 8742",
    "sg:postcode":"H2J 2M2",
    "sg:province":"QC",
    "sg:tags":[
        "oil"
    ],
    "wof:name":"Ultramar",
    "wof:placetype":"venue"
},
  "geometry": {"coordinates":[-73.58995819090001,45.5269851685],"type":"Point"}
}