{
  "type": "Feature",
  "properties": {
    "addr:full":"Regina SK S4P 1Y3",
    "addr:postcode":"s4p 1y3",
    "iso:country":"CA",
    "sg:city":"Regina",
    "sg:classifiers":[
        {
            "category":"Organizations",
            "subcategory":"Professional Association",
            "type":"Services"
        }
    ],
    "sg:phone":"+1 306 352 7601",
    "sg:postcode":"S4P 1Y3",
    "sg:province":"SK",
    "wof:name":"Better Bus Bureau of Sask Inc",
    "wof:placetype":"venue"
},
  "geometry": {"coordinates":[-104.606719971,50.4459190369],"type":"Point"}
}