{
  "type": "Feature",
  "properties": {
    "iso:country":"CA",
    "sg:address":"2957 Ch Sainte-Marie",
    "sg:city":"Mascouche",
    "sg:classifiers":[
        {
            "category":"Retail",
            "subcategory":"Animal Services",
            "type":"Services"
        }
    ],
    "sg:phone":"+1 450 474 0174",
    "sg:postcode":"J7K 1N6",
    "sg:province":"QC",
    "sg:tags":[
        "pet",
        "grooming",
        "washing"
    ],
    "wof:name":"Studio Canin DE Mascouche Enr",
    "wof:placetype":"venue"
},
  "geometry": {"coordinates":[-73.602753,45.748173],"type":"Point"}
}