{
  "type": "Feature",
  "properties": {
    "addr:full":"374 South Service Rd E Oakville ON L6J 2X6",
    "addr:housenumber":"374",
    "addr:postcode":"l6j 2x6",
    "addr:street":"South Service Rd E",
    "iso:country":"CA",
    "sg:address":"374 South Service Rd E",
    "sg:city":"Oakville",
    "sg:classifiers":[
        {
            "category":"Travel",
            "subcategory":"Hotels & Motels",
            "type":"Entertainment"
        }
    ],
    "sg:phone":"+1 905 849 9500",
    "sg:postcode":"L6J 2X6",
    "sg:province":"ON",
    "wof:name":"Monte Carlo Inn Oakville",
    "wof:placetype":"venue"
},
  "geometry": {"coordinates":[-79.681938,43.461025],"type":"Point"}
}