{
  "type": "Feature",
  "properties": {
    "iso:country":"CA",
    "sg:address":"3035 Boul Le Carrefour",
    "sg:city":"Laval",
    "sg:classifiers":[
        {
            "category":"Restaurant",
            "type":"Food & Drink"
        }
    ],
    "sg:phone":"+1 450 687 6930",
    "sg:postcode":"H7T 1C8",
    "sg:province":"QC",
    "sg:tags":[
        "parcel",
        "gift",
        "ice",
        "parlor",
        "basket",
        "cream"
    ],
    "wof:name":"Laura Secord",
    "wof:placetype":"venue"
},
  "geometry": {"coordinates":[-73.7505493164,45.5680847168],"type":"Point"}
}