{
  "type": "Feature",
  "properties": {
    "iso:country":"CA",
    "sg:address":"PO Box 56612 Rpo Town Square",
    "sg:city":"Markham",
    "sg:classifiers":[
        {
            "category":"Wholesale",
            "subcategory":"Photographic Equipment",
            "type":"Manufacturing & Wholesale Goods"
        }
    ],
    "sg:phone":"+1 905 470 7222",
    "sg:postcode":"L3R 0M6",
    "sg:province":"ON",
    "sg:tags":[
        "audio"
    ],
    "wof:name":"Lamp Source",
    "wof:placetype":"venue"
},
  "geometry": {"coordinates":[-79.339943,43.856033],"type":"Point"}
}