{
  "type": "Feature",
  "properties": {
    "iso:country":"CA",
    "sg:address":"4499 Wellington Rd S",
    "sg:city":"London",
    "sg:classifiers":[
        {
            "category":"Retail",
            "subcategory":"Veterinary Services",
            "type":"Services"
        }
    ],
    "sg:phone":"+1 519 681 4377",
    "sg:postcode":"N6E 2Z8",
    "sg:province":"ON",
    "sg:tags":[
        "veterinarian"
    ],
    "wof:name":"Firth Veterinary Hospital",
    "wof:placetype":"venue"
},
  "geometry": {"coordinates":[-81.208145,42.914505],"type":"Point"}
}