{
  "type": "Feature",
  "properties": {
    "addr:full":"4661 Queen St Niagara Falls ON L2E 2L9",
    "addr:housenumber":"4661",
    "addr:postcode":"l2e 2l9",
    "addr:street":"Queen St",
    "iso:country":"CA",
    "sg:address":"4661 Queen St",
    "sg:city":"Niagara Falls",
    "sg:classifiers":[
        {
            "category":"Education",
            "subcategory":"Special Training",
            "type":"Public Place"
        }
    ],
    "sg:phone":"+1 905 988 1688",
    "sg:postcode":"L2E 2L9",
    "sg:province":"ON",
    "sg:tags":[
        "instruction",
        "driving"
    ],
    "wof:name":"Aapex Driving Academy",
    "wof:placetype":"venue"
},
  "geometry": {"coordinates":[-79.07061767579999,43.10679245],"type":"Point"}
}