{
  "type": "Feature",
  "properties": {
    "addr:full":"Erbs Cove NB E5N 7Y7",
    "addr:postcode":"e5n 7y7",
    "addr:street":"Cove",
    "iso:country":"CA",
    "sg:city":"Erbs Cove",
    "sg:classifiers":[
        {
            "category":"Recreation",
            "subcategory":"Marina",
            "type":"Entertainment"
        }
    ],
    "sg:phone":"+1 506 832 7373",
    "sg:postcode":"E5N 7Y7",
    "sg:province":"NB",
    "wof:name":"Bellisle Bay Marina",
    "wof:placetype":"venue"
},
  "geometry": {"coordinates":[-65.936195,45.58511],"type":"Point"}
}