{
  "type": "Feature",
  "properties": {
    "iso:country":"CA",
    "sg:address":"2103 Edmonton Trail NE",
    "sg:city":"Calgary",
    "sg:classifiers":[
        {
            "category":"Retail",
            "subcategory":"Animal Services",
            "type":"Services"
        }
    ],
    "sg:phone":"+1 403 277 9194",
    "sg:postcode":"T2E 3M4",
    "sg:province":"AB",
    "sg:tags":[
        "pet",
        "grooming",
        "washing"
    ],
    "wof:name":"A Royal Touch Dog Grooming",
    "wof:placetype":"venue"
},
  "geometry": {"coordinates":[-114.056297302,51.0707321167],"type":"Point"}
}