{
  "type": "Feature",
  "properties": {
    "addr:full":"24 Armstrong St Orangeville ON L9W 1M1",
    "addr:housenumber":"24",
    "addr:postcode":"l9w 1m1",
    "addr:street":"Armstrong St",
    "iso:country":"CA",
    "sg:address":"24 Armstrong St",
    "sg:city":"Orangeville",
    "sg:classifiers":[
        {
            "category":"Retail",
            "subcategory":"Animal Services",
            "type":"Services"
        }
    ],
    "sg:phone":"+1 519 940 4464",
    "sg:postcode":"L9W 1M1",
    "sg:province":"ON",
    "sg:tags":[
        "pet",
        "grooming",
        "washing"
    ],
    "wof:name":"Dog Gone Glamorous",
    "wof:placetype":"venue"
},
  "geometry": {"coordinates":[-80.094475,43.918606],"type":"Point"}
}