{
  "type": "Feature",
  "properties": {
    "iso:country":"CA",
    "sg:address":"1632 Rue Stanley",
    "sg:city":"Sainte-Foy",
    "sg:classifiers":[
        {
            "category":"Social Services",
            "type":"Services"
        }
    ],
    "sg:phone":"+1 418 650 0890",
    "sg:postcode":"G1W 3T2",
    "sg:province":"QC",
    "sg:tags":[
        "employee",
        "assistance",
        "program",
        "psychologist"
    ],
    "wof:name":"Consultants Sage Inc",
    "wof:placetype":"venue"
},
  "geometry": {"coordinates":[-71.2822189331,46.7595367432],"type":"Point"}
}