{
  "type": "Feature",
  "properties": {
    "addr:full":"Lacolle QC J0J 1J0",
    "addr:postcode":"j0j 1j0",
    "iso:country":"CA",
    "sg:city":"Lacolle",
    "sg:classifiers":[
        {
            "category":"Restaurant",
            "type":"Food & Drink"
        }
    ],
    "sg:phone":"+1 450 246 3897",
    "sg:postcode":"J0J 1J0",
    "sg:province":"QC",
    "wof:name":"Brochetterie Pharos Inc",
    "wof:placetype":"venue"
},
  "geometry": {"coordinates":[-73.372986,45.081886],"type":"Point"}
}