{
  "type": "Feature",
  "properties": {
    "addr:full":"16980 Keele St Kettleby ON L0G 1J0",
    "addr:housenumber":"16980",
    "addr:postcode":"l0g 1j0",
    "addr:street":"Keele St",
    "iso:country":"CA",
    "sg:address":"16980 Keele St",
    "sg:city":"Kettleby",
    "sg:classifiers":[
        {
            "category":"Recreation",
            "type":"Entertainment"
        }
    ],
    "sg:phone":"+1 905 751 0440",
    "sg:postcode":"L0G 1J0",
    "sg:province":"ON",
    "sg:tags":[
        "stable"
    ],
    "wof:name":"Destiny Ridge",
    "wof:placetype":"venue"
},
  "geometry": {"coordinates":[-79.553787,44.026047],"type":"Point"}
}