{
  "type": "Feature",
  "properties": {
    "addr:full":"62 Doucet Ch Foster QC J0E 1R0",
    "addr:housenumber":"62",
    "addr:postcode":"j0e 1r0",
    "addr:street":"Doucet Ch Foster",
    "iso:country":"CA",
    "sg:address":"62 Doucet Ch",
    "sg:city":"Foster",
    "sg:classifiers":[
        {
            "category":"Building & Trades",
            "subcategory":"Construction",
            "type":"Services"
        }
    ],
    "sg:phone":"+1 450 539 1230",
    "sg:postcode":"J0E 1R0",
    "sg:province":"QC",
    "sg:tags":[
        "insulation",
        "heat",
        "aluminum"
    ],
    "wof:name":"Doucet Aluminium Enr",
    "wof:placetype":"venue"
},
  "geometry": {"coordinates":[-72.495422,45.295929],"type":"Point"}
}