{
  "type": "Feature",
  "properties": {
    "addr:full":"Calgary AB T2A 0W3",
    "addr:postcode":"t2a 0w3",
    "iso:country":"CA",
    "sg:city":"Calgary",
    "sg:classifiers":[
        {
            "category":"Manufacturing",
            "subcategory":"Metals",
            "type":"Manufacturing & Wholesale Goods"
        }
    ],
    "sg:phone":"+1 403 235 1090",
    "sg:postcode":"T2A 0W3",
    "sg:province":"AB",
    "sg:tags":[
        "repairing",
        "automobile",
        "heat",
        "radiator"
    ],
    "wof:name":"Arctic Radiator & Air Cond",
    "wof:placetype":"venue"
},
  "geometry": {"coordinates":[-113.952720642,51.0377426147],"type":"Point"}
}