{
  "type": "Feature",
  "properties": {
    "addr:full":"1056 Gardiners Rd Kingston ON K7P 1R7",
    "addr:housenumber":"1056",
    "addr:postcode":"k7p 1r7",
    "addr:street":"Gardiners Rd",
    "iso:country":"CA",
    "sg:address":"1056 Gardiners Rd",
    "sg:city":"Kingston",
    "sg:classifiers":[
        {
            "category":"Building & Trades",
            "subcategory":"Electrical",
            "type":"Services"
        }
    ],
    "sg:phone":"+1 613 634 3008",
    "sg:postcode":"K7P 1R7",
    "sg:province":"ON",
    "sg:tags":[
        "electric",
        "contractor"
    ],
    "wof:name":"Wylie Electric",
    "wof:placetype":"venue"
},
  "geometry": {"coordinates":[-76.56861877439999,44.2619438171],"type":"Point"}
}