{
  "type": "Feature",
  "properties": {
    "addr:full":"20 Delatre St Woodstock ON N4S 6B5",
    "addr:housenumber":"20",
    "addr:postcode":"n4s 6b5",
    "addr:street":"Delatre St",
    "iso:country":"CA",
    "sg:address":"20 Delatre St",
    "sg:city":"Woodstock",
    "sg:classifiers":[
        {
            "category":"Wholesale",
            "subcategory":"Office Equipment",
            "type":"Manufacturing & Wholesale Goods"
        }
    ],
    "sg:phone":"+1 519 421 0555",
    "sg:postcode":"N4S 6B5",
    "sg:province":"ON",
    "sg:tags":[
        "accounting",
        "bookkeeping",
        "system"
    ],
    "wof:name":"Independent Accounting Svc",
    "wof:placetype":"venue"
},
  "geometry": {"coordinates":[-80.7639007568,43.1297683716],"type":"Point"}
}