{
  "type": "Feature",
  "properties": {
    "addr:full":"737 Av Gagnon Sainte-Marie QC G6E 1R7",
    "addr:housenumber":"737",
    "addr:postcode":"g6e 1r7",
    "addr:street":"Av Gagnon",
    "iso:country":"CA",
    "sg:address":"737 Av Gagnon",
    "sg:city":"Sainte-Marie",
    "sg:classifiers":[
        {
            "category":"Building & Trades",
            "subcategory":"Electrical",
            "type":"Services"
        }
    ],
    "sg:phone":"+1 418 387 8245",
    "sg:postcode":"G6E 1R7",
    "sg:province":"QC",
    "sg:tags":[
        "electric",
        "contractor"
    ],
    "wof:name":"Carl Audet Inc",
    "wof:placetype":"venue"
},
  "geometry": {"coordinates":[-71.005875,46.435822],"type":"Point"}
}