{
  "type": "Feature",
  "properties": {
    "iso:country":"CA",
    "sg:address":"330 Washington St",
    "sg:city":"New Glasgow",
    "sg:classifiers":[
        {
            "category":"Organizations",
            "subcategory":"Religious Organization",
            "type":"Services"
        }
    ],
    "sg:phone":"+1 902 752 1360",
    "sg:postcode":"B2H 3M1",
    "sg:province":"NS",
    "sg:tags":[
        "church"
    ],
    "wof:name":"Second New United Baptist Chr",
    "wof:placetype":"venue"
},
  "geometry": {"coordinates":[-62.6420555115,45.5826835632],"type":"Point"}
}