{
  "type": "Feature",
  "properties": {
    "addr:full":"154 Bethel Rd Paris ON N3L 3E3",
    "addr:housenumber":"154",
    "addr:postcode":"n3l 3e3",
    "addr:street":"Bethel Rd",
    "iso:country":"CA",
    "sg:address":"154 Bethel Rd",
    "sg:city":"Paris",
    "sg:classifiers":[
        {
            "category":"Organizations",
            "subcategory":"Religious Organization",
            "type":"Services"
        }
    ],
    "sg:phone":"+1 519 442 3018",
    "sg:postcode":"N3L 3E3",
    "sg:province":"ON",
    "sg:tags":[
        "church"
    ],
    "wof:name":"Bethel Stone United Church",
    "wof:placetype":"venue"
},
  "geometry": {"coordinates":[-80.38649700000001,43.149689],"type":"Point"}
}