{
  "type": "Feature",
  "properties": {
    "addr:full":"9 Boul Marie-Victorin Candiac QC J5R 4S8",
    "addr:housenumber":"9",
    "addr:postcode":"j5r 4s8",
    "addr:street":"Boul Marie-Victorin",
    "iso:country":"CA",
    "sg:address":"9 Boul Marie-Victorin",
    "sg:city":"Candiac",
    "sg:classifiers":[
        {
            "category":"Manufacturing",
            "subcategory":"Rubber & Plastics",
            "type":"Manufacturing & Wholesale Goods"
        }
    ],
    "sg:phone":"+1 450 659 2921",
    "sg:postcode":"J5R 4S8",
    "sg:province":"QC",
    "sg:tags":[
        "mold",
        "maker"
    ],
    "wof:name":"Precimold Inc",
    "wof:placetype":"venue"
},
  "geometry": {"coordinates":[-73.51469400000001,45.404835],"type":"Point"}
}