{
  "type": "Feature",
  "properties": {
    "addr:full":"2925 6th Ave W Prince Albert SK S6V 5L7",
    "addr:housenumber":"2925",
    "addr:postcode":"s6v 5l7",
    "addr:street":"6Th Ave W",
    "iso:country":"CA",
    "sg:address":"2925 6th Ave W",
    "sg:city":"Prince Albert",
    "sg:classifiers":[
        {
            "category":"Social Services",
            "type":"Services"
        }
    ],
    "sg:phone":"+1 306 764 1694",
    "sg:postcode":"S6V 5L7",
    "sg:province":"SK",
    "sg:tags":[
        "counselor",
        "marriage",
        "family"
    ],
    "wof:name":"A New Way Professional",
    "wof:placetype":"venue"
},
  "geometry": {"coordinates":[-105.770088,53.186569],"type":"Point"}
}