{
  "type": "Feature",
  "properties": {
    "addr:full":"9 Mill St Bolton ON L7E 1C1",
    "addr:housenumber":"9",
    "addr:postcode":"l7e 1c1",
    "addr:street":"Mill St",
    "iso:country":"CA",
    "sg:address":"9 Mill St",
    "sg:city":"Bolton",
    "sg:classifiers":[
        {
            "category":"Retail",
            "subcategory":"Auto Repair",
            "type":"Services"
        }
    ],
    "sg:phone":"+1 905 857 3715",
    "sg:postcode":"L7E 1C1",
    "sg:province":"ON",
    "sg:tags":[
        "repairing",
        "automobile"
    ],
    "wof:name":"Auto Block Auto Repair Inc",
    "wof:placetype":"venue"
},
  "geometry": {"coordinates":[-79.739555,43.880959],"type":"Point"}
}