{
  "type": "Feature",
  "properties": {
    "addr:full":"9110 Highway 12 Orillia ON L3V 6H2",
    "addr:housenumber":"9110",
    "addr:postcode":"l3v 6h2",
    "addr:street":"Highway 12",
    "iso:country":"CA",
    "sg:address":"9110 Highway 12",
    "sg:city":"Orillia",
    "sg:classifiers":[
        {
            "category":"Cinema",
            "subcategory":"Movie Rental",
            "type":"Entertainment"
        }
    ],
    "sg:phone":"+1 705 326 9270",
    "sg:postcode":"L3V 6H2",
    "sg:province":"ON",
    "sg:tags":[
        "leasing",
        "video",
        "tape"
    ],
    "wof:name":"Patterson's Corner Store",
    "wof:placetype":"venue"
},
  "geometry": {"coordinates":[-79.418228,44.60659],"type":"Point"}
}