{
  "type": "Feature",
  "properties": {
    "addr:full":"515 28th St W Saskatoon SK S7L 4R5",
    "addr:housenumber":"515",
    "addr:postcode":"s7l 4r5",
    "addr:street":"28Th St W",
    "iso:country":"CA",
    "sg:address":"515 28th St W",
    "sg:city":"Saskatoon",
    "sg:classifiers":[
        {
            "category":"Organizations",
            "subcategory":"Religious Organization",
            "type":"Services"
        }
    ],
    "sg:phone":"+1 306 242 0165",
    "sg:postcode":"S7L 4R5",
    "sg:province":"SK",
    "sg:tags":[
        "church"
    ],
    "wof:name":"Christ Church-Anglican",
    "wof:placetype":"venue"
},
  "geometry": {"coordinates":[-106.677078247,52.1360321045],"type":"Point"}
}