{
  "type": "Feature",
  "properties": {
    "addr:full":"23 Wilton Cres Ottawa ON K1S 2T4",
    "addr:housenumber":"23",
    "addr:postcode":"k1s 2t4",
    "addr:street":"Wilton Cres",
    "iso:country":"CA",
    "sg:address":"23 Wilton Cres",
    "sg:city":"Ottawa",
    "sg:classifiers":[
        {
            "category":"Professional",
            "subcategory":"Business Services",
            "type":"Services"
        }
    ],
    "sg:phone":"+1 613 237 7897",
    "sg:postcode":"K1S 2T4",
    "sg:province":"ON",
    "sg:tags":[
        "arbitration"
    ],
    "wof:name":"M K Wexler Adr Consultants",
    "wof:placetype":"venue"
},
  "geometry": {"coordinates":[-75.68654632569999,45.3974227905],"type":"Point"}
}