{
  "type": "Feature",
  "properties": {
    "addr:full":"Richmond BC V6Y 3Y8",
    "addr:postcode":"v6y 3y8",
    "iso:country":"CA",
    "sg:city":"Richmond",
    "sg:classifiers":[
        {
            "category":"Restaurant",
            "type":"Food & Drink"
        }
    ],
    "sg:phone":"+1 604 275 2929",
    "sg:postcode":"V6Y 3Y8",
    "sg:province":"BC",
    "sg:tags":[
        "pizza"
    ],
    "wof:name":"Round Table Pizza Ltd",
    "wof:placetype":"venue"
},
  "geometry": {"coordinates":[-123.12750200000001,49.155323],"type":"Point"}
}