{
  "type": "Feature",
  "properties": {
    "addr:full":"4 Silverview Dr North York ON M2M 2B3",
    "addr:housenumber":"4",
    "addr:postcode":"m2m 2b3",
    "addr:street":"Silverview Dr",
    "iso:country":"CA",
    "sg:address":"4 Silverview Dr",
    "sg:city":"North York",
    "sg:classifiers":[
        {
            "category":"Building & Trades",
            "subcategory":"Electrical",
            "type":"Services"
        }
    ],
    "sg:phone":"+1 416 229 2711",
    "sg:postcode":"M2M 2B3",
    "sg:province":"ON",
    "sg:tags":[
        "electric",
        "contractor"
    ],
    "wof:name":"Bestway Electric",
    "wof:placetype":"venue"
},
  "geometry": {"coordinates":[-79.4099807739,43.7868423462],"type":"Point"}
}