{
  "type": "Feature",
  "properties": {
    "iso:country":"CA",
    "sg:city":"Mississauga",
    "sg:classifiers":[
        {
            "category":"Professional",
            "subcategory":"Research",
            "type":"Services"
        }
    ],
    "sg:phone":"+1 905 795 2888",
    "sg:postcode":"L5T 2N5",
    "sg:province":"ON",
    "sg:tags":[
        "laboratory",
        "computer",
        "software"
    ],
    "wof:name":"01 Communique Laboratory Inc",
    "wof:placetype":"venue"
},
  "geometry": {"coordinates":[-79.654938,43.659462],"type":"Point"}
}