{
  "type": "Feature",
  "properties": {
    "iso:country":"CA",
    "sg:address":"15 Elizabeth St # M15",
    "sg:city":"Orangeville",
    "sg:classifiers":[
        {
            "category":"Health Services",
            "subcategory":"Health Practitioner",
            "type":"Services"
        }
    ],
    "sg:phone":"+1 519 941 1314",
    "sg:postcode":"L9W 3X3",
    "sg:province":"ON",
    "sg:tags":[
        "pathologist",
        "speech",
        "rehabilitation"
    ],
    "wof:name":"Orangeville Speech & Language",
    "wof:placetype":"venue"
},
  "geometry": {"coordinates":[-80.1003189087,43.9208221436],"type":"Point"}
}