{
  "type": "Feature",
  "properties": {
    "addr:full":"Lamont AB T0B 2R0",
    "addr:postcode":"t0b 2r0",
    "iso:country":"CA",
    "sg:city":"Lamont",
    "sg:classifiers":[
        {
            "category":"Retail",
            "subcategory":"Auto Repair",
            "type":"Services"
        }
    ],
    "sg:phone":"+1 780 895 2882",
    "sg:postcode":"T0B 2R0",
    "sg:province":"AB",
    "sg:tags":[
        "repairing",
        "automobile"
    ],
    "wof:name":"Price Automotive Ltd",
    "wof:placetype":"venue"
},
  "geometry": {"coordinates":[-112.781059,53.761135],"type":"Point"}
}