{
  "type": "Feature",
  "properties": {
    "addr:full":"Parksville BC V9P 2B9",
    "addr:postcode":"v9p 2b9",
    "iso:country":"CA",
    "sg:city":"Parksville",
    "sg:classifiers":[
        {
            "category":"Home & Garden",
            "subcategory":"Building Materials",
            "type":"Retail Goods"
        }
    ],
    "sg:phone":"+1 250 248 4227",
    "sg:postcode":"V9P 2B9",
    "sg:province":"BC",
    "sg:tags":[
        "glass",
        "window",
        "plate"
    ],
    "wof:name":"Gator Auto Glass",
    "wof:placetype":"venue"
},
  "geometry": {"coordinates":[-124.32453155499999,49.3070106506],"type":"Point"}
}