{
  "type": "Feature",
  "properties": {
    "addr:full":"32915 Mission Way #A Mission BC V2V 6E4",
    "addr:housenumber":"32915",
    "addr:postcode":"v2v 6e4",
    "addr:street":"Mission Way # A",
    "iso:country":"CA",
    "sg:address":"32915 Mission Way #A",
    "sg:city":"Mission",
    "sg:classifiers":[
        {
            "category":"Freight",
            "type":"Transportation"
        }
    ],
    "sg:phone":"+1 604 826 5866",
    "sg:postcode":"V2V 6E4",
    "sg:province":"BC",
    "sg:tags":[
        "trucking"
    ],
    "wof:name":"Cousins Transport Systems Ltd",
    "wof:placetype":"venue"
},
  "geometry": {"coordinates":[-122.282822,49.159988],"type":"Point"}
}