{
  "type": "Feature",
  "properties": {
    "addr:full":"2771 Viscount Way Richmond BC V6V 2X4",
    "addr:housenumber":"2771",
    "addr:postcode":"v6v 2x4",
    "addr:street":"Viscount Way",
    "iso:country":"CA",
    "sg:address":"2771 Viscount Way",
    "sg:city":"Richmond",
    "sg:classifiers":[
        {
            "category":"Manufacturing",
            "subcategory":"Metals",
            "type":"Manufacturing & Wholesale Goods"
        }
    ],
    "sg:phone":"+1 604 231 8923",
    "sg:postcode":"V6V 2X4",
    "sg:province":"BC",
    "sg:tags":[
        "steel"
    ],
    "wof:name":"Inca Metal Cutting Ltd",
    "wof:placetype":"venue"
},
  "geometry": {"coordinates":[-123.079071,49.193443],"type":"Point"}
}