{
  "type": "Feature",
  "properties": {
    "addr:full":"4617 41 St Camrose AB T4V 2Y8",
    "addr:housenumber":"4617",
    "addr:postcode":"t4v 2y8",
    "addr:street":"41 St",
    "iso:country":"CA",
    "sg:address":"4617 41 St",
    "sg:city":"Camrose",
    "sg:classifiers":[
        {
            "category":"Wholesale",
            "subcategory":"Durable Goods & Equipment",
            "type":"Manufacturing & Wholesale Goods"
        }
    ],
    "sg:phone":"+1 780 672 7640",
    "sg:postcode":"T4V 2Y8",
    "sg:province":"AB",
    "sg:tags":[
        "fire",
        "extinguisher",
        "glove"
    ],
    "wof:name":"Abc Fire Safety Ltd",
    "wof:placetype":"venue"
},
  "geometry": {"coordinates":[-112.809753,53.012955],"type":"Point"}
}