{
  "type": "Feature",
  "properties": {
    "iso:country":"CA",
    "sg:city":"Mont-Saint-Hilaire",
    "sg:classifiers":[
        {
            "category":"Personal",
            "subcategory":"Beauty Salon",
            "type":"Services"
        }
    ],
    "sg:phone":"+1 450 446 9185",
    "sg:postcode":"J3H 3N9",
    "sg:province":"QC",
    "wof:name":"GA ma Coiffure Stylistes",
    "wof:placetype":"venue"
},
  "geometry": {"coordinates":[-73.1839752197,45.5650062561],"type":"Point"}
}