{
  "type": "Feature",
  "properties": {
    "addr:full":"720 Rue Sainte-Therese O Alma QC G8B 4M9",
    "addr:housenumber":"720",
    "addr:postcode":"g8b 4m9",
    "addr:street":"Rue Sainte-Therese O",
    "iso:country":"CA",
    "sg:address":"720 Rue Sainte-Therese O",
    "sg:city":"Alma",
    "sg:classifiers":[
        {
            "category":"Building & Trades",
            "subcategory":"Construction",
            "type":"Services"
        }
    ],
    "sg:phone":"+1 418 668 3768",
    "sg:postcode":"G8B 4M9",
    "sg:province":"QC",
    "sg:tags":[
        "concrete",
        "contractor"
    ],
    "wof:name":"Ciments Gtj Ltee",
    "wof:placetype":"venue"
},
  "geometry": {"coordinates":[-71.648422,48.55698],"type":"Point"}
}