{
  "type": "Feature",
  "properties": {
    "addr:full":"7396 Rue Saint-Hubert Montreal QC H2R 2N3",
    "addr:housenumber":"7396",
    "addr:postcode":"h2r 2n3",
    "addr:street":"Rue Saint-Hubert",
    "iso:country":"CA",
    "sg:address":"7396 Rue Saint-Hubert",
    "sg:city":"Montreal",
    "sg:classifiers":[
        {
            "category":"Shopping",
            "subcategory":"Clothing, Apparel, & Fashions",
            "type":"Retail Goods"
        }
    ],
    "sg:phone":"+1 514 271 5771",
    "sg:postcode":"H2R 2N3",
    "sg:province":"QC",
    "sg:tags":[
        "tailor",
        "furnishing"
    ],
    "wof:name":"Giantonio Le Maitre Tailleur",
    "wof:placetype":"venue"
},
  "geometry": {"coordinates":[-73.616417,45.542049],"type":"Point"}
}