{
  "type": "Feature",
  "properties": {
    "addr:full":"13608 109A Ave NW # 4 Edmonton AB T5M 2J8",
    "addr:housenumber":"13608",
    "addr:postcode":"t5m 2j8",
    "addr:street":"109A Ave Nw # 4",
    "iso:country":"CA",
    "sg:address":"13608 109A Ave NW # 4",
    "sg:city":"Edmonton",
    "sg:classifiers":[
        {
            "category":"Building & Trades",
            "subcategory":"Landscaping Services",
            "type":"Services"
        }
    ],
    "sg:phone":"+1 780 425 5994",
    "sg:postcode":"T5M 2J8",
    "sg:province":"AB",
    "sg:tags":[
        "lawn",
        "maintenance",
        "grounds"
    ],
    "wof:name":"Pronto Lawn Maintenance Ltd",
    "wof:placetype":"venue"
},
  "geometry": {"coordinates":[-113.557273865,53.5559463501],"type":"Point"}
}