{
  "type": "Feature",
  "properties": {
    "addr:full":"43 Marion St Winnipeg MB R2H 0S8",
    "addr:housenumber":"43",
    "addr:postcode":"r2h 0s8",
    "addr:street":"Marion St",
    "iso:country":"CA",
    "sg:address":"43 Marion St",
    "sg:city":"Winnipeg",
    "sg:classifiers":[
        {
            "category":"Shopping",
            "subcategory":"Optical Goods",
            "type":"Retail Goods"
        }
    ],
    "sg:phone":"+1 204 231 0375",
    "sg:postcode":"R2H 0S8",
    "sg:province":"MB",
    "sg:tags":[
        "optician"
    ],
    "wof:name":"Peoples Optical",
    "wof:placetype":"venue"
},
  "geometry": {"coordinates":[-97.1264801025,49.8814353943],"type":"Point"}
}