{
  "type": "Feature",
  "properties": {
    "addr:full":"Toronto ON M5C 1B5",
    "addr:postcode":"m5c 1b5",
    "iso:country":"CA",
    "sg:city":"Toronto",
    "sg:classifiers":[
        {
            "category":"Professional",
            "subcategory":"Employment Agencies",
            "type":"Services"
        }
    ],
    "sg:phone":"+1 416 362 2630",
    "sg:postcode":"M5C 1B5",
    "sg:province":"ON",
    "sg:tags":[
        "opportunity"
    ],
    "wof:name":"Quad Search Inc",
    "wof:placetype":"venue"
},
  "geometry": {"coordinates":[-79.3775939941,43.6493225098],"type":"Point"}
}