{
  "type": "Feature",
  "properties": {
    "addr:full":"69 Rue Pelletier Saint-Quentin NB E8A 1Y4",
    "addr:housenumber":"69",
    "addr:postcode":"e8a 1y4",
    "addr:street":"Rue Pelletier",
    "iso:country":"CA",
    "sg:address":"69 Rue Pelletier",
    "sg:city":"Saint-Quentin",
    "sg:classifiers":[
        {
            "category":"Organizations",
            "subcategory":"Membership Organization",
            "type":"Services"
        }
    ],
    "sg:phone":"+1 506 235 9188",
    "sg:postcode":"E8A 1Y4",
    "sg:province":"NB",
    "wof:name":"Club Communautaire Hockey Mnr",
    "wof:placetype":"venue"
},
  "geometry": {"coordinates":[-67.3876571655,47.5121383667],"type":"Point"}
}