{
  "type": "Feature",
  "properties": {
    "addr:full":"4795 Rue Sainte-Catherine O Westmount QC H3Z 1S8",
    "addr:housenumber":"4795",
    "addr:postcode":"h3z 1s8",
    "addr:street":"Rue Sainte-Catherine O",
    "iso:country":"CA",
    "sg:address":"4795 Rue Sainte-Catherine O",
    "sg:city":"Westmount",
    "sg:classifiers":[
        {
            "category":"Professional",
            "subcategory":"Management & Consulting",
            "type":"Services"
        }
    ],
    "sg:phone":"+1 514 846 7223",
    "sg:postcode":"H3Z 1S8",
    "sg:province":"QC",
    "sg:tags":[
        "training",
        "sales"
    ],
    "wof:name":"Mvm Communications",
    "wof:placetype":"venue"
},
  "geometry": {"coordinates":[-73.597595,45.47802],"type":"Point"}
}