{
  "type": "Feature",
  "properties": {
    "addr:full":"Provost AB T0B 3S0",
    "addr:postcode":"t0b 3s0",
    "iso:country":"CA",
    "sg:city":"Provost",
    "sg:classifiers":[
        {
            "category":"Professional",
            "subcategory":"Management & Consulting",
            "type":"Services"
        }
    ],
    "sg:phone":"+1 780 753 6996",
    "sg:postcode":"T0B 3S0",
    "sg:province":"AB",
    "sg:tags":[
        "consultant",
        "training",
        "safety"
    ],
    "wof:name":"T Mc Nalley's Oilfield Svc",
    "wof:placetype":"venue"
},
  "geometry": {"coordinates":[-110.264106751,52.3509063721],"type":"Point"}
}