{
  "type": "Feature",
  "properties": {
    "addr:full":"Pointe-Aux-Trembles QC H1A 3W2",
    "addr:postcode":"h1a 3w2",
    "iso:country":"CA",
    "sg:city":"Pointe-Aux-Trembles",
    "sg:classifiers":[
        {
            "category":"Health Services",
            "subcategory":"Doctor",
            "type":"Services"
        }
    ],
    "sg:phone":"+1 514 642 2002",
    "sg:postcode":"H1A 3W2",
    "sg:province":"QC",
    "sg:tags":[
        "clinic"
    ],
    "wof:name":"Centre Chiropratique Pat A Trm",
    "wof:placetype":"venue"
},
  "geometry": {"coordinates":[-73.50904083250001,45.6569900513],"type":"Point"}
}