{
  "type": "Feature",
  "properties": {
    "addr:full":"Markham ON L3R 1M5",
    "addr:postcode":"l3r 1m5",
    "iso:country":"CA",
    "sg:city":"Markham",
    "sg:classifiers":[
        {
            "category":"Government",
            "subcategory":"Office",
            "type":"Public Place"
        }
    ],
    "sg:phone":"+1 905 477 2559",
    "sg:postcode":"L3R 1M5",
    "sg:province":"ON",
    "wof:name":"Ontario Driver & Vehicle",
    "wof:placetype":"venue"
},
  "geometry": {"coordinates":[-79.33994300000001,43.856033],"type":"Point"}
}