{
  "type": "Feature",
  "properties": {
    "iso:country":"CA",
    "sg:address":"26 Ontario St N",
    "sg:city":"Grand Bend",
    "sg:classifiers":[
        {
            "category":"Travel",
            "subcategory":"Campground",
            "type":"Entertainment"
        }
    ],
    "sg:phone":"+1 519 238 5625",
    "sg:postcode":"N0M 1T0",
    "sg:province":"ON",
    "wof:name":"Townsite Rv Park",
    "wof:placetype":"venue"
},
  "geometry": {"coordinates":[-81.7554931641,43.3134841919],"type":"Point"}
}