{
  "type": "Feature",
  "properties": {
    "addr:full":"434 Rang DE L'Acadie Saint-Antoine-Sur-Richelieu QC J0L 1R0",
    "addr:housenumber":"434",
    "addr:postcode":"j0l 1r0",
    "addr:street":"Rang De L'Acadie",
    "iso:country":"CA",
    "sg:address":"434 Rang DE L'Acadie",
    "sg:city":"Saint-Antoine-Sur-Richelieu",
    "sg:classifiers":[
        {
            "category":"Home & Garden",
            "subcategory":"Household Appliances",
            "type":"Retail Goods"
        }
    ],
    "sg:phone":"+1 450 787 2694",
    "sg:postcode":"J0L 1R0",
    "sg:province":"QC",
    "sg:tags":[
        "refrigerator",
        "air",
        "conditioning",
        "freezer",
        "room"
    ],
    "wof:name":"Fred Frigo Refrigeration",
    "wof:placetype":"venue"
},
  "geometry": {"coordinates":[-73.23998260499999,45.7179336548],"type":"Point"}
}