{
  "type": "Feature",
  "properties": {
    "addr:full":"3188 Route 307 Wallace NS B0K 1Y0",
    "addr:housenumber":"3188",
    "addr:postcode":"b0k 1y0",
    "addr:street":"Route 307",
    "iso:country":"CA",
    "sg:address":"3188 Route 307",
    "sg:city":"Wallace",
    "sg:classifiers":[
        {
            "category":"Freight",
            "type":"Transportation"
        }
    ],
    "sg:phone":"+1 902 257 2999",
    "sg:postcode":"B0K 1Y0",
    "sg:province":"NS",
    "sg:tags":[
        "trucking"
    ],
    "wof:name":"Jerry S Coulter Ltd",
    "wof:placetype":"venue"
},
  "geometry": {"coordinates":[-63.476177,45.813232],"type":"Point"}
}