{
  "type": "Feature",
  "properties": {
    "addr:full":"3277 Dufferin St North York ON M6A 2T4",
    "addr:housenumber":"3277",
    "addr:postcode":"m6a 2t4",
    "addr:street":"Dufferin St",
    "iso:country":"CA",
    "sg:address":"3277 Dufferin St",
    "sg:city":"North York",
    "sg:classifiers":[
        {
            "category":"Restaurant",
            "type":"Food & Drink"
        }
    ],
    "sg:phone":"+1 416 787 3929",
    "sg:postcode":"M6A 2T4",
    "sg:province":"ON",
    "wof:name":"Fisherman's Corner Fish & Chip",
    "wof:placetype":"venue"
},
  "geometry": {"coordinates":[-79.4560546875,43.7210426331],"type":"Point"}
}