{
  "type": "Feature",
  "properties": {
    "addr:full":"30 Coventry Rd Brampton ON L6T 5P9",
    "addr:housenumber":"30",
    "addr:postcode":"l6t 5p9",
    "addr:street":"Coventry Rd",
    "iso:country":"CA",
    "sg:address":"30 Coventry Rd",
    "sg:city":"Brampton",
    "sg:classifiers":[
        {
            "category":"Shopping",
            "subcategory":"Shoes",
            "type":"Retail Goods"
        }
    ],
    "sg:phone":"+1 905 799 2283",
    "sg:postcode":"L6T 5P9",
    "sg:province":"ON",
    "wof:name":"Payless Shoe Source",
    "wof:placetype":"venue"
},
  "geometry": {"coordinates":[-79.6947097778,43.7394180298],"type":"Point"}
}