{
  "type": "Feature",
  "properties": {
    "iso:country":"CA",
    "sg:city":"South River",
    "sg:classifiers":[
        {
            "category":"Education",
            "subcategory":"School",
            "type":"Public Place"
        }
    ],
    "sg:phone":"+1 705 386 0764",
    "sg:postcode":"P0A 1X0",
    "sg:province":"ON",
    "sg:tags":[
        "organization",
        "social",
        "welfare"
    ],
    "wof:name":"East Parry Sound Literacy Cncl",
    "wof:placetype":"venue"
},
  "geometry": {"coordinates":[-79.3818359375,45.8405189514],"type":"Point"}
}