{
  "type": "Feature",
  "properties": {
    "iso:country":"CA",
    "sg:address":"PO Box 119",
    "sg:city":"Britt",
    "sg:classifiers":[
        {
            "category":"Freight",
            "type":"Transportation"
        }
    ],
    "sg:phone":"+1 705 383 0448",
    "sg:postcode":"P0G 1A0",
    "sg:province":"ON",
    "sg:tags":[
        "trucking"
    ],
    "wof:name":"Barron Industries",
    "wof:placetype":"venue"
},
  "geometry": {"coordinates":[-80.555015564,45.7767791748],"type":"Point"}
}