{
  "type": "Feature",
  "properties": {
    "addr:full":"50 Rue Du Pont Drummondville QC J2C 6B9",
    "addr:housenumber":"50",
    "addr:postcode":"j2c 6b9",
    "addr:street":"Rue Du Pont",
    "iso:country":"CA",
    "sg:address":"50 Rue Du Pont",
    "sg:city":"Drummondville",
    "sg:classifiers":[
        {
            "category":"Health Services",
            "subcategory":"Nursing And Care Facility",
            "type":"Services"
        }
    ],
    "sg:phone":"+1 819 477 6326",
    "sg:postcode":"J2C 6B9",
    "sg:province":"QC",
    "sg:tags":[
        "home",
        "retirement",
        "community"
    ],
    "wof:name":"Residences St-Frederic Inc",
    "wof:placetype":"venue"
},
  "geometry": {"coordinates":[-72.48596999999999,45.885544],"type":"Point"}
}