{
  "type": "Feature",
  "properties": {
    "addr:full":"Hamilton ON L8W 2E4",
    "addr:postcode":"l8w 2e4",
    "iso:country":"CA",
    "sg:city":"Hamilton",
    "sg:classifiers":[
        {
            "category":"Manufacturing",
            "subcategory":"Rubber & Plastics",
            "type":"Manufacturing & Wholesale Goods"
        }
    ],
    "sg:phone":"+1 905 575 9699",
    "sg:postcode":"L8W 2E4",
    "sg:province":"ON",
    "sg:tags":[
        "seal"
    ],
    "wof:name":"Safety Seal Plastics Inc",
    "wof:placetype":"venue"
},
  "geometry": {"coordinates":[-79.8366012573,43.1941871643],"type":"Point"}
}