{
  "type": "Feature",
  "properties": {
    "addr:full":"2650 Ch D'Entrelacs Entrelacs QC J0T 2E0",
    "addr:postcode":"2650;j0t 2e0",
    "addr:street":"Ch D'Entrelacs",
    "iso:country":"CA",
    "sg:address":"2650 Ch D'Entrelacs",
    "sg:city":"Entrelacs",
    "sg:classifiers":[
        {
            "category":"Home & Garden",
            "subcategory":"Hardware",
            "type":"Retail Goods"
        }
    ],
    "sg:phone":"+1 450 228 2575",
    "sg:postcode":"J0T 2E0",
    "sg:province":"QC",
    "wof:name":"Centre DE Renovation R Riopel",
    "wof:placetype":"venue"
},
  "geometry": {"coordinates":[-74.07656900000001,46.055885],"type":"Point"}
}