{
  "type": "Feature",
  "properties": {
    "addr:full":"9807 106 St NW Edmonton AB T5K 1C2",
    "addr:housenumber":"9807",
    "addr:postcode":"t5k 1c2",
    "addr:street":"106 St Nw",
    "iso:country":"CA",
    "sg:address":"9807 106 St NW",
    "sg:city":"Edmonton",
    "sg:classifiers":[
        {
            "category":"Education",
            "subcategory":"School",
            "type":"Public Place"
        }
    ],
    "sg:phone":"+1 780 441 6000",
    "sg:postcode":"T5K 1C2",
    "sg:province":"AB",
    "wof:name":"Edmonton Catholic Regl Div 40",
    "wof:placetype":"venue"
},
  "geometry": {"coordinates":[-113.502685547,53.5359077454],"type":"Point"}
}