{
  "type": "Feature",
  "properties": {
    "iso:country":"CA",
    "sg:address":"2191 Benjamin Ave",
    "sg:city":"Ottawa",
    "sg:classifiers":[
        {
            "category":"Education",
            "subcategory":"School",
            "type":"Public Place"
        }
    ],
    "sg:phone":"+1 613 722 5836",
    "sg:postcode":"K2A 1P6",
    "sg:province":"ON",
    "wof:name":"Ottawa Christian School",
    "wof:placetype":"venue"
},
  "geometry": {"coordinates":[-75.7675247192,45.3634643555],"type":"Point"}
}