{
  "type": "Feature",
  "properties": {
    "addr:full":"2530 Innes Rd Gloucester ON K1B 4C5",
    "addr:housenumber":"2530",
    "addr:postcode":"k1b 4c5",
    "addr:street":"Innes Rd",
    "iso:country":"CA",
    "sg:address":"2530 Innes Rd",
    "sg:city":"Gloucester",
    "sg:classifiers":[
        {
            "category":"Banks & Credit Unions",
            "subcategory":"Bank",
            "type":"Services"
        }
    ],
    "sg:phone":"+1 613 564 6680",
    "sg:postcode":"K1B 4C5",
    "sg:province":"ON",
    "wof:name":"Bank of Montreal",
    "wof:placetype":"venue"
},
  "geometry": {"coordinates":[-75.5679779053,45.4301719666],"type":"Point"}
}