{
  "type": "Feature",
  "properties": {
    "iso:country":"CA",
    "sg:city":"Sherbrooke",
    "sg:classifiers":[
        {
            "category":"Manufacturing",
            "subcategory":"Metals",
            "type":"Manufacturing & Wholesale Goods"
        }
    ],
    "sg:phone":"+1 819 565 8236",
    "sg:postcode":"J1J 4N8",
    "sg:province":"QC",
    "sg:tags":[
        "automobile",
        "scrap",
        "parts"
    ],
    "wof:name":"Metaux MD",
    "wof:placetype":"venue"
},
  "geometry": {"coordinates":[-71.919518,45.438244],"type":"Point"}
}