{
  "type": "Feature",
  "properties": {
    "iso:country":"CA",
    "sg:address":"4680 Main St",
    "sg:city":"Vancouver",
    "sg:classifiers":[
        {
            "category":"Home & Garden",
            "subcategory":"Home Furnishings",
            "type":"Retail Goods"
        }
    ],
    "sg:phone":"+1 604 871 9456",
    "sg:postcode":"V5V 3R7",
    "sg:province":"BC",
    "sg:tags":[
        "lighting",
        "fixture"
    ],
    "wof:name":"Taikoo Lighting",
    "wof:placetype":"venue"
},
  "geometry": {"coordinates":[-123.101119995,49.2429084778],"type":"Point"}
}