{
  "type": "Feature",
  "properties": {
    "iso:country":"CA",
    "sg:address":"54 Rue Saint-Emile",
    "sg:city":"Cap-DE-LA-Madeleine",
    "sg:classifiers":[
        {
            "category":"Retail",
            "subcategory":"Auto Repair",
            "type":"Services"
        }
    ],
    "sg:phone":"+1 819 376 6614",
    "sg:postcode":"G8T 7P5",
    "sg:province":"QC",
    "sg:tags":[
        "body",
        "automobile",
        "painting"
    ],
    "wof:name":"Vallee Automobiles",
    "wof:placetype":"venue"
},
  "geometry": {"coordinates":[-72.53817,46.372589],"type":"Point"}
}