{
  "type": "Feature",
  "properties": {
    "iso:country":"CA",
    "sg:address":"214 Osborne St",
    "sg:city":"Winnipeg",
    "sg:classifiers":[
        {
            "category":"Shopping",
            "subcategory":"Computers & Home Electronics",
            "type":"Retail Goods"
        }
    ],
    "sg:phone":"+1 204 452 5921",
    "sg:postcode":"R3L 1Z3",
    "sg:province":"MB",
    "sg:tags":[
        "equipment",
        "video"
    ],
    "wof:name":"Creative Audio",
    "wof:placetype":"venue"
},
  "geometry": {"coordinates":[-97.1427307129,49.8757209778],"type":"Point"}
}