{
  "type": "Feature",
  "properties": {
    "addr:full":"519 Grand Lake Rd Sydney NS B1P 5T3",
    "addr:housenumber":"519",
    "addr:postcode":"b1p 5t3",
    "addr:street":"Grand Lake Rd",
    "iso:country":"CA",
    "sg:address":"519 Grand Lake Rd",
    "sg:city":"Sydney",
    "sg:classifiers":[
        {
            "category":"Food & Beverages",
            "subcategory":"Bakery",
            "type":"Retail Goods"
        }
    ],
    "sg:phone":"+1 902 539 1722",
    "sg:postcode":"B1P 5T3",
    "sg:province":"NS",
    "sg:tags":[
        "doughnut"
    ],
    "wof:name":"Robin's Donuts",
    "wof:placetype":"venue"
},
  "geometry": {"coordinates":[-60.1285591125,46.153339386],"type":"Point"}
}