{
  "type": "Feature",
  "properties": {
    "iso:country":"CA",
    "sg:city":"Miramichi",
    "sg:classifiers":[
        {
            "category":"Restaurant",
            "type":"Food & Drink"
        }
    ],
    "sg:phone":"+1 506 623 5467",
    "sg:postcode":"E1V 6W3",
    "sg:province":"NB",
    "wof:name":"Jungle Jim's Eatery",
    "wof:placetype":"venue"
},
  "geometry": {"coordinates":[-65.49137878419999,47.0301208496],"type":"Point"}
}