{
  "type": "Feature",
  "properties": {
    "addr:full":"2933 Bessborough Ave Prince George BC V2N 1H5",
    "addr:housenumber":"2933",
    "addr:postcode":"v2n 1h5",
    "addr:street":"Bessborough Ave",
    "iso:country":"CA",
    "sg:address":"2933 Bessborough Ave",
    "sg:city":"Prince George",
    "sg:classifiers":[
        {
            "category":"Social Services",
            "subcategory":"Child Care",
            "type":"Services"
        }
    ],
    "sg:phone":"+1 250 563 1185",
    "sg:postcode":"V2N 1H5",
    "sg:province":"BC",
    "wof:name":"Mc Donald's Playhouse",
    "wof:placetype":"venue"
},
  "geometry": {"coordinates":[-122.78494999999999,53.892639],"type":"Point"}
}