{
  "type": "Feature",
  "properties": {
    "addr:full":"207 Wiggins Pvt Ottawa ON K1N 1C1",
    "addr:housenumber":"207",
    "addr:postcode":"k1n 1c1",
    "addr:street":"Wiggins Pvt",
    "iso:country":"CA",
    "sg:address":"207 Wiggins Pvt",
    "sg:city":"Ottawa",
    "sg:classifiers":[
        {
            "category":"Shopping",
            "subcategory":"Computers & Home Electronics",
            "type":"Retail Goods"
        }
    ],
    "sg:phone":"+1 613 233 9155",
    "sg:postcode":"K1N 1C1",
    "sg:province":"ON",
    "sg:tags":[
        "equipment",
        "dealer"
    ],
    "wof:name":"Verint Systems Canada Inc",
    "wof:placetype":"venue"
},
  "geometry": {"coordinates":[-75.671806,45.420376],"type":"Point"}
}