{
  "type": "Feature",
  "properties": {
    "addr:full":"L'Anse-Saint-Jean QC G0V 1J0",
    "addr:postcode":"g0v 1j0",
    "iso:country":"CA",
    "sg:city":"L'Anse-Saint-Jean",
    "sg:classifiers":[
        {
            "category":"Social Services",
            "type":"Services"
        }
    ],
    "sg:phone":"+1 418 272 3394",
    "sg:postcode":"G0V 1J0",
    "sg:province":"QC",
    "sg:tags":[
        "handicapped",
        "organization",
        "welfare"
    ],
    "wof:name":"Centres DE Readaptation Du",
    "wof:placetype":"venue"
},
  "geometry": {"coordinates":[-70.242249,48.198364],"type":"Point"}
}