{
  "type": "Feature",
  "properties": {
    "addr:full":"1426 Lonsdale Ave North Vancouver BC V7M 2J1",
    "addr:housenumber":"1426",
    "addr:postcode":"v7m 2j1",
    "addr:street":"Lonsdale Ave",
    "iso:country":"CA",
    "sg:address":"1426 Lonsdale Ave",
    "sg:city":"North Vancouver",
    "sg:classifiers":[
        {
            "category":"Restaurant",
            "type":"Food & Drink"
        }
    ],
    "sg:phone":"+1 604 990 0081",
    "sg:postcode":"V7M 2J1",
    "sg:province":"BC",
    "wof:name":"Hachi Hana Japanese Restaurant",
    "wof:placetype":"venue"
},
  "geometry": {"coordinates":[-123.072136,49.321362],"type":"Point"}
}