{
  "type": "Feature",
  "properties": {
    "addr:full":"Thornhill ON L4J 6W8",
    "addr:postcode":"l4j 6w8",
    "iso:country":"CA",
    "sg:city":"Thornhill",
    "sg:classifiers":[
        {
            "category":"Food & Beverages",
            "subcategory":"Groceries & Convenience Stores",
            "type":"Retail Goods"
        }
    ],
    "sg:phone":"+1 905 764 3666",
    "sg:postcode":"L4J 6W8",
    "sg:province":"ON",
    "wof:name":"Spring Farm Convenience",
    "wof:placetype":"venue"
},
  "geometry": {"coordinates":[-79.43835449220001,43.8052253723],"type":"Point"}
}