{
  "type": "Feature",
  "properties": {
    "addr:full":"2837 Belisle Dr Val Caron ON P3N 1B3",
    "addr:housenumber":"2837",
    "addr:postcode":"p3n 1b3",
    "addr:street":"Belisle Dr",
    "iso:country":"CA",
    "sg:address":"2837 Belisle Dr",
    "sg:city":"Val Caron",
    "sg:classifiers":[
        {
            "category":"Manufacturing",
            "subcategory":"Metals",
            "type":"Manufacturing & Wholesale Goods"
        }
    ],
    "sg:phone":"+1 705 897 2458",
    "sg:postcode":"P3N 1B3",
    "sg:province":"ON",
    "sg:tags":[
        "steel"
    ],
    "wof:name":"Stanley Appleton Corp",
    "wof:placetype":"venue"
},
  "geometry": {"coordinates":[-81.02889999999999,46.605373],"type":"Point"}
}