{
  "type": "Feature",
  "properties": {
    "iso:country":"CA",
    "sg:city":"Mississauga",
    "sg:classifiers":[
        {
            "category":"Health Services",
            "subcategory":"Doctor",
            "type":"Services"
        }
    ],
    "sg:phone":"+1 905 275 1300",
    "sg:postcode":"L5B 1M8",
    "sg:province":"ON",
    "sg:tags":[
        "clinic",
        "dentist"
    ],
    "wof:name":"Hurontario Harborn Dental Ctr",
    "wof:placetype":"venue"
},
  "geometry": {"coordinates":[-79.603027,43.570663],"type":"Point"}
}