{
  "type": "Feature",
  "properties": {
    "addr:full":"214 Broadway St Glenboro MB R0K 0X0",
    "addr:housenumber":"214",
    "addr:postcode":"r0k 0x0",
    "addr:street":"Broadway St",
    "iso:country":"CA",
    "sg:address":"214 Broadway St",
    "sg:city":"Glenboro",
    "sg:classifiers":[
        {
            "category":"Social Services",
            "subcategory":"Adult Care",
            "type":"Services"
        }
    ],
    "sg:phone":"+1 204 827 2703",
    "sg:postcode":"R0K 0X0",
    "sg:province":"MB",
    "sg:tags":[
        "organization",
        "senior",
        "citizen"
    ],
    "wof:name":"Seniors Independent Svc",
    "wof:placetype":"venue"
},
  "geometry": {"coordinates":[-99.2910003662,49.5555076599],"type":"Point"}
}