{
  "type": "Feature",
  "properties": {
    "addr:full":"111 Summerset Dr Barrie ON L4N 0A6",
    "addr:housenumber":"111",
    "addr:postcode":"l4n 0a6",
    "addr:street":"Summerset Dr",
    "iso:country":"CA",
    "sg:address":"111 Summerset Dr",
    "sg:city":"Barrie",
    "sg:classifiers":[
        {
            "category":"Education",
            "subcategory":"School",
            "type":"Public Place"
        }
    ],
    "sg:phone":"+1 705 728 7301",
    "sg:postcode":"L4N 0A6",
    "sg:province":"ON",
    "wof:name":"St Catharine of Siena",
    "wof:placetype":"venue"
},
  "geometry": {"coordinates":[-79.7242965698,44.357208252],"type":"Point"}
}