{
  "type": "Feature",
  "properties": {
    "addr:full":"North York ON M2N 6N5",
    "addr:postcode":"m2n 6n5",
    "iso:country":"CA",
    "sg:city":"North York",
    "sg:classifiers":[
        {
            "category":"Restaurant",
            "type":"Food & Drink"
        }
    ],
    "sg:phone":"+1 416 222 8181",
    "sg:postcode":"M2N 6N5",
    "sg:province":"ON",
    "wof:name":"Features Cafe",
    "wof:placetype":"venue"
},
  "geometry": {"coordinates":[-79.40576900000001,43.76281],"type":"Point"}
}