{
  "type": "Feature",
  "properties": {
    "addr:full":"L'Assomption QC J5W 2H3",
    "addr:postcode":"j5w 2h3",
    "iso:country":"CA",
    "sg:city":"L'Assomption",
    "sg:classifiers":[
        {
            "category":"Autos & Motor Vehicles",
            "subcategory":"Automobile Sales",
            "type":"Retail Goods"
        }
    ],
    "sg:phone":"+1 450 589 1355",
    "sg:postcode":"J5W 2H3",
    "sg:province":"QC",
    "sg:tags":[
        "body",
        "classic"
    ],
    "wof:name":"Atelier Speedway",
    "wof:placetype":"venue"
},
  "geometry": {"coordinates":[-73.44199399999999,45.903042],"type":"Point"}
}