{
  "type": "Feature",
  "properties": {
    "addr:full":"424 Mcdonald St Regina SK S4N 6E1",
    "addr:housenumber":"424",
    "addr:postcode":"s4n 6e1",
    "addr:street":"Mcdonald St",
    "iso:country":"CA",
    "sg:address":"424 Mcdonald St",
    "sg:city":"Regina",
    "sg:classifiers":[
        {
            "category":"Professional",
            "subcategory":"Accounting & Tax Preparation",
            "type":"Services"
        }
    ],
    "sg:phone":"+1 306 721 5181",
    "sg:postcode":"S4N 6E1",
    "sg:province":"SK",
    "sg:tags":[
        "return",
        "filing"
    ],
    "wof:name":"Town & Country Tax Consultants",
    "wof:placetype":"venue"
},
  "geometry": {"coordinates":[-104.581794739,50.47265625],"type":"Point"}
}