{
  "type": "Feature",
  "properties": {
    "addr:full":"296 Conception Bay Hwy Conception Bay South NL A1W 5K7",
    "addr:housenumber":"296",
    "addr:postcode":"a1w 5k7",
    "addr:street":"Conception Bay Hwy",
    "iso:country":"CA",
    "sg:address":"296 Conception Bay Hwy",
    "sg:city":"Conception Bay South",
    "sg:classifiers":[
        {
            "category":"Wholesale",
            "subcategory":"Machinery & Supplies",
            "type":"Manufacturing & Wholesale Goods"
        }
    ],
    "sg:phone":"+1 709 834 8182",
    "sg:postcode":"A1W 5K7",
    "sg:province":"NL",
    "sg:tags":[
        "equipment",
        "safety",
        "clothing"
    ],
    "wof:name":"Factory Footwear Outlet",
    "wof:placetype":"venue"
},
  "geometry": {"coordinates":[-52.9730453491,47.5095825195],"type":"Point"}
}