{
  "type": "Feature",
  "properties": {
    "addr:full":"3199 Cliffe Ave Courtenay BC V9N 2L9",
    "addr:housenumber":"3199",
    "addr:postcode":"v9n 2l9",
    "addr:street":"Cliffe Ave",
    "iso:country":"CA",
    "sg:address":"3199 Cliffe Ave",
    "sg:city":"Courtenay",
    "sg:classifiers":[
        {
            "category":"Shopping",
            "subcategory":"Department Store",
            "type":"Retail Goods"
        }
    ],
    "sg:phone":"+1 250 898 8998",
    "sg:postcode":"V9N 2L9",
    "sg:province":"BC",
    "wof:name":"Wal-Mart",
    "wof:placetype":"venue"
},
  "geometry": {"coordinates":[-124.977645874,49.6683387756],"type":"Point"}
}