{
  "type": "Feature",
  "properties": {
    "addr:full":"170 1st Ave E Bengough SK S0C 0K0",
    "addr:housenumber":"170",
    "addr:postcode":"s0c 0k0",
    "addr:street":"1St Ave E Bengough",
    "iso:country":"CA",
    "sg:address":"170 1st Ave E",
    "sg:city":"Bengough",
    "sg:classifiers":[
        {
            "category":"Home & Garden",
            "subcategory":"Building Materials",
            "type":"Retail Goods"
        }
    ],
    "sg:phone":"+1 306 268 2066",
    "sg:postcode":"S0C 0K0",
    "sg:province":"SK",
    "sg:tags":[
        "lumber"
    ],
    "wof:name":"North American Lumber Ltd",
    "wof:placetype":"venue"
},
  "geometry": {"coordinates":[-105.12273407000001,49.3972854614],"type":"Point"}
}