{
  "type": "Feature",
  "properties": {
    "addr:full":"150 Douglasview Rise SE Calgary AB T2Z 2H8",
    "addr:housenumber":"150",
    "addr:postcode":"t2z 2h8",
    "addr:street":"Douglasview Rise Se",
    "iso:country":"CA",
    "sg:address":"150 Douglasview Rise SE",
    "sg:city":"Calgary",
    "sg:classifiers":[
        {
            "category":"Shopping",
            "subcategory":"Clothing, Apparel, & Fashions",
            "type":"Retail Goods"
        }
    ],
    "sg:phone":"+1 403 203 5661",
    "sg:postcode":"T2Z 2H8",
    "sg:province":"AB",
    "sg:tags":[
        "sportswear"
    ],
    "wof:name":"Ashby Sports Wear",
    "wof:placetype":"venue"
},
  "geometry": {"coordinates":[-113.98748000000001,50.938896],"type":"Point"}
}