{
  "type": "Feature",
  "properties": {
    "iso:country":"CA",
    "sg:address":"885 Whitmore Ave E",
    "sg:city":"Dauphin",
    "sg:classifiers":[
        {
            "category":"Home & Garden",
            "subcategory":"Garden Supply",
            "type":"Retail Goods"
        }
    ],
    "sg:phone":"+1 204 638 8995",
    "sg:postcode":"R7N 2V1",
    "sg:province":"MB",
    "sg:tags":[
        "lawn",
        "snowmobile"
    ],
    "wof:name":"Dauphin Speed & Sport",
    "wof:placetype":"venue"
},
  "geometry": {"coordinates":[-100.030097961,51.1403083801],"type":"Point"}
}