{
  "type": "Feature",
  "properties": {
    "addr:full":"Vancouver BC V5X 4N6",
    "addr:postcode":"v5x 4n6",
    "iso:country":"CA",
    "sg:city":"Vancouver",
    "sg:classifiers":[
        {
            "category":"Wholesale",
            "subcategory":"Office Equipment",
            "type":"Manufacturing & Wholesale Goods"
        }
    ],
    "sg:phone":"+1 604 324 6210",
    "sg:postcode":"V5X 4N6",
    "sg:province":"BC",
    "sg:tags":[
        "scanning",
        "code",
        "bar"
    ],
    "wof:name":"Markhem Products",
    "wof:placetype":"venue"
},
  "geometry": {"coordinates":[-123.09849548299999,49.2072219849],"type":"Point"}
}