{
  "type": "Feature",
  "properties": {
    "addr:full":"Haileybury ON P0J 1K0",
    "addr:postcode":"p0j 1k0",
    "iso:country":"CA",
    "sg:city":"Haileybury",
    "sg:classifiers":[
        {
            "category":"Recreation",
            "type":"Entertainment"
        }
    ],
    "sg:phone":"+1 705 672 3515",
    "sg:postcode":"P0J 1K0",
    "sg:province":"ON",
    "sg:tags":[
        "hall",
        "auditorium"
    ],
    "wof:name":"Cobalt Haileybury Curling Club",
    "wof:placetype":"venue"
},
  "geometry": {"coordinates":[-79.630898,47.44812],"type":"Point"}
}