{
  "type": "Feature",
  "properties": {
    "addr:full":"7 High St Grand Falls-Windsor NL A2A 1C3",
    "addr:housenumber":"7",
    "addr:postcode":"a2a 1c3",
    "addr:street":"High St",
    "iso:country":"CA",
    "sg:address":"7 High St",
    "sg:city":"Grand Falls-Windsor",
    "sg:classifiers":[
        {
            "category":"Professional",
            "subcategory":"Employment Agencies",
            "type":"Services"
        }
    ],
    "sg:phone":"+1 709 489 5643",
    "sg:postcode":"A2A 1C3",
    "sg:province":"NL",
    "sg:tags":[
        "opportunity"
    ],
    "wof:name":"Exploits Community Employment",
    "wof:placetype":"venue"
},
  "geometry": {"coordinates":[-55.658943,48.927643],"type":"Point"}
}