{
  "type": "Feature",
  "properties": {
    "addr:full":"8 Earle St Grand Falls-Windsor NL A2B 1H5",
    "addr:housenumber":"8",
    "addr:postcode":"a2b 1h5",
    "addr:street":"Earle St",
    "iso:country":"CA",
    "sg:address":"8 Earle St",
    "sg:city":"Grand Falls-Windsor",
    "sg:classifiers":[
        {
            "category":"Retail",
            "subcategory":"Auto Repair",
            "type":"Services"
        }
    ],
    "sg:phone":"+1 709 489 8697",
    "sg:postcode":"A2B 1H5",
    "sg:province":"NL",
    "sg:tags":[
        "wrecker"
    ],
    "wof:name":"Ideal Towing & Recovery",
    "wof:placetype":"venue"
},
  "geometry": {"coordinates":[-55.656281,48.94334],"type":"Point"}
}