{
  "type": "Feature",
  "properties": {
    "addr:full":"602 Magnetic Dr North York ON M3J 2C4",
    "addr:housenumber":"602",
    "addr:postcode":"m3j 2c4",
    "addr:street":"Magnetic Dr",
    "iso:country":"CA",
    "sg:address":"602 Magnetic Dr",
    "sg:city":"North York",
    "sg:classifiers":[
        {
            "category":"Professional",
            "subcategory":"Advertising",
            "type":"Services"
        }
    ],
    "sg:phone":"+1 416 661 9434",
    "sg:postcode":"M3J 2C4",
    "sg:province":"ON",
    "sg:tags":[
        "designer",
        "display",
        "producer"
    ],
    "wof:name":"4 Solutions Display",
    "wof:placetype":"venue"
},
  "geometry": {"coordinates":[-79.47541809080001,43.783657074],"type":"Point"}
}