{
  "type": "Feature",
  "properties": {
    "iso:country":"CA",
    "name:eng_x_preferred":[
        "Koho"
    ],
    "wof:name":"Koho",
    "wof:placetype":"venue"
},
  "geometry": {"coordinates":[-123.17836111110999,49.194747222222],"type":"Point"}
}