{
  "type": "Feature",
  "properties": {
    "addr:full":"2 Short Rd Cardiff ON K0L 1M0",
    "addr:housenumber":"2",
    "addr:postcode":"k0l 1m0",
    "addr:street":"Short Rd",
    "iso:country":"CA",
    "sg:address":"2 Short Rd",
    "sg:city":"Cardiff",
    "sg:classifiers":[
        {
            "category":"Education",
            "subcategory":"School",
            "type":"Public Place"
        }
    ],
    "sg:phone":"+1 613 339 2351",
    "sg:postcode":"K0L 1M0",
    "sg:province":"ON",
    "wof:name":"Cardiff Elementary School",
    "wof:placetype":"venue"
},
  "geometry": {"coordinates":[-78.092468,44.992516],"type":"Point"}
}