{
  "type": "Feature",
  "properties": {
    "iso:country":"CA",
    "sg:address":"19 Rte Bernard",
    "sg:city":"Carleton",
    "sg:classifiers":[
        {
            "category":"Personal",
            "subcategory":"Beauty Salon",
            "type":"Services"
        }
    ],
    "sg:phone":"+1 418 364 6005",
    "sg:postcode":"G0C 1J0",
    "sg:province":"QC",
    "wof:name":"Caroline D Coiffure",
    "wof:placetype":"venue"
},
  "geometry": {"coordinates":[-66.0999984741,48.1073760986],"type":"Point"}
}