{
  "type": "Feature",
  "properties": {
    "iso:country":"CA",
    "sg:address":"110 Place D'Orleans Dr",
    "sg:city":"Orleans",
    "sg:classifiers":[
        {
            "category":"Shopping",
            "subcategory":"Clothing, Apparel, & Fashions",
            "type":"Retail Goods"
        }
    ],
    "sg:phone":"+1 613 834 2377",
    "sg:postcode":"K1C 2L9",
    "sg:province":"ON",
    "sg:tags":[
        "infant",
        "wear"
    ],
    "wof:name":"Northern Getaway",
    "wof:placetype":"venue"
},
  "geometry": {"coordinates":[-75.536125,45.476265],"type":"Point"}
}