{
  "type": "Feature",
  "properties": {
    "addr:full":"6002 Bella Vista Rd Vernon BC V1H 1B4",
    "addr:housenumber":"6002",
    "addr:postcode":"v1h 1b4",
    "addr:street":"Bella Vista Rd",
    "iso:country":"CA",
    "sg:address":"6002 Bella Vista Rd",
    "sg:city":"Vernon",
    "sg:classifiers":[
        {
            "category":"Shopping",
            "subcategory":"Jewelry",
            "type":"Retail Goods"
        }
    ],
    "sg:phone":"+1 250 542 0630",
    "sg:postcode":"V1H 1B4",
    "sg:province":"BC",
    "sg:tags":[
        "jade"
    ],
    "wof:name":"Evergreen Carvings in Jade",
    "wof:placetype":"venue"
},
  "geometry": {"coordinates":[-119.319953919,50.2597579956],"type":"Point"}
}