{
  "type": "Feature",
  "properties": {
    "addr:full":"2410 10 Ave SW Calgary AB T3C 0K6",
    "addr:housenumber":"2410",
    "addr:postcode":"t3c 0k6",
    "addr:street":"10 Ave Sw",
    "iso:country":"CA",
    "sg:address":"2410 10 Ave SW",
    "sg:city":"Calgary",
    "sg:classifiers":[
        {
            "category":"Organizations",
            "subcategory":"Professional Association",
            "type":"Services"
        }
    ],
    "sg:phone":"+1 403 249 8931",
    "sg:postcode":"T3C 0K6",
    "sg:province":"AB",
    "sg:tags":[
        "well",
        "oil",
        "exploration",
        "log",
        "library"
    ],
    "wof:name":"M J Systems",
    "wof:placetype":"venue"
},
  "geometry": {"coordinates":[-114.11597399999999,51.045422],"type":"Point"}
}