{
  "type": "Feature",
  "properties": {
    "addr:full":"215 Hodsman Rd Regina SK S4N 5W5",
    "addr:housenumber":"215",
    "addr:postcode":"s4n 5w5",
    "addr:street":"Hodsman Rd",
    "iso:country":"CA",
    "sg:address":"215 Hodsman Rd",
    "sg:city":"Regina",
    "sg:classifiers":[
        {
            "category":"Building & Trades",
            "subcategory":"Plumbing",
            "type":"Services"
        }
    ],
    "sg:phone":"+1 306 569 0047",
    "sg:postcode":"S4N 5W5",
    "sg:province":"SK",
    "sg:tags":[
        "contractor"
    ],
    "wof:name":"Able Plumbing & Heating",
    "wof:placetype":"venue"
},
  "geometry": {"coordinates":[-104.58287,50.478481],"type":"Point"}
}