{
  "type": "Feature",
  "properties": {
    "addr:full":"Yonge & Steeles Thornhill ON L4J 3E5",
    "addr:postcode":"l4j 3e5",
    "iso:country":"CA",
    "sg:address":"Yonge & Steeles",
    "sg:city":"Thornhill",
    "sg:classifiers":[
        {
            "category":"Professional",
            "subcategory":"Secretarial Services",
            "type":"Services"
        }
    ],
    "sg:phone":"+1 905 731 5938",
    "sg:postcode":"L4J 3E5",
    "sg:province":"ON",
    "sg:tags":[
        "reporting",
        "court",
        "resume"
    ],
    "wof:name":"Laser Power Resumes",
    "wof:placetype":"venue"
},
  "geometry": {"coordinates":[-79.42822265620001,43.8325500488],"type":"Point"}
}