{
  "type": "Feature",
  "properties": {
    "addr:full":"195 Boul Gagnon Sainte-Claire QC G0R 2V0",
    "addr:housenumber":"195",
    "addr:postcode":"g0r 2v0",
    "addr:street":"Boul Gagnon",
    "iso:country":"CA",
    "sg:address":"195 Boul Gagnon",
    "sg:city":"Sainte-Claire",
    "sg:classifiers":[
        {
            "category":"Retail",
            "subcategory":"Repair Shop",
            "type":"Services"
        }
    ],
    "sg:phone":"+1 418 883 3963",
    "sg:postcode":"G0R 2V0",
    "sg:province":"QC",
    "sg:tags":[
        "welding"
    ],
    "wof:name":"Atelier Andre Roy Inc",
    "wof:placetype":"venue"
},
  "geometry": {"coordinates":[-70.85655975340001,46.6023864746],"type":"Point"}
}