{
  "type": "Feature",
  "properties": {
    "addr:full":"894 Nellis St Woodstock ON N4S 4C5",
    "addr:housenumber":"894",
    "addr:postcode":"n4s 4c5",
    "addr:street":"Nellis St",
    "iso:country":"CA",
    "sg:address":"894 Nellis St",
    "sg:city":"Woodstock",
    "sg:phone":"+1 519 421 1133",
    "sg:postcode":"N4S 4C5",
    "sg:province":"ON",
    "sg:tags":[
        "oil",
        "burner"
    ],
    "wof:name":"Scott Fuels & Home Comfort",
    "wof:placetype":"venue"
},
  "geometry": {"coordinates":[-80.736038208,43.1338310242],"type":"Point"}
}