{
  "type": "Feature",
  "properties": {
    "addr:full":"Peterborough ON K9H 2P7",
    "addr:postcode":"k9h 2p7",
    "iso:country":"CA",
    "sg:city":"Peterborough",
    "sg:classifiers":[
        {
            "category":"Organizations",
            "subcategory":"Professional Association",
            "type":"Services"
        }
    ],
    "sg:phone":"+1 705 742 5698",
    "sg:postcode":"K9H 2P7",
    "sg:province":"ON",
    "sg:tags":[
        "housing"
    ],
    "wof:name":"Otonabee Native Homes Inc",
    "wof:placetype":"venue"
},
  "geometry": {"coordinates":[-78.32401275629999,44.3071403503],"type":"Point"}
}