{
  "type": "Feature",
  "properties": {
    "iso:country":"CA",
    "sg:address":"628 Rue DE L'Eglise",
    "sg:city":"Valcourt",
    "sg:classifiers":[
        {
            "category":"Building & Trades",
            "subcategory":"Construction",
            "type":"Services"
        }
    ],
    "sg:phone":"+1 450 532 3831",
    "sg:postcode":"J0E 2L0",
    "sg:province":"QC",
    "sg:tags":[
        "painter"
    ],
    "wof:name":"Renovation Alain Royer Inc",
    "wof:placetype":"venue"
},
  "geometry": {"coordinates":[-72.660774231,45.0364875793],"type":"Point"}
}