{
  "type": "Feature",
  "properties": {
    "addr:full":"Edmonton AB T5T 2R5",
    "addr:postcode":"t5t 2r5",
    "iso:country":"CA",
    "sg:city":"Edmonton",
    "sg:classifiers":[
        {
            "category":"Real Estate",
            "subcategory":"Real Estate Operator",
            "type":"Services"
        }
    ],
    "sg:phone":"+1 780 487 9830",
    "sg:postcode":"T5T 2R5",
    "sg:province":"AB",
    "sg:tags":[
        "apartment"
    ],
    "wof:name":"Parklane Apartments",
    "wof:placetype":"venue"
},
  "geometry": {"coordinates":[-113.629288,53.49715],"type":"Point"}
}