{
  "type": "Feature",
  "properties": {
    "addr:full":"6536 Rue Saint-Hubert Montreal QC H2S 2M3",
    "addr:housenumber":"6536",
    "addr:postcode":"h2s 2m3",
    "addr:street":"Rue Saint-Hubert",
    "iso:country":"CA",
    "sg:address":"6536 Rue Saint-Hubert",
    "sg:city":"Montreal",
    "sg:classifiers":[
        {
            "category":"Shopping",
            "subcategory":"Clothing, Apparel, & Fashions",
            "type":"Retail Goods"
        }
    ],
    "sg:phone":"+1 514 278 8769",
    "sg:postcode":"H2S 2M3",
    "sg:province":"QC",
    "sg:tags":[
        "jean"
    ],
    "wof:name":"Jeaner",
    "wof:placetype":"venue"
},
  "geometry": {"coordinates":[-73.603981,45.536423],"type":"Point"}
}