{
  "type": "Feature",
  "properties": {
    "addr:full":"Laval QC H7K 2J8",
    "addr:postcode":"qc h7k 2j8",
    "iso:country":"CA",
    "sg:city":"Laval",
    "sg:classifiers":[
        {
            "category":"Building & Trades",
            "subcategory":"Equipment Rental",
            "type":"Services"
        }
    ],
    "sg:phone":"+1 450 625 2681",
    "sg:postcode":"H7K 2J8",
    "sg:province":"QC",
    "sg:tags":[
        "arbitration",
        "yard"
    ],
    "wof:name":"Centre DE Reparation-Moteurs",
    "wof:placetype":"venue"
},
  "geometry": {"coordinates":[-73.7488479614,45.6236038208],"type":"Point"}
}