{
  "type": "Feature",
  "properties": {
    "addr:full":"152 Boul Sainte-Rose Laval QC H7L 1L3",
    "addr:housenumber":"152",
    "addr:postcode":"h7l 1l3",
    "addr:street":"Boul Sainte-Rose",
    "iso:country":"CA",
    "sg:address":"152 Boul Sainte-Rose",
    "sg:city":"Laval",
    "sg:classifiers":[
        {
            "category":"Manufacturing",
            "subcategory":"Chemicals & Compounds",
            "type":"Manufacturing & Wholesale Goods"
        }
    ],
    "sg:phone":"+1 450 625 7770",
    "sg:postcode":"H7L 1L3",
    "sg:province":"QC",
    "sg:tags":[
        "equipment",
        "cosmetic"
    ],
    "wof:name":"Lysette Cosmetiques Intl Ltee",
    "wof:placetype":"venue"
},
  "geometry": {"coordinates":[-73.74463653559999,45.5515670776],"type":"Point"}
}