{
  "type": "Feature",
  "properties": {
    "addr:full":"2450 Boul Des Recollets Trois-Rivieres QC G8Z 3X7",
    "addr:housenumber":"2450",
    "addr:postcode":"g8z 3x7",
    "addr:street":"Boul Des Recollets Trois-Rivieres",
    "iso:country":"CA",
    "sg:address":"2450 Boul Des Recollets",
    "sg:city":"Trois-Rivieres",
    "sg:classifiers":[
        {
            "category":"Shopping",
            "subcategory":"Stationery & Office Supplies",
            "type":"Retail Goods"
        }
    ],
    "sg:phone":"+1 819 376 2538",
    "sg:postcode":"G8Z 3X7",
    "sg:province":"QC",
    "sg:tags":[
        "furniture"
    ],
    "wof:name":"Denis Fournitures DE Bureau",
    "wof:placetype":"venue"
},
  "geometry": {"coordinates":[-72.577736,46.336433],"type":"Point"}
}