{
  "type": "Feature",
  "properties": {
    "iso:country":"CA",
    "sg:address":"60 Boul DE LA Seigneurie E",
    "sg:city":"Blainville",
    "sg:classifiers":[
        {
            "category":"Government",
            "subcategory":"Office",
            "type":"Public Place"
        }
    ],
    "sg:phone":"+1 450 434 5348",
    "sg:postcode":"J7C 4N1",
    "sg:province":"QC",
    "sg:tags":[
        "village"
    ],
    "wof:name":"Blainville Travaux Publics",
    "wof:placetype":"venue"
},
  "geometry": {"coordinates":[-73.8627700806,45.6730041504],"type":"Point"}
}