{
  "type": "Feature",
  "properties": {
    "addr:full":"5 Rampton St Morden MB R6M 1V8",
    "addr:housenumber":"5",
    "addr:postcode":"r6m 1v8",
    "addr:street":"Rampton St",
    "iso:country":"CA",
    "sg:address":"5 Rampton St",
    "sg:city":"Morden",
    "sg:classifiers":[
        {
            "category":"Social Services",
            "subcategory":"Child Care",
            "type":"Services"
        }
    ],
    "sg:phone":"+1 204 822 6663",
    "sg:postcode":"R6M 1V8",
    "sg:province":"MB",
    "wof:name":"Morden Community Child Care",
    "wof:placetype":"venue"
},
  "geometry": {"coordinates":[-98.0985488892,49.1989631653],"type":"Point"}
}