{
  "type": "Feature",
  "properties": {
    "addr:full":"1401 Ch Des Anglais Lachenaie QC J6X 4G3",
    "addr:housenumber":"1401",
    "addr:postcode":"j6x 4g3",
    "addr:street":"Ch Des Anglais",
    "iso:country":"CA",
    "sg:address":"1401 Ch Des Anglais",
    "sg:city":"Lachenaie",
    "sg:classifiers":[
        {
            "category":"Shopping",
            "type":"Retail Goods"
        }
    ],
    "sg:phone":"+1 450 471 1074",
    "sg:postcode":"J6X 4G3",
    "sg:province":"QC",
    "sg:tags":[
        "whirlpool",
        "equipment",
        "bath",
        "supply"
    ],
    "wof:name":"Bains Tourbillons Rive Nord",
    "wof:placetype":"venue"
},
  "geometry": {"coordinates":[-73.6571426392,45.7233161926],"type":"Point"}
}