{
  "type": "Feature",
  "properties": {
    "addr:full":"4898 Mackenzie St Vancouver BC V6L 2R6",
    "addr:housenumber":"4898",
    "addr:postcode":"v6l 2r6",
    "addr:street":"Mackenzie St",
    "iso:country":"CA",
    "sg:address":"4898 Mackenzie St",
    "sg:city":"Vancouver",
    "sg:classifiers":[
        {
            "category":"Health Services",
            "subcategory":"Doctor",
            "type":"Services"
        }
    ],
    "sg:phone":"+1 604 266 0421",
    "sg:postcode":"V6L 2R6",
    "sg:province":"BC",
    "sg:tags":[
        "dentist"
    ],
    "wof:name":"Phillips, Kevin A C DDS",
    "wof:placetype":"venue"
},
  "geometry": {"coordinates":[-123.170089722,49.2423858643],"type":"Point"}
}