{
  "type": "Feature",
  "properties": {
    "iso:country":"CA",
    "sg:address":"13580 Hwy 2",
    "sg:city":"Colborne",
    "sg:classifiers":[
        {
            "category":"Building & Trades",
            "subcategory":"Construction",
            "type":"Services"
        }
    ],
    "sg:phone":"+1 905 355 1500",
    "sg:postcode":"K0K 1S0",
    "sg:province":"ON",
    "sg:tags":[
        "general",
        "contractor"
    ],
    "wof:name":"Peak Engineering & Constr",
    "wof:placetype":"venue"
},
  "geometry": {"coordinates":[-77.8556060791,44.013256073],"type":"Point"}
}