{
  "type": "Feature",
  "properties": {
    "addr:full":"7755 Bayview Ave Thornhill ON L3T 4P1",
    "addr:housenumber":"7755",
    "addr:postcode":"l3t 4p1",
    "addr:street":"Bayview Ave",
    "iso:country":"CA",
    "sg:address":"7755 Bayview Ave",
    "sg:city":"Thornhill",
    "sg:classifiers":[
        {
            "category":"Shopping",
            "subcategory":"Bicycles & Sporting Goods",
            "type":"Retail Goods"
        }
    ],
    "sg:phone":"+1 905 881 2412",
    "sg:postcode":"L3T 4P1",
    "sg:province":"ON",
    "wof:name":"Fisher Sports",
    "wof:placetype":"venue"
},
  "geometry": {"coordinates":[-79.4012298584,43.8195800781],"type":"Point"}
}