{
  "type": "Feature",
  "properties": {
    "addr:full":"685 Hwy 124 Parry Sound ON P2A 2W7",
    "addr:housenumber":"685",
    "addr:postcode":"p2a 2w7",
    "addr:street":"Hwy 124",
    "iso:country":"CA",
    "sg:address":"685 Hwy 124",
    "sg:city":"Parry Sound",
    "sg:classifiers":[
        {
            "category":"Retail",
            "subcategory":"Auto Repair",
            "type":"Services"
        }
    ],
    "sg:phone":"+1 705 389 2040",
    "sg:postcode":"P2A 2W7",
    "sg:province":"ON",
    "sg:tags":[
        "repairing",
        "automobile"
    ],
    "wof:name":"Northern Automotive Ctr",
    "wof:placetype":"venue"
},
  "geometry": {"coordinates":[-80.036362,45.344769],"type":"Point"}
}