{
  "type": "Feature",
  "properties": {
    "addr:full":"North York ON M3K 1Z1",
    "addr:postcode":"m3k 1z1",
    "iso:country":"CA",
    "sg:city":"North York",
    "sg:classifiers":[
        {
            "category":"Health Services",
            "subcategory":"Doctor",
            "type":"Services"
        }
    ],
    "sg:phone":"+1 416 631 6859",
    "sg:postcode":"M3K 1Z1",
    "sg:province":"ON",
    "sg:tags":[
        "physician",
        "surgeon"
    ],
    "wof:name":"Ramprasad, H MD",
    "wof:placetype":"venue"
},
  "geometry": {"coordinates":[-79.478081,43.727966],"type":"Point"}
}