{
  "type": "Feature",
  "properties": {
    "addr:full":"3105 Don Mills Rd North York ON M2J 3C2",
    "addr:housenumber":"3105",
    "addr:postcode":"m2j 3c2",
    "addr:street":"Don Mills Rd",
    "iso:country":"CA",
    "sg:address":"3105 Don Mills Rd",
    "sg:city":"North York",
    "sg:classifiers":[
        {
            "category":"Education",
            "subcategory":"School",
            "type":"Public Place"
        }
    ],
    "sg:phone":"+1 416 393 5342",
    "sg:postcode":"M2J 3C2",
    "sg:province":"ON",
    "wof:name":"Our Lady of Guadalupe",
    "wof:placetype":"venue"
},
  "geometry": {"coordinates":[-79.35330999999999,43.788471],"type":"Point"}
}