{
  "type": "Feature",
  "properties": {
    "iso:country":"CA",
    "sg:address":"167 Boul DE Gaspe",
    "sg:city":"Gaspe",
    "sg:classifiers":[
        {
            "category":"Government",
            "subcategory":"Police Station",
            "type":"Public Place"
        }
    ],
    "sg:phone":"+1 418 368 3232",
    "sg:postcode":"G4X 1A4",
    "sg:province":"QC",
    "sg:tags":[
        "department"
    ],
    "wof:name":"Quebec Surete",
    "wof:placetype":"venue"
},
  "geometry": {"coordinates":[-64.4849014282,48.8400993347],"type":"Point"}
}