{
  "type": "Feature",
  "properties": {
    "addr:full":"2482 Sharon Cres Mississauga ON L5C 1Y8",
    "addr:housenumber":"2482",
    "addr:postcode":"l5c 1y8",
    "addr:street":"Sharon Cres",
    "iso:country":"CA",
    "sg:address":"2482 Sharon Cres",
    "sg:city":"Mississauga",
    "sg:classifiers":[
        {
            "category":"Banks & Credit Unions",
            "subcategory":"Investment Brokerage",
            "type":"Services"
        }
    ],
    "sg:phone":"+1 905 277 2078",
    "sg:postcode":"L5C 1Y8",
    "sg:province":"ON",
    "sg:tags":[
        "consultant",
        "planning",
        "financial"
    ],
    "wof:name":"Thompson Financial Svc",
    "wof:placetype":"venue"
},
  "geometry": {"coordinates":[-79.638626,43.554428],"type":"Point"}
}