{
  "type": "Feature",
  "properties": {
    "iso:country":"CA",
    "sg:address":"1204 Roland St #A",
    "sg:city":"Thunder Bay",
    "sg:classifiers":[
        {
            "category":"Organizations",
            "subcategory":"Professional Association",
            "type":"Services"
        }
    ],
    "sg:phone":"+1 807 626 9788",
    "sg:postcode":"P7B 5M4",
    "sg:province":"ON",
    "wof:name":"Northern Diabetes Health",
    "wof:placetype":"venue"
},
  "geometry": {"coordinates":[-89.2566604614,48.4032974243],"type":"Point"}
}