{
  "type": "Feature",
  "properties": {
    "iso:country":"CA",
    "sg:city":"Waterloo",
    "sg:classifiers":[
        {
            "category":"Shopping",
            "subcategory":"Optical Goods",
            "type":"Retail Goods"
        }
    ],
    "sg:phone":"+1 519 749 0592",
    "sg:postcode":"N2J 1C4",
    "sg:province":"ON",
    "sg:tags":[
        "optician"
    ],
    "wof:name":"Casselli Eye Care Ctr",
    "wof:placetype":"venue"
},
  "geometry": {"coordinates":[-80.50988,43.463505],"type":"Point"}
}