{
  "type": "Feature",
  "properties": {
    "addr:full":"601 Vernon St Nelson BC V1L 4E9",
    "addr:housenumber":"601",
    "addr:postcode":"bc v1l 4e9",
    "addr:street":"Vernon St",
    "iso:country":"CA",
    "sg:address":"601 Vernon St",
    "sg:city":"Nelson",
    "sg:classifiers":[
        {
            "category":"Government",
            "subcategory":"Office",
            "type":"Public Place"
        }
    ],
    "sg:phone":"+1 250 352 5599",
    "sg:postcode":"V1L 4E9",
    "sg:province":"BC",
    "sg:tags":[
        "village"
    ],
    "wof:name":"Central Kootenay Building Insp",
    "wof:placetype":"venue"
},
  "geometry": {"coordinates":[-117.293289,49.4935],"type":"Point"}
}