{
  "type": "Feature",
  "properties": {
    "addr:full":"Kitchener ON N2H 6M6",
    "addr:postcode":"n2h 6m6",
    "iso:country":"CA",
    "sg:city":"Kitchener",
    "sg:classifiers":[
        {
            "category":"Professional",
            "subcategory":"Lawyer & Legal Services",
            "type":"Services"
        }
    ],
    "sg:phone":"+1 519 578 1448",
    "sg:postcode":"N2H 6M6",
    "sg:province":"ON",
    "sg:tags":[
        "attorney"
    ],
    "wof:name":"Schmidt, Michael J",
    "wof:placetype":"venue"
},
  "geometry": {"coordinates":[-80.4874420166,43.4498214722],"type":"Point"}
}