{
  "type": "Feature",
  "properties": {
    "addr:full":"108 Russell St # 304 Madoc ON K0K 2K0",
    "addr:housenumber":"108",
    "addr:postcode":"k0k 2k0",
    "addr:street":"Russell St # 304",
    "iso:country":"CA",
    "sg:address":"108 Russell St # 304",
    "sg:city":"Madoc",
    "sg:classifiers":[
        {
            "category":"Social Services",
            "type":"Services"
        }
    ],
    "sg:phone":"+1 613 473 0400",
    "sg:postcode":"K0K 2K0",
    "sg:province":"ON",
    "sg:tags":[
        "organization",
        "welfare"
    ],
    "wof:name":"Youth Habilitation Quinte Inc",
    "wof:placetype":"venue"
},
  "geometry": {"coordinates":[-77.4748458862,44.5061073303],"type":"Point"}
}