{
  "type": "Feature",
  "properties": {
    "addr:full":"1630 Rue Notre Dame Saint-Maurice QC G0X 2X0",
    "addr:housenumber":"1630",
    "addr:postcode":"g0x 2x0",
    "addr:street":"Rue Notre Dame",
    "iso:country":"CA",
    "sg:address":"1630 Rue Notre Dame",
    "sg:city":"Saint-Maurice",
    "sg:classifiers":[
        {
            "category":"Retail",
            "subcategory":"Auto Repair",
            "type":"Services"
        }
    ],
    "sg:phone":"+1 819 374 2233",
    "sg:postcode":"G0X 2X0",
    "sg:province":"QC",
    "sg:tags":[
        "repairing",
        "automobile"
    ],
    "wof:name":"Garage Luc Desilets",
    "wof:placetype":"venue"
},
  "geometry": {"coordinates":[-72.53517913819999,46.4712295532],"type":"Point"}
}