{
  "type": "Feature",
  "properties": {
    "addr:full":"468 Morden Rd Oakville ON L6K 3W4",
    "addr:housenumber":"468",
    "addr:postcode":"l6k 3w4",
    "addr:street":"Morden Rd",
    "iso:country":"CA",
    "sg:address":"468 Morden Rd",
    "sg:city":"Oakville",
    "sg:classifiers":[
        {
            "category":"Professional",
            "subcategory":"Employment Agencies",
            "type":"Services"
        }
    ],
    "sg:phone":"+1 905 842 3352",
    "sg:postcode":"L6K 3W4",
    "sg:province":"ON",
    "sg:tags":[
        "consultant",
        "search",
        "executive"
    ],
    "wof:name":"Execu Grow Inc",
    "wof:placetype":"venue"
},
  "geometry": {"coordinates":[-79.6949920654,43.4410438538],"type":"Point"}
}