{
  "type": "Feature",
  "properties": {
    "iso:country":"CA",
    "sg:city":"Brandon",
    "sg:classifiers":[
        {
            "category":"Health Services",
            "subcategory":"Optometrist",
            "type":"Services"
        }
    ],
    "sg:phone":"+1 204 725 0943",
    "sg:postcode":"R7A 1M6",
    "sg:province":"MB",
    "wof:name":"Eye Outfitters",
    "wof:placetype":"venue"
},
  "geometry": {"coordinates":[-99.9521942139,49.8272972107],"type":"Point"}
}