{
  "type": "Feature",
  "properties": {
    "iso:country":"CA",
    "sg:address":"1512 Rue Lauzon",
    "sg:city":"Mascouche",
    "sg:classifiers":[
        {
            "category":"Building & Trades",
            "subcategory":"Electrical",
            "type":"Services"
        }
    ],
    "sg:phone":"+1 450 477 1288",
    "sg:postcode":"J7L 2R4",
    "sg:province":"QC",
    "sg:tags":[
        "electric",
        "contractor"
    ],
    "wof:name":"Jean Parent Electricite Eclair",
    "wof:placetype":"venue"
},
  "geometry": {"coordinates":[-73.66589355470001,45.7298698425],"type":"Point"}
}