{
  "type": "Feature",
  "properties": {
    "addr:full":"209 Rue Adelaide Sorel-Tracy QC J3P 1X6",
    "addr:housenumber":"209",
    "addr:postcode":"j3p 1x6",
    "addr:street":"Rue Adelaide",
    "iso:country":"CA",
    "sg:address":"209 Rue Adelaide",
    "sg:city":"Sorel-Tracy",
    "sg:classifiers":[
        {
            "category":"Organizations",
            "subcategory":"Religious Organization",
            "type":"Services"
        }
    ],
    "sg:phone":"+1 450 743 4490",
    "sg:postcode":"J3P 1X6",
    "sg:province":"QC",
    "sg:tags":[
        "church"
    ],
    "wof:name":"Presbytere St Maxime",
    "wof:placetype":"venue"
},
  "geometry": {"coordinates":[-73.104202,46.041306],"type":"Point"}
}