{
  "type": "Feature",
  "properties": {
    "iso:country":"CA",
    "sg:city":"Whitecourt",
    "sg:classifiers":[
        {
            "category":"Organizations",
            "subcategory":"Non-profit Organization",
            "type":"Services"
        }
    ],
    "sg:phone":"+1 780 778 2660",
    "sg:postcode":"T7S 1P7",
    "sg:province":"AB",
    "sg:tags":[
        "disability"
    ],
    "wof:name":"Echo Society",
    "wof:placetype":"venue"
},
  "geometry": {"coordinates":[-115.677627563,54.140460968],"type":"Point"}
}