{
  "type": "Feature",
  "properties": {
    "addr:full":"1805 Victoria Dr Vancouver BC V5N 4K1",
    "addr:housenumber":"1805",
    "addr:postcode":"v5n 4k1",
    "addr:street":"Victoria Dr",
    "iso:country":"CA",
    "sg:address":"1805 Victoria Dr",
    "sg:city":"Vancouver",
    "sg:classifiers":[
        {
            "category":"Government",
            "subcategory":"Fire Station",
            "type":"Public Place"
        }
    ],
    "sg:phone":"+1 604 665 6009",
    "sg:postcode":"V5N 4K1",
    "sg:province":"BC",
    "sg:tags":[
        "department"
    ],
    "wof:name":"Vancouver Firehall",
    "wof:placetype":"venue"
},
  "geometry": {"coordinates":[-123.06585699999999,49.268536],"type":"Point"}
}