{
  "type": "Feature",
  "properties": {
    "addr:full":"367 Hamilton River Rd Happy Valley-Goose Bay NL A0P 1C0",
    "addr:housenumber":"367",
    "addr:postcode":"a0p 1c0",
    "addr:street":"Hamilton River Rd",
    "iso:country":"CA",
    "sg:address":"367 Hamilton River Rd",
    "sg:city":"Happy Valley-Goose Bay",
    "sg:classifiers":[
        {
            "category":"Shopping",
            "subcategory":"Department Store",
            "type":"Retail Goods"
        }
    ],
    "sg:phone":"+1 709 896 7000",
    "sg:postcode":"A0P 1C0",
    "sg:province":"NL",
    "sg:tags":[
        "shop"
    ],
    "wof:name":"Dandy Dollar Store",
    "wof:placetype":"venue"
},
  "geometry": {"coordinates":[-60.3775901794,53.309879303],"type":"Point"}
}