{
  "type": "Feature",
  "properties": {
    "addr:full":"841 Wharncliffe Rd S London ON N6J 2N9",
    "addr:housenumber":"841",
    "addr:postcode":"n6j 2n9",
    "addr:street":"Wharncliffe Rd",
    "iso:country":"CA",
    "sg:address":"841 Wharncliffe Rd S",
    "sg:city":"London",
    "sg:classifiers":[
        {
            "category":"Food & Beverages",
            "subcategory":"Specialty",
            "type":"Retail Goods"
        }
    ],
    "sg:phone":"+1 519 686 6738",
    "sg:postcode":"N6J 2N9",
    "sg:province":"ON",
    "sg:tags":[
        "tea",
        "coffee"
    ],
    "wof:name":"Esso Tiger Express",
    "wof:placetype":"venue"
},
  "geometry": {"coordinates":[-81.2577590942,42.9419593811],"type":"Point"}
}