{
  "type": "Feature",
  "properties": {
    "iso:country":"CA",
    "sg:address":"185 Roseberry St",
    "sg:city":"Campbellton",
    "sg:classifiers":[
        {
            "category":"Restaurant",
            "type":"Food & Drink"
        }
    ],
    "sg:phone":"+1 506 759 8888",
    "sg:postcode":"E3N 2H4",
    "sg:province":"NB",
    "wof:name":"Mc Donald's",
    "wof:placetype":"venue"
},
  "geometry": {"coordinates":[-66.6851577759,48.0023384094],"type":"Point"}
}