{
  "type": "Feature",
  "properties": {
    "addr:full":"15422 Bannister Rd SE Calgary AB T2X 2X7",
    "addr:housenumber":"15422",
    "addr:postcode":"t2x 2x7",
    "addr:street":"Bannister Rd Se",
    "iso:country":"CA",
    "sg:address":"15422 Bannister Rd SE",
    "sg:city":"Calgary",
    "sg:classifiers":[
        {
            "category":"Restaurant",
            "type":"Food & Drink"
        }
    ],
    "sg:phone":"+1 403 310 1010",
    "sg:postcode":"T2X 2X7",
    "sg:province":"AB",
    "sg:tags":[
        "pizza"
    ],
    "wof:name":"Pizza Hut",
    "wof:placetype":"venue"
},
  "geometry": {"coordinates":[-114.065979,50.914951],"type":"Point"}
}