{
  "type": "Feature",
  "properties": {
    "addr:full":"Etobicoke ON M8X 2L1",
    "addr:postcode":"m8x 2l1",
    "iso:country":"CA",
    "sg:city":"Etobicoke",
    "sg:classifiers":[
        {
            "category":"Health Services",
            "subcategory":"Chiropractor",
            "type":"Services"
        }
    ],
    "sg:phone":"+1 416 236 9919",
    "sg:postcode":"M8X 2L1",
    "sg:province":"ON",
    "wof:name":"Kingsway Chiropractic Ctr",
    "wof:placetype":"venue"
},
  "geometry": {"coordinates":[-79.5065078735,43.6487121582],"type":"Point"}
}