{
  "type": "Feature",
  "properties": {
    "iso:country":"CA",
    "sg:address":"3390 Walker Rd # 2",
    "sg:city":"Windsor",
    "sg:classifiers":[
        {
            "category":"Autos & Motor Vehicles",
            "subcategory":"Auto Supplies",
            "type":"Retail Goods"
        }
    ],
    "sg:phone":"+1 519 969 6695",
    "sg:postcode":"N8W 3S1",
    "sg:province":"ON",
    "sg:tags":[
        "automobile",
        "equipment",
        "parts",
        "truck",
        "car",
        "racing"
    ],
    "wof:name":"Pro Auto Accessories",
    "wof:placetype":"venue"
},
  "geometry": {"coordinates":[-82.977715,42.276684],"type":"Point"}
}