{
  "type": "Feature",
  "properties": {
    "iso:country":"CA",
    "sg:address":"9540 62 Ave NW",
    "sg:city":"Edmonton",
    "sg:classifiers":[
        {
            "category":"Home & Garden",
            "subcategory":"Building Materials",
            "type":"Retail Goods"
        }
    ],
    "sg:phone":"+1 780 435 2291",
    "sg:postcode":"T6E 0E2",
    "sg:province":"AB",
    "sg:tags":[
        "plywood",
        "veneer"
    ],
    "wof:name":"Eberhard's Manufacturing Inc",
    "wof:placetype":"venue"
},
  "geometry": {"coordinates":[-113.475914002,53.4985847473],"type":"Point"}
}