{
  "type": "Feature",
  "properties": {
    "addr:full":"83 Shier Dr Winnipeg MB R3R 2H2",
    "addr:housenumber":"83",
    "addr:postcode":"r3r 2h2",
    "addr:street":"Shier Dr",
    "iso:country":"CA",
    "sg:address":"83 Shier Dr",
    "sg:city":"Winnipeg",
    "sg:classifiers":[
        {
            "category":"Education",
            "subcategory":"Vocational School",
            "type":"Public Place"
        }
    ],
    "sg:phone":"+1 204 831 1244",
    "sg:postcode":"R3R 2H2",
    "sg:province":"MB",
    "sg:tags":[
        "training",
        "computer"
    ],
    "wof:name":"Data Aid Systems Inc",
    "wof:placetype":"venue"
},
  "geometry": {"coordinates":[-97.315269,49.870564],"type":"Point"}
}