{
  "type": "Feature",
  "properties": {
    "addr:full":"777 the Queensway #C Etobicoke ON M8Z 1N4",
    "addr:housenumber":"777",
    "addr:postcode":"m8z 1n4",
    "addr:street":"The Queensway # C",
    "iso:country":"CA",
    "sg:address":"777 the Queensway #C",
    "sg:city":"Etobicoke",
    "sg:classifiers":[
        {
            "category":"Manufacturing",
            "subcategory":"Signs",
            "type":"Manufacturing & Wholesale Goods"
        }
    ],
    "sg:phone":"+1 416 255 9182",
    "sg:postcode":"M8Z 1N4",
    "sg:province":"ON",
    "sg:tags":[
        "printer"
    ],
    "wof:name":"Master Printing Inc",
    "wof:placetype":"venue"
},
  "geometry": {"coordinates":[-79.5054092407,43.6255722046],"type":"Point"}
}