{
  "type": "Feature",
  "properties": {
    "iso:country":"CA",
    "sg:address":"2801 Rue King E",
    "sg:city":"Fleurimont",
    "sg:classifiers":[
        {
            "category":"Building & Trades",
            "subcategory":"Construction",
            "type":"Services"
        }
    ],
    "sg:phone":"+1 819 564 2370",
    "sg:postcode":"J1G 5G9",
    "sg:province":"QC",
    "sg:tags":[
        "sandblasting"
    ],
    "wof:name":"Jet DE Sable Claude Bernier",
    "wof:placetype":"venue"
},
  "geometry": {"coordinates":[-71.83149719239999,45.415851593],"type":"Point"}
}