{
  "type": "Feature",
  "properties": {
    "addr:full":"89 Water St Summerside PE C1N 1A6",
    "addr:housenumber":"89",
    "addr:postcode":"c1n 1a6",
    "addr:street":"Water St",
    "iso:country":"CA",
    "sg:address":"89 Water St",
    "sg:city":"Summerside",
    "sg:classifiers":[
        {
            "category":"Building & Trades",
            "subcategory":"Plumbing",
            "type":"Services"
        }
    ],
    "sg:phone":"+1 902 436 3848",
    "sg:postcode":"C1N 1A6",
    "sg:province":"PE",
    "sg:tags":[
        "contractor"
    ],
    "wof:name":"George Smith & Sons Plbg & Htg",
    "wof:placetype":"venue"
},
  "geometry": {"coordinates":[-63.7820625305,46.3905639648],"type":"Point"}
}