{
  "type": "Feature",
  "properties": {
    "addr:full":"109 King St E Bowmanville ON L1C 1N4",
    "addr:housenumber":"109",
    "addr:postcode":"l1c 1n4",
    "addr:street":"King St",
    "iso:country":"CA",
    "sg:address":"109 King St E",
    "sg:city":"Bowmanville",
    "sg:classifiers":[
        {
            "category":"Restaurant",
            "type":"Food & Drink"
        }
    ],
    "sg:phone":"+1 905 623 2848",
    "sg:postcode":"L1C 1N4",
    "sg:province":"ON",
    "sg:tags":[
        "banquet",
        "association",
        "rooms"
    ],
    "wof:name":"Royal Canadian Legion Office",
    "wof:placetype":"venue"
},
  "geometry": {"coordinates":[-78.68542480470001,43.9111022949],"type":"Point"}
}