{
  "type": "Feature",
  "properties": {
    "addr:full":"256 Wallace St Nanaimo BC V9R 5B3",
    "addr:housenumber":"256",
    "addr:postcode":"v9r 5b3",
    "addr:street":"Wallace St",
    "iso:country":"CA",
    "sg:address":"256 Wallace St",
    "sg:city":"Nanaimo",
    "sg:classifiers":[
        {
            "category":"Sports & Exercise",
            "subcategory":"Gym",
            "type":"Entertainment"
        }
    ],
    "sg:phone":"+1 250 754 3123",
    "sg:postcode":"V9R 5B3",
    "sg:province":"BC",
    "sg:tags":[
        "court",
        "club",
        "gymnasium",
        "squash",
        "health",
        "studio"
    ],
    "wof:name":"Nanaimo Squash Club",
    "wof:placetype":"venue"
},
  "geometry": {"coordinates":[-123.940475464,49.1664772034],"type":"Point"}
}