{
  "type": "Feature",
  "properties": {
    "addr:full":"954 King Edward Ave W Vancouver BC V5Z 2E2",
    "addr:housenumber":"954",
    "addr:postcode":"v5z 2e2",
    "addr:street":"King Edward Ave W",
    "iso:country":"CA",
    "sg:address":"954 King Edward Ave W",
    "sg:city":"Vancouver",
    "sg:classifiers":[
        {
            "category":"Restaurant",
            "type":"Food & Drink"
        }
    ],
    "sg:phone":"+1 604 730 9687",
    "sg:postcode":"V5Z 2E2",
    "sg:province":"BC",
    "wof:name":"Sushi Ben",
    "wof:placetype":"venue"
},
  "geometry": {"coordinates":[-123.126098633,49.2490234375],"type":"Point"}
}