{
  "type": "Feature",
  "properties": {
    "addr:full":"1706 Brookland Rd Pictou NS B0K 1H0",
    "addr:housenumber":"1706",
    "addr:postcode":"b0k 1h0",
    "addr:street":"Brookland Rd",
    "iso:country":"CA",
    "sg:address":"1706 Brookland Rd",
    "sg:city":"Pictou",
    "sg:classifiers":[
        {
            "category":"Travel",
            "subcategory":"Campground",
            "type":"Entertainment"
        }
    ],
    "sg:phone":"+1 902 485 1872",
    "sg:postcode":"B0K 1H0",
    "sg:province":"NS",
    "wof:name":"Brookside Camp Ground",
    "wof:placetype":"venue"
},
  "geometry": {"coordinates":[-62.707073,45.678181],"type":"Point"}
}