{
  "type": "Feature",
  "properties": {
    "addr:full":"1211 Prospect St Fredericton NB E3B 3B9",
    "addr:housenumber":"1211",
    "addr:postcode":"e3b 3b9",
    "addr:street":"Prospect St",
    "iso:country":"CA",
    "sg:address":"1211 Prospect St",
    "sg:city":"Fredericton",
    "sg:classifiers":[
        {
            "category":"Recreation",
            "type":"Entertainment"
        }
    ],
    "sg:phone":"+1 506 455 7765",
    "sg:postcode":"E3B 3B9",
    "sg:province":"NB",
    "sg:tags":[
        "parlor",
        "billiard"
    ],
    "wof:name":"Dooly's Billiard Room",
    "wof:placetype":"venue"
},
  "geometry": {"coordinates":[-66.66246,45.939877],"type":"Point"}
}