{
  "type": "Feature",
  "properties": {
    "addr:full":"40 Wharton Blvd Winnipeg MB R2Y 0T1",
    "addr:housenumber":"40",
    "addr:postcode":"r2y 0t1",
    "addr:street":"Wharton Blvd",
    "iso:country":"CA",
    "sg:address":"40 Wharton Blvd",
    "sg:city":"Winnipeg",
    "sg:classifiers":[
        {
            "category":"Home & Garden",
            "subcategory":"Home Furnishings",
            "type":"Retail Goods"
        }
    ],
    "sg:phone":"+1 204 837 1015",
    "sg:postcode":"R2Y 0T1",
    "sg:province":"MB",
    "sg:tags":[
        "curtain",
        "made",
        "drapery"
    ],
    "wof:name":"Expert Design Drapes",
    "wof:placetype":"venue"
},
  "geometry": {"coordinates":[-97.290588,49.883324],"type":"Point"}
}