{
  "type": "Feature",
  "properties": {
    "addr:full":"1630 Ch Des Bouvreuils Becancour QC G9H 4C8",
    "addr:postcode":"1630;g9h 4c8",
    "addr:street":"Ch Des Bouvreuils Becancour",
    "iso:country":"CA",
    "sg:address":"1630 Ch Des Bouvreuils",
    "sg:city":"Becancour",
    "sg:classifiers":[
        {
            "category":"Taxi",
            "type":"Transportation"
        }
    ],
    "sg:phone":"+1 819 371 4545",
    "sg:postcode":"G9H 4C8",
    "sg:province":"QC",
    "sg:tags":[
        "taxicab"
    ],
    "wof:name":"Taxi Becandour DE Gentilly",
    "wof:placetype":"venue"
},
  "geometry": {"coordinates":[-72.231148,46.386196],"type":"Point"}
}