{
  "type": "Feature",
  "properties": {
    "addr:full":"Calgary AB T2P 3C5",
    "addr:postcode":"t2p 3c5",
    "iso:country":"CA",
    "sg:city":"Calgary",
    "sg:classifiers":[
        {
            "category":"Professional",
            "subcategory":"Business Services",
            "type":"Services"
        }
    ],
    "sg:phone":"+1 403 571 9120",
    "sg:postcode":"T2P 3C5",
    "sg:province":"AB",
    "sg:tags":[
        "license"
    ],
    "wof:name":"City Centre Registry Inc",
    "wof:placetype":"venue"
},
  "geometry": {"coordinates":[-114.070808411,51.0446777344],"type":"Point"}
}