{
  "type": "Feature",
  "properties": {
    "addr:full":"673 Boul Cure-Labelle Laval QC H7V 2T8",
    "addr:housenumber":"673",
    "addr:postcode":"h7v 2t8",
    "addr:street":"Boul Cure-Labelle",
    "iso:country":"CA",
    "sg:address":"673 Boul Cure-Labelle",
    "sg:city":"Laval",
    "sg:classifiers":[
        {
            "category":"Shopping",
            "subcategory":"Optical Goods",
            "type":"Retail Goods"
        }
    ],
    "sg:phone":"+1 450 688 9900",
    "sg:postcode":"H7V 2T8",
    "sg:province":"QC",
    "sg:tags":[
        "optician"
    ],
    "wof:name":"Laoun-Nicopoulos, P",
    "wof:placetype":"venue"
},
  "geometry": {"coordinates":[-73.7444763184,45.5377006531],"type":"Point"}
}