{
  "type": "Feature",
  "properties": {
    "addr:full":"29 Clarke St N Woodstock ON N4S 7M4",
    "addr:housenumber":"29",
    "addr:postcode":"n4s 7m4",
    "addr:street":"Clarke St N",
    "iso:country":"CA",
    "sg:address":"29 Clarke St N",
    "sg:city":"Woodstock",
    "sg:classifiers":[
        {
            "category":"Food & Beverages",
            "subcategory":"Groceries & Convenience Stores",
            "type":"Retail Goods"
        }
    ],
    "sg:phone":"+1 519 539 0990",
    "sg:postcode":"N4S 7M4",
    "sg:province":"ON",
    "wof:name":"Hasty Market",
    "wof:placetype":"venue"
},
  "geometry": {"coordinates":[-80.735191,43.135231],"type":"Point"}
}