{
  "type": "Feature",
  "properties": {
    "addr:full":"645 Rue DE Megeve Laval QC H7N 5M7",
    "addr:housenumber":"645",
    "addr:postcode":"h7n 5m7",
    "addr:street":"Rue De Megeve",
    "iso:country":"CA",
    "sg:address":"645 Rue DE Megeve",
    "sg:city":"Laval",
    "sg:classifiers":[
        {
            "category":"Building & Trades",
            "subcategory":"Construction",
            "type":"Services"
        }
    ],
    "sg:phone":"+1 450 668 9157",
    "sg:postcode":"H7N 5M7",
    "sg:province":"QC",
    "sg:tags":[
        "contractor"
    ],
    "wof:name":"Construction Briancon Inc",
    "wof:placetype":"venue"
},
  "geometry": {"coordinates":[-73.7082824707,45.5663414001],"type":"Point"}
}