{
  "type": "Feature",
  "properties": {
    "addr:full":"Granby QC J2G 2T4",
    "addr:postcode":"j2g 2t4",
    "iso:country":"CA",
    "sg:city":"Granby",
    "sg:classifiers":[
        {
            "category":"Professional",
            "subcategory":"Art Services",
            "type":"Services"
        }
    ],
    "sg:phone":"+1 450 375 7609",
    "sg:postcode":"J2G 2T4",
    "sg:province":"QC",
    "sg:tags":[
        "graphic",
        "designer"
    ],
    "wof:name":"Graphiste Anne Piche Enr",
    "wof:placetype":"venue"
},
  "geometry": {"coordinates":[-72.7227935791,45.3982315063],"type":"Point"}
}