{
  "type": "Feature",
  "properties": {
    "iso:country":"CA",
    "sg:address":"4025 101 St NW",
    "sg:city":"Edmonton",
    "sg:classifiers":[
        {
            "category":"Building & Trades",
            "subcategory":"Construction",
            "type":"Services"
        }
    ],
    "sg:phone":"+1 780 435 8338",
    "sg:postcode":"T6E 0A4",
    "sg:province":"AB",
    "sg:tags":[
        "paving",
        "contractor"
    ],
    "wof:name":"Park Paving Ltd",
    "wof:placetype":"venue"
},
  "geometry": {"coordinates":[-113.488578796,53.4761123657],"type":"Point"}
}