{
  "type": "Feature",
  "properties": {
    "addr:full":"380 Dixon Rd # 100 Etobicoke ON M9R 1T3",
    "addr:housenumber":"380",
    "addr:postcode":"m9r 1t3",
    "addr:street":"Dixon Rd # 100",
    "iso:country":"CA",
    "sg:address":"380 Dixon Rd # 100",
    "sg:city":"Etobicoke",
    "sg:classifiers":[
        {
            "category":"Personal",
            "subcategory":"Beauty Salon",
            "type":"Services"
        }
    ],
    "sg:phone":"+1 416 244 2826",
    "sg:postcode":"M9R 1T3",
    "sg:province":"ON",
    "wof:name":"Amelia's Hair Styling",
    "wof:placetype":"venue"
},
  "geometry": {"coordinates":[-79.556877,43.694855],"type":"Point"}
}