{
  "type": "Feature",
  "properties": {
    "iso:country":"CA",
    "sg:address":"103 Lakeshore Dr",
    "sg:city":"North Bay",
    "sg:classifiers":[
        {
            "category":"Personal",
            "subcategory":"Beauty Salon",
            "type":"Services"
        }
    ],
    "sg:phone":"+1 705 472 0337",
    "sg:postcode":"P1A 2A5",
    "sg:province":"ON",
    "wof:name":"Sports Cut Hairstyling",
    "wof:placetype":"venue"
},
  "geometry": {"coordinates":[-79.4532089233,46.2919654846],"type":"Point"}
}