{
  "type": "Feature",
  "properties": {
    "iso:country":"CA",
    "sg:address":"1594 Lakeshore Dr",
    "sg:city":"Thunder Bay",
    "sg:classifiers":[
        {
            "category":"Organizations",
            "subcategory":"Professional Association",
            "type":"Services"
        }
    ],
    "sg:phone":"+1 807 983 2042",
    "sg:postcode":"P7B 5E4",
    "sg:province":"ON",
    "wof:name":"Back Packers Hostel Canada",
    "wof:placetype":"venue"
},
  "geometry": {"coordinates":[-89.245475769,48.3816986084],"type":"Point"}
}