{
  "type": "Feature",
  "properties": {
    "addr:full":"778 Rue Richard Joliette QC J6E 2V1",
    "addr:housenumber":"778",
    "addr:postcode":"j6e 2v1",
    "addr:street":"Rue Richard",
    "iso:country":"CA",
    "sg:address":"778 Rue Richard",
    "sg:city":"Joliette",
    "sg:classifiers":[
        {
            "category":"Manufacturing",
            "subcategory":"Electronics",
            "type":"Manufacturing & Wholesale Goods"
        }
    ],
    "sg:phone":"+1 450 752 6610",
    "sg:postcode":"J6E 2V1",
    "sg:province":"QC",
    "sg:tags":[
        "control",
        "security",
        "system"
    ],
    "wof:name":"Secur-Icare",
    "wof:placetype":"venue"
},
  "geometry": {"coordinates":[-73.44892900000001,46.02459],"type":"Point"}
}