{
  "type": "Feature",
  "properties": {
    "addr:full":"58 Rue Notre-Dame S Thetford Mines QC G6G 1J3",
    "addr:housenumber":"58",
    "addr:postcode":"g6g 1j3",
    "addr:street":"Rue Notre-Dame S Thetford",
    "iso:country":"CA",
    "sg:address":"58 Rue Notre-Dame S",
    "sg:city":"Thetford Mines",
    "sg:classifiers":[
        {
            "category":"Shopping",
            "subcategory":"Shoes",
            "type":"Retail Goods"
        }
    ],
    "sg:phone":"+1 418 335 3118",
    "sg:postcode":"G6G 1J3",
    "sg:province":"QC",
    "wof:name":"Boutique Bon Pied Bon Oeil",
    "wof:placetype":"venue"
},
  "geometry": {"coordinates":[-71.3010482788,46.0899734497],"type":"Point"}
}