{
  "type": "Feature",
  "properties": {
    "iso:country":"CA",
    "sg:address":"346 Newkirk Rd",
    "sg:city":"Richmond Hill",
    "sg:classifiers":[
        {
            "category":"Building & Trades",
            "subcategory":"Construction",
            "type":"Services"
        }
    ],
    "sg:phone":"+1 905 508 6176",
    "sg:postcode":"L4C 0A9",
    "sg:province":"ON",
    "sg:tags":[
        "general",
        "contractor"
    ],
    "wof:name":"Peter Lee Renovation & Constr",
    "wof:placetype":"venue"
},
  "geometry": {"coordinates":[-79.43241119379999,43.8895492554],"type":"Point"}
}