{
  "type": "Feature",
  "properties": {
    "iso:country":"CA",
    "sg:address":"535 Rue DE Serres",
    "sg:city":"Terrebonne",
    "sg:classifiers":[
        {
            "category":"Professional",
            "subcategory":"Computer Services",
            "type":"Services"
        }
    ],
    "sg:phone":"+1 514 233 7711",
    "sg:postcode":"J6Y 1N1",
    "sg:province":"QC",
    "sg:tags":[
        "information",
        "system",
        "consultant"
    ],
    "wof:name":"Optisim Consultants Inc",
    "wof:placetype":"venue"
},
  "geometry": {"coordinates":[-73.746994,45.679649],"type":"Point"}
}