{
  "type": "Feature",
  "properties": {
    "addr:full":"Hwy 5 E Humboldt SK S0K 2A0",
    "addr:postcode":"s0k 2a0",
    "addr:street":"Hwy 5 E",
    "iso:country":"CA",
    "sg:address":"Hwy 5 E",
    "sg:city":"Humboldt",
    "sg:classifiers":[
        {
            "category":"Retail",
            "subcategory":"Repair Shop",
            "type":"Services"
        }
    ],
    "sg:phone":"+1 306 682 5832",
    "sg:postcode":"S0K 2A0",
    "sg:province":"SK",
    "sg:tags":[
        "machine",
        "welding"
    ],
    "wof:name":"Hi-Tech Welding Machining",
    "wof:placetype":"venue"
},
  "geometry": {"coordinates":[-105.092545,52.201939],"type":"Point"}
}