{
  "type": "Feature",
  "properties": {
    "addr:full":"325 4th St Winkler MB R6W 4B6",
    "addr:housenumber":"325",
    "addr:postcode":"r6w 4b6",
    "addr:street":"4Th St",
    "iso:country":"CA",
    "sg:address":"325 4th St",
    "sg:city":"Winkler",
    "sg:classifiers":[
        {
            "category":"Shopping",
            "subcategory":"Used Merchandise",
            "type":"Retail Goods"
        }
    ],
    "sg:phone":"+1 204 325 9770",
    "sg:postcode":"R6W 4B6",
    "sg:province":"MB",
    "sg:tags":[
        "second",
        "store",
        "hand"
    ],
    "wof:name":"Mcc Community Store",
    "wof:placetype":"venue"
},
  "geometry": {"coordinates":[-97.93757600000001,49.182228],"type":"Point"}
}