{
  "type": "Feature",
  "properties": {
    "addr:full":"4610 34 St Vernon BC V1T 5Y9",
    "addr:housenumber":"4610",
    "addr:postcode":"v1t 5y9",
    "addr:street":"34 St",
    "iso:country":"CA",
    "sg:address":"4610 34 St",
    "sg:city":"Vernon",
    "sg:classifiers":[
        {
            "category":"Retail",
            "subcategory":"Auto Repair",
            "type":"Services"
        }
    ],
    "sg:phone":"+1 250 542 3124",
    "sg:postcode":"V1T 5Y9",
    "sg:province":"BC",
    "sg:tags":[
        "body",
        "automobile",
        "painting"
    ],
    "wof:name":"Monashee Auto Body Ltd",
    "wof:placetype":"venue"
},
  "geometry": {"coordinates":[-119.276169,50.275799],"type":"Point"}
}