{
  "type": "Feature",
  "properties": {
    "addr:full":"264 Browns Line Etobicoke ON M8W 3T5",
    "addr:housenumber":"264",
    "addr:postcode":"m8w 3t5",
    "addr:street":"Browns Line",
    "iso:country":"CA",
    "sg:address":"264 Browns Line",
    "sg:city":"Etobicoke",
    "sg:classifiers":[
        {
            "category":"Bars & Pubs",
            "type":"Food & Drink"
        }
    ],
    "sg:phone":"+1 416 233 8827",
    "sg:postcode":"M8W 3T5",
    "sg:province":"ON",
    "wof:name":"Rose & Thorne Pub",
    "wof:placetype":"venue"
},
  "geometry": {"coordinates":[-79.5440292358,43.5986022949],"type":"Point"}
}