{
  "type": "Feature",
  "properties": {
    "addr:full":"1108 9th Ave W Kindersley SK S0L 1S0",
    "addr:housenumber":"1108",
    "addr:postcode":"s0l 1s0",
    "addr:street":"9Th Ave W Kindersley",
    "iso:country":"CA",
    "sg:address":"1108 9th Ave W",
    "sg:city":"Kindersley",
    "sg:classifiers":[
        {
            "category":"Wholesale",
            "subcategory":"Meat",
            "type":"Manufacturing & Wholesale Goods"
        }
    ],
    "sg:phone":"+1 306 463 3666",
    "sg:postcode":"S0L 1S0",
    "sg:province":"SK",
    "sg:tags":[
        "packer"
    ],
    "wof:name":"Kindersley Packers",
    "wof:placetype":"venue"
},
  "geometry": {"coordinates":[-109.17011261,51.4728431702],"type":"Point"}
}