{
  "type": "Feature",
  "properties": {
    "addr:full":"Toronto ON M6P 4A9",
    "addr:postcode":"m6p 4a9",
    "iso:country":"CA",
    "sg:city":"Toronto",
    "sg:classifiers":[
        {
            "category":"Recreation",
            "type":"Entertainment"
        }
    ],
    "sg:phone":"+1 416 536 1941",
    "sg:postcode":"M6P 4A9",
    "sg:province":"ON",
    "sg:tags":[
        "lottery",
        "agent"
    ],
    "wof:name":"Crossway Lottery Ctr",
    "wof:placetype":"venue"
},
  "geometry": {"coordinates":[-79.45237,43.656822],"type":"Point"}
}