{
  "type": "Feature",
  "properties": {
    "iso:country":"CA",
    "sg:address":"357 Kane Ave",
    "sg:city":"York",
    "sg:classifiers":[
        {
            "category":"Building & Trades",
            "subcategory":"Construction",
            "type":"Services"
        }
    ],
    "sg:phone":"+1 416 652 8777",
    "sg:postcode":"M6M 3N9",
    "sg:province":"ON",
    "sg:tags":[
        "concrete",
        "contractor"
    ],
    "wof:name":"Conte Brothers Concrete Pros",
    "wof:placetype":"venue"
},
  "geometry": {"coordinates":[-79.46961212159999,43.6898078918],"type":"Point"}
}