{
  "type": "Feature",
  "properties": {
    "addr:full":"3350 Spitfire Rd Cassidy BC V0R 1H0",
    "addr:housenumber":"3350",
    "addr:postcode":"v0r 1h0",
    "addr:street":"Spitfire Rd",
    "iso:country":"CA",
    "sg:address":"3350 Spitfire Rd",
    "sg:city":"Cassidy",
    "sg:classifiers":[
        {
            "category":"Autos & Motor Vehicles",
            "subcategory":"Recreational Vehicle Sales",
            "type":"Retail Goods"
        }
    ],
    "sg:phone":"+1 250 245 3858",
    "sg:postcode":"V0R 1H0",
    "sg:province":"BC",
    "wof:name":"Arbutus Rv & Marine Sales Ltd",
    "wof:placetype":"venue"
},
  "geometry": {"coordinates":[-123.862815857,49.0647201538],"type":"Point"}
}