{
  "type": "Feature",
  "properties": {
    "iso:country":"CA",
    "sg:address":"100 King St W",
    "sg:city":"Chatham",
    "sg:classifiers":[
        {
            "category":"Professional",
            "subcategory":"Business Services",
            "type":"Services"
        }
    ],
    "sg:phone":"+1 519 351 0939",
    "sg:postcode":"N7M 6A9",
    "sg:province":"ON",
    "sg:tags":[
        "engraver"
    ],
    "wof:name":"Things Engraved",
    "wof:placetype":"venue"
},
  "geometry": {"coordinates":[-82.18264,42.404991],"type":"Point"}
}