{
  "type": "Feature",
  "properties": {
    "iso:country":"CA",
    "sg:city":"Montreal",
    "sg:classifiers":[
        {
            "category":"Health Services",
            "subcategory":"Clinic",
            "type":"Services"
        }
    ],
    "sg:phone":"+1 514 335 1813",
    "sg:postcode":"H3L 2P6",
    "sg:province":"QC",
    "sg:tags":[
        "home",
        "nurse",
        "registry"
    ],
    "wof:name":"Service DE Personnel Infirmier",
    "wof:placetype":"venue"
},
  "geometry": {"coordinates":[-73.668976,45.549599],"type":"Point"}
}