{
  "type": "Feature",
  "properties": {
    "iso:country":"CA",
    "sg:address":"1890 Ch DE LA Canardiere",
    "sg:city":"Quebec",
    "sg:classifiers":[
        {
            "category":"Personal",
            "subcategory":"Beauty Salon",
            "type":"Services"
        }
    ],
    "sg:phone":"+1 418 663 8669",
    "sg:postcode":"G1J 2E4",
    "sg:province":"QC",
    "wof:name":"Salon Variance",
    "wof:placetype":"venue"
},
  "geometry": {"coordinates":[-71.221558,46.838692],"type":"Point"}
}