{
  "type": "Feature",
  "properties": {
    "iso:country":"CA",
    "sg:address":"400 Montfort St",
    "sg:city":"Vanier",
    "sg:classifiers":[
        {
            "category":"Real Estate",
            "subcategory":"Real Estate Operator",
            "type":"Services"
        }
    ],
    "sg:phone":"+1 613 745 3747",
    "sg:postcode":"K1L 8G6",
    "sg:province":"ON",
    "sg:tags":[
        "apartment"
    ],
    "wof:name":"Place Montfort",
    "wof:placetype":"venue"
},
  "geometry": {"coordinates":[-75.6536407471,45.440071106],"type":"Point"}
}