{
  "type": "Feature",
  "properties": {
    "addr:full":"3578 Boul DE LA Concorde E Laval QC H7E 2C7",
    "addr:housenumber":"3578",
    "addr:postcode":"h7e 2c7",
    "addr:street":"Boul De La Concorde E",
    "iso:country":"CA",
    "sg:address":"3578 Boul DE LA Concorde E",
    "sg:city":"Laval",
    "sg:classifiers":[
        {
            "category":"Shopping",
            "type":"Retail Goods"
        }
    ],
    "sg:phone":"+1 514 990 6043",
    "sg:postcode":"H7E 2C7",
    "sg:province":"QC",
    "sg:tags":[
        "equipment",
        "telephone",
        "supply"
    ],
    "wof:name":"Tele Data Rb Inc",
    "wof:placetype":"venue"
},
  "geometry": {"coordinates":[-73.660049,45.596043],"type":"Point"}
}