{
  "type": "Feature",
  "properties": {
    "addr:full":"10710 Boul Pie-Ix Montreal-Nord QC H1H 4A7",
    "addr:housenumber":"10710",
    "addr:postcode":"h1h 4a7",
    "addr:street":"Boul Pie-Ix",
    "iso:country":"CA",
    "sg:address":"10710 Boul Pie-Ix",
    "sg:city":"Montreal-Nord",
    "sg:classifiers":[
        {
            "category":"Restaurant",
            "type":"Food & Drink"
        }
    ],
    "sg:phone":"+1 514 323 8561",
    "sg:postcode":"H1H 4A7",
    "sg:province":"QC",
    "wof:name":"Restaurant LA Belle Province",
    "wof:placetype":"venue"
},
  "geometry": {"coordinates":[-73.63581848139999,45.589176178],"type":"Point"}
}