{
  "type": "Feature",
  "properties": {
    "addr:full":"306 Berford St Wiarton ON N0H 2T0",
    "addr:housenumber":"306",
    "addr:postcode":"n0h 2t0",
    "addr:street":"Berford St",
    "iso:country":"CA",
    "sg:address":"306 Berford St",
    "sg:city":"Wiarton",
    "sg:classifiers":[
        {
            "category":"Professional",
            "subcategory":"Business Services",
            "type":"Services"
        }
    ],
    "sg:phone":"+1 519 534 3044",
    "sg:postcode":"N0H 2T0",
    "sg:province":"ON",
    "sg:tags":[
        "license",
        "government"
    ],
    "wof:name":"Ontario Driver & Vehicle Agnts",
    "wof:placetype":"venue"
},
  "geometry": {"coordinates":[-81.140579,44.735825],"type":"Point"}
}