{
  "type": "Feature",
  "properties": {
    "iso:country":"CA",
    "sg:address":"402 Summerhill Ave",
    "sg:city":"Toronto",
    "sg:classifiers":[
        {
            "category":"Professional",
            "subcategory":"Management & Consulting",
            "type":"Services"
        }
    ],
    "sg:phone":"+1 416 963 8008",
    "sg:postcode":"M4W 2E4",
    "sg:province":"ON",
    "sg:tags":[
        "town",
        "city",
        "regional",
        "architect",
        "planner"
    ],
    "wof:name":"Lind, Victor N",
    "wof:placetype":"venue"
},
  "geometry": {"coordinates":[-79.3774032593,43.6858634949],"type":"Point"}
}