{
  "type": "Feature",
  "properties": {
    "addr:full":"Levis QC G6V 6J7",
    "addr:postcode":"g6v 6j7",
    "iso:country":"CA",
    "sg:city":"Levis",
    "sg:classifiers":[
        {
            "category":"Professional",
            "subcategory":"Accounting & Tax Preparation",
            "type":"Services"
        }
    ],
    "sg:phone":"+1 418 837 8895",
    "sg:postcode":"G6V 6J7",
    "sg:province":"QC",
    "sg:tags":[
        "accountant",
        "bookkeeping",
        "system"
    ],
    "wof:name":"Comptablilte & Controles Saj",
    "wof:placetype":"venue"
},
  "geometry": {"coordinates":[-71.188362,46.797314],"type":"Point"}
}