{
  "type": "Feature",
  "properties": {
    "iso:country":"CA",
    "sg:address":"1742 Spruce Hill Rd",
    "sg:city":"Pickering",
    "sg:classifiers":[
        {
            "category":"Building & Trades",
            "subcategory":"Construction",
            "type":"Services"
        }
    ],
    "sg:phone":"+1 905 420 5183",
    "sg:postcode":"L1V 1S4",
    "sg:province":"ON",
    "sg:tags":[
        "contractor"
    ],
    "wof:name":"W J Linder Construction Ltd",
    "wof:placetype":"venue"
},
  "geometry": {"coordinates":[-79.1100311279,43.8261070251],"type":"Point"}
}