{
  "type": "Feature",
  "properties": {
    "addr:full":"Cambridge ON N3H 4R6",
    "addr:postcode":"n3h 4r6",
    "iso:country":"CA",
    "sg:city":"Cambridge",
    "sg:classifiers":[
        {
            "category":"Building & Trades",
            "subcategory":"Landscaping Services",
            "type":"Services"
        }
    ],
    "sg:phone":"+1 519 653 5848",
    "sg:postcode":"N3H 4R6",
    "sg:province":"ON",
    "sg:tags":[
        "tree"
    ],
    "wof:name":"Moffatt Tree & Stump Removal",
    "wof:placetype":"venue"
},
  "geometry": {"coordinates":[-80.358047,43.441814],"type":"Point"}
}