{
  "type": "Feature",
  "properties": {
    "iso:country":"CA",
    "sg:address":"499 Main St S # 163",
    "sg:city":"Brampton",
    "sg:classifiers":[
        {
            "category":"Shopping",
            "subcategory":"Clothing, Apparel, & Fashions",
            "type":"Retail Goods"
        }
    ],
    "sg:phone":"+1 905 453 5984",
    "sg:postcode":"L6Y 1N7",
    "sg:province":"ON",
    "wof:name":"Stitches",
    "wof:placetype":"venue"
},
  "geometry": {"coordinates":[-79.73579406739999,43.6675834656],"type":"Point"}
}