{
  "type": "Feature",
  "properties": {
    "addr:full":"L'Assomption QC J5W 2R1",
    "addr:postcode":"j5w 2r1",
    "iso:country":"CA",
    "sg:city":"L'Assomption",
    "sg:classifiers":[
        {
            "category":"Retail",
            "subcategory":"Auto Repair",
            "type":"Services"
        }
    ],
    "sg:phone":"+1 450 589 7667",
    "sg:postcode":"J5W 2R1",
    "sg:province":"QC",
    "sg:tags":[
        "body",
        "automobile",
        "painting"
    ],
    "wof:name":"B M Auto Collision Enr",
    "wof:placetype":"venue"
},
  "geometry": {"coordinates":[-73.4139328003,45.8437080383],"type":"Point"}
}