{
  "type": "Feature",
  "properties": {
    "iso:country":"CA",
    "sg:city":"Toronto",
    "sg:classifiers":[
        {
            "category":"Professional",
            "subcategory":"Lawyer & Legal Services",
            "type":"Services"
        }
    ],
    "sg:phone":"+1 416 368 0231",
    "sg:postcode":"M5H 1T1",
    "sg:province":"ON",
    "sg:tags":[
        "attorney"
    ],
    "wof:name":"Mc Carthy, Todd J",
    "wof:placetype":"venue"
},
  "geometry": {"coordinates":[-79.3833999634,43.6494598389],"type":"Point"}
}