{
  "type": "Feature",
  "properties": {
    "addr:full":"2975 Bradner Rd Abbotsford BC V4X 1K6",
    "addr:housenumber":"2975",
    "addr:postcode":"v4x 1k6",
    "addr:street":"Bradner Rd",
    "iso:country":"CA",
    "sg:address":"2975 Bradner Rd",
    "sg:city":"Abbotsford",
    "sg:classifiers":[
        {
            "category":"Education",
            "subcategory":"School",
            "type":"Public Place"
        }
    ],
    "sg:phone":"+1 604 856 5137",
    "sg:postcode":"V4X 1K6",
    "sg:province":"BC",
    "wof:name":"Aberdeen Elementary School",
    "wof:placetype":"venue"
},
  "geometry": {"coordinates":[-122.42654419,49.0555534363],"type":"Point"}
}