{
  "type": "Feature",
  "properties": {
    "iso:country":"CA",
    "sg:city":"Vancouver",
    "sg:classifiers":[
        {
            "category":"Shopping",
            "subcategory":"Jewelry",
            "type":"Retail Goods"
        }
    ],
    "sg:phone":"+1 604 689 9608",
    "sg:postcode":"V7Y 1K8",
    "sg:province":"BC",
    "sg:tags":[
        "jeweler"
    ],
    "wof:name":"Siba Jewellers",
    "wof:placetype":"venue"
},
  "geometry": {"coordinates":[-123.11807251,49.2825660706],"type":"Point"}
}