{
  "type": "Feature",
  "properties": {
    "addr:full":"823 17 Ave SW Calgary AB T2T 0A1",
    "addr:postcode":"t2t 0a1",
    "addr:street":"823 17 Ave Sw",
    "iso:country":"CA",
    "sg:address":"823 17 Ave SW",
    "sg:city":"Calgary",
    "sg:classifiers":[
        {
            "category":"Restaurant",
            "type":"Food & Drink"
        }
    ],
    "sg:phone":"+1 403 244 5522",
    "sg:postcode":"T2T 0A1",
    "sg:province":"AB",
    "wof:name":"Buon Giorno Ristorante Italian",
    "wof:placetype":"venue"
},
  "geometry": {"coordinates":[-114.08003234900001,51.0375976562],"type":"Point"}
}