{
  "type": "Feature",
  "properties": {
    "addr:full":"Saint-Eusebe QC G0L 2Y0",
    "addr:postcode":"g0l 2y0",
    "iso:country":"CA",
    "sg:city":"Saint-Eusebe",
    "sg:classifiers":[
        {
            "category":"Government",
            "subcategory":"Office",
            "type":"Public Place"
        }
    ],
    "sg:phone":"+1 418 899 2762",
    "sg:postcode":"G0L 2Y0",
    "sg:province":"QC",
    "sg:tags":[
        "village"
    ],
    "wof:name":"St Eusebe Municipalite Office",
    "wof:placetype":"venue"
},
  "geometry": {"coordinates":[-68.9082107544,47.5526695251],"type":"Point"}
}