{
  "type": "Feature",
  "properties": {
    "iso:country":"CA",
    "sg:address":"7070 Rte Marie-Victorin",
    "sg:city":"Lotbiniere",
    "sg:classifiers":[
        {
            "category":"Home & Garden",
            "subcategory":"Furniture",
            "type":"Retail Goods"
        }
    ],
    "sg:phone":"+1 418 796 3168",
    "sg:postcode":"G0S 1S0",
    "sg:province":"QC",
    "sg:tags":[
        "equipment",
        "kitchen",
        "cabinet"
    ],
    "wof:name":"Abel Armoire",
    "wof:placetype":"venue"
},
  "geometry": {"coordinates":[-71.8675079346,46.6637916565],"type":"Point"}
}