{
  "type": "Feature",
  "properties": {
    "addr:full":"476 Holland Ave # 205 Ottawa ON K1Y 0Z5",
    "addr:housenumber":"476",
    "addr:postcode":"k1y 0z5",
    "addr:street":"Holland Ave # 205",
    "iso:country":"CA",
    "sg:address":"476 Holland Ave # 205",
    "sg:city":"Ottawa",
    "sg:classifiers":[
        {
            "category":"Banks & Credit Unions",
            "subcategory":"Bank",
            "type":"Services"
        }
    ],
    "sg:phone":"+1 613 715 9141",
    "sg:postcode":"K1Y 0Z5",
    "sg:province":"ON",
    "sg:tags":[
        "loan"
    ],
    "wof:name":"Quick Pay Day Advance",
    "wof:placetype":"venue"
},
  "geometry": {"coordinates":[-75.7263717651,45.3901138306],"type":"Point"}
}