{
  "type": "Feature",
  "properties": {
    "addr:full":"314 Rue Pasteur Boisbriand QC J7G 2B5",
    "addr:housenumber":"314",
    "addr:postcode":"j7g 2b5",
    "addr:street":"Rue Pasteur",
    "iso:country":"CA",
    "sg:address":"314 Rue Pasteur",
    "sg:city":"Boisbriand",
    "sg:classifiers":[
        {
            "category":"Manufacturing",
            "subcategory":"Glass & Minerals",
            "type":"Manufacturing & Wholesale Goods"
        }
    ],
    "sg:phone":"+1 450 433 6630",
    "sg:postcode":"J7G 2B5",
    "sg:province":"QC",
    "sg:tags":[
        "equipment",
        "dental",
        "scientific",
        "apparatus",
        "supply"
    ],
    "wof:name":"Safeguard Par Richard Collette",
    "wof:placetype":"venue"
},
  "geometry": {"coordinates":[-73.82275390620001,45.6203079224],"type":"Point"}
}