{
  "type": "Feature",
  "properties": {
    "addr:full":"11 Clifton Rd Port Hope ON L1A 2B4",
    "addr:housenumber":"11",
    "addr:postcode":"l1a 2b4",
    "addr:street":"Clifton Rd",
    "iso:country":"CA",
    "sg:address":"11 Clifton Rd",
    "sg:city":"Port Hope",
    "sg:classifiers":[
        {
            "category":"Building & Trades",
            "subcategory":"Construction",
            "type":"Services"
        }
    ],
    "sg:phone":"+1 905 885 5121",
    "sg:postcode":"L1A 2B4",
    "sg:province":"ON",
    "sg:tags":[
        "designer",
        "dealer",
        "pool",
        "swimming"
    ],
    "wof:name":"Unique Pool Supplies",
    "wof:placetype":"venue"
},
  "geometry": {"coordinates":[-78.3162994385,43.9549484253],"type":"Point"}
}