{
  "type": "Feature",
  "properties": {
    "iso:country":"CA",
    "sg:address":"96 Georgeson Bay",
    "sg:city":"Galiano",
    "sg:classifiers":[
        {
            "category":"Restaurant",
            "type":"Food & Drink"
        }
    ],
    "sg:phone":"+1 250 539 2800",
    "sg:postcode":"V0N 1P0",
    "sg:province":"BC",
    "wof:name":"Market Cafe",
    "wof:placetype":"venue"
},
  "geometry": {"coordinates":[-123.346428,48.890541],"type":"Point"}
}