{
  "type": "Feature",
  "properties": {
    "addr:full":"8720 204 St Langley BC V1M 2Y5",
    "addr:housenumber":"8720",
    "addr:postcode":"v1m 2y5",
    "addr:street":"204 St",
    "iso:country":"CA",
    "sg:address":"8720 204 St",
    "sg:city":"Langley",
    "sg:classifiers":[
        {
            "category":"Restaurant",
            "type":"Food & Drink"
        }
    ],
    "sg:phone":"+1 604 888 4211",
    "sg:postcode":"V1M 2Y5",
    "sg:province":"BC",
    "wof:name":"Ricky's All Day Grill",
    "wof:placetype":"venue"
},
  "geometry": {"coordinates":[-122.65675354,49.161857605],"type":"Point"}
}