{
  "type": "Feature",
  "properties": {
    "addr:full":"3499 Boul Saint-Laurent Montreal QC H2X 2T6",
    "addr:housenumber":"3499",
    "addr:postcode":"h2x 2t6",
    "addr:street":"Boul Saint-Laurent",
    "iso:country":"CA",
    "sg:address":"3499 Boul Saint-Laurent",
    "sg:city":"Montreal",
    "sg:classifiers":[
        {
            "category":"Wholesale",
            "subcategory":"Apparel",
            "type":"Manufacturing & Wholesale Goods"
        }
    ],
    "sg:phone":"+1 514 844 6722",
    "sg:postcode":"H2X 2T6",
    "sg:province":"QC",
    "sg:tags":[
        "infant",
        "wear"
    ],
    "wof:name":"Distributeur J-G Parenteau",
    "wof:placetype":"venue"
},
  "geometry": {"coordinates":[-73.57100699999999,45.513374],"type":"Point"}
}