{
  "type": "Feature",
  "properties": {
    "addr:full":"611 Simcoe St Niagara on the Lake ON L0S 1J0",
    "addr:housenumber":"611",
    "addr:postcode":"l0s 1j0",
    "addr:street":"Simcoe St;On",
    "iso:country":"CA",
    "sg:address":"611 Simcoe St",
    "sg:city":"Niagara on the Lake",
    "sg:classifiers":[
        {
            "category":"Building & Trades",
            "subcategory":"Construction",
            "type":"Services"
        }
    ],
    "sg:phone":"+1 905 468 5234",
    "sg:postcode":"L0S 1J0",
    "sg:province":"ON",
    "sg:tags":[
        "contractor"
    ],
    "wof:name":"Prelude Homes Ltd",
    "wof:placetype":"venue"
},
  "geometry": {"coordinates":[-79.085632,43.248333],"type":"Point"}
}