{
  "type": "Feature",
  "properties": {
    "addr:full":"169 Adelaide St N London ON N6B 3G9",
    "addr:housenumber":"169",
    "addr:postcode":"n6b 3g9",
    "addr:street":"Adelaide St N",
    "iso:country":"CA",
    "sg:address":"169 Adelaide St N",
    "sg:city":"London",
    "sg:classifiers":[
        {
            "category":"Shopping",
            "subcategory":"Bicycles & Sporting Goods",
            "type":"Retail Goods"
        }
    ],
    "sg:phone":"+1 519 432 0880",
    "sg:postcode":"N6B 3G9",
    "sg:province":"ON",
    "sg:tags":[
        "bait",
        "fishing"
    ],
    "wof:name":"Archies Stop N Go Live Bait",
    "wof:placetype":"venue"
},
  "geometry": {"coordinates":[-81.2284698486,42.9812660217],"type":"Point"}
}