{
  "type": "Feature",
  "properties": {
    "addr:full":"45774 Kipp Ave Chilliwack BC V2P 1Y4",
    "addr:postcode":"45774;v2p 1y4",
    "addr:street":"Kipp Ave",
    "iso:country":"CA",
    "sg:address":"45774 Kipp Ave",
    "sg:city":"Chilliwack",
    "sg:classifiers":[
        {
            "category":"Shopping",
            "subcategory":"Used Merchandise",
            "type":"Retail Goods"
        }
    ],
    "sg:phone":"+1 604 792 3731",
    "sg:postcode":"V2P 1Y4",
    "sg:province":"BC",
    "sg:tags":[
        "shop",
        "thrift"
    ],
    "wof:name":"Mennonite Central Committee BC",
    "wof:placetype":"venue"
},
  "geometry": {"coordinates":[-121.95704650899999,49.170425415],"type":"Point"}
}