{
  "type": "Feature",
  "properties": {
    "addr:full":"275 Main St Antigonish NS B2G 2C3",
    "addr:housenumber":"275",
    "addr:postcode":"b2g 2c3",
    "addr:street":"Main St",
    "iso:country":"CA",
    "sg:address":"275 Main St",
    "sg:city":"Antigonish",
    "sg:classifiers":[
        {
            "category":"Shopping",
            "subcategory":"Clothing, Apparel, & Fashions",
            "type":"Retail Goods"
        }
    ],
    "sg:phone":"+1 902 863 4114",
    "sg:postcode":"B2G 2C3",
    "sg:province":"NS",
    "wof:name":"D D Mac Donald Ltd",
    "wof:placetype":"venue"
},
  "geometry": {"coordinates":[-61.9919815063,45.6223449707],"type":"Point"}
}