{
  "type": "Feature",
  "properties": {
    "addr:full":"319 First Ave W Brooks AB T1R 1C4",
    "addr:housenumber":"319",
    "addr:postcode":"ab t1r 1c4",
    "addr:street":"First Ave W Brooks",
    "iso:country":"CA",
    "sg:address":"319 First Ave W",
    "sg:city":"Brooks",
    "sg:classifiers":[
        {
            "category":"Health Services",
            "subcategory":"Doctor",
            "type":"Services"
        }
    ],
    "sg:phone":"+1 403 362 3799",
    "sg:postcode":"T1R 1C4",
    "sg:province":"AB",
    "sg:tags":[
        "dentist"
    ],
    "wof:name":"Vaughan, Struan DDS",
    "wof:placetype":"venue"
},
  "geometry": {"coordinates":[-111.900299,50.564442],"type":"Point"}
}