{
  "type": "Feature",
  "properties": {
    "addr:full":"Richmond BC V6X 2W8",
    "addr:postcode":"v6x 2w8",
    "iso:country":"CA",
    "sg:city":"Richmond",
    "sg:classifiers":[
        {
            "category":"Wholesale",
            "subcategory":"Electrical",
            "type":"Manufacturing & Wholesale Goods"
        }
    ],
    "sg:phone":"+1 604 270 9538",
    "sg:postcode":"V6X 2W8",
    "sg:province":"BC",
    "sg:tags":[
        "instrument",
        "electronic"
    ],
    "wof:name":"Intertechnology Inc",
    "wof:placetype":"venue"
},
  "geometry": {"coordinates":[-123.10748291,49.186466217],"type":"Point"}
}