{
  "type": "Feature",
  "properties": {
    "iso:country":"CA",
    "sg:address":"475 Av Dumont",
    "sg:city":"Dorval",
    "sg:classifiers":[
        {
            "category":"Professional",
            "subcategory":"Computer Services",
            "type":"Services"
        }
    ],
    "sg:phone":"+1 514 636 6655",
    "sg:postcode":"H9S 5W2",
    "sg:province":"QC",
    "sg:tags":[
        "information",
        "consultant",
        "system",
        "software"
    ],
    "wof:name":"Brain Bank Inc",
    "wof:placetype":"venue"
},
  "geometry": {"coordinates":[-73.7516174316,45.4477424622],"type":"Point"}
}