{
  "type": "Feature",
  "properties": {
    "iso:country":"CA",
    "sg:address":"2398 Haines Rd",
    "sg:city":"Mississauga",
    "sg:classifiers":[
        {
            "category":"Wholesale",
            "subcategory":"Fruits & Vegetables",
            "type":"Manufacturing & Wholesale Goods"
        }
    ],
    "sg:phone":"+1 905 279 8909",
    "sg:postcode":"L4Y 1Y6",
    "sg:province":"ON",
    "wof:name":"Bitarco Wholesale",
    "wof:placetype":"venue"
},
  "geometry": {"coordinates":[-79.5909729004,43.5932350159],"type":"Point"}
}