{
  "type": "Feature",
  "properties": {
    "addr:full":"1409 Drouillard Rd Windsor ON N8Y 2R8",
    "addr:housenumber":"1409",
    "addr:postcode":"n8y 2r8",
    "addr:street":"Drouillard Rd",
    "iso:country":"CA",
    "sg:address":"1409 Drouillard Rd",
    "sg:city":"Windsor",
    "sg:classifiers":[
        {
            "category":"Manufacturing",
            "subcategory":"Printing",
            "type":"Manufacturing & Wholesale Goods"
        }
    ],
    "sg:phone":"+1 519 948 0801",
    "sg:postcode":"N8Y 2R8",
    "sg:province":"ON",
    "sg:tags":[
        "screen"
    ],
    "wof:name":"Hogan's Printing",
    "wof:placetype":"venue"
},
  "geometry": {"coordinates":[-82.9953384399,42.313747406],"type":"Point"}
}