{
  "type": "Feature",
  "properties": {
    "addr:full":"283 Main St Milton NS B0T 1P0",
    "addr:housenumber":"283",
    "addr:postcode":"b0t 1p0",
    "addr:street":"Main St",
    "iso:country":"CA",
    "sg:address":"283 Main St",
    "sg:city":"Milton",
    "sg:classifiers":[
        {
            "category":"Organizations",
            "subcategory":"Professional Association",
            "type":"Services"
        }
    ],
    "sg:phone":"+1 902 354 5816",
    "sg:postcode":"B0T 1P0",
    "sg:province":"NS",
    "sg:tags":[
        "native"
    ],
    "wof:name":"Acadia First Nations",
    "wof:placetype":"venue"
},
  "geometry": {"coordinates":[-64.751656,44.060863],"type":"Point"}
}