{
  "type": "Feature",
  "properties": {
    "iso:country":"CA",
    "sg:city":"Victoria",
    "sg:classifiers":[
        {
            "category":"Professional",
            "subcategory":"Accounting & Tax Preparation",
            "type":"Services"
        }
    ],
    "sg:phone":"+1 250 383 0337",
    "sg:postcode":"V8T 4E1",
    "sg:province":"BC",
    "sg:tags":[
        "accountant"
    ],
    "wof:name":"Collins & CO",
    "wof:placetype":"venue"
},
  "geometry": {"coordinates":[-123.358032227,48.4364547729],"type":"Point"}
}