{
  "type": "Feature",
  "properties": {
    "addr:full":"28 Rayborn Cres # 103 St Albert AB T8N 5B7",
    "addr:housenumber":"28",
    "addr:postcode":"t8n 5b7",
    "addr:street":"Rayborn Cres # 103",
    "iso:country":"CA",
    "sg:address":"28 Rayborn Cres # 103",
    "sg:city":"St Albert",
    "sg:classifiers":[
        {
            "category":"Building & Trades",
            "subcategory":"Electrical",
            "type":"Services"
        }
    ],
    "sg:phone":"+1 780 459 5442",
    "sg:postcode":"T8N 5B7",
    "sg:province":"AB",
    "sg:tags":[
        "electric",
        "contractor"
    ],
    "wof:name":"Sprint Electrical Svc",
    "wof:placetype":"venue"
},
  "geometry": {"coordinates":[-113.64315033,53.6220664978],"type":"Point"}
}