{
  "type": "Feature",
  "properties": {
    "addr:full":"Mcgettigan Blvd Marystown NL A0E 2M0",
    "addr:postcode":"a0e 2m0",
    "addr:street":"Mcgettigan Blvd",
    "iso:country":"CA",
    "sg:address":"Mcgettigan Blvd",
    "sg:city":"Marystown",
    "sg:classifiers":[
        {
            "category":"Shopping",
            "subcategory":"Florist",
            "type":"Retail Goods"
        }
    ],
    "sg:phone":"+1 709 279 3175",
    "sg:postcode":"A0E 2M0",
    "sg:province":"NL",
    "wof:name":"Dominion Stores-the Flower Mkt",
    "wof:placetype":"venue"
},
  "geometry": {"coordinates":[-55.1497650146,47.1787719727],"type":"Point"}
}