{
  "type": "Feature",
  "properties": {
    "iso:country":"CA",
    "sg:address":"Lot 20 Hwy 6",
    "sg:city":"Kenilworth",
    "sg:classifiers":[
        {
            "category":"Organizations",
            "subcategory":"Religious Organization",
            "type":"Services"
        }
    ],
    "sg:phone":"+1 519 848 3210",
    "sg:postcode":"N0G 2E0",
    "sg:province":"ON",
    "sg:tags":[
        "church"
    ],
    "wof:name":"Sacred Heart Church",
    "wof:placetype":"venue"
},
  "geometry": {"coordinates":[-80.630241394,43.8981208801],"type":"Point"}
}