{
  "type": "Feature",
  "properties": {
    "addr:full":"10 Bennett Cres Fort Mcmurray AB T9H 1H5",
    "addr:housenumber":"10",
    "addr:postcode":"t9h 1h5",
    "addr:street":"Bennett Cres",
    "iso:country":"CA",
    "sg:address":"10 Bennett Cres",
    "sg:city":"Fort Mcmurray",
    "sg:classifiers":[
        {
            "category":"Professional",
            "subcategory":"Management & Consulting",
            "type":"Services"
        }
    ],
    "sg:phone":"+1 780 791 1414",
    "sg:postcode":"T9H 1H5",
    "sg:province":"AB",
    "sg:tags":[
        "break",
        "coffee",
        "supply"
    ],
    "wof:name":"Coffee Connection",
    "wof:placetype":"venue"
},
  "geometry": {"coordinates":[-111.352554,56.714626],"type":"Point"}
}