{
  "type": "Feature",
  "properties": {
    "iso:country":"CA",
    "sg:address":"31260 South Fraser Way",
    "sg:city":"Abbotsford",
    "sg:classifiers":[
        {
            "category":"Wholesale",
            "subcategory":"Machinery & Supplies",
            "type":"Manufacturing & Wholesale Goods"
        }
    ],
    "sg:phone":"+1 604 850 7313",
    "sg:postcode":"V2T 6L5",
    "sg:province":"BC",
    "sg:tags":[
        "equipment",
        "hydraulic",
        "contractor"
    ],
    "wof:name":"Bobcat Country Sales Inc",
    "wof:placetype":"venue"
},
  "geometry": {"coordinates":[-122.358704,49.047276],"type":"Point"}
}