{
  "type": "Feature",
  "properties": {
    "addr:full":"2115 Athol St Regina SK S4T 3E8",
    "addr:housenumber":"2115",
    "addr:postcode":"s4t 3e8",
    "addr:street":"Athol St",
    "iso:country":"CA",
    "sg:address":"2115 Athol St",
    "sg:city":"Regina",
    "sg:classifiers":[
        {
            "category":"Social Services",
            "subcategory":"Child Care",
            "type":"Services"
        }
    ],
    "sg:phone":"+1 306 757 3744",
    "sg:postcode":"S4T 3E8",
    "sg:province":"SK",
    "sg:tags":[
        "kindergarten",
        "academic",
        "school"
    ],
    "wof:name":"Early Learning Ctr",
    "wof:placetype":"venue"
},
  "geometry": {"coordinates":[-104.62809753400001,50.4448318481],"type":"Point"}
}