{
  "type": "Feature",
  "properties": {
    "addr:full":"333 Av Avro Pointe-Claire QC H9R 5W3",
    "addr:postcode":"h9r 5w3",
    "addr:street":"333 Av Avro",
    "iso:country":"CA",
    "sg:address":"333 Av Avro",
    "sg:city":"Pointe-Claire",
    "sg:classifiers":[
        {
            "category":"Wholesale",
            "subcategory":"Groceries",
            "type":"Manufacturing & Wholesale Goods"
        }
    ],
    "sg:phone":"+1 514 428 1000",
    "sg:postcode":"H9R 5W3",
    "sg:province":"QC",
    "sg:tags":[
        "beverage"
    ],
    "wof:name":"Breuvages Cott",
    "wof:placetype":"venue"
},
  "geometry": {"coordinates":[-73.7972488403,45.468914032],"type":"Point"}
}