{
  "type": "Feature",
  "properties": {
    "addr:full":"3340 Lawrence Ave E Scarborough ON M1H 1A7",
    "addr:housenumber":"3340",
    "addr:postcode":"m1h 1a7",
    "addr:street":"Lawrence Ave E",
    "iso:country":"CA",
    "sg:address":"3340 Lawrence Ave E",
    "sg:city":"Scarborough",
    "sg:classifiers":[
        {
            "category":"Retail",
            "subcategory":"Self-service Laundry",
            "type":"Services"
        }
    ],
    "sg:phone":"+1 416 289 7514",
    "sg:postcode":"M1H 1A7",
    "sg:province":"ON",
    "wof:name":"Cedargreen Coin Laundry",
    "wof:placetype":"venue"
},
  "geometry": {"coordinates":[-79.2343826294,43.7580337524],"type":"Point"}
}