{
  "type": "Feature",
  "properties": {
    "iso:country":"CA",
    "sg:address":"4310 12 St SE",
    "sg:city":"Calgary",
    "sg:classifiers":[
        {
            "category":"Wholesale",
            "subcategory":"Machinery & Supplies",
            "type":"Manufacturing & Wholesale Goods"
        }
    ],
    "sg:phone":"+1 403 203 7550",
    "sg:postcode":"T2G 3H9",
    "sg:province":"AB",
    "sg:tags":[
        "equipment",
        "irrigation",
        "system",
        "sprinkler"
    ],
    "wof:name":"Consolidated Turf Equipment",
    "wof:placetype":"venue"
},
  "geometry": {"coordinates":[-114.033866882,51.0157585144],"type":"Point"}
}