{
  "type": "Feature",
  "properties": {
    "iso:country":"CA",
    "sg:city":"Toronto",
    "sg:classifiers":[
        {
            "category":"Insurance",
            "subcategory":"Insurance Agent",
            "type":"Services"
        }
    ],
    "sg:phone":"+1 416 486 0951",
    "sg:postcode":"M4P 3A1",
    "sg:province":"ON",
    "wof:name":"Canadian Insurance Brokers Inc",
    "wof:placetype":"venue"
},
  "geometry": {"coordinates":[-79.398147583,43.7066497803],"type":"Point"}
}