{
  "type": "Feature",
  "properties": {
    "addr:full":"6256 Yonge St North York ON M2M 3X4",
    "addr:housenumber":"6256",
    "addr:postcode":"m2m 3x4",
    "addr:street":"Yonge St",
    "iso:country":"CA",
    "sg:address":"6256 Yonge St",
    "sg:city":"North York",
    "sg:classifiers":[
        {
            "category":"Shopping",
            "type":"Retail Goods"
        }
    ],
    "sg:phone":"+1 416 226 3122",
    "sg:postcode":"M2M 3X4",
    "sg:province":"ON",
    "sg:tags":[
        "cosmetic",
        "perfume"
    ],
    "wof:name":"Caryl Baker Visage Cosmetics",
    "wof:placetype":"venue"
},
  "geometry": {"coordinates":[-79.419456,43.794903],"type":"Point"}
}