{
  "type": "Feature",
  "properties": {
    "addr:full":"6 Antares Dr # 205 Nepean ON K2E 8A9",
    "addr:housenumber":"6;205",
    "addr:postcode":"k2e 8a9",
    "addr:street":"Antares Dr #",
    "iso:country":"CA",
    "sg:address":"6 Antares Dr # 205",
    "sg:city":"Nepean",
    "sg:classifiers":[
        {
            "category":"Banks & Credit Unions",
            "subcategory":"Investment Brokerage",
            "type":"Services"
        }
    ],
    "sg:phone":"+1 613 727 8821",
    "sg:postcode":"K2E 8A9",
    "sg:province":"ON",
    "sg:tags":[
        "consultant",
        "planning",
        "financial"
    ],
    "wof:name":"Dundee Securities",
    "wof:placetype":"venue"
},
  "geometry": {"coordinates":[-75.70594,45.335701],"type":"Point"}
}