{
  "type": "Feature",
  "properties": {
    "addr:full":"5503 Black Gold Dr Leduc AB T9E 8C4",
    "addr:housenumber":"5503",
    "addr:postcode":"t9e 8c4",
    "addr:street":"Black Gold Dr",
    "iso:country":"CA",
    "sg:address":"5503 Black Gold Dr",
    "sg:city":"Leduc",
    "sg:classifiers":[
        {
            "category":"Organizations",
            "subcategory":"Religious Organization",
            "type":"Services"
        }
    ],
    "sg:phone":"+1 780 986 1055",
    "sg:postcode":"T9E 8C4",
    "sg:province":"AB",
    "sg:tags":[
        "church"
    ],
    "wof:name":"Leduc Alliance Church",
    "wof:placetype":"venue"
},
  "geometry": {"coordinates":[-113.563812,53.257931],"type":"Point"}
}