{
  "type": "Feature",
  "properties": {
    "addr:full":"30 Waterloo St S Stratford ON N5A 4A6",
    "addr:housenumber":"30",
    "addr:postcode":"n5a 4a6",
    "addr:street":"Waterloo St S",
    "iso:country":"CA",
    "sg:address":"30 Waterloo St S",
    "sg:city":"Stratford",
    "sg:classifiers":[
        {
            "category":"Professional",
            "subcategory":"Lawyer & Legal Services",
            "type":"Services"
        }
    ],
    "sg:phone":"+1 519 271 7602",
    "sg:postcode":"N5A 4A6",
    "sg:province":"ON",
    "sg:tags":[
        "attorney"
    ],
    "wof:name":"Burdett, Gerry",
    "wof:placetype":"venue"
},
  "geometry": {"coordinates":[-80.979912,43.372581],"type":"Point"}
}