{
  "type": "Feature",
  "properties": {
    "addr:full":"Orangeville ON L9W 2Z1",
    "addr:postcode":"l9w 2z1",
    "iso:country":"CA",
    "sg:city":"Orangeville",
    "sg:classifiers":[
        {
            "category":"Recreation",
            "type":"Entertainment"
        }
    ],
    "sg:phone":"+1 519 942 8181",
    "sg:postcode":"L9W 2Z1",
    "sg:province":"ON",
    "sg:tags":[
        "bingo",
        "game"
    ],
    "wof:name":"Orangeville & District Bingo",
    "wof:placetype":"venue"
},
  "geometry": {"coordinates":[-80.09349060060001,43.9201164246],"type":"Point"}
}