{
  "type": "Feature",
  "properties": {
    "addr:full":"695 Townline Rd N Courtice ON L1E 2J4",
    "addr:housenumber":"695",
    "addr:postcode":"l1e 2j4",
    "addr:street":"Townline Rd N Courtice",
    "iso:country":"CA",
    "sg:address":"695 Townline Rd N",
    "sg:city":"Courtice",
    "sg:classifiers":[
        {
            "category":"Retail",
            "subcategory":"Portrait Studio",
            "type":"Services"
        }
    ],
    "sg:phone":"+1 905 576 9526",
    "sg:postcode":"L1E 2J4",
    "sg:province":"ON",
    "sg:tags":[
        "photographer"
    ],
    "wof:name":"Magic Portraits",
    "wof:placetype":"venue"
},
  "geometry": {"coordinates":[-78.8217468262,43.9261131287],"type":"Point"}
}