{
  "type": "Feature",
  "properties": {
    "addr:full":"750 Goldstream Ave Victoria BC V9B 2X3",
    "addr:housenumber":"750",
    "addr:postcode":"v9b 2x3",
    "addr:street":"Goldstream Ave",
    "iso:country":"CA",
    "sg:address":"750 Goldstream Ave",
    "sg:city":"Victoria",
    "sg:classifiers":[
        {
            "category":"Professional",
            "subcategory":"Lawyer & Legal Services",
            "type":"Services"
        }
    ],
    "sg:phone":"+1 250 391 9044",
    "sg:postcode":"V9B 2X3",
    "sg:province":"BC",
    "sg:tags":[
        "attorney"
    ],
    "wof:name":"Lyon, David N",
    "wof:placetype":"venue"
},
  "geometry": {"coordinates":[-123.497802734,48.4484977722],"type":"Point"}
}