{
  "type": "Feature",
  "properties": {
    "addr:full":"400 Boul Champlain S Alma QC G8B 3N8",
    "addr:housenumber":"400",
    "addr:postcode":"g8b 3n8",
    "addr:street":"Boul Champlain S",
    "iso:country":"CA",
    "sg:address":"400 Boul Champlain S",
    "sg:city":"Alma",
    "sg:classifiers":[
        {
            "category":"Organizations",
            "subcategory":"Labor Organization",
            "type":"Services"
        }
    ],
    "sg:phone":"+1 418 668 2142",
    "sg:postcode":"G8B 3N8",
    "sg:province":"QC",
    "wof:name":"Syndicat Des Employes DE LA",
    "wof:placetype":"venue"
},
  "geometry": {"coordinates":[-71.664597,48.547798],"type":"Point"}
}