{
  "type": "Feature",
  "properties": {
    "addr:full":"519 Alliford Bay Sandspit BC V0T 1T0",
    "addr:housenumber":"519",
    "addr:postcode":"v0t 1t0",
    "addr:street":"Alliford Bay",
    "iso:country":"CA",
    "sg:address":"519 Alliford Bay",
    "sg:city":"Sandspit",
    "sg:classifiers":[
        {
            "category":"Utilities",
            "subcategory":"Refuse",
            "type":"Services"
        }
    ],
    "sg:phone":"+1 250 637 2292",
    "sg:postcode":"V0T 1T0",
    "sg:province":"BC",
    "sg:tags":[
        "garbage",
        "collection"
    ],
    "wof:name":"Hecate Junk-It",
    "wof:placetype":"venue"
},
  "geometry": {"coordinates":[-131.838348,53.238579],"type":"Point"}
}