{
  "type": "Feature",
  "properties": {
    "addr:full":"2 Rue Rubin Victoriaville QC G6P 8T7",
    "addr:housenumber":"2",
    "addr:postcode":"g6p 8t7",
    "addr:street":"Rue Rubin",
    "iso:country":"CA",
    "sg:address":"2 Rue Rubin",
    "sg:city":"Victoriaville",
    "sg:classifiers":[
        {
            "category":"Food & Beverages",
            "subcategory":"Groceries & Convenience Stores",
            "type":"Retail Goods"
        }
    ],
    "sg:phone":"+1 819 752 7292",
    "sg:postcode":"G6P 8T7",
    "sg:province":"QC",
    "wof:name":"Depanneur Du Parc",
    "wof:placetype":"venue"
},
  "geometry": {"coordinates":[-71.9664382935,46.0670166016],"type":"Point"}
}