{
  "type": "Feature",
  "properties": {
    "addr:full":"535 131 Rte Joliette QC J6E 7Y8",
    "addr:housenumber":"535 131",
    "addr:postcode":"j6e 7y8",
    "addr:street":"Rte Joliette",
    "iso:country":"CA",
    "sg:address":"535 131 Rte",
    "sg:city":"Joliette",
    "sg:classifiers":[
        {
            "category":"Travel",
            "subcategory":"Hotels & Motels",
            "type":"Entertainment"
        }
    ],
    "sg:phone":"+1 450 759 6780",
    "sg:postcode":"J6E 7Y8",
    "sg:province":"QC",
    "wof:name":"Motel Lanaudiere",
    "wof:placetype":"venue"
},
  "geometry": {"coordinates":[-73.4419555664,46.0235710144],"type":"Point"}
}