{
  "type": "Feature",
  "properties": {
    "addr:full":"Vancouver BC V6R 2B7",
    "addr:postcode":"v6r 2b7",
    "iso:country":"CA",
    "sg:city":"Vancouver",
    "sg:classifiers":[
        {
            "category":"Museum",
            "type":"Entertainment"
        }
    ],
    "sg:phone":"+1 604 732 1305",
    "sg:postcode":"V6R 2B7",
    "sg:province":"BC",
    "sg:tags":[
        "organization",
        "arts",
        "information"
    ],
    "wof:name":"Acoustic Connection",
    "wof:placetype":"venue"
},
  "geometry": {"coordinates":[-123.18440200000001,49.26416],"type":"Point"}
}