{
  "type": "Feature",
  "properties": {
    "addr:full":"3736 Laval St Lac-Megantic QC G6B 1A4",
    "addr:housenumber":"3736",
    "addr:postcode":"g6b 1a4",
    "addr:street":"Laval St",
    "iso:country":"CA",
    "sg:address":"3736 Laval St",
    "sg:city":"Lac-Megantic",
    "sg:classifiers":[
        {
            "category":"Retail",
            "subcategory":"Auto Repair",
            "type":"Services"
        }
    ],
    "sg:phone":"+1 819 583 5950",
    "sg:postcode":"G6B 1A4",
    "sg:province":"QC",
    "sg:tags":[
        "body",
        "automobile",
        "painting"
    ],
    "wof:name":"Laval Nord Autos Inc",
    "wof:placetype":"venue"
},
  "geometry": {"coordinates":[-70.9023590088,45.5879173279],"type":"Point"}
}