{
  "type": "Feature",
  "properties": {
    "addr:full":"North York ON M3J 3J2",
    "addr:postcode":"m3j 3j2",
    "iso:country":"CA",
    "sg:city":"North York",
    "sg:classifiers":[
        {
            "category":"Manufacturing",
            "subcategory":"Tools & Machinery",
            "type":"Manufacturing & Wholesale Goods"
        }
    ],
    "sg:phone":"+1 416 667 9914",
    "sg:postcode":"M3J 3J2",
    "sg:province":"ON",
    "sg:tags":[
        "transformer"
    ],
    "wof:name":"Plitron Manufacturing Inc",
    "wof:placetype":"venue"
},
  "geometry": {"coordinates":[-79.47520400000001,43.783878],"type":"Point"}
}