{
  "type": "Feature",
  "properties": {
    "addr:full":"124 Rue Principale Saint-Esprit QC J0K 2L0",
    "addr:housenumber":"124",
    "addr:postcode":"j0k 2l0",
    "addr:street":"Rue Principale",
    "iso:country":"CA",
    "sg:address":"124 Rue Principale",
    "sg:city":"Saint-Esprit",
    "sg:classifiers":[
        {
            "category":"Professional",
            "subcategory":"Business Services",
            "type":"Services"
        }
    ],
    "sg:phone":"+1 450 839 2999",
    "sg:postcode":"J0K 2L0",
    "sg:province":"QC",
    "sg:tags":[
        "grocer",
        "liquidator"
    ],
    "wof:name":"Alimentation Cag Inc",
    "wof:placetype":"venue"
},
  "geometry": {"coordinates":[-73.66699199999999,45.904797],"type":"Point"}
}