{
  "type": "Feature",
  "properties": {
    "addr:full":"4913 Argyle St Port Alberni BC V9Y 1V6",
    "addr:housenumber":"4913",
    "addr:postcode":"v9y 1v6",
    "addr:street":"Argyle St",
    "iso:country":"CA",
    "sg:address":"4913 Argyle St",
    "sg:city":"Port Alberni",
    "sg:classifiers":[
        {
            "category":"Organizations",
            "subcategory":"Labor Organization",
            "type":"Services"
        }
    ],
    "sg:phone":"+1 250 724 5021",
    "sg:postcode":"V9Y 1V6",
    "sg:province":"BC",
    "wof:name":"Alberni District Teachers Unio",
    "wof:placetype":"venue"
},
  "geometry": {"coordinates":[-124.806411743,49.2349243164],"type":"Point"}
}