{
  "type": "Feature",
  "properties": {
    "addr:full":"2 Croham Rd York ON M6E 4X8",
    "addr:housenumber":"2",
    "addr:postcode":"m6e 4x8",
    "addr:street":"Croham Rd",
    "iso:country":"CA",
    "sg:address":"2 Croham Rd",
    "sg:city":"York",
    "sg:classifiers":[
        {
            "category":"Farming",
            "subcategory":"Vineyard",
            "type":"Manufacturing & Wholesale Goods"
        }
    ],
    "sg:phone":"+1 416 783 5944",
    "sg:postcode":"M6E 4X8",
    "sg:province":"ON",
    "sg:tags":[
        "equipment",
        "wine",
        "supply"
    ],
    "wof:name":"One Consorzio California Grape",
    "wof:placetype":"venue"
},
  "geometry": {"coordinates":[-79.464127,43.692509],"type":"Point"}
}