{
  "type": "Feature",
  "properties": {
    "addr:full":"1894 Lawrence Ave E Scarborough ON M1R 2Y5",
    "addr:housenumber":"1894",
    "addr:postcode":"m1r 2y5",
    "addr:street":"Lawrence Ave E",
    "iso:country":"CA",
    "sg:address":"1894 Lawrence Ave E",
    "sg:city":"Scarborough",
    "sg:classifiers":[
        {
            "category":"Shopping",
            "subcategory":"Bicycles & Sporting Goods",
            "type":"Retail Goods"
        }
    ],
    "sg:phone":"+1 416 752 3838",
    "sg:postcode":"M1R 2Y5",
    "sg:province":"ON",
    "wof:name":"D'Ornellas Bike Shop Ltd",
    "wof:placetype":"venue"
},
  "geometry": {"coordinates":[-79.301163,43.744137],"type":"Point"}
}