{
  "type": "Feature",
  "properties": {
    "addr:full":"47715 Trans-Canada Hwy Boston Bar BC V0K 1C0",
    "addr:housenumber":"47715",
    "addr:postcode":"v0k 1c0",
    "addr:street":"Trans-Canada Hwy",
    "iso:country":"CA",
    "sg:address":"47715 Trans-Canada Hwy",
    "sg:city":"Boston Bar",
    "sg:classifiers":[
        {
            "category":"Manufacturing",
            "subcategory":"Lumber",
            "type":"Manufacturing & Wholesale Goods"
        }
    ],
    "sg:phone":"+1 604 867 9283",
    "sg:postcode":"V0K 1C0",
    "sg:province":"BC",
    "sg:tags":[
        "company",
        "logging"
    ],
    "wof:name":"May Trucking Ltd",
    "wof:placetype":"venue"
},
  "geometry": {"coordinates":[-121.441948,49.865749],"type":"Point"}
}