{
  "type": "Feature",
  "properties": {
    "addr:full":"1574 Argyle St Halifax NS B3J 2B3",
    "addr:housenumber":"1574",
    "addr:postcode":"ns b3j 2b3",
    "addr:street":"Argyle St",
    "iso:country":"CA",
    "sg:address":"1574 Argyle St",
    "sg:city":"Halifax",
    "sg:classifiers":[
        {
            "category":"Real Estate",
            "subcategory":"Real Estate Agent",
            "type":"Services"
        }
    ],
    "sg:phone":"+1 902 420 0124",
    "sg:postcode":"B3J 2B3",
    "sg:province":"NS",
    "wof:name":"Ventura Realty Ltd",
    "wof:placetype":"venue"
},
  "geometry": {"coordinates":[-63.5741996765,44.6455383301],"type":"Point"}
}