{
  "type": "Feature",
  "properties": {
    "iso:country":"CA",
    "sg:address":"1544 Jane St",
    "sg:city":"North York",
    "sg:classifiers":[
        {
            "category":"Shopping",
            "subcategory":"Discount & Variety Stores",
            "type":"Retail Goods"
        }
    ],
    "sg:phone":"+1 416 241 2111",
    "sg:postcode":"M9N 2R5",
    "sg:province":"ON",
    "wof:name":"Milk Mart & Coffee Donut Shop",
    "wof:placetype":"venue"
},
  "geometry": {"coordinates":[-79.50264,43.69788],"type":"Point"}
}