{
  "type": "Feature",
  "properties": {
    "addr:full":"544 Willowbank Trail Mississauga ON L4W 3K2",
    "addr:housenumber":"544",
    "addr:postcode":"l4w 3k2",
    "addr:street":"Willowbank Trail",
    "iso:country":"CA",
    "sg:address":"544 Willowbank Trail",
    "sg:city":"Mississauga",
    "sg:classifiers":[
        {
            "category":"Arts & Performance",
            "subcategory":"Theater",
            "type":"Entertainment"
        }
    ],
    "sg:phone":"+1 905 275 4744",
    "sg:postcode":"L4W 3K2",
    "sg:province":"ON",
    "sg:tags":[
        "music"
    ],
    "wof:name":"Debi Sander Walker Entertain",
    "wof:placetype":"venue"
},
  "geometry": {"coordinates":[-79.61835499999999,43.611252],"type":"Point"}
}