{
  "type": "Feature",
  "properties": {
    "iso:country":"CA",
    "sg:address":"544 Willowbank Trail",
    "sg:city":"Mississauga",
    "sg:classifiers":[
        {
            "category":"Arts & Performance",
            "subcategory":"Theater",
            "type":"Entertainment"
        }
    ],
    "sg:phone":"+1 905 275 4744",
    "sg:postcode":"L4W 3K2",
    "sg:province":"ON",
    "sg:tags":[
        "music"
    ],
    "wof:name":"Debi Sander Walker Entertain",
    "wof:placetype":"venue"
},
  "geometry": {"coordinates":[-79.618355,43.611252],"type":"Point"}
}