{
  "type": "Feature",
  "properties": {
    "addr:full":"Fredericton NB E3A 8V4",
    "addr:postcode":"e3a 8v4",
    "iso:country":"CA",
    "sg:city":"Fredericton",
    "sg:classifiers":[
        {
            "category":"Banks & Credit Unions",
            "subcategory":"Bank",
            "type":"Services"
        }
    ],
    "sg:phone":"+1 506 450 2300",
    "sg:postcode":"E3A 8V4",
    "sg:province":"NB",
    "wof:name":"Royal Bank Financial Group",
    "wof:placetype":"venue"
},
  "geometry": {"coordinates":[-66.65033,45.992214],"type":"Point"}
}