{
  "type": "Feature",
  "properties": {
    "addr:full":"83 Clarence St W Port Colborne ON L3K 3G2",
    "addr:housenumber":"83",
    "addr:postcode":"l3k 3g2",
    "addr:street":"Clarence St W",
    "iso:country":"CA",
    "sg:address":"83 Clarence St W",
    "sg:city":"Port Colborne",
    "sg:classifiers":[
        {
            "category":"Shopping",
            "subcategory":"Optical Goods",
            "type":"Retail Goods"
        }
    ],
    "sg:phone":"+1 905 835 8688",
    "sg:postcode":"L3K 3G2",
    "sg:province":"ON",
    "sg:tags":[
        "optician"
    ],
    "wof:name":"Port Optical Family Eye Care",
    "wof:placetype":"venue"
},
  "geometry": {"coordinates":[-79.2533416748,42.8862495422],"type":"Point"}
}