{
  "type": "Feature",
  "properties": {
    "iso:country":"CA",
    "sg:address":"17 Rue Saint-Antoine # A",
    "sg:city":"Metabetchouan-Lac-A-LA-Croix",
    "sg:classifiers":[
        {
            "category":"Shopping",
            "subcategory":"Tobacco",
            "type":"Retail Goods"
        }
    ],
    "sg:phone":"+1 418 349 3447",
    "sg:postcode":"G8G 1H2",
    "sg:province":"QC",
    "sg:tags":[
        "cigarette",
        "cigar",
        "dealer"
    ],
    "wof:name":"Tabagie Metabetchouan Enr",
    "wof:placetype":"venue"
},
  "geometry": {"coordinates":[-71.8726348877,48.4256973267],"type":"Point"}
}