{
  "type": "Feature",
  "properties": {
    "addr:full":"180 Riverside Dr Fredericton NB E3A 6P8",
    "addr:housenumber":"180",
    "addr:postcode":"e3a 6p8",
    "addr:street":"Riverside Dr",
    "iso:country":"CA",
    "sg:address":"180 Riverside Dr",
    "sg:city":"Fredericton",
    "sg:classifiers":[
        {
            "category":"Autos & Motor Vehicles",
            "subcategory":"Automobile Sales",
            "type":"Retail Goods"
        }
    ],
    "sg:phone":"+1 506 472 5525",
    "sg:postcode":"E3A 6P8",
    "sg:province":"NB",
    "sg:tags":[
        "car",
        "dealer"
    ],
    "wof:name":"Crown Auto Sales Ltd",
    "wof:placetype":"venue"
},
  "geometry": {"coordinates":[-66.62061309809999,45.9473457336],"type":"Point"}
}