{
  "type": "Feature",
  "properties": {
    "addr:full":"25 Carlson Crt Etobicoke ON M9W 6A2",
    "addr:housenumber":"25",
    "addr:postcode":"m9w 6a2",
    "addr:street":"Carlson Crt",
    "iso:country":"CA",
    "sg:address":"25 Carlson Crt",
    "sg:city":"Etobicoke",
    "sg:classifiers":[
        {
            "category":"Restaurant",
            "type":"Food & Drink"
        }
    ],
    "sg:phone":"+1 416 798 4333",
    "sg:postcode":"M9W 6A2",
    "sg:province":"ON",
    "wof:name":"Biftheque Steak House",
    "wof:placetype":"venue"
},
  "geometry": {"coordinates":[-79.586395,43.689461],"type":"Point"}
}