{
  "type": "Feature",
  "properties": {
    "addr:full":"3917 51st Ave W Vancouver BC V6N 3V9",
    "addr:housenumber":"3917",
    "addr:postcode":"v6n 3v9",
    "addr:street":"51St Ave W",
    "iso:country":"CA",
    "sg:address":"3917 51st Ave W",
    "sg:city":"Vancouver",
    "sg:classifiers":[
        {
            "category":"Shopping",
            "type":"Retail Goods"
        }
    ],
    "sg:phone":"+1 604 266 7374",
    "sg:postcode":"V6N 3V9",
    "sg:province":"BC",
    "sg:tags":[
        "art",
        "gallery",
        "dealer"
    ],
    "wof:name":"Coast Salish Arts",
    "wof:placetype":"venue"
},
  "geometry": {"coordinates":[-123.19347399999999,49.225899],"type":"Point"}
}