{
  "type": "Feature",
  "properties": {
    "addr:full":"Whitesand Indian Reserve Armstrong Station ON P0T 1A0",
    "addr:postcode":"p0t 1a0",
    "iso:country":"CA",
    "sg:address":"Whitesand Indian Reserve",
    "sg:city":"Armstrong Station",
    "sg:classifiers":[
        {
            "category":"Autos & Motor Vehicles",
            "subcategory":"Fuel & Gas Station",
            "type":"Retail Goods"
        }
    ],
    "sg:phone":"+1 807 583 2161",
    "sg:postcode":"P0T 1A0",
    "sg:province":"ON",
    "sg:tags":[
        "grocer",
        "oil"
    ],
    "wof:name":"Henry & Yvonne's Gas Bar",
    "wof:placetype":"venue"
},
  "geometry": {"coordinates":[-89.038963,50.303928],"type":"Point"}
}