{
  "type": "Feature",
  "properties": {
    "addr:full":"Victoriaville QC G6P 5T3",
    "addr:postcode":"g6p 5t3",
    "iso:country":"CA",
    "sg:city":"Victoriaville",
    "sg:classifiers":[
        {
            "category":"Shopping",
            "type":"Retail Goods"
        }
    ],
    "sg:phone":"+1 819 357 8866",
    "sg:postcode":"G6P 5T3",
    "sg:province":"QC",
    "sg:tags":[
        "hearing",
        "equipment",
        "supply",
        "impaired",
        "aid"
    ],
    "wof:name":"Audioprothesiste Desilets M-J",
    "wof:placetype":"venue"
},
  "geometry": {"coordinates":[-71.9307098389,46.0489883423],"type":"Point"}
}