{
  "type": "Feature",
  "properties": {
    "addr:full":"856 Bank St Ottawa ON K1S 3W3",
    "addr:housenumber":"856",
    "addr:postcode":"k1s 3w3",
    "addr:street":"Bank St",
    "iso:country":"CA",
    "sg:address":"856 Bank St",
    "sg:city":"Ottawa",
    "sg:classifiers":[
        {
            "category":"Food & Beverages",
            "subcategory":"Specialty",
            "type":"Retail Goods"
        }
    ],
    "sg:phone":"+1 613 236 3028",
    "sg:postcode":"K1S 3W3",
    "sg:province":"ON",
    "sg:tags":[
        "lounge",
        "health",
        "diet",
        "cocktail"
    ],
    "wof:name":"Booster Juice",
    "wof:placetype":"venue"
},
  "geometry": {"coordinates":[-75.68763,45.401405],"type":"Point"}
}