{
  "type": "Feature",
  "properties": {
    "addr:full":"180 Rue Lucien Thibodeau Portneuf QC G0A 2Y0",
    "addr:housenumber":"180",
    "addr:postcode":"g0a 2y0",
    "addr:street":"Rue Lucien Thibodeau",
    "iso:country":"CA",
    "sg:address":"180 Rue Lucien Thibodeau",
    "sg:city":"Portneuf",
    "sg:classifiers":[
        {
            "category":"Manufacturing",
            "subcategory":"Metals",
            "type":"Manufacturing & Wholesale Goods"
        }
    ],
    "sg:phone":"+1 418 286 6060",
    "sg:postcode":"G0A 2Y0",
    "sg:province":"QC",
    "sg:tags":[
        "solder",
        "mechanical",
        "contractor"
    ],
    "wof:name":"Mecanarc",
    "wof:placetype":"venue"
},
  "geometry": {"coordinates":[-71.893547,46.694984],"type":"Point"}
}