{
  "type": "Feature",
  "properties": {
    "addr:full":"426 Rte Begin # C Saint-Anselme QC G0R 2N0",
    "addr:housenumber":"426",
    "addr:postcode":"g0r 2n0",
    "addr:street":"Rte Begin # C Saint-Anselme",
    "iso:country":"CA",
    "sg:address":"426 Rte Begin # C",
    "sg:city":"Saint-Anselme",
    "sg:classifiers":[
        {
            "category":"Retail",
            "subcategory":"Auto Repair",
            "type":"Services"
        }
    ],
    "sg:phone":"+1 418 885 8130",
    "sg:postcode":"G0R 2N0",
    "sg:province":"QC",
    "sg:tags":[
        "repairing",
        "automobile"
    ],
    "wof:name":"Garage Gaetan Boissonneault",
    "wof:placetype":"venue"
},
  "geometry": {"coordinates":[-70.992706,46.643078],"type":"Point"}
}