{
  "type": "Feature",
  "properties": {
    "iso:country":"CA",
    "sg:address":"7084 Kingsway",
    "sg:city":"Burnaby",
    "sg:classifiers":[
        {
            "category":"Restaurant",
            "type":"Food & Drink"
        }
    ],
    "sg:phone":"+1 604 521 1651",
    "sg:postcode":"V5E 1E7",
    "sg:province":"BC",
    "sg:tags":[
        "pizza"
    ],
    "wof:name":"Donair Pizza",
    "wof:placetype":"venue"
},
  "geometry": {"coordinates":[-122.957923889,49.2183113098],"type":"Point"}
}