{
  "type": "Feature",
  "properties": {
    "addr:full":"23 Pemberton Rd Richmond Hill ON L4C 3T5",
    "addr:housenumber":"23",
    "addr:postcode":"l4c 3t5",
    "addr:street":"Pemberton Rd",
    "iso:country":"CA",
    "sg:address":"23 Pemberton Rd",
    "sg:city":"Richmond Hill",
    "sg:classifiers":[
        {
            "category":"Professional",
            "subcategory":"Advertising",
            "type":"Services"
        }
    ],
    "sg:phone":"+1 905 884 7004",
    "sg:postcode":"L4C 3T5",
    "sg:province":"ON",
    "sg:tags":[
        "counselor"
    ],
    "wof:name":"Buckley Creative",
    "wof:placetype":"venue"
},
  "geometry": {"coordinates":[-79.4490280151,43.8594894409],"type":"Point"}
}