{
  "type": "Feature",
  "properties": {
    "addr:full":"395 Rue Main Gatineau QC J8P 5K6",
    "addr:housenumber":"395",
    "addr:postcode":"j8p 5k6",
    "addr:street":"Rue Main",
    "iso:country":"CA",
    "sg:address":"395 Rue Main",
    "sg:city":"Gatineau",
    "sg:classifiers":[
        {
            "category":"Retail",
            "subcategory":"Laundry & Dry Cleaning",
            "type":"Services"
        }
    ],
    "sg:phone":"+1 819 669 0241",
    "sg:postcode":"J8P 5K6",
    "sg:province":"QC",
    "sg:tags":[
        "cleaners"
    ],
    "wof:name":"Chatel Cleaners Inc",
    "wof:placetype":"venue"
},
  "geometry": {"coordinates":[-75.65213799999999,45.491615],"type":"Point"}
}