{
  "type": "Feature",
  "properties": {
    "addr:full":"541 Rue DE L'Harricana Amos QC J9T 2P8",
    "addr:housenumber":"541",
    "addr:postcode":"j9t 2p8",
    "addr:street":"Rue De L'Harricana Amos",
    "iso:country":"CA",
    "sg:address":"541 Rue DE L'Harricana",
    "sg:city":"Amos",
    "sg:classifiers":[
        {
            "category":"Autos & Motor Vehicles",
            "subcategory":"Automobile Sales",
            "type":"Retail Goods"
        }
    ],
    "sg:phone":"+1 819 732 3331",
    "sg:postcode":"J9T 2P8",
    "sg:province":"QC",
    "sg:tags":[
        "truck"
    ],
    "wof:name":"Equipement Amos Ltee",
    "wof:placetype":"venue"
},
  "geometry": {"coordinates":[-78.116928,48.58778],"type":"Point"}
}