{
  "type": "Feature",
  "properties": {
    "addr:full":"179 Foord St Stellarton NS B0K 1S0",
    "addr:housenumber":"179",
    "addr:postcode":"b0k 1s0",
    "addr:street":"Foord St",
    "iso:country":"CA",
    "sg:address":"179 Foord St",
    "sg:city":"Stellarton",
    "sg:classifiers":[
        {
            "category":"Professional",
            "subcategory":"Lawyer & Legal Services",
            "type":"Services"
        }
    ],
    "sg:phone":"+1 902 752 1575",
    "sg:postcode":"B0K 1S0",
    "sg:province":"NS",
    "sg:tags":[
        "attorney"
    ],
    "wof:name":"Ray E O'Blenis Law Office Inc",
    "wof:placetype":"venue"
},
  "geometry": {"coordinates":[-62.659859,45.559391],"type":"Point"}
}