{
  "type": "Feature",
  "properties": {
    "addr:full":"RR 5 STN Main Lindsay ON K9V 4R5",
    "addr:postcode":"k9v 4r5",
    "addr:street":"Rr 5 Stn",
    "iso:country":"CA",
    "sg:address":"RR 5 STN Main",
    "sg:city":"Lindsay",
    "sg:classifiers":[
        {
            "category":"Freight",
            "type":"Transportation"
        }
    ],
    "sg:phone":"+1 705 799 6391",
    "sg:postcode":"K9V 4R5",
    "sg:province":"ON",
    "sg:tags":[
        "commercial",
        "storage"
    ],
    "wof:name":"Economy Storage",
    "wof:placetype":"venue"
},
  "geometry": {"coordinates":[-78.740067,44.354286],"type":"Point"}
}