{
  "type": "Feature",
  "properties": {
    "addr:full":"52 Hwy Ave Fox Creek AB T0H 1P0",
    "addr:postcode":"t0h 1p0",
    "addr:street":"52 Hwy Ave",
    "iso:country":"CA",
    "sg:address":"52 Hwy Ave",
    "sg:city":"Fox Creek",
    "sg:classifiers":[
        {
            "category":"Autos & Motor Vehicles",
            "subcategory":"Fuel & Gas Station",
            "type":"Retail Goods"
        }
    ],
    "sg:phone":"+1 780 622 3233",
    "sg:postcode":"T0H 1P0",
    "sg:province":"AB",
    "sg:tags":[
        "oil"
    ],
    "wof:name":"Fox Creek Petro-Canada Svc",
    "wof:placetype":"venue"
},
  "geometry": {"coordinates":[-116.809898,54.413643],"type":"Point"}
}