{
  "type": "Feature",
  "properties": {
    "addr:full":"1000 Waterloo St Port Elgin ON N0H 2C2",
    "addr:housenumber":"1000",
    "addr:postcode":"n0h 2c2",
    "addr:street":"Waterloo St",
    "iso:country":"CA",
    "sg:address":"1000 Waterloo St",
    "sg:city":"Port Elgin",
    "sg:classifiers":[
        {
            "category":"Education",
            "subcategory":"School",
            "type":"Public Place"
        }
    ],
    "sg:phone":"+1 519 832 9077",
    "sg:postcode":"N0H 2C2",
    "sg:province":"ON",
    "wof:name":"Northport Elementary School",
    "wof:placetype":"venue"
},
  "geometry": {"coordinates":[-81.384254,44.445625],"type":"Point"}
}