{
  "type": "Feature",
  "properties": {
    "addr:full":"1 Thorncliffe Park Dr East York ON M4H 1G9",
    "addr:housenumber":"1",
    "addr:postcode":"m4h 1g9",
    "addr:street":"Thorncliffe Park Dr",
    "iso:country":"CA",
    "sg:address":"1 Thorncliffe Park Dr",
    "sg:city":"East York",
    "sg:classifiers":[
        {
            "category":"Professional",
            "subcategory":"Art Services",
            "type":"Services"
        }
    ],
    "sg:phone":"+1 416 423 2898",
    "sg:postcode":"M4H 1G9",
    "sg:province":"ON",
    "sg:tags":[
        "graphic",
        "designer"
    ],
    "wof:name":"Dominion Graphics",
    "wof:placetype":"venue"
},
  "geometry": {"coordinates":[-79.351196,43.705612],"type":"Point"}
}