{
  "type": "Feature",
  "properties": {
    "addr:full":"523 Yonge St Toronto ON M4Y 1Y3",
    "addr:housenumber":"523",
    "addr:postcode":"m4y 1y3",
    "addr:street":"Yonge St",
    "iso:country":"CA",
    "sg:address":"523 Yonge St",
    "sg:city":"Toronto",
    "sg:classifiers":[
        {
            "category":"Shopping",
            "subcategory":"Clothing, Apparel, & Fashions",
            "type":"Retail Goods"
        }
    ],
    "sg:phone":"+1 416 961 2232",
    "sg:postcode":"M4Y 1Y3",
    "sg:province":"ON",
    "sg:tags":[
        "furnishing"
    ],
    "wof:name":"Nyc Toronto",
    "wof:placetype":"venue"
},
  "geometry": {"coordinates":[-79.3839416504,43.6637878418],"type":"Point"}
}