{
  "type": "Feature",
  "properties": {
    "iso:country":"CA",
    "sg:address":"2165 Rue DE Grandville",
    "sg:city":"Quebec",
    "sg:classifiers":[
        {
            "category":"Professional",
            "subcategory":"Accounting & Tax Preparation",
            "type":"Services"
        }
    ],
    "sg:phone":"+1 418 661 7893",
    "sg:postcode":"G1J 1V8",
    "sg:province":"QC",
    "sg:tags":[
        "accountant"
    ],
    "wof:name":"Beaubien, Bernard",
    "wof:placetype":"venue"
},
  "geometry": {"coordinates":[-71.222443,46.841774],"type":"Point"}
}