{
  "type": "Feature",
  "properties": {
    "addr:full":"227 Lakewood Blvd Winnipeg MB R2J 2N2",
    "addr:housenumber":"227",
    "addr:postcode":"r2j 2n2",
    "addr:street":"Lakewood Blvd",
    "iso:country":"CA",
    "sg:address":"227 Lakewood Blvd",
    "sg:city":"Winnipeg",
    "sg:classifiers":[
        {
            "category":"Organizations",
            "subcategory":"Religious Organization",
            "type":"Services"
        }
    ],
    "sg:phone":"+1 204 255 0861",
    "sg:postcode":"R2J 2N2",
    "sg:province":"MB",
    "sg:tags":[
        "church"
    ],
    "wof:name":"Jehovah's Witnesses Glenlawn",
    "wof:placetype":"venue"
},
  "geometry": {"coordinates":[-97.0768127441,49.8480796814],"type":"Point"}
}