{
  "type": "Feature",
  "properties": {
    "addr:full":"Saskatoon SK S7K 2V9",
    "addr:postcode":"s7k 2v9",
    "iso:country":"CA",
    "sg:city":"Saskatoon",
    "sg:classifiers":[
        {
            "category":"Health Services",
            "subcategory":"Medical Lab",
            "type":"Services"
        }
    ],
    "sg:phone":"+1 306 934 2977",
    "sg:postcode":"S7K 2V9",
    "sg:province":"SK",
    "sg:tags":[
        "laboratory",
        "optical"
    ],
    "wof:name":"Prairie Ophthalmics Inc",
    "wof:placetype":"venue"
},
  "geometry": {"coordinates":[-106.652114868,52.1430358887],"type":"Point"}
}