{
  "type": "Feature",
  "properties": {
    "addr:full":"1246 Upper James St Hamilton ON L9C 3B1",
    "addr:housenumber":"1246",
    "addr:postcode":"l9c 3b1",
    "addr:street":"Upper James St",
    "iso:country":"CA",
    "sg:address":"1246 Upper James St",
    "sg:city":"Hamilton",
    "sg:classifiers":[
        {
            "category":"Home & Garden",
            "subcategory":"Building Materials",
            "type":"Retail Goods"
        }
    ],
    "sg:phone":"+1 905 389 2255",
    "sg:postcode":"L9C 3B1",
    "sg:province":"ON",
    "sg:tags":[
        "paint"
    ],
    "wof:name":"Glidden Paints",
    "wof:placetype":"venue"
},
  "geometry": {"coordinates":[-79.887871,43.214546],"type":"Point"}
}