{
  "type": "Feature",
  "properties": {
    "addr:full":"Picton ON K0K 2T0",
    "addr:postcode":"k0k 2t0",
    "iso:country":"CA",
    "sg:city":"Picton",
    "sg:classifiers":[
        {
            "category":"Organizations",
            "subcategory":"Religious Organization",
            "type":"Services"
        }
    ],
    "sg:phone":"+1 613 476 2457",
    "sg:postcode":"K0K 2T0",
    "sg:province":"ON",
    "sg:tags":[
        "church"
    ],
    "wof:name":"Free Methodist Church",
    "wof:placetype":"venue"
},
  "geometry": {"coordinates":[-77.136909,44.014263],"type":"Point"}
}