{
  "type": "Feature",
  "properties": {
    "addr:full":"6550 Rue Fontaine Rock Forest QC J1N 2S6",
    "addr:housenumber":"6550",
    "addr:postcode":"j1n 2s6",
    "addr:street":"Rue Fontaine",
    "iso:country":"CA",
    "sg:address":"6550 Rue Fontaine",
    "sg:city":"Rock Forest",
    "sg:classifiers":[
        {
            "category":"Personal",
            "subcategory":"Beauty Salon",
            "type":"Services"
        }
    ],
    "sg:phone":"+1 819 864 7711",
    "sg:postcode":"J1N 2S6",
    "sg:province":"QC",
    "wof:name":"Salon Aline",
    "wof:placetype":"venue"
},
  "geometry": {"coordinates":[-71.98970031739999,45.3497581482],"type":"Point"}
}