{
  "type": "Feature",
  "properties": {
    "addr:full":"3970 Lakeshore Rd Kelowna BC V1W 1V5",
    "addr:housenumber":"3970",
    "addr:postcode":"v1w 1v5",
    "addr:street":"Lakeshore Rd",
    "iso:country":"CA",
    "sg:address":"3970 Lakeshore Rd",
    "sg:city":"Kelowna",
    "sg:classifiers":[
        {
            "category":"Health Services",
            "subcategory":"Doctor",
            "type":"Services"
        }
    ],
    "sg:phone":"+1 250 764 8878",
    "sg:postcode":"V1W 1V5",
    "sg:province":"BC",
    "sg:tags":[
        "physician",
        "surgeon"
    ],
    "wof:name":"Hopp, Marilyn MD",
    "wof:placetype":"venue"
},
  "geometry": {"coordinates":[-119.48870100000001,49.840778],"type":"Point"}
}