{
  "type": "Feature",
  "properties": {
    "iso:country":"CA",
    "sg:address":"1984 Regent St",
    "sg:city":"Sudbury",
    "sg:classifiers":[
        {
            "category":"Health Services",
            "subcategory":"Doctor",
            "type":"Services"
        }
    ],
    "sg:phone":"+1 705 522 0220",
    "sg:postcode":"P3E 5S1",
    "sg:province":"ON",
    "sg:tags":[
        "dentist"
    ],
    "wof:name":"Delorey, Ian DDS",
    "wof:placetype":"venue"
},
  "geometry": {"coordinates":[-81.0011520386,46.4510765076],"type":"Point"}
}