{
  "type": "Feature",
  "properties": {
    "addr:full":"404 Laurier Ave E Ottawa ON K1N 6R2",
    "addr:housenumber":"404",
    "addr:postcode":"k1n 6r2",
    "addr:street":"Laurier Ave E",
    "iso:country":"CA",
    "sg:address":"404 Laurier Ave E",
    "sg:city":"Ottawa",
    "sg:classifiers":[
        {
            "category":"Real Estate",
            "subcategory":"Real Estate Operator",
            "type":"Services"
        }
    ],
    "sg:phone":"+1 613 234 2004",
    "sg:postcode":"K1N 6R2",
    "sg:province":"ON",
    "sg:tags":[
        "apartment"
    ],
    "wof:name":"Andrex Holdings Ltd",
    "wof:placetype":"venue"
},
  "geometry": {"coordinates":[-75.676208,45.428055],"type":"Point"}
}