{
  "type": "Feature",
  "properties": {
    "iso:country":"CA",
    "sg:address":"133 Morrell St",
    "sg:city":"Brantford",
    "sg:classifiers":[
        {
            "category":"Retail",
            "subcategory":"Auto Repair",
            "type":"Services"
        }
    ],
    "sg:phone":"+1 519 753 1313",
    "sg:postcode":"N3T 4J9",
    "sg:province":"ON",
    "sg:tags":[
        "repairing",
        "automobile",
        "tire"
    ],
    "wof:name":"Morrell Tire & Auto",
    "wof:placetype":"venue"
},
  "geometry": {"coordinates":[-80.2874450684,43.1455192566],"type":"Point"}
}