{
  "type": "Feature",
  "properties": {
    "addr:full":"780 Boul Lebourgneuf #10 Quebec QC G2J 1S1",
    "addr:housenumber":"780;10",
    "addr:postcode":"g2j 1s1",
    "addr:street":"Boul Lebourgneuf #",
    "iso:country":"CA",
    "sg:address":"780 Boul Lebourgneuf #10",
    "sg:city":"Quebec",
    "sg:classifiers":[
        {
            "category":"Health Services",
            "subcategory":"Nursing And Care Facility",
            "type":"Services"
        }
    ],
    "sg:phone":"+1 418 623 5333",
    "sg:postcode":"G2J 1S1",
    "sg:province":"QC",
    "sg:tags":[
        "house",
        "retirement",
        "retreat",
        "community",
        "home"
    ],
    "wof:name":"Jardin Lebourgneuf",
    "wof:placetype":"venue"
},
  "geometry": {"coordinates":[-71.28106699999999,46.842323],"type":"Point"}
}