{
  "type": "Feature",
  "properties": {
    "addr:full":"1791 Boul Des Laurentides Laval QC H7M 2P7",
    "addr:housenumber":"1791",
    "addr:postcode":"h7m 2p7",
    "addr:street":"Boul Des Laurentides",
    "iso:country":"CA",
    "sg:address":"1791 Boul Des Laurentides",
    "sg:city":"Laval",
    "sg:classifiers":[
        {
            "category":"Health Services",
            "subcategory":"Doctor",
            "type":"Services"
        }
    ],
    "sg:phone":"+1 450 663 8300",
    "sg:postcode":"H7M 2P7",
    "sg:province":"QC",
    "sg:tags":[
        "clinic"
    ],
    "wof:name":"Clinique Medicale DE Vimont",
    "wof:placetype":"venue"
},
  "geometry": {"coordinates":[-73.724808,45.599785],"type":"Point"}
}