{
  "type": "Feature",
  "properties": {
    "addr:full":"10417 51 Ave NW Edmonton AB T6H 0K4",
    "addr:housenumber":"10417",
    "addr:postcode":"t6h 0k4",
    "addr:street":"51 Ave Nw",
    "iso:country":"CA",
    "sg:address":"10417 51 Ave NW",
    "sg:city":"Edmonton",
    "sg:classifiers":[
        {
            "category":"Restaurant",
            "type":"Food & Drink"
        }
    ],
    "sg:phone":"+1 780 413 0088",
    "sg:postcode":"T6H 0K4",
    "sg:province":"AB",
    "wof:name":"Lemongrass Cafe",
    "wof:placetype":"venue"
},
  "geometry": {"coordinates":[-113.498627,53.488007],"type":"Point"}
}