{
  "type": "Feature",
  "properties": {
    "addr:full":"2746 Kingsway Vancouver BC V5R 5H5",
    "addr:housenumber":"2746",
    "addr:postcode":"v5r 5h5",
    "addr:street":"Kingsway",
    "iso:country":"CA",
    "sg:address":"2746 Kingsway",
    "sg:city":"Vancouver",
    "sg:classifiers":[
        {
            "category":"Personal",
            "subcategory":"Beauty Salon",
            "type":"Services"
        }
    ],
    "sg:phone":"+1 604 433 8992",
    "sg:postcode":"V5R 5H5",
    "sg:province":"BC",
    "wof:name":"Lin's Hair Beauty Salon",
    "wof:placetype":"venue"
},
  "geometry": {"coordinates":[-123.04920199999999,49.23761],"type":"Point"}
}