{
  "type": "Feature",
  "properties": {
    "iso:country":"CA",
    "sg:address":"2606 Alliance St",
    "sg:city":"Abbotsford",
    "sg:classifiers":[
        {
            "category":"Education",
            "subcategory":"School",
            "type":"Public Place"
        }
    ],
    "sg:phone":"+1 604 859 7820",
    "sg:postcode":"V2S 3J8",
    "sg:province":"BC",
    "wof:name":"Abbotsford Continuing Ed",
    "wof:placetype":"venue"
},
  "geometry": {"coordinates":[-122.302696228,49.0493354797],"type":"Point"}
}