{
  "type": "Feature",
  "properties": {
    "addr:full":"Abbotsford BC V2S 4J8",
    "addr:postcode":"v2s 4j8",
    "iso:country":"CA",
    "sg:city":"Abbotsford",
    "sg:classifiers":[
        {
            "category":"Wholesale",
            "subcategory":"Machinery & Supplies",
            "type":"Manufacturing & Wholesale Goods"
        }
    ],
    "sg:phone":"+1 604 870 2800",
    "sg:postcode":"V2S 4J8",
    "sg:province":"BC",
    "sg:tags":[
        "equipment",
        "welding"
    ],
    "wof:name":"Air Liquide Canada Inc",
    "wof:placetype":"venue"
},
  "geometry": {"coordinates":[-122.272522,49.034306],"type":"Point"}
}