{
  "type": "Feature",
  "properties": {
    "addr:full":"122 Talbot St S Essex ON N8M 1B4",
    "addr:housenumber":"122",
    "addr:postcode":"n8m 1b4",
    "addr:street":"Talbot St S",
    "iso:country":"CA",
    "sg:address":"122 Talbot St S",
    "sg:city":"Essex",
    "sg:classifiers":[
        {
            "category":"Health Services",
            "subcategory":"Nursing And Care Facility",
            "type":"Services"
        }
    ],
    "sg:phone":"+1 519 776 6922",
    "sg:postcode":"N8M 1B4",
    "sg:province":"ON",
    "sg:tags":[
        "home",
        "rest"
    ],
    "wof:name":"Essex Manor",
    "wof:placetype":"venue"
},
  "geometry": {"coordinates":[-82.8168258667,42.1703033447],"type":"Point"}
}