{
  "type": "Feature",
  "properties": {
    "iso:country":"CA",
    "sg:city":"Beauport",
    "sg:classifiers":[
        {
            "category":"Retail",
            "subcategory":"Auto Repair",
            "type":"Services"
        }
    ],
    "sg:phone":"+1 418 667 2324",
    "sg:postcode":"G1C 1A4",
    "sg:province":"QC",
    "sg:tags":[
        "repairing",
        "automobile"
    ],
    "wof:name":"Garage Lorenzo Dumont Inc",
    "wof:placetype":"venue"
},
  "geometry": {"coordinates":[-71.1931381226,46.8592414856],"type":"Point"}
}