{
  "type": "Feature",
  "properties": {
    "addr:full":"250 Rue Duvernay Beloeil QC J3G 2M2",
    "addr:housenumber":"250",
    "addr:postcode":"j3g 2m2",
    "addr:street":"Rue Duvernay",
    "iso:country":"CA",
    "sg:address":"250 Rue Duvernay",
    "sg:city":"Beloeil",
    "sg:classifiers":[
        {
            "category":"Shopping",
            "subcategory":"Shoes",
            "type":"Retail Goods"
        }
    ],
    "sg:phone":"+1 450 446 4175",
    "sg:postcode":"J3G 2M2",
    "sg:province":"QC",
    "wof:name":"Chaussures En Liberte Inc",
    "wof:placetype":"venue"
},
  "geometry": {"coordinates":[-73.207275,45.563812],"type":"Point"}
}