{
  "type": "Feature",
  "properties": {
    "addr:full":"15 York St Ottawa ON K1N 5S7",
    "addr:housenumber":"15",
    "addr:postcode":"k1n 5s7",
    "addr:street":"York St",
    "iso:country":"CA",
    "sg:address":"15 York St",
    "sg:city":"Ottawa",
    "sg:classifiers":[
        {
            "category":"Travel",
            "subcategory":"Campground",
            "type":"Entertainment"
        }
    ],
    "sg:phone":"+1 613 234 4137",
    "sg:postcode":"K1N 5S7",
    "sg:province":"ON",
    "sg:tags":[
        "camp"
    ],
    "wof:name":"Actua",
    "wof:placetype":"venue"
},
  "geometry": {"coordinates":[-75.694480896,45.4277496338],"type":"Point"}
}