{
  "type": "Feature",
  "properties": {
    "addr:full":"Maple Ridge BC V2X 0Z2",
    "addr:postcode":"v2x 0z2",
    "iso:country":"CA",
    "sg:city":"Maple Ridge",
    "sg:classifiers":[
        {
            "category":"Education",
            "subcategory":"Dance Studio",
            "type":"Public Place"
        }
    ],
    "sg:phone":"+1 604 465 6681",
    "sg:postcode":"V2X 0Z2",
    "sg:province":"BC",
    "sg:tags":[
        "instruction",
        "dancing"
    ],
    "wof:name":"Centre Stage Dance",
    "wof:placetype":"venue"
},
  "geometry": {"coordinates":[-122.605827331,49.2168464661],"type":"Point"}
}