{
  "type": "Feature",
  "properties": {
    "addr:full":"216 Av DE LA Cathedrale Rimouski QC G5L 5J2",
    "addr:postcode":"g5l 5j2",
    "addr:street":"216 Av De La Cathedrale",
    "iso:country":"CA",
    "sg:address":"216 Av DE LA Cathedrale",
    "sg:city":"Rimouski",
    "sg:classifiers":[
        {
            "category":"Health Services",
            "subcategory":"Doctor",
            "type":"Services"
        }
    ],
    "sg:phone":"+1 418 723 0181",
    "sg:postcode":"G5L 5J2",
    "sg:province":"QC",
    "sg:tags":[
        "physician",
        "surgeon"
    ],
    "wof:name":"Lavoie, Gilles MD",
    "wof:placetype":"venue"
},
  "geometry": {"coordinates":[-68.5241775513,48.4491691589],"type":"Point"}
}