{
  "type": "Feature",
  "properties": {
    "addr:full":"785 Wonderland Rd S #4 London ON N6K 1M6",
    "addr:housenumber":"785",
    "addr:postcode":"n6k 1m6",
    "addr:street":"Wonderland Rd S # 4",
    "iso:country":"CA",
    "sg:address":"785 Wonderland Rd S #4",
    "sg:city":"London",
    "sg:classifiers":[
        {
            "category":"Restaurant",
            "type":"Food & Drink"
        }
    ],
    "sg:phone":"+1 519 471 9571",
    "sg:postcode":"N6K 1M6",
    "sg:province":"ON",
    "wof:name":"Taco Bell",
    "wof:placetype":"venue"
},
  "geometry": {"coordinates":[-81.2895736694,42.9488182068],"type":"Point"}
}