{
  "type": "Feature",
  "properties": {
    "addr:full":"60 Renfrew Ave W Renfrew ON K7V 2Y1",
    "addr:housenumber":"60",
    "addr:postcode":"k7v 2y1",
    "addr:street":"Renfrew Ave W",
    "iso:country":"CA",
    "sg:address":"60 Renfrew Ave W",
    "sg:city":"Renfrew",
    "sg:classifiers":[
        {
            "category":"Personal",
            "subcategory":"Beauty Salon",
            "type":"Services"
        }
    ],
    "sg:phone":"+1 613 433 9201",
    "sg:postcode":"K7V 2Y1",
    "sg:province":"ON",
    "wof:name":"Bonny's Beauty Parlour",
    "wof:placetype":"venue"
},
  "geometry": {"coordinates":[-76.68454699999999,45.470512],"type":"Point"}
}