{
  "type": "Feature",
  "properties": {
    "addr:full":"Montreal QC H5B 1B2",
    "addr:postcode":"h5b 1b2",
    "iso:country":"CA",
    "sg:city":"Montreal",
    "sg:classifiers":[
        {
            "category":"Shopping",
            "subcategory":"Florist",
            "type":"Retail Goods"
        }
    ],
    "sg:phone":"+1 514 284 6364",
    "sg:postcode":"H5B 1B2",
    "sg:province":"QC",
    "wof:name":"Au Nouveau Jardin Des Fleurs",
    "wof:placetype":"venue"
},
  "geometry": {"coordinates":[-73.5625534058,45.5111656189],"type":"Point"}
}