{
  "type": "Feature",
  "properties": {
    "addr:full":"153 Front St Belleville ON K8N 2Y6",
    "addr:housenumber":"153",
    "addr:postcode":"k8n 2y6",
    "addr:street":"Front St",
    "iso:country":"CA",
    "sg:address":"153 Front St",
    "sg:city":"Belleville",
    "sg:classifiers":[
        {
            "category":"Professional",
            "subcategory":"Computer Services",
            "type":"Services"
        }
    ],
    "sg:phone":"+1 613 968 7137",
    "sg:postcode":"K8N 2Y6",
    "sg:province":"ON",
    "sg:tags":[
        "internet"
    ],
    "wof:name":"Kingston Online Svc",
    "wof:placetype":"venue"
},
  "geometry": {"coordinates":[-77.383194,44.162178],"type":"Point"}
}