{
  "type": "Feature",
  "properties": {
    "addr:full":"1030 Skeena Dr Kelowna BC V1V 2K7",
    "addr:housenumber":"1030",
    "addr:postcode":"v1v 2k7",
    "addr:street":"Skeena Dr",
    "iso:country":"CA",
    "sg:address":"1030 Skeena Dr",
    "sg:city":"Kelowna",
    "sg:classifiers":[
        {
            "category":"Retail",
            "subcategory":"Portrait Studio",
            "type":"Services"
        }
    ],
    "sg:phone":"+1 250 860 0035",
    "sg:postcode":"V1V 2K7",
    "sg:province":"BC",
    "sg:tags":[
        "photographer"
    ],
    "wof:name":"Jerry Geen Photographx",
    "wof:placetype":"venue"
},
  "geometry": {"coordinates":[-119.43367000000001,49.896034],"type":"Point"}
}