{
  "type": "Feature",
  "properties": {
    "addr:full":"Saint-Eustache QC J7R 2J3",
    "addr:postcode":"j7r 2j3",
    "iso:country":"CA",
    "sg:city":"Saint-Eustache",
    "sg:classifiers":[
        {
            "category":"Personal",
            "subcategory":"Beauty Salon",
            "type":"Services"
        }
    ],
    "sg:phone":"+1 450 623 9322",
    "sg:postcode":"J7R 2J3",
    "sg:province":"QC",
    "wof:name":"Coiffure Fuzion",
    "wof:placetype":"venue"
},
  "geometry": {"coordinates":[-73.902512,45.561989],"type":"Point"}
}