{
  "type": "Feature",
  "properties": {
    "addr:full":"8 Hastings St N Bancroft ON K0L 1C0",
    "addr:housenumber":"8",
    "addr:postcode":"k0l 1c0",
    "addr:street":"Hastings St N",
    "iso:country":"CA",
    "sg:address":"8 Hastings St N",
    "sg:city":"Bancroft",
    "sg:classifiers":[
        {
            "category":"Social Services",
            "type":"Services"
        }
    ],
    "sg:phone":"+1 613 332 3807",
    "sg:postcode":"K0L 1C0",
    "sg:province":"ON",
    "sg:tags":[
        "counselor",
        "marriage",
        "family"
    ],
    "wof:name":"Childrens Mental Health Svc",
    "wof:placetype":"venue"
},
  "geometry": {"coordinates":[-77.85348500000001,45.056419],"type":"Point"}
}