{
  "type": "Feature",
  "properties": {
    "addr:full":"220 Broad St E Dunnville ON N1A 1G2",
    "addr:housenumber":"220",
    "addr:postcode":"n1a 1g2",
    "addr:street":"Broad St E",
    "iso:country":"CA",
    "sg:address":"220 Broad St E",
    "sg:city":"Dunnville",
    "sg:classifiers":[
        {
            "category":"Social Services",
            "type":"Services"
        }
    ],
    "sg:phone":"+1 905 774 3005",
    "sg:postcode":"N1A 1G2",
    "sg:province":"ON",
    "sg:tags":[
        "senior",
        "citizen"
    ],
    "wof:name":"Dunnville Senior Support Svc",
    "wof:placetype":"venue"
},
  "geometry": {"coordinates":[-79.6160202026,42.9033851624],"type":"Point"}
}