{
  "type": "Feature",
  "properties": {
    "iso:country":"CA",
    "sg:address":"28 Rosedale Rd",
    "sg:city":"Toronto",
    "sg:classifiers":[
        {
            "category":"Health Services",
            "subcategory":"Doctor",
            "type":"Services"
        }
    ],
    "sg:phone":"+1 416 928 0307",
    "sg:postcode":"M4W 2P3",
    "sg:province":"ON",
    "sg:tags":[
        "physician",
        "surgeon"
    ],
    "wof:name":"Lamon, Richard MD",
    "wof:placetype":"venue"
},
  "geometry": {"coordinates":[-79.3853378296,43.6750793457],"type":"Point"}
}