{
  "type": "Feature",
  "properties": {
    "iso:country":"CA",
    "sg:address":"3960 Boul Des Forges",
    "sg:city":"Trois-Rivieres",
    "sg:classifiers":[
        {
            "category":"Wholesale",
            "subcategory":"Meat",
            "type":"Manufacturing & Wholesale Goods"
        }
    ],
    "sg:phone":"+1 819 372 1710",
    "sg:postcode":"G8Y 1V7",
    "sg:province":"QC",
    "sg:tags":[
        "delicatessen",
        "butchering"
    ],
    "wof:name":"Fines Charcuteries Mado Inc",
    "wof:placetype":"venue"
},
  "geometry": {"coordinates":[-72.58452606199999,46.3554992676],"type":"Point"}
}