{
  "type": "Feature",
  "properties": {
    "addr:full":"500 Mouse Mountain Dr Fraser Lake BC V0J 1S0",
    "addr:housenumber":"500",
    "addr:postcode":"v0j 1s0",
    "addr:street":"Mouse Mountain Dr",
    "iso:country":"CA",
    "sg:address":"500 Mouse Mountain Dr",
    "sg:city":"Fraser Lake",
    "sg:classifiers":[
        {
            "category":"Recreation",
            "type":"Entertainment"
        }
    ],
    "sg:phone":"+1 250 699 8989",
    "sg:postcode":"V0J 1S0",
    "sg:province":"BC",
    "sg:tags":[
        "guide"
    ],
    "wof:name":"Binta Lake Outfitters",
    "wof:placetype":"venue"
},
  "geometry": {"coordinates":[-124.840400696,54.0577888489],"type":"Point"}
}