{
  "type": "Feature",
  "properties": {
    "addr:full":"1850 Ch Royal Saint-Jean-D'Orleans QC G0A 3W0",
    "addr:postcode":"1850;g0a 3w0",
    "addr:street":"Ch Royal Saint-Jean-D'Orleans",
    "iso:country":"CA",
    "sg:address":"1850 Ch Royal",
    "sg:city":"Saint-Jean-D'Orleans",
    "sg:classifiers":[
        {
            "category":"Food & Beverages",
            "subcategory":"Groceries & Convenience Stores",
            "type":"Retail Goods"
        }
    ],
    "sg:phone":"+1 418 829 2230",
    "sg:postcode":"G0A 3W0",
    "sg:province":"QC",
    "sg:tags":[
        "grocer"
    ],
    "wof:name":"Epicerie Letourneau Inc",
    "wof:placetype":"venue"
},
  "geometry": {"coordinates":[-70.8925857544,46.9190254211],"type":"Point"}
}