{
  "type": "Feature",
  "properties": {
    "addr:full":"12345 Av DE LA Misericorde Montreal QC H4J 2E8",
    "addr:housenumber":"12345",
    "addr:postcode":"h4j 2e8",
    "addr:street":"Av De La Misericorde",
    "iso:country":"CA",
    "sg:address":"12345 Av DE LA Misericorde",
    "sg:city":"Montreal",
    "sg:classifiers":[
        {
            "category":"Education",
            "subcategory":"School",
            "type":"Public Place"
        }
    ],
    "sg:phone":"+1 514 331 0850",
    "sg:postcode":"H4J 2E8",
    "sg:province":"QC",
    "wof:name":"Ecole Pasteur",
    "wof:placetype":"venue"
},
  "geometry": {"coordinates":[-73.718658,45.534203],"type":"Point"}
}