{
  "type": "Feature",
  "properties": {
    "addr:full":"2 Halifax St Moncton NB E1C 9P7",
    "addr:housenumber":"2",
    "addr:postcode":"e1c 9p7",
    "addr:street":"Halifax St",
    "iso:country":"CA",
    "sg:address":"2 Halifax St",
    "sg:city":"Moncton",
    "sg:classifiers":[
        {
            "category":"Manufacturing",
            "subcategory":"Signs",
            "type":"Manufacturing & Wholesale Goods"
        }
    ],
    "sg:phone":"+1 506 383 9990",
    "sg:postcode":"E1C 9P7",
    "sg:province":"NB",
    "wof:name":"Signway",
    "wof:placetype":"venue"
},
  "geometry": {"coordinates":[-64.80308532710001,46.0950317383],"type":"Point"}
}