{
  "type": "Feature",
  "properties": {
    "addr:full":"Ebbs Bay Carleton Place ON K7C 3P1",
    "addr:postcode":"k7c 3p1",
    "addr:street":"Ebbs Bay",
    "iso:country":"CA",
    "sg:address":"Ebbs Bay",
    "sg:city":"Carleton Place",
    "sg:classifiers":[
        {
            "category":"Professional",
            "subcategory":"Business Services",
            "type":"Services"
        }
    ],
    "sg:phone":"+1 613 253 5300",
    "sg:postcode":"K7C 3P1",
    "sg:province":"ON",
    "sg:tags":[
        "lecture",
        "bureau",
        "seminar"
    ],
    "wof:name":"Dave Kemp Seminars",
    "wof:placetype":"venue"
},
  "geometry": {"coordinates":[-76.146812,45.14045],"type":"Point"}
}