{
  "type": "Feature",
  "properties": {
    "addr:full":"47 Park St Corner Brook NL A2H 2X1",
    "addr:housenumber":"47",
    "addr:postcode":"a2h 2x1",
    "addr:street":"Park St",
    "iso:country":"CA",
    "sg:address":"47 Park St",
    "sg:city":"Corner Brook",
    "sg:classifiers":[
        {
            "category":"Shopping",
            "subcategory":"Stationery & Office Supplies",
            "type":"Retail Goods"
        }
    ],
    "sg:phone":"+1 709 639 1813",
    "sg:postcode":"A2H 2X1",
    "sg:province":"NL",
    "wof:name":"West Coast Office Products",
    "wof:placetype":"venue"
},
  "geometry": {"coordinates":[-57.942055,48.950851],"type":"Point"}
}