{
  "type": "Feature",
  "properties": {
    "addr:full":"117 Basaltic Rd Concord ON L4K 1G4",
    "addr:housenumber":"117",
    "addr:postcode":"l4k 1g4",
    "addr:street":"Basaltic Rd",
    "iso:country":"CA",
    "sg:address":"117 Basaltic Rd",
    "sg:city":"Concord",
    "sg:classifiers":[
        {
            "category":"Manufacturing",
            "subcategory":"Tools & Machinery",
            "type":"Manufacturing & Wholesale Goods"
        }
    ],
    "sg:phone":"+1 905 669 8622",
    "sg:postcode":"L4K 1G4",
    "sg:province":"ON",
    "sg:tags":[
        "automobile",
        "parts",
        "system",
        "automation",
        "supply"
    ],
    "wof:name":"Tarxien Components Corp",
    "wof:placetype":"venue"
},
  "geometry": {"coordinates":[-79.4972610474,43.823387146],"type":"Point"}
}