{
  "type": "Feature",
  "properties": {
    "iso:country":"CA",
    "sg:address":"3311 Boul Industriel",
    "sg:city":"Laval",
    "sg:classifiers":[
        {
            "category":"Wholesale",
            "subcategory":"Electrical",
            "type":"Manufacturing & Wholesale Goods"
        }
    ],
    "sg:phone":"+1 450 629 8126",
    "sg:postcode":"H7L 4S3",
    "sg:province":"QC",
    "sg:tags":[
        "control"
    ],
    "wof:name":"Standair Inc",
    "wof:placetype":"venue"
},
  "geometry": {"coordinates":[-73.744652,45.592812],"type":"Point"}
}