{
  "type": "Feature",
  "properties": {
    "addr:full":"3316 Keele St North York ON M3M 2H7",
    "addr:housenumber":"3316",
    "addr:postcode":"m3m 2h7",
    "addr:street":"Keele St",
    "iso:country":"CA",
    "sg:address":"3316 Keele St",
    "sg:city":"North York",
    "sg:classifiers":[
        {
            "category":"Shopping",
            "subcategory":"Clothing, Apparel, & Fashions",
            "type":"Retail Goods"
        }
    ],
    "sg:phone":"+1 416 636 4154",
    "sg:postcode":"M3M 2H7",
    "sg:province":"ON",
    "sg:tags":[
        "infant",
        "wear"
    ],
    "wof:name":"Kids Village",
    "wof:placetype":"venue"
},
  "geometry": {"coordinates":[-79.4864273071,43.7442016602],"type":"Point"}
}