{
  "type": "Feature",
  "properties": {
    "addr:full":"5775 Yonge St North York ON M2M 4J1",
    "addr:housenumber":"5775",
    "addr:postcode":"m2m 4j1",
    "addr:street":"Yonge St",
    "iso:country":"CA",
    "sg:address":"5775 Yonge St",
    "sg:city":"North York",
    "sg:classifiers":[
        {
            "category":"Government",
            "subcategory":"Office",
            "type":"Public Place"
        }
    ],
    "sg:phone":"+1 416 326 6700",
    "sg:postcode":"M2M 4J1",
    "sg:province":"ON",
    "wof:name":"Ontario Investigation",
    "wof:placetype":"venue"
},
  "geometry": {"coordinates":[-79.416359,43.783867],"type":"Point"}
}