{
  "type": "Feature",
  "properties": {
    "addr:full":"2 Briarhill Pl London ON N5Y 1P7",
    "addr:housenumber":"2",
    "addr:postcode":"n5y 1p7",
    "addr:street":"Briarhill Pl",
    "iso:country":"CA",
    "sg:address":"2 Briarhill Pl",
    "sg:city":"London",
    "sg:classifiers":[
        {
            "category":"Social Services",
            "subcategory":"Job Training",
            "type":"Services"
        }
    ],
    "sg:phone":"+1 519 455 4609",
    "sg:postcode":"N5Y 1P7",
    "sg:province":"ON",
    "sg:tags":[
        "career",
        "counseling",
        "vocational"
    ],
    "wof:name":"Career Strategy Counselling",
    "wof:placetype":"venue"
},
  "geometry": {"coordinates":[-81.2283782959,43.0256576538],"type":"Point"}
}