{
  "type": "Feature",
  "properties": {
    "addr:full":"4355 Av Marcil Montreal QC H4A 2Z9",
    "addr:housenumber":"4355",
    "addr:postcode":"h4a 2z9",
    "addr:street":"Av Marcil",
    "iso:country":"CA",
    "sg:address":"4355 Av Marcil",
    "sg:city":"Montreal",
    "sg:classifiers":[
        {
            "category":"Health Services",
            "subcategory":"Doctor",
            "type":"Services"
        }
    ],
    "sg:phone":"+1 514 369 0112",
    "sg:postcode":"H4A 2Z9",
    "sg:province":"QC",
    "sg:tags":[
        "dentist"
    ],
    "wof:name":"Centre Dentaire C Bota",
    "wof:placetype":"venue"
},
  "geometry": {"coordinates":[-73.6236419678,45.4762496948],"type":"Point"}
}