{
  "type": "Feature",
  "properties": {
    "addr:full":"240 Dogwood St Parksville BC V9P 1E1",
    "addr:housenumber":"240",
    "addr:postcode":"v9p 1e1",
    "addr:street":"Dogwood St",
    "iso:country":"CA",
    "sg:address":"240 Dogwood St",
    "sg:city":"Parksville",
    "sg:classifiers":[
        {
            "category":"Bars & Pubs",
            "type":"Food & Drink"
        }
    ],
    "sg:phone":"+1 250 248 8333",
    "sg:postcode":"V9P 1E1",
    "sg:province":"BC",
    "wof:name":"Upper Deck Sports Bar",
    "wof:placetype":"venue"
},
  "geometry": {"coordinates":[-124.324203,49.324623],"type":"Point"}
}