{
  "type": "Feature",
  "properties": {
    "addr:full":"Montreal QC H3H 2S2",
    "addr:postcode":"h3h 2s2",
    "iso:country":"CA",
    "sg:city":"Montreal",
    "sg:classifiers":[
        {
            "category":"Professional",
            "subcategory":"Accounting & Tax Preparation",
            "type":"Services"
        }
    ],
    "sg:phone":"+1 514 878 9161",
    "sg:postcode":"H3H 2S2",
    "sg:province":"QC",
    "sg:tags":[
        "bookkeeping",
        "general"
    ],
    "wof:name":"Services Financiers Contact 21",
    "wof:placetype":"venue"
},
  "geometry": {"coordinates":[-73.5528182983,45.5219230652],"type":"Point"}
}