{
  "type": "Feature",
  "properties": {
    "addr:full":"1832 Egremont Dr Hwy 22 Kerwood ON N0M 2B0",
    "addr:housenumber":"1832",
    "addr:postcode":"n0m 2b0",
    "addr:street":"Egremont Dr Hwy 22",
    "iso:country":"CA",
    "sg:address":"1832 Egremont Dr Hwy 22",
    "sg:city":"Kerwood",
    "sg:classifiers":[
        {
            "category":"Retail",
            "subcategory":"Auto Repair",
            "type":"Services"
        }
    ],
    "sg:phone":"+1 519 247 3417",
    "sg:postcode":"N0M 2B0",
    "sg:province":"ON",
    "sg:tags":[
        "repairing",
        "automobile"
    ],
    "wof:name":"Ray Brown Svc Ctr",
    "wof:placetype":"venue"
},
  "geometry": {"coordinates":[-81.74376700000001,42.943893],"type":"Point"}
}