{
  "type": "Feature",
  "properties": {
    "addr:full":"50 Shoreham Lane Halifax NS B3P 2R3",
    "addr:housenumber":"50",
    "addr:postcode":"b3p 2r3",
    "addr:street":"Shoreham Lane",
    "iso:country":"CA",
    "sg:address":"50 Shoreham Lane",
    "sg:city":"Halifax",
    "sg:classifiers":[
        {
            "category":"Health Services",
            "subcategory":"Nursing And Care Facility",
            "type":"Services"
        }
    ],
    "sg:phone":"+1 902 479 1030",
    "sg:postcode":"B3P 2R3",
    "sg:province":"NS",
    "sg:tags":[
        "home",
        "convalescent"
    ],
    "wof:name":"Melville Lodge",
    "wof:placetype":"venue"
},
  "geometry": {"coordinates":[-63.6153755188,44.6291923523],"type":"Point"}
}