{
  "type": "Feature",
  "properties": {
    "addr:full":"208 Rue Dominion Montreal QC H3J 2X1",
    "addr:housenumber":"208",
    "addr:postcode":"h3j 2x1",
    "addr:street":"Rue Dominion",
    "iso:country":"CA",
    "sg:address":"208 Rue Dominion",
    "sg:city":"Montreal",
    "sg:classifiers":[
        {
            "category":"Professional",
            "subcategory":"Computer Services",
            "type":"Services"
        }
    ],
    "sg:phone":"+1 514 212 1155",
    "sg:postcode":"H3J 2X1",
    "sg:province":"QC",
    "sg:tags":[
        "information",
        "system",
        "consultant"
    ],
    "wof:name":"Consultants Bug Off",
    "wof:placetype":"venue"
},
  "geometry": {"coordinates":[-73.572159,45.482929],"type":"Point"}
}