{
  "type": "Feature",
  "properties": {
    "iso:country":"CA",
    "sg:address":"503 Queen St",
    "sg:city":"Fredericton",
    "sg:classifiers":[
        {
            "category":"Organizations",
            "subcategory":"Professional Association",
            "type":"Services"
        }
    ],
    "sg:phone":"+1 506 444 3888",
    "sg:postcode":"E3B 1B8",
    "sg:province":"NB",
    "wof:name":"Centre For Coaching Education",
    "wof:placetype":"venue"
},
  "geometry": {"coordinates":[-66.6405258179,45.962059021],"type":"Point"}
}