{
  "type": "Feature",
  "properties": {
    "addr:full":"Kelowna BC V1W 4S1",
    "addr:postcode":"v1w 4s1",
    "iso:country":"CA",
    "sg:city":"Kelowna",
    "sg:classifiers":[
        {
            "category":"Restaurant",
            "type":"Food & Drink"
        }
    ],
    "sg:phone":"+1 250 862 3177",
    "sg:postcode":"V1W 4S1",
    "sg:province":"BC",
    "wof:name":"Harvest Dining Room",
    "wof:placetype":"venue"
},
  "geometry": {"coordinates":[-119.49659729,49.8868141174],"type":"Point"}
}