{
  "type": "Feature",
  "properties": {
    "addr:full":"404 Rue Principale St-Sauveur-Des-Monts QC J0R 1R0",
    "addr:housenumber":"404",
    "addr:postcode":"j0r 1r0",
    "addr:street":"Rue Principale",
    "iso:country":"CA",
    "sg:address":"404 Rue Principale",
    "sg:city":"St-Sauveur-Des-Monts",
    "sg:classifiers":[
        {
            "category":"Building & Trades",
            "subcategory":"Construction",
            "type":"Services"
        }
    ],
    "sg:phone":"+1 450 227 1934",
    "sg:postcode":"J0R 1R0",
    "sg:province":"QC",
    "sg:tags":[
        "excavating",
        "contractor"
    ],
    "wof:name":"Daniel Filion Excavation Inc",
    "wof:placetype":"venue"
},
  "geometry": {"coordinates":[-74.1640548706,45.8901939392],"type":"Point"}
}