{
  "type": "Feature",
  "properties": {
    "iso:country":"CA",
    "sg:address":"423 169 Rte",
    "sg:city":"Boulanger",
    "sg:classifiers":[
        {
            "category":"Local Transit",
            "type":"Transportation"
        }
    ],
    "sg:phone":"+1 418 276 5833",
    "sg:postcode":"G0W 1E0",
    "sg:province":"QC",
    "sg:tags":[
        "bus",
        "line"
    ],
    "wof:name":"Autobus Paul-Henri Girard",
    "wof:placetype":"venue"
},
  "geometry": {"coordinates":[-72.09493255620001,48.8586502075],"type":"Point"}
}