{
  "type": "Feature",
  "properties": {
    "addr:full":"630 17 Ave SW Calgary AB T2S 0B4",
    "addr:housenumber":"630",
    "addr:postcode":"t2s 0b4",
    "addr:street":"17 Ave Sw",
    "iso:country":"CA",
    "sg:address":"630 17 Ave SW",
    "sg:city":"Calgary",
    "sg:classifiers":[
        {
            "category":"Shopping",
            "subcategory":"Clothing, Apparel, & Fashions",
            "type":"Retail Goods"
        }
    ],
    "sg:phone":"+1 403 245 0304",
    "sg:postcode":"T2S 0B4",
    "sg:province":"AB",
    "wof:name":"R A Clothing",
    "wof:placetype":"venue"
},
  "geometry": {"coordinates":[-114.075767517,51.0379638672],"type":"Point"}
}