{
  "type": "Feature",
  "properties": {
    "addr:full":"297 O'Connell Dr Corner Brook NL A2H 7N6",
    "addr:housenumber":"297",
    "addr:postcode":"a2h 7n6",
    "addr:street":"O'Connell Dr",
    "iso:country":"CA",
    "sg:address":"297 O'Connell Dr",
    "sg:city":"Corner Brook",
    "sg:classifiers":[
        {
            "category":"Shopping",
            "type":"Retail Goods"
        }
    ],
    "sg:phone":"+1 709 634 8678",
    "sg:postcode":"A2H 7N6",
    "sg:province":"NL",
    "sg:tags":[
        "wedding",
        "supply"
    ],
    "wof:name":"Fun & Fashion",
    "wof:placetype":"venue"
},
  "geometry": {"coordinates":[-57.937332,48.943825],"type":"Point"}
}