{
  "type": "Feature",
  "properties": {
    "addr:full":"367 Hwy 94 Corbeil ON P0H 1K0",
    "addr:housenumber":"367",
    "addr:postcode":"p0h 1k0",
    "addr:street":"Hwy 94 Corbeil",
    "iso:country":"CA",
    "sg:address":"367 Hwy 94",
    "sg:city":"Corbeil",
    "sg:classifiers":[
        {
            "category":"Shopping",
            "subcategory":"Catalog Store",
            "type":"Retail Goods"
        }
    ],
    "sg:phone":"+1 705 752 3311",
    "sg:postcode":"P0H 1K0",
    "sg:province":"ON",
    "sg:tags":[
        "mail",
        "order",
        "internet"
    ],
    "wof:name":"Sears Canada Inc",
    "wof:placetype":"venue"
},
  "geometry": {"coordinates":[-79.29141235349999,46.2617683411],"type":"Point"}
}