{
  "type": "Feature",
  "properties": {
    "addr:full":"PO Box 187 Rockyford AB T0J 2R0",
    "addr:housenumber":"po",
    "addr:postcode":"t0j 2r0",
    "addr:street":"Box 187",
    "iso:country":"CA",
    "sg:address":"PO Box 187",
    "sg:city":"Rockyford",
    "sg:classifiers":[
        {
            "category":"Building & Trades",
            "subcategory":"Construction",
            "type":"Services"
        }
    ],
    "sg:phone":"+1 403 533 3884",
    "sg:postcode":"T0J 2R0",
    "sg:province":"AB",
    "sg:tags":[
        "water",
        "well",
        "drilling"
    ],
    "wof:name":"Gerritsen Drilling Ltd",
    "wof:placetype":"venue"
},
  "geometry": {"coordinates":[-113.14448547400001,51.2336158752],"type":"Point"}
}