{
  "type": "Feature",
  "properties": {
    "addr:full":"9 Oakland Blvd # 2 Elliot Lake ON P5A 2T1",
    "addr:housenumber":"9",
    "addr:postcode":"p5a 2t1",
    "addr:street":"Oakland Blvd # 2",
    "iso:country":"CA",
    "sg:address":"9 Oakland Blvd # 2",
    "sg:city":"Elliot Lake",
    "sg:classifiers":[
        {
            "category":"Social Services",
            "type":"Services"
        }
    ],
    "sg:phone":"+1 705 848 2585",
    "sg:postcode":"P5A 2T1",
    "sg:province":"ON",
    "sg:tags":[
        "organization",
        "counselor",
        "marriage",
        "family",
        "welfare"
    ],
    "wof:name":"Family Life Ctr",
    "wof:placetype":"venue"
},
  "geometry": {"coordinates":[-82.6362915039,46.3801879883],"type":"Point"}
}