{
  "type": "Feature",
  "properties": {
    "addr:full":"608 Chamblet St Midway BC V0H 1M0",
    "addr:housenumber":"608",
    "addr:postcode":"v0h 1m0",
    "addr:street":"Chamblet St",
    "iso:country":"CA",
    "sg:address":"608 Chamblet St",
    "sg:city":"Midway",
    "sg:classifiers":[
        {
            "category":"Manufacturing",
            "subcategory":"Lumber",
            "type":"Manufacturing & Wholesale Goods"
        }
    ],
    "sg:phone":"+1 250 449 2322",
    "sg:postcode":"V0H 1M0",
    "sg:province":"BC",
    "sg:tags":[
        "company",
        "logging"
    ],
    "wof:name":"R D Hedlund Logging Ltd",
    "wof:placetype":"venue"
},
  "geometry": {"coordinates":[-118.778847,49.010731],"type":"Point"}
}