{
  "type": "Feature",
  "properties": {
    "iso:country":"CA",
    "sg:address":"230 King St",
    "sg:city":"Stayner",
    "sg:classifiers":[
        {
            "category":"Health Services",
            "subcategory":"Doctor",
            "type":"Services"
        }
    ],
    "sg:phone":"+1 705 428 3246",
    "sg:postcode":"L0M 1S0",
    "sg:province":"ON",
    "sg:tags":[
        "physician",
        "surgeon"
    ],
    "wof:name":"Stayner Medical Ctr",
    "wof:placetype":"venue"
},
  "geometry": {"coordinates":[-80.0894699097,44.4197654724],"type":"Point"}
}