{
  "type": "Feature",
  "properties": {
    "addr:full":"571 15th St W Prince Albert SK S6V 3R3",
    "addr:housenumber":"571",
    "addr:postcode":"s6v 3r3",
    "addr:street":"15Th St",
    "iso:country":"CA",
    "sg:address":"571 15th St W",
    "sg:city":"Prince Albert",
    "sg:classifiers":[
        {
            "category":"Retail",
            "subcategory":"Repair Shop",
            "type":"Services"
        }
    ],
    "sg:phone":"+1 306 922 6104",
    "sg:postcode":"S6V 3R3",
    "sg:province":"SK",
    "sg:tags":[
        "upholsterer"
    ],
    "wof:name":"S & D Upholstery",
    "wof:placetype":"venue"
},
  "geometry": {"coordinates":[-105.768738,53.199162],"type":"Point"}
}