{
  "type": "Feature",
  "properties": {
    "addr:full":"5164 Av Du Parc Montreal QC H2V 4G6",
    "addr:housenumber":"5164",
    "addr:postcode":"h2v 4g6",
    "addr:street":"Av Du Parc",
    "iso:country":"CA",
    "sg:address":"5164 Av Du Parc",
    "sg:city":"Montreal",
    "sg:classifiers":[
        {
            "category":"Home & Garden",
            "subcategory":"Furniture",
            "type":"Retail Goods"
        }
    ],
    "sg:phone":"+1 514 278 4527",
    "sg:postcode":"H2V 4G6",
    "sg:province":"QC",
    "sg:tags":[
        "mattress"
    ],
    "wof:name":"Matelas Bonheur",
    "wof:placetype":"venue"
},
  "geometry": {"coordinates":[-73.597076,45.520058],"type":"Point"}
}