{
  "type": "Feature",
  "properties": {
    "addr:full":"55 Norfolk St S Simcoe ON N3Y 2W1",
    "addr:housenumber":"55",
    "addr:postcode":"n3y 2w1",
    "addr:street":"Norfolk St S",
    "iso:country":"CA",
    "sg:address":"55 Norfolk St S",
    "sg:city":"Simcoe",
    "sg:classifiers":[
        {
            "category":"Banks & Credit Unions",
            "subcategory":"Bank",
            "type":"Services"
        }
    ],
    "sg:phone":"+1 519 428 3800",
    "sg:postcode":"N3Y 2W1",
    "sg:province":"ON",
    "wof:name":"Royal Bank Financial Group",
    "wof:placetype":"venue"
},
  "geometry": {"coordinates":[-80.30350494379999,42.8362312317],"type":"Point"}
}