{
  "type": "Feature",
  "properties": {
    "addr:full":"72 King St Trenton ON K8V 3V8",
    "addr:housenumber":"72",
    "addr:postcode":"k8v 3v8",
    "addr:street":"King St",
    "iso:country":"CA",
    "sg:address":"72 King St",
    "sg:city":"Trenton",
    "sg:classifiers":[
        {
            "category":"Shopping",
            "subcategory":"Clothing, Apparel, & Fashions",
            "type":"Retail Goods"
        }
    ],
    "sg:phone":"+1 613 394 4969",
    "sg:postcode":"K8V 3V8",
    "sg:province":"ON",
    "sg:tags":[
        "tailor"
    ],
    "wof:name":"Trenton Clothing Repair",
    "wof:placetype":"venue"
},
  "geometry": {"coordinates":[-77.57868999999999,44.101315],"type":"Point"}
}