{
  "type": "Feature",
  "properties": {
    "addr:full":"2037 Long Lake Rd # 12 Sudbury ON P3E 6J9",
    "addr:housenumber":"2037",
    "addr:postcode":"p3e 6j9",
    "addr:street":"Long Lake Rd # 12",
    "iso:country":"CA",
    "sg:address":"2037 Long Lake Rd # 12",
    "sg:city":"Sudbury",
    "sg:classifiers":[
        {
            "category":"Health Services",
            "subcategory":"Doctor",
            "type":"Services"
        }
    ],
    "sg:phone":"+1 705 522 4851",
    "sg:postcode":"P3E 6J9",
    "sg:province":"ON",
    "sg:tags":[
        "physician",
        "surgeon"
    ],
    "wof:name":"Mc Cluskey, K A MD",
    "wof:placetype":"venue"
},
  "geometry": {"coordinates":[-81.003601,46.450855],"type":"Point"}
}