{
  "type": "Feature",
  "properties": {
    "addr:full":"307 15th St W Prince Albert SK S6V 3R1",
    "addr:housenumber":"307",
    "addr:postcode":"s6v 3r1",
    "addr:street":"15Th St",
    "iso:country":"CA",
    "sg:address":"307 15th St W",
    "sg:city":"Prince Albert",
    "sg:classifiers":[
        {
            "category":"Shopping",
            "subcategory":"Computers & Home Electronics",
            "type":"Retail Goods"
        }
    ],
    "sg:phone":"+1 306 763 6969",
    "sg:postcode":"S6V 3R1",
    "sg:province":"SK",
    "sg:tags":[
        "equipment",
        "electronic",
        "dealer",
        "supply"
    ],
    "wof:name":"A & R Electronics Svc",
    "wof:placetype":"venue"
},
  "geometry": {"coordinates":[-105.762604,53.199333],"type":"Point"}
}