{
  "type": "Feature",
  "properties": {
    "addr:full":"1500 King St E # 1 Hamilton ON L8K 1S8",
    "addr:housenumber":"1500",
    "addr:postcode":"l8k 1s8",
    "addr:street":"King St E # 1",
    "iso:country":"CA",
    "sg:address":"1500 King St E # 1",
    "sg:city":"Hamilton",
    "sg:classifiers":[
        {
            "category":"Personal",
            "subcategory":"Beauty Salon",
            "type":"Services"
        }
    ],
    "sg:phone":"+1 905 547 9290",
    "sg:postcode":"L8K 1S8",
    "sg:province":"ON",
    "wof:name":"Anna's Hairstyling",
    "wof:placetype":"venue"
},
  "geometry": {"coordinates":[-79.82028200000001,43.23785],"type":"Point"}
}