{
  "type": "Feature",
  "properties": {
    "iso:country":"CA",
    "sg:address":"14 Burdge Crt",
    "sg:city":"Whitby",
    "sg:classifiers":[
        {
            "category":"Building & Trades",
            "subcategory":"Construction",
            "type":"Services"
        }
    ],
    "sg:phone":"+1 905 571 2966",
    "sg:postcode":"L1N 9L1",
    "sg:province":"ON",
    "sg:tags":[
        "home",
        "improvement"
    ],
    "wof:name":"Paul's Home Improvements",
    "wof:placetype":"venue"
},
  "geometry": {"coordinates":[-78.89952850340001,43.8884391785],"type":"Point"}
}