{
  "type": "Feature",
  "properties": {
    "addr:full":"1715 Idylwyld Dr N Saskatoon SK S7L 6J2",
    "addr:housenumber":"1715",
    "addr:postcode":"s7l 6j2",
    "addr:street":"Idylwyld Dr N",
    "iso:country":"CA",
    "sg:address":"1715 Idylwyld Dr N",
    "sg:city":"Saskatoon",
    "sg:classifiers":[
        {
            "category":"Building & Trades",
            "subcategory":"Electrical",
            "type":"Services"
        }
    ],
    "sg:phone":"+1 306 665 3070",
    "sg:postcode":"S7L 6J2",
    "sg:province":"SK",
    "sg:tags":[
        "electric",
        "contractor"
    ],
    "wof:name":"Midline Electrical Svc",
    "wof:placetype":"venue"
},
  "geometry": {"coordinates":[-106.670547,52.151955],"type":"Point"}
}