{
  "type": "Feature",
  "properties": {
    "addr:full":"201 8 Ave SW Calgary AB T2P 1B7",
    "addr:housenumber":"201",
    "addr:postcode":"t2p 1b7",
    "addr:street":"8 Ave Sw",
    "iso:country":"CA",
    "sg:address":"201 8 Ave SW",
    "sg:city":"Calgary",
    "sg:classifiers":[
        {
            "category":"Restaurant",
            "type":"Food & Drink"
        }
    ],
    "sg:phone":"+1 403 234 7710",
    "sg:postcode":"T2P 1B7",
    "sg:province":"AB",
    "wof:name":"Subway Sandwiches & Salads",
    "wof:placetype":"venue"
},
  "geometry": {"coordinates":[-114.065757752,51.0454673767],"type":"Point"}
}