{
  "type": "Feature",
  "properties": {
    "addr:full":"669 Wentworth Rd Windsor NS B0N 2T0",
    "addr:housenumber":"669",
    "addr:postcode":"b0n 2t0",
    "addr:street":"Wentworth Rd",
    "iso:country":"CA",
    "sg:address":"669 Wentworth Rd",
    "sg:city":"Windsor",
    "sg:classifiers":[
        {
            "category":"Wholesale",
            "subcategory":"Construction Materials",
            "type":"Manufacturing & Wholesale Goods"
        }
    ],
    "sg:phone":"+1 902 798 4676",
    "sg:postcode":"B0N 2T0",
    "sg:province":"NS",
    "sg:tags":[
        "building"
    ],
    "wof:name":"Fundy Gypsum CO",
    "wof:placetype":"venue"
},
  "geometry": {"coordinates":[-64.126915,44.990986],"type":"Point"}
}