{
  "type": "Feature",
  "properties": {
    "iso:country":"CA",
    "sg:city":"Toronto",
    "sg:classifiers":[
        {
            "category":"Organizations",
            "subcategory":"Professional Association",
            "type":"Services"
        }
    ],
    "sg:phone":"+1 416 961 2855",
    "sg:postcode":"M4S 2Z2",
    "sg:province":"ON",
    "wof:name":"World Schizophrenia Fellowship",
    "wof:placetype":"venue"
},
  "geometry": {"coordinates":[-79.39251708979999,43.6970100403],"type":"Point"}
}