{
  "type": "Feature",
  "properties": {
    "addr:full":"38 1st Ave NE Dauphin MB R7N 1A4",
    "addr:housenumber":"38",
    "addr:postcode":"r7n 1a4",
    "addr:street":"1St Ave Ne",
    "iso:country":"CA",
    "sg:address":"38 1st Ave NE",
    "sg:city":"Dauphin",
    "sg:classifiers":[
        {
            "category":"Shopping",
            "subcategory":"Computers & Home Electronics",
            "type":"Retail Goods"
        }
    ],
    "sg:phone":"+1 204 622 5377",
    "sg:postcode":"R7N 1A4",
    "sg:province":"MB",
    "sg:tags":[
        "equipment",
        "dealer"
    ],
    "wof:name":"Baker Computers",
    "wof:placetype":"venue"
},
  "geometry": {"coordinates":[-100.048995972,51.1494255066],"type":"Point"}
}