{
  "type": "Feature",
  "properties": {
    "addr:full":"10785 Rue Saint-Urbain Montreal QC H3L 2V4",
    "addr:housenumber":"10785",
    "addr:postcode":"h3l 2v4",
    "addr:street":"Rue Saint-Urbain",
    "iso:country":"CA",
    "sg:address":"10785 Rue Saint-Urbain",
    "sg:city":"Montreal",
    "sg:classifiers":[
        {
            "category":"Professional",
            "type":"Services"
        }
    ],
    "sg:phone":"+1 514 331 7761",
    "sg:postcode":"H3L 2V4",
    "sg:province":"QC",
    "sg:tags":[
        "consultant",
        "geological"
    ],
    "wof:name":"Geon",
    "wof:placetype":"venue"
},
  "geometry": {"coordinates":[-73.67321800000001,45.549381],"type":"Point"}
}