{
  "type": "Feature",
  "properties": {
    "addr:full":"22 Cathay St Cambridge ON N1R 4V2",
    "addr:housenumber":"22",
    "addr:postcode":"n1r 4v2",
    "addr:street":"Cathay St",
    "iso:country":"CA",
    "sg:address":"22 Cathay St",
    "sg:city":"Cambridge",
    "sg:classifiers":[
        {
            "category":"Health Services",
            "subcategory":"Doctor",
            "type":"Services"
        }
    ],
    "sg:phone":"+1 519 623 1400",
    "sg:postcode":"N1R 4V2",
    "sg:province":"ON",
    "sg:tags":[
        "physician",
        "surgeon"
    ],
    "wof:name":"Butters, M W MD",
    "wof:placetype":"venue"
},
  "geometry": {"coordinates":[-80.302711,43.35672],"type":"Point"}
}