{
  "type": "Feature",
  "properties": {
    "addr:full":"10-24 Columbia Dr Marystown NL A0E 2M0",
    "addr:housenumber":"10-24",
    "addr:postcode":"a0e 2m0",
    "addr:street":"Columbia Dr",
    "iso:country":"CA",
    "sg:address":"10-24 Columbia Dr",
    "sg:city":"Marystown",
    "sg:classifiers":[
        {
            "category":"Health Services",
            "subcategory":"Doctor",
            "type":"Services"
        }
    ],
    "sg:phone":"+1 709 279 4500",
    "sg:postcode":"A0E 2M0",
    "sg:province":"NL",
    "sg:tags":[
        "physician",
        "surgeon"
    ],
    "wof:name":"Roberts, Bernard MD",
    "wof:placetype":"venue"
},
  "geometry": {"coordinates":[-55.242413,47.16143],"type":"Point"}
}