{
  "type": "Feature",
  "properties": {
    "addr:full":"Montreal QC H3Z 1X5",
    "addr:postcode":"h3z 1x5",
    "iso:country":"CA",
    "sg:city":"Montreal",
    "sg:classifiers":[
        {
            "category":"Restaurant",
            "type":"Food & Drink"
        }
    ],
    "sg:phone":"+1 514 931 7476",
    "sg:postcode":"H3Z 1X5",
    "sg:province":"QC",
    "sg:tags":[
        "shop",
        "coffee"
    ],
    "wof:name":"Muffin Plus",
    "wof:placetype":"venue"
},
  "geometry": {"coordinates":[-73.5885925293,45.4952354431],"type":"Point"}
}