{
  "type": "Feature",
  "properties": {
    "addr:full":"Central Rd Gillies Bay BC V0N 1W0",
    "addr:postcode":"v0n 1w0",
    "addr:street":"Central Rd",
    "iso:country":"CA",
    "sg:address":"Central Rd",
    "sg:city":"Gillies Bay",
    "sg:classifiers":[
        {
            "category":"Wholesale",
            "subcategory":"Machinery & Supplies",
            "type":"Manufacturing & Wholesale Goods"
        }
    ],
    "sg:phone":"+1 604 486 7316",
    "sg:postcode":"V0N 1W0",
    "sg:province":"BC",
    "sg:tags":[
        "forestry",
        "timber"
    ],
    "wof:name":"Texguard Forestry Supplies CO",
    "wof:placetype":"venue"
},
  "geometry": {"coordinates":[-124.48484000000001,49.677422],"type":"Point"}
}