{
  "type": "Feature",
  "properties": {
    "addr:full":"911 Rue Cherrier Montreal QC H2L 1J1",
    "addr:housenumber":"911",
    "addr:postcode":"h2l 1j1",
    "addr:street":"Rue Cherrier",
    "iso:country":"CA",
    "sg:address":"911 Rue Cherrier",
    "sg:city":"Montreal",
    "sg:classifiers":[
        {
            "category":"Professional",
            "subcategory":"Research",
            "type":"Services"
        }
    ],
    "sg:phone":"+1 514 596 1522",
    "sg:postcode":"H2L 1J1",
    "sg:province":"QC",
    "sg:tags":[
        "development",
        "laboratory"
    ],
    "wof:name":"Boreal Primum",
    "wof:placetype":"venue"
},
  "geometry": {"coordinates":[-73.567802,45.52084],"type":"Point"}
}