{
  "type": "Feature",
  "properties": {
    "iso:country":"CA",
    "sg:address":"655 Dixon Rd",
    "sg:city":"Etobicoke",
    "sg:classifiers":[
        {
            "category":"Retail",
            "subcategory":"Auto Rental",
            "type":"Services"
        }
    ],
    "sg:phone":"+1 416 249 5554",
    "sg:postcode":"M9W 1J3",
    "sg:province":"ON",
    "sg:tags":[
        "renting",
        "automobile"
    ],
    "wof:name":"A Discount Car & Truck Rentals",
    "wof:placetype":"venue"
},
  "geometry": {"coordinates":[-79.578011,43.689812],"type":"Point"}
}