{
  "type": "Feature",
  "properties": {
    "iso:country":"CA",
    "sg:address":"585 O'Dell Ave",
    "sg:city":"Sarnia",
    "sg:classifiers":[
        {
            "category":"Education",
            "subcategory":"School",
            "type":"Public Place"
        }
    ],
    "sg:phone":"+1 519 344 2942",
    "sg:postcode":"N7V 4H7",
    "sg:province":"ON",
    "wof:name":"King George VI School",
    "wof:placetype":"venue"
},
  "geometry": {"coordinates":[-82.3585510254,43.0127372742],"type":"Point"}
}