{
  "type": "Feature",
  "properties": {
    "iso:country":"CA",
    "sg:address":"151 York St",
    "sg:city":"London",
    "sg:classifiers":[
        {
            "category":"Real Estate",
            "subcategory":"Real Estate Agent",
            "type":"Services"
        }
    ],
    "sg:phone":"+1 519 679 4889",
    "sg:postcode":"N6A 1A8",
    "sg:province":"ON",
    "wof:name":"Broker Direct Real Estate Svc",
    "wof:placetype":"venue"
},
  "geometry": {"coordinates":[-81.24950408940001,42.980884552],"type":"Point"}
}