{
  "type": "Feature",
  "properties": {
    "addr:full":"PO Box 288 Virgil ON L0S 1T0",
    "addr:housenumber":"po",
    "addr:postcode":"l0s 1t0",
    "addr:street":"Box 288",
    "iso:country":"CA",
    "sg:address":"PO Box 288",
    "sg:city":"Virgil",
    "sg:classifiers":[
        {
            "category":"Real Estate",
            "subcategory":"Real Estate Agent",
            "type":"Services"
        }
    ],
    "sg:phone":"+1 905 468 2590",
    "sg:postcode":"L0S 1T0",
    "sg:province":"ON",
    "wof:name":"Country Canada Real Estate Ltd",
    "wof:placetype":"venue"
},
  "geometry": {"coordinates":[-79.12215399999999,43.21981],"type":"Point"}
}