{
  "type": "Feature",
  "properties": {
    "addr:full":"885 Glasgow St Kitchener ON N2M 2N7",
    "addr:housenumber":"885",
    "addr:postcode":"n2m 2n7",
    "addr:street":"Glasgow St",
    "iso:country":"CA",
    "sg:address":"885 Glasgow St",
    "sg:city":"Kitchener",
    "sg:classifiers":[
        {
            "category":"Shopping",
            "subcategory":"Optical Goods",
            "type":"Retail Goods"
        }
    ],
    "sg:phone":"+1 519 741 1233",
    "sg:postcode":"N2M 2N7",
    "sg:province":"ON",
    "sg:tags":[
        "sun",
        "goggles",
        "sunglasses",
        "optician"
    ],
    "wof:name":"Specs Appeal",
    "wof:placetype":"venue"
},
  "geometry": {"coordinates":[-80.542603,43.442146],"type":"Point"}
}