{
  "type": "Feature",
  "properties": {
    "iso:country":"CA",
    "sg:address":"1084 Haines St",
    "sg:city":"Bowmanville",
    "sg:classifiers":[
        {
            "category":"Freight",
            "type":"Transportation"
        }
    ],
    "sg:phone":"+1 905 623 6649",
    "sg:postcode":"L1C 4R2",
    "sg:province":"ON",
    "sg:tags":[
        "commercial",
        "storage"
    ],
    "wof:name":"Durham Mini Storage",
    "wof:placetype":"venue"
},
  "geometry": {"coordinates":[-78.6622390747,43.906047821],"type":"Point"}
}