{
  "type": "Feature",
  "properties": {
    "addr:full":"11010 101 St NW Edmonton AB T5H 4B9",
    "addr:housenumber":"11010",
    "addr:postcode":"t5h 4b9",
    "addr:street":"101 St Nw",
    "iso:country":"CA",
    "sg:address":"11010 101 St NW",
    "sg:city":"Edmonton",
    "sg:classifiers":[
        {
            "category":"Shopping",
            "type":"Retail Goods"
        }
    ],
    "sg:phone":"+1 780 424 7659",
    "sg:postcode":"T5H 4B9",
    "sg:province":"AB",
    "sg:tags":[
        "supply",
        "equipment",
        "audiologists",
        "hearing",
        "impaired"
    ],
    "wof:name":"Professional Audiology Clinic",
    "wof:placetype":"venue"
},
  "geometry": {"coordinates":[-113.493843079,53.5573310852],"type":"Point"}
}