{
  "type": "Feature",
  "properties": {
    "addr:full":"45 Main St Stewiacke NS B0N 2J0",
    "addr:housenumber":"45",
    "addr:postcode":"b0n 2j0",
    "addr:street":"Main St",
    "iso:country":"CA",
    "sg:address":"45 Main St",
    "sg:city":"Stewiacke",
    "sg:classifiers":[
        {
            "category":"Retail",
            "subcategory":"Auto Repair",
            "type":"Services"
        }
    ],
    "sg:phone":"+1 902 639 2444",
    "sg:postcode":"B0N 2J0",
    "sg:province":"NS",
    "sg:tags":[
        "body",
        "automobile",
        "painting"
    ],
    "wof:name":"Denney's Auto Body",
    "wof:placetype":"venue"
},
  "geometry": {"coordinates":[-63.362076,45.139614],"type":"Point"}
}