{
  "type": "Feature",
  "properties": {
    "addr:full":"195 Bay St Trenton ON K8V 1H9",
    "addr:housenumber":"195",
    "addr:postcode":"k8v 1h9",
    "addr:street":"Bay St",
    "iso:country":"CA",
    "sg:address":"195 Bay St",
    "sg:city":"Trenton",
    "sg:classifiers":[
        {
            "category":"Health Services",
            "subcategory":"Nursing And Care Facility",
            "type":"Services"
        }
    ],
    "sg:phone":"+1 613 392 9235",
    "sg:postcode":"K8V 1H9",
    "sg:province":"ON",
    "sg:tags":[
        "home",
        "convalescent"
    ],
    "wof:name":"Trent Valley Lodge Nursing Hm",
    "wof:placetype":"venue"
},
  "geometry": {"coordinates":[-77.556602,44.104248],"type":"Point"}
}