{
  "type": "Feature",
  "properties": {
    "addr:full":"161 Main St Blackville NB E9B 1S3",
    "addr:housenumber":"161",
    "addr:postcode":"e9b 1s3",
    "addr:street":"Main St",
    "iso:country":"CA",
    "sg:address":"161 Main St",
    "sg:city":"Blackville",
    "sg:classifiers":[
        {
            "category":"Shopping",
            "subcategory":"Catalog Store",
            "type":"Retail Goods"
        }
    ],
    "sg:phone":"+1 506 843 6411",
    "sg:postcode":"E9B 1S3",
    "sg:province":"NB",
    "sg:tags":[
        "mail",
        "order",
        "internet"
    ],
    "wof:name":"Sears Canada Inc",
    "wof:placetype":"venue"
},
  "geometry": {"coordinates":[-65.830681,46.738365],"type":"Point"}
}