{
  "type": "Feature",
  "properties": {
    "addr:full":"6240 Boul Des Mille-Iles Laval QC H7B 1B3",
    "addr:housenumber":"6240",
    "addr:postcode":"h7b 1b3",
    "addr:street":"Boul Des Mille-Iles",
    "iso:country":"CA",
    "sg:address":"6240 Boul Des Mille-Iles",
    "sg:city":"Laval",
    "sg:classifiers":[
        {
            "category":"Wholesale",
            "subcategory":"Machinery & Supplies",
            "type":"Manufacturing & Wholesale Goods"
        }
    ],
    "sg:phone":"+1 450 666 1710",
    "sg:postcode":"H7B 1B3",
    "sg:province":"QC",
    "sg:tags":[
        "equipment",
        "hydraulic",
        "garage"
    ],
    "wof:name":"Equipements SD Inc",
    "wof:placetype":"venue"
},
  "geometry": {"coordinates":[-73.637726,45.686939],"type":"Point"}
}