{
  "type": "Feature",
  "properties": {
    "addr:full":"380 Wellington St #36 London ON N6A 5B5",
    "addr:housenumber":"380",
    "addr:postcode":"n6a 5b5",
    "addr:street":"Wellington St # 36",
    "iso:country":"CA",
    "sg:address":"380 Wellington St #36",
    "sg:city":"London",
    "sg:classifiers":[
        {
            "category":"Health Services",
            "subcategory":"Doctor",
            "type":"Services"
        }
    ],
    "sg:phone":"+1 519 438 2020",
    "sg:postcode":"N6A 5B5",
    "sg:province":"ON",
    "sg:tags":[
        "physician",
        "surgeon"
    ],
    "wof:name":"Tlc the Laser Ctr",
    "wof:placetype":"venue"
},
  "geometry": {"coordinates":[-81.244621,42.9841],"type":"Point"}
}