{
  "type": "Feature",
  "properties": {
    "iso:country":"CA",
    "sg:city":"Mississauga",
    "sg:classifiers":[
        {
            "category":"Retail",
            "subcategory":"Laundry & Dry Cleaning",
            "type":"Services"
        }
    ],
    "sg:phone":"+1 905 625 5526",
    "sg:postcode":"L4W 1V5",
    "sg:province":"ON",
    "sg:tags":[
        "cleaners"
    ],
    "wof:name":"Award Cleaners",
    "wof:placetype":"venue"
},
  "geometry": {"coordinates":[-79.6056442261,43.6250267029],"type":"Point"}
}