{
  "type": "Feature",
  "properties": {
    "addr:full":"20 Boul Brunswick Dollard-Des-Ormeaux QC H9B 2N8",
    "addr:housenumber":"20",
    "addr:postcode":"h9b 2n8",
    "addr:street":"Boul Brunswick",
    "iso:country":"CA",
    "sg:address":"20 Boul Brunswick",
    "sg:city":"Dollard-Des-Ormeaux",
    "sg:classifiers":[
        {
            "category":"Organizations",
            "subcategory":"Professional Association",
            "type":"Services"
        }
    ],
    "sg:phone":"+1 514 684 6462",
    "sg:postcode":"H9B 2N8",
    "sg:province":"QC",
    "wof:name":"Hellenic Community of West Isl",
    "wof:placetype":"venue"
},
  "geometry": {"coordinates":[-73.789680481,45.4860038757],"type":"Point"}
}