{
  "type": "Feature",
  "properties": {
    "addr:full":"124 Rue Lavoie Dolbeau-Mistassini QC G8L 4M8",
    "addr:housenumber":"124",
    "addr:postcode":"g8l 4m8",
    "addr:street":"Rue Lavoie",
    "iso:country":"CA",
    "sg:address":"124 Rue Lavoie",
    "sg:city":"Dolbeau-Mistassini",
    "sg:classifiers":[
        {
            "category":"Freight",
            "type":"Transportation"
        }
    ],
    "sg:phone":"+1 418 276 7395",
    "sg:postcode":"G8L 4M8",
    "sg:province":"QC",
    "sg:tags":[
        "sawdust",
        "shaving",
        "sand",
        "gravel",
        "trucking"
    ],
    "wof:name":"Transport Doucet & Fils Mist",
    "wof:placetype":"venue"
},
  "geometry": {"coordinates":[-72.1912612915,48.8889770508],"type":"Point"}
}