{
  "type": "Feature",
  "properties": {
    "addr:full":"125 Rue Du Roi Sorel-Tracy QC J3P 4N2",
    "addr:housenumber":"125",
    "addr:postcode":"j3p 4n2",
    "addr:street":"Rue Du Roi",
    "iso:country":"CA",
    "sg:address":"125 Rue Du Roi",
    "sg:city":"Sorel-Tracy",
    "sg:classifiers":[
        {
            "category":"Restaurant",
            "type":"Food & Drink"
        }
    ],
    "sg:phone":"+1 450 743 3307",
    "sg:postcode":"J3P 4N2",
    "sg:province":"QC",
    "wof:name":"Prince Pizzeria",
    "wof:placetype":"venue"
},
  "geometry": {"coordinates":[-73.1149520874,46.0417022705],"type":"Point"}
}