{
  "type": "Feature",
  "properties": {
    "iso:country":"CA",
    "sg:address":"125 Rue Du Roi",
    "sg:city":"Sorel-Tracy",
    "sg:classifiers":[
        {
            "category":"Restaurant",
            "type":"Food & Drink"
        }
    ],
    "sg:phone":"+1 450 743 3307",
    "sg:postcode":"J3P 4N2",
    "sg:province":"QC",
    "wof:name":"Prince Pizzeria",
    "wof:placetype":"venue"
},
  "geometry": {"coordinates":[-73.1149520874,46.0417022705],"type":"Point"}
}