{
  "type": "Feature",
  "properties": {
    "addr:full":"1677 Carling Ave Ottawa ON K2A 1C4",
    "addr:housenumber":"1677",
    "addr:postcode":"k2a 1c4",
    "addr:street":"Carling Ave",
    "iso:country":"CA",
    "sg:address":"1677 Carling Ave",
    "sg:city":"Ottawa",
    "sg:classifiers":[
        {
            "category":"Home & Garden",
            "subcategory":"Furniture",
            "type":"Retail Goods"
        }
    ],
    "sg:phone":"+1 613 729 2355",
    "sg:postcode":"K2A 1C4",
    "sg:province":"ON",
    "wof:name":"Norwalk the Furniture Idea",
    "wof:placetype":"venue"
},
  "geometry": {"coordinates":[-75.75000799999999,45.379398],"type":"Point"}
}