{
  "type": "Feature",
  "properties": {
    "addr:full":"Calgary AB T2H 2W9",
    "addr:postcode":"t2h 2w9",
    "iso:country":"CA",
    "sg:city":"Calgary",
    "sg:classifiers":[
        {
            "category":"Manufacturing",
            "subcategory":"Retail Goods",
            "type":"Manufacturing & Wholesale Goods"
        }
    ],
    "sg:phone":"+1 403 236 9414",
    "sg:postcode":"T2H 2W9",
    "sg:province":"AB",
    "sg:tags":[
        "interior",
        "consultant",
        "design",
        "decorator"
    ],
    "wof:name":"Stewart Drummond Studios Inc",
    "wof:placetype":"venue"
},
  "geometry": {"coordinates":[-114.062057,51.004807],"type":"Point"}
}