{
  "type": "Feature",
  "properties": {
    "addr:full":"96 Lawrence Ave Richmond Hill ON L4C 1Z3",
    "addr:housenumber":"96",
    "addr:postcode":"l4c 1z3",
    "addr:street":"Lawrence Ave",
    "iso:country":"CA",
    "sg:address":"96 Lawrence Ave",
    "sg:city":"Richmond Hill",
    "sg:classifiers":[
        {
            "category":"Building & Trades",
            "subcategory":"Electrical",
            "type":"Services"
        }
    ],
    "sg:phone":"+1 905 884 3296",
    "sg:postcode":"L4C 1Z3",
    "sg:province":"ON",
    "sg:tags":[
        "plumbing",
        "electric",
        "contractor"
    ],
    "wof:name":"Pecks Plumbing & Heating",
    "wof:placetype":"venue"
},
  "geometry": {"coordinates":[-79.43227400000001,43.873302],"type":"Point"}
}