{
  "type": "Feature",
  "properties": {
    "addr:full":"301 Rue Des Roitelets Saint-Nicolas QC G7A 3B7",
    "addr:housenumber":"301",
    "addr:postcode":"g7a 3b7",
    "addr:street":"Rue Des Roitelets",
    "iso:country":"CA",
    "sg:address":"301 Rue Des Roitelets",
    "sg:city":"Saint-Nicolas",
    "sg:classifiers":[
        {
            "category":"Professional",
            "subcategory":"Art Services",
            "type":"Services"
        }
    ],
    "sg:phone":"+1 418 261 4440",
    "sg:postcode":"G7A 3B7",
    "sg:province":"QC",
    "sg:tags":[
        "photographer"
    ],
    "wof:name":"Photomedia",
    "wof:placetype":"venue"
},
  "geometry": {"coordinates":[-71.30297899999999,46.733543],"type":"Point"}
}