{
  "type": "Feature",
  "properties": {
    "addr:full":"Newcastle ON L1B 1L9",
    "addr:postcode":"l1b 1l9",
    "iso:country":"CA",
    "sg:city":"Newcastle",
    "sg:classifiers":[
        {
            "category":"Building & Trades",
            "subcategory":"Construction",
            "type":"Services"
        }
    ],
    "sg:phone":"+1 905 987 1380",
    "sg:postcode":"L1B 1L9",
    "sg:province":"ON",
    "sg:tags":[
        "erectors",
        "machinery"
    ],
    "wof:name":"Acme Machinery Movers Inc",
    "wof:placetype":"venue"
},
  "geometry": {"coordinates":[-78.6237564087,43.9128608704],"type":"Point"}
}