{
  "type": "Feature",
  "properties": {
    "addr:full":"9844 106 St NW Edmonton AB T5K 1B8",
    "addr:housenumber":"9844",
    "addr:postcode":"t5k 1b8",
    "addr:street":"106 St Nw",
    "iso:country":"CA",
    "sg:address":"9844 106 St NW",
    "sg:city":"Edmonton",
    "sg:classifiers":[
        {
            "category":"Professional",
            "subcategory":"Business Services",
            "type":"Services"
        }
    ],
    "sg:phone":"+1 780 424 9020",
    "sg:postcode":"T5K 1B8",
    "sg:province":"AB",
    "sg:tags":[
        "process",
        "civil",
        "server",
        "enforcement"
    ],
    "wof:name":"Serv-It Bailiff Svc Inc",
    "wof:placetype":"venue"
},
  "geometry": {"coordinates":[-113.50315094,53.5363845825],"type":"Point"}
}