{
  "type": "Feature",
  "properties": {
    "addr:full":"119 Osler Dr Dundas ON L9H 6X4",
    "addr:housenumber":"119",
    "addr:postcode":"l9h 6x4",
    "addr:street":"Osler Dr",
    "iso:country":"CA",
    "sg:address":"119 Osler Dr",
    "sg:city":"Dundas",
    "sg:classifiers":[
        {
            "category":"Cinema",
            "subcategory":"Movie Rental",
            "type":"Entertainment"
        }
    ],
    "sg:phone":"+1 905 627 3042",
    "sg:postcode":"L9H 6X4",
    "sg:province":"ON",
    "sg:tags":[
        "leasing",
        "video",
        "disc",
        "tape"
    ],
    "wof:name":"Jumbo Video",
    "wof:placetype":"venue"
},
  "geometry": {"coordinates":[-79.94169599999999,43.259007],"type":"Point"}
}