{
  "type": "Feature",
  "properties": {
    "addr:full":"Saskatoon SK S7K 4K7",
    "addr:postcode":"s7k 4k7",
    "iso:country":"CA",
    "sg:city":"Saskatoon",
    "sg:classifiers":[
        {
            "category":"Social Services",
            "type":"Services"
        }
    ],
    "sg:phone":"+1 306 934 5898",
    "sg:postcode":"S7K 4K7",
    "sg:province":"SK",
    "sg:tags":[
        "information",
        "organization",
        "treatment",
        "alcoholism",
        "welfare"
    ],
    "wof:name":"Professional Counselling",
    "wof:placetype":"venue"
},
  "geometry": {"coordinates":[-106.65772200000001,52.12925],"type":"Point"}
}