{
  "type": "Feature",
  "properties": {
    "addr:full":"PO Box 301 Entwistle AB T0E 0S0",
    "addr:housenumber":"po;301",
    "addr:postcode":"t0e 0s0",
    "addr:street":"Box",
    "iso:country":"CA",
    "sg:address":"PO Box 301",
    "sg:city":"Entwistle",
    "sg:classifiers":[
        {
            "category":"Home & Garden",
            "subcategory":"Building Materials",
            "type":"Retail Goods"
        }
    ],
    "sg:phone":"+1 780 727 2730",
    "sg:postcode":"T0E 0S0",
    "sg:province":"AB",
    "sg:tags":[
        "windows",
        "plate",
        "window"
    ],
    "wof:name":"Specialty Glass & Supply",
    "wof:placetype":"venue"
},
  "geometry": {"coordinates":[-114.992645264,53.5988540649],"type":"Point"}
}