{
  "type": "Feature",
  "properties": {
    "iso:country":"CA",
    "sg:address":"9179 148 St",
    "sg:city":"Surrey",
    "sg:classifiers":[
        {
            "category":"Food & Beverages",
            "subcategory":"Groceries & Convenience Stores",
            "type":"Retail Goods"
        }
    ],
    "sg:phone":"+1 604 584 3511",
    "sg:postcode":"V3R 3W7",
    "sg:province":"BC",
    "sg:tags":[
        "grocer"
    ],
    "wof:name":"153 Market",
    "wof:placetype":"venue"
},
  "geometry": {"coordinates":[-122.812568665,49.1694259644],"type":"Point"}
}