{
  "type": "Feature",
  "properties": {
    "iso:country":"CA",
    "sg:city":"Toronto",
    "sg:classifiers":[
        {
            "category":"Shopping",
            "subcategory":"Computers & Home Electronics",
            "type":"Retail Goods"
        }
    ],
    "sg:phone":"+1 416 504 0141",
    "sg:postcode":"M5V 2K6",
    "sg:province":"ON",
    "sg:tags":[
        "software"
    ],
    "wof:name":"Infrastructures For Info",
    "wof:placetype":"venue"
},
  "geometry": {"coordinates":[-79.39594268800001,43.6469726562],"type":"Point"}
}