{
  "type": "Feature",
  "properties": {
    "addr:full":"Brampton ON L6W 2E1",
    "addr:postcode":"l6w 2e1",
    "iso:country":"CA",
    "sg:city":"Brampton",
    "sg:classifiers":[
        {
            "category":"Building & Trades",
            "subcategory":"Equipment Rental",
            "type":"Services"
        }
    ],
    "sg:phone":"+1 905 459 3194",
    "sg:postcode":"L6W 2E1",
    "sg:province":"ON",
    "sg:tags":[
        "television",
        "radio"
    ],
    "wof:name":"Bramalea Repairs",
    "wof:placetype":"venue"
},
  "geometry": {"coordinates":[-79.7487487793,43.6777687073],"type":"Point"}
}