{
  "type": "Feature",
  "properties": {
    "addr:full":"5110 Av DE Courtrai Montreal QC H3W 1A7",
    "addr:housenumber":"5110",
    "addr:postcode":"h3w 1a7",
    "addr:street":"Av De Courtrai",
    "iso:country":"CA",
    "sg:address":"5110 Av DE Courtrai",
    "sg:city":"Montreal",
    "sg:classifiers":[
        {
            "category":"Building & Trades",
            "subcategory":"Construction",
            "type":"Services"
        }
    ],
    "sg:phone":"+1 514 735 9191",
    "sg:postcode":"H3W 1A7",
    "sg:province":"QC",
    "sg:tags":[
        "maker",
        "cabinet"
    ],
    "wof:name":"M & O Design",
    "wof:placetype":"venue"
},
  "geometry": {"coordinates":[-73.64743799999999,45.495152],"type":"Point"}
}