{
  "type": "Feature",
  "properties": {
    "addr:full":"5029 50th St Vegreville AB T9C 1T2",
    "addr:housenumber":"5029",
    "addr:postcode":"t9c 1t2",
    "addr:street":"50Th St",
    "iso:country":"CA",
    "sg:address":"5029 50th St",
    "sg:city":"Vegreville",
    "sg:classifiers":[
        {
            "category":"Food & Beverages",
            "subcategory":"Meat & Fish",
            "type":"Retail Goods"
        }
    ],
    "sg:phone":"+1 780 632 6149",
    "sg:postcode":"T9C 1T2",
    "sg:province":"AB",
    "wof:name":"Prime Cuts Meat & Deli Ltd",
    "wof:placetype":"venue"
},
  "geometry": {"coordinates":[-112.052459717,53.4949188232],"type":"Point"}
}