{
  "type": "Feature",
  "properties": {
    "addr:full":"London ON N5V 3L3",
    "addr:postcode":"n5v 3l3",
    "iso:country":"CA",
    "sg:city":"London",
    "sg:phone":"+1 519 451 4451",
    "sg:postcode":"N5V 3L3",
    "sg:province":"ON",
    "sg:tags":[
        "lubricant"
    ],
    "wof:name":"Ontario Warehouse Distributors",
    "wof:placetype":"venue"
},
  "geometry": {"coordinates":[-81.1593704224,43.009967804],"type":"Point"}
}