{
  "type": "Feature",
  "properties": {
    "iso:country":"CA",
    "sg:city":"Mississauga",
    "sg:classifiers":[
        {
            "category":"Professional",
            "subcategory":"Lawyer & Legal Services",
            "type":"Services"
        }
    ],
    "sg:phone":"+1 905 890 7700",
    "sg:postcode":"L4Z 2G7",
    "sg:province":"ON",
    "sg:tags":[
        "attorney"
    ],
    "wof:name":"Keel Cottrelle",
    "wof:placetype":"venue"
},
  "geometry": {"coordinates":[-79.6690826416,43.6204490662],"type":"Point"}
}