{
  "type": "Feature",
  "properties": {
    "addr:full":"8624 Rue Du Creusot Saint-Leonard QC H1P 2A7",
    "addr:housenumber":"8624",
    "addr:postcode":"h1p 2a7",
    "addr:street":"Rue Du Creusot",
    "iso:country":"CA",
    "sg:address":"8624 Rue Du Creusot",
    "sg:city":"Saint-Leonard",
    "sg:classifiers":[
        {
            "category":"Manufacturing",
            "subcategory":"Printing",
            "type":"Manufacturing & Wholesale Goods"
        }
    ],
    "sg:phone":"+1 514 321 5877",
    "sg:postcode":"H1P 2A7",
    "sg:province":"QC",
    "sg:tags":[
        "bookbinder"
    ],
    "wof:name":"Reliure Leblanc Inc",
    "wof:placetype":"venue"
},
  "geometry": {"coordinates":[-73.589127,45.6008],"type":"Point"}
}