{
  "type": "Feature",
  "properties": {
    "addr:full":"Winnipeg MB R3C 0E2",
    "addr:postcode":"r3c 0e2",
    "iso:country":"CA",
    "sg:city":"Winnipeg",
    "sg:classifiers":[
        {
            "category":"Personal",
            "type":"Services"
        }
    ],
    "sg:phone":"+1 204 943 8635",
    "sg:postcode":"R3C 0E2",
    "sg:province":"MB",
    "sg:tags":[
        "therapist",
        "massage"
    ],
    "wof:name":"Ankyo Therapeutic Massage",
    "wof:placetype":"venue"
},
  "geometry": {"coordinates":[-97.1491775513,49.8918266296],"type":"Point"}
}