{
  "type": "Feature",
  "properties": {
    "addr:full":"8310 118 Ave NW Edmonton AB T5B 0S5",
    "addr:housenumber":"8310",
    "addr:postcode":"t5b 0s5",
    "addr:street":"118 Ave Nw",
    "iso:country":"CA",
    "sg:address":"8310 118 Ave NW",
    "sg:city":"Edmonton",
    "sg:classifiers":[
        {
            "category":"Wholesale",
            "subcategory":"Electrical",
            "type":"Manufacturing & Wholesale Goods"
        }
    ],
    "sg:phone":"+1 780 474 5699",
    "sg:postcode":"T5B 0S5",
    "sg:province":"AB",
    "sg:tags":[
        "appliance"
    ],
    "wof:name":"Certified Home Appliance",
    "wof:placetype":"venue"
},
  "geometry": {"coordinates":[-113.46931499999999,53.570599],"type":"Point"}
}