{
  "type": "Feature",
  "properties": {
    "iso:country":"CA",
    "sg:address":"8310 118 Ave NW",
    "sg:city":"Edmonton",
    "sg:classifiers":[
        {
            "category":"Wholesale",
            "subcategory":"Electrical",
            "type":"Manufacturing & Wholesale Goods"
        }
    ],
    "sg:phone":"+1 780 474 5699",
    "sg:postcode":"T5B 0S5",
    "sg:province":"AB",
    "sg:tags":[
        "appliance"
    ],
    "wof:name":"Certified Home Appliance",
    "wof:placetype":"venue"
},
  "geometry": {"coordinates":[-113.469315,53.570599],"type":"Point"}
}