{
  "type": "Feature",
  "properties": {
    "addr:full":"942 Rue Galt E Sherbrooke QC J1G 1Y5",
    "addr:housenumber":"942",
    "addr:postcode":"j1g 1y5",
    "addr:street":"Rue Galt E",
    "iso:country":"CA",
    "sg:address":"942 Rue Galt E",
    "sg:city":"Sherbrooke",
    "sg:classifiers":[
        {
            "category":"Restaurant",
            "type":"Food & Drink"
        }
    ],
    "sg:phone":"+1 819 566 7447",
    "sg:postcode":"J1G 1Y5",
    "sg:province":"QC",
    "sg:tags":[
        "sandwich"
    ],
    "wof:name":"Subway Sandwiches & Salads",
    "wof:placetype":"venue"
},
  "geometry": {"coordinates":[-71.867958,45.396099],"type":"Point"}
}