{
  "type": "Feature",
  "properties": {
    "addr:full":"1773 Main St Moncton NB E1E 1H3",
    "addr:housenumber":"1773",
    "addr:postcode":"e1e 1h3",
    "addr:street":"Main St",
    "iso:country":"CA",
    "sg:address":"1773 Main St",
    "sg:city":"Moncton",
    "sg:classifiers":[
        {
            "category":"Home & Garden",
            "subcategory":"Building Materials",
            "type":"Retail Goods"
        }
    ],
    "sg:phone":"+1 506 853 0098",
    "sg:postcode":"E1E 1H3",
    "sg:province":"NB",
    "sg:tags":[
        "glass",
        "window",
        "plate"
    ],
    "wof:name":"Apple Auto Glass",
    "wof:placetype":"venue"
},
  "geometry": {"coordinates":[-64.7984390259,46.0777053833],"type":"Point"}
}