{
  "type": "Feature",
  "properties": {
    "iso:country":"CA",
    "sg:city":"Vancouver",
    "sg:classifiers":[
        {
            "category":"Real Estate",
            "subcategory":"Real Estate Operator",
            "type":"Services"
        }
    ],
    "sg:phone":"+1 604 731 6579",
    "sg:postcode":"V6K 2E8",
    "sg:province":"BC",
    "sg:tags":[
        "apartment"
    ],
    "wof:name":"Larch Way Gardens",
    "wof:placetype":"venue"
},
  "geometry": {"coordinates":[-123.161560059,49.2641372681],"type":"Point"}
}