{
  "type": "Feature",
  "properties": {
    "addr:full":"5330 Creditview Rd Mississauga ON L5M 5N5",
    "addr:housenumber":"5330",
    "addr:postcode":"l5m 5n5",
    "addr:street":"Creditview Rd",
    "iso:country":"CA",
    "sg:address":"5330 Creditview Rd",
    "sg:city":"Mississauga",
    "sg:classifiers":[
        {
            "category":"Museum",
            "subcategory":"Botanical Garden",
            "type":"Entertainment"
        }
    ],
    "sg:phone":"+1 905 542 9453",
    "sg:postcode":"L5M 5N5",
    "sg:province":"ON",
    "sg:tags":[
        "center",
        "nature"
    ],
    "wof:name":"Assisi Animal & Bird Sanctuary",
    "wof:placetype":"venue"
},
  "geometry": {"coordinates":[-79.69429,43.584396],"type":"Point"}
}