{
  "type": "Feature",
  "properties": {
    "addr:full":"Mississauga ON L5R 3G5",
    "addr:postcode":"l5r 3g5",
    "iso:country":"CA",
    "sg:city":"Mississauga",
    "sg:classifiers":[
        {
            "category":"Wholesale",
            "subcategory":"Groceries",
            "type":"Manufacturing & Wholesale Goods"
        }
    ],
    "sg:phone":"+1 905 501 8383",
    "sg:postcode":"L5R 3G5",
    "sg:province":"ON",
    "sg:tags":[
        "food",
        "broker"
    ],
    "wof:name":"Miller & Smith Foods Inc",
    "wof:placetype":"venue"
},
  "geometry": {"coordinates":[-79.673607,43.621742],"type":"Point"}
}