{
  "type": "Feature",
  "properties": {
    "iso:country":"CA",
    "sg:address":"401 3E Rue",
    "sg:city":"Chibougamau",
    "sg:classifiers":[
        {
            "category":"Insurance",
            "subcategory":"Insurance Agent",
            "type":"Services"
        }
    ],
    "sg:phone":"+1 418 748 8131",
    "sg:postcode":"G8P 1N6",
    "sg:province":"QC",
    "wof:name":"Assurances & Svc Financiers",
    "wof:placetype":"venue"
},
  "geometry": {"coordinates":[-74.3600845337,49.9137840271],"type":"Point"}
}