{
  "type": "Feature",
  "properties": {
    "addr:full":"3485 Semenyk Crt Mississauga ON L5C 4P9",
    "addr:housenumber":"3485",
    "addr:postcode":"l5c 4p9",
    "addr:street":"Semenyk Crt",
    "iso:country":"CA",
    "sg:address":"3485 Semenyk Crt",
    "sg:city":"Mississauga",
    "sg:classifiers":[
        {
            "category":"Retail",
            "subcategory":"Auto Rental",
            "type":"Services"
        }
    ],
    "sg:phone":"+1 905 276 9224",
    "sg:postcode":"L5C 4P9",
    "sg:province":"ON",
    "sg:tags":[
        "renting",
        "automobile"
    ],
    "wof:name":"Advantage Car & Truck Rentals",
    "wof:placetype":"venue"
},
  "geometry": {"coordinates":[-79.6533737183,43.568813324],"type":"Point"}
}