{
  "type": "Feature",
  "properties": {
    "addr:full":"Tilbury ON N0P 2L0",
    "addr:postcode":"n0p 2l0",
    "addr:street":"Tilbury",
    "iso:country":"CA",
    "sg:city":"Tilbury",
    "sg:classifiers":[
        {
            "category":"Retail",
            "subcategory":"Auto Repair",
            "type":"Services"
        }
    ],
    "sg:phone":"+1 519 682 1853",
    "sg:postcode":"N0P 2L0",
    "sg:province":"ON",
    "sg:tags":[
        "glass",
        "coating",
        "tinting"
    ],
    "wof:name":"Sun Out Window Tinting",
    "wof:placetype":"venue"
},
  "geometry": {"coordinates":[-82.436668,42.26313],"type":"Point"}
}