{
  "type": "Feature",
  "properties": {
    "addr:full":"44 Rue DE L'Eglise Vaudreuil-Dorion QC J7V 1W4",
    "addr:housenumber":"44",
    "addr:postcode":"j7v 1w4",
    "addr:street":"Rue De L'Eglise",
    "iso:country":"CA",
    "sg:address":"44 Rue DE L'Eglise",
    "sg:city":"Vaudreuil-Dorion",
    "sg:classifiers":[
        {
            "category":"Government",
            "subcategory":"Office",
            "type":"Public Place"
        }
    ],
    "sg:phone":"+1 450 455 1133",
    "sg:postcode":"J7V 1W4",
    "sg:province":"QC",
    "sg:tags":[
        "village"
    ],
    "wof:name":"Vaudreuil-Sur-Le-Lac Hotel-Vl",
    "wof:placetype":"venue"
},
  "geometry": {"coordinates":[-74.0362701416,45.4236755371],"type":"Point"}
}