{
  "type": "Feature",
  "properties": {
    "addr:full":"394 Rang Des Chutes Saint-Patrice-DE-Beaurivage QC G0S 1B0",
    "addr:housenumber":"394",
    "addr:postcode":"g0s 1b0",
    "addr:street":"Rang Des Chutes",
    "iso:country":"CA",
    "sg:address":"394 Rang Des Chutes",
    "sg:city":"Saint-Patrice-DE-Beaurivage",
    "sg:classifiers":[
        {
            "category":"Retail",
            "subcategory":"Repair Shop",
            "type":"Services"
        }
    ],
    "sg:phone":"+1 418 596 2511",
    "sg:postcode":"G0S 1B0",
    "sg:province":"QC",
    "sg:tags":[
        "welding"
    ],
    "wof:name":"Mag Metal Inc",
    "wof:placetype":"venue"
},
  "geometry": {"coordinates":[-71.26966899999999,46.410885],"type":"Point"}
}