{
  "type": "Feature",
  "properties": {
    "addr:full":"3116 Parsons Rd NW Edmonton AB T6N 1L6",
    "addr:housenumber":"3116",
    "addr:postcode":"t6n 1l6",
    "addr:street":"Parsons Rd Nw",
    "iso:country":"CA",
    "sg:address":"3116 Parsons Rd NW",
    "sg:city":"Edmonton",
    "sg:classifiers":[
        {
            "category":"Building & Trades",
            "subcategory":"Equipment Rental",
            "type":"Services"
        }
    ],
    "sg:phone":"+1 780 433 3896",
    "sg:postcode":"T6N 1L6",
    "sg:province":"AB",
    "sg:tags":[
        "player",
        "recorder",
        "video"
    ],
    "wof:name":"Cho Eun Video",
    "wof:placetype":"venue"
},
  "geometry": {"coordinates":[-113.486328125,53.4630508423],"type":"Point"}
}