{
  "type": "Feature",
  "properties": {
    "addr:full":"65 Marr Rd Rothesay NB E2E 3J9",
    "addr:housenumber":"65",
    "addr:postcode":"e2e 3j9",
    "addr:street":"Marr Rd",
    "iso:country":"CA",
    "sg:address":"65 Marr Rd",
    "sg:city":"Rothesay",
    "sg:classifiers":[
        {
            "category":"Building & Trades",
            "subcategory":"Landscaping Services",
            "type":"Services"
        }
    ],
    "sg:phone":"+1 506 849 4124",
    "sg:postcode":"E2E 3J9",
    "sg:province":"NB",
    "sg:tags":[
        "landscape",
        "contractor"
    ],
    "wof:name":"Urban Landscaping Ltd",
    "wof:placetype":"venue"
},
  "geometry": {"coordinates":[-65.972084,45.392319],"type":"Point"}
}