{
  "type": "Feature",
  "properties": {
    "addr:full":"590 Bank St Ottawa ON K1S 3T3",
    "addr:housenumber":"590",
    "addr:postcode":"k1s 3t3",
    "addr:street":"Bank St",
    "iso:country":"CA",
    "sg:address":"590 Bank St",
    "sg:city":"Ottawa",
    "sg:classifiers":[
        {
            "category":"Shopping",
            "type":"Retail Goods"
        }
    ],
    "sg:phone":"+1 613 238 3803",
    "sg:postcode":"K1S 3T3",
    "sg:province":"ON",
    "sg:tags":[
        "material",
        "artist",
        "supply"
    ],
    "wof:name":"Artguise",
    "wof:placetype":"venue"
},
  "geometry": {"coordinates":[-75.69115447999999,45.4077377319],"type":"Point"}
}