{
  "type": "Feature",
  "properties": {
    "addr:full":"Moonstone ON L0K 1N0",
    "addr:postcode":"l0k 1n0",
    "iso:country":"CA",
    "sg:city":"Moonstone",
    "sg:classifiers":[
        {
            "category":"Manufacturing",
            "subcategory":"Buildings",
            "type":"Manufacturing & Wholesale Goods"
        }
    ],
    "sg:phone":"+1 705 835 3721",
    "sg:postcode":"L0K 1N0",
    "sg:province":"ON",
    "sg:tags":[
        "home",
        "log",
        "cabin"
    ],
    "wof:name":"Moonstone Timber Frame",
    "wof:placetype":"venue"
},
  "geometry": {"coordinates":[-79.66194915769999,44.6561050415],"type":"Point"}
}