{
  "type": "Feature",
  "properties": {
    "addr:full":"6351 Ranchview Dr NW Calgary AB T3G 1B5",
    "addr:housenumber":"6351",
    "addr:postcode":"t3g 1b5",
    "addr:street":"Ranchview Dr Nw",
    "iso:country":"CA",
    "sg:address":"6351 Ranchview Dr NW",
    "sg:city":"Calgary",
    "sg:classifiers":[
        {
            "category":"Organizations",
            "subcategory":"Religious Organization",
            "type":"Services"
        }
    ],
    "sg:phone":"+1 403 239 0104",
    "sg:postcode":"T3G 1B5",
    "sg:province":"AB",
    "sg:tags":[
        "church"
    ],
    "wof:name":"St James Anglican Church",
    "wof:placetype":"venue"
},
  "geometry": {"coordinates":[-114.18208300000001,51.115105],"type":"Point"}
}