{
  "type": "Feature",
  "properties": {
    "addr:full":"6 Bayside Dr Saint John NB E2J 1A2",
    "addr:housenumber":"6",
    "addr:postcode":"e2j 1a2",
    "addr:street":"Bayside Dr",
    "iso:country":"CA",
    "sg:address":"6 Bayside Dr",
    "sg:city":"Saint John",
    "sg:classifiers":[
        {
            "category":"Building & Trades",
            "subcategory":"Construction",
            "type":"Services"
        }
    ],
    "sg:phone":"+1 506 648 9897",
    "sg:postcode":"E2J 1A2",
    "sg:province":"NB",
    "sg:tags":[
        "painter"
    ],
    "wof:name":"Supreme Painting & Decorating",
    "wof:placetype":"venue"
},
  "geometry": {"coordinates":[-66.0425567627,45.2866096497],"type":"Point"}
}