{
  "type": "Feature",
  "properties": {
    "addr:full":"PO Box 43 Crossfield AB T0M 0S0",
    "addr:housenumber":"po box 43 crossfield ab",
    "addr:postcode":"t0m 0s0",
    "iso:country":"CA",
    "sg:address":"PO Box 43",
    "sg:city":"Crossfield",
    "sg:classifiers":[
        {
            "category":"Building & Trades",
            "subcategory":"Construction",
            "type":"Services"
        }
    ],
    "sg:phone":"+1 403 948 5274",
    "sg:postcode":"T0M 0S0",
    "sg:province":"AB",
    "sg:tags":[
        "excavating",
        "contractor"
    ],
    "wof:name":"Double H Excavating Ltd",
    "wof:placetype":"venue"
},
  "geometry": {"coordinates":[-114.02707700000001,51.429539],"type":"Point"}
}