{
  "type": "Feature",
  "properties": {
    "addr:full":"309 Centre St Assiniboia SK S0H 0B0",
    "addr:housenumber":"309",
    "addr:postcode":"s0h 0b0",
    "addr:street":"Centre St",
    "iso:country":"CA",
    "sg:address":"309 Centre St",
    "sg:city":"Assiniboia",
    "sg:classifiers":[
        {
            "category":"Local Transit",
            "type":"Transportation"
        }
    ],
    "sg:phone":"+1 306 642 4444",
    "sg:postcode":"S0H 0B0",
    "sg:province":"SK",
    "sg:tags":[
        "bus",
        "line"
    ],
    "wof:name":"Bus Depot-Stc Lines",
    "wof:placetype":"venue"
},
  "geometry": {"coordinates":[-105.992164612,49.6317024231],"type":"Point"}
}