{
  "type": "Feature",
  "properties": {
    "addr:full":"Toronto ON M5T 3B3",
    "addr:postcode":"m5t 3b3",
    "iso:country":"CA",
    "sg:city":"Toronto",
    "sg:classifiers":[
        {
            "category":"Shopping",
            "subcategory":"Books",
            "type":"Retail Goods"
        }
    ],
    "sg:phone":"+1 416 597 6593",
    "sg:postcode":"M5T 3B3",
    "sg:province":"ON",
    "sg:tags":[
        "comic"
    ],
    "wof:name":"Kikiwai Anime",
    "wof:placetype":"venue"
},
  "geometry": {"coordinates":[-79.39757537840001,43.6509819031],"type":"Point"}
}