{
  "type": "Feature",
  "properties": {
    "addr:full":"60 West Dr Brampton ON L6T 4W7",
    "addr:housenumber":"60",
    "addr:postcode":"l6t 4w7",
    "addr:street":"West Dr",
    "iso:country":"CA",
    "sg:address":"60 West Dr",
    "sg:city":"Brampton",
    "sg:classifiers":[
        {
            "category":"Manufacturing",
            "subcategory":"Chemicals & Compounds",
            "type":"Manufacturing & Wholesale Goods"
        }
    ],
    "sg:phone":"+1 905 454 4466",
    "sg:postcode":"L6T 4W7",
    "sg:province":"ON",
    "sg:tags":[
        "starch"
    ],
    "wof:name":"Nacan Products Ltd",
    "wof:placetype":"venue"
},
  "geometry": {"coordinates":[-79.72348,43.702572],"type":"Point"}
}