{
  "type": "Feature",
  "properties": {
    "addr:full":"59 Rg 5 E Evain QC J0Z 1Y0",
    "addr:housenumber":"59;5 e",
    "addr:postcode":"j0z 1y0",
    "addr:street":"Rg;Evain",
    "iso:country":"CA",
    "sg:address":"59 Rg 5 E",
    "sg:city":"Evain",
    "sg:classifiers":[
        {
            "category":"Wholesale",
            "subcategory":"Electrical",
            "type":"Manufacturing & Wholesale Goods"
        }
    ],
    "sg:phone":"+1 819 768 5401",
    "sg:postcode":"J0Z 1Y0",
    "sg:province":"QC",
    "sg:tags":[
        "communication",
        "radio",
        "system"
    ],
    "wof:name":"Entreprises En Electronique 48",
    "wof:placetype":"venue"
},
  "geometry": {"coordinates":[-79.2306976318,48.322769165],"type":"Point"}
}