{
  "type": "Feature",
  "properties": {
    "addr:full":"Beauceville QC G5X 1J2",
    "addr:postcode":"g5x 1j2",
    "iso:country":"CA",
    "sg:city":"Beauceville",
    "sg:classifiers":[
        {
            "category":"Health Services",
            "subcategory":"Doctor",
            "type":"Services"
        }
    ],
    "sg:phone":"+1 418 774 3100",
    "sg:postcode":"G5X 1J2",
    "sg:province":"QC",
    "sg:tags":[
        "physician",
        "surgeon"
    ],
    "wof:name":"Roy, Bruno MD",
    "wof:placetype":"venue"
},
  "geometry": {"coordinates":[-70.7729187012,46.2074661255],"type":"Point"}
}