{
  "type": "Feature",
  "properties": {
    "addr:full":"1095 Brazeau Rd Clarence Creek ON K0A 1N0",
    "addr:housenumber":"1095",
    "addr:postcode":"k0a 1n0",
    "addr:street":"Brazeau Rd",
    "iso:country":"CA",
    "sg:address":"1095 Brazeau Rd",
    "sg:city":"Clarence Creek",
    "sg:classifiers":[
        {
            "category":"Manufacturing",
            "subcategory":"Signs",
            "type":"Manufacturing & Wholesale Goods"
        }
    ],
    "sg:phone":"+1 613 295 7446",
    "sg:postcode":"K0A 1N0",
    "sg:province":"ON",
    "wof:name":"Louis Xvi Signs",
    "wof:placetype":"venue"
},
  "geometry": {"coordinates":[-75.2133102417,45.5298347473],"type":"Point"}
}