{
  "type": "Feature",
  "properties": {
    "iso:country":"CA",
    "sg:address":"3190 Rue Delaunay",
    "sg:city":"Laval",
    "sg:classifiers":[
        {
            "category":"Manufacturing",
            "subcategory":"Printing",
            "type":"Manufacturing & Wholesale Goods"
        }
    ],
    "sg:phone":"+1 450 973 8282",
    "sg:postcode":"H7L 5E1",
    "sg:province":"QC",
    "sg:tags":[
        "printer"
    ],
    "wof:name":"Imprimerie Groupe Deux Inc",
    "wof:placetype":"venue"
},
  "geometry": {"coordinates":[-73.75711099999999,45.586258],"type":"Point"}
}