{
  "type": "Feature",
  "properties": {
    "addr:full":"69 Yorkville Ave Toronto ON M5R 1B8",
    "addr:housenumber":"69",
    "addr:postcode":"m5r 1b8",
    "addr:street":"Yorkville Ave",
    "iso:country":"CA",
    "sg:address":"69 Yorkville Ave",
    "sg:city":"Toronto",
    "sg:classifiers":[
        {
            "category":"Arts & Performance",
            "subcategory":"Theater",
            "type":"Entertainment"
        }
    ],
    "sg:phone":"+1 416 966 6900",
    "sg:postcode":"M5R 1B8",
    "sg:province":"ON",
    "sg:tags":[
        "television",
        "station",
        "representative"
    ],
    "wof:name":"Media Alternatives",
    "wof:placetype":"venue"
},
  "geometry": {"coordinates":[-79.39083862299999,43.6711502075],"type":"Point"}
}