{
  "type": "Feature",
  "properties": {
    "addr:full":"431 Rue Principale O Magog QC J1X 2B2",
    "addr:housenumber":"431",
    "addr:postcode":"j1x 2b2",
    "addr:street":"Rue Principale O",
    "iso:country":"CA",
    "sg:address":"431 Rue Principale O",
    "sg:city":"Magog",
    "sg:classifiers":[
        {
            "category":"Banks & Credit Unions",
            "subcategory":"Bank",
            "type":"Services"
        }
    ],
    "sg:phone":"+1 819 843 6531",
    "sg:postcode":"J1X 2B2",
    "sg:province":"QC",
    "wof:name":"Cibc",
    "wof:placetype":"venue"
},
  "geometry": {"coordinates":[-72.1358947754,45.2616157532],"type":"Point"}
}