{
  "type": "Feature",
  "properties": {
    "addr:full":"PO Box 366 Koostatak MB R0C 1S0",
    "addr:housenumber":"po",
    "addr:postcode":"r0c 1s0",
    "addr:street":"Box 366 Koostatak",
    "iso:country":"CA",
    "sg:address":"PO Box 366",
    "sg:city":"Koostatak",
    "sg:classifiers":[
        {
            "category":"Health Services",
            "subcategory":"Nursing And Care Facility",
            "type":"Services"
        }
    ],
    "sg:phone":"+1 204 645 2811",
    "sg:postcode":"R0C 1S0",
    "sg:province":"MB",
    "sg:tags":[
        "personal",
        "home"
    ],
    "wof:name":"Ochekwi-Sipi First Nation",
    "wof:placetype":"venue"
},
  "geometry": {"coordinates":[-97.37409210209999,51.4423370361],"type":"Point"}
}