{
  "type": "Feature",
  "properties": {
    "addr:full":"400 Av DE L'Hotel-Dieu Sorel-Tracy QC J3P 1N5",
    "addr:postcode":"j3p 1n5",
    "addr:street":"400 Av De L'Hotel-Dieu",
    "iso:country":"CA",
    "sg:address":"400 Av DE L'Hotel-Dieu",
    "sg:city":"Sorel-Tracy",
    "sg:classifiers":[
        {
            "category":"Health Services",
            "subcategory":"Hospital",
            "type":"Services"
        }
    ],
    "sg:phone":"+1 450 746 6000",
    "sg:postcode":"J3P 1N5",
    "sg:province":"QC",
    "wof:name":"Hopital Hotel-Dieu DE Sorel",
    "wof:placetype":"venue"
},
  "geometry": {"coordinates":[-73.114288,46.042217],"type":"Point"}
}