{
  "type": "Feature",
  "properties": {
    "addr:full":"4548 Marine Ave Powell River BC V8A 2K4",
    "addr:housenumber":"4548",
    "addr:postcode":"v8a 2k4",
    "addr:street":"Marine Ave Powell",
    "iso:country":"CA",
    "sg:address":"4548 Marine Ave",
    "sg:city":"Powell River",
    "sg:classifiers":[
        {
            "category":"Shopping",
            "subcategory":"Clothing, Apparel, & Fashions",
            "type":"Retail Goods"
        }
    ],
    "sg:phone":"+1 604 485 9069",
    "sg:postcode":"V8A 2K4",
    "sg:province":"BC",
    "sg:tags":[
        "dressmaker"
    ],
    "wof:name":"Betty Condon Dressmaking",
    "wof:placetype":"venue"
},
  "geometry": {"coordinates":[-124.52771,49.839005],"type":"Point"}
}