{
  "type": "Feature",
  "properties": {
    "iso:country":"CA",
    "sg:address":"195 Rue DE Louvain O",
    "sg:city":"Montreal",
    "sg:classifiers":[
        {
            "category":"Shopping",
            "subcategory":"Clothing, Apparel, & Fashions",
            "type":"Retail Goods"
        }
    ],
    "sg:phone":"+1 514 858 6794",
    "sg:postcode":"H2N 1A3",
    "sg:province":"QC",
    "sg:tags":[
        "sweater"
    ],
    "wof:name":"Ilanco Knitting Inc",
    "wof:placetype":"venue"
},
  "geometry": {"coordinates":[-73.656639,45.542576],"type":"Point"}
}