{
  "type": "Feature",
  "properties": {
    "addr:full":"1471 Clearbrook Rd Abbotsford BC V2T 5X2",
    "addr:housenumber":"1471",
    "addr:postcode":"v2t 5x2",
    "addr:street":"Clearbrook Rd",
    "iso:country":"CA",
    "sg:address":"1471 Clearbrook Rd",
    "sg:city":"Abbotsford",
    "sg:classifiers":[
        {
            "category":"Professional",
            "subcategory":"Lawyer & Legal Services",
            "type":"Services"
        }
    ],
    "sg:phone":"+1 604 504 7472",
    "sg:postcode":"V2T 5X2",
    "sg:province":"BC",
    "sg:tags":[
        "attorney"
    ],
    "wof:name":"Neill Brown & Assoc",
    "wof:placetype":"venue"
},
  "geometry": {"coordinates":[-122.337906,49.028446],"type":"Point"}
}