{
  "type": "Feature",
  "properties": {
    "addr:full":"North Battleford SK S9A 0V6",
    "addr:postcode":"s9a 0v6",
    "iso:country":"CA",
    "sg:city":"North Battleford",
    "sg:classifiers":[
        {
            "category":"Personal",
            "subcategory":"Beauty Salon",
            "type":"Services"
        }
    ],
    "sg:phone":"+1 306 445 1277",
    "sg:postcode":"S9A 0V6",
    "sg:province":"SK",
    "wof:name":"Styles By Lana",
    "wof:placetype":"venue"
},
  "geometry": {"coordinates":[-108.299285889,52.7756271362],"type":"Point"}
}