{
  "type": "Feature",
  "properties": {
    "addr:full":"8 Main St Kearney ON P0A 1M0",
    "addr:housenumber":"8",
    "addr:postcode":"p0a 1m0",
    "addr:street":"Main St",
    "iso:country":"CA",
    "sg:address":"8 Main St",
    "sg:city":"Kearney",
    "sg:classifiers":[
        {
            "category":"Education",
            "subcategory":"Library",
            "type":"Public Place"
        }
    ],
    "sg:phone":"+1 705 636 5849",
    "sg:postcode":"P0A 1M0",
    "sg:province":"ON",
    "wof:name":"Kearney Public Library",
    "wof:placetype":"venue"
},
  "geometry": {"coordinates":[-79.227478,45.55798],"type":"Point"}
}