{
  "type": "Feature",
  "properties": {
    "iso:country":"CA",
    "sg:address":"1137 Ch Royal",
    "sg:city":"Saint-Pierre-Ile-D'Orleans",
    "sg:classifiers":[
        {
            "category":"Freight",
            "type":"Transportation"
        }
    ],
    "sg:phone":"+1 418 828 2431",
    "sg:postcode":"G0A 4E0",
    "sg:province":"QC",
    "sg:tags":[
        "warehouse",
        "storage"
    ],
    "wof:name":"Entrepot Frigorifique Orleans",
    "wof:placetype":"venue"
},
  "geometry": {"coordinates":[-70.9134216309,46.9094734192],"type":"Point"}
}