{
  "type": "Feature",
  "properties": {
    "iso:country":"CA",
    "sg:address":"121 16E Rue",
    "sg:city":"Roxboro",
    "sg:classifiers":[
        {
            "category":"Health Services",
            "subcategory":"Doctor",
            "type":"Services"
        }
    ],
    "sg:phone":"+1 514 684 1855",
    "sg:postcode":"H8Y 1P1",
    "sg:province":"QC",
    "sg:tags":[
        "dentist"
    ],
    "wof:name":"Legault, Mylene DDS",
    "wof:placetype":"venue"
},
  "geometry": {"coordinates":[-73.8067703247,45.4985122681],"type":"Point"}
}