{
  "type": "Feature",
  "properties": {
    "addr:full":"Regina SK S4P 0W5",
    "addr:postcode":"s4p 0w5",
    "iso:country":"CA",
    "sg:city":"Regina",
    "sg:classifiers":[
        {
            "category":"Health Services",
            "subcategory":"Doctor",
            "type":"Services"
        }
    ],
    "sg:phone":"+1 306 766 6955",
    "sg:postcode":"S4P 0W5",
    "sg:province":"SK",
    "sg:tags":[
        "physician",
        "surgeon"
    ],
    "wof:name":"Datta, Biswa MD",
    "wof:placetype":"venue"
},
  "geometry": {"coordinates":[-104.602020264,50.443939209],"type":"Point"}
}