{
  "type": "Feature",
  "properties": {
    "addr:full":"382 Water St Peterborough ON K9H 3L6",
    "addr:housenumber":"382",
    "addr:postcode":"k9h 3l6",
    "addr:street":"Water St",
    "iso:country":"CA",
    "sg:address":"382 Water St",
    "sg:city":"Peterborough",
    "sg:classifiers":[
        {
            "category":"Shopping",
            "subcategory":"Used Merchandise",
            "type":"Retail Goods"
        }
    ],
    "sg:phone":"+1 705 742 4514",
    "sg:postcode":"K9H 3L6",
    "sg:province":"ON",
    "sg:tags":[
        "book",
        "rare",
        "dealer"
    ],
    "wof:name":"Mark Jokinen Books",
    "wof:placetype":"venue"
},
  "geometry": {"coordinates":[-78.31871,44.305386],"type":"Point"}
}