{
  "type": "Feature",
  "properties": {
    "iso:country":"CA",
    "sg:address":"153 Mill St",
    "sg:city":"Creemore",
    "sg:classifiers":[
        {
            "category":"Home & Garden",
            "subcategory":"Hardware",
            "type":"Retail Goods"
        }
    ],
    "sg:phone":"+1 705 466 2547",
    "sg:postcode":"L0M 1G0",
    "sg:province":"ON",
    "wof:name":"Creemore Home Hardware",
    "wof:placetype":"venue"
},
  "geometry": {"coordinates":[-80.1056060791,44.3255767822],"type":"Point"}
}