{
  "type": "Feature",
  "properties": {
    "addr:full":"1808 5th Ave W Vancouver BC V6J 1P3",
    "addr:housenumber":"1808",
    "addr:postcode":"v6j 1p3",
    "addr:street":"5Th Ave W",
    "iso:country":"CA",
    "sg:address":"1808 5th Ave W",
    "sg:city":"Vancouver",
    "sg:classifiers":[
        {
            "category":"Health Services",
            "subcategory":"Doctor",
            "type":"Services"
        }
    ],
    "sg:phone":"+1 604 734 8880",
    "sg:postcode":"V6J 1P3",
    "sg:province":"BC",
    "sg:tags":[
        "dentist"
    ],
    "wof:name":"Fifth Avenue Dental Ctr",
    "wof:placetype":"venue"
},
  "geometry": {"coordinates":[-123.146018982,49.2670402527],"type":"Point"}
}