{
  "type": "Feature",
  "properties": {
    "addr:full":"261 Boul Harwood Vaudreuil-Dorion QC J7V 1Y3",
    "addr:housenumber":"261",
    "addr:postcode":"j7v 1y3",
    "addr:street":"Boul Harwood",
    "iso:country":"CA",
    "sg:address":"261 Boul Harwood",
    "sg:city":"Vaudreuil-Dorion",
    "sg:classifiers":[
        {
            "category":"Retail",
            "subcategory":"Auto Repair",
            "type":"Services"
        }
    ],
    "sg:phone":"+1 450 455 3901",
    "sg:postcode":"J7V 1Y3",
    "sg:province":"QC",
    "sg:tags":[
        "repairing",
        "automobile"
    ],
    "wof:name":"Dorion Alignement",
    "wof:placetype":"venue"
},
  "geometry": {"coordinates":[-74.01499176030001,45.3817138672],"type":"Point"}
}