{
  "type": "Feature",
  "properties": {
    "addr:full":"Montreal QC H3T 1Y3",
    "addr:postcode":"h3t 1y3",
    "iso:country":"CA",
    "sg:city":"Montreal",
    "sg:classifiers":[
        {
            "category":"Health Services",
            "subcategory":"Medical Lab",
            "type":"Services"
        }
    ],
    "sg:phone":"+1 514 738 5306",
    "sg:postcode":"H3T 1Y3",
    "sg:province":"QC",
    "sg:tags":[
        "x"
    ],
    "wof:name":"Cote Des Neiges Radiological",
    "wof:placetype":"venue"
},
  "geometry": {"coordinates":[-73.61911773680001,45.4949493408],"type":"Point"}
}