{
  "type": "Feature",
  "properties": {
    "iso:country":"CA",
    "sg:address":"1074 Av Cartier # 1",
    "sg:city":"Quebec",
    "sg:classifiers":[
        {
            "category":"Shopping",
            "subcategory":"Clothing, Apparel, & Fashions",
            "type":"Retail Goods"
        }
    ],
    "sg:phone":"+1 418 525 8408",
    "sg:postcode":"G1R 2S5",
    "sg:province":"QC",
    "sg:tags":[
        "dressmaker"
    ],
    "wof:name":"Boutique L'Idee A Coudre Enr",
    "wof:placetype":"venue"
},
  "geometry": {"coordinates":[-71.225822,46.803444],"type":"Point"}
}