{
  "type": "Feature",
  "properties": {
    "addr:full":"595 Bay St Toronto ON M5G 2C2",
    "addr:housenumber":"595",
    "addr:postcode":"m5g 2c2",
    "addr:street":"Bay St",
    "iso:country":"CA",
    "sg:address":"595 Bay St",
    "sg:city":"Toronto",
    "sg:classifiers":[
        {
            "category":"Shopping",
            "subcategory":"Computers & Home Electronics",
            "type":"Retail Goods"
        }
    ],
    "sg:phone":"+1 416 351 7065",
    "sg:postcode":"M5G 2C2",
    "sg:province":"ON",
    "sg:tags":[
        "game",
        "video"
    ],
    "wof:name":"Game Shack",
    "wof:placetype":"venue"
},
  "geometry": {"coordinates":[-79.38372,43.656143],"type":"Point"}
}