{
  "type": "Feature",
  "properties": {
    "iso:country":"CA",
    "sg:address":"108 Rue Saint-Charles # 203",
    "sg:city":"Saint-Jean-Sur-Richelieu",
    "sg:classifiers":[
        {
            "category":"Professional",
            "subcategory":"Lawyer & Legal Services",
            "type":"Services"
        }
    ],
    "sg:phone":"+1 450 346 4464",
    "sg:postcode":"J3B 2C1",
    "sg:province":"QC",
    "sg:tags":[
        "attorney"
    ],
    "wof:name":"Poirier, Luc",
    "wof:placetype":"venue"
},
  "geometry": {"coordinates":[-73.25441,45.307552],"type":"Point"}
}