{
  "type": "Feature",
  "properties": {
    "iso:country":"CA",
    "sg:address":"130 Dearborn Pl",
    "sg:city":"Waterloo",
    "sg:classifiers":[
        {
            "category":"Retail",
            "subcategory":"Auto Repair",
            "type":"Services"
        }
    ],
    "sg:phone":"+1 519 886 0561",
    "sg:postcode":"N2J 4N5",
    "sg:province":"ON",
    "sg:tags":[
        "automobile",
        "lubrication"
    ],
    "wof:name":"Jiffy Lube",
    "wof:placetype":"venue"
},
  "geometry": {"coordinates":[-80.516708374,43.4874038696],"type":"Point"}
}