{
  "type": "Feature",
  "properties": {
    "addr:full":"1280 Boul Wallberg Dolbeau-Mistassini QC G8L 1H1",
    "addr:housenumber":"1280",
    "addr:postcode":"g8l 1h1",
    "addr:street":"Boul Wallberg",
    "iso:country":"CA",
    "sg:address":"1280 Boul Wallberg",
    "sg:city":"Dolbeau-Mistassini",
    "sg:classifiers":[
        {
            "category":"Shopping",
            "subcategory":"Pharmacy",
            "type":"Retail Goods"
        }
    ],
    "sg:phone":"+1 418 276 0574",
    "sg:postcode":"G8L 1H1",
    "sg:province":"QC",
    "wof:name":"Uniprix",
    "wof:placetype":"venue"
},
  "geometry": {"coordinates":[-72.2277679443,48.8777618408],"type":"Point"}
}