{
  "type": "Feature",
  "properties": {
    "iso:country":"CA",
    "sg:address":"101 Baker St",
    "sg:city":"Nelson",
    "sg:classifiers":[
        {
            "category":"Organizations",
            "subcategory":"Labor Organization",
            "type":"Services"
        }
    ],
    "sg:phone":"+1 250 352 9223",
    "sg:postcode":"V1L 4H1",
    "sg:province":"BC",
    "wof:name":"West Kootenay Labour Council",
    "wof:placetype":"venue"
},
  "geometry": {"coordinates":[-117.299629211,49.4899215698],"type":"Point"}
}