{
  "type": "Feature",
  "properties": {
    "iso:country":"CA",
    "sg:address":"1795 Bantree St",
    "sg:city":"Ottawa",
    "sg:classifiers":[
        {
            "category":"Retail",
            "subcategory":"Car Wash",
            "type":"Services"
        }
    ],
    "sg:phone":"+1 613 749 2929",
    "sg:postcode":"K1B 4L6",
    "sg:province":"ON",
    "sg:tags":[
        "polishing",
        "washing"
    ],
    "wof:name":"Speedy Car Wash",
    "wof:placetype":"venue"
},
  "geometry": {"coordinates":[-75.6170883179,45.4061813354],"type":"Point"}
}