{
  "type": "Feature",
  "properties": {
    "addr:full":"201 Av Hotel DE Ville Shippagan NB E8S 1L1",
    "addr:housenumber":"201",
    "addr:postcode":"e8s 1l1",
    "addr:street":"Av Hotel De Ville",
    "iso:country":"CA",
    "sg:address":"201 Av Hotel DE Ville",
    "sg:city":"Shippagan",
    "sg:classifiers":[
        {
            "category":"Education",
            "subcategory":"School",
            "type":"Public Place"
        }
    ],
    "sg:phone":"+1 506 336 3000",
    "sg:postcode":"E8S 1L1",
    "sg:province":"NB",
    "wof:name":"Ecole Marie-Esther",
    "wof:placetype":"venue"
},
  "geometry": {"coordinates":[-64.71607208250001,47.7407493591],"type":"Point"}
}