{
  "type": "Feature",
  "properties": {
    "addr:full":"21 Acadia Ave Stellarton NS B0K 1S0",
    "addr:housenumber":"21",
    "addr:postcode":"b0k 1s0",
    "addr:street":"Acadia Ave",
    "iso:country":"CA",
    "sg:address":"21 Acadia Ave",
    "sg:city":"Stellarton",
    "sg:classifiers":[
        {
            "category":"Retail",
            "subcategory":"Auto Repair",
            "type":"Services"
        }
    ],
    "sg:phone":"+1 902 752 3948",
    "sg:postcode":"B0K 1S0",
    "sg:province":"NS",
    "sg:tags":[
        "repairing",
        "automobile"
    ],
    "wof:name":"Dwight's Service Station",
    "wof:placetype":"venue"
},
  "geometry": {"coordinates":[-62.6722640991,45.5584068298],"type":"Point"}
}