{
  "type": "Feature",
  "properties": {
    "addr:full":"3450 Dufferin St North York ON M6A 2V1",
    "addr:housenumber":"3450",
    "addr:postcode":"m6a 2v1",
    "addr:street":"Dufferin St",
    "iso:country":"CA",
    "sg:address":"3450 Dufferin St",
    "sg:city":"North York",
    "sg:classifiers":[
        {
            "category":"Shopping",
            "subcategory":"Gifts & Souvenirs",
            "type":"Retail Goods"
        }
    ],
    "sg:phone":"+1 416 785 8774",
    "sg:postcode":"M6A 2V1",
    "sg:province":"ON",
    "sg:tags":[
        "shop"
    ],
    "wof:name":"Fine Gift Shop",
    "wof:placetype":"venue"
},
  "geometry": {"coordinates":[-79.45738220210001,43.7250175476],"type":"Point"}
}