{
  "type": "Feature",
  "properties": {
    "iso:country":"CA",
    "sg:address":"11305 Rue Notre-Dame E",
    "sg:city":"Montreal-Est",
    "sg:classifiers":[
        {
            "category":"Health Services",
            "subcategory":"Doctor",
            "type":"Services"
        }
    ],
    "sg:phone":"+1 514 645 7426",
    "sg:postcode":"H1B 2W4",
    "sg:province":"QC",
    "sg:tags":[
        "clinic"
    ],
    "wof:name":"Clinique Medicale Montreal Est",
    "wof:placetype":"venue"
},
  "geometry": {"coordinates":[-73.497025,45.630604],"type":"Point"}
}