{
  "type": "Feature",
  "properties": {
    "addr:full":"1310 5th Ave Prince George BC V2L 3L4",
    "addr:housenumber":"1310",
    "addr:postcode":"v2l 3l4",
    "addr:street":"5Th Ave",
    "iso:country":"CA",
    "sg:address":"1310 5th Ave",
    "sg:city":"Prince George",
    "sg:classifiers":[
        {
            "category":"Social Services",
            "subcategory":"Job Training",
            "type":"Services"
        }
    ],
    "sg:phone":"+1 250 564 0181",
    "sg:postcode":"V2L 3L4",
    "sg:province":"BC",
    "sg:tags":[
        "orthopedic",
        "appliance",
        "rehabilitation"
    ],
    "wof:name":"Brian Farrance Orthotics",
    "wof:placetype":"venue"
},
  "geometry": {"coordinates":[-122.747467,53.915653],"type":"Point"}
}