{
  "type": "Feature",
  "properties": {
    "addr:full":"Gloucester ON K1B 5P2",
    "addr:postcode":"k1b 5p2",
    "iso:country":"CA",
    "sg:city":"Gloucester",
    "sg:classifiers":[
        {
            "category":"Manufacturing",
            "subcategory":"Signs",
            "type":"Manufacturing & Wholesale Goods"
        }
    ],
    "sg:phone":"+1 613 749 7303",
    "sg:postcode":"K1B 5P2",
    "sg:province":"ON",
    "wof:name":"Studio Signs",
    "wof:placetype":"venue"
},
  "geometry": {"coordinates":[-75.61573799999999,45.416031],"type":"Point"}
}