{
  "type": "Feature",
  "properties": {
    "addr:full":"721 Queen St #A Kincardine ON N2Z 1Z9",
    "addr:housenumber":"721",
    "addr:postcode":"n2z 1z9",
    "addr:street":"Queen St # A",
    "iso:country":"CA",
    "sg:address":"721 Queen St #A",
    "sg:city":"Kincardine",
    "sg:classifiers":[
        {
            "category":"Recreation",
            "type":"Entertainment"
        }
    ],
    "sg:phone":"+1 519 396 9466",
    "sg:postcode":"N2Z 1Z9",
    "sg:province":"ON",
    "sg:tags":[
        "party",
        "fishing"
    ],
    "wof:name":"Fish Kincardine Salmon Derby",
    "wof:placetype":"venue"
},
  "geometry": {"coordinates":[-81.63617706300001,44.1755447388],"type":"Point"}
}