{
  "type": "Feature",
  "properties": {
    "addr:full":"90 Colonization Rd Blind River ON P0R 1B0",
    "addr:housenumber":"90",
    "addr:postcode":"p0r 1b0",
    "addr:street":"Colonization Rd",
    "iso:country":"CA",
    "sg:address":"90 Colonization Rd",
    "sg:city":"Blind River",
    "sg:classifiers":[
        {
            "category":"Food & Beverages",
            "subcategory":"Groceries & Convenience Stores",
            "type":"Retail Goods"
        }
    ],
    "sg:phone":"+1 705 356 2289",
    "sg:postcode":"P0R 1B0",
    "sg:province":"ON",
    "sg:tags":[
        "grocer"
    ],
    "wof:name":"Quality Meats & Deli",
    "wof:placetype":"venue"
},
  "geometry": {"coordinates":[-82.962463,46.186569],"type":"Point"}
}