{
  "type": "Feature",
  "properties": {
    "iso:country":"CA",
    "sg:address":"1271 Rue Julien-Green",
    "sg:city":"Sainte-Foy",
    "sg:classifiers":[
        {
            "category":"Social Services",
            "type":"Services"
        }
    ],
    "sg:phone":"+1 418 658 2362",
    "sg:postcode":"G1W 3M4",
    "sg:province":"QC",
    "sg:tags":[
        "info",
        "drug",
        "abuse",
        "treatment",
        "welfare",
        "organization",
        "addiction"
    ],
    "wof:name":"Maison L'Esperance Inc",
    "wof:placetype":"venue"
},
  "geometry": {"coordinates":[-71.2821884155,46.7659263611],"type":"Point"}
}