{
  "type": "Feature",
  "properties": {
    "addr:full":"Bancroft ON K0L 1C0",
    "addr:postcode":"k0l 1c0",
    "iso:country":"CA",
    "sg:city":"Bancroft",
    "sg:classifiers":[
        {
            "category":"Home & Garden",
            "subcategory":"Carpets & Floor Coverings",
            "type":"Retail Goods"
        }
    ],
    "sg:phone":"+1 613 332 3770",
    "sg:postcode":"K0L 1C0",
    "sg:province":"ON",
    "sg:tags":[
        "dealer",
        "rug"
    ],
    "wof:name":"Home Store",
    "wof:placetype":"venue"
},
  "geometry": {"coordinates":[-77.85334777830001,45.0565414429],"type":"Point"}
}