{
  "type": "Feature",
  "properties": {
    "addr:full":"5501 Rue DE Verdun Verdun QC H4H 1K9",
    "addr:housenumber":"5501",
    "addr:postcode":"h4h 1k9",
    "addr:street":"Rue De Verdun",
    "iso:country":"CA",
    "sg:address":"5501 Rue DE Verdun",
    "sg:city":"Verdun",
    "sg:classifiers":[
        {
            "category":"Banks & Credit Unions",
            "subcategory":"Bank",
            "type":"Services"
        }
    ],
    "sg:phone":"+1 514 522 1846",
    "sg:postcode":"H4H 1K9",
    "sg:province":"QC",
    "wof:name":"Banque Laurentienne Du Canada",
    "wof:placetype":"venue"
},
  "geometry": {"coordinates":[-73.572372,45.452469],"type":"Point"}
}