{
  "type": "Feature",
  "properties": {
    "addr:full":"15 Bonnie Pl St Thomas ON N5R 5T8",
    "addr:housenumber":"15",
    "addr:postcode":"n5r 5t8",
    "addr:street":"Bonnie Pl",
    "iso:country":"CA",
    "sg:address":"15 Bonnie Pl",
    "sg:city":"St Thomas",
    "sg:classifiers":[
        {
            "category":"Health Services",
            "subcategory":"Nursing And Care Facility",
            "type":"Services"
        }
    ],
    "sg:phone":"+1 519 633 6493",
    "sg:postcode":"N5R 5T8",
    "sg:province":"ON",
    "sg:tags":[
        "home",
        "convalescent"
    ],
    "wof:name":"Caressant Care on Bonnie Place",
    "wof:placetype":"venue"
},
  "geometry": {"coordinates":[-81.16046142579999,42.7722854614],"type":"Point"}
}