{
  "type": "Feature",
  "properties": {
    "addr:full":"8150 Rue Aime-Renaud Saint-Leonard QC H1P 2T4",
    "addr:housenumber":"8150",
    "addr:postcode":"h1p 2t4",
    "addr:street":"Rue Aime-Renaud",
    "iso:country":"CA",
    "sg:address":"8150 Rue Aime-Renaud",
    "sg:city":"Saint-Leonard",
    "sg:classifiers":[
        {
            "category":"Building & Trades",
            "subcategory":"Electrical",
            "type":"Services"
        }
    ],
    "sg:phone":"+1 514 321 4823",
    "sg:postcode":"H1P 2T4",
    "sg:province":"QC",
    "sg:tags":[
        "electric",
        "contractor"
    ],
    "wof:name":"Rocco Electric Regd",
    "wof:placetype":"venue"
},
  "geometry": {"coordinates":[-73.5914230347,45.5869750977],"type":"Point"}
}