{
  "type": "Feature",
  "properties": {
    "addr:full":"633 Main St Selkirk MB R1A 3Y9",
    "addr:housenumber":"633",
    "addr:postcode":"r1a 3y9",
    "addr:street":"Main St",
    "iso:country":"CA",
    "sg:address":"633 Main St",
    "sg:city":"Selkirk",
    "sg:classifiers":[
        {
            "category":"Wholesale",
            "subcategory":"Auto Parts",
            "type":"Manufacturing & Wholesale Goods"
        }
    ],
    "sg:phone":"+1 204 482 2222",
    "sg:postcode":"R1A 3Y9",
    "sg:province":"MB",
    "sg:tags":[
        "automobile",
        "rebuilt"
    ],
    "wof:name":"Reward Auto Recycling",
    "wof:placetype":"venue"
},
  "geometry": {"coordinates":[-96.86698150629999,50.1533432007],"type":"Point"}
}