{
  "type": "Feature",
  "properties": {
    "addr:full":"8221 Cummington Sq E Niagara Falls ON L2G 6W1",
    "addr:housenumber":"8221",
    "addr:postcode":"l2g 6w1",
    "addr:street":"Cummington Sq E",
    "iso:country":"CA",
    "sg:address":"8221 Cummington Sq E",
    "sg:city":"Niagara Falls",
    "sg:classifiers":[
        {
            "category":"Restaurant",
            "type":"Food & Drink"
        }
    ],
    "sg:phone":"+1 905 295 3476",
    "sg:postcode":"L2G 6W1",
    "sg:province":"ON",
    "wof:name":"B Jays Family Restaurant",
    "wof:placetype":"venue"
},
  "geometry": {"coordinates":[-79.050652,43.059361],"type":"Point"}
}