{
  "type": "Feature",
  "properties": {
    "addr:full":"26 Moss Blvd # 23 Dundas ON L9H 6W7",
    "addr:housenumber":"26",
    "addr:postcode":"l9h 6w7",
    "addr:street":"Moss Blvd # 23",
    "iso:country":"CA",
    "sg:address":"26 Moss Blvd # 23",
    "sg:city":"Dundas",
    "sg:classifiers":[
        {
            "category":"Professional",
            "subcategory":"Printing & Photocopies",
            "type":"Services"
        }
    ],
    "sg:phone":"+1 905 628 0094",
    "sg:postcode":"L9H 6W7",
    "sg:province":"ON",
    "sg:tags":[
        "duplicating",
        "copying"
    ],
    "wof:name":"Discount Document Scanning",
    "wof:placetype":"venue"
},
  "geometry": {"coordinates":[-79.9825515747,43.2565956116],"type":"Point"}
}