{
  "type": "Feature",
  "properties": {
    "addr:full":"9612 76 Ave NW Edmonton AB T6C 0K3",
    "addr:housenumber":"9612",
    "addr:postcode":"t6c 0k3",
    "addr:street":"76 Ave Nw",
    "iso:country":"CA",
    "sg:address":"9612 76 Ave NW",
    "sg:city":"Edmonton",
    "sg:classifiers":[
        {
            "category":"Personal",
            "subcategory":"Beauty Salon",
            "type":"Services"
        }
    ],
    "sg:phone":"+1 780 988 6133",
    "sg:postcode":"T6C 0K3",
    "sg:province":"AB",
    "wof:name":"Shear Instinct Ltd",
    "wof:placetype":"venue"
},
  "geometry": {"coordinates":[-113.47734832800001,53.5125045776],"type":"Point"}
}