{
  "type": "Feature",
  "properties": {
    "iso:country":"CA",
    "sg:address":"91 Fernstaff Crt #4",
    "sg:city":"Concord",
    "sg:classifiers":[
        {
            "category":"Retail",
            "subcategory":"Auto Repair",
            "type":"Services"
        }
    ],
    "sg:phone":"+1 905 669 1500",
    "sg:postcode":"L4K 3L9",
    "sg:province":"ON",
    "sg:tags":[
        "repairing",
        "automobile"
    ],
    "wof:name":"Reliable Auto Svc Inc",
    "wof:placetype":"venue"
},
  "geometry": {"coordinates":[-79.48085,43.826832],"type":"Point"}
}