{
  "type": "Feature",
  "properties": {
    "iso:country":"CA",
    "sg:address":"8960 River Dr # 1A",
    "sg:city":"Richmond",
    "sg:classifiers":[
        {
            "category":"Wholesale",
            "subcategory":"Durable Goods & Equipment",
            "type":"Manufacturing & Wholesale Goods"
        }
    ],
    "sg:phone":"+1 604 232 0983",
    "sg:postcode":"V6X 1Y8",
    "sg:province":"BC",
    "sg:tags":[
        "importer"
    ],
    "wof:name":"Twin Peaks Enterprises Ltd",
    "wof:placetype":"venue"
},
  "geometry": {"coordinates":[-123.125389,49.196789],"type":"Point"}
}