{
  "type": "Feature",
  "properties": {
    "addr:full":"1771 Av Dollard Lasalle QC H8N 1T9",
    "addr:housenumber":"1771",
    "addr:postcode":"h8n 1t9",
    "addr:street":"Av Dollard",
    "iso:country":"CA",
    "sg:address":"1771 Av Dollard",
    "sg:city":"Lasalle",
    "sg:classifiers":[
        {
            "category":"Health Services",
            "subcategory":"Doctor",
            "type":"Services"
        }
    ],
    "sg:phone":"+1 514 368 5500",
    "sg:postcode":"H8N 1T9",
    "sg:province":"QC",
    "sg:tags":[
        "clinic"
    ],
    "wof:name":"Centre Medical Nazareth",
    "wof:placetype":"venue"
},
  "geometry": {"coordinates":[-73.63162231450001,45.4291915894],"type":"Point"}
}