{
  "type": "Feature",
  "properties": {
    "addr:full":"268 Tranquille Rd Kamloops BC V2B 3G3",
    "addr:housenumber":"268",
    "addr:postcode":"bc v2b 3g3",
    "addr:street":"Tranquille Rd",
    "iso:country":"CA",
    "sg:address":"268 Tranquille Rd",
    "sg:city":"Kamloops",
    "sg:classifiers":[
        {
            "category":"Shopping",
            "subcategory":"Clothing, Apparel, & Fashions",
            "type":"Retail Goods"
        }
    ],
    "sg:phone":"+1 250 376 1914",
    "sg:postcode":"V2B 3G3",
    "sg:province":"BC",
    "sg:tags":[
        "infant"
    ],
    "wof:name":"Mommy & Me",
    "wof:placetype":"venue"
},
  "geometry": {"coordinates":[-120.356506,50.687023],"type":"Point"}
}