{
  "type": "Feature",
  "properties": {
    "iso:country":"CA",
    "sg:address":"4545 Rue Foster",
    "sg:city":"Waterloo",
    "sg:classifiers":[
        {
            "category":"Health Services",
            "subcategory":"Optometrist",
            "type":"Services"
        }
    ],
    "sg:phone":"+1 450 539 3555",
    "sg:postcode":"J0E 2N0",
    "sg:province":"QC",
    "wof:name":"Opto Reseau",
    "wof:placetype":"venue"
},
  "geometry": {"coordinates":[-72.515625,45.3416023254],"type":"Point"}
}