{
  "type": "Feature",
  "properties": {
    "iso:country":"CA",
    "sg:city":"Newmarket",
    "sg:classifiers":[
        {
            "category":"Shopping",
            "subcategory":"Bicycles & Sporting Goods",
            "type":"Retail Goods"
        }
    ],
    "sg:phone":"+1 905 895 4986",
    "sg:postcode":"L3Y 8S4",
    "sg:province":"ON",
    "wof:name":"Sport Mart",
    "wof:placetype":"venue"
},
  "geometry": {"coordinates":[-79.482994,44.064713],"type":"Point"}
}