{
  "type": "Feature",
  "properties": {
    "addr:full":"580 Church St Toronto ON M4Y 2E5",
    "addr:housenumber":"580",
    "addr:postcode":"m4y 2e5",
    "addr:street":"Church St",
    "iso:country":"CA",
    "sg:address":"580 Church St",
    "sg:city":"Toronto",
    "sg:classifiers":[
        {
            "category":"Restaurant",
            "type":"Food & Drink"
        }
    ],
    "sg:phone":"+1 416 963 2222",
    "sg:postcode":"M4Y 2E5",
    "sg:province":"ON",
    "wof:name":"Petit Liban Restaurant",
    "wof:placetype":"venue"
},
  "geometry": {"coordinates":[-79.3815002441,43.6668205261],"type":"Point"}
}