{
  "type": "Feature",
  "properties": {
    "addr:full":"6770 Rue Jarry E Saint-Leonard QC H1P 1W3",
    "addr:housenumber":"6770",
    "addr:postcode":"h1p 1w3",
    "addr:street":"Rue Jarry E",
    "iso:country":"CA",
    "sg:address":"6770 Rue Jarry E",
    "sg:city":"Saint-Leonard",
    "sg:classifiers":[
        {
            "category":"Professional",
            "subcategory":"Research",
            "type":"Services"
        }
    ],
    "sg:phone":"+1 514 329 4417",
    "sg:postcode":"H1P 1W3",
    "sg:province":"QC",
    "sg:tags":[
        "development",
        "electronic"
    ],
    "wof:name":"Innovox Inc",
    "wof:placetype":"venue"
},
  "geometry": {"coordinates":[-73.579041,45.597424],"type":"Point"}
}