{
  "type": "Feature",
  "properties": {
    "addr:full":"11 West Ave Toronto ON M4M 2L7",
    "addr:housenumber":"11",
    "addr:postcode":"m4m 2l7",
    "addr:street":"West Ave",
    "iso:country":"CA",
    "sg:address":"11 West Ave",
    "sg:city":"Toronto",
    "sg:classifiers":[
        {
            "category":"Manufacturing",
            "subcategory":"Printing",
            "type":"Manufacturing & Wholesale Goods"
        }
    ],
    "sg:phone":"+1 416 778 8698",
    "sg:postcode":"M4M 2L7",
    "sg:province":"ON",
    "sg:tags":[
        "printer"
    ],
    "wof:name":"Bestway Business Forms",
    "wof:placetype":"venue"
},
  "geometry": {"coordinates":[-79.3459014893,43.6640930176],"type":"Point"}
}