{
  "type": "Feature",
  "properties": {
    "addr:full":"1156 Campbell Lane Kingsville ON N9Y 2G4",
    "addr:housenumber":"1156",
    "addr:postcode":"n9y 2g4",
    "addr:street":"Campbell Lane",
    "iso:country":"CA",
    "sg:address":"1156 Campbell Lane",
    "sg:city":"Kingsville",
    "sg:classifiers":[
        {
            "category":"Building & Trades",
            "subcategory":"Electrical",
            "type":"Services"
        }
    ],
    "sg:phone":"+1 519 733 8326",
    "sg:postcode":"N9Y 2G4",
    "sg:province":"ON",
    "sg:tags":[
        "electric",
        "contractor"
    ],
    "wof:name":"Lakeview Electric Inc",
    "wof:placetype":"venue"
},
  "geometry": {"coordinates":[-82.6934585571,42.0336799622],"type":"Point"}
}