{
  "type": "Feature",
  "properties": {
    "addr:full":"105 Baldwin St Toronto ON M5T 1L5",
    "addr:housenumber":"105",
    "addr:postcode":"m5t 1l5",
    "addr:street":"Baldwin St",
    "iso:country":"CA",
    "sg:address":"105 Baldwin St",
    "sg:city":"Toronto",
    "sg:classifiers":[
        {
            "category":"Social Services",
            "type":"Services"
        }
    ],
    "sg:phone":"+1 416 595 1904",
    "sg:postcode":"M5T 1L5",
    "sg:province":"ON",
    "sg:tags":[
        "organization",
        "association",
        "welfare"
    ],
    "wof:name":"En Ping Fellowship Society",
    "wof:placetype":"venue"
},
  "geometry": {"coordinates":[-79.396545,43.655231],"type":"Point"}
}