{
  "type": "Feature",
  "properties": {
    "addr:full":"Edmonton AB T6A 0L4",
    "addr:postcode":"t6a 0l4",
    "iso:country":"CA",
    "sg:city":"Edmonton",
    "sg:classifiers":[
        {
            "category":"Health Services",
            "subcategory":"Clinic",
            "type":"Services"
        }
    ],
    "sg:phone":"+1 780 468 4663",
    "sg:postcode":"T6A 0L4",
    "sg:province":"AB",
    "sg:tags":[
        "home"
    ],
    "wof:name":"Alberta Region We Care Home",
    "wof:placetype":"venue"
},
  "geometry": {"coordinates":[-113.418006897,53.5399742126],"type":"Point"}
}