{
  "type": "Feature",
  "properties": {
    "addr:full":"Black Diamond AB T0L 0H0",
    "addr:postcode":"t0l 0h0",
    "iso:country":"CA",
    "sg:city":"Black Diamond",
    "sg:classifiers":[
        {
            "category":"Professional",
            "subcategory":"Business Services",
            "type":"Services"
        }
    ],
    "sg:phone":"+1 403 933 2760",
    "sg:postcode":"T0L 0H0",
    "sg:province":"AB",
    "sg:tags":[
        "embroidery"
    ],
    "wof:name":"Diamond Valley Clothing CO",
    "wof:placetype":"venue"
},
  "geometry": {"coordinates":[-114.234779,50.684956],"type":"Point"}
}