{
  "type": "Feature",
  "properties": {
    "addr:full":"699 Yonge St Toronto ON M4Y 2B2",
    "addr:housenumber":"699",
    "addr:postcode":"m4y 2b2",
    "addr:street":"Yonge St",
    "iso:country":"CA",
    "sg:address":"699 Yonge St",
    "sg:city":"Toronto",
    "sg:classifiers":[
        {
            "category":"Arts & Performance",
            "subcategory":"Theater",
            "type":"Entertainment"
        }
    ],
    "sg:phone":"+1 416 934 0900",
    "sg:postcode":"M4Y 2B2",
    "sg:province":"ON",
    "sg:tags":[
        "entertainer"
    ],
    "wof:name":"Upper Brass",
    "wof:placetype":"venue"
},
  "geometry": {"coordinates":[-79.38613100000001,43.669205],"type":"Point"}
}