{
  "type": "Feature",
  "properties": {
    "addr:full":"2000 Highland Ave Brandon MB R7C 1C4",
    "addr:housenumber":"2000",
    "addr:postcode":"r7c 1c4",
    "addr:street":"Highland Ave",
    "iso:country":"CA",
    "sg:address":"2000 Highland Ave",
    "sg:city":"Brandon",
    "sg:classifiers":[
        {
            "category":"Restaurant",
            "type":"Food & Drink"
        }
    ],
    "sg:phone":"+1 204 727 3911",
    "sg:postcode":"R7C 1C4",
    "sg:province":"MB",
    "wof:name":"Albert's Family Restaurant",
    "wof:placetype":"venue"
},
  "geometry": {"coordinates":[-99.958153,49.886429],"type":"Point"}
}