{
  "type": "Feature",
  "properties": {
    "addr:full":"340 Allen Ave Essex ON N8M 3G6",
    "addr:housenumber":"340",
    "addr:postcode":"n8m 3g6",
    "addr:street":"Allen Ave",
    "iso:country":"CA",
    "sg:address":"340 Allen Ave",
    "sg:city":"Essex",
    "sg:classifiers":[
        {
            "category":"Manufacturing",
            "subcategory":"Metals",
            "type":"Manufacturing & Wholesale Goods"
        }
    ],
    "sg:phone":"+1 519 776 9153",
    "sg:postcode":"N8M 3G6",
    "sg:province":"ON",
    "sg:tags":[
        "steel",
        "processing"
    ],
    "wof:name":"Essex Weld Solutions Inc",
    "wof:placetype":"venue"
},
  "geometry": {"coordinates":[-82.834076,42.176476],"type":"Point"}
}