{
  "type": "Feature",
  "properties": {
    "addr:full":"Markham ON L3R 0B6",
    "addr:postcode":"l3r 0b6",
    "iso:country":"CA",
    "sg:city":"Markham",
    "sg:classifiers":[
        {
            "category":"Professional",
            "subcategory":"Accounting & Tax Preparation",
            "type":"Services"
        }
    ],
    "sg:phone":"+1 905 477 4301",
    "sg:postcode":"L3R 0B6",
    "sg:province":"ON",
    "sg:tags":[
        "accountant"
    ],
    "wof:name":"Khokhar, Khalid M",
    "wof:placetype":"venue"
},
  "geometry": {"coordinates":[-79.35945129389999,43.8301200867],"type":"Point"}
}