{
  "type": "Feature",
  "properties": {
    "addr:full":"Richmond BC V6X 2T1",
    "addr:postcode":"v6x 2t1",
    "iso:country":"CA",
    "sg:city":"Richmond",
    "sg:classifiers":[
        {
            "category":"Manufacturing",
            "subcategory":"Motor Vehicles & Parts",
            "type":"Manufacturing & Wholesale Goods"
        }
    ],
    "sg:phone":"+1 604 278 2068",
    "sg:postcode":"V6X 2T1",
    "sg:province":"BC",
    "sg:tags":[
        "automobile",
        "supply"
    ],
    "wof:name":"N V Plus",
    "wof:placetype":"venue"
},
  "geometry": {"coordinates":[-123.091278,49.196026],"type":"Point"}
}