{
  "type": "Feature",
  "properties": {
    "iso:country":"CA",
    "sg:address":"1077 North Service Rd",
    "sg:city":"Mississauga",
    "sg:classifiers":[
        {
            "category":"Shopping",
            "subcategory":"Gifts & Souvenirs",
            "type":"Retail Goods"
        }
    ],
    "sg:phone":"+1 905 273 6014",
    "sg:postcode":"L4Y 1A6",
    "sg:province":"ON",
    "sg:tags":[
        "party",
        "supply"
    ],
    "wof:name":"Party Market",
    "wof:placetype":"venue"
},
  "geometry": {"coordinates":[-79.575317,43.59127],"type":"Point"}
}