{
  "type": "Feature",
  "properties": {
    "addr:full":"Coldbrook NS B4R 1B6",
    "addr:postcode":"b4r 1b6",
    "iso:country":"CA",
    "sg:city":"Coldbrook",
    "sg:classifiers":[
        {
            "category":"Shopping",
            "subcategory":"Used Merchandise",
            "type":"Retail Goods"
        }
    ],
    "sg:phone":"+1 902 679 3553",
    "sg:postcode":"B4R 1B6",
    "sg:province":"NS",
    "sg:tags":[
        "clothing"
    ],
    "wof:name":"Frenchy's Used Clothing",
    "wof:placetype":"venue"
},
  "geometry": {"coordinates":[-64.576279,45.066879],"type":"Point"}
}