{
  "type": "Feature",
  "properties": {
    "addr:full":"465 S Hwy 97 100 Mile House BC V0K 2E0",
    "addr:housenumber":"465",
    "addr:postcode":"v0k 2e0",
    "addr:street":"S Hwy 97",
    "iso:country":"CA",
    "sg:address":"465 S Hwy 97",
    "sg:city":"100 Mile House",
    "sg:classifiers":[
        {
            "category":"Autos & Motor Vehicles",
            "subcategory":"Fuel & Gas Station",
            "type":"Retail Goods"
        }
    ],
    "sg:phone":"+1 250 395 4186",
    "sg:postcode":"V0K 2E0",
    "sg:province":"BC",
    "sg:tags":[
        "oil"
    ],
    "wof:name":"Cariboo Trails Turbo",
    "wof:placetype":"venue"
},
  "geometry": {"coordinates":[-121.391159,51.314026],"type":"Point"}
}