{
  "type": "Feature",
  "properties": {
    "addr:full":"15 Clubhouse Crt North York ON M3L 2L7",
    "addr:housenumber":"15",
    "addr:postcode":"m3l 2l7",
    "addr:street":"Clubhouse Crt",
    "iso:country":"CA",
    "sg:address":"15 Clubhouse Crt",
    "sg:city":"North York",
    "sg:classifiers":[
        {
            "category":"Recreation",
            "type":"Entertainment"
        }
    ],
    "sg:phone":"+1 416 395 6033",
    "sg:postcode":"M3L 2L7",
    "sg:province":"ON",
    "sg:tags":[
        "center",
        "hall",
        "auditorium"
    ],
    "wof:name":"Northwood Community Rcrtn Ctr",
    "wof:placetype":"venue"
},
  "geometry": {"coordinates":[-79.500992,43.745239],"type":"Point"}
}