{
  "type": "Feature",
  "properties": {
    "iso:country":"CA",
    "sg:address":"11430 56E Av",
    "sg:city":"Montreal",
    "sg:classifiers":[
        {
            "category":"Manufacturing",
            "subcategory":"Chemicals & Compounds",
            "type":"Manufacturing & Wholesale Goods"
        }
    ],
    "sg:phone":"+1 514 648 4911",
    "sg:postcode":"H1E 2L5",
    "sg:province":"QC",
    "sg:tags":[
        "paint"
    ],
    "wof:name":"Peintures Prolux Paint Inc",
    "wof:placetype":"venue"
},
  "geometry": {"coordinates":[-73.5581283569,45.6437263489],"type":"Point"}
}