{
  "type": "Feature",
  "properties": {
    "iso:country":"CA",
    "sg:address":"2286 Ch Des Patriotes",
    "sg:city":"Richelieu",
    "sg:classifiers":[
        {
            "category":"Home & Garden",
            "subcategory":"Carpets & Floor Coverings",
            "type":"Retail Goods"
        }
    ],
    "sg:phone":"+1 450 447 2694",
    "sg:postcode":"J3L 6M4",
    "sg:province":"QC",
    "sg:tags":[
        "builder",
        "material",
        "stair"
    ],
    "wof:name":"Escaliers Rive-Sud",
    "wof:placetype":"venue"
},
  "geometry": {"coordinates":[-73.24104309080001,45.4188270569],"type":"Point"}
}