{
  "type": "Feature",
  "properties": {
    "addr:full":"725 King St Weyburn SK S4H 0P9",
    "addr:housenumber":"725",
    "addr:postcode":"s4h 0p9",
    "addr:street":"King St",
    "iso:country":"CA",
    "sg:address":"725 King St",
    "sg:city":"Weyburn",
    "sg:classifiers":[
        {
            "category":"Education",
            "subcategory":"School",
            "type":"Public Place"
        }
    ],
    "sg:phone":"+1 306 842 3553",
    "sg:postcode":"S4H 0P9",
    "sg:province":"SK",
    "wof:name":"Queen Elizabeth School",
    "wof:placetype":"venue"
},
  "geometry": {"coordinates":[-103.858322144,49.6735916138],"type":"Point"}
}