{
  "type": "Feature",
  "properties": {
    "addr:full":"11867 Boul Saint-Germain Montreal QC H4J 2A3",
    "addr:housenumber":"11867",
    "addr:postcode":"h4j 2a3",
    "addr:street":"Boul Saint-Germain",
    "iso:country":"CA",
    "sg:address":"11867 Boul Saint-Germain",
    "sg:city":"Montreal",
    "sg:classifiers":[
        {
            "category":"Professional",
            "subcategory":"Computer Services",
            "type":"Services"
        }
    ],
    "sg:phone":"+1 514 332 9488",
    "sg:postcode":"H4J 2A3",
    "sg:province":"QC",
    "sg:tags":[
        "information",
        "system",
        "consultant"
    ],
    "wof:name":"Informatique Express",
    "wof:placetype":"venue"
},
  "geometry": {"coordinates":[-73.704956,45.530441],"type":"Point"}
}