{
  "type": "Feature",
  "properties": {
    "addr:full":"315 Rg St Antoine Sainte-Sophie-DE-Levrard QC G0X 3C0",
    "addr:housenumber":"315",
    "addr:postcode":"g0x 3c0",
    "addr:street":"Rg St Antoine Sainte-Sophie-De-Levrard",
    "iso:country":"CA",
    "sg:address":"315 Rg St Antoine",
    "sg:city":"Sainte-Sophie-DE-Levrard",
    "sg:classifiers":[
        {
            "category":"Travel",
            "subcategory":"Campground",
            "type":"Entertainment"
        }
    ],
    "sg:phone":"+1 819 288 5948",
    "sg:postcode":"G0X 3C0",
    "sg:province":"QC",
    "wof:name":"Camping Plage Paris Inc",
    "wof:placetype":"venue"
},
  "geometry": {"coordinates":[-72.12484000000001,46.390034],"type":"Point"}
}