{
  "type": "Feature",
  "properties": {
    "addr:full":"Penticton BC V2A 8R2",
    "addr:postcode":"v2a 8r2",
    "iso:country":"CA",
    "sg:city":"Penticton",
    "sg:classifiers":[
        {
            "category":"Home & Garden",
            "subcategory":"Furniture",
            "type":"Retail Goods"
        }
    ],
    "sg:phone":"+1 250 493 6836",
    "sg:postcode":"V2A 8R2",
    "sg:province":"BC",
    "sg:tags":[
        "cabinet"
    ],
    "wof:name":"Creative Millwork Ltd",
    "wof:placetype":"venue"
},
  "geometry": {"coordinates":[-119.57681274399999,49.4771881104],"type":"Point"}
}