{
  "type": "Feature",
  "properties": {
    "iso:country":"CA",
    "sg:city":"Madeira Park",
    "sg:classifiers":[
        {
            "category":"Government",
            "subcategory":"Office",
            "type":"Public Place"
        }
    ],
    "sg:phone":"+1 604 883 2954",
    "sg:postcode":"V0N 2H0",
    "sg:province":"BC",
    "sg:tags":[
        "village"
    ],
    "wof:name":"Sunshine Dist Pender Harbour",
    "wof:placetype":"venue"
},
  "geometry": {"coordinates":[-124.02136993400001,49.6130371094],"type":"Point"}
}