{
  "type": "Feature",
  "properties": {
    "addr:full":"527 Av Georges-Rainville Iberville QC J2X 5J8",
    "addr:postcode":"j2x 5j8",
    "addr:street":"527 Av Georges-Rainville",
    "iso:country":"CA",
    "sg:address":"527 Av Georges-Rainville",
    "sg:city":"Iberville",
    "sg:classifiers":[
        {
            "category":"Professional",
            "subcategory":"Detective & Security Services",
            "type":"Services"
        }
    ],
    "sg:phone":"+1 450 346 3763",
    "sg:postcode":"J2X 5J8",
    "sg:province":"QC",
    "sg:tags":[
        "control",
        "burglary",
        "protective",
        "system",
        "robbery"
    ],
    "wof:name":"Securite Rnd Inc",
    "wof:placetype":"venue"
},
  "geometry": {"coordinates":[-73.226044,45.311089],"type":"Point"}
}