{
  "type": "Feature",
  "properties": {
    "addr:full":"500 Rexdale Blvd # 75 Etobicoke ON M9W 6K5",
    "addr:housenumber":"500",
    "addr:postcode":"m9w 6k5",
    "addr:street":"Rexdale Blvd # 75",
    "iso:country":"CA",
    "sg:address":"500 Rexdale Blvd # 75",
    "sg:city":"Etobicoke",
    "sg:classifiers":[
        {
            "category":"Shopping",
            "subcategory":"Clothing, Apparel, & Fashions",
            "type":"Retail Goods"
        }
    ],
    "sg:phone":"+1 416 675 0198",
    "sg:postcode":"M9W 6K5",
    "sg:province":"ON",
    "sg:tags":[
        "furnishing"
    ],
    "wof:name":"International Clothiers",
    "wof:placetype":"venue"
},
  "geometry": {"coordinates":[-79.597084,43.717823],"type":"Point"}
}