{
  "type": "Feature",
  "properties": {
    "addr:full":"221 5E Rang Saint-Ambroise-DE-Kildare QC J0K 1C0",
    "addr:housenumber":"221",
    "addr:postcode":"j0k 1c0",
    "addr:street":"5E Rang",
    "iso:country":"CA",
    "sg:address":"221 5E Rang",
    "sg:city":"Saint-Ambroise-DE-Kildare",
    "sg:classifiers":[
        {
            "category":"Personal",
            "subcategory":"Beauty Salon",
            "type":"Services"
        }
    ],
    "sg:phone":"+1 450 753 3298",
    "sg:postcode":"J0K 1C0",
    "sg:province":"QC",
    "wof:name":"Oasis DE LA Beaute Enr",
    "wof:placetype":"venue"
},
  "geometry": {"coordinates":[-73.55443572999999,46.0767784119],"type":"Point"}
}