{
  "type": "Feature",
  "properties": {
    "addr:full":"35 Sykes St N # 1 Meaford ON N4L 1V9",
    "addr:housenumber":"35",
    "addr:postcode":"n4l 1v9",
    "addr:street":"Sykes St N # 1",
    "iso:country":"CA",
    "sg:address":"35 Sykes St N # 1",
    "sg:city":"Meaford",
    "sg:classifiers":[
        {
            "category":"Shopping",
            "subcategory":"Crafts & Fabrics",
            "type":"Retail Goods"
        }
    ],
    "sg:phone":"+1 519 538 4283",
    "sg:postcode":"N4L 1V9",
    "sg:province":"ON",
    "sg:tags":[
        "yarn"
    ],
    "wof:name":"Purrsonally Yours",
    "wof:placetype":"venue"
},
  "geometry": {"coordinates":[-80.591705,44.607342],"type":"Point"}
}