{
  "type": "Feature",
  "properties": {
    "addr:full":"2933 Richmond Rd SW Calgary AB T3E 4N3",
    "addr:housenumber":"2933",
    "addr:postcode":"t3e 4n3",
    "addr:street":"Richmond Rd Sw",
    "iso:country":"CA",
    "sg:address":"2933 Richmond Rd SW",
    "sg:city":"Calgary",
    "sg:classifiers":[
        {
            "category":"Retail",
            "subcategory":"Animal Services",
            "type":"Services"
        }
    ],
    "sg:phone":"+1 403 686 6596",
    "sg:postcode":"T3E 4N3",
    "sg:province":"AB",
    "sg:tags":[
        "pet",
        "grooming",
        "washing"
    ],
    "wof:name":"Bones Barks N' Baths",
    "wof:placetype":"venue"
},
  "geometry": {"coordinates":[-114.12852478000001,51.0261116028],"type":"Point"}
}