{
  "type": "Feature",
  "properties": {
    "addr:full":"630 Shuswap Ave Chase BC V0E 1M0",
    "addr:housenumber":"630",
    "addr:postcode":"v0e 1m0",
    "addr:street":"Shuswap Ave",
    "iso:country":"CA",
    "sg:address":"630 Shuswap Ave",
    "sg:city":"Chase",
    "sg:classifiers":[
        {
            "category":"Shopping",
            "subcategory":"Discount & Variety Stores",
            "type":"Retail Goods"
        }
    ],
    "sg:phone":"+1 250 679 8002",
    "sg:postcode":"V0E 1M0",
    "sg:province":"BC",
    "wof:name":"Dollar or More Variety Store",
    "wof:placetype":"venue"
},
  "geometry": {"coordinates":[-119.690254,50.819138],"type":"Point"}
}