{
  "type": "Feature",
  "properties": {
    "addr:full":"15883 116 Ave NW Edmonton AB T5M 3W1",
    "addr:housenumber":"15883",
    "addr:postcode":"t5m 3w1",
    "addr:street":"116 Ave Nw",
    "iso:country":"CA",
    "sg:address":"15883 116 Ave NW",
    "sg:city":"Edmonton",
    "sg:classifiers":[
        {
            "category":"Restaurant",
            "type":"Food & Drink"
        }
    ],
    "sg:phone":"+1 780 455 5060",
    "sg:postcode":"T5M 3W1",
    "sg:province":"AB",
    "wof:name":"West Point Restaurant",
    "wof:placetype":"venue"
},
  "geometry": {"coordinates":[-113.594925,53.566399],"type":"Point"}
}