{
  "type": "Feature",
  "properties": {
    "addr:full":"166 Rue Du Petit-Bois Loretteville QC G2A 4E6",
    "addr:housenumber":"166",
    "addr:postcode":"g2a 4e6",
    "addr:street":"Rue Du Petit-Bois",
    "iso:country":"CA",
    "sg:address":"166 Rue Du Petit-Bois",
    "sg:city":"Loretteville",
    "sg:classifiers":[
        {
            "category":"Organizations",
            "subcategory":"Professional Association",
            "type":"Services"
        }
    ],
    "sg:phone":"+1 418 847 1781",
    "sg:postcode":"G2A 4E6",
    "sg:province":"QC",
    "wof:name":"Assn Quebecoise D'Info Sclre",
    "wof:placetype":"venue"
},
  "geometry": {"coordinates":[-71.34958648680001,46.8618278503],"type":"Point"}
}