{
  "type": "Feature",
  "properties": {
    "addr:full":"8596 Rue DE Grosbois Montreal QC H1K 2G1",
    "addr:housenumber":"8596",
    "addr:postcode":"h1k 2g1",
    "addr:street":"Rue De Grosbois",
    "iso:country":"CA",
    "sg:address":"8596 Rue DE Grosbois",
    "sg:city":"Montreal",
    "sg:classifiers":[
        {
            "category":"Food & Beverages",
            "subcategory":"Liquor & Beverages",
            "type":"Retail Goods"
        }
    ],
    "sg:phone":"+1 514 352 0530",
    "sg:postcode":"H1K 2G1",
    "sg:province":"QC",
    "sg:tags":[
        "store"
    ],
    "wof:name":"Bonisoir Marche Bob",
    "wof:placetype":"venue"
},
  "geometry": {"coordinates":[-73.53494999999999,45.604317],"type":"Point"}
}