{
  "type": "Feature",
  "properties": {
    "addr:full":"10019 100 St Grande Cache AB T0E 0Y0",
    "addr:housenumber":"10019",
    "addr:postcode":"t0e 0y0",
    "addr:street":"100 St",
    "iso:country":"CA",
    "sg:address":"10019 100 St",
    "sg:city":"Grande Cache",
    "sg:classifiers":[
        {
            "category":"Travel",
            "subcategory":"Hotels & Motels",
            "type":"Entertainment"
        }
    ],
    "sg:phone":"+1 780 827 3744",
    "sg:postcode":"T0E 0Y0",
    "sg:province":"AB",
    "wof:name":"Big Horn Motor Inn",
    "wof:placetype":"venue"
},
  "geometry": {"coordinates":[-119.114318848,53.8890457153],"type":"Point"}
}