{
  "type": "Feature",
  "properties": {
    "addr:full":"D'Alembert QC J9X 5A3",
    "addr:postcode":"j9x 5a3",
    "addr:street":"D'Alembert",
    "iso:country":"CA",
    "sg:city":"D'Alembert",
    "sg:classifiers":[
        {
            "category":"Building & Trades",
            "subcategory":"Landscaping Services",
            "type":"Services"
        }
    ],
    "sg:phone":"+1 819 797 2553",
    "sg:postcode":"J9X 5A3",
    "sg:province":"QC",
    "sg:tags":[
        "landscape",
        "contractor"
    ],
    "wof:name":"Godin Terrassement Enr",
    "wof:placetype":"venue"
},
  "geometry": {"coordinates":[-78.97211456300001,48.2662353516],"type":"Point"}
}