{
  "type": "Feature",
  "properties": {
    "iso:country":"CA",
    "sg:address":"117 Chetwood St",
    "sg:city":"St Catharines",
    "sg:classifiers":[
        {
            "category":"Social Services",
            "type":"Services"
        }
    ],
    "sg:phone":"+1 905 684 0993",
    "sg:postcode":"L2S 2B1",
    "sg:province":"ON",
    "sg:tags":[
        "senior",
        "government",
        "citizen"
    ],
    "wof:name":"St Catharines Senior Ctzns Ctr",
    "wof:placetype":"venue"
},
  "geometry": {"coordinates":[-79.25829315190001,43.1434364319],"type":"Point"}
}