{
  "type": "Feature",
  "properties": {
    "addr:full":"6586 Randolph Ave Burnaby BC V5H 3W4",
    "addr:housenumber":"6586",
    "addr:postcode":"v5h 3w4",
    "addr:street":"Randolph Ave",
    "iso:country":"CA",
    "sg:address":"6586 Randolph Ave",
    "sg:city":"Burnaby",
    "sg:classifiers":[
        {
            "category":"Organizations",
            "subcategory":"Religious Organization",
            "type":"Services"
        }
    ],
    "sg:phone":"+1 604 438 0450",
    "sg:postcode":"V5H 3W4",
    "sg:province":"BC",
    "sg:tags":[
        "church"
    ],
    "wof:name":"Voice of Hope Mission",
    "wof:placetype":"venue"
},
  "geometry": {"coordinates":[-122.973083,49.22401],"type":"Point"}
}