{
  "type": "Feature",
  "properties": {
    "iso:country":"CA",
    "sg:address":"278 Browns Line",
    "sg:city":"Etobicoke",
    "sg:classifiers":[
        {
            "category":"Restaurant",
            "type":"Food & Drink"
        }
    ],
    "sg:phone":"+1 416 255 1098",
    "sg:postcode":"M8W 3T5",
    "sg:province":"ON",
    "sg:tags":[
        "delicatessen"
    ],
    "wof:name":"Family Meat Deli",
    "wof:placetype":"venue"
},
  "geometry": {"coordinates":[-79.544113,43.598778],"type":"Point"}
}