{
  "type": "Feature",
  "properties": {
    "addr:full":"2100 Rue LA Salle Longueuil QC J4K 3J4",
    "addr:housenumber":"2100",
    "addr:postcode":"j4k 3j4",
    "addr:street":"Rue La Salle",
    "iso:country":"CA",
    "sg:address":"2100 Rue LA Salle",
    "sg:city":"Longueuil",
    "sg:classifiers":[
        {
            "category":"Social Services",
            "subcategory":"Child Care",
            "type":"Services"
        }
    ],
    "sg:phone":"+1 450 646 1775",
    "sg:postcode":"J4K 3J4",
    "sg:province":"QC",
    "wof:name":"Garderie Pomme-Soleil Inc",
    "wof:placetype":"venue"
},
  "geometry": {"coordinates":[-73.487679,45.511589],"type":"Point"}
}