{
  "type": "Feature",
  "properties": {
    "addr:full":"152 Trafalgar Rd Oakville ON L6J 3G6",
    "addr:housenumber":"152",
    "addr:postcode":"l6j 3g6",
    "addr:street":"Trafalgar Rd",
    "iso:country":"CA",
    "sg:address":"152 Trafalgar Rd",
    "sg:city":"Oakville",
    "sg:classifiers":[
        {
            "category":"Health Services",
            "subcategory":"Doctor",
            "type":"Services"
        }
    ],
    "sg:phone":"+1 905 842 1552",
    "sg:postcode":"L6J 3G6",
    "sg:province":"ON",
    "sg:tags":[
        "dentist"
    ],
    "wof:name":"Baluschak, Mark A DDS",
    "wof:placetype":"venue"
},
  "geometry": {"coordinates":[-79.66873200000001,43.448494],"type":"Point"}
}