{
  "type": "Feature",
  "properties": {
    "addr:full":"51 King St W Bowmanville ON L1C 1R2",
    "addr:housenumber":"51",
    "addr:postcode":"l1c 1r2",
    "addr:street":"King St W",
    "iso:country":"CA",
    "sg:address":"51 King St W",
    "sg:city":"Bowmanville",
    "sg:classifiers":[
        {
            "category":"Shopping",
            "subcategory":"Crafts & Fabrics",
            "type":"Retail Goods"
        }
    ],
    "sg:phone":"+1 905 623 2404",
    "sg:postcode":"L1C 1R2",
    "sg:province":"ON",
    "sg:tags":[
        "shop"
    ],
    "wof:name":"Gould Cards and Gifts",
    "wof:placetype":"venue"
},
  "geometry": {"coordinates":[-78.690399,43.91246],"type":"Point"}
}