{
  "type": "Feature",
  "properties": {
    "addr:full":"1301 Main St S Dauphin MB R7N 2X7",
    "addr:housenumber":"1301",
    "addr:postcode":"r7n 2x7",
    "addr:street":"Main St S Dauphin",
    "iso:country":"CA",
    "sg:address":"1301 Main St S",
    "sg:city":"Dauphin",
    "sg:classifiers":[
        {
            "category":"Shopping",
            "subcategory":"Bicycles & Sporting Goods",
            "type":"Retail Goods"
        }
    ],
    "sg:phone":"+1 204 638 3658",
    "sg:postcode":"R7N 2X7",
    "sg:province":"MB",
    "wof:name":"Sticky's Service & Drive Inn",
    "wof:placetype":"venue"
},
  "geometry": {"coordinates":[-100.063369751,51.1370925903],"type":"Point"}
}