{
  "type": "Feature",
  "properties": {
    "addr:full":"305 Rue Du Tisserand Saint-Augustin-DE-Desmaures QC G3A 1K8",
    "addr:housenumber":"305",
    "addr:postcode":"g3a 1k8",
    "addr:street":"Rue Du Tisserand",
    "iso:country":"CA",
    "sg:address":"305 Rue Du Tisserand",
    "sg:city":"Saint-Augustin-DE-Desmaures",
    "sg:classifiers":[
        {
            "category":"Manufacturing",
            "subcategory":"Printing",
            "type":"Manufacturing & Wholesale Goods"
        }
    ],
    "sg:phone":"+1 418 878 5888",
    "sg:postcode":"G3A 1K8",
    "sg:province":"QC",
    "sg:tags":[
        "printer"
    ],
    "wof:name":"Lezard Graphiques Enr",
    "wof:placetype":"venue"
},
  "geometry": {"coordinates":[-71.4506530762,46.7350273132],"type":"Point"}
}