{
  "type": "Feature",
  "properties": {
    "addr:full":"10716 42A Ave NW Edmonton AB T6J 2P7",
    "addr:housenumber":"10716",
    "addr:postcode":"t6j 2p7",
    "addr:street":"42A Ave Nw",
    "iso:country":"CA",
    "sg:address":"10716 42A Ave NW",
    "sg:city":"Edmonton",
    "sg:classifiers":[
        {
            "category":"Professional",
            "subcategory":"Management & Consulting",
            "type":"Services"
        }
    ],
    "sg:phone":"+1 780 414 6727",
    "sg:postcode":"T6J 2P7",
    "sg:province":"AB",
    "sg:tags":[
        "consultant",
        "business"
    ],
    "wof:name":"Loral Management Group",
    "wof:placetype":"venue"
},
  "geometry": {"coordinates":[-113.508300781,53.4800186157],"type":"Point"}
}