{
  "type": "Feature",
  "properties": {
    "addr:full":"1072 Ch Industriel Saint-Nicolas QC G7A 1B3",
    "addr:housenumber":"1072",
    "addr:postcode":"g7a 1b3",
    "addr:street":"Ch Industriel",
    "iso:country":"CA",
    "sg:address":"1072 Ch Industriel",
    "sg:city":"Saint-Nicolas",
    "sg:classifiers":[
        {
            "category":"Manufacturing",
            "subcategory":"Food",
            "type":"Manufacturing & Wholesale Goods"
        }
    ],
    "sg:phone":"+1 418 831 1353",
    "sg:postcode":"G7A 1B3",
    "sg:province":"QC",
    "sg:tags":[
        "product",
        "manufacturer"
    ],
    "wof:name":"Aliments LA Bourgeoise Inc",
    "wof:placetype":"venue"
},
  "geometry": {"coordinates":[-71.32620199999999,46.683361],"type":"Point"}
}