{
  "type": "Feature",
  "properties": {
    "addr:full":"230 41 Ave NE Calgary AB T2E 2N3",
    "addr:housenumber":"230",
    "addr:postcode":"t2e 2n3",
    "addr:street":"41 Ave Ne",
    "iso:country":"CA",
    "sg:address":"230 41 Ave NE",
    "sg:city":"Calgary",
    "sg:classifiers":[
        {
            "category":"Retail",
            "subcategory":"Auto Repair",
            "type":"Services"
        }
    ],
    "sg:phone":"+1 403 276 5552",
    "sg:postcode":"T2E 2N3",
    "sg:province":"AB",
    "sg:tags":[
        "repairing",
        "automobile",
        "radiator"
    ],
    "wof:name":"Tops Radiator Svc",
    "wof:placetype":"venue"
},
  "geometry": {"coordinates":[-114.06090500000001,51.089237],"type":"Point"}
}