{
  "type": "Feature",
  "properties": {
    "addr:full":"8 Chapel Pl Markham ON L3R 9C4",
    "addr:housenumber":"8",
    "addr:postcode":"l3r 9c4",
    "addr:street":"Chapel Pl",
    "iso:country":"CA",
    "sg:address":"8 Chapel Pl",
    "sg:city":"Markham",
    "sg:classifiers":[
        {
            "category":"Social Services",
            "subcategory":"Child Care",
            "type":"Services"
        }
    ],
    "sg:phone":"+1 905 946 8307",
    "sg:postcode":"L3R 9C4",
    "sg:province":"ON",
    "wof:name":"Chapel Place Daycare Ctr",
    "wof:placetype":"venue"
},
  "geometry": {"coordinates":[-79.36103057859999,43.8646469116],"type":"Point"}
}