{
  "type": "Feature",
  "properties": {
    "addr:full":"5745 Tyson Rd Chilliwack BC V2R 3R6",
    "addr:housenumber":"5745",
    "addr:postcode":"v2r 3r6",
    "addr:street":"Tyson Rd",
    "iso:country":"CA",
    "sg:address":"5745 Tyson Rd",
    "sg:city":"Chilliwack",
    "sg:classifiers":[
        {
            "category":"Recreation",
            "type":"Entertainment"
        }
    ],
    "sg:phone":"+1 604 793 2904",
    "sg:postcode":"V2R 3R6",
    "sg:province":"BC",
    "sg:tags":[
        "skating",
        "rink"
    ],
    "wof:name":"Twin Rinks Ice Arena",
    "wof:placetype":"venue"
},
  "geometry": {"coordinates":[-121.976822,49.10638],"type":"Point"}
}