{
  "type": "Feature",
  "properties": {
    "addr:full":"80 Fairbanks St Dartmouth NS B3A 1C4",
    "addr:housenumber":"80",
    "addr:postcode":"b3a 1c4",
    "addr:street":"Fairbanks St",
    "iso:country":"CA",
    "sg:address":"80 Fairbanks St",
    "sg:city":"Dartmouth",
    "sg:classifiers":[
        {
            "category":"Wholesale",
            "subcategory":"Electrical",
            "type":"Manufacturing & Wholesale Goods"
        }
    ],
    "sg:phone":"+1 902 463 7418",
    "sg:postcode":"B3A 1C4",
    "sg:province":"NS",
    "sg:tags":[
        "equipment",
        "theatrical",
        "lighting",
        "system",
        "supply"
    ],
    "wof:name":"Atlantic Illumination",
    "wof:placetype":"venue"
},
  "geometry": {"coordinates":[-63.580452,44.66713],"type":"Point"}
}