{
  "type": "Feature",
  "properties": {
    "addr:full":"87 Prince William St Saint John NB E2L 2B2",
    "addr:housenumber":"87",
    "addr:postcode":"nb e2l 2b2",
    "addr:street":"Prince William St",
    "iso:country":"CA",
    "sg:address":"87 Prince William St",
    "sg:city":"Saint John",
    "sg:classifiers":[
        {
            "category":"Professional",
            "subcategory":"Lawyer & Legal Services",
            "type":"Services"
        }
    ],
    "sg:phone":"+1 506 657 2797",
    "sg:postcode":"E2L 2B2",
    "sg:province":"NB",
    "sg:tags":[
        "attorney"
    ],
    "wof:name":"Howes, J Douglas",
    "wof:placetype":"venue"
},
  "geometry": {"coordinates":[-66.06224060060001,45.2719573975],"type":"Point"}
}