{
  "type": "Feature",
  "properties": {
    "addr:full":"1 Lisa Crt Millbrook ON L0A 1G0",
    "addr:housenumber":"1",
    "addr:postcode":"l0a 1g0",
    "addr:street":"Lisa Crt",
    "iso:country":"CA",
    "sg:address":"1 Lisa Crt",
    "sg:city":"Millbrook",
    "sg:classifiers":[
        {
            "category":"Health Services",
            "subcategory":"Doctor",
            "type":"Services"
        }
    ],
    "sg:phone":"+1 705 932 2772",
    "sg:postcode":"L0A 1G0",
    "sg:province":"ON",
    "sg:tags":[
        "clinic"
    ],
    "wof:name":"Millbrook Medical Ctr",
    "wof:placetype":"venue"
},
  "geometry": {"coordinates":[-78.4593429565,44.1481628418],"type":"Point"}
}