{
  "type": "Feature",
  "properties": {
    "addr:full":"36 Nelson Rd Thompson MB R8N 0B4",
    "addr:housenumber":"36",
    "addr:postcode":"r8n 0b4",
    "addr:street":"Nelson Rd",
    "iso:country":"CA",
    "sg:address":"36 Nelson Rd",
    "sg:city":"Thompson",
    "sg:classifiers":[
        {
            "category":"Retail",
            "subcategory":"Auto Repair",
            "type":"Services"
        }
    ],
    "sg:phone":"+1 204 677 5936",
    "sg:postcode":"R8N 0B4",
    "sg:province":"MB",
    "sg:tags":[
        "repairing",
        "automobile"
    ],
    "wof:name":"Hi-Tech Automotive",
    "wof:placetype":"venue"
},
  "geometry": {"coordinates":[-97.845581,55.740372],"type":"Point"}
}