{
  "type": "Feature",
  "properties": {
    "addr:full":"1694 Eglinton Ave W York ON M6E 2H5",
    "addr:housenumber":"1694",
    "addr:postcode":"m6e 2h5",
    "addr:street":"Eglinton Ave W",
    "iso:country":"CA",
    "sg:address":"1694 Eglinton Ave W",
    "sg:city":"York",
    "sg:classifiers":[
        {
            "category":"Manufacturing",
            "subcategory":"Printing",
            "type":"Manufacturing & Wholesale Goods"
        }
    ],
    "sg:phone":"+1 416 781 3402",
    "sg:postcode":"M6E 2H5",
    "sg:province":"ON",
    "sg:tags":[
        "printer"
    ],
    "wof:name":"Berico Printing CO",
    "wof:placetype":"venue"
},
  "geometry": {"coordinates":[-79.446091,43.69672],"type":"Point"}
}