{
  "type": "Feature",
  "properties": {
    "addr:full":"170 Locke St S Hamilton ON L8P 4A9",
    "addr:housenumber":"170",
    "addr:postcode":"l8p 4a9",
    "addr:street":"Locke St S",
    "iso:country":"CA",
    "sg:address":"170 Locke St S",
    "sg:city":"Hamilton",
    "sg:classifiers":[
        {
            "category":"Personal",
            "subcategory":"Beauty Salon",
            "type":"Services"
        }
    ],
    "sg:phone":"+1 905 527 2725",
    "sg:postcode":"L8P 4A9",
    "sg:province":"ON",
    "wof:name":"Lori's Hair Design",
    "wof:placetype":"venue"
},
  "geometry": {"coordinates":[-79.885536,43.256039],"type":"Point"}
}