{
  "type": "Feature",
  "properties": {
    "addr:full":"15 Healey Rd Bolton ON L7E 5A1",
    "addr:housenumber":"15",
    "addr:postcode":"l7e 5a1",
    "addr:street":"Healey Rd",
    "iso:country":"CA",
    "sg:address":"15 Healey Rd",
    "sg:city":"Bolton",
    "sg:classifiers":[
        {
            "category":"Retail",
            "subcategory":"Auto Repair",
            "type":"Services"
        }
    ],
    "sg:phone":"+1 905 857 2200",
    "sg:postcode":"L7E 5A1",
    "sg:province":"ON",
    "sg:tags":[
        "repairing",
        "automobile",
        "tire"
    ],
    "wof:name":"Sheardown Auto Tire & Glass",
    "wof:placetype":"venue"
},
  "geometry": {"coordinates":[-79.71700286870001,43.8637504578],"type":"Point"}
}