{
  "type": "Feature",
  "properties": {
    "iso:country":"CA",
    "sg:address":"383 Rue Mgr Desmarais",
    "sg:city":"Upton",
    "sg:classifiers":[
        {
            "category":"Organizations",
            "subcategory":"Non-profit Organization",
            "type":"Services"
        }
    ],
    "sg:phone":"+1 450 549 5140",
    "sg:postcode":"J0H 2E0",
    "sg:province":"QC",
    "sg:tags":[
        "info",
        "social",
        "drug",
        "abuse",
        "treatment",
        "welfare",
        "addiction"
    ],
    "wof:name":"Toxi-Go Gite",
    "wof:placetype":"venue"
},
  "geometry": {"coordinates":[-72.6933441162,45.6516456604],"type":"Point"}
}