{
  "type": "Feature",
  "properties": {
    "addr:full":"6290 Boul Des Grandes-Prairies Saint-Leonard QC H1P 1A2",
    "addr:housenumber":"6290",
    "addr:postcode":"h1p 1a2",
    "addr:street":"Boul Des Grandes-Prairies",
    "iso:country":"CA",
    "sg:address":"6290 Boul Des Grandes-Prairies",
    "sg:city":"Saint-Leonard",
    "sg:classifiers":[
        {
            "category":"Wholesale",
            "subcategory":"Electrical",
            "type":"Manufacturing & Wholesale Goods"
        }
    ],
    "sg:phone":"+1 514 322 3311",
    "sg:postcode":"H1P 1A2",
    "sg:province":"QC",
    "sg:tags":[
        "battery"
    ],
    "wof:name":"Batterie Universelle Ltee",
    "wof:placetype":"venue"
},
  "geometry": {"coordinates":[-73.6068572998,45.6038246155],"type":"Point"}
}