{
  "type": "Feature",
  "properties": {
    "addr:full":"Lloydminster AB T9V 0A6",
    "addr:postcode":"t9v 0a6",
    "iso:country":"CA",
    "sg:city":"Lloydminster",
    "sg:classifiers":[
        {
            "category":"Personal",
            "subcategory":"Beauty Salon",
            "type":"Services"
        }
    ],
    "sg:phone":"+1 780 875 0899",
    "sg:postcode":"T9V 0A6",
    "sg:province":"AB",
    "wof:name":"Quick Stop Hair Shop",
    "wof:placetype":"venue"
},
  "geometry": {"coordinates":[-110.006897,53.277866],"type":"Point"}
}