{
  "type": "Feature",
  "properties": {
    "iso:country":"CA",
    "sg:address":"5461 Boul Decarie",
    "sg:city":"Montreal",
    "sg:classifiers":[
        {
            "category":"Social Services",
            "type":"Services"
        }
    ],
    "sg:phone":"+1 514 489 1007",
    "sg:postcode":"H3W 3C6",
    "sg:province":"QC",
    "sg:tags":[
        "organization",
        "welfare"
    ],
    "wof:name":"Compeer Montreal",
    "wof:placetype":"venue"
},
  "geometry": {"coordinates":[-73.634758,45.486519],"type":"Point"}
}