{
  "type": "Feature",
  "properties": {
    "addr:full":"9301 Bathurst St Richmond Hill ON L4C 9S2",
    "addr:housenumber":"9301",
    "addr:postcode":"l4c 9s2",
    "addr:street":"Bathurst St",
    "iso:country":"CA",
    "sg:address":"9301 Bathurst St",
    "sg:city":"Richmond Hill",
    "sg:classifiers":[
        {
            "category":"Personal",
            "subcategory":"Beauty Salon",
            "type":"Services"
        }
    ],
    "sg:phone":"+1 905 737 7773",
    "sg:postcode":"L4C 9S2",
    "sg:province":"ON",
    "wof:name":"Wild Strawberry Salon",
    "wof:placetype":"venue"
},
  "geometry": {"coordinates":[-79.4588012695,43.8490791321],"type":"Point"}
}