{
  "type": "Feature",
  "properties": {
    "addr:full":"65 Kingston Rd E Ajax ON L1S 7J4",
    "addr:housenumber":"65",
    "addr:postcode":"l1s 7j4",
    "addr:street":"Kingston Rd E",
    "iso:country":"CA",
    "sg:address":"65 Kingston Rd E",
    "sg:city":"Ajax",
    "sg:classifiers":[
        {
            "category":"Personal",
            "subcategory":"Beauty Salon",
            "type":"Services"
        }
    ],
    "sg:phone":"+1 905 427 6776",
    "sg:postcode":"L1S 7J4",
    "sg:province":"ON",
    "wof:name":"First Choice Haircutters",
    "wof:placetype":"venue"
},
  "geometry": {"coordinates":[-79.022087,43.861855],"type":"Point"}
}