{
  "type": "Feature",
  "properties": {
    "iso:country":"CA",
    "sg:address":"33 Rue Mayer",
    "sg:city":"Sainte-Therese",
    "sg:classifiers":[
        {
            "category":"Real Estate",
            "subcategory":"Real Estate Operator",
            "type":"Services"
        }
    ],
    "sg:phone":"+1 450 435 0360",
    "sg:postcode":"J7E 4T2",
    "sg:province":"QC",
    "sg:tags":[
        "apartment"
    ],
    "wof:name":"Ilots Ste Therese",
    "wof:placetype":"venue"
},
  "geometry": {"coordinates":[-73.8553695679,45.6434631348],"type":"Point"}
}