{
  "type": "Feature",
  "properties": {
    "addr:full":"318 Monument Pl SE Calgary AB T2A 1X3",
    "addr:housenumber":"318",
    "addr:postcode":"t2a 1x3",
    "addr:street":"Monument Pl Se",
    "iso:country":"CA",
    "sg:address":"318 Monument Pl SE",
    "sg:city":"Calgary",
    "sg:classifiers":[
        {
            "category":"Manufacturing",
            "subcategory":"Metals",
            "type":"Manufacturing & Wholesale Goods"
        }
    ],
    "sg:phone":"+1 403 273 5105",
    "sg:postcode":"T2A 1X3",
    "sg:province":"AB",
    "sg:tags":[
        "treating",
        "heat"
    ],
    "wof:name":"Continental Stress Relieving",
    "wof:placetype":"venue"
},
  "geometry": {"coordinates":[-113.99655199999999,51.051289],"type":"Point"}
}