{
  "type": "Feature",
  "properties": {
    "iso:country":"CA",
    "sg:city":"St Catharines",
    "sg:classifiers":[
        {
            "category":"Wholesale",
            "subcategory":"Office Equipment",
            "type":"Manufacturing & Wholesale Goods"
        }
    ],
    "sg:phone":"+1 905 984 8266",
    "sg:postcode":"L2N 1L2",
    "sg:province":"ON",
    "sg:tags":[
        "machine",
        "duplicating",
        "copying"
    ],
    "wof:name":"Brock Office Automation",
    "wof:placetype":"venue"
},
  "geometry": {"coordinates":[-79.249123,43.182892],"type":"Point"}
}