{
  "type": "Feature",
  "properties": {
    "addr:full":"3263 Rue Lafayette Sorel-Tracy QC J3R 5L8",
    "addr:housenumber":"3263",
    "addr:postcode":"j3r 5l8",
    "addr:street":"Rue Lafayette",
    "iso:country":"CA",
    "sg:address":"3263 Rue Lafayette",
    "sg:city":"Sorel-Tracy",
    "sg:classifiers":[
        {
            "category":"Personal",
            "type":"Services"
        }
    ],
    "sg:phone":"+1 450 746 3850",
    "sg:postcode":"J3R 5L8",
    "sg:province":"QC",
    "sg:tags":[
        "control",
        "weight"
    ],
    "wof:name":"Energie Minceur Plus",
    "wof:placetype":"venue"
},
  "geometry": {"coordinates":[-73.162651,46.010044],"type":"Point"}
}