{
  "type": "Feature",
  "properties": {
    "addr:full":"701 Garyray Dr North York ON M9L 1R2",
    "addr:housenumber":"701",
    "addr:postcode":"m9l 1r2",
    "addr:street":"Garyray Dr",
    "iso:country":"CA",
    "sg:address":"701 Garyray Dr",
    "sg:city":"North York",
    "sg:classifiers":[
        {
            "category":"Manufacturing",
            "subcategory":"Rubber & Plastics",
            "type":"Manufacturing & Wholesale Goods"
        }
    ],
    "sg:phone":"+1 416 744 7411",
    "sg:postcode":"M9L 1R2",
    "sg:province":"ON",
    "sg:tags":[
        "gasket"
    ],
    "wof:name":"Precision Gaskets",
    "wof:placetype":"venue"
},
  "geometry": {"coordinates":[-79.554787,43.765686],"type":"Point"}
}