{
  "type": "Feature",
  "properties": {
    "addr:full":"8444 45 St NW Edmonton AB T6B 2N6",
    "addr:housenumber":"8444",
    "addr:postcode":"t6b 2n6",
    "addr:street":"45 St Nw",
    "iso:country":"CA",
    "sg:address":"8444 45 St NW",
    "sg:city":"Edmonton",
    "sg:classifiers":[
        {
            "category":"Manufacturing",
            "subcategory":"Tools & Machinery",
            "type":"Manufacturing & Wholesale Goods"
        }
    ],
    "sg:phone":"+1 780 469 0653",
    "sg:postcode":"T6B 2N6",
    "sg:province":"AB",
    "sg:tags":[
        "instrument",
        "radioactivity"
    ],
    "wof:name":"International Radiochemical",
    "wof:placetype":"venue"
},
  "geometry": {"coordinates":[-113.410552978,53.5199203491],"type":"Point"}
}