{
  "type": "Feature",
  "properties": {
    "iso:country":"CA",
    "sg:address":"25 Hillview Blvd",
    "sg:city":"London",
    "sg:classifiers":[
        {
            "category":"Education",
            "subcategory":"School",
            "type":"Public Place"
        }
    ],
    "sg:phone":"+1 519 452 8390",
    "sg:postcode":"N6G 3A7",
    "sg:province":"ON",
    "wof:name":"Masonville School",
    "wof:placetype":"venue"
},
  "geometry": {"coordinates":[-81.2830963135,43.0247306824],"type":"Point"}
}