{
  "type": "Feature",
  "properties": {
    "addr:full":"1402 Broad St Victoria BC V8W 2B1",
    "addr:housenumber":"1402",
    "addr:postcode":"v8w 2b1",
    "addr:street":"Broad St",
    "iso:country":"CA",
    "sg:address":"1402 Broad St",
    "sg:city":"Victoria",
    "sg:classifiers":[
        {
            "category":"Social Services",
            "type":"Services"
        }
    ],
    "sg:phone":"+1 250 383 7803",
    "sg:postcode":"V8W 2B1",
    "sg:province":"BC",
    "sg:tags":[
        "information",
        "organization",
        "treatment",
        "alcoholism",
        "welfare"
    ],
    "wof:name":"Alano Club",
    "wof:placetype":"venue"
},
  "geometry": {"coordinates":[-123.36621100000001,48.427448],"type":"Point"}
}