{
  "type": "Feature",
  "properties": {
    "iso:country":"CA",
    "sg:address":"253 Jevlan Dr",
    "sg:city":"Woodbridge",
    "sg:classifiers":[
        {
            "category":"Professional",
            "subcategory":"Lawyer & Legal Services",
            "type":"Services"
        }
    ],
    "sg:phone":"+1 905 850 2642",
    "sg:postcode":"L4L 7Z6",
    "sg:province":"ON",
    "sg:tags":[
        "attorney"
    ],
    "wof:name":"Panicali, Massimo S",
    "wof:placetype":"venue"
},
  "geometry": {"coordinates":[-79.54780599999999,43.800354],"type":"Point"}
}