{
  "type": "Feature",
  "properties": {
    "addr:full":"30 Peel Centre Dr Brampton ON L6T 4G3",
    "addr:housenumber":"30",
    "addr:postcode":"l6t 4g3",
    "addr:street":"Peel Centre Dr",
    "iso:country":"CA",
    "sg:address":"30 Peel Centre Dr",
    "sg:city":"Brampton",
    "sg:classifiers":[
        {
            "category":"Travel",
            "subcategory":"Hotels & Motels",
            "type":"Entertainment"
        }
    ],
    "sg:phone":"+1 905 792 9900",
    "sg:postcode":"L6T 4G3",
    "sg:province":"ON",
    "wof:name":"Holiday Inn Select Brampton",
    "wof:placetype":"venue"
},
  "geometry": {"coordinates":[-79.7240447998,43.7169837952],"type":"Point"}
}