{
  "type": "Feature",
  "properties": {
    "iso:country":"CA",
    "sg:city":"Ottawa",
    "sg:classifiers":[
        {
            "category":"Building & Trades",
            "subcategory":"Construction",
            "type":"Services"
        }
    ],
    "sg:phone":"+1 613 729 9299",
    "sg:postcode":"K1Z 5G5",
    "sg:province":"ON",
    "sg:tags":[
        "general",
        "contractor"
    ],
    "wof:name":"R A O'Hara Construction Ltd",
    "wof:placetype":"venue"
},
  "geometry": {"coordinates":[-75.7479400635,45.3819122314],"type":"Point"}
}