{
  "type": "Feature",
  "properties": {
    "addr:full":"215 Scott St Fort Frances ON P9A 1G8",
    "addr:housenumber":"215",
    "addr:postcode":"p9a 1g8",
    "addr:street":"Scott St",
    "iso:country":"CA",
    "sg:address":"215 Scott St",
    "sg:city":"Fort Frances",
    "sg:classifiers":[
        {
            "category":"Restaurant",
            "type":"Food & Drink"
        }
    ],
    "sg:phone":"+1 807 274 6310",
    "sg:postcode":"P9A 1G8",
    "sg:province":"ON",
    "wof:name":"Mr Sub",
    "wof:placetype":"venue"
},
  "geometry": {"coordinates":[-93.397972,48.60984],"type":"Point"}
}