{
  "type": "Feature",
  "properties": {
    "addr:full":"445 Boul DE L'Universite Rouyn-Noranda QC J9X 5E4",
    "addr:housenumber":"445",
    "addr:postcode":"j9x 5e4",
    "addr:street":"Boul De L'Universite",
    "iso:country":"CA",
    "sg:address":"445 Boul DE L'Universite",
    "sg:city":"Rouyn-Noranda",
    "sg:classifiers":[
        {
            "category":"Shopping",
            "subcategory":"Books",
            "type":"Retail Goods"
        }
    ],
    "sg:phone":"+1 819 762 0734",
    "sg:postcode":"J9X 5E4",
    "sg:province":"QC",
    "sg:tags":[
        "cooperative"
    ],
    "wof:name":"Coop Scolaire Le Signet",
    "wof:placetype":"venue"
},
  "geometry": {"coordinates":[-79.0073394775,48.2371025085],"type":"Point"}
}