{
  "type": "Feature",
  "properties": {
    "iso:country":"CA",
    "sg:address":"5 Rue Papineau",
    "sg:city":"Joliette",
    "sg:classifiers":[
        {
            "category":"Home & Garden",
            "subcategory":"Furniture",
            "type":"Retail Goods"
        }
    ],
    "sg:phone":"+1 450 752 2595",
    "sg:postcode":"J6E 2K3",
    "sg:province":"QC",
    "wof:name":"Ameublement Jc Perreault Inc",
    "wof:placetype":"venue"
},
  "geometry": {"coordinates":[-73.4424209595,46.0357055664],"type":"Point"}
}