{
  "type": "Feature",
  "properties": {
    "iso:country":"CA",
    "sg:city":"Peterborough",
    "sg:classifiers":[
        {
            "category":"Real Estate",
            "subcategory":"Real Estate Agent",
            "type":"Services"
        }
    ],
    "sg:phone":"+1 705 748 5411",
    "sg:postcode":"K9J 3G9",
    "sg:province":"ON",
    "sg:tags":[
        "management"
    ],
    "wof:name":"Babcock & Robinson",
    "wof:placetype":"venue"
},
  "geometry": {"coordinates":[-78.319916,44.301434],"type":"Point"}
}