{
  "type": "Feature",
  "properties": {
    "addr:full":"8153 Rawlings Rd Forest ON N0N 1J0",
    "addr:housenumber":"8153",
    "addr:postcode":"n0n 1j0",
    "addr:street":"Rawlings Rd",
    "iso:country":"CA",
    "sg:address":"8153 Rawlings Rd",
    "sg:city":"Forest",
    "sg:classifiers":[
        {
            "category":"Retail",
            "subcategory":"Auto Repair",
            "type":"Services"
        }
    ],
    "sg:phone":"+1 519 786 6874",
    "sg:postcode":"N0N 1J0",
    "sg:province":"ON",
    "sg:tags":[
        "repairing",
        "automobile",
        "parts",
        "supply"
    ],
    "wof:name":"Bowles Garage",
    "wof:placetype":"venue"
},
  "geometry": {"coordinates":[-81.98542,43.119919],"type":"Point"}
}