{
  "type": "Feature",
  "properties": {
    "addr:full":"1191 Johnston Rd White Rock BC V4B 3Y7",
    "addr:housenumber":"1191",
    "addr:postcode":"v4b 3y7",
    "addr:street":"Johnston Rd",
    "iso:country":"CA",
    "sg:address":"1191 Johnston Rd",
    "sg:city":"White Rock",
    "sg:classifiers":[
        {
            "category":"Restaurant",
            "type":"Food & Drink"
        }
    ],
    "sg:phone":"+1 604 541 9400",
    "sg:postcode":"V4B 3Y7",
    "sg:province":"BC",
    "sg:tags":[
        "pizza"
    ],
    "wof:name":"Damianos Pizza Ltd",
    "wof:placetype":"venue"
},
  "geometry": {"coordinates":[-122.801330566,49.0237464905],"type":"Point"}
}