{
  "type": "Feature",
  "properties": {
    "addr:full":"Langley BC V1M 2C9",
    "addr:postcode":"v1m 2c9",
    "iso:country":"CA",
    "sg:city":"Langley",
    "sg:classifiers":[
        {
            "category":"Shopping",
            "subcategory":"Pharmacy",
            "type":"Retail Goods"
        }
    ],
    "sg:phone":"+1 604 888 5602",
    "sg:postcode":"V1M 2C9",
    "sg:province":"BC",
    "wof:name":"Pharmasave Drugs",
    "wof:placetype":"venue"
},
  "geometry": {"coordinates":[-122.64019,49.163734],"type":"Point"}
}