{
  "type": "Feature",
  "properties": {
    "addr:full":"4320 Boul Saint-Laurent Montreal QC H2W 1Z3",
    "addr:housenumber":"4320",
    "addr:postcode":"h2w 1z3",
    "addr:street":"Boul Saint-Laurent",
    "iso:country":"CA",
    "sg:address":"4320 Boul Saint-Laurent",
    "sg:city":"Montreal",
    "sg:classifiers":[
        {
            "category":"Restaurant",
            "type":"Food & Drink"
        }
    ],
    "sg:phone":"+1 514 845 9462",
    "sg:postcode":"H2W 1Z3",
    "sg:province":"QC",
    "wof:name":"Bagel Etc",
    "wof:placetype":"venue"
},
  "geometry": {"coordinates":[-73.58380099999999,45.518848],"type":"Point"}
}