{
  "type": "Feature",
  "properties": {
    "addr:full":"Lillooet BC V0K 1V0",
    "addr:postcode":"v0k 1v0",
    "iso:country":"CA",
    "sg:city":"Lillooet",
    "sg:classifiers":[
        {
            "category":"Building & Trades",
            "subcategory":"Cleaning & Sanitation",
            "type":"Services"
        }
    ],
    "sg:phone":"+1 250 256 0301",
    "sg:postcode":"V0K 1V0",
    "sg:province":"BC",
    "sg:tags":[
        "janitor"
    ],
    "wof:name":"Shuswap Janitorial & Supplies",
    "wof:placetype":"venue"
},
  "geometry": {"coordinates":[-121.932846,50.682789],"type":"Point"}
}