{
  "type": "Feature",
  "properties": {
    "addr:full":"1461 Av Victoria Saint-Lambert QC J4R 1R5",
    "addr:housenumber":"1461",
    "addr:postcode":"j4r 1r5",
    "addr:street":"Av Victoria",
    "iso:country":"CA",
    "sg:address":"1461 Av Victoria",
    "sg:city":"Saint-Lambert",
    "sg:classifiers":[
        {
            "category":"Food & Beverages",
            "subcategory":"Groceries & Convenience Stores",
            "type":"Retail Goods"
        }
    ],
    "sg:phone":"+1 450 671 6205",
    "sg:postcode":"J4R 1R5",
    "sg:province":"QC",
    "sg:tags":[
        "grocer"
    ],
    "wof:name":"Provigo",
    "wof:placetype":"venue"
},
  "geometry": {"coordinates":[-73.49282073969999,45.489654541],"type":"Point"}
}