{
  "type": "Feature",
  "properties": {
    "iso:country":"CA",
    "sg:city":"New Westminster",
    "sg:classifiers":[
        {
            "category":"Professional",
            "subcategory":"Engineering",
            "type":"Services"
        }
    ],
    "sg:phone":"+1 604 525 4651",
    "sg:postcode":"V3L 5P5",
    "sg:province":"BC",
    "sg:tags":[
        "engineer"
    ],
    "wof:name":"Hunter Laird Engineering Ltd",
    "wof:placetype":"venue"
},
  "geometry": {"coordinates":[-122.896606445,49.2181816101],"type":"Point"}
}