{
  "type": "Feature",
  "properties": {
    "addr:full":"1840 38 St SE Calgary AB T2B 0Z3",
    "addr:housenumber":"1840",
    "addr:postcode":"t2b 0z3",
    "addr:street":"38 St Se",
    "iso:country":"CA",
    "sg:address":"1840 38 St SE",
    "sg:city":"Calgary",
    "sg:classifiers":[
        {
            "category":"Organizations",
            "subcategory":"Religious Organization",
            "type":"Services"
        }
    ],
    "sg:phone":"+1 403 273 8665",
    "sg:postcode":"T2B 0Z3",
    "sg:province":"AB",
    "sg:tags":[
        "church"
    ],
    "wof:name":"Korean First Presbyterian Chr",
    "wof:placetype":"venue"
},
  "geometry": {"coordinates":[-113.97843899999999,51.037178],"type":"Point"}
}