{
  "type": "Feature",
  "properties": {
    "iso:country":"CA",
    "sg:address":"72 Preston Rd",
    "sg:city":"Enderby",
    "sg:classifiers":[
        {
            "category":"Manufacturing",
            "subcategory":"Lumber",
            "type":"Manufacturing & Wholesale Goods"
        }
    ],
    "sg:phone":"+1 250 838 6955",
    "sg:postcode":"V0E 1V4",
    "sg:province":"BC",
    "sg:tags":[
        "company",
        "logging"
    ],
    "wof:name":"Marshall Mountain Contracting",
    "wof:placetype":"venue"
},
  "geometry": {"coordinates":[-119.15401458700001,50.5568008423],"type":"Point"}
}