{
  "type": "Feature",
  "properties": {
    "addr:full":"650 Georgia St W #1945 Vancouver BC V6B 6L7",
    "addr:housenumber":"650",
    "addr:postcode":"v6b 6l7",
    "addr:street":"Georgia St W # 1945",
    "iso:country":"CA",
    "sg:address":"650 Georgia St W #1945",
    "sg:city":"Vancouver",
    "sg:classifiers":[
        {
            "category":"Restaurant",
            "type":"Food & Drink"
        }
    ],
    "sg:phone":"+1 604 669 2924",
    "sg:postcode":"V6B 6L7",
    "sg:province":"BC",
    "sg:tags":[
        "sandwich"
    ],
    "wof:name":"Shimmers",
    "wof:placetype":"venue"
},
  "geometry": {"coordinates":[-123.117699,49.282082],"type":"Point"}
}