{
  "type": "Feature",
  "properties": {
    "addr:full":"490 Av Du Pont N Alma QC G8B 5E6",
    "addr:housenumber":"490",
    "addr:postcode":"g8b 5e6",
    "addr:street":"Av Du Pont N",
    "iso:country":"CA",
    "sg:address":"490 Av Du Pont N",
    "sg:city":"Alma",
    "sg:classifiers":[
        {
            "category":"Building & Trades",
            "subcategory":"Landscaping Services",
            "type":"Services"
        }
    ],
    "sg:phone":"+1 418 662 5533",
    "sg:postcode":"G8B 5E6",
    "sg:province":"QC",
    "sg:tags":[
        "lawn",
        "maintenance",
        "grounds"
    ],
    "wof:name":"Vertdure Alma",
    "wof:placetype":"venue"
},
  "geometry": {"coordinates":[-71.639122,48.556316],"type":"Point"}
}