{
  "type": "Feature",
  "properties": {
    "addr:full":"500 St. George St Moncton NB E1C 1Y3",
    "addr:housenumber":"500",
    "addr:postcode":"e1c 1y3",
    "addr:street":"St. George St",
    "iso:country":"CA",
    "sg:address":"500 St. George St",
    "sg:city":"Moncton",
    "sg:classifiers":[
        {
            "category":"Professional",
            "subcategory":"Management & Consulting",
            "type":"Services"
        }
    ],
    "sg:phone":"+1 506 857 8177",
    "sg:postcode":"E1C 1Y3",
    "sg:province":"NB",
    "sg:tags":[
        "consultant",
        "business"
    ],
    "wof:name":"Business Round Table",
    "wof:placetype":"venue"
},
  "geometry": {"coordinates":[-64.796341,46.088013],"type":"Point"}
}