{
  "type": "Feature",
  "properties": {
    "addr:full":"407 Rue Des Geais Rimouski QC G5L 7X2",
    "addr:housenumber":"407",
    "addr:postcode":"g5l 7x2",
    "addr:street":"Rue Des Geais",
    "iso:country":"CA",
    "sg:address":"407 Rue Des Geais",
    "sg:city":"Rimouski",
    "sg:classifiers":[
        {
            "category":"Personal",
            "subcategory":"Beauty Salon",
            "type":"Services"
        }
    ],
    "sg:phone":"+1 418 723 7440",
    "sg:postcode":"G5L 7X2",
    "sg:province":"QC",
    "wof:name":"Coiffure Chez Jocelyne Deschen",
    "wof:placetype":"venue"
},
  "geometry": {"coordinates":[-68.531539917,48.4317550659],"type":"Point"}
}