{
  "type": "Feature",
  "properties": {
    "addr:full":"6545 Rue Saint-Laurent Levis QC G6V 3N9",
    "addr:housenumber":"6545",
    "addr:postcode":"g6v 3n9",
    "addr:street":"Rue Saint-Laurent",
    "iso:country":"CA",
    "sg:address":"6545 Rue Saint-Laurent",
    "sg:city":"Levis",
    "sg:classifiers":[
        {
            "category":"Real Estate",
            "subcategory":"Real Estate Operator",
            "type":"Services"
        }
    ],
    "sg:phone":"+1 418 833 7494",
    "sg:postcode":"G6V 3N9",
    "sg:province":"QC",
    "sg:tags":[
        "apartment"
    ],
    "wof:name":"Condominium Pointe Belle-Vue",
    "wof:placetype":"venue"
},
  "geometry": {"coordinates":[-71.182434,46.819473],"type":"Point"}
}