{
  "type": "Feature",
  "properties": {
    "addr:full":"831 Riverside Ch Wakefield QC J0X 3G0",
    "addr:housenumber":"831",
    "addr:postcode":"j0x 3g0",
    "addr:street":"Riverside Ch",
    "iso:country":"CA",
    "sg:address":"831 Riverside Ch",
    "sg:city":"Wakefield",
    "sg:classifiers":[
        {
            "category":"Restaurant",
            "type":"Food & Drink"
        }
    ],
    "sg:phone":"+1 819 459 2885",
    "sg:postcode":"J0X 3G0",
    "sg:province":"QC",
    "sg:tags":[
        "motel",
        "hotel"
    ],
    "wof:name":"Alpengruss Cafe Motel Rstrnt",
    "wof:placetype":"venue"
},
  "geometry": {"coordinates":[-75.927841,45.641884],"type":"Point"}
}