{
  "type": "Feature",
  "properties": {
    "addr:full":"4719 Watson Cres Swan Hills AB T0G 2C0",
    "addr:housenumber":"4719",
    "addr:postcode":"t0g 2c0",
    "addr:street":"Watson Cres",
    "iso:country":"CA",
    "sg:address":"4719 Watson Cres",
    "sg:city":"Swan Hills",
    "sg:classifiers":[
        {
            "category":"Wholesale",
            "subcategory":"Machinery & Supplies",
            "type":"Manufacturing & Wholesale Goods"
        }
    ],
    "sg:phone":"+1 780 333 2108",
    "sg:postcode":"T0G 2C0",
    "sg:province":"AB",
    "sg:tags":[
        "equipment",
        "oil",
        "well"
    ],
    "wof:name":"National-Oilwell Canada Ltd",
    "wof:placetype":"venue"
},
  "geometry": {"coordinates":[-115.395782,54.711411],"type":"Point"}
}