{
  "type": "Feature",
  "properties": {
    "addr:full":"Vancouver BC V5T 4T1",
    "addr:postcode":"v5t 4t1",
    "iso:country":"CA",
    "sg:city":"Vancouver",
    "sg:classifiers":[
        {
            "category":"Wholesale",
            "subcategory":"Durable Goods & Equipment",
            "type":"Manufacturing & Wholesale Goods"
        }
    ],
    "sg:phone":"+1 604 877 0062",
    "sg:postcode":"V5T 4T1",
    "sg:province":"BC",
    "sg:tags":[
        "exporter"
    ],
    "wof:name":"Cyc Design Corp",
    "wof:placetype":"venue"
},
  "geometry": {"coordinates":[-123.098579407,49.2668685913],"type":"Point"}
}