{
  "type": "Feature",
  "properties": {
    "iso:country":"CA",
    "sg:address":"558 Upper Gage Ave # 6",
    "sg:city":"Hamilton",
    "sg:classifiers":[
        {
            "category":"Shopping",
            "subcategory":"Pharmacy",
            "type":"Retail Goods"
        }
    ],
    "sg:phone":"+1 905 574 5000",
    "sg:postcode":"L8V 4J6",
    "sg:province":"ON",
    "wof:name":"Upper Gage Pharmacy",
    "wof:placetype":"venue"
},
  "geometry": {"coordinates":[-79.8390426636,43.2284812927],"type":"Point"}
}