{
  "type": "Feature",
  "properties": {
    "iso:country":"CA",
    "sg:address":"400 Ch Compton",
    "sg:city":"Bromont",
    "sg:classifiers":[
        {
            "category":"Restaurant",
            "type":"Food & Drink"
        }
    ],
    "sg:phone":"+1 450 534 4653",
    "sg:postcode":"J2L 1E9",
    "sg:province":"QC",
    "wof:name":"Cellier Du Roi",
    "wof:placetype":"venue"
},
  "geometry": {"coordinates":[-72.6683883667,45.3284454346],"type":"Point"}
}