{
  "type": "Feature",
  "properties": {
    "addr:full":"Richmond BC V7C 4V4",
    "addr:postcode":"v7c 4v4",
    "iso:country":"CA",
    "sg:city":"Richmond",
    "sg:classifiers":[
        {
            "category":"Professional",
            "subcategory":"Business Services",
            "type":"Services"
        }
    ],
    "sg:phone":"+1 604 273 2788",
    "sg:postcode":"V7C 4V4",
    "sg:province":"BC",
    "sg:tags":[
        "translator",
        "interpreter"
    ],
    "wof:name":"Prolex Services Inc",
    "wof:placetype":"venue"
},
  "geometry": {"coordinates":[-123.15745544400001,49.170375824],"type":"Point"}
}