{
  "type": "Feature",
  "properties": {
    "iso:country":"CA",
    "sg:address":"106 Caledonia Rd",
    "sg:city":"Moncton",
    "sg:classifiers":[
        {
            "category":"Freight",
            "type":"Transportation"
        }
    ],
    "sg:phone":"+1 506 855 9140",
    "sg:postcode":"E1H 3C6",
    "sg:province":"NB",
    "sg:tags":[
        "trucking"
    ],
    "wof:name":"City Cross Dock",
    "wof:placetype":"venue"
},
  "geometry": {"coordinates":[-64.7602157593,46.131603241],"type":"Point"}
}