{
  "type": "Feature",
  "properties": {
    "iso:country":"CA",
    "sg:address":"323 7E Rang",
    "sg:city":"Saint-Theodore-D'Acton",
    "sg:classifiers":[
        {
            "category":"Travel",
            "subcategory":"Campground",
            "type":"Entertainment"
        }
    ],
    "sg:phone":"+1 450 546 3626",
    "sg:postcode":"J0H 1Z0",
    "sg:province":"QC",
    "sg:tags":[
        "camp",
        "fishing"
    ],
    "wof:name":"Pourvoirie Royaume Mac",
    "wof:placetype":"venue"
},
  "geometry": {"coordinates":[-72.4692001343,45.6854553223],"type":"Point"}
}