{
  "type": "Feature",
  "properties": {
    "addr:full":"821 Rue Principale Clair NB E7A 2H7",
    "addr:housenumber":"821",
    "addr:postcode":"e7a 2h7",
    "addr:street":"Rue Principale",
    "iso:country":"CA",
    "sg:address":"821 Rue Principale",
    "sg:city":"Clair",
    "sg:classifiers":[
        {
            "category":"Banks & Credit Unions",
            "subcategory":"Bank",
            "type":"Services"
        }
    ],
    "sg:phone":"+1 506 992 2158",
    "sg:postcode":"E7A 2H7",
    "sg:province":"NB",
    "wof:name":"Caisse Populaire DE Clair",
    "wof:placetype":"venue"
},
  "geometry": {"coordinates":[-68.60768899999999,47.249554],"type":"Point"}
}