{
  "type": "Feature",
  "properties": {
    "addr:full":"1111 Ghislain St Hawkesbury ON K6A 3G5",
    "addr:housenumber":"1111",
    "addr:postcode":"k6a 3g5",
    "addr:street":"Ghislain St",
    "iso:country":"CA",
    "sg:address":"1111 Ghislain St",
    "sg:city":"Hawkesbury",
    "sg:classifiers":[
        {
            "category":"Health Services",
            "subcategory":"Clinic",
            "type":"Services"
        }
    ],
    "sg:phone":"+1 613 632 4861",
    "sg:postcode":"K6A 3G5",
    "sg:province":"ON",
    "sg:tags":[
        "home"
    ],
    "wof:name":"Community Care Access Ctr",
    "wof:placetype":"venue"
},
  "geometry": {"coordinates":[-74.607872,45.598743],"type":"Point"}
}