{
  "type": "Feature",
  "properties": {
    "addr:full":"3009 St Joseph Blvd Orleans ON K1E 1E1",
    "addr:housenumber":"3009",
    "addr:postcode":"k1e 1e1",
    "addr:street":"St Joseph Blvd",
    "iso:country":"CA",
    "sg:address":"3009 St Joseph Blvd",
    "sg:city":"Orleans",
    "sg:classifiers":[
        {
            "category":"Professional",
            "subcategory":"Lawyer & Legal Services",
            "type":"Services"
        }
    ],
    "sg:phone":"+1 613 837 7408",
    "sg:postcode":"K1E 1E1",
    "sg:province":"ON",
    "sg:tags":[
        "attorney"
    ],
    "wof:name":"Sicotte & Assoc",
    "wof:placetype":"venue"
},
  "geometry": {"coordinates":[-75.51467100000001,45.476639],"type":"Point"}
}