{
  "type": "Feature",
  "properties": {
    "addr:full":"Sainte-Foy QC G1X 4Y5",
    "addr:postcode":"g1x 4y5",
    "iso:country":"CA",
    "sg:city":"Sainte-Foy",
    "sg:classifiers":[
        {
            "category":"Personal",
            "subcategory":"Beauty Salon",
            "type":"Services"
        }
    ],
    "sg:phone":"+1 418 877 9900",
    "sg:postcode":"G1X 4Y5",
    "sg:province":"QC",
    "wof:name":"Centre Beaute Sante Genese",
    "wof:placetype":"venue"
},
  "geometry": {"coordinates":[-71.36887400000001,46.765717],"type":"Point"}
}