{
  "type": "Feature",
  "properties": {
    "iso:country":"CA",
    "sg:city":"St. John's",
    "sg:classifiers":[
        {
            "category":"Recreation",
            "type":"Entertainment"
        }
    ],
    "sg:phone":"+1 709 579 9255",
    "sg:postcode":"A1E 6A8",
    "sg:province":"NL",
    "sg:tags":[
        "center",
        "amusement"
    ],
    "wof:name":"Wallnuts Climbing Ctr",
    "wof:placetype":"venue"
},
  "geometry": {"coordinates":[-52.7492790222,47.5560340881],"type":"Point"}
}