{
  "type": "Feature",
  "properties": {
    "iso:country":"CA",
    "sg:address":"5303 50 Ave",
    "sg:city":"Valleyview",
    "sg:classifiers":[
        {
            "category":"Wholesale",
            "subcategory":"Durable Goods & Equipment",
            "type":"Manufacturing & Wholesale Goods"
        }
    ],
    "sg:phone":"+1 780 524 4221",
    "sg:postcode":"T0H 3N0",
    "sg:province":"AB",
    "sg:tags":[
        "exporter"
    ],
    "wof:name":"International Supply Svc Ltd",
    "wof:placetype":"venue"
},
  "geometry": {"coordinates":[-117.27279663100001,55.0686187744],"type":"Point"}
}