{
  "type": "Feature",
  "properties": {
    "addr:full":"Montreal QC H2N 2J6",
    "addr:postcode":"h2n 2j6",
    "iso:country":"CA",
    "sg:city":"Montreal",
    "sg:classifiers":[
        {
            "category":"Shopping",
            "subcategory":"Clothing, Apparel, & Fashions",
            "type":"Retail Goods"
        }
    ],
    "sg:phone":"+1 514 387 6275",
    "sg:postcode":"H2N 2J6",
    "sg:province":"QC",
    "sg:tags":[
        "furnishing"
    ],
    "wof:name":"Importations Resistance",
    "wof:placetype":"venue"
},
  "geometry": {"coordinates":[-73.6488647461,45.5484313965],"type":"Point"}
}