{
  "type": "Feature",
  "properties": {
    "addr:full":"20 Rue Des Pionniers Angliers QC J0Z 1A0",
    "addr:housenumber":"20",
    "addr:postcode":"j0z 1a0",
    "addr:street":"Rue Des Pionniers",
    "iso:country":"CA",
    "sg:address":"20 Rue Des Pionniers",
    "sg:city":"Angliers",
    "sg:classifiers":[
        {
            "category":"Food & Beverages",
            "subcategory":"Groceries & Convenience Stores",
            "type":"Retail Goods"
        }
    ],
    "sg:phone":"+1 819 949 2002",
    "sg:postcode":"J0Z 1A0",
    "sg:province":"QC",
    "sg:tags":[
        "grocer"
    ],
    "wof:name":"Marche Leane",
    "wof:placetype":"venue"
},
  "geometry": {"coordinates":[-79.2346115112,47.545791626],"type":"Point"}
}