{
  "type": "Feature",
  "properties": {
    "iso:country":"CA",
    "sg:address":"94 Riverside Dr",
    "sg:city":"North Vancouver",
    "sg:classifiers":[
        {
            "category":"Manufacturing",
            "subcategory":"Metals",
            "type":"Manufacturing & Wholesale Goods"
        }
    ],
    "sg:phone":"+1 604 929 1214",
    "sg:postcode":"V7H 2M6",
    "sg:province":"BC",
    "sg:tags":[
        "boiler"
    ],
    "wof:name":"Allied Engineering CO",
    "wof:placetype":"venue"
},
  "geometry": {"coordinates":[-123.014191,49.305355],"type":"Point"}
}