{
  "type": "Feature",
  "properties": {
    "addr:full":"1138 Rue Mcmanamy Sherbrooke QC J1H 2N8",
    "addr:housenumber":"1138",
    "addr:postcode":"j1h 2n8",
    "addr:street":"Rue Mcmanamy",
    "iso:country":"CA",
    "sg:address":"1138 Rue Mcmanamy",
    "sg:city":"Sherbrooke",
    "sg:classifiers":[
        {
            "category":"Manufacturing",
            "subcategory":"Printing",
            "type":"Manufacturing & Wholesale Goods"
        }
    ],
    "sg:phone":"+1 819 346 3071",
    "sg:postcode":"J1H 2N8",
    "sg:province":"QC",
    "sg:tags":[
        "printer"
    ],
    "wof:name":"Imprimerie Jmh",
    "wof:placetype":"venue"
},
  "geometry": {"coordinates":[-71.904892,45.389408],"type":"Point"}
}