{
  "type": "Feature",
  "properties": {
    "addr:full":"Vancouver BC V5T 4S7",
    "addr:postcode":"v5t 4s7",
    "iso:country":"CA",
    "sg:city":"Vancouver",
    "sg:classifiers":[
        {
            "category":"Education",
            "subcategory":"Special Training",
            "type":"Public Place"
        }
    ],
    "sg:phone":"+1 604 732 1799",
    "sg:postcode":"V5T 4S7",
    "sg:province":"BC",
    "sg:tags":[
        "management"
    ],
    "wof:name":"Arete Safety & Protection",
    "wof:placetype":"venue"
},
  "geometry": {"coordinates":[-123.10310363799999,49.2643852234],"type":"Point"}
}