{
  "type": "Feature",
  "properties": {
    "addr:full":"45 Cluett Dr Ajax ON L1S 7C4",
    "addr:housenumber":"45",
    "addr:postcode":"l1s 7c4",
    "addr:street":"Cluett Dr",
    "iso:country":"CA",
    "sg:address":"45 Cluett Dr",
    "sg:city":"Ajax",
    "sg:classifiers":[
        {
            "category":"Building & Trades",
            "subcategory":"Landscaping Services",
            "type":"Services"
        }
    ],
    "sg:phone":"+1 905 427 6885",
    "sg:postcode":"L1S 7C4",
    "sg:province":"ON",
    "sg:tags":[
        "lawn",
        "maintenance",
        "grounds"
    ],
    "wof:name":"Extra Care Property Mntnce",
    "wof:placetype":"venue"
},
  "geometry": {"coordinates":[-78.998222,43.835831],"type":"Point"}
}