{
  "type": "Feature",
  "properties": {
    "addr:full":"381 Stephen St Boissevain MB R0K 0E0",
    "addr:housenumber":"381",
    "addr:postcode":"r0k 0e0",
    "addr:street":"Stephen St",
    "iso:country":"CA",
    "sg:address":"381 Stephen St",
    "sg:city":"Boissevain",
    "sg:classifiers":[
        {
            "category":"Building & Trades",
            "subcategory":"Construction",
            "type":"Services"
        }
    ],
    "sg:phone":"+1 204 534 7247",
    "sg:postcode":"R0K 0E0",
    "sg:province":"MB",
    "sg:tags":[
        "general",
        "contractor"
    ],
    "wof:name":"Jim Fluker Construction Ltd",
    "wof:placetype":"venue"
},
  "geometry": {"coordinates":[-100.059455872,49.2296257019],"type":"Point"}
}