{
  "type": "Feature",
  "properties": {
    "iso:country":"CA",
    "sg:address":"58 the Esplanade",
    "sg:city":"Toronto",
    "sg:classifiers":[
        {
            "category":"Restaurant",
            "type":"Food & Drink"
        }
    ],
    "sg:phone":"+1 416 862 7575",
    "sg:postcode":"M5E 1A6",
    "sg:province":"ON",
    "wof:name":"Bier Market",
    "wof:placetype":"venue"
},
  "geometry": {"coordinates":[-79.3739776611,43.6470870972],"type":"Point"}
}