{
  "type": "Feature",
  "properties": {
    "iso:country":"CA",
    "sg:address":"186 Kenneth St",
    "sg:city":"Duncan",
    "sg:classifiers":[
        {
            "category":"Health Services",
            "subcategory":"Medical Lab",
            "type":"Services"
        }
    ],
    "sg:phone":"+1 250 746 1599",
    "sg:postcode":"V9L 1N4",
    "sg:province":"BC",
    "sg:tags":[
        "laboratory"
    ],
    "wof:name":"Mds Metro Laboratory Svc",
    "wof:placetype":"venue"
},
  "geometry": {"coordinates":[-123.71005249,48.778339386],"type":"Point"}
}