{
  "type": "Feature",
  "properties": {
    "addr:full":"5616 Hwy 3 Shag Harbour NS B0W 3B0",
    "addr:housenumber":"5616",
    "addr:postcode":"b0w 3b0",
    "addr:street":"Hwy 3",
    "iso:country":"CA",
    "sg:address":"5616 Hwy 3",
    "sg:city":"Shag Harbour",
    "sg:classifiers":[
        {
            "category":"Shopping",
            "subcategory":"Discount & Variety Stores",
            "type":"Retail Goods"
        }
    ],
    "sg:phone":"+1 902 723 0804",
    "sg:postcode":"B0W 3B0",
    "sg:province":"NS",
    "sg:tags":[
        "merchandise",
        "general"
    ],
    "wof:name":"Bon Portage General Store",
    "wof:placetype":"venue"
},
  "geometry": {"coordinates":[-65.71127300000001,43.493191],"type":"Point"}
}