{
  "type": "Feature",
  "properties": {
    "addr:full":"4540 50 Ave SE Calgary AB T2B 3R4",
    "addr:housenumber":"4540",
    "addr:postcode":"t2b 3r4",
    "addr:street":"50 Ave Se",
    "iso:country":"CA",
    "sg:address":"4540 50 Ave SE",
    "sg:city":"Calgary",
    "sg:classifiers":[
        {
            "category":"Wholesale",
            "subcategory":"Machinery & Supplies",
            "type":"Manufacturing & Wholesale Goods"
        }
    ],
    "sg:phone":"+1 403 720 3201",
    "sg:postcode":"T2B 3R4",
    "sg:province":"AB",
    "sg:tags":[
        "machine",
        "tool"
    ],
    "wof:name":"Thomas Skinner & Son Ltd",
    "wof:placetype":"venue"
},
  "geometry": {"coordinates":[-113.96796399999999,51.008869],"type":"Point"}
}