{
  "type": "Feature",
  "properties": {
    "addr:full":"6250 Quinpool Rd Halifax NS B3L 1A3",
    "addr:housenumber":"6250",
    "addr:postcode":"b3l 1a3",
    "addr:street":"Quinpool Rd",
    "iso:country":"CA",
    "sg:address":"6250 Quinpool Rd",
    "sg:city":"Halifax",
    "sg:classifiers":[
        {
            "category":"Restaurant",
            "type":"Food & Drink"
        }
    ],
    "sg:phone":"+1 902 425 2808",
    "sg:postcode":"B3L 1A3",
    "sg:province":"NS",
    "wof:name":"Heartwood Bakery & Cafe",
    "wof:placetype":"venue"
},
  "geometry": {"coordinates":[-63.59715271,44.6452903748],"type":"Point"}
}