{
  "type": "Feature",
  "properties": {
    "iso:country":"CA",
    "sg:address":"398 Boul Cartier O",
    "sg:city":"Laval",
    "sg:classifiers":[
        {
            "category":"Shopping",
            "type":"Retail Goods"
        }
    ],
    "sg:phone":"+1 450 669 7398",
    "sg:postcode":"H7N 2K7",
    "sg:province":"QC",
    "sg:tags":[
        "metaphysical",
        "supply"
    ],
    "wof:name":"Boutique LA Magie Des Anges",
    "wof:placetype":"venue"
},
  "geometry": {"coordinates":[-73.711617,45.549923],"type":"Point"}
}