{
  "type": "Feature",
  "properties": {
    "addr:full":"Boissevain MB R0K 0E0",
    "addr:postcode":"r0k 0e0",
    "iso:country":"CA",
    "sg:city":"Boissevain",
    "sg:classifiers":[
        {
            "category":"Wholesale",
            "subcategory":"Machinery & Supplies",
            "type":"Manufacturing & Wholesale Goods"
        }
    ],
    "sg:phone":"+1 204 534 2463",
    "sg:postcode":"R0K 0E0",
    "sg:province":"MB",
    "sg:tags":[
        "farm",
        "equipment"
    ],
    "wof:name":"Red Power & Equipment Inc",
    "wof:placetype":"venue"
},
  "geometry": {"coordinates":[-100.059456,49.232216],"type":"Point"}
}