{
  "type": "Feature",
  "properties": {
    "iso:country":"CA",
    "sg:address":"3469 Lawrence Ave E",
    "sg:city":"Scarborough",
    "sg:classifiers":[
        {
            "category":"Shopping",
            "subcategory":"Department Store",
            "type":"Retail Goods"
        }
    ],
    "sg:phone":"+1 416 431 9729",
    "sg:postcode":"M1H 1B2",
    "sg:province":"ON",
    "wof:name":"Zellers",
    "wof:placetype":"venue"
},
  "geometry": {"coordinates":[-79.229713,43.758736],"type":"Point"}
}