{
  "type": "Feature",
  "properties": {
    "addr:full":"724 55 Ave SW Calgary AB T2V 0G3",
    "addr:postcode":"t2v 0g3",
    "addr:street":"724 55 Ave Sw",
    "iso:country":"CA",
    "sg:address":"724 55 Ave SW",
    "sg:city":"Calgary",
    "sg:classifiers":[
        {
            "category":"Banks & Credit Unions",
            "subcategory":"Bank",
            "type":"Services"
        }
    ],
    "sg:phone":"+1 403 255 3100",
    "sg:postcode":"T2V 0G3",
    "sg:province":"AB",
    "sg:tags":[
        "loan",
        "real estate"
    ],
    "wof:name":"Base Mortgage & Investments",
    "wof:placetype":"venue"
},
  "geometry": {"coordinates":[-114.079582214,51.0044441223],"type":"Point"}
}