{
  "type": "Feature",
  "properties": {
    "addr:full":"3025 New St Burlington ON L7R 1K3",
    "addr:housenumber":"3025",
    "addr:postcode":"l7r 1k3",
    "addr:street":"New St",
    "iso:country":"CA",
    "sg:address":"3025 New St",
    "sg:city":"Burlington",
    "sg:classifiers":[
        {
            "category":"Personal",
            "subcategory":"Barber",
            "type":"Services"
        }
    ],
    "sg:phone":"+1 905 637 8745",
    "sg:postcode":"L7R 1K3",
    "sg:province":"ON",
    "wof:name":"Super Scissors Hairstylists",
    "wof:placetype":"venue"
},
  "geometry": {"coordinates":[-79.7845001221,43.3392562866],"type":"Point"}
}