{
  "type": "Feature",
  "properties": {
    "iso:country":"CA",
    "sg:address":"37 Main St S",
    "sg:city":"Georgetown",
    "sg:classifiers":[
        {
            "category":"Professional",
            "subcategory":"Lawyer & Legal Services",
            "type":"Services"
        }
    ],
    "sg:phone":"+1 905 877 0121",
    "sg:postcode":"L7G 3G2",
    "sg:province":"ON",
    "sg:tags":[
        "attorney"
    ],
    "wof:name":"Manderson, William H",
    "wof:placetype":"venue"
},
  "geometry": {"coordinates":[-79.92700958250001,43.6503181458],"type":"Point"}
}