{
  "type": "Feature",
  "properties": {
    "addr:full":"5401 Temple Dr NE Calgary AB T1Y 3R7",
    "addr:housenumber":"5401",
    "addr:postcode":"t1y 3r7",
    "addr:street":"Temple Dr Ne",
    "iso:country":"CA",
    "sg:address":"5401 Temple Dr NE",
    "sg:city":"Calgary",
    "sg:classifiers":[
        {
            "category":"Education",
            "subcategory":"Dance Studio",
            "type":"Public Place"
        }
    ],
    "sg:phone":"+1 403 279 4807",
    "sg:postcode":"T1Y 3R7",
    "sg:province":"AB",
    "sg:tags":[
        "instruction",
        "dancing"
    ],
    "wof:name":"Kate's Dance Academy",
    "wof:placetype":"venue"
},
  "geometry": {"coordinates":[-113.95652800000001,51.085758],"type":"Point"}
}