{
  "type": "Feature",
  "properties": {
    "iso:country":"CA",
    "sg:address":"330 Highway 7 E # 118",
    "sg:city":"Richmond Hill",
    "sg:classifiers":[
        {
            "category":"Shopping",
            "subcategory":"Florist",
            "type":"Retail Goods"
        }
    ],
    "sg:phone":"+1 905 881 3237",
    "sg:postcode":"L4B 3P8",
    "sg:province":"ON",
    "wof:name":"Lucky Flower House",
    "wof:placetype":"venue"
},
  "geometry": {"coordinates":[-79.37847137449999,43.8465538025],"type":"Point"}
}