{
  "type": "Feature",
  "properties": {
    "addr:full":"285 Beatty Line Fergus ON N1M 2W2",
    "addr:housenumber":"285",
    "addr:postcode":"n1m 2w2",
    "addr:street":"Beatty Line",
    "iso:country":"CA",
    "sg:address":"285 Beatty Line",
    "sg:city":"Fergus",
    "sg:classifiers":[
        {
            "category":"Shopping",
            "subcategory":"Used Merchandise",
            "type":"Retail Goods"
        }
    ],
    "sg:phone":"+1 519 843 3722",
    "sg:postcode":"N1M 2W2",
    "sg:province":"ON",
    "sg:tags":[
        "book",
        "rare",
        "dealer"
    ],
    "wof:name":"Quality Used Books",
    "wof:placetype":"venue"
},
  "geometry": {"coordinates":[-80.386101,43.697659],"type":"Point"}
}