{
  "type": "Feature",
  "properties": {
    "addr:full":"21 Exeter St North Bay ON P1B 8G5",
    "addr:housenumber":"21",
    "addr:postcode":"p1b 8g5",
    "addr:street":"Exeter St",
    "iso:country":"CA",
    "sg:address":"21 Exeter St",
    "sg:city":"North Bay",
    "sg:classifiers":[
        {
            "category":"Manufacturing",
            "subcategory":"Tools & Machinery",
            "type":"Manufacturing & Wholesale Goods"
        }
    ],
    "sg:phone":"+1 705 472 5207",
    "sg:postcode":"P1B 8G5",
    "sg:province":"ON",
    "sg:tags":[
        "equipment",
        "hydraulic",
        "supply"
    ],
    "wof:name":"Mining Technologies Intl Inc",
    "wof:placetype":"venue"
},
  "geometry": {"coordinates":[-79.49406399999999,46.325382],"type":"Point"}
}