{
  "type": "Feature",
  "properties": {
    "addr:full":"1273 Bloor St W Toronto ON M6H 1N7",
    "addr:housenumber":"1273",
    "addr:postcode":"m6h 1n7",
    "addr:street":"Bloor St W",
    "iso:country":"CA",
    "sg:address":"1273 Bloor St W",
    "sg:city":"Toronto",
    "sg:classifiers":[
        {
            "category":"Shopping",
            "subcategory":"Used Merchandise",
            "type":"Retail Goods"
        }
    ],
    "sg:phone":"+1 416 539 9170",
    "sg:postcode":"M6H 1N7",
    "sg:province":"ON",
    "sg:tags":[
        "pawnbroker"
    ],
    "wof:name":"Sunny Jewellery & Pawnshop",
    "wof:placetype":"venue"
},
  "geometry": {"coordinates":[-79.442116,43.658325],"type":"Point"}
}