{
  "type": "Feature",
  "properties": {
    "addr:full":"999 Upper Wentworth St # 135A Hamilton ON L9A 4X5",
    "addr:housenumber":"999;135a",
    "addr:postcode":"l9a 4x5",
    "addr:street":"Upper Wentworth St #",
    "iso:country":"CA",
    "sg:address":"999 Upper Wentworth St # 135A",
    "sg:city":"Hamilton",
    "sg:classifiers":[
        {
            "category":"Shopping",
            "subcategory":"Clothing, Apparel, & Fashions",
            "type":"Retail Goods"
        }
    ],
    "sg:phone":"+1 905 574 4818",
    "sg:postcode":"L9A 4X5",
    "sg:province":"ON",
    "sg:tags":[
        "hat"
    ],
    "wof:name":"Headquarters",
    "wof:placetype":"venue"
},
  "geometry": {"coordinates":[-79.86444899999999,43.216717],"type":"Point"}
}