{
  "type": "Feature",
  "properties": {
    "addr:full":"277 Castor St Russell ON K4R 1B8",
    "addr:housenumber":"277",
    "addr:postcode":"k4r 1b8",
    "addr:street":"Castor St",
    "iso:country":"CA",
    "sg:address":"277 Castor St",
    "sg:city":"Russell",
    "sg:classifiers":[
        {
            "category":"Restaurant",
            "type":"Food & Drink"
        }
    ],
    "sg:phone":"+1 613 445 3743",
    "sg:postcode":"K4R 1B8",
    "sg:province":"ON",
    "wof:name":"Mimi's Fries",
    "wof:placetype":"venue"
},
  "geometry": {"coordinates":[-75.35240899999999,45.259724],"type":"Point"}
}