{
  "type": "Feature",
  "properties": {
    "iso:country":"CA",
    "sg:address":"2820 50th St",
    "sg:city":"Smoky Lake",
    "sg:classifiers":[
        {
            "category":"Retail",
            "subcategory":"Auto Repair",
            "type":"Services"
        }
    ],
    "sg:phone":"+1 780 656 3668",
    "sg:postcode":"T0A 3C0",
    "sg:province":"AB",
    "sg:tags":[
        "body",
        "automobile",
        "painting"
    ],
    "wof:name":"Correction Autobody",
    "wof:placetype":"venue"
},
  "geometry": {"coordinates":[-112.47588348399999,54.0951690674],"type":"Point"}
}