{
  "type": "Feature",
  "properties": {
    "iso:country":"CA",
    "sg:address":"4770 46 Ave SE",
    "sg:city":"Salmon Arm",
    "sg:classifiers":[
        {
            "category":"Wholesale",
            "subcategory":"Machinery & Supplies",
            "type":"Manufacturing & Wholesale Goods"
        }
    ],
    "sg:phone":"+1 250 833 1944",
    "sg:postcode":"V1E 2W1",
    "sg:province":"BC",
    "sg:tags":[
        "equipment",
        "sawmill"
    ],
    "wof:name":"Wood-Mizer Canada West",
    "wof:placetype":"venue"
},
  "geometry": {"coordinates":[-119.232719421,50.6679763794],"type":"Point"}
}