{
  "type": "Feature",
  "properties": {
    "addr:full":"5 Fairway Blvd Bancroft ON K0L 1C0",
    "addr:housenumber":"5",
    "addr:postcode":"k0l 1c0",
    "addr:street":"Fairway Blvd",
    "iso:country":"CA",
    "sg:address":"5 Fairway Blvd",
    "sg:city":"Bancroft",
    "sg:classifiers":[
        {
            "category":"Government",
            "subcategory":"Office",
            "type":"Public Place"
        }
    ],
    "sg:phone":"+1 613 332 4040",
    "sg:postcode":"K0L 1C0",
    "sg:province":"ON",
    "wof:name":"Ontario Probation & Parole",
    "wof:placetype":"venue"
},
  "geometry": {"coordinates":[-77.86236572270001,45.084777832],"type":"Point"}
}