{
  "type": "Feature",
  "properties": {
    "addr:full":"501 University Cres Winnipeg MB R3T 2N6",
    "addr:housenumber":"501",
    "addr:postcode":"r3t 2n6",
    "addr:street":"University Cres",
    "iso:country":"CA",
    "sg:address":"501 University Cres",
    "sg:city":"Winnipeg",
    "sg:classifiers":[
        {
            "category":"Restaurant",
            "type":"Food & Drink"
        }
    ],
    "sg:phone":"+1 204 269 2488",
    "sg:postcode":"R3T 2N6",
    "sg:province":"MB",
    "sg:tags":[
        "caterer"
    ],
    "wof:name":"Canadian Select Food Svc",
    "wof:placetype":"venue"
},
  "geometry": {"coordinates":[-97.1390533447,49.8056602478],"type":"Point"}
}