{
  "type": "Feature",
  "properties": {
    "addr:full":"5110 Boul Jean-Xxiii Trois-Rivieres-Ouest QC G8Z 4A7",
    "addr:housenumber":"5110",
    "addr:postcode":"g8z 4a7",
    "addr:street":"Boul Jean-Xxiii Trois-Rivieres-Ouest",
    "iso:country":"CA",
    "sg:address":"5110 Boul Jean-Xxiii",
    "sg:city":"Trois-Rivieres-Ouest",
    "sg:classifiers":[
        {
            "category":"Autos & Motor Vehicles",
            "subcategory":"Automobile Sales",
            "type":"Retail Goods"
        }
    ],
    "sg:phone":"+1 819 374 5323",
    "sg:postcode":"G8Z 4A7",
    "sg:province":"QC",
    "sg:tags":[
        "car",
        "dealer"
    ],
    "wof:name":"Trois-Rivieres Toyota Ltee",
    "wof:placetype":"venue"
},
  "geometry": {"coordinates":[-72.59326934809999,46.3322525024],"type":"Point"}
}