{
  "type": "Feature",
  "properties": {
    "addr:full":"Toronto ON M6H 1V7",
    "addr:postcode":"m6h 1v7",
    "iso:country":"CA",
    "sg:city":"Toronto",
    "sg:classifiers":[
        {
            "category":"Retail",
            "subcategory":"Portrait Studio",
            "type":"Services"
        }
    ],
    "sg:phone":"+1 416 588 8864",
    "sg:postcode":"M6H 1V7",
    "sg:province":"ON",
    "sg:tags":[
        "photographer"
    ],
    "wof:name":"David Beckett Photography",
    "wof:placetype":"venue"
},
  "geometry": {"coordinates":[-79.4459991455,43.6621017456],"type":"Point"}
}