{
  "type": "Feature",
  "properties": {
    "addr:full":"Etobicoke ON M9W 6Y6",
    "addr:postcode":"m9w 6y6",
    "iso:country":"CA",
    "sg:city":"Etobicoke",
    "sg:classifiers":[
        {
            "category":"Building & Trades",
            "subcategory":"Electrical",
            "type":"Services"
        }
    ],
    "sg:phone":"+1 416 798 0096",
    "sg:postcode":"M9W 6Y6",
    "sg:province":"ON",
    "sg:tags":[
        "electric",
        "contractor"
    ],
    "wof:name":"Ici Automation",
    "wof:placetype":"venue"
},
  "geometry": {"coordinates":[-79.62312300000001,43.750927],"type":"Point"}
}