{
  "type": "Feature",
  "properties": {
    "addr:full":"1099 Kingston Rd # 212 Pickering ON L1V 1B5",
    "addr:housenumber":"1099",
    "addr:postcode":"l1v 1b5",
    "addr:street":"Kingston Rd # 212",
    "iso:country":"CA",
    "sg:address":"1099 Kingston Rd # 212",
    "sg:city":"Pickering",
    "sg:classifiers":[
        {
            "category":"Manufacturing",
            "subcategory":"Electronics",
            "type":"Manufacturing & Wholesale Goods"
        }
    ],
    "sg:phone":"+1 905 837 5666",
    "sg:postcode":"L1V 1B5",
    "sg:province":"ON",
    "sg:tags":[
        "control",
        "security",
        "system"
    ],
    "wof:name":"Deister Electronics Inc",
    "wof:placetype":"venue"
},
  "geometry": {"coordinates":[-79.09833526609999,43.8290138245],"type":"Point"}
}