{
  "type": "Feature",
  "properties": {
    "addr:full":"43 6th Ave W Vancouver BC V5Y 1K2",
    "addr:housenumber":"43",
    "addr:postcode":"v5y 1k2",
    "addr:street":"6Th Ave W",
    "iso:country":"CA",
    "sg:address":"43 6th Ave W",
    "sg:city":"Vancouver",
    "sg:classifiers":[
        {
            "category":"Wholesale",
            "subcategory":"Vending Machines",
            "type":"Manufacturing & Wholesale Goods"
        }
    ],
    "sg:phone":"+1 604 876 2824",
    "sg:postcode":"V5Y 1K2",
    "sg:province":"BC",
    "wof:name":"Modern-Pak Mfg CO",
    "wof:placetype":"venue"
},
  "geometry": {"coordinates":[-123.10568237299999,49.2657394409],"type":"Point"}
}