{
  "type": "Feature",
  "properties": {
    "addr:full":"1244 Commissioners Rd W London ON N6K 1C7",
    "addr:housenumber":"1244",
    "addr:postcode":"n6k 1c7",
    "addr:street":"Commissioners Rd W",
    "iso:country":"CA",
    "sg:address":"1244 Commissioners Rd W",
    "sg:city":"London",
    "sg:classifiers":[
        {
            "category":"Shopping",
            "subcategory":"Florist",
            "type":"Retail Goods"
        }
    ],
    "sg:phone":"+1 519 473 3389",
    "sg:postcode":"N6K 1C7",
    "sg:province":"ON",
    "sg:tags":[
        "grocer",
        "pharmacy"
    ],
    "wof:name":"A & P Food Stores Pharmacies",
    "wof:placetype":"venue"
},
  "geometry": {"coordinates":[-81.3313903809,42.9591636658],"type":"Point"}
}