{
  "type": "Feature",
  "properties": {
    "addr:full":"13549 Bentley Rd Surrey BC V3R 5B8",
    "addr:housenumber":"13549",
    "addr:postcode":"v3r 5b8",
    "addr:street":"Bentley Rd",
    "iso:country":"CA",
    "sg:address":"13549 Bentley Rd",
    "sg:city":"Surrey",
    "sg:classifiers":[
        {
            "category":"Recreation",
            "type":"Entertainment"
        }
    ],
    "sg:phone":"+1 604 580 3940",
    "sg:postcode":"V3R 5B8",
    "sg:province":"BC",
    "sg:tags":[
        "martial",
        "arts",
        "instruction"
    ],
    "wof:name":"Fasso Martial Art School Ltd",
    "wof:placetype":"venue"
},
  "geometry": {"coordinates":[-122.84684799999999,49.200607],"type":"Point"}
}