{
  "type": "Feature",
  "properties": {
    "addr:full":"1616 Duranleau St Vancouver BC V6H 3S4",
    "addr:housenumber":"1616",
    "addr:postcode":"v6h 3s4",
    "addr:street":"Duranleau St",
    "iso:country":"CA",
    "sg:address":"1616 Duranleau St",
    "sg:city":"Vancouver",
    "sg:classifiers":[
        {
            "category":"Shopping",
            "subcategory":"Bicycles & Sporting Goods",
            "type":"Retail Goods"
        }
    ],
    "sg:phone":"+1 604 683 8388",
    "sg:postcode":"V6H 3S4",
    "sg:province":"BC",
    "wof:name":"Specialties West",
    "wof:placetype":"venue"
},
  "geometry": {"coordinates":[-123.136093,49.271488],"type":"Point"}
}