{
  "type": "Feature",
  "properties": {
    "addr:full":"810 45th Ave W Vancouver BC V5Z 2P9",
    "addr:housenumber":"810",
    "addr:postcode":"v5z 2p9",
    "addr:street":"45Th Ave W",
    "iso:country":"CA",
    "sg:address":"810 45th Ave W",
    "sg:city":"Vancouver",
    "sg:classifiers":[
        {
            "category":"Freight",
            "type":"Transportation"
        }
    ],
    "sg:phone":"+1 604 263 2366",
    "sg:postcode":"V5Z 2P9",
    "sg:province":"BC",
    "sg:tags":[
        "broker",
        "customs"
    ],
    "wof:name":"Meir Cohen Customs Brokers Ltd",
    "wof:placetype":"venue"
},
  "geometry": {"coordinates":[-123.12507600000001,49.230019],"type":"Point"}
}