{
  "type": "Feature",
  "properties": {
    "addr:full":"Regina SK S4R 1C9",
    "addr:postcode":"s4r 1c9",
    "iso:country":"CA",
    "sg:city":"Regina",
    "sg:classifiers":[
        {
            "category":"Professional",
            "subcategory":"Accounting & Tax Preparation",
            "type":"Services"
        }
    ],
    "sg:phone":"+1 306 761 1332",
    "sg:postcode":"S4R 1C9",
    "sg:province":"SK",
    "sg:tags":[
        "accountant"
    ],
    "wof:name":"Pippin, Shelly CA",
    "wof:placetype":"venue"
},
  "geometry": {"coordinates":[-104.59668000000001,50.456867],"type":"Point"}
}