{
  "type": "Feature",
  "properties": {
    "addr:full":"879 Bloor St W Toronto ON M6G 1M4",
    "addr:housenumber":"879",
    "addr:postcode":"m6g 1m4",
    "addr:street":"Bloor St W",
    "iso:country":"CA",
    "sg:address":"879 Bloor St W",
    "sg:city":"Toronto",
    "sg:classifiers":[
        {
            "category":"Food & Beverages",
            "subcategory":"Liquor & Beverages",
            "type":"Retail Goods"
        }
    ],
    "sg:phone":"+1 416 536 4340",
    "sg:postcode":"M6G 1M4",
    "sg:province":"ON",
    "sg:tags":[
        "store"
    ],
    "wof:name":"Ontario Liquor Store",
    "wof:placetype":"venue"
},
  "geometry": {"coordinates":[-79.424927,43.661983],"type":"Point"}
}