{
  "type": "Feature",
  "properties": {
    "iso:country":"CA",
    "sg:address":"299 3E Av",
    "sg:city":"Quebec",
    "sg:classifiers":[
        {
            "category":"Education",
            "subcategory":"Special Training",
            "type":"Public Place"
        }
    ],
    "sg:phone":"+1 418 647 4127",
    "sg:postcode":"G1L 2V7",
    "sg:province":"QC",
    "sg:tags":[
        "instruction",
        "music"
    ],
    "wof:name":"Premier Mouvement",
    "wof:placetype":"venue"
},
  "geometry": {"coordinates":[-71.225730896,46.8218955994],"type":"Point"}
}