{
  "type": "Feature",
  "properties": {
    "addr:full":"304 8th Ave E Meadow Lake SK S9X 1G9",
    "addr:housenumber":"304",
    "addr:postcode":"s9x 1g9",
    "addr:street":"8Th Ave E;Lake",
    "iso:country":"CA",
    "sg:address":"304 8th Ave E",
    "sg:city":"Meadow Lake",
    "sg:classifiers":[
        {
            "category":"Education",
            "subcategory":"School",
            "type":"Public Place"
        }
    ],
    "sg:phone":"+1 306 236 5810",
    "sg:postcode":"S9X 1G9",
    "sg:province":"SK",
    "wof:name":"Lakeview School",
    "wof:placetype":"venue"
},
  "geometry": {"coordinates":[-108.432411,54.12294],"type":"Point"}
}