{
  "type": "Feature",
  "properties": {
    "addr:full":"Bridge Lake BC V0K 1E0",
    "addr:postcode":"v0k 1e0",
    "iso:country":"CA",
    "sg:city":"Bridge Lake",
    "sg:classifiers":[
        {
            "category":"Government",
            "subcategory":"Office",
            "type":"Public Place"
        }
    ],
    "sg:phone":"+1 250 593 4296",
    "sg:postcode":"V0K 1E0",
    "sg:province":"BC",
    "sg:tags":[
        "general",
        "contractor"
    ],
    "wof:name":"Interior Roads Ltd",
    "wof:placetype":"venue"
},
  "geometry": {"coordinates":[-120.725845337,51.4768447876],"type":"Point"}
}