{
  "type": "Feature",
  "properties": {
    "addr:full":"2142 Blue Ridge Cres Pickering ON L1X 2M7",
    "addr:housenumber":"2142",
    "addr:postcode":"l1x 2m7",
    "addr:street":"Blue Ridge Cres",
    "iso:country":"CA",
    "sg:address":"2142 Blue Ridge Cres",
    "sg:city":"Pickering",
    "sg:classifiers":[
        {
            "category":"Taxi",
            "type":"Transportation"
        }
    ],
    "sg:phone":"+1 905 426 7800",
    "sg:postcode":"L1X 2M7",
    "sg:province":"ON",
    "sg:tags":[
        "taxicab"
    ],
    "wof:name":"Allied Taxi",
    "wof:placetype":"venue"
},
  "geometry": {"coordinates":[-79.08633399999999,43.861897],"type":"Point"}
}