{
  "type": "Feature",
  "properties": {
    "addr:full":"13016 N Victoria Rd Summerland BC V0H 1Z0",
    "addr:housenumber":"13016",
    "addr:postcode":"v0h 1z0",
    "addr:street":"N Victoria Rd",
    "iso:country":"CA",
    "sg:address":"13016 N Victoria Rd",
    "sg:city":"Summerland",
    "sg:classifiers":[
        {
            "category":"Restaurant",
            "type":"Food & Drink"
        }
    ],
    "sg:phone":"+1 250 494 1884",
    "sg:postcode":"V0H 1Z0",
    "sg:province":"BC",
    "sg:tags":[
        "shop",
        "coffee"
    ],
    "wof:name":"Beanery Coffee CO",
    "wof:placetype":"venue"
},
  "geometry": {"coordinates":[-119.683586121,49.601348877],"type":"Point"}
}