{
  "type": "Feature",
  "properties": {
    "iso:country":"CA",
    "sg:address":"914 Rue Laurier",
    "sg:city":"Beloeil",
    "sg:classifiers":[
        {
            "category":"Restaurant",
            "type":"Food & Drink"
        }
    ],
    "sg:phone":"+1 450 464 7491",
    "sg:postcode":"J3G 4K9",
    "sg:province":"QC",
    "wof:name":"Restaurant Osteria Du Vieux",
    "wof:placetype":"venue"
},
  "geometry": {"coordinates":[-73.200478,45.569866],"type":"Point"}
}