{
  "type": "Feature",
  "properties": {
    "addr:full":"2582 Wallace Cres Vancouver BC V6R 3V4",
    "addr:housenumber":"2582",
    "addr:postcode":"v6r 3v4",
    "addr:street":"Wallace Cres",
    "iso:country":"CA",
    "sg:address":"2582 Wallace Cres",
    "sg:city":"Vancouver",
    "sg:classifiers":[
        {
            "category":"Professional",
            "subcategory":"Art Services",
            "type":"Services"
        }
    ],
    "sg:phone":"+1 604 877 1550",
    "sg:postcode":"V6R 3V4",
    "sg:province":"BC",
    "sg:tags":[
        "photographer"
    ],
    "wof:name":"David Gray Photography",
    "wof:placetype":"venue"
},
  "geometry": {"coordinates":[-123.19107099999999,49.264107],"type":"Point"}
}