{
  "type": "Feature",
  "properties": {
    "addr:full":"1187 Princess St Kingston ON K7M 3E1",
    "addr:housenumber":"1187",
    "addr:postcode":"k7m 3e1",
    "addr:street":"Princess St",
    "iso:country":"CA",
    "sg:address":"1187 Princess St",
    "sg:city":"Kingston",
    "sg:classifiers":[
        {
            "category":"Travel",
            "subcategory":"Hotels & Motels",
            "type":"Entertainment"
        }
    ],
    "sg:phone":"+1 613 546 4411",
    "sg:postcode":"K7M 3E1",
    "sg:province":"ON",
    "wof:name":"Peachtree Inn",
    "wof:placetype":"venue"
},
  "geometry": {"coordinates":[-76.521889,44.246166],"type":"Point"}
}