{
  "type": "Feature",
  "properties": {
    "addr:full":"434 Av Lariviere Rouyn-Noranda QC J9X 4J1",
    "addr:postcode":"j9x 4j1",
    "addr:street":"434 Av Lariviere",
    "iso:country":"CA",
    "sg:address":"434 Av Lariviere",
    "sg:city":"Rouyn-Noranda",
    "sg:classifiers":[
        {
            "category":"Restaurant",
            "type":"Food & Drink"
        }
    ],
    "sg:phone":"+1 819 764 4142",
    "sg:postcode":"J9X 4J1",
    "sg:province":"QC",
    "wof:name":"Aliments Pg Inc",
    "wof:placetype":"venue"
},
  "geometry": {"coordinates":[-79.014755249,48.2309341431],"type":"Point"}
}