{
  "type": "Feature",
  "properties": {
    "addr:full":"125 Lancing Dr Hamilton ON L8W 2Z9",
    "addr:housenumber":"125",
    "addr:postcode":"l8w 2z9",
    "addr:street":"Lancing Dr",
    "iso:country":"CA",
    "sg:address":"125 Lancing Dr",
    "sg:city":"Hamilton",
    "sg:classifiers":[
        {
            "category":"Restaurant",
            "type":"Food & Drink"
        }
    ],
    "sg:phone":"+1 905 318 1913",
    "sg:postcode":"L8W 2Z9",
    "sg:province":"ON",
    "sg:tags":[
        "caterer"
    ],
    "wof:name":"Catering By Luigi",
    "wof:placetype":"venue"
},
  "geometry": {"coordinates":[-79.8405838013,43.1917190552],"type":"Point"}
}