{
  "type": "Feature",
  "properties": {
    "addr:full":"309 Kernstead Rd Winnipeg Beach MB R0C 3G0",
    "addr:housenumber":"309",
    "addr:postcode":"r0c 3g0",
    "addr:street":"Kernstead Rd",
    "iso:country":"CA",
    "sg:address":"309 Kernstead Rd",
    "sg:city":"Winnipeg Beach",
    "sg:classifiers":[
        {
            "category":"Restaurant",
            "type":"Food & Drink"
        }
    ],
    "sg:phone":"+1 204 389 2299",
    "sg:postcode":"R0C 3G0",
    "sg:province":"MB",
    "wof:name":"Niakwa Family Restaurant",
    "wof:placetype":"venue"
},
  "geometry": {"coordinates":[-96.9756393433,50.4919319153],"type":"Point"}
}