{
  "type": "Feature",
  "properties": {
    "addr:full":"8321 Oak St Vancouver BC V6P 4A9",
    "addr:housenumber":"8321",
    "addr:postcode":"v6p 4a9",
    "addr:street":"Oak St",
    "iso:country":"CA",
    "sg:address":"8321 Oak St",
    "sg:city":"Vancouver",
    "sg:classifiers":[
        {
            "category":"Personal",
            "subcategory":"Shoe Repair & Shine",
            "type":"Services"
        }
    ],
    "sg:phone":"+1 604 261 5141",
    "sg:postcode":"V6P 4A9",
    "sg:province":"BC",
    "sg:tags":[
        "repairing",
        "boot"
    ],
    "wof:name":"Boris Shoe Repair",
    "wof:placetype":"venue"
},
  "geometry": {"coordinates":[-123.130394,49.210419],"type":"Point"}
}