{
  "type": "Feature",
  "properties": {
    "addr:full":"Waseca SK S0M 3A0",
    "addr:postcode":"s0m 3a0",
    "iso:country":"CA",
    "sg:city":"Waseca",
    "sg:classifiers":[
        {
            "category":"Insurance",
            "subcategory":"Insurance Agent",
            "type":"Services"
        }
    ],
    "sg:phone":"+1 306 893 4554",
    "sg:postcode":"S0M 3A0",
    "sg:province":"SK",
    "wof:name":"Mc Fadyen & Sons Agencies Ltd",
    "wof:placetype":"venue"
},
  "geometry": {"coordinates":[-109.46711000000001,53.099735],"type":"Point"}
}