{
  "type": "Feature",
  "properties": {
    "addr:full":"1587 Rue Royale Trois-Rivieres QC G9A 4J9",
    "addr:housenumber":"1587",
    "addr:postcode":"g9a 4j9",
    "addr:street":"Rue Royale",
    "iso:country":"CA",
    "sg:address":"1587 Rue Royale",
    "sg:city":"Trois-Rivieres",
    "sg:classifiers":[
        {
            "category":"Recreation",
            "type":"Entertainment"
        }
    ],
    "sg:phone":"+1 819 691 5043",
    "sg:postcode":"G9A 4J9",
    "sg:province":"QC",
    "sg:tags":[
        "martial",
        "arts",
        "instruction"
    ],
    "wof:name":"Aaron Ouellet Arts Martiaux",
    "wof:placetype":"venue"
},
  "geometry": {"coordinates":[-72.544487,46.341522],"type":"Point"}
}