{
  "type": "Feature",
  "properties": {
    "addr:full":"Orillia ON L3V 3A8",
    "addr:postcode":"l3v 3a8",
    "iso:country":"CA",
    "sg:city":"Orillia",
    "sg:classifiers":[
        {
            "category":"Personal",
            "subcategory":"Beauty Salon",
            "type":"Services"
        }
    ],
    "sg:phone":"+1 705 329 1818",
    "sg:postcode":"L3V 3A8",
    "sg:province":"ON",
    "wof:name":"Classic Hairstylist",
    "wof:placetype":"venue"
},
  "geometry": {"coordinates":[-79.4216995239,44.6075668335],"type":"Point"}
}