{
  "type": "Feature",
  "properties": {
    "iso:country":"CA",
    "sg:address":"245 Mcdermot Ave # 200",
    "sg:city":"Winnipeg",
    "sg:classifiers":[
        {
            "category":"Professional",
            "subcategory":"Business Services",
            "type":"Services"
        }
    ],
    "sg:phone":"+1 204 942 2129",
    "sg:postcode":"R3B 0S6",
    "sg:province":"MB",
    "sg:tags":[
        "interior",
        "consultant",
        "design",
        "decorator"
    ],
    "wof:name":"Adi Designworks Ltd",
    "wof:placetype":"venue"
},
  "geometry": {"coordinates":[-97.1409454346,49.8973274231],"type":"Point"}
}