{
  "type": "Feature",
  "properties": {
    "addr:full":"1505 4th St N Cranbrook BC V1C 3L6",
    "addr:housenumber":"1505",
    "addr:postcode":"v1c 3l6",
    "addr:street":"4Th St N",
    "iso:country":"CA",
    "sg:address":"1505 4th St N",
    "sg:city":"Cranbrook",
    "sg:classifiers":[
        {
            "category":"Freight",
            "type":"Transportation"
        }
    ],
    "sg:phone":"+1 250 426 7271",
    "sg:postcode":"V1C 3L6",
    "sg:province":"BC",
    "sg:tags":[
        "trucking"
    ],
    "wof:name":"Byers Transportation Systems",
    "wof:placetype":"venue"
},
  "geometry": {"coordinates":[-115.760536194,49.5155601501],"type":"Point"}
}