{
  "type": "Feature",
  "properties": {
    "addr:full":"262 22nd St Battleford SK S0M 0E0",
    "addr:housenumber":"262",
    "addr:postcode":"s0m 0e0",
    "addr:street":"22Nd St",
    "iso:country":"CA",
    "sg:address":"262 22nd St",
    "sg:city":"Battleford",
    "sg:classifiers":[
        {
            "category":"Organizations",
            "subcategory":"Professional Association",
            "type":"Services"
        }
    ],
    "sg:phone":"+1 306 937 2161",
    "sg:postcode":"S0M 0E0",
    "sg:province":"SK",
    "sg:tags":[
        "club"
    ],
    "wof:name":"Royal Canadian Legion",
    "wof:placetype":"venue"
},
  "geometry": {"coordinates":[-108.313141,52.736237],"type":"Point"}
}