{
  "type": "Feature",
  "properties": {
    "addr:full":"Hwy 857 Willingdon AB T0B 4R0",
    "addr:postcode":"t0b 4r0",
    "addr:street":"Hwy 857 Willingdon",
    "iso:country":"CA",
    "sg:address":"Hwy 857",
    "sg:city":"Willingdon",
    "sg:classifiers":[
        {
            "category":"Professional",
            "subcategory":"Management & Consulting",
            "type":"Services"
        }
    ],
    "sg:phone":"+1 780 367 2355",
    "sg:postcode":"T0B 4R0",
    "sg:province":"AB",
    "sg:tags":[
        "agricultural",
        "consultant"
    ],
    "wof:name":"Marv Anderson & Assoc Ltd",
    "wof:placetype":"venue"
},
  "geometry": {"coordinates":[-112.12178,53.828556],"type":"Point"}
}