{
  "type": "Feature",
  "properties": {
    "addr:full":"495 Ball St Cobourg ON K9A 3J6",
    "addr:housenumber":"495",
    "addr:postcode":"k9a 3j6",
    "addr:street":"Ball St",
    "iso:country":"CA",
    "sg:address":"495 Ball St",
    "sg:city":"Cobourg",
    "sg:classifiers":[
        {
            "category":"Manufacturing",
            "subcategory":"Food",
            "type":"Manufacturing & Wholesale Goods"
        }
    ],
    "sg:phone":"+1 905 372 7373",
    "sg:postcode":"K9A 3J6",
    "sg:province":"ON",
    "sg:tags":[
        "baker",
        "supply"
    ],
    "wof:name":"Enjay Converters Ltd",
    "wof:placetype":"venue"
},
  "geometry": {"coordinates":[-78.1745681763,43.9642028809],"type":"Point"}
}