{
  "type": "Feature",
  "properties": {
    "addr:full":"933 Rue Saint-Vallier O Quebec QC G1N 1E9",
    "addr:housenumber":"933",
    "addr:postcode":"g1n 1e9",
    "addr:street":"Rue Saint-Vallier O",
    "iso:country":"CA",
    "sg:address":"933 Rue Saint-Vallier O",
    "sg:city":"Quebec",
    "sg:classifiers":[
        {
            "category":"Wholesale",
            "subcategory":"Hardware",
            "type":"Manufacturing & Wholesale Goods"
        }
    ],
    "sg:phone":"+1 418 681 0077",
    "sg:postcode":"G1N 1E9",
    "sg:province":"QC",
    "sg:tags":[
        "bearing"
    ],
    "wof:name":"Pieces DE Machinerie Delisle",
    "wof:placetype":"venue"
},
  "geometry": {"coordinates":[-71.215187,46.814793],"type":"Point"}
}