{
  "type": "Feature",
  "properties": {
    "addr:full":"Scarborough ON M1R 5G4",
    "addr:postcode":"m1r 5g4",
    "iso:country":"CA",
    "sg:city":"Scarborough",
    "sg:classifiers":[
        {
            "category":"Food & Beverages",
            "subcategory":"Bakery",
            "type":"Retail Goods"
        }
    ],
    "sg:phone":"+1 416 288 6068",
    "sg:postcode":"M1R 5G4",
    "sg:province":"ON",
    "sg:tags":[
        "doughnut"
    ],
    "wof:name":"Coffee Time Donuts",
    "wof:placetype":"venue"
},
  "geometry": {"coordinates":[-79.288521,43.746544],"type":"Point"}
}