{
  "type": "Feature",
  "properties": {
    "addr:full":"9475 Rue Jean-Pratt Montreal QC H4N 2W7",
    "addr:housenumber":"9475",
    "addr:postcode":"h4n 2w7",
    "addr:street":"Rue Jean-Pratt",
    "iso:country":"CA",
    "sg:address":"9475 Rue Jean-Pratt",
    "sg:city":"Montreal",
    "sg:classifiers":[
        {
            "category":"Manufacturing",
            "subcategory":"Printing",
            "type":"Manufacturing & Wholesale Goods"
        }
    ],
    "sg:phone":"+1 514 382 0351",
    "sg:postcode":"H4N 2W7",
    "sg:province":"QC",
    "sg:tags":[
        "screen"
    ],
    "wof:name":"Decalcomanie Artistic Ltd",
    "wof:placetype":"venue"
},
  "geometry": {"coordinates":[-73.6618804932,45.5304145813],"type":"Point"}
}