{
  "type": "Feature",
  "properties": {
    "iso:country":"CA",
    "sg:address":"250 Du Moulin Mtee",
    "sg:city":"Vercheres",
    "sg:classifiers":[
        {
            "category":"Sports & Exercise",
            "subcategory":"Golf",
            "type":"Entertainment"
        }
    ],
    "sg:phone":"+1 450 583 3319",
    "sg:postcode":"J0L 2R0",
    "sg:province":"QC",
    "sg:tags":[
        "course"
    ],
    "wof:name":"Club DE Golf Vercheres Inc",
    "wof:placetype":"venue"
},
  "geometry": {"coordinates":[-73.357552,45.775921],"type":"Point"}
}