{
  "type": "Feature",
  "properties": {
    "addr:full":"Edmonton AB T6L 3K8",
    "addr:postcode":"t6l 3k8",
    "iso:country":"CA",
    "sg:city":"Edmonton",
    "sg:classifiers":[
        {
            "category":"Real Estate",
            "subcategory":"Real Estate Operator",
            "type":"Services"
        }
    ],
    "sg:phone":"+1 780 414 6711",
    "sg:postcode":"T6L 3K8",
    "sg:province":"AB",
    "sg:tags":[
        "apartment"
    ],
    "wof:name":"Tamarack East & West",
    "wof:placetype":"venue"
},
  "geometry": {"coordinates":[-113.45127100000001,53.446339],"type":"Point"}
}