{
  "type": "Feature",
  "properties": {
    "addr:full":"Montreal QC H3A 1K2",
    "addr:postcode":"h3a 1k2",
    "iso:country":"CA",
    "sg:city":"Montreal",
    "sg:classifiers":[
        {
            "category":"Banks & Credit Unions",
            "subcategory":"Investment Brokerage",
            "type":"Services"
        }
    ],
    "sg:phone":"+1 514 856 6845",
    "sg:postcode":"H3A 1K2",
    "sg:province":"QC",
    "sg:tags":[
        "funds",
        "mutual"
    ],
    "wof:name":"Fonds Clarington",
    "wof:placetype":"venue"
},
  "geometry": {"coordinates":[-73.572281,45.504887],"type":"Point"}
}