{
  "type": "Feature",
  "properties": {
    "iso:country":"CA",
    "sg:address":"1857 Centre Ave SE",
    "sg:city":"Calgary",
    "sg:classifiers":[
        {
            "category":"Freight",
            "type":"Transportation"
        }
    ],
    "sg:phone":"+1 403 248 1866",
    "sg:postcode":"T2E 6L3",
    "sg:province":"AB",
    "sg:tags":[
        "courier"
    ],
    "wof:name":"Red Arrow Express Freight",
    "wof:placetype":"venue"
},
  "geometry": {"coordinates":[-114.01222229,51.0521774292],"type":"Point"}
}