{
  "type": "Feature",
  "properties": {
    "addr:full":"625 1st Ave N Saskatoon SK S7K 1X7",
    "addr:housenumber":"625",
    "addr:postcode":"s7k 1x7",
    "addr:street":"1St Ave N",
    "iso:country":"CA",
    "sg:address":"625 1st Ave N",
    "sg:city":"Saskatoon",
    "sg:classifiers":[
        {
            "category":"Professional",
            "subcategory":"Business Services",
            "type":"Services"
        }
    ],
    "sg:phone":"+1 306 664 4094",
    "sg:postcode":"S7K 1X7",
    "sg:province":"SK",
    "sg:tags":[
        "interior",
        "consultant",
        "design",
        "decorator"
    ],
    "wof:name":"Collector's Choice Contract",
    "wof:placetype":"venue"
},
  "geometry": {"coordinates":[-106.661812,52.137203],"type":"Point"}
}