{
  "type": "Feature",
  "properties": {
    "addr:full":"210 Pacific Ave Winnipeg MB R3B 0M4",
    "addr:housenumber":"210",
    "addr:postcode":"r3b 0m4",
    "addr:street":"Pacific Ave",
    "iso:country":"CA",
    "sg:address":"210 Pacific Ave",
    "sg:city":"Winnipeg",
    "sg:classifiers":[
        {
            "category":"Food & Beverages",
            "subcategory":"Groceries & Convenience Stores",
            "type":"Retail Goods"
        }
    ],
    "sg:phone":"+1 204 956 7948",
    "sg:postcode":"R3B 0M4",
    "sg:province":"MB",
    "sg:tags":[
        "grocer"
    ],
    "wof:name":"Ming's International Trading",
    "wof:placetype":"venue"
},
  "geometry": {"coordinates":[-97.13748931879999,49.9011611938],"type":"Point"}
}