{
  "type": "Feature",
  "properties": {
    "addr:full":"152 3rd Ave W Melville SK S0A 2P0",
    "addr:housenumber":"152",
    "addr:postcode":"s0a 2p0",
    "addr:street":"3Rd Ave W",
    "iso:country":"CA",
    "sg:address":"152 3rd Ave W",
    "sg:city":"Melville",
    "sg:classifiers":[
        {
            "category":"Shopping",
            "subcategory":"Florist",
            "type":"Retail Goods"
        }
    ],
    "sg:phone":"+1 306 728 2000",
    "sg:postcode":"S0A 2P0",
    "sg:province":"SK",
    "wof:name":"Bo-Kay Florists",
    "wof:placetype":"venue"
},
  "geometry": {"coordinates":[-102.816093,50.931126],"type":"Point"}
}