{
  "type": "Feature",
  "properties": {
    "addr:full":"81 Rte Ditton N LA Patrie QC J0B 1Y0",
    "addr:housenumber":"81",
    "addr:postcode":"j0b 1y0",
    "addr:street":"Rte Ditton N La Patrie",
    "iso:country":"CA",
    "sg:address":"81 Rte Ditton N",
    "sg:city":"LA Patrie",
    "sg:classifiers":[
        {
            "category":"Freight",
            "type":"Transportation"
        }
    ],
    "sg:phone":"+1 819 888 2296",
    "sg:postcode":"J0B 1Y0",
    "sg:province":"QC",
    "sg:tags":[
        "trucking"
    ],
    "wof:name":"Transport Robert Verret",
    "wof:placetype":"venue"
},
  "geometry": {"coordinates":[-71.250427,45.401814],"type":"Point"}
}