{
  "type": "Feature",
  "properties": {
    "addr:full":"1338 Boul Saint-Germain Rimouski QC G5L 8Y9",
    "addr:housenumber":"1338",
    "addr:postcode":"g5l 8y9",
    "addr:street":"Boul Saint-Germain",
    "iso:country":"CA",
    "sg:address":"1338 Boul Saint-Germain",
    "sg:city":"Rimouski",
    "sg:classifiers":[
        {
            "category":"Building & Trades",
            "subcategory":"Construction",
            "type":"Services"
        }
    ],
    "sg:phone":"+1 418 722 8030",
    "sg:postcode":"G5L 8Y9",
    "sg:province":"QC",
    "sg:tags":[
        "contractor"
    ],
    "wof:name":"Construction Sylvain Pigeon",
    "wof:placetype":"venue"
},
  "geometry": {"coordinates":[-68.6089935303,48.42029953],"type":"Point"}
}