{
  "type": "Feature",
  "properties": {
    "addr:full":"2571 Rue Jean-Talon E Montreal QC H2A 1T8",
    "addr:housenumber":"2571",
    "addr:postcode":"h2a 1t8",
    "addr:street":"Rue Jean-Talon E",
    "iso:country":"CA",
    "sg:address":"2571 Rue Jean-Talon E",
    "sg:city":"Montreal",
    "sg:classifiers":[
        {
            "category":"Health Services",
            "subcategory":"Doctor",
            "type":"Services"
        }
    ],
    "sg:phone":"+1 514 374 2932",
    "sg:postcode":"H2A 1T8",
    "sg:province":"QC",
    "sg:tags":[
        "clinic"
    ],
    "wof:name":"Clinique Medicale St Mathieu",
    "wof:placetype":"venue"
},
  "geometry": {"coordinates":[-73.6020278931,45.5536308289],"type":"Point"}
}