{
  "type": "Feature",
  "properties": {
    "iso:country":"CA",
    "sg:address":"449 Sanatorium Rd",
    "sg:city":"Hamilton",
    "sg:classifiers":[
        {
            "category":"Health Services",
            "subcategory":"Nursing And Care Facility",
            "type":"Services"
        }
    ],
    "sg:phone":"+1 905 574 2000",
    "sg:postcode":"L9C 2A7",
    "sg:province":"ON",
    "sg:tags":[
        "home",
        "convalescent"
    ],
    "wof:name":"Idlewyld Manor",
    "wof:placetype":"venue"
},
  "geometry": {"coordinates":[-79.91408538819999,43.2366485596],"type":"Point"}
}