{
  "type": "Feature",
  "properties": {
    "addr:full":"2444 Bloor St W York ON M6S 1R2",
    "addr:housenumber":"2444",
    "addr:postcode":"m6s 1r2",
    "addr:street":"Bloor St W",
    "iso:country":"CA",
    "sg:address":"2444 Bloor St W",
    "sg:city":"York",
    "sg:classifiers":[
        {
            "category":"Cinema",
            "subcategory":"Movie Rental",
            "type":"Entertainment"
        }
    ],
    "sg:phone":"+1 416 767 0110",
    "sg:postcode":"M6S 1R2",
    "sg:province":"ON",
    "sg:tags":[
        "leasing",
        "video",
        "disc",
        "tape"
    ],
    "wof:name":"2 For 1 Movies",
    "wof:placetype":"venue"
},
  "geometry": {"coordinates":[-79.490562439,43.6479911804],"type":"Point"}
}