{
  "type": "Feature",
  "properties": {
    "addr:full":"60 Moore St # A Carleton Place ON K7C 2R2",
    "addr:housenumber":"60",
    "addr:postcode":"k7c 2r2",
    "addr:street":"Moore St # A",
    "iso:country":"CA",
    "sg:address":"60 Moore St # A",
    "sg:city":"Carleton Place",
    "sg:classifiers":[
        {
            "category":"Wholesale",
            "subcategory":"Auto Parts",
            "type":"Manufacturing & Wholesale Goods"
        }
    ],
    "sg:phone":"+1 613 257 2599",
    "sg:postcode":"K7C 2R2",
    "sg:province":"ON",
    "sg:tags":[
        "equipment",
        "truck"
    ],
    "wof:name":"Carleton Auto Parts Ltd",
    "wof:placetype":"venue"
},
  "geometry": {"coordinates":[-76.13954200000001,45.136375],"type":"Point"}
}