{
  "type": "Feature",
  "properties": {
    "addr:full":"5010 Victoria Ave Coronation AB T0C 1C0",
    "addr:housenumber":"5010",
    "addr:postcode":"t0c 1c0",
    "addr:street":"Victoria Ave",
    "iso:country":"CA",
    "sg:address":"5010 Victoria Ave",
    "sg:city":"Coronation",
    "sg:classifiers":[
        {
            "category":"Home & Garden",
            "subcategory":"Household Appliances",
            "type":"Retail Goods"
        }
    ],
    "sg:phone":"+1 403 578 4220",
    "sg:postcode":"T0C 1C0",
    "sg:province":"AB",
    "sg:tags":[
        "machine",
        "sewing"
    ],
    "wof:name":"Sew & Save",
    "wof:placetype":"venue"
},
  "geometry": {"coordinates":[-111.449738,52.092518],"type":"Point"}
}