{
  "type": "Feature",
  "properties": {
    "addr:full":"5724 Av Deom Montreal QC H3S 2N4",
    "addr:housenumber":"5724",
    "addr:postcode":"h3s 2n4",
    "addr:street":"Av Deom",
    "iso:country":"CA",
    "sg:address":"5724 Av Deom",
    "sg:city":"Montreal",
    "sg:classifiers":[
        {
            "category":"Professional",
            "subcategory":"Management & Consulting",
            "type":"Services"
        }
    ],
    "sg:phone":"+1 514 735 3679",
    "sg:postcode":"H3S 2N4",
    "sg:province":"QC",
    "sg:tags":[
        "communications",
        "consultant"
    ],
    "wof:name":"Communimage",
    "wof:placetype":"venue"
},
  "geometry": {"coordinates":[-73.61800384519999,45.5099754333],"type":"Point"}
}