{
  "type": "Feature",
  "properties": {
    "addr:full":"Kitchener ON N2G 4W1",
    "addr:postcode":"n2g 4w1",
    "iso:country":"CA",
    "sg:city":"Kitchener",
    "sg:classifiers":[
        {
            "category":"Insurance",
            "subcategory":"Hazard Insurance",
            "type":"Services"
        }
    ],
    "sg:phone":"+1 519 743 9000",
    "sg:postcode":"N2G 4W1",
    "sg:province":"ON",
    "sg:tags":[
        "profit",
        "sharing",
        "pension",
        "plan"
    ],
    "wof:name":"Penad Pension Svc Ltd",
    "wof:placetype":"venue"
},
  "geometry": {"coordinates":[-80.490227,43.450035],"type":"Point"}
}