{
  "type": "Feature",
  "properties": {
    "addr:full":"607 South Dr Summerside PE C1N 3Z6",
    "addr:housenumber":"607",
    "addr:postcode":"c1n 3z6",
    "addr:street":"South Dr",
    "iso:country":"CA",
    "sg:address":"607 South Dr",
    "sg:city":"Summerside",
    "sg:classifiers":[
        {
            "category":"Autos & Motor Vehicles",
            "subcategory":"Fuel & Gas Station",
            "type":"Retail Goods"
        }
    ],
    "sg:phone":"+1 902 888 2252",
    "sg:postcode":"C1N 3Z6",
    "sg:province":"PE",
    "sg:tags":[
        "grocer",
        "oil"
    ],
    "wof:name":"Ramsays Ultramar & Convenience",
    "wof:placetype":"venue"
},
  "geometry": {"coordinates":[-63.8097076416,46.4012947083],"type":"Point"}
}