{
  "type": "Feature",
  "properties": {
    "addr:full":"North York ON M3J 1Y8",
    "addr:postcode":"m3j 1y8",
    "iso:country":"CA",
    "sg:city":"North York",
    "sg:classifiers":[
        {
            "category":"Building & Trades",
            "subcategory":"Construction",
            "type":"Services"
        }
    ],
    "sg:phone":"+1 416 633 2311",
    "sg:postcode":"M3J 1Y8",
    "sg:province":"ON",
    "sg:tags":[
        "concrete",
        "cutting",
        "breaking",
        "sawing"
    ],
    "wof:name":"Metro Concrete Cutting Inc",
    "wof:placetype":"venue"
},
  "geometry": {"coordinates":[-79.48374176030001,43.7547340393],"type":"Point"}
}