{
  "type": "Feature",
  "properties": {
    "addr:full":"Oshawa ON L1J 2K5",
    "addr:postcode":"l1j 2k5",
    "iso:country":"CA",
    "sg:city":"Oshawa",
    "sg:classifiers":[
        {
            "category":"Banks & Credit Unions",
            "subcategory":"Investment Brokerage",
            "type":"Services"
        }
    ],
    "sg:phone":"+1 905 404 8088",
    "sg:postcode":"L1J 2K5",
    "sg:province":"ON",
    "sg:tags":[
        "stock",
        "broker",
        "bond"
    ],
    "wof:name":"Bmo Nesbitt Burns",
    "wof:placetype":"venue"
},
  "geometry": {"coordinates":[-78.880028,43.893684],"type":"Point"}
}