{
  "type": "Feature",
  "properties": {
    "addr:full":"201 Rue Parc E Beresford NB E8K 1V9",
    "addr:housenumber":"201",
    "addr:postcode":"e8k 1v9",
    "addr:street":"Rue Parc E Beresford",
    "iso:country":"CA",
    "sg:address":"201 Rue Parc E",
    "sg:city":"Beresford",
    "sg:classifiers":[
        {
            "category":"Recreation",
            "type":"Entertainment"
        }
    ],
    "sg:phone":"+1 506 542 1500",
    "sg:postcode":"E8K 1V9",
    "sg:province":"NB",
    "sg:tags":[
        "club",
        "curling"
    ],
    "wof:name":"Club DE Curling DE Beresford",
    "wof:placetype":"venue"
},
  "geometry": {"coordinates":[-65.6999053955,47.7096672058],"type":"Point"}
}