{
  "type": "Feature",
  "properties": {
    "addr:full":"8601 Warden Ave Markham ON L3R 0B5",
    "addr:housenumber":"8601",
    "addr:postcode":"l3r 0b5",
    "addr:street":"Warden Ave",
    "iso:country":"CA",
    "sg:address":"8601 Warden Ave",
    "sg:city":"Markham",
    "sg:classifiers":[
        {
            "category":"Cinema",
            "subcategory":"Movie Rental",
            "type":"Entertainment"
        }
    ],
    "sg:phone":"+1 905 946 8292",
    "sg:postcode":"L3R 0B5",
    "sg:province":"ON",
    "sg:tags":[
        "leasing",
        "video",
        "disc",
        "tape"
    ],
    "wof:name":"Roger's Video",
    "wof:placetype":"venue"
},
  "geometry": {"coordinates":[-79.334351,43.85812],"type":"Point"}
}