{
  "type": "Feature",
  "properties": {
    "addr:full":"208 Av DE LA Cathedrale Rimouski QC G5L 5J2",
    "addr:postcode":"g5l 5j2",
    "addr:street":"208 Av De La Cathedrale",
    "iso:country":"CA",
    "sg:address":"208 Av DE LA Cathedrale",
    "sg:city":"Rimouski",
    "sg:classifiers":[
        {
            "category":"Health Services",
            "subcategory":"Doctor",
            "type":"Services"
        }
    ],
    "sg:phone":"+1 418 725 4211",
    "sg:postcode":"G5L 5J2",
    "sg:province":"QC",
    "sg:tags":[
        "physician",
        "surgeon"
    ],
    "wof:name":"Demalsy, Jean-Claude MD",
    "wof:placetype":"venue"
},
  "geometry": {"coordinates":[-68.52443700000001,48.449333],"type":"Point"}
}