{
  "type": "Feature",
  "properties": {
    "addr:full":"60 Dalton Ave Kingston ON K7K 6C3",
    "addr:housenumber":"60",
    "addr:postcode":"k7k 6c3",
    "addr:street":"Dalton Ave",
    "iso:country":"CA",
    "sg:address":"60 Dalton Ave",
    "sg:city":"Kingston",
    "sg:classifiers":[
        {
            "category":"Wholesale",
            "subcategory":"Hardware",
            "type":"Manufacturing & Wholesale Goods"
        }
    ],
    "sg:phone":"+1 613 549 3320",
    "sg:postcode":"K7K 6C3",
    "sg:province":"ON",
    "sg:tags":[
        "equipment",
        "heating",
        "system"
    ],
    "wof:name":"Tackaberry Heating & Refrig",
    "wof:placetype":"venue"
},
  "geometry": {"coordinates":[-76.5003890991,44.2656669617],"type":"Point"}
}