{
  "type": "Feature",
  "properties": {
    "addr:full":"3131 Boul DE LA Cote-Vertu Saint-Laurent QC H4R 1Y8",
    "addr:housenumber":"3131",
    "addr:postcode":"h4r 1y8",
    "addr:street":"Boul De La Cote-Vertu",
    "iso:country":"CA",
    "sg:address":"3131 Boul DE LA Cote-Vertu",
    "sg:city":"Saint-Laurent",
    "sg:classifiers":[
        {
            "category":"Shopping",
            "subcategory":"Clothing, Apparel, & Fashions",
            "type":"Retail Goods"
        }
    ],
    "sg:phone":"+1 514 856 2694",
    "sg:postcode":"H4R 1Y8",
    "sg:province":"QC",
    "wof:name":"Garage",
    "wof:placetype":"venue"
},
  "geometry": {"coordinates":[-73.70356,45.49799],"type":"Point"}
}