{
  "type": "Feature",
  "properties": {
    "addr:full":"3535 Av Papineau # 100 Montreal QC H2K 4J9",
    "addr:housenumber":"3535",
    "addr:postcode":"h2k 4j9",
    "addr:street":"Av Papineau # 100",
    "iso:country":"CA",
    "sg:address":"3535 Av Papineau # 100",
    "sg:city":"Montreal",
    "sg:classifiers":[
        {
            "category":"Real Estate",
            "subcategory":"Real Estate Operator",
            "type":"Services"
        }
    ],
    "sg:phone":"+1 514 524 7587",
    "sg:postcode":"H2K 4J9",
    "sg:province":"QC",
    "sg:tags":[
        "apartment"
    ],
    "wof:name":"Dauphins Sur Le Parc",
    "wof:placetype":"venue"
},
  "geometry": {"coordinates":[-73.5648117065,45.5285148621],"type":"Point"}
}