{
  "type": "Feature",
  "properties": {
    "iso:country":"CA",
    "sg:address":"2905 Boul Losch",
    "sg:city":"Saint-Hubert",
    "sg:classifiers":[
        {
            "category":"Building & Trades",
            "subcategory":"Construction",
            "type":"Services"
        }
    ],
    "sg:phone":"+1 450 443 4150",
    "sg:postcode":"J3Y 3V6",
    "sg:province":"QC",
    "sg:tags":[
        "roofing",
        "contractor"
    ],
    "wof:name":"Etancheite Trudeau",
    "wof:placetype":"venue"
},
  "geometry": {"coordinates":[-73.43817138670001,45.5056838989],"type":"Point"}
}