{
  "type": "Feature",
  "properties": {
    "addr:full":"2301 Carling Ave # 100 Ottawa ON K2B 7G3",
    "addr:housenumber":"2301",
    "addr:postcode":"k2b 7g3",
    "addr:street":"Carling Ave # 100",
    "iso:country":"CA",
    "sg:address":"2301 Carling Ave # 100",
    "sg:city":"Ottawa",
    "sg:classifiers":[
        {
            "category":"Professional",
            "subcategory":"Employment Agencies",
            "type":"Services"
        }
    ],
    "sg:phone":"+1 613 225 5417",
    "sg:postcode":"K2B 7G3",
    "sg:province":"ON",
    "sg:tags":[
        "opportunity"
    ],
    "wof:name":"Stevenson & White",
    "wof:placetype":"venue"
},
  "geometry": {"coordinates":[-75.77582550050001,45.3680877686],"type":"Point"}
}