{
  "type": "Feature",
  "properties": {
    "addr:full":"149 Macintosh St New Glasgow NS B2H 4R6",
    "addr:housenumber":"149",
    "addr:postcode":"b2h 4r6",
    "addr:street":"Macintosh St",
    "iso:country":"CA",
    "sg:address":"149 Macintosh St",
    "sg:city":"New Glasgow",
    "sg:classifiers":[
        {
            "category":"Wholesale",
            "subcategory":"Construction Materials",
            "type":"Manufacturing & Wholesale Goods"
        }
    ],
    "sg:phone":"+1 902 755 4033",
    "sg:postcode":"B2H 4R6",
    "sg:province":"NS",
    "sg:tags":[
        "fence"
    ],
    "wof:name":"Nova Fencing Ltd",
    "wof:placetype":"venue"
},
  "geometry": {"coordinates":[-62.645802,45.584869],"type":"Point"}
}