{
  "type": "Feature",
  "properties": {
    "addr:full":"3445 43 Ave Vernon BC V1T 8P5",
    "addr:housenumber":"3445",
    "addr:postcode":"v1t 8p5",
    "addr:street":"43 Ave",
    "iso:country":"CA",
    "sg:address":"3445 43 Ave",
    "sg:city":"Vernon",
    "sg:classifiers":[
        {
            "category":"Recreation",
            "type":"Entertainment"
        }
    ],
    "sg:phone":"+1 250 542 5623",
    "sg:postcode":"V1T 8P5",
    "sg:province":"BC",
    "sg:tags":[
        "center"
    ],
    "wof:name":"Vernon & District Multi-Use",
    "wof:placetype":"venue"
},
  "geometry": {"coordinates":[-119.27853399999999,50.274803],"type":"Point"}
}