{
  "type": "Feature",
  "properties": {
    "addr:full":"589 Steven Crt Newmarket ON L3Y 6Z3",
    "addr:housenumber":"589",
    "addr:postcode":"l3y 6z3",
    "addr:street":"Steven Crt",
    "iso:country":"CA",
    "sg:address":"589 Steven Crt",
    "sg:city":"Newmarket",
    "sg:classifiers":[
        {
            "category":"Manufacturing",
            "subcategory":"Printing",
            "type":"Manufacturing & Wholesale Goods"
        }
    ],
    "sg:phone":"+1 905 898 7212",
    "sg:postcode":"L3Y 6Z3",
    "sg:province":"ON",
    "sg:tags":[
        "screen"
    ],
    "wof:name":"Leader Laminators Ltd",
    "wof:placetype":"venue"
},
  "geometry": {"coordinates":[-79.45431518549999,44.0395927429],"type":"Point"}
}