{
  "type": "Feature",
  "properties": {
    "addr:full":"1266 16th St E Owen Sound ON N4K 1Z3",
    "addr:housenumber":"1266",
    "addr:postcode":"n4k 1z3",
    "addr:street":"16Th St E",
    "iso:country":"CA",
    "sg:address":"1266 16th St E",
    "sg:city":"Owen Sound",
    "sg:classifiers":[
        {
            "category":"Health Services",
            "subcategory":"Doctor",
            "type":"Services"
        }
    ],
    "sg:phone":"+1 519 371 6500",
    "sg:postcode":"N4K 1Z3",
    "sg:province":"ON",
    "sg:tags":[
        "physician",
        "surgeon"
    ],
    "wof:name":"Kumar, Ganraj MD",
    "wof:placetype":"venue"
},
  "geometry": {"coordinates":[-80.9222869873,44.5742301941],"type":"Point"}
}