{
  "type": "Feature",
  "properties": {
    "iso:country":"CA",
    "sg:address":"Hwy 71",
    "sg:city":"Sioux Narrows",
    "sg:classifiers":[
        {
            "category":"Shopping",
            "subcategory":"Discount & Variety Stores",
            "type":"Retail Goods"
        }
    ],
    "sg:phone":"+1 807 226 5252",
    "sg:postcode":"P0X 1N0",
    "sg:province":"ON",
    "sg:tags":[
        "merchandise",
        "general"
    ],
    "wof:name":"Trading Post",
    "wof:placetype":"venue"
},
  "geometry": {"coordinates":[-94.01765441889999,49.3930091858],"type":"Point"}
}