{
  "type": "Feature",
  "properties": {
    "addr:full":"543 Fisgard St Victoria BC V8W 1R3",
    "addr:housenumber":"543",
    "addr:postcode":"v8w 1r3",
    "addr:street":"Fisgard St",
    "iso:country":"CA",
    "sg:address":"543 Fisgard St",
    "sg:city":"Victoria",
    "sg:classifiers":[
        {
            "category":"Restaurant",
            "type":"Food & Drink"
        }
    ],
    "sg:phone":"+1 250 383 5251",
    "sg:postcode":"V8W 1R3",
    "sg:province":"BC",
    "wof:name":"Kimbo Restaurant",
    "wof:placetype":"venue"
},
  "geometry": {"coordinates":[-123.368156433,48.4292106628],"type":"Point"}
}