{
  "type": "Feature",
  "properties": {
    "addr:full":"726 Queen St Kincardine ON N2Z 1Z8",
    "addr:housenumber":"726",
    "addr:postcode":"n2z 1z8",
    "addr:street":"Queen St",
    "iso:country":"CA",
    "sg:address":"726 Queen St",
    "sg:city":"Kincardine",
    "sg:classifiers":[
        {
            "category":"Shopping",
            "subcategory":"Shoes",
            "type":"Retail Goods"
        }
    ],
    "sg:phone":"+1 519 396 8633",
    "sg:postcode":"N2Z 1Z8",
    "sg:province":"ON",
    "wof:name":"Sandy's Sportswear",
    "wof:placetype":"venue"
},
  "geometry": {"coordinates":[-81.636398,44.175789],"type":"Point"}
}