{
  "type": "Feature",
  "properties": {
    "addr:full":"263 Speers Rd Oakville ON L6K 2E8",
    "addr:housenumber":"263",
    "addr:postcode":"l6k 2e8",
    "addr:street":"Speers Rd",
    "iso:country":"CA",
    "sg:address":"263 Speers Rd",
    "sg:city":"Oakville",
    "sg:classifiers":[
        {
            "category":"Retail",
            "subcategory":"Auto Rental",
            "type":"Services"
        }
    ],
    "sg:phone":"+1 905 842 3180",
    "sg:postcode":"L6K 2E8",
    "sg:province":"ON",
    "sg:tags":[
        "renting",
        "automobile"
    ],
    "wof:name":"Hertz Rent A Car",
    "wof:placetype":"venue"
},
  "geometry": {"coordinates":[-79.6908950806,43.443145752],"type":"Point"}
}