{
  "type": "Feature",
  "properties": {
    "iso:country":"CA",
    "sg:address":"2998 Ch Royal # A",
    "sg:city":"Beauport",
    "sg:classifiers":[
        {
            "category":"Retail",
            "subcategory":"Auto Repair",
            "type":"Services"
        }
    ],
    "sg:phone":"+1 418 666 1616",
    "sg:postcode":"G1E 1T3",
    "sg:province":"QC",
    "sg:tags":[
        "repairing",
        "automobile"
    ],
    "wof:name":"Garage Luc Auto Inc",
    "wof:placetype":"venue"
},
  "geometry": {"coordinates":[-71.212875,46.848412],"type":"Point"}
}