{
  "type": "Feature",
  "properties": {
    "iso:country":"CA",
    "sg:address":"32 Hodder Dr",
    "sg:city":"Pasadena",
    "sg:classifiers":[
        {
            "category":"Shopping",
            "type":"Retail Goods"
        }
    ],
    "sg:phone":"+1 709 686 2102",
    "sg:postcode":"A0L 1K0",
    "sg:province":"NL",
    "sg:tags":[
        "cosmetic",
        "perfume"
    ],
    "wof:name":"Mary Kay Cosmetics",
    "wof:placetype":"venue"
},
  "geometry": {"coordinates":[-57.5980377197,49.0142478943],"type":"Point"}
}