{
  "type": "Feature",
  "properties": {
    "addr:full":"12065 Rue DE Montigny Montreal QC H1B 1P4",
    "addr:housenumber":"12065",
    "addr:postcode":"h1b 1p4",
    "addr:street":"Rue De Montigny",
    "iso:country":"CA",
    "sg:address":"12065 Rue DE Montigny",
    "sg:city":"Montreal",
    "sg:classifiers":[
        {
            "category":"Building & Trades",
            "subcategory":"Construction",
            "type":"Services"
        }
    ],
    "sg:phone":"+1 514 498 2067",
    "sg:postcode":"H1B 1P4",
    "sg:province":"QC",
    "sg:tags":[
        "contractor"
    ],
    "wof:name":"Constructions Venne & Fils Lte",
    "wof:placetype":"venue"
},
  "geometry": {"coordinates":[-73.50648498539999,45.6430702209],"type":"Point"}
}