{
  "type": "Feature",
  "properties": {
    "addr:full":"243211 Paradise Rd Calgary AB T2M 4L5",
    "addr:housenumber":"243211",
    "addr:postcode":"t2m 4l5",
    "addr:street":"Paradise Rd",
    "iso:country":"CA",
    "sg:address":"243211 Paradise Rd",
    "sg:city":"Calgary",
    "sg:classifiers":[
        {
            "category":"Wholesale",
            "subcategory":"Meat",
            "type":"Manufacturing & Wholesale Goods"
        }
    ],
    "sg:phone":"+1 403 272 3033",
    "sg:postcode":"T2M 4L5",
    "sg:province":"AB",
    "sg:tags":[
        "sausage",
        "maker"
    ],
    "wof:name":"Dominion Meat Market",
    "wof:placetype":"venue"
},
  "geometry": {"coordinates":[-114.063194275,51.0450744629],"type":"Point"}
}