{
  "type": "Feature",
  "properties": {
    "addr:full":"Toronto ON M5H 3W1",
    "addr:postcode":"m5h 3w1",
    "iso:country":"CA",
    "sg:city":"Toronto",
    "sg:classifiers":[
        {
            "category":"Professional",
            "subcategory":"Lawyer & Legal Services",
            "type":"Services"
        }
    ],
    "sg:phone":"+1 416 365 7756",
    "sg:postcode":"M5H 3W1",
    "sg:province":"ON",
    "sg:tags":[
        "attorney"
    ],
    "wof:name":"Williams & Price",
    "wof:placetype":"venue"
},
  "geometry": {"coordinates":[-79.3814163208,43.650932312],"type":"Point"}
}