{
  "type": "Feature",
  "properties": {
    "iso:country":"CA",
    "sg:address":"1470 Rue Boissonneault",
    "sg:city":"Mascouche",
    "sg:classifiers":[
        {
            "category":"Manufacturing",
            "subcategory":"Printing",
            "type":"Manufacturing & Wholesale Goods"
        }
    ],
    "sg:phone":"+1 450 477 0018",
    "sg:postcode":"J7L 1T9",
    "sg:province":"QC",
    "sg:tags":[
        "screen"
    ],
    "wof:name":"Serigraphie Du Nord Inc",
    "wof:placetype":"venue"
},
  "geometry": {"coordinates":[-73.653091,45.73967],"type":"Point"}
}