{
  "type": "Feature",
  "properties": {
    "addr:full":"28 Amisk St Moose Factory ON P0L 1W0",
    "addr:housenumber":"28",
    "addr:postcode":"p0l 1w0",
    "addr:street":"Amisk St",
    "iso:country":"CA",
    "sg:address":"28 Amisk St",
    "sg:city":"Moose Factory",
    "sg:classifiers":[
        {
            "category":"Education",
            "subcategory":"School",
            "type":"Public Place"
        }
    ],
    "sg:phone":"+1 705 658 5610",
    "sg:postcode":"P0L 1W0",
    "sg:province":"ON",
    "wof:name":"Delores D Echum High School",
    "wof:placetype":"venue"
},
  "geometry": {"coordinates":[-80.59711456300001,51.2601966858],"type":"Point"}
}