{
  "type": "Feature",
  "properties": {
    "addr:full":"Langley BC V2Y 1N1",
    "addr:postcode":"v2y 1n1",
    "iso:country":"CA",
    "sg:city":"Langley",
    "sg:classifiers":[
        {
            "category":"Farming",
            "subcategory":"Farm",
            "type":"Manufacturing & Wholesale Goods"
        }
    ],
    "sg:phone":"+1 604 534 0278",
    "sg:postcode":"V2Y 1N1",
    "sg:province":"BC",
    "sg:tags":[
        "mushroom"
    ],
    "wof:name":"All Seasons Mushroom Farms Inc",
    "wof:placetype":"venue"
},
  "geometry": {"coordinates":[-122.663521,49.118229],"type":"Point"}
}