{
  "type": "Feature",
  "properties": {
    "iso:country":"CA",
    "sg:address":"11 Cartwright St",
    "sg:city":"Grand Falls-Windsor",
    "sg:classifiers":[
        {
            "category":"Health Services",
            "subcategory":"Doctor",
            "type":"Services"
        }
    ],
    "sg:phone":"+1 709 489 5566",
    "sg:postcode":"A2A 1L7",
    "sg:province":"NL",
    "sg:tags":[
        "physician",
        "surgeon"
    ],
    "wof:name":"Sheridan, J J MD",
    "wof:placetype":"venue"
},
  "geometry": {"coordinates":[-55.6416473389,48.9311408997],"type":"Point"}
}