{
  "type": "Feature",
  "properties": {
    "addr:full":"310 First St Midland ON L4R 3N9",
    "addr:housenumber":"310",
    "addr:postcode":"l4r 3n9",
    "addr:street":"First St",
    "iso:country":"CA",
    "sg:address":"310 First St",
    "sg:city":"Midland",
    "sg:classifiers":[
        {
            "category":"Health Services",
            "subcategory":"Chiropractor",
            "type":"Services"
        }
    ],
    "sg:phone":"+1 705 527 9021",
    "sg:postcode":"L4R 3N9",
    "sg:province":"ON",
    "wof:name":"Edwards, William R DC",
    "wof:placetype":"venue"
},
  "geometry": {"coordinates":[-79.88632200000001,44.748604],"type":"Point"}
}