{
  "type": "Feature",
  "properties": {
    "addr:full":"2228 Kingston Rd Scarborough ON M1N 1T9",
    "addr:housenumber":"2228",
    "addr:postcode":"m1n 1t9",
    "addr:street":"Kingston Rd",
    "iso:country":"CA",
    "sg:address":"2228 Kingston Rd",
    "sg:city":"Scarborough",
    "sg:classifiers":[
        {
            "category":"Restaurant",
            "type":"Food & Drink"
        }
    ],
    "sg:phone":"+1 416 264 1677",
    "sg:postcode":"M1N 1T9",
    "sg:province":"ON",
    "sg:tags":[
        "pizza"
    ],
    "wof:name":"Pizzaville",
    "wof:placetype":"venue"
},
  "geometry": {"coordinates":[-79.252762,43.70438],"type":"Point"}
}