{
  "type": "Feature",
  "properties": {
    "addr:full":"1616 Rue Sainte-Catherine O Montreal QC H3H 1L7",
    "addr:housenumber":"1616",
    "addr:postcode":"h3h 1l7",
    "addr:street":"Rue Sainte-Catherine O",
    "iso:country":"CA",
    "sg:address":"1616 Rue Sainte-Catherine O",
    "sg:city":"Montreal",
    "sg:classifiers":[
        {
            "category":"Restaurant",
            "type":"Food & Drink"
        }
    ],
    "sg:phone":"+1 514 934 1512",
    "sg:postcode":"H3H 1L7",
    "sg:province":"QC",
    "sg:tags":[
        "cafe"
    ],
    "wof:name":"Pagnelli Bistro",
    "wof:placetype":"venue"
},
  "geometry": {"coordinates":[-73.55278,45.521931],"type":"Point"}
}