{
  "type": "Feature",
  "properties": {
    "addr:full":"Timmins ON P4N 6A3",
    "addr:postcode":"p4n 6a3",
    "iso:country":"CA",
    "sg:city":"Timmins",
    "sg:classifiers":[
        {
            "category":"Building & Trades",
            "subcategory":"Construction",
            "type":"Services"
        }
    ],
    "sg:phone":"+1 705 264 2680",
    "sg:postcode":"P4N 6A3",
    "sg:province":"ON",
    "sg:tags":[
        "painter"
    ],
    "wof:name":"Gil's Painting & Decorating",
    "wof:placetype":"venue"
},
  "geometry": {"coordinates":[-81.334656,48.476952],"type":"Point"}
}