{
  "type": "Feature",
  "properties": {
    "iso:country":"CA",
    "sg:address":"64 Six Point Rd",
    "sg:city":"Etobicoke",
    "sg:classifiers":[
        {
            "category":"Building & Trades",
            "subcategory":"Construction",
            "type":"Services"
        }
    ],
    "sg:phone":"+1 416 234 5966",
    "sg:postcode":"M8Z 2X2",
    "sg:province":"ON",
    "sg:tags":[
        "woodworker"
    ],
    "wof:name":"Concepts Inc Wood",
    "wof:placetype":"venue"
},
  "geometry": {"coordinates":[-79.52294921879999,43.6365661621],"type":"Point"}
}