{
  "type": "Feature",
  "properties": {
    "addr:full":"11565 149 St NW Edmonton AB T5M 1W9",
    "addr:housenumber":"11565",
    "addr:postcode":"t5m 1w9",
    "addr:street":"149 St Nw",
    "iso:country":"CA",
    "sg:address":"11565 149 St NW",
    "sg:city":"Edmonton",
    "sg:classifiers":[
        {
            "category":"Wholesale",
            "subcategory":"Chemicals & Plastics",
            "type":"Manufacturing & Wholesale Goods"
        }
    ],
    "sg:phone":"+1 780 454 2006",
    "sg:postcode":"T5M 1W9",
    "sg:province":"AB",
    "sg:tags":[
        "lighting",
        "fixture"
    ],
    "wof:name":"Convex Light Control Media",
    "wof:placetype":"venue"
},
  "geometry": {"coordinates":[-113.577758789,53.5668334961],"type":"Point"}
}