{
  "type": "Feature",
  "properties": {
    "addr:full":"251 Rue Robinson S Granby QC J2G 7M5",
    "addr:housenumber":"251",
    "addr:postcode":"j2g 7m5",
    "addr:street":"Rue Robinson S Granby",
    "iso:country":"CA",
    "sg:address":"251 Rue Robinson S",
    "sg:city":"Granby",
    "sg:classifiers":[
        {
            "category":"Shopping",
            "type":"Retail Goods"
        }
    ],
    "sg:phone":"+1 450 375 7000",
    "sg:postcode":"J2G 7M5",
    "sg:province":"QC",
    "sg:tags":[
        "equipment",
        "telephone",
        "supply"
    ],
    "wof:name":"Systeme Telephonique L'Estrie",
    "wof:placetype":"venue"
},
  "geometry": {"coordinates":[-72.74127960209999,45.3994522095],"type":"Point"}
}