{
  "type": "Feature",
  "properties": {
    "iso:country":"CA",
    "sg:address":"2160 Lonsdale Ave",
    "sg:city":"North Vancouver",
    "sg:classifiers":[
        {
            "category":"Recreation",
            "type":"Entertainment"
        }
    ],
    "sg:phone":"+1 604 985 2321",
    "sg:postcode":"V7M 2K7",
    "sg:province":"BC",
    "sg:tags":[
        "amusement"
    ],
    "wof:name":"North Vancouver Lawn Bwlng Clb",
    "wof:placetype":"venue"
},
  "geometry": {"coordinates":[-123.072006226,49.3289794922],"type":"Point"}
}