{
  "type": "Feature",
  "properties": {
    "addr:full":"Trois-Pistoles QC G0L 4K0",
    "addr:postcode":"g0l 4k0",
    "iso:country":"CA",
    "sg:city":"Trois-Pistoles",
    "sg:classifiers":[
        {
            "category":"Government",
            "subcategory":"Office",
            "type":"Public Place"
        }
    ],
    "sg:phone":"+1 418 851 1995",
    "sg:postcode":"G0L 4K0",
    "sg:province":"QC",
    "sg:tags":[
        "municipality"
    ],
    "wof:name":"Ville DE Trois-Pistoles",
    "wof:placetype":"venue"
},
  "geometry": {"coordinates":[-69.17514799999999,48.125515],"type":"Point"}
}