{
  "type": "Feature",
  "properties": {
    "addr:full":"821 St George St Annapolis Royal NS B0S 1A0",
    "addr:housenumber":"821",
    "addr:postcode":"b0s 1a0",
    "addr:street":"St George St",
    "iso:country":"CA",
    "sg:address":"821 St George St",
    "sg:city":"Annapolis Royal",
    "sg:classifiers":[
        {
            "category":"Health Services",
            "subcategory":"Clinic",
            "type":"Services"
        }
    ],
    "sg:phone":"+1 902 532 2381",
    "sg:postcode":"B0S 1A0",
    "sg:province":"NS",
    "wof:name":"Nova Scotia Public Health",
    "wof:placetype":"venue"
},
  "geometry": {"coordinates":[-65.50054900000001,44.736813],"type":"Point"}
}