{
  "type": "Feature",
  "properties": {
    "iso:country":"CA",
    "sg:city":"Montreal",
    "sg:classifiers":[
        {
            "category":"Personal",
            "subcategory":"Beauty Salon",
            "type":"Services"
        }
    ],
    "sg:phone":"+1 514 351 1616",
    "sg:postcode":"H1L 2N7",
    "sg:province":"QC",
    "wof:name":"Coiffure Josee Longpre Enr",
    "wof:placetype":"venue"
},
  "geometry": {"coordinates":[-73.51754,45.60487],"type":"Point"}
}