{
  "type": "Feature",
  "properties": {
    "iso:country":"CA",
    "sg:address":"875 Route 101",
    "sg:city":"Nasonworth",
    "sg:classifiers":[
        {
            "category":"Organizations",
            "subcategory":"Religious Organization",
            "type":"Services"
        }
    ],
    "sg:phone":"+1 506 459 3313",
    "sg:postcode":"E3C 2C1",
    "sg:province":"NB",
    "sg:tags":[
        "church"
    ],
    "wof:name":"New Maryland United Church",
    "wof:placetype":"venue"
},
  "geometry": {"coordinates":[-66.6780700684,45.8380508423],"type":"Point"}
}