{
  "type": "Feature",
  "properties": {
    "addr:full":"428 Rue Principale Vallee-Jonction QC G0S 3J0",
    "addr:housenumber":"428",
    "addr:postcode":"g0s 3j0",
    "addr:street":"Rue Principale",
    "iso:country":"CA",
    "sg:address":"428 Rue Principale",
    "sg:city":"Vallee-Jonction",
    "sg:classifiers":[
        {
            "category":"Autos & Motor Vehicles",
            "subcategory":"Motorcycle Sales",
            "type":"Retail Goods"
        }
    ],
    "sg:phone":"+1 418 253 6164",
    "sg:postcode":"G0S 3J0",
    "sg:province":"QC",
    "sg:tags":[
        "saw"
    ],
    "wof:name":"Sport Tardif Inc",
    "wof:placetype":"venue"
},
  "geometry": {"coordinates":[-70.9205322266,46.3714866638],"type":"Point"}
}