{
  "type": "Feature",
  "properties": {
    "iso:country":"CA",
    "sg:address":"16 Pine St",
    "sg:city":"Collingwood",
    "sg:classifiers":[
        {
            "category":"Retail",
            "subcategory":"Veterinary Services",
            "type":"Services"
        }
    ],
    "sg:phone":"+1 705 445 1901",
    "sg:postcode":"L9Y 2N7",
    "sg:province":"ON",
    "sg:tags":[
        "veterinarian"
    ],
    "wof:name":"Collingwood Veterinary Svc",
    "wof:placetype":"venue"
},
  "geometry": {"coordinates":[-80.2190704346,44.5022010803],"type":"Point"}
}