{
  "type": "Feature",
  "properties": {
    "addr:full":"100 Medhurst Dr # 515 Nepean ON K2G 5W7",
    "addr:housenumber":"100;515",
    "addr:postcode":"k2g 5w7",
    "addr:street":"Medhurst Dr #",
    "iso:country":"CA",
    "sg:address":"100 Medhurst Dr # 515",
    "sg:city":"Nepean",
    "sg:classifiers":[
        {
            "category":"Professional",
            "subcategory":"Computer Services",
            "type":"Services"
        }
    ],
    "sg:phone":"+1 613 225 8658",
    "sg:postcode":"K2G 5W7",
    "sg:province":"ON",
    "sg:tags":[
        "internet"
    ],
    "wof:name":"Insta.biz",
    "wof:placetype":"venue"
},
  "geometry": {"coordinates":[-75.747131,45.336044],"type":"Point"}
}