{
  "type": "Feature",
  "properties": {
    "iso:country":"CA",
    "sg:address":"50 Don Park Rd # 4",
    "sg:city":"Markham",
    "sg:classifiers":[
        {
            "category":"Food & Beverages",
            "subcategory":"Meat & Fish",
            "type":"Retail Goods"
        }
    ],
    "sg:phone":"+1 905 475 6374",
    "sg:postcode":"L3R 1J3",
    "sg:province":"ON",
    "sg:tags":[
        "seafood"
    ],
    "wof:name":"Bergon Lobsters",
    "wof:placetype":"venue"
},
  "geometry": {"coordinates":[-79.349075,43.823933],"type":"Point"}
}