{
  "type": "Feature",
  "properties": {
    "iso:country":"CA",
    "sg:city":"London",
    "sg:classifiers":[
        {
            "category":"Insurance",
            "subcategory":"Insurance Agent",
            "type":"Services"
        }
    ],
    "sg:phone":"+1 519 645 6500",
    "sg:postcode":"N6C 2R5",
    "sg:province":"ON",
    "sg:tags":[
        "adjuster"
    ],
    "wof:name":"Shumka Craig & Moore",
    "wof:placetype":"venue"
},
  "geometry": {"coordinates":[-81.227409,42.962193],"type":"Point"}
}