{
  "type": "Feature",
  "properties": {
    "addr:full":"6465 Millcreek Dr # 100 Mississauga ON L5N 5R3",
    "addr:housenumber":"6465",
    "addr:postcode":"l5n 5r3",
    "addr:street":"Millcreek Dr # 100",
    "iso:country":"CA",
    "sg:address":"6465 Millcreek Dr # 100",
    "sg:city":"Mississauga",
    "sg:classifiers":[
        {
            "category":"Personal",
            "type":"Services"
        }
    ],
    "sg:phone":"+1 905 814 0400",
    "sg:postcode":"L5N 5R3",
    "sg:province":"ON",
    "sg:tags":[
        "control",
        "weight"
    ],
    "wof:name":"Good Life Fitness Clubs",
    "wof:placetype":"venue"
},
  "geometry": {"coordinates":[-79.741562,43.590412],"type":"Point"}
}