{
  "type": "Feature",
  "properties": {
    "addr:full":"4955 Clifton Hill Niagara Falls ON L2G 3N5",
    "addr:housenumber":"4955",
    "addr:postcode":"l2g 3n5",
    "addr:street":"Clifton Hill",
    "iso:country":"CA",
    "sg:address":"4955 Clifton Hill",
    "sg:city":"Niagara Falls",
    "sg:classifiers":[
        {
            "category":"Shopping",
            "subcategory":"Jewelry",
            "type":"Retail Goods"
        }
    ],
    "sg:phone":"+1 905 358 1612",
    "sg:postcode":"L2G 3N5",
    "sg:province":"ON",
    "sg:tags":[
        "jeweler"
    ],
    "wof:name":"Canada's Original Jewellery",
    "wof:placetype":"venue"
},
  "geometry": {"coordinates":[-79.075478,43.091778],"type":"Point"}
}