{
  "type": "Feature",
  "properties": {
    "addr:full":"Toronto ON M5G 1Z8",
    "addr:postcode":"m5g 1z8",
    "iso:country":"CA",
    "sg:city":"Toronto",
    "sg:classifiers":[
        {
            "category":"Local Transit",
            "type":"Transportation"
        }
    ],
    "sg:phone":"+1 416 594 0343",
    "sg:postcode":"M5G 1Z8",
    "sg:province":"ON",
    "sg:tags":[
        "bus",
        "line"
    ],
    "wof:name":"Greyhound Canada Trans Corp",
    "wof:placetype":"venue"
},
  "geometry": {"coordinates":[-79.38649700000001,43.655277],"type":"Point"}
}