{
  "type": "Feature",
  "properties": {
    "addr:full":"1053 Rue Bourget Longueuil QC J4K 2V7",
    "addr:housenumber":"1053",
    "addr:postcode":"j4k 2v7",
    "addr:street":"Rue Bourget",
    "iso:country":"CA",
    "sg:address":"1053 Rue Bourget",
    "sg:city":"Longueuil",
    "sg:classifiers":[
        {
            "category":"Manufacturing",
            "subcategory":"Tools & Machinery",
            "type":"Manufacturing & Wholesale Goods"
        }
    ],
    "sg:phone":"+1 450 679 4120",
    "sg:postcode":"J4K 2V7",
    "sg:province":"QC",
    "sg:tags":[
        "equipment",
        "system",
        "automation"
    ],
    "wof:name":"Lavoservice Electronique Tf",
    "wof:placetype":"venue"
},
  "geometry": {"coordinates":[-73.506744,45.513905],"type":"Point"}
}