{
  "type": "Feature",
  "properties": {
    "iso:country":"CA",
    "sg:address":"181 Harbord St",
    "sg:city":"Toronto",
    "sg:classifiers":[
        {
            "category":"Health Services",
            "subcategory":"Clinic",
            "type":"Services"
        }
    ],
    "sg:phone":"+1 416 706 6305",
    "sg:postcode":"M5S 1H5",
    "sg:province":"ON",
    "wof:name":"Feet For Life Reflexology Clnc",
    "wof:placetype":"venue"
},
  "geometry": {"coordinates":[-79.408058,43.66169],"type":"Point"}
}