{
  "type": "Feature",
  "properties": {
    "addr:full":"181 Harbord St Toronto ON M5S 1H5",
    "addr:housenumber":"181",
    "addr:postcode":"m5s 1h5",
    "addr:street":"Harbord St",
    "iso:country":"CA",
    "sg:address":"181 Harbord St",
    "sg:city":"Toronto",
    "sg:classifiers":[
        {
            "category":"Health Services",
            "subcategory":"Clinic",
            "type":"Services"
        }
    ],
    "sg:phone":"+1 416 706 6305",
    "sg:postcode":"M5S 1H5",
    "sg:province":"ON",
    "wof:name":"Feet For Life Reflexology Clnc",
    "wof:placetype":"venue"
},
  "geometry": {"coordinates":[-79.408058,43.66169],"type":"Point"}
}