{
  "type": "Feature",
  "properties": {
    "addr:full":"Scarborough ON M1V 3S2",
    "addr:postcode":"m1v 3s2",
    "iso:country":"CA",
    "sg:city":"Scarborough",
    "sg:classifiers":[
        {
            "category":"Shopping",
            "subcategory":"Used Merchandise",
            "type":"Retail Goods"
        }
    ],
    "sg:phone":"+1 416 297 5151",
    "sg:postcode":"M1V 3S2",
    "sg:province":"ON",
    "sg:tags":[
        "exporter"
    ],
    "wof:name":"Impx Canada Inc",
    "wof:placetype":"venue"
},
  "geometry": {"coordinates":[-79.258644,43.812553],"type":"Point"}
}