{
  "type": "Feature",
  "properties": {
    "iso:country":"CA",
    "sg:address":"40 Osprey Rd",
    "sg:city":"Upper Coverdale",
    "sg:classifiers":[
        {
            "category":"Professional",
            "subcategory":"Business Services",
            "type":"Services"
        }
    ],
    "sg:phone":"+1 506 857 3078",
    "sg:postcode":"E1J 1T8",
    "sg:province":"NB",
    "sg:tags":[
        "trade",
        "exposition",
        "fair",
        "show"
    ],
    "wof:name":"Legault Decorating Ltd",
    "wof:placetype":"venue"
},
  "geometry": {"coordinates":[-64.89953613279999,46.0451660156],"type":"Point"}
}