{
  "type": "Feature",
  "properties": {
    "addr:full":"4815 Swannell Dr Hazelton BC V0J 1Y0",
    "addr:housenumber":"4815",
    "addr:postcode":"v0j 1y0",
    "addr:street":"Swannell Dr",
    "iso:country":"CA",
    "sg:address":"4815 Swannell Dr",
    "sg:city":"Hazelton",
    "sg:classifiers":[
        {
            "category":"Education",
            "subcategory":"College",
            "type":"Public Place"
        }
    ],
    "sg:phone":"+1 250 842 5291",
    "sg:postcode":"V0J 1Y0",
    "sg:province":"BC",
    "sg:tags":[
        "academic",
        "school"
    ],
    "wof:name":"Northwest Community College",
    "wof:placetype":"venue"
},
  "geometry": {"coordinates":[-127.650757,55.265137],"type":"Point"}
}