{
  "type": "Feature",
  "properties": {
    "addr:full":"Langley BC V2Y 1A2",
    "addr:postcode":"v2y 1a2",
    "iso:country":"CA",
    "sg:city":"Langley",
    "sg:classifiers":[
        {
            "category":"Freight",
            "type":"Transportation"
        }
    ],
    "sg:phone":"+1 604 513 6100",
    "sg:postcode":"V2Y 1A2",
    "sg:province":"BC",
    "sg:tags":[
        "courier"
    ],
    "wof:name":"Purolator Courier Ltd",
    "wof:placetype":"venue"
},
  "geometry": {"coordinates":[-122.669006,49.114082],"type":"Point"}
}