{
  "type": "Feature",
  "properties": {
    "addr:full":"680 Columbia Blvd W Lethbridge AB T1K 5J9",
    "addr:housenumber":"680",
    "addr:postcode":"t1k 5j9",
    "addr:street":"Columbia Blvd W",
    "iso:country":"CA",
    "sg:address":"680 Columbia Blvd W",
    "sg:city":"Lethbridge",
    "sg:classifiers":[
        {
            "category":"Food & Beverages",
            "subcategory":"Liquor & Beverages",
            "type":"Retail Goods"
        }
    ],
    "sg:phone":"+1 403 381 1133",
    "sg:postcode":"T1K 5J9",
    "sg:province":"AB",
    "sg:tags":[
        "store"
    ],
    "wof:name":"Westgate Liquor Store",
    "wof:placetype":"venue"
},
  "geometry": {"coordinates":[-112.89041899999999,49.670296],"type":"Point"}
}