{
  "type": "Feature",
  "properties": {
    "addr:full":"Lac LA Hache BC V0K 1T0",
    "addr:postcode":"v0k 1t0",
    "addr:street":"Lac",
    "iso:country":"CA",
    "sg:city":"Lac LA Hache",
    "sg:classifiers":[
        {
            "category":"Manufacturing",
            "subcategory":"Lumber",
            "type":"Manufacturing & Wholesale Goods"
        }
    ],
    "sg:phone":"+1 250 396 7208",
    "sg:postcode":"V0K 1T0",
    "sg:province":"BC",
    "sg:tags":[
        "forester"
    ],
    "wof:name":"Dwb Forestry Svc Ltd",
    "wof:placetype":"venue"
},
  "geometry": {"coordinates":[-121.533195496,51.8289222717],"type":"Point"}
}