{
  "type": "Feature",
  "properties": {
    "addr:full":"Caplan QC G0C 1H0",
    "addr:postcode":"g0c 1h0",
    "iso:country":"CA",
    "sg:city":"Caplan",
    "sg:classifiers":[
        {
            "category":"Building & Trades",
            "subcategory":"Construction",
            "type":"Services"
        }
    ],
    "sg:phone":"+1 418 388 2961",
    "sg:postcode":"G0C 1H0",
    "sg:province":"QC",
    "sg:tags":[
        "general",
        "contractor"
    ],
    "wof:name":"Jean-Yves Lepage Constr Inc",
    "wof:placetype":"venue"
},
  "geometry": {"coordinates":[-65.68244199999999,48.103828],"type":"Point"}
}