{
  "type": "Feature",
  "properties": {
    "addr:full":"1552 King St E Hamilton ON L8K 1T2",
    "addr:housenumber":"1552",
    "addr:postcode":"l8k 1t2",
    "addr:street":"King St E",
    "iso:country":"CA",
    "sg:address":"1552 King St E",
    "sg:city":"Hamilton",
    "sg:classifiers":[
        {
            "category":"Health Services",
            "subcategory":"Medical Lab",
            "type":"Services"
        }
    ],
    "sg:phone":"+1 905 549 2274",
    "sg:postcode":"L8K 1T2",
    "sg:province":"ON",
    "wof:name":"Di Nardo Denture Clinic",
    "wof:placetype":"venue"
},
  "geometry": {"coordinates":[-79.81896999999999,43.236343],"type":"Point"}
}