{
  "type": "Feature",
  "properties": {
    "addr:full":"1263 Boul Des Seigneurs Terrebonne QC J6W 4P7",
    "addr:housenumber":"1263",
    "addr:postcode":"j6w 4p7",
    "addr:street":"Boul Des Seigneurs",
    "iso:country":"CA",
    "sg:address":"1263 Boul Des Seigneurs",
    "sg:city":"Terrebonne",
    "sg:classifiers":[
        {
            "category":"Personal",
            "subcategory":"Beauty Salon",
            "type":"Services"
        }
    ],
    "sg:phone":"+1 450 961 2828",
    "sg:postcode":"J6W 4P7",
    "sg:province":"QC",
    "sg:tags":[
        "manicuring"
    ],
    "wof:name":"Ongles Design Kh",
    "wof:placetype":"venue"
},
  "geometry": {"coordinates":[-73.64812499999999,45.70018],"type":"Point"}
}