{
  "type": "Feature",
  "properties": {
    "iso:country":"CA",
    "sg:address":"620 Rue Desmarais",
    "sg:city":"Richmond",
    "sg:classifiers":[
        {
            "category":"Manufacturing",
            "subcategory":"Tools & Machinery",
            "type":"Manufacturing & Wholesale Goods"
        }
    ],
    "sg:phone":"+1 819 826 3379",
    "sg:postcode":"J0B 2H0",
    "sg:province":"QC",
    "sg:tags":[
        "machine",
        "shop"
    ],
    "wof:name":"Engrenages Specialises Inc",
    "wof:placetype":"venue"
},
  "geometry": {"coordinates":[-72.12916564939999,45.66147995],"type":"Point"}
}