{
  "type": "Feature",
  "properties": {
    "addr:full":"Schreiber ON P0T 2S0",
    "addr:postcode":"p0t 2s0",
    "iso:country":"CA",
    "sg:city":"Schreiber",
    "sg:classifiers":[
        {
            "category":"Retail",
            "subcategory":"Funeral Services",
            "type":"Services"
        }
    ],
    "sg:phone":"+1 807 824 2261",
    "sg:postcode":"P0T 2S0",
    "sg:province":"ON",
    "sg:tags":[
        "director"
    ],
    "wof:name":"King Funeral Home Ltd",
    "wof:placetype":"venue"
},
  "geometry": {"coordinates":[-87.2687988281,48.8082847595],"type":"Point"}
}