{
  "type": "Feature",
  "properties": {
    "addr:full":"1075 Av Bernard Outremont QC H2V 1V1",
    "addr:housenumber":"1075",
    "addr:postcode":"h2v 1v1",
    "addr:street":"Av Bernard",
    "iso:country":"CA",
    "sg:address":"1075 Av Bernard",
    "sg:city":"Outremont",
    "sg:classifiers":[
        {
            "category":"Organizations",
            "subcategory":"Religious Organization",
            "type":"Services"
        }
    ],
    "sg:phone":"+1 514 274 0564",
    "sg:postcode":"H2V 1V1",
    "sg:province":"QC",
    "sg:tags":[
        "synagogue"
    ],
    "wof:name":"Congregation Machzikei Torah",
    "wof:placetype":"venue"
},
  "geometry": {"coordinates":[-73.60716247560001,45.522102356],"type":"Point"}
}