{
  "type": "Feature",
  "properties": {
    "addr:full":"Oakbank MB R0E 1J0",
    "addr:postcode":"r0e 1j0",
    "iso:country":"CA",
    "sg:city":"Oakbank",
    "sg:classifiers":[
        {
            "category":"Health Services",
            "subcategory":"Doctor",
            "type":"Services"
        }
    ],
    "sg:phone":"+1 204 444 2934",
    "sg:postcode":"R0E 1J0",
    "sg:province":"MB",
    "sg:tags":[
        "physician",
        "surgeon"
    ],
    "wof:name":"Oakbank Medical Clinic",
    "wof:placetype":"venue"
},
  "geometry": {"coordinates":[-96.8665313721,50.152545929],"type":"Point"}
}