{
  "type": "Feature",
  "properties": {
    "addr:full":"Etobicoke ON M9A 1B2",
    "addr:postcode":"m9a 1b2",
    "iso:country":"CA",
    "sg:city":"Etobicoke",
    "sg:classifiers":[
        {
            "category":"Banks & Credit Unions",
            "subcategory":"Investment Brokerage",
            "type":"Services"
        }
    ],
    "sg:phone":"+1 416 239 0415",
    "sg:postcode":"M9A 1B2",
    "sg:province":"ON",
    "wof:name":"Edward Jones",
    "wof:placetype":"venue"
},
  "geometry": {"coordinates":[-79.514893,43.658909],"type":"Point"}
}