{
  "type": "Feature",
  "properties": {
    "addr:full":"80 Boul Henri-Bourassa E # 200 Montreal QC H3L 1B5",
    "addr:housenumber":"80",
    "addr:postcode":"h3l 1b5",
    "addr:street":"Boul Henri-Bourassa E # 200",
    "iso:country":"CA",
    "sg:address":"80 Boul Henri-Bourassa E # 200",
    "sg:city":"Montreal",
    "sg:classifiers":[
        {
            "category":"Professional",
            "subcategory":"Business Services",
            "type":"Services"
        }
    ],
    "sg:phone":"+1 514 381 2525",
    "sg:postcode":"H3L 1B5",
    "sg:province":"QC",
    "sg:tags":[
        "notary"
    ],
    "wof:name":"Meunier, Francine",
    "wof:placetype":"venue"
},
  "geometry": {"coordinates":[-73.6703033447,45.550868988],"type":"Point"}
}