{
  "type": "Feature",
  "properties": {
    "iso:country":"CA",
    "sg:city":"Richmond",
    "sg:classifiers":[
        {
            "category":"Food & Beverages",
            "subcategory":"Specialty",
            "type":"Retail Goods"
        }
    ],
    "sg:phone":"+1 604 273 2922",
    "sg:postcode":"V6Y 4B6",
    "sg:province":"BC",
    "sg:tags":[
        "tea",
        "coffee"
    ],
    "wof:name":"Java Jungle Cafe",
    "wof:placetype":"venue"
},
  "geometry": {"coordinates":[-123.13203430199999,49.1690063477],"type":"Point"}
}