{
  "type": "Feature",
  "properties": {
    "addr:full":"Lewisporte NL A0G 3A0",
    "addr:postcode":"a0g 3a0",
    "iso:country":"CA",
    "sg:city":"Lewisporte",
    "sg:classifiers":[
        {
            "category":"Insurance",
            "subcategory":"Insurance Agent",
            "type":"Services"
        }
    ],
    "sg:phone":"+1 709 535 2768",
    "sg:postcode":"A0G 3A0",
    "sg:province":"NL",
    "wof:name":"Steers Insurance Ltd",
    "wof:placetype":"venue"
},
  "geometry": {"coordinates":[-55.059929,49.241791],"type":"Point"}
}