{
  "type": "Feature",
  "properties": {
    "addr:full":"1398 Cartwright St Vancouver BC V6H 3R8",
    "addr:housenumber":"1398",
    "addr:postcode":"v6h 3r8",
    "addr:street":"Cartwright St",
    "iso:country":"CA",
    "sg:address":"1398 Cartwright St",
    "sg:city":"Vancouver",
    "sg:classifiers":[
        {
            "category":"Organizations",
            "subcategory":"Professional Association",
            "type":"Services"
        }
    ],
    "sg:phone":"+1 604 684 7223",
    "sg:postcode":"V6H 3R8",
    "sg:province":"BC",
    "wof:name":"False Creek Racing Canoe Club",
    "wof:placetype":"venue"
},
  "geometry": {"coordinates":[-123.135109,49.269962],"type":"Point"}
}