{
  "type": "Feature",
  "properties": {
    "addr:full":"150 King St W Toronto ON M5H 1J9",
    "addr:housenumber":"150",
    "addr:postcode":"m5h 1j9",
    "addr:street":"King St W",
    "iso:country":"CA",
    "sg:address":"150 King St W",
    "sg:city":"Toronto",
    "sg:classifiers":[
        {
            "category":"Retail",
            "subcategory":"Laundry & Dry Cleaning",
            "type":"Services"
        }
    ],
    "sg:phone":"+1 416 408 0990",
    "sg:postcode":"M5H 1J9",
    "sg:province":"ON",
    "sg:tags":[
        "cleaners"
    ],
    "wof:name":"Junction Dry Cleaners",
    "wof:placetype":"venue"
},
  "geometry": {"coordinates":[-79.38372,43.647972],"type":"Point"}
}