{
  "type": "Feature",
  "properties": {
    "addr:full":"2015 Continental Ave Windsor ON N9E 3P2",
    "addr:housenumber":"2015",
    "addr:postcode":"n9e 3p2",
    "addr:street":"Continental Ave",
    "iso:country":"CA",
    "sg:address":"2015 Continental Ave",
    "sg:city":"Windsor",
    "sg:classifiers":[
        {
            "category":"Building & Trades",
            "subcategory":"Plumbing",
            "type":"Services"
        }
    ],
    "sg:phone":"+1 519 250 8990",
    "sg:postcode":"N9E 3P2",
    "sg:province":"ON",
    "sg:tags":[
        "contractor"
    ],
    "wof:name":"Vitella Plumbing Inc",
    "wof:placetype":"venue"
},
  "geometry": {"coordinates":[-83.055176,42.272751],"type":"Point"}
}