{
  "type": "Feature",
  "properties": {
    "addr:full":"Surrey BC V3R 4G8",
    "addr:postcode":"v3r 4g8",
    "iso:country":"CA",
    "sg:city":"Surrey",
    "sg:classifiers":[
        {
            "category":"Professional",
            "subcategory":"Lawyer & Legal Services",
            "type":"Services"
        }
    ],
    "sg:phone":"+1 604 585 1196",
    "sg:postcode":"V3R 4G8",
    "sg:province":"BC",
    "sg:tags":[
        "attorney"
    ],
    "wof:name":"Guildford Law Group",
    "wof:placetype":"venue"
},
  "geometry": {"coordinates":[-122.80059799999999,49.190231],"type":"Point"}
}