{
  "type": "Feature",
  "properties": {
    "addr:full":"380 Boul Labrosse Gatineau QC J8P 4P8",
    "addr:housenumber":"380",
    "addr:postcode":"j8p 4p8",
    "addr:street":"Boul Labrosse",
    "iso:country":"CA",
    "sg:address":"380 Boul Labrosse",
    "sg:city":"Gatineau",
    "sg:classifiers":[
        {
            "category":"Retail",
            "subcategory":"Auto Repair",
            "type":"Services"
        }
    ],
    "sg:phone":"+1 819 663 4014",
    "sg:postcode":"J8P 4P8",
    "sg:province":"QC",
    "sg:tags":[
        "body",
        "automobile",
        "painting"
    ],
    "wof:name":"Louis Guay Garage",
    "wof:placetype":"venue"
},
  "geometry": {"coordinates":[-75.640968,45.492134],"type":"Point"}
}