{
  "type": "Feature",
  "properties": {
    "addr:full":"900 Dufferin St Toronto ON M6H 4B1",
    "addr:housenumber":"900",
    "addr:postcode":"m6h 4b1",
    "addr:street":"Dufferin St",
    "iso:country":"CA",
    "sg:address":"900 Dufferin St",
    "sg:city":"Toronto",
    "sg:classifiers":[
        {
            "category":"Shopping",
            "subcategory":"Photographic Equipment",
            "type":"Retail Goods"
        }
    ],
    "sg:phone":"+1 416 535 8912",
    "sg:postcode":"M6H 4B1",
    "sg:province":"ON",
    "sg:tags":[
        "photo",
        "finishing"
    ],
    "wof:name":"Black's Photography",
    "wof:placetype":"venue"
},
  "geometry": {"coordinates":[-79.43435668950001,43.6567726135],"type":"Point"}
}