{
  "type": "Feature",
  "properties": {
    "addr:full":"2111 Rue Jean-Talon E Montreal QC H2E 1V4",
    "addr:housenumber":"2111",
    "addr:postcode":"h2e 1v4",
    "addr:street":"Rue Jean-Talon E",
    "iso:country":"CA",
    "sg:address":"2111 Rue Jean-Talon E",
    "sg:city":"Montreal",
    "sg:classifiers":[
        {
            "category":"Shopping",
            "subcategory":"Tobacco",
            "type":"Retail Goods"
        }
    ],
    "sg:phone":"+1 514 727 6894",
    "sg:postcode":"H2E 1V4",
    "sg:province":"QC",
    "sg:tags":[
        "cigarette",
        "cigar",
        "dealer"
    ],
    "wof:name":"Tabagie Des Deux Freres",
    "wof:placetype":"venue"
},
  "geometry": {"coordinates":[-73.60502624510001,45.5504112244],"type":"Point"}
}