{
  "type": "Feature",
  "properties": {
    "addr:full":"99 Jaguar Rd Timmins ON P4N 7C3",
    "addr:housenumber":"99",
    "addr:postcode":"p4n 7c3",
    "addr:street":"Jaguar Rd",
    "iso:country":"CA",
    "sg:address":"99 Jaguar Rd",
    "sg:city":"Timmins",
    "sg:classifiers":[
        {
            "category":"Wholesale",
            "subcategory":"Machinery & Supplies",
            "type":"Manufacturing & Wholesale Goods"
        }
    ],
    "sg:phone":"+1 705 268 9900",
    "sg:postcode":"P4N 7C3",
    "sg:province":"ON",
    "sg:tags":[
        "contractor"
    ],
    "wof:name":"Toromont Cat",
    "wof:placetype":"venue"
},
  "geometry": {"coordinates":[-81.42202,48.46999],"type":"Point"}
}