{
  "type": "Feature",
  "properties": {
    "iso:country":"CA",
    "sg:address":"301 Tillson Ave",
    "sg:city":"Tillsonburg",
    "sg:classifiers":[
        {
            "category":"Freight",
            "type":"Transportation"
        }
    ],
    "sg:phone":"+1 519 842 4215",
    "sg:postcode":"N4G 5E5",
    "sg:province":"ON",
    "sg:tags":[
        "packing",
        "export"
    ],
    "wof:name":"Tds Group Ltd",
    "wof:placetype":"venue"
},
  "geometry": {"coordinates":[-80.726578,42.876568],"type":"Point"}
}