{
  "type": "Feature",
  "properties": {
    "addr:full":"Burnaby BC V5J 3H6",
    "addr:postcode":"v5j 3h6",
    "iso:country":"CA",
    "sg:city":"Burnaby",
    "sg:classifiers":[
        {
            "category":"Retail",
            "subcategory":"Repair Shop",
            "type":"Services"
        }
    ],
    "sg:phone":"+1 604 451 7655",
    "sg:postcode":"V5J 3H6",
    "sg:province":"BC",
    "sg:tags":[
        "sharpening",
        "saw"
    ],
    "wof:name":"T & M Saw Svc",
    "wof:placetype":"venue"
},
  "geometry": {"coordinates":[-122.99642900000001,49.194138],"type":"Point"}
}