{
  "type": "Feature",
  "properties": {
    "addr:full":"29 Rue Saint-Pierre Quebec QC G1K 3Z3",
    "addr:housenumber":"29",
    "addr:postcode":"g1k 3z3",
    "addr:street":"Rue Saint-Pierre",
    "iso:country":"CA",
    "sg:address":"29 Rue Saint-Pierre",
    "sg:city":"Quebec",
    "sg:classifiers":[
        {
            "category":"Restaurant",
            "type":"Food & Drink"
        }
    ],
    "sg:phone":"+1 418 694 9176",
    "sg:postcode":"G1K 3Z3",
    "sg:province":"QC",
    "sg:tags":[
        "pub"
    ],
    "wof:name":"L'Oncle Antoine",
    "wof:placetype":"venue"
},
  "geometry": {"coordinates":[-71.20263671879999,46.8134536743],"type":"Point"}
}