{
  "type": "Feature",
  "properties": {
    "addr:full":"1275 Jacques-Cartier Riviere-Au-Tonnerre QC G0G 2L0",
    "addr:housenumber":"1275",
    "addr:postcode":"g0g 2l0",
    "addr:street":"Jacques-Cartier Riviere-Au-Tonnerre",
    "iso:country":"CA",
    "sg:address":"1275 Jacques-Cartier",
    "sg:city":"Riviere-Au-Tonnerre",
    "sg:classifiers":[
        {
            "category":"Organizations",
            "subcategory":"Professional Association",
            "type":"Services"
        }
    ],
    "sg:phone":"+1 418 465 2850",
    "sg:postcode":"G0G 2L0",
    "sg:province":"QC",
    "wof:name":"Loisirs DE Sheldrake",
    "wof:placetype":"venue"
},
  "geometry": {"coordinates":[-64.900566,50.264751],"type":"Point"}
}