{
  "type": "Feature",
  "properties": {
    "addr:full":"1155 Rue Saint-Joseph Valcourt QC J0E 2L0",
    "addr:housenumber":"1155",
    "addr:postcode":"j0e 2l0",
    "addr:street":"Rue Saint-Joseph",
    "iso:country":"CA",
    "sg:address":"1155 Rue Saint-Joseph",
    "sg:city":"Valcourt",
    "sg:classifiers":[
        {
            "category":"Government",
            "subcategory":"Office",
            "type":"Public Place"
        }
    ],
    "sg:phone":"+1 450 532 3313",
    "sg:postcode":"J0E 2L0",
    "sg:province":"QC",
    "sg:tags":[
        "village"
    ],
    "wof:name":"Valcourt Ville Ofc",
    "wof:placetype":"venue"
},
  "geometry": {"coordinates":[-72.314682,45.49202],"type":"Point"}
}