{
  "type": "Feature",
  "properties": {
    "addr:full":"86 Plant Farm Blvd Brantford ON N3S 7W3",
    "addr:housenumber":"86",
    "addr:postcode":"n3s 7w3",
    "addr:street":"Plant Farm Blvd",
    "iso:country":"CA",
    "sg:address":"86 Plant Farm Blvd",
    "sg:city":"Brantford",
    "sg:classifiers":[
        {
            "category":"Wholesale",
            "subcategory":"Machinery & Supplies",
            "type":"Manufacturing & Wholesale Goods"
        }
    ],
    "sg:phone":"+1 519 754 0015",
    "sg:postcode":"N3S 7W3",
    "sg:province":"ON",
    "sg:tags":[
        "equipment",
        "log",
        "splitting"
    ],
    "wof:name":"Tigercat Industries Inc",
    "wof:placetype":"venue"
},
  "geometry": {"coordinates":[-80.21366119379999,43.1542243958],"type":"Point"}
}