{
  "type": "Feature",
  "properties": {
    "addr:full":"North York ON M3N 2S5",
    "addr:postcode":"m3n 2s5",
    "iso:country":"CA",
    "sg:city":"North York",
    "sg:classifiers":[
        {
            "category":"Professional",
            "subcategory":"Detective & Security Services",
            "type":"Services"
        }
    ],
    "sg:phone":"+1 416 746 6007",
    "sg:postcode":"M3N 2S5",
    "sg:province":"ON",
    "sg:tags":[
        "guard",
        "patrol"
    ],
    "wof:name":"Gardwell Security Agency Inc",
    "wof:placetype":"venue"
},
  "geometry": {"coordinates":[-79.526169,43.745094],"type":"Point"}
}