{
  "type": "Feature",
  "properties": {
    "iso:country":"CA",
    "sg:city":"The Pas",
    "sg:classifiers":[
        {
            "category":"Shopping",
            "subcategory":"Florist",
            "type":"Retail Goods"
        }
    ],
    "sg:phone":"+1 204 623 5426",
    "sg:postcode":"R9A 1K9",
    "sg:province":"MB",
    "wof:name":"Berna-Dean Flowers & Gifts",
    "wof:placetype":"venue"
},
  "geometry": {"coordinates":[-101.253204346,53.822933197],"type":"Point"}
}