{
  "type": "Feature",
  "properties": {
    "addr:full":"812 Queen St E Sault Ste Marie ON P6A 2B1",
    "addr:housenumber":"812",
    "addr:postcode":"p6a 2b1",
    "addr:street":"Queen St E",
    "iso:country":"CA",
    "sg:address":"812 Queen St E",
    "sg:city":"Sault Ste Marie",
    "sg:classifiers":[
        {
            "category":"Shopping",
            "subcategory":"Used Merchandise",
            "type":"Retail Goods"
        }
    ],
    "sg:phone":"+1 705 253 7481",
    "sg:postcode":"P6A 2B1",
    "sg:province":"ON",
    "sg:tags":[
        "antique"
    ],
    "wof:name":"LA Grotta Antiques",
    "wof:placetype":"venue"
},
  "geometry": {"coordinates":[-84.32505,46.506954],"type":"Point"}
}