{
  "type": "Feature",
  "properties": {
    "addr:full":"479 Hochelaga St W Moose Jaw SK S6H 2G8",
    "addr:housenumber":"479",
    "addr:postcode":"s6h 2g8",
    "addr:street":"Hochelaga St W",
    "iso:country":"CA",
    "sg:address":"479 Hochelaga St W",
    "sg:city":"Moose Jaw",
    "sg:classifiers":[
        {
            "category":"Building & Trades",
            "subcategory":"Electrical",
            "type":"Services"
        }
    ],
    "sg:phone":"+1 306 692 6221",
    "sg:postcode":"S6H 2G8",
    "sg:province":"SK",
    "sg:tags":[
        "electric",
        "contractor"
    ],
    "wof:name":"Regal Electric Ltd",
    "wof:placetype":"venue"
},
  "geometry": {"coordinates":[-105.546440124,50.3960380554],"type":"Point"}
}