{
  "type": "Feature",
  "properties": {
    "addr:full":"Calgary AB T2Y 3H9",
    "addr:postcode":"t2y 3h9",
    "iso:country":"CA",
    "sg:city":"Calgary",
    "sg:classifiers":[
        {
            "category":"Restaurant",
            "type":"Food & Drink"
        }
    ],
    "sg:phone":"+1 403 254 5958",
    "sg:postcode":"T2Y 3H9",
    "sg:province":"AB",
    "wof:name":"Donair Place & Mediterranean",
    "wof:placetype":"venue"
},
  "geometry": {"coordinates":[-114.06486511200001,50.9015083313],"type":"Point"}
}