{
  "type": "Feature",
  "properties": {
    "addr:full":"50 Rossdean Dr North York ON M9L 2S1",
    "addr:housenumber":"50",
    "addr:postcode":"m9l 2s1",
    "addr:street":"Rossdean Dr",
    "iso:country":"CA",
    "sg:address":"50 Rossdean Dr",
    "sg:city":"North York",
    "sg:classifiers":[
        {
            "category":"Retail",
            "subcategory":"Auto Repair",
            "type":"Services"
        }
    ],
    "sg:phone":"+1 416 749 8183",
    "sg:postcode":"M9L 2S1",
    "sg:province":"ON",
    "sg:tags":[
        "exchanging",
        "engine"
    ],
    "wof:name":"Newport Motor Mfg CO Ltd",
    "wof:placetype":"venue"
},
  "geometry": {"coordinates":[-79.5400848389,43.7697029114],"type":"Point"}
}