{
  "type": "Feature",
  "properties": {
    "addr:full":"RR 3 Clifford ON N0G 1M0",
    "addr:postcode":"n0g 1m0",
    "addr:street":"Rr 3",
    "iso:country":"CA",
    "sg:address":"RR 3",
    "sg:city":"Clifford",
    "sg:classifiers":[
        {
            "category":"Organizations",
            "subcategory":"Religious Organization",
            "type":"Services"
        }
    ],
    "sg:phone":"+1 519 327 8222",
    "sg:postcode":"N0G 1M0",
    "sg:province":"ON",
    "sg:tags":[
        "church"
    ],
    "wof:name":"St James Lutheran Church",
    "wof:placetype":"venue"
},
  "geometry": {"coordinates":[-80.97931699999999,43.969601],"type":"Point"}
}