{
  "type": "Feature",
  "properties": {
    "addr:full":"Guelph ON N1H 1G8",
    "addr:postcode":"n1h 1g8",
    "iso:country":"CA",
    "sg:city":"Guelph",
    "sg:classifiers":[
        {
            "category":"Health Services",
            "subcategory":"Doctor",
            "type":"Services"
        }
    ],
    "sg:phone":"+1 519 821 1909",
    "sg:postcode":"N1H 1G8",
    "sg:province":"ON",
    "sg:tags":[
        "dentist"
    ],
    "wof:name":"Wright, Wayne D DDS",
    "wof:placetype":"venue"
},
  "geometry": {"coordinates":[-80.27996826170001,43.5633583069],"type":"Point"}
}