{
  "type": "Feature",
  "properties": {
    "addr:full":"56 Rue Hemmings Saint-Jean-Sur-Richelieu QC J3B 4P5",
    "addr:housenumber":"56",
    "addr:postcode":"j3b 4p5",
    "addr:street":"Rue Hemmings",
    "iso:country":"CA",
    "sg:address":"56 Rue Hemmings",
    "sg:city":"Saint-Jean-Sur-Richelieu",
    "sg:classifiers":[
        {
            "category":"Building & Trades",
            "subcategory":"Construction",
            "type":"Services"
        }
    ],
    "sg:phone":"+1 450 346 9834",
    "sg:postcode":"J3B 4P5",
    "sg:province":"QC",
    "sg:tags":[
        "excavating",
        "contractor"
    ],
    "wof:name":"P'Tit Loader Inc",
    "wof:placetype":"venue"
},
  "geometry": {"coordinates":[-73.291855,45.296753],"type":"Point"}
}