{
  "type": "Feature",
  "properties": {
    "iso:country":"CA",
    "sg:address":"674 Front St",
    "sg:city":"Quesnel",
    "sg:classifiers":[
        {
            "category":"Health Services",
            "subcategory":"Doctor",
            "type":"Services"
        }
    ],
    "sg:phone":"+1 250 992 2511",
    "sg:postcode":"V2J 2K8",
    "sg:province":"BC",
    "sg:tags":[
        "dentist"
    ],
    "wof:name":"Wood, T A DDS",
    "wof:placetype":"venue"
},
  "geometry": {"coordinates":[-122.49885559099999,52.9835777283],"type":"Point"}
}