{
  "type": "Feature",
  "properties": {
    "addr:full":"1127 4E Av Thetford Mines QC G6G 2Z6",
    "addr:housenumber":"1127",
    "addr:postcode":"g6g 2z6",
    "addr:street":"4E Av",
    "iso:country":"CA",
    "sg:address":"1127 4E Av",
    "sg:city":"Thetford Mines",
    "sg:classifiers":[
        {
            "category":"Building & Trades",
            "subcategory":"Construction",
            "type":"Services"
        }
    ],
    "sg:phone":"+1 418 335 5624",
    "sg:postcode":"G6G 2Z6",
    "sg:province":"QC",
    "sg:tags":[
        "cleaners",
        "carpet",
        "steam",
        "rug"
    ],
    "wof:name":"Jac-Net",
    "wof:placetype":"venue"
},
  "geometry": {"coordinates":[-71.280998,46.10202],"type":"Point"}
}