{
  "type": "Feature",
  "properties": {
    "addr:full":"25 Butterfield Rd Munster ON K0A 3P0",
    "addr:housenumber":"25",
    "addr:postcode":"k0a 3p0",
    "addr:street":"Butterfield Rd",
    "iso:country":"CA",
    "sg:address":"25 Butterfield Rd",
    "sg:city":"Munster",
    "sg:classifiers":[
        {
            "category":"Building & Trades",
            "subcategory":"Construction",
            "type":"Services"
        }
    ],
    "sg:phone":"+1 613 838 3728",
    "sg:postcode":"K0A 3P0",
    "sg:province":"ON",
    "sg:tags":[
        "elevator"
    ],
    "wof:name":"Cbm Elevators Ltd",
    "wof:placetype":"venue"
},
  "geometry": {"coordinates":[-75.93994903559999,45.1689414978],"type":"Point"}
}