{
  "type": "Feature",
  "properties": {
    "addr:full":"200 Broadway St Tillsonburg ON N4G 5A7",
    "addr:housenumber":"200",
    "addr:postcode":"n4g 5a7",
    "addr:street":"Broadway St",
    "iso:country":"CA",
    "sg:address":"200 Broadway St",
    "sg:city":"Tillsonburg",
    "sg:classifiers":[
        {
            "category":"Utilities",
            "subcategory":"Mobile Phone",
            "type":"Services"
        }
    ],
    "sg:phone":"+1 519 842 8811",
    "sg:postcode":"N4G 5A7",
    "sg:province":"ON",
    "sg:tags":[
        "telephone",
        "cellular"
    ],
    "wof:name":"Advanced Cellular",
    "wof:placetype":"venue"
},
  "geometry": {"coordinates":[-80.729164,42.862103],"type":"Point"}
}