{
  "type": "Feature",
  "properties": {
    "iso:country":"CA",
    "sg:address":"83 Rue King O",
    "sg:city":"Sherbrooke",
    "sg:classifiers":[
        {
            "category":"Shopping",
            "subcategory":"Clothing, Apparel, & Fashions",
            "type":"Retail Goods"
        }
    ],
    "sg:phone":"+1 819 564 7746",
    "sg:postcode":"J1H 1P1",
    "sg:province":"QC",
    "sg:tags":[
        "item",
        "boutique"
    ],
    "wof:name":"Rock",
    "wof:placetype":"venue"
},
  "geometry": {"coordinates":[-71.88543701170001,45.4040107727],"type":"Point"}
}