{
  "type": "Feature",
  "properties": {
    "iso:country":"CA",
    "sg:address":"80 Bloor St W",
    "sg:city":"Toronto",
    "sg:classifiers":[
        {
            "category":"Organizations",
            "subcategory":"Professional Association",
            "type":"Services"
        }
    ],
    "sg:phone":"+1 416 960 2434",
    "sg:postcode":"M5S 2V1",
    "sg:province":"ON",
    "sg:tags":[
        "program",
        "physical",
        "exercise",
        "fitness"
    ],
    "wof:name":"Bally Total Fitness",
    "wof:placetype":"venue"
},
  "geometry": {"coordinates":[-79.3904037476,43.6696090698],"type":"Point"}
}