{
  "type": "Feature",
  "properties": {
    "addr:full":"230 Boul DE L'Aeroport Gatineau QC J8P 7G7",
    "addr:housenumber":"230",
    "addr:postcode":"j8p 7g7",
    "addr:street":"Boul De L'Aeroport",
    "iso:country":"CA",
    "sg:address":"230 Boul DE L'Aeroport",
    "sg:city":"Gatineau",
    "sg:classifiers":[
        {
            "category":"Home & Garden",
            "subcategory":"Carpets & Floor Coverings",
            "type":"Retail Goods"
        }
    ],
    "sg:phone":"+1 819 663 2811",
    "sg:postcode":"J8P 7G7",
    "sg:province":"QC",
    "sg:tags":[
        "material"
    ],
    "wof:name":"Insulfloor Inc",
    "wof:placetype":"venue"
},
  "geometry": {"coordinates":[-75.71050262449999,45.4278488159],"type":"Point"}
}