{
  "type": "Feature",
  "properties": {
    "iso:country":"CA",
    "sg:address":"2191 16th Line",
    "sg:city":"Lakefield",
    "sg:classifiers":[
        {
            "category":"Food & Beverages",
            "subcategory":"Fruits & Vegetables",
            "type":"Retail Goods"
        }
    ],
    "sg:phone":"+1 705 657 2134",
    "sg:postcode":"K0L 2H0",
    "sg:province":"ON",
    "sg:tags":[
        "produce"
    ],
    "wof:name":"Mc Lean Berry Farm",
    "wof:placetype":"venue"
},
  "geometry": {"coordinates":[-78.2727813721,44.4225082397],"type":"Point"}
}