{
  "type": "Feature",
  "properties": {
    "addr:full":"64 Main St Cobden ON K0J 1K0",
    "addr:housenumber":"64",
    "addr:postcode":"k0j 1k0",
    "addr:street":"Main St",
    "iso:country":"CA",
    "sg:address":"64 Main St",
    "sg:city":"Cobden",
    "sg:classifiers":[
        {
            "category":"Shopping",
            "type":"Retail Goods"
        }
    ],
    "sg:phone":"+1 613 646 2275",
    "sg:postcode":"K0J 1K0",
    "sg:province":"ON",
    "sg:tags":[
        "monument"
    ],
    "wof:name":"Yolkowski Monuments Ltd",
    "wof:placetype":"venue"
},
  "geometry": {"coordinates":[-76.88632200000001,45.626549],"type":"Point"}
}