{
  "type": "Feature",
  "properties": {
    "addr:full":"Cheneville QC J0V 1E0",
    "addr:postcode":"j0v 1e0",
    "iso:country":"CA",
    "sg:city":"Cheneville",
    "sg:classifiers":[
        {
            "category":"Health Services",
            "subcategory":"Doctor",
            "type":"Services"
        }
    ],
    "sg:phone":"+1 819 428 1222",
    "sg:postcode":"J0V 1E0",
    "sg:province":"QC",
    "sg:tags":[
        "clinic"
    ],
    "wof:name":"Clinique Medicale-Cheneville",
    "wof:placetype":"venue"
},
  "geometry": {"coordinates":[-75.054794,45.883366],"type":"Point"}
}