{
  "type": "Feature",
  "properties": {
    "addr:full":"916 Alpine Ave 100 Mile House BC V0K 2E0",
    "addr:housenumber":"916",
    "addr:postcode":"v0k 2e0",
    "addr:street":"Alpine Ave",
    "iso:country":"CA",
    "sg:address":"916 Alpine Ave",
    "sg:city":"100 Mile House",
    "sg:classifiers":[
        {
            "category":"Wholesale",
            "subcategory":"Electrical",
            "type":"Manufacturing & Wholesale Goods"
        }
    ],
    "sg:phone":"+1 250 395 4015",
    "sg:postcode":"V0K 2E0",
    "sg:province":"BC",
    "sg:tags":[
        "communication",
        "radio",
        "system"
    ],
    "wof:name":"Ksm Communications Ltd",
    "wof:placetype":"venue"
},
  "geometry": {"coordinates":[-121.301002502,51.6309623718],"type":"Point"}
}