{
  "type": "Feature",
  "properties": {
    "addr:full":"289 Daimler Pky Welland ON L3B 6H2",
    "addr:housenumber":"289",
    "addr:postcode":"l3b 6h2",
    "addr:street":"Daimler Pky",
    "iso:country":"CA",
    "sg:address":"289 Daimler Pky",
    "sg:city":"Welland",
    "sg:classifiers":[
        {
            "category":"Sports & Exercise",
            "subcategory":"Golf",
            "type":"Entertainment"
        }
    ],
    "sg:phone":"+1 905 714 4659",
    "sg:postcode":"L3B 6H2",
    "sg:province":"ON",
    "sg:tags":[
        "course"
    ],
    "wof:name":"Hunters Pointe Golf Course",
    "wof:placetype":"venue"
},
  "geometry": {"coordinates":[-79.218407,43.020798],"type":"Point"}
}