{
  "type": "Feature",
  "properties": {
    "addr:full":"12122 68 St NW Edmonton AB T5B 1R1",
    "addr:housenumber":"12122",
    "addr:postcode":"t5b 1r1",
    "addr:street":"68 St Nw",
    "iso:country":"CA",
    "sg:address":"12122 68 St NW",
    "sg:city":"Edmonton",
    "sg:classifiers":[
        {
            "category":"Wholesale",
            "subcategory":"Machinery & Supplies",
            "type":"Manufacturing & Wholesale Goods"
        }
    ],
    "sg:phone":"+1 780 474 5414",
    "sg:postcode":"T5B 1R1",
    "sg:province":"AB",
    "sg:tags":[
        "upholsterer"
    ],
    "wof:name":"J Ennis Fabrics Ltd",
    "wof:placetype":"venue"
},
  "geometry": {"coordinates":[-113.44704400000001,53.57605],"type":"Point"}
}