{
  "type": "Feature",
  "properties": {
    "addr:full":"Richmond BC V6V 1Y1",
    "addr:postcode":"v6v 1y1",
    "iso:country":"CA",
    "sg:city":"Richmond",
    "sg:classifiers":[
        {
            "category":"Wholesale",
            "subcategory":"Machinery & Supplies",
            "type":"Manufacturing & Wholesale Goods"
        }
    ],
    "sg:phone":"+1 604 244 8005",
    "sg:postcode":"V6V 1Y1",
    "sg:province":"BC",
    "sg:tags":[
        "asbestos",
        "equipment",
        "safety",
        "clothing",
        "removal"
    ],
    "wof:name":"Safety Express",
    "wof:placetype":"venue"
},
  "geometry": {"coordinates":[-123.07343292199999,49.1922950745],"type":"Point"}
}