{
  "type": "Feature",
  "properties": {
    "addr:full":"227 Main St Beardmore ON P0T 1G0",
    "addr:housenumber":"227",
    "addr:postcode":"p0t 1g0",
    "addr:street":"Main St",
    "iso:country":"CA",
    "sg:address":"227 Main St",
    "sg:city":"Beardmore",
    "sg:classifiers":[
        {
            "category":"Travel",
            "subcategory":"Hotels & Motels",
            "type":"Entertainment"
        }
    ],
    "sg:phone":"+1 807 875 1037",
    "sg:postcode":"P0T 1G0",
    "sg:province":"ON",
    "wof:name":"Roxy Place Motel",
    "wof:placetype":"venue"
},
  "geometry": {"coordinates":[-87.958977,49.601894],"type":"Point"}
}