{
  "type": "Feature",
  "properties": {
    "addr:full":"15 2E Av Forestville QC G0T 1E0",
    "addr:housenumber":"15",
    "addr:postcode":"g0t 1e0",
    "addr:street":"2E Av",
    "iso:country":"CA",
    "sg:address":"15 2E Av",
    "sg:city":"Forestville",
    "sg:classifiers":[
        {
            "category":"Home & Garden",
            "subcategory":"Furniture",
            "type":"Retail Goods"
        }
    ],
    "sg:phone":"+1 418 587 6628",
    "sg:postcode":"G0T 1E0",
    "sg:province":"QC",
    "wof:name":"Decoration Vickie Inc",
    "wof:placetype":"venue"
},
  "geometry": {"coordinates":[-69.079041,48.738663],"type":"Point"}
}