{
  "type": "Feature",
  "properties": {
    "addr:full":"Paspebiac QC G0C 2K0",
    "addr:postcode":"g0c 2k0",
    "iso:country":"CA",
    "sg:city":"Paspebiac",
    "sg:classifiers":[
        {
            "category":"Food & Beverages",
            "subcategory":"Groceries & Convenience Stores",
            "type":"Retail Goods"
        }
    ],
    "sg:phone":"+1 418 752 6987",
    "sg:postcode":"G0C 2K0",
    "sg:province":"QC",
    "wof:name":"Alimentation Couche-Tard",
    "wof:placetype":"venue"
},
  "geometry": {"coordinates":[-65.244095,48.03006],"type":"Point"}
}