{
  "type": "Feature",
  "properties": {
    "addr:full":"North Bay ON P1B 8G3",
    "addr:postcode":"p1b 8g3",
    "iso:country":"CA",
    "sg:city":"North Bay",
    "sg:classifiers":[
        {
            "category":"Freight",
            "type":"Transportation"
        }
    ],
    "sg:phone":"+1 705 840 8532",
    "sg:postcode":"P1B 8G3",
    "sg:province":"ON",
    "sg:tags":[
        "courier"
    ],
    "wof:name":"Tims Delivery",
    "wof:placetype":"venue"
},
  "geometry": {"coordinates":[-79.4339065552,46.3069534302],"type":"Point"}
}