{
  "type": "Feature",
  "properties": {
    "addr:full":"138 Veronica Dr North Bay ON P1B 9K6",
    "addr:housenumber":"138",
    "addr:postcode":"p1b 9k6",
    "addr:street":"Veronica Dr",
    "iso:country":"CA",
    "sg:address":"138 Veronica Dr",
    "sg:city":"North Bay",
    "sg:classifiers":[
        {
            "category":"Building & Trades",
            "subcategory":"Construction",
            "type":"Services"
        }
    ],
    "sg:phone":"+1 705 474 8963",
    "sg:postcode":"P1B 9K6",
    "sg:province":"ON",
    "sg:tags":[
        "contractor"
    ],
    "wof:name":"Di Bart Builders",
    "wof:placetype":"venue"
},
  "geometry": {"coordinates":[-79.43367004389999,46.3183784485],"type":"Point"}
}