{
  "type": "Feature",
  "properties": {
    "iso:country":"CA",
    "sg:address":"888 Rue Soulanges",
    "sg:city":"Repentigny",
    "sg:classifiers":[
        {
            "category":"Professional",
            "subcategory":"Lawyer & Legal Services",
            "type":"Services"
        }
    ],
    "sg:phone":"+1 450 654 3378",
    "sg:postcode":"J5Y 2A8",
    "sg:province":"QC",
    "sg:tags":[
        "attorney"
    ],
    "wof:name":"Forest, Gilles",
    "wof:placetype":"venue"
},
  "geometry": {"coordinates":[-73.432487,45.771259],"type":"Point"}
}