{
  "type": "Feature",
  "properties": {
    "addr:full":"888 Rue Soulanges Repentigny QC J5Y 2A8",
    "addr:housenumber":"888",
    "addr:postcode":"j5y 2a8",
    "addr:street":"Rue Soulanges",
    "iso:country":"CA",
    "sg:address":"888 Rue Soulanges",
    "sg:city":"Repentigny",
    "sg:classifiers":[
        {
            "category":"Professional",
            "subcategory":"Lawyer & Legal Services",
            "type":"Services"
        }
    ],
    "sg:phone":"+1 450 654 3378",
    "sg:postcode":"J5Y 2A8",
    "sg:province":"QC",
    "sg:tags":[
        "attorney"
    ],
    "wof:name":"Forest, Gilles",
    "wof:placetype":"venue"
},
  "geometry": {"coordinates":[-73.43248699999999,45.771259],"type":"Point"}
}