{
  "type": "Feature",
  "properties": {
    "addr:full":"5414 Argyle St Port Alberni BC V9Y 1T7",
    "addr:housenumber":"5414",
    "addr:postcode":"v9y 1t7",
    "addr:street":"Argyle St",
    "iso:country":"CA",
    "sg:address":"5414 Argyle St",
    "sg:city":"Port Alberni",
    "sg:classifiers":[
        {
            "category":"Professional",
            "subcategory":"Detective & Security Services",
            "type":"Services"
        }
    ],
    "sg:phone":"+1 250 724 0732",
    "sg:postcode":"V9Y 1T7",
    "sg:province":"BC",
    "sg:tags":[
        "guard",
        "patrol"
    ],
    "wof:name":"Quay Security Patrol",
    "wof:placetype":"venue"
},
  "geometry": {"coordinates":[-124.81364440900001,49.2345123291],"type":"Point"}
}