{
  "type": "Feature",
  "properties": {
    "addr:full":"Princeton BC V0X 1W0",
    "addr:postcode":"v0x 1w0",
    "iso:country":"CA",
    "sg:city":"Princeton",
    "sg:classifiers":[
        {
            "category":"Shopping",
            "subcategory":"Gifts & Souvenirs",
            "type":"Retail Goods"
        }
    ],
    "sg:phone":"+1 250 295 0404",
    "sg:postcode":"V0X 1W0",
    "sg:province":"BC",
    "sg:tags":[
        "shop"
    ],
    "wof:name":"Your Dollar Store With More",
    "wof:placetype":"venue"
},
  "geometry": {"coordinates":[-120.506989,49.458138],"type":"Point"}
}