{
  "type": "Feature",
  "properties": {
    "addr:full":"2606 Lakeshore Rd Vernon BC V1H 1N1",
    "addr:housenumber":"2606",
    "addr:postcode":"v1h 1n1",
    "addr:street":"Lakeshore Rd",
    "iso:country":"CA",
    "sg:address":"2606 Lakeshore Rd",
    "sg:city":"Vernon",
    "sg:classifiers":[
        {
            "category":"Building & Trades",
            "subcategory":"Construction",
            "type":"Services"
        }
    ],
    "sg:phone":"+1 250 549 3663",
    "sg:postcode":"V1H 1N1",
    "sg:province":"BC",
    "sg:tags":[
        "builder",
        "patio",
        "deck"
    ],
    "wof:name":"Valley Vinyl Decking",
    "wof:placetype":"venue"
},
  "geometry": {"coordinates":[-119.34300994900001,50.2424468994],"type":"Point"}
}