{
  "type": "Feature",
  "properties": {
    "addr:full":"Sussex NB E4E 3E1",
    "addr:postcode":"e4e 3e1",
    "iso:country":"CA",
    "sg:city":"Sussex",
    "sg:classifiers":[
        {
            "category":"Shopping",
            "subcategory":"Clothing, Apparel, & Fashions",
            "type":"Retail Goods"
        }
    ],
    "sg:phone":"+1 506 432 6244",
    "sg:postcode":"E4E 3E1",
    "sg:province":"NB",
    "wof:name":"Reitmans",
    "wof:placetype":"venue"
},
  "geometry": {"coordinates":[-65.52619199999999,45.724747],"type":"Point"}
}