{
  "type": "Feature",
  "properties": {
    "addr:full":"47 Lansdowne Ave Carleton Place ON K7C 3S9",
    "addr:housenumber":"47",
    "addr:postcode":"k7c 3s9",
    "addr:street":"Lansdowne Ave",
    "iso:country":"CA",
    "sg:address":"47 Lansdowne Ave",
    "sg:city":"Carleton Place",
    "sg:classifiers":[
        {
            "category":"Government",
            "subcategory":"Post Office",
            "type":"Public Place"
        }
    ],
    "sg:phone":"+1 613 257 1414",
    "sg:postcode":"K7C 3S9",
    "sg:province":"ON",
    "sg:tags":[
        "pharmacy"
    ],
    "wof:name":"Ida Drug Mart",
    "wof:placetype":"venue"
},
  "geometry": {"coordinates":[-76.1402511597,45.1355323792],"type":"Point"}
}