{
  "type": "Feature",
  "properties": {
    "iso:country":"CA",
    "sg:address":"60 Shorting Rd",
    "sg:city":"Scarborough",
    "sg:classifiers":[
        {
            "category":"Shopping",
            "subcategory":"Pharmacy",
            "type":"Retail Goods"
        }
    ],
    "sg:phone":"+1 416 298 8500",
    "sg:postcode":"M1S 3S3",
    "sg:province":"ON",
    "wof:name":"Ontario Ostomy Supply",
    "wof:placetype":"venue"
},
  "geometry": {"coordinates":[-79.25012207029999,43.7940444946],"type":"Point"}
}