{
  "type": "Feature",
  "properties": {
    "iso:country":"CA",
    "sg:city":"Saint-Romuald",
    "sg:classifiers":[
        {
            "category":"Insurance",
            "subcategory":"Insurance Agent",
            "type":"Services"
        }
    ],
    "sg:phone":"+1 418 839 1341",
    "sg:postcode":"G6W 5M6",
    "sg:province":"QC",
    "wof:name":"Promutuel",
    "wof:placetype":"venue"
},
  "geometry": {"coordinates":[-71.240089,46.758121],"type":"Point"}
}