{
  "type": "Feature",
  "properties": {
    "addr:full":"Gatineau QC J8P 2K7",
    "addr:postcode":"j8p 2k7",
    "iso:country":"CA",
    "sg:city":"Gatineau",
    "sg:classifiers":[
        {
            "category":"Building & Trades",
            "subcategory":"Cleaning & Sanitation",
            "type":"Services"
        }
    ],
    "sg:phone":"+1 819 643 1179",
    "sg:postcode":"J8P 2K7",
    "sg:province":"QC",
    "sg:tags":[
        "janitor"
    ],
    "wof:name":"Entretien Menager Vs",
    "wof:placetype":"venue"
},
  "geometry": {"coordinates":[-75.6094284058,45.4780311584],"type":"Point"}
}