{
  "type": "Feature",
  "properties": {
    "addr:full":"1880 Tuscarora Rd Ohsweken ON N0A 1M0",
    "addr:housenumber":"1880",
    "addr:postcode":"n0a 1m0",
    "addr:street":"Tuscarora Rd",
    "iso:country":"CA",
    "sg:address":"1880 Tuscarora Rd",
    "sg:city":"Ohsweken",
    "sg:classifiers":[
        {
            "category":"Shopping",
            "subcategory":"Gifts & Souvenirs",
            "type":"Retail Goods"
        }
    ],
    "sg:phone":"+1 519 445 0414",
    "sg:postcode":"N0A 1M0",
    "sg:province":"ON",
    "sg:tags":[
        "shop"
    ],
    "wof:name":"Iroqrafts",
    "wof:placetype":"venue"
},
  "geometry": {"coordinates":[-80.11879730219999,43.0690460205],"type":"Point"}
}