{
  "type": "Feature",
  "properties": {
    "addr:full":"203 Rue Saint-Edmond Rimouski QC G5L 3K1",
    "addr:housenumber":"203",
    "addr:postcode":"g5l 3k1",
    "addr:street":"Rue Saint-Edmond",
    "iso:country":"CA",
    "sg:address":"203 Rue Saint-Edmond",
    "sg:city":"Rimouski",
    "sg:classifiers":[
        {
            "category":"Health Services",
            "subcategory":"Health Practitioner",
            "type":"Services"
        }
    ],
    "sg:phone":"+1 418 722 0614",
    "sg:postcode":"G5L 3K1",
    "sg:province":"QC",
    "sg:tags":[
        "psychologist"
    ],
    "wof:name":"Laroche, Pierrette",
    "wof:placetype":"venue"
},
  "geometry": {"coordinates":[-68.524269,48.450123],"type":"Point"}
}