{
  "type": "Feature",
  "properties": {
    "addr:full":"Leduc AB T9E 6J6",
    "addr:postcode":"t9e 6j6",
    "iso:country":"CA",
    "sg:city":"Leduc",
    "sg:classifiers":[
        {
            "category":"Recreation",
            "type":"Entertainment"
        }
    ],
    "sg:phone":"+1 780 986 2112",
    "sg:postcode":"T9E 6J6",
    "sg:province":"AB",
    "sg:tags":[
        "bingo",
        "game"
    ],
    "wof:name":"Rapid Bingo Hall",
    "wof:placetype":"venue"
},
  "geometry": {"coordinates":[-113.550583,53.272896],"type":"Point"}
}