{
  "type": "Feature",
  "properties": {
    "addr:full":"1512 Duranleau St Vancouver BC V6H 3S4",
    "addr:housenumber":"1512",
    "addr:postcode":"v6h 3s4",
    "addr:street":"Duranleau St",
    "iso:country":"CA",
    "sg:address":"1512 Duranleau St",
    "sg:city":"Vancouver",
    "sg:classifiers":[
        {
            "category":"Shopping",
            "subcategory":"Bicycles & Sporting Goods",
            "type":"Retail Goods"
        }
    ],
    "sg:phone":"+1 604 669 3483",
    "sg:postcode":"V6H 3S4",
    "sg:province":"BC",
    "sg:tags":[
        "equipment",
        "diver",
        "supply"
    ],
    "wof:name":"Rowand's Reef Scuba Shop Ltd",
    "wof:placetype":"venue"
},
  "geometry": {"coordinates":[-123.136054993,49.2707328796],"type":"Point"}
}