{
  "type": "Feature",
  "properties": {
    "addr:full":"5004 52 St Whitecourt AB T7S 1N2",
    "addr:housenumber":"5004",
    "addr:postcode":"t7s 1n2",
    "addr:street":"52 St",
    "iso:country":"CA",
    "sg:address":"5004 52 St",
    "sg:city":"Whitecourt",
    "sg:classifiers":[
        {
            "category":"Wholesale",
            "subcategory":"Construction Materials",
            "type":"Manufacturing & Wholesale Goods"
        }
    ],
    "sg:phone":"+1 780 778 2221",
    "sg:postcode":"T7S 1N2",
    "sg:province":"AB",
    "sg:tags":[
        "lumber"
    ],
    "wof:name":"Millar Western Forest Products",
    "wof:placetype":"venue"
},
  "geometry": {"coordinates":[-115.689086914,54.1416893005],"type":"Point"}
}