{
  "type": "Feature",
  "properties": {
    "addr:full":"Calgary AB T2E 7S8",
    "addr:postcode":"t2e 7s8",
    "iso:country":"CA",
    "sg:city":"Calgary",
    "sg:classifiers":[
        {
            "category":"Shopping",
            "subcategory":"Musical Instruments",
            "type":"Retail Goods"
        }
    ],
    "sg:phone":"+1 403 291 2346",
    "sg:postcode":"T2E 7S8",
    "sg:province":"AB",
    "sg:tags":[
        "instruction",
        "music",
        "dealer"
    ],
    "wof:name":"United Conservatory of Music",
    "wof:placetype":"venue"
},
  "geometry": {"coordinates":[-114.029915,51.080025],"type":"Point"}
}