{
  "type": "Feature",
  "properties": {
    "addr:full":"5208 82 Ave NW Edmonton AB T6B 0E6",
    "addr:housenumber":"5208",
    "addr:postcode":"t6b 0e6",
    "addr:street":"82 Ave Nw",
    "iso:country":"CA",
    "sg:address":"5208 82 Ave NW",
    "sg:city":"Edmonton",
    "sg:classifiers":[
        {
            "category":"Building & Trades",
            "subcategory":"Cleaning & Sanitation",
            "type":"Services"
        }
    ],
    "sg:phone":"+1 780 440 9770",
    "sg:postcode":"T6B 0E6",
    "sg:province":"AB",
    "sg:tags":[
        "cleaners",
        "janitor",
        "rug",
        "carpet"
    ],
    "wof:name":"Necula White Glove Svc Inc",
    "wof:placetype":"venue"
},
  "geometry": {"coordinates":[-113.420188904,53.5181655884],"type":"Point"}
}