{
  "type": "Feature",
  "properties": {
    "addr:full":"324 221 Rte Lacolle QC J0J 1J0",
    "addr:housenumber":"221",
    "addr:postcode":"j0j 1j0",
    "addr:street":"Rte Lacolle",
    "iso:country":"CA",
    "sg:address":"324 221 Rte",
    "sg:city":"Lacolle",
    "sg:classifiers":[
        {
            "category":"Wholesale",
            "subcategory":"Machinery & Supplies",
            "type":"Manufacturing & Wholesale Goods"
        }
    ],
    "sg:phone":"+1 450 246 2845",
    "sg:postcode":"J0J 1J0",
    "sg:province":"QC",
    "wof:name":"Machineries Brunet",
    "wof:placetype":"venue"
},
  "geometry": {"coordinates":[-73.3729019165,45.0824737549],"type":"Point"}
}