{
  "type": "Feature",
  "properties": {
    "addr:full":"25 Beasley Dr Kitchener ON N2E 1W7",
    "addr:housenumber":"25",
    "addr:postcode":"n2e 1w7",
    "addr:street":"Beasley Dr",
    "iso:country":"CA",
    "sg:address":"25 Beasley Dr",
    "sg:city":"Kitchener",
    "sg:classifiers":[
        {
            "category":"Wholesale",
            "subcategory":"Machinery & Supplies",
            "type":"Manufacturing & Wholesale Goods"
        }
    ],
    "sg:phone":"+1 519 763 3434",
    "sg:postcode":"N2E 1W7",
    "sg:province":"ON",
    "sg:tags":[
        "truck"
    ],
    "wof:name":"J H Ryder Machinery Ltd",
    "wof:placetype":"venue"
},
  "geometry": {"coordinates":[-80.45775604249999,43.4017562866],"type":"Point"}
}