{
  "type": "Feature",
  "properties": {
    "addr:full":"Victoria BC V8T 5C5",
    "addr:postcode":"v8t 5c5",
    "iso:country":"CA",
    "sg:city":"Victoria",
    "sg:classifiers":[
        {
            "category":"Autos & Motor Vehicles",
            "subcategory":"Auto Supplies",
            "type":"Retail Goods"
        }
    ],
    "sg:phone":"+1 250 383 0101",
    "sg:postcode":"V8T 5C5",
    "sg:province":"BC",
    "sg:tags":[
        "alternator",
        "automobile",
        "parts",
        "starter"
    ],
    "wof:name":"Mac's Auto Electric",
    "wof:placetype":"venue"
},
  "geometry": {"coordinates":[-123.373718262,48.43724823],"type":"Point"}
}