{
  "type": "Feature",
  "properties": {
    "addr:full":"Burlington ON L7S 1W6",
    "addr:postcode":"l7s 1w6",
    "iso:country":"CA",
    "sg:city":"Burlington",
    "sg:classifiers":[
        {
            "category":"Retail",
            "subcategory":"Auto Repair",
            "type":"Services"
        }
    ],
    "sg:phone":"+1 905 634 9313",
    "sg:postcode":"L7S 1W6",
    "sg:province":"ON",
    "sg:tags":[
        "repairing",
        "automobile"
    ],
    "wof:name":"Burlington Alignment Svc",
    "wof:placetype":"venue"
},
  "geometry": {"coordinates":[-79.82172393800001,43.3327941895],"type":"Point"}
}