{
  "type": "Feature",
  "properties": {
    "addr:full":"217 Front St Duck Lake SK S0K 1J0",
    "addr:housenumber":"217",
    "addr:postcode":"s0k 1j0",
    "addr:street":"Front St Duck Lake",
    "iso:country":"CA",
    "sg:address":"217 Front St",
    "sg:city":"Duck Lake",
    "sg:classifiers":[
        {
            "category":"Home & Garden",
            "subcategory":"Building Materials",
            "type":"Retail Goods"
        }
    ],
    "sg:phone":"+1 306 467 4408",
    "sg:postcode":"S0K 1J0",
    "sg:province":"SK",
    "sg:tags":[
        "lumber"
    ],
    "wof:name":"D & H Lumber",
    "wof:placetype":"venue"
},
  "geometry": {"coordinates":[-106.224205,52.809196],"type":"Point"}
}