{
  "type": "Feature",
  "properties": {
    "addr:full":"PO Box 5 Sinclair MB R0M 2A0",
    "addr:housenumber":"po;5",
    "addr:postcode":"r0m 2a0",
    "addr:street":"Box",
    "iso:country":"CA",
    "sg:address":"PO Box 5",
    "sg:city":"Sinclair",
    "sg:classifiers":[
        {
            "category":"Education",
            "subcategory":"School",
            "type":"Public Place"
        }
    ],
    "sg:phone":"+1 204 662 4431",
    "sg:postcode":"R0M 2A0",
    "sg:province":"MB",
    "wof:name":"Stony Creek School",
    "wof:placetype":"venue"
},
  "geometry": {"coordinates":[-101.292816,49.569382],"type":"Point"}
}