{
  "type": "Feature",
  "properties": {
    "iso:country":"CA",
    "sg:city":"Richmond",
    "sg:classifiers":[
        {
            "category":"Farming",
            "subcategory":"Farm",
            "type":"Manufacturing & Wholesale Goods"
        }
    ],
    "sg:phone":"+1 604 273 8299",
    "sg:postcode":"V6V 1Y1",
    "sg:province":"BC",
    "sg:tags":[
        "mushroom"
    ],
    "wof:name":"Misty Mountain Industries Ltd",
    "wof:placetype":"venue"
},
  "geometry": {"coordinates":[-123.07343292199999,49.1922950745],"type":"Point"}
}