{
  "type": "Feature",
  "properties": {
    "iso:country":"CA",
    "sg:city":"Hamilton",
    "sg:classifiers":[
        {
            "category":"Professional",
            "subcategory":"Engineering",
            "type":"Services"
        }
    ],
    "sg:phone":"+1 905 525 6957",
    "sg:postcode":"L8P 4Z2",
    "sg:province":"ON",
    "sg:tags":[
        "engineer"
    ],
    "wof:name":"Warren Works Lighting",
    "wof:placetype":"venue"
},
  "geometry": {"coordinates":[-79.9035873413,43.2512893677],"type":"Point"}
}