{
  "type": "Feature",
  "properties": {
    "iso:country":"CA",
    "sg:address":"2 Rang 2 Ctr",
    "sg:city":"Trois-Pistoles",
    "sg:classifiers":[
        {
            "category":"Government",
            "subcategory":"Office",
            "type":"Public Place"
        }
    ],
    "sg:phone":"+1 418 851 2518",
    "sg:postcode":"G0L 4K0",
    "sg:province":"QC",
    "sg:tags":[
        "village"
    ],
    "wof:name":"Notre-Dame Des Neiges Garage",
    "wof:placetype":"venue"
},
  "geometry": {"coordinates":[-69.17487335209999,48.1250190735],"type":"Point"}
}