{
  "type": "Feature",
  "properties": {
    "addr:full":"6265 Thorold Stone Rd Niagara Falls ON L2J 1A6",
    "addr:housenumber":"6265",
    "addr:postcode":"l2j 1a6",
    "addr:street":"Thorold Stone Rd",
    "iso:country":"CA",
    "sg:address":"6265 Thorold Stone Rd",
    "sg:city":"Niagara Falls",
    "sg:classifiers":[
        {
            "category":"Restaurant",
            "type":"Food & Drink"
        }
    ],
    "sg:phone":"+1 905 354 7888",
    "sg:postcode":"L2J 1A6",
    "sg:province":"ON",
    "sg:tags":[
        "sandwich"
    ],
    "wof:name":"Sub Junction",
    "wof:placetype":"venue"
},
  "geometry": {"coordinates":[-79.09992200000001,43.115368],"type":"Point"}
}