{
  "type": "Feature",
  "properties": {
    "iso:country":"CA",
    "sg:city":"Maple Ridge",
    "sg:classifiers":[
        {
            "category":"Recreation",
            "type":"Entertainment"
        }
    ],
    "sg:phone":"+1 604 463 7612",
    "sg:postcode":"V2X 8R9",
    "sg:province":"BC",
    "sg:tags":[
        "lottery",
        "agent"
    ],
    "wof:name":"Haney Place Lottery",
    "wof:placetype":"venue"
},
  "geometry": {"coordinates":[-122.601517,49.218918],"type":"Point"}
}