{
  "type": "Feature",
  "properties": {
    "addr:full":"4801 26 Ave NE Calgary AB T1Y 3E1",
    "addr:housenumber":"4801",
    "addr:postcode":"t1y 3e1",
    "addr:street":"26 Ave Ne",
    "iso:country":"CA",
    "sg:address":"4801 26 Ave NE",
    "sg:city":"Calgary",
    "sg:classifiers":[
        {
            "category":"Restaurant",
            "type":"Food & Drink"
        }
    ],
    "sg:phone":"+1 403 285 5116",
    "sg:postcode":"T1Y 3E1",
    "sg:province":"AB",
    "sg:tags":[
        "pizza"
    ],
    "wof:name":"Cal Pizza",
    "wof:placetype":"venue"
},
  "geometry": {"coordinates":[-113.96597300000001,51.077183],"type":"Point"}
}