{
  "type": "Feature",
  "properties": {
    "addr:full":"909 High St W Moose Jaw SK S6H 7P7",
    "addr:housenumber":"909",
    "addr:postcode":"s6h 7p7",
    "addr:street":"High St W",
    "iso:country":"CA",
    "sg:address":"909 High St W",
    "sg:city":"Moose Jaw",
    "sg:classifiers":[
        {
            "category":"Building & Trades",
            "subcategory":"Construction",
            "type":"Services"
        }
    ],
    "sg:phone":"+1 306 693 3924",
    "sg:postcode":"S6H 7P7",
    "sg:province":"SK",
    "sg:tags":[
        "painter"
    ],
    "wof:name":"Adam's Painting & Decorating",
    "wof:placetype":"venue"
},
  "geometry": {"coordinates":[-105.558556,50.391216],"type":"Point"}
}