{
  "type": "Feature",
  "properties": {
    "iso:country":"CA",
    "sg:city":"Hamilton",
    "sg:classifiers":[
        {
            "category":"Health Services",
            "subcategory":"Doctor",
            "type":"Services"
        }
    ],
    "sg:phone":"+1 905 385 9654",
    "sg:postcode":"L8V 1C1",
    "sg:province":"ON",
    "sg:tags":[
        "dentist"
    ],
    "wof:name":"Dinniwell, Edward R DDS",
    "wof:placetype":"venue"
},
  "geometry": {"coordinates":[-79.844833,43.238998],"type":"Point"}
}