{
  "type": "Feature",
  "properties": {
    "addr:full":"149 Boul Notre-Dame Clermont QC G4A 1E7",
    "addr:housenumber":"149",
    "addr:postcode":"g4a 1e7",
    "addr:street":"Boul Notre-Dame",
    "iso:country":"CA",
    "sg:address":"149 Boul Notre-Dame",
    "sg:city":"Clermont",
    "sg:classifiers":[
        {
            "category":"Banks & Credit Unions",
            "subcategory":"Bank",
            "type":"Services"
        }
    ],
    "sg:phone":"+1 418 439 3982",
    "sg:postcode":"G4A 1E7",
    "sg:province":"QC",
    "wof:name":"Caisse Desjardins",
    "wof:placetype":"venue"
},
  "geometry": {"coordinates":[-70.2287826538,47.6913604736],"type":"Point"}
}