{
  "type": "Feature",
  "properties": {
    "addr:full":"Vancouver BC V6P 4J6",
    "addr:postcode":"v6p 4j6",
    "iso:country":"CA",
    "sg:city":"Vancouver",
    "sg:classifiers":[
        {
            "category":"Wholesale",
            "subcategory":"Groceries",
            "type":"Manufacturing & Wholesale Goods"
        }
    ],
    "sg:phone":"+1 604 258 7437",
    "sg:postcode":"V6P 4J6",
    "sg:province":"BC",
    "sg:tags":[
        "grocer"
    ],
    "wof:name":"Blackberry Hill Farm",
    "wof:placetype":"venue"
},
  "geometry": {"coordinates":[-123.133522,49.205444],"type":"Point"}
}