{
  "type": "Feature",
  "properties": {
    "addr:full":"180 Bethridge Rd Etobicoke ON M9W 1N3",
    "addr:housenumber":"180",
    "addr:postcode":"m9w 1n3",
    "addr:street":"Bethridge Rd",
    "iso:country":"CA",
    "sg:address":"180 Bethridge Rd",
    "sg:city":"Etobicoke",
    "sg:classifiers":[
        {
            "category":"Wholesale",
            "subcategory":"Chemicals & Plastics",
            "type":"Manufacturing & Wholesale Goods"
        }
    ],
    "sg:phone":"+1 416 674 0363",
    "sg:postcode":"M9W 1N3",
    "sg:province":"ON",
    "sg:tags":[
        "product",
        "allied"
    ],
    "wof:name":"Terrafix Geosynthetics Inc",
    "wof:placetype":"venue"
},
  "geometry": {"coordinates":[-79.584801,43.708485],"type":"Point"}
}