{
  "type": "Feature",
  "properties": {
    "addr:full":"9610 Rue Ignace # F Brossard QC J4Y 2R4",
    "addr:housenumber":"9610",
    "addr:postcode":"j4y 2r4",
    "addr:street":"Rue Ignace # F",
    "iso:country":"CA",
    "sg:address":"9610 Rue Ignace # F",
    "sg:city":"Brossard",
    "sg:classifiers":[
        {
            "category":"Shopping",
            "type":"Retail Goods"
        }
    ],
    "sg:phone":"+1 450 444 1806",
    "sg:postcode":"J4Y 2R4",
    "sg:province":"QC",
    "sg:tags":[
        "cosmetic",
        "perfume"
    ],
    "wof:name":"Fragrance",
    "wof:placetype":"venue"
},
  "geometry": {"coordinates":[-73.4764099121,45.4314117432],"type":"Point"}
}