{
  "type": "Feature",
  "properties": {
    "addr:full":"12 Mill Hill Rd Nepean ON K2H 9N4",
    "addr:housenumber":"12",
    "addr:postcode":"k2h 9n4",
    "addr:street":"Mill Hill Rd",
    "iso:country":"CA",
    "sg:address":"12 Mill Hill Rd",
    "sg:city":"Nepean",
    "sg:classifiers":[
        {
            "category":"Freight",
            "type":"Transportation"
        }
    ],
    "sg:phone":"+1 613 726 8749",
    "sg:postcode":"K2H 9N4",
    "sg:province":"ON",
    "sg:tags":[
        "delivery",
        "mover"
    ],
    "wof:name":"Trinity Moving",
    "wof:placetype":"venue"
},
  "geometry": {"coordinates":[-75.84358978269999,45.316947937],"type":"Point"}
}