{
  "type": "Feature",
  "properties": {
    "addr:full":"10371 Av Armand-Lavergne Montreal-Nord QC H1H 3N8",
    "addr:housenumber":"10371",
    "addr:postcode":"h1h 3n8",
    "addr:street":"Av Armand-Lavergne",
    "iso:country":"CA",
    "sg:address":"10371 Av Armand-Lavergne",
    "sg:city":"Montreal-Nord",
    "sg:classifiers":[
        {
            "category":"Wholesale",
            "subcategory":"Auto Parts",
            "type":"Manufacturing & Wholesale Goods"
        }
    ],
    "sg:phone":"+1 514 326 9910",
    "sg:postcode":"H1H 3N8",
    "sg:province":"QC",
    "sg:tags":[
        "automobile",
        "rebuilt"
    ],
    "wof:name":"Reusinage Precision",
    "wof:placetype":"venue"
},
  "geometry": {"coordinates":[-73.62793000000001,45.589325],"type":"Point"}
}