{
  "type": "Feature",
  "properties": {
    "iso:country":"CA",
    "sg:address":"10371 Av Armand-Lavergne",
    "sg:city":"Montreal-Nord",
    "sg:classifiers":[
        {
            "category":"Wholesale",
            "subcategory":"Auto Parts",
            "type":"Manufacturing & Wholesale Goods"
        }
    ],
    "sg:phone":"+1 514 326 9910",
    "sg:postcode":"H1H 3N8",
    "sg:province":"QC",
    "sg:tags":[
        "automobile",
        "rebuilt"
    ],
    "wof:name":"Reusinage Precision",
    "wof:placetype":"venue"
},
  "geometry": {"coordinates":[-73.62793,45.589325],"type":"Point"}
}