{
  "type": "Feature",
  "properties": {
    "addr:full":"Blainville QC J7C 2L3",
    "addr:postcode":"j7c 2l3",
    "iso:country":"CA",
    "sg:city":"Blainville",
    "sg:classifiers":[
        {
            "category":"Shopping",
            "subcategory":"Bicycles & Sporting Goods",
            "type":"Retail Goods"
        }
    ],
    "sg:phone":"+1 450 434 5924",
    "sg:postcode":"J7C 2L3",
    "sg:province":"QC",
    "wof:name":"Evangelista Sports Blainville",
    "wof:placetype":"venue"
},
  "geometry": {"coordinates":[-73.87769299999999,45.67186],"type":"Point"}
}