{
  "type": "Feature",
  "properties": {
    "addr:full":"688 Hwy 325 Block House NS B0J 1E0",
    "addr:housenumber":"688",
    "addr:postcode":"ns b0j 1e0",
    "addr:street":"Hwy 325 Block",
    "iso:country":"CA",
    "sg:address":"688 Hwy 325",
    "sg:city":"Block House",
    "sg:classifiers":[
        {
            "category":"Autos & Motor Vehicles",
            "subcategory":"Motorcycle Sales",
            "type":"Retail Goods"
        }
    ],
    "sg:phone":"+1 902 624 0505",
    "sg:postcode":"B0J 1E0",
    "sg:province":"NS",
    "sg:tags":[
        "all",
        "terrain"
    ],
    "wof:name":"Block House Sports & Rv",
    "wof:placetype":"venue"
},
  "geometry": {"coordinates":[-64.4183502197,44.4453277588],"type":"Point"}
}