{
  "type": "Feature",
  "properties": {
    "addr:full":"1671 Ryan Rd Lazo BC V0R 2K0",
    "addr:housenumber":"1671",
    "addr:postcode":"v0r 2k0",
    "addr:street":"Ryan Rd",
    "iso:country":"CA",
    "sg:address":"1671 Ryan Rd",
    "sg:city":"Lazo",
    "sg:classifiers":[
        {
            "category":"Retail",
            "subcategory":"Auto Repair",
            "type":"Services"
        }
    ],
    "sg:phone":"+1 250 339 1950",
    "sg:postcode":"V0R 2K0",
    "sg:province":"BC",
    "sg:tags":[
        "body",
        "automobile",
        "painting"
    ],
    "wof:name":"T-Bird Auto Body",
    "wof:placetype":"venue"
},
  "geometry": {"coordinates":[-124.908958435,49.7131996155],"type":"Point"}
}