{
  "type": "Feature",
  "properties": {
    "iso:country":"CA",
    "sg:address":"2710 Main St",
    "sg:city":"Vancouver",
    "sg:classifiers":[
        {
            "category":"Restaurant",
            "type":"Food & Drink"
        }
    ],
    "sg:phone":"+1 604 879 0560",
    "sg:postcode":"V5T 3E8",
    "sg:province":"BC",
    "wof:name":"Confucius Says Restaurant",
    "wof:placetype":"venue"
},
  "geometry": {"coordinates":[-123.100754,49.26099],"type":"Point"}
}