{
  "type": "Feature",
  "properties": {
    "addr:full":"10378 Boul Gouin O Roxboro QC H8Y 1S3",
    "addr:housenumber":"10378",
    "addr:postcode":"h8y 1s3",
    "addr:street":"Boul Gouin O",
    "iso:country":"CA",
    "sg:address":"10378 Boul Gouin O",
    "sg:city":"Roxboro",
    "sg:classifiers":[
        {
            "category":"Shopping",
            "subcategory":"Used Merchandise",
            "type":"Retail Goods"
        }
    ],
    "sg:phone":"+1 514 685 3323",
    "sg:postcode":"H8Y 1S3",
    "sg:province":"QC",
    "sg:tags":[
        "antique"
    ],
    "wof:name":"Decor Elegante",
    "wof:placetype":"venue"
},
  "geometry": {"coordinates":[-73.80270400000001,45.509613],"type":"Point"}
}