{
  "type": "Feature",
  "properties": {
    "iso:country":"CA",
    "sg:address":"10378 Boul Gouin O",
    "sg:city":"Roxboro",
    "sg:classifiers":[
        {
            "category":"Shopping",
            "subcategory":"Used Merchandise",
            "type":"Retail Goods"
        }
    ],
    "sg:phone":"+1 514 685 3323",
    "sg:postcode":"H8Y 1S3",
    "sg:province":"QC",
    "sg:tags":[
        "antique"
    ],
    "wof:name":"Decor Elegante",
    "wof:placetype":"venue"
},
  "geometry": {"coordinates":[-73.802704,45.509613],"type":"Point"}
}