{
  "type": "Feature",
  "properties": {
    "addr:full":"1316 Rte Marie-Victorin Saint-Nicolas QC G7A 4G1",
    "addr:housenumber":"1316",
    "addr:postcode":"g7a 4g1",
    "addr:street":"Rte Marie-Victorin",
    "iso:country":"CA",
    "sg:address":"1316 Rte Marie-Victorin",
    "sg:city":"Saint-Nicolas",
    "sg:classifiers":[
        {
            "category":"Retail",
            "subcategory":"Repair Shop",
            "type":"Services"
        }
    ],
    "sg:phone":"+1 418 831 3882",
    "sg:postcode":"G7A 4G1",
    "sg:province":"QC",
    "sg:tags":[
        "upholsterer"
    ],
    "wof:name":"Rembourrage Francis Inc",
    "wof:placetype":"venue"
},
  "geometry": {"coordinates":[-71.39088439939999,46.7021255493],"type":"Point"}
}