{
  "type": "Feature",
  "properties": {
    "iso:country":"CA",
    "sg:address":"43 Main St",
    "sg:city":"Springhill",
    "sg:classifiers":[
        {
            "category":"Government",
            "subcategory":"Office",
            "type":"Public Place"
        }
    ],
    "sg:phone":"+1 902 597 3751",
    "sg:postcode":"B0M 1X0",
    "sg:province":"NS",
    "sg:tags":[
        "village"
    ],
    "wof:name":"Springhill Town Clerk's Office",
    "wof:placetype":"venue"
},
  "geometry": {"coordinates":[-64.05693817140001,45.6506500244],"type":"Point"}
}