{
  "type": "Feature",
  "properties": {
    "addr:full":"1 Promenade Cir #F112 Thornhill ON L4J 4P8",
    "addr:housenumber":"1;# f112",
    "addr:postcode":"l4j 4p8",
    "addr:street":"Promenade Cir",
    "iso:country":"CA",
    "sg:address":"1 Promenade Cir #F112",
    "sg:city":"Thornhill",
    "sg:classifiers":[
        {
            "category":"Restaurant",
            "type":"Food & Drink"
        }
    ],
    "sg:phone":"+1 905 764 1264",
    "sg:postcode":"L4J 4P8",
    "sg:province":"ON",
    "sg:tags":[
        "caterer"
    ],
    "wof:name":"Cultures Fresh Food Restaurant",
    "wof:placetype":"venue"
},
  "geometry": {"coordinates":[-79.423553,43.81554],"type":"Point"}
}