{
  "type": "Feature",
  "properties": {
    "iso:country":"CA",
    "sg:city":"Saint-Boniface-DE-Shawinigan",
    "sg:classifiers":[
        {
            "category":"Building & Trades",
            "subcategory":"Construction",
            "type":"Services"
        }
    ],
    "sg:phone":"+1 819 535 5435",
    "sg:postcode":"G0X 2L0",
    "sg:province":"QC",
    "sg:tags":[
        "consultant",
        "excavating",
        "tax",
        "contractor"
    ],
    "wof:name":"Immeubles Eau-Bois Inc",
    "wof:placetype":"venue"
},
  "geometry": {"coordinates":[-72.92683410639999,46.523399353],"type":"Point"}
}