{
  "type": "Feature",
  "properties": {
    "addr:full":"401 Av Pie-Xii Louiseville QC J5V 1T1",
    "addr:housenumber":"401",
    "addr:postcode":"j5v 1t1",
    "addr:street":"Av Pie-Xii",
    "iso:country":"CA",
    "sg:address":"401 Av Pie-Xii",
    "sg:city":"Louiseville",
    "sg:classifiers":[
        {
            "category":"Personal",
            "subcategory":"Beauty Salon",
            "type":"Services"
        }
    ],
    "sg:phone":"+1 819 228 4888",
    "sg:postcode":"J5V 1T1",
    "sg:province":"QC",
    "wof:name":"Clinique D'Esthetique Athena",
    "wof:placetype":"venue"
},
  "geometry": {"coordinates":[-72.94719696040001,46.2511863708],"type":"Point"}
}