{
  "type": "Feature",
  "properties": {
    "addr:full":"10617 Rue Principale Saint-Louis-DE-Kent NB E4X 1G1",
    "addr:housenumber":"10617",
    "addr:postcode":"e4x 1g1",
    "addr:street":"Rue Principale",
    "iso:country":"CA",
    "sg:address":"10617 Rue Principale",
    "sg:city":"Saint-Louis-DE-Kent",
    "sg:classifiers":[
        {
            "category":"Autos & Motor Vehicles",
            "subcategory":"Boat Sales",
            "type":"Retail Goods"
        }
    ],
    "sg:phone":"+1 506 876 1199",
    "sg:postcode":"E4X 1G1",
    "sg:province":"NB",
    "sg:tags":[
        "tours",
        "dealer",
        "sightseeing"
    ],
    "wof:name":"Kayakouch Inc",
    "wof:placetype":"venue"
},
  "geometry": {"coordinates":[-64.98384900000001,46.744251],"type":"Point"}
}