{
  "type": "Feature",
  "properties": {
    "addr:full":"2241 Mississauga Rd Mississauga ON L5H 2K8",
    "addr:housenumber":"2241",
    "addr:postcode":"l5h 2k8",
    "addr:street":"Mississauga Rd",
    "iso:country":"CA",
    "sg:address":"2241 Mississauga Rd",
    "sg:city":"Mississauga",
    "sg:classifiers":[
        {
            "category":"Education",
            "subcategory":"School",
            "type":"Public Place"
        }
    ],
    "sg:phone":"+1 905 274 2401",
    "sg:postcode":"L5H 2K8",
    "sg:province":"ON",
    "wof:name":"Holy Name of Mary School",
    "wof:placetype":"venue"
},
  "geometry": {"coordinates":[-79.63706999999999,43.541775],"type":"Point"}
}