{
  "type": "Feature",
  "properties": {
    "addr:full":"North York ON M3J 3H9",
    "addr:postcode":"m3j 3h9",
    "iso:country":"CA",
    "sg:city":"North York",
    "sg:classifiers":[
        {
            "category":"Professional",
            "subcategory":"Art Services",
            "type":"Services"
        }
    ],
    "sg:phone":"+1 416 665 6260",
    "sg:postcode":"M3J 3H9",
    "sg:province":"ON",
    "sg:tags":[
        "photographer"
    ],
    "wof:name":"Lane Studios Ltd",
    "wof:placetype":"venue"
},
  "geometry": {"coordinates":[-79.4738082886,43.783203125],"type":"Point"}
}