{
  "type": "Feature",
  "properties": {
    "iso:country":"CA",
    "sg:address":"35 North St",
    "sg:city":"Bobcaygeon",
    "sg:classifiers":[
        {
            "category":"Retail",
            "subcategory":"Auto Repair",
            "type":"Services"
        }
    ],
    "sg:phone":"+1 705 738 2241",
    "sg:postcode":"K0M 1A0",
    "sg:province":"ON",
    "sg:tags":[
        "repairing",
        "automobile"
    ],
    "wof:name":"Pieter Von Oudenaren Garage",
    "wof:placetype":"venue"
},
  "geometry": {"coordinates":[-78.55121612550001,44.5436592102],"type":"Point"}
}