{
  "type": "Feature",
  "properties": {
    "iso:country":"CA",
    "sg:address":"1000 Boul St-Joseph",
    "sg:city":"Laurier-Station",
    "sg:classifiers":[
        {
            "category":"Autos & Motor Vehicles",
            "subcategory":"Auto Supplies",
            "type":"Retail Goods"
        }
    ],
    "sg:phone":"+1 418 728 3510",
    "sg:postcode":"G0S 1N0",
    "sg:province":"QC",
    "sg:tags":[
        "automobile",
        "parts"
    ],
    "wof:name":"Pieces D'Autos Carquest",
    "wof:placetype":"venue"
},
  "geometry": {"coordinates":[-71.6262664795,46.5350189209],"type":"Point"}
}