{
  "type": "Feature",
  "properties": {
    "addr:full":"Hughenden AB T0B 2E0",
    "addr:postcode":"t0b 2e0",
    "iso:country":"CA",
    "sg:city":"Hughenden",
    "sg:classifiers":[
        {
            "category":"Mining & Drilling",
            "type":"Manufacturing & Wholesale Goods"
        }
    ],
    "sg:phone":"+1 780 856 3660",
    "sg:postcode":"T0B 2E0",
    "sg:province":"AB",
    "sg:tags":[
        "company",
        "oil"
    ],
    "wof:name":"Husky Oil Operations Ltd",
    "wof:placetype":"venue"
},
  "geometry": {"coordinates":[-110.975334,52.509483],"type":"Point"}
}