{
  "type": "Feature",
  "properties": {
    "addr:full":"General Delivery Fond Du Lac SK S0J 0W0",
    "addr:postcode":"s0j 0w0",
    "iso:country":"CA",
    "sg:address":"General Delivery",
    "sg:city":"Fond Du Lac",
    "sg:classifiers":[
        {
            "category":"Organizations",
            "subcategory":"Professional Association",
            "type":"Services"
        }
    ],
    "sg:phone":"+1 306 686 2155",
    "sg:postcode":"S0J 0W0",
    "sg:province":"SK",
    "sg:tags":[
        "native"
    ],
    "wof:name":"Fond Du Lac Indian Reserve",
    "wof:placetype":"venue"
},
  "geometry": {"coordinates":[-107.187569,59.327782],"type":"Point"}
}