{
  "type": "Feature",
  "properties": {
    "addr:full":"10040 248 St Maple Ridge BC V2W 1S8",
    "addr:housenumber":"10040",
    "addr:postcode":"v2w 1s8",
    "addr:street":"248 St",
    "iso:country":"CA",
    "sg:address":"10040 248 St",
    "sg:city":"Maple Ridge",
    "sg:classifiers":[
        {
            "category":"Professional",
            "subcategory":"Testing Lab",
            "type":"Services"
        }
    ],
    "sg:phone":"+1 604 463 4120",
    "sg:postcode":"V2W 1S8",
    "sg:province":"BC",
    "sg:tags":[
        "laboratory"
    ],
    "wof:name":"Itl Testing Laboratories",
    "wof:placetype":"venue"
},
  "geometry": {"coordinates":[-122.534485,49.185028],"type":"Point"}
}