{
  "type": "Feature",
  "properties": {
    "iso:country":"CA",
    "sg:address":"198 Rue Montmorency",
    "sg:city":"Boischatel",
    "sg:classifiers":[
        {
            "category":"Freight",
            "type":"Transportation"
        }
    ],
    "sg:phone":"+1 418 822 0261",
    "sg:postcode":"G0A 1H0",
    "sg:province":"QC",
    "sg:tags":[
        "mover"
    ],
    "wof:name":"Demenagement Rt Enr",
    "wof:placetype":"venue"
},
  "geometry": {"coordinates":[-71.156265,46.897213],"type":"Point"}
}