{
  "type": "Feature",
  "properties": {
    "addr:full":"3175 Boul Du Royaume Jonquiere QC G7X 7V3",
    "addr:housenumber":"3175",
    "addr:postcode":"g7x 7v3",
    "addr:street":"Boul Du Royaume",
    "iso:country":"CA",
    "sg:address":"3175 Boul Du Royaume",
    "sg:city":"Jonquiere",
    "sg:classifiers":[
        {
            "category":"Wholesale",
            "subcategory":"Machinery & Supplies",
            "type":"Manufacturing & Wholesale Goods"
        }
    ],
    "sg:phone":"+1 418 548 7182",
    "sg:postcode":"G7X 7V3",
    "sg:province":"QC",
    "sg:tags":[
        "truck"
    ],
    "wof:name":"Equipments J Achard Ltee",
    "wof:placetype":"venue"
},
  "geometry": {"coordinates":[-71.201897,48.409389],"type":"Point"}
}