{
  "type": "Feature",
  "properties": {
    "iso:country":"CA",
    "sg:address":"110 John Button Blvd",
    "sg:city":"Markham",
    "sg:classifiers":[
        {
            "category":"Building & Trades",
            "subcategory":"Construction",
            "type":"Services"
        }
    ],
    "sg:phone":"+1 905 479 5778",
    "sg:postcode":"L3R 9C8",
    "sg:province":"ON",
    "sg:tags":[
        "builder",
        "fireplace",
        "repairer",
        "chimney",
        "cleaning"
    ],
    "wof:name":"Carleton Chimney Svc Inc",
    "wof:placetype":"venue"
},
  "geometry": {"coordinates":[-79.35881,43.864746],"type":"Point"}
}