{
  "type": "Feature",
  "properties": {
    "addr:full":"208 St George Ave Annapolis Royal NS B0S 1A0",
    "addr:housenumber":"208",
    "addr:postcode":"b0s 1a0",
    "addr:street":"St George Ave",
    "iso:country":"CA",
    "sg:address":"208 St George Ave",
    "sg:city":"Annapolis Royal",
    "sg:classifiers":[
        {
            "category":"Health Services",
            "subcategory":"Doctor",
            "type":"Services"
        }
    ],
    "sg:phone":"+1 902 532 2324",
    "sg:postcode":"B0S 1A0",
    "sg:province":"NS",
    "sg:tags":[
        "physician",
        "surgeon"
    ],
    "wof:name":"Buchholz, Kenneth P MD",
    "wof:placetype":"venue"
},
  "geometry": {"coordinates":[-65.51939400000001,44.74519],"type":"Point"}
}