{
  "type": "Feature",
  "properties": {
    "addr:full":"1188 Matthews Ave Vancouver BC V6H 1W4",
    "addr:housenumber":"1188",
    "addr:postcode":"v6h 1w4",
    "addr:street":"Matthews Ave",
    "iso:country":"CA",
    "sg:address":"1188 Matthews Ave",
    "sg:city":"Vancouver",
    "sg:classifiers":[
        {
            "category":"Health Services",
            "subcategory":"Health Practitioner",
            "type":"Services"
        }
    ],
    "sg:phone":"+1 604 731 3280",
    "sg:postcode":"V6H 1W4",
    "sg:province":"BC",
    "sg:tags":[
        "psychologist"
    ],
    "wof:name":"Alfonso, V",
    "wof:placetype":"venue"
},
  "geometry": {"coordinates":[-123.132476807,49.2536468506],"type":"Point"}
}