{
  "type": "Feature",
  "properties": {
    "addr:full":"2 King St W Kitchener ON N2G 1A3",
    "addr:housenumber":"2",
    "addr:postcode":"n2g 1a3",
    "addr:street":"King St W",
    "iso:country":"CA",
    "sg:address":"2 King St W",
    "sg:city":"Kitchener",
    "sg:classifiers":[
        {
            "category":"Banks & Credit Unions",
            "subcategory":"Bank",
            "type":"Services"
        }
    ],
    "sg:phone":"+1 519 885 9200",
    "sg:postcode":"N2G 1A3",
    "sg:province":"ON",
    "wof:name":"Bank of Montreal",
    "wof:placetype":"venue"
},
  "geometry": {"coordinates":[-80.4892578125,43.4499053955],"type":"Point"}
}