{
  "type": "Feature",
  "properties": {
    "addr:full":"11355 105 Ave NW Edmonton AB T5H 3Y3",
    "addr:housenumber":"11355",
    "addr:postcode":"t5h 3y3",
    "addr:street":"105 Ave Nw",
    "iso:country":"CA",
    "sg:address":"11355 105 Ave NW",
    "sg:city":"Edmonton",
    "sg:classifiers":[
        {
            "category":"Manufacturing",
            "subcategory":"Printing",
            "type":"Manufacturing & Wholesale Goods"
        }
    ],
    "sg:phone":"+1 780 439 7485",
    "sg:postcode":"T5H 3Y3",
    "sg:province":"AB",
    "sg:tags":[
        "printer"
    ],
    "wof:name":"Action Printing Svc",
    "wof:placetype":"venue"
},
  "geometry": {"coordinates":[-113.516777039,53.548122406],"type":"Point"}
}