{
  "type": "Feature",
  "properties": {
    "addr:full":"5722 Rue Saint-Andre Montreal QC H2S 2K1",
    "addr:housenumber":"5722",
    "addr:postcode":"h2s 2k1",
    "addr:street":"Rue Saint-Andre",
    "iso:country":"CA",
    "sg:address":"5722 Rue Saint-Andre",
    "sg:city":"Montreal",
    "sg:classifiers":[
        {
            "category":"Organizations",
            "subcategory":"Professional Association",
            "type":"Services"
        }
    ],
    "sg:phone":"+1 514 843 7875",
    "sg:postcode":"H2S 2K1",
    "sg:province":"QC",
    "wof:name":"Aide Medicale Pour LA",
    "wof:placetype":"venue"
},
  "geometry": {"coordinates":[-73.595032,45.533207],"type":"Point"}
}