{
  "type": "Feature",
  "properties": {
    "addr:full":"146 Roger Rd Ottawa ON K1H 5C8",
    "addr:housenumber":"146",
    "addr:postcode":"k1h 5c8",
    "addr:street":"Roger Rd",
    "iso:country":"CA",
    "sg:address":"146 Roger Rd",
    "sg:city":"Ottawa",
    "sg:classifiers":[
        {
            "category":"Professional",
            "type":"Services"
        }
    ],
    "sg:phone":"+1 613 733 5441",
    "sg:postcode":"K1H 5C8",
    "sg:province":"ON",
    "sg:tags":[
        "interior",
        "consultant",
        "design",
        "establishment",
        "decorator"
    ],
    "wof:name":"C Carin Reisman Design",
    "wof:placetype":"venue"
},
  "geometry": {"coordinates":[-75.66456604,45.3964424133],"type":"Point"}
}