{
  "type": "Feature",
  "properties": {
    "addr:full":"38 Prince Albert Rd Annapolis Royal NS B0S 1A0",
    "addr:housenumber":"38",
    "addr:postcode":"b0s 1a0",
    "addr:street":"Prince Albert Rd",
    "iso:country":"CA",
    "sg:address":"38 Prince Albert Rd",
    "sg:city":"Annapolis Royal",
    "sg:classifiers":[
        {
            "category":"Restaurant",
            "type":"Food & Drink"
        }
    ],
    "sg:phone":"+1 902 532 2111",
    "sg:postcode":"B0S 1A0",
    "sg:province":"NS",
    "wof:name":"Charlie's Place Restaurant Ltd",
    "wof:placetype":"venue"
},
  "geometry": {"coordinates":[-65.512444,44.749294],"type":"Point"}
}