{
  "type": "Feature",
  "properties": {
    "iso:country":"CA",
    "sg:address":"RR 3 STN Main",
    "sg:city":"Acton",
    "sg:classifiers":[
        {
            "category":"Building & Trades",
            "subcategory":"Construction",
            "type":"Services"
        }
    ],
    "sg:phone":"+1 519 853 2202",
    "sg:postcode":"L7J 2L9",
    "sg:province":"ON",
    "sg:tags":[
        "general",
        "contractor"
    ],
    "wof:name":"Tas Contracting",
    "wof:placetype":"venue"
},
  "geometry": {"coordinates":[-80.040329,43.630733],"type":"Point"}
}