{
  "type": "Feature",
  "properties": {
    "addr:full":"RR 4 STN Main Cobourg ON K9A 4J7",
    "addr:postcode":"k9a 4j7",
    "addr:street":"Rr 4 Stn Main",
    "iso:country":"CA",
    "sg:address":"RR 4 STN Main",
    "sg:city":"Cobourg",
    "sg:classifiers":[
        {
            "category":"Recreation",
            "type":"Entertainment"
        }
    ],
    "sg:phone":"+1 905 342 2249",
    "sg:postcode":"K9A 4J7",
    "sg:province":"ON",
    "sg:tags":[
        "hall",
        "auditorium"
    ],
    "wof:name":"Cold Springs Memorial Hall",
    "wof:placetype":"venue"
},
  "geometry": {"coordinates":[-78.1677780151,43.9596061707],"type":"Point"}
}