{
  "type": "Feature",
  "properties": {
    "addr:full":"60 Tillson Ave Tillsonburg ON N4G 3A1",
    "addr:housenumber":"60",
    "addr:postcode":"n4g 3a1",
    "addr:street":"Tillson Ave",
    "iso:country":"CA",
    "sg:address":"60 Tillson Ave",
    "sg:city":"Tillsonburg",
    "sg:classifiers":[
        {
            "category":"Education",
            "subcategory":"School",
            "type":"Public Place"
        }
    ],
    "sg:phone":"+1 519 688 3498",
    "sg:postcode":"N4G 3A1",
    "sg:province":"ON",
    "wof:name":"Annandale School",
    "wof:placetype":"venue"
},
  "geometry": {"coordinates":[-80.7227935791,42.8640022278],"type":"Point"}
}