{
  "type": "Feature",
  "properties": {
    "addr:full":"289 King St Midland ON L4R 3M5",
    "addr:housenumber":"289",
    "addr:postcode":"l4r 3m5",
    "addr:street":"King St",
    "iso:country":"CA",
    "sg:address":"289 King St",
    "sg:city":"Midland",
    "sg:classifiers":[
        {
            "category":"Shopping",
            "subcategory":"Photographic Equipment",
            "type":"Retail Goods"
        }
    ],
    "sg:phone":"+1 705 526 2671",
    "sg:postcode":"L4R 3M5",
    "sg:province":"ON",
    "sg:tags":[
        "supply"
    ],
    "wof:name":"Watson's Camera Shop",
    "wof:placetype":"venue"
},
  "geometry": {"coordinates":[-79.88493347169999,44.7496337891],"type":"Point"}
}