{
  "type": "Feature",
  "properties": {
    "addr:full":"2150 Rue Letendre Drummondville QC J2C 7E9",
    "addr:housenumber":"2150",
    "addr:postcode":"j2c 7e9",
    "addr:street":"Rue Letendre",
    "iso:country":"CA",
    "sg:address":"2150 Rue Letendre",
    "sg:city":"Drummondville",
    "sg:classifiers":[
        {
            "category":"Manufacturing",
            "subcategory":"Printing",
            "type":"Manufacturing & Wholesale Goods"
        }
    ],
    "sg:phone":"+1 819 478 2870",
    "sg:postcode":"J2C 7E9",
    "sg:province":"QC",
    "sg:tags":[
        "printer"
    ],
    "wof:name":"Imprimerie Lemire Enr",
    "wof:placetype":"venue"
},
  "geometry": {"coordinates":[-72.521469,45.872948],"type":"Point"}
}