{
  "type": "Feature",
  "properties": {
    "addr:full":"45896 Alexander Ave Chilliwack BC V2P 1L5",
    "addr:postcode":"45896;v2p 1l5",
    "addr:street":"Alexander Ave",
    "iso:country":"CA",
    "sg:address":"45896 Alexander Ave",
    "sg:city":"Chilliwack",
    "sg:classifiers":[
        {
            "category":"Autos & Motor Vehicles",
            "subcategory":"Auto Supplies",
            "type":"Retail Goods"
        }
    ],
    "sg:phone":"+1 604 792 7277",
    "sg:postcode":"V2P 1L5",
    "sg:province":"BC",
    "sg:tags":[
        "machine",
        "automobile",
        "parts",
        "shop"
    ],
    "wof:name":"Ken's Automotive Machine Shop",
    "wof:placetype":"venue"
},
  "geometry": {"coordinates":[-121.95465900000001,49.164288],"type":"Point"}
}