{
  "type": "Feature",
  "properties": {
    "addr:full":"210 Creditstone Rd Concord ON L4K 1P3",
    "addr:housenumber":"210",
    "addr:postcode":"l4k 1p3",
    "addr:street":"Creditstone Rd",
    "iso:country":"CA",
    "sg:address":"210 Creditstone Rd",
    "sg:city":"Concord",
    "sg:classifiers":[
        {
            "category":"Building & Trades",
            "subcategory":"Cleaning & Sanitation",
            "type":"Services"
        }
    ],
    "sg:phone":"+1 905 660 1967",
    "sg:postcode":"L4K 1P3",
    "sg:province":"ON",
    "sg:tags":[
        "window"
    ],
    "wof:name":"Royal Anchor Systems Ltd",
    "wof:placetype":"venue"
},
  "geometry": {"coordinates":[-79.5175628662,43.7938804626],"type":"Point"}
}