{
  "type": "Feature",
  "properties": {
    "addr:full":"119 Cowan Ave St. John's NL A1E 4W4",
    "addr:housenumber":"119",
    "addr:postcode":"a1e 4w4",
    "addr:street":"Cowan Ave",
    "iso:country":"CA",
    "sg:address":"119 Cowan Ave",
    "sg:city":"St. John's",
    "sg:classifiers":[
        {
            "category":"Education",
            "subcategory":"School",
            "type":"Public Place"
        }
    ],
    "sg:phone":"+1 709 745 1513",
    "sg:postcode":"A1E 4W4",
    "sg:province":"NL",
    "wof:name":"St Matthew's School",
    "wof:placetype":"venue"
},
  "geometry": {"coordinates":[-52.7626457214,47.532749176],"type":"Point"}
}