{
  "type": "Feature",
  "properties": {
    "addr:full":"PO Box 361 Ryley AB T0B 4A0",
    "addr:housenumber":"po",
    "addr:postcode":"t0b 4a0",
    "addr:street":"Box 361 Ryley",
    "iso:country":"CA",
    "sg:address":"PO Box 361",
    "sg:city":"Ryley",
    "sg:classifiers":[
        {
            "category":"Wholesale",
            "subcategory":"Durable Goods & Equipment",
            "type":"Manufacturing & Wholesale Goods"
        }
    ],
    "sg:phone":"+1 780 663 2344",
    "sg:postcode":"T0B 4A0",
    "sg:province":"AB",
    "sg:tags":[
        "environmental",
        "product"
    ],
    "wof:name":"For Lands Sake Environmental",
    "wof:placetype":"venue"
},
  "geometry": {"coordinates":[-112.42781100000001,53.289848],"type":"Point"}
}