{
  "type": "Feature",
  "properties": {
    "addr:full":"2283 41st Ave W Vancouver BC V6M 2A3",
    "addr:housenumber":"2283",
    "addr:postcode":"v6m 2a3",
    "addr:street":"41St Ave W",
    "iso:country":"CA",
    "sg:address":"2283 41st Ave W",
    "sg:city":"Vancouver",
    "sg:classifiers":[
        {
            "category":"Shopping",
            "subcategory":"Clothing, Apparel, & Fashions",
            "type":"Retail Goods"
        }
    ],
    "sg:phone":"+1 604 266 4598",
    "sg:postcode":"V6M 2A3",
    "sg:province":"BC",
    "sg:tags":[
        "lingerie"
    ],
    "wof:name":"Monaliza's Lingerie Ltd",
    "wof:placetype":"venue"
},
  "geometry": {"coordinates":[-123.15947,49.234756],"type":"Point"}
}