{
  "type": "Feature",
  "properties": {
    "addr:full":"863 Rue Alexandre Levis QC G6V 7M5",
    "addr:housenumber":"863",
    "addr:postcode":"g6v 7m5",
    "addr:street":"Rue Alexandre Levis",
    "iso:country":"CA",
    "sg:address":"863 Rue Alexandre",
    "sg:city":"Levis",
    "sg:classifiers":[
        {
            "category":"Manufacturing",
            "subcategory":"Tools & Machinery",
            "type":"Manufacturing & Wholesale Goods"
        }
    ],
    "sg:phone":"+1 418 838 3711",
    "sg:postcode":"G6V 7M5",
    "sg:province":"QC",
    "sg:tags":[
        "photographic",
        "supply"
    ],
    "wof:name":"Distribution Voltimage Inc",
    "wof:placetype":"venue"
},
  "geometry": {"coordinates":[-71.18436431879999,46.7589302063],"type":"Point"}
}