{
  "type": "Feature",
  "properties": {
    "addr:full":"20457 Douglas Cres Langley BC V3A 4B6",
    "addr:housenumber":"20457",
    "addr:postcode":"v3a 4b6",
    "addr:street":"Douglas Cres",
    "iso:country":"CA",
    "sg:address":"20457 Douglas Cres",
    "sg:city":"Langley",
    "sg:classifiers":[
        {
            "category":"Shopping",
            "type":"Retail Goods"
        }
    ],
    "sg:phone":"+1 604 514 0044",
    "sg:postcode":"V3A 4B6",
    "sg:province":"BC",
    "sg:tags":[
        "wedding",
        "supply"
    ],
    "wof:name":"Making Memories Svc",
    "wof:placetype":"venue"
},
  "geometry": {"coordinates":[-122.655181885,49.1035346985],"type":"Point"}
}