{
  "type": "Feature",
  "properties": {
    "iso:country":"CA",
    "sg:address":"785 Bridge St W",
    "sg:city":"Waterloo",
    "sg:classifiers":[
        {
            "category":"Shopping",
            "subcategory":"Computers & Home Electronics",
            "type":"Retail Goods"
        }
    ],
    "sg:phone":"+1 519 746 7190",
    "sg:postcode":"N2V 2K1",
    "sg:province":"ON",
    "sg:tags":[
        "software"
    ],
    "wof:name":"Virtek Vision Corp",
    "wof:placetype":"venue"
},
  "geometry": {"coordinates":[-80.5251235962,43.5138473511],"type":"Point"}
}