{
  "type": "Feature",
  "properties": {
    "addr:full":"6 Parade St Yarmouth NS B5A 3A4",
    "addr:housenumber":"6",
    "addr:postcode":"b5a 3a4",
    "addr:street":"Parade St",
    "iso:country":"CA",
    "sg:address":"6 Parade St",
    "sg:city":"Yarmouth",
    "sg:classifiers":[
        {
            "category":"Health Services",
            "subcategory":"Doctor",
            "type":"Services"
        }
    ],
    "sg:phone":"+1 902 742 9151",
    "sg:postcode":"B5A 3A4",
    "sg:province":"NS",
    "sg:tags":[
        "physician",
        "surgeon"
    ],
    "wof:name":"Wyman, Chester R MD",
    "wof:placetype":"venue"
},
  "geometry": {"coordinates":[-66.119591,43.83786],"type":"Point"}
}