{
  "type": "Feature",
  "properties": {
    "addr:full":"6101 Boul Talbot Laterriere QC G7N 1V9",
    "addr:housenumber":"6101",
    "addr:postcode":"g7n 1v9",
    "addr:street":"Boul Talbot Laterriere",
    "iso:country":"CA",
    "sg:address":"6101 Boul Talbot",
    "sg:city":"Laterriere",
    "sg:classifiers":[
        {
            "category":"Professional",
            "subcategory":"Engineering",
            "type":"Services"
        }
    ],
    "sg:phone":"+1 418 678 3061",
    "sg:postcode":"G7N 1V9",
    "sg:province":"QC",
    "sg:tags":[
        "engineer"
    ],
    "wof:name":"Delgesco Inc",
    "wof:placetype":"venue"
},
  "geometry": {"coordinates":[-71.137856,48.312244],"type":"Point"}
}