{
  "type": "Feature",
  "properties": {
    "iso:country":"CA",
    "sg:address":"PO Box 1027 STN Main",
    "sg:city":"Guelph",
    "sg:classifiers":[
        {
            "category":"Social Services",
            "type":"Services"
        }
    ],
    "sg:phone":"+1 519 821 3760",
    "sg:postcode":"N1H 6N1",
    "sg:province":"ON",
    "sg:tags":[
        "organization",
        "welfare"
    ],
    "wof:name":"Distress Centre",
    "wof:placetype":"venue"
},
  "geometry": {"coordinates":[-80.247871,43.544563],"type":"Point"}
}