{
  "type": "Feature",
  "properties": {
    "addr:full":"3516 Cape Rd Dorchester NB E4K 2X5",
    "addr:housenumber":"3516",
    "addr:postcode":"e4k 2x5",
    "addr:street":"Cape Rd",
    "iso:country":"CA",
    "sg:address":"3516 Cape Rd",
    "sg:city":"Dorchester",
    "sg:classifiers":[
        {
            "category":"Education",
            "subcategory":"Library",
            "type":"Public Place"
        }
    ],
    "sg:phone":"+1 506 379 3032",
    "sg:postcode":"E4K 2X5",
    "sg:province":"NB",
    "wof:name":"Dorchester Memorial Library",
    "wof:placetype":"venue"
},
  "geometry": {"coordinates":[-64.5183563232,45.8975524902],"type":"Point"}
}