{
  "type": "Feature",
  "properties": {
    "addr:full":"10770 Av Moisan Montreal-Nord QC H1G 4N4",
    "addr:housenumber":"10770",
    "addr:postcode":"h1g 4n4",
    "addr:street":"Av Moisan",
    "iso:country":"CA",
    "sg:address":"10770 Av Moisan",
    "sg:city":"Montreal-Nord",
    "sg:classifiers":[
        {
            "category":"Retail",
            "subcategory":"Auto Repair",
            "type":"Services"
        }
    ],
    "sg:phone":"+1 514 325 0403",
    "sg:postcode":"H1G 4N4",
    "sg:province":"QC",
    "sg:tags":[
        "body",
        "automobile",
        "painting"
    ],
    "wof:name":"Gms Enr",
    "wof:placetype":"venue"
},
  "geometry": {"coordinates":[-73.616005,45.600834],"type":"Point"}
}