{
  "type": "Feature",
  "properties": {
    "iso:country":"CA",
    "sg:city":"Orleans",
    "sg:classifiers":[
        {
            "category":"Shopping",
            "subcategory":"Jewelry",
            "type":"Retail Goods"
        }
    ],
    "sg:phone":"+1 613 834 9369",
    "sg:postcode":"K1C 2L9",
    "sg:province":"ON",
    "sg:tags":[
        "jeweler"
    ],
    "wof:name":"Ardene",
    "wof:placetype":"venue"
},
  "geometry": {"coordinates":[-75.505943,45.483261],"type":"Point"}
}