{
  "type": "Feature",
  "properties": {
    "iso:country":"CA",
    "sg:city":"Montreal",
    "sg:classifiers":[
        {
            "category":"Restaurant",
            "type":"Food & Drink"
        }
    ],
    "sg:phone":"+1 514 382 1151",
    "sg:postcode":"H2N 2E7",
    "sg:province":"QC",
    "wof:name":"Restaurant Three Three Three",
    "wof:placetype":"venue"
},
  "geometry": {"coordinates":[-73.653969,45.539986],"type":"Point"}
}