{
  "type": "Feature",
  "properties": {
    "addr:full":"PO Box 23169 Rpo Churchill Sq. St. John's NL A1B 4J9",
    "addr:housenumber":"po box",
    "addr:postcode":"23169;a1b 4j9",
    "addr:street":"Churchill Sq.",
    "iso:country":"CA",
    "sg:address":"PO Box 23169 Rpo Churchill Sq.",
    "sg:city":"St. John's",
    "sg:classifiers":[
        {
            "category":"Building & Trades",
            "subcategory":"Equipment Rental",
            "type":"Services"
        }
    ],
    "sg:phone":"+1 709 726 7368",
    "sg:postcode":"A1B 4J9",
    "sg:province":"NL",
    "wof:name":"B'n W Rentals",
    "wof:placetype":"venue"
},
  "geometry": {"coordinates":[-52.7221107483,47.5749435425],"type":"Point"}
}