{
  "type": "Feature",
  "properties": {
    "addr:full":"65 Shore St Fredericton NB E3B 1R3",
    "addr:housenumber":"65",
    "addr:postcode":"e3b 1r3",
    "addr:street":"Shore St",
    "iso:country":"CA",
    "sg:address":"65 Shore St",
    "sg:city":"Fredericton",
    "sg:classifiers":[
        {
            "category":"Shopping",
            "type":"Retail Goods"
        }
    ],
    "sg:phone":"+1 506 454 7361",
    "sg:postcode":"E3B 1R3",
    "sg:province":"NB",
    "sg:tags":[
        "shop",
        "art",
        "gallery",
        "gift",
        "dealer"
    ],
    "wof:name":"Botinicals Gift Shop Inc",
    "wof:placetype":"venue"
},
  "geometry": {"coordinates":[-66.633682251,45.9533843994],"type":"Point"}
}