{
  "type": "Feature",
  "properties": {
    "iso:country":"CA",
    "sg:address":"101 Boul DE LA Concorde E",
    "sg:city":"Laval",
    "sg:classifiers":[
        {
            "category":"Organizations",
            "subcategory":"Professional Association",
            "type":"Services"
        }
    ],
    "sg:phone":"+1 450 972 1818",
    "sg:postcode":"H7G 2C1",
    "sg:province":"QC",
    "wof:name":"Ludotheque Aldi",
    "wof:placetype":"venue"
},
  "geometry": {"coordinates":[-73.688805,45.572128],"type":"Point"}
}