{
  "type": "Feature",
  "properties": {
    "addr:full":"610 Princess Ave London ON N6B 2B9",
    "addr:housenumber":"610",
    "addr:postcode":"n6b 2b9",
    "addr:street":"Princess Ave",
    "iso:country":"CA",
    "sg:address":"610 Princess Ave",
    "sg:city":"London",
    "sg:classifiers":[
        {
            "category":"Professional",
            "subcategory":"Management & Consulting",
            "type":"Services"
        }
    ],
    "sg:phone":"+1 519 686 1300",
    "sg:postcode":"N6B 2B9",
    "sg:province":"ON",
    "sg:tags":[
        "town",
        "city",
        "regional",
        "planner"
    ],
    "wof:name":"Monteith Planning Consultants",
    "wof:placetype":"venue"
},
  "geometry": {"coordinates":[-81.2338562012,42.9927825928],"type":"Point"}
}