{
  "type": "Feature",
  "properties": {
    "iso:country":"CA",
    "sg:address":"Bldg 83",
    "sg:city":"Easterville",
    "sg:classifiers":[
        {
            "category":"Food & Beverages",
            "subcategory":"Groceries & Convenience Stores",
            "type":"Retail Goods"
        }
    ],
    "sg:phone":"+1 204 329 2156",
    "sg:postcode":"R0C 0V0",
    "sg:province":"MB",
    "sg:tags":[
        "grocer"
    ],
    "wof:name":"Griffin's Lucky Dollar Foods",
    "wof:placetype":"venue"
},
  "geometry": {"coordinates":[-99.8197097778,53.1060409546],"type":"Point"}
}