{
  "type": "Feature",
  "properties": {
    "addr:full":"31 Rue Guizot E Montreal QC H2P 1L7",
    "addr:housenumber":"31",
    "addr:postcode":"h2p 1l7",
    "addr:street":"Rue Guizot E",
    "iso:country":"CA",
    "sg:address":"31 Rue Guizot E",
    "sg:city":"Montreal",
    "sg:classifiers":[
        {
            "category":"Food & Beverages",
            "subcategory":"Bakery",
            "type":"Retail Goods"
        }
    ],
    "sg:phone":"+1 514 385 4361",
    "sg:postcode":"H2P 1L7",
    "sg:province":"QC",
    "sg:tags":[
        "baker"
    ],
    "wof:name":"Boulangerie Patisserie Guizot",
    "wof:placetype":"venue"
},
  "geometry": {"coordinates":[-73.634438,45.540302],"type":"Point"}
}