{
  "type": "Feature",
  "properties": {
    "iso:country":"CA",
    "sg:address":"2360 2E Rue",
    "sg:city":"Sainte-Sophie",
    "sg:classifiers":[
        {
            "category":"Building & Trades",
            "subcategory":"Construction",
            "type":"Services"
        }
    ],
    "sg:phone":"+1 450 438 2623",
    "sg:postcode":"J5J 1N5",
    "sg:province":"QC",
    "sg:tags":[
        "excavating",
        "contractor"
    ],
    "wof:name":"Excavation Jmj Corbeil Enr",
    "wof:placetype":"venue"
},
  "geometry": {"coordinates":[-73.89660644529999,45.8193588257],"type":"Point"}
}