{
  "type": "Feature",
  "properties": {
    "addr:full":"538 Topsail Rd St. John's NL A1E 2C5",
    "addr:housenumber":"538",
    "addr:postcode":"a1e 2c5",
    "addr:street":"Topsail Rd",
    "iso:country":"CA",
    "sg:address":"538 Topsail Rd",
    "sg:city":"St. John's",
    "sg:classifiers":[
        {
            "category":"Health Services",
            "subcategory":"Medical Lab",
            "type":"Services"
        }
    ],
    "sg:phone":"+1 709 364 8100",
    "sg:postcode":"A1E 2C5",
    "sg:province":"NL",
    "wof:name":"Joan Andrews Denture Clinic",
    "wof:placetype":"venue"
},
  "geometry": {"coordinates":[-52.7591972351,47.5296478271],"type":"Point"}
}