{
  "type": "Feature",
  "properties": {
    "addr:full":"Route 6 Hunter River PE C0A 1N0",
    "addr:postcode":"c0a 1n0",
    "addr:street":"Route 6",
    "iso:country":"CA",
    "sg:address":"Route 6",
    "sg:city":"Hunter River",
    "sg:classifiers":[
        {
            "category":"Shopping",
            "subcategory":"Gifts & Souvenirs",
            "type":"Retail Goods"
        }
    ],
    "sg:phone":"+1 902 963 2393",
    "sg:postcode":"C0A 1N0",
    "sg:province":"PE",
    "sg:tags":[
        "shop"
    ],
    "wof:name":"Dow's Gift Shop",
    "wof:placetype":"venue"
},
  "geometry": {"coordinates":[-63.343147,46.351761],"type":"Point"}
}