{
  "type": "Feature",
  "properties": {
    "addr:full":"579 Niagara St Victoria BC V8V 1H8",
    "addr:housenumber":"579",
    "addr:postcode":"v8v 1h8",
    "addr:street":"Niagara St",
    "iso:country":"CA",
    "sg:address":"579 Niagara St",
    "sg:city":"Victoria",
    "sg:classifiers":[
        {
            "category":"Food & Beverages",
            "subcategory":"Groceries & Convenience Stores",
            "type":"Retail Goods"
        }
    ],
    "sg:phone":"+1 250 383 1223",
    "sg:postcode":"V8V 1H8",
    "sg:province":"BC",
    "sg:tags":[
        "grocer"
    ],
    "wof:name":"Niagara Grocery",
    "wof:placetype":"venue"
},
  "geometry": {"coordinates":[-123.372550964,48.4122161865],"type":"Point"}
}