{
  "type": "Feature",
  "properties": {
    "addr:full":"2053 Park St Regina SK S4N 6S2",
    "addr:housenumber":"2053",
    "addr:postcode":"s4n 6s2",
    "addr:street":"Park St",
    "iso:country":"CA",
    "sg:address":"2053 Park St",
    "sg:city":"Regina",
    "sg:classifiers":[
        {
            "category":"Personal",
            "subcategory":"Beauty Salon",
            "type":"Services"
        }
    ],
    "sg:phone":"+1 306 352 8210",
    "sg:postcode":"S4N 6S2",
    "sg:province":"SK",
    "wof:name":"Ultracuts",
    "wof:placetype":"venue"
},
  "geometry": {"coordinates":[-104.57204400000001,50.446312],"type":"Point"}
}