{
  "type": "Feature",
  "properties": {
    "iso:country":"CA",
    "sg:address":"330 4th Ave E",
    "sg:city":"Regina",
    "sg:classifiers":[
        {
            "category":"Retail",
            "subcategory":"Auto Repair",
            "type":"Services"
        }
    ],
    "sg:phone":"+1 306 359 1930",
    "sg:postcode":"S4N 4Z6",
    "sg:province":"SK",
    "sg:tags":[
        "truck"
    ],
    "wof:name":"Warner Industries",
    "wof:placetype":"venue"
},
  "geometry": {"coordinates":[-104.578918457,50.463104248],"type":"Point"}
}