{
  "type": "Feature",
  "properties": {
    "addr:full":"10 Queen St Grand Falls-Windsor NL A2A 1H7",
    "addr:housenumber":"10",
    "addr:postcode":"a2a 1h7",
    "addr:street":"Queen St",
    "iso:country":"CA",
    "sg:address":"10 Queen St",
    "sg:city":"Grand Falls-Windsor",
    "sg:classifiers":[
        {
            "category":"Organizations",
            "subcategory":"Community Association",
            "type":"Services"
        }
    ],
    "sg:phone":"+1 709 489 6560",
    "sg:postcode":"A2A 1H7",
    "sg:province":"NL",
    "sg:tags":[
        "club"
    ],
    "wof:name":"Royal Canadian Legion Club",
    "wof:placetype":"venue"
},
  "geometry": {"coordinates":[-55.654991,48.929363],"type":"Point"}
}