{
  "type": "Feature",
  "properties": {
    "iso:country":"CA",
    "sg:address":"516 Parkdale Ave N",
    "sg:city":"Hamilton",
    "sg:classifiers":[
        {
            "category":"Retail",
            "subcategory":"Auto Repair",
            "type":"Services"
        }
    ],
    "sg:phone":"+1 905 549 2206",
    "sg:postcode":"L8H 5Y5",
    "sg:province":"ON",
    "sg:tags":[
        "repairing",
        "automobile",
        "racing",
        "car",
        "equipment"
    ],
    "wof:name":"Northern Motorsport",
    "wof:placetype":"venue"
},
  "geometry": {"coordinates":[-79.78610992430001,43.2501564026],"type":"Point"}
}