{
  "type": "Feature",
  "properties": {
    "addr:full":"1907 Albion Rd Etobicoke ON M9W 5S8",
    "addr:housenumber":"1907",
    "addr:postcode":"m9w 5s8",
    "addr:street":"Albion Rd",
    "iso:country":"CA",
    "sg:address":"1907 Albion Rd",
    "sg:city":"Etobicoke",
    "sg:classifiers":[
        {
            "category":"Wholesale",
            "subcategory":"Metals & Minerals",
            "type":"Manufacturing & Wholesale Goods"
        }
    ],
    "sg:phone":"+1 416 675 2020",
    "sg:postcode":"M9W 5S8",
    "sg:province":"ON",
    "sg:tags":[
        "steel",
        "warehouse"
    ],
    "wof:name":"Sturdell Industries Inc",
    "wof:placetype":"venue"
},
  "geometry": {"coordinates":[-79.6197052002,43.7463111877],"type":"Point"}
}