{
  "type": "Feature",
  "properties": {
    "addr:full":"511 Ridge Rd Stirling ON K0K 3E0",
    "addr:housenumber":"511",
    "addr:postcode":"k0k 3e0",
    "addr:street":"Ridge Rd",
    "iso:country":"CA",
    "sg:address":"511 Ridge Rd",
    "sg:city":"Stirling",
    "sg:classifiers":[
        {
            "category":"Retail",
            "subcategory":"Auto Repair",
            "type":"Services"
        }
    ],
    "sg:phone":"+1 613 395 4495",
    "sg:postcode":"K0K 3E0",
    "sg:province":"ON",
    "sg:tags":[
        "repairing",
        "tire"
    ],
    "wof:name":"Marathon Tire",
    "wof:placetype":"venue"
},
  "geometry": {"coordinates":[-77.530388,44.313946],"type":"Point"}
}