{
  "type": "Feature",
  "properties": {
    "iso:country":"CA",
    "sg:address":"282 Ottawa St N",
    "sg:city":"Hamilton",
    "sg:classifiers":[
        {
            "category":"Restaurant",
            "type":"Food & Drink"
        }
    ],
    "sg:phone":"+1 905 545 0352",
    "sg:postcode":"L8H 3Z9",
    "sg:province":"ON",
    "wof:name":"South Sea Restaurant",
    "wof:placetype":"venue"
},
  "geometry": {"coordinates":[-79.8165435791,43.2500076294],"type":"Point"}
}