{
  "type": "Feature",
  "properties": {
    "addr:full":"7605 Woodbine Ave # 12 Markham ON L3R 5V3",
    "addr:housenumber":"7605",
    "addr:postcode":"l3r 5v3",
    "addr:street":"Woodbine Ave # 12",
    "iso:country":"CA",
    "sg:address":"7605 Woodbine Ave # 12",
    "sg:city":"Markham",
    "sg:classifiers":[
        {
            "category":"Retail",
            "subcategory":"Auto Repair",
            "type":"Services"
        }
    ],
    "sg:phone":"+1 905 477 6157",
    "sg:postcode":"L3R 5V3",
    "sg:province":"ON",
    "sg:tags":[
        "repairing",
        "automobile"
    ],
    "wof:name":"J & F Auto Ctr",
    "wof:placetype":"venue"
},
  "geometry": {"coordinates":[-79.352242,43.828293],"type":"Point"}
}