{
  "type": "Feature",
  "properties": {
    "addr:full":"20407 Trans Canada Hwy Crapaud PE C0A 1J0",
    "addr:housenumber":"20407",
    "addr:postcode":"c0a 1j0",
    "addr:street":"Trans Canada Hwy",
    "iso:country":"CA",
    "sg:address":"20407 Trans Canada Hwy",
    "sg:city":"Crapaud",
    "sg:classifiers":[
        {
            "category":"Personal",
            "subcategory":"Beauty Salon",
            "type":"Services"
        }
    ],
    "sg:phone":"+1 902 658 2878",
    "sg:postcode":"C0A 1J0",
    "sg:province":"PE",
    "wof:name":"Salon 22",
    "wof:placetype":"venue"
},
  "geometry": {"coordinates":[-63.499088,46.235577],"type":"Point"}
}