{
  "type": "Feature",
  "properties": {
    "addr:full":"187 Rte Principale Saint-Jean-DE-Matha QC J0K 2S0",
    "addr:housenumber":"187",
    "addr:postcode":"j0k 2s0",
    "addr:street":"Rte Principale",
    "iso:country":"CA",
    "sg:address":"187 Rte Principale",
    "sg:city":"Saint-Jean-DE-Matha",
    "sg:classifiers":[
        {
            "category":"Retail",
            "subcategory":"Auto Repair",
            "type":"Services"
        }
    ],
    "sg:phone":"+1 450 886 3751",
    "sg:postcode":"J0K 2S0",
    "sg:province":"QC",
    "sg:tags":[
        "repairing",
        "automobile"
    ],
    "wof:name":"Garage Jacques Racine",
    "wof:placetype":"venue"
},
  "geometry": {"coordinates":[-73.5289764404,46.2263565063],"type":"Point"}
}