{
  "type": "Feature",
  "properties": {
    "addr:full":"10 River St Acton ON L7J 1C1",
    "addr:housenumber":"10",
    "addr:postcode":"l7j 1c1",
    "addr:street":"River St",
    "iso:country":"CA",
    "sg:address":"10 River St",
    "sg:city":"Acton",
    "sg:classifiers":[
        {
            "category":"Retail",
            "subcategory":"Animal Services",
            "type":"Services"
        }
    ],
    "sg:phone":"+1 519 853 2201",
    "sg:postcode":"L7J 1C1",
    "sg:province":"ON",
    "sg:tags":[
        "pet",
        "grooming",
        "washing"
    ],
    "wof:name":"Pet Junction",
    "wof:placetype":"venue"
},
  "geometry": {"coordinates":[-80.04357899999999,43.631477],"type":"Point"}
}