{
  "type": "Feature",
  "properties": {
    "addr:full":"1217 20 St Didsbury AB T0M 0W0",
    "addr:housenumber":"1217",
    "addr:postcode":"t0m 0w0",
    "addr:street":"20 St",
    "iso:country":"CA",
    "sg:address":"1217 20 St",
    "sg:city":"Didsbury",
    "sg:classifiers":[
        {
            "category":"Manufacturing",
            "subcategory":"Pet Food",
            "type":"Manufacturing & Wholesale Goods"
        }
    ],
    "sg:phone":"+1 403 335 8010",
    "sg:postcode":"T0M 0W0",
    "sg:province":"AB",
    "sg:tags":[
        "poultry",
        "bedding",
        "dog",
        "cat"
    ],
    "wof:name":"Masterfeeds",
    "wof:placetype":"venue"
},
  "geometry": {"coordinates":[-114.138008,51.654419],"type":"Point"}
}