{
  "type": "Feature",
  "properties": {
    "addr:full":"141 Morris Ave S Gladstone MB R0J 0T0",
    "addr:housenumber":"141",
    "addr:postcode":"r0j 0t0",
    "addr:street":"Morris Ave S",
    "iso:country":"CA",
    "sg:address":"141 Morris Ave S",
    "sg:city":"Gladstone",
    "sg:classifiers":[
        {
            "category":"Education",
            "subcategory":"School",
            "type":"Public Place"
        }
    ],
    "sg:phone":"+1 204 385 2845",
    "sg:postcode":"R0J 0T0",
    "sg:province":"MB",
    "wof:name":"William Morton Collegiate",
    "wof:placetype":"venue"
},
  "geometry": {"coordinates":[-98.95075199999999,50.225422],"type":"Point"}
}