{
  "type": "Feature",
  "properties": {
    "addr:full":"276 Restigouche Rd Oromocto NB E2V 2G9",
    "addr:housenumber":"276",
    "addr:postcode":"e2v 2g9",
    "addr:street":"Restigouche Rd",
    "iso:country":"CA",
    "sg:address":"276 Restigouche Rd",
    "sg:city":"Oromocto",
    "sg:classifiers":[
        {
            "category":"Retail",
            "subcategory":"Auto Repair",
            "type":"Services"
        }
    ],
    "sg:phone":"+1 506 357 9990",
    "sg:postcode":"E2V 2G9",
    "sg:province":"NB",
    "sg:tags":[
        "repairing",
        "automobile",
        "polishing",
        "washing",
        "car"
    ],
    "wof:name":"Oromocto Power Kleen Svc",
    "wof:placetype":"venue"
},
  "geometry": {"coordinates":[-66.500778,45.841812],"type":"Point"}
}