{
  "type": "Feature",
  "properties": {
    "addr:full":"PO Box 120 Whale Cove NU X0C 0J0",
    "addr:housenumber":"po",
    "addr:postcode":"x0c 0j0",
    "addr:street":"Box 120",
    "iso:country":"CA",
    "sg:address":"PO Box 120",
    "sg:city":"Whale Cove",
    "sg:classifiers":[
        {
            "category":"Government",
            "subcategory":"Office",
            "type":"Public Place"
        }
    ],
    "sg:phone":"+1 867 896 9045",
    "sg:postcode":"X0C 0J0",
    "sg:province":"NU",
    "sg:tags":[
        "village"
    ],
    "wof:name":"Whale Cove Foreman",
    "wof:placetype":"venue"
},
  "geometry": {"coordinates":[-92.580406,62.173222],"type":"Point"}
}