{
  "type": "Feature",
  "properties": {
    "addr:full":"47 Churchill Dr Barrie ON L4N 8Z5",
    "addr:housenumber":"47",
    "addr:postcode":"l4n 8z5",
    "addr:street":"Churchill Dr",
    "iso:country":"CA",
    "sg:address":"47 Churchill Dr",
    "sg:city":"Barrie",
    "sg:classifiers":[
        {
            "category":"Building & Trades",
            "subcategory":"Construction",
            "type":"Services"
        }
    ],
    "sg:phone":"+1 705 728 3736",
    "sg:postcode":"L4N 8Z5",
    "sg:province":"ON",
    "sg:tags":[
        "builder",
        "material",
        "patio",
        "deck"
    ],
    "wof:name":"Cozy Plastic Lumber Products",
    "wof:placetype":"venue"
},
  "geometry": {"coordinates":[-79.6739120483,44.3442344666],"type":"Point"}
}