{
  "type": "Feature",
  "properties": {
    "addr:full":"514 Bayfield St Barrie ON L4M 5A2",
    "addr:housenumber":"514",
    "addr:postcode":"l4m 5a2",
    "addr:street":"Bayfield St",
    "iso:country":"CA",
    "sg:address":"514 Bayfield St",
    "sg:city":"Barrie",
    "sg:classifiers":[
        {
            "category":"Home & Garden",
            "subcategory":"Home Furnishings",
            "type":"Retail Goods"
        }
    ],
    "sg:phone":"+1 705 728 5566",
    "sg:postcode":"L4M 5A2",
    "sg:province":"ON",
    "sg:tags":[
        "made",
        "consultant",
        "design",
        "decorator",
        "interior",
        "drapery"
    ],
    "wof:name":"Irvine Carpet One & Decor Ctr",
    "wof:placetype":"venue"
},
  "geometry": {"coordinates":[-79.7122497559,44.4144477844],"type":"Point"}
}