{
  "type": "Feature",
  "properties": {
    "addr:full":"Vernon BC V1T 7G7",
    "addr:postcode":"v1t 7g7",
    "iso:country":"CA",
    "sg:city":"Vernon",
    "sg:classifiers":[
        {
            "category":"Shopping",
            "subcategory":"Jewelry",
            "type":"Retail Goods"
        }
    ],
    "sg:phone":"+1 250 545 4418",
    "sg:postcode":"V1T 7G7",
    "sg:province":"BC",
    "sg:tags":[
        "jeweler"
    ],
    "wof:name":"Peoples Jewellers",
    "wof:placetype":"venue"
},
  "geometry": {"coordinates":[-119.266853,50.283592],"type":"Point"}
}