{
  "type": "Feature",
  "properties": {
    "addr:full":"1106 Chevrier Blvd Winnipeg MB R3T 1Y1",
    "addr:housenumber":"1106",
    "addr:postcode":"r3t 1y1",
    "addr:street":"Chevrier Blvd",
    "iso:country":"CA",
    "sg:address":"1106 Chevrier Blvd",
    "sg:city":"Winnipeg",
    "sg:classifiers":[
        {
            "category":"Retail",
            "subcategory":"Auto Repair",
            "type":"Services"
        }
    ],
    "sg:phone":"+1 204 475 7193",
    "sg:postcode":"R3T 1Y1",
    "sg:province":"MB",
    "sg:tags":[
        "body",
        "automobile",
        "painting"
    ],
    "wof:name":"Prelude Auto Body Ltd",
    "wof:placetype":"venue"
},
  "geometry": {"coordinates":[-97.1566314697,49.8300018311],"type":"Point"}
}