{
  "type": "Feature",
  "properties": {
    "addr:full":"PO Box 324 Rainbow Lake AB T0H 2Y0",
    "addr:housenumber":"po",
    "addr:postcode":"t0h 2y0",
    "addr:street":"Box 324 Rainbow",
    "iso:country":"CA",
    "sg:address":"PO Box 324",
    "sg:city":"Rainbow Lake",
    "sg:classifiers":[
        {
            "category":"Organizations",
            "subcategory":"Religious Organization",
            "type":"Services"
        }
    ],
    "sg:phone":"+1 403 956 3389",
    "sg:postcode":"T0H 2Y0",
    "sg:province":"AB",
    "sg:tags":[
        "church"
    ],
    "wof:name":"Rainbow Lake Christian Flshp",
    "wof:placetype":"venue"
},
  "geometry": {"coordinates":[-119.410248,58.499573],"type":"Point"}
}