{
  "type": "Feature",
  "properties": {
    "addr:full":"40 Elgin St E Princeton ON N0J 1V0",
    "addr:housenumber":"40",
    "addr:postcode":"n0j 1v0",
    "addr:street":"Elgin St E",
    "iso:country":"CA",
    "sg:address":"40 Elgin St E",
    "sg:city":"Princeton",
    "sg:classifiers":[
        {
            "category":"Education",
            "subcategory":"School",
            "type":"Public Place"
        }
    ],
    "sg:phone":"+1 519 458 4315",
    "sg:postcode":"N0J 1V0",
    "sg:province":"ON",
    "wof:name":"Princeton Central School",
    "wof:placetype":"venue"
},
  "geometry": {"coordinates":[-80.5261383057,43.1702804565],"type":"Point"}
}