{
  "type": "Feature",
  "properties": {
    "addr:full":"332 Yonge St Toronto ON M5B 1R8",
    "addr:housenumber":"332",
    "addr:postcode":"m5b 1r8",
    "addr:street":"Yonge St",
    "iso:country":"CA",
    "sg:address":"332 Yonge St",
    "sg:city":"Toronto",
    "sg:classifiers":[
        {
            "category":"Shopping",
            "subcategory":"Shoes",
            "type":"Retail Goods"
        }
    ],
    "sg:phone":"+1 416 596 1390",
    "sg:postcode":"M5B 1R8",
    "sg:province":"ON",
    "wof:name":"Aldo Shoes",
    "wof:placetype":"venue"
},
  "geometry": {"coordinates":[-79.381401,43.657326],"type":"Point"}
}