{
  "type": "Feature",
  "properties": {
    "addr:full":"7010 Rue Marconi Montreal QC H2S 3K1",
    "addr:housenumber":"7010",
    "addr:postcode":"h2s 3k1",
    "addr:street":"Rue Marconi",
    "iso:country":"CA",
    "sg:address":"7010 Rue Marconi",
    "sg:city":"Montreal",
    "sg:classifiers":[
        {
            "category":"Retail",
            "subcategory":"Auto Repair",
            "type":"Services"
        }
    ],
    "sg:phone":"+1 514 276 1034",
    "sg:postcode":"H2S 3K1",
    "sg:province":"QC",
    "sg:tags":[
        "repairing",
        "automobile"
    ],
    "wof:name":"Electron Auto Engineers",
    "wof:placetype":"venue"
},
  "geometry": {"coordinates":[-73.618225,45.530899],"type":"Point"}
}