{
  "type": "Feature",
  "properties": {
    "iso:country":"CA",
    "sg:address":"1419 Grande Allee St",
    "sg:city":"Lachenaie",
    "sg:classifiers":[
        {
            "category":"Health Services",
            "subcategory":"Doctor",
            "type":"Services"
        }
    ],
    "sg:phone":"+1 450 471 7066",
    "sg:postcode":"J6W 5M9",
    "sg:province":"QC",
    "sg:tags":[
        "clinic"
    ],
    "wof:name":"Urgence Medicale Grande Allee",
    "wof:placetype":"venue"
},
  "geometry": {"coordinates":[-73.6223526001,45.7077980042],"type":"Point"}
}