{
  "type": "Feature",
  "properties": {
    "addr:full":"33 5th St E Cornwall ON K6H 2L5",
    "addr:housenumber":"33",
    "addr:postcode":"k6h 2l5",
    "addr:street":"5Th St E",
    "iso:country":"CA",
    "sg:address":"33 5th St E",
    "sg:city":"Cornwall",
    "sg:classifiers":[
        {
            "category":"Health Services",
            "subcategory":"Doctor",
            "type":"Services"
        }
    ],
    "sg:phone":"+1 613 936 2106",
    "sg:postcode":"K6H 2L5",
    "sg:province":"ON",
    "sg:tags":[
        "physician",
        "surgeon"
    ],
    "wof:name":"Carson, Leigh MD",
    "wof:placetype":"venue"
},
  "geometry": {"coordinates":[-74.730591,45.023075],"type":"Point"}
}