{
  "type": "Feature",
  "properties": {
    "iso:country":"CA",
    "sg:city":"Baie-Saint-Paul",
    "sg:classifiers":[
        {
            "category":"Shopping",
            "subcategory":"Jewelry",
            "type":"Retail Goods"
        }
    ],
    "sg:phone":"+1 418 435 2237",
    "sg:postcode":"G3Z 2Y5",
    "sg:province":"QC",
    "sg:tags":[
        "jeweler"
    ],
    "wof:name":"Bijouterie Rayon D'Or",
    "wof:placetype":"venue"
},
  "geometry": {"coordinates":[-70.51750183110001,47.4475288391],"type":"Point"}
}