{
  "type": "Feature",
  "properties": {
    "addr:full":"1257 Michigan Ave Sarnia ON N7S 3Y3",
    "addr:housenumber":"1257",
    "addr:postcode":"n7s 3y3",
    "addr:street":"Michigan Ave",
    "iso:country":"CA",
    "sg:address":"1257 Michigan Ave",
    "sg:city":"Sarnia",
    "sg:classifiers":[
        {
            "category":"Education",
            "subcategory":"School",
            "type":"Public Place"
        }
    ],
    "sg:phone":"+1 519 542 5505",
    "sg:postcode":"N7S 3Y3",
    "sg:province":"ON",
    "wof:name":"Alexander Mac Kenzie Secondary",
    "wof:placetype":"venue"
},
  "geometry": {"coordinates":[-82.360893,43.000015],"type":"Point"}
}