{
  "type": "Feature",
  "properties": {
    "addr:full":"1022 Pembina Hwy Winnipeg MB R3T 1Z7",
    "addr:housenumber":"1022",
    "addr:postcode":"r3t 1z7",
    "addr:street":"Pembina Hwy",
    "iso:country":"CA",
    "sg:address":"1022 Pembina Hwy",
    "sg:city":"Winnipeg",
    "sg:classifiers":[
        {
            "category":"Travel",
            "subcategory":"Hotels & Motels",
            "type":"Entertainment"
        }
    ],
    "sg:phone":"+1 204 284 0183",
    "sg:postcode":"R3T 1Z7",
    "sg:province":"MB",
    "wof:name":"Cambridge Hotel",
    "wof:placetype":"venue"
},
  "geometry": {"coordinates":[-97.1520767212,49.8509712219],"type":"Point"}
}