{
  "type": "Feature",
  "properties": {
    "iso:country":"CA",
    "sg:address":"340 Spruce St S",
    "sg:city":"Timmins",
    "sg:classifiers":[
        {
            "category":"Autos & Motor Vehicles",
            "subcategory":"Auto Supplies",
            "type":"Retail Goods"
        }
    ],
    "sg:phone":"+1 705 268 2307",
    "sg:postcode":"P4N 2M9",
    "sg:province":"ON",
    "sg:tags":[
        "automobile",
        "parts"
    ],
    "wof:name":"Timmins Automotive Ltd",
    "wof:placetype":"venue"
},
  "geometry": {"coordinates":[-81.32698822019999,48.4692611694],"type":"Point"}
}