{
  "type": "Feature",
  "properties": {
    "addr:full":"137 Av Laurier O Montreal QC H2T 2N6",
    "addr:postcode":"h2t 2n6",
    "addr:street":"137 Av Laurier O",
    "iso:country":"CA",
    "sg:address":"137 Av Laurier O",
    "sg:city":"Montreal",
    "sg:classifiers":[
        {
            "category":"Shopping",
            "subcategory":"Jewelry",
            "type":"Retail Goods"
        }
    ],
    "sg:phone":"+1 514 840 9362",
    "sg:postcode":"H2T 2N6",
    "sg:province":"QC",
    "sg:tags":[
        "art",
        "gallery",
        "dealer"
    ],
    "wof:name":"Galerie N Guyomarc'h Bijoux",
    "wof:placetype":"venue"
},
  "geometry": {"coordinates":[-73.59198000000001,45.52425],"type":"Point"}
}