{
  "type": "Feature",
  "properties": {
    "addr:full":"2628 Yonge St Toronto ON M4P 2J4",
    "addr:housenumber":"2628",
    "addr:postcode":"m4p 2j4",
    "addr:street":"Yonge St",
    "iso:country":"CA",
    "sg:address":"2628 Yonge St",
    "sg:city":"Toronto",
    "sg:classifiers":[
        {
            "category":"Shopping",
            "subcategory":"Discount & Variety Stores",
            "type":"Retail Goods"
        }
    ],
    "sg:phone":"+1 416 487 9792",
    "sg:postcode":"M4P 2J4",
    "sg:province":"ON",
    "wof:name":"Yonge Gift & Variety Store",
    "wof:placetype":"venue"
},
  "geometry": {"coordinates":[-79.400284,43.71537],"type":"Point"}
}