{
  "type": "Feature",
  "properties": {
    "iso:country":"CA",
    "sg:address":"2024 Dufferin Ave",
    "sg:city":"Wallaceburg",
    "sg:classifiers":[
        {
            "category":"Freight",
            "type":"Transportation"
        }
    ],
    "sg:phone":"+1 519 627 8063",
    "sg:postcode":"N8A 4M4",
    "sg:province":"ON",
    "sg:tags":[
        "trucking"
    ],
    "wof:name":"Landstar Ranger",
    "wof:placetype":"venue"
},
  "geometry": {"coordinates":[-82.4249038696,42.5937004089],"type":"Point"}
}