{
  "type": "Feature",
  "properties": {
    "iso:country":"CA",
    "sg:address":"1706 Dundas St E",
    "sg:city":"Mississauga",
    "sg:classifiers":[
        {
            "category":"Shopping",
            "subcategory":"Books",
            "type":"Retail Goods"
        }
    ],
    "sg:phone":"+1 905 279 6055",
    "sg:postcode":"L4X 1L7",
    "sg:province":"ON",
    "sg:tags":[
        "dealer"
    ],
    "wof:name":"Mississauga Computer Books",
    "wof:placetype":"venue"
},
  "geometry": {"coordinates":[-79.57633972169999,43.6159706116],"type":"Point"}
}