{
  "type": "Feature",
  "properties": {
    "iso:country":"CA",
    "sg:address":"12 Bannockburn Ave",
    "sg:city":"North York",
    "sg:classifiers":[
        {
            "category":"Organizations",
            "subcategory":"Professional Association",
            "type":"Services"
        }
    ],
    "sg:phone":"+1 416 785 0430",
    "sg:postcode":"M5M 2M8",
    "sg:province":"ON",
    "sg:tags":[
        "club"
    ],
    "wof:name":"North York Aquatic Club",
    "wof:placetype":"venue"
},
  "geometry": {"coordinates":[-79.42231750489999,43.7336654663],"type":"Point"}
}