{
  "type": "Feature",
  "properties": {
    "addr:full":"Canoe Lake Km 14 Huntsville ON P1H 2H4",
    "addr:postcode":"p1h 2h4",
    "addr:street":"Canoe Lake Km 14",
    "iso:country":"CA",
    "sg:address":"Canoe Lake Km 14",
    "sg:city":"Huntsville",
    "sg:classifiers":[
        {
            "category":"Recreation",
            "type":"Entertainment"
        }
    ],
    "sg:phone":"+1 705 633 5622",
    "sg:postcode":"P1H 2H4",
    "sg:province":"ON",
    "sg:tags":[
        "outfitter",
        "trip",
        "canoe"
    ],
    "wof:name":"Portage Store",
    "wof:placetype":"venue"
},
  "geometry": {"coordinates":[-79.2180023193,45.3265647888],"type":"Point"}
}