{
  "type": "Feature",
  "properties": {
    "addr:full":"50 Diefenbaker Dr Moose Jaw SK S6J 1L9",
    "addr:housenumber":"50",
    "addr:postcode":"s6j 1l9",
    "addr:street":"Diefenbaker Dr",
    "iso:country":"CA",
    "sg:address":"50 Diefenbaker Dr",
    "sg:city":"Moose Jaw",
    "sg:classifiers":[
        {
            "category":"Museum",
            "type":"Entertainment"
        }
    ],
    "sg:phone":"+1 306 693 6556",
    "sg:postcode":"S6J 1L9",
    "sg:province":"SK",
    "wof:name":"Western Development Museum",
    "wof:placetype":"venue"
},
  "geometry": {"coordinates":[-105.51855500000001,50.419109],"type":"Point"}
}