{
  "type": "Feature",
  "properties": {
    "addr:full":"2770 Cote Richelieu Trois-Rivieres-Ouest QC G8Z 3Y5",
    "addr:postcode":"2770;g8z 3y5",
    "addr:street":"Cote Richelieu Trois-Rivieres-Ouest",
    "iso:country":"CA",
    "sg:address":"2770 Cote Richelieu",
    "sg:city":"Trois-Rivieres-Ouest",
    "sg:classifiers":[
        {
            "category":"Food & Beverages",
            "subcategory":"Specialty",
            "type":"Retail Goods"
        }
    ],
    "sg:phone":"+1 819 378 6471",
    "sg:postcode":"G8Z 3Y5",
    "sg:province":"QC",
    "sg:tags":[
        "water",
        "bulk"
    ],
    "wof:name":"Vapor'o Pure",
    "wof:placetype":"venue"
},
  "geometry": {"coordinates":[-72.59326934809999,46.3322525024],"type":"Point"}
}