{
  "type": "Feature",
  "properties": {
    "addr:full":"Cornwall ON K6H 1N9",
    "addr:postcode":"k6h 1n9",
    "iso:country":"CA",
    "sg:city":"Cornwall",
    "sg:classifiers":[
        {
            "category":"Wholesale",
            "subcategory":"Meat",
            "type":"Manufacturing & Wholesale Goods"
        }
    ],
    "sg:phone":"+1 613 932 1990",
    "sg:postcode":"K6H 1N9",
    "sg:province":"ON",
    "sg:tags":[
        "butchering"
    ],
    "wof:name":"Moise Red & White",
    "wof:placetype":"venue"
},
  "geometry": {"coordinates":[-74.73569500000001,45.028435],"type":"Point"}
}