{
  "type": "Feature",
  "properties": {
    "addr:full":"555 Mckeown Ave North Bay ON P1B 9E4",
    "addr:housenumber":"555",
    "addr:postcode":"p1b 9e4",
    "addr:street":"Mckeown Ave",
    "iso:country":"CA",
    "sg:address":"555 Mckeown Ave",
    "sg:city":"North Bay",
    "sg:classifiers":[
        {
            "category":"Food & Beverages",
            "subcategory":"Groceries & Convenience Stores",
            "type":"Retail Goods"
        }
    ],
    "sg:phone":"+1 705 476 8813",
    "sg:postcode":"P1B 9E4",
    "sg:province":"ON",
    "wof:name":"Lucky 13",
    "wof:placetype":"venue"
},
  "geometry": {"coordinates":[-79.48221599999999,46.332603],"type":"Point"}
}