{
  "type": "Feature",
  "properties": {
    "addr:full":"1980 Queen St E Toronto ON M4L 1J2",
    "addr:housenumber":"1980",
    "addr:postcode":"m4l 1j2",
    "addr:street":"Queen St E",
    "iso:country":"CA",
    "sg:address":"1980 Queen St E",
    "sg:city":"Toronto",
    "sg:classifiers":[
        {
            "category":"Restaurant",
            "type":"Food & Drink"
        }
    ],
    "sg:phone":"+1 416 690 3838",
    "sg:postcode":"M4L 1J2",
    "sg:province":"ON",
    "wof:name":"Mr Greek Mediterranean Grill",
    "wof:placetype":"venue"
},
  "geometry": {"coordinates":[-79.300758,43.669975],"type":"Point"}
}