{
  "type": "Feature",
  "properties": {
    "addr:full":"307 Hamilton Ave St. John's NL A1E 1J8",
    "addr:housenumber":"307",
    "addr:postcode":"a1e 1j8",
    "addr:street":"Hamilton Ave",
    "iso:country":"CA",
    "sg:address":"307 Hamilton Ave",
    "sg:city":"St. John's",
    "sg:classifiers":[
        {
            "category":"Retail",
            "subcategory":"Laundry & Dry Cleaning",
            "type":"Services"
        }
    ],
    "sg:phone":"+1 709 579 7837",
    "sg:postcode":"A1E 1J8",
    "sg:province":"NL",
    "wof:name":"Super Suds",
    "wof:placetype":"venue"
},
  "geometry": {"coordinates":[-52.727177,47.549664],"type":"Point"}
}