{
  "type": "Feature",
  "properties": {
    "iso:country":"CA",
    "sg:city":"Markham",
    "sg:classifiers":[
        {
            "category":"Manufacturing",
            "subcategory":"Tools & Machinery",
            "type":"Manufacturing & Wholesale Goods"
        }
    ],
    "sg:phone":"+1 905 474 9144",
    "sg:postcode":"L3R 4L9",
    "sg:province":"ON",
    "sg:tags":[
        "machine",
        "shop"
    ],
    "wof:name":"Torrovap Industries Inc",
    "wof:placetype":"venue"
},
  "geometry": {"coordinates":[-79.355972,43.823906],"type":"Point"}
}