{
  "type": "Feature",
  "properties": {
    "addr:full":"1867 Ch Sainte-Angelique Saint-Lazare QC J7T 2X9",
    "addr:postcode":"1867;j7t 2x9",
    "addr:street":"Ch Sainte-Angelique",
    "iso:country":"CA",
    "sg:address":"1867 Ch Sainte-Angelique",
    "sg:city":"Saint-Lazare",
    "sg:classifiers":[
        {
            "category":"Retail",
            "subcategory":"Laundry & Dry Cleaning",
            "type":"Services"
        }
    ],
    "sg:phone":"+1 450 455 1057",
    "sg:postcode":"J7T 2X9",
    "sg:province":"QC",
    "sg:tags":[
        "cleaners"
    ],
    "wof:name":"Nettoyeur Maxi",
    "wof:placetype":"venue"
},
  "geometry": {"coordinates":[-74.138977,45.400108],"type":"Point"}
}