{
  "type": "Feature",
  "properties": {
    "iso:country":"CA",
    "sg:city":"Abbotsford",
    "sg:classifiers":[
        {
            "category":"Health Services",
            "subcategory":"Medical Lab",
            "type":"Services"
        }
    ],
    "sg:phone":"+1 604 859 4888",
    "sg:postcode":"V2S 3N8",
    "sg:province":"BC",
    "sg:tags":[
        "clinic"
    ],
    "wof:name":"X-Ray Clinic",
    "wof:placetype":"venue"
},
  "geometry": {"coordinates":[-122.293434143,49.0408592224],"type":"Point"}
}