{
  "type": "Feature",
  "properties": {
    "iso:country":"CA",
    "sg:city":"Richmond",
    "sg:classifiers":[
        {
            "category":"Restaurant",
            "type":"Food & Drink"
        }
    ],
    "sg:phone":"+1 604 273 3500",
    "sg:postcode":"V6X 1A7",
    "sg:province":"BC",
    "wof:name":"I Love Sushi",
    "wof:placetype":"venue"
},
  "geometry": {"coordinates":[-123.133034,49.17033],"type":"Point"}
}