{
  "type": "Feature",
  "properties": {
    "addr:full":"295 Wellington St Bracebridge ON P1L 1P3",
    "addr:housenumber":"295",
    "addr:postcode":"p1l 1p3",
    "addr:street":"Wellington St",
    "iso:country":"CA",
    "sg:address":"295 Wellington St",
    "sg:city":"Bracebridge",
    "sg:classifiers":[
        {
            "category":"Restaurant",
            "type":"Food & Drink"
        }
    ],
    "sg:phone":"+1 705 645 4580",
    "sg:postcode":"P1L 1P3",
    "sg:province":"ON",
    "wof:name":"Wellington Fish & Chips Ltd",
    "wof:placetype":"venue"
},
  "geometry": {"coordinates":[-79.319298,45.039234],"type":"Point"}
}