{
  "type": "Feature",
  "properties": {
    "iso:country":"CA",
    "sg:address":"8228 River Way",
    "sg:city":"Delta",
    "sg:classifiers":[
        {
            "category":"Manufacturing",
            "subcategory":"Tools & Machinery",
            "type":"Manufacturing & Wholesale Goods"
        }
    ],
    "sg:phone":"+1 604 952 6664",
    "sg:postcode":"V4G 1C4",
    "sg:province":"BC",
    "sg:tags":[
        "machine",
        "shop"
    ],
    "wof:name":"Richmond Machine Works Ltd",
    "wof:placetype":"venue"
},
  "geometry": {"coordinates":[-122.995537,49.145657],"type":"Point"}
}