{
  "type": "Feature",
  "properties": {
    "iso:country":"CA",
    "sg:address":"35 Coronet Rd",
    "sg:city":"Etobicoke",
    "sg:classifiers":[
        {
            "category":"Freight",
            "type":"Transportation"
        }
    ],
    "sg:phone":"+1 416 239 2991",
    "sg:postcode":"M8Z 2L8",
    "sg:province":"ON",
    "sg:tags":[
        "mover",
        "trucking"
    ],
    "wof:name":"AAA Collins & Greig Cartage",
    "wof:placetype":"venue"
},
  "geometry": {"coordinates":[-79.548431,43.622875],"type":"Point"}
}