{
  "type": "Feature",
  "properties": {
    "addr:full":"113 3rd Ave W Melville SK S0A 2P0",
    "addr:housenumber":"113",
    "addr:postcode":"s0a 2p0",
    "addr:street":"3Rd Ave W",
    "iso:country":"CA",
    "sg:address":"113 3rd Ave W",
    "sg:city":"Melville",
    "sg:classifiers":[
        {
            "category":"Shopping",
            "subcategory":"Computers & Home Electronics",
            "type":"Retail Goods"
        }
    ],
    "sg:phone":"+1 306 728 5650",
    "sg:postcode":"S0A 2P0",
    "sg:province":"SK",
    "sg:tags":[
        "equipment",
        "dealer"
    ],
    "wof:name":"Care Tek Computers",
    "wof:placetype":"venue"
},
  "geometry": {"coordinates":[-102.816093,50.931126],"type":"Point"}
}