{
  "type": "Feature",
  "properties": {
    "addr:full":"Calgary AB T2E 6L1",
    "addr:postcode":"t2e 6l1",
    "iso:country":"CA",
    "sg:city":"Calgary",
    "sg:classifiers":[
        {
            "category":"Wholesale",
            "subcategory":"Machinery & Supplies",
            "type":"Manufacturing & Wholesale Goods"
        }
    ],
    "sg:phone":"+1 403 250 7514",
    "sg:postcode":"T2E 6L1",
    "sg:province":"AB",
    "sg:tags":[
        "concrete",
        "equipment"
    ],
    "wof:name":"C & H Concrete Forming Sys Ltd",
    "wof:placetype":"venue"
},
  "geometry": {"coordinates":[-114.02986900000001,51.08886],"type":"Point"}
}