{
  "type": "Feature",
  "properties": {
    "addr:full":"Scarborough ON M1V 2N3",
    "addr:postcode":"m1v 2n3",
    "iso:country":"CA",
    "sg:city":"Scarborough",
    "sg:classifiers":[
        {
            "category":"Wholesale",
            "subcategory":"Fruits & Vegetables",
            "type":"Manufacturing & Wholesale Goods"
        }
    ],
    "sg:phone":"+1 416 412 7788",
    "sg:postcode":"M1V 2N3",
    "sg:province":"ON",
    "wof:name":"Ever Fortune Specialty Inc",
    "wof:placetype":"venue"
},
  "geometry": {"coordinates":[-79.251007,43.823204],"type":"Point"}
}