{
  "type": "Feature",
  "properties": {
    "iso:country":"CA",
    "sg:address":"166 Metcalfe St S",
    "sg:city":"Simcoe",
    "sg:classifiers":[
        {
            "category":"Manufacturing",
            "subcategory":"Printing",
            "type":"Manufacturing & Wholesale Goods"
        }
    ],
    "sg:phone":"+1 519 426 1393",
    "sg:postcode":"N3Y 3C2",
    "sg:province":"ON",
    "sg:tags":[
        "printer"
    ],
    "wof:name":"Morris Printing Svc",
    "wof:placetype":"venue"
},
  "geometry": {"coordinates":[-80.3089981079,42.8324966431],"type":"Point"}
}