{
  "type": "Feature",
  "properties": {
    "addr:full":"4500 Fountain Dr Red Deer AB T4N 6W8",
    "addr:housenumber":"4500",
    "addr:postcode":"t4n 6w8",
    "addr:street":"Fountain Dr",
    "iso:country":"CA",
    "sg:address":"4500 Fountain Dr",
    "sg:city":"Red Deer",
    "sg:classifiers":[
        {
            "category":"Shopping",
            "subcategory":"Bicycles & Sporting Goods",
            "type":"Retail Goods"
        }
    ],
    "sg:phone":"+1 403 340 4461",
    "sg:postcode":"T4N 6W8",
    "sg:province":"AB",
    "sg:tags":[
        "equipment",
        "golf",
        "supply"
    ],
    "wof:name":"Ken Frame Golf Sales",
    "wof:placetype":"venue"
},
  "geometry": {"coordinates":[-113.83731842,52.2639122009],"type":"Point"}
}