{
  "type": "Feature",
  "properties": {
    "addr:full":"Sherbrooke QC J1H 5B9",
    "addr:postcode":"j1h 5b9",
    "iso:country":"CA",
    "sg:city":"Sherbrooke",
    "sg:classifiers":[
        {
            "category":"Professional",
            "subcategory":"Lawyer & Legal Services",
            "type":"Services"
        }
    ],
    "sg:phone":"+1 819 563 6565",
    "sg:postcode":"J1H 5B9",
    "sg:province":"QC",
    "sg:tags":[
        "attorney"
    ],
    "wof:name":"Walsh, Thomas",
    "wof:placetype":"venue"
},
  "geometry": {"coordinates":[-71.89193,45.403599],"type":"Point"}
}