{
  "type": "Feature",
  "properties": {
    "addr:full":"820 N 10th Ave Golden BC V0A 1H0",
    "addr:housenumber":"820",
    "addr:postcode":"v0a 1h0",
    "addr:street":"N 10Th Ave",
    "iso:country":"CA",
    "sg:address":"820 N 10th Ave",
    "sg:city":"Golden",
    "sg:phone":"+1 250 344 6161",
    "sg:postcode":"V0A 1H0",
    "sg:province":"BC",
    "sg:tags":[
        "oil"
    ],
    "wof:name":"Petro-Canada",
    "wof:placetype":"venue"
},
  "geometry": {"coordinates":[-116.968727112,51.3036003113],"type":"Point"}
}