{
  "type": "Feature",
  "properties": {
    "addr:full":"Terrenceville NL A0E 2X0",
    "iso:country":"CA",
    "sg:city":"Terrenceville",
    "sg:classifiers":[
        {
            "category":"Organizations",
            "subcategory":"Professional Association",
            "type":"Services"
        }
    ],
    "sg:phone":"+1 709 662 2078",
    "sg:postcode":"A0E 2X0",
    "sg:province":"NL",
    "sg:tags":[
        "club"
    ],
    "wof:name":"Terrenceville Lions Club",
    "wof:placetype":"venue"
},
  "geometry": {"coordinates":[-54.7206268311,47.6625671387],"type":"Point"}
}