{
  "type": "Feature",
  "properties": {
    "addr:full":"214 Furnival Rd Rodney ON N0L 2C0",
    "addr:housenumber":"214",
    "addr:postcode":"n0l 2c0",
    "addr:street":"Furnival Rd",
    "iso:country":"CA",
    "sg:address":"214 Furnival Rd",
    "sg:city":"Rodney",
    "sg:classifiers":[
        {
            "category":"Food & Beverages",
            "subcategory":"Groceries & Convenience Stores",
            "type":"Retail Goods"
        }
    ],
    "sg:phone":"+1 519 785 0741",
    "sg:postcode":"N0L 2C0",
    "sg:province":"ON",
    "sg:tags":[
        "variety"
    ],
    "wof:name":"Gigi's Variety",
    "wof:placetype":"venue"
},
  "geometry": {"coordinates":[-81.6815032959,42.5665969849],"type":"Point"}
}