{
  "type": "Feature",
  "properties": {
    "addr:full":"1765 Boul Saint-Martin O Laval QC H7S 1N2",
    "addr:housenumber":"1765",
    "addr:postcode":"h7s 1n2",
    "addr:street":"Boul Saint-Martin O",
    "iso:country":"CA",
    "sg:address":"1765 Boul Saint-Martin O",
    "sg:city":"Laval",
    "sg:classifiers":[
        {
            "category":"Personal",
            "type":"Services"
        }
    ],
    "sg:phone":"+1 450 688 5270",
    "sg:postcode":"H7S 1N2",
    "sg:province":"QC",
    "sg:tags":[
        "electrolysis"
    ],
    "wof:name":"Esthetique Nathalie Nepveu",
    "wof:placetype":"venue"
},
  "geometry": {"coordinates":[-73.72953800000001,45.567242],"type":"Point"}
}