{
  "type": "Feature",
  "properties": {
    "iso:country":"CA",
    "sg:address":"163 First St",
    "sg:city":"Orangeville",
    "sg:classifiers":[
        {
            "category":"Shopping",
            "subcategory":"Clothing, Apparel, & Fashions",
            "type":"Retail Goods"
        }
    ],
    "sg:phone":"+1 519 940 9416",
    "sg:postcode":"L9W 3J8",
    "sg:province":"ON",
    "sg:tags":[
        "jean"
    ],
    "wof:name":"Body Graphics",
    "wof:placetype":"venue"
},
  "geometry": {"coordinates":[-80.100548,43.93243],"type":"Point"}
}