{
  "type": "Feature",
  "properties": {
    "iso:country":"CA",
    "sg:address":"2651 Carlisle Way",
    "sg:city":"Prince George",
    "sg:classifiers":[
        {
            "category":"Building & Trades",
            "subcategory":"Plumbing",
            "type":"Services"
        }
    ],
    "sg:phone":"+1 250 962 6306",
    "sg:postcode":"V2K 4B5",
    "sg:province":"BC",
    "sg:tags":[
        "contractor"
    ],
    "wof:name":"Ozborne Mechanical",
    "wof:placetype":"venue"
},
  "geometry": {"coordinates":[-122.790031433,53.9709243774],"type":"Point"}
}