{
  "type": "Feature",
  "properties": {
    "addr:full":"Calgary AB T2A 6R3",
    "addr:postcode":"t2a 6r3",
    "iso:country":"CA",
    "sg:city":"Calgary",
    "sg:classifiers":[
        {
            "category":"Mining & Drilling",
            "type":"Manufacturing & Wholesale Goods"
        }
    ],
    "sg:phone":"+1 403 272 0703",
    "sg:postcode":"T2A 6R3",
    "sg:province":"AB",
    "sg:tags":[
        "consultant",
        "oil",
        "gas",
        "field"
    ],
    "wof:name":"Remedy Energy Svc Inc",
    "wof:placetype":"venue"
},
  "geometry": {"coordinates":[-113.99308000000001,51.0583],"type":"Point"}
}