{
  "type": "Feature",
  "properties": {
    "iso:country":"CA",
    "sg:address":"170 Notre-Dame",
    "sg:city":"Philipsburg",
    "sg:classifiers":[
        {
            "category":"Government",
            "subcategory":"Office",
            "type":"Public Place"
        }
    ],
    "sg:phone":"+1 450 248 2759",
    "sg:postcode":"J0J 1N0",
    "sg:province":"QC",
    "sg:tags":[
        "village"
    ],
    "wof:name":"Philipsburg Garage Municipal",
    "wof:placetype":"venue"
},
  "geometry": {"coordinates":[-73.0748748779,45.0448188782],"type":"Point"}
}