{
  "type": "Feature",
  "properties": {
    "addr:full":"355 Boul Samson Laval QC H7X 2Z7",
    "addr:housenumber":"355",
    "addr:postcode":"h7x 2z7",
    "addr:street":"Boul Samson",
    "iso:country":"CA",
    "sg:address":"355 Boul Samson",
    "sg:city":"Laval",
    "sg:classifiers":[
        {
            "category":"Restaurant",
            "type":"Food & Drink"
        }
    ],
    "sg:phone":"+1 450 969 5840",
    "sg:postcode":"H7X 2Z7",
    "sg:province":"QC",
    "wof:name":"Subway Sandwiches & Salads",
    "wof:placetype":"venue"
},
  "geometry": {"coordinates":[-73.8030166626,45.5240211487],"type":"Point"}
}