{
  "type": "Feature",
  "properties": {
    "iso:country":"CA",
    "sg:address":"1635 Laval Aut W",
    "sg:city":"Laval",
    "sg:classifiers":[
        {
            "category":"Building & Trades",
            "subcategory":"Construction",
            "type":"Services"
        }
    ],
    "sg:phone":"+1 450 973 6369",
    "sg:postcode":"H7L 3W3",
    "sg:province":"QC",
    "sg:tags":[
        "tile",
        "dealer"
    ],
    "wof:name":"Importations Dek-Kor Ceramique",
    "wof:placetype":"venue"
},
  "geometry": {"coordinates":[-73.744637,45.551567],"type":"Point"}
}