{
  "type": "Feature",
  "properties": {
    "addr:full":"Coquitlam BC V3B 1A1",
    "addr:postcode":"v3b 1a1",
    "iso:country":"CA",
    "sg:city":"Coquitlam",
    "sg:classifiers":[
        {
            "category":"Building & Trades",
            "subcategory":"Plumbing",
            "type":"Services"
        }
    ],
    "sg:phone":"+1 604 464 1514",
    "sg:postcode":"V3B 1A1",
    "sg:province":"BC",
    "sg:tags":[
        "heating",
        "contractor"
    ],
    "wof:name":"Efficient Heating Ltd",
    "wof:placetype":"venue"
},
  "geometry": {"coordinates":[-122.796448,49.273319],"type":"Point"}
}