{
  "type": "Feature",
  "properties": {
    "addr:full":"10 Clarence St W Port Colborne ON L3K 3E8",
    "addr:housenumber":"10",
    "addr:postcode":"l3k 3e8",
    "addr:street":"Clarence St W",
    "iso:country":"CA",
    "sg:address":"10 Clarence St W",
    "sg:city":"Port Colborne",
    "sg:classifiers":[
        {
            "category":"Shopping",
            "subcategory":"Jewelry",
            "type":"Retail Goods"
        }
    ],
    "sg:phone":"+1 905 834 3823",
    "sg:postcode":"L3K 3E8",
    "sg:province":"ON",
    "sg:tags":[
        "jeweler"
    ],
    "wof:name":"Tuck Jewellers Ltd",
    "wof:placetype":"venue"
},
  "geometry": {"coordinates":[-79.250435,42.886131],"type":"Point"}
}