{
  "type": "Feature",
  "properties": {
    "addr:full":"5899 123A St Surrey BC V3X 1Y3",
    "addr:housenumber":"5899",
    "addr:postcode":"v3x 1y3",
    "addr:street":"123A St",
    "iso:country":"CA",
    "sg:address":"5899 123A St",
    "sg:city":"Surrey",
    "sg:classifiers":[
        {
            "category":"Freight",
            "type":"Transportation"
        }
    ],
    "sg:phone":"+1 604 599 1569",
    "sg:postcode":"V3X 1Y3",
    "sg:province":"BC",
    "sg:tags":[
        "trucking"
    ],
    "wof:name":"Amrit Transportation Systems",
    "wof:placetype":"venue"
},
  "geometry": {"coordinates":[-122.830215,49.105179],"type":"Point"}
}