{
  "type": "Feature",
  "properties": {
    "iso:country":"CA",
    "sg:address":"4492 Rue DE Namur",
    "sg:city":"Pierrefonds",
    "sg:classifiers":[
        {
            "category":"Shopping",
            "subcategory":"Computers & Home Electronics",
            "type":"Retail Goods"
        }
    ],
    "sg:phone":"+1 514 620 6823",
    "sg:postcode":"H9A 2S1",
    "sg:province":"QC",
    "sg:tags":[
        "equipment",
        "dealer"
    ],
    "wof:name":"Datalogic Inc",
    "wof:placetype":"venue"
},
  "geometry": {"coordinates":[-73.838303,45.498627],"type":"Point"}
}