{
  "type": "Feature",
  "properties": {
    "addr:full":"89 Matheson Ave E Winnipeg MB R2W 0C3",
    "addr:housenumber":"89",
    "addr:postcode":"r2w 0c3",
    "addr:street":"Matheson Ave E",
    "iso:country":"CA",
    "sg:address":"89 Matheson Ave E",
    "sg:city":"Winnipeg",
    "sg:classifiers":[
        {
            "category":"Wholesale",
            "subcategory":"Construction Materials",
            "type":"Manufacturing & Wholesale Goods"
        }
    ],
    "sg:phone":"+1 204 944 8288",
    "sg:postcode":"R2W 0C3",
    "sg:province":"MB",
    "sg:tags":[
        "pallet",
        "skid"
    ],
    "wof:name":"Custom Pallet",
    "wof:placetype":"venue"
},
  "geometry": {"coordinates":[-97.1162948608,49.9272384644],"type":"Point"}
}