{
  "type": "Feature",
  "properties": {
    "addr:full":"Invermere BC V0A 1K0",
    "addr:postcode":"v0a 1k0",
    "iso:country":"CA",
    "sg:city":"Invermere",
    "sg:classifiers":[
        {
            "category":"Professional",
            "subcategory":"Business Services",
            "type":"Services"
        }
    ],
    "sg:phone":"+1 250 342 9463",
    "sg:postcode":"V0A 1K0",
    "sg:province":"BC",
    "sg:tags":[
        "consultant",
        "design",
        "decorator",
        "interior",
        "curtain",
        "drapery"
    ],
    "wof:name":"Mc Craig's Interior Design",
    "wof:placetype":"venue"
},
  "geometry": {"coordinates":[-116.968079,51.295055],"type":"Point"}
}