{
  "type": "Feature",
  "properties": {
    "addr:full":"St. John's NL A1C 6G8",
    "addr:postcode":"a1c 6g8",
    "iso:country":"CA",
    "sg:city":"St. John's",
    "sg:classifiers":[
        {
            "category":"Education",
            "subcategory":"School",
            "type":"Public Place"
        }
    ],
    "sg:phone":"+1 709 579 0443",
    "sg:postcode":"A1C 6G8",
    "sg:province":"NL",
    "wof:name":"Holy Cross Junior High",
    "wof:placetype":"venue"
},
  "geometry": {"coordinates":[-52.72401,47.555733],"type":"Point"}
}