{
  "type": "Feature",
  "properties": {
    "iso:country":"CA",
    "sg:address":"6711 Mississauga Rd",
    "sg:city":"Mississauga",
    "sg:classifiers":[
        {
            "category":"Banks & Credit Unions",
            "subcategory":"Bank",
            "type":"Services"
        }
    ],
    "sg:phone":"+1 905 826 3771",
    "sg:postcode":"L5N 2W3",
    "sg:province":"ON",
    "wof:name":"Cibc",
    "wof:placetype":"venue"
},
  "geometry": {"coordinates":[-79.7405014038,43.6015129089],"type":"Point"}
}