{
  "type": "Feature",
  "properties": {
    "addr:full":"108 Ahrens St W Kitchener ON N2H 4C3",
    "addr:housenumber":"108",
    "addr:postcode":"n2h 4c3",
    "addr:street":"Ahrens St W",
    "iso:country":"CA",
    "sg:address":"108 Ahrens St W",
    "sg:city":"Kitchener",
    "sg:classifiers":[
        {
            "category":"Wholesale",
            "subcategory":"Machinery & Supplies",
            "type":"Manufacturing & Wholesale Goods"
        }
    ],
    "sg:phone":"+1 519 743 1494",
    "sg:postcode":"N2H 4C3",
    "sg:province":"ON",
    "sg:tags":[
        "pipe",
        "fitting"
    ],
    "wof:name":"Desco Plumbing & Heating Supl",
    "wof:placetype":"venue"
},
  "geometry": {"coordinates":[-80.492149353,43.4562492371],"type":"Point"}
}