{
  "type": "Feature",
  "properties": {
    "addr:full":"8197 Hwy 101 Barton NS B0W 1H0",
    "addr:housenumber":"8197",
    "addr:postcode":"b0w 1h0",
    "addr:street":"Hwy 101",
    "iso:country":"CA",
    "sg:address":"8197 Hwy 101",
    "sg:city":"Barton",
    "sg:classifiers":[
        {
            "category":"Wholesale",
            "subcategory":"Electrical",
            "type":"Manufacturing & Wholesale Goods"
        }
    ],
    "sg:phone":"+1 902 245 1850",
    "sg:postcode":"B0W 1H0",
    "sg:province":"NS",
    "sg:tags":[
        "electric",
        "motor"
    ],
    "wof:name":"Bmr Electric",
    "wof:placetype":"venue"
},
  "geometry": {"coordinates":[-65.87449599999999,44.536087],"type":"Point"}
}