{
  "type": "Feature",
  "properties": {
    "addr:full":"118 King St Port Hope ON L1A 2R9",
    "addr:housenumber":"118",
    "addr:postcode":"l1a 2r9",
    "addr:street":"King St",
    "iso:country":"CA",
    "sg:address":"118 King St",
    "sg:city":"Port Hope",
    "sg:phone":"+1 905 885 2153",
    "sg:postcode":"L1A 2R9",
    "sg:province":"ON",
    "sg:tags":[
        "oil"
    ],
    "wof:name":"Endicott Fuels Ltd",
    "wof:placetype":"venue"
},
  "geometry": {"coordinates":[-78.2903060913,43.9475975037],"type":"Point"}
}