{
  "type": "Feature",
  "properties": {
    "addr:full":"RR 2 STN Main Okotoks AB T1S 1A2",
    "addr:postcode":"t1s 1a2",
    "addr:street":"Rr 2 Stn Main Okotoks Ab",
    "iso:country":"CA",
    "sg:address":"RR 2 STN Main",
    "sg:city":"Okotoks",
    "sg:classifiers":[
        {
            "category":"Education",
            "subcategory":"School",
            "type":"Public Place"
        }
    ],
    "sg:phone":"+1 403 938 4431",
    "sg:postcode":"T1S 1A2",
    "sg:province":"AB",
    "wof:name":"Strathcona-Tweedsmuir School",
    "wof:placetype":"venue"
},
  "geometry": {"coordinates":[-113.974937439,50.7258911133],"type":"Point"}
}