{
  "type": "Feature",
  "properties": {
    "iso:country":"CA",
    "sg:address":"3927 Boul Leman",
    "sg:city":"Laval",
    "sg:classifiers":[
        {
            "category":"Building & Trades",
            "subcategory":"Construction",
            "type":"Services"
        }
    ],
    "sg:phone":"+1 450 664 0833",
    "sg:postcode":"H7E 4V7",
    "sg:province":"QC",
    "sg:tags":[
        "railing"
    ],
    "wof:name":"Inter Aluminium Inc",
    "wof:placetype":"venue"
},
  "geometry": {"coordinates":[-73.67215,45.61274],"type":"Point"}
}