{
  "type": "Feature",
  "properties": {
    "addr:full":"1747 Mackay St Regina SK S4N 6H2",
    "addr:housenumber":"1747",
    "addr:postcode":"s4n 6h2",
    "addr:street":"Mackay St",
    "iso:country":"CA",
    "sg:address":"1747 Mackay St",
    "sg:city":"Regina",
    "sg:classifiers":[
        {
            "category":"Retail",
            "subcategory":"Auto Repair",
            "type":"Services"
        }
    ],
    "sg:phone":"+1 306 949 6665",
    "sg:postcode":"S4N 6H2",
    "sg:province":"SK",
    "sg:tags":[
        "body",
        "automobile",
        "painting"
    ],
    "wof:name":"Brinks Auto Body",
    "wof:placetype":"venue"
},
  "geometry": {"coordinates":[-104.580551,50.451153],"type":"Point"}
}