{
  "type": "Feature",
  "properties": {
    "addr:full":"138 2nd St E Cornwall ON K6H 1Y4",
    "addr:housenumber":"138",
    "addr:postcode":"k6h 1y4",
    "addr:street":"2Nd St E",
    "iso:country":"CA",
    "sg:address":"138 2nd St E",
    "sg:city":"Cornwall",
    "sg:classifiers":[
        {
            "category":"Professional",
            "subcategory":"Accounting & Tax Preparation",
            "type":"Services"
        }
    ],
    "sg:phone":"+1 613 932 6612",
    "sg:postcode":"K6H 1Y4",
    "sg:province":"ON",
    "sg:tags":[
        "accountant"
    ],
    "wof:name":"Bissonnette, Roland E CA",
    "wof:placetype":"venue"
},
  "geometry": {"coordinates":[-74.7258071899,45.0189437866],"type":"Point"}
}