{
  "type": "Feature",
  "properties": {
    "addr:full":"9030 Ch Des Merisiers Becancour QC G9H 3J8",
    "addr:postcode":"9030;g9h 3j8",
    "addr:street":"Ch Des Merisiers Becancour",
    "iso:country":"CA",
    "sg:address":"9030 Ch Des Merisiers",
    "sg:city":"Becancour",
    "sg:classifiers":[
        {
            "category":"Manufacturing",
            "subcategory":"Tools & Machinery",
            "type":"Manufacturing & Wholesale Goods"
        }
    ],
    "sg:phone":"+1 819 297 2577",
    "sg:postcode":"G9H 3J8",
    "sg:province":"QC",
    "sg:tags":[
        "lubricating",
        "system",
        "devices"
    ],
    "wof:name":"Mecalub Senc",
    "wof:placetype":"venue"
},
  "geometry": {"coordinates":[-72.341499,46.275475],"type":"Point"}
}