{
  "type": "Feature",
  "properties": {
    "addr:full":"650 Rue Graham-Bell Sainte-Foy QC G1N 4H5",
    "addr:housenumber":"650",
    "addr:postcode":"g1n 4h5",
    "addr:street":"Rue Graham-Bell",
    "iso:country":"CA",
    "sg:address":"650 Rue Graham-Bell",
    "sg:city":"Sainte-Foy",
    "sg:classifiers":[
        {
            "category":"Organizations",
            "subcategory":"Labor Organization",
            "type":"Services"
        }
    ],
    "sg:phone":"+1 418 527 2512",
    "sg:postcode":"G1N 4H5",
    "sg:province":"QC",
    "wof:name":"Syndicat Des Constables",
    "wof:placetype":"venue"
},
  "geometry": {"coordinates":[-71.27373504640001,46.7941703796],"type":"Point"}
}