{
  "type": "Feature",
  "properties": {
    "addr:full":"73 Rue Du Sault-Au-Matelot Quebec QC G1K 3Y9",
    "addr:housenumber":"73",
    "addr:postcode":"g1k 3y9",
    "addr:street":"Rue Du Sault-Au-Matelot",
    "iso:country":"CA",
    "sg:address":"73 Rue Du Sault-Au-Matelot",
    "sg:city":"Quebec",
    "sg:classifiers":[
        {
            "category":"Restaurant",
            "type":"Food & Drink"
        }
    ],
    "sg:phone":"+1 418 692 1299",
    "sg:postcode":"G1K 3Y9",
    "sg:province":"QC",
    "wof:name":"Restaurant L'Echaude",
    "wof:placetype":"venue"
},
  "geometry": {"coordinates":[-71.20370483400001,46.8157157898],"type":"Point"}
}