{
  "type": "Feature",
  "properties": {
    "addr:full":"312 15th Ave N Creston BC V0B 1G0",
    "addr:housenumber":"312",
    "addr:postcode":"bc v0b 1g0",
    "addr:street":"15Th Ave N",
    "iso:country":"CA",
    "sg:address":"312 15th Ave N",
    "sg:city":"Creston",
    "sg:classifiers":[
        {
            "category":"Health Services",
            "subcategory":"Hospital",
            "type":"Services"
        }
    ],
    "sg:phone":"+1 250 428 2286",
    "sg:postcode":"V0B 1G0",
    "sg:province":"BC",
    "wof:name":"Creston Valley Hospital",
    "wof:placetype":"venue"
},
  "geometry": {"coordinates":[-116.50818599999999,49.098164],"type":"Point"}
}