{
  "type": "Feature",
  "properties": {
    "addr:full":"8994 Rue Mauriac Saint-Leonard QC H1P 2N3",
    "addr:housenumber":"8994",
    "addr:postcode":"h1p 2n3",
    "addr:street":"Rue Mauriac",
    "iso:country":"CA",
    "sg:address":"8994 Rue Mauriac",
    "sg:city":"Saint-Leonard",
    "sg:classifiers":[
        {
            "category":"Building & Trades",
            "subcategory":"Construction",
            "type":"Services"
        }
    ],
    "sg:phone":"+1 514 326 4581",
    "sg:postcode":"H1P 2N3",
    "sg:province":"QC",
    "sg:tags":[
        "contractor"
    ],
    "wof:name":"Stena Construction Inc",
    "wof:placetype":"venue"
},
  "geometry": {"coordinates":[-73.60308074949999,45.5959091187],"type":"Point"}
}