{
  "type": "Feature",
  "properties": {
    "addr:full":"Two Hills AB T0B 4K0",
    "addr:postcode":"t0b 4k0",
    "iso:country":"CA",
    "sg:city":"Two Hills",
    "sg:classifiers":[
        {
            "category":"Personal",
            "subcategory":"Beauty Salon",
            "type":"Services"
        }
    ],
    "sg:phone":"+1 780 657 2929",
    "sg:postcode":"T0B 4K0",
    "sg:province":"AB",
    "wof:name":"Family Hair Salon",
    "wof:placetype":"venue"
},
  "geometry": {"coordinates":[-111.742104,53.710297],"type":"Point"}
}