{
  "type": "Feature",
  "properties": {
    "addr:full":"410 Sherbourne St Toronto ON M4X 1K2",
    "addr:housenumber":"410",
    "addr:postcode":"m4x 1k2",
    "addr:street":"Sherbourne St",
    "iso:country":"CA",
    "sg:address":"410 Sherbourne St",
    "sg:city":"Toronto",
    "sg:classifiers":[
        {
            "category":"Bars & Pubs",
            "type":"Food & Drink"
        }
    ],
    "sg:phone":"+1 416 323 1251",
    "sg:postcode":"M4X 1K2",
    "sg:province":"ON",
    "sg:tags":[
        "dance",
        "club",
        "night"
    ],
    "wof:name":"Phoenix Concert Theatre",
    "wof:placetype":"venue"
},
  "geometry": {"coordinates":[-79.373795,43.664513],"type":"Point"}
}