{
  "type": "Feature",
  "properties": {
    "addr:full":"202 Rue Des Erables Saint-Elzear QC G0S 2J0",
    "addr:housenumber":"202",
    "addr:postcode":"g0s 2j0",
    "addr:street":"Rue Des Erables Saint-Elzear",
    "iso:country":"CA",
    "sg:address":"202 Rue Des Erables",
    "sg:city":"Saint-Elzear",
    "sg:classifiers":[
        {
            "category":"Retail",
            "subcategory":"Auto Repair",
            "type":"Services"
        }
    ],
    "sg:phone":"+1 418 387 7905",
    "sg:postcode":"G0S 2J0",
    "sg:province":"QC",
    "sg:tags":[
        "repairing",
        "automobile"
    ],
    "wof:name":"Auto Hlr Ltee",
    "wof:placetype":"venue"
},
  "geometry": {"coordinates":[-71.04763800000001,46.417747],"type":"Point"}
}