{
  "type": "Feature",
  "properties": {
    "addr:full":"122 Front St Belleville ON K8N 2Y7",
    "addr:housenumber":"122",
    "addr:postcode":"k8n 2y7",
    "addr:street":"Front St",
    "iso:country":"CA",
    "sg:address":"122 Front St",
    "sg:city":"Belleville",
    "sg:classifiers":[
        {
            "category":"Shopping",
            "subcategory":"Florist",
            "type":"Retail Goods"
        }
    ],
    "sg:phone":"+1 613 968 5783",
    "sg:postcode":"K8N 2Y7",
    "sg:province":"ON",
    "wof:name":"Barbers Flowers Ltd",
    "wof:placetype":"venue"
},
  "geometry": {"coordinates":[-77.383369,44.161705],"type":"Point"}
}