{
  "type": "Feature",
  "properties": {
    "iso:country":"CA",
    "sg:address":"7127 Boul Saint-Michel",
    "sg:city":"Montreal",
    "sg:classifiers":[
        {
            "category":"Personal",
            "subcategory":"Beauty Salon",
            "type":"Services"
        }
    ],
    "sg:phone":"+1 514 722 0435",
    "sg:postcode":"H2A 2Z6",
    "sg:province":"QC",
    "wof:name":"Salon Universel Jp",
    "wof:placetype":"venue"
},
  "geometry": {"coordinates":[-73.596771,45.558445],"type":"Point"}
}