{
  "type": "Feature",
  "properties": {
    "addr:full":"624 Third St London ON N5V 2C2",
    "addr:housenumber":"624",
    "addr:postcode":"n5v 2c2",
    "addr:street":"Third St",
    "iso:country":"CA",
    "sg:address":"624 Third St",
    "sg:city":"London",
    "sg:classifiers":[
        {
            "category":"Autos & Motor Vehicles",
            "subcategory":"Automobile Sales",
            "type":"Retail Goods"
        }
    ],
    "sg:phone":"+1 519 457 3600",
    "sg:postcode":"N5V 2C2",
    "sg:province":"ON",
    "sg:tags":[
        "car",
        "dealer"
    ],
    "wof:name":"G & R Auto Salesmen",
    "wof:placetype":"venue"
},
  "geometry": {"coordinates":[-81.189217,43.01059],"type":"Point"}
}