{
  "type": "Feature",
  "properties": {
    "iso:country":"CA",
    "sg:city":"Oxford",
    "sg:classifiers":[
        {
            "category":"Retail",
            "subcategory":"Auto Repair",
            "type":"Services"
        }
    ],
    "sg:phone":"+1 902 447 3318",
    "sg:postcode":"B0M 1P0",
    "sg:province":"NS",
    "sg:tags":[
        "repairing",
        "automobile"
    ],
    "wof:name":"Dale Mattison's Auto Svc",
    "wof:placetype":"venue"
},
  "geometry": {"coordinates":[-63.8678245544,45.7359542847],"type":"Point"}
}