{
  "type": "Feature",
  "properties": {
    "addr:full":"202 Maceachern #101 Summerside PE C1N 5V4",
    "addr:housenumber":"202;# 101",
    "addr:postcode":"c1n 5v4",
    "addr:street":"Maceachern",
    "iso:country":"CA",
    "sg:address":"202 Maceachern #101",
    "sg:city":"Summerside",
    "sg:classifiers":[
        {
            "category":"Health Services",
            "subcategory":"Doctor",
            "type":"Services"
        }
    ],
    "sg:phone":"+1 902 436 5766",
    "sg:postcode":"C1N 5V4",
    "sg:province":"PE",
    "sg:tags":[
        "dentist"
    ],
    "wof:name":"Thompson, Tara DDS",
    "wof:placetype":"venue"
},
  "geometry": {"coordinates":[-63.775097,46.400684],"type":"Point"}
}