{
  "type": "Feature",
  "properties": {
    "iso:country":"CA",
    "sg:address":"147 Rue Saint-Paul O",
    "sg:city":"Montreal",
    "sg:classifiers":[
        {
            "category":"Communications",
            "subcategory":"Film & Video Production",
            "type":"Services"
        }
    ],
    "sg:phone":"+1 514 841 1910",
    "sg:postcode":"H2Y 1Z5",
    "sg:province":"QC",
    "sg:tags":[
        "motion",
        "picture"
    ],
    "wof:name":"Films Seville",
    "wof:placetype":"venue"
},
  "geometry": {"coordinates":[-73.55291,45.507118],"type":"Point"}
}