{
  "type": "Feature",
  "properties": {
    "iso:country":"CA",
    "sg:city":"Vancouver",
    "sg:classifiers":[
        {
            "category":"Health Services",
            "subcategory":"Doctor",
            "type":"Services"
        }
    ],
    "sg:phone":"+1 604 879 3032",
    "sg:postcode":"V5Z 3X7",
    "sg:province":"BC",
    "sg:tags":[
        "clinic"
    ],
    "wof:name":"Genesis Fertility Ctr Inc",
    "wof:placetype":"venue"
},
  "geometry": {"coordinates":[-123.116402,49.260601],"type":"Point"}
}