{
  "type": "Feature",
  "properties": {
    "addr:full":"1162 Weston Rd York ON M6M 4P4",
    "addr:housenumber":"1162",
    "addr:postcode":"m6m 4p4",
    "addr:street":"Weston Rd",
    "iso:country":"CA",
    "sg:address":"1162 Weston Rd",
    "sg:city":"York",
    "sg:classifiers":[
        {
            "category":"Health Services",
            "subcategory":"Doctor",
            "type":"Services"
        }
    ],
    "sg:phone":"+1 416 248 1660",
    "sg:postcode":"M6M 4P4",
    "sg:province":"ON",
    "sg:tags":[
        "physician",
        "surgeon"
    ],
    "wof:name":"Northwestern Eye Assoc",
    "wof:placetype":"venue"
},
  "geometry": {"coordinates":[-79.49044000000001,43.687191],"type":"Point"}
}