{
  "type": "Feature",
  "properties": {
    "addr:full":"702 Newcastle Blvd Miramichi NB E1V 2L5",
    "addr:housenumber":"702",
    "addr:postcode":"e1v 2l5",
    "addr:street":"Newcastle Blvd",
    "iso:country":"CA",
    "sg:address":"702 Newcastle Blvd",
    "sg:city":"Miramichi",
    "sg:classifiers":[
        {
            "category":"Manufacturing",
            "subcategory":"Tools & Machinery",
            "type":"Manufacturing & Wholesale Goods"
        }
    ],
    "sg:phone":"+1 506 622 1819",
    "sg:postcode":"E1V 2L5",
    "sg:province":"NB",
    "sg:tags":[
        "alternator",
        "starter"
    ],
    "wof:name":"Newcastle Alternator & Starter",
    "wof:placetype":"venue"
},
  "geometry": {"coordinates":[-65.585701,47.015663],"type":"Point"}
}