{
  "type": "Feature",
  "properties": {
    "addr:full":"549 Rue Principale Saint-Amable QC J0L 1N0",
    "addr:housenumber":"549",
    "addr:postcode":"j0l 1n0",
    "addr:street":"Rue Principale",
    "iso:country":"CA",
    "sg:address":"549 Rue Principale",
    "sg:city":"Saint-Amable",
    "sg:classifiers":[
        {
            "category":"Cinema",
            "subcategory":"Movie Rental",
            "type":"Entertainment"
        }
    ],
    "sg:phone":"+1 450 649 5675",
    "sg:postcode":"J0L 1N0",
    "sg:province":"QC",
    "sg:tags":[
        "leasing",
        "video",
        "disc",
        "tape"
    ],
    "wof:name":"Video Look",
    "wof:placetype":"venue"
},
  "geometry": {"coordinates":[-73.3060760498,45.6428947449],"type":"Point"}
}