{
  "type": "Feature",
  "properties": {
    "addr:full":"499 Rue DE LA Visitation Saint-Charles-Borromee QC J6E 4P1",
    "addr:housenumber":"499",
    "addr:postcode":"j6e 4p1",
    "addr:street":"Rue De La Visitation Saint-Charles-Borromee",
    "iso:country":"CA",
    "sg:address":"499 Rue DE LA Visitation",
    "sg:city":"Saint-Charles-Borromee",
    "sg:classifiers":[
        {
            "category":"Sports & Exercise",
            "subcategory":"Gym",
            "type":"Entertainment"
        }
    ],
    "sg:phone":"+1 450 753 3315",
    "sg:postcode":"J6E 4P1",
    "sg:province":"QC",
    "sg:tags":[
        "club",
        "health",
        "studio",
        "gymnasium"
    ],
    "wof:name":"Palais Des Sports Atlantis",
    "wof:placetype":"venue"
},
  "geometry": {"coordinates":[-73.46154799999999,46.047424],"type":"Point"}
}