{
  "type": "Feature",
  "properties": {
    "addr:full":"North York ON M3J 3A1",
    "addr:postcode":"m3j 3a1",
    "iso:country":"CA",
    "sg:city":"North York",
    "sg:classifiers":[
        {
            "category":"Retail",
            "subcategory":"Auto Repair",
            "type":"Services"
        }
    ],
    "sg:phone":"+1 416 736 0221",
    "sg:postcode":"M3J 3A1",
    "sg:province":"ON",
    "sg:tags":[
        "repairing",
        "automobile"
    ],
    "wof:name":"Gery's Auto Repairs",
    "wof:placetype":"venue"
},
  "geometry": {"coordinates":[-79.493027,43.781746],"type":"Point"}
}