{
  "type": "Feature",
  "properties": {
    "addr:full":"186 Rue Manseau Drummondville QC J2B 5Z8",
    "addr:housenumber":"186",
    "addr:postcode":"j2b 5z8",
    "addr:street":"Rue Manseau",
    "iso:country":"CA",
    "sg:address":"186 Rue Manseau",
    "sg:city":"Drummondville",
    "sg:classifiers":[
        {
            "category":"Food & Beverages",
            "subcategory":"Bakery",
            "type":"Retail Goods"
        }
    ],
    "sg:phone":"+1 819 472 1325",
    "sg:postcode":"J2B 5Z8",
    "sg:province":"QC",
    "sg:tags":[
        "baker"
    ],
    "wof:name":"Patisserie St-Joseph",
    "wof:placetype":"venue"
},
  "geometry": {"coordinates":[-72.48696136469999,45.8732757568],"type":"Point"}
}