{
  "type": "Feature",
  "properties": {
    "addr:full":"335 Rue Saint-Francois LA Tuque QC G9X 1S2",
    "addr:housenumber":"335",
    "addr:postcode":"g9x 1s2",
    "addr:street":"Rue Saint-Francois",
    "iso:country":"CA",
    "sg:address":"335 Rue Saint-Francois",
    "sg:city":"LA Tuque",
    "sg:classifiers":[
        {
            "category":"Retail",
            "subcategory":"Auto Repair",
            "type":"Services"
        }
    ],
    "sg:phone":"+1 819 523 7300",
    "sg:postcode":"G9X 1S2",
    "sg:province":"QC",
    "sg:tags":[
        "repairing",
        "automobile"
    ],
    "wof:name":"Garage Tremblay Richard Sergaz",
    "wof:placetype":"venue"
},
  "geometry": {"coordinates":[-72.78346999999999,47.437641],"type":"Point"}
}