{
  "type": "Feature",
  "properties": {
    "iso:country":"CA",
    "sg:address":"10301 109 St NW",
    "sg:city":"Edmonton",
    "sg:classifiers":[
        {
            "category":"Professional",
            "subcategory":"Management & Consulting",
            "type":"Services"
        }
    ],
    "sg:phone":"+1 780 488 3936",
    "sg:postcode":"T5J 1N4",
    "sg:province":"AB",
    "sg:tags":[
        "consultant",
        "business"
    ],
    "wof:name":"Hampton Group Inc",
    "wof:placetype":"venue"
},
  "geometry": {"coordinates":[-113.50819396999999,53.5447692871],"type":"Point"}
}