{
  "type": "Feature",
  "properties": {
    "addr:full":"1254 Rue Mackay Montreal QC H3G 2H4",
    "addr:housenumber":"1254",
    "addr:postcode":"h3g 2h4",
    "addr:street":"Rue Mackay",
    "iso:country":"CA",
    "sg:address":"1254 Rue Mackay",
    "sg:city":"Montreal",
    "sg:classifiers":[
        {
            "category":"Bars & Pubs",
            "type":"Food & Drink"
        }
    ],
    "sg:phone":"+1 514 931 6808",
    "sg:postcode":"H3G 2H4",
    "sg:province":"QC",
    "sg:tags":[
        "club",
        "night"
    ],
    "wof:name":"Upstairs",
    "wof:placetype":"venue"
},
  "geometry": {"coordinates":[-73.576363,45.495399],"type":"Point"}
}