{
  "type": "Feature",
  "properties": {
    "addr:full":"Montreal QC H3K 1G6",
    "addr:postcode":"h3k 1g6",
    "iso:country":"CA",
    "sg:city":"Montreal",
    "sg:classifiers":[
        {
            "category":"Communications",
            "subcategory":"Film & Video Production",
            "type":"Services"
        }
    ],
    "sg:phone":"+1 514 932 2600",
    "sg:postcode":"H3K 1G6",
    "sg:province":"QC",
    "sg:tags":[
        "taping"
    ],
    "wof:name":"Pbq Le Groupe",
    "wof:placetype":"venue"
},
  "geometry": {"coordinates":[-73.56215667719999,45.484046936],"type":"Point"}
}