{
  "type": "Feature",
  "properties": {
    "addr:full":"7502 100 Ave Peace River AB T8S 1M5",
    "addr:housenumber":"7502",
    "addr:postcode":"t8s 1m5",
    "addr:street":"100 Ave",
    "iso:country":"CA",
    "sg:address":"7502 100 Ave",
    "sg:city":"Peace River",
    "sg:classifiers":[
        {
            "category":"Autos & Motor Vehicles",
            "subcategory":"Automobile Sales",
            "type":"Retail Goods"
        }
    ],
    "sg:phone":"+1 780 624 9633",
    "sg:postcode":"T8S 1M5",
    "sg:province":"AB",
    "sg:tags":[
        "car",
        "dealer"
    ],
    "wof:name":"Westhill Auto & Equipment Sale",
    "wof:placetype":"venue"
},
  "geometry": {"coordinates":[-117.34644317599999,56.2337760925],"type":"Point"}
}