{
  "type": "Feature",
  "properties": {
    "addr:full":"15491 Rue DE Saint-Augustin Mirabel QC J7N 2B1",
    "addr:housenumber":"15491",
    "addr:postcode":"j7n 2b1",
    "addr:street":"Rue De Saint-Augustin",
    "iso:country":"CA",
    "sg:address":"15491 Rue DE Saint-Augustin",
    "sg:city":"Mirabel",
    "sg:classifiers":[
        {
            "category":"Home & Garden",
            "subcategory":"Hardware",
            "type":"Retail Goods"
        }
    ],
    "sg:phone":"+1 450 475 8051",
    "sg:postcode":"J7N 2B1",
    "sg:province":"QC",
    "wof:name":"Quincaillerie St Augustin Inc",
    "wof:placetype":"venue"
},
  "geometry": {"coordinates":[-73.97434199999999,45.626358],"type":"Point"}
}