{
  "type": "Feature",
  "properties": {
    "iso:country":"CA",
    "sg:address":"2001 County Road 10",
    "sg:city":"Cavan",
    "sg:classifiers":[
        {
            "category":"Education",
            "subcategory":"School",
            "type":"Public Place"
        }
    ],
    "sg:phone":"+1 705 944 5366",
    "sg:postcode":"L0A 1C0",
    "sg:province":"ON",
    "wof:name":"North Cavan Public School",
    "wof:placetype":"venue"
},
  "geometry": {"coordinates":[-78.4702377319,44.2036018372],"type":"Point"}
}