{
  "type": "Feature",
  "properties": {
    "addr:full":"Shippagan NB E8S 1M9",
    "addr:postcode":"e8s 1m9",
    "iso:country":"CA",
    "sg:city":"Shippagan",
    "sg:classifiers":[
        {
            "category":"Professional",
            "subcategory":"Lawyer & Legal Services",
            "type":"Services"
        }
    ],
    "sg:phone":"+1 506 336 2388",
    "sg:postcode":"E8S 1M9",
    "sg:province":"NB",
    "sg:tags":[
        "attorney"
    ],
    "wof:name":"Chiasson Nathalie Avocate",
    "wof:placetype":"venue"
},
  "geometry": {"coordinates":[-64.708763,47.743839],"type":"Point"}
}