{
  "type": "Feature",
  "properties": {
    "addr:full":"2360 Baron Rd # 111 Kelowna BC V1X 6X4",
    "addr:housenumber":"2360",
    "addr:postcode":"v1x 6x4",
    "addr:street":"Baron Rd # 111",
    "iso:country":"CA",
    "sg:address":"2360 Baron Rd # 111",
    "sg:city":"Kelowna",
    "sg:classifiers":[
        {
            "category":"Real Estate",
            "subcategory":"Real Estate Operator",
            "type":"Services"
        }
    ],
    "sg:phone":"+1 250 762 2285",
    "sg:postcode":"V1X 6X4",
    "sg:province":"BC",
    "sg:tags":[
        "apartment"
    ],
    "wof:name":"Benvoulin Orchard Manor",
    "wof:placetype":"venue"
},
  "geometry": {"coordinates":[-119.435501,49.879753],"type":"Point"}
}