{
  "type": "Feature",
  "properties": {
    "addr:full":"L'Assomption QC J5W 3B4",
    "addr:postcode":"j5w 3b4",
    "iso:country":"CA",
    "sg:city":"L'Assomption",
    "sg:classifiers":[
        {
            "category":"Home & Garden",
            "subcategory":"Home Furnishings",
            "type":"Retail Goods"
        }
    ],
    "sg:phone":"+1 450 589 7938",
    "sg:postcode":"J5W 3B4",
    "sg:province":"QC",
    "sg:tags":[
        "shop",
        "made",
        "fabric",
        "drapery"
    ],
    "wof:name":"Tissus Monique Michaud Inc",
    "wof:placetype":"venue"
},
  "geometry": {"coordinates":[-73.42179899999999,45.826023],"type":"Point"}
}