{
  "type": "Feature",
  "properties": {
    "iso:country":"CA",
    "sg:address":"289 Leamon St",
    "sg:city":"Waterford",
    "sg:classifiers":[
        {
            "category":"Wholesale",
            "subcategory":"Machinery & Supplies",
            "type":"Manufacturing & Wholesale Goods"
        }
    ],
    "sg:phone":"+1 519 443 8601",
    "sg:postcode":"N0E 1Y0",
    "sg:province":"ON",
    "sg:tags":[
        "farm",
        "equipment"
    ],
    "wof:name":"Robert H Laning & Sons Ltd",
    "wof:placetype":"venue"
},
  "geometry": {"coordinates":[-80.28960418699999,42.9255638123],"type":"Point"}
}