{
  "type": "Feature",
  "properties": {
    "addr:full":"1130 James Ave Pincher Creek AB T0K 1W0",
    "addr:housenumber":"1130",
    "addr:postcode":"t0k 1w0",
    "addr:street":"James Ave",
    "iso:country":"CA",
    "sg:address":"1130 James Ave",
    "sg:city":"Pincher Creek",
    "sg:classifiers":[
        {
            "category":"Wholesale",
            "subcategory":"Electrical",
            "type":"Manufacturing & Wholesale Goods"
        }
    ],
    "sg:phone":"+1 403 627 3654",
    "sg:postcode":"T0K 1W0",
    "sg:province":"AB",
    "sg:tags":[
        "appliance"
    ],
    "wof:name":"Halliday's Appliance Svc Ltd",
    "wof:placetype":"venue"
},
  "geometry": {"coordinates":[-113.94367200000001,49.489037],"type":"Point"}
}