{
  "type": "Feature",
  "properties": {
    "iso:country":"CA",
    "sg:address":"107 Rue Court",
    "sg:city":"Granby",
    "sg:classifiers":[
        {
            "category":"Personal",
            "type":"Services"
        }
    ],
    "sg:phone":"+1 450 372 3502",
    "sg:postcode":"J2G 4Z1",
    "sg:province":"QC",
    "sg:tags":[
        "therapist",
        "massage"
    ],
    "wof:name":"O 4 Mains",
    "wof:placetype":"venue"
},
  "geometry": {"coordinates":[-72.723282,45.402905],"type":"Point"}
}