{
  "type": "Feature",
  "properties": {
    "addr:full":"Cap-DE-LA-Madeleine QC G8T 8J1",
    "addr:postcode":"g8t 8j1",
    "iso:country":"CA",
    "sg:city":"Cap-DE-LA-Madeleine",
    "sg:classifiers":[
        {
            "category":"Manufacturing",
            "subcategory":"Metals",
            "type":"Manufacturing & Wholesale Goods"
        }
    ],
    "sg:phone":"+1 819 376 7744",
    "sg:postcode":"G8T 8J1",
    "sg:province":"QC",
    "sg:tags":[
        "steel"
    ],
    "wof:name":"Metals Lamines Dr",
    "wof:placetype":"venue"
},
  "geometry": {"coordinates":[-72.546547,46.382526],"type":"Point"}
}