{
  "type": "Feature",
  "properties": {
    "addr:full":"4685 215B St Langley BC V3A 9E9",
    "addr:housenumber":"4685",
    "addr:postcode":"v3a 9e9",
    "addr:street":"215B St",
    "iso:country":"CA",
    "sg:address":"4685 215B St",
    "sg:city":"Langley",
    "sg:classifiers":[
        {
            "category":"Wholesale",
            "subcategory":"Durable Goods & Equipment",
            "type":"Manufacturing & Wholesale Goods"
        }
    ],
    "sg:phone":"+1 604 530 1919",
    "sg:postcode":"V3A 9E9",
    "sg:province":"BC",
    "sg:tags":[
        "log",
        "broker"
    ],
    "wof:name":"Westcoast Cedar Corp",
    "wof:placetype":"venue"
},
  "geometry": {"coordinates":[-122.65657043500001,49.1041221619],"type":"Point"}
}