{
  "type": "Feature",
  "properties": {
    "addr:full":"12756 20 Ave Surrey BC V4A 1Y7",
    "addr:housenumber":"12756",
    "addr:postcode":"v4a 1y7",
    "addr:street":"20 Ave",
    "iso:country":"CA",
    "sg:address":"12756 20 Ave",
    "sg:city":"Surrey",
    "sg:classifiers":[
        {
            "category":"Building & Trades",
            "subcategory":"Electrical",
            "type":"Services"
        }
    ],
    "sg:phone":"+1 604 538 4041",
    "sg:postcode":"V4A 1Y7",
    "sg:province":"BC",
    "sg:tags":[
        "electric",
        "contractor"
    ],
    "wof:name":"Riddoch Electrical Contracting",
    "wof:placetype":"venue"
},
  "geometry": {"coordinates":[-122.868622,49.038296],"type":"Point"}
}