{
  "type": "Feature",
  "properties": {
    "addr:full":"30 Rue Seguin St Isidore ON K0C 2B0",
    "addr:housenumber":"30",
    "addr:postcode":"k0c 2b0",
    "addr:street":"Rue Seguin St",
    "iso:country":"CA",
    "sg:address":"30 Rue Seguin",
    "sg:city":"St Isidore",
    "sg:classifiers":[
        {
            "category":"Building & Trades",
            "subcategory":"Plumbing",
            "type":"Services"
        }
    ],
    "sg:phone":"+1 613 524 2712",
    "sg:postcode":"K0C 2B0",
    "sg:province":"ON",
    "sg:tags":[
        "contractor"
    ],
    "wof:name":"Plombier Le Bergevin Inc",
    "wof:placetype":"venue"
},
  "geometry": {"coordinates":[-74.90683,45.385212],"type":"Point"}
}