{
  "type": "Feature",
  "properties": {
    "addr:full":"8171 Ackroyd Rd # 6040 Richmond BC V6X 3K1",
    "addr:housenumber":"8171",
    "addr:postcode":"v6x 3k1",
    "addr:street":"Ackroyd Rd # 6040",
    "iso:country":"CA",
    "sg:address":"8171 Ackroyd Rd # 6040",
    "sg:city":"Richmond",
    "sg:classifiers":[
        {
            "category":"Health Services",
            "subcategory":"Doctor",
            "type":"Services"
        }
    ],
    "sg:phone":"+1 604 273 5501",
    "sg:postcode":"V6X 3K1",
    "sg:province":"BC",
    "sg:tags":[
        "physician",
        "surgeon"
    ],
    "wof:name":"Wong, Patricia MD",
    "wof:placetype":"venue"
},
  "geometry": {"coordinates":[-123.134307861,49.1721801758],"type":"Point"}
}