{
  "type": "Feature",
  "properties": {
    "addr:full":"578 Mcgill St Hawkesbury ON K6A 1R3",
    "addr:housenumber":"578",
    "addr:postcode":"k6a 1r3",
    "addr:street":"Mcgill St",
    "iso:country":"CA",
    "sg:address":"578 Mcgill St",
    "sg:city":"Hawkesbury",
    "sg:classifiers":[
        {
            "category":"Real Estate",
            "subcategory":"Real Estate Agent",
            "type":"Services"
        }
    ],
    "sg:phone":"+1 613 632 3325",
    "sg:postcode":"K6A 1R3",
    "sg:province":"ON",
    "sg:tags":[
        "appraiser"
    ],
    "wof:name":"Brisson & Assoc",
    "wof:placetype":"venue"
},
  "geometry": {"coordinates":[-74.616776,45.604446],"type":"Point"}
}