{
  "type": "Feature",
  "properties": {
    "addr:full":"143 Rue Des Chenes O Quebec QC G1L 1K6",
    "addr:housenumber":"143",
    "addr:postcode":"g1l 1k6",
    "addr:street":"Rue Des Chenes O",
    "iso:country":"CA",
    "sg:address":"143 Rue Des Chenes O",
    "sg:city":"Quebec",
    "sg:classifiers":[
        {
            "category":"Personal",
            "subcategory":"Beauty Salon",
            "type":"Services"
        }
    ],
    "sg:phone":"+1 418 623 4800",
    "sg:postcode":"G1L 1K6",
    "sg:province":"QC",
    "wof:name":"Salon DE Coiffure Rejeanne Enr",
    "wof:placetype":"venue"
},
  "geometry": {"coordinates":[-71.242622,46.837868],"type":"Point"}
}