{
  "type": "Feature",
  "properties": {
    "addr:full":"105 Maitland St Toronto ON M4Y 1E4",
    "addr:housenumber":"105",
    "addr:postcode":"m4y 1e4",
    "addr:street":"Maitland St",
    "iso:country":"CA",
    "sg:address":"105 Maitland St",
    "sg:city":"Toronto",
    "sg:classifiers":[
        {
            "category":"Education",
            "subcategory":"Dance Studio",
            "type":"Public Place"
        }
    ],
    "sg:phone":"+1 416 964 3780",
    "sg:postcode":"M4Y 1E4",
    "sg:province":"ON",
    "sg:tags":[
        "instruction",
        "dancing"
    ],
    "wof:name":"National Ballet School",
    "wof:placetype":"venue"
},
  "geometry": {"coordinates":[-79.379448,43.664715],"type":"Point"}
}