{
  "type": "Feature",
  "properties": {
    "addr:full":"339 Bevan Dr Burlington ON L7L 4L3",
    "addr:housenumber":"339",
    "addr:postcode":"l7l 4l3",
    "addr:street":"Bevan Dr",
    "iso:country":"CA",
    "sg:address":"339 Bevan Dr",
    "sg:city":"Burlington",
    "sg:classifiers":[
        {
            "category":"Shopping",
            "type":"Retail Goods"
        }
    ],
    "sg:phone":"+1 905 637 9960",
    "sg:postcode":"L7L 4L3",
    "sg:province":"ON",
    "sg:tags":[
        "equipment",
        "telephone",
        "supply"
    ],
    "wof:name":"Arch Communications",
    "wof:placetype":"venue"
},
  "geometry": {"coordinates":[-79.74202699999999,43.371944],"type":"Point"}
}