{
  "type": "Feature",
  "properties": {
    "iso:country":"CA",
    "sg:address":"339 Bevan Dr",
    "sg:city":"Burlington",
    "sg:classifiers":[
        {
            "category":"Shopping",
            "type":"Retail Goods"
        }
    ],
    "sg:phone":"+1 905 637 9960",
    "sg:postcode":"L7L 4L3",
    "sg:province":"ON",
    "sg:tags":[
        "equipment",
        "telephone",
        "supply"
    ],
    "wof:name":"Arch Communications",
    "wof:placetype":"venue"
},
  "geometry": {"coordinates":[-79.742027,43.371944],"type":"Point"}
}