{
  "type": "Feature",
  "properties": {
    "iso:country":"CA",
    "sg:city":"Didsbury",
    "sg:classifiers":[
        {
            "category":"Travel",
            "subcategory":"Hotels & Motels",
            "type":"Entertainment"
        }
    ],
    "sg:phone":"+1 403 335 8888",
    "sg:postcode":"T0M 0W0",
    "sg:province":"AB",
    "wof:name":"Didsbury Inn",
    "wof:placetype":"venue"
},
  "geometry": {"coordinates":[-114.138000488,51.6601524353],"type":"Point"}
}