{
  "type": "Feature",
  "properties": {
    "addr:full":"2517 Av Haig Montreal QC H1N 3E6",
    "addr:housenumber":"2517",
    "addr:postcode":"h1n 3e6",
    "addr:street":"Av Haig",
    "iso:country":"CA",
    "sg:address":"2517 Av Haig",
    "sg:city":"Montreal",
    "sg:classifiers":[
        {
            "category":"Wholesale",
            "subcategory":"Machinery & Supplies",
            "type":"Manufacturing & Wholesale Goods"
        }
    ],
    "sg:phone":"+1 514 254 6038",
    "sg:postcode":"H1N 3E6",
    "sg:province":"QC",
    "sg:tags":[
        "bearing"
    ],
    "wof:name":"General Bearing Svc Inc",
    "wof:placetype":"venue"
},
  "geometry": {"coordinates":[-73.53080749510001,45.5827102661],"type":"Point"}
}