{
  "type": "Feature",
  "properties": {
    "addr:full":"5570 Rue Cartier Montreal QC H2H 1X9",
    "addr:housenumber":"5570",
    "addr:postcode":"h2h 1x9",
    "addr:street":"Rue Cartier",
    "iso:country":"CA",
    "sg:address":"5570 Rue Cartier",
    "sg:city":"Montreal",
    "sg:classifiers":[
        {
            "category":"Communications",
            "subcategory":"Film & Video Production",
            "type":"Services"
        }
    ],
    "sg:phone":"+1 514 524 6644",
    "sg:postcode":"H2H 1X9",
    "sg:province":"QC",
    "sg:tags":[
        "motion",
        "picture",
        "casting"
    ],
    "wof:name":"Casting Murielle Laferriere",
    "wof:placetype":"venue"
},
  "geometry": {"coordinates":[-73.5849685669,45.5386314392],"type":"Point"}
}