{
  "type": "Feature",
  "properties": {
    "addr:full":"Courtenay BC V9N 5M6",
    "addr:postcode":"v9n 5m6",
    "iso:country":"CA",
    "sg:city":"Courtenay",
    "sg:classifiers":[
        {
            "category":"Government",
            "subcategory":"Office",
            "type":"Public Place"
        }
    ],
    "sg:phone":"+1 250 897 7556",
    "sg:postcode":"V9N 5M6",
    "sg:province":"BC",
    "wof:name":"B C Family Justice Ctr",
    "wof:placetype":"venue"
},
  "geometry": {"coordinates":[-124.982383728,49.6760940552],"type":"Point"}
}