{
  "type": "Feature",
  "properties": {
    "addr:full":"200 Elm St Aylmer ON N5H 2M8",
    "addr:housenumber":"200",
    "addr:postcode":"n5h 2m8",
    "addr:street":"Elm St",
    "iso:country":"CA",
    "sg:address":"200 Elm St",
    "sg:city":"Aylmer",
    "sg:classifiers":[
        {
            "category":"Manufacturing",
            "subcategory":"Tools & Machinery",
            "type":"Manufacturing & Wholesale Goods"
        }
    ],
    "sg:phone":"+1 519 765 1556",
    "sg:postcode":"N5H 2M8",
    "sg:province":"ON",
    "sg:tags":[
        "refrigeration",
        "refrigerating"
    ],
    "wof:name":"Tecumseh Products of Canada",
    "wof:placetype":"venue"
},
  "geometry": {"coordinates":[-80.989594,42.780979],"type":"Point"}
}