{
  "type": "Feature",
  "properties": {
    "addr:full":"1035 Hewetson Ave Pincher Creek AB T0K 1W0",
    "addr:housenumber":"1035",
    "addr:postcode":"t0k 1w0",
    "addr:street":"Hewetson Ave",
    "iso:country":"CA",
    "sg:address":"1035 Hewetson Ave",
    "sg:city":"Pincher Creek",
    "sg:classifiers":[
        {
            "category":"Health Services",
            "subcategory":"Doctor",
            "type":"Services"
        }
    ],
    "sg:phone":"+1 403 627 4900",
    "sg:postcode":"T0K 1W0",
    "sg:province":"AB",
    "sg:tags":[
        "dentist"
    ],
    "wof:name":"Creekside Dental Office",
    "wof:placetype":"venue"
},
  "geometry": {"coordinates":[-113.949813843,49.4862976074],"type":"Point"}
}