{
  "type": "Feature",
  "properties": {
    "addr:full":"RR 3 Tusket NS B0W 3M0",
    "addr:postcode":"b0w 3m0",
    "addr:street":"Rr 3",
    "iso:country":"CA",
    "sg:address":"RR 3",
    "sg:city":"Tusket",
    "sg:classifiers":[
        {
            "category":"Organizations",
            "subcategory":"Professional Association",
            "type":"Services"
        }
    ],
    "sg:phone":"+1 902 648 3291",
    "sg:postcode":"B0W 3M0",
    "sg:province":"NS",
    "sg:tags":[
        "club"
    ],
    "wof:name":"Quinan Community Ctr",
    "wof:placetype":"venue"
},
  "geometry": {"coordinates":[-65.9767532349,43.8594474792],"type":"Point"}
}