{
  "type": "Feature",
  "properties": {
    "addr:full":"153 Rue Thibault Matane QC G4W 2V8",
    "addr:housenumber":"153",
    "addr:postcode":"g4w 2v8",
    "addr:street":"Rue Thibault",
    "iso:country":"CA",
    "sg:address":"153 Rue Thibault",
    "sg:city":"Matane",
    "sg:classifiers":[
        {
            "category":"Personal",
            "subcategory":"Tanning Parlor",
            "type":"Services"
        }
    ],
    "sg:phone":"+1 418 562 2620",
    "sg:postcode":"G4W 2V8",
    "sg:province":"QC",
    "sg:tags":[
        "salon"
    ],
    "wof:name":"Bronzage Detente Enr",
    "wof:placetype":"venue"
},
  "geometry": {"coordinates":[-67.520363,48.850334],"type":"Point"}
}