{
  "type": "Feature",
  "properties": {
    "iso:country":"CA",
    "sg:address":"105 1st St W",
    "sg:city":"Glenavon",
    "sg:classifiers":[
        {
            "category":"Travel",
            "subcategory":"Hotels & Motels",
            "type":"Entertainment"
        }
    ],
    "sg:phone":"+1 306 429 2217",
    "sg:postcode":"S0G 1Y0",
    "sg:province":"SK",
    "wof:name":"Sportsman's Inn",
    "wof:placetype":"venue"
},
  "geometry": {"coordinates":[-103.142601013,50.1950035095],"type":"Point"}
}