{
  "type": "Feature",
  "properties": {
    "addr:full":"Toronto ON M5H 3B8",
    "addr:postcode":"m5h 3b8",
    "iso:country":"CA",
    "sg:city":"Toronto",
    "sg:classifiers":[
        {
            "category":"Museum",
            "type":"Entertainment"
        }
    ],
    "sg:phone":"+1 416 869 3016",
    "sg:postcode":"M5H 3B8",
    "sg:province":"ON",
    "sg:tags":[
        "organization",
        "arts",
        "information"
    ],
    "wof:name":"Council For Business",
    "wof:placetype":"venue"
},
  "geometry": {"coordinates":[-79.3851547241,43.6486167908],"type":"Point"}
}