{
  "type": "Feature",
  "properties": {
    "iso:country":"CA",
    "sg:address":"980 Av Stravinski",
    "sg:city":"Brossard",
    "sg:classifiers":[
        {
            "category":"Insurance",
            "subcategory":"Insurance Agent",
            "type":"Services"
        }
    ],
    "sg:phone":"+1 450 466 4705",
    "sg:postcode":"J4X 1W9",
    "sg:province":"QC",
    "wof:name":"Assurance Pham T Long Enr",
    "wof:placetype":"venue"
},
  "geometry": {"coordinates":[-73.489975,45.451355],"type":"Point"}
}