{
  "type": "Feature",
  "properties": {
    "iso:country":"CA",
    "sg:address":"5156 Rue Beaubien E",
    "sg:city":"Montreal",
    "sg:classifiers":[
        {
            "category":"Shopping",
            "subcategory":"Optical Goods",
            "type":"Retail Goods"
        }
    ],
    "sg:phone":"+1 514 252 1802",
    "sg:postcode":"H1T 1W1",
    "sg:province":"QC",
    "sg:tags":[
        "optician"
    ],
    "wof:name":"Cogek",
    "wof:placetype":"venue"
},
  "geometry": {"coordinates":[-73.570396,45.573048],"type":"Point"}
}