{
  "type": "Feature",
  "properties": {
    "iso:country":"CA",
    "sg:address":"12075 Rue Valmont",
    "sg:city":"Montreal",
    "sg:classifiers":[
        {
            "category":"Organizations",
            "subcategory":"Professional Association",
            "type":"Services"
        }
    ],
    "sg:phone":"+1 514 334 5231",
    "sg:postcode":"H3M 2V6",
    "sg:province":"QC",
    "wof:name":"L'Age D'Or St Joseph-Bordeaux",
    "wof:placetype":"venue"
},
  "geometry": {"coordinates":[-73.69718933110001,45.5423164368],"type":"Point"}
}