{
  "type": "Feature",
  "properties": {
    "addr:full":"4003 Ch Du Lac-Morgan Rawdon QC J0K 1S0",
    "addr:postcode":"4003;j0k 1s0",
    "addr:street":"Ch Du Lac-Morgan",
    "iso:country":"CA",
    "sg:address":"4003 Ch Du Lac-Morgan",
    "sg:city":"Rawdon",
    "sg:classifiers":[
        {
            "category":"Professional",
            "subcategory":"Business Services",
            "type":"Services"
        }
    ],
    "sg:phone":"+1 450 834 8156",
    "sg:postcode":"J0K 1S0",
    "sg:province":"QC",
    "sg:tags":[
        "translator",
        "interpreter"
    ],
    "wof:name":"Traduction Jacinthe Beausejour",
    "wof:placetype":"venue"
},
  "geometry": {"coordinates":[-73.715324,46.054638],"type":"Point"}
}