{
  "type": "Feature",
  "properties": {
    "iso:country":"CA",
    "sg:city":"Montreal",
    "sg:classifiers":[
        {
            "category":"Wholesale",
            "subcategory":"Apparel",
            "type":"Manufacturing & Wholesale Goods"
        }
    ],
    "sg:phone":"+1 514 842 0290",
    "sg:postcode":"H3A 3J5",
    "sg:province":"QC",
    "sg:tags":[
        "clothing"
    ],
    "wof:name":"Esprit DE Corp Ltee",
    "wof:placetype":"venue"
},
  "geometry": {"coordinates":[-73.57177734379999,45.5020332336],"type":"Point"}
}