{
  "type": "Feature",
  "properties": {
    "addr:full":"163 Dupont St Toronto ON M5R 1V5",
    "addr:housenumber":"163",
    "addr:postcode":"m5r 1v5",
    "addr:street":"Dupont St",
    "iso:country":"CA",
    "sg:address":"163 Dupont St",
    "sg:city":"Toronto",
    "sg:classifiers":[
        {
            "category":"Manufacturing",
            "subcategory":"Food",
            "type":"Manufacturing & Wholesale Goods"
        }
    ],
    "sg:phone":"+1 416 920 0274",
    "sg:postcode":"M5R 1V5",
    "sg:province":"ON",
    "sg:tags":[
        "cocoa",
        "chocolate"
    ],
    "wof:name":"J S Bon Bons",
    "wof:placetype":"venue"
},
  "geometry": {"coordinates":[-79.4030914307,43.6755638123],"type":"Point"}
}