{
  "type": "Feature",
  "properties": {
    "addr:full":"930 Burnham St Cobourg ON K9A 2X9",
    "addr:housenumber":"930",
    "addr:postcode":"k9a 2x9",
    "addr:street":"Burnham St",
    "iso:country":"CA",
    "sg:address":"930 Burnham St",
    "sg:city":"Cobourg",
    "sg:classifiers":[
        {
            "category":"Travel",
            "subcategory":"Hotels & Motels",
            "type":"Entertainment"
        }
    ],
    "sg:phone":"+1 905 372 2105",
    "sg:postcode":"K9A 2X9",
    "sg:province":"ON",
    "wof:name":"Best Western Cobourg Motor Inn",
    "wof:placetype":"venue"
},
  "geometry": {"coordinates":[-78.193314,43.973831],"type":"Point"}
}