{
  "type": "Feature",
  "properties": {
    "iso:country":"CA",
    "sg:address":"41 Indian Grove",
    "sg:city":"Toronto",
    "sg:classifiers":[
        {
            "category":"Professional",
            "subcategory":"Management & Consulting",
            "type":"Services"
        }
    ],
    "sg:phone":"+1 416 766 8948",
    "sg:postcode":"M6R 2Y1",
    "sg:province":"ON",
    "sg:tags":[
        "consultant",
        "business"
    ],
    "wof:name":"Archer Henderson Inc",
    "wof:placetype":"venue"
},
  "geometry": {"coordinates":[-79.4571380615,43.6518516541],"type":"Point"}
}