{
  "type": "Feature",
  "properties": {
    "addr:full":"Saint-Hubert QC J3Y 2S4",
    "addr:postcode":"j3y 2s4",
    "iso:country":"CA",
    "sg:city":"Saint-Hubert",
    "sg:classifiers":[
        {
            "category":"Wholesale",
            "subcategory":"Auto Parts",
            "type":"Manufacturing & Wholesale Goods"
        }
    ],
    "sg:phone":"+1 450 676 8021",
    "sg:postcode":"J3Y 2S4",
    "sg:province":"QC",
    "sg:tags":[
        "automobile",
        "rebuilt"
    ],
    "wof:name":"Centre DE Recyclage",
    "wof:placetype":"venue"
},
  "geometry": {"coordinates":[-73.42803192140001,45.4683685303],"type":"Point"}
}