{
  "type": "Feature",
  "properties": {
    "addr:full":"13 Boulder Blvd Stony Plain AB T7Z 1V6",
    "addr:housenumber":"13",
    "addr:postcode":"t7z 1v6",
    "addr:street":"Boulder Blvd",
    "iso:country":"CA",
    "sg:address":"13 Boulder Blvd",
    "sg:city":"Stony Plain",
    "sg:classifiers":[
        {
            "category":"Freight",
            "type":"Transportation"
        }
    ],
    "sg:phone":"+1 780 963 1888",
    "sg:postcode":"T7Z 1V6",
    "sg:province":"AB",
    "sg:tags":[
        "commercial",
        "storage"
    ],
    "wof:name":"Stony Plain Truck & Car Wash",
    "wof:placetype":"venue"
},
  "geometry": {"coordinates":[-113.993843,53.545631],"type":"Point"}
}