{
  "type": "Feature",
  "properties": {
    "addr:full":"45 Twenty Seventh St Etobicoke ON M8W 2X2",
    "addr:housenumber":"45",
    "addr:postcode":"m8w 2x2",
    "addr:street":"Twenty Seventh St",
    "iso:country":"CA",
    "sg:address":"45 Twenty Seventh St",
    "sg:city":"Etobicoke",
    "sg:classifiers":[
        {
            "category":"Wholesale",
            "subcategory":"Non-durable Goods",
            "type":"Manufacturing & Wholesale Goods"
        }
    ],
    "sg:phone":"+1 416 252 8275",
    "sg:postcode":"M8W 2X2",
    "sg:province":"ON",
    "sg:tags":[
        "advertising"
    ],
    "wof:name":"Task Force Marketing Group",
    "wof:placetype":"venue"
},
  "geometry": {"coordinates":[-79.5234222412,43.5928535461],"type":"Point"}
}