{
  "type": "Feature",
  "properties": {
    "addr:full":"507 Rue DE L'Hotel-DE-Ville Chandler QC G0C 1K0",
    "addr:housenumber":"507",
    "addr:postcode":"g0c 1k0",
    "addr:street":"Rue De L'Hotel-De-Ville",
    "iso:country":"CA",
    "sg:address":"507 Rue DE L'Hotel-DE-Ville",
    "sg:city":"Chandler",
    "sg:classifiers":[
        {
            "category":"Health Services",
            "subcategory":"Doctor",
            "type":"Services"
        }
    ],
    "sg:phone":"+1 418 689 3636",
    "sg:postcode":"G0C 1K0",
    "sg:province":"QC",
    "sg:tags":[
        "clinic"
    ],
    "wof:name":"Ste-Croix, Jean-Pierre",
    "wof:placetype":"venue"
},
  "geometry": {"coordinates":[-64.68018341059999,48.3490104675],"type":"Point"}
}