{
  "type": "Feature",
  "properties": {
    "addr:full":"815 Boul Decarie Saint-Laurent QC H4L 3L7",
    "addr:housenumber":"815",
    "addr:postcode":"h4l 3l7",
    "addr:street":"Boul Decarie",
    "iso:country":"CA",
    "sg:address":"815 Boul Decarie",
    "sg:city":"Saint-Laurent",
    "sg:classifiers":[
        {
            "category":"Personal",
            "subcategory":"Beauty Salon",
            "type":"Services"
        }
    ],
    "sg:phone":"+1 514 748 8081",
    "sg:postcode":"H4L 3L7",
    "sg:province":"QC",
    "wof:name":"Star Millennium",
    "wof:placetype":"venue"
},
  "geometry": {"coordinates":[-73.6786804199,45.5119247437],"type":"Point"}
}