{
  "type": "Feature",
  "properties": {
    "addr:full":"84 King George Rd Brantford ON N3R 5K4",
    "addr:housenumber":"84",
    "addr:postcode":"n3r 5k4",
    "addr:street":"King George Rd",
    "iso:country":"CA",
    "sg:address":"84 King George Rd",
    "sg:city":"Brantford",
    "sg:classifiers":[
        {
            "category":"Retail",
            "subcategory":"Auto Repair",
            "type":"Services"
        }
    ],
    "sg:phone":"+1 519 753 4601",
    "sg:postcode":"N3R 5K4",
    "sg:province":"ON",
    "sg:tags":[
        "automobile",
        "lubrication"
    ],
    "wof:name":"Jiffy Lube",
    "wof:placetype":"venue"
},
  "geometry": {"coordinates":[-80.27488700000001,43.166023],"type":"Point"}
}