{
  "type": "Feature",
  "properties": {
    "iso:country":"CA",
    "sg:address":"84 King George Rd",
    "sg:city":"Brantford",
    "sg:classifiers":[
        {
            "category":"Retail",
            "subcategory":"Auto Repair",
            "type":"Services"
        }
    ],
    "sg:phone":"+1 519 753 4601",
    "sg:postcode":"N3R 5K4",
    "sg:province":"ON",
    "sg:tags":[
        "automobile",
        "lubrication"
    ],
    "wof:name":"Jiffy Lube",
    "wof:placetype":"venue"
},
  "geometry": {"coordinates":[-80.274887,43.166023],"type":"Point"}
}