{
  "type": "Feature",
  "properties": {
    "addr:full":"721 Rue Real LA Tuque QC G9X 2S4",
    "addr:housenumber":"721",
    "addr:postcode":"g9x 2s4",
    "addr:street":"Rue Real",
    "iso:country":"CA",
    "sg:address":"721 Rue Real",
    "sg:city":"LA Tuque",
    "sg:classifiers":[
        {
            "category":"Wholesale",
            "subcategory":"Electrical",
            "type":"Manufacturing & Wholesale Goods"
        }
    ],
    "sg:phone":"+1 819 523 8598",
    "sg:postcode":"G9X 2S4",
    "sg:province":"QC",
    "sg:tags":[
        "control",
        "burglary",
        "security",
        "protective",
        "robbery"
    ],
    "wof:name":"Chanitec Inc",
    "wof:placetype":"venue"
},
  "geometry": {"coordinates":[-72.780693,47.433998],"type":"Point"}
}