{
  "type": "Feature",
  "properties": {
    "addr:full":"1446 Don Mills Rd #110 North York ON M3B 3N3",
    "addr:housenumber":"1446",
    "addr:postcode":"m3b 3n3",
    "addr:street":"Don Mills Rd # 110",
    "iso:country":"CA",
    "sg:address":"1446 Don Mills Rd #110",
    "sg:city":"North York",
    "sg:classifiers":[
        {
            "category":"Real Estate",
            "subcategory":"Real Estate Agent",
            "type":"Services"
        }
    ],
    "sg:phone":"+1 416 510 2700",
    "sg:postcode":"M3B 3N3",
    "sg:province":"ON",
    "wof:name":"Real Estate Marketing Inc",
    "wof:placetype":"venue"
},
  "geometry": {"coordinates":[-79.34730500000001,43.750687],"type":"Point"}
}