{
  "type": "Feature",
  "properties": {
    "addr:full":"2128 Boul Sainte-Anne Quebec QC G1J 1X8",
    "addr:housenumber":"2128",
    "addr:postcode":"g1j 1x8",
    "addr:street":"Boul Sainte-Anne",
    "iso:country":"CA",
    "sg:address":"2128 Boul Sainte-Anne",
    "sg:city":"Quebec",
    "sg:classifiers":[
        {
            "category":"Personal",
            "subcategory":"Shoe Repair & Shine",
            "type":"Services"
        }
    ],
    "sg:phone":"+1 418 663 8662",
    "sg:postcode":"G1J 1X8",
    "sg:province":"QC",
    "sg:tags":[
        "repairing",
        "boot",
        "shoes"
    ],
    "wof:name":"Cordonnerie Au Pas",
    "wof:placetype":"venue"
},
  "geometry": {"coordinates":[-71.2198181152,46.8408279419],"type":"Point"}
}