{
  "type": "Feature",
  "properties": {
    "iso:country":"CA",
    "sg:address":"285 Hope St N",
    "sg:city":"Port Hope",
    "sg:classifiers":[
        {
            "category":"Shopping",
            "subcategory":"Used Merchandise",
            "type":"Retail Goods"
        }
    ],
    "sg:phone":"+1 905 885 8000",
    "sg:postcode":"L1A 2P7",
    "sg:province":"ON",
    "sg:tags":[
        "antique"
    ],
    "wof:name":"Benson Clay Antiques",
    "wof:placetype":"venue"
},
  "geometry": {"coordinates":[-78.2939605713,43.9677963257],"type":"Point"}
}