{
  "type": "Feature",
  "properties": {
    "addr:full":"187 Botsford St Moncton NB E1C 4X4",
    "addr:housenumber":"187",
    "addr:postcode":"e1c 4x4",
    "addr:street":"Botsford St",
    "iso:country":"CA",
    "sg:address":"187 Botsford St",
    "sg:city":"Moncton",
    "sg:classifiers":[
        {
            "category":"Professional",
            "subcategory":"Business Services",
            "type":"Services"
        }
    ],
    "sg:phone":"+1 506 859 1995",
    "sg:postcode":"E1C 4X4",
    "sg:province":"NB",
    "sg:tags":[
        "interior",
        "consultant",
        "design",
        "decorator"
    ],
    "wof:name":"Brunswick Decorating Ctr Ltd",
    "wof:placetype":"venue"
},
  "geometry": {"coordinates":[-64.77797698969999,46.0942459106],"type":"Point"}
}