{
  "type": "Feature",
  "properties": {
    "addr:full":"West Montrose ON N0B 2V0",
    "addr:postcode":"n0b 2v0",
    "addr:street":"West Montrose",
    "iso:country":"CA",
    "sg:city":"West Montrose",
    "sg:classifiers":[
        {
            "category":"Building & Trades",
            "subcategory":"Plumbing",
            "type":"Services"
        }
    ],
    "sg:phone":"+1 519 664 1288",
    "sg:postcode":"N0B 2V0",
    "sg:province":"ON",
    "sg:tags":[
        "contractor"
    ],
    "wof:name":"Wrightway Mechanical",
    "wof:placetype":"venue"
},
  "geometry": {"coordinates":[-80.481918335,43.587562561],"type":"Point"}
}