{
  "type": "Feature",
  "properties": {
    "iso:country":"CA",
    "sg:address":"1 Rue Turgeon",
    "sg:city":"Sainte-Therese",
    "sg:classifiers":[
        {
            "category":"Shopping",
            "subcategory":"Books",
            "type":"Retail Goods"
        }
    ],
    "sg:phone":"+1 450 435 6060",
    "sg:postcode":"J7E 3H2",
    "sg:province":"QC",
    "sg:tags":[
        "dealer"
    ],
    "wof:name":"Librairie Ste Therese",
    "wof:placetype":"venue"
},
  "geometry": {"coordinates":[-73.841484,45.639305],"type":"Point"}
}