{
  "type": "Feature",
  "properties": {
    "addr:full":"1 Rue Turgeon Sainte-Therese QC J7E 3H2",
    "addr:housenumber":"1",
    "addr:postcode":"j7e 3h2",
    "addr:street":"Rue Turgeon Sainte-Therese",
    "iso:country":"CA",
    "sg:address":"1 Rue Turgeon",
    "sg:city":"Sainte-Therese",
    "sg:classifiers":[
        {
            "category":"Shopping",
            "subcategory":"Books",
            "type":"Retail Goods"
        }
    ],
    "sg:phone":"+1 450 435 6060",
    "sg:postcode":"J7E 3H2",
    "sg:province":"QC",
    "sg:tags":[
        "dealer"
    ],
    "wof:name":"Librairie Ste Therese",
    "wof:placetype":"venue"
},
  "geometry": {"coordinates":[-73.84148399999999,45.639305],"type":"Point"}
}