{
  "type": "Feature",
  "properties": {
    "addr:full":"349 Main St W North Bay ON P1B 2T9",
    "addr:housenumber":"349",
    "addr:postcode":"p1b 2t9",
    "addr:street":"Main St W",
    "iso:country":"CA",
    "sg:address":"349 Main St W",
    "sg:city":"North Bay",
    "sg:classifiers":[
        {
            "category":"Restaurant",
            "type":"Food & Drink"
        }
    ],
    "sg:phone":"+1 705 495 0999",
    "sg:postcode":"P1B 2T9",
    "sg:province":"ON",
    "wof:name":"Kabuki House",
    "wof:placetype":"venue"
},
  "geometry": {"coordinates":[-79.4672698975,46.3139152527],"type":"Point"}
}