{
  "type": "Feature",
  "properties": {
    "iso:country":"CA",
    "sg:address":"109 Rue William-Chapman",
    "sg:city":"Saint-Augustin-DE-Desmaures",
    "sg:classifiers":[
        {
            "category":"Building & Trades",
            "subcategory":"Construction",
            "type":"Services"
        }
    ],
    "sg:phone":"+1 418 871 1141",
    "sg:postcode":"G3A 2N4",
    "sg:province":"QC",
    "sg:tags":[
        "general",
        "contractor"
    ],
    "wof:name":"Estimations Si-Mag Inc",
    "wof:placetype":"venue"
},
  "geometry": {"coordinates":[-71.3961257935,46.7385253906],"type":"Point"}
}