{
  "type": "Feature",
  "properties": {
    "iso:country":"CA",
    "sg:address":"SW 15-8-1E",
    "sg:city":"Sanford",
    "sg:classifiers":[
        {
            "category":"Home & Garden",
            "subcategory":"Building Materials",
            "type":"Retail Goods"
        }
    ],
    "sg:phone":"+1 204 736 2746",
    "sg:postcode":"R0G 2J0",
    "sg:province":"MB",
    "sg:tags":[
        "mixed",
        "concrete"
    ],
    "wof:name":"Lewko Bros Construction Ltd",
    "wof:placetype":"venue"
},
  "geometry": {"coordinates":[-97.4463729858,49.6804656982],"type":"Point"}
}