{
  "type": "Feature",
  "properties": {
    "addr:full":"515 Main St Vancouver BC V6A 2V1",
    "addr:housenumber":"515",
    "addr:postcode":"v6a 2v1",
    "addr:street":"Main St",
    "iso:country":"CA",
    "sg:address":"515 Main St",
    "sg:city":"Vancouver",
    "sg:classifiers":[
        {
            "category":"Health Services",
            "subcategory":"Doctor",
            "type":"Services"
        }
    ],
    "sg:phone":"+1 604 685 4017",
    "sg:postcode":"V6A 2V1",
    "sg:province":"BC",
    "sg:tags":[
        "physician",
        "surgeon"
    ],
    "wof:name":"Chan, Kai Sun MD",
    "wof:placetype":"venue"
},
  "geometry": {"coordinates":[-123.09992200000001,49.280186],"type":"Point"}
}