{
  "type": "Feature",
  "properties": {
    "addr:full":"151 Delaware Ave Hamilton ON L8M 1V5",
    "addr:housenumber":"151",
    "addr:postcode":"l8m 1v5",
    "addr:street":"Delaware Ave",
    "iso:country":"CA",
    "sg:address":"151 Delaware Ave",
    "sg:city":"Hamilton",
    "sg:classifiers":[
        {
            "category":"Communications",
            "subcategory":"Film & Video Production",
            "type":"Services"
        }
    ],
    "sg:phone":"+1 905 312 0909",
    "sg:postcode":"L8M 1V5",
    "sg:province":"ON",
    "sg:tags":[
        "taping"
    ],
    "wof:name":"Beaulah Film",
    "wof:placetype":"venue"
},
  "geometry": {"coordinates":[-79.84406300000001,43.246689],"type":"Point"}
}