{
  "type": "Feature",
  "properties": {
    "addr:full":"241 Boul Samson Laval QC H7X 3E4",
    "addr:housenumber":"241",
    "addr:postcode":"h7x 3e4",
    "addr:street":"Boul Samson",
    "iso:country":"CA",
    "sg:address":"241 Boul Samson",
    "sg:city":"Laval",
    "sg:classifiers":[
        {
            "category":"Cinema",
            "subcategory":"Movie Rental",
            "type":"Entertainment"
        }
    ],
    "sg:phone":"+1 450 969 2815",
    "sg:postcode":"H7X 3E4",
    "sg:province":"QC",
    "sg:tags":[
        "leasing",
        "video",
        "disc",
        "tape"
    ],
    "wof:name":"Super Club Videotron",
    "wof:placetype":"venue"
},
  "geometry": {"coordinates":[-73.79946136469999,45.5219612122],"type":"Point"}
}