{
  "type": "Feature",
  "properties": {
    "addr:full":"Thornhill ON L4J 6X3",
    "addr:postcode":"l4j 6x3",
    "iso:country":"CA",
    "sg:city":"Thornhill",
    "sg:classifiers":[
        {
            "category":"Government",
            "subcategory":"Office",
            "type":"Public Place"
        }
    ],
    "sg:phone":"+1 905 771 9548",
    "sg:postcode":"L4J 6X3",
    "sg:province":"ON",
    "sg:tags":[
        "commission",
        "trade"
    ],
    "wof:name":"Intergalex Canada Inc",
    "wof:placetype":"venue"
},
  "geometry": {"coordinates":[-79.43380000000001,43.795166],"type":"Point"}
}