{
  "type": "Feature",
  "properties": {
    "addr:full":"Williams Lake BC V2G 1L8",
    "addr:postcode":"bc v2g 1l8",
    "iso:country":"CA",
    "sg:city":"Williams Lake",
    "sg:classifiers":[
        {
            "category":"Shopping",
            "type":"Retail Goods"
        }
    ],
    "sg:phone":"+1 250 398 8545",
    "sg:postcode":"V2G 1L8",
    "sg:province":"BC",
    "sg:tags":[
        "trophy",
        "medal",
        "award"
    ],
    "wof:name":"Woodland Trophies",
    "wof:placetype":"venue"
},
  "geometry": {"coordinates":[-122.144721985,52.1290206909],"type":"Point"}
}