{
  "type": "Feature",
  "properties": {
    "addr:full":"751 East West Rd Pelee Island ON N0R 1M0",
    "addr:housenumber":"751",
    "addr:postcode":"n0r 1m0",
    "addr:street":"East West Rd",
    "iso:country":"CA",
    "sg:address":"751 East West Rd",
    "sg:city":"Pelee Island",
    "sg:classifiers":[
        {
            "category":"Travel",
            "subcategory":"Hotels & Motels",
            "type":"Entertainment"
        }
    ],
    "sg:phone":"+1 519 724 2434",
    "sg:postcode":"N0R 1M0",
    "sg:province":"ON",
    "sg:tags":[
        "breakfast",
        "accommodation",
        "bed"
    ],
    "wof:name":"Twin Oaks Retreat B & B",
    "wof:placetype":"venue"
},
  "geometry": {"coordinates":[-82.64431,41.761246],"type":"Point"}
}