{
  "type": "Feature",
  "properties": {
    "iso:country":"CA",
    "sg:address":"141 John Button Blvd",
    "sg:city":"Markham",
    "sg:classifiers":[
        {
            "category":"Social Services",
            "subcategory":"Child Care",
            "type":"Services"
        }
    ],
    "sg:phone":"+1 905 946 1216",
    "sg:postcode":"L3R 9C2",
    "sg:province":"ON",
    "wof:name":"Buttonville Child Care",
    "wof:placetype":"venue"
},
  "geometry": {"coordinates":[-79.356552124,43.8652420044],"type":"Point"}
}