{
  "type": "Feature",
  "properties": {
    "addr:full":"7 1E Ave Forestville QC G0T 1E0",
    "addr:housenumber":"7",
    "addr:postcode":"g0t 1e0",
    "addr:street":"1E Ave",
    "iso:country":"CA",
    "sg:address":"7 1E Ave",
    "sg:city":"Forestville",
    "sg:classifiers":[
        {
            "category":"Banks & Credit Unions",
            "subcategory":"Bank",
            "type":"Services"
        }
    ],
    "sg:phone":"+1 418 587 2281",
    "sg:postcode":"G0T 1E0",
    "sg:province":"QC",
    "wof:name":"Banque Nationale Du Canada",
    "wof:placetype":"venue"
},
  "geometry": {"coordinates":[-69.0868,48.739159],"type":"Point"}
}