{
  "type": "Feature",
  "properties": {
    "addr:full":"2502 Route 102 Lincoln NB E3B 7E6",
    "addr:housenumber":"2502",
    "addr:postcode":"e3b 7e6",
    "addr:street":"Route 102",
    "iso:country":"CA",
    "sg:address":"2502 Route 102",
    "sg:city":"Lincoln",
    "sg:classifiers":[
        {
            "category":"Professional",
            "subcategory":"Art Services",
            "type":"Services"
        }
    ],
    "sg:phone":"+1 506 446 6930",
    "sg:postcode":"E3B 7E6",
    "sg:province":"NB",
    "sg:tags":[
        "rental",
        "aircraft",
        "leasing",
        "charter"
    ],
    "wof:name":"Forest Protection Ltd",
    "wof:placetype":"venue"
},
  "geometry": {"coordinates":[-66.535721,45.876522],"type":"Point"}
}