{
  "type": "Feature",
  "properties": {
    "addr:full":"554 Boul Perron Maria QC G0C 1Y0",
    "addr:housenumber":"554",
    "addr:postcode":"g0c 1y0",
    "addr:street":"Boul Perron",
    "iso:country":"CA",
    "sg:address":"554 Boul Perron",
    "sg:city":"Maria",
    "sg:classifiers":[
        {
            "category":"Banks & Credit Unions",
            "subcategory":"Bank",
            "type":"Services"
        }
    ],
    "sg:phone":"+1 418 759 3456",
    "sg:postcode":"G0C 1Y0",
    "sg:province":"QC",
    "wof:name":"Caisses Desjardins",
    "wof:placetype":"venue"
},
  "geometry": {"coordinates":[-65.9797668457,48.1775588989],"type":"Point"}
}