{
  "type": "Feature",
  "properties": {
    "addr:full":"421 Baker St Nelson BC V1L 4H7",
    "addr:housenumber":"421",
    "addr:postcode":"bc v1l 4h7",
    "addr:street":"Baker St",
    "iso:country":"CA",
    "sg:address":"421 Baker St",
    "sg:city":"Nelson",
    "sg:classifiers":[
        {
            "category":"Insurance",
            "subcategory":"Insurance Agent",
            "type":"Services"
        }
    ],
    "sg:phone":"+1 250 352 7217",
    "sg:postcode":"V1L 4H7",
    "sg:province":"BC",
    "wof:name":"Poulin Agencies Ltd",
    "wof:placetype":"venue"
},
  "geometry": {"coordinates":[-117.295089722,49.4917259216],"type":"Point"}
}