{
  "type": "Feature",
  "properties": {
    "addr:full":"13933 Rue Victoria Pointe-Aux-Trembles QC H1A 1N5",
    "addr:housenumber":"13933",
    "addr:postcode":"h1a 1n5",
    "addr:street":"Rue Victoria",
    "iso:country":"CA",
    "sg:address":"13933 Rue Victoria",
    "sg:city":"Pointe-Aux-Trembles",
    "sg:classifiers":[
        {
            "category":"Health Services",
            "subcategory":"Medical Lab",
            "type":"Services"
        }
    ],
    "sg:phone":"+1 514 642 2511",
    "sg:postcode":"H1A 1N5",
    "sg:province":"QC",
    "wof:name":"Beaudry, Mario",
    "wof:placetype":"venue"
},
  "geometry": {"coordinates":[-73.49567399999999,45.666718],"type":"Point"}
}