{
  "type": "Feature",
  "properties": {
    "addr:full":"Varennes QC J3X 1P7",
    "addr:postcode":"j3x 1p7",
    "iso:country":"CA",
    "sg:city":"Varennes",
    "sg:classifiers":[
        {
            "category":"Retail",
            "subcategory":"Auto Repair",
            "type":"Services"
        }
    ],
    "sg:phone":"+1 450 652 3066",
    "sg:postcode":"J3X 1P7",
    "sg:province":"QC",
    "sg:tags":[
        "body",
        "automobile",
        "painting"
    ],
    "wof:name":"Fix Auto Collision",
    "wof:placetype":"venue"
},
  "geometry": {"coordinates":[-73.41864013670001,45.6539878845],"type":"Point"}
}