{
  "type": "Feature",
  "properties": {
    "addr:full":"9620 Boul Saint-Laurent Montreal QC H2N 1R1",
    "addr:housenumber":"9620",
    "addr:postcode":"h2n 1r1",
    "addr:street":"Boul Saint-Laurent",
    "iso:country":"CA",
    "sg:address":"9620 Boul Saint-Laurent",
    "sg:city":"Montreal",
    "sg:classifiers":[
        {
            "category":"Home & Garden",
            "subcategory":"Home Furnishings",
            "type":"Retail Goods"
        }
    ],
    "sg:phone":"+1 514 382 5954",
    "sg:postcode":"H2N 1R1",
    "sg:province":"QC",
    "sg:tags":[
        "curtain",
        "made",
        "drapery"
    ],
    "wof:name":"Entrepot Du Decor Toptex",
    "wof:placetype":"venue"
},
  "geometry": {"coordinates":[-73.656136,45.54575],"type":"Point"}
}