{
  "type": "Feature",
  "properties": {
    "addr:full":"46 Palsen St Nepean ON K2G 2W4",
    "addr:housenumber":"46",
    "addr:postcode":"k2g 2w4",
    "addr:street":"Palsen St",
    "iso:country":"CA",
    "sg:address":"46 Palsen St",
    "sg:city":"Nepean",
    "sg:classifiers":[
        {
            "category":"Banks & Credit Unions",
            "subcategory":"Investment Brokerage",
            "type":"Services"
        }
    ],
    "sg:phone":"+1 613 228 1700",
    "sg:postcode":"K2G 2W4",
    "sg:province":"ON",
    "sg:tags":[
        "retirement",
        "planning"
    ],
    "wof:name":"Moeller Independent",
    "wof:placetype":"venue"
},
  "geometry": {"coordinates":[-75.739769,45.346283],"type":"Point"}
}