{
  "type": "Feature",
  "properties": {
    "addr:full":"15135 86 Ave Surrey BC V3S 4T8",
    "addr:housenumber":"15135",
    "addr:postcode":"v3s 4t8",
    "addr:street":"86 Ave",
    "iso:country":"CA",
    "sg:address":"15135 86 Ave",
    "sg:city":"Surrey",
    "sg:classifiers":[
        {
            "category":"Farming",
            "subcategory":"Nursery",
            "type":"Manufacturing & Wholesale Goods"
        }
    ],
    "sg:phone":"+1 604 599 0041",
    "sg:postcode":"V3S 4T8",
    "sg:province":"BC",
    "sg:tags":[
        "greenhouse"
    ],
    "wof:name":"Ultra Spen Inc",
    "wof:placetype":"venue"
},
  "geometry": {"coordinates":[-122.80360400000001,49.159363],"type":"Point"}
}