{
  "type": "Feature",
  "properties": {
    "addr:full":"821 Tsse Lecavalier Laval QC H7X 2C5",
    "addr:housenumber":"821",
    "addr:postcode":"h7x 2c5",
    "addr:street":"Tsse Lecavalier",
    "iso:country":"CA",
    "sg:address":"821 Tsse Lecavalier",
    "sg:city":"Laval",
    "sg:classifiers":[
        {
            "category":"Health Services",
            "subcategory":"Doctor",
            "type":"Services"
        }
    ],
    "sg:phone":"+1 450 689 0128",
    "sg:postcode":"H7X 2C5",
    "sg:province":"QC",
    "sg:tags":[
        "physician",
        "surgeon"
    ],
    "wof:name":"Poitras, Daniel MD",
    "wof:placetype":"venue"
},
  "geometry": {"coordinates":[-73.8154602051,45.5241165161],"type":"Point"}
}