{
  "type": "Feature",
  "properties": {
    "iso:country":"CA",
    "sg:address":"1174 Lansing Ave",
    "sg:city":"Sudbury",
    "sg:classifiers":[
        {
            "category":"Shopping",
            "subcategory":"Books",
            "type":"Retail Goods"
        }
    ],
    "sg:phone":"+1 705 524 7411",
    "sg:postcode":"P3A 4C3",
    "sg:province":"ON",
    "sg:tags":[
        "dealer"
    ],
    "wof:name":"Cornerstone Christian Bkstr",
    "wof:placetype":"venue"
},
  "geometry": {"coordinates":[-80.928855896,46.5231285095],"type":"Point"}
}