{
  "type": "Feature",
  "properties": {
    "iso:country":"CA",
    "sg:city":"Saskatoon",
    "sg:classifiers":[
        {
            "category":"Insurance",
            "subcategory":"Insurance Agent",
            "type":"Services"
        }
    ],
    "sg:phone":"+1 306 975 9040",
    "sg:postcode":"S7N 3A1",
    "sg:province":"SK",
    "wof:name":"Cherry Insurance Ltd",
    "wof:placetype":"venue"
},
  "geometry": {"coordinates":[-106.575302,52.144848],"type":"Point"}
}