{
  "type": "Feature",
  "properties": {
    "addr:full":"24 Ch Saint-Charles Mercier QC J6R 2L1",
    "addr:housenumber":"24",
    "addr:postcode":"j6r 2l1",
    "addr:street":"Ch Saint-Charles",
    "iso:country":"CA",
    "sg:address":"24 Ch Saint-Charles",
    "sg:city":"Mercier",
    "sg:classifiers":[
        {
            "category":"Wholesale",
            "subcategory":"Auto Parts",
            "type":"Manufacturing & Wholesale Goods"
        }
    ],
    "sg:phone":"+1 450 691 1847",
    "sg:postcode":"J6R 2L1",
    "sg:province":"QC",
    "sg:tags":[
        "equipment",
        "truck"
    ],
    "wof:name":"Centre Du Camion pa Inc",
    "wof:placetype":"venue"
},
  "geometry": {"coordinates":[-73.76634979249999,45.3086547852],"type":"Point"}
}