{
  "type": "Feature",
  "properties": {
    "addr:full":"5235 Mississauga Rd Mississauga ON L5M 2M1",
    "addr:housenumber":"5235",
    "addr:postcode":"l5m 2m1",
    "addr:street":"Mississauga Rd",
    "iso:country":"CA",
    "sg:address":"5235 Mississauga Rd",
    "sg:city":"Mississauga",
    "sg:classifiers":[
        {
            "category":"Retail",
            "subcategory":"Auto Repair",
            "type":"Services"
        }
    ],
    "sg:phone":"+1 905 814 8711",
    "sg:postcode":"L5M 2M1",
    "sg:province":"ON",
    "sg:tags":[
        "repairing",
        "automobile"
    ],
    "wof:name":"L A Auto Repairs",
    "wof:placetype":"venue"
},
  "geometry": {"coordinates":[-79.702736,43.573746],"type":"Point"}
}