{
  "type": "Feature",
  "properties": {
    "addr:full":"Calgary AB T2P 3V4",
    "addr:postcode":"t2p 3v4",
    "iso:country":"CA",
    "sg:city":"Calgary",
    "sg:classifiers":[
        {
            "category":"Mining & Drilling",
            "type":"Manufacturing & Wholesale Goods"
        }
    ],
    "sg:phone":"+1 403 261 1200",
    "sg:postcode":"T2P 3V4",
    "sg:province":"AB",
    "sg:tags":[
        "company",
        "oil"
    ],
    "wof:name":"Apache Canada Ltd",
    "wof:placetype":"venue"
},
  "geometry": {"coordinates":[-114.07661438,51.0451622009],"type":"Point"}
}