{
  "type": "Feature",
  "properties": {
    "addr:full":"291 Rue LA Grande-Allee E Grande-Riviere QC G0C 1V0",
    "addr:housenumber":"291",
    "addr:postcode":"g0c 1v0",
    "addr:street":"Rue La Grande-Allee E Grande-Riviere",
    "iso:country":"CA",
    "sg:address":"291 Rue LA Grande-Allee E",
    "sg:city":"Grande-Riviere",
    "sg:classifiers":[
        {
            "category":"Personal",
            "subcategory":"Beauty Salon",
            "type":"Services"
        }
    ],
    "sg:phone":"+1 418 385 3880",
    "sg:postcode":"G0C 1V0",
    "sg:province":"QC",
    "wof:name":"Institut DE Beaute",
    "wof:placetype":"venue"
},
  "geometry": {"coordinates":[-64.476524,48.402496],"type":"Point"}
}