{
  "type": "Feature",
  "properties": {
    "addr:full":"Saint-Basile-Le-Grand QC J3N 1M2",
    "addr:postcode":"j3n 1m2",
    "iso:country":"CA",
    "sg:city":"Saint-Basile-Le-Grand",
    "sg:classifiers":[
        {
            "category":"Autos & Motor Vehicles",
            "subcategory":"Auto Supplies",
            "type":"Retail Goods"
        }
    ],
    "sg:phone":"+1 450 441 1982",
    "sg:postcode":"J3N 1M2",
    "sg:province":"QC",
    "sg:tags":[
        "automobile",
        "parts"
    ],
    "wof:name":"Pieces D'Auto St-Basile Inc",
    "wof:placetype":"venue"
},
  "geometry": {"coordinates":[-73.275803,45.532913],"type":"Point"}
}