{
  "type": "Feature",
  "properties": {
    "addr:full":"81 Wootten Way N Markham ON L3P 2Y5",
    "addr:housenumber":"81",
    "addr:postcode":"l3p 2y5",
    "addr:street":"Wootten Way N",
    "iso:country":"CA",
    "sg:address":"81 Wootten Way N",
    "sg:city":"Markham",
    "sg:classifiers":[
        {
            "category":"Wholesale",
            "subcategory":"Machinery & Supplies",
            "type":"Manufacturing & Wholesale Goods"
        }
    ],
    "sg:phone":"+1 905 472 3606",
    "sg:postcode":"L3P 2Y5",
    "sg:province":"ON",
    "sg:tags":[
        "packaging"
    ],
    "wof:name":"Ram Packaging Systems Inc",
    "wof:placetype":"venue"
},
  "geometry": {"coordinates":[-79.2451477051,43.8870391846],"type":"Point"}
}