{
  "type": "Feature",
  "properties": {
    "addr:full":"1620 Rue Saint-Hubert Montreal QC H2L 3Z3",
    "addr:housenumber":"1620",
    "addr:postcode":"h2l 3z3",
    "addr:street":"Rue Saint-Hubert",
    "iso:country":"CA",
    "sg:address":"1620 Rue Saint-Hubert",
    "sg:city":"Montreal",
    "sg:classifiers":[
        {
            "category":"Travel",
            "subcategory":"Hotels & Motels",
            "type":"Entertainment"
        }
    ],
    "sg:phone":"+1 514 282 8749",
    "sg:postcode":"H2L 3Z3",
    "sg:province":"QC",
    "wof:name":"A LA Europeenne",
    "wof:placetype":"venue"
},
  "geometry": {"coordinates":[-73.561531,45.516514],"type":"Point"}
}