{
  "type": "Feature",
  "properties": {
    "iso:country":"CA",
    "sg:address":"76 Main St W",
    "sg:city":"Port Colborne",
    "sg:classifiers":[
        {
            "category":"Organizations",
            "subcategory":"Professional Association",
            "type":"Services"
        }
    ],
    "sg:phone":"+1 905 834 9765",
    "sg:postcode":"L3K 3V2",
    "sg:province":"ON",
    "sg:tags":[
        "business",
        "trade"
    ],
    "wof:name":"Chamber of Commerce",
    "wof:placetype":"venue"
},
  "geometry": {"coordinates":[-79.247787,42.901012],"type":"Point"}
}