{
  "type": "Feature",
  "properties": {
    "addr:full":"2707 Arrow Lakes Dr Castlegar BC V1N 4G4",
    "addr:housenumber":"2707",
    "addr:postcode":"v1n 4g4",
    "addr:street":"Arrow Lakes Dr",
    "iso:country":"CA",
    "sg:address":"2707 Arrow Lakes Dr",
    "sg:city":"Castlegar",
    "sg:classifiers":[
        {
            "category":"Wholesale",
            "subcategory":"Construction Materials",
            "type":"Manufacturing & Wholesale Goods"
        }
    ],
    "sg:phone":"+1 250 304 2658",
    "sg:postcode":"V1N 4G4",
    "sg:province":"BC",
    "sg:tags":[
        "building",
        "cement"
    ],
    "wof:name":"Lafarge Canada Inc",
    "wof:placetype":"venue"
},
  "geometry": {"coordinates":[-117.678527832,49.3277587891],"type":"Point"}
}