{
  "type": "Feature",
  "properties": {
    "addr:full":"Saint John NB E2K 1J5",
    "addr:postcode":"e2k 1j5",
    "iso:country":"CA",
    "sg:city":"Saint John",
    "sg:classifiers":[
        {
            "category":"Retail",
            "subcategory":"Funeral Services",
            "type":"Services"
        }
    ],
    "sg:phone":"+1 506 658 9707",
    "sg:postcode":"E2K 1J5",
    "sg:province":"NB",
    "sg:tags":[
        "plan"
    ],
    "wof:name":"Last Post Fund",
    "wof:placetype":"venue"
},
  "geometry": {"coordinates":[-66.073357,45.275383],"type":"Point"}
}