{
  "type": "Feature",
  "properties": {
    "iso:country":"CA",
    "sg:address":"198 Gatineau Rd",
    "sg:city":"London",
    "sg:classifiers":[
        {
            "category":"Retail",
            "subcategory":"Portrait Studio",
            "type":"Services"
        }
    ],
    "sg:phone":"+1 519 474 9147",
    "sg:postcode":"N6K 2Z9",
    "sg:province":"ON",
    "sg:tags":[
        "photographer"
    ],
    "wof:name":"Vassallo Photography",
    "wof:placetype":"venue"
},
  "geometry": {"coordinates":[-81.3298492432,42.9471321106],"type":"Point"}
}