{
  "type": "Feature",
  "properties": {
    "addr:full":"366 Boul Manseau Joliette QC J6E 3E1",
    "addr:housenumber":"366",
    "addr:postcode":"j6e 3e1",
    "addr:street":"Boul Manseau",
    "iso:country":"CA",
    "sg:address":"366 Boul Manseau",
    "sg:city":"Joliette",
    "sg:classifiers":[
        {
            "category":"Health Services",
            "subcategory":"Optometrist",
            "type":"Services"
        }
    ],
    "sg:phone":"+1 450 755 4779",
    "sg:postcode":"J6E 3E1",
    "sg:province":"QC",
    "wof:name":"Lauzon, Sylvie OD",
    "wof:placetype":"venue"
},
  "geometry": {"coordinates":[-73.4389419556,46.0258331299],"type":"Point"}
}