{
  "type": "Feature",
  "properties": {
    "addr:full":"North York ON M3H 2T2",
    "addr:postcode":"m3h 2t2",
    "iso:country":"CA",
    "sg:city":"North York",
    "sg:classifiers":[
        {
            "category":"Food & Beverages",
            "subcategory":"Bakery",
            "type":"Retail Goods"
        }
    ],
    "sg:phone":"+1 416 636 0383",
    "sg:postcode":"M3H 2T2",
    "sg:province":"ON",
    "sg:tags":[
        "doughnut"
    ],
    "wof:name":"Coffee Time Donuts",
    "wof:placetype":"venue"
},
  "geometry": {"coordinates":[-79.450844,43.753052],"type":"Point"}
}