{
  "type": "Feature",
  "properties": {
    "addr:full":"79 Hwy 410 Baie Verte NL A0K 1B0",
    "addr:postcode":"a0k 1b0",
    "addr:street":"79 Hwy 410",
    "iso:country":"CA",
    "sg:address":"79 Hwy 410",
    "sg:city":"Baie Verte",
    "sg:classifiers":[
        {
            "category":"Shopping",
            "subcategory":"Discount & Variety Stores",
            "type":"Retail Goods"
        }
    ],
    "sg:phone":"+1 709 532 4279",
    "sg:postcode":"A0K 1B0",
    "sg:province":"NL",
    "sg:tags":[
        "merchandise",
        "general"
    ],
    "wof:name":"Jim's Store",
    "wof:placetype":"venue"
},
  "geometry": {"coordinates":[-56.17831,49.960636],"type":"Point"}
}