{
  "type": "Feature",
  "properties": {
    "addr:full":"302 B-Say-Tah Fort Qu'Appelle SK S0G 1S0",
    "addr:housenumber":"302",
    "addr:postcode":"s0g 1s0",
    "addr:street":"B-Say-Tah Fort Qu'Appelle",
    "iso:country":"CA",
    "sg:address":"302 B-Say-Tah",
    "sg:city":"Fort Qu'Appelle",
    "sg:classifiers":[
        {
            "category":"Recreation",
            "type":"Entertainment"
        }
    ],
    "sg:phone":"+1 306 332 6821",
    "sg:postcode":"S0G 1S0",
    "sg:province":"SK",
    "sg:tags":[
        "system",
        "equipment",
        "heating",
        "tourist",
        "attraction"
    ],
    "wof:name":"Mci",
    "wof:placetype":"venue"
},
  "geometry": {"coordinates":[-103.877251,50.539394],"type":"Point"}
}