{
  "type": "Feature",
  "properties": {
    "addr:full":"2440 Cliffe Ave Courtenay BC V9N 2L6",
    "addr:housenumber":"2440",
    "addr:postcode":"v9n 2l6",
    "addr:street":"Cliffe Ave",
    "iso:country":"CA",
    "sg:address":"2440 Cliffe Ave",
    "sg:city":"Courtenay",
    "sg:phone":"+1 250 334 3377",
    "sg:postcode":"V9N 2L6",
    "sg:province":"BC",
    "sg:tags":[
        "oil"
    ],
    "wof:name":"Columbia Fuels Inc",
    "wof:placetype":"venue"
},
  "geometry": {"coordinates":[-124.982818603,49.6768531799],"type":"Point"}
}