{
  "type": "Feature",
  "properties": {
    "addr:full":"1260 Kelly Lake Rd Sudbury ON P3E 5P4",
    "addr:housenumber":"1260",
    "addr:postcode":"p3e 5p4",
    "addr:street":"Kelly Lake Rd",
    "iso:country":"CA",
    "sg:address":"1260 Kelly Lake Rd",
    "sg:city":"Sudbury",
    "sg:classifiers":[
        {
            "category":"Building & Trades",
            "subcategory":"Construction",
            "type":"Services"
        }
    ],
    "sg:phone":"+1 705 673 5213",
    "sg:postcode":"P3E 5P4",
    "sg:province":"ON",
    "sg:tags":[
        "concrete",
        "contractor"
    ],
    "wof:name":"Centis Tile & Terrazzo Inc",
    "wof:placetype":"venue"
},
  "geometry": {"coordinates":[-81.032166,46.466103],"type":"Point"}
}