{
  "type": "Feature",
  "properties": {
    "addr:full":"8207 Argyll Rd NW Edmonton AB T6C 4B2",
    "addr:housenumber":"8207",
    "addr:postcode":"t6c 4b2",
    "addr:street":"Argyll Rd Nw",
    "iso:country":"CA",
    "sg:address":"8207 Argyll Rd NW",
    "sg:city":"Edmonton",
    "sg:classifiers":[
        {
            "category":"Government",
            "subcategory":"Office",
            "type":"Public Place"
        }
    ],
    "sg:phone":"+1 780 466 3737",
    "sg:postcode":"T6C 4B2",
    "sg:province":"AB",
    "wof:name":"Edmonton Millcreek Cnstncy",
    "wof:placetype":"venue"
},
  "geometry": {"coordinates":[-113.45199599999999,53.503399],"type":"Point"}
}