{
  "type": "Feature",
  "properties": {
    "addr:full":"358 Ottawa St S Kitchener ON N2M 4Z7",
    "addr:housenumber":"358",
    "addr:postcode":"n2m 4z7",
    "addr:street":"Ottawa St S",
    "iso:country":"CA",
    "sg:address":"358 Ottawa St S",
    "sg:city":"Kitchener",
    "sg:classifiers":[
        {
            "category":"Organizations",
            "subcategory":"Religious Organization",
            "type":"Services"
        }
    ],
    "sg:phone":"+1 519 744 0130",
    "sg:postcode":"N2M 4Z7",
    "sg:province":"ON",
    "sg:tags":[
        "church"
    ],
    "wof:name":"Central Baptist Church",
    "wof:placetype":"venue"
},
  "geometry": {"coordinates":[-80.47872924799999,43.434211731],"type":"Point"}
}