{
  "type": "Feature",
  "properties": {
    "iso:country":"CA",
    "sg:address":"4 Rue Aesop",
    "sg:city":"Kirkland",
    "sg:classifiers":[
        {
            "category":"Education",
            "subcategory":"School",
            "type":"Public Place"
        }
    ],
    "sg:phone":"+1 514 693 0363",
    "sg:postcode":"H9H 5G5",
    "sg:province":"QC",
    "wof:name":"Kuper Mini Academy",
    "wof:placetype":"venue"
},
  "geometry": {"coordinates":[-73.838333,45.452721],"type":"Point"}
}