{
  "type": "Feature",
  "properties": {
    "iso:country":"CA",
    "sg:address":"501 4E Rue",
    "sg:city":"Chibougamau",
    "sg:classifiers":[
        {
            "category":"Food & Beverages",
            "subcategory":"Groceries & Convenience Stores",
            "type":"Retail Goods"
        }
    ],
    "sg:phone":"+1 418 748 2842",
    "sg:postcode":"G8P 1S4",
    "sg:province":"QC",
    "wof:name":"Depanneur Chez Carole",
    "wof:placetype":"venue"
},
  "geometry": {"coordinates":[-74.3631515503,49.9128608704],"type":"Point"}
}