{
  "type": "Feature",
  "properties": {
    "addr:full":"245 Main St Wellington ON K0K 3L0",
    "addr:housenumber":"245",
    "addr:postcode":"k0k 3l0",
    "addr:street":"Main St",
    "iso:country":"CA",
    "sg:address":"245 Main St",
    "sg:city":"Wellington",
    "sg:classifiers":[
        {
            "category":"Organizations",
            "subcategory":"Religious Organization",
            "type":"Services"
        }
    ],
    "sg:phone":"+1 613 399 3708",
    "sg:postcode":"K0K 3L0",
    "sg:province":"ON",
    "sg:tags":[
        "church"
    ],
    "wof:name":"Wellington United Church",
    "wof:placetype":"venue"
},
  "geometry": {"coordinates":[-77.34716033940001,43.951675415],"type":"Point"}
}