{
  "type": "Feature",
  "properties": {
    "addr:full":"Burnaby BC V5J 3J3",
    "addr:postcode":"v5j 3j3",
    "iso:country":"CA",
    "sg:city":"Burnaby",
    "sg:classifiers":[
        {
            "category":"Manufacturing",
            "subcategory":"Building Materials",
            "type":"Manufacturing & Wholesale Goods"
        }
    ],
    "sg:phone":"+1 604 451 0282",
    "sg:postcode":"V5J 3J3",
    "sg:province":"BC",
    "wof:name":"Benchmark Architectural",
    "wof:placetype":"venue"
},
  "geometry": {"coordinates":[-122.97895800000001,49.20343],"type":"Point"}
}