{
  "type": "Feature",
  "properties": {
    "addr:full":"133 Robert St W Penetanguishene ON L9M 1P3",
    "addr:housenumber":"133",
    "addr:postcode":"l9m 1p3",
    "addr:street":"Robert St W",
    "iso:country":"CA",
    "sg:address":"133 Robert St W",
    "sg:city":"Penetanguishene",
    "sg:phone":"+1 705 549 3177",
    "sg:postcode":"L9M 1P3",
    "sg:province":"ON",
    "sg:tags":[
        "oil"
    ],
    "wof:name":"Stewart's Fuels Distr",
    "wof:placetype":"venue"
},
  "geometry": {"coordinates":[-79.949287,44.762119],"type":"Point"}
}