{
  "type": "Feature",
  "properties": {
    "iso:country":"CA",
    "sg:address":"5200 Rue Albert-Millichamp",
    "sg:city":"Saint-Hubert",
    "sg:classifiers":[
        {
            "category":"Manufacturing",
            "subcategory":"Glass & Minerals",
            "type":"Manufacturing & Wholesale Goods"
        }
    ],
    "sg:phone":"+1 450 656 2992",
    "sg:postcode":"J3Y 8X8",
    "sg:province":"QC",
    "sg:tags":[
        "concrete",
        "brick"
    ],
    "wof:name":"Techo-Bloc Inc",
    "wof:placetype":"venue"
},
  "geometry": {"coordinates":[-73.423500061,45.4662818909],"type":"Point"}
}