{
  "type": "Feature",
  "properties": {
    "addr:full":"Toronto ON M5A 1J2",
    "addr:postcode":"m5a 1j2",
    "iso:country":"CA",
    "sg:city":"Toronto",
    "sg:classifiers":[
        {
            "category":"Social Services",
            "type":"Services"
        }
    ],
    "sg:phone":"+1 416 868 1493",
    "sg:postcode":"M5A 1J2",
    "sg:province":"ON",
    "sg:tags":[
        "organization",
        "welfare"
    ],
    "wof:name":"New Visions Toronto",
    "wof:placetype":"venue"
},
  "geometry": {"coordinates":[-79.36489899999999,43.649731],"type":"Point"}
}