{
  "type": "Feature",
  "properties": {
    "addr:full":"1819 Tedesco Rd Christina Lake BC V0H 1E2",
    "addr:housenumber":"1819",
    "addr:postcode":"v0h 1e2",
    "addr:street":"Tedesco Rd",
    "iso:country":"CA",
    "sg:address":"1819 Tedesco Rd",
    "sg:city":"Christina Lake",
    "sg:classifiers":[
        {
            "category":"Freight",
            "type":"Transportation"
        }
    ],
    "sg:phone":"+1 250 447 6222",
    "sg:postcode":"V0H 1E2",
    "sg:province":"BC",
    "sg:tags":[
        "courier"
    ],
    "wof:name":"Greyhound Lines of Canada Ltd",
    "wof:placetype":"venue"
},
  "geometry": {"coordinates":[-118.21060900000001,49.050777],"type":"Point"}
}