{
  "type": "Feature",
  "properties": {
    "addr:full":"133 Argyle St Sydney NS B1S 2V4",
    "addr:housenumber":"133",
    "addr:postcode":"b1s 2v4",
    "addr:street":"Argyle St",
    "iso:country":"CA",
    "sg:address":"133 Argyle St",
    "sg:city":"Sydney",
    "sg:classifiers":[
        {
            "category":"Retail",
            "subcategory":"Self-service Laundry",
            "type":"Services"
        }
    ],
    "sg:phone":"+1 902 539 5504",
    "sg:postcode":"B1S 2V4",
    "sg:province":"NS",
    "wof:name":"Shipyard Laundromat",
    "wof:placetype":"venue"
},
  "geometry": {"coordinates":[-60.1922721863,46.1291809082],"type":"Point"}
}