{
  "type": "Feature",
  "properties": {
    "addr:full":"109 3rd Ave N Saskatoon SK S7K 2H4",
    "addr:housenumber":"109",
    "addr:postcode":"s7k 2h4",
    "addr:street":"3Rd Ave N",
    "iso:country":"CA",
    "sg:address":"109 3rd Ave N",
    "sg:city":"Saskatoon",
    "sg:classifiers":[
        {
            "category":"Shopping",
            "subcategory":"Florist",
            "type":"Retail Goods"
        }
    ],
    "sg:phone":"+1 306 664 3618",
    "sg:postcode":"S7K 2H4",
    "sg:province":"SK",
    "sg:tags":[
        "basket",
        "parcel",
        "gift"
    ],
    "wof:name":"Creative Compliment Gift Bskt",
    "wof:placetype":"venue"
},
  "geometry": {"coordinates":[-106.66218600000001,52.128773],"type":"Point"}
}