{
  "type": "Feature",
  "properties": {
    "addr:full":"1205 Wellington St W Ottawa ON K1Y 2Z8",
    "addr:housenumber":"1205",
    "addr:postcode":"k1y 2z8",
    "addr:street":"Wellington St W",
    "iso:country":"CA",
    "sg:address":"1205 Wellington St W",
    "sg:city":"Ottawa",
    "sg:classifiers":[
        {
            "category":"Sports & Exercise",
            "subcategory":"Bowling",
            "type":"Entertainment"
        }
    ],
    "sg:phone":"+1 613 728 0933",
    "sg:postcode":"K1Y 2Z8",
    "sg:province":"ON",
    "sg:tags":[
        "center"
    ],
    "wof:name":"West Park Bowling",
    "wof:placetype":"venue"
},
  "geometry": {"coordinates":[-75.730644,45.400379],"type":"Point"}
}