{
  "type": "Feature",
  "properties": {
    "addr:full":"95 East St Cambridge ON N1R 4P5",
    "addr:housenumber":"95",
    "addr:postcode":"n1r 4p5",
    "addr:street":"East St",
    "iso:country":"CA",
    "sg:address":"95 East St",
    "sg:city":"Cambridge",
    "sg:classifiers":[
        {
            "category":"Social Services",
            "subcategory":"Child Care",
            "type":"Services"
        }
    ],
    "sg:phone":"+1 519 621 3056",
    "sg:postcode":"N1R 4P5",
    "sg:province":"ON",
    "wof:name":"East Side Daycare",
    "wof:placetype":"venue"
},
  "geometry": {"coordinates":[-80.3027420044,43.3501052856],"type":"Point"}
}