{
  "type": "Feature",
  "properties": {
    "addr:full":"Lantzville BC V0R 2H0",
    "addr:postcode":"v0r 2h0",
    "iso:country":"CA",
    "sg:city":"Lantzville",
    "sg:classifiers":[
        {
            "category":"Organizations",
            "subcategory":"Professional Association",
            "type":"Services"
        }
    ],
    "sg:phone":"+1 250 390 0821",
    "sg:postcode":"V0R 2H0",
    "sg:province":"BC",
    "wof:name":"Nanoose First Nation Nurses",
    "wof:placetype":"venue"
},
  "geometry": {"coordinates":[-124.073257446,49.2489776611],"type":"Point"}
}