{
  "type": "Feature",
  "properties": {
    "addr:full":"Hope BC V0X 1L0",
    "addr:postcode":"v0x 1l0",
    "iso:country":"CA",
    "sg:city":"Hope",
    "sg:classifiers":[
        {
            "category":"Professional",
            "subcategory":"Business Services",
            "type":"Services"
        }
    ],
    "sg:phone":"+1 604 869 3833",
    "sg:postcode":"V0X 1L0",
    "sg:province":"BC",
    "sg:tags":[
        "lecture",
        "bureau",
        "seminar"
    ],
    "wof:name":"Lavin Agency",
    "wof:placetype":"venue"
},
  "geometry": {"coordinates":[-121.439224,49.380573],"type":"Point"}
}