{
  "type": "Feature",
  "properties": {
    "addr:full":"761 Woolwich St Guelph ON N1H 3Z2",
    "addr:housenumber":"761",
    "addr:postcode":"n1h 3z2",
    "addr:street":"Woolwich St",
    "iso:country":"CA",
    "sg:address":"761 Woolwich St",
    "sg:city":"Guelph",
    "sg:classifiers":[
        {
            "category":"Retail",
            "subcategory":"Auto Repair",
            "type":"Services"
        }
    ],
    "sg:phone":"+1 519 836 1168",
    "sg:postcode":"N1H 3Z2",
    "sg:province":"ON",
    "sg:tags":[
        "repairing",
        "automobile"
    ],
    "wof:name":"Frank's Auto Shop",
    "wof:placetype":"venue"
},
  "geometry": {"coordinates":[-80.275406,43.563782],"type":"Point"}
}