{
  "type": "Feature",
  "properties": {
    "iso:country":"CA",
    "sg:address":"140 Richmond Blvd",
    "sg:city":"Napanee",
    "sg:classifiers":[
        {
            "category":"Recreation",
            "type":"Entertainment"
        }
    ],
    "sg:phone":"+1 613 354 0506",
    "sg:postcode":"K7R 3Z7",
    "sg:province":"ON",
    "sg:tags":[
        "martial",
        "arts",
        "instruction"
    ],
    "wof:name":"Napanee Karate Club",
    "wof:placetype":"venue"
},
  "geometry": {"coordinates":[-76.9567184448,44.2630233765],"type":"Point"}
}