{
  "type": "Feature",
  "properties": {
    "addr:full":"1999 Boul Roland-Therrien Longueuil QC J4N 1A3",
    "addr:housenumber":"1999",
    "addr:postcode":"j4n 1a3",
    "addr:street":"Boul Roland-Therrien",
    "iso:country":"CA",
    "sg:address":"1999 Boul Roland-Therrien",
    "sg:city":"Longueuil",
    "sg:classifiers":[
        {
            "category":"Shopping",
            "subcategory":"Department Store",
            "type":"Retail Goods"
        }
    ],
    "sg:phone":"+1 450 448 2688",
    "sg:postcode":"J4N 1A3",
    "sg:province":"QC",
    "wof:name":"Wal-Mart",
    "wof:placetype":"venue"
},
  "geometry": {"coordinates":[-73.47457900000001,45.537571],"type":"Point"}
}