{
  "type": "Feature",
  "properties": {
    "addr:full":"503 201 Rte Sainte-Marthe QC J0P 1W0",
    "addr:housenumber":"201",
    "addr:postcode":"j0p 1w0",
    "addr:street":"Rte Sainte-Marthe",
    "iso:country":"CA",
    "sg:address":"503 201 Rte",
    "sg:city":"Sainte-Marthe",
    "sg:classifiers":[
        {
            "category":"Building & Trades",
            "subcategory":"Construction",
            "type":"Services"
        }
    ],
    "sg:phone":"+1 450 459 4471",
    "sg:postcode":"J0P 1W0",
    "sg:province":"QC",
    "sg:tags":[
        "concrete",
        "contractor"
    ],
    "wof:name":"Robert Cousineau Enr",
    "wof:placetype":"venue"
},
  "geometry": {"coordinates":[-74.23821258540001,45.4135246277],"type":"Point"}
}