{
  "type": "Feature",
  "properties": {
    "addr:full":"100 Main St Ucluelet BC V0R 3A0",
    "addr:housenumber":"100",
    "addr:postcode":"bc v0r 3a0",
    "addr:street":"Main St",
    "iso:country":"CA",
    "sg:address":"100 Main St",
    "sg:city":"Ucluelet",
    "sg:classifiers":[
        {
            "category":"Organizations",
            "subcategory":"Professional Association",
            "type":"Services"
        }
    ],
    "sg:phone":"+1 250 726 4641",
    "sg:postcode":"V0R 3A0",
    "sg:province":"BC",
    "wof:name":"Chamber of Commerce",
    "wof:placetype":"venue"
},
  "geometry": {"coordinates":[-125.54631000000001,48.942554],"type":"Point"}
}