{
  "type": "Feature",
  "properties": {
    "addr:full":"3078 111 Rte E Amos QC J9T 3A1",
    "addr:housenumber":"3078",
    "addr:postcode":"j9t 3a1",
    "addr:street":"111 Rte E Amos",
    "iso:country":"CA",
    "sg:address":"3078 111 Rte E",
    "sg:city":"Amos",
    "sg:classifiers":[
        {
            "category":"Autos & Motor Vehicles",
            "subcategory":"Auto Supplies",
            "type":"Retail Goods"
        }
    ],
    "sg:phone":"+1 819 732 5207",
    "sg:postcode":"J9T 3A1",
    "sg:province":"QC",
    "sg:tags":[
        "tire"
    ],
    "wof:name":"Pneus Abitibi",
    "wof:placetype":"venue"
},
  "geometry": {"coordinates":[-78.16078948969999,48.6009674072],"type":"Point"}
}