{
  "type": "Feature",
  "properties": {
    "addr:full":"598 Av Des Oblats Quebec QC G1N 1V7",
    "addr:postcode":"g1n 1v7",
    "addr:street":"598 Av Des Oblats",
    "iso:country":"CA",
    "sg:address":"598 Av Des Oblats",
    "sg:city":"Quebec",
    "sg:classifiers":[
        {
            "category":"Food & Beverages",
            "subcategory":"Groceries & Convenience Stores",
            "type":"Retail Goods"
        }
    ],
    "sg:phone":"+1 418 523 4819",
    "sg:postcode":"G1N 1V7",
    "sg:province":"QC",
    "sg:tags":[
        "grocer"
    ],
    "wof:name":"Epicerie Jeanne Enrg",
    "wof:placetype":"venue"
},
  "geometry": {"coordinates":[-71.2410583496,46.8084030151],"type":"Point"}
}