{
  "type": "Feature",
  "properties": {
    "iso:country":"CA",
    "sg:address":"2940 Av Barclay",
    "sg:city":"Montreal",
    "sg:classifiers":[
        {
            "category":"Freight",
            "type":"Transportation"
        }
    ],
    "sg:phone":"+1 514 736 5158",
    "sg:postcode":"H3S 1J8",
    "sg:province":"QC",
    "sg:tags":[
        "mover"
    ],
    "wof:name":"Nebika Transport",
    "wof:placetype":"venue"
},
  "geometry": {"coordinates":[-73.6299743652,45.5084838867],"type":"Point"}
}