{
  "type": "Feature",
  "properties": {
    "addr:full":"6280 Av Goncourt Anjou QC H1K 3X5",
    "addr:housenumber":"6280",
    "addr:postcode":"h1k 3x5",
    "addr:street":"Av Goncourt",
    "iso:country":"CA",
    "sg:address":"6280 Av Goncourt",
    "sg:city":"Anjou",
    "sg:classifiers":[
        {
            "category":"Manufacturing",
            "subcategory":"Printing",
            "type":"Manufacturing & Wholesale Goods"
        }
    ],
    "sg:phone":"+1 514 351 8774",
    "sg:postcode":"H1K 3X5",
    "sg:province":"QC",
    "sg:tags":[
        "printer"
    ],
    "wof:name":"Techno Form",
    "wof:placetype":"venue"
},
  "geometry": {"coordinates":[-73.5518875122,45.6021308899],"type":"Point"}
}