{
  "type": "Feature",
  "properties": {
    "addr:full":"Edmonton AB T5J 3S7",
    "addr:postcode":"t5j 3s7",
    "iso:country":"CA",
    "sg:city":"Edmonton",
    "sg:classifiers":[
        {
            "category":"Organizations",
            "subcategory":"Professional Association",
            "type":"Services"
        }
    ],
    "sg:phone":"+1 780 426 8500",
    "sg:postcode":"T5J 3S7",
    "sg:province":"AB",
    "wof:name":"Provincial Health Authorities",
    "wof:placetype":"venue"
},
  "geometry": {"coordinates":[-113.506820679,53.5397949219],"type":"Point"}
}