{
  "type": "Feature",
  "properties": {
    "iso:country":"CA",
    "sg:address":"1648 York Rd",
    "sg:city":"St Davids",
    "sg:classifiers":[
        {
            "category":"Home & Garden",
            "subcategory":"Home Furnishings",
            "type":"Retail Goods"
        }
    ],
    "sg:phone":"+1 905 262 4196",
    "sg:postcode":"L0S 1P0",
    "sg:province":"ON",
    "sg:tags":[
        "pottery"
    ],
    "wof:name":"Queenston Pottery Studio",
    "wof:placetype":"venue"
},
  "geometry": {"coordinates":[-79.09581756590001,43.1584701538],"type":"Point"}
}