{
  "type": "Feature",
  "properties": {
    "addr:full":"Hull QC J8Z 2B4",
    "addr:postcode":"j8z 2b4",
    "iso:country":"CA",
    "sg:city":"Hull",
    "sg:classifiers":[
        {
            "category":"Real Estate",
            "subcategory":"Real Estate Agent",
            "type":"Services"
        }
    ],
    "sg:phone":"+1 819 770 8911",
    "sg:postcode":"J8Z 2B4",
    "sg:province":"QC",
    "sg:tags":[
        "renting",
        "leasing",
        "agency",
        "rental",
        "trailer"
    ],
    "wof:name":"Mobil-Tech",
    "wof:placetype":"venue"
},
  "geometry": {"coordinates":[-75.74324799999999,45.472866],"type":"Point"}
}