{
  "type": "Feature",
  "properties": {
    "iso:country":"CA",
    "sg:address":"810 Boul DE Maisonneuve O",
    "sg:city":"Montreal",
    "sg:classifiers":[
        {
            "category":"Professional",
            "subcategory":"Employment Agencies",
            "type":"Services"
        }
    ],
    "sg:phone":"+1 514 350 0033",
    "sg:postcode":"H3A 3E6",
    "sg:province":"QC",
    "sg:tags":[
        "opportunity",
        "contractor"
    ],
    "wof:name":"Randstad",
    "wof:placetype":"venue"
},
  "geometry": {"coordinates":[-73.5600814819,45.5161933899],"type":"Point"}
}