{
  "type": "Feature",
  "properties": {
    "addr:full":"5 Glenaden Ave E Etobicoke ON M8Y 2L2",
    "addr:housenumber":"5",
    "addr:postcode":"m8y 2l2",
    "addr:street":"Glenaden Ave E",
    "iso:country":"CA",
    "sg:address":"5 Glenaden Ave E",
    "sg:city":"Etobicoke",
    "sg:classifiers":[
        {
            "category":"Professional",
            "subcategory":"Advertising",
            "type":"Services"
        }
    ],
    "sg:phone":"+1 416 235 0194",
    "sg:postcode":"M8Y 2L2",
    "sg:province":"ON",
    "sg:tags":[
        "counselor"
    ],
    "wof:name":"Mvp Marketing Inc",
    "wof:placetype":"venue"
},
  "geometry": {"coordinates":[-79.502289,43.64286],"type":"Point"}
}