{
  "type": "Feature",
  "properties": {
    "addr:full":"11953 94 Ave Delta BC V4C 3R8",
    "addr:housenumber":"11953",
    "addr:postcode":"v4c 3r8",
    "addr:street":"94 Ave",
    "iso:country":"CA",
    "sg:address":"11953 94 Ave",
    "sg:city":"Delta",
    "sg:classifiers":[
        {
            "category":"Retail",
            "subcategory":"Auto Repair",
            "type":"Services"
        }
    ],
    "sg:phone":"+1 604 588 7717",
    "sg:postcode":"V4C 3R8",
    "sg:province":"BC",
    "sg:tags":[
        "body",
        "automobile",
        "painting"
    ],
    "wof:name":"Ed's Auto Body",
    "wof:placetype":"venue"
},
  "geometry": {"coordinates":[-122.89097595200001,49.1741905212],"type":"Point"}
}