{
  "type": "Feature",
  "properties": {
    "addr:full":"Toronto ON M5V 3A8",
    "addr:postcode":"m5v 3a8",
    "iso:country":"CA",
    "sg:city":"Toronto",
    "sg:classifiers":[
        {
            "category":"Professional",
            "subcategory":"Advertising",
            "type":"Services"
        }
    ],
    "sg:phone":"+1 416 977 7704",
    "sg:postcode":"M5V 3A8",
    "sg:province":"ON",
    "sg:tags":[
        "publicity"
    ],
    "wof:name":"Anya Wilson Promotion",
    "wof:placetype":"venue"
},
  "geometry": {"coordinates":[-79.3950881958,43.6478500366],"type":"Point"}
}