{
  "type": "Feature",
  "properties": {
    "addr:full":"1911 Dundas St E Mississauga ON L4X 1M1",
    "addr:housenumber":"1911",
    "addr:postcode":"l4x 1m1",
    "addr:street":"Dundas St E",
    "iso:country":"CA",
    "sg:address":"1911 Dundas St E",
    "sg:city":"Mississauga",
    "sg:classifiers":[
        {
            "category":"Wholesale",
            "subcategory":"Non-durable Goods",
            "type":"Manufacturing & Wholesale Goods"
        }
    ],
    "sg:phone":"+1 905 602 8905",
    "sg:postcode":"L4X 1M1",
    "sg:province":"ON",
    "sg:tags":[
        "interior"
    ],
    "wof:name":"Adobe Home Collection Inc",
    "wof:placetype":"venue"
},
  "geometry": {"coordinates":[-79.571609,43.620934],"type":"Point"}
}