{
  "type": "Feature",
  "properties": {
    "addr:full":"740 Richmond St London ON N6A 1L6",
    "addr:housenumber":"740",
    "addr:postcode":"n6a 1l6",
    "addr:street":"Richmond St",
    "iso:country":"CA",
    "sg:address":"740 Richmond St",
    "sg:city":"London",
    "sg:classifiers":[
        {
            "category":"Shopping",
            "subcategory":"Books",
            "type":"Retail Goods"
        }
    ],
    "sg:phone":"+1 519 438 8336",
    "sg:postcode":"N6A 1L6",
    "sg:province":"ON",
    "sg:tags":[
        "dealer"
    ],
    "wof:name":"Oxford Books Shop Ltd",
    "wof:placetype":"venue"
},
  "geometry": {"coordinates":[-81.2526626587,42.9948692322],"type":"Point"}
}