{
  "type": "Feature",
  "properties": {
    "addr:full":"984 Rue DE L'Emeraude Saint-Jean-Chrysostome QC G6Z 2X8",
    "addr:housenumber":"984",
    "addr:postcode":"g6z 2x8",
    "addr:street":"Rue De L'Emeraude Saint-Jean-Chrysostome",
    "iso:country":"CA",
    "sg:address":"984 Rue DE L'Emeraude",
    "sg:city":"Saint-Jean-Chrysostome",
    "sg:classifiers":[
        {
            "category":"Building & Trades",
            "subcategory":"Electrical",
            "type":"Services"
        }
    ],
    "sg:phone":"+1 418 839 0172",
    "sg:postcode":"G6Z 2X8",
    "sg:province":"QC",
    "sg:tags":[
        "electric",
        "contractor"
    ],
    "wof:name":"Jean-Yves Garon Entrepreneur",
    "wof:placetype":"venue"
},
  "geometry": {"coordinates":[-71.19519042970001,46.7234039307],"type":"Point"}
}