{
  "type": "Feature",
  "properties": {
    "addr:full":"629 Hamony Rd #A Corbyville ON K0K 1V0",
    "addr:housenumber":"629",
    "addr:postcode":"k0k 1v0",
    "addr:street":"Hamony Rd # A",
    "iso:country":"CA",
    "sg:address":"629 Hamony Rd #A",
    "sg:city":"Corbyville",
    "sg:classifiers":[
        {
            "category":"Retail",
            "subcategory":"Animal Services",
            "type":"Services"
        }
    ],
    "sg:phone":"+1 613 969 8886",
    "sg:postcode":"K0K 1V0",
    "sg:province":"ON",
    "sg:tags":[
        "pet",
        "boarding",
        "sitting"
    ],
    "wof:name":"Pinegrove Kennels",
    "wof:placetype":"venue"
},
  "geometry": {"coordinates":[-77.38832855219999,44.2199707031],"type":"Point"}
}