{
  "type": "Feature",
  "properties": {
    "addr:full":"Gloucester ON K1J 9H1",
    "addr:postcode":"k1j 9h1",
    "iso:country":"CA",
    "sg:city":"Gloucester",
    "sg:classifiers":[
        {
            "category":"Building & Trades",
            "subcategory":"Construction",
            "type":"Services"
        }
    ],
    "sg:phone":"+1 613 745 3697",
    "sg:postcode":"K1J 9H1",
    "sg:province":"ON",
    "sg:tags":[
        "general",
        "contractor"
    ],
    "wof:name":"R C Construction Ltd",
    "wof:placetype":"venue"
},
  "geometry": {"coordinates":[-75.58253479,45.4588813782],"type":"Point"}
}