{
  "type": "Feature",
  "properties": {
    "addr:full":"Marathon ON P0T 2E0",
    "addr:postcode":"p0t 2e0",
    "iso:country":"CA",
    "sg:city":"Marathon",
    "sg:classifiers":[
        {
            "category":"Social Services",
            "type":"Services"
        }
    ],
    "sg:phone":"+1 807 229 0607",
    "sg:postcode":"P0T 2E0",
    "sg:province":"ON",
    "sg:tags":[
        "organization",
        "welfare"
    ],
    "wof:name":"North of Superior Programs",
    "wof:placetype":"venue"
},
  "geometry": {"coordinates":[-86.3756942749,48.7199363708],"type":"Point"}
}