{
  "type": "Feature",
  "properties": {
    "addr:full":"Yankee Valley Rd Airdrie AB T4B 2B8",
    "addr:postcode":"t4b 2b8",
    "addr:street":"Valley Rd",
    "iso:country":"CA",
    "sg:address":"Yankee Valley Rd",
    "sg:city":"Airdrie",
    "sg:classifiers":[
        {
            "category":"Manufacturing",
            "subcategory":"Wood Products",
            "type":"Manufacturing & Wholesale Goods"
        }
    ],
    "sg:phone":"+1 403 948 5977",
    "sg:postcode":"T4B 2B8",
    "sg:province":"AB",
    "sg:tags":[
        "pallet",
        "skid"
    ],
    "wof:name":"Alberta Pallet CO Ltd",
    "wof:placetype":"venue"
},
  "geometry": {"coordinates":[-113.97972900000001,51.270805],"type":"Point"}
}