{
  "type": "Feature",
  "properties": {
    "addr:full":"132 15th St W # 202 North Vancouver BC V7M 1R5",
    "addr:housenumber":"132",
    "addr:postcode":"v7m 1r5",
    "addr:street":"15Th St W # 202",
    "iso:country":"CA",
    "sg:address":"132 15th St W # 202",
    "sg:city":"North Vancouver",
    "sg:classifiers":[
        {
            "category":"Professional",
            "subcategory":"Accounting & Tax Preparation",
            "type":"Services"
        }
    ],
    "sg:phone":"+1 604 984 9016",
    "sg:postcode":"V7M 1R5",
    "sg:province":"BC",
    "sg:tags":[
        "accountant"
    ],
    "wof:name":"Hamer Accounting & Management",
    "wof:placetype":"venue"
},
  "geometry": {"coordinates":[-123.07344055199999,49.3222198486],"type":"Point"}
}