{
  "type": "Feature",
  "properties": {
    "addr:full":"Whitecourt AB T7S 1J2",
    "addr:postcode":"t7s 1j2",
    "iso:country":"CA",
    "sg:city":"Whitecourt",
    "sg:classifiers":[
        {
            "category":"Real Estate",
            "subcategory":"Developer",
            "type":"Services"
        }
    ],
    "sg:phone":"+1 780 778 4420",
    "sg:postcode":"T7S 1J2",
    "sg:province":"AB",
    "sg:tags":[
        "mobile",
        "home"
    ],
    "wof:name":"Evergreen Mobile Home Park",
    "wof:placetype":"venue"
},
  "geometry": {"coordinates":[-115.658042908,54.1301994324],"type":"Point"}
}