{
  "type": "Feature",
  "properties": {
    "addr:full":"1977 Norris Rd Winnipeg MB R2G 4C1",
    "addr:housenumber":"1977",
    "addr:postcode":"r2g 4c1",
    "addr:street":"Norris Rd",
    "iso:country":"CA",
    "sg:address":"1977 Norris Rd",
    "sg:city":"Winnipeg",
    "sg:classifiers":[
        {
            "category":"Organizations",
            "subcategory":"Religious Organization",
            "type":"Services"
        }
    ],
    "sg:phone":"+1 204 222 7384",
    "sg:postcode":"R2G 4C1",
    "sg:province":"MB",
    "sg:tags":[
        "church"
    ],
    "wof:name":"Kilcona Park Alliance Church",
    "wof:placetype":"venue"
},
  "geometry": {"coordinates":[-97.039581,49.935501],"type":"Point"}
}