{
  "type": "Feature",
  "properties": {
    "addr:full":"4271 Rue Hochelaga Montreal QC H1V 1C1",
    "addr:housenumber":"4271",
    "addr:postcode":"h1v 1c1",
    "addr:street":"Rue Hochelaga",
    "iso:country":"CA",
    "sg:address":"4271 Rue Hochelaga",
    "sg:city":"Montreal",
    "sg:classifiers":[
        {
            "category":"Personal",
            "subcategory":"Beauty Salon",
            "type":"Services"
        }
    ],
    "sg:phone":"+1 514 255 4703",
    "sg:postcode":"H1V 1C1",
    "sg:province":"QC",
    "wof:name":"Salon Paulard's Enr",
    "wof:placetype":"venue"
},
  "geometry": {"coordinates":[-73.547211,45.554428],"type":"Point"}
}