{
  "type": "Feature",
  "properties": {
    "addr:full":"Edmonton AB T5J 0G5",
    "addr:postcode":"t5j 0g5",
    "iso:country":"CA",
    "sg:city":"Edmonton",
    "sg:classifiers":[
        {
            "category":"Wholesale",
            "subcategory":"Medical Equipment & Supplies",
            "type":"Manufacturing & Wholesale Goods"
        }
    ],
    "sg:phone":"+1 780 422 6664",
    "sg:postcode":"T5J 0G5",
    "sg:province":"AB",
    "sg:tags":[
        "x",
        "apparatus"
    ],
    "wof:name":"Taneron Medical Systems",
    "wof:placetype":"venue"
},
  "geometry": {"coordinates":[-113.49176799999999,53.544537],"type":"Point"}
}