{
  "type": "Feature",
  "properties": {
    "iso:country":"CA",
    "sg:address":"268 Moffat St",
    "sg:city":"Orillia",
    "sg:classifiers":[
        {
            "category":"Building & Trades",
            "subcategory":"Construction",
            "type":"Services"
        }
    ],
    "sg:phone":"+1 705 327 2086",
    "sg:postcode":"L3V 4G1",
    "sg:province":"ON",
    "sg:tags":[
        "home",
        "improvement"
    ],
    "wof:name":"Boss Eavestroughing",
    "wof:placetype":"venue"
},
  "geometry": {"coordinates":[-79.4029541016,44.6044082642],"type":"Point"}
}