{
  "type": "Feature",
  "properties": {
    "addr:full":"Scarborough ON M1W 3K6",
    "addr:postcode":"m1w 3k6",
    "iso:country":"CA",
    "sg:city":"Scarborough",
    "sg:classifiers":[
        {
            "category":"Shopping",
            "subcategory":"Tobacco",
            "type":"Retail Goods"
        }
    ],
    "sg:phone":"+1 416 492 6424",
    "sg:postcode":"M1W 3K6",
    "sg:province":"ON",
    "sg:tags":[
        "cigarette",
        "cigar",
        "dealer"
    ],
    "wof:name":"Nicholby's Limited",
    "wof:placetype":"venue"
},
  "geometry": {"coordinates":[-79.33863100000001,43.809788],"type":"Point"}
}