{
  "type": "Feature",
  "properties": {
    "addr:full":"2233 Rue Guenette Saint-Laurent QC H4R 2E9",
    "addr:housenumber":"2233",
    "addr:postcode":"h4r 2e9",
    "addr:street":"Rue Guenette",
    "iso:country":"CA",
    "sg:address":"2233 Rue Guenette",
    "sg:city":"Saint-Laurent",
    "sg:classifiers":[
        {
            "category":"Manufacturing",
            "subcategory":"Tools & Machinery",
            "type":"Manufacturing & Wholesale Goods"
        }
    ],
    "sg:phone":"+1 514 337 7800",
    "sg:postcode":"H4R 2E9",
    "sg:province":"QC",
    "sg:tags":[
        "electric",
        "motor"
    ],
    "wof:name":"Lefevre Armatures Inc",
    "wof:placetype":"venue"
},
  "geometry": {"coordinates":[-73.72533416749999,45.4983406067],"type":"Point"}
}