{
  "type": "Feature",
  "properties": {
    "addr:full":"1543 Dupont St Toronto ON M6P 3S5",
    "addr:housenumber":"1543",
    "addr:postcode":"m6p 3s5",
    "addr:street":"Dupont St",
    "iso:country":"CA",
    "sg:address":"1543 Dupont St",
    "sg:city":"Toronto",
    "sg:classifiers":[
        {
            "category":"Shopping",
            "subcategory":"Department Store",
            "type":"Retail Goods"
        }
    ],
    "sg:phone":"+1 416 538 9825",
    "sg:postcode":"M6P 3S5",
    "sg:province":"ON",
    "sg:tags":[
        "shop"
    ],
    "wof:name":"A & P Loonie",
    "wof:placetype":"venue"
},
  "geometry": {"coordinates":[-79.45259094239999,43.6653175354],"type":"Point"}
}