{
  "type": "Feature",
  "properties": {
    "addr:full":"Scarborough ON M1B 1Y9",
    "addr:postcode":"m1b 1y9",
    "iso:country":"CA",
    "sg:city":"Scarborough",
    "sg:classifiers":[
        {
            "category":"Manufacturing",
            "subcategory":"Tools & Machinery",
            "type":"Manufacturing & Wholesale Goods"
        }
    ],
    "sg:phone":"+1 416 297 9323",
    "sg:postcode":"M1B 1Y9",
    "sg:province":"ON",
    "sg:tags":[
        "mold"
    ],
    "wof:name":"Pro Tool & Mould Ltd",
    "wof:placetype":"venue"
},
  "geometry": {"coordinates":[-79.23773199999999,43.808064],"type":"Point"}
}