{
  "type": "Feature",
  "properties": {
    "addr:full":"630 Millbank Vancouver BC V5Z 4B7",
    "addr:housenumber":"630",
    "addr:postcode":"v5z 4b7",
    "addr:street":"Millbank",
    "iso:country":"CA",
    "sg:address":"630 Millbank",
    "sg:city":"Vancouver",
    "sg:classifiers":[
        {
            "category":"Real Estate",
            "subcategory":"Developer",
            "type":"Services"
        }
    ],
    "sg:phone":"+1 604 874 8308",
    "sg:postcode":"V5Z 4B7",
    "sg:province":"BC",
    "sg:tags":[
        "company",
        "land"
    ],
    "wof:name":"Pan West Group",
    "wof:placetype":"venue"
},
  "geometry": {"coordinates":[-123.118515,49.268223],"type":"Point"}
}