{
  "type": "Feature",
  "properties": {
    "addr:full":"1025 Rue Saint-Jean Quebec QC G1R 1R9",
    "addr:housenumber":"1025",
    "addr:postcode":"g1r 1r9",
    "addr:street":"Rue Saint-Jean",
    "iso:country":"CA",
    "sg:address":"1025 Rue Saint-Jean",
    "sg:city":"Quebec",
    "sg:classifiers":[
        {
            "category":"Organizations",
            "subcategory":"Religious Organization",
            "type":"Services"
        }
    ],
    "sg:phone":"+1 418 692 2698",
    "sg:postcode":"G1R 1R9",
    "sg:province":"QC",
    "sg:tags":[
        "bible"
    ],
    "wof:name":"Societe Biblique Canadienne",
    "wof:placetype":"venue"
},
  "geometry": {"coordinates":[-71.21216583250001,46.8130378723],"type":"Point"}
}