{
  "type": "Feature",
  "properties": {
    "addr:full":"2000 Boul Marie Saint-Hubert QC J4T 2B1",
    "addr:housenumber":"2000",
    "addr:postcode":"j4t 2b1",
    "addr:street":"Boul Marie",
    "iso:country":"CA",
    "sg:address":"2000 Boul Marie",
    "sg:city":"Saint-Hubert",
    "sg:classifiers":[
        {
            "category":"Organizations",
            "subcategory":"Religious Organization",
            "type":"Services"
        }
    ],
    "sg:phone":"+1 450 671 7424",
    "sg:postcode":"J4T 2B1",
    "sg:province":"QC",
    "sg:tags":[
        "church"
    ],
    "wof:name":"St Jean Eudes Eglise",
    "wof:placetype":"venue"
},
  "geometry": {"coordinates":[-73.480492,45.499386],"type":"Point"}
}