{
  "type": "Feature",
  "properties": {
    "iso:country":"CA",
    "sg:city":"Richmond",
    "sg:classifiers":[
        {
            "category":"Government",
            "subcategory":"Office",
            "type":"Public Place"
        }
    ],
    "sg:phone":"+1 604 713 0360",
    "sg:postcode":"V6V 3B1",
    "sg:province":"BC",
    "wof:name":"B C Workers' Advisers-Assist",
    "wof:placetype":"venue"
},
  "geometry": {"coordinates":[-123.080215,49.178722],"type":"Point"}
}