{
  "type": "Feature",
  "properties": {
    "addr:full":"22 Eccles St Ottawa ON K1R 6S2",
    "addr:housenumber":"22",
    "addr:postcode":"k1r 6s2",
    "addr:street":"Eccles St",
    "iso:country":"CA",
    "sg:address":"22 Eccles St",
    "sg:city":"Ottawa",
    "sg:classifiers":[
        {
            "category":"Organizations",
            "subcategory":"Religious Organization",
            "type":"Services"
        }
    ],
    "sg:phone":"+1 613 235 8187",
    "sg:postcode":"K1R 6S2",
    "sg:province":"ON",
    "sg:tags":[
        "church"
    ],
    "wof:name":"Ottawa Chinese Alliance Church",
    "wof:placetype":"venue"
},
  "geometry": {"coordinates":[-75.7087097168,45.4090652466],"type":"Point"}
}