{
  "type": "Feature",
  "properties": {
    "addr:full":"Fort Mcmurray AB T9H 2K1",
    "addr:postcode":"t9h 2k1",
    "iso:country":"CA",
    "sg:city":"Fort Mcmurray",
    "sg:classifiers":[
        {
            "category":"Professional",
            "subcategory":"Lawyer & Legal Services",
            "type":"Services"
        }
    ],
    "sg:phone":"+1 780 743 6221",
    "sg:postcode":"T9H 2K1",
    "sg:province":"AB",
    "sg:tags":[
        "attorney"
    ],
    "wof:name":"Dawson, Kelly",
    "wof:placetype":"venue"
},
  "geometry": {"coordinates":[-111.37495422400001,56.7249221802],"type":"Point"}
}