{
  "type": "Feature",
  "properties": {
    "addr:full":"1693 Rue Saint-Denis Montreal QC H2X 3K4",
    "addr:housenumber":"1693",
    "addr:postcode":"h2x 3k4",
    "addr:street":"Rue Saint-Denis",
    "iso:country":"CA",
    "sg:address":"1693 Rue Saint-Denis",
    "sg:city":"Montreal",
    "sg:classifiers":[
        {
            "category":"Bars & Pubs",
            "type":"Food & Drink"
        }
    ],
    "sg:phone":"+1 514 843 6360",
    "sg:postcode":"H2X 3K4",
    "sg:province":"QC",
    "sg:tags":[
        "lounge",
        "cocktail"
    ],
    "wof:name":"Odyssee",
    "wof:placetype":"venue"
},
  "geometry": {"coordinates":[-73.56366,45.515369],"type":"Point"}
}