{
  "type": "Feature",
  "properties": {
    "addr:full":"Seeleys Bay ON K0H 2N0",
    "addr:postcode":"k0h 2n0",
    "addr:street":"Seeleys Bay",
    "iso:country":"CA",
    "sg:city":"Seeleys Bay",
    "sg:classifiers":[
        {
            "category":"Building & Trades",
            "subcategory":"Plumbing",
            "type":"Services"
        }
    ],
    "sg:phone":"+1 613 387 3432",
    "sg:postcode":"K0H 2N0",
    "sg:province":"ON",
    "sg:tags":[
        "septic"
    ],
    "wof:name":"Hogan's Septic Svc",
    "wof:placetype":"venue"
},
  "geometry": {"coordinates":[-76.2335891724,44.4783859253],"type":"Point"}
}