{
  "type": "Feature",
  "properties": {
    "addr:full":"2075 Mamette Ave Merritt BC V1K 1B8",
    "addr:housenumber":"2075",
    "addr:postcode":"v1k 1b8",
    "addr:street":"Mamette Ave",
    "iso:country":"CA",
    "sg:address":"2075 Mamette Ave",
    "sg:city":"Merritt",
    "sg:classifiers":[
        {
            "category":"Arena",
            "subcategory":"Sports Club",
            "type":"Entertainment"
        }
    ],
    "sg:phone":"+1 250 378 4832",
    "sg:postcode":"V1K 1B8",
    "sg:province":"BC",
    "sg:tags":[
        "athletic",
        "fields",
        "stadium",
        "government"
    ],
    "wof:name":"Nicola Valley Memorial Arena",
    "wof:placetype":"venue"
},
  "geometry": {"coordinates":[-120.78633117699999,50.1124000549],"type":"Point"}
}