{
  "type": "Feature",
  "properties": {
    "addr:full":"1155 Rue DE Claire-Fontaine Quebec QC G1R 3B2",
    "addr:housenumber":"1155",
    "addr:postcode":"g1r 3b2",
    "addr:street":"Rue De Claire-Fontaine",
    "iso:country":"CA",
    "sg:address":"1155 Rue DE Claire-Fontaine",
    "sg:city":"Quebec",
    "sg:classifiers":[
        {
            "category":"Shopping",
            "subcategory":"Tobacco",
            "type":"Retail Goods"
        }
    ],
    "sg:phone":"+1 418 648 9185",
    "sg:postcode":"G1R 3B2",
    "sg:province":"QC",
    "sg:tags":[
        "cigarette",
        "cigar",
        "dealer"
    ],
    "wof:name":"Tabagie Dumas Enr",
    "wof:placetype":"venue"
},
  "geometry": {"coordinates":[-71.220207,46.805878],"type":"Point"}
}