{
  "type": "Feature",
  "properties": {
    "addr:full":"5026 106 Ave NW Edmonton AB T6A 1E9",
    "addr:housenumber":"5026",
    "addr:postcode":"t6a 1e9",
    "addr:street":"106 Ave Nw",
    "iso:country":"CA",
    "sg:address":"5026 106 Ave NW",
    "sg:city":"Edmonton",
    "sg:classifiers":[
        {
            "category":"Personal",
            "subcategory":"Beauty Salon",
            "type":"Services"
        }
    ],
    "sg:phone":"+1 780 463 8197",
    "sg:postcode":"T6A 1E9",
    "sg:province":"AB",
    "wof:name":"Insync Hair & Tanning Studio",
    "wof:placetype":"venue"
},
  "geometry": {"coordinates":[-113.420868,53.551186],"type":"Point"}
}