{
  "type": "Feature",
  "properties": {
    "addr:full":"49 Rowand Ave Winnipeg MB R3J 2N6",
    "addr:housenumber":"49",
    "addr:postcode":"r3j 2n6",
    "addr:street":"Rowand Ave",
    "iso:country":"CA",
    "sg:address":"49 Rowand Ave",
    "sg:city":"Winnipeg",
    "sg:classifiers":[
        {
            "category":"Wholesale",
            "subcategory":"Non-durable Goods",
            "type":"Manufacturing & Wholesale Goods"
        }
    ],
    "sg:phone":"+1 204 831 8122",
    "sg:postcode":"R3J 2N6",
    "sg:province":"MB",
    "sg:tags":[
        "decoration",
        "glassware"
    ],
    "wof:name":"Cottage Advertising Spec",
    "wof:placetype":"venue"
},
  "geometry": {"coordinates":[-97.242081,49.877922],"type":"Point"}
}