{
  "type": "Feature",
  "properties": {
    "addr:full":"North Vancouver BC V7M 2H9",
    "addr:postcode":"v7m 2h9",
    "iso:country":"CA",
    "sg:city":"North Vancouver",
    "sg:classifiers":[
        {
            "category":"Personal",
            "subcategory":"Beauty Salon",
            "type":"Services"
        }
    ],
    "sg:phone":"+1 604 983 9900",
    "sg:postcode":"V7M 2H9",
    "sg:province":"BC",
    "sg:tags":[
        "school"
    ],
    "wof:name":"Vogue Esthetics College",
    "wof:placetype":"venue"
},
  "geometry": {"coordinates":[-123.07254,49.321419],"type":"Point"}
}