{
  "type": "Feature",
  "properties": {
    "addr:full":"160 Charing Cross Cres Winnipeg MB R2N 1P6",
    "addr:housenumber":"160",
    "addr:postcode":"r2n 1p6",
    "addr:street":"Charing Cross Cres",
    "iso:country":"CA",
    "sg:address":"160 Charing Cross Cres",
    "sg:city":"Winnipeg",
    "sg:classifiers":[
        {
            "category":"Building & Trades",
            "subcategory":"Construction",
            "type":"Services"
        }
    ],
    "sg:phone":"+1 204 254 4550",
    "sg:postcode":"R2N 1P6",
    "sg:province":"MB",
    "sg:tags":[
        "concrete",
        "contractor"
    ],
    "wof:name":"A & L Concrete Svc",
    "wof:placetype":"venue"
},
  "geometry": {"coordinates":[-97.103821,49.810112],"type":"Point"}
}