{
  "type": "Feature",
  "properties": {
    "addr:full":"26 Byng Cres Pinawa MB R0E 1L0",
    "addr:housenumber":"26",
    "addr:postcode":"r0e 1l0",
    "addr:street":"Byng Cres",
    "iso:country":"CA",
    "sg:address":"26 Byng Cres",
    "sg:city":"Pinawa",
    "sg:classifiers":[
        {
            "category":"Home & Garden",
            "subcategory":"Hardware",
            "type":"Retail Goods"
        }
    ],
    "sg:phone":"+1 204 753 2223",
    "sg:postcode":"R0E 1L0",
    "sg:province":"MB",
    "wof:name":"Pinawa Paint & Hardware",
    "wof:placetype":"venue"
},
  "geometry": {"coordinates":[-95.8869552612,50.1476974487],"type":"Point"}
}