{
  "type": "Feature",
  "properties": {
    "addr:full":"Brooks AB T1R 0G8",
    "addr:postcode":"t1r 0g8",
    "iso:country":"CA",
    "sg:city":"Brooks",
    "sg:classifiers":[
        {
            "category":"Banks & Credit Unions",
            "subcategory":"Bank",
            "type":"Services"
        }
    ],
    "sg:phone":"+1 403 362 3491",
    "sg:postcode":"T1R 0G8",
    "sg:province":"AB",
    "wof:name":"Scotiabank",
    "wof:placetype":"venue"
},
  "geometry": {"coordinates":[-111.893738,50.565525],"type":"Point"}
}