{
  "type": "Feature",
  "properties": {
    "addr:full":"1813 Route 103 Wakefield NB E7M 1B2",
    "addr:housenumber":"1813",
    "addr:postcode":"e7m 1b2",
    "addr:street":"Route 103",
    "iso:country":"CA",
    "sg:address":"1813 Route 103",
    "sg:city":"Wakefield",
    "sg:classifiers":[
        {
            "category":"Organizations",
            "subcategory":"Religious Organization",
            "type":"Services"
        }
    ],
    "sg:phone":"+1 506 375 4886",
    "sg:postcode":"E7M 1B2",
    "sg:province":"NB",
    "sg:tags":[
        "church"
    ],
    "wof:name":"Futherance Ministries",
    "wof:placetype":"venue"
},
  "geometry": {"coordinates":[-67.51992799999999,46.227417],"type":"Point"}
}