{
  "type": "Feature",
  "properties": {
    "addr:full":"Winnipeg MB R2V 3C8",
    "addr:postcode":"r2v 3c8",
    "iso:country":"CA",
    "sg:city":"Winnipeg",
    "sg:classifiers":[
        {
            "category":"Health Services",
            "subcategory":"Doctor",
            "type":"Services"
        }
    ],
    "sg:phone":"+1 204 925 4746",
    "sg:postcode":"R2V 3C8",
    "sg:province":"MB",
    "sg:tags":[
        "dentist"
    ],
    "wof:name":"Mark Rykiss & Assoc",
    "wof:placetype":"venue"
},
  "geometry": {"coordinates":[-97.149551,49.951447],"type":"Point"}
}