{
  "type": "Feature",
  "properties": {
    "iso:country":"CA",
    "sg:city":"Winnipeg",
    "sg:classifiers":[
        {
            "category":"Wholesale",
            "subcategory":"Durable Goods & Equipment",
            "type":"Manufacturing & Wholesale Goods"
        }
    ],
    "sg:phone":"+1 204 255 3109",
    "sg:postcode":"R2J 4A9",
    "sg:province":"MB",
    "sg:tags":[
        "representative",
        "manufacturer"
    ],
    "wof:name":"NU-Dent Canada",
    "wof:placetype":"venue"
},
  "geometry": {"coordinates":[-97.07164001460001,49.854259491],"type":"Point"}
}