{
  "type": "Feature",
  "properties": {
    "addr:full":"1265 Boul Saint-Laurent O Louiseville QC J5V 2L4",
    "addr:housenumber":"1265",
    "addr:postcode":"j5v 2l4",
    "addr:street":"Boul Saint-Laurent O",
    "iso:country":"CA",
    "sg:address":"1265 Boul Saint-Laurent O",
    "sg:city":"Louiseville",
    "sg:classifiers":[
        {
            "category":"Autos & Motor Vehicles",
            "subcategory":"Recreational Vehicle Sales",
            "type":"Retail Goods"
        }
    ],
    "sg:phone":"+1 819 228 5852",
    "sg:postcode":"J5V 2L4",
    "sg:province":"QC",
    "wof:name":"Roulottes Gaetan Dupuis Inc",
    "wof:placetype":"venue"
},
  "geometry": {"coordinates":[-72.8938903809,46.2619667053],"type":"Point"}
}