{
  "type": "Feature",
  "properties": {
    "addr:full":"7492 Broadway Burnaby BC V5A 1S4",
    "addr:housenumber":"7492",
    "addr:postcode":"v5a 1s4",
    "addr:street":"Broadway",
    "iso:country":"CA",
    "sg:address":"7492 Broadway",
    "sg:city":"Burnaby",
    "sg:classifiers":[
        {
            "category":"Building & Trades",
            "subcategory":"Construction",
            "type":"Services"
        }
    ],
    "sg:phone":"+1 604 420 2329",
    "sg:postcode":"V5A 1S4",
    "sg:province":"BC",
    "sg:tags":[
        "contractor",
        "dry wall",
        "general"
    ],
    "wof:name":"Coastal Plastering & Drywall",
    "wof:placetype":"venue"
},
  "geometry": {"coordinates":[-122.945396,49.261139],"type":"Point"}
}