{
  "type": "Feature",
  "properties": {
    "addr:full":"4308 Kingston Rd Scarborough ON M1E 2M8",
    "addr:housenumber":"4308",
    "addr:postcode":"m1e 2m8",
    "addr:street":"Kingston Rd",
    "iso:country":"CA",
    "sg:address":"4308 Kingston Rd",
    "sg:city":"Scarborough",
    "sg:classifiers":[
        {
            "category":"Autos & Motor Vehicles",
            "subcategory":"Automobile Sales",
            "type":"Retail Goods"
        }
    ],
    "sg:phone":"+1 416 283 4944",
    "sg:postcode":"M1E 2M8",
    "sg:province":"ON",
    "sg:tags":[
        "car",
        "dealer"
    ],
    "wof:name":"Emerald Motors Inc",
    "wof:placetype":"venue"
},
  "geometry": {"coordinates":[-79.1929550171,43.7643432617],"type":"Point"}
}