{
  "type": "Feature",
  "properties": {
    "addr:full":"Calgary AB T2T 5R9",
    "addr:postcode":"t2t 5r9",
    "iso:country":"CA",
    "sg:city":"Calgary",
    "sg:classifiers":[
        {
            "category":"Professional",
            "subcategory":"Detective & Security Services",
            "type":"Services"
        }
    ],
    "sg:phone":"+1 403 237 5468",
    "sg:postcode":"T2T 5R9",
    "sg:province":"AB",
    "sg:tags":[
        "civil",
        "enforcement"
    ],
    "wof:name":"Allied Civil Enforcement Inc",
    "wof:placetype":"venue"
},
  "geometry": {"coordinates":[-114.08764600000001,51.037685],"type":"Point"}
}