{
  "type": "Feature",
  "properties": {
    "iso:country":"CA",
    "sg:city":"North Vancouver",
    "sg:classifiers":[
        {
            "category":"Health Services",
            "subcategory":"Health Practitioner",
            "type":"Services"
        }
    ],
    "sg:phone":"+1 604 987 5291",
    "sg:postcode":"V7L 2L3",
    "sg:province":"BC",
    "sg:tags":[
        "physiotherapist"
    ],
    "wof:name":"North Shore Orthopedic & Sprts",
    "wof:placetype":"venue"
},
  "geometry": {"coordinates":[-123.07144928,49.319858551],"type":"Point"}
}