{
  "type": "Feature",
  "properties": {
    "iso:country":"CA",
    "sg:address":"50 Albert St",
    "sg:city":"Clinton",
    "sg:classifiers":[
        {
            "category":"Health Services",
            "subcategory":"Medical Lab",
            "type":"Services"
        }
    ],
    "sg:phone":"+1 519 482 1195",
    "sg:postcode":"N0M 1L0",
    "sg:province":"ON",
    "wof:name":"Albert Street Denture Clinic",
    "wof:placetype":"venue"
},
  "geometry": {"coordinates":[-81.5399017334,43.6189346313],"type":"Point"}
}