{
  "type": "Feature",
  "properties": {
    "iso:country":"CA",
    "sg:address":"278 132 Rte",
    "sg:city":"Paspebiac",
    "sg:classifiers":[
        {
            "category":"Personal",
            "subcategory":"Beauty Salon",
            "type":"Services"
        }
    ],
    "sg:phone":"+1 418 752 6707",
    "sg:postcode":"G0C 2K0",
    "sg:province":"QC",
    "wof:name":"Salon DE Coiffure Janique",
    "wof:placetype":"venue"
},
  "geometry": {"coordinates":[-65.2492675781,48.028968811],"type":"Point"}
}