{
  "type": "Feature",
  "properties": {
    "addr:full":"North York ON M3J 2C9",
    "addr:postcode":"m3j 2c9",
    "iso:country":"CA",
    "sg:city":"North York",
    "sg:classifiers":[
        {
            "category":"Home & Garden",
            "subcategory":"Carpets & Floor Coverings",
            "type":"Retail Goods"
        }
    ],
    "sg:phone":"+1 416 665 1510",
    "sg:postcode":"M3J 2C9",
    "sg:province":"ON",
    "sg:tags":[
        "dealer",
        "rug"
    ],
    "wof:name":"Top Quality Carpet",
    "wof:placetype":"venue"
},
  "geometry": {"coordinates":[-79.47086299999999,43.767838],"type":"Point"}
}