{
  "type": "Feature",
  "properties": {
    "addr:full":"1453 Rue Beaubien E Montreal QC H2G 3C6",
    "addr:housenumber":"1453",
    "addr:postcode":"h2g 3c6",
    "addr:street":"Rue Beaubien E",
    "iso:country":"CA",
    "sg:address":"1453 Rue Beaubien E",
    "sg:city":"Montreal",
    "sg:classifiers":[
        {
            "category":"Professional",
            "subcategory":"Management & Consulting",
            "type":"Services"
        }
    ],
    "sg:phone":"+1 514 278 7211",
    "sg:postcode":"H2G 3C6",
    "sg:province":"QC",
    "sg:tags":[
        "consultant",
        "business"
    ],
    "wof:name":"Groupe Conseil Saint Denis",
    "wof:placetype":"venue"
},
  "geometry": {"coordinates":[-73.5986633301,45.5412368774],"type":"Point"}
}