{
  "type": "Feature",
  "properties": {
    "addr:full":"Red Deer AB T4N 4L1",
    "addr:postcode":"t4n 4l1",
    "iso:country":"CA",
    "sg:city":"Red Deer",
    "sg:classifiers":[
        {
            "category":"Autos & Motor Vehicles",
            "subcategory":"Auto Supplies",
            "type":"Retail Goods"
        }
    ],
    "sg:phone":"+1 403 340 2773",
    "sg:postcode":"T4N 4L1",
    "sg:province":"AB",
    "sg:tags":[
        "alternator",
        "generator"
    ],
    "wof:name":"Choice Auto Electric Repair",
    "wof:placetype":"venue"
},
  "geometry": {"coordinates":[-113.81708500000001,52.29414],"type":"Point"}
}