{
  "type": "Feature",
  "properties": {
    "iso:country":"CA",
    "sg:address":"83 Ashwarren Rd",
    "sg:city":"North York",
    "sg:classifiers":[
        {
            "category":"Wholesale",
            "subcategory":"Non-durable Goods",
            "type":"Manufacturing & Wholesale Goods"
        }
    ],
    "sg:phone":"+1 416 398 4445",
    "sg:postcode":"M3J 1Z7",
    "sg:province":"ON",
    "sg:tags":[
        "novelty"
    ],
    "wof:name":"Jal Enterprises",
    "wof:placetype":"venue"
},
  "geometry": {"coordinates":[-79.48365783689999,43.7574005127],"type":"Point"}
}