{
  "type": "Feature",
  "properties": {
    "addr:full":"22 Nantucket Blvd Scarborough ON M1P 2N4",
    "addr:housenumber":"22",
    "addr:postcode":"m1p 2n4",
    "addr:street":"Nantucket Blvd",
    "iso:country":"CA",
    "sg:address":"22 Nantucket Blvd",
    "sg:city":"Scarborough",
    "sg:classifiers":[
        {
            "category":"Professional",
            "subcategory":"Employment Agencies",
            "type":"Services"
        }
    ],
    "sg:phone":"+1 416 614 2398",
    "sg:postcode":"M1P 2N4",
    "sg:province":"ON",
    "sg:tags":[
        "leasing"
    ],
    "wof:name":"Hamilton Distributions",
    "wof:placetype":"venue"
},
  "geometry": {"coordinates":[-79.2724075317,43.7522277832],"type":"Point"}
}