{
  "type": "Feature",
  "properties": {
    "addr:full":"3450 Landmark Rd Burlington ON L7M 1S8",
    "addr:housenumber":"3450",
    "addr:postcode":"l7m 1s8",
    "addr:street":"Landmark Rd",
    "iso:country":"CA",
    "sg:address":"3450 Landmark Rd",
    "sg:city":"Burlington",
    "sg:classifiers":[
        {
            "category":"Building & Trades",
            "subcategory":"Plumbing",
            "type":"Services"
        }
    ],
    "sg:phone":"+1 905 319 2730",
    "sg:postcode":"L7M 1S8",
    "sg:province":"ON",
    "sg:tags":[
        "mechanical",
        "general",
        "contractor"
    ],
    "wof:name":"Bramkal Contractors Inc",
    "wof:placetype":"venue"
},
  "geometry": {"coordinates":[-79.797234,43.367023],"type":"Point"}
}