{
  "type": "Feature",
  "properties": {
    "addr:full":"90 Northline Rd North York ON M4B 3E5",
    "addr:housenumber":"90",
    "addr:postcode":"m4b 3e5",
    "addr:street":"Northline Rd",
    "iso:country":"CA",
    "sg:address":"90 Northline Rd",
    "sg:city":"North York",
    "sg:classifiers":[
        {
            "category":"Real Estate",
            "subcategory":"Real Estate Agent",
            "type":"Services"
        }
    ],
    "sg:phone":"+1 416 750 4644",
    "sg:postcode":"M4B 3E5",
    "sg:province":"ON",
    "sg:tags":[
        "management"
    ],
    "wof:name":"Surrey Plaza Ltd",
    "wof:placetype":"venue"
},
  "geometry": {"coordinates":[-79.41255200000001,43.767914],"type":"Point"}
}