{
  "type": "Feature",
  "properties": {
    "iso:country":"CA",
    "sg:address":"533 Dominion St",
    "sg:city":"Prince George",
    "sg:classifiers":[
        {
            "category":"Organizations",
            "subcategory":"Professional Association",
            "type":"Services"
        }
    ],
    "sg:phone":"+1 250 562 4722",
    "sg:postcode":"V2L 1T7",
    "sg:province":"BC",
    "sg:tags":[
        "club"
    ],
    "wof:name":"Prince George Italian Club",
    "wof:placetype":"venue"
},
  "geometry": {"coordinates":[-122.746482849,53.914478302],"type":"Point"}
}