{
  "type": "Feature",
  "properties": {
    "addr:full":"1277 Jalna Blvd London ON N6E 2G3",
    "addr:housenumber":"1277",
    "addr:postcode":"n6e 2g3",
    "addr:street":"Jalna Blvd",
    "iso:country":"CA",
    "sg:address":"1277 Jalna Blvd",
    "sg:city":"London",
    "sg:classifiers":[
        {
            "category":"Wholesale",
            "subcategory":"Durable Goods & Equipment",
            "type":"Manufacturing & Wholesale Goods"
        }
    ],
    "sg:phone":"+1 519 668 3607",
    "sg:postcode":"N6E 2G3",
    "sg:province":"ON",
    "sg:tags":[
        "fire",
        "extinguisher"
    ],
    "wof:name":"Brennan Fire Equipment",
    "wof:placetype":"venue"
},
  "geometry": {"coordinates":[-81.231697,42.92614],"type":"Point"}
}