{
  "type": "Feature",
  "properties": {
    "addr:full":"640 Front St Nelson BC V1L 4B7",
    "addr:housenumber":"640",
    "addr:postcode":"bc v1l 4b7",
    "addr:street":"Front St",
    "iso:country":"CA",
    "sg:address":"640 Front St",
    "sg:city":"Nelson",
    "sg:classifiers":[
        {
            "category":"Shopping",
            "type":"Retail Goods"
        }
    ],
    "sg:phone":"+1 250 354 4338",
    "sg:postcode":"V1L 4B7",
    "sg:province":"BC",
    "sg:tags":[
        "picture",
        "frame"
    ],
    "wof:name":"Frame Shop",
    "wof:placetype":"venue"
},
  "geometry": {"coordinates":[-117.293968201,49.4946632385],"type":"Point"}
}