{
  "type": "Feature",
  "properties": {
    "addr:full":"930 Edgemere Rd Fort Erie ON L2A 1A8",
    "addr:housenumber":"930",
    "addr:postcode":"l2a 1a8",
    "addr:street":"Edgemere Rd",
    "iso:country":"CA",
    "sg:address":"930 Edgemere Rd",
    "sg:city":"Fort Erie",
    "sg:classifiers":[
        {
            "category":"Real Estate",
            "subcategory":"Real Estate Agent",
            "type":"Services"
        }
    ],
    "sg:phone":"+1 905 871 7360",
    "sg:postcode":"L2A 1A8",
    "sg:province":"ON",
    "sg:tags":[
        "inspection"
    ],
    "wof:name":"Peninsula Home Inspection",
    "wof:placetype":"venue"
},
  "geometry": {"coordinates":[-78.94795999999999,42.883919],"type":"Point"}
}