{
  "type": "Feature",
  "properties": {
    "addr:full":"Winnipeg MB R2H 0R7",
    "addr:postcode":"r2h 0r7",
    "iso:country":"CA",
    "sg:city":"Winnipeg",
    "sg:classifiers":[
        {
            "category":"Professional",
            "subcategory":"Business Services",
            "type":"Services"
        }
    ],
    "sg:phone":"+1 204 233 6286",
    "sg:postcode":"R2H 0R7",
    "sg:province":"MB",
    "sg:tags":[
        "recording",
        "studio"
    ],
    "wof:name":"Kzoo Radio Works",
    "wof:placetype":"venue"
},
  "geometry": {"coordinates":[-97.12159699999999,49.882252],"type":"Point"}
}