{
  "type": "Feature",
  "properties": {
    "addr:full":"1385 Kingsway Ave Port Coquitlam BC V3C 1S2",
    "addr:housenumber":"1385",
    "addr:postcode":"v3c 1s2",
    "addr:street":"Kingsway Ave",
    "iso:country":"CA",
    "sg:address":"1385 Kingsway Ave",
    "sg:city":"Port Coquitlam",
    "sg:classifiers":[
        {
            "category":"Building & Trades",
            "subcategory":"Construction",
            "type":"Services"
        }
    ],
    "sg:phone":"+1 604 944 2977",
    "sg:postcode":"V3C 1S2",
    "sg:province":"BC",
    "sg:tags":[
        "roofing",
        "contractor"
    ],
    "wof:name":"Design Roofing & Sheet Metal",
    "wof:placetype":"venue"
},
  "geometry": {"coordinates":[-122.7525177,49.248752594],"type":"Point"}
}