{
  "type": "Feature",
  "properties": {
    "addr:full":"1095 Rue Vincent-Massey Quebec QC G1N 1N2",
    "addr:housenumber":"1095",
    "addr:postcode":"g1n 1n2",
    "addr:street":"Rue Vincent-Massey",
    "iso:country":"CA",
    "sg:address":"1095 Rue Vincent-Massey",
    "sg:city":"Quebec",
    "sg:classifiers":[
        {
            "category":"Wholesale",
            "subcategory":"Scrap",
            "type":"Manufacturing & Wholesale Goods"
        }
    ],
    "sg:phone":"+1 418 527 8050",
    "sg:postcode":"G1N 1N2",
    "sg:province":"QC",
    "sg:tags":[
        "recycling",
        "paper",
        "center"
    ],
    "wof:name":"Recyclage Vanier Inc",
    "wof:placetype":"venue"
},
  "geometry": {"coordinates":[-71.2531585693,46.8041763306],"type":"Point"}
}