{
  "type": "Feature",
  "properties": {
    "addr:full":"587 Devonshire Ave Woodstock ON N4S 5P9",
    "addr:housenumber":"587",
    "addr:postcode":"n4s 5p9",
    "addr:street":"Devonshire Ave",
    "iso:country":"CA",
    "sg:address":"587 Devonshire Ave",
    "sg:city":"Woodstock",
    "sg:classifiers":[
        {
            "category":"Wholesale",
            "subcategory":"Apparel",
            "type":"Manufacturing & Wholesale Goods"
        }
    ],
    "sg:phone":"+1 519 421 1840",
    "sg:postcode":"N4S 5P9",
    "sg:province":"ON",
    "sg:tags":[
        "textile",
        "broker"
    ],
    "wof:name":"Textile Technology Transfers",
    "wof:placetype":"venue"
},
  "geometry": {"coordinates":[-80.755257,43.143124],"type":"Point"}
}