{
  "type": "Feature",
  "properties": {
    "addr:full":"42 Havenwood Way London ON N6H 5B8",
    "addr:housenumber":"42",
    "addr:postcode":"n6h 5b8",
    "addr:street":"Havenwood Way",
    "iso:country":"CA",
    "sg:address":"42 Havenwood Way",
    "sg:city":"London",
    "sg:classifiers":[
        {
            "category":"Shopping",
            "subcategory":"Computers & Home Electronics",
            "type":"Retail Goods"
        }
    ],
    "sg:phone":"+1 519 657 4873",
    "sg:postcode":"N6H 5B8",
    "sg:province":"ON",
    "sg:tags":[
        "software"
    ],
    "wof:name":"Planet Micro",
    "wof:placetype":"venue"
},
  "geometry": {"coordinates":[-81.32512664790001,42.9671173096],"type":"Point"}
}