{
  "type": "Feature",
  "properties": {
    "iso:country":"CA",
    "sg:city":"Toronto",
    "sg:classifiers":[
        {
            "category":"Building & Trades",
            "subcategory":"Construction",
            "type":"Services"
        }
    ],
    "sg:phone":"+1 416 866 8966",
    "sg:postcode":"M5A 1M1",
    "sg:province":"ON",
    "sg:tags":[
        "general",
        "contractor"
    ],
    "wof:name":"Equinox Development Inc",
    "wof:placetype":"venue"
},
  "geometry": {"coordinates":[-79.35743,43.656292],"type":"Point"}
}