{
  "type": "Feature",
  "properties": {
    "addr:full":"511 Robinson Ave Selkirk MB R1A 1E5",
    "addr:housenumber":"511",
    "addr:postcode":"r1a 1e5",
    "addr:street":"Robinson Ave",
    "iso:country":"CA",
    "sg:address":"511 Robinson Ave",
    "sg:city":"Selkirk",
    "sg:classifiers":[
        {
            "category":"Professional",
            "subcategory":"Employment Agencies",
            "type":"Services"
        }
    ],
    "sg:phone":"+1 204 482 2100",
    "sg:postcode":"R1A 1E5",
    "sg:province":"MB",
    "sg:tags":[
        "opportunity"
    ],
    "wof:name":"Job Quest",
    "wof:placetype":"venue"
},
  "geometry": {"coordinates":[-96.875778,50.150806],"type":"Point"}
}