{
  "type": "Feature",
  "properties": {
    "addr:full":"950 Brookdale Ave Cornwall ON K6J 4P5",
    "addr:housenumber":"950",
    "addr:postcode":"k6j 4p5",
    "addr:street":"Brookdale Ave",
    "iso:country":"CA",
    "sg:address":"950 Brookdale Ave",
    "sg:city":"Cornwall",
    "sg:classifiers":[
        {
            "category":"Personal",
            "subcategory":"Beauty Salon",
            "type":"Services"
        }
    ],
    "sg:phone":"+1 613 933 1049",
    "sg:postcode":"K6J 4P5",
    "sg:province":"ON",
    "wof:name":"Smart Style Inc",
    "wof:placetype":"venue"
},
  "geometry": {"coordinates":[-74.7498626709,45.0246391296],"type":"Point"}
}