{
  "type": "Feature",
  "properties": {
    "addr:full":"414 Erb St W Waterloo ON N2L 1W8",
    "addr:housenumber":"414",
    "addr:postcode":"n2l 1w8",
    "addr:street":"Erb St W",
    "iso:country":"CA",
    "sg:address":"414 Erb St W",
    "sg:city":"Waterloo",
    "sg:classifiers":[
        {
            "category":"Retail",
            "subcategory":"Veterinary Services",
            "type":"Services"
        }
    ],
    "sg:phone":"+1 519 747 2020",
    "sg:postcode":"N2L 1W8",
    "sg:province":"ON",
    "sg:tags":[
        "veterinarian"
    ],
    "wof:name":"Waterloo West Animal Hospital",
    "wof:placetype":"venue"
},
  "geometry": {"coordinates":[-80.552887,43.452785],"type":"Point"}
}