{
  "type": "Feature",
  "properties": {
    "iso:country":"CA",
    "sg:address":"673 Trunk Rd",
    "sg:city":"Sault Ste Marie",
    "sg:classifiers":[
        {
            "category":"Restaurant",
            "type":"Food & Drink"
        }
    ],
    "sg:phone":"+1 705 942 2459",
    "sg:postcode":"P6A 3T1",
    "sg:province":"ON",
    "wof:name":"Mc Donald's",
    "wof:placetype":"venue"
},
  "geometry": {"coordinates":[-84.274055481,46.5216217041],"type":"Point"}
}