{
  "type": "Feature",
  "properties": {
    "iso:country":"CA",
    "sg:address":"335 Bloor St W",
    "sg:city":"Oshawa",
    "sg:classifiers":[
        {
            "category":"Retail",
            "subcategory":"Auto Repair",
            "type":"Services"
        }
    ],
    "sg:phone":"+1 905 723 8181",
    "sg:postcode":"L1J 1R1",
    "sg:province":"ON",
    "sg:tags":[
        "body",
        "automobile",
        "painting"
    ],
    "wof:name":"Gannon's Auto Body Ltd",
    "wof:placetype":"venue"
},
  "geometry": {"coordinates":[-78.8682174683,43.8775596619],"type":"Point"}
}