{
  "type": "Feature",
  "properties": {
    "addr:full":"750 Rue DE LA Visitation Saint-Charles-Borromee QC J6E 7Y8",
    "addr:housenumber":"750",
    "addr:postcode":"j6e 7y8",
    "addr:street":"Rue De La Visitation Saint-Charles-Borromee",
    "iso:country":"CA",
    "sg:address":"750 Rue DE LA Visitation",
    "sg:city":"Saint-Charles-Borromee",
    "sg:classifiers":[
        {
            "category":"Retail",
            "subcategory":"Auto Repair",
            "type":"Services"
        }
    ],
    "sg:phone":"+1 450 756 8922",
    "sg:postcode":"J6E 7Y8",
    "sg:province":"QC",
    "sg:tags":[
        "repairing",
        "automobile",
        "wheel",
        "alignment"
    ],
    "wof:name":"Alignement Raymond Enrg",
    "wof:placetype":"venue"
},
  "geometry": {"coordinates":[-73.472786,46.054039],"type":"Point"}
}