{
  "type": "Feature",
  "properties": {
    "iso:country":"CA",
    "sg:address":"1990 Como Lake Ave",
    "sg:city":"Coquitlam",
    "sg:classifiers":[
        {
            "category":"Autos & Motor Vehicles",
            "subcategory":"Fuel & Gas Station",
            "type":"Retail Goods"
        }
    ],
    "sg:phone":"+1 604 939 8626",
    "sg:postcode":"V3J 3R3",
    "sg:province":"BC",
    "sg:tags":[
        "oil"
    ],
    "wof:name":"Como Lake Village Shell",
    "wof:placetype":"venue"
},
  "geometry": {"coordinates":[-122.837524414,49.2632217407],"type":"Point"}
}