{
  "type": "Feature",
  "properties": {
    "addr:full":"252 North Front St Belleville ON K8P 3C4",
    "addr:housenumber":"252",
    "addr:postcode":"k8p 3c4",
    "addr:street":"North Front St",
    "iso:country":"CA",
    "sg:address":"252 North Front St",
    "sg:city":"Belleville",
    "sg:classifiers":[
        {
            "category":"Retail",
            "subcategory":"Auto Rental",
            "type":"Services"
        }
    ],
    "sg:phone":"+1 613 969 1645",
    "sg:postcode":"K8P 3C4",
    "sg:province":"ON",
    "sg:tags":[
        "renting",
        "automobile"
    ],
    "wof:name":"A Discount Car & Truck Rentals",
    "wof:placetype":"venue"
},
  "geometry": {"coordinates":[-77.393585,44.18222],"type":"Point"}
}