{
  "type": "Feature",
  "properties": {
    "addr:full":"1756 Pandora St Vancouver BC V5L 1M1",
    "addr:housenumber":"1756",
    "addr:postcode":"v5l 1m1",
    "addr:street":"Pandora St",
    "iso:country":"CA",
    "sg:address":"1756 Pandora St",
    "sg:city":"Vancouver",
    "sg:classifiers":[
        {
            "category":"Wholesale",
            "subcategory":"Meat",
            "type":"Manufacturing & Wholesale Goods"
        }
    ],
    "sg:phone":"+1 604 254 9885",
    "sg:postcode":"V5L 1M1",
    "sg:province":"BC",
    "sg:tags":[
        "poultry",
        "plant",
        "processing"
    ],
    "wof:name":"Hallmark Poultry Processors",
    "wof:placetype":"venue"
},
  "geometry": {"coordinates":[-123.06912199999999,49.282997],"type":"Point"}
}