{
  "type": "Feature",
  "properties": {
    "iso:country":"CA",
    "sg:address":"21 Main St W",
    "sg:city":"Saint John",
    "sg:classifiers":[
        {
            "category":"Food & Beverages",
            "subcategory":"Groceries & Convenience Stores",
            "type":"Retail Goods"
        }
    ],
    "sg:phone":"+1 506 657 1000",
    "sg:postcode":"E2M 3M9",
    "sg:province":"NB",
    "sg:tags":[
        "grocer"
    ],
    "wof:name":"Westside Variety & Video",
    "wof:placetype":"venue"
},
  "geometry": {"coordinates":[-66.0995254517,45.2571601868],"type":"Point"}
}