{
  "type": "Feature",
  "properties": {
    "addr:full":"22444 72 Ave Langley BC V2Y 2K4",
    "addr:housenumber":"22444",
    "addr:postcode":"v2y 2k4",
    "addr:street":"72 Ave",
    "iso:country":"CA",
    "sg:address":"22444 72 Ave",
    "sg:city":"Langley",
    "sg:classifiers":[
        {
            "category":"Wholesale",
            "subcategory":"Machinery & Supplies",
            "type":"Manufacturing & Wholesale Goods"
        }
    ],
    "sg:phone":"+1 604 888 7105",
    "sg:postcode":"V2Y 2K4",
    "sg:province":"BC",
    "sg:tags":[
        "equipment",
        "foundry"
    ],
    "wof:name":"Mc Nicholls Foundry & Tool",
    "wof:placetype":"venue"
},
  "geometry": {"coordinates":[-122.600578308,49.1316680908],"type":"Point"}
}