{
  "type": "Feature",
  "properties": {
    "addr:full":"1505 13th St W Prince Albert SK S6V 3J7",
    "addr:housenumber":"1505",
    "addr:postcode":"s6v 3j7",
    "addr:street":"13Th St",
    "iso:country":"CA",
    "sg:address":"1505 13th St W",
    "sg:city":"Prince Albert",
    "sg:classifiers":[
        {
            "category":"Organizations",
            "subcategory":"Religious Organization",
            "type":"Services"
        }
    ],
    "sg:phone":"+1 306 763 5658",
    "sg:postcode":"S6V 3J7",
    "sg:province":"SK",
    "sg:tags":[
        "church"
    ],
    "wof:name":"St Michael's Parish",
    "wof:placetype":"venue"
},
  "geometry": {"coordinates":[-105.790863,53.200806],"type":"Point"}
}