{
  "type": "Feature",
  "properties": {
    "iso:country":"CA",
    "sg:city":"Toronto",
    "sg:classifiers":[
        {
            "category":"Banks & Credit Unions",
            "subcategory":"Investment Brokerage",
            "type":"Services"
        }
    ],
    "sg:phone":"+1 416 594 7950",
    "sg:postcode":"M5H 3G2",
    "sg:province":"ON",
    "wof:name":"Wood Gundy Inc",
    "wof:placetype":"venue"
},
  "geometry": {"coordinates":[-79.3866653442,43.648311615],"type":"Point"}
}