{
  "type": "Feature",
  "properties": {
    "iso:country":"CA",
    "sg:address":"2257 Bloor St W",
    "sg:city":"Toronto",
    "sg:classifiers":[
        {
            "category":"Shopping",
            "subcategory":"Gifts & Souvenirs",
            "type":"Retail Goods"
        }
    ],
    "sg:phone":"+1 416 767 6233",
    "sg:postcode":"M6S 1N8",
    "sg:province":"ON",
    "sg:tags":[
        "shop"
    ],
    "wof:name":"Ling's Importers",
    "wof:placetype":"venue"
},
  "geometry": {"coordinates":[-79.4778213501,43.6506538391],"type":"Point"}
}