{
  "type": "Feature",
  "properties": {
    "iso:country":"CA",
    "sg:address":"307 Av Dorval",
    "sg:city":"Dorval",
    "sg:classifiers":[
        {
            "category":"Retail",
            "subcategory":"Veterinary Services",
            "type":"Services"
        }
    ],
    "sg:phone":"+1 514 631 2345",
    "sg:postcode":"H9S 3H6",
    "sg:province":"QC",
    "sg:tags":[
        "clinic",
        "veterinarian"
    ],
    "wof:name":"Clinique Veterinaire Dorval",
    "wof:placetype":"venue"
},
  "geometry": {"coordinates":[-73.74053192140001,45.4439811707],"type":"Point"}
}