{
  "type": "Feature",
  "properties": {
    "addr:full":"1920 Bank St Ottawa ON K1V 7Z8",
    "addr:housenumber":"1920",
    "addr:postcode":"k1v 7z8",
    "addr:street":"Bank St",
    "iso:country":"CA",
    "sg:address":"1920 Bank St",
    "sg:city":"Ottawa",
    "sg:classifiers":[
        {
            "category":"Restaurant",
            "type":"Food & Drink"
        }
    ],
    "sg:phone":"+1 613 521 5557",
    "sg:postcode":"K1V 7Z8",
    "sg:province":"ON",
    "sg:tags":[
        "delicatessen",
        "sausage"
    ],
    "wof:name":"Bank Street Sausage & Deli",
    "wof:placetype":"venue"
},
  "geometry": {"coordinates":[-75.662155,45.368107],"type":"Point"}
}