{
  "type": "Feature",
  "properties": {
    "addr:full":"16020 River Rd Richmond BC V6V 1L6",
    "addr:housenumber":"16020",
    "addr:postcode":"v6v 1l6",
    "addr:street":"River Rd",
    "iso:country":"CA",
    "sg:address":"16020 River Rd",
    "sg:city":"Richmond",
    "sg:classifiers":[
        {
            "category":"Recreation",
            "subcategory":"Marina",
            "type":"Entertainment"
        }
    ],
    "sg:phone":"+1 604 273 8321",
    "sg:postcode":"V6V 1L6",
    "sg:province":"BC",
    "sg:tags":[
        "automobile",
        "storage",
        "boat"
    ],
    "wof:name":"North Fraser Storage Park",
    "wof:placetype":"venue"
},
  "geometry": {"coordinates":[-123.04497499999999,49.202072],"type":"Point"}
}