{
  "type": "Feature",
  "properties": {
    "iso:country":"CA",
    "sg:address":"1983 Rue Principale",
    "sg:city":"Saint-Dominique",
    "sg:classifiers":[
        {
            "category":"Wholesale",
            "subcategory":"Groceries",
            "type":"Manufacturing & Wholesale Goods"
        }
    ],
    "sg:phone":"+1 450 773 3232",
    "sg:postcode":"J0H 1L0",
    "sg:province":"QC",
    "sg:tags":[
        "honey"
    ],
    "wof:name":"Dubreuil Francois Agneau Laine",
    "wof:placetype":"venue"
},
  "geometry": {"coordinates":[-72.8165359497,45.5376739502],"type":"Point"}
}