{
  "type": "Feature",
  "properties": {
    "iso:country":"CA",
    "sg:address":"1502 Coldwater Ave",
    "sg:city":"Merritt",
    "sg:classifiers":[
        {
            "category":"Food & Beverages",
            "subcategory":"Groceries & Convenience Stores",
            "type":"Retail Goods"
        }
    ],
    "sg:phone":"+1 250 378 5336",
    "sg:postcode":"V1K 1B8",
    "sg:province":"BC",
    "sg:tags":[
        "grocer"
    ],
    "wof:name":"Corner Market",
    "wof:placetype":"venue"
},
  "geometry": {"coordinates":[-120.799072266,50.1122436523],"type":"Point"}
}