{
  "type": "Feature",
  "properties": {
    "addr:full":"41 Bridge St W Tillsonburg ON N4G 5P2",
    "addr:housenumber":"41",
    "addr:postcode":"n4g 5p2",
    "addr:street":"Bridge St W",
    "iso:country":"CA",
    "sg:address":"41 Bridge St W",
    "sg:city":"Tillsonburg",
    "sg:classifiers":[
        {
            "category":"Shopping",
            "type":"Retail Goods"
        }
    ],
    "sg:phone":"+1 519 842 6151",
    "sg:postcode":"N4G 5P2",
    "sg:province":"ON",
    "sg:tags":[
        "art",
        "gallery",
        "dealer"
    ],
    "wof:name":"Station Arts Ctr",
    "wof:placetype":"venue"
},
  "geometry": {"coordinates":[-80.73188781739999,42.862197876],"type":"Point"}
}