{
  "type": "Feature",
  "properties": {
    "addr:full":"29 Ridgeview Dr Lower Sackville NS B4C 1L8",
    "addr:housenumber":"29",
    "addr:postcode":"b4c 1l8",
    "addr:street":"Ridgeview Dr",
    "iso:country":"CA",
    "sg:address":"29 Ridgeview Dr",
    "sg:city":"Lower Sackville",
    "sg:classifiers":[
        {
            "category":"Building & Trades",
            "subcategory":"Construction",
            "type":"Services"
        }
    ],
    "sg:phone":"+1 902 864 1810",
    "sg:postcode":"B4C 1L8",
    "sg:province":"NS",
    "sg:tags":[
        "general",
        "contractor"
    ],
    "wof:name":"Bollivar Construction Ltd",
    "wof:placetype":"venue"
},
  "geometry": {"coordinates":[-63.677292,44.769382],"type":"Point"}
}