{
  "type": "Feature",
  "properties": {
    "addr:full":"461 Rue Richelieu Quebec QC G1R 1K2",
    "addr:housenumber":"461",
    "addr:postcode":"g1r 1k2",
    "addr:street":"Rue Richelieu",
    "iso:country":"CA",
    "sg:address":"461 Rue Richelieu",
    "sg:city":"Quebec",
    "sg:classifiers":[
        {
            "category":"Government",
            "subcategory":"Office",
            "type":"Public Place"
        }
    ],
    "sg:phone":"+1 418 644 4482",
    "sg:postcode":"G1R 1K2",
    "sg:province":"QC",
    "wof:name":"Quebec Conservatoire D'Art",
    "wof:placetype":"venue"
},
  "geometry": {"coordinates":[-71.2222442627,46.8100318909],"type":"Point"}
}