{
  "type": "Feature",
  "properties": {
    "addr:full":"1086 Rue Marquette Longueuil QC J4K 4H6",
    "addr:housenumber":"1086",
    "addr:postcode":"j4k 4h6",
    "addr:street":"Rue Marquette",
    "iso:country":"CA",
    "sg:address":"1086 Rue Marquette",
    "sg:city":"Longueuil",
    "sg:classifiers":[
        {
            "category":"Building & Trades",
            "subcategory":"Plumbing",
            "type":"Services"
        }
    ],
    "sg:phone":"+1 450 442 9305",
    "sg:postcode":"J4K 4H6",
    "sg:province":"QC",
    "sg:tags":[
        "contractor"
    ],
    "wof:name":"Debouchage D'Egouts R Fournier",
    "wof:placetype":"venue"
},
  "geometry": {"coordinates":[-73.50121300000001,45.521568],"type":"Point"}
}