{
  "type": "Feature",
  "properties": {
    "addr:full":"2340 Rosser Ave Brandon MB R7B 0E3",
    "addr:postcode":"2340;r7b 0e3",
    "addr:street":"Rosser Ave",
    "iso:country":"CA",
    "sg:address":"2340 Rosser Ave",
    "sg:city":"Brandon",
    "sg:classifiers":[
        {
            "category":"Cinema",
            "subcategory":"Movie Rental",
            "type":"Entertainment"
        }
    ],
    "sg:phone":"+1 204 727 7856",
    "sg:postcode":"R7B 0E3",
    "sg:province":"MB",
    "sg:tags":[
        "leasing",
        "video",
        "disc",
        "tape"
    ],
    "wof:name":"Clemmensen's Movies & More",
    "wof:placetype":"venue"
},
  "geometry": {"coordinates":[-99.969543,49.84827],"type":"Point"}
}