{
  "type": "Feature",
  "properties": {
    "addr:full":"13 Irwin Ave Toronto ON M4Y 1L1",
    "addr:housenumber":"13",
    "addr:postcode":"m4y 1l1",
    "addr:street":"Irwin Ave",
    "iso:country":"CA",
    "sg:address":"13 Irwin Ave",
    "sg:city":"Toronto",
    "sg:classifiers":[
        {
            "category":"Personal",
            "subcategory":"Beauty Salon",
            "type":"Services"
        }
    ],
    "sg:phone":"+1 416 413 0333",
    "sg:postcode":"M4Y 1L1",
    "sg:province":"ON",
    "sg:tags":[
        "therapist",
        "day",
        "massage"
    ],
    "wof:name":"Promised Care Ctr",
    "wof:placetype":"venue"
},
  "geometry": {"coordinates":[-79.385803,43.666435],"type":"Point"}
}