{
  "type": "Feature",
  "properties": {
    "addr:full":"622 Hawkhill Pl NW Calgary AB T3G 3M6",
    "addr:housenumber":"622",
    "addr:postcode":"t3g 3m6",
    "addr:street":"Hawkhill Pl Nw",
    "iso:country":"CA",
    "sg:address":"622 Hawkhill Pl NW",
    "sg:city":"Calgary",
    "sg:classifiers":[
        {
            "category":"Retail",
            "subcategory":"Repair Shop",
            "type":"Services"
        }
    ],
    "sg:phone":"+1 403 239 0094",
    "sg:postcode":"T3G 3M6",
    "sg:province":"AB",
    "sg:tags":[
        "equipment"
    ],
    "wof:name":"Gallant Mechanical Corp",
    "wof:placetype":"venue"
},
  "geometry": {"coordinates":[-114.164550781,51.1330757141],"type":"Point"}
}