{
  "type": "Feature",
  "properties": {
    "addr:full":"39997 Dinsley Terr Clinton ON N0M 1L0",
    "addr:postcode":"39997;n0m 1l0",
    "addr:street":"Dinsley Terr",
    "iso:country":"CA",
    "sg:address":"39997 Dinsley Terr",
    "sg:city":"Clinton",
    "sg:classifiers":[
        {
            "category":"Wholesale",
            "subcategory":"Hardware",
            "type":"Manufacturing & Wholesale Goods"
        }
    ],
    "sg:phone":"+1 519 482 7992",
    "sg:postcode":"N0M 1L0",
    "sg:province":"ON",
    "sg:tags":[
        "fastener",
        "bolt",
        "nut"
    ],
    "wof:name":"Comco Distributing",
    "wof:placetype":"venue"
},
  "geometry": {"coordinates":[-81.53969600000001,43.617668],"type":"Point"}
}