{
  "type": "Feature",
  "properties": {
    "addr:full":"4819C 48 Ave Red Deer AB T4N 3T2",
    "addr:housenumber":"4819c",
    "addr:postcode":"t4n 3t2",
    "addr:street":"48 Ave",
    "iso:country":"CA",
    "sg:address":"4819C 48 Ave",
    "sg:city":"Red Deer",
    "sg:classifiers":[
        {
            "category":"Government",
            "subcategory":"Post Office",
            "type":"Public Place"
        }
    ],
    "sg:phone":"+1 403 342 2289",
    "sg:postcode":"T4N 3T2",
    "sg:province":"AB",
    "wof:name":"Pack & Post",
    "wof:placetype":"venue"
},
  "geometry": {"coordinates":[-113.808807,52.267349],"type":"Point"}
}