{
  "type": "Feature",
  "properties": {
    "addr:full":"Saint-Simon-Les-Mines QC G0M 1K0",
    "addr:postcode":"g0m 1k0",
    "iso:country":"CA",
    "sg:city":"Saint-Simon-Les-Mines",
    "sg:classifiers":[
        {
            "category":"Personal",
            "subcategory":"Beauty Salon",
            "type":"Services"
        }
    ],
    "sg:phone":"+1 418 774 2057",
    "sg:postcode":"G0M 1K0",
    "sg:province":"QC",
    "wof:name":"Coiffure Fancy Enr",
    "wof:placetype":"venue"
},
  "geometry": {"coordinates":[-70.66887664790001,46.2156333923],"type":"Point"}
}