{
  "type": "Feature",
  "properties": {
    "addr:full":"1407 9 Ave SW Calgary AB T3C 0H9",
    "addr:housenumber":"1407",
    "addr:postcode":"t3c 0h9",
    "addr:street":"9 Ave Sw",
    "iso:country":"CA",
    "sg:address":"1407 9 Ave SW",
    "sg:city":"Calgary",
    "sg:classifiers":[
        {
            "category":"Retail",
            "subcategory":"Auto Repair",
            "type":"Services"
        }
    ],
    "sg:phone":"+1 403 261 3717",
    "sg:postcode":"T3C 0H9",
    "sg:province":"AB",
    "sg:tags":[
        "body",
        "automobile",
        "painting"
    ],
    "wof:name":"G T Carstar Collision",
    "wof:placetype":"venue"
},
  "geometry": {"coordinates":[-114.093124,51.045731],"type":"Point"}
}