{
  "type": "Feature",
  "properties": {
    "addr:full":"1 Rue Wellington Hull QC J8X 2H3",
    "addr:housenumber":"1",
    "addr:postcode":"j8x 2h3",
    "addr:street":"Rue Wellington",
    "iso:country":"CA",
    "sg:address":"1 Rue Wellington",
    "sg:city":"Hull",
    "sg:classifiers":[
        {
            "category":"Government",
            "subcategory":"Office",
            "type":"Public Place"
        }
    ],
    "sg:phone":"+1 819 595 7455",
    "sg:postcode":"J8X 2H3",
    "sg:province":"QC",
    "sg:tags":[
        "village"
    ],
    "wof:name":"Theatre DE I'Lle",
    "wof:placetype":"venue"
},
  "geometry": {"coordinates":[-75.724228,45.425877],"type":"Point"}
}