{
  "type": "Feature",
  "properties": {
    "addr:full":"70 Boul L'Assomption O Saint-Charles-Borromee QC J6E 7H3",
    "addr:housenumber":"70",
    "addr:postcode":"j6e 7h3",
    "addr:street":"Boul L'Assomption O Saint-Charles-Borromee",
    "iso:country":"CA",
    "sg:address":"70 Boul L'Assomption O",
    "sg:city":"Saint-Charles-Borromee",
    "sg:classifiers":[
        {
            "category":"Professional",
            "subcategory":"Advertising",
            "type":"Services"
        }
    ],
    "sg:phone":"+1 450 759 1338",
    "sg:postcode":"J6E 7H3",
    "sg:province":"QC",
    "wof:name":"Publicite Lanaudiere Inc",
    "wof:placetype":"venue"
},
  "geometry": {"coordinates":[-73.43498200000001,46.033951],"type":"Point"}
}