{
  "type": "Feature",
  "properties": {
    "addr:full":"North York ON M3J 1V2",
    "addr:postcode":"m3j 1v2",
    "iso:country":"CA",
    "sg:city":"North York",
    "sg:classifiers":[
        {
            "category":"Real Estate",
            "subcategory":"Real Estate Operator",
            "type":"Services"
        }
    ],
    "sg:phone":"+1 416 638 4017",
    "sg:postcode":"M3J 1V2",
    "sg:province":"ON",
    "sg:tags":[
        "apartment"
    ],
    "wof:name":"University Colony Apts",
    "wof:placetype":"venue"
},
  "geometry": {"coordinates":[-79.49894714360001,43.757434845],"type":"Point"}
}