{
  "type": "Feature",
  "properties": {
    "iso:country":"CA",
    "sg:address":"8325 Bonaventure Dr SE",
    "sg:city":"Calgary",
    "sg:classifiers":[
        {
            "category":"Government",
            "subcategory":"Police Station",
            "type":"Public Place"
        }
    ],
    "sg:phone":"+1 403 253 3376",
    "sg:postcode":"T2H 2R7",
    "sg:province":"AB",
    "sg:tags":[
        "department"
    ],
    "wof:name":"Calgary Police Dept",
    "wof:placetype":"venue"
},
  "geometry": {"coordinates":[-114.06824493400001,50.9790229797],"type":"Point"}
}