{
  "type": "Feature",
  "properties": {
    "addr:full":"Warwick QC J0A 1M0",
    "addr:postcode":"j0a 1m0",
    "iso:country":"CA",
    "sg:city":"Warwick",
    "sg:classifiers":[
        {
            "category":"Education",
            "subcategory":"School",
            "type":"Public Place"
        }
    ],
    "sg:phone":"+1 819 358 2260",
    "sg:postcode":"J0A 1M0",
    "sg:province":"QC",
    "wof:name":"Ecole St-Medard",
    "wof:placetype":"venue"
},
  "geometry": {"coordinates":[-71.9867935181,45.9481315613],"type":"Point"}
}