{
  "type": "Feature",
  "properties": {
    "addr:full":"Rl 338-PR 246 Morris MB R0G 1K0",
    "addr:housenumber":"246",
    "addr:postcode":"r0g 1k0",
    "addr:street":"Morris",
    "iso:country":"CA",
    "sg:address":"Rl 338-PR 246",
    "sg:city":"Morris",
    "sg:classifiers":[
        {
            "category":"Farming",
            "subcategory":"Nursery",
            "type":"Manufacturing & Wholesale Goods"
        }
    ],
    "sg:phone":"+1 204 746 8505",
    "sg:postcode":"R0G 1K0",
    "sg:province":"MB",
    "sg:tags":[
        "greenhouse"
    ],
    "wof:name":"Hillbilly Garden Ctr",
    "wof:placetype":"venue"
},
  "geometry": {"coordinates":[-97.366043,49.354687],"type":"Point"}
}