{
  "type": "Feature",
  "properties": {
    "addr:full":"33 Robert St Thornton ON L0L 2N0",
    "addr:housenumber":"33",
    "addr:postcode":"l0l 2n0",
    "addr:street":"Robert St",
    "iso:country":"CA",
    "sg:address":"33 Robert St",
    "sg:city":"Thornton",
    "sg:classifiers":[
        {
            "category":"Wholesale",
            "subcategory":"Farm Supplies",
            "type":"Manufacturing & Wholesale Goods"
        }
    ],
    "sg:phone":"+1 705 458 9290",
    "sg:postcode":"L0L 2N0",
    "sg:province":"ON",
    "sg:tags":[
        "livestock"
    ],
    "wof:name":"Len Vanderpost Transport",
    "wof:placetype":"venue"
},
  "geometry": {"coordinates":[-79.72744,44.269848],"type":"Point"}
}