{
  "type": "Feature",
  "properties": {
    "addr:full":"5120 49 St Yellowknife NT X1A 1P8",
    "addr:housenumber":"5120",
    "addr:postcode":"x1a 1p8",
    "addr:street":"49 St",
    "iso:country":"CA",
    "sg:address":"5120 49 St",
    "sg:city":"Yellowknife",
    "sg:classifiers":[
        {
            "category":"Organizations",
            "subcategory":"Professional Association",
            "type":"Services"
        }
    ],
    "sg:phone":"+1 867 873 4081",
    "sg:postcode":"X1A 1P8",
    "sg:province":"NT",
    "wof:name":"Dene Nation",
    "wof:placetype":"venue"
},
  "geometry": {"coordinates":[-114.365859985,62.4522895813],"type":"Point"}
}