{
  "type": "Feature",
  "properties": {
    "addr:full":"4910 45 St Red Deer AB T4N 1K6",
    "addr:housenumber":"4910",
    "addr:postcode":"t4n 1k6",
    "addr:street":"45 St",
    "iso:country":"CA",
    "sg:address":"4910 45 St",
    "sg:city":"Red Deer",
    "sg:classifiers":[
        {
            "category":"Shopping",
            "subcategory":"Jewelry",
            "type":"Retail Goods"
        }
    ],
    "sg:phone":"+1 403 346 2514",
    "sg:postcode":"T4N 1K6",
    "sg:province":"AB",
    "sg:tags":[
        "jeweler"
    ],
    "wof:name":"Mitchell & Jewell Ltd",
    "wof:placetype":"venue"
},
  "geometry": {"coordinates":[-113.812057495,52.264541626],"type":"Point"}
}