{
  "type": "Feature",
  "properties": {
    "addr:full":"1330 Riverside Rd Abbotsford BC V2S 7P1",
    "addr:housenumber":"1330",
    "addr:postcode":"v2s 7p1",
    "addr:street":"Riverside Rd",
    "iso:country":"CA",
    "sg:address":"1330 Riverside Rd",
    "sg:city":"Abbotsford",
    "sg:classifiers":[
        {
            "category":"Autos & Motor Vehicles",
            "subcategory":"Automobile Sales",
            "type":"Retail Goods"
        }
    ],
    "sg:phone":"+1 604 853 5262",
    "sg:postcode":"V2S 7P1",
    "sg:province":"BC",
    "sg:tags":[
        "sport",
        "trailer",
        "utility"
    ],
    "wof:name":"Trailer Man",
    "wof:placetype":"venue"
},
  "geometry": {"coordinates":[-122.27179717999999,49.0261154175],"type":"Point"}
}