{
  "type": "Feature",
  "properties": {
    "addr:full":"89 Valley Rd Corner Brook NL A2H 5B9",
    "addr:housenumber":"89",
    "addr:postcode":"a2h 5b9",
    "addr:street":"Valley Rd",
    "iso:country":"CA",
    "sg:address":"89 Valley Rd",
    "sg:city":"Corner Brook",
    "sg:classifiers":[
        {
            "category":"Health Services",
            "subcategory":"Health Practitioner",
            "type":"Services"
        }
    ],
    "sg:phone":"+1 709 634 9540",
    "sg:postcode":"A2H 5B9",
    "sg:province":"NL",
    "sg:tags":[
        "physiotherapist"
    ],
    "wof:name":"West Coast Physiotherapy Clnc",
    "wof:placetype":"venue"
},
  "geometry": {"coordinates":[-57.9573287964,48.9449691772],"type":"Point"}
}