{
  "type": "Feature",
  "properties": {
    "iso:country":"CA",
    "sg:address":"80 Second Line W",
    "sg:city":"Sault Ste Marie",
    "sg:classifiers":[
        {
            "category":"Health Services",
            "subcategory":"Chiropractor",
            "type":"Services"
        }
    ],
    "sg:phone":"+1 705 949 1799",
    "sg:postcode":"P6C 2H9",
    "sg:province":"ON",
    "wof:name":"Sicoli Chiropractic & Massage",
    "wof:placetype":"venue"
},
  "geometry": {"coordinates":[-84.3541107178,46.5377426147],"type":"Point"}
}