{
  "type": "Feature",
  "properties": {
    "addr:full":"5395 Steeles Ave W North York ON M9L 1R6",
    "addr:housenumber":"5395",
    "addr:postcode":"m9l 1r6",
    "addr:street":"Steeles Ave W",
    "iso:country":"CA",
    "sg:address":"5395 Steeles Ave W",
    "sg:city":"North York",
    "sg:classifiers":[
        {
            "category":"Autos & Motor Vehicles",
            "subcategory":"Automobile Sales",
            "type":"Retail Goods"
        }
    ],
    "sg:phone":"+1 416 749 9522",
    "sg:postcode":"M9L 1R6",
    "sg:province":"ON",
    "sg:tags":[
        "car",
        "dealer"
    ],
    "wof:name":"Trento Motors Ltd",
    "wof:placetype":"venue"
},
  "geometry": {"coordinates":[-79.556892,43.768021],"type":"Point"}
}