{
  "type": "Feature",
  "properties": {
    "addr:full":"1007 90E Av Lasalle QC H8R 3A4",
    "addr:housenumber":"1007",
    "addr:postcode":"h8r 3a4",
    "addr:street":"90E Av",
    "iso:country":"CA",
    "sg:address":"1007 90E Av",
    "sg:city":"Lasalle",
    "sg:classifiers":[
        {
            "category":"Health Services",
            "subcategory":"Medical Lab",
            "type":"Services"
        }
    ],
    "sg:phone":"+1 514 366 7306",
    "sg:postcode":"H8R 3A4",
    "sg:province":"QC",
    "wof:name":"Richard Lamothe Inc",
    "wof:placetype":"venue"
},
  "geometry": {"coordinates":[-73.662819,45.428658],"type":"Point"}
}