{
  "type": "Feature",
  "properties": {
    "addr:full":"1545 100th St North Battleford SK S9A 0W3",
    "addr:housenumber":"1545",
    "addr:postcode":"s9a 0w3",
    "addr:street":"100Th St",
    "iso:country":"CA",
    "sg:address":"1545 100th St",
    "sg:city":"North Battleford",
    "sg:classifiers":[
        {
            "category":"Home & Garden",
            "subcategory":"Carpets & Floor Coverings",
            "type":"Retail Goods"
        }
    ],
    "sg:phone":"+1 306 445 8169",
    "sg:postcode":"S9A 0W3",
    "sg:province":"SK",
    "sg:tags":[
        "rug"
    ],
    "wof:name":"North Battleford Carpet One",
    "wof:placetype":"venue"
},
  "geometry": {"coordinates":[-108.299255371,52.7803344727],"type":"Point"}
}