{
  "type": "Feature",
  "properties": {
    "addr:full":"4149 Rue Jean-Talon E Saint-Leonard QC H1S 1J6",
    "addr:housenumber":"4149",
    "addr:postcode":"h1s 1j6",
    "addr:street":"Rue Jean-Talon E",
    "iso:country":"CA",
    "sg:address":"4149 Rue Jean-Talon E",
    "sg:city":"Saint-Leonard",
    "sg:classifiers":[
        {
            "category":"Banks & Credit Unions",
            "subcategory":"Bank",
            "type":"Services"
        }
    ],
    "sg:phone":"+1 514 725 4761",
    "sg:postcode":"H1S 1J6",
    "sg:province":"QC",
    "wof:name":"Cibc",
    "wof:placetype":"venue"
},
  "geometry": {"coordinates":[-73.59023999999999,45.56778],"type":"Point"}
}