{
  "type": "Feature",
  "properties": {
    "addr:full":"484 Maryland St Winnipeg MB R3G 1M5",
    "addr:housenumber":"484",
    "addr:postcode":"r3g 1m5",
    "addr:street":"Maryland St",
    "iso:country":"CA",
    "sg:address":"484 Maryland St",
    "sg:city":"Winnipeg",
    "sg:classifiers":[
        {
            "category":"Organizations",
            "subcategory":"Religious Organization",
            "type":"Services"
        }
    ],
    "sg:phone":"+1 204 774 3143",
    "sg:postcode":"R3G 1M5",
    "sg:province":"MB",
    "sg:tags":[
        "church"
    ],
    "wof:name":"First English Lutheran Church",
    "wof:placetype":"venue"
},
  "geometry": {"coordinates":[-97.160309,49.89386],"type":"Point"}
}