{
  "type": "Feature",
  "properties": {
    "addr:full":"75 Rue Cremazie Hull QC J8Y 3P1",
    "addr:housenumber":"75",
    "addr:postcode":"j8y 3p1",
    "addr:street":"Rue Cremazie",
    "iso:country":"CA",
    "sg:address":"75 Rue Cremazie",
    "sg:city":"Hull",
    "sg:classifiers":[
        {
            "category":"Retail",
            "subcategory":"Repair Shop",
            "type":"Services"
        }
    ],
    "sg:phone":"+1 819 771 3863",
    "sg:postcode":"J8Y 3P1",
    "sg:province":"QC",
    "sg:tags":[
        "upholsterer"
    ],
    "wof:name":"Rembourreur Hull Wrightville",
    "wof:placetype":"venue"
},
  "geometry": {"coordinates":[-75.73133900000001,45.43338],"type":"Point"}
}