{
  "type": "Feature",
  "properties": {
    "addr:full":"52 Bermondsey Rd NW Calgary AB T3K 1V3",
    "addr:housenumber":"52",
    "addr:postcode":"t3k 1v3",
    "addr:street":"Bermondsey Rd Nw",
    "iso:country":"CA",
    "sg:address":"52 Bermondsey Rd NW",
    "sg:city":"Calgary",
    "sg:classifiers":[
        {
            "category":"Building & Trades",
            "subcategory":"Construction",
            "type":"Services"
        }
    ],
    "sg:phone":"+1 403 275 8290",
    "sg:postcode":"T3K 1V3",
    "sg:province":"AB",
    "sg:tags":[
        "general",
        "contractor"
    ],
    "wof:name":"Greco & Son Concrete & Constr",
    "wof:placetype":"venue"
},
  "geometry": {"coordinates":[-114.08871499999999,51.127239],"type":"Point"}
}