{
  "type": "Feature",
  "properties": {
    "addr:full":"2 Rue Saint-Francois Sorel-Tracy QC J3P 3M4",
    "addr:housenumber":"2",
    "addr:postcode":"j3p 3m4",
    "addr:street":"Rue Saint-Francois",
    "iso:country":"CA",
    "sg:address":"2 Rue Saint-Francois",
    "sg:city":"Sorel-Tracy",
    "sg:classifiers":[
        {
            "category":"Retail",
            "subcategory":"Laundry & Dry Cleaning",
            "type":"Services"
        }
    ],
    "sg:phone":"+1 450 743 9906",
    "sg:postcode":"J3P 3M4",
    "sg:province":"QC",
    "sg:tags":[
        "cleaners",
        "rug",
        "carpet"
    ],
    "wof:name":"Nettoyage Fauteuils Enr",
    "wof:placetype":"venue"
},
  "geometry": {"coordinates":[-73.09721374510001,46.0360183716],"type":"Point"}
}