{
  "type": "Feature",
  "properties": {
    "addr:full":"50 Cumberland St Toronto ON M4W 1J5",
    "addr:housenumber":"50",
    "addr:postcode":"m4w 1j5",
    "addr:street":"Cumberland St",
    "iso:country":"CA",
    "sg:address":"50 Cumberland St",
    "sg:city":"Toronto",
    "sg:classifiers":[
        {
            "category":"Professional",
            "subcategory":"Printing & Photocopies",
            "type":"Services"
        }
    ],
    "sg:phone":"+1 416 925 3409",
    "sg:postcode":"M4W 1J5",
    "sg:province":"ON",
    "sg:tags":[
        "printer",
        "duplicating",
        "copying"
    ],
    "wof:name":"Minuteman Press",
    "wof:placetype":"venue"
},
  "geometry": {"coordinates":[-79.38880899999999,43.670891],"type":"Point"}
}