{
  "type": "Feature",
  "properties": {
    "addr:full":"1060 Springhill Dr Mississauga ON L5H 1M9",
    "addr:housenumber":"1060",
    "addr:postcode":"l5h 1m9",
    "addr:street":"Springhill Dr",
    "iso:country":"CA",
    "sg:address":"1060 Springhill Dr",
    "sg:city":"Mississauga",
    "sg:classifiers":[
        {
            "category":"Health Services",
            "subcategory":"Doctor",
            "type":"Services"
        }
    ],
    "sg:phone":"+1 905 891 3220",
    "sg:postcode":"L5H 1M9",
    "sg:province":"ON",
    "sg:tags":[
        "dentist"
    ],
    "wof:name":"Limeback, Hardy DDS",
    "wof:placetype":"venue"
},
  "geometry": {"coordinates":[-79.61372375489999,43.5375671387],"type":"Point"}
}