{
  "type": "Feature",
  "properties": {
    "addr:full":"1262 Hillcrest Ave London ON N5Y 4N4",
    "addr:housenumber":"1262",
    "addr:postcode":"n5y 4n4",
    "addr:street":"Hillcrest Ave",
    "iso:country":"CA",
    "sg:address":"1262 Hillcrest Ave",
    "sg:city":"London",
    "sg:classifiers":[
        {
            "category":"Social Services",
            "type":"Services"
        }
    ],
    "sg:phone":"+1 519 455 6512",
    "sg:postcode":"N5Y 4N4",
    "sg:province":"ON",
    "sg:tags":[
        "organization",
        "welfare"
    ],
    "wof:name":"Natural Family Planning",
    "wof:placetype":"venue"
},
  "geometry": {"coordinates":[-81.220993042,43.0210342407],"type":"Point"}
}