{
  "type": "Feature",
  "properties": {
    "addr:full":"Pitt Meadows BC V3Y 2J4",
    "addr:postcode":"v3y 2j4",
    "iso:country":"CA",
    "sg:city":"Pitt Meadows",
    "sg:classifiers":[
        {
            "category":"Restaurant",
            "type":"Food & Drink"
        }
    ],
    "sg:phone":"+1 604 465 7701",
    "sg:postcode":"V3Y 2J4",
    "sg:province":"BC",
    "sg:tags":[
        "sandwich"
    ],
    "wof:name":"Subway Sandwiches & Salads",
    "wof:placetype":"venue"
},
  "geometry": {"coordinates":[-122.689308,49.230061],"type":"Point"}
}