{
  "type": "Feature",
  "properties": {
    "addr:full":"31 Parliament St Toronto ON M5A 2Y2",
    "addr:housenumber":"31",
    "addr:postcode":"m5a 2y2",
    "addr:street":"Parliament St",
    "iso:country":"CA",
    "sg:address":"31 Parliament St",
    "sg:city":"Toronto",
    "sg:classifiers":[
        {
            "category":"Wholesale",
            "subcategory":"Hardware",
            "type":"Manufacturing & Wholesale Goods"
        }
    ],
    "sg:phone":"+1 416 364 9191",
    "sg:postcode":"M5A 2Y2",
    "sg:province":"ON",
    "sg:tags":[
        "tool"
    ],
    "wof:name":"Ctf Supply Ltd",
    "wof:placetype":"venue"
},
  "geometry": {"coordinates":[-79.3616104126,43.6494216919],"type":"Point"}
}