{
  "type": "Feature",
  "properties": {
    "addr:full":"3030 Lawrence Ave E Scarborough ON M1P 2T7",
    "addr:housenumber":"3030",
    "addr:postcode":"m1p 2t7",
    "addr:street":"Lawrence Ave E",
    "iso:country":"CA",
    "sg:address":"3030 Lawrence Ave E",
    "sg:city":"Scarborough",
    "sg:classifiers":[
        {
            "category":"Health Services",
            "subcategory":"Doctor",
            "type":"Services"
        }
    ],
    "sg:phone":"+1 416 438 8828",
    "sg:postcode":"M1P 2T7",
    "sg:province":"ON",
    "sg:tags":[
        "physician",
        "surgeon"
    ],
    "wof:name":"Cherry, James MD",
    "wof:placetype":"venue"
},
  "geometry": {"coordinates":[-79.247756958,43.7552146912],"type":"Point"}
}