{
  "type": "Feature",
  "properties": {
    "addr:full":"303 5th Ave Stewart BC V0T 1W0",
    "addr:housenumber":"303",
    "addr:postcode":"v0t 1w0",
    "addr:street":"5Th Ave",
    "iso:country":"CA",
    "sg:address":"303 5th Ave",
    "sg:city":"Stewart",
    "sg:classifiers":[
        {
            "category":"Food & Beverages",
            "subcategory":"Groceries & Convenience Stores",
            "type":"Retail Goods"
        }
    ],
    "sg:phone":"+1 250 636 2377",
    "sg:postcode":"V0T 1W0",
    "sg:province":"BC",
    "sg:tags":[
        "grocer"
    ],
    "wof:name":"Bob's Mercantile Ltd",
    "wof:placetype":"venue"
},
  "geometry": {"coordinates":[-129.98503099999999,55.935856],"type":"Point"}
}