{
  "type": "Feature",
  "properties": {
    "addr:full":"Vancouver BC V6A 4H8",
    "addr:postcode":"v6a 4h8",
    "iso:country":"CA",
    "sg:city":"Vancouver",
    "sg:classifiers":[
        {
            "category":"Health Services",
            "subcategory":"Doctor",
            "type":"Services"
        }
    ],
    "sg:phone":"+1 604 605 3382",
    "sg:postcode":"V6A 4H8",
    "sg:province":"BC",
    "sg:tags":[
        "clinic"
    ],
    "wof:name":"Chinatown Centre Medical Clnc",
    "wof:placetype":"venue"
},
  "geometry": {"coordinates":[-123.09750366199999,49.2783737183],"type":"Point"}
}