{
  "type": "Feature",
  "properties": {
    "addr:full":"324 9E Av Iberville QC J2X 1K3",
    "addr:housenumber":"324",
    "addr:postcode":"j2x 1k3",
    "addr:street":"9E Av",
    "iso:country":"CA",
    "sg:address":"324 9E Av",
    "sg:city":"Iberville",
    "sg:classifiers":[
        {
            "category":"Personal",
            "subcategory":"Beauty Salon",
            "type":"Services"
        }
    ],
    "sg:phone":"+1 450 347 6311",
    "sg:postcode":"J2X 1K3",
    "sg:province":"QC",
    "wof:name":"Salon Romain Coiffure",
    "wof:placetype":"venue"
},
  "geometry": {"coordinates":[-73.237511,45.310966],"type":"Point"}
}