{
  "type": "Feature",
  "properties": {
    "iso:country":"CA",
    "sg:address":"50 Church St S",
    "sg:city":"Alliston",
    "sg:classifiers":[
        {
            "category":"Health Services",
            "subcategory":"Doctor",
            "type":"Services"
        }
    ],
    "sg:phone":"+1 705 435 7963",
    "sg:postcode":"L9R 1G9",
    "sg:province":"ON",
    "sg:tags":[
        "dentist"
    ],
    "wof:name":"Dunn, Stephen DDS",
    "wof:placetype":"venue"
},
  "geometry": {"coordinates":[-79.8684387207,44.1517066956],"type":"Point"}
}