{
  "type": "Feature",
  "properties": {
    "addr:full":"Hwy 13 # 4 Carlyle SK S0C 0R0",
    "addr:postcode":"s0c 0r0",
    "addr:street":"Hwy 13 # 4 Carlyle",
    "iso:country":"CA",
    "sg:address":"Hwy 13 # 4",
    "sg:city":"Carlyle",
    "sg:classifiers":[
        {
            "category":"Health Services",
            "subcategory":"Doctor",
            "type":"Services"
        }
    ],
    "sg:phone":"+1 306 453 6346",
    "sg:postcode":"S0C 0R0",
    "sg:province":"SK",
    "sg:tags":[
        "dentist"
    ],
    "wof:name":"Johnstone, Clayton DDS",
    "wof:placetype":"venue"
},
  "geometry": {"coordinates":[-102.277542,49.63961],"type":"Point"}
}