{
  "type": "Feature",
  "properties": {
    "addr:full":"5276 Hinchinbrook Rd Hartington ON K0H 1W0",
    "addr:housenumber":"5276",
    "addr:postcode":"k0h 1w0",
    "addr:street":"Hinchinbrook Rd",
    "iso:country":"CA",
    "sg:address":"5276 Hinchinbrook Rd",
    "sg:city":"Hartington",
    "sg:classifiers":[
        {
            "category":"Home & Garden",
            "subcategory":"Building Materials",
            "type":"Retail Goods"
        }
    ],
    "sg:phone":"+1 613 372 2838",
    "sg:postcode":"K0H 1W0",
    "sg:province":"ON",
    "sg:tags":[
        "lumber"
    ],
    "wof:name":"Bmp Home Building Ctr",
    "wof:placetype":"venue"
},
  "geometry": {"coordinates":[-76.668663,44.440907],"type":"Point"}
}