{
  "type": "Feature",
  "properties": {
    "addr:full":"2640 Boul DE LA Concorde E Laval QC H7E 2B4",
    "addr:housenumber":"2640",
    "addr:postcode":"h7e 2b4",
    "addr:street":"Boul De La Concorde E",
    "iso:country":"CA",
    "sg:address":"2640 Boul DE LA Concorde E",
    "sg:city":"Laval",
    "sg:classifiers":[
        {
            "category":"Health Services",
            "subcategory":"Doctor",
            "type":"Services"
        }
    ],
    "sg:phone":"+1 450 669 6004",
    "sg:postcode":"H7E 2B4",
    "sg:province":"QC",
    "sg:tags":[
        "clinic",
        "dentist"
    ],
    "wof:name":"Clinique Dentaire Blouin",
    "wof:placetype":"venue"
},
  "geometry": {"coordinates":[-73.671593,45.588707],"type":"Point"}
}