{
  "type": "Feature",
  "properties": {
    "iso:country":"CA",
    "sg:address":"5835 York Rd",
    "sg:city":"Duncan",
    "sg:classifiers":[
        {
            "category":"Cinema",
            "subcategory":"Movie Rental",
            "type":"Entertainment"
        }
    ],
    "sg:phone":"+1 250 748 3444",
    "sg:postcode":"V9L 3S2",
    "sg:province":"BC",
    "sg:tags":[
        "leasing",
        "video",
        "disc",
        "tape"
    ],
    "wof:name":"L J Video Rentals",
    "wof:placetype":"venue"
},
  "geometry": {"coordinates":[-123.70738220200001,48.779094696],"type":"Point"}
}