{
  "type": "Feature",
  "properties": {
    "addr:full":"Richmond Hill ON L4B 1K5",
    "addr:postcode":"l4b 1k5",
    "iso:country":"CA",
    "sg:city":"Richmond Hill",
    "sg:classifiers":[
        {
            "category":"Manufacturing",
            "subcategory":"Toys & Sporting Goods",
            "type":"Manufacturing & Wholesale Goods"
        }
    ],
    "sg:phone":"+1 905 882 0396",
    "sg:postcode":"L4B 1K5",
    "sg:province":"ON",
    "sg:tags":[
        "athletic"
    ],
    "wof:name":"Silverstar Sports",
    "wof:placetype":"venue"
},
  "geometry": {"coordinates":[-79.391937,43.855412],"type":"Point"}
}