{
  "type": "Feature",
  "properties": {
    "addr:full":"Fort Saskatchewan AB T8L 4B9",
    "addr:postcode":"t8l 4b9",
    "iso:country":"CA",
    "sg:city":"Fort Saskatchewan",
    "sg:classifiers":[
        {
            "category":"Airport",
            "type":"Transportation"
        }
    ],
    "sg:phone":"+1 780 998 9547",
    "sg:postcode":"T8L 4B9",
    "sg:province":"AB",
    "sg:tags":[
        "aircraft",
        "maintenance"
    ],
    "wof:name":"Sure Flight Aviation Mntnc Ltd",
    "wof:placetype":"venue"
},
  "geometry": {"coordinates":[-113.214172,53.712887],"type":"Point"}
}