{
  "type": "Feature",
  "properties": {
    "addr:full":"28 Mill St Aurora ON L4G 2R9",
    "addr:housenumber":"28",
    "addr:postcode":"l4g 2r9",
    "addr:street":"Mill St",
    "iso:country":"CA",
    "sg:address":"28 Mill St",
    "sg:city":"Aurora",
    "sg:classifiers":[
        {
            "category":"Travel",
            "subcategory":"Travel Agent",
            "type":"Entertainment"
        }
    ],
    "sg:phone":"+1 905 727 1956",
    "sg:postcode":"L4G 2R9",
    "sg:province":"ON",
    "sg:tags":[
        "agency",
        "bureau",
        "gun",
        "gunsmith"
    ],
    "wof:name":"Outdoor Hunting & Safari",
    "wof:placetype":"venue"
},
  "geometry": {"coordinates":[-79.47049713129999,43.998374939],"type":"Point"}
}