{
  "type": "Feature",
  "properties": {
    "addr:full":"11666 95 St NW Edmonton AB T5G 1L8",
    "addr:housenumber":"11666",
    "addr:postcode":"t5g 1l8",
    "addr:street":"95 St Nw",
    "iso:country":"CA",
    "sg:address":"11666 95 St NW",
    "sg:city":"Edmonton",
    "sg:classifiers":[
        {
            "category":"Social Services",
            "type":"Services"
        }
    ],
    "sg:phone":"+1 780 474 2400",
    "sg:postcode":"T5G 1L8",
    "sg:province":"AB",
    "sg:tags":[
        "organization",
        "welfare",
        "personnel",
        "consultant"
    ],
    "wof:name":"Bent Arrow Sacred Circle",
    "wof:placetype":"venue"
},
  "geometry": {"coordinates":[-113.48744201700001,53.5683021545],"type":"Point"}
}