{
  "type": "Feature",
  "properties": {
    "addr:full":"Burlington ON L7M 2A3",
    "addr:postcode":"l7m 2a3",
    "iso:country":"CA",
    "sg:city":"Burlington",
    "sg:classifiers":[
        {
            "category":"Health Services",
            "subcategory":"Chiropractor",
            "type":"Services"
        }
    ],
    "sg:phone":"+1 905 335 5433",
    "sg:postcode":"L7M 2A3",
    "sg:province":"ON",
    "wof:name":"Life Chiropractic Ctr",
    "wof:placetype":"venue"
},
  "geometry": {"coordinates":[-79.839752,43.37772],"type":"Point"}
}