{
  "type": "Feature",
  "properties": {
    "addr:full":"11431 98 Ave Grande Prairie AB T8V 5S5",
    "addr:housenumber":"11431",
    "addr:postcode":"t8v 5s5",
    "addr:street":"98 Ave",
    "iso:country":"CA",
    "sg:address":"11431 98 Ave",
    "sg:city":"Grande Prairie",
    "sg:classifiers":[
        {
            "category":"Mining & Drilling",
            "type":"Manufacturing & Wholesale Goods"
        }
    ],
    "sg:phone":"+1 780 814 5992",
    "sg:postcode":"T8V 5S5",
    "sg:province":"AB",
    "sg:tags":[
        "company",
        "oil",
        "establishment"
    ],
    "wof:name":"Eog Resources Canada Ltd",
    "wof:placetype":"venue"
},
  "geometry": {"coordinates":[-118.839287,55.168648],"type":"Point"}
}