{
  "type": "Feature",
  "properties": {
    "addr:full":"1017 Boul Des Chutes Beauport QC G1E 2E6",
    "addr:housenumber":"1017",
    "addr:postcode":"qc g1e 2e6",
    "addr:street":"Boul Des Chutes",
    "iso:country":"CA",
    "sg:address":"1017 Boul Des Chutes",
    "sg:city":"Beauport",
    "sg:classifiers":[
        {
            "category":"Retail",
            "subcategory":"Repair Shop",
            "type":"Services"
        }
    ],
    "sg:phone":"+1 418 667 3011",
    "sg:postcode":"G1E 2E6",
    "sg:province":"QC",
    "sg:tags":[
        "equipment",
        "video",
        "electronic"
    ],
    "wof:name":"Simard Audio-Visuel Enr",
    "wof:placetype":"venue"
},
  "geometry": {"coordinates":[-71.17841300000001,46.868256],"type":"Point"}
}