{
  "type": "Feature",
  "properties": {
    "addr:full":"143 Rue Saint-Jean-Baptiste E Montmagny QC G5V 1K4",
    "addr:housenumber":"143",
    "addr:postcode":"g5v 1k4",
    "addr:street":"Rue Saint-Jean-Baptiste E",
    "iso:country":"CA",
    "sg:address":"143 Rue Saint-Jean-Baptiste E",
    "sg:city":"Montmagny",
    "sg:classifiers":[
        {
            "category":"Banks & Credit Unions",
            "subcategory":"Bank",
            "type":"Services"
        }
    ],
    "sg:phone":"+1 418 248 4884",
    "sg:postcode":"G5V 1K4",
    "sg:province":"QC",
    "wof:name":"Caisses Desjardins",
    "wof:placetype":"venue"
},
  "geometry": {"coordinates":[-70.5570068359,46.9813652039],"type":"Point"}
}