{
  "type": "Feature",
  "properties": {
    "addr:full":"New Westminster BC V3L 2B8",
    "addr:postcode":"v3l 2b8",
    "iso:country":"CA",
    "sg:city":"New Westminster",
    "sg:classifiers":[
        {
            "category":"Restaurant",
            "type":"Food & Drink"
        }
    ],
    "sg:phone":"+1 604 526 3829",
    "sg:postcode":"V3L 2B8",
    "sg:province":"BC",
    "wof:name":"Tokyo Town",
    "wof:placetype":"venue"
},
  "geometry": {"coordinates":[-122.912254334,49.222442627],"type":"Point"}
}