{
  "type": "Feature",
  "properties": {
    "addr:full":"17446 Hillview Pl Surrey BC V3S 0C3",
    "addr:housenumber":"17446",
    "addr:postcode":"v3s 0c3",
    "addr:street":"Hillview Pl",
    "iso:country":"CA",
    "sg:address":"17446 Hillview Pl",
    "sg:city":"Surrey",
    "sg:classifiers":[
        {
            "category":"Wholesale",
            "subcategory":"Durable Goods & Equipment",
            "type":"Manufacturing & Wholesale Goods"
        }
    ],
    "sg:phone":"+1 604 538 0886",
    "sg:postcode":"V3S 0C3",
    "sg:province":"BC",
    "sg:tags":[
        "exporter"
    ],
    "wof:name":"Tokunaga Trading CO",
    "wof:placetype":"venue"
},
  "geometry": {"coordinates":[-122.738716126,49.0566444397],"type":"Point"}
}