{
  "type": "Feature",
  "properties": {
    "addr:full":"10 Yacht Club Rd Hudson QC J0P 1H0",
    "addr:housenumber":"10",
    "addr:postcode":"j0p 1h0",
    "addr:street":"Yacht Club Rd",
    "iso:country":"CA",
    "sg:address":"10 Yacht Club Rd",
    "sg:city":"Hudson",
    "sg:classifiers":[
        {
            "category":"Organizations",
            "subcategory":"Community Association",
            "type":"Services"
        }
    ],
    "sg:phone":"+1 450 458 5326",
    "sg:postcode":"J0P 1H0",
    "sg:province":"QC",
    "sg:tags":[
        "club"
    ],
    "wof:name":"Hudson Yacht Club",
    "wof:placetype":"venue"
},
  "geometry": {"coordinates":[-74.1419830322,45.4619674683],"type":"Point"}
}