{
  "type": "Feature",
  "properties": {
    "iso:country":"CA",
    "sg:address":"5315 Boul Saint-Laurent",
    "sg:city":"Montreal",
    "sg:classifiers":[
        {
            "category":"Manufacturing",
            "subcategory":"Apparel",
            "type":"Manufacturing & Wholesale Goods"
        }
    ],
    "sg:phone":"+1 514 271 3102",
    "sg:postcode":"H2T 1S5",
    "sg:province":"QC",
    "sg:tags":[
        "clothing"
    ],
    "wof:name":"Tricots Lela",
    "wof:placetype":"venue"
},
  "geometry": {"coordinates":[-73.59626,45.52478],"type":"Point"}
}