{
  "type": "Feature",
  "properties": {
    "addr:full":"2053 Portage Ave Winnipeg MB R3J 0K9",
    "addr:housenumber":"2053",
    "addr:postcode":"r3j 0k9",
    "addr:street":"Portage Ave",
    "iso:country":"CA",
    "sg:address":"2053 Portage Ave",
    "sg:city":"Winnipeg",
    "sg:classifiers":[
        {
            "category":"Restaurant",
            "type":"Food & Drink"
        }
    ],
    "sg:phone":"+1 204 832 5021",
    "sg:postcode":"R3J 0K9",
    "sg:province":"MB",
    "sg:tags":[
        "parlor",
        "ice",
        "cream"
    ],
    "wof:name":"Sargent Sundae",
    "wof:placetype":"venue"
},
  "geometry": {"coordinates":[-97.23111,49.877392],"type":"Point"}
}