{
  "type": "Feature",
  "properties": {
    "iso:country":"CA",
    "sg:address":"144 138 Rte E",
    "sg:city":"Forestville",
    "sg:classifiers":[
        {
            "category":"Building & Trades",
            "subcategory":"Construction",
            "type":"Services"
        }
    ],
    "sg:phone":"+1 418 587 4773",
    "sg:postcode":"G0T 1E0",
    "sg:province":"QC",
    "sg:tags":[
        "general",
        "contractor"
    ],
    "wof:name":"Entreprise RR",
    "wof:placetype":"venue"
},
  "geometry": {"coordinates":[-69.0843963623,48.7387237549],"type":"Point"}
}