{
  "type": "Feature",
  "properties": {
    "addr:full":"2150 Rue Theodore Montreal QC H1V 3B9",
    "addr:housenumber":"2150",
    "addr:postcode":"h1v 3b9",
    "addr:street":"Rue Theodore",
    "iso:country":"CA",
    "sg:address":"2150 Rue Theodore",
    "sg:city":"Montreal",
    "sg:classifiers":[
        {
            "category":"Organizations",
            "subcategory":"Professional Association",
            "type":"Services"
        }
    ],
    "sg:phone":"+1 514 254 6120",
    "sg:postcode":"H1V 3B9",
    "sg:province":"QC",
    "wof:name":"Peres Separes Inc",
    "wof:placetype":"venue"
},
  "geometry": {"coordinates":[-73.538628,45.558376],"type":"Point"}
}