{
  "type": "Feature",
  "properties": {
    "addr:full":"Calgary AB T2H 2S5",
    "addr:postcode":"t2h 2s5",
    "iso:country":"CA",
    "sg:city":"Calgary",
    "sg:classifiers":[
        {
            "category":"Insurance",
            "subcategory":"Insurance Agent",
            "type":"Services"
        }
    ],
    "sg:phone":"+1 403 256 8400",
    "sg:postcode":"T2H 2S5",
    "sg:province":"AB",
    "sg:tags":[
        "adjuster"
    ],
    "wof:name":"Kendal Adjusters Inc",
    "wof:placetype":"venue"
},
  "geometry": {"coordinates":[-114.036705,50.989555],"type":"Point"}
}