{
  "type": "Feature",
  "properties": {
    "iso:country":"CA",
    "sg:address":"441 Clark Ave W",
    "sg:city":"Thornhill",
    "sg:classifiers":[
        {
            "category":"Personal",
            "subcategory":"Beauty Salon",
            "type":"Services"
        }
    ],
    "sg:phone":"+1 905 771 6350",
    "sg:postcode":"L4J 6W8",
    "sg:province":"ON",
    "wof:name":"D & M Esthetics",
    "wof:placetype":"venue"
},
  "geometry": {"coordinates":[-79.438354,43.805225],"type":"Point"}
}