{
  "type": "Feature",
  "properties": {
    "addr:full":"Hebron NS B0W 1X0",
    "addr:postcode":"b0w 1x0",
    "iso:country":"CA",
    "sg:city":"Hebron",
    "sg:classifiers":[
        {
            "category":"Government",
            "subcategory":"Office",
            "type":"Public Place"
        }
    ],
    "sg:phone":"+1 902 742 8782",
    "sg:postcode":"B0W 1X0",
    "sg:province":"NS",
    "wof:name":"Nova Scotia Family & Child Svc",
    "wof:placetype":"venue"
},
  "geometry": {"coordinates":[-66.090385,43.887215],"type":"Point"}
}