{
  "type": "Feature",
  "properties": {
    "addr:full":"3023 Rue Jacques-Amyot Sainte-Foy QC G1X 1Z3",
    "addr:housenumber":"3023",
    "addr:postcode":"g1x 1z3",
    "addr:street":"Rue Jacques-Amyot",
    "iso:country":"CA",
    "sg:address":"3023 Rue Jacques-Amyot",
    "sg:city":"Sainte-Foy",
    "sg:classifiers":[
        {
            "category":"Building & Trades",
            "subcategory":"Plumbing",
            "type":"Services"
        }
    ],
    "sg:phone":"+1 418 653 2504",
    "sg:postcode":"G1X 1Z3",
    "sg:province":"QC",
    "sg:tags":[
        "contractor"
    ],
    "wof:name":"J Raymond Gravel Inc",
    "wof:placetype":"venue"
},
  "geometry": {"coordinates":[-71.3049316406,46.7715759277],"type":"Point"}
}