{
  "type": "Feature",
  "properties": {
    "addr:full":"1039 Regent St Fredericton NB E3B 3Y9",
    "addr:housenumber":"1039",
    "addr:postcode":"e3b 3y9",
    "addr:street":"Regent St",
    "iso:country":"CA",
    "sg:address":"1039 Regent St",
    "sg:city":"Fredericton",
    "sg:classifiers":[
        {
            "category":"Organizations",
            "subcategory":"Religious Organization",
            "type":"Services"
        }
    ],
    "sg:phone":"+1 506 457 0619",
    "sg:postcode":"E3B 3Y9",
    "sg:province":"NB",
    "sg:tags":[
        "church"
    ],
    "wof:name":"Fredericton Congregation",
    "wof:placetype":"venue"
},
  "geometry": {"coordinates":[-66.6545715332,45.9429779053],"type":"Point"}
}