{
  "type": "Feature",
  "properties": {
    "iso:country":"CA",
    "sg:address":"8393 120 St",
    "sg:city":"Delta",
    "sg:classifiers":[
        {
            "category":"Insurance",
            "subcategory":"Insurance Agent",
            "type":"Services"
        }
    ],
    "sg:phone":"+1 604 501 4229",
    "sg:postcode":"V4C 6R1",
    "sg:province":"BC",
    "wof:name":"Envision Insurance Svc Ltd",
    "wof:placetype":"venue"
},
  "geometry": {"coordinates":[-122.89051055900001,49.1555595398],"type":"Point"}
}