{
  "type": "Feature",
  "properties": {
    "iso:country":"CA",
    "sg:address":"170 Hanlan Rd",
    "sg:city":"Woodbridge",
    "sg:classifiers":[
        {
            "category":"Wholesale",
            "subcategory":"Machinery & Supplies",
            "type":"Manufacturing & Wholesale Goods"
        }
    ],
    "sg:phone":"+1 905 265 9800",
    "sg:postcode":"L4L 3P6",
    "sg:province":"ON",
    "sg:tags":[
        "equipment",
        "plastic"
    ],
    "wof:name":"Alpha Marathon",
    "wof:placetype":"venue"
},
  "geometry": {"coordinates":[-79.5629043579,43.7694740295],"type":"Point"}
}