{
  "type": "Feature",
  "properties": {
    "addr:full":"5 Bulloch Rd Willow Grove NB E2S 1H2",
    "addr:housenumber":"5",
    "addr:postcode":"e2s 1h2",
    "addr:street":"Bulloch Rd",
    "iso:country":"CA",
    "sg:address":"5 Bulloch Rd",
    "sg:city":"Willow Grove",
    "sg:classifiers":[
        {
            "category":"Retail",
            "subcategory":"Auto Repair",
            "type":"Services"
        }
    ],
    "sg:phone":"+1 506 652 1998",
    "sg:postcode":"E2S 1H2",
    "sg:province":"NB",
    "sg:tags":[
        "repairing",
        "automobile"
    ],
    "wof:name":"Willow Grove Auto Repair",
    "wof:placetype":"venue"
},
  "geometry": {"coordinates":[-65.811684,45.338703],"type":"Point"}
}