{
  "type": "Feature",
  "properties": {
    "addr:full":"13018 50 St NW Edmonton AB T5A 4V9",
    "addr:housenumber":"13018",
    "addr:postcode":"t5a 4v9",
    "addr:street":"50 St Nw",
    "iso:country":"CA",
    "sg:address":"13018 50 St NW",
    "sg:city":"Edmonton",
    "sg:classifiers":[
        {
            "category":"Restaurant",
            "type":"Food & Drink"
        }
    ],
    "sg:phone":"+1 780 476 1866",
    "sg:postcode":"T5A 4V9",
    "sg:province":"AB",
    "wof:name":"Subway Sandwiches & Salads",
    "wof:placetype":"venue"
},
  "geometry": {"coordinates":[-113.418037415,53.5903167725],"type":"Point"}
}