{
  "type": "Feature",
  "properties": {
    "addr:full":"2605 27 St SW Calgary AB T3E 2G4",
    "addr:housenumber":"2605",
    "addr:postcode":"t3e 2g4",
    "addr:street":"27 St Sw",
    "iso:country":"CA",
    "sg:address":"2605 27 St SW",
    "sg:city":"Calgary",
    "sg:classifiers":[
        {
            "category":"Personal",
            "type":"Services"
        }
    ],
    "sg:phone":"+1 403 242 1401",
    "sg:postcode":"T3E 2G4",
    "sg:province":"AB",
    "sg:tags":[
        "electrolysis"
    ],
    "wof:name":"Acton Electrolysis",
    "wof:placetype":"venue"
},
  "geometry": {"coordinates":[-114.126831055,51.0313568115],"type":"Point"}
}