{
  "type": "Feature",
  "properties": {
    "addr:full":"42 Sturgeon Rd St Albert AB T8N 0E7",
    "addr:housenumber":"42",
    "addr:postcode":"t8n 0e7",
    "addr:street":"Sturgeon Rd St Albert",
    "iso:country":"CA",
    "sg:address":"42 Sturgeon Rd",
    "sg:city":"St Albert",
    "sg:classifiers":[
        {
            "category":"Building & Trades",
            "subcategory":"Construction",
            "type":"Services"
        }
    ],
    "sg:phone":"+1 780 459 0477",
    "sg:postcode":"T8N 0E7",
    "sg:province":"AB",
    "sg:tags":[
        "general",
        "contractor"
    ],
    "wof:name":"Garry Builders Ltd",
    "wof:placetype":"venue"
},
  "geometry": {"coordinates":[-113.618904,53.637321],"type":"Point"}
}