{
  "type": "Feature",
  "properties": {
    "addr:full":"11180 Coppersmith Pl # 243 Richmond BC V7A 5G8",
    "addr:housenumber":"11180;243",
    "addr:postcode":"v7a 5g8",
    "addr:street":"Coppersmith Pl #",
    "iso:country":"CA",
    "sg:address":"11180 Coppersmith Pl # 243",
    "sg:city":"Richmond",
    "sg:classifiers":[
        {
            "category":"Professional",
            "subcategory":"Accounting & Tax Preparation",
            "type":"Services"
        }
    ],
    "sg:phone":"+1 604 275 2181",
    "sg:postcode":"V7A 5G8",
    "sg:province":"BC",
    "sg:tags":[
        "accountant"
    ],
    "wof:name":"Lim & CO",
    "wof:placetype":"venue"
},
  "geometry": {"coordinates":[-123.09663399999999,49.131428],"type":"Point"}
}