{
  "type": "Feature",
  "properties": {
    "addr:full":"300 Montee Monette Saint-Philippe QC J0L 2K0",
    "addr:housenumber":"300",
    "addr:postcode":"j0l 2k0",
    "addr:street":"Montee Monette",
    "iso:country":"CA",
    "sg:address":"300 Montee Monette",
    "sg:city":"Saint-Philippe",
    "sg:classifiers":[
        {
            "category":"Utilities",
            "subcategory":"Fuel Oil & Lpg",
            "type":"Services"
        }
    ],
    "sg:phone":"+1 450 444 3444",
    "sg:postcode":"J0L 2K0",
    "sg:province":"QC",
    "sg:tags":[
        "propane",
        "gas"
    ],
    "wof:name":"Propane Express Inc",
    "wof:placetype":"venue"
},
  "geometry": {"coordinates":[-73.49956512449999,45.3401527405],"type":"Point"}
}