{
  "type": "Feature",
  "properties": {
    "addr:full":"23 Passmore St Charlottetown PE C1A 2B8",
    "addr:housenumber":"23",
    "addr:postcode":"c1a 2b8",
    "addr:street":"Passmore St",
    "iso:country":"CA",
    "sg:address":"23 Passmore St",
    "sg:city":"Charlottetown",
    "sg:classifiers":[
        {
            "category":"Building & Trades",
            "subcategory":"Construction",
            "type":"Services"
        }
    ],
    "sg:phone":"+1 902 368 7546",
    "sg:postcode":"C1A 2B8",
    "sg:province":"PE",
    "sg:tags":[
        "painter"
    ],
    "wof:name":"Vaive Painting CO Ltd",
    "wof:placetype":"venue"
},
  "geometry": {"coordinates":[-63.131916,46.238148],"type":"Point"}
}