{
  "type": "Feature",
  "properties": {
    "addr:full":"24 Rue Grant Longueuil QC J4H 3H3",
    "addr:housenumber":"24",
    "addr:postcode":"j4h 3h3",
    "addr:street":"Rue Grant",
    "iso:country":"CA",
    "sg:address":"24 Rue Grant",
    "sg:city":"Longueuil",
    "sg:classifiers":[
        {
            "category":"Social Services",
            "subcategory":"Child Care",
            "type":"Services"
        }
    ],
    "sg:phone":"+1 450 670 4118",
    "sg:postcode":"J4H 3H3",
    "sg:province":"QC",
    "wof:name":"Jardin D'Enfants Chanterelle",
    "wof:placetype":"venue"
},
  "geometry": {"coordinates":[-73.51068100000001,45.540062],"type":"Point"}
}