{
  "type": "Feature",
  "properties": {
    "iso:country":"CA",
    "sg:address":"24 Rue Grant",
    "sg:city":"Longueuil",
    "sg:classifiers":[
        {
            "category":"Social Services",
            "subcategory":"Child Care",
            "type":"Services"
        }
    ],
    "sg:phone":"+1 450 670 4118",
    "sg:postcode":"J4H 3H3",
    "sg:province":"QC",
    "wof:name":"Jardin D'Enfants Chanterelle",
    "wof:placetype":"venue"
},
  "geometry": {"coordinates":[-73.510681,45.540062],"type":"Point"}
}