{
  "type": "Feature",
  "properties": {
    "addr:full":"77 Brentwood Cres Kingston ON K7M 4V9",
    "addr:housenumber":"77",
    "addr:postcode":"k7m 4v9",
    "addr:street":"Brentwood Cres",
    "iso:country":"CA",
    "sg:address":"77 Brentwood Cres",
    "sg:city":"Kingston",
    "sg:classifiers":[
        {
            "category":"Professional",
            "subcategory":"Business Services",
            "type":"Services"
        }
    ],
    "sg:phone":"+1 613 384 0908",
    "sg:postcode":"K7M 4V9",
    "sg:province":"ON",
    "sg:tags":[
        "appraiser"
    ],
    "wof:name":"Thomas Quirk Fine Art",
    "wof:placetype":"venue"
},
  "geometry": {"coordinates":[-76.5767364502,44.2299499512],"type":"Point"}
}