{
  "type": "Feature",
  "properties": {
    "addr:full":"575 Queen St W Toronto ON M5V 2B6",
    "addr:housenumber":"575",
    "addr:postcode":"m5v 2b6",
    "addr:street":"Queen St W",
    "iso:country":"CA",
    "sg:address":"575 Queen St W",
    "sg:city":"Toronto",
    "sg:classifiers":[
        {
            "category":"Wholesale",
            "subcategory":"Jewelry",
            "type":"Manufacturing & Wholesale Goods"
        }
    ],
    "sg:phone":"+1 416 504 5358",
    "sg:postcode":"M5V 2B6",
    "sg:province":"ON",
    "sg:tags":[
        "ribbon"
    ],
    "wof:name":"Mokuba",
    "wof:placetype":"venue"
},
  "geometry": {"coordinates":[-79.40106964109999,43.6476364136],"type":"Point"}
}