{
  "type": "Feature",
  "properties": {
    "addr:full":"1814 Mast Tower Rd Vancouver BC V6H 4B6",
    "addr:housenumber":"1814",
    "addr:postcode":"v6h 4b6",
    "addr:street":"Mast Tower Rd",
    "iso:country":"CA",
    "sg:address":"1814 Mast Tower Rd",
    "sg:city":"Vancouver",
    "sg:classifiers":[
        {
            "category":"Recreation",
            "subcategory":"Marina",
            "type":"Entertainment"
        }
    ],
    "sg:phone":"+1 604 681 5511",
    "sg:postcode":"V6H 4B6",
    "sg:province":"BC",
    "sg:tags":[
        "repairing",
        "repair",
        "marine",
        "boat"
    ],
    "wof:name":"K & D Marine Ltd",
    "wof:placetype":"venue"
},
  "geometry": {"coordinates":[-123.13621500000001,49.27129],"type":"Point"}
}