{
  "type": "Feature",
  "properties": {
    "addr:full":"12 1Ere Rue O Mont-Louis QC G0E 1T0",
    "addr:housenumber":"12",
    "addr:postcode":"g0e 1t0",
    "addr:street":"1Ere Rue O",
    "iso:country":"CA",
    "sg:address":"12 1Ere Rue O",
    "sg:city":"Mont-Louis",
    "sg:classifiers":[
        {
            "category":"Retail",
            "subcategory":"Funeral Services",
            "type":"Services"
        }
    ],
    "sg:phone":"+1 418 797 2627",
    "sg:postcode":"G0E 1T0",
    "sg:province":"QC",
    "sg:tags":[
        "director"
    ],
    "wof:name":"Salon Funeraire Gilles Marmen",
    "wof:placetype":"venue"
},
  "geometry": {"coordinates":[-65.729248,49.229439],"type":"Point"}
}