{
  "type": "Feature",
  "properties": {
    "addr:full":"4 Pownal St Charlottetown PE C1A 3V6",
    "addr:housenumber":"4",
    "addr:postcode":"c1a 3v6",
    "addr:street":"Pownal St",
    "iso:country":"CA",
    "sg:address":"4 Pownal St",
    "sg:city":"Charlottetown",
    "sg:classifiers":[
        {
            "category":"Real Estate",
            "subcategory":"Real Estate Operator",
            "type":"Services"
        }
    ],
    "sg:phone":"+1 902 892 5341",
    "sg:postcode":"C1A 3V6",
    "sg:province":"PE",
    "sg:tags":[
        "building",
        "apartment",
        "parks"
    ],
    "wof:name":"Charlottetown Area Dev Corp",
    "wof:placetype":"venue"
},
  "geometry": {"coordinates":[-63.125412,46.230408],"type":"Point"}
}