{
  "type": "Feature",
  "properties": {
    "addr:full":"925 Georgia St W # 912 Vancouver BC V6C 3L2",
    "addr:housenumber":"925",
    "addr:postcode":"v6c 3l2",
    "addr:street":"Georgia St W # 912",
    "iso:country":"CA",
    "sg:address":"925 Georgia St W # 912",
    "sg:city":"Vancouver",
    "sg:classifiers":[
        {
            "category":"Real Estate",
            "subcategory":"Real Estate Agent",
            "type":"Services"
        }
    ],
    "sg:phone":"+1 604 687 2121",
    "sg:postcode":"V6C 3L2",
    "sg:province":"BC",
    "sg:tags":[
        "management"
    ],
    "wof:name":"Derby Holdings Ltd",
    "wof:placetype":"venue"
},
  "geometry": {"coordinates":[-123.120132446,49.2840385437],"type":"Point"}
}