{
  "type": "Feature",
  "properties": {
    "addr:full":"Crossfield AB T0M 0S0",
    "addr:postcode":"t0m 0s0",
    "iso:country":"CA",
    "sg:city":"Crossfield",
    "sg:classifiers":[
        {
            "category":"Professional",
            "subcategory":"Testing Lab",
            "type":"Services"
        }
    ],
    "sg:phone":"+1 403 946 4833",
    "sg:postcode":"T0M 0S0",
    "sg:province":"AB",
    "sg:tags":[
        "x"
    ],
    "wof:name":"Western Inspection Ltd",
    "wof:placetype":"venue"
},
  "geometry": {"coordinates":[-114.02707700000001,51.429539],"type":"Point"}
}