{
  "type": "Feature",
  "properties": {
    "addr:full":"Panet QC G0R 2J0",
    "addr:postcode":"g0r 2j0",
    "iso:country":"CA",
    "sg:city":"Panet",
    "sg:classifiers":[
        {
            "category":"Recreation",
            "type":"Entertainment"
        }
    ],
    "sg:phone":"+1 418 249 2018",
    "sg:postcode":"G0R 2J0",
    "sg:province":"QC",
    "sg:tags":[
        "center",
        "government"
    ],
    "wof:name":"Chalet Des Loisirs",
    "wof:placetype":"venue"
},
  "geometry": {"coordinates":[-70.14453125,46.6562309265],"type":"Point"}
}