{
  "type": "Feature",
  "properties": {
    "addr:full":"31 Rue Jacques-Cartier O Chicoutimi QC G7J 1E7",
    "addr:housenumber":"31",
    "addr:postcode":"g7j 1e7",
    "addr:street":"Rue Jacques-Cartier O",
    "iso:country":"CA",
    "sg:address":"31 Rue Jacques-Cartier O",
    "sg:city":"Chicoutimi",
    "sg:classifiers":[
        {
            "category":"Food & Beverages",
            "subcategory":"Groceries & Convenience Stores",
            "type":"Retail Goods"
        }
    ],
    "sg:phone":"+1 418 543 3387",
    "sg:postcode":"G7J 1E7",
    "sg:province":"QC",
    "sg:tags":[
        "grocer"
    ],
    "wof:name":"Marche Centre-Ville",
    "wof:placetype":"venue"
},
  "geometry": {"coordinates":[-71.06755800000001,48.426781],"type":"Point"}
}