{
  "type": "Feature",
  "properties": {
    "addr:full":"Valcourt QC J0E 2L0",
    "addr:postcode":"j0e 2l0",
    "iso:country":"CA",
    "sg:city":"Valcourt",
    "sg:classifiers":[
        {
            "category":"Shopping",
            "subcategory":"Jewelry",
            "type":"Retail Goods"
        }
    ],
    "sg:phone":"+1 450 532 5954",
    "sg:postcode":"J0E 2L0",
    "sg:province":"QC",
    "sg:tags":[
        "jeweler"
    ],
    "wof:name":"Bijouterie Frederic Duval",
    "wof:placetype":"venue"
},
  "geometry": {"coordinates":[-72.308228,45.488552],"type":"Point"}
}