{
  "type": "Feature",
  "properties": {
    "addr:full":"550 Mark St Kimberley BC V1A 2B8",
    "addr:housenumber":"550",
    "addr:postcode":"v1a 2b8",
    "addr:street":"Mark St",
    "iso:country":"CA",
    "sg:address":"550 Mark St",
    "sg:city":"Kimberley",
    "sg:classifiers":[
        {
            "category":"Retail",
            "subcategory":"Animal Services",
            "type":"Services"
        }
    ],
    "sg:phone":"+1 250 427 2311",
    "sg:postcode":"V1A 2B8",
    "sg:province":"BC",
    "sg:tags":[
        "pet",
        "grooming",
        "washing"
    ],
    "wof:name":"Top Dog Grooming & Spa",
    "wof:placetype":"venue"
},
  "geometry": {"coordinates":[-115.981285095,49.6827278137],"type":"Point"}
}