{
  "type": "Feature",
  "properties": {
    "iso:country":"CA",
    "sg:address":"1200 Commissioners Rd E",
    "sg:city":"London",
    "sg:classifiers":[
        {
            "category":"Shopping",
            "subcategory":"Pharmacy",
            "type":"Retail Goods"
        }
    ],
    "sg:phone":"+1 519 686 6395",
    "sg:postcode":"N5Z 4R3",
    "sg:province":"ON",
    "wof:name":"Zellers Pharmacy",
    "wof:placetype":"venue"
},
  "geometry": {"coordinates":[-81.1949005127,42.9624977112],"type":"Point"}
}