{
  "type": "Feature",
  "properties": {
    "addr:full":"4349 Rue Saint-Denis Montreal QC H2J 2K9",
    "addr:housenumber":"4349",
    "addr:postcode":"h2j 2k9",
    "addr:street":"Rue Saint-Denis",
    "iso:country":"CA",
    "sg:address":"4349 Rue Saint-Denis",
    "sg:city":"Montreal",
    "sg:classifiers":[
        {
            "category":"Home & Garden",
            "subcategory":"Furniture",
            "type":"Retail Goods"
        }
    ],
    "sg:phone":"+1 514 527 1293",
    "sg:postcode":"H2J 2K9",
    "sg:province":"QC",
    "wof:name":"Atmosphere Mobilier",
    "wof:placetype":"venue"
},
  "geometry": {"coordinates":[-73.58019299999999,45.522903],"type":"Point"}
}