{
  "type": "Feature",
  "properties": {
    "addr:full":"163 St. Paul Cres St Catharines ON L2S 1N4",
    "addr:housenumber":"163",
    "addr:postcode":"l2s 1n4",
    "addr:street":"St. Paul Cres",
    "iso:country":"CA",
    "sg:address":"163 St. Paul Cres",
    "sg:city":"St Catharines",
    "sg:classifiers":[
        {
            "category":"Health Services",
            "subcategory":"Doctor",
            "type":"Services"
        }
    ],
    "sg:phone":"+1 905 684 9408",
    "sg:postcode":"L2S 1N4",
    "sg:province":"ON",
    "sg:tags":[
        "laboratory",
        "dentist"
    ],
    "wof:name":"Opal Dental",
    "wof:placetype":"venue"
},
  "geometry": {"coordinates":[-79.25090026860001,43.1480674744],"type":"Point"}
}