{
  "type": "Feature",
  "properties": {
    "addr:full":"430 King St Wallaceburg ON N8A 1J1",
    "addr:housenumber":"430",
    "addr:postcode":"n8a 1j1",
    "addr:street":"King St",
    "iso:country":"CA",
    "sg:address":"430 King St",
    "sg:city":"Wallaceburg",
    "sg:classifiers":[
        {
            "category":"Education",
            "subcategory":"School",
            "type":"Public Place"
        }
    ],
    "sg:phone":"+1 519 627 5151",
    "sg:postcode":"N8A 1J1",
    "sg:province":"ON",
    "wof:name":"D A Gordon School",
    "wof:placetype":"venue"
},
  "geometry": {"coordinates":[-82.380775,42.592789],"type":"Point"}
}