{
  "type": "Feature",
  "properties": {
    "addr:full":"Vegreville AB T9C 1R7",
    "addr:postcode":"t9c 1r7",
    "iso:country":"CA",
    "sg:city":"Vegreville",
    "sg:classifiers":[
        {
            "category":"Sports & Exercise",
            "subcategory":"Bowling",
            "type":"Entertainment"
        }
    ],
    "sg:phone":"+1 780 632 7665",
    "sg:postcode":"T9C 1R7",
    "sg:province":"AB",
    "sg:tags":[
        "center"
    ],
    "wof:name":"Vegreville Bowling Lanes",
    "wof:placetype":"venue"
},
  "geometry": {"coordinates":[-112.050133,53.494625],"type":"Point"}
}