{
  "type": "Feature",
  "properties": {
    "addr:full":"735 Weller Crt Oakville ON L6K 3S9",
    "addr:housenumber":"735",
    "addr:postcode":"l6k 3s9",
    "addr:street":"Weller Crt",
    "iso:country":"CA",
    "sg:address":"735 Weller Crt",
    "sg:city":"Oakville",
    "sg:classifiers":[
        {
            "category":"Building & Trades",
            "subcategory":"Construction",
            "type":"Services"
        }
    ],
    "sg:phone":"+1 905 662 0123",
    "sg:postcode":"L6K 3S9",
    "sg:province":"ON",
    "sg:tags":[
        "sewer",
        "cleaning",
        "contractor"
    ],
    "wof:name":"Bcs Inc",
    "wof:placetype":"venue"
},
  "geometry": {"coordinates":[-79.698494,43.442062],"type":"Point"}
}