{
  "type": "Feature",
  "properties": {
    "addr:full":"5203 44 Ave Drayton Valley AB T7A 1L2",
    "addr:housenumber":"5203",
    "addr:postcode":"t7a 1l2",
    "addr:street":"44 Ave",
    "iso:country":"CA",
    "sg:address":"5203 44 Ave",
    "sg:city":"Drayton Valley",
    "sg:classifiers":[
        {
            "category":"Travel",
            "subcategory":"Campground",
            "type":"Entertainment"
        }
    ],
    "sg:phone":"+1 780 894 3555",
    "sg:postcode":"T7A 1L2",
    "sg:province":"AB",
    "sg:tags":[
        "camp"
    ],
    "wof:name":"Peco Inn",
    "wof:placetype":"venue"
},
  "geometry": {"coordinates":[-114.979675293,53.2153778076],"type":"Point"}
}