{
  "type": "Feature",
  "properties": {
    "addr:full":"86 Scollard St Toronto ON M5R 1G2",
    "addr:housenumber":"86",
    "addr:postcode":"m5r 1g2",
    "addr:street":"Scollard St",
    "iso:country":"CA",
    "sg:address":"86 Scollard St",
    "sg:city":"Toronto",
    "sg:classifiers":[
        {
            "category":"Wholesale",
            "subcategory":"Apparel",
            "type":"Manufacturing & Wholesale Goods"
        }
    ],
    "sg:phone":"+1 416 926 0663",
    "sg:postcode":"M5R 1G2",
    "sg:province":"ON",
    "sg:tags":[
        "clothing"
    ],
    "wof:name":"Chambers & Sons Agents",
    "wof:placetype":"venue"
},
  "geometry": {"coordinates":[-79.391823,43.671986],"type":"Point"}
}