{
  "type": "Feature",
  "properties": {
    "addr:full":"870 Red River Rd Thunder Bay ON P7B 1K2",
    "addr:housenumber":"870",
    "addr:postcode":"p7b 1k2",
    "addr:street":"Red River Rd",
    "iso:country":"CA",
    "sg:address":"870 Red River Rd",
    "sg:city":"Thunder Bay",
    "sg:classifiers":[
        {
            "category":"Shopping",
            "subcategory":"Used Merchandise",
            "type":"Retail Goods"
        }
    ],
    "sg:phone":"+1 807 767 7768",
    "sg:postcode":"P7B 1K2",
    "sg:province":"ON",
    "sg:tags":[
        "second",
        "store",
        "hand"
    ],
    "wof:name":"Salvation Army",
    "wof:placetype":"venue"
},
  "geometry": {"coordinates":[-89.24839,48.446609],"type":"Point"}
}