{
  "type": "Feature",
  "properties": {
    "iso:country":"CA",
    "sg:city":"Brooks",
    "sg:classifiers":[
        {
            "category":"Retail",
            "subcategory":"Car Wash",
            "type":"Services"
        }
    ],
    "sg:phone":"+1 403 793 8003",
    "sg:postcode":"T1R 0N3",
    "sg:province":"AB",
    "sg:tags":[
        "polishing",
        "washing"
    ],
    "wof:name":"Spot Free Car & Truck Wash Ltd",
    "wof:placetype":"venue"
},
  "geometry": {"coordinates":[-111.895713806,50.5745162964],"type":"Point"}
}