{
  "type": "Feature",
  "properties": {
    "addr:full":"9021 Boul Saint-Michel Montreal QC H1Z 3G3",
    "addr:housenumber":"9021",
    "addr:postcode":"h1z 3g3",
    "addr:street":"Boul Saint-Michel",
    "iso:country":"CA",
    "sg:address":"9021 Boul Saint-Michel",
    "sg:city":"Montreal",
    "sg:classifiers":[
        {
            "category":"Shopping",
            "subcategory":"Pharmacy",
            "type":"Retail Goods"
        }
    ],
    "sg:phone":"+1 514 955 0800",
    "sg:postcode":"H1Z 3G3",
    "sg:province":"QC",
    "wof:name":"Jean Coutu Pharmacy",
    "wof:placetype":"venue"
},
  "geometry": {"coordinates":[-73.62670135499999,45.5715866089],"type":"Point"}
}