{
  "type": "Feature",
  "properties": {
    "addr:full":"926 116A St NW Edmonton AB T6J 6Z7",
    "addr:housenumber":"926 116a",
    "addr:postcode":"t6j 6z7",
    "addr:street":"St Nw",
    "iso:country":"CA",
    "sg:address":"926 116A St NW",
    "sg:city":"Edmonton",
    "sg:classifiers":[
        {
            "category":"Insurance",
            "subcategory":"Insurance Agent",
            "type":"Services"
        }
    ],
    "sg:phone":"+1 780 988 0098",
    "sg:postcode":"T6J 6Z7",
    "sg:province":"AB",
    "wof:name":"Health Risk Mgmt Group",
    "wof:placetype":"venue"
},
  "geometry": {"coordinates":[-113.53434753400001,53.4379997253],"type":"Point"}
}