{
  "type": "Feature",
  "properties": {
    "addr:full":"603 Ch Des Patriotes Saint-Denis-Sur-Richelieu QC J0H 1K0",
    "addr:housenumber":"603",
    "addr:postcode":"j0h 1k0",
    "addr:street":"Ch Des Patriotes",
    "iso:country":"CA",
    "sg:address":"603 Ch Des Patriotes",
    "sg:city":"Saint-Denis-Sur-Richelieu",
    "sg:classifiers":[
        {
            "category":"Restaurant",
            "type":"Food & Drink"
        }
    ],
    "sg:phone":"+1 450 787 4078",
    "sg:postcode":"J0H 1K0",
    "sg:province":"QC",
    "wof:name":"Auberge St-Denis Sur Richelieu",
    "wof:placetype":"venue"
},
  "geometry": {"coordinates":[-73.15952299999999,45.786079],"type":"Point"}
}