{
  "type": "Feature",
  "properties": {
    "addr:full":"360 Mountain Rd Moncton NB E1C 2M6",
    "addr:housenumber":"360",
    "addr:postcode":"e1c 2m6",
    "addr:street":"Mountain Rd",
    "iso:country":"CA",
    "sg:address":"360 Mountain Rd",
    "sg:city":"Moncton",
    "sg:classifiers":[
        {
            "category":"Shopping",
            "subcategory":"Florist",
            "type":"Retail Goods"
        }
    ],
    "sg:phone":"+1 506 857 4888",
    "sg:postcode":"E1C 2M6",
    "sg:province":"NB",
    "wof:name":"Mac Arthur's Flower Shop Ltd",
    "wof:placetype":"venue"
},
  "geometry": {"coordinates":[-64.791786,46.096207],"type":"Point"}
}