{
  "type": "Feature",
  "properties": {
    "addr:full":"304 Parliament St Toronto ON M5A 3A4",
    "addr:housenumber":"304",
    "addr:postcode":"m5a 3a4",
    "addr:street":"Parliament St",
    "iso:country":"CA",
    "sg:address":"304 Parliament St",
    "sg:city":"Toronto",
    "sg:classifiers":[
        {
            "category":"Organizations",
            "subcategory":"Religious Organization",
            "type":"Services"
        }
    ],
    "sg:phone":"+1 416 366 9768",
    "sg:postcode":"M5A 3A4",
    "sg:province":"ON",
    "sg:tags":[
        "church"
    ],
    "wof:name":"Salvation Army",
    "wof:placetype":"venue"
},
  "geometry": {"coordinates":[-79.36608886720001,43.659160614],"type":"Point"}
}