{
  "type": "Feature",
  "properties": {
    "addr:full":"413 Tranquille Rd Kamloops BC V2B 3G9",
    "addr:housenumber":"413",
    "addr:postcode":"bc v2b 3g9",
    "addr:street":"Tranquille Rd",
    "iso:country":"CA",
    "sg:address":"413 Tranquille Rd",
    "sg:city":"Kamloops",
    "sg:classifiers":[
        {
            "category":"Restaurant",
            "type":"Food & Drink"
        }
    ],
    "sg:phone":"+1 250 554 7080",
    "sg:postcode":"V2B 3G9",
    "sg:province":"BC",
    "wof:name":"Warunee's Thai Restaurant",
    "wof:placetype":"venue"
},
  "geometry": {"coordinates":[-120.358727,50.690338],"type":"Point"}
}