{
  "type": "Feature",
  "properties": {
    "addr:full":"9148 Rue DE Louisiane Saint-Leonard QC H1P 2P5",
    "addr:housenumber":"9148",
    "addr:postcode":"h1p 2p5",
    "addr:street":"Rue De Louisiane",
    "iso:country":"CA",
    "sg:address":"9148 Rue DE Louisiane",
    "sg:city":"Saint-Leonard",
    "sg:classifiers":[
        {
            "category":"Building & Trades",
            "subcategory":"Electrical",
            "type":"Services"
        }
    ],
    "sg:phone":"+1 514 321 9350",
    "sg:postcode":"H1P 2P5",
    "sg:province":"QC",
    "sg:tags":[
        "electric",
        "contractor"
    ],
    "wof:name":"Entreprises D'Elect Rbl Ltee",
    "wof:placetype":"venue"
},
  "geometry": {"coordinates":[-73.607201,45.596664],"type":"Point"}
}