{
  "type": "Feature",
  "properties": {
    "addr:full":"38900 No. 4 Rd Abbotsford BC V3G 2G2",
    "addr:postcode":"38900;v3g 2g2",
    "addr:street":"4 Rd",
    "iso:country":"CA",
    "sg:address":"38900 No. 4 Rd",
    "sg:city":"Abbotsford",
    "sg:classifiers":[
        {
            "category":"Wholesale",
            "subcategory":"Fruits & Vegetables",
            "type":"Manufacturing & Wholesale Goods"
        }
    ],
    "sg:phone":"+1 604 852 4009",
    "sg:postcode":"V3G 2G2",
    "sg:province":"BC",
    "sg:tags":[
        "shipper"
    ],
    "wof:name":"Van Eekelen Enterprises Ltd",
    "wof:placetype":"venue"
},
  "geometry": {"coordinates":[-122.14634700000001,49.074898],"type":"Point"}
}