{
  "type": "Feature",
  "properties": {
    "iso:country":"CA",
    "sg:address":"7725 Rue DE Teck",
    "sg:city":"Montreal",
    "sg:classifiers":[
        {
            "category":"Building & Trades",
            "subcategory":"Cleaning & Sanitation",
            "type":"Services"
        }
    ],
    "sg:phone":"+1 514 353 7811",
    "sg:postcode":"H1L 1G5",
    "sg:province":"QC",
    "sg:tags":[
        "window"
    ],
    "wof:name":"Lavage DE Vitres DE L'Est Ltee",
    "wof:placetype":"venue"
},
  "geometry": {"coordinates":[-73.534203,45.593925],"type":"Point"}
}