{
  "type": "Feature",
  "properties": {
    "addr:full":"306 Mercer St Chatham ON N7M 6E1",
    "addr:housenumber":"306",
    "addr:postcode":"n7m 6e1",
    "addr:street":"Mercer St",
    "iso:country":"CA",
    "sg:address":"306 Mercer St",
    "sg:city":"Chatham",
    "sg:classifiers":[
        {
            "category":"Home & Garden",
            "subcategory":"Household Appliances",
            "type":"Retail Goods"
        }
    ],
    "sg:phone":"+1 519 358 1700",
    "sg:postcode":"N7M 6E1",
    "sg:province":"ON",
    "wof:name":"Gilbert's Appliance Svc",
    "wof:placetype":"venue"
},
  "geometry": {"coordinates":[-82.16237599999999,42.398544],"type":"Point"}
}