{
  "type": "Feature",
  "properties": {
    "iso:country":"CA",
    "sg:address":"629 1st Ave Hwy 25 W",
    "sg:city":"Rivers",
    "sg:classifiers":[
        {
            "category":"Autos & Motor Vehicles",
            "subcategory":"Fuel & Gas Station",
            "type":"Retail Goods"
        }
    ],
    "sg:phone":"+1 204 328 7893",
    "sg:postcode":"R0K 1X0",
    "sg:province":"MB",
    "sg:tags":[
        "oil"
    ],
    "wof:name":"Cross Town Tempo Inn",
    "wof:placetype":"venue"
},
  "geometry": {"coordinates":[-100.23764038100001,50.0292854309],"type":"Point"}
}