{
  "type": "Feature",
  "properties": {
    "addr:full":"Hwy 5 Mountain View AB T0K 1N0",
    "addr:postcode":"t0k 1n0",
    "addr:street":"Hwy 5 Mountain View",
    "iso:country":"CA",
    "sg:address":"Hwy 5",
    "sg:city":"Mountain View",
    "sg:classifiers":[
        {
            "category":"Education",
            "subcategory":"School",
            "type":"Public Place"
        }
    ],
    "sg:phone":"+1 403 653 2404",
    "sg:postcode":"T0K 1N0",
    "sg:province":"AB",
    "wof:name":"Mountain View School",
    "wof:placetype":"venue"
},
  "geometry": {"coordinates":[-113.59053,49.132339],"type":"Point"}
}