{
  "type": "Feature",
  "properties": {
    "addr:full":"1501 Rue Principale Saint-Come QC J0K 2B0",
    "addr:housenumber":"1501",
    "addr:postcode":"j0k 2b0",
    "addr:street":"Rue Principale",
    "iso:country":"CA",
    "sg:address":"1501 Rue Principale",
    "sg:city":"Saint-Come",
    "sg:classifiers":[
        {
            "category":"Food & Beverages",
            "subcategory":"Bakery",
            "type":"Retail Goods"
        }
    ],
    "sg:phone":"+1 450 883 5101",
    "sg:postcode":"J0K 2B0",
    "sg:province":"QC",
    "sg:tags":[
        "baker"
    ],
    "wof:name":"Boulangerie St-Come Inc",
    "wof:placetype":"venue"
},
  "geometry": {"coordinates":[-73.77134700000001,46.27137],"type":"Point"}
}