{
  "type": "Feature",
  "properties": {
    "addr:full":"2441 Lakeshore Rd W Oakville ON L6L 5V5",
    "addr:housenumber":"2441",
    "addr:postcode":"l6l 5v5",
    "addr:street":"Lakeshore Rd W",
    "iso:country":"CA",
    "sg:address":"2441 Lakeshore Rd W",
    "sg:city":"Oakville",
    "sg:classifiers":[
        {
            "category":"Shopping",
            "subcategory":"Pharmacy",
            "type":"Retail Goods"
        }
    ],
    "sg:phone":"+1 905 825 0677",
    "sg:postcode":"L6L 5V5",
    "sg:province":"ON",
    "wof:name":"Pharma Plus Drugmart",
    "wof:placetype":"venue"
},
  "geometry": {"coordinates":[-79.711555481,43.3947753906],"type":"Point"}
}