{
  "type": "Feature",
  "properties": {
    "iso:country":"CA",
    "sg:address":"5820 50 Ave",
    "sg:city":"Red Deer",
    "sg:classifiers":[
        {
            "category":"Retail",
            "subcategory":"Auto Repair",
            "type":"Services"
        }
    ],
    "sg:phone":"+1 403 342 1233",
    "sg:postcode":"T4N 4C2",
    "sg:province":"AB",
    "sg:tags":[
        "repairing",
        "automobile"
    ],
    "wof:name":"Express Automotive Ctr",
    "wof:placetype":"venue"
},
  "geometry": {"coordinates":[-113.81420135499999,52.2777709961],"type":"Point"}
}