{
  "type": "Feature",
  "properties": {
    "addr:full":"6248 Pleasant Valley Rd Vernon BC V1B 3R3",
    "addr:housenumber":"6248",
    "addr:postcode":"bc v1b 3r3",
    "addr:street":"Pleasant Valley Rd",
    "iso:country":"CA",
    "sg:address":"6248 Pleasant Valley Rd",
    "sg:city":"Vernon",
    "sg:classifiers":[
        {
            "category":"Manufacturing",
            "subcategory":"Watercraft",
            "type":"Manufacturing & Wholesale Goods"
        }
    ],
    "sg:phone":"+1 250 542 4866",
    "sg:postcode":"V1B 3R3",
    "sg:province":"BC",
    "sg:tags":[
        "boat"
    ],
    "wof:name":"Interior Fiberglas Ltd",
    "wof:placetype":"venue"
},
  "geometry": {"coordinates":[-119.25355529799999,50.2829284668],"type":"Point"}
}