{
  "type": "Feature",
  "properties": {
    "addr:full":"4270 Mountain Sq Whistler BC V0N 1B4",
    "addr:housenumber":"4270",
    "addr:postcode":"v0n 1b4",
    "addr:street":"Mountain Sq",
    "iso:country":"CA",
    "sg:address":"4270 Mountain Sq",
    "sg:city":"Whistler",
    "sg:classifiers":[
        {
            "category":"Restaurant",
            "type":"Food & Drink"
        }
    ],
    "sg:phone":"+1 604 932 6945",
    "sg:postcode":"V0N 1B4",
    "sg:province":"BC",
    "wof:name":"Black's Pub & Restaurant",
    "wof:placetype":"venue"
},
  "geometry": {"coordinates":[-122.954819,50.113594],"type":"Point"}
}