{
  "type": "Feature",
  "properties": {
    "iso:country":"CA",
    "sg:city":"Corbeil",
    "sg:classifiers":[
        {
            "category":"Building & Trades",
            "subcategory":"Plumbing",
            "type":"Services"
        }
    ],
    "sg:phone":"+1 705 752 1623",
    "sg:postcode":"P0H 1K0",
    "sg:province":"ON",
    "sg:tags":[
        "contractor"
    ],
    "wof:name":"Bob's Plumbing",
    "wof:placetype":"venue"
},
  "geometry": {"coordinates":[-79.29141235349999,46.2617683411],"type":"Point"}
}