{
  "type": "Feature",
  "properties": {
    "addr:full":"16615 116 Ave NW Edmonton AB T5M 3V1",
    "addr:housenumber":"16615",
    "addr:postcode":"t5m 3v1",
    "addr:street":"116 Ave Nw",
    "iso:country":"CA",
    "sg:address":"16615 116 Ave NW",
    "sg:city":"Edmonton",
    "sg:classifiers":[
        {
            "category":"Manufacturing",
            "subcategory":"Tools & Machinery",
            "type":"Manufacturing & Wholesale Goods"
        }
    ],
    "sg:phone":"+1 780 452 5353",
    "sg:postcode":"T5M 3V1",
    "sg:province":"AB",
    "sg:tags":[
        "storage"
    ],
    "wof:name":"Exide Batteries",
    "wof:placetype":"venue"
},
  "geometry": {"coordinates":[-113.61058807400001,53.5653991699],"type":"Point"}
}