{
  "type": "Feature",
  "properties": {
    "iso:country":"CA",
    "sg:address":"1 Regan Rd # 7",
    "sg:city":"Brampton",
    "sg:classifiers":[
        {
            "category":"Shopping",
            "subcategory":"Computers & Home Electronics",
            "type":"Retail Goods"
        }
    ],
    "sg:phone":"+1 905 840 5706",
    "sg:postcode":"L7A 1B8",
    "sg:province":"ON",
    "sg:tags":[
        "equipment",
        "satellite",
        "system"
    ],
    "wof:name":"Dupes International Ltd",
    "wof:placetype":"venue"
},
  "geometry": {"coordinates":[-79.798897,43.699833],"type":"Point"}
}