{
  "type": "Feature",
  "properties": {
    "addr:full":"6066 Rue Sherbrooke O Montreal QC H4A 1Y1",
    "addr:housenumber":"6066",
    "addr:postcode":"h4a 1y1",
    "addr:street":"Rue Sherbrooke O",
    "iso:country":"CA",
    "sg:address":"6066 Rue Sherbrooke O",
    "sg:city":"Montreal",
    "sg:classifiers":[
        {
            "category":"Restaurant",
            "type":"Food & Drink"
        }
    ],
    "sg:phone":"+1 514 487 7744",
    "sg:postcode":"H4A 1Y1",
    "sg:province":"QC",
    "wof:name":"Tchang Kiang Restaurant",
    "wof:placetype":"venue"
},
  "geometry": {"coordinates":[-73.54583740229999,45.5777053833],"type":"Point"}
}