{
  "type": "Feature",
  "properties": {
    "addr:full":"Pointe-Claire QC H9R 1G6",
    "addr:postcode":"h9r 1g6",
    "iso:country":"CA",
    "sg:city":"Pointe-Claire",
    "sg:classifiers":[
        {
            "category":"Professional",
            "subcategory":"Advertising",
            "type":"Services"
        }
    ],
    "sg:phone":"+1 514 426 4000",
    "sg:postcode":"H9R 1G6",
    "sg:province":"QC",
    "sg:tags":[
        "counselor"
    ],
    "wof:name":"Adperformance Direct Inc",
    "wof:placetype":"venue"
},
  "geometry": {"coordinates":[-73.8306503296,45.4560203552],"type":"Point"}
}