{
  "type": "Feature",
  "properties": {
    "addr:full":"25 Cityview Ave Fredericton NB E3A 1S9",
    "addr:housenumber":"25",
    "addr:postcode":"e3a 1s9",
    "addr:street":"Cityview Ave",
    "iso:country":"CA",
    "sg:address":"25 Cityview Ave",
    "sg:city":"Fredericton",
    "sg:classifiers":[
        {
            "category":"Retail",
            "subcategory":"Auto Repair",
            "type":"Services"
        }
    ],
    "sg:phone":"+1 506 472 3879",
    "sg:postcode":"E3A 1S9",
    "sg:province":"NB",
    "sg:tags":[
        "repairing",
        "automobile"
    ],
    "wof:name":"King Performance",
    "wof:placetype":"venue"
},
  "geometry": {"coordinates":[-66.64671300000001,45.974438],"type":"Point"}
}