{
  "type": "Feature",
  "properties": {
    "addr:full":"1514 Pine Portage Rd Kenora ON P9N 2K2",
    "addr:housenumber":"1514",
    "addr:postcode":"p9n 2k2",
    "addr:street":"Pine Portage Rd",
    "iso:country":"CA",
    "sg:address":"1514 Pine Portage Rd",
    "sg:city":"Kenora",
    "sg:classifiers":[
        {
            "category":"Travel",
            "subcategory":"Campground",
            "type":"Entertainment"
        }
    ],
    "sg:phone":"+1 807 224 4531",
    "sg:postcode":"P9N 2K2",
    "sg:province":"ON",
    "sg:tags":[
        "camp"
    ],
    "wof:name":"Kcr Landing",
    "wof:placetype":"venue"
},
  "geometry": {"coordinates":[-94.467117,49.758228],"type":"Point"}
}