{
  "type": "Feature",
  "properties": {
    "addr:full":"330 Jarvis Ave Winnipeg MB R2W 5L3",
    "addr:housenumber":"330",
    "addr:postcode":"r2w 5l3",
    "addr:street":"Jarvis Ave",
    "iso:country":"CA",
    "sg:address":"330 Jarvis Ave",
    "sg:city":"Winnipeg",
    "sg:classifiers":[
        {
            "category":"Recreation",
            "type":"Entertainment"
        }
    ],
    "sg:phone":"+1 204 586 9555",
    "sg:postcode":"R2W 5L3",
    "sg:province":"MB",
    "sg:tags":[
        "martial",
        "arts",
        "instruction"
    ],
    "wof:name":"Dragon Muay Thai Kickboxing",
    "wof:placetype":"venue"
},
  "geometry": {"coordinates":[-97.1405258179,49.9096031189],"type":"Point"}
}