{
  "type": "Feature",
  "properties": {
    "addr:full":"21 Bradgate Dr Nepean ON K2G 0R7",
    "addr:housenumber":"21",
    "addr:postcode":"k2g 0r7",
    "addr:street":"Bradgate Dr",
    "iso:country":"CA",
    "sg:address":"21 Bradgate Dr",
    "sg:city":"Nepean",
    "sg:classifiers":[
        {
            "category":"Professional",
            "subcategory":"Business Services",
            "type":"Services"
        }
    ],
    "sg:phone":"+1 613 596 3000",
    "sg:postcode":"K2G 0R7",
    "sg:province":"ON",
    "sg:tags":[
        "event"
    ],
    "wof:name":"Stanton Total Event Planning",
    "wof:placetype":"venue"
},
  "geometry": {"coordinates":[-75.782066,45.336143],"type":"Point"}
}