{
  "type": "Feature",
  "properties": {
    "addr:full":"1169 Michener Rd Sarnia ON N7S 4W3",
    "addr:housenumber":"1169",
    "addr:postcode":"n7s 4w3",
    "addr:street":"Michener Rd",
    "iso:country":"CA",
    "sg:address":"1169 Michener Rd",
    "sg:city":"Sarnia",
    "sg:classifiers":[
        {
            "category":"Local Transit",
            "type":"Transportation"
        }
    ],
    "sg:phone":"+1 519 336 3271",
    "sg:postcode":"N7S 4W3",
    "sg:province":"ON",
    "sg:tags":[
        "bus",
        "line",
        "government"
    ],
    "wof:name":"Sarnia Transit CO",
    "wof:placetype":"venue"
},
  "geometry": {"coordinates":[-82.370384,42.958145],"type":"Point"}
}