{
  "type": "Feature",
  "properties": {
    "addr:full":"178 Mechanic St W Waterford ON N0E 1Y0",
    "addr:housenumber":"178",
    "addr:postcode":"n0e 1y0",
    "addr:street":"Mechanic St W",
    "iso:country":"CA",
    "sg:address":"178 Mechanic St W",
    "sg:city":"Waterford",
    "sg:classifiers":[
        {
            "category":"Building & Trades",
            "subcategory":"Construction",
            "type":"Services"
        }
    ],
    "sg:phone":"+1 519 443 4690",
    "sg:postcode":"N0E 1Y0",
    "sg:province":"ON",
    "sg:tags":[
        "concrete",
        "contractor"
    ],
    "wof:name":"Terra Firma Decorative Concret",
    "wof:placetype":"venue"
},
  "geometry": {"coordinates":[-80.302155,42.935345],"type":"Point"}
}