{
  "type": "Feature",
  "properties": {
    "addr:full":"5702 King St Riverside-Albert NB E4H 4B2",
    "addr:housenumber":"5702",
    "addr:postcode":"e4h 4b2",
    "addr:street":"King St",
    "iso:country":"CA",
    "sg:address":"5702 King St",
    "sg:city":"Riverside-Albert",
    "sg:classifiers":[
        {
            "category":"Shopping",
            "type":"Retail Goods"
        }
    ],
    "sg:phone":"+1 506 882 2276",
    "sg:postcode":"E4H 4B2",
    "sg:province":"NB",
    "sg:tags":[
        "art",
        "gallery",
        "dealer"
    ],
    "wof:name":"Joie DE Vivre",
    "wof:placetype":"venue"
},
  "geometry": {"coordinates":[-64.72550200000001,45.753769],"type":"Point"}
}