{
  "type": "Feature",
  "properties": {
    "addr:full":"566 Willoughby St Lucknow ON N0G 2H0",
    "addr:housenumber":"566",
    "addr:postcode":"n0g 2h0",
    "addr:street":"Willoughby St",
    "iso:country":"CA",
    "sg:address":"566 Willoughby St",
    "sg:city":"Lucknow",
    "sg:classifiers":[
        {
            "category":"Food & Beverages",
            "subcategory":"Liquor & Beverages",
            "type":"Retail Goods"
        }
    ],
    "sg:phone":"+1 519 528 2335",
    "sg:postcode":"N0G 2H0",
    "sg:province":"ON",
    "sg:tags":[
        "store"
    ],
    "wof:name":"Liquor Control Board of Ont",
    "wof:placetype":"venue"
},
  "geometry": {"coordinates":[-81.515564,43.959686],"type":"Point"}
}