{
  "type": "Feature",
  "properties": {
    "addr:full":"Happy Valley-Goose Bay NL A0P 1C0",
    "addr:postcode":"a0p 1c0",
    "iso:country":"CA",
    "sg:city":"Happy Valley-Goose Bay",
    "sg:classifiers":[
        {
            "category":"Airport",
            "type":"Transportation"
        }
    ],
    "sg:phone":"+1 709 896 7373",
    "sg:postcode":"A0P 1C0",
    "sg:province":"NL",
    "sg:tags":[
        "aircraft",
        "maintenance"
    ],
    "wof:name":"Irving Aviation Svc Ltd",
    "wof:placetype":"venue"
},
  "geometry": {"coordinates":[-60.29594,53.29583],"type":"Point"}
}