{
  "type": "Feature",
  "properties": {
    "addr:full":"4130 Petrolia St Petrolia ON N0N 1R0",
    "addr:housenumber":"4130",
    "addr:postcode":"n0n 1r0",
    "addr:street":"Petrolia St",
    "iso:country":"CA",
    "sg:address":"4130 Petrolia St",
    "sg:city":"Petrolia",
    "sg:classifiers":[
        {
            "category":"Banks & Credit Unions",
            "subcategory":"Bank",
            "type":"Services"
        }
    ],
    "sg:phone":"+1 519 882 1357",
    "sg:postcode":"N0N 1R0",
    "sg:province":"ON",
    "wof:name":"Cibc",
    "wof:placetype":"venue"
},
  "geometry": {"coordinates":[-82.150887,42.882149],"type":"Point"}
}