{
  "type": "Feature",
  "properties": {
    "addr:full":"718 Manitoba St Melville SK S0A 2P0",
    "addr:housenumber":"718",
    "addr:postcode":"s0a 2p0",
    "addr:street":"Manitoba St",
    "iso:country":"CA",
    "sg:address":"718 Manitoba St",
    "sg:city":"Melville",
    "sg:classifiers":[
        {
            "category":"Health Services",
            "subcategory":"Hospital",
            "type":"Services"
        }
    ],
    "sg:phone":"+1 306 728 5407",
    "sg:postcode":"S0A 2P0",
    "sg:province":"SK",
    "wof:name":"St Peter's Hospital",
    "wof:placetype":"venue"
},
  "geometry": {"coordinates":[-102.793037,50.924919],"type":"Point"}
}