{
  "type": "Feature",
  "properties": {
    "addr:full":"56 Kensington Ave # D Toronto ON M5T 2K1",
    "addr:housenumber":"56",
    "addr:postcode":"m5t 2k1",
    "addr:street":"Kensington Ave # D",
    "iso:country":"CA",
    "sg:address":"56 Kensington Ave # D",
    "sg:city":"Toronto",
    "sg:classifiers":[
        {
            "category":"Food & Beverages",
            "subcategory":"Groceries & Convenience Stores",
            "type":"Retail Goods"
        }
    ],
    "sg:phone":"+1 416 595 5891",
    "sg:postcode":"M5T 2K1",
    "sg:province":"ON",
    "sg:tags":[
        "variety"
    ],
    "wof:name":"Kensington Variety",
    "wof:placetype":"venue"
},
  "geometry": {"coordinates":[-79.40064239500001,43.6541633606],"type":"Point"}
}