{
  "type": "Feature",
  "properties": {
    "addr:full":"182 Ch St-Henri Sainte-Marthe QC J0P 1W0",
    "addr:housenumber":"182",
    "addr:postcode":"j0p 1w0",
    "addr:street":"Ch St-Henri",
    "iso:country":"CA",
    "sg:address":"182 Ch St-Henri",
    "sg:city":"Sainte-Marthe",
    "sg:classifiers":[
        {
            "category":"Recreation",
            "type":"Entertainment"
        }
    ],
    "sg:phone":"+1 450 458 7810",
    "sg:postcode":"J0P 1W0",
    "sg:province":"QC",
    "sg:tags":[
        "stable"
    ],
    "wof:name":"Equane Connection",
    "wof:placetype":"venue"
},
  "geometry": {"coordinates":[-74.2575302124,45.4224357605],"type":"Point"}
}