{
  "type": "Feature",
  "properties": {
    "addr:full":"11 Elizabeth Dr Paradise NL A1L 1E5",
    "addr:housenumber":"11",
    "addr:postcode":"a1l 1e5",
    "addr:street":"Elizabeth Dr",
    "iso:country":"CA",
    "sg:address":"11 Elizabeth Dr",
    "sg:city":"Paradise",
    "sg:classifiers":[
        {
            "category":"Social Services",
            "subcategory":"Child Care",
            "type":"Services"
        }
    ],
    "sg:phone":"+1 709 782 7007",
    "sg:postcode":"A1L 1E5",
    "sg:province":"NL",
    "wof:name":"Rainbow Day Care Ctr",
    "wof:placetype":"venue"
},
  "geometry": {"coordinates":[-52.840427,47.541767],"type":"Point"}
}