{
  "type": "Feature",
  "properties": {
    "iso:country":"CA",
    "sg:address":"137 Campbell St",
    "sg:city":"Sarnia",
    "sg:classifiers":[
        {
            "category":"Home & Garden",
            "subcategory":"Building Materials",
            "type":"Retail Goods"
        }
    ],
    "sg:phone":"+1 519 336 7930",
    "sg:postcode":"N7T 2G6",
    "sg:province":"ON",
    "sg:tags":[
        "windows"
    ],
    "wof:name":"Sarnia Glass & Aluminum Prods",
    "wof:placetype":"venue"
},
  "geometry": {"coordinates":[-82.40283966059999,42.9590530396],"type":"Point"}
}