{
  "type": "Feature",
  "properties": {
    "addr:full":"PO Box 18 Kayville SK S0H 2C0",
    "addr:housenumber":"po box 18",
    "addr:postcode":"s0h 2c0",
    "addr:street":"Kayville",
    "iso:country":"CA",
    "sg:address":"PO Box 18",
    "sg:city":"Kayville",
    "sg:classifiers":[
        {
            "category":"Banks & Credit Unions",
            "subcategory":"Bank",
            "type":"Services"
        }
    ],
    "sg:phone":"+1 306 475 2712",
    "sg:postcode":"S0H 2C0",
    "sg:province":"SK",
    "wof:name":"Kayville Credit Union",
    "wof:placetype":"venue"
},
  "geometry": {"coordinates":[-105.14596557599999,49.7265396118],"type":"Point"}
}