{
  "type": "Feature",
  "properties": {
    "addr:full":"PO Box 368 Cremona AB T0M 0R0",
    "addr:housenumber":"po",
    "addr:postcode":"t0m 0r0",
    "addr:street":"Box 368",
    "iso:country":"CA",
    "sg:address":"PO Box 368",
    "sg:city":"Cremona",
    "sg:classifiers":[
        {
            "category":"Organizations",
            "subcategory":"Religious Organization",
            "type":"Services"
        }
    ],
    "sg:phone":"+1 403 637 2200",
    "sg:postcode":"T0M 0R0",
    "sg:province":"AB",
    "sg:tags":[
        "church"
    ],
    "wof:name":"Cremona United Church",
    "wof:placetype":"venue"
},
  "geometry": {"coordinates":[-114.494499,51.545464],"type":"Point"}
}