{
  "type": "Feature",
  "properties": {
    "addr:full":"9001 County Rd 29 Addison ON K0E 1A0",
    "addr:housenumber":"9001;29",
    "addr:postcode":"k0e 1a0",
    "addr:street":"County Rd",
    "iso:country":"CA",
    "sg:address":"9001 County Rd 29",
    "sg:city":"Addison",
    "sg:classifiers":[
        {
            "category":"Autos & Motor Vehicles",
            "subcategory":"Fuel & Gas Station",
            "type":"Retail Goods"
        }
    ],
    "sg:phone":"+1 613 924 1692",
    "sg:postcode":"K0E 1A0",
    "sg:province":"ON",
    "sg:tags":[
        "oil"
    ],
    "wof:name":"Addison Gas & Grocery",
    "wof:placetype":"venue"
},
  "geometry": {"coordinates":[-75.88283538819999,44.660774231],"type":"Point"}
}