{
  "type": "Feature",
  "properties": {
    "addr:full":"330 Rte Begin S Sainte-Claire QC G0R 2V0",
    "addr:housenumber":"330",
    "addr:postcode":"g0r 2v0",
    "addr:street":"Rte Begin S",
    "iso:country":"CA",
    "sg:address":"330 Rte Begin S",
    "sg:city":"Sainte-Claire",
    "sg:classifiers":[
        {
            "category":"Building & Trades",
            "subcategory":"Construction",
            "type":"Services"
        }
    ],
    "sg:phone":"+1 418 883 3282",
    "sg:postcode":"G0R 2V0",
    "sg:province":"QC",
    "sg:tags":[
        "general",
        "contractor"
    ],
    "wof:name":"Debo Construction Inc",
    "wof:placetype":"venue"
},
  "geometry": {"coordinates":[-70.83049,46.592495],"type":"Point"}
}