{
  "type": "Feature",
  "properties": {
    "addr:full":"1660 Ch Du Tremblay Longueuil QC J4N 1E1",
    "addr:housenumber":"1660",
    "addr:postcode":"j4n 1e1",
    "addr:street":"Ch Du Tremblay",
    "iso:country":"CA",
    "sg:address":"1660 Ch Du Tremblay",
    "sg:city":"Longueuil",
    "sg:classifiers":[
        {
            "category":"Health Services",
            "subcategory":"Doctor",
            "type":"Services"
        }
    ],
    "sg:phone":"+1 450 468 2946",
    "sg:postcode":"J4N 1E1",
    "sg:province":"QC",
    "sg:tags":[
        "laboratory",
        "clinic"
    ],
    "wof:name":"Invascor Inc",
    "wof:placetype":"venue"
},
  "geometry": {"coordinates":[-73.45436096189999,45.5431175232],"type":"Point"}
}