{
  "type": "Feature",
  "properties": {
    "addr:full":"Air Ronge SK S0J 3G0",
    "addr:postcode":"s0j 3g0",
    "iso:country":"CA",
    "sg:city":"Air Ronge",
    "sg:classifiers":[
        {
            "category":"Autos & Motor Vehicles",
            "subcategory":"Fuel & Gas Station",
            "type":"Retail Goods"
        }
    ],
    "sg:phone":"+1 306 425 1252",
    "sg:postcode":"S0J 3G0",
    "sg:province":"SK",
    "sg:tags":[
        "oil"
    ],
    "wof:name":"CO-OP Gas Bar & Convenience",
    "wof:placetype":"venue"
},
  "geometry": {"coordinates":[-105.318794251,55.0824584961],"type":"Point"}
}