{
  "type": "Feature",
  "properties": {
    "addr:full":"2 Rue Lessard Hull QC J8Y 1M5",
    "addr:housenumber":"2",
    "addr:postcode":"j8y 1m5",
    "addr:street":"Rue Lessard",
    "iso:country":"CA",
    "sg:address":"2 Rue Lessard",
    "sg:city":"Hull",
    "sg:classifiers":[
        {
            "category":"Building & Trades",
            "subcategory":"Electrical",
            "type":"Services"
        }
    ],
    "sg:phone":"+1 819 771 2020",
    "sg:postcode":"J8Y 1M5",
    "sg:province":"QC",
    "sg:tags":[
        "electric",
        "contractor"
    ],
    "wof:name":"Brissette Electrique Ltee",
    "wof:placetype":"venue"
},
  "geometry": {"coordinates":[-75.73904400000001,45.449409],"type":"Point"}
}