{
  "type": "Feature",
  "properties": {
    "addr:full":"Levis QC G6V 6C9",
    "addr:postcode":"g6v 6c9",
    "iso:country":"CA",
    "sg:city":"Levis",
    "sg:classifiers":[
        {
            "category":"Restaurant",
            "type":"Food & Drink"
        }
    ],
    "sg:phone":"+1 418 833 8883",
    "sg:postcode":"G6V 6C9",
    "sg:province":"QC",
    "wof:name":"Welat Pizza 2 Pour 1",
    "wof:placetype":"venue"
},
  "geometry": {"coordinates":[-71.168114,46.789352],"type":"Point"}
}