{
  "type": "Feature",
  "properties": {
    "addr:full":"13 Rayborn Cres St Albert AB T8N 5C3",
    "addr:housenumber":"13",
    "addr:postcode":"t8n 5c3",
    "addr:street":"Rayborn Cres",
    "iso:country":"CA",
    "sg:address":"13 Rayborn Cres",
    "sg:city":"St Albert",
    "sg:classifiers":[
        {
            "category":"Taxi",
            "type":"Transportation"
        }
    ],
    "sg:phone":"+1 780 458 8888",
    "sg:postcode":"T8N 5C3",
    "sg:province":"AB",
    "sg:tags":[
        "taxicab"
    ],
    "wof:name":"Sturgeon Cabs Ltd",
    "wof:placetype":"venue"
},
  "geometry": {"coordinates":[-113.643272,53.622608],"type":"Point"}
}