{
  "type": "Feature",
  "properties": {
    "addr:full":"7 Allen St Weyburn SK S4H 2L5",
    "addr:housenumber":"7",
    "addr:postcode":"s4h 2l5",
    "addr:street":"Allen St",
    "iso:country":"CA",
    "sg:address":"7 Allen St",
    "sg:city":"Weyburn",
    "sg:classifiers":[
        {
            "category":"Restaurant",
            "type":"Food & Drink"
        }
    ],
    "sg:phone":"+1 306 842 4660",
    "sg:postcode":"S4H 2L5",
    "sg:province":"SK",
    "wof:name":"Mc Donald's",
    "wof:placetype":"venue"
},
  "geometry": {"coordinates":[-103.866699,49.659916],"type":"Point"}
}