{
  "type": "Feature",
  "properties": {
    "addr:full":"2455 Rue Du Neptune Quebec QC G2E 6A3",
    "addr:housenumber":"2455",
    "addr:postcode":"qc g2e 6a3",
    "addr:street":"Rue Du Neptune",
    "iso:country":"CA",
    "sg:address":"2455 Rue Du Neptune",
    "sg:city":"Quebec",
    "sg:classifiers":[
        {
            "category":"Social Services",
            "type":"Services"
        }
    ],
    "sg:phone":"+1 418 872 6485",
    "sg:postcode":"G2E 6A3",
    "sg:province":"QC",
    "sg:tags":[
        "organization",
        "welfare"
    ],
    "wof:name":"Serena Regionale DE Quebec",
    "wof:placetype":"venue"
},
  "geometry": {"coordinates":[-71.338966,46.802273],"type":"Point"}
}