{
  "type": "Feature",
  "properties": {
    "addr:full":"430 Industrial Ave Vancouver BC V6A 2P3",
    "addr:housenumber":"430",
    "addr:postcode":"v6a 2p3",
    "addr:street":"Industrial Ave",
    "iso:country":"CA",
    "sg:address":"430 Industrial Ave",
    "sg:city":"Vancouver",
    "sg:classifiers":[
        {
            "category":"Building & Trades",
            "subcategory":"Construction",
            "type":"Services"
        }
    ],
    "sg:phone":"+1 604 844 1625",
    "sg:postcode":"V6A 2P3",
    "sg:province":"BC",
    "sg:tags":[
        "motion",
        "picture",
        "set",
        "design"
    ],
    "wof:name":"Rhino Fabricators",
    "wof:placetype":"venue"
},
  "geometry": {"coordinates":[-123.09492492699999,49.2692337036],"type":"Point"}
}