{
  "type": "Feature",
  "properties": {
    "addr:full":"101 Brock St W Thunder Bay ON P7E 4H9",
    "addr:housenumber":"101",
    "addr:postcode":"p7e 4h9",
    "addr:street":"Brock St W",
    "iso:country":"CA",
    "sg:address":"101 Brock St W",
    "sg:city":"Thunder Bay",
    "sg:classifiers":[
        {
            "category":"Organizations",
            "subcategory":"Religious Organization",
            "type":"Services"
        }
    ],
    "sg:phone":"+1 807 475 4025",
    "sg:postcode":"P7E 4H9",
    "sg:province":"ON",
    "sg:tags":[
        "church"
    ],
    "wof:name":"Westmount Gospel Chapel",
    "wof:placetype":"venue"
},
  "geometry": {"coordinates":[-89.278862,48.368511],"type":"Point"}
}