{
  "type": "Feature",
  "properties": {
    "addr:full":"104 Lakeshore Rd E Mississauga ON L5G 1E3",
    "addr:housenumber":"104",
    "addr:postcode":"l5g 1e3",
    "addr:street":"Lakeshore Rd E",
    "iso:country":"CA",
    "sg:address":"104 Lakeshore Rd E",
    "sg:city":"Mississauga",
    "sg:classifiers":[
        {
            "category":"Food & Beverages",
            "subcategory":"Bakery",
            "type":"Retail Goods"
        }
    ],
    "sg:phone":"+1 905 274 2224",
    "sg:postcode":"L5G 1E3",
    "sg:province":"ON",
    "sg:tags":[
        "baker"
    ],
    "wof:name":"Marish's Boulangerie",
    "wof:placetype":"venue"
},
  "geometry": {"coordinates":[-79.583733,43.55365],"type":"Point"}
}