{
  "type": "Feature",
  "properties": {
    "addr:full":"Inverary ON K0H 1X0",
    "addr:postcode":"k0h 1x0",
    "iso:country":"CA",
    "sg:city":"Inverary",
    "sg:classifiers":[
        {
            "category":"Organizations",
            "subcategory":"Religious Organization",
            "type":"Services"
        }
    ],
    "sg:phone":"+1 613 353 1724",
    "sg:postcode":"K0H 1X0",
    "sg:province":"ON",
    "sg:tags":[
        "church"
    ],
    "wof:name":"Inverary United Church Hall",
    "wof:placetype":"venue"
},
  "geometry": {"coordinates":[-76.474358,44.386196],"type":"Point"}
}