{
  "type": "Feature",
  "properties": {
    "addr:full":"20383 Langley Bypass Langley BC V3A 5E8",
    "addr:housenumber":"20383",
    "addr:postcode":"v3a 5e8",
    "addr:street":"Langley Bypass",
    "iso:country":"CA",
    "sg:address":"20383 Langley Bypass",
    "sg:city":"Langley",
    "sg:classifiers":[
        {
            "category":"Retail",
            "subcategory":"Auto Rental",
            "type":"Services"
        }
    ],
    "sg:phone":"+1 604 533 1566",
    "sg:postcode":"V3A 5E8",
    "sg:province":"BC",
    "sg:tags":[
        "recreational",
        "leasing",
        "vehicle"
    ],
    "wof:name":"Travelhome Rv Marketplace",
    "wof:placetype":"venue"
},
  "geometry": {"coordinates":[-122.659004,49.113415],"type":"Point"}
}