{
  "type": "Feature",
  "properties": {
    "addr:full":"1550 Granville St Halifax NS B3J 1X1",
    "addr:housenumber":"1550",
    "addr:postcode":"ns b3j 1x1",
    "addr:street":"Granville St",
    "iso:country":"CA",
    "sg:address":"1550 Granville St",
    "sg:city":"Halifax",
    "sg:classifiers":[
        {
            "category":"Shopping",
            "subcategory":"Bicycles & Sporting Goods",
            "type":"Retail Goods"
        }
    ],
    "sg:phone":"+1 902 421 2667",
    "sg:postcode":"B3J 1X1",
    "sg:province":"NS",
    "sg:tags":[
        "equipment",
        "camping"
    ],
    "wof:name":"Mountain Equipment CO-OP",
    "wof:placetype":"venue"
},
  "geometry": {"coordinates":[-63.572506,44.64518],"type":"Point"}
}