{
  "type": "Feature",
  "properties": {
    "addr:full":"1516 17 Ave SW Calgary AB T2T 0C8",
    "addr:housenumber":"1516",
    "addr:postcode":"t2t 0c8",
    "addr:street":"17 Ave Sw",
    "iso:country":"CA",
    "sg:address":"1516 17 Ave SW",
    "sg:city":"Calgary",
    "sg:classifiers":[
        {
            "category":"Travel",
            "subcategory":"Travel Agent",
            "type":"Entertainment"
        }
    ],
    "sg:phone":"+1 403 266 7300",
    "sg:postcode":"T2T 0C8",
    "sg:province":"AB",
    "sg:tags":[
        "agency",
        "bureau"
    ],
    "wof:name":"Ski & Fun Travel",
    "wof:placetype":"venue"
},
  "geometry": {"coordinates":[-114.096107,51.037937],"type":"Point"}
}