{
  "type": "Feature",
  "properties": {
    "addr:full":"512 7th St Humboldt SK S0K 2A0",
    "addr:housenumber":"512",
    "addr:postcode":"s0k 2a0",
    "addr:street":"7Th St",
    "iso:country":"CA",
    "sg:address":"512 7th St",
    "sg:city":"Humboldt",
    "sg:classifiers":[
        {
            "category":"Professional",
            "subcategory":"Accounting & Tax Preparation",
            "type":"Services"
        }
    ],
    "sg:phone":"+1 306 682 5058",
    "sg:postcode":"S0K 2A0",
    "sg:province":"SK",
    "sg:tags":[
        "accountant"
    ],
    "wof:name":"Mark Seidel Holdings Ltd",
    "wof:placetype":"venue"
},
  "geometry": {"coordinates":[-105.12160491900001,52.2026405334],"type":"Point"}
}