{
  "type": "Feature",
  "properties": {
    "addr:full":"1665 Carling Ave Ottawa ON K2A 1C4",
    "addr:housenumber":"1665",
    "addr:postcode":"k2a 1c4",
    "addr:street":"Carling Ave",
    "iso:country":"CA",
    "sg:address":"1665 Carling Ave",
    "sg:city":"Ottawa",
    "sg:classifiers":[
        {
            "category":"Personal",
            "subcategory":"Beauty Salon",
            "type":"Services"
        }
    ],
    "sg:phone":"+1 613 728 1719",
    "sg:postcode":"K2A 1C4",
    "sg:province":"ON",
    "wof:name":"Guy's Hair Creations Tres Vous",
    "wof:placetype":"venue"
},
  "geometry": {"coordinates":[-75.749611,45.379574],"type":"Point"}
}