{
  "type": "Feature",
  "properties": {
    "addr:full":"3273 Moodie Dr Nepean ON K2J 4S9",
    "addr:housenumber":"3273",
    "addr:postcode":"k2j 4s9",
    "addr:street":"Moodie Dr",
    "iso:country":"CA",
    "sg:address":"3273 Moodie Dr",
    "sg:city":"Nepean",
    "sg:classifiers":[
        {
            "category":"Building & Trades",
            "subcategory":"Electrical",
            "type":"Services"
        }
    ],
    "sg:phone":"+1 613 838 5272",
    "sg:postcode":"K2J 4S9",
    "sg:province":"ON",
    "sg:tags":[
        "electric",
        "contractor"
    ],
    "wof:name":"Scott Electric",
    "wof:placetype":"venue"
},
  "geometry": {"coordinates":[-75.7884521484,45.2456588745],"type":"Point"}
}