{
  "type": "Feature",
  "properties": {
    "addr:full":"9201 Forest Grove Dr Burnaby BC V5A 4R3",
    "addr:housenumber":"9201",
    "addr:postcode":"v5a 4r3",
    "addr:street":"Forest Grove Dr",
    "iso:country":"CA",
    "sg:address":"9201 Forest Grove Dr",
    "sg:city":"Burnaby",
    "sg:classifiers":[
        {
            "category":"Real Estate",
            "subcategory":"Real Estate Agent",
            "type":"Services"
        }
    ],
    "sg:phone":"+1 604 421 4308",
    "sg:postcode":"V5A 4R3",
    "sg:province":"BC",
    "sg:tags":[
        "cooperative"
    ],
    "wof:name":"Misty Ridge Housing CO-OP",
    "wof:placetype":"venue"
},
  "geometry": {"coordinates":[-122.909729004,49.2617492676],"type":"Point"}
}