{
  "type": "Feature",
  "properties": {
    "addr:full":"573 Prometheus Pl Bowen Island BC V0N 1G0",
    "addr:housenumber":"573",
    "addr:postcode":"v0n 1g0",
    "addr:street":"Prometheus Pl",
    "iso:country":"CA",
    "sg:address":"573 Prometheus Pl",
    "sg:city":"Bowen Island",
    "sg:classifiers":[
        {
            "category":"Retail",
            "subcategory":"Veterinary Services",
            "type":"Services"
        }
    ],
    "sg:phone":"+1 604 947 9247",
    "sg:postcode":"V0N 1G0",
    "sg:province":"BC",
    "sg:tags":[
        "veterinarian"
    ],
    "wof:name":"Bowen Veterinary Svc",
    "wof:placetype":"venue"
},
  "geometry": {"coordinates":[-123.34437561,49.3803253174],"type":"Point"}
}