{
  "type": "Feature",
  "properties": {
    "addr:full":"23A Railside Rd North York ON M3A 1B2",
    "addr:housenumber":"23a",
    "addr:postcode":"m3a 1b2",
    "addr:street":"Railside Rd",
    "iso:country":"CA",
    "sg:address":"23A Railside Rd",
    "sg:city":"North York",
    "sg:classifiers":[
        {
            "category":"Building & Trades",
            "subcategory":"Construction",
            "type":"Services"
        }
    ],
    "sg:phone":"+1 416 445 7581",
    "sg:postcode":"M3A 1B2",
    "sg:province":"ON",
    "sg:tags":[
        "general",
        "contractor"
    ],
    "wof:name":"R W Hope Ltd",
    "wof:placetype":"venue"
},
  "geometry": {"coordinates":[-79.31998400000001,43.739662],"type":"Point"}
}