{
  "type": "Feature",
  "properties": {
    "addr:full":"424 18th St N Brandon MB R7A 7P3",
    "addr:housenumber":"424",
    "addr:postcode":"r7a 7p3",
    "addr:street":"18Th St N",
    "iso:country":"CA",
    "sg:address":"424 18th St N",
    "sg:city":"Brandon",
    "sg:classifiers":[
        {
            "category":"Autos & Motor Vehicles",
            "subcategory":"Automobile Sales",
            "type":"Retail Goods"
        }
    ],
    "sg:phone":"+1 204 728 4848",
    "sg:postcode":"R7A 7P3",
    "sg:province":"MB",
    "sg:tags":[
        "car",
        "dealer"
    ],
    "wof:name":"Northside Mazda",
    "wof:placetype":"venue"
},
  "geometry": {"coordinates":[-99.962082,49.85886],"type":"Point"}
}