{
  "type": "Feature",
  "properties": {
    "iso:country":"CA",
    "sg:city":"North York",
    "sg:classifiers":[
        {
            "category":"Wholesale",
            "subcategory":"Machinery & Supplies",
            "type":"Manufacturing & Wholesale Goods"
        }
    ],
    "sg:phone":"+1 416 743 9779",
    "sg:postcode":"M9L 2Y7",
    "sg:province":"ON",
    "sg:tags":[
        "salon",
        "beauty"
    ],
    "wof:name":"Lanvain Design Intl Inc",
    "wof:placetype":"venue"
},
  "geometry": {"coordinates":[-79.5560836792,43.7586784363],"type":"Point"}
}