{
  "type": "Feature",
  "properties": {
    "iso:country":"CA",
    "sg:address":"1765 Merivale Rd",
    "sg:city":"Nepean",
    "sg:classifiers":[
        {
            "category":"Arena",
            "subcategory":"Sports Club",
            "type":"Entertainment"
        }
    ],
    "sg:phone":"+1 613 224 3168",
    "sg:postcode":"K2G 1E1",
    "sg:province":"ON",
    "sg:tags":[
        "athletic",
        "fields",
        "stadium",
        "government"
    ],
    "wof:name":"Merivale Centennial",
    "wof:placetype":"venue"
},
  "geometry": {"coordinates":[-75.72737884519999,45.3408508301],"type":"Point"}
}