{
  "type": "Feature",
  "properties": {
    "addr:full":"6725 Churchill Line Watford ON N0M 2S0",
    "addr:housenumber":"6725",
    "addr:postcode":"n0m 2s0",
    "addr:street":"Churchill Line",
    "iso:country":"CA",
    "sg:address":"6725 Churchill Line",
    "sg:city":"Watford",
    "sg:classifiers":[
        {
            "category":"Building & Trades",
            "subcategory":"Equipment Rental",
            "type":"Services"
        }
    ],
    "sg:phone":"+1 519 849 6472",
    "sg:postcode":"N0M 2S0",
    "sg:province":"ON",
    "sg:tags":[
        "crane"
    ],
    "wof:name":"Shea Cranes",
    "wof:placetype":"venue"
},
  "geometry": {"coordinates":[-81.88001300000001,42.949474],"type":"Point"}
}