{
  "type": "Feature",
  "properties": {
    "addr:full":"SE 11 25 23W Gilbert Plains MB R0L 0X0",
    "addr:housenumber":"11 25 23w gilbert",
    "addr:postcode":"r0l 0x0",
    "addr:street":"Se;Plains",
    "iso:country":"CA",
    "sg:address":"SE 11 25 23W",
    "sg:city":"Gilbert Plains",
    "sg:classifiers":[
        {
            "category":"Freight",
            "type":"Transportation"
        }
    ],
    "sg:phone":"+1 204 548 2160",
    "sg:postcode":"R0L 0X0",
    "sg:province":"MB",
    "sg:tags":[
        "grain",
        "broker",
        "elevator"
    ],
    "wof:name":"Parrish & Heimbecker Ltd",
    "wof:placetype":"venue"
},
  "geometry": {"coordinates":[-100.485573,51.147266],"type":"Point"}
}