{
  "type": "Feature",
  "properties": {
    "addr:full":"101 Main St Kindersley SK S0L 1S0",
    "addr:housenumber":"101",
    "addr:postcode":"s0l 1s0",
    "addr:street":"Main St",
    "iso:country":"CA",
    "sg:address":"101 Main St",
    "sg:city":"Kindersley",
    "sg:classifiers":[
        {
            "category":"Travel",
            "subcategory":"Hotels & Motels",
            "type":"Entertainment"
        }
    ],
    "sg:phone":"+1 306 463 2633",
    "sg:postcode":"S0L 1S0",
    "sg:province":"SK",
    "wof:name":"Prairie Trail Hotel",
    "wof:placetype":"venue"
},
  "geometry": {"coordinates":[-109.161056519,51.4721603394],"type":"Point"}
}