{
  "type": "Feature",
  "properties": {
    "addr:full":"110 113 Rte N Senneterre QC J0Y 2M0",
    "addr:housenumber":"113",
    "addr:postcode":"j0y 2m0",
    "addr:street":"Rte N",
    "iso:country":"CA",
    "sg:address":"110 113 Rte N",
    "sg:city":"Senneterre",
    "sg:classifiers":[
        {
            "category":"Restaurant",
            "type":"Food & Drink"
        }
    ],
    "sg:phone":"+1 819 737 8868",
    "sg:postcode":"J0Y 2M0",
    "sg:province":"QC",
    "wof:name":"L'Arret 113",
    "wof:placetype":"venue"
},
  "geometry": {"coordinates":[-77.2596664429,48.3703155518],"type":"Point"}
}