{
  "type": "Feature",
  "properties": {
    "iso:country":"CA",
    "sg:address":"123 Rue Marois",
    "sg:city":"Saint-Etienne-DE-Lauzon",
    "sg:classifiers":[
        {
            "category":"Manufacturing",
            "subcategory":"Glass & Minerals",
            "type":"Manufacturing & Wholesale Goods"
        }
    ],
    "sg:phone":"+1 418 831 8657",
    "sg:postcode":"G6J 1L3",
    "sg:province":"QC",
    "sg:tags":[
        "lamp",
        "parts"
    ],
    "wof:name":"J & M Parent Inc",
    "wof:placetype":"venue"
},
  "geometry": {"coordinates":[-71.3066482544,46.6556777954],"type":"Point"}
}