{
  "type": "Feature",
  "properties": {
    "addr:full":"14 Legallais St Isle-Aux-Morts NL A0M 1J0",
    "addr:housenumber":"14",
    "addr:postcode":"a0m 1j0",
    "addr:street":"Legallais St",
    "iso:country":"CA",
    "sg:address":"14 Legallais St",
    "sg:city":"Isle-Aux-Morts",
    "sg:classifiers":[
        {
            "category":"Government",
            "subcategory":"Office",
            "type":"Public Place"
        }
    ],
    "sg:phone":"+1 709 698 3441",
    "sg:postcode":"A0M 1J0",
    "sg:province":"NL",
    "sg:tags":[
        "village"
    ],
    "wof:name":"Town Hall",
    "wof:placetype":"venue"
},
  "geometry": {"coordinates":[-58.9743,47.587341],"type":"Point"}
}