{
  "type": "Feature",
  "properties": {
    "iso:country":"CA",
    "sg:address":"35 Macdonell St",
    "sg:city":"Guelph",
    "sg:classifiers":[
        {
            "category":"Restaurant",
            "type":"Food & Drink"
        }
    ],
    "sg:phone":"+1 519 836 0273",
    "sg:postcode":"N1H 2Z4",
    "sg:province":"ON",
    "wof:name":"Friends in Our Kitchen",
    "wof:placetype":"venue"
},
  "geometry": {"coordinates":[-80.248878479,43.5442085266],"type":"Point"}
}