{
  "type": "Feature",
  "properties": {
    "addr:full":"42 Mctavish Ave E Brandon MB R7A 2B2",
    "addr:housenumber":"42",
    "addr:postcode":"r7a 2b2",
    "addr:street":"Mctavish Ave E",
    "iso:country":"CA",
    "sg:address":"42 Mctavish Ave E",
    "sg:city":"Brandon",
    "sg:classifiers":[
        {
            "category":"Health Services",
            "subcategory":"Health Practitioner",
            "type":"Services"
        }
    ],
    "sg:phone":"+1 204 726 1850",
    "sg:postcode":"R7A 2B2",
    "sg:province":"MB",
    "sg:tags":[
        "occupational",
        "therapist"
    ],
    "wof:name":"Brandon Private Occptnl Thrpy",
    "wof:placetype":"venue"
},
  "geometry": {"coordinates":[-99.93856,49.840454],"type":"Point"}
}