{
  "type": "Feature",
  "properties": {
    "addr:full":"208 Pemberton Ave North Vancouver BC V7P 2R5",
    "addr:housenumber":"208",
    "addr:postcode":"v7p 2r5",
    "addr:street":"Pemberton Ave",
    "iso:country":"CA",
    "sg:address":"208 Pemberton Ave",
    "sg:city":"North Vancouver",
    "sg:classifiers":[
        {
            "category":"Retail",
            "subcategory":"Auto Repair",
            "type":"Services"
        }
    ],
    "sg:phone":"+1 604 985 7646",
    "sg:postcode":"V7P 2R5",
    "sg:province":"BC",
    "sg:tags":[
        "repairing",
        "automobile",
        "radiator"
    ],
    "wof:name":"Allied Radiators & Trans",
    "wof:placetype":"venue"
},
  "geometry": {"coordinates":[-123.107674,49.318768],"type":"Point"}
}