{
  "type": "Feature",
  "properties": {
    "addr:full":"6000 Ch DE LA Cote-DE-Liesse Saint-Laurent QC H4T 1E3",
    "addr:postcode":"6000;h4t 1e3",
    "addr:street":"Ch De La Cote-De-Liesse",
    "iso:country":"CA",
    "sg:address":"6000 Ch DE LA Cote-DE-Liesse",
    "sg:city":"Saint-Laurent",
    "sg:classifiers":[
        {
            "category":"Wholesale",
            "subcategory":"Durable Goods & Equipment",
            "type":"Manufacturing & Wholesale Goods"
        }
    ],
    "sg:phone":"+1 514 738 6665",
    "sg:postcode":"H4T 1E3",
    "sg:province":"QC",
    "sg:tags":[
        "compact",
        "video",
        "disc",
        "tape",
        "record"
    ],
    "wof:name":"Videoglobe Inc",
    "wof:placetype":"venue"
},
  "geometry": {"coordinates":[-73.6863479614,45.4891586304],"type":"Point"}
}