{
  "type": "Feature",
  "properties": {
    "addr:full":"7820 Williams Rd Richmond BC V7A 1G3",
    "addr:housenumber":"7820",
    "addr:postcode":"v7a 1g3",
    "addr:street":"Williams Rd",
    "iso:country":"CA",
    "sg:address":"7820 Williams Rd",
    "sg:city":"Richmond",
    "sg:classifiers":[
        {
            "category":"Retail",
            "subcategory":"Laundry & Dry Cleaning",
            "type":"Services"
        }
    ],
    "sg:phone":"+1 604 277 5515",
    "sg:postcode":"V7A 1G3",
    "sg:province":"BC",
    "sg:tags":[
        "cleaners"
    ],
    "wof:name":"Broadmoor Busy Bee",
    "wof:placetype":"venue"
},
  "geometry": {"coordinates":[-123.137985,49.140736],"type":"Point"}
}