{
  "type": "Feature",
  "properties": {
    "iso:country":"CA",
    "sg:address":"1800 Boul Graham",
    "sg:city":"Mont-Royal",
    "sg:classifiers":[
        {
            "category":"Social Services",
            "subcategory":"Child Care",
            "type":"Services"
        }
    ],
    "sg:phone":"+1 514 731 6706",
    "sg:postcode":"H3R 1G9",
    "sg:province":"QC",
    "sg:tags":[
        "kindergarten",
        "academic",
        "school"
    ],
    "wof:name":"Royaume Des Enfants",
    "wof:placetype":"venue"
},
  "geometry": {"coordinates":[-73.6457366943,45.5144538879],"type":"Point"}
}