{
  "type": "Feature",
  "properties": {
    "addr:full":"10277 97 St NW Edmonton AB T5J 0L9",
    "addr:housenumber":"10277",
    "addr:postcode":"t5j 0l9",
    "addr:street":"97 St Nw",
    "iso:country":"CA",
    "sg:address":"10277 97 St NW",
    "sg:city":"Edmonton",
    "sg:classifiers":[
        {
            "category":"Professional",
            "subcategory":"Lawyer & Legal Services",
            "type":"Services"
        }
    ],
    "sg:phone":"+1 780 421 8245",
    "sg:postcode":"T5J 0L9",
    "sg:province":"AB",
    "sg:tags":[
        "attorney"
    ],
    "wof:name":"Gourlay, Marshall R",
    "wof:placetype":"venue"
},
  "geometry": {"coordinates":[-113.48657989500001,53.5454750061],"type":"Point"}
}