{
  "type": "Feature",
  "properties": {
    "addr:full":"3610 Boul Masson Quebec QC G1P 1K1",
    "addr:housenumber":"3610",
    "addr:postcode":"g1p 1k1",
    "addr:street":"Boul Masson",
    "iso:country":"CA",
    "sg:address":"3610 Boul Masson",
    "sg:city":"Quebec",
    "sg:classifiers":[
        {
            "category":"Social Services",
            "subcategory":"Child Care",
            "type":"Services"
        }
    ],
    "sg:phone":"+1 418 871 8749",
    "sg:postcode":"G1P 1K1",
    "sg:province":"QC",
    "wof:name":"Garderie L'Oasis Enfantin Inc",
    "wof:placetype":"venue"
},
  "geometry": {"coordinates":[-71.324394,46.813705],"type":"Point"}
}