{
  "type": "Feature",
  "properties": {
    "addr:full":"Brampton ON L6T 3T6",
    "addr:postcode":"l6t 3t6",
    "iso:country":"CA",
    "sg:city":"Brampton",
    "sg:classifiers":[
        {
            "category":"Wholesale",
            "subcategory":"Electrical",
            "type":"Manufacturing & Wholesale Goods"
        }
    ],
    "sg:phone":"+1 905 450 5111",
    "sg:postcode":"L6T 3T6",
    "sg:province":"ON",
    "sg:tags":[
        "discharge",
        "machining"
    ],
    "wof:name":"Excel Wire Erosion Canada Ltd",
    "wof:placetype":"venue"
},
  "geometry": {"coordinates":[-79.7212219238,43.7013473511],"type":"Point"}
}