{
  "type": "Feature",
  "properties": {
    "addr:full":"1144 North Augusta Rd Brockville ON K6V 5T2",
    "addr:housenumber":"1144",
    "addr:postcode":"k6v 5t2",
    "addr:street":"North Augusta Rd",
    "iso:country":"CA",
    "sg:address":"1144 North Augusta Rd",
    "sg:city":"Brockville",
    "sg:classifiers":[
        {
            "category":"Building & Trades",
            "subcategory":"Plumbing",
            "type":"Services"
        }
    ],
    "sg:phone":"+1 613 342 5115",
    "sg:postcode":"K6V 5T2",
    "sg:province":"ON",
    "sg:tags":[
        "air",
        "conditioning",
        "contractor",
        "system",
        "heating"
    ],
    "wof:name":"Petersen Mechanical Ltd",
    "wof:placetype":"venue"
},
  "geometry": {"coordinates":[-75.682411,44.620033],"type":"Point"}
}