{
  "type": "Feature",
  "properties": {
    "iso:country":"CA",
    "sg:address":"355 Huntsmill Blvd",
    "sg:city":"Scarborough",
    "sg:classifiers":[
        {
            "category":"Building & Trades",
            "subcategory":"Construction",
            "type":"Services"
        }
    ],
    "sg:phone":"+1 416 492 2835",
    "sg:postcode":"M1W 3C9",
    "sg:province":"ON",
    "sg:tags":[
        "painter"
    ],
    "wof:name":"Group of Two Painters",
    "wof:placetype":"venue"
},
  "geometry": {"coordinates":[-79.3316726685,43.816280365],"type":"Point"}
}