{
  "type": "Feature",
  "properties": {
    "addr:full":"3185 Orlando Dr Mississauga ON L4V 1C5",
    "addr:housenumber":"3185",
    "addr:postcode":"l4v 1c5",
    "addr:street":"Orlando Dr",
    "iso:country":"CA",
    "sg:address":"3185 Orlando Dr",
    "sg:city":"Mississauga",
    "sg:classifiers":[
        {
            "category":"Wholesale",
            "subcategory":"Machinery & Supplies",
            "type":"Manufacturing & Wholesale Goods"
        }
    ],
    "sg:phone":"+1 905 678 1946",
    "sg:postcode":"L4V 1C5",
    "sg:province":"ON",
    "sg:tags":[
        "equipment",
        "laundry"
    ],
    "wof:name":"Coinamatic Canada Inc",
    "wof:placetype":"venue"
},
  "geometry": {"coordinates":[-79.626396,43.698776],"type":"Point"}
}