{
  "type": "Feature",
  "properties": {
    "addr:full":"North York ON M2K 2S5",
    "addr:postcode":"m2k 2s5",
    "iso:country":"CA",
    "sg:city":"North York",
    "sg:classifiers":[
        {
            "category":"Real Estate",
            "subcategory":"Real Estate Agent",
            "type":"Services"
        }
    ],
    "sg:phone":"+1 416 498 4980",
    "sg:postcode":"M2K 2S5",
    "sg:province":"ON",
    "sg:tags":[
        "management"
    ],
    "wof:name":"Sherwood Park Management",
    "wof:placetype":"venue"
},
  "geometry": {"coordinates":[-79.366005,43.771584],"type":"Point"}
}