{
  "type": "Feature",
  "properties": {
    "iso:country":"CA",
    "sg:address":"3326 Lakeshore Rd",
    "sg:city":"Kelowna",
    "sg:classifiers":[
        {
            "category":"Restaurant",
            "type":"Food & Drink"
        }
    ],
    "sg:phone":"+1 250 763 8389",
    "sg:postcode":"V1W 3T1",
    "sg:province":"BC",
    "wof:name":"Wok Inn Restaurant",
    "wof:placetype":"venue"
},
  "geometry": {"coordinates":[-119.49140930199999,49.8573417664],"type":"Point"}
}