{
  "type": "Feature",
  "properties": {
    "addr:full":"4245 Madeley Rd. North Vancouver V7N 4E1",
    "addr:housenumber":"4245",
    "addr:postcode":"v7n 4e1",
    "addr:street":"Madeley Rd.",
    "iso:country":"CA",
    "sg:address":"4245 Madeley Rd.",
    "sg:city":"North Vancouver",
    "sg:classifiers":[
        {
            "category":"Professional",
            "subcategory":"Computer Services",
            "type":"Services"
        }
    ],
    "sg:postcode":"V7N 4E1",
    "sg:tags":[
        "vancouver",
        "events",
        "vancouver-events",
        "venues"
    ],
    "sg:website":"http://uqevents.com",
    "wof:name":"UQ Events",
    "wof:placetype":"venue"
},
  "geometry": {"coordinates":[-123.0778974,49.3484032],"type":"Point"}
}