{
  "type": "Feature",
  "properties": {
    "addr:full":"SE 11-11-3W Elie MB R0H 0H0",
    "addr:postcode":"r0h 0h0",
    "addr:street":"Se 11-11-3W Elie",
    "iso:country":"CA",
    "sg:address":"SE 11-11-3W",
    "sg:city":"Elie",
    "sg:classifiers":[
        {
            "category":"Government",
            "subcategory":"Office",
            "type":"Public Place"
        }
    ],
    "sg:phone":"+1 204 353 2616",
    "sg:postcode":"R0H 0H0",
    "sg:province":"MB",
    "wof:name":"Manitoba Maintenance Yard",
    "wof:placetype":"venue"
},
  "geometry": {"coordinates":[-97.7596740723,49.901424408],"type":"Point"}
}