{
  "type": "Feature",
  "properties": {
    "addr:full":"9204 62 Ave NW Edmonton AB T6E 0C9",
    "addr:housenumber":"9204",
    "addr:postcode":"t6e 0c9",
    "addr:street":"62 Ave Nw",
    "iso:country":"CA",
    "sg:address":"9204 62 Ave NW",
    "sg:city":"Edmonton",
    "sg:classifiers":[
        {
            "category":"Retail",
            "subcategory":"Auto Repair",
            "type":"Services"
        }
    ],
    "sg:phone":"+1 780 436 8434",
    "sg:postcode":"T6E 0C9",
    "sg:province":"AB",
    "sg:tags":[
        "fuel",
        "equipment",
        "injection"
    ],
    "wof:name":"Fuel Injection Plus",
    "wof:placetype":"venue"
},
  "geometry": {"coordinates":[-113.470298767,53.4985847473],"type":"Point"}
}