{
  "type": "Feature",
  "properties": {
    "addr:full":"Chilliwack BC V2P 2P2",
    "addr:postcode":"v2p 2p2",
    "iso:country":"CA",
    "sg:city":"Chilliwack",
    "sg:classifiers":[
        {
            "category":"Professional",
            "subcategory":"Employment Agencies",
            "type":"Services"
        }
    ],
    "sg:phone":"+1 604 702 4664",
    "sg:postcode":"V2P 2P2",
    "sg:province":"BC",
    "sg:tags":[
        "organization",
        "social",
        "opportunity",
        "welfare"
    ],
    "wof:name":"Chilliwack Employment Svc",
    "wof:placetype":"venue"
},
  "geometry": {"coordinates":[-121.951347,49.171555],"type":"Point"}
}