{
  "type": "Feature",
  "properties": {
    "addr:full":"Loretteville QC G2A 3W8",
    "addr:postcode":"g2a 3w8",
    "iso:country":"CA",
    "sg:city":"Loretteville",
    "sg:classifiers":[
        {
            "category":"Manufacturing",
            "subcategory":"Toys & Sporting Goods",
            "type":"Manufacturing & Wholesale Goods"
        }
    ],
    "sg:phone":"+1 418 842 8476",
    "sg:postcode":"G2A 3W8",
    "sg:province":"QC",
    "sg:tags":[
        "athletic"
    ],
    "wof:name":"Faber & CO",
    "wof:placetype":"venue"
},
  "geometry": {"coordinates":[-71.357956,46.861012],"type":"Point"}
}