{
  "type": "Feature",
  "properties": {
    "addr:full":"331 Main St Port Dover ON N0A 1N0",
    "addr:housenumber":"331",
    "addr:postcode":"n0a 1n0",
    "addr:street":"Main St",
    "iso:country":"CA",
    "sg:address":"331 Main St",
    "sg:city":"Port Dover",
    "sg:classifiers":[
        {
            "category":"Shopping",
            "subcategory":"Department Store",
            "type":"Retail Goods"
        }
    ],
    "sg:phone":"+1 519 583 3891",
    "sg:postcode":"N0A 1N0",
    "sg:province":"ON",
    "sg:tags":[
        "shop"
    ],
    "wof:name":"Toro Pt Dover Ltd",
    "wof:placetype":"venue"
},
  "geometry": {"coordinates":[-80.2042770386,42.7870025635],"type":"Point"}
}