{
  "type": "Feature",
  "properties": {
    "addr:full":"109 Av Dalcourt Louiseville QC J5V 1A6",
    "addr:postcode":"j5v 1a6",
    "addr:street":"109 Av Dalcourt",
    "iso:country":"CA",
    "sg:address":"109 Av Dalcourt",
    "sg:city":"Louiseville",
    "sg:classifiers":[
        {
            "category":"Manufacturing",
            "subcategory":"Glass & Minerals",
            "type":"Manufacturing & Wholesale Goods"
        }
    ],
    "sg:phone":"+1 819 228 2751",
    "sg:postcode":"J5V 1A6",
    "sg:province":"QC",
    "sg:tags":[
        "pipe",
        "drain"
    ],
    "wof:name":"Industries Atlantic Canada",
    "wof:placetype":"venue"
},
  "geometry": {"coordinates":[-72.9412994385,46.2616081238],"type":"Point"}
}