{
  "type": "Feature",
  "properties": {
    "addr:full":"Montreal QC H3B 3Y1",
    "addr:postcode":"h3b 3y1",
    "iso:country":"CA",
    "sg:city":"Montreal",
    "sg:classifiers":[
        {
            "category":"Personal",
            "subcategory":"Shoe Repair & Shine",
            "type":"Services"
        }
    ],
    "sg:phone":"+1 514 398 9057",
    "sg:postcode":"H3B 3Y1",
    "sg:province":"QC",
    "sg:tags":[
        "repairing",
        "boot"
    ],
    "wof:name":"Moneysworth & Best Maitre",
    "wof:placetype":"venue"
},
  "geometry": {"coordinates":[-73.56797,45.50182],"type":"Point"}
}