{
  "type": "Feature",
  "properties": {
    "addr:full":"2351 Royal Windsor Dr # 7 Mississauga ON L5J 4S7",
    "addr:housenumber":"2351",
    "addr:postcode":"l5j 4s7",
    "addr:street":"Royal Windsor Dr # 7",
    "iso:country":"CA",
    "sg:address":"2351 Royal Windsor Dr # 7",
    "sg:city":"Mississauga",
    "sg:classifiers":[
        {
            "category":"Retail",
            "subcategory":"Auto Repair",
            "type":"Services"
        }
    ],
    "sg:phone":"+1 905 823 8881",
    "sg:postcode":"L5J 4S7",
    "sg:province":"ON",
    "sg:tags":[
        "repairing",
        "automobile"
    ],
    "wof:name":"Smart Auto Repairs",
    "wof:placetype":"venue"
},
  "geometry": {"coordinates":[-79.637947,43.503834],"type":"Point"}
}