{
  "type": "Feature",
  "properties": {
    "addr:full":"270 Bleams Rd Kitchener ON N2C 2K6",
    "addr:housenumber":"270",
    "addr:postcode":"n2c 2k6",
    "addr:street":"Bleams Rd",
    "iso:country":"CA",
    "sg:address":"270 Bleams Rd",
    "sg:city":"Kitchener",
    "sg:classifiers":[
        {
            "category":"Restaurant",
            "type":"Food & Drink"
        }
    ],
    "sg:phone":"+1 519 895 1761",
    "sg:postcode":"N2C 2K6",
    "sg:province":"ON",
    "sg:tags":[
        "out",
        "pizza"
    ],
    "wof:name":"Little Caesars Pizza",
    "wof:placetype":"venue"
},
  "geometry": {"coordinates":[-80.4596710205,43.4106178284],"type":"Point"}
}