{
  "type": "Feature",
  "properties": {
    "addr:full":"6955 Rue Bombardier Saint-Leonard QC H1P 3G6",
    "addr:housenumber":"6955",
    "addr:postcode":"h1p 3g6",
    "addr:street":"Rue Bombardier",
    "iso:country":"CA",
    "sg:address":"6955 Rue Bombardier",
    "sg:city":"Saint-Leonard",
    "sg:classifiers":[
        {
            "category":"Retail",
            "subcategory":"Auto Repair",
            "type":"Services"
        }
    ],
    "sg:phone":"+1 514 321 3221",
    "sg:postcode":"H1P 3G6",
    "sg:province":"QC",
    "sg:tags":[
        "body",
        "automobile",
        "painting"
    ],
    "wof:name":"Principe Automobiles Inc",
    "wof:placetype":"venue"
},
  "geometry": {"coordinates":[-73.5894317627,45.6046562195],"type":"Point"}
}