{
  "type": "Feature",
  "properties": {
    "addr:full":"34 Clayson Rd North York ON M9M 2G8",
    "addr:housenumber":"34",
    "addr:postcode":"m9m 2g8",
    "addr:street":"Clayson Rd",
    "iso:country":"CA",
    "sg:address":"34 Clayson Rd",
    "sg:city":"North York",
    "sg:classifiers":[
        {
            "category":"Wholesale",
            "subcategory":"Chemicals & Plastics",
            "type":"Manufacturing & Wholesale Goods"
        }
    ],
    "sg:phone":"+1 416 741 9264",
    "sg:postcode":"M9M 2G8",
    "sg:province":"ON",
    "wof:name":"Charles Tennant & CO Ltd",
    "wof:placetype":"venue"
},
  "geometry": {"coordinates":[-79.5239028931,43.7192726135],"type":"Point"}
}