{
  "type": "Feature",
  "properties": {
    "addr:full":"70 Westchester Cres St Catharines ON L2R 3P4",
    "addr:housenumber":"70",
    "addr:postcode":"l2r 3p4",
    "addr:street":"Westchester Cres",
    "iso:country":"CA",
    "sg:address":"70 Westchester Cres",
    "sg:city":"St Catharines",
    "sg:classifiers":[
        {
            "category":"Recreation",
            "type":"Entertainment"
        }
    ],
    "sg:phone":"+1 905 682 8681",
    "sg:postcode":"L2R 3P4",
    "sg:province":"ON",
    "sg:tags":[
        "course",
        "golf"
    ],
    "wof:name":"St Cathrines Golf & Cntry Club",
    "wof:placetype":"venue"
},
  "geometry": {"coordinates":[-79.238884,43.156578],"type":"Point"}
}