{
  "type": "Feature",
  "properties": {
    "iso:country":"CA",
    "sg:address":"9709 42 Ave NW",
    "sg:city":"Edmonton",
    "sg:classifiers":[
        {
            "category":"Manufacturing",
            "subcategory":"Tools & Machinery",
            "type":"Manufacturing & Wholesale Goods"
        }
    ],
    "sg:phone":"+1 780 434 5544",
    "sg:postcode":"T6E 5P8",
    "sg:province":"AB",
    "sg:tags":[
        "field",
        "oil",
        "equipment"
    ],
    "wof:name":"Sage Fluid Control",
    "wof:placetype":"venue"
},
  "geometry": {"coordinates":[-113.479911804,53.478603363],"type":"Point"}
}