{
  "type": "Feature",
  "properties": {
    "iso:country":"CA",
    "sg:address":"Hwy 6",
    "sg:city":"Watson",
    "sg:classifiers":[
        {
            "category":"Retail",
            "subcategory":"Laundry & Dry Cleaning",
            "type":"Services"
        }
    ],
    "sg:phone":"+1 306 287 7727",
    "sg:postcode":"S0K 4V0",
    "sg:province":"SK",
    "sg:tags":[
        "cleaners",
        "rug",
        "carpet"
    ],
    "wof:name":"Columbia Carpet Care",
    "wof:placetype":"venue"
},
  "geometry": {"coordinates":[-104.530319214,52.1267738342],"type":"Point"}
}