{
  "type": "Feature",
  "properties": {
    "addr:full":"Bridge St E Campbellford ON K0L 1L0",
    "addr:postcode":"k0l 1l0",
    "addr:street":"Bridge St E Campbellford",
    "iso:country":"CA",
    "sg:address":"Bridge St E",
    "sg:city":"Campbellford",
    "sg:classifiers":[
        {
            "category":"Organizations",
            "subcategory":"Religious Organization",
            "type":"Services"
        }
    ],
    "sg:phone":"+1 705 653 3396",
    "sg:postcode":"K0L 1L0",
    "sg:province":"ON",
    "sg:tags":[
        "church"
    ],
    "wof:name":"St Andrew's Presbyterian Ch",
    "wof:placetype":"venue"
},
  "geometry": {"coordinates":[-77.79564666749999,44.3080062866],"type":"Point"}
}