{
  "type": "Feature",
  "properties": {
    "addr:full":"Winnipeg MB R2M 3K1",
    "addr:postcode":"r2m 3k1",
    "iso:country":"CA",
    "sg:city":"Winnipeg",
    "sg:classifiers":[
        {
            "category":"Banks & Credit Unions",
            "subcategory":"Bank",
            "type":"Services"
        }
    ],
    "sg:phone":"+1 204 982 3754",
    "sg:postcode":"R2M 3K1",
    "sg:province":"MB",
    "sg:tags":[
        "exchange",
        "cashing",
        "dealer",
        "broker",
        "foreign",
        "check"
    ],
    "wof:name":"Money Mart",
    "wof:placetype":"venue"
},
  "geometry": {"coordinates":[-97.1120147705,49.8354377747],"type":"Point"}
}