{
  "type": "Feature",
  "properties": {
    "addr:full":"2104 Cliffe Ave Courtenay BC V9N 2L4",
    "addr:housenumber":"2104",
    "addr:postcode":"v9n 2l4",
    "addr:street":"Cliffe Ave",
    "iso:country":"CA",
    "sg:address":"2104 Cliffe Ave",
    "sg:city":"Courtenay",
    "sg:classifiers":[
        {
            "category":"Restaurant",
            "type":"Food & Drink"
        }
    ],
    "sg:phone":"+1 250 334 3812",
    "sg:postcode":"V9N 2L4",
    "sg:province":"BC",
    "wof:name":"Thai Cafe",
    "wof:placetype":"venue"
},
  "geometry": {"coordinates":[-124.984459,49.680416],"type":"Point"}
}