{
  "type": "Feature",
  "properties": {
    "addr:full":"1 Minto St Glace Bay NS B1A 5B2",
    "addr:housenumber":"1",
    "addr:postcode":"b1a 5b2",
    "addr:street":"Minto St",
    "iso:country":"CA",
    "sg:address":"1 Minto St",
    "sg:city":"Glace Bay",
    "sg:classifiers":[
        {
            "category":"Health Services",
            "subcategory":"Nursing And Care Facility",
            "type":"Services"
        }
    ],
    "sg:phone":"+1 902 849 1605",
    "sg:postcode":"B1A 5B2",
    "sg:province":"NS",
    "sg:tags":[
        "home",
        "rest"
    ],
    "wof:name":"Jones Manor Home-Special Care",
    "wof:placetype":"venue"
},
  "geometry": {"coordinates":[-59.955288,46.197281],"type":"Point"}
}