{
  "type": "Feature",
  "properties": {
    "iso:country":"CA",
    "sg:city":"Victoria",
    "sg:classifiers":[
        {
            "category":"Professional",
            "subcategory":"Lawyer & Legal Services",
            "type":"Services"
        }
    ],
    "sg:phone":"+1 250 385 5787",
    "sg:postcode":"V8V 3K5",
    "sg:province":"BC",
    "sg:tags":[
        "attorney"
    ],
    "wof:name":"Jawl & Bundon",
    "wof:placetype":"venue"
},
  "geometry": {"coordinates":[-123.356498718,48.4235115051],"type":"Point"}
}