{
  "type": "Feature",
  "properties": {
    "iso:country":"CA",
    "sg:address":"1795 Drew Rd",
    "sg:city":"Mississauga",
    "sg:classifiers":[
        {
            "category":"Freight",
            "type":"Transportation"
        }
    ],
    "sg:phone":"+1 905 672 2990",
    "sg:postcode":"L5S 1J5",
    "sg:province":"ON",
    "sg:tags":[
        "cartage"
    ],
    "wof:name":"Lumsden & Daughters Cartage",
    "wof:placetype":"venue"
},
  "geometry": {"coordinates":[-79.67455291749999,43.6861724854],"type":"Point"}
}