{
  "type": "Feature",
  "properties": {
    "addr:full":"2267 Dundas St W Toronto ON M6R 1X6",
    "addr:housenumber":"2267",
    "addr:postcode":"m6r 1x6",
    "addr:street":"Dundas St W",
    "iso:country":"CA",
    "sg:address":"2267 Dundas St W",
    "sg:city":"Toronto",
    "sg:classifiers":[
        {
            "category":"Personal",
            "subcategory":"Beauty Salon",
            "type":"Services"
        }
    ],
    "sg:phone":"+1 416 531 1106",
    "sg:postcode":"M6R 1X6",
    "sg:province":"ON",
    "wof:name":"Adin's Hair Design & Beauty",
    "wof:placetype":"venue"
},
  "geometry": {"coordinates":[-79.4522781372,43.6549720764],"type":"Point"}
}