{
  "type": "Feature",
  "properties": {
    "addr:full":"5391 Miller Rd Duncan BC V9L 6R2",
    "addr:housenumber":"5391",
    "addr:postcode":"v9l 6r2",
    "addr:street":"Miller Rd",
    "iso:country":"CA",
    "sg:address":"5391 Miller Rd",
    "sg:city":"Duncan",
    "sg:classifiers":[
        {
            "category":"Manufacturing",
            "subcategory":"Signs",
            "type":"Manufacturing & Wholesale Goods"
        }
    ],
    "sg:phone":"+1 250 748 9086",
    "sg:postcode":"V9L 6R2",
    "sg:province":"BC",
    "wof:name":"Gerald Thompson Signs",
    "wof:placetype":"venue"
},
  "geometry": {"coordinates":[-123.707382,48.779095],"type":"Point"}
}