{
  "type": "Feature",
  "properties": {
    "addr:full":"3000 Gateby Pl Vernon BC V1T 8V8",
    "addr:housenumber":"3000",
    "addr:postcode":"v1t 8v8",
    "addr:street":"Gateby Pl",
    "iso:country":"CA",
    "sg:address":"3000 Gateby Pl",
    "sg:city":"Vernon",
    "sg:classifiers":[
        {
            "category":"Social Services",
            "subcategory":"Adult Care",
            "type":"Services"
        }
    ],
    "sg:phone":"+1 250 545 4456",
    "sg:postcode":"V1T 8V8",
    "sg:province":"BC",
    "sg:tags":[
        "community",
        "government"
    ],
    "wof:name":"Gateby Intermed Care Residence",
    "wof:placetype":"venue"
},
  "geometry": {"coordinates":[-119.28299,50.265144],"type":"Point"}
}