{
  "type": "Feature",
  "properties": {
    "iso:country":"CA",
    "sg:address":"3108 30 Ave",
    "sg:city":"Vernon",
    "sg:classifiers":[
        {
            "category":"Insurance",
            "subcategory":"Insurance Agent",
            "type":"Services"
        }
    ],
    "sg:phone":"+1 250 558 5431",
    "sg:postcode":"V1T 2C2",
    "sg:province":"BC",
    "sg:tags":[
        "investment"
    ],
    "wof:name":"Canaccord Capital Corp",
    "wof:placetype":"venue"
},
  "geometry": {"coordinates":[-119.272506714,50.2636222839],"type":"Point"}
}