{
  "type": "Feature",
  "properties": {
    "addr:full":"225 Rue DE Liege O # 100 Montreal QC H2P 1H4",
    "addr:housenumber":"225",
    "addr:postcode":"h2p 1h4",
    "addr:street":"Rue De Liege O # 100",
    "iso:country":"CA",
    "sg:address":"225 Rue DE Liege O # 100",
    "sg:city":"Montreal",
    "sg:classifiers":[
        {
            "category":"Wholesale",
            "subcategory":"Apparel",
            "type":"Manufacturing & Wholesale Goods"
        }
    ],
    "sg:phone":"+1 514 277 7777",
    "sg:postcode":"H2P 1H4",
    "sg:province":"QC",
    "sg:tags":[
        "clothing"
    ],
    "wof:name":"Campea Bellotti Soccer Inc",
    "wof:placetype":"venue"
},
  "geometry": {"coordinates":[-73.63652,45.542755],"type":"Point"}
}