{
  "type": "Feature",
  "properties": {
    "addr:full":"Vancouver BC V6E 2P4",
    "addr:postcode":"v6e 2p4",
    "iso:country":"CA",
    "sg:city":"Vancouver",
    "sg:classifiers":[
        {
            "category":"Professional",
            "subcategory":"Business Services",
            "type":"Services"
        }
    ],
    "sg:phone":"+1 604 688 3721",
    "sg:postcode":"V6E 2P4",
    "sg:province":"BC",
    "sg:tags":[
        "event"
    ],
    "wof:name":"Events One Management",
    "wof:placetype":"venue"
},
  "geometry": {"coordinates":[-123.12252807599999,49.2883682251],"type":"Point"}
}