{
  "type": "Feature",
  "properties": {
    "addr:full":"13 Parnell Rd St Catharines ON L2N 2W1",
    "addr:housenumber":"13",
    "addr:postcode":"l2n 2w1",
    "addr:street":"Parnell Rd",
    "iso:country":"CA",
    "sg:address":"13 Parnell Rd",
    "sg:city":"St Catharines",
    "sg:classifiers":[
        {
            "category":"Building & Trades",
            "subcategory":"Construction",
            "type":"Services"
        }
    ],
    "sg:phone":"+1 905 937 6932",
    "sg:postcode":"L2N 2W1",
    "sg:province":"ON",
    "sg:tags":[
        "home",
        "improvement"
    ],
    "wof:name":"Blue Spruce Homes",
    "wof:placetype":"venue"
},
  "geometry": {"coordinates":[-79.2402648926,43.2043800354],"type":"Point"}
}