{
  "type": "Feature",
  "properties": {
    "addr:full":"1219 14 Ave SW Calgary AB T3C 0W1",
    "addr:housenumber":"1219",
    "addr:postcode":"t3c 0w1",
    "addr:street":"14 Ave Sw",
    "iso:country":"CA",
    "sg:address":"1219 14 Ave SW",
    "sg:city":"Calgary",
    "sg:classifiers":[
        {
            "category":"Banks & Credit Unions",
            "subcategory":"Investment Brokerage",
            "type":"Services"
        }
    ],
    "sg:phone":"+1 403 543 5005",
    "sg:postcode":"T3C 0W1",
    "sg:province":"AB",
    "sg:tags":[
        "consultant",
        "planning",
        "financial"
    ],
    "wof:name":"Compass Financial Planning Svc",
    "wof:placetype":"venue"
},
  "geometry": {"coordinates":[-114.08966100000001,51.040134],"type":"Point"}
}