{
  "type": "Feature",
  "properties": {
    "addr:full":"PO Box 254 Nampa AB T0H 2R0",
    "addr:housenumber":"po",
    "addr:postcode":"t0h 2r0",
    "addr:street":"Box 254",
    "iso:country":"CA",
    "sg:address":"PO Box 254",
    "sg:city":"Nampa",
    "sg:classifiers":[
        {
            "category":"Arena",
            "subcategory":"Sports Club",
            "type":"Entertainment"
        }
    ],
    "sg:phone":"+1 780 322 3808",
    "sg:postcode":"T0H 2R0",
    "sg:province":"AB",
    "sg:tags":[
        "athletic",
        "fields",
        "stadium"
    ],
    "wof:name":"Nampa & District Agri Society",
    "wof:placetype":"venue"
},
  "geometry": {"coordinates":[-117.134315,56.038799],"type":"Point"}
}