{
  "type": "Feature",
  "properties": {
    "addr:full":"8845 Rue Pascal-Gagnon Saint-Leonard QC H1P 1Z4",
    "addr:housenumber":"8845",
    "addr:postcode":"h1p 1z4",
    "addr:street":"Rue Pascal-Gagnon",
    "iso:country":"CA",
    "sg:address":"8845 Rue Pascal-Gagnon",
    "sg:city":"Saint-Leonard",
    "sg:classifiers":[
        {
            "category":"Wholesale",
            "subcategory":"Construction Materials",
            "type":"Manufacturing & Wholesale Goods"
        }
    ],
    "sg:phone":"+1 514 324 0002",
    "sg:postcode":"H1P 1Z4",
    "sg:province":"QC",
    "sg:tags":[
        "tile"
    ],
    "wof:name":"Ceramiques Royal Ltee",
    "wof:placetype":"venue"
},
  "geometry": {"coordinates":[-73.5923919678,45.6041755676],"type":"Point"}
}