{
  "type": "Feature",
  "properties": {
    "addr:full":"2001 Alberta Ave # B Saskatoon SK S7K 1S2",
    "addr:housenumber":"2001",
    "addr:postcode":"s7k 1s2",
    "addr:street":"Alberta Ave # B",
    "iso:country":"CA",
    "sg:address":"2001 Alberta Ave # B",
    "sg:city":"Saskatoon",
    "sg:classifiers":[
        {
            "category":"Wholesale",
            "subcategory":"Sporting Goods",
            "type":"Manufacturing & Wholesale Goods"
        }
    ],
    "sg:phone":"+1 306 374 2727",
    "sg:postcode":"S7K 1S2",
    "sg:province":"SK",
    "sg:tags":[
        "tackle",
        "fishing"
    ],
    "wof:name":"Morse Distributors",
    "wof:placetype":"venue"
},
  "geometry": {"coordinates":[-106.667724609,52.1565551758],"type":"Point"}
}