{
  "type": "Feature",
  "properties": {
    "addr:full":"1494 Fairfield Rd Victoria BC V8S 1E8",
    "addr:housenumber":"1494",
    "addr:postcode":"v8s 1e8",
    "addr:street":"Fairfield Rd",
    "iso:country":"CA",
    "sg:address":"1494 Fairfield Rd",
    "sg:city":"Victoria",
    "sg:classifiers":[
        {
            "category":"Health Services",
            "subcategory":"Doctor",
            "type":"Services"
        }
    ],
    "sg:phone":"+1 250 598 5158",
    "sg:postcode":"V8S 1E8",
    "sg:province":"BC",
    "sg:tags":[
        "physician",
        "surgeon"
    ],
    "wof:name":"Nuttall, Richard MD",
    "wof:placetype":"venue"
},
  "geometry": {"coordinates":[-123.341560364,48.4120140076],"type":"Point"}
}