{
  "type": "Feature",
  "properties": {
    "addr:full":"42 Byng Ave Kapuskasing ON P5N 1W4",
    "addr:housenumber":"42",
    "addr:postcode":"p5n 1w4",
    "addr:street":"Byng Ave",
    "iso:country":"CA",
    "sg:address":"42 Byng Ave",
    "sg:city":"Kapuskasing",
    "sg:classifiers":[
        {
            "category":"Personal",
            "subcategory":"Beauty Salon",
            "type":"Services"
        }
    ],
    "sg:phone":"+1 705 335 2565",
    "sg:postcode":"P5N 1W4",
    "sg:province":"ON",
    "wof:name":"Studio Lise",
    "wof:placetype":"venue"
},
  "geometry": {"coordinates":[-82.4216995239,49.4182701111],"type":"Point"}
}