{
  "type": "Feature",
  "properties": {
    "iso:country":"CA",
    "sg:address":"15261 Hwy 2",
    "sg:city":"Ingleside",
    "sg:classifiers":[
        {
            "category":"Travel",
            "subcategory":"Hotels & Motels",
            "type":"Entertainment"
        }
    ],
    "sg:phone":"+1 613 537 2642",
    "sg:postcode":"K0C 1M0",
    "sg:province":"ON",
    "wof:name":"Bavarian Bierstube",
    "wof:placetype":"venue"
},
  "geometry": {"coordinates":[-74.9833984375,44.9963912964],"type":"Point"}
}