{
  "type": "Feature",
  "properties": {
    "iso:country":"CA",
    "sg:city":"Trois-Rivieres",
    "sg:classifiers":[
        {
            "category":"Food & Beverages",
            "subcategory":"Groceries & Convenience Stores",
            "type":"Retail Goods"
        }
    ],
    "sg:phone":"+1 819 373 7221",
    "sg:postcode":"G8Z 2C8",
    "sg:province":"QC",
    "wof:name":"Depanneur Plus",
    "wof:placetype":"venue"
},
  "geometry": {"coordinates":[-72.5596694946,46.3410835266],"type":"Point"}
}