{
  "type": "Feature",
  "properties": {
    "addr:full":"1317 Exmouth St Sarnia ON N7S 3Y1",
    "addr:housenumber":"1317",
    "addr:postcode":"n7s 3y1",
    "addr:street":"Exmouth St",
    "iso:country":"CA",
    "sg:address":"1317 Exmouth St",
    "sg:city":"Sarnia",
    "sg:classifiers":[
        {
            "category":"Health Services",
            "subcategory":"Doctor",
            "type":"Services"
        }
    ],
    "sg:phone":"+1 519 542 1447",
    "sg:postcode":"N7S 3Y1",
    "sg:province":"ON",
    "sg:tags":[
        "dentist"
    ],
    "wof:name":"Orthotech Health Svc Inc",
    "wof:placetype":"venue"
},
  "geometry": {"coordinates":[-82.35732299999999,42.984398],"type":"Point"}
}