{
  "type": "Feature",
  "properties": {
    "addr:full":"1 Regency Dr Dartmouth NS B2Y 1Z7",
    "addr:housenumber":"1",
    "addr:postcode":"b2y 1z7",
    "addr:street":"Regency Dr",
    "iso:country":"CA",
    "sg:address":"1 Regency Dr",
    "sg:city":"Dartmouth",
    "sg:classifiers":[
        {
            "category":"Social Services",
            "subcategory":"Child Care",
            "type":"Services"
        }
    ],
    "sg:phone":"+1 902 466 7714",
    "sg:postcode":"B2Y 1Z7",
    "sg:province":"NS",
    "wof:name":"Southdale Day Care Ctr",
    "wof:placetype":"venue"
},
  "geometry": {"coordinates":[-63.5423164368,44.6663093567],"type":"Point"}
}