{
  "type": "Feature",
  "properties": {
    "addr:full":"207 King Ave Bathurst NB E2A 1N9",
    "addr:housenumber":"207",
    "addr:postcode":"e2a 1n9",
    "addr:street":"King Ave",
    "iso:country":"CA",
    "sg:address":"207 King Ave",
    "sg:city":"Bathurst",
    "sg:classifiers":[
        {
            "category":"Shopping",
            "type":"Retail Goods"
        }
    ],
    "sg:phone":"+1 506 548 3607",
    "sg:postcode":"E2A 1N9",
    "sg:province":"NB",
    "sg:tags":[
        "pet",
        "shop"
    ],
    "wof:name":"Bird's Eye View",
    "wof:placetype":"venue"
},
  "geometry": {"coordinates":[-65.653542,47.620586],"type":"Point"}
}