{
  "type": "Feature",
  "properties": {
    "addr:full":"22 Court St S Thunder Bay ON P7B 2W3",
    "addr:housenumber":"22",
    "addr:postcode":"p7b 2w3",
    "addr:street":"Court St S Thunder",
    "iso:country":"CA",
    "sg:address":"22 Court St S",
    "sg:city":"Thunder Bay",
    "sg:classifiers":[
        {
            "category":"Shopping",
            "subcategory":"Clothing, Apparel, & Fashions",
            "type":"Retail Goods"
        }
    ],
    "sg:phone":"+1 807 345 8412",
    "sg:postcode":"P7B 2W3",
    "sg:province":"ON",
    "sg:tags":[
        "tailor"
    ],
    "wof:name":"Russell Tailors",
    "wof:placetype":"venue"
},
  "geometry": {"coordinates":[-89.222549,48.435001],"type":"Point"}
}