{
  "type": "Feature",
  "properties": {
    "addr:full":"8730 Boul Provencher Saint-Leonard QC H1R 3N7",
    "addr:housenumber":"8730",
    "addr:postcode":"h1r 3n7",
    "addr:street":"Boul Provencher",
    "iso:country":"CA",
    "sg:address":"8730 Boul Provencher",
    "sg:city":"Saint-Leonard",
    "sg:classifiers":[
        {
            "category":"Banks & Credit Unions",
            "subcategory":"Bank",
            "type":"Services"
        }
    ],
    "sg:phone":"+1 514 394 5555",
    "sg:postcode":"H1R 3N7",
    "sg:province":"QC",
    "wof:name":"Banque National Du Canada",
    "wof:placetype":"venue"
},
  "geometry": {"coordinates":[-73.610435,45.58094],"type":"Point"}
}