{
  "type": "Feature",
  "properties": {
    "iso:country":"CA",
    "sg:address":"26 Rue Isabelle",
    "sg:city":"Vaudreuil-Dorion",
    "sg:classifiers":[
        {
            "category":"Real Estate",
            "subcategory":"Architect",
            "type":"Services"
        }
    ],
    "sg:phone":"+1 450 424 8880",
    "sg:postcode":"J7V 8B2",
    "sg:province":"QC",
    "wof:name":"Deschamps, Marc",
    "wof:placetype":"venue"
},
  "geometry": {"coordinates":[-74.0384597778,45.3974342346],"type":"Point"}
}