{
  "type": "Feature",
  "properties": {
    "addr:full":"16 Steel St Welland ON L3B 3L9",
    "addr:housenumber":"16",
    "addr:postcode":"l3b 3l9",
    "addr:street":"Steel St",
    "iso:country":"CA",
    "sg:address":"16 Steel St",
    "sg:city":"Welland",
    "sg:classifiers":[
        {
            "category":"Organizations",
            "subcategory":"Labor Organization",
            "type":"Services"
        }
    ],
    "sg:phone":"+1 905 735 5340",
    "sg:postcode":"L3B 3L9",
    "sg:province":"ON",
    "wof:name":"Caw",
    "wof:placetype":"venue"
},
  "geometry": {"coordinates":[-79.252472,42.975533],"type":"Point"}
}