{
  "type": "Feature",
  "properties": {
    "addr:full":"987 Gordon St Guelph ON N1G 4W3",
    "addr:housenumber":"987",
    "addr:postcode":"n1g 4w3",
    "addr:street":"Gordon St",
    "iso:country":"CA",
    "sg:address":"987 Gordon St",
    "sg:city":"Guelph",
    "sg:classifiers":[
        {
            "category":"Banks & Credit Unions",
            "subcategory":"Bank",
            "type":"Services"
        }
    ],
    "sg:phone":"+1 519 821 5610",
    "sg:postcode":"N1G 4W3",
    "sg:province":"ON",
    "wof:name":"Royal Bank Financial Group",
    "wof:placetype":"venue"
},
  "geometry": {"coordinates":[-80.211517,43.521351],"type":"Point"}
}