{
  "type": "Feature",
  "properties": {
    "iso:country":"CA",
    "sg:address":"3475 Albert St",
    "sg:city":"Regina",
    "sg:classifiers":[
        {
            "category":"Government",
            "subcategory":"Office",
            "type":"Public Place"
        }
    ],
    "sg:phone":"+1 306 787 9693",
    "sg:postcode":"S4S 6X6",
    "sg:province":"SK",
    "wof:name":"Sask Cafeterias",
    "wof:placetype":"venue"
},
  "geometry": {"coordinates":[-104.617889,50.423927],"type":"Point"}
}