{
  "type": "Feature",
  "properties": {
    "addr:full":"12903 54 St NW Edmonton AB T5A 5E5",
    "addr:housenumber":"12903",
    "addr:postcode":"t5a 5e5",
    "addr:street":"54 St Nw",
    "iso:country":"CA",
    "sg:address":"12903 54 St NW",
    "sg:city":"Edmonton",
    "sg:classifiers":[
        {
            "category":"Building & Trades",
            "subcategory":"Construction",
            "type":"Services"
        }
    ],
    "sg:phone":"+1 780 476 0661",
    "sg:postcode":"T5A 5E5",
    "sg:province":"AB",
    "sg:tags":[
        "resurfacing",
        "material",
        "laying",
        "refinishing",
        "floor"
    ],
    "wof:name":"Vinton Centre Carpets",
    "wof:placetype":"venue"
},
  "geometry": {"coordinates":[-113.424385,53.587852],"type":"Point"}
}