{
  "type": "Feature",
  "properties": {
    "addr:full":"8192 Government Rd Burnaby BC V5A 2E2",
    "addr:housenumber":"8192",
    "addr:postcode":"v5a 2e2",
    "addr:street":"Rd",
    "iso:country":"CA",
    "sg:address":"8192 Government Rd",
    "sg:city":"Burnaby",
    "sg:classifiers":[
        {
            "category":"Building & Trades",
            "subcategory":"Electrical",
            "type":"Services"
        }
    ],
    "sg:phone":"+1 604 421 7811",
    "sg:postcode":"V5A 2E2",
    "sg:province":"BC",
    "sg:tags":[
        "electric",
        "contractor"
    ],
    "wof:name":"Marathon Electric Ltd",
    "wof:placetype":"venue"
},
  "geometry": {"coordinates":[-122.926795959,49.250629425],"type":"Point"}
}