{
  "type": "Feature",
  "properties": {
    "addr:full":"2580 Gilmore Ave Burnaby BC V5C 4T5",
    "addr:housenumber":"2580",
    "addr:postcode":"v5c 4t5",
    "addr:street":"Gilmore Ave",
    "iso:country":"CA",
    "sg:address":"2580 Gilmore Ave",
    "sg:city":"Burnaby",
    "sg:classifiers":[
        {
            "category":"Wholesale",
            "subcategory":"Construction Materials",
            "type":"Manufacturing & Wholesale Goods"
        }
    ],
    "sg:phone":"+1 604 437 1111",
    "sg:postcode":"V5C 4T5",
    "sg:province":"BC",
    "sg:tags":[
        "lumber"
    ],
    "wof:name":"Dick's Lumber & Bldg Supls Ltd",
    "wof:placetype":"venue"
},
  "geometry": {"coordinates":[-123.014068603,49.2611656189],"type":"Point"}
}