{
  "type": "Feature",
  "properties": {
    "addr:full":"298 Boul Armand-Theriault Riviere-Du-Loup QC G5R 4C2",
    "addr:housenumber":"298",
    "addr:postcode":"g5r 4c2",
    "addr:street":"Boul Armand-Theriault Riviere-Du-Loup",
    "iso:country":"CA",
    "sg:address":"298 Boul Armand-Theriault",
    "sg:city":"Riviere-Du-Loup",
    "sg:classifiers":[
        {
            "category":"Shopping",
            "subcategory":"Books",
            "type":"Retail Goods"
        }
    ],
    "sg:phone":"+1 418 862 3561",
    "sg:postcode":"G5R 4C2",
    "sg:province":"QC",
    "sg:tags":[
        "dealer"
    ],
    "wof:name":"Librairie Du Portage Enr",
    "wof:placetype":"venue"
},
  "geometry": {"coordinates":[-69.5459365845,47.8246498108],"type":"Point"}
}