{
  "type": "Feature",
  "properties": {
    "addr:full":"14 Mill St Vankleek Hill ON K0B 1R0",
    "addr:housenumber":"14",
    "addr:postcode":"k0b 1r0",
    "addr:street":"Mill St",
    "iso:country":"CA",
    "sg:address":"14 Mill St",
    "sg:city":"Vankleek Hill",
    "sg:classifiers":[
        {
            "category":"Organizations",
            "subcategory":"Religious Organization",
            "type":"Services"
        }
    ],
    "sg:phone":"+1 613 678 2436",
    "sg:postcode":"K0B 1R0",
    "sg:province":"ON",
    "sg:tags":[
        "church"
    ],
    "wof:name":"Trinity United Church",
    "wof:placetype":"venue"
},
  "geometry": {"coordinates":[-74.653847,45.518116],"type":"Point"}
}