{
  "type": "Feature",
  "properties": {
    "addr:full":"Rosseau ON P0C 1J0",
    "addr:postcode":"p0c 1j0",
    "iso:country":"CA",
    "sg:city":"Rosseau",
    "sg:classifiers":[
        {
            "category":"Building & Trades",
            "subcategory":"Construction",
            "type":"Services"
        }
    ],
    "sg:phone":"+1 705 732 4289",
    "sg:postcode":"P0C 1J0",
    "sg:province":"ON",
    "sg:tags":[
        "general",
        "contractor"
    ],
    "wof:name":"Ken Bissonette Excavating Inc",
    "wof:placetype":"venue"
},
  "geometry": {"coordinates":[-79.645393,45.259136],"type":"Point"}
}