{
  "type": "Feature",
  "properties": {
    "addr:full":"Powell River BC V8A 2B6",
    "addr:postcode":"v8a 2b6",
    "iso:country":"CA",
    "sg:city":"Powell River",
    "sg:classifiers":[
        {
            "category":"Real Estate",
            "subcategory":"Real Estate Operator",
            "type":"Services"
        }
    ],
    "sg:phone":"+1 604 485 7411",
    "sg:postcode":"V8A 2B6",
    "sg:province":"BC",
    "sg:tags":[
        "apartment"
    ],
    "wof:name":"Texada Apartments Ltd",
    "wof:placetype":"venue"
},
  "geometry": {"coordinates":[-124.52574199999999,49.844444],"type":"Point"}
}