{
  "type": "Feature",
  "properties": {
    "addr:full":"526 Av Georges-V Montreal-Est QC H1L 3T6",
    "addr:postcode":"h1l 3t6",
    "addr:street":"526 Av Georges-V",
    "iso:country":"CA",
    "sg:address":"526 Av Georges-V",
    "sg:city":"Montreal-Est",
    "sg:classifiers":[
        {
            "category":"Shopping",
            "subcategory":"Pharmacy",
            "type":"Retail Goods"
        }
    ],
    "sg:phone":"+1 514 351 8330",
    "sg:postcode":"H1L 3T6",
    "sg:province":"QC",
    "wof:name":"Pharmacie Lan Nguyen",
    "wof:placetype":"venue"
},
  "geometry": {"coordinates":[-73.510735,45.611366],"type":"Point"}
}