{
  "type": "Feature",
  "properties": {
    "addr:full":"1000 Boul Decarie Montreal QC H4A 3H9",
    "addr:housenumber":"1000",
    "addr:postcode":"h4a 3h9",
    "addr:street":"Boul Decarie",
    "iso:country":"CA",
    "sg:address":"1000 Boul Decarie",
    "sg:city":"Montreal",
    "sg:classifiers":[
        {
            "category":"Retail",
            "subcategory":"Auto Repair",
            "type":"Services"
        }
    ],
    "sg:phone":"+1 514 484 7011",
    "sg:postcode":"H4A 3H9",
    "sg:province":"QC",
    "sg:tags":[
        "repairing",
        "automobile"
    ],
    "wof:name":"S A Repairs Ltd",
    "wof:placetype":"venue"
},
  "geometry": {"coordinates":[-73.60289,45.471493],"type":"Point"}
}