{
  "type": "Feature",
  "properties": {
    "addr:full":"56 Stanley St Ayr ON N0B 1E0",
    "addr:housenumber":"56",
    "addr:postcode":"n0b 1e0",
    "addr:street":"Stanley St",
    "iso:country":"CA",
    "sg:address":"56 Stanley St",
    "sg:city":"Ayr",
    "sg:classifiers":[
        {
            "category":"Shopping",
            "subcategory":"Florist",
            "type":"Retail Goods"
        }
    ],
    "sg:phone":"+1 519 632 7691",
    "sg:postcode":"N0B 1E0",
    "sg:province":"ON",
    "wof:name":"Mc Tayrn Flowers & Gifts",
    "wof:placetype":"venue"
},
  "geometry": {"coordinates":[-80.450188,43.285671],"type":"Point"}
}