{
  "type": "Feature",
  "properties": {
    "iso:country":"CA",
    "sg:address":"1191 Gordon Dr",
    "sg:city":"Kelowna",
    "sg:classifiers":[
        {
            "category":"Freight",
            "type":"Transportation"
        }
    ],
    "sg:phone":"+1 250 861 8623",
    "sg:postcode":"V1Y 3E5",
    "sg:province":"BC",
    "sg:tags":[
        "courier"
    ],
    "wof:name":"Medi-Trans Svc Ltd",
    "wof:placetype":"venue"
},
  "geometry": {"coordinates":[-119.476806641,49.8930702209],"type":"Point"}
}