{
  "type": "Feature",
  "properties": {
    "addr:full":"37 Shaw Rd Miramichi NB E1V 6K9",
    "addr:housenumber":"37",
    "addr:postcode":"e1v 6k9",
    "addr:street":"Shaw Rd",
    "iso:country":"CA",
    "sg:address":"37 Shaw Rd",
    "sg:city":"Miramichi",
    "sg:classifiers":[
        {
            "category":"Professional",
            "subcategory":"Management & Consulting",
            "type":"Services"
        }
    ],
    "sg:phone":"+1 506 627 2722",
    "sg:postcode":"E1V 6K9",
    "sg:province":"NB",
    "sg:tags":[
        "consultant",
        "educational"
    ],
    "wof:name":"Aspen Communications Corp",
    "wof:placetype":"venue"
},
  "geometry": {"coordinates":[-65.49955,47.06514],"type":"Point"}
}