{
  "type": "Feature",
  "properties": {
    "addr:full":"512 Mcnicoll Ave North York ON M2H 2E1",
    "addr:housenumber":"512",
    "addr:postcode":"m2h 2e1",
    "addr:street":"Mcnicoll Ave",
    "iso:country":"CA",
    "sg:address":"512 Mcnicoll Ave",
    "sg:city":"North York",
    "sg:classifiers":[
        {
            "category":"Professional",
            "type":"Services"
        }
    ],
    "sg:phone":"+1 416 499 4531",
    "sg:postcode":"M2H 2E1",
    "sg:province":"ON",
    "sg:tags":[
        "clocks",
        "establishment"
    ],
    "wof:name":"Murray Clock Craft Ltd",
    "wof:placetype":"venue"
},
  "geometry": {"coordinates":[-79.340118,43.803902],"type":"Point"}
}