{
  "type": "Feature",
  "properties": {
    "addr:full":"1002 8 St Cold Lake AB T9M 1H7",
    "addr:housenumber":"1002 8",
    "addr:postcode":"t9m 1h7",
    "addr:street":"St",
    "iso:country":"CA",
    "sg:address":"1002 8 St",
    "sg:city":"Cold Lake",
    "sg:classifiers":[
        {
            "category":"Professional",
            "subcategory":"Business Services",
            "type":"Services"
        }
    ],
    "sg:phone":"+1 780 639 3030",
    "sg:postcode":"T9M 1H7",
    "sg:province":"AB",
    "sg:tags":[
        "reservation",
        "motel",
        "hotel"
    ],
    "wof:name":"Frontier Motel",
    "wof:placetype":"venue"
},
  "geometry": {"coordinates":[-110.169464,54.462387],"type":"Point"}
}