{
  "type": "Feature",
  "properties": {
    "addr:full":"1170 Weston Rd # A York ON M6M 4P4",
    "addr:housenumber":"1170",
    "addr:postcode":"m6m 4p4",
    "addr:street":"Weston Rd # A",
    "iso:country":"CA",
    "sg:address":"1170 Weston Rd # A",
    "sg:city":"York",
    "sg:classifiers":[
        {
            "category":"Food & Beverages",
            "subcategory":"Groceries & Convenience Stores",
            "type":"Retail Goods"
        }
    ],
    "sg:phone":"+1 416 248 5308",
    "sg:postcode":"M6M 4P4",
    "sg:province":"ON",
    "wof:name":"S J Food Mart",
    "wof:placetype":"venue"
},
  "geometry": {"coordinates":[-79.490623,43.687263],"type":"Point"}
}