{
  "type": "Feature",
  "properties": {
    "addr:full":"Sorel-Tracy QC J3P 1E2",
    "addr:postcode":"j3p 1e2",
    "iso:country":"CA",
    "sg:city":"Sorel-Tracy",
    "sg:classifiers":[
        {
            "category":"Health Services",
            "subcategory":"Health Practitioner",
            "type":"Services"
        }
    ],
    "sg:phone":"+1 450 742 7321",
    "sg:postcode":"J3P 1E2",
    "sg:province":"QC",
    "sg:tags":[
        "psychologist"
    ],
    "wof:name":"Au Centre DE Soi",
    "wof:placetype":"venue"
},
  "geometry": {"coordinates":[-73.106628,46.046078],"type":"Point"}
}