{
  "type": "Feature",
  "properties": {
    "iso:country":"CA",
    "sg:address":"1800 Rue Michelin",
    "sg:city":"Laval",
    "sg:classifiers":[
        {
            "category":"Wholesale",
            "subcategory":"Chemicals & Plastics",
            "type":"Manufacturing & Wholesale Goods"
        }
    ],
    "sg:phone":"+1 450 682 4044",
    "sg:postcode":"H7L 4R3",
    "sg:province":"QC",
    "wof:name":"Pachem Distribution Inc",
    "wof:placetype":"venue"
},
  "geometry": {"coordinates":[-73.752052,45.587196],"type":"Point"}
}