{
  "type": "Feature",
  "properties": {
    "iso:country":"CA",
    "sg:address":"161 Walnut Ave",
    "sg:city":"Toronto",
    "sg:classifiers":[
        {
            "category":"Building & Trades",
            "subcategory":"Construction",
            "type":"Services"
        }
    ],
    "sg:phone":"+1 416 504 7707",
    "sg:postcode":"M6J 3W3",
    "sg:province":"ON",
    "sg:tags":[
        "designer"
    ],
    "wof:name":"Brian Foster Ltd",
    "wof:placetype":"venue"
},
  "geometry": {"coordinates":[-79.409828186,43.6441650391],"type":"Point"}
}