{
  "type": "Feature",
  "properties": {
    "addr:full":"40 Jutland Rd Etobicoke ON M8Z 2G9",
    "addr:housenumber":"40",
    "addr:postcode":"m8z 2g9",
    "addr:street":"Jutland Rd",
    "iso:country":"CA",
    "sg:address":"40 Jutland Rd",
    "sg:city":"Etobicoke",
    "sg:classifiers":[
        {
            "category":"Manufacturing",
            "subcategory":"Tools & Machinery",
            "type":"Manufacturing & Wholesale Goods"
        }
    ],
    "sg:phone":"+1 416 255 1321",
    "sg:postcode":"M8Z 2G9",
    "sg:province":"ON",
    "sg:tags":[
        "machine",
        "shop"
    ],
    "wof:name":"Sirco Machinery CO Ltd",
    "wof:placetype":"venue"
},
  "geometry": {"coordinates":[-79.525299,43.627262],"type":"Point"}
}