{
  "type": "Feature",
  "properties": {
    "iso:country":"CA",
    "sg:address":"1310 Rue Galt O",
    "sg:city":"Sherbrooke",
    "sg:classifiers":[
        {
            "category":"Organizations",
            "subcategory":"Religious Organization",
            "type":"Services"
        }
    ],
    "sg:phone":"+1 819 822 3083",
    "sg:postcode":"J1H 2A7",
    "sg:province":"QC",
    "sg:tags":[
        "house",
        "retreat"
    ],
    "wof:name":"Terrasses Belle-Vue Enr",
    "wof:placetype":"venue"
},
  "geometry": {"coordinates":[-71.908646,45.387657],"type":"Point"}
}