{
  "type": "Feature",
  "properties": {
    "addr:full":"1600 Theatre Rd Cranbrook BC V1C 7G1",
    "addr:housenumber":"1600",
    "addr:postcode":"bc v1c 7g1",
    "addr:street":"Theatre Rd",
    "iso:country":"CA",
    "sg:address":"1600 Theatre Rd",
    "sg:city":"Cranbrook",
    "sg:classifiers":[
        {
            "category":"Manufacturing",
            "subcategory":"Metals",
            "type":"Manufacturing & Wholesale Goods"
        }
    ],
    "sg:phone":"+1 250 426 3817",
    "sg:postcode":"V1C 7G1",
    "sg:province":"BC",
    "sg:tags":[
        "steel"
    ],
    "wof:name":"Long Valley Steel Ltd",
    "wof:placetype":"venue"
},
  "geometry": {"coordinates":[-115.755126953,49.5277328491],"type":"Point"}
}