{
  "type": "Feature",
  "properties": {
    "addr:full":"1010 Polytek St Gloucester ON K1J 9H8",
    "addr:housenumber":"1010",
    "addr:postcode":"k1j 9h8",
    "addr:street":"Polytek St",
    "iso:country":"CA",
    "sg:address":"1010 Polytek St",
    "sg:city":"Gloucester",
    "sg:classifiers":[
        {
            "category":"Professional",
            "subcategory":"Management & Consulting",
            "type":"Services"
        }
    ],
    "sg:phone":"+1 613 749 4738",
    "sg:postcode":"K1J 9H8",
    "sg:province":"ON",
    "sg:tags":[
        "consultant",
        "government"
    ],
    "wof:name":"Bernard Wood & Assoc Ltd",
    "wof:placetype":"venue"
},
  "geometry": {"coordinates":[-75.58419000000001,45.456493],"type":"Point"}
}