{
  "type": "Feature",
  "properties": {
    "addr:full":"45 Saint Nicholas St Toronto ON M4Y 1W6",
    "addr:housenumber":"45",
    "addr:postcode":"m4y 1w6",
    "addr:street":"Saint Nicholas St",
    "iso:country":"CA",
    "sg:address":"45 Saint Nicholas St",
    "sg:city":"Toronto",
    "sg:classifiers":[
        {
            "category":"Professional",
            "subcategory":"Lawyer & Legal Services",
            "type":"Services"
        }
    ],
    "sg:phone":"+1 416 963 8405",
    "sg:postcode":"M4Y 1W6",
    "sg:province":"ON",
    "sg:tags":[
        "attorney"
    ],
    "wof:name":"Vander Vennen Lehrer",
    "wof:placetype":"venue"
},
  "geometry": {"coordinates":[-79.386124,43.666779],"type":"Point"}
}