{
  "type": "Feature",
  "properties": {
    "addr:full":"126 Wellington St W #105 Aurora ON L4G 2N9",
    "addr:housenumber":"126",
    "addr:postcode":"l4g 2n9",
    "addr:street":"Wellington St W # 105",
    "iso:country":"CA",
    "sg:address":"126 Wellington St W #105",
    "sg:city":"Aurora",
    "sg:classifiers":[
        {
            "category":"Shopping",
            "subcategory":"Pharmacy",
            "type":"Retail Goods"
        }
    ],
    "sg:phone":"+1 905 841 2133",
    "sg:postcode":"L4G 2N9",
    "sg:province":"ON",
    "wof:name":"Pharmasave",
    "wof:placetype":"venue"
},
  "geometry": {"coordinates":[-79.477554,43.997627],"type":"Point"}
}