{
  "type": "Feature",
  "properties": {
    "addr:full":"1 Rue Robitaille Saint-Thomas QC J0K 3L0",
    "addr:housenumber":"1",
    "addr:postcode":"j0k 3l0",
    "addr:street":"Rue Robitaille",
    "iso:country":"CA",
    "sg:address":"1 Rue Robitaille",
    "sg:city":"Saint-Thomas",
    "sg:classifiers":[
        {
            "category":"Real Estate",
            "subcategory":"Real Estate Operator",
            "type":"Services"
        }
    ],
    "sg:phone":"+1 450 759 1186",
    "sg:postcode":"J0K 3L0",
    "sg:province":"QC",
    "sg:tags":[
        "apartment"
    ],
    "wof:name":"Office Municipale D'Habitation",
    "wof:placetype":"venue"
},
  "geometry": {"coordinates":[-73.3546905518,46.0139694214],"type":"Point"}
}