{
  "type": "Feature",
  "properties": {
    "iso:country":"CA",
    "sg:city":"Montreal",
    "sg:classifiers":[
        {
            "category":"Banks & Credit Unions",
            "subcategory":"Bank",
            "type":"Services"
        }
    ],
    "sg:phone":"+1 514 284 1004",
    "sg:postcode":"H3A 3C6",
    "sg:province":"QC",
    "sg:tags":[
        "financing"
    ],
    "wof:name":"Corporation DE Capital Capda",
    "wof:placetype":"venue"
},
  "geometry": {"coordinates":[-73.56674957280001,45.5182266235],"type":"Point"}
}