{
  "type": "Feature",
  "properties": {
    "iso:country":"CA",
    "sg:city":"Montreal",
    "sg:classifiers":[
        {
            "category":"Personal",
            "subcategory":"Beauty Salon",
            "type":"Services"
        }
    ],
    "sg:phone":"+1 514 284 0661",
    "sg:postcode":"H2L 2E7",
    "sg:province":"QC",
    "wof:name":"St-Laurent Coiffure",
    "wof:placetype":"venue"
},
  "geometry": {"coordinates":[-73.557747,45.516453],"type":"Point"}
}