{
  "type": "Feature",
  "properties": {
    "addr:full":"3091 Appleby Line Burlington ON L7R 3X4",
    "addr:housenumber":"3091",
    "addr:postcode":"l7r 3x4",
    "addr:street":"Appleby Line",
    "iso:country":"CA",
    "sg:address":"3091 Appleby Line",
    "sg:city":"Burlington",
    "sg:classifiers":[
        {
            "category":"Retail",
            "subcategory":"Auto Repair",
            "type":"Services"
        }
    ],
    "sg:phone":"+1 905 331 5282",
    "sg:postcode":"L7R 3X4",
    "sg:province":"ON",
    "sg:tags":[
        "truck"
    ],
    "wof:name":"Appleby Truck & Trailer",
    "wof:placetype":"venue"
},
  "geometry": {"coordinates":[-79.8097457886,43.408000946],"type":"Point"}
}