{
  "type": "Feature",
  "properties": {
    "addr:full":"104 Rue Notre-Dame Est Cap-DE-LA-Madeleine QC G8T 4B7",
    "addr:housenumber":"104",
    "addr:postcode":"g8t 4b7",
    "addr:street":"Rue Notre-Dame Est",
    "iso:country":"CA",
    "sg:address":"104 Rue Notre-Dame Est",
    "sg:city":"Cap-DE-LA-Madeleine",
    "sg:classifiers":[
        {
            "category":"Shopping",
            "subcategory":"Clothing, Apparel, & Fashions",
            "type":"Retail Goods"
        }
    ],
    "sg:phone":"+1 819 376 7560",
    "sg:postcode":"G8T 4B7",
    "sg:province":"QC",
    "sg:tags":[
        "fur",
        "business"
    ],
    "wof:name":"LA Flamme Fourrures",
    "wof:placetype":"venue"
},
  "geometry": {"coordinates":[-72.523117,46.362209],"type":"Point"}
}