{
  "type": "Feature",
  "properties": {
    "addr:full":"851 Ancienne Route DE L'Eglise Lourdes QC G0S 1T0",
    "addr:housenumber":"851",
    "addr:postcode":"g0s 1t0",
    "addr:street":"Ancienne Route De L'Eglise",
    "iso:country":"CA",
    "sg:address":"851 Ancienne Route DE L'Eglise",
    "sg:city":"Lourdes",
    "sg:classifiers":[
        {
            "category":"Local Transit",
            "type":"Transportation"
        }
    ],
    "sg:phone":"+1 819 385 4088",
    "sg:postcode":"G0S 1T0",
    "sg:province":"QC",
    "sg:tags":[
        "bus",
        "line"
    ],
    "wof:name":"Autobus Bso",
    "wof:placetype":"venue"
},
  "geometry": {"coordinates":[-71.509064,46.614849],"type":"Point"}
}