{
  "type": "Feature",
  "properties": {
    "iso:country":"CA",
    "sg:address":"233 Manitoba Ave",
    "sg:city":"Selkirk",
    "sg:classifiers":[
        {
            "category":"Shopping",
            "type":"Retail Goods"
        }
    ],
    "sg:phone":"+1 204 785 1782",
    "sg:postcode":"R1A 0Y4",
    "sg:province":"MB",
    "sg:tags":[
        "art",
        "gallery",
        "dealer"
    ],
    "wof:name":"Waterfront Gallery/Village Frm",
    "wof:placetype":"venue"
},
  "geometry": {"coordinates":[-96.8703079224,50.1443138123],"type":"Point"}
}