{
  "type": "Feature",
  "properties": {
    "iso:country":"CA",
    "sg:city":"Newton",
    "sg:classifiers":[
        {
            "category":"Retail",
            "subcategory":"Auto Repair",
            "type":"Services"
        }
    ],
    "sg:phone":"+1 519 595 8926",
    "sg:postcode":"N0K 1R0",
    "sg:province":"ON",
    "sg:tags":[
        "repairing",
        "automobile"
    ],
    "wof:name":"Jacob's Family Svc",
    "wof:placetype":"venue"
},
  "geometry": {"coordinates":[-80.87869262700001,43.5900650024],"type":"Point"}
}