{
  "type": "Feature",
  "properties": {
    "addr:full":"4517 Cape Rd Salmon Beach NB E2A 6C3",
    "addr:housenumber":"4517",
    "addr:postcode":"e2a 6c3",
    "addr:street":"Cape Rd",
    "iso:country":"CA",
    "sg:address":"4517 Cape Rd",
    "sg:city":"Salmon Beach",
    "sg:classifiers":[
        {
            "category":"Wholesale",
            "subcategory":"Seafood",
            "type":"Manufacturing & Wholesale Goods"
        }
    ],
    "sg:phone":"+1 506 548 4353",
    "sg:postcode":"E2A 6C3",
    "sg:province":"NB",
    "wof:name":"Doris's Fish Shop Ltd",
    "wof:placetype":"venue"
},
  "geometry": {"coordinates":[-65.50263214109999,47.6658668518],"type":"Point"}
}