{
  "type": "Feature",
  "properties": {
    "addr:full":"4397 2nd Ave W Vancouver BC V6R 1K4",
    "addr:housenumber":"4397",
    "addr:postcode":"v6r 1k4",
    "addr:street":"2Nd Ave W",
    "iso:country":"CA",
    "sg:address":"4397 2nd Ave W",
    "sg:city":"Vancouver",
    "sg:classifiers":[
        {
            "category":"Recreation",
            "type":"Entertainment"
        }
    ],
    "sg:phone":"+1 604 257 8140",
    "sg:postcode":"V6R 1K4",
    "sg:province":"BC",
    "sg:tags":[
        "government",
        "hall",
        "auditorium"
    ],
    "wof:name":"West Point Grey Community Ctr",
    "wof:placetype":"venue"
},
  "geometry": {"coordinates":[-123.205413818,49.2714233398],"type":"Point"}
}