{
  "type": "Feature",
  "properties": {
    "iso:country":"CA",
    "sg:address":"199 Colonnade Rd",
    "sg:city":"Nepean",
    "sg:classifiers":[
        {
            "category":"Education",
            "subcategory":"Vocational School",
            "type":"Public Place"
        }
    ],
    "sg:phone":"+1 613 228 5222",
    "sg:postcode":"K2E 7K3",
    "sg:province":"ON",
    "sg:tags":[
        "technical",
        "trade"
    ],
    "wof:name":"Ontario Industrial & Finishing",
    "wof:placetype":"venue"
},
  "geometry": {"coordinates":[-75.710579,45.342018],"type":"Point"}
}