{
  "type": "Feature",
  "properties": {
    "addr:full":"6200 Rte Transcanadienne Saint-Laurent QC H4T 1X9",
    "addr:housenumber":"6200",
    "addr:postcode":"h4t 1x9",
    "addr:street":"Rte Transcanadienne",
    "iso:country":"CA",
    "sg:address":"6200 Rte Transcanadienne",
    "sg:city":"Saint-Laurent",
    "sg:classifiers":[
        {
            "category":"Wholesale",
            "subcategory":"Durable Goods & Equipment",
            "type":"Manufacturing & Wholesale Goods"
        }
    ],
    "sg:phone":"+1 514 731 0010",
    "sg:postcode":"H4T 1X9",
    "sg:province":"QC",
    "sg:tags":[
        "importer"
    ],
    "wof:name":"Amcan-Charter Imports Ltd",
    "wof:placetype":"venue"
},
  "geometry": {"coordinates":[-73.685204,45.494297],"type":"Point"}
}