{
  "type": "Feature",
  "properties": {
    "addr:full":"1512 Rue Sainte-Catherine O Montreal QC H3G 1S8",
    "addr:housenumber":"1512",
    "addr:postcode":"h3g 1s8",
    "addr:street":"Rue Sainte-Catherine O",
    "iso:country":"CA",
    "sg:address":"1512 Rue Sainte-Catherine O",
    "sg:city":"Montreal",
    "sg:classifiers":[
        {
            "category":"Shopping",
            "subcategory":"Jewelry",
            "type":"Retail Goods"
        }
    ],
    "sg:phone":"+1 514 931 9622",
    "sg:postcode":"H3G 1S8",
    "sg:province":"QC",
    "sg:tags":[
        "jeweler"
    ],
    "wof:name":"Bijouterie Yadel Ltee",
    "wof:placetype":"venue"
},
  "geometry": {"coordinates":[-73.5533294678,45.5212554932],"type":"Point"}
}