{
  "type": "Feature",
  "properties": {
    "addr:full":"6305 48 Ave Ponoka AB T4J 1K3",
    "addr:housenumber":"6305",
    "addr:postcode":"t4j 1k3",
    "addr:street":"48 Ave",
    "iso:country":"CA",
    "sg:address":"6305 48 Ave",
    "sg:city":"Ponoka",
    "sg:classifiers":[
        {
            "category":"Retail",
            "subcategory":"Repair Shop",
            "type":"Services"
        }
    ],
    "sg:phone":"+1 403 783 5555",
    "sg:postcode":"T4J 1K3",
    "sg:province":"AB",
    "sg:tags":[
        "farm",
        "bearing",
        "parts"
    ],
    "wof:name":"Town & Country Supplies Ltd",
    "wof:placetype":"venue"
},
  "geometry": {"coordinates":[-113.59742,52.675819],"type":"Point"}
}