{
  "type": "Feature",
  "properties": {
    "addr:full":"White Rock BC V4B 4A3",
    "addr:postcode":"v4b 4a3",
    "iso:country":"CA",
    "sg:city":"White Rock",
    "sg:classifiers":[
        {
            "category":"Health Services",
            "subcategory":"Health Practitioner",
            "type":"Services"
        }
    ],
    "sg:phone":"+1 604 536 2900",
    "sg:postcode":"V4B 4A3",
    "sg:province":"BC",
    "sg:tags":[
        "physiotherapist"
    ],
    "wof:name":"In Motion Physiotherapy",
    "wof:placetype":"venue"
},
  "geometry": {"coordinates":[-122.799667,49.027702],"type":"Point"}
}