{
  "type": "Feature",
  "properties": {
    "iso:country":"CA",
    "sg:address":"430 Rue Sainte-Helene",
    "sg:city":"Montreal",
    "sg:classifiers":[
        {
            "category":"Professional",
            "subcategory":"Computer Services",
            "type":"Services"
        }
    ],
    "sg:phone":"+1 514 281 8570",
    "sg:postcode":"H2Y 2K7",
    "sg:province":"QC",
    "sg:tags":[
        "consultant"
    ],
    "wof:name":"Stelvio Inc",
    "wof:placetype":"venue"
},
  "geometry": {"coordinates":[-73.558197,45.501122],"type":"Point"}
}