{
  "type": "Feature",
  "properties": {
    "iso:country":"CA",
    "sg:address":"1016 Canyon St",
    "sg:city":"Creston",
    "sg:classifiers":[
        {
            "category":"Wholesale",
            "subcategory":"Medical Equipment & Supplies",
            "type":"Manufacturing & Wholesale Goods"
        }
    ],
    "sg:phone":"+1 250 428 8766",
    "sg:postcode":"V0B 1G0",
    "sg:province":"BC",
    "sg:tags":[
        "physician",
        "surgeon",
        "hospital"
    ],
    "wof:name":"Kootenay Medical Supplies",
    "wof:placetype":"venue"
},
  "geometry": {"coordinates":[-116.5131073,49.0953292847],"type":"Point"}
}