{
  "type": "Feature",
  "properties": {
    "addr:full":"Port Perry ON L9L 1J1",
    "addr:postcode":"l9l 1j1",
    "iso:country":"CA",
    "sg:city":"Port Perry",
    "sg:classifiers":[
        {
            "category":"Health Services",
            "subcategory":"Optometrist",
            "type":"Services"
        }
    ],
    "sg:phone":"+1 905 985 9385",
    "sg:postcode":"L9L 1J1",
    "sg:province":"ON",
    "wof:name":"Hadden, Brian J OD",
    "wof:placetype":"venue"
},
  "geometry": {"coordinates":[-78.9397277832,44.1017379761],"type":"Point"}
}