{
  "type": "Feature",
  "properties": {
    "iso:country":"CA",
    "sg:address":"3425 Rue Saint-Denis",
    "sg:city":"Montreal",
    "sg:classifiers":[
        {
            "category":"Personal",
            "type":"Services"
        }
    ],
    "sg:phone":"+1 514 288 3118",
    "sg:postcode":"H2X 3L1",
    "sg:province":"QC",
    "sg:tags":[
        "acupuncture",
        "paying",
        "bill"
    ],
    "wof:name":"Gestimed Inc",
    "wof:placetype":"venue"
},
  "geometry": {"coordinates":[-73.567772,45.517258],"type":"Point"}
}