{
  "type": "Feature",
  "properties": {
    "addr:full":"3425 Rue Saint-Denis Montreal QC H2X 3L1",
    "addr:housenumber":"3425",
    "addr:postcode":"h2x 3l1",
    "addr:street":"Rue Saint-Denis",
    "iso:country":"CA",
    "sg:address":"3425 Rue Saint-Denis",
    "sg:city":"Montreal",
    "sg:classifiers":[
        {
            "category":"Personal",
            "type":"Services"
        }
    ],
    "sg:phone":"+1 514 288 3118",
    "sg:postcode":"H2X 3L1",
    "sg:province":"QC",
    "sg:tags":[
        "acupuncture",
        "paying",
        "bill"
    ],
    "wof:name":"Gestimed Inc",
    "wof:placetype":"venue"
},
  "geometry": {"coordinates":[-73.56777200000001,45.517258],"type":"Point"}
}