{
  "type": "Feature",
  "properties": {
    "addr:full":"5519 South River Dr Manotick ON K4M 1J3",
    "addr:housenumber":"5519",
    "addr:postcode":"k4m 1j3",
    "addr:street":"South River Dr",
    "iso:country":"CA",
    "sg:address":"5519 South River Dr",
    "sg:city":"Manotick",
    "sg:classifiers":[
        {
            "category":"Recreation",
            "type":"Entertainment"
        }
    ],
    "sg:phone":"+1 613 692 1489",
    "sg:postcode":"K4M 1J3",
    "sg:province":"ON",
    "sg:tags":[
        "club",
        "curling"
    ],
    "wof:name":"Manotick Curling Ctr",
    "wof:placetype":"venue"
},
  "geometry": {"coordinates":[-75.67920700000001,45.229015],"type":"Point"}
}