{
  "type": "Feature",
  "properties": {
    "addr:full":"50 William St Fredericton NB E3A 4V8",
    "addr:housenumber":"50",
    "addr:postcode":"e3a 4v8",
    "addr:street":"William St",
    "iso:country":"CA",
    "sg:address":"50 William St",
    "sg:city":"Fredericton",
    "sg:classifiers":[
        {
            "category":"Personal",
            "subcategory":"Beauty Salon",
            "type":"Services"
        }
    ],
    "sg:phone":"+1 506 451 9401",
    "sg:postcode":"E3A 4V8",
    "sg:province":"NB",
    "wof:name":"Hair Design By Kathy",
    "wof:placetype":"venue"
},
  "geometry": {"coordinates":[-66.670891,45.989006],"type":"Point"}
}