{
  "type": "Feature",
  "properties": {
    "iso:country":"CA",
    "sg:address":"405 Huronia Rd",
    "sg:city":"Barrie",
    "sg:classifiers":[
        {
            "category":"Food & Beverages",
            "subcategory":"Bakery",
            "type":"Retail Goods"
        }
    ],
    "sg:phone":"+1 705 730 1696",
    "sg:postcode":"L4N 8Z1",
    "sg:province":"ON",
    "sg:tags":[
        "doughnut"
    ],
    "wof:name":"Tim Hortons",
    "wof:placetype":"venue"
},
  "geometry": {"coordinates":[-79.664734,44.352489],"type":"Point"}
}