{
  "type": "Feature",
  "properties": {
    "iso:country":"CA",
    "sg:address":"135 Wallace Ave S",
    "sg:city":"Listowel",
    "sg:classifiers":[
        {
            "category":"Retail",
            "subcategory":"Self-service Laundry",
            "type":"Services"
        }
    ],
    "sg:phone":"+1 519 291 2720",
    "sg:postcode":"N4W 1Y1",
    "sg:province":"ON",
    "wof:name":"Speed Queen Laundry & Dry Clng",
    "wof:placetype":"venue"
},
  "geometry": {"coordinates":[-80.9534378052,43.7306785583],"type":"Point"}
}