{
  "type": "Feature",
  "properties": {
    "addr:full":"227 7th Ave Regina SK S4N 5H5",
    "addr:housenumber":"227",
    "addr:postcode":"s4n 5h5",
    "addr:street":"7Th Ave",
    "iso:country":"CA",
    "sg:address":"227 7th Ave",
    "sg:city":"Regina",
    "sg:classifiers":[
        {
            "category":"Organizations",
            "subcategory":"Labor Organization",
            "type":"Services"
        }
    ],
    "sg:phone":"+1 306 569 0624",
    "sg:postcode":"S4N 5H5",
    "sg:province":"SK",
    "wof:name":"Plumbers & Pipe Fitters",
    "wof:placetype":"venue"
},
  "geometry": {"coordinates":[-104.584084,50.458176],"type":"Point"}
}