{
  "type": "Feature",
  "properties": {
    "addr:full":"158 Boul Brunswick Pointe-Claire QC H9R 5P9",
    "addr:housenumber":"158",
    "addr:postcode":"h9r 5p9",
    "addr:street":"Boul Brunswick",
    "iso:country":"CA",
    "sg:address":"158 Boul Brunswick",
    "sg:city":"Pointe-Claire",
    "sg:classifiers":[
        {
            "category":"Manufacturing",
            "subcategory":"Rubber & Plastics",
            "type":"Manufacturing & Wholesale Goods"
        }
    ],
    "sg:phone":"+1 514 697 3701",
    "sg:postcode":"H9R 5P9",
    "sg:province":"QC",
    "sg:tags":[
        "equipment",
        "hose",
        "heating",
        "system"
    ],
    "wof:name":"Flexmaster Canada Ltee",
    "wof:placetype":"venue"
},
  "geometry": {"coordinates":[-73.818138,45.473042],"type":"Point"}
}