{
  "type": "Feature",
  "properties": {
    "iso:country":"CA",
    "sg:address":"2 Jody Ave",
    "sg:city":"North York",
    "sg:classifiers":[
        {
            "category":"Manufacturing",
            "subcategory":"Rubber & Plastics",
            "type":"Manufacturing & Wholesale Goods"
        }
    ],
    "sg:phone":"+1 416 749 8835",
    "sg:postcode":"M3N 1H1",
    "sg:province":"ON",
    "sg:tags":[
        "mold",
        "maker"
    ],
    "wof:name":"Inventive Plastic Products Ltd",
    "wof:placetype":"venue"
},
  "geometry": {"coordinates":[-79.5241394043,43.7453994751],"type":"Point"}
}