{
  "type": "Feature",
  "properties": {
    "addr:full":"217 Russell St S Sarnia ON N7T 3L6",
    "addr:housenumber":"217",
    "addr:postcode":"n7t 3l6",
    "addr:street":"Russell St S",
    "iso:country":"CA",
    "sg:address":"217 Russell St S",
    "sg:city":"Sarnia",
    "sg:classifiers":[
        {
            "category":"Education",
            "subcategory":"School",
            "type":"Public Place"
        }
    ],
    "sg:phone":"+1 519 344 7531",
    "sg:postcode":"N7T 3L6",
    "sg:province":"ON",
    "wof:name":"Johnston Memorial School",
    "wof:placetype":"venue"
},
  "geometry": {"coordinates":[-82.3918304443,42.9666023254],"type":"Point"}
}