{
  "type": "Feature",
  "properties": {
    "addr:full":"4249 Kingston Rd Scarborough ON M1E 2M5",
    "addr:housenumber":"4249",
    "addr:postcode":"m1e 2m5",
    "addr:street":"Kingston Rd",
    "iso:country":"CA",
    "sg:address":"4249 Kingston Rd",
    "sg:city":"Scarborough",
    "sg:classifiers":[
        {
            "category":"Autos & Motor Vehicles",
            "subcategory":"Automobile Sales",
            "type":"Retail Goods"
        }
    ],
    "sg:phone":"+1 416 283 4262",
    "sg:postcode":"M1E 2M5",
    "sg:province":"ON",
    "sg:tags":[
        "car",
        "dealer"
    ],
    "wof:name":"Loan Arranger",
    "wof:placetype":"venue"
},
  "geometry": {"coordinates":[-79.194923,43.76152],"type":"Point"}
}