{
  "type": "Feature",
  "properties": {
    "addr:full":"17 Queen St Bracebridge ON P1L 1H2",
    "addr:housenumber":"17",
    "addr:postcode":"p1l 1h2",
    "addr:street":"Queen St",
    "iso:country":"CA",
    "sg:address":"17 Queen St",
    "sg:city":"Bracebridge",
    "sg:classifiers":[
        {
            "category":"Organizations",
            "subcategory":"Religious Organization",
            "type":"Services"
        }
    ],
    "sg:phone":"+1 705 645 4926",
    "sg:postcode":"P1L 1H2",
    "sg:province":"ON",
    "sg:tags":[
        "church"
    ],
    "wof:name":"New Hope Free Methodist Church",
    "wof:placetype":"venue"
},
  "geometry": {"coordinates":[-79.30558776860001,45.0376586914],"type":"Point"}
}