{
  "type": "Feature",
  "properties": {
    "addr:full":"Scarborough ON M1K 2P8",
    "addr:postcode":"m1k 2p8",
    "iso:country":"CA",
    "sg:city":"Scarborough",
    "sg:classifiers":[
        {
            "category":"Restaurant",
            "type":"Food & Drink"
        }
    ],
    "sg:phone":"+1 416 285 1818",
    "sg:postcode":"M1K 2P8",
    "sg:province":"ON",
    "wof:name":"Good Luck Restaurant",
    "wof:placetype":"venue"
},
  "geometry": {"coordinates":[-79.266914,43.73262],"type":"Point"}
}