{
  "type": "Feature",
  "properties": {
    "addr:full":"8585 Boul Lacroix # 260 Saint-Georges QC G5Y 5L6",
    "addr:housenumber":"8585",
    "addr:postcode":"g5y 5l6",
    "addr:street":"Boul Lacroix # 260",
    "iso:country":"CA",
    "sg:address":"8585 Boul Lacroix # 260",
    "sg:city":"Saint-Georges",
    "sg:classifiers":[
        {
            "category":"Restaurant",
            "type":"Food & Drink"
        }
    ],
    "sg:phone":"+1 418 228 4453",
    "sg:postcode":"G5Y 5L6",
    "sg:province":"QC",
    "sg:tags":[
        "parlor",
        "ice",
        "cream"
    ],
    "wof:name":"Bar Laitier St-Georges",
    "wof:placetype":"venue"
},
  "geometry": {"coordinates":[-70.6993026733,46.1324539185],"type":"Point"}
}