{
  "type": "Feature",
  "properties": {
    "addr:full":"2502 Rue Lapierre Lasalle QC H8N 2W9",
    "addr:housenumber":"2502",
    "addr:postcode":"h8n 2w9",
    "addr:street":"Rue Lapierre",
    "iso:country":"CA",
    "sg:address":"2502 Rue Lapierre",
    "sg:city":"Lasalle",
    "sg:classifiers":[
        {
            "category":"Home & Garden",
            "subcategory":"Building Materials",
            "type":"Retail Goods"
        }
    ],
    "sg:phone":"+1 514 765 0654",
    "sg:postcode":"H8N 2W9",
    "sg:province":"QC",
    "sg:tags":[
        "builder",
        "door",
        "deck"
    ],
    "wof:name":"Balcon Ideal Inc",
    "wof:placetype":"venue"
},
  "geometry": {"coordinates":[-73.629593,45.442627],"type":"Point"}
}