{
  "type": "Feature",
  "properties": {
    "addr:full":"216 25 Ave SW Calgary AB T2S 0L1",
    "addr:housenumber":"216",
    "addr:postcode":"t2s 0l1",
    "addr:street":"25 Ave Sw",
    "iso:country":"CA",
    "sg:address":"216 25 Ave SW",
    "sg:city":"Calgary",
    "sg:classifiers":[
        {
            "category":"Travel",
            "subcategory":"Hotels & Motels",
            "type":"Entertainment"
        }
    ],
    "sg:phone":"+1 403 229 1758",
    "sg:postcode":"T2S 0L1",
    "sg:province":"AB",
    "sg:tags":[
        "breakfast",
        "accommodation",
        "bed"
    ],
    "wof:name":"Calgary Westways Guest House",
    "wof:placetype":"venue"
},
  "geometry": {"coordinates":[-114.067108,51.030609],"type":"Point"}
}