{
  "type": "Feature",
  "properties": {
    "addr:full":"310 Main St Champion AB T0L 0R0",
    "addr:housenumber":"310",
    "addr:postcode":"t0l 0r0",
    "addr:street":"Main St",
    "iso:country":"CA",
    "sg:address":"310 Main St",
    "sg:city":"Champion",
    "sg:classifiers":[
        {
            "category":"Education",
            "subcategory":"School",
            "type":"Public Place"
        }
    ],
    "sg:phone":"+1 403 897 3831",
    "sg:postcode":"T0L 0R0",
    "sg:province":"AB",
    "wof:name":"Champion School",
    "wof:placetype":"venue"
},
  "geometry": {"coordinates":[-113.14709499999999,50.241577],"type":"Point"}
}