{
  "type": "Feature",
  "properties": {
    "addr:full":"11417 99 St Peace River AB T8S 1L8",
    "addr:housenumber":"11417",
    "addr:postcode":"t8s 1l8",
    "addr:street":"99 St",
    "iso:country":"CA",
    "sg:address":"11417 99 St",
    "sg:city":"Peace River",
    "sg:classifiers":[
        {
            "category":"Shopping",
            "subcategory":"Florist",
            "type":"Retail Goods"
        }
    ],
    "sg:phone":"+1 780 532 7725",
    "sg:postcode":"T8S 1L8",
    "sg:province":"AB",
    "wof:name":"Iga North Side",
    "wof:placetype":"venue"
},
  "geometry": {"coordinates":[-117.28318,56.218487],"type":"Point"}
}