{
  "type": "Feature",
  "properties": {
    "addr:full":"312 Legget Dr Kanata ON K2K 1Y6",
    "addr:housenumber":"312",
    "addr:postcode":"k2k 1y6",
    "addr:street":"Legget Dr",
    "iso:country":"CA",
    "sg:address":"312 Legget Dr",
    "sg:city":"Kanata",
    "sg:classifiers":[
        {
            "category":"Professional",
            "subcategory":"Research",
            "type":"Services"
        }
    ],
    "sg:phone":"+1 613 599 9248",
    "sg:postcode":"K2K 1Y6",
    "sg:province":"ON",
    "sg:tags":[
        "development",
        "laboratory"
    ],
    "wof:name":"Iotron Technologies Corp",
    "wof:placetype":"venue"
},
  "geometry": {"coordinates":[-75.9058303833,45.3399505615],"type":"Point"}
}