{
  "type": "Feature",
  "properties": {
    "addr:full":"96 Gordon St Garson ON P3L 1M9",
    "addr:housenumber":"96",
    "addr:postcode":"p3l 1m9",
    "addr:street":"Gordon St",
    "iso:country":"CA",
    "sg:address":"96 Gordon St",
    "sg:city":"Garson",
    "sg:classifiers":[
        {
            "category":"Building & Trades",
            "subcategory":"Cleaning & Sanitation",
            "type":"Services"
        }
    ],
    "sg:phone":"+1 705 693 3658",
    "sg:postcode":"P3L 1M9",
    "sg:province":"ON",
    "sg:tags":[
        "property",
        "maintenance"
    ],
    "wof:name":"Merrill, Frank",
    "wof:placetype":"venue"
},
  "geometry": {"coordinates":[-80.86219,46.554264],"type":"Point"}
}