{
  "type": "Feature",
  "properties": {
    "addr:full":"Saint-Boniface-DE-Shawinigan QC G0X 2L0",
    "addr:postcode":"g0x 2l0",
    "iso:country":"CA",
    "sg:city":"Saint-Boniface-DE-Shawinigan",
    "sg:classifiers":[
        {
            "category":"Government",
            "subcategory":"Office",
            "type":"Public Place"
        }
    ],
    "sg:phone":"+1 819 535 9084",
    "sg:postcode":"G0X 2L0",
    "sg:province":"QC",
    "sg:tags":[
        "village"
    ],
    "wof:name":"St-Etienne-Des-Grecs Travaux",
    "wof:placetype":"venue"
},
  "geometry": {"coordinates":[-72.817902,46.496964],"type":"Point"}
}