{
  "type": "Feature",
  "properties": {
    "addr:full":"1205 Okalta Rd SW Turner Valley AB T0L 2A0",
    "addr:housenumber":"1205",
    "addr:postcode":"t0l 2a0",
    "addr:street":"Okalta Rd Sw Turner Valley",
    "iso:country":"CA",
    "sg:address":"1205 Okalta Rd SW",
    "sg:city":"Turner Valley",
    "sg:classifiers":[
        {
            "category":"Organizations",
            "subcategory":"Religious Organization",
            "type":"Services"
        }
    ],
    "sg:phone":"+1 403 933 3754",
    "sg:postcode":"T0L 2A0",
    "sg:province":"AB",
    "sg:tags":[
        "church"
    ],
    "wof:name":"Youth With A Mission",
    "wof:placetype":"venue"
},
  "geometry": {"coordinates":[-114.28977999999999,50.663975],"type":"Point"}
}