{
  "type": "Feature",
  "properties": {
    "addr:full":"186 Carlton St Toronto ON M5A 2K6",
    "addr:housenumber":"186",
    "addr:postcode":"m5a 2k6",
    "addr:street":"Carlton St",
    "iso:country":"CA",
    "sg:address":"186 Carlton St",
    "sg:city":"Toronto",
    "sg:classifiers":[
        {
            "category":"Restaurant",
            "type":"Food & Drink"
        }
    ],
    "sg:phone":"+1 416 924 7583",
    "sg:postcode":"M5A 2K6",
    "sg:province":"ON",
    "wof:name":"Steerburger Restaurant",
    "wof:placetype":"venue"
},
  "geometry": {"coordinates":[-79.37237548829999,43.6633987427],"type":"Point"}
}