{
  "type": "Feature",
  "properties": {
    "iso:country":"CA",
    "sg:address":"505 St Anne's Rd",
    "sg:city":"Winnipeg",
    "sg:classifiers":[
        {
            "category":"Education",
            "subcategory":"School",
            "type":"Public Place"
        }
    ],
    "sg:phone":"+1 204 253 1388",
    "sg:postcode":"R2M 3E5",
    "sg:province":"MB",
    "wof:name":"Lavallee School",
    "wof:placetype":"venue"
},
  "geometry": {"coordinates":[-97.09465026860001,49.8423538208],"type":"Point"}
}