{
  "type": "Feature",
  "properties": {
    "iso:country":"CA",
    "sg:city":"Calgary",
    "sg:classifiers":[
        {
            "category":"Restaurant",
            "type":"Food & Drink"
        }
    ],
    "sg:phone":"+1 403 235 1993",
    "sg:postcode":"T2A 0A7",
    "sg:province":"AB",
    "wof:name":"Gong Kee Bbq Noodle House",
    "wof:placetype":"venue"
},
  "geometry": {"coordinates":[-113.969238,51.045025],"type":"Point"}
}