{
  "type": "Feature",
  "properties": {
    "iso:country":"CA",
    "sg:city":"Alliston",
    "sg:classifiers":[
        {
            "category":"Home & Garden",
            "subcategory":"Furniture",
            "type":"Retail Goods"
        }
    ],
    "sg:phone":"+1 705 435 6169",
    "sg:postcode":"L9R 1E7",
    "sg:province":"ON",
    "sg:tags":[
        "equipment",
        "kitchen",
        "cabinet"
    ],
    "wof:name":"Lrw Cabinets & Millwork",
    "wof:placetype":"venue"
},
  "geometry": {"coordinates":[-79.86219024659999,44.1478843689],"type":"Point"}
}