{
  "type": "Feature",
  "properties": {
    "addr:full":"Pouce Coupe BC V0C 2C0",
    "addr:postcode":"bc v0c 2c0",
    "iso:country":"CA",
    "sg:city":"Pouce Coupe",
    "sg:classifiers":[
        {
            "category":"Education",
            "subcategory":"Library",
            "type":"Public Place"
        }
    ],
    "sg:phone":"+1 250 786 5765",
    "sg:postcode":"V0C 2C0",
    "sg:province":"BC",
    "wof:name":"Pouce Coupe Public Library",
    "wof:placetype":"venue"
},
  "geometry": {"coordinates":[-120.133636,55.715107],"type":"Point"}
}