{
  "type": "Feature",
  "properties": {
    "addr:full":"1408 Lougar Ave Sarnia ON N7S 5N4",
    "addr:housenumber":"1408",
    "addr:postcode":"n7s 5n4",
    "addr:street":"Lougar Ave",
    "iso:country":"CA",
    "sg:address":"1408 Lougar Ave",
    "sg:city":"Sarnia",
    "sg:classifiers":[
        {
            "category":"Freight",
            "type":"Transportation"
        }
    ],
    "sg:phone":"+1 519 344 8451",
    "sg:postcode":"N7S 5N4",
    "sg:province":"ON",
    "sg:tags":[
        "mover"
    ],
    "wof:name":"Capes Movers Ltd",
    "wof:placetype":"venue"
},
  "geometry": {"coordinates":[-82.352425,42.957901],"type":"Point"}
}