{
  "type": "Feature",
  "properties": {
    "addr:full":"3904 78 Ave NW Edmonton AB T6B 2W4",
    "addr:housenumber":"3904",
    "addr:postcode":"t6b 2w4",
    "addr:street":"78 Ave Nw",
    "iso:country":"CA",
    "sg:address":"3904 78 Ave NW",
    "sg:city":"Edmonton",
    "sg:classifiers":[
        {
            "category":"Manufacturing",
            "subcategory":"Motor Vehicles & Parts",
            "type":"Manufacturing & Wholesale Goods"
        }
    ],
    "sg:phone":"+1 780 447 2662",
    "sg:postcode":"T6B 2W4",
    "sg:province":"AB",
    "sg:tags":[
        "trailer"
    ],
    "wof:name":"Scona Manufacturing",
    "wof:placetype":"venue"
},
  "geometry": {"coordinates":[-113.401786804,53.514377594],"type":"Point"}
}