{
  "type": "Feature",
  "properties": {
    "addr:full":"39 Main St N Milverton ON N0K 1M0",
    "addr:housenumber":"39",
    "addr:postcode":"n0k 1m0",
    "addr:street":"Main St N Milverton",
    "iso:country":"CA",
    "sg:address":"39 Main St N",
    "sg:city":"Milverton",
    "sg:classifiers":[
        {
            "category":"Food & Beverages",
            "subcategory":"Bakery",
            "type":"Retail Goods"
        }
    ],
    "sg:phone":"+1 519 595 8854",
    "sg:postcode":"N0K 1M0",
    "sg:province":"ON",
    "sg:tags":[
        "baker"
    ],
    "wof:name":"Guenther's Bakery",
    "wof:placetype":"venue"
},
  "geometry": {"coordinates":[-80.92112,43.56691],"type":"Point"}
}