{
  "type": "Feature",
  "properties": {
    "addr:full":"11338 149 St NW Edmonton AB T5M 1W5",
    "addr:housenumber":"11338",
    "addr:postcode":"t5m 1w5",
    "addr:street":"149 St Nw",
    "iso:country":"CA",
    "sg:address":"11338 149 St NW",
    "sg:city":"Edmonton",
    "sg:classifiers":[
        {
            "category":"Retail",
            "subcategory":"Auto Repair",
            "type":"Services"
        }
    ],
    "sg:phone":"+1 780 454 6407",
    "sg:postcode":"T5M 1W5",
    "sg:province":"AB",
    "sg:tags":[
        "repairing",
        "automobile"
    ],
    "wof:name":"J D Car Care",
    "wof:placetype":"venue"
},
  "geometry": {"coordinates":[-113.578392029,53.5623016357],"type":"Point"}
}