{
  "type": "Feature",
  "properties": {
    "addr:full":"383 Dundas St E Toronto ON M5A 2A6",
    "addr:housenumber":"383",
    "addr:postcode":"m5a 2a6",
    "addr:street":"Dundas St E",
    "iso:country":"CA",
    "sg:address":"383 Dundas St E",
    "sg:city":"Toronto",
    "sg:classifiers":[
        {
            "category":"Restaurant",
            "type":"Food & Drink"
        }
    ],
    "sg:phone":"+1 416 366 0539",
    "sg:postcode":"M5A 2A6",
    "sg:province":"ON",
    "wof:name":"Ontario Restaurant",
    "wof:placetype":"venue"
},
  "geometry": {"coordinates":[-79.36827850340001,43.6587867737],"type":"Point"}
}