{
  "type": "Feature",
  "properties": {
    "iso:country":"CA",
    "sg:address":"4225 1E Av",
    "sg:city":"Charlesbourg",
    "sg:classifiers":[
        {
            "category":"Personal",
            "subcategory":"Beauty Salon",
            "type":"Services"
        }
    ],
    "sg:phone":"+1 418 622 0606",
    "sg:postcode":"G1H 2S3",
    "sg:province":"QC",
    "wof:name":"Coiffure Sophie Laberge",
    "wof:placetype":"venue"
},
  "geometry": {"coordinates":[-71.24983978269999,46.8425483704],"type":"Point"}
}