{
  "type": "Feature",
  "properties": {
    "addr:full":"Baie-D'Urfe QC H9X 3T5",
    "addr:postcode":"h9x 3t5",
    "iso:country":"CA",
    "sg:city":"Baie-D'Urfe",
    "sg:classifiers":[
        {
            "category":"Professional",
            "subcategory":"Business Services",
            "type":"Services"
        }
    ],
    "sg:phone":"+1 514 457 7753",
    "sg:postcode":"H9X 3T5",
    "sg:province":"QC",
    "sg:tags":[
        "water",
        "treatment"
    ],
    "wof:name":"Dedremont Erpac Canada Inc",
    "wof:placetype":"venue"
},
  "geometry": {"coordinates":[-71.495659,46.980713],"type":"Point"}
}