{
  "type": "Feature",
  "properties": {
    "addr:full":"141 DE LA Presentation Saint-Pie QC J0H 1W0",
    "addr:housenumber":"141",
    "addr:postcode":"j0h 1w0",
    "addr:street":"De La Presentation",
    "iso:country":"CA",
    "sg:address":"141 DE LA Presentation",
    "sg:city":"Saint-Pie",
    "sg:classifiers":[
        {
            "category":"Organizations",
            "subcategory":"Professional Association",
            "type":"Services"
        }
    ],
    "sg:phone":"+1 450 772 5248",
    "sg:postcode":"J0H 1W0",
    "sg:province":"QC",
    "wof:name":"C DE C Conseil 2958",
    "wof:placetype":"venue"
},
  "geometry": {"coordinates":[-72.90765399999999,45.504738],"type":"Point"}
}