{
  "type": "Feature",
  "properties": {
    "addr:full":"71 Main St N Markham ON L3P 1X7",
    "addr:housenumber":"71",
    "addr:postcode":"l3p 1x7",
    "addr:street":"Main St N",
    "iso:country":"CA",
    "sg:address":"71 Main St N",
    "sg:city":"Markham",
    "sg:classifiers":[
        {
            "category":"Professional",
            "subcategory":"Art Services",
            "type":"Services"
        }
    ],
    "sg:phone":"+1 905 471 9428",
    "sg:postcode":"L3P 1X7",
    "sg:province":"ON",
    "sg:tags":[
        "graphic",
        "designer"
    ],
    "wof:name":"Say What Communications Inc",
    "wof:placetype":"venue"
},
  "geometry": {"coordinates":[-79.260323,43.876617],"type":"Point"}
}