{
  "type": "Feature",
  "properties": {
    "addr:full":"York ON M6S 4W3",
    "addr:postcode":"m6s 4w3",
    "iso:country":"CA",
    "sg:city":"York",
    "sg:classifiers":[
        {
            "category":"Health Services",
            "subcategory":"Optometrist",
            "type":"Services"
        }
    ],
    "sg:phone":"+1 416 762 7391",
    "sg:postcode":"M6S 4W3",
    "sg:province":"ON",
    "wof:name":"Witer, Marta OD",
    "wof:placetype":"venue"
},
  "geometry": {"coordinates":[-79.49881000000001,43.68446],"type":"Point"}
}