{
  "type": "Feature",
  "properties": {
    "iso:country":"CA",
    "sg:address":"135 Rue Jean-Talon",
    "sg:city":"Saint-Luc",
    "sg:classifiers":[
        {
            "category":"Building & Trades",
            "subcategory":"Construction",
            "type":"Services"
        }
    ],
    "sg:phone":"+1 450 348 7410",
    "sg:postcode":"J2W 1N7",
    "sg:province":"QC",
    "sg:tags":[
        "general",
        "contractor"
    ],
    "wof:name":"Entreprises Robert Viau Inc",
    "wof:placetype":"venue"
},
  "geometry": {"coordinates":[-73.266273,45.349834],"type":"Point"}
}