{
  "type": "Feature",
  "properties": {
    "addr:full":"178 Norseman St Etobicoke ON M8Z 2R4",
    "addr:housenumber":"178",
    "addr:postcode":"m8z 2r4",
    "addr:street":"Norseman St",
    "iso:country":"CA",
    "sg:address":"178 Norseman St",
    "sg:city":"Etobicoke",
    "sg:classifiers":[
        {
            "category":"Wholesale",
            "subcategory":"Non-durable Goods",
            "type":"Manufacturing & Wholesale Goods"
        }
    ],
    "sg:phone":"+1 416 231 3127",
    "sg:postcode":"M8Z 2R4",
    "sg:province":"ON",
    "sg:tags":[
        "advertising"
    ],
    "wof:name":"Mci Marketing Canada Inc",
    "wof:placetype":"venue"
},
  "geometry": {"coordinates":[-79.522469,43.633518],"type":"Point"}
}