{
  "type": "Feature",
  "properties": {
    "addr:full":"873 Rue Scott Chicoutimi QC G7H 2S6",
    "addr:housenumber":"873",
    "addr:postcode":"g7h 2s6",
    "addr:street":"Rue Scott",
    "iso:country":"CA",
    "sg:address":"873 Rue Scott",
    "sg:city":"Chicoutimi",
    "sg:classifiers":[
        {
            "category":"Building & Trades",
            "subcategory":"Construction",
            "type":"Services"
        }
    ],
    "sg:phone":"+1 418 820 6737",
    "sg:postcode":"G7H 2S6",
    "sg:province":"QC",
    "sg:tags":[
        "well",
        "drilling"
    ],
    "wof:name":"Forage Directionnel 3D",
    "wof:placetype":"venue"
},
  "geometry": {"coordinates":[-71.041901,48.415844],"type":"Point"}
}