{
  "type": "Feature",
  "properties": {
    "iso:country":"CA",
    "sg:address":"460 Traverse Rd",
    "sg:city":"Ste Anne",
    "sg:classifiers":[
        {
            "category":"Wholesale",
            "subcategory":"Wine & Distilled Alcoholic Beverages",
            "type":"Manufacturing & Wholesale Goods"
        }
    ],
    "sg:phone":"+1 204 422 9880",
    "sg:postcode":"R5H 1A3",
    "sg:province":"MB",
    "sg:tags":[
        "equipment",
        "brewer",
        "supply"
    ],
    "wof:name":"Bernard's Brew Supplies",
    "wof:placetype":"venue"
},
  "geometry": {"coordinates":[-96.6524276733,49.6711997986],"type":"Point"}
}