{
  "type": "Feature",
  "properties": {
    "addr:full":"2420 Beacon Ave Sidney BC V8L 1X4",
    "addr:housenumber":"2420",
    "addr:postcode":"v8l 1x4",
    "addr:street":"Beacon Ave",
    "iso:country":"CA",
    "sg:address":"2420 Beacon Ave",
    "sg:city":"Sidney",
    "sg:classifiers":[
        {
            "category":"Shopping",
            "subcategory":"Clothing, Apparel, & Fashions",
            "type":"Retail Goods"
        }
    ],
    "sg:phone":"+1 250 656 1002",
    "sg:postcode":"V8L 1X4",
    "sg:province":"BC",
    "sg:tags":[
        "lingerie"
    ],
    "wof:name":"Sweet Talk & Lace",
    "wof:placetype":"venue"
},
  "geometry": {"coordinates":[-123.399506,48.649055],"type":"Point"}
}