{
  "type": "Feature",
  "properties": {
    "addr:full":"1225 Kensington Rd NW Calgary AB T2N 3P8",
    "addr:housenumber":"1225",
    "addr:postcode":"t2n 3p8",
    "addr:street":"Kensington Rd Nw",
    "iso:country":"CA",
    "sg:address":"1225 Kensington Rd NW",
    "sg:city":"Calgary",
    "sg:classifiers":[
        {
            "category":"Personal",
            "subcategory":"Shoe Repair & Shine",
            "type":"Services"
        }
    ],
    "sg:phone":"+1 403 283 5224",
    "sg:postcode":"T2N 3P8",
    "sg:province":"AB",
    "sg:tags":[
        "repairing",
        "boot"
    ],
    "wof:name":"Alpine Shoe Svc",
    "wof:placetype":"venue"
},
  "geometry": {"coordinates":[-114.09071400000001,51.052376],"type":"Point"}
}