{
  "type": "Feature",
  "properties": {
    "iso:country":"CA",
    "sg:address":"6 Con Glackmeyer",
    "sg:city":"Cochrane",
    "sg:classifiers":[
        {
            "category":"Airport",
            "type":"Transportation"
        }
    ],
    "sg:phone":"+1 705 272 5786",
    "sg:postcode":"P0L 1C0",
    "sg:province":"ON",
    "sg:tags":[
        "aircraft",
        "maintenance"
    ],
    "wof:name":"Skywrench Inc",
    "wof:placetype":"venue"
},
  "geometry": {"coordinates":[-81.02895355219999,49.0652198792],"type":"Point"}
}