{
  "type": "Feature",
  "properties": {
    "addr:full":"2203 Mildred St Sudbury ON P3B 1L5",
    "addr:housenumber":"2203",
    "addr:postcode":"p3b 1l5",
    "addr:street":"Mildred St",
    "iso:country":"CA",
    "sg:address":"2203 Mildred St",
    "sg:city":"Sudbury",
    "sg:classifiers":[
        {
            "category":"Recreation",
            "type":"Entertainment"
        }
    ],
    "sg:phone":"+1 705 521 0024",
    "sg:postcode":"P3B 1L5",
    "sg:province":"ON",
    "sg:tags":[
        "arts",
        "instruction",
        "art",
        "school"
    ],
    "wof:name":"Tole House",
    "wof:placetype":"venue"
},
  "geometry": {"coordinates":[-80.928635,46.487198],"type":"Point"}
}