{
  "type": "Feature",
  "properties": {
    "addr:full":"321 Davenport Rd Toronto ON M5R 1K5",
    "addr:housenumber":"321",
    "addr:postcode":"m5r 1k5",
    "addr:street":"Davenport Rd",
    "iso:country":"CA",
    "sg:address":"321 Davenport Rd",
    "sg:city":"Toronto",
    "sg:classifiers":[
        {
            "category":"Museum",
            "type":"Entertainment"
        }
    ],
    "sg:phone":"+1 416 928 9292",
    "sg:postcode":"M5R 1K5",
    "sg:province":"ON",
    "wof:name":"Lord Cultural Resources Inc",
    "wof:placetype":"venue"
},
  "geometry": {"coordinates":[-79.4011764526,43.6747131348],"type":"Point"}
}