{
  "type": "Feature",
  "properties": {
    "addr:full":"596 Colby Dr Waterloo ON N2V 1A2",
    "addr:housenumber":"596",
    "addr:postcode":"n2v 1a2",
    "addr:street":"Colby Dr",
    "iso:country":"CA",
    "sg:address":"596 Colby Dr",
    "sg:city":"Waterloo",
    "sg:classifiers":[
        {
            "category":"Home & Garden",
            "subcategory":"Building Materials",
            "type":"Retail Goods"
        }
    ],
    "sg:phone":"+1 519 885 0060",
    "sg:postcode":"N2V 1A2",
    "sg:province":"ON",
    "sg:tags":[
        "door"
    ],
    "wof:name":"P G Heldmann Woodworking Ltd",
    "wof:placetype":"venue"
},
  "geometry": {"coordinates":[-80.54055,43.502842],"type":"Point"}
}