{
  "type": "Feature",
  "properties": {
    "addr:full":"412 Queen St E Toronto ON M5A 1T3",
    "addr:housenumber":"412",
    "addr:postcode":"m5a 1t3",
    "addr:street":"Queen St E",
    "iso:country":"CA",
    "sg:address":"412 Queen St E",
    "sg:city":"Toronto",
    "sg:classifiers":[
        {
            "category":"Organizations",
            "subcategory":"Religious Organization",
            "type":"Services"
        }
    ],
    "sg:phone":"+1 416 869 3619",
    "sg:postcode":"M5A 1T3",
    "sg:province":"ON",
    "sg:tags":[
        "association"
    ],
    "wof:name":"Good Shepherd Refuge",
    "wof:placetype":"venue"
},
  "geometry": {"coordinates":[-79.36238899999999,43.656124],"type":"Point"}
}