{
  "type": "Feature",
  "properties": {
    "addr:full":"60 Saulnierville Rd Saulnierville NS B0W 2Z0",
    "addr:housenumber":"60",
    "addr:postcode":"b0w 2z0",
    "addr:street":"Saulnierville Rd",
    "iso:country":"CA",
    "sg:address":"60 Saulnierville Rd",
    "sg:city":"Saulnierville",
    "sg:classifiers":[
        {
            "category":"Manufacturing",
            "subcategory":"Food",
            "type":"Manufacturing & Wholesale Goods"
        }
    ],
    "sg:phone":"+1 902 769 2101",
    "sg:postcode":"B0W 2Z0",
    "sg:province":"NS",
    "sg:tags":[
        "packer",
        "seafood",
        "fish"
    ],
    "wof:name":"Comeau Sea Foods Ltd",
    "wof:placetype":"venue"
},
  "geometry": {"coordinates":[-66.1288146973,44.2592544556],"type":"Point"}
}