{
  "type": "Feature",
  "properties": {
    "addr:full":"22 Rizer Cres Winnipeg MB R2K 3V2",
    "addr:housenumber":"22",
    "addr:postcode":"r2k 3v2",
    "addr:street":"Rizer Cres",
    "iso:country":"CA",
    "sg:address":"22 Rizer Cres",
    "sg:city":"Winnipeg",
    "sg:classifiers":[
        {
            "category":"Building & Trades",
            "subcategory":"Electrical",
            "type":"Services"
        }
    ],
    "sg:phone":"+1 204 669 3176",
    "sg:postcode":"R2K 3V2",
    "sg:province":"MB",
    "sg:tags":[
        "electric",
        "contractor"
    ],
    "wof:name":"Labiuk Installations",
    "wof:placetype":"venue"
},
  "geometry": {"coordinates":[-97.0694656372,49.9151268005],"type":"Point"}
}