{
  "type": "Feature",
  "properties": {
    "addr:full":"RR 2 Gabriola BC V0R 1X2",
    "addr:postcode":"v0r 1x2",
    "addr:street":"Rr 2",
    "iso:country":"CA",
    "sg:address":"RR 2",
    "sg:city":"Gabriola",
    "sg:classifiers":[
        {
            "category":"Home & Garden",
            "subcategory":"Carpets & Floor Coverings",
            "type":"Retail Goods"
        }
    ],
    "sg:phone":"+1 250 247 9044",
    "sg:postcode":"V0R 1X2",
    "sg:province":"BC",
    "wof:name":"Island Hardwood Renew",
    "wof:placetype":"venue"
},
  "geometry": {"coordinates":[-123.82800293,49.1863479614],"type":"Point"}
}