{
  "type": "Feature",
  "properties": {
    "addr:full":"RR 3 Sutton West ON L0E 1R0",
    "addr:postcode":"l0e 1r0",
    "addr:street":"Rr 3",
    "iso:country":"CA",
    "sg:address":"RR 3",
    "sg:city":"Sutton West",
    "sg:classifiers":[
        {
            "category":"Shopping",
            "subcategory":"Used Merchandise",
            "type":"Retail Goods"
        }
    ],
    "sg:phone":"+1 905 722 6353",
    "sg:postcode":"L0E 1R0",
    "sg:province":"ON",
    "sg:tags":[
        "antique"
    ],
    "wof:name":"J B's Bargain Barn",
    "wof:placetype":"venue"
},
  "geometry": {"coordinates":[-79.361237,44.304867],"type":"Point"}
}