{
  "type": "Feature",
  "properties": {
    "addr:full":"1825 Fort St Victoria BC V8R 1J6",
    "addr:housenumber":"1825",
    "addr:postcode":"v8r 1j6",
    "addr:street":"Fort St",
    "iso:country":"CA",
    "sg:address":"1825 Fort St",
    "sg:city":"Victoria",
    "sg:classifiers":[
        {
            "category":"Health Services",
            "subcategory":"Chiropractor",
            "type":"Services"
        }
    ],
    "sg:phone":"+1 250 477 1133",
    "sg:postcode":"V8R 1J6",
    "sg:province":"BC",
    "wof:name":"Curran, Barry J DC",
    "wof:placetype":"venue"
},
  "geometry": {"coordinates":[-123.32943725600001,48.4296379089],"type":"Point"}
}