{
  "type": "Feature",
  "properties": {
    "addr:full":"265 Peter St Port Hope ON L1A 3Z4",
    "addr:housenumber":"265",
    "addr:postcode":"l1a 3z4",
    "addr:street":"Peter St",
    "iso:country":"CA",
    "sg:address":"265 Peter St",
    "sg:city":"Port Hope",
    "sg:classifiers":[
        {
            "category":"Autos & Motor Vehicles",
            "subcategory":"Automobile Sales",
            "type":"Retail Goods"
        }
    ],
    "sg:phone":"+1 905 885 4573",
    "sg:postcode":"L1A 3Z4",
    "sg:province":"ON",
    "sg:tags":[
        "car",
        "dealer"
    ],
    "wof:name":"Quantrill Chev Olds Cad",
    "wof:placetype":"venue"
},
  "geometry": {"coordinates":[-78.27011899999999,43.954617],"type":"Point"}
}