{
  "type": "Feature",
  "properties": {
    "addr:full":"200 Centre Ave Castlegar BC V1N 3B9",
    "addr:housenumber":"200",
    "addr:postcode":"v1n 3b9",
    "addr:street":"Centre Ave",
    "iso:country":"CA",
    "sg:address":"200 Centre Ave",
    "sg:city":"Castlegar",
    "sg:classifiers":[
        {
            "category":"Education",
            "subcategory":"School",
            "type":"Public Place"
        }
    ],
    "sg:phone":"+1 250 365 7201",
    "sg:postcode":"V1N 3B9",
    "sg:province":"BC",
    "wof:name":"Blueberry Creek Community Schl",
    "wof:placetype":"venue"
},
  "geometry": {"coordinates":[-117.65418243400001,49.2962532043],"type":"Point"}
}