{
  "type": "Feature",
  "properties": {
    "iso:country":"CA",
    "sg:address":"371 Wellington Rd",
    "sg:city":"London",
    "sg:classifiers":[
        {
            "category":"Shopping",
            "subcategory":"Clothing, Apparel, & Fashions",
            "type":"Retail Goods"
        }
    ],
    "sg:phone":"+1 519 668 3334",
    "sg:postcode":"N6C 4P9",
    "sg:province":"ON",
    "sg:tags":[
        "lingerie"
    ],
    "wof:name":"Stag Shop Inc",
    "wof:placetype":"venue"
},
  "geometry": {"coordinates":[-81.231056,42.960964],"type":"Point"}
}