{
  "type": "Feature",
  "properties": {
    "addr:full":"Calgary AB T2P 2W3",
    "addr:postcode":"t2p 2w3",
    "iso:country":"CA",
    "sg:city":"Calgary",
    "sg:classifiers":[
        {
            "category":"Personal",
            "subcategory":"Beauty Salon",
            "type":"Services"
        }
    ],
    "sg:phone":"+1 403 266 1688",
    "sg:postcode":"T2P 2W3",
    "sg:province":"AB",
    "wof:name":"Hits Hair & Skincare Inc",
    "wof:placetype":"venue"
},
  "geometry": {"coordinates":[-114.066147,51.046406],"type":"Point"}
}