{
  "type": "Feature",
  "properties": {
    "addr:full":"West Vancouver BC V7T 1A1",
    "addr:postcode":"v7t 1a1",
    "iso:country":"CA",
    "sg:city":"West Vancouver",
    "sg:classifiers":[
        {
            "category":"Restaurant",
            "type":"Food & Drink"
        }
    ],
    "sg:phone":"+1 604 926 3462",
    "sg:postcode":"V7T 1A1",
    "sg:province":"BC",
    "sg:tags":[
        "delicatessen",
        "sausage"
    ],
    "wof:name":"Black Forest Delicatessen",
    "wof:placetype":"venue"
},
  "geometry": {"coordinates":[-123.13671100000001,49.324024],"type":"Point"}
}