{
  "type": "Feature",
  "properties": {
    "addr:full":"411 Cumberland St N Thunder Bay ON P7A 4P9",
    "addr:housenumber":"411",
    "addr:postcode":"p7a 4p9",
    "addr:street":"Cumberland St N",
    "iso:country":"CA",
    "sg:address":"411 Cumberland St N",
    "sg:city":"Thunder Bay",
    "sg:classifiers":[
        {
            "category":"Autos & Motor Vehicles",
            "subcategory":"Automobile Sales",
            "type":"Retail Goods"
        }
    ],
    "sg:phone":"+1 807 345 3733",
    "sg:postcode":"P7A 4P9",
    "sg:province":"ON",
    "sg:tags":[
        "car",
        "dealer"
    ],
    "wof:name":"Courtesy Auto Sales",
    "wof:placetype":"venue"
},
  "geometry": {"coordinates":[-89.2011642456,48.4469490051],"type":"Point"}
}