{
  "type": "Feature",
  "properties": {
    "addr:full":"90 Wellesley St W Toronto ON M5S 1C5",
    "addr:housenumber":"90",
    "addr:postcode":"m5s 1c5",
    "addr:street":"Wellesley St W",
    "iso:country":"CA",
    "sg:address":"90 Wellesley St W",
    "sg:city":"Toronto",
    "sg:classifiers":[
        {
            "category":"Education",
            "subcategory":"College",
            "type":"Public Place"
        }
    ],
    "sg:phone":"+1 416 924 2121",
    "sg:postcode":"M5S 1C5",
    "sg:province":"ON",
    "sg:tags":[
        "academic",
        "school"
    ],
    "wof:name":"St Josephs College",
    "wof:placetype":"venue"
},
  "geometry": {"coordinates":[-79.3898468018,43.6638908386],"type":"Point"}
}