{
  "type": "Feature",
  "properties": {
    "iso:country":"CA",
    "sg:address":"PO Box 1034",
    "sg:city":"Grimshaw",
    "sg:classifiers":[
        {
            "category":"Wholesale",
            "subcategory":"Farm Supplies",
            "type":"Manufacturing & Wholesale Goods"
        }
    ],
    "sg:phone":"+1 780 332 2355",
    "sg:postcode":"T0H 1W0",
    "sg:province":"AB",
    "sg:tags":[
        "fertilizer"
    ],
    "wof:name":"Agrium Inc",
    "wof:placetype":"venue"
},
  "geometry": {"coordinates":[-117.610466003,56.1913795471],"type":"Point"}
}