{
  "type": "Feature",
  "properties": {
    "iso:country":"CA",
    "sg:city":"Regina",
    "sg:classifiers":[
        {
            "category":"Shopping",
            "subcategory":"Clothing, Apparel, & Fashions",
            "type":"Retail Goods"
        }
    ],
    "sg:phone":"+1 306 584 2655",
    "sg:postcode":"S4S 6H7",
    "sg:province":"SK",
    "wof:name":"Tan Jay",
    "wof:placetype":"venue"
},
  "geometry": {"coordinates":[-104.623093,50.404617],"type":"Point"}
}