{
  "type": "Feature",
  "properties": {
    "iso:country":"CA",
    "sg:address":"2411 Vermilion St NE",
    "sg:city":"Calgary",
    "sg:classifiers":[
        {
            "category":"Education",
            "subcategory":"School",
            "type":"Public Place"
        }
    ],
    "sg:phone":"+1 403 777 6000",
    "sg:postcode":"T2E 6J3",
    "sg:province":"AB",
    "wof:name":"Vista Heights Elementary Schl",
    "wof:placetype":"venue"
},
  "geometry": {"coordinates":[-114.016418457,51.0733718872],"type":"Point"}
}