{
  "type": "Feature",
  "properties": {
    "addr:full":"372 Stephen St Morden MB R6M 1T5",
    "addr:housenumber":"372",
    "addr:postcode":"r6m 1t5",
    "addr:street":"Stephen St",
    "iso:country":"CA",
    "sg:address":"372 Stephen St",
    "sg:city":"Morden",
    "sg:classifiers":[
        {
            "category":"Food & Beverages",
            "subcategory":"Specialty",
            "type":"Retail Goods"
        }
    ],
    "sg:phone":"+1 204 822 6707",
    "sg:postcode":"R6M 1T5",
    "sg:province":"MB",
    "sg:tags":[
        "health",
        "diet"
    ],
    "wof:name":"Feelin' Good Health Products",
    "wof:placetype":"venue"
},
  "geometry": {"coordinates":[-98.102554,49.189747],"type":"Point"}
}