{
  "type": "Feature",
  "properties": {
    "iso:country":"CA",
    "sg:city":"London",
    "sg:classifiers":[
        {
            "category":"Building & Trades",
            "subcategory":"Construction",
            "type":"Services"
        }
    ],
    "sg:phone":"+1 519 451 8313",
    "sg:postcode":"N6A 5C7",
    "sg:province":"ON",
    "sg:tags":[
        "painter"
    ],
    "wof:name":"College Pro Painters Ltd",
    "wof:placetype":"venue"
},
  "geometry": {"coordinates":[-81.252251,42.993977],"type":"Point"}
}