{
  "type": "Feature",
  "properties": {
    "addr:full":"Woodbridge ON L4L 8B7",
    "addr:postcode":"l4l 8b7",
    "iso:country":"CA",
    "sg:city":"Woodbridge",
    "sg:classifiers":[
        {
            "category":"Shopping",
            "subcategory":"Clothing, Apparel, & Fashions",
            "type":"Retail Goods"
        }
    ],
    "sg:phone":"+1 905 851 9600",
    "sg:postcode":"L4L 8B7",
    "sg:province":"ON",
    "sg:tags":[
        "infant",
        "wear"
    ],
    "wof:name":"Botteghino For Children",
    "wof:placetype":"venue"
},
  "geometry": {"coordinates":[-79.54734000000001,43.787727],"type":"Point"}
}