{
  "type": "Feature",
  "properties": {
    "addr:full":"2121 Rue Belanger Mascouche QC J7K 3C2",
    "addr:housenumber":"2121",
    "addr:postcode":"j7k 3c2",
    "addr:street":"Rue Belanger",
    "iso:country":"CA",
    "sg:address":"2121 Rue Belanger",
    "sg:city":"Mascouche",
    "sg:classifiers":[
        {
            "category":"Arts & Performance",
            "subcategory":"Theater",
            "type":"Entertainment"
        }
    ],
    "sg:phone":"+1 514 994 1847",
    "sg:postcode":"J7K 3C2",
    "sg:province":"QC",
    "sg:tags":[
        "clown"
    ],
    "wof:name":"Clown Fifi",
    "wof:placetype":"venue"
},
  "geometry": {"coordinates":[-73.630928,45.779427],"type":"Point"}
}