{
  "type": "Feature",
  "properties": {
    "addr:full":"3907 15th Ave Prince George BC V2N 1A5",
    "addr:housenumber":"3907",
    "addr:postcode":"v2n 1a5",
    "addr:street":"15Th Ave",
    "iso:country":"CA",
    "sg:address":"3907 15th Ave",
    "sg:city":"Prince George",
    "sg:classifiers":[
        {
            "category":"Home & Garden",
            "subcategory":"Furniture",
            "type":"Retail Goods"
        }
    ],
    "sg:phone":"+1 250 564 7333",
    "sg:postcode":"V2N 1A5",
    "sg:province":"BC",
    "wof:name":"Factory Direct Furniture",
    "wof:placetype":"venue"
},
  "geometry": {"coordinates":[-122.791985,53.910141],"type":"Point"}
}