{
  "type": "Feature",
  "properties": {
    "iso:country":"CA",
    "sg:address":"628 Arvin Ave",
    "sg:city":"Stoney Creek",
    "sg:classifiers":[
        {
            "category":"Wholesale",
            "subcategory":"Machinery & Supplies",
            "type":"Manufacturing & Wholesale Goods"
        }
    ],
    "sg:phone":"+1 905 643 4105",
    "sg:postcode":"L8E 5P1",
    "sg:province":"ON",
    "sg:tags":[
        "equipment",
        "material",
        "truck",
        "handling"
    ],
    "wof:name":"Yale Industrial Trucks Ontario",
    "wof:placetype":"venue"
},
  "geometry": {"coordinates":[-79.7010726929,43.2258605957],"type":"Point"}
}