{
  "type": "Feature",
  "properties": {
    "addr:full":"82 Colin Ave Toronto ON M5P 2C2",
    "addr:housenumber":"82",
    "addr:postcode":"m5p 2c2",
    "addr:street":"Colin Ave",
    "iso:country":"CA",
    "sg:address":"82 Colin Ave",
    "sg:city":"Toronto",
    "sg:classifiers":[
        {
            "category":"Professional",
            "subcategory":"Business Services",
            "type":"Services"
        }
    ],
    "sg:phone":"+1 416 485 2856",
    "sg:postcode":"M5P 2C2",
    "sg:province":"ON",
    "sg:tags":[
        "interior",
        "consultant",
        "design",
        "decorator"
    ],
    "wof:name":"Linda Crammond Interiors Ltd",
    "wof:placetype":"venue"
},
  "geometry": {"coordinates":[-79.400826,43.70113],"type":"Point"}
}