{
  "type": "Feature",
  "properties": {
    "addr:full":"Scarborough ON M1R 2J7",
    "addr:postcode":"m1r 2j7",
    "iso:country":"CA",
    "sg:city":"Scarborough",
    "sg:classifiers":[
        {
            "category":"Health Services",
            "subcategory":"Doctor",
            "type":"Services"
        }
    ],
    "sg:phone":"+1 416 449 8331",
    "sg:postcode":"M1R 2J7",
    "sg:province":"ON",
    "sg:tags":[
        "clinic"
    ],
    "wof:name":"Maryvale Denture Clinic",
    "wof:placetype":"venue"
},
  "geometry": {"coordinates":[-79.310081,43.759312],"type":"Point"}
}