{
  "type": "Feature",
  "properties": {
    "iso:country":"CA",
    "sg:city":"Ottawa",
    "sg:classifiers":[
        {
            "category":"Autos & Motor Vehicles",
            "subcategory":"Auto Supplies",
            "type":"Retail Goods"
        }
    ],
    "sg:phone":"+1 613 737 6521",
    "sg:postcode":"K1B 4W5",
    "sg:province":"ON",
    "sg:tags":[
        "automobile",
        "parts"
    ],
    "wof:name":"Ats Automotive",
    "wof:placetype":"venue"
},
  "geometry": {"coordinates":[-75.6098861694,45.3951148987],"type":"Point"}
}