{
  "type": "Feature",
  "properties": {
    "iso:country":"CA",
    "sg:city":"Burnaby",
    "sg:classifiers":[
        {
            "category":"Shopping",
            "type":"Retail Goods"
        }
    ],
    "sg:phone":"+1 604 681 9665",
    "sg:postcode":"V5C 6P3",
    "sg:province":"BC",
    "sg:tags":[
        "religious"
    ],
    "wof:name":"Lotus Pond Religious Ctr Inc",
    "wof:placetype":"venue"
},
  "geometry": {"coordinates":[-123.020591736,49.2640800476],"type":"Point"}
}