{
  "type": "Feature",
  "properties": {
    "addr:full":"Ottawa ON K1Z 8N8",
    "addr:postcode":"k1z 8n8",
    "iso:country":"CA",
    "sg:city":"Ottawa",
    "sg:classifiers":[
        {
            "category":"Professional",
            "subcategory":"Lawyer & Legal Services",
            "type":"Services"
        }
    ],
    "sg:phone":"+1 613 761 1000",
    "sg:postcode":"K1Z 8N8",
    "sg:province":"ON",
    "sg:tags":[
        "attorney"
    ],
    "wof:name":"Nahas, J Taffy",
    "wof:placetype":"venue"
},
  "geometry": {"coordinates":[-75.7348327637,45.3860092163],"type":"Point"}
}