{
  "type": "Feature",
  "properties": {
    "addr:full":"10929 23 Ave NW # 101 Edmonton AB T6J 7B9",
    "addr:housenumber":"10929",
    "addr:postcode":"t6j 7b9",
    "addr:street":"23 Ave Nw # 101",
    "iso:country":"CA",
    "sg:address":"10929 23 Ave NW # 101",
    "sg:city":"Edmonton",
    "sg:classifiers":[
        {
            "category":"Restaurant",
            "type":"Food & Drink"
        }
    ],
    "sg:phone":"+1 780 413 4140",
    "sg:postcode":"T6J 7B9",
    "sg:province":"AB",
    "wof:name":"Subway Sandwiches & Salads",
    "wof:placetype":"venue"
},
  "geometry": {"coordinates":[-113.50985,53.453583],"type":"Point"}
}