{
  "type": "Feature",
  "properties": {
    "addr:full":"3779 Sexsmith Rd # 1168 Richmond BC V6X 3Z9",
    "addr:housenumber":"3779",
    "addr:postcode":"v6x 3z9",
    "addr:street":"Sexsmith Rd # 1168",
    "iso:country":"CA",
    "sg:address":"3779 Sexsmith Rd # 1168",
    "sg:city":"Richmond",
    "sg:classifiers":[
        {
            "category":"Wholesale",
            "subcategory":"Seafood",
            "type":"Manufacturing & Wholesale Goods"
        }
    ],
    "sg:phone":"+1 604 207 9268",
    "sg:postcode":"V6X 3Z9",
    "sg:province":"BC",
    "wof:name":"Daily Seafood Supply Ltd",
    "wof:placetype":"venue"
},
  "geometry": {"coordinates":[-123.128304,49.185127],"type":"Point"}
}