{
  "type": "Feature",
  "properties": {
    "addr:full":"Dartmouth NS B3B 1N4",
    "addr:postcode":"b3b 1n4",
    "iso:country":"CA",
    "sg:city":"Dartmouth",
    "sg:classifiers":[
        {
            "category":"Retail",
            "subcategory":"Laundry & Dry Cleaning",
            "type":"Services"
        }
    ],
    "sg:phone":"+1 902 468 1901",
    "sg:postcode":"B3B 1N4",
    "sg:province":"NS",
    "sg:tags":[
        "cleaners",
        "upholstery",
        "rug",
        "carpet"
    ],
    "wof:name":"Sears Carpet & Upholstery Care",
    "wof:placetype":"venue"
},
  "geometry": {"coordinates":[-63.602688,44.714542],"type":"Point"}
}