{
  "type": "Feature",
  "properties": {
    "iso:country":"CA",
    "sg:address":"108 S Railway Ave",
    "sg:city":"Deloraine",
    "sg:classifiers":[
        {
            "category":"Personal",
            "subcategory":"Beauty Salon",
            "type":"Services"
        }
    ],
    "sg:phone":"+1 204 747 2167",
    "sg:postcode":"R0M 0M0",
    "sg:province":"MB",
    "wof:name":"Vickie's Cuts N' Curls",
    "wof:placetype":"venue"
},
  "geometry": {"coordinates":[-100.49888610799999,49.192363739],"type":"Point"}
}