{
  "type": "Feature",
  "properties": {
    "addr:full":"11692 Hurontario St Brampton ON L7A 1E6",
    "addr:housenumber":"11692",
    "addr:postcode":"l7a 1e6",
    "addr:street":"Hurontario St",
    "iso:country":"CA",
    "sg:address":"11692 Hurontario St",
    "sg:city":"Brampton",
    "sg:classifiers":[
        {
            "category":"Government",
            "subcategory":"Office",
            "type":"Public Place"
        }
    ],
    "sg:phone":"+1 905 846 1228",
    "sg:postcode":"L7A 1E6",
    "sg:province":"ON",
    "sg:tags":[
        "village"
    ],
    "wof:name":"Brampton Snelgrove Community",
    "wof:placetype":"venue"
},
  "geometry": {"coordinates":[-79.8220672607,43.7314338684],"type":"Point"}
}