{
  "type": "Feature",
  "properties": {
    "iso:country":"CA",
    "sg:address":"34 Hobart Dr",
    "sg:city":"North York",
    "sg:classifiers":[
        {
            "category":"Building & Trades",
            "subcategory":"Electrical",
            "type":"Services"
        }
    ],
    "sg:phone":"+1 416 756 9054",
    "sg:postcode":"M2J 3J7",
    "sg:province":"ON",
    "sg:tags":[
        "electric",
        "contractor"
    ],
    "wof:name":"Naito Electric",
    "wof:placetype":"venue"
},
  "geometry": {"coordinates":[-79.3498382568,43.7884178162],"type":"Point"}
}