{
  "type": "Feature",
  "properties": {
    "addr:full":"1871 Market St # 216 Halifax NS B3J 3S1",
    "addr:housenumber":"1871",
    "addr:postcode":"ns b3j 3s1",
    "addr:street":"Market St # 216",
    "iso:country":"CA",
    "sg:address":"1871 Market St # 216",
    "sg:city":"Halifax",
    "sg:classifiers":[
        {
            "category":"Social Services",
            "type":"Services"
        }
    ],
    "sg:phone":"+1 902 420 1355",
    "sg:postcode":"B3J 3S1",
    "sg:province":"NS",
    "sg:tags":[
        "stress",
        "management"
    ],
    "wof:name":"City Centre Ministry",
    "wof:placetype":"venue"
},
  "geometry": {"coordinates":[-63.5771713257,44.6494636536],"type":"Point"}
}