{
  "type": "Feature",
  "properties": {
    "addr:full":"1111 Elgin St W #C2 Cobourg ON K9A 5H7",
    "addr:housenumber":"1111",
    "addr:postcode":"k9a 5h7",
    "addr:street":"Elgin St W # C2",
    "iso:country":"CA",
    "sg:address":"1111 Elgin St W #C2",
    "sg:city":"Cobourg",
    "sg:classifiers":[
        {
            "category":"Shopping",
            "subcategory":"Clothing, Apparel, & Fashions",
            "type":"Retail Goods"
        }
    ],
    "sg:phone":"+1 905 372 8994",
    "sg:postcode":"K9A 5H7",
    "sg:province":"ON",
    "wof:name":"John Roberts",
    "wof:placetype":"venue"
},
  "geometry": {"coordinates":[-78.202286,43.970566],"type":"Point"}
}