{
  "type": "Feature",
  "properties": {
    "iso:country":"CA",
    "sg:address":"479 Boul Saint-Jude S",
    "sg:city":"Alma",
    "sg:classifiers":[
        {
            "category":"Health Services",
            "subcategory":"Doctor",
            "type":"Services"
        }
    ],
    "sg:phone":"+1 418 668 3351",
    "sg:postcode":"G8B 3J7",
    "sg:province":"QC",
    "sg:tags":[
        "clinic"
    ],
    "wof:name":"Clinique Medicale St-Jude",
    "wof:placetype":"venue"
},
  "geometry": {"coordinates":[-71.6590957642,48.5457267761],"type":"Point"}
}