{
  "type": "Feature",
  "properties": {
    "addr:full":"170 Memorial Ave # 1 Orillia ON L3V 7M9",
    "addr:housenumber":"170",
    "addr:postcode":"l3v 7m9",
    "addr:street":"Memorial Ave # 1",
    "iso:country":"CA",
    "sg:address":"170 Memorial Ave # 1",
    "sg:city":"Orillia",
    "sg:classifiers":[
        {
            "category":"Professional",
            "subcategory":"Printing & Photocopies",
            "type":"Services"
        }
    ],
    "sg:phone":"+1 705 327 2131",
    "sg:postcode":"L3V 7M9",
    "sg:province":"ON",
    "sg:tags":[
        "courier",
        "copying",
        "duplicating"
    ],
    "wof:name":"Express Business Svc",
    "wof:placetype":"venue"
},
  "geometry": {"coordinates":[-79.4247207642,44.5996437073],"type":"Point"}
}