{
  "type": "Feature",
  "properties": {
    "addr:full":"1031 Davie St Vancouver BC V6E 1M5",
    "addr:housenumber":"1031",
    "addr:postcode":"v6e 1m5",
    "addr:street":"Davie St",
    "iso:country":"CA",
    "sg:address":"1031 Davie St",
    "sg:city":"Vancouver",
    "sg:classifiers":[
        {
            "category":"Restaurant",
            "type":"Food & Drink"
        }
    ],
    "sg:phone":"+1 604 682 3683",
    "sg:postcode":"V6E 1M5",
    "sg:province":"BC",
    "wof:name":"Joe's Grill",
    "wof:placetype":"venue"
},
  "geometry": {"coordinates":[-123.12975311300001,49.2796287537],"type":"Point"}
}