{
  "type": "Feature",
  "properties": {
    "addr:full":"Saint-Laurent QC H4R 1W4",
    "addr:postcode":"h4r 1w4",
    "iso:country":"CA",
    "sg:city":"Saint-Laurent",
    "sg:classifiers":[
        {
            "category":"Professional",
            "subcategory":"Art Services",
            "type":"Services"
        }
    ],
    "sg:phone":"+1 514 384 8433",
    "sg:postcode":"H4R 1W4",
    "sg:province":"QC",
    "sg:tags":[
        "publisher",
        "graphic",
        "designer"
    ],
    "wof:name":"Point Multi Media",
    "wof:placetype":"venue"
},
  "geometry": {"coordinates":[-73.714553833,45.4961738586],"type":"Point"}
}