{
  "type": "Feature",
  "properties": {
    "addr:full":"2755 Av Van Horne Montreal QC H3S 1P6",
    "addr:housenumber":"2755",
    "addr:postcode":"h3s 1p6",
    "addr:street":"Av Van Horne",
    "iso:country":"CA",
    "sg:address":"2755 Av Van Horne",
    "sg:city":"Montreal",
    "sg:classifiers":[
        {
            "category":"Health Services",
            "subcategory":"Optometrist",
            "type":"Services"
        }
    ],
    "sg:phone":"+1 514 731 8668",
    "sg:postcode":"H3S 1P6",
    "sg:province":"QC",
    "wof:name":"Centre DE Vision Wilderton",
    "wof:placetype":"venue"
},
  "geometry": {"coordinates":[-73.624961853,45.5087738037],"type":"Point"}
}