{
  "type": "Feature",
  "properties": {
    "addr:full":"94 Principale Rue Yamaska QC J0G 1W0",
    "addr:housenumber":"94",
    "addr:postcode":"j0g 1w0",
    "addr:street":"Principale Rue Yamaska",
    "iso:country":"CA",
    "sg:address":"94 Principale Rue",
    "sg:city":"Yamaska",
    "sg:classifiers":[
        {
            "category":"Restaurant",
            "type":"Food & Drink"
        }
    ],
    "sg:phone":"+1 450 789 2081",
    "sg:postcode":"J0G 1W0",
    "sg:province":"QC",
    "sg:tags":[
        "video",
        "disc",
        "tape"
    ],
    "wof:name":"Cantine Yamaska Enr",
    "wof:placetype":"venue"
},
  "geometry": {"coordinates":[-72.9142379761,46.0051956177],"type":"Point"}
}