{
  "type": "Feature",
  "properties": {
    "addr:full":"11 Cedarbrae Lane Halifax NS B3M 3M4",
    "addr:housenumber":"11",
    "addr:postcode":"b3m 3m4",
    "addr:street":"Cedarbrae Lane",
    "iso:country":"CA",
    "sg:address":"11 Cedarbrae Lane",
    "sg:city":"Halifax",
    "sg:classifiers":[
        {
            "category":"Shopping",
            "type":"Retail Goods"
        }
    ],
    "sg:phone":"+1 902 445 2687",
    "sg:postcode":"B3M 3M4",
    "sg:province":"NS",
    "sg:tags":[
        "cosmetic",
        "perfume"
    ],
    "wof:name":"Mary Kay Cosmetics",
    "wof:placetype":"venue"
},
  "geometry": {"coordinates":[-63.6484642029,44.6640510559],"type":"Point"}
}