{
  "type": "Feature",
  "properties": {
    "iso:country":"CA",
    "sg:address":"1527 Tie Lake Loop Rd",
    "sg:city":"Jaffray",
    "sg:classifiers":[
        {
            "category":"Retail",
            "subcategory":"Auto Repair",
            "type":"Services"
        }
    ],
    "sg:phone":"+1 250 429 3413",
    "sg:postcode":"V0B 1T0",
    "sg:province":"BC",
    "sg:tags":[
        "body",
        "automobile",
        "painting"
    ],
    "wof:name":"Kmb Autobody",
    "wof:placetype":"venue"
},
  "geometry": {"coordinates":[-115.297241,49.37674],"type":"Point"}
}