{
  "type": "Feature",
  "properties": {
    "addr:full":"6438 Bay St West Vancouver BC V7W 2H1",
    "addr:housenumber":"6438",
    "addr:postcode":"v7w 2h1",
    "addr:street":"Bay St",
    "iso:country":"CA",
    "sg:address":"6438 Bay St",
    "sg:city":"West Vancouver",
    "sg:classifiers":[
        {
            "category":"Professional",
            "subcategory":"Lawyer & Legal Services",
            "type":"Services"
        }
    ],
    "sg:phone":"+1 604 921 1122",
    "sg:postcode":"V7W 2H1",
    "sg:province":"BC",
    "sg:tags":[
        "attorney"
    ],
    "wof:name":"Spears, K Joseph",
    "wof:placetype":"venue"
},
  "geometry": {"coordinates":[-123.275131226,49.3747673035],"type":"Point"}
}