{
  "type": "Feature",
  "properties": {
    "addr:full":"Andrew AB T0B 0C0",
    "addr:postcode":"t0b 0c0",
    "iso:country":"CA",
    "sg:city":"Andrew",
    "sg:classifiers":[
        {
            "category":"Food & Beverages",
            "subcategory":"Liquor & Beverages",
            "type":"Retail Goods"
        }
    ],
    "sg:phone":"+1 780 365 2373",
    "sg:postcode":"T0B 0C0",
    "sg:province":"AB",
    "sg:tags":[
        "store"
    ],
    "wof:name":"Andrew Liquor Svc",
    "wof:placetype":"venue"
},
  "geometry": {"coordinates":[-112.334419251,53.8787689209],"type":"Point"}
}