{
  "type": "Feature",
  "properties": {
    "addr:full":"1361 Ch Lucien-Lefrancois L'Ange Gardien QC G0A 2K0",
    "addr:housenumber":"1361",
    "addr:postcode":"g0a 2k0",
    "addr:street":"Ch Lucien-Lefrancois",
    "iso:country":"CA",
    "sg:address":"1361 Ch Lucien-Lefrancois",
    "sg:city":"L'Ange Gardien",
    "sg:classifiers":[
        {
            "category":"Food & Beverages",
            "subcategory":"Groceries & Convenience Stores",
            "type":"Retail Goods"
        }
    ],
    "sg:phone":"+1 418 822 4905",
    "sg:postcode":"G0A 2K0",
    "sg:province":"QC",
    "wof:name":"Accommodation Aquarelle",
    "wof:placetype":"venue"
},
  "geometry": {"coordinates":[-71.126167,46.957058],"type":"Point"}
}