{
  "type": "Feature",
  "properties": {
    "addr:full":"2711 Hwy 3 Creston BC V0B 1G1",
    "addr:housenumber":"2711",
    "addr:postcode":"bc v0b 1g1",
    "addr:street":"Hwy 3",
    "iso:country":"CA",
    "sg:address":"2711 Hwy 3",
    "sg:city":"Creston",
    "sg:classifiers":[
        {
            "category":"Travel",
            "subcategory":"Hotels & Motels",
            "type":"Entertainment"
        }
    ],
    "sg:phone":"+1 250 428 4009",
    "sg:postcode":"V0B 1G1",
    "sg:province":"BC",
    "wof:name":"Skimmerhorn Inn",
    "wof:placetype":"venue"
},
  "geometry": {"coordinates":[-116.492065,49.095379],"type":"Point"}
}