{
  "type": "Feature",
  "properties": {
    "iso:country":"CA",
    "sg:city":"Brampton",
    "sg:classifiers":[
        {
            "category":"Building & Trades",
            "subcategory":"Construction",
            "type":"Services"
        }
    ],
    "sg:phone":"+1 905 793 7920",
    "sg:postcode":"L6S 5Z4",
    "sg:province":"ON",
    "sg:tags":[
        "caulking",
        "waterproofing",
        "contractor"
    ],
    "wof:name":"Ernie Contracting",
    "wof:placetype":"venue"
},
  "geometry": {"coordinates":[-79.70519256590001,43.7562332153],"type":"Point"}
}