{
  "type": "Feature",
  "properties": {
    "addr:full":"Chiblow Lake Rd Iron Bridge ON P0R 1H0",
    "addr:postcode":"p0r 1h0",
    "addr:street":"Chiblow Lake Rd",
    "iso:country":"CA",
    "sg:address":"Chiblow Lake Rd",
    "sg:city":"Iron Bridge",
    "sg:classifiers":[
        {
            "category":"Arena",
            "subcategory":"Sports Club",
            "type":"Entertainment"
        }
    ],
    "sg:phone":"+1 705 843 2988",
    "sg:postcode":"P0R 1H0",
    "sg:province":"ON",
    "sg:tags":[
        "athletic",
        "fields",
        "stadium",
        "government"
    ],
    "wof:name":"Iron Bridge Arena",
    "wof:placetype":"venue"
},
  "geometry": {"coordinates":[-83.21807098390001,46.2803764343],"type":"Point"}
}