{
  "type": "Feature",
  "properties": {
    "addr:full":"Salt Spring Island BC V8K 2V4",
    "addr:postcode":"v8k 2v4",
    "iso:country":"CA",
    "sg:city":"Salt Spring Island",
    "sg:classifiers":[
        {
            "category":"Professional",
            "subcategory":"Accounting & Tax Preparation",
            "type":"Services"
        }
    ],
    "sg:phone":"+1 250 537 2133",
    "sg:postcode":"V8K 2V4",
    "sg:province":"BC",
    "sg:tags":[
        "accountant"
    ],
    "wof:name":"Roland C Hanoski & CO",
    "wof:placetype":"venue"
},
  "geometry": {"coordinates":[-123.507942,48.859669],"type":"Point"}
}