{
  "type": "Feature",
  "properties": {
    "addr:full":"16 Dundas St W Trenton ON K8V 6V9",
    "addr:housenumber":"16",
    "addr:postcode":"k8v 6v9",
    "addr:street":"Dundas St W",
    "iso:country":"CA",
    "sg:address":"16 Dundas St W",
    "sg:city":"Trenton",
    "sg:classifiers":[
        {
            "category":"Government",
            "subcategory":"Office",
            "type":"Public Place"
        }
    ],
    "sg:phone":"+1 613 392 1387",
    "sg:postcode":"K8V 6V9",
    "sg:province":"ON",
    "sg:tags":[
        "village"
    ],
    "wof:name":"Hastings County Housing Prog",
    "wof:placetype":"venue"
},
  "geometry": {"coordinates":[-77.5758056641,44.1017112732],"type":"Point"}
}