{
  "type": "Feature",
  "properties": {
    "addr:full":"Vancouver BC V5R 5K6",
    "addr:postcode":"v5r 5k6",
    "iso:country":"CA",
    "sg:city":"Vancouver",
    "sg:classifiers":[
        {
            "category":"Restaurant",
            "type":"Food & Drink"
        }
    ],
    "sg:phone":"+1 604 437 6689",
    "sg:postcode":"V5R 5K6",
    "sg:province":"BC",
    "wof:name":"Frank's Restaurant",
    "wof:placetype":"venue"
},
  "geometry": {"coordinates":[-123.033821,49.233265],"type":"Point"}
}