{
  "type": "Feature",
  "properties": {
    "addr:full":"1166 Boul Cure-Labelle Laval QC H7V 2V5",
    "addr:housenumber":"1166",
    "addr:postcode":"h7v 2v5",
    "addr:street":"Boul Cure-Labelle",
    "iso:country":"CA",
    "sg:address":"1166 Boul Cure-Labelle",
    "sg:city":"Laval",
    "sg:classifiers":[
        {
            "category":"Shopping",
            "subcategory":"Florist",
            "type":"Retail Goods"
        }
    ],
    "sg:phone":"+1 450 687 2238",
    "sg:postcode":"H7V 2V5",
    "sg:province":"QC",
    "wof:name":"Decor Thai",
    "wof:placetype":"venue"
},
  "geometry": {"coordinates":[-73.75267791749999,45.544708252],"type":"Point"}
}