{
  "type": "Feature",
  "properties": {
    "addr:full":"525 Oshawa Blvd N Oshawa ON L1G 5T6",
    "addr:housenumber":"525",
    "addr:postcode":"l1g 5t6",
    "addr:street":"Oshawa Blvd N",
    "iso:country":"CA",
    "sg:address":"525 Oshawa Blvd N",
    "sg:city":"Oshawa",
    "sg:classifiers":[
        {
            "category":"Education",
            "subcategory":"School",
            "type":"Public Place"
        }
    ],
    "sg:phone":"+1 905 723 1231",
    "sg:postcode":"L1G 5T6",
    "sg:province":"ON",
    "wof:name":"Hillsdale Public School",
    "wof:placetype":"venue"
},
  "geometry": {"coordinates":[-78.8589248657,43.9147109985],"type":"Point"}
}