{
  "type": "Feature",
  "properties": {
    "iso:country":"CA",
    "sg:address":"48 Avalon Rd",
    "sg:city":"Winnipeg",
    "sg:classifiers":[
        {
            "category":"Retail",
            "subcategory":"Repair Shop",
            "type":"Services"
        }
    ],
    "sg:phone":"+1 204 254 1393",
    "sg:postcode":"R2M 2L3",
    "sg:province":"MB",
    "sg:tags":[
        "taxidermist"
    ],
    "wof:name":"Starodub's Freeze-Dry",
    "wof:placetype":"venue"
},
  "geometry": {"coordinates":[-97.1175537109,49.8281440735],"type":"Point"}
}