{
  "type": "Feature",
  "properties": {
    "iso:country":"CA",
    "sg:address":"11 Michael Ann Dr",
    "sg:city":"Coldwater",
    "sg:classifiers":[
        {
            "category":"Recreation",
            "type":"Entertainment"
        }
    ],
    "sg:phone":"+1 705 686 3322",
    "sg:postcode":"L0K 1E0",
    "sg:province":"ON",
    "sg:tags":[
        "government",
        "hall",
        "auditorium"
    ],
    "wof:name":"Coldwater Community Ctr",
    "wof:placetype":"venue"
},
  "geometry": {"coordinates":[-79.64436340330001,44.7102241516],"type":"Point"}
}