{
  "type": "Feature",
  "properties": {
    "addr:full":"795 Boul Saint-Charles Saint-Charles-DE-Drummond QC J2C 4Y7",
    "addr:housenumber":"795",
    "addr:postcode":"j2c 4y7",
    "addr:street":"Boul Saint-Charles",
    "iso:country":"CA",
    "sg:address":"795 Boul Saint-Charles",
    "sg:city":"Saint-Charles-DE-Drummond",
    "sg:classifiers":[
        {
            "category":"Retail",
            "subcategory":"Auto Repair",
            "type":"Services"
        }
    ],
    "sg:phone":"+1 819 472 7771",
    "sg:postcode":"J2C 4Y7",
    "sg:province":"QC",
    "sg:tags":[
        "wrecker"
    ],
    "wof:name":"Garage G Cote Inc",
    "wof:placetype":"venue"
},
  "geometry": {"coordinates":[-72.471413,45.896687],"type":"Point"}
}