{
  "type": "Feature",
  "properties": {
    "iso:country":"CA",
    "sg:address":"680 South Railway St SE",
    "sg:city":"Medicine Hat",
    "sg:classifiers":[
        {
            "category":"Home & Garden",
            "subcategory":"Garden Supply",
            "type":"Retail Goods"
        }
    ],
    "sg:phone":"+1 403 529 0037",
    "sg:postcode":"T1A 2W1",
    "sg:province":"AB",
    "sg:tags":[
        "engine",
        "lawn",
        "mower"
    ],
    "wof:name":"Ernie's Small Engine Repair",
    "wof:placetype":"venue"
},
  "geometry": {"coordinates":[-110.666290283,50.0326080322],"type":"Point"}
}