{
  "type": "Feature",
  "properties": {
    "addr:full":"Burnaby BC V5G 4W9",
    "addr:postcode":"v5g 4w9",
    "iso:country":"CA",
    "sg:city":"Burnaby",
    "sg:classifiers":[
        {
            "category":"Professional",
            "subcategory":"Computer Services",
            "type":"Services"
        }
    ],
    "sg:phone":"+1 604 685 3596",
    "sg:postcode":"V5G 4W9",
    "sg:province":"BC",
    "sg:tags":[
        "consultant",
        "designer"
    ],
    "wof:name":"Coregenesis Systems Inc",
    "wof:placetype":"venue"
},
  "geometry": {"coordinates":[-123.01056699999999,49.251217],"type":"Point"}
}