{
  "type": "Feature",
  "properties": {
    "addr:full":"104 Kenogami Dr Longlac ON P0T 2A0",
    "addr:housenumber":"104",
    "addr:postcode":"p0t 2a0",
    "addr:street":"Kenogami Dr",
    "iso:country":"CA",
    "sg:address":"104 Kenogami Dr",
    "sg:city":"Longlac",
    "sg:classifiers":[
        {
            "category":"Freight",
            "type":"Transportation"
        }
    ],
    "sg:phone":"+1 807 876 4302",
    "sg:postcode":"P0T 2A0",
    "sg:province":"ON",
    "sg:tags":[
        "trucking",
        "general",
        "contractor"
    ],
    "wof:name":"Fournier Trucking & Gravel",
    "wof:placetype":"venue"
},
  "geometry": {"coordinates":[-86.538948,49.777184],"type":"Point"}
}