{
  "type": "Feature",
  "properties": {
    "addr:full":"69 Ridgefield Cres Nepean ON K2H 6S8",
    "addr:housenumber":"69",
    "addr:postcode":"k2h 6s8",
    "addr:street":"Ridgefield Cres",
    "iso:country":"CA",
    "sg:address":"69 Ridgefield Cres",
    "sg:city":"Nepean",
    "sg:classifiers":[
        {
            "category":"Shopping",
            "subcategory":"Computers & Home Electronics",
            "type":"Retail Goods"
        }
    ],
    "sg:phone":"+1 613 820 8900",
    "sg:postcode":"K2H 6S8",
    "sg:province":"ON",
    "sg:tags":[
        "software"
    ],
    "wof:name":"Russ Staynor Consulting Corp",
    "wof:placetype":"venue"
},
  "geometry": {"coordinates":[-75.818359,45.316399],"type":"Point"}
}