{
  "type": "Feature",
  "properties": {
    "addr:full":"2019 Rue Lapierre Lasalle QC H8N 1B1",
    "addr:housenumber":"2019",
    "addr:postcode":"h8n 1b1",
    "addr:street":"Rue Lapierre",
    "iso:country":"CA",
    "sg:address":"2019 Rue Lapierre",
    "sg:city":"Lasalle",
    "sg:classifiers":[
        {
            "category":"Retail",
            "subcategory":"Repair Shop",
            "type":"Services"
        }
    ],
    "sg:phone":"+1 514 363 1222",
    "sg:postcode":"H8N 1B1",
    "sg:province":"QC",
    "sg:tags":[
        "cushion"
    ],
    "wof:name":"Ian Maxwell Inc",
    "wof:placetype":"venue"
},
  "geometry": {"coordinates":[-73.614059,45.43684],"type":"Point"}
}