{
  "type": "Feature",
  "properties": {
    "addr:full":"4333 Takla Rd Kelowna BC V1W 3C4",
    "addr:housenumber":"4333",
    "addr:postcode":"v1w 3c4",
    "addr:street":"Takla Rd",
    "iso:country":"CA",
    "sg:address":"4333 Takla Rd",
    "sg:city":"Kelowna",
    "sg:classifiers":[
        {
            "category":"Building & Trades",
            "subcategory":"Construction",
            "type":"Services"
        }
    ],
    "sg:phone":"+1 250 764 0214",
    "sg:postcode":"V1W 3C4",
    "sg:province":"BC",
    "sg:tags":[
        "contractor"
    ],
    "wof:name":"Shiloh Management",
    "wof:placetype":"venue"
},
  "geometry": {"coordinates":[-119.44933319099999,49.8269920349],"type":"Point"}
}