{
  "type": "Feature",
  "properties": {
    "iso:country":"CA",
    "sg:city":"Coquitlam",
    "sg:classifiers":[
        {
            "category":"Restaurant",
            "type":"Food & Drink"
        }
    ],
    "sg:phone":"+1 604 464 3611",
    "sg:postcode":"V3B 6J6",
    "sg:province":"BC",
    "wof:name":"C-Lovers Fish & Chips",
    "wof:placetype":"venue"
},
  "geometry": {"coordinates":[-122.794289,49.275261],"type":"Point"}
}