{
  "type": "Feature",
  "properties": {
    "addr:full":"378 Wilbrod St Ottawa ON K1N 6M8",
    "addr:housenumber":"378",
    "addr:postcode":"k1n 6m8",
    "addr:street":"Wilbrod St",
    "iso:country":"CA",
    "sg:address":"378 Wilbrod St",
    "sg:city":"Ottawa",
    "sg:classifiers":[
        {
            "category":"Shopping",
            "subcategory":"Computers & Home Electronics",
            "type":"Retail Goods"
        }
    ],
    "sg:phone":"+1 613 569 3354",
    "sg:postcode":"K1N 6M8",
    "sg:province":"ON",
    "sg:tags":[
        "software"
    ],
    "wof:name":"Simbit Corp",
    "wof:placetype":"venue"
},
  "geometry": {"coordinates":[-75.67821499999999,45.42844],"type":"Point"}
}