{
  "type": "Feature",
  "properties": {
    "addr:full":"Castlegar BC V1N 1H2",
    "addr:postcode":"v1n 1h2",
    "iso:country":"CA",
    "sg:city":"Castlegar",
    "sg:classifiers":[
        {
            "category":"Travel",
            "subcategory":"Hotels & Motels",
            "type":"Entertainment"
        }
    ],
    "sg:phone":"+1 250 365 3333",
    "sg:postcode":"V1N 1H2",
    "sg:province":"BC",
    "wof:name":"Castlegar Motel",
    "wof:placetype":"venue"
},
  "geometry": {"coordinates":[-117.66044599999999,49.309605],"type":"Point"}
}