{
  "type": "Feature",
  "properties": {
    "addr:full":"2655 Rue King O # 106 Sherbrooke QC J1L 2G4",
    "addr:housenumber":"2655",
    "addr:postcode":"j1l 2g4",
    "addr:street":"Rue King O # 106",
    "iso:country":"CA",
    "sg:address":"2655 Rue King O # 106",
    "sg:city":"Sherbrooke",
    "sg:classifiers":[
        {
            "category":"Restaurant",
            "type":"Food & Drink"
        }
    ],
    "sg:phone":"+1 819 822 0050",
    "sg:postcode":"J1L 2G4",
    "sg:province":"QC",
    "wof:name":"LA Cage Aux Sports",
    "wof:placetype":"venue"
},
  "geometry": {"coordinates":[-71.9379272461,45.3983955383],"type":"Point"}
}