{
  "type": "Feature",
  "properties": {
    "iso:country":"CA",
    "sg:city":"Bridgewater",
    "sg:classifiers":[
        {
            "category":"Shopping",
            "type":"Retail Goods"
        }
    ],
    "sg:phone":"+1 902 543 2275",
    "sg:postcode":"B4V 3A2",
    "sg:province":"NS",
    "sg:tags":[
        "pet",
        "food",
        "shop",
        "supply"
    ],
    "wof:name":"Claws 'N Paws Pet Shop",
    "wof:placetype":"venue"
},
  "geometry": {"coordinates":[-64.5143737793,44.3780212402],"type":"Point"}
}