{
  "type": "Feature",
  "properties": {
    "addr:full":"3030 Rue Baldwin Montreal QC H1L 5B7",
    "addr:housenumber":"3030",
    "addr:postcode":"h1l 5b7",
    "addr:street":"Rue Baldwin",
    "iso:country":"CA",
    "sg:address":"3030 Rue Baldwin",
    "sg:city":"Montreal",
    "sg:classifiers":[
        {
            "category":"Organizations",
            "subcategory":"Religious Organization",
            "type":"Services"
        }
    ],
    "sg:phone":"+1 514 351 5580",
    "sg:postcode":"H1L 5B7",
    "sg:province":"QC",
    "sg:tags":[
        "church"
    ],
    "wof:name":"St-George's United Church",
    "wof:placetype":"venue"
},
  "geometry": {"coordinates":[-73.5273895264,45.6020698547],"type":"Point"}
}