{
  "type": "Feature",
  "properties": {
    "addr:full":"307 Rue DE Villemure Saint-Jerome QC J7Z 5J5",
    "addr:housenumber":"307",
    "addr:postcode":"j7z 5j5",
    "addr:street":"Rue De Villemure Saint-Jerome",
    "iso:country":"CA",
    "sg:address":"307 Rue DE Villemure",
    "sg:city":"Saint-Jerome",
    "sg:classifiers":[
        {
            "category":"Personal",
            "subcategory":"Beauty Salon",
            "type":"Services"
        }
    ],
    "sg:phone":"+1 450 436 2711",
    "sg:postcode":"J7Z 5J5",
    "sg:province":"QC",
    "wof:name":"Inter-Coupe Coiffure",
    "wof:placetype":"venue"
},
  "geometry": {"coordinates":[-74.00170135499999,45.7770080566],"type":"Point"}
}