{
  "type": "Feature",
  "properties": {
    "addr:full":"300 Ch Sainte-Foy Quebec QC G1R 1T3",
    "addr:housenumber":"300",
    "addr:postcode":"g1r 1t3",
    "addr:street":"Ch Sainte-Foy",
    "iso:country":"CA",
    "sg:address":"300 Ch Sainte-Foy",
    "sg:city":"Quebec",
    "sg:classifiers":[
        {
            "category":"Retail",
            "subcategory":"Funeral Services",
            "type":"Services"
        }
    ],
    "sg:phone":"+1 418 529 3371",
    "sg:postcode":"G1R 1T3",
    "sg:province":"QC",
    "sg:tags":[
        "director"
    ],
    "wof:name":"Lepine-Cloutier Ltee",
    "wof:placetype":"venue"
},
  "geometry": {"coordinates":[-71.23175000000001,46.804401],"type":"Point"}
}