{
  "type": "Feature",
  "properties": {
    "iso:country":"CA",
    "sg:address":"16 Elm Ave",
    "sg:city":"Wolfville",
    "sg:classifiers":[
        {
            "category":"Home & Garden",
            "subcategory":"Home Furnishings",
            "type":"Retail Goods"
        }
    ],
    "sg:phone":"+1 902 542 3431",
    "sg:postcode":"B4P 1Z9",
    "sg:province":"NS",
    "sg:tags":[
        "lighting",
        "fixture"
    ],
    "wof:name":"Atlantic Lighting Studio Ltd",
    "wof:placetype":"venue"
},
  "geometry": {"coordinates":[-64.36372375489999,45.0916633606],"type":"Point"}
}