{
  "type": "Feature",
  "properties": {
    "addr:full":"1237 Rue Principale Canton-DE-Granby QC J2G 8C8",
    "addr:housenumber":"1237",
    "addr:postcode":"j2g 8c8",
    "addr:street":"Rue Principale",
    "iso:country":"CA",
    "sg:address":"1237 Rue Principale",
    "sg:city":"Canton-DE-Granby",
    "sg:classifiers":[
        {
            "category":"Autos & Motor Vehicles",
            "subcategory":"Automobile Sales",
            "type":"Retail Goods"
        }
    ],
    "sg:phone":"+1 450 777 3624",
    "sg:postcode":"J2G 8C8",
    "sg:province":"QC",
    "sg:tags":[
        "car",
        "dealer"
    ],
    "wof:name":"Gestion Amigo Enr",
    "wof:placetype":"venue"
},
  "geometry": {"coordinates":[-72.7779846191,45.4208526611],"type":"Point"}
}