{
  "type": "Feature",
  "properties": {
    "iso:country":"CA",
    "sg:city":"Mississauga",
    "sg:classifiers":[
        {
            "category":"Manufacturing",
            "subcategory":"Rubber & Plastics",
            "type":"Manufacturing & Wholesale Goods"
        }
    ],
    "sg:phone":"+1 905 672 0931",
    "sg:postcode":"L5S 1V3",
    "sg:province":"ON",
    "sg:tags":[
        "mold",
        "maker"
    ],
    "wof:name":"Ttm Plastics Inc",
    "wof:placetype":"venue"
},
  "geometry": {"coordinates":[-79.656624,43.694454],"type":"Point"}
}