{
  "type": "Feature",
  "properties": {
    "addr:full":"447 Rue Duchesneau Montreal QC H1L 4E5",
    "addr:housenumber":"447",
    "addr:postcode":"h1l 4e5",
    "addr:street":"Rue Duchesneau",
    "iso:country":"CA",
    "sg:address":"447 Rue Duchesneau",
    "sg:city":"Montreal",
    "sg:classifiers":[
        {
            "category":"Building & Trades",
            "subcategory":"Plumbing",
            "type":"Services"
        }
    ],
    "sg:phone":"+1 514 493 3437",
    "sg:postcode":"H1L 4E5",
    "sg:province":"QC",
    "sg:tags":[
        "ventilating",
        "contractor"
    ],
    "wof:name":"Ventilation Jdl Inc",
    "wof:placetype":"venue"
},
  "geometry": {"coordinates":[-73.51067352290001,45.6079444885],"type":"Point"}
}