{
  "type": "Feature",
  "properties": {
    "addr:full":"Burlington ON L7L 4X9",
    "addr:postcode":"l7l 4x9",
    "iso:country":"CA",
    "sg:city":"Burlington",
    "sg:classifiers":[
        {
            "category":"Retail",
            "subcategory":"Repair Shop",
            "type":"Services"
        }
    ],
    "sg:phone":"+1 905 319 0505",
    "sg:postcode":"L7L 4X9",
    "sg:province":"ON",
    "sg:tags":[
        "refinishing",
        "furniture"
    ],
    "wof:name":"Pro Finishing",
    "wof:placetype":"venue"
},
  "geometry": {"coordinates":[-79.7852554321,43.3760757446],"type":"Point"}
}