{
  "type": "Feature",
  "properties": {
    "addr:full":"19 School St Rexton NB E4W 2E4",
    "addr:housenumber":"19",
    "addr:postcode":"e4w 2e4",
    "addr:street":"School St",
    "iso:country":"CA",
    "sg:address":"19 School St",
    "sg:city":"Rexton",
    "sg:classifiers":[
        {
            "category":"Education",
            "subcategory":"School",
            "type":"Public Place"
        }
    ],
    "sg:phone":"+1 506 523 7152",
    "sg:postcode":"E4W 2E4",
    "sg:province":"NB",
    "wof:name":"Rexton Elementary",
    "wof:placetype":"venue"
},
  "geometry": {"coordinates":[-64.8698730469,46.6398124695],"type":"Point"}
}