{
  "type": "Feature",
  "properties": {
    "addr:full":"6122 Rue Jean-Talon E Saint-Leonard QC H1S 1M7",
    "addr:housenumber":"6122",
    "addr:postcode":"h1s 1m7",
    "addr:street":"Rue Jean-Talon E",
    "iso:country":"CA",
    "sg:address":"6122 Rue Jean-Talon E",
    "sg:city":"Saint-Leonard",
    "sg:classifiers":[
        {
            "category":"Personal",
            "subcategory":"Beauty Salon",
            "type":"Services"
        }
    ],
    "sg:phone":"+1 514 253 7934",
    "sg:postcode":"H1S 1M7",
    "sg:province":"QC",
    "sg:tags":[
        "make"
    ],
    "wof:name":"Centre DE Cosmetique Diva",
    "wof:placetype":"venue"
},
  "geometry": {"coordinates":[-73.57769012449999,45.588470459],"type":"Point"}
}