{
  "type": "Feature",
  "properties": {
    "addr:full":"Calgary AB T2E 7B1",
    "addr:postcode":"t2e 7b1",
    "iso:country":"CA",
    "sg:city":"Calgary",
    "sg:classifiers":[
        {
            "category":"Wholesale",
            "subcategory":"Vending Machines",
            "type":"Manufacturing & Wholesale Goods"
        }
    ],
    "sg:phone":"+1 403 250 8616",
    "sg:postcode":"T2E 7B1",
    "sg:province":"AB",
    "wof:name":"B & R Vending Distributors",
    "wof:placetype":"venue"
},
  "geometry": {"coordinates":[-114.01443500000001,51.077507],"type":"Point"}
}