{
  "type": "Feature",
  "properties": {
    "addr:full":"59 Racherie Dr Lillooet BC V0K 1V0",
    "addr:housenumber":"59",
    "addr:postcode":"v0k 1v0",
    "addr:street":"Racherie Dr",
    "iso:country":"CA",
    "sg:address":"59 Racherie Dr",
    "sg:city":"Lillooet",
    "sg:classifiers":[
        {
            "category":"Organizations",
            "subcategory":"Professional Association",
            "type":"Services"
        }
    ],
    "sg:phone":"+1 250 256 7130",
    "sg:postcode":"V0K 1V0",
    "sg:province":"BC",
    "sg:tags":[
        "native"
    ],
    "wof:name":"Julianne Hall",
    "wof:placetype":"venue"
},
  "geometry": {"coordinates":[-121.936515808,50.6865348816],"type":"Point"}
}