{
  "type": "Feature",
  "properties": {
    "addr:full":"Red Deer County AB T4S 2A8",
    "addr:postcode":"t4s 2a8",
    "iso:country":"CA",
    "sg:city":"Red Deer County",
    "sg:classifiers":[
        {
            "category":"Retail",
            "subcategory":"Laundry & Dry Cleaning",
            "type":"Services"
        }
    ],
    "sg:phone":"+1 403 346 8919",
    "sg:postcode":"T4S 2A8",
    "sg:province":"AB",
    "sg:tags":[
        "cleaners",
        "oil",
        "field"
    ],
    "wof:name":"Ceda Reactor Ltd",
    "wof:placetype":"venue"
},
  "geometry": {"coordinates":[-113.81401099999999,52.284874],"type":"Point"}
}