{
  "type": "Feature",
  "properties": {
    "addr:full":"6 King George Rd Brantford ON N3R 5J7",
    "addr:housenumber":"6",
    "addr:postcode":"n3r 5j7",
    "addr:street":"King George Rd",
    "iso:country":"CA",
    "sg:address":"6 King George Rd",
    "sg:city":"Brantford",
    "sg:classifiers":[
        {
            "category":"Real Estate",
            "subcategory":"Real Estate Agent",
            "type":"Services"
        }
    ],
    "sg:phone":"+1 519 751 2929",
    "sg:postcode":"N3R 5J7",
    "sg:province":"ON",
    "wof:name":"Homelife Choice Realty Ltd",
    "wof:placetype":"venue"
},
  "geometry": {"coordinates":[-80.27256800000001,43.160007],"type":"Point"}
}