{
  "type": "Feature",
  "properties": {
    "addr:full":"5 Queensway E Simcoe ON N3Y 5K2",
    "addr:housenumber":"5",
    "addr:postcode":"n3y 5k2",
    "addr:street":"Queensway E",
    "iso:country":"CA",
    "sg:address":"5 Queensway E",
    "sg:city":"Simcoe",
    "sg:classifiers":[
        {
            "category":"Professional",
            "subcategory":"Employment Agencies",
            "type":"Services"
        }
    ],
    "sg:phone":"+1 519 428 4069",
    "sg:postcode":"N3Y 5K2",
    "sg:province":"ON",
    "sg:tags":[
        "opportunity"
    ],
    "wof:name":"Norfolk Association For Living",
    "wof:placetype":"venue"
},
  "geometry": {"coordinates":[-80.30624389650001,42.8464927673],"type":"Point"}
}