{
  "type": "Feature",
  "properties": {
    "addr:full":"340 Pinnacle St Belleville ON K8N 3B4",
    "addr:housenumber":"340",
    "addr:postcode":"k8n 3b4",
    "addr:street":"Pinnacle St",
    "iso:country":"CA",
    "sg:address":"340 Pinnacle St",
    "sg:city":"Belleville",
    "sg:classifiers":[
        {
            "category":"Building & Trades",
            "subcategory":"Construction",
            "type":"Services"
        }
    ],
    "sg:phone":"+1 613 969 1135",
    "sg:postcode":"K8N 3B4",
    "sg:province":"ON",
    "sg:tags":[
        "contractor"
    ],
    "wof:name":"Paul A Stinson Builder Ltd",
    "wof:placetype":"venue"
},
  "geometry": {"coordinates":[-77.3847732544,44.1682472229],"type":"Point"}
}