{
  "type": "Feature",
  "properties": {
    "addr:full":"669 Rue Maurice Repentigny QC J6A 2M8",
    "addr:housenumber":"669",
    "addr:postcode":"j6a 2m8",
    "addr:street":"Rue Maurice",
    "iso:country":"CA",
    "sg:address":"669 Rue Maurice",
    "sg:city":"Repentigny",
    "sg:classifiers":[
        {
            "category":"Building & Trades",
            "subcategory":"Plumbing",
            "type":"Services"
        }
    ],
    "sg:phone":"+1 514 820 6890",
    "sg:postcode":"J6A 2M8",
    "sg:province":"QC",
    "sg:tags":[
        "conditioning",
        "air",
        "system",
        "contractor"
    ],
    "wof:name":"Vair Climatisation Inc",
    "wof:placetype":"venue"
},
  "geometry": {"coordinates":[-73.4333724976,45.7539558411],"type":"Point"}
}