{
  "type": "Feature",
  "properties": {
    "addr:full":"4911 50th Ave St Paul AB T0A 3A0",
    "addr:housenumber":"4911",
    "addr:postcode":"t0a 3a0",
    "addr:street":"50Th Ave",
    "iso:country":"CA",
    "sg:address":"4911 50th Ave",
    "sg:city":"St Paul",
    "sg:classifiers":[
        {
            "category":"Shopping",
            "subcategory":"Clothing, Apparel, & Fashions",
            "type":"Retail Goods"
        }
    ],
    "sg:phone":"+1 780 645 3652",
    "sg:postcode":"T0A 3A0",
    "sg:province":"AB",
    "wof:name":"Mr G's Fine Fashions",
    "wof:placetype":"venue"
},
  "geometry": {"coordinates":[-111.294914246,53.9911727905],"type":"Point"}
}