{
  "type": "Feature",
  "properties": {
    "addr:full":"514 1st Ave W Meadow Lake SK S9X 1N6",
    "addr:housenumber":"514",
    "addr:postcode":"s9x 1n6",
    "addr:street":"1St Ave W Meadow",
    "iso:country":"CA",
    "sg:address":"514 1st Ave W",
    "sg:city":"Meadow Lake",
    "sg:classifiers":[
        {
            "category":"Wholesale",
            "subcategory":"Machinery & Supplies",
            "type":"Manufacturing & Wholesale Goods"
        }
    ],
    "sg:phone":"+1 306 236 5621",
    "sg:postcode":"S9X 1N6",
    "sg:province":"SK",
    "sg:tags":[
        "equipment",
        "industrial"
    ],
    "wof:name":"Acklands-Grainger Inc",
    "wof:placetype":"venue"
},
  "geometry": {"coordinates":[-108.44172668500001,54.1332588196],"type":"Point"}
}