{
  "type": "Feature",
  "properties": {
    "addr:full":"845 Cameron St Regina SK S4T 2S4",
    "addr:housenumber":"845",
    "addr:postcode":"s4t 2s4",
    "addr:street":"Cameron St",
    "iso:country":"CA",
    "sg:address":"845 Cameron St",
    "sg:city":"Regina",
    "sg:classifiers":[
        {
            "category":"Building & Trades",
            "subcategory":"Construction",
            "type":"Services"
        }
    ],
    "sg:phone":"+1 306 757 6254",
    "sg:postcode":"S4T 2S4",
    "sg:province":"SK",
    "sg:tags":[
        "painter"
    ],
    "wof:name":"Philly's Painting & Carpet",
    "wof:placetype":"venue"
},
  "geometry": {"coordinates":[-104.625205994,50.4654312134],"type":"Point"}
}