{
  "type": "Feature",
  "properties": {
    "addr:full":"2888 Dufferin St North York ON M6B 3S6",
    "addr:housenumber":"2888",
    "addr:postcode":"m6b 3s6",
    "addr:street":"Dufferin St",
    "iso:country":"CA",
    "sg:address":"2888 Dufferin St",
    "sg:city":"North York",
    "sg:classifiers":[
        {
            "category":"Organizations",
            "subcategory":"Labor Organization",
            "type":"Services"
        }
    ],
    "sg:phone":"+1 416 785 8787",
    "sg:postcode":"M6B 3S6",
    "sg:province":"ON",
    "sg:tags":[
        "social",
        "welfare"
    ],
    "wof:name":"Union of Injured Workers",
    "wof:placetype":"venue"
},
  "geometry": {"coordinates":[-79.453514,43.707672],"type":"Point"}
}