{
  "type": "Feature",
  "properties": {
    "addr:full":"Sainte-Brigitte-DE-Laval QC G0A 3K0",
    "addr:postcode":"g0a 3k0",
    "iso:country":"CA",
    "sg:city":"Sainte-Brigitte-DE-Laval",
    "sg:classifiers":[
        {
            "category":"Organizations",
            "subcategory":"Religious Organization",
            "type":"Services"
        }
    ],
    "sg:phone":"+1 418 825 3384",
    "sg:postcode":"G0A 3K0",
    "sg:province":"QC",
    "sg:tags":[
        "church"
    ],
    "wof:name":"Fabrique DE Ste-Brigette",
    "wof:placetype":"venue"
},
  "geometry": {"coordinates":[-73.744637,45.551567],"type":"Point"}
}