{
  "type": "Feature",
  "properties": {
    "addr:full":"583 Robinson Rd Peterborough ON K9J 6X2",
    "addr:housenumber":"583",
    "addr:postcode":"k9j 6x2",
    "addr:street":"Robinson Rd",
    "iso:country":"CA",
    "sg:address":"583 Robinson Rd",
    "sg:city":"Peterborough",
    "sg:classifiers":[
        {
            "category":"Restaurant",
            "type":"Food & Drink"
        }
    ],
    "sg:phone":"+1 705 292 9175",
    "sg:postcode":"K9J 6X2",
    "sg:province":"ON",
    "wof:name":"Jesse's Tap & Grill",
    "wof:placetype":"venue"
},
  "geometry": {"coordinates":[-78.30647999999999,44.30508],"type":"Point"}
}