{
  "type": "Feature",
  "properties": {
    "addr:full":"General Delivery Repulse Bay NU X0C 0H0",
    "addr:postcode":"x0c 0h0",
    "iso:country":"CA",
    "sg:address":"General Delivery",
    "sg:city":"Repulse Bay",
    "sg:classifiers":[
        {
            "category":"Government",
            "subcategory":"Office",
            "type":"Public Place"
        }
    ],
    "sg:phone":"+1 867 462 4093",
    "sg:postcode":"X0C 0H0",
    "sg:province":"NU",
    "sg:tags":[
        "village"
    ],
    "wof:name":"Repulse Bay Public Works",
    "wof:placetype":"venue"
},
  "geometry": {"coordinates":[-86.2357177734,66.5250701904],"type":"Point"}
}