{
  "type": "Feature",
  "properties": {
    "iso:country":"CA",
    "sg:city":"London",
    "sg:classifiers":[
        {
            "category":"Personal",
            "subcategory":"Beauty Salon",
            "type":"Services"
        }
    ],
    "sg:phone":"+1 519 472 4420",
    "sg:postcode":"N6J 1G9",
    "sg:province":"ON",
    "wof:name":"Mel's Hair Care",
    "wof:placetype":"venue"
},
  "geometry": {"coordinates":[-81.2824554443,42.9686050415],"type":"Point"}
}