{
  "type": "Feature",
  "properties": {
    "iso:country":"CA",
    "sg:city":"Saint-Pie-DE-Guire",
    "sg:classifiers":[
        {
            "category":"Wholesale",
            "subcategory":"Groceries",
            "type":"Manufacturing & Wholesale Goods"
        }
    ],
    "sg:phone":"+1 450 784 2417",
    "sg:postcode":"J0G 1R0",
    "sg:province":"QC",
    "sg:tags":[
        "feed",
        "pet"
    ],
    "wof:name":"Centre DE Distribution",
    "wof:placetype":"venue"
},
  "geometry": {"coordinates":[-72.750038147,46.0012245178],"type":"Point"}
}