{
  "type": "Feature",
  "properties": {
    "addr:full":"287 Old Kingston Rd Scarborough ON M1C 1B4",
    "addr:housenumber":"287",
    "addr:postcode":"m1c 1b4",
    "addr:street":"Old Kingston Rd",
    "iso:country":"CA",
    "sg:address":"287 Old Kingston Rd",
    "sg:city":"Scarborough",
    "sg:classifiers":[
        {
            "category":"Retail",
            "subcategory":"Auto Repair",
            "type":"Services"
        }
    ],
    "sg:phone":"+1 416 283 7011",
    "sg:postcode":"M1C 1B4",
    "sg:province":"ON",
    "sg:tags":[
        "repairing",
        "automobile"
    ],
    "wof:name":"Auto Techniques",
    "wof:placetype":"venue"
},
  "geometry": {"coordinates":[-79.1714096069,43.7826347351],"type":"Point"}
}