{
  "type": "Feature",
  "properties": {
    "addr:full":"Toronto ON M4P 1A9",
    "addr:postcode":"m4p 1a9",
    "iso:country":"CA",
    "sg:city":"Toronto",
    "sg:classifiers":[
        {
            "category":"Health Services",
            "subcategory":"Health Practitioner",
            "type":"Services"
        }
    ],
    "sg:phone":"+1 416 483 6920",
    "sg:postcode":"M4P 1A9",
    "sg:province":"ON",
    "sg:tags":[
        "dietitian"
    ],
    "wof:name":"Carex Dietary Information Syst",
    "wof:placetype":"venue"
},
  "geometry": {"coordinates":[-79.39788799999999,43.70697],"type":"Point"}
}