{
  "type": "Feature",
  "properties": {
    "addr:full":"Richmond BC V6V 2H9",
    "addr:postcode":"v6v 2h9",
    "iso:country":"CA",
    "sg:city":"Richmond",
    "sg:classifiers":[
        {
            "category":"Wholesale",
            "subcategory":"Chemicals & Plastics",
            "type":"Manufacturing & Wholesale Goods"
        }
    ],
    "sg:phone":"+1 604 278 1833",
    "sg:postcode":"V6V 2H9",
    "sg:province":"BC",
    "sg:tags":[
        "cleaning",
        "compound"
    ],
    "wof:name":"Dynamic Detergent Ltd",
    "wof:placetype":"venue"
},
  "geometry": {"coordinates":[-123.082695007,49.1858558655],"type":"Point"}
}