{
  "type": "Feature",
  "properties": {
    "addr:full":"25 Byron St New Hamburg ON N3A 1P1",
    "addr:housenumber":"25",
    "addr:postcode":"n3a 1p1",
    "addr:street":"Byron St",
    "iso:country":"CA",
    "sg:address":"25 Byron St",
    "sg:city":"New Hamburg",
    "sg:classifiers":[
        {
            "category":"Health Services",
            "subcategory":"Doctor",
            "type":"Services"
        }
    ],
    "sg:phone":"+1 519 662 2632",
    "sg:postcode":"N3A 1P1",
    "sg:province":"ON",
    "sg:tags":[
        "dentist"
    ],
    "wof:name":"Mac Cara, Ruth DDS",
    "wof:placetype":"venue"
},
  "geometry": {"coordinates":[-80.715034,43.377987],"type":"Point"}
}