{
  "type": "Feature",
  "properties": {
    "addr:full":"1279 5th St Courtenay BC V9N 1L7",
    "addr:housenumber":"1279",
    "addr:postcode":"v9n 1l7",
    "addr:street":"5Th St",
    "iso:country":"CA",
    "sg:address":"1279 5th St",
    "sg:city":"Courtenay",
    "sg:classifiers":[
        {
            "category":"Restaurant",
            "type":"Food & Drink"
        }
    ],
    "sg:phone":"+1 250 338 7398",
    "sg:postcode":"V9N 1L7",
    "sg:province":"BC",
    "sg:tags":[
        "caterer"
    ],
    "wof:name":"Country Catering",
    "wof:placetype":"venue"
},
  "geometry": {"coordinates":[-125.010314941,49.6823348999],"type":"Point"}
}