{
  "type": "Feature",
  "properties": {
    "addr:full":"701 Primrose St Qualicum Beach BC V9K 1T2",
    "addr:housenumber":"701",
    "addr:postcode":"v9k 1t2",
    "addr:street":"Primrose St",
    "iso:country":"CA",
    "sg:address":"701 Primrose St",
    "sg:city":"Qualicum Beach",
    "sg:classifiers":[
        {
            "category":"Shopping",
            "subcategory":"Bicycles & Sporting Goods",
            "type":"Retail Goods"
        }
    ],
    "sg:phone":"+1 250 752 9833",
    "sg:postcode":"V9K 1T2",
    "sg:province":"BC",
    "sg:tags":[
        "hardware"
    ],
    "wof:name":"Dolly's Home Hardware",
    "wof:placetype":"venue"
},
  "geometry": {"coordinates":[-124.44455000000001,49.346867],"type":"Point"}
}