{
  "type": "Feature",
  "properties": {
    "addr:full":"1813 Versatile Dr Kamloops BC V1S 1C5",
    "addr:housenumber":"1813",
    "addr:postcode":"bc v1s 1c5",
    "addr:street":"Versatile Dr",
    "iso:country":"CA",
    "sg:address":"1813 Versatile Dr",
    "sg:city":"Kamloops",
    "sg:classifiers":[
        {
            "category":"Freight",
            "type":"Transportation"
        }
    ],
    "sg:phone":"+1 250 374 6232",
    "sg:postcode":"V1S 1C5",
    "sg:province":"BC",
    "sg:tags":[
        "trucking"
    ],
    "wof:name":"Trimac Transportation Svc Inc",
    "wof:placetype":"venue"
},
  "geometry": {"coordinates":[-120.394302,50.657925],"type":"Point"}
}