{
  "type": "Feature",
  "properties": {
    "addr:full":"Port Coquitlam BC V3B 1S9",
    "addr:postcode":"v3b 1s9",
    "iso:country":"CA",
    "sg:city":"Port Coquitlam",
    "sg:classifiers":[
        {
            "category":"Food & Beverages",
            "subcategory":"Groceries & Convenience Stores",
            "type":"Retail Goods"
        }
    ],
    "sg:phone":"+1 604 942 8448",
    "sg:postcode":"V3B 1S9",
    "sg:province":"BC",
    "sg:tags":[
        "grocer"
    ],
    "wof:name":"Honey & Milk",
    "wof:placetype":"venue"
},
  "geometry": {"coordinates":[-122.754211,49.271271],"type":"Point"}
}