{
  "type": "Feature",
  "properties": {
    "addr:full":"140 DE LA Mer Longue-Pointe-DE-Mingan QC G0G 1V0",
    "addr:housenumber":"140",
    "addr:postcode":"g0g 1v0",
    "addr:street":"De La Mer",
    "iso:country":"CA",
    "sg:address":"140 DE LA Mer",
    "sg:city":"Longue-Pointe-DE-Mingan",
    "sg:classifiers":[
        {
            "category":"Ferry",
            "type":"Transportation"
        }
    ],
    "sg:phone":"+1 418 949 2307",
    "sg:postcode":"G0G 1V0",
    "sg:province":"QC",
    "sg:tags":[
        "boat"
    ],
    "wof:name":"Entreprises Touristiques",
    "wof:placetype":"venue"
},
  "geometry": {"coordinates":[-64.15190124510001,50.2638015747],"type":"Point"}
}