{
  "type": "Feature",
  "properties": {
    "addr:full":"775 Rue Cormier Sorel-Tracy QC J3R 5A3",
    "addr:housenumber":"775",
    "addr:postcode":"j3r 5a3",
    "addr:street":"Rue Cormier",
    "iso:country":"CA",
    "sg:address":"775 Rue Cormier",
    "sg:city":"Sorel-Tracy",
    "sg:classifiers":[
        {
            "category":"Home & Garden",
            "subcategory":"Building Materials",
            "type":"Retail Goods"
        }
    ],
    "sg:phone":"+1 450 743 0028",
    "sg:postcode":"J3R 5A3",
    "sg:province":"QC",
    "sg:tags":[
        "glass",
        "window",
        "plate"
    ],
    "wof:name":"Duchesne Vitrerie Inc",
    "wof:placetype":"venue"
},
  "geometry": {"coordinates":[-73.12642700000001,46.039036],"type":"Point"}
}