{
  "type": "Feature",
  "properties": {
    "addr:full":"109 Mclaughlin Rd N Brampton ON L6X 1Y9",
    "addr:housenumber":"109",
    "addr:postcode":"l6x 1y9",
    "addr:street":"Mclaughlin Rd N",
    "iso:country":"CA",
    "sg:address":"109 Mclaughlin Rd N",
    "sg:city":"Brampton",
    "sg:classifiers":[
        {
            "category":"Government",
            "subcategory":"Jail",
            "type":"Public Place"
        }
    ],
    "sg:phone":"+1 905 457 7050",
    "sg:postcode":"L6X 1Y9",
    "sg:province":"ON",
    "sg:tags":[
        "provincial",
        "institution"
    ],
    "wof:name":"Ontario Correctional Institute",
    "wof:placetype":"venue"
},
  "geometry": {"coordinates":[-79.7786560059,43.6822052002],"type":"Point"}
}