{
  "type": "Feature",
  "properties": {
    "iso:country":"CA",
    "sg:address":"123 Commerce Valley Dr E # 300",
    "sg:city":"Thornhill",
    "sg:classifiers":[
        {
            "category":"Banks & Credit Unions",
            "subcategory":"Investment Brokerage",
            "type":"Services"
        }
    ],
    "sg:phone":"+1 905 882 9728",
    "sg:postcode":"L3T 7W8",
    "sg:province":"ON",
    "sg:tags":[
        "consultant",
        "planning",
        "financial"
    ],
    "wof:name":"Trillion Financial Group",
    "wof:placetype":"venue"
},
  "geometry": {"coordinates":[-79.37507629389999,43.8416366577],"type":"Point"}
}