{
  "type": "Feature",
  "properties": {
    "addr:full":"16 Front St E Strathroy ON N7G 1Y4",
    "addr:housenumber":"16",
    "addr:postcode":"n7g 1y4",
    "addr:street":"Front St E",
    "iso:country":"CA",
    "sg:address":"16 Front St E",
    "sg:city":"Strathroy",
    "sg:classifiers":[
        {
            "category":"Professional",
            "subcategory":"Lawyer & Legal Services",
            "type":"Services"
        }
    ],
    "sg:phone":"+1 519 245 0370",
    "sg:postcode":"N7G 1Y4",
    "sg:province":"ON",
    "sg:tags":[
        "attorney"
    ],
    "wof:name":"Dack, Robert J",
    "wof:placetype":"venue"
},
  "geometry": {"coordinates":[-81.6233673096,42.9588050842],"type":"Point"}
}