{
  "type": "Feature",
  "properties": {
    "addr:full":"1565 Rue DE L'Innovation Val-Belair QC G3K 2P9",
    "addr:housenumber":"1565",
    "addr:postcode":"g3k 2p9",
    "addr:street":"Rue De L'Innovation Val-Belair",
    "iso:country":"CA",
    "sg:address":"1565 Rue DE L'Innovation",
    "sg:city":"Val-Belair",
    "sg:classifiers":[
        {
            "category":"Social Services",
            "type":"Services"
        }
    ],
    "sg:phone":"+1 418 843 5166",
    "sg:postcode":"G3K 2P9",
    "sg:province":"QC",
    "sg:tags":[
        "youth",
        "organization",
        "center",
        "government"
    ],
    "wof:name":"Maison Des Jeunes-Val-Belair",
    "wof:placetype":"venue"
},
  "geometry": {"coordinates":[-71.419472,46.858582],"type":"Point"}
}