{
  "type": "Feature",
  "properties": {
    "addr:full":"2072 Falcon Rd Kamloops BC V2C 4J3",
    "addr:housenumber":"2072",
    "addr:postcode":"bc v2c 4j3",
    "addr:street":"Falcon Rd",
    "iso:country":"CA",
    "sg:address":"2072 Falcon Rd",
    "sg:city":"Kamloops",
    "sg:classifiers":[
        {
            "category":"Autos & Motor Vehicles",
            "subcategory":"Automobile Sales",
            "type":"Retail Goods"
        }
    ],
    "sg:phone":"+1 250 374 1431",
    "sg:postcode":"V2C 4J3",
    "sg:province":"BC",
    "sg:tags":[
        "truck"
    ],
    "wof:name":"James Western Star Ltd",
    "wof:placetype":"venue"
},
  "geometry": {"coordinates":[-120.269783,50.678768],"type":"Point"}
}