{
  "type": "Feature",
  "properties": {
    "addr:full":"106 Souris St Yellow Grass SK S0G 5J0",
    "addr:housenumber":"106",
    "addr:postcode":"s0g 5j0",
    "addr:street":"Souris St",
    "iso:country":"CA",
    "sg:address":"106 Souris St",
    "sg:city":"Yellow Grass",
    "sg:classifiers":[
        {
            "category":"Organizations",
            "subcategory":"Community Association",
            "type":"Services"
        }
    ],
    "sg:phone":"+1 306 465 2221",
    "sg:postcode":"S0G 5J0",
    "sg:province":"SK",
    "sg:tags":[
        "club"
    ],
    "wof:name":"Yellow Grass Golden Harvest",
    "wof:placetype":"venue"
},
  "geometry": {"coordinates":[-104.160690308,49.8053894043],"type":"Point"}
}