{
  "type": "Feature",
  "properties": {
    "addr:full":"15459 Semiahmoo Ave White Rock BC V4B 1T7",
    "addr:housenumber":"15459",
    "addr:postcode":"v4b 1t7",
    "addr:street":"Semiahmoo Ave",
    "iso:country":"CA",
    "sg:address":"15459 Semiahmoo Ave",
    "sg:city":"White Rock",
    "sg:classifiers":[
        {
            "category":"Social Services",
            "type":"Services"
        }
    ],
    "sg:phone":"+1 604 536 7402",
    "sg:postcode":"V4B 1T7",
    "sg:province":"BC",
    "sg:tags":[
        "counselor",
        "marriage",
        "family"
    ],
    "wof:name":"Core Belief Engineering Ltd",
    "wof:placetype":"venue"
},
  "geometry": {"coordinates":[-122.793983459,49.0226669312],"type":"Point"}
}