{
  "type": "Feature",
  "properties": {
    "addr:full":"33 Inglis Pl Truro NS B2N 4B5",
    "addr:housenumber":"33",
    "addr:postcode":"b2n 4b5",
    "addr:street":"Inglis Pl",
    "iso:country":"CA",
    "sg:address":"33 Inglis Pl",
    "sg:city":"Truro",
    "sg:classifiers":[
        {
            "category":"Shopping",
            "subcategory":"Bicycles & Sporting Goods",
            "type":"Retail Goods"
        }
    ],
    "sg:phone":"+1 902 897 2482",
    "sg:postcode":"B2N 4B5",
    "sg:province":"NS",
    "wof:name":"Hub Cycle",
    "wof:placetype":"venue"
},
  "geometry": {"coordinates":[-63.276154,45.364094],"type":"Point"}
}