{
  "type": "Feature",
  "properties": {
    "addr:full":"261 Van Horne Ave Dryden ON P8N 2C3",
    "addr:housenumber":"261",
    "addr:postcode":"p8n 2c3",
    "addr:street":"Van Horne Ave",
    "iso:country":"CA",
    "sg:address":"261 Van Horne Ave",
    "sg:city":"Dryden",
    "sg:classifiers":[
        {
            "category":"Organizations",
            "subcategory":"Religious Organization",
            "type":"Services"
        }
    ],
    "sg:phone":"+1 807 223 2755",
    "sg:postcode":"P8N 2C3",
    "sg:province":"ON",
    "sg:tags":[
        "church"
    ],
    "wof:name":"Dryden Free Methodist Ch",
    "wof:placetype":"venue"
},
  "geometry": {"coordinates":[-92.8360824585,49.7720031738],"type":"Point"}
}