{
  "type": "Feature",
  "properties": {
    "addr:full":"664 Oliver St Williams Lake BC V2G 1M6",
    "addr:housenumber":"664",
    "addr:postcode":"v2g 1m6",
    "addr:street":"Oliver St",
    "iso:country":"CA",
    "sg:address":"664 Oliver St",
    "sg:city":"Williams Lake",
    "sg:classifiers":[
        {
            "category":"Restaurant",
            "type":"Food & Drink"
        }
    ],
    "sg:phone":"+1 250 398 5343",
    "sg:postcode":"V2G 1M6",
    "sg:province":"BC",
    "wof:name":"Denny's Restaurant",
    "wof:placetype":"venue"
},
  "geometry": {"coordinates":[-122.137749,52.128422],"type":"Point"}
}