{
  "type": "Feature",
  "properties": {
    "addr:full":"499 112 Rte E Vallee-Jonction QC G0S 3J0",
    "addr:housenumber":"112",
    "addr:postcode":"g0s 3j0",
    "addr:street":"Rte E Vallee-Jonction",
    "iso:country":"CA",
    "sg:address":"499 112 Rte E",
    "sg:city":"Vallee-Jonction",
    "sg:classifiers":[
        {
            "category":"Manufacturing",
            "subcategory":"Metals",
            "type":"Manufacturing & Wholesale Goods"
        }
    ],
    "sg:phone":"+1 418 253 5333",
    "sg:postcode":"G0S 3J0",
    "sg:province":"QC",
    "sg:tags":[
        "steel"
    ],
    "wof:name":"Metal Bgl Inc",
    "wof:placetype":"venue"
},
  "geometry": {"coordinates":[-70.9239273071,46.3760528564],"type":"Point"}
}