{
  "type": "Feature",
  "properties": {
    "addr:full":"6593 Rue Beaubien E Montreal QC H1M 1B1",
    "addr:housenumber":"6593",
    "addr:postcode":"h1m 1b1",
    "addr:street":"Rue Beaubien E",
    "iso:country":"CA",
    "sg:address":"6593 Rue Beaubien E",
    "sg:city":"Montreal",
    "sg:classifiers":[
        {
            "category":"Banks & Credit Unions",
            "subcategory":"Bank",
            "type":"Services"
        }
    ],
    "sg:phone":"+1 514 522 1846",
    "sg:postcode":"H1M 1B1",
    "sg:province":"QC",
    "wof:name":"Banque Laurentienne Du Canada",
    "wof:placetype":"venue"
},
  "geometry": {"coordinates":[-73.56086000000001,45.5882],"type":"Point"}
}