{
  "type": "Feature",
  "properties": {
    "addr:full":"Salt Spring Island BC V8K 2S5",
    "addr:postcode":"v8k 2s5",
    "iso:country":"CA",
    "sg:city":"Salt Spring Island",
    "sg:classifiers":[
        {
            "category":"Shopping",
            "type":"Retail Goods"
        }
    ],
    "sg:phone":"+1 250 537 1589",
    "sg:postcode":"V8K 2S5",
    "sg:province":"BC",
    "sg:tags":[
        "art",
        "gallery",
        "dealer"
    ],
    "wof:name":"Jill Campbell Art Gallery",
    "wof:placetype":"venue"
},
  "geometry": {"coordinates":[-123.499718,48.853687],"type":"Point"}
}