{
  "type": "Feature",
  "properties": {
    "addr:full":"880 Prospect St Fredericton NB E3B 2T8",
    "addr:housenumber":"880",
    "addr:postcode":"e3b 2t8",
    "addr:street":"Prospect St",
    "iso:country":"CA",
    "sg:address":"880 Prospect St",
    "sg:city":"Fredericton",
    "sg:classifiers":[
        {
            "category":"Autos & Motor Vehicles",
            "subcategory":"Automobile Sales",
            "type":"Retail Goods"
        }
    ],
    "sg:phone":"+1 506 452 6611",
    "sg:postcode":"E3B 2T8",
    "sg:province":"NB",
    "sg:tags":[
        "car",
        "dealer"
    ],
    "wof:name":"Wood Motors Ltd",
    "wof:placetype":"venue"
},
  "geometry": {"coordinates":[-66.6738433838,45.9441223145],"type":"Point"}
}