{
  "type": "Feature",
  "properties": {
    "addr:full":"Montreal QC H2X 2G1",
    "addr:postcode":"h2x 2g1",
    "iso:country":"CA",
    "sg:city":"Montreal",
    "sg:classifiers":[
        {
            "category":"Professional",
            "subcategory":"Computer Services",
            "type":"Services"
        }
    ],
    "sg:phone":"+1 514 288 7646",
    "sg:postcode":"H2X 2G1",
    "sg:province":"QC",
    "sg:tags":[
        "internet"
    ],
    "wof:name":"Soho-It Inc",
    "wof:placetype":"venue"
},
  "geometry": {"coordinates":[-73.57358551030001,45.5087432861],"type":"Point"}
}