{
  "type": "Feature",
  "properties": {
    "iso:country":"CA",
    "sg:address":"5 Prince St",
    "sg:city":"Sydney",
    "sg:classifiers":[
        {
            "category":"Shopping",
            "subcategory":"Optical Goods",
            "type":"Retail Goods"
        }
    ],
    "sg:phone":"+1 902 562 0221",
    "sg:postcode":"B1P 5J4",
    "sg:province":"NS",
    "sg:tags":[
        "sun",
        "goggles",
        "sunglasses",
        "optician"
    ],
    "wof:name":"Vogue Optical Ltd",
    "wof:placetype":"venue"
},
  "geometry": {"coordinates":[-60.195587,46.138042],"type":"Point"}
}