{
  "type": "Feature",
  "properties": {
    "addr:full":"7225 Lundy's Lane Niagara Falls ON L2G 1W3",
    "addr:housenumber":"7225",
    "addr:postcode":"l2g 1w3",
    "addr:street":"Lundy'S Lane",
    "iso:country":"CA",
    "sg:address":"7225 Lundy's Lane",
    "sg:city":"Niagara Falls",
    "sg:classifiers":[
        {
            "category":"Travel",
            "subcategory":"Hotels & Motels",
            "type":"Entertainment"
        }
    ],
    "sg:phone":"+1 905 354 0281",
    "sg:postcode":"L2G 1W3",
    "sg:province":"ON",
    "wof:name":"Niagara Inn Motel",
    "wof:placetype":"venue"
},
  "geometry": {"coordinates":[-77.565369,45.042416],"type":"Point"}
}