{
  "type": "Feature",
  "properties": {
    "addr:full":"550 Rue Richmond Montreal QC H3J 1V3",
    "addr:housenumber":"550",
    "addr:postcode":"h3j 1v3",
    "addr:street":"Rue Richmond",
    "iso:country":"CA",
    "sg:address":"550 Rue Richmond",
    "sg:city":"Montreal",
    "sg:classifiers":[
        {
            "category":"Organizations",
            "subcategory":"Religious Organization",
            "type":"Services"
        }
    ],
    "sg:phone":"+1 514 932 7270",
    "sg:postcode":"H3J 1V3",
    "sg:province":"QC",
    "sg:tags":[
        "church"
    ],
    "wof:name":"St-Joseph Church",
    "wof:placetype":"venue"
},
  "geometry": {"coordinates":[-73.568932,45.489544],"type":"Point"}
}