{
  "type": "Feature",
  "properties": {
    "addr:full":"15335 116 Ave NW Edmonton AB T5M 3Z5",
    "addr:housenumber":"15335",
    "addr:postcode":"t5m 3z5",
    "addr:street":"116 Ave Nw",
    "iso:country":"CA",
    "sg:address":"15335 116 Ave NW",
    "sg:city":"Edmonton",
    "sg:classifiers":[
        {
            "category":"Retail",
            "subcategory":"Auto Repair",
            "type":"Services"
        }
    ],
    "sg:phone":"+1 780 448 9310",
    "sg:postcode":"T5M 3Z5",
    "sg:province":"AB",
    "sg:tags":[
        "repairing",
        "automobile"
    ],
    "wof:name":"Jass Auto",
    "wof:placetype":"venue"
},
  "geometry": {"coordinates":[-113.585899,53.567822],"type":"Point"}
}