{
  "type": "Feature",
  "properties": {
    "addr:full":"Vancouver BC V5P 3W4",
    "addr:postcode":"v5p 3w4",
    "iso:country":"CA",
    "sg:city":"Vancouver",
    "sg:classifiers":[
        {
            "category":"Education",
            "subcategory":"Special Training",
            "type":"Public Place"
        }
    ],
    "sg:phone":"+1 604 322 1585",
    "sg:postcode":"V5P 3W4",
    "sg:province":"BC",
    "sg:tags":[
        "school",
        "language"
    ],
    "wof:name":"Ninagawa Japanese Language Ctr",
    "wof:placetype":"venue"
},
  "geometry": {"coordinates":[-123.0652771,49.2337493896],"type":"Point"}
}