{
  "type": "Feature",
  "properties": {
    "addr:full":"1010 Rue Saint-Georges Saint-Jerome QC J7Z 5E8",
    "addr:housenumber":"1010",
    "addr:postcode":"j7z 5e8",
    "addr:street":"Rue Saint-Georges Saint-Jerome",
    "iso:country":"CA",
    "sg:address":"1010 Rue Saint-Georges",
    "sg:city":"Saint-Jerome",
    "sg:classifiers":[
        {
            "category":"Autos & Motor Vehicles",
            "subcategory":"Auto Supplies",
            "type":"Retail Goods"
        }
    ],
    "sg:phone":"+1 450 432 9721",
    "sg:postcode":"J7Z 5E8",
    "sg:province":"QC",
    "sg:tags":[
        "automobile",
        "parts"
    ],
    "wof:name":"Carquest Canada Ltee",
    "wof:placetype":"venue"
},
  "geometry": {"coordinates":[-74.005661,45.792671],"type":"Point"}
}