{
  "type": "Feature",
  "properties": {
    "addr:full":"Whistler BC V0N 1B4",
    "addr:postcode":"v0n 1b4",
    "iso:country":"CA",
    "sg:city":"Whistler",
    "sg:classifiers":[
        {
            "category":"Real Estate",
            "subcategory":"Real Estate Agent",
            "type":"Services"
        }
    ],
    "sg:phone":"+1 604 932 5538",
    "sg:postcode":"V0N 1B4",
    "sg:province":"BC",
    "wof:name":"Whistler Real Estate CO Ltd",
    "wof:placetype":"venue"
},
  "geometry": {"coordinates":[-122.95552063,50.1202888489],"type":"Point"}
}