{
  "type": "Feature",
  "properties": {
    "iso:country":"CA",
    "sg:city":"Brampton",
    "sg:classifiers":[
        {
            "category":"Retail",
            "subcategory":"Auto Repair",
            "type":"Services"
        }
    ],
    "sg:phone":"+1 905 796 9362",
    "sg:postcode":"L6W 3J6",
    "sg:province":"ON",
    "sg:tags":[
        "machine",
        "automobile",
        "shop"
    ],
    "wof:name":"Magrinho, Rui",
    "wof:placetype":"venue"
},
  "geometry": {"coordinates":[-79.73067474370001,43.6902313232],"type":"Point"}
}