{
  "type": "Feature",
  "properties": {
    "addr:full":"Hanna AB T0J 1P0",
    "addr:postcode":"t0j 1p0",
    "iso:country":"CA",
    "sg:city":"Hanna",
    "sg:classifiers":[
        {
            "category":"Health Services",
            "subcategory":"Doctor",
            "type":"Services"
        }
    ],
    "sg:phone":"+1 403 854 3351",
    "sg:postcode":"T0J 1P0",
    "sg:province":"AB",
    "sg:tags":[
        "physician",
        "surgeon"
    ],
    "wof:name":"Hanna Medical Clinic",
    "wof:placetype":"venue"
},
  "geometry": {"coordinates":[-111.927818,51.649197],"type":"Point"}
}