{
  "type": "Feature",
  "properties": {
    "addr:full":"114 Rg 3 Saint-Godefroi QC G0C 3C0",
    "addr:housenumber":"114;3",
    "addr:postcode":"g0c 3c0",
    "addr:street":"Rg",
    "iso:country":"CA",
    "sg:address":"114 Rg 3",
    "sg:city":"Saint-Godefroi",
    "sg:classifiers":[
        {
            "category":"Building & Trades",
            "subcategory":"Electrical",
            "type":"Services"
        }
    ],
    "sg:phone":"+1 418 752 6252",
    "sg:postcode":"G0C 3C0",
    "sg:province":"QC",
    "sg:tags":[
        "electric",
        "contractor"
    ],
    "wof:name":"Arsenault Electrique Enr",
    "wof:placetype":"venue"
},
  "geometry": {"coordinates":[-65.112663,48.076721],"type":"Point"}
}