{
  "type": "Feature",
  "properties": {
    "addr:full":"430 Rue Sacre-Coeur O Alma QC G8B 1L9",
    "addr:housenumber":"430",
    "addr:postcode":"g8b 1l9",
    "addr:street":"Rue Sacre-Coeur O",
    "iso:country":"CA",
    "sg:address":"430 Rue Sacre-Coeur O",
    "sg:city":"Alma",
    "sg:classifiers":[
        {
            "category":"Restaurant",
            "type":"Food & Drink"
        }
    ],
    "sg:phone":"+1 418 668 4571",
    "sg:postcode":"G8B 1L9",
    "sg:province":"QC",
    "wof:name":"Coq Roti Pizza Delight",
    "wof:placetype":"venue"
},
  "geometry": {"coordinates":[-71.634437561,48.5439872742],"type":"Point"}
}