{
  "type": "Feature",
  "properties": {
    "addr:full":"Brandon MB R7B 3M9",
    "addr:postcode":"r7b 3m9",
    "iso:country":"CA",
    "sg:city":"Brandon",
    "sg:classifiers":[
        {
            "category":"Sports & Exercise",
            "subcategory":"Golf",
            "type":"Entertainment"
        }
    ],
    "sg:phone":"+1 204 728 2374",
    "sg:postcode":"R7B 3M9",
    "sg:province":"MB",
    "sg:tags":[
        "course"
    ],
    "wof:name":"Sunnyside Golf Club",
    "wof:placetype":"venue"
},
  "geometry": {"coordinates":[-99.9619522095,49.8476982117],"type":"Point"}
}