{
  "type": "Feature",
  "properties": {
    "addr:full":"1009 5E Rue Val-D'Or QC J9P 3Z1",
    "addr:housenumber":"1009",
    "addr:postcode":"j9p 3z1",
    "addr:street":"5E Rue",
    "iso:country":"CA",
    "sg:address":"1009 5E Rue",
    "sg:city":"Val-D'Or",
    "sg:classifiers":[
        {
            "category":"Professional",
            "subcategory":"Business Services",
            "type":"Services"
        }
    ],
    "sg:phone":"+1 819 824 6583",
    "sg:postcode":"J9P 3Z1",
    "sg:province":"QC",
    "sg:tags":[
        "planning",
        "estate"
    ],
    "wof:name":"Turcotte, Diane",
    "wof:placetype":"venue"
},
  "geometry": {"coordinates":[-74.38098144529999,49.9116859436],"type":"Point"}
}