{
  "type": "Feature",
  "properties": {
    "addr:full":"62 Lunness Rd Etobicoke ON M8W 4M6",
    "addr:housenumber":"62",
    "addr:postcode":"m8w 4m6",
    "addr:street":"Lunness Rd",
    "iso:country":"CA",
    "sg:address":"62 Lunness Rd",
    "sg:city":"Etobicoke",
    "sg:classifiers":[
        {
            "category":"Organizations",
            "subcategory":"Religious Organization",
            "type":"Services"
        }
    ],
    "sg:phone":"+1 416 255 4942",
    "sg:postcode":"M8W 4M6",
    "sg:province":"ON",
    "sg:tags":[
        "church"
    ],
    "wof:name":"Holy Family Coptic Catholic",
    "wof:placetype":"venue"
},
  "geometry": {"coordinates":[-79.546318,43.606701],"type":"Point"}
}