{
  "type": "Feature",
  "properties": {
    "iso:country":"CA",
    "sg:address":"16 Towering Heights Blvd # 107",
    "sg:city":"St Catharines",
    "sg:classifiers":[
        {
            "category":"Real Estate",
            "subcategory":"Real Estate Agent",
            "type":"Services"
        }
    ],
    "sg:phone":"+1 905 688 6600",
    "sg:postcode":"L2T 3G9",
    "sg:province":"ON",
    "sg:tags":[
        "management"
    ],
    "wof:name":"Joseph Tonnos & Assoc Inc",
    "wof:placetype":"venue"
},
  "geometry": {"coordinates":[-79.236343,43.142429],"type":"Point"}
}