{
  "type": "Feature",
  "properties": {
    "addr:full":"770 Boul Du Cure-Boivin Boisbriand QC J7G 2A7",
    "addr:housenumber":"770",
    "addr:postcode":"j7g 2a7",
    "addr:street":"Boul Du Cure-Boivin",
    "iso:country":"CA",
    "sg:address":"770 Boul Du Cure-Boivin",
    "sg:city":"Boisbriand",
    "sg:classifiers":[
        {
            "category":"Home & Garden",
            "subcategory":"Building Materials",
            "type":"Retail Goods"
        }
    ],
    "sg:phone":"+1 514 875 0708",
    "sg:postcode":"J7G 2A7",
    "sg:province":"QC",
    "sg:tags":[
        "door"
    ],
    "wof:name":"Solaris Quebec Inc",
    "wof:placetype":"venue"
},
  "geometry": {"coordinates":[-73.8306884766,45.6235580444],"type":"Point"}
}