{
  "type": "Feature",
  "properties": {
    "addr:full":"279 High St Fort Erie ON L2A 3R4",
    "addr:housenumber":"279",
    "addr:postcode":"l2a 3r4",
    "addr:street":"High St",
    "iso:country":"CA",
    "sg:address":"279 High St",
    "sg:city":"Fort Erie",
    "sg:classifiers":[
        {
            "category":"Insurance",
            "subcategory":"Insurance Agent",
            "type":"Services"
        }
    ],
    "sg:phone":"+1 905 871 3623",
    "sg:postcode":"L2A 3R4",
    "sg:province":"ON",
    "wof:name":"Mc Gregor Miller Ltd",
    "wof:placetype":"venue"
},
  "geometry": {"coordinates":[-78.9156494141,42.9104614258],"type":"Point"}
}