{
  "type": "Feature",
  "properties": {
    "iso:country":"CA",
    "sg:address":"1439 Kingsway",
    "sg:city":"Vancouver",
    "sg:classifiers":[
        {
            "category":"Social Services",
            "type":"Services"
        }
    ],
    "sg:phone":"+1 604 708 3976",
    "sg:postcode":"V5N 2R6",
    "sg:province":"BC",
    "sg:tags":[
        "organization",
        "welfare"
    ],
    "wof:name":"Mainstream Assn For Proactive",
    "wof:placetype":"venue"
},
  "geometry": {"coordinates":[-123.074867,49.249752],"type":"Point"}
}