{
  "type": "Feature",
  "properties": {
    "iso:country":"CA",
    "sg:address":"PO Box 166",
    "sg:city":"Deline",
    "sg:classifiers":[
        {
            "category":"Organizations",
            "subcategory":"Professional Association",
            "type":"Services"
        }
    ],
    "sg:phone":"+1 867 589 4701",
    "sg:postcode":"X0E 0G0",
    "sg:province":"NT",
    "sg:tags":[
        "government"
    ],
    "wof:name":"Basic Awareness Program",
    "wof:placetype":"venue"
},
  "geometry": {"coordinates":[-123.421516419,65.1852264404],"type":"Point"}
}