{
  "type": "Feature",
  "properties": {
    "addr:full":"1556 Rue Belvedere S Sherbrooke QC J1H 4E5",
    "addr:housenumber":"1556",
    "addr:postcode":"j1h 4e5",
    "addr:street":"Rue Belvedere S",
    "iso:country":"CA",
    "sg:address":"1556 Rue Belvedere S",
    "sg:city":"Sherbrooke",
    "sg:classifiers":[
        {
            "category":"Freight",
            "type":"Transportation"
        }
    ],
    "sg:phone":"+1 819 566 9491",
    "sg:postcode":"J1H 4E5",
    "sg:province":"QC",
    "sg:tags":[
        "trucking"
    ],
    "wof:name":"Transport Spn",
    "wof:placetype":"venue"
},
  "geometry": {"coordinates":[-71.893845,45.382832],"type":"Point"}
}