{
  "type": "Feature",
  "properties": {
    "addr:full":"451 116 Rte Acton Vale QC J0H 1A0",
    "addr:housenumber":"451 116",
    "addr:postcode":"j0h 1a0",
    "addr:street":"Rte",
    "iso:country":"CA",
    "sg:address":"451 116 Rte",
    "sg:city":"Acton Vale",
    "sg:classifiers":[
        {
            "category":"Retail",
            "subcategory":"Repair Shop",
            "type":"Services"
        }
    ],
    "sg:phone":"+1 450 546 7227",
    "sg:postcode":"J0H 1A0",
    "sg:province":"QC",
    "sg:tags":[
        "trailer",
        "welding"
    ],
    "wof:name":"Soudures R & R St Amant Inc",
    "wof:placetype":"venue"
},
  "geometry": {"coordinates":[-72.42334700000001,45.629257],"type":"Point"}
}