{
  "type": "Feature",
  "properties": {
    "addr:full":"204 Rue Principale Saint-Adelme QC G0J 2B0",
    "addr:housenumber":"204",
    "addr:postcode":"g0j 2b0",
    "addr:street":"Rue Principale",
    "iso:country":"CA",
    "sg:address":"204 Rue Principale",
    "sg:city":"Saint-Adelme",
    "sg:classifiers":[
        {
            "category":"Education",
            "subcategory":"School",
            "type":"Public Place"
        }
    ],
    "sg:phone":"+1 418 733 4462",
    "sg:postcode":"G0J 2B0",
    "sg:province":"QC",
    "wof:name":"Ecole Emile Dube",
    "wof:placetype":"venue"
},
  "geometry": {"coordinates":[-67.31487300000001,48.821213],"type":"Point"}
}