{
  "type": "Feature",
  "properties": {
    "addr:full":"1321 Kirk Rd Binbrook ON L0R 1C0",
    "addr:housenumber":"1321",
    "addr:postcode":"l0r 1c0",
    "addr:street":"Kirk Rd",
    "iso:country":"CA",
    "sg:address":"1321 Kirk Rd",
    "sg:city":"Binbrook",
    "sg:classifiers":[
        {
            "category":"Building & Trades",
            "subcategory":"Plumbing",
            "type":"Services"
        }
    ],
    "sg:phone":"+1 905 692 3322",
    "sg:postcode":"L0R 1C0",
    "sg:province":"ON",
    "sg:tags":[
        "contractor"
    ],
    "wof:name":"Laidman Elwood Plumbing & Htg",
    "wof:placetype":"venue"
},
  "geometry": {"coordinates":[-79.787025,43.099201],"type":"Point"}
}