{
  "type": "Feature",
  "properties": {
    "addr:full":"5500 Rue Montpetit Rock Forest QC J1N 2S2",
    "addr:housenumber":"5500",
    "addr:postcode":"j1n 2s2",
    "addr:street":"Rue Montpetit",
    "iso:country":"CA",
    "sg:address":"5500 Rue Montpetit",
    "sg:city":"Rock Forest",
    "sg:classifiers":[
        {
            "category":"Building & Trades",
            "subcategory":"Construction",
            "type":"Services"
        }
    ],
    "sg:phone":"+1 819 822 4254",
    "sg:postcode":"J1N 2S2",
    "sg:province":"QC",
    "sg:tags":[
        "insulation",
        "heat",
        "contractor"
    ],
    "wof:name":"Indusco Isolation Inc",
    "wof:placetype":"venue"
},
  "geometry": {"coordinates":[-71.97421300000001,45.356373],"type":"Point"}
}