{
  "type": "Feature",
  "properties": {
    "addr:full":"Richmond Hill ON L4B 1L6",
    "addr:postcode":"l4b 1l6",
    "iso:country":"CA",
    "sg:city":"Richmond Hill",
    "sg:classifiers":[
        {
            "category":"Professional",
            "subcategory":"Advertising",
            "type":"Services"
        }
    ],
    "sg:phone":"+1 905 886 6677",
    "sg:postcode":"L4B 1L6",
    "sg:province":"ON",
    "sg:tags":[
        "counselor"
    ],
    "wof:name":"Kwan Go Advertising",
    "wof:placetype":"venue"
},
  "geometry": {"coordinates":[-79.387749,43.847263],"type":"Point"}
}