{
  "type": "Feature",
  "properties": {
    "iso:country":"CA",
    "sg:address":"6630 Tomken Rd",
    "sg:city":"Mississauga",
    "sg:classifiers":[
        {
            "category":"Freight",
            "type":"Transportation"
        }
    ],
    "sg:phone":"+1 905 696 0126",
    "sg:postcode":"L5T 1N1",
    "sg:province":"ON",
    "wof:name":"Kelron North American Logistic",
    "wof:placetype":"venue"
},
  "geometry": {"coordinates":[-79.6748886108,43.6578826904],"type":"Point"}
}