{
  "type": "Feature",
  "properties": {
    "addr:full":"5855 Boul Taschereau Brossard QC J4Z 1A5",
    "addr:housenumber":"5855",
    "addr:postcode":"j4z 1a5",
    "addr:street":"Boul Taschereau",
    "iso:country":"CA",
    "sg:address":"5855 Boul Taschereau",
    "sg:city":"Brossard",
    "sg:classifiers":[
        {
            "category":"Home & Garden",
            "subcategory":"Home Furnishings",
            "type":"Retail Goods"
        }
    ],
    "sg:phone":"+1 450 443 4303",
    "sg:postcode":"J4Z 1A5",
    "sg:province":"QC",
    "sg:tags":[
        "lighting",
        "fixture"
    ],
    "wof:name":"Multi Luminaire",
    "wof:placetype":"venue"
},
  "geometry": {"coordinates":[-73.46547698969999,45.4777412415],"type":"Point"}
}