{
  "type": "Feature",
  "properties": {
    "addr:full":"945 Ch Fresniere Saint-Eustache QC J7R 4K3",
    "addr:housenumber":"945",
    "addr:postcode":"j7r 4k3",
    "addr:street":"Ch Fresniere",
    "iso:country":"CA",
    "sg:address":"945 Ch Fresniere",
    "sg:city":"Saint-Eustache",
    "sg:classifiers":[
        {
            "category":"Retail",
            "subcategory":"Auto Repair",
            "type":"Services"
        }
    ],
    "sg:phone":"+1 450 473 9100",
    "sg:postcode":"J7R 4K3",
    "sg:province":"QC",
    "sg:tags":[
        "body",
        "automobile",
        "painting"
    ],
    "wof:name":"F Grenier & Fils Enr",
    "wof:placetype":"venue"
},
  "geometry": {"coordinates":[-74.009407,45.569836],"type":"Point"}
}