{
  "type": "Feature",
  "properties": {
    "addr:full":"4 DE LA Longue Pt Petite-Vallee QC G0E 1Y0",
    "addr:housenumber":"4",
    "addr:postcode":"g0e 1y0",
    "addr:street":"De La Longue Pt Petite-Vallee",
    "iso:country":"CA",
    "sg:address":"4 DE LA Longue Pt",
    "sg:city":"Petite-Vallee",
    "sg:classifiers":[
        {
            "category":"Restaurant",
            "type":"Food & Drink"
        }
    ],
    "sg:phone":"+1 418 393 2222",
    "sg:postcode":"G0E 1Y0",
    "sg:province":"QC",
    "wof:name":"Cafe DE LA Vieille Forge",
    "wof:placetype":"venue"
},
  "geometry": {"coordinates":[-65.04378509519999,49.2218780518],"type":"Point"}
}