{
  "type": "Feature",
  "properties": {
    "iso:country":"CA",
    "sg:address":"710 Prince St",
    "sg:city":"Truro",
    "sg:classifiers":[
        {
            "category":"Professional",
            "subcategory":"Accounting & Tax Preparation",
            "type":"Services"
        }
    ],
    "sg:phone":"+1 902 895 1641",
    "sg:postcode":"B2N 1G6",
    "sg:province":"NS",
    "sg:tags":[
        "accountant"
    ],
    "wof:name":"Pricewaterhouse Coopers",
    "wof:placetype":"venue"
},
  "geometry": {"coordinates":[-63.2808113098,45.3649673462],"type":"Point"}
}