{
  "type": "Feature",
  "properties": {
    "iso:country":"CA",
    "sg:address":"70 Williams St",
    "sg:city":"Port Moody",
    "sg:classifiers":[
        {
            "category":"Manufacturing",
            "subcategory":"Metals",
            "type":"Manufacturing & Wholesale Goods"
        }
    ],
    "sg:phone":"+1 604 469 4480",
    "sg:postcode":"V3H 2R5",
    "sg:province":"BC",
    "sg:tags":[
        "steel"
    ],
    "wof:name":"Rodger Alain Steel Enterprises",
    "wof:placetype":"venue"
},
  "geometry": {"coordinates":[-122.845261,49.27734],"type":"Point"}
}