{
  "type": "Feature",
  "properties": {
    "addr:full":"239 Harrow St Winnipeg MB R3M 2Y3",
    "addr:housenumber":"239",
    "addr:postcode":"r3m 2y3",
    "addr:street":"Harrow St",
    "iso:country":"CA",
    "sg:address":"239 Harrow St",
    "sg:city":"Winnipeg",
    "sg:classifiers":[
        {
            "category":"Education",
            "subcategory":"School",
            "type":"Public Place"
        }
    ],
    "sg:phone":"+1 204 475 1386",
    "sg:postcode":"R3M 2Y3",
    "sg:province":"MB",
    "wof:name":"St Ignatius School",
    "wof:placetype":"venue"
},
  "geometry": {"coordinates":[-97.16339111329999,49.8673362732],"type":"Point"}
}