{
  "type": "Feature",
  "properties": {
    "iso:country":"CA",
    "sg:address":"2037 Boul Du Saguenay",
    "sg:city":"Jonquiere",
    "sg:classifiers":[
        {
            "category":"Farming",
            "subcategory":"Dairy Farm",
            "type":"Manufacturing & Wholesale Goods"
        }
    ],
    "sg:phone":"+1 418 543 5115",
    "sg:postcode":"G7S 4J1",
    "sg:province":"QC",
    "sg:tags":[
        "product"
    ],
    "wof:name":"Distributions Trois S Inc",
    "wof:placetype":"venue"
},
  "geometry": {"coordinates":[-71.1299285889,48.4382286072],"type":"Point"}
}