{
  "type": "Feature",
  "properties": {
    "iso:country":"CA",
    "sg:city":"Kitchener",
    "sg:classifiers":[
        {
            "category":"Shopping",
            "type":"Retail Goods"
        }
    ],
    "sg:phone":"+1 519 579 6333",
    "sg:postcode":"N2B 3T2",
    "sg:province":"ON",
    "sg:tags":[
        "telephone",
        "cellular"
    ],
    "wof:name":"Rogers At & T Store",
    "wof:placetype":"venue"
},
  "geometry": {"coordinates":[-80.4569320679,43.4666633606],"type":"Point"}
}