{
  "type": "Feature",
  "properties": {
    "addr:full":"Hwy 557 Blind River ON P0R 1B0",
    "addr:postcode":"p0r 1b0",
    "addr:street":"Hwy 557",
    "iso:country":"CA",
    "sg:address":"Hwy 557",
    "sg:city":"Blind River",
    "sg:classifiers":[
        {
            "category":"Travel",
            "subcategory":"Hotels & Motels",
            "type":"Entertainment"
        }
    ],
    "sg:phone":"+1 705 848 2881",
    "sg:postcode":"P0R 1B0",
    "sg:province":"ON",
    "sg:tags":[
        "tourist",
        "accommodation"
    ],
    "wof:name":"Lodge on Lake Matinenda Ont",
    "wof:placetype":"venue"
},
  "geometry": {"coordinates":[-82.9532775879,46.1855316162],"type":"Point"}
}