{
  "type": "Feature",
  "properties": {
    "addr:full":"4440 Ontario St Beamsville ON L0R 1B5",
    "addr:housenumber":"4440",
    "addr:postcode":"l0r 1b5",
    "addr:street":"Ontario St",
    "iso:country":"CA",
    "sg:address":"4440 Ontario St",
    "sg:city":"Beamsville",
    "sg:classifiers":[
        {
            "category":"Building & Trades",
            "subcategory":"Plumbing",
            "type":"Services"
        }
    ],
    "sg:phone":"+1 905 563 8341",
    "sg:postcode":"L0R 1B5",
    "sg:province":"ON",
    "sg:tags":[
        "contractor"
    ],
    "wof:name":"H Cornelius & Son",
    "wof:placetype":"venue"
},
  "geometry": {"coordinates":[-79.476974,43.173096],"type":"Point"}
}