{
  "type": "Feature",
  "properties": {
    "addr:full":"571 16th St W Prince Albert SK S6V 3V9",
    "addr:housenumber":"571",
    "addr:postcode":"s6v 3v9",
    "addr:street":"16Th St",
    "iso:country":"CA",
    "sg:address":"571 16th St W",
    "sg:city":"Prince Albert",
    "sg:classifiers":[
        {
            "category":"Retail",
            "subcategory":"Repair Shop",
            "type":"Services"
        }
    ],
    "sg:phone":"+1 306 764 5028",
    "sg:postcode":"S6V 3V9",
    "sg:province":"SK",
    "sg:tags":[
        "vinyl"
    ],
    "wof:name":"Fibrenew Industries",
    "wof:placetype":"venue"
},
  "geometry": {"coordinates":[-105.768272,53.198242],"type":"Point"}
}