{
  "type": "Feature",
  "properties": {
    "iso:country":"CA",
    "sg:city":"Mississauga",
    "sg:classifiers":[
        {
            "category":"Wholesale",
            "subcategory":"Electrical",
            "type":"Manufacturing & Wholesale Goods"
        }
    ],
    "sg:phone":"+1 905 501 1500",
    "sg:postcode":"L4Z 3E2",
    "sg:province":"ON",
    "sg:tags":[
        "communication",
        "duplicating",
        "machine",
        "equipment",
        "facsimile",
        "copying"
    ],
    "wof:name":"4 Office Automation",
    "wof:placetype":"venue"
},
  "geometry": {"coordinates":[-79.66947937010001,43.6328239441],"type":"Point"}
}