{
  "type": "Feature",
  "properties": {
    "iso:country":"CA",
    "sg:address":"4898 Kitchener St",
    "sg:city":"Niagara Falls",
    "sg:classifiers":[
        {
            "category":"Organizations",
            "subcategory":"Religious Organization",
            "type":"Services"
        }
    ],
    "sg:phone":"+1 905 354 0191",
    "sg:postcode":"L2G 1A7",
    "sg:province":"ON",
    "sg:tags":[
        "church"
    ],
    "wof:name":"Korean Presbyterian Church",
    "wof:placetype":"venue"
},
  "geometry": {"coordinates":[-79.07373046879999,43.095451355],"type":"Point"}
}