{
  "type": "Feature",
  "properties": {
    "addr:full":"201 134E Rue Beauceville QC G5X 3H9",
    "addr:housenumber":"201",
    "addr:postcode":"g5x 3h9",
    "addr:street":"134E Rue",
    "iso:country":"CA",
    "sg:address":"201 134E Rue",
    "sg:city":"Beauceville",
    "sg:classifiers":[
        {
            "category":"Manufacturing",
            "subcategory":"Building Materials",
            "type":"Manufacturing & Wholesale Goods"
        }
    ],
    "sg:phone":"+1 418 774 3606",
    "sg:postcode":"G5X 3H9",
    "sg:province":"QC",
    "wof:name":"Bois Ouvre DE Beauceville 1992",
    "wof:placetype":"venue"
},
  "geometry": {"coordinates":[-70.78247833250001,46.2143630981],"type":"Point"}
}