{
  "type": "Feature",
  "properties": {
    "addr:full":"Mississauga ON L4W 3C6",
    "addr:postcode":"l4w 3c6",
    "iso:country":"CA",
    "sg:city":"Mississauga",
    "sg:classifiers":[
        {
            "category":"Wholesale",
            "subcategory":"Hardware",
            "type":"Manufacturing & Wholesale Goods"
        }
    ],
    "sg:phone":"+1 905 795 1515",
    "sg:postcode":"L4W 3C6",
    "sg:province":"ON",
    "sg:tags":[
        "parts",
        "refrigerating"
    ],
    "wof:name":"United Refrigeration of Canada",
    "wof:placetype":"venue"
},
  "geometry": {"coordinates":[-79.64653,43.656513],"type":"Point"}
}