{
  "type": "Feature",
  "properties": {
    "addr:full":"828 Boul Decarie # 102 Saint-Laurent QC H4L 3L9",
    "addr:housenumber":"828",
    "addr:postcode":"h4l 3l9",
    "addr:street":"Boul Decarie # 102 Saint-Laurent",
    "iso:country":"CA",
    "sg:address":"828 Boul Decarie # 102",
    "sg:city":"Saint-Laurent",
    "sg:classifiers":[
        {
            "category":"Personal",
            "subcategory":"Beauty Salon",
            "type":"Services"
        }
    ],
    "sg:phone":"+1 514 748 8284",
    "sg:postcode":"H4L 3L9",
    "sg:province":"QC",
    "wof:name":"Salon Michel",
    "wof:placetype":"venue"
},
  "geometry": {"coordinates":[-73.679199,45.511757],"type":"Point"}
}