{
  "type": "Feature",
  "properties": {
    "addr:full":"Oil Springs ON N0N 1P0",
    "addr:postcode":"n0n 1p0",
    "iso:country":"CA",
    "sg:city":"Oil Springs",
    "sg:classifiers":[
        {
            "category":"Sports & Exercise",
            "subcategory":"Golf",
            "type":"Entertainment"
        }
    ],
    "sg:phone":"+1 519 834 2552",
    "sg:postcode":"N0N 1P0",
    "sg:province":"ON",
    "sg:tags":[
        "course"
    ],
    "wof:name":"Black Creek Golf Course",
    "wof:placetype":"venue"
},
  "geometry": {"coordinates":[-82.11998,42.783772],"type":"Point"}
}