{
  "type": "Feature",
  "properties": {
    "addr:full":"Winnipeg MB R3T 2G7",
    "addr:postcode":"r3t 2g7",
    "iso:country":"CA",
    "sg:city":"Winnipeg",
    "sg:classifiers":[
        {
            "category":"Health Services",
            "subcategory":"Doctor",
            "type":"Services"
        }
    ],
    "sg:phone":"+1 204 269 3498",
    "sg:postcode":"R3T 2G7",
    "sg:province":"MB",
    "sg:tags":[
        "dentist"
    ],
    "wof:name":"Dillon, John DDS",
    "wof:placetype":"venue"
},
  "geometry": {"coordinates":[-97.15315246580001,49.8224563599],"type":"Point"}
}