{
  "type": "Feature",
  "properties": {
    "addr:full":"1050 Main St E Cambridge ON N1R 7G8",
    "addr:housenumber":"1050",
    "addr:postcode":"n1r 7g8",
    "addr:street":"Main St E",
    "iso:country":"CA",
    "sg:address":"1050 Main St E",
    "sg:city":"Cambridge",
    "sg:classifiers":[
        {
            "category":"Wholesale",
            "subcategory":"Scrap",
            "type":"Manufacturing & Wholesale Goods"
        }
    ],
    "sg:phone":"+1 519 621 9840",
    "sg:postcode":"N1R 7G8",
    "sg:province":"ON",
    "sg:tags":[
        "metal",
        "iron"
    ],
    "wof:name":"Woznuk Bros Ltd Steel & Metal",
    "wof:placetype":"venue"
},
  "geometry": {"coordinates":[-80.278603,43.359818],"type":"Point"}
}