{
  "type": "Feature",
  "properties": {
    "addr:full":"1336 Granville St Vancouver BC V6Z 1M8",
    "addr:housenumber":"1336",
    "addr:postcode":"v6z 1m8",
    "addr:street":"Granville St",
    "iso:country":"CA",
    "sg:address":"1336 Granville St",
    "sg:city":"Vancouver",
    "sg:classifiers":[
        {
            "category":"Travel",
            "subcategory":"Hotels & Motels",
            "type":"Entertainment"
        }
    ],
    "sg:phone":"+1 604 683 8505",
    "sg:postcode":"V6Z 1M8",
    "sg:province":"BC",
    "wof:name":"Cecil Hotel",
    "wof:placetype":"venue"
},
  "geometry": {"coordinates":[-123.128074646,49.2757339478],"type":"Point"}
}