{
  "type": "Feature",
  "properties": {
    "addr:full":"40 Twenty Second St Etobicoke ON M8V 3M1",
    "addr:housenumber":"40",
    "addr:postcode":"m8v 3m1",
    "addr:street":"Twenty Second St",
    "iso:country":"CA",
    "sg:address":"40 Twenty Second St",
    "sg:city":"Etobicoke",
    "sg:classifiers":[
        {
            "category":"Building & Trades",
            "subcategory":"Construction",
            "type":"Services"
        }
    ],
    "sg:phone":"+1 416 255 7288",
    "sg:postcode":"M8V 3M1",
    "sg:province":"ON",
    "sg:tags":[
        "equipment",
        "computer",
        "rooms"
    ],
    "wof:name":"40 22nd St Computer Room Envir",
    "wof:placetype":"venue"
},
  "geometry": {"coordinates":[-79.52206420900001,43.5985488892],"type":"Point"}
}