{
  "type": "Feature",
  "properties": {
    "addr:full":"5415 Elm St Niagara Falls ON L2E 2V5",
    "addr:housenumber":"5415",
    "addr:postcode":"l2e 2v5",
    "addr:street":"Elm St",
    "iso:country":"CA",
    "sg:address":"5415 Elm St",
    "sg:city":"Niagara Falls",
    "sg:classifiers":[
        {
            "category":"Retail",
            "subcategory":"Repair Shop",
            "type":"Services"
        }
    ],
    "sg:phone":"+1 905 354 9984",
    "sg:postcode":"L2E 2V5",
    "sg:province":"ON",
    "sg:tags":[
        "lock",
        "locksmith"
    ],
    "wof:name":"AAA Mobile Locksmith Niagara",
    "wof:placetype":"venue"
},
  "geometry": {"coordinates":[-79.0846939087,43.1078262329],"type":"Point"}
}