{
  "type": "Feature",
  "properties": {
    "addr:full":"Main St Fairy Glen SK S0E 0T0",
    "addr:postcode":"s0e 0t0",
    "addr:street":"Main St",
    "iso:country":"CA",
    "sg:address":"Main St",
    "sg:city":"Fairy Glen",
    "sg:classifiers":[
        {
            "category":"Wholesale",
            "subcategory":"Petroleum",
            "type":"Manufacturing & Wholesale Goods"
        }
    ],
    "sg:phone":"+1 306 752 4162",
    "sg:postcode":"S0E 0T0",
    "sg:province":"SK",
    "sg:tags":[
        "oil"
    ],
    "wof:name":"Fairy Glen CO-OP Oil",
    "wof:placetype":"venue"
},
  "geometry": {"coordinates":[-104.512383,53.058834],"type":"Point"}
}