{
  "type": "Feature",
  "properties": {
    "iso:country":"CA",
    "sg:address":"90C Centurian Dr # 203",
    "sg:city":"Markham",
    "sg:classifiers":[
        {
            "category":"Insurance",
            "subcategory":"Insurance Agent",
            "type":"Services"
        }
    ],
    "sg:phone":"+1 905 946 9995",
    "sg:postcode":"L3R 8C5",
    "sg:province":"ON",
    "sg:tags":[
        "adjuster"
    ],
    "wof:name":"Vanler Insurance Adjusters",
    "wof:placetype":"venue"
},
  "geometry": {"coordinates":[-79.3656234741,43.8521957397],"type":"Point"}
}