{
  "type": "Feature",
  "properties": {
    "addr:full":"1611 18 Ave Coaldale AB T1M 1K7",
    "addr:housenumber":"1611",
    "addr:postcode":"t1m 1k7",
    "addr:street":"18 Ave",
    "iso:country":"CA",
    "sg:address":"1611 18 Ave",
    "sg:city":"Coaldale",
    "sg:classifiers":[
        {
            "category":"Freight",
            "type":"Transportation"
        }
    ],
    "sg:phone":"+1 403 345 2026",
    "sg:postcode":"T1M 1K7",
    "sg:province":"AB",
    "sg:tags":[
        "trucking"
    ],
    "wof:name":"Venture Inc",
    "wof:placetype":"venue"
},
  "geometry": {"coordinates":[-112.617149,49.73003],"type":"Point"}
}