{
  "type": "Feature",
  "properties": {
    "addr:full":"425 Avenue P S Saskatoon SK S7M 2W5",
    "addr:housenumber":"425",
    "addr:postcode":"s7m 2w5",
    "addr:street":"Avenue",
    "iso:country":"CA",
    "sg:address":"425 Avenue P S",
    "sg:city":"Saskatoon",
    "sg:classifiers":[
        {
            "category":"Wholesale",
            "subcategory":"Machinery & Supplies",
            "type":"Manufacturing & Wholesale Goods"
        }
    ],
    "sg:phone":"+1 306 384 1455",
    "sg:postcode":"S7M 2W5",
    "sg:province":"SK",
    "sg:tags":[
        "poultry",
        "equipment"
    ],
    "wof:name":"Betker Livestock Equip Sales",
    "wof:placetype":"venue"
},
  "geometry": {"coordinates":[-106.694298,52.123665],"type":"Point"}
}