{
  "type": "Feature",
  "properties": {
    "addr:full":"1039 Av Du Palais Saint-Joseph-DE-Beauce QC G0S 2V0",
    "addr:housenumber":"1039",
    "addr:postcode":"g0s 2v0",
    "addr:street":"Av Du Palais",
    "iso:country":"CA",
    "sg:address":"1039 Av Du Palais",
    "sg:city":"Saint-Joseph-DE-Beauce",
    "sg:classifiers":[
        {
            "category":"Utilities",
            "subcategory":"Fuel Oil & Lpg",
            "type":"Services"
        }
    ],
    "sg:phone":"+1 418 397 6609",
    "sg:postcode":"G0S 2V0",
    "sg:province":"QC",
    "sg:tags":[
        "wood"
    ],
    "wof:name":"Eloi Maheu Inc",
    "wof:placetype":"venue"
},
  "geometry": {"coordinates":[-70.8735580444,46.301574707],"type":"Point"}
}