{
  "type": "Feature",
  "properties": {
    "addr:full":"Brampton ON L6V 4H4",
    "addr:postcode":"l6v 4h4",
    "iso:country":"CA",
    "sg:city":"Brampton",
    "sg:classifiers":[
        {
            "category":"Shopping",
            "subcategory":"Pharmacy",
            "type":"Retail Goods"
        }
    ],
    "sg:phone":"+1 905 455 3381",
    "sg:postcode":"L6V 4H4",
    "sg:province":"ON",
    "wof:name":"Vodden Medical Arts Pharmacy",
    "wof:placetype":"venue"
},
  "geometry": {"coordinates":[-79.76788330079999,43.6945457458],"type":"Point"}
}