{
  "type": "Feature",
  "properties": {
    "addr:full":"Greenspond NL A0G 2N0",
    "addr:postcode":"a0g 2n0",
    "iso:country":"CA",
    "sg:city":"Greenspond",
    "sg:classifiers":[
        {
            "category":"Food & Beverages",
            "subcategory":"Groceries & Convenience Stores",
            "type":"Retail Goods"
        }
    ],
    "sg:phone":"+1 709 269 3411",
    "sg:postcode":"A0G 2N0",
    "sg:province":"NL",
    "sg:tags":[
        "grocer"
    ],
    "wof:name":"Island Mini Mart",
    "wof:placetype":"venue"
},
  "geometry": {"coordinates":[-53.570324,49.069061],"type":"Point"}
}