{
  "type": "Feature",
  "properties": {
    "addr:full":"Glencoe ON N0L 1M0",
    "addr:postcode":"n0l 1m0",
    "iso:country":"CA",
    "sg:city":"Glencoe",
    "sg:classifiers":[
        {
            "category":"Insurance",
            "subcategory":"Insurance Agent",
            "type":"Services"
        }
    ],
    "sg:phone":"+1 519 287 2955",
    "sg:postcode":"N0L 1M0",
    "sg:province":"ON",
    "wof:name":"Mc Coll Financial Svc",
    "wof:placetype":"venue"
},
  "geometry": {"coordinates":[-81.712272644,42.7486953735],"type":"Point"}
}