{
  "type": "Feature",
  "properties": {
    "addr:full":"341 Collishaw St Moncton NB E1C 9R2",
    "addr:housenumber":"341",
    "addr:postcode":"e1c 9r2",
    "addr:street":"Collishaw St",
    "iso:country":"CA",
    "sg:address":"341 Collishaw St",
    "sg:city":"Moncton",
    "sg:classifiers":[
        {
            "category":"Professional",
            "subcategory":"Advertising",
            "type":"Services"
        }
    ],
    "sg:phone":"+1 506 858 5952",
    "sg:postcode":"E1C 9R2",
    "sg:province":"NB",
    "sg:tags":[
        "concrete",
        "distribution",
        "restoration",
        "cleaning",
        "repair"
    ],
    "wof:name":"Arrow Construction Products",
    "wof:placetype":"venue"
},
  "geometry": {"coordinates":[-64.81299591059999,46.0971298218],"type":"Point"}
}