{
  "type": "Feature",
  "properties": {
    "addr:full":"122 County Rd 4 Peterborough ON K9L 1V6",
    "addr:housenumber":"122",
    "addr:postcode":"k9l 1v6",
    "addr:street":"County Rd 4",
    "iso:country":"CA",
    "sg:address":"122 County Rd 4",
    "sg:city":"Peterborough",
    "sg:classifiers":[
        {
            "category":"Building & Trades",
            "subcategory":"Construction",
            "type":"Services"
        }
    ],
    "sg:phone":"+1 705 749 1887",
    "sg:postcode":"K9L 1V6",
    "sg:province":"ON",
    "sg:tags":[
        "cabinet",
        "maker",
        "woodworker"
    ],
    "wof:name":"Mintlaw Woodcrafters",
    "wof:placetype":"venue"
},
  "geometry": {"coordinates":[-78.32131200000001,44.300732],"type":"Point"}
}