{
  "type": "Feature",
  "properties": {
    "addr:full":"121 Duke St Dryden ON P8N 1G4",
    "addr:housenumber":"121",
    "addr:postcode":"p8n 1g4",
    "addr:street":"Duke St",
    "iso:country":"CA",
    "sg:address":"121 Duke St",
    "sg:city":"Dryden",
    "sg:classifiers":[
        {
            "category":"Retail",
            "subcategory":"Self-service Laundry",
            "type":"Services"
        }
    ],
    "sg:phone":"+1 807 223 4599",
    "sg:postcode":"P8N 1G4",
    "sg:province":"ON",
    "wof:name":"Highlander Centre",
    "wof:placetype":"venue"
},
  "geometry": {"coordinates":[-92.8331069946,49.7822570801],"type":"Point"}
}