{
  "type": "Feature",
  "properties": {
    "addr:full":"382 Rue Craig Richmond QC J0B 2H0",
    "addr:housenumber":"382",
    "addr:postcode":"j0b 2h0",
    "addr:street":"Rue Craig",
    "iso:country":"CA",
    "sg:address":"382 Rue Craig",
    "sg:city":"Richmond",
    "sg:classifiers":[
        {
            "category":"Restaurant",
            "type":"Food & Drink"
        }
    ],
    "sg:phone":"+1 819 826 0826",
    "sg:postcode":"J0B 2H0",
    "sg:province":"QC",
    "wof:name":"Restaurant Chez Mike",
    "wof:placetype":"venue"
},
  "geometry": {"coordinates":[-72.1361083984,45.6615562439],"type":"Point"}
}