{
  "type": "Feature",
  "properties": {
    "addr:full":"74 Devon Rd Brampton ON L6T 5H3",
    "addr:housenumber":"74",
    "addr:postcode":"l6t 5h3",
    "addr:street":"Devon Rd",
    "iso:country":"CA",
    "sg:address":"74 Devon Rd",
    "sg:city":"Brampton",
    "sg:classifiers":[
        {
            "category":"Manufacturing",
            "subcategory":"Furniture",
            "type":"Manufacturing & Wholesale Goods"
        }
    ],
    "sg:phone":"+1 905 793 1857",
    "sg:postcode":"L6T 5H3",
    "sg:province":"ON",
    "sg:tags":[
        "chair"
    ],
    "wof:name":"Janpath Metal Fabrication Ltd",
    "wof:placetype":"venue"
},
  "geometry": {"coordinates":[-79.68029,43.73362],"type":"Point"}
}