{
  "type": "Feature",
  "properties": {
    "addr:full":"21 Montrose St Rosedale Valley AB T4L 1Y3",
    "addr:housenumber":"21",
    "addr:postcode":"t4l 1y3",
    "addr:street":"Montrose St",
    "iso:country":"CA",
    "sg:address":"21 Montrose St",
    "sg:city":"Rosedale Valley",
    "sg:classifiers":[
        {
            "category":"Retail",
            "subcategory":"Portrait Studio",
            "type":"Services"
        }
    ],
    "sg:phone":"+1 403 782 5407",
    "sg:postcode":"T4L 1Y3",
    "sg:province":"AB",
    "sg:tags":[
        "photographer"
    ],
    "wof:name":"Jerry Livadney Photography Inc",
    "wof:placetype":"venue"
},
  "geometry": {"coordinates":[-113.747559,52.479862],"type":"Point"}
}