{
  "type": "Feature",
  "properties": {
    "addr:full":"PO Box 4804 STN Main Taber AB T1G 2E1",
    "addr:housenumber":"po",
    "addr:postcode":"t1g 2e1",
    "addr:street":"Box 4804 Stn Main",
    "iso:country":"CA",
    "sg:address":"PO Box 4804 STN Main",
    "sg:city":"Taber",
    "sg:classifiers":[
        {
            "category":"Mining & Drilling",
            "type":"Manufacturing & Wholesale Goods"
        }
    ],
    "sg:phone":"+1 403 223 1730",
    "sg:postcode":"T1G 2E1",
    "sg:province":"AB",
    "sg:tags":[
        "field",
        "oil"
    ],
    "wof:name":"Allwest Line Locators Ltd",
    "wof:placetype":"venue"
},
  "geometry": {"coordinates":[-112.12713599999999,49.787216],"type":"Point"}
}