{
  "type": "Feature",
  "properties": {
    "addr:full":"4304 Industrial Ave Onoway AB T0E 1V0",
    "addr:housenumber":"4304",
    "addr:postcode":"t0e 1v0",
    "addr:street":"Industrial Ave",
    "iso:country":"CA",
    "sg:address":"4304 Industrial Ave",
    "sg:city":"Onoway",
    "sg:classifiers":[
        {
            "category":"Utilities",
            "subcategory":"Refuse",
            "type":"Services"
        }
    ],
    "sg:phone":"+1 780 967 4450",
    "sg:postcode":"T0E 1V0",
    "sg:province":"AB",
    "sg:tags":[
        "garbage",
        "collection"
    ],
    "wof:name":"Stand-Stone Waste Svc Ltd",
    "wof:placetype":"venue"
},
  "geometry": {"coordinates":[-114.17598700000001,53.706974],"type":"Point"}
}