{
  "type": "Feature",
  "properties": {
    "addr:full":"Knowlton QC J0E 1V0",
    "addr:postcode":"j0e 1v0",
    "addr:street":"Knowlton",
    "iso:country":"CA",
    "sg:city":"Knowlton",
    "sg:classifiers":[
        {
            "category":"Shopping",
            "subcategory":"Clothing, Apparel, & Fashions",
            "type":"Retail Goods"
        }
    ],
    "sg:phone":"+1 450 242 5862",
    "sg:postcode":"J0E 1V0",
    "sg:province":"QC",
    "sg:tags":[
        "item",
        "boutique"
    ],
    "wof:name":"Station Knowlton",
    "wof:placetype":"venue"
},
  "geometry": {"coordinates":[-72.51102400000001,45.215302],"type":"Point"}
}