{
  "type": "Feature",
  "properties": {
    "addr:full":"321 1 St NW Medicine Hat AB T1A 6H4",
    "addr:housenumber":"321 1",
    "addr:postcode":"t1a 6h4",
    "addr:street":"St Nw",
    "iso:country":"CA",
    "sg:address":"321 1 St NW",
    "sg:city":"Medicine Hat",
    "sg:classifiers":[
        {
            "category":"Building & Trades",
            "subcategory":"Construction",
            "type":"Services"
        }
    ],
    "sg:phone":"+1 403 526 1121",
    "sg:postcode":"T1A 6H4",
    "sg:province":"AB",
    "sg:tags":[
        "contractor",
        "material",
        "floor"
    ],
    "wof:name":"Jim's Hardwood Flooring",
    "wof:placetype":"venue"
},
  "geometry": {"coordinates":[-110.694885,50.042679],"type":"Point"}
}