{
  "type": "Feature",
  "properties": {
    "addr:full":"420 Malabar Dr Kingston ON K7M 8Z5",
    "addr:housenumber":"420",
    "addr:postcode":"k7m 8z5",
    "addr:street":"Malabar Dr",
    "iso:country":"CA",
    "sg:address":"420 Malabar Dr",
    "sg:city":"Kingston",
    "sg:classifiers":[
        {
            "category":"Building & Trades",
            "subcategory":"Construction",
            "type":"Services"
        }
    ],
    "sg:phone":"+1 613 536 0385",
    "sg:postcode":"K7M 8Z5",
    "sg:province":"ON",
    "sg:tags":[
        "general",
        "contractor"
    ],
    "wof:name":"Destin Homes Corp",
    "wof:placetype":"venue"
},
  "geometry": {"coordinates":[-76.551979,44.241707],"type":"Point"}
}