{
  "type": "Feature",
  "properties": {
    "iso:country":"CA",
    "sg:address":"5109 Rue Frontenac",
    "sg:city":"Lac-Megantic",
    "sg:classifiers":[
        {
            "category":"Professional",
            "subcategory":"Lawyer & Legal Services",
            "type":"Services"
        }
    ],
    "sg:phone":"+1 819 583 3833",
    "sg:postcode":"G6B 1H2",
    "sg:province":"QC",
    "sg:tags":[
        "attorney"
    ],
    "wof:name":"Monty Coulombe",
    "wof:placetype":"venue"
},
  "geometry": {"coordinates":[-70.88442230219999,45.5769767761],"type":"Point"}
}