{
  "type": "Feature",
  "properties": {
    "addr:full":"1028 Queen St New Dundee ON N0B 2E0",
    "addr:housenumber":"1028",
    "addr:postcode":"n0b 2e0",
    "addr:street":"Queen St",
    "iso:country":"CA",
    "sg:address":"1028 Queen St",
    "sg:city":"New Dundee",
    "sg:classifiers":[
        {
            "category":"Shopping",
            "type":"Retail Goods"
        }
    ],
    "sg:phone":"+1 519 696 3327",
    "sg:postcode":"N0B 2E0",
    "sg:province":"ON",
    "sg:tags":[
        "wedding",
        "supply",
        "hall",
        "auditorium"
    ],
    "wof:name":"New Dundee Community Ctr",
    "wof:placetype":"venue"
},
  "geometry": {"coordinates":[-80.53434799999999,43.344105],"type":"Point"}
}