{
  "type": "Feature",
  "properties": {
    "addr:full":"North York ON M2N 6C6",
    "addr:postcode":"m2n 6c6",
    "iso:country":"CA",
    "sg:city":"North York",
    "sg:classifiers":[
        {
            "category":"Professional",
            "subcategory":"Accounting & Tax Preparation",
            "type":"Services"
        }
    ],
    "sg:phone":"+1 416 226 3811",
    "sg:postcode":"M2N 6C6",
    "sg:province":"ON",
    "sg:tags":[
        "accountant"
    ],
    "wof:name":"Greenwood, Sheldon R CA",
    "wof:placetype":"venue"
},
  "geometry": {"coordinates":[-79.4122924805,43.7676544189],"type":"Point"}
}