{
  "type": "Feature",
  "properties": {
    "addr:full":"Coquitlam BC V3C 3L4",
    "addr:postcode":"bc v3c 3l4",
    "iso:country":"CA",
    "sg:city":"Coquitlam",
    "sg:classifiers":[
        {
            "category":"Shopping",
            "subcategory":"Bicycles & Sporting Goods",
            "type":"Retail Goods"
        }
    ],
    "sg:phone":"+1 604 941 6933",
    "sg:postcode":"V3C 3L4",
    "sg:province":"BC",
    "sg:tags":[
        "gun",
        "gunsmith"
    ],
    "wof:name":"Smokin Gun Fx",
    "wof:placetype":"venue"
},
  "geometry": {"coordinates":[-122.790878296,49.2683792114],"type":"Point"}
}