{
  "type": "Feature",
  "properties": {
    "addr:full":"159 Prince Albert Rd Dartmouth NS B2Y 1M5",
    "addr:housenumber":"159",
    "addr:postcode":"b2y 1m5",
    "addr:street":"Prince Albert Rd",
    "iso:country":"CA",
    "sg:address":"159 Prince Albert Rd",
    "sg:city":"Dartmouth",
    "sg:classifiers":[
        {
            "category":"Travel",
            "subcategory":"Hotels & Motels",
            "type":"Entertainment"
        }
    ],
    "sg:phone":"+1 902 463 6089",
    "sg:postcode":"B2Y 1M5",
    "sg:province":"NS",
    "sg:tags":[
        "breakfast",
        "accommodation",
        "bed"
    ],
    "wof:name":"Turtle Grove Bed & Breakfast",
    "wof:placetype":"venue"
},
  "geometry": {"coordinates":[-63.559685,44.674706],"type":"Point"}
}