{
  "type": "Feature",
  "properties": {
    "addr:full":"570 Dundas St W Toronto ON M5T 1H5",
    "addr:housenumber":"570",
    "addr:postcode":"m5t 1h5",
    "addr:street":"Dundas St W",
    "iso:country":"CA",
    "sg:address":"570 Dundas St W",
    "sg:city":"Toronto",
    "sg:classifiers":[
        {
            "category":"Shopping",
            "subcategory":"Optical Goods",
            "type":"Retail Goods"
        }
    ],
    "sg:phone":"+1 416 596 0824",
    "sg:postcode":"M5T 1H5",
    "sg:province":"ON",
    "sg:tags":[
        "optician"
    ],
    "wof:name":"Bright Eyes Optical",
    "wof:placetype":"venue"
},
  "geometry": {"coordinates":[-79.4001541138,43.6525993347],"type":"Point"}
}