{
  "type": "Feature",
  "properties": {
    "addr:full":"580 Rue Monty Laval QC H7A 2C3",
    "addr:housenumber":"580",
    "addr:postcode":"h7a 2c3",
    "addr:street":"Rue Monty",
    "iso:country":"CA",
    "sg:address":"580 Rue Monty",
    "sg:city":"Laval",
    "sg:classifiers":[
        {
            "category":"Home & Garden",
            "subcategory":"Building Materials",
            "type":"Retail Goods"
        }
    ],
    "sg:phone":"+1 450 665 7056",
    "sg:postcode":"H7A 2C3",
    "sg:province":"QC",
    "sg:tags":[
        "windows",
        "window"
    ],
    "wof:name":"Reparations DE Fenetres Protec",
    "wof:placetype":"venue"
},
  "geometry": {"coordinates":[-73.578018,45.666023],"type":"Point"}
}