{
  "type": "Feature",
  "properties": {
    "addr:full":"240 Milltown Blvd St Stephen NB E3L 1G9",
    "addr:housenumber":"240",
    "addr:postcode":"e3l 1g9",
    "addr:street":"Milltown Blvd",
    "iso:country":"CA",
    "sg:address":"240 Milltown Blvd",
    "sg:city":"St Stephen",
    "sg:classifiers":[
        {
            "category":"Restaurant",
            "type":"Food & Drink"
        }
    ],
    "sg:phone":"+1 506 466 3000",
    "sg:postcode":"E3L 1G9",
    "sg:province":"NB",
    "sg:tags":[
        "pizza"
    ],
    "wof:name":"Pizza Shack",
    "wof:placetype":"venue"
},
  "geometry": {"coordinates":[-67.2849731445,45.1925811768],"type":"Point"}
}