{
  "type": "Feature",
  "properties": {
    "addr:full":"Richmond BC V6X 2B1",
    "addr:postcode":"v6x 2b1",
    "iso:country":"CA",
    "sg:city":"Richmond",
    "sg:classifiers":[
        {
            "category":"Retail",
            "subcategory":"Auto Repair",
            "type":"Services"
        }
    ],
    "sg:phone":"+1 604 233 1828",
    "sg:postcode":"V6X 2B1",
    "sg:province":"BC",
    "sg:tags":[
        "repairing",
        "automobile"
    ],
    "wof:name":"Sky Auto Svc",
    "wof:placetype":"venue"
},
  "geometry": {"coordinates":[-123.140343,49.172829],"type":"Point"}
}