{
  "type": "Feature",
  "properties": {
    "addr:full":"331 Frontenac Ave Oshawa ON L1J 2A7",
    "addr:housenumber":"331",
    "addr:postcode":"l1j 2a7",
    "addr:street":"Frontenac Ave",
    "iso:country":"CA",
    "sg:address":"331 Frontenac Ave",
    "sg:city":"Oshawa",
    "sg:classifiers":[
        {
            "category":"Social Services",
            "type":"Services"
        }
    ],
    "sg:phone":"+1 905 436 6564",
    "sg:postcode":"L1J 2A7",
    "sg:province":"ON",
    "sg:tags":[
        "organization",
        "welfare"
    ],
    "wof:name":"Frontenac Youth Svc",
    "wof:placetype":"venue"
},
  "geometry": {"coordinates":[-78.872505,43.888359],"type":"Point"}
}