{
  "type": "Feature",
  "properties": {
    "addr:full":"Toronto ON M4E 1E5",
    "addr:postcode":"m4e 1e5",
    "iso:country":"CA",
    "sg:city":"Toronto",
    "sg:classifiers":[
        {
            "category":"Health Services",
            "subcategory":"Podiatrist",
            "type":"Services"
        }
    ],
    "sg:phone":"+1 416 693 7897",
    "sg:postcode":"M4E 1E5",
    "sg:province":"ON",
    "wof:name":"Foot Care in the Beach",
    "wof:placetype":"venue"
},
  "geometry": {"coordinates":[-79.297501,43.670444],"type":"Point"}
}