{
  "type": "Feature",
  "properties": {
    "iso:country":"CA",
    "sg:address":"1977 Keele St",
    "sg:city":"York",
    "sg:classifiers":[
        {
            "category":"Food & Beverages",
            "subcategory":"Groceries & Convenience Stores",
            "type":"Retail Goods"
        }
    ],
    "sg:phone":"+1 416 651 4399",
    "sg:postcode":"M6M 3Y2",
    "sg:province":"ON",
    "sg:tags":[
        "grocer"
    ],
    "wof:name":"Zak's Convenience",
    "wof:placetype":"venue"
},
  "geometry": {"coordinates":[-79.474647522,43.6897277832],"type":"Point"}
}