{
  "type": "Feature",
  "properties": {
    "addr:full":"160 Rue Reservoir Grand Falls NB E3Y 3W3",
    "addr:housenumber":"160",
    "addr:postcode":"e3y 3w3",
    "addr:street":"Rue Reservoir",
    "iso:country":"CA",
    "sg:address":"160 Rue Reservoir",
    "sg:city":"Grand Falls",
    "sg:classifiers":[
        {
            "category":"Government",
            "subcategory":"Office",
            "type":"Public Place"
        }
    ],
    "sg:phone":"+1 506 473 3900",
    "sg:postcode":"E3Y 3W3",
    "sg:province":"NB",
    "wof:name":"Canada Human Resources Dev",
    "wof:placetype":"venue"
},
  "geometry": {"coordinates":[-67.73687,47.05439],"type":"Point"}
}