{
  "type": "Feature",
  "properties": {
    "addr:full":"45560 South Sumas Rd Chilliwack BC V2R 1S3",
    "addr:housenumber":"45560",
    "addr:postcode":"v2r 1s3",
    "addr:street":"South Sumas Rd",
    "iso:country":"CA",
    "sg:address":"45560 South Sumas Rd",
    "sg:city":"Chilliwack",
    "sg:classifiers":[
        {
            "category":"Education",
            "subcategory":"School",
            "type":"Public Place"
        }
    ],
    "sg:phone":"+1 604 858 7141",
    "sg:postcode":"V2R 1S3",
    "sg:province":"BC",
    "wof:name":"Vedder Middle School",
    "wof:placetype":"venue"
},
  "geometry": {"coordinates":[-121.96296700000001,49.118408],"type":"Point"}
}