{
  "type": "Feature",
  "properties": {
    "addr:full":"8639 8E Av Montreal QC H1Z 2X4",
    "addr:housenumber":"8639",
    "addr:postcode":"h1z 2x4",
    "addr:street":"8E Av",
    "iso:country":"CA",
    "sg:address":"8639 8E Av",
    "sg:city":"Montreal",
    "sg:classifiers":[
        {
            "category":"Manufacturing",
            "subcategory":"Retail Goods",
            "type":"Manufacturing & Wholesale Goods"
        }
    ],
    "sg:phone":"+1 514 721 5221",
    "sg:postcode":"H1Z 2X4",
    "sg:province":"QC",
    "sg:tags":[
        "equipment",
        "button",
        "maker",
        "laminating",
        "supply"
    ],
    "wof:name":"M Macaron Inc",
    "wof:placetype":"venue"
},
  "geometry": {"coordinates":[-73.62111663819999,45.5664367676],"type":"Point"}
}