{
  "type": "Feature",
  "properties": {
    "addr:full":"750 Tin Can Alley Gabriola BC V0R 1X3",
    "addr:housenumber":"750",
    "addr:postcode":"v0r 1x3",
    "addr:street":"Tin",
    "iso:country":"CA",
    "sg:address":"750 Tin Can Alley",
    "sg:city":"Gabriola",
    "sg:classifiers":[
        {
            "category":"Home & Garden",
            "subcategory":"Garden Supply",
            "type":"Retail Goods"
        }
    ],
    "sg:phone":"+1 250 247 7887",
    "sg:postcode":"V0R 1X3",
    "sg:province":"BC",
    "sg:tags":[
        "center"
    ],
    "wof:name":"Wild Rose Garden Ctr",
    "wof:placetype":"venue"
},
  "geometry": {"coordinates":[-123.83198547400001,49.1765441895],"type":"Point"}
}