{
  "type": "Feature",
  "properties": {
    "addr:full":"1435 Woodroffe Ave Nepean ON K2G 1W1",
    "addr:housenumber":"1435",
    "addr:postcode":"k2g 1w1",
    "addr:street":"Woodroffe Ave",
    "iso:country":"CA",
    "sg:address":"1435 Woodroffe Ave",
    "sg:city":"Nepean",
    "sg:classifiers":[
        {
            "category":"Health Services",
            "subcategory":"Chiropractor",
            "type":"Services"
        }
    ],
    "sg:phone":"+1 613 224 8543",
    "sg:postcode":"K2G 1W1",
    "sg:province":"ON",
    "wof:name":"Woodroffe Chiropractic",
    "wof:placetype":"venue"
},
  "geometry": {"coordinates":[-75.75608800000001,45.341606],"type":"Point"}
}