{
  "type": "Feature",
  "properties": {
    "addr:full":"124 Medora Port Carling ON P0B 1J0",
    "addr:housenumber":"124",
    "addr:postcode":"p0b 1j0",
    "addr:street":"Medora",
    "iso:country":"CA",
    "sg:address":"124 Medora",
    "sg:city":"Port Carling",
    "sg:classifiers":[
        {
            "category":"Shopping",
            "type":"Retail Goods"
        }
    ],
    "sg:phone":"+1 705 765 0663",
    "sg:postcode":"P0B 1J0",
    "sg:province":"ON",
    "sg:tags":[
        "dealer",
        "art",
        "gallery",
        "furniture"
    ],
    "wof:name":"Northern Quest Gallery",
    "wof:placetype":"venue"
},
  "geometry": {"coordinates":[-79.579224,45.121426],"type":"Point"}
}