{
  "type": "Feature",
  "properties": {
    "iso:country":"CA",
    "sg:city":"Vancouver",
    "sg:classifiers":[
        {
            "category":"Wholesale",
            "subcategory":"Metals & Minerals",
            "type":"Manufacturing & Wholesale Goods"
        }
    ],
    "sg:phone":"+1 604 331 3100",
    "sg:postcode":"V7X 1E6",
    "sg:province":"BC",
    "sg:tags":[
        "steel",
        "warehouse"
    ],
    "wof:name":"Mitsui & CO Ltd",
    "wof:placetype":"venue"
},
  "geometry": {"coordinates":[-123.12001,49.285961],"type":"Point"}
}