{
  "type": "Feature",
  "properties": {
    "iso:country":"CA",
    "sg:address":"175 Progress Dr",
    "sg:city":"Gravenhurst",
    "sg:classifiers":[
        {
            "category":"Recreation",
            "subcategory":"Marina",
            "type":"Entertainment"
        }
    ],
    "sg:phone":"+1 705 687 6378",
    "sg:postcode":"P1P 1X4",
    "sg:province":"ON",
    "sg:tags":[
        "repairing",
        "boat"
    ],
    "wof:name":"Kahshe Boat Works",
    "wof:placetype":"venue"
},
  "geometry": {"coordinates":[-79.361000061,44.937915802],"type":"Point"}
}