{
  "type": "Feature",
  "properties": {
    "iso:country":"CA",
    "sg:address":"Kettle Falls",
    "sg:city":"Minaki",
    "sg:classifiers":[
        {
            "category":"Travel",
            "subcategory":"Hotels & Motels",
            "type":"Entertainment"
        }
    ],
    "sg:phone":"+1 807 224 3483",
    "sg:postcode":"P0X 1J0",
    "sg:province":"ON",
    "sg:tags":[
        "resort",
        "camp",
        "fishing"
    ],
    "wof:name":"Halley's Kettle Falls Lodge",
    "wof:placetype":"venue"
},
  "geometry": {"coordinates":[-94.6706771851,49.9853515625],"type":"Point"}
}