{
  "type": "Feature",
  "properties": {
    "addr:full":"7030 Woodbine Avenue, 6th Floor Markham, Ontario L3R 6G2",
    "addr:housenumber":"7030;6th",
    "addr:postcode":"l3r 6g2",
    "addr:street":"Woodbine Avenue;Floor",
    "iso:country":"CA",
    "sg:address":"7030 Woodbine Avenue, 6th Floor Markham, Ontario",
    "sg:classifiers":[
        {
            "category":"Professional",
            "subcategory":"Computer Services",
            "type":"Services"
        }
    ],
    "sg:postcode":"L3R 6G2",
    "sg:tags":[
        "oem-marketers",
        "torque-products"
    ],
    "sg:website":"http://www.scitorque.com",
    "wof:name":"SCI",
    "wof:placetype":"venue"
},
  "geometry": {"coordinates":[-79.3503,43.814185],"type":"Point"}
}