{
  "type": "Feature",
  "properties": {
    "addr:full":"4 9E Av Boisbriand QC J7G 1E4",
    "addr:housenumber":"4",
    "addr:postcode":"j7g 1e4",
    "addr:street":"9E Av",
    "iso:country":"CA",
    "sg:address":"4 9E Av",
    "sg:city":"Boisbriand",
    "sg:classifiers":[
        {
            "category":"Shopping",
            "subcategory":"Computers & Home Electronics",
            "type":"Retail Goods"
        }
    ],
    "sg:phone":"+1 450 434 1909",
    "sg:postcode":"J7G 1E4",
    "sg:province":"QC",
    "sg:tags":[
        "television",
        "radio"
    ],
    "wof:name":"Electronique Paquette Enr",
    "wof:placetype":"venue"
},
  "geometry": {"coordinates":[-73.818245,45.615673],"type":"Point"}
}