{
  "type": "Feature",
  "properties": {
    "addr:full":"33 Terminal Ave Nanaimo BC V9R 5C4",
    "addr:housenumber":"33",
    "addr:postcode":"v9r 5c4",
    "addr:street":"Terminal Ave",
    "iso:country":"CA",
    "sg:address":"33 Terminal Ave",
    "sg:city":"Nanaimo",
    "sg:classifiers":[
        {
            "category":"Retail",
            "subcategory":"Auto Rental",
            "type":"Services"
        }
    ],
    "sg:phone":"+1 250 754 7368",
    "sg:postcode":"V9R 5C4",
    "sg:province":"BC",
    "sg:tags":[
        "renting",
        "automobile",
        "mover"
    ],
    "wof:name":"Budget Rent-A-Car",
    "wof:placetype":"venue"
},
  "geometry": {"coordinates":[-123.94101000000001,49.169838],"type":"Point"}
}