{
  "type": "Feature",
  "properties": {
    "addr:full":"32 Front St N Thorold ON L2V 1X5",
    "addr:housenumber":"32",
    "addr:postcode":"l2v 1x5",
    "addr:street":"Front St N",
    "iso:country":"CA",
    "sg:address":"32 Front St N",
    "sg:city":"Thorold",
    "sg:classifiers":[
        {
            "category":"Restaurant",
            "type":"Food & Drink"
        }
    ],
    "sg:phone":"+1 905 227 5676",
    "sg:postcode":"L2V 1X5",
    "sg:province":"ON",
    "wof:name":"Tony's Pizzeria",
    "wof:placetype":"venue"
},
  "geometry": {"coordinates":[-79.200592,43.126087],"type":"Point"}
}