{
  "type": "Feature",
  "properties": {
    "addr:full":"2441 Av DE LA Rotonde Charny QC G6X 2M2",
    "addr:housenumber":"2441",
    "addr:postcode":"g6x 2m2",
    "addr:street":"Av De La Rotonde",
    "iso:country":"CA",
    "sg:address":"2441 Av DE LA Rotonde",
    "sg:city":"Charny",
    "sg:classifiers":[
        {
            "category":"Sports & Exercise",
            "subcategory":"Golf",
            "type":"Entertainment"
        }
    ],
    "sg:phone":"+1 418 832 4432",
    "sg:postcode":"G6X 2M2",
    "sg:province":"QC",
    "sg:tags":[
        "course"
    ],
    "wof:name":"Club DE Golf Charny Inc",
    "wof:placetype":"venue"
},
  "geometry": {"coordinates":[-71.25993347169999,46.7115936279],"type":"Point"}
}