{
  "type": "Feature",
  "properties": {
    "iso:country":"CA",
    "sg:address":"8362 Kennedy Rd # 8",
    "sg:city":"Markham",
    "sg:classifiers":[
        {
            "category":"Restaurant",
            "type":"Food & Drink"
        }
    ],
    "sg:phone":"+1 905 415 1666",
    "sg:postcode":"L3R 9W5",
    "sg:province":"ON",
    "wof:name":"Grand Lake Chinese Cuisine",
    "wof:placetype":"venue"
},
  "geometry": {"coordinates":[-79.3028259277,43.8598175049],"type":"Point"}
}