{
  "type": "Feature",
  "properties": {
    "addr:full":"5115 Rue Rivard Montreal QC H2J 2P2",
    "addr:housenumber":"5115",
    "addr:postcode":"h2j 2p2",
    "addr:street":"Rue Rivard",
    "iso:country":"CA",
    "sg:address":"5115 Rue Rivard",
    "sg:city":"Montreal",
    "sg:classifiers":[
        {
            "category":"Professional",
            "subcategory":"Management & Consulting",
            "type":"Services"
        }
    ],
    "sg:phone":"+1 514 274 7358",
    "sg:postcode":"H2J 2P2",
    "sg:province":"QC",
    "sg:tags":[
        "consultant",
        "recreation",
        "program"
    ],
    "wof:name":"Relance Des Loisirs Tout 9 Inc",
    "wof:placetype":"venue"
},
  "geometry": {"coordinates":[-73.5890655518,45.5277442932],"type":"Point"}
}