{
  "type": "Feature",
  "properties": {
    "addr:full":"Brampton ON L6T 5H8",
    "addr:postcode":"l6t 5h8",
    "iso:country":"CA",
    "sg:city":"Brampton",
    "sg:classifiers":[
        {
            "category":"Food & Beverages",
            "subcategory":"Groceries & Convenience Stores",
            "type":"Retail Goods"
        }
    ],
    "sg:phone":"+1 905 790 7159",
    "sg:postcode":"L6T 5H8",
    "sg:province":"ON",
    "wof:name":"Melanie Convenience",
    "wof:placetype":"venue"
},
  "geometry": {"coordinates":[-79.68023700000001,43.710888],"type":"Point"}
}