{
  "type": "Feature",
  "properties": {
    "addr:full":"48 Kenmount Rd St. John's NL A1B 1W3",
    "addr:housenumber":"48",
    "addr:postcode":"a1b 1w3",
    "addr:street":"Kenmount Rd",
    "iso:country":"CA",
    "sg:address":"48 Kenmount Rd",
    "sg:city":"St. John's",
    "sg:classifiers":[
        {
            "category":"Shopping",
            "subcategory":"Gifts & Souvenirs",
            "type":"Retail Goods"
        }
    ],
    "sg:phone":"+1 709 739 1439",
    "sg:postcode":"A1B 1W3",
    "sg:province":"NL",
    "sg:tags":[
        "cards",
        "greeting"
    ],
    "wof:name":"Hallmark",
    "wof:placetype":"venue"
},
  "geometry": {"coordinates":[-52.7521095276,47.5592498779],"type":"Point"}
}