{
  "type": "Feature",
  "properties": {
    "iso:country":"CA",
    "sg:address":"188 Boul Saint-Joseph",
    "sg:city":"Hull",
    "sg:classifiers":[
        {
            "category":"Restaurant",
            "type":"Food & Drink"
        }
    ],
    "sg:phone":"+1 819 595 3333",
    "sg:postcode":"J8Y 3W9",
    "sg:province":"QC",
    "sg:tags":[
        "pizza"
    ],
    "wof:name":"Riviera Pizza Original",
    "wof:placetype":"venue"
},
  "geometry": {"coordinates":[-75.732986,45.433525],"type":"Point"}
}