{
  "type": "Feature",
  "properties": {
    "addr:full":"1570 Elgin Ave W Winnipeg MB R3E 1C2",
    "addr:housenumber":"1570",
    "addr:postcode":"r3e 1c2",
    "addr:street":"Elgin Ave W",
    "iso:country":"CA",
    "sg:address":"1570 Elgin Ave W",
    "sg:city":"Winnipeg",
    "sg:classifiers":[
        {
            "category":"Education",
            "subcategory":"School",
            "type":"Public Place"
        }
    ],
    "sg:phone":"+1 204 783 9012",
    "sg:postcode":"R3E 1C2",
    "sg:province":"MB",
    "wof:name":"Cecil Rhodes School",
    "wof:placetype":"venue"
},
  "geometry": {"coordinates":[-97.19149,49.916664],"type":"Point"}
}