{
  "type": "Feature",
  "properties": {
    "addr:full":"5 Edgecliff Cres Garson ON P3L 1H9",
    "addr:housenumber":"5",
    "addr:postcode":"p3l 1h9",
    "addr:street":"Edgecliff Cres",
    "iso:country":"CA",
    "sg:address":"5 Edgecliff Cres",
    "sg:city":"Garson",
    "sg:classifiers":[
        {
            "category":"Building & Trades",
            "subcategory":"Construction",
            "type":"Services"
        }
    ],
    "sg:phone":"+1 705 693 5097",
    "sg:postcode":"P3L 1H9",
    "sg:province":"ON",
    "sg:tags":[
        "contractor"
    ],
    "wof:name":"D J Builders",
    "wof:placetype":"venue"
},
  "geometry": {"coordinates":[-80.8723831177,46.5461044312],"type":"Point"}
}