{
  "type": "Feature",
  "properties": {
    "addr:full":"PO Box 61009 Rpo Delton Edmonton AB T5E 6J6",
    "addr:housenumber":"po box",
    "addr:postcode":"t5e 6j6",
    "addr:street":"61009 Rpo",
    "iso:country":"CA",
    "sg:address":"PO Box 61009 Rpo Delton",
    "sg:city":"Edmonton",
    "sg:classifiers":[
        {
            "category":"Building & Trades",
            "subcategory":"Construction",
            "type":"Services"
        }
    ],
    "sg:phone":"+1 780 916 4648",
    "sg:postcode":"T5E 6J6",
    "sg:province":"AB",
    "sg:tags":[
        "excavating",
        "contractor"
    ],
    "wof:name":"Capital City Excavating Ltd",
    "wof:placetype":"venue"
},
  "geometry": {"coordinates":[-113.49037199999999,53.546219],"type":"Point"}
}