{
  "type": "Feature",
  "properties": {
    "addr:full":"3879 Rue Wellington Verdun QC H4G 1V1",
    "addr:housenumber":"3879",
    "addr:postcode":"h4g 1v1",
    "addr:street":"Rue Wellington",
    "iso:country":"CA",
    "sg:address":"3879 Rue Wellington",
    "sg:city":"Verdun",
    "sg:classifiers":[
        {
            "category":"Shopping",
            "subcategory":"Clothing, Apparel, & Fashions",
            "type":"Retail Goods"
        }
    ],
    "sg:phone":"+1 514 761 1733",
    "sg:postcode":"H4G 1V1",
    "sg:province":"QC",
    "sg:tags":[
        "jean"
    ],
    "wof:name":"Jeanex Inc",
    "wof:placetype":"venue"
},
  "geometry": {"coordinates":[-73.566986,45.465298],"type":"Point"}
}