{
  "type": "Feature",
  "properties": {
    "addr:full":"131 Timber Lane Flin Flon MB R8A 1M9",
    "addr:housenumber":"131",
    "addr:postcode":"r8a 1m9",
    "addr:street":"Timber Lane",
    "iso:country":"CA",
    "sg:address":"131 Timber Lane",
    "sg:city":"Flin Flon",
    "sg:classifiers":[
        {
            "category":"Freight",
            "type":"Transportation"
        }
    ],
    "sg:phone":"+1 204 687 7546",
    "sg:postcode":"R8A 1M9",
    "sg:province":"MB",
    "sg:tags":[
        "trucking"
    ],
    "wof:name":"Gardewine North",
    "wof:placetype":"venue"
},
  "geometry": {"coordinates":[-101.855278015,54.7888755798],"type":"Point"}
}