{
  "type": "Feature",
  "properties": {
    "addr:full":"783 Rue Kennebec Pintendre QC G6C 1E7",
    "addr:housenumber":"783",
    "addr:postcode":"g6c 1e7",
    "addr:street":"Rue Kennebec Pintendre",
    "iso:country":"CA",
    "sg:address":"783 Rue Kennebec",
    "sg:city":"Pintendre",
    "sg:classifiers":[
        {
            "category":"Manufacturing",
            "subcategory":"Printing",
            "type":"Manufacturing & Wholesale Goods"
        }
    ],
    "sg:phone":"+1 418 833 4775",
    "sg:postcode":"G6C 1E7",
    "sg:province":"QC",
    "sg:tags":[
        "screen"
    ],
    "wof:name":"Bo-Concept Enr",
    "wof:placetype":"venue"
},
  "geometry": {"coordinates":[-71.125473,46.756203],"type":"Point"}
}