{
  "type": "Feature",
  "properties": {
    "iso:country":"CA",
    "sg:city":"Saint-Leonard",
    "sg:classifiers":[
        {
            "category":"Cinema",
            "subcategory":"Movie Rental",
            "type":"Entertainment"
        }
    ],
    "sg:phone":"+1 514 259 6000",
    "sg:postcode":"H1S 3E8",
    "sg:province":"QC",
    "sg:tags":[
        "leasing",
        "video",
        "disc",
        "tape"
    ],
    "wof:name":"Superclub Videotron Ltee",
    "wof:placetype":"venue"
},
  "geometry": {"coordinates":[-73.5754852295,45.5918083191],"type":"Point"}
}