{
  "type": "Feature",
  "properties": {
    "addr:full":"31 Rue Principale Bedford QC J0J 1A0",
    "addr:housenumber":"31",
    "addr:postcode":"j0j 1a0",
    "addr:street":"Rue Principale",
    "iso:country":"CA",
    "sg:address":"31 Rue Principale",
    "sg:city":"Bedford",
    "sg:classifiers":[
        {
            "category":"Shopping",
            "subcategory":"Jewelry",
            "type":"Retail Goods"
        }
    ],
    "sg:phone":"+1 450 248 2858",
    "sg:postcode":"J0J 1A0",
    "sg:province":"QC",
    "sg:tags":[
        "jeweler"
    ],
    "wof:name":"Fournier Bijouterie Inc",
    "wof:placetype":"venue"
},
  "geometry": {"coordinates":[-72.98876199999999,45.121006],"type":"Point"}
}