{
  "type": "Feature",
  "properties": {
    "addr:full":"High Prairie AB T0G 1E0",
    "addr:postcode":"t0g 1e0",
    "iso:country":"CA",
    "sg:city":"High Prairie",
    "sg:classifiers":[
        {
            "category":"Wholesale",
            "subcategory":"Machinery & Supplies",
            "type":"Manufacturing & Wholesale Goods"
        }
    ],
    "sg:phone":"+1 780 523 0063",
    "sg:postcode":"T0G 1E0",
    "sg:province":"AB",
    "sg:tags":[
        "field",
        "oil",
        "equipment"
    ],
    "wof:name":"Petroline Rentals Ltd",
    "wof:placetype":"venue"
},
  "geometry": {"coordinates":[-116.48042297400001,55.4328842163],"type":"Point"}
}