{
  "type": "Feature",
  "properties": {
    "addr:full":"Sexsmith AB T0H 3C0",
    "addr:postcode":"t0h 3c0",
    "iso:country":"CA",
    "sg:city":"Sexsmith",
    "sg:classifiers":[
        {
            "category":"Building & Trades",
            "subcategory":"Construction",
            "type":"Services"
        }
    ],
    "sg:phone":"+1 780 568 2461",
    "sg:postcode":"T0H 3C0",
    "sg:province":"AB",
    "sg:tags":[
        "stucco",
        "contractor"
    ],
    "wof:name":"Stucco Tech",
    "wof:placetype":"venue"
},
  "geometry": {"coordinates":[-118.77079000000001,55.348686],"type":"Point"}
}