{
  "type": "Feature",
  "properties": {
    "iso:country":"CA",
    "sg:address":"5409 Eglinton Ave W",
    "sg:city":"Etobicoke",
    "sg:classifiers":[
        {
            "category":"Manufacturing",
            "subcategory":"Printing",
            "type":"Manufacturing & Wholesale Goods"
        }
    ],
    "sg:phone":"+1 416 620 1940",
    "sg:postcode":"M9C 5K6",
    "sg:province":"ON",
    "sg:tags":[
        "publisher",
        "guide"
    ],
    "wof:name":"Marskell Group",
    "wof:placetype":"venue"
},
  "geometry": {"coordinates":[-79.5922546387,43.6613082886],"type":"Point"}
}