{
  "type": "Feature",
  "properties": {
    "addr:full":"2082 Lawrence Ave E Scarborough ON M1R 2Z5",
    "addr:housenumber":"2082",
    "addr:postcode":"m1r 2z5",
    "addr:street":"Lawrence Ave E",
    "iso:country":"CA",
    "sg:address":"2082 Lawrence Ave E",
    "sg:city":"Scarborough",
    "sg:classifiers":[
        {
            "category":"Food & Beverages",
            "subcategory":"Bakery",
            "type":"Retail Goods"
        }
    ],
    "sg:phone":"+1 416 285 6300",
    "sg:postcode":"M1R 2Z5",
    "sg:province":"ON",
    "sg:tags":[
        "baker"
    ],
    "wof:name":"Athena Sweets Bakery & Deli",
    "wof:placetype":"venue"
},
  "geometry": {"coordinates":[-79.2930526733,43.7458763123],"type":"Point"}
}