{
  "type": "Feature",
  "properties": {
    "addr:full":"666 Burrard St # 2338 Vancouver BC V6C 2X8",
    "addr:housenumber":"666",
    "addr:postcode":"v6c 2x8",
    "addr:street":"Burrard St # 2338",
    "iso:country":"CA",
    "sg:address":"666 Burrard St # 2338",
    "sg:city":"Vancouver",
    "sg:classifiers":[
        {
            "category":"Insurance",
            "subcategory":"Insurance Agent",
            "type":"Services"
        }
    ],
    "sg:phone":"+1 604 738 2600",
    "sg:postcode":"V6C 2X8",
    "sg:province":"BC",
    "sg:tags":[
        "consultant"
    ],
    "wof:name":"Mc Evoy Insurance Svc Ltd",
    "wof:placetype":"venue"
},
  "geometry": {"coordinates":[-123.11982727,49.2851448059],"type":"Point"}
}