{
  "type": "Feature",
  "properties": {
    "addr:full":"Nobel ON P0G 1G0",
    "addr:postcode":"p0g 1g0",
    "iso:country":"CA",
    "sg:city":"Nobel",
    "sg:classifiers":[
        {
            "category":"Health Services",
            "subcategory":"Clinic",
            "type":"Services"
        }
    ],
    "sg:phone":"+1 705 366 2378",
    "sg:postcode":"P0G 1G0",
    "sg:province":"ON",
    "sg:tags":[
        "holistic",
        "practitioner"
    ],
    "wof:name":"Shawanaga First Nation Healing",
    "wof:placetype":"venue"
},
  "geometry": {"coordinates":[-80.09229999999999,45.414669],"type":"Point"}
}