{
  "type": "Feature",
  "properties": {
    "addr:full":"383 Simcoe St Beaverton ON L0K 1A0",
    "addr:housenumber":"383",
    "addr:postcode":"l0k 1a0",
    "addr:street":"Simcoe St",
    "iso:country":"CA",
    "sg:address":"383 Simcoe St",
    "sg:city":"Beaverton",
    "sg:classifiers":[
        {
            "category":"Food & Beverages",
            "subcategory":"Groceries & Convenience Stores",
            "type":"Retail Goods"
        }
    ],
    "sg:phone":"+1 705 426 9061",
    "sg:postcode":"L0K 1A0",
    "sg:province":"ON",
    "sg:tags":[
        "grocer"
    ],
    "wof:name":"Beaverton Foodland",
    "wof:placetype":"venue"
},
  "geometry": {"coordinates":[-79.153656,44.429428],"type":"Point"}
}