{
  "type": "Feature",
  "properties": {
    "iso:country":"CA",
    "sg:address":"525 Main St E",
    "sg:city":"North Bay",
    "sg:classifiers":[
        {
            "category":"Banks & Credit Unions",
            "subcategory":"Bank",
            "type":"Services"
        }
    ],
    "sg:phone":"+1 705 476 3500",
    "sg:postcode":"P1B 1B7",
    "sg:province":"ON",
    "wof:name":"Northern Credit Union Ltd",
    "wof:placetype":"venue"
},
  "geometry": {"coordinates":[-79.4590759277,46.3046264648],"type":"Point"}
}