{
  "type": "Feature",
  "properties": {
    "addr:full":"Saint-Leonard QC H1R 1Y1",
    "addr:postcode":"h1r 1y1",
    "iso:country":"CA",
    "sg:city":"Saint-Leonard",
    "sg:classifiers":[
        {
            "category":"Personal",
            "subcategory":"Beauty Salon",
            "type":"Services"
        }
    ],
    "sg:phone":"+1 514 852 1823",
    "sg:postcode":"H1R 1Y1",
    "sg:province":"QC",
    "wof:name":"Esthetique Christina",
    "wof:placetype":"venue"
},
  "geometry": {"coordinates":[-73.596085,45.579147],"type":"Point"}
}