{
  "type": "Feature",
  "properties": {
    "addr:full":"904 Downie St Stratford ON N5A 6T3",
    "addr:housenumber":"904",
    "addr:postcode":"n5a 6t3",
    "addr:street":"Downie St",
    "iso:country":"CA",
    "sg:address":"904 Downie St",
    "sg:city":"Stratford",
    "sg:classifiers":[
        {
            "category":"Manufacturing",
            "subcategory":"Metals",
            "type":"Manufacturing & Wholesale Goods"
        }
    ],
    "sg:phone":"+1 519 271 4750",
    "sg:postcode":"N5A 6T3",
    "sg:province":"ON",
    "sg:tags":[
        "steel",
        "processing"
    ],
    "wof:name":"Steel Craft Ltd",
    "wof:placetype":"venue"
},
  "geometry": {"coordinates":[-80.9723434448,43.3525276184],"type":"Point"}
}