{
  "type": "Feature",
  "properties": {
    "iso:country":"CA",
    "sg:address":"10 Park Ave E",
    "sg:city":"Burlington",
    "sg:classifiers":[
        {
            "category":"Building & Trades",
            "subcategory":"Pest Control",
            "type":"Services"
        }
    ],
    "sg:phone":"+1 905 637 3373",
    "sg:postcode":"L7T 1Y1",
    "sg:province":"ON",
    "wof:name":"Action Pest Control",
    "wof:placetype":"venue"
},
  "geometry": {"coordinates":[-79.848137,43.304077],"type":"Point"}
}