{
  "type": "Feature",
  "properties": {
    "addr:full":"Fredericton NB E3B 3Z2",
    "addr:postcode":"e3b 3z2",
    "iso:country":"CA",
    "sg:city":"Fredericton",
    "sg:classifiers":[
        {
            "category":"Professional",
            "subcategory":"Lawyer & Legal Services",
            "type":"Services"
        }
    ],
    "sg:phone":"+1 506 458 1989",
    "sg:postcode":"E3B 3Z2",
    "sg:province":"NB",
    "sg:tags":[
        "attorney"
    ],
    "wof:name":"Pink Breen Larkin",
    "wof:placetype":"venue"
},
  "geometry": {"coordinates":[-66.65728759770001,45.9398384094],"type":"Point"}
}