{
  "type": "Feature",
  "properties": {
    "addr:full":"62 Bacchus Island Rd Smiths Falls ON K7A 5B8",
    "addr:housenumber":"62",
    "addr:postcode":"k7a 5b8",
    "addr:street":"Bacchus Island Rd",
    "iso:country":"CA",
    "sg:address":"62 Bacchus Island Rd",
    "sg:city":"Smiths Falls",
    "sg:classifiers":[
        {
            "category":"Building & Trades",
            "subcategory":"Construction",
            "type":"Services"
        }
    ],
    "sg:phone":"+1 613 283 3717",
    "sg:postcode":"K7A 5B8",
    "sg:province":"ON",
    "sg:tags":[
        "contractor"
    ],
    "wof:name":"J A Gallipeau Construction Ltd",
    "wof:placetype":"venue"
},
  "geometry": {"coordinates":[-76.0215148926,44.9025840759],"type":"Point"}
}