{
  "type": "Feature",
  "properties": {
    "addr:full":"9417 Rue Saint-Vincent Mirabel QC J7N 2V6",
    "addr:housenumber":"9417",
    "addr:postcode":"j7n 2v6",
    "addr:street":"Rue Saint-Vincent",
    "iso:country":"CA",
    "sg:address":"9417 Rue Saint-Vincent",
    "sg:city":"Mirabel",
    "sg:classifiers":[
        {
            "category":"Professional",
            "subcategory":"Business Services",
            "type":"Services"
        }
    ],
    "sg:phone":"+1 514 251 5353",
    "sg:postcode":"J7N 2V6",
    "sg:province":"QC",
    "sg:tags":[
        "painter",
        "embroidery",
        "sign"
    ],
    "wof:name":"Enseigne Info Vision Design",
    "wof:placetype":"venue"
},
  "geometry": {"coordinates":[-74.099487,45.640652],"type":"Point"}
}