{
  "type": "Feature",
  "properties": {
    "addr:full":"Strathmore AB T1P 1J4",
    "addr:postcode":"t1p 1j4",
    "iso:country":"CA",
    "sg:city":"Strathmore",
    "sg:classifiers":[
        {
            "category":"Education",
            "subcategory":"School",
            "type":"Public Place"
        }
    ],
    "sg:phone":"+1 403 787 2121",
    "sg:postcode":"T1P 1J4",
    "sg:province":"AB",
    "wof:name":"Crawling Valley Colony School",
    "wof:placetype":"venue"
},
  "geometry": {"coordinates":[-113.388138,51.037682],"type":"Point"}
}