{
  "type": "Feature",
  "properties": {
    "addr:full":"324 Logan Ave Winnipeg MB R3A 0L5",
    "addr:housenumber":"324",
    "addr:postcode":"r3a 0l5",
    "addr:street":"Logan Ave",
    "iso:country":"CA",
    "sg:address":"324 Logan Ave",
    "sg:city":"Winnipeg",
    "sg:classifiers":[
        {
            "category":"Organizations",
            "subcategory":"Religious Organization",
            "type":"Services"
        }
    ],
    "sg:phone":"+1 204 946 9490",
    "sg:postcode":"R3A 0L5",
    "sg:province":"MB",
    "sg:tags":[
        "church"
    ],
    "wof:name":"Salvation Army",
    "wof:placetype":"venue"
},
  "geometry": {"coordinates":[-97.13986199999999,49.903816],"type":"Point"}
}