{
  "type": "Feature",
  "properties": {
    "addr:full":"Odessa ON K0H 2H0",
    "addr:postcode":"k0h 2h0",
    "iso:country":"CA",
    "sg:city":"Odessa",
    "sg:classifiers":[
        {
            "category":"Wholesale",
            "subcategory":"Machinery & Supplies",
            "type":"Manufacturing & Wholesale Goods"
        }
    ],
    "sg:phone":"+1 613 386 3149",
    "sg:postcode":"K0H 2H0",
    "sg:province":"ON",
    "sg:tags":[
        "farm",
        "equipment"
    ],
    "wof:name":"Wiljan Farm Equipment",
    "wof:placetype":"venue"
},
  "geometry": {"coordinates":[-76.718918,44.276974],"type":"Point"}
}