{
  "type": "Feature",
  "properties": {
    "addr:full":"Surrey BC V3W 4N2",
    "addr:postcode":"v3w 4n2",
    "iso:country":"CA",
    "sg:city":"Surrey",
    "sg:classifiers":[
        {
            "category":"Wholesale",
            "subcategory":"Groceries",
            "type":"Manufacturing & Wholesale Goods"
        }
    ],
    "sg:phone":"+1 604 594 6833",
    "sg:postcode":"V3W 4N2",
    "sg:province":"BC",
    "sg:tags":[
        "honey"
    ],
    "wof:name":"St Michael Honey Ltd",
    "wof:placetype":"venue"
},
  "geometry": {"coordinates":[-122.85694100000001,49.146225],"type":"Point"}
}