{
  "type": "Feature",
  "properties": {
    "addr:full":"5 Burleigh Hill Dr St Catharines ON L2T 2L5",
    "addr:housenumber":"5",
    "addr:postcode":"l2t 2l5",
    "addr:street":"Burleigh Hill Dr",
    "iso:country":"CA",
    "sg:address":"5 Burleigh Hill Dr",
    "sg:city":"St Catharines",
    "sg:classifiers":[
        {
            "category":"Autos & Motor Vehicles",
            "subcategory":"Auto Supplies",
            "type":"Retail Goods"
        }
    ],
    "sg:phone":"+1 905 227 7861",
    "sg:postcode":"L2T 2L5",
    "sg:province":"ON",
    "sg:tags":[
        "automobile",
        "parts"
    ],
    "wof:name":"Canadian Tire Gas Bar",
    "wof:placetype":"venue"
},
  "geometry": {"coordinates":[-79.2186050415,43.134967804],"type":"Point"}
}