{
  "type": "Feature",
  "properties": {
    "iso:country":"CA",
    "sg:address":"2970 Hwy 43",
    "sg:city":"Kemptville",
    "sg:classifiers":[
        {
            "category":"Autos & Motor Vehicles",
            "subcategory":"Auto Supplies",
            "type":"Retail Goods"
        }
    ],
    "sg:phone":"+1 613 258 3311",
    "sg:postcode":"K0G 1J0",
    "sg:province":"ON",
    "sg:tags":[
        "automobile",
        "parts"
    ],
    "wof:name":"Canadian Tire",
    "wof:placetype":"venue"
},
  "geometry": {"coordinates":[-75.638702,45.02869],"type":"Point"}
}