{
  "type": "Feature",
  "properties": {
    "iso:country":"CA",
    "sg:city":"Stellarton",
    "sg:classifiers":[
        {
            "category":"Government",
            "subcategory":"Office",
            "type":"Public Place"
        }
    ],
    "sg:phone":"+1 902 752 5273",
    "sg:postcode":"B0K 1S0",
    "sg:province":"NS",
    "sg:tags":[
        "village"
    ],
    "wof:name":"Stellarton Pumping Station",
    "wof:placetype":"venue"
},
  "geometry": {"coordinates":[-62.659683,45.561745],"type":"Point"}
}