{
  "type": "Feature",
  "properties": {
    "addr:full":"Trois-Rivieres QC G9A 4L5",
    "addr:postcode":"g9a 4l5",
    "iso:country":"CA",
    "sg:city":"Trois-Rivieres",
    "sg:classifiers":[
        {
            "category":"Retail",
            "subcategory":"Auto Rental",
            "type":"Services"
        }
    ],
    "sg:phone":"+1 819 371 3484",
    "sg:postcode":"G9A 4L5",
    "sg:province":"QC",
    "sg:tags":[
        "renting",
        "automobile"
    ],
    "wof:name":"Location Kiroule Inc",
    "wof:placetype":"venue"
},
  "geometry": {"coordinates":[-72.54988899999999,46.333832],"type":"Point"}
}