{
  "type": "Feature",
  "properties": {
    "addr:full":"3321 Ogdens Beach Rd Midland ON L4R 4K6",
    "addr:housenumber":"3321",
    "addr:postcode":"l4r 4k6",
    "addr:street":"Ogdens Beach Rd",
    "iso:country":"CA",
    "sg:address":"3321 Ogdens Beach Rd",
    "sg:city":"Midland",
    "sg:classifiers":[
        {
            "category":"Travel",
            "subcategory":"Campground",
            "type":"Entertainment"
        }
    ],
    "sg:phone":"+1 705 526 8704",
    "sg:postcode":"L4R 4K6",
    "sg:province":"ON",
    "wof:name":"Bayfort Camp",
    "wof:placetype":"venue"
},
  "geometry": {"coordinates":[-79.88851200000001,44.749905],"type":"Point"}
}