{
  "type": "Feature",
  "properties": {
    "iso:country":"CA",
    "sg:address":"5 Estate Dr",
    "sg:city":"Lower Sackville",
    "sg:classifiers":[
        {
            "category":"Home & Garden",
            "subcategory":"Furniture",
            "type":"Retail Goods"
        }
    ],
    "sg:phone":"+1 902 864 7390",
    "sg:postcode":"B4C 3Z2",
    "sg:province":"NS",
    "sg:tags":[
        "equipment",
        "kitchen",
        "cabinet"
    ],
    "wof:name":"Mury Industries",
    "wof:placetype":"venue"
},
  "geometry": {"coordinates":[-63.654881,44.757309],"type":"Point"}
}