{
  "type": "Feature",
  "properties": {
    "iso:country":"CA",
    "sg:address":"40 Hallbrook Dr SW",
    "sg:city":"Calgary",
    "sg:classifiers":[
        {
            "category":"Building & Trades",
            "subcategory":"Construction",
            "type":"Services"
        }
    ],
    "sg:phone":"+1 403 253 3111",
    "sg:postcode":"T2V 3H4",
    "sg:province":"AB",
    "sg:tags":[
        "marking",
        "parking",
        "paving",
        "maintenance",
        "contractor"
    ],
    "wof:name":"Southwood Paving & Patching",
    "wof:placetype":"venue"
},
  "geometry": {"coordinates":[-114.092514038,50.9737815857],"type":"Point"}
}