{
  "type": "Feature",
  "properties": {
    "iso:country":"CA",
    "sg:address":"4631 Caulfeild Dr",
    "sg:city":"West Vancouver",
    "sg:classifiers":[
        {
            "category":"Wholesale",
            "subcategory":"Durable Goods & Equipment",
            "type":"Manufacturing & Wholesale Goods"
        }
    ],
    "sg:phone":"+1 604 913 3408",
    "sg:postcode":"V7W 1E9",
    "sg:province":"BC",
    "sg:tags":[
        "representative",
        "manufacturer"
    ],
    "wof:name":"R A Hastings Agencies",
    "wof:placetype":"venue"
},
  "geometry": {"coordinates":[-123.25163268999999,49.3460006714],"type":"Point"}
}