{
  "type": "Feature",
  "properties": {
    "addr:full":"Brussels ON N0G 1H0",
    "addr:postcode":"n0g 1h0",
    "iso:country":"CA",
    "sg:city":"Brussels",
    "sg:classifiers":[
        {
            "category":"Government",
            "subcategory":"Office",
            "type":"Public Place"
        }
    ],
    "sg:phone":"+1 519 887 6137",
    "sg:postcode":"N0G 1H0",
    "sg:province":"ON",
    "sg:tags":[
        "village"
    ],
    "wof:name":"Morris Township Municipal Ofc",
    "wof:placetype":"venue"
},
  "geometry": {"coordinates":[-81.25166299999999,43.741852],"type":"Point"}
}