{
  "type": "Feature",
  "properties": {
    "addr:full":"34 Argyle St S Renfrew ON K7V 1T3",
    "addr:housenumber":"34",
    "addr:postcode":"k7v 1t3",
    "addr:street":"Argyle St S",
    "iso:country":"CA",
    "sg:address":"34 Argyle St S",
    "sg:city":"Renfrew",
    "sg:classifiers":[
        {
            "category":"Retail",
            "subcategory":"Auto Repair",
            "type":"Services"
        }
    ],
    "sg:phone":"+1 613 432 3399",
    "sg:postcode":"K7V 1T3",
    "sg:province":"ON",
    "sg:tags":[
        "repairing",
        "automobile"
    ],
    "wof:name":"Jim's Auto Care",
    "wof:placetype":"venue"
},
  "geometry": {"coordinates":[-76.68792000000001,45.473637],"type":"Point"}
}