{
  "type": "Feature",
  "properties": {
    "addr:full":"Moose Jaw SK S6H 7X5",
    "addr:postcode":"s6h 7x5",
    "iso:country":"CA",
    "sg:city":"Moose Jaw",
    "sg:classifiers":[
        {
            "category":"Banks & Credit Unions",
            "subcategory":"Investment Brokerage",
            "type":"Services"
        }
    ],
    "sg:phone":"+1 306 692 2337",
    "sg:postcode":"S6H 7X5",
    "sg:province":"SK",
    "wof:name":"Rbc Dominion Securities Inc",
    "wof:placetype":"venue"
},
  "geometry": {"coordinates":[-105.531532,50.392715],"type":"Point"}
}