{
  "type": "Feature",
  "properties": {
    "addr:full":"12936 Keele St King City ON L7B 1H8",
    "addr:housenumber":"12936",
    "addr:postcode":"l7b 1h8",
    "addr:street":"Keele St",
    "iso:country":"CA",
    "sg:address":"12936 Keele St",
    "sg:city":"King City",
    "sg:classifiers":[
        {
            "category":"Museum",
            "type":"Entertainment"
        }
    ],
    "sg:phone":"+1 905 833 1897",
    "sg:postcode":"L7B 1H8",
    "sg:province":"ON",
    "sg:tags":[
        "organization",
        "arts",
        "information"
    ],
    "wof:name":"Kingcrafts",
    "wof:placetype":"venue"
},
  "geometry": {"coordinates":[-79.52789300000001,43.92683],"type":"Point"}
}