{
  "type": "Feature",
  "properties": {
    "addr:full":"42 Voyager Crt S Etobicoke ON M9W 5M7",
    "addr:housenumber":"42",
    "addr:postcode":"m9w 5m7",
    "addr:street":"Voyager Crt S",
    "iso:country":"CA",
    "sg:address":"42 Voyager Crt S",
    "sg:city":"Etobicoke",
    "sg:classifiers":[
        {
            "category":"Manufacturing",
            "subcategory":"Printing",
            "type":"Manufacturing & Wholesale Goods"
        }
    ],
    "sg:phone":"+1 416 679 0170",
    "sg:postcode":"M9W 5M7",
    "sg:province":"ON",
    "sg:tags":[
        "publisher"
    ],
    "wof:name":"Retail News Magazine",
    "wof:placetype":"venue"
},
  "geometry": {"coordinates":[-79.58773040769999,43.6770744324],"type":"Point"}
}