{
  "type": "Feature",
  "properties": {
    "addr:full":"1928 Beaver St Fruitvale BC V0G 1L0",
    "addr:housenumber":"1928",
    "addr:postcode":"v0g 1l0",
    "addr:street":"Beaver St",
    "iso:country":"CA",
    "sg:address":"1928 Beaver St",
    "sg:city":"Fruitvale",
    "sg:classifiers":[
        {
            "category":"Social Services",
            "type":"Services"
        }
    ],
    "sg:phone":"+1 250 367 0212",
    "sg:postcode":"V0G 1L0",
    "sg:province":"BC",
    "sg:tags":[
        "youth",
        "organization",
        "center"
    ],
    "wof:name":"Beaver Valley Youth Ctr",
    "wof:placetype":"venue"
},
  "geometry": {"coordinates":[-117.547157,49.112415],"type":"Point"}
}