{
  "type": "Feature",
  "properties": {
    "addr:full":"1410 Main St E Hamilton ON L8K 1C3",
    "addr:housenumber":"1410",
    "addr:postcode":"l8k 1c3",
    "addr:street":"Main St E",
    "iso:country":"CA",
    "sg:address":"1410 Main St E",
    "sg:city":"Hamilton",
    "sg:classifiers":[
        {
            "category":"Restaurant",
            "type":"Food & Drink"
        }
    ],
    "sg:phone":"+1 905 545 7423",
    "sg:postcode":"L8K 1C3",
    "sg:province":"ON",
    "wof:name":"South Pacific Chinese Food",
    "wof:placetype":"venue"
},
  "geometry": {"coordinates":[-79.80978393549999,43.2402954102],"type":"Point"}
}