{
  "type": "Feature",
  "properties": {
    "addr:full":"146 Elgin Hastings ON K0L 1Y0",
    "addr:housenumber":"146",
    "addr:postcode":"k0l 1y0",
    "addr:street":"Elgin",
    "iso:country":"CA",
    "sg:address":"146 Elgin",
    "sg:city":"Hastings",
    "sg:classifiers":[
        {
            "category":"Government",
            "subcategory":"Office",
            "type":"Public Place"
        }
    ],
    "sg:phone":"+1 705 696 3984",
    "sg:postcode":"K0L 1Y0",
    "sg:province":"ON",
    "sg:tags":[
        "village"
    ],
    "wof:name":"Hastings Municipal Garage",
    "wof:placetype":"venue"
},
  "geometry": {"coordinates":[-77.958229,44.303364],"type":"Point"}
}