{
  "type": "Feature",
  "properties": {
    "addr:full":"Calgary AB T1Y 3R6",
    "addr:postcode":"t1y 3r6",
    "iso:country":"CA",
    "sg:city":"Calgary",
    "sg:classifiers":[
        {
            "category":"Health Services",
            "subcategory":"Health Practitioner",
            "type":"Services"
        }
    ],
    "sg:phone":"+1 403 280 9728",
    "sg:postcode":"T1Y 3R6",
    "sg:province":"AB",
    "sg:tags":[
        "therapist",
        "physical"
    ],
    "wof:name":"Village Square Sport Physio",
    "wof:placetype":"venue"
},
  "geometry": {"coordinates":[-113.958275,51.075523],"type":"Point"}
}