{
  "type": "Feature",
  "properties": {
    "addr:full":"26 Hwy 105 Red Lake ON P0V 2M0",
    "addr:postcode":"p0v 2m0",
    "addr:street":"26 Hwy 105;Lake",
    "iso:country":"CA",
    "sg:address":"26 Hwy 105",
    "sg:city":"Red Lake",
    "sg:classifiers":[
        {
            "category":"Travel",
            "subcategory":"Hotels & Motels",
            "type":"Entertainment"
        }
    ],
    "sg:phone":"+1 807 727 3419",
    "sg:postcode":"P0V 2M0",
    "sg:province":"ON",
    "wof:name":"Howey Bay Motel",
    "wof:placetype":"venue"
},
  "geometry": {"coordinates":[-93.82073200000001,51.018318],"type":"Point"}
}