{
  "type": "Feature",
  "properties": {
    "addr:full":"125 128E Av Saint-Hippolyte QC J8A 2H7",
    "addr:housenumber":"125",
    "addr:postcode":"j8a 2h7",
    "addr:street":"128E Av Saint-Hippolyte",
    "iso:country":"CA",
    "sg:address":"125 128E Av",
    "sg:city":"Saint-Hippolyte",
    "sg:classifiers":[
        {
            "category":"Building & Trades",
            "subcategory":"Landscaping Services",
            "type":"Services"
        }
    ],
    "sg:phone":"+1 450 563 3821",
    "sg:postcode":"J8A 2H7",
    "sg:province":"QC",
    "sg:tags":[
        "landscape",
        "contractor"
    ],
    "wof:name":"Amenagements Paysager 2000 Enr",
    "wof:placetype":"venue"
},
  "geometry": {"coordinates":[-74.02508544920001,45.930644989],"type":"Point"}
}