{
  "type": "Feature",
  "properties": {
    "addr:full":"255 Broadway Ave E Regina SK S4N 0Z6",
    "addr:housenumber":"255",
    "addr:postcode":"s4n 0z6",
    "addr:street":"Broadway Ave E",
    "iso:country":"CA",
    "sg:address":"255 Broadway Ave E",
    "sg:city":"Regina",
    "sg:classifiers":[
        {
            "category":"Retail",
            "subcategory":"Laundry & Dry Cleaning",
            "type":"Services"
        }
    ],
    "sg:phone":"+1 306 757 3354",
    "sg:postcode":"S4N 0Z6",
    "sg:province":"SK",
    "sg:tags":[
        "cleaners",
        "convenience",
        "store"
    ],
    "wof:name":"Klein's Food Mart",
    "wof:placetype":"venue"
},
  "geometry": {"coordinates":[-104.579544067,50.4375953674],"type":"Point"}
}