{
  "type": "Feature",
  "properties": {
    "iso:country":"CA",
    "sg:city":"Oakville",
    "sg:classifiers":[
        {
            "category":"Wholesale",
            "subcategory":"Non-durable Goods",
            "type":"Manufacturing & Wholesale Goods"
        }
    ],
    "sg:phone":"+1 905 842 3355",
    "sg:postcode":"L6H 3K4",
    "sg:province":"ON",
    "sg:tags":[
        "advertising"
    ],
    "wof:name":"Promotion Resource Group",
    "wof:placetype":"venue"
},
  "geometry": {"coordinates":[-79.681534,43.467503],"type":"Point"}
}