{
  "type": "Feature",
  "properties": {
    "iso:country":"CA",
    "sg:city":"Newmarket",
    "sg:classifiers":[
        {
            "category":"Health Services",
            "subcategory":"Doctor",
            "type":"Services"
        }
    ],
    "sg:phone":"+1 905 898 7667",
    "sg:postcode":"L3Y 5G8",
    "sg:province":"ON",
    "sg:tags":[
        "physician",
        "surgeon"
    ],
    "wof:name":"Sweet Dreams Snoring & Laser",
    "wof:placetype":"venue"
},
  "geometry": {"coordinates":[-79.448883,44.06205],"type":"Point"}
}