{
  "type": "Feature",
  "properties": {
    "addr:full":"23 Main St W Norwich ON N0J 1P0",
    "addr:housenumber":"23",
    "addr:postcode":"n0j 1p0",
    "addr:street":"Main St W",
    "iso:country":"CA",
    "sg:address":"23 Main St W",
    "sg:city":"Norwich",
    "sg:classifiers":[
        {
            "category":"Personal",
            "subcategory":"Beauty Salon",
            "type":"Services"
        }
    ],
    "sg:phone":"+1 519 863 2237",
    "sg:postcode":"N0J 1P0",
    "sg:province":"ON",
    "wof:name":"Mane Event",
    "wof:placetype":"venue"
},
  "geometry": {"coordinates":[-80.59819,42.987366],"type":"Point"}
}