{
  "type": "Feature",
  "properties": {
    "addr:full":"348 Rue Denison O Granby QC J2G 4E6",
    "addr:housenumber":"348",
    "addr:postcode":"j2g 4e6",
    "addr:street":"Rue Denison O",
    "iso:country":"CA",
    "sg:address":"348 Rue Denison O",
    "sg:city":"Granby",
    "sg:classifiers":[
        {
            "category":"Shopping",
            "subcategory":"Gifts & Souvenirs",
            "type":"Retail Goods"
        }
    ],
    "sg:phone":"+1 450 378 2473",
    "sg:postcode":"J2G 4E6",
    "sg:province":"QC",
    "sg:tags":[
        "hardware",
        "party",
        "supply"
    ],
    "wof:name":"Quincaillerie St-Charles",
    "wof:placetype":"venue"
},
  "geometry": {"coordinates":[-72.699997,45.393978],"type":"Point"}
}