{
  "type": "Feature",
  "properties": {
    "addr:full":"1648 Derwent Way Delta BC V3M 6R9",
    "addr:housenumber":"1648",
    "addr:postcode":"v3m 6r9",
    "addr:street":"Derwent Way",
    "iso:country":"CA",
    "sg:address":"1648 Derwent Way",
    "sg:city":"Delta",
    "sg:classifiers":[
        {
            "category":"Manufacturing",
            "subcategory":"Food",
            "type":"Manufacturing & Wholesale Goods"
        }
    ],
    "sg:phone":"+1 604 515 7117",
    "sg:postcode":"V3M 6R9",
    "sg:province":"BC",
    "sg:tags":[
        "product",
        "candy"
    ],
    "wof:name":"Dynamic Chocolates Inc",
    "wof:placetype":"venue"
},
  "geometry": {"coordinates":[-122.968216,49.161381],"type":"Point"}
}