{
  "type": "Feature",
  "properties": {
    "addr:full":"1389 Rue Des Camarades Val-Belair QC G3K 2N5",
    "addr:housenumber":"1389",
    "addr:postcode":"g3k 2n5",
    "addr:street":"Rue Des Camarades Val-Belair",
    "iso:country":"CA",
    "sg:address":"1389 Rue Des Camarades",
    "sg:city":"Val-Belair",
    "sg:classifiers":[
        {
            "category":"Education",
            "subcategory":"School",
            "type":"Public Place"
        }
    ],
    "sg:phone":"+1 418 847 7129",
    "sg:postcode":"G3K 2N5",
    "sg:province":"QC",
    "wof:name":"A L'Oree-Des-Bois",
    "wof:placetype":"venue"
},
  "geometry": {"coordinates":[-71.41217041020001,46.8465156555],"type":"Point"}
}