{
  "type": "Feature",
  "properties": {
    "addr:full":"613 Danforth Ave Toronto ON M4K 1R2",
    "addr:housenumber":"613",
    "addr:postcode":"m4k 1r2",
    "addr:street":"Danforth Ave",
    "iso:country":"CA",
    "sg:address":"613 Danforth Ave",
    "sg:city":"Toronto",
    "sg:classifiers":[
        {
            "category":"Shopping",
            "subcategory":"Department Store",
            "type":"Retail Goods"
        }
    ],
    "sg:phone":"+1 416 778 8829",
    "sg:postcode":"M4K 1R2",
    "sg:province":"ON",
    "sg:tags":[
        "shop"
    ],
    "wof:name":"Dollar Depot Plus",
    "wof:placetype":"venue"
},
  "geometry": {"coordinates":[-79.34577941889999,43.6785774231],"type":"Point"}
}