{
  "type": "Feature",
  "properties": {
    "addr:full":"10040 164 St NW Edmonton AB T5P 4Y3",
    "addr:housenumber":"10040",
    "addr:postcode":"t5p 4y3",
    "addr:street":"164 St Nw",
    "iso:country":"CA",
    "sg:address":"10040 164 St NW",
    "sg:city":"Edmonton",
    "sg:classifiers":[
        {
            "category":"Arts & Performance",
            "subcategory":"Theater",
            "type":"Entertainment"
        }
    ],
    "sg:phone":"+1 780 413 1756",
    "sg:postcode":"T5P 4Y3",
    "sg:province":"AB",
    "sg:tags":[
        "live",
        "music"
    ],
    "wof:name":"Atomic Sound & Dj Svc",
    "wof:placetype":"venue"
},
  "geometry": {"coordinates":[-113.604766846,53.5401382446],"type":"Point"}
}