{
  "type": "Feature",
  "properties": {
    "addr:full":"854 Pandora Ave Victoria BC V8W 1P4",
    "addr:housenumber":"854",
    "addr:postcode":"v8w 1p4",
    "addr:street":"Pandora Ave",
    "iso:country":"CA",
    "sg:address":"854 Pandora Ave",
    "sg:city":"Victoria",
    "sg:classifiers":[
        {
            "category":"Professional",
            "subcategory":"Computer Services",
            "type":"Services"
        }
    ],
    "sg:phone":"+1 250 595 8282",
    "sg:postcode":"V8W 1P4",
    "sg:province":"BC",
    "sg:tags":[
        "consultant",
        "designer"
    ],
    "wof:name":"Iti Intl Technology",
    "wof:placetype":"venue"
},
  "geometry": {"coordinates":[-123.35975646999999,48.4277076721],"type":"Point"}
}