{
  "type": "Feature",
  "properties": {
    "addr:full":"9 Boul Montclair Hull QC J8Y 2E2",
    "addr:housenumber":"9",
    "addr:postcode":"j8y 2e2",
    "addr:street":"Boul Montclair",
    "iso:country":"CA",
    "sg:address":"9 Boul Montclair",
    "sg:city":"Hull",
    "sg:classifiers":[
        {
            "category":"Shopping",
            "subcategory":"Department Store",
            "type":"Retail Goods"
        }
    ],
    "sg:phone":"+1 819 770 6886",
    "sg:postcode":"J8Y 2E2",
    "sg:province":"QC",
    "wof:name":"Aubainerie",
    "wof:placetype":"venue"
},
  "geometry": {"coordinates":[-75.728889,45.440289],"type":"Point"}
}