{
  "type": "Feature",
  "properties": {
    "addr:full":"261 Talbot St W Aylmer ON N5H 1J9",
    "addr:housenumber":"261",
    "addr:postcode":"n5h 1j9",
    "addr:street":"Talbot St W",
    "iso:country":"CA",
    "sg:address":"261 Talbot St W",
    "sg:city":"Aylmer",
    "sg:classifiers":[
        {
            "category":"Shopping",
            "subcategory":"Optical Goods",
            "type":"Retail Goods"
        }
    ],
    "sg:phone":"+1 519 765 2084",
    "sg:postcode":"N5H 1J9",
    "sg:province":"ON",
    "sg:tags":[
        "sun",
        "goggles",
        "sunglasses",
        "optician"
    ],
    "wof:name":"Dan Axford Opticians",
    "wof:placetype":"venue"
},
  "geometry": {"coordinates":[-80.987991333,42.7732162476],"type":"Point"}
}