{
  "type": "Feature",
  "properties": {
    "iso:country":"CA",
    "sg:city":"North York",
    "sg:classifiers":[
        {
            "category":"Health Services",
            "subcategory":"Doctor",
            "type":"Services"
        }
    ],
    "sg:phone":"+1 416 491 8306",
    "sg:postcode":"M2J 2Z1",
    "sg:province":"ON",
    "sg:tags":[
        "physician",
        "surgeon"
    ],
    "wof:name":"Weinstein, Joel MD",
    "wof:placetype":"venue"
},
  "geometry": {"coordinates":[-79.3483200073,43.7790222168],"type":"Point"}
}