{
  "type": "Feature",
  "properties": {
    "addr:full":"100 Munro St Bathurst NB E2A 1G1",
    "addr:housenumber":"100",
    "addr:postcode":"e2a 1g1",
    "addr:street":"Munro St",
    "iso:country":"CA",
    "sg:address":"100 Munro St",
    "sg:city":"Bathurst",
    "sg:classifiers":[
        {
            "category":"Wholesale",
            "subcategory":"Farm Supplies",
            "type":"Manufacturing & Wholesale Goods"
        }
    ],
    "sg:phone":"+1 506 548 8730",
    "sg:postcode":"E2A 1G1",
    "sg:province":"NB",
    "sg:tags":[
        "feed"
    ],
    "wof:name":"Bathurst Agriculture Society",
    "wof:placetype":"venue"
},
  "geometry": {"coordinates":[-65.6532745361,47.6139297485],"type":"Point"}
}