{
  "type": "Feature",
  "properties": {
    "addr:full":"61 Burnett Ave Winnipeg MB R2G 1C2",
    "addr:housenumber":"61",
    "addr:postcode":"r2g 1c2",
    "addr:street":"Burnett Ave",
    "iso:country":"CA",
    "sg:address":"61 Burnett Ave",
    "sg:city":"Winnipeg",
    "sg:classifiers":[
        {
            "category":"Home & Garden",
            "subcategory":"Building Materials",
            "type":"Retail Goods"
        }
    ],
    "sg:phone":"+1 204 235 1872",
    "sg:postcode":"R2G 1C2",
    "sg:province":"MB",
    "sg:tags":[
        "door"
    ],
    "wof:name":"Dave's Overhead Doors",
    "wof:placetype":"venue"
},
  "geometry": {"coordinates":[-97.0637435913,49.9318962097],"type":"Point"}
}