{
  "type": "Feature",
  "properties": {
    "iso:country":"CA",
    "sg:address":"669 Principale St",
    "sg:city":"Casselman",
    "sg:classifiers":[
        {
            "category":"Retail",
            "subcategory":"Auto Repair",
            "type":"Services"
        }
    ],
    "sg:phone":"+1 613 764 1670",
    "sg:postcode":"K0A 1M0",
    "sg:province":"ON",
    "sg:tags":[
        "repairing",
        "automobile",
        "wrecker"
    ],
    "wof:name":"Menard Garage",
    "wof:placetype":"venue"
},
  "geometry": {"coordinates":[-75.0838088989,45.308807373],"type":"Point"}
}