{
  "type": "Feature",
  "properties": {
    "addr:full":"Brooks AB T1R 0C3",
    "addr:postcode":"t1r 0c3",
    "iso:country":"CA",
    "sg:city":"Brooks",
    "sg:classifiers":[
        {
            "category":"Mining & Drilling",
            "type":"Manufacturing & Wholesale Goods"
        }
    ],
    "sg:phone":"+1 403 362 3800",
    "sg:postcode":"T1R 0C3",
    "sg:province":"AB",
    "sg:tags":[
        "field",
        "oil"
    ],
    "wof:name":"Midfield Supply Ltd",
    "wof:placetype":"venue"
},
  "geometry": {"coordinates":[-111.896996,50.580875],"type":"Point"}
}