{
  "type": "Feature",
  "properties": {
    "addr:full":"319 17th St W North Vancouver BC V7M 1V9",
    "addr:housenumber":"319",
    "addr:postcode":"v7m 1v9",
    "addr:street":"17Th St W",
    "iso:country":"CA",
    "sg:address":"319 17th St W",
    "sg:city":"North Vancouver",
    "sg:classifiers":[
        {
            "category":"Professional",
            "subcategory":"Art Services",
            "type":"Services"
        }
    ],
    "sg:phone":"+1 604 986 1044",
    "sg:postcode":"V7M 1V9",
    "sg:province":"BC",
    "sg:tags":[
        "graphic",
        "designer"
    ],
    "wof:name":"Insights Images",
    "wof:placetype":"venue"
},
  "geometry": {"coordinates":[-123.07929229699999,49.3240699768],"type":"Point"}
}