{
  "type": "Feature",
  "properties": {
    "addr:full":"360 Rue Saint-Jacques # 415 Montreal QC H2Y 1P5",
    "addr:housenumber":"360;415",
    "addr:postcode":"h2y 1p5",
    "addr:street":"Rue Saint-Jacques #",
    "iso:country":"CA",
    "sg:address":"360 Rue Saint-Jacques # 415",
    "sg:city":"Montreal",
    "sg:classifiers":[
        {
            "category":"Wholesale",
            "subcategory":"Machinery & Supplies",
            "type":"Manufacturing & Wholesale Goods"
        }
    ],
    "sg:phone":"+1 514 380 8558",
    "sg:postcode":"H2Y 1P5",
    "sg:province":"QC",
    "sg:tags":[
        "stock",
        "boards",
        "system",
        "quotation"
    ],
    "wof:name":"Belzberg Technologies Inc",
    "wof:placetype":"venue"
},
  "geometry": {"coordinates":[-73.559425354,45.5022315979],"type":"Point"}
}