{
  "type": "Feature",
  "properties": {
    "addr:full":"977 Pantera Dr # 6 Mississauga ON L4W 2W6",
    "addr:housenumber":"977",
    "addr:postcode":"l4w 2w6",
    "addr:street":"Pantera Dr # 6",
    "iso:country":"CA",
    "sg:address":"977 Pantera Dr # 6",
    "sg:city":"Mississauga",
    "sg:classifiers":[
        {
            "category":"Manufacturing",
            "subcategory":"Furniture",
            "type":"Manufacturing & Wholesale Goods"
        }
    ],
    "sg:phone":"+1 905 629 9996",
    "sg:postcode":"L4W 2W6",
    "sg:province":"ON",
    "wof:name":"Temdex Industries Ltd",
    "wof:placetype":"venue"
},
  "geometry": {"coordinates":[-79.6384506226,43.6304397583],"type":"Point"}
}