{
  "type": "Feature",
  "properties": {
    "addr:full":"649 Justus Dr Kingston ON K7M 4H5",
    "addr:housenumber":"649",
    "addr:postcode":"k7m 4h5",
    "addr:street":"Justus Dr",
    "iso:country":"CA",
    "sg:address":"649 Justus Dr",
    "sg:city":"Kingston",
    "sg:classifiers":[
        {
            "category":"Home & Garden",
            "subcategory":"Carpets & Floor Coverings",
            "type":"Retail Goods"
        }
    ],
    "sg:phone":"+1 613 384 7447",
    "sg:postcode":"K7M 4H5",
    "sg:province":"ON",
    "sg:tags":[
        "material"
    ],
    "wof:name":"Grant's Tile & Bath Ctr",
    "wof:placetype":"venue"
},
  "geometry": {"coordinates":[-76.57251739500001,44.2452087402],"type":"Point"}
}