{
  "type": "Feature",
  "properties": {
    "iso:country":"CA",
    "sg:address":"2726 Loon Lake Rd",
    "sg:city":"Cache Creek",
    "sg:classifiers":[
        {
            "category":"Travel",
            "subcategory":"Hotels & Motels",
            "type":"Entertainment"
        }
    ],
    "sg:phone":"+1 250 459 2537",
    "sg:postcode":"V0K 1H0",
    "sg:province":"BC",
    "sg:tags":[
        "resort"
    ],
    "wof:name":"Loon Lake Resort",
    "wof:placetype":"venue"
},
  "geometry": {"coordinates":[-121.326438904,50.8133850098],"type":"Point"}
}