{
  "type": "Feature",
  "properties": {
    "addr:full":"Pierrefonds QC H9H 1A9",
    "addr:postcode":"h9h 1a9",
    "iso:country":"CA",
    "sg:city":"Pierrefonds",
    "sg:classifiers":[
        {
            "category":"Retail",
            "subcategory":"Auto Repair",
            "type":"Services"
        }
    ],
    "sg:phone":"+1 514 620 0157",
    "sg:postcode":"H9H 1A9",
    "sg:province":"QC",
    "sg:tags":[
        "repairing",
        "automobile"
    ],
    "wof:name":"Garage Gilbert Trivaudey Enr",
    "wof:placetype":"venue"
},
  "geometry": {"coordinates":[-73.853989,45.493004],"type":"Point"}
}