{
  "type": "Feature",
  "properties": {
    "addr:full":"Edwardsville NS B2A 4T1",
    "addr:postcode":"b2a 4t1",
    "iso:country":"CA",
    "sg:city":"Edwardsville",
    "sg:classifiers":[
        {
            "category":"Professional",
            "subcategory":"Management & Consulting",
            "type":"Services"
        }
    ],
    "sg:phone":"+1 902 564 6768",
    "sg:postcode":"B2A 4T1",
    "sg:province":"NS",
    "sg:tags":[
        "consultant",
        "mining"
    ],
    "wof:name":"S Farrell & Assoc Ltd",
    "wof:placetype":"venue"
},
  "geometry": {"coordinates":[-60.229969,46.157864],"type":"Point"}
}