{
  "type": "Feature",
  "properties": {
    "addr:full":"753 Mccraney Cres Prince Albert SK S6V 6W3",
    "addr:housenumber":"753",
    "addr:postcode":"s6v 6w3",
    "addr:street":"Mccraney Cres",
    "iso:country":"CA",
    "sg:address":"753 Mccraney Cres",
    "sg:city":"Prince Albert",
    "sg:classifiers":[
        {
            "category":"Freight",
            "type":"Transportation"
        }
    ],
    "sg:phone":"+1 306 763 5378",
    "sg:postcode":"S6V 6W3",
    "sg:province":"SK",
    "sg:tags":[
        "trucking"
    ],
    "wof:name":"Central Transport",
    "wof:placetype":"venue"
},
  "geometry": {"coordinates":[-105.705788,53.201328],"type":"Point"}
}