{
  "type": "Feature",
  "properties": {
    "iso:country":"CA",
    "sg:address":"1311 Day St",
    "sg:city":"Winnipeg",
    "sg:classifiers":[
        {
            "category":"Restaurant",
            "type":"Food & Drink"
        }
    ],
    "sg:phone":"+1 204 222 6365",
    "sg:postcode":"R2C 1E1",
    "sg:province":"MB",
    "wof:name":"Mr B's Pizza & Chicken",
    "wof:placetype":"venue"
},
  "geometry": {"coordinates":[-97.002731,49.903236],"type":"Point"}
}