{
  "type": "Feature",
  "properties": {
    "addr:full":"9972 350th Ave Oliver BC V0H 1T0",
    "addr:housenumber":"9972",
    "addr:postcode":"bc v0h 1t0",
    "addr:street":"350Th Ave",
    "iso:country":"CA",
    "sg:address":"9972 350th Ave",
    "sg:city":"Oliver",
    "sg:classifiers":[
        {
            "category":"Personal",
            "subcategory":"Beauty Salon",
            "type":"Services"
        }
    ],
    "sg:phone":"+1 250 498 3064",
    "sg:postcode":"V0H 1T0",
    "sg:province":"BC",
    "wof:name":"Inner Visions Hair Design",
    "wof:placetype":"venue"
},
  "geometry": {"coordinates":[-119.553696,49.181156],"type":"Point"}
}