{
  "type": "Feature",
  "properties": {
    "iso:country":"CA",
    "sg:city":"Montreal",
    "sg:classifiers":[
        {
            "category":"Professional",
            "subcategory":"Accounting & Tax Preparation",
            "type":"Services"
        }
    ],
    "sg:phone":"+1 514 277 7009",
    "sg:postcode":"H2R 2E9",
    "sg:province":"QC",
    "sg:tags":[
        "accountant"
    ],
    "wof:name":"Lyrette, Robert CA",
    "wof:placetype":"venue"
},
  "geometry": {"coordinates":[-73.62334442140001,45.5410995483],"type":"Point"}
}