{
  "type": "Feature",
  "properties": {
    "addr:full":"638 Highlands Cres Saskatoon SK S7H 4Y4",
    "addr:housenumber":"638",
    "addr:postcode":"s7h 4y4",
    "addr:street":"Highlands Cres",
    "iso:country":"CA",
    "sg:address":"638 Highlands Cres",
    "sg:city":"Saskatoon",
    "sg:classifiers":[
        {
            "category":"Real Estate",
            "subcategory":"Real Estate Agent",
            "type":"Services"
        }
    ],
    "sg:phone":"+1 306 373 0326",
    "sg:postcode":"S7H 4Y4",
    "sg:province":"SK",
    "sg:tags":[
        "management",
        "rental",
        "agency"
    ],
    "wof:name":"Normand Properties Agencies",
    "wof:placetype":"venue"
},
  "geometry": {"coordinates":[-106.60127300000001,52.110157],"type":"Point"}
}