{
  "type": "Feature",
  "properties": {
    "iso:country":"CA",
    "sg:address":"260 Rue Gagnon",
    "sg:city":"Beauharnois",
    "sg:classifiers":[
        {
            "category":"Education",
            "subcategory":"School",
            "type":"Public Place"
        }
    ],
    "sg:phone":"+1 450 225 1084",
    "sg:postcode":"J6N 2W8",
    "sg:province":"QC",
    "sg:tags":[
        "academic",
        "special"
    ],
    "wof:name":"Centre Professionel-Moissons",
    "wof:placetype":"venue"
},
  "geometry": {"coordinates":[-73.870598,45.302128],"type":"Point"}
}