{
  "type": "Feature",
  "properties": {
    "addr:full":"494 Talbot St E Leamington ON N8H 3V6",
    "addr:housenumber":"494",
    "addr:postcode":"n8h 3v6",
    "addr:street":"Talbot St E",
    "iso:country":"CA",
    "sg:address":"494 Talbot St E",
    "sg:city":"Leamington",
    "sg:classifiers":[
        {
            "category":"Social Services",
            "subcategory":"Child Care",
            "type":"Services"
        }
    ],
    "sg:phone":"+1 519 326 0579",
    "sg:postcode":"N8H 3V6",
    "sg:province":"ON",
    "wof:name":"Playtime Village Day Care Ctr",
    "wof:placetype":"venue"
},
  "geometry": {"coordinates":[-82.543396,42.06673],"type":"Point"}
}