{
  "type": "Feature",
  "properties": {
    "addr:full":"9557 Yonge St Richmond Hill ON L4C 9M5",
    "addr:housenumber":"9557",
    "addr:postcode":"l4c 9m5",
    "addr:street":"Yonge St",
    "iso:country":"CA",
    "sg:address":"9557 Yonge St",
    "sg:city":"Richmond Hill",
    "sg:classifiers":[
        {
            "category":"Restaurant",
            "type":"Food & Drink"
        }
    ],
    "sg:phone":"+1 905 737 2486",
    "sg:postcode":"L4C 9M5",
    "sg:province":"ON",
    "wof:name":"Kfc",
    "wof:placetype":"venue"
},
  "geometry": {"coordinates":[-79.43444824220001,43.8599967957],"type":"Point"}
}