{
  "type": "Feature",
  "properties": {
    "addr:full":"PO Box 225 Barrington Passage NS B0W 1G0",
    "addr:housenumber":"po;225",
    "addr:postcode":"b0w 1g0",
    "addr:street":"Box",
    "iso:country":"CA",
    "sg:address":"PO Box 225",
    "sg:city":"Barrington Passage",
    "sg:classifiers":[
        {
            "category":"Personal",
            "subcategory":"Beauty Salon",
            "type":"Services"
        }
    ],
    "sg:phone":"+1 902 637 3444",
    "sg:postcode":"B0W 1G0",
    "sg:province":"NS",
    "wof:name":"Hair Emporium",
    "wof:placetype":"venue"
},
  "geometry": {"coordinates":[-65.61045799999999,43.525871],"type":"Point"}
}