{
  "type": "Feature",
  "properties": {
    "iso:country":"CA",
    "sg:address":"53 Rue Fortier",
    "sg:city":"Hull",
    "sg:classifiers":[
        {
            "category":"Personal",
            "subcategory":"Beauty Salon",
            "type":"Services"
        }
    ],
    "sg:phone":"+1 819 771 2902",
    "sg:postcode":"J8Y 4R2",
    "sg:province":"QC",
    "wof:name":"Salon D'Auteuil",
    "wof:placetype":"venue"
},
  "geometry": {"coordinates":[-75.7373352051,45.4414215088],"type":"Point"}
}