{
  "type": "Feature",
  "properties": {
    "addr:full":"64 Royalty Rd Charlottetown PE C1E 1Z4",
    "addr:housenumber":"64",
    "addr:postcode":"c1e 1z4",
    "addr:street":"Royalty Rd",
    "iso:country":"CA",
    "sg:address":"64 Royalty Rd",
    "sg:city":"Charlottetown",
    "sg:classifiers":[
        {
            "category":"Building & Trades",
            "subcategory":"Construction",
            "type":"Services"
        }
    ],
    "sg:phone":"+1 902 368 1740",
    "sg:postcode":"C1E 1Z4",
    "sg:province":"PE",
    "sg:tags":[
        "wire",
        "cable",
        "laying",
        "derrick",
        "underground",
        "crane"
    ],
    "wof:name":"Atlantic Enterprise Ltd",
    "wof:placetype":"venue"
},
  "geometry": {"coordinates":[-63.1741447449,46.2812843323],"type":"Point"}
}