{
  "type": "Feature",
  "properties": {
    "iso:country":"CA",
    "sg:address":"333 Rue Labbe",
    "sg:city":"Thetford Mines",
    "sg:classifiers":[
        {
            "category":"Food & Beverages",
            "subcategory":"Groceries & Convenience Stores",
            "type":"Retail Goods"
        }
    ],
    "sg:phone":"+1 418 335 3089",
    "sg:postcode":"G6G 1Z2",
    "sg:province":"QC",
    "sg:tags":[
        "post"
    ],
    "wof:name":"Depanneur Chez Pee-Wee Inc",
    "wof:placetype":"venue"
},
  "geometry": {"coordinates":[-71.29829406739999,46.0982475281],"type":"Point"}
}