{
  "type": "Feature",
  "properties": {
    "addr:full":"21765 48 Ave Langley BC V3A 3N1",
    "addr:housenumber":"21765",
    "addr:postcode":"v3a 3n1",
    "addr:street":"48 Ave",
    "iso:country":"CA",
    "sg:address":"21765 48 Ave",
    "sg:city":"Langley",
    "sg:classifiers":[
        {
            "category":"Health Services",
            "subcategory":"Doctor",
            "type":"Services"
        }
    ],
    "sg:phone":"+1 604 534 8707",
    "sg:postcode":"V3A 3N1",
    "sg:province":"BC",
    "sg:tags":[
        "physician",
        "surgeon"
    ],
    "wof:name":"Poynter, Aven J MD",
    "wof:placetype":"venue"
},
  "geometry": {"coordinates":[-122.620025635,49.089515686],"type":"Point"}
}