{
  "type": "Feature",
  "properties": {
    "addr:full":"Delta BC V4C 3C7",
    "addr:postcode":"v4c 3c7",
    "iso:country":"CA",
    "sg:city":"Delta",
    "sg:classifiers":[
        {
            "category":"Real Estate",
            "subcategory":"Real Estate Operator",
            "type":"Services"
        }
    ],
    "sg:phone":"+1 604 596 9588",
    "sg:postcode":"V4C 3C7",
    "sg:province":"BC",
    "sg:tags":[
        "apartment"
    ],
    "wof:name":"Kennedy Place Apartments",
    "wof:placetype":"venue"
},
  "geometry": {"coordinates":[-122.893997192,49.1631278992],"type":"Point"}
}