{
  "type": "Feature",
  "properties": {
    "iso:country":"CA",
    "sg:city":"London",
    "sg:classifiers":[
        {
            "category":"Health Services",
            "subcategory":"Health Practitioner",
            "type":"Services"
        }
    ],
    "sg:phone":"+1 519 438 8591",
    "sg:postcode":"N6A 1S2",
    "sg:province":"ON",
    "sg:tags":[
        "psychologist"
    ],
    "wof:name":"Partridge, Kate PhD",
    "wof:placetype":"venue"
},
  "geometry": {"coordinates":[-81.2529220581,42.9942741394],"type":"Point"}
}