{
  "type": "Feature",
  "properties": {
    "addr:full":"3040 Deziel Dr Windsor ON N8W 5H8",
    "addr:housenumber":"3040",
    "addr:postcode":"n8w 5h8",
    "addr:street":"Deziel Dr",
    "iso:country":"CA",
    "sg:address":"3040 Deziel Dr",
    "sg:city":"Windsor",
    "sg:classifiers":[
        {
            "category":"Wholesale",
            "subcategory":"Electrical",
            "type":"Manufacturing & Wholesale Goods"
        }
    ],
    "sg:phone":"+1 519 974 0099",
    "sg:postcode":"N8W 5H8",
    "sg:province":"ON",
    "sg:tags":[
        "equipment",
        "electric",
        "supply"
    ],
    "wof:name":"Nedco",
    "wof:placetype":"venue"
},
  "geometry": {"coordinates":[-82.97207641599999,42.2823753357],"type":"Point"}
}