{
  "type": "Feature",
  "properties": {
    "addr:full":"10729 104 Ave NW Edmonton AB T5J 3K1",
    "addr:housenumber":"10729",
    "addr:postcode":"t5j 3k1",
    "addr:street":"104 Ave Nw",
    "iso:country":"CA",
    "sg:address":"10729 104 Ave NW",
    "sg:city":"Edmonton",
    "sg:classifiers":[
        {
            "category":"Travel",
            "subcategory":"Travel Agent",
            "type":"Entertainment"
        }
    ],
    "sg:phone":"+1 780 496 7587",
    "sg:postcode":"T5J 3K1",
    "sg:province":"AB",
    "sg:tags":[
        "agency",
        "bureau"
    ],
    "wof:name":"Vacations Plus/Travel Sprstore",
    "wof:placetype":"venue"
},
  "geometry": {"coordinates":[-113.50535600000001,53.546116],"type":"Point"}
}