{
  "type": "Feature",
  "properties": {
    "iso:country":"CA",
    "sg:address":"Hwy 43",
    "sg:city":"Debolt",
    "sg:classifiers":[
        {
            "category":"Building & Trades",
            "subcategory":"Construction",
            "type":"Services"
        }
    ],
    "sg:phone":"+1 780 957 2535",
    "sg:postcode":"T0H 1B0",
    "sg:province":"AB",
    "sg:tags":[
        "maker",
        "cabinet"
    ],
    "wof:name":"P & G Kitchens",
    "wof:placetype":"venue"
},
  "geometry": {"coordinates":[-118.026420593,55.2171669006],"type":"Point"}
}