{
  "type": "Feature",
  "properties": {
    "addr:full":"960 19 St S Lethbridge AB T1J 1W5",
    "addr:postcode":"960 19;t1j 1w5",
    "addr:street":"St S",
    "iso:country":"CA",
    "sg:address":"960 19 St S",
    "sg:city":"Lethbridge",
    "sg:classifiers":[
        {
            "category":"Health Services",
            "subcategory":"Hospital",
            "type":"Services"
        }
    ],
    "sg:phone":"+1 403 388 6111",
    "sg:postcode":"T1J 1W5",
    "sg:province":"AB",
    "wof:name":"Lethbridge Regional Hospital",
    "wof:placetype":"venue"
},
  "geometry": {"coordinates":[-112.81487300000001,49.684879],"type":"Point"}
}