{
  "type": "Feature",
  "properties": {
    "addr:full":"744 Quesnel Rd Sturgeon Falls ON P2B 2W3",
    "addr:housenumber":"744",
    "addr:postcode":"p2b 2w3",
    "addr:street":"Quesnel Rd",
    "iso:country":"CA",
    "sg:address":"744 Quesnel Rd",
    "sg:city":"Sturgeon Falls",
    "sg:classifiers":[
        {
            "category":"Wholesale",
            "subcategory":"Fruits & Vegetables",
            "type":"Manufacturing & Wholesale Goods"
        }
    ],
    "sg:phone":"+1 705 753 0109",
    "sg:postcode":"P2B 2W3",
    "sg:province":"ON",
    "sg:tags":[
        "shipper"
    ],
    "wof:name":"Leisure Farm",
    "wof:placetype":"venue"
},
  "geometry": {"coordinates":[-79.93905599999999,46.349606],"type":"Point"}
}