{
  "type": "Feature",
  "properties": {
    "iso:country":"CA",
    "sg:address":"1716 Mattawa Ave",
    "sg:city":"Mississauga",
    "sg:classifiers":[
        {
            "category":"Manufacturing",
            "subcategory":"Metals",
            "type":"Manufacturing & Wholesale Goods"
        }
    ],
    "sg:phone":"+1 905 277 3790",
    "sg:postcode":"L4X 1K1",
    "sg:province":"ON",
    "sg:tags":[
        "stamping"
    ],
    "wof:name":"Terminal Tool CO",
    "wof:placetype":"venue"
},
  "geometry": {"coordinates":[-79.5721588135,43.6135292053],"type":"Point"}
}