{
  "type": "Feature",
  "properties": {
    "iso:country":"CA",
    "sg:city":"Brampton",
    "sg:classifiers":[
        {
            "category":"Health Services",
            "subcategory":"Optometrist",
            "type":"Services"
        }
    ],
    "sg:phone":"+1 905 453 3503",
    "sg:postcode":"L6Y 2E4",
    "sg:province":"ON",
    "wof:name":"Mc Veigh-Regier, Jana OD",
    "wof:placetype":"venue"
},
  "geometry": {"coordinates":[-79.7621688843,43.6835899353],"type":"Point"}
}