{
  "type": "Feature",
  "properties": {
    "addr:full":"Brockville ON K6V 1A8",
    "addr:postcode":"k6v 1a8",
    "iso:country":"CA",
    "sg:city":"Brockville",
    "sg:classifiers":[
        {
            "category":"Insurance",
            "subcategory":"Insurance Agent",
            "type":"Services"
        }
    ],
    "sg:phone":"+1 613 345 5617",
    "sg:postcode":"K6V 1A8",
    "sg:province":"ON",
    "sg:tags":[
        "adjuster"
    ],
    "wof:name":"Cunningham Lindsey Canada Ltd",
    "wof:placetype":"venue"
},
  "geometry": {"coordinates":[-75.6812667847,44.5913162231],"type":"Point"}
}