{
  "type": "Feature",
  "properties": {
    "addr:full":"350 Rue Ontario E Montreal QC H2X 1H8",
    "addr:housenumber":"350",
    "addr:postcode":"h2x 1h8",
    "addr:street":"Rue Ontario E",
    "iso:country":"CA",
    "sg:address":"350 Rue Ontario E",
    "sg:city":"Montreal",
    "sg:classifiers":[
        {
            "category":"Food & Beverages",
            "subcategory":"Groceries & Convenience Stores",
            "type":"Retail Goods"
        }
    ],
    "sg:phone":"+1 514 842 4847",
    "sg:postcode":"H2X 1H8",
    "sg:province":"QC",
    "wof:name":"Depanneur Polash",
    "wof:placetype":"venue"
},
  "geometry": {"coordinates":[-73.565269,45.515556],"type":"Point"}
}