{
  "type": "Feature",
  "properties": {
    "addr:full":"787 Rue Notre-Dame Saint-Remi QC J0L 2L0",
    "addr:housenumber":"787",
    "addr:postcode":"j0l 2l0",
    "addr:street":"Rue Notre-Dame Saint-Remi",
    "iso:country":"CA",
    "sg:address":"787 Rue Notre-Dame",
    "sg:city":"Saint-Remi",
    "sg:classifiers":[
        {
            "category":"Restaurant",
            "type":"Food & Drink"
        }
    ],
    "sg:phone":"+1 450 454 5848",
    "sg:postcode":"J0L 2L0",
    "sg:province":"QC",
    "sg:tags":[
        "parlor",
        "ice",
        "cream"
    ],
    "wof:name":"Glaces Michael",
    "wof:placetype":"venue"
},
  "geometry": {"coordinates":[-73.6175079346,45.2606163025],"type":"Point"}
}