{
  "type": "Feature",
  "properties": {
    "addr:full":"4749 Park St Niagara Falls ON L2E 2P7",
    "addr:housenumber":"4749",
    "addr:postcode":"l2e 2p7",
    "addr:street":"Park St",
    "iso:country":"CA",
    "sg:address":"4749 Park St",
    "sg:city":"Niagara Falls",
    "sg:classifiers":[
        {
            "category":"Wholesale",
            "subcategory":"Home Furnishings",
            "type":"Manufacturing & Wholesale Goods"
        }
    ],
    "sg:phone":"+1 905 374 3121",
    "sg:postcode":"L2E 2P7",
    "sg:province":"ON",
    "sg:tags":[
        "linen"
    ],
    "wof:name":"Cantex Distribution Inc",
    "wof:placetype":"venue"
},
  "geometry": {"coordinates":[-79.071861,43.107723],"type":"Point"}
}