{
  "type": "Feature",
  "properties": {
    "addr:full":"Montreal QC H3B 4R4",
    "addr:postcode":"h3b 4r4",
    "iso:country":"CA",
    "sg:city":"Montreal",
    "sg:classifiers":[
        {
            "category":"Professional",
            "subcategory":"Management & Consulting",
            "type":"Services"
        }
    ],
    "sg:phone":"+1 514 282 1818",
    "sg:postcode":"H3B 4R4",
    "sg:province":"QC",
    "sg:tags":[
        "consultant",
        "business"
    ],
    "wof:name":"Roland Farley & Cie Inc",
    "wof:placetype":"venue"
},
  "geometry": {"coordinates":[-73.56797,45.50182],"type":"Point"}
}