{
  "type": "Feature",
  "properties": {
    "addr:full":"109 Main St S Newmarket ON L3Y 3Y8",
    "addr:housenumber":"109",
    "addr:postcode":"l3y 3y8",
    "addr:street":"Main St S",
    "iso:country":"CA",
    "sg:address":"109 Main St S",
    "sg:city":"Newmarket",
    "sg:classifiers":[
        {
            "category":"Health Services",
            "subcategory":"Chiropractor",
            "type":"Services"
        }
    ],
    "sg:phone":"+1 905 895 1299",
    "sg:postcode":"L3Y 3Y8",
    "sg:province":"ON",
    "wof:name":"Ruegg, Richard P DC",
    "wof:placetype":"venue"
},
  "geometry": {"coordinates":[-79.45896148680001,44.0556335449],"type":"Point"}
}