{
  "type": "Feature",
  "properties": {
    "addr:full":"Saint-Narcisse-DE-Rimouski QC G0K 1S0",
    "addr:postcode":"g0k 1s0",
    "iso:country":"CA",
    "sg:city":"Saint-Narcisse-DE-Rimouski",
    "sg:classifiers":[
        {
            "category":"Building & Trades",
            "subcategory":"Construction",
            "type":"Services"
        }
    ],
    "sg:phone":"+1 418 735 2202",
    "sg:postcode":"G0K 1S0",
    "sg:province":"QC",
    "sg:tags":[
        "contractor"
    ],
    "wof:name":"Belanger, Real",
    "wof:placetype":"venue"
},
  "geometry": {"coordinates":[-68.4303894043,48.2768630981],"type":"Point"}
}