{
  "type": "Feature",
  "properties": {
    "addr:full":"223 Av Frontenac Pointe-Claire QC H9R 4Z7",
    "addr:postcode":"h9r 4z7",
    "addr:street":"223 Av Frontenac",
    "iso:country":"CA",
    "sg:address":"223 Av Frontenac",
    "sg:city":"Pointe-Claire",
    "sg:classifiers":[
        {
            "category":"Personal",
            "subcategory":"Beauty Salon",
            "type":"Services"
        }
    ],
    "sg:phone":"+1 514 694 1223",
    "sg:postcode":"H9R 4Z7",
    "sg:province":"QC",
    "sg:tags":[
        "day"
    ],
    "wof:name":"Spa",
    "wof:placetype":"venue"
},
  "geometry": {"coordinates":[-73.8277664185,45.46900177],"type":"Point"}
}