{
  "type": "Feature",
  "properties": {
    "iso:country":"CA",
    "sg:address":"2800 Rang Du Ruisseau",
    "sg:city":"Sainte-Elisabeth",
    "sg:classifiers":[
        {
            "category":"Building & Trades",
            "subcategory":"Construction",
            "type":"Services"
        }
    ],
    "sg:phone":"+1 450 753 5710",
    "sg:postcode":"J0K 2J0",
    "sg:province":"QC",
    "sg:tags":[
        "maker",
        "cabinet"
    ],
    "wof:name":"Ebenisterie Quepav",
    "wof:placetype":"venue"
},
  "geometry": {"coordinates":[-73.372718811,46.0994491577],"type":"Point"}
}