{
  "type": "Feature",
  "properties": {
    "addr:full":"465 Boul Saint-Germain Rimouski QC G5L 3P2",
    "addr:housenumber":"465",
    "addr:postcode":"g5l 3p2",
    "addr:street":"Boul Saint-Germain",
    "iso:country":"CA",
    "sg:address":"465 Boul Saint-Germain",
    "sg:city":"Rimouski",
    "sg:classifiers":[
        {
            "category":"Food & Beverages",
            "subcategory":"Groceries & Convenience Stores",
            "type":"Retail Goods"
        }
    ],
    "sg:phone":"+1 418 722 0722",
    "sg:postcode":"G5L 3P2",
    "sg:province":"QC",
    "sg:tags":[
        "grocer"
    ],
    "wof:name":"Marche Metro Sirois",
    "wof:placetype":"venue"
},
  "geometry": {"coordinates":[-68.553894,48.439384],"type":"Point"}
}