{
  "type": "Feature",
  "properties": {
    "iso:country":"CA",
    "sg:address":"2713 Murray St",
    "sg:city":"Port Moody",
    "sg:classifiers":[
        {
            "category":"Building & Trades",
            "subcategory":"Electrical",
            "type":"Services"
        }
    ],
    "sg:phone":"+1 604 931 6173",
    "sg:postcode":"V3H 1X1",
    "sg:province":"BC",
    "sg:tags":[
        "electric",
        "contractor"
    ],
    "wof:name":"Cel Electric Ltd",
    "wof:placetype":"venue"
},
  "geometry": {"coordinates":[-122.854317,49.278824],"type":"Point"}
}