{
  "type": "Feature",
  "properties": {
    "addr:full":"2713 Murray St Port Moody BC V3H 1X1",
    "addr:housenumber":"2713",
    "addr:postcode":"v3h 1x1",
    "addr:street":"Murray St",
    "iso:country":"CA",
    "sg:address":"2713 Murray St",
    "sg:city":"Port Moody",
    "sg:classifiers":[
        {
            "category":"Building & Trades",
            "subcategory":"Electrical",
            "type":"Services"
        }
    ],
    "sg:phone":"+1 604 931 6173",
    "sg:postcode":"V3H 1X1",
    "sg:province":"BC",
    "sg:tags":[
        "electric",
        "contractor"
    ],
    "wof:name":"Cel Electric Ltd",
    "wof:placetype":"venue"
},
  "geometry": {"coordinates":[-122.85431699999999,49.278824],"type":"Point"}
}