{
  "type": "Feature",
  "properties": {
    "addr:full":"2511 Wilcox Terr Victoria BC V8Z 5R7",
    "addr:housenumber":"2511",
    "addr:postcode":"v8z 5r7",
    "addr:street":"Wilcox Terr",
    "iso:country":"CA",
    "sg:address":"2511 Wilcox Terr",
    "sg:city":"Victoria",
    "sg:classifiers":[
        {
            "category":"Shopping",
            "type":"Retail Goods"
        }
    ],
    "sg:phone":"+1 250 652 6128",
    "sg:postcode":"V8Z 5R7",
    "sg:province":"BC",
    "sg:tags":[
        "cosmetic",
        "perfume"
    ],
    "wof:name":"Mary Kay Cosmetics",
    "wof:placetype":"venue"
},
  "geometry": {"coordinates":[-123.364517212,48.428314209],"type":"Point"}
}