{
  "type": "Feature",
  "properties": {
    "addr:full":"2 Patton Ave Sedgewick AB T0B 4C0",
    "addr:housenumber":"2",
    "addr:postcode":"t0b 4c0",
    "addr:street":"Patton Ave",
    "iso:country":"CA",
    "sg:address":"2 Patton Ave",
    "sg:city":"Sedgewick",
    "sg:classifiers":[
        {
            "category":"Mining & Drilling",
            "type":"Manufacturing & Wholesale Goods"
        }
    ],
    "sg:phone":"+1 780 384 3777",
    "sg:postcode":"T0B 4C0",
    "sg:province":"AB",
    "sg:tags":[
        "field",
        "oil"
    ],
    "wof:name":"Accell Well Svc Ltd",
    "wof:placetype":"venue"
},
  "geometry": {"coordinates":[-111.69705999999999,52.776264],"type":"Point"}
}