{
  "type": "Feature",
  "properties": {
    "addr:full":"450 Dundas St Cambridge ON N1R 5R4",
    "addr:housenumber":"450",
    "addr:postcode":"n1r 5r4",
    "addr:street":"Dundas St",
    "iso:country":"CA",
    "sg:address":"450 Dundas St",
    "sg:city":"Cambridge",
    "sg:classifiers":[
        {
            "category":"Shopping",
            "type":"Retail Goods"
        }
    ],
    "sg:phone":"+1 519 740 0190",
    "sg:postcode":"N1R 5R4",
    "sg:province":"ON",
    "sg:tags":[
        "monument"
    ],
    "wof:name":"Dumfries Superior Memorials",
    "wof:placetype":"venue"
},
  "geometry": {"coordinates":[-80.3138580322,43.3702812195],"type":"Point"}
}