{
  "type": "Feature",
  "properties": {
    "addr:full":"65 Rue Principale Saint-Anselme QC G0R 2N0",
    "addr:housenumber":"65",
    "addr:postcode":"g0r 2n0",
    "addr:street":"Rue Principale",
    "iso:country":"CA",
    "sg:address":"65 Rue Principale",
    "sg:city":"Saint-Anselme",
    "sg:classifiers":[
        {
            "category":"Health Services",
            "subcategory":"Nursing And Care Facility",
            "type":"Services"
        }
    ],
    "sg:phone":"+1 418 885 8338",
    "sg:postcode":"G0R 2N0",
    "sg:province":"QC",
    "sg:tags":[
        "home",
        "retirement",
        "community"
    ],
    "wof:name":"Residence Le Royal Senc",
    "wof:placetype":"venue"
},
  "geometry": {"coordinates":[-70.9744720459,46.6303596497],"type":"Point"}
}