{
  "type": "Feature",
  "properties": {
    "addr:full":"SW 77 11 7W Edwin MB R0H 0G0",
    "addr:housenumber":"11 7w",
    "addr:postcode":"r0h 0g0",
    "addr:street":"Sw 77",
    "iso:country":"CA",
    "sg:address":"SW 77 11 7W",
    "sg:city":"Edwin",
    "sg:classifiers":[
        {
            "category":"Education",
            "subcategory":"School",
            "type":"Public Place"
        }
    ],
    "sg:phone":"+1 204 252 2568",
    "sg:postcode":"R0H 0G0",
    "sg:province":"MB",
    "wof:name":"Good Hope Colony School",
    "wof:placetype":"venue"
},
  "geometry": {"coordinates":[-98.514565,49.893906],"type":"Point"}
}