{
  "type": "Feature",
  "properties": {
    "addr:full":"3250 Bloor St W #705 Etobicoke ON M8X 2X9",
    "addr:housenumber":"3250",
    "addr:postcode":"m8x 2x9",
    "addr:street":"Bloor St W # 705",
    "iso:country":"CA",
    "sg:address":"3250 Bloor St W #705",
    "sg:city":"Etobicoke",
    "sg:classifiers":[
        {
            "category":"Banks & Credit Unions",
            "subcategory":"Investment Brokerage",
            "type":"Services"
        }
    ],
    "sg:phone":"+1 416 231 6766",
    "sg:postcode":"M8X 2X9",
    "sg:province":"ON",
    "wof:name":"Rbc Dominion Securities Inc",
    "wof:placetype":"venue"
},
  "geometry": {"coordinates":[-79.520264,43.645485],"type":"Point"}
}