{
  "type": "Feature",
  "properties": {
    "iso:country":"CA",
    "sg:address":"Provincial Rd 203 & 210",
    "sg:city":"Woodridge",
    "sg:classifiers":[
        {
            "category":"Restaurant",
            "type":"Food & Drink"
        }
    ],
    "sg:phone":"+1 204 429 2178",
    "sg:postcode":"R0A 2N0",
    "sg:province":"MB",
    "wof:name":"Woodridge Inn",
    "wof:placetype":"venue"
},
  "geometry": {"coordinates":[-96.1541671753,49.2817802429],"type":"Point"}
}