{
  "type": "Feature",
  "properties": {
    "addr:full":"Trois-Rivieres QC G9A 6A7",
    "addr:postcode":"g9a 6a7",
    "iso:country":"CA",
    "sg:city":"Trois-Rivieres",
    "sg:classifiers":[
        {
            "category":"Government",
            "subcategory":"Office",
            "type":"Public Place"
        }
    ],
    "sg:phone":"+1 819 371 5207",
    "sg:postcode":"G9A 6A7",
    "sg:province":"QC",
    "wof:name":"Canada Agriculture",
    "wof:placetype":"venue"
},
  "geometry": {"coordinates":[-72.5391082764,46.3414726257],"type":"Point"}
}