{
  "type": "Feature",
  "properties": {
    "addr:full":"23 Kent St S Simcoe ON N3Y 2X7",
    "addr:housenumber":"23",
    "addr:postcode":"n3y 2x7",
    "addr:street":"Kent St S",
    "iso:country":"CA",
    "sg:address":"23 Kent St S",
    "sg:city":"Simcoe",
    "sg:classifiers":[
        {
            "category":"Food & Beverages",
            "subcategory":"Specialty",
            "type":"Retail Goods"
        }
    ],
    "sg:phone":"+1 519 428 2077",
    "sg:postcode":"N3Y 2X7",
    "sg:province":"ON",
    "sg:tags":[
        "health",
        "diet"
    ],
    "wof:name":"Simcoe Natural Foods",
    "wof:placetype":"venue"
},
  "geometry": {"coordinates":[-80.305115,42.836468],"type":"Point"}
}