{
  "type": "Feature",
  "properties": {
    "iso:country":"CA",
    "sg:city":"Edmonton",
    "sg:classifiers":[
        {
            "category":"Wholesale",
            "subcategory":"Electrical",
            "type":"Manufacturing & Wholesale Goods"
        }
    ],
    "sg:phone":"+1 780 437 4266",
    "sg:postcode":"T6E 6M3",
    "sg:province":"AB",
    "sg:tags":[
        "control",
        "cleaners",
        "security",
        "vacuum"
    ],
    "wof:name":"Readco Industries Ltd",
    "wof:placetype":"venue"
},
  "geometry": {"coordinates":[-113.48194122300001,53.4743804932],"type":"Point"}
}