{
  "type": "Feature",
  "properties": {
    "addr:full":"Rose St Mortlach SK S0H 3E0",
    "addr:postcode":"s0h 3e0",
    "addr:street":"Rose St",
    "iso:country":"CA",
    "sg:address":"Rose St",
    "sg:city":"Mortlach",
    "sg:classifiers":[
        {
            "category":"Government",
            "subcategory":"Office",
            "type":"Public Place"
        }
    ],
    "sg:phone":"+1 306 355 2233",
    "sg:postcode":"S0H 3E0",
    "sg:province":"SK",
    "sg:tags":[
        "municipality"
    ],
    "wof:name":"R M of Wheatlands 163",
    "wof:placetype":"venue"
},
  "geometry": {"coordinates":[-106.066795,50.459919],"type":"Point"}
}