{
  "type": "Feature",
  "properties": {
    "addr:full":"210 West Rd Leroy SK S0K 2P0",
    "addr:housenumber":"210",
    "addr:postcode":"s0k 2p0",
    "addr:street":"West Rd",
    "iso:country":"CA",
    "sg:address":"210 West Rd",
    "sg:city":"Leroy",
    "sg:classifiers":[
        {
            "category":"Personal",
            "subcategory":"Beauty Salon",
            "type":"Services"
        }
    ],
    "sg:phone":"+1 306 286 3651",
    "sg:postcode":"S0K 2P0",
    "sg:province":"SK",
    "wof:name":"Olive's Style Shop",
    "wof:placetype":"venue"
},
  "geometry": {"coordinates":[-104.74407196,52.003364563],"type":"Point"}
}