{
  "type": "Feature",
  "properties": {
    "iso:country":"CA",
    "sg:address":"2028 Maire-Anne",
    "sg:city":"Val-David",
    "sg:classifiers":[
        {
            "category":"Building & Trades",
            "subcategory":"Landscaping Services",
            "type":"Services"
        }
    ],
    "sg:phone":"+1 819 322 1059",
    "sg:postcode":"J0T 2N0",
    "sg:province":"QC",
    "sg:tags":[
        "tree"
    ],
    "wof:name":"Legautl Deboisement",
    "wof:placetype":"venue"
},
  "geometry": {"coordinates":[-74.21593475340001,46.0173301697],"type":"Point"}
}