{
  "type": "Feature",
  "properties": {
    "addr:full":"440 Mcdonald St Regina SK S4N 6E1",
    "addr:housenumber":"440",
    "addr:postcode":"s4n 6e1",
    "addr:street":"Mcdonald St",
    "iso:country":"CA",
    "sg:address":"440 Mcdonald St",
    "sg:city":"Regina",
    "sg:classifiers":[
        {
            "category":"Restaurant",
            "type":"Food & Drink"
        }
    ],
    "sg:phone":"+1 306 721 2323",
    "sg:postcode":"S4N 6E1",
    "sg:province":"SK",
    "wof:name":"Mr Sub",
    "wof:placetype":"venue"
},
  "geometry": {"coordinates":[-104.582176209,50.4723014832],"type":"Point"}
}