{
  "type": "Feature",
  "properties": {
    "addr:full":"North York ON M3J 3H7",
    "addr:postcode":"m3j 3h7",
    "iso:country":"CA",
    "sg:city":"North York",
    "sg:classifiers":[
        {
            "category":"Professional",
            "subcategory":"Lawyer & Legal Services",
            "type":"Services"
        }
    ],
    "sg:phone":"+1 416 667 9393",
    "sg:postcode":"M3J 3H7",
    "sg:province":"ON",
    "sg:tags":[
        "attorney"
    ],
    "wof:name":"Stone, R Richard",
    "wof:placetype":"venue"
},
  "geometry": {"coordinates":[-79.4763717651,43.7668800354],"type":"Point"}
}