{
  "type": "Feature",
  "properties": {
    "iso:country":"CA",
    "sg:city":"Whistler",
    "sg:classifiers":[
        {
            "category":"Retail",
            "subcategory":"Repair Shop",
            "type":"Services"
        }
    ],
    "sg:phone":"+1 604 938 8817",
    "sg:postcode":"V0N 1B1",
    "sg:province":"BC",
    "sg:tags":[
        "radio",
        "television",
        "electronic",
        "equipment"
    ],
    "wof:name":"Whistler Tv Svc",
    "wof:placetype":"venue"
},
  "geometry": {"coordinates":[-123.039085388,50.0887718201],"type":"Point"}
}