{
  "type": "Feature",
  "properties": {
    "addr:full":"Saskatoon SK S7M 0W7",
    "addr:postcode":"s7m 0w7",
    "iso:country":"CA",
    "sg:city":"Saskatoon",
    "sg:classifiers":[
        {
            "category":"Recreation",
            "type":"Entertainment"
        }
    ],
    "sg:phone":"+1 306 934 1565",
    "sg:postcode":"S7M 0W7",
    "sg:province":"SK",
    "sg:tags":[
        "parlor",
        "billiard"
    ],
    "wof:name":"Royal Billiards",
    "wof:placetype":"venue"
},
  "geometry": {"coordinates":[-106.670677,52.126038],"type":"Point"}
}