{
  "type": "Feature",
  "properties": {
    "iso:country":"CA",
    "sg:city":"Brampton",
    "sg:classifiers":[
        {
            "category":"Wholesale",
            "subcategory":"Auto Parts",
            "type":"Manufacturing & Wholesale Goods"
        }
    ],
    "sg:phone":"+1 905 451 4611",
    "sg:postcode":"L7A 1A2",
    "sg:province":"ON",
    "sg:tags":[
        "automobile",
        "supply"
    ],
    "wof:name":"Marklyn CO",
    "wof:placetype":"venue"
},
  "geometry": {"coordinates":[-79.652237,43.766663],"type":"Point"}
}