{
  "type": "Feature",
  "properties": {
    "addr:full":"55 Rue Principale Lameque NB E8T 1N1",
    "addr:housenumber":"55",
    "addr:postcode":"e8t 1n1",
    "addr:street":"Rue Principale",
    "iso:country":"CA",
    "sg:address":"55 Rue Principale",
    "sg:city":"Lameque",
    "sg:classifiers":[
        {
            "category":"Personal",
            "subcategory":"Beauty Salon",
            "type":"Services"
        }
    ],
    "sg:phone":"+1 506 344 2547",
    "sg:postcode":"E8T 1N1",
    "sg:province":"NB",
    "wof:name":"Beaute Francaise",
    "wof:placetype":"venue"
},
  "geometry": {"coordinates":[-64.647217,47.793392],"type":"Point"}
}