{
  "type": "Feature",
  "properties": {
    "iso:country":"CA",
    "sg:city":"Windsor",
    "sg:classifiers":[
        {
            "category":"Education",
            "subcategory":"Special Training",
            "type":"Public Place"
        }
    ],
    "sg:phone":"+1 519 253 1232",
    "sg:postcode":"N9A 6V2",
    "sg:province":"ON",
    "sg:tags":[
        "traffic",
        "representation",
        "law",
        "paralegal"
    ],
    "wof:name":"A Pointts Traffic Ticket Spec",
    "wof:placetype":"venue"
},
  "geometry": {"coordinates":[-83.0374755859,42.3182945251],"type":"Point"}
}