{
  "type": "Feature",
  "properties": {
    "addr:full":"Thunder Bay ON P7B 6M4",
    "addr:postcode":"p7b 6m4",
    "iso:country":"CA",
    "sg:city":"Thunder Bay",
    "sg:classifiers":[
        {
            "category":"Insurance",
            "subcategory":"Insurance Agent",
            "type":"Services"
        }
    ],
    "sg:phone":"+1 807 346 7450",
    "sg:postcode":"P7B 6M4",
    "sg:province":"ON",
    "wof:name":"Aon Reed Stenhouse Inc",
    "wof:placetype":"venue"
},
  "geometry": {"coordinates":[-89.26223,48.409657],"type":"Point"}
}