{
  "type": "Feature",
  "properties": {
    "addr:full":"Calgary AB T2M 3N3",
    "addr:postcode":"t2m 3n3",
    "iso:country":"CA",
    "sg:city":"Calgary",
    "sg:classifiers":[
        {
            "category":"Health Services",
            "subcategory":"Doctor",
            "type":"Services"
        }
    ],
    "sg:phone":"+1 403 220 9353",
    "sg:postcode":"T2M 3N3",
    "sg:province":"AB",
    "sg:tags":[
        "physician",
        "surgeon"
    ],
    "wof:name":"Vein Treatment Ctr",
    "wof:placetype":"venue"
},
  "geometry": {"coordinates":[-114.10807,51.065346],"type":"Point"}
}