{
  "type": "Feature",
  "properties": {
    "addr:full":"3rd St Chaplin SK S0H 0V0",
    "addr:postcode":"s0h 0v0",
    "addr:street":"3Rd St",
    "iso:country":"CA",
    "sg:address":"3rd St",
    "sg:city":"Chaplin",
    "sg:classifiers":[
        {
            "category":"Education",
            "subcategory":"Library",
            "type":"Public Place"
        }
    ],
    "sg:phone":"+1 306 395 2524",
    "sg:postcode":"S0H 0V0",
    "sg:province":"SK",
    "wof:name":"Chaplin Library",
    "wof:placetype":"venue"
},
  "geometry": {"coordinates":[-106.656593323,50.4620513916],"type":"Point"}
}