{
  "type": "Feature",
  "properties": {
    "addr:full":"226 Ritson Ave Quesnel BC V2J 1B1",
    "addr:housenumber":"226",
    "addr:postcode":"v2j 1b1",
    "addr:street":"Ritson Ave",
    "iso:country":"CA",
    "sg:address":"226 Ritson Ave",
    "sg:city":"Quesnel",
    "sg:classifiers":[
        {
            "category":"Real Estate",
            "subcategory":"Real Estate Operator",
            "type":"Services"
        }
    ],
    "sg:phone":"+1 250 992 2670",
    "sg:postcode":"V2J 1B1",
    "sg:province":"BC",
    "sg:tags":[
        "apartment"
    ],
    "wof:name":"Charlotte Manor",
    "wof:placetype":"venue"
},
  "geometry": {"coordinates":[-122.50701100000001,52.96891],"type":"Point"}
}