{
  "type": "Feature",
  "properties": {
    "addr:full":"808 Larch Pl Canmore AB T1W 1S4",
    "addr:housenumber":"808",
    "addr:postcode":"t1w 1s4",
    "addr:street":"Larch Pl",
    "iso:country":"CA",
    "sg:address":"808 Larch Pl",
    "sg:city":"Canmore",
    "sg:classifiers":[
        {
            "category":"Travel",
            "subcategory":"Travel Agent",
            "type":"Entertainment"
        }
    ],
    "sg:phone":"+1 403 678 4338",
    "sg:postcode":"T1W 1S4",
    "sg:province":"AB",
    "sg:tags":[
        "agency",
        "bureau"
    ],
    "wof:name":"Mountain Adventure Canada Ltd",
    "wof:placetype":"venue"
},
  "geometry": {"coordinates":[-115.375748,51.102638],"type":"Point"}
}