{
  "type": "Feature",
  "properties": {
    "addr:full":"1540 Gamble Pl Winnipeg MB R3T 1N6",
    "addr:housenumber":"1540",
    "addr:postcode":"r3t 1n6",
    "addr:street":"Gamble Pl",
    "iso:country":"CA",
    "sg:address":"1540 Gamble Pl",
    "sg:city":"Winnipeg",
    "sg:classifiers":[
        {
            "category":"Building & Trades",
            "subcategory":"Construction",
            "type":"Services"
        }
    ],
    "sg:phone":"+1 204 949 8900",
    "sg:postcode":"R3T 1N6",
    "sg:province":"MB",
    "sg:tags":[
        "general",
        "contractor"
    ],
    "wof:name":"Pcl Constructors Canada Inc",
    "wof:placetype":"venue"
},
  "geometry": {"coordinates":[-97.17449999999999,49.833904],"type":"Point"}
}