{
  "type": "Feature",
  "properties": {
    "iso:country":"CA",
    "sg:address":"11 1Re Rue E",
    "sg:city":"Saint-Mathieu-DE-Laprairie",
    "sg:classifiers":[
        {
            "category":"Building & Trades",
            "subcategory":"Construction",
            "type":"Services"
        }
    ],
    "sg:phone":"+1 450 659 6885",
    "sg:postcode":"J0L 2H0",
    "sg:province":"QC",
    "sg:tags":[
        "resurfacing",
        "laying",
        "refinishing",
        "floor"
    ],
    "wof:name":"Plancher Sos Enr",
    "wof:placetype":"venue"
},
  "geometry": {"coordinates":[-73.48807499999999,45.417454],"type":"Point"}
}