{
  "type": "Feature",
  "properties": {
    "addr:full":"11 1Re Rue E Saint-Mathieu-DE-Laprairie QC J0L 2H0",
    "addr:housenumber":"11",
    "addr:postcode":"j0l 2h0",
    "addr:street":"1Re Rue E Saint-Mathieu-De-Laprairie",
    "iso:country":"CA",
    "sg:address":"11 1Re Rue E",
    "sg:city":"Saint-Mathieu-DE-Laprairie",
    "sg:classifiers":[
        {
            "category":"Building & Trades",
            "subcategory":"Construction",
            "type":"Services"
        }
    ],
    "sg:phone":"+1 450 659 6885",
    "sg:postcode":"J0L 2H0",
    "sg:province":"QC",
    "sg:tags":[
        "resurfacing",
        "laying",
        "refinishing",
        "floor"
    ],
    "wof:name":"Plancher Sos Enr",
    "wof:placetype":"venue"
},
  "geometry": {"coordinates":[-73.48807499999999,45.417454],"type":"Point"}
}