{
  "type": "Feature",
  "properties": {
    "addr:full":"Harriston ON N0G 1Z0",
    "addr:postcode":"n0g 1z0",
    "iso:country":"CA",
    "sg:city":"Harriston",
    "sg:classifiers":[
        {
            "category":"Manufacturing",
            "subcategory":"Chemicals & Compounds",
            "type":"Manufacturing & Wholesale Goods"
        }
    ],
    "sg:phone":"+1 519 338 2015",
    "sg:postcode":"N0G 1Z0",
    "sg:province":"ON",
    "sg:tags":[
        "fertilizer"
    ],
    "wof:name":"Cargill Fertilizer",
    "wof:placetype":"venue"
},
  "geometry": {"coordinates":[-80.82575199999999,43.889538],"type":"Point"}
}