{
  "type": "Feature",
  "properties": {
    "addr:full":"48 Rue DE L'Eglise Nord Lacolle QC J0J 1J0",
    "addr:housenumber":"48",
    "addr:postcode":"j0j 1j0",
    "addr:street":"Rue De L'Eglise Nord",
    "iso:country":"CA",
    "sg:address":"48 Rue DE L'Eglise Nord",
    "sg:city":"Lacolle",
    "sg:classifiers":[
        {
            "category":"Retail",
            "subcategory":"Funeral Services",
            "type":"Services"
        }
    ],
    "sg:phone":"+1 450 246 3988",
    "sg:postcode":"J0J 1J0",
    "sg:province":"QC",
    "sg:tags":[
        "director"
    ],
    "wof:name":"Salon Funeraire Gilles Serre",
    "wof:placetype":"venue"
},
  "geometry": {"coordinates":[-73.3729019165,45.0842971802],"type":"Point"}
}