{
  "type": "Feature",
  "properties": {
    "addr:full":"1256 Parkinson Rd Woodstock ON N4S 7W3",
    "addr:housenumber":"1256",
    "addr:postcode":"n4s 7w3",
    "addr:street":"Parkinson Rd",
    "iso:country":"CA",
    "sg:address":"1256 Parkinson Rd",
    "sg:city":"Woodstock",
    "sg:classifiers":[
        {
            "category":"Manufacturing",
            "subcategory":"Wood Products",
            "type":"Manufacturing & Wholesale Goods"
        }
    ],
    "sg:phone":"+1 519 537 3466",
    "sg:postcode":"N4S 7W3",
    "sg:province":"ON",
    "sg:tags":[
        "pallet",
        "skid"
    ],
    "wof:name":"Huron Pallet & Box CO",
    "wof:placetype":"venue"
},
  "geometry": {"coordinates":[-80.756561,43.130112],"type":"Point"}
}