{
  "type": "Feature",
  "properties": {
    "addr:full":"1722 Second Ave Trail BC V1R 1M7",
    "addr:housenumber":"1722",
    "addr:postcode":"bc v1r 1m7",
    "addr:street":"Second Ave Trail",
    "iso:country":"CA",
    "sg:address":"1722 Second Ave",
    "sg:city":"Trail",
    "sg:classifiers":[
        {
            "category":"Retail",
            "subcategory":"Veterinary Services",
            "type":"Services"
        }
    ],
    "sg:phone":"+1 250 364 0422",
    "sg:postcode":"V1R 1M7",
    "sg:province":"BC",
    "sg:tags":[
        "veterinarian"
    ],
    "wof:name":"Gresley-Jones Veterinary Svc",
    "wof:placetype":"venue"
},
  "geometry": {"coordinates":[-117.6996,49.096432],"type":"Point"}
}