{
  "type": "Feature",
  "properties": {
    "addr:full":"1625 Allee Du Marche Saint-Hyacinthe QC J2S 8E8",
    "addr:housenumber":"1625",
    "addr:postcode":"j2s 8e8",
    "addr:street":"Allee Du Marche",
    "iso:country":"CA",
    "sg:address":"1625 Allee Du Marche",
    "sg:city":"Saint-Hyacinthe",
    "sg:classifiers":[
        {
            "category":"Personal",
            "subcategory":"Beauty Salon",
            "type":"Services"
        }
    ],
    "sg:phone":"+1 450 773 5444",
    "sg:postcode":"J2S 8E8",
    "sg:province":"QC",
    "wof:name":"Salon Stop Coiffure Enr",
    "wof:placetype":"venue"
},
  "geometry": {"coordinates":[-72.945717,45.623867],"type":"Point"}
}