{
  "type": "Feature",
  "properties": {
    "iso:country":"CA",
    "sg:address":"2835 Boul Lemire",
    "sg:city":"Drummondville",
    "sg:classifiers":[
        {
            "category":"Food & Beverages",
            "subcategory":"Groceries & Convenience Stores",
            "type":"Retail Goods"
        }
    ],
    "sg:phone":"+1 819 474 3497",
    "sg:postcode":"J2B 6Y8",
    "sg:province":"QC",
    "sg:tags":[
        "grocer"
    ],
    "wof:name":"Couche-Tard",
    "wof:placetype":"venue"
},
  "geometry": {"coordinates":[-72.4890136719,45.8585472107],"type":"Point"}
}