{
  "type": "Feature",
  "properties": {
    "addr:full":"120 5th Ave Kamloops BC V2C 3P8",
    "addr:housenumber":"120",
    "addr:postcode":"bc v2c 3p8",
    "addr:street":"5Th Ave",
    "iso:country":"CA",
    "sg:address":"120 5th Ave",
    "sg:city":"Kamloops",
    "sg:classifiers":[
        {
            "category":"Restaurant",
            "type":"Food & Drink"
        }
    ],
    "sg:phone":"+1 250 851 8651",
    "sg:postcode":"V2C 3P8",
    "sg:province":"BC",
    "sg:tags":[
        "grocer"
    ],
    "wof:name":"Uptown Ag Foods",
    "wof:placetype":"venue"
},
  "geometry": {"coordinates":[-120.329826,50.676456],"type":"Point"}
}