{
  "type": "Feature",
  "properties": {
    "addr:full":"1125 Rue Principale Saint-Agapit QC G0S 1Z0",
    "addr:housenumber":"1125",
    "addr:postcode":"g0s 1z0",
    "addr:street":"Rue Principale",
    "iso:country":"CA",
    "sg:address":"1125 Rue Principale",
    "sg:city":"Saint-Agapit",
    "sg:classifiers":[
        {
            "category":"Shopping",
            "subcategory":"Pharmacy",
            "type":"Retail Goods"
        }
    ],
    "sg:phone":"+1 418 888 5555",
    "sg:postcode":"G0S 1Z0",
    "sg:province":"QC",
    "wof:name":"Pharmacie Yvan Duval",
    "wof:placetype":"venue"
},
  "geometry": {"coordinates":[-71.43293,46.562096],"type":"Point"}
}