{
  "type": "Feature",
  "properties": {
    "addr:full":"116 Dunkirk Rd St Catharines ON L2P 3H5",
    "addr:housenumber":"116",
    "addr:postcode":"l2p 3h5",
    "addr:street":"Dunkirk Rd",
    "iso:country":"CA",
    "sg:address":"116 Dunkirk Rd",
    "sg:city":"St Catharines",
    "sg:classifiers":[
        {
            "category":"Building & Trades",
            "subcategory":"Construction",
            "type":"Services"
        }
    ],
    "sg:phone":"+1 905 684 4791",
    "sg:postcode":"L2P 3H5",
    "sg:province":"ON",
    "sg:tags":[
        "roofing",
        "contractor"
    ],
    "wof:name":"Cedar Roof Ontario",
    "wof:placetype":"venue"
},
  "geometry": {"coordinates":[-79.21680499999999,43.16925],"type":"Point"}
}