{
  "type": "Feature",
  "properties": {
    "addr:full":"272 Rooth Rd Tracy NB E5L 1K4",
    "addr:housenumber":"272",
    "addr:postcode":"e5l 1k4",
    "addr:street":"Rooth Rd",
    "iso:country":"CA",
    "sg:address":"272 Rooth Rd",
    "sg:city":"Tracy",
    "sg:classifiers":[
        {
            "category":"Manufacturing",
            "subcategory":"Tools & Machinery",
            "type":"Manufacturing & Wholesale Goods"
        }
    ],
    "sg:phone":"+1 506 368 7750",
    "sg:postcode":"E5L 1K4",
    "sg:province":"NB",
    "sg:tags":[
        "alternator",
        "starter"
    ],
    "wof:name":"Edwards Rebuilding Svc",
    "wof:placetype":"venue"
},
  "geometry": {"coordinates":[-66.694397,45.677513],"type":"Point"}
}