{
  "type": "Feature",
  "properties": {
    "addr:full":"2 Wilkinson Rd Brampton ON L6T 4M3",
    "addr:housenumber":"2",
    "addr:postcode":"l6t 4m3",
    "addr:street":"Wilkinson Rd",
    "iso:country":"CA",
    "sg:address":"2 Wilkinson Rd",
    "sg:city":"Brampton",
    "sg:classifiers":[
        {
            "category":"Wholesale",
            "subcategory":"Machinery & Supplies",
            "type":"Manufacturing & Wholesale Goods"
        }
    ],
    "sg:phone":"+1 905 456 2226",
    "sg:postcode":"L6T 4M3",
    "sg:province":"ON",
    "sg:tags":[
        "bearing"
    ],
    "wof:name":"Toronto Bearings & Belting Ltd",
    "wof:placetype":"venue"
},
  "geometry": {"coordinates":[-79.704247,43.689716],"type":"Point"}
}