{
  "type": "Feature",
  "properties": {
    "addr:full":"4606 Greig Ave Terrace BC V8G 1M9",
    "addr:housenumber":"4606",
    "addr:postcode":"v8g 1m9",
    "addr:street":"Greig Ave",
    "iso:country":"CA",
    "sg:address":"4606 Greig Ave",
    "sg:city":"Terrace",
    "sg:classifiers":[
        {
            "category":"Restaurant",
            "type":"Food & Drink"
        }
    ],
    "sg:phone":"+1 250 635 6184",
    "sg:postcode":"V8G 1M9",
    "sg:province":"BC",
    "wof:name":"Shan Yan Restaurant Ltd",
    "wof:placetype":"venue"
},
  "geometry": {"coordinates":[-128.587097,54.515892],"type":"Point"}
}