{
  "type": "Feature",
  "properties": {
    "addr:full":"Roberval QC G8H 2J4",
    "addr:postcode":"g8h 2j4",
    "iso:country":"CA",
    "sg:city":"Roberval",
    "sg:classifiers":[
        {
            "category":"Health Services",
            "subcategory":"Doctor",
            "type":"Services"
        }
    ],
    "sg:phone":"+1 418 275 5522",
    "sg:postcode":"G8H 2J4",
    "sg:province":"QC",
    "sg:tags":[
        "clinic",
        "dentist"
    ],
    "wof:name":"Clinique Dentaire Nadeau",
    "wof:placetype":"venue"
},
  "geometry": {"coordinates":[-72.221992,48.514507],"type":"Point"}
}