{
  "type": "Feature",
  "properties": {
    "iso:country":"CA",
    "sg:city":"Warwick",
    "sg:classifiers":[
        {
            "category":"Professional",
            "subcategory":"Accounting & Tax Preparation",
            "type":"Services"
        }
    ],
    "sg:phone":"+1 819 358 3254",
    "sg:postcode":"J0A 1M0",
    "sg:province":"QC",
    "sg:tags":[
        "accountant"
    ],
    "wof:name":"Lemire Lemire",
    "wof:placetype":"venue"
},
  "geometry": {"coordinates":[-71.98453521730001,45.9431762695],"type":"Point"}
}