{
  "type": "Feature",
  "properties": {
    "addr:full":"37460 Hwy 62 Combermere ON K0J 1L0",
    "addr:housenumber":"37460",
    "addr:postcode":"k0j 1l0",
    "addr:street":"Hwy 62 Combermere",
    "iso:country":"CA",
    "sg:address":"37460 Hwy 62",
    "sg:city":"Combermere",
    "sg:classifiers":[
        {
            "category":"Shopping",
            "subcategory":"Gifts & Souvenirs",
            "type":"Retail Goods"
        }
    ],
    "sg:phone":"+1 613 756 0685",
    "sg:postcode":"K0J 1L0",
    "sg:province":"ON",
    "sg:tags":[
        "shop"
    ],
    "wof:name":"Candlesberry Cottage Gifts",
    "wof:placetype":"venue"
},
  "geometry": {"coordinates":[-77.61418151860001,45.3652114868],"type":"Point"}
}