{
  "type": "Feature",
  "properties": {
    "addr:full":"260 Moore St South Porcupine ON P0N 1H0",
    "addr:housenumber":"260",
    "addr:postcode":"p0n 1h0",
    "addr:street":"Moore St",
    "iso:country":"CA",
    "sg:address":"260 Moore St",
    "sg:city":"South Porcupine",
    "sg:classifiers":[
        {
            "category":"Building & Trades",
            "subcategory":"Construction",
            "type":"Services"
        }
    ],
    "sg:phone":"+1 705 235 2226",
    "sg:postcode":"P0N 1H0",
    "sg:province":"ON",
    "sg:tags":[
        "general",
        "contractor"
    ],
    "wof:name":"Qualitech Construction",
    "wof:placetype":"venue"
},
  "geometry": {"coordinates":[-81.21341700000001,48.486908],"type":"Point"}
}