{
  "type": "Feature",
  "properties": {
    "addr:full":"2508 Marine Dr West Vancouver BC V7V 1L4",
    "addr:housenumber":"2508",
    "addr:postcode":"v7v 1l4",
    "addr:street":"Marine Dr",
    "iso:country":"CA",
    "sg:address":"2508 Marine Dr",
    "sg:city":"West Vancouver",
    "sg:classifiers":[
        {
            "category":"Restaurant",
            "type":"Food & Drink"
        }
    ],
    "sg:phone":"+1 604 926 6001",
    "sg:postcode":"V7V 1L4",
    "sg:province":"BC",
    "wof:name":"Vina Vietnamese Cuisine",
    "wof:placetype":"venue"
},
  "geometry": {"coordinates":[-123.182991028,49.3349571228],"type":"Point"}
}