{
  "type": "Feature",
  "properties": {
    "addr:full":"203 Colborne St London ON N6B 2S3",
    "addr:housenumber":"203",
    "addr:postcode":"n6b 2s3",
    "addr:street":"Colborne St",
    "iso:country":"CA",
    "sg:address":"203 Colborne St",
    "sg:city":"London",
    "sg:classifiers":[
        {
            "category":"Shopping",
            "subcategory":"Discount & Variety Stores",
            "type":"Retail Goods"
        }
    ],
    "sg:phone":"+1 519 439 0287",
    "sg:postcode":"N6B 2S3",
    "sg:province":"ON",
    "wof:name":"California Convenience",
    "wof:placetype":"venue"
},
  "geometry": {"coordinates":[-81.236656189,42.9801177979],"type":"Point"}
}