{
  "type": "Feature",
  "properties": {
    "addr:full":"297 Lakeshore Rd E #7 Oakville ON L6J 1J3",
    "addr:housenumber":"297",
    "addr:postcode":"l6j 1j3",
    "addr:street":"Lakeshore Rd E # 7",
    "iso:country":"CA",
    "sg:address":"297 Lakeshore Rd E #7",
    "sg:city":"Oakville",
    "sg:classifiers":[
        {
            "category":"Travel",
            "subcategory":"Travel Agent",
            "type":"Entertainment"
        }
    ],
    "sg:phone":"+1 905 368 1800",
    "sg:postcode":"L6J 1J3",
    "sg:province":"ON",
    "sg:tags":[
        "agency",
        "bureau"
    ],
    "wof:name":"Reach Out Tours Inc",
    "wof:placetype":"venue"
},
  "geometry": {"coordinates":[-79.6662597656,43.4477996826],"type":"Point"}
}