{
  "type": "Feature",
  "properties": {
    "addr:full":"632 St Clair Ave W Toronto ON M6C 1A9",
    "addr:housenumber":"632",
    "addr:postcode":"m6c 1a9",
    "addr:street":"St Clair Ave W",
    "iso:country":"CA",
    "sg:address":"632 St Clair Ave W",
    "sg:city":"Toronto",
    "sg:classifiers":[
        {
            "category":"Banks & Credit Unions",
            "subcategory":"Bank",
            "type":"Services"
        }
    ],
    "sg:phone":"+1 416 656 2269",
    "sg:postcode":"M6C 1A9",
    "sg:province":"ON",
    "sg:tags":[
        "money",
        "order",
        "transfer"
    ],
    "wof:name":"Tropical Express",
    "wof:placetype":"venue"
},
  "geometry": {"coordinates":[-79.4236831665,43.6822280884],"type":"Point"}
}