{
  "type": "Feature",
  "properties": {
    "iso:country":"CA",
    "sg:address":"118 10th St",
    "sg:city":"Brandon",
    "sg:classifiers":[
        {
            "category":"Personal",
            "subcategory":"Beauty Salon",
            "type":"Services"
        }
    ],
    "sg:phone":"+1 204 728 8843",
    "sg:postcode":"R7A 4E6",
    "sg:province":"MB",
    "sg:tags":[
        "school"
    ],
    "wof:name":"Classic Hairstyling Academy",
    "wof:placetype":"venue"
},
  "geometry": {"coordinates":[-99.9515609741,49.8480796814],"type":"Point"}
}