{
  "type": "Feature",
  "properties": {
    "addr:full":"2993 Sheppard Ave E Scarborough ON M1T 3J5",
    "addr:housenumber":"2993",
    "addr:postcode":"m1t 3j5",
    "addr:street":"Sheppard Ave E",
    "iso:country":"CA",
    "sg:address":"2993 Sheppard Ave E",
    "sg:city":"Scarborough",
    "sg:classifiers":[
        {
            "category":"Restaurant",
            "type":"Food & Drink"
        }
    ],
    "sg:phone":"+1 416 756 0077",
    "sg:postcode":"M1T 3J5",
    "sg:province":"ON",
    "wof:name":"Mr Submarine",
    "wof:placetype":"venue"
},
  "geometry": {"coordinates":[-79.31951100000001,43.775944],"type":"Point"}
}