{
  "type": "Feature",
  "properties": {
    "addr:full":"54 Main St Cobden ON K0J 1K0",
    "addr:housenumber":"54",
    "addr:postcode":"k0j 1k0",
    "addr:street":"Main St",
    "iso:country":"CA",
    "sg:address":"54 Main St",
    "sg:city":"Cobden",
    "sg:classifiers":[
        {
            "category":"Food & Beverages",
            "subcategory":"Groceries & Convenience Stores",
            "type":"Retail Goods"
        }
    ],
    "sg:phone":"+1 613 646 2197",
    "sg:postcode":"K0J 1K0",
    "sg:province":"ON",
    "sg:tags":[
        "grocer"
    ],
    "wof:name":"Cobden Freshmart",
    "wof:placetype":"venue"
},
  "geometry": {"coordinates":[-76.88481899999999,45.626671],"type":"Point"}
}