{
  "type": "Feature",
  "properties": {
    "addr:full":"Ryley AB T0B 4A0",
    "addr:postcode":"t0b 4a0",
    "iso:country":"CA",
    "sg:city":"Ryley",
    "sg:classifiers":[
        {
            "category":"Mining & Drilling",
            "type":"Manufacturing & Wholesale Goods"
        }
    ],
    "sg:phone":"+1 780 663 2285",
    "sg:postcode":"T0B 4A0",
    "sg:province":"AB",
    "sg:tags":[
        "coal",
        "shipping"
    ],
    "wof:name":"Dodds Coal Mining CO Ltd",
    "wof:placetype":"venue"
},
  "geometry": {"coordinates":[-112.42781100000001,53.289848],"type":"Point"}
}