{
  "type": "Feature",
  "properties": {
    "iso:country":"CA",
    "sg:address":"11930 Route 11",
    "sg:city":"Village Blanchard",
    "sg:classifiers":[
        {
            "category":"Organizations",
            "subcategory":"Religious Organization",
            "type":"Services"
        }
    ],
    "sg:phone":"+1 506 727 7579",
    "sg:postcode":"E8P 1R6",
    "sg:province":"NB",
    "sg:tags":[
        "church"
    ],
    "wof:name":"Temoins DE Jehovah",
    "wof:placetype":"venue"
},
  "geometry": {"coordinates":[-66.3815002441,48.0558013916],"type":"Point"}
}