{
  "type": "Feature",
  "properties": {
    "addr:full":"1105 Queen St E Toronto ON M4M 1K7",
    "addr:housenumber":"1105",
    "addr:postcode":"m4m 1k7",
    "addr:street":"Queen St E",
    "iso:country":"CA",
    "sg:address":"1105 Queen St E",
    "sg:city":"Toronto",
    "sg:classifiers":[
        {
            "category":"Manufacturing",
            "subcategory":"Printing",
            "type":"Manufacturing & Wholesale Goods"
        }
    ],
    "sg:phone":"+1 416 466 4606",
    "sg:postcode":"M4M 1K7",
    "sg:province":"ON",
    "sg:tags":[
        "printer"
    ],
    "wof:name":"We Print",
    "wof:placetype":"venue"
},
  "geometry": {"coordinates":[-79.335548,43.661915],"type":"Point"}
}