{
  "type": "Feature",
  "properties": {
    "addr:full":"Vancouver BC V6B 1A4",
    "addr:postcode":"v6b 1a4",
    "iso:country":"CA",
    "sg:city":"Vancouver",
    "sg:classifiers":[
        {
            "category":"Arts & Performance",
            "subcategory":"Theater",
            "type":"Entertainment"
        }
    ],
    "sg:phone":"+1 604 689 7070",
    "sg:postcode":"V6B 1A4",
    "sg:province":"BC",
    "sg:tags":[
        "bureau"
    ],
    "wof:name":"Lou Blair Management",
    "wof:placetype":"venue"
},
  "geometry": {"coordinates":[-123.105728149,49.2836303711],"type":"Point"}
}