{
  "type": "Feature",
  "properties": {
    "addr:full":"287 Glidden Rd Brampton ON L6W 1H9",
    "addr:housenumber":"287",
    "addr:postcode":"l6w 1h9",
    "addr:street":"Glidden Rd",
    "iso:country":"CA",
    "sg:address":"287 Glidden Rd",
    "sg:city":"Brampton",
    "sg:classifiers":[
        {
            "category":"Wholesale",
            "subcategory":"Electrical",
            "type":"Manufacturing & Wholesale Goods"
        }
    ],
    "sg:phone":"+1 905 452 7752",
    "sg:postcode":"L6W 1H9",
    "sg:province":"ON",
    "sg:tags":[
        "equipment",
        "electric",
        "supply"
    ],
    "wof:name":"Torbram Electric Supply",
    "wof:placetype":"venue"
},
  "geometry": {"coordinates":[-79.730171,43.682999],"type":"Point"}
}