{
  "type": "Feature",
  "properties": {
    "addr:full":"Sundridge ON P0A 1Z0",
    "addr:postcode":"p0a 1z0",
    "iso:country":"CA",
    "sg:city":"Sundridge",
    "sg:classifiers":[
        {
            "category":"Professional",
            "subcategory":"Business Services",
            "type":"Services"
        }
    ],
    "sg:phone":"+1 705 384 5944",
    "sg:postcode":"P0A 1Z0",
    "sg:province":"ON",
    "sg:tags":[
        "auctioneer"
    ],
    "wof:name":"Northern Auction Sales",
    "wof:placetype":"venue"
},
  "geometry": {"coordinates":[-79.3837814331,45.7729949951],"type":"Point"}
}