{
  "type": "Feature",
  "properties": {
    "addr:full":"Winnipeg MB R3T 4R6",
    "addr:postcode":"r3t 4r6",
    "iso:country":"CA",
    "sg:city":"Winnipeg",
    "sg:classifiers":[
        {
            "category":"Real Estate",
            "subcategory":"Real Estate Operator",
            "type":"Services"
        }
    ],
    "sg:phone":"+1 204 275 1172",
    "sg:postcode":"R3T 4R6",
    "sg:province":"MB",
    "sg:tags":[
        "condominium"
    ],
    "wof:name":"Country Knoll",
    "wof:placetype":"venue"
},
  "geometry": {"coordinates":[-97.15716552729999,49.7808876038],"type":"Point"}
}