{
  "type": "Feature",
  "properties": {
    "addr:full":"Gibsons BC V0N 1V4",
    "addr:postcode":"v0n 1v4",
    "iso:country":"CA",
    "sg:city":"Gibsons",
    "sg:classifiers":[
        {
            "category":"Freight",
            "type":"Transportation"
        }
    ],
    "sg:phone":"+1 604 886 7698",
    "sg:postcode":"V0N 1V4",
    "sg:province":"BC",
    "sg:tags":[
        "commercial",
        "storage"
    ],
    "wof:name":"Sunshine Coast Self Storage",
    "wof:placetype":"venue"
},
  "geometry": {"coordinates":[-123.526145935,49.4066390991],"type":"Point"}
}