{
  "type": "Feature",
  "properties": {
    "iso:country":"CA",
    "sg:city":"Barrie",
    "sg:classifiers":[
        {
            "category":"Shopping",
            "type":"Retail Goods"
        }
    ],
    "sg:phone":"+1 705 737 5555",
    "sg:postcode":"L4N 1L2",
    "sg:province":"ON",
    "sg:tags":[
        "supply",
        "equipment",
        "audiologists",
        "hearing",
        "impaired"
    ],
    "wof:name":"Hearing Clinic",
    "wof:placetype":"venue"
},
  "geometry": {"coordinates":[-79.70314788819999,44.3894729614],"type":"Point"}
}