{
  "type": "Feature",
  "properties": {
    "addr:full":"Ottawa ON K1B 4W5",
    "addr:postcode":"k1b 4w5",
    "iso:country":"CA",
    "sg:city":"Ottawa",
    "sg:classifiers":[
        {
            "category":"Banks & Credit Unions",
            "subcategory":"Investment Brokerage",
            "type":"Services"
        }
    ],
    "sg:phone":"+1 613 594 8485",
    "sg:postcode":"K1B 4W5",
    "sg:province":"ON",
    "sg:tags":[
        "consultant",
        "planning",
        "financial"
    ],
    "wof:name":"Gauri Enterprises",
    "wof:placetype":"venue"
},
  "geometry": {"coordinates":[-75.609886,45.395115],"type":"Point"}
}