{
  "type": "Feature",
  "properties": {
    "addr:full":"2075 Rue University # 1010 Montreal QC H3A 2L1",
    "addr:housenumber":"2075;#",
    "addr:postcode":"h3a 2l1",
    "addr:street":"Rue University",
    "iso:country":"CA",
    "sg:address":"2075 Rue University # 1010",
    "sg:city":"Montreal",
    "sg:classifiers":[
        {
            "category":"Professional",
            "subcategory":"Management & Consulting",
            "type":"Services"
        }
    ],
    "sg:phone":"+1 514 288 5900",
    "sg:postcode":"H3A 2L1",
    "sg:province":"QC",
    "sg:tags":[
        "employee",
        "advisory",
        "benefit",
        "financial",
        "consultant"
    ],
    "wof:name":"Pensul Inc",
    "wof:placetype":"venue"
},
  "geometry": {"coordinates":[-73.5724868774,45.5046005249],"type":"Point"}
}