{
  "type": "Feature",
  "properties": {
    "addr:full":"722 S Hwy 23 Revelstoke BC V0E 2S0",
    "addr:housenumber":"722",
    "addr:postcode":"v0e 2s0",
    "addr:street":"S Hwy 23",
    "iso:country":"CA",
    "sg:address":"722 S Hwy 23",
    "sg:city":"Revelstoke",
    "sg:classifiers":[
        {
            "category":"Autos & Motor Vehicles",
            "subcategory":"Auto Supplies",
            "type":"Retail Goods"
        }
    ],
    "sg:phone":"+1 250 837 6181",
    "sg:postcode":"V0E 2S0",
    "sg:province":"BC",
    "sg:tags":[
        "tire"
    ],
    "wof:name":"Revelstoke Tire Svc Ltd",
    "wof:placetype":"venue"
},
  "geometry": {"coordinates":[-118.211402893,51.0248374939],"type":"Point"}
}