{
  "type": "Feature",
  "properties": {
    "addr:full":"5232 4 St SW Calgary AB T2V 0Z4",
    "addr:housenumber":"5232 4",
    "addr:postcode":"t2v 0z4",
    "addr:street":"St Sw",
    "iso:country":"CA",
    "sg:address":"5232 4 St SW",
    "sg:city":"Calgary",
    "sg:classifiers":[
        {
            "category":"Social Services",
            "subcategory":"Child Care",
            "type":"Services"
        }
    ],
    "sg:phone":"+1 403 255 5577",
    "sg:postcode":"T2V 0Z4",
    "sg:province":"AB",
    "sg:tags":[
        "kindergarten",
        "academic"
    ],
    "wof:name":"Providence Children's Ctr",
    "wof:placetype":"venue"
},
  "geometry": {"coordinates":[-114.07118988000001,51.0082054138],"type":"Point"}
}