{
  "type": "Feature",
  "properties": {
    "addr:full":"6212 Av Clanranald Montreal QC H3X 2T3",
    "addr:housenumber":"6212",
    "addr:postcode":"h3x 2t3",
    "addr:street":"Av Clanranald",
    "iso:country":"CA",
    "sg:address":"6212 Av Clanranald",
    "sg:city":"Montreal",
    "sg:classifiers":[
        {
            "category":"Health Services",
            "subcategory":"Doctor",
            "type":"Services"
        }
    ],
    "sg:phone":"+1 514 737 6687",
    "sg:postcode":"H3X 2T3",
    "sg:province":"QC",
    "sg:tags":[
        "physician",
        "surgeon"
    ],
    "wof:name":"Wiener, Fred MD",
    "wof:placetype":"venue"
},
  "geometry": {"coordinates":[-73.644997,45.487068],"type":"Point"}
}