{
  "type": "Feature",
  "properties": {
    "addr:full":"917 Mcdowell Rd W Simcoe ON N3Y 4J9",
    "addr:housenumber":"917",
    "addr:postcode":"n3y 4j9",
    "addr:street":"Mcdowell Rd W",
    "iso:country":"CA",
    "sg:address":"917 Mcdowell Rd W",
    "sg:city":"Simcoe",
    "sg:classifiers":[
        {
            "category":"Building & Trades",
            "subcategory":"Construction",
            "type":"Services"
        }
    ],
    "sg:phone":"+1 519 426 3569",
    "sg:postcode":"N3Y 4J9",
    "sg:province":"ON",
    "sg:tags":[
        "masonry",
        "contractor"
    ],
    "wof:name":"Paul Shepherd's Masonry",
    "wof:placetype":"venue"
},
  "geometry": {"coordinates":[-80.30529,42.835903],"type":"Point"}
}