{
  "type": "Feature",
  "properties": {
    "iso:country":"CA",
    "sg:city":"Etobicoke",
    "sg:classifiers":[
        {
            "category":"Organizations",
            "subcategory":"Professional Association",
            "type":"Services"
        }
    ],
    "sg:phone":"+1 416 239 6462",
    "sg:postcode":"M9B 6C7",
    "sg:province":"ON",
    "wof:name":"Ontario Occupational Health",
    "wof:placetype":"venue"
},
  "geometry": {"coordinates":[-79.5569992065,43.6371307373],"type":"Point"}
}