{
  "type": "Feature",
  "properties": {
    "addr:full":"325 Breithaupt St Kitchener ON N2H 5H6",
    "addr:housenumber":"325",
    "addr:postcode":"n2h 5h6",
    "addr:street":"Breithaupt St",
    "iso:country":"CA",
    "sg:address":"325 Breithaupt St",
    "sg:city":"Kitchener",
    "sg:classifiers":[
        {
            "category":"Manufacturing",
            "subcategory":"Signs",
            "type":"Manufacturing & Wholesale Goods"
        }
    ],
    "sg:phone":"+1 519 741 1220",
    "sg:postcode":"N2H 5H6",
    "sg:province":"ON",
    "wof:name":"Sign Shack",
    "wof:placetype":"venue"
},
  "geometry": {"coordinates":[-80.48511499999999,43.459026],"type":"Point"}
}