{
  "type": "Feature",
  "properties": {
    "iso:country":"CA",
    "sg:address":"61 Ch Station",
    "sg:city":"Memramcook",
    "sg:classifiers":[
        {
            "category":"Building & Trades",
            "subcategory":"Construction",
            "type":"Services"
        }
    ],
    "sg:phone":"+1 506 758 2495",
    "sg:postcode":"E4K 1S3",
    "sg:province":"NB",
    "sg:tags":[
        "masonry",
        "contractor"
    ],
    "wof:name":"J & L Masonry Ltd",
    "wof:placetype":"venue"
},
  "geometry": {"coordinates":[-64.5605926514,46.0287475586],"type":"Point"}
}