{
  "type": "Feature",
  "properties": {
    "addr:full":"440 Upper Wentworth St Hamilton ON L9A 4T7",
    "addr:housenumber":"440",
    "addr:postcode":"l9a 4t7",
    "addr:street":"Upper Wentworth St",
    "iso:country":"CA",
    "sg:address":"440 Upper Wentworth St",
    "sg:city":"Hamilton",
    "sg:classifiers":[
        {
            "category":"Organizations",
            "subcategory":"Religious Organization",
            "type":"Services"
        }
    ],
    "sg:phone":"+1 905 387 2228",
    "sg:postcode":"L9A 4T7",
    "sg:province":"ON",
    "sg:tags":[
        "church",
        "care",
        "child"
    ],
    "wof:name":"Mount Hamilton Baptist Church",
    "wof:placetype":"venue"
},
  "geometry": {"coordinates":[-79.85586499999999,43.237999],"type":"Point"}
}