{
  "type": "Feature",
  "properties": {
    "addr:full":"Surrey BC V3W 3E9",
    "addr:postcode":"v3w 3e9",
    "iso:country":"CA",
    "sg:city":"Surrey",
    "sg:classifiers":[
        {
            "category":"Restaurant",
            "type":"Food & Drink"
        }
    ],
    "sg:phone":"+1 604 591 1181",
    "sg:postcode":"V3W 3E9",
    "sg:province":"BC",
    "wof:name":"China Express Food Ltd",
    "wof:placetype":"venue"
},
  "geometry": {"coordinates":[-122.87663999999999,49.151939],"type":"Point"}
}