{
  "type": "Feature",
  "properties": {
    "addr:full":"2677 Clearbrook Rd Abbotsford BC V2T 2Y6",
    "addr:housenumber":"2677",
    "addr:postcode":"v2t 2y6",
    "addr:street":"Clearbrook Rd",
    "iso:country":"CA",
    "sg:address":"2677 Clearbrook Rd",
    "sg:city":"Abbotsford",
    "sg:classifiers":[
        {
            "category":"Restaurant",
            "type":"Food & Drink"
        }
    ],
    "sg:phone":"+1 604 854 5614",
    "sg:postcode":"V2T 2Y6",
    "sg:province":"BC",
    "wof:name":"Kfc",
    "wof:placetype":"venue"
},
  "geometry": {"coordinates":[-122.33777618400001,49.0519599915],"type":"Point"}
}