{
  "type": "Feature",
  "properties": {
    "iso:country":"CA",
    "sg:address":"1941 Route 3",
    "sg:city":"Harvey Station",
    "sg:classifiers":[
        {
            "category":"Banks & Credit Unions",
            "subcategory":"Bank",
            "type":"Services"
        }
    ],
    "sg:phone":"+1 506 366 9020",
    "sg:postcode":"E6K 1K3",
    "sg:province":"NB",
    "wof:name":"Royal Bank Financial Group",
    "wof:placetype":"venue"
},
  "geometry": {"coordinates":[-67.01449599999999,45.737926],"type":"Point"}
}