{
  "type": "Feature",
  "properties": {
    "iso:country":"CA",
    "sg:city":"Kamloops",
    "sg:classifiers":[
        {
            "category":"Social Services",
            "type":"Services"
        }
    ],
    "sg:phone":"+1 250 851 2542",
    "sg:postcode":"V1S 1J9",
    "sg:province":"BC",
    "sg:tags":[
        "employee",
        "assistance",
        "program"
    ],
    "wof:name":"Smart Options Inc",
    "wof:placetype":"venue"
},
  "geometry": {"coordinates":[-120.378647,50.649982],"type":"Point"}
}