{
  "type": "Feature",
  "properties": {
    "addr:full":"105 Ontario St Sarnia ON N7T 1K9",
    "addr:housenumber":"105",
    "addr:postcode":"n7t 1k9",
    "addr:street":"Ontario St",
    "iso:country":"CA",
    "sg:address":"105 Ontario St",
    "sg:city":"Sarnia",
    "sg:classifiers":[
        {
            "category":"Professional",
            "subcategory":"Computer Services",
            "type":"Services"
        }
    ],
    "sg:phone":"+1 519 383 6504",
    "sg:postcode":"N7T 1K9",
    "sg:province":"ON",
    "sg:tags":[
        "repair",
        "dealer",
        "equipment"
    ],
    "wof:name":"Sarnia Computer Ctr",
    "wof:placetype":"venue"
},
  "geometry": {"coordinates":[-82.39827,42.968426],"type":"Point"}
}