{
  "type": "Feature",
  "properties": {
    "addr:full":"143 Rue Saint-Jean-Baptiste L'Isle-Verte QC G0L 1K0",
    "addr:housenumber":"143",
    "addr:postcode":"g0l 1k0",
    "addr:street":"Rue Saint-Jean-Baptiste",
    "iso:country":"CA",
    "sg:address":"143 Rue Saint-Jean-Baptiste",
    "sg:city":"L'Isle-Verte",
    "sg:classifiers":[
        {
            "category":"Food & Beverages",
            "subcategory":"Groceries & Convenience Stores",
            "type":"Retail Goods"
        }
    ],
    "sg:phone":"+1 418 898 2680",
    "sg:postcode":"G0L 1K0",
    "sg:province":"QC",
    "sg:tags":[
        "grocer"
    ],
    "wof:name":"Soucy & Fils Inc",
    "wof:placetype":"venue"
},
  "geometry": {"coordinates":[-69.33599100000001,48.014515],"type":"Point"}
}