{
  "type": "Feature",
  "properties": {
    "addr:full":"2131 Boul Marcel-Laurin Saint-Laurent QC H4R 1K4",
    "addr:housenumber":"2131",
    "addr:postcode":"h4r 1k4",
    "addr:street":"Boul Marcel-Laurin",
    "iso:country":"CA",
    "sg:address":"2131 Boul Marcel-Laurin",
    "sg:city":"Saint-Laurent",
    "sg:classifiers":[
        {
            "category":"Restaurant",
            "type":"Food & Drink"
        }
    ],
    "sg:phone":"+1 514 334 2909",
    "sg:postcode":"H4R 1K4",
    "sg:province":"QC",
    "wof:name":"Pik-Nik",
    "wof:placetype":"venue"
},
  "geometry": {"coordinates":[-73.702438,45.51923],"type":"Point"}
}