{
  "type": "Feature",
  "properties": {
    "addr:full":"Waterloo ON N2K 3P9",
    "addr:postcode":"n2k 3p9",
    "iso:country":"CA",
    "sg:city":"Waterloo",
    "sg:classifiers":[
        {
            "category":"Social Services",
            "subcategory":"Job Training",
            "type":"Services"
        }
    ],
    "sg:phone":"+1 519 746 8172",
    "sg:postcode":"N2K 3P9",
    "sg:province":"ON",
    "sg:tags":[
        "physiotherapist",
        "rehabilitation"
    ],
    "wof:name":"Back Works Spinal & Sports",
    "wof:placetype":"venue"
},
  "geometry": {"coordinates":[-80.52587127690001,43.5046195984],"type":"Point"}
}