{
  "type": "Feature",
  "properties": {
    "addr:full":"4 West St Port Carling ON P0B 1J0",
    "addr:housenumber":"4",
    "addr:postcode":"p0b 1j0",
    "addr:street":"West St",
    "iso:country":"CA",
    "sg:address":"4 West St",
    "sg:city":"Port Carling",
    "sg:classifiers":[
        {
            "category":"Building & Trades",
            "subcategory":"Construction",
            "type":"Services"
        }
    ],
    "sg:phone":"+1 705 765 0080",
    "sg:postcode":"P0B 1J0",
    "sg:province":"ON",
    "sg:tags":[
        "dock"
    ],
    "wof:name":"Muskoka Steel Dock CO",
    "wof:placetype":"venue"
},
  "geometry": {"coordinates":[-79.5746917725,45.1155433655],"type":"Point"}
}