{
  "type": "Feature",
  "properties": {
    "addr:full":"1771 Avenue Rd North York ON M5M 3Y8",
    "addr:housenumber":"1771",
    "addr:postcode":"m5m 3y8",
    "addr:street":"Avenue Rd",
    "iso:country":"CA",
    "sg:address":"1771 Avenue Rd",
    "sg:city":"North York",
    "sg:classifiers":[
        {
            "category":"Retail",
            "subcategory":"Photofinishing",
            "type":"Services"
        }
    ],
    "sg:phone":"+1 416 785 3070",
    "sg:postcode":"M5M 3Y8",
    "sg:province":"ON",
    "sg:tags":[
        "photo",
        "finishing"
    ],
    "wof:name":"Photo Innovations",
    "wof:placetype":"venue"
},
  "geometry": {"coordinates":[-79.41255187989999,43.7679138184],"type":"Point"}
}