{
  "type": "Feature",
  "properties": {
    "iso:country":"CA",
    "sg:address":"1240 Woodbine Ave",
    "sg:city":"East York",
    "sg:classifiers":[
        {
            "category":"Organizations",
            "subcategory":"Professional Association",
            "type":"Services"
        }
    ],
    "sg:phone":"+1 416 425 1714",
    "sg:postcode":"M4C 4E4",
    "sg:province":"ON",
    "wof:name":"Royal Canadian Legion",
    "wof:placetype":"venue"
},
  "geometry": {"coordinates":[-79.3161392212,43.6932258606],"type":"Point"}
}