{
  "type": "Feature",
  "properties": {
    "addr:full":"Scarborough ON M1B 4Z5",
    "addr:postcode":"m1b 4z5",
    "iso:country":"CA",
    "sg:city":"Scarborough",
    "sg:classifiers":[
        {
            "category":"Retail",
            "subcategory":"Repair Shop",
            "type":"Services"
        }
    ],
    "sg:phone":"+1 416 286 6868",
    "sg:postcode":"M1B 4Z5",
    "sg:province":"ON",
    "sg:tags":[
        "interior",
        "consultant",
        "design",
        "refinishing",
        "decorator"
    ],
    "wof:name":"Pbi Office Interiors",
    "wof:placetype":"venue"
},
  "geometry": {"coordinates":[-79.20095825200001,43.8058319092],"type":"Point"}
}