{
  "type": "Feature",
  "properties": {
    "addr:full":"130 Rue Claire-Fontaine O Alma QC G8B 6R1",
    "addr:housenumber":"130",
    "addr:postcode":"g8b 6r1",
    "addr:street":"Rue Claire-Fontaine O",
    "iso:country":"CA",
    "sg:address":"130 Rue Claire-Fontaine O",
    "sg:city":"Alma",
    "sg:classifiers":[
        {
            "category":"Building & Trades",
            "subcategory":"Construction",
            "type":"Services"
        }
    ],
    "sg:phone":"+1 418 668 6215",
    "sg:postcode":"G8B 6R1",
    "sg:province":"QC",
    "sg:tags":[
        "maker",
        "cabinet"
    ],
    "wof:name":"Creation Alpha Design",
    "wof:placetype":"venue"
},
  "geometry": {"coordinates":[-71.644272,48.563965],"type":"Point"}
}