{
  "type": "Feature",
  "properties": {
    "addr:full":"509 2nd Ave S Martensville SK S0K 2T0",
    "addr:housenumber":"509",
    "addr:postcode":"s0k 2t0",
    "addr:street":"2Nd Ave S",
    "iso:country":"CA",
    "sg:address":"509 2nd Ave S",
    "sg:city":"Martensville",
    "sg:classifiers":[
        {
            "category":"Retail",
            "subcategory":"Animal Services",
            "type":"Services"
        }
    ],
    "sg:phone":"+1 306 382 8338",
    "sg:postcode":"S0K 2T0",
    "sg:province":"SK",
    "sg:tags":[
        "pet",
        "grooming",
        "washing"
    ],
    "wof:name":"Heavenly Hounds All-Breed",
    "wof:placetype":"venue"
},
  "geometry": {"coordinates":[-106.670731,52.296265],"type":"Point"}
}