{
  "type": "Feature",
  "properties": {
    "addr:full":"York ON N0A 1R0",
    "addr:postcode":"n0a 1r0",
    "iso:country":"CA",
    "sg:city":"York",
    "sg:classifiers":[
        {
            "category":"Education",
            "subcategory":"School",
            "type":"Public Place"
        }
    ],
    "sg:phone":"+1 905 772 5222",
    "sg:postcode":"N0A 1R0",
    "sg:province":"ON",
    "wof:name":"Seneca Central Public School",
    "wof:placetype":"venue"
},
  "geometry": {"coordinates":[-79.891113,43.022419],"type":"Point"}
}