{
  "type": "Feature",
  "properties": {
    "iso:country":"CA",
    "sg:city":"Gimli",
    "sg:classifiers":[
        {
            "category":"Personal",
            "subcategory":"Beauty Salon",
            "type":"Services"
        }
    ],
    "sg:phone":"+1 204 642 7951",
    "sg:postcode":"R0C 1B0",
    "sg:province":"MB",
    "wof:name":"Hair Goes",
    "wof:placetype":"venue"
},
  "geometry": {"coordinates":[-96.9910125732,50.6335716248],"type":"Point"}
}