{
  "type": "Feature",
  "properties": {
    "addr:full":"18 Rue Haendel Kirkland QC H9H 4Y9",
    "addr:housenumber":"18",
    "addr:postcode":"h9h 4y9",
    "addr:street":"Rue Haendel",
    "iso:country":"CA",
    "sg:address":"18 Rue Haendel",
    "sg:city":"Kirkland",
    "sg:classifiers":[
        {
            "category":"Shopping",
            "subcategory":"Florist",
            "type":"Retail Goods"
        }
    ],
    "sg:phone":"+1 514 695 0235",
    "sg:postcode":"H9H 4Y9",
    "sg:province":"QC",
    "sg:tags":[
        "plant"
    ],
    "wof:name":"Atelier Patrick Studio Inc",
    "wof:placetype":"venue"
},
  "geometry": {"coordinates":[-73.8577880859,45.4665527344],"type":"Point"}
}