{
  "type": "Feature",
  "properties": {
    "addr:full":"411 Chantenay Dr Mississauga ON L5A 1E9",
    "addr:housenumber":"411",
    "addr:postcode":"l5a 1e9",
    "addr:street":"Chantenay Dr",
    "iso:country":"CA",
    "sg:address":"411 Chantenay Dr",
    "sg:city":"Mississauga",
    "sg:classifiers":[
        {
            "category":"Banks & Credit Unions",
            "subcategory":"Investment Brokerage",
            "type":"Services"
        }
    ],
    "sg:phone":"+1 905 279 9196",
    "sg:postcode":"L5A 1E9",
    "sg:province":"ON",
    "sg:tags":[
        "advisory",
        "financial"
    ],
    "wof:name":"Anvest Financial Svc Inc",
    "wof:placetype":"venue"
},
  "geometry": {"coordinates":[-79.59284210209999,43.5793418884],"type":"Point"}
}