{
  "type": "Feature",
  "properties": {
    "addr:full":"385 Nebo Rd Hamilton ON L8W 3P4",
    "addr:housenumber":"385",
    "addr:postcode":"l8w 3p4",
    "addr:street":"Nebo Rd",
    "iso:country":"CA",
    "sg:address":"385 Nebo Rd",
    "sg:city":"Hamilton",
    "sg:classifiers":[
        {
            "category":"Manufacturing",
            "subcategory":"Metals",
            "type":"Manufacturing & Wholesale Goods"
        }
    ],
    "sg:phone":"+1 905 385 3183",
    "sg:postcode":"L8W 3P4",
    "sg:province":"ON",
    "sg:tags":[
        "pipe",
        "lining",
        "coating"
    ],
    "wof:name":"Shaw Pipe Protection Ltd",
    "wof:placetype":"venue"
},
  "geometry": {"coordinates":[-79.83981300000001,43.187923],"type":"Point"}
}