{
  "type": "Feature",
  "properties": {
    "iso:country":"CA",
    "sg:address":"888 Ch DE Chambly",
    "sg:city":"Longueuil",
    "sg:classifiers":[
        {
            "category":"Food & Beverages",
            "subcategory":"Groceries & Convenience Stores",
            "type":"Retail Goods"
        }
    ],
    "sg:phone":"+1 450 677 5502",
    "sg:postcode":"J4H 3M3",
    "sg:province":"QC",
    "wof:name":"Depanneur Du Campus",
    "wof:placetype":"venue"
},
  "geometry": {"coordinates":[-73.49639129640001,45.5353126526],"type":"Point"}
}