{
  "type": "Feature",
  "properties": {
    "iso:country":"CA",
    "sg:address":"306 Simcoe St # 1",
    "sg:city":"London",
    "sg:classifiers":[
        {
            "category":"Personal",
            "subcategory":"Tattoo Parlor",
            "type":"Services"
        }
    ],
    "sg:phone":"+1 519 642 3049",
    "sg:postcode":"N6B 1J6",
    "sg:province":"ON",
    "sg:tags":[
        "tattooing"
    ],
    "wof:name":"Custom Tattooing By Mike",
    "wof:placetype":"venue"
},
  "geometry": {"coordinates":[-81.2407836914,42.979511261],"type":"Point"}
}