{
  "type": "Feature",
  "properties": {
    "addr:full":"Montague PE C0A 1R0",
    "addr:postcode":"c0a 1r0",
    "iso:country":"CA",
    "sg:city":"Montague",
    "sg:classifiers":[
        {
            "category":"Government",
            "subcategory":"Office",
            "type":"Public Place"
        }
    ],
    "sg:phone":"+1 902 838 0880",
    "sg:postcode":"C0A 1R0",
    "sg:province":"PE",
    "wof:name":"Pei Vital Statistics",
    "wof:placetype":"venue"
},
  "geometry": {"coordinates":[-62.6497192383,46.1671638489],"type":"Point"}
}