{
  "type": "Feature",
  "properties": {
    "iso:country":"CA",
    "sg:address":"8 Front St S",
    "sg:city":"Thorold",
    "sg:classifiers":[
        {
            "category":"Restaurant",
            "type":"Food & Drink"
        }
    ],
    "sg:phone":"+1 905 680 1931",
    "sg:postcode":"L2V 1W9",
    "sg:province":"ON",
    "wof:name":"Hana's Place Restaurant",
    "wof:placetype":"venue"
},
  "geometry": {"coordinates":[-79.2005,43.124653],"type":"Point"}
}