{
  "type": "Feature",
  "properties": {
    "addr:full":"8 Front St S Thorold ON L2V 1W9",
    "addr:housenumber":"8",
    "addr:postcode":"l2v 1w9",
    "addr:street":"Front St S",
    "iso:country":"CA",
    "sg:address":"8 Front St S",
    "sg:city":"Thorold",
    "sg:classifiers":[
        {
            "category":"Restaurant",
            "type":"Food & Drink"
        }
    ],
    "sg:phone":"+1 905 680 1931",
    "sg:postcode":"L2V 1W9",
    "sg:province":"ON",
    "wof:name":"Hana's Place Restaurant",
    "wof:placetype":"venue"
},
  "geometry": {"coordinates":[-79.20050000000001,43.124653],"type":"Point"}
}