{
  "type": "Feature",
  "properties": {
    "addr:full":"7 Rue Academy Sutton QC J0E 2K0",
    "addr:housenumber":"7",
    "addr:postcode":"j0e 2k0",
    "addr:street":"Rue Academy",
    "iso:country":"CA",
    "sg:address":"7 Rue Academy",
    "sg:city":"Sutton",
    "sg:classifiers":[
        {
            "category":"Shopping",
            "type":"Retail Goods"
        }
    ],
    "sg:phone":"+1 450 538 2563",
    "sg:postcode":"J0E 2K0",
    "sg:province":"QC",
    "sg:tags":[
        "art",
        "gallery",
        "dealer"
    ],
    "wof:name":"Arts Sutton Inc",
    "wof:placetype":"venue"
},
  "geometry": {"coordinates":[-72.615387,45.108734],"type":"Point"}
}