{
  "type": "Feature",
  "properties": {
    "addr:full":"1371 Lawrence Ave W North York ON M6L 1A4",
    "addr:housenumber":"1371",
    "addr:postcode":"m6l 1a4",
    "addr:street":"Lawrence Ave W",
    "iso:country":"CA",
    "sg:address":"1371 Lawrence Ave W",
    "sg:city":"North York",
    "sg:classifiers":[
        {
            "category":"Personal",
            "subcategory":"Beauty Salon",
            "type":"Services"
        }
    ],
    "sg:phone":"+1 416 241 4884",
    "sg:postcode":"M6L 1A4",
    "sg:province":"ON",
    "sg:tags":[
        "barber"
    ],
    "wof:name":"North Park Barber Shop",
    "wof:placetype":"venue"
},
  "geometry": {"coordinates":[-79.476517,43.709129],"type":"Point"}
}