{
  "type": "Feature",
  "properties": {
    "addr:full":"281 Rue DE LA Couronne Quebec QC G1K 6E2",
    "addr:housenumber":"281",
    "addr:postcode":"g1k 6e2",
    "addr:street":"Rue De La Couronne",
    "iso:country":"CA",
    "sg:address":"281 Rue DE LA Couronne",
    "sg:city":"Quebec",
    "sg:classifiers":[
        {
            "category":"Restaurant",
            "type":"Food & Drink"
        }
    ],
    "sg:phone":"+1 418 649 9530",
    "sg:postcode":"G1K 6E2",
    "sg:province":"QC",
    "wof:name":"Pub Paradisio",
    "wof:placetype":"venue"
},
  "geometry": {"coordinates":[-71.22574615480001,46.8158874512],"type":"Point"}
}