{
  "type": "Feature",
  "properties": {
    "addr:full":"4600 Boul Henri-Bourassa # 246 Charlesbourg QC G1H 3A5",
    "addr:housenumber":"4600",
    "addr:postcode":"g1h 3a5",
    "addr:street":"Boul Henri-Bourassa # 246",
    "iso:country":"CA",
    "sg:address":"4600 Boul Henri-Bourassa # 246",
    "sg:city":"Charlesbourg",
    "sg:classifiers":[
        {
            "category":"Banks & Credit Unions",
            "subcategory":"Investment Brokerage",
            "type":"Services"
        }
    ],
    "sg:phone":"+1 418 624 1546",
    "sg:postcode":"G1H 3A5",
    "sg:province":"QC",
    "sg:tags":[
        "consultant",
        "financing"
    ],
    "wof:name":"Service D'Aide Aux Entreprises",
    "wof:placetype":"venue"
},
  "geometry": {"coordinates":[-71.24146270750001,46.849281311],"type":"Point"}
}