{
  "type": "Feature",
  "properties": {
    "iso:country":"CA",
    "sg:address":"36 Prince Edward St",
    "sg:city":"Brighton",
    "sg:classifiers":[
        {
            "category":"Restaurant",
            "type":"Food & Drink"
        }
    ],
    "sg:phone":"+1 613 475 0568",
    "sg:postcode":"K0K 1H0",
    "sg:province":"ON",
    "wof:name":"Vito's Pizzeria",
    "wof:placetype":"venue"
},
  "geometry": {"coordinates":[-77.7367782593,44.0411834717],"type":"Point"}
}