{
  "type": "Feature",
  "properties": {
    "iso:country":"CA",
    "sg:city":"Scarborough",
    "sg:classifiers":[
        {
            "category":"Retail",
            "subcategory":"Portrait Studio",
            "type":"Services"
        }
    ],
    "sg:phone":"+1 416 412 1709",
    "sg:postcode":"M1V 2T3",
    "sg:province":"ON",
    "sg:tags":[
        "photographer"
    ],
    "wof:name":"Nice Photography",
    "wof:placetype":"venue"
},
  "geometry": {"coordinates":[-79.2483139038,43.8196563721],"type":"Point"}
}