{
  "type": "Feature",
  "properties": {
    "addr:full":"4801 Valley Way Niagara Falls ON L2E 1W4",
    "addr:housenumber":"4801",
    "addr:postcode":"l2e 1w4",
    "addr:street":"Valley Way",
    "iso:country":"CA",
    "sg:address":"4801 Valley Way",
    "sg:city":"Niagara Falls",
    "sg:classifiers":[
        {
            "category":"Manufacturing",
            "subcategory":"Printing",
            "type":"Manufacturing & Wholesale Goods"
        }
    ],
    "sg:phone":"+1 905 358 5711",
    "sg:postcode":"L2E 1W4",
    "sg:province":"ON",
    "sg:tags":[
        "newspaper"
    ],
    "wof:name":"Niagara Falls Review",
    "wof:placetype":"venue"
},
  "geometry": {"coordinates":[-79.074333,43.104454],"type":"Point"}
}