{
  "type": "Feature",
  "properties": {
    "addr:full":"1035 Pandora Ave Victoria BC V8V 3P6",
    "addr:housenumber":"1035",
    "addr:postcode":"v8v 3p6",
    "addr:street":"Pandora Ave",
    "iso:country":"CA",
    "sg:address":"1035 Pandora Ave",
    "sg:city":"Victoria",
    "sg:classifiers":[
        {
            "category":"Health Services",
            "subcategory":"Doctor",
            "type":"Services"
        }
    ],
    "sg:phone":"+1 250 385 0311",
    "sg:postcode":"V8V 3P6",
    "sg:province":"BC",
    "sg:tags":[
        "dentist"
    ],
    "wof:name":"Pandora Dental Group",
    "wof:placetype":"venue"
},
  "geometry": {"coordinates":[-123.35498,48.426807],"type":"Point"}
}