{
  "type": "Feature",
  "properties": {
    "addr:full":"180 6th St Glenella MB R0J 0V0",
    "addr:housenumber":"180",
    "addr:postcode":"r0j 0v0",
    "addr:street":"6Th St",
    "iso:country":"CA",
    "sg:address":"180 6th St",
    "sg:city":"Glenella",
    "sg:classifiers":[
        {
            "category":"Shopping",
            "subcategory":"Hobbies, Toys, & Games",
            "type":"Retail Goods"
        }
    ],
    "sg:phone":"+1 204 352 4236",
    "sg:postcode":"R0J 0V0",
    "sg:province":"MB",
    "sg:tags":[
        "product",
        "ceramic"
    ],
    "wof:name":"Whitehorse Ceramics",
    "wof:placetype":"venue"
},
  "geometry": {"coordinates":[-99.14655303959999,50.5723991394],"type":"Point"}
}