{
  "type": "Feature",
  "properties": {
    "addr:full":"3038 Broadway W Vancouver BC V6K 2H1",
    "addr:housenumber":"3038",
    "addr:postcode":"v6k 2h1",
    "addr:street":"Broadway W",
    "iso:country":"CA",
    "sg:address":"3038 Broadway W",
    "sg:city":"Vancouver",
    "sg:classifiers":[
        {
            "category":"Shopping",
            "subcategory":"Hobbies, Toys, & Games",
            "type":"Retail Goods"
        }
    ],
    "sg:phone":"+1 604 733 7114",
    "sg:postcode":"V6K 2H1",
    "sg:province":"BC",
    "sg:tags":[
        "model",
        "supply"
    ],
    "wof:name":"Grand Prix Hobbies & Crafts",
    "wof:placetype":"venue"
},
  "geometry": {"coordinates":[-123.172706604,49.2639808655],"type":"Point"}
}