{
  "type": "Feature",
  "properties": {
    "addr:full":"10 Algoma St S Thunder Bay ON P7B 3A7",
    "addr:housenumber":"10",
    "addr:postcode":"p7b 3a7",
    "addr:street":"Algoma St S",
    "iso:country":"CA",
    "sg:address":"10 Algoma St S",
    "sg:city":"Thunder Bay",
    "sg:classifiers":[
        {
            "category":"Arts & Performance",
            "subcategory":"Theater",
            "type":"Entertainment"
        }
    ],
    "sg:phone":"+1 807 345 5552",
    "sg:postcode":"P7B 3A7",
    "sg:province":"ON",
    "wof:name":"Magnus Theatre",
    "wof:placetype":"venue"
},
  "geometry": {"coordinates":[-89.22434997560001,48.4368934631],"type":"Point"}
}