{
  "type": "Feature",
  "properties": {
    "addr:full":"896 Meyerside Dr Mississauga ON L5T 1R9",
    "addr:housenumber":"896",
    "addr:postcode":"l5t 1r9",
    "addr:street":"Meyerside Dr",
    "iso:country":"CA",
    "sg:address":"896 Meyerside Dr",
    "sg:city":"Mississauga",
    "sg:classifiers":[
        {
            "category":"Manufacturing",
            "subcategory":"Tools & Machinery",
            "type":"Manufacturing & Wholesale Goods"
        }
    ],
    "sg:phone":"+1 905 670 1991",
    "sg:postcode":"L5T 1R9",
    "sg:province":"ON",
    "sg:tags":[
        "transmission",
        "power"
    ],
    "wof:name":"Martin Sprocket & Gear Canada",
    "wof:placetype":"venue"
},
  "geometry": {"coordinates":[-79.6670303345,43.6490211487],"type":"Point"}
}