{
  "type": "Feature",
  "properties": {
    "addr:full":"266 Main St Wellington ON K0K 3L0",
    "addr:housenumber":"266",
    "addr:postcode":"k0k 3l0",
    "addr:street":"Main St",
    "iso:country":"CA",
    "sg:address":"266 Main St",
    "sg:city":"Wellington",
    "sg:classifiers":[
        {
            "category":"Freight",
            "type":"Transportation"
        }
    ],
    "sg:phone":"+1 613 399 3100",
    "sg:postcode":"K0K 3L0",
    "sg:province":"ON",
    "sg:tags":[
        "storage",
        "butchering"
    ],
    "wof:name":"Midtown Cold Storage & Meats",
    "wof:placetype":"venue"
},
  "geometry": {"coordinates":[-77.34893798829999,43.9518852234],"type":"Point"}
}