{
  "type": "Feature",
  "properties": {
    "addr:full":"1201 Division St Kingston ON K7K 6X4",
    "addr:housenumber":"1201",
    "addr:postcode":"k7k 6x4",
    "addr:street":"Division St",
    "iso:country":"CA",
    "sg:address":"1201 Division St",
    "sg:city":"Kingston",
    "sg:classifiers":[
        {
            "category":"Shopping",
            "subcategory":"Pharmacy",
            "type":"Retail Goods"
        }
    ],
    "sg:phone":"+1 613 546 3544",
    "sg:postcode":"K7K 6X4",
    "sg:province":"ON",
    "sg:tags":[
        "post"
    ],
    "wof:name":"Shoppers Drug Mart",
    "wof:placetype":"venue"
},
  "geometry": {"coordinates":[-76.498383,44.26548],"type":"Point"}
}