{
  "type": "Feature",
  "properties": {
    "addr:full":"41 Woodslee Ave Paris ON N3L 3T5",
    "addr:housenumber":"41",
    "addr:postcode":"n3l 3t5",
    "addr:street":"Woodslee Ave",
    "iso:country":"CA",
    "sg:address":"41 Woodslee Ave",
    "sg:city":"Paris",
    "sg:classifiers":[
        {
            "category":"Manufacturing",
            "subcategory":"Metals",
            "type":"Manufacturing & Wholesale Goods"
        }
    ],
    "sg:phone":"+1 519 442 1502",
    "sg:postcode":"N3L 3T5",
    "sg:province":"ON",
    "sg:tags":[
        "spring"
    ],
    "wof:name":"Paris Spring",
    "wof:placetype":"venue"
},
  "geometry": {"coordinates":[-80.396461,43.214905],"type":"Point"}
}