{
  "type": "Feature",
  "properties": {
    "addr:full":"641 King St W # 100 Kitchener ON N2G 1C7",
    "addr:housenumber":"641;100",
    "addr:postcode":"n2g 1c7",
    "addr:street":"King St W #",
    "iso:country":"CA",
    "sg:address":"641 King St W # 100",
    "sg:city":"Kitchener",
    "sg:classifiers":[
        {
            "category":"Health Services",
            "subcategory":"Health Practitioner",
            "type":"Services"
        }
    ],
    "sg:phone":"+1 519 570 3400",
    "sg:postcode":"N2G 1C7",
    "sg:province":"ON",
    "sg:tags":[
        "physiotherapist"
    ],
    "wof:name":"Cbi Physiotherapy & Rehab",
    "wof:placetype":"venue"
},
  "geometry": {"coordinates":[-80.502663,43.454105],"type":"Point"}
}