{
  "type": "Feature",
  "properties": {
    "addr:full":"136 Ellen St Miramichi NB E1V 2N1",
    "addr:housenumber":"136",
    "addr:postcode":"e1v 2n1",
    "addr:street":"Ellen St",
    "iso:country":"CA",
    "sg:address":"136 Ellen St",
    "sg:city":"Miramichi",
    "sg:classifiers":[
        {
            "category":"Insurance",
            "subcategory":"Insurance Agent",
            "type":"Services"
        }
    ],
    "sg:phone":"+1 506 622 2126",
    "sg:postcode":"E1V 2N1",
    "sg:province":"NB",
    "sg:tags":[
        "adjuster"
    ],
    "wof:name":"CO-Operators",
    "wof:placetype":"venue"
},
  "geometry": {"coordinates":[-65.565392,47.001747],"type":"Point"}
}