{
  "type": "Feature",
  "properties": {
    "addr:full":"4913 50 Ave Red Deer AB T4N 4A6",
    "addr:housenumber":"4913",
    "addr:postcode":"t4n 4a6",
    "addr:street":"50 Ave",
    "iso:country":"CA",
    "sg:address":"4913 50 Ave",
    "sg:city":"Red Deer",
    "sg:classifiers":[
        {
            "category":"Home & Garden",
            "subcategory":"Home Furnishings",
            "type":"Retail Goods"
        }
    ],
    "sg:phone":"+1 403 346 1231",
    "sg:postcode":"T4N 4A6",
    "sg:province":"AB",
    "sg:tags":[
        "shop",
        "gift"
    ],
    "wof:name":"Loonie Lane",
    "wof:placetype":"venue"
},
  "geometry": {"coordinates":[-113.813866,52.268562],"type":"Point"}
}