{
  "type": "Feature",
  "properties": {
    "addr:full":"5124 53 St Yellowknife NT X1A 1V6",
    "addr:housenumber":"5124",
    "addr:postcode":"x1a 1v6",
    "addr:street":"53 St",
    "iso:country":"CA",
    "sg:address":"5124 53 St",
    "sg:city":"Yellowknife",
    "sg:classifiers":[
        {
            "category":"Restaurant",
            "type":"Food & Drink"
        }
    ],
    "sg:phone":"+1 867 920 2130",
    "sg:postcode":"X1A 1V6",
    "sg:province":"NT",
    "sg:tags":[
        "pizza"
    ],
    "wof:name":"Bruno's Pizza",
    "wof:placetype":"venue"
},
  "geometry": {"coordinates":[-114.37216949499999,62.4507331848],"type":"Point"}
}