{
  "type": "Feature",
  "properties": {
    "addr:full":"9539 Jasper Ave NW Edmonton AB T5H 3V2",
    "addr:housenumber":"9539",
    "addr:postcode":"t5h 3v2",
    "addr:street":"Jasper Ave Nw",
    "iso:country":"CA",
    "sg:address":"9539 Jasper Ave NW",
    "sg:city":"Edmonton",
    "sg:classifiers":[
        {
            "category":"Food & Beverages",
            "subcategory":"Liquor & Beverages",
            "type":"Retail Goods"
        }
    ],
    "sg:phone":"+1 780 702 0416",
    "sg:postcode":"T5H 3V2",
    "sg:province":"AB",
    "sg:tags":[
        "store"
    ],
    "wof:name":"Liquors on Jasper",
    "wof:placetype":"venue"
},
  "geometry": {"coordinates":[-113.480385,53.544331],"type":"Point"}
}