{
  "type": "Feature",
  "properties": {
    "iso:country":"CA",
    "sg:address":"123 Mclean Dr",
    "sg:city":"London",
    "sg:classifiers":[
        {
            "category":"Personal",
            "subcategory":"Beauty Salon",
            "type":"Services"
        }
    ],
    "sg:phone":"+1 519 659 7881",
    "sg:postcode":"N5X 1Y8",
    "sg:province":"ON",
    "wof:name":"Northridge Beauty Salon",
    "wof:placetype":"venue"
},
  "geometry": {"coordinates":[-81.231461,43.04068],"type":"Point"}
}