{
  "type": "Feature",
  "properties": {
    "iso:country":"CA",
    "sg:city":"Rockwood",
    "sg:classifiers":[
        {
            "category":"Shopping",
            "subcategory":"Florist",
            "type":"Retail Goods"
        }
    ],
    "sg:phone":"+1 519 856 4730",
    "sg:postcode":"N0B 2K0",
    "sg:province":"ON",
    "wof:name":"An Elegant Touch",
    "wof:placetype":"venue"
},
  "geometry": {"coordinates":[-80.14473724370001,43.6194038391],"type":"Point"}
}