{
  "type": "Feature",
  "properties": {
    "addr:full":"13561 King George Hwy Surrey BC V3T 2V1",
    "addr:housenumber":"13561",
    "addr:postcode":"v3t 2v1",
    "addr:street":"King George Hwy",
    "iso:country":"CA",
    "sg:address":"13561 King George Hwy",
    "sg:city":"Surrey",
    "sg:classifiers":[
        {
            "category":"Food & Beverages",
            "subcategory":"Groceries & Convenience Stores",
            "type":"Retail Goods"
        }
    ],
    "sg:phone":"+1 604 584 1170",
    "sg:postcode":"V3T 2V1",
    "sg:province":"BC",
    "sg:tags":[
        "grocer"
    ],
    "wof:name":"Lucky Convenience Store",
    "wof:placetype":"venue"
},
  "geometry": {"coordinates":[-122.84626,49.199818],"type":"Point"}
}