{
  "type": "Feature",
  "properties": {
    "addr:full":"4609 Manitoba Rd SE Calgary AB T2G 4B9",
    "addr:housenumber":"4609",
    "addr:postcode":"t2g 4b9",
    "addr:street":"Manitoba Rd Se",
    "iso:country":"CA",
    "sg:address":"4609 Manitoba Rd SE",
    "sg:city":"Calgary",
    "sg:classifiers":[
        {
            "category":"Manufacturing",
            "subcategory":"Motor Vehicles & Parts",
            "type":"Manufacturing & Wholesale Goods"
        }
    ],
    "sg:phone":"+1 403 243 8170",
    "sg:postcode":"T2G 4B9",
    "sg:province":"AB",
    "sg:tags":[
        "trailer"
    ],
    "wof:name":"Corab Services Ltd",
    "wof:placetype":"venue"
},
  "geometry": {"coordinates":[-114.05622099999999,51.012665],"type":"Point"}
}