{
  "type": "Feature",
  "properties": {
    "iso:country":"CA",
    "sg:city":"Swift Current",
    "sg:classifiers":[
        {
            "category":"Shopping",
            "subcategory":"Gifts & Souvenirs",
            "type":"Retail Goods"
        }
    ],
    "sg:phone":"+1 306 773 0303",
    "sg:postcode":"S9H 3X6",
    "sg:province":"SK",
    "sg:tags":[
        "shop"
    ],
    "wof:name":"Et Cetera Et Cetera",
    "wof:placetype":"venue"
},
  "geometry": {"coordinates":[-107.781051636,50.3051147461],"type":"Point"}
}