{
  "type": "Feature",
  "properties": {
    "addr:full":"25 Holloway St Belleville ON K8P 1N8",
    "addr:housenumber":"25",
    "addr:postcode":"k8p 1n8",
    "addr:street":"Holloway St",
    "iso:country":"CA",
    "sg:address":"25 Holloway St",
    "sg:city":"Belleville",
    "sg:classifiers":[
        {
            "category":"Organizations",
            "subcategory":"Religious Organization",
            "type":"Services"
        }
    ],
    "sg:phone":"+1 613 967 1991",
    "sg:postcode":"K8P 1N8",
    "sg:province":"ON",
    "sg:tags":[
        "church"
    ],
    "wof:name":"Belleville Presbytery Resource",
    "wof:placetype":"venue"
},
  "geometry": {"coordinates":[-77.393562,44.165077],"type":"Point"}
}