{
  "type": "Feature",
  "properties": {
    "iso:country":"CA",
    "sg:address":"677 Lakeshore Dr",
    "sg:city":"Thunder Bay",
    "sg:classifiers":[
        {
            "category":"Local Transit",
            "type":"Transportation"
        }
    ],
    "sg:phone":"+1 807 683 5911",
    "sg:postcode":"P7B 5E4",
    "sg:province":"ON",
    "sg:tags":[
        "bus",
        "line"
    ],
    "wof:name":"Trottier Bus Lines",
    "wof:placetype":"venue"
},
  "geometry": {"coordinates":[-89.245476,48.381699],"type":"Point"}
}