{
  "type": "Feature",
  "properties": {
    "addr:full":"Scarborough ON M1C 2L3",
    "addr:postcode":"m1c 2l3",
    "iso:country":"CA",
    "sg:city":"Scarborough",
    "sg:classifiers":[
        {
            "category":"Retail",
            "subcategory":"Repair Shop",
            "type":"Services"
        }
    ],
    "sg:phone":"+1 416 287 7773",
    "sg:postcode":"M1C 2L3",
    "sg:province":"ON",
    "sg:tags":[
        "sharpening",
        "sporting",
        "good"
    ],
    "wof:name":"Hockey Guys Inc",
    "wof:placetype":"venue"
},
  "geometry": {"coordinates":[-79.14032745359999,43.7886352539],"type":"Point"}
}