{
  "type": "Feature",
  "properties": {
    "addr:full":"550 3rd Ave Prince George BC V2L 3C3",
    "addr:housenumber":"550",
    "addr:postcode":"v2l 3c3",
    "addr:street":"3Rd Ave",
    "iso:country":"CA",
    "sg:address":"550 3rd Ave",
    "sg:city":"Prince George",
    "sg:classifiers":[
        {
            "category":"Home & Garden",
            "subcategory":"Household Appliances",
            "type":"Retail Goods"
        }
    ],
    "sg:phone":"+1 250 564 1414",
    "sg:postcode":"V2L 3C3",
    "sg:province":"BC",
    "sg:tags":[
        "fireplace"
    ],
    "wof:name":"Furnaceland",
    "wof:placetype":"venue"
},
  "geometry": {"coordinates":[-122.73402404799999,53.9137496948],"type":"Point"}
}