{
  "type": "Feature",
  "properties": {
    "iso:country":"CA",
    "sg:address":"421 Shepherdson Rd",
    "sg:city":"New Liskeard",
    "sg:classifiers":[
        {
            "category":"Health Services",
            "subcategory":"Clinic",
            "type":"Services"
        }
    ],
    "sg:phone":"+1 705 647 6999",
    "sg:postcode":"P0J 1P0",
    "sg:province":"ON",
    "sg:tags":[
        "equipment",
        "therapy",
        "oxygen"
    ],
    "wof:name":"Vital Aire",
    "wof:placetype":"venue"
},
  "geometry": {"coordinates":[-79.6954498291,47.4953422546],"type":"Point"}
}