{
  "type": "Feature",
  "properties": {
    "iso:country":"CA",
    "sg:address":"56 Rte Marie-Victorin",
    "sg:city":"Saint-Francois-Du-Lac",
    "sg:classifiers":[
        {
            "category":"Manufacturing",
            "subcategory":"Lumber",
            "type":"Manufacturing & Wholesale Goods"
        }
    ],
    "sg:phone":"+1 450 568 3535",
    "sg:postcode":"J0G 1M0",
    "sg:province":"QC",
    "sg:tags":[
        "sawmill"
    ],
    "wof:name":"Scierie Bois St-Francois Inc",
    "wof:placetype":"venue"
},
  "geometry": {"coordinates":[-72.8227920532,46.0594482422],"type":"Point"}
}