{
  "type": "Feature",
  "properties": {
    "addr:full":"67 Av Westminster N Montreal-Ouest QC H4X 1Y8",
    "addr:postcode":"h4x 1y8",
    "addr:street":"67 Av Westminster N",
    "iso:country":"CA",
    "sg:address":"67 Av Westminster N",
    "sg:city":"Montreal-Ouest",
    "sg:classifiers":[
        {
            "category":"Professional",
            "subcategory":"Management & Consulting",
            "type":"Services"
        }
    ],
    "sg:phone":"+1 514 481 0331",
    "sg:postcode":"H4X 1Y8",
    "sg:province":"QC",
    "sg:tags":[
        "consultant",
        "business"
    ],
    "wof:name":"Consultants D & A Mc Laughlin",
    "wof:placetype":"venue"
},
  "geometry": {"coordinates":[-73.64614899999999,45.453346],"type":"Point"}
}