{
  "type": "Feature",
  "properties": {
    "addr:full":"Brampton ON L6X 4N7",
    "addr:postcode":"l6x 4n7",
    "iso:country":"CA",
    "sg:city":"Brampton",
    "sg:classifiers":[
        {
            "category":"Retail",
            "subcategory":"Laundry & Dry Cleaning",
            "type":"Services"
        }
    ],
    "sg:phone":"+1 905 452 0268",
    "sg:postcode":"L6X 4N7",
    "sg:province":"ON",
    "sg:tags":[
        "cleaners"
    ],
    "wof:name":"Bridlewood Custom Cleaners",
    "wof:placetype":"venue"
},
  "geometry": {"coordinates":[-79.79072600000001,43.692642],"type":"Point"}
}