{
  "type": "Feature",
  "properties": {
    "addr:full":"4405 Canada Way Burnaby BC V5G 1J3",
    "addr:housenumber":"4405",
    "addr:postcode":"v5g 1j3",
    "addr:street":"Canada Way",
    "iso:country":"CA",
    "sg:address":"4405 Canada Way",
    "sg:city":"Burnaby",
    "sg:classifiers":[
        {
            "category":"Professional",
            "subcategory":"Management & Consulting",
            "type":"Services"
        }
    ],
    "sg:phone":"+1 604 433 8275",
    "sg:postcode":"V5G 1J3",
    "sg:province":"BC",
    "sg:tags":[
        "construction"
    ],
    "wof:name":"Task Construction Management",
    "wof:placetype":"venue"
},
  "geometry": {"coordinates":[-123.006218,49.254795],"type":"Point"}
}