{
  "type": "Feature",
  "properties": {
    "addr:full":"322 Carrie Rd W Manitou MB R0G 1G0",
    "addr:housenumber":"322",
    "addr:postcode":"r0g 1g0",
    "addr:street":"Carrie Rd W",
    "iso:country":"CA",
    "sg:address":"322 Carrie Rd W",
    "sg:city":"Manitou",
    "sg:classifiers":[
        {
            "category":"Education",
            "subcategory":"School",
            "type":"Public Place"
        }
    ],
    "sg:phone":"+1 204 242 2640",
    "sg:postcode":"R0G 1G0",
    "sg:province":"MB",
    "wof:name":"Nellie Mc Clung Collegiate",
    "wof:placetype":"venue"
},
  "geometry": {"coordinates":[-98.53465300000001,49.236721],"type":"Point"}
}