{
  "type": "Feature",
  "properties": {
    "addr:full":"108 Main St Kelvington SK S0A 1W0",
    "addr:housenumber":"108",
    "addr:postcode":"s0a 1w0",
    "addr:street":"Main St",
    "iso:country":"CA",
    "sg:address":"108 Main St",
    "sg:city":"Kelvington",
    "sg:classifiers":[
        {
            "category":"Restaurant",
            "type":"Food & Drink"
        }
    ],
    "sg:phone":"+1 306 327 4438",
    "sg:postcode":"S0A 1W0",
    "sg:province":"SK",
    "wof:name":"Fran's Country Kitchen",
    "wof:placetype":"venue"
},
  "geometry": {"coordinates":[-103.529502869,52.16456604],"type":"Point"}
}