{
  "type": "Feature",
  "properties": {
    "iso:country":"CA",
    "sg:city":"Brampton",
    "sg:classifiers":[
        {
            "category":"Professional",
            "type":"Services"
        }
    ],
    "sg:phone":"+1 905 453 9142",
    "sg:postcode":"L6W 3T7",
    "sg:province":"ON",
    "sg:tags":[
        "arts",
        "artist"
    ],
    "wof:name":"Visual Arts Brampton",
    "wof:placetype":"venue"
},
  "geometry": {"coordinates":[-79.7348403931,43.6678085327],"type":"Point"}
}