{
  "type": "Feature",
  "properties": {
    "addr:full":"792 Broadway St Kincardine ON N2Z 2G1",
    "addr:housenumber":"792",
    "addr:postcode":"n2z 2g1",
    "addr:street":"Broadway St",
    "iso:country":"CA",
    "sg:address":"792 Broadway St",
    "sg:city":"Kincardine",
    "sg:classifiers":[
        {
            "category":"Cinema",
            "subcategory":"Movie Rental",
            "type":"Entertainment"
        }
    ],
    "sg:phone":"+1 519 396 6055",
    "sg:postcode":"N2Z 2G1",
    "sg:province":"ON",
    "sg:tags":[
        "leasing",
        "video",
        "disc",
        "tape"
    ],
    "wof:name":"Just New Releases",
    "wof:placetype":"venue"
},
  "geometry": {"coordinates":[-81.6157073975,44.1751365662],"type":"Point"}
}