{
  "type": "Feature",
  "properties": {
    "iso:country":"CA",
    "sg:address":"48 2E Rang Centre",
    "sg:city":"Trois-Pistoles",
    "sg:classifiers":[
        {
            "category":"Building & Trades",
            "subcategory":"Plumbing",
            "type":"Services"
        }
    ],
    "sg:phone":"+1 418 851 1577",
    "sg:postcode":"G0L 4K0",
    "sg:province":"QC",
    "sg:tags":[
        "contractor"
    ],
    "wof:name":"Plomberie Leclerc Enr",
    "wof:placetype":"venue"
},
  "geometry": {"coordinates":[-69.15808868409999,48.1146430969],"type":"Point"}
}