{
  "type": "Feature",
  "properties": {
    "iso:country":"CA",
    "sg:address":"625 Greenhill Ave",
    "sg:city":"Hamilton",
    "sg:classifiers":[
        {
            "category":"Shopping",
            "subcategory":"Department Store",
            "type":"Retail Goods"
        }
    ],
    "sg:phone":"+1 905 560 8963",
    "sg:postcode":"L8K 5W9",
    "sg:province":"ON",
    "sg:tags":[
        "shop"
    ],
    "wof:name":"Dollar Place",
    "wof:placetype":"venue"
},
  "geometry": {"coordinates":[-79.7866516113,43.2097396851],"type":"Point"}
}