{
  "type": "Feature",
  "properties": {
    "addr:full":"82589 London Rd Auburn ON N0M 1E0",
    "addr:housenumber":"82589",
    "addr:postcode":"n0m 1e0",
    "addr:street":"London Rd",
    "iso:country":"CA",
    "sg:address":"82589 London Rd",
    "sg:city":"Auburn",
    "sg:classifiers":[
        {
            "category":"Retail",
            "subcategory":"Auto Repair",
            "type":"Services"
        }
    ],
    "sg:phone":"+1 519 523 9726",
    "sg:postcode":"N0M 1E0",
    "sg:province":"ON",
    "sg:tags":[
        "body",
        "automobile",
        "painting"
    ],
    "wof:name":"Countryside Collision",
    "wof:placetype":"venue"
},
  "geometry": {"coordinates":[-81.53529399999999,43.774422],"type":"Point"}
}