{
  "type": "Feature",
  "properties": {
    "addr:full":"Saint-Leonard QC H1S 1V7",
    "addr:postcode":"h1s 1v7",
    "iso:country":"CA",
    "sg:city":"Saint-Leonard",
    "sg:classifiers":[
        {
            "category":"Shopping",
            "subcategory":"Clothing, Apparel, & Fashions",
            "type":"Retail Goods"
        }
    ],
    "sg:phone":"+1 514 251 0542",
    "sg:postcode":"H1S 1V7",
    "sg:province":"QC",
    "wof:name":"Boutique Sopa",
    "wof:placetype":"venue"
},
  "geometry": {"coordinates":[-73.5723190308,45.5915985107],"type":"Point"}
}