{
  "type": "Feature",
  "properties": {
    "iso:country":"CA",
    "sg:city":"Montreal",
    "sg:classifiers":[
        {
            "category":"Building & Trades",
            "subcategory":"Equipment Rental",
            "type":"Services"
        }
    ],
    "sg:phone":"+1 514 985 9391",
    "sg:postcode":"H2W 2R2",
    "sg:province":"QC",
    "sg:tags":[
        "party",
        "camping"
    ],
    "wof:name":"Gestion Mjm Scene Inc",
    "wof:placetype":"venue"
},
  "geometry": {"coordinates":[-73.582184,45.518108],"type":"Point"}
}