{
  "type": "Feature",
  "properties": {
    "addr:full":"245 Rue DE LA Montagne Montreal QC H3C 2A6",
    "addr:housenumber":"245",
    "addr:postcode":"h3c 2a6",
    "addr:street":"Rue De La Montagne",
    "iso:country":"CA",
    "sg:address":"245 Rue DE LA Montagne",
    "sg:city":"Montreal",
    "sg:classifiers":[
        {
            "category":"Retail",
            "subcategory":"Auto Repair",
            "type":"Services"
        }
    ],
    "sg:phone":"+1 514 932 1722",
    "sg:postcode":"H3C 2A6",
    "sg:province":"QC",
    "sg:tags":[
        "repairing",
        "automobile",
        "body"
    ],
    "wof:name":"Carrosserie & Radiateur Royal",
    "wof:placetype":"venue"
},
  "geometry": {"coordinates":[-73.56060791020001,45.492149353],"type":"Point"}
}