{
  "type": "Feature",
  "properties": {
    "addr:full":"4481 Alma St Amherstburg ON N9V 2Y9",
    "addr:housenumber":"4481",
    "addr:postcode":"n9v 2y9",
    "addr:street":"Alma St",
    "iso:country":"CA",
    "sg:address":"4481 Alma St",
    "sg:city":"Amherstburg",
    "sg:classifiers":[
        {
            "category":"Home & Garden",
            "subcategory":"Garden Supply",
            "type":"Retail Goods"
        }
    ],
    "sg:phone":"+1 519 736 4829",
    "sg:postcode":"N9V 2Y9",
    "sg:province":"ON",
    "sg:tags":[
        "nurseryman"
    ],
    "wof:name":"Paradise Nursery & Garden Ctr",
    "wof:placetype":"venue"
},
  "geometry": {"coordinates":[-83.05920399999999,42.109146],"type":"Point"}
}