{
  "type": "Feature",
  "properties": {
    "addr:full":"Red Deer AB T4N 6H3",
    "addr:postcode":"t4n 6h3",
    "iso:country":"CA",
    "sg:city":"Red Deer",
    "sg:classifiers":[
        {
            "category":"Personal",
            "subcategory":"Barber",
            "type":"Services"
        }
    ],
    "sg:phone":"+1 403 346 6984",
    "sg:postcode":"T4N 6H3",
    "sg:province":"AB",
    "sg:tags":[
        "salon",
        "beauty"
    ],
    "wof:name":"Adam & Eve Unisex Ctr Barbers",
    "wof:placetype":"venue"
},
  "geometry": {"coordinates":[-113.801552,52.28751],"type":"Point"}
}