{
  "type": "Feature",
  "properties": {
    "iso:country":"CA",
    "sg:address":"3425 Rue Masson",
    "sg:city":"Montreal",
    "sg:classifiers":[
        {
            "category":"Health Services",
            "subcategory":"Health Practitioner",
            "type":"Services"
        }
    ],
    "sg:phone":"+1 514 727 1176",
    "sg:postcode":"H1X 1R6",
    "sg:province":"QC",
    "sg:tags":[
        "physiotherapist"
    ],
    "wof:name":"Kinatex Sports Physio",
    "wof:placetype":"venue"
},
  "geometry": {"coordinates":[-73.572517,45.552322],"type":"Point"}
}