{
  "type": "Feature",
  "properties": {
    "addr:full":"St-Valerien QC J0H 2B0",
    "addr:postcode":"j0h 2b0",
    "iso:country":"CA",
    "sg:city":"St-Valerien",
    "sg:classifiers":[
        {
            "category":"Education",
            "subcategory":"Library",
            "type":"Public Place"
        }
    ],
    "sg:phone":"+1 450 549 2058",
    "sg:postcode":"J0H 2B0",
    "sg:province":"QC",
    "sg:tags":[
        "government"
    ],
    "wof:name":"St-Valerien Bibliotheque",
    "wof:placetype":"venue"
},
  "geometry": {"coordinates":[-68.67347717289999,48.3350715637],"type":"Point"}
}