{
  "type": "Feature",
  "properties": {
    "addr:full":"2435 Eagle St N Cambridge ON N3H 4R7",
    "addr:housenumber":"2435",
    "addr:postcode":"n3h 4r7",
    "addr:street":"Eagle St N",
    "iso:country":"CA",
    "sg:address":"2435 Eagle St N",
    "sg:city":"Cambridge",
    "sg:classifiers":[
        {
            "category":"Wholesale",
            "subcategory":"Auto Parts",
            "type":"Manufacturing & Wholesale Goods"
        }
    ],
    "sg:phone":"+1 519 653 8383",
    "sg:postcode":"N3H 4R7",
    "sg:province":"ON",
    "sg:tags":[
        "equipment",
        "towing"
    ],
    "wof:name":"Eagle Towing Equipment",
    "wof:placetype":"venue"
},
  "geometry": {"coordinates":[-80.3299789429,43.4075622559],"type":"Point"}
}