{
  "type": "Feature",
  "properties": {
    "addr:full":"PO Box 305 Madeira Park BC V0N 2H0",
    "addr:housenumber":"po",
    "addr:postcode":"v0n 2h0",
    "addr:street":"Box 305 Madeira Park",
    "iso:country":"CA",
    "sg:address":"PO Box 305",
    "sg:city":"Madeira Park",
    "sg:classifiers":[
        {
            "category":"Communications",
            "subcategory":"Film & Video Production",
            "type":"Services"
        }
    ],
    "sg:phone":"+1 604 883 9899",
    "sg:postcode":"V0N 2H0",
    "sg:province":"BC",
    "sg:tags":[
        "taping"
    ],
    "wof:name":"R Gregory & Assoc",
    "wof:placetype":"venue"
},
  "geometry": {"coordinates":[-124.02137,49.613037],"type":"Point"}
}