{
  "type": "Feature",
  "properties": {
    "iso:country":"CA",
    "sg:address":"6400 Boul Monk",
    "sg:city":"Montreal",
    "sg:classifiers":[
        {
            "category":"Food & Beverages",
            "subcategory":"Groceries & Convenience Stores",
            "type":"Retail Goods"
        }
    ],
    "sg:phone":"+1 514 768 3441",
    "sg:postcode":"H4E 3H9",
    "sg:province":"QC",
    "sg:tags":[
        "grocer"
    ],
    "wof:name":"Marche Gregoire Inc",
    "wof:placetype":"venue"
},
  "geometry": {"coordinates":[-73.594429,45.454781],"type":"Point"}
}