{
  "type": "Feature",
  "properties": {
    "addr:full":"2144 Rue DE LA Province Longueuil QC J4G 1R7",
    "addr:housenumber":"2144",
    "addr:postcode":"j4g 1r7",
    "addr:street":"Rue De La Province",
    "iso:country":"CA",
    "sg:address":"2144 Rue DE LA Province",
    "sg:city":"Longueuil",
    "sg:classifiers":[
        {
            "category":"Professional",
            "type":"Services"
        }
    ],
    "sg:phone":"+1 450 442 4450",
    "sg:postcode":"J4G 1R7",
    "sg:province":"QC",
    "sg:tags":[
        "equipment",
        "establishment",
        "butcher",
        "supply"
    ],
    "wof:name":"Lumar Ideal Ll Inc",
    "wof:placetype":"venue"
},
  "geometry": {"coordinates":[-73.471474,45.564732],"type":"Point"}
}