{
  "type": "Feature",
  "properties": {
    "addr:full":"Whistler BC V0N 1B1",
    "addr:postcode":"v0n 1b1",
    "iso:country":"CA",
    "sg:city":"Whistler",
    "sg:classifiers":[
        {
            "category":"Building & Trades",
            "subcategory":"Construction",
            "type":"Services"
        }
    ],
    "sg:phone":"+1 604 938 0688",
    "sg:postcode":"V0N 1B1",
    "sg:province":"BC",
    "sg:tags":[
        "general",
        "contractor"
    ],
    "wof:name":"Peak Ventures",
    "wof:placetype":"venue"
},
  "geometry": {"coordinates":[-123.038437,50.087761],"type":"Point"}
}