{
  "type": "Feature",
  "properties": {
    "addr:full":"2101 Av Dollard Lasalle QC H8N 1S2",
    "addr:housenumber":"2101",
    "addr:postcode":"h8n 1s2",
    "addr:street":"Av Dollard",
    "iso:country":"CA",
    "sg:address":"2101 Av Dollard",
    "sg:city":"Lasalle",
    "sg:classifiers":[
        {
            "category":"Shopping",
            "subcategory":"Gifts & Souvenirs",
            "type":"Retail Goods"
        }
    ],
    "sg:phone":"+1 514 365 7337",
    "sg:postcode":"H8N 1S2",
    "sg:province":"QC",
    "sg:tags":[
        "shop",
        "party",
        "fabric",
        "supply"
    ],
    "wof:name":"Bou Clair Inc",
    "wof:placetype":"venue"
},
  "geometry": {"coordinates":[-73.63506317140001,45.4310035706],"type":"Point"}
}