{
  "type": "Feature",
  "properties": {
    "addr:full":"Windsor NS B0N 2T0",
    "addr:postcode":"b0n 2t0",
    "iso:country":"CA",
    "sg:city":"Windsor",
    "sg:classifiers":[
        {
            "category":"Retail",
            "subcategory":"Veterinary Services",
            "type":"Services"
        }
    ],
    "sg:phone":"+1 902 798 4633",
    "sg:postcode":"B0N 2T0",
    "sg:province":"NS",
    "sg:tags":[
        "veterinarian"
    ],
    "wof:name":"Avon Animal Hospital",
    "wof:placetype":"venue"
},
  "geometry": {"coordinates":[-64.11103799999999,44.991051],"type":"Point"}
}