{
  "type": "Feature",
  "properties": {
    "addr:full":"Rock Forest QC J1N 2P7",
    "addr:postcode":"j1n 2p7",
    "iso:country":"CA",
    "sg:city":"Rock Forest",
    "sg:classifiers":[
        {
            "category":"Personal",
            "subcategory":"Tanning Parlor",
            "type":"Services"
        }
    ],
    "sg:phone":"+1 819 864 0505",
    "sg:postcode":"J1N 2P7",
    "sg:province":"QC",
    "sg:tags":[
        "salon"
    ],
    "wof:name":"Bronzage Guylaine",
    "wof:placetype":"venue"
},
  "geometry": {"coordinates":[-71.9940567017,45.3637771606],"type":"Point"}
}