{
  "type": "Feature",
  "properties": {
    "addr:full":"311 Poplar Churchbridge SK S0A 0M0",
    "addr:housenumber":"311",
    "addr:postcode":"s0a 0m0",
    "addr:street":"Poplar Churchbridge",
    "iso:country":"CA",
    "sg:address":"311 Poplar",
    "sg:city":"Churchbridge",
    "sg:classifiers":[
        {
            "category":"Organizations",
            "subcategory":"Religious Organization",
            "type":"Services"
        }
    ],
    "sg:phone":"+1 306 372 5451",
    "sg:postcode":"S0A 0M0",
    "sg:province":"SK",
    "sg:tags":[
        "church"
    ],
    "wof:name":"Concordia Lutheran Church",
    "wof:placetype":"venue"
},
  "geometry": {"coordinates":[-101.89769699999999,50.897385],"type":"Point"}
}