{
  "type": "Feature",
  "properties": {
    "addr:full":"32 Rue Notre-Dame N Louiseville QC J5V 1X5",
    "addr:housenumber":"32",
    "addr:postcode":"j5v 1x5",
    "addr:street":"Rue Notre-Dame N",
    "iso:country":"CA",
    "sg:address":"32 Rue Notre-Dame N",
    "sg:city":"Louiseville",
    "sg:classifiers":[
        {
            "category":"Freight",
            "type":"Transportation"
        }
    ],
    "sg:phone":"+1 819 228 2464",
    "sg:postcode":"J5V 1X5",
    "sg:province":"QC",
    "sg:tags":[
        "taxicab",
        "trucking"
    ],
    "wof:name":"Desaulniers Taxi",
    "wof:placetype":"venue"
},
  "geometry": {"coordinates":[-72.93944500000001,46.256557],"type":"Point"}
}