{
  "type": "Feature",
  "properties": {
    "addr:full":"2 Huron Rd E Shakespeare ON N0B 2P0",
    "addr:housenumber":"2",
    "addr:postcode":"n0b 2p0",
    "addr:street":"Huron Rd E Shakespeare",
    "iso:country":"CA",
    "sg:address":"2 Huron Rd E",
    "sg:city":"Shakespeare",
    "sg:classifiers":[
        {
            "category":"Organizations",
            "subcategory":"Religious Organization",
            "type":"Services"
        }
    ],
    "sg:phone":"+1 519 625 8317",
    "sg:postcode":"N0B 2P0",
    "sg:province":"ON",
    "sg:tags":[
        "church"
    ],
    "wof:name":"Shakespeare Presbyterian Chr",
    "wof:placetype":"venue"
},
  "geometry": {"coordinates":[-80.83023834230001,43.3695297241],"type":"Point"}
}