{
  "type": "Feature",
  "properties": {
    "addr:full":"1595 Bedford Hwy Bedford NS B4A 3Y4",
    "addr:housenumber":"1595",
    "addr:postcode":"b4a 3y4",
    "addr:street":"Bedford Hwy",
    "iso:country":"CA",
    "sg:address":"1595 Bedford Hwy",
    "sg:city":"Bedford",
    "sg:classifiers":[
        {
            "category":"Shopping",
            "subcategory":"Clothing, Apparel, & Fashions",
            "type":"Retail Goods"
        }
    ],
    "sg:phone":"+1 902 832 3515",
    "sg:postcode":"B4A 3Y4",
    "sg:province":"NS",
    "wof:name":"Garage Clothing CO",
    "wof:placetype":"venue"
},
  "geometry": {"coordinates":[-63.6559715271,44.7327804565],"type":"Point"}
}