{
  "type": "Feature",
  "properties": {
    "iso:country":"CA",
    "sg:address":"82 Westheights Dr",
    "sg:city":"Kitchener",
    "sg:classifiers":[
        {
            "category":"Organizations",
            "subcategory":"Religious Organization",
            "type":"Services"
        }
    ],
    "sg:phone":"+1 519 741 1986",
    "sg:postcode":"N2N 2A8",
    "sg:province":"ON",
    "sg:tags":[
        "church"
    ],
    "wof:name":"Westheights Brethren in Christ",
    "wof:placetype":"venue"
},
  "geometry": {"coordinates":[-80.5298,43.42741],"type":"Point"}
}