{
  "type": "Feature",
  "properties": {
    "iso:country":"CA",
    "sg:address":"1821 Marine Dr",
    "sg:city":"West Vancouver",
    "sg:classifiers":[
        {
            "category":"Shopping",
            "subcategory":"Florist",
            "type":"Retail Goods"
        }
    ],
    "sg:phone":"+1 604 922 4171",
    "sg:postcode":"V7V 1J7",
    "sg:province":"BC",
    "wof:name":"West Van Florist Ltd",
    "wof:placetype":"venue"
},
  "geometry": {"coordinates":[-123.16278839100001,49.3287620544],"type":"Point"}
}