{
  "type": "Feature",
  "properties": {
    "addr:full":"125 Bay St Embrun ON K0A 1W1",
    "addr:housenumber":"125",
    "addr:postcode":"k0a 1w1",
    "addr:street":"Bay St",
    "iso:country":"CA",
    "sg:address":"125 Bay St",
    "sg:city":"Embrun",
    "sg:classifiers":[
        {
            "category":"Personal",
            "type":"Services"
        }
    ],
    "sg:phone":"+1 613 443 3030",
    "sg:postcode":"K0A 1W1",
    "sg:province":"ON",
    "sg:tags":[
        "program",
        "physical",
        "exercise",
        "fitness"
    ],
    "wof:name":"Norm's Gym",
    "wof:placetype":"venue"
},
  "geometry": {"coordinates":[-75.30777,45.269531],"type":"Point"}
}