{
  "type": "Feature",
  "properties": {
    "addr:full":"265 Boul Lebeau Saint-Laurent QC H4N 3H8",
    "addr:housenumber":"265",
    "addr:postcode":"h4n 3h8",
    "addr:street":"Boul Lebeau",
    "iso:country":"CA",
    "sg:address":"265 Boul Lebeau",
    "sg:city":"Saint-Laurent",
    "sg:classifiers":[
        {
            "category":"Manufacturing",
            "subcategory":"Apparel",
            "type":"Manufacturing & Wholesale Goods"
        }
    ],
    "sg:phone":"+1 514 334 1265",
    "sg:postcode":"H4N 3H8",
    "sg:province":"QC",
    "sg:tags":[
        "clothing"
    ],
    "wof:name":"In-Wear Canada",
    "wof:placetype":"venue"
},
  "geometry": {"coordinates":[-73.65692901609999,45.5255622864],"type":"Point"}
}