{
  "type": "Feature",
  "properties": {
    "addr:full":"North York ON M3J 2B9",
    "addr:postcode":"m3j 2b9",
    "iso:country":"CA",
    "sg:city":"North York",
    "sg:classifiers":[
        {
            "category":"Manufacturing",
            "subcategory":"Furniture",
            "type":"Manufacturing & Wholesale Goods"
        }
    ],
    "sg:phone":"+1 416 633 4567",
    "sg:postcode":"M3J 2B9",
    "sg:province":"ON",
    "wof:name":"Vitalia Sofa Design Inc",
    "wof:placetype":"venue"
},
  "geometry": {"coordinates":[-79.47685199999999,43.764503],"type":"Point"}
}