{
  "type": "Feature",
  "properties": {
    "addr:full":"821 Twelfth St New Westminster BC V3M 4K2",
    "addr:housenumber":"821",
    "addr:postcode":"v3m 4k2",
    "addr:street":"Twelfth St",
    "iso:country":"CA",
    "sg:address":"821 Twelfth St",
    "sg:city":"New Westminster",
    "sg:classifiers":[
        {
            "category":"Restaurant",
            "type":"Food & Drink"
        }
    ],
    "sg:phone":"+1 604 524 2812",
    "sg:postcode":"V3M 4K2",
    "sg:province":"BC",
    "wof:name":"Mom's Cafe",
    "wof:placetype":"venue"
},
  "geometry": {"coordinates":[-122.934967,49.211281],"type":"Point"}
}