{
  "type": "Feature",
  "properties": {
    "addr:full":"Langley BC V1M 2N9",
    "addr:postcode":"v1m 2n9",
    "iso:country":"CA",
    "sg:city":"Langley",
    "sg:classifiers":[
        {
            "category":"Restaurant",
            "type":"Food & Drink"
        }
    ],
    "sg:phone":"+1 604 882 7362",
    "sg:postcode":"V1M 2N9",
    "sg:province":"BC",
    "wof:name":"Taco Time",
    "wof:placetype":"venue"
},
  "geometry": {"coordinates":[-122.664260864,49.1637535095],"type":"Point"}
}