{
  "type": "Feature",
  "properties": {
    "addr:full":"2366 Dougall Ave Windsor ON N8X 1T1",
    "addr:housenumber":"2366",
    "addr:postcode":"n8x 1t1",
    "addr:street":"Dougall Ave",
    "iso:country":"CA",
    "sg:address":"2366 Dougall Ave",
    "sg:city":"Windsor",
    "sg:classifiers":[
        {
            "category":"Shopping",
            "subcategory":"Musical Instruments",
            "type":"Retail Goods"
        }
    ],
    "sg:phone":"+1 519 258 6160",
    "sg:postcode":"N8X 1T1",
    "sg:province":"ON",
    "wof:name":"Leone's Music World",
    "wof:placetype":"venue"
},
  "geometry": {"coordinates":[-83.0243606567,42.2894935608],"type":"Point"}
}