{
  "type": "Feature",
  "properties": {
    "addr:full":"Edmonton AB T5J 2T2",
    "addr:postcode":"t5j 2t2",
    "iso:country":"CA",
    "sg:city":"Edmonton",
    "sg:classifiers":[
        {
            "category":"Retail",
            "subcategory":"Auto Rental",
            "type":"Services"
        }
    ],
    "sg:phone":"+1 780 890 7596",
    "sg:postcode":"T5J 2T2",
    "sg:province":"AB",
    "sg:tags":[
        "renting",
        "automobile"
    ],
    "wof:name":"Avis Rent A Car",
    "wof:placetype":"venue"
},
  "geometry": {"coordinates":[-113.490371704,53.5462188721],"type":"Point"}
}