{
  "type": "Feature",
  "properties": {
    "addr:full":"160 Dundas St W Belleville ON K8P 1A6",
    "addr:housenumber":"160",
    "addr:postcode":"k8p 1a6",
    "addr:street":"Dundas St W",
    "iso:country":"CA",
    "sg:address":"160 Dundas St W",
    "sg:city":"Belleville",
    "sg:classifiers":[
        {
            "category":"Education",
            "subcategory":"School",
            "type":"Public Place"
        }
    ],
    "sg:phone":"+1 613 968 5726",
    "sg:postcode":"K8P 1A6",
    "sg:province":"ON",
    "wof:name":"Albert College",
    "wof:placetype":"venue"
},
  "geometry": {"coordinates":[-77.393196106,44.1549186707],"type":"Point"}
}