{
  "type": "Feature",
  "properties": {
    "addr:full":"Lot 11 112th St E High River AB T1V 1P6",
    "addr:postcode":"t1v 1p6",
    "addr:street":"112Th St E",
    "iso:country":"CA",
    "sg:address":"Lot 11 112th St E",
    "sg:city":"High River",
    "sg:classifiers":[
        {
            "category":"Wholesale",
            "subcategory":"Machinery & Supplies",
            "type":"Manufacturing & Wholesale Goods"
        }
    ],
    "sg:phone":"+1 403 652 1410",
    "sg:postcode":"T1V 1P6",
    "sg:province":"AB",
    "sg:tags":[
        "farm",
        "equipment"
    ],
    "wof:name":"High River New Holland Ltd",
    "wof:placetype":"venue"
},
  "geometry": {"coordinates":[-113.85912322999999,50.577999115],"type":"Point"}
}