{
  "type": "Feature",
  "properties": {
    "addr:full":"3 Newcastle St Minden ON K0M 2K0",
    "addr:housenumber":"3",
    "addr:postcode":"k0m 2k0",
    "addr:street":"Newcastle St",
    "iso:country":"CA",
    "sg:address":"3 Newcastle St",
    "sg:city":"Minden",
    "sg:classifiers":[
        {
            "category":"Real Estate",
            "subcategory":"Surveying",
            "type":"Services"
        }
    ],
    "sg:phone":"+1 705 286 1768",
    "sg:postcode":"K0M 2K0",
    "sg:province":"ON",
    "sg:tags":[
        "surveyor"
    ],
    "wof:name":"Paul Wilson Surveying Ltd",
    "wof:placetype":"venue"
},
  "geometry": {"coordinates":[-78.72365600000001,44.924835],"type":"Point"}
}