{
  "type": "Feature",
  "properties": {
    "addr:full":"310 Stouffville Rd Richmond Hill ON L4E 3P4",
    "addr:housenumber":"310",
    "addr:postcode":"l4e 3p4",
    "addr:street":"Stouffville Rd",
    "iso:country":"CA",
    "sg:address":"310 Stouffville Rd",
    "sg:city":"Richmond Hill",
    "sg:classifiers":[
        {
            "category":"Wholesale",
            "subcategory":"Stationery",
            "type":"Manufacturing & Wholesale Goods"
        }
    ],
    "sg:phone":"+1 905 773 4000",
    "sg:postcode":"L4E 3P4",
    "sg:province":"ON",
    "sg:tags":[
        "business",
        "form",
        "system"
    ],
    "wof:name":"Safeguard Business Systems",
    "wof:placetype":"venue"
},
  "geometry": {"coordinates":[-79.4393997192,43.9286499023],"type":"Point"}
}