{
  "type": "Feature",
  "properties": {
    "addr:full":"Devlin ON P0W 1C0",
    "addr:postcode":"p0w 1c0",
    "iso:country":"CA",
    "sg:city":"Devlin",
    "sg:classifiers":[
        {
            "category":"Social Services",
            "subcategory":"Child Care",
            "type":"Services"
        }
    ],
    "sg:phone":"+1 807 486 1264",
    "sg:postcode":"P0W 1C0",
    "sg:province":"ON",
    "wof:name":"Country View Child Care",
    "wof:placetype":"venue"
},
  "geometry": {"coordinates":[-93.670776,48.656284],"type":"Point"}
}