{
  "type": "Feature",
  "properties": {
    "addr:full":"104 Timber Dr Nipawin SK S0E 1E0",
    "addr:housenumber":"104",
    "addr:postcode":"s0e 1e0",
    "addr:street":"Timber Dr Nipawin",
    "iso:country":"CA",
    "sg:address":"104 Timber Dr",
    "sg:city":"Nipawin",
    "sg:classifiers":[
        {
            "category":"Autos & Motor Vehicles",
            "subcategory":"Motorcycle Sales",
            "type":"Retail Goods"
        }
    ],
    "sg:phone":"+1 306 862 5538",
    "sg:postcode":"S0E 1E0",
    "sg:province":"SK",
    "sg:tags":[
        "all",
        "terrain",
        "snowmobile"
    ],
    "wof:name":"Seasons Edge Recreation",
    "wof:placetype":"venue"
},
  "geometry": {"coordinates":[-104.02628300000001,53.356743],"type":"Point"}
}