{
  "type": "Feature",
  "properties": {
    "addr:full":"1650 Rte DE Fossambault Saint-Augustin-DE-Desmaures QC G3A 1W8",
    "addr:housenumber":"1650",
    "addr:postcode":"g3a 1w8",
    "addr:street":"Rte De Fossambault",
    "iso:country":"CA",
    "sg:address":"1650 Rte DE Fossambault",
    "sg:city":"Saint-Augustin-DE-Desmaures",
    "sg:classifiers":[
        {
            "category":"Retail",
            "subcategory":"Auto Repair",
            "type":"Services"
        }
    ],
    "sg:phone":"+1 418 878 2925",
    "sg:postcode":"G3A 1W8",
    "sg:province":"QC",
    "sg:tags":[
        "repairing",
        "automobile"
    ],
    "wof:name":"Garage Gingras",
    "wof:placetype":"venue"
},
  "geometry": {"coordinates":[-71.518005,46.776051],"type":"Point"}
}