{
  "type": "Feature",
  "properties": {
    "addr:full":"600 Eagleson Rd Kanata ON K2M 1H4",
    "addr:housenumber":"600",
    "addr:postcode":"k2m 1h4",
    "addr:street":"Eagleson Rd",
    "iso:country":"CA",
    "sg:address":"600 Eagleson Rd",
    "sg:city":"Kanata",
    "sg:classifiers":[
        {
            "category":"Building & Trades",
            "subcategory":"Construction",
            "type":"Services"
        }
    ],
    "sg:phone":"+1 613 591 8814",
    "sg:postcode":"K2M 1H4",
    "sg:province":"ON",
    "sg:tags":[
        "cabinet",
        "maker",
        "woodworker"
    ],
    "wof:name":"Habib Custom Woodwork Ltd",
    "wof:placetype":"venue"
},
  "geometry": {"coordinates":[-75.869232,45.289619],"type":"Point"}
}