{
  "type": "Feature",
  "properties": {
    "addr:full":"Petrolia ON N0N 1R0",
    "addr:postcode":"n0n 1r0",
    "iso:country":"CA",
    "sg:city":"Petrolia",
    "sg:classifiers":[
        {
            "category":"Home & Garden",
            "subcategory":"Building Materials",
            "type":"Retail Goods"
        }
    ],
    "sg:phone":"+1 519 882 3330",
    "sg:postcode":"N0N 1R0",
    "sg:province":"ON",
    "sg:tags":[
        "glass",
        "window",
        "plate"
    ],
    "wof:name":"Color Craft Auto Glass",
    "wof:placetype":"venue"
},
  "geometry": {"coordinates":[-82.123955,42.884148],"type":"Point"}
}