{
  "type": "Feature",
  "properties": {
    "iso:country":"CA",
    "sg:address":"2500 Lake Bonavista Dr SE",
    "sg:city":"Calgary",
    "sg:classifiers":[
        {
            "category":"Education",
            "subcategory":"School",
            "type":"Public Place"
        }
    ],
    "sg:phone":"+1 403 777 7720",
    "sg:postcode":"T2J 2Y6",
    "sg:province":"AB",
    "wof:name":"Nickle Junior High School",
    "wof:placetype":"venue"
},
  "geometry": {"coordinates":[-114.061149597,50.9410705566],"type":"Point"}
}