{
  "type": "Feature",
  "properties": {
    "addr:full":"627 St George St Port Dover ON N0A 1N0",
    "addr:housenumber":"627",
    "addr:postcode":"n0a 1n0",
    "addr:street":"St George St Port Dover",
    "iso:country":"CA",
    "sg:address":"627 St George St",
    "sg:city":"Port Dover",
    "sg:classifiers":[
        {
            "category":"Health Services",
            "subcategory":"Chiropractor",
            "type":"Services"
        }
    ],
    "sg:phone":"+1 519 583 2880",
    "sg:postcode":"N0A 1N0",
    "sg:province":"ON",
    "wof:name":"Port Dover Chiropractic Clinic",
    "wof:placetype":"venue"
},
  "geometry": {"coordinates":[-80.21026611329999,42.7897567749],"type":"Point"}
}