{
  "type": "Feature",
  "properties": {
    "addr:full":"336 Dundas St W #201 Toronto ON M5T 1G5",
    "addr:housenumber":"336",
    "addr:postcode":"m5t 1g5",
    "addr:street":"Dundas St W # 201",
    "iso:country":"CA",
    "sg:address":"336 Dundas St W #201",
    "sg:city":"Toronto",
    "sg:classifiers":[
        {
            "category":"Health Services",
            "subcategory":"Doctor",
            "type":"Services"
        }
    ],
    "sg:phone":"+1 416 971 7311",
    "sg:postcode":"M5T 1G5",
    "sg:province":"ON",
    "sg:tags":[
        "dentist"
    ],
    "wof:name":"Wang, Richard DDS",
    "wof:placetype":"venue"
},
  "geometry": {"coordinates":[-79.3927078247,43.6541786194],"type":"Point"}
}