{
  "type": "Feature",
  "properties": {
    "addr:full":"45 Robertson Rd Nepean ON K2H 5Y9",
    "addr:housenumber":"45",
    "addr:postcode":"k2h 5y9",
    "addr:street":"Robertson Rd",
    "iso:country":"CA",
    "sg:address":"45 Robertson Rd",
    "sg:city":"Nepean",
    "sg:classifiers":[
        {
            "category":"Restaurant",
            "type":"Food & Drink"
        }
    ],
    "sg:phone":"+1 613 820 8660",
    "sg:postcode":"K2H 5Y9",
    "sg:province":"ON",
    "wof:name":"Burger King",
    "wof:placetype":"venue"
},
  "geometry": {"coordinates":[-75.8304901123,45.3233566284],"type":"Point"}
}