{
  "type": "Feature",
  "properties": {
    "addr:full":"51 Beverly Hills Dr North York ON M3L 1A2",
    "addr:housenumber":"51",
    "addr:postcode":"m3l 1a2",
    "addr:street":"Beverly Hills Dr",
    "iso:country":"CA",
    "sg:address":"51 Beverly Hills Dr",
    "sg:city":"North York",
    "sg:classifiers":[
        {
            "category":"Shopping",
            "subcategory":"Musical Instruments",
            "type":"Retail Goods"
        }
    ],
    "sg:phone":"+1 416 247 2910",
    "sg:postcode":"M3L 1A2",
    "sg:province":"ON",
    "wof:name":"Ontario Academy of Music",
    "wof:placetype":"venue"
},
  "geometry": {"coordinates":[-79.51293200000001,43.717827],"type":"Point"}
}