{
  "type": "Feature",
  "properties": {
    "iso:country":"CA",
    "sg:city":"Louiseville",
    "sg:classifiers":[
        {
            "category":"Retail",
            "subcategory":"Laundry & Dry Cleaning",
            "type":"Services"
        }
    ],
    "sg:phone":"+1 819 228 9901",
    "sg:postcode":"J5V 2H1",
    "sg:province":"QC",
    "sg:tags":[
        "cleaners",
        "rug",
        "carpet"
    ],
    "wof:name":"Nettoyage Marc Dalcourt",
    "wof:placetype":"venue"
},
  "geometry": {"coordinates":[-72.95038599999999,46.255257],"type":"Point"}
}