{
  "type": "Feature",
  "properties": {
    "addr:full":"43 Fulbert Cres Scarborough ON M1S 1C5",
    "addr:housenumber":"43",
    "addr:postcode":"m1s 1c5",
    "addr:street":"Fulbert Cres",
    "iso:country":"CA",
    "sg:address":"43 Fulbert Cres",
    "sg:city":"Scarborough",
    "sg:classifiers":[
        {
            "category":"Wholesale",
            "subcategory":"Machinery & Supplies",
            "type":"Manufacturing & Wholesale Goods"
        }
    ],
    "sg:phone":"+1 416 292 2859",
    "sg:postcode":"M1S 1C5",
    "sg:province":"ON",
    "sg:tags":[
        "machine",
        "tool"
    ],
    "wof:name":"M Jahn Machine Tools Inc",
    "wof:placetype":"venue"
},
  "geometry": {"coordinates":[-79.28903200000001,43.789978],"type":"Point"}
}