{
  "type": "Feature",
  "properties": {
    "iso:country":"CA",
    "sg:address":"2155 Lawrence Ave E",
    "sg:city":"Scarborough",
    "sg:classifiers":[
        {
            "category":"Real Estate",
            "subcategory":"Real Estate Operator",
            "type":"Services"
        }
    ],
    "sg:phone":"+1 416 285 5447",
    "sg:postcode":"M1R 5G9",
    "sg:province":"ON",
    "sg:tags":[
        "apartment"
    ],
    "wof:name":"Aldebrain Attendant Care Svc",
    "wof:placetype":"venue"
},
  "geometry": {"coordinates":[-79.2851867676,43.7472877502],"type":"Point"}
}