{
  "type": "Feature",
  "properties": {
    "addr:full":"140 Mackenzie Ave N Williams Lake BC V2G 1N6",
    "addr:housenumber":"140",
    "addr:postcode":"v2g 1n6",
    "addr:street":"Mackenzie Ave N",
    "iso:country":"CA",
    "sg:address":"140 Mackenzie Ave N",
    "sg:city":"Williams Lake",
    "sg:classifiers":[
        {
            "category":"Autos & Motor Vehicles",
            "subcategory":"Motorcycle Sales",
            "type":"Retail Goods"
        }
    ],
    "sg:phone":"+1 250 392 2528",
    "sg:postcode":"V2G 1N6",
    "sg:province":"BC",
    "sg:tags":[
        "all",
        "terrain"
    ],
    "wof:name":"Rosk Yamaha",
    "wof:placetype":"venue"
},
  "geometry": {"coordinates":[-122.146942,52.13044],"type":"Point"}
}