{
  "type": "Feature",
  "properties": {
    "addr:full":"Williams Lake BC V2G 2X5",
    "addr:postcode":"bc v2g 2x5",
    "iso:country":"CA",
    "sg:city":"Williams Lake",
    "sg:classifiers":[
        {
            "category":"Retail",
            "subcategory":"Animal Services",
            "type":"Services"
        }
    ],
    "sg:phone":"+1 250 392 3034",
    "sg:postcode":"V2G 2X5",
    "sg:province":"BC",
    "sg:tags":[
        "pet",
        "grooming",
        "washing"
    ],
    "wof:name":"Sherry's Furry Fashions Grmng",
    "wof:placetype":"venue"
},
  "geometry": {"coordinates":[-122.11170959499999,52.1238746643],"type":"Point"}
}