{
  "type": "Feature",
  "properties": {
    "addr:full":"1320 Wilton Ave London ON N5W 2H6",
    "addr:housenumber":"1320",
    "addr:postcode":"n5w 2h6",
    "addr:street":"Wilton Ave",
    "iso:country":"CA",
    "sg:address":"1320 Wilton Ave",
    "sg:city":"London",
    "sg:classifiers":[
        {
            "category":"Organizations",
            "subcategory":"Religious Organization",
            "type":"Services"
        }
    ],
    "sg:phone":"+1 519 455 8160",
    "sg:postcode":"N5W 2H6",
    "sg:province":"ON",
    "sg:tags":[
        "church"
    ],
    "wof:name":"St Mark's Church",
    "wof:placetype":"venue"
},
  "geometry": {"coordinates":[-81.19971466059999,42.9913330078],"type":"Point"}
}