{
  "type": "Feature",
  "properties": {
    "addr:full":"995 Arena Rd Winnipeg MB R3G 3H7",
    "addr:housenumber":"995",
    "addr:postcode":"r3g 3h7",
    "addr:street":"Arena Rd",
    "iso:country":"CA",
    "sg:address":"995 Arena Rd",
    "sg:city":"Winnipeg",
    "sg:classifiers":[
        {
            "category":"Home & Garden",
            "subcategory":"Building Materials",
            "type":"Retail Goods"
        }
    ],
    "sg:phone":"+1 204 958 7100",
    "sg:postcode":"R3G 3H7",
    "sg:province":"MB",
    "sg:tags":[
        "paint"
    ],
    "wof:name":"Ici Glidden CO",
    "wof:placetype":"venue"
},
  "geometry": {"coordinates":[-97.197952,49.893761],"type":"Point"}
}