{
  "type": "Feature",
  "properties": {
    "addr:full":"121 Boul Springer Chapais QC G0W 1H0",
    "addr:housenumber":"121",
    "addr:postcode":"g0w 1h0",
    "addr:street":"Boul Springer",
    "iso:country":"CA",
    "sg:address":"121 Boul Springer",
    "sg:city":"Chapais",
    "sg:classifiers":[
        {
            "category":"Organizations",
            "subcategory":"Professional Association",
            "type":"Services"
        }
    ],
    "sg:phone":"+1 418 745 4012",
    "sg:postcode":"G0W 1H0",
    "sg:province":"QC",
    "wof:name":"Centre DE Femmes Les",
    "wof:placetype":"venue"
},
  "geometry": {"coordinates":[-74.8554534912,49.7821731567],"type":"Point"}
}