{
  "type": "Feature",
  "properties": {
    "addr:full":"397 Rue Dufferin Granby QC J2G 4Y3",
    "addr:housenumber":"397",
    "addr:postcode":"j2g 4y3",
    "addr:street":"Rue Dufferin",
    "iso:country":"CA",
    "sg:address":"397 Rue Dufferin",
    "sg:city":"Granby",
    "sg:classifiers":[
        {
            "category":"Insurance",
            "subcategory":"Insurance Agent",
            "type":"Services"
        }
    ],
    "sg:phone":"+1 450 378 4813",
    "sg:postcode":"J2G 4Y3",
    "sg:province":"QC",
    "wof:name":"Assur Experts Luc Perrier Inc",
    "wof:placetype":"venue"
},
  "geometry": {"coordinates":[-72.7178192139,45.4160614014],"type":"Point"}
}