{
  "type": "Feature",
  "properties": {
    "addr:full":"Salaberry-DE-Valleyfield QC J6T 6L4",
    "addr:postcode":"j6t 6l4",
    "iso:country":"CA",
    "sg:city":"Salaberry-DE-Valleyfield",
    "sg:classifiers":[
        {
            "category":"Freight",
            "type":"Transportation"
        }
    ],
    "sg:phone":"+1 450 373 4021",
    "sg:postcode":"J6T 6L4",
    "sg:province":"QC",
    "sg:tags":[
        "trucking"
    ],
    "wof:name":"Societe Du Port DE Valleyfield",
    "wof:placetype":"venue"
},
  "geometry": {"coordinates":[-74.092628,45.229214],"type":"Point"}
}