{
  "type": "Feature",
  "properties": {
    "addr:full":"860 Fairville Blvd Saint John NB E2M 5T5",
    "addr:housenumber":"860",
    "addr:postcode":"e2m 5t5",
    "addr:street":"Fairville Blvd",
    "iso:country":"CA",
    "sg:address":"860 Fairville Blvd",
    "sg:city":"Saint John",
    "sg:classifiers":[
        {
            "category":"Retail",
            "subcategory":"Auto Repair",
            "type":"Services"
        }
    ],
    "sg:phone":"+1 506 674 9630",
    "sg:postcode":"E2M 5T5",
    "sg:province":"NB",
    "sg:tags":[
        "repairing",
        "automobile",
        "tire"
    ],
    "wof:name":"Coast Tire Svc Ltd",
    "wof:placetype":"venue"
},
  "geometry": {"coordinates":[-66.103165,45.249344],"type":"Point"}
}