{
  "type": "Feature",
  "properties": {
    "addr:full":"Gatineau QC J8T 4H2",
    "addr:postcode":"j8t 4h2",
    "iso:country":"CA",
    "sg:city":"Gatineau",
    "sg:classifiers":[
        {
            "category":"Retail",
            "subcategory":"Animal Services",
            "type":"Services"
        }
    ],
    "sg:phone":"+1 819 243 8555",
    "sg:postcode":"J8T 4H2",
    "sg:province":"QC",
    "sg:tags":[
        "pet",
        "grooming",
        "washing"
    ],
    "wof:name":"Studio Belle Bete",
    "wof:placetype":"venue"
},
  "geometry": {"coordinates":[-75.7104873657,45.4278526306],"type":"Point"}
}