{
  "type": "Feature",
  "properties": {
    "addr:full":"1 Court House Sq Brockville ON K6V 3X2",
    "addr:housenumber":"1",
    "addr:postcode":"k6v 3x2",
    "addr:street":"Court House Sq",
    "iso:country":"CA",
    "sg:address":"1 Court House Sq",
    "sg:city":"Brockville",
    "sg:classifiers":[
        {
            "category":"Banks & Credit Unions",
            "subcategory":"Investment Brokerage",
            "type":"Services"
        }
    ],
    "sg:phone":"+1 613 498 2228",
    "sg:postcode":"K6V 3X2",
    "sg:province":"ON",
    "wof:name":"Bmo Nesbitt Burns Inc",
    "wof:placetype":"venue"
},
  "geometry": {"coordinates":[-75.685226,44.590893],"type":"Point"}
}