{
  "type": "Feature",
  "properties": {
    "addr:full":"1720 20th Ave Nanton AB T0L 1R0",
    "addr:housenumber":"1720",
    "addr:postcode":"t0l 1r0",
    "addr:street":"20Th Ave",
    "iso:country":"CA",
    "sg:address":"1720 20th Ave",
    "sg:city":"Nanton",
    "sg:classifiers":[
        {
            "category":"Restaurant",
            "type":"Food & Drink"
        }
    ],
    "sg:phone":"+1 403 646 2922",
    "sg:postcode":"T0L 1R0",
    "sg:province":"AB",
    "wof:name":"Kens Restaurant Ltd",
    "wof:placetype":"venue"
},
  "geometry": {"coordinates":[-113.773239136,50.3508872986],"type":"Point"}
}