{
  "type": "Feature",
  "properties": {
    "addr:full":"4844 Rue Sainte-Catherine E Montreal QC H1V 1Z6",
    "addr:housenumber":"4844",
    "addr:postcode":"h1v 1z6",
    "addr:street":"Rue Sainte-Catherine E",
    "iso:country":"CA",
    "sg:address":"4844 Rue Sainte-Catherine E",
    "sg:city":"Montreal",
    "sg:classifiers":[
        {
            "category":"Bars & Pubs",
            "type":"Food & Drink"
        }
    ],
    "sg:phone":"+1 514 252 0026",
    "sg:postcode":"H1V 1Z6",
    "sg:province":"QC",
    "wof:name":"Taverne Vv Inc",
    "wof:placetype":"venue"
},
  "geometry": {"coordinates":[-73.53029632569999,45.5561027527],"type":"Point"}
}