{
  "type": "Feature",
  "properties": {
    "addr:full":"Mississauga ON L4W 1P9",
    "addr:postcode":"l4w 1p9",
    "iso:country":"CA",
    "sg:city":"Mississauga",
    "sg:classifiers":[
        {
            "category":"Manufacturing",
            "subcategory":"Printing",
            "type":"Manufacturing & Wholesale Goods"
        }
    ],
    "sg:phone":"+1 905 212 1010",
    "sg:postcode":"L4W 1P9",
    "sg:province":"ON",
    "sg:tags":[
        "bookbinder"
    ],
    "wof:name":"Webber Bindery Svc Ltd",
    "wof:placetype":"venue"
},
  "geometry": {"coordinates":[-79.624062,43.643459],"type":"Point"}
}