{
  "type": "Feature",
  "properties": {
    "addr:full":"48 Rosewarne Ave Winnipeg MB R2M 0V7",
    "addr:housenumber":"48",
    "addr:postcode":"r2m 0v7",
    "addr:street":"Rosewarne Ave",
    "iso:country":"CA",
    "sg:address":"48 Rosewarne Ave",
    "sg:city":"Winnipeg",
    "sg:classifiers":[
        {
            "category":"Freight",
            "type":"Transportation"
        }
    ],
    "sg:phone":"+1 204 231 4371",
    "sg:postcode":"R2M 0V7",
    "sg:province":"MB",
    "sg:tags":[
        "trucking"
    ],
    "wof:name":"Expense Data Systems",
    "wof:placetype":"venue"
},
  "geometry": {"coordinates":[-97.114861,49.857819],"type":"Point"}
}