{
  "type": "Feature",
  "properties": {
    "addr:full":"539 College St Toronto ON M6G 1A9",
    "addr:housenumber":"539",
    "addr:postcode":"m6g 1a9",
    "addr:street":"College St",
    "iso:country":"CA",
    "sg:address":"539 College St",
    "sg:city":"Toronto",
    "sg:classifiers":[
        {
            "category":"Restaurant",
            "type":"Food & Drink"
        }
    ],
    "sg:phone":"+1 416 922 1703",
    "sg:postcode":"M6G 1A9",
    "sg:province":"ON",
    "wof:name":"Perla Restaurant",
    "wof:placetype":"venue"
},
  "geometry": {"coordinates":[-79.4115829468,43.6555595398],"type":"Point"}
}