{
  "type": "Feature",
  "properties": {
    "addr:full":"1110 Rue Clark Montreal QC H2Z 1K2",
    "addr:housenumber":"1110",
    "addr:postcode":"h2z 1k2",
    "addr:street":"Rue Clark",
    "iso:country":"CA",
    "sg:address":"1110 Rue Clark",
    "sg:city":"Montreal",
    "sg:classifiers":[
        {
            "category":"Restaurant",
            "type":"Food & Drink"
        }
    ],
    "sg:phone":"+1 514 871 8778",
    "sg:postcode":"H2Z 1K2",
    "sg:province":"QC",
    "wof:name":"New Dynasty",
    "wof:placetype":"venue"
},
  "geometry": {"coordinates":[-73.56102799999999,45.507923],"type":"Point"}
}