{
  "type": "Feature",
  "properties": {
    "addr:full":"1914 Boul Des Laurentides Laval QC H7M 2Y5",
    "addr:housenumber":"1914",
    "addr:postcode":"h7m 2y5",
    "addr:street":"Boul Des Laurentides",
    "iso:country":"CA",
    "sg:address":"1914 Boul Des Laurentides",
    "sg:city":"Laval",
    "sg:classifiers":[
        {
            "category":"Personal",
            "subcategory":"Beauty Salon",
            "type":"Services"
        }
    ],
    "sg:phone":"+1 450 669 2923",
    "sg:postcode":"H7M 2Y5",
    "sg:province":"QC",
    "wof:name":"Coiffure Sa-Nic Elle & Lui",
    "wof:placetype":"venue"
},
  "geometry": {"coordinates":[-73.708961,45.584904],"type":"Point"}
}