{
  "type": "Feature",
  "properties": {
    "addr:full":"458 Rue Principale Standon QC G0R 4L0",
    "addr:housenumber":"458",
    "addr:postcode":"g0r 4l0",
    "addr:street":"Rue Principale",
    "iso:country":"CA",
    "sg:address":"458 Rue Principale",
    "sg:city":"Standon",
    "sg:classifiers":[
        {
            "category":"Retail",
            "subcategory":"Funeral Services",
            "type":"Services"
        }
    ],
    "sg:phone":"+1 418 642 2010",
    "sg:postcode":"G0R 4L0",
    "sg:province":"QC",
    "sg:tags":[
        "director"
    ],
    "wof:name":"Roland Couture & Fils Inc",
    "wof:placetype":"venue"
},
  "geometry": {"coordinates":[-70.62033099999999,46.480629],"type":"Point"}
}