{
  "type": "Feature",
  "properties": {
    "addr:full":"1171 1E Rue LA Baie QC G7B 2H7",
    "addr:housenumber":"1171",
    "addr:postcode":"g7b 2h7",
    "addr:street":"1E Rue La",
    "iso:country":"CA",
    "sg:address":"1171 1E Rue",
    "sg:city":"LA Baie",
    "sg:classifiers":[
        {
            "category":"Health Services",
            "subcategory":"Nursing And Care Facility",
            "type":"Services"
        }
    ],
    "sg:phone":"+1 418 544 2148",
    "sg:postcode":"G7B 2H7",
    "sg:province":"QC",
    "sg:tags":[
        "home",
        "retirement",
        "community"
    ],
    "wof:name":"Maison Des Notres Inc",
    "wof:placetype":"venue"
},
  "geometry": {"coordinates":[-70.87715900000001,48.326824],"type":"Point"}
}