{
  "type": "Feature",
  "properties": {
    "iso:country":"CA",
    "sg:address":"480 Rue Saint-Saens E",
    "sg:city":"Laval",
    "sg:classifiers":[
        {
            "category":"Personal",
            "type":"Services"
        }
    ],
    "sg:phone":"+1 450 625 5835",
    "sg:postcode":"H7H 2V8",
    "sg:province":"QC",
    "sg:tags":[
        "therapist",
        "massage"
    ],
    "wof:name":"Clinique DE Sante E Berube",
    "wof:placetype":"venue"
},
  "geometry": {"coordinates":[-73.7505722046,45.6376075745],"type":"Point"}
}