{
  "type": "Feature",
  "properties": {
    "addr:full":"Winnipeg MB R3T 0P7",
    "addr:postcode":"r3t 0p7",
    "iso:country":"CA",
    "sg:city":"Winnipeg",
    "sg:classifiers":[
        {
            "category":"Food & Beverages",
            "subcategory":"Specialty",
            "type":"Retail Goods"
        }
    ],
    "sg:phone":"+1 204 477 0001",
    "sg:postcode":"R3T 0P7",
    "sg:province":"MB",
    "sg:tags":[
        "water",
        "bulk",
        "company"
    ],
    "wof:name":"Waterro Corp",
    "wof:placetype":"venue"
},
  "geometry": {"coordinates":[-97.1798324585,49.8261108398],"type":"Point"}
}