{
  "type": "Feature",
  "properties": {
    "iso:country":"CA",
    "sg:address":"15150 Rue Notre-Dame E",
    "sg:city":"Pointe-Aux-Trembles",
    "sg:classifiers":[
        {
            "category":"Health Services",
            "subcategory":"Nursing And Care Facility",
            "type":"Services"
        }
    ],
    "sg:phone":"+1 514 642 5509",
    "sg:postcode":"H1A 1W6",
    "sg:province":"QC",
    "sg:tags":[
        "home",
        "rest"
    ],
    "wof:name":"Residence Rive Soleil Inc",
    "wof:placetype":"venue"
},
  "geometry": {"coordinates":[-73.490738,45.683681],"type":"Point"}
}