{
  "type": "Feature",
  "properties": {
    "addr:full":"Fort Mcmurray AB T9H 3E1",
    "addr:postcode":"t9h 3e1",
    "iso:country":"CA",
    "sg:city":"Fort Mcmurray",
    "sg:classifiers":[
        {
            "category":"Home & Garden",
            "subcategory":"Carpets & Floor Coverings",
            "type":"Retail Goods"
        }
    ],
    "sg:phone":"+1 780 791 0069",
    "sg:postcode":"T9H 3E1",
    "sg:province":"AB",
    "sg:tags":[
        "dealer",
        "rug"
    ],
    "wof:name":"End of the Roll",
    "wof:placetype":"venue"
},
  "geometry": {"coordinates":[-111.36274,56.723854],"type":"Point"}
}