{
  "type": "Feature",
  "properties": {
    "addr:full":"Keswick ON L4P 3E9",
    "addr:postcode":"l4p 3e9",
    "iso:country":"CA",
    "sg:city":"Keswick",
    "sg:classifiers":[
        {
            "category":"Retail",
            "subcategory":"Auto Repair",
            "type":"Services"
        }
    ],
    "sg:phone":"+1 905 476 2845",
    "sg:postcode":"L4P 3E9",
    "sg:province":"ON",
    "sg:tags":[
        "spring"
    ],
    "wof:name":"Tom's Spring Svc",
    "wof:placetype":"venue"
},
  "geometry": {"coordinates":[-79.4529418945,44.2476158142],"type":"Point"}
}