{
  "type": "Feature",
  "properties": {
    "addr:full":"2855 6th Ave W Vancouver BC V6K 1X2",
    "addr:housenumber":"2855",
    "addr:postcode":"v6k 1x2",
    "addr:street":"6Th Ave W",
    "iso:country":"CA",
    "sg:address":"2855 6th Ave W",
    "sg:city":"Vancouver",
    "sg:classifiers":[
        {
            "category":"Travel",
            "subcategory":"Hotels & Motels",
            "type":"Entertainment"
        }
    ],
    "sg:phone":"+1 604 739 9002",
    "sg:postcode":"V6K 1X2",
    "sg:province":"BC",
    "sg:tags":[
        "breakfast",
        "accommodation",
        "bed"
    ],
    "wof:name":"Penny Farthing Inn",
    "wof:placetype":"venue"
},
  "geometry": {"coordinates":[-123.169792,49.266796],"type":"Point"}
}