{
  "type": "Feature",
  "properties": {
    "addr:full":"260 Edward St London ON N6C 3J8",
    "addr:housenumber":"260",
    "addr:postcode":"n6c 3j8",
    "addr:street":"Edward St",
    "iso:country":"CA",
    "sg:address":"260 Edward St",
    "sg:city":"London",
    "sg:classifiers":[
        {
            "category":"Professional",
            "subcategory":"Computer Services",
            "type":"Services"
        }
    ],
    "sg:phone":"+1 519 433 9955",
    "sg:postcode":"N6C 3J8",
    "sg:province":"ON",
    "sg:tags":[
        "consultant"
    ],
    "wof:name":"Visual Software Evolutions Inc",
    "wof:placetype":"venue"
},
  "geometry": {"coordinates":[-81.25643920900001,42.9611129761],"type":"Point"}
}