{
  "type": "Feature",
  "properties": {
    "addr:full":"112 Post Rd Antigonish NS B2G 2K5",
    "addr:housenumber":"112",
    "addr:postcode":"b2g 2k5",
    "addr:street":"Post Rd",
    "iso:country":"CA",
    "sg:address":"112 Post Rd",
    "sg:city":"Antigonish",
    "sg:classifiers":[
        {
            "category":"Travel",
            "subcategory":"Hotels & Motels",
            "type":"Entertainment"
        }
    ],
    "sg:phone":"+1 902 863 4842",
    "sg:postcode":"B2G 2K5",
    "sg:province":"NS",
    "wof:name":"Chateau Motel",
    "wof:placetype":"venue"
},
  "geometry": {"coordinates":[-62.01955,45.607029],"type":"Point"}
}