{
  "type": "Feature",
  "properties": {
    "addr:full":"30 Marlene Crt Woodbridge ON L4L 8L3",
    "addr:housenumber":"30",
    "addr:postcode":"l4l 8l3",
    "addr:street":"Marlene Crt",
    "iso:country":"CA",
    "sg:address":"30 Marlene Crt",
    "sg:city":"Woodbridge",
    "sg:classifiers":[
        {
            "category":"Professional",
            "subcategory":"Business Services",
            "type":"Services"
        }
    ],
    "sg:phone":"+1 905 832 9417",
    "sg:postcode":"L4L 8L3",
    "sg:province":"ON",
    "sg:tags":[
        "interior",
        "consultant",
        "design",
        "decorator"
    ],
    "wof:name":"Dori Interior Decorating",
    "wof:placetype":"venue"
},
  "geometry": {"coordinates":[-79.563461,43.866364],"type":"Point"}
}