{
  "type": "Feature",
  "properties": {
    "addr:full":"Port Moody BC V3H 2J3",
    "addr:postcode":"v3h 2j3",
    "iso:country":"CA",
    "sg:city":"Port Moody",
    "sg:classifiers":[
        {
            "category":"Social Services",
            "type":"Services"
        }
    ],
    "sg:phone":"+1 604 461 9044",
    "sg:postcode":"V3H 2J3",
    "sg:province":"BC",
    "sg:tags":[
        "senior",
        "citizen"
    ],
    "wof:name":"Port Moody Legion Society",
    "wof:placetype":"venue"
},
  "geometry": {"coordinates":[-122.847542,49.274933],"type":"Point"}
}