{
  "type": "Feature",
  "properties": {
    "iso:country":"CA",
    "sg:address":"38 Lakeport Rd",
    "sg:city":"St Catharines",
    "sg:classifiers":[
        {
            "category":"Restaurant",
            "type":"Food & Drink"
        }
    ],
    "sg:phone":"+1 905 934 1913",
    "sg:postcode":"L2N 4P5",
    "sg:province":"ON",
    "sg:tags":[
        "breakfast",
        "accommodation",
        "bed"
    ],
    "wof:name":"Murphy's Restaurant & Harbor",
    "wof:placetype":"venue"
},
  "geometry": {"coordinates":[-79.265839,43.201992],"type":"Point"}
}