{
  "type": "Feature",
  "properties": {
    "addr:full":"Waterloo ON N2V 2C5",
    "addr:postcode":"n2v 2c5",
    "iso:country":"CA",
    "sg:city":"Waterloo",
    "sg:classifiers":[
        {
            "category":"Professional",
            "subcategory":"Art Services",
            "type":"Services"
        }
    ],
    "sg:phone":"+1 519 884 4930",
    "sg:postcode":"N2V 2C5",
    "sg:province":"ON",
    "sg:tags":[
        "photographer"
    ],
    "wof:name":"Greg Fess Photography",
    "wof:placetype":"venue"
},
  "geometry": {"coordinates":[-80.53792572019999,43.507522583],"type":"Point"}
}