{
  "type": "Feature",
  "properties": {
    "addr:full":"41 Roehampton Ave Toronto ON M4P 1P9",
    "addr:housenumber":"41",
    "addr:postcode":"m4p 1p9",
    "addr:street":"Roehampton Ave",
    "iso:country":"CA",
    "sg:address":"41 Roehampton Ave",
    "sg:city":"Toronto",
    "sg:classifiers":[
        {
            "category":"Education",
            "subcategory":"School",
            "type":"Public Place"
        }
    ],
    "sg:phone":"+1 416 489 3636",
    "sg:postcode":"M4P 1P9",
    "sg:province":"ON",
    "wof:name":"Kohai Educational Ctr",
    "wof:placetype":"venue"
},
  "geometry": {"coordinates":[-79.3970413208,43.7081489563],"type":"Point"}
}