{
  "type": "Feature",
  "properties": {
    "addr:full":"4100 Mackenzie Ave N Williams Lake BC V2G 1P6",
    "addr:housenumber":"4100",
    "addr:postcode":"v2g 1p6",
    "addr:street":"Mackenzie Ave N",
    "iso:country":"CA",
    "sg:address":"4100 Mackenzie Ave N",
    "sg:city":"Williams Lake",
    "sg:classifiers":[
        {
            "category":"Arts & Performance",
            "subcategory":"Theater",
            "type":"Entertainment"
        }
    ],
    "sg:phone":"+1 250 392 4383",
    "sg:postcode":"V2G 1P6",
    "sg:province":"BC",
    "wof:name":"Williams Lake Studio Theatre",
    "wof:placetype":"venue"
},
  "geometry": {"coordinates":[-122.17556762700001,52.1526069641],"type":"Point"}
}