{
  "type": "Feature",
  "properties": {
    "addr:full":"425 Rue Saint-Alfred Drummondville QC J2C 4A8",
    "addr:housenumber":"425",
    "addr:postcode":"j2c 4a8",
    "addr:street":"Rue Saint-Alfred",
    "iso:country":"CA",
    "sg:address":"425 Rue Saint-Alfred",
    "sg:city":"Drummondville",
    "sg:classifiers":[
        {
            "category":"Wholesale",
            "subcategory":"Durable Goods & Equipment",
            "type":"Manufacturing & Wholesale Goods"
        }
    ],
    "sg:phone":"+1 819 474 7501",
    "sg:postcode":"J2C 4A8",
    "sg:province":"QC",
    "sg:tags":[
        "fire",
        "extinguisher"
    ],
    "wof:name":"Securite Maska Inc",
    "wof:placetype":"venue"
},
  "geometry": {"coordinates":[-72.499908,45.883785],"type":"Point"}
}