{
  "type": "Feature",
  "properties": {
    "iso:country":"CA",
    "sg:city":"Oshawa",
    "sg:classifiers":[
        {
            "category":"Professional",
            "subcategory":"Lawyer & Legal Services",
            "type":"Services"
        }
    ],
    "sg:phone":"+1 905 576 2670",
    "sg:postcode":"L1H 4G4",
    "sg:province":"ON",
    "sg:tags":[
        "attorney"
    ],
    "wof:name":"Boychyn & Boychyn",
    "wof:placetype":"venue"
},
  "geometry": {"coordinates":[-78.862747,43.896042],"type":"Point"}
}