{
  "type": "Feature",
  "properties": {
    "addr:full":"25 Rue Willard East Angus QC J0B 1R0",
    "addr:housenumber":"25",
    "addr:postcode":"j0b 1r0",
    "addr:street":"Rue Willard",
    "iso:country":"CA",
    "sg:address":"25 Rue Willard",
    "sg:city":"East Angus",
    "sg:classifiers":[
        {
            "category":"Wholesale",
            "subcategory":"Construction Materials",
            "type":"Manufacturing & Wholesale Goods"
        }
    ],
    "sg:phone":"+1 819 832 2746",
    "sg:postcode":"J0B 1R0",
    "sg:province":"QC",
    "sg:tags":[
        "pallet",
        "skid"
    ],
    "wof:name":"Menuiserie D'East Angus Inc",
    "wof:placetype":"venue"
},
  "geometry": {"coordinates":[-71.65136699999999,45.479053],"type":"Point"}
}