{
  "type": "Feature",
  "properties": {
    "addr:full":"29 Water St Portland ON K0G 1V0",
    "addr:housenumber":"29",
    "addr:postcode":"k0g 1v0",
    "addr:street":"Water St",
    "iso:country":"CA",
    "sg:address":"29 Water St",
    "sg:city":"Portland",
    "sg:classifiers":[
        {
            "category":"Building & Trades",
            "subcategory":"Electrical",
            "type":"Services"
        }
    ],
    "sg:phone":"+1 613 272 2837",
    "sg:postcode":"K0G 1V0",
    "sg:province":"ON",
    "sg:tags":[
        "electric",
        "contractor"
    ],
    "wof:name":"Vanluven",
    "wof:placetype":"venue"
},
  "geometry": {"coordinates":[-76.191063,44.699749],"type":"Point"}
}