{
  "type": "Feature",
  "properties": {
    "addr:full":"Vernon BC V1B 2R5",
    "addr:postcode":"v1b 2r5",
    "iso:country":"CA",
    "sg:city":"Vernon",
    "sg:classifiers":[
        {
            "category":"Building & Trades",
            "subcategory":"Electrical",
            "type":"Services"
        }
    ],
    "sg:phone":"+1 250 549 0914",
    "sg:postcode":"V1B 2R5",
    "sg:province":"BC",
    "sg:tags":[
        "electric",
        "contractor"
    ],
    "wof:name":"A-OK Electric",
    "wof:placetype":"venue"
},
  "geometry": {"coordinates":[-119.25592804,50.2467918396],"type":"Point"}
}