{
  "type": "Feature",
  "properties": {
    "addr:full":"Terrace BC V8G 4R6",
    "addr:postcode":"v8g 4r6",
    "iso:country":"CA",
    "sg:city":"Terrace",
    "sg:classifiers":[
        {
            "category":"Manufacturing",
            "subcategory":"Lumber",
            "type":"Manufacturing & Wholesale Goods"
        }
    ],
    "sg:phone":"+1 250 635 6336",
    "sg:postcode":"V8G 4R6",
    "sg:province":"BC",
    "sg:tags":[
        "sawmill"
    ],
    "wof:name":"Skeena Sawmills",
    "wof:placetype":"venue"
},
  "geometry": {"coordinates":[-128.60217299999999,54.515858],"type":"Point"}
}