{
  "type": "Feature",
  "properties": {
    "iso:country":"CA",
    "sg:address":"375 Rue Chabot",
    "sg:city":"Boisbriand",
    "sg:classifiers":[
        {
            "category":"Professional",
            "subcategory":"Detective & Security Services",
            "type":"Services"
        }
    ],
    "sg:phone":"+1 514 918 1212",
    "sg:postcode":"J7G 1J7",
    "sg:province":"QC",
    "sg:tags":[
        "guard",
        "patrol"
    ],
    "wof:name":"Service Securite Ind Coml",
    "wof:placetype":"venue"
},
  "geometry": {"coordinates":[-73.842384,45.612324],"type":"Point"}
}