{
  "type": "Feature",
  "properties": {
    "addr:full":"Grande Prairie AB T8V 2Z8",
    "addr:postcode":"t8v 2z8",
    "iso:country":"CA",
    "sg:city":"Grande Prairie",
    "sg:classifiers":[
        {
            "category":"Building & Trades",
            "subcategory":"Construction",
            "type":"Services"
        }
    ],
    "sg:phone":"+1 780 539 3246",
    "sg:postcode":"T8V 2Z8",
    "sg:province":"AB",
    "sg:tags":[
        "home",
        "builder",
        "contractor"
    ],
    "wof:name":"Cardon Homes Ltd",
    "wof:placetype":"venue"
},
  "geometry": {"coordinates":[-118.794891357,55.1711616516],"type":"Point"}
}