{
  "type": "Feature",
  "properties": {
    "addr:full":"9 Cedar Ave Thornhill ON L3T 3W1",
    "addr:housenumber":"9",
    "addr:postcode":"l3t 3w1",
    "addr:street":"Cedar Ave",
    "iso:country":"CA",
    "sg:address":"9 Cedar Ave",
    "sg:city":"Thornhill",
    "sg:classifiers":[
        {
            "category":"Building & Trades",
            "subcategory":"Construction",
            "type":"Services"
        }
    ],
    "sg:phone":"+1 905 731 7646",
    "sg:postcode":"L3T 3W1",
    "sg:province":"ON",
    "sg:tags":[
        "sewer",
        "contractor"
    ],
    "wof:name":"Power Contracting 1997 Ltd",
    "wof:placetype":"venue"
},
  "geometry": {"coordinates":[-79.4171447754,43.8352127075],"type":"Point"}
}