{
  "type": "Feature",
  "properties": {
    "addr:full":"Vancouver BC V6E 4H3",
    "addr:postcode":"v6e 4h3",
    "iso:country":"CA",
    "sg:city":"Vancouver",
    "sg:classifiers":[
        {
            "category":"Professional",
            "subcategory":"Lawyer & Legal Services",
            "type":"Services"
        }
    ],
    "sg:phone":"+1 604 689 1811",
    "sg:postcode":"V6E 4H3",
    "sg:province":"BC",
    "sg:tags":[
        "attorney"
    ],
    "wof:name":"Letcher, Gary A",
    "wof:placetype":"venue"
},
  "geometry": {"coordinates":[-123.122032166,49.2848739624],"type":"Point"}
}