{
  "type": "Feature",
  "properties": {
    "iso:country":"CA",
    "sg:address":"2000 Rue Notre-Dame E",
    "sg:city":"Montreal",
    "sg:classifiers":[
        {
            "category":"Freight",
            "type":"Transportation"
        }
    ],
    "sg:phone":"+1 514 523 2772",
    "sg:postcode":"H2K 2N3",
    "sg:province":"QC",
    "sg:tags":[
        "mover"
    ],
    "wof:name":"A Agence DE Demenagement Jmv",
    "wof:placetype":"venue"
},
  "geometry": {"coordinates":[-73.546761,45.520508],"type":"Point"}
}