{
  "type": "Feature",
  "properties": {
    "addr:full":"Donalda AB T0B 1H0",
    "addr:postcode":"t0b 1h0",
    "iso:country":"CA",
    "sg:city":"Donalda",
    "sg:classifiers":[
        {
            "category":"Museum",
            "type":"Entertainment"
        }
    ],
    "sg:phone":"+1 403 883 2100",
    "sg:postcode":"T0B 1H0",
    "sg:province":"AB",
    "wof:name":"Donalda & District Museum",
    "wof:placetype":"venue"
},
  "geometry": {"coordinates":[-112.573501587,52.5852012634],"type":"Point"}
}