{
  "type": "Feature",
  "properties": {
    "addr:full":"703 Devonshire Ave Woodstock ON N4S 5R3",
    "addr:housenumber":"703",
    "addr:postcode":"n4s 5r3",
    "addr:street":"Devonshire Ave",
    "iso:country":"CA",
    "sg:address":"703 Devonshire Ave",
    "sg:city":"Woodstock",
    "sg:classifiers":[
        {
            "category":"Retail",
            "subcategory":"Auto Repair",
            "type":"Services"
        }
    ],
    "sg:phone":"+1 519 539 1417",
    "sg:postcode":"N4S 5R3",
    "sg:province":"ON",
    "sg:tags":[
        "repairing",
        "automobile"
    ],
    "wof:name":"Eaton & Thompson Ltd",
    "wof:placetype":"venue"
},
  "geometry": {"coordinates":[-80.751282,43.143684],"type":"Point"}
}