{
  "type": "Feature",
  "properties": {
    "addr:full":"710A Columbia St New Westminster BC V3M 1A9",
    "addr:housenumber":"710a",
    "addr:postcode":"v3m 1a9",
    "iso:country":"CA",
    "sg:address":"710A Columbia St",
    "sg:city":"New Westminster",
    "sg:classifiers":[
        {
            "category":"Real Estate",
            "subcategory":"Real Estate Agent",
            "type":"Services"
        }
    ],
    "sg:phone":"+1 604 540 4564",
    "sg:postcode":"V3M 1A9",
    "sg:province":"BC",
    "sg:tags":[
        "appraiser"
    ],
    "wof:name":"Lands West Property Svc Inc",
    "wof:placetype":"venue"
},
  "geometry": {"coordinates":[-122.909881592,49.2019271851],"type":"Point"}
}