{
  "type": "Feature",
  "properties": {
    "iso:country":"CA",
    "sg:address":"470 Rte 263",
    "sg:city":"Saint-Romain",
    "sg:classifiers":[
        {
            "category":"Travel",
            "subcategory":"Hotels & Motels",
            "type":"Entertainment"
        }
    ],
    "sg:phone":"+1 418 486 2420",
    "sg:postcode":"G0Y 1L0",
    "sg:province":"QC",
    "wof:name":"Motel Source Argentee Inc",
    "wof:placetype":"venue"
},
  "geometry": {"coordinates":[-71.1020126343,45.8121490479],"type":"Point"}
}