{
  "type": "Feature",
  "properties": {
    "addr:full":"745 Thompson Dr Thompson MB R8N 0C7",
    "addr:housenumber":"745",
    "addr:postcode":"r8n 0c7",
    "addr:street":"Thompson Dr",
    "iso:country":"CA",
    "sg:address":"745 Thompson Dr",
    "sg:city":"Thompson",
    "sg:classifiers":[
        {
            "category":"Autos & Motor Vehicles",
            "subcategory":"Fuel & Gas Station",
            "type":"Retail Goods"
        }
    ],
    "sg:phone":"+1 204 677 2023",
    "sg:postcode":"R8N 0C7",
    "sg:province":"MB",
    "sg:tags":[
        "oil"
    ],
    "wof:name":"Thompson Shell",
    "wof:placetype":"venue"
},
  "geometry": {"coordinates":[-97.8645935059,55.7372283936],"type":"Point"}
}