{
  "type": "Feature",
  "properties": {
    "addr:full":"4410 45 St Lacombe AB T4L 1W3",
    "addr:housenumber":"4410",
    "addr:postcode":"t4l 1w3",
    "addr:street":"45 St",
    "iso:country":"CA",
    "sg:address":"4410 45 St",
    "sg:city":"Lacombe",
    "sg:classifiers":[
        {
            "category":"Building & Trades",
            "subcategory":"Construction",
            "type":"Services"
        }
    ],
    "sg:phone":"+1 403 782 2781",
    "sg:postcode":"T4L 1W3",
    "sg:province":"AB",
    "sg:tags":[
        "excavating",
        "contractor"
    ],
    "wof:name":"Graham's Backhoe Svc",
    "wof:placetype":"venue"
},
  "geometry": {"coordinates":[-113.723541,52.452778],"type":"Point"}
}