{
  "type": "Feature",
  "properties": {
    "addr:full":"649 Carnaby St Kingston ON K7M 5M6",
    "addr:housenumber":"649",
    "addr:postcode":"k7m 5m6",
    "addr:street":"Carnaby St",
    "iso:country":"CA",
    "sg:address":"649 Carnaby St",
    "sg:city":"Kingston",
    "sg:classifiers":[
        {
            "category":"Shopping",
            "subcategory":"Computers & Home Electronics",
            "type":"Retail Goods"
        }
    ],
    "sg:phone":"+1 613 384 2000",
    "sg:postcode":"K7M 5M6",
    "sg:province":"ON",
    "sg:tags":[
        "equipment",
        "satellite"
    ],
    "wof:name":"Netcomm Kingston",
    "wof:placetype":"venue"
},
  "geometry": {"coordinates":[-76.59683200000001,44.243412],"type":"Point"}
}