{
  "type": "Feature",
  "properties": {
    "addr:full":"218 Main St Road 19 Otterville ON N0J 1R0",
    "addr:housenumber":"218",
    "addr:postcode":"n0j 1r0",
    "addr:street":"Main St Road 19 Otterville",
    "iso:country":"CA",
    "sg:address":"218 Main St Road 19",
    "sg:city":"Otterville",
    "sg:classifiers":[
        {
            "category":"Education",
            "subcategory":"Library",
            "type":"Public Place"
        }
    ],
    "sg:phone":"+1 519 879 6984",
    "sg:postcode":"N0J 1R0",
    "sg:province":"ON",
    "wof:name":"Otterville Public Library",
    "wof:placetype":"venue"
},
  "geometry": {"coordinates":[-80.6046218872,42.926448822],"type":"Point"}
}