{
  "type": "Feature",
  "properties": {
    "addr:full":"Timmins ON P4N 7X8",
    "addr:postcode":"p4n 7x8",
    "iso:country":"CA",
    "sg:city":"Timmins",
    "sg:classifiers":[
        {
            "category":"Social Services",
            "subcategory":"Child Care",
            "type":"Services"
        }
    ],
    "sg:phone":"+1 705 268 7690",
    "sg:postcode":"P4N 7X8",
    "sg:province":"ON",
    "wof:name":"Garderie Clin D'Oeil",
    "wof:placetype":"venue"
},
  "geometry": {"coordinates":[-81.343391,48.477539],"type":"Point"}
}