{
  "type": "Feature",
  "properties": {
    "iso:country":"CA",
    "sg:address":"660 Inverness Ave",
    "sg:city":"London",
    "sg:classifiers":[
        {
            "category":"Professional",
            "subcategory":"Management & Consulting",
            "type":"Services"
        }
    ],
    "sg:phone":"+1 519 474 2527",
    "sg:postcode":"N6H 5R4",
    "sg:province":"ON",
    "sg:tags":[
        "town",
        "city",
        "regional",
        "planner"
    ],
    "wof:name":"F R Berry & Assoc",
    "wof:placetype":"venue"
},
  "geometry": {"coordinates":[-81.29821,42.981014],"type":"Point"}
}