{
  "type": "Feature",
  "properties": {
    "addr:full":"2710 Av Lafleche Shawinigan QC G9N 6H5",
    "addr:housenumber":"2710",
    "addr:postcode":"g9n 6h5",
    "addr:street":"Av Lafleche",
    "iso:country":"CA",
    "sg:address":"2710 Av Lafleche",
    "sg:city":"Shawinigan",
    "sg:classifiers":[
        {
            "category":"Organizations",
            "subcategory":"Professional Association",
            "type":"Services"
        }
    ],
    "sg:phone":"+1 819 539 5746",
    "sg:postcode":"G9N 6H5",
    "sg:province":"QC",
    "wof:name":"Gambler Anonyme Gam-Anon",
    "wof:placetype":"venue"
},
  "geometry": {"coordinates":[-72.758698,46.57185],"type":"Point"}
}