{
  "type": "Feature",
  "properties": {
    "iso:country":"CA",
    "sg:address":"3860 Lougheed Hwy",
    "sg:city":"Burnaby",
    "sg:classifiers":[
        {
            "category":"Restaurant",
            "type":"Food & Drink"
        }
    ],
    "sg:phone":"+1 604 299 1761",
    "sg:postcode":"V5C 6N4",
    "sg:province":"BC",
    "wof:name":"Swiss Chalet Rotisserie/Grill",
    "wof:placetype":"venue"
},
  "geometry": {"coordinates":[-123.018295288,49.2657051086],"type":"Point"}
}