{
  "type": "Feature",
  "properties": {
    "addr:full":"Hall Beach NU X0A 0K0",
    "addr:postcode":"x0a 0k0",
    "iso:country":"CA",
    "sg:city":"Hall Beach",
    "sg:classifiers":[
        {
            "category":"Government",
            "subcategory":"Office",
            "type":"Public Place"
        }
    ],
    "sg:phone":"+1 867 928 8276",
    "sg:postcode":"X0A 0K0",
    "sg:province":"NU",
    "sg:tags":[
        "village"
    ],
    "wof:name":"Hall Beach Community",
    "wof:placetype":"venue"
},
  "geometry": {"coordinates":[-81.237549,68.79278600000001],"type":"Point"}
}