{
  "type": "Feature",
  "properties": {
    "addr:full":"2944 Boul Taschereau Greenfield Park QC J4V 2G8",
    "addr:housenumber":"2944",
    "addr:postcode":"j4v 2g8",
    "addr:street":"Boul Taschereau",
    "iso:country":"CA",
    "sg:address":"2944 Boul Taschereau",
    "sg:city":"Greenfield Park",
    "sg:classifiers":[
        {
            "category":"Professional",
            "subcategory":"Research",
            "type":"Services"
        }
    ],
    "sg:phone":"+1 450 465 5090",
    "sg:postcode":"J4V 2G8",
    "sg:province":"QC",
    "sg:tags":[
        "development",
        "laboratory"
    ],
    "wof:name":"Medica-Yeb",
    "wof:placetype":"venue"
},
  "geometry": {"coordinates":[-73.4871673584,45.4994850159],"type":"Point"}
}