{
  "type": "Feature",
  "properties": {
    "addr:full":"333 Brooksbank Ave # 730 North Vancouver BC V7J 3S8",
    "addr:housenumber":"333",
    "addr:postcode":"v7j 3s8",
    "addr:street":"Brooksbank Ave # 730",
    "iso:country":"CA",
    "sg:address":"333 Brooksbank Ave # 730",
    "sg:city":"North Vancouver",
    "sg:classifiers":[
        {
            "category":"Shopping",
            "subcategory":"Clothing, Apparel, & Fashions",
            "type":"Retail Goods"
        }
    ],
    "sg:phone":"+1 604 924 5517",
    "sg:postcode":"V7J 3S8",
    "sg:province":"BC",
    "sg:tags":[
        "sportswear"
    ],
    "wof:name":"Penningtons Superstore",
    "wof:placetype":"venue"
},
  "geometry": {"coordinates":[-123.040665,49.308781],"type":"Point"}
}