{
  "type": "Feature",
  "properties": {
    "addr:full":"246 Boul Rene-Levesque E Chandler QC G0C 1K0",
    "addr:housenumber":"246",
    "addr:postcode":"g0c 1k0",
    "addr:street":"Boul Rene-Levesque E",
    "iso:country":"CA",
    "sg:address":"246 Boul Rene-Levesque E",
    "sg:city":"Chandler",
    "sg:classifiers":[
        {
            "category":"Insurance",
            "subcategory":"Insurance Agent",
            "type":"Services"
        }
    ],
    "sg:phone":"+1 418 689 6177",
    "sg:postcode":"G0C 1K0",
    "sg:province":"QC",
    "wof:name":"Assurance Brian Brochet Inc",
    "wof:placetype":"venue"
},
  "geometry": {"coordinates":[-64.666183,48.350452],"type":"Point"}
}