{
  "type": "Feature",
  "properties": {
    "addr:full":"659 Lansdowne Ave Toronto ON M6H 3Y2",
    "addr:housenumber":"659",
    "addr:postcode":"m6h 3y2",
    "addr:street":"Lansdowne Ave",
    "iso:country":"CA",
    "sg:address":"659 Lansdowne Ave",
    "sg:city":"Toronto",
    "sg:classifiers":[
        {
            "category":"Personal",
            "subcategory":"Beauty Salon",
            "type":"Services"
        }
    ],
    "sg:phone":"+1 416 532 8132",
    "sg:postcode":"M6H 3Y2",
    "sg:province":"ON",
    "wof:name":"Virgo Beauty Salon",
    "wof:placetype":"venue"
},
  "geometry": {"coordinates":[-79.4423980713,43.6576118469],"type":"Point"}
}