{
  "type": "Feature",
  "properties": {
    "addr:full":"Callander ON P0H 1H0",
    "addr:postcode":"p0h 1h0",
    "iso:country":"CA",
    "sg:city":"Callander",
    "sg:classifiers":[
        {
            "category":"Professional",
            "subcategory":"Lawyer & Legal Services",
            "type":"Services"
        }
    ],
    "sg:phone":"+1 705 752 2200",
    "sg:postcode":"P0H 1H0",
    "sg:province":"ON",
    "sg:tags":[
        "attorney"
    ],
    "wof:name":"Valin Partners",
    "wof:placetype":"venue"
},
  "geometry": {"coordinates":[-79.36199999999999,46.223549],"type":"Point"}
}