{
  "type": "Feature",
  "properties": {
    "addr:full":"62 Charles St W Ingersoll ON N5C 2L6",
    "addr:housenumber":"62",
    "addr:postcode":"n5c 2l6",
    "addr:street":"Charles St W",
    "iso:country":"CA",
    "sg:address":"62 Charles St W",
    "sg:city":"Ingersoll",
    "sg:classifiers":[
        {
            "category":"Food & Beverages",
            "subcategory":"Liquor & Beverages",
            "type":"Retail Goods"
        }
    ],
    "sg:phone":"+1 519 485 3430",
    "sg:postcode":"N5C 2L6",
    "sg:province":"ON",
    "sg:tags":[
        "beer",
        "ale"
    ],
    "wof:name":"Beer Store",
    "wof:placetype":"venue"
},
  "geometry": {"coordinates":[-80.885666,43.038422],"type":"Point"}
}