{
  "type": "Feature",
  "properties": {
    "addr:full":"18 15th St E Prince Albert SK S6V 1E8",
    "addr:housenumber":"18",
    "addr:postcode":"s6v 1e8",
    "addr:street":"15Th St",
    "iso:country":"CA",
    "sg:address":"18 15th St E",
    "sg:city":"Prince Albert",
    "sg:classifiers":[
        {
            "category":"Recreation",
            "type":"Entertainment"
        }
    ],
    "sg:phone":"+1 306 763 5600",
    "sg:postcode":"S6V 1E8",
    "sg:province":"SK",
    "sg:tags":[
        "parlor",
        "billiard"
    ],
    "wof:name":"Suzy Cues",
    "wof:placetype":"venue"
},
  "geometry": {"coordinates":[-105.75361599999999,53.199665],"type":"Point"}
}