{
  "type": "Feature",
  "properties": {
    "iso:country":"CA",
    "sg:address":"500 George St",
    "sg:city":"Sarnia",
    "sg:classifiers":[
        {
            "category":"Professional",
            "subcategory":"Business Services",
            "type":"Services"
        }
    ],
    "sg:phone":"+1 519 344 4729",
    "sg:postcode":"N7T 4P9",
    "sg:province":"ON",
    "sg:tags":[
        "engraver"
    ],
    "wof:name":"Abc Engraving",
    "wof:placetype":"venue"
},
  "geometry": {"coordinates":[-82.38986206049999,42.9742927551],"type":"Point"}
}