{
  "type": "Feature",
  "properties": {
    "addr:full":"2426 200 St Langley BC V2Z 1X1",
    "addr:housenumber":"2426",
    "addr:postcode":"v2z 1x1",
    "addr:street":"200 St",
    "iso:country":"CA",
    "sg:address":"2426 200 St",
    "sg:city":"Langley",
    "sg:classifiers":[
        {
            "category":"Restaurant",
            "type":"Food & Drink"
        }
    ],
    "sg:phone":"+1 604 534 0103",
    "sg:postcode":"V2Z 1X1",
    "sg:province":"BC",
    "wof:name":"Coffee Mug Restaurant",
    "wof:placetype":"venue"
},
  "geometry": {"coordinates":[-122.66918200000001,49.046684],"type":"Point"}
}