{
  "type": "Feature",
  "properties": {
    "iso:country":"CA",
    "sg:address":"701 Rue Industrielle",
    "sg:city":"Rockland",
    "sg:classifiers":[
        {
            "category":"Manufacturing",
            "subcategory":"Paper Products",
            "type":"Manufacturing & Wholesale Goods"
        }
    ],
    "sg:phone":"+1 613 446 2828",
    "sg:postcode":"K4K 1T2",
    "sg:province":"ON",
    "sg:tags":[
        "packaging",
        "material"
    ],
    "wof:name":"Pack All Mfg",
    "wof:placetype":"venue"
},
  "geometry": {"coordinates":[-75.2779312134,45.5580368042],"type":"Point"}
}