{
  "type": "Feature",
  "properties": {
    "addr:full":"1487 Dundas St London ON N5W 3B8",
    "addr:housenumber":"1487",
    "addr:postcode":"n5w 3b8",
    "addr:street":"Dundas St",
    "iso:country":"CA",
    "sg:address":"1487 Dundas St",
    "sg:city":"London",
    "sg:classifiers":[
        {
            "category":"Restaurant",
            "type":"Food & Drink"
        }
    ],
    "sg:phone":"+1 519 453 0066",
    "sg:postcode":"N5W 3B8",
    "sg:province":"ON",
    "wof:name":"Whitehouse Pizzeria",
    "wof:placetype":"venue"
},
  "geometry": {"coordinates":[-81.1968460083,42.9986686707],"type":"Point"}
}