{
  "type": "Feature",
  "properties": {
    "addr:full":"4758 Grange St Burnaby BC V5H 1R2",
    "addr:housenumber":"4758",
    "addr:postcode":"v5h 1r2",
    "addr:street":"Grange St",
    "iso:country":"CA",
    "sg:address":"4758 Grange St",
    "sg:city":"Burnaby",
    "sg:classifiers":[
        {
            "category":"Real Estate",
            "subcategory":"Real Estate Operator",
            "type":"Services"
        }
    ],
    "sg:phone":"+1 604 451 0387",
    "sg:postcode":"V5H 1R2",
    "sg:province":"BC",
    "sg:tags":[
        "apartment"
    ],
    "wof:name":"Parkview Towers II",
    "wof:placetype":"venue"
},
  "geometry": {"coordinates":[-122.99687957800001,49.2297973633],"type":"Point"}
}