{
  "type": "Feature",
  "properties": {
    "addr:full":"128 Queen St S Mississauga ON L5M 1K8",
    "addr:housenumber":"128",
    "addr:postcode":"l5m 1k8",
    "addr:street":"Queen St S",
    "iso:country":"CA",
    "sg:address":"128 Queen St S",
    "sg:city":"Mississauga",
    "sg:classifiers":[
        {
            "category":"Building & Trades",
            "subcategory":"Construction",
            "type":"Services"
        }
    ],
    "sg:phone":"+1 905 820 1108",
    "sg:postcode":"L5M 1K8",
    "sg:province":"ON",
    "sg:tags":[
        "concrete",
        "cutting",
        "breaking",
        "sawing"
    ],
    "wof:name":"Star Diamond Drilling & Sawing",
    "wof:placetype":"venue"
},
  "geometry": {"coordinates":[-79.59740447999999,43.5460853577],"type":"Point"}
}