{
  "type": "Feature",
  "properties": {
    "addr:full":"21 St. Helena St St Catharines ON L2N 7P3",
    "addr:housenumber":"21",
    "addr:postcode":"l2n 7p3",
    "addr:street":"St. Helena St",
    "iso:country":"CA",
    "sg:address":"21 St. Helena St",
    "sg:city":"St Catharines",
    "sg:classifiers":[
        {
            "category":"Health Services",
            "subcategory":"Nursing And Care Facility",
            "type":"Services"
        }
    ],
    "sg:phone":"+1 905 937 2161",
    "sg:postcode":"L2N 7P3",
    "sg:province":"ON",
    "sg:tags":[
        "home",
        "retirement",
        "community"
    ],
    "wof:name":"Meadowgreen Manor",
    "wof:placetype":"venue"
},
  "geometry": {"coordinates":[-79.259437561,43.1799125671],"type":"Point"}
}