{
  "type": "Feature",
  "properties": {
    "addr:full":"2651 Eglinton Ave E Scarborough ON M1K 2S2",
    "addr:housenumber":"2651",
    "addr:postcode":"m1k 2s2",
    "addr:street":"Eglinton Ave E",
    "iso:country":"CA",
    "sg:address":"2651 Eglinton Ave E",
    "sg:city":"Scarborough",
    "sg:classifiers":[
        {
            "category":"Home & Garden",
            "subcategory":"Carpets & Floor Coverings",
            "type":"Retail Goods"
        }
    ],
    "sg:phone":"+1 416 264 2233",
    "sg:postcode":"M1K 2S2",
    "sg:province":"ON",
    "sg:tags":[
        "dealer",
        "rug"
    ],
    "wof:name":"Alex's Flooring",
    "wof:placetype":"venue"
},
  "geometry": {"coordinates":[-79.250809,43.736],"type":"Point"}
}