{
  "type": "Feature",
  "properties": {
    "addr:full":"2360 4th Ave W Vancouver BC V6K 1P1",
    "addr:housenumber":"2360",
    "addr:postcode":"v6k 1p1",
    "addr:street":"4Th Ave W",
    "iso:country":"CA",
    "sg:address":"2360 4th Ave W",
    "sg:city":"Vancouver",
    "sg:classifiers":[
        {
            "category":"Shopping",
            "subcategory":"Shoes",
            "type":"Retail Goods"
        }
    ],
    "sg:phone":"+1 604 732 3521",
    "sg:postcode":"V6K 1P1",
    "sg:province":"BC",
    "sg:tags":[
        "apparel"
    ],
    "wof:name":"Wear Else",
    "wof:placetype":"venue"
},
  "geometry": {"coordinates":[-123.158829,49.268154],"type":"Point"}
}