{
  "type": "Feature",
  "properties": {
    "addr:full":"Hamilton ON L8T 3B1",
    "addr:postcode":"l8t 3b1",
    "iso:country":"CA",
    "sg:city":"Hamilton",
    "sg:classifiers":[
        {
            "category":"Real Estate",
            "subcategory":"Real Estate Operator",
            "type":"Services"
        }
    ],
    "sg:phone":"+1 905 574 2881",
    "sg:postcode":"L8T 3B1",
    "sg:province":"ON",
    "sg:tags":[
        "apartment"
    ],
    "wof:name":"Talia Manor",
    "wof:placetype":"venue"
},
  "geometry": {"coordinates":[-79.8398361206,43.2223625183],"type":"Point"}
}