{
  "type": "Feature",
  "properties": {
    "addr:full":"86 Honeysuckle Rd N Lethbridge AB T1H 4J9",
    "addr:housenumber":"86",
    "addr:postcode":"t1h 4j9",
    "addr:street":"Honeysuckle Rd N",
    "iso:country":"CA",
    "sg:address":"86 Honeysuckle Rd N",
    "sg:city":"Lethbridge",
    "sg:classifiers":[
        {
            "category":"Communications",
            "subcategory":"Film & Video Production",
            "type":"Services"
        }
    ],
    "sg:phone":"+1 403 329 1274",
    "sg:postcode":"T1H 4J9",
    "sg:province":"AB",
    "sg:tags":[
        "taping"
    ],
    "wof:name":"M T Photo To Video Productions",
    "wof:placetype":"venue"
},
  "geometry": {"coordinates":[-112.803406,49.721291],"type":"Point"}
}