{
  "type": "Feature",
  "properties": {
    "addr:full":"762 Island Hwy E Parksville BC V9P 1T8",
    "addr:housenumber":"762",
    "addr:postcode":"v9p 1t8",
    "addr:street":"Island Hwy E",
    "iso:country":"CA",
    "sg:address":"762 Island Hwy E",
    "sg:city":"Parksville",
    "sg:classifiers":[
        {
            "category":"Travel",
            "subcategory":"Hotels & Motels",
            "type":"Entertainment"
        }
    ],
    "sg:phone":"+1 250 248 6532",
    "sg:postcode":"V9P 1T8",
    "sg:province":"BC",
    "wof:name":"Englishman River Motel",
    "wof:placetype":"venue"
},
  "geometry": {"coordinates":[-124.285988,49.316212],"type":"Point"}
}