{
  "type": "Feature",
  "properties": {
    "addr:full":"126 Concession St E Tillsonburg ON N4G 1P7",
    "addr:housenumber":"126",
    "addr:postcode":"n4g 1p7",
    "addr:street":"Concession St",
    "iso:country":"CA",
    "sg:address":"126 Concession St E",
    "sg:city":"Tillsonburg",
    "sg:classifiers":[
        {
            "category":"Building & Trades",
            "subcategory":"Construction",
            "type":"Services"
        }
    ],
    "sg:phone":"+1 519 842 8406",
    "sg:postcode":"N4G 1P7",
    "sg:province":"ON",
    "sg:tags":[
        "general",
        "contractor"
    ],
    "wof:name":"Arc Industries",
    "wof:placetype":"venue"
},
  "geometry": {"coordinates":[-80.721779,42.867725],"type":"Point"}
}