{
  "type": "Feature",
  "properties": {
    "addr:full":"182 10E Av O Amos QC J9T 1W8",
    "addr:housenumber":"182",
    "addr:postcode":"j9t 1w8",
    "addr:street":"10E Av O Amos",
    "iso:country":"CA",
    "sg:address":"182 10E Av O",
    "sg:city":"Amos",
    "sg:classifiers":[
        {
            "category":"Organizations",
            "subcategory":"Professional Association",
            "type":"Services"
        }
    ],
    "sg:phone":"+1 819 732 2168",
    "sg:postcode":"J9T 1W8",
    "sg:province":"QC",
    "wof:name":"L'Association Du Hockey Mineur",
    "wof:placetype":"venue"
},
  "geometry": {"coordinates":[-78.111923,48.569557],"type":"Point"}
}