{
  "type": "Feature",
  "properties": {
    "addr:full":"7 Marville St Miramichi NB E1N 3A6",
    "addr:housenumber":"7",
    "addr:postcode":"e1n 3a6",
    "addr:street":"Marville St",
    "iso:country":"CA",
    "sg:address":"7 Marville St",
    "sg:city":"Miramichi",
    "sg:classifiers":[
        {
            "category":"Freight",
            "type":"Transportation"
        }
    ],
    "sg:phone":"+1 506 773 3146",
    "sg:postcode":"E1N 3A6",
    "sg:province":"NB",
    "sg:tags":[
        "trucking"
    ],
    "wof:name":"R B Walsh Transport Ltd",
    "wof:placetype":"venue"
},
  "geometry": {"coordinates":[-65.440079,47.016872],"type":"Point"}
}