{
  "type": "Feature",
  "properties": {
    "iso:country":"CA",
    "sg:address":"211 Johnstone Rd",
    "sg:city":"North Sydney",
    "sg:classifiers":[
        {
            "category":"Recreation",
            "type":"Entertainment"
        }
    ],
    "sg:phone":"+1 902 794 8359",
    "sg:postcode":"B2A 1Z8",
    "sg:province":"NS",
    "sg:tags":[
        "stable"
    ],
    "wof:name":"Sunrise Stable",
    "wof:placetype":"venue"
},
  "geometry": {"coordinates":[-60.1909408569,46.1392745972],"type":"Point"}
}