{
  "type": "Feature",
  "properties": {
    "addr:full":"9110 110 Ave NW Edmonton AB T5H 4A1",
    "addr:housenumber":"9110",
    "addr:postcode":"t5h 4a1",
    "addr:street":"110 Ave Nw",
    "iso:country":"CA",
    "sg:address":"9110 110 Ave NW",
    "sg:city":"Edmonton",
    "sg:classifiers":[
        {
            "category":"Organizations",
            "subcategory":"Religious Organization",
            "type":"Services"
        }
    ],
    "sg:phone":"+1 780 422 8304",
    "sg:postcode":"T5H 4A1",
    "sg:province":"AB",
    "sg:tags":[
        "church"
    ],
    "wof:name":"Santa Maria Goretti Catholic",
    "wof:placetype":"venue"
},
  "geometry": {"coordinates":[-113.480881,53.559555],"type":"Point"}
}