{
  "type": "Feature",
  "properties": {
    "addr:full":"Montreal QC H3B 1A7",
    "addr:postcode":"h3b 1a7",
    "iso:country":"CA",
    "sg:city":"Montreal",
    "sg:classifiers":[
        {
            "category":"Shopping",
            "subcategory":"Computers & Home Electronics",
            "type":"Retail Goods"
        }
    ],
    "sg:phone":"+1 514 395 9059",
    "sg:postcode":"H3B 1A7",
    "sg:province":"QC",
    "sg:tags":[
        "software"
    ],
    "wof:name":"Corporation Cortex Machina",
    "wof:placetype":"venue"
},
  "geometry": {"coordinates":[-73.5597915649,45.5141944885],"type":"Point"}
}