{
  "type": "Feature",
  "properties": {
    "addr:full":"2 Queen St E Sault Ste Marie ON P6A 1Y3",
    "addr:housenumber":"2",
    "addr:postcode":"p6a 1y3",
    "addr:street":"Queen St E",
    "iso:country":"CA",
    "sg:address":"2 Queen St E",
    "sg:city":"Sault Ste Marie",
    "sg:classifiers":[
        {
            "category":"Bars & Pubs",
            "type":"Food & Drink"
        }
    ],
    "sg:phone":"+1 705 256 7000",
    "sg:postcode":"P6A 1Y3",
    "sg:province":"ON",
    "wof:name":"O'Aces Bar & Cafe",
    "wof:placetype":"venue"
},
  "geometry": {"coordinates":[-84.340919,46.517693],"type":"Point"}
}