{
  "type": "Feature",
  "properties": {
    "addr:full":"Surrey BC V3W 3E9",
    "addr:postcode":"v3w 3e9",
    "iso:country":"CA",
    "sg:city":"Surrey",
    "sg:classifiers":[
        {
            "category":"Wholesale",
            "subcategory":"Electrical",
            "type":"Manufacturing & Wholesale Goods"
        }
    ],
    "sg:phone":"+1 604 507 9551",
    "sg:postcode":"V3W 3E9",
    "sg:province":"BC",
    "sg:tags":[
        "transmission",
        "equipment",
        "power"
    ],
    "wof:name":"Pacific Bearing Ltd",
    "wof:placetype":"venue"
},
  "geometry": {"coordinates":[-122.87664032000001,49.1519393921],"type":"Point"}
}