{
  "type": "Feature",
  "properties": {
    "iso:country":"CA",
    "sg:address":"1311 Hopkins St",
    "sg:city":"Whitby",
    "sg:classifiers":[
        {
            "category":"Autos & Motor Vehicles",
            "subcategory":"Automobile Sales",
            "type":"Retail Goods"
        }
    ],
    "sg:phone":"+1 905 665 8888",
    "sg:postcode":"L1N 2C2",
    "sg:province":"ON",
    "sg:tags":[
        "truck"
    ],
    "wof:name":"Premier Peterbilt Inc",
    "wof:placetype":"venue"
},
  "geometry": {"coordinates":[-78.917381,43.872894],"type":"Point"}
}