{
  "type": "Feature",
  "properties": {
    "addr:full":"2355 Montee Saint-Hubert Saint-Hubert QC J3Y 4H6",
    "addr:postcode":"2355;j3y 4h6",
    "addr:street":"Montee Saint-Hubert",
    "iso:country":"CA",
    "sg:address":"2355 Montee Saint-Hubert",
    "sg:city":"Saint-Hubert",
    "sg:classifiers":[
        {
            "category":"Health Services",
            "subcategory":"Chiropractor",
            "type":"Services"
        }
    ],
    "sg:phone":"+1 450 445 5476",
    "sg:postcode":"J3Y 4H6",
    "sg:province":"QC",
    "wof:name":"Centre Chiropratique Desmarais",
    "wof:placetype":"venue"
},
  "geometry": {"coordinates":[-73.42208099370001,45.5033187866],"type":"Point"}
}