{
  "type": "Feature",
  "properties": {
    "addr:full":"5007 Maryvale Dr NE Calgary AB T2A 3A2",
    "addr:housenumber":"5007",
    "addr:postcode":"t2a 3a2",
    "addr:street":"Maryvale Dr Ne",
    "iso:country":"CA",
    "sg:address":"5007 Maryvale Dr NE",
    "sg:city":"Calgary",
    "sg:classifiers":[
        {
            "category":"Building & Trades",
            "subcategory":"Construction",
            "type":"Services"
        }
    ],
    "sg:phone":"+1 403 273 5221",
    "sg:postcode":"T2A 3A2",
    "sg:province":"AB",
    "sg:tags":[
        "marking",
        "maintenance",
        "parking"
    ],
    "wof:name":"Sharp Shooter Enterprises",
    "wof:placetype":"venue"
},
  "geometry": {"coordinates":[-113.962013,51.056061],"type":"Point"}
}