{
  "type": "Feature",
  "properties": {
    "addr:full":"900 Millwood Rd East York ON M4G 1X1",
    "addr:housenumber":"900",
    "addr:postcode":"m4g 1x1",
    "addr:street":"Millwood Rd",
    "iso:country":"CA",
    "sg:address":"900 Millwood Rd",
    "sg:city":"East York",
    "sg:classifiers":[
        {
            "category":"Restaurant",
            "type":"Food & Drink"
        }
    ],
    "sg:phone":"+1 416 467 8277",
    "sg:postcode":"M4G 1X1",
    "sg:province":"ON",
    "sg:tags":[
        "caterer"
    ],
    "wof:name":"Stars Food Shop Espresso Bar",
    "wof:placetype":"venue"
},
  "geometry": {"coordinates":[-79.363686,43.703445],"type":"Point"}
}