{
  "type": "Feature",
  "properties": {
    "addr:full":"North York ON M2J 4Y8",
    "addr:postcode":"m2j 4y8",
    "iso:country":"CA",
    "sg:city":"North York",
    "sg:classifiers":[
        {
            "category":"Professional",
            "subcategory":"Lawyer & Legal Services",
            "type":"Services"
        }
    ],
    "sg:phone":"+1 416 494 2817",
    "sg:postcode":"M2J 4Y8",
    "sg:province":"ON",
    "sg:tags":[
        "attorney"
    ],
    "wof:name":"Cheng, Willie",
    "wof:placetype":"venue"
},
  "geometry": {"coordinates":[-79.33623504640001,43.7724876404],"type":"Point"}
}