{
  "type": "Feature",
  "properties": {
    "addr:full":"Toronto ON M6S 1P7",
    "addr:postcode":"m6s 1p7",
    "iso:country":"CA",
    "sg:city":"Toronto",
    "sg:classifiers":[
        {
            "category":"Education",
            "subcategory":"Dance Studio",
            "type":"Public Place"
        }
    ],
    "sg:phone":"+1 416 767 3062",
    "sg:postcode":"M6S 1P7",
    "sg:province":"ON",
    "sg:tags":[
        "instruction",
        "dancing"
    ],
    "wof:name":"Doreen Hayes School of Dancing",
    "wof:placetype":"venue"
},
  "geometry": {"coordinates":[-79.4844665527,43.649181366],"type":"Point"}
}