{
  "type": "Feature",
  "properties": {
    "addr:full":"8990 Rue Sherbrooke E Montreal QC H1L 1C9",
    "addr:housenumber":"8990",
    "addr:postcode":"h1l 1c9",
    "addr:street":"Rue Sherbrooke E",
    "iso:country":"CA",
    "sg:address":"8990 Rue Sherbrooke E",
    "sg:city":"Montreal",
    "sg:classifiers":[
        {
            "category":"Food & Beverages",
            "subcategory":"Bakery",
            "type":"Retail Goods"
        }
    ],
    "sg:phone":"+1 514 353 8204",
    "sg:postcode":"H1L 1C9",
    "sg:province":"QC",
    "sg:tags":[
        "baker"
    ],
    "wof:name":"Patisserie St Justin",
    "wof:placetype":"venue"
},
  "geometry": {"coordinates":[-73.5282287598,45.6074142456],"type":"Point"}
}