{
  "type": "Feature",
  "properties": {
    "addr:full":"12944 148 St NW Edmonton AB T5L 2H8",
    "addr:housenumber":"12944",
    "addr:postcode":"t5l 2h8",
    "addr:street":"148 St Nw",
    "iso:country":"CA",
    "sg:address":"12944 148 St NW",
    "sg:city":"Edmonton",
    "sg:classifiers":[
        {
            "category":"Wholesale",
            "subcategory":"Hardware",
            "type":"Manufacturing & Wholesale Goods"
        }
    ],
    "sg:phone":"+1 780 477 9231",
    "sg:postcode":"T5L 2H8",
    "sg:province":"AB",
    "sg:tags":[
        "ventilating",
        "equipment",
        "heating",
        "system"
    ],
    "wof:name":"E H Price Ltd",
    "wof:placetype":"venue"
},
  "geometry": {"coordinates":[-113.574524,53.587593],"type":"Point"}
}