{
  "type": "Feature",
  "properties": {
    "addr:full":"1700 Bathurst St York ON M5P 3K3",
    "addr:housenumber":"1700",
    "addr:postcode":"m5p 3k3",
    "addr:street":"Bathurst St",
    "iso:country":"CA",
    "sg:address":"1700 Bathurst St",
    "sg:city":"York",
    "sg:classifiers":[
        {
            "category":"Restaurant",
            "type":"Food & Drink"
        }
    ],
    "sg:phone":"+1 416 783 4293",
    "sg:postcode":"M5P 3K3",
    "sg:province":"ON",
    "sg:tags":[
        "caterer"
    ],
    "wof:name":"Caterers York Ltd",
    "wof:placetype":"venue"
},
  "geometry": {"coordinates":[-79.4234161377,43.6955413818],"type":"Point"}
}