{
  "type": "Feature",
  "properties": {
    "addr:full":"Victoria BC V9A 3S2",
    "addr:postcode":"v9a 3s2",
    "iso:country":"CA",
    "sg:city":"Victoria",
    "sg:classifiers":[
        {
            "category":"Social Services",
            "type":"Services"
        }
    ],
    "sg:phone":"+1 250 383 6811",
    "sg:postcode":"V9A 3S2",
    "sg:province":"BC",
    "sg:tags":[
        "youth",
        "organization",
        "center"
    ],
    "wof:name":"Salts Sail & Life Training",
    "wof:placetype":"venue"
},
  "geometry": {"coordinates":[-123.374664,48.428959],"type":"Point"}
}