{
  "type": "Feature",
  "properties": {
    "addr:full":"18 Second Ave Brantford ON N3S 6R1",
    "addr:housenumber":"18",
    "addr:postcode":"n3s 6r1",
    "addr:street":"Second Ave",
    "iso:country":"CA",
    "sg:address":"18 Second Ave",
    "sg:city":"Brantford",
    "sg:classifiers":[
        {
            "category":"Organizations",
            "subcategory":"Religious Organization",
            "type":"Services"
        }
    ],
    "sg:phone":"+1 519 752 6163",
    "sg:postcode":"N3S 6R1",
    "sg:province":"ON",
    "sg:tags":[
        "church"
    ],
    "wof:name":"Oneness Penetecostal Church",
    "wof:placetype":"venue"
},
  "geometry": {"coordinates":[-80.237358,43.142754],"type":"Point"}
}