{
  "type": "Feature",
  "properties": {
    "iso:country":"CA",
    "sg:address":"330 12 Ave SW",
    "sg:city":"Calgary",
    "sg:classifiers":[
        {
            "category":"Organizations",
            "subcategory":"Community Association",
            "type":"Services"
        }
    ],
    "sg:phone":"+1 403 269 7486",
    "sg:postcode":"T2R 0H2",
    "sg:province":"AB",
    "sg:tags":[
        "sorority",
        "fraternity"
    ],
    "wof:name":"Ancient & Accepted Scottish Rt",
    "wof:placetype":"venue"
},
  "geometry": {"coordinates":[-114.06895400000001,51.04171],"type":"Point"}
}