{
  "type": "Feature",
  "properties": {
    "addr:full":"Saint-Alexandre-DE-Kamouraska QC G0L 2G0",
    "addr:postcode":"g0l 2g0",
    "iso:country":"CA",
    "sg:city":"Saint-Alexandre-DE-Kamouraska",
    "sg:classifiers":[
        {
            "category":"Building & Trades",
            "subcategory":"Electrical",
            "type":"Services"
        }
    ],
    "sg:phone":"+1 418 495 2124",
    "sg:postcode":"G0L 2G0",
    "sg:province":"QC",
    "sg:tags":[
        "electric",
        "contractor"
    ],
    "wof:name":"Entreprises Jacques Lajoie Enr",
    "wof:placetype":"venue"
},
  "geometry": {"coordinates":[-69.624016,47.67971],"type":"Point"}
}