{
  "type": "Feature",
  "properties": {
    "addr:full":"1900 Moody Dr Denare Beach SK S0P 0B0",
    "addr:housenumber":"1900",
    "addr:postcode":"s0p 0b0",
    "addr:street":"Moody Dr Denare Beach",
    "iso:country":"CA",
    "sg:address":"1900 Moody Dr",
    "sg:city":"Denare Beach",
    "sg:classifiers":[
        {
            "category":"Food & Beverages",
            "subcategory":"Groceries & Convenience Stores",
            "type":"Retail Goods"
        }
    ],
    "sg:phone":"+1 306 362 2133",
    "sg:postcode":"S0P 0B0",
    "sg:province":"SK",
    "wof:name":"Alpine Convenience Store",
    "wof:placetype":"venue"
},
  "geometry": {"coordinates":[-102.079803467,54.6589126587],"type":"Point"}
}