{
  "type": "Feature",
  "properties": {
    "addr:full":"312 Main St S Exeter ON N0M 1S0",
    "addr:housenumber":"312",
    "addr:postcode":"n0m 1s0",
    "addr:street":"Main St S",
    "iso:country":"CA",
    "sg:address":"312 Main St S",
    "sg:city":"Exeter",
    "sg:classifiers":[
        {
            "category":"Restaurant",
            "type":"Food & Drink"
        }
    ],
    "sg:phone":"+1 519 235 1730",
    "sg:postcode":"N0M 1S0",
    "sg:province":"ON",
    "wof:name":"Burkley Restaurant & Tavern",
    "wof:placetype":"venue"
},
  "geometry": {"coordinates":[-81.4805603027,43.3480186462],"type":"Point"}
}