{
  "type": "Feature",
  "properties": {
    "addr:full":"5220 Av Clarendon Laval QC H7W 4W9",
    "addr:housenumber":"5220",
    "addr:postcode":"h7w 4w9",
    "addr:street":"Av Clarendon",
    "iso:country":"CA",
    "sg:address":"5220 Av Clarendon",
    "sg:city":"Laval",
    "sg:classifiers":[
        {
            "category":"Home & Garden",
            "subcategory":"Household Appliances",
            "type":"Retail Goods"
        }
    ],
    "sg:phone":"+1 450 973 9179",
    "sg:postcode":"H7W 4W9",
    "sg:province":"QC",
    "wof:name":"Electroflex Electronique",
    "wof:placetype":"venue"
},
  "geometry": {"coordinates":[-73.77677199999999,45.529312],"type":"Point"}
}