{
  "type": "Feature",
  "properties": {
    "addr:full":"Gaspe QC G4X 5M7",
    "addr:postcode":"g4x 5m7",
    "iso:country":"CA",
    "sg:city":"Gaspe",
    "sg:classifiers":[
        {
            "category":"Building & Trades",
            "subcategory":"Equipment Rental",
            "type":"Services"
        }
    ],
    "sg:phone":"+1 418 269 3838",
    "sg:postcode":"G4X 5M7",
    "sg:province":"QC",
    "sg:tags":[
        "tool"
    ],
    "wof:name":"Magasin Clement Dufresne Inc",
    "wof:placetype":"venue"
},
  "geometry": {"coordinates":[-64.4078216553,48.991733551],"type":"Point"}
}