{
  "type": "Feature",
  "properties": {
    "addr:full":"2035 Boul Rosemont Montreal QC H2G 1T2",
    "addr:housenumber":"2035",
    "addr:postcode":"h2g 1t2",
    "addr:street":"Boul Rosemont",
    "iso:country":"CA",
    "sg:address":"2035 Boul Rosemont",
    "sg:city":"Montreal",
    "sg:classifiers":[
        {
            "category":"Shopping",
            "subcategory":"Computers & Home Electronics",
            "type":"Retail Goods"
        }
    ],
    "sg:phone":"+1 514 374 0621",
    "sg:postcode":"H2G 1T2",
    "sg:province":"QC",
    "sg:tags":[
        "equipment",
        "dealer"
    ],
    "wof:name":"Conseilleurs En Informatique",
    "wof:placetype":"venue"
},
  "geometry": {"coordinates":[-73.58972900000001,45.542763],"type":"Point"}
}