{
  "type": "Feature",
  "properties": {
    "iso:country":"CA",
    "sg:city":"Laval",
    "sg:classifiers":[
        {
            "category":"Insurance",
            "subcategory":"Insurance Agent",
            "type":"Services"
        }
    ],
    "sg:phone":"+1 450 661 4033",
    "sg:postcode":"H7E 4Y6",
    "sg:province":"QC",
    "wof:name":"Beaudet Mc Cann Inc",
    "wof:placetype":"venue"
},
  "geometry": {"coordinates":[-73.682236,45.599735],"type":"Point"}
}