{
  "type": "Feature",
  "properties": {
    "addr:full":"46 Fieldway Rd Etobicoke ON M8Z 3L2",
    "addr:housenumber":"46",
    "addr:postcode":"m8z 3l2",
    "addr:street":"Fieldway Rd",
    "iso:country":"CA",
    "sg:address":"46 Fieldway Rd",
    "sg:city":"Etobicoke",
    "sg:classifiers":[
        {
            "category":"Building & Trades",
            "subcategory":"Electrical",
            "type":"Services"
        }
    ],
    "sg:phone":"+1 416 237 0005",
    "sg:postcode":"M8Z 3L2",
    "sg:province":"ON",
    "sg:tags":[
        "electric",
        "contractor"
    ],
    "wof:name":"Hopper Electric",
    "wof:placetype":"venue"
},
  "geometry": {"coordinates":[-79.52806099999999,43.641933],"type":"Point"}
}