{
  "type": "Feature",
  "properties": {
    "addr:full":"32 Smith St W Yorkton SK S3N 3X5",
    "addr:housenumber":"32",
    "addr:postcode":"s3n 3x5",
    "addr:street":"Smith St W",
    "iso:country":"CA",
    "sg:address":"32 Smith St W",
    "sg:city":"Yorkton",
    "sg:classifiers":[
        {
            "category":"Food & Beverages",
            "subcategory":"Bakery",
            "type":"Retail Goods"
        }
    ],
    "sg:phone":"+1 306 786 7224",
    "sg:postcode":"S3N 3X5",
    "sg:province":"SK",
    "sg:tags":[
        "baker"
    ],
    "wof:name":"Buns Master Bakery",
    "wof:placetype":"venue"
},
  "geometry": {"coordinates":[-102.459328,51.211868],"type":"Point"}
}