{
  "type": "Feature",
  "properties": {
    "addr:full":"1955 Rue Cabot Montreal QC H4E 1E2",
    "addr:housenumber":"1955",
    "addr:postcode":"h4e 1e2",
    "addr:street":"Rue Cabot",
    "iso:country":"CA",
    "sg:address":"1955 Rue Cabot",
    "sg:city":"Montreal",
    "sg:classifiers":[
        {
            "category":"Building & Trades",
            "subcategory":"Plumbing",
            "type":"Services"
        }
    ],
    "sg:phone":"+1 514 766 3531",
    "sg:postcode":"H4E 1E2",
    "sg:province":"QC",
    "sg:tags":[
        "heating",
        "contractor"
    ],
    "wof:name":"Charbonneau Lucien Ltee",
    "wof:placetype":"venue"
},
  "geometry": {"coordinates":[-73.59037780760001,45.4657554626],"type":"Point"}
}