{
  "type": "Feature",
  "properties": {
    "addr:full":"439 Champlain St Dieppe NB E1A 1P2",
    "addr:housenumber":"439",
    "addr:postcode":"e1a 1p2",
    "addr:street":"Champlain St",
    "iso:country":"CA",
    "sg:address":"439 Champlain St",
    "sg:city":"Dieppe",
    "sg:classifiers":[
        {
            "category":"Retail",
            "subcategory":"Auto Rental",
            "type":"Services"
        }
    ],
    "sg:phone":"+1 506 855 4660",
    "sg:postcode":"E1A 1P2",
    "sg:province":"NB",
    "sg:tags":[
        "renting",
        "automobile"
    ],
    "wof:name":"Enterprise Rent-A-Car",
    "wof:placetype":"venue"
},
  "geometry": {"coordinates":[-64.73737300000001,46.097851],"type":"Point"}
}