{
  "type": "Feature",
  "properties": {
    "iso:country":"CA",
    "sg:address":"5241 Rice Lake Dr N",
    "sg:city":"Bewdley",
    "sg:classifiers":[
        {
            "category":"Travel",
            "subcategory":"Campground",
            "type":"Entertainment"
        }
    ],
    "sg:phone":"+1 905 797 2456",
    "sg:postcode":"K0L 1E0",
    "sg:province":"ON",
    "wof:name":"Sunrise Tourist Trailer Park",
    "wof:placetype":"venue"
},
  "geometry": {"coordinates":[-78.3299255371,44.0933799744],"type":"Point"}
}