{
  "type": "Feature",
  "properties": {
    "addr:full":"7007 5 St SE Calgary AB T2H 2G2",
    "addr:housenumber":"7007 5",
    "addr:postcode":"t2h 2g2",
    "addr:street":"St Se",
    "iso:country":"CA",
    "sg:address":"7007 5 St SE",
    "sg:city":"Calgary",
    "sg:classifiers":[
        {
            "category":"Manufacturing",
            "subcategory":"Apparel",
            "type":"Manufacturing & Wholesale Goods"
        }
    ],
    "sg:phone":"+1 403 259 0162",
    "sg:postcode":"T2H 2G2",
    "sg:province":"AB",
    "sg:tags":[
        "screen",
        "printing",
        "flag"
    ],
    "wof:name":"Process Color Print Ltd",
    "wof:placetype":"venue"
},
  "geometry": {"coordinates":[-114.051041,50.991753],"type":"Point"}
}