{
  "type": "Feature",
  "properties": {
    "iso:country":"CA",
    "sg:address":"1255 Firestone Cres",
    "sg:city":"Ottawa",
    "sg:classifiers":[
        {
            "category":"Manufacturing",
            "subcategory":"Buildings",
            "type":"Manufacturing & Wholesale Goods"
        }
    ],
    "sg:phone":"+1 613 820 4944",
    "sg:postcode":"K2C 3E4",
    "sg:province":"ON",
    "sg:tags":[
        "home",
        "log",
        "cabin"
    ],
    "wof:name":"Wood Pro Wood Colour Rstrtn",
    "wof:placetype":"venue"
},
  "geometry": {"coordinates":[-75.7862625122,45.3454017639],"type":"Point"}
}