{
  "type": "Feature",
  "properties": {
    "addr:full":"Beauport QC G1C 5A5",
    "addr:postcode":"qc g1c 5a5",
    "iso:country":"CA",
    "sg:city":"Beauport",
    "sg:classifiers":[
        {
            "category":"Wholesale",
            "subcategory":"Machinery & Supplies",
            "type":"Manufacturing & Wholesale Goods"
        }
    ],
    "sg:phone":"+1 418 666 2791",
    "sg:postcode":"G1C 5A5",
    "sg:province":"QC",
    "sg:tags":[
        "equipment",
        "laundry"
    ],
    "wof:name":"Lavoie Services Techniques",
    "wof:placetype":"venue"
},
  "geometry": {"coordinates":[-71.169624,46.883465],"type":"Point"}
}