{
  "type": "Feature",
  "properties": {
    "addr:full":"5334 89 St NW Edmonton AB T6E 5P9",
    "addr:housenumber":"5334",
    "addr:postcode":"t6e 5p9",
    "addr:street":"89 St Nw",
    "iso:country":"CA",
    "sg:address":"5334 89 St NW",
    "sg:city":"Edmonton",
    "sg:classifiers":[
        {
            "category":"Building & Trades",
            "subcategory":"Plumbing",
            "type":"Services"
        }
    ],
    "sg:phone":"+1 780 489 0127",
    "sg:postcode":"T6E 5P9",
    "sg:province":"AB",
    "sg:tags":[
        "contractor"
    ],
    "wof:name":"Save-On Mechanical Svc",
    "wof:placetype":"venue"
},
  "geometry": {"coordinates":[-113.464225769,53.490032196],"type":"Point"}
}