{
  "type": "Feature",
  "properties": {
    "addr:full":"7709 Giles Dr Coldstream BC V1B 1G4",
    "addr:housenumber":"7709",
    "addr:postcode":"bc v1b 1g4",
    "addr:street":"Giles Dr",
    "iso:country":"CA",
    "sg:address":"7709 Giles Dr",
    "sg:city":"Coldstream",
    "sg:classifiers":[
        {
            "category":"Manufacturing",
            "subcategory":"Printing",
            "type":"Manufacturing & Wholesale Goods"
        }
    ],
    "sg:phone":"+1 250 542 7831",
    "sg:postcode":"V1B 1G4",
    "sg:province":"BC",
    "sg:tags":[
        "printer",
        "advertising"
    ],
    "wof:name":"Gold Leaf Imprinters Ltd",
    "wof:placetype":"venue"
},
  "geometry": {"coordinates":[-119.227203,50.221298],"type":"Point"}
}