{
  "type": "Feature",
  "properties": {
    "addr:full":"Cambridge Station NS B0P 1G0",
    "addr:postcode":"b0p 1g0",
    "addr:street":"Cambridge",
    "iso:country":"CA",
    "sg:city":"Cambridge Station",
    "sg:classifiers":[
        {
            "category":"Wholesale",
            "subcategory":"Fruits & Vegetables",
            "type":"Manufacturing & Wholesale Goods"
        }
    ],
    "sg:phone":"+1 902 679 6615",
    "sg:postcode":"B0P 1G0",
    "sg:province":"NS",
    "wof:name":"James Bezanson Produce Ltd",
    "wof:placetype":"venue"
},
  "geometry": {"coordinates":[-64.64434799999999,45.055843],"type":"Point"}
}