{
  "type": "Feature",
  "properties": {
    "addr:full":"Jacksonville NB E7M 3H1",
    "addr:postcode":"e7m 3h1",
    "iso:country":"CA",
    "sg:city":"Jacksonville",
    "sg:classifiers":[
        {
            "category":"Professional",
            "subcategory":"Business Services",
            "type":"Services"
        }
    ],
    "sg:phone":"+1 506 458 8050",
    "sg:postcode":"E7M 3H1",
    "sg:province":"NB",
    "sg:tags":[
        "water",
        "treatment"
    ],
    "wof:name":"All Clear Water Treatment",
    "wof:placetype":"venue"
},
  "geometry": {"coordinates":[-67.622337,46.197159],"type":"Point"}
}