{
  "type": "Feature",
  "properties": {
    "iso:country":"CA",
    "sg:address":"20 Mountain Park Cir SE",
    "sg:city":"Calgary",
    "sg:classifiers":[
        {
            "category":"Professional",
            "subcategory":"Accounting & Tax Preparation",
            "type":"Services"
        }
    ],
    "sg:phone":"+1 403 257 1582",
    "sg:postcode":"T2Z 2B8",
    "sg:province":"AB",
    "sg:tags":[
        "accountant"
    ],
    "wof:name":"Doherty, Stan",
    "wof:placetype":"venue"
},
  "geometry": {"coordinates":[-113.98770141599999,50.9117164612],"type":"Point"}
}