{
  "type": "Feature",
  "properties": {
    "addr:full":"3635 Rue Brassens Boisbriand QC J7H 1J4",
    "addr:housenumber":"3635",
    "addr:postcode":"j7h 1j4",
    "addr:street":"Rue Brassens",
    "iso:country":"CA",
    "sg:address":"3635 Rue Brassens",
    "sg:city":"Boisbriand",
    "sg:classifiers":[
        {
            "category":"Building & Trades",
            "subcategory":"Construction",
            "type":"Services"
        }
    ],
    "sg:phone":"+1 450 433 7688",
    "sg:postcode":"J7H 1J4",
    "sg:province":"QC",
    "sg:tags":[
        "general",
        "contractor"
    ],
    "wof:name":"Jean-Denis Boyer Inc",
    "wof:placetype":"venue"
},
  "geometry": {"coordinates":[-73.863365,45.626575],"type":"Point"}
}