{
  "type": "Feature",
  "properties": {
    "iso:country":"CA",
    "sg:address":"161 Rue Principale",
    "sg:city":"Aylmer",
    "sg:classifiers":[
        {
            "category":"Organizations",
            "subcategory":"Religious Organization",
            "type":"Services"
        }
    ],
    "sg:phone":"+1 819 684 1379",
    "sg:postcode":"J9H 7H4",
    "sg:province":"QC",
    "sg:tags":[
        "home",
        "retirement",
        "community",
        "retreat",
        "house"
    ],
    "wof:name":"Residence Le Monastere",
    "wof:placetype":"venue"
},
  "geometry": {"coordinates":[-75.839401,45.39542],"type":"Point"}
}