{
  "type": "Feature",
  "properties": {
    "addr:full":"Route 138 Saint-Hilarion QC G0A 3V0",
    "addr:postcode":"g0a 3v0",
    "addr:street":"Route 138",
    "iso:country":"CA",
    "sg:address":"Route 138",
    "sg:city":"Saint-Hilarion",
    "sg:classifiers":[
        {
            "category":"Government",
            "subcategory":"Office",
            "type":"Public Place"
        }
    ],
    "sg:phone":"+1 418 457 3491",
    "sg:postcode":"G0A 3V0",
    "sg:province":"QC",
    "sg:tags":[
        "village"
    ],
    "wof:name":"St-Hilarion Usine D'Epuration",
    "wof:placetype":"venue"
},
  "geometry": {"coordinates":[-70.3945007324,47.5674057007],"type":"Point"}
}