{
  "type": "Feature",
  "properties": {
    "iso:country":"CA",
    "sg:city":"Hamilton",
    "sg:classifiers":[
        {
            "category":"Health Services",
            "subcategory":"Doctor",
            "type":"Services"
        }
    ],
    "sg:phone":"+1 905 575 2888",
    "sg:postcode":"L8V 1C4",
    "sg:province":"ON",
    "sg:tags":[
        "physician",
        "surgeon"
    ],
    "wof:name":"Di Paolo, B L MD",
    "wof:placetype":"venue"
},
  "geometry": {"coordinates":[-79.8432922363,43.2388153076],"type":"Point"}
}