{
  "type": "Feature",
  "properties": {
    "addr:full":"181 Church St Oakville ON L6J 1N3",
    "addr:housenumber":"181",
    "addr:postcode":"l6j 1n3",
    "addr:street":"Church St",
    "iso:country":"CA",
    "sg:address":"181 Church St",
    "sg:city":"Oakville",
    "sg:classifiers":[
        {
            "category":"Health Services",
            "subcategory":"Doctor",
            "type":"Services"
        }
    ],
    "sg:phone":"+1 905 842 4556",
    "sg:postcode":"L6J 1N3",
    "sg:province":"ON",
    "sg:tags":[
        "dentist"
    ],
    "wof:name":"Sevels, Ingrid I DDS",
    "wof:placetype":"venue"
},
  "geometry": {"coordinates":[-79.6696853638,43.4458961487],"type":"Point"}
}