{
  "type": "Feature",
  "properties": {
    "addr:full":"Gatineau QC J8P 2W6",
    "addr:postcode":"j8p 2w6",
    "iso:country":"CA",
    "sg:city":"Gatineau",
    "sg:classifiers":[
        {
            "category":"Home & Garden",
            "subcategory":"Garden Supply",
            "type":"Retail Goods"
        }
    ],
    "sg:phone":"+1 819 669 6706",
    "sg:postcode":"J8P 2W6",
    "sg:province":"QC",
    "sg:tags":[
        "lawn",
        "tool",
        "mower"
    ],
    "wof:name":"Electro-Mecanique Lpl Enr",
    "wof:placetype":"venue"
},
  "geometry": {"coordinates":[-75.63582599999999,45.493656],"type":"Point"}
}