{
  "type": "Feature",
  "properties": {
    "addr:full":"41 Jane Pl Comox BC V9M 3N4",
    "addr:housenumber":"41",
    "addr:postcode":"v9m 3n4",
    "addr:street":"Jane Pl",
    "iso:country":"CA",
    "sg:address":"41 Jane Pl",
    "sg:city":"Comox",
    "sg:classifiers":[
        {
            "category":"Professional",
            "subcategory":"Art Services",
            "type":"Services"
        }
    ],
    "sg:phone":"+1 250 339 6070",
    "sg:postcode":"V9M 3N4",
    "sg:province":"BC",
    "sg:tags":[
        "photographer"
    ],
    "wof:name":"Mc Kinnon Photography",
    "wof:placetype":"venue"
},
  "geometry": {"coordinates":[-124.92305,49.669987],"type":"Point"}
}