{
  "type": "Feature",
  "properties": {
    "addr:full":"Richmond BC V6X 3L4",
    "addr:postcode":"v6x 3l4",
    "iso:country":"CA",
    "sg:city":"Richmond",
    "sg:classifiers":[
        {
            "category":"Restaurant",
            "type":"Food & Drink"
        }
    ],
    "sg:phone":"+1 604 207 0202",
    "sg:postcode":"V6X 3L4",
    "sg:province":"BC",
    "wof:name":"Pure Tea Pub",
    "wof:placetype":"venue"
},
  "geometry": {"coordinates":[-123.129798889,49.178188324],"type":"Point"}
}