{
  "type": "Feature",
  "properties": {
    "addr:full":"12530 110 Ave Surrey BC V3V 3J8",
    "addr:housenumber":"12530",
    "addr:postcode":"v3v 3j8",
    "addr:street":"110 Ave",
    "iso:country":"CA",
    "sg:address":"12530 110 Ave",
    "sg:city":"Surrey",
    "sg:classifiers":[
        {
            "category":"Wholesale",
            "subcategory":"Scrap",
            "type":"Manufacturing & Wholesale Goods"
        }
    ],
    "sg:phone":"+1 604 580 7729",
    "sg:postcode":"V3V 3J8",
    "sg:province":"BC",
    "sg:tags":[
        "metal",
        "iron"
    ],
    "wof:name":"Kentru Trading Ltd",
    "wof:placetype":"venue"
},
  "geometry": {"coordinates":[-122.874847,49.202488],"type":"Point"}
}