{
  "type": "Feature",
  "properties": {
    "iso:country":"CA",
    "sg:address":"45 Gordon Mackay Rd",
    "sg:city":"North York",
    "sg:classifiers":[
        {
            "category":"Real Estate",
            "subcategory":"Developer",
            "type":"Services"
        }
    ],
    "sg:phone":"+1 416 243 7880",
    "sg:postcode":"M9N 3X3",
    "sg:province":"ON",
    "sg:tags":[
        "company",
        "land"
    ],
    "wof:name":"Murlee Holding Ltd",
    "wof:placetype":"venue"
},
  "geometry": {"coordinates":[-79.5110244751,43.7150688171],"type":"Point"}
}