{
  "type": "Feature",
  "properties": {
    "addr:full":"196 1E Av S St-Nazaire-Du-Lac-St-Jean QC G0W 2V0",
    "addr:housenumber":"196",
    "addr:postcode":"g0w 2v0",
    "addr:street":"1E Av S St-Nazaire-Du-Lac-St-Jean",
    "iso:country":"CA",
    "sg:address":"196 1E Av S",
    "sg:city":"St-Nazaire-Du-Lac-St-Jean",
    "sg:classifiers":[
        {
            "category":"Sports & Exercise",
            "subcategory":"Bowling",
            "type":"Entertainment"
        }
    ],
    "sg:phone":"+1 418 668 4505",
    "sg:postcode":"G0W 2V0",
    "sg:province":"QC",
    "sg:tags":[
        "center"
    ],
    "wof:name":"Salon DE Quilles DE St-Nazaire",
    "wof:placetype":"venue"
},
  "geometry": {"coordinates":[-70.8897018433,46.9212303162],"type":"Point"}
}