{
  "type": "Feature",
  "properties": {
    "addr:full":"1342 Hwy 9 Mildmay ON N0G 2J0",
    "addr:housenumber":"1342",
    "addr:postcode":"n0g 2j0",
    "addr:street":"Hwy 9 Mildmay",
    "iso:country":"CA",
    "sg:address":"1342 Hwy 9",
    "sg:city":"Mildmay",
    "sg:classifiers":[
        {
            "category":"Retail",
            "subcategory":"Veterinary Services",
            "type":"Services"
        }
    ],
    "sg:phone":"+1 519 367 2691",
    "sg:postcode":"N0G 2J0",
    "sg:province":"ON",
    "sg:tags":[
        "veterinarian"
    ],
    "wof:name":"Mildmay Veterinary Clinic",
    "wof:placetype":"venue"
},
  "geometry": {"coordinates":[-81.1149215698,44.0401916504],"type":"Point"}
}