{
  "type": "Feature",
  "properties": {
    "addr:full":"1091 Dawson Rd Thunder Bay ON P7B 1K8",
    "addr:housenumber":"1091",
    "addr:postcode":"p7b 1k8",
    "addr:street":"Dawson Rd",
    "iso:country":"CA",
    "sg:address":"1091 Dawson Rd",
    "sg:city":"Thunder Bay",
    "sg:classifiers":[
        {
            "category":"Restaurant",
            "type":"Food & Drink"
        }
    ],
    "sg:phone":"+1 807 767 4177",
    "sg:postcode":"P7B 1K8",
    "sg:province":"ON",
    "wof:name":"Oriental Garden",
    "wof:placetype":"venue"
},
  "geometry": {"coordinates":[-89.25500488279999,48.4518203735],"type":"Point"}
}