{
  "type": "Feature",
  "properties": {
    "addr:full":"355 Av Principale Degelis QC G5T 1L2",
    "addr:housenumber":"355",
    "addr:postcode":"g5t 1l2",
    "addr:street":"Av Principale",
    "iso:country":"CA",
    "sg:address":"355 Av Principale",
    "sg:city":"Degelis",
    "sg:classifiers":[
        {
            "category":"Health Services",
            "subcategory":"Nursing And Care Facility",
            "type":"Services"
        }
    ],
    "sg:phone":"+1 418 853 5132",
    "sg:postcode":"G5T 1L2",
    "sg:province":"QC",
    "sg:tags":[
        "home",
        "retirement",
        "community"
    ],
    "wof:name":"Auberge Rose DE LA Riviere",
    "wof:placetype":"venue"
},
  "geometry": {"coordinates":[-68.6480178833,47.5480079651],"type":"Point"}
}