{
  "type": "Feature",
  "properties": {
    "iso:country":"CA",
    "sg:address":"820 Av Du Mont-Royal E",
    "sg:city":"Montreal",
    "sg:classifiers":[
        {
            "category":"Shopping",
            "subcategory":"Used Merchandise",
            "type":"Retail Goods"
        }
    ],
    "sg:phone":"+1 514 596 2618",
    "sg:postcode":"H2J 1X1",
    "sg:province":"QC",
    "sg:tags":[
        "clothing"
    ],
    "wof:name":"Boutique Retromania",
    "wof:placetype":"venue"
},
  "geometry": {"coordinates":[-73.5808639526,45.5260353088],"type":"Point"}
}