{
  "type": "Feature",
  "properties": {
    "addr:full":"221 Sarsons Rd Vernon BC V1B 2M6",
    "addr:housenumber":"221",
    "addr:postcode":"bc v1b 2m6",
    "addr:street":"Sarsons Rd",
    "iso:country":"CA",
    "sg:address":"221 Sarsons Rd",
    "sg:city":"Vernon",
    "sg:classifiers":[
        {
            "category":"Professional",
            "subcategory":"Business Services",
            "type":"Services"
        }
    ],
    "sg:phone":"+1 250 542 7718",
    "sg:postcode":"V1B 2M6",
    "sg:province":"BC",
    "sg:tags":[
        "embroidery"
    ],
    "wof:name":"Celebrity Sportswear Plus",
    "wof:placetype":"venue"
},
  "geometry": {"coordinates":[-119.24372100799999,50.2483215332],"type":"Point"}
}