{
  "type": "Feature",
  "properties": {
    "iso:country":"CA",
    "sg:address":"12039 Rose Beach Line",
    "sg:city":"Morpeth",
    "sg:classifiers":[
        {
            "category":"Autos & Motor Vehicles",
            "subcategory":"Boat Sales",
            "type":"Retail Goods"
        }
    ],
    "sg:phone":"+1 519 437 8047",
    "sg:postcode":"N0P 1X0",
    "sg:province":"ON",
    "sg:tags":[
        "dealer"
    ],
    "wof:name":"Sailboats Southwest Hobie Cat",
    "wof:placetype":"venue"
},
  "geometry": {"coordinates":[-81.8358,42.351467],"type":"Point"}
}