{
  "type": "Feature",
  "properties": {
    "addr:full":"108 Wellington St W Exeter ON N0M 1S2",
    "addr:housenumber":"108",
    "addr:postcode":"n0m 1s2",
    "addr:street":"Wellington St W",
    "iso:country":"CA",
    "sg:address":"108 Wellington St W",
    "sg:city":"Exeter",
    "sg:classifiers":[
        {
            "category":"Home & Garden",
            "subcategory":"Furniture",
            "type":"Retail Goods"
        }
    ],
    "sg:phone":"+1 519 235 0554",
    "sg:postcode":"N0M 1S2",
    "sg:province":"ON",
    "sg:tags":[
        "equipment",
        "kitchen",
        "cabinet"
    ],
    "wof:name":"Thames Road Cabinets",
    "wof:placetype":"venue"
},
  "geometry": {"coordinates":[-81.48587000000001,43.352406],"type":"Point"}
}