{
  "type": "Feature",
  "properties": {
    "addr:full":"441 Dodding Lower Nicola BC V0K 1Y0",
    "addr:housenumber":"441",
    "addr:postcode":"v0k 1y0",
    "addr:street":"Dodding Lower",
    "iso:country":"CA",
    "sg:address":"441 Dodding",
    "sg:city":"Lower Nicola",
    "sg:classifiers":[
        {
            "category":"Manufacturing",
            "subcategory":"Lumber",
            "type":"Manufacturing & Wholesale Goods"
        }
    ],
    "sg:phone":"+1 250 378 5617",
    "sg:postcode":"V0K 1Y0",
    "sg:province":"BC",
    "sg:tags":[
        "forester"
    ],
    "wof:name":"Nicola Valley Forest Cnsltnts",
    "wof:placetype":"venue"
},
  "geometry": {"coordinates":[-120.88099699999999,50.156361],"type":"Point"}
}