{
  "type": "Feature",
  "properties": {
    "addr:full":"6527 Av Azilda Anjou QC H1K 2Z8",
    "addr:housenumber":"6527",
    "addr:postcode":"h1k 2z8",
    "addr:street":"Av Azilda",
    "iso:country":"CA",
    "sg:address":"6527 Av Azilda",
    "sg:city":"Anjou",
    "sg:classifiers":[
        {
            "category":"Organizations",
            "subcategory":"Professional Association",
            "type":"Services"
        }
    ],
    "sg:phone":"+1 514 351 2887",
    "sg:postcode":"H1K 2Z8",
    "sg:province":"QC",
    "sg:tags":[
        "club"
    ],
    "wof:name":"Conference St-Conrad",
    "wof:placetype":"venue"
},
  "geometry": {"coordinates":[-73.5458602905,45.6098976135],"type":"Point"}
}