{
  "type": "Feature",
  "properties": {
    "addr:full":"North York ON M3C 2G3",
    "addr:postcode":"m3c 2g3",
    "iso:country":"CA",
    "sg:city":"North York",
    "sg:classifiers":[
        {
            "category":"Mining & Drilling",
            "type":"Manufacturing & Wholesale Goods"
        }
    ],
    "sg:phone":"+1 416 441 3700",
    "sg:postcode":"M3C 2G3",
    "sg:province":"ON",
    "sg:tags":[
        "company"
    ],
    "wof:name":"Fonteneau Resources Ltd",
    "wof:placetype":"venue"
},
  "geometry": {"coordinates":[-79.34838104249999,43.7346992493],"type":"Point"}
}