{
  "type": "Feature",
  "properties": {
    "addr:full":"1201 Boul Rene-Levesque O Montreal QC H3B 2L7",
    "addr:housenumber":"1201",
    "addr:postcode":"h3b 2l7",
    "addr:street":"Boul Rene-Levesque O",
    "iso:country":"CA",
    "sg:address":"1201 Boul Rene-Levesque O",
    "sg:city":"Montreal",
    "sg:classifiers":[
        {
            "category":"Personal",
            "type":"Services"
        }
    ],
    "sg:phone":"+1 514 861 1207",
    "sg:postcode":"H3B 2L7",
    "sg:province":"QC",
    "sg:tags":[
        "therapist",
        "massage"
    ],
    "wof:name":"Studio Pressurat Inc",
    "wof:placetype":"venue"
},
  "geometry": {"coordinates":[-73.553917,45.517418],"type":"Point"}
}