{
  "type": "Feature",
  "properties": {
    "iso:country":"CA",
    "sg:address":"9156 Macleod Trail SE",
    "sg:city":"Calgary",
    "sg:classifiers":[
        {
            "category":"Retail",
            "subcategory":"Laundry & Dry Cleaning",
            "type":"Services"
        }
    ],
    "sg:phone":"+1 403 255 5586",
    "sg:postcode":"T2J 0P5",
    "sg:province":"AB",
    "sg:tags":[
        "cleaners"
    ],
    "wof:name":"Gellibrand's Excellence",
    "wof:placetype":"venue"
},
  "geometry": {"coordinates":[-114.07125854500001,50.9715957642],"type":"Point"}
}