{
  "type": "Feature",
  "properties": {
    "addr:full":"3 Renfrew St Petawawa ON K8H 2H3",
    "addr:housenumber":"3",
    "addr:postcode":"k8h 2h3",
    "addr:street":"Renfrew St",
    "iso:country":"CA",
    "sg:address":"3 Renfrew St",
    "sg:city":"Petawawa",
    "sg:classifiers":[
        {
            "category":"Food & Beverages",
            "subcategory":"Liquor & Beverages",
            "type":"Retail Goods"
        }
    ],
    "sg:phone":"+1 613 687 4364",
    "sg:postcode":"K8H 2H3",
    "sg:province":"ON",
    "sg:tags":[
        "beer",
        "ale"
    ],
    "wof:name":"Beer Store",
    "wof:placetype":"venue"
},
  "geometry": {"coordinates":[-77.2603530884,45.8883209229],"type":"Point"}
}