{
  "type": "Feature",
  "properties": {
    "addr:full":"109 Superior Ave Wawa ON P0S 1K0",
    "addr:housenumber":"109",
    "addr:postcode":"p0s 1k0",
    "addr:street":"Superior Ave",
    "iso:country":"CA",
    "sg:address":"109 Superior Ave",
    "sg:city":"Wawa",
    "sg:classifiers":[
        {
            "category":"Shopping",
            "subcategory":"Bicycles & Sporting Goods",
            "type":"Retail Goods"
        }
    ],
    "sg:phone":"+1 705 856 7304",
    "sg:postcode":"P0S 1K0",
    "sg:province":"ON",
    "wof:name":"Superior Archery",
    "wof:placetype":"venue"
},
  "geometry": {"coordinates":[-84.7830657959,47.9938735962],"type":"Point"}
}