{
  "type": "Feature",
  "properties": {
    "iso:country":"CA",
    "sg:city":"Hamilton",
    "sg:classifiers":[
        {
            "category":"Health Services",
            "subcategory":"Doctor",
            "type":"Services"
        }
    ],
    "sg:phone":"+1 905 318 3333",
    "sg:postcode":"L8T 1S2",
    "sg:province":"ON",
    "sg:tags":[
        "dentist"
    ],
    "wof:name":"Miarczynski, U DDS",
    "wof:placetype":"venue"
},
  "geometry": {"coordinates":[-79.82921600340001,43.2256393433],"type":"Point"}
}