{
  "type": "Feature",
  "properties": {
    "addr:full":"Winnipeg MB R3L 1Z3",
    "addr:postcode":"r3l 1z3",
    "iso:country":"CA",
    "sg:city":"Winnipeg",
    "sg:classifiers":[
        {
            "category":"Organizations",
            "subcategory":"Professional Association",
            "type":"Services"
        }
    ],
    "sg:phone":"+1 204 452 2572",
    "sg:postcode":"R3L 1Z3",
    "sg:province":"MB",
    "wof:name":"Consumers' Association-Canada",
    "wof:placetype":"venue"
},
  "geometry": {"coordinates":[-97.142601,49.875553],"type":"Point"}
}