{
  "type": "Feature",
  "properties": {
    "addr:full":"798 Goldstream Ave Victoria BC V9B 2X6",
    "addr:housenumber":"798",
    "addr:postcode":"v9b 2x6",
    "addr:street":"Goldstream Ave",
    "iso:country":"CA",
    "sg:address":"798 Goldstream Ave",
    "sg:city":"Victoria",
    "sg:classifiers":[
        {
            "category":"Organizations",
            "subcategory":"Religious Organization",
            "type":"Services"
        }
    ],
    "sg:phone":"+1 250 478 3482",
    "sg:postcode":"V9B 2X6",
    "sg:province":"BC",
    "sg:tags":[
        "church"
    ],
    "wof:name":"Our Lady of the Rosary",
    "wof:placetype":"venue"
},
  "geometry": {"coordinates":[-123.364517212,48.428314209],"type":"Point"}
}