{
  "type": "Feature",
  "properties": {
    "addr:full":"44 King St W Dundas ON L9H 1T7",
    "addr:housenumber":"44",
    "addr:postcode":"l9h 1t7",
    "addr:street":"King St W",
    "iso:country":"CA",
    "sg:address":"44 King St W",
    "sg:city":"Dundas",
    "sg:classifiers":[
        {
            "category":"Restaurant",
            "type":"Food & Drink"
        }
    ],
    "sg:phone":"+1 905 628 0020",
    "sg:postcode":"L9H 1T7",
    "sg:province":"ON",
    "wof:name":"Valley Charcoal",
    "wof:placetype":"venue"
},
  "geometry": {"coordinates":[-79.9556274414,43.2662467957],"type":"Point"}
}