{
  "type": "Feature",
  "properties": {
    "iso:country":"CA",
    "sg:city":"Blenheim",
    "sg:classifiers":[
        {
            "category":"Personal",
            "subcategory":"Beauty Salon",
            "type":"Services"
        }
    ],
    "sg:phone":"+1 519 676 2666",
    "sg:postcode":"N0P 1A0",
    "sg:province":"ON",
    "wof:name":"Noggins Hair Design Studio",
    "wof:placetype":"venue"
},
  "geometry": {"coordinates":[-81.998322,42.334229],"type":"Point"}
}