{
  "type": "Feature",
  "properties": {
    "addr:full":"5111 New St # 31 Burlington ON L7L 1V2",
    "addr:housenumber":"5111",
    "addr:postcode":"l7l 1v2",
    "addr:street":"New St # 31",
    "iso:country":"CA",
    "sg:address":"5111 New St # 31",
    "sg:city":"Burlington",
    "sg:classifiers":[
        {
            "category":"Shopping",
            "subcategory":"Optical Goods",
            "type":"Retail Goods"
        }
    ],
    "sg:phone":"+1 905 634 3220",
    "sg:postcode":"L7L 1V2",
    "sg:province":"ON",
    "sg:tags":[
        "optician"
    ],
    "wof:name":"Akber Optical",
    "wof:placetype":"venue"
},
  "geometry": {"coordinates":[-79.751724,43.36911],"type":"Point"}
}