{
  "type": "Feature",
  "properties": {
    "addr:full":"Saint-Bernard QC G0S 2G0",
    "addr:postcode":"g0s 2g0",
    "iso:country":"CA",
    "sg:city":"Saint-Bernard",
    "sg:classifiers":[
        {
            "category":"Personal",
            "subcategory":"Beauty Salon",
            "type":"Services"
        }
    ],
    "sg:phone":"+1 418 475 6244",
    "sg:postcode":"G0S 2G0",
    "sg:province":"QC",
    "wof:name":"Coiffure Isabelle Lessard",
    "wof:placetype":"venue"
},
  "geometry": {"coordinates":[-71.1837463379,46.4409446716],"type":"Point"}
}