{
  "type": "Feature",
  "properties": {
    "addr:full":"45 3rd St Roland MB R0G 1T0",
    "addr:housenumber":"45",
    "addr:postcode":"r0g 1t0",
    "addr:street":"3Rd St Roland",
    "iso:country":"CA",
    "sg:address":"45 3rd St",
    "sg:city":"Roland",
    "sg:classifiers":[
        {
            "category":"Government",
            "subcategory":"Office",
            "type":"Public Place"
        }
    ],
    "sg:phone":"+1 204 343 2061",
    "sg:postcode":"R0G 1T0",
    "sg:province":"MB",
    "sg:tags":[
        "village"
    ],
    "wof:name":"Roland Rural Municipality Ofc",
    "wof:placetype":"venue"
},
  "geometry": {"coordinates":[-97.92993199999999,49.356239],"type":"Point"}
}