{
  "type": "Feature",
  "properties": {
    "addr:full":"91 Mill St Orono ON L0B 1M0",
    "addr:housenumber":"91",
    "addr:postcode":"l0b 1m0",
    "addr:street":"Mill St",
    "iso:country":"CA",
    "sg:address":"91 Mill St",
    "sg:city":"Orono",
    "sg:classifiers":[
        {
            "category":"Food & Beverages",
            "subcategory":"Groceries & Convenience Stores",
            "type":"Retail Goods"
        }
    ],
    "sg:phone":"+1 905 983 5306",
    "sg:postcode":"L0B 1M0",
    "sg:province":"ON",
    "sg:tags":[
        "grocer"
    ],
    "wof:name":"Armstrong Iga Ltd",
    "wof:placetype":"venue"
},
  "geometry": {"coordinates":[-78.61730194090001,43.9828720093],"type":"Point"}
}