{
  "type": "Feature",
  "properties": {
    "addr:full":"131 Rue Principale Saint-Gervais QC G0R 3C0",
    "addr:housenumber":"131",
    "addr:postcode":"g0r 3c0",
    "addr:street":"Rue Principale",
    "iso:country":"CA",
    "sg:address":"131 Rue Principale",
    "sg:city":"Saint-Gervais",
    "sg:classifiers":[
        {
            "category":"Retail",
            "subcategory":"Auto Repair",
            "type":"Services"
        }
    ],
    "sg:phone":"+1 418 887 6164",
    "sg:postcode":"G0R 3C0",
    "sg:province":"QC",
    "sg:tags":[
        "repairing",
        "automobile",
        "wrecker"
    ],
    "wof:name":"Station Service Claude Roy Inc",
    "wof:placetype":"venue"
},
  "geometry": {"coordinates":[-70.89419599999999,46.718716],"type":"Point"}
}