{
  "type": "Feature",
  "properties": {
    "iso:country":"CA",
    "sg:address":"47 Rue Compton E",
    "sg:city":"Waterville",
    "sg:classifiers":[
        {
            "category":"Food & Beverages",
            "subcategory":"Groceries & Convenience Stores",
            "type":"Retail Goods"
        }
    ],
    "sg:phone":"+1 819 837 2345",
    "sg:postcode":"J0B 3H0",
    "sg:province":"QC",
    "wof:name":"Depanneur Mado",
    "wof:placetype":"venue"
},
  "geometry": {"coordinates":[-71.88999176030001,45.2772674561],"type":"Point"}
}