{
  "type": "Feature",
  "properties": {
    "addr:full":"374 Jerseyville Rd W Ancaster ON L9G 3K8",
    "addr:housenumber":"374",
    "addr:postcode":"l9g 3k8",
    "addr:street":"Jerseyville Rd W",
    "iso:country":"CA",
    "sg:address":"374 Jerseyville Rd W",
    "sg:city":"Ancaster",
    "sg:classifiers":[
        {
            "category":"Professional",
            "subcategory":"Management & Consulting",
            "type":"Services"
        }
    ],
    "sg:phone":"+1 905 304 8911",
    "sg:postcode":"L9G 3K8",
    "sg:province":"ON",
    "sg:tags":[
        "food"
    ],
    "wof:name":"Compass of Canada",
    "wof:placetype":"venue"
},
  "geometry": {"coordinates":[-80.00559997560001,43.2166366577],"type":"Point"}
}