{
  "type": "Feature",
  "properties": {
    "addr:full":"Kelowna BC V1V 2K7",
    "addr:postcode":"v1v 2k7",
    "iso:country":"CA",
    "sg:city":"Kelowna",
    "sg:classifiers":[
        {
            "category":"Professional",
            "subcategory":"Lawyer & Legal Services",
            "type":"Services"
        }
    ],
    "sg:phone":"+1 250 862 6538",
    "sg:postcode":"V1V 2K7",
    "sg:province":"BC",
    "sg:tags":[
        "attorney"
    ],
    "wof:name":"Mc Guire, Cori L",
    "wof:placetype":"venue"
},
  "geometry": {"coordinates":[-119.435417,49.895878],"type":"Point"}
}