{
  "type": "Feature",
  "properties": {
    "addr:full":"102 Queens St E St Marys ON N4X 1B4",
    "addr:housenumber":"102",
    "addr:postcode":"n4x 1b4",
    "addr:street":"Queens St E",
    "iso:country":"CA",
    "sg:address":"102 Queens St E",
    "sg:city":"St Marys",
    "sg:classifiers":[
        {
            "category":"Retail",
            "subcategory":"Photofinishing",
            "type":"Services"
        }
    ],
    "sg:phone":"+1 519 284 0507",
    "sg:postcode":"N4X 1B4",
    "sg:province":"ON",
    "sg:tags":[
        "photo",
        "finishing"
    ],
    "wof:name":"Van Galen Photo",
    "wof:placetype":"venue"
},
  "geometry": {"coordinates":[-81.14250946040001,43.2592353821],"type":"Point"}
}