{
  "type": "Feature",
  "properties": {
    "iso:country":"CA",
    "sg:address":"450 2E Av",
    "sg:city":"Portneuf",
    "sg:classifiers":[
        {
            "category":"Food & Beverages",
            "subcategory":"Bakery",
            "type":"Retail Goods"
        }
    ],
    "sg:phone":"+1 418 286 3400",
    "sg:postcode":"G0A 2Y0",
    "sg:province":"QC",
    "sg:tags":[
        "baker"
    ],
    "wof:name":"Selection Du Patissier Inc",
    "wof:placetype":"venue"
},
  "geometry": {"coordinates":[-71.89697265620001,46.6844787598],"type":"Point"}
}