{
  "type": "Feature",
  "properties": {
    "addr:full":"73 11th St Birtle MB R0M 0C0",
    "addr:housenumber":"73",
    "addr:postcode":"r0m 0c0",
    "addr:street":"11Th St",
    "iso:country":"CA",
    "sg:address":"73 11th St",
    "sg:city":"Birtle",
    "sg:classifiers":[
        {
            "category":"Education",
            "subcategory":"School",
            "type":"Public Place"
        }
    ],
    "sg:phone":"+1 204 842 3315",
    "sg:postcode":"R0M 0C0",
    "sg:province":"MB",
    "wof:name":"Birtle Collegiate Institute",
    "wof:placetype":"venue"
},
  "geometry": {"coordinates":[-101.039841,50.422157],"type":"Point"}
}