{
  "type": "Feature",
  "properties": {
    "addr:full":"6402 118 Ave NW Edmonton AB T5W 1G3",
    "addr:housenumber":"6402",
    "addr:postcode":"t5w 1g3",
    "addr:street":"118 Ave Nw",
    "iso:country":"CA",
    "sg:address":"6402 118 Ave NW",
    "sg:city":"Edmonton",
    "sg:classifiers":[
        {
            "category":"Bars & Pubs",
            "type":"Food & Drink"
        }
    ],
    "sg:phone":"+1 780 474 5554",
    "sg:postcode":"T5W 1G3",
    "sg:province":"AB",
    "sg:tags":[
        "lounge",
        "cocktail"
    ],
    "wof:name":"Duster's Pub",
    "wof:placetype":"venue"
},
  "geometry": {"coordinates":[-113.440078735,53.5705108643],"type":"Point"}
}