{
  "type": "Feature",
  "properties": {
    "addr:full":"355 Boul Cremazie O Montreal QC H2N 1M1",
    "addr:housenumber":"355",
    "addr:postcode":"h2n 1m1",
    "addr:street":"Boul Cremazie O",
    "iso:country":"CA",
    "sg:address":"355 Boul Cremazie O",
    "sg:city":"Montreal",
    "sg:classifiers":[
        {
            "category":"Home & Garden",
            "subcategory":"Carpets & Floor Coverings",
            "type":"Retail Goods"
        }
    ],
    "sg:phone":"+1 514 384 4695",
    "sg:postcode":"H2N 1M1",
    "sg:province":"QC",
    "sg:tags":[
        "material"
    ],
    "wof:name":"Montreal Parquetry Floors Inc",
    "wof:placetype":"venue"
},
  "geometry": {"coordinates":[-73.63957214360001,45.5451278687],"type":"Point"}
}