{
  "type": "Feature",
  "properties": {
    "addr:full":"146 Fox St Penetanguishene ON L9M 1E7",
    "addr:housenumber":"146",
    "addr:postcode":"l9m 1e7",
    "addr:street":"Fox St",
    "iso:country":"CA",
    "sg:address":"146 Fox St",
    "sg:city":"Penetanguishene",
    "sg:classifiers":[
        {
            "category":"Government",
            "subcategory":"Office",
            "type":"Public Place"
        }
    ],
    "sg:phone":"+1 705 549 2773",
    "sg:postcode":"L9M 1E7",
    "sg:province":"ON",
    "sg:tags":[
        "village"
    ],
    "wof:name":"Penetanguishene Sewage Treat",
    "wof:placetype":"venue"
},
  "geometry": {"coordinates":[-79.9328536987,44.7830581665],"type":"Point"}
}