{
  "type": "Feature",
  "properties": {
    "addr:full":"1 Holborn Ave London ON N6J 1K5",
    "addr:housenumber":"1",
    "addr:postcode":"n6j 1k5",
    "addr:street":"Holborn Ave",
    "iso:country":"CA",
    "sg:address":"1 Holborn Ave",
    "sg:city":"London",
    "sg:classifiers":[
        {
            "category":"Retail",
            "subcategory":"Auto Repair",
            "type":"Services"
        }
    ],
    "sg:phone":"+1 519 434 7798",
    "sg:postcode":"N6J 1K5",
    "sg:province":"ON",
    "sg:tags":[
        "repairing",
        "automobile"
    ],
    "wof:name":"Wayne Evoy Auto Svc",
    "wof:placetype":"venue"
},
  "geometry": {"coordinates":[-81.2627487183,42.9671401978],"type":"Point"}
}