{
  "type": "Feature",
  "properties": {
    "iso:country":"CA",
    "sg:address":"5020 50 St",
    "sg:city":"Sylvan Lake",
    "sg:classifiers":[
        {
            "category":"Shopping",
            "subcategory":"Department Store",
            "type":"Retail Goods"
        }
    ],
    "sg:phone":"+1 403 887 8854",
    "sg:postcode":"T4S 1P3",
    "sg:province":"AB",
    "sg:tags":[
        "shop"
    ],
    "wof:name":"Great Canadian Dollar Store",
    "wof:placetype":"venue"
},
  "geometry": {"coordinates":[-114.09750366199999,52.3088188171],"type":"Point"}
}