{
  "type": "Feature",
  "properties": {
    "addr:full":"46 Dominion St Alliston ON L9R 1L5",
    "addr:housenumber":"46",
    "addr:postcode":"l9r 1l5",
    "addr:street":"Dominion St",
    "iso:country":"CA",
    "sg:address":"46 Dominion St",
    "sg:city":"Alliston",
    "sg:classifiers":[
        {
            "category":"Health Services",
            "subcategory":"Doctor",
            "type":"Services"
        }
    ],
    "sg:phone":"+1 705 435 4124",
    "sg:postcode":"L9R 1L5",
    "sg:province":"ON",
    "sg:tags":[
        "dentist"
    ],
    "wof:name":"Mackle, James DDS",
    "wof:placetype":"venue"
},
  "geometry": {"coordinates":[-79.868309,44.154465],"type":"Point"}
}