{
  "type": "Feature",
  "properties": {
    "addr:full":"35 Riddell St Woodstock ON N4S 6L9",
    "addr:housenumber":"35",
    "addr:postcode":"n4s 6l9",
    "addr:street":"Riddell St",
    "iso:country":"CA",
    "sg:address":"35 Riddell St",
    "sg:city":"Woodstock",
    "sg:classifiers":[
        {
            "category":"Education",
            "subcategory":"School",
            "type":"Public Place"
        }
    ],
    "sg:phone":"+1 519 537 1050",
    "sg:postcode":"N4S 6L9",
    "sg:province":"ON",
    "wof:name":"Woodstock Collegiate Institute",
    "wof:placetype":"venue"
},
  "geometry": {"coordinates":[-80.7573394775,43.1311988831],"type":"Point"}
}