{
  "type": "Feature",
  "properties": {
    "iso:country":"CA",
    "sg:city":"Regina",
    "sg:classifiers":[
        {
            "category":"Shopping",
            "subcategory":"Clothing, Apparel, & Fashions",
            "type":"Retail Goods"
        }
    ],
    "sg:phone":"+1 306 545 5069",
    "sg:postcode":"S4R 3C3",
    "sg:province":"SK",
    "wof:name":"Tan Jay",
    "wof:placetype":"venue"
},
  "geometry": {"coordinates":[-104.61786651600001,50.4838409424],"type":"Point"}
}