{
  "type": "Feature",
  "properties": {
    "addr:full":"Calgary AB T2E 7A7",
    "addr:postcode":"t2e 7a7",
    "iso:country":"CA",
    "sg:city":"Calgary",
    "sg:classifiers":[
        {
            "category":"Home & Garden",
            "subcategory":"Carpets & Floor Coverings",
            "type":"Retail Goods"
        }
    ],
    "sg:phone":"+1 403 250 6766",
    "sg:postcode":"T2E 7A7",
    "sg:province":"AB",
    "sg:tags":[
        "material"
    ],
    "wof:name":"Woodfellow Flooring",
    "wof:placetype":"venue"
},
  "geometry": {"coordinates":[-114.006584167,51.0770568848],"type":"Point"}
}