{
  "type": "Feature",
  "properties": {
    "addr:full":"1313 Hastings Cres SE Calgary AB T2G 4C8",
    "addr:housenumber":"1313",
    "addr:postcode":"t2g 4c8",
    "addr:street":"Hastings Cres Se",
    "iso:country":"CA",
    "sg:address":"1313 Hastings Cres SE",
    "sg:city":"Calgary",
    "sg:classifiers":[
        {
            "category":"Professional",
            "subcategory":"Engineering",
            "type":"Services"
        }
    ],
    "sg:phone":"+1 403 243 8270",
    "sg:postcode":"T2G 4C8",
    "sg:province":"AB",
    "sg:tags":[
        "compressor",
        "engineer"
    ],
    "wof:name":"Able Compressor Svc",
    "wof:placetype":"venue"
},
  "geometry": {"coordinates":[-114.03364563,51.0133018494],"type":"Point"}
}