{
  "type": "Feature",
  "properties": {
    "addr:full":"2606 Cedar Park Pl Abbotsford BC V2T 3S5",
    "addr:housenumber":"2606",
    "addr:postcode":"v2t 3s5",
    "addr:street":"Cedar Park Pl",
    "iso:country":"CA",
    "sg:address":"2606 Cedar Park Pl",
    "sg:city":"Abbotsford",
    "sg:classifiers":[
        {
            "category":"Shopping",
            "subcategory":"Crafts & Fabrics",
            "type":"Retail Goods"
        }
    ],
    "sg:phone":"+1 604 854 6213",
    "sg:postcode":"V2T 3S5",
    "sg:province":"BC",
    "sg:tags":[
        "shop"
    ],
    "wof:name":"Banwait Fine Fashions",
    "wof:placetype":"venue"
},
  "geometry": {"coordinates":[-122.335075378,49.0496864319],"type":"Point"}
}