{
  "type": "Feature",
  "properties": {
    "addr:full":"Toronto ON M4M 2X9",
    "addr:postcode":"m4m 2x9",
    "iso:country":"CA",
    "sg:city":"Toronto",
    "sg:classifiers":[
        {
            "category":"Building & Trades",
            "subcategory":"Construction",
            "type":"Services"
        }
    ],
    "sg:phone":"+1 416 466 9025",
    "sg:postcode":"M4M 2X9",
    "sg:province":"ON",
    "sg:tags":[
        "roofing",
        "contractor"
    ],
    "wof:name":"Bergeron Roofing",
    "wof:placetype":"venue"
},
  "geometry": {"coordinates":[-79.3364944458,43.6656265259],"type":"Point"}
}