{
  "type": "Feature",
  "properties": {
    "addr:full":"Sainte-Julie QC J3E 1N8",
    "addr:postcode":"j3e 1n8",
    "iso:country":"CA",
    "sg:city":"Sainte-Julie",
    "sg:classifiers":[
        {
            "category":"Professional",
            "subcategory":"Engineering",
            "type":"Services"
        }
    ],
    "sg:phone":"+1 450 649 1130",
    "sg:postcode":"J3E 1N8",
    "sg:province":"QC",
    "sg:tags":[
        "engineer"
    ],
    "wof:name":"G N Solutions",
    "wof:placetype":"venue"
},
  "geometry": {"coordinates":[-73.33921100000001,45.59359],"type":"Point"}
}