{
  "type": "Feature",
  "properties": {
    "addr:full":"10A Gagnier St Hay River NT X0E 1G1",
    "addr:housenumber":"10a",
    "addr:postcode":"x0e 1g1",
    "addr:street":"Gagnier St",
    "iso:country":"CA",
    "sg:address":"10A Gagnier St",
    "sg:city":"Hay River",
    "sg:classifiers":[
        {
            "category":"Banks & Credit Unions",
            "subcategory":"Bank",
            "type":"Services"
        }
    ],
    "sg:phone":"+1 867 874 6746",
    "sg:postcode":"X0E 1G1",
    "sg:province":"NT",
    "wof:name":"Cibc",
    "wof:placetype":"venue"
},
  "geometry": {"coordinates":[-115.788856506,60.80809021],"type":"Point"}
}