{
  "type": "Feature",
  "properties": {
    "addr:full":"Mississauga ON L5B 4A2",
    "addr:postcode":"l5b 4a2",
    "iso:country":"CA",
    "sg:city":"Mississauga",
    "sg:classifiers":[
        {
            "category":"Shopping",
            "subcategory":"Optical Goods",
            "type":"Retail Goods"
        }
    ],
    "sg:phone":"+1 905 275 2400",
    "sg:postcode":"L5B 4A2",
    "sg:province":"ON",
    "sg:tags":[
        "optician"
    ],
    "wof:name":"Mississauga Optical",
    "wof:placetype":"venue"
},
  "geometry": {"coordinates":[-79.6155090332,43.5777587891],"type":"Point"}
}