{
  "type": "Feature",
  "properties": {
    "addr:full":"811 Des Pionniers Ave Balmoral NB E8E 1B4",
    "addr:housenumber":"811",
    "addr:postcode":"e8e 1b4",
    "addr:street":"Des Pionniers Ave",
    "iso:country":"CA",
    "sg:address":"811 Des Pionniers Ave",
    "sg:city":"Balmoral",
    "sg:classifiers":[
        {
            "category":"Retail",
            "subcategory":"Repair Shop",
            "type":"Services"
        }
    ],
    "sg:phone":"+1 506 826 3110",
    "sg:postcode":"E8E 1B4",
    "sg:province":"NB",
    "sg:tags":[
        "welding"
    ],
    "wof:name":"Roga Arc Enr",
    "wof:placetype":"venue"
},
  "geometry": {"coordinates":[-66.43034400000001,47.976761],"type":"Point"}
}