{
  "type": "Feature",
  "properties": {
    "addr:full":"Regina SK S4P 0J8",
    "addr:postcode":"s4p 0j8",
    "iso:country":"CA",
    "sg:city":"Regina",
    "sg:classifiers":[
        {
            "category":"Government",
            "subcategory":"Office",
            "type":"Public Place"
        }
    ],
    "sg:phone":"+1 306 780 7287",
    "sg:postcode":"S4P 0J8",
    "sg:province":"SK",
    "wof:name":"Canada Heritage",
    "wof:placetype":"venue"
},
  "geometry": {"coordinates":[-104.612464905,50.4503364563],"type":"Point"}
}