{
  "type": "Feature",
  "properties": {
    "addr:full":"200 Rue DE Montreal Sherbrooke QC J1H 1E3",
    "addr:housenumber":"200",
    "addr:postcode":"j1h 1e3",
    "addr:street":"Rue De Montreal",
    "iso:country":"CA",
    "sg:address":"200 Rue DE Montreal",
    "sg:city":"Sherbrooke",
    "sg:classifiers":[
        {
            "category":"Organizations",
            "subcategory":"Religious Organization",
            "type":"Services"
        }
    ],
    "sg:phone":"+1 819 564 0279",
    "sg:postcode":"J1H 1E3",
    "sg:province":"QC",
    "sg:tags":[
        "church"
    ],
    "wof:name":"St-Peter's Church Hall",
    "wof:placetype":"venue"
},
  "geometry": {"coordinates":[-71.89604187010001,45.4067802429],"type":"Point"}
}