{
  "type": "Feature",
  "properties": {
    "addr:full":"125 John St Nipigon ON P0T 2J0",
    "addr:housenumber":"125",
    "addr:postcode":"p0t 2j0",
    "addr:street":"John St",
    "iso:country":"CA",
    "sg:address":"125 John St",
    "sg:city":"Nipigon",
    "sg:classifiers":[
        {
            "category":"Wholesale",
            "subcategory":"Hardware",
            "type":"Manufacturing & Wholesale Goods"
        }
    ],
    "sg:phone":"+1 807 887 1713",
    "sg:postcode":"P0T 2J0",
    "sg:province":"ON",
    "sg:tags":[
        "furnace"
    ],
    "wof:name":"S Ribeiro Heating",
    "wof:placetype":"venue"
},
  "geometry": {"coordinates":[-88.270980835,49.015411377],"type":"Point"}
}