{
  "type": "Feature",
  "properties": {
    "iso:country":"CA",
    "sg:address":"85 Rue Lauzon",
    "sg:city":"Saint-Jerome",
    "sg:classifiers":[
        {
            "category":"Education",
            "subcategory":"School",
            "type":"Public Place"
        }
    ],
    "sg:phone":"+1 450 438 5603",
    "sg:postcode":"J7Y 1V8",
    "sg:province":"QC",
    "wof:name":"Prevost Ecole",
    "wof:placetype":"venue"
},
  "geometry": {"coordinates":[-74.0143585205,45.7912826538],"type":"Point"}
}