{
  "type": "Feature",
  "properties": {
    "iso:country":"CA",
    "sg:address":"1391 Mission Flats Rd",
    "sg:city":"Kamloops",
    "sg:phone":"+1 250 374 0614",
    "sg:postcode":"V2C 1A9",
    "sg:province":"BC",
    "sg:tags":[
        "oil"
    ],
    "wof:name":"Cool Creek Agencies Ltd",
    "wof:placetype":"venue"
},
  "geometry": {"coordinates":[-120.371498108,50.6826820374],"type":"Point"}
}