{
  "type": "Feature",
  "properties": {
    "addr:full":"1391 Mission Flats Rd Kamloops BC V2C 1A9",
    "addr:housenumber":"1391",
    "addr:postcode":"bc v2c 1a9",
    "addr:street":"Mission Flats Rd",
    "iso:country":"CA",
    "sg:address":"1391 Mission Flats Rd",
    "sg:city":"Kamloops",
    "sg:phone":"+1 250 374 0614",
    "sg:postcode":"V2C 1A9",
    "sg:province":"BC",
    "sg:tags":[
        "oil"
    ],
    "wof:name":"Cool Creek Agencies Ltd",
    "wof:placetype":"venue"
},
  "geometry": {"coordinates":[-120.371498108,50.6826820374],"type":"Point"}
}