{
  "type": "Feature",
  "properties": {
    "addr:full":"92 Merit Cres West St Paul MB R2P 2W5",
    "addr:housenumber":"92",
    "addr:postcode":"r2p 2w5",
    "addr:street":"Merit Cres West",
    "iso:country":"CA",
    "sg:address":"92 Merit Cres",
    "sg:city":"West St Paul",
    "sg:classifiers":[
        {
            "category":"Building & Trades",
            "subcategory":"Construction",
            "type":"Services"
        }
    ],
    "sg:phone":"+1 204 334 4705",
    "sg:postcode":"R2P 2W5",
    "sg:province":"MB",
    "sg:tags":[
        "general",
        "contractor"
    ],
    "wof:name":"Permanent Builders Ltd",
    "wof:placetype":"venue"
},
  "geometry": {"coordinates":[-97.11592899999999,49.982838],"type":"Point"}
}