{
  "type": "Feature",
  "properties": {
    "addr:full":"261 Brackley Point Rd Charlottetown PE C1E 2A3",
    "addr:housenumber":"261",
    "addr:postcode":"c1e 2a3",
    "addr:street":"Brackley Point Rd",
    "iso:country":"CA",
    "sg:address":"261 Brackley Point Rd",
    "sg:city":"Charlottetown",
    "sg:classifiers":[
        {
            "category":"Travel",
            "subcategory":"Hotels & Motels",
            "type":"Entertainment"
        }
    ],
    "sg:phone":"+1 902 566 3373",
    "sg:postcode":"C1E 2A3",
    "sg:province":"PE",
    "sg:tags":[
        "tourist",
        "accommodation"
    ],
    "wof:name":"Princess Motel",
    "wof:placetype":"venue"
},
  "geometry": {"coordinates":[-63.1351318359,46.2812538147],"type":"Point"}
}