{
  "type": "Feature",
  "properties": {
    "addr:full":"Melville SK S0A 2P0",
    "addr:postcode":"s0a 2p0",
    "iso:country":"CA",
    "sg:city":"Melville",
    "sg:classifiers":[
        {
            "category":"Government",
            "subcategory":"Office",
            "type":"Public Place"
        }
    ],
    "sg:phone":"+1 306 728 6850",
    "sg:postcode":"S0A 2P0",
    "sg:province":"SK",
    "sg:tags":[
        "village"
    ],
    "wof:name":"Melville City Utility",
    "wof:placetype":"venue"
},
  "geometry": {"coordinates":[-102.818237305,50.9316902161],"type":"Point"}
}