{
  "type": "Feature",
  "properties": {
    "addr:full":"Sherwood Park AB T8A 5V3",
    "addr:postcode":"t8a 5v3",
    "iso:country":"CA",
    "sg:city":"Sherwood Park",
    "sg:classifiers":[
        {
            "category":"Personal",
            "type":"Services"
        }
    ],
    "sg:phone":"+1 780 449 1081",
    "sg:postcode":"T8A 5V3",
    "sg:province":"AB",
    "sg:tags":[
        "therapist",
        "massage"
    ],
    "wof:name":"Healthy Balance Massage Thrpy",
    "wof:placetype":"venue"
},
  "geometry": {"coordinates":[-113.295418,53.528767],"type":"Point"}
}