{
  "type": "Feature",
  "properties": {
    "iso:country":"CA",
    "sg:address":"55 Mill St",
    "sg:city":"Toronto",
    "sg:classifiers":[
        {
            "category":"Wholesale",
            "subcategory":"Groceries",
            "type":"Manufacturing & Wholesale Goods"
        }
    ],
    "sg:phone":"+1 416 207 1709",
    "sg:postcode":"M5A 3C4",
    "sg:province":"ON",
    "sg:tags":[
        "tea",
        "coffee"
    ],
    "wof:name":"Balzac's Coffee Roastery",
    "wof:placetype":"venue"
},
  "geometry": {"coordinates":[-79.3601150513,43.65051651],"type":"Point"}
}