{
  "type": "Feature",
  "properties": {
    "iso:country":"CA",
    "sg:address":"4100 27 Ave",
    "sg:city":"Vernon",
    "sg:classifiers":[
        {
            "category":"Organizations",
            "subcategory":"Religious Organization",
            "type":"Services"
        }
    ],
    "sg:phone":"+1 250 545 6253",
    "sg:postcode":"V1T 1T1",
    "sg:province":"BC",
    "sg:tags":[
        "church"
    ],
    "wof:name":"Ukrainian Orthodox Church",
    "wof:placetype":"venue"
},
  "geometry": {"coordinates":[-119.29189300500001,50.2615203857],"type":"Point"}
}