{
  "type": "Feature",
  "properties": {
    "addr:full":"149 Woodfield Rd Toronto ON M4L 2W8",
    "addr:housenumber":"149",
    "addr:postcode":"m4l 2w8",
    "addr:street":"Woodfield Rd",
    "iso:country":"CA",
    "sg:address":"149 Woodfield Rd",
    "sg:city":"Toronto",
    "sg:classifiers":[
        {
            "category":"Personal",
            "subcategory":"Beauty Salon",
            "type":"Services"
        }
    ],
    "sg:phone":"+1 416 466 9347",
    "sg:postcode":"M4L 2W8",
    "sg:province":"ON",
    "wof:name":"Helen's House of Hair",
    "wof:placetype":"venue"
},
  "geometry": {"coordinates":[-79.32231899999999,43.668327],"type":"Point"}
}