{
  "type": "Feature",
  "properties": {
    "addr:full":"101 Queensway W # 300 Mississauga ON L5B 2P7",
    "addr:housenumber":"101",
    "addr:postcode":"l5b 2p7",
    "addr:street":"Queensway W # 300",
    "iso:country":"CA",
    "sg:address":"101 Queensway W # 300",
    "sg:city":"Mississauga",
    "sg:classifiers":[
        {
            "category":"Professional",
            "subcategory":"Accounting & Tax Preparation",
            "type":"Services"
        }
    ],
    "sg:phone":"+1 905 566 0037",
    "sg:postcode":"L5B 2P7",
    "sg:province":"ON",
    "sg:tags":[
        "accountant"
    ],
    "wof:name":"Marcia Mc Cann & Assoc",
    "wof:placetype":"venue"
},
  "geometry": {"coordinates":[-79.6106872559,43.5718040466],"type":"Point"}
}