{
  "type": "Feature",
  "properties": {
    "addr:full":"3571 Rue Sainte-Catherine E Montreal QC H1W 2E6",
    "addr:housenumber":"3571",
    "addr:postcode":"h1w 2e6",
    "addr:street":"Rue Sainte-Catherine E",
    "iso:country":"CA",
    "sg:address":"3571 Rue Sainte-Catherine E",
    "sg:city":"Montreal",
    "sg:classifiers":[
        {
            "category":"Food & Beverages",
            "subcategory":"Groceries & Convenience Stores",
            "type":"Retail Goods"
        }
    ],
    "sg:phone":"+1 514 524 4445",
    "sg:postcode":"H1W 2E6",
    "sg:province":"QC",
    "wof:name":"Depanneur Tina",
    "wof:placetype":"venue"
},
  "geometry": {"coordinates":[-73.53881072999999,45.5431556702],"type":"Point"}
}