{
  "type": "Feature",
  "properties": {
    "addr:full":"3232 Grand Marais Rd E Windsor ON N8W 1W6",
    "addr:housenumber":"3232",
    "addr:postcode":"n8w 1w6",
    "addr:street":"Grand Marais Rd E",
    "iso:country":"CA",
    "sg:address":"3232 Grand Marais Rd E",
    "sg:city":"Windsor",
    "sg:classifiers":[
        {
            "category":"Manufacturing",
            "subcategory":"Tools & Machinery",
            "type":"Manufacturing & Wholesale Goods"
        }
    ],
    "sg:phone":"+1 519 948 1361",
    "sg:postcode":"N8W 1W6",
    "sg:province":"ON",
    "sg:tags":[
        "die",
        "maker"
    ],
    "wof:name":"Essex Service Machine & Tool",
    "wof:placetype":"venue"
},
  "geometry": {"coordinates":[-82.97685199999999,42.292908],"type":"Point"}
}