{
  "type": "Feature",
  "properties": {
    "addr:full":"31 Maxwell Dr Kitchener ON N2R 1A3",
    "addr:housenumber":"31",
    "addr:postcode":"n2r 1a3",
    "addr:street":"Maxwell Dr",
    "iso:country":"CA",
    "sg:address":"31 Maxwell Dr",
    "sg:city":"Kitchener",
    "sg:classifiers":[
        {
            "category":"Professional",
            "subcategory":"Advertising",
            "type":"Services"
        }
    ],
    "sg:phone":"+1 519 748 5601",
    "sg:postcode":"N2R 1A3",
    "sg:province":"ON",
    "sg:tags":[
        "counselor"
    ],
    "wof:name":"Wayne Gregory Advertising",
    "wof:placetype":"venue"
},
  "geometry": {"coordinates":[-80.457863,43.395725],"type":"Point"}
}