{
  "type": "Feature",
  "properties": {
    "addr:full":"Toronto ON M4P 3H1",
    "addr:postcode":"m4p 3h1",
    "iso:country":"CA",
    "sg:city":"Toronto",
    "sg:classifiers":[
        {
            "category":"Health Services",
            "subcategory":"Doctor",
            "type":"Services"
        }
    ],
    "sg:phone":"+1 416 486 9600",
    "sg:postcode":"M4P 3H1",
    "sg:province":"ON",
    "sg:tags":[
        "physician",
        "surgeon"
    ],
    "wof:name":"Mozes, R S MD",
    "wof:placetype":"venue"
},
  "geometry": {"coordinates":[-79.39888000489999,43.7100753784],"type":"Point"}
}