{
  "type": "Feature",
  "properties": {
    "addr:full":"244 Grantham Ave St Catharines ON L2M 4Z4",
    "addr:housenumber":"244",
    "addr:postcode":"l2m 4z4",
    "addr:street":"Grantham Ave",
    "iso:country":"CA",
    "sg:address":"244 Grantham Ave",
    "sg:city":"St Catharines",
    "sg:classifiers":[
        {
            "category":"Personal",
            "subcategory":"Beauty Salon",
            "type":"Services"
        }
    ],
    "sg:phone":"+1 905 937 1623",
    "sg:postcode":"L2M 4Z4",
    "sg:province":"ON",
    "wof:name":"Salon 244",
    "wof:placetype":"venue"
},
  "geometry": {"coordinates":[-79.220207,43.175697],"type":"Point"}
}