{
  "type": "Feature",
  "properties": {
    "addr:full":"15483 Kilmore Crt Surrey BC V3S 6N8",
    "addr:housenumber":"15483",
    "addr:postcode":"v3s 6n8",
    "addr:street":"Kilmore Crt",
    "iso:country":"CA",
    "sg:address":"15483 Kilmore Crt",
    "sg:city":"Surrey",
    "sg:classifiers":[
        {
            "category":"Wholesale",
            "subcategory":"Electrical",
            "type":"Manufacturing & Wholesale Goods"
        }
    ],
    "sg:phone":"+1 604 574 3946",
    "sg:postcode":"V3S 6N8",
    "sg:province":"BC",
    "sg:tags":[
        "control"
    ],
    "wof:name":"Summetrix System Integration",
    "wof:placetype":"venue"
},
  "geometry": {"coordinates":[-122.793205,49.105618],"type":"Point"}
}