{
  "type": "Feature",
  "properties": {
    "iso:country":"CA",
    "sg:address":"12 10E Rue",
    "sg:city":"Forestville",
    "sg:classifiers":[
        {
            "category":"Sports & Exercise",
            "subcategory":"Bowling",
            "type":"Entertainment"
        }
    ],
    "sg:phone":"+1 418 587 2228",
    "sg:postcode":"G0T 1E0",
    "sg:province":"QC",
    "sg:tags":[
        "center"
    ],
    "wof:name":"Quillorama Forestville Inc",
    "wof:placetype":"venue"
},
  "geometry": {"coordinates":[-69.0793762207,48.7452354431],"type":"Point"}
}