{
  "type": "Feature",
  "properties": {
    "addr:full":"21 Division St N Kingsville ON N9Y 1C7",
    "addr:housenumber":"21",
    "addr:postcode":"n9y 1c7",
    "addr:street":"Division St N",
    "iso:country":"CA",
    "sg:address":"21 Division St N",
    "sg:city":"Kingsville",
    "sg:classifiers":[
        {
            "category":"Personal",
            "subcategory":"Beauty Salon",
            "type":"Services"
        }
    ],
    "sg:phone":"+1 519 733 6040",
    "sg:postcode":"N9Y 1C7",
    "sg:province":"ON",
    "wof:name":"Accent Hairstyles",
    "wof:placetype":"venue"
},
  "geometry": {"coordinates":[-82.739372,42.03846],"type":"Point"}
}