{
  "type": "Feature",
  "properties": {
    "addr:full":"351 Boul Samson Laval QC H7X 2Z7",
    "addr:housenumber":"351",
    "addr:postcode":"h7x 2z7",
    "addr:street":"Boul Samson",
    "iso:country":"CA",
    "sg:address":"351 Boul Samson",
    "sg:city":"Laval",
    "sg:classifiers":[
        {
            "category":"Recreation",
            "type":"Entertainment"
        }
    ],
    "sg:phone":"+1 450 689 1800",
    "sg:postcode":"H7X 2Z7",
    "sg:province":"QC",
    "sg:tags":[
        "balloon"
    ],
    "wof:name":"Ballons Dirigeables Vision-Air",
    "wof:placetype":"venue"
},
  "geometry": {"coordinates":[-73.802902,45.523952],"type":"Point"}
}