{
  "type": "Feature",
  "properties": {
    "addr:full":"11003 Tahltan Rd Fort St John BC V1J 6G8",
    "addr:housenumber":"11003",
    "addr:postcode":"v1j 6g8",
    "addr:street":"Tahltan Rd",
    "iso:country":"CA",
    "sg:address":"11003 Tahltan Rd",
    "sg:city":"Fort St John",
    "sg:classifiers":[
        {
            "category":"Retail",
            "subcategory":"Repair Shop",
            "type":"Services"
        }
    ],
    "sg:phone":"+1 250 785 2423",
    "sg:postcode":"V1J 6G8",
    "sg:province":"BC",
    "sg:tags":[
        "excavating",
        "contractor",
        "welding"
    ],
    "wof:name":"Surerus Pipeline Inc",
    "wof:placetype":"venue"
},
  "geometry": {"coordinates":[-120.863945,56.240196],"type":"Point"}
}