{
  "type": "Feature",
  "properties": {
    "addr:full":"Azilda ON P0M 1B0",
    "addr:postcode":"p0m 1b0",
    "iso:country":"CA",
    "sg:city":"Azilda",
    "sg:classifiers":[
        {
            "category":"Wholesale",
            "subcategory":"Auto Parts",
            "type":"Manufacturing & Wholesale Goods"
        }
    ],
    "sg:phone":"+1 705 983 2220",
    "sg:postcode":"P0M 1B0",
    "sg:province":"ON",
    "sg:tags":[
        "automobile",
        "wrecking"
    ],
    "wof:name":"Azilda Auto Wreckers",
    "wof:placetype":"venue"
},
  "geometry": {"coordinates":[-81.123734,46.558411],"type":"Point"}
}