{
  "type": "Feature",
  "properties": {
    "addr:full":"1064 Bustin Ave Lower Sackville NS B4E 1K9",
    "addr:housenumber":"1064",
    "addr:postcode":"b4e 1k9",
    "addr:street":"Bustin Ave",
    "iso:country":"CA",
    "sg:address":"1064 Bustin Ave",
    "sg:city":"Lower Sackville",
    "sg:classifiers":[
        {
            "category":"Real Estate",
            "subcategory":"Real Estate Operator",
            "type":"Services"
        }
    ],
    "sg:phone":"+1 902 865 2700",
    "sg:postcode":"B4E 1K9",
    "sg:province":"NS",
    "sg:tags":[
        "mobile",
        "home",
        "community"
    ],
    "wof:name":"Springfield Estates",
    "wof:placetype":"venue"
},
  "geometry": {"coordinates":[-63.695839,44.776299],"type":"Point"}
}