{
  "type": "Feature",
  "properties": {
    "addr:full":"2137 Innisfil Beach Rd Innisfil ON L9S 1A2",
    "addr:housenumber":"2137",
    "addr:postcode":"l9s 1a2",
    "addr:street":"Innisfil Beach Rd",
    "iso:country":"CA",
    "sg:address":"2137 Innisfil Beach Rd",
    "sg:city":"Innisfil",
    "sg:classifiers":[
        {
            "category":"Government",
            "subcategory":"Police Station",
            "type":"Public Place"
        }
    ],
    "sg:phone":"+1 705 436 2141",
    "sg:postcode":"L9S 1A2",
    "sg:province":"ON",
    "sg:tags":[
        "department"
    ],
    "wof:name":"Innisfil Police Svc",
    "wof:placetype":"venue"
},
  "geometry": {"coordinates":[-79.60717010499999,44.3012962341],"type":"Point"}
}