{
  "type": "Feature",
  "properties": {
    "iso:country":"CA",
    "sg:city":"LA Broquerie",
    "sg:classifiers":[
        {
            "category":"Farming",
            "subcategory":"Dairy Farm",
            "type":"Manufacturing & Wholesale Goods"
        }
    ],
    "sg:phone":"+1 204 424 9729",
    "sg:postcode":"R0A 0W0",
    "sg:province":"MB",
    "wof:name":"LA Bass Holstens Ltd",
    "wof:placetype":"venue"
},
  "geometry": {"coordinates":[-96.5105667114,49.480670929],"type":"Point"}
}