{
  "type": "Feature",
  "properties": {
    "iso:country":"CA",
    "sg:address":"1682 Victoria Park Ave",
    "sg:city":"North York",
    "sg:classifiers":[
        {
            "category":"Building & Trades",
            "subcategory":"Cleaning & Sanitation",
            "type":"Services"
        }
    ],
    "sg:phone":"+1 416 421 2505",
    "sg:postcode":"M1R 1P7",
    "sg:province":"ON",
    "sg:tags":[
        "janitor"
    ],
    "wof:name":"Jeeves Janitorial & Carpet",
    "wof:placetype":"venue"
},
  "geometry": {"coordinates":[-79.3059387207,43.7324333191],"type":"Point"}
}