{
  "type": "Feature",
  "properties": {
    "addr:full":"7516 Gateway Blvd NW Edmonton AB T6E 6E8",
    "addr:housenumber":"7516",
    "addr:postcode":"t6e 6e8",
    "addr:street":"Gateway Blvd Nw",
    "iso:country":"CA",
    "sg:address":"7516 Gateway Blvd NW",
    "sg:city":"Edmonton",
    "sg:classifiers":[
        {
            "category":"Shopping",
            "subcategory":"Clothing, Apparel, & Fashions",
            "type":"Retail Goods"
        }
    ],
    "sg:phone":"+1 780 439 9914",
    "sg:postcode":"T6E 6E8",
    "sg:province":"AB",
    "sg:tags":[
        "breast",
        "artificial"
    ],
    "wof:name":"Gracefully Yours",
    "wof:placetype":"venue"
},
  "geometry": {"coordinates":[-113.494698,53.511402],"type":"Point"}
}