{
  "type": "Feature",
  "properties": {
    "addr:full":"1035 King St W Hamilton ON L8S 1L6",
    "addr:housenumber":"1035",
    "addr:postcode":"l8s 1l6",
    "addr:street":"King St W",
    "iso:country":"CA",
    "sg:address":"1035 King St W",
    "sg:city":"Hamilton",
    "sg:classifiers":[
        {
            "category":"Shopping",
            "subcategory":"Clothing, Apparel, & Fashions",
            "type":"Retail Goods"
        }
    ],
    "sg:phone":"+1 905 529 1106",
    "sg:postcode":"L8S 1L6",
    "sg:province":"ON",
    "sg:tags":[
        "furnishing"
    ],
    "wof:name":"Villager",
    "wof:placetype":"venue"
},
  "geometry": {"coordinates":[-79.906403,43.261517],"type":"Point"}
}