{
  "type": "Feature",
  "properties": {
    "addr:full":"320 Boul Saint-Joseph #101 Hull QC J8Y 3Y8",
    "addr:housenumber":"320",
    "addr:postcode":"j8y 3y8",
    "addr:street":"Boul Saint-Joseph # 101",
    "iso:country":"CA",
    "sg:address":"320 Boul Saint-Joseph #101",
    "sg:city":"Hull",
    "sg:classifiers":[
        {
            "category":"Shopping",
            "subcategory":"Bicycles & Sporting Goods",
            "type":"Retail Goods"
        }
    ],
    "sg:phone":"+1 819 775 9500",
    "sg:postcode":"J8Y 3Y8",
    "sg:province":"QC",
    "wof:name":"Super Monde Des Athletes",
    "wof:placetype":"venue"
},
  "geometry": {"coordinates":[-75.73267364500001,45.4412155151],"type":"Point"}
}