{
  "type": "Feature",
  "properties": {
    "addr:full":"3184 Holbrook Rd Pinantan Lake BC V0E 3E1",
    "addr:housenumber":"3184",
    "addr:postcode":"bc v0e 3e1",
    "addr:street":"Holbrook Rd",
    "iso:country":"CA",
    "sg:address":"3184 Holbrook Rd",
    "sg:city":"Pinantan Lake",
    "sg:classifiers":[
        {
            "category":"Building & Trades",
            "subcategory":"Landscaping Services",
            "type":"Services"
        }
    ],
    "sg:phone":"+1 250 318 5240",
    "sg:postcode":"V0E 3E1",
    "sg:province":"BC",
    "sg:tags":[
        "tree",
        "landscape",
        "contractor"
    ],
    "wof:name":"Stumped Tree Svc",
    "wof:placetype":"venue"
},
  "geometry": {"coordinates":[-120.025192,50.729549],"type":"Point"}
}