{
  "type": "Feature",
  "properties": {
    "iso:country":"CA",
    "sg:address":"15 Cobequid Rd",
    "sg:city":"Lower Sackville",
    "sg:classifiers":[
        {
            "category":"Retail",
            "subcategory":"Veterinary Services",
            "type":"Services"
        }
    ],
    "sg:phone":"+1 902 865 8110",
    "sg:postcode":"B4C 2M9",
    "sg:province":"NS",
    "sg:tags":[
        "veterinarian"
    ],
    "wof:name":"Moncayo, Fernando DVM",
    "wof:placetype":"venue"
},
  "geometry": {"coordinates":[-63.663974762,44.7527961731],"type":"Point"}
}