{
  "type": "Feature",
  "properties": {
    "addr:full":"264 Douglas Rd Fort St James BC V0J 1P0",
    "addr:housenumber":"264",
    "addr:postcode":"v0j 1p0",
    "addr:street":"Douglas Rd",
    "iso:country":"CA",
    "sg:address":"264 Douglas Rd",
    "sg:city":"Fort St James",
    "sg:classifiers":[
        {
            "category":"Wholesale",
            "subcategory":"Machinery & Supplies",
            "type":"Manufacturing & Wholesale Goods"
        }
    ],
    "sg:phone":"+1 250 996 7466",
    "sg:postcode":"V0J 1P0",
    "sg:province":"BC",
    "sg:tags":[
        "truck"
    ],
    "wof:name":"Fort Diesel",
    "wof:placetype":"venue"
},
  "geometry": {"coordinates":[-124.288956,54.457569],"type":"Point"}
}