{
  "type": "Feature",
  "properties": {
    "addr:full":"Ottawa ON K1H 8K2",
    "addr:postcode":"k1h 8k2",
    "iso:country":"CA",
    "sg:city":"Ottawa",
    "sg:classifiers":[
        {
            "category":"Shopping",
            "subcategory":"Luggage & Leather Goods",
            "type":"Retail Goods"
        }
    ],
    "sg:phone":"+1 613 523 3719",
    "sg:postcode":"K1H 8K2",
    "sg:province":"ON",
    "wof:name":"Bentley Leather Inc",
    "wof:placetype":"venue"
},
  "geometry": {"coordinates":[-75.6797409058,45.3866271973],"type":"Point"}
}