{
  "type": "Feature",
  "properties": {
    "addr:full":"2085 Boul Decarie Montreal QC H4A 3J2",
    "addr:housenumber":"2085",
    "addr:postcode":"h4a 3j2",
    "addr:street":"Boul Decarie",
    "iso:country":"CA",
    "sg:address":"2085 Boul Decarie",
    "sg:city":"Montreal",
    "sg:classifiers":[
        {
            "category":"Real Estate",
            "subcategory":"Real Estate Operator",
            "type":"Services"
        }
    ],
    "sg:phone":"+1 514 485 6496",
    "sg:postcode":"H4A 3J2",
    "sg:province":"QC",
    "sg:tags":[
        "apartment"
    ],
    "wof:name":"Propriete L-S Properties",
    "wof:placetype":"venue"
},
  "geometry": {"coordinates":[-73.607094,45.473679],"type":"Point"}
}