{
  "type": "Feature",
  "properties": {
    "addr:full":"5405 Av Trudeau # 1 Saint-Hyacinthe QC J2S 7W9",
    "addr:housenumber":"5405",
    "addr:postcode":"j2s 7w9",
    "addr:street":"Av Trudeau # 1",
    "iso:country":"CA",
    "sg:address":"5405 Av Trudeau # 1",
    "sg:city":"Saint-Hyacinthe",
    "sg:classifiers":[
        {
            "category":"Professional",
            "subcategory":"Business Services",
            "type":"Services"
        }
    ],
    "sg:phone":"+1 450 261 1109",
    "sg:postcode":"J2S 7W9",
    "sg:province":"QC",
    "sg:tags":[
        "painter",
        "sign"
    ],
    "wof:name":"Lettrage Maska Design",
    "wof:placetype":"venue"
},
  "geometry": {"coordinates":[-72.97575399999999,45.63464],"type":"Point"}
}