{
  "type": "Feature",
  "properties": {
    "iso:country":"CA",
    "sg:address":"PO Box 282",
    "sg:city":"Rossburn",
    "sg:classifiers":[
        {
            "category":"Organizations",
            "subcategory":"Religious Organization",
            "type":"Services"
        }
    ],
    "sg:phone":"+1 204 859 2260",
    "sg:postcode":"R0J 1V0",
    "sg:province":"MB",
    "sg:tags":[
        "church"
    ],
    "wof:name":"Rossburn United Church",
    "wof:placetype":"venue"
},
  "geometry": {"coordinates":[-100.81082916299999,50.6689682007],"type":"Point"}
}