{
  "type": "Feature",
  "properties": {
    "addr:full":"182 Rue Wellington N Sherbrooke QC J1H 5C5",
    "addr:housenumber":"182",
    "addr:postcode":"j1h 5c5",
    "addr:street":"Rue Wellington N",
    "iso:country":"CA",
    "sg:address":"182 Rue Wellington N",
    "sg:city":"Sherbrooke",
    "sg:classifiers":[
        {
            "category":"Restaurant",
            "type":"Food & Drink"
        }
    ],
    "sg:phone":"+1 819 562 1800",
    "sg:postcode":"J1H 5C5",
    "sg:province":"QC",
    "wof:name":"Antiquarius Cafe",
    "wof:placetype":"venue"
},
  "geometry": {"coordinates":[-71.89164700000001,45.403797],"type":"Point"}
}