{
  "type": "Feature",
  "properties": {
    "iso:country":"CA",
    "sg:address":"7161 Rte Sir-Wilfrid-Laurier",
    "sg:city":"Mirabel",
    "sg:classifiers":[
        {
            "category":"Farming",
            "subcategory":"Farm",
            "type":"Manufacturing & Wholesale Goods"
        }
    ],
    "sg:phone":"+1 450 258 2117",
    "sg:postcode":"J7N 1L6",
    "sg:province":"QC",
    "wof:name":"Ferme Bourgeois Enr",
    "wof:placetype":"venue"
},
  "geometry": {"coordinates":[-74.1361160278,45.694770813],"type":"Point"}
}