{
  "type": "Feature",
  "properties": {
    "addr:full":"115 Park St N Hamilton ON L8R 2N2",
    "addr:housenumber":"115",
    "addr:postcode":"l8r 2n2",
    "addr:street":"Park St N",
    "iso:country":"CA",
    "sg:address":"115 Park St N",
    "sg:city":"Hamilton",
    "sg:classifiers":[
        {
            "category":"Restaurant",
            "type":"Food & Drink"
        }
    ],
    "sg:phone":"+1 905 528 6888",
    "sg:postcode":"L8R 2N2",
    "sg:province":"ON",
    "wof:name":"B & T Restaurant",
    "wof:placetype":"venue"
},
  "geometry": {"coordinates":[-79.87074279789999,43.2611312866],"type":"Point"}
}