{
  "type": "Feature",
  "properties": {
    "addr:full":"9th Ave N Regina SK S4P 3C6",
    "addr:postcode":"s4p 3c6",
    "addr:street":"9Th Ave N",
    "iso:country":"CA",
    "sg:address":"9th Ave N",
    "sg:city":"Regina",
    "sg:classifiers":[
        {
            "category":"Wholesale",
            "subcategory":"Farm Supplies",
            "type":"Manufacturing & Wholesale Goods"
        }
    ],
    "sg:phone":"+1 306 543 4777",
    "sg:postcode":"S4P 3C6",
    "sg:province":"SK",
    "sg:tags":[
        "eggs"
    ],
    "wof:name":"O & T Poultry Farms Ltd",
    "wof:placetype":"venue"
},
  "geometry": {"coordinates":[-104.577552795,50.4823913574],"type":"Point"}
}