{
  "type": "Feature",
  "properties": {
    "addr:full":"325 Mcdonald St N Regina SK S4N 7M1",
    "addr:housenumber":"325",
    "addr:postcode":"s4n 7m1",
    "addr:street":"Mcdonald St N",
    "iso:country":"CA",
    "sg:address":"325 Mcdonald St N",
    "sg:city":"Regina",
    "sg:classifiers":[
        {
            "category":"Wholesale",
            "subcategory":"Petroleum",
            "type":"Manufacturing & Wholesale Goods"
        }
    ],
    "sg:phone":"+1 306 543 3077",
    "sg:postcode":"S4N 7M1",
    "sg:province":"SK",
    "sg:tags":[
        "pipe",
        "line",
        "company"
    ],
    "wof:name":"Plains Marketing Canada Lp",
    "wof:placetype":"venue"
},
  "geometry": {"coordinates":[-104.57257799999999,50.480579],"type":"Point"}
}