{
  "type": "Feature",
  "properties": {
    "addr:full":"22 Alford Cres Scarborough ON M1B 4C8",
    "addr:housenumber":"22",
    "addr:postcode":"m1b 4c8",
    "addr:street":"Alford Cres",
    "iso:country":"CA",
    "sg:address":"22 Alford Cres",
    "sg:city":"Scarborough",
    "sg:classifiers":[
        {
            "category":"Organizations",
            "subcategory":"Labor Organization",
            "type":"Services"
        }
    ],
    "sg:phone":"+1 416 281 9423",
    "sg:postcode":"M1B 4C8",
    "sg:province":"ON",
    "wof:name":"Caw",
    "wof:placetype":"venue"
},
  "geometry": {"coordinates":[-79.21307400000001,43.809288],"type":"Point"}
}