{
  "type": "Feature",
  "properties": {
    "iso:country":"CA",
    "sg:address":"530 Vidal St S",
    "sg:city":"Sarnia",
    "sg:classifiers":[
        {
            "category":"Building & Trades",
            "subcategory":"Plumbing",
            "type":"Services"
        }
    ],
    "sg:phone":"+1 519 332 8277",
    "sg:postcode":"N7T 8E7",
    "sg:province":"ON",
    "sg:tags":[
        "sheet",
        "work",
        "metal",
        "contractor"
    ],
    "wof:name":"Mc Intosh Mechanical Inc",
    "wof:placetype":"venue"
},
  "geometry": {"coordinates":[-82.40874481199999,42.9555053711],"type":"Point"}
}