{
  "type": "Feature",
  "properties": {
    "addr:full":"7 Manitoba St Bracebridge ON P1L 1S4",
    "addr:housenumber":"7",
    "addr:postcode":"p1l 1s4",
    "addr:street":"Manitoba St",
    "iso:country":"CA",
    "sg:address":"7 Manitoba St",
    "sg:city":"Bracebridge",
    "sg:classifiers":[
        {
            "category":"Shopping",
            "subcategory":"Clothing, Apparel, & Fashions",
            "type":"Retail Goods"
        }
    ],
    "sg:phone":"+1 705 645 3131",
    "sg:postcode":"P1L 1S4",
    "sg:province":"ON",
    "sg:tags":[
        "sporting"
    ],
    "wof:name":"Campbell Sports",
    "wof:placetype":"venue"
},
  "geometry": {"coordinates":[-79.30884552000001,45.0405578613],"type":"Point"}
}