{
  "type": "Feature",
  "properties": {
    "iso:country":"CA",
    "sg:city":"Saint-Jean-DE-Dieu",
    "sg:classifiers":[
        {
            "category":"Sports & Exercise",
            "subcategory":"Golf",
            "type":"Entertainment"
        }
    ],
    "sg:phone":"+1 418 963 4653",
    "sg:postcode":"G0L 3M0",
    "sg:province":"QC",
    "sg:tags":[
        "course"
    ],
    "wof:name":"Club DE Golf Coop",
    "wof:placetype":"venue"
},
  "geometry": {"coordinates":[-69.0458450317,48.0079879761],"type":"Point"}
}