{
  "type": "Feature",
  "properties": {
    "addr:full":"St Catharines ON L2R 3X4",
    "addr:postcode":"l2r 3x4",
    "iso:country":"CA",
    "sg:city":"St Catharines",
    "sg:classifiers":[
        {
            "category":"Professional",
            "subcategory":"Art Services",
            "type":"Services"
        }
    ],
    "sg:phone":"+1 905 988 9202",
    "sg:postcode":"L2R 3X4",
    "sg:province":"ON",
    "sg:tags":[
        "graphic",
        "designer"
    ],
    "wof:name":"Car & Other Enterprises",
    "wof:placetype":"venue"
},
  "geometry": {"coordinates":[-79.2274475098,43.1626052856],"type":"Point"}
}