{
  "type": "Feature",
  "properties": {
    "addr:full":"4765 Old Scugog Rd RR 1 Bowmanville ON L1C 3K2",
    "addr:housenumber":"4765",
    "addr:postcode":"l1c 3k2",
    "addr:street":"Old Scugog Rd",
    "iso:country":"CA",
    "sg:address":"4765 Old Scugog Rd RR 1",
    "sg:city":"Bowmanville",
    "sg:classifiers":[
        {
            "category":"Home & Garden",
            "subcategory":"Garden Supply",
            "type":"Retail Goods"
        }
    ],
    "sg:phone":"+1 905 263 8814",
    "sg:postcode":"L1C 3K2",
    "sg:province":"ON",
    "sg:tags":[
        "nurseryman"
    ],
    "wof:name":"Kobes Nurseries Inc",
    "wof:placetype":"venue"
},
  "geometry": {"coordinates":[-78.73239100000001,43.961151],"type":"Point"}
}