{
  "type": "Feature",
  "properties": {
    "addr:full":"Nouvelle QC G0C 2E0",
    "addr:postcode":"g0c 2e0",
    "iso:country":"CA",
    "sg:city":"Nouvelle",
    "sg:classifiers":[
        {
            "category":"Shopping",
            "subcategory":"Catalog Store",
            "type":"Retail Goods"
        }
    ],
    "sg:phone":"+1 418 794 2209",
    "sg:postcode":"G0C 2E0",
    "sg:province":"QC",
    "sg:tags":[
        "mail",
        "order",
        "internet"
    ],
    "wof:name":"Sears Canada Inc",
    "wof:placetype":"venue"
},
  "geometry": {"coordinates":[-66.307968,48.133633],"type":"Point"}
}