{
  "type": "Feature",
  "properties": {
    "addr:full":"12 Water St Brigus NL A0A 1K0",
    "addr:housenumber":"12",
    "addr:postcode":"a0a 1k0",
    "addr:street":"Water St",
    "iso:country":"CA",
    "sg:address":"12 Water St",
    "sg:city":"Brigus",
    "sg:classifiers":[
        {
            "category":"Travel",
            "subcategory":"Hotels & Motels",
            "type":"Entertainment"
        }
    ],
    "sg:phone":"+1 709 528 3412",
    "sg:postcode":"A0A 1K0",
    "sg:province":"NL",
    "sg:tags":[
        "breakfast",
        "accommodation",
        "bed"
    ],
    "wof:name":"Brittoner Bed & Breakfast",
    "wof:placetype":"venue"
},
  "geometry": {"coordinates":[-53.232132,47.530632],"type":"Point"}
}