{
  "type": "Feature",
  "properties": {
    "iso:country":"CA",
    "sg:address":"99 Rue Chabanel O",
    "sg:city":"Montreal",
    "sg:classifiers":[
        {
            "category":"Parking",
            "type":"Transportation"
        }
    ],
    "sg:phone":"+1 514 381 4013",
    "sg:postcode":"H2N 1C3",
    "sg:province":"QC",
    "sg:tags":[
        "garage"
    ],
    "wof:name":"Stationnement Metropolitain",
    "wof:placetype":"venue"
},
  "geometry": {"coordinates":[-73.650742,45.545265],"type":"Point"}
}