{
  "type": "Feature",
  "properties": {
    "addr:full":"1881 Rue Principale Pohenegamook QC G0L 1J0",
    "addr:housenumber":"1881",
    "addr:postcode":"g0l 1j0",
    "addr:street":"Rue Principale",
    "iso:country":"CA",
    "sg:address":"1881 Rue Principale",
    "sg:city":"Pohenegamook",
    "sg:classifiers":[
        {
            "category":"Food & Beverages",
            "subcategory":"Groceries & Convenience Stores",
            "type":"Retail Goods"
        }
    ],
    "sg:phone":"+1 418 859 2055",
    "sg:postcode":"G0L 1J0",
    "sg:province":"QC",
    "wof:name":"Depanneur Quatre-Temps Enr",
    "wof:placetype":"venue"
},
  "geometry": {"coordinates":[-69.28054,47.486454],"type":"Point"}
}