{
  "type": "Feature",
  "properties": {
    "addr:full":"11315 182 St NW Edmonton AB T5S 1R3",
    "addr:housenumber":"11315",
    "addr:postcode":"t5s 1r3",
    "addr:street":"182 St Nw",
    "iso:country":"CA",
    "sg:address":"11315 182 St NW",
    "sg:city":"Edmonton",
    "sg:classifiers":[
        {
            "category":"Restaurant",
            "type":"Food & Drink"
        }
    ],
    "sg:phone":"+1 780 930 7700",
    "sg:postcode":"T5S 1R3",
    "sg:province":"AB",
    "sg:tags":[
        "beverage"
    ],
    "wof:name":"Pepsi-Cola",
    "wof:placetype":"venue"
},
  "geometry": {"coordinates":[-113.635857,53.562012],"type":"Point"}
}