{
  "type": "Feature",
  "properties": {
    "addr:full":"Montague PE C0A 1R0",
    "addr:postcode":"c0a 1r0",
    "iso:country":"CA",
    "sg:city":"Montague",
    "sg:classifiers":[
        {
            "category":"Shopping",
            "subcategory":"Pharmacy",
            "type":"Retail Goods"
        }
    ],
    "sg:phone":"+1 902 838 4961",
    "sg:postcode":"C0A 1R0",
    "sg:province":"PE",
    "wof:name":"Sobeys Pharmacy",
    "wof:placetype":"venue"
},
  "geometry": {"coordinates":[-62.650841,46.17379],"type":"Point"}
}