{
  "type": "Feature",
  "properties": {
    "iso:country":"CA",
    "sg:address":"8550 Boul Taschereau",
    "sg:city":"Brossard",
    "sg:classifiers":[
        {
            "category":"Travel",
            "subcategory":"Hotels & Motels",
            "type":"Entertainment"
        }
    ],
    "sg:phone":"+1 450 466 1565",
    "sg:postcode":"J4X 1C2",
    "sg:province":"QC",
    "wof:name":"Motel L'Oiseau Bleu",
    "wof:placetype":"venue"
},
  "geometry": {"coordinates":[-73.472626,45.443554],"type":"Point"}
}