{
  "type": "Feature",
  "properties": {
    "addr:full":"111 Davisville Ave Toronto ON M4S 1G5",
    "addr:housenumber":"111",
    "addr:postcode":"m4s 1g5",
    "addr:street":"Davisville Ave",
    "iso:country":"CA",
    "sg:address":"111 Davisville Ave",
    "sg:city":"Toronto",
    "sg:classifiers":[
        {
            "category":"Banks & Credit Unions",
            "subcategory":"Investment Brokerage",
            "type":"Services"
        }
    ],
    "sg:phone":"+1 416 481 1850",
    "sg:postcode":"M4S 1G5",
    "sg:province":"ON",
    "sg:tags":[
        "advisory",
        "financial"
    ],
    "wof:name":"Sharp Asset Management Inc",
    "wof:placetype":"venue"
},
  "geometry": {"coordinates":[-79.3928451538,43.6989402771],"type":"Point"}
}