{
  "type": "Feature",
  "properties": {
    "addr:full":"Belsyde E Fergus ON N1M 1Z5",
    "addr:postcode":"n1m 1z5",
    "iso:country":"CA",
    "sg:address":"Belsyde E",
    "sg:city":"Fergus",
    "sg:classifiers":[
        {
            "category":"Organizations",
            "subcategory":"Religious Organization",
            "type":"Services"
        }
    ],
    "sg:phone":"+1 519 843 1118",
    "sg:postcode":"N1M 1Z5",
    "sg:province":"ON",
    "sg:tags":[
        "church"
    ],
    "wof:name":"Canadian Reformed Church",
    "wof:placetype":"venue"
},
  "geometry": {"coordinates":[-80.3666381836,43.7032241821],"type":"Point"}
}