{
  "type": "Feature",
  "properties": {
    "addr:full":"Winnipeg MB R3T 1Z7",
    "addr:postcode":"r3t 1z7",
    "iso:country":"CA",
    "sg:city":"Winnipeg",
    "sg:classifiers":[
        {
            "category":"Food & Beverages",
            "subcategory":"Fruits & Vegetables",
            "type":"Retail Goods"
        }
    ],
    "sg:phone":"+1 204 475 8332",
    "sg:postcode":"R3T 1Z7",
    "sg:province":"MB",
    "sg:tags":[
        "produce"
    ],
    "wof:name":"Vic's Fruit Market",
    "wof:placetype":"venue"
},
  "geometry": {"coordinates":[-97.1522369385,49.8505172729],"type":"Point"}
}