{
  "type": "Feature",
  "properties": {
    "addr:full":"1065 Principale Albertville QC G0J 1A0",
    "addr:housenumber":"1065",
    "addr:postcode":"g0j 1a0",
    "addr:street":"Principale",
    "iso:country":"CA",
    "sg:address":"1065 Principale",
    "sg:city":"Albertville",
    "sg:classifiers":[
        {
            "category":"Restaurant",
            "type":"Food & Drink"
        }
    ],
    "sg:phone":"+1 418 756 3333",
    "sg:postcode":"G0J 1A0",
    "sg:province":"QC",
    "sg:tags":[
        "repairing",
        "automobile"
    ],
    "wof:name":"Garage Coop D'Albertville",
    "wof:placetype":"venue"
},
  "geometry": {"coordinates":[-67.35533100000001,48.326183],"type":"Point"}
}