{
  "type": "Feature",
  "properties": {
    "addr:full":"2442 Boul Royal Shawinigan QC G9N 2W6",
    "addr:housenumber":"2442",
    "addr:postcode":"g9n 2w6",
    "addr:street":"Boul Royal",
    "iso:country":"CA",
    "sg:address":"2442 Boul Royal",
    "sg:city":"Shawinigan",
    "sg:classifiers":[
        {
            "category":"Shopping",
            "subcategory":"Shoes",
            "type":"Retail Goods"
        }
    ],
    "sg:phone":"+1 819 539 4310",
    "sg:postcode":"G9N 2W6",
    "sg:province":"QC",
    "sg:tags":[
        "repairing",
        "boot",
        "shoe"
    ],
    "wof:name":"Cordonnerie Royale",
    "wof:placetype":"venue"
},
  "geometry": {"coordinates":[-72.7423782349,46.5586585999],"type":"Point"}
}