{
  "type": "Feature",
  "properties": {
    "addr:full":"1840 Ontario Ave Saskatoon SK S7K 1T4",
    "addr:housenumber":"1840",
    "addr:postcode":"s7k 1t4",
    "addr:street":"Ontario Ave",
    "iso:country":"CA",
    "sg:address":"1840 Ontario Ave",
    "sg:city":"Saskatoon",
    "sg:classifiers":[
        {
            "category":"Building & Trades",
            "subcategory":"Construction",
            "type":"Services"
        }
    ],
    "sg:phone":"+1 306 652 5525",
    "sg:postcode":"S7K 1T4",
    "sg:province":"SK",
    "sg:tags":[
        "marking",
        "parking",
        "paving",
        "maintenance",
        "contractor"
    ],
    "wof:name":"Asl Paving Ltd",
    "wof:placetype":"venue"
},
  "geometry": {"coordinates":[-106.665939331,52.153881073],"type":"Point"}
}