{
  "type": "Feature",
  "properties": {
    "iso:country":"CA",
    "sg:city":"Kelowna",
    "sg:classifiers":[
        {
            "category":"Personal",
            "subcategory":"Tattoo Parlor",
            "type":"Services"
        }
    ],
    "sg:phone":"+1 250 862 8205",
    "sg:postcode":"V1Y 6N9",
    "sg:province":"BC",
    "sg:tags":[
        "tattooing"
    ],
    "wof:name":"Ritual Tattoo",
    "wof:placetype":"venue"
},
  "geometry": {"coordinates":[-119.492393494,49.886100769],"type":"Point"}
}