{
  "type": "Feature",
  "properties": {
    "addr:full":"1 Alhambra Sq Belleville ON K8N 5V7",
    "addr:housenumber":"1",
    "addr:postcode":"k8n 5v7",
    "addr:street":"Alhambra Sq",
    "iso:country":"CA",
    "sg:address":"1 Alhambra Sq",
    "sg:city":"Belleville",
    "sg:classifiers":[
        {
            "category":"Recreation",
            "type":"Entertainment"
        }
    ],
    "sg:phone":"+1 613 966 1222",
    "sg:postcode":"K8N 5V7",
    "sg:province":"ON",
    "sg:tags":[
        "auditorium",
        "rooms",
        "banquet",
        "hall"
    ],
    "wof:name":"Banquet Centre",
    "wof:placetype":"venue"
},
  "geometry": {"coordinates":[-77.377022,44.177532],"type":"Point"}
}