{
  "type": "Feature",
  "properties": {
    "addr:full":"837 Prospect St Fredericton NB E3B 5Y4",
    "addr:housenumber":"837",
    "addr:postcode":"e3b 5y4",
    "addr:street":"Prospect St",
    "iso:country":"CA",
    "sg:address":"837 Prospect St",
    "sg:city":"Fredericton",
    "sg:classifiers":[
        {
            "category":"Restaurant",
            "type":"Food & Drink"
        }
    ],
    "sg:phone":"+1 506 452 8888",
    "sg:postcode":"E3B 5Y4",
    "sg:province":"NB",
    "wof:name":"Jubilee Super Buffet",
    "wof:placetype":"venue"
},
  "geometry": {"coordinates":[-66.6779708862,45.9462203979],"type":"Point"}
}