{
  "type": "Feature",
  "properties": {
    "iso:country":"CA",
    "sg:address":"64 Rue DE LA Fonderie",
    "sg:city":"Cap-DE-LA-Madeleine",
    "sg:classifiers":[
        {
            "category":"Wholesale",
            "subcategory":"Groceries",
            "type":"Manufacturing & Wholesale Goods"
        }
    ],
    "sg:phone":"+1 819 374 0564",
    "sg:postcode":"G8T 2E9",
    "sg:province":"QC",
    "sg:tags":[
        "frozen",
        "dessert",
        "beverage",
        "ice",
        "cream"
    ],
    "wof:name":"Slush Puppie Trois-Rivieres",
    "wof:placetype":"venue"
},
  "geometry": {"coordinates":[-72.5426330566,46.3764305115],"type":"Point"}
}