{
  "type": "Feature",
  "properties": {
    "addr:full":"Laurel Morin-Heights QC J0R 1H0",
    "addr:postcode":"j0r 1h0",
    "addr:street":"Laurel",
    "iso:country":"CA",
    "sg:address":"Laurel",
    "sg:city":"Morin-Heights",
    "sg:classifiers":[
        {
            "category":"Government",
            "subcategory":"Office",
            "type":"Public Place"
        }
    ],
    "sg:phone":"+1 450 226 2416",
    "sg:postcode":"J0R 1H0",
    "sg:province":"QC",
    "sg:tags":[
        "village"
    ],
    "wof:name":"Wentworth Nord Secretariat",
    "wof:placetype":"venue"
},
  "geometry": {"coordinates":[-74.23455,45.905979],"type":"Point"}
}