{
  "type": "Feature",
  "properties": {
    "addr:full":"1947 Sheppard Ave W North York ON M3L 1Y8",
    "addr:housenumber":"1947",
    "addr:postcode":"m3l 1y8",
    "addr:street":"Sheppard Ave W",
    "iso:country":"CA",
    "sg:address":"1947 Sheppard Ave W",
    "sg:city":"North York",
    "sg:classifiers":[
        {
            "category":"Restaurant",
            "type":"Food & Drink"
        }
    ],
    "sg:phone":"+1 416 746 9496",
    "sg:postcode":"M3L 1Y8",
    "sg:province":"ON",
    "sg:tags":[
        "shop",
        "coffee"
    ],
    "wof:name":"Cafe Mondeale & Bar",
    "wof:placetype":"venue"
},
  "geometry": {"coordinates":[-79.51222199999999,43.739384],"type":"Point"}
}