{
  "type": "Feature",
  "properties": {
    "addr:full":"9256 Commercial St New Minas NS B4N 4A9",
    "addr:housenumber":"9256",
    "addr:postcode":"b4n 4a9",
    "addr:street":"Commercial St",
    "iso:country":"CA",
    "sg:address":"9256 Commercial St",
    "sg:city":"New Minas",
    "sg:classifiers":[
        {
            "category":"Banks & Credit Unions",
            "subcategory":"Bank",
            "type":"Services"
        }
    ],
    "sg:phone":"+1 902 681 8333",
    "sg:postcode":"B4N 4A9",
    "sg:province":"NS",
    "wof:name":"Royal Bank Financial Group",
    "wof:placetype":"venue"
},
  "geometry": {"coordinates":[-64.443077,45.068253],"type":"Point"}
}