{
  "type": "Feature",
  "properties": {
    "addr:full":"Toronto ON M4M 3H7",
    "addr:postcode":"m4m 3h7",
    "iso:country":"CA",
    "sg:city":"Toronto",
    "sg:classifiers":[
        {
            "category":"Autos & Motor Vehicles",
            "subcategory":"Boat Sales",
            "type":"Retail Goods"
        }
    ],
    "sg:phone":"+1 416 465 1668",
    "sg:postcode":"M4M 3H7",
    "sg:province":"ON",
    "sg:tags":[
        "equipment",
        "marine",
        "dealer",
        "supply"
    ],
    "wof:name":"Eastern Marine Systems",
    "wof:placetype":"venue"
},
  "geometry": {"coordinates":[-79.3260803223,43.6560249329],"type":"Point"}
}