{
  "type": "Feature",
  "properties": {
    "iso:country":"CA",
    "sg:address":"362 Dundas St",
    "sg:city":"Woodstock",
    "sg:classifiers":[
        {
            "category":"Personal",
            "subcategory":"Beauty Salon",
            "type":"Services"
        }
    ],
    "sg:phone":"+1 519 537 3691",
    "sg:postcode":"N4S 1B7",
    "sg:province":"ON",
    "wof:name":"Lucky's Hair Stylists",
    "wof:placetype":"venue"
},
  "geometry": {"coordinates":[-80.761528,43.12928],"type":"Point"}
}