{
  "type": "Feature",
  "properties": {
    "addr:full":"46 Empey St Brantford ON N3S 7R2",
    "addr:housenumber":"46",
    "addr:postcode":"n3s 7r2",
    "addr:street":"Empey St",
    "iso:country":"CA",
    "sg:address":"46 Empey St",
    "sg:city":"Brantford",
    "sg:classifiers":[
        {
            "category":"Building & Trades",
            "subcategory":"Construction",
            "type":"Services"
        }
    ],
    "sg:phone":"+1 519 756 7540",
    "sg:postcode":"N3S 7R2",
    "sg:province":"ON",
    "sg:tags":[
        "excavating",
        "contractor"
    ],
    "wof:name":"Haggerty Brothers Constr Inc",
    "wof:placetype":"venue"
},
  "geometry": {"coordinates":[-80.221558,43.1553],"type":"Point"}
}