{
  "type": "Feature",
  "properties": {
    "addr:full":"14 Victoria St W Amherst NS B4H 1B8",
    "addr:housenumber":"14",
    "addr:postcode":"b4h 1b8",
    "addr:street":"Victoria St W",
    "iso:country":"CA",
    "sg:address":"14 Victoria St W",
    "sg:city":"Amherst",
    "sg:classifiers":[
        {
            "category":"Health Services",
            "subcategory":"Nursing And Care Facility",
            "type":"Services"
        }
    ],
    "sg:phone":"+1 902 667 9464",
    "sg:postcode":"B4H 1B8",
    "sg:province":"NS",
    "sg:tags":[
        "home",
        "convalescent",
        "rest"
    ],
    "wof:name":"Victoria Manor",
    "wof:placetype":"venue"
},
  "geometry": {"coordinates":[-64.214798,45.830082],"type":"Point"}
}