{
  "type": "Feature",
  "properties": {
    "addr:full":"2000 8 Ave Canmore AB T1W 1Y2",
    "addr:housenumber":"2000",
    "addr:postcode":"t1w 1y2",
    "addr:street":"8 Ave",
    "iso:country":"CA",
    "sg:address":"2000 8 Ave",
    "sg:city":"Canmore",
    "sg:classifiers":[
        {
            "category":"Sports & Exercise",
            "subcategory":"Golf",
            "type":"Entertainment"
        }
    ],
    "sg:phone":"+1 403 678 4785",
    "sg:postcode":"T1W 1Y2",
    "sg:province":"AB",
    "sg:tags":[
        "course"
    ],
    "wof:name":"Canmore Golf & Curling Club",
    "wof:placetype":"venue"
},
  "geometry": {"coordinates":[-115.364349,51.10125],"type":"Point"}
}