{
  "type": "Feature",
  "properties": {
    "iso:country":"CA",
    "sg:address":"168 Av Broadway",
    "sg:city":"Montreal-Est",
    "sg:classifiers":[
        {
            "category":"Autos & Motor Vehicles",
            "subcategory":"Automobile Sales",
            "type":"Retail Goods"
        }
    ],
    "sg:phone":"+1 514 645 7042",
    "sg:postcode":"H1B 5A3",
    "sg:province":"QC",
    "sg:tags":[
        "car",
        "dealer"
    ],
    "wof:name":"Location Marc Beaudry Inc",
    "wof:placetype":"venue"
},
  "geometry": {"coordinates":[-73.5046539307,45.6315078735],"type":"Point"}
}