{
  "type": "Feature",
  "properties": {
    "addr:full":"1611 Mountdale Ave Thunder Bay ON P7E 3A7",
    "addr:housenumber":"1611",
    "addr:postcode":"p7e 3a7",
    "addr:street":"Mountdale Ave",
    "iso:country":"CA",
    "sg:address":"1611 Mountdale Ave",
    "sg:city":"Thunder Bay",
    "sg:classifiers":[
        {
            "category":"Organizations",
            "subcategory":"Religious Organization",
            "type":"Services"
        }
    ],
    "sg:phone":"+1 807 577 7651",
    "sg:postcode":"P7E 3A7",
    "sg:province":"ON",
    "sg:tags":[
        "church"
    ],
    "wof:name":"Ascension Catholic Church",
    "wof:placetype":"venue"
},
  "geometry": {"coordinates":[-89.295097,48.363682],"type":"Point"}
}