{
  "type": "Feature",
  "properties": {
    "addr:full":"Mississauga ON L4W 4Y4",
    "addr:postcode":"l4w 4y4",
    "iso:country":"CA",
    "sg:city":"Mississauga",
    "sg:classifiers":[
        {
            "category":"Organizations",
            "subcategory":"Professional Association",
            "type":"Services"
        }
    ],
    "sg:phone":"+1 905 602 4700",
    "sg:postcode":"L4W 4Y4",
    "sg:province":"ON",
    "wof:name":"Heating Refrigerating Inst",
    "wof:placetype":"venue"
},
  "geometry": {"coordinates":[-79.599197,43.656467],"type":"Point"}
}