{
  "type": "Feature",
  "properties": {
    "addr:full":"9457 Rue Saint-Vincent Mirabel QC J7N 2V6",
    "addr:housenumber":"9457",
    "addr:postcode":"j7n 2v6",
    "addr:street":"Rue Saint-Vincent",
    "iso:country":"CA",
    "sg:address":"9457 Rue Saint-Vincent",
    "sg:city":"Mirabel",
    "sg:classifiers":[
        {
            "category":"Wholesale",
            "subcategory":"Metals & Minerals",
            "type":"Manufacturing & Wholesale Goods"
        }
    ],
    "sg:phone":"+1 450 258 3984",
    "sg:postcode":"J7N 2V6",
    "sg:province":"QC",
    "sg:tags":[
        "pipe"
    ],
    "wof:name":"Tuyaux Andre Jette",
    "wof:placetype":"venue"
},
  "geometry": {"coordinates":[-74.0991516113,45.6413574219],"type":"Point"}
}