{
  "type": "Feature",
  "properties": {
    "addr:full":"PO Box 274 St Pierre Jolys MB R0A 1V0",
    "addr:housenumber":"po",
    "addr:postcode":"r0a 1v0",
    "addr:street":"Box 274 St Pierre Jolys",
    "iso:country":"CA",
    "sg:address":"PO Box 274",
    "sg:city":"St Pierre Jolys",
    "sg:classifiers":[
        {
            "category":"Building & Trades",
            "subcategory":"Landscaping Services",
            "type":"Services"
        }
    ],
    "sg:phone":"+1 204 433 3309",
    "sg:postcode":"R0A 1V0",
    "sg:province":"MB",
    "sg:tags":[
        "landscape",
        "contractor"
    ],
    "wof:name":"N Tessier Landscaping Ltd",
    "wof:placetype":"venue"
},
  "geometry": {"coordinates":[-96.985123,49.440708],"type":"Point"}
}