{
  "type": "Feature",
  "properties": {
    "addr:full":"Virden MB R0M 2C0",
    "addr:postcode":"r0m 2c0",
    "iso:country":"CA",
    "sg:city":"Virden",
    "sg:classifiers":[
        {
            "category":"Building & Trades",
            "subcategory":"Electrical",
            "type":"Services"
        }
    ],
    "sg:phone":"+1 204 748 1753",
    "sg:postcode":"R0M 2C0",
    "sg:province":"MB",
    "sg:tags":[
        "electric",
        "contractor"
    ],
    "wof:name":"D B Higginbotham Electric Ltd",
    "wof:placetype":"venue"
},
  "geometry": {"coordinates":[-100.919715881,49.8560256958],"type":"Point"}
}