{
  "type": "Feature",
  "properties": {
    "iso:country":"CA",
    "sg:address":"167 Simcoe St N",
    "sg:city":"Oshawa",
    "sg:classifiers":[
        {
            "category":"Professional",
            "subcategory":"Lawyer & Legal Services",
            "type":"Services"
        }
    ],
    "sg:phone":"+1 905 721 1277",
    "sg:postcode":"L1G 4S8",
    "sg:province":"ON",
    "sg:tags":[
        "attorney"
    ],
    "wof:name":"England, Diane M",
    "wof:placetype":"venue"
},
  "geometry": {"coordinates":[-78.8654251099,43.9020423889],"type":"Point"}
}