{
  "type": "Feature",
  "properties": {
    "addr:full":"Dunnville ON N1A 2Z2",
    "addr:postcode":"n1a 2z2",
    "iso:country":"CA",
    "sg:city":"Dunnville",
    "sg:classifiers":[
        {
            "category":"Retail",
            "subcategory":"Auto Repair",
            "type":"Services"
        }
    ],
    "sg:phone":"+1 905 774 6238",
    "sg:postcode":"N1A 2Z2",
    "sg:province":"ON",
    "sg:tags":[
        "wrecker"
    ],
    "wof:name":"Allen's Towing & Recovery",
    "wof:placetype":"venue"
},
  "geometry": {"coordinates":[-79.594658,42.904133],"type":"Point"}
}