{
  "type": "Feature",
  "properties": {
    "addr:full":"1537 Kelly Lake Rd Sudbury ON P3E 4L8",
    "addr:housenumber":"1537",
    "addr:postcode":"p3e 4l8",
    "addr:street":"Kelly Lake Rd",
    "iso:country":"CA",
    "sg:address":"1537 Kelly Lake Rd",
    "sg:city":"Sudbury",
    "sg:classifiers":[
        {
            "category":"Wholesale",
            "subcategory":"Groceries",
            "type":"Manufacturing & Wholesale Goods"
        }
    ],
    "sg:phone":"+1 705 523 2324",
    "sg:postcode":"P3E 4L8",
    "sg:province":"ON",
    "sg:tags":[
        "grocer"
    ],
    "wof:name":"Humpty Dumpty Snack Foods Inc",
    "wof:placetype":"venue"
},
  "geometry": {"coordinates":[-81.02824401860001,46.4620513916],"type":"Point"}
}