{
  "type": "Feature",
  "properties": {
    "addr:full":"467 Parliament St Toronto ON M5A 3A3",
    "addr:housenumber":"467",
    "addr:postcode":"m5a 3a3",
    "addr:street":"Parliament St",
    "iso:country":"CA",
    "sg:address":"467 Parliament St",
    "sg:city":"Toronto",
    "sg:classifiers":[
        {
            "category":"Shopping",
            "subcategory":"Pharmacy",
            "type":"Retail Goods"
        }
    ],
    "sg:phone":"+1 416 925 4121",
    "sg:postcode":"M5A 3A3",
    "sg:province":"ON",
    "wof:name":"Shoppers Drug Mart",
    "wof:placetype":"venue"
},
  "geometry": {"coordinates":[-79.367577,43.663784],"type":"Point"}
}