{
  "type": "Feature",
  "properties": {
    "addr:full":"315 Algonquin Ave North Bay ON P1B 4W1",
    "addr:housenumber":"315",
    "addr:postcode":"p1b 4w1",
    "addr:street":"Algonquin Ave",
    "iso:country":"CA",
    "sg:address":"315 Algonquin Ave",
    "sg:city":"North Bay",
    "sg:classifiers":[
        {
            "category":"Retail",
            "subcategory":"Repair Shop",
            "type":"Services"
        }
    ],
    "sg:phone":"+1 705 472 2080",
    "sg:postcode":"P1B 4W1",
    "sg:province":"ON",
    "sg:tags":[
        "lock",
        "locksmith"
    ],
    "wof:name":"Jim's Locksmithing & Shrpng",
    "wof:placetype":"venue"
},
  "geometry": {"coordinates":[-79.4662246704,46.3139343262],"type":"Point"}
}