{
  "type": "Feature",
  "properties": {
    "addr:full":"303 Bosworth St Wynyard SK S0A 4T0",
    "addr:housenumber":"303",
    "addr:postcode":"s0a 4t0",
    "addr:street":"Bosworth St",
    "iso:country":"CA",
    "sg:address":"303 Bosworth St",
    "sg:city":"Wynyard",
    "sg:classifiers":[
        {
            "category":"Shopping",
            "subcategory":"Gifts & Souvenirs",
            "type":"Retail Goods"
        }
    ],
    "sg:phone":"+1 306 554 2422",
    "sg:postcode":"S0A 4T0",
    "sg:province":"SK",
    "sg:tags":[
        "shop"
    ],
    "wof:name":"Jenn's Perfect Presents",
    "wof:placetype":"venue"
},
  "geometry": {"coordinates":[-104.18596649200001,51.7689781189],"type":"Point"}
}