{
  "type": "Feature",
  "properties": {
    "addr:full":"Rouyn-Noranda QC J9X 1P8",
    "addr:postcode":"j9x 1p8",
    "iso:country":"CA",
    "sg:city":"Rouyn-Noranda",
    "sg:classifiers":[
        {
            "category":"Utilities",
            "subcategory":"Fuel Oil & Lpg",
            "type":"Services"
        }
    ],
    "sg:phone":"+1 819 797 4222",
    "sg:postcode":"J9X 1P8",
    "sg:province":"QC",
    "wof:name":"Esso Confort Au Foyer",
    "wof:placetype":"venue"
},
  "geometry": {"coordinates":[-79.020866394,48.2495918274],"type":"Point"}
}