{
  "type": "Feature",
  "properties": {
    "addr:full":"182 Water St St Andrews NB E5B 1B2",
    "addr:housenumber":"182",
    "addr:postcode":"nb e5b 1b2",
    "addr:street":"Water St",
    "iso:country":"CA",
    "sg:address":"182 Water St",
    "sg:city":"St Andrews",
    "sg:classifiers":[
        {
            "category":"Restaurant",
            "type":"Food & Drink"
        }
    ],
    "sg:phone":"+1 506 529 6249",
    "sg:postcode":"E5B 1B2",
    "sg:province":"NB",
    "sg:tags":[
        "baker"
    ],
    "wof:name":"Sweet Harvest Market",
    "wof:placetype":"venue"
},
  "geometry": {"coordinates":[-67.053391,45.074085],"type":"Point"}
}