{
  "type": "Feature",
  "properties": {
    "addr:full":"373 Vantage Dr Orleans ON K4A 3W2",
    "addr:housenumber":"373",
    "addr:postcode":"k4a 3w2",
    "addr:street":"Vantage Dr",
    "iso:country":"CA",
    "sg:address":"373 Vantage Dr",
    "sg:city":"Orleans",
    "sg:classifiers":[
        {
            "category":"Shopping",
            "subcategory":"Pharmacy",
            "type":"Retail Goods"
        }
    ],
    "sg:phone":"+1 613 841 3470",
    "sg:postcode":"K4A 3W2",
    "sg:province":"ON",
    "wof:name":"Vantage Medical Pharmacy",
    "wof:placetype":"venue"
},
  "geometry": {"coordinates":[-75.4905700684,45.4588165283],"type":"Point"}
}