{
  "type": "Feature",
  "properties": {
    "addr:full":"1401 4th Ave W Prince Albert SK S6V 5H1",
    "addr:housenumber":"1401",
    "addr:postcode":"s6v 5h1",
    "addr:street":"4Th Ave W",
    "iso:country":"CA",
    "sg:address":"1401 4th Ave W",
    "sg:city":"Prince Albert",
    "sg:classifiers":[
        {
            "category":"Organizations",
            "subcategory":"Religious Organization",
            "type":"Services"
        }
    ],
    "sg:phone":"+1 306 763 2319",
    "sg:postcode":"S6V 5H1",
    "sg:province":"SK",
    "sg:tags":[
        "church"
    ],
    "wof:name":"Sacred Heart Cathedral",
    "wof:placetype":"venue"
},
  "geometry": {"coordinates":[-105.76525116000001,53.2008552551],"type":"Point"}
}