{
  "type": "Feature",
  "properties": {
    "addr:full":"Campbellford ON K0L 1L0",
    "addr:postcode":"k0l 1l0",
    "iso:country":"CA",
    "sg:city":"Campbellford",
    "sg:classifiers":[
        {
            "category":"Restaurant",
            "type":"Food & Drink"
        }
    ],
    "sg:phone":"+1 705 653 2908",
    "sg:postcode":"K0L 1L0",
    "sg:province":"ON",
    "wof:name":"Chubby's Restaurant",
    "wof:placetype":"venue"
},
  "geometry": {"coordinates":[-77.797492981,44.309211731],"type":"Point"}
}