{
  "type": "Feature",
  "properties": {
    "addr:full":"316 Welland Rd Fenwick ON L0S 1C0",
    "addr:housenumber":"316",
    "addr:postcode":"l0s 1c0",
    "addr:street":"Welland Rd",
    "iso:country":"CA",
    "sg:address":"316 Welland Rd",
    "sg:city":"Fenwick",
    "sg:classifiers":[
        {
            "category":"Building & Trades",
            "subcategory":"Construction",
            "type":"Services"
        }
    ],
    "sg:phone":"+1 905 892 3757",
    "sg:postcode":"L0S 1C0",
    "sg:province":"ON",
    "sg:tags":[
        "siding",
        "contractor"
    ],
    "wof:name":"William L Hall Installations",
    "wof:placetype":"venue"
},
  "geometry": {"coordinates":[-79.340729,43.02459],"type":"Point"}
}