{
  "type": "Feature",
  "properties": {
    "addr:full":"169 Rue Saint-Jacques O Princeville QC G6L 4Y2",
    "addr:housenumber":"169",
    "addr:postcode":"g6l 4y2",
    "addr:street":"Rue Saint-Jacques O",
    "iso:country":"CA",
    "sg:address":"169 Rue Saint-Jacques O",
    "sg:city":"Princeville",
    "sg:classifiers":[
        {
            "category":"Organizations",
            "subcategory":"Non-profit Organization",
            "type":"Services"
        }
    ],
    "sg:phone":"+1 819 364 3409",
    "sg:postcode":"G6L 4Y2",
    "sg:province":"QC",
    "sg:tags":[
        "charitable",
        "institution",
        "business"
    ],
    "wof:name":"Orasse",
    "wof:placetype":"venue"
},
  "geometry": {"coordinates":[-71.87333700000001,46.174068],"type":"Point"}
}