{
  "type": "Feature",
  "properties": {
    "addr:full":"461 Lake Edwards Rd Lake Edward NB E7G 1Z6",
    "addr:housenumber":"461",
    "addr:postcode":"e7g 1z6",
    "addr:street":"Lake Edwards Rd",
    "iso:country":"CA",
    "sg:address":"461 Lake Edwards Rd",
    "sg:city":"Lake Edward",
    "sg:classifiers":[
        {
            "category":"Building & Trades",
            "subcategory":"Construction",
            "type":"Services"
        }
    ],
    "sg:phone":"+1 506 553 1083",
    "sg:postcode":"E7G 1Z6",
    "sg:province":"NB",
    "sg:tags":[
        "general",
        "contractor"
    ],
    "wof:name":"D B Construction Ltd",
    "wof:placetype":"venue"
},
  "geometry": {"coordinates":[-67.64943695069999,46.9052124023],"type":"Point"}
}