{
  "type": "Feature",
  "properties": {
    "iso:country":"CA",
    "sg:address":"8360 Kennedy Rd # 62",
    "sg:city":"Markham",
    "sg:classifiers":[
        {
            "category":"Restaurant",
            "type":"Food & Drink"
        }
    ],
    "sg:phone":"+1 905 479 8388",
    "sg:postcode":"L3R 9W4",
    "sg:province":"ON",
    "wof:name":"Sunlight Snack & Juice",
    "wof:placetype":"venue"
},
  "geometry": {"coordinates":[-79.30287199999999,43.859375],"type":"Point"}
}