{
  "type": "Feature",
  "properties": {
    "addr:full":"320 Dalton Ave Miramichi NB E1V 3N9",
    "addr:housenumber":"320",
    "addr:postcode":"e1v 3n9",
    "addr:street":"Dalton Ave",
    "iso:country":"CA",
    "sg:address":"320 Dalton Ave",
    "sg:city":"Miramichi",
    "sg:classifiers":[
        {
            "category":"Wholesale",
            "subcategory":"Auto Parts",
            "type":"Manufacturing & Wholesale Goods"
        }
    ],
    "sg:phone":"+1 506 622 6200",
    "sg:postcode":"E1V 3N9",
    "sg:province":"NB",
    "sg:tags":[
        "equipment",
        "truck"
    ],
    "wof:name":"Parts For Trucks Inc",
    "wof:placetype":"venue"
},
  "geometry": {"coordinates":[-65.5824584961,46.9955024719],"type":"Point"}
}