{
  "type": "Feature",
  "properties": {
    "addr:full":"101 Hwy 6 N Watson SK S0K 4V0",
    "addr:housenumber":"101",
    "addr:postcode":"s0k 4v0",
    "addr:street":"Hwy 6 N",
    "iso:country":"CA",
    "sg:address":"101 Hwy 6 N",
    "sg:city":"Watson",
    "sg:classifiers":[
        {
            "category":"Autos & Motor Vehicles",
            "subcategory":"Auto Supplies",
            "type":"Retail Goods"
        }
    ],
    "sg:phone":"+1 306 287 3445",
    "sg:postcode":"S0K 4V0",
    "sg:province":"SK",
    "sg:tags":[
        "automobile",
        "parts"
    ],
    "wof:name":"Uap Napa Auto Parts",
    "wof:placetype":"venue"
},
  "geometry": {"coordinates":[-104.530182,52.126774],"type":"Point"}
}