{
  "type": "Feature",
  "properties": {
    "addr:full":"221 4th St Estevan SK S4A 0T5",
    "addr:housenumber":"221",
    "addr:postcode":"s4a 0t5",
    "addr:street":"4Th St",
    "iso:country":"CA",
    "sg:address":"221 4th St",
    "sg:city":"Estevan",
    "sg:classifiers":[
        {
            "category":"Autos & Motor Vehicles",
            "subcategory":"Motorcycle Sales",
            "type":"Retail Goods"
        }
    ],
    "sg:phone":"+1 306 634 0030",
    "sg:postcode":"S4A 0T5",
    "sg:province":"SK",
    "sg:tags":[
        "recreational"
    ],
    "wof:name":"Frosty's Motorcycles Parts",
    "wof:placetype":"venue"
},
  "geometry": {"coordinates":[-102.97534942599999,49.1331939697],"type":"Point"}
}