{
  "type": "Feature",
  "properties": {
    "addr:full":"105 Main St Unionville ON L3R 2G1",
    "addr:housenumber":"105",
    "addr:postcode":"l3r 2g1",
    "addr:street":"Main St",
    "iso:country":"CA",
    "sg:address":"105 Main St",
    "sg:city":"Unionville",
    "sg:classifiers":[
        {
            "category":"Social Services",
            "subcategory":"Child Care",
            "type":"Services"
        }
    ],
    "sg:phone":"+1 905 479 4274",
    "sg:postcode":"L3R 2G1",
    "sg:province":"ON",
    "wof:name":"Wee Watch",
    "wof:placetype":"venue"
},
  "geometry": {"coordinates":[-79.3095626831,43.8619155884],"type":"Point"}
}