{
  "type": "Feature",
  "properties": {
    "iso:country":"CA",
    "sg:address":"27 Main St W",
    "sg:city":"Grimsby",
    "sg:classifiers":[
        {
            "category":"Banks & Credit Unions",
            "subcategory":"Bank",
            "type":"Services"
        }
    ],
    "sg:phone":"+1 905 945 2239",
    "sg:postcode":"L3M 1R3",
    "sg:province":"ON",
    "wof:name":"Cibc",
    "wof:placetype":"venue"
},
  "geometry": {"coordinates":[-79.56172943120001,43.1935119629],"type":"Point"}
}