{
  "type": "Feature",
  "properties": {
    "iso:country":"CA",
    "sg:address":"1652 Rue Jarry E",
    "sg:city":"Montreal",
    "sg:classifiers":[
        {
            "category":"Retail",
            "subcategory":"Laundry & Dry Cleaning",
            "type":"Services"
        }
    ],
    "sg:phone":"+1 514 728 6775",
    "sg:postcode":"H2E 1B3",
    "sg:province":"QC",
    "sg:tags":[
        "cleaners"
    ],
    "wof:name":"Nettoyeur Bonjour",
    "wof:placetype":"venue"
},
  "geometry": {"coordinates":[-73.619438,45.552696],"type":"Point"}
}