{
  "type": "Feature",
  "properties": {
    "addr:full":"176 Bullock Dr #1 Markham ON L3P 7N1",
    "addr:housenumber":"176",
    "addr:postcode":"l3p 7n1",
    "addr:street":"Bullock Dr # 1",
    "iso:country":"CA",
    "sg:address":"176 Bullock Dr #1",
    "sg:city":"Markham",
    "sg:classifiers":[
        {
            "category":"Real Estate",
            "subcategory":"Real Estate Agent",
            "type":"Services"
        }
    ],
    "sg:phone":"+1 416 291 1558",
    "sg:postcode":"L3P 7N1",
    "sg:province":"ON",
    "wof:name":"Realty Shoppe Ltd",
    "wof:placetype":"venue"
},
  "geometry": {"coordinates":[-79.279015,43.874954],"type":"Point"}
}