{
  "type": "Feature",
  "properties": {
    "addr:full":"277 Lakeshore Rd E Oakville ON L6J 6J3",
    "addr:housenumber":"277",
    "addr:postcode":"l6j 6j3",
    "addr:street":"Lakeshore Rd E",
    "iso:country":"CA",
    "sg:address":"277 Lakeshore Rd E",
    "sg:city":"Oakville",
    "sg:classifiers":[
        {
            "category":"Parking",
            "type":"Transportation"
        }
    ],
    "sg:phone":"+1 905 842 4047",
    "sg:postcode":"L6J 6J3",
    "sg:province":"ON",
    "sg:tags":[
        "garage"
    ],
    "wof:name":"Imperial Parking",
    "wof:placetype":"venue"
},
  "geometry": {"coordinates":[-79.66677900000001,43.447311],"type":"Point"}
}