{
  "type": "Feature",
  "properties": {
    "iso:country":"CA",
    "sg:address":"346 Main St E",
    "sg:city":"Hawkesbury",
    "sg:classifiers":[
        {
            "category":"Restaurant",
            "type":"Food & Drink"
        }
    ],
    "sg:phone":"+1 613 632 7012",
    "sg:postcode":"K6A 1A5",
    "sg:province":"ON",
    "wof:name":"Dong Kong Cafe",
    "wof:placetype":"venue"
},
  "geometry": {"coordinates":[-74.60627746580001,45.6101493835],"type":"Point"}
}