{
  "type": "Feature",
  "properties": {
    "addr:full":"834 Boul Saint-Joseph E Montreal QC H2J 1K4",
    "addr:housenumber":"834",
    "addr:postcode":"h2j 1k4",
    "addr:street":"Boul Saint-Joseph E",
    "iso:country":"CA",
    "sg:address":"834 Boul Saint-Joseph E",
    "sg:city":"Montreal",
    "sg:classifiers":[
        {
            "category":"Health Services",
            "subcategory":"Doctor",
            "type":"Services"
        }
    ],
    "sg:phone":"+1 514 524 9772",
    "sg:postcode":"H2J 1K4",
    "sg:province":"QC",
    "sg:tags":[
        "physician",
        "surgeon"
    ],
    "wof:name":"Lefebvre, Andre MD",
    "wof:placetype":"venue"
},
  "geometry": {"coordinates":[-73.58568572999999,45.5283279419],"type":"Point"}
}