{
  "type": "Feature",
  "properties": {
    "addr:full":"3131 Boul Rosemont Montreal QC H1Y 1M4",
    "addr:housenumber":"3131",
    "addr:postcode":"h1y 1m4",
    "addr:street":"Boul Rosemont",
    "iso:country":"CA",
    "sg:address":"3131 Boul Rosemont",
    "sg:city":"Montreal",
    "sg:classifiers":[
        {
            "category":"Education",
            "subcategory":"Library",
            "type":"Public Place"
        }
    ],
    "sg:phone":"+1 514 872 4701",
    "sg:postcode":"H1Y 1M4",
    "sg:province":"QC",
    "wof:name":"Montreal Bibliotheque",
    "wof:placetype":"venue"
},
  "geometry": {"coordinates":[-73.581779,45.55188],"type":"Point"}
}