{
  "type": "Feature",
  "properties": {
    "addr:full":"468 Boul Saint-Joseph E Montreal QC H2J 1J7",
    "addr:housenumber":"468",
    "addr:postcode":"h2j 1j7",
    "addr:street":"Boul Saint-Joseph E",
    "iso:country":"CA",
    "sg:address":"468 Boul Saint-Joseph E",
    "sg:city":"Montreal",
    "sg:classifiers":[
        {
            "category":"Health Services",
            "subcategory":"Doctor",
            "type":"Services"
        }
    ],
    "sg:phone":"+1 514 849 3511",
    "sg:postcode":"H2J 1J7",
    "sg:province":"QC",
    "sg:tags":[
        "dentist"
    ],
    "wof:name":"Gagnon, Pierre DDS",
    "wof:placetype":"venue"
},
  "geometry": {"coordinates":[-73.5869216919,45.5269622803],"type":"Point"}
}