{
  "type": "Feature",
  "properties": {
    "addr:full":"RR 3 Ingleside ON K0C 1M0",
    "addr:postcode":"k0c 1m0",
    "addr:street":"Rr 3",
    "iso:country":"CA",
    "sg:address":"RR 3",
    "sg:city":"Ingleside",
    "sg:classifiers":[
        {
            "category":"Building & Trades",
            "subcategory":"Construction",
            "type":"Services"
        }
    ],
    "sg:phone":"+1 613 534 2989",
    "sg:postcode":"K0C 1M0",
    "sg:province":"ON",
    "sg:tags":[
        "maker",
        "cabinet"
    ],
    "wof:name":"David Fougere Cabinet Maker",
    "wof:placetype":"venue"
},
  "geometry": {"coordinates":[-74.9868545532,44.9957885742],"type":"Point"}
}