{
  "type": "Feature",
  "properties": {
    "addr:full":"220 Ch Du Mont-Trinite Saint-Michel-Des-Saints QC J0K 3B0",
    "addr:housenumber":"220",
    "addr:postcode":"j0k 3b0",
    "addr:street":"Ch Du Mont-Trinite",
    "iso:country":"CA",
    "sg:address":"220 Ch Du Mont-Trinite",
    "sg:city":"Saint-Michel-Des-Saints",
    "sg:classifiers":[
        {
            "category":"Sports & Exercise",
            "subcategory":"Golf",
            "type":"Entertainment"
        }
    ],
    "sg:phone":"+1 450 833 5050",
    "sg:postcode":"J0K 3B0",
    "sg:province":"QC",
    "sg:tags":[
        "course"
    ],
    "wof:name":"Club DE Golf St-Michel-Saints",
    "wof:placetype":"venue"
},
  "geometry": {"coordinates":[-73.90385437010001,46.6756782532],"type":"Point"}
}