{
  "type": "Feature",
  "properties": {
    "addr:full":"7160 Pacific Cir Mississauga ON L5T 2A6",
    "addr:housenumber":"7160",
    "addr:postcode":"l5t 2a6",
    "addr:street":"Pacific Cir",
    "iso:country":"CA",
    "sg:address":"7160 Pacific Cir",
    "sg:city":"Mississauga",
    "sg:classifiers":[
        {
            "category":"Wholesale",
            "subcategory":"Non-durable Goods",
            "type":"Manufacturing & Wholesale Goods"
        }
    ],
    "sg:phone":"+1 905 564 3219",
    "sg:postcode":"L5T 2A6",
    "sg:province":"ON",
    "sg:tags":[
        "building",
        "plaster",
        "material"
    ],
    "wof:name":"Webster & Sons",
    "wof:placetype":"venue"
},
  "geometry": {"coordinates":[-79.6825866699,43.6590957642],"type":"Point"}
}