{
  "type": "Feature",
  "properties": {
    "addr:full":"95 King St E Bowmanville ON L1C 1N4",
    "addr:housenumber":"95",
    "addr:postcode":"l1c 1n4",
    "addr:street":"King St",
    "iso:country":"CA",
    "sg:address":"95 King St E",
    "sg:city":"Bowmanville",
    "sg:classifiers":[
        {
            "category":"Home & Garden",
            "subcategory":"Building Materials",
            "type":"Retail Goods"
        }
    ],
    "sg:phone":"+1 905 623 5431",
    "sg:postcode":"L1C 1N4",
    "sg:province":"ON",
    "sg:tags":[
        "paint"
    ],
    "wof:name":"Abernethy's Paint & Wallpaper",
    "wof:placetype":"venue"
},
  "geometry": {"coordinates":[-78.686356,43.911339],"type":"Point"}
}