{
  "type": "Feature",
  "properties": {
    "addr:full":"4995 Hardy Bay Rd Port Hardy BC V0N 2P0",
    "addr:housenumber":"4995",
    "addr:postcode":"v0n 2p0",
    "addr:street":"Hardy Bay Rd",
    "iso:country":"CA",
    "sg:address":"4995 Hardy Bay Rd",
    "sg:city":"Port Hardy",
    "sg:classifiers":[
        {
            "category":"Manufacturing",
            "subcategory":"Signs",
            "type":"Manufacturing & Wholesale Goods"
        }
    ],
    "sg:phone":"+1 250 949 9930",
    "sg:postcode":"V0N 2P0",
    "sg:province":"BC",
    "wof:name":"Somerset Signs",
    "wof:placetype":"venue"
},
  "geometry": {"coordinates":[-127.482811,50.699291],"type":"Point"}
}