{
  "type": "Feature",
  "properties": {
    "iso:country":"CA",
    "sg:city":"Verdun",
    "sg:classifiers":[
        {
            "category":"Banks & Credit Unions",
            "subcategory":"Investment Brokerage",
            "type":"Services"
        }
    ],
    "sg:phone":"+1 514 767 7701",
    "sg:postcode":"H3E 1J4",
    "sg:province":"QC",
    "sg:tags":[
        "consultant",
        "planning",
        "financial"
    ],
    "wof:name":"Consult-Action Progresco Inc",
    "wof:placetype":"venue"
},
  "geometry": {"coordinates":[-73.571762,45.459019],"type":"Point"}
}