{
  "type": "Feature",
  "properties": {
    "iso:country":"CA",
    "sg:address":"509 Dominion Ave",
    "sg:city":"Midland",
    "sg:classifiers":[
        {
            "category":"Shopping",
            "subcategory":"Clothing, Apparel, & Fashions",
            "type":"Retail Goods"
        }
    ],
    "sg:phone":"+1 705 526 4220",
    "sg:postcode":"L4R 1P7",
    "sg:province":"ON",
    "sg:tags":[
        "dressmaker",
        "tailor"
    ],
    "wof:name":"Creative Sewing & Alterations",
    "wof:placetype":"venue"
},
  "geometry": {"coordinates":[-79.8862991333,44.7507133484],"type":"Point"}
}