{
  "type": "Feature",
  "properties": {
    "addr:full":"2235 Sheppard Ave E North York ON M2J 5B5",
    "addr:housenumber":"2235",
    "addr:postcode":"m2j 5b5",
    "addr:street":"Sheppard Ave E",
    "iso:country":"CA",
    "sg:address":"2235 Sheppard Ave E",
    "sg:city":"North York",
    "sg:classifiers":[
        {
            "category":"Parking",
            "type":"Transportation"
        }
    ],
    "sg:phone":"+1 416 492 2142",
    "sg:postcode":"M2J 5B5",
    "sg:province":"ON",
    "sg:tags":[
        "garage"
    ],
    "wof:name":"Impark",
    "wof:placetype":"venue"
},
  "geometry": {"coordinates":[-79.32957500000001,43.774757],"type":"Point"}
}