{
  "type": "Feature",
  "properties": {
    "addr:full":"10737 Yonge St #6 Richmond Hill ON L4C 9M9",
    "addr:housenumber":"10737",
    "addr:postcode":"l4c 9m9",
    "addr:street":"Yonge St # 6",
    "iso:country":"CA",
    "sg:address":"10737 Yonge St #6",
    "sg:city":"Richmond Hill",
    "sg:classifiers":[
        {
            "category":"Shopping",
            "subcategory":"Clothing, Apparel, & Fashions",
            "type":"Retail Goods"
        }
    ],
    "sg:phone":"+1 905 780 6731",
    "sg:postcode":"L4C 9M9",
    "sg:province":"ON",
    "sg:tags":[
        "infant",
        "wear"
    ],
    "wof:name":"Treehouse Kids",
    "wof:placetype":"venue"
},
  "geometry": {"coordinates":[-79.4413909912,43.8897171021],"type":"Point"}
}