{
  "type": "Feature",
  "properties": {
    "addr:full":"1084 Rue DE Fontenay-Le-Comte Cap-Rouge QC G1Y 2Y1",
    "addr:housenumber":"1084",
    "addr:postcode":"g1y 2y1",
    "addr:street":"Rue De Fontenay-Le-Comte",
    "iso:country":"CA",
    "sg:address":"1084 Rue DE Fontenay-Le-Comte",
    "sg:city":"Cap-Rouge",
    "sg:classifiers":[
        {
            "category":"Professional",
            "subcategory":"Advertising",
            "type":"Services"
        }
    ],
    "sg:phone":"+1 418 653 2275",
    "sg:postcode":"G1Y 2Y1",
    "sg:province":"QC",
    "sg:tags":[
        "counselor"
    ],
    "wof:name":"Lefrancois Strategies & Medias",
    "wof:placetype":"venue"
},
  "geometry": {"coordinates":[-71.367493,46.750935],"type":"Point"}
}