{
  "type": "Feature",
  "properties": {
    "iso:country":"CA",
    "sg:address":"16 Dentith Rd",
    "sg:city":"Halifax",
    "sg:classifiers":[
        {
            "category":"Food & Beverages",
            "subcategory":"Liquor & Beverages",
            "type":"Retail Goods"
        }
    ],
    "sg:phone":"+1 902 477 4615",
    "sg:postcode":"B3R 2H9",
    "sg:province":"NS",
    "sg:tags":[
        "store"
    ],
    "wof:name":"Nova Scotia Liquor Store",
    "wof:placetype":"venue"
},
  "geometry": {"coordinates":[-63.6193351746,44.6138000488],"type":"Point"}
}