{
  "type": "Feature",
  "properties": {
    "addr:full":"Iroquois Falls ON P0K 1E0",
    "addr:postcode":"p0k 1e0",
    "iso:country":"CA",
    "sg:city":"Iroquois Falls",
    "sg:classifiers":[
        {
            "category":"Food & Beverages",
            "subcategory":"Bakery",
            "type":"Retail Goods"
        }
    ],
    "sg:phone":"+1 705 232 4366",
    "sg:postcode":"P0K 1E0",
    "sg:province":"ON",
    "sg:tags":[
        "doughnut"
    ],
    "wof:name":"Tim Hortons",
    "wof:placetype":"venue"
},
  "geometry": {"coordinates":[-80.681877,48.763836],"type":"Point"}
}