{
  "type": "Feature",
  "properties": {
    "addr:full":"88 College St Antigonish NS B2G 1X7",
    "addr:housenumber":"88",
    "addr:postcode":"b2g 1x7",
    "addr:street":"College St",
    "iso:country":"CA",
    "sg:address":"88 College St",
    "sg:city":"Antigonish",
    "sg:classifiers":[
        {
            "category":"Manufacturing",
            "subcategory":"Printing",
            "type":"Manufacturing & Wholesale Goods"
        }
    ],
    "sg:phone":"+1 902 863 4370",
    "sg:postcode":"B2G 1X7",
    "sg:province":"NS",
    "sg:tags":[
        "newspaper",
        "printer"
    ],
    "wof:name":"Casket Print & Pub CO Ltd",
    "wof:placetype":"venue"
},
  "geometry": {"coordinates":[-61.991428,45.622982],"type":"Point"}
}