{
  "type": "Feature",
  "properties": {
    "iso:country":"CA",
    "sg:city":"Ile-Aux-Noix",
    "sg:classifiers":[
        {
            "category":"Restaurant",
            "type":"Food & Drink"
        }
    ],
    "sg:phone":"+1 450 291 3821",
    "sg:postcode":"J0J 1G0",
    "sg:province":"QC",
    "wof:name":"Restaurant Le Relais Du Marin",
    "wof:placetype":"venue"
},
  "geometry": {"coordinates":[-73.2805938721,45.1277427673],"type":"Point"}
}