{
  "type": "Feature",
  "properties": {
    "addr:full":"876 Springside Crt Kelowna BC V1W 3L8",
    "addr:housenumber":"876",
    "addr:postcode":"v1w 3l8",
    "addr:street":"Springside Crt",
    "iso:country":"CA",
    "sg:address":"876 Springside Crt",
    "sg:city":"Kelowna",
    "sg:classifiers":[
        {
            "category":"Wholesale",
            "subcategory":"Durable Goods & Equipment",
            "type":"Manufacturing & Wholesale Goods"
        }
    ],
    "sg:phone":"+1 250 861 7778",
    "sg:postcode":"V1W 3L8",
    "sg:province":"BC",
    "sg:tags":[
        "laboratory",
        "instrument",
        "scientific",
        "apparatus",
        "supply"
    ],
    "wof:name":"Anachemia Science",
    "wof:placetype":"venue"
},
  "geometry": {"coordinates":[-119.47958374,49.8513298035],"type":"Point"}
}