{
  "type": "Feature",
  "properties": {
    "addr:full":"Waterloo ON N2V 1Y9",
    "addr:postcode":"n2v 1y9",
    "iso:country":"CA",
    "sg:city":"Waterloo",
    "sg:classifiers":[
        {
            "category":"Building & Trades",
            "subcategory":"Plumbing",
            "type":"Services"
        }
    ],
    "sg:phone":"+1 519 884 0990",
    "sg:postcode":"N2V 1Y9",
    "sg:province":"ON",
    "sg:tags":[
        "contractor"
    ],
    "wof:name":"Kastl & Zuch Plumbing & Htg",
    "wof:placetype":"venue"
},
  "geometry": {"coordinates":[-80.5439453125,43.5073318481],"type":"Point"}
}