{
  "type": "Feature",
  "properties": {
    "iso:country":"CA",
    "sg:address":"106 Wakefield Rd",
    "sg:city":"Milton",
    "sg:classifiers":[
        {
            "category":"Health Services",
            "subcategory":"Optometrist",
            "type":"Services"
        }
    ],
    "sg:phone":"+1 905 878 5882",
    "sg:postcode":"L9T 2L8",
    "sg:province":"ON",
    "wof:name":"Wakefield Professional Ctr",
    "wof:placetype":"venue"
},
  "geometry": {"coordinates":[-79.875,43.5157928467],"type":"Point"}
}