{
  "type": "Feature",
  "properties": {
    "addr:full":"416 King Rd Richmond Hill ON L4E 2X4",
    "addr:housenumber":"416",
    "addr:postcode":"l4e 2x4",
    "addr:street":"King Rd",
    "iso:country":"CA",
    "sg:address":"416 King Rd",
    "sg:city":"Richmond Hill",
    "sg:classifiers":[
        {
            "category":"Building & Trades",
            "subcategory":"Cleaning & Sanitation",
            "type":"Services"
        }
    ],
    "sg:phone":"+1 905 773 5893",
    "sg:postcode":"L4E 2X4",
    "sg:province":"ON",
    "sg:tags":[
        "glass"
    ],
    "wof:name":"Marathon Glass & Mirror Ltd",
    "wof:placetype":"venue"
},
  "geometry": {"coordinates":[-79.47028400000001,43.941448],"type":"Point"}
}