{
  "type": "Feature",
  "properties": {
    "addr:full":"110 Rue Richer Lachine QC H8R 1R2",
    "addr:housenumber":"110",
    "addr:postcode":"h8r 1r2",
    "addr:street":"Rue Richer",
    "iso:country":"CA",
    "sg:address":"110 Rue Richer",
    "sg:city":"Lachine",
    "sg:classifiers":[
        {
            "category":"Manufacturing",
            "subcategory":"Rubber & Plastics",
            "type":"Manufacturing & Wholesale Goods"
        }
    ],
    "sg:phone":"+1 514 369 8980",
    "sg:postcode":"H8R 1R2",
    "sg:province":"QC",
    "sg:tags":[
        "producer"
    ],
    "wof:name":"Plastiques Dura Ltee",
    "wof:placetype":"venue"
},
  "geometry": {"coordinates":[-73.6637802124,45.4498405457],"type":"Point"}
}