{
  "type": "Feature",
  "properties": {
    "addr:full":"171 Main St Dartmouth NS B2X 1S1",
    "addr:housenumber":"171",
    "addr:postcode":"b2x 1s1",
    "addr:street":"Main St",
    "iso:country":"CA",
    "sg:address":"171 Main St",
    "sg:city":"Dartmouth",
    "sg:classifiers":[
        {
            "category":"Personal",
            "subcategory":"Tanning Parlor",
            "type":"Services"
        }
    ],
    "sg:phone":"+1 902 434 9997",
    "sg:postcode":"B2X 1S1",
    "sg:province":"NS",
    "sg:tags":[
        "salon"
    ],
    "wof:name":"Tanning Zone",
    "wof:placetype":"venue"
},
  "geometry": {"coordinates":[-63.520981,44.686321],"type":"Point"}
}