{
  "type": "Feature",
  "properties": {
    "addr:full":"180 Renfrew Dr Markham ON L3R 8B7",
    "addr:housenumber":"180",
    "addr:postcode":"l3r 8b7",
    "addr:street":"Renfrew Dr",
    "iso:country":"CA",
    "sg:address":"180 Renfrew Dr",
    "sg:city":"Markham",
    "sg:classifiers":[
        {
            "category":"Insurance",
            "subcategory":"Insurance Agent",
            "type":"Services"
        }
    ],
    "sg:phone":"+1 905 513 7600",
    "sg:postcode":"L3R 8B7",
    "sg:province":"ON",
    "wof:name":"Rhodes & Williams Ltd",
    "wof:placetype":"venue"
},
  "geometry": {"coordinates":[-79.364616,43.860229],"type":"Point"}
}