{
  "type": "Feature",
  "properties": {
    "iso:country":"CA",
    "sg:address":"102 Centre St N",
    "sg:city":"Oshawa",
    "sg:classifiers":[
        {
            "category":"Shopping",
            "subcategory":"Discount & Variety Stores",
            "type":"Retail Goods"
        }
    ],
    "sg:phone":"+1 905 433 4275",
    "sg:postcode":"L1G 4B8",
    "sg:province":"ON",
    "wof:name":"C W Food Mart",
    "wof:placetype":"venue"
},
  "geometry": {"coordinates":[-78.8672409058,43.8997497559],"type":"Point"}
}