{
  "type": "Feature",
  "properties": {
    "addr:full":"781 20E Av S Saint-Jerome QC J7Z 6Y8",
    "addr:housenumber":"781",
    "addr:postcode":"j7z 6y8",
    "addr:street":"20E Av S Saint-Jerome",
    "iso:country":"CA",
    "sg:address":"781 20E Av S",
    "sg:city":"Saint-Jerome",
    "sg:classifiers":[
        {
            "category":"Personal",
            "subcategory":"Tanning Parlor",
            "type":"Services"
        }
    ],
    "sg:phone":"+1 450 565 1991",
    "sg:postcode":"J7Z 6Y8",
    "sg:province":"QC",
    "sg:tags":[
        "salon"
    ],
    "wof:name":"Passion Soleil",
    "wof:placetype":"venue"
},
  "geometry": {"coordinates":[-74.00351000000001,45.775009],"type":"Point"}
}