{
  "type": "Feature",
  "properties": {
    "addr:full":"1184 Aviator Dr Abbotsford BC V2T 6H5",
    "addr:housenumber":"1184",
    "addr:postcode":"v2t 6h5",
    "addr:street":"Aviator Dr",
    "iso:country":"CA",
    "sg:address":"1184 Aviator Dr",
    "sg:city":"Abbotsford",
    "sg:classifiers":[
        {
            "category":"Education",
            "subcategory":"Special Training",
            "type":"Public Place"
        }
    ],
    "sg:phone":"+1 604 855 1100",
    "sg:postcode":"V2T 6H5",
    "sg:province":"BC",
    "sg:tags":[
        "aircraft",
        "school"
    ],
    "wof:name":"Chinook Helicopters Ltd",
    "wof:placetype":"venue"
},
  "geometry": {"coordinates":[-122.382408,49.022942],"type":"Point"}
}