{
  "type": "Feature",
  "properties": {
    "iso:country":"CA",
    "sg:address":"205 Rang Saint-Joseph E",
    "sg:city":"Armagh",
    "sg:classifiers":[
        {
            "category":"Building & Trades",
            "subcategory":"Construction",
            "type":"Services"
        }
    ],
    "sg:phone":"+1 418 466 2239",
    "sg:postcode":"G0R 1A0",
    "sg:province":"QC",
    "sg:tags":[
        "excavating",
        "contractor"
    ],
    "wof:name":"Excavations Chanel & Fils",
    "wof:placetype":"venue"
},
  "geometry": {"coordinates":[-70.54467,46.751209],"type":"Point"}
}