{
  "type": "Feature",
  "properties": {
    "addr:full":"245 Industrial Dr Saint John NB E2R 1A4",
    "addr:housenumber":"245",
    "addr:postcode":"e2r 1a4",
    "addr:street":"Industrial Dr",
    "iso:country":"CA",
    "sg:address":"245 Industrial Dr",
    "sg:city":"Saint John",
    "sg:classifiers":[
        {
            "category":"Manufacturing",
            "subcategory":"Metals",
            "type":"Manufacturing & Wholesale Goods"
        }
    ],
    "sg:phone":"+1 506 633 2541",
    "sg:postcode":"E2R 1A4",
    "sg:province":"NB",
    "sg:tags":[
        "valve"
    ],
    "wof:name":"Clow Canada-Saint John Plant",
    "wof:placetype":"venue"
},
  "geometry": {"coordinates":[-66.0032424927,45.276184082],"type":"Point"}
}