{
  "type": "Feature",
  "properties": {
    "addr:full":"10035 101 Ave Lac LA Biche AB T0A 2C0",
    "addr:housenumber":"10035",
    "addr:postcode":"t0a 2c0",
    "addr:street":"101 Ave",
    "iso:country":"CA",
    "sg:address":"10035 101 Ave",
    "sg:city":"Lac LA Biche",
    "sg:classifiers":[
        {
            "category":"Shopping",
            "subcategory":"Crafts & Fabrics",
            "type":"Retail Goods"
        }
    ],
    "sg:phone":"+1 780 623 3141",
    "sg:postcode":"T0A 2C0",
    "sg:province":"AB",
    "sg:tags":[
        "shop"
    ],
    "wof:name":"Creative Beginnings",
    "wof:placetype":"venue"
},
  "geometry": {"coordinates":[-111.973969,54.771126],"type":"Point"}
}