{
  "type": "Feature",
  "properties": {
    "addr:full":"106 Akins St Meaford ON N4L 1B3",
    "addr:housenumber":"106",
    "addr:postcode":"n4l 1b3",
    "addr:street":"Akins St",
    "iso:country":"CA",
    "sg:address":"106 Akins St",
    "sg:city":"Meaford",
    "sg:classifiers":[
        {
            "category":"Home & Garden",
            "subcategory":"Building Materials",
            "type":"Retail Goods"
        }
    ],
    "sg:phone":"+1 519 538 2965",
    "sg:postcode":"N4L 1B3",
    "sg:province":"ON",
    "sg:tags":[
        "door"
    ],
    "wof:name":"Georgian Highland Overhead",
    "wof:placetype":"venue"
},
  "geometry": {"coordinates":[-80.5928573608,44.6066551208],"type":"Point"}
}