{
  "type": "Feature",
  "properties": {
    "addr:full":"534 Rue Sainte-Marthe Thetford Mines QC G6G 7M3",
    "addr:housenumber":"534",
    "addr:postcode":"g6g 7m3",
    "addr:street":"Rue Sainte-Marthe",
    "iso:country":"CA",
    "sg:address":"534 Rue Sainte-Marthe",
    "sg:city":"Thetford Mines",
    "sg:classifiers":[
        {
            "category":"Organizations",
            "subcategory":"Professional Association",
            "type":"Services"
        }
    ],
    "sg:phone":"+1 418 335 5075",
    "sg:postcode":"G6G 7M3",
    "sg:province":"QC",
    "wof:name":"Maison Des Jeunes DE Thetford",
    "wof:placetype":"venue"
},
  "geometry": {"coordinates":[-71.302521,46.100079],"type":"Point"}
}