{
  "type": "Feature",
  "properties": {
    "addr:full":"4150 Rue Barbeau Saint-Hubert QC J3Y 5Y1",
    "addr:housenumber":"4150",
    "addr:postcode":"j3y 5y1",
    "addr:street":"Rue Barbeau",
    "iso:country":"CA",
    "sg:address":"4150 Rue Barbeau",
    "sg:city":"Saint-Hubert",
    "sg:classifiers":[
        {
            "category":"Retail",
            "subcategory":"Repair Shop",
            "type":"Services"
        }
    ],
    "sg:phone":"+1 450 462 2248",
    "sg:postcode":"J3Y 5Y1",
    "sg:province":"QC",
    "sg:tags":[
        "lock",
        "locksmith"
    ],
    "wof:name":"A B Cardinal Serrurier Rive S",
    "wof:placetype":"venue"
},
  "geometry": {"coordinates":[-73.423393,45.482178],"type":"Point"}
}