{
  "type": "Feature",
  "properties": {
    "addr:full":"1377 Boul Pie-Xi S Val-Belair QC G3K 1H2",
    "addr:housenumber":"1377",
    "addr:postcode":"g3k 1h2",
    "addr:street":"Boul Pie-Xi S Val-Belair",
    "iso:country":"CA",
    "sg:address":"1377 Boul Pie-Xi S",
    "sg:city":"Val-Belair",
    "sg:classifiers":[
        {
            "category":"Personal",
            "subcategory":"Beauty Salon",
            "type":"Services"
        }
    ],
    "sg:phone":"+1 418 843 9254",
    "sg:postcode":"G3K 1H2",
    "sg:province":"QC",
    "wof:name":"Salon Bel-Homme",
    "wof:placetype":"venue"
},
  "geometry": {"coordinates":[-71.3988647461,46.8454818726],"type":"Point"}
}