{
  "type": "Feature",
  "properties": {
    "addr:full":"222 Eramosa Rd Guelph ON N1E 2M4",
    "addr:housenumber":"222",
    "addr:postcode":"n1e 2m4",
    "addr:street":"Eramosa Rd",
    "iso:country":"CA",
    "sg:address":"222 Eramosa Rd",
    "sg:city":"Guelph",
    "sg:classifiers":[
        {
            "category":"Health Services",
            "subcategory":"Optometrist",
            "type":"Services"
        }
    ],
    "sg:phone":"+1 519 836 2590",
    "sg:postcode":"N1E 2M4",
    "sg:province":"ON",
    "wof:name":"Tessel, Patrick OD",
    "wof:placetype":"venue"
},
  "geometry": {"coordinates":[-80.2497177124,43.5561256409],"type":"Point"}
}