{
  "type": "Feature",
  "properties": {
    "addr:full":"5181 Bradco Blvd Mississauga ON L4W 2A6",
    "addr:housenumber":"5181",
    "addr:postcode":"l4w 2a6",
    "addr:street":"Bradco Blvd",
    "iso:country":"CA",
    "sg:address":"5181 Bradco Blvd",
    "sg:city":"Mississauga",
    "sg:classifiers":[
        {
            "category":"Wholesale",
            "subcategory":"Machinery & Supplies",
            "type":"Manufacturing & Wholesale Goods"
        }
    ],
    "sg:phone":"+1 905 625 7257",
    "sg:postcode":"L4W 2A6",
    "sg:province":"ON",
    "sg:tags":[
        "equipment",
        "plastic"
    ],
    "wof:name":"Negri Boss Inc",
    "wof:placetype":"venue"
},
  "geometry": {"coordinates":[-79.63041699999999,43.636036],"type":"Point"}
}