{
  "type": "Feature",
  "properties": {
    "addr:full":"464 Bloor St W Toronto ON M5S 1X8",
    "addr:housenumber":"464",
    "addr:postcode":"m5s 1x8",
    "addr:street":"Bloor St W",
    "iso:country":"CA",
    "sg:address":"464 Bloor St W",
    "sg:city":"Toronto",
    "sg:classifiers":[
        {
            "category":"Home & Garden",
            "subcategory":"Furniture",
            "type":"Retail Goods"
        }
    ],
    "sg:phone":"+1 416 588 1391",
    "sg:postcode":"M5S 1X8",
    "sg:province":"ON",
    "sg:tags":[
        "mattress",
        "futon"
    ],
    "wof:name":"East West Futons",
    "wof:placetype":"venue"
},
  "geometry": {"coordinates":[-79.4094696045,43.6655273438],"type":"Point"}
}