{
  "type": "Feature",
  "properties": {
    "addr:full":"PO Box 433 Lantzville BC V0R 2H0",
    "addr:housenumber":"po",
    "addr:postcode":"v0r 2h0",
    "addr:street":"Box 433",
    "iso:country":"CA",
    "sg:address":"PO Box 433",
    "sg:city":"Lantzville",
    "sg:classifiers":[
        {
            "category":"Professional",
            "subcategory":"Detective & Security Services",
            "type":"Services"
        }
    ],
    "sg:phone":"+1 250 755 5081",
    "sg:postcode":"V0R 2H0",
    "sg:province":"BC",
    "sg:tags":[
        "investigator"
    ],
    "wof:name":"Q T Investigations",
    "wof:placetype":"venue"
},
  "geometry": {"coordinates":[-124.073257446,49.2489776611],"type":"Point"}
}