{
  "type": "Feature",
  "properties": {
    "iso:country":"CA",
    "sg:address":"5837 Victoria Dr",
    "sg:city":"Vancouver",
    "sg:classifiers":[
        {
            "category":"Health Services",
            "subcategory":"Clinic",
            "type":"Services"
        }
    ],
    "sg:phone":"+1 604 323 1283",
    "sg:postcode":"V5P 3W5",
    "sg:province":"BC",
    "sg:tags":[
        "herbalist"
    ],
    "wof:name":"Wui King Herbal CO Ltd",
    "wof:placetype":"venue"
},
  "geometry": {"coordinates":[-123.065697,49.231388],"type":"Point"}
}