{
  "type": "Feature",
  "properties": {
    "addr:full":"Mountain View AB T0K 1N0",
    "addr:postcode":"t0k 1n0",
    "iso:country":"CA",
    "sg:city":"Mountain View",
    "sg:classifiers":[
        {
            "category":"Travel",
            "subcategory":"Hotels & Motels",
            "type":"Entertainment"
        }
    ],
    "sg:phone":"+1 403 653 2353",
    "sg:postcode":"T0K 1N0",
    "sg:province":"AB",
    "wof:name":"Mountain View Motel",
    "wof:placetype":"venue"
},
  "geometry": {"coordinates":[-113.605834961,49.1324195862],"type":"Point"}
}