{
  "type": "Feature",
  "properties": {
    "addr:full":"310 24th St Fort Macleod AB T0L 0Z0",
    "addr:housenumber":"310",
    "addr:postcode":"t0l 0z0",
    "addr:street":"24Th St",
    "iso:country":"CA",
    "sg:address":"310 24th St",
    "sg:city":"Fort Macleod",
    "sg:classifiers":[
        {
            "category":"Manufacturing",
            "subcategory":"Printing",
            "type":"Manufacturing & Wholesale Goods"
        }
    ],
    "sg:phone":"+1 403 553 3391",
    "sg:postcode":"T0L 0Z0",
    "sg:province":"AB",
    "sg:tags":[
        "newspaper"
    ],
    "wof:name":"Mac Leod Gazette Ltd",
    "wof:placetype":"venue"
},
  "geometry": {"coordinates":[-113.395584,49.726074],"type":"Point"}
}