{
  "type": "Feature",
  "properties": {
    "iso:country":"CA",
    "sg:address":"7412 Kipling Ave",
    "sg:city":"Woodbridge",
    "sg:classifiers":[
        {
            "category":"Restaurant",
            "type":"Food & Drink"
        }
    ],
    "sg:phone":"+1 905 851 6905",
    "sg:postcode":"L4L 1Y4",
    "sg:province":"ON",
    "sg:tags":[
        "banquet",
        "rooms"
    ],
    "wof:name":"Ciociaro Social Club",
    "wof:placetype":"venue"
},
  "geometry": {"coordinates":[-79.5957870483,43.7719841003],"type":"Point"}
}