{
  "type": "Feature",
  "properties": {
    "addr:full":"1355 Huntingwood Dr Scarborough ON M1S 3J1",
    "addr:housenumber":"1355",
    "addr:postcode":"m1s 3j1",
    "addr:street":"Huntingwood Dr",
    "iso:country":"CA",
    "sg:address":"1355 Huntingwood Dr",
    "sg:city":"Scarborough",
    "sg:classifiers":[
        {
            "category":"Manufacturing",
            "subcategory":"Printing",
            "type":"Manufacturing & Wholesale Goods"
        }
    ],
    "sg:phone":"+1 416 321 0088",
    "sg:postcode":"M1S 3J1",
    "sg:province":"ON",
    "sg:tags":[
        "newspaper"
    ],
    "wof:name":"Ming Pao Newspapers Ltd",
    "wof:placetype":"venue"
},
  "geometry": {"coordinates":[-79.26796,43.797699],"type":"Point"}
}