{
  "type": "Feature",
  "properties": {
    "addr:full":"302 Central Ave N Swift Current SK S9H 0L4",
    "addr:housenumber":"302",
    "addr:postcode":"s9h 0l4",
    "addr:street":"Central Ave N",
    "iso:country":"CA",
    "sg:address":"302 Central Ave N",
    "sg:city":"Swift Current",
    "sg:classifiers":[
        {
            "category":"Health Services",
            "subcategory":"Health Practitioner",
            "type":"Services"
        }
    ],
    "sg:phone":"+1 306 773 8313",
    "sg:postcode":"S9H 0L4",
    "sg:province":"SK",
    "sg:tags":[
        "therapist",
        "physical"
    ],
    "wof:name":"Farrell, Tami",
    "wof:placetype":"venue"
},
  "geometry": {"coordinates":[-107.800315857,50.2867774963],"type":"Point"}
}