{
  "type": "Feature",
  "properties": {
    "addr:full":"1288A Torbay Rd Torbay NL A1K 1B2",
    "addr:housenumber":"1288a",
    "addr:postcode":"a1k 1b2",
    "addr:street":"Torbay Rd",
    "iso:country":"CA",
    "sg:address":"1288A Torbay Rd",
    "sg:city":"Torbay",
    "sg:classifiers":[
        {
            "category":"Education",
            "subcategory":"Library",
            "type":"Public Place"
        }
    ],
    "sg:phone":"+1 709 437 6571",
    "sg:postcode":"A1K 1B2",
    "sg:province":"NL",
    "wof:name":"Torbay Public Library",
    "wof:placetype":"venue"
},
  "geometry": {"coordinates":[-52.7286338806,47.6563987732],"type":"Point"}
}