{
  "type": "Feature",
  "properties": {
    "addr:full":"London ON N6L 1C1",
    "addr:postcode":"n6l 1c1",
    "iso:country":"CA",
    "sg:city":"London",
    "sg:classifiers":[
        {
            "category":"Wholesale",
            "subcategory":"Machinery & Supplies",
            "type":"Manufacturing & Wholesale Goods"
        }
    ],
    "sg:phone":"+1 519 686 5882",
    "sg:postcode":"N6L 1C1",
    "sg:province":"ON",
    "sg:tags":[
        "equipment",
        "hydraulic"
    ],
    "wof:name":"Hydraulic Sales & Repair",
    "wof:placetype":"venue"
},
  "geometry": {"coordinates":[-81.250648,42.922844],"type":"Point"}
}