{
  "type": "Feature",
  "properties": {
    "addr:full":"51 Simcoe St # B Tillsonburg ON N4G 2H6",
    "addr:housenumber":"51",
    "addr:postcode":"n4g 2h6",
    "addr:street":"Simcoe St # B",
    "iso:country":"CA",
    "sg:address":"51 Simcoe St # B",
    "sg:city":"Tillsonburg",
    "sg:classifiers":[
        {
            "category":"Food & Beverages",
            "subcategory":"Meat & Fish",
            "type":"Retail Goods"
        }
    ],
    "sg:phone":"+1 519 842 4641",
    "sg:postcode":"N4G 2H6",
    "sg:province":"ON",
    "sg:tags":[
        "frozen"
    ],
    "wof:name":"M & M Meat Shops Ltd",
    "wof:placetype":"venue"
},
  "geometry": {"coordinates":[-80.7158203125,42.8597755432],"type":"Point"}
}