{
  "type": "Feature",
  "properties": {
    "addr:full":"Placentia NL A0B 2Y0",
    "addr:postcode":"a0b 2y0",
    "iso:country":"CA",
    "sg:city":"Placentia",
    "sg:classifiers":[
        {
            "category":"Home & Garden",
            "subcategory":"Building Materials",
            "type":"Retail Goods"
        }
    ],
    "sg:phone":"+1 709 227 5253",
    "sg:postcode":"A0B 2Y0",
    "sg:province":"NL",
    "sg:tags":[
        "paint"
    ],
    "wof:name":"Paint Shop",
    "wof:placetype":"venue"
},
  "geometry": {"coordinates":[-53.9622192383,47.2540740967],"type":"Point"}
}