{
  "type": "Feature",
  "properties": {
    "addr:full":"2715 Place Darlington Montreal QC H3S 1L4",
    "addr:housenumber":"2715",
    "addr:postcode":"h3s 1l4",
    "addr:street":"Place Darlington",
    "iso:country":"CA",
    "sg:address":"2715 Place Darlington",
    "sg:city":"Montreal",
    "sg:classifiers":[
        {
            "category":"Professional",
            "subcategory":"Management & Consulting",
            "type":"Services"
        }
    ],
    "sg:phone":"+1 514 940 2475",
    "sg:postcode":"H3S 1L4",
    "sg:province":"QC",
    "sg:tags":[
        "consultant",
        "business"
    ],
    "wof:name":"Edna Hypotherapie Enr",
    "wof:placetype":"venue"
},
  "geometry": {"coordinates":[-73.628525,45.509212],"type":"Point"}
}