{
  "type": "Feature",
  "properties": {
    "addr:full":"Winnipeg MB R2M 5G9",
    "addr:postcode":"r2m 5g9",
    "iso:country":"CA",
    "sg:city":"Winnipeg",
    "sg:classifiers":[
        {
            "category":"Health Services",
            "subcategory":"Doctor",
            "type":"Services"
        }
    ],
    "sg:phone":"+1 204 253 5786",
    "sg:postcode":"R2M 5G9",
    "sg:province":"MB",
    "sg:tags":[
        "dentist"
    ],
    "wof:name":"Levine & Row",
    "wof:placetype":"venue"
},
  "geometry": {"coordinates":[-97.136482,49.891891],"type":"Point"}
}