{
  "type": "Feature",
  "properties": {
    "addr:full":"70 Main St E Milton ON L9T 1N3",
    "addr:housenumber":"70",
    "addr:postcode":"l9t 1n3",
    "addr:street":"Main St E",
    "iso:country":"CA",
    "sg:address":"70 Main St E",
    "sg:city":"Milton",
    "sg:classifiers":[
        {
            "category":"Shopping",
            "subcategory":"Pharmacy",
            "type":"Retail Goods"
        }
    ],
    "sg:phone":"+1 905 875 2424",
    "sg:postcode":"L9T 1N3",
    "sg:province":"ON",
    "wof:name":"Zak's Pharmacy",
    "wof:placetype":"venue"
},
  "geometry": {"coordinates":[-79.886208,43.510071],"type":"Point"}
}