{
  "type": "Feature",
  "properties": {
    "addr:full":"Saint-Hyacinthe QC J2S 1H5",
    "addr:postcode":"j2s 1h5",
    "iso:country":"CA",
    "sg:city":"Saint-Hyacinthe",
    "sg:classifiers":[
        {
            "category":"Wholesale",
            "subcategory":"Farm Supplies",
            "type":"Manufacturing & Wholesale Goods"
        }
    ],
    "sg:phone":"+1 450 778 1349",
    "sg:postcode":"J2S 1H5",
    "sg:province":"QC",
    "sg:tags":[
        "feed"
    ],
    "wof:name":"Bio Biscuit Inc",
    "wof:placetype":"venue"
},
  "geometry": {"coordinates":[-72.975692749,45.6352615356],"type":"Point"}
}