{
  "type": "Feature",
  "properties": {
    "addr:full":"161 Laurier Ave W Ottawa ON K1P 5J2",
    "addr:housenumber":"161",
    "addr:postcode":"k1p 5j2",
    "addr:street":"Laurier Ave W",
    "iso:country":"CA",
    "sg:address":"161 Laurier Ave W",
    "sg:city":"Ottawa",
    "sg:classifiers":[
        {
            "category":"Personal",
            "subcategory":"Beauty Salon",
            "type":"Services"
        }
    ],
    "sg:phone":"+1 613 230 2500",
    "sg:postcode":"K1P 5J2",
    "sg:province":"ON",
    "wof:name":"Boss Arts Beauty in Balance",
    "wof:placetype":"venue"
},
  "geometry": {"coordinates":[-75.69427490229999,45.4206809998],"type":"Point"}
}