{
  "type": "Feature",
  "properties": {
    "addr:full":"2127 146 Ave SE Calgary AB T2J 6P8",
    "addr:housenumber":"2127",
    "addr:postcode":"t2j 6p8",
    "addr:street":"146 Ave Se",
    "iso:country":"CA",
    "sg:address":"2127 146 Ave SE",
    "sg:city":"Calgary",
    "sg:classifiers":[
        {
            "category":"Education",
            "subcategory":"School",
            "type":"Public Place"
        }
    ],
    "sg:phone":"+1 403 777 6840",
    "sg:postcode":"T2J 6P8",
    "sg:province":"AB",
    "wof:name":"Deer Run Elementary School",
    "wof:placetype":"venue"
},
  "geometry": {"coordinates":[-114.009757996,50.9218902588],"type":"Point"}
}