{
  "type": "Feature",
  "properties": {
    "addr:full":"17303 107 Ave NW Edmonton AB T5S 1E5",
    "addr:housenumber":"17303",
    "addr:postcode":"t5s 1e5",
    "addr:street":"107 Ave Nw",
    "iso:country":"CA",
    "sg:address":"17303 107 Ave NW",
    "sg:city":"Edmonton",
    "sg:classifiers":[
        {
            "category":"Manufacturing",
            "subcategory":"Tools & Machinery",
            "type":"Manufacturing & Wholesale Goods"
        }
    ],
    "sg:phone":"+1 780 444 7184",
    "sg:postcode":"T5S 1E5",
    "sg:province":"AB",
    "sg:tags":[
        "control"
    ],
    "wof:name":"Indcon Design Ltd",
    "wof:placetype":"venue"
},
  "geometry": {"coordinates":[-113.61985799999999,53.553131],"type":"Point"}
}