{
  "type": "Feature",
  "properties": {
    "addr:full":"Edmonton AB T6J 5M5",
    "addr:postcode":"t6j 5m5",
    "iso:country":"CA",
    "sg:city":"Edmonton",
    "sg:classifiers":[
        {
            "category":"Travel",
            "subcategory":"Travel Agent",
            "type":"Entertainment"
        }
    ],
    "sg:phone":"+1 780 413 8155",
    "sg:postcode":"T6J 5M5",
    "sg:province":"AB",
    "sg:tags":[
        "agency",
        "bureau"
    ],
    "wof:name":"Travel Home",
    "wof:placetype":"venue"
},
  "geometry": {"coordinates":[-113.501762,53.461987],"type":"Point"}
}