{
  "type": "Feature",
  "properties": {
    "addr:full":"17615 South Branch Rd Cornwall ON K6H 5R6",
    "addr:housenumber":"17615",
    "addr:postcode":"k6h 5r6",
    "addr:street":"South Branch Rd",
    "iso:country":"CA",
    "sg:address":"17615 South Branch Rd",
    "sg:city":"Cornwall",
    "sg:classifiers":[
        {
            "category":"Building & Trades",
            "subcategory":"Electrical",
            "type":"Services"
        }
    ],
    "sg:phone":"+1 613 938 1770",
    "sg:postcode":"K6H 5R6",
    "sg:province":"ON",
    "sg:tags":[
        "electric",
        "contractor"
    ],
    "wof:name":"Seymour & Boals Ltd",
    "wof:placetype":"venue"
},
  "geometry": {"coordinates":[-74.755669,45.066662],"type":"Point"}
}