{
  "type": "Feature",
  "properties": {
    "addr:full":"21 Arthur St W Thornbury ON N0H 2P0",
    "addr:housenumber":"21",
    "addr:postcode":"n0h 2p0",
    "addr:street":"Arthur St W",
    "iso:country":"CA",
    "sg:address":"21 Arthur St W",
    "sg:city":"Thornbury",
    "sg:classifiers":[
        {
            "category":"Health Services",
            "subcategory":"Doctor",
            "type":"Services"
        }
    ],
    "sg:phone":"+1 519 599 2732",
    "sg:postcode":"N0H 2P0",
    "sg:province":"ON",
    "sg:tags":[
        "physician",
        "surgeon"
    ],
    "wof:name":"Remillard, Tim MD",
    "wof:placetype":"venue"
},
  "geometry": {"coordinates":[-80.45426940919999,44.5623855591],"type":"Point"}
}