{
  "type": "Feature",
  "properties": {
    "addr:full":"Winnipeg MB R3C 3T1",
    "addr:postcode":"r3c 3t1",
    "iso:country":"CA",
    "sg:city":"Winnipeg",
    "sg:classifiers":[
        {
            "category":"Professional",
            "subcategory":"Employment Agencies",
            "type":"Services"
        }
    ],
    "sg:phone":"+1 204 942 8735",
    "sg:postcode":"R3C 3T1",
    "sg:province":"MB",
    "sg:tags":[
        "consultant",
        "search",
        "executive",
        "management",
        "business"
    ],
    "wof:name":"Harris Consulting Corp",
    "wof:placetype":"venue"
},
  "geometry": {"coordinates":[-97.149033,49.888851],"type":"Point"}
}