{
  "type": "Feature",
  "properties": {
    "iso:country":"CA",
    "sg:address":"326 Victoria St",
    "sg:city":"London",
    "sg:classifiers":[
        {
            "category":"Banks & Credit Unions",
            "subcategory":"Bank",
            "type":"Services"
        }
    ],
    "sg:phone":"+1 519 858 4646",
    "sg:postcode":"N6A 2C5",
    "sg:province":"ON",
    "sg:tags":[
        "financing"
    ],
    "wof:name":"Park Street Capital Corp",
    "wof:placetype":"venue"
},
  "geometry": {"coordinates":[-81.2532119751,43.0050392151],"type":"Point"}
}