{
  "type": "Feature",
  "properties": {
    "addr:full":"10251 101st Ave Lac LA Biche AB T0A 2C0",
    "addr:housenumber":"10251",
    "addr:postcode":"t0a 2c0",
    "addr:street":"101St Ave",
    "iso:country":"CA",
    "sg:address":"10251 101st Ave",
    "sg:city":"Lac LA Biche",
    "sg:classifiers":[
        {
            "category":"Home & Garden",
            "subcategory":"Household Appliances",
            "type":"Retail Goods"
        }
    ],
    "sg:phone":"+1 780 623 4456",
    "sg:postcode":"T0A 2C0",
    "sg:province":"AB",
    "sg:tags":[
        "mail",
        "catalog",
        "shopping",
        "order"
    ],
    "wof:name":"Sears Canada Inc",
    "wof:placetype":"venue"
},
  "geometry": {"coordinates":[-111.98097199999999,54.768566],"type":"Point"}
}