{
  "type": "Feature",
  "properties": {
    "addr:full":"3174 Sunridge Blvd NE Calgary AB T1Y 7G6",
    "addr:housenumber":"3174",
    "addr:postcode":"t1y 7g6",
    "addr:street":"Sunridge Blvd Ne",
    "iso:country":"CA",
    "sg:address":"3174 Sunridge Blvd NE",
    "sg:city":"Calgary",
    "sg:classifiers":[
        {
            "category":"Restaurant",
            "type":"Food & Drink"
        }
    ],
    "sg:phone":"+1 403 250 5295",
    "sg:postcode":"T1Y 7G6",
    "sg:province":"AB",
    "wof:name":"Subway Sandwiches & Salads",
    "wof:placetype":"venue"
},
  "geometry": {"coordinates":[-113.987464905,51.07579422],"type":"Point"}
}