{
  "type": "Feature",
  "properties": {
    "addr:full":"93 Bronte Rd Oakville ON L6L 3B7",
    "addr:housenumber":"93",
    "addr:postcode":"l6l 3b7",
    "addr:street":"Bronte Rd",
    "iso:country":"CA",
    "sg:address":"93 Bronte Rd",
    "sg:city":"Oakville",
    "sg:classifiers":[
        {
            "category":"Restaurant",
            "type":"Food & Drink"
        }
    ],
    "sg:phone":"+1 905 827 2378",
    "sg:postcode":"L6L 3B7",
    "sg:province":"ON",
    "wof:name":"Parisienne Creperie",
    "wof:placetype":"venue"
},
  "geometry": {"coordinates":[-79.71165499999999,43.394199],"type":"Point"}
}