{
  "type": "Feature",
  "properties": {
    "addr:full":"2080 Piper Lane London ON N5V 3N6",
    "addr:housenumber":"2080",
    "addr:postcode":"n5v 3n6",
    "addr:street":"Piper Lane",
    "iso:country":"CA",
    "sg:address":"2080 Piper Lane",
    "sg:city":"London",
    "sg:classifiers":[
        {
            "category":"Shopping",
            "subcategory":"Gifts & Souvenirs",
            "type":"Retail Goods"
        }
    ],
    "sg:phone":"+1 519 452 1990",
    "sg:postcode":"N5V 3N6",
    "sg:province":"ON",
    "sg:tags":[
        "collectible"
    ],
    "wof:name":"Bradford Exchange",
    "wof:placetype":"venue"
},
  "geometry": {"coordinates":[-81.166664,43.024559],"type":"Point"}
}