{
  "type": "Feature",
  "properties": {
    "addr:full":"21 Mckenzie Lane Moose Jaw SK S6J 1M7",
    "addr:housenumber":"21",
    "addr:postcode":"s6j 1m7",
    "addr:street":"Mckenzie Lane",
    "iso:country":"CA",
    "sg:address":"21 Mckenzie Lane",
    "sg:city":"Moose Jaw",
    "sg:classifiers":[
        {
            "category":"Home & Garden",
            "subcategory":"Carpets & Floor Coverings",
            "type":"Retail Goods"
        }
    ],
    "sg:phone":"+1 306 693 3977",
    "sg:postcode":"S6J 1M7",
    "sg:province":"SK",
    "sg:tags":[
        "rug"
    ],
    "wof:name":"Carpet Gallery of Moose Jaw",
    "wof:placetype":"venue"
},
  "geometry": {"coordinates":[-105.520683289,50.4130973816],"type":"Point"}
}