{
  "type": "Feature",
  "properties": {
    "addr:full":"Shannon QC G0A 4N0",
    "addr:postcode":"g0a 4n0",
    "iso:country":"CA",
    "sg:city":"Shannon",
    "sg:classifiers":[
        {
            "category":"Shopping",
            "subcategory":"Computers & Home Electronics",
            "type":"Retail Goods"
        }
    ],
    "sg:phone":"+1 418 844 1997",
    "sg:postcode":"G0A 4N0",
    "sg:province":"QC",
    "sg:tags":[
        "equipment",
        "video"
    ],
    "wof:name":"Pedro Video",
    "wof:placetype":"venue"
},
  "geometry": {"coordinates":[-71.5166931152,46.8879966736],"type":"Point"}
}