{
  "type": "Feature",
  "properties": {
    "iso:country":"CA",
    "sg:address":"2 Wendover Rd",
    "sg:city":"Etobicoke",
    "sg:classifiers":[
        {
            "category":"Shopping",
            "subcategory":"Discount & Variety Stores",
            "type":"Retail Goods"
        }
    ],
    "sg:phone":"+1 416 239 9752",
    "sg:postcode":"M8X 2K9",
    "sg:province":"ON",
    "wof:name":"Kingsway Pops Variety Ltd",
    "wof:placetype":"venue"
},
  "geometry": {"coordinates":[-79.5068893433,43.6486434937],"type":"Point"}
}