{
  "type": "Feature",
  "properties": {
    "addr:full":"Matane QC G4W 2Y5",
    "addr:postcode":"g4w 2y5",
    "iso:country":"CA",
    "sg:city":"Matane",
    "sg:classifiers":[
        {
            "category":"Travel",
            "subcategory":"Hotels & Motels",
            "type":"Entertainment"
        }
    ],
    "sg:phone":"+1 418 562 6688",
    "sg:postcode":"G4W 2Y5",
    "sg:province":"QC",
    "sg:tags":[
        "breakfast",
        "accommodation",
        "bed"
    ],
    "wof:name":"Gite Des Iles",
    "wof:placetype":"venue"
},
  "geometry": {"coordinates":[-67.5271987915,48.8432617188],"type":"Point"}
}