{
  "type": "Feature",
  "properties": {
    "iso:country":"CA",
    "sg:address":"1839 Rue Lepine",
    "sg:city":"Joliette",
    "sg:classifiers":[
        {
            "category":"Wholesale",
            "subcategory":"Electrical",
            "type":"Manufacturing & Wholesale Goods"
        }
    ],
    "sg:phone":"+1 450 755 2002",
    "sg:postcode":"J6E 7G3",
    "sg:province":"QC",
    "sg:tags":[
        "electric",
        "motor"
    ],
    "wof:name":"Jolec Industrie Inc",
    "wof:placetype":"venue"
},
  "geometry": {"coordinates":[-73.4556274414,46.004108429],"type":"Point"}
}