{
  "type": "Feature",
  "properties": {
    "iso:country":"CA",
    "sg:city":"Toronto",
    "sg:classifiers":[
        {
            "category":"Professional",
            "subcategory":"Lawyer & Legal Services",
            "type":"Services"
        }
    ],
    "sg:phone":"+1 416 362 6437",
    "sg:postcode":"M5H 2S8",
    "sg:province":"ON",
    "sg:tags":[
        "attorney"
    ],
    "wof:name":"Bellissimo, Steven",
    "wof:placetype":"venue"
},
  "geometry": {"coordinates":[-79.38106536870001,43.6500816345],"type":"Point"}
}