{
  "type": "Feature",
  "properties": {
    "addr:full":"1950 Angus St Regina SK S4T 1Z6",
    "addr:housenumber":"1950",
    "addr:postcode":"s4t 1z6",
    "addr:street":"Angus St",
    "iso:country":"CA",
    "sg:address":"1950 Angus St",
    "sg:city":"Regina",
    "sg:classifiers":[
        {
            "category":"Personal",
            "subcategory":"Beauty Salon",
            "type":"Services"
        }
    ],
    "sg:phone":"+1 306 757 6200",
    "sg:postcode":"S4T 1Z6",
    "sg:province":"SK",
    "wof:name":"Colour Box",
    "wof:placetype":"venue"
},
  "geometry": {"coordinates":[-104.61983499999999,50.448032],"type":"Point"}
}