{
  "type": "Feature",
  "properties": {
    "addr:full":"Etobicoke ON M8V 2W8",
    "addr:postcode":"m8v 2w8",
    "iso:country":"CA",
    "sg:city":"Etobicoke",
    "sg:classifiers":[
        {
            "category":"Retail",
            "subcategory":"Auto Repair",
            "type":"Services"
        }
    ],
    "sg:phone":"+1 416 251 3493",
    "sg:postcode":"M8V 2W8",
    "sg:province":"ON",
    "sg:tags":[
        "repairing",
        "automobile"
    ],
    "wof:name":"M & W General Auto Repairs",
    "wof:placetype":"venue"
},
  "geometry": {"coordinates":[-79.4994506836,43.6129875183],"type":"Point"}
}