{
  "type": "Feature",
  "properties": {
    "iso:country":"CA",
    "sg:city":"Burnaby",
    "sg:classifiers":[
        {
            "category":"Restaurant",
            "type":"Food & Drink"
        }
    ],
    "sg:phone":"+1 604 421 0087",
    "sg:postcode":"V3J 1N4",
    "sg:province":"BC",
    "wof:name":"Grainery Cafe",
    "wof:placetype":"venue"
},
  "geometry": {"coordinates":[-122.895767,49.249142],"type":"Point"}
}