{
  "type": "Feature",
  "properties": {
    "addr:full":"1210 Adelaide St N London ON N5Y 4T6",
    "addr:housenumber":"1210",
    "addr:postcode":"n5y 4t6",
    "addr:street":"Adelaide St N",
    "iso:country":"CA",
    "sg:address":"1210 Adelaide St N",
    "sg:city":"London",
    "sg:classifiers":[
        {
            "category":"Organizations",
            "subcategory":"Religious Organization",
            "type":"Services"
        }
    ],
    "sg:phone":"+1 519 433 7081",
    "sg:postcode":"N5Y 4T6",
    "sg:province":"ON",
    "sg:tags":[
        "synagogue"
    ],
    "wof:name":"Beth Tefilah Synagogue",
    "wof:placetype":"venue"
},
  "geometry": {"coordinates":[-81.246178,43.018394],"type":"Point"}
}