{
  "type": "Feature",
  "properties": {
    "iso:country":"CA",
    "sg:address":"170 King St W",
    "sg:city":"Prescott",
    "sg:classifiers":[
        {
            "category":"Food & Beverages",
            "subcategory":"Groceries & Convenience Stores",
            "type":"Retail Goods"
        }
    ],
    "sg:phone":"+1 613 925 2939",
    "sg:postcode":"K0E 1T0",
    "sg:province":"ON",
    "sg:tags":[
        "cigarette",
        "cigar",
        "dealer",
        "tobacco"
    ],
    "wof:name":"Lane's Smoke Shop",
    "wof:placetype":"venue"
},
  "geometry": {"coordinates":[-75.514053,44.709827],"type":"Point"}
}