{
  "type": "Feature",
  "properties": {
    "addr:full":"31 Golden Gate Crt Scarborough ON M1P 3A4",
    "addr:housenumber":"31",
    "addr:postcode":"m1p 3a4",
    "addr:street":"Golden Gate Crt",
    "iso:country":"CA",
    "sg:address":"31 Golden Gate Crt",
    "sg:city":"Scarborough",
    "sg:classifiers":[
        {
            "category":"Wholesale",
            "subcategory":"Scrap",
            "type":"Manufacturing & Wholesale Goods"
        }
    ],
    "sg:phone":"+1 416 299 0116",
    "sg:postcode":"M1P 3A4",
    "sg:province":"ON",
    "sg:tags":[
        "waste"
    ],
    "wof:name":"Network Environmental Svc Inc",
    "wof:placetype":"venue"
},
  "geometry": {"coordinates":[-79.26402299999999,43.77132],"type":"Point"}
}