{
  "type": "Feature",
  "properties": {
    "addr:full":"5419 Elgin Rd Harrietsville ON N0L 1N0",
    "addr:housenumber":"5419",
    "addr:postcode":"n0l 1n0",
    "addr:street":"Elgin Rd",
    "iso:country":"CA",
    "sg:address":"5419 Elgin Rd",
    "sg:city":"Harrietsville",
    "sg:classifiers":[
        {
            "category":"Retail",
            "subcategory":"Auto Repair",
            "type":"Services"
        }
    ],
    "sg:phone":"+1 519 269 3787",
    "sg:postcode":"N0L 1N0",
    "sg:province":"ON",
    "sg:tags":[
        "automobile",
        "rustproofing",
        "undercoating"
    ],
    "wof:name":"Ron's Rust Control",
    "wof:placetype":"venue"
},
  "geometry": {"coordinates":[-81.00296,42.910896],"type":"Point"}
}