{
  "type": "Feature",
  "properties": {
    "addr:full":"10759 Rue Laverdure Montreal QC H3L 2L8",
    "addr:housenumber":"10759",
    "addr:postcode":"h3l 2l8",
    "addr:street":"Rue Laverdure",
    "iso:country":"CA",
    "sg:address":"10759 Rue Laverdure",
    "sg:city":"Montreal",
    "sg:classifiers":[
        {
            "category":"Shopping",
            "subcategory":"Clothing, Apparel, & Fashions",
            "type":"Retail Goods"
        }
    ],
    "sg:phone":"+1 514 388 5332",
    "sg:postcode":"H3L 2L8",
    "sg:province":"QC",
    "sg:tags":[
        "designer",
        "fur",
        "business"
    ],
    "wof:name":"Fourrures Marie-Martine Inc",
    "wof:placetype":"venue"
},
  "geometry": {"coordinates":[-73.67112,45.552532],"type":"Point"}
}