{
  "type": "Feature",
  "properties": {
    "addr:full":"Saint-Clet QC J0P 1S0",
    "addr:postcode":"j0p 1s0",
    "iso:country":"CA",
    "sg:city":"Saint-Clet",
    "sg:classifiers":[
        {
            "category":"Home & Garden",
            "subcategory":"Building Materials",
            "type":"Retail Goods"
        }
    ],
    "sg:phone":"+1 450 456 3277",
    "sg:postcode":"J0P 1S0",
    "sg:province":"QC",
    "sg:tags":[
        "windows",
        "door"
    ],
    "wof:name":"Atelier R Sabourin Inc",
    "wof:placetype":"venue"
},
  "geometry": {"coordinates":[-74.2166061401,45.3563995361],"type":"Point"}
}