{
  "type": "Feature",
  "properties": {
    "addr:full":"Almonte ON K0A 1A0",
    "addr:postcode":"k0a 1a0",
    "iso:country":"CA",
    "sg:city":"Almonte",
    "sg:classifiers":[
        {
            "category":"Health Services",
            "subcategory":"Chiropractor",
            "type":"Services"
        }
    ],
    "sg:phone":"+1 613 256 2813",
    "sg:postcode":"K0A 1A0",
    "sg:province":"ON",
    "wof:name":"Almonte Chiropractic Ctr",
    "wof:placetype":"venue"
},
  "geometry": {"coordinates":[-76.19371,45.226063],"type":"Point"}
}