{
  "type": "Feature",
  "properties": {
    "addr:full":"8495 Rue Adrien Laval QC H7A 1J9",
    "addr:housenumber":"8495",
    "addr:postcode":"h7a 1j9",
    "addr:street":"Rue Adrien",
    "iso:country":"CA",
    "sg:address":"8495 Rue Adrien",
    "sg:city":"Laval",
    "sg:classifiers":[
        {
            "category":"Health Services",
            "subcategory":"Doctor",
            "type":"Services"
        }
    ],
    "sg:phone":"+1 450 665 1702",
    "sg:postcode":"H7A 1J9",
    "sg:province":"QC",
    "sg:tags":[
        "clinic"
    ],
    "wof:name":"Clinique Medicale St-Francois",
    "wof:placetype":"venue"
},
  "geometry": {"coordinates":[-73.57740020750001,45.669418335],"type":"Point"}
}