{
  "type": "Feature",
  "properties": {
    "iso:country":"CA",
    "sg:address":"3425 Rue DE Mont-Joli",
    "sg:city":"Montreal-Nord",
    "sg:classifiers":[
        {
            "category":"Manufacturing",
            "subcategory":"Printing",
            "type":"Manufacturing & Wholesale Goods"
        }
    ],
    "sg:phone":"+1 514 321 5920",
    "sg:postcode":"H1H 2X9",
    "sg:province":"QC",
    "sg:tags":[
        "printer"
    ],
    "wof:name":"Imprimerie Contact",
    "wof:placetype":"venue"
},
  "geometry": {"coordinates":[-73.638999939,45.5788650513],"type":"Point"}
}