{
  "type": "Feature",
  "properties": {
    "addr:full":"219 Rue St-Francois Edmundston NB E3V 1G1",
    "addr:housenumber":"219",
    "addr:postcode":"e3v 1g1",
    "addr:street":"Rue St-Francois",
    "iso:country":"CA",
    "sg:address":"219 Rue St-Francois",
    "sg:city":"Edmundston",
    "sg:classifiers":[
        {
            "category":"Real Estate",
            "subcategory":"Surveying",
            "type":"Services"
        }
    ],
    "sg:phone":"+1 506 739 8831",
    "sg:postcode":"E3V 1G1",
    "sg:province":"NB",
    "sg:tags":[
        "engineer"
    ],
    "wof:name":"Arpenteurs Du Nord Ltee",
    "wof:placetype":"venue"
},
  "geometry": {"coordinates":[-68.33670806879999,47.3617591858],"type":"Point"}
}