{
  "type": "Feature",
  "properties": {
    "iso:country":"CA",
    "sg:address":"705 103 Ave",
    "sg:city":"Dawson Creek",
    "sg:classifiers":[
        {
            "category":"Banks & Credit Unions",
            "subcategory":"Bank",
            "type":"Services"
        }
    ],
    "sg:phone":"+1 250 782 1346",
    "sg:postcode":"V1G 4W8",
    "sg:province":"BC",
    "sg:tags":[
        "government"
    ],
    "wof:name":"Farm Credit Corp Canada",
    "wof:placetype":"venue"
},
  "geometry": {"coordinates":[-120.222396851,55.7560310364],"type":"Point"}
}