{
  "type": "Feature",
  "properties": {
    "addr:full":"Etobicoke ON M9V 1B4",
    "addr:postcode":"m9v 1b4",
    "iso:country":"CA",
    "sg:city":"Etobicoke",
    "sg:classifiers":[
        {
            "category":"Shopping",
            "type":"Retail Goods"
        }
    ],
    "sg:phone":"+1 416 742 0961",
    "sg:postcode":"M9V 1B4",
    "sg:province":"ON",
    "sg:tags":[
        "cosmetic",
        "perfume"
    ],
    "wof:name":"S & S Perfumes & Cosmetics",
    "wof:placetype":"venue"
},
  "geometry": {"coordinates":[-79.58191680909999,43.7400894165],"type":"Point"}
}