{
  "type": "Feature",
  "properties": {
    "iso:country":"CA",
    "sg:address":"350 Rockwood St",
    "sg:city":"Winnipeg",
    "sg:classifiers":[
        {
            "category":"Education",
            "subcategory":"School",
            "type":"Public Place"
        }
    ],
    "sg:phone":"+1 204 452 4210",
    "sg:postcode":"R3M 3C5",
    "sg:province":"MB",
    "wof:name":"Rockwood School",
    "wof:placetype":"venue"
},
  "geometry": {"coordinates":[-97.167038,49.861439],"type":"Point"}
}