{
  "type": "Feature",
  "properties": {
    "addr:full":"350 Rockwood St Winnipeg MB R3M 3C5",
    "addr:housenumber":"350",
    "addr:postcode":"r3m 3c5",
    "addr:street":"Rockwood St",
    "iso:country":"CA",
    "sg:address":"350 Rockwood St",
    "sg:city":"Winnipeg",
    "sg:classifiers":[
        {
            "category":"Education",
            "subcategory":"School",
            "type":"Public Place"
        }
    ],
    "sg:phone":"+1 204 452 4210",
    "sg:postcode":"R3M 3C5",
    "sg:province":"MB",
    "wof:name":"Rockwood School",
    "wof:placetype":"venue"
},
  "geometry": {"coordinates":[-97.16703800000001,49.861439],"type":"Point"}
}