{
  "type": "Feature",
  "properties": {
    "addr:full":"Nipawin SK S0E 1E0",
    "addr:postcode":"s0e 1e0",
    "iso:country":"CA",
    "sg:city":"Nipawin",
    "sg:classifiers":[
        {
            "category":"Real Estate",
            "subcategory":"Real Estate Operator",
            "type":"Services"
        }
    ],
    "sg:phone":"+1 306 862 4106",
    "sg:postcode":"S0E 1E0",
    "sg:province":"SK",
    "sg:tags":[
        "mall",
        "shopping",
        "center",
        "store",
        "variety"
    ],
    "wof:name":"Your Dollar Store With More",
    "wof:placetype":"venue"
},
  "geometry": {"coordinates":[-104.885353088,52.6312217712],"type":"Point"}
}