{
  "type": "Feature",
  "properties": {
    "addr:full":"121 1st Ave N Milk River AB T0K 1M0",
    "addr:housenumber":"121",
    "addr:postcode":"t0k 1m0",
    "addr:street":"1St Ave N Milk",
    "iso:country":"CA",
    "sg:address":"121 1st Ave N",
    "sg:city":"Milk River",
    "sg:classifiers":[
        {
            "category":"Retail",
            "subcategory":"Auto Repair",
            "type":"Services"
        }
    ],
    "sg:phone":"+1 403 647 3571",
    "sg:postcode":"T0K 1M0",
    "sg:province":"AB",
    "sg:tags":[
        "wrecker"
    ],
    "wof:name":"Bordertown Auto Body",
    "wof:placetype":"venue"
},
  "geometry": {"coordinates":[-112.086044312,49.1492767334],"type":"Point"}
}