{
  "type": "Feature",
  "properties": {
    "iso:country":"CA",
    "sg:address":"87 Bishop Cres",
    "sg:city":"Markham",
    "sg:classifiers":[
        {
            "category":"Retail",
            "subcategory":"Repair Shop",
            "type":"Services"
        }
    ],
    "sg:phone":"+1 905 294 9688",
    "sg:postcode":"L3P 4N5",
    "sg:province":"ON",
    "sg:tags":[
        "lock",
        "locksmith"
    ],
    "wof:name":"Allan's Lock & Door CO Ltd",
    "wof:placetype":"venue"
},
  "geometry": {"coordinates":[-79.2581329346,43.8870620728],"type":"Point"}
}