{
  "type": "Feature",
  "properties": {
    "addr:full":"421 LA Have St Bridgewater NS B4V 3A2",
    "addr:housenumber":"421",
    "addr:postcode":"b4v 3a2",
    "addr:street":"La Have St",
    "iso:country":"CA",
    "sg:address":"421 LA Have St",
    "sg:city":"Bridgewater",
    "sg:classifiers":[
        {
            "category":"Personal",
            "subcategory":"Beauty Salon",
            "type":"Services"
        }
    ],
    "sg:phone":"+1 902 543 3180",
    "sg:postcode":"B4V 3A2",
    "sg:province":"NS",
    "wof:name":"In Town Connections",
    "wof:placetype":"venue"
},
  "geometry": {"coordinates":[-64.514374,44.378021],"type":"Point"}
}