{
  "type": "Feature",
  "properties": {
    "addr:full":"5115 Rue Vezina Montreal QC H3W 1C2",
    "addr:housenumber":"5115",
    "addr:postcode":"h3w 1c2",
    "addr:street":"Rue Vezina",
    "iso:country":"CA",
    "sg:address":"5115 Rue Vezina",
    "sg:city":"Montreal",
    "sg:classifiers":[
        {
            "category":"Education",
            "subcategory":"College",
            "type":"Public Place"
        }
    ],
    "sg:phone":"+1 514 733 2221",
    "sg:postcode":"H3W 1C2",
    "sg:province":"QC",
    "sg:tags":[
        "academic",
        "school"
    ],
    "wof:name":"Bais Chaya Mushka Seminary",
    "wof:placetype":"venue"
},
  "geometry": {"coordinates":[-73.64659881590001,45.4935417175],"type":"Point"}
}