{
  "type": "Feature",
  "properties": {
    "addr:full":"666 Wilson Ave North York ON M3K 1E1",
    "addr:housenumber":"666",
    "addr:postcode":"m3k 1e1",
    "addr:street":"Wilson Ave",
    "iso:country":"CA",
    "sg:address":"666 Wilson Ave",
    "sg:city":"North York",
    "sg:classifiers":[
        {
            "category":"Professional",
            "subcategory":"Accounting & Tax Preparation",
            "type":"Services"
        }
    ],
    "sg:phone":"+1 416 633 2536",
    "sg:postcode":"M3K 1E1",
    "sg:province":"ON",
    "sg:tags":[
        "accountant"
    ],
    "wof:name":"Spiegel & Assoc",
    "wof:placetype":"venue"
},
  "geometry": {"coordinates":[-79.461502,43.731956],"type":"Point"}
}