{
  "type": "Feature",
  "properties": {
    "addr:full":"102 Hymus Rd Scarborough ON M1L 2C9",
    "addr:housenumber":"102",
    "addr:postcode":"m1l 2c9",
    "addr:street":"Hymus Rd",
    "iso:country":"CA",
    "sg:address":"102 Hymus Rd",
    "sg:city":"Scarborough",
    "sg:classifiers":[
        {
            "category":"Retail",
            "subcategory":"Repair Shop",
            "type":"Services"
        }
    ],
    "sg:phone":"+1 416 288 6575",
    "sg:postcode":"M1L 2C9",
    "sg:province":"ON",
    "sg:tags":[
        "filter"
    ],
    "wof:name":"Quick Filter Restaurant Exchng",
    "wof:placetype":"venue"
},
  "geometry": {"coordinates":[-79.2828826904,43.7200088501],"type":"Point"}
}