{
  "type": "Feature",
  "properties": {
    "addr:full":"1801 Lawrence Ave E # 1 Scarborough ON M1R 2X9",
    "addr:housenumber":"1801",
    "addr:postcode":"m1r 2x9",
    "addr:street":"Lawrence Ave E # 1",
    "iso:country":"CA",
    "sg:address":"1801 Lawrence Ave E # 1",
    "sg:city":"Scarborough",
    "sg:classifiers":[
        {
            "category":"Restaurant",
            "type":"Food & Drink"
        }
    ],
    "sg:phone":"+1 416 285 4740",
    "sg:postcode":"M1R 2X9",
    "sg:province":"ON",
    "wof:name":"Cafe Sinai & Restaurant",
    "wof:placetype":"venue"
},
  "geometry": {"coordinates":[-79.305115,43.742985],"type":"Point"}
}