{
  "type": "Feature",
  "properties": {
    "addr:full":"High Level AB T0H 1Z0",
    "addr:postcode":"t0h 1z0",
    "iso:country":"CA",
    "sg:city":"High Level",
    "sg:classifiers":[
        {
            "category":"Building & Trades",
            "subcategory":"Equipment Rental",
            "type":"Services"
        }
    ],
    "sg:phone":"+1 780 926 5558",
    "sg:postcode":"T0H 1Z0",
    "sg:province":"AB",
    "sg:tags":[
        "helicopter",
        "aircraft",
        "leasing",
        "charter"
    ],
    "wof:name":"Gemini Helicopters Inc",
    "wof:placetype":"venue"
},
  "geometry": {"coordinates":[-117.16269699999999,58.613708],"type":"Point"}
}