{
  "type": "Feature",
  "properties": {
    "addr:full":"London ON N5Y 5K7",
    "addr:postcode":"n5y 5k7",
    "iso:country":"CA",
    "sg:city":"London",
    "sg:classifiers":[
        {
            "category":"Health Services",
            "subcategory":"Doctor",
            "type":"Services"
        }
    ],
    "sg:phone":"+1 519 433 6810",
    "sg:postcode":"N5Y 5K7",
    "sg:province":"ON",
    "sg:tags":[
        "physician",
        "surgeon"
    ],
    "wof:name":"Wong, N R MD",
    "wof:placetype":"venue"
},
  "geometry": {"coordinates":[-81.2450714111,43.0153236389],"type":"Point"}
}