{
  "type": "Feature",
  "properties": {
    "iso:country":"CA",
    "sg:address":"620 17 Ave SW",
    "sg:city":"Calgary",
    "sg:classifiers":[
        {
            "category":"Home & Garden",
            "subcategory":"Furniture",
            "type":"Retail Goods"
        }
    ],
    "sg:phone":"+1 403 229 0156",
    "sg:postcode":"T2S 0B4",
    "sg:province":"AB",
    "sg:tags":[
        "carpet",
        "dealer",
        "rug"
    ],
    "wof:name":"Indo-Designers Rugs Trdng Inc",
    "wof:placetype":"venue"
},
  "geometry": {"coordinates":[-114.075638,51.037903],"type":"Point"}
}