{
  "type": "Feature",
  "properties": {
    "addr:full":"350 Rue Masson Sainte-Thecle QC G0X 3G0",
    "addr:housenumber":"350",
    "addr:postcode":"g0x 3g0",
    "addr:street":"Rue Masson Sainte-Thecle",
    "iso:country":"CA",
    "sg:address":"350 Rue Masson",
    "sg:city":"Sainte-Thecle",
    "sg:classifiers":[
        {
            "category":"Wholesale",
            "subcategory":"Meat",
            "type":"Manufacturing & Wholesale Goods"
        }
    ],
    "sg:phone":"+1 418 289 2044",
    "sg:postcode":"G0X 3G0",
    "sg:province":"QC",
    "sg:tags":[
        "butchering"
    ],
    "wof:name":"Boucherie Gagnon",
    "wof:placetype":"venue"
},
  "geometry": {"coordinates":[-72.509125,46.819386],"type":"Point"}
}