{
  "type": "Feature",
  "properties": {
    "addr:full":"Greenwood NS B0P 1N0",
    "addr:postcode":"b0p 1n0",
    "iso:country":"CA",
    "sg:city":"Greenwood",
    "sg:classifiers":[
        {
            "category":"Recreation",
            "type":"Entertainment"
        }
    ],
    "sg:phone":"+1 902 765 8165",
    "sg:postcode":"B0P 1N0",
    "sg:province":"NS",
    "sg:tags":[
        "center"
    ],
    "wof:name":"Greenwood Community Ctr",
    "wof:placetype":"venue"
},
  "geometry": {"coordinates":[-64.937775,44.969486],"type":"Point"}
}