{
  "type": "Feature",
  "properties": {
    "addr:full":"9 the Market Place East York ON M4C 5M2",
    "addr:housenumber":"9",
    "addr:postcode":"m4c 5m2",
    "addr:street":"Market Place",
    "iso:country":"CA",
    "sg:address":"9 the Market Place",
    "sg:city":"East York",
    "sg:classifiers":[
        {
            "category":"Health Services",
            "subcategory":"Doctor",
            "type":"Services"
        }
    ],
    "sg:phone":"+1 416 691 9767",
    "sg:postcode":"M4C 5M2",
    "sg:province":"ON",
    "sg:tags":[
        "dentist"
    ],
    "wof:name":"Ward, Richard S DDS",
    "wof:placetype":"venue"
},
  "geometry": {"coordinates":[-79.29289245610001,43.6952209473],"type":"Point"}
}