{
  "type": "Feature",
  "properties": {
    "addr:full":"415 Mackenzie Ave Ajax ON L1S 2G2",
    "addr:housenumber":"415",
    "addr:postcode":"l1s 2g2",
    "addr:street":"Mackenzie Ave",
    "iso:country":"CA",
    "sg:address":"415 Mackenzie Ave",
    "sg:city":"Ajax",
    "sg:classifiers":[
        {
            "category":"Manufacturing",
            "subcategory":"Metals",
            "type":"Manufacturing & Wholesale Goods"
        }
    ],
    "sg:phone":"+1 905 427 3770",
    "sg:postcode":"L1S 2G2",
    "sg:province":"ON",
    "sg:tags":[
        "steel"
    ],
    "wof:name":"R & D Fabricating Consultant",
    "wof:placetype":"venue"
},
  "geometry": {"coordinates":[-79.026794,43.839233],"type":"Point"}
}