{
  "type": "Feature",
  "properties": {
    "addr:full":"4011 49th Ave Pouce Coupe BC V0C 2C0",
    "addr:housenumber":"4011",
    "addr:postcode":"bc v0c 2c0",
    "addr:street":"49Th Ave",
    "iso:country":"CA",
    "sg:address":"4011 49th Ave",
    "sg:city":"Pouce Coupe",
    "sg:classifiers":[
        {
            "category":"Government",
            "subcategory":"Office",
            "type":"Public Place"
        }
    ],
    "sg:phone":"+1 250 786 5794",
    "sg:postcode":"V0C 2C0",
    "sg:province":"BC",
    "sg:tags":[
        "village"
    ],
    "wof:name":"Village of Pouce Coupe",
    "wof:placetype":"venue"
},
  "geometry": {"coordinates":[-120.138847,55.714951],"type":"Point"}
}