{
  "type": "Feature",
  "properties": {
    "addr:full":"44 Maple Valley Rd Corner Brook NL A2H 6L8",
    "addr:housenumber":"44",
    "addr:postcode":"a2h 6l8",
    "addr:street":"Maple Valley Rd",
    "iso:country":"CA",
    "sg:address":"44 Maple Valley Rd",
    "sg:city":"Corner Brook",
    "sg:classifiers":[
        {
            "category":"Shopping",
            "subcategory":"Clothing, Apparel, & Fashions",
            "type":"Retail Goods"
        }
    ],
    "sg:phone":"+1 709 634 3443",
    "sg:postcode":"A2H 6L8",
    "sg:province":"NL",
    "wof:name":"Garage",
    "wof:placetype":"venue"
},
  "geometry": {"coordinates":[-57.916546,48.948753],"type":"Point"}
}