{
  "type": "Feature",
  "properties": {
    "addr:full":"16 Suffield Crt Quispamsis NB E2E 2S5",
    "addr:housenumber":"16",
    "addr:postcode":"e2e 2s5",
    "addr:street":"Suffield Crt",
    "iso:country":"CA",
    "sg:address":"16 Suffield Crt",
    "sg:city":"Quispamsis",
    "sg:classifiers":[
        {
            "category":"Building & Trades",
            "subcategory":"Construction",
            "type":"Services"
        }
    ],
    "sg:phone":"+1 506 847 5904",
    "sg:postcode":"E2E 2S5",
    "sg:province":"NB",
    "sg:tags":[
        "excavating",
        "contractor"
    ],
    "wof:name":"M J Cote Backhoeing",
    "wof:placetype":"venue"
},
  "geometry": {"coordinates":[-65.9859161377,45.4215354919],"type":"Point"}
}