{
  "type": "Feature",
  "properties": {
    "addr:full":"1909 10 Ave SW #200 Calgary AB T3C 0K3",
    "addr:housenumber":"1909",
    "addr:postcode":"t3c 0k3",
    "addr:street":"10 Ave Sw # 200",
    "iso:country":"CA",
    "sg:address":"1909 10 Ave SW #200",
    "sg:city":"Calgary",
    "sg:classifiers":[
        {
            "category":"Real Estate",
            "subcategory":"Architect",
            "type":"Services"
        }
    ],
    "sg:phone":"+1 403 244 8818",
    "sg:postcode":"T3C 0K3",
    "sg:province":"AB",
    "wof:name":"Arup Datta Architect Ltd",
    "wof:placetype":"venue"
},
  "geometry": {"coordinates":[-114.104485,51.044338],"type":"Point"}
}