{
  "type": "Feature",
  "properties": {
    "addr:full":"510 Trans Canada Hwy Hope BC V0X 1L0",
    "addr:housenumber":"510",
    "addr:postcode":"v0x 1l0",
    "addr:street":"Trans Canada Hwy",
    "iso:country":"CA",
    "sg:address":"510 Trans Canada Hwy",
    "sg:city":"Hope",
    "sg:classifiers":[
        {
            "category":"Travel",
            "subcategory":"Hotels & Motels",
            "type":"Entertainment"
        }
    ],
    "sg:phone":"+1 604 869 7276",
    "sg:postcode":"V0X 1L0",
    "sg:province":"BC",
    "sg:tags":[
        "resort"
    ],
    "wof:name":"Inn Towne Motel",
    "wof:placetype":"venue"
},
  "geometry": {"coordinates":[-121.50042000000001,49.363068],"type":"Point"}
}