{
  "type": "Feature",
  "properties": {
    "iso:country":"CA",
    "sg:address":"387 Elizabeth St",
    "sg:city":"Grimsby",
    "sg:classifiers":[
        {
            "category":"Shopping",
            "subcategory":"Gifts & Souvenirs",
            "type":"Retail Goods"
        }
    ],
    "sg:phone":"+1 905 945 5795",
    "sg:postcode":"L3M 3K6",
    "sg:province":"ON",
    "sg:tags":[
        "shop",
        "glass"
    ],
    "wof:name":"Catch the Sun Stained Glass",
    "wof:placetype":"venue"
},
  "geometry": {"coordinates":[-79.557693,43.200138],"type":"Point"}
}