{
  "type": "Feature",
  "properties": {
    "addr:full":"33 Church St Westport ON K0G 1X0",
    "addr:housenumber":"33",
    "addr:postcode":"k0g 1x0",
    "addr:street":"Church St",
    "iso:country":"CA",
    "sg:address":"33 Church St",
    "sg:city":"Westport",
    "sg:classifiers":[
        {
            "category":"Retail",
            "subcategory":"Repair Shop",
            "type":"Services"
        }
    ],
    "sg:phone":"+1 613 273 3665",
    "sg:postcode":"K0G 1X0",
    "sg:province":"ON",
    "sg:tags":[
        "upholsterer"
    ],
    "wof:name":"Upholstery Shoppe",
    "wof:placetype":"venue"
},
  "geometry": {"coordinates":[-76.39636230470001,44.677646637],"type":"Point"}
}