{
  "type": "Feature",
  "properties": {
    "addr:full":"1277 10 Rg Wickham QC J0C 1S0",
    "addr:housenumber":"1277",
    "addr:postcode":"j0c 1s0",
    "addr:street":"10 Rg",
    "iso:country":"CA",
    "sg:address":"1277 10 Rg",
    "sg:city":"Wickham",
    "sg:classifiers":[
        {
            "category":"Building & Trades",
            "subcategory":"Construction",
            "type":"Services"
        }
    ],
    "sg:phone":"+1 819 398 6831",
    "sg:postcode":"J0C 1S0",
    "sg:province":"QC",
    "sg:tags":[
        "road",
        "contractor"
    ],
    "wof:name":"Lacbec Inc",
    "wof:placetype":"venue"
},
  "geometry": {"coordinates":[-72.498901,45.759651],"type":"Point"}
}