{
  "type": "Feature",
  "properties": {
    "addr:full":"1580 Highway 33 W Kelowna BC V1X 1Z9",
    "addr:housenumber":"1580",
    "addr:postcode":"v1x 1z9",
    "addr:street":"Highway 33 W",
    "iso:country":"CA",
    "sg:address":"1580 Highway 33 W",
    "sg:city":"Kelowna",
    "sg:classifiers":[
        {
            "category":"Travel",
            "subcategory":"Hotels & Motels",
            "type":"Entertainment"
        }
    ],
    "sg:phone":"+1 250 860 5707",
    "sg:postcode":"V1X 1Z9",
    "sg:province":"BC",
    "sg:tags":[
        "breakfast",
        "accommodation",
        "bed"
    ],
    "wof:name":"Okanagan Seasons Resort",
    "wof:placetype":"venue"
},
  "geometry": {"coordinates":[-119.49659729,49.8868141174],"type":"Point"}
}