{
  "type": "Feature",
  "properties": {
    "addr:full":"300 Taunton Rd E Oshawa ON L1G 7T4",
    "addr:housenumber":"300",
    "addr:postcode":"l1g 7t4",
    "addr:street":"Taunton Rd E",
    "iso:country":"CA",
    "sg:address":"300 Taunton Rd E",
    "sg:city":"Oshawa",
    "sg:classifiers":[
        {
            "category":"Shopping",
            "subcategory":"Hobbies, Toys, & Games",
            "type":"Retail Goods"
        }
    ],
    "sg:phone":"+1 905 723 8759",
    "sg:postcode":"L1G 7T4",
    "sg:province":"ON",
    "sg:tags":[
        "model",
        "supply"
    ],
    "wof:name":"Hobby Stuff",
    "wof:placetype":"venue"
},
  "geometry": {"coordinates":[-78.86735534669999,43.9356880188],"type":"Point"}
}