{
  "type": "Feature",
  "properties": {
    "addr:full":"1582 97th St North Battleford SK S9A 0K4",
    "addr:housenumber":"1582",
    "addr:postcode":"s9a 0k4",
    "addr:street":"97Th St",
    "iso:country":"CA",
    "sg:address":"1582 97th St",
    "sg:city":"North Battleford",
    "sg:classifiers":[
        {
            "category":"Retail",
            "subcategory":"Repair Shop",
            "type":"Services"
        }
    ],
    "sg:phone":"+1 306 445 9787",
    "sg:postcode":"S9A 0K4",
    "sg:province":"SK",
    "sg:tags":[
        "sharpening"
    ],
    "wof:name":"Con's Sharpening",
    "wof:placetype":"venue"
},
  "geometry": {"coordinates":[-108.303268,52.780811],"type":"Point"}
}