{
  "type": "Feature",
  "properties": {
    "addr:full":"Blainville QC J7C 2L9",
    "addr:postcode":"j7c 2l9",
    "iso:country":"CA",
    "sg:city":"Blainville",
    "sg:classifiers":[
        {
            "category":"Shopping",
            "subcategory":"Computers & Home Electronics",
            "type":"Retail Goods"
        }
    ],
    "sg:phone":"+1 450 435 3142",
    "sg:postcode":"J7C 2L9",
    "sg:province":"QC",
    "sg:tags":[
        "equipment",
        "dealer"
    ],
    "wof:name":"Electronique & Info Ethier",
    "wof:placetype":"venue"
},
  "geometry": {"coordinates":[-73.8810577393,45.6743507385],"type":"Point"}
}