{
  "type": "Feature",
  "properties": {
    "addr:full":"416 Rue Principale Saint-Marc-Du-Lac-Long QC G0L 1T0",
    "addr:housenumber":"416",
    "addr:postcode":"g0l 1t0",
    "addr:street":"Rue Principale",
    "iso:country":"CA",
    "sg:address":"416 Rue Principale",
    "sg:city":"Saint-Marc-Du-Lac-Long",
    "sg:classifiers":[
        {
            "category":"Food & Beverages",
            "subcategory":"Groceries & Convenience Stores",
            "type":"Retail Goods"
        }
    ],
    "sg:phone":"+1 418 893 5659",
    "sg:postcode":"G0L 1T0",
    "sg:province":"QC",
    "sg:tags":[
        "grocer"
    ],
    "wof:name":"Epicerie Du Coin",
    "wof:placetype":"venue"
},
  "geometry": {"coordinates":[-68.89727000000001,47.389763],"type":"Point"}
}