{
  "type": "Feature",
  "properties": {
    "addr:full":"342 Grafton St Charlottetown PE C1A 1L8",
    "addr:housenumber":"342",
    "addr:postcode":"c1a 1l8",
    "addr:street":"Grafton St",
    "iso:country":"CA",
    "sg:address":"342 Grafton St",
    "sg:city":"Charlottetown",
    "sg:classifiers":[
        {
            "category":"Health Services",
            "subcategory":"Doctor",
            "type":"Services"
        }
    ],
    "sg:phone":"+1 902 892 7600",
    "sg:postcode":"C1A 1L8",
    "sg:province":"PE",
    "sg:tags":[
        "dentist"
    ],
    "wof:name":"Gregory A Mitton Inc",
    "wof:placetype":"venue"
},
  "geometry": {"coordinates":[-63.1192321777,46.2398796082],"type":"Point"}
}