{
  "type": "Feature",
  "properties": {
    "addr:full":"805 Meech Lake Rd Chelsea QC J9B 1H9",
    "addr:housenumber":"805",
    "addr:postcode":"qc j9b 1h9",
    "addr:street":"Meech Lake Rd",
    "iso:country":"CA",
    "sg:address":"805 Meech Lake Rd",
    "sg:city":"Chelsea",
    "sg:classifiers":[
        {
            "category":"Real Estate",
            "subcategory":"Real Estate Agent",
            "type":"Services"
        }
    ],
    "sg:phone":"+1 819 827 0898",
    "sg:postcode":"J9B 1H9",
    "sg:province":"QC",
    "sg:tags":[
        "inspection"
    ],
    "wof:name":"Chelsea Home Inspections",
    "wof:placetype":"venue"
},
  "geometry": {"coordinates":[-75.804382,45.526974],"type":"Point"}
}