{
  "type": "Feature",
  "properties": {
    "addr:full":"2507 Broadway W Vancouver BC V6K 2E9",
    "addr:housenumber":"2507",
    "addr:postcode":"v6k 2e9",
    "addr:street":"Broadway W",
    "iso:country":"CA",
    "sg:address":"2507 Broadway W",
    "sg:city":"Vancouver",
    "sg:classifiers":[
        {
            "category":"Restaurant",
            "type":"Food & Drink"
        }
    ],
    "sg:phone":"+1 604 739 0005",
    "sg:postcode":"V6K 2E9",
    "sg:province":"BC",
    "wof:name":"Moderne Burger",
    "wof:placetype":"venue"
},
  "geometry": {"coordinates":[-123.162597656,49.2641448975],"type":"Point"}
}