{
  "type": "Feature",
  "properties": {
    "addr:full":"255 S Cooper Greenwood BC V0H 1J0",
    "addr:housenumber":"255",
    "addr:postcode":"v0h 1j0",
    "addr:street":"S Cooper",
    "iso:country":"CA",
    "sg:address":"255 S Cooper",
    "sg:city":"Greenwood",
    "sg:classifiers":[
        {
            "category":"Organizations",
            "subcategory":"Professional Association",
            "type":"Services"
        }
    ],
    "sg:phone":"+1 250 445 2333",
    "sg:postcode":"V0H 1J0",
    "sg:province":"BC",
    "wof:name":"Boundary Citizen's Patrol",
    "wof:placetype":"venue"
},
  "geometry": {"coordinates":[-118.67765045199999,49.0936775208],"type":"Point"}
}