{
  "type": "Feature",
  "properties": {
    "addr:full":"Hunter River PE C0A 1N0",
    "addr:postcode":"c0a 1n0",
    "iso:country":"CA",
    "sg:city":"Hunter River",
    "sg:classifiers":[
        {
            "category":"Organizations",
            "subcategory":"Professional Association",
            "type":"Services"
        }
    ],
    "sg:phone":"+1 902 963 3252",
    "sg:postcode":"C0A 1N0",
    "sg:province":"PE",
    "sg:tags":[
        "club"
    ],
    "wof:name":"Conseil Acadien DE Rustico",
    "wof:placetype":"venue"
},
  "geometry": {"coordinates":[-63.343147,46.351761],"type":"Point"}
}