{
  "type": "Feature",
  "properties": {
    "addr:full":"Wetaskiwin AB T9A 2E8",
    "addr:postcode":"t9a 2e8",
    "iso:country":"CA",
    "sg:city":"Wetaskiwin",
    "sg:classifiers":[
        {
            "category":"Farming",
            "subcategory":"Farm & Veterinary Services",
            "type":"Manufacturing & Wholesale Goods"
        }
    ],
    "sg:phone":"+1 780 352 7833",
    "sg:postcode":"T9A 2E8",
    "sg:province":"AB",
    "sg:tags":[
        "aerial",
        "applicator"
    ],
    "wof:name":"Wetaskiwin Aerial Applicators",
    "wof:placetype":"venue"
},
  "geometry": {"coordinates":[-113.37724300000001,52.96991],"type":"Point"}
}