{
  "type": "Feature",
  "properties": {
    "iso:country":"CA",
    "sg:address":"100 Artesian Industrial Pky",
    "sg:city":"Bradford",
    "sg:classifiers":[
        {
            "category":"Manufacturing",
            "subcategory":"Electronics",
            "type":"Manufacturing & Wholesale Goods"
        }
    ],
    "sg:phone":"+1 905 775 0590",
    "sg:postcode":"L3Z 3G3",
    "sg:province":"ON",
    "sg:tags":[
        "signal",
        "traffic",
        "sign"
    ],
    "wof:name":"Advance Warning Inc",
    "wof:placetype":"venue"
},
  "geometry": {"coordinates":[-79.55558776860001,44.1332511902],"type":"Point"}
}