{
  "type": "Feature",
  "properties": {
    "addr:full":"Wilsonville ON N0E 1Z0",
    "addr:postcode":"n0e 1z0",
    "iso:country":"CA",
    "sg:city":"Wilsonville",
    "sg:classifiers":[
        {
            "category":"Autos & Motor Vehicles",
            "subcategory":"Automobile Sales",
            "type":"Retail Goods"
        }
    ],
    "sg:phone":"+1 519 445 2545",
    "sg:postcode":"N0E 1Z0",
    "sg:province":"ON",
    "sg:tags":[
        "car",
        "dealer"
    ],
    "wof:name":"Jay & S Auto Sales",
    "wof:placetype":"venue"
},
  "geometry": {"coordinates":[-80.31768035890001,42.9954147339],"type":"Point"}
}