{
  "type": "Feature",
  "properties": {
    "addr:full":"30 Broadview Ave Saint John NB E2L 5E8",
    "addr:housenumber":"30",
    "addr:postcode":"e2l 5e8",
    "addr:street":"Broadview Ave",
    "iso:country":"CA",
    "sg:address":"30 Broadview Ave",
    "sg:city":"Saint John",
    "sg:classifiers":[
        {
            "category":"Shopping",
            "subcategory":"Computers & Home Electronics",
            "type":"Retail Goods"
        }
    ],
    "sg:phone":"+1 506 632 6484",
    "sg:postcode":"E2L 5E8",
    "sg:province":"NB",
    "sg:tags":[
        "equipment",
        "training",
        "dealer",
        "consultant"
    ],
    "wof:name":"X Wave Solutions",
    "wof:placetype":"venue"
},
  "geometry": {"coordinates":[-66.055351,45.264603],"type":"Point"}
}