{
  "type": "Feature",
  "properties": {
    "addr:full":"45 Division St N Kingsville ON N9Y 1E1",
    "addr:housenumber":"45",
    "addr:postcode":"n9y 1e1",
    "addr:street":"Division St N",
    "iso:country":"CA",
    "sg:address":"45 Division St N",
    "sg:city":"Kingsville",
    "sg:classifiers":[
        {
            "category":"Professional",
            "subcategory":"Engineering",
            "type":"Services"
        }
    ],
    "sg:phone":"+1 519 733 6587",
    "sg:postcode":"N9Y 1E1",
    "sg:province":"ON",
    "sg:tags":[
        "engineer"
    ],
    "wof:name":"N J Peralta Engineering Ltd",
    "wof:placetype":"venue"
},
  "geometry": {"coordinates":[-82.7393112183,42.0393791199],"type":"Point"}
}