{
  "type": "Feature",
  "properties": {
    "iso:country":"CA",
    "sg:address":"73561 London Rd",
    "sg:city":"Kippen",
    "sg:classifiers":[
        {
            "category":"Home & Garden",
            "subcategory":"Furniture",
            "type":"Retail Goods"
        }
    ],
    "sg:phone":"+1 519 263 5222",
    "sg:postcode":"N0M 2E0",
    "sg:province":"ON",
    "wof:name":"Baker, Terry",
    "wof:placetype":"venue"
},
  "geometry": {"coordinates":[-81.5057601929,43.4700508118],"type":"Point"}
}