{
  "type": "Feature",
  "properties": {
    "addr:full":"2440 Finch Ave W North York ON M9M 2E1",
    "addr:housenumber":"2440",
    "addr:postcode":"m9m 2e1",
    "addr:street":"Finch Ave W",
    "iso:country":"CA",
    "sg:address":"2440 Finch Ave W",
    "sg:city":"North York",
    "sg:classifiers":[
        {
            "category":"Restaurant",
            "type":"Food & Drink"
        }
    ],
    "sg:phone":"+1 416 746 8868",
    "sg:postcode":"M9M 2E1",
    "sg:province":"ON",
    "wof:name":"Thai Royal Orchid Restaurant",
    "wof:placetype":"venue"
},
  "geometry": {"coordinates":[-79.551773,43.75021],"type":"Point"}
}