{
  "type": "Feature",
  "properties": {
    "addr:full":"Kamsack SK S0A 1S0",
    "addr:postcode":"s0a 1s0",
    "addr:street":"Kamsack",
    "iso:country":"CA",
    "sg:city":"Kamsack",
    "sg:classifiers":[
        {
            "category":"Manufacturing",
            "subcategory":"Chemicals & Compounds",
            "type":"Manufacturing & Wholesale Goods"
        }
    ],
    "sg:phone":"+1 306 542 2439",
    "sg:postcode":"S0A 1S0",
    "sg:province":"SK",
    "sg:tags":[
        "biological",
        "product"
    ],
    "wof:name":"Enquce Biochemicals",
    "wof:placetype":"venue"
},
  "geometry": {"coordinates":[-101.89865112299999,51.5649604797],"type":"Point"}
}