{
  "type": "Feature",
  "properties": {
    "addr:full":"Dorval QC H9S 2B6",
    "addr:postcode":"h9s 2b6",
    "iso:country":"CA",
    "sg:city":"Dorval",
    "sg:classifiers":[
        {
            "category":"Health Services",
            "subcategory":"Doctor",
            "type":"Services"
        }
    ],
    "sg:phone":"+1 514 631 6422",
    "sg:postcode":"H9S 2B6",
    "sg:province":"QC",
    "sg:tags":[
        "physician",
        "surgeon"
    ],
    "wof:name":"Rajakumar, Chellappa MD",
    "wof:placetype":"venue"
},
  "geometry": {"coordinates":[-73.7350692749,45.4399795532],"type":"Point"}
}