{
  "type": "Feature",
  "properties": {
    "iso:country":"CA",
    "sg:address":"312 Commissioners Rd W",
    "sg:city":"London",
    "sg:classifiers":[
        {
            "category":"Bars & Pubs",
            "type":"Food & Drink"
        }
    ],
    "sg:phone":"+1 519 472 9455",
    "sg:postcode":"N6J 1Y3",
    "sg:province":"ON",
    "wof:name":"Kubby's Draft Bar & Grill",
    "wof:placetype":"venue"
},
  "geometry": {"coordinates":[-81.2765960693,42.9559631348],"type":"Point"}
}