{
  "type": "Feature",
  "properties": {
    "addr:full":"Brossard QC J4Y 2R2",
    "addr:postcode":"j4y 2r2",
    "iso:country":"CA",
    "sg:city":"Brossard",
    "sg:classifiers":[
        {
            "category":"Building & Trades",
            "subcategory":"Electrical",
            "type":"Services"
        }
    ],
    "sg:phone":"+1 450 444 7444",
    "sg:postcode":"J4Y 2R2",
    "sg:province":"QC",
    "sg:tags":[
        "electric",
        "contractor"
    ],
    "wof:name":"Goupil & Fils Inc",
    "wof:placetype":"venue"
},
  "geometry": {"coordinates":[-73.4687347412,45.4279556274],"type":"Point"}
}