{
  "type": "Feature",
  "properties": {
    "addr:full":"600 Queens Quay W #103 Toronto ON M5V 3M3",
    "addr:housenumber":"600",
    "addr:postcode":"m5v 3m3",
    "addr:street":"Queens Quay W # 103",
    "iso:country":"CA",
    "sg:address":"600 Queens Quay W #103",
    "sg:city":"Toronto",
    "sg:classifiers":[
        {
            "category":"Recreation",
            "subcategory":"Marina",
            "type":"Entertainment"
        }
    ],
    "sg:phone":"+1 416 364 3244",
    "sg:postcode":"M5V 3M3",
    "sg:province":"ON",
    "sg:tags":[
        "repairing",
        "boat"
    ],
    "wof:name":"Toronto Drydock",
    "wof:placetype":"venue"
},
  "geometry": {"coordinates":[-79.39785766599999,43.6363220215],"type":"Point"}
}