{
  "type": "Feature",
  "properties": {
    "addr:full":"185 Mcarthur Ave Vanier ON K1L 6P6",
    "addr:housenumber":"185",
    "addr:postcode":"k1l 6p6",
    "addr:street":"Mcarthur Ave",
    "iso:country":"CA",
    "sg:address":"185 Mcarthur Ave",
    "sg:city":"Vanier",
    "sg:classifiers":[
        {
            "category":"Home & Garden",
            "subcategory":"Carpets & Floor Coverings",
            "type":"Retail Goods"
        }
    ],
    "sg:phone":"+1 613 745 6680",
    "sg:postcode":"K1L 6P6",
    "sg:province":"ON",
    "sg:tags":[
        "material",
        "dealer",
        "rug"
    ],
    "wof:name":"Tapis Rozon Carpet Inc",
    "wof:placetype":"venue"
},
  "geometry": {"coordinates":[-75.662125,45.431309],"type":"Point"}
}