{
  "type": "Feature",
  "properties": {
    "addr:full":"PO Box 2081 STN Main Whitecourt AB T7S 1P7",
    "addr:housenumber":"po",
    "addr:postcode":"t7s 1p7",
    "addr:street":"Box 2081 Stn Main",
    "iso:country":"CA",
    "sg:address":"PO Box 2081 STN Main",
    "sg:city":"Whitecourt",
    "sg:classifiers":[
        {
            "category":"Building & Trades",
            "subcategory":"Construction",
            "type":"Services"
        }
    ],
    "sg:phone":"+1 780 778 3679",
    "sg:postcode":"T7S 1P7",
    "sg:province":"AB",
    "sg:tags":[
        "road",
        "contractor"
    ],
    "wof:name":"D Ash Grading Ltd",
    "wof:placetype":"venue"
},
  "geometry": {"coordinates":[-115.70787799999999,54.139435],"type":"Point"}
}