{
  "type": "Feature",
  "properties": {
    "addr:full":"12 Taylor Close SE Medicine Hat AB T1B 4B4",
    "addr:housenumber":"12",
    "addr:postcode":"t1b 4b4",
    "addr:street":"Taylor Close Se",
    "iso:country":"CA",
    "sg:address":"12 Taylor Close SE",
    "sg:city":"Medicine Hat",
    "sg:classifiers":[
        {
            "category":"Building & Trades",
            "subcategory":"Construction",
            "type":"Services"
        }
    ],
    "sg:phone":"+1 403 548 4433",
    "sg:postcode":"T1B 4B4",
    "sg:province":"AB",
    "sg:tags":[
        "repair",
        "material",
        "cleaning",
        "restoration",
        "concrete"
    ],
    "wof:name":"Creative Curb & Concrete",
    "wof:placetype":"venue"
},
  "geometry": {"coordinates":[-110.62818900000001,49.992599],"type":"Point"}
}