{
  "type": "Feature",
  "properties": {
    "addr:full":"5339 2 St SW Calgary AB T2H 0G8",
    "addr:housenumber":"5339 2",
    "addr:postcode":"t2h 0g8",
    "addr:street":"St Sw",
    "iso:country":"CA",
    "sg:address":"5339 2 St SW",
    "sg:city":"Calgary",
    "sg:classifiers":[
        {
            "category":"Shopping",
            "subcategory":"Shoes",
            "type":"Retail Goods"
        }
    ],
    "sg:phone":"+1 403 252 2212",
    "sg:postcode":"T2H 0G8",
    "sg:province":"AB",
    "sg:tags":[
        "repairing",
        "boot",
        "shoe"
    ],
    "wof:name":"Stampede Boot CO & Shoe Repair",
    "wof:placetype":"venue"
},
  "geometry": {"coordinates":[-114.06883999999999,51.006481],"type":"Point"}
}