{
  "type": "Feature",
  "properties": {
    "iso:country":"CA",
    "sg:address":"3660 Glenora Rd",
    "sg:city":"Duncan",
    "sg:classifiers":[
        {
            "category":"Recreation",
            "type":"Entertainment"
        }
    ],
    "sg:phone":"+1 250 746 6741",
    "sg:postcode":"V9L 6S3",
    "sg:province":"BC",
    "sg:tags":[
        "hall",
        "auditorium"
    ],
    "wof:name":"Glenora Community Assn",
    "wof:placetype":"venue"
},
  "geometry": {"coordinates":[-123.70738220200001,48.779094696],"type":"Point"}
}