{
  "type": "Feature",
  "properties": {
    "iso:country":"CA",
    "sg:address":"380 Brunel Rd",
    "sg:city":"Mississauga",
    "sg:classifiers":[
        {
            "category":"Shopping",
            "subcategory":"Clothing, Apparel, & Fashions",
            "type":"Retail Goods"
        }
    ],
    "sg:phone":"+1 905 890 2430",
    "sg:postcode":"L4Z 2C2",
    "sg:province":"ON",
    "wof:name":"Tall Girl Shop Ltd",
    "wof:placetype":"venue"
},
  "geometry": {"coordinates":[-79.667198,43.630962],"type":"Point"}
}