{
  "type": "Feature",
  "properties": {
    "addr:full":"64 Rue Alexandre Sherbrooke QC J1H 4S6",
    "addr:housenumber":"64",
    "addr:postcode":"j1h 4s6",
    "addr:street":"Rue Alexandre",
    "iso:country":"CA",
    "sg:address":"64 Rue Alexandre",
    "sg:city":"Sherbrooke",
    "sg:classifiers":[
        {
            "category":"Professional",
            "subcategory":"Business Services",
            "type":"Services"
        }
    ],
    "sg:phone":"+1 819 569 8065",
    "sg:postcode":"J1H 4S6",
    "sg:province":"QC",
    "sg:tags":[
        "inventory"
    ],
    "wof:name":"Inventaires DE L'Est Inc",
    "wof:placetype":"venue"
},
  "geometry": {"coordinates":[-71.8933334351,45.3988571167],"type":"Point"}
}