{
  "type": "Feature",
  "properties": {
    "iso:country":"CA",
    "sg:city":"Ottawa",
    "sg:classifiers":[
        {
            "category":"Social Services",
            "type":"Services"
        }
    ],
    "sg:phone":"+1 613 563 4400",
    "sg:postcode":"K2P 0Z8",
    "sg:province":"ON",
    "sg:tags":[
        "counselor",
        "marriage",
        "family"
    ],
    "wof:name":"Dalfen, Susannah",
    "wof:placetype":"venue"
},
  "geometry": {"coordinates":[-75.688766,45.413528],"type":"Point"}
}