{
  "type": "Feature",
  "properties": {
    "addr:full":"555 Rue DE L'Accueil Chesterville QC G0P 1J0",
    "addr:housenumber":"555",
    "addr:postcode":"g0p 1j0",
    "addr:street":"Rue De L'Accueil",
    "iso:country":"CA",
    "sg:address":"555 Rue DE L'Accueil",
    "sg:city":"Chesterville",
    "sg:classifiers":[
        {
            "category":"Wholesale",
            "subcategory":"Farm Supplies",
            "type":"Manufacturing & Wholesale Goods"
        }
    ],
    "sg:phone":"+1 819 382 2451",
    "sg:postcode":"G0P 1J0",
    "sg:province":"QC",
    "sg:tags":[
        "grain"
    ],
    "wof:name":"Cooperative Agricole Pre-Vert",
    "wof:placetype":"venue"
},
  "geometry": {"coordinates":[-71.842552,45.965618],"type":"Point"}
}