{
  "type": "Feature",
  "properties": {
    "iso:country":"CA",
    "sg:address":"2475 Rue Alexandra",
    "sg:city":"Beauport",
    "sg:classifiers":[
        {
            "category":"Organizations",
            "subcategory":"Religious Organization",
            "type":"Services"
        }
    ],
    "sg:phone":"+1 418 666 7636",
    "sg:postcode":"G1E 7A8",
    "sg:province":"QC",
    "sg:tags":[
        "home",
        "retirement",
        "community",
        "retreat",
        "house"
    ],
    "wof:name":"Place Alexandra",
    "wof:placetype":"venue"
},
  "geometry": {"coordinates":[-71.231354,46.851143],"type":"Point"}
}