{
  "type": "Feature",
  "properties": {
    "addr:full":"7091 Boul Newman Lasalle QC H8N 1X1",
    "addr:housenumber":"7091",
    "addr:postcode":"h8n 1x1",
    "addr:street":"Boul Newman",
    "iso:country":"CA",
    "sg:address":"7091 Boul Newman",
    "sg:city":"Lasalle",
    "sg:classifiers":[
        {
            "category":"Personal",
            "subcategory":"Beauty Salon",
            "type":"Services"
        }
    ],
    "sg:phone":"+1 514 368 0597",
    "sg:postcode":"H8N 1X1",
    "sg:province":"QC",
    "wof:name":"Magicuts",
    "wof:placetype":"venue"
},
  "geometry": {"coordinates":[-73.612663269,45.4457168579],"type":"Point"}
}