{
  "type": "Feature",
  "properties": {
    "iso:country":"CA",
    "sg:address":"1188 Rockingham Ave",
    "sg:city":"Ottawa",
    "sg:classifiers":[
        {
            "category":"Retail",
            "subcategory":"Auto Repair",
            "type":"Services"
        }
    ],
    "sg:phone":"+1 613 733 9180",
    "sg:postcode":"K1H 8A7",
    "sg:province":"ON",
    "sg:tags":[
        "body",
        "automobile",
        "painting"
    ],
    "wof:name":"Bobby's Auto Collision",
    "wof:placetype":"venue"
},
  "geometry": {"coordinates":[-75.67180633540001,45.3825798035],"type":"Point"}
}