{
  "type": "Feature",
  "properties": {
    "iso:country":"CA",
    "sg:address":"1899 Boul Edouard",
    "sg:city":"Saint-Hubert",
    "sg:classifiers":[
        {
            "category":"Personal",
            "subcategory":"Beauty Salon",
            "type":"Services"
        }
    ],
    "sg:phone":"+1 450 671 3434",
    "sg:postcode":"J4T 1Z3",
    "sg:province":"QC",
    "wof:name":"Elite Sante Beaute",
    "wof:placetype":"venue"
},
  "geometry": {"coordinates":[-73.47677612299999,45.4990730286],"type":"Point"}
}