{
  "type": "Feature",
  "properties": {
    "addr:full":"437 Signet Dr North York ON M9L 1V5",
    "addr:housenumber":"437",
    "addr:postcode":"m9l 1v5",
    "addr:street":"Signet Dr",
    "iso:country":"CA",
    "sg:address":"437 Signet Dr",
    "sg:city":"North York",
    "sg:classifiers":[
        {
            "category":"Retail",
            "subcategory":"Auto Repair",
            "type":"Services"
        }
    ],
    "sg:phone":"+1 416 741 2877",
    "sg:postcode":"M9L 1V5",
    "sg:province":"ON",
    "sg:tags":[
        "repairing",
        "automobile"
    ],
    "wof:name":"Larry's Automotive Svc",
    "wof:placetype":"venue"
},
  "geometry": {"coordinates":[-79.5424118042,43.7691497803],"type":"Point"}
}