{
  "type": "Feature",
  "properties": {
    "addr:full":"Burlington ON L7L 4X8",
    "addr:postcode":"l7l 4x8",
    "iso:country":"CA",
    "sg:city":"Burlington",
    "sg:classifiers":[
        {
            "category":"Organizations",
            "subcategory":"Professional Association",
            "type":"Services"
        }
    ],
    "sg:phone":"+1 905 631 0211",
    "sg:postcode":"L7L 4X8",
    "sg:province":"ON",
    "wof:name":"Burlington Organized Minor",
    "wof:placetype":"venue"
},
  "geometry": {"coordinates":[-79.78183,43.365944],"type":"Point"}
}