{
  "type": "Feature",
  "properties": {
    "iso:country":"CA",
    "sg:address":"397 Route 530",
    "sg:city":"Grande-Digue",
    "sg:classifiers":[
        {
            "category":"Government",
            "subcategory":"Post Office",
            "type":"Public Place"
        }
    ],
    "sg:phone":"+1 506 532 5720",
    "sg:postcode":"E4R 5C8",
    "sg:province":"NB",
    "wof:name":"Grande-Digue Poste Canada Post",
    "wof:placetype":"venue"
},
  "geometry": {"coordinates":[-64.567543,46.290688],"type":"Point"}
}