{
  "type": "Feature",
  "properties": {
    "addr:full":"49 Poplar Ave Jasper AB T0E 1E0",
    "addr:housenumber":"49",
    "addr:postcode":"t0e 1e0",
    "addr:street":"Poplar Ave",
    "iso:country":"CA",
    "sg:address":"49 Poplar Ave",
    "sg:city":"Jasper",
    "sg:classifiers":[
        {
            "category":"Travel",
            "subcategory":"Travel Agent",
            "type":"Entertainment"
        }
    ],
    "sg:phone":"+1 780 852 5929",
    "sg:postcode":"T0E 1E0",
    "sg:province":"AB",
    "sg:tags":[
        "agency",
        "bureau"
    ],
    "wof:name":"Buckaroo Travel",
    "wof:placetype":"venue"
},
  "geometry": {"coordinates":[-118.09714508099999,52.8714447021],"type":"Point"}
}