{
  "type": "Feature",
  "properties": {
    "iso:country":"CA",
    "sg:address":"60 Hochelaga St W",
    "sg:city":"Moose Jaw",
    "sg:classifiers":[
        {
            "category":"Organizations",
            "subcategory":"Religious Organization",
            "type":"Services"
        }
    ],
    "sg:phone":"+1 306 692 4515",
    "sg:postcode":"S6H 2G1",
    "sg:province":"SK",
    "sg:tags":[
        "church"
    ],
    "wof:name":"Calvary Baptist Church",
    "wof:placetype":"venue"
},
  "geometry": {"coordinates":[-105.53626300000001,50.396381],"type":"Point"}
}