{
  "type": "Feature",
  "properties": {
    "addr:full":"13385 Trafalgar Rd Georgetown ON L7G 4S4",
    "addr:housenumber":"13385",
    "addr:postcode":"l7g 4s4",
    "addr:street":"Trafalgar Rd",
    "iso:country":"CA",
    "sg:address":"13385 Trafalgar Rd",
    "sg:city":"Georgetown",
    "sg:classifiers":[
        {
            "category":"Building & Trades",
            "subcategory":"Electrical",
            "type":"Services"
        }
    ],
    "sg:phone":"+1 905 702 0515",
    "sg:postcode":"L7G 4S4",
    "sg:province":"ON",
    "sg:tags":[
        "electric",
        "contractor"
    ],
    "wof:name":"Deker Electric Ltd",
    "wof:placetype":"venue"
},
  "geometry": {"coordinates":[-79.984711,43.675774],"type":"Point"}
}