{
  "type": "Feature",
  "properties": {
    "addr:full":"4455 99 St NW Edmonton AB T6E 5B6",
    "addr:housenumber":"4455",
    "addr:postcode":"t6e 5b6",
    "addr:street":"99 St Nw",
    "iso:country":"CA",
    "sg:address":"4455 99 St NW",
    "sg:city":"Edmonton",
    "sg:classifiers":[
        {
            "category":"Shopping",
            "subcategory":"Crafts & Fabrics",
            "type":"Retail Goods"
        }
    ],
    "sg:phone":"+1 780 437 1621",
    "sg:postcode":"T6E 5B6",
    "sg:province":"AB",
    "sg:tags":[
        "shop"
    ],
    "wof:name":"Mac Phee Workshop Ltd",
    "wof:placetype":"venue"
},
  "geometry": {"coordinates":[-113.485794,53.482536],"type":"Point"}
}