{
  "type": "Feature",
  "properties": {
    "addr:full":"3857 Rue Saint-Denis Montreal QC H2W 2M4",
    "addr:housenumber":"3857",
    "addr:postcode":"h2w 2m4",
    "addr:street":"Rue Saint-Denis",
    "iso:country":"CA",
    "sg:address":"3857 Rue Saint-Denis",
    "sg:city":"Montreal",
    "sg:classifiers":[
        {
            "category":"Restaurant",
            "type":"Food & Drink"
        }
    ],
    "sg:phone":"+1 514 843 9454",
    "sg:postcode":"H2W 2M4",
    "sg:province":"QC",
    "wof:name":"Restaurant Mediterraneen",
    "wof:placetype":"venue"
},
  "geometry": {"coordinates":[-73.5733337402,45.5197906494],"type":"Point"}
}