{
  "type": "Feature",
  "properties": {
    "addr:full":"Aurora ON L4G 1L8",
    "addr:postcode":"l4g 1l8",
    "iso:country":"CA",
    "sg:city":"Aurora",
    "sg:classifiers":[
        {
            "category":"Banks & Credit Unions",
            "subcategory":"Bank",
            "type":"Services"
        }
    ],
    "sg:phone":"+1 905 989 1422",
    "sg:postcode":"L4G 1L8",
    "sg:province":"ON",
    "sg:tags":[
        "loan",
        "real estate"
    ],
    "wof:name":"Mc Kay Mortgages",
    "wof:placetype":"venue"
},
  "geometry": {"coordinates":[-79.467163,43.998821],"type":"Point"}
}