{
  "type": "Feature",
  "properties": {
    "addr:full":"1882 Av Saint-Marc Shawinigan QC G9N 2H9",
    "addr:housenumber":"1882",
    "addr:postcode":"g9n 2h9",
    "addr:street":"Av Saint-Marc",
    "iso:country":"CA",
    "sg:address":"1882 Av Saint-Marc",
    "sg:city":"Shawinigan",
    "sg:classifiers":[
        {
            "category":"Health Services",
            "subcategory":"Optometrist",
            "type":"Services"
        }
    ],
    "sg:phone":"+1 819 536 2504",
    "sg:postcode":"G9N 2H9",
    "sg:province":"QC",
    "wof:name":"Bordeleau, Isabelle OD",
    "wof:placetype":"venue"
},
  "geometry": {"coordinates":[-72.7435379028,46.5527954102],"type":"Point"}
}