{
  "type": "Feature",
  "properties": {
    "addr:full":"Toronto ON M5R 2E3",
    "addr:postcode":"m5r 2e3",
    "iso:country":"CA",
    "sg:city":"Toronto",
    "sg:classifiers":[
        {
            "category":"Shopping",
            "subcategory":"Used Merchandise",
            "type":"Retail Goods"
        }
    ],
    "sg:phone":"+1 416 972 1378",
    "sg:postcode":"M5R 2E3",
    "sg:province":"ON",
    "sg:tags":[
        "antique"
    ],
    "wof:name":"Elisabeth Legge Antique Prints",
    "wof:placetype":"venue"
},
  "geometry": {"coordinates":[-79.39334869379999,43.6719055176],"type":"Point"}
}