{
  "type": "Feature",
  "properties": {
    "addr:full":"Provost AB T0B 3S0",
    "addr:postcode":"t0b 3s0",
    "iso:country":"CA",
    "sg:city":"Provost",
    "sg:classifiers":[
        {
            "category":"Real Estate",
            "subcategory":"Real Estate Agent",
            "type":"Services"
        }
    ],
    "sg:phone":"+1 780 753 6869",
    "sg:postcode":"T0B 3S0",
    "sg:province":"AB",
    "wof:name":"Meiklejohn Realty Ltd",
    "wof:placetype":"venue"
},
  "geometry": {"coordinates":[-110.251289368,52.3590507507],"type":"Point"}
}