{
  "type": "Feature",
  "properties": {
    "iso:country":"CA",
    "sg:city":"Palgrave",
    "sg:classifiers":[
        {
            "category":"Cinema",
            "subcategory":"Movie Rental",
            "type":"Entertainment"
        }
    ],
    "sg:phone":"+1 905 880 2425",
    "sg:postcode":"L0N 1P0",
    "sg:province":"ON",
    "sg:tags":[
        "leasing",
        "video",
        "disc",
        "tape"
    ],
    "wof:name":"L J's Video",
    "wof:placetype":"venue"
},
  "geometry": {"coordinates":[-79.834091,43.948635],"type":"Point"}
}