{
  "type": "Feature",
  "properties": {
    "addr:full":"21 Eddfield Ave North York ON M2N 2M5",
    "addr:housenumber":"21",
    "addr:postcode":"m2n 2m5",
    "addr:street":"Eddfield Ave",
    "iso:country":"CA",
    "sg:address":"21 Eddfield Ave",
    "sg:city":"North York",
    "sg:classifiers":[
        {
            "category":"Education",
            "subcategory":"School",
            "type":"Public Place"
        }
    ],
    "sg:phone":"+1 416 393 5255",
    "sg:postcode":"M2N 2M5",
    "sg:province":"ON",
    "wof:name":"Saint Edward Elementary",
    "wof:placetype":"venue"
},
  "geometry": {"coordinates":[-79.4281997681,43.7603759766],"type":"Point"}
}