{
  "type": "Feature",
  "properties": {
    "addr:full":"22 Av Juneau Shannon QC G0A 4N0",
    "addr:postcode":"g0a 4n0",
    "addr:street":"22 Av",
    "iso:country":"CA",
    "sg:address":"22 Av Juneau",
    "sg:city":"Shannon",
    "sg:classifiers":[
        {
            "category":"Manufacturing",
            "subcategory":"Paper Products",
            "type":"Manufacturing & Wholesale Goods"
        }
    ],
    "sg:phone":"+1 418 844 3530",
    "sg:postcode":"G0A 4N0",
    "sg:province":"QC",
    "sg:tags":[
        "tag"
    ],
    "wof:name":"Attaches Et Etiquettes Lmb",
    "wof:placetype":"venue"
},
  "geometry": {"coordinates":[-71.521652,46.887608],"type":"Point"}
}