{
  "type": "Feature",
  "properties": {
    "addr:full":"7 Cromwell St Campbellton NB E3N 3C1",
    "addr:housenumber":"7",
    "addr:postcode":"e3n 3c1",
    "addr:street":"Cromwell St",
    "iso:country":"CA",
    "sg:address":"7 Cromwell St",
    "sg:city":"Campbellton",
    "sg:classifiers":[
        {
            "category":"Retail",
            "subcategory":"Auto Repair",
            "type":"Services"
        }
    ],
    "sg:phone":"+1 506 789 7611",
    "sg:postcode":"E3N 3C1",
    "sg:province":"NB",
    "sg:tags":[
        "repairing",
        "automobile"
    ],
    "wof:name":"Mortlock Services",
    "wof:placetype":"venue"
},
  "geometry": {"coordinates":[-66.68817138670001,48.0013504028],"type":"Point"}
}