{
  "type": "Feature",
  "properties": {
    "addr:full":"3 Frances Crt Essex ON N8M 2V5",
    "addr:housenumber":"3",
    "addr:postcode":"n8m 2v5",
    "addr:street":"Frances Crt",
    "iso:country":"CA",
    "sg:address":"3 Frances Crt",
    "sg:city":"Essex",
    "sg:classifiers":[
        {
            "category":"Building & Trades",
            "subcategory":"Construction",
            "type":"Services"
        }
    ],
    "sg:phone":"+1 519 776 7931",
    "sg:postcode":"N8M 2V5",
    "sg:province":"ON",
    "sg:tags":[
        "contractor"
    ],
    "wof:name":"Edward C Sargent Constr Ltd",
    "wof:placetype":"venue"
},
  "geometry": {"coordinates":[-82.813339,42.175529],"type":"Point"}
}