{
  "type": "Feature",
  "properties": {
    "addr:full":"69 Ch Lac Des Lys Val-D'Amour NB E3N 5E7",
    "addr:housenumber":"69",
    "addr:postcode":"e3n 5e7",
    "addr:street":"Ch Lac Des Lys",
    "iso:country":"CA",
    "sg:address":"69 Ch Lac Des Lys",
    "sg:city":"Val-D'Amour",
    "sg:classifiers":[
        {
            "category":"Manufacturing",
            "subcategory":"Tools & Machinery",
            "type":"Manufacturing & Wholesale Goods"
        }
    ],
    "sg:phone":"+1 506 753 5574",
    "sg:postcode":"E3N 5E7",
    "sg:province":"NB",
    "sg:tags":[
        "machine",
        "shop"
    ],
    "wof:name":"Johnson Enterprises Inc",
    "wof:placetype":"venue"
},
  "geometry": {"coordinates":[-66.6686325073,47.9581298828],"type":"Point"}
}