{
  "type": "Feature",
  "properties": {
    "addr:full":"613 Front Hearst ON P0L 1N0",
    "addr:housenumber":"613",
    "addr:postcode":"p0l 1n0",
    "addr:street":"Front Hearst",
    "iso:country":"CA",
    "sg:address":"613 Front",
    "sg:city":"Hearst",
    "sg:classifiers":[
        {
            "category":"Government",
            "subcategory":"Office",
            "type":"Public Place"
        }
    ],
    "sg:phone":"+1 705 362 4346",
    "sg:postcode":"P0L 1N0",
    "sg:province":"ON",
    "wof:name":"Ontario Hunting Licenses",
    "wof:placetype":"venue"
},
  "geometry": {"coordinates":[-83.6590957642,49.6887931824],"type":"Point"}
}