{
  "type": "Feature",
  "properties": {
    "addr:full":"Lakefield ON K0L 2H0",
    "addr:postcode":"k0l 2h0",
    "iso:country":"CA",
    "sg:city":"Lakefield",
    "sg:classifiers":[
        {
            "category":"Travel",
            "subcategory":"Campground",
            "type":"Entertainment"
        }
    ],
    "sg:phone":"+1 705 652 8610",
    "sg:postcode":"K0L 2H0",
    "sg:province":"ON",
    "wof:name":"Lakefield Campground",
    "wof:placetype":"venue"
},
  "geometry": {"coordinates":[-78.27546700000001,44.42585],"type":"Point"}
}