{
  "type": "Feature",
  "properties": {
    "iso:country":"CA",
    "sg:address":"4573 Rue Saint-Felix",
    "sg:city":"Cap-Rouge",
    "sg:classifiers":[
        {
            "category":"Wholesale",
            "subcategory":"Metals & Minerals",
            "type":"Manufacturing & Wholesale Goods"
        }
    ],
    "sg:phone":"+1 418 654 1177",
    "sg:postcode":"G1Y 3B4",
    "sg:province":"QC",
    "sg:tags":[
        "aluminum"
    ],
    "wof:name":"Kawneer",
    "wof:placetype":"venue"
},
  "geometry": {"coordinates":[-71.361885,46.738716],"type":"Point"}
}