{
  "type": "Feature",
  "properties": {
    "addr:full":"86 6th Ave Cochrane ON P0L 1C0",
    "addr:housenumber":"86",
    "addr:postcode":"p0l 1c0",
    "addr:street":"6Th Ave",
    "iso:country":"CA",
    "sg:address":"86 6th Ave",
    "sg:city":"Cochrane",
    "sg:classifiers":[
        {
            "category":"Retail",
            "subcategory":"Laundry & Dry Cleaning",
            "type":"Services"
        }
    ],
    "sg:phone":"+1 705 272 4589",
    "sg:postcode":"P0L 1C0",
    "sg:province":"ON",
    "sg:tags":[
        "mending",
        "weaving"
    ],
    "wof:name":"Jeunes Tisserandes",
    "wof:placetype":"venue"
},
  "geometry": {"coordinates":[-81.02930499999999,49.066719],"type":"Point"}
}