{
  "type": "Feature",
  "properties": {
    "addr:full":"Vancouver BC V6R 4N6",
    "addr:postcode":"v6r 4n6",
    "iso:country":"CA",
    "sg:city":"Vancouver",
    "sg:classifiers":[
        {
            "category":"Personal",
            "subcategory":"Shoe Repair & Shine",
            "type":"Services"
        }
    ],
    "sg:phone":"+1 604 222 1780",
    "sg:postcode":"V6R 4N6",
    "sg:province":"BC",
    "sg:tags":[
        "repairing",
        "boot"
    ],
    "wof:name":"Jericho Shoe Repair",
    "wof:placetype":"venue"
},
  "geometry": {"coordinates":[-123.18590500000001,49.267956],"type":"Point"}
}