{
  "type": "Feature",
  "properties": {
    "addr:full":"Westbank BC V4T 2B4",
    "addr:postcode":"v4t 2b4",
    "iso:country":"CA",
    "sg:city":"Westbank",
    "sg:classifiers":[
        {
            "category":"Freight",
            "type":"Transportation"
        }
    ],
    "sg:phone":"+1 250 768 0122",
    "sg:postcode":"V4T 2B4",
    "sg:province":"BC",
    "sg:tags":[
        "bus",
        "line",
        "courier"
    ],
    "wof:name":"Greyhound Lines of Canada Ltd",
    "wof:placetype":"venue"
},
  "geometry": {"coordinates":[-119.634872,49.829647],"type":"Point"}
}