{
  "type": "Feature",
  "properties": {
    "addr:full":"5024 49th St Clyde AB T0G 0P0",
    "addr:housenumber":"5024",
    "addr:postcode":"t0g 0p0",
    "addr:street":"49Th St",
    "iso:country":"CA",
    "sg:address":"5024 49th St",
    "sg:city":"Clyde",
    "sg:classifiers":[
        {
            "category":"Building & Trades",
            "subcategory":"Construction",
            "type":"Services"
        }
    ],
    "sg:phone":"+1 780 348 5804",
    "sg:postcode":"T0G 0P0",
    "sg:province":"AB",
    "sg:tags":[
        "downspouts",
        "gutter"
    ],
    "wof:name":"Westlock Eavestroughing",
    "wof:placetype":"venue"
},
  "geometry": {"coordinates":[-113.634232,54.147873],"type":"Point"}
}