{
  "type": "Feature",
  "properties": {
    "addr:full":"2555 Rue Beaubien E Montreal QC H1Y 1G4",
    "addr:housenumber":"2555",
    "addr:postcode":"h1y 1g4",
    "addr:street":"Rue Beaubien E",
    "iso:country":"CA",
    "sg:address":"2555 Rue Beaubien E",
    "sg:city":"Montreal",
    "sg:classifiers":[
        {
            "category":"Personal",
            "subcategory":"Beauty Salon",
            "type":"Services"
        }
    ],
    "sg:phone":"+1 514 729 3838",
    "sg:postcode":"H1Y 1G4",
    "sg:province":"QC",
    "wof:name":"Coiffure Avant-Tout Enr",
    "wof:placetype":"venue"
},
  "geometry": {"coordinates":[-73.5916213989,45.5489883423],"type":"Point"}
}