{
  "type": "Feature",
  "properties": {
    "addr:full":"Saint-Felicien QC G8K 1P8",
    "addr:postcode":"g8k 1p8",
    "iso:country":"CA",
    "sg:city":"Saint-Felicien",
    "sg:classifiers":[
        {
            "category":"Shopping",
            "subcategory":"Computers & Home Electronics",
            "type":"Retail Goods"
        }
    ],
    "sg:phone":"+1 418 679 5809",
    "sg:postcode":"G8K 1P8",
    "sg:province":"QC",
    "sg:tags":[
        "equipment",
        "dealer"
    ],
    "wof:name":"Informatik Vision Inc",
    "wof:placetype":"venue"
},
  "geometry": {"coordinates":[-72.444199,48.650955],"type":"Point"}
}