{
  "type": "Feature",
  "properties": {
    "addr:full":"922 5 Rang W Joly QC G0S 1M0",
    "addr:housenumber":"922 5",
    "addr:postcode":"g0s 1m0",
    "addr:street":"Rang W Joly",
    "iso:country":"CA",
    "sg:address":"922 5 Rang W",
    "sg:city":"Joly",
    "sg:classifiers":[
        {
            "category":"Wholesale",
            "subcategory":"Machinery & Supplies",
            "type":"Manufacturing & Wholesale Goods"
        }
    ],
    "sg:phone":"+1 418 728 3666",
    "sg:postcode":"G0S 1M0",
    "sg:province":"QC",
    "sg:tags":[
        "equipment",
        "parts",
        "tractor"
    ],
    "wof:name":"Garage Yvon Cote",
    "wof:placetype":"venue"
},
  "geometry": {"coordinates":[-71.66822814939999,46.484752655],"type":"Point"}
}