{
  "type": "Feature",
  "properties": {
    "addr:full":"Beamsville ON L0R 1B4",
    "addr:postcode":"l0r 1b4",
    "iso:country":"CA",
    "sg:city":"Beamsville",
    "sg:classifiers":[
        {
            "category":"Retail",
            "subcategory":"Auto Repair",
            "type":"Services"
        }
    ],
    "sg:phone":"+1 905 945 6366",
    "sg:postcode":"L0R 1B4",
    "sg:province":"ON",
    "sg:tags":[
        "wrecker"
    ],
    "wof:name":"Hmb Enterprises",
    "wof:placetype":"venue"
},
  "geometry": {"coordinates":[-79.47439575200001,43.1838493347],"type":"Point"}
}