{
  "type": "Feature",
  "properties": {
    "addr:full":"10 Barton Cres Fredericton NB E3A 5S3",
    "addr:housenumber":"10",
    "addr:postcode":"e3a 5s3",
    "addr:street":"Barton Cres",
    "iso:country":"CA",
    "sg:address":"10 Barton Cres",
    "sg:city":"Fredericton",
    "sg:classifiers":[
        {
            "category":"Health Services",
            "subcategory":"Nursing And Care Facility",
            "type":"Services"
        }
    ],
    "sg:phone":"+1 506 450 7088",
    "sg:postcode":"E3A 5S3",
    "sg:province":"NB",
    "sg:tags":[
        "home",
        "retirement",
        "community"
    ],
    "wof:name":"Windsor Court Retirement Res",
    "wof:placetype":"venue"
},
  "geometry": {"coordinates":[-66.665176,45.991386],"type":"Point"}
}