{
  "type": "Feature",
  "properties": {
    "addr:full":"51 First Ave W Simcoe ON N3Y 2P6",
    "addr:housenumber":"51",
    "addr:postcode":"n3y 2p6",
    "addr:street":"First Ave W",
    "iso:country":"CA",
    "sg:address":"51 First Ave W",
    "sg:city":"Simcoe",
    "sg:classifiers":[
        {
            "category":"Retail",
            "subcategory":"Auto Repair",
            "type":"Services"
        }
    ],
    "sg:phone":"+1 519 426 6893",
    "sg:postcode":"N3Y 2P6",
    "sg:province":"ON",
    "sg:tags":[
        "repairing",
        "automobile",
        "electric"
    ],
    "wof:name":"Simcoe Starter & Alternators",
    "wof:placetype":"venue"
},
  "geometry": {"coordinates":[-80.30999,42.850613],"type":"Point"}
}