{
  "type": "Feature",
  "properties": {
    "addr:full":"42538 Peters Rd Chilliwack BC V2R 4K3",
    "addr:housenumber":"42538",
    "addr:postcode":"v2r 4k3",
    "addr:street":"Peters Rd",
    "iso:country":"CA",
    "sg:address":"42538 Peters Rd",
    "sg:city":"Chilliwack",
    "sg:classifiers":[
        {
            "category":"Building & Trades",
            "subcategory":"Construction",
            "type":"Services"
        }
    ],
    "sg:phone":"+1 604 823 4250",
    "sg:postcode":"V2R 4K3",
    "sg:province":"BC",
    "sg:tags":[
        "plastering",
        "stucco",
        "contractor"
    ],
    "wof:name":"Riverside Stucco",
    "wof:placetype":"venue"
},
  "geometry": {"coordinates":[-122.04740099999999,49.120049],"type":"Point"}
}