{
  "type": "Feature",
  "properties": {
    "addr:full":"26 Water St Yarmouth NS B5A 4B2",
    "addr:housenumber":"26",
    "addr:postcode":"b5a 4b2",
    "addr:street":"Water St",
    "iso:country":"CA",
    "sg:address":"26 Water St",
    "sg:city":"Yarmouth",
    "sg:classifiers":[
        {
            "category":"Manufacturing",
            "subcategory":"Food",
            "type":"Manufacturing & Wholesale Goods"
        }
    ],
    "sg:phone":"+1 902 742 3519",
    "sg:postcode":"B5A 4B2",
    "sg:province":"NS",
    "sg:tags":[
        "packer",
        "fish"
    ],
    "wof:name":"Imo Foods Ltd",
    "wof:placetype":"venue"
},
  "geometry": {"coordinates":[-66.122925,43.827209],"type":"Point"}
}