{
  "type": "Feature",
  "properties": {
    "addr:full":"209 Lardeau River Rd Meadow Creek BC V0G 1N0",
    "addr:housenumber":"209",
    "addr:postcode":"v0g 1n0",
    "addr:street":"Lardeau River Rd",
    "iso:country":"CA",
    "sg:address":"209 Lardeau River Rd",
    "sg:city":"Meadow Creek",
    "sg:classifiers":[
        {
            "category":"Manufacturing",
            "subcategory":"Lumber",
            "type":"Manufacturing & Wholesale Goods"
        }
    ],
    "sg:phone":"+1 250 366 4235",
    "sg:postcode":"V0G 1N0",
    "sg:province":"BC",
    "sg:tags":[
        "sawmill"
    ],
    "wof:name":"Boards By George Lumber Inc",
    "wof:placetype":"venue"
},
  "geometry": {"coordinates":[-116.960182,50.196888],"type":"Point"}
}