{
  "type": "Feature",
  "properties": {
    "addr:full":"5763 Rue Cartier Montreal QC H2G 2V1",
    "addr:housenumber":"5763",
    "addr:postcode":"h2g 2v1",
    "addr:street":"Rue Cartier",
    "iso:country":"CA",
    "sg:address":"5763 Rue Cartier",
    "sg:city":"Montreal",
    "sg:classifiers":[
        {
            "category":"Food & Beverages",
            "subcategory":"Groceries & Convenience Stores",
            "type":"Retail Goods"
        }
    ],
    "sg:phone":"+1 514 495 3369",
    "sg:postcode":"H2G 2V1",
    "sg:province":"QC",
    "wof:name":"Depanneur Cartier Enr",
    "wof:placetype":"venue"
},
  "geometry": {"coordinates":[-73.5885772705,45.5402565002],"type":"Point"}
}