{
  "type": "Feature",
  "properties": {
    "addr:full":"30 Boul Rene-Levesque E Quebec QC G1R 2B1",
    "addr:housenumber":"30",
    "addr:postcode":"g1r 2b1",
    "addr:street":"Boul Rene-Levesque E",
    "iso:country":"CA",
    "sg:address":"30 Boul Rene-Levesque E",
    "sg:city":"Quebec",
    "sg:classifiers":[
        {
            "category":"Travel",
            "subcategory":"Travel Agent",
            "type":"Entertainment"
        }
    ],
    "sg:phone":"+1 418 522 2791",
    "sg:postcode":"G1R 2B1",
    "sg:province":"QC",
    "sg:tags":[
        "agency",
        "bureau"
    ],
    "wof:name":"Vacances Tourbec",
    "wof:placetype":"venue"
},
  "geometry": {"coordinates":[-71.2251281738,46.8053474426],"type":"Point"}
}