{
  "type": "Feature",
  "properties": {
    "iso:country":"CA",
    "sg:address":"527 Queen St",
    "sg:city":"Fredericton",
    "sg:classifiers":[
        {
            "category":"Government",
            "subcategory":"Office",
            "type":"Public Place"
        }
    ],
    "sg:phone":"+1 506 452 3018",
    "sg:postcode":"E3B 1B8",
    "sg:province":"NB",
    "wof:name":"Canada Fisheries & Habitat",
    "wof:placetype":"venue"
},
  "geometry": {"coordinates":[-66.6400985718,45.9618797302],"type":"Point"}
}