{
  "type": "Feature",
  "properties": {
    "addr:full":"10 First Ave Uxbridge ON L9P 1J6",
    "addr:housenumber":"10",
    "addr:postcode":"l9p 1j6",
    "addr:street":"First Ave",
    "iso:country":"CA",
    "sg:address":"10 First Ave",
    "sg:city":"Uxbridge",
    "sg:classifiers":[
        {
            "category":"Health Services",
            "subcategory":"Nursing And Care Facility",
            "type":"Services"
        }
    ],
    "sg:phone":"+1 905 852 3805",
    "sg:postcode":"L9P 1J6",
    "sg:province":"ON",
    "sg:tags":[
        "home",
        "retirement",
        "community"
    ],
    "wof:name":"Trinity Manor",
    "wof:placetype":"venue"
},
  "geometry": {"coordinates":[-79.11937,44.110088],"type":"Point"}
}