{
  "type": "Feature",
  "properties": {
    "addr:full":"Scarborough ON M1E 5G6",
    "addr:postcode":"m1e 5g6",
    "iso:country":"CA",
    "sg:city":"Scarborough",
    "sg:classifiers":[
        {
            "category":"Social Services",
            "type":"Services"
        }
    ],
    "sg:phone":"+1 416 287 0025",
    "sg:postcode":"M1E 5G6",
    "sg:province":"ON",
    "sg:tags":[
        "housing",
        "assistance"
    ],
    "wof:name":"Estorada",
    "wof:placetype":"venue"
},
  "geometry": {"coordinates":[-79.196556,43.767471],"type":"Point"}
}