{
  "type": "Feature",
  "properties": {
    "addr:full":"217 Keefer St Vancouver BC V6A 1X6",
    "addr:housenumber":"217",
    "addr:postcode":"v6a 1x6",
    "addr:street":"Keefer St",
    "iso:country":"CA",
    "sg:address":"217 Keefer St",
    "sg:city":"Vancouver",
    "sg:classifiers":[
        {
            "category":"Food & Beverages",
            "subcategory":"Specialty",
            "type":"Retail Goods"
        }
    ],
    "sg:phone":"+1 604 689 8028",
    "sg:postcode":"V6A 1X6",
    "sg:province":"BC",
    "sg:tags":[
        "health",
        "diet"
    ],
    "wof:name":"Ngai Hoi Trading Ltd",
    "wof:placetype":"venue"
},
  "geometry": {"coordinates":[-123.099098,49.279602],"type":"Point"}
}