{
  "type": "Feature",
  "properties": {
    "addr:full":"294 Big Bend Hwy Revelstoke BC V0E 2S0",
    "addr:housenumber":"294",
    "addr:postcode":"v0e 2s0",
    "addr:street":"Big Bend Hwy",
    "iso:country":"CA",
    "sg:address":"294 Big Bend Hwy",
    "sg:city":"Revelstoke",
    "sg:classifiers":[
        {
            "category":"Retail",
            "subcategory":"Auto Repair",
            "type":"Services"
        }
    ],
    "sg:phone":"+1 250 837 4393",
    "sg:postcode":"V0E 2S0",
    "sg:province":"BC",
    "sg:tags":[
        "repairing",
        "automobile",
        "muffler",
        "system",
        "exhaust"
    ],
    "wof:name":"Stay Cool Radiators & Mufflers",
    "wof:placetype":"venue"
},
  "geometry": {"coordinates":[-118.214477539,51.0101470947],"type":"Point"}
}