{
  "type": "Feature",
  "properties": {
    "addr:full":"Vaughan ON L6A 1T1",
    "addr:postcode":"l6a 1t1",
    "iso:country":"CA",
    "sg:city":"Vaughan",
    "sg:classifiers":[
        {
            "category":"Recreation",
            "type":"Entertainment"
        }
    ],
    "sg:phone":"+1 905 832 8577",
    "sg:postcode":"L6A 1T1",
    "sg:province":"ON",
    "sg:tags":[
        "provincial",
        "parks"
    ],
    "wof:name":"Vaughan Parks Administration",
    "wof:placetype":"venue"
},
  "geometry": {"coordinates":[-79.50810199999999,43.856419],"type":"Point"}
}