{
  "type": "Feature",
  "properties": {
    "addr:full":"1477 Diamondview Rd Carp ON K0A 1L0",
    "addr:housenumber":"1477",
    "addr:postcode":"k0a 1l0",
    "addr:street":"Diamondview Rd",
    "iso:country":"CA",
    "sg:address":"1477 Diamondview Rd",
    "sg:city":"Carp",
    "sg:classifiers":[
        {
            "category":"Building & Trades",
            "subcategory":"Construction",
            "type":"Services"
        }
    ],
    "sg:phone":"+1 613 839 3932",
    "sg:postcode":"K0A 1L0",
    "sg:province":"ON",
    "sg:tags":[
        "maker",
        "cabinet"
    ],
    "wof:name":"Lifestyles Interiors Ltd",
    "wof:placetype":"venue"
},
  "geometry": {"coordinates":[-76.041771,45.311481],"type":"Point"}
}