{
  "type": "Feature",
  "properties": {
    "addr:full":"Edmonton AB T6G 1K4",
    "addr:postcode":"t6g 1k4",
    "iso:country":"CA",
    "sg:city":"Edmonton",
    "sg:classifiers":[
        {
            "category":"Health Services",
            "subcategory":"Doctor",
            "type":"Services"
        }
    ],
    "sg:phone":"+1 780 448 7347",
    "sg:postcode":"T6G 1K4",
    "sg:province":"AB",
    "sg:tags":[
        "physician",
        "surgeon"
    ],
    "wof:name":"Rigal, Wynne M MD",
    "wof:placetype":"venue"
},
  "geometry": {"coordinates":[-113.520599365,53.5192222595],"type":"Point"}
}