{
  "type": "Feature",
  "properties": {
    "addr:full":"9907 86 St Fort St John BC V1J 3G4",
    "addr:housenumber":"9907",
    "addr:postcode":"v1j 3g4",
    "addr:street":"86 St",
    "iso:country":"CA",
    "sg:address":"9907 86 St",
    "sg:city":"Fort St John",
    "sg:classifiers":[
        {
            "category":"Education",
            "subcategory":"School",
            "type":"Public Place"
        }
    ],
    "sg:phone":"+1 250 785 3704",
    "sg:postcode":"V1J 3G4",
    "sg:province":"BC",
    "wof:name":"Robert Ogilvie Elementary",
    "wof:placetype":"venue"
},
  "geometry": {"coordinates":[-120.82093,56.245499],"type":"Point"}
}