{
  "type": "Feature",
  "properties": {
    "addr:full":"Surrey BC V4A 2J4",
    "addr:postcode":"v4a 2j4",
    "iso:country":"CA",
    "sg:city":"Surrey",
    "sg:classifiers":[
        {
            "category":"Wholesale",
            "subcategory":"Machinery & Supplies",
            "type":"Manufacturing & Wholesale Goods"
        }
    ],
    "sg:phone":"+1 604 531 9277",
    "sg:postcode":"V4A 2J4",
    "sg:province":"BC",
    "sg:tags":[
        "pump"
    ],
    "wof:name":"Viking Pump CO of Canada Inc",
    "wof:placetype":"venue"
},
  "geometry": {"coordinates":[-122.792366028,49.0457191467],"type":"Point"}
}