{
  "type": "Feature",
  "properties": {
    "addr:full":"Vancouver BC V6C 1N5",
    "addr:postcode":"v6c 1n5",
    "iso:country":"CA",
    "sg:city":"Vancouver",
    "sg:classifiers":[
        {
            "category":"Professional",
            "subcategory":"Computer Services",
            "type":"Services"
        }
    ],
    "sg:phone":"+1 604 669 6266",
    "sg:postcode":"V6C 1N5",
    "sg:province":"BC",
    "sg:tags":[
        "internet"
    ],
    "wof:name":"Cool 2000 Internet Ltd",
    "wof:placetype":"venue"
},
  "geometry": {"coordinates":[-123.11788199999999,49.284832],"type":"Point"}
}