{
  "type": "Feature",
  "properties": {
    "addr:full":"671 Hastings St E Vancouver BC V6A 1R2",
    "addr:housenumber":"671",
    "addr:postcode":"v6a 1r2",
    "addr:street":"Hastings St E",
    "iso:country":"CA",
    "sg:address":"671 Hastings St E",
    "sg:city":"Vancouver",
    "sg:classifiers":[
        {
            "category":"Shopping",
            "subcategory":"Used Merchandise",
            "type":"Retail Goods"
        }
    ],
    "sg:phone":"+1 604 254 8721",
    "sg:postcode":"V6A 1R2",
    "sg:province":"BC",
    "sg:tags":[
        "shop",
        "thrift"
    ],
    "wof:name":"Union Gospel Mission Thrft Shp",
    "wof:placetype":"venue"
},
  "geometry": {"coordinates":[-123.090301514,49.2812767029],"type":"Point"}
}