{
  "type": "Feature",
  "properties": {
    "addr:full":"72 Rue Montcalm Salaberry-DE-Valleyfield QC J6T 2C9",
    "addr:housenumber":"72",
    "addr:postcode":"j6t 2c9",
    "addr:street":"Rue Montcalm",
    "iso:country":"CA",
    "sg:address":"72 Rue Montcalm",
    "sg:city":"Salaberry-DE-Valleyfield",
    "sg:classifiers":[
        {
            "category":"Professional",
            "subcategory":"Lawyer & Legal Services",
            "type":"Services"
        }
    ],
    "sg:phone":"+1 450 371 7771",
    "sg:postcode":"J6T 2C9",
    "sg:province":"QC",
    "sg:tags":[
        "attorney"
    ],
    "wof:name":"Martin, Claire",
    "wof:placetype":"venue"
},
  "geometry": {"coordinates":[-74.127022,45.254356],"type":"Point"}
}