{
  "type": "Feature",
  "properties": {
    "addr:full":"Magog QC J1X 2B2",
    "addr:postcode":"j1x 2b2",
    "iso:country":"CA",
    "sg:city":"Magog",
    "sg:classifiers":[
        {
            "category":"Professional",
            "subcategory":"Business Services",
            "type":"Services"
        }
    ],
    "sg:phone":"+1 819 868 4360",
    "sg:postcode":"J1X 2B2",
    "sg:province":"QC",
    "sg:tags":[
        "notary"
    ],
    "wof:name":"Caron, Andre",
    "wof:placetype":"venue"
},
  "geometry": {"coordinates":[-72.134682,45.26078],"type":"Point"}
}