{
  "type": "Feature",
  "properties": {
    "addr:full":"120 Main St Spiritwood SK S0J 2M0",
    "addr:housenumber":"120",
    "addr:postcode":"s0j 2m0",
    "addr:street":"Main St",
    "iso:country":"CA",
    "sg:address":"120 Main St",
    "sg:city":"Spiritwood",
    "sg:classifiers":[
        {
            "category":"Food & Beverages",
            "subcategory":"Groceries & Convenience Stores",
            "type":"Retail Goods"
        }
    ],
    "sg:phone":"+1 306 883 2444",
    "sg:postcode":"S0J 2M0",
    "sg:province":"SK",
    "sg:tags":[
        "grocer"
    ],
    "wof:name":"Shop Easy Foods",
    "wof:placetype":"venue"
},
  "geometry": {"coordinates":[-107.51890564,53.3658561707],"type":"Point"}
}