{
  "type": "Feature",
  "properties": {
    "addr:full":"6560 Av Isaac-Bedard Charlesbourg QC G1H 2Z9",
    "addr:housenumber":"6560",
    "addr:postcode":"g1h 2z9",
    "addr:street":"Av Isaac-Bedard",
    "iso:country":"CA",
    "sg:address":"6560 Av Isaac-Bedard",
    "sg:city":"Charlesbourg",
    "sg:classifiers":[
        {
            "category":"Personal",
            "subcategory":"Beauty Salon",
            "type":"Services"
        }
    ],
    "sg:phone":"+1 418 621 9889",
    "sg:postcode":"G1H 2Z9",
    "sg:province":"QC",
    "wof:name":"Coiffure Marc Dumont",
    "wof:placetype":"venue"
},
  "geometry": {"coordinates":[-71.2591781616,46.8539810181],"type":"Point"}
}