{
  "type": "Feature",
  "properties": {
    "addr:full":"3485 Rue Queen Rawdon QC J0K 1S0",
    "addr:housenumber":"3485",
    "addr:postcode":"j0k 1s0",
    "addr:street":"Rue Queen",
    "iso:country":"CA",
    "sg:address":"3485 Rue Queen",
    "sg:city":"Rawdon",
    "sg:classifiers":[
        {
            "category":"Restaurant",
            "type":"Food & Drink"
        }
    ],
    "sg:phone":"+1 450 834 4225",
    "sg:postcode":"J0K 1S0",
    "sg:province":"QC",
    "wof:name":"Restaurant Rosa Pizzeria",
    "wof:placetype":"venue"
},
  "geometry": {"coordinates":[-73.7019271851,46.0386772156],"type":"Point"}
}