{
  "type": "Feature",
  "properties": {
    "addr:full":"3415 Roblin Blvd Winnipeg MB R3R 0C6",
    "addr:housenumber":"3415",
    "addr:postcode":"r3r 0c6",
    "addr:street":"Roblin Blvd",
    "iso:country":"CA",
    "sg:address":"3415 Roblin Blvd",
    "sg:city":"Winnipeg",
    "sg:classifiers":[
        {
            "category":"Real Estate",
            "subcategory":"Real Estate Agent",
            "type":"Services"
        }
    ],
    "sg:phone":"+1 204 888 1898",
    "sg:postcode":"R3R 0C6",
    "sg:province":"MB",
    "wof:name":"Canadian Corporate Real Estate",
    "wof:placetype":"venue"
},
  "geometry": {"coordinates":[-97.257057,49.868584],"type":"Point"}
}