{
  "type": "Feature",
  "properties": {
    "iso:country":"CA",
    "sg:address":"2340 Rte 138 E",
    "sg:city":"Havre-Saint-Pierre",
    "sg:classifiers":[
        {
            "category":"Real Estate",
            "subcategory":"Surveying",
            "type":"Services"
        }
    ],
    "sg:phone":"+1 418 538 3800",
    "sg:postcode":"G0G 1P0",
    "sg:province":"QC",
    "sg:tags":[
        "surveyor"
    ],
    "wof:name":"Services Azimut Enr",
    "wof:placetype":"venue"
},
  "geometry": {"coordinates":[-63.5813751221,50.2515335083],"type":"Point"}
}