{
  "type": "Feature",
  "properties": {
    "addr:full":"70 Wynford Dr North York ON M3C 1J9",
    "addr:housenumber":"70",
    "addr:postcode":"m3c 1j9",
    "addr:street":"Wynford Dr",
    "iso:country":"CA",
    "sg:address":"70 Wynford Dr",
    "sg:city":"North York",
    "sg:classifiers":[
        {
            "category":"Manufacturing",
            "subcategory":"Printing",
            "type":"Manufacturing & Wholesale Goods"
        }
    ],
    "sg:phone":"+1 416 441 2941",
    "sg:postcode":"M3C 1J9",
    "sg:province":"ON",
    "sg:tags":[
        "publisher"
    ],
    "wof:name":"Oxford University Press",
    "wof:placetype":"venue"
},
  "geometry": {"coordinates":[-79.3339,43.725307],"type":"Point"}
}