{
  "type": "Feature",
  "properties": {
    "addr:full":"2170 Harvey Ave Kelowna BC V1Y 6G8",
    "addr:housenumber":"2170",
    "addr:postcode":"v1y 6g8",
    "addr:street":"Harvey Ave",
    "iso:country":"CA",
    "sg:address":"2170 Harvey Ave",
    "sg:city":"Kelowna",
    "sg:classifiers":[
        {
            "category":"Bars & Pubs",
            "type":"Food & Drink"
        }
    ],
    "sg:phone":"+1 250 979 4548",
    "sg:postcode":"V1Y 6G8",
    "sg:province":"BC",
    "wof:name":"Mickie's Pub",
    "wof:placetype":"venue"
},
  "geometry": {"coordinates":[-119.439552307,49.8820304871],"type":"Point"}
}