{
  "type": "Feature",
  "properties": {
    "addr:full":"641 Rue Mediane E LA Presentation QC J0H 1B0",
    "addr:housenumber":"641",
    "addr:postcode":"j0h 1b0",
    "addr:street":"Rue Mediane E La Presentation",
    "iso:country":"CA",
    "sg:address":"641 Rue Mediane E",
    "sg:city":"LA Presentation",
    "sg:classifiers":[
        {
            "category":"Personal",
            "subcategory":"Beauty Salon",
            "type":"Services"
        }
    ],
    "sg:phone":"+1 450 796 5900",
    "sg:postcode":"J0H 1B0",
    "sg:province":"QC",
    "wof:name":"Salon 641 Enr",
    "wof:placetype":"venue"
},
  "geometry": {"coordinates":[-73.05583190919999,45.670135498],"type":"Point"}
}