{
  "type": "Feature",
  "properties": {
    "addr:full":"Eriksdale MB R0C 0W0",
    "addr:postcode":"r0c 0w0",
    "iso:country":"CA",
    "sg:city":"Eriksdale",
    "sg:classifiers":[
        {
            "category":"Organizations",
            "subcategory":"Religious Organization",
            "type":"Services"
        }
    ],
    "sg:phone":"+1 204 739 2146",
    "sg:postcode":"R0C 0W0",
    "sg:province":"MB",
    "sg:tags":[
        "church"
    ],
    "wof:name":"United Church of Eriksdale",
    "wof:placetype":"venue"
},
  "geometry": {"coordinates":[-98.1222991943,50.8600883484],"type":"Point"}
}