{
  "type": "Feature",
  "properties": {
    "addr:full":"70 Mcleod Ave Spruce Grove AB T7X 3C7",
    "addr:housenumber":"70",
    "addr:postcode":"t7x 3c7",
    "addr:street":"Mcleod Ave",
    "iso:country":"CA",
    "sg:address":"70 Mcleod Ave",
    "sg:city":"Spruce Grove",
    "sg:classifiers":[
        {
            "category":"Shopping",
            "subcategory":"Books",
            "type":"Retail Goods"
        }
    ],
    "sg:phone":"+1 780 962 9355",
    "sg:postcode":"T7X 3C7",
    "sg:province":"AB",
    "sg:tags":[
        "dealer"
    ],
    "wof:name":"Coles",
    "wof:placetype":"venue"
},
  "geometry": {"coordinates":[-113.913757324,53.5429916382],"type":"Point"}
}