{
  "type": "Feature",
  "properties": {
    "addr:full":"Panet QC G0R 2J0",
    "addr:postcode":"g0r 2j0",
    "iso:country":"CA",
    "sg:city":"Panet",
    "sg:classifiers":[
        {
            "category":"Organizations",
            "subcategory":"Religious Organization",
            "type":"Services"
        }
    ],
    "sg:phone":"+1 418 249 4171",
    "sg:postcode":"G0R 2J0",
    "sg:province":"QC",
    "sg:tags":[
        "church"
    ],
    "wof:name":"Presbytere St-Fabien",
    "wof:placetype":"venue"
},
  "geometry": {"coordinates":[-70.1456451416,46.655292511],"type":"Point"}
}