{
  "type": "Feature",
  "properties": {
    "addr:full":"1111 Cranbrook St N Cranbrook BC V1C 3S4",
    "addr:housenumber":"1111",
    "addr:postcode":"v1c 3s4",
    "addr:street":"Cranbrook St N",
    "iso:country":"CA",
    "sg:address":"1111 Cranbrook St N",
    "sg:city":"Cranbrook",
    "sg:classifiers":[
        {
            "category":"Retail",
            "subcategory":"Self-service Laundry",
            "type":"Services"
        }
    ],
    "sg:phone":"+1 250 426 2296",
    "sg:postcode":"V1C 3S4",
    "sg:province":"BC",
    "wof:name":"Suds & Duds Laundromat",
    "wof:placetype":"venue"
},
  "geometry": {"coordinates":[-115.756355286,49.5224456787],"type":"Point"}
}