{
  "type": "Feature",
  "properties": {
    "addr:full":"Vernon BC V1T 5B8",
    "addr:postcode":"v1t 5b8",
    "iso:country":"CA",
    "sg:city":"Vernon",
    "sg:classifiers":[
        {
            "category":"Retail",
            "subcategory":"Auto Repair",
            "type":"Services"
        }
    ],
    "sg:phone":"+1 250 542 5494",
    "sg:postcode":"V1T 5B8",
    "sg:province":"BC",
    "sg:tags":[
        "repairing",
        "automobile",
        "injection",
        "fuel",
        "equipment"
    ],
    "wof:name":"Abernathy's Service Ltd",
    "wof:placetype":"venue"
},
  "geometry": {"coordinates":[-119.27021000000001,50.276375],"type":"Point"}
}