{
  "type": "Feature",
  "properties": {
    "addr:full":"9 Front St W Strathroy ON N7G 1X5",
    "addr:housenumber":"9",
    "addr:postcode":"n7g 1x5",
    "addr:street":"Front St W",
    "iso:country":"CA",
    "sg:address":"9 Front St W",
    "sg:city":"Strathroy",
    "sg:classifiers":[
        {
            "category":"Shopping",
            "subcategory":"Used Merchandise",
            "type":"Retail Goods"
        }
    ],
    "sg:phone":"+1 519 245 7287",
    "sg:postcode":"N7G 1X5",
    "sg:province":"ON",
    "sg:tags":[
        "second",
        "store",
        "hand"
    ],
    "wof:name":"Keepers",
    "wof:placetype":"venue"
},
  "geometry": {"coordinates":[-81.6245422363,42.9585189819],"type":"Point"}
}