{
  "type": "Feature",
  "properties": {
    "addr:full":"716 Ch Des Pionniers Cap-Saint-Ignace QC G0R 1H0",
    "addr:housenumber":"716",
    "addr:postcode":"g0r 1h0",
    "addr:street":"Ch Des Pionniers",
    "iso:country":"CA",
    "sg:address":"716 Ch Des Pionniers",
    "sg:city":"Cap-Saint-Ignace",
    "sg:classifiers":[
        {
            "category":"Retail",
            "subcategory":"Auto Repair",
            "type":"Services"
        }
    ],
    "sg:phone":"+1 418 246 5829",
    "sg:postcode":"G0R 1H0",
    "sg:province":"QC",
    "sg:tags":[
        "body",
        "automobile",
        "painting"
    ],
    "wof:name":"Garage Soins DE L'Auto Enr",
    "wof:placetype":"venue"
},
  "geometry": {"coordinates":[-70.45018,47.065414],"type":"Point"}
}