{
  "type": "Feature",
  "properties": {
    "addr:full":"2150 Windsor St Halifax NS B3K 5B6",
    "addr:housenumber":"2150",
    "addr:postcode":"b3k 5b6",
    "addr:street":"Windsor St",
    "iso:country":"CA",
    "sg:address":"2150 Windsor St",
    "sg:city":"Halifax",
    "sg:classifiers":[
        {
            "category":"Food & Beverages",
            "subcategory":"Groceries & Convenience Stores",
            "type":"Retail Goods"
        }
    ],
    "sg:phone":"+1 902 429 6464",
    "sg:postcode":"B3K 5B6",
    "sg:province":"NS",
    "sg:tags":[
        "video",
        "disc",
        "tape"
    ],
    "wof:name":"Showtime Video & Variety",
    "wof:placetype":"venue"
},
  "geometry": {"coordinates":[-63.5944976807,44.6493759155],"type":"Point"}
}