{
  "type": "Feature",
  "properties": {
    "iso:country":"CA",
    "sg:address":"43 Rue Saint-Eugene",
    "sg:city":"Varennes",
    "sg:classifiers":[
        {
            "category":"Retail",
            "subcategory":"Portrait Studio",
            "type":"Services"
        }
    ],
    "sg:phone":"+1 450 652 9743",
    "sg:postcode":"J3X 1E3",
    "sg:province":"QC",
    "sg:tags":[
        "photo",
        "finishing"
    ],
    "wof:name":"Atelier-Photographie-Varennois",
    "wof:placetype":"venue"
},
  "geometry": {"coordinates":[-73.43742370610001,45.681022644],"type":"Point"}
}