{
  "type": "Feature",
  "properties": {
    "iso:country":"CA",
    "sg:address":"1980 Hwy 20",
    "sg:city":"Fonthill",
    "sg:classifiers":[
        {
            "category":"Shopping",
            "subcategory":"Books",
            "type":"Retail Goods"
        }
    ],
    "sg:phone":"+1 905 892 3164",
    "sg:postcode":"L0S 1E6",
    "sg:province":"ON",
    "sg:tags":[
        "dealer"
    ],
    "wof:name":"Christian Book Corner",
    "wof:placetype":"venue"
},
  "geometry": {"coordinates":[-79.31098937989999,43.0434188843],"type":"Point"}
}