{
  "type": "Feature",
  "properties": {
    "addr:full":"240 Sixth Ave Bassano AB T0J 0B0",
    "addr:housenumber":"240",
    "addr:postcode":"t0j 0b0",
    "addr:street":"Sixth Ave",
    "iso:country":"CA",
    "sg:address":"240 Sixth Ave",
    "sg:city":"Bassano",
    "sg:classifiers":[
        {
            "category":"Education",
            "subcategory":"School",
            "type":"Public Place"
        }
    ],
    "sg:phone":"+1 403 641 3577",
    "sg:postcode":"T0J 0B0",
    "sg:province":"AB",
    "wof:name":"Bassano School",
    "wof:placetype":"venue"
},
  "geometry": {"coordinates":[-112.474113464,50.7906303406],"type":"Point"}
}