{
  "type": "Feature",
  "properties": {
    "iso:country":"CA",
    "sg:city":"Burnaby",
    "sg:classifiers":[
        {
            "category":"Bars & Pubs",
            "type":"Food & Drink"
        }
    ],
    "sg:phone":"+1 604 433 8942",
    "sg:postcode":"V5H 2G4",
    "sg:province":"BC",
    "wof:name":"Delaney's Pub",
    "wof:placetype":"venue"
},
  "geometry": {"coordinates":[-122.981529236,49.2228355408],"type":"Point"}
}