{
  "type": "Feature",
  "properties": {
    "addr:full":"Toronto ON M4J 1N5",
    "addr:postcode":"m4j 1n5",
    "iso:country":"CA",
    "sg:city":"Toronto",
    "sg:classifiers":[
        {
            "category":"Health Services",
            "subcategory":"Doctor",
            "type":"Services"
        }
    ],
    "sg:phone":"+1 416 466 3035",
    "sg:postcode":"M4J 1N5",
    "sg:province":"ON",
    "sg:tags":[
        "physician",
        "surgeon"
    ],
    "wof:name":"Scala, Sam J MD",
    "wof:placetype":"venue"
},
  "geometry": {"coordinates":[-79.3259048462,43.6827163696],"type":"Point"}
}