{
  "type": "Feature",
  "properties": {
    "addr:full":"1865 Leslie St North York ON M3B 2M3",
    "addr:housenumber":"1865",
    "addr:postcode":"m3b 2m3",
    "addr:street":"Leslie St",
    "iso:country":"CA",
    "sg:address":"1865 Leslie St",
    "sg:city":"North York",
    "sg:classifiers":[
        {
            "category":"Personal",
            "subcategory":"Beauty Salon",
            "type":"Services"
        }
    ],
    "sg:phone":"+1 416 443 2690",
    "sg:postcode":"M3B 2M3",
    "sg:province":"ON",
    "wof:name":"St George Hair Salon",
    "wof:placetype":"venue"
},
  "geometry": {"coordinates":[-79.360283,43.7551],"type":"Point"}
}