{
  "type": "Feature",
  "properties": {
    "addr:full":"412 Rue Minto Sherbrooke QC J1H 1T6",
    "addr:housenumber":"412",
    "addr:postcode":"j1h 1t6",
    "addr:street":"Rue Minto",
    "iso:country":"CA",
    "sg:address":"412 Rue Minto",
    "sg:city":"Sherbrooke",
    "sg:classifiers":[
        {
            "category":"Social Services",
            "subcategory":"Job Training",
            "type":"Services"
        }
    ],
    "sg:phone":"+1 819 822 4114",
    "sg:postcode":"J1H 1T6",
    "sg:province":"QC",
    "sg:tags":[
        "employment"
    ],
    "wof:name":"Contact",
    "wof:placetype":"venue"
},
  "geometry": {"coordinates":[-71.895065,45.397552],"type":"Point"}
}