{
  "type": "Feature",
  "properties": {
    "addr:full":"Edmonton AB T5J 4C3",
    "addr:postcode":"t5j 4c3",
    "iso:country":"CA",
    "sg:city":"Edmonton",
    "sg:classifiers":[
        {
            "category":"Restaurant",
            "type":"Food & Drink"
        }
    ],
    "sg:phone":"+1 780 426 7380",
    "sg:postcode":"T5J 4C3",
    "sg:province":"AB",
    "wof:name":"Mr Donair & Sub",
    "wof:placetype":"venue"
},
  "geometry": {"coordinates":[-113.48584,53.542244],"type":"Point"}
}