{
  "type": "Feature",
  "properties": {
    "addr:full":"82 Waterbridge Dr Nepean ON K2G 6T3",
    "addr:housenumber":"82",
    "addr:postcode":"k2g 6t3",
    "addr:street":"Waterbridge Dr",
    "iso:country":"CA",
    "sg:address":"82 Waterbridge Dr",
    "sg:city":"Nepean",
    "sg:classifiers":[
        {
            "category":"Organizations",
            "subcategory":"Non-profit Organization",
            "type":"Services"
        }
    ],
    "sg:phone":"+1 613 843 9212",
    "sg:postcode":"K2G 6T3",
    "sg:province":"ON",
    "sg:tags":[
        "charitable",
        "institution"
    ],
    "wof:name":"Victoriaos Quilts Canada",
    "wof:placetype":"venue"
},
  "geometry": {"coordinates":[-75.70925099999999,45.28117],"type":"Point"}
}