{
  "type": "Feature",
  "properties": {
    "iso:country":"CA",
    "sg:address":"82 Waterbridge Dr",
    "sg:city":"Nepean",
    "sg:classifiers":[
        {
            "category":"Organizations",
            "subcategory":"Non-profit Organization",
            "type":"Services"
        }
    ],
    "sg:phone":"+1 613 843 9212",
    "sg:postcode":"K2G 6T3",
    "sg:province":"ON",
    "sg:tags":[
        "charitable",
        "institution"
    ],
    "wof:name":"Victoriaos Quilts Canada",
    "wof:placetype":"venue"
},
  "geometry": {"coordinates":[-75.709251,45.28117],"type":"Point"}
}