{
  "type": "Feature",
  "properties": {
    "addr:full":"37 Av Du Saut Sainte-Helene-DE-Breakeyville QC G0S 1E3",
    "addr:postcode":"g0s 1e3",
    "addr:street":"37 Av Du Saut Sainte-Helene-De-Breakeyville",
    "iso:country":"CA",
    "sg:address":"37 Av Du Saut",
    "sg:city":"Sainte-Helene-DE-Breakeyville",
    "sg:classifiers":[
        {
            "category":"Manufacturing",
            "subcategory":"Tools & Machinery",
            "type":"Manufacturing & Wholesale Goods"
        }
    ],
    "sg:phone":"+1 418 832 1415",
    "sg:postcode":"G0S 1E3",
    "sg:province":"QC",
    "sg:tags":[
        "filter"
    ],
    "wof:name":"Filtrindustries",
    "wof:placetype":"venue"
},
  "geometry": {"coordinates":[-71.239525,46.654659],"type":"Point"}
}