{
  "type": "Feature",
  "properties": {
    "addr:full":"Whitecourt AB T7S 1P8",
    "addr:postcode":"t7s 1p8",
    "iso:country":"CA",
    "sg:city":"Whitecourt",
    "sg:classifiers":[
        {
            "category":"Retail",
            "subcategory":"Auto Repair",
            "type":"Services"
        }
    ],
    "sg:phone":"+1 780 778 2770",
    "sg:postcode":"T7S 1P8",
    "sg:province":"AB",
    "sg:tags":[
        "repairing",
        "engine"
    ],
    "wof:name":"Conrad's Shop",
    "wof:placetype":"venue"
},
  "geometry": {"coordinates":[-115.68717956499999,54.1382789612],"type":"Point"}
}