{
  "type": "Feature",
  "properties": {
    "addr:full":"242 Montee Gagnon Sainte-Anne-Des-Plaines QC J0N 1H0",
    "addr:housenumber":"242",
    "addr:postcode":"j0n 1h0",
    "addr:street":"Montee Gagnon",
    "iso:country":"CA",
    "sg:address":"242 Montee Gagnon",
    "sg:city":"Sainte-Anne-Des-Plaines",
    "sg:classifiers":[
        {
            "category":"Government",
            "subcategory":"Office",
            "type":"Public Place"
        }
    ],
    "sg:phone":"+1 450 478 5960",
    "sg:postcode":"J0N 1H0",
    "sg:province":"QC",
    "wof:name":"Canada Etablissement Archambau",
    "wof:placetype":"venue"
},
  "geometry": {"coordinates":[-73.82563,45.742107],"type":"Point"}
}