{
  "type": "Feature",
  "properties": {
    "addr:full":"165 Av Saint-Rene Saint-Rene-DE-Matane QC G0J 3E0",
    "addr:housenumber":"165",
    "addr:postcode":"g0j 3e0",
    "addr:street":"Av Saint-Rene Saint-Rene-De-Matane",
    "iso:country":"CA",
    "sg:address":"165 Av Saint-Rene",
    "sg:city":"Saint-Rene-DE-Matane",
    "sg:classifiers":[
        {
            "category":"Education",
            "subcategory":"School",
            "type":"Public Place"
        }
    ],
    "sg:phone":"+1 418 224 3372",
    "sg:postcode":"G0J 3E0",
    "sg:province":"QC",
    "wof:name":"Ecole Saint-Rene-Goupil",
    "wof:placetype":"venue"
},
  "geometry": {"coordinates":[-67.387978,48.706921],"type":"Point"}
}