{
  "type": "Feature",
  "properties": {
    "addr:full":"101 3rd Ave N Craik SK S0G 0V0",
    "addr:housenumber":"101",
    "addr:postcode":"s0g 0v0",
    "addr:street":"3Rd Ave N Craik",
    "iso:country":"CA",
    "sg:address":"101 3rd Ave N",
    "sg:city":"Craik",
    "sg:classifiers":[
        {
            "category":"Wholesale",
            "subcategory":"Machinery & Supplies",
            "type":"Manufacturing & Wholesale Goods"
        }
    ],
    "sg:phone":"+1 306 734 2228",
    "sg:postcode":"S0G 0V0",
    "sg:province":"SK",
    "sg:tags":[
        "agricultural",
        "implement"
    ],
    "wof:name":"Glen's Grain Vac Svc",
    "wof:placetype":"venue"
},
  "geometry": {"coordinates":[-105.82261657700001,51.047164917],"type":"Point"}
}