{
  "type": "Feature",
  "properties": {
    "addr:full":"6949 Hwy 17 Desbarats ON P0R 1E0",
    "addr:housenumber":"6949",
    "addr:postcode":"p0r 1e0",
    "addr:street":"Hwy 17 Desbarats",
    "iso:country":"CA",
    "sg:address":"6949 Hwy 17",
    "sg:city":"Desbarats",
    "sg:classifiers":[
        {
            "category":"Autos & Motor Vehicles",
            "subcategory":"Automobile Sales",
            "type":"Retail Goods"
        }
    ],
    "sg:phone":"+1 705 782 0123",
    "sg:postcode":"P0R 1E0",
    "sg:province":"ON",
    "sg:tags":[
        "car",
        "dealer"
    ],
    "wof:name":"Grand North Auto & Equipment",
    "wof:placetype":"venue"
},
  "geometry": {"coordinates":[-83.93305969239999,46.3421096802],"type":"Point"}
}