{
  "type": "Feature",
  "properties": {
    "addr:full":"1283 Rue Notre-Dame E Victoriaville QC G6P 4B8",
    "addr:housenumber":"1283",
    "addr:postcode":"g6p 4b8",
    "addr:street":"Rue Notre-Dame E",
    "iso:country":"CA",
    "sg:address":"1283 Rue Notre-Dame E",
    "sg:city":"Victoriaville",
    "sg:classifiers":[
        {
            "category":"Retail",
            "subcategory":"Auto Repair",
            "type":"Services"
        }
    ],
    "sg:phone":"+1 819 758 7373",
    "sg:postcode":"G6P 4B8",
    "sg:province":"QC",
    "sg:tags":[
        "repairing",
        "automobile",
        "truck"
    ],
    "wof:name":"Garage Piche Desjardins Inc",
    "wof:placetype":"venue"
},
  "geometry": {"coordinates":[-71.934448,46.071552],"type":"Point"}
}