{
  "type": "Feature",
  "properties": {
    "addr:full":"1905 Rue DE Cadillac Montreal QC H1N 2T4",
    "addr:housenumber":"1905",
    "addr:postcode":"h1n 2t4",
    "addr:street":"Rue De Cadillac",
    "iso:country":"CA",
    "sg:address":"1905 Rue DE Cadillac",
    "sg:city":"Montreal",
    "sg:classifiers":[
        {
            "category":"Organizations",
            "subcategory":"Professional Association",
            "type":"Services"
        }
    ],
    "sg:phone":"+1 514 251 7636",
    "sg:postcode":"H1N 2T4",
    "sg:province":"QC",
    "wof:name":"Conseil DE Loisirs Scientifiq",
    "wof:placetype":"venue"
},
  "geometry": {"coordinates":[-73.52694700000001,45.570465],"type":"Point"}
}