{
  "type": "Feature",
  "properties": {
    "addr:full":"2345 Main St London ON N6P 1A7",
    "addr:housenumber":"2345",
    "addr:postcode":"n6p 1a7",
    "addr:street":"Main St",
    "iso:country":"CA",
    "sg:address":"2345 Main St",
    "sg:city":"London",
    "sg:classifiers":[
        {
            "category":"Home & Garden",
            "subcategory":"Home Furnishings",
            "type":"Retail Goods"
        }
    ],
    "sg:phone":"+1 519 652 9650",
    "sg:postcode":"N6P 1A7",
    "sg:province":"ON",
    "sg:tags":[
        "curtain",
        "made",
        "drapery"
    ],
    "wof:name":"Creative Decor",
    "wof:placetype":"venue"
},
  "geometry": {"coordinates":[-81.293205,42.911446],"type":"Point"}
}