{
  "type": "Feature",
  "properties": {
    "addr:full":"65 Amelia St Barrie ON L4M 1M7",
    "addr:housenumber":"65",
    "addr:postcode":"l4m 1m7",
    "addr:street":"Amelia St",
    "iso:country":"CA",
    "sg:address":"65 Amelia St",
    "sg:city":"Barrie",
    "sg:classifiers":[
        {
            "category":"Organizations",
            "subcategory":"Religious Organization",
            "type":"Services"
        }
    ],
    "sg:phone":"+1 705 728 2985",
    "sg:postcode":"L4M 1M7",
    "sg:province":"ON",
    "sg:tags":[
        "church"
    ],
    "wof:name":"St Mary's Church",
    "wof:placetype":"venue"
},
  "geometry": {"coordinates":[-79.6785354614,44.3938865662],"type":"Point"}
}