{
  "type": "Feature",
  "properties": {
    "addr:full":"2882 Ellesmere Rd Scarborough ON M1E 4B8",
    "addr:housenumber":"2882",
    "addr:postcode":"m1e 4b8",
    "addr:street":"Ellesmere Rd",
    "iso:country":"CA",
    "sg:address":"2882 Ellesmere Rd",
    "sg:city":"Scarborough",
    "sg:classifiers":[
        {
            "category":"Personal",
            "subcategory":"Beauty Salon",
            "type":"Services"
        }
    ],
    "sg:phone":"+1 416 284 0197",
    "sg:postcode":"M1E 4B8",
    "sg:province":"ON",
    "wof:name":"Oggi Hair Fashion",
    "wof:placetype":"venue"
},
  "geometry": {"coordinates":[-79.203598,43.783066],"type":"Point"}
}