{
  "type": "Feature",
  "properties": {
    "iso:country":"CA",
    "sg:address":"5004 50th St",
    "sg:city":"Vilna",
    "sg:classifiers":[
        {
            "category":"Shopping",
            "subcategory":"Discount & Variety Stores",
            "type":"Retail Goods"
        }
    ],
    "sg:phone":"+1 780 636 3505",
    "sg:postcode":"T0A 3L0",
    "sg:province":"AB",
    "sg:tags":[
        "merchandise",
        "general"
    ],
    "wof:name":"Vilna True Value Hardware",
    "wof:placetype":"venue"
},
  "geometry": {"coordinates":[-111.92082977299999,54.1156997681],"type":"Point"}
}