{
  "type": "Feature",
  "properties": {
    "addr:full":"Abbotsford BC V2S 2C6",
    "addr:postcode":"v2s 2c6",
    "iso:country":"CA",
    "sg:city":"Abbotsford",
    "sg:classifiers":[
        {
            "category":"Education",
            "subcategory":"Dance Studio",
            "type":"Public Place"
        }
    ],
    "sg:phone":"+1 604 852 8780",
    "sg:postcode":"V2S 2C6",
    "sg:province":"BC",
    "sg:tags":[
        "instruction",
        "dancing"
    ],
    "wof:name":"Dance in Motion",
    "wof:placetype":"venue"
},
  "geometry": {"coordinates":[-122.28061700000001,49.041763],"type":"Point"}
}