{
  "type": "Feature",
  "properties": {
    "iso:country":"CA",
    "sg:city":"Scarborough",
    "sg:classifiers":[
        {
            "category":"Manufacturing",
            "subcategory":"Furniture",
            "type":"Manufacturing & Wholesale Goods"
        }
    ],
    "sg:phone":"+1 416 321 8876",
    "sg:postcode":"M1X 1L5",
    "sg:province":"ON",
    "sg:tags":[
        "equipment",
        "supply"
    ],
    "wof:name":"Emerald Restaurant Equipment",
    "wof:placetype":"venue"
},
  "geometry": {"coordinates":[-79.24626159669999,43.8211097717],"type":"Point"}
}