{
  "type": "Feature",
  "properties": {
    "addr:full":"Aklavik NT X0E 0A0",
    "addr:postcode":"x0e 0a0",
    "iso:country":"CA",
    "sg:city":"Aklavik",
    "sg:classifiers":[
        {
            "category":"Travel",
            "subcategory":"Hotels & Motels",
            "type":"Entertainment"
        }
    ],
    "sg:phone":"+1 867 978 2205",
    "sg:postcode":"X0E 0A0",
    "sg:province":"NT",
    "sg:tags":[
        "grocer"
    ],
    "wof:name":"Aklavik General Store",
    "wof:placetype":"venue"
},
  "geometry": {"coordinates":[-135.013351,68.217545],"type":"Point"}
}