{
  "type": "Feature",
  "properties": {
    "addr:full":"813 18A Ave N Cranbrook BC V1C 3Y1",
    "addr:postcode":"v1c 3y1",
    "addr:street":"813 18A Ave N",
    "iso:country":"CA",
    "sg:address":"813 18A Ave N",
    "sg:city":"Cranbrook",
    "sg:classifiers":[
        {
            "category":"Building & Trades",
            "subcategory":"Construction",
            "type":"Services"
        }
    ],
    "sg:phone":"+1 250 426 5832",
    "sg:postcode":"V1C 3Y1",
    "sg:province":"BC",
    "sg:tags":[
        "repairing",
        "remodeling",
        "contractor"
    ],
    "wof:name":"R & K Renovations",
    "wof:placetype":"venue"
},
  "geometry": {"coordinates":[-115.755958557,49.5195732117],"type":"Point"}
}