{
  "type": "Feature",
  "properties": {
    "addr:full":"535 Rue Saint-Georges Saint-Jerome QC J7Z 5B7",
    "addr:housenumber":"535",
    "addr:postcode":"j7z 5b7",
    "addr:street":"Rue Saint-Georges Saint-Jerome",
    "iso:country":"CA",
    "sg:address":"535 Rue Saint-Georges",
    "sg:city":"Saint-Jerome",
    "sg:classifiers":[
        {
            "category":"Retail",
            "subcategory":"Laundry & Dry Cleaning",
            "type":"Services"
        }
    ],
    "sg:phone":"+1 450 569 8091",
    "sg:postcode":"J7Z 5B7",
    "sg:province":"QC",
    "wof:name":"Buanderie Multi Svc",
    "wof:placetype":"venue"
},
  "geometry": {"coordinates":[-74.001503,45.782539],"type":"Point"}
}