{
  "type": "Feature",
  "properties": {
    "addr:full":"1695 Ch DE LA Canardiere Quebec QC G1J 2E1",
    "addr:housenumber":"1695",
    "addr:postcode":"g1j 2e1",
    "addr:street":"Ch De La Canardiere",
    "iso:country":"CA",
    "sg:address":"1695 Ch DE LA Canardiere",
    "sg:city":"Quebec",
    "sg:classifiers":[
        {
            "category":"Retail",
            "subcategory":"Portrait Studio",
            "type":"Services"
        }
    ],
    "sg:phone":"+1 418 667 1222",
    "sg:postcode":"G1J 2E1",
    "sg:province":"QC",
    "sg:tags":[
        "photographer"
    ],
    "wof:name":"Studio Phos",
    "wof:placetype":"venue"
},
  "geometry": {"coordinates":[-71.222313,46.83754],"type":"Point"}
}