{
  "type": "Feature",
  "properties": {
    "addr:full":"130 Main St N Brampton ON L6V 1N8",
    "addr:housenumber":"130",
    "addr:postcode":"l6v 1n8",
    "addr:street":"Main St N",
    "iso:country":"CA",
    "sg:address":"130 Main St N",
    "sg:city":"Brampton",
    "sg:classifiers":[
        {
            "category":"Shopping",
            "subcategory":"Gifts & Souvenirs",
            "type":"Retail Goods"
        }
    ],
    "sg:phone":"+1 905 453 3733",
    "sg:postcode":"L6V 1N8",
    "sg:province":"ON",
    "sg:tags":[
        "novelty"
    ],
    "wof:name":"Aren't We Naughty",
    "wof:placetype":"venue"
},
  "geometry": {"coordinates":[-79.76251999999999,43.688004],"type":"Point"}
}