{
  "type": "Feature",
  "properties": {
    "addr:full":"360 Princess St Winnipeg MB R3B 1M6",
    "addr:housenumber":"360",
    "addr:postcode":"r3b 1m6",
    "addr:street":"Princess St",
    "iso:country":"CA",
    "sg:address":"360 Princess St",
    "sg:city":"Winnipeg",
    "sg:classifiers":[
        {
            "category":"Manufacturing",
            "subcategory":"Furniture",
            "type":"Manufacturing & Wholesale Goods"
        }
    ],
    "sg:phone":"+1 204 942 0127",
    "sg:postcode":"R3B 1M6",
    "sg:province":"MB",
    "wof:name":"Ambassador Furniture Ltd",
    "wof:placetype":"venue"
},
  "geometry": {"coordinates":[-97.13744354249999,49.9054985046],"type":"Point"}
}