{
  "type": "Feature",
  "properties": {
    "iso:country":"CA",
    "sg:city":"Aurora",
    "sg:classifiers":[
        {
            "category":"Manufacturing",
            "subcategory":"Tools & Machinery",
            "type":"Manufacturing & Wholesale Goods"
        }
    ],
    "sg:phone":"+1 905 713 3424",
    "sg:postcode":"L4G 6W1",
    "sg:province":"ON",
    "sg:tags":[
        "die",
        "maker"
    ],
    "wof:name":"Micro Quality Tool Ltd",
    "wof:placetype":"venue"
},
  "geometry": {"coordinates":[-79.44973,43.988953],"type":"Point"}
}