{
  "type": "Feature",
  "properties": {
    "addr:full":"145 Talbot St E Leamington ON N8H 1L8",
    "addr:housenumber":"145",
    "addr:postcode":"n8h 1l8",
    "addr:street":"Talbot St E",
    "iso:country":"CA",
    "sg:address":"145 Talbot St E",
    "sg:city":"Leamington",
    "sg:classifiers":[
        {
            "category":"Autos & Motor Vehicles",
            "subcategory":"Auto Supplies",
            "type":"Retail Goods"
        }
    ],
    "sg:phone":"+1 519 322 0609",
    "sg:postcode":"N8H 1L8",
    "sg:province":"ON",
    "sg:tags":[
        "automobile",
        "stereo",
        "radio"
    ],
    "wof:name":"Sound Designs",
    "wof:placetype":"venue"
},
  "geometry": {"coordinates":[-82.59317,42.054802],"type":"Point"}
}