{
  "type": "Feature",
  "properties": {
    "iso:country":"CA",
    "sg:address":"1025 Av DE L'Amiral",
    "sg:city":"Val-Belair",
    "sg:classifiers":[
        {
            "category":"Organizations",
            "subcategory":"Professional Association",
            "type":"Services"
        }
    ],
    "sg:phone":"+1 418 845 4489",
    "sg:postcode":"G3K 1C3",
    "sg:province":"QC",
    "wof:name":"Chevaliers DE Colomb",
    "wof:placetype":"venue"
},
  "geometry": {"coordinates":[-71.4595489502,46.8424186707],"type":"Point"}
}