{
  "type": "Feature",
  "properties": {
    "addr:full":"1200 8th St Kamloops BC V2B 2Y4",
    "addr:housenumber":"1200",
    "addr:postcode":"bc v2b 2y4",
    "addr:street":"8Th St",
    "iso:country":"CA",
    "sg:address":"1200 8th St",
    "sg:city":"Kamloops",
    "sg:classifiers":[
        {
            "category":"Sports & Exercise",
            "subcategory":"Bowling",
            "type":"Entertainment"
        }
    ],
    "sg:phone":"+1 250 554 1610",
    "sg:postcode":"V2B 2Y4",
    "sg:province":"BC",
    "sg:tags":[
        "center"
    ],
    "wof:name":"Bowlertime 5 Pin Bowling Ctr",
    "wof:placetype":"venue"
},
  "geometry": {"coordinates":[-120.364280701,50.7075157166],"type":"Point"}
}