{
  "type": "Feature",
  "properties": {
    "addr:full":"2450 Shore Rd Liverpool NS B0T 1K0",
    "addr:housenumber":"2450",
    "addr:postcode":"b0t 1k0",
    "addr:street":"Shore Rd",
    "iso:country":"CA",
    "sg:address":"2450 Shore Rd",
    "sg:city":"Liverpool",
    "sg:classifiers":[
        {
            "category":"Wholesale",
            "subcategory":"Auto Parts",
            "type":"Manufacturing & Wholesale Goods"
        }
    ],
    "sg:phone":"+1 902 354 2829",
    "sg:postcode":"B0T 1K0",
    "sg:province":"NS",
    "sg:tags":[
        "automobile",
        "rebuilt"
    ],
    "wof:name":"Western Head Auto Salvage",
    "wof:placetype":"venue"
},
  "geometry": {"coordinates":[-64.700653,44.022915],"type":"Point"}
}