{
  "type": "Feature",
  "properties": {
    "addr:full":"567 Rue Jarry O Montreal QC H3N 1G1",
    "addr:housenumber":"567",
    "addr:postcode":"h3n 1g1",
    "addr:street":"Rue Jarry O",
    "iso:country":"CA",
    "sg:address":"567 Rue Jarry O",
    "sg:city":"Montreal",
    "sg:classifiers":[
        {
            "category":"Social Services",
            "subcategory":"Child Care",
            "type":"Services"
        }
    ],
    "sg:phone":"+1 514 270 7256",
    "sg:postcode":"H3N 1G1",
    "sg:province":"QC",
    "wof:name":"Garderie Marie Inc",
    "wof:placetype":"venue"
},
  "geometry": {"coordinates":[-73.62854799999999,45.544037],"type":"Point"}
}