{
  "type": "Feature",
  "properties": {
    "addr:full":"Mississauga ON L5S 1J9",
    "addr:postcode":"l5s 1j9",
    "iso:country":"CA",
    "sg:city":"Mississauga",
    "sg:classifiers":[
        {
            "category":"Shopping",
            "subcategory":"Hobbies, Toys, & Games",
            "type":"Retail Goods"
        }
    ],
    "sg:phone":"+1 905 673 3315",
    "sg:postcode":"L5S 1J9",
    "sg:province":"ON",
    "sg:tags":[
        "equipment",
        "aircraft",
        "parts",
        "model",
        "supply"
    ],
    "wof:name":"Threshold Aviation",
    "wof:placetype":"venue"
},
  "geometry": {"coordinates":[-79.655921936,43.6950569153],"type":"Point"}
}