{
  "type": "Feature",
  "properties": {
    "iso:country":"CA",
    "sg:address":"12998 Keele St",
    "sg:city":"King City",
    "sg:classifiers":[
        {
            "category":"Restaurant",
            "type":"Food & Drink"
        }
    ],
    "sg:phone":"+1 905 833 5311",
    "sg:postcode":"L7B 1H8",
    "sg:province":"ON",
    "sg:tags":[
        "caterer"
    ],
    "wof:name":"Hogan's Inn At Four Corners",
    "wof:placetype":"venue"
},
  "geometry": {"coordinates":[-79.528244,43.928112],"type":"Point"}
}