{
  "type": "Feature",
  "properties": {
    "addr:full":"2200 Nadina Ave Houston BC V0J 1Z0",
    "addr:housenumber":"2200",
    "addr:postcode":"v0j 1z0",
    "addr:street":"Nadina Ave",
    "iso:country":"CA",
    "sg:address":"2200 Nadina Ave",
    "sg:city":"Houston",
    "sg:classifiers":[
        {
            "category":"Wholesale",
            "subcategory":"Machinery & Supplies",
            "type":"Manufacturing & Wholesale Goods"
        }
    ],
    "sg:phone":"+1 250 845 2333",
    "sg:postcode":"V0J 1Z0",
    "sg:province":"BC",
    "wof:name":"Parker Pacific",
    "wof:placetype":"venue"
},
  "geometry": {"coordinates":[-126.66679382300001,54.394443512],"type":"Point"}
}