{
  "type": "Feature",
  "properties": {
    "iso:country":"CA",
    "sg:address":"43064 Mackenzie Hwy",
    "sg:city":"Hay River",
    "sg:phone":"+1 867 874 2215",
    "sg:postcode":"X0E 0R9",
    "sg:province":"NT",
    "sg:tags":[
        "oil"
    ],
    "wof:name":"Petro-Canada",
    "wof:placetype":"venue"
},
  "geometry": {"coordinates":[-115.788757,60.813107],"type":"Point"}
}