{
  "type": "Feature",
  "properties": {
    "iso:country":"CA",
    "sg:city":"Oakville",
    "sg:classifiers":[
        {
            "category":"Wholesale",
            "subcategory":"Durable Goods & Equipment",
            "type":"Manufacturing & Wholesale Goods"
        }
    ],
    "sg:phone":"+1 905 855 8550",
    "sg:postcode":"L6J 7K1",
    "sg:province":"ON",
    "sg:tags":[
        "representative",
        "manufacturer"
    ],
    "wof:name":"Mcdonald Sales & Merchandising",
    "wof:placetype":"venue"
},
  "geometry": {"coordinates":[-79.6664352417,43.5044326782],"type":"Point"}
}