{
  "type": "Feature",
  "properties": {
    "iso:country":"CA",
    "sg:city":"Maple",
    "sg:classifiers":[
        {
            "category":"Food & Beverages",
            "subcategory":"Bakery",
            "type":"Retail Goods"
        }
    ],
    "sg:phone":"+1 905 832 9787",
    "sg:postcode":"L6A 1W3",
    "sg:province":"ON",
    "sg:tags":[
        "baker"
    ],
    "wof:name":"Maple Gate Italian Bakery",
    "wof:placetype":"venue"
},
  "geometry": {"coordinates":[-79.509262085,43.8420639038],"type":"Point"}
}