{
  "type": "Feature",
  "properties": {
    "addr:full":"194 Goulding Ave North York ON M2R 2P4",
    "addr:housenumber":"194",
    "addr:postcode":"m2r 2p4",
    "addr:street":"Goulding Ave",
    "iso:country":"CA",
    "sg:address":"194 Goulding Ave",
    "sg:city":"North York",
    "sg:classifiers":[
        {
            "category":"Building & Trades",
            "subcategory":"Construction",
            "type":"Services"
        }
    ],
    "sg:phone":"+1 905 470 0482",
    "sg:postcode":"M2R 2P4",
    "sg:province":"ON",
    "sg:tags":[
        "excavating",
        "contractor"
    ],
    "wof:name":"Gabriel Excavating Ltd",
    "wof:placetype":"venue"
},
  "geometry": {"coordinates":[-79.43478399999999,43.788589],"type":"Point"}
}