{
  "type": "Feature",
  "properties": {
    "addr:full":"380 Rue St-Francois Edmundston NB E3V 1G6",
    "addr:housenumber":"380",
    "addr:postcode":"e3v 1g6",
    "addr:street":"Rue St-Francois",
    "iso:country":"CA",
    "sg:address":"380 Rue St-Francois",
    "sg:city":"Edmundston",
    "sg:classifiers":[
        {
            "category":"Professional",
            "subcategory":"Accounting & Tax Preparation",
            "type":"Services"
        }
    ],
    "sg:phone":"+1 506 735 4711",
    "sg:postcode":"E3V 1G6",
    "sg:province":"NB",
    "sg:tags":[
        "return",
        "filing"
    ],
    "wof:name":"H & R Block Canada Inc",
    "wof:placetype":"venue"
},
  "geometry": {"coordinates":[-68.34420799999999,47.359924],"type":"Point"}
}