{
  "type": "Feature",
  "properties": {
    "addr:full":"5000 8th Ave Regina SK S4T 0W3",
    "addr:housenumber":"5000",
    "addr:postcode":"s4t 0w3",
    "addr:street":"8Th Ave",
    "iso:country":"CA",
    "sg:address":"5000 8th Ave",
    "sg:city":"Regina",
    "sg:classifiers":[
        {
            "category":"Organizations",
            "subcategory":"Religious Organization",
            "type":"Services"
        }
    ],
    "sg:phone":"+1 306 545 2511",
    "sg:postcode":"S4T 0W3",
    "sg:province":"SK",
    "sg:tags":[
        "church"
    ],
    "wof:name":"Rosemont United Church",
    "wof:placetype":"venue"
},
  "geometry": {"coordinates":[-104.652649,50.456974],"type":"Point"}
}