{
  "type": "Feature",
  "properties": {
    "addr:full":"500 Rue Upper Edison Saint-Lambert QC J4R 2V5",
    "addr:housenumber":"500",
    "addr:postcode":"j4r 2v5",
    "addr:street":"Rue Upper Edison",
    "iso:country":"CA",
    "sg:address":"500 Rue Upper Edison",
    "sg:city":"Saint-Lambert",
    "sg:classifiers":[
        {
            "category":"Building & Trades",
            "subcategory":"Landscaping Services",
            "type":"Services"
        }
    ],
    "sg:phone":"+1 450 672 5518",
    "sg:postcode":"J4R 2V5",
    "sg:province":"QC",
    "sg:tags":[
        "tree"
    ],
    "wof:name":"Taille D'Arbres Ornementaux",
    "wof:placetype":"venue"
},
  "geometry": {"coordinates":[-73.49443100000001,45.502197],"type":"Point"}
}