{
  "type": "Feature",
  "properties": {
    "addr:full":"523 Antwerp Ave Sudbury ON P3C 4M9",
    "addr:housenumber":"523",
    "addr:postcode":"p3c 4m9",
    "addr:street":"Antwerp Ave",
    "iso:country":"CA",
    "sg:address":"523 Antwerp Ave",
    "sg:city":"Sudbury",
    "sg:classifiers":[
        {
            "category":"Organizations",
            "subcategory":"Religious Organization",
            "type":"Services"
        }
    ],
    "sg:phone":"+1 705 670 1934",
    "sg:postcode":"P3C 4M9",
    "sg:province":"ON",
    "sg:tags":[
        "church"
    ],
    "wof:name":"Jovanovic, M",
    "wof:placetype":"venue"
},
  "geometry": {"coordinates":[-81.0020980835,46.5035552979],"type":"Point"}
}