{
  "type": "Feature",
  "properties": {
    "addr:full":"1250 Rue Principale E Sainte-Agathe-Des-Monts QC J8C 1L9",
    "addr:housenumber":"1250",
    "addr:postcode":"j8c 1l9",
    "addr:street":"Rue Principale E Sainte-Agathe-Des-Monts",
    "iso:country":"CA",
    "sg:address":"1250 Rue Principale E",
    "sg:city":"Sainte-Agathe-Des-Monts",
    "sg:classifiers":[
        {
            "category":"Freight",
            "type":"Transportation"
        }
    ],
    "sg:phone":"+1 819 326 1353",
    "sg:postcode":"J8C 1L9",
    "sg:province":"QC",
    "sg:tags":[
        "trucking",
        "automobile",
        "parts",
        "supply"
    ],
    "wof:name":"Pieces D'Autos Ste Agathe Inc",
    "wof:placetype":"venue"
},
  "geometry": {"coordinates":[-74.260338,46.042702],"type":"Point"}
}