{
  "type": "Feature",
  "properties": {
    "addr:full":"Vulcan AB T0L 2B0",
    "addr:postcode":"t0l 2b0",
    "iso:country":"CA",
    "sg:city":"Vulcan",
    "sg:classifiers":[
        {
            "category":"Health Services",
            "subcategory":"Chiropractor",
            "type":"Services"
        }
    ],
    "sg:phone":"+1 403 485 2979",
    "sg:postcode":"T0L 2B0",
    "sg:province":"AB",
    "wof:name":"Vulcan Chiropractic Clinic",
    "wof:placetype":"venue"
},
  "geometry": {"coordinates":[-112.640022278,50.3497467041],"type":"Point"}
}