{
  "type": "Feature",
  "properties": {
    "addr:full":"175 Rue Commerciale Maniwaki QC J9E 1P1",
    "addr:housenumber":"175",
    "addr:postcode":"j9e 1p1",
    "addr:street":"Rue Commerciale",
    "iso:country":"CA",
    "sg:address":"175 Rue Commerciale",
    "sg:city":"Maniwaki",
    "sg:classifiers":[
        {
            "category":"Travel",
            "subcategory":"Hotels & Motels",
            "type":"Entertainment"
        }
    ],
    "sg:phone":"+1 819 449 1213",
    "sg:postcode":"J9E 1P1",
    "sg:province":"QC",
    "sg:tags":[
        "inn"
    ],
    "wof:name":"Auberge DE LA Desert",
    "wof:placetype":"venue"
},
  "geometry": {"coordinates":[-75.980293,46.374985],"type":"Point"}
}