{
  "type": "Feature",
  "properties": {
    "addr:full":"Railway St Matheson ON P0K 1N0",
    "addr:postcode":"p0k 1n0",
    "addr:street":"Railway St",
    "iso:country":"CA",
    "sg:address":"Railway St",
    "sg:city":"Matheson",
    "sg:classifiers":[
        {
            "category":"Government",
            "subcategory":"Police Station",
            "type":"Public Place"
        }
    ],
    "sg:phone":"+1 705 273 2213",
    "sg:postcode":"P0K 1N0",
    "sg:province":"ON",
    "sg:tags":[
        "department"
    ],
    "wof:name":"Ontario Provincial Police",
    "wof:placetype":"venue"
},
  "geometry": {"coordinates":[-80.4661560059,48.5347213745],"type":"Point"}
}