{
  "type": "Feature",
  "properties": {
    "addr:full":"5 Vata Crt Aurora ON L4G 4B6",
    "addr:housenumber":"5",
    "addr:postcode":"l4g 4b6",
    "addr:street":"Vata Crt",
    "iso:country":"CA",
    "sg:address":"5 Vata Crt",
    "sg:city":"Aurora",
    "sg:classifiers":[
        {
            "category":"Food & Beverages",
            "subcategory":"Meat & Fish",
            "type":"Retail Goods"
        }
    ],
    "sg:phone":"+1 905 727 8558",
    "sg:postcode":"L4G 4B6",
    "sg:province":"ON",
    "sg:tags":[
        "sausage"
    ],
    "wof:name":"Gourmet Sausage Inc",
    "wof:placetype":"venue"
},
  "geometry": {"coordinates":[-79.4579925537,43.9884185791],"type":"Point"}
}