{
  "type": "Feature",
  "properties": {
    "addr:full":"397 Danforth Ave Toronto ON M4K 1P1",
    "addr:housenumber":"397",
    "addr:postcode":"m4k 1p1",
    "addr:street":"Danforth Ave",
    "iso:country":"CA",
    "sg:address":"397 Danforth Ave",
    "sg:city":"Toronto",
    "sg:classifiers":[
        {
            "category":"Organizations",
            "subcategory":"Professional Association",
            "type":"Services"
        }
    ],
    "sg:phone":"+1 416 466 6256",
    "sg:postcode":"M4K 1P1",
    "sg:province":"ON",
    "wof:name":"Brotherhood of Pontion Assoc",
    "wof:placetype":"venue"
},
  "geometry": {"coordinates":[-79.35202,43.677429],"type":"Point"}
}