{
  "type": "Feature",
  "properties": {
    "addr:full":"Richmond BC V6X 2A9",
    "addr:postcode":"v6x 2a9",
    "iso:country":"CA",
    "sg:city":"Richmond",
    "sg:classifiers":[
        {
            "category":"Manufacturing",
            "subcategory":"Food",
            "type":"Manufacturing & Wholesale Goods"
        }
    ],
    "sg:phone":"+1 604 270 3885",
    "sg:postcode":"V6X 2A9",
    "sg:province":"BC",
    "sg:tags":[
        "grocer",
        "product",
        "manufacturer"
    ],
    "wof:name":"Brilliant Food Inc",
    "wof:placetype":"venue"
},
  "geometry": {"coordinates":[-123.139930725,49.1749649048],"type":"Point"}
}