{
  "type": "Feature",
  "properties": {
    "iso:country":"CA",
    "sg:address":"488 Cosburn Ave",
    "sg:city":"East York",
    "sg:classifiers":[
        {
            "category":"Restaurant",
            "type":"Food & Drink"
        }
    ],
    "sg:phone":"+1 416 422 4362",
    "sg:postcode":"M4J 2N5",
    "sg:province":"ON",
    "wof:name":"Paul's Spaghetti",
    "wof:placetype":"venue"
},
  "geometry": {"coordinates":[-79.333565,43.693016],"type":"Point"}
}