{
  "type": "Feature",
  "properties": {
    "addr:full":"1 Front St Alert Bay BC V0N 1A0",
    "addr:housenumber":"1",
    "addr:postcode":"v0n 1a0",
    "addr:street":"Front St",
    "iso:country":"CA",
    "sg:address":"1 Front St",
    "sg:city":"Alert Bay",
    "sg:classifiers":[
        {
            "category":"Museum",
            "type":"Entertainment"
        }
    ],
    "sg:phone":"+1 250 974 5403",
    "sg:postcode":"V0N 1A0",
    "sg:province":"BC",
    "wof:name":"U'Mista Museum",
    "wof:placetype":"venue"
},
  "geometry": {"coordinates":[-126.929962,50.587749],"type":"Point"}
}