{
  "type": "Feature",
  "properties": {
    "addr:full":"604 Stewart St Fort Frances ON P9A 2Y2",
    "addr:housenumber":"604",
    "addr:postcode":"p9a 2y2",
    "addr:street":"Stewart St",
    "iso:country":"CA",
    "sg:address":"604 Stewart St",
    "sg:city":"Fort Frances",
    "sg:classifiers":[
        {
            "category":"Food & Beverages",
            "subcategory":"Groceries & Convenience Stores",
            "type":"Retail Goods"
        }
    ],
    "sg:phone":"+1 807 274 7849",
    "sg:postcode":"P9A 2Y2",
    "sg:province":"ON",
    "sg:tags":[
        "grocer"
    ],
    "wof:name":"Place",
    "wof:placetype":"venue"
},
  "geometry": {"coordinates":[-93.4179763794,48.6094894409],"type":"Point"}
}