{
  "type": "Feature",
  "properties": {
    "addr:full":"4346 Orkney Beach Rd Orillia ON L3V 6H7",
    "addr:housenumber":"4346",
    "addr:postcode":"l3v 6h7",
    "addr:street":"Orkney Beach Rd",
    "iso:country":"CA",
    "sg:address":"4346 Orkney Beach Rd",
    "sg:city":"Orillia",
    "sg:classifiers":[
        {
            "category":"Professional",
            "subcategory":"Lawyer & Legal Services",
            "type":"Services"
        }
    ],
    "sg:phone":"+1 705 238 6024",
    "sg:postcode":"L3V 6H7",
    "sg:province":"ON",
    "sg:tags":[
        "attorney"
    ],
    "wof:name":"Manners, Charles",
    "wof:placetype":"venue"
},
  "geometry": {"coordinates":[-79.41822814939999,44.606590271],"type":"Point"}
}