{
  "type": "Feature",
  "properties": {
    "addr:full":"532 Rue Notre-Dame Montebello QC J0V 1L0",
    "addr:housenumber":"532",
    "addr:postcode":"j0v 1l0",
    "addr:street":"Rue Notre-Dame",
    "iso:country":"CA",
    "sg:address":"532 Rue Notre-Dame",
    "sg:city":"Montebello",
    "sg:classifiers":[
        {
            "category":"Health Services",
            "subcategory":"Nursing And Care Facility",
            "type":"Services"
        }
    ],
    "sg:phone":"+1 819 423 6673",
    "sg:postcode":"J0V 1L0",
    "sg:province":"QC",
    "sg:tags":[
        "home",
        "retirement",
        "community"
    ],
    "wof:name":"Residence Montebello",
    "wof:placetype":"venue"
},
  "geometry": {"coordinates":[-74.94072723390001,45.6500396729],"type":"Point"}
}