{
  "type": "Feature",
  "properties": {
    "addr:full":"1020 College Dr Saskatoon SK S7N 0W1",
    "addr:housenumber":"1020",
    "addr:postcode":"s7n 0w1",
    "addr:street":"College Dr",
    "iso:country":"CA",
    "sg:address":"1020 College Dr",
    "sg:city":"Saskatoon",
    "sg:classifiers":[
        {
            "category":"Travel",
            "subcategory":"Hotels & Motels",
            "type":"Entertainment"
        }
    ],
    "sg:phone":"+1 306 665 9111",
    "sg:postcode":"S7N 0W1",
    "sg:province":"SK",
    "wof:name":"College Drive Lodge",
    "wof:placetype":"venue"
},
  "geometry": {"coordinates":[-106.64592,52.128662],"type":"Point"}
}