{
  "type": "Feature",
  "properties": {
    "addr:full":"5218 Yonge St North York ON M2N 5P6",
    "addr:housenumber":"5218",
    "addr:postcode":"m2n 5p6",
    "addr:street":"Yonge St",
    "iso:country":"CA",
    "sg:address":"5218 Yonge St",
    "sg:city":"North York",
    "sg:classifiers":[
        {
            "category":"Banks & Credit Unions",
            "subcategory":"Bank",
            "type":"Services"
        }
    ],
    "sg:phone":"+1 416 223 8111",
    "sg:postcode":"M2N 5P6",
    "sg:province":"ON",
    "sg:tags":[
        "loan",
        "real estate"
    ],
    "wof:name":"Wildwood Capital Inc",
    "wof:placetype":"venue"
},
  "geometry": {"coordinates":[-79.413483,43.770786],"type":"Point"}
}