{
  "type": "Feature",
  "properties": {
    "addr:full":"Toronto ON M6R 2Y9",
    "addr:postcode":"m6r 2y9",
    "iso:country":"CA",
    "sg:city":"Toronto",
    "sg:classifiers":[
        {
            "category":"Recreation",
            "type":"Entertainment"
        }
    ],
    "sg:phone":"+1 416 531 7770",
    "sg:postcode":"M6R 2Y9",
    "sg:province":"ON",
    "sg:tags":[
        "tours",
        "sightseeing"
    ],
    "wof:name":"Unique Views",
    "wof:placetype":"venue"
},
  "geometry": {"coordinates":[-79.4554138184,43.6432723999],"type":"Point"}
}