{
  "type": "Feature",
  "properties": {
    "addr:full":"178 Old Kennedy Rd Markham ON L3R 0L5",
    "addr:housenumber":"178",
    "addr:postcode":"l3r 0l5",
    "addr:street":"Old Kennedy Rd",
    "iso:country":"CA",
    "sg:address":"178 Old Kennedy Rd",
    "sg:city":"Markham",
    "sg:classifiers":[
        {
            "category":"Social Services",
            "subcategory":"Child Care",
            "type":"Services"
        }
    ],
    "sg:phone":"+1 905 470 6595",
    "sg:postcode":"L3R 0L5",
    "sg:province":"ON",
    "wof:name":"Learning Fun Daycare & Nrsy",
    "wof:placetype":"venue"
},
  "geometry": {"coordinates":[-79.301468,43.829746],"type":"Point"}
}