{
  "type": "Feature",
  "properties": {
    "addr:full":"10 St George St St Thomas ON N5P 2K9",
    "addr:housenumber":"10",
    "addr:postcode":"n5p 2k9",
    "addr:street":"St George St",
    "iso:country":"CA",
    "sg:address":"10 St George St",
    "sg:city":"St Thomas",
    "sg:classifiers":[
        {
            "category":"Personal",
            "subcategory":"Beauty Salon",
            "type":"Services"
        }
    ],
    "sg:phone":"+1 519 631 4444",
    "sg:postcode":"N5P 2K9",
    "sg:province":"ON",
    "wof:name":"Cherola's Hair Design",
    "wof:placetype":"venue"
},
  "geometry": {"coordinates":[-81.20193481450001,42.7793960571],"type":"Point"}
}