{
  "type": "Feature",
  "properties": {
    "addr:full":"Calgary AB T2E 8C8",
    "addr:postcode":"t2e 8c8",
    "iso:country":"CA",
    "sg:city":"Calgary",
    "sg:classifiers":[
        {
            "category":"Freight",
            "type":"Transportation"
        }
    ],
    "sg:phone":"+1 403 277 6643",
    "sg:postcode":"T2E 8C8",
    "sg:province":"AB",
    "sg:tags":[
        "mover"
    ],
    "wof:name":"Ralph's Moving & Storage",
    "wof:placetype":"venue"
},
  "geometry": {"coordinates":[-114.04798889200001,51.0889778137],"type":"Point"}
}