{
  "type": "Feature",
  "properties": {
    "iso:country":"CA",
    "sg:address":"9100 Charles St",
    "sg:city":"Chilliwack",
    "sg:classifiers":[
        {
            "category":"Social Services",
            "subcategory":"Adult Care",
            "type":"Services"
        }
    ],
    "sg:phone":"+1 604 792 8166",
    "sg:postcode":"V2P 5K6",
    "sg:province":"BC",
    "sg:tags":[
        "community",
        "facility"
    ],
    "wof:name":"Eden Intermediate Care Home",
    "wof:placetype":"venue"
},
  "geometry": {"coordinates":[-121.942474365,49.1671257019],"type":"Point"}
}