{
  "type": "Feature",
  "properties": {
    "addr:full":"8444 Highway 93 & 95 Fort Steele BC V0B 1N0",
    "addr:housenumber":"8444",
    "addr:postcode":"bc v0b 1n0",
    "addr:street":"Highway 93 & 95 Fort Steele",
    "iso:country":"CA",
    "sg:address":"8444 Highway 93 & 95",
    "sg:city":"Fort Steele",
    "sg:classifiers":[
        {
            "category":"Wholesale",
            "subcategory":"Poultry",
            "type":"Manufacturing & Wholesale Goods"
        }
    ],
    "sg:phone":"+1 250 489 3068",
    "sg:postcode":"V0B 1N0",
    "sg:province":"BC",
    "sg:tags":[
        "eggs"
    ],
    "wof:name":"Fort Steele Farms",
    "wof:placetype":"venue"
},
  "geometry": {"coordinates":[-115.68048899999999,49.684551],"type":"Point"}
}