{
  "type": "Feature",
  "properties": {
    "addr:full":"2385 Ottawa St Port Coquitlam BC V3B 8A4",
    "addr:housenumber":"2385",
    "addr:postcode":"v3b 8a4",
    "addr:street":"Ottawa St",
    "iso:country":"CA",
    "sg:address":"2385 Ottawa St",
    "sg:city":"Port Coquitlam",
    "sg:classifiers":[
        {
            "category":"Food & Beverages",
            "subcategory":"Groceries & Convenience Stores",
            "type":"Retail Goods"
        }
    ],
    "sg:phone":"+1 604 464 9984",
    "sg:postcode":"V3B 8A4",
    "sg:province":"BC",
    "sg:tags":[
        "grocer"
    ],
    "wof:name":"Save-On-Foods & Drugs",
    "wof:placetype":"venue"
},
  "geometry": {"coordinates":[-122.74678,49.257175],"type":"Point"}
}