{
  "type": "Feature",
  "properties": {
    "addr:full":"90 Hutchings St Winnipeg MB R2X 2X1",
    "addr:housenumber":"90",
    "addr:postcode":"r2x 2x1",
    "addr:street":"Hutchings St",
    "iso:country":"CA",
    "sg:address":"90 Hutchings St",
    "sg:city":"Winnipeg",
    "sg:classifiers":[
        {
            "category":"Manufacturing",
            "subcategory":"Rubber & Plastics",
            "type":"Manufacturing & Wholesale Goods"
        }
    ],
    "sg:phone":"+1 204 697 8408",
    "sg:postcode":"R2X 2X1",
    "sg:province":"MB",
    "wof:name":"Dynast Plastics Ltd",
    "wof:placetype":"venue"
},
  "geometry": {"coordinates":[-97.183883667,49.9390296936],"type":"Point"}
}