{
  "type": "Feature",
  "properties": {
    "addr:full":"3995 Main St Vancouver BC V5V 3P3",
    "addr:housenumber":"3995",
    "addr:postcode":"v5v 3p3",
    "addr:street":"Main St",
    "iso:country":"CA",
    "sg:address":"3995 Main St",
    "sg:city":"Vancouver",
    "sg:classifiers":[
        {
            "category":"Restaurant",
            "type":"Food & Drink"
        }
    ],
    "sg:phone":"+1 604 879 0020",
    "sg:postcode":"V5V 3P3",
    "sg:province":"BC",
    "wof:name":"Cipriano's Ristorante & Pizza",
    "wof:placetype":"venue"
},
  "geometry": {"coordinates":[-123.10111999999999,49.249622],"type":"Point"}
}