{
  "type": "Feature",
  "properties": {
    "addr:full":"329 Main St Wolfville NS B4P 1C8",
    "addr:housenumber":"329",
    "addr:postcode":"b4p 1c8",
    "addr:street":"Main St",
    "iso:country":"CA",
    "sg:address":"329 Main St",
    "sg:city":"Wolfville",
    "sg:classifiers":[
        {
            "category":"Organizations",
            "subcategory":"Religious Organization",
            "type":"Services"
        }
    ],
    "sg:phone":"+1 902 542 3796",
    "sg:postcode":"B4P 1C8",
    "sg:province":"NS",
    "sg:tags":[
        "church"
    ],
    "wof:name":"St Andrews United Church",
    "wof:placetype":"venue"
},
  "geometry": {"coordinates":[-64.3728256226,45.0900688171],"type":"Point"}
}