{
  "type": "Feature",
  "properties": {
    "addr:full":"1928 Queensdale Ave Gloucester ON K1T 1K1",
    "addr:housenumber":"1928",
    "addr:postcode":"k1t 1k1",
    "addr:street":"Queensdale Ave",
    "iso:country":"CA",
    "sg:address":"1928 Queensdale Ave",
    "sg:city":"Gloucester",
    "sg:classifiers":[
        {
            "category":"Home & Garden",
            "subcategory":"Building Materials",
            "type":"Retail Goods"
        }
    ],
    "sg:phone":"+1 613 521 5513",
    "sg:postcode":"K1T 1K1",
    "sg:province":"ON",
    "sg:tags":[
        "windows"
    ],
    "wof:name":"Siwicki Services",
    "wof:placetype":"venue"
},
  "geometry": {"coordinates":[-75.615028,45.351593],"type":"Point"}
}