{
  "type": "Feature",
  "properties": {
    "addr:full":"34 Rue Michel-Quintal Saint-Luc QC J2W 2T4",
    "addr:housenumber":"34",
    "addr:postcode":"j2w 2t4",
    "addr:street":"Rue Michel-Quintal",
    "iso:country":"CA",
    "sg:address":"34 Rue Michel-Quintal",
    "sg:city":"Saint-Luc",
    "sg:classifiers":[
        {
            "category":"Professional",
            "subcategory":"Lawyer & Legal Services",
            "type":"Services"
        }
    ],
    "sg:phone":"+1 450 349 0794",
    "sg:postcode":"J2W 2T4",
    "sg:province":"QC",
    "sg:tags":[
        "attorney"
    ],
    "wof:name":"Bedard, Martine",
    "wof:placetype":"venue"
},
  "geometry": {"coordinates":[-73.29496,45.339706],"type":"Point"}
}