{
  "type": "Feature",
  "properties": {
    "addr:full":"5 Homewood Hastings ON K0L 1Y0",
    "addr:housenumber":"5",
    "addr:postcode":"k0l 1y0",
    "addr:street":"Homewood",
    "iso:country":"CA",
    "sg:address":"5 Homewood",
    "sg:city":"Hastings",
    "sg:classifiers":[
        {
            "category":"Shopping",
            "subcategory":"Bicycles & Sporting Goods",
            "type":"Retail Goods"
        }
    ],
    "sg:phone":"+1 705 696 3387",
    "sg:postcode":"K0L 1Y0",
    "sg:province":"ON",
    "wof:name":"Val's Live Bait",
    "wof:placetype":"venue"
},
  "geometry": {"coordinates":[-77.957649231,44.3068351746],"type":"Point"}
}