{
  "type": "Feature",
  "properties": {
    "addr:full":"Val Therese ON P3P 1S7",
    "addr:postcode":"p3p 1s7",
    "addr:street":"Val",
    "iso:country":"CA",
    "sg:city":"Val Therese",
    "sg:classifiers":[
        {
            "category":"Autos & Motor Vehicles",
            "subcategory":"Recreational Vehicle Sales",
            "type":"Retail Goods"
        }
    ],
    "sg:phone":"+1 705 969 4056",
    "sg:postcode":"P3P 1S7",
    "sg:province":"ON",
    "wof:name":"Foucault Trailer Sales",
    "wof:placetype":"venue"
},
  "geometry": {"coordinates":[-81.0072250366,46.6526603699],"type":"Point"}
}