{
  "type": "Feature",
  "properties": {
    "addr:full":"5027 51st Ave Barrhead AB T7N 1A5",
    "addr:housenumber":"5027",
    "addr:postcode":"t7n 1a5",
    "addr:street":"51St Ave",
    "iso:country":"CA",
    "sg:address":"5027 51st Ave",
    "sg:city":"Barrhead",
    "sg:classifiers":[
        {
            "category":"Health Services",
            "subcategory":"Doctor",
            "type":"Services"
        }
    ],
    "sg:phone":"+1 780 674 5667",
    "sg:postcode":"T7N 1A5",
    "sg:province":"AB",
    "sg:tags":[
        "dentist"
    ],
    "wof:name":"Yuill, Allan L DDS",
    "wof:placetype":"venue"
},
  "geometry": {"coordinates":[-114.405884,54.120792],"type":"Point"}
}