{
  "type": "Feature",
  "properties": {
    "addr:full":"2 Johnson Ave Miramichi NB E1N 3B7",
    "addr:housenumber":"2",
    "addr:postcode":"e1n 3b7",
    "addr:street":"Johnson Ave",
    "iso:country":"CA",
    "sg:address":"2 Johnson Ave",
    "sg:city":"Miramichi",
    "sg:classifiers":[
        {
            "category":"Health Services",
            "subcategory":"Doctor",
            "type":"Services"
        }
    ],
    "sg:phone":"+1 506 778 8994",
    "sg:postcode":"E1N 3B7",
    "sg:province":"NB",
    "sg:tags":[
        "physician",
        "surgeon"
    ],
    "wof:name":"Boulay, Robert M MD",
    "wof:placetype":"venue"
},
  "geometry": {"coordinates":[-65.471619,47.028469],"type":"Point"}
}