{
  "type": "Feature",
  "properties": {
    "addr:full":"1095 Boul Saint-Joseph Drummondville QC J2C 2C4",
    "addr:housenumber":"1095",
    "addr:postcode":"j2c 2c4",
    "addr:street":"Boul Saint-Joseph",
    "iso:country":"CA",
    "sg:address":"1095 Boul Saint-Joseph",
    "sg:city":"Drummondville",
    "sg:classifiers":[
        {
            "category":"Retail",
            "subcategory":"Auto Repair",
            "type":"Services"
        }
    ],
    "sg:phone":"+1 819 478 1321",
    "sg:postcode":"J2C 2C4",
    "sg:province":"QC",
    "sg:tags":[
        "repairing",
        "automobile"
    ],
    "wof:name":"Gougeon & Frere Ltee",
    "wof:placetype":"venue"
},
  "geometry": {"coordinates":[-72.5060882568,45.8880386353],"type":"Point"}
}