{
  "type": "Feature",
  "properties": {
    "addr:full":"28636 Centre Rd Strathroy ON N7G 3H6",
    "addr:housenumber":"28636",
    "addr:postcode":"n7g 3h6",
    "addr:street":"Centre Rd",
    "iso:country":"CA",
    "sg:address":"28636 Centre Rd",
    "sg:city":"Strathroy",
    "sg:classifiers":[
        {
            "category":"Professional",
            "subcategory":"Accounting & Tax Preparation",
            "type":"Services"
        }
    ],
    "sg:phone":"+1 519 245 1913",
    "sg:postcode":"N7G 3H6",
    "sg:province":"ON",
    "sg:tags":[
        "accountant"
    ],
    "wof:name":"Bdo Dunwoody",
    "wof:placetype":"venue"
},
  "geometry": {"coordinates":[-81.622299,42.955772],"type":"Point"}
}