{
  "type": "Feature",
  "properties": {
    "addr:full":"363 Bering Ave Etobicoke ON M8Z 3B1",
    "addr:housenumber":"363",
    "addr:postcode":"m8z 3b1",
    "addr:street":"Bering Ave",
    "iso:country":"CA",
    "sg:address":"363 Bering Ave",
    "sg:city":"Etobicoke",
    "sg:classifiers":[
        {
            "category":"Building & Trades",
            "subcategory":"Construction",
            "type":"Services"
        }
    ],
    "sg:phone":"+1 416 231 7438",
    "sg:postcode":"M8Z 3B1",
    "sg:province":"ON",
    "sg:tags":[
        "general",
        "contractor"
    ],
    "wof:name":"Caruk Group Ltd",
    "wof:placetype":"venue"
},
  "geometry": {"coordinates":[-79.5314025879,43.6369514465],"type":"Point"}
}