{
  "type": "Feature",
  "properties": {
    "addr:full":"4544 47 Ave Rocky Mountain House AB T4T 1C5",
    "addr:housenumber":"4544",
    "addr:postcode":"t4t 1c5",
    "addr:street":"47 Ave",
    "iso:country":"CA",
    "sg:address":"4544 47 Ave",
    "sg:city":"Rocky Mountain House",
    "sg:classifiers":[
        {
            "category":"Local Transit",
            "type":"Transportation"
        }
    ],
    "sg:phone":"+1 403 845 2642",
    "sg:postcode":"T4T 1C5",
    "sg:province":"AB",
    "sg:tags":[
        "ambulance"
    ],
    "wof:name":"Rocky Ambulance Svc",
    "wof:placetype":"venue"
},
  "geometry": {"coordinates":[-114.910141,52.370373],"type":"Point"}
}