{
  "type": "Feature",
  "properties": {
    "addr:full":"101 4th St W Kindersley SK S0L 1S0",
    "addr:housenumber":"101",
    "addr:postcode":"s0l 1s0",
    "addr:street":"4Th St W Kindersley",
    "iso:country":"CA",
    "sg:address":"101 4th St W",
    "sg:city":"Kindersley",
    "sg:classifiers":[
        {
            "category":"Autos & Motor Vehicles",
            "subcategory":"Auto Supplies",
            "type":"Retail Goods"
        }
    ],
    "sg:phone":"+1 306 463 4242",
    "sg:postcode":"S0L 1S0",
    "sg:province":"SK",
    "sg:tags":[
        "automobile",
        "parts"
    ],
    "wof:name":"Western Farmers Supply",
    "wof:placetype":"venue"
},
  "geometry": {"coordinates":[-109.161483765,51.4629211426],"type":"Point"}
}