{
  "type": "Feature",
  "properties": {
    "addr:full":"4819 50 Ave Barrhead AB T7N 1G9",
    "addr:housenumber":"4819",
    "addr:postcode":"t7n 1g9",
    "addr:street":"50 Ave",
    "iso:country":"CA",
    "sg:address":"4819 50 Ave",
    "sg:city":"Barrhead",
    "sg:classifiers":[
        {
            "category":"Personal",
            "subcategory":"Beauty Salon",
            "type":"Services"
        }
    ],
    "sg:phone":"+1 780 674 3673",
    "sg:postcode":"T7N 1G9",
    "sg:province":"AB",
    "wof:name":"Heather's Hair Design",
    "wof:placetype":"venue"
},
  "geometry": {"coordinates":[-114.39958190900001,54.1175193787],"type":"Point"}
}