{
  "type": "Feature",
  "properties": {
    "addr:full":"Miller Lake ON N0H 1Z0",
    "addr:postcode":"n0h 1z0",
    "iso:country":"CA",
    "sg:city":"Miller Lake",
    "sg:classifiers":[
        {
            "category":"Travel",
            "subcategory":"Campground",
            "type":"Entertainment"
        }
    ],
    "sg:phone":"+1 519 795 7851",
    "sg:postcode":"N0H 1Z0",
    "sg:province":"ON",
    "sg:tags":[
        "camp"
    ],
    "wof:name":"Miller Lake Baptist Camp",
    "wof:placetype":"venue"
},
  "geometry": {"coordinates":[-81.44310760499999,45.1025695801],"type":"Point"}
}