{
  "type": "Feature",
  "properties": {
    "addr:full":"Nelson BC V1L 4B8",
    "addr:postcode":"bc v1l 4b8",
    "iso:country":"CA",
    "sg:city":"Nelson",
    "sg:classifiers":[
        {
            "category":"Wholesale",
            "subcategory":"Machinery & Supplies",
            "type":"Manufacturing & Wholesale Goods"
        }
    ],
    "sg:phone":"+1 250 352 7221",
    "sg:postcode":"V1L 4B8",
    "sg:province":"BC",
    "sg:tags":[
        "plumbing",
        "pump",
        "fixture"
    ],
    "wof:name":"Interior Hardware & Supply CO",
    "wof:placetype":"venue"
},
  "geometry": {"coordinates":[-117.29315200000001,49.495602],"type":"Point"}
}