{
  "type": "Feature",
  "properties": {
    "addr:full":"Victoriaville QC G6P 7L6",
    "addr:postcode":"g6p 7l6",
    "iso:country":"CA",
    "sg:city":"Victoriaville",
    "sg:classifiers":[
        {
            "category":"Retail",
            "subcategory":"Auto Repair",
            "type":"Services"
        }
    ],
    "sg:phone":"+1 819 758 3606",
    "sg:postcode":"G6P 7L6",
    "sg:province":"QC",
    "sg:tags":[
        "repairing",
        "automobile"
    ],
    "wof:name":"Garage Doc Donald Enr",
    "wof:placetype":"venue"
},
  "geometry": {"coordinates":[-72.004143,46.051167],"type":"Point"}
}