{
  "type": "Feature",
  "properties": {
    "addr:full":"3760 48 Ave Camrose AB T4V 3Z8",
    "addr:housenumber":"3760",
    "addr:postcode":"t4v 3z8",
    "addr:street":"48 Ave",
    "iso:country":"CA",
    "sg:address":"3760 48 Ave",
    "sg:city":"Camrose",
    "sg:classifiers":[
        {
            "category":"Autos & Motor Vehicles",
            "subcategory":"Automobile Sales",
            "type":"Retail Goods"
        }
    ],
    "sg:phone":"+1 780 672 0123",
    "sg:postcode":"T4V 3Z8",
    "sg:province":"AB",
    "sg:tags":[
        "car",
        "dealer"
    ],
    "wof:name":"Norseman Pontiac Buick Gmc Ltd",
    "wof:placetype":"venue"
},
  "geometry": {"coordinates":[-112.798553,53.018276],"type":"Point"}
}