{
  "type": "Feature",
  "properties": {
    "addr:full":"2165 Guildford Town Ctr Surrey BC V3R 7B9",
    "addr:housenumber":"2165",
    "addr:postcode":"v3r 7b9",
    "addr:street":"Guildford Town Ctr",
    "iso:country":"CA",
    "sg:address":"2165 Guildford Town Ctr",
    "sg:city":"Surrey",
    "sg:classifiers":[
        {
            "category":"Shopping",
            "subcategory":"Clothing, Apparel, & Fashions",
            "type":"Retail Goods"
        }
    ],
    "sg:phone":"+1 604 588 4212",
    "sg:postcode":"V3R 7B9",
    "sg:province":"BC",
    "wof:name":"Mariposa Stores Ltd",
    "wof:placetype":"venue"
},
  "geometry": {"coordinates":[-122.804016,49.188332],"type":"Point"}
}