{
  "type": "Feature",
  "properties": {
    "iso:country":"CA",
    "sg:address":"2279 Queen St E",
    "sg:city":"Toronto",
    "sg:classifiers":[
        {
            "category":"Personal",
            "subcategory":"Beauty Salon",
            "type":"Services"
        }
    ],
    "sg:phone":"+1 416 690 2279",
    "sg:postcode":"M4E 1G5",
    "sg:province":"ON",
    "wof:name":"Strands Hair Studio",
    "wof:placetype":"venue"
},
  "geometry": {"coordinates":[-79.2928237915,43.6715011597],"type":"Point"}
}