{
  "type": "Feature",
  "properties": {
    "addr:full":"30 Water St Port Hood NS B0E 2W0",
    "addr:housenumber":"30",
    "addr:postcode":"b0e 2w0",
    "addr:street":"Water St",
    "iso:country":"CA",
    "sg:address":"30 Water St",
    "sg:city":"Port Hood",
    "sg:classifiers":[
        {
            "category":"Health Services",
            "subcategory":"Doctor",
            "type":"Services"
        }
    ],
    "sg:phone":"+1 902 787 2245",
    "sg:postcode":"B0E 2W0",
    "sg:province":"NS",
    "sg:tags":[
        "dentist"
    ],
    "wof:name":"Ojoleck, Michael DDS",
    "wof:placetype":"venue"
},
  "geometry": {"coordinates":[-61.530663,46.0158],"type":"Point"}
}