{
  "type": "Feature",
  "properties": {
    "iso:country":"CA",
    "sg:address":"1500 Rue Alphonse-D.-Roy",
    "sg:city":"Montreal",
    "sg:classifiers":[
        {
            "category":"Retail",
            "subcategory":"Auto Repair",
            "type":"Services"
        }
    ],
    "sg:phone":"+1 514 521 6622",
    "sg:postcode":"H1W 3X4",
    "sg:province":"QC",
    "sg:tags":[
        "bus"
    ],
    "wof:name":"Centre Express DE Svc Au Mntrl",
    "wof:placetype":"venue"
},
  "geometry": {"coordinates":[-73.544289,45.537239],"type":"Point"}
}