{
  "type": "Feature",
  "properties": {
    "addr:full":"15228 Woodbine Ave S Gormley ON L0H 1G0",
    "addr:housenumber":"15228",
    "addr:postcode":"l0h 1g0",
    "addr:street":"Woodbine Ave S",
    "iso:country":"CA",
    "sg:address":"15228 Woodbine Ave S",
    "sg:city":"Gormley",
    "sg:classifiers":[
        {
            "category":"Autos & Motor Vehicles",
            "subcategory":"Fuel & Gas Station",
            "type":"Retail Goods"
        }
    ],
    "sg:phone":"+1 905 727 2432",
    "sg:postcode":"L0H 1G0",
    "sg:province":"ON",
    "sg:tags":[
        "oil"
    ],
    "wof:name":"Gormley Gas & Convenience",
    "wof:placetype":"venue"
},
  "geometry": {"coordinates":[-79.39167,43.999699],"type":"Point"}
}