{
  "type": "Feature",
  "properties": {
    "iso:country":"CA",
    "sg:address":"1480 80E Rue E",
    "sg:city":"Charlesbourg",
    "sg:classifiers":[
        {
            "category":"Organizations",
            "subcategory":"Professional Association",
            "type":"Services"
        }
    ],
    "sg:phone":"+1 418 623 5335",
    "sg:postcode":"G2L 1M3",
    "sg:province":"QC",
    "wof:name":"Comite Sectoriel DE Main",
    "wof:placetype":"venue"
},
  "geometry": {"coordinates":[-71.251159668,46.8457183838],"type":"Point"}
}