{
  "type": "Feature",
  "properties": {
    "addr:full":"Montreal QC H2T 1S6",
    "addr:postcode":"h2t 1s6",
    "iso:country":"CA",
    "sg:city":"Montreal",
    "sg:classifiers":[
        {
            "category":"Communications",
            "subcategory":"Film & Video Production",
            "type":"Services"
        }
    ],
    "sg:phone":"+1 514 278 3140",
    "sg:postcode":"H2T 1S6",
    "sg:province":"QC",
    "sg:tags":[
        "motion",
        "picture",
        "studio",
        "producer"
    ],
    "wof:name":"Cineflix Inc",
    "wof:placetype":"venue"
},
  "geometry": {"coordinates":[-73.5984573364,45.5257911682],"type":"Point"}
}