{
  "type": "Feature",
  "properties": {
    "addr:full":"10000 Av DE Bruxelles Montreal-Nord QC H1H 4P9",
    "addr:postcode":"h1h 4p9",
    "addr:street":"Av De Bruxelles",
    "iso:country":"CA",
    "sg:address":"10000 Av DE Bruxelles",
    "sg:city":"Montreal-Nord",
    "sg:classifiers":[
        {
            "category":"Building & Trades",
            "subcategory":"Construction",
            "type":"Services"
        }
    ],
    "sg:phone":"+1 514 325 2511",
    "sg:postcode":"H1H 4P9",
    "sg:province":"QC",
    "sg:tags":[
        "maker",
        "cabinet"
    ],
    "wof:name":"Wizo Inc",
    "wof:placetype":"venue"
},
  "geometry": {"coordinates":[-73.63505600000001,45.580429],"type":"Point"}
}