{
  "type": "Feature",
  "properties": {
    "addr:full":"2272 Regional Road 9 York ON N0A 1R0",
    "addr:housenumber":"2272",
    "addr:postcode":"n0a 1r0",
    "addr:street":"Regional Road 9",
    "iso:country":"CA",
    "sg:address":"2272 Regional Road 9",
    "sg:city":"York",
    "sg:classifiers":[
        {
            "category":"Building & Trades",
            "subcategory":"Construction",
            "type":"Services"
        }
    ],
    "sg:phone":"+1 905 772 1649",
    "sg:postcode":"N0A 1R0",
    "sg:province":"ON",
    "sg:tags":[
        "maker",
        "cabinet"
    ],
    "wof:name":"Taylor Made Cabinets",
    "wof:placetype":"venue"
},
  "geometry": {"coordinates":[-79.891113,43.022419],"type":"Point"}
}