{
  "type": "Feature",
  "properties": {
    "addr:full":"Georgetown ON L7G 5E9",
    "addr:postcode":"l7g 5e9",
    "iso:country":"CA",
    "sg:city":"Georgetown",
    "sg:classifiers":[
        {
            "category":"Professional",
            "subcategory":"Lawyer & Legal Services",
            "type":"Services"
        }
    ],
    "sg:phone":"+1 905 877 5139",
    "sg:postcode":"L7G 5E9",
    "sg:province":"ON",
    "sg:tags":[
        "attorney"
    ],
    "wof:name":"Howitt, Richard T QC",
    "wof:placetype":"venue"
},
  "geometry": {"coordinates":[-79.9250793457,43.6499252319],"type":"Point"}
}