{
  "type": "Feature",
  "properties": {
    "addr:full":"Welland ON L3B 6A4",
    "addr:postcode":"l3b 6a4",
    "iso:country":"CA",
    "sg:city":"Welland",
    "sg:classifiers":[
        {
            "category":"Professional",
            "subcategory":"Lawyer & Legal Services",
            "type":"Services"
        }
    ],
    "sg:phone":"+1 905 732 1352",
    "sg:postcode":"L3B 6A4",
    "sg:province":"ON",
    "sg:tags":[
        "attorney"
    ],
    "wof:name":"Kajan, Rodney J",
    "wof:placetype":"venue"
},
  "geometry": {"coordinates":[-79.2507095337,42.9907455444],"type":"Point"}
}