{
  "type": "Feature",
  "properties": {
    "iso:country":"CA",
    "sg:address":"175 Main St",
    "sg:city":"Blackville",
    "sg:classifiers":[
        {
            "category":"Shopping",
            "subcategory":"Pharmacy",
            "type":"Retail Goods"
        }
    ],
    "sg:phone":"+1 506 843 6444",
    "sg:postcode":"E9B 1S3",
    "sg:province":"NB",
    "wof:name":"Blackville Pharmasave",
    "wof:placetype":"venue"
},
  "geometry": {"coordinates":[-65.83049,46.74091],"type":"Point"}
}