{
  "type": "Feature",
  "properties": {
    "addr:full":"3236 Kerrydale Rd SW Calgary AB T3E 4S6",
    "addr:housenumber":"3236",
    "addr:postcode":"t3e 4s6",
    "addr:street":"Kerrydale Rd Sw",
    "iso:country":"CA",
    "sg:address":"3236 Kerrydale Rd SW",
    "sg:city":"Calgary",
    "sg:classifiers":[
        {
            "category":"Building & Trades",
            "subcategory":"Construction",
            "type":"Services"
        }
    ],
    "sg:phone":"+1 403 246 3850",
    "sg:postcode":"T3E 4S6",
    "sg:province":"AB",
    "sg:tags":[
        "designer"
    ],
    "wof:name":"Nea Designs",
    "wof:placetype":"venue"
},
  "geometry": {"coordinates":[-114.138465881,51.0240592957],"type":"Point"}
}