{
  "type": "Feature",
  "properties": {
    "addr:full":"150 Hedgedale Rd Brampton ON L6T 5L2",
    "addr:housenumber":"150",
    "addr:postcode":"l6t 5l2",
    "addr:street":"Hedgedale Rd",
    "iso:country":"CA",
    "sg:address":"150 Hedgedale Rd",
    "sg:city":"Brampton",
    "sg:classifiers":[
        {
            "category":"Wholesale",
            "subcategory":"Machinery & Supplies",
            "type":"Manufacturing & Wholesale Goods"
        }
    ],
    "sg:phone":"+1 905 459 4350",
    "sg:postcode":"L6T 5L2",
    "sg:province":"ON",
    "sg:tags":[
        "contractor"
    ],
    "wof:name":"Federal Equipment Inc",
    "wof:placetype":"venue"
},
  "geometry": {"coordinates":[-79.705589,43.685966],"type":"Point"}
}