{
  "type": "Feature",
  "properties": {
    "addr:full":"927 Rue Gaudette Saint-Jean-Sur-Richelieu QC J3B 7S7",
    "addr:housenumber":"927",
    "addr:postcode":"j3b 7s7",
    "addr:street":"Rue Gaudette",
    "iso:country":"CA",
    "sg:address":"927 Rue Gaudette",
    "sg:city":"Saint-Jean-Sur-Richelieu",
    "sg:classifiers":[
        {
            "category":"Manufacturing",
            "subcategory":"Tools & Machinery",
            "type":"Manufacturing & Wholesale Goods"
        }
    ],
    "sg:phone":"+1 514 856 7701",
    "sg:postcode":"J3B 7S7",
    "sg:province":"QC",
    "sg:tags":[
        "sound",
        "equipment",
        "lighting",
        "system"
    ],
    "wof:name":"Groupe Berger Son & Lumiere",
    "wof:placetype":"venue"
},
  "geometry": {"coordinates":[-73.29435700000001,45.321777],"type":"Point"}
}