{
  "type": "Feature",
  "properties": {
    "addr:full":"18113 57A Ave Surrey BC V3S 1J7",
    "addr:housenumber":"18113",
    "addr:postcode":"v3s 1j7",
    "addr:street":"57A Ave",
    "iso:country":"CA",
    "sg:address":"18113 57A Ave",
    "sg:city":"Surrey",
    "sg:classifiers":[
        {
            "category":"Shopping",
            "type":"Retail Goods"
        }
    ],
    "sg:phone":"+1 604 574 5700",
    "sg:postcode":"V3S 1J7",
    "sg:province":"BC",
    "sg:tags":[
        "picture",
        "frame"
    ],
    "wof:name":"Frameline Art",
    "wof:placetype":"venue"
},
  "geometry": {"coordinates":[-122.830215454,49.105178833],"type":"Point"}
}