{
  "type": "Feature",
  "properties": {
    "addr:full":"170 Hawthorne St Antigonish NS B2G 1B1",
    "addr:housenumber":"170",
    "addr:postcode":"b2g 1b1",
    "addr:street":"Hawthorne St",
    "iso:country":"CA",
    "sg:address":"170 Hawthorne St",
    "sg:city":"Antigonish",
    "sg:classifiers":[
        {
            "category":"Health Services",
            "subcategory":"Doctor",
            "type":"Services"
        }
    ],
    "sg:phone":"+1 902 863 0018",
    "sg:postcode":"B2G 1B1",
    "sg:province":"NS",
    "sg:tags":[
        "dentist"
    ],
    "wof:name":"Mac Isaac, Allana DDS",
    "wof:placetype":"venue"
},
  "geometry": {"coordinates":[-61.99427,45.622189],"type":"Point"}
}