{
  "type": "Feature",
  "properties": {
    "addr:full":"PO Box 51 Falun AB T0C 1H0",
    "addr:housenumber":"po box 51",
    "addr:postcode":"t0c 1h0",
    "iso:country":"CA",
    "sg:address":"PO Box 51",
    "sg:city":"Falun",
    "sg:classifiers":[
        {
            "category":"Manufacturing",
            "subcategory":"Jewelry",
            "type":"Manufacturing & Wholesale Goods"
        }
    ],
    "sg:phone":"+1 780 586 2846",
    "sg:postcode":"T0C 1H0",
    "sg:province":"AB",
    "sg:tags":[
        "platinum",
        "product",
        "gold",
        "silversmith",
        "goldsmith",
        "silver"
    ],
    "wof:name":"Wmj Metals Ltd",
    "wof:placetype":"venue"
},
  "geometry": {"coordinates":[-113.83280944800001,52.9597969055],"type":"Point"}
}