{
  "type": "Feature",
  "properties": {
    "addr:full":"19 Coral Springs Blvd NE Calgary AB T3J 4J1",
    "addr:housenumber":"19",
    "addr:postcode":"t3j 4j1",
    "addr:street":"Coral Springs Blvd Ne",
    "iso:country":"CA",
    "sg:address":"19 Coral Springs Blvd NE",
    "sg:city":"Calgary",
    "sg:classifiers":[
        {
            "category":"Personal",
            "subcategory":"Beauty Salon",
            "type":"Services"
        }
    ],
    "sg:phone":"+1 403 285 2700",
    "sg:postcode":"T3J 4J1",
    "sg:province":"AB",
    "wof:name":"Aurora Beauty Salon",
    "wof:placetype":"venue"
},
  "geometry": {"coordinates":[-113.933014,51.098881],"type":"Point"}
}