{
  "type": "Feature",
  "properties": {
    "iso:country":"CA",
    "sg:address":"4210 Mountain View Rd",
    "sg:city":"Smithers",
    "sg:classifiers":[
        {
            "category":"Retail",
            "subcategory":"Repair Shop",
            "type":"Services"
        }
    ],
    "sg:phone":"+1 250 847 2016",
    "sg:postcode":"V0J 2N6",
    "sg:province":"BC",
    "sg:tags":[
        "contractor"
    ],
    "wof:name":"Rodger D'Amours Contracting",
    "wof:placetype":"venue"
},
  "geometry": {"coordinates":[-127.172966003,54.7891464233],"type":"Point"}
}