{
  "type": "Feature",
  "properties": {
    "addr:full":"2460 Queen St E Brampton ON L6S 5X9",
    "addr:housenumber":"2460",
    "addr:postcode":"l6s 5x9",
    "addr:street":"Queen St E",
    "iso:country":"CA",
    "sg:address":"2460 Queen St E",
    "sg:city":"Brampton",
    "sg:classifiers":[
        {
            "category":"Home & Garden",
            "subcategory":"Garden Supply",
            "type":"Retail Goods"
        }
    ],
    "sg:phone":"+1 905 791 0692",
    "sg:postcode":"L6S 5X9",
    "sg:province":"ON",
    "sg:tags":[
        "center"
    ],
    "wof:name":"Imperial Garden Ctr",
    "wof:placetype":"venue"
},
  "geometry": {"coordinates":[-79.702698,43.737766],"type":"Point"}
}