{
  "type": "Feature",
  "properties": {
    "addr:full":"Surrey BC V4A 1N2",
    "addr:postcode":"v4a 1n2",
    "iso:country":"CA",
    "sg:city":"Surrey",
    "sg:classifiers":[
        {
            "category":"Personal",
            "type":"Services"
        }
    ],
    "sg:phone":"+1 604 531 1776",
    "sg:postcode":"V4A 1N2",
    "sg:province":"BC",
    "sg:tags":[
        "therapist",
        "massage"
    ],
    "wof:name":"Ocean Park Massage Therapy",
    "wof:placetype":"venue"
},
  "geometry": {"coordinates":[-122.868652344,49.0314254761],"type":"Point"}
}