{
  "type": "Feature",
  "properties": {
    "addr:full":"612 N 7th St Golden BC V0A 1H0",
    "addr:housenumber":"612",
    "addr:postcode":"v0a 1h0",
    "addr:street":"N 7Th St",
    "iso:country":"CA",
    "sg:address":"612 N 7th St",
    "sg:city":"Golden",
    "sg:classifiers":[
        {
            "category":"Recreation",
            "type":"Entertainment"
        }
    ],
    "sg:phone":"+1 250 344 6521",
    "sg:postcode":"V0A 1H0",
    "sg:province":"BC",
    "sg:tags":[
        "raft",
        "trip"
    ],
    "wof:name":"Glacier Raft CO Ltd",
    "wof:placetype":"venue"
},
  "geometry": {"coordinates":[-116.97007000000001,51.302109],"type":"Point"}
}