{
  "type": "Feature",
  "properties": {
    "addr:full":"910 Rue DE L'Ecole Mont-Tremblant QC J8E 2W3",
    "addr:housenumber":"910",
    "addr:postcode":"j8e 2w3",
    "addr:street":"Rue De L'Ecole",
    "iso:country":"CA",
    "sg:address":"910 Rue DE L'Ecole",
    "sg:city":"Mont-Tremblant",
    "sg:classifiers":[
        {
            "category":"Health Services",
            "subcategory":"Doctor",
            "type":"Services"
        }
    ],
    "sg:phone":"+1 819 425 5544",
    "sg:postcode":"J8E 2W3",
    "sg:province":"QC",
    "sg:tags":[
        "clinic"
    ],
    "wof:name":"Clinique Radiologique-P Savoie",
    "wof:placetype":"venue"
},
  "geometry": {"coordinates":[-74.593254,46.122082],"type":"Point"}
}