{
  "type": "Feature",
  "properties": {
    "addr:full":"8450 Granville St Vancouver BC V6P 4Z7",
    "addr:housenumber":"8450",
    "addr:postcode":"v6p 4z7",
    "addr:street":"Granville St",
    "iso:country":"CA",
    "sg:address":"8450 Granville St",
    "sg:city":"Vancouver",
    "sg:classifiers":[
        {
            "category":"Banks & Credit Unions",
            "subcategory":"Bank",
            "type":"Services"
        }
    ],
    "sg:phone":"+1 604 257 1120",
    "sg:postcode":"V6P 4Z7",
    "sg:province":"BC",
    "wof:name":"Cibc",
    "wof:placetype":"venue"
},
  "geometry": {"coordinates":[-123.140297,49.209595],"type":"Point"}
}