{
  "type": "Feature",
  "properties": {
    "addr:full":"Panet QC G0R 2J0",
    "addr:postcode":"g0r 2j0",
    "iso:country":"CA",
    "sg:city":"Panet",
    "sg:classifiers":[
        {
            "category":"Building & Trades",
            "subcategory":"Construction",
            "type":"Services"
        }
    ],
    "sg:phone":"+1 418 249 4081",
    "sg:postcode":"G0R 2J0",
    "sg:province":"QC",
    "sg:tags":[
        "concrete",
        "excavating",
        "contractor"
    ],
    "wof:name":"9010-3250 Quebec Inc",
    "wof:placetype":"venue"
},
  "geometry": {"coordinates":[-70.144531,46.656231],"type":"Point"}
}