{
  "type": "Feature",
  "properties": {
    "addr:full":"5939 Dundas St E RR 4 Thamesford ON N0M 2M0",
    "addr:housenumber":"5939",
    "addr:postcode":"n0m 2m0",
    "addr:street":"Dundas St;Rr 4",
    "iso:country":"CA",
    "sg:address":"5939 Dundas St E RR 4",
    "sg:city":"Thamesford",
    "sg:classifiers":[
        {
            "category":"Retail",
            "subcategory":"Auto Repair",
            "type":"Services"
        }
    ],
    "sg:phone":"+1 519 285 3809",
    "sg:postcode":"N0M 2M0",
    "sg:province":"ON",
    "sg:tags":[
        "repairing",
        "automobile"
    ],
    "wof:name":"Three Brydges Auto Sls & Svc",
    "wof:placetype":"venue"
},
  "geometry": {"coordinates":[-80.99784099999999,43.05843],"type":"Point"}
}