{
  "type": "Feature",
  "properties": {
    "addr:full":"1300 Av Esioff-Patenaude Sillery QC G1T 2J6",
    "addr:housenumber":"1300",
    "addr:postcode":"g1t 2j6",
    "addr:street":"Av Esioff-Patenaude",
    "iso:country":"CA",
    "sg:address":"1300 Av Esioff-Patenaude",
    "sg:city":"Sillery",
    "sg:classifiers":[
        {
            "category":"Professional",
            "subcategory":"Computer Services",
            "type":"Services"
        }
    ],
    "sg:phone":"+1 418 688 4289",
    "sg:postcode":"G1T 2J6",
    "sg:province":"QC",
    "sg:tags":[
        "information",
        "system",
        "consultant"
    ],
    "wof:name":"Bourgeois L'Ecuyer & Assoc Inc",
    "wof:placetype":"venue"
},
  "geometry": {"coordinates":[-71.263733,46.773891],"type":"Point"}
}