{
  "type": "Feature",
  "properties": {
    "addr:full":"Calgary AB T2P 2Y6",
    "addr:postcode":"t2p 2y6",
    "iso:country":"CA",
    "sg:city":"Calgary",
    "sg:classifiers":[
        {
            "category":"Banks & Credit Unions",
            "subcategory":"Bank",
            "type":"Services"
        }
    ],
    "sg:phone":"+1 403 270 7000",
    "sg:postcode":"T2P 2Y6",
    "sg:province":"AB",
    "sg:tags":[
        "loan",
        "real estate"
    ],
    "wof:name":"Gibraltar Mortgage Ltd",
    "wof:placetype":"venue"
},
  "geometry": {"coordinates":[-114.084007263,51.0453224182],"type":"Point"}
}