{
  "type": "Feature",
  "properties": {
    "addr:full":"1721 Nicholson St S Prince George BC V2N 1V7",
    "addr:housenumber":"1721",
    "addr:postcode":"v2n 1v7",
    "addr:street":"Nicholson St S",
    "iso:country":"CA",
    "sg:address":"1721 Nicholson St S",
    "sg:city":"Prince George",
    "sg:classifiers":[
        {
            "category":"Building & Trades",
            "subcategory":"Construction",
            "type":"Services"
        }
    ],
    "sg:phone":"+1 250 562 6620",
    "sg:postcode":"V2N 1V7",
    "sg:province":"BC",
    "sg:tags":[
        "builder",
        "stair",
        "contractor"
    ],
    "wof:name":"Caledonia Stairs Mantels-More",
    "wof:placetype":"venue"
},
  "geometry": {"coordinates":[-122.78616332999999,53.9083862305],"type":"Point"}
}