{
  "type": "Feature",
  "properties": {
    "addr:full":"90 Parkway Cres Bowmanville ON L1C 1C3",
    "addr:housenumber":"90",
    "addr:postcode":"l1c 1c3",
    "addr:street":"Parkway Cres",
    "iso:country":"CA",
    "sg:address":"90 Parkway Cres",
    "sg:city":"Bowmanville",
    "sg:classifiers":[
        {
            "category":"Education",
            "subcategory":"School",
            "type":"Public Place"
        }
    ],
    "sg:phone":"+1 905 623 5151",
    "sg:postcode":"L1C 1C3",
    "sg:province":"ON",
    "wof:name":"St Joseph's School",
    "wof:placetype":"venue"
},
  "geometry": {"coordinates":[-78.674812,43.903233],"type":"Point"}
}