{
  "type": "Feature",
  "properties": {
    "iso:country":"CA",
    "sg:city":"Thornhill",
    "sg:classifiers":[
        {
            "category":"Health Services",
            "subcategory":"Medical Lab",
            "type":"Services"
        }
    ],
    "sg:phone":"+1 905 771 7221",
    "sg:postcode":"L3T 5W4",
    "sg:province":"ON",
    "sg:tags":[
        "laboratory"
    ],
    "wof:name":"Leon's Dental Art Ltd",
    "wof:placetype":"venue"
},
  "geometry": {"coordinates":[-79.397263,43.819481],"type":"Point"}
}