{
  "type": "Feature",
  "properties": {
    "iso:country":"CA",
    "sg:address":"11019 137 Ave NW",
    "sg:city":"Edmonton",
    "sg:classifiers":[
        {
            "category":"Wholesale",
            "subcategory":"Hardware",
            "type":"Manufacturing & Wholesale Goods"
        }
    ],
    "sg:phone":"+1 780 475 4067",
    "sg:postcode":"T5E 1Z2",
    "sg:province":"AB",
    "sg:tags":[
        "purifying",
        "cleaning",
        "air"
    ],
    "wof:name":"Lcs Svc Ltd",
    "wof:placetype":"venue"
},
  "geometry": {"coordinates":[-113.510421753,53.5990524292],"type":"Point"}
}