{
  "type": "Feature",
  "properties": {
    "addr:full":"Richmond BC V6V 2N4",
    "addr:postcode":"v6v 2n4",
    "iso:country":"CA",
    "sg:city":"Richmond",
    "sg:classifiers":[
        {
            "category":"Manufacturing",
            "subcategory":"Apparel",
            "type":"Manufacturing & Wholesale Goods"
        }
    ],
    "sg:phone":"+1 604 231 8248",
    "sg:postcode":"V6V 2N4",
    "sg:province":"BC",
    "sg:tags":[
        "clothing"
    ],
    "wof:name":"Kimberly Garments Ltd",
    "wof:placetype":"venue"
},
  "geometry": {"coordinates":[-123.084739685,49.1914367676],"type":"Point"}
}