{
  "type": "Feature",
  "properties": {
    "addr:full":"1301 Victoria Ave E Thunder Bay ON P7C 1C3",
    "addr:housenumber":"1301",
    "addr:postcode":"p7c 1c3",
    "addr:street":"Victoria Ave E",
    "iso:country":"CA",
    "sg:address":"1301 Victoria Ave E",
    "sg:city":"Thunder Bay",
    "sg:classifiers":[
        {
            "category":"Insurance",
            "subcategory":"Insurance Agent",
            "type":"Services"
        }
    ],
    "sg:phone":"+1 807 623 4848",
    "sg:postcode":"P7C 1C3",
    "sg:province":"ON",
    "wof:name":"Willport Realty Ltd",
    "wof:placetype":"venue"
},
  "geometry": {"coordinates":[-89.255447,48.38427],"type":"Point"}
}