{
  "type": "Feature",
  "properties": {
    "addr:full":"86 Centennial St # 7 Mackenzie BC V0J 2C0",
    "addr:housenumber":"86",
    "addr:postcode":"v0j 2c0",
    "addr:street":"Centennial St # 7",
    "iso:country":"CA",
    "sg:address":"86 Centennial St # 7",
    "sg:city":"Mackenzie",
    "sg:classifiers":[
        {
            "category":"Social Services",
            "type":"Services"
        }
    ],
    "sg:phone":"+1 250 997 4593",
    "sg:postcode":"V0J 2C0",
    "sg:province":"BC",
    "sg:tags":[
        "senior",
        "citizen"
    ],
    "wof:name":"Club 55 Senior's",
    "wof:placetype":"venue"
},
  "geometry": {"coordinates":[-123.08889770499999,55.3373603821],"type":"Point"}
}