{
  "type": "Feature",
  "properties": {
    "addr:full":"182 Wellington St Bowmanville ON L1C 1W3",
    "addr:housenumber":"182",
    "addr:postcode":"l1c 1w3",
    "addr:street":"Wellington St",
    "iso:country":"CA",
    "sg:address":"182 Wellington St",
    "sg:city":"Bowmanville",
    "sg:classifiers":[
        {
            "category":"Manufacturing",
            "subcategory":"Printing",
            "type":"Manufacturing & Wholesale Goods"
        }
    ],
    "sg:phone":"+1 905 623 1155",
    "sg:postcode":"L1C 1W3",
    "sg:province":"ON",
    "sg:tags":[
        "printer"
    ],
    "wof:name":"Mothersill Printing Inc",
    "wof:placetype":"venue"
},
  "geometry": {"coordinates":[-78.6936416626,43.915851593],"type":"Point"}
}