{
  "type": "Feature",
  "properties": {
    "addr:full":"60 Rte Leblanc Pabos QC G0C 2H0",
    "addr:housenumber":"60",
    "addr:postcode":"g0c 2h0",
    "addr:street":"Rte Leblanc Pabos",
    "iso:country":"CA",
    "sg:address":"60 Rte Leblanc",
    "sg:city":"Pabos",
    "sg:classifiers":[
        {
            "category":"Building & Trades",
            "subcategory":"Construction",
            "type":"Services"
        }
    ],
    "sg:phone":"+1 418 689 5050",
    "sg:postcode":"G0C 2H0",
    "sg:province":"QC",
    "sg:tags":[
        "general",
        "contractor"
    ],
    "wof:name":"Construction Michel Leblanc",
    "wof:placetype":"venue"
},
  "geometry": {"coordinates":[-64.640175,48.363552],"type":"Point"}
}