{
  "type": "Feature",
  "properties": {
    "addr:full":"825 Browns Line Etobicoke ON M8W 3V7",
    "addr:housenumber":"825",
    "addr:postcode":"m8w 3v7",
    "addr:street":"Browns Line",
    "iso:country":"CA",
    "sg:address":"825 Browns Line",
    "sg:city":"Etobicoke",
    "sg:classifiers":[
        {
            "category":"Personal",
            "subcategory":"Beauty Salon",
            "type":"Services"
        }
    ],
    "sg:phone":"+1 416 255 2131",
    "sg:postcode":"M8W 3V7",
    "sg:province":"ON",
    "wof:name":"Joseph & Nicholas Coiffures",
    "wof:placetype":"venue"
},
  "geometry": {"coordinates":[-79.548019,43.60865],"type":"Point"}
}