{
  "type": "Feature",
  "properties": {
    "iso:country":"CA",
    "sg:address":"4063 Boul Saint-Jean",
    "sg:city":"Dollard-Des-Ormeaux",
    "sg:classifiers":[
        {
            "category":"Retail",
            "subcategory":"Laundry & Dry Cleaning",
            "type":"Services"
        }
    ],
    "sg:phone":"+1 514 620 5543",
    "sg:postcode":"H9G 2R4",
    "sg:province":"QC",
    "sg:tags":[
        "cleaners"
    ],
    "wof:name":"Betty Brite Ddo",
    "wof:placetype":"venue"
},
  "geometry": {"coordinates":[-73.838684082,45.4773406982],"type":"Point"}
}