{
  "type": "Feature",
  "properties": {
    "addr:full":"2639 Black Rock Rd Waterville NS B0P 1V0",
    "addr:housenumber":"2639",
    "addr:postcode":"b0p 1v0",
    "addr:street":"Black Rock Rd",
    "iso:country":"CA",
    "sg:address":"2639 Black Rock Rd",
    "sg:city":"Waterville",
    "sg:classifiers":[
        {
            "category":"Organizations",
            "subcategory":"Religious Organization",
            "type":"Services"
        }
    ],
    "sg:phone":"+1 902 538 1197",
    "sg:postcode":"B0P 1V0",
    "sg:province":"NS",
    "sg:tags":[
        "church"
    ],
    "wof:name":"Annapolis Valley Church of God",
    "wof:placetype":"venue"
},
  "geometry": {"coordinates":[-64.677986,45.052334],"type":"Point"}
}