{
  "type": "Feature",
  "properties": {
    "addr:full":"136 Adelaide St E Toronto ON M5C 1K9",
    "addr:housenumber":"136",
    "addr:postcode":"m5c 1k9",
    "addr:street":"Adelaide St E",
    "iso:country":"CA",
    "sg:address":"136 Adelaide St E",
    "sg:city":"Toronto",
    "sg:classifiers":[
        {
            "category":"Shopping",
            "subcategory":"Clothing, Apparel, & Fashions",
            "type":"Retail Goods"
        }
    ],
    "sg:phone":"+1 416 941 9280",
    "sg:postcode":"M5C 1K9",
    "sg:province":"ON",
    "wof:name":"Studio No Fashion Design",
    "wof:placetype":"venue"
},
  "geometry": {"coordinates":[-79.37284088129999,43.6517562866],"type":"Point"}
}