{
  "type": "Feature",
  "properties": {
    "addr:full":"7820 Venture St Burnaby BC V5A 1V3",
    "addr:housenumber":"7820",
    "addr:postcode":"v5a 1v3",
    "addr:street":"Venture St",
    "iso:country":"CA",
    "sg:address":"7820 Venture St",
    "sg:city":"Burnaby",
    "sg:classifiers":[
        {
            "category":"Wholesale",
            "subcategory":"Electrical",
            "type":"Manufacturing & Wholesale Goods"
        }
    ],
    "sg:phone":"+1 604 444 4502",
    "sg:postcode":"V5A 1V3",
    "sg:province":"BC",
    "sg:tags":[
        "video",
        "disc",
        "tape"
    ],
    "wof:name":"Tape House",
    "wof:placetype":"venue"
},
  "geometry": {"coordinates":[-122.937171936,49.257434845],"type":"Point"}
}