{
  "type": "Feature",
  "properties": {
    "addr:full":"Harrowsmith ON K0H 1V0",
    "addr:postcode":"k0h 1v0",
    "iso:country":"CA",
    "sg:city":"Harrowsmith",
    "sg:classifiers":[
        {
            "category":"Building & Trades",
            "subcategory":"Landscaping Services",
            "type":"Services"
        }
    ],
    "sg:phone":"+1 613 539 0537",
    "sg:postcode":"K0H 1V0",
    "sg:province":"ON",
    "sg:tags":[
        "tree"
    ],
    "wof:name":"Alpine Valley Tree Specialists",
    "wof:placetype":"venue"
},
  "geometry": {"coordinates":[-76.66557312010001,44.4049949646],"type":"Point"}
}