{
  "type": "Feature",
  "properties": {
    "addr:full":"5 Kennedy Ch Sainte-Cecile-DE-Masham QC J0X 2W0",
    "addr:housenumber":"5",
    "addr:postcode":"j0x 2w0",
    "addr:street":"Kennedy Ch Sainte-Cecile-De-Masham",
    "iso:country":"CA",
    "sg:address":"5 Kennedy Ch",
    "sg:city":"Sainte-Cecile-DE-Masham",
    "sg:classifiers":[
        {
            "category":"Shopping",
            "subcategory":"Computers & Home Electronics",
            "type":"Retail Goods"
        }
    ],
    "sg:phone":"+1 819 456 2176",
    "sg:postcode":"J0X 2W0",
    "sg:province":"QC",
    "sg:tags":[
        "equipment",
        "video"
    ],
    "wof:name":"Video Kennedy",
    "wof:placetype":"venue"
},
  "geometry": {"coordinates":[-76.037392,45.64109],"type":"Point"}
}