{
  "type": "Feature",
  "properties": {
    "addr:full":"327 Rue Matton Granby QC J2G 7R1",
    "addr:housenumber":"327",
    "addr:postcode":"j2g 7r1",
    "addr:street":"Rue Matton",
    "iso:country":"CA",
    "sg:address":"327 Rue Matton",
    "sg:city":"Granby",
    "sg:classifiers":[
        {
            "category":"Social Services",
            "type":"Services"
        }
    ],
    "sg:phone":"+1 450 378 0221",
    "sg:postcode":"J2G 7R1",
    "sg:province":"QC",
    "sg:tags":[
        "organization",
        "welfare"
    ],
    "wof:name":"Sos Depannage Granby Et Rgn",
    "wof:placetype":"venue"
},
  "geometry": {"coordinates":[-72.742355,45.393353],"type":"Point"}
}