{
  "type": "Feature",
  "properties": {
    "addr:full":"63 Rue Principale Saint-Leonard-D'Aston QC J0C 1M0",
    "addr:housenumber":"63",
    "addr:postcode":"j0c 1m0",
    "addr:street":"Rue Principale",
    "iso:country":"CA",
    "sg:address":"63 Rue Principale",
    "sg:city":"Saint-Leonard-D'Aston",
    "sg:classifiers":[
        {
            "category":"Banks & Credit Unions",
            "subcategory":"Bank",
            "type":"Services"
        }
    ],
    "sg:phone":"+1 819 399 2224",
    "sg:postcode":"J0C 1M0",
    "sg:province":"QC",
    "wof:name":"Banque Nationale Du Canada",
    "wof:placetype":"venue"
},
  "geometry": {"coordinates":[-68.1390380859,48.4557762146],"type":"Point"}
}