{
  "type": "Feature",
  "properties": {
    "addr:full":"105 Rue Ontario E Montreal QC H2X 1G9",
    "addr:housenumber":"105",
    "addr:postcode":"h2x 1g9",
    "addr:street":"Rue Ontario E",
    "iso:country":"CA",
    "sg:address":"105 Rue Ontario E",
    "sg:city":"Montreal",
    "sg:classifiers":[
        {
            "category":"Communications",
            "subcategory":"Film & Video Production",
            "type":"Services"
        }
    ],
    "sg:phone":"+1 514 985 2285",
    "sg:postcode":"H2X 1G9",
    "sg:province":"QC",
    "sg:tags":[
        "motion",
        "picture",
        "studio",
        "producer"
    ],
    "wof:name":"Bloom Films-Project Station N",
    "wof:placetype":"venue"
},
  "geometry": {"coordinates":[-73.56658899999999,45.512314],"type":"Point"}
}