{
  "type": "Feature",
  "properties": {
    "addr:full":"116 Kent Ave Kitchener ON N2G 3R1",
    "addr:housenumber":"116",
    "addr:postcode":"n2g 3r1",
    "addr:street":"Kent Ave",
    "iso:country":"CA",
    "sg:address":"116 Kent Ave",
    "sg:city":"Kitchener",
    "sg:classifiers":[
        {
            "category":"Autos & Motor Vehicles",
            "subcategory":"Auto Supplies",
            "type":"Retail Goods"
        }
    ],
    "sg:phone":"+1 519 745 5182",
    "sg:postcode":"N2G 3R1",
    "sg:province":"ON",
    "sg:tags":[
        "tire"
    ],
    "wof:name":"Colonial Tire Svc",
    "wof:placetype":"venue"
},
  "geometry": {"coordinates":[-80.47909545900001,43.4413261414],"type":"Point"}
}