{
  "type": "Feature",
  "properties": {
    "addr:full":"1757 Burlington St E Hamilton ON L8H 3L5",
    "addr:housenumber":"1757",
    "addr:postcode":"l8h 3l5",
    "addr:street":"Burlington St E",
    "iso:country":"CA",
    "sg:address":"1757 Burlington St E",
    "sg:city":"Hamilton",
    "sg:classifiers":[
        {
            "category":"Manufacturing",
            "subcategory":"Tools & Machinery",
            "type":"Manufacturing & Wholesale Goods"
        }
    ],
    "sg:phone":"+1 905 312 4776",
    "sg:postcode":"L8H 3L5",
    "sg:province":"ON",
    "sg:tags":[
        "water",
        "equipment",
        "works",
        "supply"
    ],
    "wof:name":"Bibby Water Works Div Canada",
    "wof:placetype":"venue"
},
  "geometry": {"coordinates":[-79.789467,43.25713],"type":"Point"}
}