{
  "type": "Feature",
  "properties": {
    "addr:full":"Picton ON K0K 2T0",
    "addr:postcode":"k0k 2t0",
    "iso:country":"CA",
    "sg:city":"Picton",
    "sg:classifiers":[
        {
            "category":"Health Services",
            "subcategory":"Chiropractor",
            "type":"Services"
        }
    ],
    "sg:phone":"+1 613 476 4645",
    "sg:postcode":"K0K 2T0",
    "sg:province":"ON",
    "wof:name":"Gerow, Todd DC",
    "wof:placetype":"venue"
},
  "geometry": {"coordinates":[-77.13706970210001,44.0148582458],"type":"Point"}
}