{
  "type": "Feature",
  "properties": {
    "iso:country":"CA",
    "sg:address":"765 Exeter Rd",
    "sg:city":"London",
    "sg:classifiers":[
        {
            "category":"Restaurant",
            "type":"Food & Drink"
        }
    ],
    "sg:phone":"+1 519 686 6025",
    "sg:postcode":"N6E 3T2",
    "sg:province":"ON",
    "wof:name":"Outback Steakhouse",
    "wof:placetype":"venue"
},
  "geometry": {"coordinates":[-81.218842,42.925613],"type":"Point"}
}