{
  "type": "Feature",
  "properties": {
    "addr:full":"7127 79 Ave NW Edmonton AB T6B 0C2",
    "addr:housenumber":"7127",
    "addr:postcode":"t6b 0c2",
    "addr:street":"79 Ave Nw",
    "iso:country":"CA",
    "sg:address":"7127 79 Ave NW",
    "sg:city":"Edmonton",
    "sg:classifiers":[
        {
            "category":"Social Services",
            "subcategory":"Adult Care",
            "type":"Services"
        }
    ],
    "sg:phone":"+1 780 422 3088",
    "sg:postcode":"T6B 0C2",
    "sg:province":"AB",
    "sg:tags":[
        "home"
    ],
    "wof:name":"King Edward Park Group Home",
    "wof:placetype":"venue"
},
  "geometry": {"coordinates":[-113.437423706,53.5149230957],"type":"Point"}
}