{
  "type": "Feature",
  "properties": {
    "iso:country":"CA",
    "sg:address":"3305 Fairview St",
    "sg:city":"Burlington",
    "sg:classifiers":[
        {
            "category":"Shopping",
            "subcategory":"Clothing, Apparel, & Fashions",
            "type":"Retail Goods"
        }
    ],
    "sg:phone":"+1 905 634 2371",
    "sg:postcode":"L7N 3N9",
    "sg:province":"ON",
    "sg:tags":[
        "furnishing"
    ],
    "wof:name":"Moore's Clothing For Men",
    "wof:placetype":"venue"
},
  "geometry": {"coordinates":[-79.7869110107,43.3535919189],"type":"Point"}
}