{
  "type": "Feature",
  "properties": {
    "addr:full":"1818 Weston Rd York ON M9N 1V8",
    "addr:housenumber":"1818",
    "addr:postcode":"m9n 1v8",
    "addr:street":"Weston Rd",
    "iso:country":"CA",
    "sg:address":"1818 Weston Rd",
    "sg:city":"York",
    "sg:classifiers":[
        {
            "category":"Home & Garden",
            "subcategory":"Furniture",
            "type":"Retail Goods"
        }
    ],
    "sg:phone":"+1 416 244 2059",
    "sg:postcode":"M9N 1V8",
    "sg:province":"ON",
    "wof:name":"Edel Furniture Ltd",
    "wof:placetype":"venue"
},
  "geometry": {"coordinates":[-79.51406900000001,43.699207],"type":"Point"}
}