{
  "type": "Feature",
  "properties": {
    "addr:full":"1400 78th Ave Grand Forks BC V0H 1H0",
    "addr:housenumber":"1400",
    "addr:postcode":"v0h 1h0",
    "addr:street":"78Th Ave",
    "iso:country":"CA",
    "sg:address":"1400 78th Ave",
    "sg:city":"Grand Forks",
    "sg:classifiers":[
        {
            "category":"Building & Trades",
            "subcategory":"Cleaning & Sanitation",
            "type":"Services"
        }
    ],
    "sg:phone":"+1 250 442 5202",
    "sg:postcode":"V0H 1H0",
    "sg:province":"BC",
    "sg:tags":[
        "house"
    ],
    "wof:name":"Sparkle 'N Shine",
    "wof:placetype":"venue"
},
  "geometry": {"coordinates":[-118.45174400000001,49.034046],"type":"Point"}
}