{
  "type": "Feature",
  "properties": {
    "addr:full":"Vancouver BC V6M 1Y9",
    "addr:postcode":"v6m 1y9",
    "iso:country":"CA",
    "sg:city":"Vancouver",
    "sg:classifiers":[
        {
            "category":"Personal",
            "subcategory":"Beauty Salon",
            "type":"Services"
        }
    ],
    "sg:phone":"+1 604 263 3636",
    "sg:postcode":"V6M 1Y9",
    "sg:province":"BC",
    "sg:tags":[
        "consultant",
        "health"
    ],
    "wof:name":"Jenny Pearson Esthetic Studio",
    "wof:placetype":"venue"
},
  "geometry": {"coordinates":[-123.15458700000001,49.234402],"type":"Point"}
}