{
  "type": "Feature",
  "properties": {
    "addr:full":"PO Box 24 Hoey SK S0J 1E0",
    "addr:housenumber":"po box 24",
    "addr:postcode":"s0j 1e0",
    "addr:street":"Hoey",
    "iso:country":"CA",
    "sg:address":"PO Box 24",
    "sg:city":"Hoey",
    "sg:classifiers":[
        {
            "category":"Building & Trades",
            "subcategory":"Electrical",
            "type":"Services"
        }
    ],
    "sg:phone":"+1 306 423 5508",
    "sg:postcode":"S0J 1E0",
    "sg:province":"SK",
    "sg:tags":[
        "electric",
        "contractor"
    ],
    "wof:name":"Trumier Electric",
    "wof:placetype":"venue"
},
  "geometry": {"coordinates":[-105.787277,52.864979],"type":"Point"}
}