{
  "type": "Feature",
  "properties": {
    "addr:full":"1335 Killarney Bay Rd Cameron ON K0M 1G0",
    "addr:housenumber":"1335",
    "addr:postcode":"k0m 1g0",
    "addr:street":"Killarney Bay Rd",
    "iso:country":"CA",
    "sg:address":"1335 Killarney Bay Rd",
    "sg:city":"Cameron",
    "sg:classifiers":[
        {
            "category":"Travel",
            "subcategory":"Campground",
            "type":"Entertainment"
        }
    ],
    "sg:phone":"+1 705 887 3420",
    "sg:postcode":"K0M 1G0",
    "sg:province":"ON",
    "wof:name":"Kenhaven Trailer Park",
    "wof:placetype":"venue"
},
  "geometry": {"coordinates":[-78.774597,44.439243],"type":"Point"}
}