{
  "type": "Feature",
  "properties": {
    "addr:full":"11515 Boul Louis-H.-Lafontaine Montreal QC H1E 7M1",
    "addr:housenumber":"11515",
    "addr:postcode":"h1e 7m1",
    "addr:street":"Boul Louis-H.-Lafontaine",
    "iso:country":"CA",
    "sg:address":"11515 Boul Louis-H.-Lafontaine",
    "sg:city":"Montreal",
    "sg:classifiers":[
        {
            "category":"Manufacturing",
            "subcategory":"Food",
            "type":"Manufacturing & Wholesale Goods"
        }
    ],
    "sg:phone":"+1 514 643 4341",
    "sg:postcode":"H1E 7M1",
    "sg:province":"QC",
    "sg:tags":[
        "grocer",
        "product",
        "manufacturer"
    ],
    "wof:name":"Provisions Marquis Inc",
    "wof:placetype":"venue"
},
  "geometry": {"coordinates":[-73.5996246338,45.6186103821],"type":"Point"}
}