{
  "type": "Feature",
  "properties": {
    "iso:country":"CA",
    "sg:address":"2881 Brighton Rd",
    "sg:city":"Oakville",
    "sg:classifiers":[
        {
            "category":"Wholesale",
            "subcategory":"Apparel",
            "type":"Manufacturing & Wholesale Goods"
        }
    ],
    "sg:phone":"+1 905 829 1825",
    "sg:postcode":"L6H 6C9",
    "sg:province":"ON",
    "sg:tags":[
        "shoes"
    ],
    "wof:name":"Clarks of England",
    "wof:placetype":"venue"
},
  "geometry": {"coordinates":[-79.6791305542,43.5156707764],"type":"Point"}
}