{
  "type": "Feature",
  "properties": {
    "addr:full":"175 Yonge St Midland ON L4R 2A7",
    "addr:housenumber":"175",
    "addr:postcode":"l4r 2a7",
    "addr:street":"Yonge St",
    "iso:country":"CA",
    "sg:address":"175 Yonge St",
    "sg:city":"Midland",
    "sg:classifiers":[
        {
            "category":"Social Services",
            "type":"Services"
        }
    ],
    "sg:phone":"+1 705 527 1560",
    "sg:postcode":"L4R 2A7",
    "sg:province":"ON",
    "sg:tags":[
        "information",
        "center",
        "diabetes"
    ],
    "wof:name":"Soadi",
    "wof:placetype":"venue"
},
  "geometry": {"coordinates":[-79.869438,44.752369],"type":"Point"}
}