{
  "type": "Feature",
  "properties": {
    "addr:full":"1091 Bathurst St Toronto ON M5R 3G8",
    "addr:housenumber":"1091",
    "addr:postcode":"m5r 3g8",
    "addr:street":"Bathurst St",
    "iso:country":"CA",
    "sg:address":"1091 Bathurst St",
    "sg:city":"Toronto",
    "sg:classifiers":[
        {
            "category":"Shopping",
            "subcategory":"Used Merchandise",
            "type":"Retail Goods"
        }
    ],
    "sg:phone":"+1 416 538 4428",
    "sg:postcode":"M5R 3G8",
    "sg:province":"ON",
    "sg:tags":[
        "antique"
    ],
    "wof:name":"Variations Boutique",
    "wof:placetype":"venue"
},
  "geometry": {"coordinates":[-79.414085,43.672894],"type":"Point"}
}