{
  "type": "Feature",
  "properties": {
    "addr:full":"620 Lauder Ave York ON M6E 3J7",
    "addr:housenumber":"620",
    "addr:postcode":"m6e 3j7",
    "addr:street":"Lauder Ave",
    "iso:country":"CA",
    "sg:address":"620 Lauder Ave",
    "sg:city":"York",
    "sg:classifiers":[
        {
            "category":"Building & Trades",
            "subcategory":"Construction",
            "type":"Services"
        }
    ],
    "sg:phone":"+1 416 651 9962",
    "sg:postcode":"M6E 3J7",
    "sg:province":"ON",
    "sg:tags":[
        "excavating",
        "contractor"
    ],
    "wof:name":"Forli Excavating & Demo",
    "wof:placetype":"venue"
},
  "geometry": {"coordinates":[-79.445671,43.692883],"type":"Point"}
}