{
  "type": "Feature",
  "properties": {
    "addr:full":"1100 Rg Sud Saint-Thomas QC J0K 3L0",
    "addr:housenumber":"1100",
    "addr:postcode":"j0k 3l0",
    "addr:street":"Rg Sud",
    "iso:country":"CA",
    "sg:address":"1100 Rg Sud",
    "sg:city":"Saint-Thomas",
    "sg:classifiers":[
        {
            "category":"Wholesale",
            "subcategory":"Farm Supplies",
            "type":"Manufacturing & Wholesale Goods"
        }
    ],
    "sg:phone":"+1 450 759 7219",
    "sg:postcode":"J0K 3L0",
    "sg:province":"QC",
    "sg:tags":[
        "control",
        "equipment",
        "fertilizer",
        "pest"
    ],
    "wof:name":"Produits Harnois Inc",
    "wof:placetype":"venue"
},
  "geometry": {"coordinates":[-73.350067,46.01553],"type":"Point"}
}