{
  "type": "Feature",
  "properties": {
    "addr:full":"969 Wellington St W Ottawa ON K1Y 2X7",
    "addr:housenumber":"969",
    "addr:postcode":"k1y 2x7",
    "addr:street":"Wellington St W",
    "iso:country":"CA",
    "sg:address":"969 Wellington St W",
    "sg:city":"Ottawa",
    "sg:classifiers":[
        {
            "category":"Organizations",
            "subcategory":"Religious Organization",
            "type":"Services"
        }
    ],
    "sg:phone":"+1 613 728 5935",
    "sg:postcode":"K1Y 2X7",
    "sg:province":"ON",
    "sg:tags":[
        "church"
    ],
    "wof:name":"Eglesia DE Cristo Misionera",
    "wof:placetype":"venue"
},
  "geometry": {"coordinates":[-75.722649,45.406158],"type":"Point"}
}