{
  "type": "Feature",
  "properties": {
    "addr:full":"Terrebonne QC J6X 4N1",
    "addr:postcode":"j6x 4n1",
    "iso:country":"CA",
    "sg:city":"Terrebonne",
    "sg:classifiers":[
        {
            "category":"Health Services",
            "subcategory":"Doctor",
            "type":"Services"
        }
    ],
    "sg:phone":"+1 450 492 9999",
    "sg:postcode":"J6X 4N1",
    "sg:province":"QC",
    "sg:tags":[
        "clinic"
    ],
    "wof:name":"Physio-Ergo Plus",
    "wof:placetype":"venue"
},
  "geometry": {"coordinates":[-73.6797409058,45.7241821289],"type":"Point"}
}