{
  "type": "Feature",
  "properties": {
    "addr:full":"8704 53 Ave NW Edmonton AB T6E 5G2",
    "addr:housenumber":"8704",
    "addr:postcode":"t6e 5g2",
    "addr:street":"53 Ave Nw",
    "iso:country":"CA",
    "sg:address":"8704 53 Ave NW",
    "sg:city":"Edmonton",
    "sg:classifiers":[
        {
            "category":"Wholesale",
            "subcategory":"Groceries",
            "type":"Manufacturing & Wholesale Goods"
        }
    ],
    "sg:phone":"+1 780 463 2991",
    "sg:postcode":"T6E 5G2",
    "sg:province":"AB",
    "sg:tags":[
        "food",
        "product",
        "manufacturer"
    ],
    "wof:name":"Canyon Creek Soup CO",
    "wof:placetype":"venue"
},
  "geometry": {"coordinates":[-113.457909,53.489948],"type":"Point"}
}