{
  "type": "Feature",
  "properties": {
    "iso:country":"CA",
    "sg:address":"PO Box 6987 STN Main",
    "sg:city":"Peace River",
    "sg:classifiers":[
        {
            "category":"Building & Trades",
            "subcategory":"Construction",
            "type":"Services"
        }
    ],
    "sg:phone":"+1 780 624 4160",
    "sg:postcode":"T8S 1S7",
    "sg:province":"AB",
    "sg:tags":[
        "general",
        "contractor"
    ],
    "wof:name":"Ruel Brothers",
    "wof:placetype":"venue"
},
  "geometry": {"coordinates":[-117.290382385,56.2329711914],"type":"Point"}
}