{
  "type": "Feature",
  "properties": {
    "addr:full":"Richmond BC V6X 3Z8",
    "addr:postcode":"v6x 3z8",
    "iso:country":"CA",
    "sg:city":"Richmond",
    "sg:classifiers":[
        {
            "category":"Insurance",
            "subcategory":"Insurance Agent",
            "type":"Services"
        }
    ],
    "sg:phone":"+1 604 279 8638",
    "sg:postcode":"V6X 3Z8",
    "sg:province":"BC",
    "wof:name":"A & A Wong's",
    "wof:placetype":"venue"
},
  "geometry": {"coordinates":[-123.126801,49.183811],"type":"Point"}
}