{
  "type": "Feature",
  "properties": {
    "iso:country":"CA",
    "sg:address":"PO Box 322",
    "sg:city":"Grand Rapids",
    "sg:classifiers":[
        {
            "category":"Government",
            "subcategory":"Office",
            "type":"Public Place"
        }
    ],
    "sg:phone":"+1 204 639 2241",
    "sg:postcode":"R0C 1E0",
    "sg:province":"MB",
    "wof:name":"Manitoba Natural Resources",
    "wof:placetype":"venue"
},
  "geometry": {"coordinates":[-99.2845077515,53.1849594116],"type":"Point"}
}