{
  "type": "Feature",
  "properties": {
    "addr:full":"23 Rue Jacques-Cartier Salaberry-DE-Valleyfield QC J6T 4P7",
    "addr:housenumber":"23",
    "addr:postcode":"j6t 4p7",
    "addr:street":"Rue Jacques-Cartier",
    "iso:country":"CA",
    "sg:address":"23 Rue Jacques-Cartier",
    "sg:city":"Salaberry-DE-Valleyfield",
    "sg:classifiers":[
        {
            "category":"Retail",
            "subcategory":"Auto Repair",
            "type":"Services"
        }
    ],
    "sg:phone":"+1 450 373 5465",
    "sg:postcode":"J6T 4P7",
    "sg:province":"QC",
    "sg:tags":[
        "repairing",
        "automobile",
        "radiator"
    ],
    "wof:name":"Atelier-Radiateurs Valleyfield",
    "wof:placetype":"venue"
},
  "geometry": {"coordinates":[-74.12958526609999,45.2555503845],"type":"Point"}
}