{
  "type": "Feature",
  "properties": {
    "addr:full":"684 Tripp Settlement Rd Keswick Ridge NB E6L 1X2",
    "addr:housenumber":"684",
    "addr:postcode":"e6l 1x2",
    "addr:street":"Tripp Settlement Rd",
    "iso:country":"CA",
    "sg:address":"684 Tripp Settlement Rd",
    "sg:city":"Keswick Ridge",
    "sg:classifiers":[
        {
            "category":"Shopping",
            "subcategory":"Shoes",
            "type":"Retail Goods"
        }
    ],
    "sg:phone":"+1 506 363 4376",
    "sg:postcode":"E6L 1X2",
    "sg:province":"NB",
    "wof:name":"Touch the Earth Footwear",
    "wof:placetype":"venue"
},
  "geometry": {"coordinates":[-66.88110399999999,45.991375],"type":"Point"}
}