{
  "type": "Feature",
  "properties": {
    "addr:full":"5409 51st Ave Killam AB T0B 2L0",
    "addr:housenumber":"5409",
    "addr:postcode":"t0b 2l0",
    "addr:street":"51St Ave",
    "iso:country":"CA",
    "sg:address":"5409 51st Ave",
    "sg:city":"Killam",
    "sg:classifiers":[
        {
            "category":"Autos & Motor Vehicles",
            "subcategory":"Fuel & Gas Station",
            "type":"Retail Goods"
        }
    ],
    "sg:phone":"+1 780 385 3644",
    "sg:postcode":"T0B 2L0",
    "sg:province":"AB",
    "sg:tags":[
        "oil"
    ],
    "wof:name":"Jerry's Auto Svc",
    "wof:placetype":"venue"
},
  "geometry": {"coordinates":[-111.849510193,52.7918395996],"type":"Point"}
}