{
  "type": "Feature",
  "properties": {
    "addr:full":"Scarborough ON M1V 5H4",
    "addr:postcode":"m1v 5h4",
    "iso:country":"CA",
    "sg:city":"Scarborough",
    "sg:classifiers":[
        {
            "category":"Manufacturing",
            "subcategory":"Signs",
            "type":"Manufacturing & Wholesale Goods"
        }
    ],
    "sg:phone":"+1 416 609 8811",
    "sg:postcode":"M1V 5H4",
    "sg:province":"ON",
    "wof:name":"Broadway Signs & Graphics",
    "wof:placetype":"venue"
},
  "geometry": {"coordinates":[-79.29285400000001,43.809364],"type":"Point"}
}