{
  "type": "Feature",
  "properties": {
    "iso:country":"CA",
    "sg:city":"Victoriaville",
    "sg:classifiers":[
        {
            "category":"Organizations",
            "subcategory":"Professional Association",
            "type":"Services"
        }
    ],
    "sg:phone":"+1 819 758 0574",
    "sg:postcode":"G6P 1J8",
    "sg:province":"QC",
    "wof:name":"Association Pour L'Integration",
    "wof:placetype":"venue"
},
  "geometry": {"coordinates":[-71.966293335,46.0614814758],"type":"Point"}
}