{
  "type": "Feature",
  "properties": {
    "addr:full":"Coaticook QC J1A 2B2",
    "addr:postcode":"j1a 2b2",
    "iso:country":"CA",
    "sg:city":"Coaticook",
    "sg:classifiers":[
        {
            "category":"Real Estate",
            "subcategory":"Real Estate Agent",
            "type":"Services"
        }
    ],
    "sg:phone":"+1 819 849 2484",
    "sg:postcode":"J1A 2B2",
    "sg:province":"QC",
    "wof:name":"Lebel Immeubles",
    "wof:placetype":"venue"
},
  "geometry": {"coordinates":[-71.8045578003,45.1340370178],"type":"Point"}
}