{
  "type": "Feature",
  "properties": {
    "addr:full":"351 Reid St Quesnel BC V2J 2M5",
    "addr:housenumber":"351",
    "addr:postcode":"v2j 2m5",
    "addr:street":"Reid St",
    "iso:country":"CA",
    "sg:address":"351 Reid St",
    "sg:city":"Quesnel",
    "sg:classifiers":[
        {
            "category":"Food & Beverages",
            "subcategory":"Specialty",
            "type":"Retail Goods"
        }
    ],
    "sg:phone":"+1 250 991 0298",
    "sg:postcode":"V2J 2M5",
    "sg:province":"BC",
    "sg:tags":[
        "health",
        "diet"
    ],
    "wof:name":"River Valley Health Products",
    "wof:placetype":"venue"
},
  "geometry": {"coordinates":[-122.497017,52.978195],"type":"Point"}
}