{
  "type": "Feature",
  "properties": {
    "iso:country":"CA",
    "sg:address":"3199 Percy Ave",
    "sg:city":"Val Caron",
    "sg:classifiers":[
        {
            "category":"Retail",
            "subcategory":"Repair Shop",
            "type":"Services"
        }
    ],
    "sg:phone":"+1 705 897 6067",
    "sg:postcode":"P3N 1A4",
    "sg:province":"ON",
    "sg:tags":[
        "upholsterer"
    ],
    "wof:name":"Ava Upholstering",
    "wof:placetype":"venue"
},
  "geometry": {"coordinates":[-81.0361480713,46.6152000427],"type":"Point"}
}