{
  "type": "Feature",
  "properties": {
    "addr:full":"380 Armour Rd # 220 Peterborough ON K9H 7L7",
    "addr:housenumber":"380",
    "addr:postcode":"k9h 7l7",
    "addr:street":"Armour Rd # 220",
    "iso:country":"CA",
    "sg:address":"380 Armour Rd # 220",
    "sg:city":"Peterborough",
    "sg:classifiers":[
        {
            "category":"Professional",
            "subcategory":"Business Services",
            "type":"Services"
        }
    ],
    "sg:phone":"+1 705 749 5945",
    "sg:postcode":"K9H 7L7",
    "sg:province":"ON",
    "sg:tags":[
        "telemarketing"
    ],
    "wof:name":"Minacs Worldwide Inc",
    "wof:placetype":"venue"
},
  "geometry": {"coordinates":[-78.305038,44.306854],"type":"Point"}
}