{
  "type": "Feature",
  "properties": {
    "iso:country":"CA",
    "sg:city":"Bay Bulls",
    "sg:classifiers":[
        {
            "category":"Recreation",
            "type":"Entertainment"
        }
    ],
    "sg:phone":"+1 709 753 4850",
    "sg:postcode":"A0A 1C0",
    "sg:province":"NL",
    "sg:tags":[
        "tours",
        "sightseeing"
    ],
    "wof:name":"O'Brien's Whale & Bird Tours",
    "wof:placetype":"venue"
},
  "geometry": {"coordinates":[-52.8186035156,47.3170166016],"type":"Point"}
}