{
  "type": "Feature",
  "properties": {
    "addr:full":"Abbotsford BC V2T 6G9",
    "addr:postcode":"v2t 6g9",
    "iso:country":"CA",
    "sg:city":"Abbotsford",
    "sg:classifiers":[
        {
            "category":"Freight",
            "type":"Transportation"
        }
    ],
    "sg:phone":"+1 604 852 6059",
    "sg:postcode":"V2T 6G9",
    "sg:province":"BC",
    "sg:tags":[
        "mover"
    ],
    "wof:name":"Alert Moving & Storage",
    "wof:placetype":"venue"
},
  "geometry": {"coordinates":[-122.356407166,49.0434951782],"type":"Point"}
}