{
  "type": "Feature",
  "properties": {
    "addr:full":"6010 Boul Wilfrid-Hamel L'Ancienne-Lorette QC G2E 2H5",
    "addr:housenumber":"6010",
    "addr:postcode":"g2e 2h5",
    "addr:street":"Boul Wilfrid-Hamel",
    "iso:country":"CA",
    "sg:address":"6010 Boul Wilfrid-Hamel",
    "sg:city":"L'Ancienne-Lorette",
    "sg:classifiers":[
        {
            "category":"Professional",
            "subcategory":"Lawyer & Legal Services",
            "type":"Services"
        }
    ],
    "sg:phone":"+1 418 871 6060",
    "sg:postcode":"G2E 2H5",
    "sg:province":"QC",
    "sg:tags":[
        "attorney"
    ],
    "wof:name":"Noor, Chantal",
    "wof:placetype":"venue"
},
  "geometry": {"coordinates":[-71.3548736572,46.7887268066],"type":"Point"}
}