{
  "type": "Feature",
  "properties": {
    "addr:full":"168 Manitoba Dr Toronto ON M6K 3C3",
    "addr:housenumber":"168",
    "addr:postcode":"m6k 3c3",
    "addr:street":"Manitoba Dr",
    "iso:country":"CA",
    "sg:address":"168 Manitoba Dr",
    "sg:city":"Toronto",
    "sg:classifiers":[
        {
            "category":"Home & Garden",
            "subcategory":"Building Materials",
            "type":"Retail Goods"
        }
    ],
    "sg:phone":"+1 416 255 6666",
    "sg:postcode":"M6K 3C3",
    "sg:province":"ON",
    "sg:tags":[
        "shutter"
    ],
    "wof:name":"Look Through",
    "wof:placetype":"venue"
},
  "geometry": {"coordinates":[-79.41675600000001,43.635979],"type":"Point"}
}