{
  "type": "Feature",
  "properties": {
    "iso:country":"CA",
    "sg:address":"7655 Boul Henri-Bourassa E",
    "sg:city":"Montreal",
    "sg:classifiers":[
        {
            "category":"Retail",
            "subcategory":"Auto Repair",
            "type":"Services"
        }
    ],
    "sg:phone":"+1 514 494 4040",
    "sg:postcode":"H1E 1N9",
    "sg:province":"QC",
    "sg:tags":[
        "repairing",
        "automobile"
    ],
    "wof:name":"Gino & Tony Gt Automobile Inc",
    "wof:placetype":"venue"
},
  "geometry": {"coordinates":[-73.586594,45.622181],"type":"Point"}
}