{
  "type": "Feature",
  "properties": {
    "addr:full":"5651 River Rd Niagara Falls ON L2E 7M7",
    "addr:housenumber":"5651",
    "addr:postcode":"l2e 7m7",
    "addr:street":"River Rd",
    "iso:country":"CA",
    "sg:address":"5651 River Rd",
    "sg:city":"Niagara Falls",
    "sg:classifiers":[
        {
            "category":"Recreation",
            "type":"Entertainment"
        }
    ],
    "sg:phone":"+1 905 356 8888",
    "sg:postcode":"L2E 7M7",
    "sg:province":"ON",
    "sg:tags":[
        "attraction",
        "tourist"
    ],
    "wof:name":"Niagara Falls Aviary",
    "wof:placetype":"venue"
},
  "geometry": {"coordinates":[-79.067787,43.093407],"type":"Point"}
}