{
  "type": "Feature",
  "properties": {
    "addr:full":"Andrew AB T0B 0C0",
    "addr:postcode":"t0b 0c0",
    "iso:country":"CA",
    "sg:city":"Andrew",
    "sg:classifiers":[
        {
            "category":"Retail",
            "subcategory":"Auto Repair",
            "type":"Services"
        }
    ],
    "sg:phone":"+1 780 365 2112",
    "sg:postcode":"T0B 0C0",
    "sg:province":"AB",
    "sg:tags":[
        "body",
        "automobile",
        "painting"
    ],
    "wof:name":"Karmel Autobody",
    "wof:placetype":"venue"
},
  "geometry": {"coordinates":[-112.33522000000001,53.879864],"type":"Point"}
}