{
  "type": "Feature",
  "properties": {
    "iso:country":"CA",
    "sg:address":"5 Donald Pl",
    "sg:city":"St Albert",
    "sg:classifiers":[
        {
            "category":"Wholesale",
            "subcategory":"Stationery",
            "type":"Manufacturing & Wholesale Goods"
        }
    ],
    "sg:phone":"+1 780 459 6169",
    "sg:postcode":"T8N 6A8",
    "sg:province":"AB",
    "sg:tags":[
        "business",
        "form",
        "system"
    ],
    "wof:name":"Safeguard Systems By R Morris",
    "wof:placetype":"venue"
},
  "geometry": {"coordinates":[-113.64564514200001,53.6568908691],"type":"Point"}
}