{
  "type": "Feature",
  "properties": {
    "addr:full":"170 Bridgeport Rd E Waterloo ON N2J 2K5",
    "addr:housenumber":"170",
    "addr:postcode":"n2j 2k5",
    "addr:street":"Bridgeport Rd E",
    "iso:country":"CA",
    "sg:address":"170 Bridgeport Rd E",
    "sg:city":"Waterloo",
    "sg:classifiers":[
        {
            "category":"Personal",
            "subcategory":"Beauty Salon",
            "type":"Services"
        }
    ],
    "sg:phone":"+1 519 885 4040",
    "sg:postcode":"N2J 2K5",
    "sg:province":"ON",
    "wof:name":"Jan's Place",
    "wof:placetype":"venue"
},
  "geometry": {"coordinates":[-80.5071487427,43.471912384],"type":"Point"}
}