{
  "type": "Feature",
  "properties": {
    "addr:full":"Rocky Mountain House AB T4T 1B7",
    "addr:postcode":"t4t 1b7",
    "iso:country":"CA",
    "sg:city":"Rocky Mountain House",
    "sg:classifiers":[
        {
            "category":"Shopping",
            "type":"Retail Goods"
        }
    ],
    "sg:phone":"+1 403 845 5256",
    "sg:postcode":"T4T 1B7",
    "sg:province":"AB",
    "sg:tags":[
        "florist",
        "plant",
        "flower",
        "tree",
        "artificial"
    ],
    "wof:name":"Country Cottage Florists",
    "wof:placetype":"venue"
},
  "geometry": {"coordinates":[-114.919113,52.375858],"type":"Point"}
}