{
  "type": "Feature",
  "properties": {
    "addr:full":"207 10 Ave SW Calgary AB T2R 0A4",
    "addr:postcode":"t2r 0a4",
    "addr:street":"207 10 Ave Sw",
    "iso:country":"CA",
    "sg:address":"207 10 Ave SW",
    "sg:city":"Calgary",
    "sg:classifiers":[
        {
            "category":"Personal",
            "subcategory":"Massage",
            "type":"Services"
        }
    ],
    "sg:phone":"+1 403 237 9956",
    "sg:postcode":"T2R 0A4",
    "sg:province":"AB",
    "wof:name":"10th Avenue Place",
    "wof:placetype":"venue"
},
  "geometry": {"coordinates":[-114.06603241000001,51.0432472229],"type":"Point"}
}