{
  "type": "Feature",
  "properties": {
    "iso:country":"CA",
    "sg:city":"North Battleford",
    "sg:classifiers":[
        {
            "category":"Banks & Credit Unions",
            "subcategory":"Investment Brokerage",
            "type":"Services"
        }
    ],
    "sg:phone":"+1 306 445 5433",
    "sg:postcode":"S9A 0V7",
    "sg:province":"SK",
    "sg:tags":[
        "consultant",
        "planning",
        "financial"
    ],
    "wof:name":"Yahn Investment Planning",
    "wof:placetype":"venue"
},
  "geometry": {"coordinates":[-108.298851013,52.776058197],"type":"Point"}
}