{
  "type": "Feature",
  "properties": {
    "addr:full":"2158 213 St Bellevue AB T0K 0C0",
    "addr:housenumber":"2158",
    "addr:postcode":"t0k 0c0",
    "addr:street":"213 St",
    "iso:country":"CA",
    "sg:address":"2158 213 St",
    "sg:city":"Bellevue",
    "sg:classifiers":[
        {
            "category":"Health Services",
            "subcategory":"Doctor",
            "type":"Services"
        }
    ],
    "sg:phone":"+1 403 562 8804",
    "sg:postcode":"T0K 0C0",
    "sg:province":"AB",
    "sg:tags":[
        "physician",
        "surgeon"
    ],
    "wof:name":"Sara, William MD",
    "wof:placetype":"venue"
},
  "geometry": {"coordinates":[-114.369438,49.582138],"type":"Point"}
}