{
  "type": "Feature",
  "properties": {
    "addr:full":"681 10th St W Owen Sound ON N4K 3R8",
    "addr:housenumber":"681",
    "addr:postcode":"n4k 3r8",
    "addr:street":"10Th St W",
    "iso:country":"CA",
    "sg:address":"681 10th St W",
    "sg:city":"Owen Sound",
    "sg:classifiers":[
        {
            "category":"Insurance",
            "subcategory":"Insurance Agent",
            "type":"Services"
        }
    ],
    "sg:phone":"+1 519 376 0590",
    "sg:postcode":"N4K 3R8",
    "sg:province":"ON",
    "wof:name":"Miller Insurance Brokers Inc",
    "wof:placetype":"venue"
},
  "geometry": {"coordinates":[-80.956413269,44.5666275024],"type":"Point"}
}