{
  "type": "Feature",
  "properties": {
    "iso:country":"CA",
    "sg:address":"2323 Yonge St",
    "sg:city":"Toronto",
    "sg:classifiers":[
        {
            "category":"Professional",
            "subcategory":"Research",
            "type":"Services"
        }
    ],
    "sg:phone":"+1 416 489 4539",
    "sg:postcode":"M4P 2C9",
    "sg:province":"ON",
    "sg:tags":[
        "market",
        "analysis"
    ],
    "wof:name":"Health Care Marketing & Comms",
    "wof:placetype":"venue"
},
  "geometry": {"coordinates":[-79.3984909058,43.7080993652],"type":"Point"}
}