{
  "type": "Feature",
  "properties": {
    "addr:full":"86 Rue Saint-Hubert Chateauguay QC J6K 4A4",
    "addr:housenumber":"86",
    "addr:postcode":"j6k 4a4",
    "addr:street":"Rue Saint-Hubert",
    "iso:country":"CA",
    "sg:address":"86 Rue Saint-Hubert",
    "sg:city":"Chateauguay",
    "sg:classifiers":[
        {
            "category":"Shopping",
            "subcategory":"Shoes",
            "type":"Retail Goods"
        }
    ],
    "sg:phone":"+1 450 692 2569",
    "sg:postcode":"J6K 4A4",
    "sg:province":"QC",
    "wof:name":"Chaussures Pop",
    "wof:placetype":"venue"
},
  "geometry": {"coordinates":[-73.733101,45.353233],"type":"Point"}
}