{
  "type": "Feature",
  "properties": {
    "addr:full":"Winnipeg MB R3R 3V5",
    "addr:postcode":"r3r 3v5",
    "iso:country":"CA",
    "sg:city":"Winnipeg",
    "sg:classifiers":[
        {
            "category":"Organizations",
            "subcategory":"Non-profit Organization",
            "type":"Services"
        }
    ],
    "sg:phone":"+1 204 888 4653",
    "sg:postcode":"R3R 3V5",
    "sg:province":"MB",
    "sg:tags":[
        "fund",
        "counselor",
        "raising"
    ],
    "wof:name":"Million Dollar Hole-In-One Inc",
    "wof:placetype":"venue"
},
  "geometry": {"coordinates":[-97.26763916020001,49.8678855896],"type":"Point"}
}