{
  "type": "Feature",
  "properties": {
    "addr:full":"46 Boul Notre-Dame Clermont QC G4A 1C4",
    "addr:housenumber":"46",
    "addr:postcode":"g4a 1c4",
    "addr:street":"Boul Notre-Dame",
    "iso:country":"CA",
    "sg:address":"46 Boul Notre-Dame",
    "sg:city":"Clermont",
    "sg:classifiers":[
        {
            "category":"Manufacturing",
            "subcategory":"Tools & Machinery",
            "type":"Manufacturing & Wholesale Goods"
        }
    ],
    "sg:phone":"+1 418 439 2097",
    "sg:postcode":"G4A 1C4",
    "sg:province":"QC",
    "sg:tags":[
        "repairing",
        "automobile",
        "machine",
        "shop"
    ],
    "wof:name":"Garage Francis Bouchard Inc",
    "wof:placetype":"venue"
},
  "geometry": {"coordinates":[-70.2153625488,47.6881980896],"type":"Point"}
}