{
  "type": "Feature",
  "properties": {
    "addr:full":"1071 Goderich St Port Elgin ON N0H 2C3",
    "addr:housenumber":"1071",
    "addr:postcode":"n0h 2c3",
    "addr:street":"Goderich St",
    "iso:country":"CA",
    "sg:address":"1071 Goderich St",
    "sg:city":"Port Elgin",
    "sg:classifiers":[
        {
            "category":"Manufacturing",
            "subcategory":"Rubber & Plastics",
            "type":"Manufacturing & Wholesale Goods"
        }
    ],
    "sg:phone":"+1 519 389 4700",
    "sg:postcode":"N0H 2C3",
    "sg:province":"ON",
    "wof:name":"Carson's Custom Injection",
    "wof:placetype":"venue"
},
  "geometry": {"coordinates":[-81.37990570069999,44.4472198486],"type":"Point"}
}