{
  "type": "Feature",
  "properties": {
    "addr:full":"Gloucester ON K1J 9M2",
    "addr:postcode":"k1j 9m2",
    "iso:country":"CA",
    "sg:city":"Gloucester",
    "sg:classifiers":[
        {
            "category":"Professional",
            "subcategory":"Lawyer & Legal Services",
            "type":"Services"
        }
    ],
    "sg:phone":"+1 613 745 0395",
    "sg:postcode":"K1J 9M2",
    "sg:province":"ON",
    "sg:tags":[
        "attorney"
    ],
    "wof:name":"Mc Closkey & Mc Closkey",
    "wof:placetype":"venue"
},
  "geometry": {"coordinates":[-75.58841700000001,45.452522],"type":"Point"}
}