{
  "type": "Feature",
  "properties": {
    "addr:full":"2600 Boul DE Comporte LA Malbaie QC G5A 1N4",
    "addr:housenumber":"2600",
    "addr:postcode":"g5a 1n4",
    "addr:street":"Boul De Comporte",
    "iso:country":"CA",
    "sg:address":"2600 Boul DE Comporte",
    "sg:city":"LA Malbaie",
    "sg:classifiers":[
        {
            "category":"Wholesale",
            "subcategory":"Electrical",
            "type":"Manufacturing & Wholesale Goods"
        }
    ],
    "sg:phone":"+1 418 439 3916",
    "sg:postcode":"G5A 1N4",
    "sg:province":"QC",
    "sg:tags":[
        "harness",
        "wire"
    ],
    "wof:name":"Cables Bicc Canada Inc",
    "wof:placetype":"venue"
},
  "geometry": {"coordinates":[-70.199836731,47.6837806702],"type":"Point"}
}