{
  "type": "Feature",
  "properties": {
    "addr:full":"Oshawa ON L1J 5Z4",
    "addr:postcode":"l1j 5z4",
    "iso:country":"CA",
    "sg:city":"Oshawa",
    "sg:classifiers":[
        {
            "category":"Real Estate",
            "subcategory":"Real Estate Operator",
            "type":"Services"
        }
    ],
    "sg:phone":"+1 905 728 4993",
    "sg:postcode":"L1J 5Z4",
    "sg:province":"ON",
    "sg:tags":[
        "apartment"
    ],
    "wof:name":"Venice Park Developments Ltd",
    "wof:placetype":"venue"
},
  "geometry": {"coordinates":[-78.8562240601,43.8738861084],"type":"Point"}
}