{
  "type": "Feature",
  "properties": {
    "addr:full":"1203 Hollis St Halifax NS B3H 2P6",
    "addr:housenumber":"1203",
    "addr:postcode":"b3h 2p6",
    "addr:street":"Hollis St",
    "iso:country":"CA",
    "sg:address":"1203 Hollis St",
    "sg:city":"Halifax",
    "sg:classifiers":[
        {
            "category":"Professional",
            "subcategory":"Business Services",
            "type":"Services"
        }
    ],
    "sg:phone":"+1 902 422 0963",
    "sg:postcode":"B3H 2P6",
    "sg:province":"NS",
    "sg:tags":[
        "interior",
        "consultant",
        "design",
        "decorator"
    ],
    "wof:name":"Doucet-Watts & Davis Interiors",
    "wof:placetype":"venue"
},
  "geometry": {"coordinates":[-63.5688552856,44.6402015686],"type":"Point"}
}