{
  "type": "Feature",
  "properties": {
    "addr:full":"89 Rue Villeray L'Isle-Verte-Ouest QC G0L 1L0",
    "addr:housenumber":"89",
    "addr:postcode":"g0l 1l0",
    "addr:street":"Rue Villeray L'Isle-Verte-Ouest",
    "iso:country":"CA",
    "sg:address":"89 Rue Villeray",
    "sg:city":"L'Isle-Verte-Ouest",
    "sg:classifiers":[
        {
            "category":"Manufacturing",
            "subcategory":"Lumber",
            "type":"Manufacturing & Wholesale Goods"
        }
    ],
    "sg:phone":"+1 418 898 2641",
    "sg:postcode":"G0L 1L0",
    "sg:province":"QC",
    "sg:tags":[
        "sawmill"
    ],
    "wof:name":"Produits Forestiers Dube Inc",
    "wof:placetype":"venue"
},
  "geometry": {"coordinates":[-69.3451385498,48.0044517517],"type":"Point"}
}