{
  "type": "Feature",
  "properties": {
    "iso:country":"CA",
    "sg:address":"640 Main St",
    "sg:city":"Woodstock",
    "sg:classifiers":[
        {
            "category":"Wholesale",
            "subcategory":"Non-durable Goods",
            "type":"Manufacturing & Wholesale Goods"
        }
    ],
    "sg:phone":"+1 519 537 7759",
    "sg:postcode":"N4S 8Y5",
    "sg:province":"ON",
    "sg:tags":[
        "advertising"
    ],
    "wof:name":"Arrow Specialties",
    "wof:placetype":"venue"
},
  "geometry": {"coordinates":[-80.75020599370001,43.1274871826],"type":"Point"}
}