{
  "type": "Feature",
  "properties": {
    "iso:country":"CA",
    "sg:city":"Maxville",
    "sg:classifiers":[
        {
            "category":"Wholesale",
            "subcategory":"Farm Supplies",
            "type":"Manufacturing & Wholesale Goods"
        }
    ],
    "sg:phone":"+1 613 527 2175",
    "sg:postcode":"K0C 1T0",
    "sg:province":"ON",
    "sg:tags":[
        "feed",
        "fertilizer"
    ],
    "wof:name":"Mac Ewen Agricentre Inc",
    "wof:placetype":"venue"
},
  "geometry": {"coordinates":[-74.85712432859999,45.2858276367],"type":"Point"}
}