{
  "type": "Feature",
  "properties": {
    "iso:country":"CA",
    "sg:address":"42 Brucewood Cres",
    "sg:city":"North York",
    "sg:classifiers":[
        {
            "category":"Professional",
            "subcategory":"Art Services",
            "type":"Services"
        }
    ],
    "sg:phone":"+1 416 781 8379",
    "sg:postcode":"M6A 2G6",
    "sg:province":"ON",
    "sg:tags":[
        "photographer"
    ],
    "wof:name":"Silvio Calcagno Photography",
    "wof:placetype":"venue"
},
  "geometry": {"coordinates":[-79.4341812134,43.7210388184],"type":"Point"}
}