{
  "type": "Feature",
  "properties": {
    "addr:full":"Ottawa ON K1B 5R4",
    "addr:postcode":"k1b 5r4",
    "iso:country":"CA",
    "sg:city":"Ottawa",
    "sg:classifiers":[
        {
            "category":"Shopping",
            "subcategory":"Bicycles & Sporting Goods",
            "type":"Retail Goods"
        }
    ],
    "sg:phone":"+1 613 745 1177",
    "sg:postcode":"K1B 5R4",
    "sg:province":"ON",
    "sg:tags":[
        "exercise"
    ],
    "wof:name":"Kinetic Solutions",
    "wof:placetype":"venue"
},
  "geometry": {"coordinates":[-75.610596,45.405876],"type":"Point"}
}