{
  "type": "Feature",
  "properties": {
    "addr:full":"11420 156 St NW Edmonton AB T5M 3N2",
    "addr:housenumber":"11420",
    "addr:postcode":"t5m 3n2",
    "addr:street":"156 St Nw",
    "iso:country":"CA",
    "sg:address":"11420 156 St NW",
    "sg:city":"Edmonton",
    "sg:classifiers":[
        {
            "category":"Retail",
            "subcategory":"Repair Shop",
            "type":"Services"
        }
    ],
    "sg:phone":"+1 780 702 1686",
    "sg:postcode":"T5M 3N2",
    "sg:province":"AB",
    "sg:tags":[
        "tool",
        "parts"
    ],
    "wof:name":"Quality Tool Repair",
    "wof:placetype":"venue"
},
  "geometry": {"coordinates":[-113.59064499999999,53.56369],"type":"Point"}
}