{
  "type": "Feature",
  "properties": {
    "addr:full":"4330 Island Hwy S Courtenay BC V9N 9R9",
    "addr:housenumber":"4330",
    "addr:postcode":"v9n 9r9",
    "addr:street":"Island Hwy S",
    "iso:country":"CA",
    "sg:address":"4330 Island Hwy S",
    "sg:city":"Courtenay",
    "sg:classifiers":[
        {
            "category":"Travel",
            "subcategory":"Hotels & Motels",
            "type":"Entertainment"
        }
    ],
    "sg:phone":"+1 250 334 9966",
    "sg:postcode":"V9N 9R9",
    "sg:province":"BC",
    "sg:tags":[
        "resort",
        "health"
    ],
    "wof:name":"Kingfisher Oceanside Resort",
    "wof:placetype":"venue"
},
  "geometry": {"coordinates":[-124.990135,49.694324],"type":"Point"}
}