{
  "type": "Feature",
  "properties": {
    "addr:full":"1737 Rue Saint-Denis Montreal QC H2X 3K4",
    "addr:housenumber":"1737",
    "addr:postcode":"h2x 3k4",
    "addr:street":"Rue Saint-Denis",
    "iso:country":"CA",
    "sg:address":"1737 Rue Saint-Denis",
    "sg:city":"Montreal",
    "sg:classifiers":[
        {
            "category":"Shopping",
            "subcategory":"Hobbies, Toys, & Games",
            "type":"Retail Goods"
        }
    ],
    "sg:phone":"+1 514 286 5446",
    "sg:postcode":"H2X 3K4",
    "sg:province":"QC",
    "sg:tags":[
        "supply"
    ],
    "wof:name":"Netopia Technologies",
    "wof:placetype":"venue"
},
  "geometry": {"coordinates":[-73.5638427734,45.5154533386],"type":"Point"}
}