{
  "type": "Feature",
  "properties": {
    "addr:full":"4419 Colonel Talbot Rd S London ON N6P 1R2",
    "addr:housenumber":"4419",
    "addr:postcode":"n6p 1r2",
    "addr:street":"Colonel Talbot Rd",
    "iso:country":"CA",
    "sg:address":"4419 Colonel Talbot Rd S",
    "sg:city":"London",
    "sg:classifiers":[
        {
            "category":"Retail",
            "subcategory":"Auto Repair",
            "type":"Services"
        }
    ],
    "sg:phone":"+1 519 652 2067",
    "sg:postcode":"N6P 1R2",
    "sg:province":"ON",
    "sg:tags":[
        "repairing",
        "automobile"
    ],
    "wof:name":"Lambeth Car & Truck Ctr",
    "wof:placetype":"venue"
},
  "geometry": {"coordinates":[-81.29872899999999,42.906384],"type":"Point"}
}