{
  "type": "Feature",
  "properties": {
    "addr:full":"33 Lisgar St Toronto ON M6J 3T3",
    "addr:housenumber":"33",
    "addr:postcode":"m6j 3t3",
    "addr:street":"Lisgar St",
    "iso:country":"CA",
    "sg:address":"33 Lisgar St",
    "sg:city":"Toronto",
    "sg:classifiers":[
        {
            "category":"Restaurant",
            "type":"Food & Drink"
        }
    ],
    "sg:phone":"+1 416 532 1137",
    "sg:postcode":"M6J 3T3",
    "sg:province":"ON",
    "wof:name":"Famous People Players",
    "wof:placetype":"venue"
},
  "geometry": {"coordinates":[-79.422951,43.642029],"type":"Point"}
}