{
  "type": "Feature",
  "properties": {
    "addr:full":"389 Avon St Windsor NS B0N 2T0",
    "addr:housenumber":"389",
    "addr:postcode":"b0n 2t0",
    "addr:street":"Avon St",
    "iso:country":"CA",
    "sg:address":"389 Avon St",
    "sg:city":"Windsor",
    "sg:classifiers":[
        {
            "category":"Museum",
            "type":"Entertainment"
        }
    ],
    "sg:phone":"+1 902 798 8213",
    "sg:postcode":"B0N 2T0",
    "sg:province":"NS",
    "wof:name":"Shand House",
    "wof:placetype":"venue"
},
  "geometry": {"coordinates":[-64.14246368409999,44.991569519],"type":"Point"}
}