{
  "type": "Feature",
  "properties": {
    "addr:full":"62 Rue DE Palma Laval QC H7M 1H7",
    "addr:housenumber":"62",
    "addr:postcode":"h7m 1h7",
    "addr:street":"Rue De Palma",
    "iso:country":"CA",
    "sg:address":"62 Rue DE Palma",
    "sg:city":"Laval",
    "sg:classifiers":[
        {
            "category":"Building & Trades",
            "subcategory":"Construction",
            "type":"Services"
        }
    ],
    "sg:phone":"+1 450 663 2817",
    "sg:postcode":"H7M 1H7",
    "sg:province":"QC",
    "sg:tags":[
        "masonry",
        "contractor"
    ],
    "wof:name":"Caron, Jean Louis",
    "wof:placetype":"venue"
},
  "geometry": {"coordinates":[-73.729141,45.599632],"type":"Point"}
}