{
  "type": "Feature",
  "properties": {
    "addr:full":"165 Sandwich St S Amherstburg ON N9V 1Z9",
    "addr:housenumber":"165",
    "addr:postcode":"n9v 1z9",
    "addr:street":"Sandwich St S",
    "iso:country":"CA",
    "sg:address":"165 Sandwich St S",
    "sg:city":"Amherstburg",
    "sg:classifiers":[
        {
            "category":"Health Services",
            "subcategory":"Doctor",
            "type":"Services"
        }
    ],
    "sg:phone":"+1 519 736 4073",
    "sg:postcode":"N9V 1Z9",
    "sg:province":"ON",
    "sg:tags":[
        "dentist"
    ],
    "wof:name":"Harris, Louise DDS",
    "wof:placetype":"venue"
},
  "geometry": {"coordinates":[-83.109818,42.105255],"type":"Point"}
}