{
  "type": "Feature",
  "properties": {
    "addr:full":"44 Poplar Ave Atikokan ON P0T 1C0",
    "addr:housenumber":"44",
    "addr:postcode":"p0t 1c0",
    "addr:street":"Poplar Ave",
    "iso:country":"CA",
    "sg:address":"44 Poplar Ave",
    "sg:city":"Atikokan",
    "sg:classifiers":[
        {
            "category":"Wholesale",
            "subcategory":"Hardware",
            "type":"Manufacturing & Wholesale Goods"
        }
    ],
    "sg:phone":"+1 807 597 4253",
    "sg:postcode":"P0T 1C0",
    "sg:province":"ON",
    "sg:tags":[
        "wind",
        "equipment",
        "energy",
        "system",
        "solar"
    ],
    "wof:name":"Northern Lights Solar Systems",
    "wof:placetype":"venue"
},
  "geometry": {"coordinates":[-91.6191253662,48.7626647949],"type":"Point"}
}