{
  "type": "Feature",
  "properties": {
    "addr:full":"925 Boul DE LA Carriere Hull QC J8Y 6W5",
    "addr:housenumber":"925",
    "addr:postcode":"j8y 6w5",
    "addr:street":"Boul De La Carriere",
    "iso:country":"CA",
    "sg:address":"925 Boul DE LA Carriere",
    "sg:city":"Hull",
    "sg:classifiers":[
        {
            "category":"Restaurant",
            "type":"Food & Drink"
        }
    ],
    "sg:phone":"+1 819 770 4424",
    "sg:postcode":"J8Y 6W5",
    "sg:province":"QC",
    "sg:tags":[
        "janitor"
    ],
    "wof:name":"Sanitaires En Gros",
    "wof:placetype":"venue"
},
  "geometry": {"coordinates":[-75.731415,45.455105],"type":"Point"}
}