{
  "type": "Feature",
  "properties": {
    "addr:full":"3545 Boul Henri-Bourassa E Montreal-Nord QC H1H 1J2",
    "addr:housenumber":"3545",
    "addr:postcode":"h1h 1j2",
    "addr:street":"Boul Henri-Bourassa E",
    "iso:country":"CA",
    "sg:address":"3545 Boul Henri-Bourassa E",
    "sg:city":"Montreal-Nord",
    "sg:classifiers":[
        {
            "category":"Shopping",
            "subcategory":"Clothing, Apparel, & Fashions",
            "type":"Retail Goods"
        }
    ],
    "sg:phone":"+1 514 326 1116",
    "sg:postcode":"H1H 1J2",
    "sg:province":"QC",
    "sg:tags":[
        "alteration"
    ],
    "wof:name":"Chic Chez Vous Enr",
    "wof:placetype":"venue"
},
  "geometry": {"coordinates":[-73.6481018066,45.5894088745],"type":"Point"}
}