{
  "type": "Feature",
  "properties": {
    "addr:full":"726 Rue Gagne O Alma QC G8B 1J8",
    "addr:housenumber":"726",
    "addr:postcode":"g8b 1j8",
    "addr:street":"Rue Gagne O",
    "iso:country":"CA",
    "sg:address":"726 Rue Gagne O",
    "sg:city":"Alma",
    "sg:classifiers":[
        {
            "category":"Shopping",
            "subcategory":"Crafts & Fabrics",
            "type":"Retail Goods"
        }
    ],
    "sg:phone":"+1 418 668 9254",
    "sg:postcode":"G8B 1J8",
    "sg:province":"QC",
    "sg:tags":[
        "woolen"
    ],
    "wof:name":"Petit Point",
    "wof:placetype":"venue"
},
  "geometry": {"coordinates":[-71.653229,48.552883],"type":"Point"}
}