{
  "type": "Feature",
  "properties": {
    "addr:full":"5718 Gateway Blvd NW Edmonton AB T6H 2H5",
    "addr:housenumber":"5718",
    "addr:postcode":"t6h 2h5",
    "addr:street":"Gateway Blvd Nw",
    "iso:country":"CA",
    "sg:address":"5718 Gateway Blvd NW",
    "sg:city":"Edmonton",
    "sg:classifiers":[
        {
            "category":"Building & Trades",
            "subcategory":"Plumbing",
            "type":"Services"
        }
    ],
    "sg:phone":"+1 780 430 0194",
    "sg:postcode":"T6H 2H5",
    "sg:province":"AB",
    "sg:tags":[
        "air",
        "conditioning",
        "furnace",
        "system",
        "contractor"
    ],
    "wof:name":"Dyand Mechanical Systems Ltd",
    "wof:placetype":"venue"
},
  "geometry": {"coordinates":[-113.492104,53.49371],"type":"Point"}
}