{
  "type": "Feature",
  "properties": {
    "iso:country":"CA",
    "sg:address":"7 Wyndham St S",
    "sg:city":"Guelph",
    "sg:classifiers":[
        {
            "category":"Social Services",
            "type":"Services"
        }
    ],
    "sg:phone":"+1 519 836 1611",
    "sg:postcode":"N1H 4C4",
    "sg:province":"ON",
    "sg:tags":[
        "youth",
        "organization",
        "center"
    ],
    "wof:name":"Royal Canadian Air Cadets",
    "wof:placetype":"venue"
},
  "geometry": {"coordinates":[-80.246674,43.543587],"type":"Point"}
}