{
  "type": "Feature",
  "properties": {
    "iso:country":"CA",
    "sg:city":"Nanaimo",
    "sg:classifiers":[
        {
            "category":"Professional",
            "subcategory":"Computer Services",
            "type":"Services"
        }
    ],
    "sg:phone":"+1 250 751 1770",
    "sg:postcode":"V9S 4M4",
    "sg:province":"BC",
    "sg:tags":[
        "consultant",
        "bookkeeping",
        "system",
        "designer",
        "accounting"
    ],
    "wof:name":"Alliance Business Solutions",
    "wof:placetype":"venue"
},
  "geometry": {"coordinates":[-123.982727051,49.1932220459],"type":"Point"}
}