{
  "type": "Feature",
  "properties": {
    "iso:country":"CA",
    "sg:city":"North York",
    "sg:classifiers":[
        {
            "category":"Shopping",
            "type":"Retail Goods"
        }
    ],
    "sg:phone":"+1 416 383 1051",
    "sg:postcode":"M3C 1P8",
    "sg:province":"ON",
    "sg:tags":[
        "cosmetic",
        "perfume"
    ],
    "wof:name":"Fragrance Avenue",
    "wof:placetype":"venue"
},
  "geometry": {"coordinates":[-79.3451766968,43.7366752625],"type":"Point"}
}