{
  "type": "Feature",
  "properties": {
    "addr:full":"214 Woolwich St Guelph ON N1H 3V7",
    "addr:housenumber":"214",
    "addr:postcode":"n1h 3v7",
    "addr:street":"Woolwich St",
    "iso:country":"CA",
    "sg:address":"214 Woolwich St",
    "sg:city":"Guelph",
    "sg:classifiers":[
        {
            "category":"Professional",
            "subcategory":"Business Services",
            "type":"Services"
        }
    ],
    "sg:phone":"+1 519 767 1970",
    "sg:postcode":"N1H 3V7",
    "sg:province":"ON",
    "sg:tags":[
        "interior",
        "consultant",
        "design",
        "decorator"
    ],
    "wof:name":"Buy the Yard",
    "wof:placetype":"venue"
},
  "geometry": {"coordinates":[-80.254288,43.548409],"type":"Point"}
}