{
  "type": "Feature",
  "properties": {
    "addr:full":"227 Av Frontenac Pointe-Claire QC H9R 4Z7",
    "addr:postcode":"h9r 4z7",
    "addr:street":"227 Av Frontenac",
    "iso:country":"CA",
    "sg:address":"227 Av Frontenac",
    "sg:city":"Pointe-Claire",
    "sg:classifiers":[
        {
            "category":"Personal",
            "subcategory":"Beauty Salon",
            "type":"Services"
        }
    ],
    "sg:phone":"+1 514 694 1884",
    "sg:postcode":"H9R 4Z7",
    "sg:province":"QC",
    "wof:name":"Anton Designs Coiffure",
    "wof:placetype":"venue"
},
  "geometry": {"coordinates":[-73.82646942140001,45.4697532654],"type":"Point"}
}