{
  "type": "Feature",
  "properties": {
    "addr:full":"Calgary AB T2S 0B3",
    "addr:postcode":"t2s 0b3",
    "iso:country":"CA",
    "sg:city":"Calgary",
    "sg:classifiers":[
        {
            "category":"Restaurant",
            "type":"Food & Drink"
        }
    ],
    "sg:phone":"+1 403 693 7272",
    "sg:postcode":"T2S 0B3",
    "sg:province":"AB",
    "sg:tags":[
        "pizza"
    ],
    "wof:name":"Papa Johns",
    "wof:placetype":"venue"
},
  "geometry": {"coordinates":[-114.074585,51.037712],"type":"Point"}
}