{
  "type": "Feature",
  "properties": {
    "addr:full":"254 Ch Jordan Hill Cookshire QC J0B 1M0",
    "addr:housenumber":"254",
    "addr:postcode":"j0b 1m0",
    "addr:street":"Ch Jordan Hill Cookshire",
    "iso:country":"CA",
    "sg:address":"254 Ch Jordan Hill",
    "sg:city":"Cookshire",
    "sg:classifiers":[
        {
            "category":"Recreation",
            "type":"Entertainment"
        }
    ],
    "sg:phone":"+1 819 875 3452",
    "sg:postcode":"J0B 1M0",
    "sg:province":"QC",
    "sg:tags":[
        "center"
    ],
    "wof:name":"Bulwer Community Ctr",
    "wof:placetype":"venue"
},
  "geometry": {"coordinates":[-71.7046279907,45.3456382751],"type":"Point"}
}