{
  "type": "Feature",
  "properties": {
    "addr:full":"674 Rue Notre-Dame E Victoriaville QC G6P 4B6",
    "addr:housenumber":"674",
    "addr:postcode":"g6p 4b6",
    "addr:street":"Rue Notre-Dame E",
    "iso:country":"CA",
    "sg:address":"674 Rue Notre-Dame E",
    "sg:city":"Victoriaville",
    "sg:classifiers":[
        {
            "category":"Restaurant",
            "type":"Food & Drink"
        }
    ],
    "sg:phone":"+1 819 758 9165",
    "sg:postcode":"G6P 4B6",
    "sg:province":"QC",
    "wof:name":"Restaurant Max Poutine Inc",
    "wof:placetype":"venue"
},
  "geometry": {"coordinates":[-71.9424743652,46.0633773804],"type":"Point"}
}