{
  "type": "Feature",
  "properties": {
    "addr:full":"188 Boul Rene-Levesque E Montreal QC H2X 1N4",
    "addr:housenumber":"188",
    "addr:postcode":"h2x 1n4",
    "addr:street":"Boul Rene-Levesque E",
    "iso:country":"CA",
    "sg:address":"188 Boul Rene-Levesque E",
    "sg:city":"Montreal",
    "sg:classifiers":[
        {
            "category":"Social Services",
            "type":"Services"
        }
    ],
    "sg:phone":"+1 514 861 9691",
    "sg:postcode":"H2X 1N4",
    "sg:province":"QC",
    "sg:tags":[
        "organization",
        "welfare"
    ],
    "wof:name":"Centres DE Jeunesse Shawbridge",
    "wof:placetype":"venue"
},
  "geometry": {"coordinates":[-73.5598373413,45.5105171204],"type":"Point"}
}