{
  "type": "Feature",
  "properties": {
    "addr:full":"Clinton BC V0K 1K0",
    "addr:postcode":"v0k 1k0",
    "iso:country":"CA",
    "sg:city":"Clinton",
    "sg:classifiers":[
        {
            "category":"Travel",
            "subcategory":"Hotels & Motels",
            "type":"Entertainment"
        }
    ],
    "sg:phone":"+1 250 459 2565",
    "sg:postcode":"V0K 1K0",
    "sg:province":"BC",
    "sg:tags":[
        "ranch",
        "guest"
    ],
    "wof:name":"Circle H Mountain Lodge",
    "wof:placetype":"venue"
},
  "geometry": {"coordinates":[-121.58731079099999,51.0916290283],"type":"Point"}
}