{
  "type": "Feature",
  "properties": {
    "iso:country":"CA",
    "sg:address":"3349 Rue Adam",
    "sg:city":"Montreal",
    "sg:classifiers":[
        {
            "category":"Education",
            "subcategory":"School",
            "type":"Public Place"
        }
    ],
    "sg:phone":"+1 514 596 5060",
    "sg:postcode":"H1W 1Y2",
    "sg:province":"QC",
    "wof:name":"Ecole Hochelaga",
    "wof:placetype":"venue"
},
  "geometry": {"coordinates":[-73.542564,45.541508],"type":"Point"}
}