{
  "type": "Feature",
  "properties": {
    "addr:full":"Morell PE C0A 1S0",
    "addr:postcode":"c0a 1s0",
    "iso:country":"CA",
    "sg:city":"Morell",
    "sg:classifiers":[
        {
            "category":"Banks & Credit Unions",
            "subcategory":"Bank",
            "type":"Services"
        }
    ],
    "sg:phone":"+1 902 961 2019",
    "sg:postcode":"C0A 1S0",
    "sg:province":"PE",
    "wof:name":"Scotiabank",
    "wof:placetype":"venue"
},
  "geometry": {"coordinates":[-62.7043571472,46.4161109924],"type":"Point"}
}