{
  "type": "Feature",
  "properties": {
    "addr:full":"Duncan BC V9L 1M8",
    "addr:postcode":"v9l 1m8",
    "iso:country":"CA",
    "sg:city":"Duncan",
    "sg:classifiers":[
        {
            "category":"Shopping",
            "type":"Retail Goods"
        }
    ],
    "sg:phone":"+1 250 748 3311",
    "sg:postcode":"V9L 1M8",
    "sg:province":"BC",
    "sg:tags":[
        "picture",
        "frame"
    ],
    "wof:name":"Station Street Gallery & Frame",
    "wof:placetype":"venue"
},
  "geometry": {"coordinates":[-123.70905304,48.7777862549],"type":"Point"}
}