{
  "type": "Feature",
  "properties": {
    "iso:country":"CA",
    "sg:city":"Mont-Royal",
    "sg:classifiers":[
        {
            "category":"Banks & Credit Unions",
            "subcategory":"Investment Brokerage",
            "type":"Services"
        }
    ],
    "sg:phone":"+1 514 736 0123",
    "sg:postcode":"H3P 3A6",
    "sg:province":"QC",
    "sg:tags":[
        "advisory",
        "financial"
    ],
    "wof:name":"Masvil Captial Inc",
    "wof:placetype":"venue"
},
  "geometry": {"coordinates":[-73.631966,45.524498],"type":"Point"}
}