{
  "type": "Feature",
  "properties": {
    "addr:full":"Nakina ON P0T 2H0",
    "addr:postcode":"p0t 2h0",
    "iso:country":"CA",
    "sg:city":"Nakina",
    "sg:classifiers":[
        {
            "category":"Wholesale",
            "subcategory":"Motor Vehicles",
            "type":"Manufacturing & Wholesale Goods"
        }
    ],
    "sg:phone":"+1 807 329 5332",
    "sg:postcode":"P0T 2H0",
    "sg:province":"ON",
    "sg:tags":[
        "hearse",
        "government",
        "ambulance"
    ],
    "wof:name":"Nakina Ambulance",
    "wof:placetype":"venue"
},
  "geometry": {"coordinates":[-86.7118606567,50.1797599792],"type":"Point"}
}