{
  "type": "Feature",
  "properties": {
    "iso:country":"CA",
    "sg:address":"3339 Mainway",
    "sg:city":"Burlington",
    "sg:classifiers":[
        {
            "category":"Building & Trades",
            "subcategory":"Plumbing",
            "type":"Services"
        }
    ],
    "sg:phone":"+1 905 332 7710",
    "sg:postcode":"L7M 1A6",
    "sg:province":"ON",
    "sg:tags":[
        "conditioning",
        "air",
        "system",
        "contractor"
    ],
    "wof:name":"A Joseph Mechanical",
    "wof:placetype":"venue"
},
  "geometry": {"coordinates":[-79.8010482788,43.3666419983],"type":"Point"}
}