{
  "type": "Feature",
  "properties": {
    "addr:full":"Edmonton AB T5N 3R3",
    "addr:postcode":"t5n 3r3",
    "iso:country":"CA",
    "sg:city":"Edmonton",
    "sg:classifiers":[
        {
            "category":"Real Estate",
            "subcategory":"Real Estate Agent",
            "type":"Services"
        }
    ],
    "sg:phone":"+1 780 453 2555",
    "sg:postcode":"T5N 3R3",
    "sg:province":"AB",
    "sg:tags":[
        "management"
    ],
    "wof:name":"Kelly Management & Realty",
    "wof:placetype":"venue"
},
  "geometry": {"coordinates":[-113.566231,53.543098],"type":"Point"}
}