{
  "type": "Feature",
  "properties": {
    "addr:full":"2364 20 Ave NE Calgary AB T2E 8J1",
    "addr:housenumber":"2364",
    "addr:postcode":"t2e 8j1",
    "addr:street":"20 Ave Ne",
    "iso:country":"CA",
    "sg:address":"2364 20 Ave NE",
    "sg:city":"Calgary",
    "sg:classifiers":[
        {
            "category":"Autos & Motor Vehicles",
            "subcategory":"Fuel & Gas Station",
            "type":"Retail Goods"
        }
    ],
    "sg:phone":"+1 403 291 0550",
    "sg:postcode":"T2E 8J1",
    "sg:province":"AB",
    "sg:tags":[
        "oil"
    ],
    "wof:name":"Gas Plus Inc",
    "wof:placetype":"venue"
},
  "geometry": {"coordinates":[-114.005104,51.070892],"type":"Point"}
}