{
  "type": "Feature",
  "properties": {
    "iso:country":"CA",
    "sg:address":"100 Metcalfe St",
    "sg:city":"Ottawa",
    "sg:classifiers":[
        {
            "category":"Restaurant",
            "type":"Food & Drink"
        }
    ],
    "sg:phone":"+1 613 594 9365",
    "sg:postcode":"K1P 5M1",
    "sg:province":"ON",
    "wof:name":"Druxy's Famous Deli Sandwiches",
    "wof:placetype":"venue"
},
  "geometry": {"coordinates":[-75.69580841059999,45.4206352234],"type":"Point"}
}