{
  "type": "Feature",
  "properties": {
    "addr:full":"Oshawa ON L1G 4W5",
    "addr:postcode":"l1g 4w5",
    "iso:country":"CA",
    "sg:city":"Oshawa",
    "sg:classifiers":[
        {
            "category":"Personal",
            "subcategory":"Beauty Salon",
            "type":"Services"
        }
    ],
    "sg:phone":"+1 905 576 3222",
    "sg:postcode":"L1G 4W5",
    "sg:province":"ON",
    "wof:name":"Knots Landing",
    "wof:placetype":"venue"
},
  "geometry": {"coordinates":[-78.87595399999999,43.925694],"type":"Point"}
}