{
  "type": "Feature",
  "properties": {
    "addr:full":"258 Carlton St Toronto ON M5A 2L3",
    "addr:housenumber":"258",
    "addr:postcode":"m5a 2l3",
    "addr:street":"Carlton St",
    "iso:country":"CA",
    "sg:address":"258 Carlton St",
    "sg:city":"Toronto",
    "sg:classifiers":[
        {
            "category":"Professional",
            "subcategory":"Management & Consulting",
            "type":"Services"
        }
    ],
    "sg:phone":"+1 416 964 6118",
    "sg:postcode":"M5A 2L3",
    "sg:province":"ON",
    "sg:tags":[
        "communications",
        "consultant"
    ],
    "wof:name":"Special Assignment",
    "wof:placetype":"venue"
},
  "geometry": {"coordinates":[-79.367279,43.664764],"type":"Point"}
}