{
  "type": "Feature",
  "properties": {
    "addr:full":"Fraserwood MB R0C 1A0",
    "addr:postcode":"r0c 1a0",
    "iso:country":"CA",
    "sg:city":"Fraserwood",
    "sg:classifiers":[
        {
            "category":"Shopping",
            "subcategory":"Discount & Variety Stores",
            "type":"Retail Goods"
        }
    ],
    "sg:phone":"+1 204 643 5556",
    "sg:postcode":"R0C 1A0",
    "sg:province":"MB",
    "sg:tags":[
        "merchandise",
        "general"
    ],
    "wof:name":"J & J Store",
    "wof:placetype":"venue"
},
  "geometry": {"coordinates":[-97.2144622803,50.6422653198],"type":"Point"}
}