{
  "type": "Feature",
  "properties": {
    "addr:full":"468 Main St E Beaverton ON L0K 1A0",
    "addr:housenumber":"468",
    "addr:postcode":"l0k 1a0",
    "addr:street":"Main St E",
    "iso:country":"CA",
    "sg:address":"468 Main St E",
    "sg:city":"Beaverton",
    "sg:classifiers":[
        {
            "category":"Health Services",
            "subcategory":"Doctor",
            "type":"Services"
        }
    ],
    "sg:phone":"+1 705 426 7331",
    "sg:postcode":"L0K 1A0",
    "sg:province":"ON",
    "sg:tags":[
        "physician",
        "surgeon"
    ],
    "wof:name":"Mc Cordic, Francis D MD",
    "wof:placetype":"venue"
},
  "geometry": {"coordinates":[-79.14830000000001,44.433193],"type":"Point"}
}