{
  "type": "Feature",
  "properties": {
    "iso:country":"CA",
    "sg:city":"Calgary",
    "sg:classifiers":[
        {
            "category":"Real Estate",
            "subcategory":"Real Estate Operator",
            "type":"Services"
        }
    ],
    "sg:phone":"+1 403 295 3809",
    "sg:postcode":"T2K 5X9",
    "sg:province":"AB",
    "sg:tags":[
        "apartment"
    ],
    "wof:name":"Beddington Court",
    "wof:placetype":"venue"
},
  "geometry": {"coordinates":[-114.05669403100001,51.1249923706],"type":"Point"}
}