{
  "type": "Feature",
  "properties": {
    "addr:full":"Brampton ON L6X 1R5",
    "addr:postcode":"l6x 1r5",
    "iso:country":"CA",
    "sg:city":"Brampton",
    "sg:classifiers":[
        {
            "category":"Insurance",
            "subcategory":"Insurance Agent",
            "type":"Services"
        }
    ],
    "sg:phone":"+1 905 840 6964",
    "sg:postcode":"L6X 1R5",
    "sg:province":"ON",
    "wof:name":"R Picano Insurance",
    "wof:placetype":"venue"
},
  "geometry": {"coordinates":[-79.762794,43.686291],"type":"Point"}
}