{
  "type": "Feature",
  "properties": {
    "addr:full":"7400 Boul Taschereau Brossard QC J4W 1M9",
    "addr:housenumber":"7400",
    "addr:postcode":"j4w 1m9",
    "addr:street":"Boul Taschereau",
    "iso:country":"CA",
    "sg:address":"7400 Boul Taschereau",
    "sg:city":"Brossard",
    "sg:classifiers":[
        {
            "category":"Shopping",
            "subcategory":"Pharmacy",
            "type":"Retail Goods"
        }
    ],
    "sg:phone":"+1 450 672 5550",
    "sg:postcode":"J4W 1M9",
    "sg:province":"QC",
    "wof:name":"Jean Coutu",
    "wof:placetype":"venue"
},
  "geometry": {"coordinates":[-73.4654006958,45.4588890076],"type":"Point"}
}