{
  "type": "Feature",
  "properties": {
    "addr:full":"12165 Boul Saint-Jean-Baptiste Montreal QC H1C 1S4",
    "addr:housenumber":"12165",
    "addr:postcode":"h1c 1s4",
    "addr:street":"Boul Saint-Jean-Baptiste",
    "iso:country":"CA",
    "sg:address":"12165 Boul Saint-Jean-Baptiste",
    "sg:city":"Montreal",
    "sg:classifiers":[
        {
            "category":"Education",
            "subcategory":"School",
            "type":"Public Place"
        }
    ],
    "sg:phone":"+1 514 881 4690",
    "sg:postcode":"H1C 1S4",
    "sg:province":"QC",
    "wof:name":"Ecole LA Passerelle",
    "wof:placetype":"venue"
},
  "geometry": {"coordinates":[-73.54405975340001,45.6624603271],"type":"Point"}
}