{
  "type": "Feature",
  "properties": {
    "addr:full":"115 Forestry Rd Longlac ON P0T 2A0",
    "addr:housenumber":"115",
    "addr:postcode":"p0t 2a0",
    "addr:street":"Forestry Rd",
    "iso:country":"CA",
    "sg:address":"115 Forestry Rd",
    "sg:city":"Longlac",
    "sg:classifiers":[
        {
            "category":"Home & Garden",
            "subcategory":"Hardware",
            "type":"Retail Goods"
        }
    ],
    "sg:phone":"+1 807 876 4513",
    "sg:postcode":"P0T 2A0",
    "sg:province":"ON",
    "wof:name":"Gauthier Home Hardware",
    "wof:placetype":"venue"
},
  "geometry": {"coordinates":[-86.535172,49.779655],"type":"Point"}
}