{
  "type": "Feature",
  "properties": {
    "addr:full":"8336 34 Ave NW Calgary AB T3B 1R2",
    "addr:housenumber":"8336",
    "addr:postcode":"t3b 1r2",
    "addr:street":"34 Ave Nw",
    "iso:country":"CA",
    "sg:address":"8336 34 Ave NW",
    "sg:city":"Calgary",
    "sg:classifiers":[
        {
            "category":"Organizations",
            "subcategory":"Religious Organization",
            "type":"Services"
        }
    ],
    "sg:phone":"+1 403 288 6330",
    "sg:postcode":"T3B 1R2",
    "sg:province":"AB",
    "sg:tags":[
        "church"
    ],
    "wof:name":"St Edmund's Anglican Church",
    "wof:placetype":"venue"
},
  "geometry": {"coordinates":[-114.2081604,51.0894622803],"type":"Point"}
}