{
  "type": "Feature",
  "properties": {
    "addr:full":"112 Tranquility St Brantford ON N3R 3J1",
    "addr:housenumber":"112",
    "addr:postcode":"n3r 3j1",
    "addr:street":"Tranquility St",
    "iso:country":"CA",
    "sg:address":"112 Tranquility St",
    "sg:city":"Brantford",
    "sg:classifiers":[
        {
            "category":"Wholesale",
            "subcategory":"Construction Materials",
            "type":"Manufacturing & Wholesale Goods"
        }
    ],
    "sg:phone":"+1 519 756 3443",
    "sg:postcode":"N3R 3J1",
    "sg:province":"ON",
    "sg:tags":[
        "fence"
    ],
    "wof:name":"Fence & Deck Perfection",
    "wof:placetype":"venue"
},
  "geometry": {"coordinates":[-80.268204,43.176468],"type":"Point"}
}