{
  "type": "Feature",
  "properties": {
    "addr:full":"3030 Highway 69 N Val Caron ON P3N 1R8",
    "addr:housenumber":"3030",
    "addr:postcode":"p3n 1r8",
    "addr:street":"Highway 69 N",
    "iso:country":"CA",
    "sg:address":"3030 Highway 69 N",
    "sg:city":"Val Caron",
    "sg:classifiers":[
        {
            "category":"Shopping",
            "subcategory":"Florist",
            "type":"Retail Goods"
        }
    ],
    "sg:phone":"+1 705 897 2956",
    "sg:postcode":"P3N 1R8",
    "sg:province":"ON",
    "wof:name":"Flower Store Inc",
    "wof:placetype":"venue"
},
  "geometry": {"coordinates":[-81.008644,46.610432],"type":"Point"}
}