{
  "type": "Feature",
  "properties": {
    "addr:full":"361 Fort William Rd Thunder Bay ON P7B 2Z4",
    "addr:housenumber":"361",
    "addr:postcode":"p7b 2z4",
    "addr:street":"Fort William Rd",
    "iso:country":"CA",
    "sg:address":"361 Fort William Rd",
    "sg:city":"Thunder Bay",
    "sg:classifiers":[
        {
            "category":"Home & Garden",
            "subcategory":"Furniture",
            "type":"Retail Goods"
        }
    ],
    "sg:phone":"+1 807 345 2307",
    "sg:postcode":"P7B 2Z4",
    "sg:province":"ON",
    "wof:name":"Peterson Furniture & Appls Ltd",
    "wof:placetype":"venue"
},
  "geometry": {"coordinates":[-89.23299400000001,48.425224],"type":"Point"}
}