{
  "type": "Feature",
  "properties": {
    "iso:country":"CA",
    "sg:city":"Calgary",
    "sg:classifiers":[
        {
            "category":"Real Estate",
            "subcategory":"Real Estate Operator",
            "type":"Services"
        }
    ],
    "sg:phone":"+1 403 250 7135",
    "sg:postcode":"T2E 6V2",
    "sg:province":"AB",
    "sg:tags":[
        "condominium"
    ],
    "wof:name":"Landmark Projects Corp",
    "wof:placetype":"venue"
},
  "geometry": {"coordinates":[-114.011543274,51.0861434937],"type":"Point"}
}