{
  "type": "Feature",
  "properties": {
    "iso:country":"CA",
    "sg:address":"113 235 Rte",
    "sg:city":"Ange-Gardien",
    "sg:classifiers":[
        {
            "category":"Restaurant",
            "type":"Food & Drink"
        }
    ],
    "sg:phone":"+1 450 293 0240",
    "sg:postcode":"J0E 1E0",
    "sg:province":"QC",
    "wof:name":"Belle Province",
    "wof:placetype":"venue"
},
  "geometry": {"coordinates":[-72.93468475340001,45.3619232178],"type":"Point"}
}