{
  "type": "Feature",
  "properties": {
    "addr:full":"3449 Boul Saint-Laurent Montreal QC H2X 2T6",
    "addr:housenumber":"3449",
    "addr:postcode":"h2x 2t6",
    "addr:street":"Boul Saint-Laurent",
    "iso:country":"CA",
    "sg:address":"3449 Boul Saint-Laurent",
    "sg:city":"Montreal",
    "sg:classifiers":[
        {
            "category":"Restaurant",
            "type":"Food & Drink"
        }
    ],
    "sg:phone":"+1 514 281 0275",
    "sg:postcode":"H2X 2T6",
    "sg:province":"QC",
    "wof:name":"Mezze Restaurant",
    "wof:placetype":"venue"
},
  "geometry": {"coordinates":[-73.5700836182,45.5129623413],"type":"Point"}
}