{
  "type": "Feature",
  "properties": {
    "addr:full":"5020 50 Ave Bonnyville AB T9N 2J6",
    "addr:housenumber":"5020",
    "addr:postcode":"t9n 2j6",
    "addr:street":"50 Ave",
    "iso:country":"CA",
    "sg:address":"5020 50 Ave",
    "sg:city":"Bonnyville",
    "sg:classifiers":[
        {
            "category":"Home & Garden",
            "subcategory":"Furniture",
            "type":"Retail Goods"
        }
    ],
    "sg:phone":"+1 780 826 1926",
    "sg:postcode":"T9N 2J6",
    "sg:province":"AB",
    "wof:name":"Gmg Furniture Villa",
    "wof:placetype":"venue"
},
  "geometry": {"coordinates":[-110.740699768,54.267829895],"type":"Point"}
}