{
  "type": "Feature",
  "properties": {
    "addr:full":"Lone Butte BC V0K 1X0",
    "addr:postcode":"v0k 1x0",
    "addr:street":"Lone",
    "iso:country":"CA",
    "sg:city":"Lone Butte",
    "sg:classifiers":[
        {
            "category":"Food & Beverages",
            "subcategory":"Groceries & Convenience Stores",
            "type":"Retail Goods"
        }
    ],
    "sg:phone":"+1 250 395 4386",
    "sg:postcode":"V0K 1X0",
    "sg:province":"BC",
    "sg:tags":[
        "grocer"
    ],
    "wof:name":"Lone Butte General Store Ltd",
    "wof:placetype":"venue"
},
  "geometry": {"coordinates":[-121.19148300000001,51.553112],"type":"Point"}
}