{
  "type": "Feature",
  "properties": {
    "addr:full":"48 Dermot St Lindsay ON K9V 4Y9",
    "addr:housenumber":"48",
    "addr:postcode":"k9v 4y9",
    "addr:street":"Dermot St",
    "iso:country":"CA",
    "sg:address":"48 Dermot St",
    "sg:city":"Lindsay",
    "sg:classifiers":[
        {
            "category":"Autos & Motor Vehicles",
            "subcategory":"Auto Supplies",
            "type":"Retail Goods"
        }
    ],
    "sg:phone":"+1 705 878 0534",
    "sg:postcode":"K9V 4Y9",
    "sg:province":"ON",
    "sg:tags":[
        "automobile",
        "parts"
    ],
    "wof:name":"Tgf Bumper & Fender Inc",
    "wof:placetype":"venue"
},
  "geometry": {"coordinates":[-78.7316665649,44.3707542419],"type":"Point"}
}