{
  "type": "Feature",
  "properties": {
    "addr:full":"4708 50th Ave Redwater AB T0A 2W0",
    "addr:housenumber":"4708",
    "addr:postcode":"t0a 2w0",
    "addr:street":"50Th Ave",
    "iso:country":"CA",
    "sg:address":"4708 50th Ave",
    "sg:city":"Redwater",
    "sg:classifiers":[
        {
            "category":"Organizations",
            "subcategory":"Professional Association",
            "type":"Services"
        }
    ],
    "sg:phone":"+1 780 942 3841",
    "sg:postcode":"T0A 2W0",
    "sg:province":"AB",
    "sg:tags":[
        "club"
    ],
    "wof:name":"Royal Canadian Legion",
    "wof:placetype":"venue"
},
  "geometry": {"coordinates":[-113.107460022,53.9523200989],"type":"Point"}
}