{
  "type": "Feature",
  "properties": {
    "addr:full":"1002 Hwy 169 Bala ON P0C 1A0",
    "addr:housenumber":"1002",
    "addr:postcode":"p0c 1a0",
    "addr:street":"Hwy 169",
    "iso:country":"CA",
    "sg:address":"1002 Hwy 169",
    "sg:city":"Bala",
    "sg:classifiers":[
        {
            "category":"Home & Garden",
            "subcategory":"Building Materials",
            "type":"Retail Goods"
        }
    ],
    "sg:phone":"+1 705 762 0121",
    "sg:postcode":"P0C 1A0",
    "sg:province":"ON",
    "wof:name":"Muskoka Lumber",
    "wof:placetype":"venue"
},
  "geometry": {"coordinates":[-79.618118,45.018749],"type":"Point"}
}