{
  "type": "Feature",
  "properties": {
    "addr:full":"43 Michael Dr North York ON M2H 2A4",
    "addr:housenumber":"43",
    "addr:postcode":"m2h 2a4",
    "addr:street":"Michael Dr",
    "iso:country":"CA",
    "sg:address":"43 Michael Dr",
    "sg:city":"North York",
    "sg:classifiers":[
        {
            "category":"Building & Trades",
            "subcategory":"Construction",
            "type":"Services"
        }
    ],
    "sg:phone":"+1 416 493 5988",
    "sg:postcode":"M2H 2A4",
    "sg:province":"ON",
    "sg:tags":[
        "tile",
        "dealer"
    ],
    "wof:name":"Vincent Floor & Wall Contr",
    "wof:placetype":"venue"
},
  "geometry": {"coordinates":[-79.36460099999999,43.8032],"type":"Point"}
}