{
  "type": "Feature",
  "properties": {
    "iso:country":"CA",
    "sg:address":"43 Michael Dr",
    "sg:city":"North York",
    "sg:classifiers":[
        {
            "category":"Building & Trades",
            "subcategory":"Construction",
            "type":"Services"
        }
    ],
    "sg:phone":"+1 416 493 5988",
    "sg:postcode":"M2H 2A4",
    "sg:province":"ON",
    "sg:tags":[
        "tile",
        "dealer"
    ],
    "wof:name":"Vincent Floor & Wall Contr",
    "wof:placetype":"venue"
},
  "geometry": {"coordinates":[-79.364601,43.8032],"type":"Point"}
}