{
  "type": "Feature",
  "properties": {
    "addr:full":"1124 Winnipeg St Regina SK S4R 1J6",
    "addr:housenumber":"1124",
    "addr:postcode":"s4r 1j6",
    "addr:street":"Winnipeg St",
    "iso:country":"CA",
    "sg:address":"1124 Winnipeg St",
    "sg:city":"Regina",
    "sg:classifiers":[
        {
            "category":"Wholesale",
            "subcategory":"Hardware",
            "type":"Manufacturing & Wholesale Goods"
        }
    ],
    "sg:phone":"+1 306 522 9929",
    "sg:postcode":"S4R 1J6",
    "sg:province":"SK",
    "sg:tags":[
        "make",
        "system",
        "air",
        "equipment",
        "heating",
        "furnace"
    ],
    "wof:name":"NU-Trend Industries",
    "wof:placetype":"venue"
},
  "geometry": {"coordinates":[-104.595443726,50.4609336853],"type":"Point"}
}