{
  "type": "Feature",
  "properties": {
    "addr:full":"3 Rue Hotel DE Ville Notre-Dame-Du-Lac QC G0L 1X0",
    "addr:housenumber":"3",
    "addr:postcode":"g0l 1x0",
    "addr:street":"Rue Hotel De Ville",
    "iso:country":"CA",
    "sg:address":"3 Rue Hotel DE Ville",
    "sg:city":"Notre-Dame-Du-Lac",
    "sg:classifiers":[
        {
            "category":"Professional",
            "subcategory":"Business Services",
            "type":"Services"
        }
    ],
    "sg:phone":"+1 418 899 2381",
    "sg:postcode":"G0L 1X0",
    "sg:province":"QC",
    "sg:tags":[
        "trade",
        "exposition",
        "fair",
        "show"
    ],
    "wof:name":"Societe D'Agriculture",
    "wof:placetype":"venue"
},
  "geometry": {"coordinates":[-68.79055,47.610531],"type":"Point"}
}