{
  "type": "Feature",
  "properties": {
    "addr:full":"6711 Tecumseh Rd E Windsor ON N8T 3K7",
    "addr:housenumber":"6711",
    "addr:postcode":"n8t 3k7",
    "addr:street":"Tecumseh Rd E",
    "iso:country":"CA",
    "sg:address":"6711 Tecumseh Rd E",
    "sg:city":"Windsor",
    "sg:classifiers":[
        {
            "category":"Shopping",
            "subcategory":"Used Merchandise",
            "type":"Retail Goods"
        }
    ],
    "sg:phone":"+1 519 944 0022",
    "sg:postcode":"N8T 3K7",
    "sg:province":"ON",
    "sg:tags":[
        "second",
        "hand",
        "store",
        "jeweler"
    ],
    "wof:name":"Cash Converters",
    "wof:placetype":"venue"
},
  "geometry": {"coordinates":[-82.944138,42.311768],"type":"Point"}
}