{
  "type": "Feature",
  "properties": {
    "addr:full":"108 Water St Guelph ON N1G 1A6",
    "addr:housenumber":"108",
    "addr:postcode":"n1g 1a6",
    "addr:street":"Water St",
    "iso:country":"CA",
    "sg:address":"108 Water St",
    "sg:city":"Guelph",
    "sg:classifiers":[
        {
            "category":"Museum",
            "type":"Entertainment"
        }
    ],
    "sg:phone":"+1 519 836 1482",
    "sg:postcode":"N1G 1A6",
    "sg:province":"ON",
    "sg:tags":[
        "government"
    ],
    "wof:name":"Mc Crae House",
    "wof:placetype":"venue"
},
  "geometry": {"coordinates":[-80.245102,43.53598],"type":"Point"}
}