{
  "type": "Feature",
  "properties": {
    "addr:full":"Perth ON K7H 3C9",
    "addr:postcode":"k7h 3c9",
    "iso:country":"CA",
    "sg:city":"Perth",
    "sg:classifiers":[
        {
            "category":"Manufacturing",
            "subcategory":"Building Materials",
            "type":"Manufacturing & Wholesale Goods"
        }
    ],
    "sg:phone":"+1 613 267 4265",
    "sg:postcode":"K7H 3C9",
    "sg:province":"ON",
    "wof:name":"Byway Lumber Ltd",
    "wof:placetype":"venue"
},
  "geometry": {"coordinates":[-76.2483291626,44.8989448547],"type":"Point"}
}