{
  "type": "Feature",
  "properties": {
    "addr:full":"Musgrave Harbour NL A0G 3J0",
    "addr:postcode":"a0g 3j0",
    "addr:street":"Musgrave",
    "iso:country":"CA",
    "sg:city":"Musgrave Harbour",
    "sg:classifiers":[
        {
            "category":"Building & Trades",
            "subcategory":"Construction",
            "type":"Services"
        }
    ],
    "sg:phone":"+1 709 655 2855",
    "sg:postcode":"A0G 3J0",
    "sg:province":"NL",
    "sg:tags":[
        "maker",
        "cabinet"
    ],
    "wof:name":"Tripar Enterprises Ltd",
    "wof:placetype":"venue"
},
  "geometry": {"coordinates":[-53.9642982483,49.4476699829],"type":"Point"}
}