{
  "type": "Feature",
  "properties": {
    "addr:full":"1723 Rue Saint-Denis Montreal QC H2X 3K4",
    "addr:housenumber":"1723",
    "addr:postcode":"h2x 3k4",
    "addr:street":"Rue Saint-Denis",
    "iso:country":"CA",
    "sg:address":"1723 Rue Saint-Denis",
    "sg:city":"Montreal",
    "sg:classifiers":[
        {
            "category":"Restaurant",
            "type":"Food & Drink"
        }
    ],
    "sg:phone":"+1 514 845 8080",
    "sg:postcode":"H2X 3K4",
    "sg:province":"QC",
    "wof:name":"Restaurant Bombay",
    "wof:placetype":"venue"
},
  "geometry": {"coordinates":[-73.5637893677,45.5154266357],"type":"Point"}
}