{
  "type": "Feature",
  "properties": {
    "addr:full":"1 Canfield Rd Nepean ON K2H 5S7",
    "addr:housenumber":"1",
    "addr:postcode":"k2h 5s7",
    "addr:street":"Canfield Rd",
    "iso:country":"CA",
    "sg:address":"1 Canfield Rd",
    "sg:city":"Nepean",
    "sg:classifiers":[
        {
            "category":"Organizations",
            "subcategory":"Religious Organization",
            "type":"Services"
        }
    ],
    "sg:phone":"+1 613 596 0052",
    "sg:postcode":"K2H 5S7",
    "sg:province":"ON",
    "sg:tags":[
        "church"
    ],
    "wof:name":"St Mary Coptic Orthodox Church",
    "wof:placetype":"venue"
},
  "geometry": {"coordinates":[-75.782196,45.329956],"type":"Point"}
}