{
  "type": "Feature",
  "properties": {
    "addr:full":"Surrey BC V3R 6Y8",
    "addr:postcode":"v3r 6y8",
    "iso:country":"CA",
    "sg:city":"Surrey",
    "sg:classifiers":[
        {
            "category":"Health Services",
            "subcategory":"Health Practitioner",
            "type":"Services"
        }
    ],
    "sg:phone":"+1 604 583 4842",
    "sg:postcode":"V3R 6Y8",
    "sg:province":"BC",
    "sg:tags":[
        "dietitian"
    ],
    "wof:name":"Pro Active Nutrition",
    "wof:placetype":"venue"
},
  "geometry": {"coordinates":[-122.799888611,49.1917953491],"type":"Point"}
}