{
  "type": "Feature",
  "properties": {
    "addr:full":"42 Burgosa Crt Woodbridge ON L4L 5C3",
    "addr:housenumber":"42",
    "addr:postcode":"l4l 5c3",
    "addr:street":"Burgosa Crt",
    "iso:country":"CA",
    "sg:address":"42 Burgosa Crt",
    "sg:city":"Woodbridge",
    "sg:classifiers":[
        {
            "category":"Wholesale",
            "subcategory":"Sporting Goods",
            "type":"Manufacturing & Wholesale Goods"
        }
    ],
    "sg:phone":"+1 905 265 8151",
    "sg:postcode":"L4L 5C3",
    "sg:province":"ON",
    "wof:name":"Bellsports Canada",
    "wof:placetype":"venue"
},
  "geometry": {"coordinates":[-79.5649642944,43.7945480347],"type":"Point"}
}