{
  "type": "Feature",
  "properties": {
    "addr:full":"412 Barton St Stoney Creek ON L8E 2L3",
    "addr:housenumber":"412",
    "addr:postcode":"l8e 2l3",
    "addr:street":"Barton St",
    "iso:country":"CA",
    "sg:address":"412 Barton St",
    "sg:city":"Stoney Creek",
    "sg:classifiers":[
        {
            "category":"Food & Beverages",
            "subcategory":"Groceries & Convenience Stores",
            "type":"Retail Goods"
        }
    ],
    "sg:phone":"+1 905 664 6755",
    "sg:postcode":"L8E 2L3",
    "sg:province":"ON",
    "wof:name":"Avondale Stores Ltd",
    "wof:placetype":"venue"
},
  "geometry": {"coordinates":[-79.718788,43.226814],"type":"Point"}
}