{
  "type": "Feature",
  "properties": {
    "addr:full":"1212 Douglas St Victoria BC V8W 2E5",
    "addr:housenumber":"1212",
    "addr:postcode":"v8w 2e5",
    "addr:street":"Douglas St",
    "iso:country":"CA",
    "sg:address":"1212 Douglas St",
    "sg:city":"Victoria",
    "sg:classifiers":[
        {
            "category":"Shopping",
            "subcategory":"Books",
            "type":"Retail Goods"
        }
    ],
    "sg:phone":"+1 250 380 9009",
    "sg:postcode":"V8W 2E5",
    "sg:province":"BC",
    "sg:tags":[
        "dealer"
    ],
    "wof:name":"Chapters",
    "wof:placetype":"venue"
},
  "geometry": {"coordinates":[-123.36534881599999,48.4256706238],"type":"Point"}
}