{
  "type": "Feature",
  "properties": {
    "addr:full":"801 102 Ave Dawson Creek BC V1G 2B4",
    "addr:housenumber":"801",
    "addr:postcode":"v1g 2b4",
    "addr:street":"102 Ave",
    "iso:country":"CA",
    "sg:address":"801 102 Ave",
    "sg:city":"Dawson Creek",
    "sg:classifiers":[
        {
            "category":"Wholesale",
            "subcategory":"Machinery & Supplies",
            "type":"Manufacturing & Wholesale Goods"
        }
    ],
    "sg:phone":"+1 250 782 5824",
    "sg:postcode":"V1G 2B4",
    "sg:province":"BC",
    "sg:tags":[
        "bearing"
    ],
    "wof:name":"B C Bearing Engineers Ltd",
    "wof:placetype":"venue"
},
  "geometry": {"coordinates":[-120.224632,55.757462],"type":"Point"}
}