{
  "type": "Feature",
  "properties": {
    "addr:full":"460 Brentcliffe Dr Waterloo ON N2T 2R5",
    "addr:housenumber":"460",
    "addr:postcode":"n2t 2r5",
    "addr:street":"Brentcliffe Dr",
    "iso:country":"CA",
    "sg:address":"460 Brentcliffe Dr",
    "sg:city":"Waterloo",
    "sg:classifiers":[
        {
            "category":"Education",
            "subcategory":"School",
            "type":"Public Place"
        }
    ],
    "sg:phone":"+1 519 884 9999",
    "sg:postcode":"N2T 2R5",
    "sg:province":"ON",
    "wof:name":"Laurelwood Public School",
    "wof:placetype":"venue"
},
  "geometry": {"coordinates":[-80.576286,43.46854],"type":"Point"}
}