{
  "type": "Feature",
  "properties": {
    "addr:full":"127 Jasper St Maple Creek SK S0N 1N0",
    "addr:housenumber":"127",
    "addr:postcode":"s0n 1n0",
    "addr:street":"Jasper St",
    "iso:country":"CA",
    "sg:address":"127 Jasper St",
    "sg:city":"Maple Creek",
    "sg:classifiers":[
        {
            "category":"Home & Garden",
            "subcategory":"Furniture",
            "type":"Retail Goods"
        }
    ],
    "sg:phone":"+1 306 662 4200",
    "sg:postcode":"S0N 1N0",
    "sg:province":"SK",
    "wof:name":"Weswood Furniture",
    "wof:placetype":"venue"
},
  "geometry": {"coordinates":[-109.480407715,49.9065856934],"type":"Point"}
}