{
  "type": "Feature",
  "properties": {
    "addr:full":"9 Rue Martin Gaspe QC G4X 5C9",
    "addr:housenumber":"9",
    "addr:postcode":"g4x 5c9",
    "addr:street":"Rue Martin Gaspe",
    "iso:country":"CA",
    "sg:address":"9 Rue Martin",
    "sg:city":"Gaspe",
    "sg:classifiers":[
        {
            "category":"Shopping",
            "type":"Retail Goods"
        }
    ],
    "sg:phone":"+1 418 269 3914",
    "sg:postcode":"G4X 5C9",
    "sg:province":"QC",
    "sg:tags":[
        "trophy",
        "medal",
        "award"
    ],
    "wof:name":"Centre Du Trophee Enr",
    "wof:placetype":"venue"
},
  "geometry": {"coordinates":[-64.393761,48.998234],"type":"Point"}
}