{
  "type": "Feature",
  "properties": {
    "addr:full":"870 Ellice Ave Winnipeg MB R3G 0C4",
    "addr:housenumber":"870",
    "addr:postcode":"r3g 0c4",
    "addr:street":"Ellice Ave",
    "iso:country":"CA",
    "sg:address":"870 Ellice Ave",
    "sg:city":"Winnipeg",
    "sg:classifiers":[
        {
            "category":"Banks & Credit Unions",
            "subcategory":"Investment Brokerage",
            "type":"Services"
        }
    ],
    "sg:phone":"+1 204 779 4444",
    "sg:postcode":"R3G 0C4",
    "sg:province":"MB",
    "sg:tags":[
        "consultant",
        "financing",
        "planning",
        "financial"
    ],
    "wof:name":"Berkshire Investment Group Inc",
    "wof:placetype":"venue"
},
  "geometry": {"coordinates":[-97.17203499999999,49.893288],"type":"Point"}
}