{
  "type": "Feature",
  "properties": {
    "addr:full":"159 Rue Louvois Chicoutimi QC G7G 2K2",
    "addr:housenumber":"159",
    "addr:postcode":"g7g 2k2",
    "addr:street":"Rue Louvois",
    "iso:country":"CA",
    "sg:address":"159 Rue Louvois",
    "sg:city":"Chicoutimi",
    "sg:classifiers":[
        {
            "category":"Home & Garden",
            "subcategory":"Household Appliances",
            "type":"Retail Goods"
        }
    ],
    "sg:phone":"+1 418 545 8521",
    "sg:postcode":"G7G 2K2",
    "sg:province":"QC",
    "wof:name":"Protection Service Select",
    "wof:placetype":"venue"
},
  "geometry": {"coordinates":[-71.046532,48.441055],"type":"Point"}
}