{
  "type": "Feature",
  "properties": {
    "addr:full":"1210 French Settlement Kemptville ON K0G 1J0",
    "addr:housenumber":"1210",
    "addr:postcode":"k0g 1j0",
    "addr:street":"French Settlement",
    "iso:country":"CA",
    "sg:address":"1210 French Settlement",
    "sg:city":"Kemptville",
    "sg:classifiers":[
        {
            "category":"Building & Trades",
            "subcategory":"Landscaping Services",
            "type":"Services"
        }
    ],
    "sg:phone":"+1 613 258 1177",
    "sg:postcode":"K0G 1J0",
    "sg:province":"ON",
    "sg:tags":[
        "landscape",
        "contractor"
    ],
    "wof:name":"John Denk Landscaping",
    "wof:placetype":"venue"
},
  "geometry": {"coordinates":[-75.6204528809,45.0359115601],"type":"Point"}
}