{
  "type": "Feature",
  "properties": {
    "addr:full":"7430 50th Ave Gibbons AB T0A 1N0",
    "addr:housenumber":"7430",
    "addr:postcode":"t0a 1n0",
    "addr:street":"50Th Ave",
    "iso:country":"CA",
    "sg:address":"7430 50th Ave",
    "sg:city":"Gibbons",
    "sg:classifiers":[
        {
            "category":"Real Estate",
            "subcategory":"Real Estate Agent",
            "type":"Services"
        }
    ],
    "sg:phone":"+1 780 923 3000",
    "sg:postcode":"T0A 1N0",
    "sg:province":"AB",
    "wof:name":"Re/Max Real Estate",
    "wof:placetype":"venue"
},
  "geometry": {"coordinates":[-113.33049,53.828999],"type":"Point"}
}