{
  "type": "Feature",
  "properties": {
    "addr:full":"Vancouver BC V6Z 1N9",
    "addr:postcode":"v6z 1n9",
    "iso:country":"CA",
    "sg:city":"Vancouver",
    "sg:classifiers":[
        {
            "category":"Wholesale",
            "subcategory":"Durable Goods & Equipment",
            "type":"Manufacturing & Wholesale Goods"
        }
    ],
    "sg:phone":"+1 604 682 0308",
    "sg:postcode":"V6Z 1N9",
    "sg:province":"BC",
    "sg:tags":[
        "importer"
    ],
    "wof:name":"Laicor International Ltd",
    "wof:placetype":"venue"
},
  "geometry": {"coordinates":[-123.122840881,49.2804031372],"type":"Point"}
}