{
  "type": "Feature",
  "properties": {
    "addr:full":"11862 Highway 48 Stouffville ON L4A 7X5",
    "addr:housenumber":"11862",
    "addr:postcode":"l4a 7x5",
    "addr:street":"Highway 48",
    "iso:country":"CA",
    "sg:address":"11862 Highway 48",
    "sg:city":"Stouffville",
    "sg:classifiers":[
        {
            "category":"Utilities",
            "subcategory":"Refuse",
            "type":"Services"
        }
    ],
    "sg:phone":"+1 905 642 5380",
    "sg:postcode":"L4A 7X5",
    "sg:province":"ON",
    "sg:tags":[
        "garbage",
        "garden",
        "collection",
        "center"
    ],
    "wof:name":"Farmer Jack's Gardens 1993 Inc",
    "wof:placetype":"venue"
},
  "geometry": {"coordinates":[-79.248024,43.971085],"type":"Point"}
}