{
  "type": "Feature",
  "properties": {
    "addr:full":"229 Rue Fleury O Montreal QC H3L 1T8",
    "addr:housenumber":"229",
    "addr:postcode":"h3l 1t8",
    "addr:street":"Rue Fleury O",
    "iso:country":"CA",
    "sg:address":"229 Rue Fleury O",
    "sg:city":"Montreal",
    "sg:classifiers":[
        {
            "category":"Organizations",
            "subcategory":"Professional Association",
            "type":"Services"
        }
    ],
    "sg:phone":"+1 514 388 4129",
    "sg:postcode":"H3L 1T8",
    "sg:province":"QC",
    "wof:name":"Casa Dos Acores DO Quebeque",
    "wof:placetype":"venue"
},
  "geometry": {"coordinates":[-73.663826,45.550541],"type":"Point"}
}