{
  "type": "Feature",
  "properties": {
    "addr:full":"373 John St Neustadt ON N0G 2M0",
    "addr:housenumber":"373",
    "addr:postcode":"n0g 2m0",
    "addr:street":"John St",
    "iso:country":"CA",
    "sg:address":"373 John St",
    "sg:city":"Neustadt",
    "sg:classifiers":[
        {
            "category":"Professional",
            "subcategory":"Business Services",
            "type":"Services"
        }
    ],
    "sg:phone":"+1 519 799 5952",
    "sg:postcode":"N0G 2M0",
    "sg:province":"ON",
    "sg:tags":[
        "painter",
        "sign"
    ],
    "wof:name":"Gemini Canada",
    "wof:placetype":"venue"
},
  "geometry": {"coordinates":[-81.0000305176,44.0808372498],"type":"Point"}
}