{
  "type": "Feature",
  "properties": {
    "addr:full":"102 Rue Saint-Antoine Gatineau QC J8T 3M1",
    "addr:housenumber":"102",
    "addr:postcode":"j8t 3m1",
    "addr:street":"Rue Saint-Antoine",
    "iso:country":"CA",
    "sg:address":"102 Rue Saint-Antoine",
    "sg:city":"Gatineau",
    "sg:classifiers":[
        {
            "category":"Shopping",
            "subcategory":"Used Merchandise",
            "type":"Retail Goods"
        }
    ],
    "sg:phone":"+1 819 246 2264",
    "sg:postcode":"J8T 3M1",
    "sg:province":"QC",
    "sg:tags":[
        "pawnbroker"
    ],
    "wof:name":"Howard's Pawn Shop",
    "wof:placetype":"venue"
},
  "geometry": {"coordinates":[-75.69886779789999,45.4619636536],"type":"Point"}
}