{
  "type": "Feature",
  "properties": {
    "addr:full":"4905 Darcy Rd Courtenay BC V9J 1R5",
    "addr:housenumber":"4905",
    "addr:postcode":"v9j 1r5",
    "addr:street":"Darcy Rd",
    "iso:country":"CA",
    "sg:address":"4905 Darcy Rd",
    "sg:city":"Courtenay",
    "sg:classifiers":[
        {
            "category":"Food & Beverages",
            "subcategory":"Fruits & Vegetables",
            "type":"Retail Goods"
        }
    ],
    "sg:phone":"+1 250 338 9765",
    "sg:postcode":"V9J 1R5",
    "sg:province":"BC",
    "sg:tags":[
        "produce"
    ],
    "wof:name":"Nature's Way Farm",
    "wof:placetype":"venue"
},
  "geometry": {"coordinates":[-124.99314099999999,49.686722],"type":"Point"}
}