{
  "type": "Feature",
  "properties": {
    "addr:full":"221 Turtlehead Rd Belcarra BC V3H 4P3",
    "addr:housenumber":"221",
    "addr:postcode":"v3h 4p3",
    "addr:street":"Turtlehead Rd",
    "iso:country":"CA",
    "sg:address":"221 Turtlehead Rd",
    "sg:city":"Belcarra",
    "sg:classifiers":[
        {
            "category":"Wholesale",
            "subcategory":"Medical Equipment & Supplies",
            "type":"Manufacturing & Wholesale Goods"
        }
    ],
    "sg:phone":"+1 604 469 4968",
    "sg:postcode":"V3H 4P3",
    "sg:province":"BC",
    "sg:tags":[
        "dental"
    ],
    "wof:name":"Davis Dental Cabinets",
    "wof:placetype":"venue"
},
  "geometry": {"coordinates":[-122.93104599999999,49.317635],"type":"Point"}
}