{
  "type": "Feature",
  "properties": {
    "addr:full":"2002 Park Royal S West Vancouver BC V7T 2W4",
    "addr:housenumber":"2002",
    "addr:postcode":"v7t 2w4",
    "addr:street":"Park Royal S West",
    "iso:country":"CA",
    "sg:address":"2002 Park Royal S",
    "sg:city":"West Vancouver",
    "sg:classifiers":[
        {
            "category":"Real Estate",
            "subcategory":"Real Estate Operator",
            "type":"Services"
        }
    ],
    "sg:phone":"+1 604 925 9576",
    "sg:postcode":"V7T 2W4",
    "sg:province":"BC",
    "sg:tags":[
        "mall",
        "shopping",
        "center"
    ],
    "wof:name":"Park Royal Shopping Ctr",
    "wof:placetype":"venue"
},
  "geometry": {"coordinates":[-123.140137,49.324551],"type":"Point"}
}