{
  "type": "Feature",
  "properties": {
    "addr:full":"4944 John St Beamsville ON L0R 1B6",
    "addr:housenumber":"4944",
    "addr:postcode":"l0r 1b6",
    "addr:street":"John St",
    "iso:country":"CA",
    "sg:address":"4944 John St",
    "sg:city":"Beamsville",
    "sg:classifiers":[
        {
            "category":"Education",
            "subcategory":"School",
            "type":"Public Place"
        }
    ],
    "sg:phone":"+1 905 563 7431",
    "sg:postcode":"L0R 1B6",
    "sg:province":"ON",
    "wof:name":"Senator Gibson School",
    "wof:placetype":"venue"
},
  "geometry": {"coordinates":[-79.4737854004,43.1711845398],"type":"Point"}
}