{
  "type": "Feature",
  "properties": {
    "addr:full":"13050 88 Ave Surrey BC V3W 3K3",
    "addr:housenumber":"13050",
    "addr:postcode":"v3w 3k3",
    "addr:street":"88 Ave",
    "iso:country":"CA",
    "sg:address":"13050 88 Ave",
    "sg:city":"Surrey",
    "sg:classifiers":[
        {
            "category":"Wholesale",
            "subcategory":"Auto Parts",
            "type":"Manufacturing & Wholesale Goods"
        }
    ],
    "sg:phone":"+1 604 543 0880",
    "sg:postcode":"V3W 3K3",
    "sg:province":"BC",
    "sg:tags":[
        "automobile",
        "wrecking"
    ],
    "wof:name":"Vancouver Core Supply Ltd",
    "wof:placetype":"venue"
},
  "geometry": {"coordinates":[-122.860710144,49.1624755859],"type":"Point"}
}