{
  "type": "Feature",
  "properties": {
    "addr:full":"999 Rue Dollard Buckingham QC J8L 3E6",
    "addr:housenumber":"999",
    "addr:postcode":"j8l 3e6",
    "addr:street":"Rue Dollard",
    "iso:country":"CA",
    "sg:address":"999 Rue Dollard",
    "sg:city":"Buckingham",
    "sg:classifiers":[
        {
            "category":"Restaurant",
            "type":"Food & Drink"
        }
    ],
    "sg:phone":"+1 819 986 2724",
    "sg:postcode":"J8L 3E6",
    "sg:province":"QC",
    "wof:name":"Jardins Buckingham",
    "wof:placetype":"venue"
},
  "geometry": {"coordinates":[-75.40706634519999,45.5765647888],"type":"Point"}
}