{
  "type": "Feature",
  "properties": {
    "addr:full":"20834 3 Hwy W Port Colborne ON L3K 5V4",
    "addr:housenumber":"20834",
    "addr:postcode":"l3k 5v4",
    "addr:street":"3 Hwy W",
    "iso:country":"CA",
    "sg:address":"20834 3 Hwy W",
    "sg:city":"Port Colborne",
    "sg:classifiers":[
        {
            "category":"Professional",
            "subcategory":"Accounting & Tax Preparation",
            "type":"Services"
        }
    ],
    "sg:phone":"+1 905 835 0273",
    "sg:postcode":"L3K 5V4",
    "sg:province":"ON",
    "sg:tags":[
        "bookkeeping",
        "general"
    ],
    "wof:name":"Merritt Bookkeeping Svc",
    "wof:placetype":"venue"
},
  "geometry": {"coordinates":[-79.1814956665,42.8735694885],"type":"Point"}
}