{
  "type": "Feature",
  "properties": {
    "addr:full":"1416 Front St Hearst ON P0L 1N0",
    "addr:housenumber":"1416",
    "addr:postcode":"p0l 1n0",
    "addr:street":"Front St",
    "iso:country":"CA",
    "sg:address":"1416 Front St",
    "sg:city":"Hearst",
    "sg:classifiers":[
        {
            "category":"Professional",
            "subcategory":"Business Services",
            "type":"Services"
        }
    ],
    "sg:phone":"+1 705 362 8755",
    "sg:postcode":"P0L 1N0",
    "sg:province":"ON",
    "sg:tags":[
        "embroidery"
    ],
    "wof:name":"Nicole Stitch on",
    "wof:placetype":"venue"
},
  "geometry": {"coordinates":[-83.6788024902,49.6910095215],"type":"Point"}
}