{
  "type": "Feature",
  "properties": {
    "addr:full":"9 Second Ave Orangeville ON L9W 1H4",
    "addr:housenumber":"9",
    "addr:postcode":"l9w 1h4",
    "addr:street":"Second Ave",
    "iso:country":"CA",
    "sg:address":"9 Second Ave",
    "sg:city":"Orangeville",
    "sg:classifiers":[
        {
            "category":"Personal",
            "subcategory":"Beauty Salon",
            "type":"Services"
        }
    ],
    "sg:phone":"+1 519 942 3905",
    "sg:postcode":"L9W 1H4",
    "sg:province":"ON",
    "wof:name":"Tender Touch",
    "wof:placetype":"venue"
},
  "geometry": {"coordinates":[-80.09635900000001,43.921806],"type":"Point"}
}