{
  "type": "Feature",
  "properties": {
    "addr:full":"1207 12 Ave SW Calgary AB T3C 3S7",
    "addr:housenumber":"1207",
    "addr:postcode":"t3c 3s7",
    "addr:street":"12 Ave Sw",
    "iso:country":"CA",
    "sg:address":"1207 12 Ave SW",
    "sg:city":"Calgary",
    "sg:classifiers":[
        {
            "category":"Restaurant",
            "type":"Food & Drink"
        }
    ],
    "sg:phone":"+1 403 244 3183",
    "sg:postcode":"T3C 3S7",
    "sg:province":"AB",
    "wof:name":"Subway Sandwiches & Salads",
    "wof:placetype":"venue"
},
  "geometry": {"coordinates":[-114.089294434,51.0420150757],"type":"Point"}
}