{
  "type": "Feature",
  "properties": {
    "addr:full":"Sherwood Park AB T8A 3W8",
    "addr:postcode":"t8a 3w8",
    "iso:country":"CA",
    "sg:city":"Sherwood Park",
    "sg:classifiers":[
        {
            "category":"Health Services",
            "subcategory":"Doctor",
            "type":"Services"
        }
    ],
    "sg:phone":"+1 780 464 6411",
    "sg:postcode":"T8A 3W8",
    "sg:province":"AB",
    "sg:tags":[
        "physician",
        "clinic",
        "surgeon"
    ],
    "wof:name":"Main Medical Clinic",
    "wof:placetype":"venue"
},
  "geometry": {"coordinates":[-113.31857299799999,53.53748703],"type":"Point"}
}