{
  "type": "Feature",
  "properties": {
    "iso:country":"CA",
    "sg:address":"6831 Av DE L'Epee",
    "sg:city":"Montreal",
    "sg:classifiers":[
        {
            "category":"Manufacturing",
            "subcategory":"Wood Products",
            "type":"Manufacturing & Wholesale Goods"
        }
    ],
    "sg:phone":"+1 514 495 1930",
    "sg:postcode":"H3N 2C7",
    "sg:province":"QC",
    "sg:tags":[
        "picture",
        "frame"
    ],
    "wof:name":"Encadrement Olympic",
    "wof:placetype":"venue"
},
  "geometry": {"coordinates":[-73.621887,45.527435],"type":"Point"}
}