{
  "type": "Feature",
  "properties": {
    "addr:full":"Cabot Hwy Catalina NL A0C 1J0",
    "addr:postcode":"a0c 1j0",
    "addr:street":"Cabot Hwy",
    "iso:country":"CA",
    "sg:address":"Cabot Hwy",
    "sg:city":"Catalina",
    "sg:classifiers":[
        {
            "category":"Retail",
            "subcategory":"Auto Repair",
            "type":"Services"
        }
    ],
    "sg:phone":"+1 709 469 2276",
    "sg:postcode":"A0C 1J0",
    "sg:province":"NL",
    "sg:tags":[
        "repairing",
        "automobile"
    ],
    "wof:name":"Roger's Service Ltd",
    "wof:placetype":"venue"
},
  "geometry": {"coordinates":[-53.0776176453,48.5178451538],"type":"Point"}
}