{
  "type": "Feature",
  "properties": {
    "addr:full":"1185 Riverside Dr Timmins ON P4R 1A3",
    "addr:housenumber":"1185",
    "addr:postcode":"p4r 1a3",
    "addr:street":"Riverside Dr",
    "iso:country":"CA",
    "sg:address":"1185 Riverside Dr",
    "sg:city":"Timmins",
    "sg:classifiers":[
        {
            "category":"Manufacturing",
            "subcategory":"Signs",
            "type":"Manufacturing & Wholesale Goods"
        }
    ],
    "sg:phone":"+1 705 268 8383",
    "sg:postcode":"P4R 1A3",
    "sg:province":"ON",
    "wof:name":"Computerized Lettering & Signs",
    "wof:placetype":"venue"
},
  "geometry": {"coordinates":[-81.37101745610001,48.4724006653],"type":"Point"}
}