{
  "type": "Feature",
  "properties": {
    "iso:country":"CA",
    "sg:address":"41 Alice St",
    "sg:city":"Mount Albert",
    "sg:classifiers":[
        {
            "category":"Organizations",
            "subcategory":"Religious Organization",
            "type":"Services"
        }
    ],
    "sg:phone":"+1 905 473 2562",
    "sg:postcode":"L0G 1M0",
    "sg:province":"ON",
    "sg:tags":[
        "church"
    ],
    "wof:name":"Mount Albert United Church",
    "wof:placetype":"venue"
},
  "geometry": {"coordinates":[-79.306969,44.135914],"type":"Point"}
}