{
  "type": "Feature",
  "properties": {
    "iso:country":"CA",
    "sg:address":"7293 Wilson Ave",
    "sg:city":"Delta",
    "sg:classifiers":[
        {
            "category":"Airport",
            "type":"Transportation"
        }
    ],
    "sg:phone":"+1 604 940 1715",
    "sg:postcode":"V4G 1E5",
    "sg:province":"BC",
    "sg:tags":[
        "support",
        "airline"
    ],
    "wof:name":"Canadian Air-Crane",
    "wof:placetype":"venue"
},
  "geometry": {"coordinates":[-123.020080566,49.1298561096],"type":"Point"}
}