{
  "type": "Feature",
  "properties": {
    "addr:full":"126 Sykes St N Meaford ON N4L 1P3",
    "addr:housenumber":"126",
    "addr:postcode":"n4l 1p3",
    "addr:street":"Sykes St N",
    "iso:country":"CA",
    "sg:address":"126 Sykes St N",
    "sg:city":"Meaford",
    "sg:classifiers":[
        {
            "category":"Travel",
            "subcategory":"Hotels & Motels",
            "type":"Entertainment"
        }
    ],
    "sg:phone":"+1 519 538 5799",
    "sg:postcode":"N4L 1P3",
    "sg:province":"ON",
    "wof:name":"Meaford Motel & Restaurant",
    "wof:placetype":"venue"
},
  "geometry": {"coordinates":[-80.59293365480001,44.6095123291],"type":"Point"}
}