{
  "type": "Feature",
  "properties": {
    "addr:full":"550 Industrial Rd Cambridge ON N3H 4V9",
    "addr:housenumber":"550",
    "addr:postcode":"n3h 4v9",
    "addr:street":"Industrial Rd",
    "iso:country":"CA",
    "sg:address":"550 Industrial Rd",
    "sg:city":"Cambridge",
    "sg:classifiers":[
        {
            "category":"Retail",
            "subcategory":"Auto Rental",
            "type":"Services"
        }
    ],
    "sg:phone":"+1 519 650 3242",
    "sg:postcode":"N3H 4V9",
    "sg:province":"ON",
    "sg:tags":[
        "renting",
        "automobile"
    ],
    "wof:name":"Carter Car & Truck Rentals",
    "wof:placetype":"venue"
},
  "geometry": {"coordinates":[-80.333152771,43.4061050415],"type":"Point"}
}