{
  "type": "Feature",
  "properties": {
    "addr:full":"10686 Stella Rd Fraser Lake BC V0J 1S0",
    "addr:housenumber":"10686",
    "addr:postcode":"v0j 1s0",
    "addr:street":"Stella Rd",
    "iso:country":"CA",
    "sg:address":"10686 Stella Rd",
    "sg:city":"Fraser Lake",
    "sg:classifiers":[
        {
            "category":"Manufacturing",
            "subcategory":"Lumber",
            "type":"Manufacturing & Wholesale Goods"
        }
    ],
    "sg:phone":"+1 250 699 6406",
    "sg:postcode":"V0J 1S0",
    "sg:province":"BC",
    "sg:tags":[
        "company",
        "logging"
    ],
    "wof:name":"Sandback Logging Ltd",
    "wof:placetype":"venue"
},
  "geometry": {"coordinates":[-124.845947266,54.0573425293],"type":"Point"}
}