{
  "type": "Feature",
  "properties": {
    "addr:full":"Omemee ON K0L 2W0",
    "addr:postcode":"k0l 2w0",
    "iso:country":"CA",
    "sg:city":"Omemee",
    "sg:classifiers":[
        {
            "category":"Shopping",
            "subcategory":"Computers & Home Electronics",
            "type":"Retail Goods"
        }
    ],
    "sg:phone":"+1 705 799 7227",
    "sg:postcode":"K0L 2W0",
    "sg:province":"ON",
    "sg:tags":[
        "equipment",
        "television",
        "radio",
        "satellite"
    ],
    "wof:name":"Hale Tv & Stereo Svc",
    "wof:placetype":"venue"
},
  "geometry": {"coordinates":[-78.5489578247,44.2920761108],"type":"Point"}
}