{
  "type": "Feature",
  "properties": {
    "addr:full":"121 21 Ave NE Calgary AB T2E 1S3",
    "addr:housenumber":"121",
    "addr:postcode":"t2e 1s3",
    "addr:street":"21 Ave Ne",
    "iso:country":"CA",
    "sg:address":"121 21 Ave NE",
    "sg:city":"Calgary",
    "sg:classifiers":[
        {
            "category":"Travel",
            "subcategory":"Hotels & Motels",
            "type":"Entertainment"
        }
    ],
    "sg:phone":"+1 403 277 5298",
    "sg:postcode":"T2E 1S3",
    "sg:province":"AB",
    "sg:tags":[
        "breakfast",
        "accommodation",
        "bed"
    ],
    "wof:name":"Tuxedo House Bed & Breakfast",
    "wof:placetype":"venue"
},
  "geometry": {"coordinates":[-114.061813355,51.071395874],"type":"Point"}
}