{
  "type": "Feature",
  "properties": {
    "addr:full":"4132 Boul Dagenais O Laval QC H7R 1L4",
    "addr:housenumber":"4132",
    "addr:postcode":"h7r 1l4",
    "addr:street":"Boul Dagenais O",
    "iso:country":"CA",
    "sg:address":"4132 Boul Dagenais O",
    "sg:city":"Laval",
    "sg:classifiers":[
        {
            "category":"Utilities",
            "subcategory":"Fuel Oil & Lpg",
            "type":"Services"
        }
    ],
    "sg:phone":"+1 450 628 1010",
    "sg:postcode":"H7R 1L4",
    "sg:province":"QC",
    "sg:tags":[
        "firewood"
    ],
    "wof:name":"Real Gauthier Bois DE Foyer",
    "wof:placetype":"venue"
},
  "geometry": {"coordinates":[-73.83255,45.561047],"type":"Point"}
}