{
  "type": "Feature",
  "properties": {
    "addr:full":"PO Box 115 Burdett AB T0K 0J0",
    "addr:housenumber":"po",
    "addr:postcode":"t0k 0j0",
    "addr:street":"Box 115",
    "iso:country":"CA",
    "sg:address":"PO Box 115",
    "sg:city":"Burdett",
    "sg:classifiers":[
        {
            "category":"Arena",
            "subcategory":"Sports Club",
            "type":"Entertainment"
        }
    ],
    "sg:phone":"+1 403 833 3825",
    "sg:postcode":"T0K 0J0",
    "sg:province":"AB",
    "sg:tags":[
        "athletic",
        "fields",
        "stadium"
    ],
    "wof:name":"Burdett Arena",
    "wof:placetype":"venue"
},
  "geometry": {"coordinates":[-111.51973,49.828758],"type":"Point"}
}