{
  "type": "Feature",
  "properties": {
    "addr:full":"744 St Clair Ave W Toronto ON M6C 1B5",
    "addr:housenumber":"744",
    "addr:postcode":"m6c 1b5",
    "addr:street":"St Clair Ave W",
    "iso:country":"CA",
    "sg:address":"744 St Clair Ave W",
    "sg:city":"Toronto",
    "sg:classifiers":[
        {
            "category":"Restaurant",
            "type":"Food & Drink"
        }
    ],
    "sg:phone":"+1 416 658 0568",
    "sg:postcode":"M6C 1B5",
    "sg:province":"ON",
    "wof:name":"Filippo's",
    "wof:placetype":"venue"
},
  "geometry": {"coordinates":[-79.42794036870001,43.6813926697],"type":"Point"}
}