{
  "type": "Feature",
  "properties": {
    "addr:full":"30 Kains St St Thomas ON N5P 1M9",
    "addr:housenumber":"30",
    "addr:postcode":"n5p 1m9",
    "addr:street":"Kains St",
    "iso:country":"CA",
    "sg:address":"30 Kains St",
    "sg:city":"St Thomas",
    "sg:classifiers":[
        {
            "category":"Building & Trades",
            "subcategory":"Cleaning & Sanitation",
            "type":"Services"
        }
    ],
    "sg:phone":"+1 519 631 0789",
    "sg:postcode":"N5P 1M9",
    "sg:province":"ON",
    "sg:tags":[
        "butler",
        "maid"
    ],
    "wof:name":"J & J Cleaning",
    "wof:placetype":"venue"
},
  "geometry": {"coordinates":[-81.189606,42.781174],"type":"Point"}
}