{
  "type": "Feature",
  "properties": {
    "addr:full":"Sydney NS B1P 1J7",
    "addr:postcode":"b1p 1j7",
    "iso:country":"CA",
    "sg:city":"Sydney",
    "sg:classifiers":[
        {
            "category":"Health Services",
            "subcategory":"Doctor",
            "type":"Services"
        }
    ],
    "sg:phone":"+1 902 564 8105",
    "sg:postcode":"B1P 1J7",
    "sg:province":"NS",
    "sg:tags":[
        "physician",
        "surgeon"
    ],
    "wof:name":"Myatt, Gregory MD",
    "wof:placetype":"venue"
},
  "geometry": {"coordinates":[-60.193134,46.140709],"type":"Point"}
}