{
  "type": "Feature",
  "properties": {
    "iso:country":"CA",
    "sg:address":"1947 Cook St",
    "sg:city":"Victoria",
    "sg:classifiers":[
        {
            "category":"Government",
            "subcategory":"Office",
            "type":"Public Place"
        }
    ],
    "sg:phone":"+1 250 388 2300",
    "sg:postcode":"V8T 3P7",
    "sg:province":"BC",
    "wof:name":"B C Primary/Community Care",
    "wof:placetype":"venue"
},
  "geometry": {"coordinates":[-123.352516174,48.431137085],"type":"Point"}
}