{
  "type": "Feature",
  "properties": {
    "addr:full":"24 King St W Dundas ON L9H 1T7",
    "addr:housenumber":"24",
    "addr:postcode":"l9h 1t7",
    "addr:street":"King St W",
    "iso:country":"CA",
    "sg:address":"24 King St W",
    "sg:city":"Dundas",
    "sg:classifiers":[
        {
            "category":"Food & Beverages",
            "subcategory":"Specialty",
            "type":"Retail Goods"
        }
    ],
    "sg:phone":"+1 905 627 9980",
    "sg:postcode":"L9H 1T7",
    "sg:province":"ON",
    "sg:tags":[
        "health",
        "diet"
    ],
    "wof:name":"Horn of Plenty",
    "wof:placetype":"venue"
},
  "geometry": {"coordinates":[-79.95510101319999,43.2661323547],"type":"Point"}
}