{
  "type": "Feature",
  "properties": {
    "addr:full":"182 Turbine Dr North York ON M9L 2S2",
    "addr:housenumber":"182",
    "addr:postcode":"m9l 2s2",
    "addr:street":"Turbine Dr",
    "iso:country":"CA",
    "sg:address":"182 Turbine Dr",
    "sg:city":"North York",
    "sg:classifiers":[
        {
            "category":"Manufacturing",
            "subcategory":"Glass & Minerals",
            "type":"Manufacturing & Wholesale Goods"
        }
    ],
    "sg:phone":"+1 416 749 4637",
    "sg:postcode":"M9L 2S2",
    "sg:province":"ON",
    "sg:tags":[
        "product",
        "marble"
    ],
    "wof:name":"Accurate Ceramics & Marble",
    "wof:placetype":"venue"
},
  "geometry": {"coordinates":[-79.5577926636,43.7675056458],"type":"Point"}
}