{
  "type": "Feature",
  "properties": {
    "addr:full":"5653 Boul Henri-Bourassa E Montreal-Nord QC H1G 2T4",
    "addr:housenumber":"5653",
    "addr:postcode":"h1g 2t4",
    "addr:street":"Boul Henri-Bourassa E",
    "iso:country":"CA",
    "sg:address":"5653 Boul Henri-Bourassa E",
    "sg:city":"Montreal-Nord",
    "sg:classifiers":[
        {
            "category":"Health Services",
            "subcategory":"Health Practitioner",
            "type":"Services"
        }
    ],
    "sg:phone":"+1 514 327 8972",
    "sg:postcode":"H1G 2T4",
    "sg:province":"QC",
    "sg:tags":[
        "acupuncture"
    ],
    "wof:name":"Clinique D'Acpnctr H Nguyen",
    "wof:placetype":"venue"
},
  "geometry": {"coordinates":[-73.620811,45.606617],"type":"Point"}
}