{
  "type": "Feature",
  "properties": {
    "addr:full":"3121 St Mary's Rd Winnipeg MB R2N 4B1",
    "addr:housenumber":"3121",
    "addr:postcode":"r2n 4b1",
    "addr:street":"St Mary'S Rd",
    "iso:country":"CA",
    "sg:address":"3121 St Mary's Rd",
    "sg:city":"Winnipeg",
    "sg:classifiers":[
        {
            "category":"Building & Trades",
            "subcategory":"Construction",
            "type":"Services"
        }
    ],
    "sg:phone":"+1 204 257 9519",
    "sg:postcode":"R2N 4B1",
    "sg:province":"MB",
    "sg:tags":[
        "general",
        "contractor"
    ],
    "wof:name":"Pine Ridge Construction",
    "wof:placetype":"venue"
},
  "geometry": {"coordinates":[-97.1276397705,49.7707176208],"type":"Point"}
}