{
  "type": "Feature",
  "properties": {
    "iso:country":"CA",
    "sg:address":"120 Boul DE Bromont",
    "sg:city":"Bromont",
    "sg:classifiers":[
        {
            "category":"Restaurant",
            "type":"Food & Drink"
        }
    ],
    "sg:phone":"+1 450 534 3000",
    "sg:postcode":"J2L 2K8",
    "sg:province":"QC",
    "sg:tags":[
        "glassware",
        "chinaware"
    ],
    "wof:name":"Cuisine Et Cie",
    "wof:placetype":"venue"
},
  "geometry": {"coordinates":[-72.64045715330001,45.3154373169],"type":"Point"}
}