{
  "type": "Feature",
  "properties": {
    "addr:full":"Rouyn-Noranda QC J9X 7A2",
    "addr:postcode":"j9x 7a2",
    "iso:country":"CA",
    "sg:city":"Rouyn-Noranda",
    "sg:classifiers":[
        {
            "category":"Organizations",
            "subcategory":"Labor Organization",
            "type":"Services"
        }
    ],
    "sg:phone":"+1 819 762 3001",
    "sg:postcode":"J9X 7A2",
    "sg:province":"QC",
    "wof:name":"Syndicat Des Metallos",
    "wof:placetype":"venue"
},
  "geometry": {"coordinates":[-79.02718400000001,48.241749],"type":"Point"}
}