{
  "type": "Feature",
  "properties": {
    "iso:country":"CA",
    "sg:address":"8007 King George Hwy",
    "sg:city":"Surrey",
    "sg:classifiers":[
        {
            "category":"Food & Beverages",
            "subcategory":"Groceries & Convenience Stores",
            "type":"Retail Goods"
        }
    ],
    "sg:phone":"+1 604 590 5336",
    "sg:postcode":"V3W 5B4",
    "sg:province":"BC",
    "sg:tags":[
        "grocer"
    ],
    "wof:name":"Mac's Convenience Stores Ltd",
    "wof:placetype":"venue"
},
  "geometry": {"coordinates":[-122.845932,49.148453],"type":"Point"}
}