{
  "type": "Feature",
  "properties": {
    "addr:full":"134 Caradoc St N Strathroy ON N7G 2M8",
    "addr:housenumber":"134",
    "addr:postcode":"n7g 2m8",
    "addr:street":"Caradoc St N",
    "iso:country":"CA",
    "sg:address":"134 Caradoc St N",
    "sg:city":"Strathroy",
    "sg:classifiers":[
        {
            "category":"Home & Garden",
            "subcategory":"Hardware",
            "type":"Retail Goods"
        }
    ],
    "sg:phone":"+1 519 245 2599",
    "sg:postcode":"N7G 2M8",
    "sg:province":"ON",
    "wof:name":"Tsc Stores Ltd",
    "wof:placetype":"venue"
},
  "geometry": {"coordinates":[-81.624573,42.958923],"type":"Point"}
}