{
  "type": "Feature",
  "properties": {
    "addr:full":"192 283 Rte Panet QC G0R 2J0",
    "addr:housenumber":"283",
    "addr:postcode":"g0r 2j0",
    "addr:street":"Rte Panet",
    "iso:country":"CA",
    "sg:address":"192 283 Rte",
    "sg:city":"Panet",
    "sg:classifiers":[
        {
            "category":"Shopping",
            "subcategory":"Pharmacy",
            "type":"Retail Goods"
        }
    ],
    "sg:phone":"+1 418 249 2391",
    "sg:postcode":"G0R 2J0",
    "sg:province":"QC",
    "wof:name":"Marcoux & Caron",
    "wof:placetype":"venue"
},
  "geometry": {"coordinates":[-70.14881099999999,46.655239],"type":"Point"}
}