{
  "type": "Feature",
  "properties": {
    "addr:full":"7902 73 Ave NW Edmonton AB T6C 0C5",
    "addr:housenumber":"7902",
    "addr:postcode":"t6c 0c5",
    "addr:street":"73 Ave Nw",
    "iso:country":"CA",
    "sg:address":"7902 73 Ave NW",
    "sg:city":"Edmonton",
    "sg:classifiers":[
        {
            "category":"Recreation",
            "type":"Entertainment"
        }
    ],
    "sg:phone":"+1 780 465 1941",
    "sg:postcode":"T6C 0C5",
    "sg:province":"AB",
    "sg:tags":[
        "hall",
        "auditorium"
    ],
    "wof:name":"Avonmore Community League",
    "wof:placetype":"venue"
},
  "geometry": {"coordinates":[-113.449295044,53.509601593],"type":"Point"}
}