{
  "type": "Feature",
  "properties": {
    "addr:full":"Galiano BC V0N 1P0",
    "addr:postcode":"v0n 1p0",
    "iso:country":"CA",
    "sg:city":"Galiano",
    "sg:classifiers":[
        {
            "category":"Home & Garden",
            "subcategory":"Home Furnishings",
            "type":"Retail Goods"
        }
    ],
    "sg:phone":"+1 250 539 2806",
    "sg:postcode":"V0N 1P0",
    "sg:province":"BC",
    "sg:tags":[
        "cutlery"
    ],
    "wof:name":"Schoenfeld Custom Knives",
    "wof:placetype":"venue"
},
  "geometry": {"coordinates":[-123.33142100000001,48.868591],"type":"Point"}
}