{
  "type": "Feature",
  "properties": {
    "addr:full":"5361 Richmond Rd Nepean ON K2R 1G4",
    "addr:housenumber":"5361",
    "addr:postcode":"k2r 1g4",
    "addr:street":"Richmond Rd",
    "iso:country":"CA",
    "sg:address":"5361 Richmond Rd",
    "sg:city":"Nepean",
    "sg:classifiers":[
        {
            "category":"Retail",
            "subcategory":"Auto Repair",
            "type":"Services"
        }
    ],
    "sg:phone":"+1 613 591 1120",
    "sg:postcode":"K2R 1G4",
    "sg:province":"ON",
    "sg:tags":[
        "repairing",
        "automobile"
    ],
    "wof:name":"Fallowfield Garage",
    "wof:placetype":"venue"
},
  "geometry": {"coordinates":[-75.8337478638,45.2743110657],"type":"Point"}
}