{
  "type": "Feature",
  "properties": {
    "iso:country":"CA",
    "sg:address":"690 2E Av",
    "sg:city":"Louiseville",
    "sg:classifiers":[
        {
            "category":"Building & Trades",
            "subcategory":"Plumbing",
            "type":"Services"
        }
    ],
    "sg:phone":"+1 819 228 5078",
    "sg:postcode":"J5V 2L4",
    "sg:province":"QC",
    "sg:tags":[
        "contractor"
    ],
    "wof:name":"Plomberie R Bellemare Ltee",
    "wof:placetype":"venue"
},
  "geometry": {"coordinates":[-72.92572021479999,46.2457771301],"type":"Point"}
}