{
  "type": "Feature",
  "properties": {
    "addr:full":"1644 Bank St Ottawa ON K1V 7Y6",
    "addr:housenumber":"1644",
    "addr:postcode":"k1v 7y6",
    "addr:street":"Bank St",
    "iso:country":"CA",
    "sg:address":"1644 Bank St",
    "sg:city":"Ottawa",
    "sg:classifiers":[
        {
            "category":"Health Services",
            "subcategory":"Clinic",
            "type":"Services"
        }
    ],
    "sg:phone":"+1 613 738 9661",
    "sg:postcode":"K1V 7Y6",
    "sg:province":"ON",
    "sg:tags":[
        "home"
    ],
    "wof:name":"Saint Elizabeth Health Care",
    "wof:placetype":"venue"
},
  "geometry": {"coordinates":[-75.6669006348,45.3769416809],"type":"Point"}
}