{
  "type": "Feature",
  "properties": {
    "addr:full":"Toronto ON M6P 1T4",
    "addr:postcode":"m6p 1t4",
    "iso:country":"CA",
    "sg:city":"Toronto",
    "sg:classifiers":[
        {
            "category":"Building & Trades",
            "subcategory":"Construction",
            "type":"Services"
        }
    ],
    "sg:phone":"+1 416 588 2004",
    "sg:postcode":"M6P 1T4",
    "sg:province":"ON",
    "sg:tags":[
        "general",
        "contractor"
    ],
    "wof:name":"Structure Corp",
    "wof:placetype":"venue"
},
  "geometry": {"coordinates":[-79.461372,43.666176],"type":"Point"}
}