{
  "type": "Feature",
  "properties": {
    "addr:full":"260 Unimin Rd County Rd 46 Havelock ON K0L 1Z0",
    "addr:housenumber":"260;46",
    "addr:postcode":"k0l 1z0",
    "addr:street":"Unimin Rd County Rd",
    "iso:country":"CA",
    "sg:address":"260 Unimin Rd County Rd 46",
    "sg:city":"Havelock",
    "sg:classifiers":[
        {
            "category":"Professional",
            "type":"Services"
        }
    ],
    "sg:phone":"+1 705 877 2500",
    "sg:postcode":"K0L 1Z0",
    "sg:province":"ON",
    "sg:tags":[
        "mineral"
    ],
    "wof:name":"Unimin Canada Ltd",
    "wof:placetype":"venue"
},
  "geometry": {"coordinates":[-77.8863830566,44.4332008362],"type":"Point"}
}