{
  "type": "Feature",
  "properties": {
    "addr:full":"374 Lower Ganges Rd Salt Spring Island BC V8K 2V7",
    "addr:housenumber":"374",
    "addr:postcode":"v8k 2v7",
    "addr:street":"Lower Ganges Rd",
    "iso:country":"CA",
    "sg:address":"374 Lower Ganges Rd",
    "sg:city":"Salt Spring Island",
    "sg:classifiers":[
        {
            "category":"Food & Beverages",
            "subcategory":"Groceries & Convenience Stores",
            "type":"Retail Goods"
        }
    ],
    "sg:phone":"+1 250 537 4144",
    "sg:postcode":"V8K 2V7",
    "sg:province":"BC",
    "sg:tags":[
        "grocer"
    ],
    "wof:name":"Ganges Village Market",
    "wof:placetype":"venue"
},
  "geometry": {"coordinates":[-123.510811,48.860649],"type":"Point"}
}