{
  "type": "Feature",
  "properties": {
    "addr:full":"1200 Eglinton Ave E # 203 North York ON M3C 1H9",
    "addr:housenumber":"1200",
    "addr:postcode":"m3c 1h9",
    "addr:street":"Eglinton Ave E # 203",
    "iso:country":"CA",
    "sg:address":"1200 Eglinton Ave E # 203",
    "sg:city":"North York",
    "sg:classifiers":[
        {
            "category":"Professional",
            "subcategory":"Lawyer & Legal Services",
            "type":"Services"
        }
    ],
    "sg:phone":"+1 416 398 6900",
    "sg:postcode":"M3C 1H9",
    "sg:province":"ON",
    "sg:tags":[
        "attorney"
    ],
    "wof:name":"Maltz, Murray N",
    "wof:placetype":"venue"
},
  "geometry": {"coordinates":[-79.3354873657,43.721698761],"type":"Point"}
}