{
  "type": "Feature",
  "properties": {
    "addr:full":"1607 Hyde Park Rd London ON N6H 5L7",
    "addr:housenumber":"1607",
    "addr:postcode":"n6h 5l7",
    "addr:street":"Hyde Park Rd",
    "iso:country":"CA",
    "sg:address":"1607 Hyde Park Rd",
    "sg:city":"London",
    "sg:classifiers":[
        {
            "category":"Retail",
            "subcategory":"Auto Repair",
            "type":"Services"
        }
    ],
    "sg:phone":"+1 519 471 3640",
    "sg:postcode":"N6H 5L7",
    "sg:province":"ON",
    "sg:tags":[
        "repairing",
        "automobile"
    ],
    "wof:name":"George Morris Garage",
    "wof:placetype":"venue"
},
  "geometry": {"coordinates":[-81.3321304321,42.9993553162],"type":"Point"}
}