{
  "type": "Feature",
  "properties": {
    "addr:full":"4 Boul Des Iles Port-Cartier QC G5B 1V6",
    "addr:housenumber":"4",
    "addr:postcode":"g5b 1v6",
    "addr:street":"Boul Des Iles",
    "iso:country":"CA",
    "sg:address":"4 Boul Des Iles",
    "sg:city":"Port-Cartier",
    "sg:classifiers":[
        {
            "category":"Bars & Pubs",
            "type":"Food & Drink"
        }
    ],
    "sg:phone":"+1 418 766 4035",
    "sg:postcode":"G5B 1V6",
    "sg:province":"QC",
    "sg:tags":[
        "lounge",
        "cocktail"
    ],
    "wof:name":"Bar LA Casa Enr",
    "wof:placetype":"venue"
},
  "geometry": {"coordinates":[-66.876389,50.021053],"type":"Point"}
}