{
  "type": "Feature",
  "properties": {
    "iso:country":"CA",
    "sg:address":"5101 Highway 59",
    "sg:city":"Brockville",
    "sg:classifiers":[
        {
            "category":"Building & Trades",
            "subcategory":"Construction",
            "type":"Services"
        }
    ],
    "sg:phone":"+1 613 342 6030",
    "sg:postcode":"K6V 5T4",
    "sg:province":"ON",
    "sg:tags":[
        "roofing",
        "contractor",
        "auctioneer"
    ],
    "wof:name":"Bob Perkins Auction Svc",
    "wof:placetype":"venue"
},
  "geometry": {"coordinates":[-75.68301391599999,44.5903892517],"type":"Point"}
}