{
  "type": "Feature",
  "properties": {
    "iso:country":"CA",
    "sg:city":"Woodbridge",
    "sg:classifiers":[
        {
            "category":"Banks & Credit Unions",
            "subcategory":"Investment Brokerage",
            "type":"Services"
        }
    ],
    "sg:phone":"+1 905 856 8000",
    "sg:postcode":"L4L 1S8",
    "sg:province":"ON",
    "sg:tags":[
        "trade",
        "barter",
        "exchange"
    ],
    "wof:name":"Barter Xchange Canada Inc",
    "wof:placetype":"venue"
},
  "geometry": {"coordinates":[-79.586182,43.781418],"type":"Point"}
}