{
  "type": "Feature",
  "properties": {
    "addr:full":"504 Gormanville Rd North Bay ON P1B 4V5",
    "addr:housenumber":"504",
    "addr:postcode":"p1b 4v5",
    "addr:street":"Gormanville Rd",
    "iso:country":"CA",
    "sg:address":"504 Gormanville Rd",
    "sg:city":"North Bay",
    "sg:classifiers":[
        {
            "category":"Food & Beverages",
            "subcategory":"Groceries & Convenience Stores",
            "type":"Retail Goods"
        }
    ],
    "sg:phone":"+1 705 497 0300",
    "sg:postcode":"P1B 4V5",
    "sg:province":"ON",
    "sg:tags":[
        "grocer"
    ],
    "wof:name":"Gormanville Grocery",
    "wof:placetype":"venue"
},
  "geometry": {"coordinates":[-79.487297,46.325314],"type":"Point"}
}