{
  "type": "Feature",
  "properties": {
    "addr:full":"Ashern MB R0C 0E0",
    "addr:postcode":"r0c 0e0",
    "iso:country":"CA",
    "sg:city":"Ashern",
    "sg:classifiers":[
        {
            "category":"Banks & Credit Unions",
            "subcategory":"Bank",
            "type":"Services"
        }
    ],
    "sg:phone":"+1 204 768 2733",
    "sg:postcode":"R0C 0E0",
    "sg:province":"MB",
    "wof:name":"Eriksdale Credit Union Ltd",
    "wof:placetype":"venue"
},
  "geometry": {"coordinates":[-98.3502655029,51.1808052063],"type":"Point"}
}