{
  "type": "Feature",
  "properties": {
    "addr:full":"1644 Marine Dr SE Vancouver BC V5P 2R6",
    "addr:housenumber":"1644",
    "addr:postcode":"v5p 2r6",
    "addr:street":"Marine Dr Se",
    "iso:country":"CA",
    "sg:address":"1644 Marine Dr SE",
    "sg:city":"Vancouver",
    "sg:classifiers":[
        {
            "category":"Wholesale",
            "subcategory":"Sporting Goods",
            "type":"Manufacturing & Wholesale Goods"
        }
    ],
    "sg:phone":"+1 604 321 5553",
    "sg:postcode":"V5P 2R6",
    "sg:province":"BC",
    "sg:tags":[
        "equipment",
        "billiard",
        "supply"
    ],
    "wof:name":"Home Billiards Sales & Svc",
    "wof:placetype":"venue"
},
  "geometry": {"coordinates":[-123.07254,49.210823],"type":"Point"}
}