{
  "type": "Feature",
  "properties": {
    "addr:full":"Vancouver BC V6B 2T5",
    "addr:postcode":"v6b 2t5",
    "iso:country":"CA",
    "sg:city":"Vancouver",
    "sg:classifiers":[
        {
            "category":"Professional",
            "subcategory":"Advertising",
            "type":"Services"
        }
    ],
    "sg:phone":"+1 604 684 3170",
    "sg:postcode":"V6B 2T5",
    "sg:province":"BC",
    "sg:tags":[
        "counselor",
        "public",
        "relations"
    ],
    "wof:name":"Curve Communications",
    "wof:placetype":"venue"
},
  "geometry": {"coordinates":[-123.119164,49.276299],"type":"Point"}
}