{
  "type": "Feature",
  "properties": {
    "addr:full":"Slave River Slave Lake AB T0G 2A0",
    "addr:postcode":"t0g 2a0",
    "addr:street":"River",
    "iso:country":"CA",
    "sg:address":"Slave River",
    "sg:city":"Slave Lake",
    "sg:classifiers":[
        {
            "category":"Mining & Drilling",
            "type":"Manufacturing & Wholesale Goods"
        }
    ],
    "sg:phone":"+1 780 849 4873",
    "sg:postcode":"T0G 2A0",
    "sg:province":"AB",
    "sg:tags":[
        "field",
        "oil"
    ],
    "wof:name":"Dennis Bellerose Enterprises",
    "wof:placetype":"venue"
},
  "geometry": {"coordinates":[-114.771912,55.269184],"type":"Point"}
}