{
  "type": "Feature",
  "properties": {
    "addr:full":"Surrey BC V4P 3K1",
    "addr:postcode":"v4p 3k1",
    "iso:country":"CA",
    "sg:city":"Surrey",
    "sg:classifiers":[
        {
            "category":"Food & Beverages",
            "subcategory":"Bakery",
            "type":"Retail Goods"
        }
    ],
    "sg:phone":"+1 604 538 8198",
    "sg:postcode":"V4P 3K1",
    "sg:province":"BC",
    "sg:tags":[
        "doughnut"
    ],
    "wof:name":"Tim Hortons",
    "wof:placetype":"venue"
},
  "geometry": {"coordinates":[-122.801346,49.056923],"type":"Point"}
}