{
  "type": "Feature",
  "properties": {
    "addr:full":"1203 Broadview Ave East York ON M4K 2T1",
    "addr:housenumber":"1203",
    "addr:postcode":"m4k 2t1",
    "addr:street":"Broadview Ave",
    "iso:country":"CA",
    "sg:address":"1203 Broadview Ave",
    "sg:city":"East York",
    "sg:classifiers":[
        {
            "category":"Retail",
            "subcategory":"Auto Repair",
            "type":"Services"
        }
    ],
    "sg:phone":"+1 416 696 2277",
    "sg:postcode":"M4K 2T1",
    "sg:province":"ON",
    "sg:tags":[
        "repairing",
        "automobile"
    ],
    "wof:name":"Auto Trend",
    "wof:placetype":"venue"
},
  "geometry": {"coordinates":[-79.354675,43.689541],"type":"Point"}
}