{
  "type": "Feature",
  "properties": {
    "addr:full":"641 Sladen Ave Ottawa ON K1K 2S8",
    "addr:housenumber":"641",
    "addr:postcode":"k1k 2s8",
    "addr:street":"Sladen Ave",
    "iso:country":"CA",
    "sg:address":"641 Sladen Ave",
    "sg:city":"Ottawa",
    "sg:classifiers":[
        {
            "category":"Education",
            "subcategory":"School",
            "type":"Public Place"
        }
    ],
    "sg:phone":"+1 613 745 3310",
    "sg:postcode":"K1K 2S8",
    "sg:province":"ON",
    "wof:name":"Ecole Montfort",
    "wof:placetype":"venue"
},
  "geometry": {"coordinates":[-75.64347839360001,45.4401512146],"type":"Point"}
}