{
  "type": "Feature",
  "properties": {
    "iso:country":"CA",
    "sg:city":"Tobermory",
    "sg:classifiers":[
        {
            "category":"Retail",
            "subcategory":"Repair Shop",
            "type":"Services"
        }
    ],
    "sg:phone":"+1 519 596 2929",
    "sg:postcode":"N0H 2R0",
    "sg:province":"ON",
    "sg:tags":[
        "welding"
    ],
    "wof:name":"Tobercrafts",
    "wof:placetype":"venue"
},
  "geometry": {"coordinates":[-81.6650924683,45.2538261414],"type":"Point"}
}