{
  "type": "Feature",
  "properties": {
    "addr:full":"Lacolle QC J0J 1J0",
    "addr:postcode":"j0j 1j0",
    "iso:country":"CA",
    "sg:city":"Lacolle",
    "sg:classifiers":[
        {
            "category":"Manufacturing",
            "subcategory":"Printing",
            "type":"Manufacturing & Wholesale Goods"
        }
    ],
    "sg:phone":"+1 450 246 4696",
    "sg:postcode":"J0J 1J0",
    "sg:province":"QC",
    "sg:tags":[
        "bookbinder"
    ],
    "wof:name":"Francois Ouvrard Relieur",
    "wof:placetype":"venue"
},
  "geometry": {"coordinates":[-73.3679885864,45.0752792358],"type":"Point"}
}