{
  "type": "Feature",
  "properties": {
    "addr:full":"8495 Boul Decarie Mont-Royal QC H4P 2J2",
    "addr:housenumber":"8495",
    "addr:postcode":"h4p 2j2",
    "addr:street":"Boul Decarie",
    "iso:country":"CA",
    "sg:address":"8495 Boul Decarie",
    "sg:city":"Mont-Royal",
    "sg:classifiers":[
        {
            "category":"Home & Garden",
            "subcategory":"Furniture",
            "type":"Retail Goods"
        }
    ],
    "sg:phone":"+1 514 735 5957",
    "sg:postcode":"H4P 2J2",
    "sg:province":"QC",
    "wof:name":"Cashin",
    "wof:placetype":"venue"
},
  "geometry": {"coordinates":[-73.662941,45.501423],"type":"Point"}
}