{
  "type": "Feature",
  "properties": {
    "addr:full":"285 Geneva St # C1 St Catharines ON L2N 2G1",
    "addr:housenumber":"285",
    "addr:postcode":"l2n 2g1",
    "addr:street":"Geneva St # C1",
    "iso:country":"CA",
    "sg:address":"285 Geneva St # C1",
    "sg:city":"St Catharines",
    "sg:classifiers":[
        {
            "category":"Food & Beverages",
            "subcategory":"Specialty",
            "type":"Retail Goods"
        }
    ],
    "sg:phone":"+1 905 935 1872",
    "sg:postcode":"L2N 2G1",
    "sg:province":"ON",
    "sg:tags":[
        "health",
        "diet"
    ],
    "wof:name":"Nutrition House",
    "wof:placetype":"venue"
},
  "geometry": {"coordinates":[-79.2409896851,43.1771812439],"type":"Point"}
}