{
  "type": "Feature",
  "properties": {
    "addr:full":"2485 Day St Winnipeg MB R2C 2X5",
    "addr:housenumber":"2485",
    "addr:postcode":"r2c 2x5",
    "addr:street":"Day St",
    "iso:country":"CA",
    "sg:address":"2485 Day St",
    "sg:city":"Winnipeg",
    "sg:classifiers":[
        {
            "category":"Wholesale",
            "subcategory":"Construction Materials",
            "type":"Manufacturing & Wholesale Goods"
        }
    ],
    "sg:phone":"+1 204 222 3261",
    "sg:postcode":"R2C 2X5",
    "sg:province":"MB",
    "sg:tags":[
        "dock",
        "form",
        "concrete"
    ],
    "wof:name":"Plasti-Fab",
    "wof:placetype":"venue"
},
  "geometry": {"coordinates":[-97.00262499999999,49.914433],"type":"Point"}
}