{
  "type": "Feature",
  "properties": {
    "addr:full":"126 Rue Heriot Drummondville QC J2C 1J8",
    "addr:housenumber":"126",
    "addr:postcode":"j2c 1j8",
    "addr:street":"Rue Heriot",
    "iso:country":"CA",
    "sg:address":"126 Rue Heriot",
    "sg:city":"Drummondville",
    "sg:classifiers":[
        {
            "category":"Shopping",
            "type":"Retail Goods"
        }
    ],
    "sg:phone":"+1 819 472 1121",
    "sg:postcode":"J2C 1J8",
    "sg:province":"QC",
    "sg:tags":[
        "orthopedic",
        "appliance"
    ],
    "wof:name":"Centre Orthopedique Cloutier",
    "wof:placetype":"venue"
},
  "geometry": {"coordinates":[-72.4911727905,45.8866195679],"type":"Point"}
}