{
  "type": "Feature",
  "properties": {
    "iso:country":"CA",
    "sg:address":"2566 South Island Hwy",
    "sg:city":"Campbell River",
    "sg:classifiers":[
        {
            "category":"Retail",
            "subcategory":"Veterinary Services",
            "type":"Services"
        }
    ],
    "sg:phone":"+1 250 923 4292",
    "sg:postcode":"V9W 1C6",
    "sg:province":"BC",
    "sg:tags":[
        "veterinarian"
    ],
    "wof:name":"Campbell River Veterinary Hosp",
    "wof:placetype":"venue"
},
  "geometry": {"coordinates":[-125.209274292,49.9671096802],"type":"Point"}
}