{
  "type": "Feature",
  "properties": {
    "addr:full":"King City ON L7B 1L3",
    "addr:postcode":"l7b 1l3",
    "iso:country":"CA",
    "sg:city":"King City",
    "sg:classifiers":[
        {
            "category":"Building & Trades",
            "subcategory":"Construction",
            "type":"Services"
        }
    ],
    "sg:phone":"+1 905 833 0681",
    "sg:postcode":"L7B 1L3",
    "sg:province":"ON",
    "sg:tags":[
        "contractor",
        "general"
    ],
    "wof:name":"J D Strachan Construction",
    "wof:placetype":"venue"
},
  "geometry": {"coordinates":[-79.52662658689999,43.9291877747],"type":"Point"}
}