{
  "type": "Feature",
  "properties": {
    "iso:country":"CA",
    "sg:city":"Vaudreuil-Dorion",
    "sg:classifiers":[
        {
            "category":"Professional",
            "subcategory":"Accounting & Tax Preparation",
            "type":"Services"
        }
    ],
    "sg:phone":"+1 450 424 5511",
    "sg:postcode":"J7V 1X9",
    "sg:province":"QC",
    "sg:tags":[
        "accountant"
    ],
    "wof:name":"Gestion Taxco Inc",
    "wof:placetype":"venue"
},
  "geometry": {"coordinates":[-74.0095367432,45.3840827942],"type":"Point"}
}