{
  "type": "Feature",
  "properties": {
    "addr:full":"1530 Rue D'Acton Acton Vale QC J0H 1A0",
    "addr:housenumber":"1530",
    "addr:postcode":"j0h 1a0",
    "addr:street":"Rue D'Acton",
    "iso:country":"CA",
    "sg:address":"1530 Rue D'Acton",
    "sg:city":"Acton Vale",
    "sg:classifiers":[
        {
            "category":"Food & Beverages",
            "subcategory":"Groceries & Convenience Stores",
            "type":"Retail Goods"
        }
    ],
    "sg:phone":"+1 450 546 7733",
    "sg:postcode":"J0H 1A0",
    "sg:province":"QC",
    "sg:tags":[
        "grocer"
    ],
    "wof:name":"Provigo",
    "wof:placetype":"venue"
},
  "geometry": {"coordinates":[-72.56585699999999,45.646996],"type":"Point"}
}