{
  "type": "Feature",
  "properties": {
    "addr:full":"29 Skyridge Ave Lower Sackville NS B4C 1P8",
    "addr:housenumber":"29",
    "addr:postcode":"b4c 1p8",
    "addr:street":"Skyridge Ave",
    "iso:country":"CA",
    "sg:address":"29 Skyridge Ave",
    "sg:city":"Lower Sackville",
    "sg:classifiers":[
        {
            "category":"Retail",
            "subcategory":"Auto Repair",
            "type":"Services"
        }
    ],
    "sg:phone":"+1 902 865 4575",
    "sg:postcode":"B4C 1P8",
    "sg:province":"NS",
    "sg:tags":[
        "wrecker"
    ],
    "wof:name":"A-1 Towing & Recovery Ltd",
    "wof:placetype":"venue"
},
  "geometry": {"coordinates":[-63.671486,44.761555],"type":"Point"}
}