{
  "type": "Feature",
  "properties": {
    "addr:full":"Pickering ON L1W 3X8",
    "addr:postcode":"l1w 3x8",
    "iso:country":"CA",
    "sg:city":"Pickering",
    "sg:classifiers":[
        {
            "category":"Manufacturing",
            "subcategory":"Tools & Machinery",
            "type":"Manufacturing & Wholesale Goods"
        }
    ],
    "sg:phone":"+1 905 683 5298",
    "sg:postcode":"L1W 3X8",
    "sg:province":"ON",
    "sg:tags":[
        "pattern",
        "maker"
    ],
    "wof:name":"Metro Pattern & Model Ltd",
    "wof:placetype":"venue"
},
  "geometry": {"coordinates":[-79.04997253419999,43.8219070435],"type":"Point"}
}