{
  "type": "Feature",
  "properties": {
    "addr:full":"50 Rue Saint-Joseph Baie-Saint-Paul QC G3Z 1H7",
    "addr:housenumber":"50",
    "addr:postcode":"g3z 1h7",
    "addr:street":"Rue Saint-Joseph",
    "iso:country":"CA",
    "sg:address":"50 Rue Saint-Joseph",
    "sg:city":"Baie-Saint-Paul",
    "sg:classifiers":[
        {
            "category":"Travel",
            "subcategory":"Hotels & Motels",
            "type":"Entertainment"
        }
    ],
    "sg:phone":"+1 418 435 3393",
    "sg:postcode":"G3Z 1H7",
    "sg:province":"QC",
    "sg:tags":[
        "breakfast",
        "accommodation",
        "bed"
    ],
    "wof:name":"Au Clocheton",
    "wof:placetype":"venue"
},
  "geometry": {"coordinates":[-70.495605,47.442471],"type":"Point"}
}