{
  "type": "Feature",
  "properties": {
    "iso:country":"CA",
    "sg:address":"5027 Still Creek Ave",
    "sg:city":"Burnaby",
    "sg:classifiers":[
        {
            "category":"Manufacturing",
            "subcategory":"Metals",
            "type":"Manufacturing & Wholesale Goods"
        }
    ],
    "sg:phone":"+1 604 294 9473",
    "sg:postcode":"V5C 5V1",
    "sg:province":"BC",
    "sg:tags":[
        "cable"
    ],
    "wof:name":"Allied Wire & Cable Ltd",
    "wof:placetype":"venue"
},
  "geometry": {"coordinates":[-122.990837,49.260986],"type":"Point"}
}