{
  "type": "Feature",
  "properties": {
    "iso:country":"CA",
    "sg:city":"Aurora",
    "sg:classifiers":[
        {
            "category":"Health Services",
            "subcategory":"Optometrist",
            "type":"Services"
        }
    ],
    "sg:phone":"+1 905 727 0139",
    "sg:postcode":"L4G 1M5",
    "sg:province":"ON",
    "wof:name":"Postiglione, Sonia OD",
    "wof:placetype":"venue"
},
  "geometry": {"coordinates":[-79.46593475340001,43.9936637878],"type":"Point"}
}