{
  "type": "Feature",
  "properties": {
    "addr:full":"5020 52nd Ave Two Hills AB T0B 4K0",
    "addr:housenumber":"5020",
    "addr:postcode":"t0b 4k0",
    "addr:street":"52Nd Ave",
    "iso:country":"CA",
    "sg:address":"5020 52nd Ave",
    "sg:city":"Two Hills",
    "sg:classifiers":[
        {
            "category":"Restaurant",
            "type":"Food & Drink"
        }
    ],
    "sg:phone":"+1 780 657 2848",
    "sg:postcode":"T0B 4K0",
    "sg:province":"AB",
    "wof:name":"G O's Drive-In",
    "wof:placetype":"venue"
},
  "geometry": {"coordinates":[-111.744286,53.712528],"type":"Point"}
}