{
  "type": "Feature",
  "properties": {
    "addr:full":"Toronto ON M5S 2R4",
    "addr:postcode":"m5s 2r4",
    "iso:country":"CA",
    "sg:city":"Toronto",
    "sg:classifiers":[
        {
            "category":"Manufacturing",
            "subcategory":"Printing",
            "type":"Manufacturing & Wholesale Goods"
        }
    ],
    "sg:phone":"+1 416 535 9914",
    "sg:postcode":"M5S 2R4",
    "sg:province":"ON",
    "sg:tags":[
        "publisher"
    ],
    "wof:name":"Between the Lines Publishing",
    "wof:placetype":"venue"
},
  "geometry": {"coordinates":[-79.41063690190001,43.6632385254],"type":"Point"}
}