{
  "type": "Feature",
  "properties": {
    "addr:full":"1675 Commercial Dr Vancouver BC V5L 3Y3",
    "addr:housenumber":"1675",
    "addr:postcode":"v5l 3y3",
    "addr:street":"Commercial Dr",
    "iso:country":"CA",
    "sg:address":"1675 Commercial Dr",
    "sg:city":"Vancouver",
    "sg:classifiers":[
        {
            "category":"Banks & Credit Unions",
            "subcategory":"Bank",
            "type":"Services"
        }
    ],
    "sg:phone":"+1 604 877 7000",
    "sg:postcode":"V5L 3Y3",
    "sg:province":"BC",
    "wof:name":"Van City Savings Credit Union",
    "wof:placetype":"venue"
},
  "geometry": {"coordinates":[-123.069901,49.269859],"type":"Point"}
}