{
  "type": "Feature",
  "properties": {
    "iso:country":"CA",
    "sg:address":"1779 White Cedar Dr",
    "sg:city":"Pickering",
    "sg:classifiers":[
        {
            "category":"Building & Trades",
            "subcategory":"Electrical",
            "type":"Services"
        }
    ],
    "sg:phone":"+1 416 410 5403",
    "sg:postcode":"L1V 6Z1",
    "sg:province":"ON",
    "sg:tags":[
        "electric",
        "contractor"
    ],
    "wof:name":"Cornerstone Electric Ltd",
    "wof:placetype":"venue"
},
  "geometry": {"coordinates":[-79.1306762695,43.8239059448],"type":"Point"}
}