{
  "type": "Feature",
  "properties": {
    "addr:full":"Calgary AB T3E 6W4",
    "addr:postcode":"t3e 6w4",
    "iso:country":"CA",
    "sg:city":"Calgary",
    "sg:classifiers":[
        {
            "category":"Health Services",
            "subcategory":"Doctor",
            "type":"Services"
        }
    ],
    "sg:phone":"+1 403 571 3157",
    "sg:postcode":"T3E 6W4",
    "sg:province":"AB",
    "sg:tags":[
        "physician",
        "surgeon"
    ],
    "wof:name":"Harrop, A R MD",
    "wof:placetype":"venue"
},
  "geometry": {"coordinates":[-114.161308289,51.0218238831],"type":"Point"}
}