{
  "type": "Feature",
  "properties": {
    "addr:full":"Deep River ON K0J 1P0",
    "addr:postcode":"k0j 1p0",
    "iso:country":"CA",
    "sg:city":"Deep River",
    "sg:classifiers":[
        {
            "category":"Shopping",
            "subcategory":"Clothing, Apparel, & Fashions",
            "type":"Retail Goods"
        }
    ],
    "sg:phone":"+1 613 584 1144",
    "sg:postcode":"K0J 1P0",
    "sg:province":"ON",
    "wof:name":"Deep in Fashion",
    "wof:placetype":"venue"
},
  "geometry": {"coordinates":[-77.48839569090001,46.1015205383],"type":"Point"}
}