{
  "type": "Feature",
  "properties": {
    "addr:full":"11333 101 St NW Edmonton AB T5G 2A6",
    "addr:housenumber":"11333",
    "addr:postcode":"t5g 2a6",
    "addr:street":"101 St Nw",
    "iso:country":"CA",
    "sg:address":"11333 101 St NW",
    "sg:city":"Edmonton",
    "sg:classifiers":[
        {
            "category":"Building & Trades",
            "subcategory":"Construction",
            "type":"Services"
        }
    ],
    "sg:phone":"+1 780 471 6887",
    "sg:postcode":"T5G 2A6",
    "sg:province":"AB",
    "sg:tags":[
        "painter"
    ],
    "wof:name":"Marcel Darmanin Painting",
    "wof:placetype":"venue"
},
  "geometry": {"coordinates":[-113.493576,53.563255],"type":"Point"}
}