{
  "type": "Feature",
  "properties": {
    "addr:full":"175 Catharine St Port Colborne ON L3K 4K7",
    "addr:housenumber":"175",
    "addr:postcode":"l3k 4k7",
    "addr:street":"Catharine St",
    "iso:country":"CA",
    "sg:address":"175 Catharine St",
    "sg:city":"Port Colborne",
    "sg:classifiers":[
        {
            "category":"Shopping",
            "subcategory":"Stationery & Office Supplies",
            "type":"Retail Goods"
        }
    ],
    "sg:phone":"+1 905 834 4114",
    "sg:postcode":"L3K 4K7",
    "sg:province":"ON",
    "sg:tags":[
        "rubber",
        "stamp",
        "plastic"
    ],
    "wof:name":"Super Service Rubber Stamp",
    "wof:placetype":"venue"
},
  "geometry": {"coordinates":[-79.25245700000001,42.884201],"type":"Point"}
}