{
  "type": "Feature",
  "properties": {
    "addr:full":"1296 Robson St Vancouver BC V6E 1C1",
    "addr:housenumber":"1296",
    "addr:postcode":"v6e 1c1",
    "addr:street":"Robson St",
    "iso:country":"CA",
    "sg:address":"1296 Robson St",
    "sg:city":"Vancouver",
    "sg:classifiers":[
        {
            "category":"Food & Beverages",
            "subcategory":"Groceries & Convenience Stores",
            "type":"Retail Goods"
        }
    ],
    "sg:phone":"+1 604 688 6053",
    "sg:postcode":"V6E 1C1",
    "sg:province":"BC",
    "sg:tags":[
        "grocer"
    ],
    "wof:name":"B C Cherry Market",
    "wof:placetype":"venue"
},
  "geometry": {"coordinates":[-123.128502,49.286819],"type":"Point"}
}