{
  "type": "Feature",
  "properties": {
    "addr:full":"209 1st Ave W Shellbrook SK S0J 2E0",
    "addr:housenumber":"209",
    "addr:postcode":"s0j 2e0",
    "addr:street":"1St Ave W Shellbrook",
    "iso:country":"CA",
    "sg:address":"209 1st Ave W",
    "sg:city":"Shellbrook",
    "sg:classifiers":[
        {
            "category":"Retail",
            "subcategory":"Repair Shop",
            "type":"Services"
        }
    ],
    "sg:phone":"+1 306 747 2346",
    "sg:postcode":"S0J 2E0",
    "sg:province":"SK",
    "sg:tags":[
        "equipment",
        "video"
    ],
    "wof:name":"Aurel's Vcr & Tv Repair",
    "wof:placetype":"venue"
},
  "geometry": {"coordinates":[-106.39232635499999,53.2194633484],"type":"Point"}
}