{
  "type": "Feature",
  "properties": {
    "addr:full":"21 Lakeshore Rd D'Arcy BC V0N 1L0",
    "addr:housenumber":"21",
    "addr:postcode":"v0n 1l0",
    "addr:street":"Lakeshore Rd",
    "iso:country":"CA",
    "sg:address":"21 Lakeshore Rd",
    "sg:city":"D'Arcy",
    "sg:classifiers":[
        {
            "category":"Organizations",
            "subcategory":"Professional Association",
            "type":"Services"
        }
    ],
    "sg:phone":"+1 604 452 3221",
    "sg:postcode":"V0N 1L0",
    "sg:province":"BC",
    "wof:name":"N'Quatqua Band",
    "wof:placetype":"venue"
},
  "geometry": {"coordinates":[-122.502533,50.521122],"type":"Point"}
}