{
  "type": "Feature",
  "properties": {
    "addr:full":"935 Rue Saint-Michel Terrebonne QC J6W 3Y7",
    "addr:housenumber":"935",
    "addr:postcode":"j6w 3y7",
    "addr:street":"Rue Saint-Michel",
    "iso:country":"CA",
    "sg:address":"935 Rue Saint-Michel",
    "sg:city":"Terrebonne",
    "sg:classifiers":[
        {
            "category":"Professional",
            "subcategory":"Business Services",
            "type":"Services"
        }
    ],
    "sg:phone":"+1 450 471 9748",
    "sg:postcode":"J6W 3Y7",
    "sg:province":"QC",
    "sg:tags":[
        "consultant",
        "design",
        "decorator",
        "interior",
        "curtain",
        "drapery"
    ],
    "wof:name":"Draperies D Lemieux",
    "wof:placetype":"venue"
},
  "geometry": {"coordinates":[-73.64372299999999,45.70052],"type":"Point"}
}