{
  "type": "Feature",
  "properties": {
    "addr:full":"9809 100 St Morinville AB T8R 1R3",
    "addr:housenumber":"9809",
    "addr:postcode":"t8r 1r3",
    "addr:street":"100 St",
    "iso:country":"CA",
    "sg:address":"9809 100 St",
    "sg:city":"Morinville",
    "sg:classifiers":[
        {
            "category":"Retail",
            "subcategory":"Laundry & Dry Cleaning",
            "type":"Services"
        }
    ],
    "sg:phone":"+1 780 939 5776",
    "sg:postcode":"T8R 1R3",
    "sg:province":"AB",
    "sg:tags":[
        "cleaners"
    ],
    "wof:name":"Morinville Cleanitizing Ltd",
    "wof:placetype":"venue"
},
  "geometry": {"coordinates":[-113.64463000000001,53.799004],"type":"Point"}
}