{
  "type": "Feature",
  "properties": {
    "addr:full":"Sherwood Park AB T8A 3H9",
    "addr:postcode":"t8a 3h9",
    "iso:country":"CA",
    "sg:city":"Sherwood Park",
    "sg:classifiers":[
        {
            "category":"Shopping",
            "subcategory":"Jewelry",
            "type":"Retail Goods"
        }
    ],
    "sg:phone":"+1 780 467 3740",
    "sg:postcode":"T8A 3H9",
    "sg:province":"AB",
    "sg:tags":[
        "jeweler"
    ],
    "wof:name":"Peoples Jewellers",
    "wof:placetype":"venue"
},
  "geometry": {"coordinates":[-113.295418,53.529671],"type":"Point"}
}