{
  "type": "Feature",
  "properties": {
    "addr:full":"94 Chestnut Hills Pky Etobicoke ON M9A 3R3",
    "addr:housenumber":"94",
    "addr:postcode":"m9a 3r3",
    "addr:street":"Chestnut Hills Pky",
    "iso:country":"CA",
    "sg:address":"94 Chestnut Hills Pky",
    "sg:city":"Etobicoke",
    "sg:classifiers":[
        {
            "category":"Professional",
            "subcategory":"Employment Agencies",
            "type":"Services"
        }
    ],
    "sg:phone":"+1 416 239 9966",
    "sg:postcode":"M9A 3R3",
    "sg:province":"ON",
    "sg:tags":[
        "opportunity"
    ],
    "wof:name":"Solution Partners Inc",
    "wof:placetype":"venue"
},
  "geometry": {"coordinates":[-79.525925,43.659317],"type":"Point"}
}