{
  "type": "Feature",
  "properties": {
    "addr:full":"943 Stisted St Burks Falls ON P0A 1C0",
    "addr:housenumber":"943",
    "addr:postcode":"p0a 1c0",
    "addr:street":"Stisted St",
    "iso:country":"CA",
    "sg:address":"943 Stisted St",
    "sg:city":"Burks Falls",
    "sg:classifiers":[
        {
            "category":"Wholesale",
            "subcategory":"Machinery & Supplies",
            "type":"Manufacturing & Wholesale Goods"
        }
    ],
    "sg:phone":"+1 705 685 7449",
    "sg:postcode":"P0A 1C0",
    "sg:province":"ON",
    "sg:tags":[
        "pump"
    ],
    "wof:name":"Marshall Pump",
    "wof:placetype":"venue"
},
  "geometry": {"coordinates":[-79.44426727290001,45.5284118652],"type":"Point"}
}