{
  "type": "Feature",
  "properties": {
    "addr:full":"120 Laird Dr East York ON M4G 3V3",
    "addr:housenumber":"120",
    "addr:postcode":"m4g 3v3",
    "addr:street":"Laird Dr",
    "iso:country":"CA",
    "sg:address":"120 Laird Dr",
    "sg:city":"East York",
    "sg:classifiers":[
        {
            "category":"Restaurant",
            "type":"Food & Drink"
        }
    ],
    "sg:phone":"+1 416 421 8228",
    "sg:postcode":"M4G 3V3",
    "sg:province":"ON",
    "wof:name":"Marvellous Edibles Leaside",
    "wof:placetype":"venue"
},
  "geometry": {"coordinates":[-79.3623352051,43.706943512],"type":"Point"}
}