{
  "type": "Feature",
  "properties": {
    "addr:full":"9716 17 St Dawson Creek BC V1G 4B3",
    "addr:housenumber":"9716",
    "addr:postcode":"v1g 4b3",
    "addr:street":"17 St",
    "iso:country":"CA",
    "sg:address":"9716 17 St",
    "sg:city":"Dawson Creek",
    "sg:classifiers":[
        {
            "category":"Wholesale",
            "subcategory":"Machinery & Supplies",
            "type":"Manufacturing & Wholesale Goods"
        }
    ],
    "sg:phone":"+1 250 782 1534",
    "sg:postcode":"V1G 4B3",
    "sg:province":"BC",
    "sg:tags":[
        "field",
        "oil"
    ],
    "wof:name":"Baron Oil Field Supply Ltd",
    "wof:placetype":"venue"
},
  "geometry": {"coordinates":[-120.25038146999999,55.7648696899],"type":"Point"}
}