{
  "type": "Feature",
  "properties": {
    "iso:country":"CA",
    "sg:city":"Crabtree",
    "sg:classifiers":[
        {
            "category":"Health Services",
            "subcategory":"Health Practitioner",
            "type":"Services"
        }
    ],
    "sg:phone":"+1 450 754 4270",
    "sg:postcode":"J0K 1B0",
    "sg:province":"QC",
    "sg:tags":[
        "acupuncture",
        "therapist",
        "massage"
    ],
    "wof:name":"Acupuncture & Shiatsu Jackson",
    "wof:placetype":"venue"
},
  "geometry": {"coordinates":[-73.47328186039999,45.9612731934],"type":"Point"}
}