{
  "type": "Feature",
  "properties": {
    "addr:full":"PO Box 47 Plum Point NL A0K 4A0",
    "addr:housenumber":"po box 47",
    "addr:postcode":"a0k 4a0",
    "addr:street":"Plum Point",
    "iso:country":"CA",
    "sg:address":"PO Box 47",
    "sg:city":"Plum Point",
    "sg:classifiers":[
        {
            "category":"Building & Trades",
            "subcategory":"Construction",
            "type":"Services"
        }
    ],
    "sg:phone":"+1 709 247 2085",
    "sg:postcode":"A0K 4A0",
    "sg:province":"NL",
    "sg:tags":[
        "road",
        "contractor"
    ],
    "wof:name":"Abe Gibbons & Sons Ltd",
    "wof:placetype":"venue"
},
  "geometry": {"coordinates":[-56.8771934509,51.0777702332],"type":"Point"}
}