{
  "type": "Feature",
  "properties": {
    "addr:full":"1380 Kivinen Rd Sudbury ON P3G 1H5",
    "addr:housenumber":"1380",
    "addr:postcode":"p3g 1h5",
    "addr:street":"Kivinen Rd",
    "iso:country":"CA",
    "sg:address":"1380 Kivinen Rd",
    "sg:city":"Sudbury",
    "sg:classifiers":[
        {
            "category":"Building & Trades",
            "subcategory":"Construction",
            "type":"Services"
        }
    ],
    "sg:phone":"+1 705 522 9989",
    "sg:postcode":"P3G 1H5",
    "sg:province":"ON",
    "sg:tags":[
        "resurfacing",
        "laying",
        "refinishing",
        "floor"
    ],
    "wof:name":"Tri Star Floor Sanders",
    "wof:placetype":"venue"
},
  "geometry": {"coordinates":[-81.039146,46.420017],"type":"Point"}
}