{
  "type": "Feature",
  "properties": {
    "addr:full":"10 Hamilton Rd Barrie ON L4N 8Y5",
    "addr:housenumber":"10",
    "addr:postcode":"l4n 8y5",
    "addr:street":"Hamilton Rd",
    "iso:country":"CA",
    "sg:address":"10 Hamilton Rd",
    "sg:city":"Barrie",
    "sg:classifiers":[
        {
            "category":"Manufacturing",
            "subcategory":"Signs",
            "type":"Manufacturing & Wholesale Goods"
        }
    ],
    "sg:phone":"+1 705 722 0006",
    "sg:postcode":"L4N 8Y5",
    "sg:province":"ON",
    "wof:name":"Trillium Signs & Designs",
    "wof:placetype":"venue"
},
  "geometry": {"coordinates":[-79.672951,44.357224],"type":"Point"}
}