{
  "type": "Feature",
  "properties": {
    "addr:full":"2 Hunter's Point Dr # 10 Richmond Hill ON L4C 9Y4",
    "addr:housenumber":"2;10",
    "addr:postcode":"l4c 9y4",
    "addr:street":"Hunter'S Point Dr #",
    "iso:country":"CA",
    "sg:address":"2 Hunter's Point Dr # 10",
    "sg:city":"Richmond Hill",
    "sg:classifiers":[
        {
            "category":"Retail",
            "subcategory":"Veterinary Services",
            "type":"Services"
        }
    ],
    "sg:phone":"+1 905 764 1144",
    "sg:postcode":"L4C 9Y4",
    "sg:province":"ON",
    "sg:tags":[
        "veterinarian"
    ],
    "wof:name":"Bell, Peter DVM",
    "wof:placetype":"venue"
},
  "geometry": {"coordinates":[-79.378479,43.84655],"type":"Point"}
}