{
  "type": "Feature",
  "properties": {
    "addr:full":"771 Golf Links Rd Ancaster ON L9K 1L5",
    "addr:housenumber":"771",
    "addr:postcode":"l9k 1l5",
    "addr:street":"Golf Links Rd",
    "iso:country":"CA",
    "sg:address":"771 Golf Links Rd",
    "sg:city":"Ancaster",
    "sg:classifiers":[
        {
            "category":"Restaurant",
            "type":"Food & Drink"
        }
    ],
    "sg:phone":"+1 905 304 4980",
    "sg:postcode":"L9K 1L5",
    "sg:province":"ON",
    "wof:name":"Montana's Cookhouse Saloon",
    "wof:placetype":"venue"
},
  "geometry": {"coordinates":[-79.95343800000001,43.225639],"type":"Point"}
}