{
  "type": "Feature",
  "properties": {
    "addr:full":"283 Boul Gagne Sorel-Tracy QC J3P 5Z9",
    "addr:housenumber":"283",
    "addr:postcode":"j3p 5z9",
    "addr:street":"Boul Gagne",
    "iso:country":"CA",
    "sg:address":"283 Boul Gagne",
    "sg:city":"Sorel-Tracy",
    "sg:classifiers":[
        {
            "category":"Professional",
            "subcategory":"Business Services",
            "type":"Services"
        }
    ],
    "sg:phone":"+1 450 742 0497",
    "sg:postcode":"J3P 5Z9",
    "sg:province":"QC",
    "sg:tags":[
        "notary"
    ],
    "wof:name":"Stephan Rousseau L'Heureux",
    "wof:placetype":"venue"
},
  "geometry": {"coordinates":[-73.12117004389999,46.0214691162],"type":"Point"}
}