{
  "type": "Feature",
  "properties": {
    "iso:country":"CA",
    "sg:address":"1842 3E Av",
    "sg:city":"Val-D'Or",
    "sg:classifiers":[
        {
            "category":"Manufacturing",
            "subcategory":"Lumber",
            "type":"Manufacturing & Wholesale Goods"
        }
    ],
    "sg:phone":"+1 819 874 1265",
    "sg:postcode":"J9P 7A9",
    "sg:province":"QC",
    "sg:tags":[
        "forester"
    ],
    "wof:name":"Services Forestiers Matagami",
    "wof:placetype":"venue"
},
  "geometry": {"coordinates":[-68.42929077150001,53.89012146],"type":"Point"}
}