{
  "type": "Feature",
  "properties": {
    "iso:country":"CA",
    "sg:address":"1770 Boul Vezina",
    "sg:city":"Dolbeau-Mistassini",
    "sg:classifiers":[
        {
            "category":"Local Transit",
            "type":"Transportation"
        }
    ],
    "sg:phone":"+1 418 239 0042",
    "sg:postcode":"G8L 3M5",
    "sg:province":"QC",
    "sg:tags":[
        "bus",
        "line"
    ],
    "wof:name":"Transport Leo Cadoret",
    "wof:placetype":"venue"
},
  "geometry": {"coordinates":[-72.2420043945,48.8783874512],"type":"Point"}
}