{
  "type": "Feature",
  "properties": {
    "addr:full":"1122 Saskatchewan Dr Regina SK S4P 0C4",
    "addr:housenumber":"1122",
    "addr:postcode":"s4p 0c4",
    "addr:street":"Saskatchewan Dr",
    "iso:country":"CA",
    "sg:address":"1122 Saskatchewan Dr",
    "sg:city":"Regina",
    "sg:classifiers":[
        {
            "category":"Organizations",
            "subcategory":"Political Organization",
            "type":"Services"
        }
    ],
    "sg:phone":"+1 306 525 1322",
    "sg:postcode":"S4P 0C4",
    "sg:province":"SK",
    "wof:name":"New Democratic Party of Sask",
    "wof:placetype":"venue"
},
  "geometry": {"coordinates":[-104.596695,50.452091],"type":"Point"}
}