{
  "type": "Feature",
  "properties": {
    "addr:full":"Calgary AB T2E 3Z7",
    "addr:postcode":"t2e 3z7",
    "iso:country":"CA",
    "sg:city":"Calgary",
    "sg:classifiers":[
        {
            "category":"Manufacturing",
            "subcategory":"Metals",
            "type":"Manufacturing & Wholesale Goods"
        }
    ],
    "sg:phone":"+1 403 277 5010",
    "sg:postcode":"T2E 3Z7",
    "sg:province":"AB",
    "sg:tags":[
        "fabricator",
        "sheet"
    ],
    "wof:name":"Cal-Garry's Sheet Metal Ltd",
    "wof:placetype":"venue"
},
  "geometry": {"coordinates":[-114.047904968,51.0919380188],"type":"Point"}
}