{
  "type": "Feature",
  "properties": {
    "addr:full":"745 South Pelham Rd Welland ON L3C 3C9",
    "addr:housenumber":"745",
    "addr:postcode":"l3c 3c9",
    "addr:street":"South Pelham Rd",
    "iso:country":"CA",
    "sg:address":"745 South Pelham Rd",
    "sg:city":"Welland",
    "sg:classifiers":[
        {
            "category":"Building & Trades",
            "subcategory":"Construction",
            "type":"Services"
        }
    ],
    "sg:phone":"+1 905 735 0848",
    "sg:postcode":"L3C 3C9",
    "sg:province":"ON",
    "sg:tags":[
        "contractor",
        "trucking"
    ],
    "wof:name":"Policella Homes",
    "wof:placetype":"venue"
},
  "geometry": {"coordinates":[-79.285477,43.010197],"type":"Point"}
}