{
  "type": "Feature",
  "properties": {
    "addr:full":"7969 Wallace Dr Saanichton BC V8M 1L4",
    "addr:housenumber":"7969",
    "addr:postcode":"v8m 1l4",
    "addr:street":"Wallace Dr",
    "iso:country":"CA",
    "sg:address":"7969 Wallace Dr",
    "sg:city":"Saanichton",
    "sg:classifiers":[
        {
            "category":"Building & Trades",
            "subcategory":"Construction",
            "type":"Services"
        }
    ],
    "sg:phone":"+1 250 652 2309",
    "sg:postcode":"V8M 1L4",
    "sg:province":"BC",
    "sg:tags":[
        "excavating",
        "contractor"
    ],
    "wof:name":"Bickford Enterprises Ltd",
    "wof:placetype":"venue"
},
  "geometry": {"coordinates":[-123.41480300000001,48.598358],"type":"Point"}
}