{
  "type": "Feature",
  "properties": {
    "addr:full":"820 Ch DE LA Grande Riviere S Yamachiche QC G0X 3L0",
    "addr:housenumber":"820",
    "addr:postcode":"g0x 3l0",
    "addr:street":"Ch De La Grande Riviere S",
    "iso:country":"CA",
    "sg:address":"820 Ch DE LA Grande Riviere S",
    "sg:city":"Yamachiche",
    "sg:classifiers":[
        {
            "category":"Building & Trades",
            "subcategory":"Plumbing",
            "type":"Services"
        }
    ],
    "sg:phone":"+1 819 296 1299",
    "sg:postcode":"G0X 3L0",
    "sg:province":"QC",
    "sg:tags":[
        "contractor"
    ],
    "wof:name":"Plomberie Mario Lavaute",
    "wof:placetype":"venue"
},
  "geometry": {"coordinates":[-72.7966766357,46.318321228],"type":"Point"}
}