{
  "type": "Feature",
  "properties": {
    "addr:full":"Salaberry-DE-Valleyfield QC J6T 6G4",
    "addr:postcode":"j6t 6g4",
    "iso:country":"CA",
    "sg:city":"Salaberry-DE-Valleyfield",
    "sg:classifiers":[
        {
            "category":"Building & Trades",
            "subcategory":"Construction",
            "type":"Services"
        }
    ],
    "sg:phone":"+1 450 373 2010",
    "sg:postcode":"J6T 6G4",
    "sg:province":"QC",
    "sg:tags":[
        "excavating",
        "paving",
        "contractor"
    ],
    "wof:name":"Ali Excavation Inc",
    "wof:placetype":"venue"
},
  "geometry": {"coordinates":[-74.08754,45.234661],"type":"Point"}
}