{
  "type": "Feature",
  "properties": {
    "addr:full":"PO Box 179 Port-Menier QC G0G 2Y0",
    "addr:housenumber":"po",
    "addr:postcode":"g0g 2y0",
    "addr:street":"Box 179 Port-Menier",
    "iso:country":"CA",
    "sg:address":"PO Box 179",
    "sg:city":"Port-Menier",
    "sg:classifiers":[
        {
            "category":"Government",
            "subcategory":"Office",
            "type":"Public Place"
        }
    ],
    "sg:phone":"+1 418 535 0156",
    "sg:postcode":"G0G 2Y0",
    "sg:province":"QC",
    "wof:name":"Quebec Sepaq",
    "wof:placetype":"venue"
},
  "geometry": {"coordinates":[-64.368454,49.826405],"type":"Point"}
}