{
  "type": "Feature",
  "properties": {
    "iso:country":"CA",
    "sg:city":"Waterloo",
    "sg:classifiers":[
        {
            "category":"Manufacturing",
            "subcategory":"Rubber & Plastics",
            "type":"Manufacturing & Wholesale Goods"
        }
    ],
    "sg:phone":"+1 519 747 0559",
    "sg:postcode":"N2V 2A9",
    "sg:province":"ON",
    "sg:tags":[
        "mold",
        "maker"
    ],
    "wof:name":"Polyman Plastics CO",
    "wof:placetype":"venue"
},
  "geometry": {"coordinates":[-80.53825378419999,43.5078201294],"type":"Point"}
}