{
  "type": "Feature",
  "properties": {
    "addr:full":"563 Fort Island Rd Norway House MB R0B 1B0",
    "addr:housenumber":"563",
    "addr:postcode":"r0b 1b0",
    "addr:street":"Fort Island Rd",
    "iso:country":"CA",
    "sg:address":"563 Fort Island Rd",
    "sg:city":"Norway House",
    "sg:classifiers":[
        {
            "category":"Restaurant",
            "type":"Food & Drink"
        }
    ],
    "sg:phone":"+1 204 359 6646",
    "sg:postcode":"R0B 1B0",
    "sg:province":"MB",
    "wof:name":"Chicken Chef",
    "wof:placetype":"venue"
},
  "geometry": {"coordinates":[-97.76863098139999,53.9951553345],"type":"Point"}
}