{
  "type": "Feature",
  "properties": {
    "iso:country":"CA",
    "sg:address":"5105 48 St",
    "sg:city":"Stony Plain",
    "sg:classifiers":[
        {
            "category":"Health Services",
            "subcategory":"Chiropractor",
            "type":"Services"
        }
    ],
    "sg:phone":"+1 780 963 3466",
    "sg:postcode":"T7Z 1X6",
    "sg:province":"AB",
    "wof:name":"Shiloh Chiropractic Clinic",
    "wof:placetype":"venue"
},
  "geometry": {"coordinates":[-114.00173950200001,53.5288887024],"type":"Point"}
}