{
  "type": "Feature",
  "properties": {
    "addr:full":"Richmond BC V6X 3Z6",
    "addr:postcode":"v6x 3z6",
    "iso:country":"CA",
    "sg:city":"Richmond",
    "sg:classifiers":[
        {
            "category":"Wholesale",
            "subcategory":"Non-durable Goods",
            "type":"Manufacturing & Wholesale Goods"
        }
    ],
    "sg:phone":"+1 604 273 7206",
    "sg:postcode":"V6X 3Z6",
    "sg:province":"BC",
    "sg:tags":[
        "bag",
        "canvas",
        "cotton"
    ],
    "wof:name":"Barvivian Bags & Sports Wear",
    "wof:placetype":"venue"
},
  "geometry": {"coordinates":[-123.103088379,49.1777992249],"type":"Point"}
}