{
  "type": "Feature",
  "properties": {
    "addr:full":"6873 Morrison St Niagara Falls ON L2E 2G5",
    "addr:housenumber":"6873",
    "addr:postcode":"l2e 2g5",
    "addr:street":"Morrison St",
    "iso:country":"CA",
    "sg:address":"6873 Morrison St",
    "sg:city":"Niagara Falls",
    "sg:classifiers":[
        {
            "category":"Shopping",
            "subcategory":"Jewelry",
            "type":"Retail Goods"
        }
    ],
    "sg:phone":"+1 905 374 4075",
    "sg:postcode":"L2E 2G5",
    "sg:province":"ON",
    "sg:tags":[
        "jeweler"
    ],
    "wof:name":"Gold'n Memories Jewellery",
    "wof:placetype":"venue"
},
  "geometry": {"coordinates":[-79.1100616455,43.1043739319],"type":"Point"}
}