{
  "type": "Feature",
  "properties": {
    "addr:full":"54 Church St W Elmira ON N3B 1M9",
    "addr:housenumber":"54",
    "addr:postcode":"n3b 1m9",
    "addr:street":"Church St W",
    "iso:country":"CA",
    "sg:address":"54 Church St W",
    "sg:city":"Elmira",
    "sg:classifiers":[
        {
            "category":"Manufacturing",
            "subcategory":"Apparel",
            "type":"Manufacturing & Wholesale Goods"
        }
    ],
    "sg:phone":"+1 519 669 3033",
    "sg:postcode":"N3B 1M9",
    "sg:province":"ON",
    "sg:tags":[
        "clothing"
    ],
    "wof:name":"John G Brown & Sons",
    "wof:placetype":"venue"
},
  "geometry": {"coordinates":[-80.56381988530001,43.6006317139],"type":"Point"}
}