{
  "type": "Feature",
  "properties": {
    "addr:full":"1530 6E Av Grand-Mere QC G9T 2K1",
    "addr:housenumber":"1530",
    "addr:postcode":"g9t 2k1",
    "addr:street":"6E Av Grand-Mere",
    "iso:country":"CA",
    "sg:address":"1530 6E Av",
    "sg:city":"Grand-Mere",
    "sg:classifiers":[
        {
            "category":"Building & Trades",
            "subcategory":"Electrical",
            "type":"Services"
        }
    ],
    "sg:phone":"+1 819 538 3803",
    "sg:postcode":"G9T 2K1",
    "sg:province":"QC",
    "sg:tags":[
        "electric",
        "contractor"
    ],
    "wof:name":"Pierre Lemire Electrique Inc",
    "wof:placetype":"venue"
},
  "geometry": {"coordinates":[-72.703918,46.606876],"type":"Point"}
}