{
  "type": "Feature",
  "properties": {
    "addr:full":"668 Sackville Dr Lower Sackville NS B4C 2S5",
    "addr:housenumber":"668",
    "addr:postcode":"b4c 2s5",
    "addr:street":"Sackville Dr",
    "iso:country":"CA",
    "sg:address":"668 Sackville Dr",
    "sg:city":"Lower Sackville",
    "sg:classifiers":[
        {
            "category":"Health Services",
            "subcategory":"Medical Lab",
            "type":"Services"
        }
    ],
    "sg:phone":"+1 902 864 4400",
    "sg:postcode":"B4C 2S5",
    "sg:province":"NS",
    "wof:name":"Mason Denture Clinic Sackville",
    "wof:placetype":"venue"
},
  "geometry": {"coordinates":[-63.689365387,44.7699165344],"type":"Point"}
}