{
  "type": "Feature",
  "properties": {
    "iso:country":"CA",
    "sg:address":"280 Tranquille Rd",
    "sg:city":"Kamloops",
    "sg:classifiers":[
        {
            "category":"Autos & Motor Vehicles",
            "subcategory":"Fuel & Gas Station",
            "type":"Retail Goods"
        }
    ],
    "sg:phone":"+1 250 554 2966",
    "sg:postcode":"V2B 3G3",
    "sg:province":"BC",
    "sg:tags":[
        "oil"
    ],
    "wof:name":"Super-Save Gas",
    "wof:placetype":"venue"
},
  "geometry": {"coordinates":[-120.356628,50.687172],"type":"Point"}
}