{
  "type": "Feature",
  "properties": {
    "iso:country":"CA",
    "sg:address":"512 Rue Saint-Louis",
    "sg:city":"Terrebonne",
    "sg:classifiers":[
        {
            "category":"Retail",
            "subcategory":"Animal Services",
            "type":"Services"
        }
    ],
    "sg:phone":"+1 450 964 9674",
    "sg:postcode":"J6W 1J2",
    "sg:province":"QC",
    "sg:tags":[
        "pet",
        "grooming",
        "washing"
    ],
    "wof:name":"Aminalerie Yopi",
    "wof:placetype":"venue"
},
  "geometry": {"coordinates":[-73.6301193237,45.6948471069],"type":"Point"}
}