{
  "type": "Feature",
  "properties": {
    "addr:full":"1234 3 Ave N Lethbridge AB T1H 0H9",
    "addr:housenumber":"1234",
    "addr:postcode":"t1h 0h9",
    "addr:street":"3 Ave N",
    "iso:country":"CA",
    "sg:address":"1234 3 Ave N",
    "sg:city":"Lethbridge",
    "sg:classifiers":[
        {
            "category":"Building & Trades",
            "subcategory":"Construction",
            "type":"Services"
        }
    ],
    "sg:phone":"+1 403 381 7504",
    "sg:postcode":"T1H 0H9",
    "sg:province":"AB",
    "sg:tags":[
        "general",
        "contractor"
    ],
    "wof:name":"Riverpark Homes Ltd",
    "wof:placetype":"venue"
},
  "geometry": {"coordinates":[-112.827972,49.702972],"type":"Point"}
}