{
  "type": "Feature",
  "properties": {
    "addr:full":"Burnaby BC V5H 4J2",
    "addr:postcode":"v5h 4j2",
    "iso:country":"CA",
    "sg:city":"Burnaby",
    "sg:classifiers":[
        {
            "category":"Manufacturing",
            "subcategory":"Metals",
            "type":"Manufacturing & Wholesale Goods"
        }
    ],
    "sg:phone":"+1 604 434 8815",
    "sg:postcode":"V5H 4J2",
    "sg:province":"BC",
    "sg:tags":[
        "engraver"
    ],
    "wof:name":"Personally Yours",
    "wof:placetype":"venue"
},
  "geometry": {"coordinates":[-122.996178,49.227299],"type":"Point"}
}