{
  "type": "Feature",
  "properties": {
    "addr:full":"1516 Telephone Rd Colborne ON K0K 1S0",
    "addr:housenumber":"1516",
    "addr:postcode":"k0k 1s0",
    "addr:street":"Telephone Rd",
    "iso:country":"CA",
    "sg:address":"1516 Telephone Rd",
    "sg:city":"Colborne",
    "sg:classifiers":[
        {
            "category":"Banks & Credit Unions",
            "subcategory":"Investment Brokerage",
            "type":"Services"
        }
    ],
    "sg:phone":"+1 905 355 2828",
    "sg:postcode":"K0K 1S0",
    "sg:province":"ON",
    "wof:name":"Pagun Capital Corp",
    "wof:placetype":"venue"
},
  "geometry": {"coordinates":[-77.92282899999999,44.03495],"type":"Point"}
}