{
  "type": "Feature",
  "properties": {
    "iso:country":"CA",
    "sg:address":"6415 Viscount Rd",
    "sg:city":"Mississauga",
    "sg:classifiers":[
        {
            "category":"Manufacturing",
            "subcategory":"Signs",
            "type":"Manufacturing & Wholesale Goods"
        }
    ],
    "sg:phone":"+1 905 677 6361",
    "sg:postcode":"L4V 1H5",
    "sg:province":"ON",
    "wof:name":"Teksign Inc",
    "wof:placetype":"venue"
},
  "geometry": {"coordinates":[-79.624664,43.69426],"type":"Point"}
}