{
  "type": "Feature",
  "properties": {
    "addr:full":"Alberton PE C0B 1B0",
    "addr:postcode":"c0b 1b0",
    "iso:country":"CA",
    "sg:city":"Alberton",
    "sg:classifiers":[
        {
            "category":"Government",
            "subcategory":"Office",
            "type":"Public Place"
        }
    ],
    "sg:phone":"+1 902 853 8610",
    "sg:postcode":"C0B 1B0",
    "sg:province":"PE",
    "wof:name":"Maplewood Manor",
    "wof:placetype":"venue"
},
  "geometry": {"coordinates":[-64.067657,46.812294],"type":"Point"}
}