{
  "type": "Feature",
  "properties": {
    "addr:full":"741 Av Des Cedres Shawinigan QC G9N 1N9",
    "addr:postcode":"g9n 1n9",
    "addr:street":"741 Av Des Cedres",
    "iso:country":"CA",
    "sg:address":"741 Av Des Cedres",
    "sg:city":"Shawinigan",
    "sg:classifiers":[
        {
            "category":"Organizations",
            "subcategory":"Professional Association",
            "type":"Services"
        }
    ],
    "sg:phone":"+1 819 537 8759",
    "sg:postcode":"G9N 1N9",
    "sg:province":"QC",
    "wof:name":"Scouts St-Pierre St-Bernard",
    "wof:placetype":"venue"
},
  "geometry": {"coordinates":[-72.74642900000001,46.542427],"type":"Point"}
}