{
  "type": "Feature",
  "properties": {
    "addr:full":"926 Boul Du Royaume O Chicoutimi QC G7H 5B1",
    "addr:housenumber":"926",
    "addr:postcode":"g7h 5b1",
    "addr:street":"Boul Du Royaume O",
    "iso:country":"CA",
    "sg:address":"926 Boul Du Royaume O",
    "sg:city":"Chicoutimi",
    "sg:classifiers":[
        {
            "category":"Wholesale",
            "subcategory":"Machinery & Supplies",
            "type":"Manufacturing & Wholesale Goods"
        }
    ],
    "sg:phone":"+1 418 698 6656",
    "sg:postcode":"G7H 5B1",
    "sg:province":"QC",
    "wof:name":"Equipment Jyl Inc",
    "wof:placetype":"venue"
},
  "geometry": {"coordinates":[-71.102898,48.38438],"type":"Point"}
}