{
  "type": "Feature",
  "properties": {
    "addr:full":"7219 7th Ave Whitehorse YT Y1A 1R8",
    "addr:housenumber":"7219",
    "addr:postcode":"y1a 1r8",
    "addr:street":"7Th Ave",
    "iso:country":"CA",
    "sg:address":"7219 7th Ave",
    "sg:city":"Whitehorse",
    "sg:classifiers":[
        {
            "category":"Professional",
            "subcategory":"Art Services",
            "type":"Services"
        }
    ],
    "sg:phone":"+1 867 668 4144",
    "sg:postcode":"Y1A 1R8",
    "sg:province":"YT",
    "sg:tags":[
        "graphic",
        "designer"
    ],
    "wof:name":"Patrick Reece Svc Ltd",
    "wof:placetype":"venue"
},
  "geometry": {"coordinates":[-135.06744384800001,60.7256088257],"type":"Point"}
}