{
  "type": "Feature",
  "properties": {
    "iso:country":"CA",
    "sg:address":"9605 Rue Ignace # N",
    "sg:city":"Brossard",
    "sg:classifiers":[
        {
            "category":"Retail",
            "subcategory":"Auto Repair",
            "type":"Services"
        }
    ],
    "sg:phone":"+1 450 659 2229",
    "sg:postcode":"J4Y 2P3",
    "sg:province":"QC",
    "sg:tags":[
        "repairing",
        "automobile",
        "wheel",
        "alignment"
    ],
    "wof:name":"Spectrum Auto Inc",
    "wof:placetype":"venue"
},
  "geometry": {"coordinates":[-73.475731,45.4314],"type":"Point"}
}