{
  "type": "Feature",
  "properties": {
    "addr:full":"4991 Regional Rd 55 Whitefish ON P0M 3E0",
    "addr:housenumber":"4991;55",
    "addr:postcode":"p0m 3e0",
    "addr:street":"Regional Rd",
    "iso:country":"CA",
    "sg:address":"4991 Regional Rd 55",
    "sg:city":"Whitefish",
    "sg:classifiers":[
        {
            "category":"Organizations",
            "subcategory":"Religious Organization",
            "type":"Services"
        }
    ],
    "sg:phone":"+1 705 692 3138",
    "sg:postcode":"P0M 3E0",
    "sg:province":"ON",
    "sg:tags":[
        "church"
    ],
    "wof:name":"St Christopher Church",
    "wof:placetype":"venue"
},
  "geometry": {"coordinates":[-81.31559799999999,46.378181],"type":"Point"}
}