{
  "type": "Feature",
  "properties": {
    "addr:full":"7550 Hart Hwy Prince George BC V2K 3B2",
    "addr:housenumber":"7550",
    "addr:postcode":"v2k 3b2",
    "addr:street":"Hart Hwy",
    "iso:country":"CA",
    "sg:address":"7550 Hart Hwy",
    "sg:city":"Prince George",
    "sg:classifiers":[
        {
            "category":"Food & Beverages",
            "subcategory":"Groceries & Convenience Stores",
            "type":"Retail Goods"
        }
    ],
    "sg:phone":"+1 250 962 7444",
    "sg:postcode":"V2K 3B2",
    "sg:province":"BC",
    "sg:tags":[
        "grocer"
    ],
    "wof:name":"Pgi Foods",
    "wof:placetype":"venue"
},
  "geometry": {"coordinates":[-122.79961400000001,53.998146],"type":"Point"}
}