{
  "type": "Feature",
  "properties": {
    "addr:full":"65 Rue Principale E Saint-Aubert QC G0R 2R0",
    "addr:housenumber":"65",
    "addr:postcode":"g0r 2r0",
    "addr:street":"Rue Principale E Saint-Aubert",
    "iso:country":"CA",
    "sg:address":"65 Rue Principale E",
    "sg:city":"Saint-Aubert",
    "sg:classifiers":[
        {
            "category":"Taxi",
            "type":"Transportation"
        }
    ],
    "sg:phone":"+1 418 598 6333",
    "sg:postcode":"G0R 2R0",
    "sg:province":"QC",
    "sg:tags":[
        "taxicab"
    ],
    "wof:name":"Transport Scolaire C Fortin",
    "wof:placetype":"venue"
},
  "geometry": {"coordinates":[-70.210678,47.187775],"type":"Point"}
}