{
  "type": "Feature",
  "properties": {
    "addr:full":"Pierrefonds QC H9H 2A8",
    "addr:postcode":"h9h 2a8",
    "iso:country":"CA",
    "sg:city":"Pierrefonds",
    "sg:classifiers":[
        {
            "category":"Retail",
            "subcategory":"Auto Repair",
            "type":"Services"
        }
    ],
    "sg:phone":"+1 514 620 4868",
    "sg:postcode":"H9H 2A8",
    "sg:province":"QC",
    "sg:tags":[
        "repairing",
        "automobile"
    ],
    "wof:name":"Garage Autoscan",
    "wof:placetype":"venue"
},
  "geometry": {"coordinates":[-73.85279800000001,45.49297],"type":"Point"}
}