{
  "type": "Feature",
  "properties": {
    "addr:full":"Surrey BC V3W 2P3",
    "addr:postcode":"v3w 2p3",
    "iso:country":"CA",
    "sg:city":"Surrey",
    "sg:classifiers":[
        {
            "category":"Government",
            "subcategory":"Office",
            "type":"Public Place"
        }
    ],
    "sg:phone":"+1 604 501 3122",
    "sg:postcode":"V3W 2P3",
    "sg:province":"BC",
    "wof:name":"B C Child Protection & Family",
    "wof:placetype":"venue"
},
  "geometry": {"coordinates":[-122.844703674,49.133354187],"type":"Point"}
}