{
  "type": "Feature",
  "properties": {
    "addr:full":"62 Ontario St N Kitchener ON N2H 4Y4",
    "addr:housenumber":"62",
    "addr:postcode":"n2h 4y4",
    "addr:street":"Ontario St N",
    "iso:country":"CA",
    "sg:address":"62 Ontario St N",
    "sg:city":"Kitchener",
    "sg:classifiers":[
        {
            "category":"Health Services",
            "subcategory":"Doctor",
            "type":"Services"
        }
    ],
    "sg:phone":"+1 519 569 8338",
    "sg:postcode":"N2H 4Y4",
    "sg:province":"ON",
    "sg:tags":[
        "dentist"
    ],
    "wof:name":"Tucakov & Tucakov Dental Ofc",
    "wof:placetype":"venue"
},
  "geometry": {"coordinates":[-80.490005,43.451206],"type":"Point"}
}