{
  "type": "Feature",
  "properties": {
    "addr:full":"280 Main Parkhill ON N0M 2K0",
    "addr:housenumber":"280",
    "addr:postcode":"n0m 2k0",
    "addr:street":"Main",
    "iso:country":"CA",
    "sg:address":"280 Main",
    "sg:city":"Parkhill",
    "sg:classifiers":[
        {
            "category":"Government",
            "subcategory":"Police Station",
            "type":"Public Place"
        }
    ],
    "sg:phone":"+1 519 294 0011",
    "sg:postcode":"N0M 2K0",
    "sg:province":"ON",
    "sg:tags":[
        "department"
    ],
    "wof:name":"Ontario Provincial Police",
    "wof:placetype":"venue"
},
  "geometry": {"coordinates":[-81.68399047849999,43.1628913879],"type":"Point"}
}