{
  "type": "Feature",
  "properties": {
    "addr:full":"115 Yorkville Ave Toronto ON M5R 1C1",
    "addr:housenumber":"115",
    "addr:postcode":"m5r 1c1",
    "addr:street":"Yorkville Ave",
    "iso:country":"CA",
    "sg:address":"115 Yorkville Ave",
    "sg:city":"Toronto",
    "sg:classifiers":[
        {
            "category":"Restaurant",
            "type":"Food & Drink"
        }
    ],
    "sg:phone":"+1 416 968 9429",
    "sg:postcode":"M5R 1C1",
    "sg:province":"ON",
    "wof:name":"Remys Restaurant Ltd",
    "wof:placetype":"venue"
},
  "geometry": {"coordinates":[-79.3926696777,43.6706771851],"type":"Point"}
}