{
  "type": "Feature",
  "properties": {
    "addr:full":"1001 Rossland Ave Trail BC V1R 3N7",
    "addr:housenumber":"1001",
    "addr:postcode":"bc v1r 3n7",
    "addr:street":"Rossland Ave Trail",
    "iso:country":"CA",
    "sg:address":"1001 Rossland Ave",
    "sg:city":"Trail",
    "sg:classifiers":[
        {
            "category":"Restaurant",
            "type":"Food & Drink"
        }
    ],
    "sg:phone":"+1 250 368 3355",
    "sg:postcode":"V1R 3N7",
    "sg:province":"BC",
    "wof:name":"Peppercorn Restaurant",
    "wof:placetype":"venue"
},
  "geometry": {"coordinates":[-117.71455400000001,49.096375],"type":"Point"}
}