{
  "type": "Feature",
  "properties": {
    "addr:full":"330 26 Ave SW #100 Calgary AB T2S 2T3",
    "addr:housenumber":"330",
    "addr:postcode":"t2s 2t3",
    "addr:street":"26 Ave Sw # 100",
    "iso:country":"CA",
    "sg:address":"330 26 Ave SW #100",
    "sg:city":"Calgary",
    "sg:classifiers":[
        {
            "category":"Real Estate",
            "subcategory":"Real Estate Operator",
            "type":"Services"
        }
    ],
    "sg:phone":"+1 403 228 6116",
    "sg:postcode":"T2S 2T3",
    "sg:province":"AB",
    "sg:tags":[
        "condominium"
    ],
    "wof:name":"Roxboro House",
    "wof:placetype":"venue"
},
  "geometry": {"coordinates":[-114.06993866000001,51.0297431946],"type":"Point"}
}