{
  "type": "Feature",
  "properties": {
    "addr:full":"1295 Highbury Ave N London ON N5Y 5L3",
    "addr:housenumber":"1295",
    "addr:postcode":"n5y 5l3",
    "addr:street":"Highbury Ave N",
    "iso:country":"CA",
    "sg:address":"1295 Highbury Ave N",
    "sg:city":"London",
    "sg:classifiers":[
        {
            "category":"Health Services",
            "subcategory":"Doctor",
            "type":"Services"
        }
    ],
    "sg:phone":"+1 519 659 2331",
    "sg:postcode":"N5Y 5L3",
    "sg:province":"ON",
    "sg:tags":[
        "clinic"
    ],
    "wof:name":"Highbury Medical",
    "wof:placetype":"venue"
},
  "geometry": {"coordinates":[-81.2161941528,43.0207901001],"type":"Point"}
}