{
  "type": "Feature",
  "properties": {
    "addr:full":"71146 Blue Water Rd Grand Bend ON N0M 1T0",
    "addr:housenumber":"71146",
    "addr:postcode":"n0m 1t0",
    "addr:street":"Blue Water Rd Grand Bend",
    "iso:country":"CA",
    "sg:address":"71146 Blue Water Rd",
    "sg:city":"Grand Bend",
    "sg:classifiers":[
        {
            "category":"Shopping",
            "subcategory":"Discount & Variety Stores",
            "type":"Retail Goods"
        }
    ],
    "sg:phone":"+1 519 238 8542",
    "sg:postcode":"N0M 1T0",
    "sg:province":"ON",
    "wof:name":"Country Market",
    "wof:placetype":"venue"
},
  "geometry": {"coordinates":[-81.74569700000001,43.325668],"type":"Point"}
}