{
  "type": "Feature",
  "properties": {
    "addr:full":"23 Mcadam Ave North York ON M6A 1S4",
    "addr:housenumber":"23",
    "addr:postcode":"m6a 1s4",
    "addr:street":"Mcadam Ave",
    "iso:country":"CA",
    "sg:address":"23 Mcadam Ave",
    "sg:city":"North York",
    "sg:classifiers":[
        {
            "category":"Professional",
            "subcategory":"Research",
            "type":"Services"
        }
    ],
    "sg:phone":"+1 416 654 9810",
    "sg:postcode":"M6A 1S4",
    "sg:province":"ON",
    "sg:tags":[
        "organization",
        "social",
        "philanthropic",
        "welfare"
    ],
    "wof:name":"St Bernadette Family Resource",
    "wof:placetype":"venue"
},
  "geometry": {"coordinates":[-79.458214,43.722233],"type":"Point"}
}