{
  "type": "Feature",
  "properties": {
    "iso:country":"CA",
    "sg:city":"Brossard",
    "sg:classifiers":[
        {
            "category":"Shopping",
            "subcategory":"Clothing, Apparel, & Fashions",
            "type":"Retail Goods"
        }
    ],
    "sg:phone":"+1 450 466 0853",
    "sg:postcode":"J4W 2T5",
    "sg:province":"QC",
    "sg:tags":[
        "item",
        "boutique"
    ],
    "wof:name":"Manteaux Manteaux",
    "wof:placetype":"venue"
},
  "geometry": {"coordinates":[-73.470322,45.473396],"type":"Point"}
}