{
  "type": "Feature",
  "properties": {
    "addr:full":"9238 Armitage St Chilliwack BC V2P 5Y4",
    "addr:housenumber":"9238",
    "addr:postcode":"v2p 5y4",
    "addr:street":"Armitage St",
    "iso:country":"CA",
    "sg:address":"9238 Armitage St",
    "sg:city":"Chilliwack",
    "sg:classifiers":[
        {
            "category":"Building & Trades",
            "subcategory":"Construction",
            "type":"Services"
        }
    ],
    "sg:phone":"+1 604 793 3517",
    "sg:postcode":"V2P 5Y4",
    "sg:province":"BC",
    "sg:tags":[
        "insulation",
        "heat",
        "contractor"
    ],
    "wof:name":"Mart CO Insulating",
    "wof:placetype":"venue"
},
  "geometry": {"coordinates":[-121.93336499999999,49.16993],"type":"Point"}
}