{
  "type": "Feature",
  "properties": {
    "iso:country":"CA",
    "sg:city":"Newmarket",
    "sg:classifiers":[
        {
            "category":"Professional",
            "subcategory":"Lawyer & Legal Services",
            "type":"Services"
        }
    ],
    "sg:phone":"+1 905 895 1090",
    "sg:postcode":"L3Y 8C3",
    "sg:province":"ON",
    "sg:tags":[
        "physician",
        "surgeon",
        "attorney"
    ],
    "wof:name":"Roberts, Kenneth MD",
    "wof:placetype":"venue"
},
  "geometry": {"coordinates":[-79.4476242065,44.0620613098],"type":"Point"}
}