{
  "type": "Feature",
  "properties": {
    "addr:full":"4901 51st Ave High Prairie AB T0G 1E0",
    "addr:housenumber":"4901",
    "addr:postcode":"t0g 1e0",
    "addr:street":"51St Ave",
    "iso:country":"CA",
    "sg:address":"4901 51st Ave",
    "sg:city":"High Prairie",
    "sg:classifiers":[
        {
            "category":"Manufacturing",
            "subcategory":"Printing",
            "type":"Manufacturing & Wholesale Goods"
        }
    ],
    "sg:phone":"+1 780 523 4484",
    "sg:postcode":"T0G 1E0",
    "sg:province":"AB",
    "sg:tags":[
        "newspaper"
    ],
    "wof:name":"South Peace News",
    "wof:placetype":"venue"
},
  "geometry": {"coordinates":[-116.492172,55.430927],"type":"Point"}
}