{
  "type": "Feature",
  "properties": {
    "addr:full":"Knowlton QC J0E 1V0",
    "addr:postcode":"j0e 1v0",
    "addr:street":"Knowlton",
    "iso:country":"CA",
    "sg:city":"Knowlton",
    "sg:classifiers":[
        {
            "category":"Building & Trades",
            "subcategory":"Landscaping Services",
            "type":"Services"
        }
    ],
    "sg:phone":"+1 450 243 6435",
    "sg:postcode":"J0E 1V0",
    "sg:province":"QC",
    "sg:tags":[
        "landscape",
        "contractor"
    ],
    "wof:name":"T K Sports",
    "wof:placetype":"venue"
},
  "geometry": {"coordinates":[-72.52681699999999,45.221275],"type":"Point"}
}