{
  "type": "Feature",
  "properties": {
    "addr:full":"2975 Rue Victoria Lachine QC H8S 1Z4",
    "addr:housenumber":"2975",
    "addr:postcode":"h8s 1z4",
    "addr:street":"Rue Victoria",
    "iso:country":"CA",
    "sg:address":"2975 Rue Victoria",
    "sg:city":"Lachine",
    "sg:classifiers":[
        {
            "category":"Manufacturing",
            "subcategory":"Tools & Machinery",
            "type":"Manufacturing & Wholesale Goods"
        }
    ],
    "sg:phone":"+1 514 637 0050",
    "sg:postcode":"H8S 1Z4",
    "sg:province":"QC",
    "sg:tags":[
        "equipment",
        "electric"
    ],
    "wof:name":"Theovine Inc",
    "wof:placetype":"venue"
},
  "geometry": {"coordinates":[-73.68946099999999,45.43623],"type":"Point"}
}