{
  "type": "Feature",
  "properties": {
    "addr:full":"LA Durantaye QC G0R 1W0",
    "addr:postcode":"g0r 1w0",
    "iso:country":"CA",
    "sg:city":"LA Durantaye",
    "sg:classifiers":[
        {
            "category":"Manufacturing",
            "subcategory":"Rubber & Plastics",
            "type":"Manufacturing & Wholesale Goods"
        }
    ],
    "sg:phone":"+1 418 884 2247",
    "sg:postcode":"G0R 1W0",
    "sg:province":"QC",
    "sg:tags":[
        "container",
        "scrap",
        "metal",
        "iron"
    ],
    "wof:name":"Breton Metal Ltee",
    "wof:placetype":"venue"
},
  "geometry": {"coordinates":[-70.85601043699999,46.8348960876],"type":"Point"}
}