{
  "type": "Feature",
  "properties": {
    "addr:full":"1435 Boul Industriel Saint-Felicien QC G8K 1W1",
    "addr:housenumber":"1435",
    "addr:postcode":"g8k 1w1",
    "addr:street":"Boul Industriel Saint-Felicien",
    "iso:country":"CA",
    "sg:address":"1435 Boul Industriel",
    "sg:city":"Saint-Felicien",
    "sg:classifiers":[
        {
            "category":"Building & Trades",
            "subcategory":"Construction",
            "type":"Services"
        }
    ],
    "sg:phone":"+1 418 679 0965",
    "sg:postcode":"G8K 1W1",
    "sg:province":"QC",
    "sg:tags":[
        "sand",
        "gravel",
        "excavating",
        "contractor"
    ],
    "wof:name":"Machinerie Tremblay & Potvin",
    "wof:placetype":"venue"
},
  "geometry": {"coordinates":[-72.453239,48.639458],"type":"Point"}
}