{
  "type": "Feature",
  "properties": {
    "addr:full":"370 Ch DE LA Grande-Cote Boisbriand QC J7G 1B1",
    "addr:housenumber":"370",
    "addr:postcode":"j7g 1b1",
    "addr:street":"Ch De La Grande-Cote",
    "iso:country":"CA",
    "sg:address":"370 Ch DE LA Grande-Cote",
    "sg:city":"Boisbriand",
    "sg:classifiers":[
        {
            "category":"Home & Garden",
            "subcategory":"Home Furnishings",
            "type":"Retail Goods"
        }
    ],
    "sg:phone":"+1 450 433 2242",
    "sg:postcode":"J7G 1B1",
    "sg:province":"QC",
    "sg:tags":[
        "paint",
        "made",
        "drapery"
    ],
    "wof:name":"Maison Du Decor Enr",
    "wof:placetype":"venue"
},
  "geometry": {"coordinates":[-73.833939,45.606651],"type":"Point"}
}