{
  "type": "Feature",
  "properties": {
    "addr:full":"159 Panin Rd Burlington ON L7P 5A6",
    "addr:housenumber":"159",
    "addr:postcode":"l7p 5a6",
    "addr:street":"Panin Rd",
    "iso:country":"CA",
    "sg:address":"159 Panin Rd",
    "sg:city":"Burlington",
    "sg:classifiers":[
        {
            "category":"Health Services",
            "subcategory":"Nursing And Care Facility",
            "type":"Services"
        }
    ],
    "sg:phone":"+1 905 681 6441",
    "sg:postcode":"L7P 5A6",
    "sg:province":"ON",
    "sg:tags":[
        "home",
        "convalescent"
    ],
    "wof:name":"Cama Woodlands",
    "wof:placetype":"venue"
},
  "geometry": {"coordinates":[-79.8650054932,43.3089942932],"type":"Point"}
}