{
  "type": "Feature",
  "properties": {
    "iso:country":"CA",
    "sg:address":"1628 4th Ave W",
    "sg:city":"Vancouver",
    "sg:classifiers":[
        {
            "category":"Shopping",
            "subcategory":"Clothing, Apparel, & Fashions",
            "type":"Retail Goods"
        }
    ],
    "sg:phone":"+1 604 736 6262",
    "sg:postcode":"V6J 1L9",
    "sg:province":"BC",
    "sg:tags":[
        "item",
        "boutique"
    ],
    "wof:name":"Alison Boutique",
    "wof:placetype":"venue"
},
  "geometry": {"coordinates":[-123.141861,49.267841],"type":"Point"}
}