{
  "type": "Feature",
  "properties": {
    "addr:full":"483 Lawrence Ave W North York ON M5M 1C6",
    "addr:housenumber":"483",
    "addr:postcode":"m5m 1c6",
    "addr:street":"Lawrence Ave W",
    "iso:country":"CA",
    "sg:address":"483 Lawrence Ave W",
    "sg:city":"North York",
    "sg:classifiers":[
        {
            "category":"Food & Beverages",
            "subcategory":"Specialty",
            "type":"Retail Goods"
        }
    ],
    "sg:phone":"+1 416 785 3154",
    "sg:postcode":"M5M 1C6",
    "sg:province":"ON",
    "sg:tags":[
        "health",
        "diet"
    ],
    "wof:name":"A C Tristar Marketing Corp",
    "wof:placetype":"venue"
},
  "geometry": {"coordinates":[-79.4287109375,43.719367981],"type":"Point"}
}