{
  "type": "Feature",
  "properties": {
    "addr:full":"4828 Full Moon Cir Mississauga ON L4Z 2M6",
    "addr:housenumber":"4828",
    "addr:postcode":"l4z 2m6",
    "addr:street":"Full Moon Cir",
    "iso:country":"CA",
    "sg:address":"4828 Full Moon Cir",
    "sg:city":"Mississauga",
    "sg:classifiers":[
        {
            "category":"Building & Trades",
            "subcategory":"Cleaning & Sanitation",
            "type":"Services"
        }
    ],
    "sg:phone":"+1 905 890 2146",
    "sg:postcode":"L4Z 2M6",
    "sg:province":"ON",
    "sg:tags":[
        "janitor"
    ],
    "wof:name":"Globe Janitorial Svc Ltd",
    "wof:placetype":"venue"
},
  "geometry": {"coordinates":[-79.64060211180001,43.6166954041],"type":"Point"}
}