{
  "type": "Feature",
  "properties": {
    "iso:country":"CA",
    "sg:address":"335 Lakeshore Rd E",
    "sg:city":"Oakville",
    "sg:classifiers":[
        {
            "category":"Retail",
            "subcategory":"Laundry & Dry Cleaning",
            "type":"Services"
        }
    ],
    "sg:phone":"+1 905 338 5436",
    "sg:postcode":"L6J 1J4",
    "sg:province":"ON",
    "sg:tags":[
        "cleaners"
    ],
    "wof:name":"Pink Rose",
    "wof:placetype":"venue"
},
  "geometry": {"coordinates":[-79.6654434204,43.4485778809],"type":"Point"}
}