{
  "type": "Feature",
  "properties": {
    "iso:country":"CA",
    "sg:address":"201 City Centre",
    "sg:city":"Kitimat",
    "sg:classifiers":[
        {
            "category":"Banks & Credit Unions",
            "subcategory":"Bank",
            "type":"Services"
        }
    ],
    "sg:phone":"+1 250 632 8420",
    "sg:postcode":"V8C 1T6",
    "sg:province":"BC",
    "wof:name":"Scotiabank",
    "wof:placetype":"venue"
},
  "geometry": {"coordinates":[-128.655639648,54.0531463623],"type":"Point"}
}