{
  "type": "Feature",
  "properties": {
    "addr:full":"1611 Hudson Rd Comox BC V9M 4C7",
    "addr:housenumber":"1611",
    "addr:postcode":"v9m 4c7",
    "addr:street":"Hudson Rd",
    "iso:country":"CA",
    "sg:address":"1611 Hudson Rd",
    "sg:city":"Comox",
    "sg:classifiers":[
        {
            "category":"Autos & Motor Vehicles",
            "subcategory":"Motorcycle Sales",
            "type":"Retail Goods"
        }
    ],
    "sg:phone":"+1 250 339 4825",
    "sg:postcode":"V9M 4C7",
    "sg:province":"BC",
    "sg:tags":[
        "scooter"
    ],
    "wof:name":"Jack's Motorcycle Salvage",
    "wof:placetype":"venue"
},
  "geometry": {"coordinates":[-124.92681899999999,49.673538],"type":"Point"}
}