{
  "type": "Feature",
  "properties": {
    "addr:full":"Ottawa ON K1G 1A4",
    "addr:postcode":"k1g 1a4",
    "iso:country":"CA",
    "sg:city":"Ottawa",
    "sg:classifiers":[
        {
            "category":"Shopping",
            "subcategory":"Jewelry",
            "type":"Retail Goods"
        }
    ],
    "sg:phone":"+1 613 744 8986",
    "sg:postcode":"K1G 1A4",
    "sg:province":"ON",
    "sg:tags":[
        "jeweler"
    ],
    "wof:name":"Vinasia Jewellers",
    "wof:placetype":"venue"
},
  "geometry": {"coordinates":[-75.62404600000001,45.400059],"type":"Point"}
}