{
  "type": "Feature",
  "properties": {
    "addr:full":"10 Des Loisirs Saint-Gedeon-DE-Beauce QC G0M 1T0",
    "addr:housenumber":"10",
    "addr:postcode":"g0m 1t0",
    "addr:street":"Des Loisirs Saint-Gedeon-De-Beauce",
    "iso:country":"CA",
    "sg:address":"10 Des Loisirs",
    "sg:city":"Saint-Gedeon-DE-Beauce",
    "sg:classifiers":[
        {
            "category":"Recreation",
            "type":"Entertainment"
        }
    ],
    "sg:phone":"+1 418 582 3826",
    "sg:postcode":"G0M 1T0",
    "sg:province":"QC",
    "sg:tags":[
        "center"
    ],
    "wof:name":"Loisirs DE St-Robert Inc",
    "wof:placetype":"venue"
},
  "geometry": {"coordinates":[-70.6349868774,45.8565635681],"type":"Point"}
}