{
  "type": "Feature",
  "properties": {
    "addr:full":"420 Glover Rd Stoney Creek ON L8E 5M4",
    "addr:housenumber":"420",
    "addr:postcode":"l8e 5m4",
    "addr:street":"Glover Rd",
    "iso:country":"CA",
    "sg:address":"420 Glover Rd",
    "sg:city":"Stoney Creek",
    "sg:classifiers":[
        {
            "category":"Manufacturing",
            "subcategory":"Tools & Machinery",
            "type":"Manufacturing & Wholesale Goods"
        }
    ],
    "sg:phone":"+1 905 643 2937",
    "sg:postcode":"L8E 5M4",
    "sg:province":"ON",
    "sg:tags":[
        "machine",
        "shop"
    ],
    "wof:name":"Industrial Tooling & Mfg",
    "wof:placetype":"venue"
},
  "geometry": {"coordinates":[-79.6764297485,43.2243309021],"type":"Point"}
}