{
  "type": "Feature",
  "properties": {
    "addr:full":"362 Main St Kentville NS B4N 1K6",
    "addr:housenumber":"362",
    "addr:postcode":"b4n 1k6",
    "addr:street":"Main St",
    "iso:country":"CA",
    "sg:address":"362 Main St",
    "sg:city":"Kentville",
    "sg:classifiers":[
        {
            "category":"Personal",
            "subcategory":"Tattoo Parlor",
            "type":"Services"
        }
    ],
    "sg:phone":"+1 902 679 1965",
    "sg:postcode":"B4N 1K6",
    "sg:province":"NS",
    "sg:tags":[
        "tattooing"
    ],
    "wof:name":"Arts Under Skin",
    "wof:placetype":"venue"
},
  "geometry": {"coordinates":[-64.4905166626,45.075756073],"type":"Point"}
}