{
  "type": "Feature",
  "properties": {
    "addr:full":"241 Rue Principale Cowansville QC J2K 1J4",
    "addr:housenumber":"241",
    "addr:postcode":"j2k 1j4",
    "addr:street":"Rue Principale",
    "iso:country":"CA",
    "sg:address":"241 Rue Principale",
    "sg:city":"Cowansville",
    "sg:classifiers":[
        {
            "category":"Health Services",
            "subcategory":"Doctor",
            "type":"Services"
        }
    ],
    "sg:phone":"+1 450 263 4846",
    "sg:postcode":"J2K 1J4",
    "sg:province":"QC",
    "sg:tags":[
        "clinic"
    ],
    "wof:name":"Clinique Medica Clinic",
    "wof:placetype":"venue"
},
  "geometry": {"coordinates":[-72.74082900000001,45.208771],"type":"Point"}
}