{
  "type": "Feature",
  "properties": {
    "iso:country":"CA",
    "sg:address":"63 Church St W",
    "sg:city":"Smiths Falls",
    "sg:classifiers":[
        {
            "category":"Wholesale",
            "subcategory":"Fruits & Vegetables",
            "type":"Manufacturing & Wholesale Goods"
        }
    ],
    "sg:phone":"+1 613 283 4980",
    "sg:postcode":"K7A 1R2",
    "sg:province":"ON",
    "sg:tags":[
        "grocer"
    ],
    "wof:name":"J Quattrocchi & CO Ltd",
    "wof:placetype":"venue"
},
  "geometry": {"coordinates":[-76.02658099999999,44.901741],"type":"Point"}
}