{
  "type": "Feature",
  "properties": {
    "addr:full":"312 1Re Av Deux-Montagnes QC J7R 4X7",
    "addr:housenumber":"312",
    "addr:postcode":"j7r 4x7",
    "addr:street":"1Re Av Deux-Montagnes",
    "iso:country":"CA",
    "sg:address":"312 1Re Av",
    "sg:city":"Deux-Montagnes",
    "sg:classifiers":[
        {
            "category":"Real Estate",
            "subcategory":"Real Estate Operator",
            "type":"Services"
        }
    ],
    "sg:phone":"+1 450 472 1169",
    "sg:postcode":"J7R 4X7",
    "sg:province":"QC",
    "sg:tags":[
        "apartment",
        "rental",
        "agency"
    ],
    "wof:name":"Fere Construction Inc",
    "wof:placetype":"venue"
},
  "geometry": {"coordinates":[-73.89250946040001,45.5484962463],"type":"Point"}
}