{
  "type": "Feature",
  "properties": {
    "addr:full":"4655 Crescent Rd Nelson BC V1L 6N3",
    "addr:housenumber":"4655",
    "addr:postcode":"bc v1l 6n3",
    "addr:street":"Crescent Rd",
    "iso:country":"CA",
    "sg:address":"4655 Crescent Rd",
    "sg:city":"Nelson",
    "sg:classifiers":[
        {
            "category":"Wholesale",
            "subcategory":"Hardware",
            "type":"Manufacturing & Wholesale Goods"
        }
    ],
    "sg:phone":"+1 250 825 3428",
    "sg:postcode":"V1L 6N3",
    "sg:province":"BC",
    "sg:tags":[
        "tool"
    ],
    "wof:name":"Starlight Tool Svc",
    "wof:placetype":"venue"
},
  "geometry": {"coordinates":[-117.288811,49.49754],"type":"Point"}
}