{
  "type": "Feature",
  "properties": {
    "iso:country":"CA",
    "sg:address":"934 Boul L'Assomption",
    "sg:city":"Repentigny",
    "sg:classifiers":[
        {
            "category":"Social Services",
            "subcategory":"Child Care",
            "type":"Services"
        }
    ],
    "sg:phone":"+1 450 581 1211",
    "sg:postcode":"J6A 5H5",
    "sg:province":"QC",
    "wof:name":"Centre DE LA Petite Enfance",
    "wof:placetype":"venue"
},
  "geometry": {"coordinates":[-73.4440612793,45.7554397583],"type":"Point"}
}