{
  "type": "Feature",
  "properties": {
    "addr:full":"2218 Governor's Rd Copetown ON L0R 1J0",
    "addr:housenumber":"2218",
    "addr:postcode":"l0r 1j0",
    "addr:street":"Governor'S Rd",
    "iso:country":"CA",
    "sg:address":"2218 Governor's Rd",
    "sg:city":"Copetown",
    "sg:classifiers":[
        {
            "category":"Organizations",
            "subcategory":"Religious Organization",
            "type":"Services"
        }
    ],
    "sg:phone":"+1 905 627 9460",
    "sg:postcode":"L0R 1J0",
    "sg:province":"ON",
    "sg:tags":[
        "church"
    ],
    "wof:name":"Copetown Rockton United Church",
    "wof:placetype":"venue"
},
  "geometry": {"coordinates":[-80.216309,43.260162],"type":"Point"}
}