{
  "type": "Feature",
  "properties": {
    "addr:full":"910 Rue Cote Rouyn-Noranda QC J9X 3S5",
    "addr:housenumber":"910",
    "addr:postcode":"j9x 3s5",
    "addr:street":"Rue Cote",
    "iso:country":"CA",
    "sg:address":"910 Rue Cote",
    "sg:city":"Rouyn-Noranda",
    "sg:classifiers":[
        {
            "category":"Social Services",
            "subcategory":"Child Care",
            "type":"Services"
        }
    ],
    "sg:phone":"+1 819 762 0550",
    "sg:postcode":"J9X 3S5",
    "sg:province":"QC",
    "wof:name":"Garderie Ecole Le Prelude",
    "wof:placetype":"venue"
},
  "geometry": {"coordinates":[-79.0006561279,48.2268447876],"type":"Point"}
}