{
  "type": "Feature",
  "properties": {
    "addr:full":"Sutton QC J0E 2K0",
    "addr:postcode":"j0e 2k0",
    "iso:country":"CA",
    "sg:city":"Sutton",
    "sg:classifiers":[
        {
            "category":"Personal",
            "subcategory":"Barber",
            "type":"Services"
        }
    ],
    "sg:phone":"+1 450 538 0117",
    "sg:postcode":"J0E 2K0",
    "sg:province":"QC",
    "sg:tags":[
        "salon",
        "beauty"
    ],
    "wof:name":"Salon Entre Amies Enr",
    "wof:placetype":"venue"
},
  "geometry": {"coordinates":[-72.61595199999999,45.107944],"type":"Point"}
}