{
  "type": "Feature",
  "properties": {
    "addr:full":"Vercheres QC J0L 2R0",
    "addr:postcode":"j0l 2r0",
    "iso:country":"CA",
    "sg:city":"Vercheres",
    "sg:classifiers":[
        {
            "category":"Retail",
            "subcategory":"Auto Repair",
            "type":"Services"
        }
    ],
    "sg:phone":"+1 450 583 3071",
    "sg:postcode":"J0L 2R0",
    "sg:province":"QC",
    "sg:tags":[
        "repairing",
        "automobile"
    ],
    "wof:name":"Garage Mario Dansereau Enr",
    "wof:placetype":"venue"
},
  "geometry": {"coordinates":[-73.34741200000001,45.769348],"type":"Point"}
}