{
  "type": "Feature",
  "properties": {
    "addr:full":"130 1 Ave W Canora SK S0A 0L0",
    "addr:housenumber":"130",
    "addr:postcode":"s0a 0l0",
    "addr:street":"1 Ave W Canora",
    "iso:country":"CA",
    "sg:address":"130 1 Ave W",
    "sg:city":"Canora",
    "sg:classifiers":[
        {
            "category":"Professional",
            "subcategory":"Accounting & Tax Preparation",
            "type":"Services"
        }
    ],
    "sg:phone":"+1 306 563 5662",
    "sg:postcode":"S0A 0L0",
    "sg:province":"SK",
    "sg:tags":[
        "accountant"
    ],
    "wof:name":"Active Accounting Ltd",
    "wof:placetype":"venue"
},
  "geometry": {"coordinates":[-102.432434,51.635456],"type":"Point"}
}