{
  "type": "Feature",
  "properties": {
    "addr:full":"77 8th Ave W Vancouver BC V5Y 1M8",
    "addr:housenumber":"77",
    "addr:postcode":"v5y 1m8",
    "addr:street":"8Th Ave W",
    "iso:country":"CA",
    "sg:address":"77 8th Ave W",
    "sg:city":"Vancouver",
    "sg:classifiers":[
        {
            "category":"Professional",
            "subcategory":"Advertising",
            "type":"Services"
        }
    ],
    "sg:phone":"+1 604 606 1846",
    "sg:postcode":"V5Y 1M8",
    "sg:province":"BC",
    "wof:name":"Light Viion Media",
    "wof:placetype":"venue"
},
  "geometry": {"coordinates":[-123.106255,49.263927],"type":"Point"}
}