{
  "type": "Feature",
  "properties": {
    "addr:full":"929 Bowen Rd Fort Erie ON L2A 5M4",
    "addr:housenumber":"929",
    "addr:postcode":"l2a 5m4",
    "addr:street":"Bowen Rd",
    "iso:country":"CA",
    "sg:address":"929 Bowen Rd",
    "sg:city":"Fort Erie",
    "sg:classifiers":[
        {
            "category":"Retail",
            "subcategory":"Auto Repair",
            "type":"Services"
        }
    ],
    "sg:phone":"+1 905 991 0001",
    "sg:postcode":"L2A 5M4",
    "sg:province":"ON",
    "sg:tags":[
        "truck"
    ],
    "wof:name":"Zanchin Truck & Trailer Inc",
    "wof:placetype":"venue"
},
  "geometry": {"coordinates":[-78.9523391724,42.9315490723],"type":"Point"}
}