{
  "type": "Feature",
  "properties": {
    "iso:country":"CA",
    "sg:address":"929 Bowen Rd",
    "sg:city":"Fort Erie",
    "sg:classifiers":[
        {
            "category":"Retail",
            "subcategory":"Auto Repair",
            "type":"Services"
        }
    ],
    "sg:phone":"+1 905 991 0001",
    "sg:postcode":"L2A 5M4",
    "sg:province":"ON",
    "sg:tags":[
        "truck"
    ],
    "wof:name":"Zanchin Truck & Trailer Inc",
    "wof:placetype":"venue"
},
  "geometry": {"coordinates":[-78.9523391724,42.9315490723],"type":"Point"}
}