{
  "type": "Feature",
  "properties": {
    "iso:country":"CA",
    "sg:address":"5431 Av Du Parc",
    "sg:city":"Montreal",
    "sg:classifiers":[
        {
            "category":"Shopping",
            "subcategory":"Optical Goods",
            "type":"Retail Goods"
        }
    ],
    "sg:phone":"+1 514 908 0808",
    "sg:postcode":"H2V 4G9",
    "sg:province":"QC",
    "sg:tags":[
        "optician"
    ],
    "wof:name":"Illusion Optique",
    "wof:placetype":"venue"
},
  "geometry": {"coordinates":[-73.60084533689999,45.5217704773],"type":"Point"}
}