{
  "type": "Feature",
  "properties": {
    "addr:full":"835 Birchmount Rd Scarborough ON M1K 5K1",
    "addr:housenumber":"835",
    "addr:postcode":"m1k 5k1",
    "addr:street":"Birchmount Rd",
    "iso:country":"CA",
    "sg:address":"835 Birchmount Rd",
    "sg:city":"Scarborough",
    "sg:classifiers":[
        {
            "category":"Social Services",
            "subcategory":"Child Care",
            "type":"Services"
        }
    ],
    "sg:phone":"+1 416 750 4598",
    "sg:postcode":"M1K 5K1",
    "sg:province":"ON",
    "wof:name":"Isabella Walton Childcare Ctr",
    "wof:placetype":"venue"
},
  "geometry": {"coordinates":[-79.277214,43.728584],"type":"Point"}
}