{
  "type": "Feature",
  "properties": {
    "addr:full":"785 Rue DE Saint-Jovite Mont-Tremblant QC J8E 3J8",
    "addr:housenumber":"785",
    "addr:postcode":"j8e 3j8",
    "addr:street":"Rue De Saint-Jovite",
    "iso:country":"CA",
    "sg:address":"785 Rue DE Saint-Jovite",
    "sg:city":"Mont-Tremblant",
    "sg:classifiers":[
        {
            "category":"Real Estate",
            "subcategory":"Real Estate Agent",
            "type":"Services"
        }
    ],
    "sg:phone":"+1 819 425 3338",
    "sg:postcode":"J8E 3J8",
    "sg:province":"QC",
    "wof:name":"Remax St Jovite MT-Tremblant",
    "wof:placetype":"venue"
},
  "geometry": {"coordinates":[-74.589493,46.118538],"type":"Point"}
}