{
  "type": "Feature",
  "properties": {
    "addr:full":"455 Rue Sherbrooke O Montreal QC H3A 1B7",
    "addr:housenumber":"455",
    "addr:postcode":"h3a 1b7",
    "addr:street":"Rue Sherbrooke O",
    "iso:country":"CA",
    "sg:address":"455 Rue Sherbrooke O",
    "sg:city":"Montreal",
    "sg:classifiers":[
        {
            "category":"Shopping",
            "subcategory":"Pharmacy",
            "type":"Retail Goods"
        }
    ],
    "sg:phone":"+1 514 849 6019",
    "sg:postcode":"H3A 1B7",
    "sg:province":"QC",
    "wof:name":"Cresent Pharmacy",
    "wof:placetype":"venue"
},
  "geometry": {"coordinates":[-73.567398,45.517479],"type":"Point"}
}