{
  "type": "Feature",
  "properties": {
    "addr:full":"2515 Pollock Rd North Gower ON K0A 2T0",
    "addr:housenumber":"2515",
    "addr:postcode":"k0a 2t0",
    "addr:street":"Pollock Rd",
    "iso:country":"CA",
    "sg:address":"2515 Pollock Rd",
    "sg:city":"North Gower",
    "sg:classifiers":[
        {
            "category":"Food & Beverages",
            "subcategory":"Dairy",
            "type":"Retail Goods"
        }
    ],
    "sg:phone":"+1 613 489 3805",
    "sg:postcode":"K0A 2T0",
    "sg:province":"ON",
    "sg:tags":[
        "product"
    ],
    "wof:name":"North Gower Cheese Factory",
    "wof:placetype":"venue"
},
  "geometry": {"coordinates":[-75.7574920654,45.1474494934],"type":"Point"}
}