{
  "type": "Feature",
  "properties": {
    "addr:full":"46 Titan Dr Stoney Creek ON L8E 6A1",
    "addr:housenumber":"46",
    "addr:postcode":"l8e 6a1",
    "addr:street":"Titan Dr",
    "iso:country":"CA",
    "sg:address":"46 Titan Dr",
    "sg:city":"Stoney Creek",
    "sg:classifiers":[
        {
            "category":"Shopping",
            "type":"Retail Goods"
        }
    ],
    "sg:phone":"+1 905 662 3747",
    "sg:postcode":"L8E 6A1",
    "sg:province":"ON",
    "sg:tags":[
        "cosmetic",
        "perfume"
    ],
    "wof:name":"Garon Enterprises",
    "wof:placetype":"venue"
},
  "geometry": {"coordinates":[-79.718842,43.218357],"type":"Point"}
}