{
  "type": "Feature",
  "properties": {
    "addr:full":"68 Railway Ave Pierson MB R0M 1S0",
    "addr:housenumber":"68",
    "addr:postcode":"r0m 1s0",
    "addr:street":"Railway Ave",
    "iso:country":"CA",
    "sg:address":"68 Railway Ave",
    "sg:city":"Pierson",
    "sg:classifiers":[
        {
            "category":"Banks & Credit Unions",
            "subcategory":"Bank",
            "type":"Services"
        }
    ],
    "sg:phone":"+1 204 634 2351",
    "sg:postcode":"R0M 1S0",
    "sg:province":"MB",
    "wof:name":"Royal Bank Financial Group",
    "wof:placetype":"venue"
},
  "geometry": {"coordinates":[-101.267303467,49.1780433655],"type":"Point"}
}