{
  "type": "Feature",
  "properties": {
    "addr:full":"PO Box 961 STN Main Nelson BC V1L 6A5",
    "addr:housenumber":"po",
    "addr:postcode":"bc v1l 6a5",
    "addr:street":"Box 961 Stn Main",
    "iso:country":"CA",
    "sg:address":"PO Box 961 STN Main",
    "sg:city":"Nelson",
    "sg:classifiers":[
        {
            "category":"Building & Trades",
            "subcategory":"Landscaping Services",
            "type":"Services"
        }
    ],
    "sg:phone":"+1 250 352 5995",
    "sg:postcode":"V1L 6A5",
    "sg:province":"BC",
    "sg:tags":[
        "lawn",
        "contractor",
        "landscape",
        "maintenance",
        "grounds"
    ],
    "wof:name":"A-1 Lawn Care Svc",
    "wof:placetype":"venue"
},
  "geometry": {"coordinates":[-117.28881072999999,49.4975395203],"type":"Point"}
}