{
  "type": "Feature",
  "properties": {
    "addr:full":"502 114th St North Battleford SK S9A 4A6",
    "addr:housenumber":"502",
    "addr:postcode":"s9a 4a6",
    "addr:street":"114Th St",
    "iso:country":"CA",
    "sg:address":"502 114th St",
    "sg:city":"North Battleford",
    "sg:classifiers":[
        {
            "category":"Professional",
            "subcategory":"Lawyer & Legal Services",
            "type":"Services"
        }
    ],
    "sg:phone":"+1 306 446 7585",
    "sg:postcode":"S9A 4A6",
    "sg:province":"SK",
    "sg:tags":[
        "attorney",
        "government"
    ],
    "wof:name":"Sask Highway Repair Depot",
    "wof:placetype":"venue"
},
  "geometry": {"coordinates":[-108.27770200000001,52.764393],"type":"Point"}
}