{
  "type": "Feature",
  "properties": {
    "addr:full":"1041 Whenun Rd Prince George BC V2K 5X8",
    "addr:housenumber":"1041",
    "addr:postcode":"v2k 5x8",
    "addr:street":"Whenun Rd",
    "iso:country":"CA",
    "sg:address":"1041 Whenun Rd",
    "sg:city":"Prince George",
    "sg:classifiers":[
        {
            "category":"Organizations",
            "subcategory":"Professional Association",
            "type":"Services"
        }
    ],
    "sg:phone":"+1 250 963 8451",
    "sg:postcode":"V2K 5X8",
    "sg:province":"BC",
    "wof:name":"Lheidli T'Enneh Band",
    "wof:placetype":"venue"
},
  "geometry": {"coordinates":[-122.745087,53.91235],"type":"Point"}
}