{
  "type": "Feature",
  "properties": {
    "addr:full":"12900 Rue Notre-Dame E Pointe-Aux-Trembles QC H1A 1R9",
    "addr:housenumber":"12900",
    "addr:postcode":"h1a 1r9",
    "addr:street":"Rue Notre-Dame E Pointe-Aux-Trembles",
    "iso:country":"CA",
    "sg:address":"12900 Rue Notre-Dame E",
    "sg:city":"Pointe-Aux-Trembles",
    "sg:classifiers":[
        {
            "category":"Real Estate",
            "subcategory":"Real Estate Operator",
            "type":"Services"
        }
    ],
    "sg:phone":"+1 514 640 1442",
    "sg:postcode":"H1A 1R9",
    "sg:province":"QC",
    "sg:tags":[
        "mall",
        "shopping",
        "center"
    ],
    "wof:name":"Multi-Soins Inc",
    "wof:placetype":"venue"
},
  "geometry": {"coordinates":[-73.489586,45.652744],"type":"Point"}
}