{
  "type": "Feature",
  "properties": {
    "addr:full":"104 Rue Barr Saint-Laurent QC H4T 1Y4",
    "addr:housenumber":"104",
    "addr:postcode":"h4t 1y4",
    "addr:street":"Rue Barr",
    "iso:country":"CA",
    "sg:address":"104 Rue Barr",
    "sg:city":"Saint-Laurent",
    "sg:classifiers":[
        {
            "category":"Wholesale",
            "subcategory":"Sporting Goods",
            "type":"Manufacturing & Wholesale Goods"
        }
    ],
    "sg:phone":"+1 514 341 6767",
    "sg:postcode":"H4T 1Y4",
    "sg:province":"QC",
    "sg:tags":[
        "equipment",
        "golf",
        "supply"
    ],
    "wof:name":"Fletcher Leisure Group",
    "wof:placetype":"venue"
},
  "geometry": {"coordinates":[-73.691368103,45.4808197021],"type":"Point"}
}