{
  "type": "Feature",
  "properties": {
    "addr:full":"Burnaby BC V5H 4G3",
    "addr:postcode":"v5h 4g3",
    "iso:country":"CA",
    "sg:city":"Burnaby",
    "sg:classifiers":[
        {
            "category":"Personal",
            "subcategory":"Beauty Salon",
            "type":"Services"
        }
    ],
    "sg:phone":"+1 604 433 5311",
    "sg:postcode":"V5H 4G3",
    "sg:province":"BC",
    "wof:name":"Trask, D",
    "wof:placetype":"venue"
},
  "geometry": {"coordinates":[-122.990005,49.22456],"type":"Point"}
}