{
  "type": "Feature",
  "properties": {
    "addr:full":"251 Woolner Ave York ON M6N 1Y8",
    "addr:housenumber":"251",
    "addr:postcode":"m6n 1y8",
    "addr:street":"Woolner Ave",
    "iso:country":"CA",
    "sg:address":"251 Woolner Ave",
    "sg:city":"York",
    "sg:classifiers":[
        {
            "category":"Food & Beverages",
            "subcategory":"Groceries & Convenience Stores",
            "type":"Retail Goods"
        }
    ],
    "sg:phone":"+1 416 604 4998",
    "sg:postcode":"M6N 1Y8",
    "sg:province":"ON",
    "sg:tags":[
        "grocer"
    ],
    "wof:name":"Joseph Saba Foods Inc",
    "wof:placetype":"venue"
},
  "geometry": {"coordinates":[-79.49185199999999,43.671856],"type":"Point"}
}