{
  "type": "Feature",
  "properties": {
    "addr:full":"Ward Rd Kingston NS B0P 1R0",
    "addr:postcode":"b0p 1r0",
    "addr:street":"Ward Rd",
    "iso:country":"CA",
    "sg:address":"Ward Rd",
    "sg:city":"Kingston",
    "sg:classifiers":[
        {
            "category":"Organizations",
            "subcategory":"Religious Organization",
            "type":"Services"
        }
    ],
    "sg:phone":"+1 902 765 6181",
    "sg:postcode":"B0P 1R0",
    "sg:province":"NS",
    "sg:tags":[
        "church"
    ],
    "wof:name":"Church of Jesus Christ-Lds",
    "wof:placetype":"venue"
},
  "geometry": {"coordinates":[-64.94935599999999,44.987438],"type":"Point"}
}