{
  "type": "Feature",
  "properties": {
    "addr:full":"373 Rue Parent Saint-Jerome QC J7Z 2A1",
    "addr:housenumber":"373",
    "addr:postcode":"j7z 2a1",
    "addr:street":"Rue Parent Saint-Jerome",
    "iso:country":"CA",
    "sg:address":"373 Rue Parent",
    "sg:city":"Saint-Jerome",
    "sg:classifiers":[
        {
            "category":"Organizations",
            "subcategory":"Professional Association",
            "type":"Services"
        }
    ],
    "sg:phone":"+1 450 438 4291",
    "sg:postcode":"J7Z 2A1",
    "sg:province":"QC",
    "wof:name":"Association Laurentienne",
    "wof:placetype":"venue"
},
  "geometry": {"coordinates":[-73.99912999999999,45.777237],"type":"Point"}
}