{
  "type": "Feature",
  "properties": {
    "addr:full":"120 Boul DE L'Hopital #105 Gatineau QC J8T 8M2",
    "addr:housenumber":"120",
    "addr:postcode":"j8t 8m2",
    "addr:street":"Boul De L'Hopital # 105",
    "iso:country":"CA",
    "sg:address":"120 Boul DE L'Hopital #105",
    "sg:city":"Gatineau",
    "sg:classifiers":[
        {
            "category":"Restaurant",
            "type":"Food & Drink"
        }
    ],
    "sg:phone":"+1 819 561 3354",
    "sg:postcode":"J8T 8M2",
    "sg:province":"QC",
    "wof:name":"Chenoy's",
    "wof:placetype":"venue"
},
  "geometry": {"coordinates":[-75.710503,45.427849],"type":"Point"}
}