{
  "type": "Feature",
  "properties": {
    "iso:country":"CA",
    "sg:address":"1112 Route 101",
    "sg:city":"Poularies",
    "sg:classifiers":[
        {
            "category":"Recreation",
            "type":"Entertainment"
        }
    ],
    "sg:phone":"+1 819 782 5721",
    "sg:postcode":"J0Z 3E0",
    "sg:province":"QC",
    "sg:tags":[
        "amusement"
    ],
    "wof:name":"Club DE Motoneige Aventuriers",
    "wof:placetype":"venue"
},
  "geometry": {"coordinates":[-78.9853820801,48.6753234863],"type":"Point"}
}