{
  "type": "Feature",
  "properties": {
    "iso:country":"CA",
    "sg:address":"36 Steel St",
    "sg:city":"Barrie",
    "sg:classifiers":[
        {
            "category":"Education",
            "subcategory":"School",
            "type":"Public Place"
        }
    ],
    "sg:phone":"+1 705 728 9292",
    "sg:postcode":"L4M 2E7",
    "sg:province":"ON",
    "wof:name":"Steele Street School",
    "wof:placetype":"venue"
},
  "geometry": {"coordinates":[-79.671371,44.40266],"type":"Point"}
}