{
  "type": "Feature",
  "properties": {
    "addr:full":"315 Rue Bagot Quebec QC G1K 1V9",
    "addr:housenumber":"315",
    "addr:postcode":"g1k 1v9",
    "addr:street":"Rue Bagot",
    "iso:country":"CA",
    "sg:address":"315 Rue Bagot",
    "sg:city":"Quebec",
    "sg:classifiers":[
        {
            "category":"Retail",
            "subcategory":"Auto Repair",
            "type":"Services"
        }
    ],
    "sg:phone":"+1 418 529 3632",
    "sg:postcode":"G1K 1V9",
    "sg:province":"QC",
    "sg:tags":[
        "repairing",
        "automobile"
    ],
    "wof:name":"Careau & Fils Enrg",
    "wof:placetype":"venue"
},
  "geometry": {"coordinates":[-71.23500061039999,46.8098526001],"type":"Point"}
}