{
  "type": "Feature",
  "properties": {
    "iso:country":"CA",
    "sg:address":"29 Rue Ducharme",
    "sg:city":"Hull",
    "sg:classifiers":[
        {
            "category":"Health Services",
            "subcategory":"Doctor",
            "type":"Services"
        }
    ],
    "sg:phone":"+1 819 770 2021",
    "sg:postcode":"J8Y 3P7",
    "sg:province":"QC",
    "sg:tags":[
        "physician",
        "surgeon"
    ],
    "wof:name":"Mercier, Francois MD",
    "wof:placetype":"venue"
},
  "geometry": {"coordinates":[-75.73155975340001,45.4383163452],"type":"Point"}
}