{
  "type": "Feature",
  "properties": {
    "addr:full":"North Bay ON P1B 8X1",
    "addr:postcode":"p1b 8x1",
    "iso:country":"CA",
    "sg:city":"North Bay",
    "sg:classifiers":[
        {
            "category":"Shopping",
            "subcategory":"Catalog Store",
            "type":"Retail Goods"
        }
    ],
    "sg:phone":"+1 705 476 6835",
    "sg:postcode":"P1B 8X1",
    "sg:province":"ON",
    "sg:tags":[
        "mail",
        "order",
        "internet"
    ],
    "wof:name":"Sears Canada Inc",
    "wof:placetype":"venue"
},
  "geometry": {"coordinates":[-79.456619,46.33654],"type":"Point"}
}