{
  "type": "Feature",
  "properties": {
    "iso:country":"CA",
    "sg:city":"Mississauga",
    "sg:classifiers":[
        {
            "category":"Shopping",
            "subcategory":"Tobacco",
            "type":"Retail Goods"
        }
    ],
    "sg:phone":"+1 905 276 5124",
    "sg:postcode":"L5B 4L2",
    "sg:province":"ON",
    "sg:tags":[
        "cigarette",
        "cigar",
        "dealer"
    ],
    "wof:name":"Eagle Cigars",
    "wof:placetype":"venue"
},
  "geometry": {"coordinates":[-79.6291503906,43.5716590881],"type":"Point"}
}