{
  "type": "Feature",
  "properties": {
    "addr:full":"150 Av Percival Montreal-Ouest QC H4X 1T6",
    "addr:postcode":"h4x 1t6",
    "addr:street":"150 Av Percival Montreal-Ouest",
    "iso:country":"CA",
    "sg:address":"150 Av Percival",
    "sg:city":"Montreal-Ouest",
    "sg:classifiers":[
        {
            "category":"Professional",
            "subcategory":"Research",
            "type":"Services"
        }
    ],
    "sg:phone":"+1 514 487 2295",
    "sg:postcode":"H4X 1T6",
    "sg:province":"QC",
    "sg:tags":[
        "development",
        "laboratory"
    ],
    "wof:name":"Michele Bally Pharmaconsult",
    "wof:placetype":"venue"
},
  "geometry": {"coordinates":[-73.65081000000001,45.452583],"type":"Point"}
}