{
  "type": "Feature",
  "properties": {
    "addr:full":"Port Carling ON P0B 1J0",
    "addr:postcode":"p0b 1j0",
    "iso:country":"CA",
    "sg:city":"Port Carling",
    "sg:classifiers":[
        {
            "category":"Retail",
            "subcategory":"Veterinary Services",
            "type":"Services"
        }
    ],
    "sg:phone":"+1 705 765 3935",
    "sg:postcode":"P0B 1J0",
    "sg:province":"ON",
    "sg:tags":[
        "veterinarian"
    ],
    "wof:name":"White, Ian M DVM",
    "wof:placetype":"venue"
},
  "geometry": {"coordinates":[-79.527412,45.100857],"type":"Point"}
}