{
  "type": "Feature",
  "properties": {
    "addr:full":"Mission BC V2V 1A3",
    "addr:postcode":"v2v 1a3",
    "iso:country":"CA",
    "sg:city":"Mission",
    "sg:classifiers":[
        {
            "category":"Retail",
            "subcategory":"Animal Services",
            "type":"Services"
        }
    ],
    "sg:phone":"+1 604 820 0891",
    "sg:postcode":"V2V 1A3",
    "sg:province":"BC",
    "sg:tags":[
        "pet",
        "grooming",
        "washing"
    ],
    "wof:name":"Bark Avenue Dog Grooming",
    "wof:placetype":"venue"
},
  "geometry": {"coordinates":[-122.33635711700001,49.1331748962],"type":"Point"}
}