{
  "type": "Feature",
  "properties": {
    "addr:full":"300 Rue Notre-Dame-DE-Fatima Laval QC H7G 3Y9",
    "addr:housenumber":"300",
    "addr:postcode":"qc h7g 3y9",
    "addr:street":"Rue Notre-Dame-De-Fatima",
    "iso:country":"CA",
    "sg:address":"300 Rue Notre-Dame-DE-Fatima",
    "sg:city":"Laval",
    "sg:classifiers":[
        {
            "category":"Professional",
            "subcategory":"Computer Services",
            "type":"Services"
        }
    ],
    "sg:phone":"+1 450 667 2020",
    "sg:postcode":"H7G 3Y9",
    "sg:province":"QC",
    "sg:tags":[
        "website",
        "design"
    ],
    "wof:name":"Alliance Webaxis",
    "wof:placetype":"venue"
},
  "geometry": {"coordinates":[-73.67729187010001,45.5751686096],"type":"Point"}
}