{
  "type": "Feature",
  "properties": {
    "addr:full":"911 Watters Rd Orleans ON K4A 3K5",
    "addr:housenumber":"911",
    "addr:postcode":"k4a 3k5",
    "addr:street":"Watters Rd",
    "iso:country":"CA",
    "sg:address":"911 Watters Rd",
    "sg:city":"Orleans",
    "sg:classifiers":[
        {
            "category":"Food & Beverages",
            "subcategory":"Bakery",
            "type":"Retail Goods"
        }
    ],
    "sg:phone":"+1 613 590 2458",
    "sg:postcode":"K4A 3K5",
    "sg:province":"ON",
    "sg:tags":[
        "tea",
        "coffee",
        "doughnut"
    ],
    "wof:name":"Tim Horton's",
    "wof:placetype":"venue"
},
  "geometry": {"coordinates":[-75.475677,45.483093],"type":"Point"}
}