{
  "type": "Feature",
  "properties": {
    "iso:country":"CA",
    "sg:address":"14207 78 St NW",
    "sg:city":"Edmonton",
    "sg:classifiers":[
        {
            "category":"Manufacturing",
            "subcategory":"Printing",
            "type":"Manufacturing & Wholesale Goods"
        }
    ],
    "sg:phone":"+1 780 414 1118",
    "sg:postcode":"T5C 1H4",
    "sg:province":"AB",
    "sg:tags":[
        "printer"
    ],
    "wof:name":"Printing Fx",
    "wof:placetype":"venue"
},
  "geometry": {"coordinates":[-113.46105194099999,53.6041030884],"type":"Point"}
}