{
  "type": "Feature",
  "properties": {
    "addr:full":"Lethbridge AB T1H 5J1",
    "addr:postcode":"t1h 5j1",
    "iso:country":"CA",
    "sg:city":"Lethbridge",
    "sg:classifiers":[
        {
            "category":"Professional",
            "subcategory":"Management & Consulting",
            "type":"Services"
        }
    ],
    "sg:phone":"+1 403 394 2345",
    "sg:postcode":"T1H 5J1",
    "sg:province":"AB",
    "sg:tags":[
        "poultry",
        "agricultural",
        "bedding",
        "consultant"
    ],
    "wof:name":"Pro J & R Feeds",
    "wof:placetype":"venue"
},
  "geometry": {"coordinates":[-112.784164,49.723034],"type":"Point"}
}