{
  "type": "Feature",
  "properties": {
    "addr:full":"West Guilford ON K0M 2S0",
    "addr:postcode":"k0m 2s0",
    "addr:street":"West",
    "iso:country":"CA",
    "sg:city":"West Guilford",
    "sg:classifiers":[
        {
            "category":"Travel",
            "subcategory":"Campground",
            "type":"Entertainment"
        }
    ],
    "sg:phone":"+1 705 754 2507",
    "sg:postcode":"K0M 2S0",
    "sg:province":"ON",
    "sg:tags":[
        "camp"
    ],
    "wof:name":"Camp Kakeka",
    "wof:placetype":"venue"
},
  "geometry": {"coordinates":[-78.600525,45.109039],"type":"Point"}
}