{
  "type": "Feature",
  "properties": {
    "iso:country":"CA",
    "sg:city":"Alert Bay",
    "sg:classifiers":[
        {
            "category":"Government",
            "subcategory":"Office",
            "type":"Public Place"
        }
    ],
    "sg:phone":"+1 250 974 5213",
    "sg:postcode":"V0N 1A0",
    "sg:province":"BC",
    "sg:tags":[
        "village"
    ],
    "wof:name":"Alert Bay Village Offices",
    "wof:placetype":"venue"
},
  "geometry": {"coordinates":[-126.90657043500001,50.5772018433],"type":"Point"}
}