{
  "type": "Feature",
  "properties": {
    "addr:full":"108 Ranleigh Ave Toronto ON M4N 1W9",
    "addr:housenumber":"108",
    "addr:postcode":"m4n 1w9",
    "addr:street":"Ranleigh Ave",
    "iso:country":"CA",
    "sg:address":"108 Ranleigh Ave",
    "sg:city":"Toronto",
    "sg:classifiers":[
        {
            "category":"Professional",
            "subcategory":"Art Services",
            "type":"Services"
        }
    ],
    "sg:phone":"+1 416 487 2019",
    "sg:postcode":"M4N 1W9",
    "sg:province":"ON",
    "sg:tags":[
        "graphic",
        "designer"
    ],
    "wof:name":"David Shaw & Assoc Ltd",
    "wof:placetype":"venue"
},
  "geometry": {"coordinates":[-79.399765,43.728348],"type":"Point"}
}