{
  "type": "Feature",
  "properties": {
    "addr:full":"102757 Grey Road 18 Owen Sound ON N4K 5N6",
    "addr:housenumber":"102757",
    "addr:postcode":"n4k 5n6",
    "addr:street":"Grey Road 18",
    "iso:country":"CA",
    "sg:address":"102757 Grey Road 18",
    "sg:city":"Owen Sound",
    "sg:classifiers":[
        {
            "category":"Wholesale",
            "subcategory":"Electrical",
            "type":"Manufacturing & Wholesale Goods"
        }
    ],
    "sg:phone":"+1 519 372 0957",
    "sg:postcode":"N4K 5N6",
    "sg:province":"ON",
    "sg:tags":[
        "electric",
        "motor"
    ],
    "wof:name":"Brian's Electric Pumps & Motor",
    "wof:placetype":"venue"
},
  "geometry": {"coordinates":[-80.942604,44.564877],"type":"Point"}
}