{
  "type": "Feature",
  "properties": {
    "addr:full":"151 Main St E # 123 Hawkesbury ON K6A 1A1",
    "addr:housenumber":"151",
    "addr:postcode":"k6a 1a1",
    "addr:street":"Main St E # 123",
    "iso:country":"CA",
    "sg:address":"151 Main St E # 123",
    "sg:city":"Hawkesbury",
    "sg:classifiers":[
        {
            "category":"Shopping",
            "type":"Retail Goods"
        }
    ],
    "sg:phone":"+1 613 632 4505",
    "sg:postcode":"K6A 1A1",
    "sg:province":"ON",
    "sg:tags":[
        "hearing",
        "equipment",
        "supply",
        "impaired"
    ],
    "wof:name":"Hawkesbury Audiology Svc",
    "wof:placetype":"venue"
},
  "geometry": {"coordinates":[-74.61037445069999,45.6097564697],"type":"Point"}
}