{
  "type": "Feature",
  "properties": {
    "iso:country":"CA",
    "sg:address":"777 Jarvis St",
    "sg:city":"Toronto",
    "sg:classifiers":[
        {
            "category":"Communications",
            "subcategory":"Radio Station",
            "type":"Services"
        }
    ],
    "sg:phone":"+1 416 935 8200",
    "sg:postcode":"M4Y 3B7",
    "sg:province":"ON",
    "sg:tags":[
        "company",
        "broadcasting"
    ],
    "wof:name":"Rogers Media Inc",
    "wof:placetype":"venue"
},
  "geometry": {"coordinates":[-79.38042449949999,43.6715278625],"type":"Point"}
}