{
  "type": "Feature",
  "properties": {
    "addr:full":"Gunning Cove Shelburne NS B0T 1W0",
    "addr:postcode":"b0t 1w0",
    "iso:country":"CA",
    "sg:address":"Gunning Cove",
    "sg:city":"Shelburne",
    "sg:classifiers":[
        {
            "category":"Organizations",
            "subcategory":"Religious Organization",
            "type":"Services"
        }
    ],
    "sg:phone":"+1 902 875 3358",
    "sg:postcode":"B0T 1W0",
    "sg:province":"NS",
    "sg:tags":[
        "church"
    ],
    "wof:name":"St Paul's United Church Hall",
    "wof:placetype":"venue"
},
  "geometry": {"coordinates":[-65.31564331049999,43.7656593323],"type":"Point"}
}