{
  "type": "Feature",
  "properties": {
    "addr:full":"2183 Rue Monterey Laval QC H7L 3T6",
    "addr:housenumber":"2183",
    "addr:postcode":"h7l 3t6",
    "addr:street":"Rue Monterey",
    "iso:country":"CA",
    "sg:address":"2183 Rue Monterey",
    "sg:city":"Laval",
    "sg:classifiers":[
        {
            "category":"Building & Trades",
            "subcategory":"Construction",
            "type":"Services"
        }
    ],
    "sg:phone":"+1 450 682 0703",
    "sg:postcode":"H7L 3T6",
    "sg:province":"QC",
    "sg:tags":[
        "roofing",
        "contractor"
    ],
    "wof:name":"Marc Filiatreault Couvreur Inc",
    "wof:placetype":"venue"
},
  "geometry": {"coordinates":[-73.75657653810001,45.5828971863],"type":"Point"}
}