{
  "type": "Feature",
  "properties": {
    "addr:full":"50 Mackenzie Dr Yorkton SK S3N 3H5",
    "addr:housenumber":"50",
    "addr:postcode":"s3n 3h5",
    "addr:street":"Mackenzie Dr",
    "iso:country":"CA",
    "sg:address":"50 Mackenzie Dr",
    "sg:city":"Yorkton",
    "sg:classifiers":[
        {
            "category":"Professional",
            "subcategory":"Accounting & Tax Preparation",
            "type":"Services"
        }
    ],
    "sg:phone":"+1 306 783 3607",
    "sg:postcode":"S3N 3H5",
    "sg:province":"SK",
    "sg:tags":[
        "bookkeeping",
        "system",
        "general"
    ],
    "wof:name":"Lsf Accounting",
    "wof:placetype":"venue"
},
  "geometry": {"coordinates":[-102.44261899999999,51.220989],"type":"Point"}
}