{
  "type": "Feature",
  "properties": {
    "addr:full":"Markham ON L3P 5X4",
    "addr:postcode":"l3p 5x4",
    "iso:country":"CA",
    "sg:city":"Markham",
    "sg:classifiers":[
        {
            "category":"Shopping",
            "subcategory":"Pharmacy",
            "type":"Retail Goods"
        }
    ],
    "sg:phone":"+1 905 471 6010",
    "sg:postcode":"L3P 5X4",
    "sg:province":"ON",
    "wof:name":"16th Avenue Drug Mart",
    "wof:placetype":"venue"
},
  "geometry": {"coordinates":[-79.2500152588,43.8950195312],"type":"Point"}
}