{
  "type": "Feature",
  "properties": {
    "addr:full":"355 Wilson Ave North York ON M3H 1T3",
    "addr:housenumber":"355",
    "addr:postcode":"m3h 1t3",
    "addr:street":"Wilson Ave",
    "iso:country":"CA",
    "sg:address":"355 Wilson Ave",
    "sg:city":"North York",
    "sg:classifiers":[
        {
            "category":"Restaurant",
            "type":"Food & Drink"
        }
    ],
    "sg:phone":"+1 416 635 6812",
    "sg:postcode":"M3H 1T3",
    "sg:province":"ON",
    "wof:name":"Aristokrat Bbq Restaurant",
    "wof:placetype":"venue"
},
  "geometry": {"coordinates":[-79.436806,43.736763],"type":"Point"}
}