{
  "type": "Feature",
  "properties": {
    "addr:full":"49 Rue Principale Saint-Boniface-DE-Shawinigan QC G0X 2L0",
    "addr:housenumber":"49",
    "addr:postcode":"g0x 2l0",
    "addr:street":"Rue Principale",
    "iso:country":"CA",
    "sg:address":"49 Rue Principale",
    "sg:city":"Saint-Boniface-DE-Shawinigan",
    "sg:classifiers":[
        {
            "category":"Restaurant",
            "type":"Food & Drink"
        }
    ],
    "sg:phone":"+1 819 535 9510",
    "sg:postcode":"G0X 2L0",
    "sg:province":"QC",
    "wof:name":"Auberge LA Boulangere",
    "wof:placetype":"venue"
},
  "geometry": {"coordinates":[-72.8290939331,46.5050048828],"type":"Point"}
}