{
  "type": "Feature",
  "properties": {
    "addr:full":"475 Pine Ave W Montreal QC H3B 3A9",
    "addr:housenumber":"475",
    "addr:postcode":"h3b 3a9",
    "addr:street":"Pine Ave W",
    "iso:country":"CA",
    "sg:address":"475 Pine Ave W",
    "sg:city":"Montreal",
    "sg:classifiers":[
        {
            "category":"Arena",
            "subcategory":"Sports Club",
            "type":"Entertainment"
        }
    ],
    "sg:phone":"+1 514 871 2266",
    "sg:postcode":"H3B 3A9",
    "sg:province":"QC",
    "sg:tags":[
        "athletic",
        "fields",
        "stadium"
    ],
    "wof:name":"Molson Stadium",
    "wof:placetype":"venue"
},
  "geometry": {"coordinates":[-73.57939910890001,45.5097961426],"type":"Point"}
}