{
  "type": "Feature",
  "properties": {
    "addr:full":"409 19E Rue Saint-Redempteur QC G6K 1K8",
    "addr:housenumber":"409",
    "addr:postcode":"g6k 1k8",
    "addr:street":"19E Rue Saint-Redempteur",
    "iso:country":"CA",
    "sg:address":"409 19E Rue",
    "sg:city":"Saint-Redempteur",
    "sg:classifiers":[
        {
            "category":"Manufacturing",
            "subcategory":"Metals",
            "type":"Manufacturing & Wholesale Goods"
        }
    ],
    "sg:phone":"+1 418 831 0567",
    "sg:postcode":"G6K 1K8",
    "sg:province":"QC",
    "sg:tags":[
        "shelter",
        "garage",
        "temporary"
    ],
    "wof:name":"Auvents Serge Bilodeau Inc",
    "wof:placetype":"venue"
},
  "geometry": {"coordinates":[-71.2949371338,46.6962127686],"type":"Point"}
}