{
  "type": "Feature",
  "properties": {
    "addr:full":"4660 Blackcomb Way Whistler BC V0N 1B4",
    "addr:housenumber":"4660",
    "addr:postcode":"v0n 1b4",
    "addr:street":"Blackcomb Way",
    "iso:country":"CA",
    "sg:address":"4660 Blackcomb Way",
    "sg:city":"Whistler",
    "sg:classifiers":[
        {
            "category":"Travel",
            "subcategory":"Hotels & Motels",
            "type":"Entertainment"
        }
    ],
    "sg:phone":"+1 604 905 7631",
    "sg:postcode":"V0N 1B4",
    "sg:province":"BC",
    "wof:name":"Lost Lake Lodge",
    "wof:placetype":"venue"
},
  "geometry": {"coordinates":[-122.934997559,50.1221618652],"type":"Point"}
}