{
  "type": "Feature",
  "properties": {
    "addr:full":"15 West Ave N Hamilton ON L8L 5B9",
    "addr:housenumber":"15",
    "addr:postcode":"l8l 5b9",
    "addr:street":"West Ave N",
    "iso:country":"CA",
    "sg:address":"15 West Ave N",
    "sg:city":"Hamilton",
    "sg:classifiers":[
        {
            "category":"Retail",
            "subcategory":"Funeral Services",
            "type":"Services"
        }
    ],
    "sg:phone":"+1 905 522 2496",
    "sg:postcode":"L8L 5B9",
    "sg:province":"ON",
    "sg:tags":[
        "director"
    ],
    "wof:name":"Dodsworth & Brown Funeral Home",
    "wof:placetype":"venue"
},
  "geometry": {"coordinates":[-79.85807800000001,43.253838],"type":"Point"}
}