{
  "type": "Feature",
  "properties": {
    "addr:full":"474 Wentworth St N Hamilton ON L8L 5W8",
    "addr:housenumber":"474",
    "addr:postcode":"l8l 5w8",
    "addr:street":"Wentworth St N",
    "iso:country":"CA",
    "sg:address":"474 Wentworth St N",
    "sg:city":"Hamilton",
    "sg:classifiers":[
        {
            "category":"Organizations",
            "subcategory":"Religious Organization",
            "type":"Services"
        }
    ],
    "sg:phone":"+1 905 522 1355",
    "sg:postcode":"L8L 5W8",
    "sg:province":"ON",
    "sg:tags":[
        "church"
    ],
    "wof:name":"St David's Presbyterian Church",
    "wof:placetype":"venue"
},
  "geometry": {"coordinates":[-79.842873,43.26598],"type":"Point"}
}