{
  "type": "Feature",
  "properties": {
    "addr:full":"Cap-DE-LA-Madeleine QC G8T 6Y6",
    "addr:postcode":"g8t 6y6",
    "iso:country":"CA",
    "sg:city":"Cap-DE-LA-Madeleine",
    "sg:classifiers":[
        {
            "category":"Insurance",
            "subcategory":"Insurance Agent",
            "type":"Services"
        }
    ],
    "sg:phone":"+1 819 376 4447",
    "sg:postcode":"G8T 6Y6",
    "sg:province":"QC",
    "wof:name":"Desjardins Financial Security",
    "wof:placetype":"venue"
},
  "geometry": {"coordinates":[-72.53746032710001,46.3762550354],"type":"Point"}
}