{
  "type": "Feature",
  "properties": {
    "iso:country":"CA",
    "sg:address":"219 Lakeshore Rd E",
    "sg:city":"Mississauga",
    "sg:classifiers":[
        {
            "category":"Arts & Performance",
            "subcategory":"Theater",
            "type":"Entertainment"
        }
    ],
    "sg:phone":"+1 905 274 8018",
    "sg:postcode":"L5G 1G5",
    "sg:province":"ON",
    "sg:tags":[
        "pet",
        "shop",
        "entertainer"
    ],
    "wof:name":"Port Credit Pet Ctr",
    "wof:placetype":"venue"
},
  "geometry": {"coordinates":[-79.5778961182,43.5586471558],"type":"Point"}
}