{
  "type": "Feature",
  "properties": {
    "addr:full":"112 Railway St S Pilot Mound MB R0G 1P0",
    "addr:housenumber":"112",
    "addr:postcode":"r0g 1p0",
    "addr:street":"Railway St S Pilot Mound",
    "iso:country":"CA",
    "sg:address":"112 Railway St S",
    "sg:city":"Pilot Mound",
    "sg:classifiers":[
        {
            "category":"Shopping",
            "subcategory":"Catalog Store",
            "type":"Retail Goods"
        }
    ],
    "sg:phone":"+1 204 825 2543",
    "sg:postcode":"R0G 1P0",
    "sg:province":"MB",
    "sg:tags":[
        "mail",
        "order",
        "internet"
    ],
    "wof:name":"Sears Canada Inc",
    "wof:placetype":"venue"
},
  "geometry": {"coordinates":[-98.8960723877,49.202381134],"type":"Point"}
}