{
  "type": "Feature",
  "properties": {
    "addr:full":"104 Route 104 Keswick NB E6L 2A2",
    "addr:housenumber":"104",
    "addr:postcode":"e6l 2a2",
    "addr:street":"Route 104",
    "iso:country":"CA",
    "sg:address":"104 Route 104",
    "sg:city":"Keswick",
    "sg:classifiers":[
        {
            "category":"Wholesale",
            "subcategory":"Poultry",
            "type":"Manufacturing & Wholesale Goods"
        }
    ],
    "sg:phone":"+1 506 363 3092",
    "sg:postcode":"E6L 2A2",
    "sg:province":"NB",
    "sg:tags":[
        "eggs"
    ],
    "wof:name":"Dunphy's Poultry Farm Ltd",
    "wof:placetype":"venue"
},
  "geometry": {"coordinates":[-66.82936100000001,46.000092],"type":"Point"}
}