{
  "type": "Feature",
  "properties": {
    "addr:full":"54 Bryant Crt Brampton ON L6X 2T1",
    "addr:housenumber":"54",
    "addr:postcode":"l6x 2t1",
    "addr:street":"Bryant Crt",
    "iso:country":"CA",
    "sg:address":"54 Bryant Crt",
    "sg:city":"Brampton",
    "sg:classifiers":[
        {
            "category":"Building & Trades",
            "subcategory":"Plumbing",
            "type":"Services"
        }
    ],
    "sg:phone":"+1 905 455 3469",
    "sg:postcode":"L6X 2T1",
    "sg:province":"ON",
    "sg:tags":[
        "contractor"
    ],
    "wof:name":"Acadian Mechanical",
    "wof:placetype":"venue"
},
  "geometry": {"coordinates":[-79.77866400000001,43.696545],"type":"Point"}
}