{
  "type": "Feature",
  "properties": {
    "addr:full":"Toronto ON M5S 2B4",
    "addr:postcode":"m5s 2b4",
    "iso:country":"CA",
    "sg:city":"Toronto",
    "sg:classifiers":[
        {
            "category":"Shopping",
            "subcategory":"Optical Goods",
            "type":"Retail Goods"
        }
    ],
    "sg:phone":"+1 416 922 5093",
    "sg:postcode":"M5S 2B4",
    "sg:province":"ON",
    "sg:tags":[
        "optician"
    ],
    "wof:name":"Cristall Opticians",
    "wof:placetype":"venue"
},
  "geometry": {"coordinates":[-79.38935089109999,43.6690292358],"type":"Point"}
}