{
  "type": "Feature",
  "properties": {
    "addr:full":"165 Boul Sainte-Anne O Sainte-Anne-Des-Monts QC G4V 1R7",
    "addr:housenumber":"165",
    "addr:postcode":"g4v 1r7",
    "addr:street":"Boul Sainte-Anne O",
    "iso:country":"CA",
    "sg:address":"165 Boul Sainte-Anne O",
    "sg:city":"Sainte-Anne-Des-Monts",
    "sg:classifiers":[
        {
            "category":"Retail",
            "subcategory":"Funeral Services",
            "type":"Services"
        }
    ],
    "sg:phone":"+1 418 763 3131",
    "sg:postcode":"G4V 1R7",
    "sg:province":"QC",
    "sg:tags":[
        "director"
    ],
    "wof:name":"Residence Funeraire J Landry",
    "wof:placetype":"venue"
},
  "geometry": {"coordinates":[-66.48639678959999,49.1292152405],"type":"Point"}
}