{
  "type": "Feature",
  "properties": {
    "addr:full":"248 11th Ave E Vancouver BC V5T 2C3",
    "addr:housenumber":"248",
    "addr:postcode":"v5t 2c3",
    "addr:street":"11Th Ave E",
    "iso:country":"CA",
    "sg:address":"248 11th Ave E",
    "sg:city":"Vancouver",
    "sg:classifiers":[
        {
            "category":"Organizations",
            "subcategory":"Religious Organization",
            "type":"Services"
        }
    ],
    "sg:phone":"+1 604 709 0248",
    "sg:postcode":"V5T 2C3",
    "sg:province":"BC",
    "sg:tags":[
        "church"
    ],
    "wof:name":"Gold Buddha Monastery",
    "wof:placetype":"venue"
},
  "geometry": {"coordinates":[-123.099251,49.261002],"type":"Point"}
}