{
  "type": "Feature",
  "properties": {
    "addr:full":"1751 Brigantine Dr Coquitlam BC V3K 7B4",
    "addr:housenumber":"1751",
    "addr:postcode":"v3k 7b4",
    "addr:street":"Brigantine Dr",
    "iso:country":"CA",
    "sg:address":"1751 Brigantine Dr",
    "sg:city":"Coquitlam",
    "sg:classifiers":[
        {
            "category":"Manufacturing",
            "subcategory":"Food",
            "type":"Manufacturing & Wholesale Goods"
        }
    ],
    "sg:phone":"+1 604 516 0199",
    "sg:postcode":"V3K 7B4",
    "sg:province":"BC",
    "sg:tags":[
        "grocer",
        "health"
    ],
    "wof:name":"Rhema Industries Ltd",
    "wof:placetype":"venue"
},
  "geometry": {"coordinates":[-122.842636,49.224819],"type":"Point"}
}