{
  "type": "Feature",
  "properties": {
    "addr:full":"560 Anne St N Barrie ON L4M 4S4",
    "addr:housenumber":"560",
    "addr:postcode":"l4m 4s4",
    "addr:street":"Anne St N",
    "iso:country":"CA",
    "sg:address":"560 Anne St N",
    "sg:city":"Barrie",
    "sg:classifiers":[
        {
            "category":"Insurance",
            "subcategory":"Insurance Agent",
            "type":"Services"
        }
    ],
    "sg:phone":"+1 705 721 9659",
    "sg:postcode":"L4M 4S4",
    "sg:province":"ON",
    "wof:name":"Wise Riddell Financial Group",
    "wof:placetype":"venue"
},
  "geometry": {"coordinates":[-79.7271652222,44.4078903198],"type":"Point"}
}