{
  "type": "Feature",
  "properties": {
    "addr:full":"4560 Rue Cardinal Ascot Corner QC J0B 1A0",
    "addr:housenumber":"4560",
    "addr:postcode":"j0b 1a0",
    "addr:street":"Rue Cardinal",
    "iso:country":"CA",
    "sg:address":"4560 Rue Cardinal",
    "sg:city":"Ascot Corner",
    "sg:classifiers":[
        {
            "category":"Building & Trades",
            "subcategory":"Landscaping Services",
            "type":"Services"
        }
    ],
    "sg:phone":"+1 819 563 9105",
    "sg:postcode":"J0B 1A0",
    "sg:province":"QC",
    "sg:tags":[
        "landscape",
        "contractor"
    ],
    "wof:name":"Terrassement DE L'Estrie Enr",
    "wof:placetype":"venue"
},
  "geometry": {"coordinates":[-71.8076705933,45.437625885],"type":"Point"}
}