{
  "type": "Feature",
  "properties": {
    "addr:full":"PO Box 6558 STN Main Bonnyville AB T9N 2H1",
    "addr:housenumber":"po",
    "addr:postcode":"t9n 2h1",
    "addr:street":"Box 6558 Stn Main",
    "iso:country":"CA",
    "sg:address":"PO Box 6558 STN Main",
    "sg:city":"Bonnyville",
    "sg:classifiers":[
        {
            "category":"Building & Trades",
            "subcategory":"Construction",
            "type":"Services"
        }
    ],
    "sg:phone":"+1 780 812 5539",
    "sg:postcode":"T9N 2H1",
    "sg:province":"AB",
    "sg:tags":[
        "excavating",
        "contractor"
    ],
    "wof:name":"Minor Trenching",
    "wof:placetype":"venue"
},
  "geometry": {"coordinates":[-110.75366200000001,54.267956],"type":"Point"}
}