{
  "type": "Feature",
  "properties": {
    "addr:full":"6315 90 Ave NW Edmonton AB T6B 0P1",
    "addr:housenumber":"6315",
    "addr:postcode":"t6b 0p1",
    "addr:street":"90 Ave Nw",
    "iso:country":"CA",
    "sg:address":"6315 90 Ave NW",
    "sg:city":"Edmonton",
    "sg:classifiers":[
        {
            "category":"Retail",
            "subcategory":"Auto Repair",
            "type":"Services"
        }
    ],
    "sg:phone":"+1 780 448 0826",
    "sg:postcode":"T6B 0P1",
    "sg:province":"AB",
    "sg:tags":[
        "automobile",
        "co",
        "drive",
        "transporter"
    ],
    "wof:name":"Galaxy Road Svc Ltd",
    "wof:placetype":"venue"
},
  "geometry": {"coordinates":[-113.428085,53.52441],"type":"Point"}
}