{
  "type": "Feature",
  "properties": {
    "addr:full":"31 Mill St Georgetown ON L7G 2H6",
    "addr:housenumber":"31",
    "addr:postcode":"l7g 2h6",
    "addr:street":"Mill St",
    "iso:country":"CA",
    "sg:address":"31 Mill St",
    "sg:city":"Georgetown",
    "sg:classifiers":[
        {
            "category":"Wholesale",
            "subcategory":"Electrical",
            "type":"Manufacturing & Wholesale Goods"
        }
    ],
    "sg:phone":"+1 519 853 8677",
    "sg:postcode":"L7G 2H6",
    "sg:province":"ON",
    "sg:tags":[
        "control",
        "security",
        "system"
    ],
    "wof:name":"K M Video",
    "wof:placetype":"venue"
},
  "geometry": {"coordinates":[-79.92366,43.652382],"type":"Point"}
}