{
  "type": "Feature",
  "properties": {
    "iso:country":"CA",
    "sg:address":"2024 Ottawa St",
    "sg:city":"Windsor",
    "sg:classifiers":[
        {
            "category":"Shopping",
            "subcategory":"Clothing, Apparel, & Fashions",
            "type":"Retail Goods"
        }
    ],
    "sg:phone":"+1 519 255 7134",
    "sg:postcode":"N8Y 1R7",
    "sg:province":"ON",
    "sg:tags":[
        "tailor"
    ],
    "wof:name":"Mak's Alterations",
    "wof:placetype":"venue"
},
  "geometry": {"coordinates":[-83.0050735474,42.3125495911],"type":"Point"}
}