{
  "type": "Feature",
  "properties": {
    "iso:country":"CA",
    "sg:address":"2 Rayborn Cres",
    "sg:city":"St Albert",
    "sg:classifiers":[
        {
            "category":"Building & Trades",
            "subcategory":"Construction",
            "type":"Services"
        }
    ],
    "sg:phone":"+1 780 458 7807",
    "sg:postcode":"T8N 5C5",
    "sg:province":"AB",
    "sg:tags":[
        "equipment",
        "station"
    ],
    "wof:name":"4-Way Petroleum Svc Ltd",
    "wof:placetype":"venue"
},
  "geometry": {"coordinates":[-113.643371582,53.6231956482],"type":"Point"}
}