{
  "type": "Feature",
  "properties": {
    "addr:full":"5807 104 St NW # 200 Edmonton AB T6H 2K4",
    "addr:housenumber":"5807",
    "addr:postcode":"t6h 2k4",
    "addr:street":"104 St Nw # 200",
    "iso:country":"CA",
    "sg:address":"5807 104 St NW # 200",
    "sg:city":"Edmonton",
    "sg:classifiers":[
        {
            "category":"Insurance",
            "subcategory":"Insurance Agent",
            "type":"Services"
        }
    ],
    "sg:phone":"+1 780 433 7200",
    "sg:postcode":"T6H 2K4",
    "sg:province":"AB",
    "wof:name":"Ted Byrt Insurance Ltd",
    "wof:placetype":"venue"
},
  "geometry": {"coordinates":[-113.49745900000001,53.495281],"type":"Point"}
}