{
  "type": "Feature",
  "properties": {
    "iso:country":"CA",
    "sg:city":"Richmond",
    "sg:classifiers":[
        {
            "category":"Home & Garden",
            "subcategory":"Home Furnishings",
            "type":"Retail Goods"
        }
    ],
    "sg:phone":"+1 604 270 4641",
    "sg:postcode":"V6V 1J4",
    "sg:province":"BC",
    "sg:tags":[
        "lighting",
        "fixture"
    ],
    "wof:name":"Vancouver Lighting",
    "wof:placetype":"venue"
},
  "geometry": {"coordinates":[-123.083282471,49.1921958923],"type":"Point"}
}