{
  "type": "Feature",
  "properties": {
    "addr:full":"Thunder Bay ON P7A 7Z1",
    "addr:postcode":"p7a 7z1",
    "iso:country":"CA",
    "sg:city":"Thunder Bay",
    "sg:classifiers":[
        {
            "category":"Real Estate",
            "subcategory":"Real Estate Operator",
            "type":"Services"
        }
    ],
    "sg:phone":"+1 807 344 6677",
    "sg:postcode":"P7A 7Z1",
    "sg:province":"ON",
    "sg:tags":[
        "apartment"
    ],
    "wof:name":"Parkview Place Apartments",
    "wof:placetype":"venue"
},
  "geometry": {"coordinates":[-89.206284,48.465122],"type":"Point"}
}