{
  "type": "Feature",
  "properties": {
    "addr:full":"House 65 Little Grand Rapids MB R0B 0V0",
    "addr:housenumber":"65",
    "addr:postcode":"r0b 0v0",
    "addr:street":"Little Grand",
    "iso:country":"CA",
    "sg:address":"House 65",
    "sg:city":"Little Grand Rapids",
    "sg:classifiers":[
        {
            "category":"Organizations",
            "subcategory":"Professional Association",
            "type":"Services"
        }
    ],
    "sg:phone":"+1 204 397 2407",
    "sg:postcode":"R0B 0V0",
    "sg:province":"MB",
    "sg:tags":[
        "native"
    ],
    "wof:name":"Southeast Child & Family Svc",
    "wof:placetype":"venue"
},
  "geometry": {"coordinates":[-99.2845077515,53.1849594116],"type":"Point"}
}