{
  "type": "Feature",
  "properties": {
    "addr:full":"2560 Matheson Blvd E # 120 Mississauga ON L4W 4Y9",
    "addr:housenumber":"2560",
    "addr:postcode":"l4w 4y9",
    "addr:street":"Matheson Blvd E # 120",
    "iso:country":"CA",
    "sg:address":"2560 Matheson Blvd E # 120",
    "sg:city":"Mississauga",
    "sg:classifiers":[
        {
            "category":"Professional",
            "subcategory":"Management & Consulting",
            "type":"Services"
        }
    ],
    "sg:phone":"+1 905 625 0909",
    "sg:postcode":"L4W 4Y9",
    "sg:province":"ON",
    "sg:tags":[
        "consultant",
        "business"
    ],
    "wof:name":"Omnex Canada Inc",
    "wof:placetype":"venue"
},
  "geometry": {"coordinates":[-79.60209655760001,43.6595497131],"type":"Point"}
}