{
  "type": "Feature",
  "properties": {
    "addr:full":"2282 Av Saint-Marc Shawinigan QC G9N 2J6",
    "addr:housenumber":"2282",
    "addr:postcode":"g9n 2j6",
    "addr:street":"Av Saint-Marc",
    "iso:country":"CA",
    "sg:address":"2282 Av Saint-Marc",
    "sg:city":"Shawinigan",
    "sg:classifiers":[
        {
            "category":"Bars & Pubs",
            "type":"Food & Drink"
        }
    ],
    "sg:phone":"+1 819 537 9947",
    "sg:postcode":"G9N 2J6",
    "sg:province":"QC",
    "wof:name":"Taverne Moderne",
    "wof:placetype":"venue"
},
  "geometry": {"coordinates":[-72.740059,46.555035],"type":"Point"}
}