{
  "type": "Feature",
  "properties": {
    "addr:full":"300 Westminster Ave W Penticton BC V2A 1K2",
    "addr:housenumber":"300",
    "addr:postcode":"v2a 1k2",
    "addr:street":"Westminster Ave W",
    "iso:country":"CA",
    "sg:address":"300 Westminster Ave W",
    "sg:city":"Penticton",
    "sg:classifiers":[
        {
            "category":"Shopping",
            "subcategory":"Bicycles & Sporting Goods",
            "type":"Retail Goods"
        }
    ],
    "sg:phone":"+1 250 492 4140",
    "sg:postcode":"V2A 1K2",
    "sg:province":"BC",
    "wof:name":"Bike Barn",
    "wof:placetype":"venue"
},
  "geometry": {"coordinates":[-119.59783899999999,49.499271],"type":"Point"}
}