{
  "type": "Feature",
  "properties": {
    "iso:country":"CA",
    "sg:address":"5743 Thorold Stone Rd #2",
    "sg:city":"Niagara Falls",
    "sg:classifiers":[
        {
            "category":"Personal",
            "subcategory":"Beauty Salon",
            "type":"Services"
        }
    ],
    "sg:phone":"+1 905 358 8864",
    "sg:postcode":"L2J 1A1",
    "sg:province":"ON",
    "wof:name":"Athena Beauty Institute",
    "wof:placetype":"venue"
},
  "geometry": {"coordinates":[-79.0907211304,43.1155891418],"type":"Point"}
}