{
  "type": "Feature",
  "properties": {
    "iso:country":"CA",
    "sg:city":"Abbotsford",
    "sg:classifiers":[
        {
            "category":"Health Services",
            "subcategory":"Podiatrist",
            "type":"Services"
        }
    ],
    "sg:phone":"+1 604 853 3338",
    "sg:postcode":"V2S 2J5",
    "sg:province":"BC",
    "wof:name":"Duft, George DPM",
    "wof:placetype":"venue"
},
  "geometry": {"coordinates":[-122.30344390899999,49.0512580872],"type":"Point"}
}