{
  "type": "Feature",
  "properties": {
    "addr:full":"129 Boul Springer Chapais QC G0W 1H0",
    "addr:housenumber":"129",
    "addr:postcode":"g0w 1h0",
    "addr:street":"Boul Springer",
    "iso:country":"CA",
    "sg:address":"129 Boul Springer",
    "sg:city":"Chapais",
    "sg:classifiers":[
        {
            "category":"Home & Garden",
            "subcategory":"Hardware",
            "type":"Retail Goods"
        }
    ],
    "sg:phone":"+1 418 745 2517",
    "sg:postcode":"G0W 1H0",
    "sg:province":"QC",
    "wof:name":"Quincaillerie Rd Inc",
    "wof:placetype":"venue"
},
  "geometry": {"coordinates":[-74.85597229,49.7823181152],"type":"Point"}
}