{
  "type": "Feature",
  "properties": {
    "addr:full":"109 15th St E North Vancouver BC V7L 2P7",
    "addr:housenumber":"109",
    "addr:postcode":"v7l 2p7",
    "addr:street":"15Th St E",
    "iso:country":"CA",
    "sg:address":"109 15th St E",
    "sg:city":"North Vancouver",
    "sg:classifiers":[
        {
            "category":"Retail",
            "subcategory":"Laundry & Dry Cleaning",
            "type":"Services"
        }
    ],
    "sg:phone":"+1 604 987 0244",
    "sg:postcode":"V7L 2P7",
    "sg:province":"BC",
    "sg:tags":[
        "cleaners"
    ],
    "wof:name":"Paul's Tailors & Cleaners Ltd",
    "wof:placetype":"venue"
},
  "geometry": {"coordinates":[-123.071838379,49.3218650818],"type":"Point"}
}