{
  "type": "Feature",
  "properties": {
    "addr:full":"75 Wales St Saint-Andre-D'Argenteuil QC J0V 1X0",
    "addr:housenumber":"75",
    "addr:postcode":"j0v 1x0",
    "addr:street":"Wales St",
    "iso:country":"CA",
    "sg:address":"75 Wales St",
    "sg:city":"Saint-Andre-D'Argenteuil",
    "sg:classifiers":[
        {
            "category":"Wholesale",
            "subcategory":"Electrical",
            "type":"Manufacturing & Wholesale Goods"
        }
    ],
    "sg:phone":"+1 450 537 3311",
    "sg:postcode":"J0V 1X0",
    "sg:province":"QC",
    "sg:tags":[
        "conduit",
        "fitting"
    ],
    "wof:name":"Fre Composites Inc",
    "wof:placetype":"venue"
},
  "geometry": {"coordinates":[-74.338623,45.561836],"type":"Point"}
}