{
  "type": "Feature",
  "properties": {
    "addr:full":"Nanaimo BC V9T 2H1",
    "addr:postcode":"v9t 2h1",
    "iso:country":"CA",
    "sg:city":"Nanaimo",
    "sg:classifiers":[
        {
            "category":"Freight",
            "type":"Transportation"
        }
    ],
    "sg:phone":"+1 250 758 9156",
    "sg:postcode":"V9T 2H1",
    "sg:province":"BC",
    "sg:tags":[
        "mover"
    ],
    "wof:name":"Metro Moving & Storage Ltd",
    "wof:placetype":"venue"
},
  "geometry": {"coordinates":[-124.007156372,49.2032623291],"type":"Point"}
}