{
  "type": "Feature",
  "properties": {
    "iso:country":"CA",
    "sg:address":"85 Renfrew Dr",
    "sg:city":"Markham",
    "sg:classifiers":[
        {
            "category":"Organizations",
            "subcategory":"Professional Association",
            "type":"Services"
        }
    ],
    "sg:phone":"+1 905 940 2800",
    "sg:postcode":"L3R 0N9",
    "sg:province":"ON",
    "wof:name":"Canadian International Auto Sh",
    "wof:placetype":"venue"
},
  "geometry": {"coordinates":[-79.36223602290001,43.858505249],"type":"Point"}
}