{
  "type": "Feature",
  "properties": {
    "addr:full":"10767 148 St Surrey BC V3R 0S4",
    "addr:housenumber":"10767",
    "addr:postcode":"v3r 0s4",
    "addr:street":"148 St",
    "iso:country":"CA",
    "sg:address":"10767 148 St",
    "sg:city":"Surrey",
    "sg:classifiers":[
        {
            "category":"Organizations",
            "subcategory":"Professional Association",
            "type":"Services"
        }
    ],
    "sg:phone":"+1 604 585 2788",
    "sg:postcode":"V3R 0S4",
    "sg:province":"BC",
    "wof:name":"Applied Science Technologists",
    "wof:placetype":"venue"
},
  "geometry": {"coordinates":[-122.81270600000001,49.19817],"type":"Point"}
}