{
  "type": "Feature",
  "properties": {
    "addr:full":"Toronto ON M6C 1C6",
    "addr:postcode":"m6c 1c6",
    "iso:country":"CA",
    "sg:city":"Toronto",
    "sg:classifiers":[
        {
            "category":"Health Services",
            "subcategory":"Medical Lab",
            "type":"Services"
        }
    ],
    "sg:phone":"+1 416 656 6968",
    "sg:postcode":"M6C 1C6",
    "sg:province":"ON",
    "sg:tags":[
        "laboratory"
    ],
    "wof:name":"Sterling Dental Laboratory",
    "wof:placetype":"venue"
},
  "geometry": {"coordinates":[-79.434212,43.680061],"type":"Point"}
}