{
  "type": "Feature",
  "properties": {
    "addr:full":"89 Dufferin Rd Perth ON K7H 3B3",
    "addr:housenumber":"89",
    "addr:postcode":"k7h 3b3",
    "addr:street":"Dufferin Rd",
    "iso:country":"CA",
    "sg:address":"89 Dufferin Rd",
    "sg:city":"Perth",
    "sg:classifiers":[
        {
            "category":"Autos & Motor Vehicles",
            "subcategory":"Fuel & Gas Station",
            "type":"Retail Goods"
        }
    ],
    "sg:phone":"+1 613 264 0668",
    "sg:postcode":"K7H 3B3",
    "sg:province":"ON",
    "sg:tags":[
        "oil"
    ],
    "wof:name":"Perth Esso",
    "wof:placetype":"venue"
},
  "geometry": {"coordinates":[-76.2601852417,44.9141960144],"type":"Point"}
}