{
  "type": "Feature",
  "properties": {
    "addr:full":"1425 Evans Rd Errington BC V0R 1V0",
    "addr:housenumber":"1425",
    "addr:postcode":"v0r 1v0",
    "addr:street":"Evans Rd",
    "iso:country":"CA",
    "sg:address":"1425 Evans Rd",
    "sg:city":"Errington",
    "sg:classifiers":[
        {
            "category":"Manufacturing",
            "subcategory":"Tools & Machinery",
            "type":"Manufacturing & Wholesale Goods"
        }
    ],
    "sg:phone":"+1 250 248 3352",
    "sg:postcode":"V0R 1V0",
    "sg:province":"BC",
    "sg:tags":[
        "machine",
        "shop"
    ],
    "wof:name":"Cullen Machine",
    "wof:placetype":"venue"
},
  "geometry": {"coordinates":[-124.376091,49.289455],"type":"Point"}
}