{
  "type": "Feature",
  "properties": {
    "addr:full":"403 Wiley St Thunder Bay ON P7C 3N1",
    "addr:housenumber":"403",
    "addr:postcode":"p7c 3n1",
    "addr:street":"Wiley St",
    "iso:country":"CA",
    "sg:address":"403 Wiley St",
    "sg:city":"Thunder Bay",
    "sg:classifiers":[
        {
            "category":"Professional",
            "subcategory":"Research",
            "type":"Services"
        }
    ],
    "sg:phone":"+1 807 577 7723",
    "sg:postcode":"P7C 3N1",
    "sg:province":"ON",
    "sg:tags":[
        "environmental",
        "ecological"
    ],
    "wof:name":"Environmental Control Systems",
    "wof:placetype":"venue"
},
  "geometry": {"coordinates":[-89.2444610596,48.3904418945],"type":"Point"}
}