{
  "type": "Feature",
  "properties": {
    "addr:full":"9700 Rue Sherbrooke E Montreal QC H1L 6N8",
    "addr:housenumber":"9700",
    "addr:postcode":"h1l 6n8",
    "addr:street":"Rue Sherbrooke E",
    "iso:country":"CA",
    "sg:address":"9700 Rue Sherbrooke E",
    "sg:city":"Montreal",
    "sg:classifiers":[
        {
            "category":"Building & Trades",
            "subcategory":"Construction",
            "type":"Services"
        }
    ],
    "sg:phone":"+1 514 352 3900",
    "sg:postcode":"H1L 6N8",
    "sg:province":"QC",
    "sg:tags":[
        "builder",
        "stair"
    ],
    "wof:name":"G & S Fer Ornemental Aluminium",
    "wof:placetype":"venue"
},
  "geometry": {"coordinates":[-73.525871,45.611908],"type":"Point"}
}