{
  "type": "Feature",
  "properties": {
    "addr:full":"5004 52nd Ave W Fort Nelson BC V0C 1R0",
    "addr:housenumber":"5004",
    "addr:postcode":"bc v0c 1r0",
    "addr:street":"52Nd Ave W",
    "iso:country":"CA",
    "sg:address":"5004 52nd Ave W",
    "sg:city":"Fort Nelson",
    "sg:classifiers":[
        {
            "category":"Health Services",
            "subcategory":"Doctor",
            "type":"Services"
        }
    ],
    "sg:phone":"+1 250 774 6769",
    "sg:postcode":"V0C 1R0",
    "sg:province":"BC",
    "sg:tags":[
        "clinic",
        "therapist",
        "massage"
    ],
    "wof:name":"Massage Therapy Clinic",
    "wof:placetype":"venue"
},
  "geometry": {"coordinates":[-122.701454,58.807339],"type":"Point"}
}