{
  "type": "Feature",
  "properties": {
    "iso:country":"CA",
    "sg:address":"584 Ontario St",
    "sg:city":"Stratford",
    "sg:classifiers":[
        {
            "category":"Restaurant",
            "type":"Food & Drink"
        }
    ],
    "sg:phone":"+1 519 273 6691",
    "sg:postcode":"N5A 3J5",
    "sg:province":"ON",
    "wof:name":"Williams Coffee Pub",
    "wof:placetype":"venue"
},
  "geometry": {"coordinates":[-80.96264600000001,43.371178],"type":"Point"}
}