{
  "type": "Feature",
  "properties": {
    "addr:full":"480 Ch Duchenier Saint-Narcisse-DE-Rimouski QC G0K 1S0",
    "addr:housenumber":"480",
    "addr:postcode":"g0k 1s0",
    "addr:street":"Ch Duchenier",
    "iso:country":"CA",
    "sg:address":"480 Ch Duchenier",
    "sg:city":"Saint-Narcisse-DE-Rimouski",
    "sg:classifiers":[
        {
            "category":"Food & Beverages",
            "subcategory":"Groceries & Convenience Stores",
            "type":"Retail Goods"
        }
    ],
    "sg:phone":"+1 418 735 2197",
    "sg:postcode":"G0K 1S0",
    "sg:province":"QC",
    "sg:tags":[
        "grocer"
    ],
    "wof:name":"Epicerie Ouellet",
    "wof:placetype":"venue"
},
  "geometry": {"coordinates":[-68.43742399999999,48.287827],"type":"Point"}
}