{
  "type": "Feature",
  "properties": {
    "addr:full":"12 Oakridge Cres Guelph ON N1L 1J1",
    "addr:housenumber":"12",
    "addr:postcode":"n1l 1j1",
    "addr:street":"Oakridge Cres",
    "iso:country":"CA",
    "sg:address":"12 Oakridge Cres",
    "sg:city":"Guelph",
    "sg:classifiers":[
        {
            "category":"Health Services",
            "subcategory":"Clinic",
            "type":"Services"
        }
    ],
    "sg:phone":"+1 519 823 2162",
    "sg:postcode":"N1L 1J1",
    "sg:province":"ON",
    "sg:tags":[
        "school",
        "holistic",
        "practitioner"
    ],
    "wof:name":"Soul Connection",
    "wof:placetype":"venue"
},
  "geometry": {"coordinates":[-80.19347399999999,43.511883],"type":"Point"}
}