{
  "type": "Feature",
  "properties": {
    "addr:full":"386 Skyline Dr Gibsons BC V0N 1V8",
    "addr:housenumber":"386",
    "addr:postcode":"v0n 1v8",
    "addr:street":"Skyline Dr",
    "iso:country":"CA",
    "sg:address":"386 Skyline Dr",
    "sg:city":"Gibsons",
    "sg:classifiers":[
        {
            "category":"Marine",
            "type":"Transportation"
        }
    ],
    "sg:phone":"+1 604 886 7707",
    "sg:postcode":"V0N 1V8",
    "sg:province":"BC",
    "sg:tags":[
        "towing"
    ],
    "wof:name":"Smitty's Towing & Barges",
    "wof:placetype":"venue"
},
  "geometry": {"coordinates":[-123.503440857,49.4034538269],"type":"Point"}
}