{
  "type": "Feature",
  "properties": {
    "iso:country":"CA",
    "sg:address":"26 Rue Sainte-Angele",
    "sg:city":"Quebec",
    "sg:classifiers":[
        {
            "category":"Bars & Pubs",
            "type":"Food & Drink"
        }
    ],
    "sg:phone":"+1 418 692 2171",
    "sg:postcode":"G1R 4G4",
    "sg:province":"QC",
    "sg:tags":[
        "lounge",
        "cocktail"
    ],
    "wof:name":"Bar Ste-Angele",
    "wof:placetype":"venue"
},
  "geometry": {"coordinates":[-71.211739,46.813019],"type":"Point"}
}