{
  "type": "Feature",
  "properties": {
    "addr:full":"170 Barrette St Vanier ON K1L 8A1",
    "addr:housenumber":"170",
    "addr:postcode":"k1l 8a1",
    "addr:street":"Barrette St",
    "iso:country":"CA",
    "sg:address":"170 Barrette St",
    "sg:city":"Vanier",
    "sg:classifiers":[
        {
            "category":"Insurance",
            "subcategory":"Life Insurance",
            "type":"Services"
        }
    ],
    "sg:phone":"+1 613 741 0410",
    "sg:postcode":"K1L 8A1",
    "sg:province":"ON",
    "sg:tags":[
        "consultant",
        "planning",
        "financial"
    ],
    "wof:name":"Burtonshaw, Carol",
    "wof:placetype":"venue"
},
  "geometry": {"coordinates":[-75.67197400000001,45.441296],"type":"Point"}
}