{
  "type": "Feature",
  "properties": {
    "addr:full":"11416 6E Av Montreal QC H1E 1R9",
    "addr:housenumber":"11416",
    "addr:postcode":"h1e 1r9",
    "addr:street":"6E Av",
    "iso:country":"CA",
    "sg:address":"11416 6E Av",
    "sg:city":"Montreal",
    "sg:classifiers":[
        {
            "category":"Home & Garden",
            "subcategory":"Building Materials",
            "type":"Retail Goods"
        }
    ],
    "sg:phone":"+1 514 648 2556",
    "sg:postcode":"H1E 1R9",
    "sg:province":"QC",
    "sg:tags":[
        "type",
        "door"
    ],
    "wof:name":"Astral Porte DE Garage",
    "wof:placetype":"venue"
},
  "geometry": {"coordinates":[-73.596451,45.619038],"type":"Point"}
}