{
  "type": "Feature",
  "properties": {
    "iso:country":"CA",
    "sg:address":"758 Murphy Rd",
    "sg:city":"Sarnia",
    "sg:classifiers":[
        {
            "category":"Building & Trades",
            "subcategory":"Electrical",
            "type":"Services"
        }
    ],
    "sg:phone":"+1 519 337 7468",
    "sg:postcode":"N7S 2X8",
    "sg:province":"ON",
    "sg:tags":[
        "electric",
        "contractor"
    ],
    "wof:name":"Earl Sipkens Electric Ltd",
    "wof:placetype":"venue"
},
  "geometry": {"coordinates":[-82.366257,42.983051],"type":"Point"}
}