{
  "type": "Feature",
  "properties": {
    "addr:full":"169 Rue King O Sherbrooke QC J1H 1P4",
    "addr:housenumber":"169",
    "addr:postcode":"j1h 1p4",
    "addr:street":"Rue King O",
    "iso:country":"CA",
    "sg:address":"169 Rue King O",
    "sg:city":"Sherbrooke",
    "sg:classifiers":[
        {
            "category":"Shopping",
            "subcategory":"Music",
            "type":"Retail Goods"
        }
    ],
    "sg:phone":"+1 819 569 0473",
    "sg:postcode":"J1H 1P4",
    "sg:province":"QC",
    "sg:tags":[
        "compact",
        "record",
        "disc",
        "tape"
    ],
    "wof:name":"Musique Cite Sherbrooke Inc",
    "wof:placetype":"venue"
},
  "geometry": {"coordinates":[-71.88402600000001,45.405304],"type":"Point"}
}