{
  "type": "Feature",
  "properties": {
    "addr:full":"2913 Upper N River Truro NS B2N 5B4",
    "addr:housenumber":"2913",
    "addr:postcode":"b2n 5b4",
    "addr:street":"Upper N River",
    "iso:country":"CA",
    "sg:address":"2913 Upper N River",
    "sg:city":"Truro",
    "sg:classifiers":[
        {
            "category":"Wholesale",
            "subcategory":"Meat",
            "type":"Manufacturing & Wholesale Goods"
        }
    ],
    "sg:phone":"+1 902 897 6116",
    "sg:postcode":"B2N 5B4",
    "sg:province":"NS",
    "sg:tags":[
        "delicatessen",
        "butchering"
    ],
    "wof:name":"Austrian Smokehaus",
    "wof:placetype":"venue"
},
  "geometry": {"coordinates":[-63.28904,45.36602],"type":"Point"}
}