{
  "type": "Feature",
  "properties": {
    "addr:full":"4944 60 Av High Prairie AB T0G 1E0",
    "addr:housenumber":"4944",
    "addr:postcode":"t0g 1e0",
    "addr:street":"60 Av High Prairie",
    "iso:country":"CA",
    "sg:address":"4944 60 Av",
    "sg:city":"High Prairie",
    "sg:classifiers":[
        {
            "category":"Government",
            "subcategory":"Office",
            "type":"Public Place"
        }
    ],
    "sg:phone":"+1 780 523 6665",
    "sg:postcode":"T0G 1E0",
    "sg:province":"AB",
    "wof:name":"Alberta Youth Assessment Ctr",
    "wof:placetype":"venue"
},
  "geometry": {"coordinates":[-116.480423,55.432884],"type":"Point"}
}