{
  "type": "Feature",
  "properties": {
    "iso:country":"CA",
    "sg:address":"527 Mississagua St",
    "sg:city":"Niagara on the Lake",
    "sg:classifiers":[
        {
            "category":"Travel",
            "subcategory":"Hotels & Motels",
            "type":"Entertainment"
        }
    ],
    "sg:phone":"+1 905 468 4138",
    "sg:postcode":"L0S 1J0",
    "sg:province":"ON",
    "sg:tags":[
        "breakfast",
        "accommodation",
        "bed"
    ],
    "wof:name":"Silver Maple Bed & Breakfast",
    "wof:placetype":"venue"
},
  "geometry": {"coordinates":[-79.08551,43.251377],"type":"Point"}
}