{
  "type": "Feature",
  "properties": {
    "iso:country":"CA",
    "sg:address":"RR 1",
    "sg:city":"LA Salette",
    "sg:classifiers":[
        {
            "category":"Farming",
            "subcategory":"Farm & Veterinary Services",
            "type":"Manufacturing & Wholesale Goods"
        }
    ],
    "sg:phone":"+1 519 879 6390",
    "sg:postcode":"N0E 1H0",
    "sg:province":"ON",
    "sg:tags":[
        "seed",
        "grain",
        "cleaning"
    ],
    "wof:name":"Belterre Seeds",
    "wof:placetype":"venue"
},
  "geometry": {"coordinates":[-80.5016708374,42.9024505615],"type":"Point"}
}