{
  "type": "Feature",
  "properties": {
    "addr:full":"2410 Ch Du Lac Saint-Pascal-Baylon ON K0A 3N0",
    "addr:postcode":"2410;k0a 3n0",
    "addr:street":"Ch Du Lac",
    "iso:country":"CA",
    "sg:address":"2410 Ch Du Lac",
    "sg:city":"Saint-Pascal-Baylon",
    "sg:classifiers":[
        {
            "category":"Education",
            "subcategory":"School",
            "type":"Public Place"
        }
    ],
    "sg:phone":"+1 613 488 2494",
    "sg:postcode":"K0A 3N0",
    "sg:province":"ON",
    "wof:name":"Ecole Catholique Du Rosaire",
    "wof:placetype":"venue"
},
  "geometry": {"coordinates":[-75.155197,45.493412],"type":"Point"}
}