{
  "type": "Feature",
  "properties": {
    "addr:full":"1678 Sansonnet St Orleans ON K1C 5Y7",
    "addr:housenumber":"1678",
    "addr:postcode":"k1c 5y7",
    "addr:street":"Sansonnet St",
    "iso:country":"CA",
    "sg:address":"1678 Sansonnet St",
    "sg:city":"Orleans",
    "sg:classifiers":[
        {
            "category":"Manufacturing",
            "subcategory":"Printing",
            "type":"Manufacturing & Wholesale Goods"
        }
    ],
    "sg:phone":"+1 613 830 3336",
    "sg:postcode":"K1C 5Y7",
    "sg:province":"ON",
    "sg:tags":[
        "publisher"
    ],
    "wof:name":"Editions David",
    "wof:placetype":"venue"
},
  "geometry": {"coordinates":[-75.539711,45.446438],"type":"Point"}
}