{
  "type": "Feature",
  "properties": {
    "addr:full":"2945 Boul Laframboise Saint-Hyacinthe QC J2S 4Z3",
    "addr:housenumber":"2945",
    "addr:postcode":"j2s 4z3",
    "addr:street":"Boul Laframboise",
    "iso:country":"CA",
    "sg:address":"2945 Boul Laframboise",
    "sg:city":"Saint-Hyacinthe",
    "sg:classifiers":[
        {
            "category":"Health Services",
            "subcategory":"Doctor",
            "type":"Services"
        }
    ],
    "sg:phone":"+1 450 773 8345",
    "sg:postcode":"J2S 4Z3",
    "sg:province":"QC",
    "sg:tags":[
        "clinic"
    ],
    "wof:name":"Clinique D'Urgence",
    "wof:placetype":"venue"
},
  "geometry": {"coordinates":[-72.96423299999999,45.634289],"type":"Point"}
}