{
  "type": "Feature",
  "properties": {
    "addr:full":"2151 Rue DE Cambrai Saint-Bruno QC J3V 3J4",
    "addr:housenumber":"2151",
    "addr:postcode":"j3v 3j4",
    "addr:street":"Rue De Cambrai",
    "iso:country":"CA",
    "sg:address":"2151 Rue DE Cambrai",
    "sg:city":"Saint-Bruno",
    "sg:classifiers":[
        {
            "category":"Building & Trades",
            "subcategory":"Landscaping Services",
            "type":"Services"
        }
    ],
    "sg:phone":"+1 450 461 0269",
    "sg:postcode":"J3V 3J4",
    "sg:province":"QC",
    "sg:tags":[
        "landscape",
        "contractor"
    ],
    "wof:name":"Paysagiste Simon Goyer Enr",
    "wof:placetype":"venue"
},
  "geometry": {"coordinates":[-71.675522,48.471771],"type":"Point"}
}