{
  "type": "Feature",
  "properties": {
    "addr:full":"22 Lessi St Sydney NS B1R 1T6",
    "addr:housenumber":"22",
    "addr:postcode":"b1r 1t6",
    "addr:street":"Lessi St",
    "iso:country":"CA",
    "sg:address":"22 Lessi St",
    "sg:city":"Sydney",
    "sg:classifiers":[
        {
            "category":"Autos & Motor Vehicles",
            "subcategory":"Boat Sales",
            "type":"Retail Goods"
        }
    ],
    "sg:phone":"+1 902 567 2339",
    "sg:postcode":"B1R 1T6",
    "sg:province":"NS",
    "sg:tags":[
        "outboard",
        "dealer"
    ],
    "wof:name":"Leon's Marine & Small Engine",
    "wof:placetype":"venue"
},
  "geometry": {"coordinates":[-60.195568,46.137341],"type":"Point"}
}