{
  "type": "Feature",
  "properties": {
    "addr:full":"308 Oxford St E London ON N6A 1V5",
    "addr:housenumber":"308",
    "addr:postcode":"n6a 1v5",
    "addr:street":"Oxford St E",
    "iso:country":"CA",
    "sg:address":"308 Oxford St E",
    "sg:city":"London",
    "sg:classifiers":[
        {
            "category":"Personal",
            "subcategory":"Beauty Salon",
            "type":"Services"
        }
    ],
    "sg:phone":"+1 519 667 9693",
    "sg:postcode":"N6A 1V5",
    "sg:province":"ON",
    "sg:tags":[
        "spa",
        "day"
    ],
    "wof:name":"Beauty Total Skin Care Salon",
    "wof:placetype":"venue"
},
  "geometry": {"coordinates":[-81.249512,42.996693],"type":"Point"}
}