{
  "type": "Feature",
  "properties": {
    "addr:full":"447 Highway 77 Leamington ON N8H 3V6",
    "addr:housenumber":"447",
    "addr:postcode":"n8h 3v6",
    "addr:street":"Highway 77",
    "iso:country":"CA",
    "sg:address":"447 Highway 77",
    "sg:city":"Leamington",
    "sg:classifiers":[
        {
            "category":"Organizations",
            "subcategory":"Community Association",
            "type":"Services"
        }
    ],
    "sg:phone":"+1 519 326 3883",
    "sg:postcode":"N8H 3V6",
    "sg:province":"ON",
    "sg:tags":[
        "club"
    ],
    "wof:name":"Leamington Lebanese Club",
    "wof:placetype":"venue"
},
  "geometry": {"coordinates":[-82.5997161865,42.0541534424],"type":"Point"}
}