{
  "type": "Feature",
  "properties": {
    "addr:full":"Joliette QC J6E 6X6",
    "addr:postcode":"j6e 6x6",
    "iso:country":"CA",
    "sg:city":"Joliette",
    "sg:classifiers":[
        {
            "category":"Shopping",
            "subcategory":"Shoes",
            "type":"Retail Goods"
        }
    ],
    "sg:phone":"+1 450 752 0950",
    "sg:postcode":"J6E 6X6",
    "sg:province":"QC",
    "sg:tags":[
        "clothing",
        "furnishing"
    ],
    "wof:name":"Bovet",
    "wof:placetype":"venue"
},
  "geometry": {"coordinates":[-73.426109314,46.0338401794],"type":"Point"}
}