{
  "type": "Feature",
  "properties": {
    "addr:full":"195 Rang Saint-Alexis Nicolet-Sud QC J3T 1T5",
    "addr:housenumber":"195",
    "addr:postcode":"j3t 1t5",
    "addr:street":"Rang Saint-Alexis Nicolet-Sud",
    "iso:country":"CA",
    "sg:address":"195 Rang Saint-Alexis",
    "sg:city":"Nicolet-Sud",
    "sg:classifiers":[
        {
            "category":"Museum",
            "type":"Entertainment"
        }
    ],
    "sg:phone":"+1 819 293 4103",
    "sg:postcode":"J3T 1T5",
    "sg:province":"QC",
    "wof:name":"Maison Rodolphe Duguay",
    "wof:placetype":"venue"
},
  "geometry": {"coordinates":[-72.621048,46.221882],"type":"Point"}
}