{
  "type": "Feature",
  "properties": {
    "addr:full":"214 Main St Elrose SK S0L 0Z0",
    "addr:housenumber":"214",
    "addr:postcode":"s0l 0z0",
    "addr:street":"Main St",
    "iso:country":"CA",
    "sg:address":"214 Main St",
    "sg:city":"Elrose",
    "sg:classifiers":[
        {
            "category":"Farming",
            "subcategory":"Nursery",
            "type":"Manufacturing & Wholesale Goods"
        }
    ],
    "sg:phone":"+1 306 378 4103",
    "sg:postcode":"S0L 0Z0",
    "sg:province":"SK",
    "sg:tags":[
        "greenhouse"
    ],
    "wof:name":"Youngplants Canada",
    "wof:placetype":"venue"
},
  "geometry": {"coordinates":[-108.02726,51.201286],"type":"Point"}
}