{
  "type": "Feature",
  "properties": {
    "addr:full":"145 Churchill Ave Moose Lake MB R0B 0Y0",
    "addr:housenumber":"145",
    "addr:postcode":"r0b 0y0",
    "addr:street":"Churchill Ave",
    "iso:country":"CA",
    "sg:address":"145 Churchill Ave",
    "sg:city":"Moose Lake",
    "sg:classifiers":[
        {
            "category":"Organizations",
            "subcategory":"Professional Association",
            "type":"Services"
        }
    ],
    "sg:phone":"+1 204 678 2113",
    "sg:postcode":"R0B 0Y0",
    "sg:province":"MB",
    "sg:tags":[
        "native"
    ],
    "wof:name":"Moosakahikan Cree Nation",
    "wof:placetype":"venue"
},
  "geometry": {"coordinates":[-100.330368042,53.699306488],"type":"Point"}
}