{
  "type": "Feature",
  "properties": {
    "addr:full":"66 Riel Dr St Albert AB T8N 6L4",
    "addr:housenumber":"66",
    "addr:postcode":"t8n 6l4",
    "addr:street":"Riel Dr",
    "iso:country":"CA",
    "sg:address":"66 Riel Dr",
    "sg:city":"St Albert",
    "sg:classifiers":[
        {
            "category":"Building & Trades",
            "subcategory":"Plumbing",
            "type":"Services"
        }
    ],
    "sg:phone":"+1 780 460 4505",
    "sg:postcode":"T8N 6L4",
    "sg:province":"AB",
    "sg:tags":[
        "mechanical",
        "contractor"
    ],
    "wof:name":"Accurate Mechanical",
    "wof:placetype":"venue"
},
  "geometry": {"coordinates":[-113.647842,53.61631],"type":"Point"}
}