{
  "type": "Feature",
  "properties": {
    "addr:full":"3919 Gordon Rd Regina SK S4S 6G6",
    "addr:housenumber":"3919",
    "addr:postcode":"s4s 6g6",
    "addr:street":"Gordon Rd",
    "iso:country":"CA",
    "sg:address":"3919 Gordon Rd",
    "sg:city":"Regina",
    "sg:classifiers":[
        {
            "category":"Professional",
            "type":"Services"
        }
    ],
    "sg:phone":"+1 306 543 8722",
    "sg:postcode":"S4S 6G6",
    "sg:province":"SK",
    "sg:tags":[
        "writer"
    ],
    "wof:name":"Bill Armstrong Communications",
    "wof:placetype":"venue"
},
  "geometry": {"coordinates":[-104.637519836,50.4052658081],"type":"Point"}
}