{
  "type": "Feature",
  "properties": {
    "addr:full":"331 Rue Laviolette Gatineau QC J8P 5Z1",
    "addr:housenumber":"331",
    "addr:postcode":"j8p 5z1",
    "addr:street":"Rue Laviolette",
    "iso:country":"CA",
    "sg:address":"331 Rue Laviolette",
    "sg:city":"Gatineau",
    "sg:classifiers":[
        {
            "category":"Restaurant",
            "type":"Food & Drink"
        }
    ],
    "sg:phone":"+1 819 643 3363",
    "sg:postcode":"J8P 5Z1",
    "sg:province":"QC",
    "wof:name":"Restaurant Lucie",
    "wof:placetype":"venue"
},
  "geometry": {"coordinates":[-75.660843,45.489101],"type":"Point"}
}