{
  "type": "Feature",
  "properties": {
    "addr:full":"Calgary AB T2R 1K1",
    "addr:postcode":"t2r 1k1",
    "iso:country":"CA",
    "sg:city":"Calgary",
    "sg:classifiers":[
        {
            "category":"Professional",
            "subcategory":"Lawyer & Legal Services",
            "type":"Services"
        }
    ],
    "sg:phone":"+1 403 245 9000",
    "sg:postcode":"T2R 1K1",
    "sg:province":"AB",
    "sg:tags":[
        "attorney"
    ],
    "wof:name":"Martin G Schulz & Assoc",
    "wof:placetype":"venue"
},
  "geometry": {"coordinates":[-114.08152008099999,51.0385742188],"type":"Point"}
}