{
  "type": "Feature",
  "properties": {
    "addr:full":"1178 Falconbridge Rd Sudbury ON P3A 4N1",
    "addr:housenumber":"1178",
    "addr:postcode":"p3a 4n1",
    "addr:street":"Falconbridge Rd",
    "iso:country":"CA",
    "sg:address":"1178 Falconbridge Rd",
    "sg:city":"Sudbury",
    "sg:classifiers":[
        {
            "category":"Autos & Motor Vehicles",
            "subcategory":"Automobile Sales",
            "type":"Retail Goods"
        }
    ],
    "sg:phone":"+1 705 560 4518",
    "sg:postcode":"P3A 4N1",
    "sg:province":"ON",
    "sg:tags":[
        "car",
        "dealer"
    ],
    "wof:name":"Baldwin Motors",
    "wof:placetype":"venue"
},
  "geometry": {"coordinates":[-80.91675600000001,46.52261],"type":"Point"}
}