{
  "type": "Feature",
  "properties": {
    "addr:full":"36104 Cabot Trl Ingonish NS B0C 1K0",
    "addr:housenumber":"36104",
    "addr:postcode":"b0c 1k0",
    "addr:street":"Cabot Trl",
    "iso:country":"CA",
    "sg:address":"36104 Cabot Trl",
    "sg:city":"Ingonish",
    "sg:classifiers":[
        {
            "category":"Travel",
            "subcategory":"Hotels & Motels",
            "type":"Entertainment"
        }
    ],
    "sg:phone":"+1 902 285 2879",
    "sg:postcode":"B0C 1K0",
    "sg:province":"NS",
    "sg:tags":[
        "cottage",
        "cabin"
    ],
    "wof:name":"Seabreeze Cottages",
    "wof:placetype":"venue"
},
  "geometry": {"coordinates":[-60.3739089966,46.6915550232],"type":"Point"}
}