{
  "type": "Feature",
  "properties": {
    "iso:country":"CA",
    "sg:city":"Pointe-Claire",
    "sg:classifiers":[
        {
            "category":"Professional",
            "subcategory":"Accounting & Tax Preparation",
            "type":"Services"
        }
    ],
    "sg:phone":"+1 514 697 8282",
    "sg:postcode":"H9R 1G4",
    "sg:province":"QC",
    "sg:tags":[
        "accountant"
    ],
    "wof:name":"Andrews & Assoc",
    "wof:placetype":"venue"
},
  "geometry": {"coordinates":[-73.82331848139999,45.4591331482],"type":"Point"}
}