{
  "type": "Feature",
  "properties": {
    "iso:country":"CA",
    "sg:address":"1701 Rue Parthenais",
    "sg:city":"Montreal",
    "sg:classifiers":[
        {
            "category":"Government",
            "subcategory":"Police Station",
            "type":"Public Place"
        }
    ],
    "sg:phone":"+1 514 598 4141",
    "sg:postcode":"H2K 3S7",
    "sg:province":"QC",
    "sg:tags":[
        "department"
    ],
    "wof:name":"Quebec Grand Quartier General",
    "wof:placetype":"venue"
},
  "geometry": {"coordinates":[-73.552109,45.527763],"type":"Point"}
}