{
  "type": "Feature",
  "properties": {
    "addr:full":"11723 170 St NW Edmonton AB T5M 3W7",
    "addr:housenumber":"11723",
    "addr:postcode":"t5m 3w7",
    "addr:street":"170 St Nw",
    "iso:country":"CA",
    "sg:address":"11723 170 St NW",
    "sg:city":"Edmonton",
    "sg:classifiers":[
        {
            "category":"Wholesale",
            "subcategory":"Machinery & Supplies",
            "type":"Manufacturing & Wholesale Goods"
        }
    ],
    "sg:phone":"+1 780 452 4055",
    "sg:postcode":"T5M 3W7",
    "sg:province":"AB",
    "sg:tags":[
        "bearing",
        "reducer",
        "speed"
    ],
    "wof:name":"B C Bearing Engineers Ltd",
    "wof:placetype":"venue"
},
  "geometry": {"coordinates":[-113.61467,53.568169],"type":"Point"}
}