{
  "type": "Feature",
  "properties": {
    "addr:full":"Cranbrook BC V1C 1A7",
    "addr:postcode":"v1c 1a7",
    "iso:country":"CA",
    "sg:city":"Cranbrook",
    "sg:classifiers":[
        {
            "category":"Government",
            "subcategory":"Office",
            "type":"Public Place"
        }
    ],
    "sg:phone":"+1 250 426 1557",
    "sg:postcode":"V1C 1A7",
    "sg:province":"BC",
    "wof:name":"BC Energy Mines & Petroleum",
    "wof:placetype":"venue"
},
  "geometry": {"coordinates":[-115.76589199999999,49.512005],"type":"Point"}
}