{
  "type": "Feature",
  "properties": {
    "addr:full":"Montreal QC H2N 2C9",
    "addr:postcode":"h2n 2c9",
    "iso:country":"CA",
    "sg:city":"Montreal",
    "sg:classifiers":[
        {
            "category":"Wholesale",
            "subcategory":"Non-durable Goods",
            "type":"Manufacturing & Wholesale Goods"
        }
    ],
    "sg:phone":"+1 514 385 4440",
    "sg:postcode":"H2N 2C9",
    "sg:province":"QC",
    "sg:tags":[
        "leather"
    ],
    "wof:name":"Italo Leather Canada Inc",
    "wof:placetype":"venue"
},
  "geometry": {"coordinates":[-73.65353393549999,45.5406227112],"type":"Point"}
}