{
  "type": "Feature",
  "properties": {
    "addr:full":"36 Stoffel Dr #C Etobicoke ON M9W 1A8",
    "addr:housenumber":"36",
    "addr:postcode":"m9w 1a8",
    "addr:street":"Stoffel Dr # C",
    "iso:country":"CA",
    "sg:address":"36 Stoffel Dr #C",
    "sg:city":"Etobicoke",
    "sg:classifiers":[
        {
            "category":"Building & Trades",
            "subcategory":"Electrical",
            "type":"Services"
        }
    ],
    "sg:phone":"+1 416 410 2873",
    "sg:postcode":"M9W 1A8",
    "sg:province":"ON",
    "sg:tags":[
        "home",
        "system",
        "automation"
    ],
    "wof:name":"Automated Home Technologies",
    "wof:placetype":"venue"
},
  "geometry": {"coordinates":[-79.5749588013,43.688419342],"type":"Point"}
}