{
  "type": "Feature",
  "properties": {
    "addr:full":"3439 East Kelowna Rd Kelowna BC V1W 4H1",
    "addr:housenumber":"3439",
    "addr:postcode":"v1w 4h1",
    "addr:street":"East Kelowna Rd",
    "iso:country":"CA",
    "sg:address":"3439 East Kelowna Rd",
    "sg:city":"Kelowna",
    "sg:classifiers":[
        {
            "category":"Education",
            "subcategory":"School",
            "type":"Public Place"
        }
    ],
    "sg:phone":"+1 250 860 1165",
    "sg:postcode":"V1W 4H1",
    "sg:province":"BC",
    "wof:name":"Okanagan Montessori Elementary",
    "wof:placetype":"venue"
},
  "geometry": {"coordinates":[-119.40682200000001,49.867043],"type":"Point"}
}