{
  "type": "Feature",
  "properties": {
    "addr:full":"4489 Gary Lane Campbell River BC V9H 1B8",
    "addr:housenumber":"4489",
    "addr:postcode":"v9h 1b8",
    "addr:street":"Gary Lane",
    "iso:country":"CA",
    "sg:address":"4489 Gary Lane",
    "sg:city":"Campbell River",
    "sg:classifiers":[
        {
            "category":"Shopping",
            "subcategory":"Crafts & Fabrics",
            "type":"Retail Goods"
        }
    ],
    "sg:phone":"+1 250 923 0801",
    "sg:postcode":"V9H 1B8",
    "sg:province":"BC",
    "sg:tags":[
        "shop"
    ],
    "wof:name":"Fabric Studio",
    "wof:placetype":"venue"
},
  "geometry": {"coordinates":[-125.248169,50.024609],"type":"Point"}
}