{
  "type": "Feature",
  "properties": {
    "addr:full":"3955 Tecumseh Rd E Windsor ON N8W 1J5",
    "addr:housenumber":"3955",
    "addr:postcode":"n8w 1j5",
    "addr:street":"Tecumseh Rd E",
    "iso:country":"CA",
    "sg:address":"3955 Tecumseh Rd E",
    "sg:city":"Windsor",
    "sg:classifiers":[
        {
            "category":"Health Services",
            "subcategory":"Doctor",
            "type":"Services"
        }
    ],
    "sg:phone":"+1 519 974 9778",
    "sg:postcode":"N8W 1J5",
    "sg:province":"ON",
    "sg:tags":[
        "physician",
        "surgeon"
    ],
    "wof:name":"Koutras, Nicholas MD",
    "wof:placetype":"venue"
},
  "geometry": {"coordinates":[-82.976051,42.305721],"type":"Point"}
}