{
  "type": "Feature",
  "properties": {
    "addr:full":"64 Argyle Ave Delhi ON N4B 1J3",
    "addr:housenumber":"64",
    "addr:postcode":"n4b 1j3",
    "addr:street":"Argyle Ave",
    "iso:country":"CA",
    "sg:address":"64 Argyle Ave",
    "sg:city":"Delhi",
    "sg:classifiers":[
        {
            "category":"Food & Beverages",
            "subcategory":"Liquor & Beverages",
            "type":"Retail Goods"
        }
    ],
    "sg:phone":"+1 519 582 0550",
    "sg:postcode":"N4B 1J3",
    "sg:province":"ON",
    "sg:tags":[
        "beer",
        "ale"
    ],
    "wof:name":"Brewers Retail Store",
    "wof:placetype":"venue"
},
  "geometry": {"coordinates":[-80.489845,42.849228],"type":"Point"}
}