{
  "type": "Feature",
  "properties": {
    "addr:full":"8401 Weston Rd Woodbridge ON L4L 1A6",
    "addr:housenumber":"8401",
    "addr:postcode":"l4l 1a6",
    "addr:street":"Weston Rd",
    "iso:country":"CA",
    "sg:address":"8401 Weston Rd",
    "sg:city":"Woodbridge",
    "sg:classifiers":[
        {
            "category":"Social Services",
            "type":"Services"
        }
    ],
    "sg:phone":"+1 905 851 6558",
    "sg:postcode":"L4L 1A6",
    "sg:province":"ON",
    "sg:tags":[
        "organization",
        "welfare"
    ],
    "wof:name":"Patronato Acli",
    "wof:placetype":"venue"
},
  "geometry": {"coordinates":[-79.55136899999999,43.806595],"type":"Point"}
}