{
  "type": "Feature",
  "properties": {
    "addr:full":"400 Taunton Rd E Oshawa ON L1H 7K5",
    "addr:housenumber":"400",
    "addr:postcode":"l1h 7k5",
    "addr:street":"Taunton Rd E",
    "iso:country":"CA",
    "sg:address":"400 Taunton Rd E",
    "sg:city":"Oshawa",
    "sg:classifiers":[
        {
            "category":"Autos & Motor Vehicles",
            "subcategory":"Automobile Sales",
            "type":"Retail Goods"
        }
    ],
    "sg:phone":"+1 905 721 9523",
    "sg:postcode":"L1H 7K5",
    "sg:province":"ON",
    "sg:tags":[
        "car",
        "dealer"
    ],
    "wof:name":"Switzer Motors",
    "wof:placetype":"venue"
},
  "geometry": {"coordinates":[-78.86346399999999,43.93652],"type":"Point"}
}