{
  "type": "Feature",
  "properties": {
    "addr:full":"58 Old Kennedy Rd Markham ON L3R 0L6",
    "addr:housenumber":"58",
    "addr:postcode":"l3r 0l6",
    "addr:street":"Old Kennedy Rd",
    "iso:country":"CA",
    "sg:address":"58 Old Kennedy Rd",
    "sg:city":"Markham",
    "sg:classifiers":[
        {
            "category":"Building & Trades",
            "subcategory":"Construction",
            "type":"Services"
        }
    ],
    "sg:phone":"+1 905 475 7181",
    "sg:postcode":"L3R 0L6",
    "sg:province":"ON",
    "sg:tags":[
        "builder",
        "patio",
        "deck"
    ],
    "wof:name":"Deck Depot Ltd",
    "wof:placetype":"venue"
},
  "geometry": {"coordinates":[-79.30078125,43.8272628784],"type":"Point"}
}