{
  "type": "Feature",
  "properties": {
    "iso:country":"CA",
    "sg:address":"355 Erb St W",
    "sg:city":"Waterloo",
    "sg:classifiers":[
        {
            "category":"Restaurant",
            "type":"Food & Drink"
        }
    ],
    "sg:phone":"+1 519 746 2530",
    "sg:postcode":"N2L 1W4",
    "sg:province":"ON",
    "wof:name":"Baker's Cove Family Seafood",
    "wof:placetype":"venue"
},
  "geometry": {"coordinates":[-80.54657745359999,43.4547462463],"type":"Point"}
}