{
  "type": "Feature",
  "properties": {
    "addr:full":"44 Castledene Cres Scarborough ON M1T 1S1",
    "addr:housenumber":"44",
    "addr:postcode":"m1t 1s1",
    "addr:street":"Castledene Cres",
    "iso:country":"CA",
    "sg:address":"44 Castledene Cres",
    "sg:city":"Scarborough",
    "sg:classifiers":[
        {
            "category":"Professional",
            "subcategory":"Accounting & Tax Preparation",
            "type":"Services"
        }
    ],
    "sg:phone":"+1 416 496 8030",
    "sg:postcode":"M1T 1S1",
    "sg:province":"ON",
    "sg:tags":[
        "accountant"
    ],
    "wof:name":"Dingwall, R T CA",
    "wof:placetype":"venue"
},
  "geometry": {"coordinates":[-79.3189620972,43.7804679871],"type":"Point"}
}