{
  "type": "Feature",
  "properties": {
    "addr:full":"475 114E Rue Shawinigan-Sud QC G9P 2X6",
    "addr:housenumber":"475",
    "addr:postcode":"g9p 2x6",
    "addr:street":"114E Rue Shawinigan-Sud",
    "iso:country":"CA",
    "sg:address":"475 114E Rue",
    "sg:city":"Shawinigan-Sud",
    "sg:classifiers":[
        {
            "category":"Building & Trades",
            "subcategory":"Plumbing",
            "type":"Services"
        }
    ],
    "sg:phone":"+1 819 537 6691",
    "sg:postcode":"G9P 2X6",
    "sg:province":"QC",
    "sg:tags":[
        "roofing",
        "heating",
        "contractor"
    ],
    "wof:name":"Lucien Laurendeau Inc",
    "wof:placetype":"venue"
},
  "geometry": {"coordinates":[-72.7496643066,46.523475647],"type":"Point"}
}