{
  "type": "Feature",
  "properties": {
    "addr:full":"36 Baldwin St Toronto ON M5T 1L3",
    "addr:housenumber":"36",
    "addr:postcode":"m5t 1l3",
    "addr:street":"Baldwin St",
    "iso:country":"CA",
    "sg:address":"36 Baldwin St",
    "sg:city":"Toronto",
    "sg:classifiers":[
        {
            "category":"Food & Beverages",
            "subcategory":"Groceries & Convenience Stores",
            "type":"Retail Goods"
        }
    ],
    "sg:phone":"+1 416 977 3518",
    "sg:postcode":"M5T 1L3",
    "sg:province":"ON",
    "sg:tags":[
        "grocer"
    ],
    "wof:name":"Baldwin Smoke & Grocery",
    "wof:placetype":"venue"
},
  "geometry": {"coordinates":[-79.39398199999999,43.656044],"type":"Point"}
}