{
  "type": "Feature",
  "properties": {
    "addr:full":"8559 Roblin Blvd Headingley MB R4J 1B3",
    "addr:housenumber":"8559",
    "addr:postcode":"r4j 1b3",
    "addr:street":"Roblin Blvd",
    "iso:country":"CA",
    "sg:address":"8559 Roblin Blvd",
    "sg:city":"Headingley",
    "sg:classifiers":[
        {
            "category":"Building & Trades",
            "subcategory":"Construction",
            "type":"Services"
        }
    ],
    "sg:phone":"+1 204 885 2386",
    "sg:postcode":"R4J 1B3",
    "sg:province":"MB",
    "sg:tags":[
        "home",
        "improvement"
    ],
    "wof:name":"Alr Renovations Ltd",
    "wof:placetype":"venue"
},
  "geometry": {"coordinates":[-97.417603,49.869312],"type":"Point"}
}