{
  "type": "Feature",
  "properties": {
    "iso:country":"CA",
    "sg:address":"69 Rang Saint-Pierre N",
    "sg:city":"Saint-Constant",
    "sg:classifiers":[
        {
            "category":"Personal",
            "subcategory":"Barber",
            "type":"Services"
        }
    ],
    "sg:phone":"+1 450 632 9159",
    "sg:postcode":"J5A 2E7",
    "sg:province":"QC",
    "wof:name":"Coiffure Au Masculin L",
    "wof:placetype":"venue"
},
  "geometry": {"coordinates":[-73.56391143800001,45.3798484802],"type":"Point"}
}