{
  "type": "Feature",
  "properties": {
    "addr:full":"1840 Trans Canada Hwy Revelstoke BC V0E 2S0",
    "addr:housenumber":"1840",
    "addr:postcode":"v0e 2s0",
    "addr:street":"Trans Canada Hwy",
    "iso:country":"CA",
    "sg:address":"1840 Trans Canada Hwy",
    "sg:city":"Revelstoke",
    "sg:classifiers":[
        {
            "category":"Autos & Motor Vehicles",
            "subcategory":"Fuel & Gas Station",
            "type":"Retail Goods"
        }
    ],
    "sg:phone":"+1 250 837 4266",
    "sg:postcode":"V0E 2S0",
    "sg:province":"BC",
    "sg:tags":[
        "oil"
    ],
    "wof:name":"Alpine Shell",
    "wof:placetype":"venue"
},
  "geometry": {"coordinates":[-118.21522521999999,51.0096931458],"type":"Point"}
}