{
  "type": "Feature",
  "properties": {
    "addr:full":"20 First Ave Uxbridge ON L9P 1M4",
    "addr:housenumber":"20",
    "addr:postcode":"l9p 1m4",
    "addr:street":"First Ave",
    "iso:country":"CA",
    "sg:address":"20 First Ave",
    "sg:city":"Uxbridge",
    "sg:classifiers":[
        {
            "category":"Organizations",
            "subcategory":"Religious Organization",
            "type":"Services"
        }
    ],
    "sg:phone":"+1 905 852 6213",
    "sg:postcode":"L9P 1M4",
    "sg:province":"ON",
    "sg:tags":[
        "church"
    ],
    "wof:name":"Trinity United Church",
    "wof:placetype":"venue"
},
  "geometry": {"coordinates":[-79.1195068359,44.1103935242],"type":"Point"}
}