{
  "type": "Feature",
  "properties": {
    "addr:full":"25 Talbot St N Essex ON N8M 1A5",
    "addr:housenumber":"25",
    "addr:postcode":"n8m 1a5",
    "addr:street":"Talbot St N",
    "iso:country":"CA",
    "sg:address":"25 Talbot St N",
    "sg:city":"Essex",
    "sg:classifiers":[
        {
            "category":"Shopping",
            "subcategory":"Bicycles & Sporting Goods",
            "type":"Retail Goods"
        }
    ],
    "sg:phone":"+1 519 776 5115",
    "sg:postcode":"N8M 1A5",
    "sg:province":"ON",
    "wof:name":"Essex Source For Sports",
    "wof:placetype":"venue"
},
  "geometry": {"coordinates":[-82.82131195069999,42.1743240356],"type":"Point"}
}