{
  "type": "Feature",
  "properties": {
    "addr:full":"2356 Mcphillips St Winnipeg MB R2V 4J6",
    "addr:housenumber":"2356",
    "addr:postcode":"r2v 4j6",
    "addr:street":"Mcphillips St",
    "iso:country":"CA",
    "sg:address":"2356 Mcphillips St",
    "sg:city":"Winnipeg",
    "sg:classifiers":[
        {
            "category":"Autos & Motor Vehicles",
            "subcategory":"Auto Supplies",
            "type":"Retail Goods"
        }
    ],
    "sg:phone":"+1 204 334 2880",
    "sg:postcode":"R2V 4J6",
    "sg:province":"MB",
    "sg:tags":[
        "automobile",
        "parts"
    ],
    "wof:name":"Part Source",
    "wof:placetype":"venue"
},
  "geometry": {"coordinates":[-97.14587400000001,49.955757],"type":"Point"}
}