{
  "type": "Feature",
  "properties": {
    "iso:country":"CA",
    "sg:address":"2356 Mcphillips St",
    "sg:city":"Winnipeg",
    "sg:classifiers":[
        {
            "category":"Autos & Motor Vehicles",
            "subcategory":"Auto Supplies",
            "type":"Retail Goods"
        }
    ],
    "sg:phone":"+1 204 334 2880",
    "sg:postcode":"R2V 4J6",
    "sg:province":"MB",
    "sg:tags":[
        "automobile",
        "parts"
    ],
    "wof:name":"Part Source",
    "wof:placetype":"venue"
},
  "geometry": {"coordinates":[-97.145874,49.955757],"type":"Point"}
}