{
  "type": "Feature",
  "properties": {
    "iso:country":"CA",
    "sg:address":"444 Queen St",
    "sg:city":"Hope",
    "sg:classifiers":[
        {
            "category":"Education",
            "subcategory":"School",
            "type":"Public Place"
        }
    ],
    "sg:phone":"+1 604 869 2451",
    "sg:postcode":"V0X 1L0",
    "sg:province":"BC",
    "wof:name":"C E Barry School",
    "wof:placetype":"venue"
},
  "geometry": {"coordinates":[-121.44190979,49.383354187],"type":"Point"}
}