{
  "type": "Feature",
  "properties": {
    "addr:full":"4503 47 Ave Rocky Mountain House AB T4T 1C5",
    "addr:housenumber":"4503",
    "addr:postcode":"t4t 1c5",
    "addr:street":"47 Ave",
    "iso:country":"CA",
    "sg:address":"4503 47 Ave",
    "sg:city":"Rocky Mountain House",
    "sg:classifiers":[
        {
            "category":"Autos & Motor Vehicles",
            "subcategory":"Fuel & Gas Station",
            "type":"Retail Goods"
        }
    ],
    "sg:phone":"+1 403 845 2036",
    "sg:postcode":"T4T 1C5",
    "sg:province":"AB",
    "sg:tags":[
        "oil"
    ],
    "wof:name":"Fas Gas Westview Svc",
    "wof:placetype":"venue"
},
  "geometry": {"coordinates":[-114.910027,52.370274],"type":"Point"}
}