{
  "type": "Feature",
  "properties": {
    "addr:full":"Sainte-Genevieve-DE-Batiscan QC G0X 2R0",
    "addr:postcode":"g0x 2r0",
    "iso:country":"CA",
    "sg:city":"Sainte-Genevieve-DE-Batiscan",
    "sg:classifiers":[
        {
            "category":"Social Services",
            "type":"Services"
        }
    ],
    "sg:phone":"+1 418 362 3300",
    "sg:postcode":"G0X 2R0",
    "sg:province":"QC",
    "sg:tags":[
        "organization",
        "welfare"
    ],
    "wof:name":"Projet Defi Autonomie",
    "wof:placetype":"venue"
},
  "geometry": {"coordinates":[-72.2467346191,46.5050315857],"type":"Point"}
}