{
  "type": "Feature",
  "properties": {
    "addr:full":"235 Boul Yvon-L'Heureux N Beloeil QC J3G 5R8",
    "addr:housenumber":"235",
    "addr:postcode":"j3g 5r8",
    "addr:street":"Boul Yvon-L'Heureux N",
    "iso:country":"CA",
    "sg:address":"235 Boul Yvon-L'Heureux N",
    "sg:city":"Beloeil",
    "sg:classifiers":[
        {
            "category":"Retail",
            "subcategory":"Auto Repair",
            "type":"Services"
        }
    ],
    "sg:phone":"+1 450 467 5280",
    "sg:postcode":"J3G 5R8",
    "sg:province":"QC",
    "sg:tags":[
        "repairing",
        "automobile"
    ],
    "wof:name":"Garage Rejean Guy Inc",
    "wof:placetype":"venue"
},
  "geometry": {"coordinates":[-73.20761899999999,45.57486],"type":"Point"}
}