{
  "type": "Feature",
  "properties": {
    "addr:full":"58 Brisbane Ave Winnipeg MB R3T 0T2",
    "addr:housenumber":"58",
    "addr:postcode":"r3t 0t2",
    "addr:street":"Brisbane Ave",
    "iso:country":"CA",
    "sg:address":"58 Brisbane Ave",
    "sg:city":"Winnipeg",
    "sg:classifiers":[
        {
            "category":"Health Services",
            "subcategory":"Clinic",
            "type":"Services"
        }
    ],
    "sg:phone":"+1 204 453 8629",
    "sg:postcode":"R3T 0T2",
    "sg:province":"MB",
    "wof:name":"Health Maintenance Enterprises",
    "wof:placetype":"venue"
},
  "geometry": {"coordinates":[-97.15830200000001,49.832951],"type":"Point"}
}