{
  "type": "Feature",
  "properties": {
    "addr:full":"720 Arrow Rd North York ON M9M 2M1",
    "addr:housenumber":"720",
    "addr:postcode":"m9m 2m1",
    "addr:street":"Arrow Rd",
    "iso:country":"CA",
    "sg:address":"720 Arrow Rd",
    "sg:city":"North York",
    "sg:classifiers":[
        {
            "category":"Retail",
            "subcategory":"Auto Rental",
            "type":"Services"
        }
    ],
    "sg:phone":"+1 416 744 0123",
    "sg:postcode":"M9M 2M1",
    "sg:province":"ON",
    "sg:tags":[
        "renting",
        "automobile"
    ],
    "wof:name":"Discount Car & Truck Rentals",
    "wof:placetype":"venue"
},
  "geometry": {"coordinates":[-79.53001399999999,43.746929],"type":"Point"}
}