{
  "type": "Feature",
  "properties": {
    "addr:full":"20 Pointview Dr Lions Head ON N0H 1W0",
    "addr:housenumber":"20",
    "addr:postcode":"n0h 1w0",
    "addr:street":"Pointview Dr Lions Head",
    "iso:country":"CA",
    "sg:address":"20 Pointview Dr",
    "sg:city":"Lions Head",
    "sg:classifiers":[
        {
            "category":"Building & Trades",
            "subcategory":"Construction",
            "type":"Services"
        }
    ],
    "sg:phone":"+1 519 793 3325",
    "sg:postcode":"N0H 1W0",
    "sg:province":"ON",
    "sg:tags":[
        "contractor"
    ],
    "wof:name":"James Hill Construction Ltd",
    "wof:placetype":"venue"
},
  "geometry": {"coordinates":[-81.2564468384,44.9850311279],"type":"Point"}
}