{
  "type": "Feature",
  "properties": {
    "addr:full":"303 Main St Selkirk MB R1A 1S7",
    "addr:housenumber":"303",
    "addr:postcode":"r1a 1s7",
    "addr:street":"Main St",
    "iso:country":"CA",
    "sg:address":"303 Main St",
    "sg:city":"Selkirk",
    "sg:classifiers":[
        {
            "category":"Education",
            "subcategory":"Library",
            "type":"Public Place"
        }
    ],
    "sg:phone":"+1 204 482 3522",
    "sg:postcode":"R1A 1S7",
    "sg:province":"MB",
    "wof:name":"Selkirk & St Andrews Regl Libr",
    "wof:placetype":"venue"
},
  "geometry": {"coordinates":[-96.87848700000001,50.140881],"type":"Point"}
}