{
  "type": "Feature",
  "properties": {
    "addr:full":"166 Esplanade St Truro NS B2N 2K3",
    "addr:housenumber":"166",
    "addr:postcode":"b2n 2k3",
    "addr:street":"Esplanade St",
    "iso:country":"CA",
    "sg:address":"166 Esplanade St",
    "sg:city":"Truro",
    "sg:classifiers":[
        {
            "category":"Bars & Pubs",
            "type":"Food & Drink"
        }
    ],
    "sg:phone":"+1 902 895 5151",
    "sg:postcode":"B2N 2K3",
    "sg:province":"NS",
    "wof:name":"Engine Room",
    "wof:placetype":"venue"
},
  "geometry": {"coordinates":[-63.2739982605,45.3632698059],"type":"Point"}
}