{
  "type": "Feature",
  "properties": {
    "iso:country":"CA",
    "sg:address":"166 Esplanade St",
    "sg:city":"Truro",
    "sg:classifiers":[
        {
            "category":"Bars & Pubs",
            "type":"Food & Drink"
        }
    ],
    "sg:phone":"+1 902 895 5151",
    "sg:postcode":"B2N 2K3",
    "sg:province":"NS",
    "wof:name":"Engine Room",
    "wof:placetype":"venue"
},
  "geometry": {"coordinates":[-63.2739982605,45.3632698059],"type":"Point"}
}