{
  "type": "Feature",
  "properties": {
    "addr:full":"955 Lougheed Hwy Coquitlam BC V3K 3T4",
    "addr:housenumber":"955",
    "addr:postcode":"v3k 3t4",
    "addr:street":"Lougheed Hwy",
    "iso:country":"CA",
    "sg:address":"955 Lougheed Hwy",
    "sg:city":"Coquitlam",
    "sg:classifiers":[
        {
            "category":"Retail",
            "subcategory":"Auto Repair",
            "type":"Services"
        }
    ],
    "sg:phone":"+1 604 523 2203",
    "sg:postcode":"V3K 3T4",
    "sg:province":"BC",
    "sg:tags":[
        "body",
        "automobile",
        "painting"
    ],
    "wof:name":"Craftsman Collision",
    "wof:placetype":"venue"
},
  "geometry": {"coordinates":[-122.87077331499999,49.2366142273],"type":"Point"}
}