{
  "type": "Feature",
  "properties": {
    "addr:full":"401 Rue Du Prince-Edward Otterburn Park QC J3H 1W3",
    "addr:housenumber":"401",
    "addr:postcode":"j3h 1w3",
    "addr:street":"Rue Du Prince-Edward;Park",
    "iso:country":"CA",
    "sg:address":"401 Rue Du Prince-Edward",
    "sg:city":"Otterburn Park",
    "sg:classifiers":[
        {
            "category":"Home & Garden",
            "subcategory":"Household Appliances",
            "type":"Retail Goods"
        }
    ],
    "sg:phone":"+1 450 464 2958",
    "sg:postcode":"J3H 1W3",
    "sg:province":"QC",
    "wof:name":"Claude Tessier Svc",
    "wof:placetype":"venue"
},
  "geometry": {"coordinates":[-73.1918640137,45.5418281555],"type":"Point"}
}