{
  "type": "Feature",
  "properties": {
    "addr:full":"512 Hendryx St Nelson BC V1L 2A8",
    "addr:housenumber":"512",
    "addr:postcode":"bc v1l 2a8",
    "addr:street":"Hendryx St",
    "iso:country":"CA",
    "sg:address":"512 Hendryx St",
    "sg:city":"Nelson",
    "sg:classifiers":[
        {
            "category":"Shopping",
            "subcategory":"Gifts & Souvenirs",
            "type":"Retail Goods"
        }
    ],
    "sg:phone":"+1 250 352 9477",
    "sg:postcode":"V1L 2A8",
    "sg:province":"BC",
    "sg:tags":[
        "shop"
    ],
    "wof:name":"Holy Smoke Culture Shop",
    "wof:placetype":"venue"
},
  "geometry": {"coordinates":[-117.289551,49.493019],"type":"Point"}
}