{
  "type": "Feature",
  "properties": {
    "iso:country":"CA",
    "sg:address":"246 Rochester St",
    "sg:city":"Ottawa",
    "sg:classifiers":[
        {
            "category":"Retail",
            "subcategory":"Repair Shop",
            "type":"Services"
        }
    ],
    "sg:phone":"+1 613 233 9428",
    "sg:postcode":"K1R 7N1",
    "sg:province":"ON",
    "sg:tags":[
        "appliance"
    ],
    "wof:name":"Renato's Appliance Repair",
    "wof:placetype":"venue"
},
  "geometry": {"coordinates":[-75.7106170654,45.4062919617],"type":"Point"}
}