{
  "type": "Feature",
  "properties": {
    "addr:full":"Sherwood Park AB T8A 6A2",
    "addr:postcode":"t8a 6a2",
    "iso:country":"CA",
    "sg:city":"Sherwood Park",
    "sg:classifiers":[
        {
            "category":"Professional",
            "subcategory":"Business Services",
            "type":"Services"
        }
    ],
    "sg:phone":"+1 780 467 0903",
    "sg:postcode":"T8A 6A2",
    "sg:province":"AB",
    "sg:tags":[
        "drafting"
    ],
    "wof:name":"M-Tec Drafting Svc Inc",
    "wof:placetype":"venue"
},
  "geometry": {"coordinates":[-113.32456999999999,53.53809],"type":"Point"}
}