{
  "type": "Feature",
  "properties": {
    "addr:full":"Concord ON L4K 3Z3",
    "addr:postcode":"l4k 3z3",
    "iso:country":"CA",
    "sg:city":"Concord",
    "sg:classifiers":[
        {
            "category":"Building & Trades",
            "subcategory":"Construction",
            "type":"Services"
        }
    ],
    "sg:phone":"+1 905 761 8690",
    "sg:postcode":"L4K 3Z3",
    "sg:province":"ON",
    "sg:tags":[
        "contractor"
    ],
    "wof:name":"Saberwood Homes",
    "wof:placetype":"venue"
},
  "geometry": {"coordinates":[-79.5188293457,43.799156189],"type":"Point"}
}