{
  "type": "Feature",
  "properties": {
    "addr:full":"Vancouver BC V6K 4S2",
    "addr:postcode":"v6k 4s2",
    "iso:country":"CA",
    "sg:city":"Vancouver",
    "sg:classifiers":[
        {
            "category":"Professional",
            "subcategory":"Accounting & Tax Preparation",
            "type":"Services"
        }
    ],
    "sg:phone":"+1 604 732 1515",
    "sg:postcode":"V6K 4S2",
    "sg:province":"BC",
    "sg:tags":[
        "consultant"
    ],
    "wof:name":"Stephen Katz Ltd",
    "wof:placetype":"venue"
},
  "geometry": {"coordinates":[-123.155525208,49.268371582],"type":"Point"}
}