{
  "type": "Feature",
  "properties": {
    "addr:full":"Port-Cartier QC G5B 1C9",
    "addr:postcode":"g5b 1c9",
    "iso:country":"CA",
    "sg:city":"Port-Cartier",
    "sg:classifiers":[
        {
            "category":"Health Services",
            "subcategory":"Hospital",
            "type":"Services"
        }
    ],
    "sg:phone":"+1 418 766 8969",
    "sg:postcode":"G5B 1C9",
    "sg:province":"QC",
    "sg:tags":[
        "mental"
    ],
    "wof:name":"Ressource DE Reinsertion-Phare",
    "wof:placetype":"venue"
},
  "geometry": {"coordinates":[-66.84796142579999,50.0343856812],"type":"Point"}
}