{
  "type": "Feature",
  "properties": {
    "addr:full":"Nepean ON K2E 7Z7",
    "addr:postcode":"k2e 7z7",
    "iso:country":"CA",
    "sg:city":"Nepean",
    "sg:classifiers":[
        {
            "category":"Building & Trades",
            "subcategory":"Construction",
            "type":"Services"
        }
    ],
    "sg:phone":"+1 613 727 0680",
    "sg:postcode":"K2E 7Z7",
    "sg:province":"ON",
    "sg:tags":[
        "railing"
    ],
    "wof:name":"Ottawa Valley Handrailing CO",
    "wof:placetype":"venue"
},
  "geometry": {"coordinates":[-75.7113113403,45.3285903931],"type":"Point"}
}