{
  "type": "Feature",
  "properties": {
    "addr:full":"201 Rue Merry S Magog QC J1X 3L2",
    "addr:housenumber":"201",
    "addr:postcode":"j1x 3l2",
    "addr:street":"Rue Merry S",
    "iso:country":"CA",
    "sg:address":"201 Rue Merry S",
    "sg:city":"Magog",
    "sg:classifiers":[
        {
            "category":"Recreation",
            "subcategory":"Marina",
            "type":"Entertainment"
        }
    ],
    "sg:phone":"+1 819 843 2102",
    "sg:postcode":"J1X 3L2",
    "sg:province":"QC",
    "sg:tags":[
        "repairing",
        "boat"
    ],
    "wof:name":"Boutique Nautique 30 Degres",
    "wof:placetype":"venue"
},
  "geometry": {"coordinates":[-72.15831,45.261848],"type":"Point"}
}