{
  "type": "Feature",
  "properties": {
    "iso:country":"CA",
    "sg:city":"Melita",
    "sg:classifiers":[
        {
            "category":"Building & Trades",
            "subcategory":"Construction",
            "type":"Services"
        }
    ],
    "sg:phone":"+1 204 522 3872",
    "sg:postcode":"R0M 1L0",
    "sg:province":"MB",
    "sg:tags":[
        "excavating",
        "contractor"
    ],
    "wof:name":"Dan Cameron Trucking & Excvtng",
    "wof:placetype":"venue"
},
  "geometry": {"coordinates":[-100.985801697,49.2723083496],"type":"Point"}
}