{
  "type": "Feature",
  "properties": {
    "addr:full":"Burnaby BC V5J 3H6",
    "addr:postcode":"v5j 3h6",
    "iso:country":"CA",
    "sg:city":"Burnaby",
    "sg:classifiers":[
        {
            "category":"Manufacturing",
            "subcategory":"Metals",
            "type":"Manufacturing & Wholesale Goods"
        }
    ],
    "sg:phone":"+1 604 451 3930",
    "sg:postcode":"V5J 3H6",
    "sg:province":"BC",
    "sg:tags":[
        "welding"
    ],
    "wof:name":"Ray's Welding",
    "wof:placetype":"venue"
},
  "geometry": {"coordinates":[-122.98949432400001,49.197971344],"type":"Point"}
}