{
  "type": "Feature",
  "properties": {
    "addr:full":"5 Sherbourne St N Bancroft ON K0L 1C0",
    "addr:housenumber":"5",
    "addr:postcode":"k0l 1c0",
    "addr:street":"Sherbourne St N",
    "iso:country":"CA",
    "sg:address":"5 Sherbourne St N",
    "sg:city":"Bancroft",
    "sg:classifiers":[
        {
            "category":"Professional",
            "subcategory":"Lawyer & Legal Services",
            "type":"Services"
        }
    ],
    "sg:phone":"+1 613 332 3022",
    "sg:postcode":"K0L 1C0",
    "sg:province":"ON",
    "sg:tags":[
        "attorney"
    ],
    "wof:name":"Watson, William D",
    "wof:placetype":"venue"
},
  "geometry": {"coordinates":[-77.86283874510001,45.0726585388],"type":"Point"}
}