{
  "type": "Feature",
  "properties": {
    "addr:full":"11339 Albion Vaughan Rd Kleinburg ON L0J 1C0",
    "addr:housenumber":"11339",
    "addr:postcode":"l0j 1c0",
    "addr:street":"Albion Vaughan Rd",
    "iso:country":"CA",
    "sg:address":"11339 Albion Vaughan Rd",
    "sg:city":"Kleinburg",
    "sg:classifiers":[
        {
            "category":"Freight",
            "type":"Transportation"
        }
    ],
    "sg:phone":"+1 905 893 2626",
    "sg:postcode":"L0J 1C0",
    "sg:province":"ON",
    "sg:tags":[
        "trucking"
    ],
    "wof:name":"Bulk Transfer Systems Inc",
    "wof:placetype":"venue"
},
  "geometry": {"coordinates":[-79.694969,43.850155],"type":"Point"}
}