{
  "type": "Feature",
  "properties": {
    "addr:full":"377 Baker St Nelson BC V1L 4H6",
    "addr:housenumber":"377",
    "addr:postcode":"bc v1l 4h6",
    "addr:street":"Baker St",
    "iso:country":"CA",
    "sg:address":"377 Baker St",
    "sg:city":"Nelson",
    "sg:classifiers":[
        {
            "category":"Manufacturing",
            "subcategory":"Food",
            "type":"Manufacturing & Wholesale Goods"
        }
    ],
    "sg:phone":"+1 250 352 2274",
    "sg:postcode":"V1L 4H6",
    "sg:province":"BC",
    "sg:tags":[
        "baker",
        "product",
        "manufacturer"
    ],
    "wof:name":"Kootenay Bakery Cafe Coop",
    "wof:placetype":"venue"
},
  "geometry": {"coordinates":[-117.295845032,49.4914398193],"type":"Point"}
}