{
  "type": "Feature",
  "properties": {
    "iso:country":"CA",
    "sg:address":"2 Rowntree Ave",
    "sg:city":"Toronto",
    "sg:classifiers":[
        {
            "category":"Recreation",
            "type":"Entertainment"
        }
    ],
    "sg:phone":"+1 416 394 8679",
    "sg:postcode":"M6N 1R3",
    "sg:province":"ON",
    "sg:tags":[
        "government",
        "hall",
        "auditorium"
    ],
    "wof:name":"Etobicoke North Kipling Comm",
    "wof:placetype":"venue"
},
  "geometry": {"coordinates":[-79.4606246948,43.6814613342],"type":"Point"}
}