{
  "type": "Feature",
  "properties": {
    "addr:full":"160 2nd Ave NW Roblin MB R0L 1P0",
    "addr:housenumber":"160",
    "addr:postcode":"roblin;r0l 1p0",
    "addr:street":"2Nd Ave Nw",
    "iso:country":"CA",
    "sg:address":"160 2nd Ave NW",
    "sg:city":"Roblin",
    "sg:classifiers":[
        {
            "category":"Restaurant",
            "type":"Food & Drink"
        }
    ],
    "sg:phone":"+1 204 937 8000",
    "sg:postcode":"R0L 1P0",
    "sg:province":"MB",
    "wof:name":"China Rose Restaurant",
    "wof:placetype":"venue"
},
  "geometry": {"coordinates":[-101.35244751,51.2261657715],"type":"Point"}
}