{
  "type": "Feature",
  "properties": {
    "iso:country":"CA",
    "sg:address":"129 Tudhope St",
    "sg:city":"Espanola",
    "sg:classifiers":[
        {
            "category":"Personal",
            "subcategory":"Beauty Salon",
            "type":"Services"
        }
    ],
    "sg:phone":"+1 705 869 4880",
    "sg:postcode":"P5E 1S6",
    "sg:province":"ON",
    "wof:name":"Hair Dynamics",
    "wof:placetype":"venue"
},
  "geometry": {"coordinates":[-81.7717285156,46.2652206421],"type":"Point"}
}