{
  "type": "Feature",
  "properties": {
    "iso:country":"CA",
    "sg:address":"600 Rue Dublin",
    "sg:city":"Montreal",
    "sg:classifiers":[
        {
            "category":"Education",
            "subcategory":"School",
            "type":"Public Place"
        }
    ],
    "sg:phone":"+1 514 934 2111",
    "sg:postcode":"H3K 2S4",
    "sg:province":"QC",
    "wof:name":"St Gabriel Ecoles",
    "wof:placetype":"venue"
},
  "geometry": {"coordinates":[-73.5588760376,45.4769058228],"type":"Point"}
}