{
  "type": "Feature",
  "properties": {
    "addr:full":"Vancouver BC V6J 4S6",
    "addr:postcode":"v6j 4s6",
    "iso:country":"CA",
    "sg:city":"Vancouver",
    "sg:classifiers":[
        {
            "category":"Banks & Credit Unions",
            "subcategory":"Investment Brokerage",
            "type":"Services"
        }
    ],
    "sg:phone":"+1 604 681 9100",
    "sg:postcode":"V6J 4S6",
    "sg:province":"BC",
    "wof:name":"Cantrell Capital Corp",
    "wof:placetype":"venue"
},
  "geometry": {"coordinates":[-123.142769,49.265308],"type":"Point"}
}