{
  "type": "Feature",
  "properties": {
    "addr:full":"Abbotsford BC V2S 2L8",
    "addr:postcode":"v2s 2l8",
    "iso:country":"CA",
    "sg:city":"Abbotsford",
    "sg:classifiers":[
        {
            "category":"Building & Trades",
            "subcategory":"Construction",
            "type":"Services"
        }
    ],
    "sg:phone":"+1 604 852 6402",
    "sg:postcode":"V2S 2L8",
    "sg:province":"BC",
    "sg:tags":[
        "roofing",
        "contractor"
    ],
    "wof:name":"Doerksen Roofing Inc",
    "wof:placetype":"venue"
},
  "geometry": {"coordinates":[-122.312943,49.056019],"type":"Point"}
}