{
  "type": "Feature",
  "properties": {
    "addr:full":"Halifax NS B3L 2H8",
    "addr:postcode":"b3l 2h8",
    "iso:country":"CA",
    "sg:city":"Halifax",
    "sg:classifiers":[
        {
            "category":"Health Services",
            "subcategory":"Health Practitioner",
            "type":"Services"
        }
    ],
    "sg:phone":"+1 902 454 2828",
    "sg:postcode":"B3L 2H8",
    "sg:province":"NS",
    "sg:tags":[
        "correction",
        "laser",
        "vision"
    ],
    "wof:name":"Nova Vision Ctr Inc",
    "wof:placetype":"venue"
},
  "geometry": {"coordinates":[-63.6196632385,44.6477851868],"type":"Point"}
}