{
  "type": "Feature",
  "properties": {
    "addr:full":"28 Titus St Halifax NS B3M 2N4",
    "addr:housenumber":"28",
    "addr:postcode":"b3m 2n4",
    "addr:street":"Titus St",
    "iso:country":"CA",
    "sg:address":"28 Titus St",
    "sg:city":"Halifax",
    "sg:classifiers":[
        {
            "category":"Food & Beverages",
            "subcategory":"Groceries & Convenience Stores",
            "type":"Retail Goods"
        }
    ],
    "sg:phone":"+1 902 445 4736",
    "sg:postcode":"B3M 2N4",
    "sg:province":"NS",
    "sg:tags":[
        "grocer"
    ],
    "wof:name":"Bluenose Mini Market",
    "wof:placetype":"venue"
},
  "geometry": {"coordinates":[-63.6350479126,44.660068512],"type":"Point"}
}