{
  "type": "Feature",
  "properties": {
    "iso:country":"CA",
    "sg:city":"Brampton",
    "sg:classifiers":[
        {
            "category":"Professional",
            "subcategory":"Lawyer & Legal Services",
            "type":"Services"
        }
    ],
    "sg:phone":"+1 905 451 6714",
    "sg:postcode":"L6V 1A3",
    "sg:province":"ON",
    "sg:tags":[
        "attorney"
    ],
    "wof:name":"Davis, Neil G",
    "wof:placetype":"venue"
},
  "geometry": {"coordinates":[-79.759475708,43.6865463257],"type":"Point"}
}