{
  "type": "Feature",
  "properties": {
    "iso:country":"CA",
    "sg:address":"3408 Rue Jalbert",
    "sg:city":"Levis",
    "sg:classifiers":[
        {
            "category":"Manufacturing",
            "subcategory":"Jewelry",
            "type":"Manufacturing & Wholesale Goods"
        }
    ],
    "sg:phone":"+1 418 833 5008",
    "sg:postcode":"G6V 4Y3",
    "sg:province":"QC",
    "sg:tags":[
        "craftsman",
        "jeweler"
    ],
    "wof:name":"Lepage Joaillier Inc",
    "wof:placetype":"venue"
},
  "geometry": {"coordinates":[-71.20993804930001,46.7719688416],"type":"Point"}
}