{
  "type": "Feature",
  "properties": {
    "addr:full":"1203 Roselawn Ave York ON M6B 1C6",
    "addr:housenumber":"1203",
    "addr:postcode":"m6b 1c6",
    "addr:street":"Roselawn Ave",
    "iso:country":"CA",
    "sg:address":"1203 Roselawn Ave",
    "sg:city":"York",
    "sg:classifiers":[
        {
            "category":"Arts & Performance",
            "subcategory":"Theater",
            "type":"Entertainment"
        }
    ],
    "sg:phone":"+1 416 789 0242",
    "sg:postcode":"M6B 1C6",
    "sg:province":"ON",
    "sg:tags":[
        "television",
        "program",
        "producer"
    ],
    "wof:name":"Gpi Corp",
    "wof:placetype":"venue"
},
  "geometry": {"coordinates":[-79.45529174799999,43.6992721558],"type":"Point"}
}