{
  "type": "Feature",
  "properties": {
    "addr:full":"840 Rue Alfred-Viau Saint-Jerome QC J7Y 4N8",
    "addr:housenumber":"840",
    "addr:postcode":"j7y 4n8",
    "addr:street":"Rue Alfred-Viau Saint-Jerome",
    "iso:country":"CA",
    "sg:address":"840 Rue Alfred-Viau",
    "sg:city":"Saint-Jerome",
    "sg:classifiers":[
        {
            "category":"Manufacturing",
            "subcategory":"Food",
            "type":"Manufacturing & Wholesale Goods"
        }
    ],
    "sg:phone":"+1 450 565 2300",
    "sg:postcode":"J7Y 4N8",
    "sg:province":"QC",
    "sg:tags":[
        "brewer"
    ],
    "wof:name":"Molson Canada-Region Du Quebec",
    "wof:placetype":"venue"
},
  "geometry": {"coordinates":[-74.02443700000001,45.764668],"type":"Point"}
}