{
  "type": "Feature",
  "properties": {
    "iso:country":"CA",
    "sg:city":"Thunder Bay",
    "sg:classifiers":[
        {
            "category":"Organizations",
            "subcategory":"Labor Organization",
            "type":"Services"
        }
    ],
    "sg:phone":"+1 807 624 9131",
    "sg:postcode":"P7C 1J6",
    "sg:province":"ON",
    "wof:name":"Cupw",
    "wof:placetype":"venue"
},
  "geometry": {"coordinates":[-89.244133,48.385353],"type":"Point"}
}