{
  "type": "Feature",
  "properties": {
    "addr:full":"618 Columbia St # 3 New Westminster BC V3M 1A5",
    "addr:housenumber":"618",
    "addr:postcode":"v3m 1a5",
    "addr:street":"Columbia St # 3",
    "iso:country":"CA",
    "sg:address":"618 Columbia St # 3",
    "sg:city":"New Westminster",
    "sg:classifiers":[
        {
            "category":"Professional",
            "type":"Services"
        }
    ],
    "sg:phone":"+1 604 519 1551",
    "sg:postcode":"V3M 1A5",
    "sg:province":"BC",
    "sg:tags":[
        "nurse",
        "establishment",
        "registry"
    ],
    "wof:name":"Assured Care of Shaughnessy",
    "wof:placetype":"venue"
},
  "geometry": {"coordinates":[-122.90815000000001,49.202847],"type":"Point"}
}