{
  "type": "Feature",
  "properties": {
    "addr:full":"245 Av Victoria # 120 Westmount QC H3Z 2M6",
    "addr:housenumber":"245",
    "addr:postcode":"h3z 2m6",
    "addr:street":"Av Victoria # 120",
    "iso:country":"CA",
    "sg:address":"245 Av Victoria # 120",
    "sg:city":"Westmount",
    "sg:classifiers":[
        {
            "category":"Health Services",
            "subcategory":"Health Practitioner",
            "type":"Services"
        }
    ],
    "sg:phone":"+1 514 931 4848",
    "sg:postcode":"H3Z 2M6",
    "sg:province":"QC",
    "sg:tags":[
        "psychologist"
    ],
    "wof:name":"Lalinec, Constance",
    "wof:placetype":"venue"
},
  "geometry": {"coordinates":[-73.599403,45.477222],"type":"Point"}
}