{
  "type": "Feature",
  "properties": {
    "iso:country":"CA",
    "sg:address":"11520 3rd Ave",
    "sg:city":"Richmond",
    "sg:classifiers":[
        {
            "category":"Wholesale",
            "subcategory":"Medical Equipment & Supplies",
            "type":"Manufacturing & Wholesale Goods"
        }
    ],
    "sg:phone":"+1 604 274 9310",
    "sg:postcode":"V7E 4W4",
    "sg:province":"BC",
    "sg:tags":[
        "dental"
    ],
    "wof:name":"Dentist's Choice",
    "wof:placetype":"venue"
},
  "geometry": {"coordinates":[-123.18547821,49.1299629211],"type":"Point"}
}