{
  "type": "Feature",
  "properties": {
    "addr:full":"220 Basaltic Rd Concord ON L4K 1G6",
    "addr:housenumber":"220",
    "addr:postcode":"l4k 1g6",
    "addr:street":"Basaltic Rd",
    "iso:country":"CA",
    "sg:address":"220 Basaltic Rd",
    "sg:city":"Concord",
    "sg:classifiers":[
        {
            "category":"Building & Trades",
            "subcategory":"Construction",
            "type":"Services"
        }
    ],
    "sg:phone":"+1 905 669 9579",
    "sg:postcode":"L4K 1G6",
    "sg:province":"ON",
    "sg:tags":[
        "paving",
        "contractor"
    ],
    "wof:name":"Vaughan Paving Ltd",
    "wof:placetype":"venue"
},
  "geometry": {"coordinates":[-79.49816131590001,43.8254508972],"type":"Point"}
}