{
  "type": "Feature",
  "properties": {
    "addr:full":"Montreal QC H3A 1G1",
    "addr:postcode":"h3a 1g1",
    "iso:country":"CA",
    "sg:city":"Montreal",
    "sg:classifiers":[
        {
            "category":"Real Estate",
            "subcategory":"Real Estate Agent",
            "type":"Services"
        }
    ],
    "sg:phone":"+1 514 847 9461",
    "sg:postcode":"H3A 1G1",
    "sg:province":"QC",
    "sg:tags":[
        "management"
    ],
    "wof:name":"Sitq Immobilier",
    "wof:placetype":"venue"
},
  "geometry": {"coordinates":[-73.573624,45.503395],"type":"Point"}
}