{
  "type": "Feature",
  "properties": {
    "addr:full":"42 Noam Dr Barrie ON L4N 4P2",
    "addr:housenumber":"42",
    "addr:postcode":"l4n 4p2",
    "addr:street":"Noam Dr",
    "iso:country":"CA",
    "sg:address":"42 Noam Dr",
    "sg:city":"Barrie",
    "sg:classifiers":[
        {
            "category":"Building & Trades",
            "subcategory":"Construction",
            "type":"Services"
        }
    ],
    "sg:phone":"+1 705 728 2702",
    "sg:postcode":"L4N 4P2",
    "sg:province":"ON",
    "sg:tags":[
        "home",
        "siding",
        "material",
        "improvement"
    ],
    "wof:name":"Simcoe Aluminum Svc",
    "wof:placetype":"venue"
},
  "geometry": {"coordinates":[-79.7124328613,44.4048500061],"type":"Point"}
}