{
  "type": "Feature",
  "properties": {
    "addr:full":"1258 Wellington St W Ottawa ON K1Y 3A5",
    "addr:housenumber":"1258",
    "addr:postcode":"k1y 3a5",
    "addr:street":"Wellington St W",
    "iso:country":"CA",
    "sg:address":"1258 Wellington St W",
    "sg:city":"Ottawa",
    "sg:classifiers":[
        {
            "category":"Shopping",
            "subcategory":"Clothing, Apparel, & Fashions",
            "type":"Retail Goods"
        }
    ],
    "sg:phone":"+1 613 798 0167",
    "sg:postcode":"K1Y 3A5",
    "sg:province":"ON",
    "sg:tags":[
        "designer"
    ],
    "wof:name":"Clothes By Muriel Dombret",
    "wof:placetype":"venue"
},
  "geometry": {"coordinates":[-75.73329200000001,45.399246],"type":"Point"}
}