{
  "type": "Feature",
  "properties": {
    "addr:full":"137 7E Av New Richmond QC G0C 2B0",
    "addr:housenumber":"137",
    "addr:postcode":"g0c 2b0",
    "addr:street":"7E Av",
    "iso:country":"CA",
    "sg:address":"137 7E Av",
    "sg:city":"New Richmond",
    "sg:classifiers":[
        {
            "category":"Personal",
            "subcategory":"Tanning Parlor",
            "type":"Services"
        }
    ],
    "sg:phone":"+1 418 392 5228",
    "sg:postcode":"G0C 2B0",
    "sg:province":"QC",
    "sg:tags":[
        "salon",
        "electrolysis"
    ],
    "wof:name":"Salon D'Esthetique Expression",
    "wof:placetype":"venue"
},
  "geometry": {"coordinates":[-65.8535461426,48.1693191528],"type":"Point"}
}