{
  "type": "Feature",
  "properties": {
    "addr:full":"2940 Boul Lemire Drummondville QC J2B 7J6",
    "addr:housenumber":"2940",
    "addr:postcode":"j2b 7j6",
    "addr:street":"Boul Lemire",
    "iso:country":"CA",
    "sg:address":"2940 Boul Lemire",
    "sg:city":"Drummondville",
    "sg:classifiers":[
        {
            "category":"Wholesale",
            "subcategory":"Office Equipment",
            "type":"Manufacturing & Wholesale Goods"
        }
    ],
    "sg:phone":"+1 819 478 1967",
    "sg:postcode":"J2B 7J6",
    "sg:province":"QC",
    "sg:tags":[
        "accounting",
        "bookkeeping",
        "system"
    ],
    "wof:name":"Gestions Info-Comdac Inc",
    "wof:placetype":"venue"
},
  "geometry": {"coordinates":[-72.485794,45.856915],"type":"Point"}
}