{
  "type": "Feature",
  "properties": {
    "iso:country":"CA",
    "sg:address":"6138 Main St",
    "sg:city":"Stouffville",
    "sg:classifiers":[
        {
            "category":"Professional",
            "subcategory":"Accounting & Tax Preparation",
            "type":"Services"
        }
    ],
    "sg:phone":"+1 905 640 1778",
    "sg:postcode":"L4A 1A5",
    "sg:province":"ON",
    "sg:tags":[
        "return",
        "filing"
    ],
    "wof:name":"George Brodie Accounting Svc",
    "wof:placetype":"venue"
},
  "geometry": {"coordinates":[-79.25113677980001,43.9705352783],"type":"Point"}
}