{
  "type": "Feature",
  "properties": {
    "addr:full":"Vancouver BC V5S 1J9",
    "addr:postcode":"v5s 1j9",
    "iso:country":"CA",
    "sg:city":"Vancouver",
    "sg:classifiers":[
        {
            "category":"Professional",
            "subcategory":"Business Services",
            "type":"Services"
        }
    ],
    "sg:phone":"+1 604 434 8279",
    "sg:postcode":"V5S 1J9",
    "sg:province":"BC",
    "sg:tags":[
        "notary"
    ],
    "wof:name":"Chung, Agatha S",
    "wof:placetype":"venue"
},
  "geometry": {"coordinates":[-123.05437469500001,49.2249984741],"type":"Point"}
}