{
  "type": "Feature",
  "properties": {
    "addr:full":"Calgary AB T3H 3C8",
    "addr:postcode":"t3h 3c8",
    "iso:country":"CA",
    "sg:city":"Calgary",
    "sg:classifiers":[
        {
            "category":"Professional",
            "subcategory":"Business Services",
            "type":"Services"
        }
    ],
    "sg:phone":"+1 403 265 8133",
    "sg:postcode":"T3H 3C8",
    "sg:province":"AB",
    "sg:tags":[
        "lecture",
        "training",
        "bureau",
        "sales",
        "seminar"
    ],
    "wof:name":"Summit Learning Systems",
    "wof:placetype":"venue"
},
  "geometry": {"coordinates":[-114.169113,51.015247],"type":"Point"}
}