{
  "type": "Feature",
  "properties": {
    "addr:full":"251 Davidson St Neepawa MB R0J 1H0",
    "addr:housenumber":"251",
    "addr:postcode":"r0j 1h0",
    "addr:street":"Davidson St",
    "iso:country":"CA",
    "sg:address":"251 Davidson St",
    "sg:city":"Neepawa",
    "sg:classifiers":[
        {
            "category":"Professional",
            "subcategory":"Accounting & Tax Preparation",
            "type":"Services"
        }
    ],
    "sg:phone":"+1 204 476 2326",
    "sg:postcode":"R0J 1H0",
    "sg:province":"MB",
    "sg:tags":[
        "accountant"
    ],
    "wof:name":"Meyers Norris Penny",
    "wof:placetype":"venue"
},
  "geometry": {"coordinates":[-99.46257799999999,50.229343],"type":"Point"}
}