{
  "type": "Feature",
  "properties": {
    "addr:full":"103 Main St Benito MB R0L 0C0",
    "addr:housenumber":"103",
    "addr:postcode":"r0l 0c0",
    "addr:street":"Main St",
    "iso:country":"CA",
    "sg:address":"103 Main St",
    "sg:city":"Benito",
    "sg:classifiers":[
        {
            "category":"Banks & Credit Unions",
            "subcategory":"Bank",
            "type":"Services"
        }
    ],
    "sg:phone":"+1 204 539 2400",
    "sg:postcode":"R0L 0C0",
    "sg:province":"MB",
    "wof:name":"Swan Valley Credit Union Ltd",
    "wof:placetype":"venue"
},
  "geometry": {"coordinates":[-101.55149078399999,51.917263031],"type":"Point"}
}