{
  "type": "Feature",
  "properties": {
    "addr:full":"48 Cote Du Passage Levis QC G6V 5S7",
    "addr:housenumber":"48",
    "addr:postcode":"g6v 5s7",
    "addr:street":"Cote Du Passage",
    "iso:country":"CA",
    "sg:address":"48 Cote Du Passage",
    "sg:city":"Levis",
    "sg:classifiers":[
        {
            "category":"Shopping",
            "type":"Retail Goods"
        }
    ],
    "sg:phone":"+1 418 837 4099",
    "sg:postcode":"G6V 5S7",
    "sg:province":"QC",
    "sg:tags":[
        "art",
        "gallery",
        "dealer"
    ],
    "wof:name":"Collectif Regart Inc",
    "wof:placetype":"venue"
},
  "geometry": {"coordinates":[-71.1841659546,46.8065109253],"type":"Point"}
}