{
  "type": "Feature",
  "properties": {
    "iso:country":"CA",
    "sg:address":"75 Selby Rd",
    "sg:city":"Brampton",
    "sg:classifiers":[
        {
            "category":"Manufacturing",
            "subcategory":"Tools & Machinery",
            "type":"Manufacturing & Wholesale Goods"
        }
    ],
    "sg:phone":"+1 905 454 7632",
    "sg:postcode":"L6W 1K5",
    "sg:province":"ON",
    "sg:tags":[
        "equipment",
        "plating",
        "supply"
    ],
    "wof:name":"Industrial Plastics Fabric",
    "wof:placetype":"venue"
},
  "geometry": {"coordinates":[-79.7250747681,43.6926498413],"type":"Point"}
}