{
  "type": "Feature",
  "properties": {
    "addr:full":"North Side Main St Twillingate NL A0G 4M0",
    "addr:postcode":"a0g 4m0",
    "addr:street":"North Side Main St Twillingate",
    "iso:country":"CA",
    "sg:address":"North Side Main St",
    "sg:city":"Twillingate",
    "sg:classifiers":[
        {
            "category":"Home & Garden",
            "subcategory":"Building Materials",
            "type":"Retail Goods"
        }
    ],
    "sg:phone":"+1 709 884 5544",
    "sg:postcode":"A0G 4M0",
    "sg:province":"NL",
    "sg:tags":[
        "hardware"
    ],
    "wof:name":"Notre Dame Agencies Ltd",
    "wof:placetype":"venue"
},
  "geometry": {"coordinates":[-54.775974,49.656921],"type":"Point"}
}