{
  "type": "Feature",
  "properties": {
    "addr:full":"1150 Old Sambro Rd Harrietsfield NS B3V 1B1",
    "addr:housenumber":"1150",
    "addr:postcode":"b3v 1b1",
    "addr:street":"Old Sambro Rd",
    "iso:country":"CA",
    "sg:address":"1150 Old Sambro Rd",
    "sg:city":"Harrietsfield",
    "sg:classifiers":[
        {
            "category":"Education",
            "subcategory":"School",
            "type":"Public Place"
        }
    ],
    "sg:phone":"+1 902 479 4230",
    "sg:postcode":"B3V 1B1",
    "sg:province":"NS",
    "wof:name":"Harrietsfield Elementary Schl",
    "wof:placetype":"venue"
},
  "geometry": {"coordinates":[-63.634911,44.568676],"type":"Point"}
}