{
  "type": "Feature",
  "properties": {
    "addr:full":"1049 Waterton Ave Pincher Creek AB T0K 1W0",
    "addr:housenumber":"1049",
    "addr:postcode":"t0k 1w0",
    "addr:street":"Waterton Ave",
    "iso:country":"CA",
    "sg:address":"1049 Waterton Ave",
    "sg:city":"Pincher Creek",
    "sg:classifiers":[
        {
            "category":"Travel",
            "subcategory":"Hotels & Motels",
            "type":"Entertainment"
        }
    ],
    "sg:phone":"+1 403 627 3341",
    "sg:postcode":"T0K 1W0",
    "sg:province":"AB",
    "wof:name":"Foothills Motel",
    "wof:placetype":"venue"
},
  "geometry": {"coordinates":[-113.936515808,49.4872817993],"type":"Point"}
}