{
  "type": "Feature",
  "properties": {
    "addr:full":"425 Dundas St Woodstock ON N4S 1B8",
    "addr:housenumber":"425",
    "addr:postcode":"n4s 1b8",
    "addr:street":"Dundas St",
    "iso:country":"CA",
    "sg:address":"425 Dundas St",
    "sg:city":"Woodstock",
    "sg:classifiers":[
        {
            "category":"Government",
            "subcategory":"Office",
            "type":"Public Place"
        }
    ],
    "sg:phone":"+1 519 537 3662",
    "sg:postcode":"N4S 1B8",
    "sg:province":"ON",
    "wof:name":"Ontario Transportation Dept",
    "wof:placetype":"venue"
},
  "geometry": {"coordinates":[-80.75901,43.129906],"type":"Point"}
}