{
  "type": "Feature",
  "properties": {
    "addr:full":"Saint-Boniface-DE-Shawinigan QC G0X 2L0",
    "addr:postcode":"g0x 2l0",
    "iso:country":"CA",
    "sg:city":"Saint-Boniface-DE-Shawinigan",
    "sg:classifiers":[
        {
            "category":"Shopping",
            "subcategory":"Pharmacy",
            "type":"Retail Goods"
        }
    ],
    "sg:phone":"+1 819 535 3775",
    "sg:postcode":"G0X 2L0",
    "sg:province":"QC",
    "wof:name":"Pharmacie Huguette Gauvin",
    "wof:placetype":"venue"
},
  "geometry": {"coordinates":[-72.82756000000001,46.503815],"type":"Point"}
}