{
  "type": "Feature",
  "properties": {
    "iso:country":"CA",
    "sg:address":"16 John St W",
    "sg:city":"Bradford",
    "sg:classifiers":[
        {
            "category":"Recreation",
            "type":"Entertainment"
        }
    ],
    "sg:phone":"+1 905 775 1413",
    "sg:postcode":"L3Z 2B3",
    "sg:province":"ON",
    "sg:tags":[
        "martial",
        "arts",
        "instruction"
    ],
    "wof:name":"Jennings School of Karate",
    "wof:placetype":"venue"
},
  "geometry": {"coordinates":[-79.5654602051,44.115020752],"type":"Point"}
}