{
  "type": "Feature",
  "properties": {
    "iso:country":"CA",
    "sg:address":"205 3 Ave N",
    "sg:city":"Delia",
    "sg:classifiers":[
        {
            "category":"Education",
            "subcategory":"School",
            "type":"Public Place"
        }
    ],
    "sg:phone":"+1 403 364 3777",
    "sg:postcode":"T0J 0W0",
    "sg:province":"AB",
    "wof:name":"Delia School",
    "wof:placetype":"venue"
},
  "geometry": {"coordinates":[-112.376747,51.632126],"type":"Point"}
}