{
  "type": "Feature",
  "properties": {
    "addr:full":"421 33 St N Lethbridge AB T1H 3Z6",
    "addr:housenumber":"421 33",
    "addr:postcode":"t1h 3z6",
    "addr:street":"St N",
    "iso:country":"CA",
    "sg:address":"421 33 St N",
    "sg:city":"Lethbridge",
    "sg:classifiers":[
        {
            "category":"Utilities",
            "subcategory":"Fuel Oil & Lpg",
            "type":"Services"
        }
    ],
    "sg:phone":"+1 403 381 4040",
    "sg:postcode":"T1H 3Z6",
    "sg:province":"AB",
    "sg:tags":[
        "propane",
        "gas"
    ],
    "wof:name":"Blue Flame Propane Inc",
    "wof:placetype":"venue"
},
  "geometry": {"coordinates":[-112.791168,49.703403],"type":"Point"}
}