{
  "type": "Feature",
  "properties": {
    "iso:country":"CA",
    "sg:address":"700 Centre St SE",
    "sg:city":"Calgary",
    "sg:classifiers":[
        {
            "category":"Travel",
            "subcategory":"Hotels & Motels",
            "type":"Entertainment"
        }
    ],
    "sg:phone":"+1 403 717 1234",
    "sg:postcode":"T2G 5P6",
    "sg:province":"AB",
    "wof:name":"Hyatt Regency Calgary",
    "wof:placetype":"venue"
},
  "geometry": {"coordinates":[-114.062934876,51.0463447571],"type":"Point"}
}