{
  "type": "Feature",
  "properties": {
    "addr:full":"Concord ON L4K 2S4",
    "addr:postcode":"l4k 2s4",
    "iso:country":"CA",
    "sg:city":"Concord",
    "sg:classifiers":[
        {
            "category":"Wholesale",
            "subcategory":"Meat",
            "type":"Manufacturing & Wholesale Goods"
        }
    ],
    "sg:phone":"+1 905 738 0595",
    "sg:postcode":"L4K 2S4",
    "sg:province":"ON",
    "sg:tags":[
        "product"
    ],
    "wof:name":"Victors Custom Quality Meats",
    "wof:placetype":"venue"
},
  "geometry": {"coordinates":[-79.48786200000001,43.824142],"type":"Point"}
}