{
  "type": "Feature",
  "properties": {
    "addr:full":"280 King St W Hamilton ON L8P 1B1",
    "addr:housenumber":"280",
    "addr:postcode":"l8p 1b1",
    "addr:street":"King St W",
    "iso:country":"CA",
    "sg:address":"280 King St W",
    "sg:city":"Hamilton",
    "sg:classifiers":[
        {
            "category":"Professional",
            "subcategory":"Accounting & Tax Preparation",
            "type":"Services"
        }
    ],
    "sg:phone":"+1 905 522 3561",
    "sg:postcode":"L8P 1B1",
    "sg:province":"ON",
    "sg:tags":[
        "accountant"
    ],
    "wof:name":"North & Slattery",
    "wof:placetype":"venue"
},
  "geometry": {"coordinates":[-79.87771606450001,43.2592086792],"type":"Point"}
}