{
  "type": "Feature",
  "properties": {
    "addr:full":"12 Rue Sainte-Marie Hull QC J8Y 2A3",
    "addr:housenumber":"12",
    "addr:postcode":"j8y 2a3",
    "addr:street":"Rue Sainte-Marie",
    "iso:country":"CA",
    "sg:address":"12 Rue Sainte-Marie",
    "sg:city":"Hull",
    "sg:classifiers":[
        {
            "category":"Banks & Credit Unions",
            "subcategory":"Investment Brokerage",
            "type":"Services"
        }
    ],
    "sg:phone":"+1 819 772 4737",
    "sg:postcode":"J8Y 2A3",
    "sg:province":"QC",
    "sg:tags":[
        "advisory",
        "financial",
        "insurance"
    ],
    "wof:name":"Pratte & Assoc",
    "wof:placetype":"venue"
},
  "geometry": {"coordinates":[-75.733513,45.44191],"type":"Point"}
}