{
  "type": "Feature",
  "properties": {
    "iso:country":"CA",
    "sg:address":"110 Meadowbank Rd",
    "sg:city":"Etobicoke",
    "sg:classifiers":[
        {
            "category":"Retail",
            "subcategory":"Repair Shop",
            "type":"Services"
        }
    ],
    "sg:phone":"+1 416 622 5511",
    "sg:postcode":"M9B 5C9",
    "sg:province":"ON",
    "sg:tags":[
        "repairing",
        "piano",
        "refinishing"
    ],
    "wof:name":"Delyea Pianos Inc",
    "wof:placetype":"venue"
},
  "geometry": {"coordinates":[-79.5603713989,43.6532783508],"type":"Point"}
}