{
  "type": "Feature",
  "properties": {
    "addr:full":"339 Rang DE LA Grande-Ligne Saint-Alexis-DE-Montcalm QC J0K 1T0",
    "addr:housenumber":"339",
    "addr:postcode":"j0k 1t0",
    "addr:street":"Rang De La Grande-Ligne Saint-Alexis-De-Montcalm",
    "iso:country":"CA",
    "sg:address":"339 Rang DE LA Grande-Ligne",
    "sg:city":"Saint-Alexis-DE-Montcalm",
    "sg:classifiers":[
        {
            "category":"Building & Trades",
            "subcategory":"Construction",
            "type":"Services"
        }
    ],
    "sg:phone":"+1 450 839 6184",
    "sg:postcode":"J0K 1T0",
    "sg:province":"QC",
    "sg:tags":[
        "general",
        "contractor"
    ],
    "wof:name":"Construction C Lafontaine Inc",
    "wof:placetype":"venue"
},
  "geometry": {"coordinates":[-73.6132659912,45.932964325],"type":"Point"}
}