{
  "type": "Feature",
  "properties": {
    "addr:full":"1011 S 11th Ave S Golden BC V0A 1H0",
    "addr:housenumber":"1011",
    "addr:postcode":"v0a 1h0",
    "addr:street":"S 11Th Ave S",
    "iso:country":"CA",
    "sg:address":"1011 S 11th Ave S",
    "sg:city":"Golden",
    "sg:classifiers":[
        {
            "category":"Organizations",
            "subcategory":"Community Association",
            "type":"Services"
        }
    ],
    "sg:phone":"+1 250 344 6214",
    "sg:postcode":"V0A 1H0",
    "sg:province":"BC",
    "sg:tags":[
        "fraternal"
    ],
    "wof:name":"Royal Canadian Legion",
    "wof:placetype":"venue"
},
  "geometry": {"coordinates":[-116.97244999999999,51.309155],"type":"Point"}
}