{
  "type": "Feature",
  "properties": {
    "iso:country":"CA",
    "sg:city":"Ottawa",
    "sg:classifiers":[
        {
            "category":"Professional",
            "subcategory":"Lawyer & Legal Services",
            "type":"Services"
        }
    ],
    "sg:phone":"+1 613 232 9364",
    "sg:postcode":"K2P 0G1",
    "sg:province":"ON",
    "sg:tags":[
        "attorney"
    ],
    "wof:name":"Mac Lellan, Carey",
    "wof:placetype":"venue"
},
  "geometry": {"coordinates":[-75.6904373169,45.4185829163],"type":"Point"}
}