{
  "type": "Feature",
  "properties": {
    "addr:full":"1 Boul Charest O Quebec QC G1K 1X1",
    "addr:housenumber":"1",
    "addr:postcode":"g1k 1x1",
    "addr:street":"Boul Charest O",
    "iso:country":"CA",
    "sg:address":"1 Boul Charest O",
    "sg:city":"Quebec",
    "sg:classifiers":[
        {
            "category":"Restaurant",
            "type":"Food & Drink"
        }
    ],
    "sg:phone":"+1 418 529 0598",
    "sg:postcode":"G1K 1X1",
    "sg:province":"QC",
    "wof:name":"Bistro Du Quartier",
    "wof:placetype":"venue"
},
  "geometry": {"coordinates":[-71.23041499999999,46.811363],"type":"Point"}
}