{
  "type": "Feature",
  "properties": {
    "iso:country":"CA",
    "sg:address":"1 Boul Charest O",
    "sg:city":"Quebec",
    "sg:classifiers":[
        {
            "category":"Restaurant",
            "type":"Food & Drink"
        }
    ],
    "sg:phone":"+1 418 529 0598",
    "sg:postcode":"G1K 1X1",
    "sg:province":"QC",
    "wof:name":"Bistro Du Quartier",
    "wof:placetype":"venue"
},
  "geometry": {"coordinates":[-71.230415,46.811363],"type":"Point"}
}