{
  "type": "Feature",
  "properties": {
    "iso:country":"CA",
    "sg:address":"37 Ch Smith",
    "sg:city":"Saint-Basile",
    "sg:classifiers":[
        {
            "category":"Organizations",
            "subcategory":"Religious Organization",
            "type":"Services"
        }
    ],
    "sg:phone":"+1 506 263 5507",
    "sg:postcode":"E7C 2J6",
    "sg:province":"NB",
    "sg:tags":[
        "church"
    ],
    "wof:name":"Chretiens Reunis",
    "wof:placetype":"venue"
},
  "geometry": {"coordinates":[-68.1561203003,47.3555793762],"type":"Point"}
}