{
  "type": "Feature",
  "properties": {
    "addr:full":"17 King St N Cookstown ON L0L 1L0",
    "addr:housenumber":"17",
    "addr:postcode":"l0l 1l0",
    "addr:street":"King St N",
    "iso:country":"CA",
    "sg:address":"17 King St N",
    "sg:city":"Cookstown",
    "sg:classifiers":[
        {
            "category":"Autos & Motor Vehicles",
            "subcategory":"Fuel & Gas Station",
            "type":"Retail Goods"
        }
    ],
    "sg:phone":"+1 705 458 2630",
    "sg:postcode":"L0L 1L0",
    "sg:province":"ON",
    "sg:tags":[
        "oil"
    ],
    "wof:name":"Upi Gas Bar",
    "wof:placetype":"venue"
},
  "geometry": {"coordinates":[-79.70188899999999,44.191795],"type":"Point"}
}