{
  "type": "Feature",
  "properties": {
    "addr:full":"8760 Boul Des Forges Trois-Rivieres QC G8Y 4E7",
    "addr:housenumber":"8760",
    "addr:postcode":"g8y 4e7",
    "addr:street":"Boul Des Forges Trois-Rivieres",
    "iso:country":"CA",
    "sg:address":"8760 Boul Des Forges",
    "sg:city":"Trois-Rivieres",
    "sg:classifiers":[
        {
            "category":"Building & Trades",
            "subcategory":"Landscaping Services",
            "type":"Services"
        }
    ],
    "sg:phone":"+1 819 375 9307",
    "sg:postcode":"G8Y 4E7",
    "sg:province":"QC",
    "sg:tags":[
        "landscape",
        "contractor"
    ],
    "wof:name":"Services Paysagistes-Vieilles",
    "wof:placetype":"venue"
},
  "geometry": {"coordinates":[-72.637421,46.383648],"type":"Point"}
}