{
  "type": "Feature",
  "properties": {
    "addr:full":"New Dundee ON N0B 2E0",
    "addr:postcode":"n0b 2e0",
    "iso:country":"CA",
    "sg:city":"New Dundee",
    "sg:classifiers":[
        {
            "category":"Mining & Drilling",
            "type":"Manufacturing & Wholesale Goods"
        }
    ],
    "sg:phone":"+1 519 696 3774",
    "sg:postcode":"N0B 2E0",
    "sg:province":"ON",
    "sg:tags":[
        "equipment",
        "landscaping",
        "supply"
    ],
    "wof:name":"Landscape Supply Depot",
    "wof:placetype":"venue"
},
  "geometry": {"coordinates":[-80.5629730225,43.370929718],"type":"Point"}
}