{
  "type": "Feature",
  "properties": {
    "addr:full":"729 Wall St Winnipeg MB R3G 2T6",
    "addr:housenumber":"729",
    "addr:postcode":"r3g 2t6",
    "addr:street":"Wall St",
    "iso:country":"CA",
    "sg:address":"729 Wall St",
    "sg:city":"Winnipeg",
    "sg:classifiers":[
        {
            "category":"Retail",
            "subcategory":"Auto Repair",
            "type":"Services"
        }
    ],
    "sg:phone":"+1 204 783 0643",
    "sg:postcode":"R3G 2T6",
    "sg:province":"MB",
    "sg:tags":[
        "repairing",
        "automobile"
    ],
    "wof:name":"All City Transmission",
    "wof:placetype":"venue"
},
  "geometry": {"coordinates":[-97.1823272705,49.8890609741],"type":"Point"}
}