{
  "type": "Feature",
  "properties": {
    "addr:full":"287 Morningside Ave Scarborough ON M1E 3G1",
    "addr:housenumber":"287",
    "addr:postcode":"m1e 3g1",
    "addr:street":"Morningside Ave",
    "iso:country":"CA",
    "sg:address":"287 Morningside Ave",
    "sg:city":"Scarborough",
    "sg:classifiers":[
        {
            "category":"Food & Beverages",
            "subcategory":"Groceries & Convenience Stores",
            "type":"Retail Goods"
        }
    ],
    "sg:phone":"+1 416 286 0516",
    "sg:postcode":"M1E 3G1",
    "sg:province":"ON",
    "sg:tags":[
        "grocer"
    ],
    "wof:name":"East End Tropical Market",
    "wof:placetype":"venue"
},
  "geometry": {"coordinates":[-79.187111,43.771561],"type":"Point"}
}