{
  "type": "Feature",
  "properties": {
    "addr:full":"1179 Av Bourgogne Chambly QC J3L 1X3",
    "addr:housenumber":"1179",
    "addr:postcode":"j3l 1x3",
    "addr:street":"Av Bourgogne",
    "iso:country":"CA",
    "sg:address":"1179 Av Bourgogne",
    "sg:city":"Chambly",
    "sg:classifiers":[
        {
            "category":"Social Services",
            "subcategory":"Job Training",
            "type":"Services"
        }
    ],
    "sg:phone":"+1 450 447 3573",
    "sg:postcode":"J3L 1X3",
    "sg:province":"QC",
    "sg:tags":[
        "employment"
    ],
    "wof:name":"Carrefour Jeunesse Emploi DE",
    "wof:placetype":"venue"
},
  "geometry": {"coordinates":[-73.3017883301,45.4562835693],"type":"Point"}
}