{
  "type": "Feature",
  "properties": {
    "addr:full":"Hwy 216 S Grunthal MB R0A 0R0",
    "addr:postcode":"r0a 0r0",
    "addr:street":"Hwy 216 S Grunthal",
    "iso:country":"CA",
    "sg:address":"Hwy 216 S",
    "sg:city":"Grunthal",
    "sg:classifiers":[
        {
            "category":"Building & Trades",
            "subcategory":"Construction",
            "type":"Services"
        }
    ],
    "sg:phone":"+1 204 434 6447",
    "sg:postcode":"R0A 0R0",
    "sg:province":"MB",
    "sg:tags":[
        "woodworker",
        "furniture"
    ],
    "wof:name":"Lester's Workshop",
    "wof:placetype":"venue"
},
  "geometry": {"coordinates":[-96.8491439819,49.4060935974],"type":"Point"}
}