{
  "type": "Feature",
  "properties": {
    "addr:full":"1503 9 Ave Cold Lake AB T9M 1H1",
    "addr:housenumber":"1503",
    "addr:postcode":"t9m 1h1",
    "addr:street":"9 Ave",
    "iso:country":"CA",
    "sg:address":"1503 9 Ave",
    "sg:city":"Cold Lake",
    "sg:classifiers":[
        {
            "category":"Real Estate",
            "subcategory":"Real Estate Operator",
            "type":"Services"
        }
    ],
    "sg:phone":"+1 780 639 3424",
    "sg:postcode":"T9M 1H1",
    "sg:province":"AB",
    "sg:tags":[
        "apartment"
    ],
    "wof:name":"Lakewood Estates",
    "wof:placetype":"venue"
},
  "geometry": {"coordinates":[-110.182014,54.462559],"type":"Point"}
}