{
  "type": "Feature",
  "properties": {
    "addr:full":"Saint-Hyacinthe QC J2S 5C6",
    "addr:postcode":"j2s 5c6",
    "iso:country":"CA",
    "sg:city":"Saint-Hyacinthe",
    "sg:classifiers":[
        {
            "category":"Professional",
            "subcategory":"Lawyer & Legal Services",
            "type":"Services"
        }
    ],
    "sg:phone":"+1 450 773 0133",
    "sg:postcode":"J2S 5C6",
    "sg:province":"QC",
    "sg:tags":[
        "attorney"
    ],
    "wof:name":"Bergeron & Pellerin",
    "wof:placetype":"venue"
},
  "geometry": {"coordinates":[-72.947884,45.625786],"type":"Point"}
}