{
  "type": "Feature",
  "properties": {
    "addr:full":"7600 Glover Rd Langley BC V2Y 1Y1",
    "addr:housenumber":"7600",
    "addr:postcode":"v2y 1y1",
    "addr:street":"Glover Rd",
    "iso:country":"CA",
    "sg:address":"7600 Glover Rd",
    "sg:city":"Langley",
    "sg:classifiers":[
        {
            "category":"Education",
            "subcategory":"College",
            "type":"Public Place"
        }
    ],
    "sg:phone":"+1 604 888 7511",
    "sg:postcode":"V2Y 1Y1",
    "sg:province":"BC",
    "sg:tags":[
        "academic",
        "school"
    ],
    "wof:name":"Trinity Western University",
    "wof:placetype":"venue"
},
  "geometry": {"coordinates":[-122.60837600000001,49.139835],"type":"Point"}
}