{
  "type": "Feature",
  "properties": {
    "iso:country":"CA",
    "sg:address":"695 Rte Lagueux",
    "sg:city":"Saint-Nicolas",
    "sg:classifiers":[
        {
            "category":"Wholesale",
            "subcategory":"Metals & Minerals",
            "type":"Manufacturing & Wholesale Goods"
        }
    ],
    "sg:phone":"+1 418 831 9960",
    "sg:postcode":"G7A 1A6",
    "sg:province":"QC",
    "sg:tags":[
        "iron"
    ],
    "wof:name":"Aime Champagne Enr",
    "wof:placetype":"venue"
},
  "geometry": {"coordinates":[-71.3982925415,46.7007637024],"type":"Point"}
}