{
  "type": "Feature",
  "properties": {
    "addr:full":"940 Ch Du Sault Saint-Romuald QC G6W 5M6",
    "addr:housenumber":"940",
    "addr:postcode":"g6w 5m6",
    "addr:street":"Ch Du Sault",
    "iso:country":"CA",
    "sg:address":"940 Ch Du Sault",
    "sg:city":"Saint-Romuald",
    "sg:classifiers":[
        {
            "category":"Retail",
            "subcategory":"Laundry & Dry Cleaning",
            "type":"Services"
        }
    ],
    "sg:phone":"+1 418 834 5853",
    "sg:postcode":"G6W 5M6",
    "sg:province":"QC",
    "sg:tags":[
        "cleaners"
    ],
    "wof:name":"Nettoyeur Claude Hamel Inc",
    "wof:placetype":"venue"
},
  "geometry": {"coordinates":[-71.2692184448,46.7303543091],"type":"Point"}
}