{
  "type": "Feature",
  "properties": {
    "addr:full":"91 Queen St Niagara on the Lake ON L0S 1J0",
    "addr:housenumber":"91",
    "addr:postcode":"l0s 1j0",
    "addr:street":"Queen St;On",
    "iso:country":"CA",
    "sg:address":"91 Queen St",
    "sg:city":"Niagara on the Lake",
    "sg:classifiers":[
        {
            "category":"Real Estate",
            "subcategory":"Real Estate Agent",
            "type":"Services"
        }
    ],
    "sg:phone":"+1 905 468 8222",
    "sg:postcode":"L0S 1J0",
    "sg:province":"ON",
    "wof:name":"Century 21 City Realty Inc",
    "wof:placetype":"venue"
},
  "geometry": {"coordinates":[-79.073425,43.256226],"type":"Point"}
}