{
  "type": "Feature",
  "properties": {
    "iso:country":"CA",
    "sg:address":"4715 Pandora St",
    "sg:city":"Burnaby",
    "sg:classifiers":[
        {
            "category":"Education",
            "subcategory":"School",
            "type":"Public Place"
        }
    ],
    "sg:phone":"+1 604 664 8669",
    "sg:postcode":"V5C 2C2",
    "sg:province":"BC",
    "wof:name":"Confederation Park Elementary",
    "wof:placetype":"venue"
},
  "geometry": {"coordinates":[-122.99637603799999,49.2829093933],"type":"Point"}
}