{
  "type": "Feature",
  "properties": {
    "addr:full":"Bedford NS B4A 1E6",
    "addr:postcode":"b4a 1e6",
    "iso:country":"CA",
    "sg:city":"Bedford",
    "sg:classifiers":[
        {
            "category":"Shopping",
            "subcategory":"Computers & Home Electronics",
            "type":"Retail Goods"
        }
    ],
    "sg:phone":"+1 902 835 2500",
    "sg:postcode":"B4A 1E6",
    "sg:province":"NS",
    "sg:tags":[
        "equipment",
        "dealer"
    ],
    "wof:name":"Integrated Open Systems Ltd",
    "wof:placetype":"venue"
},
  "geometry": {"coordinates":[-63.6574745178,44.7319450378],"type":"Point"}
}