{
  "type": "Feature",
  "properties": {
    "iso:country":"CA",
    "sg:address":"NE 29-32-22W",
    "sg:city":"Pine River",
    "sg:classifiers":[
        {
            "category":"Government",
            "subcategory":"Office",
            "type":"Public Place"
        }
    ],
    "sg:phone":"+1 204 263 2164",
    "sg:postcode":"R0L 1M0",
    "sg:province":"MB",
    "wof:name":"Manitoba Maintenance Yard",
    "wof:placetype":"venue"
},
  "geometry": {"coordinates":[-100.530914307,51.7842597961],"type":"Point"}
}