{
  "type": "Feature",
  "properties": {
    "addr:full":"St. John's NL A1B 2X1",
    "addr:postcode":"a1b 2x1",
    "iso:country":"CA",
    "sg:city":"St. John's",
    "sg:classifiers":[
        {
            "category":"Travel",
            "subcategory":"Travel Agent",
            "type":"Entertainment"
        }
    ],
    "sg:phone":"+1 709 758 6788",
    "sg:postcode":"A1B 2X1",
    "sg:province":"NL",
    "sg:tags":[
        "agency",
        "bureau"
    ],
    "wof:name":"Le Grow's Travel",
    "wof:placetype":"venue"
},
  "geometry": {"coordinates":[-52.722759,47.574375],"type":"Point"}
}