{
  "type": "Feature",
  "properties": {
    "addr:full":"7031 120 St Delta BC V4E 2A9",
    "addr:housenumber":"7031",
    "addr:postcode":"v4e 2a9",
    "addr:street":"120 St",
    "iso:country":"CA",
    "sg:address":"7031 120 St",
    "sg:city":"Delta",
    "sg:classifiers":[
        {
            "category":"Professional",
            "subcategory":"Accounting & Tax Preparation",
            "type":"Services"
        }
    ],
    "sg:phone":"+1 604 590 5223",
    "sg:postcode":"V4E 2A9",
    "sg:province":"BC",
    "sg:tags":[
        "consultant",
        "accountant"
    ],
    "wof:name":"Moore Income Tax Svc",
    "wof:placetype":"venue"
},
  "geometry": {"coordinates":[-122.890556,49.131149],"type":"Point"}
}