{
  "type": "Feature",
  "properties": {
    "addr:full":"1281 Rue Du Bocage L'Ancienne-Lorette QC G2E 1G1",
    "addr:housenumber":"1281",
    "addr:postcode":"g2e 1g1",
    "addr:street":"Rue Du Bocage",
    "iso:country":"CA",
    "sg:address":"1281 Rue Du Bocage",
    "sg:city":"L'Ancienne-Lorette",
    "sg:classifiers":[
        {
            "category":"Wholesale",
            "subcategory":"Machinery & Supplies",
            "type":"Manufacturing & Wholesale Goods"
        }
    ],
    "sg:phone":"+1 418 877 4487",
    "sg:postcode":"G2E 1G1",
    "sg:province":"QC",
    "sg:tags":[
        "contractor"
    ],
    "wof:name":"Equipements Manuquip Inc",
    "wof:placetype":"venue"
},
  "geometry": {"coordinates":[-71.361183,46.812557],"type":"Point"}
}