{
  "type": "Feature",
  "properties": {
    "addr:full":"Toronto ON M5C 2W7",
    "addr:postcode":"m5c 2w7",
    "iso:country":"CA",
    "sg:city":"Toronto",
    "sg:classifiers":[
        {
            "category":"Professional",
            "subcategory":"Lawyer & Legal Services",
            "type":"Services"
        }
    ],
    "sg:phone":"+1 416 863 1188",
    "sg:postcode":"M5C 2W7",
    "sg:province":"ON",
    "sg:tags":[
        "attorney"
    ],
    "wof:name":"Stefanik, Thomas A",
    "wof:placetype":"venue"
},
  "geometry": {"coordinates":[-79.37870025629999,43.6515426636],"type":"Point"}
}