{
  "type": "Feature",
  "properties": {
    "iso:country":"CA",
    "sg:city":"North York",
    "sg:classifiers":[
        {
            "category":"Professional",
            "subcategory":"Accounting & Tax Preparation",
            "type":"Services"
        }
    ],
    "sg:phone":"+1 416 636 7500",
    "sg:postcode":"M3H 2V2",
    "sg:province":"ON",
    "sg:tags":[
        "accountant"
    ],
    "wof:name":"Rosenthal Zaretsky Niman & CO",
    "wof:placetype":"venue"
},
  "geometry": {"coordinates":[-79.446487,43.732204],"type":"Point"}
}