{
  "type": "Feature",
  "properties": {
    "addr:full":"Scarborough ON M1P 3C8",
    "addr:postcode":"m1p 3c8",
    "iso:country":"CA",
    "sg:city":"Scarborough",
    "sg:classifiers":[
        {
            "category":"Home & Garden",
            "subcategory":"Furniture",
            "type":"Retail Goods"
        }
    ],
    "sg:phone":"+1 416 288 9302",
    "sg:postcode":"M1P 3C8",
    "sg:province":"ON",
    "sg:tags":[
        "equipment",
        "kitchen",
        "cabinet"
    ],
    "wof:name":"B & M Selective Kitchens",
    "wof:placetype":"venue"
},
  "geometry": {"coordinates":[-79.268478,43.760124],"type":"Point"}
}