{
  "type": "Feature",
  "properties": {
    "addr:full":"1166 Commissioners Rd E London ON N5Z 4W8",
    "addr:housenumber":"1166",
    "addr:postcode":"n5z 4w8",
    "addr:street":"Commissioners Rd E",
    "iso:country":"CA",
    "sg:address":"1166 Commissioners Rd E",
    "sg:city":"London",
    "sg:classifiers":[
        {
            "category":"Food & Beverages",
            "subcategory":"Meat & Fish",
            "type":"Retail Goods"
        }
    ],
    "sg:phone":"+1 519 685 6581",
    "sg:postcode":"N5Z 4W8",
    "sg:province":"ON",
    "sg:tags":[
        "frozen"
    ],
    "wof:name":"M & M Meat Shops",
    "wof:placetype":"venue"
},
  "geometry": {"coordinates":[-81.197029,42.9622],"type":"Point"}
}