{
  "type": "Feature",
  "properties": {
    "addr:full":"661 Rue Principale E Sainte-Agathe-Des-Monts QC J8C 1L1",
    "addr:housenumber":"661",
    "addr:postcode":"j8c 1l1",
    "addr:street":"Rue Principale E Sainte-Agathe-Des-Monts",
    "iso:country":"CA",
    "sg:address":"661 Rue Principale E",
    "sg:city":"Sainte-Agathe-Des-Monts",
    "sg:classifiers":[
        {
            "category":"Retail",
            "subcategory":"Auto Rental",
            "type":"Services"
        }
    ],
    "sg:phone":"+1 819 326 4181",
    "sg:postcode":"J8C 1L1",
    "sg:province":"QC",
    "sg:tags":[
        "renting",
        "automobile"
    ],
    "wof:name":"National Location D'Autos",
    "wof:placetype":"venue"
},
  "geometry": {"coordinates":[-74.272308,46.044174],"type":"Point"}
}