{
  "type": "Feature",
  "properties": {
    "iso:country":"CA",
    "sg:address":"7 Albert St W",
    "sg:city":"Plattsville",
    "sg:classifiers":[
        {
            "category":"Retail",
            "subcategory":"Auto Repair",
            "type":"Services"
        }
    ],
    "sg:phone":"+1 519 684 7610",
    "sg:postcode":"N0J 1S0",
    "sg:province":"ON",
    "sg:tags":[
        "repairing",
        "automobile"
    ],
    "wof:name":"Pettigrew's Garage",
    "wof:placetype":"venue"
},
  "geometry": {"coordinates":[-80.6209945679,43.3034667969],"type":"Point"}
}