{
  "type": "Feature",
  "properties": {
    "addr:full":"4705 Hastings St Burnaby BC V5C 2K8",
    "addr:housenumber":"4705",
    "addr:postcode":"v5c 2k8",
    "addr:street":"Hastings St",
    "iso:country":"CA",
    "sg:address":"4705 Hastings St",
    "sg:city":"Burnaby",
    "sg:classifiers":[
        {
            "category":"Retail",
            "subcategory":"Auto Repair",
            "type":"Services"
        }
    ],
    "sg:phone":"+1 604 299 2122",
    "sg:postcode":"V5C 2K8",
    "sg:province":"BC",
    "sg:tags":[
        "repairing",
        "automobile"
    ],
    "wof:name":"T & S Automotive Svc Ltd",
    "wof:placetype":"venue"
},
  "geometry": {"coordinates":[-122.997032166,49.2811965942],"type":"Point"}
}