{
  "type": "Feature",
  "properties": {
    "addr:full":"702 9th St NW Meadow Lake SK S9X 1X8",
    "addr:housenumber":"702",
    "addr:postcode":"s9x 1x8",
    "addr:street":"9Th St Nw",
    "iso:country":"CA",
    "sg:address":"702 9th St NW",
    "sg:city":"Meadow Lake",
    "sg:classifiers":[
        {
            "category":"Travel",
            "subcategory":"Hotels & Motels",
            "type":"Entertainment"
        }
    ],
    "sg:phone":"+1 306 236 1188",
    "sg:postcode":"S9X 1X8",
    "sg:province":"SK",
    "wof:name":"Super 8 Motel",
    "wof:placetype":"venue"
},
  "geometry": {"coordinates":[-108.452744,54.124207],"type":"Point"}
}