{
  "type": "Feature",
  "properties": {
    "iso:country":"CA",
    "sg:address":"1702 Monument Rd",
    "sg:city":"Spring Bay",
    "sg:classifiers":[
        {
            "category":"Travel",
            "subcategory":"Campground",
            "type":"Entertainment"
        }
    ],
    "sg:phone":"+1 705 377 4661",
    "sg:postcode":"P0P 2B0",
    "sg:province":"ON",
    "wof:name":"Stanley Park",
    "wof:placetype":"venue"
},
  "geometry": {"coordinates":[-82.1673202515,45.6774749756],"type":"Point"}
}