{
  "type": "Feature",
  "properties": {
    "iso:country":"CA",
    "sg:address":"1203 Bloor St W # B",
    "sg:city":"Toronto",
    "sg:classifiers":[
        {
            "category":"Professional",
            "subcategory":"Lawyer & Legal Services",
            "type":"Services"
        }
    ],
    "sg:phone":"+1 416 532 2801",
    "sg:postcode":"M6H 1N4",
    "sg:province":"ON",
    "sg:tags":[
        "attorney"
    ],
    "wof:name":"Lalla, Tikam K",
    "wof:placetype":"venue"
},
  "geometry": {"coordinates":[-79.4396286011,43.6589355469],"type":"Point"}
}