{
  "type": "Feature",
  "properties": {
    "iso:country":"CA",
    "sg:city":"Stanbridge Station",
    "sg:classifiers":[
        {
            "category":"Professional",
            "subcategory":"Business Services",
            "type":"Services"
        }
    ],
    "sg:phone":"+1 450 248 3994",
    "sg:postcode":"J0J 2J0",
    "sg:province":"QC",
    "sg:tags":[
        "screen",
        "printing",
        "embroidery"
    ],
    "wof:name":"Serigraphie Multivision Enr",
    "wof:placetype":"venue"
},
  "geometry": {"coordinates":[-73.03559875489999,45.1256790161],"type":"Point"}
}