{
  "type": "Feature",
  "properties": {
    "iso:country":"CA",
    "sg:city":"Vancouver",
    "sg:classifiers":[
        {
            "category":"Wholesale",
            "subcategory":"Non-durable Goods",
            "type":"Manufacturing & Wholesale Goods"
        }
    ],
    "sg:phone":"+1 604 682 8066",
    "sg:postcode":"V6B 2T4",
    "sg:province":"BC",
    "wof:name":"Accents DE Ville Imports Inc",
    "wof:placetype":"venue"
},
  "geometry": {"coordinates":[-123.119667053,49.2759552002],"type":"Point"}
}