{
  "type": "Feature",
  "properties": {
    "addr:full":"335 Webb Dr Mississauga ON L5B 4A1",
    "addr:housenumber":"335",
    "addr:postcode":"l5b 4a1",
    "addr:street":"Webb Dr",
    "iso:country":"CA",
    "sg:address":"335 Webb Dr",
    "sg:city":"Mississauga",
    "sg:classifiers":[
        {
            "category":"Professional",
            "subcategory":"Accounting & Tax Preparation",
            "type":"Services"
        }
    ],
    "sg:phone":"+1 905 279 2844",
    "sg:postcode":"L5B 4A1",
    "sg:province":"ON",
    "sg:tags":[
        "return",
        "filing"
    ],
    "wof:name":"Tpo Accounting & Financial",
    "wof:placetype":"venue"
},
  "geometry": {"coordinates":[-79.641319,43.586159],"type":"Point"}
}