{
  "type": "Feature",
  "properties": {
    "iso:country":"CA",
    "sg:address":"1453 Boul Dr Albiny-Paquette",
    "sg:city":"Mont-Laurier",
    "sg:classifiers":[
        {
            "category":"Autos & Motor Vehicles",
            "subcategory":"Automobile Sales",
            "type":"Retail Goods"
        }
    ],
    "sg:phone":"+1 819 623 4844",
    "sg:postcode":"J9L 1M8",
    "sg:province":"QC",
    "sg:tags":[
        "car",
        "dealer"
    ],
    "wof:name":"Performe Hyundai",
    "wof:placetype":"venue"
},
  "geometry": {"coordinates":[-75.4689254761,46.5526771545],"type":"Point"}
}