{
  "type": "Feature",
  "properties": {
    "iso:country":"CA",
    "sg:address":"1832 Boul Marie-Victorin",
    "sg:city":"Longueuil",
    "sg:classifiers":[
        {
            "category":"Wholesale",
            "subcategory":"Medical Equipment & Supplies",
            "type":"Manufacturing & Wholesale Goods"
        }
    ],
    "sg:phone":"+1 450 677 1171",
    "sg:postcode":"J4G 1Y9",
    "sg:province":"QC",
    "sg:tags":[
        "optical"
    ],
    "wof:name":"Optelec",
    "wof:placetype":"venue"
},
  "geometry": {"coordinates":[-73.484955,45.570465],"type":"Point"}
}