{
  "type": "Feature",
  "properties": {
    "addr:full":"967 Rue Main Ayer's Cliff QC J0B 1C0",
    "addr:housenumber":"967",
    "addr:postcode":"j0b 1c0",
    "addr:street":"Rue Main",
    "iso:country":"CA",
    "sg:address":"967 Rue Main",
    "sg:city":"Ayer's Cliff",
    "sg:classifiers":[
        {
            "category":"Organizations",
            "subcategory":"Religious Organization",
            "type":"Services"
        }
    ],
    "sg:phone":"+1 819 838 4388",
    "sg:postcode":"J0B 1C0",
    "sg:province":"QC",
    "sg:tags":[
        "church"
    ],
    "wof:name":"United Church of Canada",
    "wof:placetype":"venue"
},
  "geometry": {"coordinates":[-72.04270935060001,45.1696243286],"type":"Point"}
}