{
  "type": "Feature",
  "properties": {
    "iso:country":"CA",
    "sg:address":"177 Christie St",
    "sg:city":"Toronto",
    "sg:classifiers":[
        {
            "category":"Organizations",
            "subcategory":"Religious Organization",
            "type":"Services"
        }
    ],
    "sg:phone":"+1 416 536 0337",
    "sg:postcode":"M6G 3B5",
    "sg:province":"ON",
    "sg:tags":[
        "church"
    ],
    "wof:name":"Christie Street Baptist Church",
    "wof:placetype":"venue"
},
  "geometry": {"coordinates":[-79.4201660156,43.6681518555],"type":"Point"}
}