{
  "type": "Feature",
  "properties": {
    "addr:full":"Brampton ON L6Y 1N3",
    "addr:postcode":"l6y 1n3",
    "iso:country":"CA",
    "sg:city":"Brampton",
    "sg:classifiers":[
        {
            "category":"Real Estate",
            "subcategory":"Real Estate Operator",
            "type":"Services"
        }
    ],
    "sg:phone":"+1 905 451 8461",
    "sg:postcode":"L6Y 1N3",
    "sg:province":"ON",
    "sg:tags":[
        "apartment"
    ],
    "wof:name":"Belvedere Apartments",
    "wof:placetype":"venue"
},
  "geometry": {"coordinates":[-79.75060999999999,43.678768],"type":"Point"}
}