{
  "type": "Feature",
  "properties": {
    "addr:full":"157 Catharine St N Hamilton ON L8L 4S4",
    "addr:housenumber":"157",
    "addr:postcode":"l8l 4s4",
    "addr:street":"Catharine St N",
    "iso:country":"CA",
    "sg:address":"157 Catharine St N",
    "sg:city":"Hamilton",
    "sg:classifiers":[
        {
            "category":"Real Estate",
            "subcategory":"Architect",
            "type":"Services"
        }
    ],
    "sg:phone":"+1 905 526 6700",
    "sg:postcode":"L8L 4S4",
    "sg:province":"ON",
    "wof:name":"Sather, Greg",
    "wof:placetype":"venue"
},
  "geometry": {"coordinates":[-79.86334228520001,43.2601089478],"type":"Point"}
}