{
  "type": "Feature",
  "properties": {
    "addr:full":"1881 Huron St London ON N5V 3A5",
    "addr:housenumber":"1881",
    "addr:postcode":"n5v 3a5",
    "addr:street":"Huron St",
    "iso:country":"CA",
    "sg:address":"1881 Huron St",
    "sg:city":"London",
    "sg:classifiers":[
        {
            "category":"Manufacturing",
            "subcategory":"Metals",
            "type":"Manufacturing & Wholesale Goods"
        }
    ],
    "sg:phone":"+1 519 659 0528",
    "sg:postcode":"N5V 3A5",
    "sg:province":"ON",
    "sg:tags":[
        "finisher"
    ],
    "wof:name":"Militex Coatings Inc",
    "wof:placetype":"venue"
},
  "geometry": {"coordinates":[-81.18918600000001,43.027317],"type":"Point"}
}