{
  "type": "Feature",
  "properties": {
    "addr:full":"7378 Rue Lajeunesse Montreal QC H2R 2H8",
    "addr:housenumber":"7378",
    "addr:postcode":"h2r 2h8",
    "addr:street":"Rue Lajeunesse",
    "iso:country":"CA",
    "sg:address":"7378 Rue Lajeunesse",
    "sg:city":"Montreal",
    "sg:classifiers":[
        {
            "category":"Museum",
            "type":"Entertainment"
        }
    ],
    "sg:phone":"+1 514 278 3941",
    "sg:postcode":"H2R 2H8",
    "sg:province":"QC",
    "sg:tags":[
        "organization",
        "arts",
        "information"
    ],
    "wof:name":"Creations Etc",
    "wof:placetype":"venue"
},
  "geometry": {"coordinates":[-73.61743199999999,45.540466],"type":"Point"}
}