{
  "type": "Feature",
  "properties": {
    "addr:full":"1775 Shelbourne Rd Jaffray BC V0B 1T0",
    "addr:housenumber":"1775",
    "addr:postcode":"bc v0b 1t0",
    "addr:street":"Shelbourne Rd",
    "iso:country":"CA",
    "sg:address":"1775 Shelbourne Rd",
    "sg:city":"Jaffray",
    "sg:classifiers":[
        {
            "category":"Organizations",
            "subcategory":"Religious Organization",
            "type":"Services"
        }
    ],
    "sg:phone":"+1 250 429 3058",
    "sg:postcode":"V0B 1T0",
    "sg:province":"BC",
    "sg:tags":[
        "church"
    ],
    "wof:name":"Jehovah's Witnesses",
    "wof:placetype":"venue"
},
  "geometry": {"coordinates":[-115.297241211,49.376739502],"type":"Point"}
}