{
  "type": "Feature",
  "properties": {
    "addr:full":"2655 Clearbrook Rd #260 Abbotsford BC V2T 2Y6",
    "addr:housenumber":"2655",
    "addr:postcode":"v2t 2y6",
    "addr:street":"Clearbrook Rd # 260",
    "iso:country":"CA",
    "sg:address":"2655 Clearbrook Rd #260",
    "sg:city":"Abbotsford",
    "sg:classifiers":[
        {
            "category":"Real Estate",
            "subcategory":"Real Estate Agent",
            "type":"Services"
        }
    ],
    "sg:phone":"+1 604 855 7393",
    "sg:postcode":"V2T 2Y6",
    "sg:province":"BC",
    "wof:name":"Lighthouse Realty Ltd",
    "wof:placetype":"venue"
},
  "geometry": {"coordinates":[-122.33777600000001,49.05196],"type":"Point"}
}