{
  "type": "Feature",
  "properties": {
    "iso:country":"CA",
    "sg:address":"50 Detta Rd",
    "sg:city":"Balmertown",
    "sg:classifiers":[
        {
            "category":"Real Estate",
            "subcategory":"Real Estate Operator",
            "type":"Services"
        }
    ],
    "sg:phone":"+1 807 735 2636",
    "sg:postcode":"P0V 1C0",
    "sg:province":"ON",
    "sg:tags":[
        "apartment"
    ],
    "wof:name":"Forest View Apartments",
    "wof:placetype":"venue"
},
  "geometry": {"coordinates":[-93.7417373657,51.0550918579],"type":"Point"}
}