{
  "type": "Feature",
  "properties": {
    "addr:full":"25 Oswego Park Dunnville ON N1A 2W2",
    "addr:housenumber":"25",
    "addr:postcode":"n1a 2w2",
    "addr:street":"Oswego Park",
    "iso:country":"CA",
    "sg:address":"25 Oswego Park",
    "sg:city":"Dunnville",
    "sg:classifiers":[
        {
            "category":"Professional",
            "subcategory":"Art Services",
            "type":"Services"
        }
    ],
    "sg:phone":"+1 905 701 4946",
    "sg:postcode":"N1A 2W2",
    "sg:province":"ON",
    "sg:tags":[
        "graphic",
        "designer",
        "sign"
    ],
    "wof:name":"Rainbow Marketing",
    "wof:placetype":"venue"
},
  "geometry": {"coordinates":[-79.565994,42.978363],"type":"Point"}
}