{
  "type": "Feature",
  "properties": {
    "addr:full":"1072 Geddes St Hawkesville ON N0B 1X0",
    "addr:housenumber":"1072",
    "addr:postcode":"n0b 1x0",
    "addr:street":"Geddes St",
    "iso:country":"CA",
    "sg:address":"1072 Geddes St",
    "sg:city":"Hawkesville",
    "sg:classifiers":[
        {
            "category":"Shopping",
            "subcategory":"Shoes",
            "type":"Retail Goods"
        }
    ],
    "sg:phone":"+1 519 699 5078",
    "sg:postcode":"N0B 1X0",
    "sg:province":"ON",
    "wof:name":"Rural Shoe & Repair",
    "wof:placetype":"venue"
},
  "geometry": {"coordinates":[-80.637184,43.562401],"type":"Point"}
}