{
  "type": "Feature",
  "properties": {
    "addr:full":"1700 Bonhill Rd Mississauga ON L5T 1C8",
    "addr:housenumber":"1700",
    "addr:postcode":"l5t 1c8",
    "addr:street":"Bonhill Rd",
    "iso:country":"CA",
    "sg:address":"1700 Bonhill Rd",
    "sg:city":"Mississauga",
    "sg:classifiers":[
        {
            "category":"Manufacturing",
            "subcategory":"Tools & Machinery",
            "type":"Manufacturing & Wholesale Goods"
        }
    ],
    "sg:phone":"+1 905 670 1713",
    "sg:postcode":"L5T 1C8",
    "sg:province":"ON",
    "sg:tags":[
        "conveying",
        "crane",
        "conveyor"
    ],
    "wof:name":"Plencon Limited",
    "wof:placetype":"venue"
},
  "geometry": {"coordinates":[-79.651473999,43.6666793823],"type":"Point"}
}