{
  "type": "Feature",
  "properties": {
    "iso:country":"CA",
    "sg:address":"43 Rue Queen",
    "sg:city":"Lennoxville",
    "sg:classifiers":[
        {
            "category":"Travel",
            "subcategory":"Hotels & Motels",
            "type":"Entertainment"
        }
    ],
    "sg:phone":"+1 819 564 9005",
    "sg:postcode":"J1M 1J2",
    "sg:province":"QC",
    "wof:name":"Motel Heritage Inc",
    "wof:placetype":"venue"
},
  "geometry": {"coordinates":[-71.85758972169999,45.3610305786],"type":"Point"}
}