{
  "type": "Feature",
  "properties": {
    "iso:country":"CA",
    "sg:address":"260 132 Rte",
    "sg:city":"Saint-Constant",
    "sg:classifiers":[
        {
            "category":"Arena",
            "subcategory":"Sports Club",
            "type":"Entertainment"
        }
    ],
    "sg:phone":"+1 450 632 8330",
    "sg:postcode":"J5A 2C9",
    "sg:province":"QC",
    "sg:tags":[
        "athletic",
        "fields",
        "stadium"
    ],
    "wof:name":"Centre Du Portage Arena",
    "wof:placetype":"venue"
},
  "geometry": {"coordinates":[-73.570999,45.371037],"type":"Point"}
}