{
  "type": "Feature",
  "properties": {
    "addr:full":"Foxboro ON K0K 2B0",
    "addr:postcode":"k0k 2b0",
    "addr:street":"Foxboro",
    "iso:country":"CA",
    "sg:city":"Foxboro",
    "sg:classifiers":[
        {
            "category":"Autos & Motor Vehicles",
            "subcategory":"Automobile Sales",
            "type":"Retail Goods"
        }
    ],
    "sg:phone":"+1 613 962 5877",
    "sg:postcode":"K0K 2B0",
    "sg:province":"ON",
    "sg:tags":[
        "car",
        "dealer"
    ],
    "wof:name":"Performance Sales & Leasing",
    "wof:placetype":"venue"
},
  "geometry": {"coordinates":[-77.419991,44.229572],"type":"Point"}
}