{
  "type": "Feature",
  "properties": {
    "addr:full":"Oshawa ON L1H 1B7",
    "addr:postcode":"l1h 1b7",
    "iso:country":"CA",
    "sg:city":"Oshawa",
    "sg:classifiers":[
        {
            "category":"Professional",
            "subcategory":"Accounting & Tax Preparation",
            "type":"Services"
        }
    ],
    "sg:phone":"+1 905 571 4010",
    "sg:postcode":"L1H 1B7",
    "sg:province":"ON",
    "sg:tags":[
        "accountant"
    ],
    "wof:name":"Mailer, Ann CA",
    "wof:placetype":"venue"
},
  "geometry": {"coordinates":[-78.85753631590001,43.8991546631],"type":"Point"}
}