{
  "type": "Feature",
  "properties": {
    "addr:full":"10551 St. Edwards Dr Richmond BC V6X 3L8",
    "addr:housenumber":"10551",
    "addr:postcode":"v6x 3l8",
    "addr:street":"St. Edwards Dr",
    "iso:country":"CA",
    "sg:address":"10551 St. Edwards Dr",
    "sg:city":"Richmond",
    "sg:classifiers":[
        {
            "category":"Travel",
            "subcategory":"Hotels & Motels",
            "type":"Entertainment"
        }
    ],
    "sg:phone":"+1 604 273 3311",
    "sg:postcode":"V6X 3L8",
    "sg:province":"BC",
    "wof:name":"Accent Inns",
    "wof:placetype":"venue"
},
  "geometry": {"coordinates":[-123.10878,49.185902],"type":"Point"}
}