{
  "type": "Feature",
  "properties": {
    "iso:country":"CA",
    "sg:address":"188 Mohawk St",
    "sg:city":"Brantford",
    "sg:classifiers":[
        {
            "category":"Shopping",
            "subcategory":"Books",
            "type":"Retail Goods"
        }
    ],
    "sg:phone":"+1 519 753 1185",
    "sg:postcode":"N3S 2X2",
    "sg:province":"ON",
    "sg:tags":[
        "educational",
        "material"
    ],
    "wof:name":"Goodminds.com",
    "wof:placetype":"venue"
},
  "geometry": {"coordinates":[-80.24137115480001,43.1258621216],"type":"Point"}
}