{
  "type": "Feature",
  "properties": {
    "addr:full":"3220 Lawrence Ave E Scarborough ON M1H 1A4",
    "addr:housenumber":"3220",
    "addr:postcode":"m1h 1a4",
    "addr:street":"Lawrence Ave E",
    "iso:country":"CA",
    "sg:address":"3220 Lawrence Ave E",
    "sg:city":"Scarborough",
    "sg:classifiers":[
        {
            "category":"Education",
            "subcategory":"School",
            "type":"Public Place"
        }
    ],
    "sg:phone":"+1 416 393 5269",
    "sg:postcode":"M1H 1A4",
    "sg:province":"ON",
    "sg:tags":[
        "child",
        "care"
    ],
    "wof:name":"Saint Rose of Lima",
    "wof:placetype":"venue"
},
  "geometry": {"coordinates":[-79.240746,43.756676],"type":"Point"}
}