{
  "type": "Feature",
  "properties": {
    "iso:country":"CA",
    "sg:address":"1100 Montee Masson # 11",
    "sg:city":"Mascouche",
    "sg:classifiers":[
        {
            "category":"Retail",
            "subcategory":"Animal Services",
            "type":"Services"
        }
    ],
    "sg:phone":"+1 450 966 9644",
    "sg:postcode":"J7K 2L8",
    "sg:province":"QC",
    "sg:tags":[
        "pet",
        "shop",
        "grooming",
        "washing"
    ],
    "wof:name":"Yogi Cote Jardin",
    "wof:placetype":"venue"
},
  "geometry": {"coordinates":[-73.606293,45.747864],"type":"Point"}
}