{
  "type": "Feature",
  "properties": {
    "addr:full":"5800 1A St SW Calgary AB T2H 0G1",
    "addr:housenumber":"5800",
    "addr:postcode":"t2h 0g1",
    "addr:street":"1A St Sw",
    "iso:country":"CA",
    "sg:address":"5800 1A St SW",
    "sg:city":"Calgary",
    "sg:classifiers":[
        {
            "category":"Professional",
            "subcategory":"Engineering",
            "type":"Services"
        }
    ],
    "sg:phone":"+1 403 640 0900",
    "sg:postcode":"T2H 0G1",
    "sg:province":"AB",
    "sg:tags":[
        "engineer"
    ],
    "wof:name":"Kellam Berg Engineering & Srvy",
    "wof:placetype":"venue"
},
  "geometry": {"coordinates":[-114.066963,51.002365],"type":"Point"}
}