{
  "type": "Feature",
  "properties": {
    "iso:country":"CA",
    "sg:city":"Chateauguay",
    "sg:classifiers":[
        {
            "category":"Freight",
            "type":"Transportation"
        }
    ],
    "sg:phone":"+1 450 692 8212",
    "sg:postcode":"J6K 3B2",
    "sg:province":"QC",
    "wof:name":"Johnson & Dever Inc",
    "wof:placetype":"venue"
},
  "geometry": {"coordinates":[-73.717079,45.356243],"type":"Point"}
}