{
  "type": "Feature",
  "properties": {
    "addr:full":"4073 Old Slope Pl Nanaimo BC V9T 5P8",
    "addr:housenumber":"4073",
    "addr:postcode":"v9t 5p8",
    "addr:street":"Old Slope Pl",
    "iso:country":"CA",
    "sg:address":"4073 Old Slope Pl",
    "sg:city":"Nanaimo",
    "sg:classifiers":[
        {
            "category":"Freight",
            "type":"Transportation"
        }
    ],
    "sg:phone":"+1 250 758 2758",
    "sg:postcode":"V9T 5P8",
    "sg:province":"BC",
    "sg:tags":[
        "commercial",
        "storage"
    ],
    "wof:name":"Mostar Mobile Mini Storage",
    "wof:placetype":"venue"
},
  "geometry": {"coordinates":[-124.033035278,49.2072410583],"type":"Point"}
}