{
  "type": "Feature",
  "properties": {
    "addr:full":"7204 Main St Vancouver BC V5X 3J4",
    "addr:housenumber":"7204",
    "addr:postcode":"v5x 3j4",
    "addr:street":"Main St",
    "iso:country":"CA",
    "sg:address":"7204 Main St",
    "sg:city":"Vancouver",
    "sg:classifiers":[
        {
            "category":"Health Services",
            "subcategory":"Doctor",
            "type":"Services"
        }
    ],
    "sg:phone":"+1 604 325 9221",
    "sg:postcode":"V5X 3J4",
    "sg:province":"BC",
    "sg:tags":[
        "physician",
        "surgeon"
    ],
    "wof:name":"William Lee Family Physician",
    "wof:placetype":"venue"
},
  "geometry": {"coordinates":[-123.101707459,49.2191772461],"type":"Point"}
}