{
  "type": "Feature",
  "properties": {
    "addr:full":"355 Montee Des Pionniers Lachenaie QC J6V 1N5",
    "addr:housenumber":"355",
    "addr:postcode":"j6v 1n5",
    "addr:street":"Montee Des Pionniers",
    "iso:country":"CA",
    "sg:address":"355 Montee Des Pionniers",
    "sg:city":"Lachenaie",
    "sg:classifiers":[
        {
            "category":"Health Services",
            "subcategory":"Doctor",
            "type":"Services"
        }
    ],
    "sg:phone":"+1 450 582 2219",
    "sg:postcode":"J6V 1N5",
    "sg:province":"QC",
    "sg:tags":[
        "clinic",
        "dentist"
    ],
    "wof:name":"Centre Dentaire C Vaillancourt",
    "wof:placetype":"venue"
},
  "geometry": {"coordinates":[-73.51239,45.713409],"type":"Point"}
}