{
  "type": "Feature",
  "properties": {
    "addr:full":"346 Grand Ave E Chatham ON N7L 1W6",
    "addr:housenumber":"346",
    "addr:postcode":"n7l 1w6",
    "addr:street":"Grand Ave E",
    "iso:country":"CA",
    "sg:address":"346 Grand Ave E",
    "sg:city":"Chatham",
    "sg:classifiers":[
        {
            "category":"Organizations",
            "subcategory":"Professional Association",
            "type":"Services"
        }
    ],
    "sg:phone":"+1 519 436 0040",
    "sg:postcode":"N7L 1W6",
    "sg:province":"ON",
    "wof:name":"Portuguese Canadian Social",
    "wof:placetype":"venue"
},
  "geometry": {"coordinates":[-82.17890199999999,42.415882],"type":"Point"}
}