{
  "type": "Feature",
  "properties": {
    "iso:country":"CA",
    "sg:city":"Gloucester",
    "sg:classifiers":[
        {
            "category":"Banks & Credit Unions",
            "subcategory":"Investment Brokerage",
            "type":"Services"
        }
    ],
    "sg:phone":"+1 613 742 4422",
    "sg:postcode":"K1J 9C1",
    "sg:province":"ON",
    "sg:tags":[
        "consultant",
        "planning",
        "financial"
    ],
    "wof:name":"J L Appotive Financial Plannin",
    "wof:placetype":"venue"
},
  "geometry": {"coordinates":[-75.5854187012,45.4533348083],"type":"Point"}
}