{
  "type": "Feature",
  "properties": {
    "addr:full":"Calgary AB T2R 0H5",
    "addr:postcode":"t2r 0h5",
    "iso:country":"CA",
    "sg:city":"Calgary",
    "sg:classifiers":[
        {
            "category":"Professional",
            "subcategory":"Engineering",
            "type":"Services"
        }
    ],
    "sg:phone":"+1 403 205 3833",
    "sg:postcode":"T2R 0H5",
    "sg:province":"AB",
    "sg:tags":[
        "engineer"
    ],
    "wof:name":"Equinox Engineering Ltd",
    "wof:placetype":"venue"
},
  "geometry": {"coordinates":[-114.075172424,51.0418739319],"type":"Point"}
}