{
  "type": "Feature",
  "properties": {
    "iso:country":"CA",
    "sg:address":"184 Rang Saint-Raphael S",
    "sg:city":"Albertville",
    "sg:classifiers":[
        {
            "category":"Building & Trades",
            "subcategory":"Construction",
            "type":"Services"
        }
    ],
    "sg:phone":"+1 418 756 3318",
    "sg:postcode":"G0J 1A0",
    "sg:province":"QC",
    "sg:tags":[
        "maker",
        "cabinet"
    ],
    "wof:name":"Ebenisterie Ml Potvin Enr",
    "wof:placetype":"venue"
},
  "geometry": {"coordinates":[-67.3521347046,48.3106536865],"type":"Point"}
}