{
  "type": "Feature",
  "properties": {
    "addr:full":"PO Box 447 Lac LA Biche AB T0A 2C0",
    "addr:housenumber":"po",
    "addr:postcode":"t0a 2c0",
    "addr:street":"Box 447 Lac La Biche",
    "iso:country":"CA",
    "sg:address":"PO Box 447",
    "sg:city":"Lac LA Biche",
    "sg:classifiers":[
        {
            "category":"Organizations",
            "subcategory":"Professional Association",
            "type":"Services"
        }
    ],
    "sg:phone":"+1 780 623 2130",
    "sg:postcode":"T0A 2C0",
    "sg:province":"AB",
    "wof:name":"Heart Lake Band Office",
    "wof:placetype":"venue"
},
  "geometry": {"coordinates":[-111.97445678699999,54.77110672],"type":"Point"}
}