{
  "type": "Feature",
  "properties": {
    "iso:country":"CA",
    "sg:address":"1307 Rue Roberval",
    "sg:city":"Saint-Bruno",
    "sg:classifiers":[
        {
            "category":"Banks & Credit Unions",
            "subcategory":"Investment Brokerage",
            "type":"Services"
        }
    ],
    "sg:phone":"+1 450 441 3300",
    "sg:postcode":"J3V 5J1",
    "sg:province":"QC",
    "sg:tags":[
        "stock",
        "broker",
        "bond"
    ],
    "wof:name":"National Bank Financial Inc",
    "wof:placetype":"venue"
},
  "geometry": {"coordinates":[-71.67552185060001,48.4717712402],"type":"Point"}
}