{
  "type": "Feature",
  "properties": {
    "addr:full":"8 Place Desjardins L'Epiphanie QC J5X 2P1",
    "addr:housenumber":"8",
    "addr:postcode":"j5x 2p1",
    "addr:street":"Place Desjardins L'Epiphanie",
    "iso:country":"CA",
    "sg:address":"8 Place Desjardins",
    "sg:city":"L'Epiphanie",
    "sg:classifiers":[
        {
            "category":"Building & Trades",
            "subcategory":"Plumbing",
            "type":"Services"
        }
    ],
    "sg:phone":"+1 450 588 3021",
    "sg:postcode":"J5X 2P1",
    "sg:province":"QC",
    "sg:tags":[
        "roofing",
        "contractor"
    ],
    "wof:name":"Toitures D Melancon Inc",
    "wof:placetype":"venue"
},
  "geometry": {"coordinates":[-73.482506,45.85088],"type":"Point"}
}