{
  "type": "Feature",
  "properties": {
    "addr:full":"126 Park Pl E Winnipeg MB R3P 2E3",
    "addr:housenumber":"126",
    "addr:postcode":"r3p 2e3",
    "addr:street":"Park Pl E",
    "iso:country":"CA",
    "sg:address":"126 Park Pl E",
    "sg:city":"Winnipeg",
    "sg:classifiers":[
        {
            "category":"Home & Garden",
            "subcategory":"Building Materials",
            "type":"Retail Goods"
        }
    ],
    "sg:phone":"+1 204 654 1644",
    "sg:postcode":"R3P 2E3",
    "sg:province":"MB",
    "sg:tags":[
        "type",
        "door"
    ],
    "wof:name":"Accurate Installation & Svc",
    "wof:placetype":"venue"
},
  "geometry": {"coordinates":[-97.21347,49.847836],"type":"Point"}
}