{
  "type": "Feature",
  "properties": {
    "addr:full":"Kitchener ON N2A 3X9",
    "addr:postcode":"n2a 3x9",
    "iso:country":"CA",
    "sg:city":"Kitchener",
    "sg:classifiers":[
        {
            "category":"Health Services",
            "subcategory":"Doctor",
            "type":"Services"
        }
    ],
    "sg:phone":"+1 519 894 7080",
    "sg:postcode":"N2A 3X9",
    "sg:province":"ON",
    "sg:tags":[
        "dentist"
    ],
    "wof:name":"Witmer, Cameron A DDS",
    "wof:placetype":"venue"
},
  "geometry": {"coordinates":[-80.4281158447,43.4341773987],"type":"Point"}
}