{
  "type": "Feature",
  "properties": {
    "addr:full":"668 5E Av Beauceville QC G5X 1L6",
    "addr:housenumber":"668",
    "addr:postcode":"g5x 1l6",
    "addr:street":"5E Av",
    "iso:country":"CA",
    "sg:address":"668 5E Av",
    "sg:city":"Beauceville",
    "sg:classifiers":[
        {
            "category":"Building & Trades",
            "subcategory":"Construction",
            "type":"Services"
        }
    ],
    "sg:phone":"+1 418 774 2424",
    "sg:postcode":"G5X 1L6",
    "sg:province":"QC",
    "sg:tags":[
        "windows",
        "glazier"
    ],
    "wof:name":"Vitralum Inc",
    "wof:placetype":"venue"
},
  "geometry": {"coordinates":[-70.76984400000001,46.203262],"type":"Point"}
}