{
  "type": "Feature",
  "properties": {
    "addr:full":"1517 Rte Kennedy N Sainte-Marie QC G6E 3P1",
    "addr:housenumber":"1517",
    "addr:postcode":"g6e 3p1",
    "addr:street":"Rte Kennedy N",
    "iso:country":"CA",
    "sg:address":"1517 Rte Kennedy N",
    "sg:city":"Sainte-Marie",
    "sg:classifiers":[
        {
            "category":"Retail",
            "subcategory":"Auto Repair",
            "type":"Services"
        }
    ],
    "sg:phone":"+1 418 387 2198",
    "sg:postcode":"G6E 3P1",
    "sg:province":"QC",
    "sg:tags":[
        "repairing",
        "automobile"
    ],
    "wof:name":"Garage Clement Berthiaume Auto",
    "wof:placetype":"venue"
},
  "geometry": {"coordinates":[-65.9838256836,48.1726264954],"type":"Point"}
}