{
  "type": "Feature",
  "properties": {
    "addr:full":"1055 Rue Masson Terrebonne QC J6W 4K9",
    "addr:housenumber":"1055",
    "addr:postcode":"j6w 4k9",
    "addr:street":"Rue Masson",
    "iso:country":"CA",
    "sg:address":"1055 Rue Masson",
    "sg:city":"Terrebonne",
    "sg:classifiers":[
        {
            "category":"Home & Garden",
            "subcategory":"Building Materials",
            "type":"Retail Goods"
        }
    ],
    "sg:phone":"+1 450 492 7220",
    "sg:postcode":"J6W 4K9",
    "sg:province":"QC",
    "sg:tags":[
        "glass",
        "window",
        "plate"
    ],
    "wof:name":"Docteur Du Pare-Brise",
    "wof:placetype":"venue"
},
  "geometry": {"coordinates":[-73.6304473877,45.7052879333],"type":"Point"}
}