{
  "type": "Feature",
  "properties": {
    "iso:country":"CA",
    "sg:address":"3500 Rue Ontario E",
    "sg:city":"Montreal",
    "sg:classifiers":[
        {
            "category":"Home & Garden",
            "subcategory":"Furniture",
            "type":"Retail Goods"
        }
    ],
    "sg:phone":"+1 514 527 4331",
    "sg:postcode":"H1W 1R2",
    "sg:province":"QC",
    "wof:name":"Meubles Domon Ltee",
    "wof:placetype":"venue"
},
  "geometry": {"coordinates":[-73.54525,45.544086],"type":"Point"}
}