{
  "type": "Feature",
  "properties": {
    "iso:country":"CA",
    "sg:address":"102 Rue Angus N",
    "sg:city":"East Angus",
    "sg:classifiers":[
        {
            "category":"Shopping",
            "subcategory":"Bicycles & Sporting Goods",
            "type":"Retail Goods"
        }
    ],
    "sg:phone":"+1 819 832 2390",
    "sg:postcode":"J0B 1R0",
    "sg:province":"QC",
    "sg:tags":[
        "hardware"
    ],
    "wof:name":"Ferronnerie Martineau Enrg",
    "wof:placetype":"venue"
},
  "geometry": {"coordinates":[-71.66004180909999,45.4865188599],"type":"Point"}
}