{
  "type": "Feature",
  "properties": {
    "addr:full":"2801 Rue Hochelaga Montreal QC H2K 1K4",
    "addr:housenumber":"2801",
    "addr:postcode":"h2k 1k4",
    "addr:street":"Rue Hochelaga",
    "iso:country":"CA",
    "sg:address":"2801 Rue Hochelaga",
    "sg:city":"Montreal",
    "sg:classifiers":[
        {
            "category":"Food & Beverages",
            "subcategory":"Groceries & Convenience Stores",
            "type":"Retail Goods"
        }
    ],
    "sg:phone":"+1 514 522 5535",
    "sg:postcode":"H2K 1K4",
    "sg:province":"QC",
    "sg:tags":[
        "grocer"
    ],
    "wof:name":"Depanneur Jean Enr",
    "wof:placetype":"venue"
},
  "geometry": {"coordinates":[-73.5568161011,45.5381851196],"type":"Point"}
}