{
  "type": "Feature",
  "properties": {
    "addr:full":"684 Huron St London ON N5Y 4J8",
    "addr:housenumber":"684",
    "addr:postcode":"n5y 4j8",
    "addr:street":"Huron St",
    "iso:country":"CA",
    "sg:address":"684 Huron St",
    "sg:city":"London",
    "sg:classifiers":[
        {
            "category":"Health Services",
            "subcategory":"Doctor",
            "type":"Services"
        }
    ],
    "sg:phone":"+1 519 433 9509",
    "sg:postcode":"N5Y 4J8",
    "sg:province":"ON",
    "sg:tags":[
        "dentist"
    ],
    "wof:name":"Dhami, Baljinder DDS",
    "wof:placetype":"venue"
},
  "geometry": {"coordinates":[-81.239349,43.013054],"type":"Point"}
}