{
  "type": "Feature",
  "properties": {
    "addr:full":"375 Pine St Sault Ste Marie ON P6B 3E6",
    "addr:housenumber":"375",
    "addr:postcode":"p6b 3e6",
    "addr:street":"Pine St",
    "iso:country":"CA",
    "sg:address":"375 Pine St",
    "sg:city":"Sault Ste Marie",
    "sg:classifiers":[
        {
            "category":"Government",
            "subcategory":"Office",
            "type":"Public Place"
        }
    ],
    "sg:phone":"+1 705 541 5200",
    "sg:postcode":"P6B 3E6",
    "sg:province":"ON",
    "wof:name":"Canada Northern Ontario Distr",
    "wof:placetype":"venue"
},
  "geometry": {"coordinates":[-84.307579,46.51104],"type":"Point"}
}