{
  "type": "Feature",
  "properties": {
    "addr:full":"141 Av Laberge Vaudreuil-Dorion QC J7V 2Y9",
    "addr:postcode":"j7v 2y9",
    "addr:street":"141 Av Laberge",
    "iso:country":"CA",
    "sg:address":"141 Av Laberge",
    "sg:city":"Vaudreuil-Dorion",
    "sg:classifiers":[
        {
            "category":"Food & Beverages",
            "subcategory":"Specialty",
            "type":"Retail Goods"
        }
    ],
    "sg:phone":"+1 450 455 4655",
    "sg:postcode":"J7V 2Y9",
    "sg:province":"QC",
    "wof:name":"Shaklee Independent Distr",
    "wof:placetype":"venue"
},
  "geometry": {"coordinates":[-74.016289,45.376297],"type":"Point"}
}