{
  "type": "Feature",
  "properties": {
    "addr:full":"PO Box 262 Waskada MB R0M 2E0",
    "addr:housenumber":"po",
    "addr:postcode":"r0m 2e0",
    "addr:street":"Box 262 Waskada",
    "iso:country":"CA",
    "sg:address":"PO Box 262",
    "sg:city":"Waskada",
    "sg:classifiers":[
        {
            "category":"Organizations",
            "subcategory":"Religious Organization",
            "type":"Services"
        }
    ],
    "sg:phone":"+1 204 747 2612",
    "sg:postcode":"R0M 2E0",
    "sg:province":"MB",
    "sg:tags":[
        "church"
    ],
    "wof:name":"Fellowship Community Church",
    "wof:placetype":"venue"
},
  "geometry": {"coordinates":[-100.802276611,49.0984115601],"type":"Point"}
}