{
  "type": "Feature",
  "properties": {
    "iso:country":"CA",
    "sg:address":"417 Huronia Rd",
    "sg:city":"Barrie",
    "sg:classifiers":[
        {
            "category":"Building & Trades",
            "subcategory":"Cleaning & Sanitation",
            "type":"Services"
        }
    ],
    "sg:phone":"+1 705 722 0062",
    "sg:postcode":"L4N 9B3",
    "sg:province":"ON",
    "sg:tags":[
        "window",
        "janitor"
    ],
    "wof:name":"Way More Window Cleaning",
    "wof:placetype":"venue"
},
  "geometry": {"coordinates":[-79.664497,44.351585],"type":"Point"}
}