{
  "type": "Feature",
  "properties": {
    "addr:full":"RR 4 Picton ON K0K 2T0",
    "addr:postcode":"k0k 2t0",
    "addr:street":"Rr 4",
    "iso:country":"CA",
    "sg:address":"RR 4",
    "sg:city":"Picton",
    "sg:classifiers":[
        {
            "category":"Manufacturing",
            "subcategory":"Metals",
            "type":"Manufacturing & Wholesale Goods"
        }
    ],
    "sg:phone":"+1 613 476 7302",
    "sg:postcode":"K0K 2T0",
    "sg:province":"ON",
    "sg:tags":[
        "building",
        "contractor"
    ],
    "wof:name":"Norton's Home Improvements",
    "wof:placetype":"venue"
},
  "geometry": {"coordinates":[-77.138977,44.009224],"type":"Point"}
}