{
  "type": "Feature",
  "properties": {
    "iso:country":"CA",
    "sg:address":"590 Beach Ave",
    "sg:city":"Meota",
    "sg:classifiers":[
        {
            "category":"Travel",
            "subcategory":"Campground",
            "type":"Entertainment"
        }
    ],
    "sg:phone":"+1 306 892 2292",
    "sg:postcode":"S0M 1X0",
    "sg:province":"SK",
    "wof:name":"Meota Regional Park",
    "wof:placetype":"venue"
},
  "geometry": {"coordinates":[-108.458656311,53.0339431763],"type":"Point"}
}