{
  "type": "Feature",
  "properties": {
    "addr:full":"Saint-Bruno QC J3V 6B7",
    "addr:postcode":"j3v 6b7",
    "iso:country":"CA",
    "sg:city":"Saint-Bruno",
    "sg:classifiers":[
        {
            "category":"Shopping",
            "type":"Retail Goods"
        }
    ],
    "sg:phone":"+1 450 441 9777",
    "sg:postcode":"J3V 6B7",
    "sg:province":"QC",
    "sg:tags":[
        "album",
        "photo",
        "frame"
    ],
    "wof:name":"Creations Dia",
    "wof:placetype":"venue"
},
  "geometry": {"coordinates":[-71.67552185060001,48.4717712402],"type":"Point"}
}