{
  "type": "Feature",
  "properties": {
    "addr:full":"Vancouver BC V6B 6B4",
    "addr:postcode":"v6b 6b4",
    "iso:country":"CA",
    "sg:city":"Vancouver",
    "sg:classifiers":[
        {
            "category":"Personal",
            "subcategory":"Beauty Salon",
            "type":"Services"
        }
    ],
    "sg:phone":"+1 604 688 7862",
    "sg:postcode":"V6B 6B4",
    "sg:province":"BC",
    "wof:name":"Hair Studio 2008",
    "wof:placetype":"venue"
},
  "geometry": {"coordinates":[-123.11432600000001,49.28001],"type":"Point"}
}