{
  "type": "Feature",
  "properties": {
    "addr:full":"3312 Sandwich St Windsor ON N9C 1B1",
    "addr:housenumber":"3312",
    "addr:postcode":"n9c 1b1",
    "addr:street":"Sandwich St",
    "iso:country":"CA",
    "sg:address":"3312 Sandwich St",
    "sg:city":"Windsor",
    "sg:classifiers":[
        {
            "category":"Education",
            "subcategory":"Library",
            "type":"Public Place"
        }
    ],
    "sg:phone":"+1 519 253 8492",
    "sg:postcode":"N9C 1B1",
    "sg:province":"ON",
    "wof:name":"Sandwich Library",
    "wof:placetype":"venue"
},
  "geometry": {"coordinates":[-83.07746899999999,42.299347],"type":"Point"}
}