{
  "type": "Feature",
  "properties": {
    "iso:country":"CA",
    "sg:city":"Richmond Hill",
    "sg:classifiers":[
        {
            "category":"Restaurant",
            "type":"Food & Drink"
        }
    ],
    "sg:phone":"+1 905 881 8406",
    "sg:postcode":"L4B 1J8",
    "sg:province":"ON",
    "sg:tags":[
        "cafe"
    ],
    "wof:name":"Caffe Demetre",
    "wof:placetype":"venue"
},
  "geometry": {"coordinates":[-79.3781051636,43.8477516174],"type":"Point"}
}