{
  "type": "Feature",
  "properties": {
    "addr:full":"2017 Amherst Heights Dr Burlington ON L7P 3R3",
    "addr:housenumber":"2017",
    "addr:postcode":"l7p 3r3",
    "addr:street":"Amherst Heights Dr",
    "iso:country":"CA",
    "sg:address":"2017 Amherst Heights Dr",
    "sg:city":"Burlington",
    "sg:classifiers":[
        {
            "category":"Building & Trades",
            "subcategory":"Construction",
            "type":"Services"
        }
    ],
    "sg:phone":"+1 905 335 9042",
    "sg:postcode":"L7P 3R3",
    "sg:province":"ON",
    "sg:tags":[
        "painter"
    ],
    "wof:name":"Bremen Painting & Decorating",
    "wof:placetype":"venue"
},
  "geometry": {"coordinates":[-79.834908,43.352249],"type":"Point"}
}