{
  "type": "Feature",
  "properties": {
    "addr:full":"562 Chrislea Rd Woodbridge ON L4L 8K9",
    "addr:housenumber":"562",
    "addr:postcode":"l4l 8k9",
    "addr:street":"Chrislea Rd",
    "iso:country":"CA",
    "sg:address":"562 Chrislea Rd",
    "sg:city":"Woodbridge",
    "sg:classifiers":[
        {
            "category":"Building & Trades",
            "subcategory":"Construction",
            "type":"Services"
        }
    ],
    "sg:phone":"+1 905 856 7217",
    "sg:postcode":"L4L 8K9",
    "sg:province":"ON",
    "sg:tags":[
        "contractor"
    ],
    "wof:name":"Tormina Construction Ltd",
    "wof:placetype":"venue"
},
  "geometry": {"coordinates":[-79.5458679199,43.8050193787],"type":"Point"}
}