{
  "type": "Feature",
  "properties": {
    "addr:full":"37 Rose Park Dr Toronto ON M4T 1R2",
    "addr:housenumber":"37",
    "addr:postcode":"m4t 1r2",
    "addr:street":"Rose Park Dr",
    "iso:country":"CA",
    "sg:address":"37 Rose Park Dr",
    "sg:city":"Toronto",
    "sg:classifiers":[
        {
            "category":"Real Estate",
            "subcategory":"Real Estate Agent",
            "type":"Services"
        }
    ],
    "sg:phone":"+1 416 483 3080",
    "sg:postcode":"M4T 1R2",
    "sg:province":"ON",
    "sg:tags":[
        "management"
    ],
    "wof:name":"Building Management Consultant",
    "wof:placetype":"venue"
},
  "geometry": {"coordinates":[-79.386185,43.690643],"type":"Point"}
}