{
  "type": "Feature",
  "properties": {
    "addr:full":"1900 Sheppard Ave E # 2005 North York ON M2J 4T4",
    "addr:housenumber":"1900",
    "addr:postcode":"m2j 4t4",
    "addr:street":"Sheppard Ave E # 2005",
    "iso:country":"CA",
    "sg:address":"1900 Sheppard Ave E # 2005",
    "sg:city":"North York",
    "sg:classifiers":[
        {
            "category":"Professional",
            "subcategory":"Engineering",
            "type":"Services"
        }
    ],
    "sg:phone":"+1 416 862 7742",
    "sg:postcode":"M2J 4T4",
    "sg:province":"ON",
    "sg:tags":[
        "engineer"
    ],
    "wof:name":"B Helm Assoc Ltd",
    "wof:placetype":"venue"
},
  "geometry": {"coordinates":[-79.337372,43.775951],"type":"Point"}
}