{
  "type": "Feature",
  "properties": {
    "addr:full":"874 Queen St W Toronto ON M6J 1G3",
    "addr:housenumber":"874",
    "addr:postcode":"m6j 1g3",
    "addr:street":"Queen St W",
    "iso:country":"CA",
    "sg:address":"874 Queen St W",
    "sg:city":"Toronto",
    "sg:classifiers":[
        {
            "category":"Shopping",
            "subcategory":"Hobbies, Toys, & Games",
            "type":"Retail Goods"
        }
    ],
    "sg:phone":"+1 416 537 7338",
    "sg:postcode":"M6J 1G3",
    "sg:province":"ON",
    "sg:tags":[
        "material",
        "craft",
        "artist",
        "supply"
    ],
    "wof:name":"Tern Art Supplies",
    "wof:placetype":"venue"
},
  "geometry": {"coordinates":[-79.41437500000001,43.645241],"type":"Point"}
}