{
  "type": "Feature",
  "properties": {
    "addr:full":"6030 Av Papineau Montreal QC H2G 2W8",
    "addr:housenumber":"6030",
    "addr:postcode":"h2g 2w8",
    "addr:street":"Av Papineau",
    "iso:country":"CA",
    "sg:address":"6030 Av Papineau",
    "sg:city":"Montreal",
    "sg:classifiers":[
        {
            "category":"Autos & Motor Vehicles",
            "subcategory":"Auto Supplies",
            "type":"Retail Goods"
        }
    ],
    "sg:phone":"+1 514 271 7112",
    "sg:postcode":"H2G 2W8",
    "sg:province":"QC",
    "sg:tags":[
        "automobile",
        "parts"
    ],
    "wof:name":"Pieces D'Auto Recyclees Rosemt",
    "wof:placetype":"venue"
},
  "geometry": {"coordinates":[-73.59226200000001,45.540977],"type":"Point"}
}