{
  "type": "Feature",
  "properties": {
    "addr:full":"General Delivery Brookfield NS B0N 1C0",
    "addr:postcode":"b0n 1c0",
    "iso:country":"CA",
    "sg:address":"General Delivery",
    "sg:city":"Brookfield",
    "sg:classifiers":[
        {
            "category":"Education",
            "subcategory":"School",
            "type":"Public Place"
        }
    ],
    "sg:phone":"+1 902 673 5000",
    "sg:postcode":"B0N 1C0",
    "sg:province":"NS",
    "wof:name":"South Colchester High School",
    "wof:placetype":"venue"
},
  "geometry": {"coordinates":[-63.2772636414,45.2542304993],"type":"Point"}
}