{
  "type": "Feature",
  "properties": {
    "iso:country":"CA",
    "sg:city":"Montreal",
    "sg:classifiers":[
        {
            "category":"Wholesale",
            "subcategory":"Apparel",
            "type":"Manufacturing & Wholesale Goods"
        }
    ],
    "sg:phone":"+1 514 288 6644",
    "sg:postcode":"H3A 2K4",
    "sg:province":"QC",
    "sg:tags":[
        "fur",
        "business"
    ],
    "wof:name":"Fourrures Global Inc",
    "wof:placetype":"venue"
},
  "geometry": {"coordinates":[-73.5689697266,45.5060577393],"type":"Point"}
}