{
  "type": "Feature",
  "properties": {
    "addr:full":"Charlottetown PE C1A 1K9",
    "addr:postcode":"c1a 1k9",
    "iso:country":"CA",
    "sg:city":"Charlottetown",
    "sg:classifiers":[
        {
            "category":"Banks & Credit Unions",
            "subcategory":"Bank",
            "type":"Services"
        }
    ],
    "sg:phone":"+1 902 892 2437",
    "sg:postcode":"C1A 1K9",
    "sg:province":"PE",
    "wof:name":"Bank of Montreal",
    "wof:placetype":"venue"
},
  "geometry": {"coordinates":[-63.1278915405,46.2347564697],"type":"Point"}
}