{
  "type": "Feature",
  "properties": {
    "iso:country":"CA",
    "sg:address":"3595 St Clair Ave E",
    "sg:city":"Scarborough",
    "sg:classifiers":[
        {
            "category":"Building & Trades",
            "subcategory":"Electrical",
            "type":"Services"
        }
    ],
    "sg:phone":"+1 416 261 6499",
    "sg:postcode":"M1K 1L8",
    "sg:province":"ON",
    "sg:tags":[
        "electric",
        "contractor"
    ],
    "wof:name":"George A Wright & Sons",
    "wof:placetype":"venue"
},
  "geometry": {"coordinates":[-79.256248,43.717514],"type":"Point"}
}