{
  "type": "Feature",
  "properties": {
    "addr:full":"54 Central St Summerside PE C1N 3L1",
    "addr:housenumber":"54",
    "addr:postcode":"c1n 3l1",
    "addr:street":"Central St",
    "iso:country":"CA",
    "sg:address":"54 Central St",
    "sg:city":"Summerside",
    "sg:classifiers":[
        {
            "category":"Shopping",
            "subcategory":"Pharmacy",
            "type":"Retail Goods"
        }
    ],
    "sg:phone":"+1 902 436 4436",
    "sg:postcode":"C1N 3L1",
    "sg:province":"PE",
    "wof:name":"Medicine Shoppe",
    "wof:placetype":"venue"
},
  "geometry": {"coordinates":[-63.792316,46.39352],"type":"Point"}
}