{
  "type": "Feature",
  "properties": {
    "addr:full":"1558 Ouellette Ave Windsor ON N8X 1K7",
    "addr:housenumber":"1558",
    "addr:postcode":"n8x 1k7",
    "addr:street":"Ouellette Ave",
    "iso:country":"CA",
    "sg:address":"1558 Ouellette Ave",
    "sg:city":"Windsor",
    "sg:classifiers":[
        {
            "category":"Health Services",
            "subcategory":"Doctor",
            "type":"Services"
        }
    ],
    "sg:phone":"+1 519 253 8507",
    "sg:postcode":"N8X 1K7",
    "sg:province":"ON",
    "sg:tags":[
        "physician",
        "surgeon"
    ],
    "wof:name":"Kooner, Sukhdev S MD",
    "wof:placetype":"venue"
},
  "geometry": {"coordinates":[-83.0269775391,42.2990608215],"type":"Point"}
}