{
  "type": "Feature",
  "properties": {
    "addr:full":"25 Thomas St Mississauga ON L5M 1Y4",
    "addr:housenumber":"25",
    "addr:postcode":"l5m 1y4",
    "addr:street":"Thomas St",
    "iso:country":"CA",
    "sg:address":"25 Thomas St",
    "sg:city":"Mississauga",
    "sg:classifiers":[
        {
            "category":"Health Services",
            "subcategory":"Nursing And Care Facility",
            "type":"Services"
        }
    ],
    "sg:phone":"+1 905 826 4510",
    "sg:postcode":"L5M 1Y4",
    "sg:province":"ON",
    "sg:tags":[
        "home",
        "retirement",
        "community"
    ],
    "wof:name":"Streetsville Retirement Home",
    "wof:placetype":"venue"
},
  "geometry": {"coordinates":[-79.712395,43.579487],"type":"Point"}
}