{
  "type": "Feature",
  "properties": {
    "addr:full":"Peterborough ON K9J 6X9",
    "addr:postcode":"k9j 6x9",
    "iso:country":"CA",
    "sg:city":"Peterborough",
    "sg:classifiers":[
        {
            "category":"Building & Trades",
            "subcategory":"Construction",
            "type":"Services"
        }
    ],
    "sg:phone":"+1 705 741 3881",
    "sg:postcode":"K9J 6X9",
    "sg:province":"ON",
    "sg:tags":[
        "designer",
        "dealer",
        "pool",
        "swimming"
    ],
    "wof:name":"Randy's Pools",
    "wof:placetype":"venue"
},
  "geometry": {"coordinates":[-78.276459,44.294441],"type":"Point"}
}