{
  "type": "Feature",
  "properties": {
    "addr:full":"PO Box 1425 STN Main Athabasca AB T9S 2B3",
    "addr:housenumber":"po",
    "addr:postcode":"1425;t9s 2b3",
    "addr:street":"Box;Stn Main",
    "iso:country":"CA",
    "sg:address":"PO Box 1425 STN Main",
    "sg:city":"Athabasca",
    "sg:classifiers":[
        {
            "category":"Building & Trades",
            "subcategory":"Plumbing",
            "type":"Services"
        }
    ],
    "sg:phone":"+1 780 675 5374",
    "sg:postcode":"T9S 2B3",
    "sg:province":"AB",
    "sg:tags":[
        "septic"
    ],
    "wof:name":"Lake District Vacuum Truck Svc",
    "wof:placetype":"venue"
},
  "geometry": {"coordinates":[-113.28351600000001,54.721233],"type":"Point"}
}