{
  "type": "Feature",
  "properties": {
    "addr:full":"215 Rue Thomas Saint-Amable QC J0L 1N0",
    "addr:housenumber":"215",
    "addr:postcode":"j0l 1n0",
    "addr:street":"Rue Thomas",
    "iso:country":"CA",
    "sg:address":"215 Rue Thomas",
    "sg:city":"Saint-Amable",
    "sg:classifiers":[
        {
            "category":"Government",
            "subcategory":"Office",
            "type":"Public Place"
        }
    ],
    "sg:phone":"+1 450 922 8143",
    "sg:postcode":"J0L 1N0",
    "sg:province":"QC",
    "sg:tags":[
        "village"
    ],
    "wof:name":"Saint-Amable Chalet DE Rocher",
    "wof:placetype":"venue"
},
  "geometry": {"coordinates":[-73.32588199999999,45.64587],"type":"Point"}
}