{
  "type": "Feature",
  "properties": {
    "addr:full":"18 Hamlyn Rd St. John's NL A1E 5X7",
    "addr:housenumber":"18",
    "addr:postcode":"a1e 5x7",
    "addr:street":"Hamlyn Rd",
    "iso:country":"CA",
    "sg:address":"18 Hamlyn Rd",
    "sg:city":"St. John's",
    "sg:classifiers":[
        {
            "category":"Food & Beverages",
            "subcategory":"Groceries & Convenience Stores",
            "type":"Retail Goods"
        }
    ],
    "sg:phone":"+1 709 364 7711",
    "sg:postcode":"A1E 5X7",
    "sg:province":"NL",
    "wof:name":"Marie's Mini Mart",
    "wof:placetype":"venue"
},
  "geometry": {"coordinates":[-52.752575,47.533951],"type":"Point"}
}