{
  "type": "Feature",
  "properties": {
    "iso:country":"CA",
    "sg:address":"1204 77 Ave NW",
    "sg:city":"Edmonton",
    "sg:classifiers":[
        {
            "category":"Retail",
            "subcategory":"Auto Repair",
            "type":"Services"
        }
    ],
    "sg:phone":"+1 780 465 5501",
    "sg:postcode":"T6P 1M2",
    "sg:province":"AB",
    "sg:tags":[
        "automobile",
        "co",
        "drive",
        "transporter"
    ],
    "wof:name":"Chey-Anne Trucking Ltd",
    "wof:placetype":"venue"
},
  "geometry": {"coordinates":[-113.363724,53.513245],"type":"Point"}
}