{
  "type": "Feature",
  "properties": {
    "addr:full":"Hudson QC J0P 1H0",
    "addr:postcode":"j0p 1h0",
    "iso:country":"CA",
    "sg:city":"Hudson",
    "sg:classifiers":[
        {
            "category":"Building & Trades",
            "subcategory":"Electrical",
            "type":"Services"
        }
    ],
    "sg:phone":"+1 450 458 5253",
    "sg:postcode":"J0P 1H0",
    "sg:province":"QC",
    "sg:tags":[
        "electric",
        "contractor"
    ],
    "wof:name":"P Leblanc & Frere Electricien",
    "wof:placetype":"venue"
},
  "geometry": {"coordinates":[-74.1306686401,45.4480857849],"type":"Point"}
}