{
  "type": "Feature",
  "properties": {
    "addr:full":"896 2E Av Quebec QC G1L 3B8",
    "addr:housenumber":"896",
    "addr:postcode":"g1l 3b8",
    "addr:street":"2E Av",
    "iso:country":"CA",
    "sg:address":"896 2E Av",
    "sg:city":"Quebec",
    "sg:classifiers":[
        {
            "category":"Shopping",
            "subcategory":"Computers & Home Electronics",
            "type":"Retail Goods"
        }
    ],
    "sg:phone":"+1 418 529 4033",
    "sg:postcode":"G1L 3B8",
    "sg:province":"QC",
    "sg:tags":[
        "equipment",
        "video",
        "microwave",
        "oven"
    ],
    "wof:name":"Atelier Video Laser Enr",
    "wof:placetype":"venue"
},
  "geometry": {"coordinates":[-71.230705,46.82513],"type":"Point"}
}