{
  "type": "Feature",
  "properties": {
    "addr:full":"Surrey BC V3W 1C2",
    "addr:postcode":"v3w 1c2",
    "iso:country":"CA",
    "sg:city":"Surrey",
    "sg:classifiers":[
        {
            "category":"Professional",
            "subcategory":"Business Services",
            "type":"Services"
        }
    ],
    "sg:phone":"+1 604 591 6844",
    "sg:postcode":"V3W 1C2",
    "sg:province":"BC",
    "sg:tags":[
        "diver"
    ],
    "wof:name":"Commercial Underwater Contr",
    "wof:placetype":"venue"
},
  "geometry": {"coordinates":[-122.887741089,49.1272773743],"type":"Point"}
}