{
  "type": "Feature",
  "properties": {
    "addr:full":"Surrey BC V4N 1P3",
    "addr:postcode":"v4n 1p3",
    "iso:country":"CA",
    "sg:city":"Surrey",
    "sg:classifiers":[
        {
            "category":"Banks & Credit Unions",
            "subcategory":"Investment Brokerage",
            "type":"Services"
        }
    ],
    "sg:phone":"+1 604 582 3040",
    "sg:postcode":"V4N 1P3",
    "sg:province":"BC",
    "wof:name":"Edward Jones",
    "wof:placetype":"venue"
},
  "geometry": {"coordinates":[-122.778869629,49.1993484497],"type":"Point"}
}