{
  "type": "Feature",
  "properties": {
    "addr:full":"3 Byng Ave Kapuskasing ON P5N 1W2",
    "addr:housenumber":"3",
    "addr:postcode":"p5n 1w2",
    "addr:street":"Byng Ave",
    "iso:country":"CA",
    "sg:address":"3 Byng Ave",
    "sg:city":"Kapuskasing",
    "sg:classifiers":[
        {
            "category":"Professional",
            "subcategory":"Computer Services",
            "type":"Services"
        }
    ],
    "sg:phone":"+1 705 335 5552",
    "sg:postcode":"P5N 1W2",
    "sg:province":"ON",
    "sg:tags":[
        "website",
        "machine",
        "design",
        "duplicating",
        "copying"
    ],
    "wof:name":"Kap Data & Systems Ltd",
    "wof:placetype":"venue"
},
  "geometry": {"coordinates":[-82.424316,49.416298],"type":"Point"}
}