{
  "type": "Feature",
  "properties": {
    "addr:full":"Oldcastle ON N0R 1L0",
    "addr:postcode":"n0r 1l0",
    "iso:country":"CA",
    "sg:city":"Oldcastle",
    "sg:classifiers":[
        {
            "category":"Wholesale",
            "subcategory":"Electrical",
            "type":"Manufacturing & Wholesale Goods"
        }
    ],
    "sg:phone":"+1 519 737 6310",
    "sg:postcode":"N0R 1L0",
    "sg:province":"ON",
    "sg:tags":[
        "equipment",
        "electric",
        "supply"
    ],
    "wof:name":"Parrline Supply Ltd",
    "wof:placetype":"venue"
},
  "geometry": {"coordinates":[-82.967377,42.228447],"type":"Point"}
}