{
  "type": "Feature",
  "properties": {
    "addr:full":"2001 Av Victoria Saint-Lambert QC J4S 1H1",
    "addr:housenumber":"2001",
    "addr:postcode":"j4s 1h1",
    "addr:street":"Av Victoria",
    "iso:country":"CA",
    "sg:address":"2001 Av Victoria",
    "sg:city":"Saint-Lambert",
    "sg:classifiers":[
        {
            "category":"Shopping",
            "subcategory":"Pharmacy",
            "type":"Retail Goods"
        }
    ],
    "sg:phone":"+1 450 465 2721",
    "sg:postcode":"J4S 1H1",
    "sg:province":"QC",
    "wof:name":"Jean Coutu Pharmacie",
    "wof:placetype":"venue"
},
  "geometry": {"coordinates":[-73.47709655760001,45.4784851074],"type":"Point"}
}