{
  "type": "Feature",
  "properties": {
    "addr:full":"1209 92 Ave #A Tisdale SK S0E 1T0",
    "addr:housenumber":"1209",
    "addr:postcode":"s0e 1t0",
    "addr:street":"92 Ave # A Tisdale",
    "iso:country":"CA",
    "sg:address":"1209 92 Ave #A",
    "sg:city":"Tisdale",
    "sg:classifiers":[
        {
            "category":"Utilities",
            "subcategory":"Refuse",
            "type":"Services"
        }
    ],
    "sg:phone":"+1 306 873 5466",
    "sg:postcode":"S0E 1T0",
    "sg:province":"SK",
    "sg:tags":[
        "garbage",
        "collection"
    ],
    "wof:name":"Tisdale Disposals",
    "wof:placetype":"venue"
},
  "geometry": {"coordinates":[-104.05291748,52.8418006897],"type":"Point"}
}