{
  "type": "Feature",
  "properties": {
    "addr:full":"245 Ch DE Saint-Jean LA Prairie QC J5R 2K2",
    "addr:housenumber":"245",
    "addr:postcode":"j5r 2k2",
    "addr:street":"Ch De Saint-Jean",
    "iso:country":"CA",
    "sg:address":"245 Ch DE Saint-Jean",
    "sg:city":"LA Prairie",
    "sg:classifiers":[
        {
            "category":"Health Services",
            "subcategory":"Chiropractor",
            "type":"Services"
        }
    ],
    "sg:phone":"+1 450 444 3028",
    "sg:postcode":"J5R 2K2",
    "sg:province":"QC",
    "wof:name":"Clinique Chiropratique-Vieux",
    "wof:placetype":"venue"
},
  "geometry": {"coordinates":[-73.492966,45.419163],"type":"Point"}
}