{
  "type": "Feature",
  "properties": {
    "addr:full":"10038 Boul DE Saint-Canut Mirabel QC J7N 1K2",
    "addr:housenumber":"10038",
    "addr:postcode":"j7n 1k2",
    "addr:street":"Boul De Saint-Canut",
    "iso:country":"CA",
    "sg:address":"10038 Boul DE Saint-Canut",
    "sg:city":"Mirabel",
    "sg:classifiers":[
        {
            "category":"Autos & Motor Vehicles",
            "subcategory":"Automobile Sales",
            "type":"Retail Goods"
        }
    ],
    "sg:phone":"+1 450 438 8168",
    "sg:postcode":"J7N 1K2",
    "sg:province":"QC",
    "sg:tags":[
        "car",
        "dealer"
    ],
    "wof:name":"H L Autos Ltee",
    "wof:placetype":"venue"
},
  "geometry": {"coordinates":[-74.08142100000001,45.719524],"type":"Point"}
}