{
  "type": "Feature",
  "properties": {
    "iso:country":"CA",
    "sg:address":"90 Rue Jean-Talon E",
    "sg:city":"Montreal",
    "sg:classifiers":[
        {
            "category":"Shopping",
            "type":"Retail Goods"
        }
    ],
    "sg:phone":"+1 514 271 5503",
    "sg:postcode":"H2R 1S5",
    "sg:province":"QC",
    "sg:tags":[
        "pet",
        "food",
        "shop",
        "supply"
    ],
    "wof:name":"J E Mondou Ltee",
    "wof:placetype":"venue"
},
  "geometry": {"coordinates":[-73.616974,45.535351],"type":"Point"}
}