{
  "type": "Feature",
  "properties": {
    "iso:country":"CA",
    "sg:address":"241 Silver Birch Ave",
    "sg:city":"Toronto",
    "sg:classifiers":[
        {
            "category":"Building & Trades",
            "subcategory":"Construction",
            "type":"Services"
        }
    ],
    "sg:phone":"+1 416 690 4688",
    "sg:postcode":"M4E 3L6",
    "sg:province":"ON",
    "sg:tags":[
        "masonry",
        "contractor"
    ],
    "wof:name":"A Site Construction CO",
    "wof:placetype":"venue"
},
  "geometry": {"coordinates":[-79.2869567871,43.6778755188],"type":"Point"}
}