{
  "type": "Feature",
  "properties": {
    "addr:full":"1670 Bayview Ave Toronto ON M4G 3C2",
    "addr:housenumber":"1670",
    "addr:postcode":"m4g 3c2",
    "addr:street":"Bayview Ave",
    "iso:country":"CA",
    "sg:address":"1670 Bayview Ave",
    "sg:city":"Toronto",
    "sg:classifiers":[
        {
            "category":"Insurance",
            "subcategory":"Insurance Agent",
            "type":"Services"
        }
    ],
    "sg:phone":"+1 416 484 6144",
    "sg:postcode":"M4G 3C2",
    "sg:province":"ON",
    "wof:name":"Piperbarber Insurance",
    "wof:placetype":"venue"
},
  "geometry": {"coordinates":[-79.37604522709999,43.7076225281],"type":"Point"}
}