{
  "type": "Feature",
  "properties": {
    "addr:full":"642 Wilson Ave North York ON M3K 1E1",
    "addr:housenumber":"642",
    "addr:postcode":"m3k 1e1",
    "addr:street":"Wilson Ave",
    "iso:country":"CA",
    "sg:address":"642 Wilson Ave",
    "sg:city":"North York",
    "sg:classifiers":[
        {
            "category":"Restaurant",
            "type":"Food & Drink"
        }
    ],
    "sg:phone":"+1 416 430 6789",
    "sg:postcode":"M3K 1E1",
    "sg:province":"ON",
    "wof:name":"J & F Cafe",
    "wof:placetype":"venue"
},
  "geometry": {"coordinates":[-79.460831,43.732075],"type":"Point"}
}