{
  "type": "Feature",
  "properties": {
    "addr:full":"Vancouver BC V5V 3T4",
    "addr:postcode":"v5v 3t4",
    "iso:country":"CA",
    "sg:city":"Vancouver",
    "sg:classifiers":[
        {
            "category":"Wholesale",
            "subcategory":"Machinery & Supplies",
            "type":"Manufacturing & Wholesale Goods"
        }
    ],
    "sg:phone":"+1 604 874 4168",
    "sg:postcode":"V5V 3T4",
    "sg:province":"BC",
    "sg:tags":[
        "compressor",
        "gas"
    ],
    "wof:name":"Breathing Air Systems",
    "wof:placetype":"venue"
},
  "geometry": {"coordinates":[-123.098572,49.255512],"type":"Point"}
}