{
  "type": "Feature",
  "properties": {
    "addr:full":"SE 36 29 22 W Ethelbert MB R0L 0T0",
    "addr:housenumber":"36 29 22",
    "addr:postcode":"r0l 0t0",
    "addr:street":"Se;W Ethelbert",
    "iso:country":"CA",
    "sg:address":"SE 36 29 22 W",
    "sg:city":"Ethelbert",
    "sg:classifiers":[
        {
            "category":"Organizations",
            "subcategory":"Community Association",
            "type":"Services"
        }
    ],
    "sg:phone":"+1 204 742 3764",
    "sg:postcode":"R0L 0T0",
    "sg:province":"MB",
    "sg:tags":[
        "environmental",
        "org"
    ],
    "wof:name":"Intermountain Conservation",
    "wof:placetype":"venue"
},
  "geometry": {"coordinates":[-100.39846,51.525059],"type":"Point"}
}