{
  "type": "Feature",
  "properties": {
    "addr:full":"Edmonton AB T5J 2W4",
    "addr:postcode":"t5j 2w4",
    "iso:country":"CA",
    "sg:city":"Edmonton",
    "sg:classifiers":[
        {
            "category":"Manufacturing",
            "subcategory":"Jewelry",
            "type":"Manufacturing & Wholesale Goods"
        }
    ],
    "sg:phone":"+1 780 429 1777",
    "sg:postcode":"T5J 2W4",
    "sg:province":"AB",
    "wof:name":"Jedco Limited",
    "wof:placetype":"venue"
},
  "geometry": {"coordinates":[-113.497749329,53.5411567688],"type":"Point"}
}