{
  "type": "Feature",
  "properties": {
    "addr:full":"3154 Millgrove St Victoria BC V9A 1X6",
    "addr:housenumber":"3154",
    "addr:postcode":"v9a 1x6",
    "addr:street":"Millgrove St",
    "iso:country":"CA",
    "sg:address":"3154 Millgrove St",
    "sg:city":"Victoria",
    "sg:classifiers":[
        {
            "category":"Building & Trades",
            "subcategory":"Construction",
            "type":"Services"
        }
    ],
    "sg:phone":"+1 250 385 1158",
    "sg:postcode":"V9A 1X6",
    "sg:province":"BC",
    "sg:tags":[
        "repairing",
        "remodeling",
        "contractor"
    ],
    "wof:name":"J R the Reno King Ltd",
    "wof:placetype":"venue"
},
  "geometry": {"coordinates":[-123.36451700000001,48.428314],"type":"Point"}
}