{
  "type": "Feature",
  "properties": {
    "iso:country":"CA",
    "sg:address":"815 Gerrard St E",
    "sg:city":"Toronto",
    "sg:classifiers":[
        {
            "category":"Shopping",
            "subcategory":"Computers & Home Electronics",
            "type":"Retail Goods"
        }
    ],
    "sg:phone":"+1 416 778 8998",
    "sg:postcode":"M4M 1Y8",
    "sg:province":"ON",
    "sg:tags":[
        "equipment",
        "dealer",
        "software"
    ],
    "wof:name":"Computer Shop",
    "wof:placetype":"venue"
},
  "geometry": {"coordinates":[-79.3445968628,43.6670684814],"type":"Point"}
}