{
  "type": "Feature",
  "properties": {
    "iso:country":"CA",
    "sg:address":"511 Main St",
    "sg:city":"Rencontre East",
    "sg:classifiers":[
        {
            "category":"Organizations",
            "subcategory":"Religious Organization",
            "type":"Services"
        }
    ],
    "sg:phone":"+1 709 258 5927",
    "sg:postcode":"A0H 2C0",
    "sg:province":"NL",
    "sg:tags":[
        "church"
    ],
    "wof:name":"United Pentecostal Church",
    "wof:placetype":"venue"
},
  "geometry": {"coordinates":[-55.212978363,47.6374816895],"type":"Point"}
}