{
  "type": "Feature",
  "properties": {
    "addr:full":"89 Mill St N Brampton ON L6X 1T5",
    "addr:housenumber":"89",
    "addr:postcode":"l6x 1t5",
    "addr:street":"Mill St N",
    "iso:country":"CA",
    "sg:address":"89 Mill St N",
    "sg:city":"Brampton",
    "sg:classifiers":[
        {
            "category":"Real Estate",
            "subcategory":"Surveying",
            "type":"Services"
        }
    ],
    "sg:phone":"+1 905 459 7814",
    "sg:postcode":"L6X 1T5",
    "sg:province":"ON",
    "sg:tags":[
        "surveyor"
    ],
    "wof:name":"B J Stassen Ltd",
    "wof:placetype":"venue"
},
  "geometry": {"coordinates":[-79.76806640620001,43.6879501343],"type":"Point"}
}