{
  "type": "Feature",
  "properties": {
    "addr:full":"Parksville BC V9P 2H1",
    "addr:postcode":"v9p 2h1",
    "iso:country":"CA",
    "sg:city":"Parksville",
    "sg:classifiers":[
        {
            "category":"Health Services",
            "subcategory":"Doctor",
            "type":"Services"
        }
    ],
    "sg:phone":"+1 250 248 1130",
    "sg:postcode":"V9P 2H1",
    "sg:province":"BC",
    "sg:tags":[
        "dentist"
    ],
    "wof:name":"Murdoch, F Edward DDS",
    "wof:placetype":"venue"
},
  "geometry": {"coordinates":[-124.312133789,49.3207626343],"type":"Point"}
}