{
  "type": "Feature",
  "properties": {
    "addr:full":"4171 15th St Jordan Station ON L0R 1S0",
    "addr:housenumber":"4171",
    "addr:postcode":"l0r 1s0",
    "addr:street":"15Th St",
    "iso:country":"CA",
    "sg:address":"4171 15th St",
    "sg:city":"Jordan Station",
    "sg:classifiers":[
        {
            "category":"Education",
            "subcategory":"School",
            "type":"Public Place"
        }
    ],
    "sg:phone":"+1 905 562 4023",
    "sg:postcode":"L0R 1S0",
    "sg:province":"ON",
    "wof:name":"Jordan Christian School",
    "wof:placetype":"venue"
},
  "geometry": {"coordinates":[-79.34973144529999,43.164691925],"type":"Point"}
}