{
  "type": "Feature",
  "properties": {
    "addr:full":"1665 Moran Rd Castlegar BC V1N 4N5",
    "addr:housenumber":"1665",
    "addr:postcode":"v1n 4n5",
    "addr:street":"Moran Rd",
    "iso:country":"CA",
    "sg:address":"1665 Moran Rd",
    "sg:city":"Castlegar",
    "sg:classifiers":[
        {
            "category":"Building & Trades",
            "subcategory":"Construction",
            "type":"Services"
        }
    ],
    "sg:phone":"+1 250 399 4317",
    "sg:postcode":"V1N 4N5",
    "sg:province":"BC",
    "sg:tags":[
        "downspouts",
        "builder",
        "gutter",
        "deck"
    ],
    "wof:name":"Scenic Contractors",
    "wof:placetype":"venue"
},
  "geometry": {"coordinates":[-117.65418243400001,49.2962532043],"type":"Point"}
}