{
  "type": "Feature",
  "properties": {
    "addr:full":"Lethbridge AB T1K 2R3",
    "addr:postcode":"t1k 2r3",
    "iso:country":"CA",
    "sg:city":"Lethbridge",
    "sg:classifiers":[
        {
            "category":"Insurance",
            "subcategory":"Insurance Agent",
            "type":"Services"
        }
    ],
    "sg:phone":"+1 403 320 5877",
    "sg:postcode":"T1K 2R3",
    "sg:province":"AB",
    "wof:name":"Meli Insurance Brokerage",
    "wof:placetype":"venue"
},
  "geometry": {"coordinates":[-112.802978516,49.6781959534],"type":"Point"}
}