{
  "type": "Feature",
  "properties": {
    "addr:full":"32 University Ave Charlottetown PE C1A 4K6",
    "addr:housenumber":"32",
    "addr:postcode":"c1a 4k6",
    "addr:street":"University Ave",
    "iso:country":"CA",
    "sg:address":"32 University Ave",
    "sg:city":"Charlottetown",
    "sg:classifiers":[
        {
            "category":"Restaurant",
            "type":"Food & Drink"
        }
    ],
    "sg:phone":"+1 902 566 2567",
    "sg:postcode":"C1A 4K6",
    "sg:province":"PE",
    "wof:name":"Blossoms Restaurant",
    "wof:placetype":"venue"
},
  "geometry": {"coordinates":[-63.127033,46.235924],"type":"Point"}
}