{
  "type": "Feature",
  "properties": {
    "iso:country":"CA",
    "sg:address":"1637 Rue Sainte-Catherine O",
    "sg:city":"Montreal",
    "sg:classifiers":[
        {
            "category":"Real Estate",
            "subcategory":"Real Estate Agent",
            "type":"Services"
        }
    ],
    "sg:phone":"+1 514 932 6114",
    "sg:postcode":"H3H 1L8",
    "sg:province":"QC",
    "sg:tags":[
        "management"
    ],
    "wof:name":"Elias Investment Corp",
    "wof:placetype":"venue"
},
  "geometry": {"coordinates":[-73.55303192140001,45.5221252441],"type":"Point"}
}