{
  "type": "Feature",
  "properties": {
    "addr:full":"Toronto ON M6K 3C5",
    "addr:postcode":"m6k 3c5",
    "iso:country":"CA",
    "sg:city":"Toronto",
    "sg:classifiers":[
        {
            "category":"Shopping",
            "subcategory":"Clothing, Apparel, & Fashions",
            "type":"Retail Goods"
        }
    ],
    "sg:phone":"+1 416 536 1565",
    "sg:postcode":"M6K 3C5",
    "sg:province":"ON",
    "sg:tags":[
        "sun",
        "goggles",
        "sunglasses"
    ],
    "wof:name":"Mercury Accessories Ltd",
    "wof:placetype":"venue"
},
  "geometry": {"coordinates":[-79.42497299999999,43.639286],"type":"Point"}
}