{
  "type": "Feature",
  "properties": {
    "addr:full":"RR 5 STN Main Perth ON K7H 3C7",
    "addr:postcode":"k7h 3c7",
    "addr:street":"Rr 5 Stn",
    "iso:country":"CA",
    "sg:address":"RR 5 STN Main",
    "sg:city":"Perth",
    "sg:classifiers":[
        {
            "category":"Government",
            "subcategory":"Office",
            "type":"Public Place"
        }
    ],
    "sg:phone":"+1 613 267 2036",
    "sg:postcode":"K7H 3C7",
    "sg:province":"ON",
    "wof:name":"Canada Beveridges Lockstation",
    "wof:placetype":"venue"
},
  "geometry": {"coordinates":[-76.248329,44.898945],"type":"Point"}
}