{
  "type": "Feature",
  "properties": {
    "addr:full":"3026 Arbutus St Vancouver BC V6J 4P7",
    "addr:housenumber":"3026",
    "addr:postcode":"v6j 4p7",
    "addr:street":"Arbutus St",
    "iso:country":"CA",
    "sg:address":"3026 Arbutus St",
    "sg:city":"Vancouver",
    "sg:classifiers":[
        {
            "category":"Organizations",
            "subcategory":"Community Association",
            "type":"Services"
        }
    ],
    "sg:phone":"+1 604 736 8166",
    "sg:postcode":"V6J 4P7",
    "sg:province":"BC",
    "sg:tags":[
        "fraternal"
    ],
    "wof:name":"Royal Canadian Legion",
    "wof:placetype":"venue"
},
  "geometry": {"coordinates":[-123.15286999999999,49.258888],"type":"Point"}
}