{
  "type": "Feature",
  "properties": {
    "addr:full":"517 Notre Dame Ave Sudbury ON P3C 5L1",
    "addr:housenumber":"517",
    "addr:postcode":"p3c 5l1",
    "addr:street":"Notre Dame Ave",
    "iso:country":"CA",
    "sg:address":"517 Notre Dame Ave",
    "sg:city":"Sudbury",
    "sg:classifiers":[
        {
            "category":"Personal",
            "subcategory":"Beauty Salon",
            "type":"Services"
        }
    ],
    "sg:phone":"+1 705 670 9110",
    "sg:postcode":"P3C 5L1",
    "sg:province":"ON",
    "wof:name":"Lucy's Hair Fashion",
    "wof:placetype":"venue"
},
  "geometry": {"coordinates":[-80.987022,46.504601],"type":"Point"}
}