{
  "type": "Feature",
  "properties": {
    "iso:country":"CA",
    "sg:address":"517 Notre Dame Ave",
    "sg:city":"Sudbury",
    "sg:classifiers":[
        {
            "category":"Personal",
            "subcategory":"Beauty Salon",
            "type":"Services"
        }
    ],
    "sg:phone":"+1 705 670 9110",
    "sg:postcode":"P3C 5L1",
    "sg:province":"ON",
    "wof:name":"Lucy's Hair Fashion",
    "wof:placetype":"venue"
},
  "geometry": {"coordinates":[-80.987022,46.504601],"type":"Point"}
}