{
  "type": "Feature",
  "properties": {
    "iso:country":"CA",
    "sg:address":"2962 Lake City Way",
    "sg:city":"Burnaby",
    "sg:classifiers":[
        {
            "category":"Wholesale",
            "subcategory":"Hardware",
            "type":"Manufacturing & Wholesale Goods"
        }
    ],
    "sg:phone":"+1 604 421 5424",
    "sg:postcode":"V5A 3A2",
    "sg:province":"BC",
    "sg:tags":[
        "furnace"
    ],
    "wof:name":"Lennox Industries Ltd",
    "wof:placetype":"venue"
},
  "geometry": {"coordinates":[-122.93754577599999,49.2581214905],"type":"Point"}
}