{
  "type": "Feature",
  "properties": {
    "addr:full":"14384 Hwy 1 Wilmot Station NS B0P 1W0",
    "addr:housenumber":"14384",
    "addr:postcode":"b0p 1w0",
    "addr:street":"Hwy 1 Wilmot Station",
    "iso:country":"CA",
    "sg:address":"14384 Hwy 1",
    "sg:city":"Wilmot Station",
    "sg:classifiers":[
        {
            "category":"Shopping",
            "subcategory":"Used Merchandise",
            "type":"Retail Goods"
        }
    ],
    "sg:phone":"+1 902 825 4731",
    "sg:postcode":"B0P 1W0",
    "sg:province":"NS",
    "sg:tags":[
        "clothing"
    ],
    "wof:name":"Guy's Frenchy's",
    "wof:placetype":"venue"
},
  "geometry": {"coordinates":[-65.06317138670001,44.9753684998],"type":"Point"}
}