{
  "type": "Feature",
  "properties": {
    "addr:full":"5440 Main Osgoode ON K0A 2W0",
    "addr:housenumber":"5440",
    "addr:postcode":"k0a 2w0",
    "addr:street":"Main Osgoode",
    "iso:country":"CA",
    "sg:address":"5440 Main",
    "sg:city":"Osgoode",
    "sg:classifiers":[
        {
            "category":"Organizations",
            "subcategory":"Professional Association",
            "type":"Services"
        }
    ],
    "sg:phone":"+1 613 826 2793",
    "sg:postcode":"K0A 2W0",
    "sg:province":"ON",
    "wof:name":"St James United Church",
    "wof:placetype":"venue"
},
  "geometry": {"coordinates":[-75.61325836180001,45.141998291],"type":"Point"}
}