{
  "type": "Feature",
  "properties": {
    "iso:country":"CA",
    "sg:address":"1242 381 Rte S",
    "sg:city":"Ferland-Et-Boilleau",
    "sg:classifiers":[
        {
            "category":"Food & Beverages",
            "subcategory":"Groceries & Convenience Stores",
            "type":"Retail Goods"
        }
    ],
    "sg:phone":"+1 418 676 2323",
    "sg:postcode":"G0V 1H0",
    "sg:province":"QC",
    "sg:tags":[
        "grocer"
    ],
    "wof:name":"Epicerie Paul-Emile Gagnon Enr",
    "wof:placetype":"venue"
},
  "geometry": {"coordinates":[-70.8756561279,48.1299743652],"type":"Point"}
}