{
  "type": "Feature",
  "properties": {
    "addr:full":"801 Centre St Hanna AB T0J 1P0",
    "addr:housenumber":"801",
    "addr:postcode":"t0j 1p0",
    "addr:street":"Centre St",
    "iso:country":"CA",
    "sg:address":"801 Centre St",
    "sg:city":"Hanna",
    "sg:classifiers":[
        {
            "category":"Organizations",
            "subcategory":"Religious Organization",
            "type":"Services"
        }
    ],
    "sg:phone":"+1 403 854 2866",
    "sg:postcode":"T0J 1P0",
    "sg:province":"AB",
    "sg:tags":[
        "church"
    ],
    "wof:name":"Hanna Sda Church",
    "wof:placetype":"venue"
},
  "geometry": {"coordinates":[-111.92795599999999,51.648026],"type":"Point"}
}