{
  "type": "Feature",
  "properties": {
    "iso:country":"CA",
    "sg:city":"Calgary",
    "sg:classifiers":[
        {
            "category":"Education",
            "subcategory":"Special Training",
            "type":"Public Place"
        }
    ],
    "sg:phone":"+1 403 263 3039",
    "sg:postcode":"T2P 3C6",
    "sg:province":"AB",
    "sg:tags":[
        "instruction",
        "driving"
    ],
    "wof:name":"One Two Three Driving School",
    "wof:placetype":"venue"
},
  "geometry": {"coordinates":[-114.063194275,51.0510902405],"type":"Point"}
}