{
  "type": "Feature",
  "properties": {
    "addr:full":"RR 1 Dalkeith ON K0B 1E0",
    "addr:postcode":"k0b 1e0",
    "addr:street":"Rr 1",
    "iso:country":"CA",
    "sg:address":"RR 1",
    "sg:city":"Dalkeith",
    "sg:classifiers":[
        {
            "category":"Organizations",
            "subcategory":"Religious Organization",
            "type":"Services"
        }
    ],
    "sg:phone":"+1 613 525 3801",
    "sg:postcode":"K0B 1E0",
    "sg:province":"ON",
    "sg:tags":[
        "church"
    ],
    "wof:name":"Kirkhill's United Church",
    "wof:placetype":"venue"
},
  "geometry": {"coordinates":[-74.574455,45.444931],"type":"Point"}
}