{
  "type": "Feature",
  "properties": {
    "addr:full":"530 3rd Ave Prince George BC V2L 3C3",
    "addr:housenumber":"530",
    "addr:postcode":"v2l 3c3",
    "addr:street":"3Rd Ave",
    "iso:country":"CA",
    "sg:address":"530 3rd Ave",
    "sg:city":"Prince George",
    "sg:classifiers":[
        {
            "category":"Professional",
            "subcategory":"Computer Services",
            "type":"Services"
        }
    ],
    "sg:phone":"+1 250 612 5270",
    "sg:postcode":"V2L 3C3",
    "sg:province":"BC",
    "sg:tags":[
        "internet"
    ],
    "wof:name":"Abc Communications",
    "wof:placetype":"venue"
},
  "geometry": {"coordinates":[-122.733779907,53.9136810303],"type":"Point"}
}