{
  "type": "Feature",
  "properties": {
    "addr:full":"3759 Jackfish Lake Rd Chetwynd BC V0C 1J0",
    "addr:housenumber":"3759",
    "addr:postcode":"bc v0c 1j0",
    "addr:street":"Jackfish Lake Rd",
    "iso:country":"CA",
    "sg:address":"3759 Jackfish Lake Rd",
    "sg:city":"Chetwynd",
    "sg:classifiers":[
        {
            "category":"Mining & Drilling",
            "type":"Manufacturing & Wholesale Goods"
        }
    ],
    "sg:phone":"+1 250 788 3929",
    "sg:postcode":"V0C 1J0",
    "sg:province":"BC",
    "sg:tags":[
        "field",
        "oil"
    ],
    "wof:name":"Omineca Oil Field Svc",
    "wof:placetype":"venue"
},
  "geometry": {"coordinates":[-121.564247131,55.7289047241],"type":"Point"}
}