{
  "type": "Feature",
  "properties": {
    "iso:country":"CA",
    "sg:address":"3355 Grandview Hwy",
    "sg:city":"Vancouver",
    "sg:classifiers":[
        {
            "category":"Manufacturing",
            "subcategory":"Printing",
            "type":"Manufacturing & Wholesale Goods"
        }
    ],
    "sg:phone":"+1 604 439 2644",
    "sg:postcode":"V5M 1Z5",
    "sg:province":"BC",
    "sg:tags":[
        "newspaper"
    ],
    "wof:name":"Van Net Newspapers",
    "wof:placetype":"venue"
},
  "geometry": {"coordinates":[-123.032173157,49.2582740784],"type":"Point"}
}