{
  "type": "Feature",
  "properties": {
    "iso:country":"CA",
    "sg:address":"71 King St",
    "sg:city":"St Stephen",
    "sg:classifiers":[
        {
            "category":"Professional",
            "subcategory":"Lawyer & Legal Services",
            "type":"Services"
        }
    ],
    "sg:phone":"+1 506 466 5330",
    "sg:postcode":"E3L 2C4",
    "sg:province":"NB",
    "sg:tags":[
        "attorney"
    ],
    "wof:name":"Sutherland, Ronald W",
    "wof:placetype":"venue"
},
  "geometry": {"coordinates":[-67.2751464844,45.1944122314],"type":"Point"}
}