{
  "type": "Feature",
  "properties": {
    "addr:full":"Newmarket ON L3Y 8T3",
    "addr:postcode":"l3y 8t3",
    "iso:country":"CA",
    "sg:city":"Newmarket",
    "sg:classifiers":[
        {
            "category":"Education",
            "subcategory":"Dance Studio",
            "type":"Public Place"
        }
    ],
    "sg:phone":"+1 905 836 8040",
    "sg:postcode":"L3Y 8T3",
    "sg:province":"ON",
    "sg:tags":[
        "instruction",
        "dancing"
    ],
    "wof:name":"Chantal's Dance Academy",
    "wof:placetype":"venue"
},
  "geometry": {"coordinates":[-79.42076900000001,44.053398],"type":"Point"}
}