{
  "type": "Feature",
  "properties": {
    "addr:full":"2400 Highland Blvd Nanaimo BC V9S 3N7",
    "addr:housenumber":"2400",
    "addr:postcode":"v9s 3n7",
    "addr:street":"Highland Blvd",
    "iso:country":"CA",
    "sg:address":"2400 Highland Blvd",
    "sg:city":"Nanaimo",
    "sg:classifiers":[
        {
            "category":"Organizations",
            "subcategory":"Religious Organization",
            "type":"Services"
        }
    ],
    "sg:phone":"+1 250 758 1334",
    "sg:postcode":"V9S 3N7",
    "sg:province":"BC",
    "sg:tags":[
        "church"
    ],
    "wof:name":"Seventh-Day Adventist Church",
    "wof:placetype":"venue"
},
  "geometry": {"coordinates":[-123.97558600000001,49.194477],"type":"Point"}
}