{
  "type": "Feature",
  "properties": {
    "addr:full":"125 Roblin Blvd E Winkler MB R6W 4A5",
    "addr:housenumber":"125",
    "addr:postcode":"r6w 4a5",
    "addr:street":"Roblin Blvd E Winkler",
    "iso:country":"CA",
    "sg:address":"125 Roblin Blvd E",
    "sg:city":"Winkler",
    "sg:classifiers":[
        {
            "category":"Retail",
            "subcategory":"Auto Repair",
            "type":"Services"
        }
    ],
    "sg:phone":"+1 204 325 2261",
    "sg:postcode":"R6W 4A5",
    "sg:province":"MB",
    "sg:tags":[
        "repairing",
        "automobile"
    ],
    "wof:name":"Framar Auto",
    "wof:placetype":"venue"
},
  "geometry": {"coordinates":[-97.932709,49.188965],"type":"Point"}
}