{
  "type": "Feature",
  "properties": {
    "addr:full":"415 Ch Des Falaises LA Malbaie QC G5A 2V4",
    "addr:housenumber":"415",
    "addr:postcode":"g5a 2v4",
    "addr:street":"Ch Des Falaises",
    "iso:country":"CA",
    "sg:address":"415 Ch Des Falaises",
    "sg:city":"LA Malbaie",
    "sg:classifiers":[
        {
            "category":"Travel",
            "subcategory":"Hotels & Motels",
            "type":"Entertainment"
        }
    ],
    "sg:phone":"+1 418 665 4865",
    "sg:postcode":"G5A 2V4",
    "sg:province":"QC",
    "sg:tags":[
        "inn"
    ],
    "wof:name":"Auberge LA Romance",
    "wof:placetype":"venue"
},
  "geometry": {"coordinates":[-70.14495100000001,47.62809],"type":"Point"}
}