{
  "type": "Feature",
  "properties": {
    "addr:full":"Leduc AB T9E 7J4",
    "addr:postcode":"t9e 7j4",
    "iso:country":"CA",
    "sg:city":"Leduc",
    "sg:classifiers":[
        {
            "category":"Health Services",
            "subcategory":"Doctor",
            "type":"Services"
        }
    ],
    "sg:phone":"+1 780 986 6500",
    "sg:postcode":"T9E 7J4",
    "sg:province":"AB",
    "sg:tags":[
        "dentist"
    ],
    "wof:name":"Kawanami, Roy H DDS",
    "wof:placetype":"venue"
},
  "geometry": {"coordinates":[-113.545959,53.262211],"type":"Point"}
}