{
  "type": "Feature",
  "properties": {
    "iso:country":"CA",
    "sg:address":"90 Rue Tetreau",
    "sg:city":"Sorel-Tracy",
    "sg:classifiers":[
        {
            "category":"Professional",
            "subcategory":"Accounting & Tax Preparation",
            "type":"Services"
        }
    ],
    "sg:phone":"+1 450 743 4112",
    "sg:postcode":"J3P 4S3",
    "sg:province":"QC",
    "sg:tags":[
        "bookkeeping",
        "return",
        "system",
        "filing"
    ],
    "wof:name":"Claude Huard & Assoc Inc",
    "wof:placetype":"venue"
},
  "geometry": {"coordinates":[-73.1075668335,46.034942627],"type":"Point"}
}