{
  "type": "Feature",
  "properties": {
    "addr:full":"L'Acadie QC J2Y 1C5",
    "addr:postcode":"j2y 1c5",
    "iso:country":"CA",
    "sg:city":"L'Acadie",
    "sg:classifiers":[
        {
            "category":"Wholesale",
            "subcategory":"Durable Goods & Equipment",
            "type":"Manufacturing & Wholesale Goods"
        }
    ],
    "sg:phone":"+1 450 347 8394",
    "sg:postcode":"J2Y 1C5",
    "sg:province":"QC",
    "sg:tags":[
        "engineering",
        "infrared",
        "inspection",
        "supply"
    ],
    "wof:name":"Services Electrotechniques Inc",
    "wof:placetype":"venue"
},
  "geometry": {"coordinates":[-73.3451766968,45.3149147034],"type":"Point"}
}