{
  "type": "Feature",
  "properties": {
    "iso:country":"CA",
    "sg:address":"849 Av Turcotte",
    "sg:city":"Sainte-Marie",
    "sg:classifiers":[
        {
            "category":"Personal",
            "subcategory":"Beauty Salon",
            "type":"Services"
        }
    ],
    "sg:phone":"+1 418 387 1310",
    "sg:postcode":"G6E 3J3",
    "sg:province":"QC",
    "wof:name":"Salon Design",
    "wof:placetype":"venue"
},
  "geometry": {"coordinates":[-71.00030517579999,46.4378356934],"type":"Point"}
}