{
  "type": "Feature",
  "properties": {
    "addr:full":"Oakville ON L6J 6G6",
    "addr:postcode":"l6j 6g6",
    "iso:country":"CA",
    "sg:city":"Oakville",
    "sg:classifiers":[
        {
            "category":"Social Services",
            "type":"Services"
        }
    ],
    "sg:phone":"+1 905 338 3873",
    "sg:postcode":"L6J 6G6",
    "sg:province":"ON",
    "sg:tags":[
        "counselor",
        "marriage",
        "family"
    ],
    "wof:name":"Wellness Counselling Group",
    "wof:placetype":"venue"
},
  "geometry": {"coordinates":[-79.68436431879999,43.458065033],"type":"Point"}
}