{
  "type": "Feature",
  "properties": {
    "addr:full":"20306 37B Ave Langley BC V3A 2T3",
    "addr:housenumber":"20306",
    "addr:postcode":"v3a 2t3",
    "addr:street":"37B Ave",
    "iso:country":"CA",
    "sg:address":"20306 37B Ave",
    "sg:city":"Langley",
    "sg:classifiers":[
        {
            "category":"Building & Trades",
            "subcategory":"Construction",
            "type":"Services"
        }
    ],
    "sg:phone":"+1 604 530 7243",
    "sg:postcode":"V3A 2T3",
    "sg:province":"BC",
    "sg:tags":[
        "marking",
        "maintenance",
        "parking"
    ],
    "wof:name":"Leading Edge Linemarking",
    "wof:placetype":"venue"
},
  "geometry": {"coordinates":[-122.65657,49.104122],"type":"Point"}
}