{
  "type": "Feature",
  "properties": {
    "iso:country":"CA",
    "sg:address":"319 5th St",
    "sg:city":"Courtenay",
    "sg:classifiers":[
        {
            "category":"Shopping",
            "subcategory":"Gifts & Souvenirs",
            "type":"Retail Goods"
        }
    ],
    "sg:phone":"+1 250 338 8404",
    "sg:postcode":"V9N 1J9",
    "sg:province":"BC",
    "sg:tags":[
        "shop"
    ],
    "wof:name":"Home & Garden Gate",
    "wof:placetype":"venue"
},
  "geometry": {"coordinates":[-124.999107,49.690952],"type":"Point"}
}