{
  "type": "Feature",
  "properties": {
    "addr:full":"3801 Rue Francois-Borel Sainte-Foy QC G1X 4T8",
    "addr:housenumber":"3801",
    "addr:postcode":"g1x 4t8",
    "addr:street":"Rue Francois-Borel",
    "iso:country":"CA",
    "sg:address":"3801 Rue Francois-Borel",
    "sg:city":"Sainte-Foy",
    "sg:classifiers":[
        {
            "category":"Health Services",
            "subcategory":"Chiropractor",
            "type":"Services"
        }
    ],
    "sg:phone":"+1 418 871 5202",
    "sg:postcode":"G1X 4T8",
    "sg:province":"QC",
    "wof:name":"Clinique Chiropratique Canuel",
    "wof:placetype":"venue"
},
  "geometry": {"coordinates":[-71.3525466919,46.7706069946],"type":"Point"}
}