{
  "type": "Feature",
  "properties": {
    "addr:full":"9132 Rue Airlie Lasalle QC H8R 2A3",
    "addr:housenumber":"9132",
    "addr:postcode":"h8r 2a3",
    "addr:street":"Rue Airlie",
    "iso:country":"CA",
    "sg:address":"9132 Rue Airlie",
    "sg:city":"Lasalle",
    "sg:classifiers":[
        {
            "category":"Autos & Motor Vehicles",
            "subcategory":"Fuel & Gas Station",
            "type":"Retail Goods"
        }
    ],
    "sg:phone":"+1 514 365 9563",
    "sg:postcode":"H8R 2A3",
    "sg:province":"QC",
    "sg:tags":[
        "oil"
    ],
    "wof:name":"Super Gaz Ltee",
    "wof:placetype":"venue"
},
  "geometry": {"coordinates":[-73.63468899999999,45.42136],"type":"Point"}
}