{
  "type": "Feature",
  "properties": {
    "iso:country":"CA",
    "sg:address":"250 Mcintyre Dr #1",
    "sg:city":"Kitchener",
    "sg:classifiers":[
        {
            "category":"Manufacturing",
            "subcategory":"Tools & Machinery",
            "type":"Manufacturing & Wholesale Goods"
        }
    ],
    "sg:phone":"+1 519 893 5015",
    "sg:postcode":"N2R 1E8",
    "sg:province":"ON",
    "sg:tags":[
        "machine",
        "shop"
    ],
    "wof:name":"Ags Machine Tool Inc",
    "wof:placetype":"venue"
},
  "geometry": {"coordinates":[-80.4826583862,43.4032859802],"type":"Point"}
}