{
  "type": "Feature",
  "properties": {
    "iso:country":"CA",
    "sg:address":"59 Ortona Crt",
    "sg:city":"Concord",
    "sg:classifiers":[
        {
            "category":"Manufacturing",
            "subcategory":"Glass & Minerals",
            "type":"Manufacturing & Wholesale Goods"
        }
    ],
    "sg:phone":"+1 905 760 2395",
    "sg:postcode":"L4K 3M2",
    "sg:province":"ON",
    "sg:tags":[
        "product",
        "marble"
    ],
    "wof:name":"Mr Marble",
    "wof:placetype":"venue"
},
  "geometry": {"coordinates":[-79.48815917970001,43.8102912903],"type":"Point"}
}