{
  "type": "Feature",
  "properties": {
    "addr:full":"1567 Cedar Hill Cross Rd Victoria BC V8P 2P3",
    "addr:housenumber":"1567",
    "addr:postcode":"v8p 2p3",
    "addr:street":"Cedar Hill Cross Rd",
    "iso:country":"CA",
    "sg:address":"1567 Cedar Hill Cross Rd",
    "sg:city":"Victoria",
    "sg:classifiers":[
        {
            "category":"Restaurant",
            "type":"Food & Drink"
        }
    ],
    "sg:phone":"+1 250 952 3610",
    "sg:postcode":"V8P 2P3",
    "sg:province":"BC",
    "wof:name":"Mc Donald's",
    "wof:placetype":"venue"
},
  "geometry": {"coordinates":[-123.364517212,48.428314209],"type":"Point"}
}