{
  "type": "Feature",
  "properties": {
    "iso:country":"CA",
    "sg:address":"106 Circle Dr W",
    "sg:city":"Saskatoon",
    "sg:classifiers":[
        {
            "category":"Shopping",
            "subcategory":"Gifts & Souvenirs",
            "type":"Retail Goods"
        }
    ],
    "sg:phone":"+1 306 652 3363",
    "sg:postcode":"S7L 4L6",
    "sg:province":"SK",
    "sg:tags":[
        "shop"
    ],
    "wof:name":"Sonquist Ventures",
    "wof:placetype":"venue"
},
  "geometry": {"coordinates":[-106.671897888,52.1580543518],"type":"Point"}
}