{
  "type": "Feature",
  "properties": {
    "addr:full":"5405 Rue Romeo-Martel Trois-Rivieres QC G8Y 4Y3",
    "addr:housenumber":"5405",
    "addr:postcode":"g8y 4y3",
    "addr:street":"Rue Romeo-Martel Trois-Rivieres",
    "iso:country":"CA",
    "sg:address":"5405 Rue Romeo-Martel",
    "sg:city":"Trois-Rivieres",
    "sg:classifiers":[
        {
            "category":"Freight",
            "type":"Transportation"
        }
    ],
    "sg:phone":"+1 819 693 4615",
    "sg:postcode":"G8Y 4Y3",
    "sg:province":"QC",
    "sg:tags":[
        "trucking"
    ],
    "wof:name":"St-Pierre, Andre",
    "wof:placetype":"venue"
},
  "geometry": {"coordinates":[-72.60086800000001,46.356815],"type":"Point"}
}