{
  "type": "Feature",
  "properties": {
    "addr:full":"4450 Ontario St Beamsville ON L0R 1B5",
    "addr:housenumber":"4450",
    "addr:postcode":"l0r 1b5",
    "addr:street":"Ontario St",
    "iso:country":"CA",
    "sg:address":"4450 Ontario St",
    "sg:city":"Beamsville",
    "sg:classifiers":[
        {
            "category":"Retail",
            "subcategory":"Animal Services",
            "type":"Services"
        }
    ],
    "sg:phone":"+1 905 563 1800",
    "sg:postcode":"L0R 1B5",
    "sg:province":"ON",
    "sg:tags":[
        "pet",
        "grooming",
        "washing"
    ],
    "wof:name":"Ryan's Pet Grooming",
    "wof:placetype":"venue"
},
  "geometry": {"coordinates":[-79.476997,43.173458],"type":"Point"}
}