{
  "type": "Feature",
  "properties": {
    "addr:full":"171 Prince William St Saint John NB E2L 2B4",
    "addr:housenumber":"171",
    "addr:postcode":"nb e2l 2b4",
    "addr:street":"Prince William St",
    "iso:country":"CA",
    "sg:address":"171 Prince William St",
    "sg:city":"Saint John",
    "sg:classifiers":[
        {
            "category":"Professional",
            "subcategory":"Accounting & Tax Preparation",
            "type":"Services"
        }
    ],
    "sg:phone":"+1 506 658 6080",
    "sg:postcode":"E2L 2B4",
    "sg:province":"NB",
    "sg:tags":[
        "accountant",
        "return",
        "filing"
    ],
    "wof:name":"D R Mc Colgan & CO",
    "wof:placetype":"venue"
},
  "geometry": {"coordinates":[-66.061706543,45.2702255249],"type":"Point"}
}