{
  "type": "Feature",
  "properties": {
    "addr:full":"1521 Hugh Allan Dr Kamloops BC V1S 1P4",
    "addr:housenumber":"1521",
    "addr:postcode":"bc v1s 1p4",
    "addr:street":"Hugh Allan Dr",
    "iso:country":"CA",
    "sg:address":"1521 Hugh Allan Dr",
    "sg:city":"Kamloops",
    "sg:classifiers":[
        {
            "category":"Travel",
            "subcategory":"Hotels & Motels",
            "type":"Entertainment"
        }
    ],
    "sg:phone":"+1 250 374 8688",
    "sg:postcode":"V1S 1P4",
    "sg:province":"BC",
    "wof:name":"Super 8 Motel",
    "wof:placetype":"venue"
},
  "geometry": {"coordinates":[-120.38059199999999,50.651859],"type":"Point"}
}