{
  "type": "Feature",
  "properties": {
    "addr:full":"Georgetown ON L7G 4S5",
    "addr:postcode":"l7g 4s5",
    "iso:country":"CA",
    "sg:city":"Georgetown",
    "sg:classifiers":[
        {
            "category":"Recreation",
            "type":"Entertainment"
        }
    ],
    "sg:phone":"+1 905 877 5236",
    "sg:postcode":"L7G 4S5",
    "sg:province":"ON",
    "sg:tags":[
        "golf",
        "banquet",
        "rooms"
    ],
    "wof:name":"North Halton Golf & Country",
    "wof:placetype":"venue"
},
  "geometry": {"coordinates":[-79.9275588989,43.6400375366],"type":"Point"}
}