{
  "type": "Feature",
  "properties": {
    "addr:full":"509 Waterloo St London ON N6B 2P8",
    "addr:housenumber":"509",
    "addr:postcode":"n6b 2p8",
    "addr:street":"Waterloo St",
    "iso:country":"CA",
    "sg:address":"509 Waterloo St",
    "sg:city":"London",
    "sg:classifiers":[
        {
            "category":"Education",
            "subcategory":"School",
            "type":"Public Place"
        }
    ],
    "sg:phone":"+1 519 452 2620",
    "sg:postcode":"N6B 2P8",
    "sg:province":"ON",
    "wof:name":"London Central Secondary Schl",
    "wof:placetype":"venue"
},
  "geometry": {"coordinates":[-81.24416351319999,42.9886169434],"type":"Point"}
}