{
  "type": "Feature",
  "properties": {
    "addr:full":"700 Finley Ave # 4 Ajax ON L1S 3Z2",
    "addr:housenumber":"700",
    "addr:postcode":"l1s 3z2",
    "addr:street":"Finley Ave # 4",
    "iso:country":"CA",
    "sg:address":"700 Finley Ave # 4",
    "sg:city":"Ajax",
    "sg:classifiers":[
        {
            "category":"Professional",
            "subcategory":"Employment Agencies",
            "type":"Services"
        }
    ],
    "sg:phone":"+1 905 428 6876",
    "sg:postcode":"L1S 3Z2",
    "sg:province":"ON",
    "sg:tags":[
        "opportunity"
    ],
    "wof:name":"Sdc Information Svc",
    "wof:placetype":"venue"
},
  "geometry": {"coordinates":[-79.0263595581,43.8306617737],"type":"Point"}
}