{
  "type": "Feature",
  "properties": {
    "addr:full":"Saint-Jean-Sur-Richelieu QC J3B 7X4",
    "addr:postcode":"j3b 7x4",
    "iso:country":"CA",
    "sg:city":"Saint-Jean-Sur-Richelieu",
    "sg:classifiers":[
        {
            "category":"Building & Trades",
            "subcategory":"Construction",
            "type":"Services"
        }
    ],
    "sg:phone":"+1 450 349 8080",
    "sg:postcode":"J3B 7X4",
    "sg:province":"QC",
    "sg:tags":[
        "house",
        "steam",
        "cleaning"
    ],
    "wof:name":"Lavage Du Haut-Richelieu Inc",
    "wof:placetype":"venue"
},
  "geometry": {"coordinates":[-73.284836,45.320766],"type":"Point"}
}