{
  "type": "Feature",
  "properties": {
    "addr:full":"340 Jamieson Bone Rd Belleville ON K8N 5S8",
    "addr:housenumber":"340",
    "addr:postcode":"k8n 5s8",
    "addr:street":"Jamieson Bone Rd",
    "iso:country":"CA",
    "sg:address":"340 Jamieson Bone Rd",
    "sg:city":"Belleville",
    "sg:classifiers":[
        {
            "category":"Wholesale",
            "subcategory":"Machinery & Supplies",
            "type":"Manufacturing & Wholesale Goods"
        }
    ],
    "sg:phone":"+1 613 966 5433",
    "sg:postcode":"K8N 5S8",
    "sg:province":"ON",
    "sg:tags":[
        "equipment",
        "material",
        "truck",
        "handling"
    ],
    "wof:name":"Hansler Industries Ltd",
    "wof:placetype":"venue"
},
  "geometry": {"coordinates":[-77.365639,44.19725],"type":"Point"}
}