{
  "type": "Feature",
  "properties": {
    "addr:full":"4404 Calgary Trail Northbound Edmonton AB T6H 5C2",
    "addr:housenumber":"4404",
    "addr:postcode":"t6h 5c2",
    "addr:street":"Calgary Trail",
    "iso:country":"CA",
    "sg:address":"4404 Calgary Trail Northbound",
    "sg:city":"Edmonton",
    "sg:classifiers":[
        {
            "category":"Retail",
            "subcategory":"Auto Rental",
            "type":"Services"
        }
    ],
    "sg:phone":"+1 780 448 0068",
    "sg:postcode":"T6H 5C2",
    "sg:province":"AB",
    "sg:tags":[
        "renting",
        "automobile"
    ],
    "wof:name":"Avis Rent A Car",
    "wof:placetype":"venue"
},
  "geometry": {"coordinates":[-113.49037199999999,53.546219],"type":"Point"}
}