{
  "type": "Feature",
  "properties": {
    "addr:full":"300 Borough Dr #726K Scarborough ON M1P 4P5",
    "addr:housenumber":"300",
    "addr:postcode":"m1p 4p5",
    "addr:street":"Borough Dr # 726K",
    "iso:country":"CA",
    "sg:address":"300 Borough Dr #726K",
    "sg:city":"Scarborough",
    "sg:classifiers":[
        {
            "category":"Restaurant",
            "type":"Food & Drink"
        }
    ],
    "sg:phone":"+1 416 296 0369",
    "sg:postcode":"M1P 4P5",
    "sg:province":"ON",
    "wof:name":"Druxy's Famous Deli Sandwiches",
    "wof:placetype":"venue"
},
  "geometry": {"coordinates":[-79.2541732788,43.7755508423],"type":"Point"}
}