{
  "type": "Feature",
  "properties": {
    "addr:full":"899 3E Rue Chibougamau QC G8P 1R3",
    "addr:housenumber":"899",
    "addr:postcode":"g8p 1r3",
    "addr:street":"3E Rue",
    "iso:country":"CA",
    "sg:address":"899 3E Rue",
    "sg:city":"Chibougamau",
    "sg:classifiers":[
        {
            "category":"Retail",
            "subcategory":"Auto Repair",
            "type":"Services"
        }
    ],
    "sg:phone":"+1 418 748 2528",
    "sg:postcode":"G8P 1R3",
    "sg:province":"QC",
    "sg:tags":[
        "repairing",
        "automobile"
    ],
    "wof:name":"Girard Esso",
    "wof:placetype":"venue"
},
  "geometry": {"coordinates":[-74.38503300000001,49.912388],"type":"Point"}
}