{
  "type": "Feature",
  "properties": {
    "iso:country":"CA",
    "sg:address":"76 Rue Jacques-Cartier",
    "sg:city":"Gaspe",
    "sg:classifiers":[
        {
            "category":"Shopping",
            "subcategory":"Florist",
            "type":"Retail Goods"
        }
    ],
    "sg:phone":"+1 418 368 3688",
    "sg:postcode":"G4X 1M4",
    "sg:province":"QC",
    "wof:name":"Gaspe Fleuriste Enr",
    "wof:placetype":"venue"
},
  "geometry": {"coordinates":[-64.481323,48.833084],"type":"Point"}
}