{
  "type": "Feature",
  "properties": {
    "addr:full":"Saint-Felix-DE-Valois QC J0K 2M0",
    "addr:postcode":"j0k 2m0",
    "iso:country":"CA",
    "sg:city":"Saint-Felix-DE-Valois",
    "sg:classifiers":[
        {
            "category":"Insurance",
            "subcategory":"Insurance Agent",
            "type":"Services"
        }
    ],
    "sg:phone":"+1 450 889 5557",
    "sg:postcode":"J0K 2M0",
    "sg:province":"QC",
    "wof:name":"Assurances Robillard & Assoc",
    "wof:placetype":"venue"
},
  "geometry": {"coordinates":[-73.4301605225,46.1595802307],"type":"Point"}
}