{
  "type": "Feature",
  "properties": {
    "addr:full":"22367 119 Ave Maple Ridge BC V2X 2Z2",
    "addr:housenumber":"22367",
    "addr:postcode":"v2x 2z2",
    "addr:street":"119 Ave",
    "iso:country":"CA",
    "sg:address":"22367 119 Ave",
    "sg:city":"Maple Ridge",
    "sg:classifiers":[
        {
            "category":"Shopping",
            "subcategory":"Used Merchandise",
            "type":"Retail Goods"
        }
    ],
    "sg:phone":"+1 604 467 5595",
    "sg:postcode":"V2X 2Z2",
    "sg:province":"BC",
    "sg:tags":[
        "book",
        "rare",
        "dealer"
    ],
    "wof:name":"Bookcase",
    "wof:placetype":"venue"
},
  "geometry": {"coordinates":[-122.602745056,49.2186775208],"type":"Point"}
}