{
  "type": "Feature",
  "properties": {
    "addr:full":"51 Esna Park Dr Markham ON L3R 1C9",
    "addr:housenumber":"51",
    "addr:postcode":"l3r 1c9",
    "addr:street":"Esna Park Dr",
    "iso:country":"CA",
    "sg:address":"51 Esna Park Dr",
    "sg:city":"Markham",
    "sg:classifiers":[
        {
            "category":"Freight",
            "type":"Transportation"
        }
    ],
    "sg:phone":"+1 905 940 1774",
    "sg:postcode":"L3R 1C9",
    "sg:province":"ON",
    "sg:tags":[
        "cartage",
        "courier"
    ],
    "wof:name":"Atlantic Courier & Cartage Ltd",
    "wof:placetype":"venue"
},
  "geometry": {"coordinates":[-79.345825,43.826874],"type":"Point"}
}