{
  "type": "Feature",
  "properties": {
    "addr:full":"26 Antonia Crt Woodbridge ON L4H 1C9",
    "addr:housenumber":"26",
    "addr:postcode":"l4h 1c9",
    "addr:street":"Antonia Crt",
    "iso:country":"CA",
    "sg:address":"26 Antonia Crt",
    "sg:city":"Woodbridge",
    "sg:classifiers":[
        {
            "category":"Building & Trades",
            "subcategory":"Construction",
            "type":"Services"
        }
    ],
    "sg:phone":"+1 905 851 1527",
    "sg:postcode":"L4H 1C9",
    "sg:province":"ON",
    "sg:tags":[
        "general",
        "contractor"
    ],
    "wof:name":"Marsab Contractors & Carpenter",
    "wof:placetype":"venue"
},
  "geometry": {"coordinates":[-79.62183400000001,43.799149],"type":"Point"}
}