{
  "type": "Feature",
  "properties": {
    "addr:full":"RR 2 Tavistock ON N0B 2R0",
    "addr:postcode":"n0b 2r0",
    "addr:street":"Rr 2",
    "iso:country":"CA",
    "sg:address":"RR 2",
    "sg:city":"Tavistock",
    "sg:classifiers":[
        {
            "category":"Building & Trades",
            "subcategory":"Construction",
            "type":"Services"
        }
    ],
    "sg:phone":"+1 519 271 4598",
    "sg:postcode":"N0B 2R0",
    "sg:province":"ON",
    "sg:tags":[
        "masonry",
        "contractor"
    ],
    "wof:name":"A Jeffrey Masonry",
    "wof:placetype":"venue"
},
  "geometry": {"coordinates":[-80.83616600000001,43.321362],"type":"Point"}
}