{
  "type": "Feature",
  "properties": {
    "addr:full":"559 Bloor St W Toronto ON M5S 1Y6",
    "addr:housenumber":"559",
    "addr:postcode":"m5s 1y6",
    "addr:street":"Bloor St W",
    "iso:country":"CA",
    "sg:address":"559 Bloor St W",
    "sg:city":"Toronto",
    "sg:classifiers":[
        {
            "category":"Restaurant",
            "type":"Food & Drink"
        }
    ],
    "sg:phone":"+1 416 536 3043",
    "sg:postcode":"M5S 1Y6",
    "sg:province":"ON",
    "wof:name":"Burger King",
    "wof:placetype":"venue"
},
  "geometry": {"coordinates":[-79.41069,43.665085],"type":"Point"}
}