{
  "type": "Feature",
  "properties": {
    "addr:full":"203 Gore St Amherstburg ON N9V 1L3",
    "addr:housenumber":"203",
    "addr:postcode":"n9v 1l3",
    "addr:street":"Gore St",
    "iso:country":"CA",
    "sg:address":"203 Gore St",
    "sg:city":"Amherstburg",
    "sg:classifiers":[
        {
            "category":"Building & Trades",
            "subcategory":"Construction",
            "type":"Services"
        }
    ],
    "sg:phone":"+1 519 736 5764",
    "sg:postcode":"N9V 1L3",
    "sg:province":"ON",
    "sg:tags":[
        "carpenter"
    ],
    "wof:name":"Morency Carpentry",
    "wof:placetype":"venue"
},
  "geometry": {"coordinates":[-83.105743,42.101818],"type":"Point"}
}