{
  "type": "Feature",
  "properties": {
    "addr:full":"3 Lyndhurst St Hamilton ON L8L 7G6",
    "addr:housenumber":"3",
    "addr:postcode":"l8l 7g6",
    "addr:street":"Lyndhurst St",
    "iso:country":"CA",
    "sg:address":"3 Lyndhurst St",
    "sg:city":"Hamilton",
    "sg:classifiers":[
        {
            "category":"Wholesale",
            "subcategory":"Vending Machines",
            "type":"Manufacturing & Wholesale Goods"
        }
    ],
    "sg:phone":"+1 905 545 0077",
    "sg:postcode":"L8L 7G6",
    "sg:province":"ON",
    "wof:name":"Tiger Vending",
    "wof:placetype":"venue"
},
  "geometry": {"coordinates":[-79.82203699999999,43.256805],"type":"Point"}
}