{
  "type": "Feature",
  "properties": {
    "addr:full":"213 St George St Annapolis Royal NS B0S 1A0",
    "addr:housenumber":"213",
    "addr:postcode":"b0s 1a0",
    "addr:street":"St George St",
    "iso:country":"CA",
    "sg:address":"213 St George St",
    "sg:city":"Annapolis Royal",
    "sg:classifiers":[
        {
            "category":"Shopping",
            "subcategory":"Clothing, Apparel, & Fashions",
            "type":"Retail Goods"
        }
    ],
    "sg:phone":"+1 902 532 2070",
    "sg:postcode":"B0S 1A0",
    "sg:province":"NS",
    "sg:tags":[
        "leather"
    ],
    "wof:name":"Bainton's Tannery Outlet",
    "wof:placetype":"venue"
},
  "geometry": {"coordinates":[-65.519051,44.745052],"type":"Point"}
}