{
  "type": "Feature",
  "properties": {
    "iso:country":"CA",
    "sg:address":"111 Rue DE Carillon",
    "sg:city":"Hull",
    "sg:classifiers":[
        {
            "category":"Education",
            "subcategory":"School",
            "type":"Public Place"
        }
    ],
    "sg:phone":"+1 819 778 8550",
    "sg:postcode":"J8X 2P8",
    "sg:province":"QC",
    "wof:name":"Vallee Jeunesse",
    "wof:placetype":"venue"
},
  "geometry": {"coordinates":[-75.723808,45.433273],"type":"Point"}
}