{
  "type": "Feature",
  "properties": {
    "addr:full":"4261 Highway 7 # 141A Markham ON L3R 9W6",
    "addr:housenumber":"4261",
    "addr:postcode":"l3r 9w6",
    "addr:street":"Highway 7 # 141A",
    "iso:country":"CA",
    "sg:address":"4261 Highway 7 # 141A",
    "sg:city":"Markham",
    "sg:classifiers":[
        {
            "category":"Manufacturing",
            "subcategory":"Printing",
            "type":"Manufacturing & Wholesale Goods"
        }
    ],
    "sg:phone":"+1 416 283 3373",
    "sg:postcode":"L3R 9W6",
    "sg:province":"ON",
    "sg:tags":[
        "newspaper"
    ],
    "wof:name":"Community Digest Multicultural",
    "wof:placetype":"venue"
},
  "geometry": {"coordinates":[-79.3399429321,43.8560333252],"type":"Point"}
}