{
  "type": "Feature",
  "properties": {
    "addr:full":"41 Kelfield St Etobicoke ON M9W 5A3",
    "addr:housenumber":"41",
    "addr:postcode":"m9w 5a3",
    "addr:street":"Kelfield St",
    "iso:country":"CA",
    "sg:address":"41 Kelfield St",
    "sg:city":"Etobicoke",
    "sg:classifiers":[
        {
            "category":"Home & Garden",
            "subcategory":"Garden Supply",
            "type":"Retail Goods"
        }
    ],
    "sg:phone":"+1 416 247 7875",
    "sg:postcode":"M9W 5A3",
    "sg:province":"ON",
    "sg:tags":[
        "lawn",
        "mower"
    ],
    "wof:name":"Gordon Bannerman Ltd",
    "wof:placetype":"venue"
},
  "geometry": {"coordinates":[-79.5758361816,43.6868286133],"type":"Point"}
}