{
  "type": "Feature",
  "properties": {
    "addr:full":"6480 Av Isaac-Bedard Charlesbourg QC G1H 2Z9",
    "addr:housenumber":"6480",
    "addr:postcode":"g1h 2z9",
    "addr:street":"Av Isaac-Bedard",
    "iso:country":"CA",
    "sg:address":"6480 Av Isaac-Bedard",
    "sg:city":"Charlesbourg",
    "sg:classifiers":[
        {
            "category":"Professional",
            "subcategory":"Accounting & Tax Preparation",
            "type":"Services"
        }
    ],
    "sg:phone":"+1 418 627 2424",
    "sg:postcode":"G1H 2Z9",
    "sg:province":"QC",
    "sg:tags":[
        "accountant"
    ],
    "wof:name":"Duclos, Jean",
    "wof:placetype":"venue"
},
  "geometry": {"coordinates":[-71.258934021,46.8538246155],"type":"Point"}
}