{
  "type": "Feature",
  "properties": {
    "iso:country":"CA",
    "sg:city":"Repulse Bay",
    "sg:classifiers":[
        {
            "category":"Shopping",
            "subcategory":"Discount & Variety Stores",
            "type":"Retail Goods"
        }
    ],
    "sg:phone":"+1 867 462 9923",
    "sg:postcode":"X0C 0H0",
    "sg:province":"NU",
    "sg:tags":[
        "department",
        "general"
    ],
    "wof:name":"Northern Stores",
    "wof:placetype":"venue"
},
  "geometry": {"coordinates":[-86.2357177734,66.5250701904],"type":"Point"}
}