{
  "type": "Feature",
  "properties": {
    "addr:full":"492 Days Rd Kingston ON K7M 5R4",
    "addr:housenumber":"492",
    "addr:postcode":"k7m 5r4",
    "addr:street":"Days Rd",
    "iso:country":"CA",
    "sg:address":"492 Days Rd",
    "sg:city":"Kingston",
    "sg:classifiers":[
        {
            "category":"Manufacturing",
            "subcategory":"Apparel",
            "type":"Manufacturing & Wholesale Goods"
        }
    ],
    "sg:phone":"+1 613 634 2437",
    "sg:postcode":"K7M 5R4",
    "sg:province":"ON",
    "sg:tags":[
        "flag",
        "banner"
    ],
    "wof:name":"Multideas Promotions",
    "wof:placetype":"venue"
},
  "geometry": {"coordinates":[-76.57068599999999,44.23468],"type":"Point"}
}