{
  "type": "Feature",
  "properties": {
    "addr:full":"210 Boul LA Salle Baie-Comeau QC G4Z 1S6",
    "addr:housenumber":"210",
    "addr:postcode":"g4z 1s6",
    "addr:street":"Boul La",
    "iso:country":"CA",
    "sg:address":"210 Boul LA Salle",
    "sg:city":"Baie-Comeau",
    "sg:classifiers":[
        {
            "category":"Retail",
            "subcategory":"Auto Rental",
            "type":"Services"
        }
    ],
    "sg:phone":"+1 418 294 2414",
    "sg:postcode":"G4Z 1S6",
    "sg:province":"QC",
    "sg:tags":[
        "renting",
        "automobile"
    ],
    "wof:name":"Location Sauvageau",
    "wof:placetype":"venue"
},
  "geometry": {"coordinates":[-68.169418335,49.2162818909],"type":"Point"}
}