{
  "type": "Feature",
  "properties": {
    "addr:full":"1105 Patricia Cres Jasper AB T0E 1E0",
    "addr:housenumber":"1105",
    "addr:postcode":"t0e 1e0",
    "addr:street":"Patricia Cres",
    "iso:country":"CA",
    "sg:address":"1105 Patricia Cres",
    "sg:city":"Jasper",
    "sg:classifiers":[
        {
            "category":"Freight",
            "type":"Transportation"
        }
    ],
    "sg:phone":"+1 780 852 4660",
    "sg:postcode":"T0E 1E0",
    "sg:province":"AB",
    "sg:tags":[
        "mover"
    ],
    "wof:name":"Advantage Relocation Systems",
    "wof:placetype":"venue"
},
  "geometry": {"coordinates":[-118.09865600000001,52.869347],"type":"Point"}
}