{
  "type": "Feature",
  "properties": {
    "addr:full":"1325 Barton St E Hamilton ON L8H 2W2",
    "addr:housenumber":"1325",
    "addr:postcode":"l8h 2w2",
    "addr:street":"Barton St E",
    "iso:country":"CA",
    "sg:address":"1325 Barton St E",
    "sg:city":"Hamilton",
    "sg:classifiers":[
        {
            "category":"Shopping",
            "subcategory":"Computers & Home Electronics",
            "type":"Retail Goods"
        }
    ],
    "sg:phone":"+1 905 549 3581",
    "sg:postcode":"L8H 2W2",
    "sg:province":"ON",
    "sg:tags":[
        "television",
        "burglar",
        "alarm",
        "system"
    ],
    "wof:name":"East Hamilton Radio Ltd",
    "wof:placetype":"venue"
},
  "geometry": {"coordinates":[-79.8057556152,43.2492485046],"type":"Point"}
}