{
  "type": "Feature",
  "properties": {
    "addr:full":"Toronto ON M5J 2N2",
    "addr:postcode":"m5j 2n2",
    "iso:country":"CA",
    "sg:city":"Toronto",
    "sg:classifiers":[
        {
            "category":"Real Estate",
            "subcategory":"Real Estate Operator",
            "type":"Services"
        }
    ],
    "sg:phone":"+1 416 260 9900",
    "sg:postcode":"M5J 2N2",
    "sg:province":"ON",
    "sg:tags":[
        "condominium"
    ],
    "wof:name":"Mtcc 719",
    "wof:placetype":"venue"
},
  "geometry": {"coordinates":[-79.384674,43.639366],"type":"Point"}
}