{
  "type": "Feature",
  "properties": {
    "addr:full":"1256 Commercial Dr Vancouver BC V5L 3X4",
    "addr:housenumber":"1256",
    "addr:postcode":"v5l 3x4",
    "addr:street":"Commercial Dr",
    "iso:country":"CA",
    "sg:address":"1256 Commercial Dr",
    "sg:city":"Vancouver",
    "sg:classifiers":[
        {
            "category":"Shopping",
            "type":"Retail Goods"
        }
    ],
    "sg:phone":"+1 604 251 5056",
    "sg:postcode":"V5L 3X4",
    "sg:province":"BC",
    "sg:tags":[
        "picture",
        "frame"
    ],
    "wof:name":"Artrageous",
    "wof:placetype":"venue"
},
  "geometry": {"coordinates":[-123.069412231,49.2734413147],"type":"Point"}
}