{
  "type": "Feature",
  "properties": {
    "addr:full":"8150 Boul Decarie Montreal QC H4P 2S8",
    "addr:housenumber":"8150",
    "addr:postcode":"h4p 2s8",
    "addr:street":"Boul Decarie",
    "iso:country":"CA",
    "sg:address":"8150 Boul Decarie",
    "sg:city":"Montreal",
    "sg:classifiers":[
        {
            "category":"Home & Garden",
            "subcategory":"Home Furnishings",
            "type":"Retail Goods"
        }
    ],
    "sg:phone":"+1 514 340 5000",
    "sg:postcode":"H4P 2S8",
    "sg:province":"QC",
    "sg:tags":[
        "lighting",
        "fixture"
    ],
    "wof:name":"Eclairage Union Limitee",
    "wof:placetype":"venue"
},
  "geometry": {"coordinates":[-73.6600723267,45.4982376099],"type":"Point"}
}