{
  "type": "Feature",
  "properties": {
    "addr:full":"301 10 St Cold Lake AB T9M 1A5",
    "addr:housenumber":"301 10",
    "addr:postcode":"t9m 1a5",
    "addr:street":"St",
    "iso:country":"CA",
    "sg:address":"301 10 St",
    "sg:city":"Cold Lake",
    "sg:classifiers":[
        {
            "category":"Social Services",
            "subcategory":"Child Care",
            "type":"Services"
        }
    ],
    "sg:phone":"+1 780 639 2925",
    "sg:postcode":"T9M 1A5",
    "sg:province":"AB",
    "sg:tags":[
        "kindergarten",
        "academic",
        "school",
        "montessori"
    ],
    "wof:name":"Kids' Time Out Play Program",
    "wof:placetype":"venue"
},
  "geometry": {"coordinates":[-110.179596,54.469551],"type":"Point"}
}