{
  "type": "Feature",
  "properties": {
    "addr:full":"606 9th St Humboldt SK S0K 2A0",
    "addr:housenumber":"606",
    "addr:postcode":"s0k 2a0",
    "addr:street":"9Th St",
    "iso:country":"CA",
    "sg:address":"606 9th St",
    "sg:city":"Humboldt",
    "sg:classifiers":[
        {
            "category":"Wholesale",
            "subcategory":"Hardware",
            "type":"Manufacturing & Wholesale Goods"
        }
    ],
    "sg:phone":"+1 306 682 2821",
    "sg:postcode":"S0K 2A0",
    "sg:province":"SK",
    "sg:tags":[
        "automobile",
        "parts",
        "supply"
    ],
    "wof:name":"Wheelers",
    "wof:placetype":"venue"
},
  "geometry": {"coordinates":[-105.12429,52.199059],"type":"Point"}
}