{
  "type": "Feature",
  "properties": {
    "addr:full":"255 Hutchings St Winnipeg MB R2X 2R4",
    "addr:housenumber":"255",
    "addr:postcode":"r2x 2r4",
    "addr:street":"Hutchings St",
    "iso:country":"CA",
    "sg:address":"255 Hutchings St",
    "sg:city":"Winnipeg",
    "sg:classifiers":[
        {
            "category":"Manufacturing",
            "subcategory":"Metals",
            "type":"Manufacturing & Wholesale Goods"
        }
    ],
    "sg:phone":"+1 204 633 6122",
    "sg:postcode":"R2X 2R4",
    "sg:province":"MB",
    "sg:tags":[
        "plumbing",
        "fixture",
        "supply"
    ],
    "wof:name":"Fiat Products Ltd",
    "wof:placetype":"venue"
},
  "geometry": {"coordinates":[-97.1800689697,49.9437904358],"type":"Point"}
}