{
  "type": "Feature",
  "properties": {
    "iso:country":"CA",
    "sg:city":"Thunder Bay",
    "sg:classifiers":[
        {
            "category":"Personal",
            "type":"Services"
        }
    ],
    "sg:phone":"+1 807 627 4147",
    "sg:postcode":"P7A 4T6",
    "sg:province":"ON",
    "sg:tags":[
        "therapist",
        "massage"
    ],
    "wof:name":"Marsh, Karen",
    "wof:placetype":"venue"
},
  "geometry": {"coordinates":[-89.2201309204,48.4373016357],"type":"Point"}
}