{
  "type": "Feature",
  "properties": {
    "addr:full":"7933 104 St NW Edmonton AB T6E 4C9",
    "addr:housenumber":"7933",
    "addr:postcode":"t6e 4c9",
    "addr:street":"104 St Nw",
    "iso:country":"CA",
    "sg:address":"7933 104 St NW",
    "sg:city":"Edmonton",
    "sg:classifiers":[
        {
            "category":"Banks & Credit Unions",
            "subcategory":"Bank",
            "type":"Services"
        }
    ],
    "sg:phone":"+1 780 433 4286",
    "sg:postcode":"T6E 4C9",
    "sg:province":"AB",
    "wof:name":"Canadian Western Bank",
    "wof:placetype":"venue"
},
  "geometry": {"coordinates":[-113.497314,53.515533],"type":"Point"}
}