{
  "type": "Feature",
  "properties": {
    "iso:country":"CA",
    "sg:address":"4634 Bowness Rd NW",
    "sg:city":"Calgary",
    "sg:classifiers":[
        {
            "category":"Autos & Motor Vehicles",
            "subcategory":"Automobile Sales",
            "type":"Retail Goods"
        }
    ],
    "sg:phone":"+1 403 247 1247",
    "sg:postcode":"T3B 0B3",
    "sg:province":"AB",
    "sg:tags":[
        "car",
        "dealer"
    ],
    "wof:name":"Cal-A Auto Sales",
    "wof:placetype":"venue"
},
  "geometry": {"coordinates":[-114.15940856900001,51.0720176697],"type":"Point"}
}