{
  "type": "Feature",
  "properties": {
    "addr:full":"678 Rue Du Ruisseau Saint-Bernard QC G0S 2G0",
    "addr:housenumber":"678",
    "addr:postcode":"g0s 2g0",
    "addr:street":"Rue Du Ruisseau",
    "iso:country":"CA",
    "sg:address":"678 Rue Du Ruisseau",
    "sg:city":"Saint-Bernard",
    "sg:classifiers":[
        {
            "category":"Retail",
            "subcategory":"Animal Services",
            "type":"Services"
        }
    ],
    "sg:phone":"+1 418 475 6969",
    "sg:postcode":"G0S 2G0",
    "sg:province":"QC",
    "sg:tags":[
        "pet",
        "cat",
        "dog",
        "kennel"
    ],
    "wof:name":"Chenil Maguire",
    "wof:placetype":"venue"
},
  "geometry": {"coordinates":[-71.1317901611,46.5000839233],"type":"Point"}
}