{
  "type": "Feature",
  "properties": {
    "addr:full":"28 Dublin St Brantford ON N3R 2E2",
    "addr:housenumber":"28",
    "addr:postcode":"n3r 2e2",
    "addr:street":"Dublin St",
    "iso:country":"CA",
    "sg:address":"28 Dublin St",
    "sg:city":"Brantford",
    "sg:classifiers":[
        {
            "category":"Organizations",
            "subcategory":"Religious Organization",
            "type":"Services"
        }
    ],
    "sg:phone":"+1 519 752 4770",
    "sg:postcode":"N3R 2E2",
    "sg:province":"ON",
    "sg:tags":[
        "church"
    ],
    "wof:name":"St James Anglican Church",
    "wof:placetype":"venue"
},
  "geometry": {"coordinates":[-80.26635,43.156754],"type":"Point"}
}