{
  "type": "Feature",
  "properties": {
    "addr:full":"Vancouver BC V6G 2Z6",
    "addr:postcode":"v6g 2z6",
    "iso:country":"CA",
    "sg:city":"Vancouver",
    "sg:classifiers":[
        {
            "category":"Real Estate",
            "subcategory":"Real Estate Agent",
            "type":"Services"
        }
    ],
    "sg:phone":"+1 604 669 3373",
    "sg:postcode":"V6G 2Z6",
    "sg:province":"BC",
    "sg:tags":[
        "environmental",
        "ecological",
        "investment"
    ],
    "wof:name":"Conor Pacific Environmental",
    "wof:placetype":"venue"
},
  "geometry": {"coordinates":[-123.130256653,49.2903213501],"type":"Point"}
}