{
  "type": "Feature",
  "properties": {
    "addr:full":"134 Inglewood Pt SE Calgary AB T2G 5K6",
    "addr:housenumber":"134",
    "addr:postcode":"t2g 5k6",
    "addr:street":"Inglewood Pt Se",
    "iso:country":"CA",
    "sg:address":"134 Inglewood Pt SE",
    "sg:city":"Calgary",
    "sg:classifiers":[
        {
            "category":"Professional",
            "subcategory":"Computer Services",
            "type":"Services"
        }
    ],
    "sg:phone":"+1 403 278 9741",
    "sg:postcode":"T2G 5K6",
    "sg:province":"AB",
    "wof:name":"Xna Telecommunications Inc",
    "wof:placetype":"venue"
},
  "geometry": {"coordinates":[-114.022605896,51.041759491],"type":"Point"}
}