{
  "type": "Feature",
  "properties": {
    "addr:full":"10209 109th St Fairview AB T0H 1L0",
    "addr:housenumber":"10209",
    "addr:postcode":"t0h 1l0",
    "addr:street":"109Th St",
    "iso:country":"CA",
    "sg:address":"10209 109th St",
    "sg:city":"Fairview",
    "sg:classifiers":[
        {
            "category":"Professional",
            "type":"Services"
        }
    ],
    "sg:phone":"+1 780 835 2687",
    "sg:postcode":"T0H 1L0",
    "sg:province":"AB",
    "sg:tags":[
        "geophysical"
    ],
    "wof:name":"Advance Resources Consulting",
    "wof:placetype":"venue"
},
  "geometry": {"coordinates":[-118.38164500000001,56.067631],"type":"Point"}
}