{
  "type": "Feature",
  "properties": {
    "addr:full":"98 Rue DE Ramezay Sorel-Tracy QC J3P 3Z2",
    "addr:housenumber":"98",
    "addr:postcode":"j3p 3z2",
    "addr:street":"Rue De Ramezay",
    "iso:country":"CA",
    "sg:address":"98 Rue DE Ramezay",
    "sg:city":"Sorel-Tracy",
    "sg:classifiers":[
        {
            "category":"Shopping",
            "subcategory":"Clothing, Apparel, & Fashions",
            "type":"Retail Goods"
        }
    ],
    "sg:phone":"+1 450 743 2421",
    "sg:postcode":"J3P 3Z2",
    "sg:province":"QC",
    "sg:tags":[
        "cleaners",
        "dressmaker"
    ],
    "wof:name":"Nettoyeur Sorel",
    "wof:placetype":"venue"
},
  "geometry": {"coordinates":[-73.112633,46.042389],"type":"Point"}
}