{
  "type": "Feature",
  "properties": {
    "addr:full":"308 Brennan Harbour Rd Spanish ON P0P 2A0",
    "addr:housenumber":"308",
    "addr:postcode":"p0p 2a0",
    "addr:street":"Brennan Harbour Rd",
    "iso:country":"CA",
    "sg:address":"308 Brennan Harbour Rd",
    "sg:city":"Spanish",
    "sg:classifiers":[
        {
            "category":"Travel",
            "subcategory":"Hotels & Motels",
            "type":"Entertainment"
        }
    ],
    "sg:phone":"+1 705 844 1136",
    "sg:postcode":"P0P 2A0",
    "sg:province":"ON",
    "sg:tags":[
        "resort"
    ],
    "wof:name":"Brennan Harbour Resort",
    "wof:placetype":"venue"
},
  "geometry": {"coordinates":[-82.33807400000001,46.1931],"type":"Point"}
}