{
  "type": "Feature",
  "properties": {
    "addr:full":"73 Main St S Georgetown ON L7G 3G2",
    "addr:housenumber":"73",
    "addr:postcode":"l7g 3g2",
    "addr:street":"Main St S",
    "iso:country":"CA",
    "sg:address":"73 Main St S",
    "sg:city":"Georgetown",
    "sg:classifiers":[
        {
            "category":"Shopping",
            "type":"Retail Goods"
        }
    ],
    "sg:phone":"+1 905 877 7065",
    "sg:postcode":"L7G 3G2",
    "sg:province":"ON",
    "sg:tags":[
        "supply",
        "craft",
        "art",
        "dealer",
        "gallery"
    ],
    "wof:name":"Artisans Attic",
    "wof:placetype":"venue"
},
  "geometry": {"coordinates":[-79.926147,43.64967],"type":"Point"}
}