{
  "type": "Feature",
  "properties": {
    "addr:full":"4009 Rue Parthenais Montreal QC H2K 3T8",
    "addr:housenumber":"4009",
    "addr:postcode":"h2k 3t8",
    "addr:street":"Rue Parthenais",
    "iso:country":"CA",
    "sg:address":"4009 Rue Parthenais",
    "sg:city":"Montreal",
    "sg:classifiers":[
        {
            "category":"Arts & Performance",
            "subcategory":"Theater",
            "type":"Entertainment"
        }
    ],
    "sg:phone":"+1 514 523 4943",
    "sg:postcode":"H2K 3T8",
    "sg:province":"QC",
    "sg:tags":[
        "music"
    ],
    "wof:name":"Dixieband",
    "wof:placetype":"venue"
},
  "geometry": {"coordinates":[-73.5651855469,45.5338973999],"type":"Point"}
}