{
  "type": "Feature",
  "properties": {
    "addr:full":"134 Brock St Sault Ste Marie ON P6A 3B5",
    "addr:housenumber":"134",
    "addr:postcode":"p6a 3b5",
    "addr:street":"Brock St",
    "iso:country":"CA",
    "sg:address":"134 Brock St",
    "sg:city":"Sault Ste Marie",
    "sg:classifiers":[
        {
            "category":"Organizations",
            "subcategory":"Religious Organization",
            "type":"Services"
        }
    ],
    "sg:phone":"+1 705 254 4801",
    "sg:postcode":"P6A 3B5",
    "sg:province":"ON",
    "sg:tags":[
        "church"
    ],
    "wof:name":"Westminster Presbyterian Chr",
    "wof:placetype":"venue"
},
  "geometry": {"coordinates":[-84.328941,46.509605],"type":"Point"}
}