{
  "type": "Feature",
  "properties": {
    "addr:full":"4522 Manilla Rd SE Calgary AB T2G 4B7",
    "addr:postcode":"4522;t2g 4b7",
    "addr:street":"Manilla Rd Se",
    "iso:country":"CA",
    "sg:address":"4522 Manilla Rd SE",
    "sg:city":"Calgary",
    "sg:phone":"+1 403 287 9596",
    "sg:postcode":"T2G 4B7",
    "sg:province":"AB",
    "sg:tags":[
        "coffee",
        "cappuccino",
        "supply",
        "espresso",
        "break",
        "mach"
    ],
    "wof:name":"Cmr Svc",
    "wof:placetype":"venue"
},
  "geometry": {"coordinates":[-114.051902771,51.01379776],"type":"Point"}
}