{
  "type": "Feature",
  "properties": {
    "addr:full":"1928 Weston Rd York ON M9N 1W2",
    "addr:housenumber":"1928",
    "addr:postcode":"m9n 1w2",
    "addr:street":"Weston Rd",
    "iso:country":"CA",
    "sg:address":"1928 Weston Rd",
    "sg:city":"York",
    "sg:classifiers":[
        {
            "category":"Health Services",
            "subcategory":"Doctor",
            "type":"Services"
        }
    ],
    "sg:phone":"+1 416 247 1928",
    "sg:postcode":"M9N 1W2",
    "sg:province":"ON",
    "sg:tags":[
        "dentist"
    ],
    "wof:name":"Weston Dental Office",
    "wof:placetype":"venue"
},
  "geometry": {"coordinates":[-79.51723480219999,43.7003173828],"type":"Point"}
}