{
  "type": "Feature",
  "properties": {
    "addr:full":"56 King St W Dundas ON L9H 1T8",
    "addr:housenumber":"56",
    "addr:postcode":"l9h 1t8",
    "addr:street":"King St W",
    "iso:country":"CA",
    "sg:address":"56 King St W",
    "sg:city":"Dundas",
    "sg:classifiers":[
        {
            "category":"Shopping",
            "subcategory":"Clothing, Apparel, & Fashions",
            "type":"Retail Goods"
        }
    ],
    "sg:phone":"+1 905 627 7909",
    "sg:postcode":"L9H 1T8",
    "sg:province":"ON",
    "sg:tags":[
        "infant",
        "wear"
    ],
    "wof:name":"Kids N Krafts",
    "wof:placetype":"venue"
},
  "geometry": {"coordinates":[-79.95618399999999,43.26627],"type":"Point"}
}