{
  "type": "Feature",
  "properties": {
    "addr:full":"Edmonton AB T6E 5P3",
    "addr:postcode":"t6e 5p3",
    "iso:country":"CA",
    "sg:city":"Edmonton",
    "sg:classifiers":[
        {
            "category":"Wholesale",
            "subcategory":"Vending Machines",
            "type":"Manufacturing & Wholesale Goods"
        }
    ],
    "sg:phone":"+1 780 435 0005",
    "sg:postcode":"T6E 5P3",
    "sg:province":"AB",
    "wof:name":"Aramark",
    "wof:placetype":"venue"
},
  "geometry": {"coordinates":[-113.483467,53.484997],"type":"Point"}
}