{
  "type": "Feature",
  "properties": {
    "iso:country":"CA",
    "sg:address":"15138 North Bluff Rd",
    "sg:city":"White Rock",
    "sg:classifiers":[
        {
            "category":"Shopping",
            "subcategory":"Photographic Equipment",
            "type":"Retail Goods"
        }
    ],
    "sg:phone":"+1 604 531 8344",
    "sg:postcode":"V4B 3E5",
    "sg:province":"BC",
    "sg:tags":[
        "photo",
        "finishing"
    ],
    "wof:name":"Reid's Foto Source",
    "wof:placetype":"venue"
},
  "geometry": {"coordinates":[-122.802696228,49.0309867859],"type":"Point"}
}