{
  "type": "Feature",
  "properties": {
    "addr:full":"236 North Queen St Etobicoke ON M9C 4Y1",
    "addr:housenumber":"236",
    "addr:postcode":"m9c 4y1",
    "addr:street":"North Queen St",
    "iso:country":"CA",
    "sg:address":"236 North Queen St",
    "sg:city":"Etobicoke",
    "sg:classifiers":[
        {
            "category":"Building & Trades",
            "subcategory":"Plumbing",
            "type":"Services"
        }
    ],
    "sg:phone":"+1 416 621 9991",
    "sg:postcode":"M9C 4Y1",
    "sg:province":"ON",
    "sg:tags":[
        "mechanical",
        "contractor"
    ],
    "wof:name":"Grist Turano & Assoc Mech",
    "wof:placetype":"venue"
},
  "geometry": {"coordinates":[-79.5576477051,43.6173439026],"type":"Point"}
}