{
  "type": "Feature",
  "properties": {
    "iso:country":"CA",
    "sg:address":"765 Rue Bocage",
    "sg:city":"Saint-Jean-Chrysostome",
    "sg:classifiers":[
        {
            "category":"Wholesale",
            "subcategory":"Machinery & Supplies",
            "type":"Manufacturing & Wholesale Goods"
        }
    ],
    "sg:phone":"+1 418 254 2959",
    "sg:postcode":"G6Z 2Z7",
    "sg:province":"QC",
    "sg:tags":[
        "equipment",
        "pile",
        "driving"
    ],
    "wof:name":"Fondations D'Acier Vistech Inc",
    "wof:placetype":"venue"
},
  "geometry": {"coordinates":[-71.2080383301,46.733505249],"type":"Point"}
}