{
  "type": "Feature",
  "properties": {
    "addr:full":"1682 Rue Principale Chambord QC G0W 1G0",
    "addr:housenumber":"1682",
    "addr:postcode":"g0w 1g0",
    "addr:street":"Rue Principale",
    "iso:country":"CA",
    "sg:address":"1682 Rue Principale",
    "sg:city":"Chambord",
    "sg:classifiers":[
        {
            "category":"Shopping",
            "subcategory":"Pharmacy",
            "type":"Retail Goods"
        }
    ],
    "sg:phone":"+1 418 342 6263",
    "sg:postcode":"G0W 1G0",
    "sg:province":"QC",
    "wof:name":"Pharmacie Mona Fortin",
    "wof:placetype":"venue"
},
  "geometry": {"coordinates":[-72.0732803345,48.4324493408],"type":"Point"}
}