{
  "type": "Feature",
  "properties": {
    "addr:full":"4150 Boul DE LA Concorde E Laval QC H7E 2E3",
    "addr:housenumber":"4150",
    "addr:postcode":"h7e 2e3",
    "addr:street":"Boul De La Concorde E",
    "iso:country":"CA",
    "sg:address":"4150 Boul DE LA Concorde E",
    "sg:city":"Laval",
    "sg:classifiers":[
        {
            "category":"Health Services",
            "subcategory":"Chiropractor",
            "type":"Services"
        }
    ],
    "sg:phone":"+1 450 661 2047",
    "sg:postcode":"H7E 2E3",
    "sg:province":"QC",
    "wof:name":"Labrecque, Jacques DC",
    "wof:placetype":"venue"
},
  "geometry": {"coordinates":[-73.65422100000001,45.601788],"type":"Point"}
}