{
  "type": "Feature",
  "properties": {
    "iso:country":"CA",
    "sg:address":"1275 Rymal Rd E",
    "sg:city":"Hamilton",
    "sg:classifiers":[
        {
            "category":"Wholesale",
            "subcategory":"Fruits & Vegetables",
            "type":"Manufacturing & Wholesale Goods"
        }
    ],
    "sg:phone":"+1 905 574 1112",
    "sg:postcode":"L8W 3N1",
    "sg:province":"ON",
    "wof:name":"J & D Foods",
    "wof:placetype":"venue"
},
  "geometry": {"coordinates":[-79.83660888670001,43.1887779236],"type":"Point"}
}