{
  "type": "Feature",
  "properties": {
    "addr:full":"703 Rue DE Lanaudiere Joliette QC J6E 3M9",
    "addr:housenumber":"703",
    "addr:postcode":"j6e 3m9",
    "addr:street":"Rue De Lanaudiere",
    "iso:country":"CA",
    "sg:address":"703 Rue DE Lanaudiere",
    "sg:city":"Joliette",
    "sg:classifiers":[
        {
            "category":"Autos & Motor Vehicles",
            "subcategory":"Fuel & Gas Station",
            "type":"Retail Goods"
        }
    ],
    "sg:phone":"+1 450 756 6080",
    "sg:postcode":"J6E 3M9",
    "sg:province":"QC",
    "sg:tags":[
        "repairing",
        "automobile",
        "oil"
    ],
    "wof:name":"Station DE Svc Brigitte Malo",
    "wof:placetype":"venue"
},
  "geometry": {"coordinates":[-73.4411621094,46.0204849243],"type":"Point"}
}