{
  "type": "Feature",
  "properties": {
    "addr:full":"Daviault Pl Fermont QC G0G 1J0",
    "addr:postcode":"g0g 1j0",
    "addr:street":"Daviault Pl",
    "iso:country":"CA",
    "sg:address":"Daviault Pl",
    "sg:city":"Fermont",
    "sg:classifiers":[
        {
            "category":"Recreation",
            "type":"Entertainment"
        }
    ],
    "sg:phone":"+1 418 287 3612",
    "sg:postcode":"G0G 1J0",
    "sg:province":"QC",
    "sg:tags":[
        "club",
        "curling"
    ],
    "wof:name":"Club Curling Daviault Place",
    "wof:placetype":"venue"
},
  "geometry": {"coordinates":[-67.09191894529999,52.8022956848],"type":"Point"}
}