{
  "type": "Feature",
  "properties": {
    "addr:full":"10671 Argentia Dr Richmond BC V7E 4K6",
    "addr:housenumber":"10671",
    "addr:postcode":"v7e 4k6",
    "addr:street":"Argentia Dr",
    "iso:country":"CA",
    "sg:address":"10671 Argentia Dr",
    "sg:city":"Richmond",
    "sg:classifiers":[
        {
            "category":"Manufacturing",
            "subcategory":"Lumber",
            "type":"Manufacturing & Wholesale Goods"
        }
    ],
    "sg:phone":"+1 604 272 0604",
    "sg:postcode":"V7E 4K6",
    "sg:province":"BC",
    "sg:tags":[
        "forester"
    ],
    "wof:name":"J Hunt & Assoc Inc",
    "wof:placetype":"venue"
},
  "geometry": {"coordinates":[-123.171082,49.136108],"type":"Point"}
}