{
  "type": "Feature",
  "properties": {
    "addr:full":"67 Cote Saint-Gregoire Beauport QC G1C 2X2",
    "addr:housenumber":"67",
    "addr:postcode":"qc g1c 2x2",
    "addr:street":"Cote Saint-Gregoire",
    "iso:country":"CA",
    "sg:address":"67 Cote Saint-Gregoire",
    "sg:city":"Beauport",
    "sg:classifiers":[
        {
            "category":"Health Services",
            "subcategory":"Nursing And Care Facility",
            "type":"Services"
        }
    ],
    "sg:phone":"+1 418 666 3282",
    "sg:postcode":"G1C 2X2",
    "sg:province":"QC",
    "sg:tags":[
        "home",
        "retirement",
        "community"
    ],
    "wof:name":"Residence Le St-Laurent",
    "wof:placetype":"venue"
},
  "geometry": {"coordinates":[-71.15892028810001,46.8804244995],"type":"Point"}
}