{
  "type": "Feature",
  "properties": {
    "addr:full":"Stephenville NL A2N 2E9",
    "addr:postcode":"a2n 2e9",
    "iso:country":"CA",
    "sg:city":"Stephenville",
    "sg:classifiers":[
        {
            "category":"Health Services",
            "subcategory":"Health Practitioner",
            "type":"Services"
        }
    ],
    "sg:phone":"+1 709 643 4666",
    "sg:postcode":"A2N 2E9",
    "sg:province":"NL",
    "sg:tags":[
        "physiotherapist"
    ],
    "wof:name":"Linnick Physiotherapy",
    "wof:placetype":"venue"
},
  "geometry": {"coordinates":[-58.589611,48.554596],"type":"Point"}
}