{
  "type": "Feature",
  "properties": {
    "addr:full":"401 Richmond St W # 399 Toronto ON M5V 3A8",
    "addr:housenumber":"401",
    "addr:postcode":"m5v 3a8",
    "addr:street":"Richmond St W # 399",
    "iso:country":"CA",
    "sg:address":"401 Richmond St W # 399",
    "sg:city":"Toronto",
    "sg:classifiers":[
        {
            "category":"Real Estate",
            "subcategory":"Architect",
            "type":"Services"
        }
    ],
    "sg:phone":"+1 416 260 9692",
    "sg:postcode":"M5V 3A8",
    "sg:province":"ON",
    "sg:tags":[
        "illustrator",
        "architectural"
    ],
    "wof:name":"Q Studio Ltd",
    "wof:placetype":"venue"
},
  "geometry": {"coordinates":[-79.39520263670001,43.6478309631],"type":"Point"}
}