{
  "type": "Feature",
  "properties": {
    "addr:full":"402 Meredith Rd NE Calgary AB T2E 5A6",
    "addr:housenumber":"402",
    "addr:postcode":"t2e 5a6",
    "addr:street":"Meredith Rd Ne",
    "iso:country":"CA",
    "sg:address":"402 Meredith Rd NE",
    "sg:city":"Calgary",
    "sg:classifiers":[
        {
            "category":"Organizations",
            "subcategory":"Religious Organization",
            "type":"Services"
        }
    ],
    "sg:phone":"+1 403 264 3437",
    "sg:postcode":"T2E 5A6",
    "sg:province":"AB",
    "sg:tags":[
        "church"
    ],
    "wof:name":"St Valadimir's Ukrann Orthodox",
    "wof:placetype":"venue"
},
  "geometry": {"coordinates":[-114.053726196,51.0519561768],"type":"Point"}
}