{
  "type": "Feature",
  "properties": {
    "addr:full":"2856 Gottingen St Halifax NS B3K 3E1",
    "addr:housenumber":"2856",
    "addr:postcode":"b3k 3e1",
    "addr:street":"Gottingen St",
    "iso:country":"CA",
    "sg:address":"2856 Gottingen St",
    "sg:city":"Halifax",
    "sg:classifiers":[
        {
            "category":"Retail",
            "subcategory":"Repair Shop",
            "type":"Services"
        }
    ],
    "sg:phone":"+1 902 454 5863",
    "sg:postcode":"B3K 3E1",
    "sg:province":"NS",
    "sg:tags":[
        "lock",
        "locksmith"
    ],
    "wof:name":"B & B Security Locksmithing",
    "wof:placetype":"venue"
},
  "geometry": {"coordinates":[-63.596149,44.660637],"type":"Point"}
}