{
  "type": "Feature",
  "properties": {
    "addr:full":"Montreal QC H2N 2H8",
    "addr:postcode":"h2n 2h8",
    "iso:country":"CA",
    "sg:city":"Montreal",
    "sg:classifiers":[
        {
            "category":"Wholesale",
            "subcategory":"Durable Goods & Equipment",
            "type":"Manufacturing & Wholesale Goods"
        }
    ],
    "sg:phone":"+1 514 389 9090",
    "sg:postcode":"H2N 2H8",
    "sg:province":"QC",
    "sg:tags":[
        "representative",
        "manufacturer"
    ],
    "wof:name":"Group LA Reine Desert",
    "wof:placetype":"venue"
},
  "geometry": {"coordinates":[-73.6481552124,45.549533844],"type":"Point"}
}