{
  "type": "Feature",
  "properties": {
    "addr:full":"703 Queen St Fredericton NB E3B 1C4",
    "addr:housenumber":"703",
    "addr:postcode":"e3b 1c4",
    "addr:street":"Queen St",
    "iso:country":"CA",
    "sg:address":"703 Queen St",
    "sg:city":"Fredericton",
    "sg:classifiers":[
        {
            "category":"Museum",
            "type":"Entertainment"
        }
    ],
    "sg:phone":"+1 506 458 8545",
    "sg:postcode":"E3B 1C4",
    "sg:province":"NB",
    "wof:name":"Beaverbrook Art Gallery",
    "wof:placetype":"venue"
},
  "geometry": {"coordinates":[-66.635994,45.960014],"type":"Point"}
}