{
  "type": "Feature",
  "properties": {
    "addr:full":"Surrey BC V3S 1X7",
    "addr:postcode":"v3s 1x7",
    "iso:country":"CA",
    "sg:city":"Surrey",
    "sg:classifiers":[
        {
            "category":"Home & Garden",
            "subcategory":"Household Appliances",
            "type":"Retail Goods"
        }
    ],
    "sg:phone":"+1 604 599 0458",
    "sg:postcode":"V3S 1X7",
    "sg:province":"BC",
    "sg:tags":[
        "cleaners",
        "vacuum"
    ],
    "wof:name":"Miracle Platinum System Ltd",
    "wof:placetype":"venue"
},
  "geometry": {"coordinates":[-122.81671905499999,49.1189727783],"type":"Point"}
}