{
  "type": "Feature",
  "properties": {
    "addr:full":"302 Chaleur St Charlo NB E8E 2G2",
    "addr:housenumber":"302",
    "addr:postcode":"e8e 2g2",
    "addr:street":"Chaleur St",
    "iso:country":"CA",
    "sg:address":"302 Chaleur St",
    "sg:city":"Charlo",
    "sg:classifiers":[
        {
            "category":"Retail",
            "subcategory":"Repair Shop",
            "type":"Services"
        }
    ],
    "sg:phone":"+1 506 684 5685",
    "sg:postcode":"E8E 2G2",
    "sg:province":"NB",
    "sg:tags":[
        "steel",
        "welding"
    ],
    "wof:name":"Audet Welding Ltd",
    "wof:placetype":"venue"
},
  "geometry": {"coordinates":[-66.334076,48.003368],"type":"Point"}
}