{
  "type": "Feature",
  "properties": {
    "iso:country":"CA",
    "sg:address":"512 Rue Joseph-Bonnet",
    "sg:city":"Saint-Eustache",
    "sg:classifiers":[
        {
            "category":"Wholesale",
            "subcategory":"Machinery & Supplies",
            "type":"Manufacturing & Wholesale Goods"
        }
    ],
    "sg:phone":"+1 450 623 6307",
    "sg:postcode":"J7R 5E1",
    "sg:province":"QC",
    "sg:tags":[
        "machine",
        "tool"
    ],
    "wof:name":"Services Mecaniques Simat",
    "wof:placetype":"venue"
},
  "geometry": {"coordinates":[-73.92692565919999,45.5682792664],"type":"Point"}
}