{
  "type": "Feature",
  "properties": {
    "addr:full":"3170 Vialoux Dr Winnipeg MB R3R 2G9",
    "addr:postcode":"3170;r3r 2g9",
    "addr:street":"Vialoux Dr",
    "iso:country":"CA",
    "sg:address":"3170 Vialoux Dr",
    "sg:city":"Winnipeg",
    "sg:classifiers":[
        {
            "category":"Personal",
            "type":"Services"
        }
    ],
    "sg:phone":"+1 204 832 3025",
    "sg:postcode":"R3R 2G9",
    "sg:province":"MB",
    "sg:tags":[
        "miscellaneous"
    ],
    "wof:name":"Moreau Institute",
    "wof:placetype":"venue"
},
  "geometry": {"coordinates":[-97.253799,49.871719],"type":"Point"}
}