{
  "type": "Feature",
  "properties": {
    "addr:full":"555 Southdale Rd E # 101 London ON N6E 1A2",
    "addr:housenumber":"555",
    "addr:postcode":"n6e 1a2",
    "addr:street":"Southdale Rd E # 101",
    "iso:country":"CA",
    "sg:address":"555 Southdale Rd E # 101",
    "sg:city":"London",
    "sg:classifiers":[
        {
            "category":"Communications",
            "subcategory":"Film & Video Production",
            "type":"Services"
        }
    ],
    "sg:phone":"+1 519 668 7120",
    "sg:postcode":"N6E 1A2",
    "sg:province":"ON",
    "sg:tags":[
        "taping"
    ],
    "wof:name":"Peel Productions",
    "wof:placetype":"venue"
},
  "geometry": {"coordinates":[-81.2342834473,42.9425926208],"type":"Point"}
}