{
  "type": "Feature",
  "properties": {
    "addr:full":"2810 Lanyon Rd Courtenay BC V9N 9N5",
    "addr:housenumber":"2810",
    "addr:postcode":"v9n 9n5",
    "addr:street":"Lanyon Rd",
    "iso:country":"CA",
    "sg:address":"2810 Lanyon Rd",
    "sg:city":"Courtenay",
    "sg:classifiers":[
        {
            "category":"Building & Trades",
            "subcategory":"Construction",
            "type":"Services"
        }
    ],
    "sg:phone":"+1 250 338 9382",
    "sg:postcode":"V9N 9N5",
    "sg:province":"BC",
    "sg:tags":[
        "general",
        "contractor"
    ],
    "wof:name":"CO-Val Plastering & Stucco",
    "wof:placetype":"venue"
},
  "geometry": {"coordinates":[-124.99314099999999,49.686722],"type":"Point"}
}