{
  "type": "Feature",
  "properties": {
    "addr:full":"581 Argus Rd Oakville ON L6J 3J4",
    "addr:housenumber":"581",
    "addr:postcode":"l6j 3j4",
    "addr:street":"Argus Rd",
    "iso:country":"CA",
    "sg:address":"581 Argus Rd",
    "sg:city":"Oakville",
    "sg:classifiers":[
        {
            "category":"Health Services",
            "subcategory":"Health Practitioner",
            "type":"Services"
        }
    ],
    "sg:phone":"+1 905 844 8425",
    "sg:postcode":"L6J 3J4",
    "sg:province":"ON",
    "sg:tags":[
        "physiotherapist"
    ],
    "wof:name":"Physical Edge Physiotherapy",
    "wof:placetype":"venue"
},
  "geometry": {"coordinates":[-79.68482208250001,43.4577445984],"type":"Point"}
}