{
  "type": "Feature",
  "properties": {
    "addr:full":"Abbotsford BC V2S 6Z3",
    "addr:postcode":"v2s 6z3",
    "iso:country":"CA",
    "sg:city":"Abbotsford",
    "sg:classifiers":[
        {
            "category":"Real Estate",
            "subcategory":"Real Estate Operator",
            "type":"Services"
        }
    ],
    "sg:phone":"+1 604 556 7742",
    "sg:postcode":"V2S 6Z3",
    "sg:province":"BC",
    "sg:tags":[
        "apartment"
    ],
    "wof:name":"Bantview Gardens",
    "wof:placetype":"venue"
},
  "geometry": {"coordinates":[-122.29961395300001,49.0483322144],"type":"Point"}
}