{
  "type": "Feature",
  "properties": {
    "addr:full":"3315 14th Ave Markham ON L3R 0H3",
    "addr:housenumber":"3315",
    "addr:postcode":"l3r 0h3",
    "addr:street":"14Th Ave",
    "iso:country":"CA",
    "sg:address":"3315 14th Ave",
    "sg:city":"Markham",
    "sg:classifiers":[
        {
            "category":"Home & Garden",
            "subcategory":"Furniture",
            "type":"Retail Goods"
        }
    ],
    "sg:phone":"+1 905 307 9667",
    "sg:postcode":"L3R 0H3",
    "sg:province":"ON",
    "sg:tags":[
        "maker",
        "cabinet"
    ],
    "wof:name":"Bay-Gis Cabinet Ltd",
    "wof:placetype":"venue"
},
  "geometry": {"coordinates":[-79.342865,43.833965],"type":"Point"}
}