{
  "type": "Feature",
  "properties": {
    "addr:full":"2404 Kingston Rd Scarborough ON M1N 1V2",
    "addr:housenumber":"2404",
    "addr:postcode":"m1n 1v2",
    "addr:street":"Kingston Rd",
    "iso:country":"CA",
    "sg:address":"2404 Kingston Rd",
    "sg:city":"Scarborough",
    "sg:classifiers":[
        {
            "category":"Manufacturing",
            "subcategory":"Printing",
            "type":"Manufacturing & Wholesale Goods"
        }
    ],
    "sg:phone":"+1 416 267 1510",
    "sg:postcode":"M1N 1V2",
    "sg:province":"ON",
    "sg:tags":[
        "printer"
    ],
    "wof:name":"K & L Stat Office Svc",
    "wof:placetype":"venue"
},
  "geometry": {"coordinates":[-79.250389,43.708218],"type":"Point"}
}