{
  "type": "Feature",
  "properties": {
    "addr:full":"106 Garden Ave Richmond Hill ON L4C 6M1",
    "addr:housenumber":"106",
    "addr:postcode":"l4c 6m1",
    "addr:street":"Garden Ave",
    "iso:country":"CA",
    "sg:address":"106 Garden Ave",
    "sg:city":"Richmond Hill",
    "sg:classifiers":[
        {
            "category":"Education",
            "subcategory":"School",
            "type":"Public Place"
        }
    ],
    "sg:phone":"+1 905 889 6266",
    "sg:postcode":"L4C 6M1",
    "sg:province":"ON",
    "wof:name":"Langstaff Secondary School",
    "wof:placetype":"venue"
},
  "geometry": {"coordinates":[-79.439407,43.837368],"type":"Point"}
}