{
  "type": "Feature",
  "properties": {
    "addr:full":"Rankin Inlet NU X0C 0G0",
    "addr:postcode":"x0c 0g0",
    "iso:country":"CA",
    "sg:city":"Rankin Inlet",
    "sg:classifiers":[
        {
            "category":"Banks & Credit Unions",
            "subcategory":"Bank",
            "type":"Services"
        }
    ],
    "sg:phone":"+1 867 645 3260",
    "sg:postcode":"X0C 0G0",
    "sg:province":"NU",
    "wof:name":"Royal Bank Financial Group",
    "wof:placetype":"venue"
},
  "geometry": {"coordinates":[-92.08335113530001,62.807144165],"type":"Point"}
}