{
  "type": "Feature",
  "properties": {
    "addr:full":"Hamilton ON L8N 2C3",
    "addr:postcode":"l8n 2c3",
    "iso:country":"CA",
    "sg:city":"Hamilton",
    "sg:classifiers":[
        {
            "category":"Education",
            "subcategory":"Vocational School",
            "type":"Public Place"
        }
    ],
    "sg:phone":"+1 905 529 4507",
    "sg:postcode":"L8N 2C3",
    "sg:province":"ON",
    "sg:tags":[
        "nurse"
    ],
    "wof:name":"Hamilton Institute For Health",
    "wof:placetype":"venue"
},
  "geometry": {"coordinates":[-79.8679733276,43.2524261475],"type":"Point"}
}