{
  "type": "Feature",
  "properties": {
    "iso:country":"CA",
    "sg:address":"1714 Echo Point Crt",
    "sg:city":"Pickering",
    "sg:classifiers":[
        {
            "category":"Building & Trades",
            "subcategory":"Landscaping Services",
            "type":"Services"
        }
    ],
    "sg:phone":"+1 905 420 9276",
    "sg:postcode":"L1V 5C9",
    "sg:province":"ON",
    "sg:tags":[
        "lawn",
        "maintenance",
        "grounds"
    ],
    "wof:name":"Bob's Weed Spray",
    "wof:placetype":"venue"
},
  "geometry": {"coordinates":[-79.10503387449999,43.8360061646],"type":"Point"}
}