{
  "type": "Feature",
  "properties": {
    "iso:country":"CA",
    "sg:city":"Calgary",
    "sg:classifiers":[
        {
            "category":"Food & Beverages",
            "subcategory":"Liquor & Beverages",
            "type":"Retail Goods"
        }
    ],
    "sg:phone":"+1 403 230 5062",
    "sg:postcode":"T2E 2V4",
    "sg:province":"AB",
    "sg:tags":[
        "store"
    ],
    "wof:name":"Bombay Liquor Store",
    "wof:placetype":"venue"
},
  "geometry": {"coordinates":[-114.062362671,51.0753517151],"type":"Point"}
}