{
  "type": "Feature",
  "properties": {
    "iso:country":"CA",
    "sg:address":"10813 182 St NW",
    "sg:city":"Edmonton",
    "sg:classifiers":[
        {
            "category":"Retail",
            "subcategory":"Auto Repair",
            "type":"Services"
        }
    ],
    "sg:phone":"+1 780 489 1499",
    "sg:postcode":"T5S 1J5",
    "sg:province":"AB",
    "sg:tags":[
        "transmission"
    ],
    "wof:name":"Torque Converter Industries",
    "wof:placetype":"venue"
},
  "geometry": {"coordinates":[-113.63587951700001,53.5547599792],"type":"Point"}
}