{
  "type": "Feature",
  "properties": {
    "iso:country":"CA",
    "sg:city":"Barrie",
    "sg:classifiers":[
        {
            "category":"Organizations",
            "subcategory":"Professional Association",
            "type":"Services"
        }
    ],
    "sg:phone":"+1 705 733 7759",
    "sg:postcode":"L4M 5K3",
    "sg:province":"ON",
    "wof:name":"Lung Association",
    "wof:placetype":"venue"
},
  "geometry": {"coordinates":[-79.6827011108,44.4096412659],"type":"Point"}
}