{
  "type": "Feature",
  "properties": {
    "addr:full":"9010 Av Andre-Grasset Montreal QC H2M 2B3",
    "addr:housenumber":"9010",
    "addr:postcode":"h2m 2b3",
    "addr:street":"Av Andre-Grasset",
    "iso:country":"CA",
    "sg:address":"9010 Av Andre-Grasset",
    "sg:city":"Montreal",
    "sg:classifiers":[
        {
            "category":"Social Services",
            "subcategory":"Child Care",
            "type":"Services"
        }
    ],
    "sg:phone":"+1 514 381 5142",
    "sg:postcode":"H2M 2B3",
    "sg:province":"QC",
    "wof:name":"Garderie Cherie Des Petits",
    "wof:placetype":"venue"
},
  "geometry": {"coordinates":[-73.63859558110001,45.5583381653],"type":"Point"}
}