{
  "type": "Feature",
  "properties": {
    "addr:full":"Rock Forest QC J1N 2S6",
    "addr:postcode":"j1n 2s6",
    "iso:country":"CA",
    "sg:city":"Rock Forest",
    "sg:classifiers":[
        {
            "category":"Manufacturing",
            "subcategory":"Paper Products",
            "type":"Manufacturing & Wholesale Goods"
        }
    ],
    "sg:phone":"+1 819 864 7234",
    "sg:postcode":"J1N 2S6",
    "sg:province":"QC",
    "sg:tags":[
        "pulp"
    ],
    "wof:name":"Lippert Pintlepin Mfg Inc",
    "wof:placetype":"venue"
},
  "geometry": {"coordinates":[-71.989029,45.350735],"type":"Point"}
}