{
  "type": "Feature",
  "properties": {
    "addr:full":"759 Barrydowne Rd Sudbury ON P3A 3T6",
    "addr:housenumber":"759",
    "addr:postcode":"p3a 3t6",
    "addr:street":"Barrydowne Rd",
    "iso:country":"CA",
    "sg:address":"759 Barrydowne Rd",
    "sg:city":"Sudbury",
    "sg:classifiers":[
        {
            "category":"Retail",
            "subcategory":"Laundry & Dry Cleaning",
            "type":"Services"
        }
    ],
    "sg:phone":"+1 705 566 3550",
    "sg:postcode":"P3A 3T6",
    "sg:province":"ON",
    "sg:tags":[
        "cleaners"
    ],
    "wof:name":"Uptown Cleaners Ltd",
    "wof:placetype":"venue"
},
  "geometry": {"coordinates":[-80.94435900000001,46.513313],"type":"Point"}
}