{
  "type": "Feature",
  "properties": {
    "addr:full":"2167 Pitt St Cornwall ON K6K 1A1",
    "addr:housenumber":"2167",
    "addr:postcode":"k6k 1a1",
    "addr:street":"Pitt St",
    "iso:country":"CA",
    "sg:address":"2167 Pitt St",
    "sg:city":"Cornwall",
    "sg:classifiers":[
        {
            "category":"Wholesale",
            "subcategory":"Machinery & Supplies",
            "type":"Manufacturing & Wholesale Goods"
        }
    ],
    "sg:phone":"+1 613 938 2740",
    "sg:postcode":"K6K 1A1",
    "sg:province":"ON",
    "sg:tags":[
        "equipment",
        "welding"
    ],
    "wof:name":"Mc D's Auto & Carpentry Supls",
    "wof:placetype":"venue"
},
  "geometry": {"coordinates":[-74.757385,45.054508],"type":"Point"}
}