{
  "type": "Feature",
  "properties": {
    "iso:country":"CA",
    "sg:address":"216 Railway Ave E",
    "sg:city":"Kindersley",
    "sg:classifiers":[
        {
            "category":"Retail",
            "subcategory":"Repair Shop",
            "type":"Services"
        }
    ],
    "sg:phone":"+1 306 463 2709",
    "sg:postcode":"S0L 1S0",
    "sg:province":"SK",
    "sg:tags":[
        "lock",
        "locksmith"
    ],
    "wof:name":"John Veller Maintenance Svc",
    "wof:placetype":"venue"
},
  "geometry": {"coordinates":[-109.165313721,51.4589080811],"type":"Point"}
}