{
  "type": "Feature",
  "properties": {
    "addr:full":"241 Rue Dupont L'Ile-Bizard QC H9C 1M3",
    "addr:housenumber":"241",
    "addr:postcode":"h9c 1m3",
    "addr:street":"Rue Dupont",
    "iso:country":"CA",
    "sg:address":"241 Rue Dupont",
    "sg:city":"L'Ile-Bizard",
    "sg:classifiers":[
        {
            "category":"Home & Garden",
            "subcategory":"Garden Supply",
            "type":"Retail Goods"
        }
    ],
    "sg:phone":"+1 514 626 5053",
    "sg:postcode":"H9C 1M3",
    "sg:province":"QC",
    "sg:tags":[
        "lawn",
        "mower"
    ],
    "wof:name":"Brunet Marine Enrg",
    "wof:placetype":"venue"
},
  "geometry": {"coordinates":[-73.87243700000001,45.488056],"type":"Point"}
}