{
  "type": "Feature",
  "properties": {
    "addr:full":"19 Yerxa Lane Keswick NB E6L 1N7",
    "addr:housenumber":"19",
    "addr:postcode":"e6l 1n7",
    "addr:street":"Yerxa Lane",
    "iso:country":"CA",
    "sg:address":"19 Yerxa Lane",
    "sg:city":"Keswick",
    "sg:classifiers":[
        {
            "category":"Building & Trades",
            "subcategory":"Construction",
            "type":"Services"
        }
    ],
    "sg:phone":"+1 506 363 1080",
    "sg:postcode":"E6L 1N7",
    "sg:province":"NB",
    "sg:tags":[
        "maker",
        "cabinet"
    ],
    "wof:name":"Oak Ridge Mfg Inc",
    "wof:placetype":"venue"
},
  "geometry": {"coordinates":[-66.829346,45.997547],"type":"Point"}
}