{
  "type": "Feature",
  "properties": {
    "iso:country":"CA",
    "sg:address":"5020 49 Ave",
    "sg:city":"Barrhead",
    "sg:classifiers":[
        {
            "category":"Food & Beverages",
            "subcategory":"Groceries & Convenience Stores",
            "type":"Retail Goods"
        }
    ],
    "sg:phone":"+1 780 674 2011",
    "sg:postcode":"T7N 1G4",
    "sg:province":"AB",
    "sg:tags":[
        "grocer"
    ],
    "wof:name":"Barrhead Iga",
    "wof:placetype":"venue"
},
  "geometry": {"coordinates":[-114.406700134,54.1179275513],"type":"Point"}
}