{
  "type": "Feature",
  "properties": {
    "addr:full":"Terrace BC V8G 4R9",
    "addr:postcode":"v8g 4r9",
    "iso:country":"CA",
    "sg:city":"Terrace",
    "sg:classifiers":[
        {
            "category":"Shopping",
            "subcategory":"Jewelry",
            "type":"Retail Goods"
        }
    ],
    "sg:phone":"+1 250 635 9000",
    "sg:postcode":"V8G 4R9",
    "sg:province":"BC",
    "sg:tags":[
        "jeweler"
    ],
    "wof:name":"Carters Jewellers Ltd",
    "wof:placetype":"venue"
},
  "geometry": {"coordinates":[-128.595505,54.516933],"type":"Point"}
}