{
  "type": "Feature",
  "properties": {
    "iso:country":"CA",
    "sg:city":"Rock Creek",
    "sg:classifiers":[
        {
            "category":"Manufacturing",
            "subcategory":"Lumber",
            "type":"Manufacturing & Wholesale Goods"
        }
    ],
    "sg:phone":"+1 250 446 2788",
    "sg:postcode":"V0H 1Y0",
    "sg:province":"BC",
    "sg:tags":[
        "company",
        "logging"
    ],
    "wof:name":"Christian Valley Svc",
    "wof:placetype":"venue"
},
  "geometry": {"coordinates":[-118.99773407000001,49.0561141968],"type":"Point"}
}