{
  "type": "Feature",
  "properties": {
    "addr:full":"7370 5th St Grand Forks BC V0H 1H0",
    "addr:housenumber":"7370",
    "addr:postcode":"v0h 1h0",
    "addr:street":"5Th St",
    "iso:country":"CA",
    "sg:address":"7370 5th St",
    "sg:city":"Grand Forks",
    "sg:classifiers":[
        {
            "category":"Museum",
            "type":"Entertainment"
        }
    ],
    "sg:phone":"+1 250 442 3737",
    "sg:postcode":"V0H 1H0",
    "sg:province":"BC",
    "wof:name":"Boundary Museum",
    "wof:placetype":"venue"
},
  "geometry": {"coordinates":[-118.440971,49.032642],"type":"Point"}
}