{
  "type": "Feature",
  "properties": {
    "addr:full":"1260 Dundas St London ON N5W 5P2",
    "addr:housenumber":"1260",
    "addr:postcode":"n5w 5p2",
    "addr:street":"Dundas St",
    "iso:country":"CA",
    "sg:address":"1260 Dundas St",
    "sg:city":"London",
    "sg:classifiers":[
        {
            "category":"Education",
            "subcategory":"School",
            "type":"Public Place"
        }
    ],
    "sg:phone":"+1 519 659 8174",
    "sg:postcode":"N5W 5P2",
    "sg:province":"ON",
    "wof:name":"Academie DE LA Tamise",
    "wof:placetype":"venue"
},
  "geometry": {"coordinates":[-81.205947876,42.9963569641],"type":"Point"}
}