{
  "type": "Feature",
  "properties": {
    "addr:full":"12089 Ormond Rd Winchester ON K0C 2K0",
    "addr:housenumber":"12089",
    "addr:postcode":"k0c 2k0",
    "addr:street":"Ormond Rd",
    "iso:country":"CA",
    "sg:address":"12089 Ormond Rd",
    "sg:city":"Winchester",
    "sg:classifiers":[
        {
            "category":"Retail",
            "subcategory":"Animal Services",
            "type":"Services"
        }
    ],
    "sg:phone":"+1 613 774 3091",
    "sg:postcode":"K0C 2K0",
    "sg:province":"ON",
    "sg:tags":[
        "pet",
        "boarding",
        "grooming",
        "washing",
        "sitting"
    ],
    "wof:name":"Shaynedoro Perm Reg'd Kennels",
    "wof:placetype":"venue"
},
  "geometry": {"coordinates":[-75.41027069090001,45.1433868408],"type":"Point"}
}