{
  "type": "Feature",
  "properties": {
    "addr:full":"Laval QC H7E 4W4",
    "addr:postcode":"h7e 4w4",
    "iso:country":"CA",
    "sg:city":"Laval",
    "sg:classifiers":[
        {
            "category":"Professional",
            "subcategory":"Business Services",
            "type":"Services"
        }
    ],
    "sg:phone":"+1 450 661 8579",
    "sg:postcode":"H7E 4W4",
    "sg:province":"QC",
    "sg:tags":[
        "notary"
    ],
    "wof:name":"Palazzo, Jean-Marc",
    "wof:placetype":"venue"
},
  "geometry": {"coordinates":[-73.667801,45.592995],"type":"Point"}
}