{
  "type": "Feature",
  "properties": {
    "addr:full":"283 Boul LA Salle #6 Baie-Comeau QC G4Z 1T2",
    "addr:housenumber":"283",
    "addr:postcode":"g4z 1t2",
    "addr:street":"Boul La Salle # 6 Baie-Comeau",
    "iso:country":"CA",
    "sg:address":"283 Boul LA Salle #6",
    "sg:city":"Baie-Comeau",
    "sg:classifiers":[
        {
            "category":"Professional",
            "subcategory":"Lawyer & Legal Services",
            "type":"Services"
        }
    ],
    "sg:phone":"+1 418 294 8793",
    "sg:postcode":"G4Z 1T2",
    "sg:province":"QC",
    "sg:tags":[
        "attorney"
    ],
    "wof:name":"Bibeau, Lise",
    "wof:placetype":"venue"
},
  "geometry": {"coordinates":[-68.1866989136,49.2141342163],"type":"Point"}
}