{
  "type": "Feature",
  "properties": {
    "addr:full":"2626 Mountain Hwy North Vancouver BC V7J 2N5",
    "addr:housenumber":"2626",
    "addr:postcode":"v7j 2n5",
    "addr:street":"Mountain Hwy",
    "iso:country":"CA",
    "sg:address":"2626 Mountain Hwy",
    "sg:city":"North Vancouver",
    "sg:classifiers":[
        {
            "category":"Organizations",
            "subcategory":"Religious Organization",
            "type":"Services"
        }
    ],
    "sg:phone":"+1 604 988 9214",
    "sg:postcode":"V7J 2N5",
    "sg:province":"BC",
    "sg:tags":[
        "church"
    ],
    "wof:name":"Jehovah's Witnesses",
    "wof:placetype":"venue"
},
  "geometry": {"coordinates":[-123.037727,49.332615],"type":"Point"}
}