{
  "type": "Feature",
  "properties": {
    "iso:country":"CA",
    "sg:address":"128 Main St",
    "sg:city":"Stephenville",
    "sg:classifiers":[
        {
            "category":"Bars & Pubs",
            "type":"Food & Drink"
        }
    ],
    "sg:phone":"+1 709 643 3619",
    "sg:postcode":"A2N 1J3",
    "sg:province":"NL",
    "sg:tags":[
        "lounge",
        "cocktail"
    ],
    "wof:name":"Brown Derby Lounge",
    "wof:placetype":"venue"
},
  "geometry": {"coordinates":[-58.5790367126,48.5486602783],"type":"Point"}
}