{
  "type": "Feature",
  "properties": {
    "addr:full":"30 Bluebell Cres Moose Jaw SK S6J 1A2",
    "addr:housenumber":"30",
    "addr:postcode":"s6j 1a2",
    "addr:street":"Bluebell Cres",
    "iso:country":"CA",
    "sg:address":"30 Bluebell Cres",
    "sg:city":"Moose Jaw",
    "sg:classifiers":[
        {
            "category":"Building & Trades",
            "subcategory":"Plumbing",
            "type":"Services"
        }
    ],
    "sg:phone":"+1 306 693 9420",
    "sg:postcode":"S6J 1A2",
    "sg:province":"SK",
    "sg:tags":[
        "contractor"
    ],
    "wof:name":"Berg Services",
    "wof:placetype":"venue"
},
  "geometry": {"coordinates":[-105.54682200000001,50.41544],"type":"Point"}
}