{
  "type": "Feature",
  "properties": {
    "iso:country":"CA",
    "sg:address":"5862 Boul Des Rossignols",
    "sg:city":"Laval",
    "sg:classifiers":[
        {
            "category":"Freight",
            "type":"Transportation"
        }
    ],
    "sg:phone":"+1 450 963 9770",
    "sg:postcode":"H7L 4Z2",
    "sg:province":"QC",
    "sg:tags":[
        "consultant"
    ],
    "wof:name":"Transport & Dist J-M Thibodeau",
    "wof:placetype":"venue"
},
  "geometry": {"coordinates":[-73.772377,45.590946],"type":"Point"}
}