{
  "type": "Feature",
  "properties": {
    "addr:full":"3851 22nd Ave Prince George BC V2N 1B5",
    "addr:housenumber":"3851",
    "addr:postcode":"v2n 1b5",
    "addr:street":"22Nd Ave",
    "iso:country":"CA",
    "sg:address":"3851 22nd Ave",
    "sg:city":"Prince George",
    "sg:classifiers":[
        {
            "category":"Freight",
            "type":"Transportation"
        }
    ],
    "sg:phone":"+1 250 561 7209",
    "sg:postcode":"V2N 1B5",
    "sg:province":"BC",
    "sg:tags":[
        "courier"
    ],
    "wof:name":"Canpar Transport Ltd",
    "wof:placetype":"venue"
},
  "geometry": {"coordinates":[-122.79085499999999,53.903412],"type":"Point"}
}