{
  "type": "Feature",
  "properties": {
    "addr:full":"Surrey BC V4P 1P1",
    "addr:postcode":"v4p 1p1",
    "iso:country":"CA",
    "sg:city":"Surrey",
    "sg:classifiers":[
        {
            "category":"Social Services",
            "type":"Services"
        }
    ],
    "sg:phone":"+1 604 542 3040",
    "sg:postcode":"V4P 1P1",
    "sg:province":"BC",
    "sg:tags":[
        "psychologist",
        "counselor",
        "marriage",
        "family"
    ],
    "wof:name":"Christoph Psychological Svc",
    "wof:placetype":"venue"
},
  "geometry": {"coordinates":[-122.806533813,49.0526885986],"type":"Point"}
}