{
  "type": "Feature",
  "properties": {
    "addr:full":"Jonquiere QC G7S 4S4",
    "addr:postcode":"g7s 4s4",
    "iso:country":"CA",
    "sg:city":"Jonquiere",
    "sg:classifiers":[
        {
            "category":"Wholesale",
            "subcategory":"Metals & Minerals",
            "type":"Manufacturing & Wholesale Goods"
        }
    ],
    "sg:phone":"+1 418 548 3103",
    "sg:postcode":"G7S 4S4",
    "sg:province":"QC",
    "sg:tags":[
        "steel",
        "warehouse"
    ],
    "wof:name":"Metaux Russel Inc",
    "wof:placetype":"venue"
},
  "geometry": {"coordinates":[-71.162598,48.405003],"type":"Point"}
}