{
  "type": "Feature",
  "properties": {
    "addr:full":"633 14 St SW Medicine Hat AB T1A 4V5",
    "addr:housenumber":"14",
    "addr:postcode":"t1a 4v5",
    "addr:street":"633;St Sw",
    "iso:country":"CA",
    "sg:address":"633 14 St SW",
    "sg:city":"Medicine Hat",
    "sg:classifiers":[
        {
            "category":"Travel",
            "subcategory":"Hotels & Motels",
            "type":"Entertainment"
        }
    ],
    "sg:phone":"+1 403 527 4421",
    "sg:postcode":"T1A 4V5",
    "sg:province":"AB",
    "wof:name":"Bel-Aire Motel",
    "wof:placetype":"venue"
},
  "geometry": {"coordinates":[-110.70158386200001,50.0260276794],"type":"Point"}
}