{
  "type": "Feature",
  "properties": {
    "addr:full":"135 Columbia St E New Westminster BC V3L 3V9",
    "addr:housenumber":"135",
    "addr:postcode":"v3l 3v9",
    "addr:street":"Columbia St E",
    "iso:country":"CA",
    "sg:address":"135 Columbia St E",
    "sg:city":"New Westminster",
    "sg:classifiers":[
        {
            "category":"Health Services",
            "subcategory":"Medical Lab",
            "type":"Services"
        }
    ],
    "sg:phone":"+1 604 526 6033",
    "sg:postcode":"V3L 3V9",
    "sg:province":"BC",
    "wof:name":"Anderson Denture Clinics",
    "wof:placetype":"venue"
},
  "geometry": {"coordinates":[-122.893127441,49.2221794128],"type":"Point"}
}