{
  "type": "Feature",
  "properties": {
    "addr:full":"15520 Yonge St Aurora ON L4G 1P2",
    "addr:housenumber":"15520",
    "addr:postcode":"l4g 1p2",
    "addr:street":"Yonge St",
    "iso:country":"CA",
    "sg:address":"15520 Yonge St",
    "sg:city":"Aurora",
    "sg:classifiers":[
        {
            "category":"Personal",
            "type":"Services"
        }
    ],
    "sg:phone":"+1 905 841 6722",
    "sg:postcode":"L4G 1P2",
    "sg:province":"ON",
    "sg:tags":[
        "program",
        "physical",
        "exercise",
        "fitness"
    ],
    "wof:name":"Fit Pro",
    "wof:placetype":"venue"
},
  "geometry": {"coordinates":[-79.46932200000001,44.006165],"type":"Point"}
}