{
  "type": "Feature",
  "properties": {
    "addr:full":"519 Prairie Ave Sedley SK S0G 4K0",
    "addr:housenumber":"519",
    "addr:postcode":"s0g 4k0",
    "addr:street":"Prairie Ave",
    "iso:country":"CA",
    "sg:address":"519 Prairie Ave",
    "sg:city":"Sedley",
    "sg:classifiers":[
        {
            "category":"Education",
            "subcategory":"School",
            "type":"Public Place"
        }
    ],
    "sg:phone":"+1 306 885 2122",
    "sg:postcode":"S0G 4K0",
    "sg:province":"SK",
    "wof:name":"Sedley School",
    "wof:placetype":"venue"
},
  "geometry": {"coordinates":[-104.01288604699999,50.170249939],"type":"Point"}
}