{
  "type": "Feature",
  "properties": {
    "iso:country":"CA",
    "sg:address":"837 Albion Rd",
    "sg:city":"Etobicoke",
    "sg:classifiers":[
        {
            "category":"Personal",
            "subcategory":"Beauty Salon",
            "type":"Services"
        }
    ],
    "sg:phone":"+1 416 741 6602",
    "sg:postcode":"M9V 1A3",
    "sg:province":"ON",
    "wof:name":"Paulette's Hair Clinic",
    "wof:placetype":"venue"
},
  "geometry": {"coordinates":[-79.55950927729999,43.7344284058],"type":"Point"}
}