{
  "type": "Feature",
  "properties": {
    "addr:full":"145 Roland Michener Dr # Y4 Kanata ON K2T 1G7",
    "addr:housenumber":"145",
    "addr:postcode":"k2t 1g7",
    "addr:street":"Roland Michener Dr # Y4",
    "iso:country":"CA",
    "sg:address":"145 Roland Michener Dr # Y4",
    "sg:city":"Kanata",
    "sg:classifiers":[
        {
            "category":"Home & Garden",
            "subcategory":"Furniture",
            "type":"Retail Goods"
        }
    ],
    "sg:phone":"+1 613 271 7045",
    "sg:postcode":"K2T 1G7",
    "sg:province":"ON",
    "sg:tags":[
        "mattress"
    ],
    "wof:name":"Sleep Country Canada Inc",
    "wof:placetype":"venue"
},
  "geometry": {"coordinates":[-75.9128036499,45.3084831238],"type":"Point"}
}