{
  "type": "Feature",
  "properties": {
    "addr:full":"304 William St Warren MB R0C 3E0",
    "addr:housenumber":"304",
    "addr:postcode":"r0c 3e0",
    "addr:street":"William St",
    "iso:country":"CA",
    "sg:address":"304 William St",
    "sg:city":"Warren",
    "sg:classifiers":[
        {
            "category":"Freight",
            "type":"Transportation"
        }
    ],
    "sg:phone":"+1 204 322 5630",
    "sg:postcode":"R0C 3E0",
    "sg:province":"MB",
    "sg:tags":[
        "trucking"
    ],
    "wof:name":"Warren/Stonewall Freight",
    "wof:placetype":"venue"
},
  "geometry": {"coordinates":[-97.551384,50.133789],"type":"Point"}
}