{
  "type": "Feature",
  "properties": {
    "addr:full":"PO Box 210 Forestburg AB T0B 1N0",
    "addr:housenumber":"po",
    "addr:postcode":"t0b 1n0",
    "addr:street":"Box 210",
    "iso:country":"CA",
    "sg:address":"PO Box 210",
    "sg:city":"Forestburg",
    "sg:classifiers":[
        {
            "category":"Recreation",
            "type":"Entertainment"
        }
    ],
    "sg:phone":"+1 780 582 4214",
    "sg:postcode":"T0B 1N0",
    "sg:province":"AB",
    "sg:tags":[
        "hall",
        "auditorium"
    ],
    "wof:name":"Forestburg Community Ctr",
    "wof:placetype":"venue"
},
  "geometry": {"coordinates":[-112.06444500000001,52.582611],"type":"Point"}
}