{
  "type": "Feature",
  "properties": {
    "iso:country":"CA",
    "sg:address":"75 Dunsmoor Rd",
    "sg:city":"London",
    "sg:classifiers":[
        {
            "category":"Manufacturing",
            "subcategory":"Toys & Sporting Goods",
            "type":"Manufacturing & Wholesale Goods"
        }
    ],
    "sg:phone":"+1 519 471 9061",
    "sg:postcode":"N6K 1T6",
    "sg:province":"ON",
    "sg:tags":[
        "hobby",
        "model",
        "supply"
    ],
    "wof:name":"Hallam Marine Hobby",
    "wof:placetype":"venue"
},
  "geometry": {"coordinates":[-81.297203,42.942131],"type":"Point"}
}