{
  "type": "Feature",
  "properties": {
    "addr:full":"267 Boul Des Peres Dolbeau-Mistassini QC G8L 5C5",
    "addr:housenumber":"267",
    "addr:postcode":"g8l 5c5",
    "addr:street":"Boul Des Peres",
    "iso:country":"CA",
    "sg:address":"267 Boul Des Peres",
    "sg:city":"Dolbeau-Mistassini",
    "sg:classifiers":[
        {
            "category":"Wholesale",
            "subcategory":"Fruits & Vegetables",
            "type":"Manufacturing & Wholesale Goods"
        }
    ],
    "sg:phone":"+1 418 276 5518",
    "sg:postcode":"G8L 5C5",
    "sg:province":"QC",
    "wof:name":"P & B Gaudreault Inc",
    "wof:placetype":"venue"
},
  "geometry": {"coordinates":[-72.219223,48.895496],"type":"Point"}
}