{
  "type": "Feature",
  "properties": {
    "addr:full":"2990 Av DE Granby # 2 Montreal QC H1N 2Z4",
    "addr:housenumber":"2990",
    "addr:postcode":"h1n 2z4",
    "addr:street":"Av De Granby # 2",
    "iso:country":"CA",
    "sg:address":"2990 Av DE Granby # 2",
    "sg:city":"Montreal",
    "sg:classifiers":[
        {
            "category":"Real Estate",
            "subcategory":"Real Estate Operator",
            "type":"Services"
        }
    ],
    "sg:phone":"+1 514 256 9037",
    "sg:postcode":"H1N 2Z4",
    "sg:province":"QC",
    "sg:tags":[
        "apartment"
    ],
    "wof:name":"Habitations Le Domaine",
    "wof:placetype":"venue"
},
  "geometry": {"coordinates":[-73.539665,45.580109],"type":"Point"}
}