{
  "type": "Feature",
  "properties": {
    "addr:full":"231 St. Paul St W St Catharines ON L2S 2E3",
    "addr:housenumber":"231",
    "addr:postcode":"l2s 2e3",
    "addr:street":"St. Paul St W",
    "iso:country":"CA",
    "sg:address":"231 St. Paul St W",
    "sg:city":"St Catharines",
    "sg:classifiers":[
        {
            "category":"Restaurant",
            "type":"Food & Drink"
        }
    ],
    "sg:phone":"+1 905 685 9077",
    "sg:postcode":"L2S 2E3",
    "sg:province":"ON",
    "sg:tags":[
        "pizza"
    ],
    "wof:name":"Mystic Jack's",
    "wof:placetype":"venue"
},
  "geometry": {"coordinates":[-79.2595672607,43.1449966431],"type":"Point"}
}