{
  "type": "Feature",
  "properties": {
    "addr:full":"Surrey BC V3W 0K6",
    "addr:postcode":"v3w 0k6",
    "iso:country":"CA",
    "sg:city":"Surrey",
    "sg:classifiers":[
        {
            "category":"Manufacturing",
            "subcategory":"Metals",
            "type":"Manufacturing & Wholesale Goods"
        }
    ],
    "sg:phone":"+1 604 507 7660",
    "sg:postcode":"V3W 0K6",
    "sg:province":"BC",
    "sg:tags":[
        "polishing",
        "plating"
    ],
    "wof:name":"Action Plating Inc",
    "wof:placetype":"venue"
},
  "geometry": {"coordinates":[-122.862693787,49.1552658081],"type":"Point"}
}