{
  "type": "Feature",
  "properties": {
    "addr:full":"160 Brock St Barrie ON L4N 2M4",
    "addr:housenumber":"160",
    "addr:postcode":"l4n 2m4",
    "addr:street":"Brock St",
    "iso:country":"CA",
    "sg:address":"160 Brock St",
    "sg:city":"Barrie",
    "sg:classifiers":[
        {
            "category":"Wholesale",
            "subcategory":"Machinery & Supplies",
            "type":"Manufacturing & Wholesale Goods"
        }
    ],
    "sg:phone":"+1 705 737 4130",
    "sg:postcode":"L4N 2M4",
    "sg:province":"ON",
    "sg:tags":[
        "equipment",
        "hydraulic"
    ],
    "wof:name":"Western Hydraulics",
    "wof:placetype":"venue"
},
  "geometry": {"coordinates":[-79.70300292970001,44.3733482361],"type":"Point"}
}