{
  "type": "Feature",
  "properties": {
    "addr:full":"2030 Paramount Cres Abbotsford BC V2T 6A5",
    "addr:housenumber":"2030",
    "addr:postcode":"v2t 6a5",
    "addr:street":"Paramount Cres",
    "iso:country":"CA",
    "sg:address":"2030 Paramount Cres",
    "sg:city":"Abbotsford",
    "sg:classifiers":[
        {
            "category":"Wholesale",
            "subcategory":"Construction Materials",
            "type":"Manufacturing & Wholesale Goods"
        }
    ],
    "sg:phone":"+1 604 504 0774",
    "sg:postcode":"V2T 6A5",
    "sg:province":"BC",
    "sg:tags":[
        "concrete",
        "form"
    ],
    "wof:name":"Coast Form Rentals Ltd",
    "wof:placetype":"venue"
},
  "geometry": {"coordinates":[-122.34556600000001,49.03923],"type":"Point"}
}