{
  "type": "Feature",
  "properties": {
    "addr:full":"71st Street Rd & Hwy 16 W Saskatoon SK S7K 3J7",
    "addr:postcode":"s7k 3j7",
    "addr:street":"71St Street Rd & Hwy 16 W",
    "iso:country":"CA",
    "sg:address":"71st Street Rd & Hwy 16 W",
    "sg:city":"Saskatoon",
    "sg:classifiers":[
        {
            "category":"Manufacturing",
            "subcategory":"Rubber & Plastics",
            "type":"Manufacturing & Wholesale Goods"
        }
    ],
    "sg:phone":"+1 306 242 4494",
    "sg:postcode":"S7K 3J7",
    "sg:province":"SK",
    "sg:tags":[
        "mold",
        "maker"
    ],
    "wof:name":"Quality Molded Plastics",
    "wof:placetype":"venue"
},
  "geometry": {"coordinates":[-106.672119,52.202091],"type":"Point"}
}