{
  "type": "Feature",
  "properties": {
    "iso:country":"CA",
    "sg:address":"Carldale Rd",
    "sg:city":"Grande Prairie",
    "sg:classifiers":[
        {
            "category":"Building & Trades",
            "subcategory":"Construction",
            "type":"Services"
        }
    ],
    "sg:phone":"+1 780 865 7676",
    "sg:postcode":"T8V 1Y1",
    "sg:province":"AB",
    "sg:tags":[
        "contractor"
    ],
    "wof:name":"Cosum Construction Ltd",
    "wof:placetype":"venue"
},
  "geometry": {"coordinates":[-118.794891357,55.1711616516],"type":"Point"}
}