{
  "type": "Feature",
  "properties": {
    "addr:full":"2045 Trans Canada Hwy W Kamloops BC V1S 1A7",
    "addr:housenumber":"2045",
    "addr:postcode":"bc v1s 1a7",
    "addr:street":"Trans Canada Hwy W",
    "iso:country":"CA",
    "sg:address":"2045 Trans Canada Hwy W",
    "sg:city":"Kamloops",
    "sg:classifiers":[
        {
            "category":"Wholesale",
            "subcategory":"Machinery & Supplies",
            "type":"Manufacturing & Wholesale Goods"
        }
    ],
    "sg:phone":"+1 250 374 3443",
    "sg:postcode":"V1S 1A7",
    "sg:province":"BC",
    "sg:tags":[
        "engine"
    ],
    "wof:name":"Interior Diesel",
    "wof:placetype":"venue"
},
  "geometry": {"coordinates":[-120.40762329099999,50.6625213623],"type":"Point"}
}