{
  "type": "Feature",
  "properties": {
    "addr:full":"16 Ripley Ave Toronto ON M6S 3P1",
    "addr:housenumber":"16",
    "addr:postcode":"m6s 3p1",
    "addr:street":"Ripley Ave",
    "iso:country":"CA",
    "sg:address":"16 Ripley Ave",
    "sg:city":"Toronto",
    "sg:classifiers":[
        {
            "category":"Manufacturing",
            "subcategory":"Jewelry",
            "type":"Manufacturing & Wholesale Goods"
        }
    ],
    "sg:phone":"+1 416 762 2222",
    "sg:postcode":"M6S 3P1",
    "sg:province":"ON",
    "wof:name":"Corona Jewellery CO",
    "wof:placetype":"venue"
},
  "geometry": {"coordinates":[-79.47474699999999,43.637135],"type":"Point"}
}