{
  "type": "Feature",
  "properties": {
    "addr:full":"1128 Broadway W #A Vancouver BC V6H 1G5",
    "addr:housenumber":"1128",
    "addr:postcode":"v6h 1g5",
    "addr:street":"Broadway W # A",
    "iso:country":"CA",
    "sg:address":"1128 Broadway W #A",
    "sg:city":"Vancouver",
    "sg:classifiers":[
        {
            "category":"Shopping",
            "subcategory":"Computers & Home Electronics",
            "type":"Retail Goods"
        }
    ],
    "sg:phone":"+1 604 731 9055",
    "sg:postcode":"V6H 1G5",
    "sg:province":"BC",
    "sg:tags":[
        "television",
        "radio"
    ],
    "wof:name":"Sony Store",
    "wof:placetype":"venue"
},
  "geometry": {"coordinates":[-123.113937378,49.2604484558],"type":"Point"}
}