{
  "type": "Feature",
  "properties": {
    "addr:full":"1177 Pontiac Dr Sarnia ON N7S 3B1",
    "addr:housenumber":"1177",
    "addr:postcode":"n7s 3b1",
    "addr:street":"Pontiac Dr",
    "iso:country":"CA",
    "sg:address":"1177 Pontiac Dr",
    "sg:city":"Sarnia",
    "sg:classifiers":[
        {
            "category":"Personal",
            "subcategory":"Beauty Salon",
            "type":"Services"
        }
    ],
    "sg:phone":"+1 519 383 7953",
    "sg:postcode":"N7S 3B1",
    "sg:province":"ON",
    "wof:name":"Peter's Hairstyling Shop",
    "wof:placetype":"venue"
},
  "geometry": {"coordinates":[-82.361763,42.982876],"type":"Point"}
}