{
  "type": "Feature",
  "properties": {
    "addr:full":"4401 47th St Forestburg AB T0B 1N0",
    "addr:housenumber":"4401",
    "addr:postcode":"t0b 1n0",
    "addr:street":"47Th St",
    "iso:country":"CA",
    "sg:address":"4401 47th St",
    "sg:city":"Forestburg",
    "sg:classifiers":[
        {
            "category":"Social Services",
            "subcategory":"Adult Care",
            "type":"Services"
        }
    ],
    "sg:phone":"+1 780 582 3564",
    "sg:postcode":"T0B 1N0",
    "sg:province":"AB",
    "sg:tags":[
        "senior",
        "housing",
        "citizen"
    ],
    "wof:name":"Big Knife Villa",
    "wof:placetype":"venue"
},
  "geometry": {"coordinates":[-112.058822632,52.5796737671],"type":"Point"}
}