{
  "type": "Feature",
  "properties": {
    "addr:full":"Montreal QC H3K 1J1",
    "addr:postcode":"h3k 1j1",
    "iso:country":"CA",
    "sg:city":"Montreal",
    "sg:classifiers":[
        {
            "category":"Building & Trades",
            "subcategory":"Plumbing",
            "type":"Services"
        }
    ],
    "sg:phone":"+1 514 931 5851",
    "sg:postcode":"H3K 1J1",
    "sg:province":"QC",
    "sg:tags":[
        "contractor"
    ],
    "wof:name":"Plomberie Roland Gauthier Inc",
    "wof:placetype":"venue"
},
  "geometry": {"coordinates":[-73.5633010864,45.4823608398],"type":"Point"}
}