{
  "type": "Feature",
  "properties": {
    "addr:full":"430 Woodward Ave Hamilton ON L8H 6N8",
    "addr:housenumber":"430",
    "addr:postcode":"l8h 6n8",
    "addr:street":"Woodward Ave",
    "iso:country":"CA",
    "sg:address":"430 Woodward Ave",
    "sg:city":"Hamilton",
    "sg:classifiers":[
        {
            "category":"Restaurant",
            "type":"Food & Drink"
        }
    ],
    "sg:phone":"+1 905 547 2827",
    "sg:postcode":"L8H 6N8",
    "sg:province":"ON",
    "wof:name":"Woodward Restaurant",
    "wof:placetype":"venue"
},
  "geometry": {"coordinates":[-79.77784699999999,43.244724],"type":"Point"}
}