{
  "type": "Feature",
  "properties": {
    "addr:full":"Maple ON L6A 3L2",
    "addr:postcode":"l6a 3l2",
    "iso:country":"CA",
    "sg:city":"Maple",
    "sg:classifiers":[
        {
            "category":"Social Services",
            "subcategory":"Job Training",
            "type":"Services"
        }
    ],
    "sg:phone":"+1 905 303 0760",
    "sg:postcode":"L6A 3L2",
    "sg:province":"ON",
    "sg:tags":[
        "physiotherapist",
        "rehabilitation"
    ],
    "wof:name":"Maple Glen Physiotherapy Clnc",
    "wof:placetype":"venue"
},
  "geometry": {"coordinates":[-79.53276099999999,43.850861],"type":"Point"}
}