{
  "type": "Feature",
  "properties": {
    "addr:full":"Baie-Des-Sables QC G0J 1C0",
    "addr:postcode":"g0j 1c0",
    "iso:country":"CA",
    "sg:city":"Baie-Des-Sables",
    "sg:classifiers":[
        {
            "category":"Government",
            "subcategory":"Office",
            "type":"Public Place"
        }
    ],
    "sg:phone":"+1 418 772 6218",
    "sg:postcode":"G0J 1C0",
    "sg:province":"QC",
    "sg:tags":[
        "village"
    ],
    "wof:name":"Municipalite DE Baie Des Sable",
    "wof:placetype":"venue"
},
  "geometry": {"coordinates":[-67.894829,48.720268],"type":"Point"}
}