{
  "type": "Feature",
  "properties": {
    "iso:country":"CA",
    "sg:address":"PO Box 536 STN Main",
    "sg:city":"Grande Prairie",
    "sg:classifiers":[
        {
            "category":"Building & Trades",
            "subcategory":"Construction",
            "type":"Services"
        }
    ],
    "sg:phone":"+1 780 538 1122",
    "sg:postcode":"T8V 3A7",
    "sg:province":"AB",
    "sg:tags":[
        "marking",
        "maintenance",
        "parking"
    ],
    "wof:name":"Highline Maintenance Ltd",
    "wof:placetype":"venue"
},
  "geometry": {"coordinates":[-118.794891357,55.1711616516],"type":"Point"}
}