{
  "type": "Feature",
  "properties": {
    "addr:full":"946 Av Victoria #5 Saint-Lambert QC J4R 1N9",
    "addr:postcode":"j4r 1n9",
    "addr:street":"946 Av Victoria # 5",
    "iso:country":"CA",
    "sg:address":"946 Av Victoria #5",
    "sg:city":"Saint-Lambert",
    "sg:classifiers":[
        {
            "category":"Real Estate",
            "subcategory":"Real Estate Agent",
            "type":"Services"
        }
    ],
    "sg:phone":"+1 450 466 6020",
    "sg:postcode":"J4R 1N9",
    "sg:province":"QC",
    "sg:tags":[
        "appraiser"
    ],
    "wof:name":"Gilles Robert & Assoc",
    "wof:placetype":"venue"
},
  "geometry": {"coordinates":[-73.5015640259,45.4962730408],"type":"Point"}
}