{
  "type": "Feature",
  "properties": {
    "iso:country":"CA",
    "sg:address":"700 Richmond St #G106",
    "sg:city":"London",
    "sg:classifiers":[
        {
            "category":"Personal",
            "subcategory":"Beauty Salon",
            "type":"Services"
        }
    ],
    "sg:phone":"+1 519 433 6221",
    "sg:postcode":"N6A 5C7",
    "sg:province":"ON",
    "wof:name":"Piccadilly Professional Hair",
    "wof:placetype":"venue"
},
  "geometry": {"coordinates":[-81.2522277832,42.9940261841],"type":"Point"}
}