{
  "type": "Feature",
  "properties": {
    "addr:full":"7144 Hunterdale Rd NW Calgary AB T2K 4S1",
    "addr:housenumber":"7144",
    "addr:postcode":"t2k 4s1",
    "addr:street":"Hunterdale Rd Nw",
    "iso:country":"CA",
    "sg:address":"7144 Hunterdale Rd NW",
    "sg:city":"Calgary",
    "sg:classifiers":[
        {
            "category":"Wholesale",
            "subcategory":"Machinery & Supplies",
            "type":"Manufacturing & Wholesale Goods"
        }
    ],
    "sg:phone":"+1 403 516 6111",
    "sg:postcode":"T2K 4S1",
    "sg:province":"AB",
    "sg:tags":[
        "equipment",
        "industrial",
        "sandblasting"
    ],
    "wof:name":"Ice Jet Inc",
    "wof:placetype":"venue"
},
  "geometry": {"coordinates":[-114.0809021,51.1149864197],"type":"Point"}
}