{
  "type": "Feature",
  "properties": {
    "addr:full":"220 Third Ave Timmins ON P4N 1E1",
    "addr:housenumber":"220",
    "addr:postcode":"p4n 1e1",
    "addr:street":"Third Ave",
    "iso:country":"CA",
    "sg:address":"220 Third Ave",
    "sg:city":"Timmins",
    "sg:classifiers":[
        {
            "category":"Shopping",
            "subcategory":"Clothing, Apparel, & Fashions",
            "type":"Retail Goods"
        }
    ],
    "sg:phone":"+1 705 264 3287",
    "sg:postcode":"P4N 1E1",
    "sg:province":"ON",
    "wof:name":"Tweed & Hickory",
    "wof:placetype":"venue"
},
  "geometry": {"coordinates":[-81.329033,48.47504],"type":"Point"}
}