{
  "type": "Feature",
  "properties": {
    "iso:country":"CA",
    "sg:address":"508 Newbold St",
    "sg:city":"London",
    "sg:classifiers":[
        {
            "category":"Manufacturing",
            "subcategory":"Printing",
            "type":"Manufacturing & Wholesale Goods"
        }
    ],
    "sg:phone":"+1 519 685 0101",
    "sg:postcode":"N6E 1K6",
    "sg:province":"ON",
    "sg:tags":[
        "printer",
        "legal",
        "form"
    ],
    "wof:name":"Dye & Durham CO",
    "wof:placetype":"venue"
},
  "geometry": {"coordinates":[-81.206688,42.934757],"type":"Point"}
}