{
  "type": "Feature",
  "properties": {
    "addr:full":"3289 Rue Ontario E Montreal QC H1W 1P5",
    "addr:housenumber":"3289",
    "addr:postcode":"h1w 1p5",
    "addr:street":"Rue Ontario E",
    "iso:country":"CA",
    "sg:address":"3289 Rue Ontario E",
    "sg:city":"Montreal",
    "sg:classifiers":[
        {
            "category":"Personal",
            "subcategory":"Beauty Salon",
            "type":"Services"
        }
    ],
    "sg:phone":"+1 514 527 4445",
    "sg:postcode":"H1W 1P5",
    "sg:province":"QC",
    "wof:name":"Salon Coiffure Berard Reg'd",
    "wof:placetype":"venue"
},
  "geometry": {"coordinates":[-73.5468444824,45.5422401428],"type":"Point"}
}