{
  "type": "Feature",
  "properties": {
    "iso:country":"CA",
    "sg:city":"Ottawa",
    "sg:classifiers":[
        {
            "category":"Manufacturing",
            "subcategory":"Printing",
            "type":"Manufacturing & Wholesale Goods"
        }
    ],
    "sg:phone":"+1 613 725 5060",
    "sg:postcode":"K1Y 4T3",
    "sg:province":"ON",
    "sg:tags":[
        "publisher"
    ],
    "wof:name":"Esprit DE Corps",
    "wof:placetype":"venue"
},
  "geometry": {"coordinates":[-75.720428,45.406414],"type":"Point"}
}