{
  "type": "Feature",
  "properties": {
    "addr:full":"1183 Bank St Ottawa ON K1S 3X7",
    "addr:housenumber":"1183",
    "addr:postcode":"k1s 3x7",
    "addr:street":"Bank St",
    "iso:country":"CA",
    "sg:address":"1183 Bank St",
    "sg:city":"Ottawa",
    "sg:classifiers":[
        {
            "category":"Personal",
            "subcategory":"Beauty Salon",
            "type":"Services"
        }
    ],
    "sg:phone":"+1 613 730 8500",
    "sg:postcode":"K1S 3X7",
    "sg:province":"ON",
    "sg:tags":[
        "spa"
    ],
    "wof:name":"Atlantis Beauty Spa",
    "wof:placetype":"venue"
},
  "geometry": {"coordinates":[-75.681549,45.392181],"type":"Point"}
}