{
  "type": "Feature",
  "properties": {
    "addr:full":"London ON N6C 5Z9",
    "addr:postcode":"n6c 5z9",
    "iso:country":"CA",
    "sg:city":"London",
    "sg:classifiers":[
        {
            "category":"Health Services",
            "subcategory":"Health Practitioner",
            "type":"Services"
        }
    ],
    "sg:phone":"+1 519 660 8139",
    "sg:postcode":"N6C 5Z9",
    "sg:province":"ON",
    "sg:tags":[
        "psychologist"
    ],
    "wof:name":"Braimoh, Gani B",
    "wof:placetype":"venue"
},
  "geometry": {"coordinates":[-81.2314910889,42.9626502991],"type":"Point"}
}