{
  "type": "Feature",
  "properties": {
    "addr:full":"253 Rue Saint-Georges Saint-Jerome QC J7Z 5A1",
    "addr:housenumber":"253",
    "addr:postcode":"j7z 5a1",
    "addr:street":"Rue Saint-Georges Saint-Jerome",
    "iso:country":"CA",
    "sg:address":"253 Rue Saint-Georges",
    "sg:city":"Saint-Jerome",
    "sg:classifiers":[
        {
            "category":"Restaurant",
            "type":"Food & Drink"
        }
    ],
    "sg:phone":"+1 450 438 7555",
    "sg:postcode":"J7Z 5A1",
    "sg:province":"QC",
    "wof:name":"Restaurant Cambodiana",
    "wof:placetype":"venue"
},
  "geometry": {"coordinates":[-74.0027999878,45.7748794556],"type":"Point"}
}