{
  "type": "Feature",
  "properties": {
    "addr:full":"Centre St Nakina ON P0T 2H0",
    "addr:postcode":"p0t 2h0",
    "addr:street":"Centre St",
    "iso:country":"CA",
    "sg:address":"Centre St",
    "sg:city":"Nakina",
    "sg:classifiers":[
        {
            "category":"Organizations",
            "subcategory":"Religious Organization",
            "type":"Services"
        }
    ],
    "sg:phone":"+1 807 329 5384",
    "sg:postcode":"P0T 2H0",
    "sg:province":"ON",
    "sg:tags":[
        "church"
    ],
    "wof:name":"St Brigid Church Northwood",
    "wof:placetype":"venue"
},
  "geometry": {"coordinates":[-86.706322,50.177975],"type":"Point"}
}