{
  "type": "Feature",
  "properties": {
    "addr:full":"1050 Salk Rd Pickering ON L1W 3C5",
    "addr:housenumber":"1050",
    "addr:postcode":"l1w 3c5",
    "addr:street":"Salk Rd",
    "iso:country":"CA",
    "sg:address":"1050 Salk Rd",
    "sg:city":"Pickering",
    "sg:classifiers":[
        {
            "category":"Wholesale",
            "subcategory":"Auto Parts",
            "type":"Manufacturing & Wholesale Goods"
        }
    ],
    "sg:phone":"+1 905 831 4211",
    "sg:postcode":"L1W 3C5",
    "sg:province":"ON",
    "sg:tags":[
        "automobile",
        "supply"
    ],
    "wof:name":"Pronto Auto Repair Dealership",
    "wof:placetype":"venue"
},
  "geometry": {"coordinates":[-79.07205963129999,43.8350143433],"type":"Point"}
}