{
  "type": "Feature",
  "properties": {
    "addr:full":"41 Paris St Alliston ON L9R 1J3",
    "addr:housenumber":"41",
    "addr:postcode":"l9r 1j3",
    "addr:street":"Paris St",
    "iso:country":"CA",
    "sg:address":"41 Paris St",
    "sg:city":"Alliston",
    "sg:classifiers":[
        {
            "category":"Organizations",
            "subcategory":"Religious Organization",
            "type":"Services"
        }
    ],
    "sg:phone":"+1 705 435 7293",
    "sg:postcode":"L9R 1J3",
    "sg:province":"ON",
    "sg:tags":[
        "church"
    ],
    "wof:name":"Alliston Christian Fellowship",
    "wof:placetype":"venue"
},
  "geometry": {"coordinates":[-79.871635,44.152168],"type":"Point"}
}