{
  "type": "Feature",
  "properties": {
    "addr:full":"66 Greenwood Ave St Catharines ON L2P 1X8",
    "addr:housenumber":"66",
    "addr:postcode":"l2p 1x8",
    "addr:street":"Greenwood Ave",
    "iso:country":"CA",
    "sg:address":"66 Greenwood Ave",
    "sg:city":"St Catharines",
    "sg:classifiers":[
        {
            "category":"Building & Trades",
            "subcategory":"Electrical",
            "type":"Services"
        }
    ],
    "sg:phone":"+1 905 682 3789",
    "sg:postcode":"L2P 1X8",
    "sg:province":"ON",
    "sg:tags":[
        "electric",
        "contractor"
    ],
    "wof:name":"Security Electric",
    "wof:placetype":"venue"
},
  "geometry": {"coordinates":[-79.204178,43.156139],"type":"Point"}
}