{
  "type": "Feature",
  "properties": {
    "addr:full":"965 Boul Arthur-Sauve Saint-Eustache QC J7R 4K3",
    "addr:housenumber":"965",
    "addr:postcode":"j7r 4k3",
    "addr:street":"Boul Arthur-Sauve",
    "iso:country":"CA",
    "sg:address":"965 Boul Arthur-Sauve",
    "sg:city":"Saint-Eustache",
    "sg:classifiers":[
        {
            "category":"Home & Garden",
            "subcategory":"Garden Supply",
            "type":"Retail Goods"
        }
    ],
    "sg:phone":"+1 450 472 6474",
    "sg:postcode":"J7R 4K3",
    "sg:province":"QC",
    "sg:tags":[
        "concrete",
        "nurseryman"
    ],
    "wof:name":"Beton Eco-Verdure",
    "wof:placetype":"venue"
},
  "geometry": {"coordinates":[-73.95705413819999,45.5836601257],"type":"Point"}
}