{
  "type": "Feature",
  "properties": {
    "addr:full":"Arnprior ON K7S 1N6",
    "addr:postcode":"k7s 1n6",
    "iso:country":"CA",
    "sg:city":"Arnprior",
    "sg:classifiers":[
        {
            "category":"Shopping",
            "subcategory":"Jewelry",
            "type":"Retail Goods"
        }
    ],
    "sg:phone":"+1 613 623 4112",
    "sg:postcode":"K7S 1N6",
    "sg:province":"ON",
    "sg:tags":[
        "jeweler"
    ],
    "wof:name":"Doreen's Goldbar",
    "wof:placetype":"venue"
},
  "geometry": {"coordinates":[-76.355148,45.434013],"type":"Point"}
}