{
  "type": "Feature",
  "properties": {
    "addr:full":"6500 Macleod Trail SW Calgary AB T2H 0K6",
    "addr:housenumber":"6500",
    "addr:postcode":"t2h 0k6",
    "addr:street":"Macleod Trail Sw",
    "iso:country":"CA",
    "sg:address":"6500 Macleod Trail SW",
    "sg:city":"Calgary",
    "sg:classifiers":[
        {
            "category":"Restaurant",
            "type":"Food & Drink"
        }
    ],
    "sg:phone":"+1 403 255 0563",
    "sg:postcode":"T2H 0K6",
    "sg:province":"AB",
    "wof:name":"Harvey's",
    "wof:placetype":"venue"
},
  "geometry": {"coordinates":[-114.071213,50.99593],"type":"Point"}
}