{
  "type": "Feature",
  "properties": {
    "addr:full":"3901 Boul Saint-Laurent Montreal QC H2W 1X9",
    "addr:housenumber":"3901",
    "addr:postcode":"h2w 1x9",
    "addr:street":"Boul Saint-Laurent",
    "iso:country":"CA",
    "sg:address":"3901 Boul Saint-Laurent",
    "sg:city":"Montreal",
    "sg:classifiers":[
        {
            "category":"Professional",
            "subcategory":"Art Services",
            "type":"Services"
        }
    ],
    "sg:phone":"+1 514 286 3737",
    "sg:postcode":"H2W 1X9",
    "sg:province":"QC",
    "sg:tags":[
        "graphic",
        "designer"
    ],
    "wof:name":"Glare Creative Conception",
    "wof:placetype":"venue"
},
  "geometry": {"coordinates":[-73.57765999999999,45.516354],"type":"Point"}
}