{
  "type": "Feature",
  "properties": {
    "addr:full":"334 15th St W North Vancouver BC V7M 1S5",
    "addr:housenumber":"334",
    "addr:postcode":"v7m 1s5",
    "addr:street":"15Th St W",
    "iso:country":"CA",
    "sg:address":"334 15th St W",
    "sg:city":"North Vancouver",
    "sg:classifiers":[
        {
            "category":"Professional",
            "subcategory":"Lawyer & Legal Services",
            "type":"Services"
        }
    ],
    "sg:phone":"+1 604 986 0488",
    "sg:postcode":"V7M 1S5",
    "sg:province":"BC",
    "sg:tags":[
        "attorney"
    ],
    "wof:name":"Roper, David A",
    "wof:placetype":"venue"
},
  "geometry": {"coordinates":[-123.079742,49.322277],"type":"Point"}
}