{
  "type": "Feature",
  "properties": {
    "iso:country":"CA",
    "sg:address":"1784 Rue Bagot",
    "sg:city":"LA Baie",
    "sg:classifiers":[
        {
            "category":"Utilities",
            "subcategory":"Fuel Oil & Lpg",
            "type":"Services"
        }
    ],
    "sg:phone":"+1 418 544 3911",
    "sg:postcode":"G7B 2R1",
    "sg:province":"QC",
    "wof:name":"Petroles Rl Inc",
    "wof:placetype":"venue"
},
  "geometry": {"coordinates":[-70.8913650513,48.3363800049],"type":"Point"}
}