{
  "type": "Feature",
  "properties": {
    "addr:full":"PO Box 6611 STN Main Edson AB T7E 1T9",
    "addr:housenumber":"po",
    "addr:postcode":"t7e 1t9",
    "addr:street":"Box 6611 Stn Main",
    "iso:country":"CA",
    "sg:address":"PO Box 6611 STN Main",
    "sg:city":"Edson",
    "sg:classifiers":[
        {
            "category":"Retail",
            "subcategory":"Repair Shop",
            "type":"Services"
        }
    ],
    "sg:phone":"+1 780 723 5481",
    "sg:postcode":"T7E 1T9",
    "sg:province":"AB",
    "sg:tags":[
        "welding"
    ],
    "wof:name":"Toba Welding Ltd",
    "wof:placetype":"venue"
},
  "geometry": {"coordinates":[-116.43409699999999,53.58213],"type":"Point"}
}