{
  "type": "Feature",
  "properties": {
    "addr:full":"1041 53E Av Pointe-Aux-Trembles QC H1A 2T8",
    "addr:housenumber":"1041",
    "addr:postcode":"h1a 2t8",
    "addr:street":"53E Av Pointe-Aux-Trembles",
    "iso:country":"CA",
    "sg:address":"1041 53E Av",
    "sg:city":"Pointe-Aux-Trembles",
    "sg:classifiers":[
        {
            "category":"Health Services",
            "subcategory":"Nursing And Care Facility",
            "type":"Services"
        }
    ],
    "sg:phone":"+1 514 642 4624",
    "sg:postcode":"H1A 2T8",
    "sg:province":"QC",
    "sg:tags":[
        "home",
        "retirement",
        "community"
    ],
    "wof:name":"Pavillon Evelyne Robert Inc",
    "wof:placetype":"venue"
},
  "geometry": {"coordinates":[-73.497108,45.671143],"type":"Point"}
}