{
  "type": "Feature",
  "properties": {
    "addr:full":"16265 Fairview Dr Avonmore ON K0C 1C0",
    "addr:housenumber":"16265",
    "addr:postcode":"k0c 1c0",
    "addr:street":"Fairview Dr",
    "iso:country":"CA",
    "sg:address":"16265 Fairview Dr",
    "sg:city":"Avonmore",
    "sg:classifiers":[
        {
            "category":"Arts & Performance",
            "subcategory":"Theater",
            "type":"Entertainment"
        }
    ],
    "sg:phone":"+1 613 346 2622",
    "sg:postcode":"K0C 1C0",
    "sg:province":"ON",
    "sg:tags":[
        "bureau",
        "concert"
    ],
    "wof:name":"Shantero Productions",
    "wof:placetype":"venue"
},
  "geometry": {"coordinates":[-74.97232099999999,45.170174],"type":"Point"}
}