{
  "type": "Feature",
  "properties": {
    "addr:full":"284 Rue Principale Audet QC G0Y 1A0",
    "addr:housenumber":"284",
    "addr:postcode":"g0y 1a0",
    "addr:street":"Rue Principale",
    "iso:country":"CA",
    "sg:address":"284 Rue Principale",
    "sg:city":"Audet",
    "sg:classifiers":[
        {
            "category":"Manufacturing",
            "subcategory":"Furniture",
            "type":"Manufacturing & Wholesale Goods"
        }
    ],
    "sg:phone":"+1 819 583 5656",
    "sg:postcode":"G0Y 1A0",
    "sg:province":"QC",
    "wof:name":"Menuiserie Belco Tech Inc",
    "wof:placetype":"venue"
},
  "geometry": {"coordinates":[-70.73412322999999,45.6573944092],"type":"Point"}
}