{
  "type": "Feature",
  "properties": {
    "addr:full":"3920 56 St Wetaskiwin AB T9A 2B2",
    "addr:housenumber":"3920",
    "addr:postcode":"t9a 2b2",
    "addr:street":"56 St",
    "iso:country":"CA",
    "sg:address":"3920 56 St",
    "sg:city":"Wetaskiwin",
    "sg:classifiers":[
        {
            "category":"Autos & Motor Vehicles",
            "subcategory":"Automobile Sales",
            "type":"Retail Goods"
        }
    ],
    "sg:phone":"+1 780 424 2277",
    "sg:postcode":"T9A 2B2",
    "sg:province":"AB",
    "sg:tags":[
        "car",
        "dealer"
    ],
    "wof:name":"Pioneer Chrysler Jeep Ltd",
    "wof:placetype":"venue"
},
  "geometry": {"coordinates":[-113.390427,52.959232],"type":"Point"}
}