{
  "type": "Feature",
  "properties": {
    "addr:full":"5419 48 St High Prairie AB T0G 1E0",
    "addr:housenumber":"5419",
    "addr:postcode":"t0g 1e0",
    "addr:street":"48 St",
    "iso:country":"CA",
    "sg:address":"5419 48 St",
    "sg:city":"High Prairie",
    "sg:classifiers":[
        {
            "category":"Organizations",
            "subcategory":"Religious Organization",
            "type":"Services"
        }
    ],
    "sg:phone":"+1 780 523 3280",
    "sg:postcode":"T0G 1E0",
    "sg:province":"AB",
    "sg:tags":[
        "church"
    ],
    "wof:name":"Church of the Nazarene",
    "wof:placetype":"venue"
},
  "geometry": {"coordinates":[-116.48838000000001,55.433998],"type":"Point"}
}