{
  "type": "Feature",
  "properties": {
    "addr:full":"Port Moody BC V3H 2B4",
    "addr:postcode":"v3h 2b4",
    "iso:country":"CA",
    "sg:city":"Port Moody",
    "sg:classifiers":[
        {
            "category":"Personal",
            "subcategory":"Tattoo Parlor",
            "type":"Services"
        }
    ],
    "sg:phone":"+1 604 931 8272",
    "sg:postcode":"V3H 2B4",
    "sg:province":"BC",
    "sg:tags":[
        "tattooing"
    ],
    "wof:name":"Sinister Skin Tattoos & Body",
    "wof:placetype":"venue"
},
  "geometry": {"coordinates":[-122.85614776600001,49.2768554688],"type":"Point"}
}