{
  "type": "Feature",
  "properties": {
    "iso:country":"CA",
    "sg:address":"870 Brock Rd",
    "sg:city":"Pickering",
    "sg:classifiers":[
        {
            "category":"Manufacturing",
            "subcategory":"Tools & Machinery",
            "type":"Manufacturing & Wholesale Goods"
        }
    ],
    "sg:phone":"+1 416 281 2010",
    "sg:postcode":"L1W 1Z8",
    "sg:province":"ON",
    "sg:tags":[
        "equipment",
        "electric"
    ],
    "wof:name":"Hubbell Canada Inc",
    "wof:placetype":"venue"
},
  "geometry": {"coordinates":[-79.06356,43.823402],"type":"Point"}
}