{
  "type": "Feature",
  "properties": {
    "addr:full":"10 Centre St E Richmond Hill ON L4C 1A1",
    "addr:housenumber":"10",
    "addr:postcode":"l4c 1a1",
    "addr:street":"Centre St",
    "iso:country":"CA",
    "sg:address":"10 Centre St E",
    "sg:city":"Richmond Hill",
    "sg:classifiers":[
        {
            "category":"Personal",
            "subcategory":"Beauty Salon",
            "type":"Services"
        }
    ],
    "sg:phone":"+1 905 884 3414",
    "sg:postcode":"L4C 1A1",
    "sg:province":"ON",
    "wof:name":"Ellen's Coiffures",
    "wof:placetype":"venue"
},
  "geometry": {"coordinates":[-79.437691,43.875874],"type":"Point"}
}