{
  "type": "Feature",
  "properties": {
    "addr:full":"Chilliwack BC V2R 4R1",
    "addr:postcode":"v2r 4r1",
    "iso:country":"CA",
    "sg:city":"Chilliwack",
    "sg:classifiers":[
        {
            "category":"Travel",
            "subcategory":"Campground",
            "type":"Entertainment"
        }
    ],
    "sg:phone":"+1 604 823 6012",
    "sg:postcode":"V2R 4R1",
    "sg:province":"BC",
    "wof:name":"Vedder River Camp Ground",
    "wof:placetype":"venue"
},
  "geometry": {"coordinates":[-122.006958,49.095955],"type":"Point"}
}