{
  "type": "Feature",
  "properties": {
    "addr:full":"2779 Kingston Rd Scarborough ON M1M 1M9",
    "addr:housenumber":"2779",
    "addr:postcode":"m1m 1m9",
    "addr:street":"Kingston Rd",
    "iso:country":"CA",
    "sg:address":"2779 Kingston Rd",
    "sg:city":"Scarborough",
    "sg:classifiers":[
        {
            "category":"Retail",
            "subcategory":"Auto Repair",
            "type":"Services"
        }
    ],
    "sg:phone":"+1 416 265 2200",
    "sg:postcode":"M1M 1M9",
    "sg:province":"ON",
    "sg:tags":[
        "repairing",
        "automobile"
    ],
    "wof:name":"Bluffers Part Auto Svc",
    "wof:placetype":"venue"
},
  "geometry": {"coordinates":[-79.238342,43.719742],"type":"Point"}
}