{
  "type": "Feature",
  "properties": {
    "addr:full":"85 Rue Victoria Sorel-Tracy QC J3P 1Y8",
    "addr:housenumber":"85",
    "addr:postcode":"j3p 1y8",
    "addr:street":"Rue Victoria",
    "iso:country":"CA",
    "sg:address":"85 Rue Victoria",
    "sg:city":"Sorel-Tracy",
    "sg:classifiers":[
        {
            "category":"Shopping",
            "subcategory":"Gifts & Souvenirs",
            "type":"Retail Goods"
        }
    ],
    "sg:phone":"+1 450 746 5741",
    "sg:postcode":"J3P 1Y8",
    "sg:province":"QC",
    "sg:tags":[
        "supply",
        "consultant",
        "design",
        "interior",
        "party",
        "decorator"
    ],
    "wof:name":"Caprices Du Decor Inc",
    "wof:placetype":"venue"
},
  "geometry": {"coordinates":[-73.1111831665,46.0389823914],"type":"Point"}
}