{
  "type": "Feature",
  "properties": {
    "addr:full":"552 Rogers Rd York ON M6M 1B5",
    "addr:housenumber":"552",
    "addr:postcode":"m6m 1b5",
    "addr:street":"Rogers Rd",
    "iso:country":"CA",
    "sg:address":"552 Rogers Rd",
    "sg:city":"York",
    "sg:classifiers":[
        {
            "category":"Real Estate",
            "subcategory":"Real Estate Agent",
            "type":"Services"
        }
    ],
    "sg:phone":"+1 416 654 3444",
    "sg:postcode":"M6M 1B5",
    "sg:province":"ON",
    "wof:name":"Now Realty Ltd",
    "wof:placetype":"venue"
},
  "geometry": {"coordinates":[-79.470116,43.682339],"type":"Point"}
}