{
  "type": "Feature",
  "properties": {
    "addr:full":"2444 Bloor St W York ON M6S 1R2",
    "addr:housenumber":"2444",
    "addr:postcode":"m6s 1r2",
    "addr:street":"Bloor St W",
    "iso:country":"CA",
    "sg:address":"2444 Bloor St W",
    "sg:city":"York",
    "sg:classifiers":[
        {
            "category":"Restaurant",
            "type":"Food & Drink"
        }
    ],
    "sg:phone":"+1 416 604 1056",
    "sg:postcode":"M6S 1R2",
    "sg:province":"ON",
    "wof:name":"Subway Sandwiches & Salads",
    "wof:placetype":"venue"
},
  "geometry": {"coordinates":[-79.490562439,43.6479911804],"type":"Point"}
}