{
  "type": "Feature",
  "properties": {
    "addr:full":"Gloucester ON K1J 9L8",
    "addr:postcode":"k1j 9l8",
    "iso:country":"CA",
    "sg:city":"Gloucester",
    "sg:classifiers":[
        {
            "category":"Professional",
            "subcategory":"Accounting & Tax Preparation",
            "type":"Services"
        }
    ],
    "sg:phone":"+1 613 747 5060",
    "sg:postcode":"K1J 9L8",
    "sg:province":"ON",
    "sg:tags":[
        "consultant"
    ],
    "wof:name":"Pryor & Assoc",
    "wof:placetype":"venue"
},
  "geometry": {"coordinates":[-75.60520200000001,45.436081],"type":"Point"}
}