{
  "type": "Feature",
  "properties": {
    "addr:full":"351 Rue Notre-Dame N Louiseville QC J5V 1X9",
    "addr:housenumber":"351",
    "addr:postcode":"j5v 1x9",
    "addr:street":"Rue Notre-Dame N",
    "iso:country":"CA",
    "sg:address":"351 Rue Notre-Dame N",
    "sg:city":"Louiseville",
    "sg:classifiers":[
        {
            "category":"Professional",
            "subcategory":"Advertising",
            "type":"Services"
        }
    ],
    "sg:phone":"+1 819 228 9497",
    "sg:postcode":"J5V 1X9",
    "sg:province":"QC",
    "sg:tags":[
        "folding"
    ],
    "wof:name":"Pliages Maskinonge Inc",
    "wof:placetype":"venue"
},
  "geometry": {"coordinates":[-72.9375305176,46.2628860474],"type":"Point"}
}