{
  "type": "Feature",
  "properties": {
    "addr:full":"4880 Rue Hickmore Saint-Laurent QC H4T 1K6",
    "addr:housenumber":"4880",
    "addr:postcode":"h4t 1k6",
    "addr:street":"Rue Hickmore",
    "iso:country":"CA",
    "sg:address":"4880 Rue Hickmore",
    "sg:city":"Saint-Laurent",
    "sg:classifiers":[
        {
            "category":"Manufacturing",
            "subcategory":"Paper Products",
            "type":"Manufacturing & Wholesale Goods"
        }
    ],
    "sg:phone":"+1 514 345 9870",
    "sg:postcode":"H4T 1K6",
    "sg:province":"QC",
    "sg:tags":[
        "envelope"
    ],
    "wof:name":"Enveloppe Laurentide Inc",
    "wof:placetype":"venue"
},
  "geometry": {"coordinates":[-73.6961364746,45.4698677063],"type":"Point"}
}