{
  "type": "Feature",
  "properties": {
    "addr:full":"17 Mill St S Port Hope ON L1A 2S6",
    "addr:housenumber":"17",
    "addr:postcode":"l1a 2s6",
    "addr:street":"Mill St S",
    "iso:country":"CA",
    "sg:address":"17 Mill St S",
    "sg:city":"Port Hope",
    "sg:classifiers":[
        {
            "category":"Organizations",
            "subcategory":"Community Association",
            "type":"Services"
        }
    ],
    "sg:phone":"+1 905 885 5659",
    "sg:postcode":"L1A 2S6",
    "sg:province":"ON",
    "sg:tags":[
        "club"
    ],
    "wof:name":"Royal Canadian Sea Cadets",
    "wof:placetype":"venue"
},
  "geometry": {"coordinates":[-78.29141235349999,43.9500541687],"type":"Point"}
}