{
  "type": "Feature",
  "properties": {
    "addr:full":"2351 Rg 2 Sainte-Justine-DE-Newton QC J0P 1T0",
    "addr:housenumber":"2351;2",
    "addr:postcode":"j0p 1t0",
    "addr:street":"Rg",
    "iso:country":"CA",
    "sg:address":"2351 Rg 2",
    "sg:city":"Sainte-Justine-DE-Newton",
    "sg:classifiers":[
        {
            "category":"Travel",
            "subcategory":"Campground",
            "type":"Entertainment"
        }
    ],
    "sg:phone":"+1 450 764 3636",
    "sg:postcode":"J0P 1T0",
    "sg:province":"QC",
    "wof:name":"Camping Ste-Jsutine",
    "wof:placetype":"venue"
},
  "geometry": {"coordinates":[-74.40473900000001,45.373703],"type":"Point"}
}