{
  "type": "Feature",
  "properties": {
    "addr:full":"2183 Boul Des Laurentides # 220 Laval QC H7K 2J3",
    "addr:housenumber":"2183;# 220",
    "addr:postcode":"qc h7k 2j3",
    "addr:street":"Boul Des Laurentides",
    "iso:country":"CA",
    "sg:address":"2183 Boul Des Laurentides # 220",
    "sg:city":"Laval",
    "sg:classifiers":[
        {
            "category":"Health Services",
            "subcategory":"Doctor",
            "type":"Services"
        }
    ],
    "sg:phone":"+1 450 667 3368",
    "sg:postcode":"H7K 2J3",
    "sg:province":"QC",
    "sg:tags":[
        "clinic",
        "dentist"
    ],
    "wof:name":"Centre Dentaire Allain",
    "wof:placetype":"venue"
},
  "geometry": {"coordinates":[-73.736267,45.611164],"type":"Point"}
}