{
  "type": "Feature",
  "properties": {
    "addr:full":"Baie-Saint-Paul QC G3Z 2Y5",
    "addr:postcode":"g3z 2y5",
    "iso:country":"CA",
    "sg:city":"Baie-Saint-Paul",
    "sg:classifiers":[
        {
            "category":"Personal",
            "subcategory":"Beauty Salon",
            "type":"Services"
        }
    ],
    "sg:phone":"+1 418 435 2534",
    "sg:postcode":"G3Z 2Y5",
    "sg:province":"QC",
    "wof:name":"Salon Claire",
    "wof:placetype":"venue"
},
  "geometry": {"coordinates":[-73.445564,45.985046],"type":"Point"}
}