{
  "type": "Feature",
  "properties": {
    "addr:full":"1051 Sydney St Cornwall ON K6H 3K1",
    "addr:housenumber":"1051",
    "addr:postcode":"k6h 3k1",
    "addr:street":"Sydney St",
    "iso:country":"CA",
    "sg:address":"1051 Sydney St",
    "sg:city":"Cornwall",
    "sg:classifiers":[
        {
            "category":"Wholesale",
            "subcategory":"Meat",
            "type":"Manufacturing & Wholesale Goods"
        }
    ],
    "sg:phone":"+1 613 932 5881",
    "sg:postcode":"K6H 3K1",
    "sg:province":"ON",
    "wof:name":"Cardinal & Son Wholesale Meat",
    "wof:placetype":"venue"
},
  "geometry": {"coordinates":[-74.73371899999999,45.030952],"type":"Point"}
}