{
  "type": "Feature",
  "properties": {
    "iso:country":"CA",
    "sg:address":"559 Waterloo St",
    "sg:city":"London",
    "sg:classifiers":[
        {
            "category":"Health Services",
            "subcategory":"Doctor",
            "type":"Services"
        }
    ],
    "sg:phone":"+1 519 438 9921",
    "sg:postcode":"N6B 2R1",
    "sg:province":"ON",
    "sg:tags":[
        "dentist"
    ],
    "wof:name":"Fendrich, Peter DDS",
    "wof:placetype":"venue"
},
  "geometry": {"coordinates":[-81.244995,42.990269],"type":"Point"}
}