{
  "type": "Feature",
  "properties": {
    "addr:full":"2190 Warden Ave Scarborough ON M1T 1V6",
    "addr:housenumber":"2190",
    "addr:postcode":"m1t 1v6",
    "addr:street":"Warden Ave",
    "iso:country":"CA",
    "sg:address":"2190 Warden Ave",
    "sg:city":"Scarborough",
    "sg:classifiers":[
        {
            "category":"Personal",
            "subcategory":"Beauty Salon",
            "type":"Services"
        }
    ],
    "sg:phone":"+1 416 756 9088",
    "sg:postcode":"M1T 1V6",
    "sg:province":"ON",
    "wof:name":"Hairflash Unisex Hair Design",
    "wof:placetype":"venue"
},
  "geometry": {"coordinates":[-79.30819700000001,43.778912],"type":"Point"}
}