{
  "type": "Feature",
  "properties": {
    "iso:country":"CA",
    "sg:address":"306 Saskatchewan Ave E",
    "sg:city":"Portage LA Prairie",
    "sg:classifiers":[
        {
            "category":"Shopping",
            "subcategory":"Used Merchandise",
            "type":"Retail Goods"
        }
    ],
    "sg:phone":"+1 204 239 1022",
    "sg:postcode":"R1N 0K8",
    "sg:province":"MB",
    "sg:tags":[
        "second",
        "store",
        "hand"
    ],
    "wof:name":"Tricky's",
    "wof:placetype":"venue"
},
  "geometry": {"coordinates":[-98.285561,49.972973],"type":"Point"}
}