{
  "type": "Feature",
  "properties": {
    "addr:full":"2440 Ash St Vancouver BC V5Z 4J6",
    "addr:housenumber":"2440",
    "addr:postcode":"v5z 4j6",
    "addr:street":"Ash St",
    "iso:country":"CA",
    "sg:address":"2440 Ash St",
    "sg:city":"Vancouver",
    "sg:classifiers":[
        {
            "category":"Communications",
            "subcategory":"Radio Station",
            "type":"Services"
        }
    ],
    "sg:phone":"+1 604 873 2599",
    "sg:postcode":"V5Z 4J6",
    "sg:province":"BC",
    "sg:tags":[
        "company",
        "broadcasting"
    ],
    "wof:name":"Ckwx",
    "wof:placetype":"venue"
},
  "geometry": {"coordinates":[-123.117332459,49.26379776],"type":"Point"}
}