{
  "type": "Feature",
  "properties": {
    "addr:full":"71 Penmeadows Pl SE Calgary AB T2A 3P8",
    "addr:housenumber":"71",
    "addr:postcode":"t2a 3p8",
    "addr:street":"Penmeadows Pl Se",
    "iso:country":"CA",
    "sg:address":"71 Penmeadows Pl SE",
    "sg:city":"Calgary",
    "sg:classifiers":[
        {
            "category":"Building & Trades",
            "subcategory":"Construction",
            "type":"Services"
        }
    ],
    "sg:phone":"+1 403 273 8225",
    "sg:postcode":"T2A 3P8",
    "sg:province":"AB",
    "sg:tags":[
        "contractor"
    ],
    "wof:name":"Noble Homes",
    "wof:placetype":"venue"
},
  "geometry": {"coordinates":[-113.95626799999999,51.046661],"type":"Point"}
}