{
  "type": "Feature",
  "properties": {
    "addr:full":"721 Caribou St W Moose Jaw SK S6H 2K8",
    "addr:housenumber":"721",
    "addr:postcode":"s6h 2k8",
    "addr:street":"Caribou St W",
    "iso:country":"CA",
    "sg:address":"721 Caribou St W",
    "sg:city":"Moose Jaw",
    "sg:classifiers":[
        {
            "category":"Real Estate",
            "subcategory":"Developer",
            "type":"Services"
        }
    ],
    "sg:phone":"+1 306 692 8855",
    "sg:postcode":"S6H 2K8",
    "sg:province":"SK",
    "sg:tags":[
        "cemetery"
    ],
    "wof:name":"Remco Sunset Cemetery",
    "wof:placetype":"venue"
},
  "geometry": {"coordinates":[-105.553665,50.396767],"type":"Point"}
}