{
  "type": "Feature",
  "properties": {
    "addr:full":"Ottawa ON K1S 1S8",
    "addr:postcode":"k1s 1s8",
    "iso:country":"CA",
    "sg:city":"Ottawa",
    "sg:classifiers":[
        {
            "category":"Professional",
            "subcategory":"Art Services",
            "type":"Services"
        }
    ],
    "sg:phone":"+1 613 730 5120",
    "sg:postcode":"K1S 1S8",
    "sg:province":"ON",
    "sg:tags":[
        "graphic",
        "designer"
    ],
    "wof:name":"Mac Kenzie Krusberg Design",
    "wof:placetype":"venue"
},
  "geometry": {"coordinates":[-75.679878,45.392612],"type":"Point"}
}