{
  "type": "Feature",
  "properties": {
    "addr:full":"14961 Stony Plain Rd NW Edmonton AB T5P 4W1",
    "addr:housenumber":"14961",
    "addr:postcode":"t5p 4w1",
    "addr:street":"Stony Plain Rd Nw",
    "iso:country":"CA",
    "sg:address":"14961 Stony Plain Rd NW",
    "sg:city":"Edmonton",
    "sg:classifiers":[
        {
            "category":"Personal",
            "subcategory":"Beauty Salon",
            "type":"Services"
        }
    ],
    "sg:phone":"+1 780 486 7447",
    "sg:postcode":"T5P 4W1",
    "sg:province":"AB",
    "wof:name":"Ultracuts",
    "wof:placetype":"venue"
},
  "geometry": {"coordinates":[-113.58028400000001,53.541191],"type":"Point"}
}