{
  "type": "Feature",
  "properties": {
    "addr:full":"7491 Pacific Cir Mississauga ON L5T 2A4",
    "addr:housenumber":"7491",
    "addr:postcode":"l5t 2a4",
    "addr:street":"Pacific Cir",
    "iso:country":"CA",
    "sg:address":"7491 Pacific Cir",
    "sg:city":"Mississauga",
    "sg:classifiers":[
        {
            "category":"Wholesale",
            "subcategory":"Groceries",
            "type":"Manufacturing & Wholesale Goods"
        }
    ],
    "sg:phone":"+1 905 564 1710",
    "sg:postcode":"L5T 2A4",
    "sg:province":"ON",
    "sg:tags":[
        "grocer"
    ],
    "wof:name":"Harold T Griffin Inc",
    "wof:placetype":"venue"
},
  "geometry": {"coordinates":[-79.67358400000001,43.656582],"type":"Point"}
}