{
  "type": "Feature",
  "properties": {
    "addr:full":"632 Auger Ave Sudbury ON P3A 5G1",
    "addr:housenumber":"632",
    "addr:postcode":"p3a 5g1",
    "addr:street":"Auger Ave",
    "iso:country":"CA",
    "sg:address":"632 Auger Ave",
    "sg:city":"Sudbury",
    "sg:classifiers":[
        {
            "category":"Building & Trades",
            "subcategory":"Cleaning & Sanitation",
            "type":"Services"
        }
    ],
    "sg:phone":"+1 705 524 5555",
    "sg:postcode":"P3A 5G1",
    "sg:province":"ON",
    "sg:tags":[
        "janitor"
    ],
    "wof:name":"Pioneer Maintenance",
    "wof:placetype":"venue"
},
  "geometry": {"coordinates":[-80.932343,46.511318],"type":"Point"}
}