{
  "type": "Feature",
  "properties": {
    "addr:full":"4804 7E Av Montreal QC H1Y 2M7",
    "addr:housenumber":"4804",
    "addr:postcode":"h1y 2m7",
    "addr:street":"7E Av",
    "iso:country":"CA",
    "sg:address":"4804 7E Av",
    "sg:city":"Montreal",
    "sg:classifiers":[
        {
            "category":"Retail",
            "subcategory":"Portrait Studio",
            "type":"Services"
        }
    ],
    "sg:phone":"+1 514 523 0107",
    "sg:postcode":"H1Y 2M7",
    "sg:province":"QC",
    "sg:tags":[
        "photographer"
    ],
    "wof:name":"Laliberte, Robert",
    "wof:placetype":"venue"
},
  "geometry": {"coordinates":[-73.56785600000001,45.546638],"type":"Point"}
}