{
  "type": "Feature",
  "properties": {
    "addr:full":"478 Av Victoria Saint-Lambert QC J4P 2J4",
    "addr:housenumber":"478",
    "addr:postcode":"j4p 2j4",
    "addr:street":"Av Victoria",
    "iso:country":"CA",
    "sg:address":"478 Av Victoria",
    "sg:city":"Saint-Lambert",
    "sg:classifiers":[
        {
            "category":"Food & Beverages",
            "subcategory":"Bakery",
            "type":"Retail Goods"
        }
    ],
    "sg:phone":"+1 450 671 6042",
    "sg:postcode":"J4P 2J4",
    "sg:province":"QC",
    "sg:tags":[
        "baker"
    ],
    "wof:name":"Patisserie Au Beau Tilleul",
    "wof:placetype":"venue"
},
  "geometry": {"coordinates":[-73.511612,45.501682],"type":"Point"}
}