{
  "type": "Feature",
  "properties": {
    "addr:full":"565 Boul Saint-Martin O Laval QC H7M 1Y9",
    "addr:housenumber":"565",
    "addr:postcode":"h7m 1y9",
    "addr:street":"Boul Saint-Martin O",
    "iso:country":"CA",
    "sg:address":"565 Boul Saint-Martin O",
    "sg:city":"Laval",
    "sg:classifiers":[
        {
            "category":"Shopping",
            "subcategory":"Hobbies, Toys, & Games",
            "type":"Retail Goods"
        }
    ],
    "sg:phone":"+1 450 669 9399",
    "sg:postcode":"H7M 1Y9",
    "sg:province":"QC",
    "sg:tags":[
        "tea",
        "coffee",
        "ceramic"
    ],
    "wof:name":"Ceramic Cafe Studio Inc",
    "wof:placetype":"venue"
},
  "geometry": {"coordinates":[-73.7132034302,45.5763816833],"type":"Point"}
}