{
  "type": "Feature",
  "properties": {
    "addr:full":"621 Bathurst St Toronto ON M5S 2R2",
    "addr:housenumber":"621",
    "addr:postcode":"m5s 2r2",
    "addr:street":"Bathurst St",
    "iso:country":"CA",
    "sg:address":"621 Bathurst St",
    "sg:city":"Toronto",
    "sg:classifiers":[
        {
            "category":"Food & Beverages",
            "subcategory":"Groceries & Convenience Stores",
            "type":"Retail Goods"
        }
    ],
    "sg:phone":"+1 416 532 6166",
    "sg:postcode":"M5S 2R2",
    "sg:province":"ON",
    "sg:tags":[
        "variety"
    ],
    "wof:name":"Three Star Variety",
    "wof:placetype":"venue"
},
  "geometry": {"coordinates":[-79.4089355469,43.6599998474],"type":"Point"}
}