{
  "type": "Feature",
  "properties": {
    "addr:full":"839 Rue Provost Lachine QC H8S 1M8",
    "addr:housenumber":"839",
    "addr:postcode":"h8s 1m8",
    "addr:street":"Rue Provost",
    "iso:country":"CA",
    "sg:address":"839 Rue Provost",
    "sg:city":"Lachine",
    "sg:classifiers":[
        {
            "category":"Health Services",
            "subcategory":"Doctor",
            "type":"Services"
        }
    ],
    "sg:phone":"+1 514 637 8771",
    "sg:postcode":"H8S 1M8",
    "sg:province":"QC",
    "sg:tags":[
        "physician",
        "surgeon"
    ],
    "wof:name":"Drapeau, Gaston MD",
    "wof:placetype":"venue"
},
  "geometry": {"coordinates":[-73.6713180542,45.4417572021],"type":"Point"}
}