{
  "type": "Feature",
  "properties": {
    "addr:full":"1162 Dufferin St Toronto ON M6H 4B8",
    "addr:housenumber":"1162",
    "addr:postcode":"m6h 4b8",
    "addr:street":"Dufferin St",
    "iso:country":"CA",
    "sg:address":"1162 Dufferin St",
    "sg:city":"Toronto",
    "sg:classifiers":[
        {
            "category":"Personal",
            "subcategory":"Beauty Salon",
            "type":"Services"
        }
    ],
    "sg:phone":"+1 416 588 7827",
    "sg:postcode":"M6H 4B8",
    "sg:province":"ON",
    "wof:name":"Uni Star Hair Studio",
    "wof:placetype":"venue"
},
  "geometry": {"coordinates":[-79.437286,43.663952],"type":"Point"}
}