{
  "type": "Feature",
  "properties": {
    "iso:country":"CA",
    "sg:address":"General Delivery",
    "sg:city":"Stauffer",
    "sg:classifiers":[
        {
            "category":"Mining & Drilling",
            "type":"Manufacturing & Wholesale Goods"
        }
    ],
    "sg:phone":"+1 403 746 2606",
    "sg:postcode":"T0M 1W0",
    "sg:province":"AB",
    "sg:tags":[
        "company",
        "oil"
    ],
    "wof:name":"Apache Canada Ltd",
    "wof:placetype":"venue"
},
  "geometry": {"coordinates":[-114.596687317,52.1633605957],"type":"Point"}
}