{
  "type": "Feature",
  "properties": {
    "addr:full":"St Catharines ON L2M 3Y2",
    "addr:postcode":"l2m 3y2",
    "iso:country":"CA",
    "sg:city":"St Catharines",
    "sg:classifiers":[
        {
            "category":"Building & Trades",
            "subcategory":"Construction",
            "type":"Services"
        }
    ],
    "sg:phone":"+1 905 641 2505",
    "sg:postcode":"L2M 3Y2",
    "sg:province":"ON",
    "sg:tags":[
        "equipment",
        "bathroom",
        "kitchen",
        "remodeling",
        "cabinet"
    ],
    "wof:name":"Tuckers Kitchen & Bath Design",
    "wof:placetype":"venue"
},
  "geometry": {"coordinates":[-79.21019,43.172676],"type":"Point"}
}