{
  "type": "Feature",
  "properties": {
    "addr:full":"4 Rice's Lane Point Leamington NL A0H 1Z0",
    "addr:housenumber":"4",
    "addr:postcode":"a0h 1z0",
    "addr:street":"Rice'S Lane",
    "iso:country":"CA",
    "sg:address":"4 Rice's Lane",
    "sg:city":"Point Leamington",
    "sg:classifiers":[
        {
            "category":"Education",
            "subcategory":"School",
            "type":"Public Place"
        }
    ],
    "sg:phone":"+1 709 484 3432",
    "sg:postcode":"A0H 1Z0",
    "sg:province":"NL",
    "wof:name":"Point Leamington Academy",
    "wof:placetype":"venue"
},
  "geometry": {"coordinates":[-55.406029,49.319309],"type":"Point"}
}