{
  "type": "Feature",
  "properties": {
    "addr:full":"55 Bellevue St Portneuf QC G0A 2Y0",
    "addr:housenumber":"55",
    "addr:postcode":"g0a 2y0",
    "addr:street":"Bellevue St",
    "iso:country":"CA",
    "sg:address":"55 Bellevue St",
    "sg:city":"Portneuf",
    "sg:classifiers":[
        {
            "category":"Building & Trades",
            "subcategory":"Construction",
            "type":"Services"
        }
    ],
    "sg:phone":"+1 418 286 3838",
    "sg:postcode":"G0A 2Y0",
    "sg:province":"QC",
    "sg:tags":[
        "general",
        "contractor"
    ],
    "wof:name":"Larochelle, Ghislain",
    "wof:placetype":"venue"
},
  "geometry": {"coordinates":[-71.891228,46.693104],"type":"Point"}
}