{
  "type": "Feature",
  "properties": {
    "addr:full":"121 Roberts Cres Kitchener ON N2E 1A6",
    "addr:housenumber":"121",
    "addr:postcode":"n2e 1a6",
    "addr:street":"Roberts Cres",
    "iso:country":"CA",
    "sg:address":"121 Roberts Cres",
    "sg:city":"Kitchener",
    "sg:classifiers":[
        {
            "category":"Real Estate",
            "subcategory":"Real Estate Agent",
            "type":"Services"
        }
    ],
    "sg:phone":"+1 519 579 9413",
    "sg:postcode":"N2E 1A6",
    "sg:province":"ON",
    "sg:tags":[
        "management"
    ],
    "wof:name":"Property Rental Ctr",
    "wof:placetype":"venue"
},
  "geometry": {"coordinates":[-80.4860076904,43.4223899841],"type":"Point"}
}