{
  "type": "Feature",
  "properties": {
    "addr:full":"1310 Av Greene Westmount QC H3Z 2B2",
    "addr:housenumber":"1310",
    "addr:postcode":"h3z 2b2",
    "addr:street":"Av Greene",
    "iso:country":"CA",
    "sg:address":"1310 Av Greene",
    "sg:city":"Westmount",
    "sg:classifiers":[
        {
            "category":"Communications",
            "subcategory":"Radio Station",
            "type":"Services"
        }
    ],
    "sg:phone":"+1 514 931 4487",
    "sg:postcode":"H3Z 2B2",
    "sg:province":"QC",
    "sg:tags":[
        "company",
        "broadcasting",
        "publicity"
    ],
    "wof:name":"Team 990",
    "wof:placetype":"venue"
},
  "geometry": {"coordinates":[-73.5900344849,45.48695755],"type":"Point"}
}