{
  "type": "Feature",
  "properties": {
    "addr:full":"1 Eldorado Crt North York ON M3J 1W8",
    "addr:housenumber":"1",
    "addr:postcode":"m3j 1w8",
    "addr:street":"Eldorado Crt",
    "iso:country":"CA",
    "sg:address":"1 Eldorado Crt",
    "sg:city":"North York",
    "sg:classifiers":[
        {
            "category":"Building & Trades",
            "subcategory":"Construction",
            "type":"Services"
        }
    ],
    "sg:phone":"+1 416 635 0095",
    "sg:postcode":"M3J 1W8",
    "sg:province":"ON",
    "sg:tags":[
        "carpenter"
    ],
    "wof:name":"Creative Carpentry",
    "wof:placetype":"venue"
},
  "geometry": {"coordinates":[-79.49902299999999,43.74802],"type":"Point"}
}