{
  "type": "Feature",
  "properties": {
    "addr:full":"314 South Railway St SE Medicine Hat AB T1A 2V4",
    "addr:housenumber":"314",
    "addr:postcode":"t1a 2v4",
    "addr:street":"South Railway St Se",
    "iso:country":"CA",
    "sg:address":"314 South Railway St SE",
    "sg:city":"Medicine Hat",
    "sg:classifiers":[
        {
            "category":"Shopping",
            "subcategory":"Clothing, Apparel, & Fashions",
            "type":"Retail Goods"
        }
    ],
    "sg:phone":"+1 403 526 4520",
    "sg:postcode":"T1A 2V4",
    "sg:province":"AB",
    "sg:tags":[
        "shop",
        "bridal"
    ],
    "wof:name":"Magic Moments Wedding Rentals",
    "wof:placetype":"venue"
},
  "geometry": {"coordinates":[-110.673561096,50.0402679443],"type":"Point"}
}