{
  "type": "Feature",
  "properties": {
    "addr:full":"214 Silvercreek Pky N Guelph ON N1H 7P8",
    "addr:housenumber":"214",
    "addr:postcode":"n1h 7p8",
    "addr:street":"Silvercreek Pky N",
    "iso:country":"CA",
    "sg:address":"214 Silvercreek Pky N",
    "sg:city":"Guelph",
    "sg:classifiers":[
        {
            "category":"Shopping",
            "subcategory":"Department Store",
            "type":"Retail Goods"
        }
    ],
    "sg:phone":"+1 519 821 9994",
    "sg:postcode":"N1H 7P8",
    "sg:province":"ON",
    "sg:tags":[
        "shop",
        "second",
        "hand"
    ],
    "wof:name":"Value Village Stores Ltd",
    "wof:placetype":"venue"
},
  "geometry": {"coordinates":[-80.2845687866,43.5427742004],"type":"Point"}
}