{
  "type": "Feature",
  "properties": {
    "addr:full":"99 Railway Ave Scandia AB T0J 2Z0",
    "addr:housenumber":"99",
    "addr:postcode":"t0j 2z0",
    "addr:street":"Railway Ave",
    "iso:country":"CA",
    "sg:address":"99 Railway Ave",
    "sg:city":"Scandia",
    "sg:classifiers":[
        {
            "category":"Wholesale",
            "subcategory":"Groceries",
            "type":"Manufacturing & Wholesale Goods"
        }
    ],
    "sg:phone":"+1 403 362 3951",
    "sg:postcode":"T0J 2Z0",
    "sg:province":"AB",
    "sg:tags":[
        "honey"
    ],
    "wof:name":"Scandia Honey Corp",
    "wof:placetype":"venue"
},
  "geometry": {"coordinates":[-112.046211,50.276749],"type":"Point"}
}