{
  "type": "Feature",
  "properties": {
    "iso:country":"CA",
    "sg:city":"Greenfield Park",
    "sg:classifiers":[
        {
            "category":"Building & Trades",
            "subcategory":"Construction",
            "type":"Services"
        }
    ],
    "sg:phone":"+1 450 923 1610",
    "sg:postcode":"J4V 2K4",
    "sg:province":"QC",
    "sg:tags":[
        "masonry",
        "contractor"
    ],
    "wof:name":"Maconnerie Au Niveau Inc",
    "wof:placetype":"venue"
},
  "geometry": {"coordinates":[-73.492584,45.492989],"type":"Point"}
}