{
  "type": "Feature",
  "properties": {
    "addr:full":"5810 58 St Taber AB T1G 1Y2",
    "addr:housenumber":"5810",
    "addr:postcode":"t1g 1y2",
    "addr:street":"58 St",
    "iso:country":"CA",
    "sg:address":"5810 58 St",
    "sg:city":"Taber",
    "sg:classifiers":[
        {
            "category":"Mining & Drilling",
            "type":"Manufacturing & Wholesale Goods"
        }
    ],
    "sg:phone":"+1 403 223 9529",
    "sg:postcode":"T1G 1Y2",
    "sg:province":"AB",
    "sg:tags":[
        "field",
        "oil"
    ],
    "wof:name":"Waterflood Service & Sales Ltd",
    "wof:placetype":"venue"
},
  "geometry": {"coordinates":[-112.13640594500001,49.7945823669],"type":"Point"}
}