{
  "type": "Feature",
  "properties": {
    "addr:full":"62724 Airport Rd Hope BC V0X 1L2",
    "addr:housenumber":"62724",
    "addr:postcode":"v0x 1l2",
    "addr:street":"Airport Rd",
    "iso:country":"CA",
    "sg:address":"62724 Airport Rd",
    "sg:city":"Hope",
    "sg:classifiers":[
        {
            "category":"Government",
            "subcategory":"Office",
            "type":"Public Place"
        }
    ],
    "sg:phone":"+1 604 869 2819",
    "sg:postcode":"V0X 1L2",
    "sg:province":"BC",
    "sg:tags":[
        "village"
    ],
    "wof:name":"Hope Regional Airpark",
    "wof:placetype":"venue"
},
  "geometry": {"coordinates":[-121.493439,49.370022],"type":"Point"}
}