{
  "type": "Feature",
  "properties": {
    "iso:country":"CA",
    "sg:address":"665 8 St SW # 21112",
    "sg:city":"Calgary",
    "sg:classifiers":[
        {
            "category":"Professional",
            "subcategory":"Credit Reporting & Collection",
            "type":"Services"
        }
    ],
    "sg:phone":"+1 403 262 8144",
    "sg:postcode":"T2P 3K7",
    "sg:province":"AB",
    "sg:tags":[
        "agency"
    ],
    "wof:name":"K N Hall & Assoc Ltd",
    "wof:placetype":"venue"
},
  "geometry": {"coordinates":[-114.081359863,51.0473747253],"type":"Point"}
}