{
  "type": "Feature",
  "properties": {
    "addr:full":"Rimouski QC G5L 5J2",
    "addr:postcode":"g5l 5j2",
    "iso:country":"CA",
    "sg:city":"Rimouski",
    "sg:classifiers":[
        {
            "category":"Professional",
            "subcategory":"Business Services",
            "type":"Services"
        }
    ],
    "sg:phone":"+1 418 722 0022",
    "sg:postcode":"G5L 5J2",
    "sg:province":"QC",
    "sg:tags":[
        "appraiser"
    ],
    "wof:name":"Dionne, Claude",
    "wof:placetype":"venue"
},
  "geometry": {"coordinates":[-68.52417800000001,48.449169],"type":"Point"}
}