{
  "type": "Feature",
  "properties": {
    "addr:full":"100 Boul Sir-Wilfrid-Laurier Beloeil QC J3G 4G3",
    "addr:housenumber":"100",
    "addr:postcode":"j3g 4g3",
    "addr:street":"Boul Sir-Wilfrid-Laurier",
    "iso:country":"CA",
    "sg:address":"100 Boul Sir-Wilfrid-Laurier",
    "sg:city":"Beloeil",
    "sg:classifiers":[
        {
            "category":"Home & Garden",
            "subcategory":"Building Materials",
            "type":"Retail Goods"
        }
    ],
    "sg:phone":"+1 450 467 9475",
    "sg:postcode":"J3G 4G3",
    "sg:province":"QC",
    "sg:tags":[
        "glass",
        "window",
        "plate"
    ],
    "wof:name":"Lebeau Vitres D'Autos",
    "wof:placetype":"venue"
},
  "geometry": {"coordinates":[-73.21674299999999,45.550835],"type":"Point"}
}