{
  "type": "Feature",
  "properties": {
    "addr:full":"402 Albert St Radisson SK S0K 3L0",
    "addr:housenumber":"402",
    "addr:postcode":"s0k 3l0",
    "addr:street":"Albert St",
    "iso:country":"CA",
    "sg:address":"402 Albert St",
    "sg:city":"Radisson",
    "sg:classifiers":[
        {
            "category":"Organizations",
            "subcategory":"Religious Organization",
            "type":"Services"
        }
    ],
    "sg:phone":"+1 306 827 2265",
    "sg:postcode":"S0K 3L0",
    "sg:province":"SK",
    "sg:tags":[
        "church"
    ],
    "wof:name":"St Paul Ev Lutheran Church",
    "wof:placetype":"venue"
},
  "geometry": {"coordinates":[-107.398170471,52.4634971619],"type":"Point"}
}