{
  "type": "Feature",
  "properties": {
    "addr:full":"39 Mississaga St W Orillia ON L3V 3A5",
    "addr:housenumber":"39",
    "addr:postcode":"l3v 3a5",
    "addr:street":"Mississaga St W",
    "iso:country":"CA",
    "sg:address":"39 Mississaga St W",
    "sg:city":"Orillia",
    "sg:classifiers":[
        {
            "category":"Wholesale",
            "subcategory":"Meat",
            "type":"Manufacturing & Wholesale Goods"
        }
    ],
    "sg:phone":"+1 705 326 3641",
    "sg:postcode":"L3V 3A5",
    "sg:province":"ON",
    "sg:tags":[
        "product"
    ],
    "wof:name":"Fred's Meat Market",
    "wof:placetype":"venue"
},
  "geometry": {"coordinates":[-79.4207077026,44.6077079773],"type":"Point"}
}