{
  "type": "Feature",
  "properties": {
    "addr:full":"545 Ch Sainte-Foy Quebec QC G1S 2J9",
    "addr:housenumber":"545",
    "addr:postcode":"g1s 2j9",
    "addr:street":"Ch Sainte-Foy",
    "iso:country":"CA",
    "sg:address":"545 Ch Sainte-Foy",
    "sg:city":"Quebec",
    "sg:classifiers":[
        {
            "category":"Social Services",
            "subcategory":"Child Care",
            "type":"Services"
        }
    ],
    "sg:phone":"+1 418 527 6627",
    "sg:postcode":"G1S 2J9",
    "sg:province":"QC",
    "wof:name":"Cpe Sophie",
    "wof:placetype":"venue"
},
  "geometry": {"coordinates":[-71.2359237671,46.802318573],"type":"Point"}
}