{
  "type": "Feature",
  "properties": {
    "addr:full":"Toronto ON M4C 1J8",
    "addr:postcode":"m4c 1j8",
    "iso:country":"CA",
    "sg:city":"Toronto",
    "sg:classifiers":[
        {
            "category":"Education",
            "subcategory":"School",
            "type":"Public Place"
        }
    ],
    "sg:phone":"+1 416 615 0004",
    "sg:postcode":"M4C 1J8",
    "sg:province":"ON",
    "sg:tags":[
        "instruction",
        "driving"
    ],
    "wof:name":"Winston's Driving Academy",
    "wof:placetype":"venue"
},
  "geometry": {"coordinates":[-79.312843,43.685516],"type":"Point"}
}