{
  "type": "Feature",
  "properties": {
    "addr:full":"8000 Av Des Eglises Charny QC G6X 1X4",
    "addr:postcode":"g6x 1x4",
    "addr:street":"Av Des Eglises",
    "iso:country":"CA",
    "sg:address":"8000 Av Des Eglises",
    "sg:city":"Charny",
    "sg:classifiers":[
        {
            "category":"Restaurant",
            "type":"Food & Drink"
        }
    ],
    "sg:phone":"+1 418 832 2962",
    "sg:postcode":"G6X 1X4",
    "sg:province":"QC",
    "wof:name":"Mc Donald's",
    "wof:placetype":"venue"
},
  "geometry": {"coordinates":[-71.2668914795,46.7225379944],"type":"Point"}
}