{
  "type": "Feature",
  "properties": {
    "addr:full":"137 City Rd Saint John NB E2L 3M6",
    "addr:housenumber":"137",
    "addr:postcode":"nb e2l 3m6",
    "addr:street":"City Rd",
    "iso:country":"CA",
    "sg:address":"137 City Rd",
    "sg:city":"Saint John",
    "sg:classifiers":[
        {
            "category":"Retail",
            "subcategory":"Auto Repair",
            "type":"Services"
        }
    ],
    "sg:phone":"+1 506 642 7995",
    "sg:postcode":"E2L 3M6",
    "sg:province":"NB",
    "sg:tags":[
        "repairing",
        "automobile"
    ],
    "wof:name":"Legere's Garage Ltd",
    "wof:placetype":"venue"
},
  "geometry": {"coordinates":[-66.058441,45.280739],"type":"Point"}
}