{
  "type": "Feature",
  "properties": {
    "addr:full":"221 Ch Freeman Hull QC J8Z 2A8",
    "addr:housenumber":"221",
    "addr:postcode":"j8z 2a8",
    "addr:street":"Ch Freeman",
    "iso:country":"CA",
    "sg:address":"221 Ch Freeman",
    "sg:city":"Hull",
    "sg:classifiers":[
        {
            "category":"Health Services",
            "subcategory":"Doctor",
            "type":"Services"
        }
    ],
    "sg:phone":"+1 819 775 5005",
    "sg:postcode":"J8Z 2A8",
    "sg:province":"QC",
    "sg:tags":[
        "physician",
        "surgeon"
    ],
    "wof:name":"Clinique DE Physiotherapie",
    "wof:placetype":"venue"
},
  "geometry": {"coordinates":[-75.747665,45.47221],"type":"Point"}
}