{
  "type": "Feature",
  "properties": {
    "addr:full":"St Albert AB T8N 5Z1",
    "addr:postcode":"t8n 5z1",
    "iso:country":"CA",
    "sg:city":"St Albert",
    "sg:classifiers":[
        {
            "category":"Health Services",
            "subcategory":"Doctor",
            "type":"Services"
        }
    ],
    "sg:phone":"+1 780 458 7040",
    "sg:postcode":"T8N 5Z1",
    "sg:province":"AB",
    "sg:tags":[
        "dentist"
    ],
    "wof:name":"Lacombe Park Dental",
    "wof:placetype":"venue"
},
  "geometry": {"coordinates":[-113.628242493,53.64894104],"type":"Point"}
}