{
  "type": "Feature",
  "properties": {
    "iso:country":"CA",
    "sg:address":"965 Boul Cure-Labelle # H",
    "sg:city":"Laval",
    "sg:classifiers":[
        {
            "category":"Shopping",
            "subcategory":"Optical Goods",
            "type":"Retail Goods"
        }
    ],
    "sg:phone":"+1 450 688 8864",
    "sg:postcode":"H7V 2V7",
    "sg:province":"QC",
    "sg:tags":[
        "optician"
    ],
    "wof:name":"Henault-Verdon",
    "wof:placetype":"venue"
},
  "geometry": {"coordinates":[-73.749206543,45.542011261],"type":"Point"}
}