{
  "type": "Feature",
  "properties": {
    "addr:full":"1505 97 Ave Dawson Creek BC V1G 1N6",
    "addr:housenumber":"1505",
    "addr:postcode":"v1g 1n6",
    "addr:street":"97 Ave",
    "iso:country":"CA",
    "sg:address":"1505 97 Ave",
    "sg:city":"Dawson Creek",
    "sg:classifiers":[
        {
            "category":"Freight",
            "type":"Transportation"
        }
    ],
    "sg:phone":"+1 250 782 1122",
    "sg:postcode":"V1G 1N6",
    "sg:province":"BC",
    "sg:tags":[
        "trucking"
    ],
    "wof:name":"Byers Transportation Systems",
    "wof:placetype":"venue"
},
  "geometry": {"coordinates":[-120.24433136,55.7652015686],"type":"Point"}
}