{
  "type": "Feature",
  "properties": {
    "addr:full":"Calgary AB T2A 6M6",
    "addr:postcode":"t2a 6m6",
    "iso:country":"CA",
    "sg:city":"Calgary",
    "sg:classifiers":[
        {
            "category":"Autos & Motor Vehicles",
            "subcategory":"Auto Supplies",
            "type":"Retail Goods"
        }
    ],
    "sg:phone":"+1 403 273 7370",
    "sg:postcode":"T2A 6M6",
    "sg:province":"AB",
    "sg:tags":[
        "automobile",
        "parts"
    ],
    "wof:name":"Parts Unlimited",
    "wof:placetype":"venue"
},
  "geometry": {"coordinates":[-113.98612199999999,51.058414],"type":"Point"}
}