{
  "type": "Feature",
  "properties": {
    "addr:full":"2020 Van Egmond Pl Regina SK S4N 7L6",
    "addr:housenumber":"2020",
    "addr:postcode":"s4n 7l6",
    "addr:street":"Van Egmond Pl",
    "iso:country":"CA",
    "sg:address":"2020 Van Egmond Pl",
    "sg:city":"Regina",
    "sg:classifiers":[
        {
            "category":"Organizations",
            "subcategory":"Religious Organization",
            "type":"Services"
        }
    ],
    "sg:phone":"+1 306 584 5300",
    "sg:postcode":"S4N 7L6",
    "sg:province":"SK",
    "sg:tags":[
        "church"
    ],
    "wof:name":"Jehovah's Witnesses",
    "wof:placetype":"venue"
},
  "geometry": {"coordinates":[-104.567993164,50.4462394714],"type":"Point"}
}