{
  "type": "Feature",
  "properties": {
    "addr:full":"642 26th Cres North Vancouver BC V7N 4J6",
    "addr:housenumber":"642",
    "addr:postcode":"v7n 4j6",
    "addr:street":"26Th Cres",
    "iso:country":"CA",
    "sg:address":"642 26th Cres",
    "sg:city":"North Vancouver",
    "sg:classifiers":[
        {
            "category":"Retail",
            "subcategory":"Veterinary Services",
            "type":"Services"
        }
    ],
    "sg:phone":"+1 604 986 1687",
    "sg:postcode":"V7N 4J6",
    "sg:province":"BC",
    "sg:tags":[
        "veterinarian"
    ],
    "wof:name":"Harbourside Veterinary House",
    "wof:placetype":"venue"
},
  "geometry": {"coordinates":[-123.05571,49.333103],"type":"Point"}
}