{
  "type": "Feature",
  "properties": {
    "addr:full":"1855 Ness Ave Winnipeg MB R3J 0Y5",
    "addr:housenumber":"1855",
    "addr:postcode":"r3j 0y5",
    "addr:street":"Ness Ave",
    "iso:country":"CA",
    "sg:address":"1855 Ness Ave",
    "sg:city":"Winnipeg",
    "sg:classifiers":[
        {
            "category":"Professional",
            "subcategory":"Business Services",
            "type":"Services"
        }
    ],
    "sg:phone":"+1 204 896 7858",
    "sg:postcode":"R3J 0Y5",
    "sg:province":"MB",
    "sg:tags":[
        "embroidery"
    ],
    "wof:name":"A Brick Shirt House",
    "wof:placetype":"venue"
},
  "geometry": {"coordinates":[-97.216103,49.884193],"type":"Point"}
}