{
  "type": "Feature",
  "properties": {
    "addr:full":"27 Dales Dr Drayton ON N0G 1P0",
    "addr:housenumber":"27",
    "addr:postcode":"n0g 1p0",
    "addr:street":"Dales Dr",
    "iso:country":"CA",
    "sg:address":"27 Dales Dr",
    "sg:city":"Drayton",
    "sg:classifiers":[
        {
            "category":"Building & Trades",
            "subcategory":"Construction",
            "type":"Services"
        }
    ],
    "sg:phone":"+1 519 638 3240",
    "sg:postcode":"N0G 1P0",
    "sg:province":"ON",
    "sg:tags":[
        "contractor"
    ],
    "wof:name":"Paul Franklin Contracting",
    "wof:placetype":"venue"
},
  "geometry": {"coordinates":[-80.674331665,43.7478179932],"type":"Point"}
}