{
  "type": "Feature",
  "properties": {
    "iso:country":"CA",
    "sg:address":"908 Royal York Rd",
    "sg:city":"Etobicoke",
    "sg:classifiers":[
        {
            "category":"Health Services",
            "subcategory":"Doctor",
            "type":"Services"
        }
    ],
    "sg:phone":"+1 416 239 8896",
    "sg:postcode":"M8Y 2V7",
    "sg:province":"ON",
    "sg:tags":[
        "physician",
        "surgeon"
    ],
    "wof:name":"Zee, Allen MD",
    "wof:placetype":"venue"
},
  "geometry": {"coordinates":[-79.51086425779999,43.6457672119],"type":"Point"}
}