{
  "type": "Feature",
  "properties": {
    "addr:full":"755 Finlayson St Victoria BC V8T 4W4",
    "addr:housenumber":"755",
    "addr:postcode":"v8t 4w4",
    "addr:street":"Finlayson St",
    "iso:country":"CA",
    "sg:address":"755 Finlayson St",
    "sg:city":"Victoria",
    "sg:classifiers":[
        {
            "category":"Shopping",
            "subcategory":"Department Store",
            "type":"Retail Goods"
        }
    ],
    "sg:phone":"+1 250 381 9190",
    "sg:postcode":"V8T 4W4",
    "sg:province":"BC",
    "wof:name":"Pier 1 Imports",
    "wof:placetype":"venue"
},
  "geometry": {"coordinates":[-123.36850699999999,48.445187],"type":"Point"}
}