{
  "type": "Feature",
  "properties": {
    "addr:full":"2002 Boul Des Chutes Beauport QC G1C 8A7",
    "addr:housenumber":"2002",
    "addr:postcode":"qc g1c 8a7",
    "addr:street":"Boul Des Chutes",
    "iso:country":"CA",
    "sg:address":"2002 Boul Des Chutes",
    "sg:city":"Beauport",
    "sg:classifiers":[
        {
            "category":"Health Services",
            "subcategory":"Nursing And Care Facility",
            "type":"Services"
        }
    ],
    "sg:phone":"+1 418 663 3300",
    "sg:postcode":"G1C 8A7",
    "sg:province":"QC",
    "sg:tags":[
        "home",
        "retirement",
        "community"
    ],
    "wof:name":"Manoir DE Courville",
    "wof:placetype":"venue"
},
  "geometry": {"coordinates":[-71.1643753052,46.8785591125],"type":"Point"}
}