{
  "type": "Feature",
  "properties": {
    "iso:country":"CA",
    "sg:address":"3330 157 Rte",
    "sg:city":"Notre-Dame-Du-Mont-Carmel",
    "sg:classifiers":[
        {
            "category":"Home & Garden",
            "subcategory":"Carpets & Floor Coverings",
            "type":"Retail Goods"
        }
    ],
    "sg:phone":"+1 819 379 2202",
    "sg:postcode":"G0X 3J0",
    "sg:province":"QC",
    "sg:tags":[
        "material"
    ],
    "wof:name":"St-Cyr Rene Inc",
    "wof:placetype":"venue"
},
  "geometry": {"coordinates":[-69.84530639650001,47.4493675232],"type":"Point"}
}