{
  "type": "Feature",
  "properties": {
    "addr:full":"77 Carleton St Digby NS B0V 1A0",
    "addr:housenumber":"77",
    "addr:postcode":"b0v 1a0",
    "addr:street":"Carleton St",
    "iso:country":"CA",
    "sg:address":"77 Carleton St",
    "sg:city":"Digby",
    "sg:classifiers":[
        {
            "category":"Marine",
            "type":"Transportation"
        }
    ],
    "sg:phone":"+1 902 245 5652",
    "sg:postcode":"B0V 1A0",
    "sg:province":"NS",
    "sg:tags":[
        "surveyor"
    ],
    "wof:name":"Coastal Marine Surveys",
    "wof:placetype":"venue"
},
  "geometry": {"coordinates":[-65.76532,44.626305],"type":"Point"}
}