{
  "type": "Feature",
  "properties": {
    "addr:full":"Vanier QC G1M 3J3",
    "addr:postcode":"g1m 3j3",
    "iso:country":"CA",
    "sg:city":"Vanier",
    "sg:classifiers":[
        {
            "category":"Retail",
            "subcategory":"Auto Rental",
            "type":"Services"
        }
    ],
    "sg:phone":"+1 418 687 2483",
    "sg:postcode":"G1M 3J3",
    "sg:province":"QC",
    "sg:tags":[
        "renting",
        "truck",
        "leasing"
    ],
    "wof:name":"Location DE Camions Ryder Du",
    "wof:placetype":"venue"
},
  "geometry": {"coordinates":[-71.2692108154,46.8203887939],"type":"Point"}
}