{
  "type": "Feature",
  "properties": {
    "addr:full":"157 Rue Jean-Juneau Saint-Augustin-DE-Desmaures QC G3A 2W1",
    "addr:housenumber":"157",
    "addr:postcode":"g3a 2w1",
    "addr:street":"Rue Jean-Juneau",
    "iso:country":"CA",
    "sg:address":"157 Rue Jean-Juneau",
    "sg:city":"Saint-Augustin-DE-Desmaures",
    "sg:classifiers":[
        {
            "category":"Restaurant",
            "type":"Food & Drink"
        }
    ],
    "sg:phone":"+1 418 878 3394",
    "sg:postcode":"G3A 2W1",
    "sg:province":"QC",
    "wof:name":"LA Resto Traitaur",
    "wof:placetype":"venue"
},
  "geometry": {"coordinates":[-71.45263671879999,46.7413482666],"type":"Point"}
}