{
  "type": "Feature",
  "properties": {
    "addr:full":"Surrey BC V3T 5R3",
    "addr:postcode":"v3t 5r3",
    "iso:country":"CA",
    "sg:city":"Surrey",
    "sg:classifiers":[
        {
            "category":"Professional",
            "subcategory":"Lawyer & Legal Services",
            "type":"Services"
        }
    ],
    "sg:phone":"+1 604 588 9321",
    "sg:postcode":"V3T 5R3",
    "sg:province":"BC",
    "sg:tags":[
        "attorney"
    ],
    "wof:name":"Jaffer, Jalal A",
    "wof:placetype":"venue"
},
  "geometry": {"coordinates":[-122.830215,49.105179],"type":"Point"}
}