{
  "type": "Feature",
  "properties": {
    "addr:full":"Leduc AB T9E 6M8",
    "addr:postcode":"t9e 6m8",
    "iso:country":"CA",
    "sg:city":"Leduc",
    "sg:classifiers":[
        {
            "category":"Retail",
            "subcategory":"Auto Repair",
            "type":"Services"
        }
    ],
    "sg:phone":"+1 780 986 6836",
    "sg:postcode":"T9E 6M8",
    "sg:province":"AB",
    "sg:tags":[
        "body",
        "automobile",
        "painting"
    ],
    "wof:name":"Dale's Autobody",
    "wof:placetype":"venue"
},
  "geometry": {"coordinates":[-113.548569,53.259377],"type":"Point"}
}