{
  "type": "Feature",
  "properties": {
    "addr:full":"5418 97 St NW # 200 Edmonton AB T6E 5C1",
    "addr:housenumber":"5418",
    "addr:postcode":"t6e 5c1",
    "addr:street":"97 St Nw # 200",
    "iso:country":"CA",
    "sg:address":"5418 97 St NW # 200",
    "sg:city":"Edmonton",
    "sg:classifiers":[
        {
            "category":"Insurance",
            "subcategory":"Insurance Agent",
            "type":"Services"
        }
    ],
    "sg:phone":"+1 780 448 1637",
    "sg:postcode":"T6E 5C1",
    "sg:province":"AB",
    "wof:name":"Highland Financial & Insurance",
    "wof:placetype":"venue"
},
  "geometry": {"coordinates":[-113.479614258,53.4900512695],"type":"Point"}
}