{
  "type": "Feature",
  "properties": {
    "addr:full":"5115 Maingate Dr Mississauga ON L4W 1G4",
    "addr:housenumber":"5115",
    "addr:postcode":"l4w 1g4",
    "addr:street":"Maingate Dr",
    "iso:country":"CA",
    "sg:address":"5115 Maingate Dr",
    "sg:city":"Mississauga",
    "sg:classifiers":[
        {
            "category":"Professional",
            "subcategory":"Business Services",
            "type":"Services"
        }
    ],
    "sg:phone":"+1 905 238 8228",
    "sg:postcode":"L4W 1G4",
    "sg:province":"ON",
    "sg:tags":[
        "packaging"
    ],
    "wof:name":"Angco Quality Packaging Ltd",
    "wof:placetype":"venue"
},
  "geometry": {"coordinates":[-79.6289596558,43.6316337585],"type":"Point"}
}