{
  "type": "Feature",
  "properties": {
    "iso:country":"CA",
    "sg:address":"4420 75 Ave SE",
    "sg:city":"Calgary",
    "sg:classifiers":[
        {
            "category":"Wholesale",
            "subcategory":"Stationery",
            "type":"Manufacturing & Wholesale Goods"
        }
    ],
    "sg:phone":"+1 403 236 0135",
    "sg:postcode":"T2C 2H8",
    "sg:province":"AB",
    "sg:tags":[
        "business",
        "form",
        "system"
    ],
    "wof:name":"Pro Forms Ltd",
    "wof:placetype":"venue"
},
  "geometry": {"coordinates":[-113.971794128,50.9874382019],"type":"Point"}
}