{
  "type": "Feature",
  "properties": {
    "addr:full":"Victoriaville QC G6P 3Z5",
    "addr:postcode":"g6p 3z5",
    "iso:country":"CA",
    "sg:city":"Victoriaville",
    "sg:classifiers":[
        {
            "category":"Travel",
            "subcategory":"Campground",
            "type":"Entertainment"
        }
    ],
    "sg:phone":"+1 819 751 2727",
    "sg:postcode":"G6P 3Z5",
    "sg:province":"QC",
    "sg:tags":[
        "game",
        "adventure",
        "activity"
    ],
    "wof:name":"Orthanc LA Forteresse",
    "wof:placetype":"venue"
},
  "geometry": {"coordinates":[-71.95832799999999,46.056011],"type":"Point"}
}