{
  "type": "Feature",
  "properties": {
    "addr:full":"75 Rue Simonds N Granby QC J2J 2S3",
    "addr:housenumber":"75",
    "addr:postcode":"j2j 2s3",
    "addr:street":"Rue Simonds N",
    "iso:country":"CA",
    "sg:address":"75 Rue Simonds N",
    "sg:city":"Granby",
    "sg:classifiers":[
        {
            "category":"Shopping",
            "subcategory":"Department Store",
            "type":"Retail Goods"
        }
    ],
    "sg:phone":"+1 450 777 8863",
    "sg:postcode":"J2J 2S3",
    "sg:province":"QC",
    "sg:tags":[
        "pharmacy"
    ],
    "wof:name":"Wal-Mart",
    "wof:placetype":"venue"
},
  "geometry": {"coordinates":[-72.753525,45.416664],"type":"Point"}
}