{
  "type": "Feature",
  "properties": {
    "addr:full":"218 Bathurst St Toronto ON M5T 2R9",
    "addr:housenumber":"218",
    "addr:postcode":"m5t 2r9",
    "addr:street":"Bathurst St",
    "iso:country":"CA",
    "sg:address":"218 Bathurst St",
    "sg:city":"Toronto",
    "sg:classifiers":[
        {
            "category":"Restaurant",
            "type":"Food & Drink"
        }
    ],
    "sg:phone":"+1 416 703 6464",
    "sg:postcode":"M5T 2R9",
    "sg:province":"ON",
    "wof:name":"Mimi's",
    "wof:placetype":"venue"
},
  "geometry": {"coordinates":[-79.404624939,43.6483573914],"type":"Point"}
}