{
  "type": "Feature",
  "properties": {
    "addr:full":"650 Stewart St Renfrew ON K7V 1Y6",
    "addr:housenumber":"650",
    "addr:postcode":"k7v 1y6",
    "addr:street":"Stewart St",
    "iso:country":"CA",
    "sg:address":"650 Stewart St",
    "sg:city":"Renfrew",
    "sg:classifiers":[
        {
            "category":"Building & Trades",
            "subcategory":"Plumbing",
            "type":"Services"
        }
    ],
    "sg:phone":"+1 613 432 9739",
    "sg:postcode":"K7V 1Y6",
    "sg:province":"ON",
    "sg:tags":[
        "air",
        "conditioning",
        "contractor",
        "system",
        "heating"
    ],
    "wof:name":"Mc Crea's Heating & Air Cond",
    "wof:placetype":"venue"
},
  "geometry": {"coordinates":[-76.70141599999999,45.481125],"type":"Point"}
}