{
  "type": "Feature",
  "properties": {
    "addr:full":"RR 3 Prescott ON K0E 1T0",
    "addr:postcode":"k0e 1t0",
    "addr:street":"Rr 3",
    "iso:country":"CA",
    "sg:address":"RR 3",
    "sg:city":"Prescott",
    "sg:classifiers":[
        {
            "category":"Home & Garden",
            "subcategory":"Household Appliances",
            "type":"Retail Goods"
        }
    ],
    "sg:phone":"+1 613 657 3256",
    "sg:postcode":"K0E 1T0",
    "sg:province":"ON",
    "wof:name":"Cook's Repair Svc",
    "wof:placetype":"venue"
},
  "geometry": {"coordinates":[-75.5184173584,44.7094192505],"type":"Point"}
}