{
  "type": "Feature",
  "properties": {
    "addr:full":"5220 Rue Gaudet Drummondville QC J2E 1L7",
    "addr:housenumber":"5220",
    "addr:postcode":"j2e 1l7",
    "addr:street":"Rue Gaudet",
    "iso:country":"CA",
    "sg:address":"5220 Rue Gaudet",
    "sg:city":"Drummondville",
    "sg:classifiers":[
        {
            "category":"Wholesale",
            "subcategory":"Office Equipment",
            "type":"Manufacturing & Wholesale Goods"
        }
    ],
    "sg:phone":"+1 819 477 6369",
    "sg:postcode":"J2E 1L7",
    "sg:province":"QC",
    "sg:tags":[
        "machine",
        "duplicating",
        "copying"
    ],
    "wof:name":"Equipement DE Bureau Real",
    "wof:placetype":"venue"
},
  "geometry": {"coordinates":[-72.536766,45.901253],"type":"Point"}
}