{
  "type": "Feature",
  "properties": {
    "addr:full":"4836 50th Ave Eckville AB T0M 0X0",
    "addr:housenumber":"4836",
    "addr:postcode":"t0m 0x0",
    "addr:street":"50Th Ave",
    "iso:country":"CA",
    "sg:address":"4836 50th Ave",
    "sg:city":"Eckville",
    "sg:classifiers":[
        {
            "category":"Utilities",
            "subcategory":"Natural Gas",
            "type":"Services"
        }
    ],
    "sg:phone":"+1 403 746 3223",
    "sg:postcode":"T0M 0X0",
    "sg:province":"AB",
    "sg:tags":[
        "company"
    ],
    "wof:name":"Diamond Valley Gas CO-OP Ltd",
    "wof:placetype":"venue"
},
  "geometry": {"coordinates":[-114.363029,52.359554],"type":"Point"}
}