{
  "type": "Feature",
  "properties": {
    "addr:full":"4611 12th Ave W Vancouver BC V6R 2R7",
    "addr:housenumber":"4611",
    "addr:postcode":"v6r 2r7",
    "addr:street":"12Th Ave W",
    "iso:country":"CA",
    "sg:address":"4611 12th Ave W",
    "sg:city":"Vancouver",
    "sg:classifiers":[
        {
            "category":"Professional",
            "subcategory":"Art Services",
            "type":"Services"
        }
    ],
    "sg:phone":"+1 604 730 5708",
    "sg:postcode":"V6R 2R7",
    "sg:province":"BC",
    "sg:tags":[
        "graphic",
        "designer"
    ],
    "wof:name":"Bodega Design",
    "wof:placetype":"venue"
},
  "geometry": {"coordinates":[-123.21270752,49.2622642517],"type":"Point"}
}