{
  "type": "Feature",
  "properties": {
    "addr:full":"Saint-Andre-Avellin QC J0V 1W0",
    "addr:postcode":"j0v 1w0",
    "iso:country":"CA",
    "sg:city":"Saint-Andre-Avellin",
    "sg:classifiers":[
        {
            "category":"Organizations",
            "subcategory":"Religious Organization",
            "type":"Services"
        }
    ],
    "sg:phone":"+1 819 983 2096",
    "sg:postcode":"J0V 1W0",
    "sg:province":"QC",
    "sg:tags":[
        "church"
    ],
    "wof:name":"Eglise Evangelique-LA Petite",
    "wof:placetype":"venue"
},
  "geometry": {"coordinates":[-75.05425262449999,45.7241668701],"type":"Point"}
}