{
  "type": "Feature",
  "properties": {
    "addr:full":"2091 Alta Vista Dr Ottawa ON K1H 7L4",
    "addr:housenumber":"2091",
    "addr:postcode":"k1h 7l4",
    "addr:street":"Alta Vista Dr",
    "iso:country":"CA",
    "sg:address":"2091 Alta Vista Dr",
    "sg:city":"Ottawa",
    "sg:classifiers":[
        {
            "category":"Health Services",
            "subcategory":"Doctor",
            "type":"Services"
        }
    ],
    "sg:phone":"+1 613 731 6296",
    "sg:postcode":"K1H 7L4",
    "sg:province":"ON",
    "sg:tags":[
        "physician",
        "surgeon"
    ],
    "wof:name":"Malek, David L MD",
    "wof:placetype":"venue"
},
  "geometry": {"coordinates":[-75.6623001099,45.3921508789],"type":"Point"}
}