{
  "type": "Feature",
  "properties": {
    "addr:full":"5140 Ure St Oldcastle ON N0R 1L0",
    "addr:housenumber":"5140",
    "addr:postcode":"n0r 1l0",
    "addr:street":"Ure St",
    "iso:country":"CA",
    "sg:address":"5140 Ure St",
    "sg:city":"Oldcastle",
    "sg:classifiers":[
        {
            "category":"Manufacturing",
            "subcategory":"Metals",
            "type":"Manufacturing & Wholesale Goods"
        }
    ],
    "sg:phone":"+1 519 737 6631",
    "sg:postcode":"N0R 1L0",
    "sg:province":"ON",
    "sg:tags":[
        "steel"
    ],
    "wof:name":"Klassen Custom Fab Inc",
    "wof:placetype":"venue"
},
  "geometry": {"coordinates":[-82.950806,42.237587],"type":"Point"}
}