{
  "type": "Feature",
  "properties": {
    "addr:full":"2252 Boul Bastien Quebec QC G2B 1B6",
    "addr:housenumber":"2252",
    "addr:postcode":"g2b 1b6",
    "addr:street":"Boul Bastien",
    "iso:country":"CA",
    "sg:address":"2252 Boul Bastien",
    "sg:city":"Quebec",
    "sg:classifiers":[
        {
            "category":"Travel",
            "subcategory":"Travel Agent",
            "type":"Entertainment"
        }
    ],
    "sg:phone":"+1 418 842 3012",
    "sg:postcode":"G2B 1B6",
    "sg:province":"QC",
    "sg:tags":[
        "agency",
        "bureau"
    ],
    "wof:name":"Agence DE Voyage Spatial Inc",
    "wof:placetype":"venue"
},
  "geometry": {"coordinates":[-71.33764600000001,46.85833],"type":"Point"}
}