{
  "type": "Feature",
  "properties": {
    "addr:full":"2153 Av Cloutier Shawinigan QC G9N 2R8",
    "addr:housenumber":"2153",
    "addr:postcode":"g9n 2r8",
    "addr:street":"Av Cloutier",
    "iso:country":"CA",
    "sg:address":"2153 Av Cloutier",
    "sg:city":"Shawinigan",
    "sg:classifiers":[
        {
            "category":"Shopping",
            "subcategory":"Computers & Home Electronics",
            "type":"Retail Goods"
        }
    ],
    "sg:phone":"+1 819 536 4187",
    "sg:postcode":"G9N 2R8",
    "sg:province":"QC",
    "sg:tags":[
        "radio",
        "television",
        "video",
        "equipment"
    ],
    "wof:name":"D H Electronic",
    "wof:placetype":"venue"
},
  "geometry": {"coordinates":[-72.743584,46.556225],"type":"Point"}
}