{
  "type": "Feature",
  "properties": {
    "addr:full":"Pemberton BC V0N 2L0",
    "addr:postcode":"v0n 2l0",
    "iso:country":"CA",
    "sg:city":"Pemberton",
    "sg:classifiers":[
        {
            "category":"Manufacturing",
            "subcategory":"Metals",
            "type":"Manufacturing & Wholesale Goods"
        }
    ],
    "sg:phone":"+1 604 894 5188",
    "sg:postcode":"V0N 2L0",
    "sg:province":"BC",
    "sg:tags":[
        "welding"
    ],
    "wof:name":"Whistler Welding Svc",
    "wof:placetype":"venue"
},
  "geometry": {"coordinates":[-122.728088379,50.3119468689],"type":"Point"}
}