{
  "type": "Feature",
  "properties": {
    "addr:full":"3153 Main St Salisbury NB E4J 2K3",
    "addr:housenumber":"3153",
    "addr:postcode":"e4j 2k3",
    "addr:street":"Main St",
    "iso:country":"CA",
    "sg:address":"3153 Main St",
    "sg:city":"Salisbury",
    "sg:classifiers":[
        {
            "category":"Bars & Pubs",
            "type":"Food & Drink"
        }
    ],
    "sg:phone":"+1 506 372 8097",
    "sg:postcode":"E4J 2K3",
    "sg:province":"NB",
    "wof:name":"Grady's Pub",
    "wof:placetype":"venue"
},
  "geometry": {"coordinates":[-65.041206,46.026989],"type":"Point"}
}