{
  "type": "Feature",
  "properties": {
    "iso:country":"CA",
    "sg:address":"331 Bayfield St",
    "sg:city":"Barrie",
    "sg:classifiers":[
        {
            "category":"Food & Beverages",
            "subcategory":"Groceries & Convenience Stores",
            "type":"Retail Goods"
        }
    ],
    "sg:phone":"+1 705 792 1700",
    "sg:postcode":"L4M 3C2",
    "sg:province":"ON",
    "sg:tags":[
        "grocer"
    ],
    "wof:name":"Bay City Convenience",
    "wof:placetype":"venue"
},
  "geometry": {"coordinates":[-79.701195,44.402344],"type":"Point"}
}