{
  "type": "Feature",
  "properties": {
    "addr:full":"888 Central Ave Prince Albert SK S6V 4V1",
    "addr:housenumber":"888",
    "addr:postcode":"s6v 4v1",
    "addr:street":"Central Ave",
    "iso:country":"CA",
    "sg:address":"888 Central Ave",
    "sg:city":"Prince Albert",
    "sg:classifiers":[
        {
            "category":"Personal",
            "subcategory":"Beauty Salon",
            "type":"Services"
        }
    ],
    "sg:phone":"+1 306 763 5090",
    "sg:postcode":"S6V 4V1",
    "sg:province":"SK",
    "wof:name":"Acquiring Look Hair Design",
    "wof:placetype":"venue"
},
  "geometry": {"coordinates":[-105.754074097,53.2050018311],"type":"Point"}
}