{
  "type": "Feature",
  "properties": {
    "addr:full":"25 Capilano Way New Westminster BC V3L 5G3",
    "addr:housenumber":"25",
    "addr:postcode":"v3l 5g3",
    "addr:street":"Capilano Way",
    "iso:country":"CA",
    "sg:address":"25 Capilano Way",
    "sg:city":"New Westminster",
    "sg:classifiers":[
        {
            "category":"Freight",
            "type":"Transportation"
        }
    ],
    "sg:phone":"+1 604 540 5572",
    "sg:postcode":"V3L 5G3",
    "sg:province":"BC",
    "sg:tags":[
        "trucking"
    ],
    "wof:name":"Transx Limited",
    "wof:placetype":"venue"
},
  "geometry": {"coordinates":[-122.88435363799999,49.2250061035],"type":"Point"}
}