{
  "type": "Feature",
  "properties": {
    "addr:full":"289 Rue DE LA Mer Saint-Simeon-DE-Bonaventure QC G0C 3A0",
    "addr:housenumber":"289",
    "addr:postcode":"g0c 3a0",
    "addr:street":"Rue De La Mer",
    "iso:country":"CA",
    "sg:address":"289 Rue DE LA Mer",
    "sg:city":"Saint-Simeon-DE-Bonaventure",
    "sg:classifiers":[
        {
            "category":"Travel",
            "subcategory":"Hotels & Motels",
            "type":"Entertainment"
        }
    ],
    "sg:phone":"+1 418 534 4950",
    "sg:postcode":"G0C 3A0",
    "sg:province":"QC",
    "sg:tags":[
        "breakfast",
        "accommodation",
        "bed"
    ],
    "wof:name":"Aux Falaises Rouges",
    "wof:placetype":"venue"
},
  "geometry": {"coordinates":[-65.49444580079999,48.0454216003],"type":"Point"}
}