{
  "type": "Feature",
  "properties": {
    "addr:full":"158 Underhill Dr North York ON M3A 2K5",
    "addr:housenumber":"158",
    "addr:postcode":"m3a 2k5",
    "addr:street":"Underhill Dr",
    "iso:country":"CA",
    "sg:address":"158 Underhill Dr",
    "sg:city":"North York",
    "sg:classifiers":[
        {
            "category":"Wholesale",
            "subcategory":"Apparel",
            "type":"Manufacturing & Wholesale Goods"
        }
    ],
    "sg:phone":"+1 416 444 6141",
    "sg:postcode":"M3A 2K5",
    "sg:province":"ON",
    "sg:tags":[
        "clothing"
    ],
    "wof:name":"Pov Design Studio Inc",
    "wof:placetype":"venue"
},
  "geometry": {"coordinates":[-79.326393,43.75222],"type":"Point"}
}