{
  "type": "Feature",
  "properties": {
    "addr:full":"11024 Oakfield Dr SW Calgary AB T2W 5G6",
    "addr:housenumber":"11024",
    "addr:postcode":"t2w 5g6",
    "addr:street":"Oakfield Dr Sw",
    "iso:country":"CA",
    "sg:address":"11024 Oakfield Dr SW",
    "sg:city":"Calgary",
    "sg:classifiers":[
        {
            "category":"Organizations",
            "subcategory":"Professional Association",
            "type":"Services"
        }
    ],
    "sg:phone":"+1 403 251 2101",
    "sg:postcode":"T2W 5G6",
    "sg:province":"AB",
    "wof:name":"Cedarbrae Community Ctr",
    "wof:placetype":"venue"
},
  "geometry": {"coordinates":[-114.13084411600001,50.9541816711],"type":"Point"}
}