{
  "type": "Feature",
  "properties": {
    "addr:full":"296 Mceachern Cres Orleans ON K1E 3K3",
    "addr:housenumber":"296",
    "addr:postcode":"k1e 3k3",
    "addr:street":"Mceachern Cres",
    "iso:country":"CA",
    "sg:address":"296 Mceachern Cres",
    "sg:city":"Orleans",
    "sg:classifiers":[
        {
            "category":"Building & Trades",
            "subcategory":"Construction",
            "type":"Services"
        }
    ],
    "sg:phone":"+1 613 824 5652",
    "sg:postcode":"K1E 3K3",
    "sg:province":"ON",
    "sg:tags":[
        "repairing",
        "contractor",
        "remodeling",
        "general"
    ],
    "wof:name":"Jonsar Construction Ltd",
    "wof:placetype":"venue"
},
  "geometry": {"coordinates":[-75.5049743652,45.4739685059],"type":"Point"}
}