{
  "type": "Feature",
  "properties": {
    "addr:full":"Surrey BC V3S 6K1",
    "addr:postcode":"v3s 6k1",
    "iso:country":"CA",
    "sg:city":"Surrey",
    "sg:classifiers":[
        {
            "category":"Retail",
            "subcategory":"Auto Rental",
            "type":"Services"
        }
    ],
    "sg:phone":"+1 604 532 8969",
    "sg:postcode":"V3S 6K1",
    "sg:province":"BC",
    "sg:tags":[
        "renting",
        "automobile"
    ],
    "wof:name":"Enterprise Rent A Car",
    "wof:placetype":"venue"
},
  "geometry": {"coordinates":[-122.688316345,49.1055335999],"type":"Point"}
}