{
  "type": "Feature",
  "properties": {
    "addr:full":"410 Main St Mcbride BC V0J 2E0",
    "addr:housenumber":"410",
    "addr:postcode":"v0j 2e0",
    "addr:street":"Main St",
    "iso:country":"CA",
    "sg:address":"410 Main St",
    "sg:city":"Mcbride",
    "sg:classifiers":[
        {
            "category":"Food & Beverages",
            "subcategory":"Groceries & Convenience Stores",
            "type":"Retail Goods"
        }
    ],
    "sg:phone":"+1 250 569 3166",
    "sg:postcode":"V0J 2E0",
    "sg:province":"BC",
    "sg:tags":[
        "grocer"
    ],
    "wof:name":"Bigway Foods",
    "wof:placetype":"venue"
},
  "geometry": {"coordinates":[-120.16629,53.301914],"type":"Point"}
}