{
  "type": "Feature",
  "properties": {
    "iso:country":"CA",
    "sg:address":"319 Bayfield St",
    "sg:city":"Barrie",
    "sg:classifiers":[
        {
            "category":"Restaurant",
            "type":"Food & Drink"
        }
    ],
    "sg:phone":"+1 705 728 2401",
    "sg:postcode":"L4M 3C2",
    "sg:province":"ON",
    "wof:name":"Red Lobster Restaurant",
    "wof:placetype":"venue"
},
  "geometry": {"coordinates":[-79.700714,44.401772],"type":"Point"}
}