{
  "type": "Feature",
  "properties": {
    "addr:full":"1066 Dunbarton Rd Pickering ON L1V 1G8",
    "addr:housenumber":"1066",
    "addr:postcode":"l1v 1g8",
    "addr:street":"Dunbarton Rd",
    "iso:country":"CA",
    "sg:address":"1066 Dunbarton Rd",
    "sg:city":"Pickering",
    "sg:classifiers":[
        {
            "category":"Social Services",
            "subcategory":"Child Care",
            "type":"Services"
        }
    ],
    "sg:phone":"+1 905 831 9161",
    "sg:postcode":"L1V 1G8",
    "sg:province":"ON",
    "wof:name":"Bridges Kinder Connection Nrsy",
    "wof:placetype":"venue"
},
  "geometry": {"coordinates":[-79.1004867554,43.8280448914],"type":"Point"}
}