{
  "type": "Feature",
  "properties": {
    "addr:full":"751 Rue Du Conseil Sherbrooke QC J1G 1L1",
    "addr:housenumber":"751",
    "addr:postcode":"j1g 1l1",
    "addr:street":"Rue Du Conseil",
    "iso:country":"CA",
    "sg:address":"751 Rue Du Conseil",
    "sg:city":"Sherbrooke",
    "sg:classifiers":[
        {
            "category":"Restaurant",
            "type":"Food & Drink"
        }
    ],
    "sg:phone":"+1 819 564 9018",
    "sg:postcode":"J1G 1L1",
    "sg:province":"QC",
    "wof:name":"Restaurant Fern",
    "wof:placetype":"venue"
},
  "geometry": {"coordinates":[-71.87246704099999,45.4038009644],"type":"Point"}
}