{
  "type": "Feature",
  "properties": {
    "addr:full":"792 Commissioners Rd W London ON N6K 1C2",
    "addr:housenumber":"792",
    "addr:postcode":"n6k 1c2",
    "addr:street":"Commissioners Rd W",
    "iso:country":"CA",
    "sg:address":"792 Commissioners Rd W",
    "sg:city":"London",
    "sg:classifiers":[
        {
            "category":"Health Services",
            "subcategory":"Doctor",
            "type":"Services"
        }
    ],
    "sg:phone":"+1 519 472 2920",
    "sg:postcode":"N6K 1C2",
    "sg:province":"ON",
    "sg:tags":[
        "physician",
        "surgeon"
    ],
    "wof:name":"Hamilton, Kirk D MD",
    "wof:placetype":"venue"
},
  "geometry": {"coordinates":[-81.3050994873,42.9520874023],"type":"Point"}
}