{
  "type": "Feature",
  "properties": {
    "addr:full":"5510 56 St Cold Lake AB T9M 1P1",
    "addr:housenumber":"5510",
    "addr:postcode":"t9m 1p1",
    "addr:street":"56 St",
    "iso:country":"CA",
    "sg:address":"5510 56 St",
    "sg:city":"Cold Lake",
    "sg:classifiers":[
        {
            "category":"Building & Trades",
            "subcategory":"Construction",
            "type":"Services"
        }
    ],
    "sg:phone":"+1 780 594 4664",
    "sg:postcode":"T9M 1P1",
    "sg:province":"AB",
    "sg:tags":[
        "general",
        "contractor"
    ],
    "wof:name":"Urlacher Construction Ltd",
    "wof:placetype":"venue"
},
  "geometry": {"coordinates":[-110.214462,54.421494],"type":"Point"}
}