{
  "type": "Feature",
  "properties": {
    "addr:full":"Rawdon QC J0K 1S0",
    "addr:postcode":"j0k 1s0",
    "iso:country":"CA",
    "sg:city":"Rawdon",
    "sg:classifiers":[
        {
            "category":"Shopping",
            "subcategory":"Used Merchandise",
            "type":"Retail Goods"
        }
    ],
    "sg:phone":"+1 450 834 8050",
    "sg:postcode":"J0K 1S0",
    "sg:province":"QC",
    "sg:tags":[
        "flea",
        "market"
    ],
    "wof:name":"Au Grenier DE Grand Mere",
    "wof:placetype":"venue"
},
  "geometry": {"coordinates":[-73.70349899999999,46.04015],"type":"Point"}
}