{
  "type": "Feature",
  "properties": {
    "addr:full":"Toronto ON M5C 3C6",
    "addr:postcode":"m5c 3c6",
    "iso:country":"CA",
    "sg:city":"Toronto",
    "sg:classifiers":[
        {
            "category":"Health Services",
            "subcategory":"Doctor",
            "type":"Services"
        }
    ],
    "sg:phone":"+1 416 368 8000",
    "sg:postcode":"M5C 3C6",
    "sg:province":"ON",
    "sg:tags":[
        "dentist"
    ],
    "wof:name":"David Cheng & Assoc",
    "wof:placetype":"venue"
},
  "geometry": {"coordinates":[-79.3775634766,43.6490592957],"type":"Point"}
}