{
  "type": "Feature",
  "properties": {
    "addr:full":"29 Stanhope Rd Lewisporte NL A0G 3A0",
    "addr:housenumber":"29",
    "addr:postcode":"a0g 3a0",
    "addr:street":"Stanhope Rd",
    "iso:country":"CA",
    "sg:address":"29 Stanhope Rd",
    "sg:city":"Lewisporte",
    "sg:classifiers":[
        {
            "category":"Freight",
            "type":"Transportation"
        }
    ],
    "sg:phone":"+1 709 535 0104",
    "sg:postcode":"A0G 3A0",
    "sg:province":"NL",
    "sg:tags":[
        "trucking"
    ],
    "wof:name":"Manuel's Trucking Ltd",
    "wof:placetype":"venue"
},
  "geometry": {"coordinates":[-55.0599365234,49.2417984009],"type":"Point"}
}