{
  "type": "Feature",
  "properties": {
    "addr:full":"350 Raglan St S Renfrew ON K7V 1R7",
    "addr:housenumber":"350",
    "addr:postcode":"k7v 1r7",
    "addr:street":"Raglan St S",
    "iso:country":"CA",
    "sg:address":"350 Raglan St S",
    "sg:city":"Renfrew",
    "sg:classifiers":[
        {
            "category":"Food & Beverages",
            "subcategory":"Specialty",
            "type":"Retail Goods"
        }
    ],
    "sg:phone":"+1 613 432 2432",
    "sg:postcode":"K7V 1R7",
    "sg:province":"ON",
    "sg:tags":[
        "gourmet",
        "shop"
    ],
    "wof:name":"Stone Meadows' Kitchen Shop",
    "wof:placetype":"venue"
},
  "geometry": {"coordinates":[-76.68126700000001,45.469604],"type":"Point"}
}