{
  "type": "Feature",
  "properties": {
    "addr:full":"200-2232 Marine Drive West Vancouver V7V1K4",
    "addr:housenumber":"200-2232",
    "addr:postcode":"v7v1k4",
    "addr:street":"Marine Drive",
    "iso:country":"CA",
    "sg:address":"200-2232 Marine Drive",
    "sg:city":"West Vancouver",
    "sg:classifiers":[
        {
            "category":"Professional",
            "subcategory":"Computer Services",
            "type":"Services"
        }
    ],
    "sg:postcode":"V7V1K4",
    "sg:tags":[
        "language-learning",
        "learn",
        "language",
        "conversation",
        "tutoring",
        "spanish",
        "english",
        "italian",
        "german",
        "french",
        "chinese",
        "japanese",
        "portuguese",
        "russian",
        "swedish"
    ],
    "sg:website":"http://www.lingq.com",
    "wof:name":"LingQ",
    "wof:placetype":"venue"
},
  "geometry": {"coordinates":[-123.17257720000001,49.3314495],"type":"Point"}
}