{
  "type": "Feature",
  "properties": {
    "addr:full":"265 Av Saint-Denis Saint-Lambert QC J4P 2G4",
    "addr:postcode":"j4p 2g4",
    "addr:street":"265 Av Saint-Denis",
    "iso:country":"CA",
    "sg:address":"265 Av Saint-Denis",
    "sg:city":"Saint-Lambert",
    "sg:classifiers":[
        {
            "category":"Shopping",
            "subcategory":"Used Merchandise",
            "type":"Retail Goods"
        }
    ],
    "sg:phone":"+1 450 443 2865",
    "sg:postcode":"J4P 2G4",
    "sg:province":"QC",
    "sg:tags":[
        "antique"
    ],
    "wof:name":"Antiquites Du Minotaure",
    "wof:placetype":"venue"
},
  "geometry": {"coordinates":[-73.5095672607,45.4991188049],"type":"Point"}
}