{
  "type": "Feature",
  "properties": {
    "addr:full":"Drumheller AB T0J 0Y0",
    "addr:postcode":"t0j 0y0",
    "iso:country":"CA",
    "sg:city":"Drumheller",
    "sg:classifiers":[
        {
            "category":"Food & Beverages",
            "subcategory":"Specialty",
            "type":"Retail Goods"
        }
    ],
    "sg:phone":"+1 403 823 5533",
    "sg:postcode":"T0J 0Y0",
    "sg:province":"AB",
    "sg:tags":[
        "health",
        "diet"
    ],
    "wof:name":"Drumheller Centre Natural Heal",
    "wof:placetype":"venue"
},
  "geometry": {"coordinates":[-112.708862,51.463993],"type":"Point"}
}