{
  "type": "Feature",
  "properties": {
    "addr:full":"Brechin ON L0K 1B0",
    "addr:postcode":"l0k 1b0",
    "iso:country":"CA",
    "sg:city":"Brechin",
    "sg:classifiers":[
        {
            "category":"Retail",
            "subcategory":"Animal Services",
            "type":"Services"
        }
    ],
    "sg:phone":"+1 705 484 0494",
    "sg:postcode":"L0K 1B0",
    "sg:province":"ON",
    "sg:tags":[
        "pet",
        "grooming",
        "washing"
    ],
    "wof:name":"Dog Daze",
    "wof:placetype":"venue"
},
  "geometry": {"coordinates":[-79.20385,44.55151],"type":"Point"}
}