{
  "type": "Feature",
  "properties": {
    "addr:full":"9 Rue DE Piemont Laval QC H7M 1B5",
    "addr:housenumber":"9",
    "addr:postcode":"h7m 1b5",
    "addr:street":"Rue De Piemont",
    "iso:country":"CA",
    "sg:address":"9 Rue DE Piemont",
    "sg:city":"Laval",
    "sg:classifiers":[
        {
            "category":"Building & Trades",
            "subcategory":"Electrical",
            "type":"Services"
        }
    ],
    "sg:phone":"+1 450 967 0649",
    "sg:postcode":"H7M 1B5",
    "sg:province":"QC",
    "sg:tags":[
        "electric",
        "contractor"
    ],
    "wof:name":"Elco Entrepreneurs Electricien",
    "wof:placetype":"venue"
},
  "geometry": {"coordinates":[-73.731903,45.603146],"type":"Point"}
}