{
  "type": "Feature",
  "properties": {
    "addr:full":"80 Rte Saint-Gerard Saint-Damien-DE-Buckland QC G0R 2Y0",
    "addr:housenumber":"80",
    "addr:postcode":"g0r 2y0",
    "addr:street":"Rte Saint-Gerard",
    "iso:country":"CA",
    "sg:address":"80 Rte Saint-Gerard",
    "sg:city":"Saint-Damien-DE-Buckland",
    "sg:classifiers":[
        {
            "category":"Arena",
            "subcategory":"Sports Club",
            "type":"Entertainment"
        }
    ],
    "sg:phone":"+1 418 789 2525",
    "sg:postcode":"G0R 2Y0",
    "sg:province":"QC",
    "sg:tags":[
        "athletic",
        "fields",
        "stadium",
        "government"
    ],
    "wof:name":"Arena Regionale Je Metivier",
    "wof:placetype":"venue"
},
  "geometry": {"coordinates":[-70.669815,46.630661],"type":"Point"}
}