{
  "type": "Feature",
  "properties": {
    "addr:full":"Brockville ON K6V 5Y2",
    "addr:postcode":"k6v 5y2",
    "iso:country":"CA",
    "sg:city":"Brockville",
    "sg:classifiers":[
        {
            "category":"Health Services",
            "subcategory":"Doctor",
            "type":"Services"
        }
    ],
    "sg:phone":"+1 613 342 8344",
    "sg:postcode":"K6V 5Y2",
    "sg:province":"ON",
    "sg:tags":[
        "dentist"
    ],
    "wof:name":"Matthews, Mark DDS",
    "wof:placetype":"venue"
},
  "geometry": {"coordinates":[-75.683296,44.59753],"type":"Point"}
}