{
  "type": "Feature",
  "properties": {
    "addr:full":"465 Rue Moge Sorel-Tracy QC J3P 7B5",
    "addr:housenumber":"465",
    "addr:postcode":"j3p 7b5",
    "addr:street":"Rue Moge",
    "iso:country":"CA",
    "sg:address":"465 Rue Moge",
    "sg:city":"Sorel-Tracy",
    "sg:classifiers":[
        {
            "category":"Building & Trades",
            "subcategory":"Construction",
            "type":"Services"
        }
    ],
    "sg:phone":"+1 450 743 3029",
    "sg:postcode":"J3P 7B5",
    "sg:province":"QC",
    "sg:tags":[
        "masonry",
        "contractor"
    ],
    "wof:name":"Entreprise P Castonguay",
    "wof:placetype":"venue"
},
  "geometry": {"coordinates":[-73.118416,46.012383],"type":"Point"}
}