{
  "type": "Feature",
  "properties": {
    "addr:full":"2140 Regent St # 8 Sudbury ON P3E 5S8",
    "addr:housenumber":"2140",
    "addr:postcode":"p3e 5s8",
    "addr:street":"Regent St # 8",
    "iso:country":"CA",
    "sg:address":"2140 Regent St # 8",
    "sg:city":"Sudbury",
    "sg:classifiers":[
        {
            "category":"Health Services",
            "subcategory":"Doctor",
            "type":"Services"
        }
    ],
    "sg:phone":"+1 705 522 0444",
    "sg:postcode":"P3E 5S8",
    "sg:province":"ON",
    "sg:tags":[
        "physician",
        "surgeon"
    ],
    "wof:name":"Juma, Zul MD",
    "wof:placetype":"venue"
},
  "geometry": {"coordinates":[-80.99723052980001,46.4505271912],"type":"Point"}
}