{
  "type": "Feature",
  "properties": {
    "addr:full":"Penticton BC V2A 5C4",
    "addr:postcode":"v2a 5c4",
    "iso:country":"CA",
    "sg:city":"Penticton",
    "sg:classifiers":[
        {
            "category":"Restaurant",
            "type":"Food & Drink"
        }
    ],
    "sg:phone":"+1 250 770 1141",
    "sg:postcode":"V2A 5C4",
    "sg:province":"BC",
    "wof:name":"Isshin Japanese Deli",
    "wof:placetype":"venue"
},
  "geometry": {"coordinates":[-119.591469,49.49641],"type":"Point"}
}