{
  "type": "Feature",
  "properties": {
    "addr:full":"149 Nichols Ave Kentville NS B4N 5E4",
    "addr:housenumber":"149",
    "addr:postcode":"b4n 5e4",
    "addr:street":"Nichols Ave",
    "iso:country":"CA",
    "sg:address":"149 Nichols Ave",
    "sg:city":"Kentville",
    "sg:classifiers":[
        {
            "category":"Retail",
            "subcategory":"Auto Repair",
            "type":"Services"
        }
    ],
    "sg:phone":"+1 902 678 2845",
    "sg:postcode":"B4N 5E4",
    "sg:province":"NS",
    "sg:tags":[
        "automobile",
        "rustproofing",
        "undercoating"
    ],
    "wof:name":"Rust Check",
    "wof:placetype":"venue"
},
  "geometry": {"coordinates":[-64.4957122803,45.0880355835],"type":"Point"}
}