{
  "type": "Feature",
  "properties": {
    "iso:country":"CA",
    "sg:address":"121 Rte 116 E",
    "sg:city":"Warwick",
    "sg:classifiers":[
        {
            "category":"Retail",
            "subcategory":"Auto Repair",
            "type":"Services"
        }
    ],
    "sg:phone":"+1 819 358 4444",
    "sg:postcode":"J0A 1M0",
    "sg:province":"QC",
    "sg:tags":[
        "repairing",
        "automobile"
    ],
    "wof:name":"Marc Biron Garage Inc",
    "wof:placetype":"venue"
},
  "geometry": {"coordinates":[-71.9511260986,45.9940223694],"type":"Point"}
}