{
  "type": "Feature",
  "properties": {
    "addr:full":"Regina SK S4R 3C3",
    "addr:postcode":"s4r 3c3",
    "iso:country":"CA",
    "sg:city":"Regina",
    "sg:classifiers":[
        {
            "category":"Government",
            "subcategory":"Office",
            "type":"Public Place"
        }
    ],
    "sg:phone":"+1 306 780 5180",
    "sg:postcode":"S4R 3C3",
    "sg:province":"SK",
    "wof:name":"Canada Food Production & Insp",
    "wof:placetype":"venue"
},
  "geometry": {"coordinates":[-104.617904663,50.4303970337],"type":"Point"}
}