{
  "type": "Feature",
  "properties": {
    "addr:full":"2190 Rue Roussel Chicoutimi QC G7G 1W6",
    "addr:housenumber":"2190",
    "addr:postcode":"g7g 1w6",
    "addr:street":"Rue Roussel",
    "iso:country":"CA",
    "sg:address":"2190 Rue Roussel",
    "sg:city":"Chicoutimi",
    "sg:classifiers":[
        {
            "category":"Personal",
            "subcategory":"Barber",
            "type":"Services"
        }
    ],
    "sg:phone":"+1 418 543 4404",
    "sg:postcode":"G7G 1W6",
    "sg:province":"QC",
    "sg:tags":[
        "salon",
        "beauty"
    ],
    "wof:name":"Coiffure Kathy Tremblay",
    "wof:placetype":"venue"
},
  "geometry": {"coordinates":[-71.0650634766,48.4374656677],"type":"Point"}
}