{
  "type": "Feature",
  "properties": {
    "addr:full":"9661 Macleod Trail SW Calgary AB T2J 0P6",
    "addr:housenumber":"9661",
    "addr:postcode":"t2j 0p6",
    "addr:street":"Macleod Trail Sw",
    "iso:country":"CA",
    "sg:address":"9661 Macleod Trail SW",
    "sg:city":"Calgary",
    "sg:classifiers":[
        {
            "category":"Freight",
            "type":"Transportation"
        }
    ],
    "sg:phone":"+1 403 571 2570",
    "sg:postcode":"T2J 0P6",
    "sg:province":"AB",
    "sg:tags":[
        "courier"
    ],
    "wof:name":"Purolator Courier Ltd",
    "wof:placetype":"venue"
},
  "geometry": {"coordinates":[-114.071854,50.967991],"type":"Point"}
}