{
  "type": "Feature",
  "properties": {
    "addr:full":"Lasalle QC H8N 1B2",
    "addr:postcode":"h8n 1b2",
    "iso:country":"CA",
    "sg:city":"Lasalle",
    "sg:classifiers":[
        {
            "category":"Shopping",
            "subcategory":"Computers & Home Electronics",
            "type":"Retail Goods"
        }
    ],
    "sg:phone":"+1 514 368 1494",
    "sg:postcode":"H8N 1B2",
    "sg:province":"QC",
    "sg:tags":[
        "equipment",
        "dealer"
    ],
    "wof:name":"Microclinique Inc",
    "wof:placetype":"venue"
},
  "geometry": {"coordinates":[-73.61837005620001,45.4375114441],"type":"Point"}
}