{
  "type": "Feature",
  "properties": {
    "addr:full":"4 Danube Dr St Clements ON N0B 2M0",
    "addr:housenumber":"4",
    "addr:postcode":"n0b 2m0",
    "addr:street":"Danube Dr St Clements",
    "iso:country":"CA",
    "sg:address":"4 Danube Dr",
    "sg:city":"St Clements",
    "sg:classifiers":[
        {
            "category":"Professional",
            "subcategory":"Management & Consulting",
            "type":"Services"
        }
    ],
    "sg:phone":"+1 519 699 5429",
    "sg:postcode":"N0B 2M0",
    "sg:province":"ON",
    "sg:tags":[
        "consultant",
        "educational"
    ],
    "wof:name":"Mainland Consulting Inc",
    "wof:placetype":"venue"
},
  "geometry": {"coordinates":[-80.651917,43.523785],"type":"Point"}
}