{
  "type": "Feature",
  "properties": {
    "addr:full":"Saint-Jerome QC J7Y 4C2",
    "addr:postcode":"j7y 4c2",
    "iso:country":"CA",
    "sg:city":"Saint-Jerome",
    "sg:classifiers":[
        {
            "category":"Manufacturing",
            "subcategory":"Chemicals & Compounds",
            "type":"Manufacturing & Wholesale Goods"
        }
    ],
    "sg:phone":"+1 450 438 3588",
    "sg:postcode":"J7Y 4C2",
    "sg:province":"QC",
    "sg:tags":[
        "paint"
    ],
    "wof:name":"Akzo Nobel Coatings Ltd",
    "wof:placetype":"venue"
},
  "geometry": {"coordinates":[-74.02815200000001,45.791508],"type":"Point"}
}