{
  "type": "Feature",
  "properties": {
    "addr:full":"1460 Prairie Ave Port Coquitlam BC V3B 5M8",
    "addr:housenumber":"1460",
    "addr:postcode":"v3b 5m8",
    "addr:street":"Prairie Ave",
    "iso:country":"CA",
    "sg:address":"1460 Prairie Ave",
    "sg:city":"Port Coquitlam",
    "sg:classifiers":[
        {
            "category":"Cinema",
            "subcategory":"Movie Rental",
            "type":"Entertainment"
        }
    ],
    "sg:phone":"+1 604 552 3316",
    "sg:postcode":"V3B 5M8",
    "sg:province":"BC",
    "sg:tags":[
        "leasing",
        "video",
        "disc",
        "tape"
    ],
    "wof:name":"Rogers Video",
    "wof:placetype":"venue"
},
  "geometry": {"coordinates":[-122.75485999999999,49.271057],"type":"Point"}
}