{
  "type": "Feature",
  "properties": {
    "addr:full":"11403 174 St NW Edmonton AB T5S 2P4",
    "addr:housenumber":"11403",
    "addr:postcode":"t5s 2p4",
    "addr:street":"174 St Nw",
    "iso:country":"CA",
    "sg:address":"11403 174 St NW",
    "sg:city":"Edmonton",
    "sg:classifiers":[
        {
            "category":"Autos & Motor Vehicles",
            "subcategory":"Automobile Sales",
            "type":"Retail Goods"
        }
    ],
    "sg:phone":"+1 780 451 2680",
    "sg:postcode":"T5S 2P4",
    "sg:province":"AB",
    "sg:tags":[
        "truck"
    ],
    "wof:name":"Volvo Truck Ctr-Edmonton",
    "wof:placetype":"venue"
},
  "geometry": {"coordinates":[-113.621246,53.563404],"type":"Point"}
}