{
  "type": "Feature",
  "properties": {
    "addr:full":"Orono ON L0B 1M0",
    "addr:postcode":"l0b 1m0",
    "iso:country":"CA",
    "sg:city":"Orono",
    "sg:classifiers":[
        {
            "category":"Freight",
            "type":"Transportation"
        }
    ],
    "sg:phone":"+1 905 983 5942",
    "sg:postcode":"L0B 1M0",
    "sg:province":"ON",
    "sg:tags":[
        "courier"
    ],
    "wof:name":"Courier Distribution Svc",
    "wof:placetype":"venue"
},
  "geometry": {"coordinates":[-78.61088599999999,43.912086],"type":"Point"}
}