{
  "type": "Feature",
  "properties": {
    "addr:full":"9340 Hwy 93 Midland ON L4R 4L3",
    "addr:housenumber":"9340",
    "addr:postcode":"l4r 4l3",
    "addr:street":"Hwy 93",
    "iso:country":"CA",
    "sg:address":"9340 Hwy 93",
    "sg:city":"Midland",
    "sg:classifiers":[
        {
            "category":"Autos & Motor Vehicles",
            "subcategory":"Fuel & Gas Station",
            "type":"Retail Goods"
        }
    ],
    "sg:phone":"+1 705 526 5863",
    "sg:postcode":"L4R 4L3",
    "sg:province":"ON",
    "sg:tags":[
        "oil"
    ],
    "wof:name":"Noco Petroleum",
    "wof:placetype":"venue"
},
  "geometry": {"coordinates":[-79.91486399999999,44.740471],"type":"Point"}
}