{
  "type": "Feature",
  "properties": {
    "iso:country":"CA",
    "sg:city":"Charlottetown",
    "sg:classifiers":[
        {
            "category":"Travel",
            "subcategory":"Hotels & Motels",
            "type":"Entertainment"
        }
    ],
    "sg:phone":"+1 902 368 1110",
    "sg:postcode":"C1A 7J9",
    "sg:province":"PE",
    "wof:name":"Econo Lodge",
    "wof:placetype":"venue"
},
  "geometry": {"coordinates":[-63.1587219238,46.2656173706],"type":"Point"}
}