{
  "type": "Feature",
  "properties": {
    "addr:full":"North York ON M3J 3H9",
    "addr:postcode":"m3j 3h9",
    "iso:country":"CA",
    "sg:city":"North York",
    "sg:classifiers":[
        {
            "category":"Manufacturing",
            "subcategory":"Printing",
            "type":"Manufacturing & Wholesale Goods"
        }
    ],
    "sg:phone":"+1 416 665 5518",
    "sg:postcode":"M3J 3H9",
    "sg:province":"ON",
    "sg:tags":[
        "color",
        "photo",
        "engrave"
    ],
    "wof:name":"Acustep Inc",
    "wof:placetype":"venue"
},
  "geometry": {"coordinates":[-79.4738082886,43.783203125],"type":"Point"}
}