{
  "type": "Feature",
  "properties": {
    "addr:full":"261 Davenport Rd Toronto ON M5R 1K3",
    "addr:housenumber":"261",
    "addr:postcode":"m5r 1k3",
    "addr:street":"Davenport Rd",
    "iso:country":"CA",
    "sg:address":"261 Davenport Rd",
    "sg:city":"Toronto",
    "sg:classifiers":[
        {
            "category":"Health Services",
            "subcategory":"Health Practitioner",
            "type":"Services"
        }
    ],
    "sg:phone":"+1 416 925 1704",
    "sg:postcode":"M5R 1K3",
    "sg:province":"ON",
    "sg:tags":[
        "acupuncture"
    ],
    "wof:name":"Grafstein, Mike",
    "wof:placetype":"venue"
},
  "geometry": {"coordinates":[-79.398163,43.674278],"type":"Point"}
}