{
  "type": "Feature",
  "properties": {
    "addr:full":"7 Fallingbrook Crt St Catharines ON L2N 6V1",
    "addr:housenumber":"7",
    "addr:postcode":"l2n 6v1",
    "addr:street":"Fallingbrook Crt",
    "iso:country":"CA",
    "sg:address":"7 Fallingbrook Crt",
    "sg:city":"St Catharines",
    "sg:classifiers":[
        {
            "category":"Shopping",
            "type":"Retail Goods"
        }
    ],
    "sg:phone":"+1 905 646 5115",
    "sg:postcode":"L2N 6V1",
    "sg:province":"ON",
    "sg:tags":[
        "cosmetic",
        "perfume"
    ],
    "wof:name":"Mary Kay Cosmetics",
    "wof:placetype":"venue"
},
  "geometry": {"coordinates":[-79.25018300000001,43.202751],"type":"Point"}
}