{
  "type": "Feature",
  "properties": {
    "addr:full":"3666 Rue Du Campanile Sainte-Foy QC G1X 4G6",
    "addr:housenumber":"3666",
    "addr:postcode":"g1x 4g6",
    "addr:street":"Rue Du Campanile",
    "iso:country":"CA",
    "sg:address":"3666 Rue Du Campanile",
    "sg:city":"Sainte-Foy",
    "sg:classifiers":[
        {
            "category":"Shopping",
            "subcategory":"Clothing, Apparel, & Fashions",
            "type":"Retail Goods"
        }
    ],
    "sg:phone":"+1 418 657 1183",
    "sg:postcode":"G1X 4G6",
    "sg:province":"QC",
    "wof:name":"Boutique Douce Heure",
    "wof:placetype":"venue"
},
  "geometry": {"coordinates":[-71.333282,46.761616],"type":"Point"}
}