{
  "type": "Feature",
  "properties": {
    "addr:full":"4963 Boul Des Sources Pierrefonds QC H8Y 3E3",
    "addr:housenumber":"4963",
    "addr:postcode":"h8y 3e3",
    "addr:street":"Boul Des Sources",
    "iso:country":"CA",
    "sg:address":"4963 Boul Des Sources",
    "sg:city":"Pierrefonds",
    "sg:classifiers":[
        {
            "category":"Home & Garden",
            "subcategory":"Building Materials",
            "type":"Retail Goods"
        }
    ],
    "sg:phone":"+1 514 685 8544",
    "sg:postcode":"H8Y 3E3",
    "sg:province":"QC",
    "sg:tags":[
        "glass",
        "window",
        "plate"
    ],
    "wof:name":"Docteur Du Pare Brise",
    "wof:placetype":"venue"
},
  "geometry": {"coordinates":[-73.819817,45.507092],"type":"Point"}
}