{
  "type": "Feature",
  "properties": {
    "iso:country":"CA",
    "sg:address":"285 Dunlop St W",
    "sg:city":"Barrie",
    "sg:classifiers":[
        {
            "category":"Retail",
            "subcategory":"Auto Repair",
            "type":"Services"
        }
    ],
    "sg:phone":"+1 705 728 1300",
    "sg:postcode":"L4N 1C1",
    "sg:province":"ON",
    "sg:tags":[
        "repairing",
        "automobile",
        "lubrication"
    ],
    "wof:name":"Oil Changers",
    "wof:placetype":"venue"
},
  "geometry": {"coordinates":[-79.70630645750001,44.3820228577],"type":"Point"}
}