{
  "type": "Feature",
  "properties": {
    "addr:full":"Orleans ON K1C 2L9",
    "addr:postcode":"k1c 2l9",
    "iso:country":"CA",
    "sg:city":"Orleans",
    "sg:classifiers":[
        {
            "category":"Shopping",
            "subcategory":"Clothing, Apparel, & Fashions",
            "type":"Retail Goods"
        }
    ],
    "sg:phone":"+1 613 824 2460",
    "sg:postcode":"K1C 2L9",
    "sg:province":"ON",
    "sg:tags":[
        "furnishing"
    ],
    "wof:name":"Randy River",
    "wof:placetype":"venue"
},
  "geometry": {"coordinates":[-75.5059432983,45.4832611084],"type":"Point"}
}