{
  "type": "Feature",
  "properties": {
    "addr:full":"1288 Mountain Rd Moncton NB E1C 2T6",
    "addr:housenumber":"1288",
    "addr:postcode":"e1c 2t6",
    "addr:street":"Mountain Rd",
    "iso:country":"CA",
    "sg:address":"1288 Mountain Rd",
    "sg:city":"Moncton",
    "sg:classifiers":[
        {
            "category":"Bars & Pubs",
            "type":"Food & Drink"
        }
    ],
    "sg:phone":"+1 506 853 7238",
    "sg:postcode":"E1C 2T6",
    "sg:province":"NB",
    "sg:tags":[
        "club",
        "night"
    ],
    "wof:name":"Blondie's Bar",
    "wof:placetype":"venue"
},
  "geometry": {"coordinates":[-64.829773,46.109474],"type":"Point"}
}