{
  "type": "Feature",
  "properties": {
    "addr:full":"3735 24E Ave Saint-Prosper-DE-Dorchester QC G0M 1Y0",
    "addr:housenumber":"3735",
    "addr:postcode":"g0m 1y0",
    "addr:street":"24E Ave",
    "iso:country":"CA",
    "sg:address":"3735 24E Ave",
    "sg:city":"Saint-Prosper-DE-Dorchester",
    "sg:classifiers":[
        {
            "category":"Health Services",
            "subcategory":"Nursing And Care Facility",
            "type":"Services"
        }
    ],
    "sg:phone":"+1 418 594 5863",
    "sg:postcode":"G0M 1Y0",
    "sg:province":"QC",
    "sg:tags":[
        "home",
        "retirement",
        "community"
    ],
    "wof:name":"Residence Adrienne",
    "wof:placetype":"venue"
},
  "geometry": {"coordinates":[-70.497749,46.221554],"type":"Point"}
}