{
  "type": "Feature",
  "properties": {
    "addr:full":"16640 95 St NW Edmonton AB T5Z 3L2",
    "addr:housenumber":"16640",
    "addr:postcode":"t5z 3l2",
    "addr:street":"95 St Nw",
    "iso:country":"CA",
    "sg:address":"16640 95 St NW",
    "sg:city":"Edmonton",
    "sg:classifiers":[
        {
            "category":"Retail",
            "subcategory":"Laundry & Dry Cleaning",
            "type":"Services"
        }
    ],
    "sg:phone":"+1 780 456 6156",
    "sg:postcode":"T5Z 3L2",
    "sg:province":"AB",
    "sg:tags":[
        "cleaners"
    ],
    "wof:name":"Castledowns Cleanitizing Drycl",
    "wof:placetype":"venue"
},
  "geometry": {"coordinates":[-113.487266541,53.6281089783],"type":"Point"}
}