{
  "type": "Feature",
  "properties": {
    "addr:full":"760 Gatensbury St Coquitlam BC V3J 5G8",
    "addr:housenumber":"760",
    "addr:postcode":"v3j 5g8",
    "addr:street":"Gatensbury St",
    "iso:country":"CA",
    "sg:address":"760 Gatensbury St",
    "sg:city":"Coquitlam",
    "sg:classifiers":[
        {
            "category":"Building & Trades",
            "subcategory":"Construction",
            "type":"Services"
        }
    ],
    "sg:phone":"+1 604 936 6882",
    "sg:postcode":"V3J 5G8",
    "sg:province":"BC",
    "sg:tags":[
        "marble",
        "terrazzo"
    ],
    "wof:name":"Blackstone Marble Care",
    "wof:placetype":"venue"
},
  "geometry": {"coordinates":[-122.857849121,49.2627983093],"type":"Point"}
}