{
  "type": "Feature",
  "properties": {
    "addr:full":"100 Rue Saint-Joseph S Alma QC G8B 7A6",
    "addr:housenumber":"100",
    "addr:postcode":"g8b 7a6",
    "addr:street":"Rue Saint-Joseph S",
    "iso:country":"CA",
    "sg:address":"100 Rue Saint-Joseph S",
    "sg:city":"Alma",
    "sg:classifiers":[
        {
            "category":"Cinema",
            "subcategory":"Movie Theater",
            "type":"Entertainment"
        }
    ],
    "sg:phone":"+1 418 662 3456",
    "sg:postcode":"G8B 7A6",
    "sg:province":"QC",
    "wof:name":"Cinema-Complexe Jacques Gagnon",
    "wof:placetype":"venue"
},
  "geometry": {"coordinates":[-71.652351,48.549927],"type":"Point"}
}