{
  "type": "Feature",
  "properties": {
    "iso:country":"CA",
    "sg:address":"41 Industrial Pky S",
    "sg:city":"Aurora",
    "sg:classifiers":[
        {
            "category":"Food & Beverages",
            "subcategory":"Bakery",
            "type":"Retail Goods"
        }
    ],
    "sg:phone":"+1 905 727 5198",
    "sg:postcode":"L4G 3Y5",
    "sg:province":"ON",
    "sg:tags":[
        "baker"
    ],
    "wof:name":"Betty's Treats",
    "wof:placetype":"venue"
},
  "geometry": {"coordinates":[-79.45826721189999,43.9996604919],"type":"Point"}
}