{
  "type": "Feature",
  "properties": {
    "addr:full":"3150 Gendron Rd Hammond ON K0A 2A0",
    "addr:housenumber":"3150",
    "addr:postcode":"k0a 2a0",
    "addr:street":"Gendron Rd",
    "iso:country":"CA",
    "sg:address":"3150 Gendron Rd",
    "sg:city":"Hammond",
    "sg:classifiers":[
        {
            "category":"Home & Garden",
            "subcategory":"Building Materials",
            "type":"Retail Goods"
        }
    ],
    "sg:phone":"+1 613 487 9900",
    "sg:postcode":"K0A 2A0",
    "sg:province":"ON",
    "sg:tags":[
        "glass",
        "window",
        "plate"
    ],
    "wof:name":"Quality Windows & Glass",
    "wof:placetype":"venue"
},
  "geometry": {"coordinates":[-75.2391586304,45.4393882751],"type":"Point"}
}