{
  "type": "Feature",
  "properties": {
    "addr:full":"4764 Regional Rd 15 Chelmsford ON P0M 1L0",
    "addr:housenumber":"4764;15",
    "addr:postcode":"p0m 1l0",
    "addr:street":"Regional Rd",
    "iso:country":"CA",
    "sg:address":"4764 Regional Rd 15",
    "sg:city":"Chelmsford",
    "sg:classifiers":[
        {
            "category":"Shopping",
            "subcategory":"Department Store",
            "type":"Retail Goods"
        }
    ],
    "sg:phone":"+1 705 855 6335",
    "sg:postcode":"P0M 1L0",
    "sg:province":"ON",
    "sg:tags":[
        "shop"
    ],
    "wof:name":"A Buck or Two",
    "wof:placetype":"venue"
},
  "geometry": {"coordinates":[-81.1973571777,46.5688743591],"type":"Point"}
}