{
  "type": "Feature",
  "properties": {
    "addr:full":"2963 Cambie St Vancouver BC V5Z 2V7",
    "addr:housenumber":"2963",
    "addr:postcode":"v5z 2v7",
    "addr:street":"Cambie St",
    "iso:country":"CA",
    "sg:address":"2963 Cambie St",
    "sg:city":"Vancouver",
    "sg:classifiers":[
        {
            "category":"Retail",
            "subcategory":"Laundry & Dry Cleaning",
            "type":"Services"
        }
    ],
    "sg:phone":"+1 604 872 0087",
    "sg:postcode":"V5Z 2V7",
    "sg:province":"BC",
    "wof:name":"Joy Wash Laundromat",
    "wof:placetype":"venue"
},
  "geometry": {"coordinates":[-123.115227,49.259087],"type":"Point"}
}