{
  "type": "Feature",
  "properties": {
    "addr:full":"2-6 Reid St Channel-Port-Aux-Basques NL A0M 1C0",
    "addr:housenumber":"2-6",
    "addr:postcode":"a0m 1c0",
    "addr:street":"Reid St",
    "iso:country":"CA",
    "sg:address":"2-6 Reid St",
    "sg:city":"Channel-Port-Aux-Basques",
    "sg:classifiers":[
        {
            "category":"Utilities",
            "subcategory":"Fuel Oil & Lpg",
            "type":"Services"
        }
    ],
    "sg:phone":"+1 709 695 7139",
    "sg:postcode":"A0M 1C0",
    "sg:province":"NL",
    "sg:tags":[
        "propane",
        "gas"
    ],
    "wof:name":"Sheaves Home Hardware",
    "wof:placetype":"venue"
},
  "geometry": {"coordinates":[-59.142372,47.573521],"type":"Point"}
}