{
  "type": "Feature",
  "properties": {
    "iso:country":"CA",
    "sg:address":"1163 Highbury Ave N",
    "sg:city":"London",
    "sg:classifiers":[
        {
            "category":"Home & Garden",
            "subcategory":"Building Materials",
            "type":"Retail Goods"
        }
    ],
    "sg:phone":"+1 519 452 3760",
    "sg:postcode":"N5Y 1A6",
    "sg:province":"ON",
    "sg:tags":[
        "paint"
    ],
    "wof:name":"Color Your World",
    "wof:placetype":"venue"
},
  "geometry": {"coordinates":[-81.21301269529999,43.0149688721],"type":"Point"}
}