{
  "type": "Feature",
  "properties": {
    "addr:full":"Gloucester ON K1J 9K9",
    "addr:postcode":"k1j 9k9",
    "iso:country":"CA",
    "sg:city":"Gloucester",
    "sg:classifiers":[
        {
            "category":"Wholesale",
            "subcategory":"Photographic Equipment",
            "type":"Manufacturing & Wholesale Goods"
        }
    ],
    "sg:phone":"+1 613 748 5946",
    "sg:postcode":"K1J 9K9",
    "sg:province":"ON",
    "sg:tags":[
        "system"
    ],
    "wof:name":"Elc Electronic Language Comm",
    "wof:placetype":"venue"
},
  "geometry": {"coordinates":[-75.583977,45.45713],"type":"Point"}
}