{
  "type": "Feature",
  "properties": {
    "addr:full":"Calgary AB T2E 7M9",
    "addr:postcode":"t2e 7m9",
    "iso:country":"CA",
    "sg:city":"Calgary",
    "sg:classifiers":[
        {
            "category":"Real Estate",
            "subcategory":"Surveying",
            "type":"Services"
        }
    ],
    "sg:phone":"+1 403 263 4400",
    "sg:postcode":"T2E 7M9",
    "sg:province":"AB",
    "sg:tags":[
        "surveyor"
    ],
    "wof:name":"Cuthbert Smith Consulting",
    "wof:placetype":"venue"
},
  "geometry": {"coordinates":[-114.01881400000001,51.056843],"type":"Point"}
}