{
  "type": "Feature",
  "properties": {
    "addr:full":"621 Av Stravinski Brossard QC J4X 1Y7",
    "addr:housenumber":"621",
    "addr:postcode":"j4x 1y7",
    "addr:street":"Av Stravinski",
    "iso:country":"CA",
    "sg:address":"621 Av Stravinski",
    "sg:city":"Brossard",
    "sg:classifiers":[
        {
            "category":"Personal",
            "subcategory":"Beauty Salon",
            "type":"Services"
        }
    ],
    "sg:phone":"+1 450 466 3120",
    "sg:postcode":"J4X 1Y7",
    "sg:province":"QC",
    "wof:name":"Coiffmania",
    "wof:placetype":"venue"
},
  "geometry": {"coordinates":[-73.491623,45.454914],"type":"Point"}
}