{
  "type": "Feature",
  "properties": {
    "iso:country":"CA",
    "sg:address":"3 Main St #E",
    "sg:city":"Cartier",
    "sg:classifiers":[
        {
            "category":"Restaurant",
            "type":"Food & Drink"
        }
    ],
    "sg:phone":"+1 705 965 2055",
    "sg:postcode":"P0M 1J0",
    "sg:province":"ON",
    "wof:name":"Pine Grove Ctr",
    "wof:placetype":"venue"
},
  "geometry": {"coordinates":[-81.1972503662,46.5832939148],"type":"Point"}
}