{
  "type": "Feature",
  "properties": {
    "addr:full":"196157 19th Line Thamesford ON N0M 2M0",
    "addr:housenumber":"196157",
    "addr:postcode":"n0m 2m0",
    "addr:street":"19Th Line",
    "iso:country":"CA",
    "sg:address":"196157 19th Line",
    "sg:city":"Thamesford",
    "sg:classifiers":[
        {
            "category":"Building & Trades",
            "subcategory":"Construction",
            "type":"Services"
        }
    ],
    "sg:phone":"+1 519 283 6387",
    "sg:postcode":"N0M 2M0",
    "sg:province":"ON",
    "sg:tags":[
        "shed",
        "utility"
    ],
    "wof:name":"Bensheds",
    "wof:placetype":"venue"
},
  "geometry": {"coordinates":[-81.030182,43.13895],"type":"Point"}
}