{
  "type": "Feature",
  "properties": {
    "addr:full":"Winnipeg MB R3H 1A7",
    "addr:postcode":"r3h 1a7",
    "iso:country":"CA",
    "sg:city":"Winnipeg",
    "sg:classifiers":[
        {
            "category":"Professional",
            "subcategory":"Advertising",
            "type":"Services"
        }
    ],
    "sg:phone":"+1 204 944 1199",
    "sg:postcode":"R3H 1A7",
    "sg:province":"MB",
    "sg:tags":[
        "designer",
        "display",
        "producer"
    ],
    "wof:name":"Light Visions",
    "wof:placetype":"venue"
},
  "geometry": {"coordinates":[-97.2095489502,49.8968353271],"type":"Point"}
}