{
  "type": "Feature",
  "properties": {
    "addr:full":"1220 Stewart Blvd Brockville ON K6V 7H2",
    "addr:housenumber":"1220",
    "addr:postcode":"k6v 7h2",
    "addr:street":"Stewart Blvd",
    "iso:country":"CA",
    "sg:address":"1220 Stewart Blvd",
    "sg:city":"Brockville",
    "sg:classifiers":[
        {
            "category":"Wholesale",
            "subcategory":"Auto Parts",
            "type":"Manufacturing & Wholesale Goods"
        }
    ],
    "sg:phone":"+1 613 342 1010",
    "sg:postcode":"K6V 7H2",
    "sg:province":"ON",
    "sg:tags":[
        "body",
        "automobile",
        "shop"
    ],
    "wof:name":"Carquest Ltd",
    "wof:placetype":"venue"
},
  "geometry": {"coordinates":[-75.7313,44.60952],"type":"Point"}
}