{
  "type": "Feature",
  "properties": {
    "addr:full":"38 Cranfield Rd East York ON M4B 3H3",
    "addr:housenumber":"38",
    "addr:postcode":"m4b 3h3",
    "addr:street":"Cranfield Rd",
    "iso:country":"CA",
    "sg:address":"38 Cranfield Rd",
    "sg:city":"East York",
    "sg:classifiers":[
        {
            "category":"Wholesale",
            "subcategory":"Hardware",
            "type":"Manufacturing & Wholesale Goods"
        }
    ],
    "sg:phone":"+1 416 751 1611",
    "sg:postcode":"M4B 3H3",
    "sg:province":"ON",
    "sg:tags":[
        "parts",
        "refrigerating"
    ],
    "wof:name":"Canadian Refrigeration Supply",
    "wof:placetype":"venue"
},
  "geometry": {"coordinates":[-79.310463,43.714241],"type":"Point"}
}