{
  "type": "Feature",
  "properties": {
    "addr:full":"Saint-Calixte QC J0K 1Z0",
    "addr:postcode":"j0k 1z0",
    "iso:country":"CA",
    "sg:city":"Saint-Calixte",
    "sg:classifiers":[
        {
            "category":"Home & Garden",
            "subcategory":"Household Appliances",
            "type":"Retail Goods"
        }
    ],
    "sg:phone":"+1 514 383 7738",
    "sg:postcode":"J0K 1Z0",
    "sg:province":"QC",
    "sg:tags":[
        "refrigerator"
    ],
    "wof:name":"Dussault Jean-Pierre Refrig",
    "wof:placetype":"venue"
},
  "geometry": {"coordinates":[-73.814842,45.90731],"type":"Point"}
}