{
  "type": "Feature",
  "properties": {
    "addr:full":"Sault Ste Marie ON P6A 1X3",
    "addr:postcode":"p6a 1x3",
    "iso:country":"CA",
    "sg:city":"Sault Ste Marie",
    "sg:classifiers":[
        {
            "category":"Professional",
            "subcategory":"Computer Services",
            "type":"Services"
        }
    ],
    "sg:phone":"+1 705 253 4700",
    "sg:postcode":"P6A 1X3",
    "sg:province":"ON",
    "sg:tags":[
        "internet"
    ],
    "wof:name":"Soo Net Vianet",
    "wof:placetype":"venue"
},
  "geometry": {"coordinates":[-84.33508300779999,46.5110397339],"type":"Point"}
}