{
  "type": "Feature",
  "properties": {
    "iso:country":"CA",
    "sg:address":"255 Ontario St",
    "sg:city":"St Catharines",
    "sg:classifiers":[
        {
            "category":"Manufacturing",
            "subcategory":"Printing",
            "type":"Manufacturing & Wholesale Goods"
        }
    ],
    "sg:phone":"+1 905 708 1121",
    "sg:postcode":"L2R 7J2",
    "sg:province":"ON",
    "sg:tags":[
        "screen"
    ],
    "wof:name":"Print By Nite",
    "wof:placetype":"venue"
},
  "geometry": {"coordinates":[-79.260834,43.164639],"type":"Point"}
}