{
  "type": "Feature",
  "properties": {
    "addr:full":"1572 Av Du Docteur-Penfield Montreal QC H3G 1C4",
    "addr:housenumber":"1572",
    "addr:postcode":"h3g 1c4",
    "addr:street":"Av Du Docteur-Penfield",
    "iso:country":"CA",
    "sg:address":"1572 Av Du Docteur-Penfield",
    "sg:city":"Montreal",
    "sg:classifiers":[
        {
            "category":"Organizations",
            "subcategory":"Professional Association",
            "type":"Services"
        }
    ],
    "sg:phone":"+1 514 937 5822",
    "sg:postcode":"H3G 1C4",
    "sg:province":"QC",
    "wof:name":"Chambre DE Commerce Canado",
    "wof:placetype":"venue"
},
  "geometry": {"coordinates":[-73.5858383179,45.497089386],"type":"Point"}
}