{
  "type": "Feature",
  "properties": {
    "addr:full":"464 Carlstrom Rd Barriere BC V0E 1E0",
    "addr:housenumber":"464",
    "addr:postcode":"bc v0e 1e0",
    "addr:street":"Carlstrom Rd",
    "iso:country":"CA",
    "sg:address":"464 Carlstrom Rd",
    "sg:city":"Barriere",
    "sg:classifiers":[
        {
            "category":"Communications",
            "subcategory":"Television Station",
            "type":"Services"
        }
    ],
    "sg:phone":"+1 250 672 5135",
    "sg:postcode":"V0E 1E0",
    "sg:province":"BC",
    "sg:tags":[
        "broadcasting",
        "co"
    ],
    "wof:name":"Barriere & District Television",
    "wof:placetype":"venue"
},
  "geometry": {"coordinates":[-120.130066,51.176498],"type":"Point"}
}