{
  "type": "Feature",
  "properties": {
    "addr:full":"404 Main St Watrous SK S0K 4T0",
    "addr:housenumber":"404",
    "addr:postcode":"s0k 4t0",
    "addr:street":"Main St",
    "iso:country":"CA",
    "sg:address":"404 Main St",
    "sg:city":"Watrous",
    "sg:classifiers":[
        {
            "category":"Education",
            "subcategory":"Library",
            "type":"Public Place"
        }
    ],
    "sg:phone":"+1 306 946 2244",
    "sg:postcode":"S0K 4T0",
    "sg:province":"SK",
    "wof:name":"Watrous Library",
    "wof:placetype":"venue"
},
  "geometry": {"coordinates":[-105.466255,51.674721],"type":"Point"}
}