{
  "type": "Feature",
  "properties": {
    "iso:country":"CA",
    "sg:city":"Montreal",
    "sg:classifiers":[
        {
            "category":"Personal",
            "subcategory":"Hair Removal",
            "type":"Services"
        }
    ],
    "sg:phone":"+1 514 382 2342",
    "sg:postcode":"H2M 1M2",
    "sg:province":"QC",
    "sg:tags":[
        "removing"
    ],
    "wof:name":"Epiderma",
    "wof:placetype":"venue"
},
  "geometry": {"coordinates":[-73.640244,45.544228],"type":"Point"}
}