{
  "type": "Feature",
  "properties": {
    "addr:full":"Kamloops BC V2C 4A6",
    "addr:postcode":"bc v2c 4a6",
    "iso:country":"CA",
    "sg:city":"Kamloops",
    "sg:classifiers":[
        {
            "category":"Wholesale",
            "subcategory":"Furniture",
            "type":"Manufacturing & Wholesale Goods"
        }
    ],
    "sg:phone":"+1 250 374 8871",
    "sg:postcode":"V2C 4A6",
    "sg:province":"BC",
    "sg:tags":[
        "supply"
    ],
    "wof:name":"City Paper Basics",
    "wof:placetype":"venue"
},
  "geometry": {"coordinates":[-120.266693,50.67989],"type":"Point"}
}