{
  "type": "Feature",
  "properties": {
    "addr:full":"1717 5 St SW Calgary AB T2S 2A8",
    "addr:housenumber":"1717 5",
    "addr:postcode":"t2s 2a8",
    "addr:street":"St Sw",
    "iso:country":"CA",
    "sg:address":"1717 5 St SW",
    "sg:city":"Calgary",
    "sg:classifiers":[
        {
            "category":"Organizations",
            "subcategory":"Religious Organization",
            "type":"Services"
        }
    ],
    "sg:phone":"+1 403 228 3619",
    "sg:postcode":"T2S 2A8",
    "sg:province":"AB",
    "sg:tags":[
        "church"
    ],
    "wof:name":"Sainte-Famille Church",
    "wof:placetype":"venue"
},
  "geometry": {"coordinates":[-114.074325562,51.0376243591],"type":"Point"}
}