{
  "type": "Feature",
  "properties": {
    "iso:country":"CA",
    "sg:address":"2951 Carling Ave",
    "sg:city":"Ottawa",
    "sg:classifiers":[
        {
            "category":"Shopping",
            "type":"Retail Goods"
        }
    ],
    "sg:phone":"+1 613 828 7634",
    "sg:postcode":"K2B 8K6",
    "sg:province":"ON",
    "sg:tags":[
        "trophy",
        "medal",
        "award"
    ],
    "wof:name":"Familiar Faces Engraving Ltd",
    "wof:placetype":"venue"
},
  "geometry": {"coordinates":[-75.802635,45.356396],"type":"Point"}
}