{
  "type": "Feature",
  "properties": {
    "addr:full":"51454 Range Road 225 Sherwood Park AB T8C 1H5",
    "addr:housenumber":"51454",
    "addr:postcode":"t8c 1h5",
    "addr:street":"Range Road 225;Park",
    "iso:country":"CA",
    "sg:address":"51454 Range Road 225",
    "sg:city":"Sherwood Park",
    "sg:classifiers":[
        {
            "category":"Manufacturing",
            "subcategory":"Metals",
            "type":"Manufacturing & Wholesale Goods"
        }
    ],
    "sg:phone":"+1 780 417 3070",
    "sg:postcode":"T8C 1H5",
    "sg:province":"AB",
    "sg:tags":[
        "concrete",
        "contractor"
    ],
    "wof:name":"Tremm Construction Ltd",
    "wof:placetype":"venue"
},
  "geometry": {"coordinates":[-113.295738,53.526402],"type":"Point"}
}