{
  "type": "Feature",
  "properties": {
    "addr:full":"612 Berford St Wiarton ON N0H 2T0",
    "addr:housenumber":"612",
    "addr:postcode":"n0h 2t0",
    "addr:street":"Berford St",
    "iso:country":"CA",
    "sg:address":"612 Berford St",
    "sg:city":"Wiarton",
    "sg:classifiers":[
        {
            "category":"Home & Garden",
            "subcategory":"Furniture",
            "type":"Retail Goods"
        }
    ],
    "sg:phone":"+1 519 534 3320",
    "sg:postcode":"N0H 2T0",
    "sg:province":"ON",
    "wof:name":"Greyfair Furniture & Carpet",
    "wof:placetype":"venue"
},
  "geometry": {"coordinates":[-81.14109000000001,44.743397],"type":"Point"}
}