{
  "type": "Feature",
  "properties": {
    "addr:full":"Sharon ON L0G 1V0",
    "addr:postcode":"l0g 1v0",
    "iso:country":"CA",
    "sg:city":"Sharon",
    "sg:classifiers":[
        {
            "category":"Cinema",
            "subcategory":"Movie Rental",
            "type":"Entertainment"
        }
    ],
    "sg:phone":"+1 905 478 2480",
    "sg:postcode":"L0G 1V0",
    "sg:province":"ON",
    "sg:tags":[
        "leasing",
        "video",
        "disc",
        "tape"
    ],
    "wof:name":"D J's Video Hut",
    "wof:placetype":"venue"
},
  "geometry": {"coordinates":[-79.4416275024,44.1047058105],"type":"Point"}
}