{
  "type": "Feature",
  "properties": {
    "addr:full":"1055 West Broadway Vancouver V6H 1E2",
    "addr:housenumber":"1055",
    "addr:postcode":"v6h 1e2",
    "addr:street":"West Broadway",
    "iso:country":"CA",
    "sg:address":"1055 West Broadway",
    "sg:city":"Vancouver",
    "sg:classifiers":[
        {
            "category":"Professional",
            "subcategory":"Computer Services",
            "type":"Services"
        }
    ],
    "sg:postcode":"V6H 1E2",
    "sg:tags":[
        "social-media",
        "twitter",
        "advertising",
        "discovery",
        "social-network"
    ],
    "sg:website":"http://www.followformation.com/",
    "wof:name":"Followformation",
    "wof:placetype":"venue"
},
  "geometry": {"coordinates":[-123.12780650000001,49.2634565],"type":"Point"}
}