{
  "type": "Feature",
  "properties": {
    "addr:full":"17895 Leslie St Newmarket ON L3Y 3E3",
    "addr:housenumber":"17895",
    "addr:postcode":"l3y 3e3",
    "addr:street":"Leslie St",
    "iso:country":"CA",
    "sg:address":"17895 Leslie St",
    "sg:city":"Newmarket",
    "sg:classifiers":[
        {
            "category":"Education",
            "subcategory":"School",
            "type":"Public Place"
        }
    ],
    "sg:phone":"+1 905 836 1878",
    "sg:postcode":"L3Y 3E3",
    "sg:province":"ON",
    "wof:name":"Northern Montessori Schools",
    "wof:placetype":"venue"
},
  "geometry": {"coordinates":[-79.4341125488,44.0753555298],"type":"Point"}
}