{
  "type": "Feature",
  "properties": {
    "addr:full":"2640 Rue Allard Montreal QC H4E 2L6",
    "addr:housenumber":"2640",
    "addr:postcode":"h4e 2l6",
    "addr:street":"Rue Allard",
    "iso:country":"CA",
    "sg:address":"2640 Rue Allard",
    "sg:city":"Montreal",
    "sg:classifiers":[
        {
            "category":"Health Services",
            "subcategory":"Doctor",
            "type":"Services"
        }
    ],
    "sg:phone":"+1 514 761 4501",
    "sg:postcode":"H4E 2L6",
    "sg:province":"QC",
    "sg:tags":[
        "dentist"
    ],
    "wof:name":"Clinique Dentaire Lefrancois",
    "wof:placetype":"venue"
},
  "geometry": {"coordinates":[-73.59582519529999,45.4505500793],"type":"Point"}
}