{
  "type": "Feature",
  "properties": {
    "iso:country":"CA",
    "sg:address":"PO Box 1017",
    "sg:city":"Carrot River",
    "sg:classifiers":[
        {
            "category":"Farming",
            "subcategory":"Farm & Veterinary Services",
            "type":"Manufacturing & Wholesale Goods"
        }
    ],
    "sg:phone":"+1 306 768 7833",
    "sg:postcode":"S0E 0L0",
    "sg:province":"SK",
    "sg:tags":[
        "seed",
        "grain",
        "cleaning"
    ],
    "wof:name":"K/C Ag Ventures Ltd",
    "wof:placetype":"venue"
},
  "geometry": {"coordinates":[-103.587532044,53.2833595276],"type":"Point"}
}