{
  "type": "Feature",
  "properties": {
    "addr:full":"Waterdown ON L0R 2H0",
    "addr:postcode":"l0r 2h0",
    "iso:country":"CA",
    "sg:city":"Waterdown",
    "sg:classifiers":[
        {
            "category":"Personal",
            "subcategory":"Beauty Salon",
            "type":"Services"
        }
    ],
    "sg:phone":"+1 905 690 3094",
    "sg:postcode":"L0R 2H0",
    "sg:province":"ON",
    "wof:name":"Magiccuts",
    "wof:placetype":"venue"
},
  "geometry": {"coordinates":[-79.9021224976,43.3354644775],"type":"Point"}
}