{
  "type": "Feature",
  "properties": {
    "addr:full":"133 Mcmillan St Parksville BC V9P 2H5",
    "addr:housenumber":"133",
    "addr:postcode":"v9p 2h5",
    "addr:street":"Mcmillan St",
    "iso:country":"CA",
    "sg:address":"133 Mcmillan St",
    "sg:city":"Parksville",
    "sg:classifiers":[
        {
            "category":"Museum",
            "type":"Entertainment"
        }
    ],
    "sg:phone":"+1 250 248 8185",
    "sg:postcode":"V9P 2H5",
    "sg:province":"BC",
    "sg:tags":[
        "organization",
        "arts",
        "information"
    ],
    "wof:name":"Oceanside Community Arts Cncl",
    "wof:placetype":"venue"
},
  "geometry": {"coordinates":[-124.31694,49.319912],"type":"Point"}
}