{
  "type": "Feature",
  "properties": {
    "addr:full":"845 Rue Robichaud Tracadie-Sheila NB E1X 1B8",
    "addr:housenumber":"845",
    "addr:postcode":"e1x 1b8",
    "addr:street":"Rue Robichaud",
    "iso:country":"CA",
    "sg:address":"845 Rue Robichaud",
    "sg:city":"Tracadie-Sheila",
    "sg:classifiers":[
        {
            "category":"Building & Trades",
            "subcategory":"Construction",
            "type":"Services"
        }
    ],
    "sg:phone":"+1 506 395 4853",
    "sg:postcode":"E1X 1B8",
    "sg:province":"NB",
    "sg:tags":[
        "product",
        "asphalt"
    ],
    "wof:name":"Lavage Asphalte DE LA Peninsul",
    "wof:placetype":"venue"
},
  "geometry": {"coordinates":[-64.9247665405,47.4882049561],"type":"Point"}
}