{
  "type": "Feature",
  "properties": {
    "iso:country":"CA",
    "sg:city":"Richmond",
    "sg:classifiers":[
        {
            "category":"Food & Beverages",
            "subcategory":"Specialty",
            "type":"Retail Goods"
        }
    ],
    "sg:phone":"+1 604 273 5698",
    "sg:postcode":"V6Y 3X9",
    "sg:province":"BC",
    "sg:tags":[
        "health",
        "vitamin",
        "diet"
    ],
    "wof:name":"Healthy Alternatives Ltd",
    "wof:placetype":"venue"
},
  "geometry": {"coordinates":[-123.123848,49.155323],"type":"Point"}
}