{
  "type": "Feature",
  "properties": {
    "iso:country":"CA",
    "sg:city":"Kamloops",
    "sg:classifiers":[
        {
            "category":"Personal",
            "subcategory":"Barber",
            "type":"Services"
        }
    ],
    "sg:phone":"+1 250 376 3211",
    "sg:postcode":"V2B 3L9",
    "sg:province":"BC",
    "wof:name":"Gino's Barber & Hairstylist",
    "wof:placetype":"venue"
},
  "geometry": {"coordinates":[-120.393501,50.700027],"type":"Point"}
}