{
  "type": "Feature",
  "properties": {
    "iso:country":"CA",
    "sg:address":"931 Commissioners Rd E",
    "sg:city":"London",
    "sg:classifiers":[
        {
            "category":"Shopping",
            "type":"Retail Goods"
        }
    ],
    "sg:phone":"+1 519 686 9682",
    "sg:postcode":"N5Z 3H9",
    "sg:province":"ON",
    "sg:tags":[
        "limb",
        "artificial"
    ],
    "wof:name":"London Prosthetics CO Ltd",
    "wof:placetype":"venue"
},
  "geometry": {"coordinates":[-81.213478,42.959419],"type":"Point"}
}