{
  "type": "Feature",
  "properties": {
    "addr:full":"931 Commissioners Rd E London ON N5Z 3H9",
    "addr:housenumber":"931",
    "addr:postcode":"n5z 3h9",
    "addr:street":"Commissioners Rd E",
    "iso:country":"CA",
    "sg:address":"931 Commissioners Rd E",
    "sg:city":"London",
    "sg:classifiers":[
        {
            "category":"Shopping",
            "type":"Retail Goods"
        }
    ],
    "sg:phone":"+1 519 686 9682",
    "sg:postcode":"N5Z 3H9",
    "sg:province":"ON",
    "sg:tags":[
        "limb",
        "artificial"
    ],
    "wof:name":"London Prosthetics CO Ltd",
    "wof:placetype":"venue"
},
  "geometry": {"coordinates":[-81.21347799999999,42.959419],"type":"Point"}
}