{
  "type": "Feature",
  "properties": {
    "addr:full":"2325 Boul Ford Chateauguay QC J6J 4Z2",
    "addr:housenumber":"2325",
    "addr:postcode":"j6j 4z2",
    "addr:street":"Boul Ford",
    "iso:country":"CA",
    "sg:address":"2325 Boul Ford",
    "sg:city":"Chateauguay",
    "sg:classifiers":[
        {
            "category":"Building & Trades",
            "subcategory":"Plumbing",
            "type":"Services"
        }
    ],
    "sg:phone":"+1 514 856 7774",
    "sg:postcode":"J6J 4Z2",
    "sg:province":"QC",
    "sg:tags":[
        "conditioning",
        "air",
        "system",
        "contractor"
    ],
    "wof:name":"Groupe N & R Sol Inc",
    "wof:placetype":"venue"
},
  "geometry": {"coordinates":[-73.6837310791,45.3453483582],"type":"Point"}
}