{
  "type": "Feature",
  "properties": {
    "addr:full":"2943 Bloor St W Etobicoke ON M8X 1B3",
    "addr:housenumber":"2943",
    "addr:postcode":"m8x 1b3",
    "addr:street":"Bloor St W",
    "iso:country":"CA",
    "sg:address":"2943 Bloor St W",
    "sg:city":"Etobicoke",
    "sg:classifiers":[
        {
            "category":"Health Services",
            "subcategory":"Doctor",
            "type":"Services"
        }
    ],
    "sg:phone":"+1 416 231 4562",
    "sg:postcode":"M8X 1B3",
    "sg:province":"ON",
    "sg:tags":[
        "dentist"
    ],
    "wof:name":"Princeview Dental Group",
    "wof:placetype":"venue"
},
  "geometry": {"coordinates":[-79.50754499999999,43.648113],"type":"Point"}
}