{
  "type": "Feature",
  "properties": {
    "iso:country":"CA",
    "sg:address":"525 Bay St",
    "sg:city":"Toronto",
    "sg:classifiers":[
        {
            "category":"Personal",
            "type":"Services"
        }
    ],
    "sg:phone":"+1 416 597 0018",
    "sg:postcode":"M5G 2L2",
    "sg:province":"ON",
    "sg:tags":[
        "therapist",
        "massage"
    ],
    "wof:name":"Toronto Retreats Massage Thrpy",
    "wof:placetype":"venue"
},
  "geometry": {"coordinates":[-79.3832321167,43.6549034119],"type":"Point"}
}