{
  "type": "Feature",
  "properties": {
    "addr:full":"8350 Prince Edward St Vancouver BC V5X 3R9",
    "addr:housenumber":"8350",
    "addr:postcode":"v5x 3r9",
    "addr:street":"Prince Edward St",
    "iso:country":"CA",
    "sg:address":"8350 Prince Edward St",
    "sg:city":"Vancouver",
    "sg:classifiers":[
        {
            "category":"Freight",
            "type":"Transportation"
        }
    ],
    "sg:phone":"+1 604 685 5900",
    "sg:postcode":"V5X 3R9",
    "sg:province":"BC",
    "sg:tags":[
        "courier"
    ],
    "wof:name":"Corp Couriers Ltd",
    "wof:placetype":"venue"
},
  "geometry": {"coordinates":[-123.098236,49.208546],"type":"Point"}
}