{
  "type": "Feature",
  "properties": {
    "addr:full":"1762 Boul Saint-Joseph Lachine QC H8S 2N2",
    "addr:housenumber":"1762",
    "addr:postcode":"h8s 2n2",
    "addr:street":"Boul Saint-Joseph",
    "iso:country":"CA",
    "sg:address":"1762 Boul Saint-Joseph",
    "sg:city":"Lachine",
    "sg:classifiers":[
        {
            "category":"Professional",
            "subcategory":"Advertising",
            "type":"Services"
        }
    ],
    "sg:phone":"+1 514 634 2072",
    "sg:postcode":"H8S 2N2",
    "sg:province":"QC",
    "sg:tags":[
        "counselor",
        "publicity"
    ],
    "wof:name":"Communications Jm Breton",
    "wof:placetype":"venue"
},
  "geometry": {"coordinates":[-73.680046,45.432858],"type":"Point"}
}