{
  "type": "Feature",
  "properties": {
    "addr:full":"115 Cottingham St Toronto ON M4V 1B9",
    "addr:housenumber":"115",
    "addr:postcode":"m4v 1b9",
    "addr:street":"Cottingham St",
    "iso:country":"CA",
    "sg:address":"115 Cottingham St",
    "sg:city":"Toronto",
    "sg:classifiers":[
        {
            "category":"Professional",
            "type":"Services"
        }
    ],
    "sg:phone":"+1 416 967 7766",
    "sg:postcode":"M4V 1B9",
    "sg:province":"ON",
    "sg:tags":[
        "interior",
        "consultant",
        "design",
        "establishment",
        "decorator"
    ],
    "wof:name":"Carol Mc Farlane Interiors",
    "wof:placetype":"venue"
},
  "geometry": {"coordinates":[-79.39688110349999,43.6796035767],"type":"Point"}
}