{
  "type": "Feature",
  "properties": {
    "addr:full":"Vancouver BC V5T 3J9",
    "addr:postcode":"v5t 3j9",
    "iso:country":"CA",
    "sg:city":"Vancouver",
    "sg:classifiers":[
        {
            "category":"Shopping",
            "subcategory":"Clothing, Apparel, & Fashions",
            "type":"Retail Goods"
        }
    ],
    "sg:phone":"+1 604 708 2183",
    "sg:postcode":"V5T 3J9",
    "sg:province":"BC",
    "sg:tags":[
        "tailor"
    ],
    "wof:name":"Tad Deg Holdings Ltd",
    "wof:placetype":"venue"
},
  "geometry": {"coordinates":[-123.09298706,49.257598877],"type":"Point"}
}