{
  "type": "Feature",
  "properties": {
    "addr:full":"Farm Prince Albert SK S6V 5P9",
    "addr:postcode":"s6v 5p9",
    "addr:street":"Albert",
    "iso:country":"CA",
    "sg:address":"Farm",
    "sg:city":"Prince Albert",
    "sg:classifiers":[
        {
            "category":"Building & Trades",
            "subcategory":"Landscaping Services",
            "type":"Services"
        }
    ],
    "sg:phone":"+1 306 764 8995",
    "sg:postcode":"S6V 5P9",
    "sg:province":"SK",
    "sg:tags":[
        "landscape",
        "contractor"
    ],
    "wof:name":"Ed's Landscaping",
    "wof:placetype":"venue"
},
  "geometry": {"coordinates":[-105.752876282,53.1994400024],"type":"Point"}
}