{
  "type": "Feature",
  "properties": {
    "addr:full":"105 132 Rte W Saint-Michel-DE-Bellechasse QC G0R 3S0",
    "addr:housenumber":"132",
    "addr:postcode":"g0r 3s0",
    "addr:street":"Rte W",
    "iso:country":"CA",
    "sg:address":"105 132 Rte W",
    "sg:city":"Saint-Michel-DE-Bellechasse",
    "sg:classifiers":[
        {
            "category":"Retail",
            "subcategory":"Auto Repair",
            "type":"Services"
        }
    ],
    "sg:phone":"+1 418 884 2455",
    "sg:postcode":"G0R 3S0",
    "sg:province":"QC",
    "sg:tags":[
        "repairing",
        "automobile"
    ],
    "wof:name":"Garage Rejean Theberge",
    "wof:placetype":"venue"
},
  "geometry": {"coordinates":[-70.91185760499999,46.8715324402],"type":"Point"}
}