{
  "type": "Feature",
  "properties": {
    "iso:country":"CA",
    "sg:city":"Pointe-Claire",
    "sg:classifiers":[
        {
            "category":"Professional",
            "subcategory":"Accounting & Tax Preparation",
            "type":"Services"
        }
    ],
    "sg:phone":"+1 514 694 7274",
    "sg:postcode":"H9R 5K3",
    "sg:province":"QC",
    "sg:tags":[
        "accountant"
    ],
    "wof:name":"Baronello, Joseph CA",
    "wof:placetype":"venue"
},
  "geometry": {"coordinates":[-73.830505,45.469242],"type":"Point"}
}