{
  "type": "Feature",
  "properties": {
    "addr:full":"PO Box 32 Vimy AB T0G 2J0",
    "addr:housenumber":"po box 32",
    "addr:postcode":"t0g 2j0",
    "iso:country":"CA",
    "sg:address":"PO Box 32",
    "sg:city":"Vimy",
    "sg:classifiers":[
        {
            "category":"Retail",
            "subcategory":"Repair Shop",
            "type":"Services"
        }
    ],
    "sg:phone":"+1 780 961 3835",
    "sg:postcode":"T0G 2J0",
    "sg:province":"AB",
    "sg:tags":[
        "welding"
    ],
    "wof:name":"New Concept Mfg Ltd",
    "wof:placetype":"venue"
},
  "geometry": {"coordinates":[-113.625443,54.079418],"type":"Point"}
}