{
  "type": "Feature",
  "properties": {
    "addr:full":"1760 Dundas St E Mississauga ON L4X 1L8",
    "addr:housenumber":"1760",
    "addr:postcode":"l4x 1l8",
    "addr:street":"Dundas St E",
    "iso:country":"CA",
    "sg:address":"1760 Dundas St E",
    "sg:city":"Mississauga",
    "sg:classifiers":[
        {
            "category":"Retail",
            "subcategory":"Veterinary Services",
            "type":"Services"
        }
    ],
    "sg:phone":"+1 905 270 5444",
    "sg:postcode":"L4X 1L8",
    "sg:province":"ON",
    "sg:tags":[
        "veterinarian"
    ],
    "wof:name":"Dixie Animal Hospital",
    "wof:placetype":"venue"
},
  "geometry": {"coordinates":[-79.57517242430001,43.6170845032],"type":"Point"}
}