{
  "type": "Feature",
  "properties": {
    "iso:country":"CA",
    "sg:address":"330 Main St",
    "sg:city":"Manitou",
    "sg:classifiers":[
        {
            "category":"Professional",
            "subcategory":"Lawyer & Legal Services",
            "type":"Services"
        }
    ],
    "sg:phone":"+1 204 242 2187",
    "sg:postcode":"R0G 1G0",
    "sg:province":"MB",
    "sg:tags":[
        "attorney"
    ],
    "wof:name":"Mc Culloch Law Office",
    "wof:placetype":"venue"
},
  "geometry": {"coordinates":[-98.53885650629999,49.2403297424],"type":"Point"}
}