{
  "type": "Feature",
  "properties": {
    "addr:full":"Wickham QC J0C 1S0",
    "addr:postcode":"j0c 1s0",
    "iso:country":"CA",
    "sg:city":"Wickham",
    "sg:classifiers":[
        {
            "category":"Manufacturing",
            "subcategory":"Glass & Minerals",
            "type":"Manufacturing & Wholesale Goods"
        }
    ],
    "sg:phone":"+1 819 398 7120",
    "sg:postcode":"J0C 1S0",
    "sg:province":"QC",
    "sg:tags":[
        "fabricator",
        "fiber"
    ],
    "wof:name":"Fibre DE Verre Rg Enr",
    "wof:placetype":"venue"
},
  "geometry": {"coordinates":[-72.700394,45.988552],"type":"Point"}
}