{
  "type": "Feature",
  "properties": {
    "addr:full":"1018 Rue Gilford Montreal QC H2J 1P6",
    "addr:housenumber":"1018",
    "addr:postcode":"h2j 1p6",
    "addr:street":"Rue Gilford",
    "iso:country":"CA",
    "sg:address":"1018 Rue Gilford",
    "sg:city":"Montreal",
    "sg:classifiers":[
        {
            "category":"Communications",
            "subcategory":"Film & Video Production",
            "type":"Services"
        }
    ],
    "sg:phone":"+1 514 596 3951",
    "sg:postcode":"H2J 1P6",
    "sg:province":"QC",
    "sg:tags":[
        "motion",
        "picture",
        "studio",
        "producer"
    ],
    "wof:name":"Kinograph Inc",
    "wof:placetype":"venue"
},
  "geometry": {"coordinates":[-73.58294677729999,45.5290412903],"type":"Point"}
}