{
  "type": "Feature",
  "properties": {
    "iso:country":"CA",
    "sg:address":"4273 Main St",
    "sg:city":"Vancouver",
    "sg:classifiers":[
        {
            "category":"Personal",
            "subcategory":"Beauty Salon",
            "type":"Services"
        }
    ],
    "sg:phone":"+1 604 876 7289",
    "sg:postcode":"V5V 3P8",
    "sg:province":"BC",
    "wof:name":"C & D Hair Salon",
    "wof:placetype":"venue"
},
  "geometry": {"coordinates":[-123.101318359,49.2473907471],"type":"Point"}
}