{
  "type": "Feature",
  "properties": {
    "iso:country":"CA",
    "sg:address":"355 Park St",
    "sg:city":"Regina",
    "sg:classifiers":[
        {
            "category":"Government",
            "subcategory":"Office",
            "type":"Public Place"
        }
    ],
    "sg:phone":"+1 306 780 5035",
    "sg:postcode":"S4N 5B2",
    "sg:province":"SK",
    "wof:name":"Canada Grain Commission",
    "wof:placetype":"venue"
},
  "geometry": {"coordinates":[-104.579307556,50.4729042053],"type":"Point"}
}