{
  "type": "Feature",
  "properties": {
    "addr:full":"115 Burrows Ave W Melfort SK S0E 1A0",
    "addr:housenumber":"115",
    "addr:postcode":"s0e 1a0",
    "addr:street":"Burrows Ave W Melfort",
    "iso:country":"CA",
    "sg:address":"115 Burrows Ave W",
    "sg:city":"Melfort",
    "sg:classifiers":[
        {
            "category":"Home & Garden",
            "subcategory":"Carpets & Floor Coverings",
            "type":"Retail Goods"
        }
    ],
    "sg:phone":"+1 306 752 5227",
    "sg:postcode":"S0E 1A0",
    "sg:province":"SK",
    "wof:name":"Floors & More",
    "wof:placetype":"venue"
},
  "geometry": {"coordinates":[-104.61142700000001,52.860573],"type":"Point"}
}