{
  "type": "Feature",
  "properties": {
    "iso:country":"CA",
    "sg:address":"4450 Rue Belanger",
    "sg:city":"Montreal",
    "sg:classifiers":[
        {
            "category":"Building & Trades",
            "subcategory":"Construction",
            "type":"Services"
        }
    ],
    "sg:phone":"+1 514 729 0008",
    "sg:postcode":"H1T 1B5",
    "sg:province":"QC",
    "sg:tags":[
        "painter"
    ],
    "wof:name":"Guy Brunelle Inc",
    "wof:placetype":"venue"
},
  "geometry": {"coordinates":[-73.58400726319999,45.5685005188],"type":"Point"}
}