{
  "type": "Feature",
  "properties": {
    "addr:full":"469 William St S Exeter ON N0M 1S2",
    "addr:housenumber":"469",
    "addr:postcode":"n0m 1s2",
    "addr:street":"William St S",
    "iso:country":"CA",
    "sg:address":"469 William St S",
    "sg:city":"Exeter",
    "sg:classifiers":[
        {
            "category":"Health Services",
            "subcategory":"Doctor",
            "type":"Services"
        }
    ],
    "sg:phone":"+1 519 235 0910",
    "sg:postcode":"N0M 1S2",
    "sg:province":"ON",
    "sg:tags":[
        "physician",
        "surgeon"
    ],
    "wof:name":"Jadd, J L MD",
    "wof:placetype":"venue"
},
  "geometry": {"coordinates":[-81.481514,43.343609],"type":"Point"}
}