{
  "type": "Feature",
  "properties": {
    "addr:full":"50 Rue St Cajetan Armagh QC G0R 1A0",
    "addr:housenumber":"50",
    "addr:postcode":"g0r 1a0",
    "addr:street":"Rue St",
    "iso:country":"CA",
    "sg:address":"50 Rue St Cajetan",
    "sg:city":"Armagh",
    "sg:classifiers":[
        {
            "category":"Building & Trades",
            "subcategory":"Electrical",
            "type":"Services"
        }
    ],
    "sg:phone":"+1 418 466 2410",
    "sg:postcode":"G0R 1A0",
    "sg:province":"QC",
    "sg:tags":[
        "electric",
        "contractor"
    ],
    "wof:name":"Entreprises Claude Cote Inc",
    "wof:placetype":"venue"
},
  "geometry": {"coordinates":[-70.5859527588,46.7416000366],"type":"Point"}
}