{
  "type": "Feature",
  "properties": {
    "iso:country":"CA",
    "sg:address":"2323 Rue Galvani",
    "sg:city":"Sainte-Foy",
    "sg:classifiers":[
        {
            "category":"Professional",
            "subcategory":"Computer Services",
            "type":"Services"
        }
    ],
    "sg:phone":"+1 418 681 4590",
    "sg:postcode":"G1N 4G3",
    "sg:province":"QC",
    "sg:tags":[
        "internet"
    ],
    "wof:name":"Edream",
    "wof:placetype":"venue"
},
  "geometry": {"coordinates":[-71.289391,46.788628],"type":"Point"}
}