{
  "type": "Feature",
  "properties": {
    "iso:country":"CA",
    "sg:city":"North Vancouver",
    "sg:classifiers":[
        {
            "category":"Manufacturing",
            "subcategory":"Printing",
            "type":"Manufacturing & Wholesale Goods"
        }
    ],
    "sg:phone":"+1 604 904 5656",
    "sg:postcode":"V7P 3P2",
    "sg:province":"BC",
    "sg:tags":[
        "printer"
    ],
    "wof:name":"A J Print",
    "wof:placetype":"venue"
},
  "geometry": {"coordinates":[-123.093628,49.321259],"type":"Point"}
}