{
  "type": "Feature",
  "properties": {
    "addr:full":"5 Mile Rd Princeton BC V0X 1W0",
    "addr:postcode":"v0x 1w0",
    "addr:street":"5 Mile Rd",
    "iso:country":"CA",
    "sg:address":"5 Mile Rd",
    "sg:city":"Princeton",
    "sg:classifiers":[
        {
            "category":"Manufacturing",
            "subcategory":"Lumber",
            "type":"Manufacturing & Wholesale Goods"
        }
    ],
    "sg:phone":"+1 250 295 3016",
    "sg:postcode":"V0X 1W0",
    "sg:province":"BC",
    "sg:tags":[
        "company",
        "logging"
    ],
    "wof:name":"Jebway Logging & Contracting",
    "wof:placetype":"venue"
},
  "geometry": {"coordinates":[-120.505897522,49.4586753845],"type":"Point"}
}