{
  "type": "Feature",
  "properties": {
    "iso:country":"CA",
    "sg:address":"219 Lorne Ave W",
    "sg:city":"Stratford",
    "sg:phone":"+1 519 272 0090",
    "sg:postcode":"N5A 6S4",
    "sg:province":"ON",
    "sg:tags":[
        "oil"
    ],
    "wof:name":"Core Fuels Ltd",
    "wof:placetype":"venue"
},
  "geometry": {"coordinates":[-81.007034,43.36063],"type":"Point"}
}