{
  "type": "Feature",
  "properties": {
    "addr:full":"10334 Alaska Rd Fort St John BC V1J 1B2",
    "addr:housenumber":"10334",
    "addr:postcode":"v1j 1b2",
    "addr:street":"Alaska Rd",
    "iso:country":"CA",
    "sg:address":"10334 Alaska Rd",
    "sg:city":"Fort St John",
    "sg:classifiers":[
        {
            "category":"Utilities",
            "subcategory":"Mobile Phone",
            "type":"Services"
        }
    ],
    "sg:phone":"+1 250 785 6084",
    "sg:postcode":"V1J 1B2",
    "sg:province":"BC",
    "sg:tags":[
        "communications",
        "telephone",
        "cellular",
        "consultant"
    ],
    "wof:name":"Glentel Wireless Wave",
    "wof:placetype":"venue"
},
  "geometry": {"coordinates":[-120.85388946499999,56.2398872375],"type":"Point"}
}