{
  "type": "Feature",
  "properties": {
    "iso:country":"CA",
    "sg:city":"Woodbridge",
    "sg:classifiers":[
        {
            "category":"Home & Garden",
            "subcategory":"Home Furnishings",
            "type":"Retail Goods"
        }
    ],
    "sg:phone":"+1 905 851 8080",
    "sg:postcode":"L4L 6C3",
    "sg:province":"ON",
    "sg:tags":[
        "venetian",
        "blind",
        "made",
        "drapery"
    ],
    "wof:name":"Sunset Window Coverings Ltd",
    "wof:placetype":"venue"
},
  "geometry": {"coordinates":[-79.55217,43.787285],"type":"Point"}
}