{
  "type": "Feature",
  "properties": {
    "addr:full":"275 Matheson Blvd E Mississauga ON L4Z 1X8",
    "addr:housenumber":"275",
    "addr:postcode":"l4z 1x8",
    "addr:street":"Matheson Blvd E",
    "iso:country":"CA",
    "sg:address":"275 Matheson Blvd E",
    "sg:city":"Mississauga",
    "sg:classifiers":[
        {
            "category":"Organizations",
            "subcategory":"Labor Organization",
            "type":"Services"
        }
    ],
    "sg:phone":"+1 905 502 0062",
    "sg:postcode":"L4Z 1X8",
    "sg:province":"ON",
    "wof:name":"Teamsters Union",
    "wof:placetype":"venue"
},
  "geometry": {"coordinates":[-79.663651,43.622406],"type":"Point"}
}