{
  "type": "Feature",
  "properties": {
    "addr:full":"2320 Rue King O Sherbrooke QC J1J 2E8",
    "addr:housenumber":"2320",
    "addr:postcode":"j1j 2e8",
    "addr:street":"Rue King O",
    "iso:country":"CA",
    "sg:address":"2320 Rue King O",
    "sg:city":"Sherbrooke",
    "sg:classifiers":[
        {
            "category":"Home & Garden",
            "subcategory":"Building Materials",
            "type":"Retail Goods"
        }
    ],
    "sg:phone":"+1 819 566 6366",
    "sg:postcode":"J1J 2E8",
    "sg:province":"QC",
    "sg:tags":[
        "paint"
    ],
    "wof:name":"Glidden Ici Paint Ctr",
    "wof:placetype":"venue"
},
  "geometry": {"coordinates":[-71.929497,45.398178],"type":"Point"}
}