{
  "type": "Feature",
  "properties": {
    "addr:full":"1696 Rue Montcalm Montreal QC H2L 3H4",
    "addr:housenumber":"1696",
    "addr:postcode":"h2l 3h4",
    "addr:street":"Rue Montcalm",
    "iso:country":"CA",
    "sg:address":"1696 Rue Montcalm",
    "sg:city":"Montreal",
    "sg:classifiers":[
        {
            "category":"Recreation",
            "type":"Entertainment"
        }
    ],
    "sg:phone":"+1 514 596 0953",
    "sg:postcode":"H2L 3H4",
    "sg:province":"QC",
    "sg:tags":[
        "skating",
        "instruction"
    ],
    "wof:name":"Club DE Patinage Artistique",
    "wof:placetype":"venue"
},
  "geometry": {"coordinates":[-73.55944824220001,45.5196647644],"type":"Point"}
}