{
  "type": "Feature",
  "properties": {
    "addr:full":"1550 Second Ave Trail BC V1R 1M4",
    "addr:housenumber":"1550",
    "addr:postcode":"bc v1r 1m4",
    "addr:street":"Second Ave Trail",
    "iso:country":"CA",
    "sg:address":"1550 Second Ave",
    "sg:city":"Trail",
    "sg:classifiers":[
        {
            "category":"Health Services",
            "subcategory":"Doctor",
            "type":"Services"
        }
    ],
    "sg:phone":"+1 250 364 2700",
    "sg:postcode":"V1R 1M4",
    "sg:province":"BC",
    "sg:tags":[
        "dentist"
    ],
    "wof:name":"Peacock, Timothy DDS",
    "wof:placetype":"venue"
},
  "geometry": {"coordinates":[-117.702049,49.097992],"type":"Point"}
}