{
  "type": "Feature",
  "properties": {
    "addr:full":"223 Main St W Port Colborne ON L3K 3V7",
    "addr:housenumber":"223",
    "addr:postcode":"l3k 3v7",
    "addr:street":"Main St W",
    "iso:country":"CA",
    "sg:address":"223 Main St W",
    "sg:city":"Port Colborne",
    "sg:classifiers":[
        {
            "category":"Personal",
            "subcategory":"Beauty Salon",
            "type":"Services"
        }
    ],
    "sg:phone":"+1 905 835 8741",
    "sg:postcode":"L3K 3V7",
    "sg:province":"ON",
    "wof:name":"Pat's Hairstyling",
    "wof:placetype":"venue"
},
  "geometry": {"coordinates":[-79.2526397705,42.8997917175],"type":"Point"}
}