{
  "type": "Feature",
  "properties": {
    "addr:full":"Hwy 3 W Tisdale SK S0E 1T0",
    "addr:postcode":"s0e 1t0",
    "addr:street":"Hwy 3 W Tisdale",
    "iso:country":"CA",
    "sg:address":"Hwy 3 W",
    "sg:city":"Tisdale",
    "sg:classifiers":[
        {
            "category":"Manufacturing",
            "subcategory":"Tools & Machinery",
            "type":"Manufacturing & Wholesale Goods"
        }
    ],
    "sg:phone":"+1 306 873 2613",
    "sg:postcode":"S0E 1T0",
    "sg:province":"SK",
    "sg:tags":[
        "contractor"
    ],
    "wof:name":"Kramer Limited",
    "wof:placetype":"venue"
},
  "geometry": {"coordinates":[-104.06793999999999,52.841824],"type":"Point"}
}