{
  "type": "Feature",
  "properties": {
    "addr:full":"3580 Rue Caron Saint-Hubert QC J3Y 5L5",
    "addr:housenumber":"3580",
    "addr:postcode":"j3y 5l5",
    "addr:street":"Rue Caron",
    "iso:country":"CA",
    "sg:address":"3580 Rue Caron",
    "sg:city":"Saint-Hubert",
    "sg:classifiers":[
        {
            "category":"Building & Trades",
            "subcategory":"Electrical",
            "type":"Services"
        }
    ],
    "sg:phone":"+1 450 445 4549",
    "sg:postcode":"J3Y 5L5",
    "sg:province":"QC",
    "sg:tags":[
        "electric",
        "contractor"
    ],
    "wof:name":"Amv Installation Electrique",
    "wof:placetype":"venue"
},
  "geometry": {"coordinates":[-73.38166,45.467808],"type":"Point"}
}