{
  "type": "Feature",
  "properties": {
    "addr:full":"755 Gardiners Rd Kingston ON K7M 3Y5",
    "addr:housenumber":"755",
    "addr:postcode":"k7m 3y5",
    "addr:street":"Gardiners Rd",
    "iso:country":"CA",
    "sg:address":"755 Gardiners Rd",
    "sg:city":"Kingston",
    "sg:classifiers":[
        {
            "category":"Restaurant",
            "type":"Food & Drink"
        }
    ],
    "sg:phone":"+1 613 634 6670",
    "sg:postcode":"K7M 3Y5",
    "sg:province":"ON",
    "wof:name":"Boston Pizza",
    "wof:placetype":"venue"
},
  "geometry": {"coordinates":[-76.56838226319999,44.2485275269],"type":"Point"}
}