{
  "type": "Feature",
  "properties": {
    "addr:full":"PO Box 252 STN A Nanaimo BC V9R 5K9",
    "addr:housenumber":"po",
    "addr:postcode":"v9r 5k9",
    "addr:street":"Box 252 Stn A",
    "iso:country":"CA",
    "sg:address":"PO Box 252 STN A",
    "sg:city":"Nanaimo",
    "sg:classifiers":[
        {
            "category":"Building & Trades",
            "subcategory":"Construction",
            "type":"Services"
        }
    ],
    "sg:phone":"+1 250 753 3066",
    "sg:postcode":"V9R 5K9",
    "sg:province":"BC",
    "sg:tags":[
        "concrete",
        "contractor"
    ],
    "wof:name":"Jeffrey Contracting Ltd",
    "wof:placetype":"venue"
},
  "geometry": {"coordinates":[-123.936157227,49.1642684937],"type":"Point"}
}