{
  "type": "Feature",
  "properties": {
    "addr:full":"495 2nd Ave Prince George BC V2L 2Z6",
    "addr:housenumber":"495",
    "addr:postcode":"v2l 2z6",
    "addr:street":"2Nd Ave",
    "iso:country":"CA",
    "sg:address":"495 2nd Ave",
    "sg:city":"Prince George",
    "sg:phone":"+1 250 562 8316",
    "sg:postcode":"V2L 2Z6",
    "sg:province":"BC",
    "sg:tags":[
        "equipment",
        "ice",
        "supply"
    ],
    "wof:name":"Northern Food Equipment Ltd",
    "wof:placetype":"venue"
},
  "geometry": {"coordinates":[-122.732566834,53.9140396118],"type":"Point"}
}