{
  "type": "Feature",
  "properties": {
    "addr:full":"84 Hwy 39 E Estevan SK S4A 2H8",
    "addr:postcode":"s4a 2h8",
    "addr:street":"84 Hwy 39 E",
    "iso:country":"CA",
    "sg:address":"84 Hwy 39 E",
    "sg:city":"Estevan",
    "sg:classifiers":[
        {
            "category":"Mining & Drilling",
            "type":"Manufacturing & Wholesale Goods"
        }
    ],
    "sg:phone":"+1 306 634 5677",
    "sg:postcode":"S4A 2H8",
    "sg:province":"SK",
    "sg:tags":[
        "company",
        "oil"
    ],
    "wof:name":"Northrock Resources Ltd",
    "wof:placetype":"venue"
},
  "geometry": {"coordinates":[-102.956177,49.131458],"type":"Point"}
}