{
  "type": "Feature",
  "properties": {
    "addr:full":"101 Edgewater St Mahone Bay NS B0J 2E0",
    "addr:housenumber":"101",
    "addr:postcode":"b0j 2e0",
    "addr:street":"Edgewater St",
    "iso:country":"CA",
    "sg:address":"101 Edgewater St",
    "sg:city":"Mahone Bay",
    "sg:classifiers":[
        {
            "category":"Organizations",
            "subcategory":"Religious Organization",
            "type":"Services"
        }
    ],
    "sg:phone":"+1 902 624 9287",
    "sg:postcode":"B0J 2E0",
    "sg:province":"NS",
    "sg:tags":[
        "church"
    ],
    "wof:name":"Trinity United Church",
    "wof:placetype":"venue"
},
  "geometry": {"coordinates":[-64.3809432983,44.4522895813],"type":"Point"}
}