{
  "type": "Feature",
  "properties": {
    "addr:full":"1045 Wonderland Rd N London ON N6G 2Y9",
    "addr:housenumber":"1045",
    "addr:postcode":"n6g 2y9",
    "addr:street":"Wonderland Rd N",
    "iso:country":"CA",
    "sg:address":"1045 Wonderland Rd N",
    "sg:city":"London",
    "sg:classifiers":[
        {
            "category":"Recreation",
            "type":"Entertainment"
        }
    ],
    "sg:phone":"+1 519 661 4455",
    "sg:postcode":"N6G 2Y9",
    "sg:province":"ON",
    "sg:tags":[
        "government",
        "swimming"
    ],
    "wof:name":"City of London Aquatic Svc",
    "wof:placetype":"venue"
},
  "geometry": {"coordinates":[-81.3021392822,43.0020866394],"type":"Point"}
}