{
  "type": "Feature",
  "properties": {
    "addr:full":"135 Newcastle Blvd Miramichi NB E1V 2L9",
    "addr:housenumber":"135",
    "addr:postcode":"e1v 2l9",
    "addr:street":"Newcastle Blvd",
    "iso:country":"CA",
    "sg:address":"135 Newcastle Blvd",
    "sg:city":"Miramichi",
    "sg:classifiers":[
        {
            "category":"Restaurant",
            "type":"Food & Drink"
        }
    ],
    "sg:phone":"+1 506 622 2222",
    "sg:postcode":"E1V 2L9",
    "sg:province":"NB",
    "sg:tags":[
        "pizza"
    ],
    "wof:name":"Greco Pizza Donair",
    "wof:placetype":"venue"
},
  "geometry": {"coordinates":[-65.5654449463,47.002204895],"type":"Point"}
}