{
  "type": "Feature",
  "properties": {
    "addr:full":"180 Amber Trail Winnipeg MB R2P 2S4",
    "addr:housenumber":"180",
    "addr:postcode":"r2p 2s4",
    "addr:street":"Amber Trail",
    "iso:country":"CA",
    "sg:address":"180 Amber Trail",
    "sg:city":"Winnipeg",
    "sg:classifiers":[
        {
            "category":"Professional",
            "subcategory":"Management & Consulting",
            "type":"Services"
        }
    ],
    "sg:phone":"+1 204 633 6002",
    "sg:postcode":"R2P 2S4",
    "sg:province":"MB",
    "sg:tags":[
        "consultant",
        "business"
    ],
    "wof:name":"G Braha & Assoc Ltd",
    "wof:placetype":"venue"
},
  "geometry": {"coordinates":[-97.1657485962,49.9613265991],"type":"Point"}
}