{
  "type": "Feature",
  "properties": {
    "addr:full":"Milverton ON N0K 1M0",
    "addr:postcode":"n0k 1m0",
    "iso:country":"CA",
    "sg:city":"Milverton",
    "sg:classifiers":[
        {
            "category":"Freight",
            "type":"Transportation"
        }
    ],
    "sg:phone":"+1 519 656 2158",
    "sg:postcode":"N0K 1M0",
    "sg:province":"ON",
    "sg:tags":[
        "trucking"
    ],
    "wof:name":"Roth Elgin Transport Ltd",
    "wof:placetype":"venue"
},
  "geometry": {"coordinates":[-80.9208679199,43.5675125122],"type":"Point"}
}