{
  "type": "Feature",
  "properties": {
    "iso:country":"CA",
    "sg:address":"617 Rue Chabanel E",
    "sg:city":"Montreal",
    "sg:classifiers":[
        {
            "category":"Wholesale",
            "subcategory":"Fruits & Vegetables",
            "type":"Manufacturing & Wholesale Goods"
        }
    ],
    "sg:phone":"+1 514 384 5066",
    "sg:postcode":"H2M 1C6",
    "sg:province":"QC",
    "wof:name":"Jean-Paul Fruits & Legumes",
    "wof:placetype":"venue"
},
  "geometry": {"coordinates":[-73.647835,45.550228],"type":"Point"}
}