{
  "type": "Feature",
  "properties": {
    "addr:full":"19 Park St Liverpool NS B0T 1K0",
    "addr:housenumber":"19",
    "addr:postcode":"b0t 1k0",
    "addr:street":"Park St",
    "iso:country":"CA",
    "sg:address":"19 Park St",
    "sg:city":"Liverpool",
    "sg:classifiers":[
        {
            "category":"Organizations",
            "subcategory":"Professional Association",
            "type":"Services"
        }
    ],
    "sg:phone":"+1 902 354 2280",
    "sg:postcode":"B0T 1K0",
    "sg:province":"NS",
    "sg:tags":[
        "club"
    ],
    "wof:name":"Liverpool Tennis Club",
    "wof:placetype":"venue"
},
  "geometry": {"coordinates":[-64.71093,44.03783],"type":"Point"}
}