{
  "type": "Feature",
  "properties": {
    "iso:country":"CA",
    "sg:address":"184 Wilson Ave",
    "sg:city":"North York",
    "sg:classifiers":[
        {
            "category":"Food & Beverages",
            "subcategory":"Bakery",
            "type":"Retail Goods"
        }
    ],
    "sg:phone":"+1 416 481 1209",
    "sg:postcode":"M5M 4N7",
    "sg:province":"ON",
    "sg:tags":[
        "delicatessen"
    ],
    "wof:name":"Neighbours Bakery & Deli Ltd",
    "wof:placetype":"venue"
},
  "geometry": {"coordinates":[-79.4231338501,43.7396621704],"type":"Point"}
}