{
  "type": "Feature",
  "properties": {
    "addr:full":"22 2nd Ave W Vancouver BC V5Y 1B3",
    "addr:housenumber":"22",
    "addr:postcode":"v5y 1b3",
    "addr:street":"2Nd Ave W",
    "iso:country":"CA",
    "sg:address":"22 2nd Ave W",
    "sg:city":"Vancouver",
    "sg:classifiers":[
        {
            "category":"Professional",
            "subcategory":"Management & Consulting",
            "type":"Services"
        }
    ],
    "sg:phone":"+1 604 874 2226",
    "sg:postcode":"V5Y 1B3",
    "sg:province":"BC",
    "sg:tags":[
        "consultant",
        "lighting"
    ],
    "wof:name":"Sls Lighting",
    "wof:placetype":"venue"
},
  "geometry": {"coordinates":[-123.105217,49.269127],"type":"Point"}
}