{
  "type": "Feature",
  "properties": {
    "addr:full":"23 Frontenac Cres Kapuskasing ON P5N 2H6",
    "addr:housenumber":"23",
    "addr:postcode":"p5n 2h6",
    "addr:street":"Frontenac Cres",
    "iso:country":"CA",
    "sg:address":"23 Frontenac Cres",
    "sg:city":"Kapuskasing",
    "sg:classifiers":[
        {
            "category":"Building & Trades",
            "subcategory":"Plumbing",
            "type":"Services"
        }
    ],
    "sg:phone":"+1 705 335 6770",
    "sg:postcode":"P5N 2H6",
    "sg:province":"ON",
    "sg:tags":[
        "contractor"
    ],
    "wof:name":"Mitch's Plumbing & Heating",
    "wof:placetype":"venue"
},
  "geometry": {"coordinates":[-82.4094543457,49.4222221375],"type":"Point"}
}