{
  "type": "Feature",
  "properties": {
    "addr:full":"792 Queen St E Toronto ON M4M 1H4",
    "addr:housenumber":"792",
    "addr:postcode":"m4m 1h4",
    "addr:street":"Queen St E",
    "iso:country":"CA",
    "sg:address":"792 Queen St E",
    "sg:city":"Toronto",
    "sg:classifiers":[
        {
            "category":"Shopping",
            "subcategory":"Used Merchandise",
            "type":"Retail Goods"
        }
    ],
    "sg:phone":"+1 416 461 9913",
    "sg:postcode":"M4M 1H4",
    "sg:province":"ON",
    "sg:tags":[
        "antique"
    ],
    "wof:name":"Phil'z",
    "wof:placetype":"venue"
},
  "geometry": {"coordinates":[-79.346992,43.659657],"type":"Point"}
}