{
  "type": "Feature",
  "properties": {
    "iso:country":"CA",
    "sg:address":"265 Rue Saint-Jacques",
    "sg:city":"Montreal",
    "sg:classifiers":[
        {
            "category":"Banks & Credit Unions",
            "subcategory":"Bank",
            "type":"Services"
        }
    ],
    "sg:phone":"+1 514 845 2119",
    "sg:postcode":"H2Y 1M6",
    "sg:province":"QC",
    "wof:name":"Cibc",
    "wof:placetype":"venue"
},
  "geometry": {"coordinates":[-73.55908966059999,45.5032272339],"type":"Point"}
}