{
  "type": "Feature",
  "properties": {
    "addr:full":"Notre-Dame-Du-Lac QC G0L 1X0",
    "addr:postcode":"g0l 1x0",
    "iso:country":"CA",
    "sg:city":"Notre-Dame-Du-Lac",
    "sg:classifiers":[
        {
            "category":"Personal",
            "subcategory":"Beauty Salon",
            "type":"Services"
        }
    ],
    "sg:phone":"+1 418 899 6230",
    "sg:postcode":"G0L 1X0",
    "sg:province":"QC",
    "wof:name":"Salon DE Coiffure Direction 20",
    "wof:placetype":"venue"
},
  "geometry": {"coordinates":[-68.798424,47.613693],"type":"Point"}
}