{
  "type": "Feature",
  "properties": {
    "addr:full":"Vancouver BC V6J 4M6",
    "addr:postcode":"v6j 4m6",
    "iso:country":"CA",
    "sg:city":"Vancouver",
    "sg:classifiers":[
        {
            "category":"Professional",
            "subcategory":"Employment Agencies",
            "type":"Services"
        }
    ],
    "sg:phone":"+1 604 739 0100",
    "sg:postcode":"V6J 4M6",
    "sg:province":"BC",
    "sg:tags":[
        "opportunity"
    ],
    "wof:name":"Dunhill Professional Search",
    "wof:placetype":"venue"
},
  "geometry": {"coordinates":[-123.146644592,49.2708702087],"type":"Point"}
}