{
  "type": "Feature",
  "properties": {
    "addr:full":"31 Rue Eugenie Salaberry-DE-Valleyfield QC J6S 2W4",
    "addr:housenumber":"31",
    "addr:postcode":"j6s 2w4",
    "addr:street":"Rue Eugenie",
    "iso:country":"CA",
    "sg:address":"31 Rue Eugenie",
    "sg:city":"Salaberry-DE-Valleyfield",
    "sg:classifiers":[
        {
            "category":"Bars & Pubs",
            "type":"Food & Drink"
        }
    ],
    "sg:phone":"+1 450 373 6960",
    "sg:postcode":"J6S 2W4",
    "sg:province":"QC",
    "sg:tags":[
        "lounge",
        "cocktail"
    ],
    "wof:name":"Bar Chez Gas",
    "wof:placetype":"venue"
},
  "geometry": {"coordinates":[-74.148529,45.25906],"type":"Point"}
}