{
  "type": "Feature",
  "properties": {
    "addr:full":"185 Rue Du Moulin Saint-Eustache QC J7R 2P5",
    "addr:housenumber":"185",
    "addr:postcode":"j7r 2p5",
    "addr:street":"Rue Du Moulin",
    "iso:country":"CA",
    "sg:address":"185 Rue Du Moulin",
    "sg:city":"Saint-Eustache",
    "sg:classifiers":[
        {
            "category":"Social Services",
            "type":"Services"
        }
    ],
    "sg:phone":"+1 450 623 1561",
    "sg:postcode":"J7R 2P5",
    "sg:province":"QC",
    "sg:tags":[
        "organization",
        "association",
        "welfare"
    ],
    "wof:name":"Atelier Ensemble on SE Tient",
    "wof:placetype":"venue"
},
  "geometry": {"coordinates":[-73.897453,45.560539],"type":"Point"}
}