{
  "type": "Feature",
  "properties": {
    "addr:full":"44 Saint Regis Cres S North York ON M3J 1Y5",
    "addr:housenumber":"44",
    "addr:postcode":"m3j 1y5",
    "addr:street":"Saint Regis Cres S North",
    "iso:country":"CA",
    "sg:address":"44 Saint Regis Cres S",
    "sg:city":"North York",
    "sg:classifiers":[
        {
            "category":"Wholesale",
            "subcategory":"Apparel",
            "type":"Manufacturing & Wholesale Goods"
        }
    ],
    "sg:phone":"+1 416 398 2517",
    "sg:postcode":"M3J 1Y5",
    "sg:province":"ON",
    "sg:tags":[
        "clothing"
    ],
    "wof:name":"Spagnolo Imports & Distr",
    "wof:placetype":"venue"
},
  "geometry": {"coordinates":[-79.486389,43.755154],"type":"Point"}
}