{
  "type": "Feature",
  "properties": {
    "addr:full":"7184 Frog St Pefferlaw ON L0E 1N0",
    "addr:housenumber":"7184",
    "addr:postcode":"l0e 1n0",
    "addr:street":"Frog St",
    "iso:country":"CA",
    "sg:address":"7184 Frog St",
    "sg:city":"Pefferlaw",
    "sg:classifiers":[
        {
            "category":"Wholesale",
            "subcategory":"Farm Supplies",
            "type":"Manufacturing & Wholesale Goods"
        }
    ],
    "sg:phone":"+1 905 722 3783",
    "sg:postcode":"L0E 1N0",
    "sg:province":"ON",
    "sg:tags":[
        "livestock"
    ],
    "wof:name":"Pleasant View Farms Ltd",
    "wof:placetype":"venue"
},
  "geometry": {"coordinates":[-79.19375599999999,44.311722],"type":"Point"}
}