{
  "type": "Feature",
  "properties": {
    "addr:full":"PO Box 117 Hare Bay Bb NL A0G 2P0",
    "addr:housenumber":"po;bb",
    "addr:postcode":"a0g 2p0",
    "addr:street":"Box 117 Hare Bay",
    "iso:country":"CA",
    "sg:address":"PO Box 117",
    "sg:city":"Hare Bay Bb",
    "sg:classifiers":[
        {
            "category":"Education",
            "subcategory":"Library",
            "type":"Public Place"
        }
    ],
    "sg:phone":"+1 709 537 2391",
    "sg:postcode":"A0G 2P0",
    "sg:province":"NL",
    "wof:name":"Hare Bay Public Library",
    "wof:placetype":"venue"
},
  "geometry": {"coordinates":[-54.010029,48.854649],"type":"Point"}
}