{
  "type": "Feature",
  "properties": {
    "addr:full":"Surrey BC V4A 4N7",
    "addr:postcode":"v4a 4n7",
    "iso:country":"CA",
    "sg:city":"Surrey",
    "sg:classifiers":[
        {
            "category":"Health Services",
            "subcategory":"Optometrist",
            "type":"Services"
        }
    ],
    "sg:phone":"+1 604 531 4274",
    "sg:postcode":"V4A 4N7",
    "sg:province":"BC",
    "wof:name":"Boardwalk Optometry",
    "wof:placetype":"venue"
},
  "geometry": {"coordinates":[-122.801368713,49.0395278931],"type":"Point"}
}