{
  "type": "Feature",
  "properties": {
    "iso:country":"CA",
    "sg:address":"150 Glendale Ave",
    "sg:city":"St Catharines",
    "sg:classifiers":[
        {
            "category":"Organizations",
            "subcategory":"Religious Organization",
            "type":"Services"
        }
    ],
    "sg:phone":"+1 905 682 0944",
    "sg:postcode":"L2T 2K1",
    "sg:province":"ON",
    "sg:tags":[
        "church"
    ],
    "wof:name":"Mountainview United Church",
    "wof:placetype":"venue"
},
  "geometry": {"coordinates":[-79.235092,43.133862],"type":"Point"}
}