{
  "type": "Feature",
  "properties": {
    "iso:country":"CA",
    "sg:address":"2814 48 Ave",
    "sg:city":"Vernon",
    "sg:classifiers":[
        {
            "category":"Government",
            "subcategory":"Office",
            "type":"Public Place"
        }
    ],
    "sg:phone":"+1 250 260 5030",
    "sg:postcode":"V1T 3R4",
    "sg:province":"BC",
    "wof:name":"Canadian Food Inspection Agcy",
    "wof:placetype":"venue"
},
  "geometry": {"coordinates":[-119.268348694,50.2818374634],"type":"Point"}
}