{
  "type": "Feature",
  "properties": {
    "addr:full":"29 11th St E Prince Albert SK S6V 0Z8",
    "addr:housenumber":"29",
    "addr:postcode":"s6v 0z8",
    "addr:street":"11Th St",
    "iso:country":"CA",
    "sg:address":"29 11th St E",
    "sg:city":"Prince Albert",
    "sg:classifiers":[
        {
            "category":"Professional",
            "subcategory":"Management & Consulting",
            "type":"Services"
        }
    ],
    "sg:phone":"+1 306 763 8558",
    "sg:postcode":"S6V 0Z8",
    "sg:province":"SK",
    "sg:tags":[
        "consultant",
        "training"
    ],
    "wof:name":"Lokken Business Consulting Svc",
    "wof:placetype":"venue"
},
  "geometry": {"coordinates":[-105.753341675,53.2028465271],"type":"Point"}
}