{
  "type": "Feature",
  "properties": {
    "addr:full":"17027 104A Ave Surrey BC V4N 4L9",
    "addr:housenumber":"17027",
    "addr:postcode":"v4n 4l9",
    "addr:street":"104A Ave",
    "iso:country":"CA",
    "sg:address":"17027 104A Ave",
    "sg:city":"Surrey",
    "sg:classifiers":[
        {
            "category":"Shopping",
            "subcategory":"Computers & Home Electronics",
            "type":"Retail Goods"
        }
    ],
    "sg:phone":"+1 604 930 2993",
    "sg:postcode":"V4N 4L9",
    "sg:province":"BC",
    "sg:tags":[
        "equipment",
        "dealer"
    ],
    "wof:name":"Microcost Computer Products",
    "wof:placetype":"venue"
},
  "geometry": {"coordinates":[-122.830215454,49.105178833],"type":"Point"}
}