{
  "type": "Feature",
  "properties": {
    "iso:country":"CA",
    "sg:address":"1695 Bank St",
    "sg:city":"Ottawa",
    "sg:classifiers":[
        {
            "category":"Shopping",
            "subcategory":"Bicycles & Sporting Goods",
            "type":"Retail Goods"
        }
    ],
    "sg:phone":"+1 613 521 3791",
    "sg:postcode":"K1V 7Z3",
    "sg:province":"ON",
    "wof:name":"Rebec & Kroes Cycle & Sport",
    "wof:placetype":"venue"
},
  "geometry": {"coordinates":[-75.66571044920001,45.3754348755],"type":"Point"}
}