{
  "type": "Feature",
  "properties": {
    "addr:full":"237 Rue Saint-Joseph E Quebec QC G1K 3B1",
    "addr:housenumber":"237",
    "addr:postcode":"g1k 3b1",
    "addr:street":"Rue Saint-Joseph E",
    "iso:country":"CA",
    "sg:address":"237 Rue Saint-Joseph E",
    "sg:city":"Quebec",
    "sg:classifiers":[
        {
            "category":"Travel",
            "subcategory":"Hotels & Motels",
            "type":"Entertainment"
        }
    ],
    "sg:phone":"+1 418 380 8080",
    "sg:postcode":"G1K 3B1",
    "sg:province":"QC",
    "wof:name":"Appartements Hotel Bonsejours",
    "wof:placetype":"venue"
},
  "geometry": {"coordinates":[-71.22753899999999,46.813065],"type":"Point"}
}