{
  "type": "Feature",
  "properties": {
    "iso:country":"CA",
    "sg:address":"2271 Bloor St W",
    "sg:city":"Toronto",
    "sg:classifiers":[
        {
            "category":"Banks & Credit Unions",
            "subcategory":"Bank",
            "type":"Services"
        }
    ],
    "sg:phone":"+1 416 763 2291",
    "sg:postcode":"M6S 1P1",
    "sg:province":"ON",
    "sg:tags":[
        "company",
        "trust"
    ],
    "wof:name":"Community Trust CO Ltd",
    "wof:placetype":"venue"
},
  "geometry": {"coordinates":[-79.4783401489,43.6505355835],"type":"Point"}
}