{
  "type": "Feature",
  "properties": {
    "addr:full":"Mississauga ON L5E 2K1",
    "addr:postcode":"l5e 2k1",
    "iso:country":"CA",
    "sg:city":"Mississauga",
    "sg:classifiers":[
        {
            "category":"Manufacturing",
            "subcategory":"Food",
            "type":"Manufacturing & Wholesale Goods"
        }
    ],
    "sg:phone":"+1 905 891 1353",
    "sg:postcode":"L5E 2K1",
    "sg:province":"ON",
    "sg:tags":[
        "brewer"
    ],
    "wof:name":"Amber Brewery",
    "wof:placetype":"venue"
},
  "geometry": {"coordinates":[-79.56028747560001,43.5795631409],"type":"Point"}
}