{
  "type": "Feature",
  "properties": {
    "addr:full":"1510 Rue Fleury E Montreal QC H2C 1S4",
    "addr:housenumber":"1510",
    "addr:postcode":"h2c 1s4",
    "addr:street":"Rue Fleury E",
    "iso:country":"CA",
    "sg:address":"1510 Rue Fleury E",
    "sg:city":"Montreal",
    "sg:classifiers":[
        {
            "category":"Restaurant",
            "type":"Food & Drink"
        }
    ],
    "sg:phone":"+1 514 388 5758",
    "sg:postcode":"H2C 1S4",
    "sg:province":"QC",
    "sg:tags":[
        "caterer"
    ],
    "wof:name":"Chemin Faisant",
    "wof:placetype":"venue"
},
  "geometry": {"coordinates":[-73.65627288819999,45.5626754761],"type":"Point"}
}