{
  "type": "Feature",
  "properties": {
    "addr:full":"189 Kent St W #215 Lindsay ON K9V 5G6",
    "addr:housenumber":"189;215",
    "addr:postcode":"k9v 5g6",
    "addr:street":"Kent St W #",
    "iso:country":"CA",
    "sg:address":"189 Kent St W #215",
    "sg:city":"Lindsay",
    "sg:classifiers":[
        {
            "category":"Organizations",
            "subcategory":"Membership Organization",
            "type":"Services"
        }
    ],
    "sg:phone":"+1 705 878 9261",
    "sg:postcode":"K9V 5G6",
    "sg:province":"ON",
    "sg:tags":[
        "development",
        "economic",
        "agency"
    ],
    "wof:name":"Technology Alliance Group For",
    "wof:placetype":"venue"
},
  "geometry": {"coordinates":[-78.74054700000001,44.354038],"type":"Point"}
}