{
  "type": "Feature",
  "properties": {
    "addr:full":"750 Du Saint-Maurice Prom Shawinigan QC G9N 1L6",
    "addr:housenumber":"750",
    "addr:postcode":"g9n 1l6",
    "addr:street":"Du Saint-Maurice Prom",
    "iso:country":"CA",
    "sg:address":"750 Du Saint-Maurice Prom",
    "sg:city":"Shawinigan",
    "sg:classifiers":[
        {
            "category":"Social Services",
            "type":"Services"
        }
    ],
    "sg:phone":"+1 819 536 5641",
    "sg:postcode":"G9N 1L6",
    "sg:province":"QC",
    "sg:tags":[
        "organization",
        "welfare"
    ],
    "wof:name":"Centre DE Svc En Deficience",
    "wof:placetype":"venue"
},
  "geometry": {"coordinates":[-72.7516403198,46.5377388],"type":"Point"}
}