{
  "type": "Feature",
  "properties": {
    "addr:full":"75 Cavendish St Regina SK S4N 5C1",
    "addr:housenumber":"75",
    "addr:postcode":"s4n 5c1",
    "addr:street":"Cavendish St",
    "iso:country":"CA",
    "sg:address":"75 Cavendish St",
    "sg:city":"Regina",
    "sg:classifiers":[
        {
            "category":"Real Estate",
            "subcategory":"Real Estate Operator",
            "type":"Services"
        }
    ],
    "sg:phone":"+1 306 751 2304",
    "sg:postcode":"S4N 5C1",
    "sg:province":"SK",
    "sg:tags":[
        "apartment"
    ],
    "wof:name":"Eastside Estates",
    "wof:placetype":"venue"
},
  "geometry": {"coordinates":[-104.557731628,50.4527893066],"type":"Point"}
}