{
  "type": "Feature",
  "properties": {
    "addr:full":"16 Centre St Marsden SK S0M 1P0",
    "addr:housenumber":"16",
    "addr:postcode":"s0m 1p0",
    "addr:street":"Centre St",
    "iso:country":"CA",
    "sg:address":"16 Centre St",
    "sg:city":"Marsden",
    "sg:classifiers":[
        {
            "category":"Restaurant",
            "type":"Food & Drink"
        }
    ],
    "sg:phone":"+1 306 826 5580",
    "sg:postcode":"S0M 1P0",
    "sg:province":"SK",
    "wof:name":"Marsden Village Cafe",
    "wof:placetype":"venue"
},
  "geometry": {"coordinates":[-109.820915222,52.8420753479],"type":"Point"}
}