{
  "type": "Feature",
  "properties": {
    "iso:country":"CA",
    "sg:address":"108 Dundas St W",
    "sg:city":"Deseronto",
    "sg:classifiers":[
        {
            "category":"Retail",
            "subcategory":"Auto Repair",
            "type":"Services"
        }
    ],
    "sg:phone":"+1 613 396 2018",
    "sg:postcode":"K0K 1X0",
    "sg:province":"ON",
    "sg:tags":[
        "repairing",
        "automobile"
    ],
    "wof:name":"Sunrise Variety Store & Shell",
    "wof:placetype":"venue"
},
  "geometry": {"coordinates":[-77.06047821040001,44.1959609985],"type":"Point"}
}