{
  "type": "Feature",
  "properties": {
    "addr:full":"727 Rue Desjardins Marieville QC J3M 1C9",
    "addr:housenumber":"727",
    "addr:postcode":"j3m 1c9",
    "addr:street":"Rue Desjardins",
    "iso:country":"CA",
    "sg:address":"727 Rue Desjardins",
    "sg:city":"Marieville",
    "sg:classifiers":[
        {
            "category":"Arena",
            "subcategory":"Sports Club",
            "type":"Entertainment"
        }
    ],
    "sg:phone":"+1 450 460 3335",
    "sg:postcode":"J3M 1C9",
    "sg:province":"QC",
    "sg:tags":[
        "athletic",
        "fields",
        "stadium"
    ],
    "wof:name":"Arena DE Marieville",
    "wof:placetype":"venue"
},
  "geometry": {"coordinates":[-73.1497955322,45.4310455322],"type":"Point"}
}