{
  "type": "Feature",
  "properties": {
    "addr:full":"6970 No. 3 Rd Richmond BC V6Y 2C5",
    "addr:postcode":"6970;v6y 2c5",
    "addr:street":"3 Rd",
    "iso:country":"CA",
    "sg:address":"6970 No. 3 Rd",
    "sg:city":"Richmond",
    "sg:classifiers":[
        {
            "category":"Shopping",
            "subcategory":"Photographic Equipment",
            "type":"Retail Goods"
        }
    ],
    "sg:phone":"+1 604 592 0724",
    "sg:postcode":"V6Y 2C5",
    "sg:province":"BC",
    "sg:tags":[
        "photo",
        "finishing"
    ],
    "wof:name":"Abc Photocolour Products Ltd",
    "wof:placetype":"venue"
},
  "geometry": {"coordinates":[-123.136375,49.163055],"type":"Point"}
}