{
  "type": "Feature",
  "properties": {
    "addr:full":"Winnipeg MB R3C 3Y4",
    "addr:postcode":"r3c 3y4",
    "iso:country":"CA",
    "sg:city":"Winnipeg",
    "sg:classifiers":[
        {
            "category":"Health Services",
            "subcategory":"Health Practitioner",
            "type":"Services"
        }
    ],
    "sg:phone":"+1 204 943 0848",
    "sg:postcode":"R3C 3Y4",
    "sg:province":"MB",
    "sg:tags":[
        "music",
        "therapy"
    ],
    "wof:name":"Motivating Sounds Music",
    "wof:placetype":"venue"
},
  "geometry": {"coordinates":[-97.1468505859,49.8913879395],"type":"Point"}
}