{
  "type": "Feature",
  "properties": {
    "iso:country":"CA",
    "sg:address":"4633 10th Ave",
    "sg:city":"New Hazelton",
    "sg:classifiers":[
        {
            "category":"Shopping",
            "subcategory":"Department Store",
            "type":"Retail Goods"
        }
    ],
    "sg:phone":"+1 250 842 6300",
    "sg:postcode":"V0J 2J0",
    "sg:province":"BC",
    "wof:name":"Fields Stores",
    "wof:placetype":"venue"
},
  "geometry": {"coordinates":[-127.581642,55.246834],"type":"Point"}
}