{
  "type": "Feature",
  "properties": {
    "addr:full":"576 Weber St N Waterloo ON N2L 5C6",
    "addr:housenumber":"576",
    "addr:postcode":"n2l 5c6",
    "addr:street":"Weber St N",
    "iso:country":"CA",
    "sg:address":"576 Weber St N",
    "sg:city":"Waterloo",
    "sg:classifiers":[
        {
            "category":"Banks & Credit Unions",
            "subcategory":"Bank",
            "type":"Services"
        }
    ],
    "sg:phone":"+1 519 883 4701",
    "sg:postcode":"N2L 5C6",
    "sg:province":"ON",
    "wof:name":"Td Canada Trust",
    "wof:placetype":"venue"
},
  "geometry": {"coordinates":[-80.548965,43.495598],"type":"Point"}
}