{
  "type": "Feature",
  "properties": {
    "addr:full":"981 Ch Denison O Granby QC J2G 8C6",
    "addr:housenumber":"981",
    "addr:postcode":"j2g 8c6",
    "addr:street":"Ch Denison O",
    "iso:country":"CA",
    "sg:address":"981 Ch Denison O",
    "sg:city":"Granby",
    "sg:classifiers":[
        {
            "category":"Home & Garden",
            "subcategory":"Household Appliances",
            "type":"Retail Goods"
        }
    ],
    "sg:phone":"+1 450 777 5566",
    "sg:postcode":"J2G 8C6",
    "sg:province":"QC",
    "sg:tags":[
        "cleaners",
        "vacuum"
    ],
    "wof:name":"Aspirateur Central Pnc",
    "wof:placetype":"venue"
},
  "geometry": {"coordinates":[-72.666695,45.387817],"type":"Point"}
}