{
  "type": "Feature",
  "properties": {
    "addr:full":"16035 114 Ave NW Edmonton AB T5M 2Z3",
    "addr:housenumber":"16035",
    "addr:postcode":"t5m 2z3",
    "addr:street":"114 Ave Nw",
    "iso:country":"CA",
    "sg:address":"16035 114 Ave NW",
    "sg:city":"Edmonton",
    "sg:classifiers":[
        {
            "category":"Building & Trades",
            "subcategory":"Construction",
            "type":"Services"
        }
    ],
    "sg:phone":"+1 780 447 2666",
    "sg:postcode":"T5M 2Z3",
    "sg:province":"AB",
    "sg:tags":[
        "concrete"
    ],
    "wof:name":"Con-Force Structures Ltd",
    "wof:placetype":"venue"
},
  "geometry": {"coordinates":[-113.59823608400001,53.5627822876],"type":"Point"}
}