{
  "type": "Feature",
  "properties": {
    "addr:full":"4675 Rue Roberge Lac-Megantic QC G6B 2Z5",
    "addr:housenumber":"4675",
    "addr:postcode":"g6b 2z5",
    "addr:street":"Rue Roberge Lac-Megantic",
    "iso:country":"CA",
    "sg:address":"4675 Rue Roberge",
    "sg:city":"Lac-Megantic",
    "sg:classifiers":[
        {
            "category":"Professional",
            "subcategory":"Management & Consulting",
            "type":"Services"
        }
    ],
    "sg:phone":"+1 819 583 4411",
    "sg:postcode":"G6B 2Z5",
    "sg:province":"QC",
    "sg:tags":[
        "consultant",
        "business"
    ],
    "wof:name":"Centre Local DE Developpement",
    "wof:placetype":"venue"
},
  "geometry": {"coordinates":[-70.877083,45.585098],"type":"Point"}
}