{
  "type": "Feature",
  "properties": {
    "addr:full":"PO Box 33 Point of Bay NL A0H 2A0",
    "addr:housenumber":"po box 33",
    "addr:postcode":"a0h 2a0",
    "addr:street":"Point",
    "iso:country":"CA",
    "sg:address":"PO Box 33",
    "sg:city":"Point of Bay",
    "sg:classifiers":[
        {
            "category":"Organizations",
            "subcategory":"Religious Organization",
            "type":"Services"
        }
    ],
    "sg:phone":"+1 709 257 4217",
    "sg:postcode":"A0H 2A0",
    "sg:province":"NL",
    "sg:tags":[
        "church"
    ],
    "wof:name":"Pentecostal Church",
    "wof:placetype":"venue"
},
  "geometry": {"coordinates":[-55.265965,49.288078],"type":"Point"}
}