{
  "type": "Feature",
  "properties": {
    "addr:full":"1026 Park Royal S West Vancouver BC V7T 1A1",
    "addr:housenumber":"1026",
    "addr:postcode":"v7t 1a1",
    "addr:street":"Park Royal S West",
    "iso:country":"CA",
    "sg:address":"1026 Park Royal S",
    "sg:city":"West Vancouver",
    "sg:classifiers":[
        {
            "category":"Shopping",
            "subcategory":"Clothing, Apparel, & Fashions",
            "type":"Retail Goods"
        }
    ],
    "sg:phone":"+1 604 913 1868",
    "sg:postcode":"V7T 1A1",
    "sg:province":"BC",
    "sg:tags":[
        "infant",
        "wear"
    ],
    "wof:name":"Vincenta Haute Couture Pour",
    "wof:placetype":"venue"
},
  "geometry": {"coordinates":[-123.140220642,49.3257026672],"type":"Point"}
}