{
  "type": "Feature",
  "properties": {
    "addr:full":"99 Rocky Lake Dr Bedford NS B4A 2T3",
    "addr:housenumber":"99",
    "addr:postcode":"b4a 2t3",
    "addr:street":"Rocky Lake Dr",
    "iso:country":"CA",
    "sg:address":"99 Rocky Lake Dr",
    "sg:city":"Bedford",
    "sg:classifiers":[
        {
            "category":"Shopping",
            "type":"Retail Goods"
        }
    ],
    "sg:phone":"+1 902 835 1819",
    "sg:postcode":"B4A 2T3",
    "sg:province":"NS",
    "sg:tags":[
        "enforcement",
        "law",
        "supply"
    ],
    "wof:name":"Atlantic Police & Security",
    "wof:placetype":"venue"
},
  "geometry": {"coordinates":[-63.6474990845,44.7375640869],"type":"Point"}
}