{
  "type": "Feature",
  "properties": {
    "addr:full":"5718 Rue Saint-Andre Montreal QC H2S 2K1",
    "addr:housenumber":"5718",
    "addr:postcode":"h2s 2k1",
    "addr:street":"Rue Saint-Andre",
    "iso:country":"CA",
    "sg:address":"5718 Rue Saint-Andre",
    "sg:city":"Montreal",
    "sg:classifiers":[
        {
            "category":"Organizations",
            "subcategory":"Professional Association",
            "type":"Services"
        }
    ],
    "sg:phone":"+1 514 278 0281",
    "sg:postcode":"H2S 2K1",
    "sg:province":"QC",
    "wof:name":"Club Intergeneration-Petite",
    "wof:placetype":"venue"
},
  "geometry": {"coordinates":[-73.59498600000001,45.533188],"type":"Point"}
}