{
  "type": "Feature",
  "properties": {
    "addr:full":"4865 Boul Rosemont Montreal QC H1T 2E5",
    "addr:housenumber":"4865",
    "addr:postcode":"h1t 2e5",
    "addr:street":"Boul Rosemont",
    "iso:country":"CA",
    "sg:address":"4865 Boul Rosemont",
    "sg:city":"Montreal",
    "sg:classifiers":[
        {
            "category":"Health Services",
            "subcategory":"Medical Lab",
            "type":"Services"
        }
    ],
    "sg:phone":"+1 514 256 0838",
    "sg:postcode":"H1T 2E5",
    "sg:province":"QC",
    "wof:name":"Lagace, Rolande",
    "wof:placetype":"venue"
},
  "geometry": {"coordinates":[-73.56726837159999,45.5684623718],"type":"Point"}
}