{
  "type": "Feature",
  "properties": {
    "iso:country":"CA",
    "sg:address":"1230 Rue Caya",
    "sg:city":"Drummondville",
    "sg:classifiers":[
        {
            "category":"Retail",
            "subcategory":"Portrait Studio",
            "type":"Services"
        }
    ],
    "sg:phone":"+1 819 478 5553",
    "sg:postcode":"J2C 3A5",
    "sg:province":"QC",
    "sg:tags":[
        "photographer"
    ],
    "wof:name":"Photographie Nicole A Lambert",
    "wof:placetype":"venue"
},
  "geometry": {"coordinates":[-72.5238494873,45.8912658691],"type":"Point"}
}