{
  "type": "Feature",
  "properties": {
    "addr:full":"11 Rue Deguise Sorel-Tracy QC J3P 1P2",
    "addr:housenumber":"11",
    "addr:postcode":"j3p 1p2",
    "addr:street":"Rue Deguise",
    "iso:country":"CA",
    "sg:address":"11 Rue Deguise",
    "sg:city":"Sorel-Tracy",
    "sg:classifiers":[
        {
            "category":"Recreation",
            "subcategory":"Marina",
            "type":"Entertainment"
        }
    ],
    "sg:phone":"+1 450 743 4749",
    "sg:postcode":"J3P 1P2",
    "sg:province":"QC",
    "sg:tags":[
        "machine",
        "shop",
        "repairing",
        "boat"
    ],
    "wof:name":"Garage DE Guise Enr",
    "wof:placetype":"venue"
},
  "geometry": {"coordinates":[-73.1078872681,46.0429611206],"type":"Point"}
}