{
  "type": "Feature",
  "properties": {
    "iso:country":"CA",
    "sg:address":"71 Rue Notre-Dame E",
    "sg:city":"Victoriaville",
    "sg:classifiers":[
        {
            "category":"Shopping",
            "subcategory":"Bicycles & Sporting Goods",
            "type":"Retail Goods"
        }
    ],
    "sg:phone":"+1 819 751 3257",
    "sg:postcode":"G6P 3Z4",
    "sg:province":"QC",
    "wof:name":"Boutique Vertical Snowboard",
    "wof:placetype":"venue"
},
  "geometry": {"coordinates":[-71.9569778442,46.056224823],"type":"Point"}
}