{
  "type": "Feature",
  "properties": {
    "addr:full":"2940 Laurie Lane Coldbrook NS B4R 1A3",
    "addr:housenumber":"2940",
    "addr:postcode":"b4r 1a3",
    "addr:street":"Laurie Lane",
    "iso:country":"CA",
    "sg:address":"2940 Laurie Lane",
    "sg:city":"Coldbrook",
    "sg:classifiers":[
        {
            "category":"Retail",
            "subcategory":"Repair Shop",
            "type":"Services"
        }
    ],
    "sg:phone":"+1 902 679 6613",
    "sg:postcode":"B4R 1A3",
    "sg:province":"NS",
    "sg:tags":[
        "upholsterer"
    ],
    "wof:name":"Beech Hill Upholstery",
    "wof:placetype":"venue"
},
  "geometry": {"coordinates":[-64.59893798829999,45.0615615845],"type":"Point"}
}