{
  "type": "Feature",
  "properties": {
    "addr:full":"453 7E Av Dolbeau-Mistassini QC G8L 3B3",
    "addr:housenumber":"453",
    "addr:postcode":"g8l 3b3",
    "addr:street":"7E Av Dolbeau-Mistassini",
    "iso:country":"CA",
    "sg:address":"453 7E Av",
    "sg:city":"Dolbeau-Mistassini",
    "sg:classifiers":[
        {
            "category":"Wholesale",
            "subcategory":"Fruits & Vegetables",
            "type":"Manufacturing & Wholesale Goods"
        }
    ],
    "sg:phone":"+1 418 276 4120",
    "sg:postcode":"G8L 3B3",
    "sg:province":"QC",
    "wof:name":"Usine DE Congelation-St-Bruno",
    "wof:placetype":"venue"
},
  "geometry": {"coordinates":[-72.23672485349999,48.8775558472],"type":"Point"}
}