{
  "type": "Feature",
  "properties": {
    "addr:full":"Saint-Come-Liniere QC G0M 1J0",
    "addr:postcode":"g0m 1j0",
    "iso:country":"CA",
    "sg:city":"Saint-Come-Liniere",
    "sg:classifiers":[
        {
            "category":"Professional",
            "subcategory":"Business Services",
            "type":"Services"
        }
    ],
    "sg:phone":"+1 418 685 2776",
    "sg:postcode":"G0M 1J0",
    "sg:province":"QC",
    "sg:tags":[
        "embroidery"
    ],
    "wof:name":"Brida Design",
    "wof:placetype":"venue"
},
  "geometry": {"coordinates":[-70.524834,46.062584],"type":"Point"}
}