{
  "type": "Feature",
  "properties": {
    "addr:full":"645 Athlone Ave Woodstock ON N4S 7V8",
    "addr:housenumber":"645",
    "addr:postcode":"n4s 7v8",
    "addr:street":"Athlone Ave",
    "iso:country":"CA",
    "sg:address":"645 Athlone Ave",
    "sg:city":"Woodstock",
    "sg:classifiers":[
        {
            "category":"Autos & Motor Vehicles",
            "subcategory":"Automobile Sales",
            "type":"Retail Goods"
        }
    ],
    "sg:phone":"+1 519 539 9837",
    "sg:postcode":"N4S 7V8",
    "sg:province":"ON",
    "sg:tags":[
        "truck"
    ],
    "wof:name":"Carrier Idealease",
    "wof:placetype":"venue"
},
  "geometry": {"coordinates":[-80.744225,43.110176],"type":"Point"}
}