{
  "type": "Feature",
  "properties": {
    "addr:full":"1950 Lawrence Ave E Scarborough ON M1R 2Y9",
    "addr:housenumber":"1950",
    "addr:postcode":"m1r 2y9",
    "addr:street":"Lawrence Ave E",
    "iso:country":"CA",
    "sg:address":"1950 Lawrence Ave E",
    "sg:city":"Scarborough",
    "sg:classifiers":[
        {
            "category":"Wholesale",
            "subcategory":"Groceries",
            "type":"Manufacturing & Wholesale Goods"
        }
    ],
    "sg:phone":"+1 416 759 2221",
    "sg:postcode":"M1R 2Y9",
    "sg:province":"ON",
    "sg:tags":[
        "nut"
    ],
    "wof:name":"Basse Golden Nuts Inc",
    "wof:placetype":"venue"
},
  "geometry": {"coordinates":[-79.29864499999999,43.744675],"type":"Point"}
}