{
  "type": "Feature",
  "properties": {
    "addr:full":"218 Rue Sainte-Anne Chicoutimi QC G7J 2L8",
    "addr:housenumber":"218",
    "addr:postcode":"g7j 2l8",
    "addr:street":"Rue Sainte-Anne",
    "iso:country":"CA",
    "sg:address":"218 Rue Sainte-Anne",
    "sg:city":"Chicoutimi",
    "sg:classifiers":[
        {
            "category":"Personal",
            "subcategory":"Beauty Salon",
            "type":"Services"
        }
    ],
    "sg:phone":"+1 418 543 0170",
    "sg:postcode":"G7J 2L8",
    "sg:province":"QC",
    "wof:name":"Fusion Coiffure Esthetique Enr",
    "wof:placetype":"venue"
},
  "geometry": {"coordinates":[-71.068451,48.429176],"type":"Point"}
}