{
  "type": "Feature",
  "properties": {
    "addr:full":"14 Rue Sicard Sainte-Therese QC J7E 3W7",
    "addr:housenumber":"14",
    "addr:postcode":"j7e 3w7",
    "addr:street":"Rue Sicard Sainte-Therese",
    "iso:country":"CA",
    "sg:address":"14 Rue Sicard",
    "sg:city":"Sainte-Therese",
    "sg:classifiers":[
        {
            "category":"Building & Trades",
            "subcategory":"Construction",
            "type":"Services"
        }
    ],
    "sg:phone":"+1 819 430 7900",
    "sg:postcode":"J7E 3W7",
    "sg:province":"QC",
    "sg:tags":[
        "roofing",
        "contractor"
    ],
    "wof:name":"J Raymond Couvreurs Inc",
    "wof:placetype":"venue"
},
  "geometry": {"coordinates":[-73.846825,45.634697],"type":"Point"}
}