{
  "type": "Feature",
  "properties": {
    "iso:country":"CA",
    "sg:city":"Repentigny",
    "sg:classifiers":[
        {
            "category":"Health Services",
            "subcategory":"Health Practitioner",
            "type":"Services"
        }
    ],
    "sg:phone":"+1 450 654 4331",
    "sg:postcode":"J5Y 1B4",
    "sg:province":"QC",
    "sg:tags":[
        "physiotherapist"
    ],
    "wof:name":"Clinique DE Physio Notre-Dame",
    "wof:placetype":"venue"
},
  "geometry": {"coordinates":[-73.424797,45.760662],"type":"Point"}
}