{
  "type": "Feature",
  "properties": {
    "addr:full":"Morrisburg ON K0C 1X0",
    "addr:postcode":"k0c 1x0",
    "iso:country":"CA",
    "sg:city":"Morrisburg",
    "sg:classifiers":[
        {
            "category":"Arts & Performance",
            "subcategory":"Theater",
            "type":"Entertainment"
        }
    ],
    "sg:phone":"+1 613 543 3713",
    "sg:postcode":"K0C 1X0",
    "sg:province":"ON",
    "wof:name":"Upper Canada Playhouse",
    "wof:placetype":"venue"
},
  "geometry": {"coordinates":[-75.188034,44.898159],"type":"Point"}
}