{
  "type": "Feature",
  "properties": {
    "iso:country":"CA",
    "sg:address":"693 Bloor St W",
    "sg:city":"Toronto",
    "sg:classifiers":[
        {
            "category":"Bars & Pubs",
            "type":"Food & Drink"
        }
    ],
    "sg:phone":"+1 416 535 9541",
    "sg:postcode":"M6G 1L5",
    "sg:province":"ON",
    "wof:name":"Clinton's",
    "wof:placetype":"venue"
},
  "geometry": {"coordinates":[-79.417336,43.663692],"type":"Point"}
}