{
  "type": "Feature",
  "properties": {
    "addr:full":"693 Bloor St W Toronto ON M6G 1L5",
    "addr:housenumber":"693",
    "addr:postcode":"m6g 1l5",
    "addr:street":"Bloor St W",
    "iso:country":"CA",
    "sg:address":"693 Bloor St W",
    "sg:city":"Toronto",
    "sg:classifiers":[
        {
            "category":"Bars & Pubs",
            "type":"Food & Drink"
        }
    ],
    "sg:phone":"+1 416 535 9541",
    "sg:postcode":"M6G 1L5",
    "sg:province":"ON",
    "wof:name":"Clinton's",
    "wof:placetype":"venue"
},
  "geometry": {"coordinates":[-79.41733600000001,43.663692],"type":"Point"}
}