{
  "type": "Feature",
  "properties": {
    "addr:full":"Montreal QC H4P 2P5",
    "addr:postcode":"h4p 2p5",
    "iso:country":"CA",
    "sg:city":"Montreal",
    "sg:classifiers":[
        {
            "category":"Wholesale",
            "subcategory":"Electrical",
            "type":"Manufacturing & Wholesale Goods"
        }
    ],
    "sg:phone":"+1 514 736 3666",
    "sg:postcode":"H4P 2P5",
    "sg:province":"QC",
    "sg:tags":[
        "radio"
    ],
    "wof:name":"Page Net",
    "wof:placetype":"venue"
},
  "geometry": {"coordinates":[-73.661605835,45.4992485046],"type":"Point"}
}