{
  "type": "Feature",
  "properties": {
    "addr:full":"1039 Mississaga St W Orillia ON L3V 3C7",
    "addr:housenumber":"1039",
    "addr:postcode":"l3v 3c7",
    "addr:street":"Mississaga St W",
    "iso:country":"CA",
    "sg:address":"1039 Mississaga St W",
    "sg:city":"Orillia",
    "sg:classifiers":[
        {
            "category":"Organizations",
            "subcategory":"Religious Organization",
            "type":"Services"
        }
    ],
    "sg:phone":"+1 705 645 2455",
    "sg:postcode":"L3V 3C7",
    "sg:province":"ON",
    "sg:tags":[
        "church"
    ],
    "wof:name":"Orillia Star of Hope Spirit Ch",
    "wof:placetype":"venue"
},
  "geometry": {"coordinates":[-79.44169599999999,44.593735],"type":"Point"}
}