{
  "type": "Feature",
  "properties": {
    "addr:full":"103 1st Ave W Assiniboia SK S0H 0B0",
    "addr:housenumber":"103",
    "addr:postcode":"s0h 0b0",
    "addr:street":"1St Ave W Assiniboia",
    "iso:country":"CA",
    "sg:address":"103 1st Ave W",
    "sg:city":"Assiniboia",
    "sg:classifiers":[
        {
            "category":"Retail",
            "subcategory":"Auto Repair",
            "type":"Services"
        }
    ],
    "sg:phone":"+1 306 642 3643",
    "sg:postcode":"S0H 0B0",
    "sg:province":"SK",
    "sg:tags":[
        "repairing",
        "automobile"
    ],
    "wof:name":"Tdc Automotive & Towing",
    "wof:placetype":"venue"
},
  "geometry": {"coordinates":[-105.992126,49.633499],"type":"Point"}
}