{
  "type": "Feature",
  "properties": {
    "addr:full":"171 Forth St Cobourg ON K9A 2Z4",
    "addr:housenumber":"171",
    "addr:postcode":"k9a 2z4",
    "addr:street":"Forth St",
    "iso:country":"CA",
    "sg:address":"171 Forth St",
    "sg:city":"Cobourg",
    "sg:classifiers":[
        {
            "category":"Home & Garden",
            "subcategory":"Household Appliances",
            "type":"Retail Goods"
        }
    ],
    "sg:phone":"+1 905 372 7690",
    "sg:postcode":"K9A 2Z4",
    "sg:province":"ON",
    "sg:tags":[
        "machine",
        "sewing"
    ],
    "wof:name":"Amos Jones Sewing Svc",
    "wof:placetype":"venue"
},
  "geometry": {"coordinates":[-78.179451,43.957127],"type":"Point"}
}