{
  "type": "Feature",
  "properties": {
    "addr:full":"3766 Ch DE LA Cote-Des-Neiges Montreal QC H3H 1V6",
    "addr:postcode":"3766;h3h 1v6",
    "addr:street":"Ch De La Cote-Des-Neiges",
    "iso:country":"CA",
    "sg:address":"3766 Ch DE LA Cote-Des-Neiges",
    "sg:city":"Montreal",
    "sg:classifiers":[
        {
            "category":"Health Services",
            "subcategory":"Doctor",
            "type":"Services"
        }
    ],
    "sg:phone":"+1 514 937 9092",
    "sg:postcode":"H3H 1V6",
    "sg:province":"QC",
    "sg:tags":[
        "physician",
        "surgeon"
    ],
    "wof:name":"Vialaser Inc",
    "wof:placetype":"venue"
},
  "geometry": {"coordinates":[-73.58856201170001,45.4958496094],"type":"Point"}
}