{
  "type": "Feature",
  "properties": {
    "addr:full":"17080 Rue Claude Pierrefonds QC H9J 2M9",
    "addr:housenumber":"17080",
    "addr:postcode":"h9j 2m9",
    "addr:street":"Rue Claude",
    "iso:country":"CA",
    "sg:address":"17080 Rue Claude",
    "sg:city":"Pierrefonds",
    "sg:classifiers":[
        {
            "category":"Retail",
            "subcategory":"Auto Repair",
            "type":"Services"
        }
    ],
    "sg:phone":"+1 514 626 6177",
    "sg:postcode":"H9J 2M9",
    "sg:province":"QC",
    "sg:tags":[
        "body",
        "automobile",
        "painting"
    ],
    "wof:name":"Bouchard Auto Body",
    "wof:placetype":"venue"
},
  "geometry": {"coordinates":[-73.8756027222,45.4677124023],"type":"Point"}
}