{
  "type": "Feature",
  "properties": {
    "addr:full":"384 Abercrombie Rd New Glasgow NS B2H 1L4",
    "addr:housenumber":"384",
    "addr:postcode":"b2h 1l4",
    "addr:street":"Abercrombie Rd",
    "iso:country":"CA",
    "sg:address":"384 Abercrombie Rd",
    "sg:city":"New Glasgow",
    "sg:classifiers":[
        {
            "category":"Organizations",
            "subcategory":"Religious Organization",
            "type":"Services"
        }
    ],
    "sg:phone":"+1 902 752 0763",
    "sg:postcode":"B2H 1L4",
    "sg:province":"NS",
    "sg:tags":[
        "church"
    ],
    "wof:name":"Church of Jesus Christ-Lds",
    "wof:placetype":"venue"
},
  "geometry": {"coordinates":[-62.651718,45.597755],"type":"Point"}
}