{
  "type": "Feature",
  "properties": {
    "addr:full":"500 Rue Principale Eastman QC J0E 1P0",
    "addr:housenumber":"500",
    "addr:postcode":"j0e 1p0",
    "addr:street":"Rue Principale",
    "iso:country":"CA",
    "sg:address":"500 Rue Principale",
    "sg:city":"Eastman",
    "sg:classifiers":[
        {
            "category":"Education",
            "subcategory":"School",
            "type":"Public Place"
        }
    ],
    "sg:phone":"+1 450 297 4879",
    "sg:postcode":"J0E 1P0",
    "sg:province":"QC",
    "wof:name":"Ecole Val DE Graces",
    "wof:placetype":"venue"
},
  "geometry": {"coordinates":[-72.30933400000001,45.301949],"type":"Point"}
}