{
  "type": "Feature",
  "properties": {
    "iso:country":"CA",
    "sg:address":"PO Box 1113 STN Postal Box Ctr",
    "sg:city":"Red Deer",
    "sg:classifiers":[
        {
            "category":"Building & Trades",
            "subcategory":"Cleaning & Sanitation",
            "type":"Services"
        }
    ],
    "sg:phone":"+1 403 304 5025",
    "sg:postcode":"T4N 6S5",
    "sg:province":"AB",
    "sg:tags":[
        "janitor"
    ],
    "wof:name":"G & S Janitorial Svc",
    "wof:placetype":"venue"
},
  "geometry": {"coordinates":[-113.817436218,52.2623023987],"type":"Point"}
}