{
  "type": "Feature",
  "properties": {
    "addr:full":"600 Rue Eastern Waterloo QC J0E 2N0",
    "addr:housenumber":"600",
    "addr:postcode":"j0e 2n0",
    "addr:street":"Rue Eastern",
    "iso:country":"CA",
    "sg:address":"600 Rue Eastern",
    "sg:city":"Waterloo",
    "sg:classifiers":[
        {
            "category":"Health Services",
            "subcategory":"Nursing And Care Facility",
            "type":"Services"
        }
    ],
    "sg:phone":"+1 450 539 4510",
    "sg:postcode":"J0E 2N0",
    "sg:province":"QC",
    "sg:tags":[
        "home",
        "retirement",
        "community"
    ],
    "wof:name":"Residence Du Sacre-Coeur Inc",
    "wof:placetype":"venue"
},
  "geometry": {"coordinates":[-72.51024627690001,45.3475074768],"type":"Point"}
}