{
  "type": "Feature",
  "properties": {
    "addr:full":"Edmonton AB T6H 4M6",
    "addr:postcode":"t6h 4m6",
    "iso:country":"CA",
    "sg:city":"Edmonton",
    "sg:classifiers":[
        {
            "category":"Shopping",
            "subcategory":"Clothing, Apparel, & Fashions",
            "type":"Retail Goods"
        }
    ],
    "sg:phone":"+1 780 439 0860",
    "sg:postcode":"T6H 4M6",
    "sg:province":"AB",
    "wof:name":"Garage Clothing CO",
    "wof:placetype":"venue"
},
  "geometry": {"coordinates":[-113.490371704,53.5462188721],"type":"Point"}
}