{
  "type": "Feature",
  "properties": {
    "addr:full":"North York ON M3B 3J5",
    "addr:postcode":"m3b 3j5",
    "iso:country":"CA",
    "sg:city":"North York",
    "sg:classifiers":[
        {
            "category":"Insurance",
            "subcategory":"Insurance Agent",
            "type":"Services"
        }
    ],
    "sg:phone":"+1 416 391 3793",
    "sg:postcode":"M3B 3J5",
    "sg:province":"ON",
    "wof:name":"Don Yu Insurance & Financial",
    "wof:placetype":"venue"
},
  "geometry": {"coordinates":[-79.3519287109,43.7618484497],"type":"Point"}
}