{
  "type": "Feature",
  "properties": {
    "addr:full":"Saint-Joseph-DE-LA-Rive QC G0A 3Y0",
    "addr:postcode":"g0a 3y0",
    "iso:country":"CA",
    "sg:city":"Saint-Joseph-DE-LA-Rive",
    "sg:classifiers":[
        {
            "category":"Manufacturing",
            "subcategory":"Paper Products",
            "type":"Manufacturing & Wholesale Goods"
        }
    ],
    "sg:phone":"+1 418 635 2430",
    "sg:postcode":"G0A 3Y0",
    "sg:province":"QC",
    "wof:name":"Papeterie Saint-Gilles",
    "wof:placetype":"venue"
},
  "geometry": {"coordinates":[-70.358253,47.459667],"type":"Point"}
}