{
  "type": "Feature",
  "properties": {
    "iso:country":"CA",
    "sg:address":"698 Conestoga St",
    "sg:city":"Cornwallis",
    "sg:classifiers":[
        {
            "category":"Farming",
            "subcategory":"Fish & Marine Products",
            "type":"Manufacturing & Wholesale Goods"
        }
    ],
    "sg:phone":"+1 902 638 8302",
    "sg:postcode":"B0S 1H0",
    "sg:province":"NS",
    "sg:tags":[
        "seaweed"
    ],
    "wof:name":"Acadian Seaplants Ltd",
    "wof:placetype":"venue"
},
  "geometry": {"coordinates":[-65.630241394,44.6516456604],"type":"Point"}
}