{
  "type": "Feature",
  "properties": {
    "addr:full":"5105 45th Ave Chetwynd BC V0C 1J0",
    "addr:housenumber":"5105",
    "addr:postcode":"bc v0c 1j0",
    "addr:street":"45Th Ave",
    "iso:country":"CA",
    "sg:address":"5105 45th Ave",
    "sg:city":"Chetwynd",
    "sg:classifiers":[
        {
            "category":"Building & Trades",
            "subcategory":"Construction",
            "type":"Services"
        }
    ],
    "sg:phone":"+1 250 788 3822",
    "sg:postcode":"V0C 1J0",
    "sg:province":"BC",
    "sg:tags":[
        "painter"
    ],
    "wof:name":"Deck's Painting & Decorating",
    "wof:placetype":"venue"
},
  "geometry": {"coordinates":[-121.629868,55.706917],"type":"Point"}
}