{
  "type": "Feature",
  "properties": {
    "addr:full":"4483 Boul Saint-Laurent Montreal QC H2W 1Z8",
    "addr:housenumber":"4483",
    "addr:postcode":"h2w 1z8",
    "addr:street":"Boul Saint-Laurent",
    "iso:country":"CA",
    "sg:address":"4483 Boul Saint-Laurent",
    "sg:city":"Montreal",
    "sg:classifiers":[
        {
            "category":"Bars & Pubs",
            "type":"Food & Drink"
        }
    ],
    "sg:phone":"+1 514 845 8443",
    "sg:postcode":"H2W 1Z8",
    "sg:province":"QC",
    "sg:tags":[
        "discotheque"
    ],
    "wof:name":"Belmont Sur Le Boulevard",
    "wof:placetype":"venue"
},
  "geometry": {"coordinates":[-73.5857925415,45.5200157166],"type":"Point"}
}