{
  "type": "Feature",
  "properties": {
    "iso:country":"CA",
    "sg:address":"40 Henri Dunant St",
    "sg:city":"Moncton",
    "sg:classifiers":[
        {
            "category":"Real Estate",
            "subcategory":"Surveying",
            "type":"Services"
        }
    ],
    "sg:phone":"+1 506 857 0022",
    "sg:postcode":"E1E 1E5",
    "sg:province":"NB",
    "sg:tags":[
        "surveyor"
    ],
    "wof:name":"Mac Aulay Surveys Ltd",
    "wof:placetype":"venue"
},
  "geometry": {"coordinates":[-64.82573699949999,46.0755958557],"type":"Point"}
}