{
  "type": "Feature",
  "properties": {
    "addr:full":"49 Charlotte St Brantford ON N3T 2W4",
    "addr:housenumber":"49",
    "addr:postcode":"n3t 2w4",
    "addr:street":"Charlotte St",
    "iso:country":"CA",
    "sg:address":"49 Charlotte St",
    "sg:city":"Brantford",
    "sg:classifiers":[
        {
            "category":"Professional",
            "subcategory":"Business Services",
            "type":"Services"
        }
    ],
    "sg:phone":"+1 519 759 6820",
    "sg:postcode":"N3T 2W4",
    "sg:province":"ON",
    "sg:tags":[
        "telephone",
        "cellular",
        "telemarketing"
    ],
    "wof:name":"Extend Communications",
    "wof:placetype":"venue"
},
  "geometry": {"coordinates":[-80.260635376,43.1412162781],"type":"Point"}
}