{
  "type": "Feature",
  "properties": {
    "addr:full":"5650 Rue DE Verdun Verdun QC H4H 1L5",
    "addr:housenumber":"5650",
    "addr:postcode":"h4h 1l5",
    "addr:street":"Rue De Verdun",
    "iso:country":"CA",
    "sg:address":"5650 Rue DE Verdun",
    "sg:city":"Verdun",
    "sg:classifiers":[
        {
            "category":"Real Estate",
            "subcategory":"Real Estate Agent",
            "type":"Services"
        }
    ],
    "sg:phone":"+1 514 493 1403",
    "sg:postcode":"H4H 1L5",
    "sg:province":"QC",
    "sg:tags":[
        "management"
    ],
    "wof:name":"Groupe Jesmark Inc",
    "wof:placetype":"venue"
},
  "geometry": {"coordinates":[-73.572372,45.450684],"type":"Point"}
}