{
  "type": "Feature",
  "properties": {
    "addr:full":"28 Cherry St St Catharines ON L2R 5M6",
    "addr:housenumber":"28",
    "addr:postcode":"l2r 5m6",
    "addr:street":"Cherry St",
    "iso:country":"CA",
    "sg:address":"28 Cherry St",
    "sg:city":"St Catharines",
    "sg:classifiers":[
        {
            "category":"Health Services",
            "subcategory":"Medical Lab",
            "type":"Services"
        }
    ],
    "sg:phone":"+1 905 682 3525",
    "sg:postcode":"L2R 5M6",
    "sg:province":"ON",
    "sg:tags":[
        "laboratory"
    ],
    "wof:name":"Niagara Dental Arts",
    "wof:placetype":"venue"
},
  "geometry": {"coordinates":[-79.2498703003,43.1559410095],"type":"Point"}
}