{
  "type": "Feature",
  "properties": {
    "addr:full":"75 Rue DE LA Gare #D3 St-Sauveur-Des-Monts QC J0R 1R6",
    "addr:housenumber":"75",
    "addr:postcode":"j0r 1r6",
    "addr:street":"Rue De La Gare # D3 St-Sauveur-Des-Monts",
    "iso:country":"CA",
    "sg:address":"75 Rue DE LA Gare #D3",
    "sg:city":"St-Sauveur-Des-Monts",
    "sg:classifiers":[
        {
            "category":"Real Estate",
            "subcategory":"Real Estate Operator",
            "type":"Services"
        }
    ],
    "sg:phone":"+1 450 227 4774",
    "sg:postcode":"J0R 1R6",
    "sg:province":"QC",
    "sg:tags":[
        "mall",
        "shopping",
        "center"
    ],
    "wof:name":"Galeries Des Monts Inc",
    "wof:placetype":"venue"
},
  "geometry": {"coordinates":[-74.0025024414,45.776134491],"type":"Point"}
}