{
  "type": "Feature",
  "properties": {
    "addr:full":"285 Smith St Winnipeg MB R3C 1K9",
    "addr:housenumber":"285",
    "addr:postcode":"r3c 1k9",
    "addr:street":"Smith St",
    "iso:country":"CA",
    "sg:address":"285 Smith St",
    "sg:city":"Winnipeg",
    "sg:classifiers":[
        {
            "category":"Travel",
            "subcategory":"Hotels & Motels",
            "type":"Entertainment"
        }
    ],
    "sg:phone":"+1 204 942 0171",
    "sg:postcode":"R3C 1K9",
    "sg:province":"MB",
    "wof:name":"St Regis Hotel",
    "wof:placetype":"venue"
},
  "geometry": {"coordinates":[-97.14123499999999,49.892738],"type":"Point"}
}