{
  "type": "Feature",
  "properties": {
    "addr:full":"Montreal QC H2Y 2W8",
    "addr:postcode":"h2y 2w8",
    "iso:country":"CA",
    "sg:city":"Montreal",
    "sg:classifiers":[
        {
            "category":"Professional",
            "subcategory":"Lawyer & Legal Services",
            "type":"Services"
        }
    ],
    "sg:phone":"+1 514 731 1144",
    "sg:postcode":"H2Y 2W8",
    "sg:province":"QC",
    "sg:tags":[
        "naturalization",
        "immigration"
    ],
    "wof:name":"Max Berger & Assoc",
    "wof:placetype":"venue"
},
  "geometry": {"coordinates":[-73.55435900000001,45.51231],"type":"Point"}
}