{
  "type": "Feature",
  "properties": {
    "addr:full":"6095 Normandy Dr Halifax NS B3K 2T2",
    "addr:housenumber":"6095",
    "addr:postcode":"b3k 2t2",
    "addr:street":"Normandy Dr",
    "iso:country":"CA",
    "sg:address":"6095 Normandy Dr",
    "sg:city":"Halifax",
    "sg:classifiers":[
        {
            "category":"Health Services",
            "subcategory":"Health Practitioner",
            "type":"Services"
        }
    ],
    "sg:phone":"+1 902 455 5526",
    "sg:postcode":"B3K 2T2",
    "sg:province":"NS",
    "sg:tags":[
        "psychologist"
    ],
    "wof:name":"Sutherland, Maria",
    "wof:placetype":"venue"
},
  "geometry": {"coordinates":[-63.6142349243,44.6660652161],"type":"Point"}
}