{
  "type": "Feature",
  "properties": {
    "addr:full":"204 Manitoba St W Moose Jaw SK S6H 1R1",
    "addr:housenumber":"204",
    "addr:postcode":"s6h 1r1",
    "addr:street":"Manitoba St W",
    "iso:country":"CA",
    "sg:address":"204 Manitoba St W",
    "sg:city":"Moose Jaw",
    "sg:classifiers":[
        {
            "category":"Autos & Motor Vehicles",
            "subcategory":"Automobile Sales",
            "type":"Retail Goods"
        }
    ],
    "sg:phone":"+1 306 693 0651",
    "sg:postcode":"S6H 1R1",
    "sg:province":"SK",
    "sg:tags":[
        "car",
        "dealer"
    ],
    "wof:name":"Moose Jaw Ford Sales Ltd",
    "wof:placetype":"venue"
},
  "geometry": {"coordinates":[-105.538719,50.389942],"type":"Point"}
}