{
  "type": "Feature",
  "properties": {
    "addr:full":"608 Rte Du President-Kennedy Pintendre QC G6C 1K1",
    "addr:housenumber":"608",
    "addr:postcode":"g6c 1k1",
    "addr:street":"Rte Du President-Kennedy Pintendre",
    "iso:country":"CA",
    "sg:address":"608 Rte Du President-Kennedy",
    "sg:city":"Pintendre",
    "sg:classifiers":[
        {
            "category":"Manufacturing",
            "subcategory":"Metals",
            "type":"Manufacturing & Wholesale Goods"
        }
    ],
    "sg:phone":"+1 418 837 1111",
    "sg:postcode":"G6C 1K1",
    "sg:province":"QC",
    "sg:tags":[
        "plate",
        "tin"
    ],
    "wof:name":"Ferblanterie R Caron",
    "wof:placetype":"venue"
},
  "geometry": {"coordinates":[-71.1399383545,46.7692756653],"type":"Point"}
}