{
  "type": "Feature",
  "properties": {
    "iso:country":"CA",
    "sg:city":"Shanty Bay",
    "sg:classifiers":[
        {
            "category":"Shopping",
            "subcategory":"Used Merchandise",
            "type":"Retail Goods"
        }
    ],
    "sg:phone":"+1 705 728 6860",
    "sg:postcode":"L0L 2L0",
    "sg:province":"ON",
    "sg:tags":[
        "antique"
    ],
    "wof:name":"Moments in Tyme Antiques",
    "wof:placetype":"venue"
},
  "geometry": {"coordinates":[-79.58197800000001,44.412922],"type":"Point"}
}