{
  "type": "Feature",
  "properties": {
    "addr:full":"410 Barrie Rd Orillia ON L3V 2R9",
    "addr:housenumber":"410",
    "addr:postcode":"l3v 2r9",
    "addr:street":"Barrie Rd",
    "iso:country":"CA",
    "sg:address":"410 Barrie Rd",
    "sg:city":"Orillia",
    "sg:classifiers":[
        {
            "category":"Home & Garden",
            "subcategory":"Household Appliances",
            "type":"Retail Goods"
        }
    ],
    "sg:phone":"+1 705 326 2711",
    "sg:postcode":"L3V 2R9",
    "sg:province":"ON",
    "wof:name":"Hack's Appliance Svc & Parts",
    "wof:placetype":"venue"
},
  "geometry": {"coordinates":[-79.43729400629999,44.5939483643],"type":"Point"}
}