{
  "type": "Feature",
  "properties": {
    "iso:country":"CA",
    "sg:address":"141 Regina St",
    "sg:city":"North Bay",
    "sg:classifiers":[
        {
            "category":"Manufacturing",
            "subcategory":"Tools & Machinery",
            "type":"Manufacturing & Wholesale Goods"
        }
    ],
    "sg:phone":"+1 705 474 0410",
    "sg:postcode":"P1A 1A1",
    "sg:province":"ON",
    "sg:tags":[
        "equipment",
        "mining",
        "trencher",
        "supply"
    ],
    "wof:name":"Rahnmet",
    "wof:placetype":"venue"
},
  "geometry": {"coordinates":[-79.4619445801,46.3037605286],"type":"Point"}
}