{
  "type": "Feature",
  "properties": {
    "addr:full":"3687 Hwy 118 W Port Carling ON P0B 1J0",
    "addr:housenumber":"3687",
    "addr:postcode":"p0b 1j0",
    "addr:street":"Hwy 118 W",
    "iso:country":"CA",
    "sg:address":"3687 Hwy 118 W",
    "sg:city":"Port Carling",
    "sg:classifiers":[
        {
            "category":"Home & Garden",
            "subcategory":"Building Materials",
            "type":"Retail Goods"
        }
    ],
    "sg:phone":"+1 705 765 3105",
    "sg:postcode":"P0B 1J0",
    "sg:province":"ON",
    "wof:name":"Muskoka Lumber Home Care Bldg",
    "wof:placetype":"venue"
},
  "geometry": {"coordinates":[-79.588768,45.104424],"type":"Point"}
}