{
  "type": "Feature",
  "properties": {
    "addr:full":"6424 Gateway Blvd NW Edmonton AB T6H 2H9",
    "addr:housenumber":"6424",
    "addr:postcode":"t6h 2h9",
    "addr:street":"Gateway Blvd Nw",
    "iso:country":"CA",
    "sg:address":"6424 Gateway Blvd NW",
    "sg:city":"Edmonton",
    "sg:classifiers":[
        {
            "category":"Home & Garden",
            "subcategory":"Building Materials",
            "type":"Retail Goods"
        }
    ],
    "sg:phone":"+1 780 436 8780",
    "sg:postcode":"T6H 2H9",
    "sg:province":"AB",
    "sg:tags":[
        "glass",
        "window",
        "plate"
    ],
    "wof:name":"Crystal Glass Canada Ltd",
    "wof:placetype":"venue"
},
  "geometry": {"coordinates":[-113.49465179400001,53.5008888245],"type":"Point"}
}