{
  "type": "Feature",
  "properties": {
    "iso:country":"CA",
    "sg:city":"Prince George",
    "sg:classifiers":[
        {
            "category":"Organizations",
            "subcategory":"Professional Association",
            "type":"Services"
        }
    ],
    "sg:phone":"+1 250 562 4882",
    "sg:postcode":"V2L 3G6",
    "sg:province":"BC",
    "wof:name":"Canadian Northern Child Fstvl",
    "wof:placetype":"venue"
},
  "geometry": {"coordinates":[-122.751708984,53.9187927246],"type":"Point"}
}