{
  "type": "Feature",
  "properties": {
    "addr:full":"22337 Hwy 17 E Iron Bridge ON P0R 1H0",
    "addr:housenumber":"22337",
    "addr:postcode":"p0r 1h0",
    "addr:street":"Hwy 17 E Iron",
    "iso:country":"CA",
    "sg:address":"22337 Hwy 17 E",
    "sg:city":"Iron Bridge",
    "sg:classifiers":[
        {
            "category":"Travel",
            "subcategory":"Hotels & Motels",
            "type":"Entertainment"
        }
    ],
    "sg:phone":"+1 705 843 0262",
    "sg:postcode":"P0R 1H0",
    "sg:province":"ON",
    "wof:name":"Village Inn",
    "wof:placetype":"venue"
},
  "geometry": {"coordinates":[-83.2158508301,46.2781105042],"type":"Point"}
}