{
  "type": "Feature",
  "properties": {
    "addr:full":"1171 Rue Notre-Dame O Victoriaville QC G6P 7L1",
    "addr:housenumber":"1171",
    "addr:postcode":"g6p 7l1",
    "addr:street":"Rue Notre-Dame O",
    "iso:country":"CA",
    "sg:address":"1171 Rue Notre-Dame O",
    "sg:city":"Victoriaville",
    "sg:classifiers":[
        {
            "category":"Manufacturing",
            "subcategory":"Tools & Machinery",
            "type":"Manufacturing & Wholesale Goods"
        }
    ],
    "sg:phone":"+1 819 751 0095",
    "sg:postcode":"G6P 7L1",
    "sg:province":"QC",
    "sg:tags":[
        "computer",
        "parts",
        "supply"
    ],
    "wof:name":"Symcod Inc",
    "wof:placetype":"venue"
},
  "geometry": {"coordinates":[-71.9364242554,46.0700569153],"type":"Point"}
}