{
  "type": "Feature",
  "properties": {
    "iso:country":"CA",
    "sg:city":"Rock Forest",
    "sg:classifiers":[
        {
            "category":"Building & Trades",
            "subcategory":"Construction",
            "type":"Services"
        }
    ],
    "sg:phone":"+1 819 864 4628",
    "sg:postcode":"J1N 2N3",
    "sg:province":"QC",
    "sg:tags":[
        "insulation",
        "heat",
        "contractor"
    ],
    "wof:name":"Raymond Bilodeau Isolation Inc",
    "wof:placetype":"venue"
},
  "geometry": {"coordinates":[-71.99406433110001,45.3574943542],"type":"Point"}
}