{
  "type": "Feature",
  "properties": {
    "iso:country":"CA",
    "sg:address":"145 Richmond St W",
    "sg:city":"Toronto",
    "sg:classifiers":[
        {
            "category":"Restaurant",
            "type":"Food & Drink"
        }
    ],
    "sg:phone":"+1 416 955 1455",
    "sg:postcode":"M5H 2L2",
    "sg:province":"ON",
    "wof:name":"Ruth's Chris Steak House",
    "wof:placetype":"venue"
},
  "geometry": {"coordinates":[-79.3853683472,43.6501426697],"type":"Point"}
}