{
  "type": "Feature",
  "properties": {
    "addr:full":"1200 Rue Saint-Jean Quebec QC G1R 1S8",
    "addr:housenumber":"1200",
    "addr:postcode":"g1r 1s8",
    "addr:street":"Rue Saint-Jean",
    "iso:country":"CA",
    "sg:address":"1200 Rue Saint-Jean",
    "sg:city":"Quebec",
    "sg:classifiers":[
        {
            "category":"Restaurant",
            "type":"Food & Drink"
        }
    ],
    "sg:phone":"+1 418 694 0618",
    "sg:postcode":"G1R 1S8",
    "sg:province":"QC",
    "sg:tags":[
        "pub"
    ],
    "wof:name":"Pub Irlandais Le Saint-Patrick",
    "wof:placetype":"venue"
},
  "geometry": {"coordinates":[-71.2094421387,46.814617157],"type":"Point"}
}