{
  "type": "Feature",
  "properties": {
    "addr:full":"326 Main St Port Dover ON N0A 1N0",
    "addr:housenumber":"326",
    "addr:postcode":"n0a 1n0",
    "addr:street":"Main St",
    "iso:country":"CA",
    "sg:address":"326 Main St",
    "sg:city":"Port Dover",
    "sg:classifiers":[
        {
            "category":"Shopping",
            "subcategory":"Computers & Home Electronics",
            "type":"Retail Goods"
        }
    ],
    "sg:phone":"+1 519 583 3404",
    "sg:postcode":"N0A 1N0",
    "sg:province":"ON",
    "sg:tags":[
        "equipment",
        "dealer"
    ],
    "wof:name":"David Eaton Computer Svs",
    "wof:placetype":"venue"
},
  "geometry": {"coordinates":[-80.203987,42.78717],"type":"Point"}
}