{
  "type": "Feature",
  "properties": {
    "addr:full":"Saskatoon SK S7K 0L4",
    "addr:postcode":"s7k 0l4",
    "iso:country":"CA",
    "sg:city":"Saskatoon",
    "sg:classifiers":[
        {
            "category":"Professional",
            "subcategory":"Accounting & Tax Preparation",
            "type":"Services"
        }
    ],
    "sg:phone":"+1 306 931 3080",
    "sg:postcode":"S7K 0L4",
    "sg:province":"SK",
    "sg:tags":[
        "accountant"
    ],
    "wof:name":"Hvizdos, Tom G CA",
    "wof:placetype":"venue"
},
  "geometry": {"coordinates":[-106.659386,52.132973],"type":"Point"}
}