{
  "type": "Feature",
  "properties": {
    "iso:country":"CA",
    "sg:address":"706 Idylwyld Dr N",
    "sg:city":"Saskatoon",
    "sg:classifiers":[
        {
            "category":"Travel",
            "subcategory":"Hotels & Motels",
            "type":"Entertainment"
        }
    ],
    "sg:phone":"+1 306 664 4414",
    "sg:postcode":"S7L 0Z2",
    "sg:province":"SK",
    "wof:name":"Northgate Motor Inn",
    "wof:placetype":"venue"
},
  "geometry": {"coordinates":[-106.669921875,52.1362991333],"type":"Point"}
}