{
  "type": "Feature",
  "properties": {
    "addr:full":"Edmonton AB T5J 0K1",
    "addr:postcode":"t5j 0k1",
    "iso:country":"CA",
    "sg:city":"Edmonton",
    "sg:classifiers":[
        {
            "category":"Professional",
            "subcategory":"Accounting & Tax Preparation",
            "type":"Services"
        }
    ],
    "sg:phone":"+1 780 461 3800",
    "sg:postcode":"T5J 0K1",
    "sg:province":"AB",
    "sg:tags":[
        "accountant"
    ],
    "wof:name":"Draper, Morris B CA",
    "wof:placetype":"venue"
},
  "geometry": {"coordinates":[-113.491608,53.546745],"type":"Point"}
}