{
  "type": "Feature",
  "properties": {
    "addr:full":"2550 Rue Dubose Jonquiere QC G7S 4R4",
    "addr:housenumber":"2550",
    "addr:postcode":"g7s 4r4",
    "addr:street":"Rue Dubose",
    "iso:country":"CA",
    "sg:address":"2550 Rue Dubose",
    "sg:city":"Jonquiere",
    "sg:classifiers":[
        {
            "category":"Utilities",
            "subcategory":"Fuel Oil & Lpg",
            "type":"Services"
        }
    ],
    "sg:phone":"+1 418 548 2322",
    "sg:postcode":"G7S 4R4",
    "sg:province":"QC",
    "sg:tags":[
        "propane",
        "gas"
    ],
    "wof:name":"Superieur Propane Inc",
    "wof:placetype":"venue"
},
  "geometry": {"coordinates":[-71.161621,48.403397],"type":"Point"}
}