{
  "type": "Feature",
  "properties": {
    "addr:full":"833 Government Rd W Chaput Hughes ON P0K 1A0",
    "addr:housenumber":"833",
    "addr:postcode":"p0k 1a0",
    "addr:street":"Government Rd W Chaput",
    "iso:country":"CA",
    "sg:address":"833 Government Rd W",
    "sg:city":"Chaput Hughes",
    "sg:classifiers":[
        {
            "category":"Food & Beverages",
            "subcategory":"Groceries & Convenience Stores",
            "type":"Retail Goods"
        }
    ],
    "sg:phone":"+1 705 567 5537",
    "sg:postcode":"P0K 1A0",
    "sg:province":"ON",
    "sg:tags":[
        "variety"
    ],
    "wof:name":"Chantel's Variety Store",
    "wof:placetype":"venue"
},
  "geometry": {"coordinates":[-80.0826797485,48.1225013733],"type":"Point"}
}