{
  "type": "Feature",
  "properties": {
    "addr:full":"8196 Rue Juliette Lasalle QC H8N 1W6",
    "addr:housenumber":"8196",
    "addr:postcode":"h8n 1w6",
    "addr:street":"Rue Juliette",
    "iso:country":"CA",
    "sg:address":"8196 Rue Juliette",
    "sg:city":"Lasalle",
    "sg:classifiers":[
        {
            "category":"Food & Beverages",
            "subcategory":"Groceries & Convenience Stores",
            "type":"Retail Goods"
        }
    ],
    "sg:phone":"+1 514 365 0499",
    "sg:postcode":"H8N 1W6",
    "sg:province":"QC",
    "wof:name":"Marche Juliette",
    "wof:placetype":"venue"
},
  "geometry": {"coordinates":[-73.6295928955,45.4341773987],"type":"Point"}
}