{
  "type": "Feature",
  "properties": {
    "addr:full":"15 Shaver St Brantford ON N3T 5M1",
    "addr:housenumber":"15",
    "addr:postcode":"n3t 5m1",
    "addr:street":"Shaver St",
    "iso:country":"CA",
    "sg:address":"15 Shaver St",
    "sg:city":"Brantford",
    "sg:classifiers":[
        {
            "category":"Wholesale",
            "subcategory":"Machinery & Supplies",
            "type":"Manufacturing & Wholesale Goods"
        }
    ],
    "sg:phone":"+1 519 756 4800",
    "sg:postcode":"N3T 5M1",
    "sg:province":"ON",
    "sg:tags":[
        "valve"
    ],
    "wof:name":"Farris Engineering",
    "wof:placetype":"venue"
},
  "geometry": {"coordinates":[-80.303391,43.135014],"type":"Point"}
}