{
  "type": "Feature",
  "properties": {
    "addr:full":"101 Orchard Crt Whitby ON L1N 1H4",
    "addr:housenumber":"101",
    "addr:postcode":"l1n 1h4",
    "addr:street":"Orchard Crt",
    "iso:country":"CA",
    "sg:address":"101 Orchard Crt",
    "sg:city":"Whitby",
    "sg:classifiers":[
        {
            "category":"Professional",
            "subcategory":"Business Services",
            "type":"Services"
        }
    ],
    "sg:phone":"+1 905 668 4290",
    "sg:postcode":"L1N 1H4",
    "sg:province":"ON",
    "sg:tags":[
        "interior",
        "consultant",
        "design",
        "decorator"
    ],
    "wof:name":"Interiors By Ada Angevaare",
    "wof:placetype":"venue"
},
  "geometry": {"coordinates":[-78.93396799999999,43.871433],"type":"Point"}
}