{
  "type": "Feature",
  "properties": {
    "addr:full":"295 Pleasant St Miramichi NB E1V 1Y7",
    "addr:housenumber":"295",
    "addr:postcode":"e1v 1y7",
    "addr:street":"Pleasant St",
    "iso:country":"CA",
    "sg:address":"295 Pleasant St",
    "sg:city":"Miramichi",
    "sg:classifiers":[
        {
            "category":"Professional",
            "subcategory":"Lawyer & Legal Services",
            "type":"Services"
        }
    ],
    "sg:phone":"+1 506 627 0091",
    "sg:postcode":"E1V 1Y7",
    "sg:province":"NB",
    "sg:tags":[
        "attorney"
    ],
    "wof:name":"Hayes, Aloysius",
    "wof:placetype":"venue"
},
  "geometry": {"coordinates":[-65.5663909912,47.0014572144],"type":"Point"}
}