{
  "type": "Feature",
  "properties": {
    "addr:full":"761 Station Ave Victoria BC V9B 2S1",
    "addr:housenumber":"761",
    "addr:postcode":"v9b 2s1",
    "addr:street":"Station Ave",
    "iso:country":"CA",
    "sg:address":"761 Station Ave",
    "sg:city":"Victoria",
    "sg:classifiers":[
        {
            "category":"Social Services",
            "type":"Services"
        }
    ],
    "sg:phone":"+1 250 474 4443",
    "sg:postcode":"V9B 2S1",
    "sg:province":"BC",
    "sg:tags":[
        "food",
        "banks"
    ],
    "wof:name":"Goldstream Food Bank",
    "wof:placetype":"venue"
},
  "geometry": {"coordinates":[-123.36451700000001,48.428314],"type":"Point"}
}