{
  "type": "Feature",
  "properties": {
    "addr:full":"1109 West Riverside Dr Perth-Andover NB E7H 5G4",
    "addr:housenumber":"1109",
    "addr:postcode":"e7h 5g4",
    "addr:street":"West Riverside Dr",
    "iso:country":"CA",
    "sg:address":"1109 West Riverside Dr",
    "sg:city":"Perth-Andover",
    "sg:classifiers":[
        {
            "category":"Retail",
            "subcategory":"Funeral Services",
            "type":"Services"
        }
    ],
    "sg:phone":"+1 506 273 4155",
    "sg:postcode":"E7H 5G4",
    "sg:province":"NB",
    "sg:tags":[
        "director"
    ],
    "wof:name":"Brunswick Funeral Home Ltd",
    "wof:placetype":"venue"
},
  "geometry": {"coordinates":[-67.7051239014,46.7390441895],"type":"Point"}
}