{
  "type": "Feature",
  "properties": {
    "addr:full":"188 Bedford Hwy Halifax NS B3M 2K1",
    "addr:housenumber":"188",
    "addr:postcode":"b3m 2k1",
    "addr:street":"Bedford Hwy",
    "iso:country":"CA",
    "sg:address":"188 Bedford Hwy",
    "sg:city":"Halifax",
    "sg:classifiers":[
        {
            "category":"Restaurant",
            "type":"Food & Drink"
        }
    ],
    "sg:phone":"+1 902 443 0006",
    "sg:postcode":"B3M 2K1",
    "sg:province":"NS",
    "sg:tags":[
        "out"
    ],
    "wof:name":"Palina Pizza & Donair",
    "wof:placetype":"venue"
},
  "geometry": {"coordinates":[-63.6469535828,44.674446106],"type":"Point"}
}