{
  "type": "Feature",
  "properties": {
    "addr:full":"Bonne Bay NL A0K 1P0",
    "addr:postcode":"a0k 1p0",
    "addr:street":"Bonne",
    "iso:country":"CA",
    "sg:city":"Bonne Bay",
    "sg:classifiers":[
        {
            "category":"Government",
            "subcategory":"Office",
            "type":"Public Place"
        }
    ],
    "sg:phone":"+1 709 453 2273",
    "sg:postcode":"A0K 1P0",
    "sg:province":"NL",
    "sg:tags":[
        "village"
    ],
    "wof:name":"Woody Point Community Council",
    "wof:placetype":"venue"
},
  "geometry": {"coordinates":[-57.9161186218,49.5032196045],"type":"Point"}
}