{
  "type": "Feature",
  "properties": {
    "iso:country":"CA",
    "sg:address":"7651 Av Papineau",
    "sg:city":"Montreal",
    "sg:classifiers":[
        {
            "category":"Communications",
            "subcategory":"Radio Station",
            "type":"Services"
        }
    ],
    "sg:phone":"+1 514 728 1100",
    "sg:postcode":"H2E 2H1",
    "sg:province":"QC",
    "sg:tags":[
        "company",
        "broadcasting"
    ],
    "wof:name":"Radio Maria Canada",
    "wof:placetype":"venue"
},
  "geometry": {"coordinates":[-73.6138534546,45.5511169434],"type":"Point"}
}