{
  "type": "Feature",
  "properties": {
    "addr:full":"2449 213 St Bellevue AB T0K 0C0",
    "addr:housenumber":"2449",
    "addr:postcode":"t0k 0c0",
    "addr:street":"213 St",
    "iso:country":"CA",
    "sg:address":"2449 213 St",
    "sg:city":"Bellevue",
    "sg:classifiers":[
        {
            "category":"Food & Beverages",
            "subcategory":"Groceries & Convenience Stores",
            "type":"Retail Goods"
        }
    ],
    "sg:phone":"+1 403 564 4100",
    "sg:postcode":"T0K 0C0",
    "sg:province":"AB",
    "wof:name":"Wild Rose Confectionary",
    "wof:placetype":"venue"
},
  "geometry": {"coordinates":[-114.368332,49.581871],"type":"Point"}
}