{
  "type": "Feature",
  "properties": {
    "iso:country":"CA",
    "sg:address":"378 Queen St W",
    "sg:city":"Toronto",
    "sg:classifiers":[
        {
            "category":"Banks & Credit Unions",
            "subcategory":"Bank",
            "type":"Services"
        }
    ],
    "sg:phone":"+1 416 980 6911",
    "sg:postcode":"M5V 2A2",
    "sg:province":"ON",
    "wof:name":"Cibc",
    "wof:placetype":"venue"
},
  "geometry": {"coordinates":[-79.3960113525,43.6489524841],"type":"Point"}
}