{
  "type": "Feature",
  "properties": {
    "iso:country":"CA",
    "sg:address":"131 College St",
    "sg:city":"Smithville",
    "sg:classifiers":[
        {
            "category":"Manufacturing",
            "subcategory":"Printing",
            "type":"Manufacturing & Wholesale Goods"
        }
    ],
    "sg:phone":"+1 905 957 3751",
    "sg:postcode":"L0R 2A0",
    "sg:province":"ON",
    "sg:tags":[
        "printer"
    ],
    "wof:name":"Carruthers Printing",
    "wof:placetype":"venue"
},
  "geometry": {"coordinates":[-79.54498291020001,43.0984077454],"type":"Point"}
}