{
  "type": "Feature",
  "properties": {
    "addr:full":"174 Charles St Arnprior ON K7S 3V5",
    "addr:housenumber":"174",
    "addr:postcode":"k7s 3v5",
    "addr:street":"Charles St",
    "iso:country":"CA",
    "sg:address":"174 Charles St",
    "sg:city":"Arnprior",
    "sg:classifiers":[
        {
            "category":"Wholesale",
            "subcategory":"Apparel",
            "type":"Manufacturing & Wholesale Goods"
        }
    ],
    "sg:phone":"+1 613 623 2252",
    "sg:postcode":"K7S 3V5",
    "sg:province":"ON",
    "sg:tags":[
        "textile",
        "broker"
    ],
    "wof:name":"Mullins Marketing & Sales",
    "wof:placetype":"venue"
},
  "geometry": {"coordinates":[-76.354744,45.423794],"type":"Point"}
}