{
  "type": "Feature",
  "properties": {
    "addr:full":"4383 Rue Chateauguay Jonquiere QC G7X 7V5",
    "addr:housenumber":"4383",
    "addr:postcode":"g7x 7v5",
    "addr:street":"Rue Chateauguay",
    "iso:country":"CA",
    "sg:address":"4383 Rue Chateauguay",
    "sg:city":"Jonquiere",
    "sg:classifiers":[
        {
            "category":"Wholesale",
            "subcategory":"Auto Parts",
            "type":"Manufacturing & Wholesale Goods"
        }
    ],
    "sg:phone":"+1 418 547 5495",
    "sg:postcode":"G7X 7V5",
    "sg:province":"QC",
    "sg:tags":[
        "automobile",
        "rebuilt"
    ],
    "wof:name":"Pieces D'Autos Chateauguay",
    "wof:placetype":"venue"
},
  "geometry": {"coordinates":[-71.279076,48.418274],"type":"Point"}
}