{
  "type": "Feature",
  "properties": {
    "addr:full":"322 Wallace St Hope BC V0X 1L0",
    "addr:housenumber":"322",
    "addr:postcode":"v0x 1l0",
    "addr:street":"Wallace St",
    "iso:country":"CA",
    "sg:address":"322 Wallace St",
    "sg:city":"Hope",
    "sg:classifiers":[
        {
            "category":"Restaurant",
            "type":"Food & Drink"
        }
    ],
    "sg:phone":"+1 604 869 0729",
    "sg:postcode":"V0X 1L0",
    "sg:province":"BC",
    "sg:tags":[
        "shop",
        "coffee"
    ],
    "wof:name":"Blue Moose",
    "wof:placetype":"venue"
},
  "geometry": {"coordinates":[-121.440940857,49.379611969],"type":"Point"}
}