{
  "type": "Feature",
  "properties": {
    "iso:country":"CA",
    "sg:address":"8603 76 St",
    "sg:city":"Fort St John",
    "sg:classifiers":[
        {
            "category":"Mining & Drilling",
            "type":"Manufacturing & Wholesale Goods"
        }
    ],
    "sg:phone":"+1 250 785 3383",
    "sg:postcode":"V1J 2Z4",
    "sg:province":"BC",
    "sg:tags":[
        "consultant",
        "oil",
        "gas"
    ],
    "wof:name":"Geralyn Services",
    "wof:placetype":"venue"
},
  "geometry": {"coordinates":[-120.80298614500001,56.2327919006],"type":"Point"}
}