{
  "type": "Feature",
  "properties": {
    "addr:full":"370 Boul Desjardins Maniwaki QC J9E 2G1",
    "addr:housenumber":"370",
    "addr:postcode":"j9e 2g1",
    "addr:street":"Boul Desjardins",
    "iso:country":"CA",
    "sg:address":"370 Boul Desjardins",
    "sg:city":"Maniwaki",
    "sg:classifiers":[
        {
            "category":"Sports & Exercise",
            "subcategory":"Bowling",
            "type":"Entertainment"
        }
    ],
    "sg:phone":"+1 819 449 1977",
    "sg:postcode":"J9E 2G1",
    "sg:province":"QC",
    "sg:tags":[
        "center"
    ],
    "wof:name":"Quillorama 105",
    "wof:placetype":"venue"
},
  "geometry": {"coordinates":[-75.98133087159999,46.3943977356],"type":"Point"}
}