{
  "type": "Feature",
  "properties": {
    "iso:country":"CA",
    "sg:city":"Toronto",
    "sg:classifiers":[
        {
            "category":"Wholesale",
            "subcategory":"Apparel",
            "type":"Manufacturing & Wholesale Goods"
        }
    ],
    "sg:phone":"+1 416 504 5680",
    "sg:postcode":"M5V 3B1",
    "sg:province":"ON",
    "wof:name":"Accentrix",
    "wof:placetype":"venue"
},
  "geometry": {"coordinates":[-79.401848,43.646679],"type":"Point"}
}