{
  "type": "Feature",
  "properties": {
    "addr:full":"1261 Abbey Rd Pickering ON L1X 1W3",
    "addr:housenumber":"1261",
    "addr:postcode":"l1x 1w3",
    "addr:street":"Abbey Rd",
    "iso:country":"CA",
    "sg:address":"1261 Abbey Rd",
    "sg:city":"Pickering",
    "sg:classifiers":[
        {
            "category":"Real Estate",
            "subcategory":"Real Estate Agent",
            "type":"Services"
        }
    ],
    "sg:phone":"+1 905 839 5300",
    "sg:postcode":"L1X 1W3",
    "sg:province":"ON",
    "wof:name":"Homelife John Oliver Rl Estate",
    "wof:placetype":"venue"
},
  "geometry": {"coordinates":[-79.10231,43.85548],"type":"Point"}
}