{
  "type": "Feature",
  "properties": {
    "addr:full":"5 Ch Sirois Sainte-Anne-DE-Madawaska NB E7E 1H8",
    "addr:housenumber":"5",
    "addr:postcode":"e7e 1h8",
    "addr:street":"Ch Sirois",
    "iso:country":"CA",
    "sg:address":"5 Ch Sirois",
    "sg:city":"Sainte-Anne-DE-Madawaska",
    "sg:classifiers":[
        {
            "category":"Retail",
            "subcategory":"Auto Repair",
            "type":"Services"
        }
    ],
    "sg:phone":"+1 506 992 3192",
    "sg:postcode":"E7E 1H8",
    "sg:province":"NB",
    "sg:tags":[
        "repairing",
        "automobile"
    ],
    "wof:name":"Garage Daniel Nadeau",
    "wof:placetype":"venue"
},
  "geometry": {"coordinates":[-68.03858200000001,47.255489],"type":"Point"}
}