{
  "type": "Feature",
  "properties": {
    "addr:full":"191 Harcourt St Winnipeg MB R3J 3H2",
    "addr:housenumber":"191",
    "addr:postcode":"r3j 3h2",
    "addr:street":"Harcourt St",
    "iso:country":"CA",
    "sg:address":"191 Harcourt St",
    "sg:city":"Winnipeg",
    "sg:classifiers":[
        {
            "category":"Organizations",
            "subcategory":"Professional Association",
            "type":"Services"
        }
    ],
    "sg:phone":"+1 204 888 7961",
    "sg:postcode":"R3J 3H2",
    "sg:province":"MB",
    "wof:name":"Manitoba Teachers Society",
    "wof:placetype":"venue"
},
  "geometry": {"coordinates":[-97.269493103,49.8788909912],"type":"Point"}
}