{
  "type": "Feature",
  "properties": {
    "addr:full":"76 Mill St Baden ON N3A 2N6",
    "addr:housenumber":"76",
    "addr:postcode":"n3a 2n6",
    "addr:street":"Mill St",
    "iso:country":"CA",
    "sg:address":"76 Mill St",
    "sg:city":"Baden",
    "sg:classifiers":[
        {
            "category":"Manufacturing",
            "subcategory":"Pet Food",
            "type":"Manufacturing & Wholesale Goods"
        }
    ],
    "sg:phone":"+1 519 634 8812",
    "sg:postcode":"N3A 2N6",
    "sg:province":"ON",
    "sg:tags":[
        "feed"
    ],
    "wof:name":"Masterfeeds",
    "wof:placetype":"venue"
},
  "geometry": {"coordinates":[-80.669518,43.401962],"type":"Point"}
}