{
  "type": "Feature",
  "properties": {
    "addr:full":"145 Rue Saint-Laurent Salaberry-DE-Valleyfield QC J6S 2N2",
    "addr:housenumber":"145",
    "addr:postcode":"j6s 2n2",
    "addr:street":"Rue Saint-Laurent",
    "iso:country":"CA",
    "sg:address":"145 Rue Saint-Laurent",
    "sg:city":"Salaberry-DE-Valleyfield",
    "sg:classifiers":[
        {
            "category":"Retail",
            "subcategory":"Funeral Services",
            "type":"Services"
        }
    ],
    "sg:phone":"+1 450 373 8638",
    "sg:postcode":"J6S 2N2",
    "sg:province":"QC",
    "sg:tags":[
        "director"
    ],
    "wof:name":"Ernest Montpetit & Fils Inc",
    "wof:placetype":"venue"
},
  "geometry": {"coordinates":[-74.12394,45.259415],"type":"Point"}
}