{
  "type": "Feature",
  "properties": {
    "addr:full":"377 Rue Notre-Dame Gatineau QC J8P 1L6",
    "addr:housenumber":"377",
    "addr:postcode":"j8p 1l6",
    "addr:street":"Rue Notre-Dame",
    "iso:country":"CA",
    "sg:address":"377 Rue Notre-Dame",
    "sg:city":"Gatineau",
    "sg:classifiers":[
        {
            "category":"Bars & Pubs",
            "type":"Food & Drink"
        }
    ],
    "sg:phone":"+1 819 643 9831",
    "sg:postcode":"J8P 1L6",
    "sg:province":"QC",
    "wof:name":"Brasserie LA Vieille",
    "wof:placetype":"venue"
},
  "geometry": {"coordinates":[-75.641014,45.481457],"type":"Point"}
}