{
  "type": "Feature",
  "properties": {
    "addr:full":"126 Cartwright Ave North York ON M6A 1V2",
    "addr:housenumber":"126",
    "addr:postcode":"m6a 1v2",
    "addr:street":"Cartwright Ave",
    "iso:country":"CA",
    "sg:address":"126 Cartwright Ave",
    "sg:city":"North York",
    "sg:classifiers":[
        {
            "category":"Shopping",
            "subcategory":"Clothing, Apparel, & Fashions",
            "type":"Retail Goods"
        }
    ],
    "sg:phone":"+1 416 782 4985",
    "sg:postcode":"M6A 1V2",
    "sg:province":"ON",
    "wof:name":"Janos",
    "wof:placetype":"venue"
},
  "geometry": {"coordinates":[-79.4663391113,43.7221298218],"type":"Point"}
}