{
  "type": "Feature",
  "properties": {
    "addr:full":"1080 Dovercourt Rd #2 Toronto ON M6H 2X8",
    "addr:housenumber":"1080",
    "addr:postcode":"m6h 2x8",
    "addr:street":"Dovercourt Rd # 2",
    "iso:country":"CA",
    "sg:address":"1080 Dovercourt Rd #2",
    "sg:city":"Toronto",
    "sg:classifiers":[
        {
            "category":"Health Services",
            "subcategory":"Medical Lab",
            "type":"Services"
        }
    ],
    "sg:phone":"+1 416 531 7262",
    "sg:postcode":"M6H 2X8",
    "sg:province":"ON",
    "sg:tags":[
        "laboratory"
    ],
    "wof:name":"Orfan Dental Laboratory",
    "wof:placetype":"venue"
},
  "geometry": {"coordinates":[-79.432816,43.669395],"type":"Point"}
}