{
  "type": "Feature",
  "properties": {
    "addr:full":"3662 Mount Seymour Pky #148 North Vancouver BC V7H 2Y5",
    "addr:housenumber":"3662",
    "addr:postcode":"v7h 2y5",
    "addr:street":"Mount Seymour Pky # 148",
    "iso:country":"CA",
    "sg:address":"3662 Mount Seymour Pky #148",
    "sg:city":"North Vancouver",
    "sg:classifiers":[
        {
            "category":"Restaurant",
            "type":"Food & Drink"
        }
    ],
    "sg:phone":"+1 604 924 2333",
    "sg:postcode":"V7H 2Y5",
    "sg:province":"BC",
    "sg:tags":[
        "pizza"
    ],
    "wof:name":"Little Caesars Pizza",
    "wof:placetype":"venue"
},
  "geometry": {"coordinates":[-122.97036,49.316044],"type":"Point"}
}