{
  "type": "Feature",
  "properties": {
    "addr:full":"Lac-Etchemin QC G0R 1S0",
    "addr:postcode":"g0r 1s0",
    "iso:country":"CA",
    "sg:city":"Lac-Etchemin",
    "sg:classifiers":[
        {
            "category":"Autos & Motor Vehicles",
            "subcategory":"Automobile Sales",
            "type":"Retail Goods"
        }
    ],
    "sg:phone":"+1 418 625 6101",
    "sg:postcode":"G0R 1S0",
    "sg:province":"QC",
    "sg:tags":[
        "car",
        "dealer"
    ],
    "wof:name":"Garage Florent Begin Inc",
    "wof:placetype":"venue"
},
  "geometry": {"coordinates":[-70.5108413696,46.3991355896],"type":"Point"}
}