{
  "type": "Feature",
  "properties": {
    "iso:country":"CA",
    "sg:address":"119 Isabella St",
    "sg:city":"Campbellford",
    "sg:classifiers":[
        {
            "category":"Shopping",
            "type":"Retail Goods"
        }
    ],
    "sg:phone":"+1 705 653 5962",
    "sg:postcode":"K0L 1L0",
    "sg:province":"ON",
    "sg:tags":[
        "supply",
        "equipment",
        "audiologists",
        "hearing",
        "impaired"
    ],
    "wof:name":"Helix Hearing Care Ctr",
    "wof:placetype":"venue"
},
  "geometry": {"coordinates":[-77.7905960083,44.3119087219],"type":"Point"}
}