{
  "type": "Feature",
  "properties": {
    "addr:full":"846 Fort Garry Rd Lockport MB R1A 3W8",
    "addr:housenumber":"846",
    "addr:postcode":"r1a 3w8",
    "addr:street":"Fort Garry Rd",
    "iso:country":"CA",
    "sg:address":"846 Fort Garry Rd",
    "sg:city":"Lockport",
    "sg:classifiers":[
        {
            "category":"Manufacturing",
            "subcategory":"Tools & Machinery",
            "type":"Manufacturing & Wholesale Goods"
        }
    ],
    "sg:phone":"+1 204 482 5257",
    "sg:postcode":"R1A 3W8",
    "sg:province":"MB",
    "sg:tags":[
        "machine",
        "shop"
    ],
    "wof:name":"G T Metal Works",
    "wof:placetype":"venue"
},
  "geometry": {"coordinates":[-96.95974,50.12471],"type":"Point"}
}