{
  "type": "Feature",
  "properties": {
    "iso:country":"CA",
    "sg:address":"217 Queen St S",
    "sg:city":"Mississauga",
    "sg:classifiers":[
        {
            "category":"Personal",
            "subcategory":"Beauty Salon",
            "type":"Services"
        }
    ],
    "sg:phone":"+1 905 542 8777",
    "sg:postcode":"L5M 1L6",
    "sg:province":"ON",
    "wof:name":"Hot Tips Nail N' Esthetics",
    "wof:placetype":"venue"
},
  "geometry": {"coordinates":[-79.60005187989999,43.5429649353],"type":"Point"}
}