{
  "type": "Feature",
  "properties": {
    "addr:full":"785 Britannia Ave Hamilton ON L8H 2B6",
    "addr:housenumber":"785",
    "addr:postcode":"l8h 2b6",
    "addr:street":"Britannia Ave",
    "iso:country":"CA",
    "sg:address":"785 Britannia Ave",
    "sg:city":"Hamilton",
    "sg:classifiers":[
        {
            "category":"Education",
            "subcategory":"School",
            "type":"Public Place"
        }
    ],
    "sg:phone":"+1 905 545 0532",
    "sg:postcode":"L8H 2B6",
    "sg:province":"ON",
    "wof:name":"St Helen's School",
    "wof:placetype":"venue"
},
  "geometry": {"coordinates":[-79.78181499999999,43.23975],"type":"Point"}
}