{
  "type": "Feature",
  "properties": {
    "addr:full":"Greeleytown Rd Conception Bay South NL A1W 1M7",
    "addr:postcode":"a1w 1m7",
    "addr:street":"Greeleytown Rd",
    "iso:country":"CA",
    "sg:address":"Greeleytown Rd",
    "sg:city":"Conception Bay South",
    "sg:classifiers":[
        {
            "category":"Retail",
            "subcategory":"Animal Services",
            "type":"Services"
        }
    ],
    "sg:phone":"+1 709 834 8822",
    "sg:postcode":"A1W 1M7",
    "sg:province":"NL",
    "sg:tags":[
        "pet",
        "grooming",
        "washing"
    ],
    "wof:name":"Bernice's Pet Boutique",
    "wof:placetype":"venue"
},
  "geometry": {"coordinates":[-52.9814147949,47.492641449],"type":"Point"}
}