{
  "type": "Feature",
  "properties": {
    "addr:full":"Whitefish ON P0M 3E0",
    "addr:postcode":"p0m 3e0",
    "iso:country":"CA",
    "sg:city":"Whitefish",
    "sg:classifiers":[
        {
            "category":"Autos & Motor Vehicles",
            "subcategory":"Boat Sales",
            "type":"Retail Goods"
        }
    ],
    "sg:phone":"+1 705 866 2821",
    "sg:postcode":"P0M 3E0",
    "sg:province":"ON",
    "sg:tags":[
        "dealer"
    ],
    "wof:name":"Duhamel & Dewar Inc",
    "wof:placetype":"venue"
},
  "geometry": {"coordinates":[-81.31559799999999,46.378181],"type":"Point"}
}