{
  "type": "Feature",
  "properties": {
    "addr:full":"Toronto ON M5A 1E3",
    "addr:postcode":"m5a 1e3",
    "iso:country":"CA",
    "sg:city":"Toronto",
    "sg:classifiers":[
        {
            "category":"Communications",
            "subcategory":"Film & Video Production",
            "type":"Services"
        }
    ],
    "sg:phone":"+1 416 214 0300",
    "sg:postcode":"M5A 1E3",
    "sg:province":"ON",
    "sg:tags":[
        "motion",
        "picture",
        "studio",
        "producer"
    ],
    "wof:name":"Filmblanc Canada",
    "wof:placetype":"venue"
},
  "geometry": {"coordinates":[-79.36930099999999,43.649899],"type":"Point"}
}