{
  "type": "Feature",
  "properties": {
    "addr:full":"Red Deer AB T4R 2T4",
    "addr:postcode":"t4r 2t4",
    "iso:country":"CA",
    "sg:city":"Red Deer",
    "sg:classifiers":[
        {
            "category":"Food & Beverages",
            "subcategory":"Liquor & Beverages",
            "type":"Retail Goods"
        }
    ],
    "sg:phone":"+1 403 347 5675",
    "sg:postcode":"T4R 2T4",
    "sg:province":"AB",
    "sg:tags":[
        "store"
    ],
    "wof:name":"Liquor Crossing",
    "wof:placetype":"venue"
},
  "geometry": {"coordinates":[-113.818535,52.239017],"type":"Point"}
}