{
  "type": "Feature",
  "properties": {
    "addr:full":"1426 Rue Notre-Dame N Sainte-Marie QC G6E 2M3",
    "addr:housenumber":"1426",
    "addr:postcode":"g6e 2m3",
    "addr:street":"Rue Notre-Dame N",
    "iso:country":"CA",
    "sg:address":"1426 Rue Notre-Dame N",
    "sg:city":"Sainte-Marie",
    "sg:classifiers":[
        {
            "category":"Organizations",
            "subcategory":"Professional Association",
            "type":"Services"
        }
    ],
    "sg:phone":"+1 418 387 3711",
    "sg:postcode":"G6E 2M3",
    "sg:province":"QC",
    "wof:name":"Club Aramis Ste-Marie Beauce",
    "wof:placetype":"venue"
},
  "geometry": {"coordinates":[-71.048897,46.460339],"type":"Point"}
}