{
  "type": "Feature",
  "properties": {
    "addr:full":"15 Aspen Rd Happy Valley-Goose Bay NL A0P 1E0",
    "addr:housenumber":"15",
    "addr:postcode":"a0p 1e0",
    "addr:street":"Aspen Rd",
    "iso:country":"CA",
    "sg:address":"15 Aspen Rd",
    "sg:city":"Happy Valley-Goose Bay",
    "sg:classifiers":[
        {
            "category":"Building & Trades",
            "subcategory":"Construction",
            "type":"Services"
        }
    ],
    "sg:phone":"+1 709 896 2033",
    "sg:postcode":"A0P 1E0",
    "sg:province":"NL",
    "sg:tags":[
        "welding",
        "general",
        "contractor"
    ],
    "wof:name":"Enviro-Safe Fuel Systems Ltd",
    "wof:placetype":"venue"
},
  "geometry": {"coordinates":[-60.3864974976,53.3168373108],"type":"Point"}
}