{
  "type": "Feature",
  "properties": {
    "addr:full":"115 Wanyandi Ave Hinton AB T7V 1M6",
    "addr:housenumber":"115",
    "addr:postcode":"t7v 1m6",
    "addr:street":"Wanyandi Ave",
    "iso:country":"CA",
    "sg:address":"115 Wanyandi Ave",
    "sg:city":"Hinton",
    "sg:classifiers":[
        {
            "category":"Organizations",
            "subcategory":"Religious Organization",
            "type":"Services"
        }
    ],
    "sg:phone":"+1 780 865 3732",
    "sg:postcode":"T7V 1M6",
    "sg:province":"AB",
    "sg:tags":[
        "church"
    ],
    "wof:name":"Jehovah's Witnesses",
    "wof:placetype":"venue"
},
  "geometry": {"coordinates":[-117.599396,53.392231],"type":"Point"}
}