{
  "type": "Feature",
  "properties": {
    "addr:full":"531 Main St Montague PE C0A 1R0",
    "addr:housenumber":"531",
    "addr:postcode":"c0a 1r0",
    "addr:street":"Main St",
    "iso:country":"CA",
    "sg:address":"531 Main St",
    "sg:city":"Montague",
    "sg:classifiers":[
        {
            "category":"Food & Beverages",
            "subcategory":"Groceries & Convenience Stores",
            "type":"Retail Goods"
        }
    ],
    "sg:phone":"+1 902 838 3388",
    "sg:postcode":"C0A 1R0",
    "sg:province":"PE",
    "sg:tags":[
        "grocer"
    ],
    "wof:name":"Sobeys Stores Ltd",
    "wof:placetype":"venue"
},
  "geometry": {"coordinates":[-62.650379,46.168346],"type":"Point"}
}