{
  "type": "Feature",
  "properties": {
    "addr:full":"144 Sheldon Ave N Kitchener ON N2H 3M8",
    "addr:housenumber":"144",
    "addr:postcode":"n2h 3m8",
    "addr:street":"Sheldon Ave N",
    "iso:country":"CA",
    "sg:address":"144 Sheldon Ave N",
    "sg:city":"Kitchener",
    "sg:classifiers":[
        {
            "category":"Shopping",
            "subcategory":"Discount & Variety Stores",
            "type":"Retail Goods"
        }
    ],
    "sg:phone":"+1 519 749 3979",
    "sg:postcode":"N2H 3M8",
    "sg:province":"ON",
    "wof:name":"Jmk Trade",
    "wof:placetype":"venue"
},
  "geometry": {"coordinates":[-80.4640426636,43.4430770874],"type":"Point"}
}