{
  "type": "Feature",
  "properties": {
    "addr:full":"Winnipeg MB R3B 3H6",
    "addr:postcode":"r3b 3h6",
    "iso:country":"CA",
    "sg:city":"Winnipeg",
    "sg:classifiers":[
        {
            "category":"Shopping",
            "subcategory":"Jewelry",
            "type":"Retail Goods"
        }
    ],
    "sg:phone":"+1 204 942 2716",
    "sg:postcode":"R3B 3H6",
    "sg:province":"MB",
    "sg:tags":[
        "jeweler"
    ],
    "wof:name":"Rings & Things",
    "wof:placetype":"venue"
},
  "geometry": {"coordinates":[-97.148155,49.892189],"type":"Point"}
}