{
  "type": "Feature",
  "properties": {
    "addr:full":"911 Purdy Mills Rd Kingston ON K7M 3N1",
    "addr:housenumber":"911",
    "addr:postcode":"k7m 3n1",
    "addr:street":"Purdy Mills Rd",
    "iso:country":"CA",
    "sg:address":"911 Purdy Mills Rd",
    "sg:city":"Kingston",
    "sg:classifiers":[
        {
            "category":"Health Services",
            "subcategory":"Chiropractor",
            "type":"Services"
        }
    ],
    "sg:phone":"+1 613 544 0591",
    "sg:postcode":"K7M 3N1",
    "sg:province":"ON",
    "wof:name":"Cataraqui Chiropractic Ctr",
    "wof:placetype":"venue"
},
  "geometry": {"coordinates":[-76.54212200000001,44.258762],"type":"Point"}
}