{
  "type": "Feature",
  "properties": {
    "addr:full":"325 Simcoe St S Oshawa ON L1H 4H9",
    "addr:housenumber":"325",
    "addr:postcode":"l1h 4h9",
    "addr:street":"Simcoe St S",
    "iso:country":"CA",
    "sg:address":"325 Simcoe St S",
    "sg:city":"Oshawa",
    "sg:classifiers":[
        {
            "category":"Personal",
            "subcategory":"Tattoo Parlor",
            "type":"Services"
        }
    ],
    "sg:phone":"+1 905 404 6603",
    "sg:postcode":"L1H 4H9",
    "sg:province":"ON",
    "sg:tags":[
        "tattooing"
    ],
    "wof:name":"Wild Ink Tattooing",
    "wof:placetype":"venue"
},
  "geometry": {"coordinates":[-78.8594589233,43.8890304565],"type":"Point"}
}