{
  "type": "Feature",
  "properties": {
    "addr:full":"6482 Rannock Ave Winnipeg MB R3R 2X1",
    "addr:housenumber":"6482",
    "addr:postcode":"r3r 2x1",
    "addr:street":"Rannock Ave",
    "iso:country":"CA",
    "sg:address":"6482 Rannock Ave",
    "sg:city":"Winnipeg",
    "sg:classifiers":[
        {
            "category":"Building & Trades",
            "subcategory":"Construction",
            "type":"Services"
        }
    ],
    "sg:phone":"+1 204 895 8999",
    "sg:postcode":"R3R 2X1",
    "sg:province":"MB",
    "sg:tags":[
        "painter"
    ],
    "wof:name":"Tomas Silva Decorating & Paint",
    "wof:placetype":"venue"
},
  "geometry": {"coordinates":[-97.31104999999999,49.850189],"type":"Point"}
}