{
  "type": "Feature",
  "properties": {
    "addr:full":"280 Boul Perron O Caplan QC G0C 1H0",
    "addr:housenumber":"280",
    "addr:postcode":"g0c 1h0",
    "addr:street":"Boul Perron O",
    "iso:country":"CA",
    "sg:address":"280 Boul Perron O",
    "sg:city":"Caplan",
    "sg:classifiers":[
        {
            "category":"Health Services",
            "subcategory":"Medical Lab",
            "type":"Services"
        }
    ],
    "sg:phone":"+1 418 388 5303",
    "sg:postcode":"G0C 1H0",
    "sg:province":"QC",
    "wof:name":"Theriault, Gerard R",
    "wof:placetype":"venue"
},
  "geometry": {"coordinates":[-65.6391983032,48.0901412964],"type":"Point"}
}