{
  "type": "Feature",
  "properties": {
    "iso:country":"CA",
    "sg:address":"484 East St N",
    "sg:city":"Sarnia",
    "sg:classifiers":[
        {
            "category":"Personal",
            "subcategory":"Beauty Salon",
            "type":"Services"
        }
    ],
    "sg:phone":"+1 519 383 0909",
    "sg:postcode":"N7T 6Y4",
    "sg:province":"ON",
    "wof:name":"Hair Sculptors",
    "wof:placetype":"venue"
},
  "geometry": {"coordinates":[-82.38600158689999,42.9846687317],"type":"Point"}
}