{
  "type": "Feature",
  "properties": {
    "addr:full":"39 Ferndale Ave Winnipeg MB R2H 1T7",
    "addr:housenumber":"39",
    "addr:postcode":"r2h 1t7",
    "addr:street":"Ferndale Ave",
    "iso:country":"CA",
    "sg:address":"39 Ferndale Ave",
    "sg:city":"Winnipeg",
    "sg:classifiers":[
        {
            "category":"Professional",
            "subcategory":"Management & Consulting",
            "type":"Services"
        }
    ],
    "sg:phone":"+1 204 231 1527",
    "sg:postcode":"R2H 1T7",
    "sg:province":"MB",
    "sg:tags":[
        "consultant",
        "educational"
    ],
    "wof:name":"Connect, Ed",
    "wof:placetype":"venue"
},
  "geometry": {"coordinates":[-97.12763200000001,49.872749],"type":"Point"}
}