{
  "type": "Feature",
  "properties": {
    "addr:full":"148 Rue Jacques-Cartier N Saint-Jean-Sur-Richelieu QC J3B 6S6",
    "addr:housenumber":"148",
    "addr:postcode":"j3b 6s6",
    "addr:street":"Rue Jacques-Cartier N",
    "iso:country":"CA",
    "sg:address":"148 Rue Jacques-Cartier N",
    "sg:city":"Saint-Jean-Sur-Richelieu",
    "sg:classifiers":[
        {
            "category":"Social Services",
            "type":"Services"
        }
    ],
    "sg:phone":"+1 450 346 7369",
    "sg:postcode":"J3B 6S6",
    "sg:province":"QC",
    "sg:tags":[
        "organization",
        "welfare"
    ],
    "wof:name":"Inclusion",
    "wof:placetype":"venue"
},
  "geometry": {"coordinates":[-73.253616333,45.3040351868],"type":"Point"}
}