{
  "type": "Feature",
  "properties": {
    "iso:country":"CA",
    "sg:address":"1214 County Road 22",
    "sg:city":"Emeryville",
    "sg:classifiers":[
        {
            "category":"Home & Garden",
            "subcategory":"Garden Supply",
            "type":"Retail Goods"
        }
    ],
    "sg:phone":"+1 519 727 5031",
    "sg:postcode":"N0R 1C0",
    "sg:province":"ON",
    "sg:tags":[
        "engine",
        "lawn",
        "mower"
    ],
    "wof:name":"Campeau Small Engine Svc",
    "wof:placetype":"venue"
},
  "geometry": {"coordinates":[-82.76020812989999,42.2976303101],"type":"Point"}
}