{
  "type": "Feature",
  "properties": {
    "addr:full":"137 George St Oakville ON L6J 3B9",
    "addr:housenumber":"137",
    "addr:postcode":"l6j 3b9",
    "addr:street":"George St",
    "iso:country":"CA",
    "sg:address":"137 George St",
    "sg:city":"Oakville",
    "sg:classifiers":[
        {
            "category":"Professional",
            "subcategory":"Advertising",
            "type":"Services"
        }
    ],
    "sg:phone":"+1 905 338 0000",
    "sg:postcode":"L6J 3B9",
    "sg:province":"ON",
    "sg:tags":[
        "counselor"
    ],
    "wof:name":"Walker Media",
    "wof:placetype":"venue"
},
  "geometry": {"coordinates":[-79.66920500000001,43.446438],"type":"Point"}
}