{
  "type": "Feature",
  "properties": {
    "addr:full":"Etobicoke ON M9C 4Z5",
    "addr:postcode":"m9c 4z5",
    "iso:country":"CA",
    "sg:city":"Etobicoke",
    "sg:classifiers":[
        {
            "category":"Wholesale",
            "subcategory":"Groceries",
            "type":"Manufacturing & Wholesale Goods"
        }
    ],
    "sg:phone":"+1 416 621 0674",
    "sg:postcode":"M9C 4Z5",
    "sg:province":"ON",
    "sg:tags":[
        "grocer"
    ],
    "wof:name":"Carriere Foods Inc",
    "wof:placetype":"venue"
},
  "geometry": {"coordinates":[-79.5632781982,43.6395187378],"type":"Point"}
}