{
  "type": "Feature",
  "properties": {
    "addr:full":"325 Av Avro Pointe-Claire QC H9R 5W3",
    "addr:postcode":"h9r 5w3",
    "addr:street":"325 Av Avro",
    "iso:country":"CA",
    "sg:address":"325 Av Avro",
    "sg:city":"Pointe-Claire",
    "sg:classifiers":[
        {
            "category":"Manufacturing",
            "subcategory":"Metals",
            "type":"Manufacturing & Wholesale Goods"
        }
    ],
    "sg:phone":"+1 514 697 5120",
    "sg:postcode":"H9R 5W3",
    "sg:province":"QC",
    "sg:tags":[
        "extruded",
        "product",
        "door",
        "aluminum"
    ],
    "wof:name":"Indalex Limitee",
    "wof:placetype":"venue"
},
  "geometry": {"coordinates":[-73.79673,45.468388],"type":"Point"}
}