{
  "type": "Feature",
  "properties": {
    "addr:full":"Bracebridge ON P1L 1R9",
    "addr:postcode":"p1l 1r9",
    "iso:country":"CA",
    "sg:city":"Bracebridge",
    "sg:classifiers":[
        {
            "category":"Home & Garden",
            "subcategory":"Household Appliances",
            "type":"Retail Goods"
        }
    ],
    "sg:phone":"+1 705 645 7579",
    "sg:postcode":"P1L 1R9",
    "sg:province":"ON",
    "wof:name":"Murray Ellis Appliances Ltd",
    "wof:placetype":"venue"
},
  "geometry": {"coordinates":[-79.308678,45.04047],"type":"Point"}
}