{
  "type": "Feature",
  "properties": {
    "addr:full":"Dorval QC H9P 2R9",
    "addr:postcode":"h9p 2r9",
    "iso:country":"CA",
    "sg:city":"Dorval",
    "sg:classifiers":[
        {
            "category":"Freight",
            "type":"Transportation"
        }
    ],
    "sg:phone":"+1 514 631 2001",
    "sg:postcode":"H9P 2R9",
    "sg:province":"QC",
    "sg:tags":[
        "trucking"
    ],
    "wof:name":"Transport Yellow Inc",
    "wof:placetype":"venue"
},
  "geometry": {"coordinates":[-73.7225112915,45.4630317688],"type":"Point"}
}