{
  "type": "Feature",
  "properties": {
    "addr:full":"225 Manitoba Ave Selkirk MB R1A 0Y4",
    "addr:housenumber":"225",
    "addr:postcode":"r1a 0y4",
    "addr:street":"Manitoba Ave",
    "iso:country":"CA",
    "sg:address":"225 Manitoba Ave",
    "sg:city":"Selkirk",
    "sg:classifiers":[
        {
            "category":"Cinema",
            "subcategory":"Movie Theater",
            "type":"Entertainment"
        }
    ],
    "sg:phone":"+1 204 482 3912",
    "sg:postcode":"R1A 0Y4",
    "sg:province":"MB",
    "wof:name":"Garry Theatre",
    "wof:placetype":"venue"
},
  "geometry": {"coordinates":[-96.8701095581,50.1442260742],"type":"Point"}
}