{
  "type": "Feature",
  "properties": {
    "iso:country":"CA",
    "sg:address":"1423 Boul Saint-Paul",
    "sg:city":"Chicoutimi",
    "sg:classifiers":[
        {
            "category":"Building & Trades",
            "subcategory":"Equipment Rental",
            "type":"Services"
        }
    ],
    "sg:phone":"+1 418 543 2525",
    "sg:postcode":"G7J 3Y3",
    "sg:province":"QC",
    "sg:tags":[
        "scaffolding"
    ],
    "wof:name":"United Rentals",
    "wof:placetype":"venue"
},
  "geometry": {"coordinates":[-71.0948791504,48.4057884216],"type":"Point"}
}