{
  "type": "Feature",
  "properties": {
    "addr:full":"312 Millidge Ave Saint John NB E2K 2N1",
    "addr:housenumber":"312",
    "addr:postcode":"e2k 2n1",
    "addr:street":"Millidge Ave",
    "iso:country":"CA",
    "sg:address":"312 Millidge Ave",
    "sg:city":"Saint John",
    "sg:classifiers":[
        {
            "category":"Social Services",
            "subcategory":"Child Care",
            "type":"Services"
        }
    ],
    "sg:phone":"+1 506 634 7414",
    "sg:postcode":"E2K 2N1",
    "sg:province":"NB",
    "wof:name":"Millidge Avenue Tot Spot Child",
    "wof:placetype":"venue"
},
  "geometry": {"coordinates":[-66.090042,45.286385],"type":"Point"}
}