{
  "type": "Feature",
  "properties": {
    "addr:full":"2391 Midlothian Rd Burks Falls ON P0A 1C0",
    "addr:housenumber":"2391",
    "addr:postcode":"p0a 1c0",
    "addr:street":"Midlothian Rd",
    "iso:country":"CA",
    "sg:address":"2391 Midlothian Rd",
    "sg:city":"Burks Falls",
    "sg:classifiers":[
        {
            "category":"Building & Trades",
            "subcategory":"Construction",
            "type":"Services"
        }
    ],
    "sg:phone":"+1 705 387 4498",
    "sg:postcode":"P0A 1C0",
    "sg:province":"ON",
    "sg:tags":[
        "water",
        "well",
        "drilling"
    ],
    "wof:name":"Ransome Well Drilling",
    "wof:placetype":"venue"
},
  "geometry": {"coordinates":[-79.5904846191,45.589805603],"type":"Point"}
}