{
  "type": "Feature",
  "properties": {
    "addr:full":"6932 76 Ave NW Edmonton AB T6B 2R2",
    "addr:housenumber":"6932",
    "addr:postcode":"t6b 2r2",
    "addr:street":"76 Ave Nw",
    "iso:country":"CA",
    "sg:address":"6932 76 Ave NW",
    "sg:city":"Edmonton",
    "sg:classifiers":[
        {
            "category":"Building & Trades",
            "subcategory":"Construction",
            "type":"Services"
        }
    ],
    "sg:phone":"+1 780 450 9100",
    "sg:postcode":"T6B 2R2",
    "sg:province":"AB",
    "sg:tags":[
        "refinishing",
        "floor",
        "laying",
        "rug",
        "resurfacing",
        "dealer",
        "carpet"
    ],
    "wof:name":"Lifestyles Flooring Outlet",
    "wof:placetype":"venue"
},
  "geometry": {"coordinates":[-113.434135,53.512451],"type":"Point"}
}