{
  "type": "Feature",
  "properties": {
    "addr:full":"6710 Hwy 89 W Mount Forest ON N0G 2L0",
    "addr:housenumber":"6710",
    "addr:postcode":"n0g 2l0",
    "addr:street":"Hwy 89 W",
    "iso:country":"CA",
    "sg:address":"6710 Hwy 89 W",
    "sg:city":"Mount Forest",
    "sg:classifiers":[
        {
            "category":"Retail",
            "subcategory":"Animal Services",
            "type":"Services"
        }
    ],
    "sg:phone":"+1 519 323 9399",
    "sg:postcode":"N0G 2L0",
    "sg:province":"ON",
    "sg:tags":[
        "pet",
        "boarding",
        "sitting"
    ],
    "wof:name":"Bonnie View Kennels",
    "wof:placetype":"venue"
},
  "geometry": {"coordinates":[-81.9993438721,43.0979690552],"type":"Point"}
}