{
  "type": "Feature",
  "properties": {
    "addr:full":"PO Box 5544 STN Main Fort Mcmurray AB T9H 3G5",
    "addr:housenumber":"po",
    "addr:postcode":"t9h 3g5",
    "addr:street":"Box 5544 Stn",
    "iso:country":"CA",
    "sg:address":"PO Box 5544 STN Main",
    "sg:city":"Fort Mcmurray",
    "sg:classifiers":[
        {
            "category":"Wholesale",
            "subcategory":"Electrical",
            "type":"Manufacturing & Wholesale Goods"
        }
    ],
    "sg:phone":"+1 780 743 4245",
    "sg:postcode":"T9H 3G5",
    "sg:province":"AB",
    "sg:tags":[
        "sound",
        "equipment",
        "system",
        "consultant"
    ],
    "wof:name":"Show 'N' Go Auto Specialties",
    "wof:placetype":"venue"
},
  "geometry": {"coordinates":[-111.380302,56.727188],"type":"Point"}
}