{
  "type": "Feature",
  "properties": {
    "addr:full":"1620 8th Ave E Owen Sound ON N4K 3B9",
    "addr:housenumber":"1620",
    "addr:postcode":"n4k 3b9",
    "addr:street":"8Th Ave E",
    "iso:country":"CA",
    "sg:address":"1620 8th Ave E",
    "sg:city":"Owen Sound",
    "sg:classifiers":[
        {
            "category":"Retail",
            "subcategory":"Self-service Laundry",
            "type":"Services"
        }
    ],
    "sg:phone":"+1 519 371 1501",
    "sg:postcode":"N4K 3B9",
    "sg:province":"ON",
    "wof:name":"Country Clean Laundry & Car",
    "wof:placetype":"venue"
},
  "geometry": {"coordinates":[-80.92865,44.574703],"type":"Point"}
}