{
  "type": "Feature",
  "properties": {
    "addr:full":"104 Boul Morin Sainte-Agathe-Des-Monts QC J8C 3K8",
    "addr:housenumber":"104",
    "addr:postcode":"j8c 3k8",
    "addr:street":"Boul Morin",
    "iso:country":"CA",
    "sg:address":"104 Boul Morin",
    "sg:city":"Sainte-Agathe-Des-Monts",
    "sg:classifiers":[
        {
            "category":"Food & Beverages",
            "subcategory":"Liquor & Beverages",
            "type":"Retail Goods"
        }
    ],
    "sg:phone":"+1 819 326 9459",
    "sg:postcode":"J8C 3K8",
    "sg:province":"QC",
    "sg:tags":[
        "beer",
        "ale"
    ],
    "wof:name":"A LA Biere Fontaine",
    "wof:placetype":"venue"
},
  "geometry": {"coordinates":[-74.283463,46.047409],"type":"Point"}
}