{
  "type": "Feature",
  "properties": {
    "addr:full":"1902 Janzen Cres Regina SK S4V 2H8",
    "addr:housenumber":"1902",
    "addr:postcode":"s4v 2h8",
    "addr:street":"Janzen Cres",
    "iso:country":"CA",
    "sg:address":"1902 Janzen Cres",
    "sg:city":"Regina",
    "sg:classifiers":[
        {
            "category":"Building & Trades",
            "subcategory":"Plumbing",
            "type":"Services"
        }
    ],
    "sg:phone":"+1 306 789 1727",
    "sg:postcode":"S4V 2H8",
    "sg:province":"SK",
    "sg:tags":[
        "conditioning",
        "contractor",
        "system",
        "air"
    ],
    "wof:name":"Porter Mechanical Svc Ltd",
    "wof:placetype":"venue"
},
  "geometry": {"coordinates":[-104.555786133,50.4227523804],"type":"Point"}
}