{
  "type": "Feature",
  "properties": {
    "addr:full":"633 Edgeley Blvd Concord ON L4K 4H6",
    "addr:housenumber":"633",
    "addr:postcode":"l4k 4h6",
    "addr:street":"Edgeley Blvd",
    "iso:country":"CA",
    "sg:address":"633 Edgeley Blvd",
    "sg:city":"Concord",
    "sg:classifiers":[
        {
            "category":"Building & Trades",
            "subcategory":"Plumbing",
            "type":"Services"
        }
    ],
    "sg:phone":"+1 905 738 0569",
    "sg:postcode":"L4K 4H6",
    "sg:province":"ON",
    "sg:tags":[
        "mechanical",
        "contractor"
    ],
    "wof:name":"D Zentil Mechanical Ltd",
    "wof:placetype":"venue"
},
  "geometry": {"coordinates":[-79.5367965698,43.8089256287],"type":"Point"}
}