{
  "type": "Feature",
  "properties": {
    "addr:full":"2319 Keele St North York ON M6M 4A1",
    "addr:housenumber":"2319",
    "addr:postcode":"m6m 4a1",
    "addr:street":"Keele St",
    "iso:country":"CA",
    "sg:address":"2319 Keele St",
    "sg:city":"North York",
    "sg:classifiers":[
        {
            "category":"Autos & Motor Vehicles",
            "subcategory":"Automobile Sales",
            "type":"Retail Goods"
        }
    ],
    "sg:phone":"+1 416 243 1550",
    "sg:postcode":"M6M 4A1",
    "sg:province":"ON",
    "sg:tags":[
        "car",
        "dealer"
    ],
    "wof:name":"Dave Nicholls Toyota",
    "wof:placetype":"venue"
},
  "geometry": {"coordinates":[-79.47695899999999,43.704811],"type":"Point"}
}