{
  "type": "Feature",
  "properties": {
    "addr:full":"Warwick QC J0A 1M0",
    "addr:postcode":"j0a 1m0",
    "iso:country":"CA",
    "sg:city":"Warwick",
    "sg:classifiers":[
        {
            "category":"Building & Trades",
            "subcategory":"Plumbing",
            "type":"Services"
        }
    ],
    "sg:phone":"+1 819 358 5323",
    "sg:postcode":"J0A 1M0",
    "sg:province":"QC",
    "sg:tags":[
        "contractor"
    ],
    "wof:name":"Plomberie Martel Inc",
    "wof:placetype":"venue"
},
  "geometry": {"coordinates":[-71.985992,45.949791],"type":"Point"}
}