{
  "type": "Feature",
  "properties": {
    "addr:full":"Bowmanville ON L1C 3K7",
    "addr:postcode":"l1c 3k7",
    "iso:country":"CA",
    "sg:city":"Bowmanville",
    "sg:classifiers":[
        {
            "category":"Building & Trades",
            "subcategory":"Construction",
            "type":"Services"
        }
    ],
    "sg:phone":"+1 905 623 5562",
    "sg:postcode":"L1C 3K7",
    "sg:province":"ON",
    "sg:tags":[
        "excavating",
        "contractor"
    ],
    "wof:name":"Robinson & Quinney Ltd",
    "wof:placetype":"venue"
},
  "geometry": {"coordinates":[-78.6884765625,43.9138336182],"type":"Point"}
}