{
  "type": "Feature",
  "properties": {
    "addr:full":"Evain QC J0Z 1Y0",
    "addr:postcode":"j0z 1y0",
    "iso:country":"CA",
    "sg:city":"Evain",
    "sg:classifiers":[
        {
            "category":"Food & Beverages",
            "subcategory":"Groceries & Convenience Stores",
            "type":"Retail Goods"
        }
    ],
    "sg:phone":"+1 819 768 2954",
    "sg:postcode":"J0Z 1Y0",
    "sg:province":"QC",
    "sg:tags":[
        "grocer"
    ],
    "wof:name":"Depanneur Chez Gibb Inc",
    "wof:placetype":"venue"
},
  "geometry": {"coordinates":[-79.230698,48.322769],"type":"Point"}
}