{
  "type": "Feature",
  "properties": {
    "addr:full":"2929 Dufferin St North York ON M6B 3S7",
    "addr:housenumber":"2929",
    "addr:postcode":"m6b 3s7",
    "addr:street":"Dufferin St",
    "iso:country":"CA",
    "sg:address":"2929 Dufferin St",
    "sg:city":"North York",
    "sg:classifiers":[
        {
            "category":"Wholesale",
            "subcategory":"Seafood",
            "type":"Manufacturing & Wholesale Goods"
        }
    ],
    "sg:phone":"+1 416 256 7373",
    "sg:postcode":"M6B 3S7",
    "sg:province":"ON",
    "wof:name":"City Fish Market",
    "wof:placetype":"venue"
},
  "geometry": {"coordinates":[-79.45355987550001,43.7091445923],"type":"Point"}
}