{
  "type": "Feature",
  "properties": {
    "iso:country":"CA",
    "sg:address":"PO Box 120",
    "sg:city":"Fort Vermilion",
    "sg:classifiers":[
        {
            "category":"Education",
            "subcategory":"School",
            "type":"Public Place"
        }
    ],
    "sg:phone":"+1 780 759 3772",
    "sg:postcode":"T0H 1N0",
    "sg:province":"AB",
    "wof:name":"Jean D'Or Prairie School",
    "wof:placetype":"venue"
},
  "geometry": {"coordinates":[-110.858520508,53.3516693115],"type":"Point"}
}