{
  "type": "Feature",
  "properties": {
    "addr:full":"64 Victoria St W Alliston ON L9R 1S6",
    "addr:housenumber":"64",
    "addr:postcode":"l9r 1s6",
    "addr:street":"Victoria St W Alliston",
    "iso:country":"CA",
    "sg:address":"64 Victoria St W",
    "sg:city":"Alliston",
    "sg:classifiers":[
        {
            "category":"Shopping",
            "subcategory":"Musical Instruments",
            "type":"Retail Goods"
        }
    ],
    "sg:phone":"+1 705 434 2222",
    "sg:postcode":"L9R 1S6",
    "sg:province":"ON",
    "wof:name":"Music Mania",
    "wof:placetype":"venue"
},
  "geometry": {"coordinates":[-79.8713607788,44.15366745],"type":"Point"}
}