{
  "type": "Feature",
  "properties": {
    "addr:full":"217 Bow St Cochrane AB T4C 2B9",
    "addr:housenumber":"217",
    "addr:postcode":"t4c 2b9",
    "addr:street":"Bow St",
    "iso:country":"CA",
    "sg:address":"217 Bow St",
    "sg:city":"Cochrane",
    "sg:classifiers":[
        {
            "category":"Home & Garden",
            "subcategory":"Garden Supply",
            "type":"Retail Goods"
        }
    ],
    "sg:phone":"+1 403 932 3230",
    "sg:postcode":"T4C 2B9",
    "sg:province":"AB",
    "sg:tags":[
        "engine",
        "gas"
    ],
    "wof:name":"Fairbanks Morse Engine Div",
    "wof:placetype":"venue"
},
  "geometry": {"coordinates":[-114.465706,51.185638],"type":"Point"}
}