{
  "type": "Feature",
  "properties": {
    "addr:full":"2025 Ch DE Saint-Jean LA Prairie QC J5R 3X8",
    "addr:postcode":"2025;j5r 3x8",
    "addr:street":"Ch De Saint-Jean",
    "iso:country":"CA",
    "sg:address":"2025 Ch DE Saint-Jean",
    "sg:city":"LA Prairie",
    "sg:classifiers":[
        {
            "category":"Building & Trades",
            "subcategory":"Construction",
            "type":"Services"
        }
    ],
    "sg:phone":"+1 450 444 4777",
    "sg:postcode":"J5R 3X8",
    "sg:province":"QC",
    "sg:tags":[
        "excavating",
        "contractor"
    ],
    "wof:name":"R Langlois Construction",
    "wof:placetype":"venue"
},
  "geometry": {"coordinates":[-73.46662902830001,45.4063186646],"type":"Point"}
}