{
  "type": "Feature",
  "properties": {
    "iso:country":"CA",
    "sg:city":"Waterloo",
    "sg:classifiers":[
        {
            "category":"Retail",
            "subcategory":"Portrait Studio",
            "type":"Services"
        }
    ],
    "sg:phone":"+1 519 746 0026",
    "sg:postcode":"N2J 2Y8",
    "sg:province":"ON",
    "sg:tags":[
        "photo",
        "finishing"
    ],
    "wof:name":"Snappy Photo & Copy Inc",
    "wof:placetype":"venue"
},
  "geometry": {"coordinates":[-80.52523040769999,43.4764328003],"type":"Point"}
}