{
  "type": "Feature",
  "properties": {
    "iso:country":"CA",
    "sg:address":"168 Copernicus Blvd",
    "sg:city":"Brantford",
    "sg:classifiers":[
        {
            "category":"Manufacturing",
            "subcategory":"Tools & Machinery",
            "type":"Manufacturing & Wholesale Goods"
        }
    ],
    "sg:phone":"+1 519 759 4780",
    "sg:postcode":"N3P 1Y5",
    "sg:province":"ON",
    "sg:tags":[
        "machine",
        "shop",
        "designer"
    ],
    "wof:name":"R & F Precision Tool Inc",
    "wof:placetype":"venue"
},
  "geometry": {"coordinates":[-80.2349777222,43.1784133911],"type":"Point"}
}