{
  "type": "Feature",
  "properties": {
    "iso:country":"CA",
    "sg:city":"Winnipeg",
    "sg:classifiers":[
        {
            "category":"Real Estate",
            "subcategory":"Real Estate Operator",
            "type":"Services"
        }
    ],
    "sg:phone":"+1 204 947 9732",
    "sg:postcode":"R3C 4H1",
    "sg:province":"MB",
    "sg:tags":[
        "apartment"
    ],
    "wof:name":"Rideau Towers",
    "wof:placetype":"venue"
},
  "geometry": {"coordinates":[-97.1375427246,49.8877487183],"type":"Point"}
}