{
  "type": "Feature",
  "properties": {
    "addr:full":"1854 Queen St E Toronto ON M4L 1H1",
    "addr:housenumber":"1854",
    "addr:postcode":"m4l 1h1",
    "addr:street":"Queen St E",
    "iso:country":"CA",
    "sg:address":"1854 Queen St E",
    "sg:city":"Toronto",
    "sg:classifiers":[
        {
            "category":"Shopping",
            "subcategory":"Used Merchandise",
            "type":"Retail Goods"
        }
    ],
    "sg:phone":"+1 416 699 9611",
    "sg:postcode":"M4L 1H1",
    "sg:province":"ON",
    "sg:tags":[
        "antique"
    ],
    "wof:name":"Sticks & Stones Antiques",
    "wof:placetype":"venue"
},
  "geometry": {"coordinates":[-79.307419,43.668533],"type":"Point"}
}