{
  "type": "Feature",
  "properties": {
    "addr:full":"55 Brunetville Rd Kapuskasing ON P5N 2E8",
    "addr:housenumber":"55",
    "addr:postcode":"p5n 2e8",
    "addr:street":"Brunetville Rd",
    "iso:country":"CA",
    "sg:address":"55 Brunetville Rd",
    "sg:city":"Kapuskasing",
    "sg:classifiers":[
        {
            "category":"Shopping",
            "subcategory":"Pharmacy",
            "type":"Retail Goods"
        }
    ],
    "sg:phone":"+1 705 337 4920",
    "sg:postcode":"P5N 2E8",
    "sg:province":"ON",
    "wof:name":"Drug Store Pharmacy",
    "wof:placetype":"venue"
},
  "geometry": {"coordinates":[-82.416473,49.4203],"type":"Point"}
}