{
  "type": "Feature",
  "properties": {
    "addr:full":"RR 1 New Sarepta AB T0B 3M0",
    "addr:postcode":"t0b 3m0",
    "addr:street":"Rr 1",
    "iso:country":"CA",
    "sg:address":"RR 1",
    "sg:city":"New Sarepta",
    "sg:classifiers":[
        {
            "category":"Mining & Drilling",
            "type":"Manufacturing & Wholesale Goods"
        }
    ],
    "sg:phone":"+1 780 941 3915",
    "sg:postcode":"T0B 3M0",
    "sg:province":"AB",
    "sg:tags":[
        "company",
        "oil"
    ],
    "wof:name":"Canadian Natural Resources Ltd",
    "wof:placetype":"venue"
},
  "geometry": {"coordinates":[-113.14743,53.278919],"type":"Point"}
}