{
  "type": "Feature",
  "properties": {
    "addr:full":"3960 Rue Belanger Montreal QC H1X 1B7",
    "addr:housenumber":"3960",
    "addr:postcode":"h1x 1b7",
    "addr:street":"Rue Belanger",
    "iso:country":"CA",
    "sg:address":"3960 Rue Belanger",
    "sg:city":"Montreal",
    "sg:classifiers":[
        {
            "category":"Wholesale",
            "subcategory":"Furniture",
            "type":"Manufacturing & Wholesale Goods"
        }
    ],
    "sg:phone":"+1 514 374 2550",
    "sg:postcode":"H1X 1B7",
    "sg:province":"QC",
    "wof:name":"Vente Magor",
    "wof:placetype":"venue"
},
  "geometry": {"coordinates":[-73.587273,45.56501],"type":"Point"}
}