{
  "type": "Feature",
  "properties": {
    "addr:full":"153 E 5th Ave Regina SK S4N 0A8",
    "addr:housenumber":"153",
    "addr:postcode":"s4n 0a8",
    "addr:street":"E 5Th Ave",
    "iso:country":"CA",
    "sg:address":"153 E 5th Ave",
    "sg:city":"Regina",
    "sg:classifiers":[
        {
            "category":"Utilities",
            "type":"Services"
        }
    ],
    "sg:phone":"+1 306 569 9041",
    "sg:postcode":"S4N 0A8",
    "sg:province":"SK",
    "sg:tags":[
        "contractor"
    ],
    "wof:name":"Fer-Marc Equipment Ltd",
    "wof:placetype":"venue"
},
  "geometry": {"coordinates":[-104.581444,50.461262],"type":"Point"}
}