{
  "type": "Feature",
  "properties": {
    "addr:full":"395 Josephine St Wingham ON N0G 2W0",
    "addr:housenumber":"395",
    "addr:postcode":"n0g 2w0",
    "addr:street":"Josephine St",
    "iso:country":"CA",
    "sg:address":"395 Josephine St",
    "sg:city":"Wingham",
    "sg:classifiers":[
        {
            "category":"Health Services",
            "subcategory":"Doctor",
            "type":"Services"
        }
    ],
    "sg:phone":"+1 519 357 2555",
    "sg:postcode":"N0G 2W0",
    "sg:province":"ON",
    "sg:tags":[
        "dentist"
    ],
    "wof:name":"Hall, D J DDS",
    "wof:placetype":"venue"
},
  "geometry": {"coordinates":[-81.309853,43.889896],"type":"Point"}
}