{
  "type": "Feature",
  "properties": {
    "addr:full":"1337 Marine Dr West Vancouver BC V7T 1B6",
    "addr:housenumber":"1337",
    "addr:postcode":"v7t 1b6",
    "addr:street":"Marine Dr",
    "iso:country":"CA",
    "sg:address":"1337 Marine Dr",
    "sg:city":"West Vancouver",
    "sg:classifiers":[
        {
            "category":"Restaurant",
            "type":"Food & Drink"
        }
    ],
    "sg:phone":"+1 604 926 7781",
    "sg:postcode":"V7T 1B6",
    "sg:province":"BC",
    "wof:name":"Taso's Pizza Steak & Seafood",
    "wof:placetype":"venue"
},
  "geometry": {"coordinates":[-123.152687073,49.3278503418],"type":"Point"}
}