{
  "type": "Feature",
  "properties": {
    "addr:full":"117 Main St Harris SK S0L 1K0",
    "addr:housenumber":"117",
    "addr:postcode":"s0l 1k0",
    "addr:street":"Main St",
    "iso:country":"CA",
    "sg:address":"117 Main St",
    "sg:city":"Harris",
    "sg:classifiers":[
        {
            "category":"Shopping",
            "subcategory":"Gifts & Souvenirs",
            "type":"Retail Goods"
        }
    ],
    "sg:phone":"+1 306 656 2155",
    "sg:postcode":"S0L 1K0",
    "sg:province":"SK",
    "sg:tags":[
        "shop"
    ],
    "wof:name":"Rex Variety Store",
    "wof:placetype":"venue"
},
  "geometry": {"coordinates":[-107.583504,51.736183],"type":"Point"}
}