{
  "type": "Feature",
  "properties": {
    "addr:full":"Hwy 748 Edson AB T7E 1V9",
    "addr:postcode":"t7e 1v9",
    "addr:street":"Hwy 748",
    "iso:country":"CA",
    "sg:address":"Hwy 748",
    "sg:city":"Edson",
    "sg:classifiers":[
        {
            "category":"Mining & Drilling",
            "type":"Manufacturing & Wholesale Goods"
        }
    ],
    "sg:phone":"+1 780 723 0511",
    "sg:postcode":"T7E 1V9",
    "sg:province":"AB",
    "sg:tags":[
        "hot",
        "shot"
    ],
    "wof:name":"Bubba's Contracting Ltd",
    "wof:placetype":"venue"
},
  "geometry": {"coordinates":[-116.43409729,53.5821304321],"type":"Point"}
}