{
  "type": "Feature",
  "properties": {
    "addr:full":"285 Rue DE Tunis Terrebonne QC J6Y 1E5",
    "addr:housenumber":"285",
    "addr:postcode":"j6y 1e5",
    "addr:street":"Rue De Tunis",
    "iso:country":"CA",
    "sg:address":"285 Rue DE Tunis",
    "sg:city":"Terrebonne",
    "sg:classifiers":[
        {
            "category":"Building & Trades",
            "subcategory":"Plumbing",
            "type":"Services"
        }
    ],
    "sg:phone":"+1 450 471 6748",
    "sg:postcode":"J6Y 1E5",
    "sg:province":"QC",
    "sg:tags":[
        "contractor"
    ],
    "wof:name":"Plomberie & Chauffage Maurice",
    "wof:placetype":"venue"
},
  "geometry": {"coordinates":[-73.669083,45.696213],"type":"Point"}
}