{
  "type": "Feature",
  "properties": {
    "addr:full":"15 Paisley St Guelph ON N1H 2N5",
    "addr:housenumber":"15",
    "addr:postcode":"n1h 2n5",
    "addr:street":"Paisley St",
    "iso:country":"CA",
    "sg:address":"15 Paisley St",
    "sg:city":"Guelph",
    "sg:classifiers":[
        {
            "category":"Health Services",
            "subcategory":"Medical Lab",
            "type":"Services"
        }
    ],
    "sg:phone":"+1 519 767 9691",
    "sg:postcode":"N1H 2N5",
    "sg:province":"ON",
    "wof:name":"Guelph Denture Clinic",
    "wof:placetype":"venue"
},
  "geometry": {"coordinates":[-80.2533340454,43.5453262329],"type":"Point"}
}