{
  "type": "Feature",
  "properties": {
    "addr:full":"18 Nelson St E Goderich ON N7A 1R6",
    "addr:housenumber":"18",
    "addr:postcode":"n7a 1r6",
    "addr:street":"Nelson St E",
    "iso:country":"CA",
    "sg:address":"18 Nelson St E",
    "sg:city":"Goderich",
    "sg:classifiers":[
        {
            "category":"Shopping",
            "type":"Retail Goods"
        }
    ],
    "sg:phone":"+1 519 524 9442",
    "sg:postcode":"N7A 1R6",
    "sg:province":"ON",
    "sg:tags":[
        "art",
        "gallery",
        "dealer"
    ],
    "wof:name":"Serrenwood Art Studio Gallery",
    "wof:placetype":"venue"
},
  "geometry": {"coordinates":[-81.710487,43.745411],"type":"Point"}
}