{
  "type": "Feature",
  "properties": {
    "addr:full":"1185 Av Bernard Outremont QC H2V 1V5",
    "addr:housenumber":"1185",
    "addr:postcode":"h2v 1v5",
    "addr:street":"Av Bernard",
    "iso:country":"CA",
    "sg:address":"1185 Av Bernard",
    "sg:city":"Outremont",
    "sg:classifiers":[
        {
            "category":"Personal",
            "subcategory":"Beauty Salon",
            "type":"Services"
        }
    ],
    "sg:phone":"+1 514 274 3304",
    "sg:postcode":"H2V 1V5",
    "sg:province":"QC",
    "wof:name":"Alvaro Coiffure",
    "wof:placetype":"venue"
},
  "geometry": {"coordinates":[-73.60832214360001,45.5208206177],"type":"Point"}
}