{
  "type": "Feature",
  "properties": {
    "addr:full":"1050 Hargrieve Rd # 9 London ON N6E 1P5",
    "addr:housenumber":"1050",
    "addr:postcode":"n6e 1p5",
    "addr:street":"Hargrieve Rd # 9",
    "iso:country":"CA",
    "sg:address":"1050 Hargrieve Rd # 9",
    "sg:city":"London",
    "sg:classifiers":[
        {
            "category":"Wholesale",
            "subcategory":"Hardware",
            "type":"Manufacturing & Wholesale Goods"
        }
    ],
    "sg:phone":"+1 519 685 5554",
    "sg:postcode":"N6E 1P5",
    "sg:province":"ON",
    "sg:tags":[
        "system",
        "air",
        "parts",
        "conditioning",
        "contractor",
        "refrigerating"
    ],
    "wof:name":"Fortress Group",
    "wof:placetype":"venue"
},
  "geometry": {"coordinates":[-81.2149276733,42.929901123],"type":"Point"}
}