{
  "type": "Feature",
  "properties": {
    "addr:full":"3500 Fallowfield Rd # 4 Nepean ON K2J 4A7",
    "addr:housenumber":"3500",
    "addr:postcode":"k2j 4a7",
    "addr:street":"Fallowfield Rd # 4",
    "iso:country":"CA",
    "sg:address":"3500 Fallowfield Rd # 4",
    "sg:city":"Nepean",
    "sg:classifiers":[
        {
            "category":"Retail",
            "subcategory":"Animal Services",
            "type":"Services"
        }
    ],
    "sg:phone":"+1 613 825 7915",
    "sg:postcode":"K2J 4A7",
    "sg:province":"ON",
    "sg:tags":[
        "pet",
        "grooming",
        "washing"
    ],
    "wof:name":"Groomingdale's",
    "wof:placetype":"venue"
},
  "geometry": {"coordinates":[-75.7423248291,45.2939758301],"type":"Point"}
}