{
  "type": "Feature",
  "properties": {
    "addr:full":"1868 Boul Des Sources #3181 Pointe-Claire QC H9R 5R2",
    "addr:housenumber":"1868",
    "addr:postcode":"h9r 5r2",
    "addr:street":"Boul Des Sources # 3181",
    "iso:country":"CA",
    "sg:address":"1868 Boul Des Sources #3181",
    "sg:city":"Pointe-Claire",
    "sg:classifiers":[
        {
            "category":"Wholesale",
            "subcategory":"Electrical",
            "type":"Manufacturing & Wholesale Goods"
        }
    ],
    "sg:phone":"+1 514 426 1212",
    "sg:postcode":"H9R 5R2",
    "sg:province":"QC",
    "sg:tags":[
        "equipment",
        "electronic",
        "supply"
    ],
    "wof:name":"Tti Inc",
    "wof:placetype":"venue"
},
  "geometry": {"coordinates":[-73.78764343260001,45.466506958],"type":"Point"}
}