{
  "type": "Feature",
  "properties": {
    "addr:full":"253 Reid St Quesnel BC V2J 2M1",
    "addr:housenumber":"253",
    "addr:postcode":"v2j 2m1",
    "addr:street":"Reid St",
    "iso:country":"CA",
    "sg:address":"253 Reid St",
    "sg:city":"Quesnel",
    "sg:classifiers":[
        {
            "category":"Banks & Credit Unions",
            "subcategory":"Bank",
            "type":"Services"
        }
    ],
    "sg:phone":"+1 250 992 9216",
    "sg:postcode":"V2J 2M1",
    "sg:province":"BC",
    "wof:name":"Quesnel & District Crdt Union",
    "wof:placetype":"venue"
},
  "geometry": {"coordinates":[-122.496780395,52.9766044617],"type":"Point"}
}