{
  "type": "Feature",
  "properties": {
    "addr:full":"2320 Rue DE LA Metropole Longueuil QC J4G 1E6",
    "addr:housenumber":"2320",
    "addr:postcode":"j4g 1e6",
    "addr:street":"Rue De La Metropole",
    "iso:country":"CA",
    "sg:address":"2320 Rue DE LA Metropole",
    "sg:city":"Longueuil",
    "sg:classifiers":[
        {
            "category":"Wholesale",
            "subcategory":"Stationery",
            "type":"Manufacturing & Wholesale Goods"
        }
    ],
    "sg:phone":"+1 450 651 2480",
    "sg:postcode":"J4G 1E6",
    "sg:province":"QC",
    "sg:tags":[
        "packaging",
        "material"
    ],
    "wof:name":"Papier International Du Canada",
    "wof:placetype":"venue"
},
  "geometry": {"coordinates":[-73.4716873169,45.5722541809],"type":"Point"}
}