{
  "type": "Feature",
  "properties": {
    "addr:full":"103 Tamarack Hudson Bay SK S0E 0Y0",
    "addr:housenumber":"103",
    "addr:postcode":"s0e 0y0",
    "addr:street":"Tamarack Hudson Bay",
    "iso:country":"CA",
    "sg:address":"103 Tamarack",
    "sg:city":"Hudson Bay",
    "sg:classifiers":[
        {
            "category":"Retail",
            "subcategory":"Auto Repair",
            "type":"Services"
        }
    ],
    "sg:phone":"+1 306 865 2612",
    "sg:postcode":"S0E 0Y0",
    "sg:province":"SK",
    "sg:tags":[
        "wrecker"
    ],
    "wof:name":"Nick's Auto Body & Towing",
    "wof:placetype":"venue"
},
  "geometry": {"coordinates":[-102.38885498,52.8626594543],"type":"Point"}
}