{
  "type": "Feature",
  "properties": {
    "addr:full":"424 Rue Saint-Georges Saint-Jerome QC J7Z 5B1",
    "addr:housenumber":"424",
    "addr:postcode":"j7z 5b1",
    "addr:street":"Rue Saint-Georges Saint-Jerome",
    "iso:country":"CA",
    "sg:address":"424 Rue Saint-Georges",
    "sg:city":"Saint-Jerome",
    "sg:classifiers":[
        {
            "category":"Building & Trades",
            "subcategory":"Construction",
            "type":"Services"
        }
    ],
    "sg:phone":"+1 450 569 2629",
    "sg:postcode":"J7Z 5B1",
    "sg:province":"QC",
    "sg:tags":[
        "steel",
        "drafting"
    ],
    "wof:name":"Techdess Inc",
    "wof:placetype":"venue"
},
  "geometry": {"coordinates":[-74.0026168823,45.7793006897],"type":"Point"}
}