{
  "type": "Feature",
  "properties": {
    "iso:country":"CA",
    "sg:city":"Scarborough",
    "sg:classifiers":[
        {
            "category":"Health Services",
            "subcategory":"Chiropractor",
            "type":"Services"
        }
    ],
    "sg:phone":"+1 416 698 1844",
    "sg:postcode":"M1N 4E4",
    "sg:province":"ON",
    "wof:name":"Galiotos, Steven DC",
    "wof:placetype":"venue"
},
  "geometry": {"coordinates":[-79.2825088501,43.6809844971],"type":"Point"}
}