{
  "type": "Feature",
  "properties": {
    "iso:country":"CA",
    "sg:address":"424 Av Ross",
    "sg:city":"Rimouski",
    "sg:classifiers":[
        {
            "category":"Restaurant",
            "type":"Food & Drink"
        }
    ],
    "sg:phone":"+1 418 722 9288",
    "sg:postcode":"G5L 6J2",
    "sg:province":"QC",
    "wof:name":"Cuisines Pentagruel",
    "wof:placetype":"venue"
},
  "geometry": {"coordinates":[-68.52471160890001,48.432144165],"type":"Point"}
}