{
  "type": "Feature",
  "properties": {
    "addr:full":"PO Box 149 Cremona AB T0M 0R0",
    "addr:housenumber":"po",
    "addr:postcode":"t0m 0r0",
    "addr:street":"Box 149",
    "iso:country":"CA",
    "sg:address":"PO Box 149",
    "sg:city":"Cremona",
    "sg:classifiers":[
        {
            "category":"Wholesale",
            "subcategory":"Construction Materials",
            "type":"Manufacturing & Wholesale Goods"
        }
    ],
    "sg:phone":"+1 403 637 3754",
    "sg:postcode":"T0M 0R0",
    "sg:province":"AB",
    "sg:tags":[
        "sand",
        "gravel"
    ],
    "wof:name":"Boyd Oborne Sand & Gravel",
    "wof:placetype":"venue"
},
  "geometry": {"coordinates":[-114.494499,51.545464],"type":"Point"}
}