{
  "type": "Feature",
  "properties": {
    "addr:full":"Stonewall MB R0C 2Z0",
    "addr:postcode":"r0c 2z0",
    "iso:country":"CA",
    "sg:city":"Stonewall",
    "sg:classifiers":[
        {
            "category":"Building & Trades",
            "subcategory":"Construction",
            "type":"Services"
        }
    ],
    "sg:phone":"+1 204 467 8454",
    "sg:postcode":"R0C 2Z0",
    "sg:province":"MB",
    "sg:tags":[
        "maker",
        "cabinet"
    ],
    "wof:name":"R & R Woodworking Ltd",
    "wof:placetype":"venue"
},
  "geometry": {"coordinates":[-97.322395,50.137653],"type":"Point"}
}