{
  "type": "Feature",
  "properties": {
    "addr:full":"525 Wellington St E Sault Ste Marie ON P6A 2M4",
    "addr:housenumber":"525",
    "addr:postcode":"p6a 2m4",
    "addr:street":"Wellington St E",
    "iso:country":"CA",
    "sg:address":"525 Wellington St E",
    "sg:city":"Sault Ste Marie",
    "sg:classifiers":[
        {
            "category":"Professional",
            "subcategory":"Lawyer & Legal Services",
            "type":"Services"
        }
    ],
    "sg:phone":"+1 705 256 7839",
    "sg:postcode":"P6A 2M4",
    "sg:province":"ON",
    "sg:tags":[
        "attorney"
    ],
    "wof:name":"Davies, Kenneth R",
    "wof:placetype":"venue"
},
  "geometry": {"coordinates":[-84.3276748657,46.5112380981],"type":"Point"}
}