{
  "type": "Feature",
  "properties": {
    "addr:full":"106 Front St Trenton ON K8V 4N7",
    "addr:housenumber":"106",
    "addr:postcode":"k8v 4n7",
    "addr:street":"Front St",
    "iso:country":"CA",
    "sg:address":"106 Front St",
    "sg:city":"Trenton",
    "sg:classifiers":[
        {
            "category":"Retail",
            "subcategory":"Auto Rental",
            "type":"Services"
        }
    ],
    "sg:phone":"+1 613 392 3300",
    "sg:postcode":"K8V 4N7",
    "sg:province":"ON",
    "sg:tags":[
        "renting",
        "automobile"
    ],
    "wof:name":"National Car Rental",
    "wof:placetype":"venue"
},
  "geometry": {"coordinates":[-77.5779342651,44.1032447815],"type":"Point"}
}