{
  "type": "Feature",
  "properties": {
    "addr:full":"395 7th St W Shaunavon SK S0N 2M0",
    "addr:housenumber":"395",
    "addr:postcode":"s0n 2m0",
    "addr:street":"7Th St W Shaunavon",
    "iso:country":"CA",
    "sg:address":"395 7th St W",
    "sg:city":"Shaunavon",
    "sg:classifiers":[
        {
            "category":"Shopping",
            "type":"Retail Goods"
        }
    ],
    "sg:phone":"+1 306 297 2776",
    "sg:postcode":"S0N 2M0",
    "sg:province":"SK",
    "sg:tags":[
        "wedding",
        "supply"
    ],
    "wof:name":"Cypress Hills Ability Ctr",
    "wof:placetype":"venue"
},
  "geometry": {"coordinates":[-108.416321,49.642616],"type":"Point"}
}