{
  "type": "Feature",
  "properties": {
    "iso:country":"CA",
    "sg:address":"6894 Regional Rd 14 RR 1",
    "sg:city":"Smithville",
    "sg:classifiers":[
        {
            "category":"Recreation",
            "type":"Entertainment"
        }
    ],
    "sg:phone":"+1 905 957 5268",
    "sg:postcode":"L0R 2A0",
    "sg:province":"ON",
    "sg:tags":[
        "riding",
        "academy"
    ],
    "wof:name":"Windcrest School of Riding",
    "wof:placetype":"venue"
},
  "geometry": {"coordinates":[-79.54889678959999,43.0939216614],"type":"Point"}
}