{
  "type": "Feature",
  "properties": {
    "addr:full":"693 Atherley Rd Orillia ON L3V 1P4",
    "addr:housenumber":"693",
    "addr:postcode":"l3v 1p4",
    "addr:street":"Atherley Rd",
    "iso:country":"CA",
    "sg:address":"693 Atherley Rd",
    "sg:city":"Orillia",
    "sg:classifiers":[
        {
            "category":"Autos & Motor Vehicles",
            "subcategory":"Boat Sales",
            "type":"Retail Goods"
        }
    ],
    "sg:phone":"+1 705 325 2526",
    "sg:postcode":"L3V 1P4",
    "sg:province":"ON",
    "sg:tags":[
        "marina",
        "dealer"
    ],
    "wof:name":"Blue Beacon Marina",
    "wof:placetype":"venue"
},
  "geometry": {"coordinates":[-79.371711731,44.6040878296],"type":"Point"}
}