{
  "type": "Feature",
  "properties": {
    "addr:full":"275 Reaume Rd Windsor ON N9J 1B2",
    "addr:housenumber":"275",
    "addr:postcode":"n9j 1b2",
    "addr:street":"Reaume Rd",
    "iso:country":"CA",
    "sg:address":"275 Reaume Rd",
    "sg:city":"Windsor",
    "sg:classifiers":[
        {
            "category":"Building & Trades",
            "subcategory":"Plumbing",
            "type":"Services"
        }
    ],
    "sg:phone":"+1 519 734 7973",
    "sg:postcode":"N9J 1B2",
    "sg:province":"ON",
    "sg:tags":[
        "contractor"
    ],
    "wof:name":"Walt's Plumbing & Heating Ltd",
    "wof:placetype":"venue"
},
  "geometry": {"coordinates":[-83.033913,42.317822],"type":"Point"}
}