{
  "type": "Feature",
  "properties": {
    "addr:full":"4465 Boundary Rd Vancouver BC V5R 2N3",
    "addr:housenumber":"4465",
    "addr:postcode":"v5r 2n3",
    "addr:street":"Boundary Rd",
    "iso:country":"CA",
    "sg:address":"4465 Boundary Rd",
    "sg:city":"Vancouver",
    "sg:classifiers":[
        {
            "category":"Retail",
            "subcategory":"Laundry & Dry Cleaning",
            "type":"Services"
        }
    ],
    "sg:phone":"+1 604 433 5287",
    "sg:postcode":"V5R 2N3",
    "sg:province":"BC",
    "sg:tags":[
        "cleaners"
    ],
    "wof:name":"Boundary Place Cleaners",
    "wof:placetype":"venue"
},
  "geometry": {"coordinates":[-123.023933,49.245106],"type":"Point"}
}