{
  "type": "Feature",
  "properties": {
    "addr:full":"Kitchener ON N2M 5N4",
    "addr:postcode":"n2m 5n4",
    "iso:country":"CA",
    "sg:city":"Kitchener",
    "sg:classifiers":[
        {
            "category":"Retail",
            "subcategory":"Self-service Laundry",
            "type":"Services"
        }
    ],
    "sg:phone":"+1 519 745 2997",
    "sg:postcode":"N2M 5N4",
    "sg:province":"ON",
    "wof:name":"D J's Laundry Cafe",
    "wof:placetype":"venue"
},
  "geometry": {"coordinates":[-80.5224533081,43.438785553],"type":"Point"}
}