{
  "type": "Feature",
  "properties": {
    "iso:country":"CA",
    "sg:address":"3300 Yonge St",
    "sg:city":"Toronto",
    "sg:classifiers":[
        {
            "category":"Education",
            "subcategory":"School",
            "type":"Public Place"
        }
    ],
    "sg:phone":"+1 416 484 0454",
    "sg:postcode":"M4N 2L6",
    "sg:province":"ON",
    "wof:name":"Transformational Arts College",
    "wof:placetype":"venue"
},
  "geometry": {"coordinates":[-79.4038391113,43.730632782],"type":"Point"}
}