{
  "type": "Feature",
  "properties": {
    "iso:country":"CA",
    "sg:address":"RR 1",
    "sg:city":"Utterson",
    "sg:classifiers":[
        {
            "category":"Professional",
            "subcategory":"Computer Services",
            "type":"Services"
        }
    ],
    "sg:phone":"+1 705 385 2893",
    "sg:postcode":"P0B 1M0",
    "sg:province":"ON",
    "wof:name":"Compulynes",
    "wof:placetype":"venue"
},
  "geometry": {"coordinates":[-79.32786560060001,45.2110404968],"type":"Point"}
}