{
  "type": "Feature",
  "properties": {
    "addr:full":"698 Spadina Ave Toronto ON M5S 2J2",
    "addr:housenumber":"698",
    "addr:postcode":"m5s 2j2",
    "addr:street":"Spadina Ave",
    "iso:country":"CA",
    "sg:address":"698 Spadina Ave",
    "sg:city":"Toronto",
    "sg:classifiers":[
        {
            "category":"Shopping",
            "subcategory":"Used Merchandise",
            "type":"Retail Goods"
        }
    ],
    "sg:phone":"+1 416 964 3803",
    "sg:postcode":"M5S 2J2",
    "sg:province":"ON",
    "sg:tags":[
        "book",
        "rare",
        "dealer"
    ],
    "wof:name":"Ten Editions Books",
    "wof:placetype":"venue"
},
  "geometry": {"coordinates":[-79.4031219482,43.6648445129],"type":"Point"}
}