{
  "type": "Feature",
  "properties": {
    "addr:full":"46420 Brooks Ave Chilliwack BC V2P 1C5",
    "addr:housenumber":"46420",
    "addr:postcode":"v2p 1c5",
    "addr:street":"Brooks Ave",
    "iso:country":"CA",
    "sg:address":"46420 Brooks Ave",
    "sg:city":"Chilliwack",
    "sg:classifiers":[
        {
            "category":"Social Services",
            "subcategory":"Child Care",
            "type":"Services"
        }
    ],
    "sg:phone":"+1 604 792 5285",
    "sg:postcode":"V2P 1C5",
    "sg:province":"BC",
    "wof:name":"Happy Hearts Daycare",
    "wof:placetype":"venue"
},
  "geometry": {"coordinates":[-121.939278,49.158684],"type":"Point"}
}