{
  "type": "Feature",
  "properties": {
    "iso:country":"CA",
    "sg:address":"4400 29 St",
    "sg:city":"Vernon",
    "sg:classifiers":[
        {
            "category":"Building & Trades",
            "subcategory":"Construction",
            "type":"Services"
        }
    ],
    "sg:phone":"+1 250 549 4448",
    "sg:postcode":"V1T 5B8",
    "sg:province":"BC",
    "sg:tags":[
        "refinishing",
        "floor",
        "laying",
        "rug",
        "resurfacing",
        "dealer",
        "carpet"
    ],
    "wof:name":"Vernon's Carpet Castle",
    "wof:placetype":"venue"
},
  "geometry": {"coordinates":[-119.27021026600001,50.2769432068],"type":"Point"}
}