{
  "type": "Feature",
  "properties": {
    "addr:full":"Toronto ON M5V 3B5",
    "addr:postcode":"m5v 3b5",
    "iso:country":"CA",
    "sg:city":"Toronto",
    "sg:classifiers":[
        {
            "category":"Real Estate",
            "subcategory":"Real Estate Agent",
            "type":"Services"
        }
    ],
    "sg:phone":"+1 416 494 2050",
    "sg:postcode":"M5V 3B5",
    "sg:province":"ON",
    "sg:tags":[
        "appraiser"
    ],
    "wof:name":"American Appraisal CO",
    "wof:placetype":"venue"
},
  "geometry": {"coordinates":[-79.3901672363,43.6437454224],"type":"Point"}
}