{
  "type": "Feature",
  "properties": {
    "addr:full":"5021 Yonge St North York ON M2N 5P1",
    "addr:housenumber":"5021",
    "addr:postcode":"m2n 5p1",
    "addr:street":"Yonge St",
    "iso:country":"CA",
    "sg:address":"5021 Yonge St",
    "sg:city":"North York",
    "sg:classifiers":[
        {
            "category":"Restaurant",
            "type":"Food & Drink"
        }
    ],
    "sg:phone":"+1 416 221 8364",
    "sg:postcode":"M2N 5P1",
    "sg:province":"ON",
    "wof:name":"Hooraiya T Japanese Restaurant",
    "wof:placetype":"venue"
},
  "geometry": {"coordinates":[-79.4119720459,43.7663955688],"type":"Point"}
}