{
  "type": "Feature",
  "properties": {
    "addr:full":"4 Sharon Park Dr Mckellar ON P0G 1C0",
    "addr:housenumber":"4",
    "addr:postcode":"p0g 1c0",
    "addr:street":"Sharon Park Dr",
    "iso:country":"CA",
    "sg:address":"4 Sharon Park Dr",
    "sg:city":"Mckellar",
    "sg:classifiers":[
        {
            "category":"Manufacturing",
            "subcategory":"Tools & Machinery",
            "type":"Manufacturing & Wholesale Goods"
        }
    ],
    "sg:phone":"+1 705 389 2000",
    "sg:postcode":"P0G 1C0",
    "sg:province":"ON",
    "sg:tags":[
        "built",
        "designed"
    ],
    "wof:name":"Stroud Graphic Equipment Ltd",
    "wof:placetype":"venue"
},
  "geometry": {"coordinates":[-79.9237442017,45.5115127563],"type":"Point"}
}