{
  "type": "Feature",
  "properties": {
    "addr:full":"297 Rue Savoie Caraquet NB E1W 1A3",
    "addr:housenumber":"297",
    "addr:postcode":"e1w 1a3",
    "addr:street":"Rue Savoie",
    "iso:country":"CA",
    "sg:address":"297 Rue Savoie",
    "sg:city":"Caraquet",
    "sg:classifiers":[
        {
            "category":"Personal",
            "type":"Services"
        }
    ],
    "sg:phone":"+1 506 727 6099",
    "sg:postcode":"E1W 1A3",
    "sg:province":"NB",
    "sg:tags":[
        "therapist",
        "massage"
    ],
    "wof:name":"Clinique Massotherapie",
    "wof:placetype":"venue"
},
  "geometry": {"coordinates":[-64.97570800779999,47.7824516296],"type":"Point"}
}