{
  "type": "Feature",
  "properties": {
    "addr:full":"Clinton ON N0M 1L0",
    "addr:postcode":"n0m 1l0",
    "iso:country":"CA",
    "sg:city":"Clinton",
    "sg:classifiers":[
        {
            "category":"Freight",
            "type":"Transportation"
        }
    ],
    "sg:phone":"+1 519 233 7579",
    "sg:postcode":"N0M 1L0",
    "sg:province":"ON",
    "sg:tags":[
        "seed",
        "grain",
        "cleaning",
        "elevator"
    ],
    "wof:name":"Nott Farms",
    "wof:placetype":"venue"
},
  "geometry": {"coordinates":[-81.53969600000001,43.617668],"type":"Point"}
}