{
  "type": "Feature",
  "properties": {
    "addr:full":"Forrest Station MB R0K 0W0",
    "addr:postcode":"r0k 0w0",
    "iso:country":"CA",
    "sg:city":"Forrest Station",
    "sg:classifiers":[
        {
            "category":"Manufacturing",
            "subcategory":"Motor Vehicles & Parts",
            "type":"Manufacturing & Wholesale Goods"
        }
    ],
    "sg:phone":"+1 204 728 3597",
    "sg:postcode":"R0K 0W0",
    "sg:province":"MB",
    "sg:tags":[
        "trailer"
    ],
    "wof:name":"Blue Hills Trailer & Fabrctng",
    "wof:placetype":"venue"
},
  "geometry": {"coordinates":[-99.93547100000001,49.966995],"type":"Point"}
}