{
  "type": "Feature",
  "properties": {
    "addr:full":"2 Ontario St # 6 Marathon ON P0T 2E0",
    "addr:housenumber":"2",
    "addr:postcode":"p0t 2e0",
    "addr:street":"Ontario St # 6",
    "iso:country":"CA",
    "sg:address":"2 Ontario St # 6",
    "sg:city":"Marathon",
    "sg:classifiers":[
        {
            "category":"Restaurant",
            "type":"Food & Drink"
        }
    ],
    "sg:phone":"+1 807 229 3333",
    "sg:postcode":"P0T 2E0",
    "sg:province":"ON",
    "wof:name":"Pizza Hut",
    "wof:placetype":"venue"
},
  "geometry": {"coordinates":[-86.37973,48.718727],"type":"Point"}
}