{
  "type": "Feature",
  "properties": {
    "addr:full":"6865 Boul DE Maisonneuve O Montreal QC H4B 1T1",
    "addr:housenumber":"6865",
    "addr:postcode":"h4b 1t1",
    "addr:street":"Boul De Maisonneuve O",
    "iso:country":"CA",
    "sg:address":"6865 Boul DE Maisonneuve O",
    "sg:city":"Montreal",
    "sg:classifiers":[
        {
            "category":"Education",
            "subcategory":"School",
            "type":"Public Place"
        }
    ],
    "sg:phone":"+1 514 485 8565",
    "sg:postcode":"H4B 1T1",
    "sg:province":"QC",
    "wof:name":"Academie Kells Inc",
    "wof:placetype":"venue"
},
  "geometry": {"coordinates":[-73.630791,45.459766],"type":"Point"}
}