{
  "type": "Feature",
  "properties": {
    "addr:full":"10672 62 Ave NW Edmonton AB T6H 1M8",
    "addr:housenumber":"10672",
    "addr:postcode":"t6h 1m8",
    "addr:street":"62 Ave Nw",
    "iso:country":"CA",
    "sg:address":"10672 62 Ave NW",
    "sg:city":"Edmonton",
    "sg:classifiers":[
        {
            "category":"Organizations",
            "subcategory":"Religious Organization",
            "type":"Services"
        }
    ],
    "sg:phone":"+1 780 434 3703",
    "sg:postcode":"T6H 1M8",
    "sg:province":"AB",
    "sg:tags":[
        "church"
    ],
    "wof:name":"Pleasantview United Church",
    "wof:placetype":"venue"
},
  "geometry": {"coordinates":[-113.506332,53.499386],"type":"Point"}
}