{
  "type": "Feature",
  "properties": {
    "addr:full":"London ON N6L 1A4",
    "addr:postcode":"n6l 1a4",
    "iso:country":"CA",
    "sg:city":"London",
    "sg:classifiers":[
        {
            "category":"Manufacturing",
            "subcategory":"Food",
            "type":"Manufacturing & Wholesale Goods"
        }
    ],
    "sg:phone":"+1 519 652 1701",
    "sg:postcode":"N6L 1A4",
    "sg:province":"ON",
    "sg:tags":[
        "grocer",
        "product",
        "manufacturer"
    ],
    "wof:name":"Sakellis Quality Foods",
    "wof:placetype":"venue"
},
  "geometry": {"coordinates":[-81.26165008540001,42.9219360352],"type":"Point"}
}