{
  "type": "Feature",
  "properties": {
    "addr:full":"RR 2 STN Main Camrose AB T4V 2N1",
    "addr:postcode":"t4v 2n1",
    "addr:street":"Rr 2 Stn Main",
    "iso:country":"CA",
    "sg:address":"RR 2 STN Main",
    "sg:city":"Camrose",
    "sg:classifiers":[
        {
            "category":"Professional",
            "subcategory":"Business Services",
            "type":"Services"
        }
    ],
    "sg:phone":"+1 780 672 8478",
    "sg:postcode":"T4V 2N1",
    "sg:province":"AB",
    "sg:tags":[
        "auctioneer"
    ],
    "wof:name":"Lindstrand Auctions",
    "wof:placetype":"venue"
},
  "geometry": {"coordinates":[-112.829781,53.024235],"type":"Point"}
}