{
  "type": "Feature",
  "properties": {
    "iso:country":"CA",
    "sg:address":"23 Stardust Dr",
    "sg:city":"Dorchester",
    "sg:classifiers":[
        {
            "category":"Building & Trades",
            "subcategory":"Construction",
            "type":"Services"
        }
    ],
    "sg:phone":"+1 519 268 2017",
    "sg:postcode":"N0L 1G5",
    "sg:province":"ON",
    "sg:tags":[
        "excavating",
        "contractor"
    ],
    "wof:name":"Fine Grade Svc",
    "wof:placetype":"venue"
},
  "geometry": {"coordinates":[-81.0725021362,42.9617843628],"type":"Point"}
}