{
  "type": "Feature",
  "properties": {
    "addr:full":"3404 County Rd 36 S Bobcaygeon ON K0M 1A0",
    "addr:housenumber":"3404;36",
    "addr:postcode":"k0m 1a0",
    "addr:street":"County Rd;S Bobcaygeon",
    "iso:country":"CA",
    "sg:address":"3404 County Rd 36 S",
    "sg:city":"Bobcaygeon",
    "sg:classifiers":[
        {
            "category":"Travel",
            "subcategory":"Hotels & Motels",
            "type":"Entertainment"
        }
    ],
    "sg:phone":"+1 705 738 2313",
    "sg:postcode":"K0M 1A0",
    "sg:province":"ON",
    "sg:tags":[
        "resort",
        "tourist",
        "accommodation"
    ],
    "wof:name":"Three Islands Motel",
    "wof:placetype":"venue"
},
  "geometry": {"coordinates":[-78.53755187989999,44.5363006592],"type":"Point"}
}