{
  "type": "Feature",
  "properties": {
    "addr:full":"North Bay ON P1B 8G3",
    "addr:postcode":"p1b 8g3",
    "iso:country":"CA",
    "sg:city":"North Bay",
    "sg:classifiers":[
        {
            "category":"Wholesale",
            "subcategory":"Machinery & Supplies",
            "type":"Manufacturing & Wholesale Goods"
        }
    ],
    "sg:phone":"+1 705 472 2340",
    "sg:postcode":"P1B 8G3",
    "sg:province":"ON",
    "sg:tags":[
        "contractor"
    ],
    "wof:name":"Champion Road Machinery Sales",
    "wof:placetype":"venue"
},
  "geometry": {"coordinates":[-79.402199,46.276829],"type":"Point"}
}