{
  "type": "Feature",
  "properties": {
    "addr:full":"90 Rue Morgan Baie-D'Urfe QC H9X 3A8",
    "addr:housenumber":"90",
    "addr:postcode":"h9x 3a8",
    "addr:street":"Rue Morgan",
    "iso:country":"CA",
    "sg:address":"90 Rue Morgan",
    "sg:city":"Baie-D'Urfe",
    "sg:classifiers":[
        {
            "category":"Professional",
            "subcategory":"Advertising",
            "type":"Services"
        }
    ],
    "sg:phone":"+1 514 457 2321",
    "sg:postcode":"H9X 3A8",
    "sg:province":"QC",
    "sg:tags":[
        "grocer",
        "distribution"
    ],
    "wof:name":"Provigo Distribution Inc",
    "wof:placetype":"venue"
},
  "geometry": {"coordinates":[-73.087852,46.043037],"type":"Point"}
}