{
  "type": "Feature",
  "properties": {
    "addr:full":"Blind River ON P0R 1B0",
    "addr:postcode":"p0r 1b0",
    "iso:country":"CA",
    "sg:city":"Blind River",
    "sg:classifiers":[
        {
            "category":"Personal",
            "subcategory":"Beauty Salon",
            "type":"Services"
        }
    ],
    "sg:phone":"+1 705 356 1562",
    "sg:postcode":"P0R 1B0",
    "sg:province":"ON",
    "wof:name":"Top Cut",
    "wof:placetype":"venue"
},
  "geometry": {"coordinates":[-82.94348144529999,46.1924743652],"type":"Point"}
}