{
  "type": "Feature",
  "properties": {
    "iso:country":"CA",
    "sg:address":"168 Westmorland St",
    "sg:city":"Fredericton",
    "sg:classifiers":[
        {
            "category":"Organizations",
            "subcategory":"Religious Organization",
            "type":"Services"
        }
    ],
    "sg:phone":"+1 506 454 9698",
    "sg:postcode":"E3B 3L7",
    "sg:province":"NB",
    "sg:tags":[
        "synagogue",
        "church"
    ],
    "wof:name":"Sgoolai Israel Synagogue",
    "wof:placetype":"venue"
},
  "geometry": {"coordinates":[-66.64696502690001,45.9618415833],"type":"Point"}
}