{
  "type": "Feature",
  "properties": {
    "addr:full":"635 Main St Sussex NB E4E 7H5",
    "addr:housenumber":"635",
    "addr:postcode":"e4e 7h5",
    "addr:street":"Main St",
    "iso:country":"CA",
    "sg:address":"635 Main St",
    "sg:city":"Sussex",
    "sg:classifiers":[
        {
            "category":"Banks & Credit Unions",
            "subcategory":"Bank",
            "type":"Services"
        }
    ],
    "sg:phone":"+1 506 432 3920",
    "sg:postcode":"E4E 7H5",
    "sg:province":"NB",
    "wof:name":"Scotiabank",
    "wof:placetype":"venue"
},
  "geometry": {"coordinates":[-65.50720200000001,45.72295],"type":"Point"}
}