{
  "type": "Feature",
  "properties": {
    "addr:full":"6 Morton Ave Sharon ON L0G 1V0",
    "addr:housenumber":"6",
    "addr:postcode":"l0g 1v0",
    "addr:street":"Morton Ave",
    "iso:country":"CA",
    "sg:address":"6 Morton Ave",
    "sg:city":"Sharon",
    "sg:classifiers":[
        {
            "category":"Retail",
            "subcategory":"Laundry & Dry Cleaning",
            "type":"Services"
        }
    ],
    "sg:phone":"+1 905 478 4572",
    "sg:postcode":"L0G 1V0",
    "sg:province":"ON",
    "sg:tags":[
        "cleaners",
        "rug",
        "carpet"
    ],
    "wof:name":"Stanley Steamer Carpet Cleaner",
    "wof:placetype":"venue"
},
  "geometry": {"coordinates":[-79.4378585815,44.1023406982],"type":"Point"}
}