{
  "type": "Feature",
  "properties": {
    "addr:full":"18 Sterling Rd Glace Bay NS B1A 3X5",
    "addr:housenumber":"18",
    "addr:postcode":"b1a 3x5",
    "addr:street":"Sterling Rd",
    "iso:country":"CA",
    "sg:address":"18 Sterling Rd",
    "sg:city":"Glace Bay",
    "sg:classifiers":[
        {
            "category":"Retail",
            "subcategory":"Auto Rental",
            "type":"Services"
        }
    ],
    "sg:phone":"+1 902 849 5579",
    "sg:postcode":"B1A 3X5",
    "sg:province":"NS",
    "sg:tags":[
        "renting",
        "leasing",
        "truck",
        "trailer"
    ],
    "wof:name":"U-Haul CO Ltd",
    "wof:placetype":"venue"
},
  "geometry": {"coordinates":[-59.955887,46.203777],"type":"Point"}
}