{
  "type": "Feature",
  "properties": {
    "addr:full":"105 Main St N Sauble Beach ON N0H 2G0",
    "addr:housenumber":"105",
    "addr:postcode":"n0h 2g0",
    "addr:street":"Main St N",
    "iso:country":"CA",
    "sg:address":"105 Main St N",
    "sg:city":"Sauble Beach",
    "sg:classifiers":[
        {
            "category":"Shopping",
            "subcategory":"Clothing, Apparel, & Fashions",
            "type":"Retail Goods"
        }
    ],
    "sg:phone":"+1 519 422 3810",
    "sg:postcode":"N0H 2G0",
    "sg:province":"ON",
    "wof:name":"Longboard Woody's Surf Shop",
    "wof:placetype":"venue"
},
  "geometry": {"coordinates":[-81.27029418950001,44.6295166016],"type":"Point"}
}