{
  "type": "Feature",
  "properties": {
    "addr:full":"748 Mckellar St Peterborough ON K9J 1R3",
    "addr:housenumber":"748",
    "addr:postcode":"k9j 1r3",
    "addr:street":"Mckellar St",
    "iso:country":"CA",
    "sg:address":"748 Mckellar St",
    "sg:city":"Peterborough",
    "sg:classifiers":[
        {
            "category":"Education",
            "subcategory":"Special Training",
            "type":"Public Place"
        }
    ],
    "sg:phone":"+1 705 749 1686",
    "sg:postcode":"K9J 1R3",
    "sg:province":"ON",
    "sg:tags":[
        "instruction",
        "driving"
    ],
    "wof:name":"Safeway Driving School",
    "wof:placetype":"venue"
},
  "geometry": {"coordinates":[-78.33208500000001,44.278713],"type":"Point"}
}