{
  "type": "Feature",
  "properties": {
    "addr:full":"Calgary AB T2P 2V6",
    "addr:postcode":"t2p 2v6",
    "iso:country":"CA",
    "sg:city":"Calgary",
    "sg:classifiers":[
        {
            "category":"Professional",
            "type":"Services"
        }
    ],
    "sg:phone":"+1 403 264 4112",
    "sg:postcode":"T2P 2V6",
    "sg:province":"AB",
    "sg:tags":[
        "geophysical"
    ],
    "wof:name":"B D Geophysical Consulting",
    "wof:placetype":"venue"
},
  "geometry": {"coordinates":[-114.071648,51.049652],"type":"Point"}
}