{
  "type": "Feature",
  "properties": {
    "iso:country":"CA",
    "sg:city":"Calixa-Lavallee",
    "sg:classifiers":[
        {
            "category":"Manufacturing",
            "subcategory":"Furniture",
            "type":"Manufacturing & Wholesale Goods"
        }
    ],
    "sg:phone":"+1 450 583 6249",
    "sg:postcode":"J0L 1A0",
    "sg:province":"QC",
    "wof:name":"Maitre Couleur",
    "wof:placetype":"venue"
},
  "geometry": {"coordinates":[-73.2721405029,45.756313324],"type":"Point"}
}