{
  "type": "Feature",
  "properties": {
    "addr:full":"Saskatoon SK S7N 5E8",
    "addr:postcode":"s7n 5e8",
    "iso:country":"CA",
    "sg:city":"Saskatoon",
    "sg:classifiers":[
        {
            "category":"Restaurant",
            "type":"Food & Drink"
        }
    ],
    "sg:phone":"+1 306 966 8600",
    "sg:postcode":"S7N 5E8",
    "sg:province":"SK",
    "sg:tags":[
        "caterer"
    ],
    "wof:name":"Conference & Catering Svc",
    "wof:placetype":"venue"
},
  "geometry": {"coordinates":[-106.633774,52.129276],"type":"Point"}
}