{
  "type": "Feature",
  "properties": {
    "addr:full":"780 Av Du Brabant Sainte-Foy QC G1X 3V9",
    "addr:housenumber":"780",
    "addr:postcode":"g1x 3v9",
    "addr:street":"Av Du Brabant",
    "iso:country":"CA",
    "sg:address":"780 Av Du Brabant",
    "sg:city":"Sainte-Foy",
    "sg:classifiers":[
        {
            "category":"Building & Trades",
            "subcategory":"Construction",
            "type":"Services"
        }
    ],
    "sg:phone":"+1 418 871 9148",
    "sg:postcode":"G1X 3V9",
    "sg:province":"QC",
    "sg:tags":[
        "general",
        "contractor"
    ],
    "wof:name":"Habitations Boivin",
    "wof:placetype":"venue"
},
  "geometry": {"coordinates":[-71.32260894780001,46.7709579468],"type":"Point"}
}