{
  "type": "Feature",
  "properties": {
    "addr:full":"100 West St Moncton NB E1E 3N9",
    "addr:housenumber":"100",
    "addr:postcode":"e1e 3n9",
    "addr:street":"West St",
    "iso:country":"CA",
    "sg:address":"100 West St",
    "sg:city":"Moncton",
    "sg:classifiers":[
        {
            "category":"Real Estate",
            "subcategory":"Real Estate Operator",
            "type":"Services"
        }
    ],
    "sg:phone":"+1 506 382 2200",
    "sg:postcode":"E1E 3N9",
    "sg:province":"NB",
    "sg:tags":[
        "apartment"
    ],
    "wof:name":"Prince Edward",
    "wof:placetype":"venue"
},
  "geometry": {"coordinates":[-64.793999,46.086636],"type":"Point"}
}