{
  "type": "Feature",
  "properties": {
    "addr:full":"Richmond Hill ON L4C 3C6",
    "addr:postcode":"l4c 3c6",
    "iso:country":"CA",
    "sg:city":"Richmond Hill",
    "sg:classifiers":[
        {
            "category":"Home & Garden",
            "subcategory":"Building Materials",
            "type":"Retail Goods"
        }
    ],
    "sg:phone":"+1 905 761 5252",
    "sg:postcode":"L4C 3C6",
    "sg:province":"ON",
    "sg:tags":[
        "windows"
    ],
    "wof:name":"Rusco Distributors Ltd",
    "wof:placetype":"venue"
},
  "geometry": {"coordinates":[-79.459808,43.921761],"type":"Point"}
}