{
  "type": "Feature",
  "properties": {
    "addr:full":"29 Rue Blainville O Sainte-Therese QC J7E 1X1",
    "addr:housenumber":"29",
    "addr:postcode":"j7e 1x1",
    "addr:street":"Rue Blainville O Sainte-Therese",
    "iso:country":"CA",
    "sg:address":"29 Rue Blainville O",
    "sg:city":"Sainte-Therese",
    "sg:classifiers":[
        {
            "category":"Travel",
            "subcategory":"Hotels & Motels",
            "type":"Entertainment"
        }
    ],
    "sg:phone":"+1 450 435 7200",
    "sg:postcode":"J7E 1X1",
    "sg:province":"QC",
    "wof:name":"Hotel Blainville",
    "wof:placetype":"venue"
},
  "geometry": {"coordinates":[-73.8396606445,45.6391334534],"type":"Point"}
}