{
  "type": "Feature",
  "properties": {
    "iso:country":"CA",
    "sg:address":"1505 Boul Saint-Martin O",
    "sg:city":"Laval",
    "sg:classifiers":[
        {
            "category":"Restaurant",
            "type":"Food & Drink"
        }
    ],
    "sg:phone":"+1 450 669 1736",
    "sg:postcode":"H7S 1N1",
    "sg:province":"QC",
    "wof:name":"Burger King",
    "wof:placetype":"venue"
},
  "geometry": {"coordinates":[-73.724983,45.569721],"type":"Point"}
}