{
  "type": "Feature",
  "properties": {
    "iso:country":"CA",
    "sg:address":"PO Box 1227",
    "sg:city":"Valleyview",
    "sg:classifiers":[
        {
            "category":"Retail",
            "subcategory":"Repair Shop",
            "type":"Services"
        }
    ],
    "sg:phone":"+1 780 524 2372",
    "sg:postcode":"T0H 3N0",
    "sg:province":"AB",
    "sg:tags":[
        "welding"
    ],
    "wof:name":"Ed Faltermeier Welding Ltd",
    "wof:placetype":"venue"
},
  "geometry": {"coordinates":[-117.27177399999999,55.068642],"type":"Point"}
}