{
  "type": "Feature",
  "properties": {
    "iso:country":"CA",
    "sg:address":"730 Glen Forrest Blvd",
    "sg:city":"Waterloo",
    "sg:classifiers":[
        {
            "category":"Banks & Credit Unions",
            "subcategory":"Bank",
            "type":"Services"
        }
    ],
    "sg:phone":"+1 519 885 8410",
    "sg:postcode":"N2L 4K8",
    "sg:province":"ON",
    "wof:name":"Bank of Montreal",
    "wof:placetype":"venue"
},
  "geometry": {"coordinates":[-80.5490570068,43.4938049316],"type":"Point"}
}