{
  "type": "Feature",
  "properties": {
    "addr:full":"1868 Salmon River Rd Salmon Arm BC V1E 3H6",
    "addr:housenumber":"1868",
    "addr:postcode":"v1e 3h6",
    "addr:street":"Salmon River Rd",
    "iso:country":"CA",
    "sg:address":"1868 Salmon River Rd",
    "sg:city":"Salmon Arm",
    "sg:classifiers":[
        {
            "category":"Building & Trades",
            "subcategory":"Construction",
            "type":"Services"
        }
    ],
    "sg:phone":"+1 250 833 1568",
    "sg:postcode":"V1E 3H6",
    "sg:province":"BC",
    "sg:tags":[
        "repairing",
        "remodeling",
        "contractor"
    ],
    "wof:name":"Interior Insulation",
    "wof:placetype":"venue"
},
  "geometry": {"coordinates":[-119.331772,50.693947],"type":"Point"}
}