{
  "type": "Feature",
  "properties": {
    "addr:full":"18 Sawmill Lane Gormley ON L0H 1G0",
    "addr:housenumber":"18",
    "addr:postcode":"l0h 1g0",
    "addr:street":"Sawmill Lane",
    "iso:country":"CA",
    "sg:address":"18 Sawmill Lane",
    "sg:city":"Gormley",
    "sg:classifiers":[
        {
            "category":"Building & Trades",
            "subcategory":"Cleaning & Sanitation",
            "type":"Services"
        }
    ],
    "sg:phone":"+1 905 888 9981",
    "sg:postcode":"L0H 1G0",
    "sg:province":"ON",
    "sg:tags":[
        "maintenance"
    ],
    "wof:name":"Brownstone Restoration Inc",
    "wof:placetype":"venue"
},
  "geometry": {"coordinates":[-79.370773,43.961876],"type":"Point"}
}