{
  "type": "Feature",
  "properties": {
    "addr:full":"Skyline Rd Ennismore ON K0L 1T0",
    "addr:postcode":"k0l 1t0",
    "addr:street":"Skyline Rd",
    "iso:country":"CA",
    "sg:address":"Skyline Rd",
    "sg:city":"Ennismore",
    "sg:classifiers":[
        {
            "category":"Manufacturing",
            "subcategory":"Electronics",
            "type":"Manufacturing & Wholesale Goods"
        }
    ],
    "sg:phone":"+1 705 292 7731",
    "sg:postcode":"K0L 1T0",
    "sg:province":"ON",
    "sg:tags":[
        "upholstery",
        "upholsterer",
        "top",
        "cover",
        "marine",
        "boat"
    ],
    "wof:name":"Ron's Upholstery & Canvas",
    "wof:placetype":"venue"
},
  "geometry": {"coordinates":[-78.42817700000001,44.410664],"type":"Point"}
}