{
  "type": "Feature",
  "properties": {
    "addr:full":"33235 Hwy 17 W Deep River ON K0J 1P0",
    "addr:housenumber":"33235",
    "addr:postcode":"k0j 1p0",
    "addr:street":"Hwy 17 W",
    "iso:country":"CA",
    "sg:address":"33235 Hwy 17 W",
    "sg:city":"Deep River",
    "sg:classifiers":[
        {
            "category":"Food & Beverages",
            "subcategory":"Bakery",
            "type":"Retail Goods"
        }
    ],
    "sg:phone":"+1 613 584 9933",
    "sg:postcode":"K0J 1P0",
    "sg:province":"ON",
    "sg:tags":[
        "doughnut"
    ],
    "wof:name":"Tim Hortons",
    "wof:placetype":"venue"
},
  "geometry": {"coordinates":[-77.497231,46.099045],"type":"Point"}
}