{
  "type": "Feature",
  "properties": {
    "addr:full":"731 Ch Du Lac-Aux-Quenouilles Lac-Superieur QC J0T 1J0",
    "addr:housenumber":"731",
    "addr:postcode":"j0t 1j0",
    "addr:street":"Ch Du Lac-Aux-Quenouilles Lac-Superieur",
    "iso:country":"CA",
    "sg:address":"731 Ch Du Lac-Aux-Quenouilles",
    "sg:city":"Lac-Superieur",
    "sg:classifiers":[
        {
            "category":"Wholesale",
            "subcategory":"Electrical",
            "type":"Manufacturing & Wholesale Goods"
        }
    ],
    "sg:phone":"+1 819 688 2754",
    "sg:postcode":"J0T 1J0",
    "sg:province":"QC",
    "sg:tags":[
        "equipment",
        "plant",
        "power"
    ],
    "wof:name":"Iesl Intl Energy Systems",
    "wof:placetype":"venue"
},
  "geometry": {"coordinates":[-74.427521,46.147934],"type":"Point"}
}