{
  "type": "Feature",
  "properties": {
    "addr:full":"5399 Jubilee Ave Drayton Valley AB T7A 1R9",
    "addr:housenumber":"5399",
    "addr:postcode":"t7a 1r9",
    "addr:street":"Jubilee Ave",
    "iso:country":"CA",
    "sg:address":"5399 Jubilee Ave",
    "sg:city":"Drayton Valley",
    "sg:classifiers":[
        {
            "category":"Mining & Drilling",
            "type":"Manufacturing & Wholesale Goods"
        }
    ],
    "sg:phone":"+1 780 542 5597",
    "sg:postcode":"T7A 1R9",
    "sg:province":"AB",
    "sg:tags":[
        "field",
        "oil"
    ],
    "wof:name":"Nelson Bros Ltd",
    "wof:placetype":"venue"
},
  "geometry": {"coordinates":[-114.98867799999999,53.227875],"type":"Point"}
}