{
  "type": "Feature",
  "properties": {
    "addr:full":"1465 Rue DE L'Innovation Val-Belair QC G3K 2P9",
    "addr:housenumber":"1465",
    "addr:postcode":"g3k 2p9",
    "addr:street":"Rue De L'Innovation Val-Belair",
    "iso:country":"CA",
    "sg:address":"1465 Rue DE L'Innovation",
    "sg:city":"Val-Belair",
    "sg:classifiers":[
        {
            "category":"Education",
            "subcategory":"Library",
            "type":"Public Place"
        }
    ],
    "sg:phone":"+1 418 641 6435",
    "sg:postcode":"G3K 2P9",
    "sg:province":"QC",
    "wof:name":"Bibliotheque Felix-Leclerc",
    "wof:placetype":"venue"
},
  "geometry": {"coordinates":[-71.4194717407,46.858581543],"type":"Point"}
}