{
  "type": "Feature",
  "properties": {
    "addr:full":"1030 Rue Fernand-Dufour Vanier QC G1M 2Y3",
    "addr:housenumber":"1030",
    "addr:postcode":"g1m 2y3",
    "addr:street":"Rue Fernand-Dufour",
    "iso:country":"CA",
    "sg:address":"1030 Rue Fernand-Dufour",
    "sg:city":"Vanier",
    "sg:classifiers":[
        {
            "category":"Retail",
            "subcategory":"Auto Rental",
            "type":"Services"
        }
    ],
    "sg:phone":"+1 418 682 0301",
    "sg:postcode":"G1M 2Y3",
    "sg:province":"QC",
    "sg:tags":[
        "renting",
        "truck",
        "leasing"
    ],
    "wof:name":"Penske Truck Leasing",
    "wof:placetype":"venue"
},
  "geometry": {"coordinates":[-71.282516,46.823975],"type":"Point"}
}