{
  "type": "Feature",
  "properties": {
    "addr:full":"Etobicoke ON M9C 2A8",
    "addr:postcode":"m9c 2a8",
    "iso:country":"CA",
    "sg:city":"Etobicoke",
    "sg:classifiers":[
        {
            "category":"Museum",
            "type":"Entertainment"
        }
    ],
    "sg:phone":"+1 416 622 8731",
    "sg:postcode":"M9C 2A8",
    "sg:province":"ON",
    "sg:tags":[
        "organization",
        "arts",
        "information"
    ],
    "wof:name":"Arts Etobicoke",
    "wof:placetype":"venue"
},
  "geometry": {"coordinates":[-79.563423,43.639744],"type":"Point"}
}