{
  "type": "Feature",
  "properties": {
    "iso:country":"CA",
    "sg:address":"2340 Boul Sainte-Anne",
    "sg:city":"Quebec",
    "sg:classifiers":[
        {
            "category":"Bars & Pubs",
            "type":"Food & Drink"
        }
    ],
    "sg:phone":"+1 418 663 3434",
    "sg:postcode":"G1J 1Y3",
    "sg:province":"QC",
    "sg:tags":[
        "lounge",
        "cocktail"
    ],
    "wof:name":"Bar Sport Vegas",
    "wof:placetype":"venue"
},
  "geometry": {"coordinates":[-71.217468,46.842403],"type":"Point"}
}