{
  "type": "Feature",
  "properties": {
    "addr:full":"977 Prince Rupert Blvd Prince Rupert BC V8J 4L3",
    "addr:housenumber":"977",
    "addr:postcode":"v8j 4l3",
    "addr:street":"Prince Rupert Blvd",
    "iso:country":"CA",
    "sg:address":"977 Prince Rupert Blvd",
    "sg:city":"Prince Rupert",
    "sg:classifiers":[
        {
            "category":"Organizations",
            "subcategory":"Religious Organization",
            "type":"Services"
        }
    ],
    "sg:phone":"+1 250 624 4449",
    "sg:postcode":"V8J 4L3",
    "sg:province":"BC",
    "sg:tags":[
        "church"
    ],
    "wof:name":"Church of Christ",
    "wof:placetype":"venue"
},
  "geometry": {"coordinates":[-130.298248,54.317348],"type":"Point"}
}