{
  "type": "Feature",
  "properties": {
    "iso:country":"CA",
    "sg:address":"136 Rue Du Souvenir",
    "sg:city":"Maniwaki",
    "sg:classifiers":[
        {
            "category":"Organizations",
            "subcategory":"Professional Association",
            "type":"Services"
        }
    ],
    "sg:phone":"+1 819 449 4487",
    "sg:postcode":"J9E 2H1",
    "sg:province":"QC",
    "sg:tags":[
        "club"
    ],
    "wof:name":"Legion Canadienne 187",
    "wof:placetype":"venue"
},
  "geometry": {"coordinates":[-75.98017120359999,46.3758583069],"type":"Point"}
}