{
  "type": "Feature",
  "properties": {
    "addr:full":"621 Kennedy Rd Scarborough ON M1K 2B2",
    "addr:housenumber":"621",
    "addr:postcode":"m1k 2b2",
    "addr:street":"Kennedy Rd",
    "iso:country":"CA",
    "sg:address":"621 Kennedy Rd",
    "sg:city":"Scarborough",
    "sg:classifiers":[
        {
            "category":"Personal",
            "subcategory":"Beauty Salon",
            "type":"Services"
        }
    ],
    "sg:phone":"+1 416 266 1661",
    "sg:postcode":"M1K 2B2",
    "sg:province":"ON",
    "wof:name":"Tina Nanda Coiffure",
    "wof:placetype":"venue"
},
  "geometry": {"coordinates":[-79.2645111084,43.7246284485],"type":"Point"}
}