{
  "type": "Feature",
  "properties": {
    "iso:country":"CA",
    "sg:address":"782 Boul DE LA Grande-Baie S",
    "sg:city":"LA Baie",
    "sg:classifiers":[
        {
            "category":"Home & Garden",
            "subcategory":"Hardware",
            "type":"Retail Goods"
        }
    ],
    "sg:phone":"+1 418 544 4034",
    "sg:postcode":"G7B 1C2",
    "sg:province":"QC",
    "wof:name":"Quincaillerie Tremblay Enr",
    "wof:placetype":"venue"
},
  "geometry": {"coordinates":[-70.877853,48.328537],"type":"Point"}
}