{
  "type": "Feature",
  "properties": {
    "iso:country":"CA",
    "sg:address":"3217 Broadway W",
    "sg:city":"Vancouver",
    "sg:classifiers":[
        {
            "category":"Wholesale",
            "subcategory":"Apparel",
            "type":"Manufacturing & Wholesale Goods"
        }
    ],
    "sg:phone":"+1 604 734 1176",
    "sg:postcode":"V6K 2H5",
    "sg:province":"BC",
    "sg:tags":[
        "clothing"
    ],
    "wof:name":"Eugenia",
    "wof:placetype":"venue"
},
  "geometry": {"coordinates":[-123.176223755,49.2643203735],"type":"Point"}
}