{
  "type": "Feature",
  "properties": {
    "addr:full":"325 Weston Rd York ON M6N 4Z9",
    "addr:housenumber":"325",
    "addr:postcode":"m6n 4z9",
    "addr:street":"Weston Rd",
    "iso:country":"CA",
    "sg:address":"325 Weston Rd",
    "sg:city":"York",
    "sg:classifiers":[
        {
            "category":"Wholesale",
            "subcategory":"Chemicals & Plastics",
            "type":"Manufacturing & Wholesale Goods"
        }
    ],
    "sg:phone":"+1 416 761 1656",
    "sg:postcode":"M6N 4Z9",
    "sg:province":"ON",
    "sg:tags":[
        "oil",
        "additive"
    ],
    "wof:name":"Quick Booster Canada Inc",
    "wof:placetype":"venue"
},
  "geometry": {"coordinates":[-79.474396,43.679211],"type":"Point"}
}