{
  "type": "Feature",
  "properties": {
    "addr:full":"520 Cranbrook St N Cranbrook BC V1C 3R6",
    "addr:housenumber":"520",
    "addr:postcode":"v1c 3r6",
    "addr:street":"Cranbrook St N",
    "iso:country":"CA",
    "sg:address":"520 Cranbrook St N",
    "sg:city":"Cranbrook",
    "sg:classifiers":[
        {
            "category":"Restaurant",
            "type":"Food & Drink"
        }
    ],
    "sg:phone":"+1 250 426 5413",
    "sg:postcode":"V1C 3R6",
    "sg:province":"BC",
    "wof:name":"Kfc",
    "wof:placetype":"venue"
},
  "geometry": {"coordinates":[-115.762145996,49.5172157288],"type":"Point"}
}