{
  "type": "Feature",
  "properties": {
    "addr:full":"3 Jerome Park Dr Dundas ON L9H 6G9",
    "addr:housenumber":"3",
    "addr:postcode":"l9h 6g9",
    "addr:street":"Jerome Park Dr",
    "iso:country":"CA",
    "sg:address":"3 Jerome Park Dr",
    "sg:city":"Dundas",
    "sg:classifiers":[
        {
            "category":"Wholesale",
            "subcategory":"Scrap",
            "type":"Manufacturing & Wholesale Goods"
        }
    ],
    "sg:phone":"+1 905 719 1535",
    "sg:postcode":"L9H 6G9",
    "sg:province":"ON",
    "sg:tags":[
        "metal",
        "iron"
    ],
    "wof:name":"Advance Recycling",
    "wof:placetype":"venue"
},
  "geometry": {"coordinates":[-79.97570037840001,43.2554626465],"type":"Point"}
}