{
  "type": "Feature",
  "properties": {
    "addr:full":"4103 Boul Sainte-Anne Beauport QC G1C 2H9",
    "addr:housenumber":"4103",
    "addr:postcode":"qc g1c 2h9",
    "addr:street":"Boul Sainte-Anne",
    "iso:country":"CA",
    "sg:address":"4103 Boul Sainte-Anne",
    "sg:city":"Beauport",
    "sg:classifiers":[
        {
            "category":"Wholesale",
            "subcategory":"Machinery & Supplies",
            "type":"Manufacturing & Wholesale Goods"
        }
    ],
    "sg:phone":"+1 418 829 2545",
    "sg:postcode":"G1C 2H9",
    "sg:province":"QC",
    "sg:tags":[
        "cleaning"
    ],
    "wof:name":"Sani-Orleans Enr",
    "wof:placetype":"venue"
},
  "geometry": {"coordinates":[-71.159981,46.872108],"type":"Point"}
}