{
  "type": "Feature",
  "properties": {
    "addr:full":"3125 Boul Saint-Charles Kirkland QC H9H 3B9",
    "addr:housenumber":"3125",
    "addr:postcode":"h9h 3b9",
    "addr:street":"Boul Saint-Charles",
    "iso:country":"CA",
    "sg:address":"3125 Boul Saint-Charles",
    "sg:city":"Kirkland",
    "sg:classifiers":[
        {
            "category":"Home & Garden",
            "subcategory":"Building Materials",
            "type":"Retail Goods"
        }
    ],
    "sg:phone":"+1 514 695 3395",
    "sg:postcode":"H9H 3B9",
    "sg:province":"QC",
    "sg:tags":[
        "mixed",
        "product",
        "asphalt"
    ],
    "wof:name":"Meloche Inc",
    "wof:placetype":"venue"
},
  "geometry": {"coordinates":[-73.856567,45.450531],"type":"Point"}
}