{
  "type": "Feature",
  "properties": {
    "addr:full":"5298 Yonge St North York ON M2N 5P9",
    "addr:housenumber":"5298",
    "addr:postcode":"m2n 5p9",
    "addr:street":"Yonge St",
    "iso:country":"CA",
    "sg:address":"5298 Yonge St",
    "sg:city":"North York",
    "sg:classifiers":[
        {
            "category":"Home & Garden",
            "subcategory":"Household Appliances",
            "type":"Retail Goods"
        }
    ],
    "sg:phone":"+1 416 225 1173",
    "sg:postcode":"M2N 5P9",
    "sg:province":"ON",
    "sg:tags":[
        "cleaners",
        "vacuum"
    ],
    "wof:name":"Electrolux Canada",
    "wof:placetype":"venue"
},
  "geometry": {"coordinates":[-79.4138793945,43.7724876404],"type":"Point"}
}