{
  "type": "Feature",
  "properties": {
    "addr:full":"34261 Industrial Way Abbotsford BC V2S 7M6",
    "addr:housenumber":"34261",
    "addr:postcode":"v2s 7m6",
    "addr:street":"Industrial Way",
    "iso:country":"CA",
    "sg:address":"34261 Industrial Way",
    "sg:city":"Abbotsford",
    "sg:classifiers":[
        {
            "category":"Wholesale",
            "subcategory":"Construction Materials",
            "type":"Manufacturing & Wholesale Goods"
        }
    ],
    "sg:phone":"+1 604 850 9355",
    "sg:postcode":"V2S 7M6",
    "sg:province":"BC",
    "sg:tags":[
        "importer",
        "lumber"
    ],
    "wof:name":"Mirax Lumber Products Ltd",
    "wof:placetype":"venue"
},
  "geometry": {"coordinates":[-122.274902344,49.0138893127],"type":"Point"}
}