{
  "type": "Feature",
  "properties": {
    "addr:full":"13135 Rue Louis-Joseph-Papinea Mirabel QC J7J 2K5",
    "addr:housenumber":"13135",
    "addr:postcode":"j7j 2k5",
    "addr:street":"Rue Louis-Joseph-Papinea",
    "iso:country":"CA",
    "sg:address":"13135 Rue Louis-Joseph-Papinea",
    "sg:city":"Mirabel",
    "sg:classifiers":[
        {
            "category":"Building & Trades",
            "subcategory":"Electrical",
            "type":"Services"
        }
    ],
    "sg:phone":"+1 450 430 6334",
    "sg:postcode":"J7J 2K5",
    "sg:province":"QC",
    "sg:tags":[
        "electric",
        "contractor"
    ],
    "wof:name":"Paul Lapointe Electrique Inc",
    "wof:placetype":"venue"
},
  "geometry": {"coordinates":[-73.91181899999999,45.700687],"type":"Point"}
}