{
  "type": "Feature",
  "properties": {
    "addr:full":"Sainte-Anne-DE-Bellevue QC H9X 1L8",
    "addr:postcode":"h9x 1l8",
    "iso:country":"CA",
    "sg:city":"Sainte-Anne-DE-Bellevue",
    "sg:classifiers":[
        {
            "category":"Health Services",
            "subcategory":"Doctor",
            "type":"Services"
        }
    ],
    "sg:phone":"+1 514 457 9355",
    "sg:postcode":"H9X 1L8",
    "sg:province":"QC",
    "sg:tags":[
        "physician",
        "surgeon"
    ],
    "wof:name":"Lakeshore Wellness Ctr",
    "wof:placetype":"venue"
},
  "geometry": {"coordinates":[-73.95246899999999,45.403725],"type":"Point"}
}