{
  "type": "Feature",
  "properties": {
    "addr:full":"Toronto ON M4W 3L8",
    "addr:postcode":"m4w 3l8",
    "iso:country":"CA",
    "sg:city":"Toronto",
    "sg:classifiers":[
        {
            "category":"Shopping",
            "subcategory":"Department Store",
            "type":"Retail Goods"
        }
    ],
    "sg:phone":"+1 416 922 2333",
    "sg:postcode":"M4W 3L8",
    "sg:province":"ON",
    "sg:tags":[
        "apparel"
    ],
    "wof:name":"Holt Renfrew & CO Ltd",
    "wof:placetype":"venue"
},
  "geometry": {"coordinates":[-79.3891448975,43.6698684692],"type":"Point"}
}