{
  "type": "Feature",
  "properties": {
    "addr:full":"10004 105 St Westlock AB T7P 1V2",
    "addr:housenumber":"10004",
    "addr:postcode":"t7p 1v2",
    "addr:street":"105 St",
    "iso:country":"CA",
    "sg:address":"10004 105 St",
    "sg:city":"Westlock",
    "sg:classifiers":[
        {
            "category":"Retail",
            "subcategory":"Funeral Services",
            "type":"Services"
        }
    ],
    "sg:phone":"+1 780 349 3474",
    "sg:postcode":"T7P 1V2",
    "sg:province":"AB",
    "sg:tags":[
        "director"
    ],
    "wof:name":"Westlock Funeral Home Ltd",
    "wof:placetype":"venue"
},
  "geometry": {"coordinates":[-113.860275,54.154381],"type":"Point"}
}