{
  "type": "Feature",
  "properties": {
    "addr:full":"8550 Granville St Vancouver BC V6P 4Z7",
    "addr:housenumber":"8550",
    "addr:postcode":"v6p 4z7",
    "addr:street":"Granville St",
    "iso:country":"CA",
    "sg:address":"8550 Granville St",
    "sg:city":"Vancouver",
    "sg:classifiers":[
        {
            "category":"Shopping",
            "subcategory":"Optical Goods",
            "type":"Retail Goods"
        }
    ],
    "sg:phone":"+1 604 264 9391",
    "sg:postcode":"V6P 4Z7",
    "sg:province":"BC",
    "sg:tags":[
        "optician"
    ],
    "wof:name":"Eyemate Optical",
    "wof:placetype":"venue"
},
  "geometry": {"coordinates":[-123.140327454,49.2090072632],"type":"Point"}
}