{
  "type": "Feature",
  "properties": {
    "addr:full":"Montreal QC H3H 2T3",
    "addr:postcode":"h3h 2t3",
    "iso:country":"CA",
    "sg:city":"Montreal",
    "sg:classifiers":[
        {
            "category":"Communications",
            "subcategory":"Film & Video Production",
            "type":"Services"
        }
    ],
    "sg:phone":"+1 514 939 5094",
    "sg:postcode":"H3H 2T3",
    "sg:province":"QC",
    "sg:tags":[
        "motion",
        "picture",
        "studio",
        "producer",
        "foundation"
    ],
    "wof:name":"Le Sondes Harold Greenberg",
    "wof:placetype":"venue"
},
  "geometry": {"coordinates":[-73.5500488281,45.5248527527],"type":"Point"}
}