{
  "type": "Feature",
  "properties": {
    "addr:full":"Faust AB T0G 0X0",
    "addr:postcode":"t0g 0x0",
    "iso:country":"CA",
    "sg:city":"Faust",
    "sg:classifiers":[
        {
            "category":"Food & Beverages",
            "subcategory":"Groceries & Convenience Stores",
            "type":"Retail Goods"
        }
    ],
    "sg:phone":"+1 780 355 3600",
    "sg:postcode":"T0G 0X0",
    "sg:province":"AB",
    "sg:tags":[
        "grocer"
    ],
    "wof:name":"Faust General Store",
    "wof:placetype":"venue"
},
  "geometry": {"coordinates":[-115.653809,55.319698],"type":"Point"}
}