{
  "type": "Feature",
  "properties": {
    "addr:full":"944 Wilson Ave North York ON M3K 1E7",
    "addr:housenumber":"944",
    "addr:postcode":"m3k 1e7",
    "addr:street":"Wilson Ave",
    "iso:country":"CA",
    "sg:address":"944 Wilson Ave",
    "sg:city":"North York",
    "sg:classifiers":[
        {
            "category":"Manufacturing",
            "subcategory":"Tools & Machinery",
            "type":"Manufacturing & Wholesale Goods"
        }
    ],
    "sg:phone":"+1 416 636 6111",
    "sg:postcode":"M3K 1E7",
    "sg:province":"ON",
    "sg:tags":[
        "laboratory",
        "salon",
        "beauty",
        "equipment"
    ],
    "wof:name":"Beauty & Esthetic Equipment",
    "wof:placetype":"venue"
},
  "geometry": {"coordinates":[-79.470512,43.729961],"type":"Point"}
}