{
  "type": "Feature",
  "properties": {
    "iso:country":"CA",
    "sg:address":"20 Rue Louis-Hebert",
    "sg:city":"Sainte-Therese",
    "sg:classifiers":[
        {
            "category":"Retail",
            "subcategory":"Laundry & Dry Cleaning",
            "type":"Services"
        }
    ],
    "sg:phone":"+1 450 435 6642",
    "sg:postcode":"J7E 3W5",
    "sg:province":"QC",
    "sg:tags":[
        "cleaners",
        "rug",
        "carpet"
    ],
    "wof:name":"Entreprises Yb",
    "wof:placetype":"venue"
},
  "geometry": {"coordinates":[-73.8523025513,45.638923645],"type":"Point"}
}