{
  "type": "Feature",
  "properties": {
    "addr:full":"1135 North Service Rd E Oakville ON L6H 1A7",
    "addr:housenumber":"1135",
    "addr:postcode":"l6h 1a7",
    "addr:street":"North Service Rd E",
    "iso:country":"CA",
    "sg:address":"1135 North Service Rd E",
    "sg:city":"Oakville",
    "sg:classifiers":[
        {
            "category":"Manufacturing",
            "subcategory":"Metals",
            "type":"Manufacturing & Wholesale Goods"
        }
    ],
    "sg:phone":"+1 905 842 8060",
    "sg:postcode":"L6H 1A7",
    "sg:province":"ON",
    "sg:tags":[
        "plumbing",
        "fixture",
        "supply"
    ],
    "wof:name":"Sexauer Limited",
    "wof:placetype":"venue"
},
  "geometry": {"coordinates":[-79.67421,43.473324],"type":"Point"}
}