{
  "type": "Feature",
  "properties": {
    "addr:full":"1833 Ch Des Patriotes N Mont-Saint-Hilaire QC J3G 4S6",
    "addr:housenumber":"1833",
    "addr:postcode":"j3g 4s6",
    "addr:street":"Ch Des Patriotes N Mont-Saint-Hilaire",
    "iso:country":"CA",
    "sg:address":"1833 Ch Des Patriotes N",
    "sg:city":"Mont-Saint-Hilaire",
    "sg:classifiers":[
        {
            "category":"Retail",
            "subcategory":"Laundry & Dry Cleaning",
            "type":"Services"
        }
    ],
    "sg:phone":"+1 450 467 3981",
    "sg:postcode":"J3G 4S6",
    "sg:province":"QC",
    "sg:tags":[
        "cleaners",
        "rug",
        "carpet"
    ],
    "wof:name":"G M Courchesne Ltee",
    "wof:placetype":"venue"
},
  "geometry": {"coordinates":[-73.18277740480001,45.6197052002],"type":"Point"}
}