{
  "type": "Feature",
  "properties": {
    "addr:full":"60 Regal Rd Guelph ON N1K 1B5",
    "addr:housenumber":"60",
    "addr:postcode":"n1k 1b5",
    "addr:street":"Regal Rd",
    "iso:country":"CA",
    "sg:address":"60 Regal Rd",
    "sg:city":"Guelph",
    "sg:classifiers":[
        {
            "category":"Manufacturing",
            "subcategory":"Tools & Machinery",
            "type":"Manufacturing & Wholesale Goods"
        }
    ],
    "sg:phone":"+1 519 824 0890",
    "sg:postcode":"N1K 1B5",
    "sg:province":"ON",
    "sg:tags":[
        "machine",
        "shop"
    ],
    "wof:name":"Fostet Manufacturing Inc",
    "wof:placetype":"venue"
},
  "geometry": {"coordinates":[-80.302414,43.549961],"type":"Point"}
}