{
  "type": "Feature",
  "properties": {
    "addr:full":"8951 Rue Salley Lasalle QC H8R 2C8",
    "addr:housenumber":"8951",
    "addr:postcode":"h8r 2c8",
    "addr:street":"Rue Salley",
    "iso:country":"CA",
    "sg:address":"8951 Rue Salley",
    "sg:city":"Lasalle",
    "sg:classifiers":[
        {
            "category":"Retail",
            "subcategory":"Laundry & Dry Cleaning",
            "type":"Services"
        }
    ],
    "sg:phone":"+1 514 365 8301",
    "sg:postcode":"H8R 2C8",
    "sg:province":"QC",
    "sg:tags":[
        "rental",
        "uniform"
    ],
    "wof:name":"Uniformes Premier Choix",
    "wof:placetype":"venue"
},
  "geometry": {"coordinates":[-73.627792,45.4245],"type":"Point"}
}