{
  "type": "Feature",
  "properties": {
    "addr:full":"13 Turtle Lake Rd Rosseau ON P0C 1J0",
    "addr:housenumber":"13",
    "addr:postcode":"p0c 1j0",
    "addr:street":"Turtle Lake Rd",
    "iso:country":"CA",
    "sg:address":"13 Turtle Lake Rd",
    "sg:city":"Rosseau",
    "sg:classifiers":[
        {
            "category":"Manufacturing",
            "subcategory":"Tools & Machinery",
            "type":"Manufacturing & Wholesale Goods"
        }
    ],
    "sg:phone":"+1 705 732 2231",
    "sg:postcode":"P0C 1J0",
    "sg:province":"ON",
    "sg:tags":[
        "machine",
        "shop",
        "trailer"
    ],
    "wof:name":"Healsteel Fabricators & Mach",
    "wof:placetype":"venue"
},
  "geometry": {"coordinates":[-79.639999,45.257069],"type":"Point"}
}