{
  "type": "Feature",
  "properties": {
    "addr:full":"60 Whellams Lane Winnipeg MB R2G 2G7",
    "addr:housenumber":"60",
    "addr:postcode":"r2g 2g7",
    "addr:street":"Whellams Lane",
    "iso:country":"CA",
    "sg:address":"60 Whellams Lane",
    "sg:city":"Winnipeg",
    "sg:classifiers":[
        {
            "category":"Real Estate",
            "subcategory":"Real Estate Operator",
            "type":"Services"
        }
    ],
    "sg:phone":"+1 204 339 9286",
    "sg:postcode":"R2G 2G7",
    "sg:province":"MB",
    "sg:tags":[
        "apartment"
    ],
    "wof:name":"Edgewood Estates",
    "wof:placetype":"venue"
},
  "geometry": {"coordinates":[-97.09324646,49.9485740662],"type":"Point"}
}