{
  "type": "Feature",
  "properties": {
    "addr:full":"223 14 St NW Calgary AB T2N 1Z6",
    "addr:housenumber":"14",
    "addr:postcode":"t2n 1z6",
    "addr:street":"223;St Nw",
    "iso:country":"CA",
    "sg:address":"223 14 St NW",
    "sg:city":"Calgary",
    "sg:classifiers":[
        {
            "category":"Professional",
            "subcategory":"Accounting & Tax Preparation",
            "type":"Services"
        }
    ],
    "sg:phone":"+1 403 283 1088",
    "sg:postcode":"T2N 1Z6",
    "sg:province":"AB",
    "sg:tags":[
        "accountant"
    ],
    "wof:name":"Lo Porter Hetu",
    "wof:placetype":"venue"
},
  "geometry": {"coordinates":[-114.09499359100001,51.0543518066],"type":"Point"}
}