{
  "type": "Feature",
  "properties": {
    "addr:full":"739 Mcmillan Ave Winnipeg MB R3M 0S8",
    "addr:housenumber":"739",
    "addr:postcode":"r3m 0s8",
    "addr:street":"Mcmillan Ave",
    "iso:country":"CA",
    "sg:address":"739 Mcmillan Ave",
    "sg:city":"Winnipeg",
    "sg:classifiers":[
        {
            "category":"Organizations",
            "subcategory":"Religious Organization",
            "type":"Services"
        }
    ],
    "sg:phone":"+1 204 475 5613",
    "sg:postcode":"R3M 0S8",
    "sg:province":"MB",
    "wof:name":"United Church Halfway House",
    "wof:placetype":"venue"
},
  "geometry": {"coordinates":[-97.15464799999999,49.871559],"type":"Point"}
}