{
  "type": "Feature",
  "properties": {
    "iso:country":"CA",
    "sg:address":"739 Mcmillan Ave",
    "sg:city":"Winnipeg",
    "sg:classifiers":[
        {
            "category":"Organizations",
            "subcategory":"Religious Organization",
            "type":"Services"
        }
    ],
    "sg:phone":"+1 204 475 5613",
    "sg:postcode":"R3M 0S8",
    "sg:province":"MB",
    "wof:name":"United Church Halfway House",
    "wof:placetype":"venue"
},
  "geometry": {"coordinates":[-97.154648,49.871559],"type":"Point"}
}