{
  "type": "Feature",
  "properties": {
    "addr:full":"Englehart ON P0J 1H0",
    "addr:postcode":"p0j 1h0",
    "iso:country":"CA",
    "sg:city":"Englehart",
    "sg:classifiers":[
        {
            "category":"Communications",
            "subcategory":"Radio Station",
            "type":"Services"
        }
    ],
    "sg:phone":"+1 705 544 1121",
    "sg:postcode":"P0J 1H0",
    "sg:province":"ON",
    "sg:tags":[
        "company",
        "broadcasting"
    ],
    "wof:name":"Cjbb",
    "wof:placetype":"venue"
},
  "geometry": {"coordinates":[-79.87307,47.824692],"type":"Point"}
}