{
  "type": "Feature",
  "properties": {
    "iso:country":"CA",
    "sg:address":"1017 Wilson Ave #105",
    "sg:city":"North York",
    "sg:classifiers":[
        {
            "category":"Health Services",
            "subcategory":"Medical Lab",
            "type":"Services"
        }
    ],
    "sg:phone":"+1 416 398 1671",
    "sg:postcode":"M3K 1Z1",
    "sg:province":"ON",
    "sg:tags":[
        "laboratory"
    ],
    "wof:name":"Canadian Medical Laboratories",
    "wof:placetype":"venue"
},
  "geometry": {"coordinates":[-79.47808074949999,43.7279663086],"type":"Point"}
}