{
  "type": "Feature",
  "properties": {
    "addr:full":"RR 1 Barrington NS B0W 1E0",
    "addr:postcode":"b0w 1e0",
    "addr:street":"Rr 1",
    "iso:country":"CA",
    "sg:address":"RR 1",
    "sg:city":"Barrington",
    "sg:classifiers":[
        {
            "category":"Wholesale",
            "subcategory":"Seafood",
            "type":"Manufacturing & Wholesale Goods"
        }
    ],
    "sg:phone":"+1 902 637 3142",
    "sg:postcode":"B0W 1E0",
    "sg:province":"NS",
    "wof:name":"L G Swim Fisheries Ltd",
    "wof:placetype":"venue"
},
  "geometry": {"coordinates":[-65.563225,43.563828],"type":"Point"}
}