{
  "type": "Feature",
  "properties": {
    "iso:country":"CA",
    "sg:address":"15 Healey Rd",
    "sg:city":"Bolton",
    "sg:classifiers":[
        {
            "category":"Professional",
            "subcategory":"Accounting & Tax Preparation",
            "type":"Services"
        }
    ],
    "sg:phone":"+1 905 857 1635",
    "sg:postcode":"L7E 5A1",
    "sg:province":"ON",
    "sg:tags":[
        "bookkeeping",
        "general"
    ],
    "wof:name":"Celeste Accounting Svc",
    "wof:placetype":"venue"
},
  "geometry": {"coordinates":[-79.71700286870001,43.8637504578],"type":"Point"}
}