{
  "type": "Feature",
  "properties": {
    "addr:full":"442 Dundas St Woodstock ON N4S 1C1",
    "addr:housenumber":"442",
    "addr:postcode":"n4s 1c1",
    "addr:street":"Dundas St",
    "iso:country":"CA",
    "sg:address":"442 Dundas St",
    "sg:city":"Woodstock",
    "sg:classifiers":[
        {
            "category":"Banks & Credit Unions",
            "subcategory":"Bank",
            "type":"Services"
        }
    ],
    "sg:phone":"+1 519 533 1766",
    "sg:postcode":"N4S 1C1",
    "sg:province":"ON",
    "sg:tags":[
        "loan"
    ],
    "wof:name":"Canada Cash Advance",
    "wof:placetype":"venue"
},
  "geometry": {"coordinates":[-80.7584533691,43.129776001],"type":"Point"}
}