{
  "type": "Feature",
  "properties": {
    "addr:full":"Grimsby ON L3M 1R4",
    "addr:postcode":"l3m 1r4",
    "iso:country":"CA",
    "sg:city":"Grimsby",
    "sg:classifiers":[
        {
            "category":"Restaurant",
            "type":"Food & Drink"
        }
    ],
    "sg:phone":"+1 905 945 3688",
    "sg:postcode":"L3M 1R4",
    "sg:province":"ON",
    "sg:tags":[
        "delicatessen"
    ],
    "wof:name":"Dutch Shop",
    "wof:placetype":"venue"
},
  "geometry": {"coordinates":[-79.5620727539,43.1940994263],"type":"Point"}
}