{
  "type": "Feature",
  "properties": {
    "addr:full":"108 Corporate Dr Scarborough ON M1H 3H9",
    "addr:housenumber":"108",
    "addr:postcode":"m1h 3h9",
    "addr:street":"Corporate Dr",
    "iso:country":"CA",
    "sg:address":"108 Corporate Dr",
    "sg:city":"Scarborough",
    "sg:classifiers":[
        {
            "category":"Freight",
            "type":"Transportation"
        }
    ],
    "sg:phone":"+1 416 439 6667",
    "sg:postcode":"M1H 3H9",
    "sg:province":"ON",
    "sg:tags":[
        "courier"
    ],
    "wof:name":"Canadian Consolidator Svc",
    "wof:placetype":"venue"
},
  "geometry": {"coordinates":[-79.246849,43.780735],"type":"Point"}
}