{
  "type": "Feature",
  "properties": {
    "addr:full":"Winnipeg MB R2J 4H2",
    "addr:postcode":"r2j 4h2",
    "iso:country":"CA",
    "sg:city":"Winnipeg",
    "sg:classifiers":[
        {
            "category":"Wholesale",
            "subcategory":"Construction Materials",
            "type":"Manufacturing & Wholesale Goods"
        }
    ],
    "sg:phone":"+1 204 668 4900",
    "sg:postcode":"R2J 4H2",
    "sg:province":"MB",
    "sg:tags":[
        "glass",
        "fiber"
    ],
    "wof:name":"Progress Plastics & Compounds",
    "wof:placetype":"venue"
},
  "geometry": {"coordinates":[-97.04939299999999,49.884491],"type":"Point"}
}