{
  "type": "Feature",
  "properties": {
    "addr:full":"96 Lynn Lake Dr Winnipeg MB R2C 4N7",
    "addr:housenumber":"96",
    "addr:postcode":"r2c 4n7",
    "addr:street":"Lynn Lake Dr",
    "iso:country":"CA",
    "sg:address":"96 Lynn Lake Dr",
    "sg:city":"Winnipeg",
    "sg:classifiers":[
        {
            "category":"Manufacturing",
            "subcategory":"Tools & Machinery",
            "type":"Manufacturing & Wholesale Goods"
        }
    ],
    "sg:phone":"+1 204 224 0114",
    "sg:postcode":"R2C 4N7",
    "sg:province":"MB",
    "sg:tags":[
        "control"
    ],
    "wof:name":"Eascan Industrial Controls",
    "wof:placetype":"venue"
},
  "geometry": {"coordinates":[-97.014832,49.913429],"type":"Point"}
}