{
  "type": "Feature",
  "properties": {
    "addr:full":"6858 Fraser St Vancouver BC V5X 3V1",
    "addr:housenumber":"6858",
    "addr:postcode":"v5x 3v1",
    "addr:street":"Fraser St",
    "iso:country":"CA",
    "sg:address":"6858 Fraser St",
    "sg:city":"Vancouver",
    "sg:classifiers":[
        {
            "category":"Social Services",
            "subcategory":"Child Care",
            "type":"Services"
        }
    ],
    "sg:phone":"+1 604 322 5197",
    "sg:postcode":"V5X 3V1",
    "sg:province":"BC",
    "wof:name":"Montessori Children's House",
    "wof:placetype":"venue"
},
  "geometry": {"coordinates":[-123.090591,49.22229],"type":"Point"}
}