{
  "type": "Feature",
  "properties": {
    "addr:full":"Ashern MB R0C 0E0",
    "addr:postcode":"r0c 0e0",
    "iso:country":"CA",
    "sg:city":"Ashern",
    "sg:classifiers":[
        {
            "category":"Organizations",
            "subcategory":"Religious Organization",
            "type":"Services"
        }
    ],
    "sg:phone":"+1 204 768 3441",
    "sg:postcode":"R0C 0E0",
    "sg:province":"MB",
    "sg:tags":[
        "church"
    ],
    "wof:name":"Kingdom Hall of Jehovah's",
    "wof:placetype":"venue"
},
  "geometry": {"coordinates":[-98.35011299999999,51.179821],"type":"Point"}
}