{
  "type": "Feature",
  "properties": {
    "addr:full":"1040 Lansdowne St W Peterborough ON K9J 1Z9",
    "addr:housenumber":"1040",
    "addr:postcode":"k9j 1z9",
    "addr:street":"Lansdowne St W",
    "iso:country":"CA",
    "sg:address":"1040 Lansdowne St W",
    "sg:city":"Peterborough",
    "sg:classifiers":[
        {
            "category":"Shopping",
            "subcategory":"Pharmacy",
            "type":"Retail Goods"
        }
    ],
    "sg:phone":"+1 705 742 2461",
    "sg:postcode":"K9J 1Z9",
    "sg:province":"ON",
    "wof:name":"Kashyap's Pharmacy Ltd",
    "wof:placetype":"venue"
},
  "geometry": {"coordinates":[-78.345528,44.281979],"type":"Point"}
}