{
  "type": "Feature",
  "properties": {
    "addr:full":"125 Circle Dr E Saskatoon SK S7K 0T4",
    "addr:housenumber":"125",
    "addr:postcode":"s7k 0t4",
    "addr:street":"Circle Dr E",
    "iso:country":"CA",
    "sg:address":"125 Circle Dr E",
    "sg:city":"Saskatoon",
    "sg:classifiers":[
        {
            "category":"Restaurant",
            "type":"Food & Drink"
        }
    ],
    "sg:phone":"+1 306 384 7427",
    "sg:postcode":"S7K 0T4",
    "sg:province":"SK",
    "wof:name":"Tony Roma's",
    "wof:placetype":"venue"
},
  "geometry": {"coordinates":[-106.668663,52.157673],"type":"Point"}
}