{
  "type": "Feature",
  "properties": {
    "addr:full":"Creston BC V0B 1G1",
    "addr:postcode":"bc v0b 1g1",
    "iso:country":"CA",
    "sg:city":"Creston",
    "sg:classifiers":[
        {
            "category":"Health Services",
            "subcategory":"Doctor",
            "type":"Services"
        }
    ],
    "sg:phone":"+1 250 428 2533",
    "sg:postcode":"V0B 1G1",
    "sg:province":"BC",
    "sg:tags":[
        "dentist"
    ],
    "wof:name":"Hoffman, Verne DDS",
    "wof:placetype":"venue"
},
  "geometry": {"coordinates":[-116.512672424,49.0954627991],"type":"Point"}
}