{
  "type": "Feature",
  "properties": {
    "addr:full":"Mississauga ON L4V 1R5",
    "addr:postcode":"l4v 1r5",
    "iso:country":"CA",
    "sg:city":"Mississauga",
    "sg:classifiers":[
        {
            "category":"Freight",
            "type":"Transportation"
        }
    ],
    "sg:phone":"+1 905 672 1108",
    "sg:postcode":"L4V 1R5",
    "sg:province":"ON",
    "wof:name":"K C Intl Forwarding CO",
    "wof:placetype":"venue"
},
  "geometry": {"coordinates":[-79.625793457,43.698890686],"type":"Point"}
}