{
  "type": "Feature",
  "properties": {
    "addr:full":"2750 Dufferin St North York ON M6B 3R4",
    "addr:housenumber":"2750",
    "addr:postcode":"m6b 3r4",
    "addr:street":"Dufferin St",
    "iso:country":"CA",
    "sg:address":"2750 Dufferin St",
    "sg:city":"North York",
    "sg:classifiers":[
        {
            "category":"Social Services",
            "type":"Services"
        }
    ],
    "sg:phone":"+1 416 789 7859",
    "sg:postcode":"M6B 3R4",
    "sg:province":"ON",
    "sg:tags":[
        "organization",
        "welfare"
    ],
    "wof:name":"Big Brothers Big Sisters",
    "wof:placetype":"venue"
},
  "geometry": {"coordinates":[-79.4525146484,43.7032737732],"type":"Point"}
}