{
  "type": "Feature",
  "properties": {
    "addr:full":"Calgary AB T2E 7G6",
    "addr:postcode":"t2e 7g6",
    "iso:country":"CA",
    "sg:city":"Calgary",
    "sg:classifiers":[
        {
            "category":"Professional",
            "subcategory":"Employment Agencies",
            "type":"Services"
        }
    ],
    "sg:phone":"+1 403 291 4877",
    "sg:postcode":"T2E 7G6",
    "sg:province":"AB",
    "sg:tags":[
        "modeling"
    ],
    "wof:name":"Arienne 7",
    "wof:placetype":"venue"
},
  "geometry": {"coordinates":[-114.015137,51.096996],"type":"Point"}
}