{
  "type": "Feature",
  "properties": {
    "addr:full":"2000 Thurston Dr #3 Ottawa ON K1G 4K7",
    "addr:housenumber":"2000",
    "addr:postcode":"k1g 4k7",
    "addr:street":"Thurston Dr # 3",
    "iso:country":"CA",
    "sg:address":"2000 Thurston Dr #3",
    "sg:city":"Ottawa",
    "sg:classifiers":[
        {
            "category":"Shopping",
            "subcategory":"Florist",
            "type":"Retail Goods"
        }
    ],
    "sg:phone":"+1 613 737 5555",
    "sg:postcode":"K1G 4K7",
    "sg:province":"ON",
    "wof:name":"Sunshine Florists Ltd",
    "wof:placetype":"venue"
},
  "geometry": {"coordinates":[-75.6234054565,45.3786888123],"type":"Point"}
}