{
  "type": "Feature",
  "properties": {
    "addr:full":"1970 Spicer Rd North Vancouver BC V7H 1A2",
    "addr:housenumber":"1970",
    "addr:postcode":"v7h 1a2",
    "addr:street":"Spicer Rd",
    "iso:country":"CA",
    "sg:address":"1970 Spicer Rd",
    "sg:city":"North Vancouver",
    "sg:classifiers":[
        {
            "category":"Restaurant",
            "type":"Food & Drink"
        }
    ],
    "sg:phone":"+1 604 924 1834",
    "sg:postcode":"V7H 1A2",
    "sg:province":"BC",
    "sg:tags":[
        "pub"
    ],
    "wof:name":"Maplewood Pub",
    "wof:placetype":"venue"
},
  "geometry": {"coordinates":[-123.018967,49.303864],"type":"Point"}
}