{
  "type": "Feature",
  "properties": {
    "addr:full":"515 Vernon St Nelson BC V1L 4E9",
    "addr:housenumber":"515",
    "addr:postcode":"bc v1l 4e9",
    "addr:street":"Vernon St",
    "iso:country":"CA",
    "sg:address":"515 Vernon St",
    "sg:city":"Nelson",
    "sg:classifiers":[
        {
            "category":"Banks & Credit Unions",
            "subcategory":"Investment Brokerage",
            "type":"Services"
        }
    ],
    "sg:phone":"+1 250 352 7777",
    "sg:postcode":"V1L 4E9",
    "sg:province":"BC",
    "wof:name":"Investors Group Financial Svc",
    "wof:placetype":"venue"
},
  "geometry": {"coordinates":[-117.29454,49.49308],"type":"Point"}
}