{
  "type": "Feature",
  "properties": {
    "addr:full":"1071 Granville St Vancouver BC V6Z 1L4",
    "addr:housenumber":"1071",
    "addr:postcode":"v6z 1l4",
    "addr:street":"Granville St",
    "iso:country":"CA",
    "sg:address":"1071 Granville St",
    "sg:city":"Vancouver",
    "sg:classifiers":[
        {
            "category":"Retail",
            "subcategory":"Laundry & Dry Cleaning",
            "type":"Services"
        }
    ],
    "sg:phone":"+1 604 684 6917",
    "sg:postcode":"V6Z 1L4",
    "sg:province":"BC",
    "sg:tags":[
        "cleaners"
    ],
    "wof:name":"Frank Cleaners",
    "wof:placetype":"venue"
},
  "geometry": {"coordinates":[-123.12421417199999,49.2786903381],"type":"Point"}
}