{
  "type": "Feature",
  "properties": {
    "addr:full":"319 1st St E Stonewall MB R0C 2Z0",
    "addr:housenumber":"319",
    "addr:postcode":"r0c 2z0",
    "addr:street":"1St St E",
    "iso:country":"CA",
    "sg:address":"319 1st St E",
    "sg:city":"Stonewall",
    "sg:classifiers":[
        {
            "category":"Cinema",
            "subcategory":"Movie Theater",
            "type":"Entertainment"
        }
    ],
    "sg:phone":"+1 204 467 8401",
    "sg:postcode":"R0C 2Z0",
    "sg:province":"MB",
    "wof:name":"Flicks Cinema",
    "wof:placetype":"venue"
},
  "geometry": {"coordinates":[-97.32530199999999,50.133991],"type":"Point"}
}