{
  "type": "Feature",
  "properties": {
    "addr:full":"908 8 Ave SW Calgary AB T2P 1H8",
    "addr:housenumber":"908",
    "addr:postcode":"t2p 1h8",
    "addr:street":"8 Ave Sw",
    "iso:country":"CA",
    "sg:address":"908 8 Ave SW",
    "sg:city":"Calgary",
    "sg:classifiers":[
        {
            "category":"Restaurant",
            "type":"Food & Drink"
        }
    ],
    "sg:phone":"+1 403 264 1355",
    "sg:postcode":"T2P 1H8",
    "sg:province":"AB",
    "sg:tags":[
        "shop",
        "coffee"
    ],
    "wof:name":"Grind Cappucino & Deli Inc",
    "wof:placetype":"venue"
},
  "geometry": {"coordinates":[-114.081665,51.046211],"type":"Point"}
}