{
  "type": "Feature",
  "properties": {
    "addr:full":"842 15th St W North Vancouver BC V7P 1M6",
    "addr:housenumber":"842",
    "addr:postcode":"v7p 1m6",
    "addr:street":"15Th St W",
    "iso:country":"CA",
    "sg:address":"842 15th St W",
    "sg:city":"North Vancouver",
    "sg:classifiers":[
        {
            "category":"Recreation",
            "type":"Entertainment"
        }
    ],
    "sg:phone":"+1 604 904 9216",
    "sg:postcode":"V7P 1M6",
    "sg:province":"BC",
    "sg:tags":[
        "martial",
        "arts",
        "instruction"
    ],
    "wof:name":"North Shore Shotokan Karate",
    "wof:placetype":"venue"
},
  "geometry": {"coordinates":[-123.09575700000001,49.322422],"type":"Point"}
}