{
  "type": "Feature",
  "properties": {
    "addr:full":"Gloucester ON K1B 3L9",
    "addr:postcode":"k1b 3l9",
    "iso:country":"CA",
    "sg:city":"Gloucester",
    "sg:classifiers":[
        {
            "category":"Wholesale",
            "subcategory":"Chemicals & Plastics",
            "type":"Manufacturing & Wholesale Goods"
        }
    ],
    "sg:phone":"+1 613 744 8896",
    "sg:postcode":"K1B 3L9",
    "sg:province":"ON",
    "sg:tags":[
        "cleaning",
        "compound"
    ],
    "wof:name":"Bsc Inc",
    "wof:placetype":"venue"
},
  "geometry": {"coordinates":[-75.61822509770001,45.4202728271],"type":"Point"}
}