{
  "type": "Feature",
  "properties": {
    "addr:full":"732 Marine Dr North Vancouver BC V7M 1H3",
    "addr:housenumber":"732",
    "addr:postcode":"v7m 1h3",
    "addr:street":"Marine Dr",
    "iso:country":"CA",
    "sg:address":"732 Marine Dr",
    "sg:city":"North Vancouver",
    "sg:classifiers":[
        {
            "category":"Manufacturing",
            "subcategory":"Food",
            "type":"Manufacturing & Wholesale Goods"
        }
    ],
    "sg:phone":"+1 604 987 8198",
    "sg:postcode":"V7M 1H3",
    "sg:province":"BC",
    "sg:tags":[
        "environmental",
        "ecological",
        "product",
        "manufacturer"
    ],
    "wof:name":"Emx Technologies Canada Inc",
    "wof:placetype":"venue"
},
  "geometry": {"coordinates":[-123.093903,49.321072],"type":"Point"}
}