{
  "type": "Feature",
  "properties": {
    "addr:full":"202 Cobden St Sarnia ON N7T 3Z8",
    "addr:housenumber":"202",
    "addr:postcode":"n7t 3z8",
    "addr:street":"Cobden St",
    "iso:country":"CA",
    "sg:address":"202 Cobden St",
    "sg:city":"Sarnia",
    "sg:classifiers":[
        {
            "category":"Organizations",
            "subcategory":"Religious Organization",
            "type":"Services"
        }
    ],
    "sg:phone":"+1 519 337 9281",
    "sg:postcode":"N7T 3Z8",
    "sg:province":"ON",
    "sg:tags":[
        "synagogue"
    ],
    "wof:name":"Isaac Ahavas Synagogue",
    "wof:placetype":"venue"
},
  "geometry": {"coordinates":[-82.39608800000001,42.972233],"type":"Point"}
}