{
  "type": "Feature",
  "properties": {
    "addr:full":"2 Summerfield Ave Stoney Creek ON L8J 3S1",
    "addr:housenumber":"2",
    "addr:postcode":"l8j 3s1",
    "addr:street":"Summerfield Ave",
    "iso:country":"CA",
    "sg:address":"2 Summerfield Ave",
    "sg:city":"Stoney Creek",
    "sg:classifiers":[
        {
            "category":"Home & Garden",
            "subcategory":"Building Materials",
            "type":"Retail Goods"
        }
    ],
    "sg:phone":"+1 905 560 2015",
    "sg:postcode":"L8J 3S1",
    "sg:province":"ON",
    "sg:tags":[
        "type",
        "door"
    ],
    "wof:name":"Mr Overhead Doors Inc",
    "wof:placetype":"venue"
},
  "geometry": {"coordinates":[-79.78739899999999,43.182873],"type":"Point"}
}