{
  "type": "Feature",
  "properties": {
    "iso:country":"CA",
    "sg:city":"Ottawa",
    "sg:classifiers":[
        {
            "category":"Shopping",
            "subcategory":"Pharmacy",
            "type":"Retail Goods"
        }
    ],
    "sg:phone":"+1 613 741 3660",
    "sg:postcode":"K1K 4L3",
    "sg:province":"ON",
    "wof:name":"Montreal Road Pharmacy",
    "wof:placetype":"venue"
},
  "geometry": {"coordinates":[-75.630577,45.446167],"type":"Point"}
}