{
  "type": "Feature",
  "properties": {
    "iso:country":"CA",
    "sg:address":"828 3rd Ave E",
    "sg:city":"Owen Sound",
    "sg:classifiers":[
        {
            "category":"Retail",
            "subcategory":"Repair Shop",
            "type":"Services"
        }
    ],
    "sg:phone":"+1 519 371 7710",
    "sg:postcode":"N4K 2K5",
    "sg:province":"ON",
    "sg:tags":[
        "equipment",
        "electronic",
        "supply"
    ],
    "wof:name":"Taylor Electronic Svc Inc",
    "wof:placetype":"venue"
},
  "geometry": {"coordinates":[-80.94086456300001,44.5647392273],"type":"Point"}
}