{
  "type": "Feature",
  "properties": {
    "iso:country":"CA",
    "sg:address":"71 Bridge St",
    "sg:city":"Almonte",
    "sg:classifiers":[
        {
            "category":"Retail",
            "subcategory":"Auto Repair",
            "type":"Services"
        }
    ],
    "sg:phone":"+1 613 256 1101",
    "sg:postcode":"K0A 1A0",
    "sg:province":"ON",
    "sg:tags":[
        "repairing",
        "automobile"
    ],
    "wof:name":"H B Auto Svc",
    "wof:placetype":"venue"
},
  "geometry": {"coordinates":[-76.19427490229999,45.2247009277],"type":"Point"}
}