{
  "type": "Feature",
  "properties": {
    "addr:full":"259 Rue Principale Grenville QC J0V 1J0",
    "addr:housenumber":"259",
    "addr:postcode":"j0v 1j0",
    "addr:street":"Rue Principale",
    "iso:country":"CA",
    "sg:address":"259 Rue Principale",
    "sg:city":"Grenville",
    "sg:classifiers":[
        {
            "category":"Wholesale",
            "subcategory":"Meat",
            "type":"Manufacturing & Wholesale Goods"
        }
    ],
    "sg:phone":"+1 819 242 2662",
    "sg:postcode":"J0V 1J0",
    "sg:province":"QC",
    "sg:tags":[
        "grocer",
        "butchering"
    ],
    "wof:name":"Boucherie Lemay",
    "wof:placetype":"venue"
},
  "geometry": {"coordinates":[-74.6031265259,45.6287231445],"type":"Point"}
}