{
  "type": "Feature",
  "properties": {
    "addr:full":"3650 Langstaff Rd Woodbridge ON L4L 9A8",
    "addr:housenumber":"3650",
    "addr:postcode":"l4l 9a8",
    "addr:street":"Langstaff Rd",
    "iso:country":"CA",
    "sg:address":"3650 Langstaff Rd",
    "sg:city":"Woodbridge",
    "sg:classifiers":[
        {
            "category":"Wholesale",
            "subcategory":"Meat",
            "type":"Manufacturing & Wholesale Goods"
        }
    ],
    "sg:phone":"+1 905 265 9994",
    "sg:postcode":"L4L 9A8",
    "sg:province":"ON",
    "sg:tags":[
        "butchering"
    ],
    "wof:name":"Riviera Meat CO",
    "wof:placetype":"venue"
},
  "geometry": {"coordinates":[-79.54922485349999,43.8084907532],"type":"Point"}
}