{
  "type": "Feature",
  "properties": {
    "addr:full":"169 Main St Dartmouth NS B2X 1S1",
    "addr:housenumber":"169",
    "addr:postcode":"b2x 1s1",
    "addr:street":"Main St",
    "iso:country":"CA",
    "sg:address":"169 Main St",
    "sg:city":"Dartmouth",
    "sg:classifiers":[
        {
            "category":"Shopping",
            "subcategory":"Computers & Home Electronics",
            "type":"Retail Goods"
        }
    ],
    "sg:phone":"+1 902 434 8306",
    "sg:postcode":"B2X 1S1",
    "sg:province":"NS",
    "sg:tags":[
        "radio",
        "television",
        "video",
        "equipment"
    ],
    "wof:name":"E P Blighs Television",
    "wof:placetype":"venue"
},
  "geometry": {"coordinates":[-63.520981,44.686321],"type":"Point"}
}