{
  "type": "Feature",
  "properties": {
    "iso:country":"CA",
    "sg:city":"Winnipeg",
    "sg:classifiers":[
        {
            "category":"Professional",
            "subcategory":"Engineering",
            "type":"Services"
        }
    ],
    "sg:phone":"+1 204 831 0351",
    "sg:postcode":"R3J 1N6",
    "sg:province":"MB",
    "sg:tags":[
        "engineer"
    ],
    "wof:name":"Mesh Technologies Inc",
    "wof:placetype":"venue"
},
  "geometry": {"coordinates":[-97.21035766599999,49.8879051208],"type":"Point"}
}