{
  "type": "Feature",
  "properties": {
    "addr:full":"Rock Forest QC J1N 1T1",
    "addr:postcode":"j1n 1t1",
    "iso:country":"CA",
    "sg:city":"Rock Forest",
    "sg:classifiers":[
        {
            "category":"Building & Trades",
            "subcategory":"Construction",
            "type":"Services"
        }
    ],
    "sg:phone":"+1 819 563 0229",
    "sg:postcode":"J1N 1T1",
    "sg:province":"QC",
    "sg:tags":[
        "foundation",
        "concrete",
        "contractor"
    ],
    "wof:name":"Construction Michel Constant",
    "wof:placetype":"venue"
},
  "geometry": {"coordinates":[-71.988281,45.371315],"type":"Point"}
}