{
  "type": "Feature",
  "properties": {
    "addr:full":"Jarvis ON N0A 1J0",
    "addr:postcode":"n0a 1j0",
    "iso:country":"CA",
    "sg:city":"Jarvis",
    "sg:classifiers":[
        {
            "category":"Mining & Drilling",
            "type":"Manufacturing & Wholesale Goods"
        }
    ],
    "sg:phone":"+1 519 587 9997",
    "sg:postcode":"N0A 1J0",
    "sg:province":"ON",
    "sg:tags":[
        "stone"
    ],
    "wof:name":"Canadian Slag Svc Inc",
    "wof:placetype":"venue"
},
  "geometry": {"coordinates":[-80.1136856079,42.8851127625],"type":"Point"}
}