{
  "type": "Feature",
  "properties": {
    "addr:full":"5595 Boul DE Maisonneuve O Montreal QC H4A 1Z8",
    "addr:housenumber":"5595",
    "addr:postcode":"h4a 1z8",
    "addr:street":"Boul De Maisonneuve O",
    "iso:country":"CA",
    "sg:address":"5595 Boul DE Maisonneuve O",
    "sg:city":"Montreal",
    "sg:classifiers":[
        {
            "category":"Building & Trades",
            "subcategory":"Electrical",
            "type":"Services"
        }
    ],
    "sg:phone":"+1 514 485 1911",
    "sg:postcode":"H4A 1Z8",
    "sg:province":"QC",
    "sg:tags":[
        "electric",
        "contractor"
    ],
    "wof:name":"Savi Electrique Inc",
    "wof:placetype":"venue"
},
  "geometry": {"coordinates":[-73.6103439331,45.4703330994],"type":"Point"}
}