{
  "type": "Feature",
  "properties": {
    "addr:full":"3 Elmwood Pl Prince Albert SK S6V 7Z3",
    "addr:housenumber":"3",
    "addr:postcode":"s6v 7z3",
    "addr:street":"Elmwood Pl",
    "iso:country":"CA",
    "sg:address":"3 Elmwood Pl",
    "sg:city":"Prince Albert",
    "sg:classifiers":[
        {
            "category":"Social Services",
            "type":"Services"
        }
    ],
    "sg:phone":"+1 306 922 4454",
    "sg:postcode":"S6V 7Z3",
    "sg:province":"SK",
    "sg:tags":[
        "crisis",
        "center"
    ],
    "wof:name":"Children's Haven",
    "wof:placetype":"venue"
},
  "geometry": {"coordinates":[-105.74822998,53.1840209961],"type":"Point"}
}