{
  "type": "Feature",
  "properties": {
    "addr:full":"PO Box 577 STN Main Brooks AB T1R 1B5",
    "addr:housenumber":"po",
    "addr:postcode":"ab t1r 1b5",
    "addr:street":"Box 577 Stn Main Brooks",
    "iso:country":"CA",
    "sg:address":"PO Box 577 STN Main",
    "sg:city":"Brooks",
    "sg:classifiers":[
        {
            "category":"Mining & Drilling",
            "type":"Manufacturing & Wholesale Goods"
        }
    ],
    "sg:phone":"+1 403 362 4266",
    "sg:postcode":"T1R 1B5",
    "sg:province":"AB",
    "sg:tags":[
        "field",
        "oil"
    ],
    "wof:name":"New Alta Corp",
    "wof:placetype":"venue"
},
  "geometry": {"coordinates":[-111.89849090600001,50.5658531189],"type":"Point"}
}