{
  "type": "Feature",
  "properties": {
    "addr:full":"59 Dalhousie St Brantford ON N3T 2J1",
    "addr:housenumber":"59",
    "addr:postcode":"n3t 2j1",
    "addr:street":"Dalhousie St",
    "iso:country":"CA",
    "sg:address":"59 Dalhousie St",
    "sg:city":"Brantford",
    "sg:classifiers":[
        {
            "category":"Shopping",
            "subcategory":"Shoes",
            "type":"Retail Goods"
        }
    ],
    "sg:phone":"+1 519 759 7463",
    "sg:postcode":"N3T 2J1",
    "sg:province":"ON",
    "wof:name":"Al's Shoe Factory Outlet",
    "wof:placetype":"venue"
},
  "geometry": {"coordinates":[-80.265404,43.139145],"type":"Point"}
}