{
  "type": "Feature",
  "properties": {
    "addr:full":"1231 16 St NE Salmon Arm BC V1E 2V2",
    "addr:housenumber":"1231",
    "addr:postcode":"v1e 2v2",
    "addr:street":"16 St Ne",
    "iso:country":"CA",
    "sg:address":"1231 16 St NE",
    "sg:city":"Salmon Arm",
    "sg:classifiers":[
        {
            "category":"Building & Trades",
            "subcategory":"Plumbing",
            "type":"Services"
        }
    ],
    "sg:phone":"+1 250 832 3083",
    "sg:postcode":"V1E 2V2",
    "sg:province":"BC",
    "sg:tags":[
        "air",
        "conditioning",
        "contractor",
        "system",
        "heating"
    ],
    "wof:name":"H Norman Morris Heating & Ac",
    "wof:placetype":"venue"
},
  "geometry": {"coordinates":[-119.267174,50.709679],"type":"Point"}
}