{
  "type": "Feature",
  "properties": {
    "iso:country":"CA",
    "sg:address":"74 Colborne St W",
    "sg:city":"Orillia",
    "sg:classifiers":[
        {
            "category":"Retail",
            "subcategory":"Auto Repair",
            "type":"Services"
        }
    ],
    "sg:phone":"+1 705 325 6633",
    "sg:postcode":"L3V 2Y7",
    "sg:province":"ON",
    "sg:tags":[
        "repairing",
        "automobile",
        "radiator"
    ],
    "wof:name":"Rad Shop",
    "wof:placetype":"venue"
},
  "geometry": {"coordinates":[-79.4216384888,44.6061058044],"type":"Point"}
}