{
  "type": "Feature",
  "properties": {
    "iso:country":"CA",
    "sg:address":"2780 Mckay Ave",
    "sg:city":"Windsor",
    "sg:classifiers":[
        {
            "category":"Building & Trades",
            "subcategory":"Cleaning & Sanitation",
            "type":"Services"
        }
    ],
    "sg:phone":"+1 519 966 2640",
    "sg:postcode":"N9E 2P6",
    "sg:province":"ON",
    "sg:tags":[
        "janitor"
    ],
    "wof:name":"Hilda's Janitorial Svc & Supls",
    "wof:placetype":"venue"
},
  "geometry": {"coordinates":[-83.0288238525,42.2713546753],"type":"Point"}
}