{
  "type": "Feature",
  "properties": {
    "addr:full":"Scarborough ON M1V 2R4",
    "addr:postcode":"m1v 2r4",
    "iso:country":"CA",
    "sg:city":"Scarborough",
    "sg:classifiers":[
        {
            "category":"Wholesale",
            "subcategory":"Groceries",
            "type":"Manufacturing & Wholesale Goods"
        }
    ],
    "sg:phone":"+1 416 292 1230",
    "sg:postcode":"M1V 2R4",
    "sg:province":"ON",
    "sg:tags":[
        "grocer"
    ],
    "wof:name":"Kingsdale Trading CO Ltd",
    "wof:placetype":"venue"
},
  "geometry": {"coordinates":[-79.29611206049999,43.8061752319],"type":"Point"}
}