{
  "type": "Feature",
  "properties": {
    "iso:country":"CA",
    "sg:city":"York",
    "sg:classifiers":[
        {
            "category":"Personal",
            "subcategory":"Beauty Salon",
            "type":"Services"
        }
    ],
    "sg:phone":"+1 416 245 4241",
    "sg:postcode":"M6M 4R3",
    "sg:province":"ON",
    "wof:name":"Ner's Beauty Salon",
    "wof:placetype":"venue"
},
  "geometry": {"coordinates":[-79.49523925779999,43.6889152527],"type":"Point"}
}