{
  "type": "Feature",
  "properties": {
    "addr:full":"693 Rue Saint-Alphonse O Thetford Mines QC G6G 3X3",
    "addr:housenumber":"693",
    "addr:postcode":"g6g 3x3",
    "addr:street":"Rue Saint-Alphonse O",
    "iso:country":"CA",
    "sg:address":"693 Rue Saint-Alphonse O",
    "sg:city":"Thetford Mines",
    "sg:classifiers":[
        {
            "category":"Organizations",
            "subcategory":"Non-profit Organization",
            "type":"Services"
        }
    ],
    "sg:phone":"+1 418 338 5656",
    "sg:postcode":"G6G 3X3",
    "sg:province":"QC",
    "sg:tags":[
        "handicapped"
    ],
    "wof:name":"Semo Chaudiere-Appalaches",
    "wof:placetype":"venue"
},
  "geometry": {"coordinates":[-71.291061,46.083637],"type":"Point"}
}