{
  "type": "Feature",
  "properties": {
    "iso:country":"CA",
    "sg:city":"Winnipeg",
    "sg:classifiers":[
        {
            "category":"Real Estate",
            "subcategory":"Real Estate Agent",
            "type":"Services"
        }
    ],
    "sg:phone":"+1 204 339 1661",
    "sg:postcode":"R2V 1Z8",
    "sg:province":"MB",
    "wof:name":"Key-Move Realty Ltd",
    "wof:placetype":"venue"
},
  "geometry": {"coordinates":[-97.11743927000001,49.9365119934],"type":"Point"}
}