{
  "type": "Feature",
  "properties": {
    "addr:full":"9889 River Rd Delta BC V4G 1B4",
    "addr:housenumber":"9889",
    "addr:postcode":"v4g 1b4",
    "addr:street":"River Rd",
    "iso:country":"CA",
    "sg:address":"9889 River Rd",
    "sg:city":"Delta",
    "sg:classifiers":[
        {
            "category":"Building & Trades",
            "subcategory":"Construction",
            "type":"Services"
        }
    ],
    "sg:phone":"+1 604 588 1448",
    "sg:postcode":"V4G 1B4",
    "sg:province":"BC",
    "sg:tags":[
        "general",
        "contractor"
    ],
    "wof:name":"Mgm Construction",
    "wof:placetype":"venue"
},
  "geometry": {"coordinates":[-122.953232,49.152668],"type":"Point"}
}