{
  "type": "Feature",
  "properties": {
    "addr:full":"159 Main St Toronto ON M4E 2V9",
    "addr:housenumber":"159",
    "addr:postcode":"m4e 2v9",
    "addr:street":"Main St",
    "iso:country":"CA",
    "sg:address":"159 Main St",
    "sg:city":"Toronto",
    "sg:classifiers":[
        {
            "category":"Food & Beverages",
            "subcategory":"Bakery",
            "type":"Retail Goods"
        }
    ],
    "sg:phone":"+1 416 699 4323",
    "sg:postcode":"M4E 2V9",
    "sg:province":"ON",
    "sg:tags":[
        "doughnut"
    ],
    "wof:name":"Premier Deli & Donuts",
    "wof:placetype":"venue"
},
  "geometry": {"coordinates":[-79.299835,43.683571],"type":"Point"}
}