{
  "type": "Feature",
  "properties": {
    "iso:country":"CA",
    "sg:address":"35 Plank Rd",
    "sg:city":"Straffordville",
    "sg:classifiers":[
        {
            "category":"Organizations",
            "subcategory":"Religious Organization",
            "type":"Services"
        }
    ],
    "sg:phone":"+1 519 866 5585",
    "sg:postcode":"N0J 1Y0",
    "sg:province":"ON",
    "sg:tags":[
        "church"
    ],
    "wof:name":"Mission Baptist Church",
    "wof:placetype":"venue"
},
  "geometry": {"coordinates":[-80.7834472656,42.7287902832],"type":"Point"}
}