{
  "type": "Feature",
  "properties": {
    "addr:full":"91 Friuli Crt # 13 Woodbridge ON L4L 7H2",
    "addr:housenumber":"91",
    "addr:postcode":"l4l 7h2",
    "addr:street":"Friuli Crt # 13",
    "iso:country":"CA",
    "sg:address":"91 Friuli Crt # 13",
    "sg:city":"Woodbridge",
    "sg:classifiers":[
        {
            "category":"Education",
            "subcategory":"Special Training",
            "type":"Public Place"
        }
    ],
    "sg:phone":"+1 905 265 2665",
    "sg:postcode":"L4L 7H2",
    "sg:province":"ON",
    "sg:tags":[
        "school"
    ],
    "wof:name":"Culinary Studio 2000",
    "wof:placetype":"venue"
},
  "geometry": {"coordinates":[-79.57312,43.765678],"type":"Point"}
}