{
  "type": "Feature",
  "properties": {
    "addr:full":"720 Rue Trotter Saint-Jean-Sur-Richelieu QC J3B 8T2",
    "addr:housenumber":"720",
    "addr:postcode":"j3b 8t2",
    "addr:street":"Rue Trotter",
    "iso:country":"CA",
    "sg:address":"720 Rue Trotter",
    "sg:city":"Saint-Jean-Sur-Richelieu",
    "sg:classifiers":[
        {
            "category":"Local Transit",
            "type":"Transportation"
        }
    ],
    "sg:phone":"+1 450 460 2000",
    "sg:postcode":"J3B 8T2",
    "sg:province":"QC",
    "sg:tags":[
        "handicapped",
        "bus",
        "line"
    ],
    "wof:name":"Handi-Bus",
    "wof:placetype":"venue"
},
  "geometry": {"coordinates":[-73.288177,45.321129],"type":"Point"}
}