{
  "type": "Feature",
  "properties": {
    "iso:country":"CA",
    "sg:address":"1224 King St W",
    "sg:city":"Toronto",
    "sg:classifiers":[
        {
            "category":"Health Services",
            "subcategory":"Doctor",
            "type":"Services"
        }
    ],
    "sg:phone":"+1 416 537 7564",
    "sg:postcode":"M6K 1G4",
    "sg:province":"ON",
    "sg:tags":[
        "dentist"
    ],
    "wof:name":"Nguyen, Thuy DDS",
    "wof:placetype":"venue"
},
  "geometry": {"coordinates":[-79.4282989502,43.6388931274],"type":"Point"}
}