{
  "type": "Feature",
  "properties": {
    "addr:full":"Grand Bend ON N0M 1T0",
    "addr:postcode":"n0m 1t0",
    "iso:country":"CA",
    "sg:city":"Grand Bend",
    "sg:classifiers":[
        {
            "category":"Shopping",
            "subcategory":"Gifts & Souvenirs",
            "type":"Retail Goods"
        }
    ],
    "sg:phone":"+1 519 238 6883",
    "sg:postcode":"N0M 1T0",
    "sg:province":"ON",
    "sg:tags":[
        "shop"
    ],
    "wof:name":"Sea Jewels",
    "wof:placetype":"venue"
},
  "geometry": {"coordinates":[-81.75653076170001,43.3124732971],"type":"Point"}
}