{
  "type": "Feature",
  "properties": {
    "addr:full":"170 Sentinel Rd North York ON M3J 1T5",
    "addr:housenumber":"170",
    "addr:postcode":"m3j 1t5",
    "addr:street":"Sentinel Rd",
    "iso:country":"CA",
    "sg:address":"170 Sentinel Rd",
    "sg:city":"North York",
    "sg:classifiers":[
        {
            "category":"Manufacturing",
            "subcategory":"Tools & Machinery",
            "type":"Manufacturing & Wholesale Goods"
        }
    ],
    "sg:phone":"+1 416 398 7135",
    "sg:postcode":"M3J 1T5",
    "sg:province":"ON",
    "sg:tags":[
        "mold"
    ],
    "wof:name":"Watkins Group",
    "wof:placetype":"venue"
},
  "geometry": {"coordinates":[-79.49718475340001,43.7518692017],"type":"Point"}
}