{
  "type": "Feature",
  "properties": {
    "addr:full":"10617 172 St NW Edmonton AB T5S 1P1",
    "addr:housenumber":"10617",
    "addr:postcode":"t5s 1p1",
    "addr:street":"172 St Nw",
    "iso:country":"CA",
    "sg:address":"10617 172 St NW",
    "sg:city":"Edmonton",
    "sg:classifiers":[
        {
            "category":"Building & Trades",
            "subcategory":"Construction",
            "type":"Services"
        }
    ],
    "sg:phone":"+1 780 444 2900",
    "sg:postcode":"T5S 1P1",
    "sg:province":"AB",
    "sg:tags":[
        "elevator"
    ],
    "wof:name":"Otis Canada Inc",
    "wof:placetype":"venue"
},
  "geometry": {"coordinates":[-113.617660523,53.5510101318],"type":"Point"}
}