{
  "type": "Feature",
  "properties": {
    "addr:full":"Carleton Place ON K7C 2T7",
    "addr:postcode":"k7c 2t7",
    "iso:country":"CA",
    "sg:city":"Carleton Place",
    "sg:classifiers":[
        {
            "category":"Government",
            "subcategory":"Office",
            "type":"Public Place"
        }
    ],
    "sg:phone":"+1 613 253 1171",
    "sg:postcode":"K7C 2T7",
    "sg:province":"ON",
    "sg:tags":[
        "organization",
        "political"
    ],
    "wof:name":"Sterling, Norman",
    "wof:placetype":"venue"
},
  "geometry": {"coordinates":[-76.139541626,45.1344909668],"type":"Point"}
}