{
  "type": "Feature",
  "properties": {
    "addr:full":"615 Yonge St Toronto ON M4Y 1Z5",
    "addr:housenumber":"615",
    "addr:postcode":"m4y 1z5",
    "addr:street":"Yonge St",
    "iso:country":"CA",
    "sg:address":"615 Yonge St",
    "sg:city":"Toronto",
    "sg:classifiers":[
        {
            "category":"Real Estate",
            "subcategory":"Architect",
            "type":"Services"
        }
    ],
    "sg:phone":"+1 416 928 0849",
    "sg:postcode":"M4Y 1Z5",
    "sg:province":"ON",
    "sg:tags":[
        "illustrator",
        "architectural"
    ],
    "wof:name":"Martin Myers Design Conslnt",
    "wof:placetype":"venue"
},
  "geometry": {"coordinates":[-79.385269165,43.6670875549],"type":"Point"}
}