{
  "type": "Feature",
  "properties": {
    "addr:full":"2723 Av DE LA Montagne Shawinigan QC G9N 6K4",
    "addr:housenumber":"2723",
    "addr:postcode":"g9n 6k4",
    "addr:street":"Av De La Montagne",
    "iso:country":"CA",
    "sg:address":"2723 Av DE LA Montagne",
    "sg:city":"Shawinigan",
    "sg:classifiers":[
        {
            "category":"Home & Garden",
            "subcategory":"Furniture",
            "type":"Retail Goods"
        }
    ],
    "sg:phone":"+1 819 539 5454",
    "sg:postcode":"G9N 6K4",
    "sg:province":"QC",
    "wof:name":"Houle & Fils Ltee",
    "wof:placetype":"venue"
},
  "geometry": {"coordinates":[-72.75975,46.574455],"type":"Point"}
}