{
  "type": "Feature",
  "properties": {
    "iso:country":"CA",
    "sg:city":"Montreal",
    "sg:classifiers":[
        {
            "category":"Manufacturing",
            "subcategory":"Apparel",
            "type":"Manufacturing & Wholesale Goods"
        }
    ],
    "sg:phone":"+1 514 387 7145",
    "sg:postcode":"H2N 1C8",
    "sg:province":"QC",
    "sg:tags":[
        "underwear"
    ],
    "wof:name":"Yves Martin Sous-Vetements Inc",
    "wof:placetype":"venue"
},
  "geometry": {"coordinates":[-73.6526184082,45.5421295166],"type":"Point"}
}