{
  "type": "Feature",
  "properties": {
    "addr:full":"Red Deer AB T4N 1X2",
    "addr:postcode":"t4n 1x2",
    "iso:country":"CA",
    "sg:city":"Red Deer",
    "sg:classifiers":[
        {
            "category":"Organizations",
            "subcategory":"Professional Association",
            "type":"Services"
        }
    ],
    "sg:phone":"+1 403 347 3662",
    "sg:postcode":"T4N 1X2",
    "sg:province":"AB",
    "wof:name":"Canadian Cancer Society",
    "wof:placetype":"venue"
},
  "geometry": {"coordinates":[-113.80635100000001,52.269138],"type":"Point"}
}