{
  "type": "Feature",
  "properties": {
    "addr:full":"1325 Eglinton Ave E # 15 Mississauga ON L4W 4L9",
    "addr:housenumber":"1325",
    "addr:postcode":"l4w 4l9",
    "addr:street":"Eglinton Ave E # 15",
    "iso:country":"CA",
    "sg:address":"1325 Eglinton Ave E # 15",
    "sg:city":"Mississauga",
    "sg:classifiers":[
        {
            "category":"Food & Beverages",
            "subcategory":"Groceries & Convenience Stores",
            "type":"Retail Goods"
        }
    ],
    "sg:phone":"+1 905 238 9100",
    "sg:postcode":"L4W 4L9",
    "sg:province":"ON",
    "sg:tags":[
        "spice"
    ],
    "wof:name":"Coconut Grove Foods",
    "wof:placetype":"venue"
},
  "geometry": {"coordinates":[-79.622406,43.634399],"type":"Point"}
}