{
  "type": "Feature",
  "properties": {
    "addr:full":"16 Murray Pl Calgary AB T3Z 3L4",
    "addr:housenumber":"16",
    "addr:postcode":"t3z 3l4",
    "addr:street":"Murray Pl",
    "iso:country":"CA",
    "sg:address":"16 Murray Pl",
    "sg:city":"Calgary",
    "sg:classifiers":[
        {
            "category":"Building & Trades",
            "subcategory":"Equipment Rental",
            "type":"Services"
        }
    ],
    "sg:phone":"+1 403 242 8401",
    "sg:postcode":"T3Z 3L4",
    "sg:province":"AB",
    "sg:tags":[
        "spa",
        "hot",
        "leasing",
        "tub"
    ],
    "wof:name":"Splash Hot Tub Rentals Ltd",
    "wof:placetype":"venue"
},
  "geometry": {"coordinates":[-114.00905609100001,51.0555992126],"type":"Point"}
}