{
  "type": "Feature",
  "properties": {
    "addr:full":"Lac-Etchemin QC G0R 1S0",
    "addr:postcode":"g0r 1s0",
    "iso:country":"CA",
    "sg:city":"Lac-Etchemin",
    "sg:classifiers":[
        {
            "category":"Food & Beverages",
            "subcategory":"Groceries & Convenience Stores",
            "type":"Retail Goods"
        }
    ],
    "sg:phone":"+1 418 625 3654",
    "sg:postcode":"G0R 1S0",
    "sg:province":"QC",
    "wof:name":"Accomodation Linda Mercier Enr",
    "wof:placetype":"venue"
},
  "geometry": {"coordinates":[-70.557709,46.426022],"type":"Point"}
}