{
  "type": "Feature",
  "properties": {
    "addr:full":"6256 4th Line E Ariss ON N0B 1B0",
    "addr:housenumber":"6256",
    "addr:postcode":"n0b 1b0",
    "addr:street":"4Th Line E Ariss",
    "iso:country":"CA",
    "sg:address":"6256 4th Line E",
    "sg:city":"Ariss",
    "sg:classifiers":[
        {
            "category":"Shopping",
            "subcategory":"Jewelry",
            "type":"Retail Goods"
        }
    ],
    "sg:phone":"+1 519 846 0955",
    "sg:postcode":"N0B 1B0",
    "sg:province":"ON",
    "sg:tags":[
        "clocks"
    ],
    "wof:name":"Craftime Clockery",
    "wof:placetype":"venue"
},
  "geometry": {"coordinates":[-80.366028,43.575733],"type":"Point"}
}