{
  "type": "Feature",
  "properties": {
    "addr:full":"PO Box 400 Trochu AB T0M 2C0",
    "addr:housenumber":"po",
    "addr:postcode":"t0m 2c0",
    "addr:street":"Box 400",
    "iso:country":"CA",
    "sg:address":"PO Box 400",
    "sg:city":"Trochu",
    "sg:classifiers":[
        {
            "category":"Building & Trades",
            "subcategory":"Electrical",
            "type":"Services"
        }
    ],
    "sg:phone":"+1 403 442 2234",
    "sg:postcode":"T0M 2C0",
    "sg:province":"AB",
    "sg:tags":[
        "electric",
        "contractor"
    ],
    "wof:name":"Ken's Electric",
    "wof:placetype":"venue"
},
  "geometry": {"coordinates":[-113.237633,51.823704],"type":"Point"}
}