{
  "type": "Feature",
  "properties": {
    "addr:full":"203 Furnival Rd Rodney ON N0L 2C0",
    "addr:housenumber":"203",
    "addr:postcode":"n0l 2c0",
    "addr:street":"Furnival Rd",
    "iso:country":"CA",
    "sg:address":"203 Furnival Rd",
    "sg:city":"Rodney",
    "sg:classifiers":[
        {
            "category":"Wholesale",
            "subcategory":"Machinery & Supplies",
            "type":"Manufacturing & Wholesale Goods"
        }
    ],
    "sg:phone":"+1 519 785 0993",
    "sg:postcode":"N0L 2C0",
    "sg:province":"ON",
    "sg:tags":[
        "generator"
    ],
    "wof:name":"Rodney Cycle & Machine",
    "wof:placetype":"venue"
},
  "geometry": {"coordinates":[-81.68029799999999,42.566017],"type":"Point"}
}