{
  "type": "Feature",
  "properties": {
    "addr:full":"303 King St Midland ON L4R 3M5",
    "addr:housenumber":"303",
    "addr:postcode":"l4r 3m5",
    "addr:street":"King St",
    "iso:country":"CA",
    "sg:address":"303 King St",
    "sg:city":"Midland",
    "sg:classifiers":[
        {
            "category":"Shopping",
            "subcategory":"Clothing, Apparel, & Fashions",
            "type":"Retail Goods"
        }
    ],
    "sg:phone":"+1 705 527 9914",
    "sg:postcode":"L4R 3M5",
    "sg:province":"ON",
    "sg:tags":[
        "lingerie"
    ],
    "wof:name":"Indulge Boutique",
    "wof:placetype":"venue"
},
  "geometry": {"coordinates":[-79.884666,44.749317],"type":"Point"}
}