{
  "type": "Feature",
  "properties": {
    "iso:country":"CA",
    "sg:address":"400 Colborne St S",
    "sg:city":"Walkerton",
    "sg:classifiers":[
        {
            "category":"Education",
            "subcategory":"School",
            "type":"Public Place"
        }
    ],
    "sg:phone":"+1 519 881 1761",
    "sg:postcode":"N0G 2V0",
    "sg:province":"ON",
    "wof:name":"Walkerton Public School",
    "wof:placetype":"venue"
},
  "geometry": {"coordinates":[-81.1498336792,44.1287498474],"type":"Point"}
}