{
  "type": "Feature",
  "properties": {
    "addr:full":"2495 Boul Henri-Bourassa Quebec QC G1J 3X2",
    "addr:housenumber":"2495",
    "addr:postcode":"g1j 3x2",
    "addr:street":"Boul Henri-Bourassa",
    "iso:country":"CA",
    "sg:address":"2495 Boul Henri-Bourassa",
    "sg:city":"Quebec",
    "sg:classifiers":[
        {
            "category":"Freight",
            "type":"Transportation"
        }
    ],
    "sg:phone":"+1 418 524 7868",
    "sg:postcode":"G1J 3X2",
    "sg:province":"QC",
    "sg:tags":[
        "renting",
        "leasing",
        "commercial",
        "truck"
    ],
    "wof:name":"U-Haul Cie Ltee",
    "wof:placetype":"venue"
},
  "geometry": {"coordinates":[-71.2335510254,46.8410377502],"type":"Point"}
}