{
  "type": "Feature",
  "properties": {
    "addr:full":"1120 Flagship Dr Mississauga ON L4Y 2K1",
    "addr:housenumber":"1120",
    "addr:postcode":"l4y 2k1",
    "addr:street":"Flagship Dr",
    "iso:country":"CA",
    "sg:address":"1120 Flagship Dr",
    "sg:city":"Mississauga",
    "sg:classifiers":[
        {
            "category":"Education",
            "subcategory":"School",
            "type":"Public Place"
        }
    ],
    "sg:phone":"+1 905 277 9505",
    "sg:postcode":"L4Y 2K1",
    "sg:province":"ON",
    "wof:name":"Dixie School",
    "wof:placetype":"venue"
},
  "geometry": {"coordinates":[-79.59688568120001,43.6083106995],"type":"Point"}
}