{
  "type": "Feature",
  "properties": {
    "addr:full":"12333 Winram Rd Surrey BC V3V 3Y4",
    "addr:housenumber":"12333",
    "addr:postcode":"v3v 3y4",
    "addr:street":"Winram Rd",
    "iso:country":"CA",
    "sg:address":"12333 Winram Rd",
    "sg:city":"Surrey",
    "sg:classifiers":[
        {
            "category":"Building & Trades",
            "subcategory":"Construction",
            "type":"Services"
        }
    ],
    "sg:phone":"+1 604 580 3332",
    "sg:postcode":"V3V 3Y4",
    "sg:province":"BC",
    "sg:tags":[
        "railing"
    ],
    "wof:name":"Eliros Aluminum & Iron Craft",
    "wof:placetype":"venue"
},
  "geometry": {"coordinates":[-122.88052399999999,49.199486],"type":"Point"}
}