{
  "type": "Feature",
  "properties": {
    "addr:full":"Burnaby BC V5H 4J2",
    "addr:postcode":"v5h 4j2",
    "iso:country":"CA",
    "sg:city":"Burnaby",
    "sg:classifiers":[
        {
            "category":"Health Services",
            "subcategory":"Doctor",
            "type":"Services"
        }
    ],
    "sg:phone":"+1 604 439 7755",
    "sg:postcode":"V5H 4J2",
    "sg:province":"BC",
    "sg:tags":[
        "clinic",
        "dentist"
    ],
    "wof:name":"Acu Dental Clinic",
    "wof:placetype":"venue"
},
  "geometry": {"coordinates":[-122.99617767300001,49.2272987366],"type":"Point"}
}