{
  "type": "Feature",
  "properties": {
    "addr:full":"3400 Boul Poirier Saint-Laurent QC H4R 2J5",
    "addr:housenumber":"3400",
    "addr:postcode":"h4r 2j5",
    "addr:street":"Boul Poirier",
    "iso:country":"CA",
    "sg:address":"3400 Boul Poirier",
    "sg:city":"Saint-Laurent",
    "sg:classifiers":[
        {
            "category":"Wholesale",
            "subcategory":"Medical Equipment & Supplies",
            "type":"Manufacturing & Wholesale Goods"
        }
    ],
    "sg:phone":"+1 514 856 0881",
    "sg:postcode":"H4R 2J5",
    "sg:province":"QC",
    "sg:tags":[
        "school"
    ],
    "wof:name":"Dectro International",
    "wof:placetype":"venue"
},
  "geometry": {"coordinates":[-73.71573600000001,45.501335],"type":"Point"}
}