{
  "type": "Feature",
  "properties": {
    "addr:full":"1735 Brier Park Rd NW Medicine Hat AB T1C 1V5",
    "addr:housenumber":"1735",
    "addr:postcode":"t1c 1v5",
    "addr:street":"Brier Park Rd Nw",
    "iso:country":"CA",
    "sg:address":"1735 Brier Park Rd NW",
    "sg:city":"Medicine Hat",
    "sg:classifiers":[
        {
            "category":"Wholesale",
            "subcategory":"Vending Machines",
            "type":"Manufacturing & Wholesale Goods"
        }
    ],
    "sg:phone":"+1 403 527 0055",
    "sg:postcode":"T1C 1V5",
    "sg:province":"AB",
    "sg:tags":[
        "beverage"
    ],
    "wof:name":"Pepsi-Cola Group",
    "wof:placetype":"venue"
},
  "geometry": {"coordinates":[-110.728233,50.055573],"type":"Point"}
}