{
  "type": "Feature",
  "properties": {
    "iso:country":"CA",
    "sg:address":"4745 Boul Grande-Allee",
    "sg:city":"Brossard",
    "sg:classifiers":[
        {
            "category":"Restaurant",
            "type":"Food & Drink"
        }
    ],
    "sg:phone":"+1 450 676 4710",
    "sg:postcode":"J4Z 3G1",
    "sg:province":"QC",
    "wof:name":"Sun Tung Lok",
    "wof:placetype":"venue"
},
  "geometry": {"coordinates":[-73.45439910890001,45.4821586609],"type":"Point"}
}