{
  "type": "Feature",
  "properties": {
    "addr:full":"Verdun QC H4G 2Y8",
    "addr:postcode":"h4g 2y8",
    "iso:country":"CA",
    "sg:city":"Verdun",
    "sg:classifiers":[
        {
            "category":"Food & Beverages",
            "subcategory":"Groceries & Convenience Stores",
            "type":"Retail Goods"
        }
    ],
    "sg:phone":"+1 514 362 9911",
    "sg:postcode":"H4G 2Y8",
    "sg:province":"QC",
    "wof:name":"Depanneur Mon-Pain",
    "wof:placetype":"venue"
},
  "geometry": {"coordinates":[-73.564774,45.456089],"type":"Point"}
}