{
  "type": "Feature",
  "properties": {
    "addr:full":"3333 Boul Du Souvenir #200 Laval QC H7V 1X1",
    "addr:housenumber":"3333",
    "addr:postcode":"h7v 1x1",
    "addr:street":"Boul Du Souvenir # 200",
    "iso:country":"CA",
    "sg:address":"3333 Boul Du Souvenir #200",
    "sg:city":"Laval",
    "sg:classifiers":[
        {
            "category":"Professional",
            "subcategory":"Lawyer & Legal Services",
            "type":"Services"
        }
    ],
    "sg:phone":"+1 450 759 6600",
    "sg:postcode":"H7V 1X1",
    "sg:province":"QC",
    "sg:tags":[
        "attorney"
    ],
    "wof:name":"Dunton Rainville Sencrl",
    "wof:placetype":"venue"
},
  "geometry": {"coordinates":[-73.74437,45.552719],"type":"Point"}
}