{
  "type": "Feature",
  "properties": {
    "addr:full":"856 2nd Ave E Owen Sound ON N4K 2H3",
    "addr:housenumber":"856",
    "addr:postcode":"n4k 2h3",
    "addr:street":"2Nd Ave E",
    "iso:country":"CA",
    "sg:address":"856 2nd Ave E",
    "sg:city":"Owen Sound",
    "sg:classifiers":[
        {
            "category":"Organizations",
            "subcategory":"Labor Organization",
            "type":"Services"
        }
    ],
    "sg:phone":"+1 519 372 0662",
    "sg:postcode":"N4K 2H3",
    "sg:province":"ON",
    "wof:name":"Cupe",
    "wof:placetype":"venue"
},
  "geometry": {"coordinates":[-80.94281768800001,44.5649604797],"type":"Point"}
}