{
  "type": "Feature",
  "properties": {
    "addr:full":"1085 Mcnabb St Sault Ste Marie ON P6B 2A1",
    "addr:housenumber":"1085",
    "addr:postcode":"p6b 2a1",
    "addr:street":"Mcnabb St",
    "iso:country":"CA",
    "sg:address":"1085 Mcnabb St",
    "sg:city":"Sault Ste Marie",
    "sg:classifiers":[
        {
            "category":"Building & Trades",
            "subcategory":"Construction",
            "type":"Services"
        }
    ],
    "sg:phone":"+1 705 949 1832",
    "sg:postcode":"P6B 2A1",
    "sg:province":"ON",
    "sg:tags":[
        "home",
        "general",
        "improvement",
        "contractor"
    ],
    "wof:name":"Ruscio Masonry & Constr Ltd",
    "wof:placetype":"venue"
},
  "geometry": {"coordinates":[-84.272171,46.523357],"type":"Point"}
}