{
  "type": "Feature",
  "properties": {
    "iso:country":"CA",
    "sg:address":"1450 Headon Rd # 3",
    "sg:city":"Burlington",
    "sg:classifiers":[
        {
            "category":"Personal",
            "type":"Services"
        }
    ],
    "sg:phone":"+1 905 332 9387",
    "sg:postcode":"L7M 3Z5",
    "sg:province":"ON",
    "sg:tags":[
        "control",
        "weight"
    ],
    "wof:name":"Herbal Magic",
    "wof:placetype":"venue"
},
  "geometry": {"coordinates":[-79.809128,43.373211],"type":"Point"}
}