{
  "type": "Feature",
  "properties": {
    "addr:full":"Welland ON L3C 5A3",
    "addr:postcode":"l3c 5a3",
    "iso:country":"CA",
    "sg:city":"Welland",
    "sg:classifiers":[
        {
            "category":"Personal",
            "subcategory":"Beauty Salon",
            "type":"Services"
        }
    ],
    "sg:phone":"+1 905 788 0169",
    "sg:postcode":"L3C 5A3",
    "sg:province":"ON",
    "wof:name":"Hairport",
    "wof:placetype":"venue"
},
  "geometry": {"coordinates":[-79.2560882568,42.9909248352],"type":"Point"}
}