{
  "type": "Feature",
  "properties": {
    "addr:full":"16500 River Rd Richmond BC V6V 1L6",
    "addr:housenumber":"16500",
    "addr:postcode":"v6v 1l6",
    "addr:street":"River Rd",
    "iso:country":"CA",
    "sg:address":"16500 River Rd",
    "sg:city":"Richmond",
    "sg:classifiers":[
        {
            "category":"Freight",
            "type":"Transportation"
        }
    ],
    "sg:phone":"+1 604 278 1123",
    "sg:postcode":"V6V 1L6",
    "sg:province":"BC",
    "sg:tags":[
        "trucking"
    ],
    "wof:name":"A & J Stock Cartage Ltd",
    "wof:placetype":"venue"
},
  "geometry": {"coordinates":[-123.039444,49.201542],"type":"Point"}
}