{
  "type": "Feature",
  "properties": {
    "addr:full":"565 Ch St-Joseph St-Joseph-DE-Madawaska NB E7B 2R8",
    "addr:housenumber":"565",
    "addr:postcode":"e7b 2r8",
    "addr:street":"Ch St-Joseph St-Joseph-De-Madawaska",
    "iso:country":"CA",
    "sg:address":"565 Ch St-Joseph",
    "sg:city":"St-Joseph-DE-Madawaska",
    "sg:classifiers":[
        {
            "category":"Retail",
            "subcategory":"Repair Shop",
            "type":"Services"
        }
    ],
    "sg:phone":"+1 506 737 1996",
    "sg:postcode":"E7B 2R8",
    "sg:province":"NB",
    "sg:tags":[
        "sharpening"
    ],
    "wof:name":"Affutage Rc Sharpening",
    "wof:placetype":"venue"
},
  "geometry": {"coordinates":[-68.153702,47.634754],"type":"Point"}
}