{
  "type": "Feature",
  "properties": {
    "addr:full":"PO Box 292 Rodney ON N0L 2C0",
    "addr:housenumber":"po;292",
    "addr:postcode":"n0l 2c0",
    "addr:street":"Box",
    "iso:country":"CA",
    "sg:address":"PO Box 292",
    "sg:city":"Rodney",
    "sg:classifiers":[
        {
            "category":"Organizations",
            "subcategory":"Religious Organization",
            "type":"Services"
        }
    ],
    "sg:phone":"+1 519 785 0311",
    "sg:postcode":"N0L 2C0",
    "sg:province":"ON",
    "sg:tags":[
        "church"
    ],
    "wof:name":"Argyle Presbyterian Church",
    "wof:placetype":"venue"
},
  "geometry": {"coordinates":[-81.68309021,42.5680351257],"type":"Point"}
}