{
  "type": "Feature",
  "properties": {
    "addr:full":"16919 Stony Plain Rd NW Edmonton AB T5P 4B2",
    "addr:housenumber":"16919",
    "addr:postcode":"t5p 4b2",
    "addr:street":"Stony Plain Rd Nw",
    "iso:country":"CA",
    "sg:address":"16919 Stony Plain Rd NW",
    "sg:city":"Edmonton",
    "sg:classifiers":[
        {
            "category":"Retail",
            "subcategory":"Auto Repair",
            "type":"Services"
        }
    ],
    "sg:phone":"+1 780 484 9468",
    "sg:postcode":"T5P 4B2",
    "sg:province":"AB",
    "sg:tags":[
        "automobile",
        "lubrication"
    ],
    "wof:name":"Mr Lube",
    "wof:placetype":"venue"
},
  "geometry": {"coordinates":[-113.61318199999999,53.540947],"type":"Point"}
}