{
  "type": "Feature",
  "properties": {
    "addr:full":"Wingham ON N0G 2W0",
    "addr:postcode":"n0g 2w0",
    "iso:country":"CA",
    "sg:city":"Wingham",
    "sg:classifiers":[
        {
            "category":"Health Services",
            "subcategory":"Nursing And Care Facility",
            "type":"Services"
        }
    ],
    "sg:phone":"+1 519 357 2037",
    "sg:postcode":"N0G 2W0",
    "sg:province":"ON",
    "sg:tags":[
        "home",
        "retirement",
        "community"
    ],
    "wof:name":"Turnberry Estates",
    "wof:placetype":"venue"
},
  "geometry": {"coordinates":[-81.31057699999999,43.889244],"type":"Point"}
}