{
  "type": "Feature",
  "properties": {
    "addr:full":"10380 Railway Ave Richmond BC V7E 2B8",
    "addr:housenumber":"10380",
    "addr:postcode":"v7e 2b8",
    "addr:street":"Railway Ave",
    "iso:country":"CA",
    "sg:address":"10380 Railway Ave",
    "sg:city":"Richmond",
    "sg:classifiers":[
        {
            "category":"Professional",
            "subcategory":"Accounting & Tax Preparation",
            "type":"Services"
        }
    ],
    "sg:phone":"+1 604 272 6972",
    "sg:postcode":"V7E 2B8",
    "sg:province":"BC",
    "sg:tags":[
        "accountant"
    ],
    "wof:name":"Maple Leaf Accounting Svc",
    "wof:placetype":"venue"
},
  "geometry": {"coordinates":[-123.169647217,49.1373405457],"type":"Point"}
}