{
  "type": "Feature",
  "properties": {
    "iso:country":"CA",
    "sg:address":"2450 Lawrence Ave E",
    "sg:city":"Scarborough",
    "sg:classifiers":[
        {
            "category":"Wholesale",
            "subcategory":"Groceries",
            "type":"Manufacturing & Wholesale Goods"
        }
    ],
    "sg:phone":"+1 416 751 1156",
    "sg:postcode":"M1P 2R7",
    "sg:province":"ON",
    "sg:tags":[
        "food",
        "product"
    ],
    "wof:name":"Reliable Food Supplies Inc",
    "wof:placetype":"venue"
},
  "geometry": {"coordinates":[-79.2698898315,43.750919342],"type":"Point"}
}