{
  "type": "Feature",
  "properties": {
    "addr:full":"175 Riverton Ave Riverton MB R0C 2R0",
    "addr:housenumber":"175",
    "addr:postcode":"r0c 2r0",
    "addr:street":"Riverton Ave",
    "iso:country":"CA",
    "sg:address":"175 Riverton Ave",
    "sg:city":"Riverton",
    "sg:classifiers":[
        {
            "category":"Recreation",
            "type":"Entertainment"
        }
    ],
    "sg:phone":"+1 204 378 5597",
    "sg:postcode":"R0C 2R0",
    "sg:province":"MB",
    "sg:tags":[
        "club",
        "curling"
    ],
    "wof:name":"Riverton Curling Club",
    "wof:placetype":"venue"
},
  "geometry": {"coordinates":[-96.9964523315,50.9984130859],"type":"Point"}
}