{
  "type": "Feature",
  "properties": {
    "addr:full":"59 White Oak Dr E Sault Ste Marie ON P6B 4J7",
    "addr:housenumber":"59",
    "addr:postcode":"p6b 4j7",
    "addr:street":"White Oak Dr E",
    "iso:country":"CA",
    "sg:address":"59 White Oak Dr E",
    "sg:city":"Sault Ste Marie",
    "sg:classifiers":[
        {
            "category":"Building & Trades",
            "subcategory":"Construction",
            "type":"Services"
        }
    ],
    "sg:phone":"+1 705 949 8316",
    "sg:postcode":"P6B 4J7",
    "sg:province":"ON",
    "sg:tags":[
        "paving",
        "contractor"
    ],
    "wof:name":"Interlockers",
    "wof:placetype":"venue"
},
  "geometry": {"coordinates":[-84.33342,46.537277],"type":"Point"}
}