{
  "type": "Feature",
  "properties": {
    "iso:country":"CA",
    "sg:address":"151 Lakeshore Rd W",
    "sg:city":"Oakville",
    "sg:classifiers":[
        {
            "category":"Shopping",
            "type":"Retail Goods"
        }
    ],
    "sg:phone":"+1 905 842 2643",
    "sg:postcode":"L6K 1E5",
    "sg:province":"ON",
    "sg:tags":[
        "for",
        "supply",
        "stamp",
        "coin",
        "collector",
        "dealer"
    ],
    "wof:name":"Trafalgar Coins",
    "wof:placetype":"venue"
},
  "geometry": {"coordinates":[-79.67626953120001,43.4384765625],"type":"Point"}
}