{
  "type": "Feature",
  "properties": {
    "addr:full":"1577 Lloyd Ave North Vancouver BC V7P 3K8",
    "addr:housenumber":"1577",
    "addr:postcode":"v7p 3k8",
    "addr:street":"Lloyd Ave",
    "iso:country":"CA",
    "sg:address":"1577 Lloyd Ave",
    "sg:city":"North Vancouver",
    "sg:classifiers":[
        {
            "category":"Autos & Motor Vehicles",
            "subcategory":"Automobile Sales",
            "type":"Retail Goods"
        }
    ],
    "sg:phone":"+1 604 987 5288",
    "sg:postcode":"V7P 3K8",
    "sg:province":"BC",
    "sg:tags":[
        "car",
        "recreational"
    ],
    "wof:name":"Go West Campers Intl Ltd",
    "wof:placetype":"venue"
},
  "geometry": {"coordinates":[-123.105125,49.322659],"type":"Point"}
}