{
  "type": "Feature",
  "properties": {
    "addr:full":"951 Henderson Hwy Winnipeg MB R2K 2M2",
    "addr:housenumber":"951",
    "addr:postcode":"r2k 2m2",
    "addr:street":"Henderson Hwy",
    "iso:country":"CA",
    "sg:address":"951 Henderson Hwy",
    "sg:city":"Winnipeg",
    "sg:classifiers":[
        {
            "category":"Retail",
            "subcategory":"Auto Repair",
            "type":"Services"
        }
    ],
    "sg:phone":"+1 204 667 9559",
    "sg:postcode":"R2K 2M2",
    "sg:province":"MB",
    "sg:tags":[
        "body",
        "automobile",
        "painting"
    ],
    "wof:name":"Boyd Autobody & Glass",
    "wof:placetype":"venue"
},
  "geometry": {"coordinates":[-97.0982131958,49.933139801],"type":"Point"}
}