{
  "type": "Feature",
  "properties": {
    "addr:full":"12 3rd St SE Chesley ON N0G 1L0",
    "addr:housenumber":"12",
    "addr:postcode":"n0g 1l0",
    "addr:street":"3Rd St Se",
    "iso:country":"CA",
    "sg:address":"12 3rd St SE",
    "sg:city":"Chesley",
    "sg:classifiers":[
        {
            "category":"Manufacturing",
            "subcategory":"Printing",
            "type":"Manufacturing & Wholesale Goods"
        }
    ],
    "sg:phone":"+1 519 363 3824",
    "sg:postcode":"N0G 1L0",
    "sg:province":"ON",
    "sg:tags":[
        "printer"
    ],
    "wof:name":"Country Squire Printery",
    "wof:placetype":"venue"
},
  "geometry": {"coordinates":[-81.094711,44.297726],"type":"Point"}
}