{
  "type": "Feature",
  "properties": {
    "iso:country":"CA",
    "sg:address":"14921 107A Ave",
    "sg:city":"Surrey",
    "sg:classifiers":[
        {
            "category":"Social Services",
            "subcategory":"Child Care",
            "type":"Services"
        }
    ],
    "sg:phone":"+1 604 584 1414",
    "sg:postcode":"V3R 1V3",
    "sg:province":"BC",
    "wof:name":"Guildford Gardens Day Care",
    "wof:placetype":"venue"
},
  "geometry": {"coordinates":[-122.830215454,49.105178833],"type":"Point"}
}