{
  "type": "Feature",
  "properties": {
    "iso:country":"CA",
    "sg:address":"2345 Mission Rd",
    "sg:city":"Courtenay",
    "sg:classifiers":[
        {
            "category":"Education",
            "subcategory":"School",
            "type":"Public Place"
        }
    ],
    "sg:phone":"+1 250 334 4089",
    "sg:postcode":"V9N 9H1",
    "sg:province":"BC",
    "wof:name":"Courtenay Middle School",
    "wof:placetype":"venue"
},
  "geometry": {"coordinates":[-124.974365234,49.7135543823],"type":"Point"}
}