{
  "type": "Feature",
  "properties": {
    "iso:country":"CA",
    "sg:city":"Killam",
    "sg:classifiers":[
        {
            "category":"Food & Beverages",
            "subcategory":"Groceries & Convenience Stores",
            "type":"Retail Goods"
        }
    ],
    "sg:phone":"+1 780 385 3666",
    "sg:postcode":"T0B 2L0",
    "sg:province":"AB",
    "sg:tags":[
        "grocer"
    ],
    "wof:name":"Camrose CO-OP Ltd",
    "wof:placetype":"venue"
},
  "geometry": {"coordinates":[-111.855735779,52.7912826538],"type":"Point"}
}