{
  "type": "Feature",
  "properties": {
    "addr:full":"24 Dalcourt Dr Scarborough ON M1E 3H1",
    "addr:housenumber":"24",
    "addr:postcode":"m1e 3h1",
    "addr:street":"Dalcourt Dr",
    "iso:country":"CA",
    "sg:address":"24 Dalcourt Dr",
    "sg:city":"Scarborough",
    "sg:classifiers":[
        {
            "category":"Building & Trades",
            "subcategory":"Plumbing",
            "type":"Services"
        }
    ],
    "sg:phone":"+1 416 690 6465",
    "sg:postcode":"M1E 3H1",
    "sg:province":"ON",
    "sg:tags":[
        "heating",
        "contractor"
    ],
    "wof:name":"Len's Heating Svc Ltd",
    "wof:placetype":"venue"
},
  "geometry": {"coordinates":[-79.180046,43.760551],"type":"Point"}
}