{
  "type": "Feature",
  "properties": {
    "addr:full":"3130 Laurier Dr Saskatoon SK S7L 5J7",
    "addr:housenumber":"3130",
    "addr:postcode":"s7l 5j7",
    "addr:street":"Laurier Dr",
    "iso:country":"CA",
    "sg:address":"3130 Laurier Dr",
    "sg:city":"Saskatoon",
    "sg:classifiers":[
        {
            "category":"Recreation",
            "type":"Entertainment"
        }
    ],
    "sg:phone":"+1 306 975 3344",
    "sg:postcode":"S7L 5J7",
    "sg:province":"SK",
    "sg:tags":[
        "government",
        "hall",
        "auditorium"
    ],
    "wof:name":"Cosmo Civic Ctr",
    "wof:placetype":"venue"
},
  "geometry": {"coordinates":[-106.72058868400001,52.1346702576],"type":"Point"}
}