{
  "type": "Feature",
  "properties": {
    "iso:country":"CA",
    "sg:address":"4968 Rue DE LA Savane",
    "sg:city":"Montreal",
    "sg:classifiers":[
        {
            "category":"Retail",
            "subcategory":"Auto Repair",
            "type":"Services"
        }
    ],
    "sg:phone":"+1 514 341 1113",
    "sg:postcode":"H4P 1T7",
    "sg:province":"QC",
    "sg:tags":[
        "automobile",
        "top",
        "upholstery"
    ],
    "wof:name":"Classic Upholstery & Wndshld",
    "wof:placetype":"venue"
},
  "geometry": {"coordinates":[-73.6534729004,45.5000038147],"type":"Point"}
}