{
  "type": "Feature",
  "properties": {
    "addr:full":"1059 Taylor-Kidd Blvd Kingston ON K7M 6J9",
    "addr:housenumber":"1059",
    "addr:postcode":"k7m 6j9",
    "addr:street":"Taylor-Kidd Blvd",
    "iso:country":"CA",
    "sg:address":"1059 Taylor-Kidd Blvd",
    "sg:city":"Kingston",
    "sg:classifiers":[
        {
            "category":"Education",
            "subcategory":"School",
            "type":"Public Place"
        }
    ],
    "sg:phone":"+1 613 389 8932",
    "sg:postcode":"K7M 6J9",
    "sg:province":"ON",
    "wof:name":"Bayridge Secondary School",
    "wof:placetype":"venue"
},
  "geometry": {"coordinates":[-76.594337,44.251377],"type":"Point"}
}