{
  "type": "Feature",
  "properties": {
    "addr:full":"1661 Mccallum Rd Abbotsford BC V2S 3M4",
    "addr:housenumber":"1661",
    "addr:postcode":"v2s 3m4",
    "addr:street":"Mccallum Rd",
    "iso:country":"CA",
    "sg:address":"1661 Mccallum Rd",
    "sg:city":"Abbotsford",
    "sg:classifiers":[
        {
            "category":"Social Services",
            "subcategory":"Child Care",
            "type":"Services"
        }
    ],
    "sg:phone":"+1 604 852 2541",
    "sg:postcode":"V2S 3M4",
    "sg:province":"BC",
    "wof:name":"Central Heights Pre-School",
    "wof:placetype":"venue"
},
  "geometry": {"coordinates":[-122.293205,49.033028],"type":"Point"}
}