{
  "type": "Feature",
  "properties": {
    "addr:full":"1230 Blackfoot Dr # 300 Regina SK S4S 7G4",
    "addr:housenumber":"1230",
    "addr:postcode":"s4s 7g4",
    "addr:street":"Blackfoot Dr # 300",
    "iso:country":"CA",
    "sg:address":"1230 Blackfoot Dr # 300",
    "sg:city":"Regina",
    "sg:classifiers":[
        {
            "category":"Banks & Credit Unions",
            "subcategory":"Investment Brokerage",
            "type":"Services"
        }
    ],
    "sg:phone":"+1 306 779 6400",
    "sg:postcode":"S4S 7G4",
    "sg:province":"SK",
    "sg:tags":[
        "advisory",
        "financial"
    ],
    "wof:name":"Greystone Managed Investments",
    "wof:placetype":"venue"
},
  "geometry": {"coordinates":[-104.599174499,50.4259300232],"type":"Point"}
}