{
  "type": "Feature",
  "properties": {
    "addr:full":"239 Station St Ajax ON L1S 1S3",
    "addr:housenumber":"239",
    "addr:postcode":"l1s 1s3",
    "addr:street":"Station St",
    "iso:country":"CA",
    "sg:address":"239 Station St",
    "sg:city":"Ajax",
    "sg:classifiers":[
        {
            "category":"Building & Trades",
            "subcategory":"Construction",
            "type":"Services"
        }
    ],
    "sg:phone":"+1 905 686 2445",
    "sg:postcode":"L1S 1S3",
    "sg:province":"ON",
    "sg:tags":[
        "home",
        "contractor",
        "improvement",
        "roofing"
    ],
    "wof:name":"Carroll Home Improvements",
    "wof:placetype":"venue"
},
  "geometry": {"coordinates":[-79.03019,43.850182],"type":"Point"}
}