{
  "type": "Feature",
  "properties": {
    "addr:full":"502 Kingsley Rd Kingsley NB E3A 6E7",
    "addr:housenumber":"502",
    "addr:postcode":"e3a 6e7",
    "addr:street":"Kingsley Rd",
    "iso:country":"CA",
    "sg:address":"502 Kingsley Rd",
    "sg:city":"Kingsley",
    "sg:classifiers":[
        {
            "category":"Manufacturing",
            "subcategory":"Tools & Machinery",
            "type":"Manufacturing & Wholesale Goods"
        }
    ],
    "sg:phone":"+1 506 450 1896",
    "sg:postcode":"E3A 6E7",
    "sg:province":"NB",
    "sg:tags":[
        "machine",
        "shop",
        "woodworking"
    ],
    "wof:name":"Anderson Ventures Ltd",
    "wof:placetype":"venue"
},
  "geometry": {"coordinates":[-66.74479700000001,46.047039],"type":"Point"}
}