{
  "type": "Feature",
  "properties": {
    "addr:full":"46 King St Clinton ON N0M 1L0",
    "addr:housenumber":"46",
    "addr:postcode":"n0m 1l0",
    "addr:street":"King St",
    "iso:country":"CA",
    "sg:address":"46 King St",
    "sg:city":"Clinton",
    "sg:classifiers":[
        {
            "category":"Shopping",
            "subcategory":"Pharmacy",
            "type":"Retail Goods"
        }
    ],
    "sg:phone":"+1 519 482 5037",
    "sg:postcode":"N0M 1L0",
    "sg:province":"ON",
    "wof:name":"Clinton Pharmacy",
    "wof:placetype":"venue"
},
  "geometry": {"coordinates":[-81.539886,43.615623],"type":"Point"}
}