{
  "type": "Feature",
  "properties": {
    "addr:full":"97 Rue Sainte-Anne Ville-Marie QC J9V 2B6",
    "addr:housenumber":"97",
    "addr:postcode":"j9v 2b6",
    "addr:street":"Rue Sainte-Anne",
    "iso:country":"CA",
    "sg:address":"97 Rue Sainte-Anne",
    "sg:city":"Ville-Marie",
    "sg:classifiers":[
        {
            "category":"Shopping",
            "subcategory":"Florist",
            "type":"Retail Goods"
        }
    ],
    "sg:phone":"+1 819 629 2248",
    "sg:postcode":"J9V 2B6",
    "sg:province":"QC",
    "wof:name":"Fleurs Et Jardins 2000 Inc",
    "wof:placetype":"venue"
},
  "geometry": {"coordinates":[-79.43306699999999,47.332821],"type":"Point"}
}