{
  "type": "Feature",
  "properties": {
    "addr:full":"971 Woodroffe Ave Ottawa ON K2A 3G9",
    "addr:housenumber":"971",
    "addr:postcode":"k2a 3g9",
    "addr:street":"Woodroffe Ave",
    "iso:country":"CA",
    "sg:address":"971 Woodroffe Ave",
    "sg:city":"Ottawa",
    "sg:classifiers":[
        {
            "category":"Organizations",
            "subcategory":"Religious Organization",
            "type":"Services"
        }
    ],
    "sg:phone":"+1 613 729 3384",
    "sg:postcode":"K2A 3G9",
    "sg:province":"ON",
    "sg:tags":[
        "church"
    ],
    "wof:name":"St Paul's Presbyterian Church",
    "wof:placetype":"venue"
},
  "geometry": {"coordinates":[-75.769615,45.363899],"type":"Point"}
}