{
  "type": "Feature",
  "properties": {
    "addr:full":"106 Townsend St Sydney NS B1P 5E1",
    "addr:housenumber":"106",
    "addr:postcode":"b1p 5e1",
    "addr:street":"Townsend St",
    "iso:country":"CA",
    "sg:address":"106 Townsend St",
    "sg:city":"Sydney",
    "sg:classifiers":[
        {
            "category":"Real Estate",
            "subcategory":"Developer",
            "type":"Services"
        }
    ],
    "sg:phone":"+1 902 562 1933",
    "sg:postcode":"B1P 5E1",
    "sg:province":"NS",
    "sg:tags":[
        "cemetery"
    ],
    "wof:name":"Hardwood Hill Cemetery CO Ltd",
    "wof:placetype":"venue"
},
  "geometry": {"coordinates":[-60.1922569275,46.1346969604],"type":"Point"}
}