{
  "type": "Feature",
  "properties": {
    "iso:country":"CA",
    "sg:address":"2972 Rue Remembrance",
    "sg:city":"Lachine",
    "sg:classifiers":[
        {
            "category":"Shopping",
            "subcategory":"Shoes",
            "type":"Retail Goods"
        }
    ],
    "sg:phone":"+1 514 637 0608",
    "sg:postcode":"H8S 1X8",
    "sg:province":"QC",
    "wof:name":"Chaussures Pitt Ltee",
    "wof:placetype":"venue"
},
  "geometry": {"coordinates":[-73.69026184080001,45.4377708435],"type":"Point"}
}