{
  "type": "Feature",
  "properties": {
    "addr:full":"625 Rue Milton Montreal QC H2X 1W7",
    "addr:housenumber":"625",
    "addr:postcode":"h2x 1w7",
    "addr:street":"Rue Milton",
    "iso:country":"CA",
    "sg:address":"625 Rue Milton",
    "sg:city":"Montreal",
    "sg:classifiers":[
        {
            "category":"Professional",
            "subcategory":"Business Services",
            "type":"Services"
        }
    ],
    "sg:phone":"+1 514 842 4551",
    "sg:postcode":"H2X 1W7",
    "sg:province":"QC",
    "wof:name":"Marton Trading",
    "wof:placetype":"venue"
},
  "geometry": {"coordinates":[-73.57614100000001,45.506973],"type":"Point"}
}