{
  "type": "Feature",
  "properties": {
    "addr:full":"2051 Trans Canada Hwy E # B Kamloops BC V2C 4A5",
    "addr:housenumber":"2051",
    "addr:postcode":"bc v2c 4a5",
    "addr:street":"Trans Canada Hwy E # B",
    "iso:country":"CA",
    "sg:address":"2051 Trans Canada Hwy E # B",
    "sg:city":"Kamloops",
    "sg:classifiers":[
        {
            "category":"Home & Garden",
            "subcategory":"Building Materials",
            "type":"Retail Goods"
        }
    ],
    "sg:phone":"+1 250 374 3374",
    "sg:postcode":"V2C 4A5",
    "sg:province":"BC",
    "sg:tags":[
        "plate",
        "window",
        "upholsterer"
    ],
    "wof:name":"Clear View Glass & Upholstery",
    "wof:placetype":"venue"
},
  "geometry": {"coordinates":[-120.269348145,50.6801567078],"type":"Point"}
}