{
  "type": "Feature",
  "properties": {
    "iso:country":"CA",
    "sg:address":"2927 Rue Ludger-Duvernay",
    "sg:city":"Trois-Rivieres",
    "sg:classifiers":[
        {
            "category":"Personal",
            "subcategory":"Beauty Salon",
            "type":"Services"
        }
    ],
    "sg:phone":"+1 819 374 0548",
    "sg:postcode":"G8Z 1K2",
    "sg:province":"QC",
    "wof:name":"Touche DE Beaute Enr",
    "wof:placetype":"venue"
},
  "geometry": {"coordinates":[-72.564468,46.359859],"type":"Point"}
}