{
  "type": "Feature",
  "properties": {
    "addr:full":"Kelowna BC V1X 2B9",
    "addr:postcode":"v1x 2b9",
    "iso:country":"CA",
    "sg:city":"Kelowna",
    "sg:classifiers":[
        {
            "category":"Building & Trades",
            "subcategory":"Plumbing",
            "type":"Services"
        }
    ],
    "sg:phone":"+1 250 763 4117",
    "sg:postcode":"V1X 2B9",
    "sg:province":"BC",
    "sg:tags":[
        "conditioning",
        "air",
        "system",
        "refrigerating",
        "contractor"
    ],
    "wof:name":"Great West Refrigeration Ltd",
    "wof:placetype":"venue"
},
  "geometry": {"coordinates":[-119.422546387,49.8919372559],"type":"Point"}
}