{
  "type": "Feature",
  "properties": {
    "addr:full":"193 Ch DE LA Savane Gatineau QC J8T 1R2",
    "addr:housenumber":"193",
    "addr:postcode":"j8t 1r2",
    "addr:street":"Ch De La Savane",
    "iso:country":"CA",
    "sg:address":"193 Ch DE LA Savane",
    "sg:city":"Gatineau",
    "sg:classifiers":[
        {
            "category":"Personal",
            "subcategory":"Beauty Salon",
            "type":"Services"
        }
    ],
    "sg:phone":"+1 819 568 5169",
    "sg:postcode":"J8T 1R2",
    "sg:province":"QC",
    "wof:name":"Coiffure Unisexe Des Galeries",
    "wof:placetype":"venue"
},
  "geometry": {"coordinates":[-75.682632,45.475185],"type":"Point"}
}