{
  "type": "Feature",
  "properties": {
    "addr:full":"212 Rue Gauthier Saint-Polycarpe QC J0P 1X0",
    "addr:housenumber":"212",
    "addr:postcode":"j0p 1x0",
    "addr:street":"Rue Gauthier",
    "iso:country":"CA",
    "sg:address":"212 Rue Gauthier",
    "sg:city":"Saint-Polycarpe",
    "sg:classifiers":[
        {
            "category":"Home & Garden",
            "subcategory":"Furniture",
            "type":"Retail Goods"
        }
    ],
    "sg:phone":"+1 450 265 3060",
    "sg:postcode":"J0P 1X0",
    "sg:province":"QC",
    "sg:tags":[
        "builder",
        "custom"
    ],
    "wof:name":"Atelier Claude Lanthier Inc",
    "wof:placetype":"venue"
},
  "geometry": {"coordinates":[-74.31379699999999,45.297306],"type":"Point"}
}