{
  "type": "Feature",
  "properties": {
    "addr:full":"2400 Boul Sainte-Sophie Sainte-Sophie QC J5J 2V3",
    "addr:housenumber":"2400",
    "addr:postcode":"j5j 2v3",
    "addr:street":"Boul Sainte-Sophie",
    "iso:country":"CA",
    "sg:address":"2400 Boul Sainte-Sophie",
    "sg:city":"Sainte-Sophie",
    "sg:classifiers":[
        {
            "category":"Food & Beverages",
            "subcategory":"Groceries & Convenience Stores",
            "type":"Retail Goods"
        }
    ],
    "sg:phone":"+1 450 432 6262",
    "sg:postcode":"J5J 2V3",
    "sg:province":"QC",
    "wof:name":"Depan-Escompte Couche-Tard",
    "wof:placetype":"venue"
},
  "geometry": {"coordinates":[-73.89660600000001,45.819359],"type":"Point"}
}