{
  "type": "Feature",
  "properties": {
    "addr:full":"Surrey BC V3W 0N2",
    "addr:postcode":"v3w 0n2",
    "iso:country":"CA",
    "sg:city":"Surrey",
    "sg:classifiers":[
        {
            "category":"Manufacturing",
            "subcategory":"Furniture",
            "type":"Manufacturing & Wholesale Goods"
        }
    ],
    "sg:phone":"+1 604 572 6144",
    "sg:postcode":"V3W 0N2",
    "sg:province":"BC",
    "wof:name":"Touchwood Creations",
    "wof:placetype":"venue"
},
  "geometry": {"coordinates":[-122.88150024399999,49.1557006836],"type":"Point"}
}