{
  "type": "Feature",
  "properties": {
    "addr:full":"114 Main St Rockyford AB T0J 2R0",
    "addr:housenumber":"114",
    "addr:postcode":"t0j 2r0",
    "addr:street":"Main St",
    "iso:country":"CA",
    "sg:address":"114 Main St",
    "sg:city":"Rockyford",
    "sg:classifiers":[
        {
            "category":"Insurance",
            "subcategory":"Insurance Agent",
            "type":"Services"
        }
    ],
    "sg:phone":"+1 403 533 3771",
    "sg:postcode":"T0J 2R0",
    "sg:province":"AB",
    "wof:name":"Rockyford Agencies",
    "wof:placetype":"venue"
},
  "geometry": {"coordinates":[-113.14173889200001,51.2338638306],"type":"Point"}
}