{
  "type": "Feature",
  "properties": {
    "addr:full":"Havre-Saint-Pierre QC G0G 1P0",
    "addr:postcode":"g0g 1p0",
    "iso:country":"CA",
    "sg:city":"Havre-Saint-Pierre",
    "sg:classifiers":[
        {
            "category":"Government",
            "subcategory":"Office",
            "type":"Public Place"
        }
    ],
    "sg:phone":"+1 418 538 2288",
    "sg:postcode":"G0G 1P0",
    "sg:province":"QC",
    "wof:name":"Quebec Securite Du Revenu",
    "wof:placetype":"venue"
},
  "geometry": {"coordinates":[-63.5945205688,50.2447090149],"type":"Point"}
}