{
  "type": "Feature",
  "properties": {
    "addr:full":"North York ON M6B 4K7",
    "addr:postcode":"m6b 4k7",
    "iso:country":"CA",
    "sg:city":"North York",
    "sg:classifiers":[
        {
            "category":"Shopping",
            "subcategory":"Computers & Home Electronics",
            "type":"Retail Goods"
        }
    ],
    "sg:phone":"+1 416 780 9532",
    "sg:postcode":"M6B 4K7",
    "sg:province":"ON",
    "sg:tags":[
        "equipment",
        "dealer",
        "software"
    ],
    "wof:name":"One on One",
    "wof:placetype":"venue"
},
  "geometry": {"coordinates":[-79.45957199999999,43.702305],"type":"Point"}
}