{
  "type": "Feature",
  "properties": {
    "addr:full":"412 Rue Crabtree Joliette QC J6E 8E9",
    "addr:housenumber":"412",
    "addr:postcode":"j6e 8e9",
    "addr:street":"Rue Crabtree",
    "iso:country":"CA",
    "sg:address":"412 Rue Crabtree",
    "sg:city":"Joliette",
    "sg:classifiers":[
        {
            "category":"Personal",
            "subcategory":"Beauty Salon",
            "type":"Services"
        }
    ],
    "sg:phone":"+1 450 756 1425",
    "sg:postcode":"J6E 8E9",
    "sg:province":"QC",
    "wof:name":"Salon DE Coiffure Le Profil",
    "wof:placetype":"venue"
},
  "geometry": {"coordinates":[-73.4127197266,46.0097160339],"type":"Point"}
}