{
  "type": "Feature",
  "properties": {
    "addr:full":"467 Cosburn Ave East York ON M4J 2N6",
    "addr:housenumber":"467",
    "addr:postcode":"m4j 2n6",
    "addr:street":"Cosburn Ave",
    "iso:country":"CA",
    "sg:address":"467 Cosburn Ave",
    "sg:city":"East York",
    "sg:classifiers":[
        {
            "category":"Shopping",
            "subcategory":"Discount & Variety Stores",
            "type":"Retail Goods"
        }
    ],
    "sg:phone":"+1 416 421 1014",
    "sg:postcode":"M4J 2N6",
    "sg:province":"ON",
    "wof:name":"Corner Smoke & Gift Shop",
    "wof:placetype":"venue"
},
  "geometry": {"coordinates":[-79.33406100000001,43.692711],"type":"Point"}
}