{
  "type": "Feature",
  "properties": {
    "iso:country":"CA",
    "sg:address":"Range Rd 630A",
    "sg:city":"Fort Assiniboine",
    "sg:classifiers":[
        {
            "category":"Manufacturing",
            "subcategory":"Lumber",
            "type":"Manufacturing & Wholesale Goods"
        }
    ],
    "sg:phone":"+1 780 584 2232",
    "sg:postcode":"T0G 1A0",
    "sg:province":"AB",
    "wof:name":"O K Lumber Ltd",
    "wof:placetype":"venue"
},
  "geometry": {"coordinates":[-114.773979,54.333961],"type":"Point"}
}