{
  "type": "Feature",
  "properties": {
    "addr:full":"3890 Oak St Vancouver BC V6H 2M5",
    "addr:housenumber":"3890",
    "addr:postcode":"v6h 2m5",
    "addr:street":"Oak St",
    "iso:country":"CA",
    "sg:address":"3890 Oak St",
    "sg:city":"Vancouver",
    "sg:classifiers":[
        {
            "category":"Restaurant",
            "type":"Food & Drink"
        }
    ],
    "sg:phone":"+1 604 732 4576",
    "sg:postcode":"V6H 2M5",
    "sg:province":"BC",
    "wof:name":"Subway Sandwiches & Salads",
    "wof:placetype":"venue"
},
  "geometry": {"coordinates":[-123.127312,49.251003],"type":"Point"}
}