{
  "type": "Feature",
  "properties": {
    "addr:full":"100 Gordon St Stratford ON N5A 7T8",
    "addr:housenumber":"100",
    "addr:postcode":"n5a 7t8",
    "addr:street":"Gordon St",
    "iso:country":"CA",
    "sg:address":"100 Gordon St",
    "sg:city":"Stratford",
    "sg:classifiers":[
        {
            "category":"Social Services",
            "type":"Services"
        }
    ],
    "sg:phone":"+1 519 271 9454",
    "sg:postcode":"N5A 7T8",
    "sg:province":"ON",
    "sg:tags":[
        "organization",
        "welfare"
    ],
    "wof:name":"Diversion Program",
    "wof:placetype":"venue"
},
  "geometry": {"coordinates":[-80.959908,43.372288],"type":"Point"}
}