{
  "type": "Feature",
  "properties": {
    "addr:full":"Red Deer AB T4N 2R2",
    "addr:postcode":"t4n 2r2",
    "iso:country":"CA",
    "sg:city":"Red Deer",
    "sg:classifiers":[
        {
            "category":"Home & Garden",
            "subcategory":"Home Furnishings",
            "type":"Retail Goods"
        }
    ],
    "sg:phone":"+1 403 314 9400",
    "sg:postcode":"T4N 2R2",
    "sg:province":"AB",
    "sg:tags":[
        "fireplace"
    ],
    "wof:name":"Wholesale Fireplace & Heating",
    "wof:placetype":"venue"
},
  "geometry": {"coordinates":[-113.810959,52.281185],"type":"Point"}
}