{
  "type": "Feature",
  "properties": {
    "addr:full":"215 1E Av Lac-Etchemin QC G0R 1S0",
    "addr:housenumber":"215",
    "addr:postcode":"g0r 1s0",
    "addr:street":"1E Av Lac-Etchemin",
    "iso:country":"CA",
    "sg:address":"215 1E Av",
    "sg:city":"Lac-Etchemin",
    "sg:classifiers":[
        {
            "category":"Restaurant",
            "type":"Food & Drink"
        }
    ],
    "sg:phone":"+1 418 625 3362",
    "sg:postcode":"G0R 1S0",
    "sg:province":"QC",
    "wof:name":"Casse-Croute Du Lac Mini-Golf",
    "wof:placetype":"venue"
},
  "geometry": {"coordinates":[-70.5078659058,46.3963737488],"type":"Point"}
}