{
  "type": "Feature",
  "properties": {
    "addr:full":"2077 Dufferin St York ON M6E 3R3",
    "addr:housenumber":"2077",
    "addr:postcode":"m6e 3r3",
    "addr:street":"Dufferin St",
    "iso:country":"CA",
    "sg:address":"2077 Dufferin St",
    "sg:city":"York",
    "sg:classifiers":[
        {
            "category":"Personal",
            "subcategory":"Beauty Salon",
            "type":"Services"
        }
    ],
    "sg:phone":"+1 416 651 8194",
    "sg:postcode":"M6E 3R3",
    "sg:province":"ON",
    "wof:name":"Three Steps Hairstylist",
    "wof:placetype":"venue"
},
  "geometry": {"coordinates":[-79.4467010498,43.6874465942],"type":"Point"}
}