{
  "type": "Feature",
  "properties": {
    "addr:full":"699 3E Av Quebec QC G1L 2W5",
    "addr:housenumber":"699",
    "addr:postcode":"g1l 2w5",
    "addr:street":"3E Av",
    "iso:country":"CA",
    "sg:address":"699 3E Av",
    "sg:city":"Quebec",
    "sg:classifiers":[
        {
            "category":"Shopping",
            "subcategory":"Clothing, Apparel, & Fashions",
            "type":"Retail Goods"
        }
    ],
    "sg:phone":"+1 418 523 4434",
    "sg:postcode":"G1L 2W5",
    "sg:province":"QC",
    "sg:tags":[
        "fur",
        "business"
    ],
    "wof:name":"Fourrures Romeo Falardeau Inc",
    "wof:placetype":"venue"
},
  "geometry": {"coordinates":[-71.22807299999999,46.824455],"type":"Point"}
}