{
  "type": "Feature",
  "properties": {
    "addr:full":"22 Boulder Ave Dease Lake BC V0C 1L0",
    "addr:housenumber":"22",
    "addr:postcode":"bc v0c 1l0",
    "addr:street":"Boulder Ave",
    "iso:country":"CA",
    "sg:address":"22 Boulder Ave",
    "sg:city":"Dease Lake",
    "sg:classifiers":[
        {
            "category":"Building & Trades",
            "subcategory":"Construction",
            "type":"Services"
        }
    ],
    "sg:phone":"+1 250 771 3105",
    "sg:postcode":"V0C 1L0",
    "sg:province":"BC",
    "sg:tags":[
        "excavating",
        "contractor"
    ],
    "wof:name":"Brentwood Enterprises Ltd",
    "wof:placetype":"venue"
},
  "geometry": {"coordinates":[-129.98916625999999,58.4387435913],"type":"Point"}
}