{
  "type": "Feature",
  "properties": {
    "addr:full":"841 Central St W Prince George BC V2M 3C8",
    "addr:housenumber":"841",
    "addr:postcode":"v2m 3c8",
    "addr:street":"Central St",
    "iso:country":"CA",
    "sg:address":"841 Central St W",
    "sg:city":"Prince George",
    "sg:classifiers":[
        {
            "category":"Restaurant",
            "type":"Food & Drink"
        }
    ],
    "sg:phone":"+1 250 564 1221",
    "sg:postcode":"V2M 3C8",
    "sg:province":"BC",
    "sg:tags":[
        "pizza"
    ],
    "wof:name":"Boston Pizza",
    "wof:placetype":"venue"
},
  "geometry": {"coordinates":[-122.782417,53.91732],"type":"Point"}
}