{
  "type": "Feature",
  "properties": {
    "iso:country":"CA",
    "sg:address":"361 Rang 5",
    "sg:city":"Lac-Drolet",
    "sg:classifiers":[
        {
            "category":"Building & Trades",
            "subcategory":"Construction",
            "type":"Services"
        }
    ],
    "sg:phone":"+1 819 549 2587",
    "sg:postcode":"G0Y 1C0",
    "sg:province":"QC",
    "sg:tags":[
        "excavating",
        "contractor"
    ],
    "wof:name":"Excavatech Inc",
    "wof:placetype":"venue"
},
  "geometry": {"coordinates":[-70.83466339109999,45.7517127991],"type":"Point"}
}