{
  "type": "Feature",
  "properties": {
    "addr:full":"713 Johnson St Victoria BC V8W 1M8",
    "addr:housenumber":"713",
    "addr:postcode":"v8w 1m8",
    "addr:street":"Johnson St",
    "iso:country":"CA",
    "sg:address":"713 Johnson St",
    "sg:city":"Victoria",
    "sg:classifiers":[
        {
            "category":"Organizations",
            "subcategory":"Professional Association",
            "type":"Services"
        }
    ],
    "sg:phone":"+1 250 380 7766",
    "sg:postcode":"V8W 1M8",
    "sg:province":"BC",
    "sg:tags":[
        "hall",
        "auditorium"
    ],
    "wof:name":"City Bingo Assn",
    "wof:placetype":"venue"
},
  "geometry": {"coordinates":[-123.36421199999999,48.427006],"type":"Point"}
}