{
  "type": "Feature",
  "properties": {
    "iso:country":"CA",
    "sg:address":"36 Queen St",
    "sg:city":"Niagara on the Lake",
    "sg:classifiers":[
        {
            "category":"Shopping",
            "type":"Retail Goods"
        }
    ],
    "sg:phone":"+1 905 468 4500",
    "sg:postcode":"L0S 1J0",
    "sg:province":"ON",
    "sg:tags":[
        "decoration",
        "light",
        "christmas"
    ],
    "wof:name":"Just Christmas",
    "wof:placetype":"venue"
},
  "geometry": {"coordinates":[-79.0721740723,43.2552566528],"type":"Point"}
}