{
  "type": "Feature",
  "properties": {
    "iso:country":"CA",
    "sg:city":"Victoria",
    "sg:classifiers":[
        {
            "category":"Professional",
            "subcategory":"Lawyer & Legal Services",
            "type":"Services"
        }
    ],
    "sg:phone":"+1 250 385 1233",
    "sg:postcode":"V9A 1M8",
    "sg:province":"BC",
    "sg:tags":[
        "attorney"
    ],
    "wof:name":"Anniko, Urmas",
    "wof:placetype":"venue"
},
  "geometry": {"coordinates":[-123.37925,48.442955],"type":"Point"}
}