{
  "type": "Feature",
  "properties": {
    "addr:full":"580 Boul Hebert Saint-Pascal QC G0L 3Y0",
    "addr:housenumber":"580",
    "addr:postcode":"g0l 3y0",
    "addr:street":"Boul Hebert",
    "iso:country":"CA",
    "sg:address":"580 Boul Hebert",
    "sg:city":"Saint-Pascal",
    "sg:classifiers":[
        {
            "category":"Autos & Motor Vehicles",
            "subcategory":"Automobile Sales",
            "type":"Retail Goods"
        }
    ],
    "sg:phone":"+1 418 492 6347",
    "sg:postcode":"G0L 3Y0",
    "sg:province":"QC",
    "sg:tags":[
        "renting",
        "car"
    ],
    "wof:name":"Location Pelletier",
    "wof:placetype":"venue"
},
  "geometry": {"coordinates":[-69.799858,47.527557],"type":"Point"}
}