{
  "type": "Feature",
  "properties": {
    "addr:full":"4922 North Haven Dr NW Calgary AB T2K 2K2",
    "addr:housenumber":"4922",
    "addr:postcode":"t2k 2k2",
    "addr:street":"North Haven Dr Nw",
    "iso:country":"CA",
    "sg:address":"4922 North Haven Dr NW",
    "sg:city":"Calgary",
    "sg:classifiers":[
        {
            "category":"Education",
            "subcategory":"School",
            "type":"Public Place"
        }
    ],
    "sg:phone":"+1 403 777 6220",
    "sg:postcode":"T2K 2K2",
    "sg:province":"AB",
    "wof:name":"North Haven Elementary School",
    "wof:placetype":"venue"
},
  "geometry": {"coordinates":[-114.08706665,51.0975990295],"type":"Point"}
}