{
  "type": "Feature",
  "properties": {
    "addr:full":"65 Elmartin Dr Scarborough ON M1W 3C6",
    "addr:housenumber":"65",
    "addr:postcode":"m1w 3c6",
    "addr:street":"Elmartin Dr",
    "iso:country":"CA",
    "sg:address":"65 Elmartin Dr",
    "sg:city":"Scarborough",
    "sg:classifiers":[
        {
            "category":"Real Estate",
            "subcategory":"Real Estate Agent",
            "type":"Services"
        }
    ],
    "sg:phone":"+1 416 756 4222",
    "sg:postcode":"M1W 3C6",
    "sg:province":"ON",
    "wof:name":"V D'Andrea Real Estate Ltd",
    "wof:placetype":"venue"
},
  "geometry": {"coordinates":[-79.31749725340001,43.8135108948],"type":"Point"}
}