{
  "type": "Feature",
  "properties": {
    "addr:full":"1696 Drouillard Rd Windsor ON N8Y 2S3",
    "addr:housenumber":"1696",
    "addr:postcode":"n8y 2s3",
    "addr:street":"Drouillard Rd",
    "iso:country":"CA",
    "sg:address":"1696 Drouillard Rd",
    "sg:city":"Windsor",
    "sg:classifiers":[
        {
            "category":"Retail",
            "subcategory":"Auto Repair",
            "type":"Services"
        }
    ],
    "sg:phone":"+1 519 948 3411",
    "sg:postcode":"N8Y 2S3",
    "sg:province":"ON",
    "sg:tags":[
        "body",
        "automobile",
        "painting"
    ],
    "wof:name":"R & G Body Shop",
    "wof:placetype":"venue"
},
  "geometry": {"coordinates":[-82.991463,42.308243],"type":"Point"}
}