{
  "type": "Feature",
  "properties": {
    "addr:full":"Vancouver BC V5M 2A4",
    "addr:postcode":"v5m 2a4",
    "iso:country":"CA",
    "sg:city":"Vancouver",
    "sg:classifiers":[
        {
            "category":"Freight",
            "type":"Transportation"
        }
    ],
    "sg:phone":"+1 604 439 8938",
    "sg:postcode":"V5M 2A4",
    "sg:province":"BC",
    "sg:tags":[
        "trucking"
    ],
    "wof:name":"18 Wheels Transport Ltd",
    "wof:placetype":"venue"
},
  "geometry": {"coordinates":[-123.02964799999999,49.262516],"type":"Point"}
}