{
  "type": "Feature",
  "properties": {
    "addr:full":"36 Rue Descoteaux Saint-Charles-Borromee QC J6E 7T2",
    "addr:housenumber":"36",
    "addr:postcode":"j6e 7t2",
    "addr:street":"Rue Descoteaux Saint-Charles-Borromee",
    "iso:country":"CA",
    "sg:address":"36 Rue Descoteaux",
    "sg:city":"Saint-Charles-Borromee",
    "sg:classifiers":[
        {
            "category":"Retail",
            "subcategory":"Portrait Studio",
            "type":"Services"
        }
    ],
    "sg:phone":"+1 450 759 7086",
    "sg:postcode":"J6E 7T2",
    "sg:province":"QC",
    "sg:tags":[
        "photographer"
    ],
    "wof:name":"Photographie Serge Hetu",
    "wof:placetype":"venue"
},
  "geometry": {"coordinates":[-73.467072,46.052456],"type":"Point"}
}