{
  "type": "Feature",
  "properties": {
    "addr:full":"4025 Taylor St E Saskatoon SK S7H 5N7",
    "addr:housenumber":"4025",
    "addr:postcode":"s7h 5n7",
    "addr:street":"Taylor St E",
    "iso:country":"CA",
    "sg:address":"4025 Taylor St E",
    "sg:city":"Saskatoon",
    "sg:classifiers":[
        {
            "category":"Social Services",
            "subcategory":"Child Care",
            "type":"Services"
        }
    ],
    "sg:phone":"+1 306 373 1780",
    "sg:postcode":"S7H 5N7",
    "sg:province":"SK",
    "sg:tags":[
        "kindergarten",
        "academic",
        "school"
    ],
    "wof:name":"Lakeview Preschool CO-OP",
    "wof:placetype":"venue"
},
  "geometry": {"coordinates":[-106.588050842,52.1018714905],"type":"Point"}
}