{
  "type": "Feature",
  "properties": {
    "addr:full":"132 Main St Grunthal MB R0A 0R0",
    "addr:housenumber":"132",
    "addr:postcode":"r0a 0r0",
    "addr:street":"Main St",
    "iso:country":"CA",
    "sg:address":"132 Main St",
    "sg:city":"Grunthal",
    "sg:classifiers":[
        {
            "category":"Food & Beverages",
            "subcategory":"Groceries & Convenience Stores",
            "type":"Retail Goods"
        }
    ],
    "sg:phone":"+1 204 434 6017",
    "sg:postcode":"R0A 0R0",
    "sg:province":"MB",
    "sg:tags":[
        "grocer"
    ],
    "wof:name":"Grunthal Grocery",
    "wof:placetype":"venue"
},
  "geometry": {"coordinates":[-96.85130310060001,49.4066886902],"type":"Point"}
}