{
  "type": "Feature",
  "properties": {
    "addr:full":"3000 Danforth Ave East York ON M4C 1M7",
    "addr:housenumber":"3000",
    "addr:postcode":"m4c 1m7",
    "addr:street":"Danforth Ave",
    "iso:country":"CA",
    "sg:address":"3000 Danforth Ave",
    "sg:city":"East York",
    "sg:classifiers":[
        {
            "category":"Banks & Credit Unions",
            "subcategory":"Investment Brokerage",
            "type":"Services"
        }
    ],
    "sg:phone":"+1 416 699 0100",
    "sg:postcode":"M4C 1M7",
    "sg:province":"ON",
    "sg:tags":[
        "consultant",
        "financing"
    ],
    "wof:name":"Sika Services Inc",
    "wof:placetype":"venue"
},
  "geometry": {"coordinates":[-79.291161,43.690704],"type":"Point"}
}