{
  "type": "Feature",
  "properties": {
    "addr:full":"2439 Hastings St E Vancouver BC V5K 1Y8",
    "addr:housenumber":"2439",
    "addr:postcode":"v5k 1y8",
    "addr:street":"Hastings St E",
    "iso:country":"CA",
    "sg:address":"2439 Hastings St E",
    "sg:city":"Vancouver",
    "sg:classifiers":[
        {
            "category":"Retail",
            "subcategory":"Photofinishing",
            "type":"Services"
        }
    ],
    "sg:phone":"+1 604 255 8338",
    "sg:postcode":"V5K 1Y8",
    "sg:province":"BC",
    "sg:tags":[
        "photo",
        "finishing"
    ],
    "wof:name":"Best Quality Photo Finishing",
    "wof:placetype":"venue"
},
  "geometry": {"coordinates":[-123.055717,49.281395],"type":"Point"}
}