{
  "type": "Feature",
  "properties": {
    "addr:full":"1094 Killarney Bay Cameron ON K0M 1G0",
    "addr:housenumber":"1094",
    "addr:postcode":"k0m 1g0",
    "addr:street":"Killarney Bay",
    "iso:country":"CA",
    "sg:address":"1094 Killarney Bay",
    "sg:city":"Cameron",
    "sg:classifiers":[
        {
            "category":"Shopping",
            "subcategory":"Discount & Variety Stores",
            "type":"Retail Goods"
        }
    ],
    "sg:phone":"+1 705 887 9221",
    "sg:postcode":"K0M 1G0",
    "sg:province":"ON",
    "wof:name":"Killarney Bay Variety",
    "wof:placetype":"venue"
},
  "geometry": {"coordinates":[-78.774597168,44.4392433167],"type":"Point"}
}