{
  "type": "Feature",
  "properties": {
    "iso:country":"CA",
    "sg:address":"2043 Rue Des Roses",
    "sg:city":"Carignan",
    "sg:classifiers":[
        {
            "category":"Building & Trades",
            "subcategory":"Construction",
            "type":"Services"
        }
    ],
    "sg:phone":"+1 450 447 8949",
    "sg:postcode":"J3L 5E1",
    "sg:province":"QC",
    "sg:tags":[
        "general",
        "contractor"
    ],
    "wof:name":"Construction M & M Alepin",
    "wof:placetype":"venue"
},
  "geometry": {"coordinates":[-73.279289,45.472366],"type":"Point"}
}