{
  "type": "Feature",
  "properties": {
    "addr:full":"2043 Rue Des Roses Carignan QC J3L 5E1",
    "addr:housenumber":"2043",
    "addr:postcode":"j3l 5e1",
    "addr:street":"Rue Des Roses",
    "iso:country":"CA",
    "sg:address":"2043 Rue Des Roses",
    "sg:city":"Carignan",
    "sg:classifiers":[
        {
            "category":"Building & Trades",
            "subcategory":"Construction",
            "type":"Services"
        }
    ],
    "sg:phone":"+1 450 447 8949",
    "sg:postcode":"J3L 5E1",
    "sg:province":"QC",
    "sg:tags":[
        "general",
        "contractor"
    ],
    "wof:name":"Construction M & M Alepin",
    "wof:placetype":"venue"
},
  "geometry": {"coordinates":[-73.27928900000001,45.472366],"type":"Point"}
}