{
  "type": "Feature",
  "properties": {
    "addr:full":"6 William St # 2 Elmvale ON L0L 1P0",
    "addr:housenumber":"6",
    "addr:postcode":"l0l 1p0",
    "addr:street":"William St # 2",
    "iso:country":"CA",
    "sg:address":"6 William St # 2",
    "sg:city":"Elmvale",
    "sg:classifiers":[
        {
            "category":"Manufacturing",
            "subcategory":"Furniture",
            "type":"Manufacturing & Wholesale Goods"
        }
    ],
    "sg:phone":"+1 705 322 1233",
    "sg:postcode":"L0L 1P0",
    "sg:province":"ON",
    "wof:name":"Barzelle Designs",
    "wof:placetype":"venue"
},
  "geometry": {"coordinates":[-79.870964,44.587875],"type":"Point"}
}