{
  "type": "Feature",
  "properties": {
    "iso:country":"CA",
    "sg:address":"2401 Millar Ave",
    "sg:city":"Saskatoon",
    "sg:classifiers":[
        {
            "category":"Manufacturing",
            "subcategory":"Metals",
            "type":"Manufacturing & Wholesale Goods"
        }
    ],
    "sg:phone":"+1 306 931 1133",
    "sg:postcode":"S7K 2Y4",
    "sg:province":"SK",
    "sg:tags":[
        "casting",
        "foundry"
    ],
    "wof:name":"Blanchard Foundry",
    "wof:placetype":"venue"
},
  "geometry": {"coordinates":[-106.648277283,52.1646614075],"type":"Point"}
}