{
  "type": "Feature",
  "properties": {
    "iso:country":"CA",
    "sg:address":"4405 Ch Du Bois-Franc",
    "sg:city":"Saint-Laurent",
    "sg:classifiers":[
        {
            "category":"Wholesale",
            "subcategory":"Machinery & Supplies",
            "type":"Manufacturing & Wholesale Goods"
        }
    ],
    "sg:phone":"+1 514 333 7744",
    "sg:postcode":"H4S 1A8",
    "sg:province":"QC",
    "sg:tags":[
        "equipment",
        "drying"
    ],
    "wof:name":"Optimum Air Corp",
    "wof:placetype":"venue"
},
  "geometry": {"coordinates":[-73.73579406739999,45.4998970032],"type":"Point"}
}