{
  "type": "Feature",
  "properties": {
    "addr:full":"Dawson YT Y0B 1G0",
    "addr:postcode":"y0b 1g0",
    "addr:street":"Dawson",
    "iso:country":"CA",
    "sg:city":"Dawson",
    "sg:classifiers":[
        {
            "category":"Health Services",
            "subcategory":"Doctor",
            "type":"Services"
        }
    ],
    "sg:phone":"+1 867 993 5744",
    "sg:postcode":"Y0B 1G0",
    "sg:province":"YT",
    "sg:tags":[
        "physician",
        "surgeon"
    ],
    "wof:name":"Dawson Medical Clinic",
    "wof:placetype":"venue"
},
  "geometry": {"coordinates":[-139.438705,64.059113],"type":"Point"}
}