{
  "type": "Feature",
  "properties": {
    "addr:full":"700 Simpson St Thunder Bay ON P7C 3K1",
    "addr:housenumber":"700",
    "addr:postcode":"p7c 3k1",
    "addr:street":"Simpson St",
    "iso:country":"CA",
    "sg:address":"700 Simpson St",
    "sg:city":"Thunder Bay",
    "sg:classifiers":[
        {
            "category":"Retail",
            "subcategory":"Repair Shop",
            "type":"Services"
        }
    ],
    "sg:phone":"+1 807 625 9494",
    "sg:postcode":"P7C 3K1",
    "sg:province":"ON",
    "sg:tags":[
        "lock",
        "locksmith"
    ],
    "wof:name":"Lock Shop",
    "wof:placetype":"venue"
},
  "geometry": {"coordinates":[-89.235496521,48.3934745789],"type":"Point"}
}