{
  "type": "Feature",
  "properties": {
    "addr:full":"204 Hill St Corunna ON N0N 1G0",
    "addr:housenumber":"204",
    "addr:postcode":"n0n 1g0",
    "addr:street":"Hill St",
    "iso:country":"CA",
    "sg:address":"204 Hill St",
    "sg:city":"Corunna",
    "sg:classifiers":[
        {
            "category":"Real Estate",
            "subcategory":"Architect",
            "type":"Services"
        }
    ],
    "sg:phone":"+1 519 862 5083",
    "sg:postcode":"N0N 1G0",
    "sg:province":"ON",
    "sg:tags":[
        "building",
        "construction",
        "contractor"
    ],
    "wof:name":"Markson Construction Svc",
    "wof:placetype":"venue"
},
  "geometry": {"coordinates":[-82.451347,42.88866],"type":"Point"}
}