{
  "type": "Feature",
  "properties": {
    "addr:full":"19 Ferry Lane Maitland NS B0N 1T0",
    "addr:housenumber":"19",
    "addr:postcode":"b0n 1t0",
    "addr:street":"Ferry Lane",
    "iso:country":"CA",
    "sg:address":"19 Ferry Lane",
    "sg:city":"Maitland",
    "sg:classifiers":[
        {
            "category":"Travel",
            "subcategory":"Hotels & Motels",
            "type":"Entertainment"
        }
    ],
    "sg:phone":"+1 902 261 2001",
    "sg:postcode":"B0N 1T0",
    "sg:province":"NS",
    "sg:tags":[
        "breakfast",
        "accommodation",
        "bed"
    ],
    "wof:name":"Cresthaven By the Sea",
    "wof:placetype":"venue"
},
  "geometry": {"coordinates":[-63.4980545044,45.3182640076],"type":"Point"}
}