{
  "type": "Feature",
  "properties": {
    "addr:full":"Nominingue QC J0W 1R0",
    "addr:postcode":"j0w 1r0",
    "iso:country":"CA",
    "sg:city":"Nominingue",
    "sg:classifiers":[
        {
            "category":"Travel",
            "subcategory":"Hotels & Motels",
            "type":"Entertainment"
        }
    ],
    "sg:phone":"+1 819 278 4928",
    "sg:postcode":"J0W 1R0",
    "sg:province":"QC",
    "sg:tags":[
        "breakfast",
        "inn",
        "bed",
        "accommodation"
    ],
    "wof:name":"Provincialat Auberge-Passant",
    "wof:placetype":"venue"
},
  "geometry": {"coordinates":[-75.02488700000001,46.40292],"type":"Point"}
}