{
  "type": "Feature",
  "properties": {
    "addr:full":"6205 Hwy 97 Vernon BC V1B 3R4",
    "addr:housenumber":"6205",
    "addr:postcode":"v1b 3r4",
    "addr:street":"Hwy 97",
    "iso:country":"CA",
    "sg:address":"6205 Hwy 97",
    "sg:city":"Vernon",
    "sg:classifiers":[
        {
            "category":"Autos & Motor Vehicles",
            "subcategory":"Automobile Sales",
            "type":"Retail Goods"
        }
    ],
    "sg:phone":"+1 250 545 2358",
    "sg:postcode":"V1B 3R4",
    "sg:province":"BC",
    "sg:tags":[
        "car",
        "dealer"
    ],
    "wof:name":"Royal Volkswagen Ltd",
    "wof:placetype":"venue"
},
  "geometry": {"coordinates":[-119.273743,50.25898],"type":"Point"}
}