{
  "type": "Feature",
  "properties": {
    "addr:full":"PO Box 55 STN Whitney Pier Sydney NS B1N 3B1",
    "addr:housenumber":"po box 55",
    "addr:postcode":"b1n 3b1",
    "addr:street":"Stn Whitney",
    "iso:country":"CA",
    "sg:address":"PO Box 55 STN Whitney Pier",
    "sg:city":"Sydney",
    "sg:classifiers":[
        {
            "category":"Organizations",
            "subcategory":"Religious Organization",
            "type":"Services"
        }
    ],
    "sg:phone":"+1 902 539 5465",
    "sg:postcode":"B1N 3B1",
    "sg:province":"NS",
    "sg:tags":[
        "church"
    ],
    "wof:name":"Salvation Army",
    "wof:placetype":"venue"
},
  "geometry": {"coordinates":[-60.195568,46.137341],"type":"Point"}
}