{
  "type": "Feature",
  "properties": {
    "addr:full":"61 Needham St Lindsay ON K9V 4Z7",
    "addr:housenumber":"61",
    "addr:postcode":"k9v 4z7",
    "addr:street":"Needham St",
    "iso:country":"CA",
    "sg:address":"61 Needham St",
    "sg:city":"Lindsay",
    "sg:classifiers":[
        {
            "category":"Organizations",
            "subcategory":"Professional Association",
            "type":"Services"
        }
    ],
    "sg:phone":"+1 705 328 3761",
    "sg:postcode":"K9V 4Z7",
    "sg:province":"ON",
    "wof:name":"Victoria County Injured Worker",
    "wof:placetype":"venue"
},
  "geometry": {"coordinates":[-78.72956085209999,44.3686599731],"type":"Point"}
}