{
  "type": "Feature",
  "properties": {
    "addr:full":"3709 Prospect Rd Shad Bay NS B3T 2B4",
    "addr:housenumber":"3709",
    "addr:postcode":"b3t 2b4",
    "addr:street":"Prospect Rd",
    "iso:country":"CA",
    "sg:address":"3709 Prospect Rd",
    "sg:city":"Shad Bay",
    "sg:classifiers":[
        {
            "category":"Organizations",
            "subcategory":"Religious Organization",
            "type":"Services"
        }
    ],
    "sg:phone":"+1 902 852 2763",
    "sg:postcode":"B3T 2B4",
    "sg:province":"NS",
    "sg:tags":[
        "church"
    ],
    "wof:name":"Our Lady of Mount Carmel",
    "wof:placetype":"venue"
},
  "geometry": {"coordinates":[-63.7822265625,44.5214118958],"type":"Point"}
}