{
  "type": "Feature",
  "properties": {
    "addr:full":"Scarborough ON M1E 5B7",
    "addr:postcode":"m1e 5b7",
    "iso:country":"CA",
    "sg:city":"Scarborough",
    "sg:classifiers":[
        {
            "category":"Autos & Motor Vehicles",
            "subcategory":"Automobile Sales",
            "type":"Retail Goods"
        }
    ],
    "sg:phone":"+1 416 287 6223",
    "sg:postcode":"M1E 5B7",
    "sg:province":"ON",
    "sg:tags":[
        "cart"
    ],
    "wof:name":"Superior Kart Parts Inc",
    "wof:placetype":"venue"
},
  "geometry": {"coordinates":[-79.16552,43.765083],"type":"Point"}
}