{
  "type": "Feature",
  "properties": {
    "iso:country":"CA",
    "sg:address":"1087 Lillian St",
    "sg:city":"North York",
    "sg:classifiers":[
        {
            "category":"Social Services",
            "subcategory":"Child Care",
            "type":"Services"
        }
    ],
    "sg:phone":"+1 416 226 1380",
    "sg:postcode":"M2M 3G1",
    "sg:province":"ON",
    "wof:name":"Kaleidoscope Preschool",
    "wof:placetype":"venue"
},
  "geometry": {"coordinates":[-79.4112243652,43.798789978],"type":"Point"}
}