{
  "type": "Feature",
  "properties": {
    "addr:full":"103 Railway Ave E Carlyle SK S0C 0R0",
    "addr:housenumber":"103",
    "addr:postcode":"s0c 0r0",
    "addr:street":"Railway Ave E Carlyle",
    "iso:country":"CA",
    "sg:address":"103 Railway Ave E",
    "sg:city":"Carlyle",
    "sg:classifiers":[
        {
            "category":"Food & Beverages",
            "subcategory":"Liquor & Beverages",
            "type":"Retail Goods"
        }
    ],
    "sg:phone":"+1 306 453 3456",
    "sg:postcode":"S0C 0R0",
    "sg:province":"SK",
    "sg:tags":[
        "store"
    ],
    "wof:name":"Liquor Board Store",
    "wof:placetype":"venue"
},
  "geometry": {"coordinates":[-102.26415299999999,49.634884],"type":"Point"}
}