{
  "type": "Feature",
  "properties": {
    "addr:full":"10215 110th St Fairview AB T0H 1L0",
    "addr:housenumber":"10215",
    "addr:postcode":"t0h 1l0",
    "addr:street":"110Th St",
    "iso:country":"CA",
    "sg:address":"10215 110th St",
    "sg:city":"Fairview",
    "sg:classifiers":[
        {
            "category":"Restaurant",
            "type":"Food & Drink"
        }
    ],
    "sg:phone":"+1 780 835 4060",
    "sg:postcode":"T0H 1L0",
    "sg:province":"AB",
    "wof:name":"Kfc",
    "wof:placetype":"venue"
},
  "geometry": {"coordinates":[-118.384041,56.066814],"type":"Point"}
}