{
  "type": "Feature",
  "properties": {
    "addr:full":"124 Rue DE Victoria Chicoutimi QC G7G 4R7",
    "addr:housenumber":"124",
    "addr:postcode":"g7g 4r7",
    "addr:street":"Rue De Victoria",
    "iso:country":"CA",
    "sg:address":"124 Rue DE Victoria",
    "sg:city":"Chicoutimi",
    "sg:classifiers":[
        {
            "category":"Building & Trades",
            "subcategory":"Plumbing",
            "type":"Services"
        }
    ],
    "sg:phone":"+1 418 545 2417",
    "sg:postcode":"G7G 4R7",
    "sg:province":"QC",
    "sg:tags":[
        "balancing",
        "air"
    ],
    "wof:name":"Hydraulique R & O Svc Inc",
    "wof:placetype":"venue"
},
  "geometry": {"coordinates":[-71.04368599999999,48.440128],"type":"Point"}
}