{
  "type": "Feature",
  "properties": {
    "iso:country":"CA",
    "sg:address":"124 Rue DE Victoria",
    "sg:city":"Chicoutimi",
    "sg:classifiers":[
        {
            "category":"Building & Trades",
            "subcategory":"Plumbing",
            "type":"Services"
        }
    ],
    "sg:phone":"+1 418 545 2417",
    "sg:postcode":"G7G 4R7",
    "sg:province":"QC",
    "sg:tags":[
        "balancing",
        "air"
    ],
    "wof:name":"Hydraulique R & O Svc Inc",
    "wof:placetype":"venue"
},
  "geometry": {"coordinates":[-71.043686,48.440128],"type":"Point"}
}