{
  "type": "Feature",
  "properties": {
    "iso:country":"CA",
    "sg:address":"431 Gibson St",
    "sg:city":"Tofino",
    "sg:classifiers":[
        {
            "category":"Education",
            "subcategory":"School",
            "type":"Public Place"
        }
    ],
    "sg:phone":"+1 250 725 3254",
    "sg:postcode":"V0R 2Z0",
    "sg:province":"BC",
    "wof:name":"Wickaninnish Elementary School",
    "wof:placetype":"venue"
},
  "geometry": {"coordinates":[-125.90414428699999,49.1504249573],"type":"Point"}
}