{
  "type": "Feature",
  "properties": {
    "addr:full":"1 Carfrae Cres London ON N6C 4A8",
    "addr:housenumber":"1",
    "addr:postcode":"n6c 4a8",
    "addr:street":"Carfrae Cres",
    "iso:country":"CA",
    "sg:address":"1 Carfrae Cres",
    "sg:city":"London",
    "sg:classifiers":[
        {
            "category":"Shopping",
            "subcategory":"Discount & Variety Stores",
            "type":"Retail Goods"
        }
    ],
    "sg:phone":"+1 519 432 2345",
    "sg:postcode":"N6C 4A8",
    "sg:province":"ON",
    "wof:name":"Carfrae Variety",
    "wof:placetype":"venue"
},
  "geometry": {"coordinates":[-81.24546051030001,42.9746055603],"type":"Point"}
}