{
  "type": "Feature",
  "properties": {
    "iso:country":"CA",
    "sg:address":"480 Rue Des Pins",
    "sg:city":"Buckingham",
    "sg:classifiers":[
        {
            "category":"Restaurant",
            "type":"Food & Drink"
        }
    ],
    "sg:phone":"+1 819 986 3293",
    "sg:postcode":"J8L 2L3",
    "sg:province":"QC",
    "sg:tags":[
        "banquet",
        "association",
        "rooms"
    ],
    "wof:name":"Chevaliers DE Colombus",
    "wof:placetype":"venue"
},
  "geometry": {"coordinates":[-75.41423034669999,45.5883789062],"type":"Point"}
}