{
  "type": "Feature",
  "properties": {
    "addr:full":"314 Main St Wakaw SK S0K 4P0",
    "addr:housenumber":"314",
    "addr:postcode":"s0k 4p0",
    "addr:street":"Main St",
    "iso:country":"CA",
    "sg:address":"314 Main St",
    "sg:city":"Wakaw",
    "sg:classifiers":[
        {
            "category":"Recreation",
            "type":"Entertainment"
        }
    ],
    "sg:phone":"+1 306 233 4662",
    "sg:postcode":"S0K 4P0",
    "sg:province":"SK",
    "sg:tags":[
        "hall",
        "auditorium"
    ],
    "wof:name":"Roman Catholic Hall",
    "wof:placetype":"venue"
},
  "geometry": {"coordinates":[-105.742706,52.65295],"type":"Point"}
}