{
  "type": "Feature",
  "properties": {
    "addr:full":"Woodbridge ON L4L 6E4",
    "addr:postcode":"l4l 6e4",
    "iso:country":"CA",
    "sg:city":"Woodbridge",
    "sg:classifiers":[
        {
            "category":"Education",
            "subcategory":"Dance Studio",
            "type":"Public Place"
        }
    ],
    "sg:phone":"+1 905 856 1338",
    "sg:postcode":"L4L 6E4",
    "sg:province":"ON",
    "sg:tags":[
        "instruction",
        "dancing"
    ],
    "wof:name":"Dance With Mara",
    "wof:placetype":"venue"
},
  "geometry": {"coordinates":[-79.5554656982,43.785572052],"type":"Point"}
}