{
  "type": "Feature",
  "properties": {
    "addr:full":"43 Rue DE Buade Quebec QC G1R 4A2",
    "addr:housenumber":"43",
    "addr:postcode":"g1r 4a2",
    "addr:street":"Rue De Buade",
    "iso:country":"CA",
    "sg:address":"43 Rue DE Buade",
    "sg:city":"Quebec",
    "sg:classifiers":[
        {
            "category":"Organizations",
            "subcategory":"Professional Association",
            "type":"Services"
        }
    ],
    "sg:phone":"+1 418 692 5752",
    "sg:postcode":"G1R 4A2",
    "sg:province":"QC",
    "wof:name":"Federation Des Communautes",
    "wof:placetype":"venue"
},
  "geometry": {"coordinates":[-71.20663452150001,46.8135375977],"type":"Point"}
}