{
  "type": "Feature",
  "properties": {
    "addr:full":"922 Dugald Rd Winnipeg MB R2J 3J9",
    "addr:housenumber":"922",
    "addr:postcode":"r2j 3j9",
    "addr:street":"Dugald Rd",
    "iso:country":"CA",
    "sg:address":"922 Dugald Rd",
    "sg:city":"Winnipeg",
    "sg:phone":"+1 204 233 0848",
    "sg:postcode":"R2J 3J9",
    "sg:province":"MB",
    "sg:tags":[
        "oil"
    ],
    "wof:name":"Husky Bulk Sales",
    "wof:placetype":"venue"
},
  "geometry": {"coordinates":[-97.08049,49.885853],"type":"Point"}
}