{
  "type": "Feature",
  "properties": {
    "iso:country":"CA",
    "sg:address":"103-8430 Jellicoe Street",
    "sg:city":"Vancouver",
    "sg:classifiers":[
        {
            "category":"Professional",
            "subcategory":"Computer Services",
            "type":"Services"
        }
    ],
    "sg:postcode":"V5S 4S7",
    "sg:tags":[
        "environment",
        "green",
        "games",
        "children",
        "eco"
    ],
    "sg:website":"http://www.ecobuddies.com",
    "wof:name":"EcoBuddies\u2122 Interactive",
    "wof:placetype":"venue"
},
  "geometry": {"coordinates":[-123.047698,49.207142],"type":"Point"}
}