{
  "type": "Feature",
  "properties": {
    "addr:full":"661 Canterbury Rd Victoria BC V8Z 1Z8",
    "addr:housenumber":"661",
    "addr:postcode":"v8z 1z8",
    "addr:street":"Canterbury Rd",
    "iso:country":"CA",
    "sg:address":"661 Canterbury Rd",
    "sg:city":"Victoria",
    "sg:classifiers":[
        {
            "category":"Professional",
            "subcategory":"Engineering",
            "type":"Services"
        }
    ],
    "sg:phone":"+1 250 479 9920",
    "sg:postcode":"V8Z 1Z8",
    "sg:province":"BC",
    "sg:tags":[
        "computer",
        "software"
    ],
    "wof:name":"Jasi Stakko Intl",
    "wof:placetype":"venue"
},
  "geometry": {"coordinates":[-123.36451700000001,48.428314],"type":"Point"}
}