{
  "type": "Feature",
  "properties": {
    "addr:full":"Vancouver BC V5Z 1K7",
    "addr:postcode":"v5z 1k7",
    "iso:country":"CA",
    "sg:city":"Vancouver",
    "sg:classifiers":[
        {
            "category":"Utilities",
            "subcategory":"Mobile Phone",
            "type":"Services"
        }
    ],
    "sg:phone":"+1 604 656 2311",
    "sg:postcode":"V5Z 1K7",
    "sg:province":"BC",
    "sg:tags":[
        "telephone",
        "cellular"
    ],
    "wof:name":"Cellcity Communications Inc",
    "wof:placetype":"venue"
},
  "geometry": {"coordinates":[-123.125443,49.26326],"type":"Point"}
}