{
  "type": "Feature",
  "properties": {
    "iso:country":"CA",
    "sg:address":"11 Allstate Pky",
    "sg:city":"Markham",
    "sg:classifiers":[
        {
            "category":"Wholesale",
            "subcategory":"Jewelry",
            "type":"Manufacturing & Wholesale Goods"
        }
    ],
    "sg:phone":"+1 905 477 2064",
    "sg:postcode":"L3R 9T8",
    "sg:province":"ON",
    "sg:tags":[
        "tubing",
        "wire",
        "sheet",
        "metal"
    ],
    "wof:name":"Krupp Vdm Canada Ltd",
    "wof:placetype":"venue"
},
  "geometry": {"coordinates":[-79.3648071289,43.8495178223],"type":"Point"}
}