{
  "type": "Feature",
  "properties": {
    "addr:full":"Castlegar BC V1N 2K6",
    "addr:postcode":"v1n 2k6",
    "iso:country":"CA",
    "sg:city":"Castlegar",
    "sg:classifiers":[
        {
            "category":"Building & Trades",
            "subcategory":"Plumbing",
            "type":"Services"
        }
    ],
    "sg:phone":"+1 250 365 2991",
    "sg:postcode":"V1N 2K6",
    "sg:province":"BC",
    "sg:tags":[
        "contractor",
        "fixture",
        "supply"
    ],
    "wof:name":"Kootenay Plumbing Supplies",
    "wof:placetype":"venue"
},
  "geometry": {"coordinates":[-117.660148621,49.3103904724],"type":"Point"}
}