{
  "type": "Feature",
  "properties": {
    "iso:country":"CA",
    "sg:address":"375 Ch Flanders",
    "sg:city":"Compton",
    "sg:classifiers":[
        {
            "category":"Wholesale",
            "subcategory":"Fruits & Vegetables",
            "type":"Manufacturing & Wholesale Goods"
        }
    ],
    "sg:phone":"+1 819 835 9162",
    "sg:postcode":"J0B 1L0",
    "sg:province":"QC",
    "sg:tags":[
        "shipper"
    ],
    "wof:name":"Bleuetiere MI-Vallon",
    "wof:placetype":"venue"
},
  "geometry": {"coordinates":[-71.8262023926,45.2418556213],"type":"Point"}
}