{
  "type": "Feature",
  "properties": {
    "addr:full":"135 West St Simcoe ON N3Y 1S6",
    "addr:housenumber":"135",
    "addr:postcode":"n3y 1s6",
    "addr:street":"West St",
    "iso:country":"CA",
    "sg:address":"135 West St",
    "sg:city":"Simcoe",
    "sg:classifiers":[
        {
            "category":"Real Estate",
            "subcategory":"Real Estate Agent",
            "type":"Services"
        }
    ],
    "sg:phone":"+1 519 426 5551",
    "sg:postcode":"N3Y 1S6",
    "sg:province":"ON",
    "wof:name":"Gene Bystryk Real Estate Ltd",
    "wof:placetype":"venue"
},
  "geometry": {"coordinates":[-80.308159,42.835724],"type":"Point"}
}