{
  "type": "Feature",
  "properties": {
    "addr:full":"260 Bank St Ottawa ON K2P 1X4",
    "addr:housenumber":"260",
    "addr:postcode":"k2p 1x4",
    "addr:street":"Bank St",
    "iso:country":"CA",
    "sg:address":"260 Bank St",
    "sg:city":"Ottawa",
    "sg:classifiers":[
        {
            "category":"Food & Beverages",
            "subcategory":"Groceries & Convenience Stores",
            "type":"Retail Goods"
        }
    ],
    "sg:phone":"+1 613 235 7797",
    "sg:postcode":"K2P 1X4",
    "sg:province":"ON",
    "wof:name":"Royal Variety",
    "wof:placetype":"venue"
},
  "geometry": {"coordinates":[-75.697166,45.416096],"type":"Point"}
}