{
  "type": "Feature",
  "properties": {
    "addr:full":"21 Beech Hill Rd Antigonish NS B2G 2P9",
    "addr:housenumber":"21",
    "addr:postcode":"b2g 2p9",
    "addr:street":"Beech Hill Rd",
    "iso:country":"CA",
    "sg:address":"21 Beech Hill Rd",
    "sg:city":"Antigonish",
    "sg:classifiers":[
        {
            "category":"Retail",
            "subcategory":"Auto Repair",
            "type":"Services"
        }
    ],
    "sg:phone":"+1 902 863 6157",
    "sg:postcode":"B2G 2P9",
    "sg:province":"NS",
    "sg:tags":[
        "repairing",
        "automobile"
    ],
    "wof:name":"Antigonish Wheel Alignment",
    "wof:placetype":"venue"
},
  "geometry": {"coordinates":[-61.970737,45.616257],"type":"Point"}
}