{
  "type": "Feature",
  "properties": {
    "addr:full":"PO Box 518 Trochu AB T0M 2C0",
    "addr:housenumber":"po",
    "addr:postcode":"t0m 2c0",
    "addr:street":"Box 518 Trochu",
    "iso:country":"CA",
    "sg:address":"PO Box 518",
    "sg:city":"Trochu",
    "sg:classifiers":[
        {
            "category":"Manufacturing",
            "subcategory":"Signs",
            "type":"Manufacturing & Wholesale Goods"
        }
    ],
    "sg:phone":"+1 403 442 2151",
    "sg:postcode":"T0M 2C0",
    "sg:province":"AB",
    "sg:tags":[
        "monument"
    ],
    "wof:name":"Countryside Monument",
    "wof:placetype":"venue"
},
  "geometry": {"coordinates":[-113.237633,51.823704],"type":"Point"}
}