{
  "type": "Feature",
  "properties": {
    "addr:full":"8780 Av Dubuisson Montreal QC H1L 2W6",
    "addr:housenumber":"8780",
    "addr:postcode":"h1l 2w6",
    "addr:street":"Av Dubuisson",
    "iso:country":"CA",
    "sg:address":"8780 Av Dubuisson",
    "sg:city":"Montreal",
    "sg:classifiers":[
        {
            "category":"Arena",
            "subcategory":"Sports Club",
            "type":"Entertainment"
        }
    ],
    "sg:phone":"+1 514 872 6708",
    "sg:postcode":"H1L 2W6",
    "sg:province":"QC",
    "sg:tags":[
        "athletic",
        "fields",
        "stadium",
        "government"
    ],
    "wof:name":"Montreal Arenas Municipales",
    "wof:placetype":"venue"
},
  "geometry": {"coordinates":[-73.516975,45.601162],"type":"Point"}
}