{
  "type": "Feature",
  "properties": {
    "addr:full":"Highway 6 S Ceylon SK S0C 0T0",
    "addr:postcode":"s0c 0t0",
    "addr:street":"Highway 6 S",
    "iso:country":"CA",
    "sg:address":"Highway 6 S",
    "sg:city":"Ceylon",
    "sg:classifiers":[
        {
            "category":"Government",
            "subcategory":"Office",
            "type":"Public Place"
        }
    ],
    "sg:phone":"+1 306 969 2255",
    "sg:postcode":"S0C 0T0",
    "sg:province":"SK",
    "wof:name":"Canada Customs & Excise Dept",
    "wof:placetype":"venue"
},
  "geometry": {"coordinates":[-104.605812,49.456829],"type":"Point"}
}