{
  "type": "Feature",
  "properties": {
    "iso:country":"CA",
    "sg:address":"5135 Hennin St",
    "sg:city":"Oldcastle",
    "sg:classifiers":[
        {
            "category":"Manufacturing",
            "subcategory":"Tools & Machinery",
            "type":"Manufacturing & Wholesale Goods"
        }
    ],
    "sg:phone":"+1 519 737 7562",
    "sg:postcode":"N0R 1L0",
    "sg:province":"ON",
    "sg:tags":[
        "control"
    ],
    "wof:name":"Mte Hydraulics",
    "wof:placetype":"venue"
},
  "geometry": {"coordinates":[-82.9569244385,42.2393341064],"type":"Point"}
}