{
  "type": "Feature",
  "properties": {
    "addr:full":"Redcliff AB T0J 2P0",
    "addr:postcode":"t0j 2p0",
    "iso:country":"CA",
    "sg:city":"Redcliff",
    "sg:classifiers":[
        {
            "category":"Home & Garden",
            "subcategory":"Garden Supply",
            "type":"Retail Goods"
        }
    ],
    "sg:phone":"+1 403 548 1839",
    "sg:postcode":"T0J 2P0",
    "sg:province":"AB",
    "sg:tags":[
        "sprinkler"
    ],
    "wof:name":"Relax Sprinklers",
    "wof:placetype":"venue"
},
  "geometry": {"coordinates":[-110.776596,50.07716],"type":"Point"}
}