{
  "type": "Feature",
  "properties": {
    "addr:full":"74 Gaylord Rd St Thomas ON N5P 3S2",
    "addr:housenumber":"74",
    "addr:postcode":"n5p 3s2",
    "addr:street":"Gaylord Rd",
    "iso:country":"CA",
    "sg:address":"74 Gaylord Rd",
    "sg:city":"St Thomas",
    "sg:classifiers":[
        {
            "category":"Bus Charters",
            "type":"Transportation"
        }
    ],
    "sg:phone":"+1 519 633 2971",
    "sg:postcode":"N5P 3S2",
    "sg:province":"ON",
    "sg:tags":[
        "rental"
    ],
    "wof:name":"Laidlaw Education Svc",
    "wof:placetype":"venue"
},
  "geometry": {"coordinates":[-81.159447,42.781063],"type":"Point"}
}