{
  "type": "Feature",
  "properties": {
    "addr:full":"Calgary AB T3J 3J8",
    "addr:postcode":"t3j 3j8",
    "iso:country":"CA",
    "sg:city":"Calgary",
    "sg:classifiers":[
        {
            "category":"Food & Beverages",
            "subcategory":"Liquor & Beverages",
            "type":"Retail Goods"
        }
    ],
    "sg:phone":"+1 403 280 8802",
    "sg:postcode":"T3J 3J8",
    "sg:province":"AB",
    "sg:tags":[
        "store"
    ],
    "wof:name":"Castleridge Liquor Depot",
    "wof:placetype":"venue"
},
  "geometry": {"coordinates":[-113.96172332800001,51.100227356],"type":"Point"}
}