{
  "type": "Feature",
  "properties": {
    "iso:country":"CA",
    "sg:address":"236 Rue Saint-Etienne",
    "sg:city":"LA Malbaie",
    "sg:classifiers":[
        {
            "category":"Personal",
            "type":"Services"
        }
    ],
    "sg:phone":"+1 418 665 7274",
    "sg:postcode":"G5A 1T2",
    "sg:province":"QC",
    "sg:tags":[
        "salon",
        "electrolysis",
        "beauty"
    ],
    "wof:name":"Salon D'Esthetique Beaute",
    "wof:placetype":"venue"
},
  "geometry": {"coordinates":[-70.1534194946,47.6564483643],"type":"Point"}
}