{
  "type": "Feature",
  "properties": {
    "addr:full":"Campbell River BC V9W 2X9",
    "addr:postcode":"v9w 2x9",
    "iso:country":"CA",
    "sg:city":"Campbell River",
    "sg:classifiers":[
        {
            "category":"Shopping",
            "subcategory":"Computers & Home Electronics",
            "type":"Retail Goods"
        }
    ],
    "sg:phone":"+1 250 286 0532",
    "sg:postcode":"V9W 2X9",
    "sg:province":"BC",
    "sg:tags":[
        "television",
        "video",
        "game"
    ],
    "wof:name":"National Tv & Video",
    "wof:placetype":"venue"
},
  "geometry": {"coordinates":[-125.247657776,50.0118141174],"type":"Point"}
}