{
  "type": "Feature",
  "properties": {
    "addr:full":"26 William St S Chatham ON N7M 4S1",
    "addr:housenumber":"26",
    "addr:postcode":"n7m 4s1",
    "addr:street":"William St S",
    "iso:country":"CA",
    "sg:address":"26 William St S",
    "sg:city":"Chatham",
    "sg:classifiers":[
        {
            "category":"Building & Trades",
            "subcategory":"Construction",
            "type":"Services"
        }
    ],
    "sg:phone":"+1 519 359 3011",
    "sg:postcode":"N7M 4S1",
    "sg:province":"ON",
    "sg:tags":[
        "contractor"
    ],
    "wof:name":"Signature Home Improvements",
    "wof:placetype":"venue"
},
  "geometry": {"coordinates":[-82.181312561,42.4043769836],"type":"Point"}
}