{
  "type": "Feature",
  "properties": {
    "addr:full":"242 Dunkirk Dr Winnipeg MB R2M 3W9",
    "addr:housenumber":"242",
    "addr:postcode":"r2m 3w9",
    "addr:street":"Dunkirk Dr",
    "iso:country":"CA",
    "sg:address":"242 Dunkirk Dr",
    "sg:city":"Winnipeg",
    "sg:classifiers":[
        {
            "category":"Professional",
            "subcategory":"Lawyer & Legal Services",
            "type":"Services"
        }
    ],
    "sg:phone":"+1 204 253 2253",
    "sg:postcode":"R2M 3W9",
    "sg:province":"MB",
    "sg:tags":[
        "attorney"
    ],
    "wof:name":"Flatt Law Office",
    "wof:placetype":"venue"
},
  "geometry": {"coordinates":[-97.11700399999999,49.845074],"type":"Point"}
}