{
  "type": "Feature",
  "properties": {
    "addr:full":"2040 10 Ave SW Salmon Arm BC V1E 1T4",
    "addr:housenumber":"2040",
    "addr:postcode":"v1e 1t4",
    "addr:street":"10 Ave Sw",
    "iso:country":"CA",
    "sg:address":"2040 10 Ave SW",
    "sg:city":"Salmon Arm",
    "sg:classifiers":[
        {
            "category":"Autos & Motor Vehicles",
            "subcategory":"Automobile Sales",
            "type":"Retail Goods"
        }
    ],
    "sg:phone":"+1 250 832 6999",
    "sg:postcode":"V1E 1T4",
    "sg:province":"BC",
    "sg:tags":[
        "car",
        "dealer"
    ],
    "wof:name":"Beater World",
    "wof:placetype":"venue"
},
  "geometry": {"coordinates":[-119.308868408,50.6924476624],"type":"Point"}
}