{
  "type": "Feature",
  "properties": {
    "addr:full":"6004 Rue Alphonse Brossard QC J4Z 1C3",
    "addr:housenumber":"6004",
    "addr:postcode":"j4z 1c3",
    "addr:street":"Rue Alphonse",
    "iso:country":"CA",
    "sg:address":"6004 Rue Alphonse",
    "sg:city":"Brossard",
    "sg:classifiers":[
        {
            "category":"Food & Beverages",
            "subcategory":"Groceries & Convenience Stores",
            "type":"Retail Goods"
        }
    ],
    "sg:phone":"+1 450 443 5759",
    "sg:postcode":"J4Z 1C3",
    "sg:province":"QC",
    "wof:name":"Depanneur Franc-Clair",
    "wof:placetype":"venue"
},
  "geometry": {"coordinates":[-73.461403,45.480259],"type":"Point"}
}