{
  "type": "Feature",
  "properties": {
    "iso:country":"CA",
    "sg:address":"1859 Hollis St",
    "sg:city":"Halifax",
    "sg:classifiers":[
        {
            "category":"Professional",
            "subcategory":"Business Services",
            "type":"Services"
        }
    ],
    "sg:phone":"+1 902 425 9500",
    "sg:postcode":"B3J 1W5",
    "sg:province":"NS",
    "sg:tags":[
        "event"
    ],
    "wof:name":"Millennium Events Inc",
    "wof:placetype":"venue"
},
  "geometry": {"coordinates":[-63.5737113953,44.6497077942],"type":"Point"}
}