{
  "type": "Feature",
  "properties": {
    "addr:full":"1648 Montreal Rd Gloucester ON K1J 6N5",
    "addr:housenumber":"1648",
    "addr:postcode":"k1j 6n5",
    "addr:street":"Montreal Rd",
    "iso:country":"CA",
    "sg:address":"1648 Montreal Rd",
    "sg:city":"Gloucester",
    "sg:classifiers":[
        {
            "category":"Banks & Credit Unions",
            "subcategory":"Bank",
            "type":"Services"
        }
    ],
    "sg:phone":"+1 613 745 6533",
    "sg:postcode":"K1J 6N5",
    "sg:province":"ON",
    "wof:name":"T D Bank Financial Group",
    "wof:placetype":"venue"
},
  "geometry": {"coordinates":[-75.6137924194,45.4461555481],"type":"Point"}
}