{
  "type": "Feature",
  "properties": {
    "addr:full":"Farm Hawarden SK S0H 1Y0",
    "addr:postcode":"s0h 1y0",
    "iso:country":"CA",
    "sg:address":"Farm",
    "sg:city":"Hawarden",
    "sg:classifiers":[
        {
            "category":"Organizations",
            "subcategory":"Religious Organization",
            "type":"Services"
        }
    ],
    "sg:phone":"+1 306 855 4820",
    "sg:postcode":"S0H 1Y0",
    "sg:province":"SK",
    "sg:tags":[
        "church"
    ],
    "wof:name":"Bethlehem Lutheran Church",
    "wof:placetype":"venue"
},
  "geometry": {"coordinates":[-106.600731,51.4165],"type":"Point"}
}