{
  "type": "Feature",
  "properties": {
    "iso:country":"CA",
    "sg:address":"5945 Rue Souart # 3",
    "sg:city":"Montreal",
    "sg:classifiers":[
        {
            "category":"Building & Trades",
            "subcategory":"Electrical",
            "type":"Services"
        }
    ],
    "sg:phone":"+1 514 737 7202",
    "sg:postcode":"H3S 2E9",
    "sg:province":"QC",
    "sg:tags":[
        "electric",
        "contractor"
    ],
    "wof:name":"Action Electrique",
    "wof:placetype":"venue"
},
  "geometry": {"coordinates":[-73.628143,45.502918],"type":"Point"}
}