{
  "type": "Feature",
  "properties": {
    "addr:full":"Edmonton AB T5T 4J5",
    "addr:postcode":"t5t 4j5",
    "iso:country":"CA",
    "sg:city":"Edmonton",
    "sg:classifiers":[
        {
            "category":"Banks & Credit Unions",
            "subcategory":"Investment Brokerage",
            "type":"Services"
        }
    ],
    "sg:phone":"+1 780 481 1888",
    "sg:postcode":"T5T 4J5",
    "sg:province":"AB",
    "wof:name":"Edward Jones",
    "wof:placetype":"venue"
},
  "geometry": {"coordinates":[-113.630409241,53.5010528564],"type":"Point"}
}