{
  "type": "Feature",
  "properties": {
    "addr:full":"Brockville ON K6V 5V6",
    "addr:postcode":"k6v 5v6",
    "iso:country":"CA",
    "sg:city":"Brockville",
    "sg:classifiers":[
        {
            "category":"Social Services",
            "type":"Services"
        }
    ],
    "sg:phone":"+1 613 345 6007",
    "sg:postcode":"K6V 5V6",
    "sg:province":"ON",
    "sg:tags":[
        "organization",
        "welfare"
    ],
    "wof:name":"Rose Garden Family Support Ctr",
    "wof:placetype":"venue"
},
  "geometry": {"coordinates":[-75.691124,44.610519],"type":"Point"}
}