{
  "type": "Feature",
  "properties": {
    "addr:full":"275 Bishop St N Alexandria ON K0C 1A0",
    "addr:housenumber":"275",
    "addr:postcode":"k0c 1a0",
    "addr:street":"Bishop St N",
    "iso:country":"CA",
    "sg:address":"275 Bishop St N",
    "sg:city":"Alexandria",
    "sg:classifiers":[
        {
            "category":"Building & Trades",
            "subcategory":"Plumbing",
            "type":"Services"
        }
    ],
    "sg:phone":"+1 613 525 1685",
    "sg:postcode":"K0C 1A0",
    "sg:province":"ON",
    "sg:tags":[
        "air",
        "conditioning",
        "oil",
        "system",
        "contractor"
    ],
    "wof:name":"Mac Ewen Petroleum Inc",
    "wof:placetype":"venue"
},
  "geometry": {"coordinates":[-74.63855,45.317116],"type":"Point"}
}