{
  "type": "Feature",
  "properties": {
    "addr:full":"Rte 107 Blueshank Rd Kensington PE C0B 1M0",
    "addr:postcode":"c0b 1m0",
    "addr:street":"Rte 107 Blueshank Rd",
    "iso:country":"CA",
    "sg:address":"Rte 107 Blueshank Rd",
    "sg:city":"Kensington",
    "sg:classifiers":[
        {
            "category":"Shopping",
            "subcategory":"Clothing, Apparel, & Fashions",
            "type":"Retail Goods"
        }
    ],
    "sg:phone":"+1 902 836 5342",
    "sg:postcode":"C0B 1M0",
    "sg:province":"PE",
    "sg:tags":[
        "shop",
        "bridal"
    ],
    "wof:name":"Caseley's Bridal Boutique",
    "wof:placetype":"venue"
},
  "geometry": {"coordinates":[-63.6368484497,46.436882019],"type":"Point"}
}