{
  "type": "Feature",
  "properties": {
    "addr:full":"90 Chedmac Dr Hamilton ON L9C 7W1",
    "addr:housenumber":"90",
    "addr:postcode":"l9c 7w1",
    "addr:street":"Chedmac Dr",
    "iso:country":"CA",
    "sg:address":"90 Chedmac Dr",
    "sg:city":"Hamilton",
    "sg:classifiers":[
        {
            "category":"Health Services",
            "subcategory":"Nursing And Care Facility",
            "type":"Services"
        }
    ],
    "sg:phone":"+1 905 318 4472",
    "sg:postcode":"L9C 7W1",
    "sg:province":"ON",
    "sg:tags":[
        "home",
        "convalescent"
    ],
    "wof:name":"Extendicare Hamilton",
    "wof:placetype":"venue"
},
  "geometry": {"coordinates":[-79.921738,43.239838],"type":"Point"}
}