{
  "type": "Feature",
  "properties": {
    "addr:full":"590 Gerrard St E Toronto ON M4M 1Y3",
    "addr:housenumber":"590",
    "addr:postcode":"m4m 1y3",
    "addr:street":"Gerrard St E",
    "iso:country":"CA",
    "sg:address":"590 Gerrard St E",
    "sg:city":"Toronto",
    "sg:classifiers":[
        {
            "category":"Shopping",
            "type":"Retail Goods"
        }
    ],
    "sg:phone":"+1 416 461 5362",
    "sg:postcode":"M4M 1Y3",
    "sg:province":"ON",
    "sg:tags":[
        "pet",
        "shop"
    ],
    "wof:name":"Wongs Aquarium",
    "wof:placetype":"venue"
},
  "geometry": {"coordinates":[-79.35142500000001,43.66584],"type":"Point"}
}