{
  "type": "Feature",
  "properties": {
    "addr:full":"13445 97 St NW Edmonton AB T5E 4C7",
    "addr:housenumber":"13445",
    "addr:postcode":"t5e 4c7",
    "addr:street":"97 St Nw",
    "iso:country":"CA",
    "sg:address":"13445 97 St NW",
    "sg:city":"Edmonton",
    "sg:classifiers":[
        {
            "category":"Restaurant",
            "type":"Food & Drink"
        }
    ],
    "sg:phone":"+1 780 478 9430",
    "sg:postcode":"T5E 4C7",
    "sg:province":"AB",
    "sg:tags":[
        "shop",
        "coffee"
    ],
    "wof:name":"Second Cup",
    "wof:placetype":"venue"
},
  "geometry": {"coordinates":[-113.491821,53.596394],"type":"Point"}
}