{
  "type": "Feature",
  "properties": {
    "addr:full":"1810 Georgia St E Vancouver BC V5L 2B6",
    "addr:housenumber":"1810",
    "addr:postcode":"v5l 2b6",
    "addr:street":"Georgia St E",
    "iso:country":"CA",
    "sg:address":"1810 Georgia St E",
    "sg:city":"Vancouver",
    "sg:classifiers":[
        {
            "category":"Real Estate",
            "subcategory":"Real Estate Agent",
            "type":"Services"
        }
    ],
    "sg:phone":"+1 604 258 4123",
    "sg:postcode":"V5L 2B6",
    "sg:province":"BC",
    "sg:tags":[
        "authorities",
        "housing"
    ],
    "wof:name":"Haley Place",
    "wof:placetype":"venue"
},
  "geometry": {"coordinates":[-123.067802429,49.278339386],"type":"Point"}
}