{
  "type": "Feature",
  "properties": {
    "addr:full":"1270 208 St Langley BC V2Z 1T3",
    "addr:housenumber":"1270",
    "addr:postcode":"v2z 1t3",
    "addr:street":"208 St",
    "iso:country":"CA",
    "sg:address":"1270 208 St",
    "sg:city":"Langley",
    "sg:classifiers":[
        {
            "category":"Wholesale",
            "subcategory":"Construction Materials",
            "type":"Manufacturing & Wholesale Goods"
        }
    ],
    "sg:phone":"+1 604 514 8766",
    "sg:postcode":"V2Z 1T3",
    "sg:province":"BC",
    "sg:tags":[
        "sand",
        "gravel"
    ],
    "wof:name":"Campbell Valley Trucking",
    "wof:placetype":"venue"
},
  "geometry": {"coordinates":[-122.646843,49.025707],"type":"Point"}
}