{
  "type": "Feature",
  "properties": {
    "addr:full":"435 Av Lariviere Rouyn-Noranda QC J9X 4H9",
    "addr:housenumber":"435",
    "addr:postcode":"j9x 4h9",
    "addr:street":"Av Lariviere",
    "iso:country":"CA",
    "sg:address":"435 Av Lariviere",
    "sg:city":"Rouyn-Noranda",
    "sg:classifiers":[
        {
            "category":"Cinema",
            "subcategory":"Movie Rental",
            "type":"Entertainment"
        }
    ],
    "sg:phone":"+1 819 764 4171",
    "sg:postcode":"J9X 4H9",
    "sg:province":"QC",
    "sg:tags":[
        "leasing",
        "video",
        "disc",
        "tape"
    ],
    "wof:name":"Video Super Choix",
    "wof:placetype":"venue"
},
  "geometry": {"coordinates":[-79.014351,48.230778],"type":"Point"}
}