{
  "type": "Feature",
  "properties": {
    "addr:full":"5300 No. 3 Rd Richmond BC V6X 2X9",
    "addr:postcode":"5300;v6x 2x9",
    "addr:street":"3 Rd",
    "iso:country":"CA",
    "sg:address":"5300 No. 3 Rd",
    "sg:city":"Richmond",
    "sg:classifiers":[
        {
            "category":"Professional",
            "subcategory":"Accounting & Tax Preparation",
            "type":"Services"
        }
    ],
    "sg:phone":"+1 604 244 5994",
    "sg:postcode":"V6X 2X9",
    "sg:province":"BC",
    "sg:tags":[
        "consultant",
        "return",
        "filing"
    ],
    "wof:name":"H & R Block Canada Inc",
    "wof:placetype":"venue"
},
  "geometry": {"coordinates":[-123.136292,49.175171],"type":"Point"}
}