{
  "type": "Feature",
  "properties": {
    "addr:full":"1514 Av Saint-Edouard Plessisville QC G6L 2K3",
    "addr:housenumber":"1514",
    "addr:postcode":"g6l 2k3",
    "addr:street":"Av Saint-Edouard",
    "iso:country":"CA",
    "sg:address":"1514 Av Saint-Edouard",
    "sg:city":"Plessisville",
    "sg:classifiers":[
        {
            "category":"Government",
            "subcategory":"Police Station",
            "type":"Public Place"
        }
    ],
    "sg:phone":"+1 819 362 6331",
    "sg:postcode":"G6L 2K3",
    "sg:province":"QC",
    "sg:tags":[
        "department"
    ],
    "wof:name":"Plessisville Police",
    "wof:placetype":"venue"
},
  "geometry": {"coordinates":[-71.7715911865,46.2185249329],"type":"Point"}
}