{
  "type": "Feature",
  "properties": {
    "addr:full":"95 Ritchie Ave Ajax ON L1S 6S2",
    "addr:housenumber":"95",
    "addr:postcode":"l1s 6s2",
    "addr:street":"Ritchie Ave",
    "iso:country":"CA",
    "sg:address":"95 Ritchie Ave",
    "sg:city":"Ajax",
    "sg:classifiers":[
        {
            "category":"Social Services",
            "subcategory":"Child Care",
            "type":"Services"
        }
    ],
    "sg:phone":"+1 905 686 5440",
    "sg:postcode":"L1S 6S2",
    "sg:province":"ON",
    "wof:name":"Schoolhouse Playcare Ctr",
    "wof:placetype":"venue"
},
  "geometry": {"coordinates":[-79.038071,43.854836],"type":"Point"}
}