{
  "type": "Feature",
  "properties": {
    "addr:full":"491 Steeles Ave E Milton ON L9T 1Y7",
    "addr:housenumber":"491",
    "addr:postcode":"l9t 1y7",
    "addr:street":"Steeles Ave E",
    "iso:country":"CA",
    "sg:address":"491 Steeles Ave E",
    "sg:city":"Milton",
    "sg:classifiers":[
        {
            "category":"Government",
            "subcategory":"Office",
            "type":"Public Place"
        }
    ],
    "sg:phone":"+1 905 878 4165",
    "sg:postcode":"L9T 1Y7",
    "sg:province":"ON",
    "wof:name":"Ontario Provincial Criminal",
    "wof:placetype":"venue"
},
  "geometry": {"coordinates":[-79.88719940190001,43.5278167725],"type":"Point"}
}