{
  "type": "Feature",
  "properties": {
    "addr:full":"Burnaby BC V5H 2E4",
    "addr:postcode":"v5h 2e4",
    "iso:country":"CA",
    "sg:city":"Burnaby",
    "sg:classifiers":[
        {
            "category":"Health Services",
            "subcategory":"Doctor",
            "type":"Services"
        }
    ],
    "sg:phone":"+1 604 434 2511",
    "sg:postcode":"V5H 2E4",
    "sg:province":"BC",
    "sg:tags":[
        "dentist"
    ],
    "wof:name":"Advance Dental Clinic",
    "wof:placetype":"venue"
},
  "geometry": {"coordinates":[-122.992538,49.226048],"type":"Point"}
}