{
  "type": "Feature",
  "properties": {
    "addr:full":"460 Macewan St Goderich ON N7A 4C7",
    "addr:housenumber":"460",
    "addr:postcode":"n7a 4c7",
    "addr:street":"Macewan St",
    "iso:country":"CA",
    "sg:address":"460 Macewan St",
    "sg:city":"Goderich",
    "sg:classifiers":[
        {
            "category":"Freight",
            "type":"Transportation"
        }
    ],
    "sg:phone":"+1 519 524 2111",
    "sg:postcode":"N7A 4C7",
    "sg:province":"ON",
    "sg:tags":[
        "commercial",
        "storage"
    ],
    "wof:name":"Woodway Enterprises Inc",
    "wof:placetype":"venue"
},
  "geometry": {"coordinates":[-81.699546814,43.7278823853],"type":"Point"}
}