{
  "type": "Feature",
  "properties": {
    "addr:full":"Montreal QC H2Y 2P5",
    "addr:postcode":"h2y 2p5",
    "iso:country":"CA",
    "sg:city":"Montreal",
    "sg:classifiers":[
        {
            "category":"Professional",
            "subcategory":"Management & Consulting",
            "type":"Services"
        }
    ],
    "sg:phone":"+1 514 499 0997",
    "sg:postcode":"H2Y 2P5",
    "sg:province":"QC",
    "sg:tags":[
        "consultant",
        "business"
    ],
    "wof:name":"Frappier St-Denis & Assoc",
    "wof:placetype":"venue"
},
  "geometry": {"coordinates":[-73.5560531616,45.5020523071],"type":"Point"}
}