{
  "type": "Feature",
  "properties": {
    "addr:full":"1370 Rue Labadie Longueuil QC J4N 1C7",
    "addr:housenumber":"1370",
    "addr:postcode":"j4n 1c7",
    "addr:street":"Rue Labadie",
    "iso:country":"CA",
    "sg:address":"1370 Rue Labadie",
    "sg:city":"Longueuil",
    "sg:classifiers":[
        {
            "category":"Wholesale",
            "subcategory":"Machinery & Supplies",
            "type":"Manufacturing & Wholesale Goods"
        }
    ],
    "sg:phone":"+1 450 646 3038",
    "sg:postcode":"J4N 1C7",
    "sg:province":"QC",
    "sg:tags":[
        "truck"
    ],
    "wof:name":"Multi Chariots Elevateurs",
    "wof:placetype":"venue"
},
  "geometry": {"coordinates":[-73.45352172849999,45.5650978088],"type":"Point"}
}