{
  "type": "Feature",
  "properties": {
    "addr:full":"5000 Rue Jean-Talon O Montreal QC H4P 1W9",
    "addr:housenumber":"5000",
    "addr:postcode":"h4p 1w9",
    "addr:street":"Rue Jean-Talon O",
    "iso:country":"CA",
    "sg:address":"5000 Rue Jean-Talon O",
    "sg:city":"Montreal",
    "sg:classifiers":[
        {
            "category":"Insurance",
            "subcategory":"Insurance Agent",
            "type":"Services"
        }
    ],
    "sg:phone":"+1 514 341 7111",
    "sg:postcode":"H4P 1W9",
    "sg:province":"QC",
    "sg:tags":[
        "adjuster"
    ],
    "wof:name":"Bourdon Juteau & Assoc Inc",
    "wof:placetype":"venue"
},
  "geometry": {"coordinates":[-73.6496124268,45.4969787598],"type":"Point"}
}