{
  "type": "Feature",
  "properties": {
    "addr:full":"710 Idylwyld Dr N Saskatoon SK S7L 0Z2",
    "addr:housenumber":"710",
    "addr:postcode":"s7l 0z2",
    "addr:street":"Idylwyld Dr N",
    "iso:country":"CA",
    "sg:address":"710 Idylwyld Dr N",
    "sg:city":"Saskatoon",
    "sg:classifiers":[
        {
            "category":"Bars & Pubs",
            "type":"Food & Drink"
        }
    ],
    "sg:phone":"+1 306 978 0808",
    "sg:postcode":"S7L 0Z2",
    "sg:province":"SK",
    "sg:tags":[
        "club",
        "night"
    ],
    "wof:name":"Overdrive",
    "wof:placetype":"venue"
},
  "geometry": {"coordinates":[-106.669899,52.13633],"type":"Point"}
}