{
  "type": "Feature",
  "properties": {
    "iso:country":"CA",
    "sg:address":"1450 Rue DE Wagram",
    "sg:city":"Longueuil",
    "sg:classifiers":[
        {
            "category":"Education",
            "subcategory":"School",
            "type":"Public Place"
        }
    ],
    "sg:phone":"+1 450 651 7768",
    "sg:postcode":"J4K 1G1",
    "sg:province":"QC",
    "wof:name":"Ecole Felix-Leclerc",
    "wof:placetype":"venue"
},
  "geometry": {"coordinates":[-73.51413,45.516178],"type":"Point"}
}