{
  "type": "Feature",
  "properties": {
    "addr:full":"1450 Rue DE Wagram Longueuil QC J4K 1G1",
    "addr:housenumber":"1450",
    "addr:postcode":"j4k 1g1",
    "addr:street":"Rue De Wagram",
    "iso:country":"CA",
    "sg:address":"1450 Rue DE Wagram",
    "sg:city":"Longueuil",
    "sg:classifiers":[
        {
            "category":"Education",
            "subcategory":"School",
            "type":"Public Place"
        }
    ],
    "sg:phone":"+1 450 651 7768",
    "sg:postcode":"J4K 1G1",
    "sg:province":"QC",
    "wof:name":"Ecole Felix-Leclerc",
    "wof:placetype":"venue"
},
  "geometry": {"coordinates":[-73.51412999999999,45.516178],"type":"Point"}
}