{
  "type": "Feature",
  "properties": {
    "iso:country":"CA",
    "sg:address":"839 Principale St",
    "sg:city":"Rougemont",
    "sg:classifiers":[
        {
            "category":"Education",
            "subcategory":"Library",
            "type":"Public Place"
        }
    ],
    "sg:phone":"+1 450 469 3213",
    "sg:postcode":"J0L 1M0",
    "sg:province":"QC",
    "wof:name":"Rougemont Bibliotheque",
    "wof:placetype":"venue"
},
  "geometry": {"coordinates":[-73.0569152832,45.4383773804],"type":"Point"}
}