{
  "type": "Feature",
  "properties": {
    "addr:full":"700 Tecumseh Rd E # 301 Windsor ON N8X 4T2",
    "addr:housenumber":"700;301",
    "addr:postcode":"n8x 4t2",
    "addr:street":"Tecumseh Rd E #",
    "iso:country":"CA",
    "sg:address":"700 Tecumseh Rd E # 301",
    "sg:city":"Windsor",
    "sg:classifiers":[
        {
            "category":"Health Services",
            "subcategory":"Doctor",
            "type":"Services"
        }
    ],
    "sg:phone":"+1 519 973 1527",
    "sg:postcode":"N8X 4T2",
    "sg:province":"ON",
    "sg:tags":[
        "dentist"
    ],
    "wof:name":"Smith, Paul F DDS",
    "wof:placetype":"venue"
},
  "geometry": {"coordinates":[-83.014374,42.29866],"type":"Point"}
}