{
  "type": "Feature",
  "properties": {
    "addr:full":"1365 117 Rte Mont-Tremblant QC J8E 2X9",
    "addr:housenumber":"1365",
    "addr:postcode":"j8e 2x9",
    "addr:street":"117 Rte",
    "iso:country":"CA",
    "sg:address":"1365 117 Rte",
    "sg:city":"Mont-Tremblant",
    "sg:classifiers":[
        {
            "category":"Restaurant",
            "type":"Food & Drink"
        }
    ],
    "sg:phone":"+1 819 425 8592",
    "sg:postcode":"J8E 2X9",
    "sg:province":"QC",
    "wof:name":"Patates Ben Venue",
    "wof:placetype":"venue"
},
  "geometry": {"coordinates":[-74.60819244379999,46.1212463379],"type":"Point"}
}