{
  "type": "Feature",
  "properties": {
    "addr:full":"Brockville ON K6V 1A8",
    "addr:postcode":"k6v 1a8",
    "iso:country":"CA",
    "sg:city":"Brockville",
    "sg:classifiers":[
        {
            "category":"Professional",
            "subcategory":"Employment Agencies",
            "type":"Services"
        }
    ],
    "sg:phone":"+1 613 342 2312",
    "sg:postcode":"K6V 1A8",
    "sg:province":"ON",
    "sg:tags":[
        "training",
        "computer",
        "co",
        "fraternal"
    ],
    "wof:name":"Cse Consulting",
    "wof:placetype":"venue"
},
  "geometry": {"coordinates":[-75.68126700000001,44.591316],"type":"Point"}
}