{
  "type": "Feature",
  "properties": {
    "addr:full":"525 4 St SE Medicine Hat AB T1A 0K7",
    "addr:housenumber":"525 4",
    "addr:postcode":"t1a 0k7",
    "addr:street":"St Se",
    "iso:country":"CA",
    "sg:address":"525 4 St SE",
    "sg:city":"Medicine Hat",
    "sg:classifiers":[
        {
            "category":"Insurance",
            "subcategory":"Insurance Agent",
            "type":"Services"
        }
    ],
    "sg:phone":"+1 403 526 8800",
    "sg:postcode":"T1A 0K7",
    "sg:province":"AB",
    "wof:name":"Andrews, Adam",
    "wof:placetype":"venue"
},
  "geometry": {"coordinates":[-110.676361,50.038288],"type":"Point"}
}