{
  "type": "Feature",
  "properties": {
    "addr:full":"520 Para Ave Van Anda BC V0N 3K0",
    "addr:housenumber":"520",
    "addr:postcode":"v0n 3k0",
    "addr:street":"Para Ave Van",
    "iso:country":"CA",
    "sg:address":"520 Para Ave",
    "sg:city":"Van Anda",
    "sg:classifiers":[
        {
            "category":"Manufacturing",
            "subcategory":"Lumber",
            "type":"Manufacturing & Wholesale Goods"
        }
    ],
    "sg:phone":"+1 604 486 7369",
    "sg:postcode":"V0N 3K0",
    "sg:province":"BC",
    "sg:tags":[
        "company",
        "logging"
    ],
    "wof:name":"Jmg Logging Ltd",
    "wof:placetype":"venue"
},
  "geometry": {"coordinates":[-124.554779,49.756359],"type":"Point"}
}