{
  "type": "Feature",
  "properties": {
    "iso:country":"CA",
    "sg:address":"1771 Albion Rd",
    "sg:city":"Etobicoke",
    "sg:classifiers":[
        {
            "category":"Restaurant",
            "type":"Food & Drink"
        }
    ],
    "sg:phone":"+1 416 675 3212",
    "sg:postcode":"M9W 5S7",
    "sg:province":"ON",
    "sg:tags":[
        "banquet",
        "rooms"
    ],
    "wof:name":"Forum Banquet Halls",
    "wof:placetype":"venue"
},
  "geometry": {"coordinates":[-79.6096878052,43.7445373535],"type":"Point"}
}