{
  "type": "Feature",
  "properties": {
    "addr:full":"3294 Sandwich St Windsor ON N9C 4G6",
    "addr:housenumber":"3294",
    "addr:postcode":"n9c 4g6",
    "addr:street":"Sandwich St",
    "iso:country":"CA",
    "sg:address":"3294 Sandwich St",
    "sg:city":"Windsor",
    "sg:classifiers":[
        {
            "category":"Social Services",
            "type":"Services"
        }
    ],
    "sg:phone":"+1 519 971 0134",
    "sg:postcode":"N9C 4G6",
    "sg:province":"ON",
    "sg:tags":[
        "housing",
        "assistance"
    ],
    "wof:name":"Westgate",
    "wof:placetype":"venue"
},
  "geometry": {"coordinates":[-83.07698822019999,42.3001174927],"type":"Point"}
}