{
  "type": "Feature",
  "properties": {
    "addr:full":"401 Railway Ave Colonsay SK S0K 0Z0",
    "addr:housenumber":"401",
    "addr:postcode":"s0k 0z0",
    "addr:street":"Railway Ave",
    "iso:country":"CA",
    "sg:address":"401 Railway Ave",
    "sg:city":"Colonsay",
    "sg:classifiers":[
        {
            "category":"Government",
            "subcategory":"Fire Station",
            "type":"Public Place"
        }
    ],
    "sg:phone":"+1 ",
    "sg:postcode":"S0K 0Z0",
    "sg:province":"SK",
    "sg:tags":[
        "department"
    ],
    "wof:name":"Colonsay Fire Hall",
    "wof:placetype":"venue"
},
  "geometry": {"coordinates":[-105.877464,51.982735],"type":"Point"}
}