{
  "type": "Feature",
  "properties": {
    "addr:full":"772 Dovercourt Rd Toronto ON M6H 2X2",
    "addr:housenumber":"772",
    "addr:postcode":"m6h 2x2",
    "addr:street":"Dovercourt Rd",
    "iso:country":"CA",
    "sg:address":"772 Dovercourt Rd",
    "sg:city":"Toronto",
    "sg:classifiers":[
        {
            "category":"Government",
            "subcategory":"Post Office",
            "type":"Public Place"
        }
    ],
    "sg:phone":"+1 416 531 3910",
    "sg:postcode":"M6H 2X2",
    "sg:province":"ON",
    "wof:name":"Canada Post Corp",
    "wof:placetype":"venue"
},
  "geometry": {"coordinates":[-79.4297866821,43.6618995667],"type":"Point"}
}