{
  "type": "Feature",
  "properties": {
    "addr:full":"1321 Third Ave New Westminster BC V3M 1R3",
    "addr:housenumber":"1321",
    "addr:postcode":"v3m 1r3",
    "addr:street":"Third Ave",
    "iso:country":"CA",
    "sg:address":"1321 Third Ave",
    "sg:city":"New Westminster",
    "sg:classifiers":[
        {
            "category":"Retail",
            "subcategory":"Auto Repair",
            "type":"Services"
        }
    ],
    "sg:phone":"+1 604 526 5444",
    "sg:postcode":"V3M 1R3",
    "sg:province":"BC",
    "sg:tags":[
        "body",
        "automobile",
        "painting"
    ],
    "wof:name":"Boyd Autobody & Glass",
    "wof:placetype":"venue"
},
  "geometry": {"coordinates":[-122.92752075200001,49.201751709],"type":"Point"}
}