{
  "type": "Feature",
  "properties": {
    "iso:country":"CA",
    "sg:address":"12222 137 Ave NW # 1222",
    "sg:city":"Edmonton",
    "sg:classifiers":[
        {
            "category":"Shopping",
            "type":"Retail Goods"
        }
    ],
    "sg:phone":"+1 780 456 7976",
    "sg:postcode":"T5L 4X5",
    "sg:province":"AB",
    "sg:tags":[
        "pet",
        "grooming",
        "washing",
        "supply"
    ],
    "wof:name":"Petcetera",
    "wof:placetype":"venue"
},
  "geometry": {"coordinates":[-113.532264709,53.59973526],"type":"Point"}
}