{
  "type": "Feature",
  "properties": {
    "addr:full":"161 Holland Ave Ottawa ON K1Y 0Y2",
    "addr:housenumber":"161",
    "addr:postcode":"k1y 0y2",
    "addr:street":"Holland Ave",
    "iso:country":"CA",
    "sg:address":"161 Holland Ave",
    "sg:city":"Ottawa",
    "sg:classifiers":[
        {
            "category":"Manufacturing",
            "subcategory":"Jewelry",
            "type":"Manufacturing & Wholesale Goods"
        }
    ],
    "sg:phone":"+1 613 725 2210",
    "sg:postcode":"K1Y 0Y2",
    "sg:province":"ON",
    "wof:name":"Goldform Manufacturing Jwlrs",
    "wof:placetype":"venue"
},
  "geometry": {"coordinates":[-75.731087,45.398571],"type":"Point"}
}