{
  "type": "Feature",
  "properties": {
    "addr:full":"383 Rue Papillon Laval QC H7K 2L5",
    "addr:housenumber":"383",
    "addr:postcode":"qc h7k 2l5",
    "addr:street":"Rue Papillon",
    "iso:country":"CA",
    "sg:address":"383 Rue Papillon",
    "sg:city":"Laval",
    "sg:classifiers":[
        {
            "category":"Building & Trades",
            "subcategory":"Electrical",
            "type":"Services"
        }
    ],
    "sg:phone":"+1 450 628 8445",
    "sg:postcode":"H7K 2L5",
    "sg:province":"QC",
    "sg:tags":[
        "electric",
        "contractor"
    ],
    "wof:name":"Entreprises D'Electricite",
    "wof:placetype":"venue"
},
  "geometry": {"coordinates":[-73.74421700000001,45.627014],"type":"Point"}
}