{
  "type": "Feature",
  "properties": {
    "iso:country":"CA",
    "sg:address":"383 Rue Papillon",
    "sg:city":"Laval",
    "sg:classifiers":[
        {
            "category":"Building & Trades",
            "subcategory":"Electrical",
            "type":"Services"
        }
    ],
    "sg:phone":"+1 450 628 8445",
    "sg:postcode":"H7K 2L5",
    "sg:province":"QC",
    "sg:tags":[
        "electric",
        "contractor"
    ],
    "wof:name":"Entreprises D'Electricite",
    "wof:placetype":"venue"
},
  "geometry": {"coordinates":[-73.744217,45.627014],"type":"Point"}
}