{
  "type": "Feature",
  "properties": {
    "addr:full":"Gaspe QC G4X 5N7",
    "addr:postcode":"g4x 5n7",
    "iso:country":"CA",
    "sg:city":"Gaspe",
    "sg:classifiers":[
        {
            "category":"Wholesale",
            "subcategory":"Construction Materials",
            "type":"Manufacturing & Wholesale Goods"
        }
    ],
    "sg:phone":"+1 418 269 5961",
    "sg:postcode":"G4X 5N7",
    "sg:province":"QC",
    "sg:tags":[
        "sand",
        "gravel"
    ],
    "wof:name":"Plourde Jacques Transport Enr",
    "wof:placetype":"venue"
},
  "geometry": {"coordinates":[-64.416237,48.988914],"type":"Point"}
}