{
  "type": "Feature",
  "properties": {
    "addr:full":"Hull QC J8Z 1A4",
    "addr:postcode":"j8z 1a4",
    "iso:country":"CA",
    "sg:city":"Hull",
    "sg:classifiers":[
        {
            "category":"Banks & Credit Unions",
            "subcategory":"Investment Brokerage",
            "type":"Services"
        }
    ],
    "sg:phone":"+1 819 771 7777",
    "sg:postcode":"J8Z 1A4",
    "sg:province":"QC",
    "sg:tags":[
        "consultant",
        "planning",
        "financial"
    ],
    "wof:name":"Marcotte & Marcotte",
    "wof:placetype":"venue"
},
  "geometry": {"coordinates":[-75.7660903931,45.4638252258],"type":"Point"}
}