{
  "type": "Feature",
  "properties": {
    "addr:full":"1705 Corydon Ave Winnipeg MB R3N 0J9",
    "addr:housenumber":"1705",
    "addr:postcode":"r3n 0j9",
    "addr:street":"Corydon Ave",
    "iso:country":"CA",
    "sg:address":"1705 Corydon Ave",
    "sg:city":"Winnipeg",
    "sg:classifiers":[
        {
            "category":"Manufacturing",
            "subcategory":"Jewelry",
            "type":"Manufacturing & Wholesale Goods"
        }
    ],
    "sg:phone":"+1 204 488 9813",
    "sg:postcode":"R3N 0J9",
    "sg:province":"MB",
    "sg:tags":[
        "jeweler"
    ],
    "wof:name":"A Diamond Gallery",
    "wof:placetype":"venue"
},
  "geometry": {"coordinates":[-97.196808,49.863976],"type":"Point"}
}