{
  "type": "Feature",
  "properties": {
    "addr:full":"Kelowna BC V1Y 8C7",
    "addr:postcode":"v1y 8c7",
    "iso:country":"CA",
    "sg:city":"Kelowna",
    "sg:classifiers":[
        {
            "category":"Banks & Credit Unions",
            "subcategory":"Bank",
            "type":"Services"
        }
    ],
    "sg:phone":"+1 250 861 7070",
    "sg:postcode":"V1Y 8C7",
    "sg:province":"BC",
    "sg:tags":[
        "loan",
        "real estate"
    ],
    "wof:name":"Capri Mortgage Corp",
    "wof:placetype":"venue"
},
  "geometry": {"coordinates":[-119.495872498,49.8844032288],"type":"Point"}
}