{
  "type": "Feature",
  "properties": {
    "addr:full":"Norwood ON K0L 2V0",
    "addr:postcode":"k0l 2v0",
    "iso:country":"CA",
    "sg:city":"Norwood",
    "sg:classifiers":[
        {
            "category":"Wholesale",
            "subcategory":"Construction Materials",
            "type":"Manufacturing & Wholesale Goods"
        }
    ],
    "sg:phone":"+1 705 639 2349",
    "sg:postcode":"K0L 2V0",
    "sg:province":"ON",
    "sg:tags":[
        "home",
        "improvement",
        "form",
        "concrete"
    ],
    "wof:name":"Greenblock",
    "wof:placetype":"venue"
},
  "geometry": {"coordinates":[-77.977547,44.381191],"type":"Point"}
}