{
  "type": "Feature",
  "properties": {
    "addr:full":"832 Brock St N Whitby ON L1N 4J5",
    "addr:housenumber":"832",
    "addr:postcode":"l1n 4j5",
    "addr:street":"Brock St N",
    "iso:country":"CA",
    "sg:address":"832 Brock St N",
    "sg:city":"Whitby",
    "sg:classifiers":[
        {
            "category":"Retail",
            "subcategory":"Auto Repair",
            "type":"Services"
        }
    ],
    "sg:phone":"+1 905 430 7577",
    "sg:postcode":"L1N 4J5",
    "sg:province":"ON",
    "sg:tags":[
        "repairing",
        "automobile"
    ],
    "wof:name":"Master Mechanic Whitby",
    "wof:placetype":"venue"
},
  "geometry": {"coordinates":[-78.94697600000001,43.890797],"type":"Point"}
}