{
  "type": "Feature",
  "properties": {
    "iso:country":"CA",
    "sg:address":"450 Nathaniel St",
    "sg:city":"Winnipeg",
    "sg:classifiers":[
        {
            "category":"Education",
            "subcategory":"School",
            "type":"Public Place"
        }
    ],
    "sg:phone":"+1 204 452 3112",
    "sg:postcode":"R3M 3E3",
    "sg:province":"MB",
    "wof:name":"Grant Park High School",
    "wof:placetype":"venue"
},
  "geometry": {"coordinates":[-97.169174,49.85643],"type":"Point"}
}