{
  "type": "Feature",
  "properties": {
    "addr:full":"818 Broughton St Victoria BC V8W 1E4",
    "addr:housenumber":"818",
    "addr:postcode":"v8w 1e4",
    "addr:street":"Broughton St",
    "iso:country":"CA",
    "sg:address":"818 Broughton St",
    "sg:city":"Victoria",
    "sg:classifiers":[
        {
            "category":"Manufacturing",
            "subcategory":"Printing",
            "type":"Manufacturing & Wholesale Goods"
        }
    ],
    "sg:phone":"+1 250 388 3676",
    "sg:postcode":"V8W 1E4",
    "sg:province":"BC",
    "sg:tags":[
        "publisher",
        "guide"
    ],
    "wof:name":"Visitor Publications Group",
    "wof:placetype":"venue"
},
  "geometry": {"coordinates":[-123.36196099999999,48.423553],"type":"Point"}
}