{
  "type": "Feature",
  "properties": {
    "addr:full":"180 Mcnaughton Ave W Chatham ON N7L 4Z7",
    "addr:housenumber":"180",
    "addr:postcode":"n7l 4z7",
    "addr:street":"Mcnaughton Ave W",
    "iso:country":"CA",
    "sg:address":"180 Mcnaughton Ave W",
    "sg:city":"Chatham",
    "sg:classifiers":[
        {
            "category":"Shopping",
            "subcategory":"Pharmacy",
            "type":"Retail Goods"
        }
    ],
    "sg:phone":"+1 519 358 1377",
    "sg:postcode":"N7L 4Z7",
    "sg:province":"ON",
    "wof:name":"Mc Naughton Pharma Plus",
    "wof:placetype":"venue"
},
  "geometry": {"coordinates":[-82.205521,42.411118],"type":"Point"}
}