{
  "type": "Feature",
  "properties": {
    "addr:full":"44 Smith St Kitimat BC V8C 2R5",
    "addr:housenumber":"44",
    "addr:postcode":"bc v8c 2r5",
    "addr:street":"Smith St",
    "iso:country":"CA",
    "sg:address":"44 Smith St",
    "sg:city":"Kitimat",
    "sg:classifiers":[
        {
            "category":"Freight",
            "type":"Transportation"
        }
    ],
    "sg:phone":"+1 250 632 7312",
    "sg:postcode":"V8C 2R5",
    "sg:province":"BC",
    "sg:tags":[
        "trucking"
    ],
    "wof:name":"J T Contracting",
    "wof:placetype":"venue"
},
  "geometry": {"coordinates":[-128.623108,54.061451],"type":"Point"}
}