{
  "type": "Feature",
  "properties": {
    "addr:full":"622 7th Ave Keremeos BC V0X 1N0",
    "addr:housenumber":"622",
    "addr:postcode":"v0x 1n0",
    "addr:street":"7Th Ave",
    "iso:country":"CA",
    "sg:address":"622 7th Ave",
    "sg:city":"Keremeos",
    "sg:classifiers":[
        {
            "category":"Shopping",
            "subcategory":"Catalog Store",
            "type":"Retail Goods"
        }
    ],
    "sg:phone":"+1 250 499 2733",
    "sg:postcode":"V0X 1N0",
    "sg:province":"BC",
    "sg:tags":[
        "mail",
        "order",
        "internet"
    ],
    "wof:name":"Sears Canada Inc",
    "wof:placetype":"venue"
},
  "geometry": {"coordinates":[-119.82459299999999,49.205345],"type":"Point"}
}