{
  "type": "Feature",
  "properties": {
    "addr:full":"8401 Weston Rd Woodbridge ON L4L 1A6",
    "addr:housenumber":"8401",
    "addr:postcode":"l4l 1a6",
    "addr:street":"Weston Rd",
    "iso:country":"CA",
    "sg:address":"8401 Weston Rd",
    "sg:city":"Woodbridge",
    "sg:classifiers":[
        {
            "category":"Food & Beverages",
            "subcategory":"Fruits & Vegetables",
            "type":"Retail Goods"
        }
    ],
    "sg:phone":"+1 905 850 6161",
    "sg:postcode":"L4L 1A6",
    "sg:province":"ON",
    "sg:tags":[
        "produce"
    ],
    "wof:name":"Longo's",
    "wof:placetype":"venue"
},
  "geometry": {"coordinates":[-79.5513687134,43.8065948486],"type":"Point"}
}