{
  "type": "Feature",
  "properties": {
    "addr:full":"2965 Islington Ave #12 North York ON M9L 2K8",
    "addr:housenumber":"2965",
    "addr:postcode":"m9l 2k8",
    "addr:street":"Islington Ave # 12",
    "iso:country":"CA",
    "sg:address":"2965 Islington Ave #12",
    "sg:city":"North York",
    "sg:classifiers":[
        {
            "category":"Wholesale",
            "subcategory":"Groceries",
            "type":"Manufacturing & Wholesale Goods"
        }
    ],
    "sg:phone":"+1 416 748 6272",
    "sg:postcode":"M9L 2K8",
    "sg:province":"ON",
    "sg:tags":[
        "baker"
    ],
    "wof:name":"Pina Italian Bakery Inc",
    "wof:placetype":"venue"
},
  "geometry": {"coordinates":[-79.56991577150001,43.7576904297],"type":"Point"}
}