{
  "type": "Feature",
  "properties": {
    "addr:full":"Halifax NS B3L 2C2",
    "addr:postcode":"b3l 2c2",
    "iso:country":"CA",
    "sg:city":"Halifax",
    "sg:classifiers":[
        {
            "category":"Retail",
            "subcategory":"Photofinishing",
            "type":"Services"
        }
    ],
    "sg:phone":"+1 902 455 0479",
    "sg:postcode":"B3L 2C2",
    "sg:province":"NS",
    "sg:tags":[
        "photo",
        "finishing"
    ],
    "wof:name":"Econo Color One Hour Photo",
    "wof:placetype":"venue"
},
  "geometry": {"coordinates":[-63.627281189,44.6537399292],"type":"Point"}
}