{
  "type": "Feature",
  "properties": {
    "addr:full":"5585 Av Auteuil Brossard QC J4Z 1M3",
    "addr:housenumber":"5585",
    "addr:postcode":"j4z 1m3",
    "addr:street":"Av Auteuil",
    "iso:country":"CA",
    "sg:address":"5585 Av Auteuil",
    "sg:city":"Brossard",
    "sg:classifiers":[
        {
            "category":"Retail",
            "subcategory":"Laundry & Dry Cleaning",
            "type":"Services"
        }
    ],
    "sg:phone":"+1 450 445 2642",
    "sg:postcode":"J4Z 1M3",
    "sg:province":"QC",
    "sg:tags":[
        "cleaners",
        "rug",
        "carpet"
    ],
    "wof:name":"Continental Rotory Nettoyage",
    "wof:placetype":"venue"
},
  "geometry": {"coordinates":[-73.4510192871,45.4772796631],"type":"Point"}
}