{
  "type": "Feature",
  "properties": {
    "addr:full":"2450 United Blvd Coquitlam BC V3K 6G2",
    "addr:postcode":"2450;v3k 6g2",
    "addr:street":"United Blvd",
    "iso:country":"CA",
    "sg:address":"2450 United Blvd",
    "sg:city":"Coquitlam",
    "sg:classifiers":[
        {
            "category":"Wholesale",
            "subcategory":"Groceries",
            "type":"Manufacturing & Wholesale Goods"
        }
    ],
    "sg:phone":"+1 604 523 7500",
    "sg:postcode":"V3K 6G2",
    "sg:province":"BC",
    "sg:tags":[
        "beverage"
    ],
    "wof:name":"Coca-Cola Bottling Ltd",
    "wof:placetype":"venue"
},
  "geometry": {"coordinates":[-122.821693,49.22591],"type":"Point"}
}