{
  "type": "Feature",
  "properties": {
    "iso:country":"CA",
    "sg:address":"47 Front St E",
    "sg:city":"Toronto",
    "sg:classifiers":[
        {
            "category":"Shopping",
            "subcategory":"Bicycles & Sporting Goods",
            "type":"Retail Goods"
        }
    ],
    "sg:phone":"+1 416 601 1990",
    "sg:postcode":"M5E 1B3",
    "sg:province":"ON",
    "wof:name":"Europe Bound",
    "wof:placetype":"venue"
},
  "geometry": {"coordinates":[-79.3744049072,43.6479682922],"type":"Point"}
}