{
  "type": "Feature",
  "properties": {
    "addr:full":"Calgary AB T2E 7M8",
    "addr:postcode":"t2e 7m8",
    "iso:country":"CA",
    "sg:city":"Calgary",
    "sg:classifiers":[
        {
            "category":"Insurance",
            "subcategory":"Insurance Agent",
            "type":"Services"
        }
    ],
    "sg:phone":"+1 403 571 2050",
    "sg:postcode":"T2E 7M8",
    "sg:province":"AB",
    "sg:tags":[
        "adjuster"
    ],
    "wof:name":"Cunningham Lindsey Canada Ltd",
    "wof:placetype":"venue"
},
  "geometry": {"coordinates":[-114.018829346,51.0567932129],"type":"Point"}
}