{
  "type": "Feature",
  "properties": {
    "addr:full":"Hillsburgh ON N0B 1Z0",
    "addr:postcode":"n0b 1z0",
    "iso:country":"CA",
    "sg:city":"Hillsburgh",
    "sg:classifiers":[
        {
            "category":"Building & Trades",
            "subcategory":"Equipment Rental",
            "type":"Services"
        }
    ],
    "sg:phone":"+1 519 763 9838",
    "sg:postcode":"N0B 1Z0",
    "sg:province":"ON",
    "sg:tags":[
        "toilet"
    ],
    "wof:name":"Abners Special Event",
    "wof:placetype":"venue"
},
  "geometry": {"coordinates":[-80.1454772949,43.7913627625],"type":"Point"}
}