{
  "type": "Feature",
  "properties": {
    "addr:full":"52 Coldstream Rd Fenelon Falls ON K0M 1N0",
    "addr:housenumber":"52",
    "addr:postcode":"k0m 1n0",
    "addr:street":"Coldstream Rd",
    "iso:country":"CA",
    "sg:address":"52 Coldstream Rd",
    "sg:city":"Fenelon Falls",
    "sg:classifiers":[
        {
            "category":"Recreation",
            "subcategory":"Marina",
            "type":"Entertainment"
        }
    ],
    "sg:phone":"+1 705 887 6921",
    "sg:postcode":"K0M 1N0",
    "sg:province":"ON",
    "wof:name":"Rosedale Marina",
    "wof:placetype":"venue"
},
  "geometry": {"coordinates":[-78.789276,44.574738],"type":"Point"}
}