{
  "type": "Feature",
  "properties": {
    "iso:country":"CA",
    "sg:address":"565 Boul DE Comporte",
    "sg:city":"LA Malbaie",
    "sg:classifiers":[
        {
            "category":"Organizations",
            "subcategory":"Professional Association",
            "type":"Services"
        }
    ],
    "sg:phone":"+1 418 665 4197",
    "sg:postcode":"G5A 1W6",
    "sg:province":"QC",
    "wof:name":"Saab Charlevoix-Est",
    "wof:placetype":"venue"
},
  "geometry": {"coordinates":[-70.1494674683,47.6553993225],"type":"Point"}
}