{
  "type": "Feature",
  "properties": {
    "addr:full":"1st Ave 2nd St S Marwayne AB T0B 2X0",
    "addr:postcode":"t0b 2x0",
    "addr:street":"1St Ave 2Nd St S",
    "iso:country":"CA",
    "sg:address":"1st Ave 2nd St S",
    "sg:city":"Marwayne",
    "sg:classifiers":[
        {
            "category":"Organizations",
            "subcategory":"Religious Organization",
            "type":"Services"
        }
    ],
    "sg:phone":"+1 780 847 3954",
    "sg:postcode":"T0B 2X0",
    "sg:province":"AB",
    "sg:tags":[
        "church"
    ],
    "wof:name":"United Church St Andrews",
    "wof:placetype":"venue"
},
  "geometry": {"coordinates":[-110.332214355,53.5189781189],"type":"Point"}
}