{
  "type": "Feature",
  "properties": {
    "addr:full":"Kamloops BC V2C 1P8",
    "addr:postcode":"bc v2c 1p8",
    "iso:country":"CA",
    "sg:city":"Kamloops",
    "sg:classifiers":[
        {
            "category":"Real Estate",
            "subcategory":"Real Estate Operator",
            "type":"Services"
        }
    ],
    "sg:phone":"+1 250 374 5535",
    "sg:postcode":"V2C 1P8",
    "sg:province":"BC",
    "sg:tags":[
        "apartment"
    ],
    "wof:name":"Viscount Villa Apartments",
    "wof:placetype":"venue"
},
  "geometry": {"coordinates":[-120.34626799999999,50.665302],"type":"Point"}
}