{
  "type": "Feature",
  "properties": {
    "addr:full":"Canso NS B0H 1H0",
    "addr:postcode":"b0h 1h0",
    "iso:country":"CA",
    "sg:city":"Canso",
    "sg:classifiers":[
        {
            "category":"Personal",
            "subcategory":"Beauty Salon",
            "type":"Services"
        }
    ],
    "sg:phone":"+1 902 366 2779",
    "sg:postcode":"B0H 1H0",
    "sg:province":"NS",
    "wof:name":"Parker Sylvester",
    "wof:placetype":"venue"
},
  "geometry": {"coordinates":[-60.996487,45.336113],"type":"Point"}
}