{
  "type": "Feature",
  "properties": {
    "addr:full":"93 Queen St W Brampton ON L6Y 1M2",
    "addr:housenumber":"93",
    "addr:postcode":"l6y 1m2",
    "addr:street":"Queen St W",
    "iso:country":"CA",
    "sg:address":"93 Queen St W",
    "sg:city":"Brampton",
    "sg:classifiers":[
        {
            "category":"Recreation",
            "type":"Entertainment"
        }
    ],
    "sg:phone":"+1 905 453 8881",
    "sg:postcode":"L6Y 1M2",
    "sg:province":"ON",
    "sg:tags":[
        "diving",
        "instruction"
    ],
    "wof:name":"Brampton Scuba",
    "wof:placetype":"venue"
},
  "geometry": {"coordinates":[-79.761482,43.684219],"type":"Point"}
}