{
  "type": "Feature",
  "properties": {
    "iso:country":"CA",
    "sg:address":"661 Upper James St",
    "sg:city":"Hamilton",
    "sg:classifiers":[
        {
            "category":"Shopping",
            "subcategory":"Optical Goods",
            "type":"Retail Goods"
        }
    ],
    "sg:phone":"+1 905 387 7327",
    "sg:postcode":"L9C 5R8",
    "sg:province":"ON",
    "sg:tags":[
        "optician"
    ],
    "wof:name":"Eye Society",
    "wof:placetype":"venue"
},
  "geometry": {"coordinates":[-79.877754,43.237297],"type":"Point"}
}