{
  "type": "Feature",
  "properties": {
    "addr:full":"1019 Main St Carrot River SK S0E 0L0",
    "addr:housenumber":"1019",
    "addr:postcode":"s0e 0l0",
    "addr:street":"Main St",
    "iso:country":"CA",
    "sg:address":"1019 Main St",
    "sg:city":"Carrot River",
    "sg:classifiers":[
        {
            "category":"Professional",
            "subcategory":"Business Services",
            "type":"Services"
        }
    ],
    "sg:phone":"+1 306 768 3887",
    "sg:postcode":"S0E 0L0",
    "sg:province":"SK",
    "sg:tags":[
        "printer",
        "embroidery"
    ],
    "wof:name":"Simply Creative",
    "wof:placetype":"venue"
},
  "geometry": {"coordinates":[-103.587532,53.28336],"type":"Point"}
}