{
  "type": "Feature",
  "properties": {
    "iso:country":"CA",
    "sg:address":"255 Boul Marcotte",
    "sg:city":"Roberval",
    "sg:classifiers":[
        {
            "category":"Building & Trades",
            "subcategory":"Construction",
            "type":"Services"
        }
    ],
    "sg:phone":"+1 418 275 2356",
    "sg:postcode":"G8H 1Z3",
    "sg:province":"QC",
    "sg:tags":[
        "hardware",
        "repairing",
        "remodeling",
        "contractor"
    ],
    "wof:name":"Ferlac Inc",
    "wof:placetype":"venue"
},
  "geometry": {"coordinates":[-72.2223434448,48.5004768372],"type":"Point"}
}