{
  "type": "Feature",
  "properties": {
    "addr:full":"494 Ch Du Petit-Brule Rigaud QC J0P 1P0",
    "addr:housenumber":"494",
    "addr:postcode":"j0p 1p0",
    "addr:street":"Ch Du Petit-Brule",
    "iso:country":"CA",
    "sg:address":"494 Ch Du Petit-Brule",
    "sg:city":"Rigaud",
    "sg:classifiers":[
        {
            "category":"Home & Garden",
            "subcategory":"Household Appliances",
            "type":"Retail Goods"
        }
    ],
    "sg:phone":"+1 450 451 0679",
    "sg:postcode":"J0P 1P0",
    "sg:province":"QC",
    "wof:name":"G G Raymond Enrg",
    "wof:placetype":"venue"
},
  "geometry": {"coordinates":[-74.3936538696,45.4596977234],"type":"Point"}
}