{
  "type": "Feature",
  "properties": {
    "addr:full":"494 Tenth St Collingwood ON L9Y 2H1",
    "addr:housenumber":"494",
    "addr:postcode":"l9y 2h1",
    "addr:street":"Tenth St",
    "iso:country":"CA",
    "sg:address":"494 Tenth St",
    "sg:city":"Collingwood",
    "sg:classifiers":[
        {
            "category":"Organizations",
            "subcategory":"Religious Organization",
            "type":"Services"
        }
    ],
    "sg:phone":"+1 705 444 0010",
    "sg:postcode":"L9Y 2H1",
    "sg:province":"ON",
    "sg:tags":[
        "church"
    ],
    "wof:name":"Church of Christ",
    "wof:placetype":"venue"
},
  "geometry": {"coordinates":[-80.22508999999999,44.488548],"type":"Point"}
}