{
  "type": "Feature",
  "properties": {
    "addr:full":"554 Spadina Cres Toronto ON M5S 2J9",
    "addr:housenumber":"554",
    "addr:postcode":"m5s 2j9",
    "addr:street":"Spadina Cres",
    "iso:country":"CA",
    "sg:address":"554 Spadina Cres",
    "sg:city":"Toronto",
    "sg:classifiers":[
        {
            "category":"Health Services",
            "subcategory":"Doctor",
            "type":"Services"
        }
    ],
    "sg:phone":"+1 416 923 8058",
    "sg:postcode":"M5S 2J9",
    "sg:province":"ON",
    "sg:tags":[
        "physician",
        "surgeon"
    ],
    "wof:name":"Finnegan, Paul MD",
    "wof:placetype":"venue"
},
  "geometry": {"coordinates":[-79.401703,43.65966],"type":"Point"}
}