{
  "type": "Feature",
  "properties": {
    "addr:full":"1830 Lawrence Ave E Scarborough ON M1R 2Y2",
    "addr:housenumber":"1830",
    "addr:postcode":"m1r 2y2",
    "addr:street":"Lawrence Ave E",
    "iso:country":"CA",
    "sg:address":"1830 Lawrence Ave E",
    "sg:city":"Scarborough",
    "sg:classifiers":[
        {
            "category":"Autos & Motor Vehicles",
            "subcategory":"Automobile Sales",
            "type":"Retail Goods"
        }
    ],
    "sg:phone":"+1 416 751 6653",
    "sg:postcode":"M1R 2Y2",
    "sg:province":"ON",
    "sg:tags":[
        "car",
        "dealer"
    ],
    "wof:name":"Warranty Auto Sales Ltd",
    "wof:placetype":"venue"
},
  "geometry": {"coordinates":[-79.3052902222,43.7432250977],"type":"Point"}
}