{
  "type": "Feature",
  "properties": {
    "addr:full":"6360 Hawthorne Dr #1 Windsor ON N8T 1J9",
    "addr:housenumber":"6360",
    "addr:postcode":"n8t 1j9",
    "addr:street":"Hawthorne Dr # 1",
    "iso:country":"CA",
    "sg:address":"6360 Hawthorne Dr #1",
    "sg:city":"Windsor",
    "sg:classifiers":[
        {
            "category":"Manufacturing",
            "subcategory":"Tools & Machinery",
            "type":"Manufacturing & Wholesale Goods"
        }
    ],
    "sg:phone":"+1 519 948 0070",
    "sg:postcode":"N8T 1J9",
    "sg:province":"ON",
    "sg:tags":[
        "machine",
        "shop"
    ],
    "wof:name":"Moderne Machining",
    "wof:placetype":"venue"
},
  "geometry": {"coordinates":[-82.94529,42.305454],"type":"Point"}
}