{
  "type": "Feature",
  "properties": {
    "addr:full":"2433 26 St SW Calgary AB T3E 2A6",
    "addr:housenumber":"2433",
    "addr:postcode":"t3e 2a6",
    "addr:street":"26 St Sw",
    "iso:country":"CA",
    "sg:address":"2433 26 St SW",
    "sg:city":"Calgary",
    "sg:classifiers":[
        {
            "category":"Organizations",
            "subcategory":"Professional Association",
            "type":"Services"
        }
    ],
    "sg:phone":"+1 403 249 8385",
    "sg:postcode":"T3E 2A6",
    "sg:province":"AB",
    "sg:tags":[
        "club"
    ],
    "wof:name":"Richmond Knob Hill Comm Assn",
    "wof:placetype":"venue"
},
  "geometry": {"coordinates":[-114.12391700000001,51.032818],"type":"Point"}
}