{
  "type": "Feature",
  "properties": {
    "addr:full":"Pierrefonds QC H8Y 3E3",
    "addr:postcode":"h8y 3e3",
    "iso:country":"CA",
    "sg:city":"Pierrefonds",
    "sg:classifiers":[
        {
            "category":"Restaurant",
            "type":"Food & Drink"
        }
    ],
    "sg:phone":"+1 514 683 1110",
    "sg:postcode":"H8Y 3E3",
    "sg:province":"QC",
    "wof:name":"Man-Li",
    "wof:placetype":"venue"
},
  "geometry": {"coordinates":[-73.893852,45.464779],"type":"Point"}
}