{
  "type": "Feature",
  "properties": {
    "addr:full":"6100 Winston Churchill Blvd Alton ON L0N 1A0",
    "addr:housenumber":"6100",
    "addr:postcode":"l0n 1a0",
    "addr:street":"Winston Churchill Blvd",
    "iso:country":"CA",
    "sg:address":"6100 Winston Churchill Blvd",
    "sg:city":"Alton",
    "sg:classifiers":[
        {
            "category":"Building & Trades",
            "subcategory":"Landscaping Services",
            "type":"Services"
        }
    ],
    "sg:phone":"+1 519 941 1380",
    "sg:postcode":"L0N 1A0",
    "sg:province":"ON",
    "sg:tags":[
        "landscape",
        "contractor"
    ],
    "wof:name":"Direct Landscape Mntnc CO",
    "wof:placetype":"venue"
},
  "geometry": {"coordinates":[-80.06530761720001,43.8584709167],"type":"Point"}
}