{
  "type": "Feature",
  "properties": {
    "addr:full":"291 Rue Saint-Joseph LA Tuque QC G9X 1K6",
    "addr:housenumber":"291",
    "addr:postcode":"g9x 1k6",
    "addr:street":"Rue Saint-Joseph",
    "iso:country":"CA",
    "sg:address":"291 Rue Saint-Joseph",
    "sg:city":"LA Tuque",
    "sg:classifiers":[
        {
            "category":"Health Services",
            "subcategory":"Doctor",
            "type":"Services"
        }
    ],
    "sg:phone":"+1 819 523 8000",
    "sg:postcode":"G9X 1K6",
    "sg:province":"QC",
    "sg:tags":[
        "clinic",
        "dentist"
    ],
    "wof:name":"Clinique Dentaire Cloutier",
    "wof:placetype":"venue"
},
  "geometry": {"coordinates":[-72.785492,47.440845],"type":"Point"}
}