{
  "type": "Feature",
  "properties": {
    "addr:full":"41 Eighth Ave Sioux Lookout ON P8T 1B7",
    "addr:housenumber":"41",
    "addr:postcode":"p8t 1b7",
    "addr:street":"Eighth Ave",
    "iso:country":"CA",
    "sg:address":"41 Eighth Ave",
    "sg:city":"Sioux Lookout",
    "sg:classifiers":[
        {
            "category":"Education",
            "subcategory":"School",
            "type":"Public Place"
        }
    ],
    "sg:phone":"+1 807 737 1121",
    "sg:postcode":"P8T 1B7",
    "sg:province":"ON",
    "wof:name":"Sacred Heart School",
    "wof:placetype":"venue"
},
  "geometry": {"coordinates":[-91.9264755249,50.0993881226],"type":"Point"}
}