{
  "type": "Feature",
  "properties": {
    "addr:full":"113 Fourth St Rainy River ON P0W 1L0",
    "addr:housenumber":"113",
    "addr:postcode":"p0w 1l0",
    "addr:street":"Fourth St",
    "iso:country":"CA",
    "sg:address":"113 Fourth St",
    "sg:city":"Rainy River",
    "sg:classifiers":[
        {
            "category":"Shopping",
            "type":"Retail Goods"
        }
    ],
    "sg:phone":"+1 807 852 3872",
    "sg:postcode":"P0W 1L0",
    "sg:province":"ON",
    "sg:tags":[
        "equipment",
        "care",
        "health",
        "home"
    ],
    "wof:name":"Home Support Program",
    "wof:placetype":"venue"
},
  "geometry": {"coordinates":[-94.5685958862,48.7175865173],"type":"Point"}
}