{
  "type": "Feature",
  "properties": {
    "addr:full":"1120 Hildebrand Dr LA Ronge SK S0J 1L0",
    "addr:housenumber":"1120",
    "addr:postcode":"s0j 1l0",
    "addr:street":"Hildebrand Dr",
    "iso:country":"CA",
    "sg:address":"1120 Hildebrand Dr",
    "sg:city":"LA Ronge",
    "sg:classifiers":[
        {
            "category":"Organizations",
            "subcategory":"Professional Association",
            "type":"Services"
        }
    ],
    "sg:phone":"+1 306 425 4141",
    "sg:postcode":"S0J 1L0",
    "sg:province":"SK",
    "sg:tags":[
        "club"
    ],
    "wof:name":"LA Ronge Ice Wolves Hockey",
    "wof:placetype":"venue"
},
  "geometry": {"coordinates":[-105.295326233,55.1124954224],"type":"Point"}
}