{
  "type": "Feature",
  "properties": {
    "addr:full":"Dorval QC H9S 2E5",
    "addr:postcode":"h9s 2e5",
    "iso:country":"CA",
    "sg:city":"Dorval",
    "sg:classifiers":[
        {
            "category":"Education",
            "subcategory":"Library",
            "type":"Public Place"
        }
    ],
    "sg:phone":"+1 514 633 4170",
    "sg:postcode":"H9S 2E5",
    "sg:province":"QC",
    "sg:tags":[
        "government"
    ],
    "wof:name":"Dorval Bibliotheque Ctr",
    "wof:placetype":"venue"
},
  "geometry": {"coordinates":[-73.778862,45.445587],"type":"Point"}
}