{
  "type": "Feature",
  "properties": {
    "iso:country":"CA",
    "sg:city":"Dingwall",
    "sg:classifiers":[
        {
            "category":"Wholesale",
            "subcategory":"Apparel",
            "type":"Manufacturing & Wholesale Goods"
        }
    ],
    "sg:phone":"+1 902 383 2005",
    "sg:postcode":"B0C 1G0",
    "sg:province":"NS",
    "sg:tags":[
        "woolen",
        "worsted",
        "gift",
        "fabric",
        "shop"
    ],
    "wof:name":"Tartan & Treasures",
    "wof:placetype":"venue"
},
  "geometry": {"coordinates":[-60.4698944092,46.8976593018],"type":"Point"}
}