{
  "type": "Feature",
  "properties": {
    "iso:country":"CA",
    "sg:address":"31 Fulton Cres",
    "sg:city":"Moncton",
    "sg:classifiers":[
        {
            "category":"Home & Garden",
            "subcategory":"Building Materials",
            "type":"Retail Goods"
        }
    ],
    "sg:phone":"+1 506 859 8993",
    "sg:postcode":"E1C 9J1",
    "sg:province":"NB",
    "sg:tags":[
        "glass",
        "leaded"
    ],
    "wof:name":"Amber Stained Glass Supplies",
    "wof:placetype":"venue"
},
  "geometry": {"coordinates":[-64.82330322270001,46.1121902466],"type":"Point"}
}