{
  "type": "Feature",
  "properties": {
    "iso:country":"CA",
    "sg:address":"452 River Ave",
    "sg:city":"Winnipeg",
    "sg:classifiers":[
        {
            "category":"Personal",
            "type":"Services"
        }
    ],
    "sg:phone":"+1 204 475 1100",
    "sg:postcode":"R3L 0C7",
    "sg:province":"MB",
    "sg:tags":[
        "therapist",
        "holistic",
        "practitioner",
        "massage"
    ],
    "wof:name":"Destress Stop Inc",
    "wof:placetype":"venue"
},
  "geometry": {"coordinates":[-97.1458969116,49.8792190552],"type":"Point"}
}