{
  "type": "Feature",
  "properties": {
    "iso:country":"CA",
    "sg:address":"94 Conc 13 E",
    "sg:city":"Perkinsfield",
    "sg:classifiers":[
        {
            "category":"Home & Garden",
            "subcategory":"Building Materials",
            "type":"Retail Goods"
        }
    ],
    "sg:phone":"+1 705 549 8705",
    "sg:postcode":"L0L 2J0",
    "sg:province":"ON",
    "sg:tags":[
        "mixed",
        "concrete"
    ],
    "wof:name":"Carriere Ready Mix Ltd",
    "wof:placetype":"venue"
},
  "geometry": {"coordinates":[-79.96974899999999,44.707382],"type":"Point"}
}