{
  "type": "Feature",
  "properties": {
    "iso:country":"CA",
    "sg:address":"866 Nellis St",
    "sg:city":"Woodstock",
    "sg:classifiers":[
        {
            "category":"Retail",
            "subcategory":"Veterinary Services",
            "type":"Services"
        }
    ],
    "sg:phone":"+1 519 421 0137",
    "sg:postcode":"N4S 4C4",
    "sg:province":"ON",
    "sg:tags":[
        "veterinarian"
    ],
    "wof:name":"Woodstock Veterinary Hospital",
    "wof:placetype":"venue"
},
  "geometry": {"coordinates":[-80.73956298829999,43.1333312988],"type":"Point"}
}