{
  "type": "Feature",
  "properties": {
    "iso:country":"CA",
    "sg:address":"4926 99 St NW",
    "sg:city":"Edmonton",
    "sg:classifiers":[
        {
            "category":"Home & Garden",
            "subcategory":"Home Furnishings",
            "type":"Retail Goods"
        }
    ],
    "sg:phone":"+1 780 437 5114",
    "sg:postcode":"T6E 3N6",
    "sg:province":"AB",
    "sg:tags":[
        "fireplace"
    ],
    "wof:name":"Northland Fireplace Ltd",
    "wof:placetype":"venue"
},
  "geometry": {"coordinates":[-113.48639679,53.486743927],"type":"Point"}
}