{
  "type": "Feature",
  "properties": {
    "addr:full":"20468 Fraser Hwy Langley BC V3A 4G2",
    "addr:housenumber":"20468",
    "addr:postcode":"v3a 4g2",
    "addr:street":"Fraser Hwy",
    "iso:country":"CA",
    "sg:address":"20468 Fraser Hwy",
    "sg:city":"Langley",
    "sg:classifiers":[
        {
            "category":"Professional",
            "subcategory":"Accounting & Tax Preparation",
            "type":"Services"
        }
    ],
    "sg:phone":"+1 604 530 3944",
    "sg:postcode":"V3A 4G2",
    "sg:province":"BC",
    "sg:tags":[
        "consultant",
        "return",
        "filing"
    ],
    "wof:name":"H & R Block Canada Inc",
    "wof:placetype":"venue"
},
  "geometry": {"coordinates":[-122.65486145,49.104221344],"type":"Point"}
}