{
  "type": "Feature",
  "properties": {
    "addr:full":"5640 Dunbar St Vancouver BC V6N 1W7",
    "addr:housenumber":"5640",
    "addr:postcode":"v6n 1w7",
    "addr:street":"Dunbar St",
    "iso:country":"CA",
    "sg:address":"5640 Dunbar St",
    "sg:city":"Vancouver",
    "sg:classifiers":[
        {
            "category":"Government",
            "subcategory":"Office",
            "type":"Public Place"
        }
    ],
    "sg:phone":"+1 604 664 0748",
    "sg:postcode":"V6N 1W7",
    "sg:province":"BC",
    "wof:name":"B C Members of the Legislative",
    "wof:placetype":"venue"
},
  "geometry": {"coordinates":[-123.185119629,49.2353286743],"type":"Point"}
}