{
  "type": "Feature",
  "properties": {
    "addr:full":"1271 Commissioners Rd W London ON N6K 1C9",
    "addr:housenumber":"1271",
    "addr:postcode":"n6k 1c9",
    "addr:street":"Commissioners Rd W",
    "iso:country":"CA",
    "sg:address":"1271 Commissioners Rd W",
    "sg:city":"London",
    "sg:classifiers":[
        {
            "category":"Restaurant",
            "type":"Food & Drink"
        }
    ],
    "sg:phone":"+1 519 473 0074",
    "sg:postcode":"N6K 1C9",
    "sg:province":"ON",
    "sg:tags":[
        "cafe"
    ],
    "wof:name":"Cafe Milagro's",
    "wof:placetype":"venue"
},
  "geometry": {"coordinates":[-81.3332519531,42.9599990845],"type":"Point"}
}