{
  "type": "Feature",
  "properties": {
    "addr:full":"1645 Bayview Ave East York ON M4G 3C1",
    "addr:housenumber":"1645",
    "addr:postcode":"m4g 3c1",
    "addr:street":"Bayview Ave",
    "iso:country":"CA",
    "sg:address":"1645 Bayview Ave",
    "sg:city":"East York",
    "sg:classifiers":[
        {
            "category":"Wholesale",
            "subcategory":"Groceries",
            "type":"Manufacturing & Wholesale Goods"
        }
    ],
    "sg:phone":"+1 416 488 1414",
    "sg:postcode":"M4G 3C1",
    "sg:province":"ON",
    "sg:tags":[
        "cocoa",
        "chocolate"
    ],
    "wof:name":"Chocolate Messenger",
    "wof:placetype":"venue"
},
  "geometry": {"coordinates":[-79.3755111694,43.7071380615],"type":"Point"}
}