{
  "type": "Feature",
  "properties": {
    "addr:full":"1009 Rue Jean-Talon O Montreal QC H3N 1T2",
    "addr:housenumber":"1009",
    "addr:postcode":"h3n 1t2",
    "addr:street":"Rue Jean-Talon O",
    "iso:country":"CA",
    "sg:address":"1009 Rue Jean-Talon O",
    "sg:city":"Montreal",
    "sg:classifiers":[
        {
            "category":"Food & Beverages",
            "subcategory":"Groceries & Convenience Stores",
            "type":"Retail Goods"
        }
    ],
    "sg:phone":"+1 514 277 7773",
    "sg:postcode":"H3N 1T2",
    "sg:province":"QC",
    "sg:tags":[
        "grocer"
    ],
    "wof:name":"Marche D'Afrique",
    "wof:placetype":"venue"
},
  "geometry": {"coordinates":[-73.6127090454,45.5418663025],"type":"Point"}
}