{
  "type": "Feature",
  "properties": {
    "addr:full":"RR 1 Apsley ON K0L 1A0",
    "addr:postcode":"k0l 1a0",
    "addr:street":"Rr 1",
    "iso:country":"CA",
    "sg:address":"RR 1",
    "sg:city":"Apsley",
    "sg:classifiers":[
        {
            "category":"Building & Trades",
            "subcategory":"Plumbing",
            "type":"Services"
        }
    ],
    "sg:phone":"+1 705 656 4893",
    "sg:postcode":"K0L 1A0",
    "sg:province":"ON",
    "sg:tags":[
        "tank",
        "septic"
    ],
    "wof:name":"Lance Mac Donald Construction",
    "wof:placetype":"venue"
},
  "geometry": {"coordinates":[-78.0853729248,44.7530212402],"type":"Point"}
}