{
  "type": "Feature",
  "properties": {
    "addr:full":"Cabano QC G0L 1E0",
    "addr:postcode":"g0l 1e0",
    "iso:country":"CA",
    "sg:city":"Cabano",
    "sg:classifiers":[
        {
            "category":"Health Services",
            "subcategory":"Doctor",
            "type":"Services"
        }
    ],
    "sg:phone":"+1 418 854 5555",
    "sg:postcode":"G0L 1E0",
    "sg:province":"QC",
    "sg:tags":[
        "physiotherapist",
        "clinic"
    ],
    "wof:name":"Clinique DE Physiotherapie",
    "wof:placetype":"venue"
},
  "geometry": {"coordinates":[-68.876442,47.680534],"type":"Point"}
}