{
  "type": "Feature",
  "properties": {
    "iso:country":"CA",
    "sg:address":"190 Lynden Rd",
    "sg:city":"Brantford",
    "sg:classifiers":[
        {
            "category":"Shopping",
            "subcategory":"Gifts & Souvenirs",
            "type":"Retail Goods"
        }
    ],
    "sg:phone":"+1 519 753 1663",
    "sg:postcode":"N3R 8A3",
    "sg:province":"ON",
    "sg:tags":[
        "shop",
        "collectible"
    ],
    "wof:name":"Flim Flam Gift Gallery",
    "wof:placetype":"venue"
},
  "geometry": {"coordinates":[-80.2310409546,43.1750488281],"type":"Point"}
}