{
  "type": "Feature",
  "properties": {
    "addr:full":"North York ON M2J 1W8",
    "addr:postcode":"m2j 1w8",
    "iso:country":"CA",
    "sg:city":"North York",
    "sg:classifiers":[
        {
            "category":"Wholesale",
            "subcategory":"Durable Goods & Equipment",
            "type":"Manufacturing & Wholesale Goods"
        }
    ],
    "sg:phone":"+1 416 490 6546",
    "sg:postcode":"M2J 1W8",
    "sg:province":"ON",
    "sg:tags":[
        "representative",
        "manufacturer"
    ],
    "wof:name":"Langford & Assoc Inc",
    "wof:placetype":"venue"
},
  "geometry": {"coordinates":[-79.3304443359,43.7748718262],"type":"Point"}
}