{
  "type": "Feature",
  "properties": {
    "addr:full":"1210 Rue Milton Laval QC H7W 1W2",
    "addr:housenumber":"1210",
    "addr:postcode":"h7w 1w2",
    "addr:street":"Rue Milton",
    "iso:country":"CA",
    "sg:address":"1210 Rue Milton",
    "sg:city":"Laval",
    "sg:classifiers":[
        {
            "category":"Education",
            "subcategory":"Special Training",
            "type":"Public Place"
        }
    ],
    "sg:phone":"+1 450 681 7028",
    "sg:postcode":"H7W 1W2",
    "sg:province":"QC",
    "sg:tags":[
        "instruction",
        "music"
    ],
    "wof:name":"Studio Dansereau Aline",
    "wof:placetype":"venue"
},
  "geometry": {"coordinates":[-73.75504302980001,45.5374946594],"type":"Point"}
}