{
  "type": "Feature",
  "properties": {
    "addr:full":"3440 Rang Saint-Elzear E Laval QC H7E 4P2",
    "addr:housenumber":"3440",
    "addr:postcode":"h7e 4p2",
    "addr:street":"Rang Saint-Elzear E",
    "iso:country":"CA",
    "sg:address":"3440 Rang Saint-Elzear E",
    "sg:city":"Laval",
    "sg:classifiers":[
        {
            "category":"Real Estate",
            "subcategory":"Architect",
            "type":"Services"
        }
    ],
    "sg:phone":"+1 450 661 2990",
    "sg:postcode":"H7E 4P2",
    "sg:province":"QC",
    "sg:tags":[
        "building",
        "construction"
    ],
    "wof:name":"Gatec Inc",
    "wof:placetype":"venue"
},
  "geometry": {"coordinates":[-73.6901092529,45.6266784668],"type":"Point"}
}