{
  "type": "Feature",
  "properties": {
    "addr:full":"Richmond BC V6X 1R4",
    "addr:postcode":"v6x 1r4",
    "iso:country":"CA",
    "sg:city":"Richmond",
    "sg:classifiers":[
        {
            "category":"Manufacturing",
            "subcategory":"Tools & Machinery",
            "type":"Manufacturing & Wholesale Goods"
        }
    ],
    "sg:phone":"+1 604 278 4836",
    "sg:postcode":"V6X 1R4",
    "sg:province":"BC",
    "sg:tags":[
        "equipment",
        "marine",
        "hydraulic",
        "supply"
    ],
    "wof:name":"Keypower Equipment Inc",
    "wof:placetype":"venue"
},
  "geometry": {"coordinates":[-123.134407,49.189095],"type":"Point"}
}