{
  "type": "Feature",
  "properties": {
    "addr:full":"275 King George Rd Brantford ON N3R 5L1",
    "addr:housenumber":"275",
    "addr:postcode":"n3r 5l1",
    "addr:street":"King George Rd",
    "iso:country":"CA",
    "sg:address":"275 King George Rd",
    "sg:city":"Brantford",
    "sg:classifiers":[
        {
            "category":"Home & Garden",
            "subcategory":"Building Materials",
            "type":"Retail Goods"
        }
    ],
    "sg:phone":"+1 519 752 3717",
    "sg:postcode":"N3R 5L1",
    "sg:province":"ON",
    "sg:tags":[
        "glass",
        "window",
        "plate"
    ],
    "wof:name":"W J Mc Clelland & Sons Glass",
    "wof:placetype":"venue"
},
  "geometry": {"coordinates":[-80.280441,43.179382],"type":"Point"}
}