{
  "type": "Feature",
  "properties": {
    "iso:country":"CA",
    "sg:address":"30 River Rd",
    "sg:city":"Winnipeg",
    "sg:classifiers":[
        {
            "category":"Recreation",
            "type":"Entertainment"
        }
    ],
    "sg:phone":"+1 204 334 2107",
    "sg:postcode":"R2M 3Z2",
    "sg:province":"MB",
    "sg:tags":[
        "course",
        "golf"
    ],
    "wof:name":"Larters At St Andrews Golf",
    "wof:placetype":"venue"
},
  "geometry": {"coordinates":[-97.128227,49.834496],"type":"Point"}
}