{
  "type": "Feature",
  "properties": {
    "addr:full":"6631 Av Papineau Montreal QC H2G 2X3",
    "addr:housenumber":"6631",
    "addr:postcode":"h2g 2x3",
    "addr:street":"Av Papineau",
    "iso:country":"CA",
    "sg:address":"6631 Av Papineau",
    "sg:city":"Montreal",
    "sg:classifiers":[
        {
            "category":"Building & Trades",
            "subcategory":"Construction",
            "type":"Services"
        }
    ],
    "sg:phone":"+1 514 725 9990",
    "sg:postcode":"H2G 2X3",
    "sg:province":"QC",
    "sg:tags":[
        "repairing",
        "remodeling",
        "contractor"
    ],
    "wof:name":"Eco Reno",
    "wof:placetype":"venue"
},
  "geometry": {"coordinates":[-73.598686,45.54427],"type":"Point"}
}