{
  "type": "Feature",
  "properties": {
    "iso:country":"CA",
    "sg:city":"St Albert",
    "sg:classifiers":[
        {
            "category":"Wholesale",
            "subcategory":"Hardware",
            "type":"Manufacturing & Wholesale Goods"
        }
    ],
    "sg:phone":"+1 780 458 0131",
    "sg:postcode":"T8N 5C2",
    "sg:province":"AB",
    "sg:tags":[
        "bar",
        "made",
        "fixture"
    ],
    "wof:name":"Best-Way Distributors Alberta",
    "wof:placetype":"venue"
},
  "geometry": {"coordinates":[-113.64311981199999,53.6229476929],"type":"Point"}
}