{
  "type": "Feature",
  "properties": {
    "addr:full":"5950 Av Tisserand Brossard QC J4W 3G9",
    "addr:housenumber":"5950",
    "addr:postcode":"j4w 3g9",
    "addr:street":"Av Tisserand",
    "iso:country":"CA",
    "sg:address":"5950 Av Tisserand",
    "sg:city":"Brossard",
    "sg:classifiers":[
        {
            "category":"Wholesale",
            "subcategory":"Home Furnishings",
            "type":"Manufacturing & Wholesale Goods"
        }
    ],
    "sg:phone":"+1 450 671 9533",
    "sg:postcode":"J4W 3G9",
    "sg:province":"QC",
    "sg:tags":[
        "rug",
        "carpet"
    ],
    "wof:name":"Bhanskraft International Inc",
    "wof:placetype":"venue"
},
  "geometry": {"coordinates":[-73.4879,45.463139],"type":"Point"}
}