{
  "type": "Feature",
  "properties": {
    "addr:full":"2534 11th Ave Regina SK S4P 0K5",
    "addr:housenumber":"2534",
    "addr:postcode":"s4p 0k5",
    "addr:street":"11Th Ave",
    "iso:country":"CA",
    "sg:address":"2534 11th Ave",
    "sg:city":"Regina",
    "sg:classifiers":[
        {
            "category":"Real Estate",
            "subcategory":"Real Estate Agent",
            "type":"Services"
        }
    ],
    "sg:phone":"+1 306 525 0125",
    "sg:postcode":"S4P 0K5",
    "sg:province":"SK",
    "wof:name":"Lloyd Realty Ltd",
    "wof:placetype":"venue"
},
  "geometry": {"coordinates":[-104.617111206,50.4505157471],"type":"Point"}
}