{
  "type": "Feature",
  "properties": {
    "iso:country":"CA",
    "sg:address":"303 2nd Ave",
    "sg:city":"Hudson Bay",
    "sg:classifiers":[
        {
            "category":"Recreation",
            "type":"Entertainment"
        }
    ],
    "sg:phone":"+1 306 865 3939",
    "sg:postcode":"S0E 0Y0",
    "sg:province":"SK",
    "sg:tags":[
        "club",
        "sport"
    ],
    "wof:name":"Hudson Bay Senior Hunters",
    "wof:placetype":"venue"
},
  "geometry": {"coordinates":[-102.391937,52.859619],"type":"Point"}
}