{
  "type": "Feature",
  "properties": {
    "addr:full":"RR 4 STN Main Innisfail AB T4G 1T9",
    "addr:postcode":"t4g 1t9",
    "addr:street":"Rr 4 Stn Main",
    "iso:country":"CA",
    "sg:address":"RR 4 STN Main",
    "sg:city":"Innisfail",
    "sg:classifiers":[
        {
            "category":"Retail",
            "subcategory":"Repair Shop",
            "type":"Services"
        }
    ],
    "sg:phone":"+1 403 227 3555",
    "sg:postcode":"T4G 1T9",
    "sg:province":"AB",
    "sg:tags":[
        "taxidermist"
    ],
    "wof:name":"Hunter's Taxidermy",
    "wof:placetype":"venue"
},
  "geometry": {"coordinates":[-113.948624,52.027409],"type":"Point"}
}