{
  "type": "Feature",
  "properties": {
    "addr:full":"General Delivery Carrot Creek AB T0E 0G0",
    "addr:postcode":"t0e 0g0",
    "iso:country":"CA",
    "sg:address":"General Delivery",
    "sg:city":"Carrot Creek",
    "sg:classifiers":[
        {
            "category":"Recreation",
            "type":"Entertainment"
        }
    ],
    "sg:phone":"+1 780 795 2299",
    "sg:postcode":"T0E 0G0",
    "sg:province":"AB",
    "sg:tags":[
        "hall",
        "auditorium"
    ],
    "wof:name":"Carrot Creek Community Hall",
    "wof:placetype":"venue"
},
  "geometry": {"coordinates":[-115.840965,53.612629],"type":"Point"}
}