{
  "type": "Feature",
  "properties": {
    "addr:full":"90 Campsite Rd Spruce Grove AB T7X 4H4",
    "addr:housenumber":"90",
    "addr:postcode":"t7x 4h4",
    "addr:street":"Campsite Rd",
    "iso:country":"CA",
    "sg:address":"90 Campsite Rd",
    "sg:city":"Spruce Grove",
    "sg:classifiers":[
        {
            "category":"Restaurant",
            "type":"Food & Drink"
        }
    ],
    "sg:phone":"+1 780 962 0924",
    "sg:postcode":"T7X 4H4",
    "sg:province":"AB",
    "wof:name":"Mc Donald's",
    "wof:placetype":"venue"
},
  "geometry": {"coordinates":[-113.934372,53.54425],"type":"Point"}
}