{
  "type": "Feature",
  "properties": {
    "iso:country":"CA",
    "sg:city":"Concord",
    "sg:classifiers":[
        {
            "category":"Professional",
            "subcategory":"Employment Agencies",
            "type":"Services"
        }
    ],
    "sg:phone":"+1 905 760 7622",
    "sg:postcode":"L4K 3C5",
    "sg:province":"ON",
    "sg:tags":[
        "opportunity"
    ],
    "wof:name":"Vector Group",
    "wof:placetype":"venue"
},
  "geometry": {"coordinates":[-79.52806854249999,43.776889801],"type":"Point"}
}