{
  "type": "Feature",
  "properties": {
    "addr:full":"555 Mapleview Dr W # 201 Barrie ON L4N 8G5",
    "addr:housenumber":"555",
    "addr:postcode":"l4n 8g5",
    "addr:street":"Mapleview Dr W # 201",
    "iso:country":"CA",
    "sg:address":"555 Mapleview Dr W # 201",
    "sg:city":"Barrie",
    "sg:classifiers":[
        {
            "category":"Health Services",
            "subcategory":"Doctor",
            "type":"Services"
        }
    ],
    "sg:phone":"+1 705 721 1182",
    "sg:postcode":"L4N 8G5",
    "sg:province":"ON",
    "sg:tags":[
        "dentist"
    ],
    "wof:name":"Mapleview Family Dentistry",
    "wof:placetype":"venue"
},
  "geometry": {"coordinates":[-79.728004,44.325588],"type":"Point"}
}