{
  "type": "Feature",
  "properties": {
    "addr:full":"Englishtown NS B0C 1H0",
    "addr:postcode":"b0c 1h0",
    "iso:country":"CA",
    "sg:city":"Englishtown",
    "sg:classifiers":[
        {
            "category":"Shopping",
            "subcategory":"Used Merchandise",
            "type":"Retail Goods"
        }
    ],
    "sg:phone":"+1 902 929 2992",
    "sg:postcode":"B0C 1H0",
    "sg:province":"NS",
    "sg:tags":[
        "antique"
    ],
    "wof:name":"Sea Shanty Craft & Antique Shp",
    "wof:placetype":"venue"
},
  "geometry": {"coordinates":[-60.5448570251,46.2795753479],"type":"Point"}
}