{
  "type": "Feature",
  "properties": {
    "iso:country":"CA",
    "sg:address":"167 Rue Canada",
    "sg:city":"Saint-Quentin",
    "sg:classifiers":[
        {
            "category":"Personal",
            "subcategory":"Beauty Salon",
            "type":"Services"
        }
    ],
    "sg:phone":"+1 506 235 3443",
    "sg:postcode":"E8A 1J6",
    "sg:province":"NB",
    "wof:name":"Salon Chantal Coiffure",
    "wof:placetype":"venue"
},
  "geometry": {"coordinates":[-67.3922958374,47.5089187622],"type":"Point"}
}