{
  "type": "Feature",
  "properties": {
    "iso:country":"CA",
    "sg:city":"Mississauga",
    "sg:classifiers":[
        {
            "category":"Wholesale",
            "subcategory":"Drugs",
            "type":"Manufacturing & Wholesale Goods"
        }
    ],
    "sg:phone":"+1 905 677 8333",
    "sg:postcode":"L5S 1B8",
    "sg:province":"ON",
    "sg:tags":[
        "cosmetic"
    ],
    "wof:name":"Body Blue Inc",
    "wof:placetype":"venue"
},
  "geometry": {"coordinates":[-79.663254,43.695583],"type":"Point"}
}