{
  "type": "Feature",
  "properties": {
    "addr:full":"2405 Legislative Dr Regina SK S4S 0B3",
    "addr:housenumber":"2405",
    "addr:postcode":"s4s 0b3",
    "addr:street":"Legislative Dr",
    "iso:country":"CA",
    "sg:address":"2405 Legislative Dr",
    "sg:city":"Regina",
    "sg:classifiers":[
        {
            "category":"Government",
            "subcategory":"Office",
            "type":"Public Place"
        }
    ],
    "sg:phone":"+1 306 787 7448",
    "sg:postcode":"S4S 0B3",
    "sg:province":"SK",
    "wof:name":"Sask Executive Council",
    "wof:placetype":"venue"
},
  "geometry": {"coordinates":[-104.613471985,50.4332046509],"type":"Point"}
}