{
  "type": "Feature",
  "properties": {
    "iso:country":"CA",
    "sg:address":"800 15th Ave E",
    "sg:city":"Prince Albert",
    "sg:classifiers":[
        {
            "category":"Shopping",
            "subcategory":"Department Store",
            "type":"Retail Goods"
        }
    ],
    "sg:phone":"+1 306 764 9770",
    "sg:postcode":"S6V 7A4",
    "sg:province":"SK",
    "wof:name":"Wal-Mart",
    "wof:placetype":"venue"
},
  "geometry": {"coordinates":[-105.70695499999999,53.201454],"type":"Point"}
}