{
  "type": "Feature",
  "properties": {
    "addr:full":"7804 141 St NW Edmonton AB T5R 0K2",
    "addr:housenumber":"7804",
    "addr:postcode":"t5r 0k2",
    "addr:street":"141 St Nw",
    "iso:country":"CA",
    "sg:address":"7804 141 St NW",
    "sg:city":"Edmonton",
    "sg:classifiers":[
        {
            "category":"Professional",
            "subcategory":"Lawyer & Legal Services",
            "type":"Services"
        }
    ],
    "sg:phone":"+1 780 444 7966",
    "sg:postcode":"T5R 0K2",
    "sg:province":"AB",
    "sg:tags":[
        "attorney"
    ],
    "wof:name":"Dunlop, C R B",
    "wof:placetype":"venue"
},
  "geometry": {"coordinates":[-113.564255,53.513771],"type":"Point"}
}