{
  "type": "Feature",
  "properties": {
    "addr:full":"6961 Rue Saint-Denis Montreal QC H2S 2S5",
    "addr:housenumber":"6961",
    "addr:postcode":"h2s 2s5",
    "addr:street":"Rue Saint-Denis",
    "iso:country":"CA",
    "sg:address":"6961 Rue Saint-Denis",
    "sg:city":"Montreal",
    "sg:classifiers":[
        {
            "category":"Shopping",
            "subcategory":"Discount & Variety Stores",
            "type":"Retail Goods"
        }
    ],
    "sg:phone":"+1 514 279 5866",
    "sg:postcode":"H2S 2S5",
    "sg:province":"QC",
    "wof:name":"Bazar DE L'Est Tp",
    "wof:placetype":"venue"
},
  "geometry": {"coordinates":[-73.612183,45.537422],"type":"Point"}
}