{
  "type": "Feature",
  "properties": {
    "iso:country":"CA",
    "sg:address":"17 Adam St",
    "sg:city":"Antigonish",
    "sg:classifiers":[
        {
            "category":"Utilities",
            "subcategory":"Refuse",
            "type":"Services"
        }
    ],
    "sg:phone":"+1 902 863 1744",
    "sg:postcode":"B2G 2G1",
    "sg:province":"NS",
    "sg:tags":[
        "garbage",
        "collection"
    ],
    "wof:name":"Eastern Sanitation Ltd",
    "wof:placetype":"venue"
},
  "geometry": {"coordinates":[-61.978481,45.62542],"type":"Point"}
}