{
  "type": "Feature",
  "properties": {
    "addr:full":"1215 Rue Beaubien E Montreal QC H2S 1T8",
    "addr:housenumber":"1215",
    "addr:postcode":"h2s 1t8",
    "addr:street":"Rue Beaubien E",
    "iso:country":"CA",
    "sg:address":"1215 Rue Beaubien E",
    "sg:city":"Montreal",
    "sg:classifiers":[
        {
            "category":"Organizations",
            "subcategory":"Religious Organization",
            "type":"Services"
        }
    ],
    "sg:phone":"+1 514 271 6511",
    "sg:postcode":"H2S 1T8",
    "sg:province":"QC",
    "sg:tags":[
        "church"
    ],
    "wof:name":"Eglise St Ambroise",
    "wof:placetype":"venue"
},
  "geometry": {"coordinates":[-73.600723,45.538895],"type":"Point"}
}