{
  "type": "Feature",
  "properties": {
    "iso:country":"CA",
    "sg:address":"1834 Lakeshore Rd W",
    "sg:city":"Mississauga",
    "sg:classifiers":[
        {
            "category":"Personal",
            "subcategory":"Beauty Salon",
            "type":"Services"
        }
    ],
    "sg:phone":"+1 905 823 5953",
    "sg:postcode":"L5J 1J7",
    "sg:province":"ON",
    "wof:name":"Split Ends Hair Design",
    "wof:placetype":"venue"
},
  "geometry": {"coordinates":[-79.6250915527,43.5152511597],"type":"Point"}
}