{
  "type": "Feature",
  "properties": {
    "addr:full":"529 Gore Ave Vancouver BC V6A 2Z6",
    "addr:housenumber":"529",
    "addr:postcode":"v6a 2z6",
    "addr:street":"Gore Ave",
    "iso:country":"CA",
    "sg:address":"529 Gore Ave",
    "sg:city":"Vancouver",
    "sg:classifiers":[
        {
            "category":"Manufacturing",
            "subcategory":"Printing",
            "type":"Manufacturing & Wholesale Goods"
        }
    ],
    "sg:phone":"+1 604 681 6022",
    "sg:postcode":"V6A 2Z6",
    "sg:province":"BC",
    "sg:tags":[
        "publication",
        "association"
    ],
    "wof:name":"Chinese Nationalists League",
    "wof:placetype":"venue"
},
  "geometry": {"coordinates":[-123.09740447999999,49.2799682617],"type":"Point"}
}