{
  "type": "Feature",
  "properties": {
    "addr:full":"1790 Midland Ave Scarborough ON M1P 3C2",
    "addr:housenumber":"1790",
    "addr:postcode":"m1p 3c2",
    "addr:street":"Midland Ave",
    "iso:country":"CA",
    "sg:address":"1790 Midland Ave",
    "sg:city":"Scarborough",
    "sg:classifiers":[
        {
            "category":"Manufacturing",
            "subcategory":"Tools & Machinery",
            "type":"Manufacturing & Wholesale Goods"
        }
    ],
    "sg:phone":"+1 416 751 0420",
    "sg:postcode":"M1P 3C2",
    "sg:province":"ON",
    "sg:tags":[
        "die",
        "maker"
    ],
    "wof:name":"Fulson Industries Ltd",
    "wof:placetype":"venue"
},
  "geometry": {"coordinates":[-79.2691574097,43.7618560791],"type":"Point"}
}