{
  "type": "Feature",
  "properties": {
    "iso:country":"CA",
    "sg:address":"124 King St E",
    "sg:city":"Gananoque",
    "sg:classifiers":[
        {
            "category":"Restaurant",
            "type":"Food & Drink"
        }
    ],
    "sg:phone":"+1 613 382 4352",
    "sg:postcode":"K7G 1G2",
    "sg:province":"ON",
    "wof:name":"Modern Restaurant & Dining Lng",
    "wof:placetype":"venue"
},
  "geometry": {"coordinates":[-76.1620941162,44.3300514221],"type":"Point"}
}