{
  "type": "Feature",
  "properties": {
    "addr:full":"Paspebiac QC G0C 2K0",
    "addr:postcode":"g0c 2k0",
    "iso:country":"CA",
    "sg:city":"Paspebiac",
    "sg:classifiers":[
        {
            "category":"Professional",
            "subcategory":"Business Services",
            "type":"Services"
        }
    ],
    "sg:phone":"+1 418 752 2205",
    "sg:postcode":"G0C 2K0",
    "sg:province":"QC",
    "sg:tags":[
        "notary"
    ],
    "wof:name":"Joseph, Hermel",
    "wof:placetype":"venue"
},
  "geometry": {"coordinates":[-65.241043,48.030067],"type":"Point"}
}