{
  "type": "Feature",
  "properties": {
    "addr:full":"2183 Av Saint-Marc Shawinigan QC G9N 2J4",
    "addr:housenumber":"2183",
    "addr:postcode":"g9n 2j4",
    "addr:street":"Av Saint-Marc",
    "iso:country":"CA",
    "sg:address":"2183 Av Saint-Marc",
    "sg:city":"Shawinigan",
    "sg:classifiers":[
        {
            "category":"Organizations",
            "subcategory":"Non-profit Organization",
            "type":"Services"
        }
    ],
    "sg:phone":"+1 819 537 8851",
    "sg:postcode":"G9N 2J4",
    "sg:province":"QC",
    "sg:tags":[
        "charitable",
        "social",
        "institution",
        "welfare"
    ],
    "wof:name":"Centre Roland-Bertrand",
    "wof:placetype":"venue"
},
  "geometry": {"coordinates":[-72.7414016724,46.5545654297],"type":"Point"}
}