{
  "type": "Feature",
  "properties": {
    "addr:full":"1375 Adanac St Vancouver BC V5L 2C4",
    "addr:housenumber":"1375",
    "addr:postcode":"v5l 2c4",
    "addr:street":"Adanac St",
    "iso:country":"CA",
    "sg:address":"1375 Adanac St",
    "sg:city":"Vancouver",
    "sg:classifiers":[
        {
            "category":"Restaurant",
            "type":"Food & Drink"
        }
    ],
    "sg:phone":"+1 604 718 5777",
    "sg:postcode":"V5L 2C4",
    "sg:province":"BC",
    "wof:name":"Benny's Bagels",
    "wof:placetype":"venue"
},
  "geometry": {"coordinates":[-123.07598877,49.2777748108],"type":"Point"}
}