{
  "type": "Feature",
  "properties": {
    "addr:full":"526 Rue Principale Saint-Patrice-DE-Beaurivage QC G0S 1B0",
    "addr:housenumber":"526",
    "addr:postcode":"g0s 1b0",
    "addr:street":"Rue Principale",
    "iso:country":"CA",
    "sg:address":"526 Rue Principale",
    "sg:city":"Saint-Patrice-DE-Beaurivage",
    "sg:classifiers":[
        {
            "category":"Food & Beverages",
            "subcategory":"Groceries & Convenience Stores",
            "type":"Retail Goods"
        }
    ],
    "sg:phone":"+1 418 596 2809",
    "sg:postcode":"G0S 1B0",
    "sg:province":"QC",
    "sg:tags":[
        "grocer"
    ],
    "wof:name":"Accommodation St-Patrice",
    "wof:placetype":"venue"
},
  "geometry": {"coordinates":[-71.2345962524,46.4121322632],"type":"Point"}
}