{
  "type": "Feature",
  "properties": {
    "addr:full":"561 Rang Nault Victoriaville QC G6P 7R9",
    "addr:housenumber":"561",
    "addr:postcode":"g6p 7r9",
    "addr:street":"Rang Nault",
    "iso:country":"CA",
    "sg:address":"561 Rang Nault",
    "sg:city":"Victoriaville",
    "sg:classifiers":[
        {
            "category":"Autos & Motor Vehicles",
            "subcategory":"Automobile Sales",
            "type":"Retail Goods"
        }
    ],
    "sg:phone":"+1 819 752 3535",
    "sg:postcode":"G6P 7R9",
    "sg:province":"QC",
    "sg:tags":[
        "snowmobile"
    ],
    "wof:name":"Club DE Motoneige Alleghanish",
    "wof:placetype":"venue"
},
  "geometry": {"coordinates":[-71.92420199999999,46.077896],"type":"Point"}
}