{
  "type": "Feature",
  "properties": {
    "addr:full":"Odessa ON K0H 2H0",
    "addr:postcode":"k0h 2h0",
    "iso:country":"CA",
    "sg:city":"Odessa",
    "sg:classifiers":[
        {
            "category":"Building & Trades",
            "subcategory":"Construction",
            "type":"Services"
        }
    ],
    "sg:phone":"+1 613 389 5949",
    "sg:postcode":"K0H 2H0",
    "sg:province":"ON",
    "sg:tags":[
        "masonry",
        "contractor"
    ],
    "wof:name":"I Pascoal Masonry Ltd",
    "wof:placetype":"venue"
},
  "geometry": {"coordinates":[-76.718918,44.276974],"type":"Point"}
}