{
  "type": "Feature",
  "properties": {
    "addr:full":"89 LA Grande Allee E Grande-Riviere QC G0C 1V0",
    "addr:housenumber":"89",
    "addr:postcode":"g0c 1v0",
    "addr:street":"La Grande Allee E Grande-Riviere",
    "iso:country":"CA",
    "sg:address":"89 LA Grande Allee E",
    "sg:city":"Grande-Riviere",
    "sg:classifiers":[
        {
            "category":"Autos & Motor Vehicles",
            "subcategory":"Automobile Sales",
            "type":"Retail Goods"
        }
    ],
    "sg:phone":"+1 418 385 2279",
    "sg:postcode":"G0C 1V0",
    "sg:province":"QC",
    "sg:tags":[
        "car",
        "dealer"
    ],
    "wof:name":"Location Sutton Autos",
    "wof:placetype":"venue"
},
  "geometry": {"coordinates":[-64.498199,48.397816],"type":"Point"}
}