{
  "type": "Feature",
  "properties": {
    "iso:country":"CA",
    "sg:address":"5915 Leslie St",
    "sg:city":"North York",
    "sg:classifiers":[
        {
            "category":"Education",
            "subcategory":"Dance Studio",
            "type":"Public Place"
        }
    ],
    "sg:phone":"+1 416 497 1793",
    "sg:postcode":"M2H 1J8",
    "sg:province":"ON",
    "sg:tags":[
        "school",
        "instruction",
        "dancing"
    ],
    "wof:name":"Conservatory of Dance & Music",
    "wof:placetype":"venue"
},
  "geometry": {"coordinates":[-79.3702697754,43.8003234863],"type":"Point"}
}