{
  "type": "Feature",
  "properties": {
    "addr:full":"34 Rue St Pierre Sainte-Sophie-DE-Levrard QC G0X 3C0",
    "addr:housenumber":"34",
    "addr:postcode":"g0x 3c0",
    "addr:street":"Rue St Pierre Sainte-Sophie-De-Levrard",
    "iso:country":"CA",
    "sg:address":"34 Rue St Pierre",
    "sg:city":"Sainte-Sophie-DE-Levrard",
    "sg:classifiers":[
        {
            "category":"Food & Beverages",
            "subcategory":"Groceries & Convenience Stores",
            "type":"Retail Goods"
        }
    ],
    "sg:phone":"+1 819 288 5923",
    "sg:postcode":"G0X 3C0",
    "sg:province":"QC",
    "sg:tags":[
        "grocer"
    ],
    "wof:name":"Epicerie Michel Morasse",
    "wof:placetype":"venue"
},
  "geometry": {"coordinates":[-72.110657,46.428799],"type":"Point"}
}