{
  "type": "Feature",
  "properties": {
    "addr:full":"311 Bowes Rd Concord ON L4K 1J1",
    "addr:housenumber":"311",
    "addr:postcode":"l4k 1j1",
    "addr:street":"Bowes Rd",
    "iso:country":"CA",
    "sg:address":"311 Bowes Rd",
    "sg:city":"Concord",
    "sg:classifiers":[
        {
            "category":"Retail",
            "subcategory":"Auto Repair",
            "type":"Services"
        }
    ],
    "sg:phone":"+1 905 669 2369",
    "sg:postcode":"L4K 1J1",
    "sg:province":"ON",
    "sg:tags":[
        "repairing",
        "automobile"
    ],
    "wof:name":"Gus's Auto Repair",
    "wof:placetype":"venue"
},
  "geometry": {"coordinates":[-79.4930725098,43.8107910156],"type":"Point"}
}