{
  "type": "Feature",
  "properties": {
    "addr:full":"40 Pleasant Blvd # 801 Toronto ON M4T 1J9",
    "addr:housenumber":"40;801",
    "addr:postcode":"m4t 1j9",
    "addr:street":"Pleasant Blvd #",
    "iso:country":"CA",
    "sg:address":"40 Pleasant Blvd # 801",
    "sg:city":"Toronto",
    "sg:classifiers":[
        {
            "category":"Professional",
            "subcategory":"Lawyer & Legal Services",
            "type":"Services"
        }
    ],
    "sg:phone":"+1 416 966 8883",
    "sg:postcode":"M4T 1J9",
    "sg:province":"ON",
    "sg:tags":[
        "attorney"
    ],
    "wof:name":"Neuberger, Edith",
    "wof:placetype":"venue"
},
  "geometry": {"coordinates":[-79.391739,43.68771],"type":"Point"}
}