{
  "type": "Feature",
  "properties": {
    "addr:full":"Trois-Rivieres QC G9A 5W3",
    "addr:postcode":"g9a 5w3",
    "iso:country":"CA",
    "sg:city":"Trois-Rivieres",
    "sg:classifiers":[
        {
            "category":"Health Services",
            "subcategory":"Nursing And Care Facility",
            "type":"Services"
        }
    ],
    "sg:phone":"+1 819 373 8996",
    "sg:postcode":"G9A 5W3",
    "sg:province":"QC",
    "sg:tags":[
        "home",
        "retirement",
        "community"
    ],
    "wof:name":"Carrefour DE LA Paix Inc",
    "wof:placetype":"venue"
},
  "geometry": {"coordinates":[-72.544685,46.33662],"type":"Point"}
}