{
  "type": "Feature",
  "properties": {
    "iso:country":"CA",
    "sg:address":"2195 Dunwin Dr",
    "sg:city":"Mississauga",
    "sg:classifiers":[
        {
            "category":"Wholesale",
            "subcategory":"Electrical",
            "type":"Manufacturing & Wholesale Goods"
        }
    ],
    "sg:phone":"+1 905 607 6600",
    "sg:postcode":"L5L 1X2",
    "sg:province":"ON",
    "sg:tags":[
        "equipment",
        "electric",
        "supply"
    ],
    "wof:name":"Ied Ltd Partnership II",
    "wof:placetype":"venue"
},
  "geometry": {"coordinates":[-79.67315673829999,43.5350799561],"type":"Point"}
}