{
  "type": "Feature",
  "properties": {
    "addr:full":"215 Confederation St Sarnia ON N7T 1Z9",
    "addr:housenumber":"215",
    "addr:postcode":"n7t 1z9",
    "addr:street":"Confederation St",
    "iso:country":"CA",
    "sg:address":"215 Confederation St",
    "sg:city":"Sarnia",
    "sg:classifiers":[
        {
            "category":"Professional",
            "subcategory":"Business Services",
            "type":"Services"
        }
    ],
    "sg:phone":"+1 519 332 1944",
    "sg:postcode":"N7T 1Z9",
    "sg:province":"ON",
    "sg:tags":[
        "paper"
    ],
    "wof:name":"A & W Security Shredding",
    "wof:placetype":"venue"
},
  "geometry": {"coordinates":[-82.40898900000001,42.96225],"type":"Point"}
}