{
  "type": "Feature",
  "properties": {
    "addr:full":"134 Central Ave N Swift Current SK S9H 0L1",
    "addr:housenumber":"134",
    "addr:postcode":"s9h 0l1",
    "addr:street":"Central Ave N",
    "iso:country":"CA",
    "sg:address":"134 Central Ave N",
    "sg:city":"Swift Current",
    "sg:classifiers":[
        {
            "category":"Communications",
            "subcategory":"Radio Station",
            "type":"Services"
        }
    ],
    "sg:phone":"+1 306 773 4605",
    "sg:postcode":"S9H 0L1",
    "sg:province":"SK",
    "sg:tags":[
        "company",
        "broadcasting"
    ],
    "wof:name":"Cksw",
    "wof:placetype":"venue"
},
  "geometry": {"coordinates":[-107.80017100000001,50.284073],"type":"Point"}
}