{
  "type": "Feature",
  "properties": {
    "addr:full":"Calgary AB T3B 2W9",
    "addr:postcode":"t3b 2w9",
    "iso:country":"CA",
    "sg:city":"Calgary",
    "sg:classifiers":[
        {
            "category":"Wholesale",
            "subcategory":"Machinery & Supplies",
            "type":"Manufacturing & Wholesale Goods"
        }
    ],
    "sg:phone":"+1 403 247 0150",
    "sg:postcode":"T3B 2W9",
    "sg:province":"AB",
    "sg:tags":[
        "equipment",
        "heat",
        "oil",
        "well",
        "exchanger"
    ],
    "wof:name":"On-Site Power Ltd",
    "wof:placetype":"venue"
},
  "geometry": {"coordinates":[-114.17208100000001,51.09766],"type":"Point"}
}