{
  "type": "Feature",
  "properties": {
    "addr:full":"1355 Weston Rd York ON M6M 4R9",
    "addr:housenumber":"1355",
    "addr:postcode":"m6m 4r9",
    "addr:street":"Weston Rd",
    "iso:country":"CA",
    "sg:address":"1355 Weston Rd",
    "sg:city":"York",
    "sg:classifiers":[
        {
            "category":"Shopping",
            "type":"Retail Goods"
        }
    ],
    "sg:phone":"+1 416 241 8080",
    "sg:postcode":"M6M 4R9",
    "sg:province":"ON",
    "sg:tags":[
        "equipment",
        "telephone",
        "supply"
    ],
    "wof:name":"A & R Communications Inc",
    "wof:placetype":"venue"
},
  "geometry": {"coordinates":[-79.49918365480001,43.6907615662],"type":"Point"}
}