{
  "type": "Feature",
  "properties": {
    "addr:full":"51 Rte Du Fleuve O Sainte-Luce QC G0K 1P0",
    "addr:housenumber":"51",
    "addr:postcode":"g0k 1p0",
    "addr:street":"Rte Du Fleuve O",
    "iso:country":"CA",
    "sg:address":"51 Rte Du Fleuve O",
    "sg:city":"Sainte-Luce",
    "sg:classifiers":[
        {
            "category":"Health Services",
            "subcategory":"Nursing And Care Facility",
            "type":"Services"
        }
    ],
    "sg:phone":"+1 418 739 3555",
    "sg:postcode":"G0K 1P0",
    "sg:province":"QC",
    "sg:tags":[
        "home",
        "rest"
    ],
    "wof:name":"Pavillon Ste-Luce",
    "wof:placetype":"venue"
},
  "geometry": {"coordinates":[-68.3614349365,48.5462265015],"type":"Point"}
}