{
  "type": "Feature",
  "properties": {
    "addr:full":"Lachute QC J8H 1R6",
    "addr:postcode":"j8h 1r6",
    "iso:country":"CA",
    "sg:city":"Lachute",
    "sg:classifiers":[
        {
            "category":"Shopping",
            "subcategory":"Crafts & Fabrics",
            "type":"Retail Goods"
        }
    ],
    "sg:phone":"+1 450 562 3470",
    "sg:postcode":"J8H 1R6",
    "sg:province":"QC",
    "sg:tags":[
        "shop"
    ],
    "wof:name":"Chez Lise Tissus",
    "wof:placetype":"venue"
},
  "geometry": {"coordinates":[-74.33225299999999,45.65583],"type":"Point"}
}