{
  "type": "Feature",
  "properties": {
    "addr:full":"613 Kennedy Rd Scarborough ON M1K 2B2",
    "addr:housenumber":"613",
    "addr:postcode":"m1k 2b2",
    "addr:street":"Kennedy Rd",
    "iso:country":"CA",
    "sg:address":"613 Kennedy Rd",
    "sg:city":"Scarborough",
    "sg:classifiers":[
        {
            "category":"Organizations",
            "subcategory":"Religious Organization",
            "type":"Services"
        }
    ],
    "sg:phone":"+1 416 266 3977",
    "sg:postcode":"M1K 2B2",
    "sg:province":"ON",
    "wof:name":"United Spiritual Baptist Chrch",
    "wof:placetype":"venue"
},
  "geometry": {"coordinates":[-79.264465332,43.7245178223],"type":"Point"}
}