{
  "type": "Feature",
  "properties": {
    "addr:full":"1418 Montee Sauvage Prevost QC J0R 1T0",
    "addr:housenumber":"1418",
    "addr:postcode":"j0r 1t0",
    "addr:street":"Montee Sauvage Prevost",
    "iso:country":"CA",
    "sg:address":"1418 Montee Sauvage",
    "sg:city":"Prevost",
    "sg:classifiers":[
        {
            "category":"Building & Trades",
            "subcategory":"Electrical",
            "type":"Services"
        }
    ],
    "sg:phone":"+1 450 224 7288",
    "sg:postcode":"J0R 1T0",
    "sg:province":"QC",
    "sg:tags":[
        "electric",
        "contractor"
    ],
    "wof:name":"Andre & Fils Electriciens",
    "wof:placetype":"venue"
},
  "geometry": {"coordinates":[-74.0699539185,45.8785858154],"type":"Point"}
}