{
  "type": "Feature",
  "properties": {
    "addr:full":"1262 Barton St E Hamilton ON L8H 2V9",
    "addr:housenumber":"1262",
    "addr:postcode":"l8h 2v9",
    "addr:street":"Barton St E",
    "iso:country":"CA",
    "sg:address":"1262 Barton St E",
    "sg:city":"Hamilton",
    "sg:classifiers":[
        {
            "category":"Retail",
            "subcategory":"Auto Repair",
            "type":"Services"
        }
    ],
    "sg:phone":"+1 905 545 2337",
    "sg:postcode":"L8H 2V9",
    "sg:province":"ON",
    "sg:tags":[
        "repairing",
        "automobile"
    ],
    "wof:name":"Brian's Automotive Svc",
    "wof:placetype":"venue"
},
  "geometry": {"coordinates":[-79.809074,43.249699],"type":"Point"}
}