{
  "type": "Feature",
  "properties": {
    "addr:full":"645 Hewitson St Thunder Bay ON P7B 5V5",
    "addr:housenumber":"645",
    "addr:postcode":"p7b 5v5",
    "addr:street":"Hewitson St",
    "iso:country":"CA",
    "sg:address":"645 Hewitson St",
    "sg:city":"Thunder Bay",
    "sg:classifiers":[
        {
            "category":"Wholesale",
            "subcategory":"Machinery & Supplies",
            "type":"Manufacturing & Wholesale Goods"
        }
    ],
    "sg:phone":"+1 807 625 0104",
    "sg:postcode":"P7B 5V5",
    "sg:province":"ON",
    "sg:tags":[
        "equipment",
        "hydraulic"
    ],
    "wof:name":"Midwest Hydraulics",
    "wof:placetype":"venue"
},
  "geometry": {"coordinates":[-89.2519683838,48.4052200317],"type":"Point"}
}