{
  "type": "Feature",
  "properties": {
    "addr:full":"3005 George St Duncan BC V9L 2A8",
    "addr:housenumber":"3005",
    "addr:postcode":"v9l 2a8",
    "addr:street":"George St",
    "iso:country":"CA",
    "sg:address":"3005 George St",
    "sg:city":"Duncan",
    "sg:classifiers":[
        {
            "category":"Personal",
            "subcategory":"Beauty Salon",
            "type":"Services"
        }
    ],
    "sg:phone":"+1 250 746 0889",
    "sg:postcode":"V9L 2A8",
    "sg:province":"BC",
    "wof:name":"Robyn's Nest Hair Design",
    "wof:placetype":"venue"
},
  "geometry": {"coordinates":[-123.70738220200001,48.779094696],"type":"Point"}
}