{
  "type": "Feature",
  "properties": {
    "addr:full":"Calgary AB T3E 4P2",
    "addr:postcode":"t3e 4p2",
    "iso:country":"CA",
    "sg:city":"Calgary",
    "sg:classifiers":[
        {
            "category":"Retail",
            "subcategory":"Veterinary Services",
            "type":"Services"
        }
    ],
    "sg:phone":"+1 403 246 1774",
    "sg:postcode":"T3E 4P2",
    "sg:province":"AB",
    "sg:tags":[
        "veterinarian"
    ],
    "wof:name":"Glamorgan Animal Clinic",
    "wof:placetype":"venue"
},
  "geometry": {"coordinates":[-114.14282989500001,51.021686554],"type":"Point"}
}