{
  "type": "Feature",
  "properties": {
    "addr:full":"304 Main St Fredericton NB E3A 1E4",
    "addr:housenumber":"304",
    "addr:postcode":"e3a 1e4",
    "addr:street":"Main St",
    "iso:country":"CA",
    "sg:address":"304 Main St",
    "sg:city":"Fredericton",
    "sg:classifiers":[
        {
            "category":"Shopping",
            "subcategory":"Florist",
            "type":"Retail Goods"
        }
    ],
    "sg:phone":"+1 506 458 9268",
    "sg:postcode":"E3A 1E4",
    "sg:province":"NB",
    "wof:name":"Main Street Floral Gallery",
    "wof:placetype":"venue"
},
  "geometry": {"coordinates":[-66.64572143549999,45.975189209],"type":"Point"}
}