{
  "type": "Feature",
  "properties": {
    "addr:full":"616 35 Ave NE Calgary AB T2E 2L1",
    "addr:postcode":"t2e 2l1",
    "addr:street":"616 35 Ave Ne",
    "iso:country":"CA",
    "sg:address":"616 35 Ave NE",
    "sg:city":"Calgary",
    "sg:classifiers":[
        {
            "category":"Manufacturing",
            "subcategory":"Metals",
            "type":"Manufacturing & Wholesale Goods"
        }
    ],
    "sg:phone":"+1 403 230 4201",
    "sg:postcode":"T2E 2L1",
    "sg:province":"AB",
    "sg:tags":[
        "steel",
        "fabricator",
        "sheet"
    ],
    "wof:name":"Calgary Precision Metal Ltd",
    "wof:placetype":"venue"
},
  "geometry": {"coordinates":[-114.05024,51.08424],"type":"Point"}
}