{
  "type": "Feature",
  "properties": {
    "addr:full":"444 Mcleod St Regina SK S4N 4Y1",
    "addr:housenumber":"444",
    "addr:postcode":"s4n 4y1",
    "addr:street":"Mcleod St",
    "iso:country":"CA",
    "sg:address":"444 Mcleod St",
    "sg:city":"Regina",
    "sg:classifiers":[
        {
            "category":"Real Estate",
            "subcategory":"Real Estate Agent",
            "type":"Services"
        }
    ],
    "sg:phone":"+1 306 721 7070",
    "sg:postcode":"S4N 4Y1",
    "sg:province":"SK",
    "sg:tags":[
        "cooperative"
    ],
    "wof:name":"Federated CO-Operatives Ltd",
    "wof:placetype":"venue"
},
  "geometry": {"coordinates":[-104.579353333,50.4715003967],"type":"Point"}
}