{
  "type": "Feature",
  "properties": {
    "iso:country":"CA",
    "sg:address":"1030 Innes Rd",
    "sg:city":"Gloucester",
    "sg:classifiers":[
        {
            "category":"Government",
            "subcategory":"Office",
            "type":"Public Place"
        }
    ],
    "sg:phone":"+1 613 998 3721",
    "sg:postcode":"K1B 4S7",
    "sg:province":"ON",
    "wof:name":"Canada Conservation Institute",
    "wof:placetype":"venue"
},
  "geometry": {"coordinates":[-75.6068725586,45.4148483276],"type":"Point"}
}