{
  "type": "Feature",
  "properties": {
    "addr:full":"Mont-Royal QC H4P 1P7",
    "addr:postcode":"h4p 1p7",
    "iso:country":"CA",
    "sg:city":"Mont-Royal",
    "sg:classifiers":[
        {
            "category":"Travel",
            "subcategory":"Travel Agent",
            "type":"Entertainment"
        }
    ],
    "sg:phone":"+1 514 738 5177",
    "sg:postcode":"H4P 1P7",
    "sg:province":"QC",
    "sg:tags":[
        "agency",
        "bureau"
    ],
    "wof:name":"Vacances Ideal",
    "wof:placetype":"venue"
},
  "geometry": {"coordinates":[-73.658417,45.493988],"type":"Point"}
}