{
  "type": "Feature",
  "properties": {
    "addr:full":"80 3rd Line Hagersville ON N0A 1H0",
    "addr:housenumber":"80",
    "addr:postcode":"n0a 1h0",
    "addr:street":"3Rd Line",
    "iso:country":"CA",
    "sg:address":"80 3rd Line",
    "sg:city":"Hagersville",
    "sg:classifiers":[
        {
            "category":"Freight",
            "type":"Transportation"
        }
    ],
    "sg:phone":"+1 905 768 5742",
    "sg:postcode":"N0A 1H0",
    "sg:province":"ON",
    "sg:tags":[
        "trucking"
    ],
    "wof:name":"Mc Burney Transport Ltd",
    "wof:placetype":"venue"
},
  "geometry": {"coordinates":[-80.01313,43.009293],"type":"Point"}
}