{
  "type": "Feature",
  "properties": {
    "addr:full":"190 Annagem Blvd Mississauga ON L5T 2V5",
    "addr:housenumber":"190",
    "addr:postcode":"l5t 2v5",
    "addr:street":"Annagem Blvd",
    "iso:country":"CA",
    "sg:address":"190 Annagem Blvd",
    "sg:city":"Mississauga",
    "sg:classifiers":[
        {
            "category":"Shopping",
            "subcategory":"Clothing, Apparel, & Fashions",
            "type":"Retail Goods"
        }
    ],
    "sg:phone":"+1 905 564 4817",
    "sg:postcode":"L5T 2V5",
    "sg:province":"ON",
    "sg:tags":[
        "umbrella"
    ],
    "wof:name":"Totes Isotoner Canada Ltd",
    "wof:placetype":"venue"
},
  "geometry": {"coordinates":[-79.687569,43.638573],"type":"Point"}
}