{
  "type": "Feature",
  "properties": {
    "addr:full":"2430 Burrard St Vancouver BC V6J 5L3",
    "addr:housenumber":"2430",
    "addr:postcode":"v6j 5l3",
    "addr:street":"Burrard St",
    "iso:country":"CA",
    "sg:address":"2430 Burrard St",
    "sg:city":"Vancouver",
    "sg:classifiers":[
        {
            "category":"Home & Garden",
            "subcategory":"Furniture",
            "type":"Retail Goods"
        }
    ],
    "sg:phone":"+1 604 731 9020",
    "sg:postcode":"V6J 5L3",
    "sg:province":"BC",
    "wof:name":"Upholstery Arts",
    "wof:placetype":"venue"
},
  "geometry": {"coordinates":[-123.145523071,49.2643127441],"type":"Point"}
}