{
  "type": "Feature",
  "properties": {
    "addr:full":"2170 Rue DE LA Montagne Montreal QC H3G 1Z7",
    "addr:housenumber":"2170",
    "addr:postcode":"h3g 1z7",
    "addr:street":"Rue De La Montagne",
    "iso:country":"CA",
    "sg:address":"2170 Rue DE LA Montagne",
    "sg:city":"Montreal",
    "sg:classifiers":[
        {
            "category":"Restaurant",
            "type":"Food & Drink"
        }
    ],
    "sg:phone":"+1 514 849 1172",
    "sg:postcode":"H3G 1Z7",
    "sg:province":"QC",
    "wof:name":"Katsura Restaurant Japonais",
    "wof:placetype":"venue"
},
  "geometry": {"coordinates":[-73.577988,45.499172],"type":"Point"}
}