{
  "type": "Feature",
  "properties": {
    "addr:full":"132 Rte DE LA Montagne Notre-Dame-Du-Portage QC G0L 1Y0",
    "addr:housenumber":"132",
    "addr:postcode":"g0l 1y0",
    "addr:street":"Rte De La Montagne",
    "iso:country":"CA",
    "sg:address":"132 Rte DE LA Montagne",
    "sg:city":"Notre-Dame-Du-Portage",
    "sg:classifiers":[
        {
            "category":"Recreation",
            "type":"Entertainment"
        }
    ],
    "sg:phone":"+1 418 862 7745",
    "sg:postcode":"G0L 1Y0",
    "sg:province":"QC",
    "sg:tags":[
        "range",
        "practice",
        "golf"
    ],
    "wof:name":"Club DE Golf DE Riviere Du Lp",
    "wof:placetype":"venue"
},
  "geometry": {"coordinates":[-69.5830230713,47.8063735962],"type":"Point"}
}