{
  "type": "Feature",
  "properties": {
    "iso:country":"CA",
    "sg:address":"136 Rue Principale",
    "sg:city":"Sainte-Claire",
    "sg:classifiers":[
        {
            "category":"Retail",
            "subcategory":"Funeral Services",
            "type":"Services"
        }
    ],
    "sg:phone":"+1 418 883 3715",
    "sg:postcode":"G0R 2V0",
    "sg:province":"QC",
    "sg:tags":[
        "director"
    ],
    "wof:name":"Roy & Rouleau Inc",
    "wof:placetype":"venue"
},
  "geometry": {"coordinates":[-70.8645782471,46.5980262756],"type":"Point"}
}