{
  "type": "Feature",
  "properties": {
    "addr:full":"Langley BC V1M 2Y2",
    "addr:postcode":"v1m 2y2",
    "iso:country":"CA",
    "sg:city":"Langley",
    "sg:classifiers":[
        {
            "category":"Cinema",
            "subcategory":"Movie Rental",
            "type":"Entertainment"
        }
    ],
    "sg:phone":"+1 604 888 4040",
    "sg:postcode":"V1M 2Y2",
    "sg:province":"BC",
    "sg:tags":[
        "leasing",
        "video",
        "disc",
        "tape"
    ],
    "wof:name":"Blockbuster Video",
    "wof:placetype":"venue"
},
  "geometry": {"coordinates":[-122.63745880099999,49.1630783081],"type":"Point"}
}