{
  "type": "Feature",
  "properties": {
    "addr:full":"6600 Carriere St Orleans ON K1C 1J4",
    "addr:housenumber":"6600",
    "addr:postcode":"k1c 1j4",
    "addr:street":"Carriere St",
    "iso:country":"CA",
    "sg:address":"6600 Carriere St",
    "sg:city":"Orleans",
    "sg:classifiers":[
        {
            "category":"Education",
            "subcategory":"School",
            "type":"Public Place"
        }
    ],
    "sg:phone":"+1 613 830 6436",
    "sg:postcode":"K1C 1J4",
    "sg:province":"ON",
    "wof:name":"Ecole DE Musique Du Ctr",
    "wof:placetype":"venue"
},
  "geometry": {"coordinates":[-75.52298,45.466244],"type":"Point"}
}