{
  "type": "Feature",
  "properties": {
    "addr:full":"503 Rue Deslauriers Saint-Laurent QC H4N 1W2",
    "addr:housenumber":"503",
    "addr:postcode":"h4n 1w2",
    "addr:street":"Rue Deslauriers",
    "iso:country":"CA",
    "sg:address":"503 Rue Deslauriers",
    "sg:city":"Saint-Laurent",
    "sg:classifiers":[
        {
            "category":"Restaurant",
            "type":"Food & Drink"
        }
    ],
    "sg:phone":"+1 514 334 1153",
    "sg:postcode":"H4N 1W2",
    "sg:province":"QC",
    "wof:name":"Nikita Foods Inc",
    "wof:placetype":"venue"
},
  "geometry": {"coordinates":[-73.66469573969999,45.5244064331],"type":"Point"}
}