{
  "type": "Feature",
  "properties": {
    "addr:full":"245 Greenwood Ave Toronto ON M4L 2R4",
    "addr:housenumber":"245",
    "addr:postcode":"m4l 2r4",
    "addr:street":"Greenwood Ave",
    "iso:country":"CA",
    "sg:address":"245 Greenwood Ave",
    "sg:city":"Toronto",
    "sg:classifiers":[
        {
            "category":"Wholesale",
            "subcategory":"Meat",
            "type":"Manufacturing & Wholesale Goods"
        }
    ],
    "sg:phone":"+1 416 461 9192",
    "sg:postcode":"M4L 2R4",
    "sg:province":"ON",
    "sg:tags":[
        "butchering"
    ],
    "wof:name":"Strickland Meat Market",
    "wof:placetype":"venue"
},
  "geometry": {"coordinates":[-79.3277206421,43.6707267761],"type":"Point"}
}