{
  "type": "Feature",
  "properties": {
    "addr:full":"141 Duquette Rd Eganville ON K0J 1T0",
    "addr:housenumber":"141",
    "addr:postcode":"k0j 1t0",
    "addr:street":"Duquette Rd",
    "iso:country":"CA",
    "sg:address":"141 Duquette Rd",
    "sg:city":"Eganville",
    "sg:classifiers":[
        {
            "category":"Professional",
            "subcategory":"Research",
            "type":"Services"
        }
    ],
    "sg:phone":"+1 613 628 2064",
    "sg:postcode":"K0J 1T0",
    "sg:province":"ON",
    "sg:tags":[
        "development",
        "electronic"
    ],
    "wof:name":"Stednitz Maritime Tech Ltd",
    "wof:placetype":"venue"
},
  "geometry": {"coordinates":[-77.1009063721,45.5400772095],"type":"Point"}
}