{
  "type": "Feature",
  "properties": {
    "addr:full":"1760 Boul Fiset Sorel-Tracy QC J3P 5K4",
    "addr:housenumber":"1760",
    "addr:postcode":"j3p 5k4",
    "addr:street":"Boul Fiset",
    "iso:country":"CA",
    "sg:address":"1760 Boul Fiset",
    "sg:city":"Sorel-Tracy",
    "sg:classifiers":[
        {
            "category":"Home & Garden",
            "subcategory":"Building Materials",
            "type":"Retail Goods"
        }
    ],
    "sg:phone":"+1 450 743 1003",
    "sg:postcode":"J3P 5K4",
    "sg:province":"QC",
    "sg:tags":[
        "glass",
        "window",
        "plate"
    ],
    "wof:name":"Docteur Du Pare-Brise",
    "wof:placetype":"venue"
},
  "geometry": {"coordinates":[-73.077393,46.024418],"type":"Point"}
}