{
  "type": "Feature",
  "properties": {
    "addr:full":"103 Railside Rd North York ON M3A 1B2",
    "addr:housenumber":"103",
    "addr:postcode":"m3a 1b2",
    "addr:street":"Railside Rd",
    "iso:country":"CA",
    "sg:address":"103 Railside Rd",
    "sg:city":"North York",
    "sg:classifiers":[
        {
            "category":"Local Transit",
            "type":"Transportation"
        }
    ],
    "sg:phone":"+1 416 444 7030",
    "sg:postcode":"M3A 1B2",
    "sg:province":"ON",
    "sg:tags":[
        "bus",
        "line"
    ],
    "wof:name":"Cardinal Coach Lines",
    "wof:placetype":"venue"
},
  "geometry": {"coordinates":[-79.324341,43.735882],"type":"Point"}
}