{
  "type": "Feature",
  "properties": {
    "addr:full":"1218 Rue Fleury E Montreal QC H2C 1R1",
    "addr:housenumber":"1218",
    "addr:postcode":"h2c 1r1",
    "addr:street":"Rue Fleury E",
    "iso:country":"CA",
    "sg:address":"1218 Rue Fleury E",
    "sg:city":"Montreal",
    "sg:classifiers":[
        {
            "category":"Shopping",
            "subcategory":"Clothing, Apparel, & Fashions",
            "type":"Retail Goods"
        }
    ],
    "sg:phone":"+1 514 387 5881",
    "sg:postcode":"H2C 1R1",
    "sg:province":"QC",
    "wof:name":"Boutique Rana Inc",
    "wof:placetype":"venue"
},
  "geometry": {"coordinates":[-73.65825700000001,45.559193],"type":"Point"}
}