{
  "type": "Feature",
  "properties": {
    "addr:full":"91 George St N # 2 Peterborough ON K9J 3G3",
    "addr:housenumber":"91",
    "addr:postcode":"k9j 3g3",
    "addr:street":"George St N # 2",
    "iso:country":"CA",
    "sg:address":"91 George St N # 2",
    "sg:city":"Peterborough",
    "sg:classifiers":[
        {
            "category":"Real Estate",
            "subcategory":"Real Estate Agent",
            "type":"Services"
        }
    ],
    "sg:phone":"+1 705 743 9111",
    "sg:postcode":"K9J 3G3",
    "sg:province":"ON",
    "wof:name":"Re/Max Eastern Realty Inc",
    "wof:placetype":"venue"
},
  "geometry": {"coordinates":[-78.319534,44.296204],"type":"Point"}
}