{
  "type": "Feature",
  "properties": {
    "addr:full":"Farm Harris SK S0L 1K0",
    "addr:postcode":"s0l 1k0",
    "iso:country":"CA",
    "sg:address":"Farm",
    "sg:city":"Harris",
    "sg:classifiers":[
        {
            "category":"Organizations",
            "subcategory":"Non-profit Organization",
            "type":"Services"
        }
    ],
    "sg:phone":"+1 306 656 4722",
    "sg:postcode":"S0L 1K0",
    "sg:province":"SK",
    "sg:tags":[
        "fund",
        "counselor",
        "raising",
        "caterer"
    ],
    "wof:name":"Pat's Family Catering",
    "wof:placetype":"venue"
},
  "geometry": {"coordinates":[-107.583504,51.736183],"type":"Point"}
}