{
  "type": "Feature",
  "properties": {
    "addr:full":"Beauport QC G1B 1H7",
    "addr:postcode":"g1b 1h7",
    "iso:country":"CA",
    "sg:city":"Beauport",
    "sg:classifiers":[
        {
            "category":"Personal",
            "subcategory":"Beauty Salon",
            "type":"Services"
        }
    ],
    "sg:phone":"+1 418 666 7705",
    "sg:postcode":"G1B 1H7",
    "sg:province":"QC",
    "wof:name":"Salon DE Coiffure Mode Plus",
    "wof:placetype":"venue"
},
  "geometry": {"coordinates":[-71.189362,46.901108],"type":"Point"}
}