{
  "type": "Feature",
  "properties": {
    "addr:full":"5420 53rd Ave Drayton Valley AB T7A 1R9",
    "addr:housenumber":"5420",
    "addr:postcode":"t7a 1r9",
    "addr:street":"53Rd Ave",
    "iso:country":"CA",
    "sg:address":"5420 53rd Ave",
    "sg:city":"Drayton Valley",
    "sg:classifiers":[
        {
            "category":"Manufacturing",
            "subcategory":"Tools & Machinery",
            "type":"Manufacturing & Wholesale Goods"
        }
    ],
    "sg:phone":"+1 780 542 5249",
    "sg:postcode":"T7A 1R9",
    "sg:province":"AB",
    "sg:tags":[
        "machine",
        "field",
        "oil",
        "shop"
    ],
    "wof:name":"Drayton Valley Mach & Welding",
    "wof:placetype":"venue"
},
  "geometry": {"coordinates":[-114.985207,53.224812],"type":"Point"}
}