{
  "type": "Feature",
  "properties": {
    "iso:country":"CA",
    "sg:address":"2619 Yonge St",
    "sg:city":"Toronto",
    "sg:classifiers":[
        {
            "category":"Shopping",
            "subcategory":"Clothing, Apparel, & Fashions",
            "type":"Retail Goods"
        }
    ],
    "sg:phone":"+1 416 482 8480",
    "sg:postcode":"M4P 2J1",
    "sg:province":"ON",
    "sg:tags":[
        "item",
        "boutique"
    ],
    "wof:name":"Cache",
    "wof:placetype":"venue"
},
  "geometry": {"coordinates":[-79.39999389650001,43.7148666382],"type":"Point"}
}