{
  "type": "Feature",
  "properties": {
    "addr:full":"41 Brydon Dr Etobicoke ON M9W 4N3",
    "addr:housenumber":"41",
    "addr:postcode":"m9w 4n3",
    "addr:street":"Brydon Dr",
    "iso:country":"CA",
    "sg:address":"41 Brydon Dr",
    "sg:city":"Etobicoke",
    "sg:classifiers":[
        {
            "category":"Retail",
            "subcategory":"Auto Repair",
            "type":"Services"
        }
    ],
    "sg:phone":"+1 416 745 2302",
    "sg:postcode":"M9W 4N3",
    "sg:province":"ON",
    "sg:tags":[
        "body",
        "automobile",
        "painting"
    ],
    "wof:name":"D & D Brydon Auto Repairs",
    "wof:placetype":"venue"
},
  "geometry": {"coordinates":[-79.57197600000001,43.71611],"type":"Point"}
}