{
  "type": "Feature",
  "properties": {
    "addr:full":"4116 Tapestry Trail Mississauga ON L4W 4B7",
    "addr:housenumber":"4116",
    "addr:postcode":"l4w 4b7",
    "addr:street":"Tapestry Trail",
    "iso:country":"CA",
    "sg:address":"4116 Tapestry Trail",
    "sg:city":"Mississauga",
    "sg:classifiers":[
        {
            "category":"Building & Trades",
            "subcategory":"Construction",
            "type":"Services"
        }
    ],
    "sg:phone":"+1 905 238 9156",
    "sg:postcode":"L4W 4B7",
    "sg:province":"ON",
    "sg:tags":[
        "general",
        "contractor"
    ],
    "wof:name":"Greendale General Contracting",
    "wof:placetype":"venue"
},
  "geometry": {"coordinates":[-79.5926742554,43.6365127563],"type":"Point"}
}