{
  "type": "Feature",
  "properties": {
    "addr:full":"416 Main St Vancouver BC V6A 2T4",
    "addr:housenumber":"416",
    "addr:postcode":"v6a 2t4",
    "addr:street":"Main St",
    "iso:country":"CA",
    "sg:address":"416 Main St",
    "sg:city":"Vancouver",
    "sg:classifiers":[
        {
            "category":"Restaurant",
            "type":"Food & Drink"
        }
    ],
    "sg:phone":"+1 604 683 7262",
    "sg:postcode":"V6A 2T4",
    "sg:province":"BC",
    "wof:name":"Marilyn Restaurant Ltd",
    "wof:placetype":"venue"
},
  "geometry": {"coordinates":[-123.099464,49.281147],"type":"Point"}
}