{
  "type": "Feature",
  "properties": {
    "iso:country":"CA",
    "sg:address":"1933 Regent St",
    "sg:city":"Sudbury",
    "sg:classifiers":[
        {
            "category":"Banks & Credit Unions",
            "subcategory":"Bank",
            "type":"Services"
        }
    ],
    "sg:phone":"+1 705 522 3866",
    "sg:postcode":"P3E 5R2",
    "sg:province":"ON",
    "wof:name":"Cibc",
    "wof:placetype":"venue"
},
  "geometry": {"coordinates":[-81.001572,46.450874],"type":"Point"}
}