{
  "type": "Feature",
  "properties": {
    "addr:full":"115 Brockelbank Cres Regina SK S4R 6J5",
    "addr:housenumber":"115",
    "addr:postcode":"s4r 6j5",
    "addr:street":"Brockelbank Cres",
    "iso:country":"CA",
    "sg:address":"115 Brockelbank Cres",
    "sg:city":"Regina",
    "sg:classifiers":[
        {
            "category":"Building & Trades",
            "subcategory":"Construction",
            "type":"Services"
        }
    ],
    "sg:phone":"+1 306 775 1578",
    "sg:postcode":"S4R 6J5",
    "sg:province":"SK",
    "sg:tags":[
        "bobcat",
        "general",
        "contractor"
    ],
    "wof:name":"Len-Rich Enterprises",
    "wof:placetype":"venue"
},
  "geometry": {"coordinates":[-104.63597869900001,50.4868621826],"type":"Point"}
}