{
  "type": "Feature",
  "properties": {
    "addr:full":"3776 Columbia Valley Rd Cultus Lake BC V2R 5A3",
    "addr:housenumber":"3776",
    "addr:postcode":"bc v2r 5a3",
    "addr:street":"Columbia Valley Rd",
    "iso:country":"CA",
    "sg:address":"3776 Columbia Valley Rd",
    "sg:city":"Cultus Lake",
    "sg:classifiers":[
        {
            "category":"Food & Beverages",
            "subcategory":"Groceries & Convenience Stores",
            "type":"Retail Goods"
        }
    ],
    "sg:phone":"+1 604 824 0067",
    "sg:postcode":"V2R 5A3",
    "sg:province":"BC",
    "sg:tags":[
        "grocer"
    ],
    "wof:name":"Cultus Lake Market",
    "wof:placetype":"venue"
},
  "geometry": {"coordinates":[-121.976364,49.074837],"type":"Point"}
}