{
  "type": "Feature",
  "properties": {
    "addr:full":"5208 52 Ave Drayton Valley AB T7A 1S9",
    "addr:housenumber":"5208",
    "addr:postcode":"t7a 1s9",
    "addr:street":"52 Ave",
    "iso:country":"CA",
    "sg:address":"5208 52 Ave",
    "sg:city":"Drayton Valley",
    "sg:classifiers":[
        {
            "category":"Professional",
            "subcategory":"Lawyer & Legal Services",
            "type":"Services"
        }
    ],
    "sg:phone":"+1 780 621 0123",
    "sg:postcode":"T7A 1S9",
    "sg:province":"AB",
    "sg:tags":[
        "attorney"
    ],
    "wof:name":"Reid Law Office",
    "wof:placetype":"venue"
},
  "geometry": {"coordinates":[-114.981049,53.224094],"type":"Point"}
}