{
  "type": "Feature",
  "properties": {
    "addr:full":"941 Clyde Ave Ottawa ON K1Z 5A6",
    "addr:housenumber":"941",
    "addr:postcode":"k1z 5a6",
    "addr:street":"Clyde Ave",
    "iso:country":"CA",
    "sg:address":"941 Clyde Ave",
    "sg:city":"Ottawa",
    "sg:classifiers":[
        {
            "category":"Government",
            "subcategory":"Office",
            "type":"Public Place"
        }
    ],
    "sg:phone":"+1 613 798 8246",
    "sg:postcode":"K1Z 5A6",
    "sg:province":"ON",
    "sg:tags":[
        "village"
    ],
    "wof:name":"Ottawa Arena",
    "wof:placetype":"venue"
},
  "geometry": {"coordinates":[-75.747322,45.374523],"type":"Point"}
}