{
  "type": "Feature",
  "properties": {
    "addr:full":"642 Barton St E Hamilton ON L8L 3A2",
    "addr:housenumber":"642",
    "addr:postcode":"l8l 3a2",
    "addr:street":"Barton St E",
    "iso:country":"CA",
    "sg:address":"642 Barton St E",
    "sg:city":"Hamilton",
    "sg:classifiers":[
        {
            "category":"Organizations",
            "subcategory":"Professional Association",
            "type":"Services"
        }
    ],
    "sg:phone":"+1 905 548 6166",
    "sg:postcode":"L8L 3A2",
    "sg:province":"ON",
    "sg:tags":[
        "club"
    ],
    "wof:name":"Associazione Nazionale Alpini",
    "wof:placetype":"venue"
},
  "geometry": {"coordinates":[-79.83783699999999,43.256832],"type":"Point"}
}