{
  "type": "Feature",
  "properties": {
    "iso:country":"CA",
    "sg:address":"632 Av Du Phare E",
    "sg:city":"Matane",
    "sg:classifiers":[
        {
            "category":"Travel",
            "subcategory":"Hotels & Motels",
            "type":"Entertainment"
        }
    ],
    "sg:phone":"+1 418 562 4030",
    "sg:postcode":"G4W 1B1",
    "sg:province":"QC",
    "wof:name":"Motel Le Campagnard",
    "wof:placetype":"venue"
},
  "geometry": {"coordinates":[-67.5068283081,48.8525276184],"type":"Point"}
}