{
  "type": "Feature",
  "properties": {
    "addr:full":"Toronto ON M6S 1M8",
    "addr:postcode":"m6s 1m8",
    "iso:country":"CA",
    "sg:city":"Toronto",
    "sg:classifiers":[
        {
            "category":"Health Services",
            "subcategory":"Health Practitioner",
            "type":"Services"
        }
    ],
    "sg:phone":"+1 416 604 9144",
    "sg:postcode":"M6S 1M8",
    "sg:province":"ON",
    "sg:tags":[
        "physician"
    ],
    "wof:name":"Alpha Naturopathic Clinic",
    "wof:placetype":"venue"
},
  "geometry": {"coordinates":[-79.47319,43.651951],"type":"Point"}
}