{
  "type": "Feature",
  "properties": {
    "addr:full":"11355 Tern Pl North Saanich BC V8L 5K6",
    "addr:housenumber":"11355",
    "addr:postcode":"v8l 5k6",
    "addr:street":"Tern Pl",
    "iso:country":"CA",
    "sg:address":"11355 Tern Pl",
    "sg:city":"North Saanich",
    "sg:classifiers":[
        {
            "category":"Professional",
            "subcategory":"Computer Services",
            "type":"Services"
        }
    ],
    "sg:phone":"+1 250 655 9383",
    "sg:postcode":"V8L 5K6",
    "sg:province":"BC",
    "sg:tags":[
        "repair",
        "internet"
    ],
    "wof:name":"Starting Point",
    "wof:placetype":"venue"
},
  "geometry": {"coordinates":[-123.437561,48.689743],"type":"Point"}
}