{
  "type": "Feature",
  "properties": {
    "addr:full":"170 Hwy 83 N Benito MB R0L 0C0",
    "addr:housenumber":"170",
    "addr:postcode":"r0l 0c0",
    "addr:street":"Hwy 83 N Benito",
    "iso:country":"CA",
    "sg:address":"170 Hwy 83 N",
    "sg:city":"Benito",
    "sg:classifiers":[
        {
            "category":"Manufacturing",
            "subcategory":"Tools & Machinery",
            "type":"Manufacturing & Wholesale Goods"
        }
    ],
    "sg:phone":"+1 204 539 2000",
    "sg:postcode":"R0L 0C0",
    "sg:province":"MB",
    "sg:tags":[
        "spraying",
        "equipment"
    ],
    "wof:name":"A G Shield Mfg",
    "wof:placetype":"venue"
},
  "geometry": {"coordinates":[-101.553398,51.91095],"type":"Point"}
}