{
  "type": "Feature",
  "properties": {
    "addr:full":"Winnipeg MB R3T 3L9",
    "addr:postcode":"r3t 3l9",
    "iso:country":"CA",
    "sg:city":"Winnipeg",
    "sg:classifiers":[
        {
            "category":"Health Services",
            "subcategory":"Doctor",
            "type":"Services"
        }
    ],
    "sg:phone":"+1 204 269 8060",
    "sg:postcode":"R3T 3L9",
    "sg:province":"MB",
    "sg:tags":[
        "dentist"
    ],
    "wof:name":"Bronstein, D DDS",
    "wof:placetype":"venue"
},
  "geometry": {"coordinates":[-97.1570358276,49.7887153625],"type":"Point"}
}