{
  "type": "Feature",
  "properties": {
    "addr:full":"Edmonton AB T5J 2Y9",
    "addr:postcode":"t5j 2y9",
    "iso:country":"CA",
    "sg:city":"Edmonton",
    "sg:classifiers":[
        {
            "category":"Personal",
            "type":"Services"
        }
    ],
    "sg:phone":"+1 780 425 4050",
    "sg:postcode":"T5J 2Y9",
    "sg:province":"AB",
    "sg:tags":[
        "clothing",
        "furnishing",
        "formal"
    ],
    "wof:name":"Tip Top Tailors",
    "wof:placetype":"venue"
},
  "geometry": {"coordinates":[-113.49343109100001,53.5435905457],"type":"Point"}
}