{
  "type": "Feature",
  "properties": {
    "addr:full":"1767 Dundas St E Mississauga ON L4X 1L5",
    "addr:housenumber":"1767",
    "addr:postcode":"l4x 1l5",
    "addr:street":"Dundas St E",
    "iso:country":"CA",
    "sg:address":"1767 Dundas St E",
    "sg:city":"Mississauga",
    "sg:classifiers":[
        {
            "category":"Travel",
            "subcategory":"Hotels & Motels",
            "type":"Entertainment"
        }
    ],
    "sg:phone":"+1 905 238 3400",
    "sg:postcode":"L4X 1L5",
    "sg:province":"ON",
    "wof:name":"Travelodge Toronto Southwest",
    "wof:placetype":"venue"
},
  "geometry": {"coordinates":[-79.574753,43.617931],"type":"Point"}
}