{
  "type": "Feature",
  "properties": {
    "addr:full":"4188 Scotsburn Rd Scotsburn NS B0K 1R0",
    "addr:housenumber":"4188",
    "addr:postcode":"b0k 1r0",
    "addr:street":"Scotsburn Rd",
    "iso:country":"CA",
    "sg:address":"4188 Scotsburn Rd",
    "sg:city":"Scotsburn",
    "sg:classifiers":[
        {
            "category":"Personal",
            "subcategory":"Beauty Salon",
            "type":"Services"
        }
    ],
    "sg:phone":"+1 902 485 4043",
    "sg:postcode":"B0K 1R0",
    "sg:province":"NS",
    "wof:name":"Scotsburn Hair Gallery",
    "wof:placetype":"venue"
},
  "geometry": {"coordinates":[-62.854424,45.651875],"type":"Point"}
}