{
  "type": "Feature",
  "properties": {
    "addr:full":"Okotoks AB T1S 1B5",
    "addr:postcode":"t1s 1b5",
    "iso:country":"CA",
    "sg:city":"Okotoks",
    "sg:classifiers":[
        {
            "category":"Shopping",
            "subcategory":"Florist",
            "type":"Retail Goods"
        }
    ],
    "sg:phone":"+1 403 938 4781",
    "sg:postcode":"T1S 1B5",
    "sg:province":"AB",
    "wof:name":"Okotoks Flowers & Things",
    "wof:placetype":"venue"
},
  "geometry": {"coordinates":[-113.97866821300001,50.7255516052],"type":"Point"}
}