{
  "type": "Feature",
  "properties": {
    "addr:full":"21 Arnold St Wallaceburg ON N8A 3P3",
    "addr:housenumber":"21",
    "addr:postcode":"n8a 3p3",
    "addr:street":"Arnold St",
    "iso:country":"CA",
    "sg:address":"21 Arnold St",
    "sg:city":"Wallaceburg",
    "sg:classifiers":[
        {
            "category":"Government",
            "subcategory":"Office",
            "type":"Public Place"
        }
    ],
    "sg:phone":"+1 519 627 2881",
    "sg:postcode":"N8A 3P3",
    "sg:province":"ON",
    "wof:name":"Ontario Driver & Vehicle",
    "wof:placetype":"venue"
},
  "geometry": {"coordinates":[-82.400093,42.592091],"type":"Point"}
}