{
  "type": "Feature",
  "properties": {
    "iso:country":"CA",
    "sg:address":"394 Selkirk Ave",
    "sg:city":"Winnipeg",
    "sg:classifiers":[
        {
            "category":"Organizations",
            "subcategory":"Professional Association",
            "type":"Services"
        }
    ],
    "sg:phone":"+1 204 589 7347",
    "sg:postcode":"R2W 2M2",
    "sg:province":"MB",
    "wof:name":"North End Women's Ctr",
    "wof:placetype":"venue"
},
  "geometry": {"coordinates":[-97.14046478269999,49.9140815735],"type":"Point"}
}