{
  "type": "Feature",
  "properties": {
    "addr:full":"Lloydminster AB T9V 2G3",
    "addr:postcode":"t9v 2g3",
    "iso:country":"CA",
    "sg:city":"Lloydminster",
    "sg:classifiers":[
        {
            "category":"Building & Trades",
            "subcategory":"Construction",
            "type":"Services"
        }
    ],
    "sg:phone":"+1 780 875 1352",
    "sg:postcode":"T9V 2G3",
    "sg:province":"AB",
    "sg:tags":[
        "maker",
        "cabinet"
    ],
    "wof:name":"T & L Custom Cabinets",
    "wof:placetype":"venue"
},
  "geometry": {"coordinates":[-110.033790588,53.2807350159],"type":"Point"}
}