{
  "type": "Feature",
  "properties": {
    "iso:country":"CA",
    "sg:city":"Richmond",
    "sg:classifiers":[
        {
            "category":"Food & Beverages",
            "subcategory":"Groceries & Convenience Stores",
            "type":"Retail Goods"
        }
    ],
    "sg:phone":"+1 604 273 9877",
    "sg:postcode":"V6X 1A7",
    "sg:province":"BC",
    "sg:tags":[
        "grocer"
    ],
    "wof:name":"Grand Value Asian Supermarket",
    "wof:placetype":"venue"
},
  "geometry": {"coordinates":[-123.133034,49.17033],"type":"Point"}
}