{
  "type": "Feature",
  "properties": {
    "addr:full":"6405 Av DE Westbury Montreal QC H3W 2X5",
    "addr:housenumber":"6405",
    "addr:postcode":"h3w 2x5",
    "addr:street":"Av De Westbury",
    "iso:country":"CA",
    "sg:address":"6405 Av DE Westbury",
    "sg:city":"Montreal",
    "sg:classifiers":[
        {
            "category":"Organizations",
            "subcategory":"Religious Organization",
            "type":"Services"
        }
    ],
    "sg:phone":"+1 514 734 7700",
    "sg:postcode":"H3W 2X5",
    "sg:province":"QC",
    "sg:tags":[
        "synagogue"
    ],
    "wof:name":"Congregation Lubavitch",
    "wof:placetype":"venue"
},
  "geometry": {"coordinates":[-73.64273799999999,45.492546],"type":"Point"}
}