{
  "type": "Feature",
  "properties": {
    "addr:full":"1 Felcher Blvd Stouffville ON L4A 7X4",
    "addr:housenumber":"1",
    "addr:postcode":"l4a 7x4",
    "addr:street":"Felcher Blvd",
    "iso:country":"CA",
    "sg:address":"1 Felcher Blvd",
    "sg:city":"Stouffville",
    "sg:classifiers":[
        {
            "category":"Food & Beverages",
            "subcategory":"Bakery",
            "type":"Retail Goods"
        }
    ],
    "sg:phone":"+1 905 642 7447",
    "sg:postcode":"L4A 7X4",
    "sg:province":"ON",
    "sg:tags":[
        "doughnut"
    ],
    "wof:name":"Coffee Master Donuts & Deli",
    "wof:placetype":"venue"
},
  "geometry": {"coordinates":[-79.2966003418,44.0333633423],"type":"Point"}
}