{
  "type": "Feature",
  "properties": {
    "iso:country":"CA",
    "sg:city":"Saint-Thomas",
    "sg:phone":"+1 450 759 2242",
    "sg:postcode":"J0K 3L0",
    "sg:province":"QC",
    "sg:tags":[
        "oil"
    ],
    "wof:name":"Harnois Petroles",
    "wof:placetype":"venue"
},
  "geometry": {"coordinates":[-73.3422698975,46.0173950195],"type":"Point"}
}