{
  "type": "Feature",
  "properties": {
    "addr:full":"1644 Hillside Ave # 24 Victoria BC V8T 2C5",
    "addr:housenumber":"1644;24",
    "addr:postcode":"v8t 2c5",
    "addr:street":"Hillside Ave #",
    "iso:country":"CA",
    "sg:address":"1644 Hillside Ave # 24",
    "sg:city":"Victoria",
    "sg:classifiers":[
        {
            "category":"Health Services",
            "subcategory":"Optometrist",
            "type":"Services"
        }
    ],
    "sg:phone":"+1 250 592 0684",
    "sg:postcode":"V8T 2C5",
    "sg:province":"BC",
    "wof:name":"Krawciw, Mary Jean OD",
    "wof:placetype":"venue"
},
  "geometry": {"coordinates":[-123.334480286,48.445350647],"type":"Point"}
}