{
  "type": "Feature",
  "properties": {
    "iso:country":"CA",
    "sg:address":"2 Industrial Rd",
    "sg:city":"Kemptville",
    "sg:classifiers":[
        {
            "category":"Farming",
            "subcategory":"Farm & Veterinary Services",
            "type":"Manufacturing & Wholesale Goods"
        }
    ],
    "sg:phone":"+1 613 258 3800",
    "sg:postcode":"K0G 1J0",
    "sg:province":"ON",
    "sg:tags":[
        "insemination"
    ],
    "wof:name":"Select Sires Canada Inc",
    "wof:placetype":"venue"
},
  "geometry": {"coordinates":[-75.645614624,45.0159187317],"type":"Point"}
}