{
  "type": "Feature",
  "properties": {
    "addr:full":"Vancouver BC V6J 4Z6",
    "addr:postcode":"v6j 4z6",
    "iso:country":"CA",
    "sg:city":"Vancouver",
    "sg:classifiers":[
        {
            "category":"Real Estate",
            "subcategory":"Real Estate Agent",
            "type":"Services"
        }
    ],
    "sg:phone":"+1 604 736 6761",
    "sg:postcode":"V6J 4Z6",
    "sg:province":"BC",
    "wof:name":"Gammon International Rl Est",
    "wof:placetype":"venue"
},
  "geometry": {"coordinates":[-123.138710022,49.2637023926],"type":"Point"}
}