{
  "type": "Feature",
  "properties": {
    "addr:full":"120 Grove Rd Enderby BC V0E 1V3",
    "addr:housenumber":"120",
    "addr:postcode":"v0e 1v3",
    "addr:street":"Grove Rd",
    "iso:country":"CA",
    "sg:address":"120 Grove Rd",
    "sg:city":"Enderby",
    "sg:classifiers":[
        {
            "category":"Wholesale",
            "subcategory":"Construction Materials",
            "type":"Manufacturing & Wholesale Goods"
        }
    ],
    "sg:phone":"+1 250 832 8907",
    "sg:postcode":"V0E 1V3",
    "sg:province":"BC",
    "sg:tags":[
        "fence"
    ],
    "wof:name":"Good Neighbour Fencing",
    "wof:placetype":"venue"
},
  "geometry": {"coordinates":[-119.14015999999999,50.550701],"type":"Point"}
}