{
  "type": "Feature",
  "properties": {
    "addr:full":"1749 Argyle St Halifax NS B3J 3K4",
    "addr:housenumber":"1749",
    "addr:postcode":"ns b3j 3k4",
    "addr:street":"Argyle St",
    "iso:country":"CA",
    "sg:address":"1749 Argyle St",
    "sg:city":"Halifax",
    "sg:classifiers":[
        {
            "category":"Organizations",
            "subcategory":"Religious Organization",
            "type":"Services"
        }
    ],
    "sg:phone":"+1 902 429 2240",
    "sg:postcode":"B3J 3K4",
    "sg:province":"NS",
    "sg:tags":[
        "church"
    ],
    "wof:name":"St Paul's Anglican Church",
    "wof:placetype":"venue"
},
  "geometry": {"coordinates":[-63.574867,44.647598],"type":"Point"}
}