{
  "type": "Feature",
  "properties": {
    "addr:full":"St Catharines ON L2R 7G1",
    "addr:postcode":"l2r 7g1",
    "iso:country":"CA",
    "sg:city":"St Catharines",
    "sg:classifiers":[
        {
            "category":"Professional",
            "subcategory":"Engineering",
            "type":"Services"
        }
    ],
    "sg:phone":"+1 905 984 8383",
    "sg:postcode":"L2R 7G1",
    "sg:province":"ON",
    "sg:tags":[
        "engineer"
    ],
    "wof:name":"Gryphon International Engrng",
    "wof:placetype":"venue"
},
  "geometry": {"coordinates":[-79.24597930909999,43.1583557129],"type":"Point"}
}