{
  "type": "Feature",
  "properties": {
    "addr:full":"16 Harbour View Ave St. John's NL A1A 5C9",
    "addr:housenumber":"16",
    "addr:postcode":"a1a 5c9",
    "addr:street":"Harbour View Ave",
    "iso:country":"CA",
    "sg:address":"16 Harbour View Ave",
    "sg:city":"St. John's",
    "sg:classifiers":[
        {
            "category":"Retail",
            "subcategory":"Auto Repair",
            "type":"Services"
        }
    ],
    "sg:phone":"+1 709 753 7373",
    "sg:postcode":"A1A 5C9",
    "sg:province":"NL",
    "sg:tags":[
        "automobile",
        "rustproofing",
        "undercoating"
    ],
    "wof:name":"Rust Check Ctr",
    "wof:placetype":"venue"
},
  "geometry": {"coordinates":[-52.7215805054,47.6072845459],"type":"Point"}
}