{
  "type": "Feature",
  "properties": {
    "addr:full":"2220 Wilgress Rd Nanaimo BC V9S 4N4",
    "addr:housenumber":"2220",
    "addr:postcode":"v9s 4n4",
    "addr:street":"Wilgress Rd",
    "iso:country":"CA",
    "sg:address":"2220 Wilgress Rd",
    "sg:city":"Nanaimo",
    "sg:classifiers":[
        {
            "category":"Wholesale",
            "subcategory":"Construction Materials",
            "type":"Manufacturing & Wholesale Goods"
        }
    ],
    "sg:phone":"+1 250 390 5162",
    "sg:postcode":"V9S 4N4",
    "sg:province":"BC",
    "sg:tags":[
        "building",
        "water",
        "works",
        "equipment",
        "supply"
    ],
    "wof:name":"Westburne Wolseley Plumbing",
    "wof:placetype":"venue"
},
  "geometry": {"coordinates":[-123.976593018,49.1928367615],"type":"Point"}
}