{
  "type": "Feature",
  "properties": {
    "addr:full":"Concord ON L4K 1L7",
    "addr:postcode":"l4k 1l7",
    "iso:country":"CA",
    "sg:city":"Concord",
    "sg:classifiers":[
        {
            "category":"Manufacturing",
            "subcategory":"Chemicals & Compounds",
            "type":"Manufacturing & Wholesale Goods"
        }
    ],
    "sg:phone":"+1 905 760 1964",
    "sg:postcode":"L4K 1L7",
    "sg:province":"ON",
    "sg:tags":[
        "cleaning"
    ],
    "wof:name":"Allspar Solutions Inc",
    "wof:placetype":"venue"
},
  "geometry": {"coordinates":[-79.48848724370001,43.8191413879],"type":"Point"}
}