{
  "type": "Feature",
  "properties": {
    "addr:full":"5320 Av Crowley Montreal QC H4A 2C5",
    "addr:housenumber":"5320",
    "addr:postcode":"h4a 2c5",
    "addr:street":"Av Crowley",
    "iso:country":"CA",
    "sg:address":"5320 Av Crowley",
    "sg:city":"Montreal",
    "sg:classifiers":[
        {
            "category":"Retail",
            "subcategory":"Auto Repair",
            "type":"Services"
        }
    ],
    "sg:phone":"+1 514 482 1636",
    "sg:postcode":"H4A 2C5",
    "sg:province":"QC",
    "sg:tags":[
        "repairing",
        "automobile"
    ],
    "wof:name":"Clinique D'Auto Bavaroise Inc",
    "wof:placetype":"venue"
},
  "geometry": {"coordinates":[-73.604263,45.471989],"type":"Point"}
}