{
  "type": "Feature",
  "properties": {
    "addr:full":"2397 West Railway St Abbotsford BC V2S 2E3",
    "addr:housenumber":"2397",
    "addr:postcode":"v2s 2e3",
    "addr:street":"West Railway St",
    "iso:country":"CA",
    "sg:address":"2397 West Railway St",
    "sg:city":"Abbotsford",
    "sg:classifiers":[
        {
            "category":"Autos & Motor Vehicles",
            "subcategory":"Automobile Sales",
            "type":"Retail Goods"
        }
    ],
    "sg:phone":"+1 604 853 4744",
    "sg:postcode":"V2S 2E3",
    "sg:province":"BC",
    "sg:tags":[
        "car",
        "dealer"
    ],
    "wof:name":"Douglas Country Motors Ltd",
    "wof:placetype":"venue"
},
  "geometry": {"coordinates":[-122.284713745,49.0451164246],"type":"Point"}
}