{
  "type": "Feature",
  "properties": {
    "addr:full":"256 Augusta Ave Toronto ON M5T 2L9",
    "addr:housenumber":"256",
    "addr:postcode":"m5t 2l9",
    "addr:street":"Augusta Ave",
    "iso:country":"CA",
    "sg:address":"256 Augusta Ave",
    "sg:city":"Toronto",
    "sg:classifiers":[
        {
            "category":"Restaurant",
            "type":"Food & Drink"
        }
    ],
    "sg:phone":"+1 416 929 4900",
    "sg:postcode":"M5T 2L9",
    "sg:province":"ON",
    "wof:name":"Palette",
    "wof:placetype":"venue"
},
  "geometry": {"coordinates":[-79.4028549194,43.6562042236],"type":"Point"}
}