{
  "type": "Feature",
  "properties": {
    "addr:full":"66 Rue Gamble O Rouyn-Noranda QC J9X 2R4",
    "addr:housenumber":"66",
    "addr:postcode":"j9x 2r4",
    "addr:street":"Rue Gamble O",
    "iso:country":"CA",
    "sg:address":"66 Rue Gamble O",
    "sg:city":"Rouyn-Noranda",
    "sg:classifiers":[
        {
            "category":"Personal",
            "subcategory":"Beauty Salon",
            "type":"Services"
        }
    ],
    "sg:phone":"+1 819 762 8630",
    "sg:postcode":"J9X 2R4",
    "sg:province":"QC",
    "wof:name":"Coiffures Dernier Cri",
    "wof:placetype":"venue"
},
  "geometry": {"coordinates":[-79.018867,48.239803],"type":"Point"}
}