{
  "type": "Feature",
  "properties": {
    "iso:country":"CA",
    "sg:address":"555 Rexdale Blvd",
    "sg:city":"Etobicoke",
    "sg:classifiers":[
        {
            "category":"Recreation",
            "type":"Entertainment"
        }
    ],
    "sg:phone":"+1 416 674 3008",
    "sg:postcode":"M9W 7G3",
    "sg:province":"ON",
    "sg:tags":[
        "stable"
    ],
    "wof:name":"Ralph Biamonte Stables",
    "wof:placetype":"venue"
},
  "geometry": {"coordinates":[-79.6031951904,43.7189025879],"type":"Point"}
}