{
  "type": "Feature",
  "properties": {
    "addr:full":"8344 Rue Saint-Denis Montreal QC H2P 2G8",
    "addr:housenumber":"8344",
    "addr:postcode":"h2p 2g8",
    "addr:street":"Rue Saint-Denis",
    "iso:country":"CA",
    "sg:address":"8344 Rue Saint-Denis",
    "sg:city":"Montreal",
    "sg:classifiers":[
        {
            "category":"Health Services",
            "subcategory":"Doctor",
            "type":"Services"
        }
    ],
    "sg:phone":"+1 514 383 4867",
    "sg:postcode":"H2P 2G8",
    "sg:province":"QC",
    "sg:tags":[
        "dentist"
    ],
    "wof:name":"Malka, Charles DDS",
    "wof:placetype":"venue"
},
  "geometry": {"coordinates":[-73.633247,45.543625],"type":"Point"}
}