{
  "type": "Feature",
  "properties": {
    "addr:full":"620 1st St Cochrane AB T4C 1B8",
    "addr:housenumber":"620",
    "addr:postcode":"t4c 1b8",
    "addr:street":"1St St",
    "iso:country":"CA",
    "sg:address":"620 1st St",
    "sg:city":"Cochrane",
    "sg:classifiers":[
        {
            "category":"Retail",
            "subcategory":"Car Wash",
            "type":"Services"
        }
    ],
    "sg:phone":"+1 403 932 4417",
    "sg:postcode":"T4C 1B8",
    "sg:province":"AB",
    "sg:tags":[
        "polishing",
        "washing"
    ],
    "wof:name":"Mountain-View Car & Truck Wash",
    "wof:placetype":"venue"
},
  "geometry": {"coordinates":[-114.454155,51.185951],"type":"Point"}
}