{
  "type": "Feature",
  "properties": {
    "addr:full":"43 Rue Turcotte Saint-Quentin NB E8A 2A8",
    "addr:housenumber":"43",
    "addr:postcode":"e8a 2a8",
    "addr:street":"Rue Turcotte",
    "iso:country":"CA",
    "sg:address":"43 Rue Turcotte",
    "sg:city":"Saint-Quentin",
    "sg:classifiers":[
        {
            "category":"Building & Trades",
            "subcategory":"Construction",
            "type":"Services"
        }
    ],
    "sg:phone":"+1 506 235 3439",
    "sg:postcode":"E8A 2A8",
    "sg:province":"NB",
    "sg:tags":[
        "excavating",
        "contractor"
    ],
    "wof:name":"Denis Banville Excavation",
    "wof:placetype":"venue"
},
  "geometry": {"coordinates":[-67.386292,47.519287],"type":"Point"}
}