{
  "type": "Feature",
  "properties": {
    "addr:full":"Kelowna BC V1Y 6G4",
    "addr:postcode":"v1y 6g4",
    "iso:country":"CA",
    "sg:city":"Kelowna",
    "sg:classifiers":[
        {
            "category":"Retail",
            "subcategory":"Auto Repair",
            "type":"Services"
        }
    ],
    "sg:phone":"+1 250 868 3533",
    "sg:postcode":"V1Y 6G4",
    "sg:province":"BC",
    "sg:tags":[
        "repairing",
        "automobile"
    ],
    "wof:name":"Rpm Automotive Ltd",
    "wof:placetype":"venue"
},
  "geometry": {"coordinates":[-119.457741,49.881828],"type":"Point"}
}