{
  "type": "Feature",
  "properties": {
    "addr:full":"2 Cullotta Dr Waterdown ON L0R 2H6",
    "addr:housenumber":"2",
    "addr:postcode":"l0r 2h6",
    "addr:street":"Cullotta Dr",
    "iso:country":"CA",
    "sg:address":"2 Cullotta Dr",
    "sg:city":"Waterdown",
    "sg:classifiers":[
        {
            "category":"Building & Trades",
            "subcategory":"Construction",
            "type":"Services"
        }
    ],
    "sg:phone":"+1 905 689 3957",
    "sg:postcode":"L0R 2H6",
    "sg:province":"ON",
    "sg:tags":[
        "roofing",
        "contractor"
    ],
    "wof:name":"Main Street Roofing",
    "wof:placetype":"venue"
},
  "geometry": {"coordinates":[-79.902671814,43.3275756836],"type":"Point"}
}