{
  "type": "Feature",
  "properties": {
    "addr:full":"244 Airdrie Rd East York ON M4G 1N1",
    "addr:housenumber":"244",
    "addr:postcode":"m4g 1n1",
    "addr:street":"Airdrie Rd",
    "iso:country":"CA",
    "sg:address":"244 Airdrie Rd",
    "sg:city":"East York",
    "sg:classifiers":[
        {
            "category":"Professional",
            "subcategory":"Management & Consulting",
            "type":"Services"
        }
    ],
    "sg:phone":"+1 416 423 4897",
    "sg:postcode":"M4G 1N1",
    "sg:province":"ON",
    "sg:tags":[
        "consultant",
        "business"
    ],
    "wof:name":"Berkeley Developmental",
    "wof:placetype":"venue"
},
  "geometry": {"coordinates":[-79.3661193848,43.706615448],"type":"Point"}
}