{
  "type": "Feature",
  "properties": {
    "addr:full":"Saint-Amable QC J0L 1N0",
    "addr:postcode":"j0l 1n0",
    "iso:country":"CA",
    "sg:city":"Saint-Amable",
    "sg:classifiers":[
        {
            "category":"Retail",
            "subcategory":"Auto Repair",
            "type":"Services"
        }
    ],
    "sg:phone":"+1 450 649 0997",
    "sg:postcode":"J0L 1N0",
    "sg:province":"QC",
    "sg:tags":[
        "truck"
    ],
    "wof:name":"Garage Guy Gemme Enr",
    "wof:placetype":"venue"
},
  "geometry": {"coordinates":[-73.3081893921,45.6430511475],"type":"Point"}
}