{
  "type": "Feature",
  "properties": {
    "addr:full":"PO Box 298 Falher AB T0H 1M0",
    "addr:housenumber":"po",
    "addr:postcode":"t0h 1m0",
    "addr:street":"Box 298",
    "iso:country":"CA",
    "sg:address":"PO Box 298",
    "sg:city":"Falher",
    "sg:classifiers":[
        {
            "category":"Organizations",
            "subcategory":"Religious Organization",
            "type":"Services"
        }
    ],
    "sg:phone":"+1 403 837 2151",
    "sg:postcode":"T0H 1M0",
    "sg:province":"AB",
    "sg:tags":[
        "church"
    ],
    "wof:name":"St Anne Catholic Church",
    "wof:placetype":"venue"
},
  "geometry": {"coordinates":[-117.201897,55.741131],"type":"Point"}
}