{
  "type": "Feature",
  "properties": {
    "iso:country":"CA",
    "sg:address":"84 Boul Harwood",
    "sg:city":"Vaudreuil-Dorion",
    "sg:classifiers":[
        {
            "category":"Utilities",
            "subcategory":"Mobile Phone",
            "type":"Services"
        }
    ],
    "sg:phone":"+1 450 424 1416",
    "sg:postcode":"J7V 1X8",
    "sg:province":"QC",
    "sg:tags":[
        "telephone",
        "cellular"
    ],
    "wof:name":"Boutique Electronique",
    "wof:placetype":"venue"
},
  "geometry": {"coordinates":[-74.0088272095,45.3844337463],"type":"Point"}
}