{
  "type": "Feature",
  "properties": {
    "addr:full":"27 Rue DE L'Eglise Evain QC J0Z 1Y0",
    "addr:housenumber":"27",
    "addr:postcode":"j0z 1y0",
    "addr:street":"Rue De L'Eglise Evain",
    "iso:country":"CA",
    "sg:address":"27 Rue DE L'Eglise",
    "sg:city":"Evain",
    "sg:classifiers":[
        {
            "category":"Organizations",
            "subcategory":"Religious Organization",
            "type":"Services"
        }
    ],
    "sg:phone":"+1 819 768 3121",
    "sg:postcode":"J0Z 1Y0",
    "sg:province":"QC",
    "sg:tags":[
        "church"
    ],
    "wof:name":"Presbytere DE St-Bernard",
    "wof:placetype":"venue"
},
  "geometry": {"coordinates":[-79.230698,48.322769],"type":"Point"}
}