{
  "type": "Feature",
  "properties": {
    "addr:full":"Ingonish Beach NS B0C 1L0",
    "addr:postcode":"b0c 1l0",
    "iso:country":"CA",
    "sg:city":"Ingonish Beach",
    "sg:classifiers":[
        {
            "category":"Travel",
            "subcategory":"Hotels & Motels",
            "type":"Entertainment"
        }
    ],
    "sg:phone":"+1 902 285 2008",
    "sg:postcode":"B0C 1L0",
    "sg:province":"NS",
    "wof:name":"Ingonish Chalets",
    "wof:placetype":"venue"
},
  "geometry": {"coordinates":[-60.401299,46.647141],"type":"Point"}
}