{
  "type": "Feature",
  "properties": {
    "addr:full":"Toronto ON M4K 1P6",
    "addr:postcode":"m4k 1p6",
    "iso:country":"CA",
    "sg:city":"Toronto",
    "sg:classifiers":[
        {
            "category":"Professional",
            "subcategory":"Accounting & Tax Preparation",
            "type":"Services"
        }
    ],
    "sg:phone":"+1 416 465 1773",
    "sg:postcode":"M4K 1P6",
    "sg:province":"ON",
    "sg:tags":[
        "accountant"
    ],
    "wof:name":"Accountants Exchange",
    "wof:placetype":"venue"
},
  "geometry": {"coordinates":[-79.3491821289,43.6782035828],"type":"Point"}
}