{
  "type": "Feature",
  "properties": {
    "iso:country":"CA",
    "sg:address":"Main St",
    "sg:city":"Lark Harbour",
    "sg:classifiers":[
        {
            "category":"Organizations",
            "subcategory":"Religious Organization",
            "type":"Services"
        }
    ],
    "sg:phone":"+1 709 681 2505",
    "sg:postcode":"A0L 1H0",
    "sg:province":"NL",
    "sg:tags":[
        "church"
    ],
    "wof:name":"St James Church",
    "wof:placetype":"venue"
},
  "geometry": {"coordinates":[-58.384705,49.100739],"type":"Point"}
}