{
  "type": "Feature",
  "properties": {
    "iso:country":"CA",
    "sg:address":"95 St. Peters Rd",
    "sg:city":"Charlottetown",
    "sg:classifiers":[
        {
            "category":"Retail",
            "subcategory":"Car Wash",
            "type":"Services"
        }
    ],
    "sg:phone":"+1 902 566 4980",
    "sg:postcode":"C1A 5N9",
    "sg:province":"PE",
    "sg:tags":[
        "automobile",
        "detail",
        "clean"
    ],
    "wof:name":"Shine Depot",
    "wof:placetype":"venue"
},
  "geometry": {"coordinates":[-63.1216697693,46.2521896362],"type":"Point"}
}