{
  "type": "Feature",
  "properties": {
    "addr:full":"St Laurent MB R0C 2S0",
    "addr:postcode":"r0c 2s0",
    "iso:country":"CA",
    "sg:city":"St Laurent",
    "sg:classifiers":[
        {
            "category":"Recreation",
            "type":"Entertainment"
        }
    ],
    "sg:phone":"+1 204 646 2253",
    "sg:postcode":"R0C 2S0",
    "sg:province":"MB",
    "sg:tags":[
        "center"
    ],
    "wof:name":"St Laurent Bowling Alley",
    "wof:placetype":"venue"
},
  "geometry": {"coordinates":[-96.88893899999999,50.143654],"type":"Point"}
}