{
  "type": "Feature",
  "properties": {
    "addr:full":"150 Rue Villeray Montreal QC H2R 1G3",
    "addr:housenumber":"150",
    "addr:postcode":"h2r 1g3",
    "addr:street":"Rue Villeray",
    "iso:country":"CA",
    "sg:address":"150 Rue Villeray",
    "sg:city":"Montreal",
    "sg:classifiers":[
        {
            "category":"Restaurant",
            "type":"Food & Drink"
        }
    ],
    "sg:phone":"+1 514 274 3430",
    "sg:postcode":"H2R 1G3",
    "sg:province":"QC",
    "sg:tags":[
        "shop",
        "delicatessen",
        "coffee"
    ],
    "wof:name":"Cafe Charcuterie Villeray",
    "wof:placetype":"venue"
},
  "geometry": {"coordinates":[-73.62404600000001,45.538574],"type":"Point"}
}