{
  "type": "Feature",
  "properties": {
    "iso:country":"CA",
    "sg:address":"45861 Wellington Ave",
    "sg:city":"Chilliwack",
    "sg:classifiers":[
        {
            "category":"Restaurant",
            "type":"Food & Drink"
        }
    ],
    "sg:phone":"+1 604 792 8198",
    "sg:postcode":"V2P 2C8",
    "sg:province":"BC",
    "wof:name":"E Yong Oriental Restaurant",
    "wof:placetype":"venue"
},
  "geometry": {"coordinates":[-121.955421448,49.1720046997],"type":"Point"}
}