{
  "type": "Feature",
  "properties": {
    "addr:full":"37 Rue Perreault O Rouyn-Noranda QC J9X 2T3",
    "addr:housenumber":"37",
    "addr:postcode":"j9x 2t3",
    "addr:street":"Rue Perreault O",
    "iso:country":"CA",
    "sg:address":"37 Rue Perreault O",
    "sg:city":"Rouyn-Noranda",
    "sg:classifiers":[
        {
            "category":"Professional",
            "subcategory":"Accounting & Tax Preparation",
            "type":"Services"
        }
    ],
    "sg:phone":"+1 819 762 1220",
    "sg:postcode":"J9X 2T3",
    "sg:province":"QC",
    "sg:tags":[
        "return",
        "filing"
    ],
    "wof:name":"E & S Lyssan",
    "wof:placetype":"venue"
},
  "geometry": {"coordinates":[-79.01890563960001,48.2383651733],"type":"Point"}
}