{
  "type": "Feature",
  "properties": {
    "iso:country":"CA",
    "sg:address":"44 Trans Canada Hwy",
    "sg:city":"Deer Lake",
    "sg:classifiers":[
        {
            "category":"Professional",
            "subcategory":"Management & Consulting",
            "type":"Services"
        }
    ],
    "sg:phone":"+1 709 635 3861",
    "sg:postcode":"A8A 2E4",
    "sg:province":"NL",
    "sg:tags":[
        "development",
        "economic",
        "agency"
    ],
    "wof:name":"Grand Lake Ctr Economic Dev",
    "wof:placetype":"venue"
},
  "geometry": {"coordinates":[-57.4311180115,49.1848869324],"type":"Point"}
}