{
  "type": "Feature",
  "properties": {
    "iso:country":"CA",
    "sg:address":"4702 31 St",
    "sg:city":"Vernon",
    "sg:classifiers":[
        {
            "category":"Autos & Motor Vehicles",
            "subcategory":"Automobile Sales",
            "type":"Retail Goods"
        }
    ],
    "sg:phone":"+1 250 549 1227",
    "sg:postcode":"V1T 5J9",
    "sg:province":"BC",
    "sg:tags":[
        "body",
        "car"
    ],
    "wof:name":"G S Lee Motors Ltd",
    "wof:placetype":"venue"
},
  "geometry": {"coordinates":[-119.271148682,50.2807922363],"type":"Point"}
}