{
  "type": "Feature",
  "properties": {
    "addr:full":"Princeton BC V0X 1W0",
    "addr:postcode":"v0x 1w0",
    "iso:country":"CA",
    "sg:city":"Princeton",
    "sg:classifiers":[
        {
            "category":"Real Estate",
            "subcategory":"Real Estate Operator",
            "type":"Services"
        }
    ],
    "sg:phone":"+1 250 295 3532",
    "sg:postcode":"V0X 1W0",
    "sg:province":"BC",
    "sg:tags":[
        "mobile",
        "home",
        "community"
    ],
    "wof:name":"Pines Mobile Home Park",
    "wof:placetype":"venue"
},
  "geometry": {"coordinates":[-120.505897522,49.4586753845],"type":"Point"}
}