{
  "type": "Feature",
  "properties": {
    "addr:full":"1746 Forest Park Dr North Saanich BC V8L 3Z7",
    "addr:housenumber":"1746",
    "addr:postcode":"v8l 3z7",
    "addr:street":"Forest Park Dr",
    "iso:country":"CA",
    "sg:address":"1746 Forest Park Dr",
    "sg:city":"North Saanich",
    "sg:classifiers":[
        {
            "category":"Building & Trades",
            "subcategory":"Construction",
            "type":"Services"
        }
    ],
    "sg:phone":"+1 250 656 4529",
    "sg:postcode":"V8L 3Z7",
    "sg:province":"BC",
    "sg:tags":[
        "builder",
        "deck"
    ],
    "wof:name":"Evans Enterprises",
    "wof:placetype":"venue"
},
  "geometry": {"coordinates":[-123.425842,48.625851],"type":"Point"}
}