{
  "type": "Feature",
  "properties": {
    "addr:full":"8949 Wellington Rd 50 RR 2 Acton ON L7J 2L8",
    "addr:housenumber":"8949;50",
    "addr:postcode":"l7j 2l8",
    "addr:street":"Wellington Rd;Rr 2",
    "iso:country":"CA",
    "sg:address":"8949 Wellington Rd 50 RR 2",
    "sg:city":"Acton",
    "sg:classifiers":[
        {
            "category":"Manufacturing",
            "subcategory":"Glass & Minerals",
            "type":"Manufacturing & Wholesale Goods"
        }
    ],
    "sg:phone":"+1 519 853 1529",
    "sg:postcode":"L7J 2L8",
    "sg:province":"ON",
    "sg:tags":[
        "concrete",
        "brick",
        "prod",
        "block"
    ],
    "wof:name":"Acton Precast Concrete Ltd",
    "wof:placetype":"venue"
},
  "geometry": {"coordinates":[-80.040329,43.630733],"type":"Point"}
}