{
  "type": "Feature",
  "properties": {
    "iso:country":"CA",
    "sg:address":"384 Hillside Ave",
    "sg:city":"Oshawa",
    "sg:classifiers":[
        {
            "category":"Organizations",
            "subcategory":"Religious Organization",
            "type":"Services"
        }
    ],
    "sg:phone":"+1 905 576 1706",
    "sg:postcode":"L1J 6L7",
    "sg:province":"ON",
    "sg:tags":[
        "church"
    ],
    "wof:name":"Paroisse Assomption Notre Dame",
    "wof:placetype":"venue"
},
  "geometry": {"coordinates":[-78.8714828491,43.8813743591],"type":"Point"}
}