{
  "type": "Feature",
  "properties": {
    "addr:full":"1020 Government St Victoria BC V8W 1X7",
    "addr:housenumber":"1020",
    "addr:postcode":"v8w 1x7",
    "addr:street":"Government St",
    "iso:country":"CA",
    "sg:address":"1020 Government St",
    "sg:city":"Victoria",
    "sg:classifiers":[
        {
            "category":"Shopping",
            "subcategory":"Gifts & Souvenirs",
            "type":"Retail Goods"
        }
    ],
    "sg:phone":"+1 250 382 8578",
    "sg:postcode":"V8W 1X7",
    "sg:province":"BC",
    "sg:tags":[
        "shop"
    ],
    "wof:name":"Seeing Is Believing",
    "wof:placetype":"venue"
},
  "geometry": {"coordinates":[-123.368225098,48.4244117737],"type":"Point"}
}