{
  "type": "Feature",
  "properties": {
    "addr:full":"3215 North Service Rd Burlington ON L7N 3G2",
    "addr:housenumber":"3215",
    "addr:postcode":"l7n 3g2",
    "addr:street":"North Service Rd",
    "iso:country":"CA",
    "sg:address":"3215 North Service Rd",
    "sg:city":"Burlington",
    "sg:classifiers":[
        {
            "category":"Professional",
            "subcategory":"Engineering",
            "type":"Services"
        }
    ],
    "sg:phone":"+1 905 335 2353",
    "sg:postcode":"L7N 3G2",
    "sg:province":"ON",
    "sg:tags":[
        "engineer"
    ],
    "wof:name":"Phillips Engineering Ltd",
    "wof:placetype":"venue"
},
  "geometry": {"coordinates":[-79.7970046997,43.3590545654],"type":"Point"}
}