{
  "type": "Feature",
  "properties": {
    "addr:full":"1480 Main St Winnipeg MB R2W 3W1",
    "addr:housenumber":"1480",
    "addr:postcode":"r2w 3w1",
    "addr:street":"Main St",
    "iso:country":"CA",
    "sg:address":"1480 Main St",
    "sg:city":"Winnipeg",
    "sg:classifiers":[
        {
            "category":"Restaurant",
            "type":"Food & Drink"
        }
    ],
    "sg:phone":"+1 204 589 8437",
    "sg:postcode":"R2W 3W1",
    "sg:province":"MB",
    "wof:name":"Super Boy's Restaurant",
    "wof:placetype":"venue"
},
  "geometry": {"coordinates":[-97.124016,49.928234],"type":"Point"}
}