{
  "type": "Feature",
  "properties": {
    "addr:full":"176 Wellington St Niagara on the Lake ON L0S 1J0",
    "addr:housenumber":"176",
    "addr:postcode":"l0s 1j0",
    "addr:street":"Wellington St;On",
    "iso:country":"CA",
    "sg:address":"176 Wellington St",
    "sg:city":"Niagara on the Lake",
    "sg:classifiers":[
        {
            "category":"Health Services",
            "subcategory":"Doctor",
            "type":"Services"
        }
    ],
    "sg:phone":"+1 905 468 0403",
    "sg:postcode":"L0S 1J0",
    "sg:province":"ON",
    "sg:tags":[
        "physician",
        "surgeon"
    ],
    "wof:name":"Nolan, J P MD",
    "wof:placetype":"venue"
},
  "geometry": {"coordinates":[-79.06707763670001,43.2536888123],"type":"Point"}
}