{
  "type": "Feature",
  "properties": {
    "addr:full":"1011 Albion Rd Etobicoke ON M9V 1A6",
    "addr:housenumber":"1011",
    "addr:postcode":"m9v 1a6",
    "addr:street":"Albion Rd",
    "iso:country":"CA",
    "sg:address":"1011 Albion Rd",
    "sg:city":"Etobicoke",
    "sg:classifiers":[
        {
            "category":"Shopping",
            "subcategory":"Jewelry",
            "type":"Retail Goods"
        }
    ],
    "sg:phone":"+1 416 746 5454",
    "sg:postcode":"M9V 1A6",
    "sg:province":"ON",
    "sg:tags":[
        "jeweler"
    ],
    "wof:name":"New Maharani Jewellers",
    "wof:placetype":"venue"
},
  "geometry": {"coordinates":[-79.56300354,43.7360115051],"type":"Point"}
}