{
  "type": "Feature",
  "properties": {
    "addr:full":"Cobourg ON K9A 5V2",
    "addr:postcode":"k9a 5v2",
    "iso:country":"CA",
    "sg:city":"Cobourg",
    "sg:classifiers":[
        {
            "category":"Manufacturing",
            "subcategory":"Printing",
            "type":"Manufacturing & Wholesale Goods"
        }
    ],
    "sg:phone":"+1 905 373 7355",
    "sg:postcode":"K9A 5V2",
    "sg:province":"ON",
    "sg:tags":[
        "newspaper"
    ],
    "wof:name":"Northumberland News",
    "wof:placetype":"venue"
},
  "geometry": {"coordinates":[-78.172417,43.975704],"type":"Point"}
}