{
  "type": "Feature",
  "properties": {
    "addr:full":"225 Rue Dessureault Cap-DE-LA-Madeleine QC G8T 2L7",
    "addr:housenumber":"225",
    "addr:postcode":"g8t 2l7",
    "addr:street":"Rue Dessureault",
    "iso:country":"CA",
    "sg:address":"225 Rue Dessureault",
    "sg:city":"Cap-DE-LA-Madeleine",
    "sg:classifiers":[
        {
            "category":"Manufacturing",
            "subcategory":"Tools & Machinery",
            "type":"Manufacturing & Wholesale Goods"
        }
    ],
    "sg:phone":"+1 819 375 6549",
    "sg:postcode":"G8T 2L7",
    "sg:province":"QC",
    "sg:tags":[
        "equipment",
        "system",
        "automation"
    ],
    "wof:name":"Automation Mauricie Inc",
    "wof:placetype":"venue"
},
  "geometry": {"coordinates":[-72.5277328491,46.3783950806],"type":"Point"}
}