{
  "type": "Feature",
  "properties": {
    "addr:full":"210 Surette Rd Wedgeport NS B0W 3P0",
    "addr:housenumber":"210",
    "addr:postcode":"b0w 3p0",
    "addr:street":"Surette Rd",
    "iso:country":"CA",
    "sg:address":"210 Surette Rd",
    "sg:city":"Wedgeport",
    "sg:classifiers":[
        {
            "category":"Professional",
            "subcategory":"Detective & Security Services",
            "type":"Services"
        }
    ],
    "sg:phone":"+1 902 740 2066",
    "sg:postcode":"B0W 3P0",
    "sg:province":"NS",
    "sg:tags":[
        "guard",
        "patrol"
    ],
    "wof:name":"Magnum Security",
    "wof:placetype":"venue"
},
  "geometry": {"coordinates":[-65.980430603,43.7313652039],"type":"Point"}
}