{
  "type": "Feature",
  "properties": {
    "addr:full":"235 St Clair Ave W Toronto ON M4V 1R4",
    "addr:housenumber":"235",
    "addr:postcode":"m4v 1r4",
    "addr:street":"St Clair Ave W",
    "iso:country":"CA",
    "sg:address":"235 St Clair Ave W",
    "sg:city":"Toronto",
    "sg:classifiers":[
        {
            "category":"Health Services",
            "subcategory":"Doctor",
            "type":"Services"
        }
    ],
    "sg:phone":"+1 416 944 1061",
    "sg:postcode":"M4V 1R4",
    "sg:province":"ON",
    "sg:tags":[
        "physician",
        "surgeon"
    ],
    "wof:name":"Wiener, John MD",
    "wof:placetype":"venue"
},
  "geometry": {"coordinates":[-79.4050750732,43.6857948303],"type":"Point"}
}