{
  "type": "Feature",
  "properties": {
    "iso:country":"CA",
    "sg:address":"10819 126 St NW",
    "sg:city":"Edmonton",
    "sg:classifiers":[
        {
            "category":"Wholesale",
            "subcategory":"Machinery & Supplies",
            "type":"Manufacturing & Wholesale Goods"
        }
    ],
    "sg:phone":"+1 780 454 9665",
    "sg:postcode":"T5M 0P2",
    "sg:province":"AB",
    "sg:tags":[
        "packaging"
    ],
    "wof:name":"Packaging 2000 Ltd",
    "wof:placetype":"venue"
},
  "geometry": {"coordinates":[-113.539230347,53.552898407],"type":"Point"}
}