{
  "type": "Feature",
  "properties": {
    "addr:full":"11445 Jasper Ave NW Edmonton AB T5K 0M6",
    "addr:housenumber":"11445",
    "addr:postcode":"t5k 0m6",
    "addr:street":"Jasper Ave Nw",
    "iso:country":"CA",
    "sg:address":"11445 Jasper Ave NW",
    "sg:city":"Edmonton",
    "sg:classifiers":[
        {
            "category":"Autos & Motor Vehicles",
            "subcategory":"Automobile Sales",
            "type":"Retail Goods"
        }
    ],
    "sg:phone":"+1 780 482 5771",
    "sg:postcode":"T5K 0M6",
    "sg:province":"AB",
    "sg:tags":[
        "car",
        "dealer"
    ],
    "wof:name":"Edmonton Motors Ltd",
    "wof:placetype":"venue"
},
  "geometry": {"coordinates":[-113.518478394,53.5407142639],"type":"Point"}
}