{
  "type": "Feature",
  "properties": {
    "addr:full":"3065 Rue Peugeot Laval QC H7L 5C4",
    "addr:housenumber":"3065",
    "addr:postcode":"h7l 5c4",
    "addr:street":"Rue Peugeot",
    "iso:country":"CA",
    "sg:address":"3065 Rue Peugeot",
    "sg:city":"Laval",
    "sg:classifiers":[
        {
            "category":"Building & Trades",
            "subcategory":"Construction",
            "type":"Services"
        }
    ],
    "sg:phone":"+1 450 688 4012",
    "sg:postcode":"H7L 5C4",
    "sg:province":"QC",
    "sg:tags":[
        "concrete",
        "general",
        "form",
        "contractor"
    ],
    "wof:name":"Norclair Inc",
    "wof:placetype":"venue"
},
  "geometry": {"coordinates":[-73.7469406128,45.5879478455],"type":"Point"}
}