{
  "type": "Feature",
  "properties": {
    "addr:full":"3366 MT Lehman Rd Abbotsford BC V4X 2M9",
    "addr:housenumber":"3366",
    "addr:postcode":"v4x 2m9",
    "addr:street":"Mt Lehman Rd",
    "iso:country":"CA",
    "sg:address":"3366 MT Lehman Rd",
    "sg:city":"Abbotsford",
    "sg:classifiers":[
        {
            "category":"Organizations",
            "subcategory":"Religious Organization",
            "type":"Services"
        }
    ],
    "sg:phone":"+1 604 856 1361",
    "sg:postcode":"V4X 2M9",
    "sg:province":"BC",
    "sg:tags":[
        "church"
    ],
    "wof:name":"Emmanuel Free Reformed Church",
    "wof:placetype":"venue"
},
  "geometry": {"coordinates":[-122.38101196300001,49.0629196167],"type":"Point"}
}