{
  "type": "Feature",
  "properties": {
    "iso:country":"CA",
    "sg:address":"15 William St",
    "sg:city":"St Andrews",
    "sg:classifiers":[
        {
            "category":"Professional",
            "subcategory":"Business Services",
            "type":"Services"
        }
    ],
    "sg:phone":"+1 506 529 4555",
    "sg:postcode":"E5B 1W6",
    "sg:province":"NB",
    "sg:tags":[
        "diving",
        "instruction",
        "diver"
    ],
    "wof:name":"Navy Island Dive CO Ltd",
    "wof:placetype":"venue"
},
  "geometry": {"coordinates":[-67.0544433594,45.0740394592],"type":"Point"}
}