{
  "type": "Feature",
  "properties": {
    "addr:full":"478 Exmouth St Sarnia ON N7T 5P3",
    "addr:housenumber":"478",
    "addr:postcode":"n7t 5p3",
    "addr:street":"Exmouth St",
    "iso:country":"CA",
    "sg:address":"478 Exmouth St",
    "sg:city":"Sarnia",
    "sg:classifiers":[
        {
            "category":"Banks & Credit Unions",
            "subcategory":"Bank",
            "type":"Services"
        }
    ],
    "sg:phone":"+1 519 336 2276",
    "sg:postcode":"N7T 5P3",
    "sg:province":"ON",
    "wof:name":"Cibc",
    "wof:placetype":"venue"
},
  "geometry": {"coordinates":[-82.38826,42.985474],"type":"Point"}
}