{
  "type": "Feature",
  "properties": {
    "iso:country":"CA",
    "sg:city":"Lachine",
    "sg:classifiers":[
        {
            "category":"Home & Garden",
            "subcategory":"Building Materials",
            "type":"Retail Goods"
        }
    ],
    "sg:phone":"+1 514 368 3160",
    "sg:postcode":"H8R 1E8",
    "sg:province":"QC",
    "sg:tags":[
        "glass",
        "window",
        "plate"
    ],
    "wof:name":"Vitrerie General Mtl",
    "wof:placetype":"venue"
},
  "geometry": {"coordinates":[-73.64915466310001,45.4428596497],"type":"Point"}
}