{
  "type": "Feature",
  "properties": {
    "iso:country":"CA",
    "sg:address":"2399 Parkedale Ave W",
    "sg:city":"Brockville",
    "sg:classifiers":[
        {
            "category":"Food & Beverages",
            "subcategory":"Bakery",
            "type":"Retail Goods"
        }
    ],
    "sg:phone":"+1 613 345 5771",
    "sg:postcode":"K6V 3G9",
    "sg:province":"ON",
    "sg:tags":[
        "baker"
    ],
    "wof:name":"Treats",
    "wof:placetype":"venue"
},
  "geometry": {"coordinates":[-75.69933319090001,44.6044769287],"type":"Point"}
}