{
  "type": "Feature",
  "properties": {
    "addr:full":"560 Exmouth St Sarnia ON N7T 5P5",
    "addr:housenumber":"560",
    "addr:postcode":"n7t 5p5",
    "addr:street":"Exmouth St",
    "iso:country":"CA",
    "sg:address":"560 Exmouth St",
    "sg:city":"Sarnia",
    "sg:classifiers":[
        {
            "category":"Personal",
            "subcategory":"Beauty Salon",
            "type":"Services"
        }
    ],
    "sg:phone":"+1 519 344 9803",
    "sg:postcode":"N7T 5P5",
    "sg:province":"ON",
    "wof:name":"A Kut Above",
    "wof:placetype":"venue"
},
  "geometry": {"coordinates":[-82.386756897,42.9854393005],"type":"Point"}
}