{
  "type": "Feature",
  "properties": {
    "iso:country":"CA",
    "sg:address":"60 Bond St E",
    "sg:city":"Oshawa",
    "sg:classifiers":[
        {
            "category":"Health Services",
            "subcategory":"Nursing And Care Facility",
            "type":"Services"
        }
    ],
    "sg:phone":"+1 905 725 2599",
    "sg:postcode":"L1G 8C9",
    "sg:province":"ON",
    "sg:tags":[
        "home",
        "retirement",
        "community"
    ],
    "wof:name":"Carriage House",
    "wof:placetype":"venue"
},
  "geometry": {"coordinates":[-78.8616943359,43.8991203308],"type":"Point"}
}