{
  "type": "Feature",
  "properties": {
    "addr:full":"1202 13th Ave Invermere BC V0A 1K4",
    "addr:housenumber":"1202",
    "addr:postcode":"v0a 1k4",
    "addr:street":"13Th Ave",
    "iso:country":"CA",
    "sg:address":"1202 13th Ave",
    "sg:city":"Invermere",
    "sg:classifiers":[
        {
            "category":"Education",
            "subcategory":"School",
            "type":"Public Place"
        }
    ],
    "sg:phone":"+1 250 342 6232",
    "sg:postcode":"V0A 1K4",
    "sg:province":"BC",
    "wof:name":"J A Laird Elementary School",
    "wof:placetype":"venue"
},
  "geometry": {"coordinates":[-116.037926,50.497639],"type":"Point"}
}