{
  "type": "Feature",
  "properties": {
    "addr:full":"Owen Sound ON N4K 5N7",
    "addr:postcode":"n4k 5n7",
    "iso:country":"CA",
    "sg:city":"Owen Sound",
    "sg:classifiers":[
        {
            "category":"Home & Garden",
            "subcategory":"Furniture",
            "type":"Retail Goods"
        }
    ],
    "sg:phone":"+1 519 371 2963",
    "sg:postcode":"N4K 5N7",
    "sg:province":"ON",
    "sg:tags":[
        "stove",
        "wood",
        "burning"
    ],
    "wof:name":"Fyre Place & Patio Shop",
    "wof:placetype":"venue"
},
  "geometry": {"coordinates":[-80.92543000000001,44.556931],"type":"Point"}
}