{
  "type": "Feature",
  "properties": {
    "addr:full":"Ingleside ON K0C 1M0",
    "addr:postcode":"k0c 1m0",
    "iso:country":"CA",
    "sg:city":"Ingleside",
    "sg:classifiers":[
        {
            "category":"Food & Beverages",
            "subcategory":"Liquor & Beverages",
            "type":"Retail Goods"
        }
    ],
    "sg:phone":"+1 613 537 5292",
    "sg:postcode":"K0C 1M0",
    "sg:province":"ON",
    "sg:tags":[
        "store"
    ],
    "wof:name":"Lcbo Ingleside",
    "wof:placetype":"venue"
},
  "geometry": {"coordinates":[-74.98937225340001,44.9950256348],"type":"Point"}
}