{
  "type": "Feature",
  "properties": {
    "addr:full":"PO Box 935 Fort Smith NT X0E 0P0",
    "addr:housenumber":"po",
    "addr:postcode":"x0e 0p0",
    "addr:street":"Box 935",
    "iso:country":"CA",
    "sg:address":"PO Box 935",
    "sg:city":"Fort Smith",
    "sg:classifiers":[
        {
            "category":"Manufacturing",
            "subcategory":"Buildings",
            "type":"Manufacturing & Wholesale Goods"
        }
    ],
    "sg:phone":"+1 867 872 4261",
    "sg:postcode":"X0E 0P0",
    "sg:province":"NT",
    "sg:tags":[
        "home",
        "log",
        "cabin"
    ],
    "wof:name":"Northwood Log Homes",
    "wof:placetype":"venue"
},
  "geometry": {"coordinates":[-111.902633667,60.0000953674],"type":"Point"}
}