{
  "type": "Feature",
  "properties": {
    "addr:full":"221 1E Av O Amos QC J9T 1V1",
    "addr:housenumber":"221",
    "addr:postcode":"j9t 1v1",
    "addr:street":"1E Av O Amos",
    "iso:country":"CA",
    "sg:address":"221 1E Av O",
    "sg:city":"Amos",
    "sg:classifiers":[
        {
            "category":"Personal",
            "type":"Services"
        }
    ],
    "sg:phone":"+1 819 732 8812",
    "sg:postcode":"J9T 1V1",
    "sg:province":"QC",
    "sg:tags":[
        "food",
        "therapist",
        "massage"
    ],
    "wof:name":"Sesame",
    "wof:placetype":"venue"
},
  "geometry": {"coordinates":[-78.110206604,48.5720596313],"type":"Point"}
}