{
  "type": "Feature",
  "properties": {
    "iso:country":"CA",
    "sg:address":"800 Queenston Rd",
    "sg:city":"Stoney Creek",
    "sg:classifiers":[
        {
            "category":"Personal",
            "subcategory":"Beauty Salon",
            "type":"Services"
        }
    ],
    "sg:phone":"+1 905 662 2437",
    "sg:postcode":"L8G 1A7",
    "sg:province":"ON",
    "wof:name":"Haircrafters",
    "wof:placetype":"venue"
},
  "geometry": {"coordinates":[-79.764946,43.228146],"type":"Point"}
}