{
  "type": "Feature",
  "properties": {
    "addr:full":"Airdrie AB T4B 2C2",
    "addr:postcode":"t4b 2c2",
    "iso:country":"CA",
    "sg:city":"Airdrie",
    "sg:classifiers":[
        {
            "category":"Professional",
            "subcategory":"Lawyer & Legal Services",
            "type":"Services"
        }
    ],
    "sg:phone":"+1 403 948 6791",
    "sg:postcode":"T4B 2C2",
    "sg:province":"AB",
    "sg:tags":[
        "attorney"
    ],
    "wof:name":"Your Lawyer",
    "wof:placetype":"venue"
},
  "geometry": {"coordinates":[-114.003311,51.289852],"type":"Point"}
}