{
  "type": "Feature",
  "properties": {
    "iso:country":"CA",
    "sg:address":"2657 Yonge St",
    "sg:city":"Toronto",
    "sg:classifiers":[
        {
            "category":"Shopping",
            "subcategory":"Optical Goods",
            "type":"Retail Goods"
        }
    ],
    "sg:phone":"+1 416 483 2123",
    "sg:postcode":"M4P 2J6",
    "sg:province":"ON",
    "sg:tags":[
        "sun",
        "goggles",
        "sunglasses",
        "optician"
    ],
    "wof:name":"Dillon Opticians",
    "wof:placetype":"venue"
},
  "geometry": {"coordinates":[-79.4001922607,43.7161216736],"type":"Point"}
}