{
  "type": "Feature",
  "properties": {
    "addr:full":"Victoria BC V8R 4R2",
    "addr:postcode":"v8r 4r2",
    "iso:country":"CA",
    "sg:city":"Victoria",
    "sg:classifiers":[
        {
            "category":"Health Services",
            "subcategory":"Doctor",
            "type":"Services"
        }
    ],
    "sg:phone":"+1 250 595 1551",
    "sg:postcode":"V8R 4R2",
    "sg:province":"BC",
    "sg:tags":[
        "physician",
        "surgeon"
    ],
    "wof:name":"Western Cardiology Assoc",
    "wof:placetype":"venue"
},
  "geometry": {"coordinates":[-123.330215,48.429512],"type":"Point"}
}