{
  "type": "Feature",
  "properties": {
    "addr:full":"4470 Boul Bourque Rock Forest QC J1N 1S3",
    "addr:housenumber":"4470",
    "addr:postcode":"j1n 1s3",
    "addr:street":"Boul Bourque",
    "iso:country":"CA",
    "sg:address":"4470 Boul Bourque",
    "sg:city":"Rock Forest",
    "sg:classifiers":[
        {
            "category":"Food & Beverages",
            "subcategory":"Groceries & Convenience Stores",
            "type":"Retail Goods"
        }
    ],
    "sg:phone":"+1 819 823 6913",
    "sg:postcode":"J1N 1S3",
    "sg:province":"QC",
    "sg:tags":[
        "polishing",
        "car",
        "washing"
    ],
    "wof:name":"Depanneur MI-Vallon",
    "wof:placetype":"venue"
},
  "geometry": {"coordinates":[-71.977058,45.377331],"type":"Point"}
}