{
  "type": "Feature",
  "properties": {
    "addr:full":"10144 79 St NW Edmonton AB T6A 3G3",
    "addr:housenumber":"10144",
    "addr:postcode":"t6a 3g3",
    "addr:street":"79 St Nw",
    "iso:country":"CA",
    "sg:address":"10144 79 St NW",
    "sg:city":"Edmonton",
    "sg:classifiers":[
        {
            "category":"Health Services",
            "subcategory":"Chiropractor",
            "type":"Services"
        }
    ],
    "sg:phone":"+1 780 469 1561",
    "sg:postcode":"T6A 3G3",
    "sg:province":"AB",
    "wof:name":"Moutran, Lorrie A DC",
    "wof:placetype":"venue"
},
  "geometry": {"coordinates":[-113.449524,53.542095],"type":"Point"}
}