{
  "type": "Feature",
  "properties": {
    "addr:full":"92 6th Ave NW Nakusp BC V0G 1R0",
    "addr:housenumber":"92",
    "addr:postcode":"v0g 1r0",
    "addr:street":"6Th Ave Nw",
    "iso:country":"CA",
    "sg:address":"92 6th Ave NW",
    "sg:city":"Nakusp",
    "sg:classifiers":[
        {
            "category":"Government",
            "subcategory":"Office",
            "type":"Public Place"
        }
    ],
    "sg:phone":"+1 250 265 4111",
    "sg:postcode":"V0G 1R0",
    "sg:province":"BC",
    "sg:tags":[
        "village"
    ],
    "wof:name":"Nakusp Building Inspector",
    "wof:placetype":"venue"
},
  "geometry": {"coordinates":[-117.805351,50.240166],"type":"Point"}
}