{
  "type": "Feature",
  "properties": {
    "addr:full":"Highway 535 St Charles ON P0M 2W0",
    "addr:postcode":"p0m 2w0",
    "addr:street":"Highway 535",
    "iso:country":"CA",
    "sg:address":"Highway 535",
    "sg:city":"St Charles",
    "sg:classifiers":[
        {
            "category":"Health Services",
            "subcategory":"Doctor",
            "type":"Services"
        }
    ],
    "sg:phone":"+1 705 867 5793",
    "sg:postcode":"P0M 2W0",
    "sg:province":"ON",
    "sg:tags":[
        "physician",
        "surgeon"
    ],
    "wof:name":"St Charles Medical Centre",
    "wof:placetype":"venue"
},
  "geometry": {"coordinates":[-80.416122,46.36792],"type":"Point"}
}