{
  "type": "Feature",
  "properties": {
    "iso:country":"CA",
    "sg:address":"89 Rue Racine E",
    "sg:city":"Chicoutimi",
    "sg:classifiers":[
        {
            "category":"Shopping",
            "subcategory":"Computers & Home Electronics",
            "type":"Retail Goods"
        }
    ],
    "sg:phone":"+1 418 690 5389",
    "sg:postcode":"G7H 1P9",
    "sg:province":"QC",
    "sg:tags":[
        "game",
        "video"
    ],
    "wof:name":"Jeux Video Hytech",
    "wof:placetype":"venue"
},
  "geometry": {"coordinates":[-71.06596374510001,48.4280395508],"type":"Point"}
}