{
  "type": "Feature",
  "properties": {
    "addr:full":"1260 Hornby St Vancouver BC V6Z 1W2",
    "addr:housenumber":"1260",
    "addr:postcode":"v6z 1w2",
    "addr:street":"Hornby St",
    "iso:country":"CA",
    "sg:address":"1260 Hornby St",
    "sg:city":"Vancouver",
    "sg:classifiers":[
        {
            "category":"Real Estate",
            "subcategory":"Real Estate Agent",
            "type":"Services"
        }
    ],
    "sg:phone":"+1 604 683 9272",
    "sg:postcode":"V6Z 1W2",
    "sg:province":"BC",
    "sg:tags":[
        "desk",
        "space"
    ],
    "wof:name":"Vancouver Estates Ltd",
    "wof:placetype":"venue"
},
  "geometry": {"coordinates":[-123.128952,49.277695],"type":"Point"}
}