{
  "type": "Feature",
  "properties": {
    "addr:full":"165 Athabascan Ave Sherwood Park AB T8A 4C8",
    "addr:housenumber":"165",
    "addr:postcode":"t8a 4c8",
    "addr:street":"Athabascan Ave",
    "iso:country":"CA",
    "sg:address":"165 Athabascan Ave",
    "sg:city":"Sherwood Park",
    "sg:classifiers":[
        {
            "category":"Building & Trades",
            "subcategory":"Construction",
            "type":"Services"
        }
    ],
    "sg:phone":"+1 780 449 3100",
    "sg:postcode":"T8A 4C8",
    "sg:province":"AB",
    "sg:tags":[
        "refinishing",
        "floor",
        "laying",
        "rug",
        "resurfacing",
        "dealer",
        "carpet"
    ],
    "wof:name":"Family Fashion Floors Inc",
    "wof:placetype":"venue"
},
  "geometry": {"coordinates":[-113.325951,53.536003],"type":"Point"}
}