{
  "type": "Feature",
  "properties": {
    "addr:full":"827 3rd Ave E Owen Sound ON N4K 2K6",
    "addr:housenumber":"827",
    "addr:postcode":"n4k 2k6",
    "addr:street":"3Rd Ave E",
    "iso:country":"CA",
    "sg:address":"827 3rd Ave E",
    "sg:city":"Owen Sound",
    "sg:classifiers":[
        {
            "category":"Retail",
            "subcategory":"Auto Repair",
            "type":"Services"
        }
    ],
    "sg:phone":"+1 519 376 4706",
    "sg:postcode":"N4K 2K6",
    "sg:province":"ON",
    "sg:tags":[
        "body",
        "automobile",
        "painting"
    ],
    "wof:name":"Mc Kee Percy & Son",
    "wof:placetype":"venue"
},
  "geometry": {"coordinates":[-80.94049072270001,44.5647506714],"type":"Point"}
}