{
  "type": "Feature",
  "properties": {
    "addr:full":"104 Johnson St Kingston ON K7L 1X8",
    "addr:housenumber":"104",
    "addr:postcode":"k7l 1x8",
    "addr:street":"Johnson St",
    "iso:country":"CA",
    "sg:address":"104 Johnson St",
    "sg:city":"Kingston",
    "sg:classifiers":[
        {
            "category":"Professional",
            "subcategory":"Lawyer & Legal Services",
            "type":"Services"
        }
    ],
    "sg:phone":"+1 613 546 5581",
    "sg:postcode":"K7L 1X8",
    "sg:province":"ON",
    "sg:tags":[
        "attorney"
    ],
    "wof:name":"O'Connor Law Office",
    "wof:placetype":"venue"
},
  "geometry": {"coordinates":[-76.4841995239,44.2294311523],"type":"Point"}
}