{
  "type": "Feature",
  "properties": {
    "addr:full":"1287 Boul Charest O Quebec QC G1N 2C9",
    "addr:housenumber":"1287",
    "addr:postcode":"g1n 2c9",
    "addr:street":"Boul Charest O",
    "iso:country":"CA",
    "sg:address":"1287 Boul Charest O",
    "sg:city":"Quebec",
    "sg:classifiers":[
        {
            "category":"Home & Garden",
            "subcategory":"Building Materials",
            "type":"Retail Goods"
        }
    ],
    "sg:phone":"+1 418 688 3333",
    "sg:postcode":"G1N 2C9",
    "sg:province":"QC",
    "sg:tags":[
        "plate",
        "window",
        "radio",
        "stereo",
        "automobile"
    ],
    "wof:name":"Automod Vitres & Accessories",
    "wof:placetype":"venue"
},
  "geometry": {"coordinates":[-71.2566604614,46.7990684509],"type":"Point"}
}