{
  "type": "Feature",
  "properties": {
    "addr:full":"10 Rue Belmont Aylmer QC J9H 6J5",
    "addr:housenumber":"10",
    "addr:postcode":"j9h 6j5",
    "addr:street":"Rue Belmont",
    "iso:country":"CA",
    "sg:address":"10 Rue Belmont",
    "sg:city":"Aylmer",
    "sg:classifiers":[
        {
            "category":"Restaurant",
            "type":"Food & Drink"
        }
    ],
    "sg:phone":"+1 819 684 4331",
    "sg:postcode":"J9H 6J5",
    "sg:province":"QC",
    "sg:tags":[
        "out",
        "pizza"
    ],
    "wof:name":"Pizza Jimmie",
    "wof:placetype":"venue"
},
  "geometry": {"coordinates":[-75.8304443359,45.3939476013],"type":"Point"}
}