{
  "type": "Feature",
  "properties": {
    "addr:full":"67 Foster Wheatley ON N0P 2P0",
    "addr:housenumber":"67",
    "addr:postcode":"n0p 2p0",
    "addr:street":"Foster",
    "iso:country":"CA",
    "sg:address":"67 Foster",
    "sg:city":"Wheatley",
    "sg:classifiers":[
        {
            "category":"Building & Trades",
            "subcategory":"Plumbing",
            "type":"Services"
        }
    ],
    "sg:phone":"+1 519 825 7245",
    "sg:postcode":"N0P 2P0",
    "sg:province":"ON",
    "sg:tags":[
        "contractor"
    ],
    "wof:name":"Irwin Plumbing",
    "wof:placetype":"venue"
},
  "geometry": {"coordinates":[-82.4652481079,42.0956497192],"type":"Point"}
}