{
  "type": "Feature",
  "properties": {
    "addr:full":"4682 Highway 2 Gananoque ON K7G 2V4",
    "addr:housenumber":"4682",
    "addr:postcode":"k7g 2v4",
    "addr:street":"Highway 2",
    "iso:country":"CA",
    "sg:address":"4682 Highway 2",
    "sg:city":"Gananoque",
    "sg:classifiers":[
        {
            "category":"Travel",
            "subcategory":"Hotels & Motels",
            "type":"Entertainment"
        }
    ],
    "sg:phone":"+1 613 382 2270",
    "sg:postcode":"K7G 2V4",
    "sg:province":"ON",
    "sg:tags":[
        "tourist",
        "accommodation"
    ],
    "wof:name":"Willowbank Motor Court",
    "wof:placetype":"venue"
},
  "geometry": {"coordinates":[-76.164261,44.32848],"type":"Point"}
}