{
  "type": "Feature",
  "properties": {
    "addr:full":"733 Clearwater Village Rd Clearwater BC V0E 1N0",
    "addr:housenumber":"733",
    "addr:postcode":"v0e 1n0",
    "addr:street":"Clearwater Village Rd",
    "iso:country":"CA",
    "sg:address":"733 Clearwater Village Rd",
    "sg:city":"Clearwater",
    "sg:classifiers":[
        {
            "category":"Food & Beverages",
            "subcategory":"Groceries & Convenience Stores",
            "type":"Retail Goods"
        }
    ],
    "sg:phone":"+1 250 674 3331",
    "sg:postcode":"V0E 1N0",
    "sg:province":"BC",
    "sg:tags":[
        "grocer"
    ],
    "wof:name":"Raft River Mini Market",
    "wof:placetype":"venue"
},
  "geometry": {"coordinates":[-120.014267,51.646236],"type":"Point"}
}