{
  "type": "Feature",
  "properties": {
    "addr:full":"5914 3 St SW Calgary AB T2H 0H8",
    "addr:housenumber":"5914 3",
    "addr:postcode":"t2h 0h8",
    "addr:street":"St Sw",
    "iso:country":"CA",
    "sg:address":"5914 3 St SW",
    "sg:city":"Calgary",
    "sg:classifiers":[
        {
            "category":"Home & Garden",
            "subcategory":"Carpets & Floor Coverings",
            "type":"Retail Goods"
        }
    ],
    "sg:phone":"+1 403 212 1000",
    "sg:postcode":"T2H 0H8",
    "sg:province":"AB",
    "sg:tags":[
        "material",
        "rug"
    ],
    "wof:name":"Jordans Floorcoverings Inc",
    "wof:placetype":"venue"
},
  "geometry": {"coordinates":[-114.06935900000001,51.001057],"type":"Point"}
}