{
  "type": "Feature",
  "properties": {
    "addr:full":"2051 Mountain Rd Moncton NB E1G 1B1",
    "addr:housenumber":"2051",
    "addr:postcode":"e1g 1b1",
    "addr:street":"Mountain Rd",
    "iso:country":"CA",
    "sg:address":"2051 Mountain Rd",
    "sg:city":"Moncton",
    "sg:classifiers":[
        {
            "category":"Social Services",
            "subcategory":"Child Care",
            "type":"Services"
        }
    ],
    "sg:phone":"+1 506 384 8682",
    "sg:postcode":"E1G 1B1",
    "sg:province":"NB",
    "wof:name":"Home With A Heart Daycare",
    "wof:placetype":"venue"
},
  "geometry": {"coordinates":[-64.85688,46.123989],"type":"Point"}
}