{
  "type": "Feature",
  "properties": {
    "addr:full":"Ancaster ON L9G 3K9",
    "addr:postcode":"l9g 3k9",
    "iso:country":"CA",
    "sg:city":"Ancaster",
    "sg:classifiers":[
        {
            "category":"Retail",
            "subcategory":"Veterinary Services",
            "type":"Services"
        }
    ],
    "sg:phone":"+1 905 648 4747",
    "sg:postcode":"L9G 3K9",
    "sg:province":"ON",
    "sg:tags":[
        "veterinarian"
    ],
    "wof:name":"Chedoke Animal Hospital",
    "wof:placetype":"venue"
},
  "geometry": {"coordinates":[-79.934471,43.232685],"type":"Point"}
}