{
  "type": "Feature",
  "properties": {
    "iso:country":"CA",
    "sg:address":"260 Redonda St",
    "sg:city":"Winnipeg",
    "sg:classifiers":[
        {
            "category":"Education",
            "subcategory":"School",
            "type":"Public Place"
        }
    ],
    "sg:phone":"+1 204 958 6460",
    "sg:postcode":"R2C 1L6",
    "sg:province":"MB",
    "wof:name":"Murdoch Mac Kay Collegiate",
    "wof:placetype":"venue"
},
  "geometry": {"coordinates":[-96.97960662840001,49.8984603882],"type":"Point"}
}