{
  "type": "Feature",
  "properties": {
    "addr:full":"5747 Coopers Ave Mississauga ON L4Z 1R9",
    "addr:housenumber":"5747",
    "addr:postcode":"l4z 1r9",
    "addr:street":"Coopers Ave",
    "iso:country":"CA",
    "sg:address":"5747 Coopers Ave",
    "sg:city":"Mississauga",
    "sg:classifiers":[
        {
            "category":"Manufacturing",
            "subcategory":"Electronics",
            "type":"Manufacturing & Wholesale Goods"
        }
    ],
    "sg:phone":"+1 905 890 9983",
    "sg:postcode":"L4Z 1R9",
    "sg:province":"ON",
    "sg:tags":[
        "sound",
        "equipment",
        "supply",
        "system",
        "telephone"
    ],
    "wof:name":"Executive Communications",
    "wof:placetype":"venue"
},
  "geometry": {"coordinates":[-79.6616592407,43.631362915],"type":"Point"}
}