{
  "type": "Feature",
  "properties": {
    "addr:full":"5011 118 Ave NW Edmonton AB T5W 1B8",
    "addr:housenumber":"5011",
    "addr:postcode":"t5w 1b8",
    "addr:street":"118 Ave Nw",
    "iso:country":"CA",
    "sg:address":"5011 118 Ave NW",
    "sg:city":"Edmonton",
    "sg:classifiers":[
        {
            "category":"Shopping",
            "subcategory":"Pharmacy",
            "type":"Retail Goods"
        }
    ],
    "sg:phone":"+1 780 448 6048",
    "sg:postcode":"T5W 1B8",
    "sg:province":"AB",
    "wof:name":"Medicine Shoppe",
    "wof:placetype":"venue"
},
  "geometry": {"coordinates":[-113.418999,53.570267],"type":"Point"}
}