{
  "type": "Feature",
  "properties": {
    "addr:full":"222 Bay St Toronto ON M5K 1K7",
    "addr:housenumber":"222",
    "addr:postcode":"m5k 1k7",
    "addr:street":"Bay St",
    "iso:country":"CA",
    "sg:address":"222 Bay St",
    "sg:city":"Toronto",
    "sg:classifiers":[
        {
            "category":"Restaurant",
            "type":"Food & Drink"
        }
    ],
    "sg:phone":"+1 416 304 1383",
    "sg:postcode":"M5K 1K7",
    "sg:province":"ON",
    "wof:name":"Soup Nutsy Canada Inc",
    "wof:placetype":"venue"
},
  "geometry": {"coordinates":[-79.380104,43.647778],"type":"Point"}
}