{
  "type": "Feature",
  "properties": {
    "addr:full":"45 6E Av Ferme-Neuve QC J0W 1C0",
    "addr:housenumber":"45",
    "addr:postcode":"j0w 1c0",
    "addr:street":"6E Av Ferme-Neuve",
    "iso:country":"CA",
    "sg:address":"45 6E Av",
    "sg:city":"Ferme-Neuve",
    "sg:classifiers":[
        {
            "category":"Building & Trades",
            "subcategory":"Construction",
            "type":"Services"
        }
    ],
    "sg:phone":"+1 819 587 3432",
    "sg:postcode":"J0W 1C0",
    "sg:province":"QC",
    "sg:tags":[
        "excavating",
        "contractor"
    ],
    "wof:name":"24224222 Quebec Inc",
    "wof:placetype":"venue"
},
  "geometry": {"coordinates":[-75.456177,46.699341],"type":"Point"}
}