{
  "type": "Feature",
  "properties": {
    "addr:full":"840 Rue Rocheleau Saint-Hubert QC J3Y 4S8",
    "addr:housenumber":"840",
    "addr:postcode":"j3y 4s8",
    "addr:street":"Rue Rocheleau",
    "iso:country":"CA",
    "sg:address":"840 Rue Rocheleau",
    "sg:city":"Saint-Hubert",
    "sg:classifiers":[
        {
            "category":"Building & Trades",
            "subcategory":"Construction",
            "type":"Services"
        }
    ],
    "sg:phone":"+1 450 443 2206",
    "sg:postcode":"J3Y 4S8",
    "sg:province":"QC",
    "sg:tags":[
        "painter"
    ],
    "wof:name":"Peintures Velours",
    "wof:placetype":"venue"
},
  "geometry": {"coordinates":[-73.41529846189999,45.5065727234],"type":"Point"}
}