{
  "type": "Feature",
  "properties": {
    "addr:full":"253 Edinburgh Rd N Guelph ON N1H 1E2",
    "addr:housenumber":"253",
    "addr:postcode":"n1h 1e2",
    "addr:street":"Edinburgh Rd N",
    "iso:country":"CA",
    "sg:address":"253 Edinburgh Rd N",
    "sg:city":"Guelph",
    "sg:classifiers":[
        {
            "category":"Manufacturing",
            "subcategory":"Motor Vehicles & Parts",
            "type":"Manufacturing & Wholesale Goods"
        }
    ],
    "sg:phone":"+1 519 823 1400",
    "sg:postcode":"N1H 1E2",
    "sg:province":"ON",
    "sg:tags":[
        "automobile",
        "supply"
    ],
    "wof:name":"Royal City Automotive",
    "wof:placetype":"venue"
},
  "geometry": {"coordinates":[-80.2685089111,43.5451927185],"type":"Point"}
}