{
  "type": "Feature",
  "properties": {
    "addr:full":"360 Lynn Ave North Vancouver BC V7J 2C5",
    "addr:housenumber":"360",
    "addr:postcode":"v7j 2c5",
    "addr:street":"Lynn Ave",
    "iso:country":"CA",
    "sg:address":"360 Lynn Ave",
    "sg:city":"North Vancouver",
    "sg:classifiers":[
        {
            "category":"Manufacturing",
            "subcategory":"Metals",
            "type":"Manufacturing & Wholesale Goods"
        }
    ],
    "sg:phone":"+1 604 984 4494",
    "sg:postcode":"V7J 2C5",
    "sg:province":"BC",
    "sg:tags":[
        "coating"
    ],
    "wof:name":"Superior Powder Coatings",
    "wof:placetype":"venue"
},
  "geometry": {"coordinates":[-123.036598,49.308178],"type":"Point"}
}