{
  "type": "Feature",
  "properties": {
    "iso:country":"CA",
    "sg:city":"Winnipeg",
    "sg:classifiers":[
        {
            "category":"Shopping",
            "subcategory":"Hobbies, Toys, & Games",
            "type":"Retail Goods"
        }
    ],
    "sg:phone":"+1 204 661 8084",
    "sg:postcode":"R2C 4J2",
    "sg:province":"MB",
    "wof:name":"Hans Christian Toy Stores",
    "wof:placetype":"venue"
},
  "geometry": {"coordinates":[-97.06182861329999,49.897277832],"type":"Point"}
}