{
  "type": "Feature",
  "properties": {
    "iso:country":"CA",
    "sg:address":"147 Queen St",
    "sg:city":"Truro",
    "sg:classifiers":[
        {
            "category":"Banks & Credit Unions",
            "subcategory":"Investment Brokerage",
            "type":"Services"
        }
    ],
    "sg:phone":"+1 902 897 1811",
    "sg:postcode":"B2N 2B4",
    "sg:province":"NS",
    "sg:tags":[
        "consultant",
        "planning",
        "financial"
    ],
    "wof:name":"Dundee Securities Corp",
    "wof:placetype":"venue"
},
  "geometry": {"coordinates":[-63.2785797119,45.366191864],"type":"Point"}
}