{
  "type": "Feature",
  "properties": {
    "iso:country":"CA",
    "sg:address":"123 Rue Du Pont",
    "sg:city":"St Leonard",
    "sg:classifiers":[
        {
            "category":"Bars & Pubs",
            "type":"Food & Drink"
        }
    ],
    "sg:phone":"+1 506 423 6770",
    "sg:postcode":"E7E 1Y4",
    "sg:province":"NB",
    "sg:tags":[
        "lounge",
        "cocktail"
    ],
    "wof:name":"Taverne Du Coin",
    "wof:placetype":"venue"
},
  "geometry": {"coordinates":[-67.9300079346,47.159828186],"type":"Point"}
}