{
  "type": "Feature",
  "properties": {
    "iso:country":"CA",
    "sg:address":"597 Carlaw Ave",
    "sg:city":"Winnipeg",
    "sg:classifiers":[
        {
            "category":"Real Estate",
            "subcategory":"Architect",
            "type":"Services"
        }
    ],
    "sg:phone":"+1 204 233 8484",
    "sg:postcode":"R3L 0V3",
    "sg:province":"MB",
    "wof:name":"Richard, Will",
    "wof:placetype":"venue"
},
  "geometry": {"coordinates":[-97.1422119141,49.8652458191],"type":"Point"}
}