{
  "type": "Feature",
  "properties": {
    "addr:full":"9360 120 St Surrey BC V3V 4B9",
    "addr:housenumber":"9360",
    "addr:postcode":"v3v 4b9",
    "addr:street":"120 St",
    "iso:country":"CA",
    "sg:address":"9360 120 St",
    "sg:city":"Surrey",
    "sg:classifiers":[
        {
            "category":"Government",
            "subcategory":"Office",
            "type":"Public Place"
        }
    ],
    "sg:phone":"+1 604 586 2755",
    "sg:postcode":"V3V 4B9",
    "sg:province":"BC",
    "wof:name":"British Columbia Social Svc",
    "wof:placetype":"venue"
},
  "geometry": {"coordinates":[-122.890038,49.17326],"type":"Point"}
}