{
  "type": "Feature",
  "properties": {
    "iso:country":"CA",
    "sg:city":"Ponoka",
    "sg:classifiers":[
        {
            "category":"Real Estate",
            "subcategory":"Developer",
            "type":"Services"
        }
    ],
    "sg:phone":"+1 403 783 6504",
    "sg:postcode":"T4J 1M5",
    "sg:province":"AB",
    "sg:tags":[
        "mobile",
        "home"
    ],
    "wof:name":"Poplar Grove Mobile Home Vlg",
    "wof:placetype":"venue"
},
  "geometry": {"coordinates":[-113.583320618,52.6878547668],"type":"Point"}
}