{
  "type": "Feature",
  "properties": {
    "addr:full":"4510 27 St Vernon BC V1T 4Y6",
    "addr:housenumber":"4510",
    "addr:postcode":"v1t 4y6",
    "addr:street":"27 St",
    "iso:country":"CA",
    "sg:address":"4510 27 St",
    "sg:city":"Vernon",
    "sg:classifiers":[
        {
            "category":"Autos & Motor Vehicles",
            "subcategory":"Auto Supplies",
            "type":"Retail Goods"
        }
    ],
    "sg:phone":"+1 250 549 2131",
    "sg:postcode":"V1T 4Y6",
    "sg:province":"BC",
    "sg:tags":[
        "department",
        "automobile",
        "parts",
        "store"
    ],
    "wof:name":"Canadian Tire",
    "wof:placetype":"venue"
},
  "geometry": {"coordinates":[-119.26694500000001,50.277996],"type":"Point"}
}