{
  "type": "Feature",
  "properties": {
    "addr:full":"8 Rue Saint-Patrick Sutton QC J0E 2K0",
    "addr:housenumber":"8",
    "addr:postcode":"j0e 2k0",
    "addr:street":"Rue Saint-Patrick",
    "iso:country":"CA",
    "sg:address":"8 Rue Saint-Patrick",
    "sg:city":"Sutton",
    "sg:classifiers":[
        {
            "category":"Building & Trades",
            "subcategory":"Electrical",
            "type":"Services"
        }
    ],
    "sg:phone":"+1 450 538 2221",
    "sg:postcode":"J0E 2K0",
    "sg:province":"QC",
    "sg:tags":[
        "electric",
        "contractor"
    ],
    "wof:name":"Daniel Mireault Electrique Inc",
    "wof:placetype":"venue"
},
  "geometry": {"coordinates":[-72.618881,45.104759],"type":"Point"}
}