{
  "type": "Feature",
  "properties": {
    "addr:full":"1439 Commercial Dr Vancouver BC V5L 3X8",
    "addr:housenumber":"1439",
    "addr:postcode":"v5l 3x8",
    "addr:street":"Commercial Dr",
    "iso:country":"CA",
    "sg:address":"1439 Commercial Dr",
    "sg:city":"Vancouver",
    "sg:classifiers":[
        {
            "category":"Restaurant",
            "type":"Food & Drink"
        }
    ],
    "sg:phone":"+1 604 254 8452",
    "sg:postcode":"V5L 3X8",
    "sg:province":"BC",
    "wof:name":"Tandoori Palace",
    "wof:placetype":"venue"
},
  "geometry": {"coordinates":[-123.069855,49.271763],"type":"Point"}
}