{
  "type": "Feature",
  "properties": {
    "iso:country":"CA",
    "sg:address":"6 Primrose St",
    "sg:city":"Dartmouth",
    "sg:classifiers":[
        {
            "category":"Restaurant",
            "type":"Food & Drink"
        }
    ],
    "sg:phone":"+1 902 466 7171",
    "sg:postcode":"B3A 4C5",
    "sg:province":"NS",
    "sg:tags":[
        "pizza"
    ],
    "wof:name":"Panada Pizza",
    "wof:placetype":"venue"
},
  "geometry": {"coordinates":[-63.5864028931,44.6814842224],"type":"Point"}
}