{
  "type": "Feature",
  "properties": {
    "addr:full":"Clearsand Beach Christopher Lake SK S0J 0N0",
    "addr:postcode":"s0j 0n0",
    "iso:country":"CA",
    "sg:address":"Clearsand Beach",
    "sg:city":"Christopher Lake",
    "sg:classifiers":[
        {
            "category":"Travel",
            "subcategory":"Campground",
            "type":"Entertainment"
        }
    ],
    "sg:phone":"+1 306 982 4912",
    "sg:postcode":"S0J 0N0",
    "sg:province":"SK",
    "sg:tags":[
        "camp"
    ],
    "wof:name":"Camp Kadesh",
    "wof:placetype":"venue"
},
  "geometry": {"coordinates":[-105.79064178500001,53.5399017334],"type":"Point"}
}