{
  "type": "Feature",
  "properties": {
    "addr:full":"5704 92 St NW Edmonton AB T6E 4Y6",
    "addr:housenumber":"5704",
    "addr:postcode":"t6e 4y6",
    "addr:street":"92 St Nw",
    "iso:country":"CA",
    "sg:address":"5704 92 St NW",
    "sg:city":"Edmonton",
    "sg:classifiers":[
        {
            "category":"Manufacturing",
            "subcategory":"Tools & Machinery",
            "type":"Manufacturing & Wholesale Goods"
        }
    ],
    "sg:phone":"+1 780 437 3741",
    "sg:postcode":"T6E 4Y6",
    "sg:province":"AB",
    "sg:tags":[
        "field",
        "oil",
        "equipment"
    ],
    "wof:name":"Galaxy Oilfield Svc Ltd",
    "wof:placetype":"venue"
},
  "geometry": {"coordinates":[-113.468948,53.492867],"type":"Point"}
}