{
  "type": "Feature",
  "properties": {
    "addr:full":"5309 Portage Rd Niagara Falls ON L2E 6B8",
    "addr:housenumber":"5309",
    "addr:postcode":"l2e 6b8",
    "addr:street":"Portage Rd",
    "iso:country":"CA",
    "sg:address":"5309 Portage Rd",
    "sg:city":"Niagara Falls",
    "sg:classifiers":[
        {
            "category":"Shopping",
            "subcategory":"Florist",
            "type":"Retail Goods"
        }
    ],
    "sg:phone":"+1 905 354 2223",
    "sg:postcode":"L2E 6B8",
    "sg:province":"ON",
    "wof:name":"Portage Flowers & Boutique Ltd",
    "wof:placetype":"venue"
},
  "geometry": {"coordinates":[-79.09089660639999,43.0972671509],"type":"Point"}
}