{
  "type": "Feature",
  "properties": {
    "addr:full":"2119 19th St Nanton AB T0L 1R0",
    "addr:housenumber":"2119",
    "addr:postcode":"t0l 1r0",
    "addr:street":"19Th St",
    "iso:country":"CA",
    "sg:address":"2119 19th St",
    "sg:city":"Nanton",
    "sg:classifiers":[
        {
            "category":"Food & Beverages",
            "subcategory":"Liquor & Beverages",
            "type":"Retail Goods"
        }
    ],
    "sg:phone":"+1 403 646 3006",
    "sg:postcode":"T0L 1R0",
    "sg:province":"AB",
    "sg:tags":[
        "store"
    ],
    "wof:name":"Nanton Liquor Store",
    "wof:placetype":"venue"
},
  "geometry": {"coordinates":[-113.772514,50.349197],"type":"Point"}
}