{
  "type": "Feature",
  "properties": {
    "iso:country":"CA",
    "sg:address":"343 Wilson Ave",
    "sg:city":"North York",
    "sg:classifiers":[
        {
            "category":"Shopping",
            "subcategory":"Gifts & Souvenirs",
            "type":"Retail Goods"
        }
    ],
    "sg:phone":"+1 416 638 9373",
    "sg:postcode":"M3H 1T1",
    "sg:province":"ON",
    "sg:tags":[
        "announcement",
        "invitation"
    ],
    "wof:name":"Main Event",
    "wof:placetype":"venue"
},
  "geometry": {"coordinates":[-79.43631,43.736778],"type":"Point"}
}