{
  "type": "Feature",
  "properties": {
    "addr:full":"343 Wilson Ave North York ON M3H 1T1",
    "addr:housenumber":"343",
    "addr:postcode":"m3h 1t1",
    "addr:street":"Wilson Ave",
    "iso:country":"CA",
    "sg:address":"343 Wilson Ave",
    "sg:city":"North York",
    "sg:classifiers":[
        {
            "category":"Shopping",
            "subcategory":"Gifts & Souvenirs",
            "type":"Retail Goods"
        }
    ],
    "sg:phone":"+1 416 638 9373",
    "sg:postcode":"M3H 1T1",
    "sg:province":"ON",
    "sg:tags":[
        "announcement",
        "invitation"
    ],
    "wof:name":"Main Event",
    "wof:placetype":"venue"
},
  "geometry": {"coordinates":[-79.43631000000001,43.736778],"type":"Point"}
}