{
  "type": "Feature",
  "properties": {
    "addr:full":"7935 8 St NE Calgary AB T2E 8A2",
    "addr:housenumber":"7935 8",
    "addr:postcode":"t2e 8a2",
    "addr:street":"St Ne",
    "iso:country":"CA",
    "sg:address":"7935 8 St NE",
    "sg:city":"Calgary",
    "sg:classifiers":[
        {
            "category":"Manufacturing",
            "subcategory":"Metals",
            "type":"Manufacturing & Wholesale Goods"
        }
    ],
    "sg:phone":"+1 403 291 1461",
    "sg:postcode":"T2E 8A2",
    "sg:province":"AB",
    "sg:tags":[
        "anodizing"
    ],
    "wof:name":"Bluewave Anodizing",
    "wof:placetype":"venue"
},
  "geometry": {"coordinates":[-114.04322052000001,51.1208114624],"type":"Point"}
}