{
  "type": "Feature",
  "properties": {
    "iso:country":"CA",
    "sg:address":"5100 Appleby Line",
    "sg:city":"Milton",
    "sg:classifiers":[
        {
            "category":"Travel",
            "subcategory":"Campground",
            "type":"Entertainment"
        }
    ],
    "sg:phone":"+1 905 335 3849",
    "sg:postcode":"L9T 2Y1",
    "sg:province":"ON",
    "sg:tags":[
        "camp"
    ],
    "wof:name":"Sidrabene Camp",
    "wof:placetype":"venue"
},
  "geometry": {"coordinates":[-79.9486694336,43.4986190796],"type":"Point"}
}