{
  "type": "Feature",
  "properties": {
    "iso:country":"CA",
    "sg:address":"860 Gabriel Rd",
    "sg:city":"Grasswood",
    "sg:classifiers":[
        {
            "category":"Recreation",
            "type":"Entertainment"
        }
    ],
    "sg:phone":"+1 306 373 8582",
    "sg:postcode":"S7T 1A8",
    "sg:province":"SK",
    "sg:tags":[
        "stable"
    ],
    "wof:name":"Grasswood Stables",
    "wof:placetype":"venue"
},
  "geometry": {"coordinates":[-106.64862100000001,52.067238],"type":"Point"}
}