{
  "type": "Feature",
  "properties": {
    "addr:full":"St-Sauveur-Des-Monts QC J0R 1R0",
    "addr:postcode":"j0r 1r0",
    "iso:country":"CA",
    "sg:city":"St-Sauveur-Des-Monts",
    "sg:classifiers":[
        {
            "category":"Professional",
            "subcategory":"Accounting & Tax Preparation",
            "type":"Services"
        }
    ],
    "sg:phone":"+1 450 227 4641",
    "sg:postcode":"J0R 1R0",
    "sg:province":"QC",
    "sg:tags":[
        "accountant"
    ],
    "wof:name":"Gougeon Ouellette & Assoc CA",
    "wof:placetype":"venue"
},
  "geometry": {"coordinates":[-74.157066,45.893929],"type":"Point"}
}