{
  "type": "Feature",
  "properties": {
    "addr:full":"2121 Kingsway # 205 Vancouver BC V5N 2T4",
    "addr:housenumber":"2121;# 205",
    "addr:postcode":"v5n 2t4",
    "addr:street":"Kingsway",
    "iso:country":"CA",
    "sg:address":"2121 Kingsway # 205",
    "sg:city":"Vancouver",
    "sg:classifiers":[
        {
            "category":"Professional",
            "subcategory":"Accounting & Tax Preparation",
            "type":"Services"
        }
    ],
    "sg:phone":"+1 604 436 9294",
    "sg:postcode":"V5N 2T4",
    "sg:province":"BC",
    "sg:tags":[
        "accountant"
    ],
    "wof:name":"A-One Data Inc",
    "wof:placetype":"venue"
},
  "geometry": {"coordinates":[-123.063118,49.24437],"type":"Point"}
}