{
  "type": "Feature",
  "properties": {
    "addr:full":"6510 28 Ave NW Edmonton AB T6L 6N3",
    "addr:housenumber":"6510",
    "addr:postcode":"t6l 6n3",
    "addr:street":"28 Ave Nw",
    "iso:country":"CA",
    "sg:address":"6510 28 Ave NW",
    "sg:city":"Edmonton",
    "sg:classifiers":[
        {
            "category":"Restaurant",
            "type":"Food & Drink"
        }
    ],
    "sg:phone":"+1 780 450 1427",
    "sg:postcode":"T6L 6N3",
    "sg:province":"AB",
    "wof:name":"Wendy's",
    "wof:placetype":"venue"
},
  "geometry": {"coordinates":[-113.432495,53.458488],"type":"Point"}
}