{
  "type": "Feature",
  "properties": {
    "addr:full":"243 Water St Yarmouth NS B5A 1M1",
    "addr:housenumber":"243",
    "addr:postcode":"b5a 1m1",
    "addr:street":"Water St",
    "iso:country":"CA",
    "sg:address":"243 Water St",
    "sg:city":"Yarmouth",
    "sg:classifiers":[
        {
            "category":"Manufacturing",
            "subcategory":"Paper Products",
            "type":"Manufacturing & Wholesale Goods"
        }
    ],
    "sg:phone":"+1 902 742 1435",
    "sg:postcode":"B5A 1M1",
    "sg:province":"NS",
    "sg:tags":[
        "packaging",
        "material"
    ],
    "wof:name":"Tech Pak Canada Inc",
    "wof:placetype":"venue"
},
  "geometry": {"coordinates":[-66.121719,43.834431],"type":"Point"}
}