{
  "type": "Feature",
  "properties": {
    "addr:full":"Langley BC V1M 3A5",
    "addr:postcode":"v1m 3a5",
    "iso:country":"CA",
    "sg:city":"Langley",
    "sg:classifiers":[
        {
            "category":"Banks & Credit Unions",
            "subcategory":"Bank",
            "type":"Services"
        }
    ],
    "sg:phone":"+1 604 513 4440",
    "sg:postcode":"V1M 3A5",
    "sg:province":"BC",
    "sg:tags":[
        "financing"
    ],
    "wof:name":"Citi Capital Commercial Corp",
    "wof:placetype":"venue"
},
  "geometry": {"coordinates":[-122.65657043500001,49.1041221619],"type":"Point"}
}