{
  "type": "Feature",
  "properties": {
    "iso:country":"CA",
    "sg:city":"Langley",
    "sg:classifiers":[
        {
            "category":"Health Services",
            "subcategory":"Clinic",
            "type":"Services"
        }
    ],
    "sg:phone":"+1 604 533 8573",
    "sg:postcode":"V3A 4K7",
    "sg:province":"BC",
    "wof:name":"China Acupuncture & Herbal",
    "wof:placetype":"venue"
},
  "geometry": {"coordinates":[-122.661277771,49.10704422],"type":"Point"}
}