{
  "type": "Feature",
  "properties": {
    "addr:full":"13190 Keele St King City ON L7B 1J2",
    "addr:housenumber":"13190",
    "addr:postcode":"l7b 1j2",
    "addr:street":"Keele St",
    "iso:country":"CA",
    "sg:address":"13190 Keele St",
    "sg:city":"King City",
    "sg:classifiers":[
        {
            "category":"Social Services",
            "subcategory":"Child Care",
            "type":"Services"
        }
    ],
    "sg:phone":"+1 905 833 2971",
    "sg:postcode":"L7B 1J2",
    "sg:province":"ON",
    "sg:tags":[
        "kindergarten",
        "academic",
        "school"
    ],
    "wof:name":"King City Montessori School",
    "wof:placetype":"venue"
},
  "geometry": {"coordinates":[-79.52961000000001,43.93327],"type":"Point"}
}