{
  "type": "Feature",
  "properties": {
    "addr:full":"Barons AB T0L 0G0",
    "addr:postcode":"t0l 0g0",
    "iso:country":"CA",
    "sg:city":"Barons",
    "sg:classifiers":[
        {
            "category":"Shopping",
            "subcategory":"Clothing, Apparel, & Fashions",
            "type":"Retail Goods"
        }
    ],
    "sg:phone":"+1 403 757 2140",
    "sg:postcode":"T0L 0G0",
    "sg:province":"AB",
    "sg:tags":[
        "baby",
        "accessory"
    ],
    "wof:name":"Rad Enterprises",
    "wof:placetype":"venue"
},
  "geometry": {"coordinates":[-113.087234,49.99894],"type":"Point"}
}