{
  "type": "Feature",
  "properties": {
    "addr:full":"534 Buckingham Rd Winnipeg MB R3R 1C1",
    "addr:housenumber":"534",
    "addr:postcode":"r3r 1c1",
    "addr:street":"Buckingham Rd",
    "iso:country":"CA",
    "sg:address":"534 Buckingham Rd",
    "sg:city":"Winnipeg",
    "sg:classifiers":[
        {
            "category":"Building & Trades",
            "subcategory":"Construction",
            "type":"Services"
        }
    ],
    "sg:phone":"+1 204 837 5419",
    "sg:postcode":"R3R 1C1",
    "sg:province":"MB",
    "sg:tags":[
        "general",
        "contractor"
    ],
    "wof:name":"G Ross Building Construction",
    "wof:placetype":"venue"
},
  "geometry": {"coordinates":[-97.27997589109999,49.8567008972],"type":"Point"}
}