{
  "type": "Feature",
  "properties": {
    "addr:full":"110 Hunt St Ajax ON L1S 1P5",
    "addr:housenumber":"110",
    "addr:postcode":"l1s 1p5",
    "addr:street":"Hunt St",
    "iso:country":"CA",
    "sg:address":"110 Hunt St",
    "sg:city":"Ajax",
    "sg:classifiers":[
        {
            "category":"Professional",
            "subcategory":"Accounting & Tax Preparation",
            "type":"Services"
        }
    ],
    "sg:phone":"+1 905 683 8787",
    "sg:postcode":"L1S 1P5",
    "sg:province":"ON",
    "sg:tags":[
        "accountant"
    ],
    "wof:name":"Taylor, Ian M CA",
    "wof:placetype":"venue"
},
  "geometry": {"coordinates":[-79.023346,43.846813],"type":"Point"}
}