{
  "type": "Feature",
  "properties": {
    "addr:full":"4850 Rue DE Charleroi Montreal-Nord QC H1H 1V4",
    "addr:housenumber":"4850",
    "addr:postcode":"h1h 1v4",
    "addr:street":"Rue De Charleroi",
    "iso:country":"CA",
    "sg:address":"4850 Rue DE Charleroi",
    "sg:city":"Montreal-Nord",
    "sg:classifiers":[
        {
            "category":"Restaurant",
            "type":"Food & Drink"
        }
    ],
    "sg:phone":"+1 514 329 0666",
    "sg:postcode":"H1H 1V4",
    "sg:province":"QC",
    "wof:name":"Restaurant Boulangerie Patisse",
    "wof:placetype":"venue"
},
  "geometry": {"coordinates":[-73.630302,45.597168],"type":"Point"}
}