{
  "type": "Feature",
  "properties": {
    "addr:full":"6969 Airport Rd Mississauga ON L4V 1E9",
    "addr:housenumber":"6969",
    "addr:postcode":"l4v 1e9",
    "addr:street":"Airport Rd",
    "iso:country":"CA",
    "sg:address":"6969 Airport Rd",
    "sg:city":"Mississauga",
    "sg:classifiers":[
        {
            "category":"Retail",
            "subcategory":"Auto Repair",
            "type":"Services"
        }
    ],
    "sg:phone":"+1 905 677 3666",
    "sg:postcode":"L4V 1E9",
    "sg:province":"ON",
    "sg:tags":[
        "repairing",
        "automobile"
    ],
    "wof:name":"Appleton Motors Ltd",
    "wof:placetype":"venue"
},
  "geometry": {"coordinates":[-79.64035,43.702351],"type":"Point"}
}