{
  "type": "Feature",
  "properties": {
    "addr:full":"41 Rue Ambroise-Fafard # 1 Baie-Saint-Paul QC G3Z 2J2",
    "addr:housenumber":"41",
    "addr:postcode":"g3z 2j2",
    "addr:street":"Rue Ambroise-Fafard # 1",
    "iso:country":"CA",
    "sg:address":"41 Rue Ambroise-Fafard # 1",
    "sg:city":"Baie-Saint-Paul",
    "sg:classifiers":[
        {
            "category":"Shopping",
            "subcategory":"Bicycles & Sporting Goods",
            "type":"Retail Goods"
        }
    ],
    "sg:phone":"+1 418 240 4999",
    "sg:postcode":"G3Z 2J2",
    "sg:province":"QC",
    "wof:name":"P N Gariepy Inc Div Sport",
    "wof:placetype":"venue"
},
  "geometry": {"coordinates":[-70.50645400000001,47.438759],"type":"Point"}
}