{
  "type": "Feature",
  "properties": {
    "addr:full":"Sidney BC V8L 5X6",
    "addr:postcode":"v8l 5x6",
    "iso:country":"CA",
    "sg:city":"Sidney",
    "sg:classifiers":[
        {
            "category":"Shopping",
            "type":"Retail Goods"
        }
    ],
    "sg:phone":"+1 250 655 7121",
    "sg:postcode":"V8L 5X6",
    "sg:province":"BC",
    "sg:tags":[
        "equipment",
        "beer",
        "wine",
        "supply"
    ],
    "wof:name":"Peninsula-U-Brew",
    "wof:placetype":"venue"
},
  "geometry": {"coordinates":[-123.415672,48.656815],"type":"Point"}
}