{
  "type": "Feature",
  "properties": {
    "addr:full":"3757 43 Ave Red Deer AB T4N 3B7",
    "addr:housenumber":"3757",
    "addr:postcode":"t4n 3b7",
    "addr:street":"43 Ave",
    "iso:country":"CA",
    "sg:address":"3757 43 Ave",
    "sg:city":"Red Deer",
    "sg:classifiers":[
        {
            "category":"Shopping",
            "subcategory":"Pharmacy",
            "type":"Retail Goods"
        }
    ],
    "sg:phone":"+1 403 347 2345",
    "sg:postcode":"T4N 3B7",
    "sg:province":"AB",
    "wof:name":"Sproule's Mountview Ida Drug",
    "wof:placetype":"venue"
},
  "geometry": {"coordinates":[-113.795715332,52.2578887939],"type":"Point"}
}