{
  "type": "Feature",
  "properties": {
    "iso:country":"CA",
    "sg:address":"1244 Tsse Dupont",
    "sg:city":"Laval",
    "sg:classifiers":[
        {
            "category":"Professional",
            "subcategory":"Business Services",
            "type":"Services"
        }
    ],
    "sg:phone":"+1 450 969 3131",
    "sg:postcode":"H7Y 1E9",
    "sg:province":"QC",
    "sg:tags":[
        "notary"
    ],
    "wof:name":"Levesque, Brigitte",
    "wof:placetype":"venue"
},
  "geometry": {"coordinates":[-73.85186,45.522858],"type":"Point"}
}