{
  "type": "Feature",
  "properties": {
    "addr:full":"14303 Trafalgar Rd N Ballinafad ON N0B 1H0",
    "addr:housenumber":"14303",
    "addr:postcode":"n0b 1h0",
    "addr:street":"Trafalgar Rd N Ballinafad",
    "iso:country":"CA",
    "sg:address":"14303 Trafalgar Rd N",
    "sg:city":"Ballinafad",
    "sg:classifiers":[
        {
            "category":"Food & Beverages",
            "subcategory":"Groceries & Convenience Stores",
            "type":"Retail Goods"
        }
    ],
    "sg:phone":"+1 905 877 3392",
    "sg:postcode":"N0B 1H0",
    "sg:province":"ON",
    "sg:tags":[
        "grocer"
    ],
    "wof:name":"Ballinafad Farm Market",
    "wof:placetype":"venue"
},
  "geometry": {"coordinates":[-80.00872,43.693745],"type":"Point"}
}