{
  "type": "Feature",
  "properties": {
    "addr:full":"Main St Birtle MB R0M 0C0",
    "addr:postcode":"r0m 0c0",
    "addr:street":"Main St",
    "iso:country":"CA",
    "sg:address":"Main St",
    "sg:city":"Birtle",
    "sg:classifiers":[
        {
            "category":"Government",
            "subcategory":"Office",
            "type":"Public Place"
        }
    ],
    "sg:phone":"+1 204 842 3403",
    "sg:postcode":"R0M 0C0",
    "sg:province":"MB",
    "sg:tags":[
        "village"
    ],
    "wof:name":"Birtle Rural Municipality Ofc",
    "wof:placetype":"venue"
},
  "geometry": {"coordinates":[-101.04576900000001,50.422134],"type":"Point"}
}