{
  "type": "Feature",
  "properties": {
    "addr:full":"7005 Boul DE Maisonneuve O Montreal QC H4B 1T3",
    "addr:housenumber":"7005",
    "addr:postcode":"h4b 1t3",
    "addr:street":"Boul De Maisonneuve O",
    "iso:country":"CA",
    "sg:address":"7005 Boul DE Maisonneuve O",
    "sg:city":"Montreal",
    "sg:classifiers":[
        {
            "category":"Shopping",
            "type":"Retail Goods"
        }
    ],
    "sg:phone":"+1 514 487 1770",
    "sg:postcode":"H4B 1T3",
    "sg:province":"QC",
    "sg:tags":[
        "orthopedic",
        "appliance",
        "rehabilitation"
    ],
    "wof:name":"Centre-Readaptation Constance",
    "wof:placetype":"venue"
},
  "geometry": {"coordinates":[-73.63279,45.458645],"type":"Point"}
}