{
  "type": "Feature",
  "properties": {
    "addr:full":"Vanier QC G1M 3H6",
    "addr:postcode":"g1m 3h6",
    "iso:country":"CA",
    "sg:city":"Vanier",
    "sg:classifiers":[
        {
            "category":"Social Services",
            "type":"Services"
        }
    ],
    "sg:phone":"+1 418 527 8097",
    "sg:postcode":"G1M 3H6",
    "sg:province":"QC",
    "sg:tags":[
        "organization",
        "welfare"
    ],
    "wof:name":"Centre DE Parrainage Civique",
    "wof:placetype":"venue"
},
  "geometry": {"coordinates":[-71.252388,46.818192],"type":"Point"}
}