{
  "type": "Feature",
  "properties": {
    "addr:full":"15350 114 Ave NW Edmonton AB T5M 2Z2",
    "addr:housenumber":"15350",
    "addr:postcode":"t5m 2z2",
    "addr:street":"114 Ave Nw",
    "iso:country":"CA",
    "sg:address":"15350 114 Ave NW",
    "sg:city":"Edmonton",
    "sg:classifiers":[
        {
            "category":"Manufacturing",
            "subcategory":"Tools & Machinery",
            "type":"Manufacturing & Wholesale Goods"
        }
    ],
    "sg:phone":"+1 780 447 2370",
    "sg:postcode":"T5M 2Z2",
    "sg:province":"AB",
    "sg:tags":[
        "machine",
        "shop"
    ],
    "wof:name":"J V Machine & Power Train Wrks",
    "wof:placetype":"venue"
},
  "geometry": {"coordinates":[-113.585739,53.563316],"type":"Point"}
}