{
  "type": "Feature",
  "properties": {
    "addr:full":"970 Syscon Rd Burlington ON L7L 5S2",
    "addr:housenumber":"970",
    "addr:postcode":"l7l 5s2",
    "addr:street":"Syscon Rd",
    "iso:country":"CA",
    "sg:address":"970 Syscon Rd",
    "sg:city":"Burlington",
    "sg:classifiers":[
        {
            "category":"Manufacturing",
            "subcategory":"Tools & Machinery",
            "type":"Manufacturing & Wholesale Goods"
        }
    ],
    "sg:phone":"+1 905 681 8575",
    "sg:postcode":"L7L 5S2",
    "sg:province":"ON",
    "sg:tags":[
        "equipment",
        "system",
        "automation"
    ],
    "wof:name":"Flow Automation",
    "wof:placetype":"venue"
},
  "geometry": {"coordinates":[-79.75752300000001,43.392357],"type":"Point"}
}