{
  "type": "Feature",
  "properties": {
    "addr:full":"351 Rue Emery Montreal QC H2X 1J2",
    "addr:housenumber":"351",
    "addr:postcode":"h2x 1j2",
    "addr:street":"Rue Emery",
    "iso:country":"CA",
    "sg:address":"351 Rue Emery",
    "sg:city":"Montreal",
    "sg:classifiers":[
        {
            "category":"Wholesale",
            "subcategory":"Groceries",
            "type":"Manufacturing & Wholesale Goods"
        }
    ],
    "sg:phone":"+1 514 286 4002",
    "sg:postcode":"H2X 1J2",
    "sg:province":"QC",
    "sg:tags":[
        "tea"
    ],
    "wof:name":"Maison DE the Camellia",
    "wof:placetype":"venue"
},
  "geometry": {"coordinates":[-73.563858,45.514626],"type":"Point"}
}