{
  "type": "Feature",
  "properties": {
    "addr:full":"526 South Service Rd Mississauga ON L5G 2S6",
    "addr:housenumber":"526",
    "addr:postcode":"l5g 2s6",
    "addr:street":"South Service",
    "iso:country":"CA",
    "sg:address":"526 South Service Rd",
    "sg:city":"Mississauga",
    "sg:classifiers":[
        {
            "category":"Retail",
            "subcategory":"Auto Repair",
            "type":"Services"
        }
    ],
    "sg:phone":"+1 905 271 5844",
    "sg:postcode":"L5G 2S6",
    "sg:province":"ON",
    "sg:tags":[
        "repairing",
        "automobile"
    ],
    "wof:name":"Ruffo Brothers Car Care Ltd",
    "wof:placetype":"venue"
},
  "geometry": {"coordinates":[-79.587059021,43.5793685913],"type":"Point"}
}