{
  "type": "Feature",
  "properties": {
    "addr:full":"3895 Hwy 35 Dwight ON P0A 1H0",
    "addr:housenumber":"3895",
    "addr:postcode":"p0a 1h0",
    "addr:street":"Hwy 35",
    "iso:country":"CA",
    "sg:address":"3895 Hwy 35",
    "sg:city":"Dwight",
    "sg:classifiers":[
        {
            "category":"Building & Trades",
            "subcategory":"Construction",
            "type":"Services"
        }
    ],
    "sg:phone":"+1 705 635 2341",
    "sg:postcode":"P0A 1H0",
    "sg:province":"ON",
    "sg:tags":[
        "excavating",
        "contractor"
    ],
    "wof:name":"Fred Boothby Contracting",
    "wof:placetype":"venue"
},
  "geometry": {"coordinates":[-78.963455,45.288769],"type":"Point"}
}