{
  "type": "Feature",
  "properties": {
    "addr:full":"635 Queen St E Toronto ON M4M 1G4",
    "addr:housenumber":"635",
    "addr:postcode":"m4m 1g4",
    "addr:street":"Queen St E",
    "iso:country":"CA",
    "sg:address":"635 Queen St E",
    "sg:city":"Toronto",
    "sg:classifiers":[
        {
            "category":"Professional",
            "subcategory":"Advertising",
            "type":"Services"
        }
    ],
    "sg:phone":"+1 416 778 5597",
    "sg:postcode":"M4M 1G4",
    "sg:province":"ON",
    "sg:tags":[
        "counselor"
    ],
    "wof:name":"Broadcast Clearance Advisory",
    "wof:placetype":"venue"
},
  "geometry": {"coordinates":[-79.35253899999999,43.658119],"type":"Point"}
}