{
  "type": "Feature",
  "properties": {
    "addr:full":"4320 81 Ave NW Edmonton AB T6B 2M2",
    "addr:housenumber":"4320",
    "addr:postcode":"t6b 2m2",
    "addr:street":"81 Ave Nw",
    "iso:country":"CA",
    "sg:address":"4320 81 Ave NW",
    "sg:city":"Edmonton",
    "sg:classifiers":[
        {
            "category":"Manufacturing",
            "subcategory":"Rubber & Plastics",
            "type":"Manufacturing & Wholesale Goods"
        }
    ],
    "sg:phone":"+1 780 440 5054",
    "sg:postcode":"T6B 2M2",
    "sg:province":"AB",
    "wof:name":"Urban Plastics",
    "wof:placetype":"venue"
},
  "geometry": {"coordinates":[-113.408462524,53.516418457],"type":"Point"}
}