{
  "type": "Feature",
  "properties": {
    "addr:full":"North York ON M3N 1W3",
    "addr:postcode":"m3n 1w3",
    "iso:country":"CA",
    "sg:city":"North York",
    "sg:classifiers":[
        {
            "category":"Professional",
            "subcategory":"Business Services",
            "type":"Services"
        }
    ],
    "sg:phone":"+1 416 740 6120",
    "sg:postcode":"M3N 1W3",
    "sg:province":"ON",
    "wof:name":"Alm Carpet Machinery",
    "wof:placetype":"venue"
},
  "geometry": {"coordinates":[-79.52562,43.741772],"type":"Point"}
}