{
  "type": "Feature",
  "properties": {
    "addr:full":"9333 41 Ave NW Edmonton AB T6E 6R5",
    "addr:housenumber":"9333",
    "addr:postcode":"t6e 6r5",
    "addr:street":"41 Ave Nw",
    "iso:country":"CA",
    "sg:address":"9333 41 Ave NW",
    "sg:city":"Edmonton",
    "sg:classifiers":[
        {
            "category":"Manufacturing",
            "subcategory":"Tools & Machinery",
            "type":"Manufacturing & Wholesale Goods"
        }
    ],
    "sg:phone":"+1 780 465 7812",
    "sg:postcode":"T6E 6R5",
    "sg:province":"AB",
    "sg:tags":[
        "pump"
    ],
    "wof:name":"Bowie Pumps of Canada Ltd",
    "wof:placetype":"venue"
},
  "geometry": {"coordinates":[-113.472900391,53.4762458801],"type":"Point"}
}