{
  "type": "Feature",
  "properties": {
    "addr:full":"Winfield AB T0C 2X0",
    "addr:postcode":"t0c 2x0",
    "iso:country":"CA",
    "sg:city":"Winfield",
    "sg:classifiers":[
        {
            "category":"Mining & Drilling",
            "type":"Manufacturing & Wholesale Goods"
        }
    ],
    "sg:phone":"+1 780 682 3738",
    "sg:postcode":"T0C 2X0",
    "sg:province":"AB",
    "sg:tags":[
        "field",
        "oil"
    ],
    "wof:name":"Maverick Supply Ltd",
    "wof:placetype":"venue"
},
  "geometry": {"coordinates":[-114.427841,52.964626],"type":"Point"}
}