{
  "type": "Feature",
  "properties": {
    "iso:country":"CA",
    "sg:address":"45 Rue Front",
    "sg:city":"Aylmer",
    "sg:classifiers":[
        {
            "category":"Retail",
            "subcategory":"Auto Repair",
            "type":"Services"
        }
    ],
    "sg:phone":"+1 819 684 6923",
    "sg:postcode":"J9H 6N7",
    "sg:province":"QC",
    "sg:tags":[
        "body",
        "automobile",
        "painting"
    ],
    "wof:name":"Atelier DE Debosselage",
    "wof:placetype":"venue"
},
  "geometry": {"coordinates":[-75.8551025391,45.3982887268],"type":"Point"}
}