{
  "type": "Feature",
  "properties": {
    "addr:full":"2200 8th St E Saskatoon SK S7H 0V3",
    "addr:housenumber":"2200",
    "addr:postcode":"s7h 0v3",
    "addr:street":"8Th St E",
    "iso:country":"CA",
    "sg:address":"2200 8th St E",
    "sg:city":"Saskatoon",
    "sg:classifiers":[
        {
            "category":"Autos & Motor Vehicles",
            "subcategory":"Automobile Sales",
            "type":"Retail Goods"
        }
    ],
    "sg:phone":"+1 306 374 2120",
    "sg:postcode":"S7H 0V3",
    "sg:province":"SK",
    "sg:tags":[
        "car",
        "dealer"
    ],
    "wof:name":"Dodge City",
    "wof:placetype":"venue"
},
  "geometry": {"coordinates":[-106.622551,52.114639],"type":"Point"}
}