{
  "type": "Feature",
  "properties": {
    "addr:full":"Amqui QC G5J 3G3",
    "addr:postcode":"g5j 3g3",
    "iso:country":"CA",
    "sg:city":"Amqui",
    "sg:classifiers":[
        {
            "category":"Wholesale",
            "subcategory":"Electrical",
            "type":"Manufacturing & Wholesale Goods"
        }
    ],
    "sg:phone":"+1 418 629 2699",
    "sg:postcode":"G5J 3G3",
    "sg:province":"QC",
    "sg:tags":[
        "electric",
        "motor"
    ],
    "wof:name":"Amqui Moteurs Enr",
    "wof:placetype":"venue"
},
  "geometry": {"coordinates":[-67.433426,48.464005],"type":"Point"}
}