{
  "type": "Feature",
  "properties": {
    "iso:country":"CA",
    "sg:address":"318 1 St W",
    "sg:city":"Cochrane",
    "sg:classifiers":[
        {
            "category":"Shopping",
            "subcategory":"Florist",
            "type":"Retail Goods"
        }
    ],
    "sg:phone":"+1 403 932 3225",
    "sg:postcode":"T4C 1A4",
    "sg:province":"AB",
    "wof:name":"Just For You Flowers & More",
    "wof:placetype":"venue"
},
  "geometry": {"coordinates":[-114.461708069,51.1879234314],"type":"Point"}
}