{
  "type": "Feature",
  "properties": {
    "addr:full":"Prince Albert SK S6V 0Y7",
    "addr:postcode":"s6v 0y7",
    "iso:country":"CA",
    "sg:city":"Prince Albert",
    "sg:classifiers":[
        {
            "category":"Shopping",
            "subcategory":"Books",
            "type":"Retail Goods"
        }
    ],
    "sg:phone":"+1 306 922 5655",
    "sg:postcode":"S6V 0Y7",
    "sg:province":"SK",
    "sg:tags":[
        "dealer"
    ],
    "wof:name":"New Way Bible Book Store",
    "wof:placetype":"venue"
},
  "geometry": {"coordinates":[-105.75126648,53.2041244507],"type":"Point"}
}