{
  "type": "Feature",
  "properties": {
    "iso:country":"CA",
    "sg:address":"3000 Sandlewood Court",
    "sg:city":"Burlington",
    "sg:classifiers":[
        {
            "category":"Professional",
            "subcategory":"Computer Services",
            "type":"Services"
        }
    ],
    "sg:postcode":"L7M 3A4",
    "sg:tags":[
        "mangaroo-media-inc",
        "www-ratesupermarket-ca",
        "canadian-online-media-publisher",
        "canadian-mortgage-rate-comparison-site",
        "mortgage-rates-canada"
    ],
    "sg:website":"http://mangaroomedia.com",
    "wof:name":"Mangaroo Media",
    "wof:placetype":"venue"
},
  "geometry": {"coordinates":[-79.82438399999999,43.366842],"type":"Point"}
}