{
  "type": "Feature",
  "properties": {
    "addr:full":"6th St Battleford SK S0M 0E0",
    "addr:postcode":"s0m 0e0",
    "addr:street":"6Th St",
    "iso:country":"CA",
    "sg:address":"6th St",
    "sg:city":"Battleford",
    "sg:classifiers":[
        {
            "category":"Manufacturing",
            "subcategory":"Printing",
            "type":"Manufacturing & Wholesale Goods"
        }
    ],
    "sg:phone":"+1 306 937 7771",
    "sg:postcode":"S0M 0E0",
    "sg:province":"SK",
    "sg:tags":[
        "printer"
    ],
    "wof:name":"Marian Press Ltd",
    "wof:placetype":"venue"
},
  "geometry": {"coordinates":[-108.31314086899999,52.7362365723],"type":"Point"}
}