{
  "type": "Feature",
  "properties": {
    "addr:full":"316 Curling St Corner Brook NL A2H 3J7",
    "addr:housenumber":"316",
    "addr:postcode":"a2h 3j7",
    "addr:street":"Curling St",
    "iso:country":"CA",
    "sg:address":"316 Curling St",
    "sg:city":"Corner Brook",
    "sg:classifiers":[
        {
            "category":"Building & Trades",
            "subcategory":"Construction",
            "type":"Services"
        }
    ],
    "sg:phone":"+1 709 634 4884",
    "sg:postcode":"A2H 3J7",
    "sg:province":"NL",
    "sg:tags":[
        "contractor"
    ],
    "wof:name":"C & M Building Contractors",
    "wof:placetype":"venue"
},
  "geometry": {"coordinates":[-57.994072,48.958042],"type":"Point"}
}