{
  "type": "Feature",
  "properties": {
    "addr:full":"102 Industrial Rd Richmond Hill ON L4C 2Y3",
    "addr:housenumber":"102",
    "addr:postcode":"l4c 2y3",
    "addr:street":"Industrial Rd",
    "iso:country":"CA",
    "sg:address":"102 Industrial Rd",
    "sg:city":"Richmond Hill",
    "sg:classifiers":[
        {
            "category":"Retail",
            "subcategory":"Auto Repair",
            "type":"Services"
        }
    ],
    "sg:phone":"+1 905 883 6404",
    "sg:postcode":"L4C 2Y3",
    "sg:province":"ON",
    "sg:tags":[
        "body",
        "automobile",
        "painting"
    ],
    "wof:name":"Maaco Auto Painting & Bodywork",
    "wof:placetype":"venue"
},
  "geometry": {"coordinates":[-79.43692016599999,43.8873558044],"type":"Point"}
}