{
  "type": "Feature",
  "properties": {
    "addr:full":"Calgary AB T2H 0C6",
    "addr:postcode":"t2h 0c6",
    "iso:country":"CA",
    "sg:city":"Calgary",
    "sg:classifiers":[
        {
            "category":"Personal",
            "subcategory":"Beauty Salon",
            "type":"Services"
        }
    ],
    "sg:phone":"+1 403 255 9396",
    "sg:postcode":"T2H 0C6",
    "sg:province":"AB",
    "wof:name":"Lavoomm Hair & Tanning Salon",
    "wof:placetype":"venue"
},
  "geometry": {"coordinates":[-114.063614,50.994827],"type":"Point"}
}