{
  "type": "Feature",
  "properties": {
    "addr:full":"350 Dundas St London ON N6B 1V7",
    "addr:housenumber":"350",
    "addr:postcode":"n6b 1v7",
    "addr:street":"Dundas St",
    "iso:country":"CA",
    "sg:address":"350 Dundas St",
    "sg:city":"London",
    "sg:classifiers":[
        {
            "category":"Personal",
            "subcategory":"Beauty Salon",
            "type":"Services"
        }
    ],
    "sg:phone":"+1 519 642 7775",
    "sg:postcode":"N6B 1V7",
    "sg:province":"ON",
    "wof:name":"David Mc Dermott Hair Salon",
    "wof:placetype":"venue"
},
  "geometry": {"coordinates":[-81.24189,42.986038],"type":"Point"}
}