{
  "type": "Feature",
  "properties": {
    "iso:country":"CA",
    "sg:city":"Red Deer",
    "sg:classifiers":[
        {
            "category":"Personal",
            "type":"Services"
        }
    ],
    "sg:phone":"+1 403 343 7333",
    "sg:postcode":"T4R 1N9",
    "sg:province":"AB",
    "sg:tags":[
        "ear",
        "piercing"
    ],
    "wof:name":"Claire's Boutique",
    "wof:placetype":"venue"
},
  "geometry": {"coordinates":[-113.807006836,52.2450561523],"type":"Point"}
}