{
  "type": "Feature",
  "properties": {
    "addr:full":"7431 113 St Delta BC V4C 5B2",
    "addr:housenumber":"7431",
    "addr:postcode":"v4c 5b2",
    "addr:street":"113 St",
    "iso:country":"CA",
    "sg:address":"7431 113 St",
    "sg:city":"Delta",
    "sg:classifiers":[
        {
            "category":"Shopping",
            "subcategory":"Computers & Home Electronics",
            "type":"Retail Goods"
        }
    ],
    "sg:phone":"+1 604 590 8478",
    "sg:postcode":"V4C 5B2",
    "sg:province":"BC",
    "sg:tags":[
        "equipment",
        "dealer"
    ],
    "wof:name":"Light Stream Resources",
    "wof:placetype":"venue"
},
  "geometry": {"coordinates":[-122.909035,49.138084],"type":"Point"}
}