{
  "type": "Feature",
  "properties": {
    "addr:full":"Kamloops BC V2C 5P4",
    "addr:postcode":"bc v2c 5p4",
    "iso:country":"CA",
    "sg:city":"Kamloops",
    "sg:classifiers":[
        {
            "category":"Shopping",
            "subcategory":"Bicycles & Sporting Goods",
            "type":"Retail Goods"
        }
    ],
    "sg:phone":"+1 250 851 8368",
    "sg:postcode":"V2C 5P4",
    "sg:province":"BC",
    "sg:tags":[
        "equipment",
        "camping"
    ],
    "wof:name":"Interior Display Svc",
    "wof:placetype":"venue"
},
  "geometry": {"coordinates":[-120.363457,50.659306],"type":"Point"}
}