{
  "type": "Feature",
  "properties": {
    "addr:full":"721 Main St Dartmouth NS B2W 3T6",
    "addr:housenumber":"721",
    "addr:postcode":"b2w 3t6",
    "addr:street":"Main St",
    "iso:country":"CA",
    "sg:address":"721 Main St",
    "sg:city":"Dartmouth",
    "sg:classifiers":[
        {
            "category":"Retail",
            "subcategory":"Veterinary Services",
            "type":"Services"
        }
    ],
    "sg:phone":"+1 902 434 4446",
    "sg:postcode":"B2W 3T6",
    "sg:province":"NS",
    "sg:tags":[
        "veterinarian"
    ],
    "wof:name":"Acres Animal Hospital",
    "wof:placetype":"venue"
},
  "geometry": {"coordinates":[-63.4946136475,44.6975250244],"type":"Point"}
}