{
  "type": "Feature",
  "properties": {
    "addr:full":"869 Bank St Ottawa ON K1S 3W4",
    "addr:housenumber":"869",
    "addr:postcode":"k1s 3w4",
    "addr:street":"Bank St",
    "iso:country":"CA",
    "sg:address":"869 Bank St",
    "sg:city":"Ottawa",
    "sg:classifiers":[
        {
            "category":"Wholesale",
            "subcategory":"Meat",
            "type":"Manufacturing & Wholesale Goods"
        }
    ],
    "sg:phone":"+1 613 235 9595",
    "sg:postcode":"K1S 3W4",
    "sg:province":"ON",
    "sg:tags":[
        "butchering"
    ],
    "wof:name":"Glebe Meat Market Ltd",
    "wof:placetype":"venue"
},
  "geometry": {"coordinates":[-75.68706512449999,45.4009284973],"type":"Point"}
}