{
  "type": "Feature",
  "properties": {
    "iso:country":"CA",
    "sg:address":"448 Ritson Rd S",
    "sg:city":"Oshawa",
    "sg:classifiers":[
        {
            "category":"Manufacturing",
            "subcategory":"Tools & Machinery",
            "type":"Manufacturing & Wholesale Goods"
        }
    ],
    "sg:phone":"+1 905 723 5535",
    "sg:postcode":"L1H 5J9",
    "sg:province":"ON",
    "sg:tags":[
        "electric",
        "motor"
    ],
    "wof:name":"South End Pump Inc",
    "wof:placetype":"venue"
},
  "geometry": {"coordinates":[-78.84874725340001,43.8883781433],"type":"Point"}
}