{
  "type": "Feature",
  "properties": {
    "addr:full":"18543 Fraser Hwy Surrey BC V3S 8E7",
    "addr:housenumber":"18543",
    "addr:postcode":"v3s 8e7",
    "addr:street":"Fraser Hwy",
    "iso:country":"CA",
    "sg:address":"18543 Fraser Hwy",
    "sg:city":"Surrey",
    "sg:classifiers":[
        {
            "category":"Home & Garden",
            "subcategory":"Household Appliances",
            "type":"Retail Goods"
        }
    ],
    "sg:phone":"+1 604 574 5333",
    "sg:postcode":"V3S 8E7",
    "sg:province":"BC",
    "sg:tags":[
        "machine",
        "sewing"
    ],
    "wof:name":"Castle Sewing Ctr",
    "wof:placetype":"venue"
},
  "geometry": {"coordinates":[-122.70860290500001,49.1271095276],"type":"Point"}
}