{
  "type": "Feature",
  "properties": {
    "addr:full":"3050 Aurora Lloydtown Rd Kettleby ON L0G 1J0",
    "addr:housenumber":"3050",
    "addr:postcode":"l0g 1j0",
    "addr:street":"Aurora Lloydtown Rd",
    "iso:country":"CA",
    "sg:address":"3050 Aurora Lloydtown Rd",
    "sg:city":"Kettleby",
    "sg:classifiers":[
        {
            "category":"Food & Beverages",
            "subcategory":"Specialty",
            "type":"Retail Goods"
        }
    ],
    "sg:phone":"+1 905 727 9097",
    "sg:postcode":"L0G 1J0",
    "sg:province":"ON",
    "sg:tags":[
        "water",
        "bulk",
        "company"
    ],
    "wof:name":"James Morning & Sons Ltd",
    "wof:placetype":"venue"
},
  "geometry": {"coordinates":[-79.575378418,44.0050735474],"type":"Point"}
}