{
  "type": "Feature",
  "properties": {
    "addr:full":"297 Nash Rd N Hamilton ON L8H 7P4",
    "addr:housenumber":"297",
    "addr:postcode":"l8h 7p4",
    "addr:street":"Nash Rd N",
    "iso:country":"CA",
    "sg:address":"297 Nash Rd N",
    "sg:city":"Hamilton",
    "sg:classifiers":[
        {
            "category":"Utilities",
            "subcategory":"Mobile Phone",
            "type":"Services"
        }
    ],
    "sg:phone":"+1 905 573 2388",
    "sg:postcode":"L8H 7P4",
    "sg:province":"ON",
    "sg:tags":[
        "communication",
        "radio",
        "telephone",
        "cellular",
        "system"
    ],
    "wof:name":"Mobile Communication Svc",
    "wof:placetype":"venue"
},
  "geometry": {"coordinates":[-79.770073,43.240025],"type":"Point"}
}