{
  "type": "Feature",
  "properties": {
    "addr:full":"1008 Victoria Ave E Thunder Bay ON P7C 1B6",
    "addr:housenumber":"1008",
    "addr:postcode":"p7c 1b6",
    "addr:street":"Victoria Ave E",
    "iso:country":"CA",
    "sg:address":"1008 Victoria Ave E",
    "sg:city":"Thunder Bay",
    "sg:classifiers":[
        {
            "category":"Personal",
            "type":"Services"
        }
    ],
    "sg:phone":"+1 807 623 5422",
    "sg:postcode":"P7C 1B6",
    "sg:province":"ON",
    "sg:tags":[
        "program",
        "physical",
        "exercise",
        "fitness"
    ],
    "wof:name":"Fitness Plus",
    "wof:placetype":"venue"
},
  "geometry": {"coordinates":[-89.25137329099999,48.3839988708],"type":"Point"}
}