{
  "type": "Feature",
  "properties": {
    "iso:country":"CA",
    "sg:city":"Vancouver",
    "sg:classifiers":[
        {
            "category":"Building & Trades",
            "subcategory":"Construction",
            "type":"Services"
        }
    ],
    "sg:phone":"+1 604 327 1096",
    "sg:postcode":"V5P 2S7",
    "sg:province":"BC",
    "sg:tags":[
        "woodworker"
    ],
    "wof:name":"Radical Wookworking",
    "wof:placetype":"venue"
},
  "geometry": {"coordinates":[-123.073135,49.20911],"type":"Point"}
}