{
  "type": "Feature",
  "properties": {
    "addr:full":"838 Mcintosh St Foam Lake SK S0A 1A0",
    "addr:housenumber":"838",
    "addr:postcode":"s0a 1a0",
    "addr:street":"Mcintosh St",
    "iso:country":"CA",
    "sg:address":"838 Mcintosh St",
    "sg:city":"Foam Lake",
    "sg:classifiers":[
        {
            "category":"Banks & Credit Unions",
            "subcategory":"Investment Brokerage",
            "type":"Services"
        }
    ],
    "sg:phone":"+1 306 272 4405",
    "sg:postcode":"S0A 1A0",
    "sg:province":"SK",
    "sg:tags":[
        "consultant",
        "planning",
        "financial"
    ],
    "wof:name":"Investors Group Financial Svc",
    "wof:placetype":"venue"
},
  "geometry": {"coordinates":[-103.53939099999999,51.639305],"type":"Point"}
}