{
  "type": "Feature",
  "properties": {
    "addr:full":"451 Rue Desrosiers Sainte-Emelie-DE-L'Energie QC J0K 2K0",
    "addr:housenumber":"451",
    "addr:postcode":"j0k 2k0",
    "addr:street":"Rue Desrosiers Sainte-Emelie-De-L'Energie",
    "iso:country":"CA",
    "sg:address":"451 Rue Desrosiers",
    "sg:city":"Sainte-Emelie-DE-L'Energie",
    "sg:classifiers":[
        {
            "category":"Personal",
            "subcategory":"Beauty Salon",
            "type":"Services"
        }
    ],
    "sg:phone":"+1 450 886 9882",
    "sg:postcode":"J0K 2K0",
    "sg:province":"QC",
    "wof:name":"Salon DE Coiffure Isabelle",
    "wof:placetype":"venue"
},
  "geometry": {"coordinates":[-73.6409,46.323483],"type":"Point"}
}