{
  "type": "Feature",
  "properties": {
    "addr:full":"1668 Victoria Park Ave North York ON M1R 1P7",
    "addr:housenumber":"1668",
    "addr:postcode":"m1r 1p7",
    "addr:street":"Victoria Park Ave",
    "iso:country":"CA",
    "sg:address":"1668 Victoria Park Ave",
    "sg:city":"North York",
    "sg:classifiers":[
        {
            "category":"Health Services",
            "subcategory":"Doctor",
            "type":"Services"
        }
    ],
    "sg:phone":"+1 416 759 6723",
    "sg:postcode":"M1R 1P7",
    "sg:province":"ON",
    "sg:tags":[
        "physician",
        "surgeon"
    ],
    "wof:name":"Tam, Christopher MD",
    "wof:placetype":"venue"
},
  "geometry": {"coordinates":[-79.30592346189999,43.7321929932],"type":"Point"}
}