{
  "type": "Feature",
  "properties": {
    "addr:full":"242 Frigate Rd Bamfield BC V0R 1B0",
    "addr:housenumber":"242",
    "addr:postcode":"v0r 1b0",
    "addr:street":"Frigate Rd",
    "iso:country":"CA",
    "sg:address":"242 Frigate Rd",
    "sg:city":"Bamfield",
    "sg:classifiers":[
        {
            "category":"Food & Beverages",
            "subcategory":"Groceries & Convenience Stores",
            "type":"Retail Goods"
        }
    ],
    "sg:phone":"+1 250 728 2000",
    "sg:postcode":"V0R 1B0",
    "sg:province":"BC",
    "sg:tags":[
        "market"
    ],
    "wof:name":"Tides & Trails Market",
    "wof:placetype":"venue"
},
  "geometry": {"coordinates":[-125.133926,48.825897],"type":"Point"}
}