{
  "type": "Feature",
  "properties": {
    "addr:full":"101 Sasaga Dr Kitchener ON N2C 2G8",
    "addr:housenumber":"101",
    "addr:postcode":"n2c 2g8",
    "addr:street":"Sasaga Dr",
    "iso:country":"CA",
    "sg:address":"101 Sasaga Dr",
    "sg:city":"Kitchener",
    "sg:classifiers":[
        {
            "category":"Manufacturing",
            "subcategory":"Chemicals & Compounds",
            "type":"Manufacturing & Wholesale Goods"
        }
    ],
    "sg:phone":"+1 519 748 5576",
    "sg:postcode":"N2C 2G8",
    "sg:province":"ON",
    "sg:tags":[
        "plastic"
    ],
    "wof:name":"Ampacet Canada CO",
    "wof:placetype":"venue"
},
  "geometry": {"coordinates":[-80.4507827759,43.4063262939],"type":"Point"}
}