{
  "type": "Feature",
  "properties": {
    "addr:full":"435 Rue Jarry E Montreal QC H2P 1V2",
    "addr:housenumber":"435",
    "addr:postcode":"h2p 1v2",
    "addr:street":"Rue Jarry E",
    "iso:country":"CA",
    "sg:address":"435 Rue Jarry E",
    "sg:city":"Montreal",
    "sg:classifiers":[
        {
            "category":"Food & Beverages",
            "subcategory":"Fruits & Vegetables",
            "type":"Retail Goods"
        }
    ],
    "sg:phone":"+1 514 389 3804",
    "sg:postcode":"H2P 1V2",
    "sg:province":"QC",
    "sg:tags":[
        "produce"
    ],
    "wof:name":"Fruiterie Forcier Enr",
    "wof:placetype":"venue"
},
  "geometry": {"coordinates":[-73.6292190552,45.5428886414],"type":"Point"}
}