{
  "type": "Feature",
  "properties": {
    "iso:country":"CA",
    "sg:address":"2855 Rue Le Noblet",
    "sg:city":"Sainte-Foy",
    "sg:classifiers":[
        {
            "category":"Health Services",
            "subcategory":"Hospital",
            "type":"Services"
        }
    ],
    "sg:phone":"+1 418 657 2227",
    "sg:postcode":"G1V 2G1",
    "sg:province":"QC",
    "sg:tags":[
        "mental"
    ],
    "wof:name":"Verger Centre Communautaire",
    "wof:placetype":"venue"
},
  "geometry": {"coordinates":[-71.29229,46.770828],"type":"Point"}
}