{
  "type": "Feature",
  "properties": {
    "addr:full":"2855 Rue Le Noblet Sainte-Foy QC G1V 2G1",
    "addr:housenumber":"2855",
    "addr:postcode":"g1v 2g1",
    "addr:street":"Rue Le Noblet",
    "iso:country":"CA",
    "sg:address":"2855 Rue Le Noblet",
    "sg:city":"Sainte-Foy",
    "sg:classifiers":[
        {
            "category":"Health Services",
            "subcategory":"Hospital",
            "type":"Services"
        }
    ],
    "sg:phone":"+1 418 657 2227",
    "sg:postcode":"G1V 2G1",
    "sg:province":"QC",
    "sg:tags":[
        "mental"
    ],
    "wof:name":"Verger Centre Communautaire",
    "wof:placetype":"venue"
},
  "geometry": {"coordinates":[-71.29228999999999,46.770828],"type":"Point"}
}