{
  "type": "Feature",
  "properties": {
    "iso:country":"CA",
    "sg:address":"355 Wellington St",
    "sg:city":"London",
    "sg:classifiers":[
        {
            "category":"Personal",
            "type":"Services"
        }
    ],
    "sg:phone":"+1 519 439 0518",
    "sg:postcode":"N6A 3N7",
    "sg:province":"ON",
    "sg:tags":[
        "control",
        "weight",
        "program",
        "fitness",
        "exercise",
        "physical"
    ],
    "wof:name":"Good Life Fitness Clubs",
    "wof:placetype":"venue"
},
  "geometry": {"coordinates":[-81.2445678711,42.9831962585],"type":"Point"}
}