{
  "type": "Feature",
  "properties": {
    "addr:full":"360 Industrial Ave Vancouver BC V6A 2P3",
    "addr:housenumber":"360",
    "addr:postcode":"v6a 2p3",
    "addr:street":"Industrial Ave",
    "iso:country":"CA",
    "sg:address":"360 Industrial Ave",
    "sg:city":"Vancouver",
    "sg:classifiers":[
        {
            "category":"Retail",
            "subcategory":"Auto Repair",
            "type":"Services"
        }
    ],
    "sg:phone":"+1 604 608 2670",
    "sg:postcode":"V6A 2P3",
    "sg:province":"BC",
    "sg:tags":[
        "repairing",
        "automobile"
    ],
    "wof:name":"Millennium Auto Ctr Ltd",
    "wof:placetype":"venue"
},
  "geometry": {"coordinates":[-123.096252441,49.2694625854],"type":"Point"}
}