{
  "type": "Feature",
  "properties": {
    "iso:country":"CA",
    "sg:city":"Plantagenet",
    "sg:classifiers":[
        {
            "category":"Government",
            "subcategory":"Office",
            "type":"Public Place"
        }
    ],
    "sg:phone":"+1 613 673 4858",
    "sg:postcode":"K0B 1L0",
    "sg:province":"ON",
    "sg:tags":[
        "village"
    ],
    "wof:name":"Plantagenet Garage",
    "wof:placetype":"venue"
},
  "geometry": {"coordinates":[-74.99816894529999,45.5352592468],"type":"Point"}
}