{
  "type": "Feature",
  "properties": {
    "addr:full":"1st St E The Pas MB R9A 1L5",
    "addr:postcode":"r9a 1l5",
    "addr:street":"1St St E",
    "iso:country":"CA",
    "sg:address":"1st St E",
    "sg:city":"The Pas",
    "sg:classifiers":[
        {
            "category":"Organizations",
            "subcategory":"Professional Association",
            "type":"Services"
        }
    ],
    "sg:phone":"+1 204 627 7811",
    "sg:postcode":"R9A 1L5",
    "sg:province":"MB",
    "sg:tags":[
        "environmental",
        "org"
    ],
    "wof:name":"Ducks Unlimited Canada",
    "wof:placetype":"venue"
},
  "geometry": {"coordinates":[-101.25035099999999,53.813435],"type":"Point"}
}