{
  "type": "Feature",
  "properties": {
    "addr:full":"56 the Esplanade Toronto ON M5E 1A7",
    "addr:housenumber":"56",
    "addr:postcode":"m5e 1a7",
    "addr:street":"The Esplanade",
    "iso:country":"CA",
    "sg:address":"56 the Esplanade",
    "sg:city":"Toronto",
    "sg:classifiers":[
        {
            "category":"Professional",
            "subcategory":"Art Services",
            "type":"Services"
        }
    ],
    "sg:phone":"+1 416 955 1880",
    "sg:postcode":"M5E 1A7",
    "sg:province":"ON",
    "sg:tags":[
        "graphic",
        "designer"
    ],
    "wof:name":"Mgt Communications Inc",
    "wof:placetype":"venue"
},
  "geometry": {"coordinates":[-79.374039,43.64706],"type":"Point"}
}