{
  "type": "Feature",
  "properties": {
    "iso:country":"CA",
    "sg:address":"862 Rte Lagueux",
    "sg:city":"Saint-Etienne-DE-Lauzon",
    "sg:classifiers":[
        {
            "category":"Home & Garden",
            "subcategory":"Garden Supply",
            "type":"Retail Goods"
        }
    ],
    "sg:phone":"+1 418 831 2023",
    "sg:postcode":"G6J 1B4",
    "sg:province":"QC",
    "sg:tags":[
        "lawn",
        "mower"
    ],
    "wof:name":"Petits Moteurs Labbe Inc",
    "wof:placetype":"venue"
},
  "geometry": {"coordinates":[-71.3281402588,46.6625747681],"type":"Point"}
}