{
  "type": "Feature",
  "properties": {
    "iso:country":"CA",
    "sg:address":"7205 Boul Newman",
    "sg:city":"Lasalle",
    "sg:classifiers":[
        {
            "category":"Restaurant",
            "type":"Food & Drink"
        }
    ],
    "sg:phone":"+1 514 367 1731",
    "sg:postcode":"H8N 2K3",
    "sg:province":"QC",
    "wof:name":"Buffet Vichy Lasalle",
    "wof:placetype":"venue"
},
  "geometry": {"coordinates":[-73.61646270750001,45.443069458],"type":"Point"}
}