{
  "type": "Feature",
  "properties": {
    "addr:full":"3740 Rue Jean-Talon O Montreal QC H3R 2G7",
    "addr:housenumber":"3740",
    "addr:postcode":"h3r 2g7",
    "addr:street":"Rue Jean-Talon O",
    "iso:country":"CA",
    "sg:address":"3740 Rue Jean-Talon O",
    "sg:city":"Montreal",
    "sg:classifiers":[
        {
            "category":"Restaurant",
            "type":"Food & Drink"
        }
    ],
    "sg:phone":"+1 514 735 5051",
    "sg:postcode":"H3R 2G7",
    "sg:province":"QC",
    "wof:name":"Mikasa Express",
    "wof:placetype":"venue"
},
  "geometry": {"coordinates":[-73.6425247192,45.5046730042],"type":"Point"}
}