{
  "type": "Feature",
  "properties": {
    "addr:full":"4907 50th Ave Legal AB T0G 1L0",
    "addr:housenumber":"4907",
    "addr:postcode":"t0g 1l0",
    "addr:street":"50Th Ave",
    "iso:country":"CA",
    "sg:address":"4907 50th Ave",
    "sg:city":"Legal",
    "sg:classifiers":[
        {
            "category":"Personal",
            "subcategory":"Beauty Salon",
            "type":"Services"
        }
    ],
    "sg:phone":"+1 780 961 3899",
    "sg:postcode":"T0G 1L0",
    "sg:province":"AB",
    "wof:name":"L A Looks",
    "wof:placetype":"venue"
},
  "geometry": {"coordinates":[-113.593391419,53.9489173889],"type":"Point"}
}