{
  "type": "Feature",
  "properties": {
    "addr:full":"303 Rue Heriot Drummondville QC J2B 1A6",
    "addr:housenumber":"303",
    "addr:postcode":"j2b 1a6",
    "addr:street":"Rue Heriot",
    "iso:country":"CA",
    "sg:address":"303 Rue Heriot",
    "sg:city":"Drummondville",
    "sg:classifiers":[
        {
            "category":"Personal",
            "subcategory":"Beauty Salon",
            "type":"Services"
        }
    ],
    "sg:phone":"+1 819 477 8745",
    "sg:postcode":"J2B 1A6",
    "sg:province":"QC",
    "wof:name":"Salon Boite A Cheveux",
    "wof:placetype":"venue"
},
  "geometry": {"coordinates":[-72.486305,45.88361],"type":"Point"}
}