{
  "type": "Feature",
  "properties": {
    "addr:full":"19 Menzies St Victoria BC V8V 2G1",
    "addr:housenumber":"19",
    "addr:postcode":"v8v 2g1",
    "addr:street":"Menzies St",
    "iso:country":"CA",
    "sg:address":"19 Menzies St",
    "sg:city":"Victoria",
    "sg:classifiers":[
        {
            "category":"Travel",
            "subcategory":"Hotels & Motels",
            "type":"Entertainment"
        }
    ],
    "sg:phone":"+1 250 384 0803",
    "sg:postcode":"V8V 2G1",
    "sg:province":"BC",
    "sg:tags":[
        "breakfast",
        "accommodation",
        "bed"
    ],
    "wof:name":"Menzies Manor",
    "wof:placetype":"venue"
},
  "geometry": {"coordinates":[-123.376922607,48.4123191833],"type":"Point"}
}