{
  "type": "Feature",
  "properties": {
    "addr:full":"583 Rue Ginette Le Gardeur QC J5Z 2W9",
    "addr:housenumber":"583",
    "addr:postcode":"j5z 2w9",
    "addr:street":"Rue Ginette;Gardeur",
    "iso:country":"CA",
    "sg:address":"583 Rue Ginette",
    "sg:city":"Le Gardeur",
    "sg:classifiers":[
        {
            "category":"Building & Trades",
            "subcategory":"Electrical",
            "type":"Services"
        }
    ],
    "sg:phone":"+1 450 657 2020",
    "sg:postcode":"J5Z 2W9",
    "sg:province":"QC",
    "sg:tags":[
        "electric",
        "contractor"
    ],
    "wof:name":"Kdm Electrique Inc",
    "wof:placetype":"venue"
},
  "geometry": {"coordinates":[-73.4621887207,45.7616615295],"type":"Point"}
}