{
  "type": "Feature",
  "properties": {
    "addr:full":"2141 Granville St Vancouver BC V6H 3E9",
    "addr:housenumber":"2141",
    "addr:postcode":"v6h 3e9",
    "addr:street":"Granville St",
    "iso:country":"CA",
    "sg:address":"2141 Granville St",
    "sg:city":"Vancouver",
    "sg:classifiers":[
        {
            "category":"Restaurant",
            "type":"Food & Drink"
        }
    ],
    "sg:phone":"+1 604 734 7704",
    "sg:postcode":"V6H 3E9",
    "sg:province":"BC",
    "wof:name":"Cheesecake Etcetera",
    "wof:placetype":"venue"
},
  "geometry": {"coordinates":[-123.138534546,49.2667236328],"type":"Point"}
}