{
  "type": "Feature",
  "properties": {
    "addr:full":"135 Rue DE L'Ecole Shippagan NB E8S 1V5",
    "addr:housenumber":"135",
    "addr:postcode":"e8s 1v5",
    "addr:street":"Rue De L'Ecole Shippagan",
    "iso:country":"CA",
    "sg:address":"135 Rue DE L'Ecole",
    "sg:city":"Shippagan",
    "sg:classifiers":[
        {
            "category":"Organizations",
            "subcategory":"Professional Association",
            "type":"Services"
        }
    ],
    "sg:phone":"+1 506 336 3024",
    "sg:postcode":"E8S 1V5",
    "sg:province":"NB",
    "wof:name":"Cac",
    "wof:placetype":"venue"
},
  "geometry": {"coordinates":[-64.7087631226,47.7438392639],"type":"Point"}
}