{
  "type": "Feature",
  "properties": {
    "addr:full":"Calgary AB T2P 2V7",
    "addr:postcode":"t2p 2v7",
    "iso:country":"CA",
    "sg:city":"Calgary",
    "sg:classifiers":[
        {
            "category":"Professional",
            "subcategory":"Lawyer & Legal Services",
            "type":"Services"
        }
    ],
    "sg:phone":"+1 403 298 0333",
    "sg:postcode":"T2P 2V7",
    "sg:province":"AB",
    "sg:tags":[
        "attorney"
    ],
    "wof:name":"Kelly, Donald J QC",
    "wof:placetype":"venue"
},
  "geometry": {"coordinates":[-114.065575,51.048267],"type":"Point"}
}