{
  "type": "Feature",
  "properties": {
    "addr:full":"LA Loche Ave LA Loche SK S0M 1G0",
    "addr:postcode":"s0m 1g0",
    "addr:street":"Loche Ave",
    "iso:country":"CA",
    "sg:address":"LA Loche Ave",
    "sg:city":"LA Loche",
    "sg:classifiers":[
        {
            "category":"Restaurant",
            "type":"Food & Drink"
        }
    ],
    "sg:phone":"+1 306 822 2600",
    "sg:postcode":"S0M 1G0",
    "sg:province":"SK",
    "sg:tags":[
        "motel",
        "hotel"
    ],
    "wof:name":"LA Loche Motor Inn",
    "wof:placetype":"venue"
},
  "geometry": {"coordinates":[-109.436096191,56.482334137],"type":"Point"}
}