{
  "type": "Feature",
  "properties": {
    "addr:full":"6025 Boul Marie-Victorin Brossard QC J4W 2M1",
    "addr:housenumber":"6025",
    "addr:postcode":"j4w 2m1",
    "addr:street":"Boul Marie-Victorin",
    "iso:country":"CA",
    "sg:address":"6025 Boul Marie-Victorin",
    "sg:city":"Brossard",
    "sg:classifiers":[
        {
            "category":"Autos & Motor Vehicles",
            "subcategory":"Fuel & Gas Station",
            "type":"Retail Goods"
        }
    ],
    "sg:phone":"+1 450 671 6212",
    "sg:postcode":"J4W 2M1",
    "sg:province":"QC",
    "sg:tags":[
        "oil"
    ],
    "wof:name":"Ultramar",
    "wof:placetype":"venue"
},
  "geometry": {"coordinates":[-73.495475769,45.4705047607],"type":"Point"}
}