{
  "type": "Feature",
  "properties": {
    "iso:country":"CA",
    "sg:address":"6654 Butler Cres # 2",
    "sg:city":"Saanichton",
    "sg:classifiers":[
        {
            "category":"Utilities",
            "subcategory":"Refuse",
            "type":"Services"
        }
    ],
    "sg:phone":"+1 250 652 6242",
    "sg:postcode":"V8M 2G8",
    "sg:province":"BC",
    "sg:tags":[
        "garbage",
        "recycling",
        "center",
        "collection"
    ],
    "wof:name":"Rdi",
    "wof:placetype":"venue"
},
  "geometry": {"coordinates":[-123.41689300500001,48.595199585],"type":"Point"}
}