{
  "type": "Feature",
  "properties": {
    "iso:country":"CA",
    "sg:address":"1312 Rue Sainte-Catherine O",
    "sg:city":"Montreal",
    "sg:classifiers":[
        {
            "category":"Freight",
            "type":"Transportation"
        }
    ],
    "sg:phone":"+1 514 398 9859",
    "sg:postcode":"H3G 1P6",
    "sg:province":"QC",
    "wof:name":"Mondabel Inc",
    "wof:placetype":"venue"
},
  "geometry": {"coordinates":[-73.555016,45.519428],"type":"Point"}
}