{
  "type": "Feature",
  "properties": {
    "addr:full":"Stonewall MB R0C 2Z0",
    "addr:postcode":"r0c 2z0",
    "iso:country":"CA",
    "sg:city":"Stonewall",
    "sg:classifiers":[
        {
            "category":"Health Services",
            "subcategory":"Health Practitioner",
            "type":"Services"
        }
    ],
    "sg:phone":"+1 204 467 9101",
    "sg:postcode":"R0C 2Z0",
    "sg:province":"MB",
    "sg:tags":[
        "physiotherapist"
    ],
    "wof:name":"Quarry Physiotherapy Sports",
    "wof:placetype":"venue"
},
  "geometry": {"coordinates":[-97.326843,50.13522],"type":"Point"}
}