{
  "type": "Feature",
  "properties": {
    "addr:full":"Edmonton AB T5J 4H5",
    "addr:postcode":"t5j 4h5",
    "iso:country":"CA",
    "sg:city":"Edmonton",
    "sg:classifiers":[
        {
            "category":"Health Services",
            "subcategory":"Optometrist",
            "type":"Services"
        }
    ],
    "sg:phone":"+1 780 429 0029",
    "sg:postcode":"T5J 4H5",
    "sg:province":"AB",
    "wof:name":"Karaim, Scott OD",
    "wof:placetype":"venue"
},
  "geometry": {"coordinates":[-113.467392,53.546982],"type":"Point"}
}