{
  "type": "Feature",
  "properties": {
    "addr:full":"Ottawa ON K1S 3W3",
    "addr:postcode":"k1s 3w3",
    "iso:country":"CA",
    "sg:city":"Ottawa",
    "sg:classifiers":[
        {
            "category":"Professional",
            "subcategory":"Management & Consulting",
            "type":"Services"
        }
    ],
    "sg:phone":"+1 613 230 5221",
    "sg:postcode":"K1S 3W3",
    "sg:province":"ON",
    "sg:tags":[
        "international",
        "consultant"
    ],
    "wof:name":"E T Jackson & Assoc Ltd",
    "wof:placetype":"venue"
},
  "geometry": {"coordinates":[-75.687592,45.40134],"type":"Point"}
}