{
  "type": "Feature",
  "properties": {
    "addr:full":"12109 121 Ave NW Edmonton AB T5L 2R9",
    "addr:housenumber":"12109",
    "addr:postcode":"t5l 2r9",
    "addr:street":"121 Ave Nw",
    "iso:country":"CA",
    "sg:address":"12109 121 Ave NW",
    "sg:city":"Edmonton",
    "sg:classifiers":[
        {
            "category":"Building & Trades",
            "subcategory":"Construction",
            "type":"Services"
        }
    ],
    "sg:phone":"+1 780 455 8555",
    "sg:postcode":"T5L 2R9",
    "sg:province":"AB",
    "sg:tags":[
        "resurfacing",
        "material",
        "laying",
        "refinishing",
        "floor"
    ],
    "wof:name":"R & S Floor Contracting Ltd",
    "wof:placetype":"venue"
},
  "geometry": {"coordinates":[-113.53182200000001,53.575047],"type":"Point"}
}