{
  "type": "Feature",
  "properties": {
    "addr:full":"455 Boul Sainte-Rose Laval QC H7L 4P5",
    "addr:housenumber":"455",
    "addr:postcode":"h7l 4p5",
    "addr:street":"Boul Sainte-Rose",
    "iso:country":"CA",
    "sg:address":"455 Boul Sainte-Rose",
    "sg:city":"Laval",
    "sg:classifiers":[
        {
            "category":"Home & Garden",
            "subcategory":"Carpets & Floor Coverings",
            "type":"Retail Goods"
        }
    ],
    "sg:phone":"+1 450 622 9460",
    "sg:postcode":"H7L 4P5",
    "sg:province":"QC",
    "sg:tags":[
        "material",
        "rug"
    ],
    "wof:name":"Decor Tapis Emard Inc",
    "wof:placetype":"venue"
},
  "geometry": {"coordinates":[-73.74463653559999,45.5515670776],"type":"Point"}
}