{
  "type": "Feature",
  "properties": {
    "addr:full":"1300 Lloyd Ave North Vancouver BC V7P 3J9",
    "addr:housenumber":"1300",
    "addr:postcode":"v7p 3j9",
    "addr:street":"Lloyd Ave",
    "iso:country":"CA",
    "sg:address":"1300 Lloyd Ave",
    "sg:city":"North Vancouver",
    "sg:classifiers":[
        {
            "category":"Home & Garden",
            "subcategory":"Furniture",
            "type":"Retail Goods"
        }
    ],
    "sg:phone":"+1 604 985 9527",
    "sg:postcode":"V7P 3J9",
    "sg:province":"BC",
    "sg:tags":[
        "cabinet"
    ],
    "wof:name":"Reynolds Cabinet Shop Ltd",
    "wof:placetype":"venue"
},
  "geometry": {"coordinates":[-123.104911804,49.3203315735],"type":"Point"}
}