{
  "type": "Feature",
  "properties": {
    "iso:country":"CA",
    "sg:address":"2920 197A St",
    "sg:city":"Langley",
    "sg:classifiers":[
        {
            "category":"Building & Trades",
            "subcategory":"Construction",
            "type":"Services"
        }
    ],
    "sg:phone":"+1 604 534 9941",
    "sg:postcode":"V2Z 1X9",
    "sg:province":"BC",
    "sg:tags":[
        "boring",
        "drilling",
        "contractor"
    ],
    "wof:name":"Clark Drilling Svc Ltd",
    "wof:placetype":"venue"
},
  "geometry": {"coordinates":[-122.65657043500001,49.1041221619],"type":"Point"}
}