{
  "type": "Feature",
  "properties": {
    "addr:full":"Richmond BC V7C 4V4",
    "addr:postcode":"v7c 4v4",
    "iso:country":"CA",
    "sg:city":"Richmond",
    "sg:classifiers":[
        {
            "category":"Retail",
            "subcategory":"Repair Shop",
            "type":"Services"
        }
    ],
    "sg:phone":"+1 604 270 3230",
    "sg:postcode":"V7C 4V4",
    "sg:province":"BC",
    "sg:tags":[
        "equipment",
        "photographic"
    ],
    "wof:name":"Brighouse Camera Repairs",
    "wof:placetype":"venue"
},
  "geometry": {"coordinates":[-123.15745544400001,49.170375824],"type":"Point"}
}