{
  "type": "Feature",
  "properties": {
    "addr:full":"5012 54 Ave Bonnyville AB T9N 2G7",
    "addr:housenumber":"5012",
    "addr:postcode":"t9n 2g7",
    "addr:street":"54 Ave",
    "iso:country":"CA",
    "sg:address":"5012 54 Ave",
    "sg:city":"Bonnyville",
    "sg:classifiers":[
        {
            "category":"Home & Garden",
            "subcategory":"Building Materials",
            "type":"Retail Goods"
        }
    ],
    "sg:phone":"+1 780 826 6405",
    "sg:postcode":"T9N 2G7",
    "sg:province":"AB",
    "sg:tags":[
        "repairing",
        "plate",
        "window",
        "remodeling",
        "contractor"
    ],
    "wof:name":"Yellowhead Home & Glass Ltd",
    "wof:placetype":"venue"
},
  "geometry": {"coordinates":[-110.740463257,54.271900177],"type":"Point"}
}