{
  "type": "Feature",
  "properties": {
    "addr:full":"99 Main St Souris PE C0A 2B0",
    "addr:housenumber":"99",
    "addr:postcode":"c0a 2b0",
    "addr:street":"Main St",
    "iso:country":"CA",
    "sg:address":"99 Main St",
    "sg:city":"Souris",
    "sg:classifiers":[
        {
            "category":"Professional",
            "subcategory":"Business Services",
            "type":"Services"
        }
    ],
    "sg:phone":"+1 902 687 7030",
    "sg:postcode":"C0A 2B0",
    "sg:province":"PE",
    "sg:tags":[
        "information",
        "referral",
        "government"
    ],
    "wof:name":"Pei Visitor Information Ctr",
    "wof:placetype":"venue"
},
  "geometry": {"coordinates":[-62.2530326843,46.3544883728],"type":"Point"}
}