{
  "type": "Feature",
  "properties": {
    "addr:full":"2815 Boul Laurier Sainte-Foy QC G1V 4H3",
    "addr:housenumber":"2815",
    "addr:postcode":"g1v 4h3",
    "addr:street":"Boul Laurier",
    "iso:country":"CA",
    "sg:address":"2815 Boul Laurier",
    "sg:city":"Sainte-Foy",
    "sg:classifiers":[
        {
            "category":"Travel",
            "subcategory":"Hotels & Motels",
            "type":"Entertainment"
        }
    ],
    "sg:phone":"+1 418 658 2793",
    "sg:postcode":"G1V 4H3",
    "sg:province":"QC",
    "wof:name":"Hotel Classique",
    "wof:placetype":"venue"
},
  "geometry": {"coordinates":[-71.28684997560001,46.7677574158],"type":"Point"}
}