{
  "type": "Feature",
  "properties": {
    "addr:full":"4100 Boul DE LA Concorde E Laval QC H7E 2E3",
    "addr:housenumber":"4100",
    "addr:postcode":"h7e 2e3",
    "addr:street":"Boul De La Concorde E",
    "iso:country":"CA",
    "sg:address":"4100 Boul DE LA Concorde E",
    "sg:city":"Laval",
    "sg:classifiers":[
        {
            "category":"Arena",
            "subcategory":"Sports Club",
            "type":"Entertainment"
        }
    ],
    "sg:phone":"+1 450 662 4934",
    "sg:postcode":"H7E 2E3",
    "sg:province":"QC",
    "sg:tags":[
        "athletic",
        "fields",
        "stadium",
        "government"
    ],
    "wof:name":"Concorde Arenas Municipales",
    "wof:placetype":"venue"
},
  "geometry": {"coordinates":[-73.65475499999999,45.601357],"type":"Point"}
}