{
  "type": "Feature",
  "properties": {
    "iso:country":"CA",
    "sg:address":"52 Campus Dr",
    "sg:city":"Saskatoon",
    "sg:classifiers":[
        {
            "category":"Government",
            "subcategory":"Office",
            "type":"Public Place"
        }
    ],
    "sg:phone":"+1 306 966 7316",
    "sg:postcode":"S7N 5B4",
    "sg:province":"SK",
    "wof:name":"Prairie Diagnostic Svc",
    "wof:placetype":"venue"
},
  "geometry": {"coordinates":[-106.629768,52.13303],"type":"Point"}
}