{
  "type": "Feature",
  "properties": {
    "addr:full":"185 Av George-V Lachine QC H8S 2R5",
    "addr:housenumber":"185",
    "addr:postcode":"h8s 2r5",
    "addr:street":"Av George-V",
    "iso:country":"CA",
    "sg:address":"185 Av George-V",
    "sg:city":"Lachine",
    "sg:classifiers":[
        {
            "category":"Building & Trades",
            "subcategory":"Construction",
            "type":"Services"
        }
    ],
    "sg:phone":"+1 514 634 7466",
    "sg:postcode":"H8S 2R5",
    "sg:province":"QC",
    "sg:tags":[
        "demolition",
        "paving",
        "contractor"
    ],
    "wof:name":"Excavations S & M Fournier",
    "wof:placetype":"venue"
},
  "geometry": {"coordinates":[-73.66356658940001,45.4367485046],"type":"Point"}
}