{
  "type": "Feature",
  "properties": {
    "addr:full":"150 Orenda Rd Brampton ON L6W 1W2",
    "addr:housenumber":"150",
    "addr:postcode":"l6w 1w2",
    "addr:street":"Orenda Rd",
    "iso:country":"CA",
    "sg:address":"150 Orenda Rd",
    "sg:city":"Brampton",
    "sg:classifiers":[
        {
            "category":"Professional",
            "subcategory":"Management & Consulting",
            "type":"Services"
        }
    ],
    "sg:phone":"+1 905 459 2716",
    "sg:postcode":"L6W 1W2",
    "sg:province":"ON",
    "sg:tags":[
        "consultant"
    ],
    "wof:name":"Wasteco",
    "wof:placetype":"venue"
},
  "geometry": {"coordinates":[-79.731148,43.695648],"type":"Point"}
}