{
  "type": "Feature",
  "properties": {
    "iso:country":"CA",
    "sg:address":"78 Burton St",
    "sg:city":"Hamilton",
    "sg:classifiers":[
        {
            "category":"Wholesale",
            "subcategory":"Meat",
            "type":"Manufacturing & Wholesale Goods"
        }
    ],
    "sg:phone":"+1 905 525 7278",
    "sg:postcode":"L8L 3R3",
    "sg:province":"ON",
    "wof:name":"Fernando Meat Products",
    "wof:placetype":"venue"
},
  "geometry": {"coordinates":[-79.8483505249,43.263923645],"type":"Point"}
}