{
  "type": "Feature",
  "properties": {
    "addr:full":"344 Lemarchant Rd St. John's NL A1E 1R2",
    "addr:housenumber":"344",
    "addr:postcode":"a1e 1r2",
    "addr:street":"Lemarchant Rd",
    "iso:country":"CA",
    "sg:address":"344 Lemarchant Rd",
    "sg:city":"St. John's",
    "sg:classifiers":[
        {
            "category":"Autos & Motor Vehicles",
            "subcategory":"Auto Supplies",
            "type":"Retail Goods"
        }
    ],
    "sg:phone":"+1 709 579 0191",
    "sg:postcode":"A1E 1R2",
    "sg:province":"NL",
    "sg:tags":[
        "automobile",
        "parts"
    ],
    "wof:name":"Grouchy's Limited",
    "wof:placetype":"venue"
},
  "geometry": {"coordinates":[-52.726093,47.551212],"type":"Point"}
}