{
  "type": "Feature",
  "properties": {
    "addr:full":"1 Gondola Point Rd Rothesay NB E2E 5J6",
    "addr:housenumber":"1",
    "addr:postcode":"e2e 5j6",
    "addr:street":"Gondola Point Rd",
    "iso:country":"CA",
    "sg:address":"1 Gondola Point Rd",
    "sg:city":"Rothesay",
    "sg:classifiers":[
        {
            "category":"Professional",
            "subcategory":"Management & Consulting",
            "type":"Services"
        }
    ],
    "sg:phone":"+1 506 847 8917",
    "sg:postcode":"E2E 5J6",
    "sg:province":"NB",
    "sg:tags":[
        "employee",
        "consultant",
        "benefit"
    ],
    "wof:name":"Fraser, Charles",
    "wof:placetype":"venue"
},
  "geometry": {"coordinates":[-65.9974441528,45.3873100281],"type":"Point"}
}