{
  "type": "Feature",
  "properties": {
    "iso:country":"CA",
    "sg:address":"3781 Boul Levesque O",
    "sg:city":"Laval",
    "sg:classifiers":[
        {
            "category":"Recreation",
            "type":"Entertainment"
        }
    ],
    "sg:phone":"+1 450 978 8959",
    "sg:postcode":"H7V 1G5",
    "sg:province":"QC",
    "sg:tags":[
        "government",
        "hall",
        "auditorium"
    ],
    "wof:name":"Laval Centre J-P Campeau",
    "wof:placetype":"venue"
},
  "geometry": {"coordinates":[-73.738449,45.534843],"type":"Point"}
}