{
  "type": "Feature",
  "properties": {
    "addr:full":"Mississauga ON L4Z 3L3",
    "addr:postcode":"l4z 3l3",
    "iso:country":"CA",
    "sg:city":"Mississauga",
    "sg:classifiers":[
        {
            "category":"Real Estate",
            "subcategory":"Real Estate Agent",
            "type":"Services"
        }
    ],
    "sg:phone":"+1 905 712 8855",
    "sg:postcode":"L4Z 3L3",
    "sg:province":"ON",
    "wof:name":"Prudential National Realty Ctr",
    "wof:placetype":"venue"
},
  "geometry": {"coordinates":[-79.6708984375,43.6262817383],"type":"Point"}
}