{
  "type": "Feature",
  "properties": {
    "addr:full":"321 Kipawa Rd Temiscaming QC J0Z 3R0",
    "addr:housenumber":"321",
    "addr:postcode":"j0z 3r0",
    "addr:street":"Kipawa Rd",
    "iso:country":"CA",
    "sg:address":"321 Kipawa Rd",
    "sg:city":"Temiscaming",
    "sg:classifiers":[
        {
            "category":"Health Services",
            "subcategory":"Chiropractor",
            "type":"Services"
        }
    ],
    "sg:phone":"+1 819 627 8181",
    "sg:postcode":"J0Z 3R0",
    "sg:province":"QC",
    "wof:name":"Wolfe Chiropractic Ctr",
    "wof:placetype":"venue"
},
  "geometry": {"coordinates":[-79.09869384770001,46.7186470032],"type":"Point"}
}