{
  "type": "Feature",
  "properties": {
    "addr:full":"443 18th St N Brandon MB R7A 6Z2",
    "addr:housenumber":"443",
    "addr:postcode":"r7a 6z2",
    "addr:street":"18Th St N",
    "iso:country":"CA",
    "sg:address":"443 18th St N",
    "sg:city":"Brandon",
    "sg:classifiers":[
        {
            "category":"Utilities",
            "subcategory":"Mobile Phone",
            "type":"Services"
        }
    ],
    "sg:phone":"+1 204 726 5552",
    "sg:postcode":"R7A 6Z2",
    "sg:province":"MB",
    "sg:tags":[
        "telephone",
        "cellular"
    ],
    "wof:name":"Cell CA",
    "wof:placetype":"venue"
},
  "geometry": {"coordinates":[-99.9618148804,49.8588867188],"type":"Point"}
}