{
  "type": "Feature",
  "properties": {
    "addr:full":"4828 Centre St NE Calgary AB T2E 2Z7",
    "addr:housenumber":"4828",
    "addr:postcode":"t2e 2z7",
    "addr:street":"Centre St Ne",
    "iso:country":"CA",
    "sg:address":"4828 Centre St NE",
    "sg:city":"Calgary",
    "sg:classifiers":[
        {
            "category":"Autos & Motor Vehicles",
            "subcategory":"Fuel & Gas Station",
            "type":"Retail Goods"
        }
    ],
    "sg:phone":"+1 403 277 6584",
    "sg:postcode":"T2E 2Z7",
    "sg:province":"AB",
    "sg:tags":[
        "oil"
    ],
    "wof:name":"Highland Shell",
    "wof:placetype":"venue"
},
  "geometry": {"coordinates":[-114.062195,51.095058],"type":"Point"}
}