{
  "type": "Feature",
  "properties": {
    "addr:full":"2 St. Clair St Devon AB T9G 1J3",
    "addr:housenumber":"2",
    "addr:postcode":"t9g 1j3",
    "addr:street":"St. Clair St",
    "iso:country":"CA",
    "sg:address":"2 St. Clair St",
    "sg:city":"Devon",
    "sg:classifiers":[
        {
            "category":"Organizations",
            "subcategory":"Religious Organization",
            "type":"Services"
        }
    ],
    "sg:phone":"+1 780 987 3714",
    "sg:postcode":"T9G 1J3",
    "sg:province":"AB",
    "sg:tags":[
        "church"
    ],
    "wof:name":"Devon United Church",
    "wof:placetype":"venue"
},
  "geometry": {"coordinates":[-113.724998474,53.3634529114],"type":"Point"}
}