{
  "type": "Feature",
  "properties": {
    "addr:full":"130 Rue Saint-Nicolas Sorel-Tracy QC J3P 6X9",
    "addr:housenumber":"130",
    "addr:postcode":"j3p 6x9",
    "addr:street":"Rue Saint-Nicolas",
    "iso:country":"CA",
    "sg:address":"130 Rue Saint-Nicolas",
    "sg:city":"Sorel-Tracy",
    "sg:classifiers":[
        {
            "category":"Health Services",
            "subcategory":"Doctor",
            "type":"Services"
        }
    ],
    "sg:phone":"+1 450 746 4800",
    "sg:postcode":"J3P 6X9",
    "sg:province":"QC",
    "sg:tags":[
        "physician",
        "surgeon"
    ],
    "wof:name":"Nantel, Pierre MD",
    "wof:placetype":"venue"
},
  "geometry": {"coordinates":[-73.110069,46.026726],"type":"Point"}
}