{
  "type": "Feature",
  "properties": {
    "addr:full":"Hamilton ON L8W 2E7",
    "addr:postcode":"l8w 2e7",
    "iso:country":"CA",
    "sg:city":"Hamilton",
    "sg:classifiers":[
        {
            "category":"Wholesale",
            "subcategory":"Groceries",
            "type":"Manufacturing & Wholesale Goods"
        }
    ],
    "sg:phone":"+1 905 574 9217",
    "sg:postcode":"L8W 2E7",
    "sg:province":"ON",
    "sg:tags":[
        "food",
        "product"
    ],
    "wof:name":"M & L Gourmet Enterprises Inc",
    "wof:placetype":"venue"
},
  "geometry": {"coordinates":[-79.839394,43.194771],"type":"Point"}
}