{
  "type": "Feature",
  "properties": {
    "addr:full":"Montreal QC H3C 2N6",
    "addr:postcode":"h3c 2n6",
    "iso:country":"CA",
    "sg:city":"Montreal",
    "sg:classifiers":[
        {
            "category":"Shopping",
            "subcategory":"Computers & Home Electronics",
            "type":"Retail Goods"
        }
    ],
    "sg:phone":"+1 514 383 4452",
    "sg:postcode":"H3C 2N6",
    "sg:province":"QC",
    "sg:tags":[
        "software"
    ],
    "wof:name":"Ordinateurs Cantel Inc",
    "wof:placetype":"venue"
},
  "geometry": {"coordinates":[-73.5547180176,45.4974250793],"type":"Point"}
}