{
  "type": "Feature",
  "properties": {
    "addr:full":"246 Lindsay Cres NW Edmonton AB T6R 2T2",
    "addr:housenumber":"246",
    "addr:postcode":"t6r 2t2",
    "addr:street":"Lindsay Cres Nw",
    "iso:country":"CA",
    "sg:address":"246 Lindsay Cres NW",
    "sg:city":"Edmonton",
    "sg:classifiers":[
        {
            "category":"Insurance",
            "subcategory":"Insurance Agent",
            "type":"Services"
        }
    ],
    "sg:phone":"+1 780 988 2220",
    "sg:postcode":"T6R 2T2",
    "sg:province":"AB",
    "wof:name":"Angeles & Assoc Financial Svc",
    "wof:placetype":"venue"
},
  "geometry": {"coordinates":[-113.570976257,53.4590835571],"type":"Point"}
}