{
  "type": "Feature",
  "properties": {
    "addr:full":"46 Goodridge Dr St Albert AB T8N 2B2",
    "addr:housenumber":"46",
    "addr:postcode":"t8n 2b2",
    "addr:street":"Goodridge Dr",
    "iso:country":"CA",
    "sg:address":"46 Goodridge Dr",
    "sg:city":"St Albert",
    "sg:classifiers":[
        {
            "category":"Professional",
            "subcategory":"Management & Consulting",
            "type":"Services"
        }
    ],
    "sg:phone":"+1 780 459 9182",
    "sg:postcode":"T8N 2B2",
    "sg:province":"AB",
    "sg:tags":[
        "insurance"
    ],
    "wof:name":"Willock Consultants Ltd",
    "wof:placetype":"venue"
},
  "geometry": {"coordinates":[-113.607879639,53.6153907776],"type":"Point"}
}