{
  "type": "Feature",
  "properties": {
    "addr:full":"Sudbury ON P3A 4V4",
    "addr:postcode":"p3a 4v4",
    "iso:country":"CA",
    "sg:city":"Sudbury",
    "sg:classifiers":[
        {
            "category":"Personal",
            "subcategory":"Beauty Salon",
            "type":"Services"
        }
    ],
    "sg:phone":"+1 705 524 2369",
    "sg:postcode":"P3A 4V4",
    "sg:province":"ON",
    "wof:name":"Cutting Loose Hair Designs",
    "wof:placetype":"venue"
},
  "geometry": {"coordinates":[-80.966431,46.522289],"type":"Point"}
}