{
  "type": "Feature",
  "properties": {
    "addr:full":"PO Box 77567 Rpo Sheppard Plaz Toronto ON M3H 6A7",
    "addr:housenumber":"po box",
    "addr:postcode":"77567;m3h 6a7",
    "addr:street":"Plaz",
    "iso:country":"CA",
    "sg:address":"PO Box 77567 Rpo Sheppard Plaz",
    "sg:city":"Toronto",
    "sg:classifiers":[
        {
            "category":"Professional",
            "subcategory":"Employment Agencies",
            "type":"Services"
        }
    ],
    "sg:phone":"+1 416 633 4844",
    "sg:postcode":"M3H 6A7",
    "sg:province":"ON",
    "sg:tags":[
        "consultant",
        "search",
        "executive"
    ],
    "wof:name":"Lily Groman Consulting Svc",
    "wof:placetype":"venue"
},
  "geometry": {"coordinates":[-79.3853302002,43.648563385],"type":"Point"}
}