{
  "type": "Feature",
  "properties": {
    "addr:full":"475 Unwin Ave Toronto ON M4M 3M2",
    "addr:housenumber":"475",
    "addr:postcode":"m4m 3m2",
    "addr:street":"Unwin Ave",
    "iso:country":"CA",
    "sg:address":"475 Unwin Ave",
    "sg:city":"Toronto",
    "sg:classifiers":[
        {
            "category":"Recreation",
            "subcategory":"Marina",
            "type":"Entertainment"
        }
    ],
    "sg:phone":"+1 416 778 6245",
    "sg:postcode":"M4M 3M2",
    "sg:province":"ON",
    "wof:name":"Outer Harbour Marina",
    "wof:placetype":"venue"
},
  "geometry": {"coordinates":[-79.3275222778,43.6485748291],"type":"Point"}
}