{
  "type": "Feature",
  "properties": {
    "addr:full":"1009 Brock St S Whitby ON L1N 4L7",
    "addr:housenumber":"1009",
    "addr:postcode":"l1n 4l7",
    "addr:street":"Brock St S",
    "iso:country":"CA",
    "sg:address":"1009 Brock St S",
    "sg:city":"Whitby",
    "sg:classifiers":[
        {
            "category":"Retail",
            "subcategory":"Auto Repair",
            "type":"Services"
        }
    ],
    "sg:phone":"+1 905 668 0021",
    "sg:postcode":"L1N 4L7",
    "sg:province":"ON",
    "sg:tags":[
        "repairing",
        "automobile"
    ],
    "wof:name":"Sarge's Service Ctr",
    "wof:placetype":"venue"
},
  "geometry": {"coordinates":[-78.93794250489999,43.8702545166],"type":"Point"}
}