{
  "type": "Feature",
  "properties": {
    "addr:full":"Winnipeg MB R2X 2Y3",
    "addr:postcode":"r2x 2y3",
    "iso:country":"CA",
    "sg:city":"Winnipeg",
    "sg:classifiers":[
        {
            "category":"Professional",
            "subcategory":"Management & Consulting",
            "type":"Services"
        }
    ],
    "sg:phone":"+1 204 633 1700",
    "sg:postcode":"R2X 2Y3",
    "sg:province":"MB",
    "sg:tags":[
        "consultant",
        "safety"
    ],
    "wof:name":"New Heights Industries Inc",
    "wof:placetype":"venue"
},
  "geometry": {"coordinates":[-97.19536600000001,49.927036],"type":"Point"}
}