{
  "type": "Feature",
  "properties": {
    "addr:full":"Etobicoke ON M9W 5Z3",
    "addr:postcode":"m9w 5z3",
    "iso:country":"CA",
    "sg:city":"Etobicoke",
    "sg:classifiers":[
        {
            "category":"Wholesale",
            "subcategory":"Meat",
            "type":"Manufacturing & Wholesale Goods"
        }
    ],
    "sg:phone":"+1 416 742 1441",
    "sg:postcode":"M9W 5Z3",
    "sg:province":"ON",
    "sg:tags":[
        "butchering"
    ],
    "wof:name":"Insaf Grocery & Halal Meat",
    "wof:placetype":"venue"
},
  "geometry": {"coordinates":[-79.55877700000001,43.713768],"type":"Point"}
}