{
  "type": "Feature",
  "properties": {
    "iso:country":"CA",
    "sg:address":"13851 Parkland Blvd SE",
    "sg:city":"Calgary",
    "sg:classifiers":[
        {
            "category":"Professional",
            "subcategory":"Engineering",
            "type":"Services"
        }
    ],
    "sg:phone":"+1 403 225 5770",
    "sg:postcode":"T2J 3X9",
    "sg:province":"AB",
    "sg:tags":[
        "engineer"
    ],
    "wof:name":"Cold Creek Enterprises Ltd",
    "wof:placetype":"venue"
},
  "geometry": {"coordinates":[-114.03578186,50.9281730652],"type":"Point"}
}