{
  "type": "Feature",
  "properties": {
    "addr:full":"159 22nd St Fort Macleod AB T0L 0Z0",
    "addr:housenumber":"159",
    "addr:postcode":"t0l 0z0",
    "addr:street":"22Nd St",
    "iso:country":"CA",
    "sg:address":"159 22nd St",
    "sg:city":"Fort Macleod",
    "sg:classifiers":[
        {
            "category":"Personal",
            "subcategory":"Beauty Salon",
            "type":"Services"
        }
    ],
    "sg:phone":"+1 403 553 4919",
    "sg:postcode":"T0L 0Z0",
    "sg:province":"AB",
    "wof:name":"Hair Palace",
    "wof:placetype":"venue"
},
  "geometry": {"coordinates":[-113.409935,49.724121],"type":"Point"}
}