{
  "type": "Feature",
  "properties": {
    "addr:full":"9648 128 St Surrey BC V3T 2X9",
    "addr:housenumber":"9648",
    "addr:postcode":"v3t 2x9",
    "addr:street":"128 St",
    "iso:country":"CA",
    "sg:address":"9648 128 St",
    "sg:city":"Surrey",
    "sg:classifiers":[
        {
            "category":"Health Services",
            "subcategory":"Doctor",
            "type":"Services"
        }
    ],
    "sg:phone":"+1 604 582 4666",
    "sg:postcode":"V3T 2X9",
    "sg:province":"BC",
    "sg:tags":[
        "physician",
        "surgeon"
    ],
    "wof:name":"Luay F Dindo Inc",
    "wof:placetype":"venue"
},
  "geometry": {"coordinates":[-122.867874145,49.1781463623],"type":"Point"}
}