{
  "type": "Feature",
  "properties": {
    "addr:full":"Vancouver BC V6M 3V8",
    "addr:postcode":"v6m 3v8",
    "iso:country":"CA",
    "sg:city":"Vancouver",
    "sg:classifiers":[
        {
            "category":"Real Estate",
            "subcategory":"Real Estate Agent",
            "type":"Services"
        }
    ],
    "sg:phone":"+1 604 267 3900",
    "sg:postcode":"V6M 3V8",
    "sg:province":"BC",
    "sg:tags":[
        "consultant"
    ],
    "wof:name":"Phone Homesearch",
    "wof:placetype":"venue"
},
  "geometry": {"coordinates":[-123.154999,49.228741],"type":"Point"}
}