{
  "type": "Feature",
  "properties": {
    "addr:full":"2731 Faithfull Ave Saskatoon SK S7K 7C3",
    "addr:housenumber":"2731",
    "addr:postcode":"s7k 7c3",
    "addr:street":"Faithfull Ave",
    "iso:country":"CA",
    "sg:address":"2731 Faithfull Ave",
    "sg:city":"Saskatoon",
    "sg:classifiers":[
        {
            "category":"Shopping",
            "subcategory":"Bicycles & Sporting Goods",
            "type":"Retail Goods"
        }
    ],
    "sg:phone":"+1 306 931 4475",
    "sg:postcode":"S7K 7C3",
    "sg:province":"SK",
    "wof:name":"Wholesale Sports Outdoor",
    "wof:placetype":"venue"
},
  "geometry": {"coordinates":[-106.665153503,52.1714477539],"type":"Point"}
}