{
  "type": "Feature",
  "properties": {
    "iso:country":"CA",
    "sg:address":"129 Church St",
    "sg:city":"St Catharines",
    "sg:classifiers":[
        {
            "category":"Social Services",
            "subcategory":"Job Training",
            "type":"Services"
        }
    ],
    "sg:phone":"+1 905 684 3500",
    "sg:postcode":"L2R 3E2",
    "sg:province":"ON",
    "sg:tags":[
        "employment",
        "association"
    ],
    "wof:name":"Ymca Employment Svc",
    "wof:placetype":"venue"
},
  "geometry": {"coordinates":[-79.24262237550001,43.1631088257],"type":"Point"}
}