{
  "type": "Feature",
  "properties": {
    "iso:country":"CA",
    "sg:address":"175 Exeter Rd",
    "sg:city":"London",
    "sg:classifiers":[
        {
            "category":"Manufacturing",
            "subcategory":"Watercraft",
            "type":"Manufacturing & Wholesale Goods"
        }
    ],
    "sg:phone":"+1 519 652 2272",
    "sg:postcode":"N6L 1A4",
    "sg:province":"ON",
    "sg:tags":[
        "boat"
    ],
    "wof:name":"Fluidesign Composites Inc",
    "wof:placetype":"venue"
},
  "geometry": {"coordinates":[-81.26313018800001,42.9217758179],"type":"Point"}
}