{
  "type": "Feature",
  "properties": {
    "iso:country":"CA",
    "sg:address":"12 Vincent St",
    "sg:city":"Newmarket",
    "sg:classifiers":[
        {
            "category":"Professional",
            "subcategory":"Computer Services",
            "type":"Services"
        }
    ],
    "sg:phone":"+1 905 836 4442",
    "sg:postcode":"L3Y 4G2",
    "sg:province":"ON",
    "sg:tags":[
        "website",
        "design"
    ],
    "wof:name":"Treefrog Interactive",
    "wof:placetype":"venue"
},
  "geometry": {"coordinates":[-79.464172,44.059002],"type":"Point"}
}