{
  "type": "Feature",
  "properties": {
    "addr:full":"766 Victor St Winnipeg MB R3E 1Y6",
    "addr:housenumber":"766",
    "addr:postcode":"r3e 1y6",
    "addr:street":"Victor St",
    "iso:country":"CA",
    "sg:address":"766 Victor St",
    "sg:city":"Winnipeg",
    "sg:classifiers":[
        {
            "category":"Social Services",
            "subcategory":"Child Care",
            "type":"Services"
        }
    ],
    "sg:phone":"+1 204 775 0946",
    "sg:postcode":"R3E 1Y6",
    "sg:province":"MB",
    "wof:name":"Victor Play Ctr Inc",
    "wof:placetype":"venue"
},
  "geometry": {"coordinates":[-97.16274300000001,49.900612],"type":"Point"}
}