{
  "type": "Feature",
  "properties": {
    "addr:full":"Abbotsford BC V2T 4A9",
    "addr:postcode":"v2t 4a9",
    "iso:country":"CA",
    "sg:city":"Abbotsford",
    "sg:classifiers":[
        {
            "category":"Real Estate",
            "subcategory":"Real Estate Operator",
            "type":"Services"
        }
    ],
    "sg:phone":"+1 604 864 8565",
    "sg:postcode":"V2T 4A9",
    "sg:province":"BC",
    "sg:tags":[
        "apartment"
    ],
    "wof:name":"Charlotte Manor",
    "wof:placetype":"venue"
},
  "geometry": {"coordinates":[-122.338165,49.057816],"type":"Point"}
}