{
  "type": "Feature",
  "properties": {
    "addr:full":"6270 Ch DE LA Cote-Des-Neiges Montreal QC H3S 2A3",
    "addr:postcode":"6270;h3s 2a3",
    "addr:street":"Ch De La Cote-Des-Neiges",
    "iso:country":"CA",
    "sg:address":"6270 Ch DE LA Cote-Des-Neiges",
    "sg:city":"Montreal",
    "sg:classifiers":[
        {
            "category":"Shopping",
            "subcategory":"Clothing, Apparel, & Fashions",
            "type":"Retail Goods"
        }
    ],
    "sg:phone":"+1 514 341 1394",
    "sg:postcode":"H3S 2A3",
    "sg:province":"QC",
    "sg:tags":[
        "item",
        "boutique"
    ],
    "wof:name":"Uma Sarees",
    "wof:placetype":"venue"
},
  "geometry": {"coordinates":[-73.6335678101,45.5013198853],"type":"Point"}
}