{
  "type": "Feature",
  "properties": {
    "iso:country":"CA",
    "sg:city":"Cobourg",
    "sg:classifiers":[
        {
            "category":"Retail",
            "subcategory":"Auto Repair",
            "type":"Services"
        }
    ],
    "sg:phone":"+1 905 373 9030",
    "sg:postcode":"K9A 5G7",
    "sg:province":"ON",
    "sg:tags":[
        "repairing",
        "automobile"
    ],
    "wof:name":"Goodyear Certified Auto Svc",
    "wof:placetype":"venue"
},
  "geometry": {"coordinates":[-78.1804351807,43.9625205994],"type":"Point"}
}