{
  "type": "Feature",
  "properties": {
    "addr:full":"800 Macleod Trail SE Calgary AB T2G 2M3",
    "addr:housenumber":"800",
    "addr:postcode":"t2g 2m3",
    "addr:street":"Macleod Trail Se",
    "iso:country":"CA",
    "sg:address":"800 Macleod Trail SE",
    "sg:city":"Calgary",
    "sg:classifiers":[
        {
            "category":"Shopping",
            "subcategory":"Tobacco",
            "type":"Retail Goods"
        }
    ],
    "sg:phone":"+1 403 233 0223",
    "sg:postcode":"T2G 2M3",
    "sg:province":"AB",
    "sg:tags":[
        "cigarette",
        "cigar",
        "dealer"
    ],
    "wof:name":"City Hall Smoke Shop",
    "wof:placetype":"venue"
},
  "geometry": {"coordinates":[-114.057991028,51.0452651978],"type":"Point"}
}