{
  "type": "Feature",
  "properties": {
    "iso:country":"CA",
    "sg:city":"Quebec",
    "sg:classifiers":[
        {
            "category":"Museum",
            "type":"Entertainment"
        }
    ],
    "sg:phone":"+1 418 691 3690",
    "sg:postcode":"G1K 3P9",
    "sg:province":"QC",
    "sg:tags":[
        "organization",
        "arts",
        "information"
    ],
    "wof:name":"Ateliers DE Creation",
    "wof:placetype":"venue"
},
  "geometry": {"coordinates":[-71.221252,46.812679],"type":"Point"}
}