{
  "type": "Feature",
  "properties": {
    "addr:full":"Timmins ON P4N 2R4",
    "addr:postcode":"p4n 2r4",
    "iso:country":"CA",
    "sg:city":"Timmins",
    "sg:classifiers":[
        {
            "category":"Banks & Credit Unions",
            "subcategory":"Investment Brokerage",
            "type":"Services"
        }
    ],
    "sg:phone":"+1 705 264 1414",
    "sg:postcode":"P4N 2R4",
    "sg:province":"ON",
    "sg:tags":[
        "consultant",
        "planning",
        "financial"
    ],
    "wof:name":"Berkshire Securities Inc",
    "wof:placetype":"venue"
},
  "geometry": {"coordinates":[-81.33754,48.476021],"type":"Point"}
}