{
  "type": "Feature",
  "properties": {
    "addr:full":"1023 7 Ave SW Calgary AB T2P 1A8",
    "addr:housenumber":"1023",
    "addr:postcode":"t2p 1a8",
    "addr:street":"7 Ave Sw",
    "iso:country":"CA",
    "sg:address":"1023 7 Ave SW",
    "sg:city":"Calgary",
    "sg:classifiers":[
        {
            "category":"Restaurant",
            "type":"Food & Drink"
        }
    ],
    "sg:phone":"+1 403 269 3365",
    "sg:postcode":"T2P 1A8",
    "sg:province":"AB",
    "sg:tags":[
        "sandwich"
    ],
    "wof:name":"C & A Deli Lunchbreak",
    "wof:placetype":"venue"
},
  "geometry": {"coordinates":[-114.08432000000001,51.046993],"type":"Point"}
}