{
  "type": "Feature",
  "properties": {
    "addr:full":"870 Upper Canada Dr #7 Sarnia ON N7W 1A4",
    "addr:housenumber":"870",
    "addr:postcode":"n7w 1a4",
    "addr:street":"Upper Canada Dr # 7",
    "iso:country":"CA",
    "sg:address":"870 Upper Canada Dr #7",
    "sg:city":"Sarnia",
    "sg:classifiers":[
        {
            "category":"Wholesale",
            "subcategory":"Machinery & Supplies",
            "type":"Manufacturing & Wholesale Goods"
        }
    ],
    "sg:phone":"+1 519 337 3258",
    "sg:postcode":"N7W 1A4",
    "sg:province":"ON",
    "sg:tags":[
        "bearing"
    ],
    "wof:name":"Canadian Bearings Ltd",
    "wof:placetype":"venue"
},
  "geometry": {"coordinates":[-82.342522,42.965027],"type":"Point"}
}