{
  "type": "Feature",
  "properties": {
    "iso:country":"CA",
    "sg:city":"Calgary",
    "sg:classifiers":[
        {
            "category":"Home & Garden",
            "subcategory":"Household Appliances",
            "type":"Retail Goods"
        }
    ],
    "sg:phone":"+1 403 276 8571",
    "sg:postcode":"T2E 6T1",
    "sg:province":"AB",
    "sg:tags":[
        "cleaners",
        "vacuum"
    ],
    "wof:name":"Vac Shop",
    "wof:placetype":"venue"
},
  "geometry": {"coordinates":[-114.051933289,51.0871315002],"type":"Point"}
}