{
  "type": "Feature",
  "properties": {
    "iso:country":"CA",
    "sg:address":"800 DE L'Hotel-DE-Ville",
    "sg:city":"Chandler",
    "sg:classifiers":[
        {
            "category":"Recreation",
            "type":"Entertainment"
        }
    ],
    "sg:phone":"+1 418 689 5533",
    "sg:postcode":"G0C 1K0",
    "sg:province":"QC",
    "sg:tags":[
        "amusement"
    ],
    "wof:name":"Club DE Motoneige Les Sentiers",
    "wof:placetype":"venue"
},
  "geometry": {"coordinates":[-64.68110656739999,48.354259491],"type":"Point"}
}