{
  "type": "Feature",
  "properties": {
    "addr:full":"446 Main St Alberton PE C0B 1B0",
    "addr:housenumber":"446",
    "addr:postcode":"c0b 1b0",
    "addr:street":"Main St",
    "iso:country":"CA",
    "sg:address":"446 Main St",
    "sg:city":"Alberton",
    "sg:classifiers":[
        {
            "category":"Autos & Motor Vehicles",
            "subcategory":"Auto Supplies",
            "type":"Retail Goods"
        }
    ],
    "sg:phone":"+1 902 853 2400",
    "sg:postcode":"C0B 1B0",
    "sg:province":"PE",
    "sg:tags":[
        "automobile",
        "parts"
    ],
    "wof:name":"Napa Auto Parts",
    "wof:placetype":"venue"
},
  "geometry": {"coordinates":[-64.06368999999999,46.811077],"type":"Point"}
}