{
  "type": "Feature",
  "properties": {
    "addr:full":"519 Highfield Cres Weyburn SK S4H 0R8",
    "addr:housenumber":"519",
    "addr:postcode":"s4h 0r8",
    "addr:street":"Highfield Cres",
    "iso:country":"CA",
    "sg:address":"519 Highfield Cres",
    "sg:city":"Weyburn",
    "sg:classifiers":[
        {
            "category":"Professional",
            "subcategory":"Management & Consulting",
            "type":"Services"
        }
    ],
    "sg:phone":"+1 306 842 0563",
    "sg:postcode":"S4H 0R8",
    "sg:province":"SK",
    "sg:tags":[
        "consultant",
        "business"
    ],
    "wof:name":"Pioneer 2001 Corp Ltd",
    "wof:placetype":"venue"
},
  "geometry": {"coordinates":[-103.855659485,49.668926239],"type":"Point"}
}