{
  "type": "Feature",
  "properties": {
    "addr:full":"96 Cowley Ave Etobicoke ON M9B 2E5",
    "addr:housenumber":"96",
    "addr:postcode":"m9b 2e5",
    "addr:street":"Cowley Ave",
    "iso:country":"CA",
    "sg:address":"96 Cowley Ave",
    "sg:city":"Etobicoke",
    "sg:classifiers":[
        {
            "category":"Professional",
            "subcategory":"Employment Agencies",
            "type":"Services"
        }
    ],
    "sg:phone":"+1 416 626 9100",
    "sg:postcode":"M9B 2E5",
    "sg:province":"ON",
    "sg:tags":[
        "opportunity"
    ],
    "wof:name":"Williams & Assoc Inc",
    "wof:placetype":"venue"
},
  "geometry": {"coordinates":[-79.56020355219999,43.6511650085],"type":"Point"}
}