{
  "type": "Feature",
  "properties": {
    "iso:country":"CA",
    "sg:address":"1074 Route 105",
    "sg:city":"Douglas",
    "sg:classifiers":[
        {
            "category":"Travel",
            "subcategory":"Hotels & Motels",
            "type":"Entertainment"
        }
    ],
    "sg:phone":"+1 506 363 4279",
    "sg:postcode":"E3A 7J5",
    "sg:province":"NB",
    "sg:tags":[
        "breakfast",
        "accommodation",
        "bed"
    ],
    "wof:name":"Raven's Rook",
    "wof:placetype":"venue"
},
  "geometry": {"coordinates":[-66.7470779419,45.9806594849],"type":"Point"}
}