{
  "type": "Feature",
  "properties": {
    "addr:full":"5022 50th St Provost AB T0B 3S0",
    "addr:housenumber":"5022",
    "addr:postcode":"t0b 3s0",
    "addr:street":"50Th St",
    "iso:country":"CA",
    "sg:address":"5022 50th St",
    "sg:city":"Provost",
    "sg:classifiers":[
        {
            "category":"Shopping",
            "subcategory":"Gifts & Souvenirs",
            "type":"Retail Goods"
        }
    ],
    "sg:phone":"+1 780 753 3962",
    "sg:postcode":"T0B 3S0",
    "sg:province":"AB",
    "sg:tags":[
        "shop"
    ],
    "wof:name":"Cazes Gift Shop",
    "wof:placetype":"venue"
},
  "geometry": {"coordinates":[-110.264709,52.351696],"type":"Point"}
}