{
  "type": "Feature",
  "properties": {
    "iso:country":"CA",
    "sg:address":"1342 Rue Notre-Dame",
    "sg:city":"Repentigny",
    "sg:classifiers":[
        {
            "category":"Wholesale",
            "subcategory":"Non-durable Goods",
            "type":"Manufacturing & Wholesale Goods"
        }
    ],
    "sg:phone":"+1 450 654 5562",
    "sg:postcode":"J5Y 3X1",
    "sg:province":"QC",
    "sg:tags":[
        "pet",
        "supply"
    ],
    "wof:name":"Litiere Magic",
    "wof:placetype":"venue"
},
  "geometry": {"coordinates":[-73.40300000000001,45.78112],"type":"Point"}
}