{
  "type": "Feature",
  "properties": {
    "addr:full":"11706 87 Ave NW Edmonton AB T6G 0Y3",
    "addr:housenumber":"11706",
    "addr:postcode":"t6g 0y3",
    "addr:street":"87 Ave Nw",
    "iso:country":"CA",
    "sg:address":"11706 87 Ave NW",
    "sg:city":"Edmonton",
    "sg:classifiers":[
        {
            "category":"Personal",
            "subcategory":"Beauty Salon",
            "type":"Services"
        }
    ],
    "sg:phone":"+1 780 439 1284",
    "sg:postcode":"T6G 0Y3",
    "sg:province":"AB",
    "wof:name":"Hair Plus",
    "wof:placetype":"venue"
},
  "geometry": {"coordinates":[-113.53276099999999,53.523079],"type":"Point"}
}