{
  "type": "Feature",
  "properties": {
    "addr:full":"4 Donlands Ave Toronto ON M4J 3N4",
    "addr:housenumber":"4",
    "addr:postcode":"m4j 3n4",
    "addr:street":"Donlands Ave",
    "iso:country":"CA",
    "sg:address":"4 Donlands Ave",
    "sg:city":"Toronto",
    "sg:classifiers":[
        {
            "category":"Food & Beverages",
            "subcategory":"Groceries & Convenience Stores",
            "type":"Retail Goods"
        }
    ],
    "sg:phone":"+1 416 465 1877",
    "sg:postcode":"M4J 3N4",
    "sg:province":"ON",
    "wof:name":"Donlands Variety",
    "wof:placetype":"venue"
},
  "geometry": {"coordinates":[-79.337502,43.680504],"type":"Point"}
}