{
  "type": "Feature",
  "properties": {
    "iso:country":"CA",
    "sg:address":"4 Donlands Ave",
    "sg:city":"Toronto",
    "sg:classifiers":[
        {
            "category":"Food & Beverages",
            "subcategory":"Groceries & Convenience Stores",
            "type":"Retail Goods"
        }
    ],
    "sg:phone":"+1 416 465 1877",
    "sg:postcode":"M4J 3N4",
    "sg:province":"ON",
    "wof:name":"Donlands Variety",
    "wof:placetype":"venue"
},
  "geometry": {"coordinates":[-79.337502,43.680504],"type":"Point"}
}