{
  "type": "Feature",
  "properties": {
    "addr:full":"826 1Re Rue Iberville QC J2X 3C4",
    "addr:housenumber":"826",
    "addr:postcode":"j2x 3c4",
    "addr:street":"1Re Rue Iberville",
    "iso:country":"CA",
    "sg:address":"826 1Re Rue",
    "sg:city":"Iberville",
    "sg:classifiers":[
        {
            "category":"Retail",
            "subcategory":"Funeral Services",
            "type":"Services"
        }
    ],
    "sg:phone":"+1 450 346 1124",
    "sg:postcode":"J2X 3C4",
    "sg:province":"QC",
    "sg:tags":[
        "director"
    ],
    "wof:name":"Centre Funeraire Desrochers",
    "wof:placetype":"venue"
},
  "geometry": {"coordinates":[-73.240776,45.303532],"type":"Point"}
}