{
  "type": "Feature",
  "properties": {
    "addr:full":"Blaketown NL A0B 1C0",
    "addr:postcode":"a0b 1c0",
    "iso:country":"CA",
    "sg:city":"Blaketown",
    "sg:classifiers":[
        {
            "category":"Home & Garden",
            "subcategory":"Furniture",
            "type":"Retail Goods"
        }
    ],
    "sg:phone":"+1 709 759 2112",
    "sg:postcode":"A0B 1C0",
    "sg:province":"NL",
    "sg:tags":[
        "equipment",
        "kitchen",
        "cabinet"
    ],
    "wof:name":"Hilco Custom Cabinetry Ltd",
    "wof:placetype":"venue"
},
  "geometry": {"coordinates":[-53.551594,47.491055],"type":"Point"}
}