{
  "type": "Feature",
  "properties": {
    "addr:full":"1320 Kingsway Ave Port Coquitlam BC V3C 6P4",
    "addr:housenumber":"1320",
    "addr:postcode":"v3c 6p4",
    "addr:street":"Kingsway Ave",
    "iso:country":"CA",
    "sg:address":"1320 Kingsway Ave",
    "sg:city":"Port Coquitlam",
    "sg:classifiers":[
        {
            "category":"Food & Beverages",
            "subcategory":"Bakery",
            "type":"Retail Goods"
        }
    ],
    "sg:phone":"+1 604 468 8870",
    "sg:postcode":"V3C 6P4",
    "sg:province":"BC",
    "sg:tags":[
        "doughnut"
    ],
    "wof:name":"Tim Hortons",
    "wof:placetype":"venue"
},
  "geometry": {"coordinates":[-122.751350403,49.2479362488],"type":"Point"}
}