{
  "type": "Feature",
  "properties": {
    "addr:full":"647 Windmill Rd Dartmouth NS B3B 1B7",
    "addr:housenumber":"647",
    "addr:postcode":"b3b 1b7",
    "addr:street":"Windmill Rd",
    "iso:country":"CA",
    "sg:address":"647 Windmill Rd",
    "sg:city":"Dartmouth",
    "sg:classifiers":[
        {
            "category":"Manufacturing",
            "subcategory":"Glass & Minerals",
            "type":"Manufacturing & Wholesale Goods"
        }
    ],
    "sg:phone":"+1 902 468 5967",
    "sg:postcode":"B3B 1B7",
    "sg:province":"NS",
    "sg:tags":[
        "fabricator",
        "fiber"
    ],
    "wof:name":"Sea Glass Industries Ltd",
    "wof:placetype":"venue"
},
  "geometry": {"coordinates":[-63.606212616,44.6991920471],"type":"Point"}
}