{
  "type": "Feature",
  "properties": {
    "addr:full":"Ottawa ON K2C 3L7",
    "addr:postcode":"k2c 3l7",
    "iso:country":"CA",
    "sg:city":"Ottawa",
    "sg:classifiers":[
        {
            "category":"Real Estate",
            "subcategory":"Real Estate Operator",
            "type":"Services"
        }
    ],
    "sg:phone":"+1 613 224 4381",
    "sg:postcode":"K2C 3L7",
    "sg:province":"ON",
    "sg:tags":[
        "apartment"
    ],
    "wof:name":"Castle Hill Apartments",
    "wof:placetype":"venue"
},
  "geometry": {"coordinates":[-75.746529,45.368629],"type":"Point"}
}