{
  "type": "Feature",
  "properties": {
    "addr:full":"35 Rue Kilteevan Hudson QC J0P 1H0",
    "addr:housenumber":"35",
    "addr:postcode":"j0p 1h0",
    "addr:street":"Rue Kilteevan",
    "iso:country":"CA",
    "sg:address":"35 Rue Kilteevan",
    "sg:city":"Hudson",
    "sg:classifiers":[
        {
            "category":"Manufacturing",
            "subcategory":"Tools & Machinery",
            "type":"Manufacturing & Wholesale Goods"
        }
    ],
    "sg:phone":"+1 450 458 1880",
    "sg:postcode":"J0P 1H0",
    "sg:province":"QC",
    "sg:tags":[
        "electric",
        "motor"
    ],
    "wof:name":"Hemco Canada Inc",
    "wof:placetype":"venue"
},
  "geometry": {"coordinates":[-74.1353759766,45.4504127502],"type":"Point"}
}