{
  "type": "Feature",
  "properties": {
    "iso:country":"CA",
    "sg:city":"Burnaby",
    "sg:classifiers":[
        {
            "category":"Social Services",
            "subcategory":"Job Training",
            "type":"Services"
        }
    ],
    "sg:phone":"+1 604 435 1937",
    "sg:postcode":"V5H 4C2",
    "sg:province":"BC",
    "sg:tags":[
        "employment"
    ],
    "wof:name":"Youth Employment Skills Canada",
    "wof:placetype":"venue"
},
  "geometry": {"coordinates":[-122.991355896,49.2257385254],"type":"Point"}
}