{
  "type": "Feature",
  "properties": {
    "addr:full":"191 Av Oneida Pointe-Claire QC H9R 1A9",
    "addr:postcode":"h9r 1a9",
    "addr:street":"191 Av",
    "iso:country":"CA",
    "sg:address":"191 Av Oneida",
    "sg:city":"Pointe-Claire",
    "sg:classifiers":[
        {
            "category":"Wholesale",
            "subcategory":"Machinery & Supplies",
            "type":"Manufacturing & Wholesale Goods"
        }
    ],
    "sg:phone":"+1 514 630 6886",
    "sg:postcode":"H9R 1A9",
    "sg:province":"QC",
    "sg:tags":[
        "compressor",
        "gas"
    ],
    "wof:name":"Tlm Machinerie & Equipement",
    "wof:placetype":"venue"
},
  "geometry": {"coordinates":[-73.81048583979999,45.4756164551],"type":"Point"}
}