{
  "type": "Feature",
  "properties": {
    "addr:full":"616 Mount Pleasant Rd Toronto ON M4S 2M8",
    "addr:housenumber":"616",
    "addr:postcode":"m4s 2m8",
    "addr:street":"Mount Pleasant Rd",
    "iso:country":"CA",
    "sg:address":"616 Mount Pleasant Rd",
    "sg:city":"Toronto",
    "sg:classifiers":[
        {
            "category":"Shopping",
            "subcategory":"Clothing, Apparel, & Fashions",
            "type":"Retail Goods"
        }
    ],
    "sg:phone":"+1 416 932 3727",
    "sg:postcode":"M4S 2M8",
    "sg:province":"ON",
    "sg:tags":[
        "second",
        "infant",
        "store",
        "hand"
    ],
    "wof:name":"Bean Sprout",
    "wof:placetype":"venue"
},
  "geometry": {"coordinates":[-79.3885879517,43.7039833069],"type":"Point"}
}