{
  "type": "Feature",
  "properties": {
    "iso:country":"CA",
    "sg:address":"100 Bayshore Dr",
    "sg:city":"Nepean",
    "sg:classifiers":[
        {
            "category":"Personal",
            "type":"Services"
        }
    ],
    "sg:phone":"+1 613 829 3651",
    "sg:postcode":"K2B 8C1",
    "sg:province":"ON",
    "sg:tags":[
        "wear",
        "formal"
    ],
    "wof:name":"Tip Top Tailors",
    "wof:placetype":"venue"
},
  "geometry": {"coordinates":[-75.8050918579,45.3490791321],"type":"Point"}
}