{
  "type": "Feature",
  "properties": {
    "addr:full":"250 Pitt St Cornwall ON K6J 3P6",
    "addr:housenumber":"250",
    "addr:postcode":"k6j 3p6",
    "addr:street":"Pitt St",
    "iso:country":"CA",
    "sg:address":"250 Pitt St",
    "sg:city":"Cornwall",
    "sg:classifiers":[
        {
            "category":"Shopping",
            "subcategory":"Stationery & Office Supplies",
            "type":"Retail Goods"
        }
    ],
    "sg:phone":"+1 613 932 3560",
    "sg:postcode":"K6J 3P6",
    "sg:province":"ON",
    "wof:name":"Stormont Stationers Ltd",
    "wof:placetype":"venue"
},
  "geometry": {"coordinates":[-74.72931699999999,45.018986],"type":"Point"}
}