{
  "type": "Feature",
  "properties": {
    "addr:full":"Consort AB T0C 1B0",
    "addr:postcode":"t0c 1b0",
    "iso:country":"CA",
    "sg:city":"Consort",
    "sg:classifiers":[
        {
            "category":"Wholesale",
            "subcategory":"Machinery & Supplies",
            "type":"Manufacturing & Wholesale Goods"
        }
    ],
    "sg:phone":"+1 403 577 3900",
    "sg:postcode":"T0C 1B0",
    "sg:province":"AB",
    "sg:tags":[
        "farm",
        "equipment",
        "parts",
        "automobile"
    ],
    "wof:name":"Consort Ag & Auto Inc",
    "wof:placetype":"venue"
},
  "geometry": {"coordinates":[-110.772476,52.007229],"type":"Point"}
}