{
  "type": "Feature",
  "properties": {
    "addr:full":"13040 Worster Crt Richmond BC V6V 2B3",
    "addr:housenumber":"13040",
    "addr:postcode":"v6v 2b3",
    "addr:street":"Worster Crt",
    "iso:country":"CA",
    "sg:address":"13040 Worster Crt",
    "sg:city":"Richmond",
    "sg:classifiers":[
        {
            "category":"Wholesale",
            "subcategory":"Electrical",
            "type":"Manufacturing & Wholesale Goods"
        }
    ],
    "sg:phone":"+1 604 270 1311",
    "sg:postcode":"V6V 2B3",
    "sg:province":"BC",
    "sg:tags":[
        "high",
        "fidelity",
        "stereophonic"
    ],
    "wof:name":"Jvc Canada Inc",
    "wof:placetype":"venue"
},
  "geometry": {"coordinates":[-123.080055,49.178814],"type":"Point"}
}