{
  "type": "Feature",
  "properties": {
    "addr:full":"Calgary AB T2P 3E5",
    "addr:postcode":"t2p 3e5",
    "iso:country":"CA",
    "sg:city":"Calgary",
    "sg:classifiers":[
        {
            "category":"Professional",
            "subcategory":"Management & Consulting",
            "type":"Services"
        }
    ],
    "sg:phone":"+1 403 263 1523",
    "sg:postcode":"T2P 3E5",
    "sg:province":"AB",
    "sg:tags":[
        "consultant",
        "business"
    ],
    "wof:name":"Flood & CO",
    "wof:placetype":"venue"
},
  "geometry": {"coordinates":[-114.079697,51.048042],"type":"Point"}
}