{
  "type": "Feature",
  "properties": {
    "addr:full":"533 Ouellette Ave Windsor ON N9A 4J3",
    "addr:housenumber":"533",
    "addr:postcode":"n9a 4j3",
    "addr:street":"Ouellette Ave",
    "iso:country":"CA",
    "sg:address":"533 Ouellette Ave",
    "sg:city":"Windsor",
    "sg:classifiers":[
        {
            "category":"Food & Beverages",
            "subcategory":"Specialty",
            "type":"Retail Goods"
        }
    ],
    "sg:phone":"+1 519 254 8486",
    "sg:postcode":"N9A 4J3",
    "sg:province":"ON",
    "sg:tags":[
        "oriental"
    ],
    "wof:name":"Silk Road Express",
    "wof:placetype":"venue"
},
  "geometry": {"coordinates":[-83.037277,42.314526],"type":"Point"}
}