{
  "type": "Feature",
  "properties": {
    "addr:full":"Scarborough ON M1S 5A3",
    "addr:postcode":"m1s 5a3",
    "iso:country":"CA",
    "sg:city":"Scarborough",
    "sg:classifiers":[
        {
            "category":"Wholesale",
            "subcategory":"Electrical",
            "type":"Manufacturing & Wholesale Goods"
        }
    ],
    "sg:phone":"+1 416 293 0737",
    "sg:postcode":"M1S 5A3",
    "sg:province":"ON",
    "sg:tags":[
        "light",
        "tube",
        "bulb"
    ],
    "wof:name":"Action Sales & Lighting Ltd",
    "wof:placetype":"venue"
},
  "geometry": {"coordinates":[-79.25567599999999,43.810406],"type":"Point"}
}