{
  "type": "Feature",
  "properties": {
    "addr:full":"Richmond Hill ON L4C 0A8",
    "addr:postcode":"l4c 0a8",
    "iso:country":"CA",
    "sg:city":"Richmond Hill",
    "sg:classifiers":[
        {
            "category":"Retail",
            "subcategory":"Laundry & Dry Cleaning",
            "type":"Services"
        }
    ],
    "sg:phone":"+1 905 508 6363",
    "sg:postcode":"L4C 0A8",
    "sg:province":"ON",
    "sg:tags":[
        "cleaners"
    ],
    "wof:name":"London Cleaners Inc",
    "wof:placetype":"venue"
},
  "geometry": {"coordinates":[-79.43302199999999,43.853874],"type":"Point"}
}