{
  "type": "Feature",
  "properties": {
    "addr:full":"Calgary AB T1Y 6E8",
    "addr:postcode":"t1y 6e8",
    "iso:country":"CA",
    "sg:city":"Calgary",
    "sg:classifiers":[
        {
            "category":"Retail",
            "subcategory":"Veterinary Services",
            "type":"Services"
        }
    ],
    "sg:phone":"+1 403 285 8777",
    "sg:postcode":"T1Y 6E8",
    "sg:province":"AB",
    "sg:tags":[
        "veterinarian"
    ],
    "wof:name":"Duncan, R DVM",
    "wof:placetype":"venue"
},
  "geometry": {"coordinates":[-113.982834,51.071735],"type":"Point"}
}