{
  "type": "Feature",
  "properties": {
    "addr:full":"7152 Airport Rd Mississauga ON L4T 2H1",
    "addr:housenumber":"7152",
    "addr:postcode":"l4t 2h1",
    "addr:street":"Airport Rd",
    "iso:country":"CA",
    "sg:address":"7152 Airport Rd",
    "sg:city":"Mississauga",
    "sg:classifiers":[
        {
            "category":"Professional",
            "subcategory":"Lawyer & Legal Services",
            "type":"Services"
        }
    ],
    "sg:phone":"+1 905 678 7418",
    "sg:postcode":"L4T 2H1",
    "sg:province":"ON",
    "sg:tags":[
        "attorney"
    ],
    "wof:name":"Lorenz, Thomas H",
    "wof:placetype":"venue"
},
  "geometry": {"coordinates":[-79.6465301514,43.7065658569],"type":"Point"}
}