{
  "type": "Feature",
  "properties": {
    "addr:full":"Calgary AB T2E 8M5",
    "addr:postcode":"t2e 8m5",
    "iso:country":"CA",
    "sg:city":"Calgary",
    "sg:classifiers":[
        {
            "category":"Wholesale",
            "subcategory":"Office Equipment",
            "type":"Manufacturing & Wholesale Goods"
        }
    ],
    "sg:phone":"+1 403 248 2348",
    "sg:postcode":"T2E 8M5",
    "sg:province":"AB",
    "sg:tags":[
        "register",
        "cash",
        "supply"
    ],
    "wof:name":"Info Spec Systems Inc",
    "wof:placetype":"venue"
},
  "geometry": {"coordinates":[-114.00505065900001,51.0954627991],"type":"Point"}
}