{
  "type": "Feature",
  "properties": {
    "iso:country":"CA",
    "sg:address":"460 Rue Sainte-Catherine O # 651",
    "sg:city":"Montreal",
    "sg:classifiers":[
        {
            "category":"Shopping",
            "subcategory":"Computers & Home Electronics",
            "type":"Retail Goods"
        }
    ],
    "sg:phone":"+1 514 393 2600",
    "sg:postcode":"H3B 1A7",
    "sg:province":"QC",
    "sg:tags":[
        "equipment",
        "electronic",
        "supply"
    ],
    "wof:name":"Future Shop",
    "wof:placetype":"venue"
},
  "geometry": {"coordinates":[-73.559792,45.514194],"type":"Point"}
}