{
  "type": "Feature",
  "properties": {
    "addr:full":"32 Main St Grand Bend ON N0M 1T0",
    "addr:housenumber":"32",
    "addr:postcode":"n0m 1t0",
    "addr:street":"Main St",
    "iso:country":"CA",
    "sg:address":"32 Main St",
    "sg:city":"Grand Bend",
    "sg:classifiers":[
        {
            "category":"Professional",
            "type":"Services"
        }
    ],
    "sg:phone":"+1 519 238 2084",
    "sg:postcode":"N0M 1T0",
    "sg:province":"ON",
    "sg:tags":[
        "establishment"
    ],
    "wof:name":"Jalapenos",
    "wof:placetype":"venue"
},
  "geometry": {"coordinates":[-81.7515945435,43.3098106384],"type":"Point"}
}