{
  "type": "Feature",
  "properties": {
    "iso:country":"CA",
    "sg:address":"1988 Vernon Dr",
    "sg:city":"Vancouver",
    "sg:classifiers":[
        {
            "category":"Wholesale",
            "subcategory":"Fruits & Vegetables",
            "type":"Manufacturing & Wholesale Goods"
        }
    ],
    "sg:phone":"+1 604 255 6522",
    "sg:postcode":"V6A 3Y6",
    "sg:province":"BC",
    "wof:name":"Yen Brothers Produce Ltd",
    "wof:placetype":"venue"
},
  "geometry": {"coordinates":[-123.07833862299999,49.2672348022],"type":"Point"}
}