{
  "type": "Feature",
  "properties": {
    "iso:country":"CA",
    "sg:city":"Oakville",
    "sg:classifiers":[
        {
            "category":"Health Services",
            "subcategory":"Doctor",
            "type":"Services"
        }
    ],
    "sg:phone":"+1 905 845 3415",
    "sg:postcode":"L6J 3L9",
    "sg:province":"ON",
    "sg:tags":[
        "physician",
        "surgeon"
    ],
    "wof:name":"Wu, H T MD",
    "wof:placetype":"venue"
},
  "geometry": {"coordinates":[-79.675446,43.453564],"type":"Point"}
}