{
  "type": "Feature",
  "properties": {
    "addr:full":"1704 Rte Du Carrefour Val-Des-Monts QC J8N 7E9",
    "addr:housenumber":"1704",
    "addr:postcode":"j8n 7e9",
    "addr:street":"Rte Du Carrefour",
    "iso:country":"CA",
    "sg:address":"1704 Rte Du Carrefour",
    "sg:city":"Val-Des-Monts",
    "sg:classifiers":[
        {
            "category":"Wholesale",
            "subcategory":"Machinery & Supplies",
            "type":"Manufacturing & Wholesale Goods"
        }
    ],
    "sg:phone":"+1 819 671 3877",
    "sg:postcode":"J8N 7E9",
    "sg:province":"QC",
    "sg:tags":[
        "plumbing",
        "pump",
        "fixture"
    ],
    "wof:name":"Aqua Pompes Plus",
    "wof:placetype":"venue"
},
  "geometry": {"coordinates":[-75.6212387085,45.6015167236],"type":"Point"}
}