{
  "type": "Feature",
  "properties": {
    "iso:country":"CA",
    "sg:address":"40 King St",
    "sg:city":"Saint John",
    "sg:classifiers":[
        {
            "category":"Professional",
            "subcategory":"Management & Consulting",
            "type":"Services"
        }
    ],
    "sg:phone":"+1 506 658 2877",
    "sg:postcode":"E2L 1G3",
    "sg:province":"NB",
    "sg:tags":[
        "development",
        "economic",
        "agency"
    ],
    "wof:name":"Enterprise St John",
    "wof:placetype":"venue"
},
  "geometry": {"coordinates":[-66.060722,45.273033],"type":"Point"}
}