{
  "type": "Feature",
  "properties": {
    "addr:full":"41 Del Aqueduc Saint-Felix-DE-Dalquier QC J0Y 1G0",
    "addr:housenumber":"41",
    "addr:postcode":"j0y 1g0",
    "addr:street":"Del Aqueduc Saint-Felix-De-Dalquier",
    "iso:country":"CA",
    "sg:address":"41 Del Aqueduc",
    "sg:city":"Saint-Felix-DE-Dalquier",
    "sg:classifiers":[
        {
            "category":"Government",
            "subcategory":"Office",
            "type":"Public Place"
        }
    ],
    "sg:phone":"+1 819 727 1806",
    "sg:postcode":"J0Y 1G0",
    "sg:province":"QC",
    "sg:tags":[
        "village"
    ],
    "wof:name":"St Felix DE Dalquier Sportif",
    "wof:placetype":"venue"
},
  "geometry": {"coordinates":[-78.1092910767,48.6750526428],"type":"Point"}
}