{
  "type": "Feature",
  "properties": {
    "iso:country":"CA",
    "sg:address":"49 Church St S",
    "sg:city":"Ajax",
    "sg:classifiers":[
        {
            "category":"Personal",
            "subcategory":"Beauty Salon",
            "type":"Services"
        }
    ],
    "sg:phone":"+1 905 686 1285",
    "sg:postcode":"L1S 6A6",
    "sg:province":"ON",
    "wof:name":"Salon",
    "wof:placetype":"venue"
},
  "geometry": {"coordinates":[-79.05457305909999,43.8531837463],"type":"Point"}
}