{
  "type": "Feature",
  "properties": {
    "iso:country":"CA",
    "sg:address":"900 Rue Papineau",
    "sg:city":"Joliette",
    "sg:classifiers":[
        {
            "category":"Utilities",
            "subcategory":"Fuel Oil & Lpg",
            "type":"Services"
        }
    ],
    "sg:phone":"+1 450 759 9522",
    "sg:postcode":"J6E 2L7",
    "sg:province":"QC",
    "wof:name":"Poirier Jean-Noel & Fils Inc",
    "wof:placetype":"venue"
},
  "geometry": {"coordinates":[-73.45584869379999,46.0269165039],"type":"Point"}
}