{
  "type": "Feature",
  "properties": {
    "iso:country":"CA",
    "sg:address":"1830 Boul Fortin",
    "sg:city":"Laval",
    "sg:classifiers":[
        {
            "category":"Building & Trades",
            "subcategory":"Electrical",
            "type":"Services"
        }
    ],
    "sg:phone":"+1 450 668 2200",
    "sg:postcode":"H7S 1N8",
    "sg:province":"QC",
    "sg:tags":[
        "electric",
        "contractor"
    ],
    "wof:name":"Saux Jl Ltee",
    "wof:placetype":"venue"
},
  "geometry": {"coordinates":[-73.72077941889999,45.5750274658],"type":"Point"}
}