{
  "type": "Feature",
  "properties": {
    "addr:full":"8 Circle Kapuskasing ON P5N 1T3",
    "addr:housenumber":"8",
    "addr:postcode":"p5n 1t3",
    "addr:street":"Circle",
    "iso:country":"CA",
    "sg:address":"8 Circle",
    "sg:city":"Kapuskasing",
    "sg:classifiers":[
        {
            "category":"Shopping",
            "subcategory":"Computers & Home Electronics",
            "type":"Retail Goods"
        }
    ],
    "sg:phone":"+1 705 335 3460",
    "sg:postcode":"P5N 1T3",
    "sg:province":"ON",
    "sg:tags":[
        "television",
        "burglar",
        "alarm",
        "system"
    ],
    "wof:name":"Spacek's Audiotronic",
    "wof:placetype":"venue"
},
  "geometry": {"coordinates":[-82.425163,49.417946],"type":"Point"}
}