{
  "type": "Feature",
  "properties": {
    "addr:full":"3440 Principale Chesterville QC G0P 1J0",
    "addr:housenumber":"3440",
    "addr:postcode":"g0p 1j0",
    "addr:street":"Principale",
    "iso:country":"CA",
    "sg:address":"3440 Principale",
    "sg:city":"Chesterville",
    "sg:classifiers":[
        {
            "category":"Health Services",
            "subcategory":"Health Practitioner",
            "type":"Services"
        }
    ],
    "sg:phone":"+1 819 382 2121",
    "sg:postcode":"G0P 1J0",
    "sg:province":"QC",
    "sg:tags":[
        "psychotherapist"
    ],
    "wof:name":"Centre LA Transition",
    "wof:placetype":"venue"
},
  "geometry": {"coordinates":[-71.74636099999999,45.909367],"type":"Point"}
}