{
  "type": "Feature",
  "properties": {
    "addr:full":"117 Front St N Sarnia ON N7T 7T1",
    "addr:housenumber":"117",
    "addr:postcode":"n7t 7t1",
    "addr:street":"Front St N",
    "iso:country":"CA",
    "sg:address":"117 Front St N",
    "sg:city":"Sarnia",
    "sg:classifiers":[
        {
            "category":"Professional",
            "subcategory":"Engineering",
            "type":"Services"
        }
    ],
    "sg:phone":"+1 519 383 8028",
    "sg:postcode":"N7T 7T1",
    "sg:province":"ON",
    "sg:tags":[
        "engineer"
    ],
    "wof:name":"Tecsar Engineering Inc",
    "wof:placetype":"venue"
},
  "geometry": {"coordinates":[-82.4089508057,42.9713439941],"type":"Point"}
}