{
  "type": "Feature",
  "properties": {
    "addr:full":"Casselman ON K0A 1M0",
    "addr:postcode":"k0a 1m0",
    "iso:country":"CA",
    "sg:city":"Casselman",
    "sg:classifiers":[
        {
            "category":"Professional",
            "subcategory":"Lawyer & Legal Services",
            "type":"Services"
        }
    ],
    "sg:phone":"+1 613 764 3694",
    "sg:postcode":"K0A 1M0",
    "sg:province":"ON",
    "sg:tags":[
        "attorney"
    ],
    "wof:name":"Benoit & Benoit",
    "wof:placetype":"venue"
},
  "geometry": {"coordinates":[-75.086052,45.312618],"type":"Point"}
}