{
  "type": "Feature",
  "properties": {
    "iso:country":"CA",
    "sg:address":"424 Mayor Magrath Dr S",
    "sg:city":"Lethbridge",
    "sg:classifiers":[
        {
            "category":"Shopping",
            "subcategory":"Pharmacy",
            "type":"Retail Goods"
        }
    ],
    "sg:phone":"+1 403 328 3565",
    "sg:postcode":"T1J 3L9",
    "sg:province":"AB",
    "wof:name":"Skelton's Prescription Phrmcy",
    "wof:placetype":"venue"
},
  "geometry": {"coordinates":[-112.811180115,49.6947517395],"type":"Point"}
}