{
  "type": "Feature",
  "properties": {
    "addr:full":"240 46E Rue O Charlesbourg QC G1H 5H9",
    "addr:housenumber":"240",
    "addr:postcode":"g1h 5h9",
    "addr:street":"46E Rue O",
    "iso:country":"CA",
    "sg:address":"240 46E Rue O",
    "sg:city":"Charlesbourg",
    "sg:classifiers":[
        {
            "category":"Banks & Credit Unions",
            "subcategory":"Investment Brokerage",
            "type":"Services"
        }
    ],
    "sg:phone":"+1 418 623 2575",
    "sg:postcode":"G1H 5H9",
    "sg:province":"QC",
    "sg:tags":[
        "advisory",
        "financial",
        "association"
    ],
    "wof:name":"Corporation Financiere Sommet",
    "wof:placetype":"venue"
},
  "geometry": {"coordinates":[-71.2514343262,46.8456039429],"type":"Point"}
}