{
  "type": "Feature",
  "properties": {
    "iso:country":"CA",
    "sg:address":"97 Rue Sauve O",
    "sg:city":"Montreal",
    "sg:classifiers":[
        {
            "category":"Food & Beverages",
            "subcategory":"Groceries & Convenience Stores",
            "type":"Retail Goods"
        }
    ],
    "sg:phone":"+1 514 387 9296",
    "sg:postcode":"H3L 1Y2",
    "sg:province":"QC",
    "sg:tags":[
        "grocer"
    ],
    "wof:name":"Marche Rue Sauve Inc",
    "wof:placetype":"venue"
},
  "geometry": {"coordinates":[-73.6595611572,45.547744751],"type":"Point"}
}