{
  "type": "Feature",
  "properties": {
    "addr:full":"7 Rue Sainte-Marie Riviere-Du-Loup QC G5R 1W4",
    "addr:housenumber":"7",
    "addr:postcode":"g5r 1w4",
    "addr:street":"Rue Sainte-Marie",
    "iso:country":"CA",
    "sg:address":"7 Rue Sainte-Marie",
    "sg:city":"Riviere-Du-Loup",
    "sg:classifiers":[
        {
            "category":"Building & Trades",
            "subcategory":"Construction",
            "type":"Services"
        }
    ],
    "sg:phone":"+1 418 862 1503",
    "sg:postcode":"G5R 1W4",
    "sg:province":"QC",
    "sg:tags":[
        "masonry",
        "contractor"
    ],
    "wof:name":"P B Maconnerie",
    "wof:placetype":"venue"
},
  "geometry": {"coordinates":[-69.534187,47.82515],"type":"Point"}
}