{
  "type": "Feature",
  "properties": {
    "addr:full":"218 Chinook Dr Cochrane AB T4C 1E4",
    "addr:housenumber":"218",
    "addr:postcode":"t4c 1e4",
    "addr:street":"Chinook Dr",
    "iso:country":"CA",
    "sg:address":"218 Chinook Dr",
    "sg:city":"Cochrane",
    "sg:classifiers":[
        {
            "category":"Building & Trades",
            "subcategory":"Plumbing",
            "type":"Services"
        }
    ],
    "sg:phone":"+1 403 932 3238",
    "sg:postcode":"T4C 1E4",
    "sg:province":"AB",
    "sg:tags":[
        "contractor"
    ],
    "wof:name":"Great Western Plumbing & Htg",
    "wof:placetype":"venue"
},
  "geometry": {"coordinates":[-114.475235,51.198994],"type":"Point"}
}