{
  "type": "Feature",
  "properties": {
    "addr:full":"3154 Sandwich St Windsor ON N9C 1A6",
    "addr:housenumber":"3154",
    "addr:postcode":"n9c 1a6",
    "addr:street":"Sandwich St",
    "iso:country":"CA",
    "sg:address":"3154 Sandwich St",
    "sg:city":"Windsor",
    "sg:classifiers":[
        {
            "category":"Shopping",
            "subcategory":"Bicycles & Sporting Goods",
            "type":"Retail Goods"
        }
    ],
    "sg:phone":"+1 519 252 0080",
    "sg:postcode":"N9C 1A6",
    "sg:province":"ON",
    "wof:name":"Courtesy Bicycles",
    "wof:placetype":"venue"
},
  "geometry": {"coordinates":[-83.0751647949,42.3031005859],"type":"Point"}
}