{
  "type": "Feature",
  "properties": {
    "addr:full":"505 Jarvis St Toronto ON M4Y 2H7",
    "addr:housenumber":"505",
    "addr:postcode":"m4y 2h7",
    "addr:street":"Jarvis St",
    "iso:country":"CA",
    "sg:address":"505 Jarvis St",
    "sg:city":"Toronto",
    "sg:classifiers":[
        {
            "category":"Autos & Motor Vehicles",
            "subcategory":"Fuel & Gas Station",
            "type":"Retail Goods"
        }
    ],
    "sg:phone":"+1 416 921 5059",
    "sg:postcode":"M4Y 2H7",
    "sg:province":"ON",
    "sg:tags":[
        "oil"
    ],
    "wof:name":"Certigard",
    "wof:placetype":"venue"
},
  "geometry": {"coordinates":[-79.378227,43.666473],"type":"Point"}
}