{
  "type": "Feature",
  "properties": {
    "addr:full":"Toronto ON M5R 2T2",
    "addr:postcode":"m5r 2t2",
    "iso:country":"CA",
    "sg:city":"Toronto",
    "sg:classifiers":[
        {
            "category":"Retail",
            "subcategory":"Repair Shop",
            "type":"Services"
        }
    ],
    "sg:phone":"+1 416 967 4814",
    "sg:postcode":"M5R 2T2",
    "sg:province":"ON",
    "sg:tags":[
        "ironwork",
        "work",
        "art",
        "metal"
    ],
    "wof:name":"Peter Danes Studio Danmark",
    "wof:placetype":"venue"
},
  "geometry": {"coordinates":[-79.4047012329,43.6693153381],"type":"Point"}
}