{
  "type": "Feature",
  "properties": {
    "addr:full":"Mabou NS B0E 1X0",
    "addr:postcode":"b0e 1x0",
    "iso:country":"CA",
    "sg:city":"Mabou",
    "sg:classifiers":[
        {
            "category":"Building & Trades",
            "subcategory":"Construction",
            "type":"Services"
        }
    ],
    "sg:phone":"+1 902 945 2178",
    "sg:postcode":"B0E 1X0",
    "sg:province":"NS",
    "sg:tags":[
        "excavating",
        "contractor",
        "general"
    ],
    "wof:name":"A C Campbell Contractors Ltd",
    "wof:placetype":"venue"
},
  "geometry": {"coordinates":[-61.3925933838,46.0716323853],"type":"Point"}
}