{
  "type": "Feature",
  "properties": {
    "addr:full":"3822 47 Ave Camrose AB T4V 3W8",
    "addr:housenumber":"3822",
    "addr:postcode":"t4v 3w8",
    "addr:street":"47 Ave",
    "iso:country":"CA",
    "sg:address":"3822 47 Ave",
    "sg:city":"Camrose",
    "sg:classifiers":[
        {
            "category":"Retail",
            "subcategory":"Auto Repair",
            "type":"Services"
        }
    ],
    "sg:phone":"+1 780 672 2198",
    "sg:postcode":"T4V 3W8",
    "sg:province":"AB",
    "sg:tags":[
        "truck"
    ],
    "wof:name":"John's Shopmobile",
    "wof:placetype":"venue"
},
  "geometry": {"coordinates":[-112.802505,53.014893],"type":"Point"}
}