{
  "type": "Feature",
  "properties": {
    "addr:full":"1202 Woodbine Ave East York ON M4C 4E3",
    "addr:housenumber":"1202",
    "addr:postcode":"m4c 4e3",
    "addr:street":"Woodbine Ave",
    "iso:country":"CA",
    "sg:address":"1202 Woodbine Ave",
    "sg:city":"East York",
    "sg:classifiers":[
        {
            "category":"Home & Garden",
            "subcategory":"Household Appliances",
            "type":"Retail Goods"
        }
    ],
    "sg:phone":"+1 416 696 1334",
    "sg:postcode":"M4C 4E3",
    "sg:province":"ON",
    "wof:name":"A A & A Appliance Warehouse",
    "wof:placetype":"venue"
},
  "geometry": {"coordinates":[-79.31568145750001,43.6919708252],"type":"Point"}
}