{
  "type": "Feature",
  "properties": {
    "addr:full":"40 Tank Farm Rd Belleville ON K8N 4Z6",
    "addr:housenumber":"40",
    "addr:postcode":"k8n 4z6",
    "addr:street":"Tank Farm Rd",
    "iso:country":"CA",
    "sg:address":"40 Tank Farm Rd",
    "sg:city":"Belleville",
    "sg:classifiers":[
        {
            "category":"Building & Trades",
            "subcategory":"Plumbing",
            "type":"Services"
        }
    ],
    "sg:phone":"+1 613 966 5568",
    "sg:postcode":"K8N 4Z6",
    "sg:province":"ON",
    "sg:tags":[
        "sheet",
        "work",
        "metal",
        "system",
        "contractor",
        "conditioning",
        "air"
    ],
    "wof:name":"Noronco Sheet Metal Ltd",
    "wof:placetype":"venue"
},
  "geometry": {"coordinates":[-77.379051,44.212048],"type":"Point"}
}