{
  "type": "Feature",
  "properties": {
    "addr:full":"Biggar SK S0K 0M0",
    "addr:postcode":"s0k 0m0",
    "iso:country":"CA",
    "sg:city":"Biggar",
    "sg:classifiers":[
        {
            "category":"Home & Garden",
            "subcategory":"Carpets & Floor Coverings",
            "type":"Retail Goods"
        }
    ],
    "sg:phone":"+1 306 948 1773",
    "sg:postcode":"S0K 0M0",
    "sg:province":"SK",
    "sg:tags":[
        "dealer",
        "rug"
    ],
    "wof:name":"Phillips Floors & More",
    "wof:placetype":"venue"
},
  "geometry": {"coordinates":[-107.985595703,52.0549888611],"type":"Point"}
}