{
  "type": "Feature",
  "properties": {
    "addr:full":"Etobicoke ON M8Z 2T4",
    "addr:postcode":"m8z 2t4",
    "iso:country":"CA",
    "sg:city":"Etobicoke",
    "sg:classifiers":[
        {
            "category":"Manufacturing",
            "subcategory":"Tools & Machinery",
            "type":"Manufacturing & Wholesale Goods"
        }
    ],
    "sg:phone":"+1 416 233 5181",
    "sg:postcode":"M8Z 2T4",
    "sg:province":"ON",
    "sg:tags":[
        "mold"
    ],
    "wof:name":"Perfectools Inc",
    "wof:placetype":"venue"
},
  "geometry": {"coordinates":[-79.530045,43.63372],"type":"Point"}
}