{
  "type": "Feature",
  "properties": {
    "addr:full":"33 Yonge St Toronto ON M5E 1G4",
    "addr:housenumber":"33",
    "addr:postcode":"m5e 1g4",
    "addr:street":"Yonge St",
    "iso:country":"CA",
    "sg:address":"33 Yonge St",
    "sg:city":"Toronto",
    "sg:classifiers":[
        {
            "category":"Health Services",
            "subcategory":"Doctor",
            "type":"Services"
        }
    ],
    "sg:phone":"+1 416 364 2444",
    "sg:postcode":"M5E 1G4",
    "sg:province":"ON",
    "sg:tags":[
        "dentist"
    ],
    "wof:name":"Horenfeldt, Allan M DDS",
    "wof:placetype":"venue"
},
  "geometry": {"coordinates":[-79.376862,43.64711],"type":"Point"}
}