{
  "type": "Feature",
  "properties": {
    "addr:full":"10260 112 St NW Edmonton AB T5K 1M4",
    "addr:housenumber":"10260",
    "addr:postcode":"t5k 1m4",
    "addr:street":"112 St Nw",
    "iso:country":"CA",
    "sg:address":"10260 112 St NW",
    "sg:city":"Edmonton",
    "sg:classifiers":[
        {
            "category":"Professional",
            "subcategory":"Art Services",
            "type":"Services"
        }
    ],
    "sg:phone":"+1 780 429 5051",
    "sg:postcode":"T5K 1M4",
    "sg:province":"AB",
    "sg:tags":[
        "training",
        "graphic",
        "computer",
        "designer"
    ],
    "wof:name":"Plastic Thought Inc",
    "wof:placetype":"venue"
},
  "geometry": {"coordinates":[-113.514144898,53.5439376831],"type":"Point"}
}