{
  "type": "Feature",
  "properties": {
    "addr:full":"Delburne AB T0M 0V0",
    "addr:postcode":"t0m 0v0",
    "iso:country":"CA",
    "sg:city":"Delburne",
    "sg:classifiers":[
        {
            "category":"Personal",
            "subcategory":"Beauty Salon",
            "type":"Services"
        }
    ],
    "sg:phone":"+1 403 749 3033",
    "sg:postcode":"T0M 0V0",
    "sg:province":"AB",
    "wof:name":"Headquarters Salon",
    "wof:placetype":"venue"
},
  "geometry": {"coordinates":[-113.23274231000001,52.1986503601],"type":"Point"}
}