{
  "type": "Feature",
  "properties": {
    "addr:full":"Lachine QC H8T 1W7",
    "addr:postcode":"h8t 1w7",
    "iso:country":"CA",
    "sg:city":"Lachine",
    "sg:classifiers":[
        {
            "category":"Professional",
            "subcategory":"Lawyer & Legal Services",
            "type":"Services"
        }
    ],
    "sg:phone":"+1 514 637 5568",
    "sg:postcode":"H8T 1W7",
    "sg:province":"QC",
    "sg:tags":[
        "attorney"
    ],
    "wof:name":"Barrette & Assoc",
    "wof:placetype":"venue"
},
  "geometry": {"coordinates":[-73.6936798096,45.4344787598],"type":"Point"}
}