{
  "type": "Feature",
  "properties": {
    "addr:full":"Campbell River BC V9W 6A3",
    "addr:postcode":"v9w 6a3",
    "iso:country":"CA",
    "sg:city":"Campbell River",
    "sg:classifiers":[
        {
            "category":"Manufacturing",
            "subcategory":"Tools & Machinery",
            "type":"Manufacturing & Wholesale Goods"
        }
    ],
    "sg:phone":"+1 250 286 9885",
    "sg:postcode":"V9W 6A3",
    "sg:province":"BC",
    "sg:tags":[
        "compressor"
    ],
    "wof:name":"Coastal Drill & Compressor Ltd",
    "wof:placetype":"venue"
},
  "geometry": {"coordinates":[-125.27346,50.04512],"type":"Point"}
}