{
  "type": "Feature",
  "properties": {
    "addr:full":"5020 47th Ave Two Hills AB T0B 4K0",
    "addr:housenumber":"5020",
    "addr:postcode":"t0b 4k0",
    "addr:street":"47Th Ave",
    "iso:country":"CA",
    "sg:address":"5020 47th Ave",
    "sg:city":"Two Hills",
    "sg:classifiers":[
        {
            "category":"Retail",
            "subcategory":"Auto Repair",
            "type":"Services"
        }
    ],
    "sg:phone":"+1 780 657 3304",
    "sg:postcode":"T0B 4K0",
    "sg:province":"AB",
    "sg:tags":[
        "repairing",
        "automobile"
    ],
    "wof:name":"Veg Automotive & Ind",
    "wof:placetype":"venue"
},
  "geometry": {"coordinates":[-111.744576,53.709396],"type":"Point"}
}