{
  "type": "Feature",
  "properties": {
    "addr:full":"7469 101 Ave NW Edmonton AB T6A 3Z5",
    "addr:housenumber":"7469",
    "addr:postcode":"t6a 3z5",
    "addr:street":"101 Ave Nw",
    "iso:country":"CA",
    "sg:address":"7469 101 Ave NW",
    "sg:city":"Edmonton",
    "sg:classifiers":[
        {
            "category":"Shopping",
            "subcategory":"Pharmacy",
            "type":"Retail Goods"
        }
    ],
    "sg:phone":"+1 780 485 1602",
    "sg:postcode":"T6A 3Z5",
    "sg:province":"AB",
    "wof:name":"Shoppers Drug Mart",
    "wof:placetype":"venue"
},
  "geometry": {"coordinates":[-113.44208526600001,53.5410346985],"type":"Point"}
}