{
  "type": "Feature",
  "properties": {
    "addr:full":"305 Fairford St W Moose Jaw SK S6H 1V8",
    "addr:housenumber":"305",
    "addr:postcode":"s6h 1v8",
    "addr:street":"Fairford St W",
    "iso:country":"CA",
    "sg:address":"305 Fairford St W",
    "sg:city":"Moose Jaw",
    "sg:classifiers":[
        {
            "category":"Organizations",
            "subcategory":"Non-profit Organization",
            "type":"Services"
        }
    ],
    "sg:phone":"+1 306 692 2911",
    "sg:postcode":"S6H 1V8",
    "sg:province":"SK",
    "sg:tags":[
        "charitable",
        "social",
        "institution",
        "welfare"
    ],
    "wof:name":"Moose Jaw & Distr Food Bnk Inc",
    "wof:placetype":"venue"
},
  "geometry": {"coordinates":[-105.542587,50.392368],"type":"Point"}
}