{
  "type": "Feature",
  "properties": {
    "addr:full":"3050 Penticton St Vancouver BC V5M 4W2",
    "addr:housenumber":"3050",
    "addr:postcode":"v5m 4w2",
    "addr:street":"Penticton St",
    "iso:country":"CA",
    "sg:address":"3050 Penticton St",
    "sg:city":"Vancouver",
    "sg:classifiers":[
        {
            "category":"Social Services",
            "subcategory":"Adult Care",
            "type":"Services"
        }
    ],
    "sg:phone":"+1 604 434 0995",
    "sg:postcode":"V5M 4W2",
    "sg:province":"BC",
    "sg:tags":[
        "community",
        "facility"
    ],
    "wof:name":"Carital Continuing Care Soc",
    "wof:placetype":"venue"
},
  "geometry": {"coordinates":[-123.052719,49.257092],"type":"Point"}
}