{
  "type": "Feature",
  "properties": {
    "addr:full":"Cp 1226 St Isidore AB T0H 3B0",
    "addr:postcode":"1226;isidore ab t0h 3b0",
    "addr:street":"Cp;St",
    "iso:country":"CA",
    "sg:address":"Cp 1226",
    "sg:city":"St Isidore",
    "sg:classifiers":[
        {
            "category":"Organizations",
            "subcategory":"Religious Organization",
            "type":"Services"
        }
    ],
    "sg:phone":"+1 780 624 8197",
    "sg:postcode":"T0H 3B0",
    "sg:province":"AB",
    "sg:tags":[
        "church"
    ],
    "wof:name":"St Isidore Catholic Church",
    "wof:placetype":"venue"
},
  "geometry": {"coordinates":[-117.10881000000001,56.205936],"type":"Point"}
}