{
  "type": "Feature",
  "properties": {
    "addr:full":"249 Dalhousie St Amherstburg ON N9V 1W8",
    "addr:housenumber":"249",
    "addr:postcode":"n9v 1w8",
    "addr:street":"Dalhousie St",
    "iso:country":"CA",
    "sg:address":"249 Dalhousie St",
    "sg:city":"Amherstburg",
    "sg:classifiers":[
        {
            "category":"Restaurant",
            "type":"Food & Drink"
        }
    ],
    "sg:phone":"+1 519 736 5924",
    "sg:postcode":"N9V 1W8",
    "sg:province":"ON",
    "sg:tags":[
        "cafe"
    ],
    "wof:name":"Downtown Expresso Cafe",
    "wof:placetype":"venue"
},
  "geometry": {"coordinates":[-83.112602,42.102242],"type":"Point"}
}