{
  "type": "Feature",
  "properties": {
    "addr:full":"3385 Av Laurin Quebec QC G1P 1T6",
    "addr:postcode":"g1p 1t6",
    "addr:street":"Av Laurin",
    "iso:country":"CA",
    "sg:address":"3385 Av Laurin",
    "sg:city":"Quebec",
    "sg:classifiers":[
        {
            "category":"Organizations",
            "subcategory":"Religious Organization",
            "type":"Services"
        }
    ],
    "sg:phone":"+1 418 872 8258",
    "sg:postcode":"G1P 1T6",
    "sg:province":"QC",
    "sg:tags":[
        "church"
    ],
    "wof:name":"Eglise Bapt LA Vieille Capital",
    "wof:placetype":"venue"
},
  "geometry": {"coordinates":[-71.3276977539,46.8112716675],"type":"Point"}
}