{
  "type": "Feature",
  "properties": {
    "addr:full":"Ashern MB R0C 0E0",
    "addr:postcode":"r0c 0e0",
    "iso:country":"CA",
    "sg:city":"Ashern",
    "sg:classifiers":[
        {
            "category":"Travel",
            "subcategory":"Hotels & Motels",
            "type":"Entertainment"
        }
    ],
    "sg:phone":"+1 204 768 2319",
    "sg:postcode":"R0C 0E0",
    "sg:province":"MB",
    "wof:name":"Sharptail Motor Inn Ltd",
    "wof:placetype":"venue"
},
  "geometry": {"coordinates":[-98.350105,51.179821],"type":"Point"}
}