{
  "type": "Feature",
  "properties": {
    "addr:full":"St Agnes Azilda ON P0M 1B0",
    "addr:postcode":"p0m 1b0",
    "iso:country":"CA",
    "sg:address":"St Agnes",
    "sg:city":"Azilda",
    "sg:classifiers":[
        {
            "category":"Recreation",
            "type":"Entertainment"
        }
    ],
    "sg:phone":"+1 705 983 1500",
    "sg:postcode":"P0M 1B0",
    "sg:province":"ON",
    "sg:tags":[
        "club",
        "hockey"
    ],
    "wof:name":"Rayside Balfour Minor Hockey",
    "wof:placetype":"venue"
},
  "geometry": {"coordinates":[-81.1431503296,46.5513801575],"type":"Point"}
}