{
  "type": "Feature",
  "properties": {
    "addr:full":"276 Main St Tobique First Nation NB E7H 2Y8",
    "addr:housenumber":"276",
    "addr:postcode":"e7h 2y8",
    "addr:street":"Main St",
    "iso:country":"CA",
    "sg:address":"276 Main St",
    "sg:city":"Tobique First Nation",
    "sg:classifiers":[
        {
            "category":"Personal",
            "subcategory":"Beauty Salon",
            "type":"Services"
        }
    ],
    "sg:phone":"+1 506 356 2602",
    "sg:postcode":"E7H 2Y8",
    "sg:province":"NB",
    "wof:name":"Klassy Kuts",
    "wof:placetype":"venue"
},
  "geometry": {"coordinates":[-66.4079818726,46.4490814209],"type":"Point"}
}