{
  "type": "Feature",
  "properties": {
    "iso:country":"CA",
    "sg:address":"350 Park St",
    "sg:city":"Kitchener",
    "sg:classifiers":[
        {
            "category":"Social Services",
            "type":"Services"
        }
    ],
    "sg:phone":"+1 519 579 3944",
    "sg:postcode":"N2G 1N1",
    "sg:province":"ON",
    "sg:tags":[
        "counselor",
        "marriage",
        "family"
    ],
    "wof:name":"Klaehn, Tracie",
    "wof:placetype":"venue"
},
  "geometry": {"coordinates":[-80.509155,43.453495],"type":"Point"}
}