{
  "type": "Feature",
  "properties": {
    "addr:full":"350 Park St Kitchener ON N2G 1N1",
    "addr:housenumber":"350",
    "addr:postcode":"n2g 1n1",
    "addr:street":"Park St",
    "iso:country":"CA",
    "sg:address":"350 Park St",
    "sg:city":"Kitchener",
    "sg:classifiers":[
        {
            "category":"Social Services",
            "type":"Services"
        }
    ],
    "sg:phone":"+1 519 579 3944",
    "sg:postcode":"N2G 1N1",
    "sg:province":"ON",
    "sg:tags":[
        "counselor",
        "marriage",
        "family"
    ],
    "wof:name":"Klaehn, Tracie",
    "wof:placetype":"venue"
},
  "geometry": {"coordinates":[-80.50915500000001,43.453495],"type":"Point"}
}