{
  "type": "Feature",
  "properties": {
    "iso:country":"CA",
    "sg:city":"Calgary",
    "sg:classifiers":[
        {
            "category":"Building & Trades",
            "subcategory":"Plumbing",
            "type":"Services"
        }
    ],
    "sg:phone":"+1 403 243 5052",
    "sg:postcode":"T2G 4R3",
    "sg:province":"AB",
    "sg:tags":[
        "balancing",
        "air"
    ],
    "wof:name":"Tech-Air Svc",
    "wof:placetype":"venue"
},
  "geometry": {"coordinates":[-114.066650391,51.0104560852],"type":"Point"}
}