{
  "type": "Feature",
  "properties": {
    "iso:country":"CA",
    "sg:city":"Val-Barrette",
    "sg:classifiers":[
        {
            "category":"Food & Beverages",
            "subcategory":"Groceries & Convenience Stores",
            "type":"Retail Goods"
        }
    ],
    "sg:phone":"+1 819 585 2525",
    "sg:postcode":"J0W 1Y0",
    "sg:province":"QC",
    "wof:name":"Depanneur Proprio",
    "wof:placetype":"venue"
},
  "geometry": {"coordinates":[-75.3558044434,46.5072593689],"type":"Point"}
}