{
  "type": "Feature",
  "properties": {
    "addr:full":"Quebec QC G1N 4L7",
    "addr:postcode":"g1n 4l7",
    "iso:country":"CA",
    "sg:city":"Quebec",
    "sg:classifiers":[
        {
            "category":"Professional",
            "subcategory":"Art Services",
            "type":"Services"
        }
    ],
    "sg:phone":"+1 418 683 4114",
    "sg:postcode":"G1N 4L7",
    "sg:province":"QC",
    "sg:tags":[
        "photographer"
    ],
    "wof:name":"Oeil Pour Oeil",
    "wof:placetype":"venue"
},
  "geometry": {"coordinates":[-71.2852630615,46.7982254028],"type":"Point"}
}