{
  "type": "Feature",
  "properties": {
    "addr:full":"4947 Rue Clement-Lockquell Saint-Augustin-DE-Desmaures QC G3A 1V4",
    "addr:housenumber":"4947",
    "addr:postcode":"g3a 1v4",
    "addr:street":"Rue Clement-Lockquell",
    "iso:country":"CA",
    "sg:address":"4947 Rue Clement-Lockquell",
    "sg:city":"Saint-Augustin-DE-Desmaures",
    "sg:classifiers":[
        {
            "category":"Social Services",
            "type":"Services"
        }
    ],
    "sg:phone":"+1 418 872 0916",
    "sg:postcode":"G3A 1V4",
    "sg:province":"QC",
    "sg:tags":[
        "counselor",
        "marriage",
        "family"
    ],
    "wof:name":"Institut DE LA Famille",
    "wof:placetype":"venue"
},
  "geometry": {"coordinates":[-71.392539978,46.7381706238],"type":"Point"}
}