{
  "type": "Feature",
  "properties": {
    "addr:full":"2350 95E Rue Saint-Georges QC G5Y 8J4",
    "addr:housenumber":"2350",
    "addr:postcode":"g5y 8j4",
    "addr:street":"95E Rue",
    "iso:country":"CA",
    "sg:address":"2350 95E Rue",
    "sg:city":"Saint-Georges",
    "sg:classifiers":[
        {
            "category":"Manufacturing",
            "subcategory":"Furniture",
            "type":"Manufacturing & Wholesale Goods"
        }
    ],
    "sg:phone":"+1 418 228 4180",
    "sg:postcode":"G5Y 8J4",
    "sg:province":"QC",
    "wof:name":"Meubles Beaucerons Inc",
    "wof:placetype":"venue"
},
  "geometry": {"coordinates":[-70.67115,46.123348],"type":"Point"}
}