{
  "type": "Feature",
  "properties": {
    "addr:full":"2095 Montee Saint-Francois Laval QC H7E 4P2",
    "addr:housenumber":"2095",
    "addr:postcode":"h7e 4p2",
    "addr:street":"Montee Saint-Francois",
    "iso:country":"CA",
    "sg:address":"2095 Montee Saint-Francois",
    "sg:city":"Laval",
    "sg:classifiers":[
        {
            "category":"Utilities",
            "subcategory":"Refuse",
            "type":"Services"
        }
    ],
    "sg:phone":"+1 450 661 5080",
    "sg:postcode":"H7E 4P2",
    "sg:province":"QC",
    "sg:tags":[
        "garbage",
        "collection"
    ],
    "wof:name":"Entreprise Sanitaire Fa Ltee",
    "wof:placetype":"venue"
},
  "geometry": {"coordinates":[-73.6692733765,45.6390571594],"type":"Point"}
}