{
  "type": "Feature",
  "properties": {
    "addr:full":"1550 Rue Fradet Drummondville QC J2B 1P1",
    "addr:housenumber":"1550",
    "addr:postcode":"j2b 1p1",
    "addr:street":"Rue Fradet",
    "iso:country":"CA",
    "sg:address":"1550 Rue Fradet",
    "sg:city":"Drummondville",
    "sg:classifiers":[
        {
            "category":"Professional",
            "subcategory":"Business Services",
            "type":"Services"
        }
    ],
    "sg:phone":"+1 819 474 3300",
    "sg:postcode":"J2B 1P1",
    "sg:province":"QC",
    "sg:tags":[
        "notary"
    ],
    "wof:name":"Boileau, Michel",
    "wof:placetype":"venue"
},
  "geometry": {"coordinates":[-72.464462,45.864849],"type":"Point"}
}