{
  "type": "Feature",
  "properties": {
    "addr:full":"2844 S Baptiste Lake Rd Bancroft ON K0L 1C0",
    "addr:housenumber":"2844",
    "addr:postcode":"k0l 1c0",
    "addr:street":"S Baptiste Lake Rd",
    "iso:country":"CA",
    "sg:address":"2844 S Baptiste Lake Rd",
    "sg:city":"Bancroft",
    "sg:classifiers":[
        {
            "category":"Travel",
            "subcategory":"Hotels & Motels",
            "type":"Entertainment"
        }
    ],
    "sg:phone":"+1 613 332 2669",
    "sg:postcode":"K0L 1C0",
    "sg:province":"ON",
    "sg:tags":[
        "resort"
    ],
    "wof:name":"Joseph's Resort & Meeting Ctr",
    "wof:placetype":"venue"
},
  "geometry": {"coordinates":[-77.85334777830001,45.0565414429],"type":"Point"}
}