{
  "type": "Feature",
  "properties": {
    "addr:full":"Vancouver BC V6C 1Z7",
    "addr:postcode":"v6c 1z7",
    "iso:country":"CA",
    "sg:city":"Vancouver",
    "sg:classifiers":[
        {
            "category":"Ferry",
            "type":"Transportation"
        }
    ],
    "sg:phone":"+1 604 682 4741",
    "sg:postcode":"V6C 1Z7",
    "sg:province":"BC",
    "sg:tags":[
        "company",
        "steamship"
    ],
    "wof:name":"Interocean Steamship Corp",
    "wof:placetype":"venue"
},
  "geometry": {"coordinates":[-123.114204,49.286469],"type":"Point"}
}