{
  "type": "Feature",
  "properties": {
    "iso:country":"CA",
    "sg:address":"255 Brimson Dr",
    "sg:city":"Newmarket",
    "sg:classifiers":[
        {
            "category":"Social Services",
            "subcategory":"Child Care",
            "type":"Services"
        }
    ],
    "sg:phone":"+1 905 898 0545",
    "sg:postcode":"L3X 1H8",
    "sg:province":"ON",
    "wof:name":"Crossland Child Care Ctr",
    "wof:placetype":"venue"
},
  "geometry": {"coordinates":[-79.4928436279,44.0429229736],"type":"Point"}
}