{
  "type": "Feature",
  "properties": {
    "iso:country":"CA",
    "sg:address":"198 St. Paul St",
    "sg:city":"St Catharines",
    "sg:classifiers":[
        {
            "category":"Manufacturing",
            "subcategory":"Motor Vehicles & Parts",
            "type":"Manufacturing & Wholesale Goods"
        }
    ],
    "sg:phone":"+1 905 688 6372",
    "sg:postcode":"L2R 3M2",
    "sg:province":"ON",
    "sg:tags":[
        "lining"
    ],
    "wof:name":"Canada Hair Cloth CO Ltd",
    "wof:placetype":"venue"
},
  "geometry": {"coordinates":[-79.2437362671,43.1579284668],"type":"Point"}
}