{
  "type": "Feature",
  "properties": {
    "addr:full":"521 Rue Principale Saint-Cleophas-DE-Brandon QC J0K 2A0",
    "addr:housenumber":"521",
    "addr:postcode":"j0k 2a0",
    "addr:street":"Rue Principale",
    "iso:country":"CA",
    "sg:address":"521 Rue Principale",
    "sg:city":"Saint-Cleophas-DE-Brandon",
    "sg:classifiers":[
        {
            "category":"Retail",
            "subcategory":"Auto Repair",
            "type":"Services"
        }
    ],
    "sg:phone":"+1 450 889 5474",
    "sg:postcode":"J0K 2A0",
    "sg:province":"QC",
    "sg:tags":[
        "repairing",
        "automobile"
    ],
    "wof:name":"Garage Paul Coutu",
    "wof:placetype":"venue"
},
  "geometry": {"coordinates":[-73.414337,46.224335],"type":"Point"}
}