{
  "type": "Feature",
  "properties": {
    "addr:full":"458 Mount William Rd Westville NS B0K 2A0",
    "addr:housenumber":"458",
    "addr:postcode":"b0k 2a0",
    "addr:street":"Mount William Rd",
    "iso:country":"CA",
    "sg:address":"458 Mount William Rd",
    "sg:city":"Westville",
    "sg:classifiers":[
        {
            "category":"Building & Trades",
            "subcategory":"Construction",
            "type":"Services"
        }
    ],
    "sg:phone":"+1 902 396 3984",
    "sg:postcode":"B0K 2A0",
    "sg:province":"NS",
    "sg:tags":[
        "product",
        "paving",
        "asphalt",
        "contractor"
    ],
    "wof:name":"Webster Bros Paving & Concrete",
    "wof:placetype":"venue"
},
  "geometry": {"coordinates":[-62.7099075317,45.5617599487],"type":"Point"}
}