{
  "type": "Feature",
  "properties": {
    "addr:full":"209 2E Av Lac-Etchemin QC G0R 1S0",
    "addr:housenumber":"209",
    "addr:postcode":"g0r 1s0",
    "addr:street":"2E Av Lac-Etchemin",
    "iso:country":"CA",
    "sg:address":"209 2E Av",
    "sg:city":"Lac-Etchemin",
    "sg:classifiers":[
        {
            "category":"Shopping",
            "subcategory":"Computers & Home Electronics",
            "type":"Retail Goods"
        }
    ],
    "sg:phone":"+1 418 625 2323",
    "sg:postcode":"G0R 1S0",
    "sg:province":"QC",
    "sg:tags":[
        "equipment",
        "electronic",
        "supply"
    ],
    "wof:name":"Boite A Son",
    "wof:placetype":"venue"
},
  "geometry": {"coordinates":[-70.5048294067,46.3961868286],"type":"Point"}
}