{
  "type": "Feature",
  "properties": {
    "addr:full":"5111 47 Ave Taber AB T1G 1R6",
    "addr:housenumber":"5111",
    "addr:postcode":"t1g 1r6",
    "addr:street":"47 Ave",
    "iso:country":"CA",
    "sg:address":"5111 47 Ave",
    "sg:city":"Taber",
    "sg:classifiers":[
        {
            "category":"Retail",
            "subcategory":"Auto Repair",
            "type":"Services"
        }
    ],
    "sg:phone":"+1 403 223 6449",
    "sg:postcode":"T1G 1R6",
    "sg:province":"AB",
    "sg:tags":[
        "repairing",
        "automobile"
    ],
    "wof:name":"A & M Auto Tec",
    "wof:placetype":"venue"
},
  "geometry": {"coordinates":[-112.147644,49.783264],"type":"Point"}
}