{
  "type": "Feature",
  "properties": {
    "addr:full":"211 Mount Royal Rd Winnipeg MB R3J 2N1",
    "addr:housenumber":"211",
    "addr:postcode":"r3j 2n1",
    "addr:street":"Mount Royal Rd",
    "iso:country":"CA",
    "sg:address":"211 Mount Royal Rd",
    "sg:city":"Winnipeg",
    "sg:classifiers":[
        {
            "category":"Shopping",
            "subcategory":"Florist",
            "type":"Retail Goods"
        }
    ],
    "sg:phone":"+1 204 832 7398",
    "sg:postcode":"R3J 2N1",
    "sg:province":"MB",
    "wof:name":"Silver Heights Florist",
    "wof:placetype":"venue"
},
  "geometry": {"coordinates":[-97.24535400000001,49.876888],"type":"Point"}
}