{
  "type": "Feature",
  "properties": {
    "addr:full":"Vancouver BC V6P 5Y7",
    "addr:postcode":"v6p 5y7",
    "iso:country":"CA",
    "sg:city":"Vancouver",
    "sg:classifiers":[
        {
            "category":"Retail",
            "subcategory":"Auto Repair",
            "type":"Services"
        }
    ],
    "sg:phone":"+1 604 321 7288",
    "sg:postcode":"V6P 5Y7",
    "sg:province":"BC",
    "sg:tags":[
        "repairing",
        "automobile"
    ],
    "wof:name":"Budget Brake & Muffler",
    "wof:placetype":"venue"
},
  "geometry": {"coordinates":[-123.124039,49.207176],"type":"Point"}
}