{
  "type": "Feature",
  "properties": {
    "iso:country":"CA",
    "sg:address":"50 Lincoln Pk # 100",
    "sg:city":"Canmore",
    "sg:classifiers":[
        {
            "category":"Manufacturing",
            "subcategory":"Printing",
            "type":"Manufacturing & Wholesale Goods"
        }
    ],
    "sg:phone":"+1 403 678 2365",
    "sg:postcode":"T1W 3E9",
    "sg:province":"AB",
    "sg:tags":[
        "newspaper"
    ],
    "wof:name":"Canmore Leader",
    "wof:placetype":"venue"
},
  "geometry": {"coordinates":[-115.360839844,51.0895652771],"type":"Point"}
}