{
  "type": "Feature",
  "properties": {
    "iso:country":"CA",
    "sg:city":"Toronto",
    "sg:classifiers":[
        {
            "category":"Health Services",
            "subcategory":"Doctor",
            "type":"Services"
        }
    ],
    "sg:phone":"+1 416 928 6828",
    "sg:postcode":"M4W 3E2",
    "sg:province":"ON",
    "sg:tags":[
        "dentist"
    ],
    "wof:name":"Accolade Dental Ctr",
    "wof:placetype":"venue"
},
  "geometry": {"coordinates":[-79.3874282837,43.6702308655],"type":"Point"}
}