{
  "type": "Feature",
  "properties": {
    "addr:full":"Richmond BC V6V 1Y4",
    "addr:postcode":"v6v 1y4",
    "iso:country":"CA",
    "sg:city":"Richmond",
    "sg:classifiers":[
        {
            "category":"Building & Trades",
            "subcategory":"Plumbing",
            "type":"Services"
        }
    ],
    "sg:phone":"+1 604 276 2716",
    "sg:postcode":"V6V 1Y4",
    "sg:province":"BC",
    "sg:tags":[
        "mechanical",
        "contractor"
    ],
    "wof:name":"Tite Mechanical",
    "wof:placetype":"venue"
},
  "geometry": {"coordinates":[-123.061630249,49.2018585205],"type":"Point"}
}