{
  "type": "Feature",
  "properties": {
    "addr:full":"Woodbridge ON L4L 8G7",
    "addr:postcode":"l4l 8g7",
    "iso:country":"CA",
    "sg:city":"Woodbridge",
    "sg:classifiers":[
        {
            "category":"Real Estate",
            "subcategory":"Real Estate Agent",
            "type":"Services"
        }
    ],
    "sg:phone":"+1 905 264 1900",
    "sg:postcode":"L4L 8G7",
    "sg:province":"ON",
    "wof:name":"Parmax Realty Svc Ltd",
    "wof:placetype":"venue"
},
  "geometry": {"coordinates":[-79.5463562012,43.771686554],"type":"Point"}
}