{
  "type": "Feature",
  "properties": {
    "addr:full":"3584 Commerce Crt Burlington ON L7N 3L7",
    "addr:housenumber":"3584",
    "addr:postcode":"l7n 3l7",
    "addr:street":"Commerce Crt",
    "iso:country":"CA",
    "sg:address":"3584 Commerce Crt",
    "sg:city":"Burlington",
    "sg:classifiers":[
        {
            "category":"Travel",
            "subcategory":"Campground",
            "type":"Entertainment"
        }
    ],
    "sg:phone":"+1 905 631 2849",
    "sg:postcode":"L7N 3L7",
    "sg:province":"ON",
    "sg:tags":[
        "camp"
    ],
    "wof:name":"Camp Wenonah",
    "wof:placetype":"venue"
},
  "geometry": {"coordinates":[-79.7805633545,43.357635498],"type":"Point"}
}