{
  "type": "Feature",
  "properties": {
    "addr:full":"2454 Bloor St W York ON M6S 1R2",
    "addr:housenumber":"2454",
    "addr:postcode":"m6s 1r2",
    "addr:street":"Bloor St W",
    "iso:country":"CA",
    "sg:address":"2454 Bloor St W",
    "sg:city":"York",
    "sg:classifiers":[
        {
            "category":"Food & Beverages",
            "subcategory":"Groceries & Convenience Stores",
            "type":"Retail Goods"
        }
    ],
    "sg:phone":"+1 416 767 3789",
    "sg:postcode":"M6S 1R2",
    "sg:province":"ON",
    "wof:name":"Old Mill Convenience",
    "wof:placetype":"venue"
},
  "geometry": {"coordinates":[-79.490562439,43.6479911804],"type":"Point"}
}