{
  "type": "Feature",
  "properties": {
    "addr:full":"49 Norfolk St N Simcoe ON N3Y 3N6",
    "addr:housenumber":"49",
    "addr:postcode":"n3y 3n6",
    "addr:street":"Norfolk St N",
    "iso:country":"CA",
    "sg:address":"49 Norfolk St N",
    "sg:city":"Simcoe",
    "sg:classifiers":[
        {
            "category":"Insurance",
            "subcategory":"Insurance Agent",
            "type":"Services"
        }
    ],
    "sg:phone":"+1 519 426 2031",
    "sg:postcode":"N3Y 3N6",
    "sg:province":"ON",
    "wof:name":"R E Mann Brokers Ltd",
    "wof:placetype":"venue"
},
  "geometry": {"coordinates":[-80.304039,42.838078],"type":"Point"}
}