{
  "type": "Feature",
  "properties": {
    "addr:full":"294 Bethel Rd Omemee ON K0L 2W0",
    "addr:housenumber":"294",
    "addr:postcode":"k0l 2w0",
    "addr:street":"Bethel Rd",
    "iso:country":"CA",
    "sg:address":"294 Bethel Rd",
    "sg:city":"Omemee",
    "sg:classifiers":[
        {
            "category":"Manufacturing",
            "subcategory":"Metals",
            "type":"Manufacturing & Wholesale Goods"
        }
    ],
    "sg:phone":"+1 705 799 7170",
    "sg:postcode":"K0L 2W0",
    "sg:province":"ON",
    "sg:tags":[
        "work",
        "sheet",
        "contractor"
    ],
    "wof:name":"Apex Custom Metal Ltd",
    "wof:placetype":"venue"
},
  "geometry": {"coordinates":[-78.48788500000001,44.346077],"type":"Point"}
}