{
  "type": "Feature",
  "properties": {
    "addr:full":"111 Belsite Crt Kleinburg ON L0J 1C0",
    "addr:housenumber":"111",
    "addr:postcode":"l0j 1c0",
    "addr:street":"Belsite Crt",
    "iso:country":"CA",
    "sg:address":"111 Belsite Crt",
    "sg:city":"Kleinburg",
    "sg:classifiers":[
        {
            "category":"Professional",
            "subcategory":"Management & Consulting",
            "type":"Services"
        }
    ],
    "sg:phone":"+1 905 893 3362",
    "sg:postcode":"L0J 1C0",
    "sg:province":"ON",
    "sg:tags":[
        "marketing",
        "consultant"
    ],
    "wof:name":"Good Vibrations Intl",
    "wof:placetype":"venue"
},
  "geometry": {"coordinates":[-79.630386,43.870571],"type":"Point"}
}