{
  "type": "Feature",
  "properties": {
    "addr:full":"Langley BC V2Y 1N2",
    "addr:postcode":"v2y 1n2",
    "iso:country":"CA",
    "sg:city":"Langley",
    "sg:classifiers":[
        {
            "category":"Education",
            "subcategory":"Dance Studio",
            "type":"Public Place"
        }
    ],
    "sg:phone":"+1 604 530 6878",
    "sg:postcode":"V2Y 1N2",
    "sg:province":"BC",
    "sg:tags":[
        "instruction",
        "dancing"
    ],
    "wof:name":"Dance Trance",
    "wof:placetype":"venue"
},
  "geometry": {"coordinates":[-122.663101,49.11684],"type":"Point"}
}