{
  "type": "Feature",
  "properties": {
    "addr:full":"1432 2nd St N Cranbrook BC V1C 3L2",
    "addr:housenumber":"1432",
    "addr:postcode":"v1c 3l2",
    "addr:street":"2Nd St N",
    "iso:country":"CA",
    "sg:address":"1432 2nd St N",
    "sg:city":"Cranbrook",
    "sg:classifiers":[
        {
            "category":"Arena",
            "subcategory":"Sports Club",
            "type":"Entertainment"
        }
    ],
    "sg:phone":"+1 250 489 0222",
    "sg:postcode":"V1C 3L2",
    "sg:province":"BC",
    "sg:tags":[
        "athletic",
        "fields",
        "stadium",
        "government"
    ],
    "wof:name":"Cranbrook Memorial Arena",
    "wof:placetype":"venue"
},
  "geometry": {"coordinates":[-115.76133728000001,49.5140228271],"type":"Point"}
}