{
  "type": "Feature",
  "properties": {
    "addr:full":"2489 Rue Jean-Talon E Montreal QC H2E 1W3",
    "addr:housenumber":"2489",
    "addr:postcode":"h2e 1w3",
    "addr:street":"Rue Jean-Talon E",
    "iso:country":"CA",
    "sg:address":"2489 Rue Jean-Talon E",
    "sg:city":"Montreal",
    "sg:classifiers":[
        {
            "category":"Restaurant",
            "type":"Food & Drink"
        }
    ],
    "sg:phone":"+1 514 374 7448",
    "sg:postcode":"H2E 1W3",
    "sg:province":"QC",
    "wof:name":"Coin Mexicain",
    "wof:placetype":"venue"
},
  "geometry": {"coordinates":[-73.6023406982,45.5535354614],"type":"Point"}
}