{
  "type": "Feature",
  "properties": {
    "addr:full":"305 Olympia Dr SE Calgary AB T2C 1H6",
    "addr:housenumber":"305",
    "addr:postcode":"t2c 1h6",
    "addr:street":"Olympia Dr Se",
    "iso:country":"CA",
    "sg:address":"305 Olympia Dr SE",
    "sg:city":"Calgary",
    "sg:classifiers":[
        {
            "category":"Professional",
            "subcategory":"Business Services",
            "type":"Services"
        }
    ],
    "sg:phone":"+1 403 720 6512",
    "sg:postcode":"T2C 1H6",
    "sg:province":"AB",
    "sg:tags":[
        "embroidery"
    ],
    "wof:name":"Westwinds Embroidery Ltd",
    "wof:placetype":"venue"
},
  "geometry": {"coordinates":[-114.003906,50.98159],"type":"Point"}
}