{
  "type": "Feature",
  "properties": {
    "addr:full":"Verona ON K0H 2W0",
    "addr:postcode":"k0h 2w0",
    "iso:country":"CA",
    "sg:city":"Verona",
    "sg:classifiers":[
        {
            "category":"Real Estate",
            "subcategory":"Real Estate Agent",
            "type":"Services"
        }
    ],
    "sg:phone":"+1 613 374 2744",
    "sg:postcode":"K0H 2W0",
    "sg:province":"ON",
    "wof:name":"Glenn J Raycraft Real Estate",
    "wof:placetype":"venue"
},
  "geometry": {"coordinates":[-76.6942062378,44.4800605774],"type":"Point"}
}