{
  "type": "Feature",
  "properties": {
    "addr:full":"Calgary AB T3A 0E2",
    "addr:postcode":"t3a 0e2",
    "iso:country":"CA",
    "sg:city":"Calgary",
    "sg:classifiers":[
        {
            "category":"Food & Beverages",
            "subcategory":"Bakery",
            "type":"Retail Goods"
        }
    ],
    "sg:phone":"+1 403 288 3500",
    "sg:postcode":"T3A 0E2",
    "sg:province":"AB",
    "sg:tags":[
        "baker"
    ],
    "wof:name":"Company's Coming Bakery",
    "wof:placetype":"venue"
},
  "geometry": {"coordinates":[-114.15316799999999,51.085464],"type":"Point"}
}