{
  "type": "Feature",
  "properties": {
    "addr:full":"7542 Gilley Ave Burnaby BC V5J 4X5",
    "addr:housenumber":"7542",
    "addr:postcode":"v5j 4x5",
    "addr:street":"Gilley Ave",
    "iso:country":"CA",
    "sg:address":"7542 Gilley Ave",
    "sg:city":"Burnaby",
    "sg:classifiers":[
        {
            "category":"Manufacturing",
            "subcategory":"Food",
            "type":"Manufacturing & Wholesale Goods"
        }
    ],
    "sg:phone":"+1 604 430 1173",
    "sg:postcode":"V5J 4X5",
    "sg:province":"BC",
    "sg:tags":[
        "product",
        "manufacturer"
    ],
    "wof:name":"J D Sweid & CO Ltd",
    "wof:placetype":"venue"
},
  "geometry": {"coordinates":[-122.971794128,49.2153015137],"type":"Point"}
}