{
  "type": "Feature",
  "properties": {
    "iso:country":"CA",
    "sg:address":"5050 Dufferin St",
    "sg:city":"North York",
    "sg:classifiers":[
        {
            "category":"Wholesale",
            "subcategory":"Vending Machines",
            "type":"Manufacturing & Wholesale Goods"
        }
    ],
    "sg:phone":"+1 416 650 0488",
    "sg:postcode":"M3H 5T5",
    "sg:province":"ON",
    "wof:name":"Mr Vending Inc",
    "wof:placetype":"venue"
},
  "geometry": {"coordinates":[-79.47016143800001,43.7814826965],"type":"Point"}
}