{
  "type": "Feature",
  "properties": {
    "addr:full":"200 Railway Ave Shell Lake SK S0J 2G0",
    "addr:housenumber":"200",
    "addr:postcode":"s0j 2g0",
    "addr:street":"Railway Ave",
    "iso:country":"CA",
    "sg:address":"200 Railway Ave",
    "sg:city":"Shell Lake",
    "sg:classifiers":[
        {
            "category":"Travel",
            "subcategory":"Travel Agent",
            "type":"Entertainment"
        }
    ],
    "sg:phone":"+1 306 427 2202",
    "sg:postcode":"S0J 2G0",
    "sg:province":"SK",
    "sg:tags":[
        "information",
        "tourist"
    ],
    "wof:name":"Northern Sask Tourism Inc",
    "wof:placetype":"venue"
},
  "geometry": {"coordinates":[-107.065262,53.305565],"type":"Point"}
}