{
  "type": "Feature",
  "properties": {
    "addr:full":"575 Royal Oak Rd Little Britain ON K0M 2C0",
    "addr:housenumber":"575",
    "addr:postcode":"k0m 2c0",
    "addr:street":"Royal Oak Rd",
    "iso:country":"CA",
    "sg:address":"575 Royal Oak Rd",
    "sg:city":"Little Britain",
    "sg:classifiers":[
        {
            "category":"Building & Trades",
            "subcategory":"Plumbing",
            "type":"Services"
        }
    ],
    "sg:phone":"+1 705 786 2673",
    "sg:postcode":"K0M 2C0",
    "sg:province":"ON",
    "sg:tags":[
        "contractor"
    ],
    "wof:name":"G & G Plumbing & Heating",
    "wof:placetype":"venue"
},
  "geometry": {"coordinates":[-78.908897,44.274078],"type":"Point"}
}