{
  "type": "Feature",
  "properties": {
    "addr:full":"19 Queen St Port Hope ON L1A 2Y8",
    "addr:housenumber":"19",
    "addr:postcode":"l1a 2y8",
    "addr:street":"Queen St",
    "iso:country":"CA",
    "sg:address":"19 Queen St",
    "sg:city":"Port Hope",
    "sg:classifiers":[
        {
            "category":"Health Services",
            "subcategory":"Doctor",
            "type":"Services"
        }
    ],
    "sg:phone":"+1 905 885 5314",
    "sg:postcode":"L1A 2Y8",
    "sg:province":"ON",
    "sg:tags":[
        "dentist"
    ],
    "wof:name":"Altima Dental Ctr",
    "wof:placetype":"venue"
},
  "geometry": {"coordinates":[-78.2928390503,43.9507446289],"type":"Point"}
}