{
  "type": "Feature",
  "properties": {
    "addr:full":"1155 Fairville Blvd Saint John NB E2M 5T9",
    "addr:housenumber":"1155",
    "addr:postcode":"e2m 5t9",
    "addr:street":"Fairville Blvd",
    "iso:country":"CA",
    "sg:address":"1155 Fairville Blvd",
    "sg:city":"Saint John",
    "sg:classifiers":[
        {
            "category":"Travel",
            "subcategory":"Hotels & Motels",
            "type":"Entertainment"
        }
    ],
    "sg:phone":"+1 506 674 1873",
    "sg:postcode":"E2M 5T9",
    "sg:province":"NB",
    "wof:name":"Comfort Inn",
    "wof:placetype":"venue"
},
  "geometry": {"coordinates":[-66.10897799999999,45.245728],"type":"Point"}
}