{
  "type": "Feature",
  "properties": {
    "iso:country":"CA",
    "sg:address":"1155 Fairville Blvd",
    "sg:city":"Saint John",
    "sg:classifiers":[
        {
            "category":"Travel",
            "subcategory":"Hotels & Motels",
            "type":"Entertainment"
        }
    ],
    "sg:phone":"+1 506 674 1873",
    "sg:postcode":"E2M 5T9",
    "sg:province":"NB",
    "wof:name":"Comfort Inn",
    "wof:placetype":"venue"
},
  "geometry": {"coordinates":[-66.108978,45.245728],"type":"Point"}
}