{
  "type": "Feature",
  "properties": {
    "addr:full":"1455 Rue Champlain Trois-Rivieres QC G9A 5X4",
    "addr:housenumber":"1455",
    "addr:postcode":"g9a 5x4",
    "addr:street":"Rue Champlain",
    "iso:country":"CA",
    "sg:address":"1455 Rue Champlain",
    "sg:city":"Trois-Rivieres",
    "sg:classifiers":[
        {
            "category":"Professional",
            "subcategory":"Engineering",
            "type":"Services"
        }
    ],
    "sg:phone":"+1 819 378 6159",
    "sg:postcode":"G9A 5X4",
    "sg:province":"QC",
    "sg:tags":[
        "engineer"
    ],
    "wof:name":"Consultants Vfp Inc",
    "wof:placetype":"venue"
},
  "geometry": {"coordinates":[-72.543716,46.34169],"type":"Point"}
}