{
  "type": "Feature",
  "properties": {
    "addr:full":"Newcastle ON L1B 1H7",
    "addr:postcode":"l1b 1h7",
    "iso:country":"CA",
    "sg:city":"Newcastle",
    "sg:classifiers":[
        {
            "category":"Health Services",
            "subcategory":"Doctor",
            "type":"Services"
        }
    ],
    "sg:phone":"+1 905 987 2155",
    "sg:postcode":"L1B 1H7",
    "sg:province":"ON",
    "sg:tags":[
        "dentist"
    ],
    "wof:name":"Wilson, Bruce DDS",
    "wof:placetype":"venue"
},
  "geometry": {"coordinates":[-78.590675,43.917191],"type":"Point"}
}