{
  "type": "Feature",
  "properties": {
    "iso:country":"CA",
    "sg:city":"Sudbury",
    "sg:classifiers":[
        {
            "category":"Home & Garden",
            "subcategory":"Furniture",
            "type":"Retail Goods"
        }
    ],
    "sg:phone":"+1 705 523 5806",
    "sg:postcode":"P3E 5R2",
    "sg:province":"ON",
    "wof:name":"Sklar Peppler Furniture",
    "wof:placetype":"venue"
},
  "geometry": {"coordinates":[-81.0015716553,46.4508743286],"type":"Point"}
}