{
  "type": "Feature",
  "properties": {
    "addr:full":"Powell River BC V8A 2N2",
    "addr:postcode":"v8a 2n2",
    "iso:country":"CA",
    "sg:city":"Powell River",
    "sg:classifiers":[
        {
            "category":"Shopping",
            "subcategory":"Used Merchandise",
            "type":"Retail Goods"
        }
    ],
    "sg:phone":"+1 604 485 6997",
    "sg:postcode":"V8A 2N2",
    "sg:province":"BC",
    "sg:tags":[
        "shop",
        "thrift"
    ],
    "wof:name":"Just A Second",
    "wof:placetype":"venue"
},
  "geometry": {"coordinates":[-124.528846741,49.8405303955],"type":"Point"}
}