{
  "type": "Feature",
  "properties": {
    "addr:full":"5680 Eighth Line Hornby ON L0P 1E0",
    "addr:housenumber":"5680",
    "addr:postcode":"l0p 1e0",
    "addr:street":"Eighth Line",
    "iso:country":"CA",
    "sg:address":"5680 Eighth Line",
    "sg:city":"Hornby",
    "sg:classifiers":[
        {
            "category":"Building & Trades",
            "subcategory":"Construction",
            "type":"Services"
        }
    ],
    "sg:phone":"+1 905 693 9757",
    "sg:postcode":"L0P 1E0",
    "sg:province":"ON",
    "sg:tags":[
        "excavating",
        "contractor"
    ],
    "wof:name":"Campbell & Son Ltd",
    "wof:placetype":"venue"
},
  "geometry": {"coordinates":[-79.837952,43.571579],"type":"Point"}
}