{
  "type": "Feature",
  "properties": {
    "addr:full":"296 Highland Rd E Kitchener ON N2M 3W4",
    "addr:housenumber":"296",
    "addr:postcode":"n2m 3w4",
    "addr:street":"Highland Rd E",
    "iso:country":"CA",
    "sg:address":"296 Highland Rd E",
    "sg:city":"Kitchener",
    "sg:classifiers":[
        {
            "category":"Shopping",
            "subcategory":"Discount & Variety Stores",
            "type":"Retail Goods"
        }
    ],
    "sg:phone":"+1 519 570 4116",
    "sg:postcode":"N2M 3W4",
    "sg:province":"ON",
    "wof:name":"Sam's Super Variety Store",
    "wof:placetype":"venue"
},
  "geometry": {"coordinates":[-80.49015799999999,43.435112],"type":"Point"}
}