{
  "type": "Feature",
  "properties": {
    "iso:country":"CA",
    "sg:address":"296 Highland Rd E",
    "sg:city":"Kitchener",
    "sg:classifiers":[
        {
            "category":"Shopping",
            "subcategory":"Discount & Variety Stores",
            "type":"Retail Goods"
        }
    ],
    "sg:phone":"+1 519 570 4116",
    "sg:postcode":"N2M 3W4",
    "sg:province":"ON",
    "wof:name":"Sam's Super Variety Store",
    "wof:placetype":"venue"
},
  "geometry": {"coordinates":[-80.490158,43.435112],"type":"Point"}
}