{
  "type": "Feature",
  "properties": {
    "addr:full":"Montreal QC H2N 2A5",
    "addr:postcode":"h2n 2a5",
    "iso:country":"CA",
    "sg:city":"Montreal",
    "sg:classifiers":[
        {
            "category":"Manufacturing",
            "subcategory":"Textiles",
            "type":"Manufacturing & Wholesale Goods"
        }
    ],
    "sg:phone":"+1 514 383 9133",
    "sg:postcode":"H2N 2A5",
    "sg:province":"QC",
    "sg:tags":[
        "finishing"
    ],
    "wof:name":"Atlas Guarantee Sponging Inc",
    "wof:placetype":"venue"
},
  "geometry": {"coordinates":[-73.65366400000001,45.536964],"type":"Point"}
}