{
  "type": "Feature",
  "properties": {
    "addr:full":"300 Milroy Dr Peterborough ON K9H 7M9",
    "addr:housenumber":"300",
    "addr:postcode":"k9h 7m9",
    "addr:street":"Milroy Dr",
    "iso:country":"CA",
    "sg:address":"300 Milroy Dr",
    "sg:city":"Peterborough",
    "sg:classifiers":[
        {
            "category":"Organizations",
            "subcategory":"Religious Organization",
            "type":"Services"
        }
    ],
    "sg:phone":"+1 705 748 2861",
    "sg:postcode":"K9H 7M9",
    "sg:province":"ON",
    "sg:tags":[
        "church"
    ],
    "wof:name":"Peterborough Christian Fellow",
    "wof:placetype":"venue"
},
  "geometry": {"coordinates":[-78.339027,44.331425],"type":"Point"}
}