{
  "type": "Feature",
  "properties": {
    "iso:country":"CA",
    "sg:address":"9 Parkside Dr",
    "sg:city":"St Jacobs",
    "sg:classifiers":[
        {
            "category":"Health Services",
            "subcategory":"Health Practitioner",
            "type":"Services"
        }
    ],
    "sg:phone":"+1 519 664 2542",
    "sg:postcode":"N0B 2N0",
    "sg:province":"ON",
    "sg:tags":[
        "midwife"
    ],
    "wof:name":"St Jacobs Midwives",
    "wof:placetype":"venue"
},
  "geometry": {"coordinates":[-80.5515213013,43.5440788269],"type":"Point"}
}