{
  "type": "Feature",
  "properties": {
    "addr:full":"Winnipeg MB R3G 0E9",
    "addr:postcode":"r3g 0e9",
    "iso:country":"CA",
    "sg:city":"Winnipeg",
    "sg:classifiers":[
        {
            "category":"Home & Garden",
            "subcategory":"Furniture",
            "type":"Retail Goods"
        }
    ],
    "sg:phone":"+1 204 954 9710",
    "sg:postcode":"R3G 0E9",
    "sg:province":"MB",
    "wof:name":"Jysk Linen 'N Furniture Inc",
    "wof:placetype":"venue"
},
  "geometry": {"coordinates":[-97.1936264038,49.8938941956],"type":"Point"}
}