{
  "type": "Feature",
  "properties": {
    "addr:full":"126 Mitton St S Sarnia ON N7T 3C4",
    "addr:housenumber":"126",
    "addr:postcode":"n7t 3c4",
    "addr:street":"Mitton St S",
    "iso:country":"CA",
    "sg:address":"126 Mitton St S",
    "sg:city":"Sarnia",
    "sg:classifiers":[
        {
            "category":"Cinema",
            "subcategory":"Movie Rental",
            "type":"Entertainment"
        }
    ],
    "sg:phone":"+1 519 336 5597",
    "sg:postcode":"N7T 3C4",
    "sg:province":"ON",
    "sg:tags":[
        "leasing",
        "video",
        "disc",
        "tape"
    ],
    "wof:name":"Video World",
    "wof:placetype":"venue"
},
  "geometry": {"coordinates":[-82.39821600000001,42.969826],"type":"Point"}
}