{
  "type": "Feature",
  "properties": {
    "addr:full":"1364 Bradner Rd Abbotsford BC V4X 1H8",
    "addr:housenumber":"1364",
    "addr:postcode":"v4x 1h8",
    "addr:street":"Bradner Rd",
    "iso:country":"CA",
    "sg:address":"1364 Bradner Rd",
    "sg:city":"Abbotsford",
    "sg:classifiers":[
        {
            "category":"Farming",
            "subcategory":"Aquatic Farm",
            "type":"Manufacturing & Wholesale Goods"
        }
    ],
    "sg:phone":"+1 604 856 2298",
    "sg:postcode":"V4X 1H8",
    "sg:province":"BC",
    "sg:tags":[
        "hatchery",
        "fish"
    ],
    "wof:name":"Silverbrook U-Catch",
    "wof:placetype":"venue"
},
  "geometry": {"coordinates":[-122.42755099999999,49.026958],"type":"Point"}
}