{
  "type": "Feature",
  "properties": {
    "addr:full":"12 Nantucket Blvd Scarborough ON M1P 2N4",
    "addr:housenumber":"12",
    "addr:postcode":"m1p 2n4",
    "addr:street":"Nantucket Blvd",
    "iso:country":"CA",
    "sg:address":"12 Nantucket Blvd",
    "sg:city":"Scarborough",
    "sg:classifiers":[
        {
            "category":"Manufacturing",
            "subcategory":"Printing",
            "type":"Manufacturing & Wholesale Goods"
        }
    ],
    "sg:phone":"+1 416 752 7220",
    "sg:postcode":"M1P 2N4",
    "sg:province":"ON",
    "sg:tags":[
        "screen"
    ],
    "wof:name":"Cameron Advertising Displays",
    "wof:placetype":"venue"
},
  "geometry": {"coordinates":[-79.272369,43.752106],"type":"Point"}
}