{
  "type": "Feature",
  "properties": {
    "addr:full":"1576 Bonhill Rd Mississauga ON L5T 1C7",
    "addr:housenumber":"1576",
    "addr:postcode":"l5t 1c7",
    "addr:street":"Bonhill Rd",
    "iso:country":"CA",
    "sg:address":"1576 Bonhill Rd",
    "sg:city":"Mississauga",
    "sg:classifiers":[
        {
            "category":"Wholesale",
            "subcategory":"Machinery & Supplies",
            "type":"Manufacturing & Wholesale Goods"
        }
    ],
    "sg:phone":"+1 905 564 2421",
    "sg:postcode":"L5T 1C7",
    "sg:province":"ON",
    "sg:tags":[
        "sprinkler"
    ],
    "wof:name":"Paul & Douglas Auto Sprinklers",
    "wof:placetype":"venue"
},
  "geometry": {"coordinates":[-79.6548461914,43.6634902954],"type":"Point"}
}