{
  "type": "Feature",
  "properties": {
    "addr:full":"14250 124 Ave NW Edmonton AB T5L 3B3",
    "addr:housenumber":"14250",
    "addr:postcode":"t5l 3b3",
    "addr:street":"124 Ave Nw",
    "iso:country":"CA",
    "sg:address":"14250 124 Ave NW",
    "sg:city":"Edmonton",
    "sg:classifiers":[
        {
            "category":"Manufacturing",
            "subcategory":"Tools & Machinery",
            "type":"Manufacturing & Wholesale Goods"
        }
    ],
    "sg:phone":"+1 780 465 8888",
    "sg:postcode":"T5L 3B3",
    "sg:province":"AB",
    "sg:tags":[
        "water",
        "equipment",
        "works",
        "valve"
    ],
    "wof:name":"Crane Supply",
    "wof:placetype":"venue"
},
  "geometry": {"coordinates":[-113.568229675,53.5791473389],"type":"Point"}
}