{
  "type": "Feature",
  "properties": {
    "addr:full":"636 Leila Ave Winnipeg MB R2V 3N7",
    "addr:housenumber":"636",
    "addr:postcode":"r2v 3n7",
    "addr:street":"Leila Ave",
    "iso:country":"CA",
    "sg:address":"636 Leila Ave",
    "sg:city":"Winnipeg",
    "sg:classifiers":[
        {
            "category":"Real Estate",
            "subcategory":"Real Estate Agent",
            "type":"Services"
        }
    ],
    "sg:phone":"+1 204 982 0984",
    "sg:postcode":"R2V 3N7",
    "sg:province":"MB",
    "wof:name":"Dettman, Richard",
    "wof:placetype":"venue"
},
  "geometry": {"coordinates":[-97.1345214844,49.9489898682],"type":"Point"}
}