{
  "type": "Feature",
  "properties": {
    "addr:full":"Ardrossan AB T8E 2H3",
    "addr:postcode":"t8e 2h3",
    "iso:country":"CA",
    "sg:city":"Ardrossan",
    "sg:classifiers":[
        {
            "category":"Wholesale",
            "subcategory":"Chemicals & Plastics",
            "type":"Manufacturing & Wholesale Goods"
        }
    ],
    "sg:phone":"+1 780 465 5823",
    "sg:postcode":"T8E 2H3",
    "sg:province":"AB",
    "sg:tags":[
        "oil",
        "additive"
    ],
    "wof:name":"Power Up Lubricants",
    "wof:placetype":"venue"
},
  "geometry": {"coordinates":[-113.148094177,53.5615539551],"type":"Point"}
}