{
  "type": "Feature",
  "properties": {
    "addr:full":"1598 Tecumseh Rd E Windsor ON N8W 1C4",
    "addr:housenumber":"1598",
    "addr:postcode":"n8w 1c4",
    "addr:street":"Tecumseh Rd E",
    "iso:country":"CA",
    "sg:address":"1598 Tecumseh Rd E",
    "sg:city":"Windsor",
    "sg:classifiers":[
        {
            "category":"Food & Beverages",
            "subcategory":"Groceries & Convenience Stores",
            "type":"Retail Goods"
        }
    ],
    "sg:phone":"+1 519 253 8939",
    "sg:postcode":"N8W 1C4",
    "sg:province":"ON",
    "sg:tags":[
        "variety"
    ],
    "wof:name":"One Stop Corner Store",
    "wof:placetype":"venue"
},
  "geometry": {"coordinates":[-83.00257873539999,42.3008308411],"type":"Point"}
}