{
  "type": "Feature",
  "properties": {
    "addr:full":"Etobicoke ON M8X 1Y4",
    "addr:postcode":"m8x 1y4",
    "iso:country":"CA",
    "sg:city":"Etobicoke",
    "sg:classifiers":[
        {
            "category":"Professional",
            "subcategory":"Lawyer & Legal Services",
            "type":"Services"
        }
    ],
    "sg:phone":"+1 416 239 3431",
    "sg:postcode":"M8X 1Y4",
    "sg:province":"ON",
    "sg:tags":[
        "attorney"
    ],
    "wof:name":"Birks Langdon & Elliott",
    "wof:placetype":"venue"
},
  "geometry": {"coordinates":[-79.510848999,43.6603431702],"type":"Point"}
}