{
  "type": "Feature",
  "properties": {
    "addr:full":"1067 Yonge St Toronto ON M4W 2L2",
    "addr:housenumber":"1067",
    "addr:postcode":"m4w 2l2",
    "addr:street":"Yonge St",
    "iso:country":"CA",
    "sg:address":"1067 Yonge St",
    "sg:city":"Toronto",
    "sg:classifiers":[
        {
            "category":"Real Estate",
            "subcategory":"Architect",
            "type":"Services"
        }
    ],
    "sg:phone":"+1 416 928 1444",
    "sg:postcode":"M4W 2L2",
    "sg:province":"ON",
    "sg:tags":[
        "course",
        "golf"
    ],
    "wof:name":"Horwath Horizon Consultants",
    "wof:placetype":"venue"
},
  "geometry": {"coordinates":[-79.390068,43.678822],"type":"Point"}
}