{
  "type": "Feature",
  "properties": {
    "addr:full":"10635 76 Ave Grande Prairie AB T8W 2J9",
    "addr:housenumber":"10635",
    "addr:postcode":"t8w 2j9",
    "addr:street":"76 Ave",
    "iso:country":"CA",
    "sg:address":"10635 76 Ave",
    "sg:city":"Grande Prairie",
    "sg:classifiers":[
        {
            "category":"Health Services",
            "subcategory":"Health Practitioner",
            "type":"Services"
        }
    ],
    "sg:phone":"+1 780 513 2261",
    "sg:postcode":"T8W 2J9",
    "sg:province":"AB",
    "sg:tags":[
        "speech",
        "therapy",
        "hearing"
    ],
    "wof:name":"Sound Discoveries",
    "wof:placetype":"venue"
},
  "geometry": {"coordinates":[-118.812904,55.148022],"type":"Point"}
}