{
  "type": "Feature",
  "properties": {
    "iso:country":"CA",
    "sg:address":"2348 Rue Jean-Talon E",
    "sg:city":"Montreal",
    "sg:classifiers":[
        {
            "category":"Professional",
            "type":"Services"
        }
    ],
    "sg:phone":"+1 514 725 7144",
    "sg:postcode":"H2E 1V7",
    "sg:province":"QC",
    "sg:tags":[
        "establishment",
        "agency",
        "employment",
        "opportunity"
    ],
    "wof:name":"Ayrton Service Enr",
    "wof:placetype":"venue"
},
  "geometry": {"coordinates":[-73.60305,45.552345],"type":"Point"}
}