{
  "type": "Feature",
  "properties": {
    "addr:full":"1382 Main St Murray Harbour PE C0A 1V0",
    "addr:housenumber":"1382",
    "addr:postcode":"c0a 1v0",
    "addr:street":"Main St",
    "iso:country":"CA",
    "sg:address":"1382 Main St",
    "sg:city":"Murray Harbour",
    "sg:classifiers":[
        {
            "category":"Education",
            "subcategory":"Library",
            "type":"Public Place"
        }
    ],
    "sg:phone":"+1 902 962 3875",
    "sg:postcode":"C0A 1V0",
    "sg:province":"PE",
    "wof:name":"PE Murray Harbour Library",
    "wof:placetype":"venue"
},
  "geometry": {"coordinates":[-62.522953,46.004765],"type":"Point"}
}