{
  "type": "Feature",
  "properties": {
    "addr:full":"173 Spadina Ave Toronto ON M5T 2C3",
    "addr:housenumber":"173",
    "addr:postcode":"m5t 2c3",
    "addr:street":"Spadina Ave",
    "iso:country":"CA",
    "sg:address":"173 Spadina Ave",
    "sg:city":"Toronto",
    "sg:classifiers":[
        {
            "category":"Wholesale",
            "subcategory":"Apparel",
            "type":"Manufacturing & Wholesale Goods"
        }
    ],
    "sg:phone":"+1 416 971 6129",
    "sg:postcode":"M5T 2C3",
    "sg:province":"ON",
    "sg:tags":[
        "clothing"
    ],
    "wof:name":"Modern Design",
    "wof:placetype":"venue"
},
  "geometry": {"coordinates":[-79.39621,43.649166],"type":"Point"}
}