{
  "type": "Feature",
  "properties": {
    "addr:full":"846 the Queensway Etobicoke ON M8Z 1N7",
    "addr:housenumber":"846",
    "addr:postcode":"m8z 1n7",
    "addr:street":"The Queensway",
    "iso:country":"CA",
    "sg:address":"846 the Queensway",
    "sg:city":"Etobicoke",
    "sg:classifiers":[
        {
            "category":"Shopping",
            "type":"Retail Goods"
        }
    ],
    "sg:phone":"+1 416 251 6669",
    "sg:postcode":"M8Z 1N7",
    "sg:province":"ON",
    "sg:tags":[
        "video",
        "disc",
        "tape",
        "miscellaneous",
        "store"
    ],
    "wof:name":"Sneak A Peek",
    "wof:placetype":"venue"
},
  "geometry": {"coordinates":[-79.50939200000001,43.624973],"type":"Point"}
}