{
  "type": "Feature",
  "properties": {
    "addr:full":"Winnipeg MB R3C 0C8",
    "addr:postcode":"r3c 0c8",
    "iso:country":"CA",
    "sg:city":"Winnipeg",
    "sg:classifiers":[
        {
            "category":"Health Services",
            "subcategory":"Medical Lab",
            "type":"Services"
        }
    ],
    "sg:phone":"+1 204 947 1082",
    "sg:postcode":"R3C 0C8",
    "sg:province":"MB",
    "wof:name":"Central Park Denture Clinic",
    "wof:placetype":"venue"
},
  "geometry": {"coordinates":[-97.14685799999999,49.892235],"type":"Point"}
}