{
  "type": "Feature",
  "properties": {
    "addr:full":"4938 Boul Allard Saint-Nicephore QC J2A 2S3",
    "addr:housenumber":"4938",
    "addr:postcode":"j2a 2s3",
    "addr:street":"Boul Allard Saint-Nicephore",
    "iso:country":"CA",
    "sg:address":"4938 Boul Allard",
    "sg:city":"Saint-Nicephore",
    "sg:classifiers":[
        {
            "category":"Organizations",
            "subcategory":"Professional Association",
            "type":"Services"
        }
    ],
    "sg:phone":"+1 819 477 0389",
    "sg:postcode":"J2A 2S3",
    "sg:province":"QC",
    "wof:name":"Club Chasse & Peche DE Drmvl",
    "wof:placetype":"venue"
},
  "geometry": {"coordinates":[-72.388161,45.85194],"type":"Point"}
}