{
  "type": "Feature",
  "properties": {
    "addr:full":"688 University Ave W Windsor ON N9A 5R5",
    "addr:housenumber":"688",
    "addr:postcode":"n9a 5r5",
    "addr:street":"University Ave W",
    "iso:country":"CA",
    "sg:address":"688 University Ave W",
    "sg:city":"Windsor",
    "sg:classifiers":[
        {
            "category":"Wholesale",
            "subcategory":"Furniture",
            "type":"Manufacturing & Wholesale Goods"
        }
    ],
    "sg:phone":"+1 519 256 3141",
    "sg:postcode":"N9A 5R5",
    "sg:province":"ON",
    "wof:name":"Mayhew & Assoc",
    "wof:placetype":"venue"
},
  "geometry": {"coordinates":[-83.04703499999999,42.315666],"type":"Point"}
}