{
  "type": "Feature",
  "properties": {
    "addr:full":"8105 Davies Rd NW Edmonton AB T6E 4N1",
    "addr:housenumber":"8105",
    "addr:postcode":"t6e 4n1",
    "addr:street":"Davies Rd Nw",
    "iso:country":"CA",
    "sg:address":"8105 Davies Rd NW",
    "sg:city":"Edmonton",
    "sg:classifiers":[
        {
            "category":"Building & Trades",
            "subcategory":"Construction",
            "type":"Services"
        }
    ],
    "sg:phone":"+1 780 466 1820",
    "sg:postcode":"T6E 4N1",
    "sg:province":"AB",
    "sg:tags":[
        "concrete",
        "restoration",
        "repair",
        "cleaning",
        "contractor"
    ],
    "wof:name":"Redco Restoration Specialists",
    "wof:placetype":"venue"
},
  "geometry": {"coordinates":[-113.448959,53.496403],"type":"Point"}
}