{
  "type": "Feature",
  "properties": {
    "addr:full":"508 3 Ave S Lethbridge AB T1J 0H3",
    "addr:housenumber":"508",
    "addr:postcode":"t1j 0h3",
    "addr:street":"3 Ave S",
    "iso:country":"CA",
    "sg:address":"508 3 Ave S",
    "sg:city":"Lethbridge",
    "sg:classifiers":[
        {
            "category":"Shopping",
            "subcategory":"Optical Goods",
            "type":"Retail Goods"
        }
    ],
    "sg:phone":"+1 403 327 4161",
    "sg:postcode":"T1J 0H3",
    "sg:province":"AB",
    "sg:tags":[
        "sun",
        "goggles",
        "sunglasses",
        "optician"
    ],
    "wof:name":"Langenberg Optical Ltd",
    "wof:placetype":"venue"
},
  "geometry": {"coordinates":[-112.840103,49.695683],"type":"Point"}
}