{
  "type": "Feature",
  "properties": {
    "iso:country":"CA",
    "sg:address":"1045 Ch Sainte-Foy",
    "sg:city":"Quebec",
    "sg:classifiers":[
        {
            "category":"Health Services",
            "subcategory":"Chiropractor",
            "type":"Services"
        }
    ],
    "sg:phone":"+1 418 681 5858",
    "sg:postcode":"G1S 2L8",
    "sg:province":"QC",
    "wof:name":"Centre Chiropratqiue Montcalm",
    "wof:placetype":"venue"
},
  "geometry": {"coordinates":[-71.2450180054,46.7986373901],"type":"Point"}
}