{
  "type": "Feature",
  "properties": {
    "iso:country":"CA",
    "sg:address":"5002 54th Ave",
    "sg:city":"Provost",
    "sg:classifiers":[
        {
            "category":"Local Transit",
            "type":"Transportation"
        }
    ],
    "sg:phone":"+1 780 753 3314",
    "sg:postcode":"T0B 3S0",
    "sg:province":"AB",
    "sg:tags":[
        "hospital",
        "ambulance"
    ],
    "wof:name":"Provost Ambulance",
    "wof:placetype":"venue"
},
  "geometry": {"coordinates":[-110.265167236,52.3572921753],"type":"Point"}
}