{
  "type": "Feature",
  "properties": {
    "iso:country":"CA",
    "sg:address":"428 Main St",
    "sg:city":"Foam Lake",
    "sg:classifiers":[
        {
            "category":"Personal",
            "type":"Services"
        }
    ],
    "sg:phone":"+1 306 272 3543",
    "sg:postcode":"S0A 1A0",
    "sg:province":"SK",
    "sg:tags":[
        "therapist",
        "massage"
    ],
    "wof:name":"Mary Ann's Massage",
    "wof:placetype":"venue"
},
  "geometry": {"coordinates":[-103.53384399399999,51.6431121826],"type":"Point"}
}