{
  "type": "Feature",
  "properties": {
    "addr:full":"Farm Cudworth SK S0K 1B0",
    "addr:postcode":"s0k 1b0",
    "iso:country":"CA",
    "sg:address":"Farm",
    "sg:city":"Cudworth",
    "sg:classifiers":[
        {
            "category":"Building & Trades",
            "subcategory":"Construction",
            "type":"Services"
        }
    ],
    "sg:phone":"+1 306 256 3686",
    "sg:postcode":"S0K 1B0",
    "sg:province":"SK",
    "sg:tags":[
        "boring",
        "drilling",
        "contractor"
    ],
    "wof:name":"Can am Drilling",
    "wof:placetype":"venue"
},
  "geometry": {"coordinates":[-105.73329200000001,52.492901],"type":"Point"}
}