{
  "type": "Feature",
  "properties": {
    "addr:full":"301 Hearn St Outlook SK S0L 2N0",
    "addr:housenumber":"301",
    "addr:postcode":"s0l 2n0",
    "addr:street":"Hearn St",
    "iso:country":"CA",
    "sg:address":"301 Hearn St",
    "sg:city":"Outlook",
    "sg:classifiers":[
        {
            "category":"Organizations",
            "subcategory":"Religious Organization",
            "type":"Services"
        }
    ],
    "sg:phone":"+1 306 867 2225",
    "sg:postcode":"S0L 2N0",
    "sg:province":"SK",
    "sg:tags":[
        "church"
    ],
    "wof:name":"Jehovah's Witnesses",
    "wof:placetype":"venue"
},
  "geometry": {"coordinates":[-107.04792,51.483696],"type":"Point"}
}