{
  "type": "Feature",
  "properties": {
    "iso:country":"CA",
    "sg:address":"380 2E Av",
    "sg:city":"Iberville",
    "sg:classifiers":[
        {
            "category":"Home & Garden",
            "subcategory":"Furniture",
            "type":"Retail Goods"
        }
    ],
    "sg:phone":"+1 450 347 1895",
    "sg:postcode":"J2X 2B8",
    "sg:province":"QC",
    "sg:tags":[
        "appliance"
    ],
    "wof:name":"Duval Meubles Usages Enr",
    "wof:placetype":"venue"
},
  "geometry": {"coordinates":[-73.2320327759,45.3043403625],"type":"Point"}
}