{
  "type": "Feature",
  "properties": {
    "addr:full":"35 William Kitchen Rd Scarborough ON M1P 5B7",
    "addr:housenumber":"35",
    "addr:postcode":"m1p 5b7",
    "addr:street":"William Kitchen Rd",
    "iso:country":"CA",
    "sg:address":"35 William Kitchen Rd",
    "sg:city":"Scarborough",
    "sg:classifiers":[
        {
            "category":"Personal",
            "type":"Services"
        }
    ],
    "sg:phone":"+1 416 755 3331",
    "sg:postcode":"M1P 5B7",
    "sg:province":"ON",
    "sg:tags":[
        "clothing",
        "furnishing",
        "formal"
    ],
    "wof:name":"Moores Clothing For Men",
    "wof:placetype":"venue"
},
  "geometry": {"coordinates":[-79.279404,43.772251],"type":"Point"}
}