{
  "type": "Feature",
  "properties": {
    "addr:full":"630 Rue Saint-Germain E Rimouski-Est QC G5L 1G4",
    "addr:housenumber":"630",
    "addr:postcode":"g5l 1g4",
    "addr:street":"Rue Saint-Germain E Rimouski-Est",
    "iso:country":"CA",
    "sg:address":"630 Rue Saint-Germain E",
    "sg:city":"Rimouski-Est",
    "sg:classifiers":[
        {
            "category":"Manufacturing",
            "subcategory":"Furniture",
            "type":"Manufacturing & Wholesale Goods"
        }
    ],
    "sg:phone":"+1 418 721 6551",
    "sg:postcode":"G5L 1G4",
    "sg:province":"QC",
    "sg:tags":[
        "upholsterer"
    ],
    "wof:name":"Nouveau Design Enr",
    "wof:placetype":"venue"
},
  "geometry": {"coordinates":[-68.50449399999999,48.480347],"type":"Point"}
}