{
  "type": "Feature",
  "properties": {
    "addr:full":"4670 Park St Niagara Falls ON L2E 2P9",
    "addr:housenumber":"4670",
    "addr:postcode":"l2e 2p9",
    "addr:street":"Park St",
    "iso:country":"CA",
    "sg:address":"4670 Park St",
    "sg:city":"Niagara Falls",
    "sg:classifiers":[
        {
            "category":"Retail",
            "subcategory":"Auto Repair",
            "type":"Services"
        }
    ],
    "sg:phone":"+1 905 358 3505",
    "sg:postcode":"L2E 2P9",
    "sg:province":"ON",
    "sg:tags":[
        "body",
        "automobile",
        "painting"
    ],
    "wof:name":"Park Auto Body Sales & Svc",
    "wof:placetype":"venue"
},
  "geometry": {"coordinates":[-79.070351,43.107464],"type":"Point"}
}