{
  "type": "Feature",
  "properties": {
    "addr:full":"44 Rue Sous-Le-Fort Quebec QC G1K 4G8",
    "addr:housenumber":"44",
    "addr:postcode":"g1k 4g8",
    "addr:street":"Rue Sous-Le-Fort",
    "iso:country":"CA",
    "sg:address":"44 Rue Sous-Le-Fort",
    "sg:city":"Quebec",
    "sg:classifiers":[
        {
            "category":"Shopping",
            "subcategory":"Gifts & Souvenirs",
            "type":"Retail Goods"
        }
    ],
    "sg:phone":"+1 418 692 3902",
    "sg:postcode":"G1K 4G8",
    "sg:province":"QC",
    "sg:tags":[
        "shop"
    ],
    "wof:name":"Boutique Du Lys",
    "wof:placetype":"venue"
},
  "geometry": {"coordinates":[-71.203003,46.812675],"type":"Point"}
}