{
  "type": "Feature",
  "properties": {
    "addr:full":"184 King St Sturgeon Falls ON P2B 1R5",
    "addr:housenumber":"184",
    "addr:postcode":"p2b 1r5",
    "addr:street":"King St",
    "iso:country":"CA",
    "sg:address":"184 King St",
    "sg:city":"Sturgeon Falls",
    "sg:classifiers":[
        {
            "category":"Shopping",
            "subcategory":"Stationery & Office Supplies",
            "type":"Retail Goods"
        }
    ],
    "sg:phone":"+1 705 753 1732",
    "sg:postcode":"P2B 1R5",
    "sg:province":"ON",
    "wof:name":"Mac's Office Supplies",
    "wof:placetype":"venue"
},
  "geometry": {"coordinates":[-79.92937499999999,46.368519],"type":"Point"}
}