{
  "type": "Feature",
  "properties": {
    "addr:full":"5611 47 St Leduc AB T9E 7A1",
    "addr:housenumber":"5611",
    "addr:postcode":"t9e 7a1",
    "addr:street":"47 St",
    "iso:country":"CA",
    "sg:address":"5611 47 St",
    "sg:city":"Leduc",
    "sg:classifiers":[
        {
            "category":"Manufacturing",
            "subcategory":"Tools & Machinery",
            "type":"Manufacturing & Wholesale Goods"
        }
    ],
    "sg:phone":"+1 780 986 6625",
    "sg:postcode":"T9E 7A1",
    "sg:province":"AB",
    "sg:tags":[
        "machine",
        "shop"
    ],
    "wof:name":"Springer Valves & Machine",
    "wof:placetype":"venue"
},
  "geometry": {"coordinates":[-113.5470047,53.2698364258],"type":"Point"}
}