{
  "type": "Feature",
  "properties": {
    "addr:full":"976 Rue Valiquette Sainte-Adele QC J8B 2M3",
    "addr:housenumber":"976",
    "addr:postcode":"j8b 2m3",
    "addr:street":"Rue Valiquette Sainte-Adele",
    "iso:country":"CA",
    "sg:address":"976 Rue Valiquette",
    "sg:city":"Sainte-Adele",
    "sg:classifiers":[
        {
            "category":"Insurance",
            "subcategory":"Insurance Agent",
            "type":"Services"
        }
    ],
    "sg:phone":"+1 450 229 3588",
    "sg:postcode":"J8B 2M3",
    "sg:province":"QC",
    "wof:name":"Groupe Lyras",
    "wof:placetype":"venue"
},
  "geometry": {"coordinates":[-74.1344833374,45.9500427246],"type":"Point"}
}