{
  "type": "Feature",
  "properties": {
    "iso:country":"CA",
    "sg:city":"Oakville",
    "sg:classifiers":[
        {
            "category":"Professional",
            "subcategory":"Business Services",
            "type":"Services"
        }
    ],
    "sg:phone":"+1 905 339 2255",
    "sg:postcode":"L6L 2X5",
    "sg:province":"ON",
    "sg:tags":[
        "water",
        "treatment"
    ],
    "wof:name":"Life Source Water Systems Ltd",
    "wof:placetype":"venue"
},
  "geometry": {"coordinates":[-79.7041931152,43.4318161011],"type":"Point"}
}