{
  "type": "Feature",
  "properties": {
    "addr:full":"200 County Court Blvd Brampton ON L6W 4K7",
    "addr:housenumber":"200",
    "addr:postcode":"l6w 4k7",
    "addr:street":"County Court Blvd",
    "iso:country":"CA",
    "sg:address":"200 County Court Blvd",
    "sg:city":"Brampton",
    "sg:classifiers":[
        {
            "category":"Health Services",
            "subcategory":"Doctor",
            "type":"Services"
        }
    ],
    "sg:phone":"+1 905 452 1227",
    "sg:postcode":"L6W 4K7",
    "sg:province":"ON",
    "sg:tags":[
        "dentist"
    ],
    "wof:name":"Chau & Chan",
    "wof:placetype":"venue"
},
  "geometry": {"coordinates":[-79.721649,43.660027],"type":"Point"}
}