{
  "type": "Feature",
  "properties": {
    "addr:full":"12 Laurelwood Dr Lower Coverdale NB E1J 1K8",
    "addr:housenumber":"12",
    "addr:postcode":"e1j 1k8",
    "addr:street":"Laurelwood Dr",
    "iso:country":"CA",
    "sg:address":"12 Laurelwood Dr",
    "sg:city":"Lower Coverdale",
    "sg:classifiers":[
        {
            "category":"Building & Trades",
            "subcategory":"Construction",
            "type":"Services"
        }
    ],
    "sg:phone":"+1 506 387 8627",
    "sg:postcode":"E1J 1K8",
    "sg:province":"NB",
    "sg:tags":[
        "concrete",
        "contractor"
    ],
    "wof:name":"John Lutes Foundations Ltd",
    "wof:placetype":"venue"
},
  "geometry": {"coordinates":[-64.716492,46.025799],"type":"Point"}
}