{
  "type": "Feature",
  "properties": {
    "addr:full":"20 Fisherman Dr Brampton ON L7A 1G2",
    "addr:housenumber":"20",
    "addr:postcode":"l7a 1g2",
    "addr:street":"Fisherman Dr",
    "iso:country":"CA",
    "sg:address":"20 Fisherman Dr",
    "sg:city":"Brampton",
    "sg:classifiers":[
        {
            "category":"Autos & Motor Vehicles",
            "subcategory":"Recreational Vehicle Sales",
            "type":"Retail Goods"
        }
    ],
    "sg:phone":"+1 905 846 8550",
    "sg:postcode":"L7A 1G2",
    "sg:province":"ON",
    "sg:tags":[
        "parts",
        "trailer"
    ],
    "wof:name":"General Axle Products Inc",
    "wof:placetype":"venue"
},
  "geometry": {"coordinates":[-79.801254,43.713688],"type":"Point"}
}