{
  "type": "Feature",
  "properties": {
    "addr:full":"842 Rang Rodrigue Woburn QC G0Y 1R0",
    "addr:housenumber":"842",
    "addr:postcode":"g0y 1r0",
    "addr:street":"Rang Rodrigue",
    "iso:country":"CA",
    "sg:address":"842 Rang Rodrigue",
    "sg:city":"Woburn",
    "sg:classifiers":[
        {
            "category":"Building & Trades",
            "subcategory":"Electrical",
            "type":"Services"
        }
    ],
    "sg:phone":"+1 819 544 2971",
    "sg:postcode":"G0Y 1R0",
    "sg:province":"QC",
    "sg:tags":[
        "electric",
        "contractor"
    ],
    "wof:name":"Bilodeau, Jean-Luc",
    "wof:placetype":"venue"
},
  "geometry": {"coordinates":[-70.863091,45.384514],"type":"Point"}
}