{
  "type": "Feature",
  "properties": {
    "iso:country":"CA",
    "sg:address":"645 Needham Lane",
    "sg:city":"Mississauga",
    "sg:classifiers":[
        {
            "category":"Manufacturing",
            "subcategory":"Apparel",
            "type":"Manufacturing & Wholesale Goods"
        }
    ],
    "sg:phone":"+1 905 272 0144",
    "sg:postcode":"L5A 1T9",
    "sg:province":"ON",
    "sg:tags":[
        "tarpaulin"
    ],
    "wof:name":"Hinspergers Poly Ind Ltd",
    "wof:placetype":"venue"
},
  "geometry": {"coordinates":[-79.59819030760001,43.5921821594],"type":"Point"}
}