{
  "type": "Feature",
  "properties": {
    "addr:full":"1053 Winnipeg St Regina SK S4R 1J3",
    "addr:housenumber":"1053",
    "addr:postcode":"s4r 1j3",
    "addr:street":"Winnipeg St",
    "iso:country":"CA",
    "sg:address":"1053 Winnipeg St",
    "sg:city":"Regina",
    "sg:classifiers":[
        {
            "category":"Professional",
            "subcategory":"Business Services",
            "type":"Services"
        }
    ],
    "sg:phone":"+1 306 522 5858",
    "sg:postcode":"S4R 1J3",
    "sg:province":"SK",
    "sg:tags":[
        "embroidery"
    ],
    "wof:name":"Embroidery Express",
    "wof:placetype":"venue"
},
  "geometry": {"coordinates":[-104.59502410899999,50.4621391296],"type":"Point"}
}