{
  "type": "Feature",
  "properties": {
    "addr:full":"63 Spring Garden Ave North York ON M2N 3G1",
    "addr:housenumber":"63",
    "addr:postcode":"m2n 3g1",
    "addr:street":"Spring Garden Ave",
    "iso:country":"CA",
    "sg:address":"63 Spring Garden Ave",
    "sg:city":"North York",
    "sg:classifiers":[
        {
            "category":"Food & Beverages",
            "subcategory":"Groceries & Convenience Stores",
            "type":"Retail Goods"
        }
    ],
    "sg:phone":"+1 416 226 5522",
    "sg:postcode":"M2N 3G1",
    "sg:province":"ON",
    "sg:tags":[
        "grocer"
    ],
    "wof:name":"Pat Spring Garden Market",
    "wof:placetype":"venue"
},
  "geometry": {"coordinates":[-79.409126,43.764706],"type":"Point"}
}