{
  "type": "Feature",
  "properties": {
    "addr:full":"377 5th St Pilot Butte SK S0G 3Z0",
    "addr:housenumber":"377",
    "addr:postcode":"s0g 3z0",
    "addr:street":"5Th St",
    "iso:country":"CA",
    "sg:address":"377 5th St",
    "sg:city":"Pilot Butte",
    "sg:classifiers":[
        {
            "category":"Building & Trades",
            "subcategory":"Construction",
            "type":"Services"
        }
    ],
    "sg:phone":"+1 306 781 4371",
    "sg:postcode":"S0G 3Z0",
    "sg:province":"SK",
    "sg:tags":[
        "concrete",
        "landscape",
        "contractor"
    ],
    "wof:name":"Kwik Kerb Pilot Butte",
    "wof:placetype":"venue"
},
  "geometry": {"coordinates":[-104.420227,50.486073],"type":"Point"}
}