{
  "type": "Feature",
  "properties": {
    "iso:country":"CA",
    "sg:address":"461 Rue Saint-Joseph",
    "sg:city":"Sainte-Julie",
    "sg:classifiers":[
        {
            "category":"Real Estate",
            "subcategory":"Surveying",
            "type":"Services"
        }
    ],
    "sg:phone":"+1 450 922 7793",
    "sg:postcode":"J3E 1W8",
    "sg:province":"QC",
    "sg:tags":[
        "surveyor"
    ],
    "wof:name":"Pineault, Marcel",
    "wof:placetype":"venue"
},
  "geometry": {"coordinates":[-73.33898162840001,45.59400177],"type":"Point"}
}