{
  "type": "Feature",
  "properties": {
    "addr:full":"7011 Elmbridge Way # 121 Richmond BC V7C 4V5",
    "addr:housenumber":"7011;121",
    "addr:postcode":"v7c 4v5",
    "addr:street":"Elmbridge Way #",
    "iso:country":"CA",
    "sg:address":"7011 Elmbridge Way # 121",
    "sg:city":"Richmond",
    "sg:classifiers":[
        {
            "category":"Shopping",
            "subcategory":"Clothing, Apparel, & Fashions",
            "type":"Retail Goods"
        }
    ],
    "sg:phone":"+1 604 278 4501",
    "sg:postcode":"V7C 4V5",
    "sg:province":"BC",
    "sg:tags":[
        "advertising"
    ],
    "wof:name":"Addictive Sportswear",
    "wof:placetype":"venue"
},
  "geometry": {"coordinates":[-123.147491,49.173019],"type":"Point"}
}