{
  "type": "Feature",
  "properties": {
    "addr:full":"3785 Lake Shore Blvd W Etobicoke ON M8W 1R1",
    "addr:housenumber":"3785",
    "addr:postcode":"m8w 1r1",
    "addr:street":"Lake Shore Blvd W",
    "iso:country":"CA",
    "sg:address":"3785 Lake Shore Blvd W",
    "sg:city":"Etobicoke",
    "sg:classifiers":[
        {
            "category":"Wholesale",
            "subcategory":"Meat",
            "type":"Manufacturing & Wholesale Goods"
        }
    ],
    "sg:phone":"+1 416 251 4321",
    "sg:postcode":"M8W 1R1",
    "sg:province":"ON",
    "sg:tags":[
        "butchering"
    ],
    "wof:name":"Long Branch Meat Market",
    "wof:placetype":"venue"
},
  "geometry": {"coordinates":[-79.541466,43.592533],"type":"Point"}
}