{
  "type": "Feature",
  "properties": {
    "addr:full":"2511 Rue Montarville Longueuil QC J4L 4C9",
    "addr:housenumber":"2511",
    "addr:postcode":"j4l 4c9",
    "addr:street":"Rue Montarville",
    "iso:country":"CA",
    "sg:address":"2511 Rue Montarville",
    "sg:city":"Longueuil",
    "sg:classifiers":[
        {
            "category":"Food & Beverages",
            "subcategory":"Groceries & Convenience Stores",
            "type":"Retail Goods"
        }
    ],
    "sg:phone":"+1 450 670 0680",
    "sg:postcode":"J4L 4C9",
    "sg:province":"QC",
    "wof:name":"Depanneur A Tout Prix",
    "wof:placetype":"venue"
},
  "geometry": {"coordinates":[-73.4718780518,45.5192375183],"type":"Point"}
}