{
  "type": "Feature",
  "properties": {
    "addr:full":"3429 Bathurst St North York ON M6A 2C3",
    "addr:housenumber":"3429",
    "addr:postcode":"m6a 2c3",
    "addr:street":"Bathurst St",
    "iso:country":"CA",
    "sg:address":"3429 Bathurst St",
    "sg:city":"North York",
    "sg:classifiers":[
        {
            "category":"Shopping",
            "type":"Retail Goods"
        }
    ],
    "sg:phone":"+1 416 782 8995",
    "sg:postcode":"M6A 2C3",
    "sg:province":"ON",
    "sg:tags":[
        "monument"
    ],
    "wof:name":"Yad Vashem Monuments",
    "wof:placetype":"venue"
},
  "geometry": {"coordinates":[-79.4315414429,43.7274856567],"type":"Point"}
}