{
  "type": "Feature",
  "properties": {
    "addr:full":"8311 153 St Surrey BC V3S 8M7",
    "addr:housenumber":"8311",
    "addr:postcode":"v3s 8m7",
    "addr:street":"153 St",
    "iso:country":"CA",
    "sg:address":"8311 153 St",
    "sg:city":"Surrey",
    "sg:classifiers":[
        {
            "category":"Building & Trades",
            "subcategory":"Construction",
            "type":"Services"
        }
    ],
    "sg:phone":"+1 604 572 3167",
    "sg:postcode":"V3S 8M7",
    "sg:province":"BC",
    "sg:tags":[
        "steel"
    ],
    "wof:name":"Jomidus Detailing Svc Ltd",
    "wof:placetype":"venue"
},
  "geometry": {"coordinates":[-122.798462,49.153748],"type":"Point"}
}