{
  "type": "Feature",
  "properties": {
    "addr:full":"31 Henry St Athens ON K0E 1B0",
    "addr:housenumber":"31",
    "addr:postcode":"k0e 1b0",
    "addr:street":"Henry St",
    "iso:country":"CA",
    "sg:address":"31 Henry St",
    "sg:city":"Athens",
    "sg:classifiers":[
        {
            "category":"Local Transit",
            "type":"Transportation"
        }
    ],
    "sg:phone":"+1 613 924 2720",
    "sg:postcode":"K0E 1B0",
    "sg:province":"ON",
    "sg:tags":[
        "bus",
        "limousine"
    ],
    "wof:name":"Howard Bus Svc Ltd",
    "wof:placetype":"venue"
},
  "geometry": {"coordinates":[-75.9533004761,44.6309242249],"type":"Point"}
}