{
  "type": "Feature",
  "properties": {
    "iso:country":"CA",
    "sg:address":"116 River Oaks Blvd E",
    "sg:city":"Oakville",
    "sg:classifiers":[
        {
            "category":"Professional",
            "subcategory":"Business Services",
            "type":"Services"
        }
    ],
    "sg:phone":"+1 905 338 1977",
    "sg:postcode":"L6H 4C5",
    "sg:province":"ON",
    "sg:tags":[
        "building",
        "inspection"
    ],
    "wof:name":"Home Buyers Guide",
    "wof:placetype":"venue"
},
  "geometry": {"coordinates":[-79.7140045166,43.4723815918],"type":"Point"}
}