{
  "type": "Feature",
  "properties": {
    "addr:full":"475 Av Perreault Sept-Iles QC G4R 1K6",
    "addr:housenumber":"475",
    "addr:postcode":"g4r 1k6",
    "addr:street":"Av Perreault Sept-Iles",
    "iso:country":"CA",
    "sg:address":"475 Av Perreault",
    "sg:city":"Sept-Iles",
    "sg:classifiers":[
        {
            "category":"Building & Trades",
            "subcategory":"Construction",
            "type":"Services"
        }
    ],
    "sg:phone":"+1 418 962 2499",
    "sg:postcode":"G4R 1K6",
    "sg:province":"QC",
    "sg:tags":[
        "general",
        "contractor"
    ],
    "wof:name":"Construction Leclerc",
    "wof:placetype":"venue"
},
  "geometry": {"coordinates":[-66.3705215454,50.2147140503],"type":"Point"}
}