{
  "type": "Feature",
  "properties": {
    "addr:full":"2928 18 St NE # 1 Calgary AB T2E 7B1",
    "addr:housenumber":"2928",
    "addr:postcode":"t2e 7b1",
    "addr:street":"18 St Ne # 1",
    "iso:country":"CA",
    "sg:address":"2928 18 St NE # 1",
    "sg:city":"Calgary",
    "sg:classifiers":[
        {
            "category":"Wholesale",
            "subcategory":"Groceries",
            "type":"Manufacturing & Wholesale Goods"
        }
    ],
    "sg:phone":"+1 403 735 1130",
    "sg:postcode":"T2E 7B1",
    "sg:province":"AB",
    "sg:tags":[
        "food",
        "product"
    ],
    "wof:name":"Esslinger Foods Ltd",
    "wof:placetype":"venue"
},
  "geometry": {"coordinates":[-114.014434815,51.0786170959],"type":"Point"}
}