{
  "type": "Feature",
  "properties": {
    "addr:full":"210 Paris St Sudbury ON P3E 3E2",
    "addr:housenumber":"210",
    "addr:postcode":"p3e 3e2",
    "addr:street":"Paris St",
    "iso:country":"CA",
    "sg:address":"210 Paris St",
    "sg:city":"Sudbury",
    "sg:classifiers":[
        {
            "category":"Organizations",
            "subcategory":"Religious Organization",
            "type":"Services"
        }
    ],
    "sg:phone":"+1 705 674 9404",
    "sg:postcode":"P3E 3E2",
    "sg:province":"ON",
    "sg:tags":[
        "church"
    ],
    "wof:name":"St Casimirs Church",
    "wof:placetype":"venue"
},
  "geometry": {"coordinates":[-80.988922,46.488663],"type":"Point"}
}