{
  "type": "Feature",
  "properties": {
    "addr:full":"1114 Rue Principale Saint-Agapit QC G0S 1Z0",
    "addr:housenumber":"1114",
    "addr:postcode":"g0s 1z0",
    "addr:street":"Rue Principale",
    "iso:country":"CA",
    "sg:address":"1114 Rue Principale",
    "sg:city":"Saint-Agapit",
    "sg:classifiers":[
        {
            "category":"Retail",
            "subcategory":"Funeral Services",
            "type":"Services"
        }
    ],
    "sg:phone":"+1 418 888 4351",
    "sg:postcode":"G0S 1Z0",
    "sg:province":"QC",
    "sg:tags":[
        "director"
    ],
    "wof:name":"Beaudoin Ferland Dupuis Ltee",
    "wof:placetype":"venue"
},
  "geometry": {"coordinates":[-71.4322433472,46.5626029968],"type":"Point"}
}