{
  "type": "Feature",
  "properties": {
    "addr:full":"2858 Agricola St Halifax NS B3K 4E6",
    "addr:housenumber":"2858",
    "addr:postcode":"b3k 4e6",
    "addr:street":"Agricola St",
    "iso:country":"CA",
    "sg:address":"2858 Agricola St",
    "sg:city":"Halifax",
    "sg:classifiers":[
        {
            "category":"Recreation",
            "type":"Entertainment"
        }
    ],
    "sg:phone":"+1 902 454 2244",
    "sg:postcode":"B3K 4E6",
    "sg:province":"NS",
    "sg:tags":[
        "tackle",
        "fishing",
        "guide"
    ],
    "wof:name":"Fishin Fever Tackle Shoppe",
    "wof:placetype":"venue"
},
  "geometry": {"coordinates":[-63.598499,44.658745],"type":"Point"}
}