{
  "type": "Feature",
  "properties": {
    "addr:full":"54 Erie St S Leamington ON N8H 3A9",
    "addr:housenumber":"54",
    "addr:postcode":"n8h 3a9",
    "addr:street":"Erie St S",
    "iso:country":"CA",
    "sg:address":"54 Erie St S",
    "sg:city":"Leamington",
    "sg:classifiers":[
        {
            "category":"Travel",
            "subcategory":"Travel Agent",
            "type":"Entertainment"
        }
    ],
    "sg:phone":"+1 519 326 2426",
    "sg:postcode":"N8H 3A9",
    "sg:province":"ON",
    "sg:tags":[
        "agency",
        "bureau"
    ],
    "wof:name":"Forno's Travel Agency Inc",
    "wof:placetype":"venue"
},
  "geometry": {"coordinates":[-82.5997390747,42.0517501831],"type":"Point"}
}