{
  "type": "Feature",
  "properties": {
    "addr:full":"2226 Inglewood Ave West Vancouver BC V7V 1Z8",
    "addr:housenumber":"2226",
    "addr:postcode":"v7v 1z8",
    "addr:street":"Inglewood Ave",
    "iso:country":"CA",
    "sg:address":"2226 Inglewood Ave",
    "sg:city":"West Vancouver",
    "sg:classifiers":[
        {
            "category":"Building & Trades",
            "subcategory":"Landscaping Services",
            "type":"Services"
        }
    ],
    "sg:phone":"+1 604 925 4587",
    "sg:postcode":"V7V 1Z8",
    "sg:province":"BC",
    "sg:tags":[
        "landscape",
        "contractor"
    ],
    "wof:name":"Heritage Stonework & Landscape",
    "wof:placetype":"venue"
},
  "geometry": {"coordinates":[-123.172089,49.334476],"type":"Point"}
}