{
  "type": "Feature",
  "properties": {
    "addr:full":"1648 Queen St W Toronto ON M6R 1B2",
    "addr:housenumber":"1648",
    "addr:postcode":"m6r 1b2",
    "addr:street":"Queen St W",
    "iso:country":"CA",
    "sg:address":"1648 Queen St W",
    "sg:city":"Toronto",
    "sg:classifiers":[
        {
            "category":"Professional",
            "subcategory":"Art Services",
            "type":"Services"
        }
    ],
    "sg:phone":"+1 416 588 3420",
    "sg:postcode":"M6R 1B2",
    "sg:province":"ON",
    "sg:tags":[
        "graphic",
        "designer"
    ],
    "wof:name":"Rene Zamic Boom",
    "wof:placetype":"venue"
},
  "geometry": {"coordinates":[-79.443192,43.639435],"type":"Point"}
}