{
  "type": "Feature",
  "properties": {
    "iso:country":"CA",
    "sg:address":"2107 17 Ave",
    "sg:city":"Wainwright",
    "sg:classifiers":[
        {
            "category":"Retail",
            "subcategory":"Auto Repair",
            "type":"Services"
        }
    ],
    "sg:phone":"+1 780 842 5711",
    "sg:postcode":"T9W 1L2",
    "sg:province":"AB",
    "sg:tags":[
        "truck"
    ],
    "wof:name":"J D Barber Equipment Ltd",
    "wof:placetype":"venue"
},
  "geometry": {"coordinates":[-110.84144592299999,52.8463821411],"type":"Point"}
}