{
  "type": "Feature",
  "properties": {
    "addr:full":"251 Bessborough Dr East York ON M4G 3K4",
    "addr:housenumber":"251",
    "addr:postcode":"m4g 3k4",
    "addr:street":"Bessborough Dr",
    "iso:country":"CA",
    "sg:address":"251 Bessborough Dr",
    "sg:city":"East York",
    "sg:classifiers":[
        {
            "category":"Freight",
            "type":"Transportation"
        }
    ],
    "sg:phone":"+1 416 757 7303",
    "sg:postcode":"M4G 3K4",
    "sg:province":"ON",
    "sg:tags":[
        "mover"
    ],
    "wof:name":"Prop Hoppers",
    "wof:placetype":"venue"
},
  "geometry": {"coordinates":[-79.370667,43.708969],"type":"Point"}
}