{
  "type": "Feature",
  "properties": {
    "addr:full":"400 Raymond Ave Bathurst NB E2A 2W4",
    "addr:housenumber":"400",
    "addr:postcode":"e2a 2w4",
    "addr:street":"Raymond Ave",
    "iso:country":"CA",
    "sg:address":"400 Raymond Ave",
    "sg:city":"Bathurst",
    "sg:classifiers":[
        {
            "category":"Building & Trades",
            "subcategory":"Construction",
            "type":"Services"
        }
    ],
    "sg:phone":"+1 506 548 3037",
    "sg:postcode":"E2A 2W4",
    "sg:province":"NB",
    "sg:tags":[
        "concrete",
        "contractor"
    ],
    "wof:name":"Marco Concrete Floors",
    "wof:placetype":"venue"
},
  "geometry": {"coordinates":[-65.67752075200001,47.6259498596],"type":"Point"}
}