{
  "type": "Feature",
  "properties": {
    "addr:full":"7105 Girard Rd NW Edmonton AB T6B 2C5",
    "addr:housenumber":"7105",
    "addr:postcode":"t6b 2c5",
    "addr:street":"Girard Rd Nw",
    "iso:country":"CA",
    "sg:address":"7105 Girard Rd NW",
    "sg:city":"Edmonton",
    "sg:classifiers":[
        {
            "category":"Wholesale",
            "subcategory":"Hardware",
            "type":"Manufacturing & Wholesale Goods"
        }
    ],
    "sg:phone":"+1 780 468 4068",
    "sg:postcode":"T6B 2C5",
    "sg:province":"AB",
    "sg:tags":[
        "fastener"
    ],
    "wof:name":"Westbrand Industries Ltd",
    "wof:placetype":"venue"
},
  "geometry": {"coordinates":[-113.4376297,53.5094070435],"type":"Point"}
}