{
  "type": "Feature",
  "properties": {
    "addr:full":"2564 Confederation Pky Mississauga ON L5B 1S2",
    "addr:housenumber":"2564",
    "addr:postcode":"l5b 1s2",
    "addr:street":"Confederation Pky",
    "iso:country":"CA",
    "sg:address":"2564 Confederation Pky",
    "sg:city":"Mississauga",
    "sg:classifiers":[
        {
            "category":"Professional",
            "subcategory":"Lawyer & Legal Services",
            "type":"Services"
        }
    ],
    "sg:phone":"+1 905 897 8611",
    "sg:postcode":"L5B 1S2",
    "sg:province":"ON",
    "sg:tags":[
        "attorney"
    ],
    "wof:name":"Law Office",
    "wof:placetype":"venue"
},
  "geometry": {"coordinates":[-79.6173706055,43.5760803223],"type":"Point"}
}