{
  "type": "Feature",
  "properties": {
    "iso:country":"CA",
    "sg:address":"2057 Boul Edouard",
    "sg:city":"Saint-Hubert",
    "sg:classifiers":[
        {
            "category":"Real Estate",
            "subcategory":"Real Estate Agent",
            "type":"Services"
        }
    ],
    "sg:phone":"+1 450 923 9300",
    "sg:postcode":"J4T 1Z9",
    "sg:province":"QC",
    "wof:name":"Societe Immobiliere Contact",
    "wof:placetype":"venue"
},
  "geometry": {"coordinates":[-73.479927,45.497036],"type":"Point"}
}