{
  "type": "Feature",
  "properties": {
    "addr:full":"2919 Boul Saint-Charles Kirkland QC H9H 3B5",
    "addr:housenumber":"2919",
    "addr:postcode":"h9h 3b5",
    "addr:street":"Boul Saint-Charles",
    "iso:country":"CA",
    "sg:address":"2919 Boul Saint-Charles",
    "sg:city":"Kirkland",
    "sg:classifiers":[
        {
            "category":"Restaurant",
            "type":"Food & Drink"
        }
    ],
    "sg:phone":"+1 514 630 6060",
    "sg:postcode":"H9H 3B5",
    "sg:province":"QC",
    "sg:tags":[
        "pizza"
    ],
    "wof:name":"Sgt Pepperoni Pizza",
    "wof:placetype":"venue"
},
  "geometry": {"coordinates":[-73.853561,45.44759],"type":"Point"}
}