{
  "type": "Feature",
  "properties": {
    "iso:country":"CA",
    "sg:address":"720 King St W",
    "sg:city":"Toronto",
    "sg:classifiers":[
        {
            "category":"Shopping",
            "subcategory":"Florist",
            "type":"Retail Goods"
        }
    ],
    "sg:phone":"+1 416 203 1258",
    "sg:postcode":"M5V 2T3",
    "sg:province":"ON",
    "wof:name":"King West Flowers",
    "wof:placetype":"venue"
},
  "geometry": {"coordinates":[-79.40381622309999,43.6438064575],"type":"Point"}
}