{
  "type": "Feature",
  "properties": {
    "addr:full":"4801 40 St Vermilion AB T9X 1H6",
    "addr:housenumber":"4801",
    "addr:postcode":"t9x 1h6",
    "addr:street":"40 St",
    "iso:country":"CA",
    "sg:address":"4801 40 St",
    "sg:city":"Vermilion",
    "sg:classifiers":[
        {
            "category":"Freight",
            "type":"Transportation"
        }
    ],
    "sg:phone":"+1 780 853 2734",
    "sg:postcode":"T9X 1H6",
    "sg:province":"AB",
    "sg:tags":[
        "trucking"
    ],
    "wof:name":"Southview Trucking Ltd",
    "wof:placetype":"venue"
},
  "geometry": {"coordinates":[-110.82827,53.350906],"type":"Point"}
}