{
  "type": "Feature",
  "properties": {
    "addr:full":"398 Montee Sainte-Victoire Sainte-Victoire-DE-Sorel QC J0G 1T0",
    "addr:housenumber":"398",
    "addr:postcode":"j0g 1t0",
    "addr:street":"Montee Sainte-Victoire",
    "iso:country":"CA",
    "sg:address":"398 Montee Sainte-Victoire",
    "sg:city":"Sainte-Victoire-DE-Sorel",
    "sg:classifiers":[
        {
            "category":"Building & Trades",
            "subcategory":"Construction",
            "type":"Services"
        }
    ],
    "sg:phone":"+1 450 782 2242",
    "sg:postcode":"J0G 1T0",
    "sg:province":"QC",
    "sg:tags":[
        "excavating",
        "contractor",
        "drainage"
    ],
    "wof:name":"Drainage Richelieu Inc",
    "wof:placetype":"venue"
},
  "geometry": {"coordinates":[-73.0787887573,45.9456634521],"type":"Point"}
}