{
  "type": "Feature",
  "properties": {
    "addr:full":"190 King George Rd Brantford ON N3R 5L3",
    "addr:housenumber":"190",
    "addr:postcode":"n3r 5l3",
    "addr:street":"King George Rd",
    "iso:country":"CA",
    "sg:address":"190 King George Rd",
    "sg:city":"Brantford",
    "sg:classifiers":[
        {
            "category":"Food & Beverages",
            "subcategory":"Specialty",
            "type":"Retail Goods"
        }
    ],
    "sg:phone":"+1 519 756 1607",
    "sg:postcode":"N3R 5L3",
    "sg:province":"ON",
    "sg:tags":[
        "health",
        "diet"
    ],
    "wof:name":"Herc's Muscle Shop Inc",
    "wof:placetype":"venue"
},
  "geometry": {"coordinates":[-80.27783203120001,43.1736297607],"type":"Point"}
}