{
  "type": "Feature",
  "properties": {
    "addr:full":"1185 Des Acadiens Havre-Saint-Pierre QC G0G 1P0",
    "addr:housenumber":"1185",
    "addr:postcode":"g0g 1p0",
    "addr:street":"Des Acadiens",
    "iso:country":"CA",
    "sg:address":"1185 Des Acadiens",
    "sg:city":"Havre-Saint-Pierre",
    "sg:classifiers":[
        {
            "category":"Building & Trades",
            "subcategory":"Electrical",
            "type":"Services"
        }
    ],
    "sg:phone":"+1 418 538 3336",
    "sg:postcode":"G0G 1P0",
    "sg:province":"QC",
    "sg:tags":[
        "electric",
        "contractor"
    ],
    "wof:name":"S G Electrique Enr",
    "wof:placetype":"venue"
},
  "geometry": {"coordinates":[-63.582413,50.250397],"type":"Point"}
}