{
  "type": "Feature",
  "properties": {
    "addr:full":"4275 Rue Frontenac Montreal QC H2H 2M4",
    "addr:housenumber":"4275",
    "addr:postcode":"rue;h2h 2m4",
    "addr:street":"Frontenac",
    "iso:country":"CA",
    "sg:address":"4275 Rue Frontenac",
    "sg:city":"Montreal",
    "sg:classifiers":[
        {
            "category":"Wholesale",
            "subcategory":"Home Furnishings",
            "type":"Manufacturing & Wholesale Goods"
        }
    ],
    "sg:phone":"+1 514 528 4333",
    "sg:postcode":"H2H 2M4",
    "sg:province":"QC",
    "sg:tags":[
        "venetian",
        "blind"
    ],
    "wof:name":"Sohji-CO Inc",
    "wof:placetype":"venue"
},
  "geometry": {"coordinates":[-73.564041,45.537994],"type":"Point"}
}