{
  "type": "Feature",
  "properties": {
    "addr:full":"4886 Rue Jarry E Saint-Leonard QC H1R 1X9",
    "addr:housenumber":"4886",
    "addr:postcode":"h1r 1x9",
    "addr:street":"Rue Jarry E",
    "iso:country":"CA",
    "sg:address":"4886 Rue Jarry E",
    "sg:city":"Saint-Leonard",
    "sg:classifiers":[
        {
            "category":"Health Services",
            "subcategory":"Doctor",
            "type":"Services"
        }
    ],
    "sg:phone":"+1 514 327 4440",
    "sg:postcode":"H1R 1X9",
    "sg:province":"QC",
    "sg:tags":[
        "clinic"
    ],
    "wof:name":"Clinique Medicale Chamilly",
    "wof:placetype":"venue"
},
  "geometry": {"coordinates":[-73.595634,45.579201],"type":"Point"}
}