{
  "type": "Feature",
  "properties": {
    "iso:country":"CA",
    "sg:address":"1164 Boul Lemay",
    "sg:city":"Thetford Mines",
    "sg:classifiers":[
        {
            "category":"Social Services",
            "subcategory":"Child Care",
            "type":"Services"
        }
    ],
    "sg:phone":"+1 418 334 0320",
    "sg:postcode":"G6G 8B7",
    "sg:province":"QC",
    "wof:name":"Cpe Le Champignon",
    "wof:placetype":"venue"
},
  "geometry": {"coordinates":[-71.32778167719999,46.0970497131],"type":"Point"}
}