{
  "type": "Feature",
  "properties": {
    "iso:country":"CA",
    "sg:address":"58 2nd Ave SW",
    "sg:city":"Chesley",
    "sg:classifiers":[
        {
            "category":"Organizations",
            "subcategory":"Religious Organization",
            "type":"Services"
        }
    ],
    "sg:phone":"+1 519 363 0858",
    "sg:postcode":"N0G 1L0",
    "sg:province":"ON",
    "sg:tags":[
        "church"
    ],
    "wof:name":"St Ann's Roman Catholic Church",
    "wof:placetype":"venue"
},
  "geometry": {"coordinates":[-81.0977554321,44.2985534668],"type":"Point"}
}