{
  "type": "Feature",
  "properties": {
    "addr:full":"3911 37 St SW Calgary AB T3E 6L6",
    "addr:housenumber":"3911",
    "addr:postcode":"t3e 6l6",
    "addr:street":"37 St Sw",
    "iso:country":"CA",
    "sg:address":"3911 37 St SW",
    "sg:city":"Calgary",
    "sg:classifiers":[
        {
            "category":"Shopping",
            "subcategory":"Gifts & Souvenirs",
            "type":"Retail Goods"
        }
    ],
    "sg:phone":"+1 403 249 6641",
    "sg:postcode":"T3E 6L6",
    "sg:province":"AB",
    "sg:tags":[
        "bingo",
        "balloon",
        "artist",
        "supply"
    ],
    "wof:name":"Canuck Amusements",
    "wof:placetype":"venue"
},
  "geometry": {"coordinates":[-114.141426086,51.0206222534],"type":"Point"}
}