{
  "type": "Feature",
  "properties": {
    "iso:country":"CA",
    "sg:address":"378 Heritage Dr",
    "sg:city":"Merrickville",
    "sg:classifiers":[
        {
            "category":"Home & Garden",
            "subcategory":"Building Materials",
            "type":"Retail Goods"
        }
    ],
    "sg:phone":"+1 613 269 3282",
    "sg:postcode":"K0G 1N0",
    "sg:province":"ON",
    "sg:tags":[
        "windows"
    ],
    "wof:name":"F M Industries",
    "wof:placetype":"venue"
},
  "geometry": {"coordinates":[-75.8361282349,44.9257392883],"type":"Point"}
}