{
  "type": "Feature",
  "properties": {
    "addr:full":"3491 Fairlight Dr Saskatoon SK S7M 3Z3",
    "addr:housenumber":"3491",
    "addr:postcode":"s7m 3z3",
    "addr:street":"Fairlight Dr",
    "iso:country":"CA",
    "sg:address":"3491 Fairlight Dr",
    "sg:city":"Saskatoon",
    "sg:classifiers":[
        {
            "category":"Home & Garden",
            "subcategory":"Building Materials",
            "type":"Retail Goods"
        }
    ],
    "sg:phone":"+1 306 978 9881",
    "sg:postcode":"S7M 3Z3",
    "sg:province":"SK",
    "sg:tags":[
        "door"
    ],
    "wof:name":"R & B Overhead Doors",
    "wof:placetype":"venue"
},
  "geometry": {"coordinates":[-106.732361,52.125805],"type":"Point"}
}