{
  "type": "Feature",
  "properties": {
    "addr:full":"PO Box 65557 Rpo Dundas Dundas ON L9H 6Y6",
    "addr:housenumber":"po box",
    "addr:postcode":"65557;l9h 6y6",
    "iso:country":"CA",
    "sg:address":"PO Box 65557 Rpo Dundas",
    "sg:city":"Dundas",
    "sg:classifiers":[
        {
            "category":"Building & Trades",
            "subcategory":"Landscaping Services",
            "type":"Services"
        }
    ],
    "sg:phone":"+1 905 628 3030",
    "sg:postcode":"L9H 6Y6",
    "sg:province":"ON",
    "sg:tags":[
        "lawn",
        "maintenance",
        "grounds"
    ],
    "wof:name":"Hired Hands Home Maintenance",
    "wof:placetype":"venue"
},
  "geometry": {"coordinates":[-79.952377,43.263779],"type":"Point"}
}