{
  "type": "Feature",
  "properties": {
    "addr:full":"616 Taku Rd Heriot Bay BC V0P 1H0",
    "addr:housenumber":"616",
    "addr:postcode":"v0p 1h0",
    "addr:street":"Taku Rd",
    "iso:country":"CA",
    "sg:address":"616 Taku Rd",
    "sg:city":"Heriot Bay",
    "sg:classifiers":[
        {
            "category":"Travel",
            "subcategory":"Campground",
            "type":"Entertainment"
        }
    ],
    "sg:phone":"+1 250 285 3031",
    "sg:postcode":"V0P 1H0",
    "sg:province":"BC",
    "sg:tags":[
        "resort"
    ],
    "wof:name":"Taku Resort",
    "wof:placetype":"venue"
},
  "geometry": {"coordinates":[-125.20143899999999,50.094368],"type":"Point"}
}