{
  "type": "Feature",
  "properties": {
    "addr:full":"301 South Railway Ave W Deloraine MB R0M 0M0",
    "addr:housenumber":"301",
    "addr:postcode":"r0m 0m0",
    "addr:street":"South Railway Ave W Deloraine",
    "iso:country":"CA",
    "sg:address":"301 South Railway Ave W",
    "sg:city":"Deloraine",
    "sg:classifiers":[
        {
            "category":"Utilities",
            "subcategory":"Cable",
            "type":"Services"
        }
    ],
    "sg:phone":"+1 204 747 2934",
    "sg:postcode":"R0M 0M0",
    "sg:province":"MB",
    "sg:tags":[
        "television"
    ],
    "wof:name":"Wcg Tb Deloraine",
    "wof:placetype":"venue"
},
  "geometry": {"coordinates":[-100.498886,49.192364],"type":"Point"}
}