{
  "type": "Feature",
  "properties": {
    "addr:full":"176 Larch St Sudbury ON P3E 1C5",
    "addr:housenumber":"176",
    "addr:postcode":"p3e 1c5",
    "addr:street":"Larch St",
    "iso:country":"CA",
    "sg:address":"176 Larch St",
    "sg:city":"Sudbury",
    "sg:classifiers":[
        {
            "category":"Professional",
            "subcategory":"Advertising",
            "type":"Services"
        }
    ],
    "sg:phone":"+1 705 673 7742",
    "sg:postcode":"P3E 1C5",
    "sg:province":"ON",
    "sg:tags":[
        "counselor"
    ],
    "wof:name":"Production Group",
    "wof:placetype":"venue"
},
  "geometry": {"coordinates":[-80.990326,46.491444],"type":"Point"}
}