{
  "type": "Feature",
  "properties": {
    "addr:full":"3 Rue Seigneuriale Victoriaville QC G6P 8J3",
    "addr:housenumber":"3",
    "addr:postcode":"g6p 8j3",
    "addr:street":"Rue Seigneuriale",
    "iso:country":"CA",
    "sg:address":"3 Rue Seigneuriale",
    "sg:city":"Victoriaville",
    "sg:classifiers":[
        {
            "category":"Personal",
            "type":"Services"
        }
    ],
    "sg:phone":"+1 819 758 8257",
    "sg:postcode":"G6P 8J3",
    "sg:province":"QC",
    "sg:tags":[
        "medicine",
        "orthopedic",
        "therapist",
        "massage"
    ],
    "wof:name":"Centre D'Orthotherapie E Cyr",
    "wof:placetype":"venue"
},
  "geometry": {"coordinates":[-72.015961,46.044773],"type":"Point"}
}