{
  "type": "Feature",
  "properties": {
    "iso:country":"CA",
    "sg:address":"8064 Huntington Rd NE",
    "sg:city":"Calgary",
    "sg:classifiers":[
        {
            "category":"Building & Trades",
            "subcategory":"Landscaping Services",
            "type":"Services"
        }
    ],
    "sg:phone":"+1 403 282 5252",
    "sg:postcode":"T2K 5A4",
    "sg:province":"AB",
    "sg:tags":[
        "lawn",
        "maintenance",
        "grounds"
    ],
    "wof:name":"Chinook Winds Lawns & Mntnce",
    "wof:placetype":"venue"
},
  "geometry": {"coordinates":[-114.05907440199999,51.1243934631],"type":"Point"}
}