{
  "type": "Feature",
  "properties": {
    "addr:full":"108 6th Ave Cochrane ON P0L 1C0",
    "addr:housenumber":"108",
    "addr:postcode":"p0l 1c0",
    "addr:street":"6Th Ave",
    "iso:country":"CA",
    "sg:address":"108 6th Ave",
    "sg:city":"Cochrane",
    "sg:classifiers":[
        {
            "category":"Shopping",
            "subcategory":"Clothing, Apparel, & Fashions",
            "type":"Retail Goods"
        }
    ],
    "sg:phone":"+1 705 272 6450",
    "sg:postcode":"P0L 1C0",
    "sg:province":"ON",
    "wof:name":"Caprice Fashion",
    "wof:placetype":"venue"
},
  "geometry": {"coordinates":[-81.028503,49.066654],"type":"Point"}
}