{
  "type": "Feature",
  "properties": {
    "addr:full":"6160 Lyons Creek Rd Niagara Falls ON L2E 6S6",
    "addr:housenumber":"6160",
    "addr:postcode":"l2e 6s6",
    "addr:street":"Lyons Creek Rd",
    "iso:country":"CA",
    "sg:address":"6160 Lyons Creek Rd",
    "sg:city":"Niagara Falls",
    "sg:classifiers":[
        {
            "category":"Building & Trades",
            "subcategory":"Plumbing",
            "type":"Services"
        }
    ],
    "sg:phone":"+1 905 295 6568",
    "sg:postcode":"L2E 6S6",
    "sg:province":"ON",
    "sg:tags":[
        "conditioning",
        "air",
        "system",
        "contractor"
    ],
    "wof:name":"Air Care Svc",
    "wof:placetype":"venue"
},
  "geometry": {"coordinates":[-79.095894,43.035633],"type":"Point"}
}