{
  "type": "Feature",
  "properties": {
    "addr:full":"191 Rue Principale S Marbleton QC J0B 2L0",
    "addr:housenumber":"191",
    "addr:postcode":"j0b 2l0",
    "addr:street":"Rue Principale S Marbleton",
    "iso:country":"CA",
    "sg:address":"191 Rue Principale S",
    "sg:city":"Marbleton",
    "sg:classifiers":[
        {
            "category":"Recreation",
            "type":"Entertainment"
        }
    ],
    "sg:phone":"+1 819 887 6058",
    "sg:postcode":"J0B 2L0",
    "sg:province":"QC",
    "sg:tags":[
        "center"
    ],
    "wof:name":"Centre Communautaire",
    "wof:placetype":"venue"
},
  "geometry": {"coordinates":[-71.59122499999999,45.633453],"type":"Point"}
}