{
  "type": "Feature",
  "properties": {
    "addr:full":"1800 Boul Le Corbusier # 134 Laval QC H7S 2K1",
    "addr:housenumber":"1800",
    "addr:postcode":"h7s 2k1",
    "addr:street":"Boul Le Corbusier # 134",
    "iso:country":"CA",
    "sg:address":"1800 Boul Le Corbusier # 134",
    "sg:city":"Laval",
    "sg:classifiers":[
        {
            "category":"Organizations",
            "subcategory":"Professional Association",
            "type":"Services"
        }
    ],
    "sg:phone":"+1 450 688 0541",
    "sg:postcode":"H7S 2K1",
    "sg:province":"QC",
    "wof:name":"Alpabem",
    "wof:placetype":"venue"
},
  "geometry": {"coordinates":[-73.735534668,45.5674667358],"type":"Point"}
}