{
  "type": "Feature",
  "properties": {
    "addr:full":"9615 Emerald Pl Whistler BC V0N 1B9",
    "addr:housenumber":"9615",
    "addr:postcode":"v0n 1b9",
    "addr:street":"Emerald Pl",
    "iso:country":"CA",
    "sg:address":"9615 Emerald Pl",
    "sg:city":"Whistler",
    "sg:classifiers":[
        {
            "category":"Travel",
            "subcategory":"Hotels & Motels",
            "type":"Entertainment"
        }
    ],
    "sg:phone":"+1 604 932 2166",
    "sg:postcode":"V0N 1B9",
    "sg:province":"BC",
    "sg:tags":[
        "resort",
        "skiing",
        "center",
        "trucking"
    ],
    "wof:name":"Backcountry Snowcats Ltd",
    "wof:placetype":"venue"
},
  "geometry": {"coordinates":[-122.934151,50.155029],"type":"Point"}
}