{
  "type": "Feature",
  "properties": {
    "iso:country":"CA",
    "sg:address":"9060 Rue DE LA Montagne",
    "sg:city":"Valcourt",
    "sg:classifiers":[
        {
            "category":"Autos & Motor Vehicles",
            "subcategory":"Boat Sales",
            "type":"Retail Goods"
        }
    ],
    "sg:phone":"+1 450 532 2262",
    "sg:postcode":"J0E 2L0",
    "sg:province":"QC",
    "sg:tags":[
        "all",
        "terrain",
        "dealer"
    ],
    "wof:name":"Centre DE LA Motoneige Enr",
    "wof:placetype":"venue"
},
  "geometry": {"coordinates":[-72.3040237427,45.4887542725],"type":"Point"}
}