{
  "type": "Feature",
  "properties": {
    "addr:full":"1746 Victoria St N Kitchener ON N2B 3E5",
    "addr:housenumber":"1746",
    "addr:postcode":"n2b 3e5",
    "addr:street":"Victoria St N",
    "iso:country":"CA",
    "sg:address":"1746 Victoria St N",
    "sg:city":"Kitchener",
    "sg:classifiers":[
        {
            "category":"Home & Garden",
            "subcategory":"Building Materials",
            "type":"Retail Goods"
        }
    ],
    "sg:phone":"+1 519 745 4745",
    "sg:postcode":"N2B 3E5",
    "sg:province":"ON",
    "sg:tags":[
        "type",
        "door"
    ],
    "wof:name":"A A Overhead Door CO",
    "wof:placetype":"venue"
},
  "geometry": {"coordinates":[-80.4304656982,43.4756851196],"type":"Point"}
}