{
  "type": "Feature",
  "properties": {
    "addr:full":"45 Kent St N Simcoe ON N3Y 3S1",
    "addr:housenumber":"45",
    "addr:postcode":"n3y 3s1",
    "addr:street":"Kent St N",
    "iso:country":"CA",
    "sg:address":"45 Kent St N",
    "sg:city":"Simcoe",
    "sg:classifiers":[
        {
            "category":"Education",
            "subcategory":"School",
            "type":"Public Place"
        }
    ],
    "sg:phone":"+1 519 428 6350",
    "sg:postcode":"N3Y 3S1",
    "sg:province":"ON",
    "wof:name":"Simcoe Driving School",
    "wof:placetype":"venue"
},
  "geometry": {"coordinates":[-80.3056335449,42.8378829956],"type":"Point"}
}