{
  "type": "Feature",
  "properties": {
    "iso:country":"CA",
    "sg:address":"13212 146 St NW",
    "sg:city":"Edmonton",
    "sg:classifiers":[
        {
            "category":"Professional",
            "type":"Services"
        }
    ],
    "sg:phone":"+1 780 454 0638",
    "sg:postcode":"T5L 4W8",
    "sg:province":"AB",
    "sg:tags":[
        "pipe",
        "equipment",
        "line"
    ],
    "wof:name":"A H Mc Elroy Sales & Svc Ltd",
    "wof:placetype":"venue"
},
  "geometry": {"coordinates":[-113.572029114,53.5918312073],"type":"Point"}
}