{
  "type": "Feature",
  "properties": {
    "iso:country":"CA",
    "sg:address":"787 Bank St",
    "sg:city":"Ottawa",
    "sg:classifiers":[
        {
            "category":"Shopping",
            "subcategory":"Clothing, Apparel, & Fashions",
            "type":"Retail Goods"
        }
    ],
    "sg:phone":"+1 613 232 3790",
    "sg:postcode":"K1S 3V5",
    "sg:province":"ON",
    "sg:tags":[
        "leather"
    ],
    "wof:name":"Roots Canada Ltd",
    "wof:placetype":"venue"
},
  "geometry": {"coordinates":[-75.68827056879999,45.4032516479],"type":"Point"}
}