{
  "type": "Feature",
  "properties": {
    "addr:full":"1 Rue Academy Lennoxville QC J1M 2A6",
    "addr:housenumber":"1",
    "addr:postcode":"j1m 2a6",
    "addr:street":"Rue Academy",
    "iso:country":"CA",
    "sg:address":"1 Rue Academy",
    "sg:city":"Lennoxville",
    "sg:classifiers":[
        {
            "category":"Social Services",
            "subcategory":"Child Care",
            "type":"Services"
        }
    ],
    "sg:phone":"+1 819 563 0108",
    "sg:postcode":"J1M 2A6",
    "sg:province":"QC",
    "sg:tags":[
        "school"
    ],
    "wof:name":"Place Des Enfants",
    "wof:placetype":"venue"
},
  "geometry": {"coordinates":[-71.85836,45.370529],"type":"Point"}
}