{
  "type": "Feature",
  "properties": {
    "addr:full":"17380 Boul Gouin O Pierrefonds QC H9J 1A3",
    "addr:housenumber":"17380",
    "addr:postcode":"h9j 1a3",
    "addr:street":"Boul Gouin O",
    "iso:country":"CA",
    "sg:address":"17380 Boul Gouin O",
    "sg:city":"Pierrefonds",
    "sg:classifiers":[
        {
            "category":"Building & Trades",
            "subcategory":"Plumbing",
            "type":"Services"
        }
    ],
    "sg:phone":"+1 514 696 4835",
    "sg:postcode":"H9J 1A3",
    "sg:province":"QC",
    "sg:tags":[
        "air",
        "conditioning",
        "contractor",
        "system",
        "heating"
    ],
    "wof:name":"Chauffage Daniel Theriault Inc",
    "wof:placetype":"venue"
},
  "geometry": {"coordinates":[-73.882187,45.468891],"type":"Point"}
}