{
  "type": "Feature",
  "properties": {
    "iso:country":"CA",
    "sg:address":"376 Powell St",
    "sg:city":"Vancouver",
    "sg:classifiers":[
        {
            "category":"Health Services",
            "subcategory":"Nursing And Care Facility",
            "type":"Services"
        }
    ],
    "sg:phone":"+1 604 681 4039",
    "sg:postcode":"V6A 1G4",
    "sg:province":"BC",
    "sg:tags":[
        "home",
        "retirement",
        "community"
    ],
    "wof:name":"Lookout Emergency Aid Society",
    "wof:placetype":"venue"
},
  "geometry": {"coordinates":[-123.095947,49.282993],"type":"Point"}
}