{
  "type": "Feature",
  "properties": {
    "addr:full":"235 Gage Ave Kitchener ON N2M 2C9",
    "addr:housenumber":"235",
    "addr:postcode":"n2m 2c9",
    "addr:street":"Gage Ave",
    "iso:country":"CA",
    "sg:address":"235 Gage Ave",
    "sg:city":"Kitchener",
    "sg:classifiers":[
        {
            "category":"Manufacturing",
            "subcategory":"Tools & Machinery",
            "type":"Manufacturing & Wholesale Goods"
        }
    ],
    "sg:phone":"+1 519 745 1002",
    "sg:postcode":"N2M 2C9",
    "sg:province":"ON",
    "sg:tags":[
        "die",
        "maker"
    ],
    "wof:name":"Ontario Die Intl Inc",
    "wof:placetype":"venue"
},
  "geometry": {"coordinates":[-80.515877,43.446911],"type":"Point"}
}