{
  "type": "Feature",
  "properties": {
    "iso:country":"CA",
    "sg:address":"2734 Kingsberry Cres",
    "sg:city":"Mississauga",
    "sg:classifiers":[
        {
            "category":"Building & Trades",
            "subcategory":"Construction",
            "type":"Services"
        }
    ],
    "sg:phone":"+1 416 823 3999",
    "sg:postcode":"L5B 2K9",
    "sg:province":"ON",
    "sg:tags":[
        "resurfacing",
        "laying",
        "refinishing",
        "floor"
    ],
    "wof:name":"Class Floor Inc",
    "wof:placetype":"venue"
},
  "geometry": {"coordinates":[-79.630295,43.565502],"type":"Point"}
}