{
  "type": "Feature",
  "properties": {
    "addr:full":"Westmount QC H3Z 1S8",
    "addr:postcode":"h3z 1s8",
    "iso:country":"CA",
    "sg:city":"Westmount",
    "sg:classifiers":[
        {
            "category":"Education",
            "subcategory":"Special Training",
            "type":"Public Place"
        }
    ],
    "sg:phone":"+1 514 932 0619",
    "sg:postcode":"H3Z 1S8",
    "sg:province":"QC",
    "sg:tags":[
        "management"
    ],
    "wof:name":"Mvm the Communications Group",
    "wof:placetype":"venue"
},
  "geometry": {"coordinates":[-73.597595,45.47802],"type":"Point"}
}