{
  "type": "Feature",
  "properties": {
    "addr:full":"919 Main St Kindersley SK S0L 1S0",
    "addr:housenumber":"919",
    "addr:postcode":"s0l 1s0",
    "addr:street":"Main St",
    "iso:country":"CA",
    "sg:address":"919 Main St",
    "sg:city":"Kindersley",
    "sg:classifiers":[
        {
            "category":"Manufacturing",
            "subcategory":"Printing",
            "type":"Manufacturing & Wholesale Goods"
        }
    ],
    "sg:phone":"+1 306 463 4611",
    "sg:postcode":"S0L 1S0",
    "sg:province":"SK",
    "sg:tags":[
        "newspaper"
    ],
    "wof:name":"Kindersley Clarion",
    "wof:placetype":"venue"
},
  "geometry": {"coordinates":[-109.161057,51.47216],"type":"Point"}
}