{
  "type": "Feature",
  "properties": {
    "iso:country":"CA",
    "sg:address":"300 King St",
    "sg:city":"London",
    "sg:classifiers":[
        {
            "category":"Travel",
            "subcategory":"Hotels & Motels",
            "type":"Entertainment"
        }
    ],
    "sg:phone":"+1 519 439 1661",
    "sg:postcode":"N6B 1S2",
    "sg:province":"ON",
    "wof:name":"Hilton London Ontario",
    "wof:placetype":"venue"
},
  "geometry": {"coordinates":[-81.24402618409999,42.9840431213],"type":"Point"}
}