{
  "type": "Feature",
  "properties": {
    "addr:full":"608 Rennie St Hamilton ON L8H 3P5",
    "addr:housenumber":"608",
    "addr:postcode":"l8h 3p5",
    "addr:street":"Rennie St",
    "iso:country":"CA",
    "sg:address":"608 Rennie St",
    "sg:city":"Hamilton",
    "sg:classifiers":[
        {
            "category":"Retail",
            "subcategory":"Laundry & Dry Cleaning",
            "type":"Services"
        }
    ],
    "sg:phone":"+1 905 549 8847",
    "sg:postcode":"L8H 3P5",
    "sg:province":"ON",
    "sg:tags":[
        "cleaners",
        "rug",
        "carpet"
    ],
    "wof:name":"Professional Carpet Svc Ltd",
    "wof:placetype":"venue"
},
  "geometry": {"coordinates":[-79.7787780762,43.2478218079],"type":"Point"}
}