{
  "type": "Feature",
  "properties": {
    "iso:country":"CA",
    "sg:address":"237 Sackville St",
    "sg:city":"Toronto",
    "sg:classifiers":[
        {
            "category":"Organizations",
            "subcategory":"Religious Organization",
            "type":"Services"
        }
    ],
    "sg:phone":"+1 416 368 2828",
    "sg:postcode":"M5A 3G1",
    "sg:province":"ON",
    "sg:tags":[
        "church"
    ],
    "wof:name":"Mac Edonian Bulgarian Orthodox",
    "wof:placetype":"venue"
},
  "geometry": {"coordinates":[-79.36319,43.661022],"type":"Point"}
}