{
  "type": "Feature",
  "properties": {
    "addr:full":"109 Rue Church Cowansville QC J2K 1T9",
    "addr:housenumber":"109",
    "addr:postcode":"j2k 1t9",
    "addr:street":"Rue Church",
    "iso:country":"CA",
    "sg:address":"109 Rue Church",
    "sg:city":"Cowansville",
    "sg:classifiers":[
        {
            "category":"Professional",
            "subcategory":"Accounting & Tax Preparation",
            "type":"Services"
        }
    ],
    "sg:phone":"+1 450 263 3252",
    "sg:postcode":"J2K 1T9",
    "sg:province":"QC",
    "sg:tags":[
        "accountant"
    ],
    "wof:name":"Bouchard, Pierre CA",
    "wof:placetype":"venue"
},
  "geometry": {"coordinates":[-72.74625399999999,45.203934],"type":"Point"}
}