{
  "type": "Feature",
  "properties": {
    "iso:country":"CA",
    "sg:address":"335 2nd Ave SE",
    "sg:city":"Owen Sound",
    "sg:classifiers":[
        {
            "category":"Building & Trades",
            "subcategory":"Construction",
            "type":"Services"
        }
    ],
    "sg:phone":"+1 519 371 4332",
    "sg:postcode":"N4K 5T2",
    "sg:province":"ON",
    "sg:tags":[
        "painter"
    ],
    "wof:name":"George Smithson Painting Ltd",
    "wof:placetype":"venue"
},
  "geometry": {"coordinates":[-80.94030761720001,44.555519104],"type":"Point"}
}