{
  "type": "Feature",
  "properties": {
    "iso:country":"CA",
    "sg:address":"48 Talbot St E",
    "sg:city":"Aylmer",
    "sg:classifiers":[
        {
            "category":"Shopping",
            "subcategory":"Department Store",
            "type":"Retail Goods"
        }
    ],
    "sg:phone":"+1 519 773 2477",
    "sg:postcode":"N5H 1H4",
    "sg:province":"ON",
    "sg:tags":[
        "shop"
    ],
    "wof:name":"Great Canadian Dollar Store",
    "wof:placetype":"venue"
},
  "geometry": {"coordinates":[-80.98212432859999,42.7728538513],"type":"Point"}
}