{
  "type": "Feature",
  "properties": {
    "addr:full":"241 High St London ON N6C 4K9",
    "addr:housenumber":"241",
    "addr:postcode":"n6c 4k9",
    "addr:street":"High St",
    "iso:country":"CA",
    "sg:address":"241 High St",
    "sg:city":"London",
    "sg:classifiers":[
        {
            "category":"Shopping",
            "subcategory":"Discount & Variety Stores",
            "type":"Retail Goods"
        }
    ],
    "sg:phone":"+1 519 439 6227",
    "sg:postcode":"N6C 4K9",
    "sg:province":"ON",
    "wof:name":"High Street Pinto",
    "wof:placetype":"venue"
},
  "geometry": {"coordinates":[-81.237121582,42.9643516541],"type":"Point"}
}