{
  "type": "Feature",
  "properties": {
    "iso:country":"CA",
    "sg:address":"74 St. Brendan St",
    "sg:city":"Sudbury",
    "sg:classifiers":[
        {
            "category":"Health Services",
            "subcategory":"Health Practitioner",
            "type":"Services"
        }
    ],
    "sg:phone":"+1 705 690 1312",
    "sg:postcode":"P3E 1K5",
    "sg:province":"ON",
    "sg:tags":[
        "holistic",
        "homeopath"
    ],
    "wof:name":"Gianni Vigna Homeopath",
    "wof:placetype":"venue"
},
  "geometry": {"coordinates":[-80.9938964844,46.4854049683],"type":"Point"}
}