{
  "type": "Feature",
  "properties": {
    "addr:full":"462 Rg DE LA Croix Saint-Bruno-DE-Kamouraska QC G0L 2M0",
    "addr:housenumber":"462",
    "addr:postcode":"g0l 2m0",
    "addr:street":"Rg De La Croix",
    "iso:country":"CA",
    "sg:address":"462 Rg DE LA Croix",
    "sg:city":"Saint-Bruno-DE-Kamouraska",
    "sg:classifiers":[
        {
            "category":"Recreation",
            "type":"Entertainment"
        }
    ],
    "sg:phone":"+1 418 492 7421",
    "sg:postcode":"G0L 2M0",
    "sg:province":"QC",
    "sg:tags":[
        "amusement"
    ],
    "wof:name":"Club Les Bells Pistes",
    "wof:placetype":"venue"
},
  "geometry": {"coordinates":[-69.86264799999999,47.563976],"type":"Point"}
}