{
  "type": "Feature",
  "properties": {
    "addr:full":"22446 Lougheed Hwy Maple Ridge BC V2X 2T6",
    "addr:housenumber":"22446",
    "addr:postcode":"v2x 2t6",
    "addr:street":"Lougheed Hwy",
    "iso:country":"CA",
    "sg:address":"22446 Lougheed Hwy",
    "sg:city":"Maple Ridge",
    "sg:classifiers":[
        {
            "category":"Shopping",
            "subcategory":"Bicycles & Sporting Goods",
            "type":"Retail Goods"
        }
    ],
    "sg:phone":"+1 604 467 6133",
    "sg:postcode":"V2X 2T6",
    "sg:province":"BC",
    "wof:name":"Bill's Skate Shop",
    "wof:placetype":"venue"
},
  "geometry": {"coordinates":[-122.600403,49.216885],"type":"Point"}
}