{
  "type": "Feature",
  "properties": {
    "addr:full":"Ottawa ON K1S 5J6",
    "addr:postcode":"k1s 5j6",
    "iso:country":"CA",
    "sg:city":"Ottawa",
    "sg:classifiers":[
        {
            "category":"Real Estate",
            "subcategory":"Real Estate Operator",
            "type":"Services"
        }
    ],
    "sg:phone":"+1 613 565 8000",
    "sg:postcode":"K1S 5J6",
    "sg:province":"ON",
    "sg:tags":[
        "apartment"
    ],
    "wof:name":"Riverview Apartments",
    "wof:placetype":"venue"
},
  "geometry": {"coordinates":[-75.671082,45.41552],"type":"Point"}
}