{
  "type": "Feature",
  "properties": {
    "addr:full":"1310 Franklin St North Bay ON P1B 2M3",
    "addr:housenumber":"1310",
    "addr:postcode":"p1b 2m3",
    "addr:street":"Franklin St",
    "iso:country":"CA",
    "sg:address":"1310 Franklin St",
    "sg:city":"North Bay",
    "sg:classifiers":[
        {
            "category":"Building & Trades",
            "subcategory":"Construction",
            "type":"Services"
        }
    ],
    "sg:phone":"+1 705 474 3730",
    "sg:postcode":"P1B 2M3",
    "sg:province":"ON",
    "sg:tags":[
        "general",
        "contractor"
    ],
    "wof:name":"Gap Construction CO Ltd",
    "wof:placetype":"venue"
},
  "geometry": {"coordinates":[-79.444946,46.309742],"type":"Point"}
}