{
  "type": "Feature",
  "properties": {
    "iso:country":"CA",
    "sg:city":"Calgary",
    "sg:classifiers":[
        {
            "category":"Professional",
            "subcategory":"Lawyer & Legal Services",
            "type":"Services"
        }
    ],
    "sg:phone":"+1 403 252 9937",
    "sg:postcode":"T2R 1J4",
    "sg:province":"AB",
    "sg:tags":[
        "attorney"
    ],
    "wof:name":"Hoffinger, Mark L",
    "wof:placetype":"venue"
},
  "geometry": {"coordinates":[-114.07155609100001,51.043056488],"type":"Point"}
}