{
  "type": "Feature",
  "properties": {
    "addr:full":"Saint-Marc-Des-Carrieres QC G0A 4B0",
    "addr:postcode":"g0a 4b0",
    "iso:country":"CA",
    "sg:city":"Saint-Marc-Des-Carrieres",
    "sg:classifiers":[
        {
            "category":"Insurance",
            "subcategory":"Insurance Agent",
            "type":"Services"
        }
    ],
    "sg:phone":"+1 418 268 3541",
    "sg:postcode":"G0A 4B0",
    "sg:province":"QC",
    "wof:name":"Promutuel LA Portneuvienne",
    "wof:placetype":"venue"
},
  "geometry": {"coordinates":[-72.0489578247,46.6810188293],"type":"Point"}
}