{
  "type": "Feature",
  "properties": {
    "addr:full":"573 Albion Rd Etobicoke ON M9V 1A1",
    "addr:housenumber":"573",
    "addr:postcode":"m9v 1a1",
    "addr:street":"Albion Rd",
    "iso:country":"CA",
    "sg:address":"573 Albion Rd",
    "sg:city":"Etobicoke",
    "sg:classifiers":[
        {
            "category":"Organizations",
            "subcategory":"Religious Organization",
            "type":"Services"
        }
    ],
    "sg:phone":"+1 416 742 6689",
    "sg:postcode":"M9V 1A1",
    "sg:province":"ON",
    "sg:tags":[
        "church"
    ],
    "wof:name":"New Life Christian Assembly",
    "wof:placetype":"venue"
},
  "geometry": {"coordinates":[-79.554359436,43.7302818298],"type":"Point"}
}