{
  "type": "Feature",
  "properties": {
    "iso:country":"CA",
    "sg:address":"222 Pellatt Ave",
    "sg:city":"North York",
    "sg:classifiers":[
        {
            "category":"Manufacturing",
            "subcategory":"Signs",
            "type":"Manufacturing & Wholesale Goods"
        }
    ],
    "sg:phone":"+1 416 243 9518",
    "sg:postcode":"M9N 2P6",
    "sg:province":"ON",
    "wof:name":"Chameleon Neon",
    "wof:placetype":"venue"
},
  "geometry": {"coordinates":[-79.5233383179,43.7139854431],"type":"Point"}
}