{
  "type": "Feature",
  "properties": {
    "addr:full":"2849 Dufferin St North York ON M6B 3S4",
    "addr:housenumber":"2849",
    "addr:postcode":"m6b 3s4",
    "addr:street":"Dufferin St",
    "iso:country":"CA",
    "sg:address":"2849 Dufferin St",
    "sg:city":"North York",
    "sg:classifiers":[
        {
            "category":"Personal",
            "subcategory":"Beauty Salon",
            "type":"Services"
        }
    ],
    "sg:phone":"+1 416 787 0994",
    "sg:postcode":"M6B 3S4",
    "sg:province":"ON",
    "wof:name":"Dynasty Hair Creation",
    "wof:placetype":"venue"
},
  "geometry": {"coordinates":[-79.452911,43.706638],"type":"Point"}
}