{
  "type": "Feature",
  "properties": {
    "addr:full":"Brougham ON L0H 1A0",
    "addr:postcode":"l0h 1a0",
    "iso:country":"CA",
    "sg:city":"Brougham",
    "sg:classifiers":[
        {
            "category":"Autos & Motor Vehicles",
            "subcategory":"Automobile Sales",
            "type":"Retail Goods"
        }
    ],
    "sg:phone":"+1 905 427 7393",
    "sg:postcode":"L0H 1A0",
    "sg:province":"ON",
    "sg:tags":[
        "car",
        "dealer"
    ],
    "wof:name":"Auto Barn Sales & Leasing Inc",
    "wof:placetype":"venue"
},
  "geometry": {"coordinates":[-79.1058731079,43.9187889099],"type":"Point"}
}