{
  "type": "Feature",
  "properties": {
    "addr:full":"475 Speedvale Ave E Guelph ON N1E 6J2",
    "addr:housenumber":"475",
    "addr:postcode":"n1e 6j2",
    "addr:street":"Speedvale Ave E",
    "iso:country":"CA",
    "sg:address":"475 Speedvale Ave E",
    "sg:city":"Guelph",
    "sg:classifiers":[
        {
            "category":"Autos & Motor Vehicles",
            "subcategory":"Fuel & Gas Station",
            "type":"Retail Goods"
        }
    ],
    "sg:phone":"+1 519 836 4064",
    "sg:postcode":"N1E 6J2",
    "sg:province":"ON",
    "sg:tags":[
        "oil"
    ],
    "wof:name":"Speedvale Sunoco Car Wash",
    "wof:placetype":"venue"
},
  "geometry": {"coordinates":[-80.25187699999999,43.570137],"type":"Point"}
}