{
  "type": "Feature",
  "properties": {
    "addr:full":"Saint-Just-DE-Bretenieres QC G0R 3H0",
    "addr:postcode":"g0r 3h0",
    "iso:country":"CA",
    "sg:city":"Saint-Just-DE-Bretenieres",
    "sg:classifiers":[
        {
            "category":"Personal",
            "subcategory":"Beauty Salon",
            "type":"Services"
        }
    ],
    "sg:phone":"+1 418 244 3644",
    "sg:postcode":"G0R 3H0",
    "sg:province":"QC",
    "wof:name":"Retro-Coiffure Enr",
    "wof:placetype":"venue"
},
  "geometry": {"coordinates":[-70.079819,46.576611],"type":"Point"}
}