{
  "type": "Feature",
  "properties": {
    "iso:country":"CA",
    "sg:address":"2230 Main St",
    "sg:city":"Winnipeg",
    "sg:classifiers":[
        {
            "category":"Government",
            "subcategory":"Office",
            "type":"Public Place"
        }
    ],
    "sg:phone":"+1 204 986 4816",
    "sg:postcode":"R2V 4T8",
    "sg:province":"MB",
    "sg:tags":[
        "village"
    ],
    "wof:name":"Winnipeg Industrial Waste Cntr",
    "wof:placetype":"venue"
},
  "geometry": {"coordinates":[-97.103325,49.952019],"type":"Point"}
}