{
  "type": "Feature",
  "properties": {
    "addr:full":"6705 Sumas Prairie Rd Chilliwack BC V2R 4K1",
    "addr:housenumber":"6705",
    "addr:postcode":"v2r 4k1",
    "addr:street":"Prairie Rd",
    "iso:country":"CA",
    "sg:address":"6705 Sumas Prairie Rd",
    "sg:city":"Chilliwack",
    "sg:classifiers":[
        {
            "category":"Personal",
            "type":"Services"
        }
    ],
    "sg:phone":"+1 604 823 4445",
    "sg:postcode":"V2R 4K1",
    "sg:province":"BC",
    "sg:tags":[
        "therapist",
        "massage"
    ],
    "wof:name":"Tennant, Loretta L",
    "wof:placetype":"venue"
},
  "geometry": {"coordinates":[-122.045723,49.124004],"type":"Point"}
}