{
  "type": "Feature",
  "properties": {
    "addr:full":"1181 Western Rd London ON N6G 1G6",
    "addr:housenumber":"1181",
    "addr:postcode":"n6g 1g6",
    "addr:street":"Western Rd",
    "iso:country":"CA",
    "sg:address":"1181 Western Rd",
    "sg:city":"London",
    "sg:classifiers":[
        {
            "category":"Restaurant",
            "type":"Food & Drink"
        }
    ],
    "sg:phone":"+1 519 438 2782",
    "sg:postcode":"N6G 1G6",
    "sg:province":"ON",
    "wof:name":"Subway Sandwiches & Salads",
    "wof:placetype":"venue"
},
  "geometry": {"coordinates":[-81.2766418457,43.0016174316],"type":"Point"}
}