{
  "type": "Feature",
  "properties": {
    "addr:full":"Sackville NB E4L 4A3",
    "addr:postcode":"e4l 4a3",
    "iso:country":"CA",
    "sg:city":"Sackville",
    "sg:classifiers":[
        {
            "category":"Health Services",
            "subcategory":"Doctor",
            "type":"Services"
        }
    ],
    "sg:phone":"+1 506 536 3111",
    "sg:postcode":"E4L 4A3",
    "sg:province":"NB",
    "sg:tags":[
        "physician",
        "surgeon"
    ],
    "wof:name":"Stewart, Graeme G R MD",
    "wof:placetype":"venue"
},
  "geometry": {"coordinates":[-64.3721160889,45.8914375305],"type":"Point"}
}