{
  "type": "Feature",
  "properties": {
    "iso:country":"CA",
    "sg:address":"1159 Rue Sainte-Anne",
    "sg:city":"Saint-Felicien",
    "sg:classifiers":[
        {
            "category":"Retail",
            "subcategory":"Funeral Services",
            "type":"Services"
        }
    ],
    "sg:phone":"+1 418 679 3334",
    "sg:postcode":"G8K 1Y5",
    "sg:province":"QC",
    "sg:tags":[
        "director"
    ],
    "wof:name":"Salon Funeraire Marc Leclerc",
    "wof:placetype":"venue"
},
  "geometry": {"coordinates":[-72.44128417970001,48.6472587585],"type":"Point"}
}