{
  "type": "Feature",
  "properties": {
    "addr:full":"25282 76 Ave Langley BC V4W 1V1",
    "addr:housenumber":"25282",
    "addr:postcode":"v4w 1v1",
    "addr:street":"76 Ave",
    "iso:country":"CA",
    "sg:address":"25282 76 Ave",
    "sg:city":"Langley",
    "sg:classifiers":[
        {
            "category":"Home & Garden",
            "subcategory":"Garden Supply",
            "type":"Retail Goods"
        }
    ],
    "sg:phone":"+1 604 856 0046",
    "sg:postcode":"V4W 1V1",
    "sg:province":"BC",
    "sg:tags":[
        "nurseryman"
    ],
    "wof:name":"Rhodo Ranch",
    "wof:placetype":"venue"
},
  "geometry": {"coordinates":[-122.523163,49.140335],"type":"Point"}
}