{
  "type": "Feature",
  "properties": {
    "addr:full":"50 65E Av Saint-Eustache QC J7P 3P8",
    "addr:housenumber":"50",
    "addr:postcode":"j7p 3p8",
    "addr:street":"65E Av Saint-Eustache",
    "iso:country":"CA",
    "sg:address":"50 65E Av",
    "sg:city":"Saint-Eustache",
    "sg:classifiers":[
        {
            "category":"Building & Trades",
            "subcategory":"Plumbing",
            "type":"Services"
        }
    ],
    "sg:phone":"+1 450 472 3800",
    "sg:postcode":"J7P 3P8",
    "sg:province":"QC",
    "sg:tags":[
        "contractor"
    ],
    "wof:name":"Plomberie Robert Morin Inc",
    "wof:placetype":"venue"
},
  "geometry": {"coordinates":[-73.888893,45.558041],"type":"Point"}
}