{
  "type": "Feature",
  "properties": {
    "addr:full":"Mississauga ON L4T 3Y8",
    "addr:postcode":"l4t 3y8",
    "iso:country":"CA",
    "sg:city":"Mississauga",
    "sg:classifiers":[
        {
            "category":"Airport",
            "type":"Transportation"
        }
    ],
    "sg:phone":"+1 905 673 0089",
    "sg:postcode":"L4T 3Y8",
    "sg:province":"ON",
    "sg:tags":[
        "aircraft",
        "maintenance"
    ],
    "wof:name":"Aero Structural Inc",
    "wof:placetype":"venue"
},
  "geometry": {"coordinates":[-79.66115570069999,43.7002258301],"type":"Point"}
}