{
  "type": "Feature",
  "properties": {
    "addr:full":"Etobicoke ON M9W 6A4",
    "addr:postcode":"m9w 6a4",
    "iso:country":"CA",
    "sg:city":"Etobicoke",
    "sg:classifiers":[
        {
            "category":"Wholesale",
            "subcategory":"Machinery & Supplies",
            "type":"Manufacturing & Wholesale Goods"
        }
    ],
    "sg:phone":"+1 416 675 2505",
    "sg:postcode":"M9W 6A4",
    "sg:province":"ON",
    "sg:tags":[
        "equipment",
        "hydraulic"
    ],
    "wof:name":"Hallite Seals Canada Ltd",
    "wof:placetype":"venue"
},
  "geometry": {"coordinates":[-79.585007,43.67894],"type":"Point"}
}