{
  "type": "Feature",
  "properties": {
    "addr:full":"414 Rue Belvedere S Sherbrooke QC J1H 4B5",
    "addr:housenumber":"414",
    "addr:postcode":"j1h 4b5",
    "addr:street":"Rue Belvedere S",
    "iso:country":"CA",
    "sg:address":"414 Rue Belvedere S",
    "sg:city":"Sherbrooke",
    "sg:classifiers":[
        {
            "category":"Shopping",
            "type":"Retail Goods"
        }
    ],
    "sg:phone":"+1 819 346 0666",
    "sg:postcode":"J1H 4B5",
    "sg:province":"QC",
    "sg:tags":[
        "pet",
        "shop"
    ],
    "wof:name":"Animalerie Pacha",
    "wof:placetype":"venue"
},
  "geometry": {"coordinates":[-71.89592,45.395699],"type":"Point"}
}