{
  "type": "Feature",
  "properties": {
    "addr:full":"Eckville AB T0M 0X0",
    "addr:postcode":"t0m 0x0",
    "iso:country":"CA",
    "sg:city":"Eckville",
    "sg:classifiers":[
        {
            "category":"Shopping",
            "subcategory":"Hobbies, Toys, & Games",
            "type":"Retail Goods"
        }
    ],
    "sg:phone":"+1 403 746 2785",
    "sg:postcode":"T0M 0X0",
    "sg:province":"AB",
    "sg:tags":[
        "equipment",
        "ceramic",
        "supply"
    ],
    "wof:name":"Doc Pots",
    "wof:placetype":"venue"
},
  "geometry": {"coordinates":[-114.361465,52.359573],"type":"Point"}
}