{
  "type": "Feature",
  "properties": {
    "iso:country":"CA",
    "sg:address":"505 Rue Collard O",
    "sg:city":"Alma",
    "sg:classifiers":[
        {
            "category":"Health Services",
            "subcategory":"Doctor",
            "type":"Services"
        }
    ],
    "sg:phone":"+1 418 668 7616",
    "sg:postcode":"G8B 1N1",
    "sg:province":"QC",
    "sg:tags":[
        "clinic"
    ],
    "wof:name":"Clinique DE Dermatologie",
    "wof:placetype":"venue"
},
  "geometry": {"coordinates":[-71.6496582031,48.5486373901],"type":"Point"}
}