{
  "type": "Feature",
  "properties": {
    "addr:full":"774 Goderich St Port Elgin ON N0H 2C3",
    "addr:housenumber":"774",
    "addr:postcode":"n0h 2c3",
    "addr:street":"Goderich St",
    "iso:country":"CA",
    "sg:address":"774 Goderich St",
    "sg:city":"Port Elgin",
    "sg:classifiers":[
        {
            "category":"Cinema",
            "subcategory":"Movie Theater",
            "type":"Entertainment"
        }
    ],
    "sg:phone":"+1 519 832 5822",
    "sg:postcode":"N0H 2C3",
    "sg:province":"ON",
    "wof:name":"Port Elgin Cinemas",
    "wof:placetype":"venue"
},
  "geometry": {"coordinates":[-81.386093,44.439976],"type":"Point"}
}