{
  "type": "Feature",
  "properties": {
    "addr:full":"7027 Rue Saint-Denis Montreal QC H2S 2S5",
    "addr:housenumber":"7027",
    "addr:postcode":"h2s 2s5",
    "addr:street":"Rue Saint-Denis",
    "iso:country":"CA",
    "sg:address":"7027 Rue Saint-Denis",
    "sg:city":"Montreal",
    "sg:classifiers":[
        {
            "category":"Personal",
            "subcategory":"Beauty Salon",
            "type":"Services"
        }
    ],
    "sg:phone":"+1 514 272 1873",
    "sg:postcode":"H2S 2S5",
    "sg:province":"QC",
    "wof:name":"Salon DE Coiffure Thanh",
    "wof:placetype":"venue"
},
  "geometry": {"coordinates":[-73.612938,45.537762],"type":"Point"}
}