{
  "type": "Feature",
  "properties": {
    "addr:full":"5525 Ch DE L'Aeroport Valcourt QC J0E 2L0",
    "addr:postcode":"5525;j0e 2l0",
    "addr:street":"Ch De L'Aeroport",
    "iso:country":"CA",
    "sg:address":"5525 Ch DE L'Aeroport",
    "sg:city":"Valcourt",
    "sg:classifiers":[
        {
            "category":"Restaurant",
            "type":"Food & Drink"
        }
    ],
    "sg:phone":"+1 450 532 4960",
    "sg:postcode":"J0E 2L0",
    "sg:province":"QC",
    "sg:tags":[
        "caterer"
    ],
    "wof:name":"Buffet Jacques",
    "wof:placetype":"venue"
},
  "geometry": {"coordinates":[-72.3921508789,45.027431488],"type":"Point"}
}