{
  "type": "Feature",
  "properties": {
    "addr:full":"119 7 Ave SE Drumheller AB T0J 0Y6",
    "addr:housenumber":"119",
    "addr:postcode":"t0j 0y6",
    "addr:street":"7 Ave Se",
    "iso:country":"CA",
    "sg:address":"119 7 Ave SE",
    "sg:city":"Drumheller",
    "sg:classifiers":[
        {
            "category":"Retail",
            "subcategory":"Auto Repair",
            "type":"Services"
        }
    ],
    "sg:phone":"+1 403 823 6916",
    "sg:postcode":"T0J 0Y6",
    "sg:province":"AB",
    "sg:tags":[
        "repairing",
        "automobile"
    ],
    "wof:name":"Honest Engine",
    "wof:placetype":"venue"
},
  "geometry": {"coordinates":[-112.70893100000001,51.457897],"type":"Point"}
}