{
  "type": "Feature",
  "properties": {
    "addr:full":"112 Marion St Winnipeg MB R2H 0T1",
    "addr:housenumber":"112",
    "addr:postcode":"r2h 0t1",
    "addr:street":"Marion St",
    "iso:country":"CA",
    "sg:address":"112 Marion St",
    "sg:city":"Winnipeg",
    "sg:classifiers":[
        {
            "category":"Travel",
            "subcategory":"Hotels & Motels",
            "type":"Entertainment"
        }
    ],
    "sg:phone":"+1 204 233 4475",
    "sg:postcode":"R2H 0T1",
    "sg:province":"MB",
    "wof:name":"Norwood Hotel",
    "wof:placetype":"venue"
},
  "geometry": {"coordinates":[-97.1238708496,49.8812713623],"type":"Point"}
}