{
  "type": "Feature",
  "properties": {
    "addr:full":"1591 Mcphee Ave Courtenay BC V9N 3A6",
    "addr:housenumber":"1591",
    "addr:postcode":"v9n 3a6",
    "addr:street":"Mcphee Ave",
    "iso:country":"CA",
    "sg:address":"1591 Mcphee Ave",
    "sg:city":"Courtenay",
    "sg:classifiers":[
        {
            "category":"Professional",
            "subcategory":"Computer Services",
            "type":"Services"
        }
    ],
    "sg:phone":"+1 250 334 0888",
    "sg:postcode":"V9N 3A6",
    "sg:province":"BC",
    "sg:tags":[
        "internet"
    ],
    "wof:name":"Shaw High Speed Internet",
    "wof:placetype":"venue"
},
  "geometry": {"coordinates":[-124.998382568,49.6811790466],"type":"Point"}
}