{
  "type": "Feature",
  "properties": {
    "addr:full":"100 Levis St Sudbury ON P3C 2H1",
    "addr:housenumber":"100",
    "addr:postcode":"p3c 2h1",
    "addr:street":"Levis St",
    "iso:country":"CA",
    "sg:address":"100 Levis St",
    "sg:city":"Sudbury",
    "sg:classifiers":[
        {
            "category":"Education",
            "subcategory":"School",
            "type":"Public Place"
        }
    ],
    "sg:phone":"+1 705 674 7484",
    "sg:postcode":"P3C 2H1",
    "sg:province":"ON",
    "wof:name":"College Notre Dame",
    "wof:placetype":"venue"
},
  "geometry": {"coordinates":[-80.9942245483,46.4984016418],"type":"Point"}
}