{
  "type": "Feature",
  "properties": {
    "addr:full":"2746 Blewett Rd Nelson BC V1L 6V4",
    "addr:housenumber":"2746",
    "addr:postcode":"bc v1l 6v4",
    "addr:street":"Blewett Rd",
    "iso:country":"CA",
    "sg:address":"2746 Blewett Rd",
    "sg:city":"Nelson",
    "sg:classifiers":[
        {
            "category":"Building & Trades",
            "subcategory":"Construction",
            "type":"Services"
        }
    ],
    "sg:phone":"+1 250 352 6529",
    "sg:postcode":"V1L 6V4",
    "sg:province":"BC",
    "sg:tags":[
        "roofing",
        "contractor"
    ],
    "wof:name":"Danco Roofing Ltd",
    "wof:placetype":"venue"
},
  "geometry": {"coordinates":[-117.288811,49.49754],"type":"Point"}
}