{
  "type": "Feature",
  "properties": {
    "iso:country":"CA",
    "sg:address":"749 33rd Ave W",
    "sg:city":"Vancouver",
    "sg:classifiers":[
        {
            "category":"Health Services",
            "subcategory":"Hospital",
            "type":"Services"
        }
    ],
    "sg:phone":"+1 604 876 7171",
    "sg:postcode":"V5Z 2K4",
    "sg:province":"BC",
    "sg:tags":[
        "laboratory"
    ],
    "wof:name":"St Vincent's Hospital Found",
    "wof:placetype":"venue"
},
  "geometry": {"coordinates":[-123.12200164799999,49.2413711548],"type":"Point"}
}