{
  "type": "Feature",
  "properties": {
    "addr:full":"50 Lorne St Smiths Falls ON K7A 3K7",
    "addr:housenumber":"50",
    "addr:postcode":"k7a 3k7",
    "addr:street":"Lorne St",
    "iso:country":"CA",
    "sg:address":"50 Lorne St",
    "sg:city":"Smiths Falls",
    "sg:classifiers":[
        {
            "category":"Personal",
            "subcategory":"Beauty Salon",
            "type":"Services"
        }
    ],
    "sg:phone":"+1 613 283 4277",
    "sg:postcode":"K7A 3K7",
    "sg:province":"ON",
    "sg:tags":[
        "manicuring"
    ],
    "wof:name":"Tammy's Nail Salon",
    "wof:placetype":"venue"
},
  "geometry": {"coordinates":[-76.0046615601,44.8985595703],"type":"Point"}
}