{
  "type": "Feature",
  "properties": {
    "addr:full":"Mississauga ON L4Z 2H7",
    "addr:postcode":"l4z 2h7",
    "iso:country":"CA",
    "sg:city":"Mississauga",
    "sg:classifiers":[
        {
            "category":"Shopping",
            "type":"Retail Goods"
        }
    ],
    "sg:phone":"+1 905 501 8240",
    "sg:postcode":"L4Z 2H7",
    "sg:province":"ON",
    "sg:tags":[
        "art",
        "gallery",
        "dealer"
    ],
    "wof:name":"Nunavut Development Corp",
    "wof:placetype":"venue"
},
  "geometry": {"coordinates":[-79.6709823608,43.6257400513],"type":"Point"}
}