{
  "type": "Feature",
  "properties": {
    "addr:full":"Calgary AB T2E 7J1",
    "addr:postcode":"t2e 7j1",
    "iso:country":"CA",
    "sg:city":"Calgary",
    "sg:classifiers":[
        {
            "category":"Organizations",
            "subcategory":"Professional Association",
            "type":"Services"
        }
    ],
    "sg:phone":"+1 403 291 9707",
    "sg:postcode":"T2E 7J1",
    "sg:province":"AB",
    "wof:name":"Alberta Allied Roofing Assn",
    "wof:placetype":"venue"
},
  "geometry": {"coordinates":[-114.02971649200001,51.0792312622],"type":"Point"}
}