{
  "type": "Feature",
  "properties": {
    "addr:full":"186 Du Lac Preissac QC J0Y 2E0",
    "addr:housenumber":"186",
    "addr:postcode":"j0y 2e0",
    "addr:street":"Du Lac",
    "iso:country":"CA",
    "sg:address":"186 Du Lac",
    "sg:city":"Preissac",
    "sg:classifiers":[
        {
            "category":"Government",
            "subcategory":"Office",
            "type":"Public Place"
        }
    ],
    "sg:phone":"+1 819 759 3360",
    "sg:postcode":"J0Y 2E0",
    "sg:province":"QC",
    "sg:tags":[
        "village"
    ],
    "wof:name":"Municipalite DE Preissac",
    "wof:placetype":"venue"
},
  "geometry": {"coordinates":[-78.448357,48.278275],"type":"Point"}
}