{
  "type": "Feature",
  "properties": {
    "addr:full":"4216 Waterworks Rd Petrolia ON N0N 1R0",
    "addr:housenumber":"4216",
    "addr:postcode":"n0n 1r0",
    "addr:street":"Waterworks Rd",
    "iso:country":"CA",
    "sg:address":"4216 Waterworks Rd",
    "sg:city":"Petrolia",
    "sg:classifiers":[
        {
            "category":"Retail",
            "subcategory":"Auto Repair",
            "type":"Services"
        }
    ],
    "sg:phone":"+1 519 882 9064",
    "sg:postcode":"N0N 1R0",
    "sg:province":"ON",
    "sg:tags":[
        "trailer"
    ],
    "wof:name":"Auto Truck Repair & Svc",
    "wof:placetype":"venue"
},
  "geometry": {"coordinates":[-82.1464004517,42.8814048767],"type":"Point"}
}