{
  "type": "Feature",
  "properties": {
    "addr:full":"80 Mcpherson St Markham ON L3R 3V6",
    "addr:housenumber":"80",
    "addr:postcode":"l3r 3v6",
    "addr:street":"Mcpherson St",
    "iso:country":"CA",
    "sg:address":"80 Mcpherson St",
    "sg:city":"Markham",
    "sg:classifiers":[
        {
            "category":"Wholesale",
            "subcategory":"Durable Goods & Equipment",
            "type":"Manufacturing & Wholesale Goods"
        }
    ],
    "sg:phone":"+1 905 475 8232",
    "sg:postcode":"L3R 3V6",
    "sg:province":"ON",
    "sg:tags":[
        "laboratory",
        "supply"
    ],
    "wof:name":"Esbe Scientific Research",
    "wof:placetype":"venue"
},
  "geometry": {"coordinates":[-79.33172607420001,43.8324813843],"type":"Point"}
}