{
  "type": "Feature",
  "properties": {
    "addr:full":"Greenfield Park QC J4V 1M1",
    "addr:postcode":"j4v 1m1",
    "addr:street":"Park",
    "iso:country":"CA",
    "sg:city":"Greenfield Park",
    "sg:classifiers":[
        {
            "category":"Restaurant",
            "type":"Food & Drink"
        }
    ],
    "sg:phone":"+1 450 466 4948",
    "sg:postcode":"J4V 1M1",
    "sg:province":"QC",
    "wof:name":"Subway Sandwiches & Salades",
    "wof:placetype":"venue"
},
  "geometry": {"coordinates":[-73.49188995359999,45.4894104004],"type":"Point"}
}