{
  "type": "Feature",
  "properties": {
    "addr:full":"464 Yonge St Toronto ON M4Y 1W9",
    "addr:housenumber":"464",
    "addr:postcode":"m4y 1w9",
    "addr:street":"Yonge St",
    "iso:country":"CA",
    "sg:address":"464 Yonge St",
    "sg:city":"Toronto",
    "sg:classifiers":[
        {
            "category":"Banks & Credit Unions",
            "subcategory":"Financial Services",
            "type":"Services"
        }
    ],
    "sg:phone":"+1 416 699 8722",
    "sg:postcode":"M4Y 1W9",
    "sg:province":"ON",
    "sg:tags":[
        "program",
        "scholarship"
    ],
    "wof:name":"Usc Consutlants",
    "wof:placetype":"venue"
},
  "geometry": {"coordinates":[-79.383461,43.661804],"type":"Point"}
}