{
  "type": "Feature",
  "properties": {
    "iso:country":"CA",
    "sg:city":"Port Moody",
    "sg:classifiers":[
        {
            "category":"Personal",
            "subcategory":"Beauty Salon",
            "type":"Services"
        }
    ],
    "sg:phone":"+1 604 461 7227",
    "sg:postcode":"V3H 5E3",
    "sg:province":"BC",
    "wof:name":"Passion Hair Salon",
    "wof:placetype":"venue"
},
  "geometry": {"coordinates":[-122.839073181,49.2767677307],"type":"Point"}
}