{
  "type": "Feature",
  "properties": {
    "iso:country":"CA",
    "sg:city":"Sainte-Foy",
    "sg:classifiers":[
        {
            "category":"Wholesale",
            "subcategory":"Groceries",
            "type":"Manufacturing & Wholesale Goods"
        }
    ],
    "sg:phone":"+1 418 651 6117",
    "sg:postcode":"G1X 4A6",
    "sg:province":"QC",
    "sg:tags":[
        "food",
        "natural"
    ],
    "wof:name":"Aliments Fontaine Sante Inc",
    "wof:placetype":"venue"
},
  "geometry": {"coordinates":[-71.325989,46.783779],"type":"Point"}
}