{
  "type": "Feature",
  "properties": {
    "addr:full":"Chibougamau QC G8P 2K6",
    "addr:postcode":"g8p 2k6",
    "iso:country":"CA",
    "sg:city":"Chibougamau",
    "sg:classifiers":[
        {
            "category":"Freight",
            "type":"Transportation"
        }
    ],
    "sg:phone":"+1 418 748 8120",
    "sg:postcode":"G8P 2K6",
    "sg:province":"QC",
    "sg:tags":[
        "trucking"
    ],
    "wof:name":"Equipements Crd",
    "wof:placetype":"venue"
},
  "geometry": {"coordinates":[-74.357727,49.91864],"type":"Point"}
}