{
  "type": "Feature",
  "properties": {
    "iso:country":"CA",
    "sg:address":"1780 St Clair Ave W",
    "sg:city":"Toronto",
    "sg:classifiers":[
        {
            "category":"Organizations",
            "subcategory":"Religious Organization",
            "type":"Services"
        }
    ],
    "sg:phone":"+1 416 656 1670",
    "sg:postcode":"M6N 1J5",
    "sg:province":"ON",
    "wof:name":"College St Church of God",
    "wof:placetype":"venue"
},
  "geometry": {"coordinates":[-79.4616851807,43.6739273071],"type":"Point"}
}