{
  "type": "Feature",
  "properties": {
    "addr:full":"569 Av Brochu Sept-Iles QC G4R 2X4",
    "addr:postcode":"g4r 2x4",
    "addr:street":"569 Av Brochu Sept-Iles",
    "iso:country":"CA",
    "sg:address":"569 Av Brochu",
    "sg:city":"Sept-Iles",
    "sg:classifiers":[
        {
            "category":"Organizations",
            "subcategory":"Religious Organization",
            "type":"Services"
        }
    ],
    "sg:phone":"+1 418 968 5057",
    "sg:postcode":"G4R 2X4",
    "sg:province":"QC",
    "sg:tags":[
        "church"
    ],
    "wof:name":"Centre Chretien Des Sept-Iles",
    "wof:placetype":"venue"
},
  "geometry": {"coordinates":[-66.38883209230001,50.2088890076],"type":"Point"}
}