{
  "type": "Feature",
  "properties": {
    "addr:full":"12930 156 St NW Edmonton AB T5V 1E9",
    "addr:housenumber":"12930",
    "addr:postcode":"t5v 1e9",
    "addr:street":"156 St Nw",
    "iso:country":"CA",
    "sg:address":"12930 156 St NW",
    "sg:city":"Edmonton",
    "sg:classifiers":[
        {
            "category":"Retail",
            "subcategory":"Auto Repair",
            "type":"Services"
        }
    ],
    "sg:phone":"+1 780 496 9326",
    "sg:postcode":"T5V 1E9",
    "sg:province":"AB",
    "sg:tags":[
        "body",
        "automobile",
        "painting",
        "shop"
    ],
    "wof:name":"Lee Jay Auto Body Ltd",
    "wof:placetype":"venue"
},
  "geometry": {"coordinates":[-113.590378,53.588589],"type":"Point"}
}