{
  "type": "Feature",
  "properties": {
    "iso:country":"CA",
    "sg:address":"88 Rue Lantier",
    "sg:city":"Loretteville",
    "sg:classifiers":[
        {
            "category":"Building & Trades",
            "subcategory":"Electrical",
            "type":"Services"
        }
    ],
    "sg:phone":"+1 418 842 9027",
    "sg:postcode":"G2B 4X2",
    "sg:province":"QC",
    "sg:tags":[
        "electric",
        "contractor"
    ],
    "wof:name":"Electricite Serge Lapointe",
    "wof:placetype":"venue"
},
  "geometry": {"coordinates":[-71.3512802124,46.8459777832],"type":"Point"}
}