{
  "type": "Feature",
  "properties": {
    "addr:full":"60 Rue Elizabeth Sorel-Tracy QC J3P 4G5",
    "addr:housenumber":"60",
    "addr:postcode":"j3p 4g5",
    "addr:street":"Rue Elizabeth",
    "iso:country":"CA",
    "sg:address":"60 Rue Elizabeth",
    "sg:city":"Sorel-Tracy",
    "sg:classifiers":[
        {
            "category":"Government",
            "subcategory":"Office",
            "type":"Public Place"
        }
    ],
    "sg:phone":"+1 450 743 0051",
    "sg:postcode":"J3P 4G5",
    "sg:province":"QC",
    "wof:name":"Canada Developpement-Ressourc",
    "wof:placetype":"venue"
},
  "geometry": {"coordinates":[-73.112892,46.044773],"type":"Point"}
}