{
  "type": "Feature",
  "properties": {
    "addr:full":"430 Rue Du Boise Deux-Montagnes QC J7R 7G4",
    "addr:housenumber":"430",
    "addr:postcode":"j7r 7g4",
    "addr:street":"Rue Du Boise",
    "iso:country":"CA",
    "sg:address":"430 Rue Du Boise",
    "sg:city":"Deux-Montagnes",
    "sg:classifiers":[
        {
            "category":"Manufacturing",
            "subcategory":"Tools & Machinery",
            "type":"Manufacturing & Wholesale Goods"
        }
    ],
    "sg:phone":"+1 450 974 1531",
    "sg:postcode":"J7R 7G4",
    "sg:province":"QC",
    "sg:tags":[
        "water",
        "equipment",
        "works",
        "supply"
    ],
    "wof:name":"Paysagiste Eco-Verdure",
    "wof:placetype":"venue"
},
  "geometry": {"coordinates":[-73.908371,45.542904],"type":"Point"}
}