{
  "type": "Feature",
  "properties": {
    "addr:full":"314 Ch St Dominique Saint-Pie QC J0H 1W0",
    "addr:housenumber":"314",
    "addr:postcode":"j0h 1w0",
    "addr:street":"Ch St Dominique",
    "iso:country":"CA",
    "sg:address":"314 Ch St Dominique",
    "sg:city":"Saint-Pie",
    "sg:classifiers":[
        {
            "category":"Building & Trades",
            "subcategory":"Pest Control",
            "type":"Services"
        }
    ],
    "sg:phone":"+1 450 772 6402",
    "sg:postcode":"J0H 1W0",
    "sg:province":"QC",
    "wof:name":"Marquette Extermination",
    "wof:placetype":"venue"
},
  "geometry": {"coordinates":[-72.88552900000001,45.525555],"type":"Point"}
}