{
  "type": "Feature",
  "properties": {
    "addr:full":"851 Willow St Truro NS B2N 6N8",
    "addr:housenumber":"851",
    "addr:postcode":"b2n 6n8",
    "addr:street":"Willow St",
    "iso:country":"CA",
    "sg:address":"851 Willow St",
    "sg:city":"Truro",
    "sg:classifiers":[
        {
            "category":"Social Services",
            "subcategory":"Child Care",
            "type":"Services"
        }
    ],
    "sg:phone":"+1 902 897 1249",
    "sg:postcode":"B2N 6N8",
    "sg:province":"NS",
    "wof:name":"Millbrook Mikmaq Day Care",
    "wof:placetype":"venue"
},
  "geometry": {"coordinates":[-63.293167,45.33567],"type":"Point"}
}