{
  "type": "Feature",
  "properties": {
    "addr:full":"Vancouver BC V6E 1C6",
    "addr:postcode":"v6e 1c6",
    "iso:country":"CA",
    "sg:city":"Vancouver",
    "sg:classifiers":[
        {
            "category":"Restaurant",
            "type":"Food & Drink"
        }
    ],
    "sg:phone":"+1 604 685 8606",
    "sg:postcode":"V6E 1C6",
    "sg:province":"BC",
    "wof:name":"Ezogiku Noodle Cafe",
    "wof:placetype":"venue"
},
  "geometry": {"coordinates":[-123.12886,49.28743],"type":"Point"}
}