{
  "type": "Feature",
  "properties": {
    "iso:country":"CA",
    "sg:address":"613 Place Des Erables",
    "sg:city":"Rouyn-Noranda",
    "sg:classifiers":[
        {
            "category":"Insurance",
            "subcategory":"Insurance Agent",
            "type":"Services"
        }
    ],
    "sg:phone":"+1 819 762 8555",
    "sg:postcode":"J9X 5P9",
    "sg:province":"QC",
    "wof:name":"Cloutier Yvan Axa Assurances",
    "wof:placetype":"venue"
},
  "geometry": {"coordinates":[-79.029144,48.223717],"type":"Point"}
}