{
  "type": "Feature",
  "properties": {
    "addr:full":"200 Hastings St N # A Bancroft ON K0L 1C0",
    "addr:housenumber":"200",
    "addr:postcode":"k0l 1c0",
    "addr:street":"Hastings St N # A",
    "iso:country":"CA",
    "sg:address":"200 Hastings St N # A",
    "sg:city":"Bancroft",
    "sg:classifiers":[
        {
            "category":"Food & Beverages",
            "subcategory":"Specialty",
            "type":"Retail Goods"
        }
    ],
    "sg:phone":"+1 613 332 6803",
    "sg:postcode":"K0L 1C0",
    "sg:province":"ON",
    "sg:tags":[
        "health",
        "diet"
    ],
    "wof:name":"Eagles Nest Nutrition Ctr",
    "wof:placetype":"venue"
},
  "geometry": {"coordinates":[-77.8619308472,45.0679359436],"type":"Point"}
}