{
  "type": "Feature",
  "properties": {
    "addr:full":"729 Aldous Rd Richmond PE C0B 1Y0",
    "addr:housenumber":"729",
    "addr:postcode":"c0b 1y0",
    "addr:street":"Aldous Rd",
    "iso:country":"CA",
    "sg:address":"729 Aldous Rd",
    "sg:city":"Richmond",
    "sg:classifiers":[
        {
            "category":"Retail",
            "subcategory":"Auto Repair",
            "type":"Services"
        }
    ],
    "sg:phone":"+1 902 854 3333",
    "sg:postcode":"C0B 1Y0",
    "sg:province":"PE",
    "sg:tags":[
        "automobile",
        "parts",
        "wrecker"
    ],
    "wof:name":"North American Auto Wreckers",
    "wof:placetype":"venue"
},
  "geometry": {"coordinates":[-63.9925956726,46.5075798035],"type":"Point"}
}