{
  "type": "Feature",
  "properties": {
    "addr:full":"1486 Oakland Rd Mahone Bay NS B0J 2E0",
    "addr:housenumber":"1486",
    "addr:postcode":"b0j 2e0",
    "addr:street":"Oakland Rd",
    "iso:country":"CA",
    "sg:address":"1486 Oakland Rd",
    "sg:city":"Mahone Bay",
    "sg:classifiers":[
        {
            "category":"Wholesale",
            "subcategory":"Electrical",
            "type":"Manufacturing & Wholesale Goods"
        }
    ],
    "sg:phone":"+1 902 624 1439",
    "sg:postcode":"B0J 2E0",
    "sg:province":"NS",
    "sg:tags":[
        "medical",
        "burglar",
        "alarm",
        "system"
    ],
    "wof:name":"South Shore Medic Aid",
    "wof:placetype":"venue"
},
  "geometry": {"coordinates":[-64.381012,44.448647],"type":"Point"}
}