{
  "type": "Feature",
  "properties": {
    "addr:full":"PO Box 12 Sandy Lake ON P0V 1V0",
    "addr:housenumber":"po box 12",
    "addr:postcode":"p0v 1v0",
    "iso:country":"CA",
    "sg:address":"PO Box 12",
    "sg:city":"Sandy Lake",
    "sg:classifiers":[
        {
            "category":"Organizations",
            "subcategory":"Professional Association",
            "type":"Services"
        }
    ],
    "sg:phone":"+1 807 774 3421",
    "sg:postcode":"P0V 1V0",
    "sg:province":"ON",
    "sg:tags":[
        "government"
    ],
    "wof:name":"Sandy Lake Band Council",
    "wof:placetype":"venue"
},
  "geometry": {"coordinates":[-93.33332799999999,53.05022],"type":"Point"}
}