{
  "type": "Feature",
  "properties": {
    "iso:country":"CA",
    "sg:address":"7185 Market St",
    "sg:city":"Port Hardy",
    "sg:classifiers":[
        {
            "category":"Professional",
            "subcategory":"Accounting & Tax Preparation",
            "type":"Services"
        }
    ],
    "sg:phone":"+1 250 949 6350",
    "sg:postcode":"V0N 2P0",
    "sg:province":"BC",
    "sg:tags":[
        "accountant"
    ],
    "wof:name":"Paterson, Irene M",
    "wof:placetype":"venue"
},
  "geometry": {"coordinates":[-127.492111206,50.7221755981],"type":"Point"}
}