{
  "type": "Feature",
  "properties": {
    "iso:country":"CA",
    "sg:address":"7000 Lantzville School Rd",
    "sg:city":"Lantzville",
    "sg:classifiers":[
        {
            "category":"Education",
            "subcategory":"School",
            "type":"Public Place"
        }
    ],
    "sg:phone":"+1 250 390 4022",
    "sg:postcode":"V0R 2H0",
    "sg:province":"BC",
    "wof:name":"Seaview School",
    "wof:placetype":"venue"
},
  "geometry": {"coordinates":[-124.07764434800001,49.2508354187],"type":"Point"}
}