{
  "type": "Feature",
  "properties": {
    "addr:full":"Calgary AB T2P 0N7",
    "addr:postcode":"t2p 0n7",
    "iso:country":"CA",
    "sg:city":"Calgary",
    "sg:classifiers":[
        {
            "category":"Banks & Credit Unions",
            "subcategory":"Investment Brokerage",
            "type":"Services"
        }
    ],
    "sg:phone":"+1 403 777 4740",
    "sg:postcode":"T2P 0N7",
    "sg:province":"AB",
    "sg:tags":[
        "home",
        "planning",
        "community",
        "retirement"
    ],
    "wof:name":"Ulevog Financial Corp",
    "wof:placetype":"venue"
},
  "geometry": {"coordinates":[-114.08181,51.049061],"type":"Point"}
}