{
  "type": "Feature",
  "properties": {
    "iso:country":"CA",
    "sg:address":"118 3rd St W",
    "sg:city":"Marsden",
    "sg:classifiers":[
        {
            "category":"Education",
            "subcategory":"School",
            "type":"Public Place"
        }
    ],
    "sg:phone":"+1 306 826 5255",
    "sg:postcode":"S0M 1P0",
    "sg:province":"SK",
    "wof:name":"Marsden Jubilee School",
    "wof:placetype":"venue"
},
  "geometry": {"coordinates":[-109.820915222,52.8420753479],"type":"Point"}
}