{
  "type": "Feature",
  "properties": {
    "addr:full":"10227 Ilderton Rd Ilderton ON N0M 2A0",
    "addr:housenumber":"10227",
    "addr:postcode":"n0m 2a0",
    "addr:street":"Ilderton Rd",
    "iso:country":"CA",
    "sg:address":"10227 Ilderton Rd",
    "sg:city":"Ilderton",
    "sg:classifiers":[
        {
            "category":"Recreation",
            "type":"Entertainment"
        }
    ],
    "sg:phone":"+1 519 666 1832",
    "sg:postcode":"N0M 2A0",
    "sg:province":"ON",
    "sg:tags":[
        "hall",
        "auditorium"
    ],
    "wof:name":"Coldstream Community Ctr",
    "wof:placetype":"venue"
},
  "geometry": {"coordinates":[-81.50202178959999,43.0147666931],"type":"Point"}
}