{
  "type": "Feature",
  "properties": {
    "addr:full":"706 10th Line Collingwood ON L9Y 3Z4",
    "addr:housenumber":"706",
    "addr:postcode":"l9y 3z4",
    "addr:street":"10Th Line",
    "iso:country":"CA",
    "sg:address":"706 10th Line",
    "sg:city":"Collingwood",
    "sg:classifiers":[
        {
            "category":"Sports & Exercise",
            "subcategory":"Golf",
            "type":"Entertainment"
        }
    ],
    "sg:phone":"+1 705 445 3918",
    "sg:postcode":"L9Y 3Z4",
    "sg:province":"ON",
    "sg:tags":[
        "course"
    ],
    "wof:name":"Blue Mountain Golf & Country",
    "wof:placetype":"venue"
},
  "geometry": {"coordinates":[-80.250687,44.498894],"type":"Point"}
}