{
  "type": "Feature",
  "properties": {
    "addr:full":"136 Rue Jacques Chan Kirkland QC H9J 3Y1",
    "addr:housenumber":"136",
    "addr:postcode":"h9j 3y1",
    "addr:street":"Rue Jacques Chan",
    "iso:country":"CA",
    "sg:address":"136 Rue Jacques Chan",
    "sg:city":"Kirkland",
    "sg:classifiers":[
        {
            "category":"Freight",
            "type":"Transportation"
        }
    ],
    "sg:phone":"+1 514 697 4193",
    "sg:postcode":"H9J 3Y1",
    "sg:province":"QC",
    "sg:tags":[
        "trucking"
    ],
    "wof:name":"Gestion Rmh Management",
    "wof:placetype":"venue"
},
  "geometry": {"coordinates":[-73.88632200000001,45.447346],"type":"Point"}
}