{
  "type": "Feature",
  "properties": {
    "iso:country":"CA",
    "sg:address":"RR 4",
    "sg:city":"Walkerton",
    "sg:classifiers":[
        {
            "category":"Recreation",
            "type":"Entertainment"
        }
    ],
    "sg:phone":"+1 519 881 4641",
    "sg:postcode":"N0G 2V0",
    "sg:province":"ON",
    "sg:tags":[
        "course",
        "golf"
    ],
    "wof:name":"Dunkled Eat 'N Putt",
    "wof:placetype":"venue"
},
  "geometry": {"coordinates":[-81.15213012700001,44.1281814575],"type":"Point"}
}