{
  "type": "Feature",
  "properties": {
    "addr:full":"75 Lowther Ave Toronto ON M5R 1C9",
    "addr:housenumber":"75",
    "addr:postcode":"m5r 1c9",
    "addr:street":"Lowther Ave",
    "iso:country":"CA",
    "sg:address":"75 Lowther Ave",
    "sg:city":"Toronto",
    "sg:classifiers":[
        {
            "category":"Professional",
            "subcategory":"Lawyer & Legal Services",
            "type":"Services"
        }
    ],
    "sg:phone":"+1 416 927 0073",
    "sg:postcode":"M5R 1C9",
    "sg:province":"ON",
    "sg:tags":[
        "attorney"
    ],
    "wof:name":"Peterson, Edmund",
    "wof:placetype":"venue"
},
  "geometry": {"coordinates":[-79.398827,43.670067],"type":"Point"}
}