{
  "type": "Feature",
  "properties": {
    "iso:country":"CA",
    "sg:address":"1033 Bay St",
    "sg:city":"Toronto",
    "sg:classifiers":[
        {
            "category":"Travel",
            "subcategory":"Travel Agent",
            "type":"Entertainment"
        }
    ],
    "sg:phone":"+1 416 926 2500",
    "sg:postcode":"M5S 3A5",
    "sg:province":"ON",
    "sg:tags":[
        "agency",
        "bureau"
    ],
    "wof:name":"Travel Society",
    "wof:placetype":"venue"
},
  "geometry": {"coordinates":[-79.3877029419,43.6660575867],"type":"Point"}
}