{
  "type": "Feature",
  "properties": {
    "iso:country":"CA",
    "sg:address":"99 Alma St",
    "sg:city":"Norwood",
    "sg:classifiers":[
        {
            "category":"Health Services",
            "subcategory":"Nursing And Care Facility",
            "type":"Services"
        }
    ],
    "sg:phone":"+1 705 639 5308",
    "sg:postcode":"K0L 2V0",
    "sg:province":"ON",
    "sg:tags":[
        "home",
        "convalescent"
    ],
    "wof:name":"Pleasant Meadow Manor",
    "wof:placetype":"venue"
},
  "geometry": {"coordinates":[-77.9748001099,44.3811607361],"type":"Point"}
}