{
  "type": "Feature",
  "properties": {
    "addr:full":"3401 35 Ave Vernon BC V1T 2T5",
    "addr:housenumber":"3401",
    "addr:postcode":"v1t 2t5",
    "addr:street":"35 Ave",
    "iso:country":"CA",
    "sg:address":"3401 35 Ave",
    "sg:city":"Vernon",
    "sg:classifiers":[
        {
            "category":"Recreation",
            "type":"Entertainment"
        }
    ],
    "sg:phone":"+1 250 545 2236",
    "sg:postcode":"V1T 2T5",
    "sg:province":"BC",
    "sg:tags":[
        "carnival"
    ],
    "wof:name":"Vernon Winter Carnival Society",
    "wof:placetype":"venue"
},
  "geometry": {"coordinates":[-119.277199,50.267502],"type":"Point"}
}