{
  "type": "Feature",
  "properties": {
    "addr:full":"400 Hwy 529 Pointe-Au-Baril-Station ON P0G 1K0",
    "addr:housenumber":"400",
    "addr:postcode":"p0g 1k0",
    "addr:street":"Hwy 529",
    "iso:country":"CA",
    "sg:address":"400 Hwy 529",
    "sg:city":"Pointe-Au-Baril-Station",
    "sg:classifiers":[
        {
            "category":"Restaurant",
            "type":"Food & Drink"
        }
    ],
    "sg:phone":"+1 705 366 2841",
    "sg:postcode":"P0G 1K0",
    "sg:province":"ON",
    "wof:name":"Forest Glen Rv Resort-Rstrnt",
    "wof:placetype":"venue"
},
  "geometry": {"coordinates":[-80.37716674799999,45.6002883911],"type":"Point"}
}