{
  "type": "Feature",
  "properties": {
    "addr:full":"7275 11 St SE Calgary AB T2H 2S1",
    "addr:housenumber":"7275",
    "addr:postcode":"t2h 2s1",
    "addr:street":"11 St Se",
    "iso:country":"CA",
    "sg:address":"7275 11 St SE",
    "sg:city":"Calgary",
    "sg:classifiers":[
        {
            "category":"Shopping",
            "type":"Retail Goods"
        }
    ],
    "sg:phone":"+1 403 319 0262",
    "sg:postcode":"T2H 2S1",
    "sg:province":"AB",
    "sg:tags":[
        "spa",
        "hot",
        "tub"
    ],
    "wof:name":"Glacier Spas Inc",
    "wof:placetype":"venue"
},
  "geometry": {"coordinates":[-114.039733887,50.9889526367],"type":"Point"}
}