{
  "type": "Feature",
  "properties": {
    "addr:full":"Montreal QC H2N 1C3",
    "addr:postcode":"h2n 1c3",
    "iso:country":"CA",
    "sg:city":"Montreal",
    "sg:classifiers":[
        {
            "category":"Shopping",
            "subcategory":"Clothing, Apparel, & Fashions",
            "type":"Retail Goods"
        }
    ],
    "sg:phone":"+1 514 382 0200",
    "sg:postcode":"H2N 1C3",
    "sg:province":"QC",
    "sg:tags":[
        "sportswear"
    ],
    "wof:name":"Aloe Boutique",
    "wof:placetype":"venue"
},
  "geometry": {"coordinates":[-73.65236663819999,45.5425262451],"type":"Point"}
}