{
  "type": "Feature",
  "properties": {
    "addr:full":"130 Ellesmere Rd Scarborough ON M1R 4C5",
    "addr:housenumber":"130",
    "addr:postcode":"m1r 4c5",
    "addr:street":"Ellesmere Rd",
    "iso:country":"CA",
    "sg:address":"130 Ellesmere Rd",
    "sg:city":"Scarborough",
    "sg:classifiers":[
        {
            "category":"Health Services",
            "subcategory":"Doctor",
            "type":"Services"
        }
    ],
    "sg:phone":"+1 416 447 5531",
    "sg:postcode":"M1R 4C5",
    "sg:province":"ON",
    "sg:tags":[
        "physician",
        "surgeon"
    ],
    "wof:name":"Ellesmere Medical Clinic",
    "wof:placetype":"venue"
},
  "geometry": {"coordinates":[-79.30911999999999,43.759441],"type":"Point"}
}