{
  "type": "Feature",
  "properties": {
    "iso:country":"CA",
    "sg:city":"Victoria",
    "sg:classifiers":[
        {
            "category":"Health Services",
            "subcategory":"Chiropractor",
            "type":"Services"
        }
    ],
    "sg:phone":"+1 250 381 7318",
    "sg:postcode":"V8V 3N1",
    "sg:province":"BC",
    "wof:name":"Wensley, Mark G DC",
    "wof:placetype":"venue"
},
  "geometry": {"coordinates":[-123.35260772700001,48.4248580933],"type":"Point"}
}