{
  "type": "Feature",
  "properties": {
    "addr:full":"734 Wilkins St London ON N6C 4Z9",
    "addr:housenumber":"734",
    "addr:postcode":"n6c 4z9",
    "addr:street":"Wilkins St",
    "iso:country":"CA",
    "sg:address":"734 Wilkins St",
    "sg:city":"London",
    "sg:classifiers":[
        {
            "category":"Building & Trades",
            "subcategory":"Construction",
            "type":"Services"
        }
    ],
    "sg:phone":"+1 519 471 2054",
    "sg:postcode":"N6C 4Z9",
    "sg:province":"ON",
    "sg:tags":[
        "home",
        "improvement"
    ],
    "wof:name":"Hhsa",
    "wof:placetype":"venue"
},
  "geometry": {"coordinates":[-81.23183400000001,42.951981],"type":"Point"}
}