{
  "type": "Feature",
  "properties": {
    "addr:full":"244 Deschenes E Saint-Epiphane QC G0L 2X0",
    "addr:housenumber":"244",
    "addr:postcode":"g0l 2x0",
    "addr:street":"Deschenes E Saint-Epiphane",
    "iso:country":"CA",
    "sg:address":"244 Deschenes E",
    "sg:city":"Saint-Epiphane",
    "sg:classifiers":[
        {
            "category":"Retail",
            "subcategory":"Funeral Services",
            "type":"Services"
        }
    ],
    "sg:phone":"+1 418 867 4492",
    "sg:postcode":"G0L 2X0",
    "sg:province":"QC",
    "sg:tags":[
        "plan"
    ],
    "wof:name":"Marc Andre Rioux Ltee",
    "wof:placetype":"venue"
},
  "geometry": {"coordinates":[-69.332161,47.89859],"type":"Point"}
}