{
  "type": "Feature",
  "properties": {
    "addr:full":"9600 Boul Gouin O Pierrefonds QC H8Y 1R5",
    "addr:housenumber":"9600",
    "addr:postcode":"h8y 1r5",
    "addr:street":"Boul Gouin O",
    "iso:country":"CA",
    "sg:address":"9600 Boul Gouin O",
    "sg:city":"Pierrefonds",
    "sg:classifiers":[
        {
            "category":"Social Services",
            "subcategory":"Child Care",
            "type":"Services"
        }
    ],
    "sg:phone":"+1 514 683 1099",
    "sg:postcode":"H8Y 1R5",
    "sg:province":"QC",
    "wof:name":"Garderie Domino",
    "wof:placetype":"venue"
},
  "geometry": {"coordinates":[-73.7823104858,45.5040092468],"type":"Point"}
}