{
  "type": "Feature",
  "properties": {
    "iso:country":"CA",
    "sg:address":"8 Wellington St W",
    "sg:city":"Exeter",
    "sg:classifiers":[
        {
            "category":"Food & Beverages",
            "subcategory":"Specialty",
            "type":"Retail Goods"
        }
    ],
    "sg:phone":"+1 519 235 3088",
    "sg:postcode":"N0M 1S2",
    "sg:province":"ON",
    "sg:tags":[
        "control",
        "health",
        "diet",
        "weight"
    ],
    "wof:name":"Herbal Magic Systems of Exeter",
    "wof:placetype":"venue"
},
  "geometry": {"coordinates":[-81.48211669920001,43.3528175354],"type":"Point"}
}