{
  "type": "Feature",
  "properties": {
    "iso:country":"CA",
    "sg:address":"238 N 10th Ave",
    "sg:city":"Creston",
    "sg:classifiers":[
        {
            "category":"Government",
            "subcategory":"Office",
            "type":"Public Place"
        }
    ],
    "sg:phone":"+1 250 428 2214",
    "sg:postcode":"V0B 1G0",
    "sg:province":"BC",
    "sg:tags":[
        "municipality"
    ],
    "wof:name":"Creston Town Hall",
    "wof:placetype":"venue"
},
  "geometry": {"coordinates":[-116.513221741,49.097202301],"type":"Point"}
}