{
  "type": "Feature",
  "properties": {
    "addr:full":"501 1 Ave S #1003 Lethbridge AB T1J 4L9",
    "addr:housenumber":"501",
    "addr:postcode":"t1j 4l9",
    "addr:street":"1 Ave S # 1003",
    "iso:country":"CA",
    "sg:address":"501 1 Ave S #1003",
    "sg:city":"Lethbridge",
    "sg:classifiers":[
        {
            "category":"Shopping",
            "subcategory":"Clothing, Apparel, & Fashions",
            "type":"Retail Goods"
        }
    ],
    "sg:phone":"+1 403 329 4047",
    "sg:postcode":"T1J 4L9",
    "sg:province":"AB",
    "sg:tags":[
        "infant",
        "wear"
    ],
    "wof:name":"Please Mum",
    "wof:placetype":"venue"
},
  "geometry": {"coordinates":[-112.840202331,49.6980705261],"type":"Point"}
}