{
  "type": "Feature",
  "properties": {
    "addr:full":"14159 Rue Forsyth Pointe-Aux-Trembles QC H1A 5M1",
    "addr:housenumber":"14159",
    "addr:postcode":"h1a 5m1",
    "addr:street":"Rue Forsyth",
    "iso:country":"CA",
    "sg:address":"14159 Rue Forsyth",
    "sg:city":"Pointe-Aux-Trembles",
    "sg:classifiers":[
        {
            "category":"Manufacturing",
            "subcategory":"Printing",
            "type":"Manufacturing & Wholesale Goods"
        }
    ],
    "sg:phone":"+1 514 498 4828",
    "sg:postcode":"H1A 5M1",
    "sg:province":"QC",
    "sg:tags":[
        "publisher",
        "guide"
    ],
    "wof:name":"Editions Du Parcours",
    "wof:placetype":"venue"
},
  "geometry": {"coordinates":[-73.502281,45.671387],"type":"Point"}
}