{
  "type": "Feature",
  "properties": {
    "addr:full":"849 63rd Ave W Vancouver BC V6P 2H3",
    "addr:housenumber":"849",
    "addr:postcode":"v6p 2h3",
    "addr:street":"63Rd Ave W",
    "iso:country":"CA",
    "sg:address":"849 63rd Ave W",
    "sg:city":"Vancouver",
    "sg:classifiers":[
        {
            "category":"Insurance",
            "subcategory":"Hazard Insurance",
            "type":"Services"
        }
    ],
    "sg:phone":"+1 604 323 9363",
    "sg:postcode":"V6P 2H3",
    "sg:province":"BC",
    "sg:tags":[
        "management",
        "business",
        "consultant",
        "benefit",
        "compensation",
        "plan",
        "employee"
    ],
    "wof:name":"Satanove & Flood Consulting",
    "wof:placetype":"venue"
},
  "geometry": {"coordinates":[-123.125359,49.213963],"type":"Point"}
}