{
  "type": "Feature",
  "properties": {
    "addr:full":"260 Whitewood Ave N New Liskeard ON P0J 1P0",
    "addr:housenumber":"260",
    "addr:postcode":"p0j 1p0",
    "addr:street":"Whitewood Ave N New",
    "iso:country":"CA",
    "sg:address":"260 Whitewood Ave N",
    "sg:city":"New Liskeard",
    "sg:classifiers":[
        {
            "category":"Organizations",
            "subcategory":"Religious Organization",
            "type":"Services"
        }
    ],
    "sg:phone":"+1 705 647 4115",
    "sg:postcode":"P0J 1P0",
    "sg:province":"ON",
    "sg:tags":[
        "church"
    ],
    "wof:name":"Salvation Army",
    "wof:placetype":"venue"
},
  "geometry": {"coordinates":[-79.68163300000001,47.508472],"type":"Point"}
}