{
  "type": "Feature",
  "properties": {
    "addr:full":"RR 2 Westville NS B0K 2A0",
    "addr:postcode":"b0k 2a0",
    "addr:street":"Rr 2",
    "iso:country":"CA",
    "sg:address":"RR 2",
    "sg:city":"Westville",
    "sg:classifiers":[
        {
            "category":"Organizations",
            "subcategory":"Religious Organization",
            "type":"Services"
        }
    ],
    "sg:phone":"+1 902 396 4206",
    "sg:postcode":"B0K 2A0",
    "sg:province":"NS",
    "sg:tags":[
        "church"
    ],
    "wof:name":"St Andrew Presbyterian Church",
    "wof:placetype":"venue"
},
  "geometry": {"coordinates":[-62.709908,45.56176],"type":"Point"}
}