{
  "type": "Feature",
  "properties": {
    "addr:full":"1375 Golf Links Rd # B Nelson BC V1L 7A2",
    "addr:housenumber":"1375",
    "addr:postcode":"bc v1l 7a2",
    "addr:street":"Golf Links Rd # B",
    "iso:country":"CA",
    "sg:address":"1375 Golf Links Rd # B",
    "sg:city":"Nelson",
    "sg:classifiers":[
        {
            "category":"Retail",
            "subcategory":"Animal Services",
            "type":"Services"
        }
    ],
    "sg:phone":"+1 250 352 2549",
    "sg:postcode":"V1L 7A2",
    "sg:province":"BC",
    "sg:tags":[
        "pet",
        "boarding",
        "grooming",
        "washing",
        "sitting"
    ],
    "wof:name":"Wagg's Boarding & Grooming",
    "wof:placetype":"venue"
},
  "geometry": {"coordinates":[-117.306190491,49.4821357727],"type":"Point"}
}