{
  "type": "Feature",
  "properties": {
    "addr:full":"2920 Bridge St Victoria BC V8T 4T3",
    "addr:housenumber":"2920",
    "addr:postcode":"v8t 4t3",
    "addr:street":"Bridge St",
    "iso:country":"CA",
    "sg:address":"2920 Bridge St",
    "sg:city":"Victoria",
    "sg:classifiers":[
        {
            "category":"Retail",
            "subcategory":"Repair Shop",
            "type":"Services"
        }
    ],
    "sg:phone":"+1 250 385 5500",
    "sg:postcode":"V8T 4T3",
    "sg:province":"BC",
    "sg:tags":[
        "sharpening",
        "woodworker"
    ],
    "wof:name":"Island Saw & Tool CO",
    "wof:placetype":"venue"
},
  "geometry": {"coordinates":[-123.37329099999999,48.439232],"type":"Point"}
}