{
  "type": "Feature",
  "properties": {
    "addr:full":"169 Bristol Ave Liverpool NS B0T 1K0",
    "addr:housenumber":"169",
    "addr:postcode":"b0t 1k0",
    "addr:street":"Bristol Ave",
    "iso:country":"CA",
    "sg:address":"169 Bristol Ave",
    "sg:city":"Liverpool",
    "sg:classifiers":[
        {
            "category":"Food & Beverages",
            "subcategory":"Groceries & Convenience Stores",
            "type":"Retail Goods"
        }
    ],
    "sg:phone":"+1 902 354 2048",
    "sg:postcode":"B0T 1K0",
    "sg:province":"NS",
    "wof:name":"Irving Mainway",
    "wof:placetype":"venue"
},
  "geometry": {"coordinates":[-64.72193900000001,44.045658],"type":"Point"}
}