{
  "type": "Feature",
  "properties": {
    "addr:full":"Drummondville QC J2C 2C8",
    "addr:postcode":"j2c 2c8",
    "iso:country":"CA",
    "sg:city":"Drummondville",
    "sg:classifiers":[
        {
            "category":"Insurance",
            "subcategory":"Insurance Agent",
            "type":"Services"
        }
    ],
    "sg:phone":"+1 819 478 1494",
    "sg:postcode":"J2C 2C8",
    "sg:province":"QC",
    "sg:tags":[
        "adjuster"
    ],
    "wof:name":"Cunningham Lindsay Canada Ltd",
    "wof:placetype":"venue"
},
  "geometry": {"coordinates":[-72.50533299999999,45.887608],"type":"Point"}
}