{
  "type": "Feature",
  "properties": {
    "iso:country":"CA",
    "sg:address":"4892 Rue Jarry E",
    "sg:city":"Saint-Leonard",
    "sg:classifiers":[
        {
            "category":"Health Services",
            "subcategory":"Doctor",
            "type":"Services"
        }
    ],
    "sg:phone":"+1 514 328 2811",
    "sg:postcode":"H1R 1X9",
    "sg:province":"QC",
    "sg:tags":[
        "dentist"
    ],
    "wof:name":"Franklin, Lorice DDS",
    "wof:placetype":"venue"
},
  "geometry": {"coordinates":[-73.5955505371,45.579284668],"type":"Point"}
}