{
  "type": "Feature",
  "properties": {
    "iso:country":"CA",
    "sg:address":"4226 Petrolia Line",
    "sg:city":"Petrolia",
    "sg:classifiers":[
        {
            "category":"Shopping",
            "subcategory":"Gifts & Souvenirs",
            "type":"Retail Goods"
        }
    ],
    "sg:phone":"+1 519 882 0747",
    "sg:postcode":"N0N 1R0",
    "sg:province":"ON",
    "sg:tags":[
        "shop"
    ],
    "wof:name":"Top of the Hill Gift Shoppe",
    "wof:placetype":"venue"
},
  "geometry": {"coordinates":[-82.1450424194,42.8819923401],"type":"Point"}
}