{
  "type": "Feature",
  "properties": {
    "addr:full":"1492 Akiskinook Rd Windermere BC V0B 2L0",
    "addr:housenumber":"1492",
    "addr:postcode":"bc v0b 2l0",
    "addr:street":"Akiskinook Rd",
    "iso:country":"CA",
    "sg:address":"1492 Akiskinook Rd",
    "sg:city":"Windermere",
    "sg:classifiers":[
        {
            "category":"Real Estate",
            "subcategory":"Real Estate Operator",
            "type":"Services"
        }
    ],
    "sg:phone":"+1 250 342 9411",
    "sg:postcode":"V0B 2L0",
    "sg:province":"BC",
    "sg:tags":[
        "condominium"
    ],
    "wof:name":"Akiskinook Resort",
    "wof:placetype":"venue"
},
  "geometry": {"coordinates":[-115.990737915,50.4722862244],"type":"Point"}
}