{
  "type": "Feature",
  "properties": {
    "iso:country":"CA",
    "sg:city":"Scarborough",
    "sg:classifiers":[
        {
            "category":"Building & Trades",
            "subcategory":"Construction",
            "type":"Services"
        }
    ],
    "sg:phone":"+1 416 752 2604",
    "sg:postcode":"M1K 1R6",
    "sg:province":"ON",
    "sg:tags":[
        "painter"
    ],
    "wof:name":"Toronto Pro Painters CO",
    "wof:placetype":"venue"
},
  "geometry": {"coordinates":[-79.2754974365,43.724609375],"type":"Point"}
}