{
  "type": "Feature",
  "properties": {
    "addr:full":"Winnipeg MB R3Y 1V2",
    "addr:postcode":"r3y 1v2",
    "iso:country":"CA",
    "sg:city":"Winnipeg",
    "sg:classifiers":[
        {
            "category":"Shopping",
            "type":"Retail Goods"
        }
    ],
    "sg:phone":"+1 204 992 2229",
    "sg:postcode":"R3Y 1V2",
    "sg:province":"MB",
    "sg:tags":[
        "equipment",
        "telephone",
        "supply"
    ],
    "wof:name":"Nrg Tele Resources Inc",
    "wof:placetype":"venue"
},
  "geometry": {"coordinates":[-97.186416626,49.8184280396],"type":"Point"}
}