{
  "type": "Feature",
  "properties": {
    "addr:full":"13700 Mayfield Pl # 2120 Richmond BC V6V 2E4",
    "addr:housenumber":"13700",
    "addr:postcode":"v6v 2e4",
    "addr:street":"Mayfield Pl # 2120",
    "iso:country":"CA",
    "sg:address":"13700 Mayfield Pl # 2120",
    "sg:city":"Richmond",
    "sg:classifiers":[
        {
            "category":"Professional",
            "subcategory":"Research",
            "type":"Services"
        }
    ],
    "sg:phone":"+1 604 207 0233",
    "sg:postcode":"V6V 2E4",
    "sg:province":"BC",
    "sg:tags":[
        "development",
        "laboratory"
    ],
    "wof:name":"Twinturbo Development Inc",
    "wof:placetype":"venue"
},
  "geometry": {"coordinates":[-123.072784,49.181576],"type":"Point"}
}