{
  "type": "Feature",
  "properties": {
    "addr:full":"811 Reeves St Port Hawkesbury NS B9A 2S4",
    "addr:housenumber":"811",
    "addr:postcode":"b9a 2s4",
    "addr:street":"Reeves St",
    "iso:country":"CA",
    "sg:address":"811 Reeves St",
    "sg:city":"Port Hawkesbury",
    "sg:classifiers":[
        {
            "category":"Shopping",
            "subcategory":"Optical Goods",
            "type":"Retail Goods"
        }
    ],
    "sg:phone":"+1 902 625 2186",
    "sg:postcode":"B9A 2S4",
    "sg:province":"NS",
    "sg:tags":[
        "optometrist",
        "contact",
        "lense"
    ],
    "wof:name":"Haines, Ronald S OD",
    "wof:placetype":"venue"
},
  "geometry": {"coordinates":[-61.34893,45.613724],"type":"Point"}
}