{
  "type": "Feature",
  "properties": {
    "addr:full":"21911 Adelaide Rd Mount Brydges ON N0L 1W0",
    "addr:housenumber":"21911",
    "addr:postcode":"n0l 1w0",
    "addr:street":"Adelaide Rd",
    "iso:country":"CA",
    "sg:address":"21911 Adelaide Rd",
    "sg:city":"Mount Brydges",
    "sg:classifiers":[
        {
            "category":"Building & Trades",
            "subcategory":"Construction",
            "type":"Services"
        }
    ],
    "sg:phone":"+1 519 264 9195",
    "sg:postcode":"N0L 1W0",
    "sg:province":"ON",
    "sg:tags":[
        "stone",
        "masonry",
        "contractor"
    ],
    "wof:name":"Stone Traditions",
    "wof:placetype":"venue"
},
  "geometry": {"coordinates":[-81.463387,42.899734],"type":"Point"}
}