{
  "type": "Feature",
  "properties": {
    "addr:full":"2554 Elizabeth Oil Springs ON N0N 1P0",
    "addr:housenumber":"2554",
    "addr:postcode":"n0n 1p0",
    "addr:street":"Elizabeth Oil",
    "iso:country":"CA",
    "sg:address":"2554 Elizabeth",
    "sg:city":"Oil Springs",
    "sg:classifiers":[
        {
            "category":"Organizations",
            "subcategory":"Religious Organization",
            "type":"Services"
        }
    ],
    "sg:phone":"+1 519 834 2984",
    "sg:postcode":"N0N 1P0",
    "sg:province":"ON",
    "sg:tags":[
        "church"
    ],
    "wof:name":"Voice of Truth Tabernacle",
    "wof:placetype":"venue"
},
  "geometry": {"coordinates":[-82.1219787598,42.7821655273],"type":"Point"}
}