{
  "type": "Feature",
  "properties": {
    "addr:full":"393 Rue Victoria Thurso QC J0X 3B0",
    "addr:housenumber":"393",
    "addr:postcode":"j0x 3b0",
    "addr:street":"Rue Victoria",
    "iso:country":"CA",
    "sg:address":"393 Rue Victoria",
    "sg:city":"Thurso",
    "sg:classifiers":[
        {
            "category":"Manufacturing",
            "subcategory":"Tools & Machinery",
            "type":"Manufacturing & Wholesale Goods"
        }
    ],
    "sg:phone":"+1 819 985 3333",
    "sg:postcode":"J0X 3B0",
    "sg:province":"QC",
    "sg:tags":[
        "equipment",
        "hydraulic",
        "supply"
    ],
    "wof:name":"E M Waters Inc",
    "wof:placetype":"venue"
},
  "geometry": {"coordinates":[-75.248741,45.595654],"type":"Point"}
}