{
  "type": "Feature",
  "properties": {
    "addr:full":"221 3E Rue E Amos QC J9T 2A5",
    "addr:housenumber":"221",
    "addr:postcode":"j9t 2a5",
    "addr:street":"3E Rue E Amos",
    "iso:country":"CA",
    "sg:address":"221 3E Rue E",
    "sg:city":"Amos",
    "sg:classifiers":[
        {
            "category":"Professional",
            "subcategory":"Secretarial Services",
            "type":"Services"
        }
    ],
    "sg:phone":"+1 819 727 1795",
    "sg:postcode":"J9T 2A5",
    "sg:province":"QC",
    "sg:tags":[
        "reporting",
        "court",
        "resume"
    ],
    "wof:name":"Centre D'Affaires Micro",
    "wof:placetype":"venue"
},
  "geometry": {"coordinates":[-78.1112823486,48.5624313354],"type":"Point"}
}