{
  "type": "Feature",
  "properties": {
    "addr:full":"230 Boul Dr Albiny-Paquette Mont-Laurier QC J9L 1J9",
    "addr:housenumber":"230",
    "addr:postcode":"j9l 1j9",
    "addr:street":"Boul Dr Albiny-Paquette",
    "iso:country":"CA",
    "sg:address":"230 Boul Dr Albiny-Paquette",
    "sg:city":"Mont-Laurier",
    "sg:classifiers":[
        {
            "category":"Retail",
            "subcategory":"Auto Repair",
            "type":"Services"
        }
    ],
    "sg:phone":"+1 819 623 4200",
    "sg:postcode":"J9L 1J9",
    "sg:province":"QC",
    "sg:tags":[
        "repairing",
        "automobile",
        "truck"
    ],
    "wof:name":"Suspension Mont-Laurier",
    "wof:placetype":"venue"
},
  "geometry": {"coordinates":[-75.5059967041,46.5485610962],"type":"Point"}
}