{
  "type": "Feature",
  "properties": {
    "addr:full":"8246 Rue Alfred-Brosseau Montreal QC H1E 2Y4",
    "addr:housenumber":"8246",
    "addr:postcode":"h1e 2y4",
    "addr:street":"Rue Alfred-Brosseau",
    "iso:country":"CA",
    "sg:address":"8246 Rue Alfred-Brosseau",
    "sg:city":"Montreal",
    "sg:classifiers":[
        {
            "category":"Building & Trades",
            "subcategory":"Cleaning & Sanitation",
            "type":"Services"
        }
    ],
    "sg:phone":"+1 514 648 0286",
    "sg:postcode":"H1E 2Y4",
    "sg:province":"QC",
    "sg:tags":[
        "ventilating",
        "system"
    ],
    "wof:name":"Nettoyeurs Provincial Conduits",
    "wof:placetype":"venue"
},
  "geometry": {"coordinates":[-73.58136,45.630009],"type":"Point"}
}