{
  "type": "Feature",
  "properties": {
    "addr:full":"42 Rue Des Entreprises Sainte-Anne-Des-Plaines QC J0N 1H0",
    "addr:housenumber":"42",
    "addr:postcode":"j0n 1h0",
    "addr:street":"Rue Des Entreprises",
    "iso:country":"CA",
    "sg:address":"42 Rue Des Entreprises",
    "sg:city":"Sainte-Anne-Des-Plaines",
    "sg:classifiers":[
        {
            "category":"Wholesale",
            "subcategory":"Auto Parts",
            "type":"Manufacturing & Wholesale Goods"
        }
    ],
    "sg:phone":"+1 450 478 0555",
    "sg:postcode":"J0N 1H0",
    "sg:province":"QC",
    "sg:tags":[
        "equipment",
        "truck"
    ],
    "wof:name":"Pieces DE Camions Rive Nord",
    "wof:placetype":"venue"
},
  "geometry": {"coordinates":[-73.81444500000001,45.760204],"type":"Point"}
}