{
  "type": "Feature",
  "properties": {
    "iso:country":"CA",
    "sg:city":"Campbellville",
    "sg:classifiers":[
        {
            "category":"Health Services",
            "subcategory":"Doctor",
            "type":"Services"
        }
    ],
    "sg:phone":"+1 905 854 2247",
    "sg:postcode":"L0P 1B0",
    "sg:province":"ON",
    "sg:tags":[
        "dentist"
    ],
    "wof:name":"Terefenko, Halina DDS",
    "wof:placetype":"venue"
},
  "geometry": {"coordinates":[-79.98505401609999,43.4877929688],"type":"Point"}
}