{
  "type": "Feature",
  "properties": {
    "addr:full":"500 1st Ave NW # B100 Moose Jaw SK S6H 3M5",
    "addr:housenumber":"500",
    "addr:postcode":"s6h 3m5",
    "addr:street":"1St Ave Nw # B100",
    "iso:country":"CA",
    "sg:address":"500 1st Ave NW # B100",
    "sg:city":"Moose Jaw",
    "sg:classifiers":[
        {
            "category":"Sports & Exercise",
            "subcategory":"Gym",
            "type":"Entertainment"
        }
    ],
    "sg:phone":"+1 306 692 1211",
    "sg:postcode":"S6H 3M5",
    "sg:province":"SK",
    "sg:tags":[
        "club",
        "health",
        "studio",
        "gymnasium"
    ],
    "wof:name":"Sterling Fitness Ctr Inc",
    "wof:placetype":"venue"
},
  "geometry": {"coordinates":[-105.537491,50.394508],"type":"Point"}
}