{
  "type": "Feature",
  "properties": {
    "addr:full":"707 Douglas Fir Rd Sparwood BC V0B 2G0",
    "addr:housenumber":"707",
    "addr:postcode":"bc v0b 2g0",
    "addr:street":"Douglas Fir Rd",
    "iso:country":"CA",
    "sg:address":"707 Douglas Fir Rd",
    "sg:city":"Sparwood",
    "sg:classifiers":[
        {
            "category":"Freight",
            "type":"Transportation"
        }
    ],
    "sg:phone":"+1 250 425 2866",
    "sg:postcode":"V0B 2G0",
    "sg:province":"BC",
    "sg:tags":[
        "hobby",
        "model",
        "public",
        "supply"
    ],
    "wof:name":"Inter Mountain Holdings Ltd",
    "wof:placetype":"venue"
},
  "geometry": {"coordinates":[-114.894348145,49.7124481201],"type":"Point"}
}