{
  "type": "Feature",
  "properties": {
    "addr:full":"RR 2 Oil Springs ON N0N 1P0",
    "addr:postcode":"n0n 1p0",
    "addr:street":"Rr;Oil",
    "iso:country":"CA",
    "sg:address":"RR 2",
    "sg:city":"Oil Springs",
    "sg:classifiers":[
        {
            "category":"Building & Trades",
            "subcategory":"Electrical",
            "type":"Services"
        }
    ],
    "sg:phone":"+1 519 844 2331",
    "sg:postcode":"N0N 1P0",
    "sg:province":"ON",
    "sg:tags":[
        "electric",
        "contractor"
    ],
    "wof:name":"Zimmerman, David",
    "wof:placetype":"venue"
},
  "geometry": {"coordinates":[-82.1199798584,42.7837715149],"type":"Point"}
}