{
  "type": "Feature",
  "properties": {
    "addr:full":"95 Rue Helene Saint-Eustache QC J7P 4J3",
    "addr:housenumber":"95",
    "addr:postcode":"j7p 4j3",
    "addr:street":"Rue Helene",
    "iso:country":"CA",
    "sg:address":"95 Rue Helene",
    "sg:city":"Saint-Eustache",
    "sg:classifiers":[
        {
            "category":"Retail",
            "subcategory":"Repair Shop",
            "type":"Services"
        }
    ],
    "sg:phone":"+1 450 473 4589",
    "sg:postcode":"J7P 4J3",
    "sg:province":"QC",
    "sg:tags":[
        "equipment",
        "electronic",
        "supply"
    ],
    "wof:name":"Service Electronique Ltd",
    "wof:placetype":"venue"
},
  "geometry": {"coordinates":[-73.88426971440001,45.5663757324],"type":"Point"}
}