{
  "type": "Feature",
  "properties": {
    "addr:full":"407 1st Ave St Brieux SK S0K 3V0",
    "addr:housenumber":"407",
    "addr:postcode":"s0k 3v0",
    "addr:street":"1St Ave St",
    "iso:country":"CA",
    "sg:address":"407 1st Ave",
    "sg:city":"St Brieux",
    "sg:classifiers":[
        {
            "category":"Restaurant",
            "type":"Food & Drink"
        }
    ],
    "sg:phone":"+1 306 275 4408",
    "sg:postcode":"S0K 3V0",
    "sg:province":"SK",
    "wof:name":"Terry's Coffee Cup & Grill",
    "wof:placetype":"venue"
},
  "geometry": {"coordinates":[-104.892776489,52.6345710754],"type":"Point"}
}