{
  "type": "Feature",
  "properties": {
    "addr:full":"370 Adelaide Ave E Oshawa ON L1G 2A1",
    "addr:housenumber":"370",
    "addr:postcode":"l1g 2a1",
    "addr:street":"Adelaide Ave E",
    "iso:country":"CA",
    "sg:address":"370 Adelaide Ave E",
    "sg:city":"Oshawa",
    "sg:classifiers":[
        {
            "category":"Education",
            "subcategory":"Special Training",
            "type":"Public Place"
        }
    ],
    "sg:phone":"+1 905 725 7464",
    "sg:postcode":"L1G 2A1",
    "sg:province":"ON",
    "sg:tags":[
        "instruction",
        "music"
    ],
    "wof:name":"Vocal Studio",
    "wof:placetype":"venue"
},
  "geometry": {"coordinates":[-78.853188,43.907436],"type":"Point"}
}