{
  "type": "Feature",
  "properties": {
    "addr:full":"27 Av Sainte-Brigitte S Montmagny QC G5V 2Y1",
    "addr:postcode":"g5v 2y1",
    "addr:street":"27 Av Sainte-Brigitte S Montmagny",
    "iso:country":"CA",
    "sg:address":"27 Av Sainte-Brigitte S",
    "sg:city":"Montmagny",
    "sg:classifiers":[
        {
            "category":"Home & Garden",
            "subcategory":"Building Materials",
            "type":"Retail Goods"
        }
    ],
    "sg:phone":"+1 418 248 3535",
    "sg:postcode":"G5V 2Y1",
    "sg:province":"QC",
    "sg:tags":[
        "upholsterer"
    ],
    "wof:name":"Atelier DE Decor Mercier Inc",
    "wof:placetype":"venue"
},
  "geometry": {"coordinates":[-70.563042,46.979691],"type":"Point"}
}