{
  "type": "Feature",
  "properties": {
    "addr:full":"Saint-Laurent QC H4T 1Z9",
    "addr:postcode":"h4t 1z9",
    "iso:country":"CA",
    "sg:city":"Saint-Laurent",
    "sg:classifiers":[
        {
            "category":"Education",
            "subcategory":"Special Training",
            "type":"Public Place"
        }
    ],
    "sg:phone":"+1 514 747 3381",
    "sg:postcode":"H4T 1Z9",
    "sg:province":"QC",
    "sg:tags":[
        "instruction",
        "speaking"
    ],
    "wof:name":"Formation Dale Carnegie System",
    "wof:placetype":"venue"
},
  "geometry": {"coordinates":[-73.68784332280001,45.4951095581],"type":"Point"}
}