{
  "type": "Feature",
  "properties": {
    "addr:full":"2948 Place Favreau Saint-Laurent QC H4M 2Y8",
    "addr:housenumber":"2948",
    "addr:postcode":"h4m 2y8",
    "addr:street":"Place Favreau",
    "iso:country":"CA",
    "sg:address":"2948 Place Favreau",
    "sg:city":"Saint-Laurent",
    "sg:classifiers":[
        {
            "category":"Retail",
            "subcategory":"Repair Shop",
            "type":"Services"
        }
    ],
    "sg:phone":"+1 514 855 0689",
    "sg:postcode":"H4M 2Y8",
    "sg:province":"QC",
    "sg:tags":[
        "equipment",
        "conditioning",
        "air"
    ],
    "wof:name":"Mecanitrol Enr",
    "wof:placetype":"venue"
},
  "geometry": {"coordinates":[-73.699135,45.49855],"type":"Point"}
}