{
  "type": "Feature",
  "properties": {
    "iso:country":"CA",
    "sg:address":"123 Water St",
    "sg:city":"Campbellton",
    "sg:classifiers":[
        {
            "category":"Restaurant",
            "type":"Food & Drink"
        }
    ],
    "sg:phone":"+1 506 759 7827",
    "sg:postcode":"E3N 1B2",
    "sg:province":"NB",
    "wof:name":"Subway Sandwiches & Salads",
    "wof:placetype":"venue"
},
  "geometry": {"coordinates":[-66.6749572754,48.0070304871],"type":"Point"}
}