{
  "type": "Feature",
  "properties": {
    "addr:full":"5124 Rue Jarry E Saint-Leonard QC H1R 1Y4",
    "addr:housenumber":"5124",
    "addr:postcode":"h1r 1y4",
    "addr:street":"Rue Jarry E",
    "iso:country":"CA",
    "sg:address":"5124 Rue Jarry E",
    "sg:city":"Saint-Leonard",
    "sg:classifiers":[
        {
            "category":"Building & Trades",
            "subcategory":"Construction",
            "type":"Services"
        }
    ],
    "sg:phone":"+1 514 323 9559",
    "sg:postcode":"H1R 1Y4",
    "sg:province":"QC",
    "sg:tags":[
        "repairing",
        "remodeling",
        "contractor"
    ],
    "wof:name":"Groupe Option Renovation",
    "wof:placetype":"venue"
},
  "geometry": {"coordinates":[-73.593559,45.581467],"type":"Point"}
}