{
  "type": "Feature",
  "properties": {
    "iso:country":"CA",
    "sg:address":"2 Ch DE Fabre",
    "sg:city":"Ville-Marie",
    "sg:classifiers":[
        {
            "category":"Travel",
            "subcategory":"Hotels & Motels",
            "type":"Entertainment"
        }
    ],
    "sg:phone":"+1 819 629 2965",
    "sg:postcode":"J9V 1E3",
    "sg:province":"QC",
    "wof:name":"Hotel Motel Caroline",
    "wof:placetype":"venue"
},
  "geometry": {"coordinates":[-79.44132995610001,47.3264884949],"type":"Point"}
}