{
  "type": "Feature",
  "properties": {
    "iso:country":"CA",
    "sg:city":"Sherwood Park",
    "sg:classifiers":[
        {
            "category":"Professional",
            "subcategory":"Engineering",
            "type":"Services"
        }
    ],
    "sg:phone":"+1 780 467 6114",
    "sg:postcode":"T8B 1K4",
    "sg:province":"AB",
    "sg:tags":[
        "engineer"
    ],
    "wof:name":"H G Engineering",
    "wof:placetype":"venue"
},
  "geometry": {"coordinates":[-113.29573822,53.5264015198],"type":"Point"}
}