{
  "type": "Feature",
  "properties": {
    "addr:full":"2555 Tachie Rd Fort St James BC V0J 1P0",
    "addr:housenumber":"2555",
    "addr:postcode":"v0j 1p0",
    "addr:street":"Tachie Rd",
    "iso:country":"CA",
    "sg:address":"2555 Tachie Rd",
    "sg:city":"Fort St James",
    "sg:classifiers":[
        {
            "category":"Manufacturing",
            "subcategory":"Lumber",
            "type":"Manufacturing & Wholesale Goods"
        }
    ],
    "sg:phone":"+1 250 996 8297",
    "sg:postcode":"V0J 1P0",
    "sg:province":"BC",
    "sg:tags":[
        "sawmill"
    ],
    "wof:name":"Apollo Forest Products Ltd",
    "wof:placetype":"venue"
},
  "geometry": {"coordinates":[-124.22769165,54.4964103699],"type":"Point"}
}