{
  "type": "Feature",
  "properties": {
    "iso:country":"CA",
    "sg:address":"916 Eglinton Ave W",
    "sg:city":"Toronto",
    "sg:classifiers":[
        {
            "category":"Manufacturing",
            "subcategory":"Food",
            "type":"Manufacturing & Wholesale Goods"
        }
    ],
    "sg:phone":"+1 416 784 5416",
    "sg:postcode":"M6C 2C2",
    "sg:province":"ON",
    "sg:tags":[
        "noodle"
    ],
    "wof:name":"Penne From Heaven",
    "wof:placetype":"venue"
},
  "geometry": {"coordinates":[-79.42798614500001,43.7006111145],"type":"Point"}
}