{
  "type": "Feature",
  "properties": {
    "addr:full":"West St Modeste NL A0K 5S0",
    "addr:postcode":"a0k 5s0",
    "addr:street":"West St",
    "iso:country":"CA",
    "sg:city":"West St Modeste",
    "sg:classifiers":[
        {
            "category":"Recreation",
            "type":"Entertainment"
        }
    ],
    "sg:phone":"+1 709 927 5033",
    "sg:postcode":"A0K 5S0",
    "sg:province":"NL",
    "sg:tags":[
        "youth",
        "information",
        "activity",
        "center",
        "organization"
    ],
    "wof:name":"Family Resource Ctr",
    "wof:placetype":"venue"
},
  "geometry": {"coordinates":[-56.707718,51.591972],"type":"Point"}
}