{
  "type": "Feature",
  "properties": {
    "addr:full":"150 Railside Rd North York ON M3A 1A3",
    "addr:housenumber":"150",
    "addr:postcode":"m3a 1a3",
    "addr:street":"Railside Rd",
    "iso:country":"CA",
    "sg:address":"150 Railside Rd",
    "sg:city":"North York",
    "sg:classifiers":[
        {
            "category":"Organizations",
            "subcategory":"Religious Organization",
            "type":"Services"
        }
    ],
    "sg:phone":"+1 416 285 4735",
    "sg:postcode":"M3A 1A3",
    "sg:province":"ON",
    "sg:tags":[
        "church"
    ],
    "wof:name":"Korean Corps Salvation Army",
    "wof:placetype":"venue"
},
  "geometry": {"coordinates":[-79.326576,43.737621],"type":"Point"}
}