{
  "type": "Feature",
  "properties": {
    "addr:full":"311 Oakland Ave London ON N5W 4J5",
    "addr:housenumber":"311",
    "addr:postcode":"n5w 4j5",
    "addr:street":"Oakland Ave",
    "iso:country":"CA",
    "sg:address":"311 Oakland Ave",
    "sg:city":"London",
    "sg:classifiers":[
        {
            "category":"Organizations",
            "subcategory":"Professional Association",
            "type":"Services"
        }
    ],
    "sg:phone":"+1 519 455 2331",
    "sg:postcode":"N5W 4J5",
    "sg:province":"ON",
    "wof:name":"Royal Canadian Legion",
    "wof:placetype":"venue"
},
  "geometry": {"coordinates":[-81.2049713135,42.9925689697],"type":"Point"}
}