{
  "type": "Feature",
  "properties": {
    "addr:full":"King Wabigoon ON P0V 2W0",
    "addr:postcode":"p0v 2w0",
    "iso:country":"CA",
    "sg:address":"King",
    "sg:city":"Wabigoon",
    "sg:classifiers":[
        {
            "category":"Personal",
            "subcategory":"Beauty Salon",
            "type":"Services"
        }
    ],
    "sg:phone":"+1 807 938 6602",
    "sg:postcode":"P0V 2W0",
    "sg:province":"ON",
    "wof:name":"Hair Expressions",
    "wof:placetype":"venue"
},
  "geometry": {"coordinates":[-92.58049,49.704788],"type":"Point"}
}