{
  "type": "Feature",
  "properties": {
    "addr:full":"750 Oakdale Rd #54 North York ON M3N 2Z4",
    "addr:housenumber":"750",
    "addr:postcode":"m3n 2z4",
    "addr:street":"Oakdale Rd # 54",
    "iso:country":"CA",
    "sg:address":"750 Oakdale Rd #54",
    "sg:city":"North York",
    "sg:classifiers":[
        {
            "category":"Real Estate",
            "subcategory":"Real Estate Agent",
            "type":"Services"
        }
    ],
    "sg:phone":"+1 416 745 6711",
    "sg:postcode":"M3N 2Z4",
    "sg:province":"ON",
    "wof:name":"Realty Group Corp",
    "wof:placetype":"venue"
},
  "geometry": {"coordinates":[-79.524033,43.754665],"type":"Point"}
}