{
  "type": "Feature",
  "properties": {
    "addr:full":"St Isidore ON K0C 2B0",
    "addr:postcode":"k0c 2b0",
    "addr:street":"St Isidore",
    "iso:country":"CA",
    "sg:city":"St Isidore",
    "sg:classifiers":[
        {
            "category":"Retail",
            "subcategory":"Auto Repair",
            "type":"Services"
        }
    ],
    "sg:phone":"+1 613 524 5522",
    "sg:postcode":"K0C 2B0",
    "sg:province":"ON",
    "sg:tags":[
        "repairing",
        "automobile",
        "wheel",
        "alignment"
    ],
    "wof:name":"Unipro St Isidore",
    "wof:placetype":"venue"
},
  "geometry": {"coordinates":[-74.907082,45.388237],"type":"Point"}
}