{
  "type": "Feature",
  "properties": {
    "iso:country":"CA",
    "sg:address":"857 Notre Dame Ave",
    "sg:city":"Winnipeg",
    "sg:classifiers":[
        {
            "category":"Food & Beverages",
            "subcategory":"Specialty",
            "type":"Retail Goods"
        }
    ],
    "sg:phone":"+1 204 772 8220",
    "sg:postcode":"R3E 0M4",
    "sg:province":"MB",
    "sg:tags":[
        "water",
        "bulk",
        "company"
    ],
    "wof:name":"Water Boy",
    "wof:placetype":"venue"
},
  "geometry": {"coordinates":[-97.166039,49.903805],"type":"Point"}
}