{
  "type": "Feature",
  "properties": {
    "addr:full":"451 Moray St Winnipeg MB R3J 3A7",
    "addr:housenumber":"451",
    "addr:postcode":"r3j 3a7",
    "addr:street":"Moray St",
    "iso:country":"CA",
    "sg:address":"451 Moray St",
    "sg:city":"Winnipeg",
    "sg:classifiers":[
        {
            "category":"Travel",
            "subcategory":"Campground",
            "type":"Entertainment"
        }
    ],
    "sg:phone":"+1 204 831 0419",
    "sg:postcode":"R3J 3A7",
    "sg:province":"MB",
    "sg:tags":[
        "camp",
        "fishing"
    ],
    "wof:name":"Bird River Outfitters",
    "wof:placetype":"venue"
},
  "geometry": {"coordinates":[-97.2618637085,49.8841247559],"type":"Point"}
}