{
  "type": "Feature",
  "properties": {
    "addr:full":"7436 Grand St Mission BC V2V 3S5",
    "addr:housenumber":"7436",
    "addr:postcode":"v2v 3s5",
    "addr:street":"Grand St",
    "iso:country":"CA",
    "sg:address":"7436 Grand St",
    "sg:city":"Mission",
    "sg:classifiers":[
        {
            "category":"Travel",
            "subcategory":"Hotels & Motels",
            "type":"Entertainment"
        }
    ],
    "sg:phone":"+1 604 826 4066",
    "sg:postcode":"V2V 3S5",
    "sg:province":"BC",
    "sg:tags":[
        "resort",
        "salon",
        "health",
        "beauty"
    ],
    "wof:name":"Mackie Naturals Salon & Spa",
    "wof:placetype":"venue"
},
  "geometry": {"coordinates":[-122.309288025,49.1366920471],"type":"Point"}
}