{
  "type": "Feature",
  "properties": {
    "addr:full":"910 Ch Du Village Morin-Heights QC J0R 1H0",
    "addr:housenumber":"910",
    "addr:postcode":"j0r 1h0",
    "addr:street":"Ch Du Village",
    "iso:country":"CA",
    "sg:address":"910 Ch Du Village",
    "sg:city":"Morin-Heights",
    "sg:classifiers":[
        {
            "category":"Real Estate",
            "subcategory":"Real Estate Agent",
            "type":"Services"
        }
    ],
    "sg:phone":"+1 450 226 2112",
    "sg:postcode":"J0R 1H0",
    "sg:province":"QC",
    "wof:name":"Immeubles Du Village Enr",
    "wof:placetype":"venue"
},
  "geometry": {"coordinates":[-74.2538223267,45.9005012512],"type":"Point"}
}