{
  "type": "Feature",
  "properties": {
    "addr:full":"206 Chain Lake Dr Halifax NS B3S 1C5",
    "addr:housenumber":"206",
    "addr:postcode":"b3s 1c5",
    "addr:street":"Chain Lake Dr",
    "iso:country":"CA",
    "sg:address":"206 Chain Lake Dr",
    "sg:city":"Halifax",
    "sg:classifiers":[
        {
            "category":"Shopping",
            "subcategory":"Clothing, Apparel, & Fashions",
            "type":"Retail Goods"
        }
    ],
    "sg:phone":"+1 902 450 5114",
    "sg:postcode":"B3S 1C5",
    "sg:province":"NS",
    "wof:name":"Winners Apparel Ltd",
    "wof:placetype":"venue"
},
  "geometry": {"coordinates":[-63.6752815247,44.6500015259],"type":"Point"}
}