{
  "type": "Feature",
  "properties": {
    "addr:full":"710 15th Ave E Prince Albert SK S6V 7A4",
    "addr:housenumber":"710",
    "addr:postcode":"s6v 7a4",
    "addr:street":"15Th Ave E",
    "iso:country":"CA",
    "sg:address":"710 15th Ave E",
    "sg:city":"Prince Albert",
    "sg:classifiers":[
        {
            "category":"Education",
            "subcategory":"School",
            "type":"Public Place"
        }
    ],
    "sg:phone":"+1 306 763 8800",
    "sg:postcode":"S6V 7A4",
    "sg:province":"SK",
    "wof:name":"National School-Dental Therapy",
    "wof:placetype":"venue"
},
  "geometry": {"coordinates":[-105.706596374,53.2024841309],"type":"Point"}
}