{
  "type": "Feature",
  "properties": {
    "addr:full":"Fenelon Falls ON K0M 1N0",
    "addr:postcode":"k0m 1n0",
    "iso:country":"CA",
    "sg:city":"Fenelon Falls",
    "sg:classifiers":[
        {
            "category":"Travel",
            "subcategory":"Hotels & Motels",
            "type":"Entertainment"
        }
    ],
    "sg:phone":"+1 705 887 2491",
    "sg:postcode":"K0M 1N0",
    "sg:province":"ON",
    "wof:name":"Rosedale Motel",
    "wof:placetype":"venue"
},
  "geometry": {"coordinates":[-78.79553199999999,44.563892],"type":"Point"}
}