{
  "type": "Feature",
  "properties": {
    "addr:full":"90 Thomas St Oakville ON L6J 3A6",
    "addr:housenumber":"90",
    "addr:postcode":"l6j 3a6",
    "addr:street":"Thomas St",
    "iso:country":"CA",
    "sg:address":"90 Thomas St",
    "sg:city":"Oakville",
    "sg:classifiers":[
        {
            "category":"Government",
            "subcategory":"Office",
            "type":"Public Place"
        }
    ],
    "sg:phone":"+1 905 844 0604",
    "sg:postcode":"L6J 3A6",
    "sg:province":"ON",
    "wof:name":"Canadian Forces Reserves",
    "wof:placetype":"venue"
},
  "geometry": {"coordinates":[-79.66888400000001,43.444569],"type":"Point"}
}