{
  "type": "Feature",
  "properties": {
    "addr:full":"4110 Railway Ave Smithers BC V0J 2N0",
    "addr:housenumber":"4110",
    "addr:postcode":"v0j 2n0",
    "addr:street":"Railway Ave",
    "iso:country":"CA",
    "sg:address":"4110 Railway Ave",
    "sg:city":"Smithers",
    "sg:classifiers":[
        {
            "category":"Organizations",
            "subcategory":"Professional Association",
            "type":"Services"
        }
    ],
    "sg:phone":"+1 250 847 9474",
    "sg:postcode":"V0J 2N0",
    "sg:province":"BC",
    "wof:name":"Bulkley Valley Lakes District",
    "wof:placetype":"venue"
},
  "geometry": {"coordinates":[-127.182090759,54.7828483582],"type":"Point"}
}