{
  "type": "Feature",
  "properties": {
    "addr:full":"Orleans ON K1C 6E7",
    "addr:postcode":"k1c 6e7",
    "iso:country":"CA",
    "sg:city":"Orleans",
    "sg:classifiers":[
        {
            "category":"Home & Garden",
            "subcategory":"Household Appliances",
            "type":"Retail Goods"
        }
    ],
    "sg:phone":"+1 613 830 5556",
    "sg:postcode":"K1C 6E7",
    "sg:province":"ON",
    "sg:tags":[
        "cleaners",
        "vacuum"
    ],
    "wof:name":"Ottawa Vacuum Svc Inc",
    "wof:placetype":"venue"
},
  "geometry": {"coordinates":[-75.54724899999999,45.461868],"type":"Point"}
}