{
  "type": "Feature",
  "properties": {
    "addr:full":"48 Sweetberry Dr Sudbury ON P3E 6E5",
    "addr:housenumber":"48",
    "addr:postcode":"p3e 6e5",
    "addr:street":"Sweetberry Dr",
    "iso:country":"CA",
    "sg:address":"48 Sweetberry Dr",
    "sg:city":"Sudbury",
    "sg:classifiers":[
        {
            "category":"Wholesale",
            "subcategory":"Construction Materials",
            "type":"Manufacturing & Wholesale Goods"
        }
    ],
    "sg:phone":"+1 705 523 0100",
    "sg:postcode":"P3E 6E5",
    "sg:province":"ON",
    "sg:tags":[
        "home",
        "stone",
        "interlocking",
        "improvement"
    ],
    "wof:name":"Waltec",
    "wof:placetype":"venue"
},
  "geometry": {"coordinates":[-80.9872055054,46.4393844604],"type":"Point"}
}