{
  "type": "Feature",
  "properties": {
    "addr:full":"590 Beresford Ave York ON M6S 3C3",
    "addr:housenumber":"590",
    "addr:postcode":"m6s 3c3",
    "addr:street":"Beresford Ave",
    "iso:country":"CA",
    "sg:address":"590 Beresford Ave",
    "sg:city":"York",
    "sg:classifiers":[
        {
            "category":"Building & Trades",
            "subcategory":"Electrical",
            "type":"Services"
        }
    ],
    "sg:phone":"+1 416 604 0691",
    "sg:postcode":"M6S 3C3",
    "sg:province":"ON",
    "sg:tags":[
        "telephone"
    ],
    "wof:name":"Expertel Phone Svc",
    "wof:placetype":"venue"
},
  "geometry": {"coordinates":[-79.482178,43.661694],"type":"Point"}
}