{
  "type": "Feature",
  "properties": {
    "addr:full":"2267 Cousins Ave Courtenay BC V9N 3N6",
    "addr:housenumber":"2267",
    "addr:postcode":"v9n 3n6",
    "addr:street":"Cousins Ave",
    "iso:country":"CA",
    "sg:address":"2267 Cousins Ave",
    "sg:city":"Courtenay",
    "sg:classifiers":[
        {
            "category":"Retail",
            "subcategory":"Repair Shop",
            "type":"Services"
        }
    ],
    "sg:phone":"+1 250 334 4553",
    "sg:postcode":"V9N 3N6",
    "sg:province":"BC",
    "sg:tags":[
        "plumbing",
        "contractor"
    ],
    "wof:name":"Salter & Newell Appliance Rpr",
    "wof:placetype":"venue"
},
  "geometry": {"coordinates":[-125.000473,49.670509],"type":"Point"}
}