{
  "type": "Feature",
  "properties": {
    "addr:full":"1255 Queen St W Toronto ON M6K 1L5",
    "addr:housenumber":"1255",
    "addr:postcode":"m6k 1l5",
    "addr:street":"Queen St W",
    "iso:country":"CA",
    "sg:address":"1255 Queen St W",
    "sg:city":"Toronto",
    "sg:classifiers":[
        {
            "category":"Restaurant",
            "type":"Food & Drink"
        }
    ],
    "sg:phone":"+1 416 536 4242",
    "sg:postcode":"M6K 1L5",
    "sg:province":"ON",
    "wof:name":"Stones Place",
    "wof:placetype":"venue"
},
  "geometry": {"coordinates":[-79.430954,43.641609],"type":"Point"}
}