{
  "type": "Feature",
  "properties": {
    "addr:full":"2759 Carousel Cres Gloucester ON K1T 2N5",
    "addr:housenumber":"2759",
    "addr:postcode":"k1t 2n5",
    "addr:street":"Carousel Cres",
    "iso:country":"CA",
    "sg:address":"2759 Carousel Cres",
    "sg:city":"Gloucester",
    "sg:classifiers":[
        {
            "category":"Real Estate",
            "subcategory":"Real Estate Operator",
            "type":"Services"
        }
    ],
    "sg:phone":"+1 613 748 0679",
    "sg:postcode":"K1T 2N5",
    "sg:province":"ON",
    "sg:tags":[
        "apartment"
    ],
    "wof:name":"Mastercraft Development Corp",
    "wof:placetype":"venue"
},
  "geometry": {"coordinates":[-75.644226,45.350037],"type":"Point"}
}