{
  "type": "Feature",
  "properties": {
    "addr:full":"Scarborough ON M1K 5G8",
    "addr:postcode":"m1k 5g8",
    "iso:country":"CA",
    "sg:city":"Scarborough",
    "sg:classifiers":[
        {
            "category":"Banks & Credit Unions",
            "subcategory":"Bank",
            "type":"Services"
        }
    ],
    "sg:phone":"+1 416 288 0277",
    "sg:postcode":"M1K 5G8",
    "sg:province":"ON",
    "sg:tags":[
        "broker",
        "foreign",
        "dealer",
        "exchange"
    ],
    "wof:name":"Sindi Financial Svc",
    "wof:placetype":"venue"
},
  "geometry": {"coordinates":[-79.26767700000001,43.732174],"type":"Point"}
}