{
  "type": "Feature",
  "properties": {
    "addr:full":"Delta BC V4K 5B8",
    "addr:postcode":"v4k 5b8",
    "iso:country":"CA",
    "sg:city":"Delta",
    "sg:classifiers":[
        {
            "category":"Autos & Motor Vehicles",
            "subcategory":"Recreational Vehicle Sales",
            "type":"Retail Goods"
        }
    ],
    "sg:phone":"+1 604 946 1968",
    "sg:postcode":"V4K 5B8",
    "sg:province":"BC",
    "wof:name":"Al's Rv Parts & Svc Ltd",
    "wof:placetype":"venue"
},
  "geometry": {"coordinates":[-123.05961600000001,49.084801],"type":"Point"}
}