{
  "type": "Feature",
  "properties": {
    "addr:full":"2227 Stouffville Rd Gormley ON L0H 1G0",
    "addr:housenumber":"2227",
    "addr:postcode":"l0h 1g0",
    "addr:street":"Stouffville Rd",
    "iso:country":"CA",
    "sg:address":"2227 Stouffville Rd",
    "sg:city":"Gormley",
    "sg:classifiers":[
        {
            "category":"Wholesale",
            "subcategory":"Meat",
            "type":"Manufacturing & Wholesale Goods"
        }
    ],
    "sg:phone":"+1 905 887 5526",
    "sg:postcode":"L0H 1G0",
    "sg:province":"ON",
    "sg:tags":[
        "butchering"
    ],
    "wof:name":"Boadway's Meats",
    "wof:placetype":"venue"
},
  "geometry": {"coordinates":[-79.3814620972,43.9411315918],"type":"Point"}
}