{
  "type": "Feature",
  "properties": {
    "addr:full":"39 George St N Peterborough ON K9J 3E9",
    "addr:housenumber":"39",
    "addr:postcode":"k9j 3e9",
    "addr:street":"George St N",
    "iso:country":"CA",
    "sg:address":"39 George St N",
    "sg:city":"Peterborough",
    "sg:classifiers":[
        {
            "category":"Home & Garden",
            "subcategory":"Building Materials",
            "type":"Retail Goods"
        }
    ],
    "sg:phone":"+1 705 745 6874",
    "sg:postcode":"K9J 3E9",
    "sg:province":"ON",
    "sg:tags":[
        "paint"
    ],
    "wof:name":"Color Your World",
    "wof:placetype":"venue"
},
  "geometry": {"coordinates":[-78.319427,44.294445],"type":"Point"}
}