{
  "type": "Feature",
  "properties": {
    "addr:full":"2203 4 St SW Calgary AB T2S 1X1",
    "addr:housenumber":"2203 4",
    "addr:postcode":"t2s 1x1",
    "addr:street":"St Sw",
    "iso:country":"CA",
    "sg:address":"2203 4 St SW",
    "sg:city":"Calgary",
    "sg:classifiers":[
        {
            "category":"Shopping",
            "subcategory":"News",
            "type":"Retail Goods"
        }
    ],
    "sg:phone":"+1 403 244 8020",
    "sg:postcode":"T2S 1X1",
    "sg:province":"AB",
    "sg:tags":[
        "magazine"
    ],
    "wof:name":"With the Times",
    "wof:placetype":"venue"
},
  "geometry": {"coordinates":[-114.071579,51.033249],"type":"Point"}
}