{
  "type": "Feature",
  "properties": {
    "addr:full":"Mississauga ON L5B 1B7",
    "addr:postcode":"l5b 1b7",
    "iso:country":"CA",
    "sg:city":"Mississauga",
    "sg:classifiers":[
        {
            "category":"Health Services",
            "subcategory":"Doctor",
            "type":"Services"
        }
    ],
    "sg:phone":"+1 905 279 1071",
    "sg:postcode":"L5B 1B7",
    "sg:province":"ON",
    "sg:tags":[
        "dentist"
    ],
    "wof:name":"Cochran, W S DDS",
    "wof:placetype":"venue"
},
  "geometry": {"coordinates":[-79.6101608276,43.5722885132],"type":"Point"}
}