{
  "type": "Feature",
  "properties": {
    "addr:full":"Nelson BC V1L 6B9",
    "addr:postcode":"bc v1l 6b9",
    "iso:country":"CA",
    "sg:city":"Nelson",
    "sg:classifiers":[
        {
            "category":"Autos & Motor Vehicles",
            "subcategory":"Auto Supplies",
            "type":"Retail Goods"
        }
    ],
    "sg:phone":"+1 250 505 5115",
    "sg:postcode":"V1L 6B9",
    "sg:province":"BC",
    "sg:tags":[
        "repairing",
        "automobile"
    ],
    "wof:name":"O K Tire & Auto Svc",
    "wof:placetype":"venue"
},
  "geometry": {"coordinates":[-117.301872,49.491943],"type":"Point"}
}