{
  "type": "Feature",
  "properties": {
    "addr:full":"4521 Southclark Pl Gloucester ON K1T 3V2",
    "addr:housenumber":"4521",
    "addr:postcode":"k1t 3v2",
    "addr:street":"Southclark Pl",
    "iso:country":"CA",
    "sg:address":"4521 Southclark Pl",
    "sg:city":"Gloucester",
    "sg:classifiers":[
        {
            "category":"Home & Garden",
            "subcategory":"Home Furnishings",
            "type":"Retail Goods"
        }
    ],
    "sg:phone":"+1 613 822 8626",
    "sg:postcode":"K1T 3V2",
    "sg:province":"ON",
    "sg:tags":[
        "utensil",
        "cooking"
    ],
    "wof:name":"Ashton Green Ltd",
    "wof:placetype":"venue"
},
  "geometry": {"coordinates":[-75.6180267334,45.3210487366],"type":"Point"}
}