{
  "type": "Feature",
  "properties": {
    "addr:full":"315 Lincoln Rd Waterloo ON N2J 4H7",
    "addr:housenumber":"315",
    "addr:postcode":"n2j 4h7",
    "addr:street":"Lincoln Rd",
    "iso:country":"CA",
    "sg:address":"315 Lincoln Rd",
    "sg:city":"Waterloo",
    "sg:classifiers":[
        {
            "category":"Banks & Credit Unions",
            "subcategory":"Bank",
            "type":"Services"
        }
    ],
    "sg:phone":"+1 519 884 9290",
    "sg:postcode":"N2J 4H7",
    "sg:province":"ON",
    "wof:name":"Cibc",
    "wof:placetype":"venue"
},
  "geometry": {"coordinates":[-80.506393,43.48267],"type":"Point"}
}