{
  "type": "Feature",
  "properties": {
    "iso:country":"CA",
    "sg:address":"315 Lincoln Rd",
    "sg:city":"Waterloo",
    "sg:classifiers":[
        {
            "category":"Banks & Credit Unions",
            "subcategory":"Bank",
            "type":"Services"
        }
    ],
    "sg:phone":"+1 519 884 9290",
    "sg:postcode":"N2J 4H7",
    "sg:province":"ON",
    "wof:name":"Cibc",
    "wof:placetype":"venue"
},
  "geometry": {"coordinates":[-80.506393,43.48267],"type":"Point"}
}