{
  "type": "Feature",
  "properties": {
    "addr:full":"1682A Victoria Park Ave North York ON M1R 1P7",
    "addr:housenumber":"1682a",
    "addr:postcode":"m1r 1p7",
    "addr:street":"Victoria Park Ave",
    "iso:country":"CA",
    "sg:address":"1682A Victoria Park Ave",
    "sg:city":"North York",
    "sg:classifiers":[
        {
            "category":"Professional",
            "subcategory":"Art Services",
            "type":"Services"
        }
    ],
    "sg:phone":"+1 416 757 1701",
    "sg:postcode":"M1R 1P7",
    "sg:province":"ON",
    "sg:tags":[
        "graphic",
        "designer"
    ],
    "wof:name":"Graphart Reproductions",
    "wof:placetype":"venue"
},
  "geometry": {"coordinates":[-79.3059387207,43.7324333191],"type":"Point"}
}