{
  "type": "Feature",
  "properties": {
    "addr:full":"Ohsweken ON N0A 1M0",
    "addr:postcode":"n0a 1m0",
    "iso:country":"CA",
    "sg:city":"Ohsweken",
    "sg:classifiers":[
        {
            "category":"Health Services",
            "subcategory":"Doctor",
            "type":"Services"
        }
    ],
    "sg:phone":"+1 519 445 2252",
    "sg:postcode":"N0A 1M0",
    "sg:province":"ON",
    "sg:tags":[
        "clinic"
    ],
    "wof:name":"Gane Yohs Community Health Ctr",
    "wof:placetype":"venue"
},
  "geometry": {"coordinates":[-80.118797,43.069046],"type":"Point"}
}