{
  "type": "Feature",
  "properties": {
    "addr:full":"240 Nelson Hill Rd Milford Station NS B0N 1Y0",
    "addr:housenumber":"240",
    "addr:postcode":"b0n 1y0",
    "addr:street":"Nelson Hill Rd",
    "iso:country":"CA",
    "sg:address":"240 Nelson Hill Rd",
    "sg:city":"Milford Station",
    "sg:classifiers":[
        {
            "category":"Building & Trades",
            "subcategory":"Landscaping Services",
            "type":"Services"
        }
    ],
    "sg:phone":"+1 902 758 3873",
    "sg:postcode":"B0N 1Y0",
    "sg:province":"NS",
    "sg:tags":[
        "equipment",
        "supply",
        "topsoil"
    ],
    "wof:name":"T Q Topsoil Trucking",
    "wof:placetype":"venue"
},
  "geometry": {"coordinates":[-63.438847,45.040562],"type":"Point"}
}