{
  "type": "Feature",
  "properties": {
    "addr:full":"1347 Fletcher Rd Saskatoon SK S7M 5H5",
    "addr:housenumber":"1347",
    "addr:postcode":"s7m 5h5",
    "addr:street":"Fletcher Rd",
    "iso:country":"CA",
    "sg:address":"1347 Fletcher Rd",
    "sg:city":"Saskatoon",
    "sg:classifiers":[
        {
            "category":"Arena",
            "subcategory":"Sports Club",
            "type":"Entertainment"
        }
    ],
    "sg:phone":"+1 306 978 8777",
    "sg:postcode":"S7M 5H5",
    "sg:province":"SK",
    "sg:tags":[
        "athletic",
        "fields",
        "stadium"
    ],
    "wof:name":"Harold Latrace Arena",
    "wof:placetype":"venue"
},
  "geometry": {"coordinates":[-106.703941,52.109337],"type":"Point"}
}