{
  "type": "Feature",
  "properties": {
    "iso:country":"CA",
    "sg:address":"3950 Boul Sir-Wilfrid-Laurier",
    "sg:city":"Saint-Hubert",
    "sg:classifiers":[
        {
            "category":"Real Estate",
            "subcategory":"Real Estate Operator",
            "type":"Services"
        }
    ],
    "sg:phone":"+1 450 676 0221",
    "sg:postcode":"J3Y 5Y9",
    "sg:province":"QC",
    "sg:tags":[
        "mobile",
        "home",
        "community"
    ],
    "wof:name":"Modlivco Inc",
    "wof:placetype":"venue"
},
  "geometry": {"coordinates":[-73.44519042970001,45.5063896179],"type":"Point"}
}