{
  "type": "Feature",
  "properties": {
    "iso:country":"CA",
    "sg:address":"73 Water St",
    "sg:city":"Campbellton",
    "sg:classifiers":[
        {
            "category":"Retail",
            "subcategory":"Laundry & Dry Cleaning",
            "type":"Services"
        }
    ],
    "sg:phone":"+1 506 753 3391",
    "sg:postcode":"E3N 1A9",
    "sg:province":"NB",
    "sg:tags":[
        "cleaners"
    ],
    "wof:name":"Chaleur Cleaners Ltd",
    "wof:placetype":"venue"
},
  "geometry": {"coordinates":[-66.6713562012,48.0086669922],"type":"Point"}
}