{
  "type": "Feature",
  "properties": {
    "addr:full":"1435 Boul Dr Albiny-Paquette Mont-Laurier QC J9L 1M8",
    "addr:housenumber":"1435",
    "addr:postcode":"j9l 1m8",
    "addr:street":"Boul Dr Albiny-Paquette",
    "iso:country":"CA",
    "sg:address":"1435 Boul Dr Albiny-Paquette",
    "sg:city":"Mont-Laurier",
    "sg:classifiers":[
        {
            "category":"Autos & Motor Vehicles",
            "subcategory":"Automobile Sales",
            "type":"Retail Goods"
        }
    ],
    "sg:phone":"+1 819 623 6331",
    "sg:postcode":"J9L 1M8",
    "sg:province":"QC",
    "sg:tags":[
        "car",
        "wrecker"
    ],
    "wof:name":"Performance Remorquage",
    "wof:placetype":"venue"
},
  "geometry": {"coordinates":[-75.469292,46.552692],"type":"Point"}
}