{
  "type": "Feature",
  "properties": {
    "addr:full":"4005 Highway 16 W Prince George BC V2N 1P3",
    "addr:housenumber":"4005",
    "addr:postcode":"v2n 1p3",
    "addr:street":"Highway 16 W",
    "iso:country":"CA",
    "sg:address":"4005 Highway 16 W",
    "sg:city":"Prince George",
    "sg:classifiers":[
        {
            "category":"Food & Beverages",
            "subcategory":"Groceries & Convenience Stores",
            "type":"Retail Goods"
        }
    ],
    "sg:phone":"+1 250 562 5773",
    "sg:postcode":"V2N 1P3",
    "sg:province":"BC",
    "sg:tags":[
        "grocer"
    ],
    "wof:name":"Mr G",
    "wof:placetype":"venue"
},
  "geometry": {"coordinates":[-122.80294799799999,53.8601570129],"type":"Point"}
}