{
  "type": "Feature",
  "properties": {
    "iso:country":"CA",
    "sg:address":"607 Third Ave",
    "sg:city":"New Westminster",
    "sg:classifiers":[
        {
            "category":"Professional",
            "subcategory":"Accounting & Tax Preparation",
            "type":"Services"
        }
    ],
    "sg:phone":"+1 604 525 5343",
    "sg:postcode":"V3M 1N4",
    "sg:province":"BC",
    "sg:tags":[
        "consultant"
    ],
    "wof:name":"Adams & CO",
    "wof:placetype":"venue"
},
  "geometry": {"coordinates":[-122.91497039799999,49.2085914612],"type":"Point"}
}