{
  "type": "Feature",
  "properties": {
    "addr:full":"260 Shoemaker St Kitchener ON N2E 3E1",
    "addr:housenumber":"260",
    "addr:postcode":"n2e 3e1",
    "addr:street":"Shoemaker St",
    "iso:country":"CA",
    "sg:address":"260 Shoemaker St",
    "sg:city":"Kitchener",
    "sg:classifiers":[
        {
            "category":"Utilities",
            "subcategory":"Refuse",
            "type":"Services"
        }
    ],
    "sg:phone":"+1 519 748 5348",
    "sg:postcode":"N2E 3E1",
    "sg:province":"ON",
    "sg:tags":[
        "waste",
        "liquid",
        "removal"
    ],
    "wof:name":"Quantex Technologies",
    "wof:placetype":"venue"
},
  "geometry": {"coordinates":[-80.46777299999999,43.405327],"type":"Point"}
}