{
  "type": "Feature",
  "properties": {
    "addr:full":"15 Savona Dr Etobicoke ON M8W 4T9",
    "addr:housenumber":"15",
    "addr:postcode":"m8w 4t9",
    "addr:street":"Savona Dr",
    "iso:country":"CA",
    "sg:address":"15 Savona Dr",
    "sg:city":"Etobicoke",
    "sg:classifiers":[
        {
            "category":"Manufacturing",
            "subcategory":"Tools & Machinery",
            "type":"Manufacturing & Wholesale Goods"
        }
    ],
    "sg:phone":"+1 416 201 8098",
    "sg:postcode":"M8W 4T9",
    "sg:province":"ON",
    "sg:tags":[
        "die",
        "maker"
    ],
    "wof:name":"Reed Rico Pcc Specialty",
    "wof:placetype":"venue"
},
  "geometry": {"coordinates":[-79.5536270142,43.6077880859],"type":"Point"}
}