{
  "type": "Feature",
  "properties": {
    "iso:country":"CA",
    "sg:address":"24 Cross St",
    "sg:city":"Welland",
    "sg:classifiers":[
        {
            "category":"Shopping",
            "subcategory":"Clothing, Apparel, & Fashions",
            "type":"Retail Goods"
        }
    ],
    "sg:phone":"+1 905 735 7248",
    "sg:postcode":"L3B 3G1",
    "sg:province":"ON",
    "sg:tags":[
        "furnishing"
    ],
    "wof:name":"Dietrick's",
    "wof:placetype":"venue"
},
  "geometry": {"coordinates":[-79.2479171753,42.9918518066],"type":"Point"}
}