{
  "type": "Feature",
  "properties": {
    "addr:full":"Freshwater Pb NL A0B 1W0",
    "addr:postcode":"a0b 1w0",
    "iso:country":"CA",
    "sg:city":"Freshwater Pb",
    "sg:classifiers":[
        {
            "category":"Arts & Performance",
            "subcategory":"Theater",
            "type":"Entertainment"
        }
    ],
    "sg:phone":"+1 709 227 2299",
    "sg:postcode":"A0B 1W0",
    "sg:province":"NL",
    "wof:name":"Placentia Area Theatre",
    "wof:placetype":"venue"
},
  "geometry": {"coordinates":[-53.9959220886,47.2723007202],"type":"Point"}
}