{
  "type": "Feature",
  "properties": {
    "addr:full":"3537 Bouvier Ch Bourget ON K0A 1E0",
    "addr:housenumber":"3537",
    "addr:postcode":"k0a 1e0",
    "addr:street":"Bouvier Ch Bourget",
    "iso:country":"CA",
    "sg:address":"3537 Bouvier Ch",
    "sg:city":"Bourget",
    "sg:classifiers":[
        {
            "category":"Professional",
            "subcategory":"Art Services",
            "type":"Services"
        }
    ],
    "sg:phone":"+1 613 487 3583",
    "sg:postcode":"K0A 1E0",
    "sg:province":"ON",
    "sg:tags":[
        "graphic",
        "designer"
    ],
    "wof:name":"Le Page Grafix",
    "wof:placetype":"venue"
},
  "geometry": {"coordinates":[-75.19395400000001,45.436367],"type":"Point"}
}