{
  "type": "Feature",
  "properties": {
    "addr:full":"245 Charlesworth Ave Cochrane AB T4C 2B7",
    "addr:housenumber":"245",
    "addr:postcode":"t4c 2b7",
    "addr:street":"Charlesworth Ave",
    "iso:country":"CA",
    "sg:address":"245 Charlesworth Ave",
    "sg:city":"Cochrane",
    "sg:classifiers":[
        {
            "category":"Retail",
            "subcategory":"Auto Repair",
            "type":"Services"
        }
    ],
    "sg:phone":"+1 403 932 5917",
    "sg:postcode":"T4C 2B7",
    "sg:province":"AB",
    "sg:tags":[
        "body",
        "automobile",
        "painting"
    ],
    "wof:name":"Cochrane Collision Repair",
    "wof:placetype":"venue"
},
  "geometry": {"coordinates":[-114.467499,51.184715],"type":"Point"}
}