{
  "type": "Feature",
  "properties": {
    "addr:full":"960 Frenette Ave Moncton NB E1H 2P8",
    "addr:housenumber":"960",
    "addr:postcode":"e1h 2p8",
    "addr:street":"Frenette Ave",
    "iso:country":"CA",
    "sg:address":"960 Frenette Ave",
    "sg:city":"Moncton",
    "sg:classifiers":[
        {
            "category":"Wholesale",
            "subcategory":"Construction Materials",
            "type":"Manufacturing & Wholesale Goods"
        }
    ],
    "sg:phone":"+1 506 857 9977",
    "sg:postcode":"E1H 2P8",
    "sg:province":"NB",
    "sg:tags":[
        "building"
    ],
    "wof:name":"Lighthouse Lumber Wholesalers",
    "wof:placetype":"venue"
},
  "geometry": {"coordinates":[-64.778267,46.088364],"type":"Point"}
}