{
  "type": "Feature",
  "properties": {
    "addr:full":"Montreal QC H2V 2A1",
    "addr:postcode":"h2v 2a1",
    "iso:country":"CA",
    "sg:city":"Montreal",
    "sg:classifiers":[
        {
            "category":"Real Estate",
            "subcategory":"Real Estate Operator",
            "type":"Services"
        }
    ],
    "sg:phone":"+1 514 277 5873",
    "sg:postcode":"H2V 2A1",
    "sg:province":"QC",
    "sg:tags":[
        "apartment"
    ],
    "wof:name":"Terrasse Outremont",
    "wof:placetype":"venue"
},
  "geometry": {"coordinates":[-73.59144592289999,45.516292572],"type":"Point"}
}