{
  "type": "Feature",
  "properties": {
    "addr:full":"614 Main St Three Hills AB T0M 2A0",
    "addr:housenumber":"614",
    "addr:postcode":"t0m 2a0",
    "addr:street":"Main St",
    "iso:country":"CA",
    "sg:address":"614 Main St",
    "sg:city":"Three Hills",
    "sg:classifiers":[
        {
            "category":"Manufacturing",
            "subcategory":"Printing",
            "type":"Manufacturing & Wholesale Goods"
        }
    ],
    "sg:phone":"+1 403 443 5345",
    "sg:postcode":"T0M 2A0",
    "sg:province":"AB",
    "sg:tags":[
        "printer"
    ],
    "wof:name":"Inkkers Fine Printing",
    "wof:placetype":"venue"
},
  "geometry": {"coordinates":[-113.266021728,51.7041893005],"type":"Point"}
}