{
  "type": "Feature",
  "properties": {
    "addr:full":"1222 Main St Smithers BC V0J 2N0",
    "addr:housenumber":"1222",
    "addr:postcode":"v0j 2n0",
    "addr:street":"Main St",
    "iso:country":"CA",
    "sg:address":"1222 Main St",
    "sg:city":"Smithers",
    "sg:classifiers":[
        {
            "category":"Banks & Credit Unions",
            "subcategory":"Bank",
            "type":"Services"
        }
    ],
    "sg:phone":"+1 250 877 5060",
    "sg:postcode":"V0J 2N0",
    "sg:province":"BC",
    "wof:name":"Cibc",
    "wof:placetype":"venue"
},
  "geometry": {"coordinates":[-127.17009,54.78027],"type":"Point"}
}