{
  "type": "Feature",
  "properties": {
    "iso:country":"CA",
    "sg:address":"33529 1st Ave",
    "sg:city":"Mission",
    "sg:classifiers":[
        {
            "category":"Organizations",
            "subcategory":"Professional Association",
            "type":"Services"
        }
    ],
    "sg:phone":"+1 604 826 5937",
    "sg:postcode":"V2V 1H1",
    "sg:province":"BC",
    "wof:name":"Mission Folk Music Festival",
    "wof:placetype":"venue"
},
  "geometry": {"coordinates":[-122.296836853,49.134475708],"type":"Point"}
}