{
  "type": "Feature",
  "properties": {
    "addr:full":"1804 13th Ave W #1 Vancouver BC V6J 2H3",
    "addr:housenumber":"1804",
    "addr:postcode":"v6j 2h3",
    "addr:street":"13Th Ave W # 1",
    "iso:country":"CA",
    "sg:address":"1804 13th Ave W #1",
    "sg:city":"Vancouver",
    "sg:classifiers":[
        {
            "category":"Professional",
            "type":"Services"
        }
    ],
    "sg:phone":"+1 604 734 9590",
    "sg:postcode":"V6J 2H3",
    "sg:province":"BC",
    "sg:tags":[
        "multimedia",
        "establishment"
    ],
    "wof:name":"Reality Software Ltd",
    "wof:placetype":"venue"
},
  "geometry": {"coordinates":[-123.146179,49.259804],"type":"Point"}
}