{
  "type": "Feature",
  "properties": {
    "addr:full":"3173 Rue Milleret Sainte-Foy QC G1X 1N6",
    "addr:housenumber":"3173",
    "addr:postcode":"g1x 1n6",
    "addr:street":"Rue Milleret",
    "iso:country":"CA",
    "sg:address":"3173 Rue Milleret",
    "sg:city":"Sainte-Foy",
    "sg:classifiers":[
        {
            "category":"Building & Trades",
            "subcategory":"Landscaping Services",
            "type":"Services"
        }
    ],
    "sg:phone":"+1 418 659 4256",
    "sg:postcode":"G1X 1N6",
    "sg:province":"QC",
    "sg:tags":[
        "landscape",
        "contractor"
    ],
    "wof:name":"A Rousseau Paysagiste Enr",
    "wof:placetype":"venue"
},
  "geometry": {"coordinates":[-71.31568900000001,46.774395],"type":"Point"}
}