{
  "type": "Feature",
  "properties": {
    "addr:full":"12710 Winterburn Rd NW Edmonton AB T5S 2B9",
    "addr:housenumber":"12710",
    "addr:postcode":"t5s 2b9",
    "addr:street":"Winterburn Rd Nw",
    "iso:country":"CA",
    "sg:address":"12710 Winterburn Rd NW",
    "sg:city":"Edmonton",
    "sg:classifiers":[
        {
            "category":"Building & Trades",
            "subcategory":"Construction",
            "type":"Services"
        }
    ],
    "sg:phone":"+1 780 460 0440",
    "sg:postcode":"T5S 2B9",
    "sg:province":"AB",
    "sg:tags":[
        "finishing",
        "wood",
        "refinishing"
    ],
    "wof:name":"Coatings Unlimited",
    "wof:placetype":"venue"
},
  "geometry": {"coordinates":[-113.689331,53.584595],"type":"Point"}
}