{
  "type": "Feature",
  "properties": {
    "addr:full":"220 Murray St Peterborough ON K9H 2S8",
    "addr:housenumber":"220",
    "addr:postcode":"k9h 2s8",
    "addr:street":"Murray St",
    "iso:country":"CA",
    "sg:address":"220 Murray St",
    "sg:city":"Peterborough",
    "sg:classifiers":[
        {
            "category":"Education",
            "subcategory":"School",
            "type":"Public Place"
        }
    ],
    "sg:phone":"+1 705 742 8442",
    "sg:postcode":"K9H 2S8",
    "sg:province":"ON",
    "wof:name":"Children's Montessori School",
    "wof:placetype":"venue"
},
  "geometry": {"coordinates":[-78.32254,44.308445],"type":"Point"}
}