{
  "type": "Feature",
  "properties": {
    "addr:full":"Durham ON N0G 1R0",
    "addr:postcode":"n0g 1r0",
    "iso:country":"CA",
    "sg:city":"Durham",
    "sg:classifiers":[
        {
            "category":"Wholesale",
            "subcategory":"Meat",
            "type":"Manufacturing & Wholesale Goods"
        }
    ],
    "sg:phone":"+1 519 369 6328",
    "sg:postcode":"N0G 1R0",
    "sg:province":"ON",
    "sg:tags":[
        "packer"
    ],
    "wof:name":"Lantz Meat Market",
    "wof:placetype":"venue"
},
  "geometry": {"coordinates":[-80.7847290039,44.1759490967],"type":"Point"}
}