{
  "type": "Feature",
  "properties": {
    "addr:full":"Edmonton AB T5H 4B9",
    "addr:postcode":"t5h 4b9",
    "iso:country":"CA",
    "sg:city":"Edmonton",
    "sg:classifiers":[
        {
            "category":"Health Services",
            "subcategory":"Doctor",
            "type":"Services"
        }
    ],
    "sg:phone":"+1 780 423 5832",
    "sg:postcode":"T5H 4B9",
    "sg:province":"AB",
    "sg:tags":[
        "physician",
        "surgeon"
    ],
    "wof:name":"Estey, Eric P MD",
    "wof:placetype":"venue"
},
  "geometry": {"coordinates":[-113.493843,53.557331],"type":"Point"}
}