{
  "type": "Feature",
  "properties": {
    "addr:full":"86 Rue Lombardy Grand-Sault/Grand Falls NB E3Z 2V6",
    "addr:housenumber":"86",
    "addr:postcode":"e3z 2v6",
    "addr:street":"Rue Lombardy",
    "iso:country":"CA",
    "sg:address":"86 Rue Lombardy",
    "sg:city":"Grand-Sault/Grand Falls",
    "sg:classifiers":[
        {
            "category":"Building & Trades",
            "subcategory":"Construction",
            "type":"Services"
        }
    ],
    "sg:phone":"+1 506 473 3688",
    "sg:postcode":"E3Z 2V6",
    "sg:province":"NB",
    "sg:tags":[
        "contractor",
        "general"
    ],
    "wof:name":"Mario Rioux Construction",
    "wof:placetype":"venue"
},
  "geometry": {"coordinates":[-67.780991,47.059261],"type":"Point"}
}