{
  "type": "Feature",
  "properties": {
    "addr:full":"240 Garafraxa St N Durham ON N0G 1R0",
    "addr:housenumber":"240",
    "addr:postcode":"n0g 1r0",
    "addr:street":"Garafraxa St N",
    "iso:country":"CA",
    "sg:address":"240 Garafraxa St N",
    "sg:city":"Durham",
    "sg:classifiers":[
        {
            "category":"Education",
            "subcategory":"Library",
            "type":"Public Place"
        }
    ],
    "sg:phone":"+1 519 369 2107",
    "sg:postcode":"N0G 1R0",
    "sg:province":"ON",
    "wof:name":"Durham Public Library",
    "wof:placetype":"venue"
},
  "geometry": {"coordinates":[-80.81939697270001,44.1788749695],"type":"Point"}
}