{
  "type": "Feature",
  "properties": {
    "addr:full":"1340 Northmount Dr NW Calgary AB T2L 0E6",
    "addr:housenumber":"1340",
    "addr:postcode":"t2l 0e6",
    "addr:street":"Northmount Dr Nw",
    "iso:country":"CA",
    "sg:address":"1340 Northmount Dr NW",
    "sg:city":"Calgary",
    "sg:classifiers":[
        {
            "category":"Education",
            "subcategory":"Special Training",
            "type":"Public Place"
        }
    ],
    "sg:phone":"+1 403 289 1787",
    "sg:postcode":"T2L 0E6",
    "sg:province":"AB",
    "sg:tags":[
        "school",
        "instruction",
        "art"
    ],
    "wof:name":"Northwest Art Studio",
    "wof:placetype":"venue"
},
  "geometry": {"coordinates":[-114.128967285,51.0932121277],"type":"Point"}
}