{
  "type": "Feature",
  "properties": {
    "addr:full":"Nanaimo BC V9R 2X3",
    "addr:postcode":"v9r 2x3",
    "iso:country":"CA",
    "sg:city":"Nanaimo",
    "sg:classifiers":[
        {
            "category":"Insurance",
            "subcategory":"Insurance Agent",
            "type":"Services"
        }
    ],
    "sg:phone":"+1 250 741 3175",
    "sg:postcode":"V9R 2X3",
    "sg:province":"BC",
    "wof:name":"Coastal Community Insurance",
    "wof:placetype":"venue"
},
  "geometry": {"coordinates":[-123.936256,49.16597],"type":"Point"}
}