{
  "type": "Feature",
  "properties": {
    "addr:full":"587 Rue DE LA Riviere Cowansville QC J2K 3G6",
    "addr:housenumber":"587",
    "addr:postcode":"j2k 3g6",
    "addr:street":"Rue De La Riviere",
    "iso:country":"CA",
    "sg:address":"587 Rue DE LA Riviere",
    "sg:city":"Cowansville",
    "sg:classifiers":[
        {
            "category":"Utilities",
            "subcategory":"Refuse",
            "type":"Services"
        }
    ],
    "sg:phone":"+1 450 266 6544",
    "sg:postcode":"J2K 3G6",
    "sg:province":"QC",
    "sg:tags":[
        "garbage",
        "collection"
    ],
    "wof:name":"Services Sanitaires Brodeur",
    "wof:placetype":"venue"
},
  "geometry": {"coordinates":[-72.798157,45.210358],"type":"Point"}
}