{
  "type": "Feature",
  "properties": {
    "addr:full":"183 Boul Industriel Saint-Eustache QC J7R 5P2",
    "addr:housenumber":"183",
    "addr:postcode":"j7r 5p2",
    "addr:street":"Boul Industriel",
    "iso:country":"CA",
    "sg:address":"183 Boul Industriel",
    "sg:city":"Saint-Eustache",
    "sg:classifiers":[
        {
            "category":"Cinema",
            "subcategory":"Movie Rental",
            "type":"Entertainment"
        }
    ],
    "sg:phone":"+1 450 472 8922",
    "sg:postcode":"J7R 5P2",
    "sg:province":"QC",
    "sg:tags":[
        "leasing",
        "video",
        "disc",
        "tape"
    ],
    "wof:name":"Video Des Patriotes Enr",
    "wof:placetype":"venue"
},
  "geometry": {"coordinates":[-73.923965,45.568466],"type":"Point"}
}