{
  "type": "Feature",
  "properties": {
    "addr:full":"2991 Grauman Rd Roberts Creek BC V0N 2W1",
    "addr:housenumber":"2991",
    "addr:postcode":"v0n 2w1",
    "addr:street":"Grauman Rd",
    "iso:country":"CA",
    "sg:address":"2991 Grauman Rd",
    "sg:city":"Roberts Creek",
    "sg:classifiers":[
        {
            "category":"Social Services",
            "type":"Services"
        }
    ],
    "sg:phone":"+1 604 740 0982",
    "sg:postcode":"V0N 2W1",
    "sg:province":"BC",
    "sg:tags":[
        "counselor",
        "marriage",
        "family"
    ],
    "wof:name":"Creative Counselling Svc",
    "wof:placetype":"venue"
},
  "geometry": {"coordinates":[-123.606460571,49.4132614136],"type":"Point"}
}