{
  "type": "Feature",
  "properties": {
    "addr:full":"700 Boul Rene-Levesque Drummondville QC J2C 7A7",
    "addr:housenumber":"700",
    "addr:postcode":"j2c 7a7",
    "addr:street":"Boul Rene-Levesque",
    "iso:country":"CA",
    "sg:address":"700 Boul Rene-Levesque",
    "sg:city":"Drummondville",
    "sg:classifiers":[
        {
            "category":"Shopping",
            "subcategory":"Clothing, Apparel, & Fashions",
            "type":"Retail Goods"
        }
    ],
    "sg:phone":"+1 819 474 2497",
    "sg:postcode":"J2C 7A7",
    "sg:province":"QC",
    "sg:tags":[
        "boutique",
        "furnishing"
    ],
    "wof:name":"Boutique Impact",
    "wof:placetype":"venue"
},
  "geometry": {"coordinates":[-72.513969,45.90012],"type":"Point"}
}