{
  "type": "Feature",
  "properties": {
    "addr:full":"Montreal QC H2V 4G3",
    "addr:postcode":"h2v 4g3",
    "iso:country":"CA",
    "sg:city":"Montreal",
    "sg:classifiers":[
        {
            "category":"Shopping",
            "subcategory":"Computers & Home Electronics",
            "type":"Retail Goods"
        }
    ],
    "sg:phone":"+1 514 495 7770",
    "sg:postcode":"H2V 4G3",
    "sg:province":"QC",
    "sg:tags":[
        "equipment",
        "dealer"
    ],
    "wof:name":"Tech Pc Experts Inc",
    "wof:placetype":"venue"
},
  "geometry": {"coordinates":[-73.64715576170001,45.5361213684],"type":"Point"}
}