{
  "type": "Feature",
  "properties": {
    "addr:full":"14 Wilma St St Agatha ON N0B 2L0",
    "addr:housenumber":"14",
    "addr:postcode":"n0b 2l0",
    "addr:street":"Wilma St",
    "iso:country":"CA",
    "sg:address":"14 Wilma St",
    "sg:city":"St Agatha",
    "sg:classifiers":[
        {
            "category":"Building & Trades",
            "subcategory":"Plumbing",
            "type":"Services"
        }
    ],
    "sg:phone":"+1 519 747 3474",
    "sg:postcode":"N0B 2L0",
    "sg:province":"ON",
    "sg:tags":[
        "contractor"
    ],
    "wof:name":"Pjr Plumbing & Heating",
    "wof:placetype":"venue"
},
  "geometry": {"coordinates":[-80.63385,43.434452],"type":"Point"}
}