{
  "type": "Feature",
  "properties": {
    "addr:full":"114 Falconer Dr Mississauga ON L5N 1B4",
    "addr:housenumber":"114",
    "addr:postcode":"l5n 1b4",
    "addr:street":"Falconer Dr",
    "iso:country":"CA",
    "sg:address":"114 Falconer Dr",
    "sg:city":"Mississauga",
    "sg:classifiers":[
        {
            "category":"Social Services",
            "subcategory":"Child Care",
            "type":"Services"
        }
    ],
    "sg:phone":"+1 905 826 3191",
    "sg:postcode":"L5N 1B4",
    "sg:province":"ON",
    "sg:tags":[
        "government"
    ],
    "wof:name":"Streetsville Child Development",
    "wof:placetype":"venue"
},
  "geometry": {"coordinates":[-79.72949199999999,43.602318],"type":"Point"}
}