{
  "type": "Feature",
  "properties": {
    "addr:full":"731 North Rd Gibsons BC V0N 1V9",
    "addr:housenumber":"731",
    "addr:postcode":"v0n 1v9",
    "addr:street":"North Rd",
    "iso:country":"CA",
    "sg:address":"731 North Rd",
    "sg:city":"Gibsons",
    "sg:classifiers":[
        {
            "category":"Shopping",
            "subcategory":"Used Merchandise",
            "type":"Retail Goods"
        }
    ],
    "sg:phone":"+1 604 886 2811",
    "sg:postcode":"V0N 1V9",
    "sg:province":"BC",
    "sg:tags":[
        "shop",
        "thrift"
    ],
    "wof:name":"Gibsons Thrift Shoppe",
    "wof:placetype":"venue"
},
  "geometry": {"coordinates":[-123.513741,49.40947],"type":"Point"}
}