{
  "type": "Feature",
  "properties": {
    "addr:full":"22 Cardigan St Guelph ON N1E 3K2",
    "addr:housenumber":"22",
    "addr:postcode":"n1e 3k2",
    "addr:street":"Cardigan St",
    "iso:country":"CA",
    "sg:address":"22 Cardigan St",
    "sg:city":"Guelph",
    "sg:classifiers":[
        {
            "category":"Manufacturing",
            "subcategory":"Signs",
            "type":"Manufacturing & Wholesale Goods"
        }
    ],
    "sg:phone":"+1 519 837 8932",
    "sg:postcode":"N1E 3K2",
    "sg:province":"ON",
    "wof:name":"Bulldog Signs",
    "wof:placetype":"venue"
},
  "geometry": {"coordinates":[-80.25238,43.548721],"type":"Point"}
}