{
  "type": "Feature",
  "properties": {
    "addr:full":"Lethbridge AB T1J 0N4",
    "addr:postcode":"t1j 0n4",
    "iso:country":"CA",
    "sg:city":"Lethbridge",
    "sg:classifiers":[
        {
            "category":"Professional",
            "subcategory":"Lawyer & Legal Services",
            "type":"Services"
        }
    ],
    "sg:phone":"+1 403 380 2499",
    "sg:postcode":"T1J 0N4",
    "sg:province":"AB",
    "sg:tags":[
        "attorney"
    ],
    "wof:name":"Richard A Low Law Office",
    "wof:placetype":"venue"
},
  "geometry": {"coordinates":[-112.83979034399999,49.6944541931],"type":"Point"}
}