{
  "type": "Feature",
  "properties": {
    "addr:full":"350 Ch Du Grand-Pre L'Acadie QC J2Y 1E3",
    "addr:housenumber":"350",
    "addr:postcode":"j2y 1e3",
    "addr:street":"Ch Du Grand-Pre",
    "iso:country":"CA",
    "sg:address":"350 Ch Du Grand-Pre",
    "sg:city":"L'Acadie",
    "sg:classifiers":[
        {
            "category":"Restaurant",
            "type":"Food & Drink"
        }
    ],
    "sg:phone":"+1 450 347 5274",
    "sg:postcode":"J2Y 1E3",
    "sg:province":"QC",
    "wof:name":"Bergeries DE L'Acadie",
    "wof:placetype":"venue"
},
  "geometry": {"coordinates":[-73.34961699999999,45.333996],"type":"Point"}
}