{
  "type": "Feature",
  "properties": {
    "iso:country":"CA",
    "sg:address":"350 Ch Du Grand-Pre",
    "sg:city":"L'Acadie",
    "sg:classifiers":[
        {
            "category":"Restaurant",
            "type":"Food & Drink"
        }
    ],
    "sg:phone":"+1 450 347 5274",
    "sg:postcode":"J2Y 1E3",
    "sg:province":"QC",
    "wof:name":"Bergeries DE L'Acadie",
    "wof:placetype":"venue"
},
  "geometry": {"coordinates":[-73.349617,45.333996],"type":"Point"}
}