{
  "type": "Feature",
  "properties": {
    "addr:full":"Didsbury AB T0M 0W0",
    "addr:postcode":"t0m 0w0",
    "iso:country":"CA",
    "sg:city":"Didsbury",
    "sg:classifiers":[
        {
            "category":"Restaurant",
            "type":"Food & Drink"
        }
    ],
    "sg:phone":"+1 403 335 3390",
    "sg:postcode":"T0M 0W0",
    "sg:province":"AB",
    "wof:name":"Macy's Family Restaurant",
    "wof:placetype":"venue"
},
  "geometry": {"coordinates":[-114.133888,51.660683],"type":"Point"}
}