{
  "type": "Feature",
  "properties": {
    "addr:full":"67 Rue Papineau Hull QC J8X 1T9",
    "addr:housenumber":"67",
    "addr:postcode":"j8x 1t9",
    "addr:street":"Rue Papineau",
    "iso:country":"CA",
    "sg:address":"67 Rue Papineau",
    "sg:city":"Hull",
    "sg:classifiers":[
        {
            "category":"Retail",
            "subcategory":"Laundry & Dry Cleaning",
            "type":"Services"
        }
    ],
    "sg:phone":"+1 819 777 1611",
    "sg:postcode":"J8X 1T9",
    "sg:province":"QC",
    "sg:tags":[
        "cleaners"
    ],
    "wof:name":"Nettoyeurs St Louis",
    "wof:placetype":"venue"
},
  "geometry": {"coordinates":[-75.72265625,45.4306793213],"type":"Point"}
}