{
  "type": "Feature",
  "properties": {
    "addr:full":"194 Avondale Ave Stratford ON N5A 6N4",
    "addr:housenumber":"194",
    "addr:postcode":"n5a 6n4",
    "addr:street":"Avondale Ave",
    "iso:country":"CA",
    "sg:address":"194 Avondale Ave",
    "sg:city":"Stratford",
    "sg:classifiers":[
        {
            "category":"Organizations",
            "subcategory":"Religious Organization",
            "type":"Services"
        }
    ],
    "sg:phone":"+1 519 271 7946",
    "sg:postcode":"N5A 6N4",
    "sg:province":"ON",
    "sg:tags":[
        "church"
    ],
    "wof:name":"Central United Church",
    "wof:placetype":"venue"
},
  "geometry": {"coordinates":[-80.9925003052,43.3775863647],"type":"Point"}
}