{
  "type": "Feature",
  "properties": {
    "iso:country":"CA",
    "sg:address":"46 13th St",
    "sg:city":"Weyburn",
    "sg:classifiers":[
        {
            "category":"Professional",
            "subcategory":"Management & Consulting",
            "type":"Services"
        }
    ],
    "sg:phone":"+1 306 842 5490",
    "sg:postcode":"S4H 1K8",
    "sg:province":"SK",
    "sg:tags":[
        "consultant",
        "safety"
    ],
    "wof:name":"Prairie Wide Safety Ltd",
    "wof:placetype":"venue"
},
  "geometry": {"coordinates":[-103.839706421,49.6587371826],"type":"Point"}
}