{
  "type": "Feature",
  "properties": {
    "addr:full":"344 King St Bridgewater NS B4V 1A9",
    "addr:housenumber":"344",
    "addr:postcode":"b4v 1a9",
    "addr:street":"King St",
    "iso:country":"CA",
    "sg:address":"344 King St",
    "sg:city":"Bridgewater",
    "sg:classifiers":[
        {
            "category":"Professional",
            "subcategory":"Computer Services",
            "type":"Services"
        }
    ],
    "sg:phone":"+1 902 543 5274",
    "sg:postcode":"B4V 1A9",
    "sg:province":"NS",
    "sg:tags":[
        "internet"
    ],
    "wof:name":"Tallships Internet",
    "wof:placetype":"venue"
},
  "geometry": {"coordinates":[-64.515236,44.375084],"type":"Point"}
}