{
  "type": "Feature",
  "properties": {
    "addr:full":"571 Rang 3 O Saint-Anaclet QC G0K 1H0",
    "addr:housenumber":"571",
    "addr:postcode":"g0k 1h0",
    "addr:street":"Rang 3 O Saint-Anaclet",
    "iso:country":"CA",
    "sg:address":"571 Rang 3 O",
    "sg:city":"Saint-Anaclet",
    "sg:classifiers":[
        {
            "category":"Building & Trades",
            "subcategory":"Plumbing",
            "type":"Services"
        }
    ],
    "sg:phone":"+1 418 724 6792",
    "sg:postcode":"G0K 1H0",
    "sg:province":"QC",
    "sg:tags":[
        "ventilating",
        "conditioning",
        "contractor",
        "system",
        "air"
    ],
    "wof:name":"Camec Inc",
    "wof:placetype":"venue"
},
  "geometry": {"coordinates":[-68.4098815918,48.4665107727],"type":"Point"}
}