{
  "type": "Feature",
  "properties": {
    "iso:country":"CA",
    "sg:address":"5241 Calgary Trail NW # 300",
    "sg:city":"Edmonton",
    "sg:classifiers":[
        {
            "category":"Banks & Credit Unions",
            "subcategory":"Bank",
            "type":"Services"
        }
    ],
    "sg:phone":"+1 780 435 3411",
    "sg:postcode":"T6H 5G8",
    "sg:province":"AB",
    "wof:name":"Hsbc Bank Canada",
    "wof:placetype":"venue"
},
  "geometry": {"coordinates":[-113.495132446,53.4893074036],"type":"Point"}
}