{
  "type": "Feature",
  "properties": {
    "addr:full":"Calgary AB T3C 0K1",
    "addr:postcode":"t3c 0k1",
    "iso:country":"CA",
    "sg:city":"Calgary",
    "sg:classifiers":[
        {
            "category":"Professional",
            "subcategory":"Management & Consulting",
            "type":"Services"
        }
    ],
    "sg:phone":"+1 403 245 5661",
    "sg:postcode":"T3C 0K1",
    "sg:province":"AB",
    "sg:tags":[
        "archaeologist"
    ],
    "wof:name":"Fma Heritage Resources Conslnt",
    "wof:placetype":"venue"
},
  "geometry": {"coordinates":[-114.09980011,51.0442123413],"type":"Point"}
}