{
  "type": "Feature",
  "properties": {
    "addr:full":"543 Wyandotte St E Windsor ON N9A 3J1",
    "addr:housenumber":"543",
    "addr:postcode":"n9a 3j1",
    "addr:street":"Wyandotte St E",
    "iso:country":"CA",
    "sg:address":"543 Wyandotte St E",
    "sg:city":"Windsor",
    "sg:classifiers":[
        {
            "category":"Restaurant",
            "type":"Food & Drink"
        }
    ],
    "sg:phone":"+1 519 252 3886",
    "sg:postcode":"N9A 3J1",
    "sg:province":"ON",
    "wof:name":"Malic's Restaurant & Deli",
    "wof:placetype":"venue"
},
  "geometry": {"coordinates":[-83.029205,42.316669],"type":"Point"}
}