{
  "type": "Feature",
  "properties": {
    "addr:full":"306 Midland Ave Midland ON L4R 3K6",
    "addr:housenumber":"306",
    "addr:postcode":"l4r 3k6",
    "addr:street":"Midland Ave",
    "iso:country":"CA",
    "sg:address":"306 Midland Ave",
    "sg:city":"Midland",
    "sg:classifiers":[
        {
            "category":"Health Services",
            "subcategory":"Doctor",
            "type":"Services"
        }
    ],
    "sg:phone":"+1 705 526 6011",
    "sg:postcode":"L4R 3K6",
    "sg:province":"ON",
    "sg:tags":[
        "physician",
        "surgeon"
    ],
    "wof:name":"Seaman, Ken MD",
    "wof:placetype":"venue"
},
  "geometry": {"coordinates":[-79.883797,44.750137],"type":"Point"}
}