{
  "type": "Feature",
  "properties": {
    "iso:country":"CA",
    "sg:address":"540 1st Ave",
    "sg:city":"Ladysmith",
    "sg:classifiers":[
        {
            "category":"Banks & Credit Unions",
            "subcategory":"Bank",
            "type":"Services"
        }
    ],
    "sg:phone":"+1 250 245 2265",
    "sg:postcode":"V9G 1A1",
    "sg:province":"BC",
    "wof:name":"Cibc",
    "wof:placetype":"venue"
},
  "geometry": {"coordinates":[-123.818328857,48.9937591553],"type":"Point"}
}