{
  "type": "Feature",
  "properties": {
    "iso:country":"CA",
    "sg:address":"131 Rue Maple Dale",
    "sg:city":"East Farnham",
    "sg:classifiers":[
        {
            "category":"Freight",
            "type":"Transportation"
        }
    ],
    "sg:phone":"+1 450 263 2631",
    "sg:postcode":"J2K 4M7",
    "sg:province":"QC",
    "sg:tags":[
        "trucking"
    ],
    "wof:name":"Transport Rpr Inc",
    "wof:placetype":"venue"
},
  "geometry": {"coordinates":[-72.7807846069,45.2336196899],"type":"Point"}
}