{
  "type": "Feature",
  "properties": {
    "iso:country":"CA",
    "sg:address":"4211 Rue Hochelaga",
    "sg:city":"Montreal",
    "sg:classifiers":[
        {
            "category":"Social Services",
            "subcategory":"Job Training",
            "type":"Services"
        }
    ],
    "sg:phone":"+1 514 252 0133",
    "sg:postcode":"H1V 1B8",
    "sg:province":"QC",
    "sg:tags":[
        "rehabilitation"
    ],
    "wof:name":"Centre DE Readaptation G Major",
    "wof:placetype":"venue"
},
  "geometry": {"coordinates":[-73.547737,45.553616],"type":"Point"}
}