{
  "type": "Feature",
  "properties": {
    "iso:country":"CA",
    "sg:address":"76 Magill Dr",
    "sg:city":"Ajax",
    "sg:classifiers":[
        {
            "category":"Professional",
            "subcategory":"Accounting & Tax Preparation",
            "type":"Services"
        }
    ],
    "sg:phone":"+1 905 426 2458",
    "sg:postcode":"L1T 3K7",
    "sg:province":"ON",
    "sg:tags":[
        "return",
        "filing"
    ],
    "wof:name":"In Touch Accounting & Fincl",
    "wof:placetype":"venue"
},
  "geometry": {"coordinates":[-79.035416,43.868168],"type":"Point"}
}