{
  "type": "Feature",
  "properties": {
    "addr:full":"862 Richmond St London ON N6A 3H8",
    "addr:housenumber":"862",
    "addr:postcode":"n6a 3h8",
    "addr:street":"Richmond St",
    "iso:country":"CA",
    "sg:address":"862 Richmond St",
    "sg:city":"London",
    "sg:classifiers":[
        {
            "category":"Health Services",
            "subcategory":"Hospital",
            "type":"Services"
        }
    ],
    "sg:phone":"+1 519 433 2023",
    "sg:postcode":"N6A 3H8",
    "sg:province":"ON",
    "sg:tags":[
        "mental"
    ],
    "wof:name":"London Mental Health Crisis",
    "wof:placetype":"venue"
},
  "geometry": {"coordinates":[-81.2548294067,42.9991035461],"type":"Point"}
}