{
  "type": "Feature",
  "properties": {
    "addr:full":"5630 48 Ave SE Salmon Arm BC V1E 1X2",
    "addr:housenumber":"5630",
    "addr:postcode":"v1e 1x2",
    "addr:street":"48 Ave Se",
    "iso:country":"CA",
    "sg:address":"5630 48 Ave SE",
    "sg:city":"Salmon Arm",
    "sg:classifiers":[
        {
            "category":"Building & Trades",
            "subcategory":"Electrical",
            "type":"Services"
        }
    ],
    "sg:phone":"+1 250 833 0341",
    "sg:postcode":"V1E 1X2",
    "sg:province":"BC",
    "sg:tags":[
        "electric",
        "contractor"
    ],
    "wof:name":"Glenn Power Contractors Ltd",
    "wof:placetype":"venue"
},
  "geometry": {"coordinates":[-119.221283,50.664238],"type":"Point"}
}