{
  "type": "Feature",
  "properties": {
    "addr:full":"16049 Beach Rd Surrey BC V3S 9R6",
    "addr:housenumber":"16049",
    "addr:postcode":"v3s 9r6",
    "addr:street":"Beach Rd",
    "iso:country":"CA",
    "sg:address":"16049 Beach Rd",
    "sg:city":"Surrey",
    "sg:classifiers":[
        {
            "category":"Organizations",
            "subcategory":"Community Association",
            "type":"Services"
        }
    ],
    "sg:phone":"+1 604 536 3101",
    "sg:postcode":"V3S 9R6",
    "sg:province":"BC",
    "sg:tags":[
        "native"
    ],
    "wof:name":"Semiahmoo First Nation",
    "wof:placetype":"venue"
},
  "geometry": {"coordinates":[-122.759552,49.007568],"type":"Point"}
}