{
  "type": "Feature",
  "properties": {
    "addr:full":"1095 Erin St Winnipeg MB R3G 2X1",
    "addr:housenumber":"1095",
    "addr:postcode":"r3g 2x1",
    "addr:street":"Erin St",
    "iso:country":"CA",
    "sg:address":"1095 Erin St",
    "sg:city":"Winnipeg",
    "sg:classifiers":[
        {
            "category":"Wholesale",
            "subcategory":"Hardware",
            "type":"Manufacturing & Wholesale Goods"
        }
    ],
    "sg:phone":"+1 204 775 5887",
    "sg:postcode":"R3G 2X1",
    "sg:province":"MB",
    "sg:tags":[
        "refrigerating"
    ],
    "wof:name":"Refrigerative Supply",
    "wof:placetype":"venue"
},
  "geometry": {"coordinates":[-97.18407440190001,49.8953437805],"type":"Point"}
}