{
  "type": "Feature",
  "properties": {
    "addr:full":"Scarborough ON M1S 5B8",
    "addr:postcode":"m1s 5b8",
    "iso:country":"CA",
    "sg:city":"Scarborough",
    "sg:classifiers":[
        {
            "category":"Restaurant",
            "type":"Food & Drink"
        }
    ],
    "sg:phone":"+1 416 297 6492",
    "sg:postcode":"M1S 5B8",
    "sg:province":"ON",
    "wof:name":"Yogi's Noodles",
    "wof:placetype":"venue"
},
  "geometry": {"coordinates":[-79.2711029053,43.7937393188],"type":"Point"}
}