{
  "type": "Feature",
  "properties": {
    "addr:full":"468 King St New Waterford NS B1H 3Y6",
    "addr:housenumber":"468",
    "addr:postcode":"b1h 3y6",
    "addr:street":"King St",
    "iso:country":"CA",
    "sg:address":"468 King St",
    "sg:city":"New Waterford",
    "sg:classifiers":[
        {
            "category":"Restaurant",
            "type":"Food & Drink"
        }
    ],
    "sg:phone":"+1 902 862 7800",
    "sg:postcode":"B1H 3Y6",
    "sg:province":"NS",
    "wof:name":"Micky D's",
    "wof:placetype":"venue"
},
  "geometry": {"coordinates":[-60.082954,46.24741],"type":"Point"}
}