{
  "type": "Feature",
  "properties": {
    "addr:full":"82 Berkeley St Toronto ON M5A 2W7",
    "addr:housenumber":"82",
    "addr:postcode":"m5a 2w7",
    "addr:street":"Berkeley St",
    "iso:country":"CA",
    "sg:address":"82 Berkeley St",
    "sg:city":"Toronto",
    "sg:classifiers":[
        {
            "category":"Manufacturing",
            "subcategory":"Printing",
            "type":"Manufacturing & Wholesale Goods"
        }
    ],
    "sg:phone":"+1 416 368 2737",
    "sg:postcode":"M5A 2W7",
    "sg:province":"ON",
    "sg:tags":[
        "printer"
    ],
    "wof:name":"Alexander Lithographers Ltd",
    "wof:placetype":"venue"
},
  "geometry": {"coordinates":[-79.3650970459,43.6533050537],"type":"Point"}
}