{
  "type": "Feature",
  "properties": {
    "iso:country":"CA",
    "sg:address":"2225 Meadowpine Blvd",
    "sg:city":"Mississauga",
    "sg:classifiers":[
        {
            "category":"Wholesale",
            "subcategory":"Chemicals & Plastics",
            "type":"Manufacturing & Wholesale Goods"
        }
    ],
    "sg:phone":"+1 905 814 6511",
    "sg:postcode":"L5N 7P2",
    "sg:province":"ON",
    "sg:tags":[
        "adhesive",
        "glue"
    ],
    "wof:name":"Loctite Canada Inc",
    "wof:placetype":"venue"
},
  "geometry": {"coordinates":[-79.7709579468,43.6044540405],"type":"Point"}
}