{
  "type": "Feature",
  "properties": {
    "addr:full":"5542 Ann St Manotick ON K4M 1A3",
    "addr:housenumber":"5542",
    "addr:postcode":"k4m 1a3",
    "addr:street":"Ann St",
    "iso:country":"CA",
    "sg:address":"5542 Ann St",
    "sg:city":"Manotick",
    "sg:classifiers":[
        {
            "category":"Health Services",
            "subcategory":"Health Practitioner",
            "type":"Services"
        }
    ],
    "sg:phone":"+1 613 692 1847",
    "sg:postcode":"K4M 1A3",
    "sg:province":"ON",
    "sg:tags":[
        "acupuncture",
        "physiotherapist"
    ],
    "wof:name":"Ann Street Physiotherapy Clnc",
    "wof:placetype":"venue"
},
  "geometry": {"coordinates":[-75.68523399999999,45.224728],"type":"Point"}
}