{
  "type": "Feature",
  "properties": {
    "addr:full":"Charlottetown Lab NL A0K 5Y0",
    "addr:postcode":"a0k 5y0",
    "iso:country":"CA",
    "sg:city":"Charlottetown Lab",
    "sg:classifiers":[
        {
            "category":"Restaurant",
            "type":"Food & Drink"
        }
    ],
    "sg:phone":"+1 709 949 0388",
    "sg:postcode":"A0K 5Y0",
    "sg:province":"NL",
    "wof:name":"Wentzell's Take-Out & Rstrnt",
    "wof:placetype":"venue"
},
  "geometry": {"coordinates":[-56.139359,52.769733],"type":"Point"}
}