{
  "type": "Feature",
  "properties": {
    "addr:full":"533 58 Ave SE Calgary AB T2H 0P7",
    "addr:postcode":"t2h 0p7",
    "addr:street":"533 58 Ave Se",
    "iso:country":"CA",
    "sg:address":"533 58 Ave SE",
    "sg:city":"Calgary",
    "sg:classifiers":[
        {
            "category":"Shopping",
            "subcategory":"Used Merchandise",
            "type":"Retail Goods"
        }
    ],
    "sg:phone":"+1 403 253 7880",
    "sg:postcode":"T2H 0P7",
    "sg:province":"AB",
    "sg:tags":[
        "antique"
    ],
    "wof:name":"Consignment Gallery Inc",
    "wof:placetype":"venue"
},
  "geometry": {"coordinates":[-114.052841187,51.0008850098],"type":"Point"}
}