{
  "type": "Feature",
  "properties": {
    "addr:full":"180 St Anthony St Annapolis Royal NS B0S 1A0",
    "addr:housenumber":"180",
    "addr:postcode":"b0s 1a0",
    "addr:street":"St Anthony St",
    "iso:country":"CA",
    "sg:address":"180 St Anthony St",
    "sg:city":"Annapolis Royal",
    "sg:classifiers":[
        {
            "category":"Food & Beverages",
            "subcategory":"Liquor & Beverages",
            "type":"Retail Goods"
        }
    ],
    "sg:phone":"+1 902 532 2153",
    "sg:postcode":"B0S 1A0",
    "sg:province":"NS",
    "sg:tags":[
        "store"
    ],
    "wof:name":"Nova Scotia Liquor Commission",
    "wof:placetype":"venue"
},
  "geometry": {"coordinates":[-65.516685,44.74548],"type":"Point"}
}