{
  "type": "Feature",
  "properties": {
    "addr:full":"381 Richmond Rd Ottawa ON K2A 0E7",
    "addr:housenumber":"381",
    "addr:postcode":"k2a 0e7",
    "addr:street":"Richmond Rd",
    "iso:country":"CA",
    "sg:address":"381 Richmond Rd",
    "sg:city":"Ottawa",
    "sg:classifiers":[
        {
            "category":"Organizations",
            "subcategory":"Religious Organization",
            "type":"Services"
        }
    ],
    "sg:phone":"+1 613 722 5252",
    "sg:postcode":"K2A 0E7",
    "sg:province":"ON",
    "sg:tags":[
        "church"
    ],
    "wof:name":"Ottawa Chinese Bible Church",
    "wof:placetype":"venue"
},
  "geometry": {"coordinates":[-75.7558288574,45.3913421631],"type":"Point"}
}