{
  "type": "Feature",
  "properties": {
    "addr:full":"60 Front St Manitou MB R0G 1G0",
    "addr:housenumber":"60",
    "addr:postcode":"r0g 1g0",
    "addr:street":"Front St",
    "iso:country":"CA",
    "sg:address":"60 Front St",
    "sg:city":"Manitou",
    "sg:classifiers":[
        {
            "category":"Autos & Motor Vehicles",
            "subcategory":"Fuel & Gas Station",
            "type":"Retail Goods"
        }
    ],
    "sg:phone":"+1 204 242 2416",
    "sg:postcode":"R0G 1G0",
    "sg:province":"MB",
    "sg:tags":[
        "oil"
    ],
    "wof:name":"P J Droux Garage Ltd",
    "wof:placetype":"venue"
},
  "geometry": {"coordinates":[-98.53465300000001,49.236721],"type":"Point"}
}