{
  "type": "Feature",
  "properties": {
    "addr:full":"32830 Mission Way Mission BC V2V 5X9",
    "addr:housenumber":"32830",
    "addr:postcode":"v2v 5x9",
    "addr:street":"Mission Way",
    "iso:country":"CA",
    "sg:address":"32830 Mission Way",
    "sg:city":"Mission",
    "sg:classifiers":[
        {
            "category":"Manufacturing",
            "subcategory":"Wood Products",
            "type":"Manufacturing & Wholesale Goods"
        }
    ],
    "sg:phone":"+1 604 826 3938",
    "sg:postcode":"V2V 5X9",
    "sg:province":"BC",
    "sg:tags":[
        "pallet",
        "skid"
    ],
    "wof:name":"Verbeek Pallet Supply",
    "wof:placetype":"venue"
},
  "geometry": {"coordinates":[-122.31464386,49.1306915283],"type":"Point"}
}