{
  "type": "Feature",
  "properties": {
    "addr:full":"Channel-Port-Aux-Basques NL A0M 1C0",
    "addr:postcode":"a0m 1c0",
    "iso:country":"CA",
    "sg:city":"Channel-Port-Aux-Basques",
    "sg:classifiers":[
        {
            "category":"Shopping",
            "subcategory":"Florist",
            "type":"Retail Goods"
        }
    ],
    "sg:phone":"+1 709 695 3611",
    "sg:postcode":"A0M 1C0",
    "sg:province":"NL",
    "wof:name":"Pitcher Plant Flower Shop",
    "wof:placetype":"venue"
},
  "geometry": {"coordinates":[-59.142372,47.573521],"type":"Point"}
}