{
  "type": "Feature",
  "properties": {
    "addr:full":"516 Rte DE Sainte-Marguerite-M Dolbeau-Mistassini QC G8L 5P7",
    "addr:housenumber":"516",
    "addr:postcode":"g8l 5p7",
    "addr:street":"Rte De Sainte-Marguerite-M",
    "iso:country":"CA",
    "sg:address":"516 Rte DE Sainte-Marguerite-M",
    "sg:city":"Dolbeau-Mistassini",
    "sg:classifiers":[
        {
            "category":"Social Services",
            "type":"Services"
        }
    ],
    "sg:phone":"+1 418 276 8337",
    "sg:postcode":"G8L 5P7",
    "sg:province":"QC",
    "sg:tags":[
        "handicapped",
        "organization",
        "welfare"
    ],
    "wof:name":"Groupe Espoir Dolbeau Inc",
    "wof:placetype":"venue"
},
  "geometry": {"coordinates":[-72.241989,48.813931],"type":"Point"}
}