{
  "type": "Feature",
  "properties": {
    "iso:country":"CA",
    "sg:address":"222 Main St",
    "sg:city":"Spruce Grove",
    "sg:classifiers":[
        {
            "category":"Social Services",
            "subcategory":"Child Care",
            "type":"Services"
        }
    ],
    "sg:phone":"+1 780 962 8756",
    "sg:postcode":"T7X 3A3",
    "sg:province":"AB",
    "wof:name":"Creative Children's Daycare",
    "wof:placetype":"venue"
},
  "geometry": {"coordinates":[-113.90271758999999,53.5427970886],"type":"Point"}
}