{
  "type": "Feature",
  "properties": {
    "addr:full":"566 Rue Salaberry Beauharnois QC J6N 2E1",
    "addr:housenumber":"566",
    "addr:postcode":"j6n 2e1",
    "addr:street":"Rue Salaberry",
    "iso:country":"CA",
    "sg:address":"566 Rue Salaberry",
    "sg:city":"Beauharnois",
    "sg:classifiers":[
        {
            "category":"Health Services",
            "subcategory":"Nursing And Care Facility",
            "type":"Services"
        }
    ],
    "sg:phone":"+1 450 225 3035",
    "sg:postcode":"J6N 2E1",
    "sg:province":"QC",
    "sg:tags":[
        "home",
        "retirement",
        "community"
    ],
    "wof:name":"Residence Marie-Eve",
    "wof:placetype":"venue"
},
  "geometry": {"coordinates":[-73.866348,45.307613],"type":"Point"}
}