{
  "type": "Feature",
  "properties": {
    "addr:full":"560 King St W Hamilton ON L8P 1C2",
    "addr:housenumber":"560",
    "addr:postcode":"l8p 1c2",
    "addr:street":"King St W",
    "iso:country":"CA",
    "sg:address":"560 King St W",
    "sg:city":"Hamilton",
    "sg:classifiers":[
        {
            "category":"Food & Beverages",
            "subcategory":"Bakery",
            "type":"Retail Goods"
        }
    ],
    "sg:phone":"+1 905 529 9673",
    "sg:postcode":"L8P 1C2",
    "sg:province":"ON",
    "sg:tags":[
        "baker"
    ],
    "wof:name":"Portuguese Bakery",
    "wof:placetype":"venue"
},
  "geometry": {"coordinates":[-79.88563499999999,43.261608],"type":"Point"}
}