{
  "type": "Feature",
  "properties": {
    "addr:full":"PO Box 660 Wembley AB T0H 3S0",
    "addr:housenumber":"po;660",
    "addr:postcode":"t0h 3s0",
    "addr:street":"Box",
    "iso:country":"CA",
    "sg:address":"PO Box 660",
    "sg:city":"Wembley",
    "sg:classifiers":[
        {
            "category":"Mining & Drilling",
            "type":"Manufacturing & Wholesale Goods"
        }
    ],
    "sg:phone":"+1 780 354 2262",
    "sg:postcode":"T0H 3S0",
    "sg:province":"AB",
    "sg:tags":[
        "consultant",
        "oil",
        "gas"
    ],
    "wof:name":"D Madison Well Site Super",
    "wof:placetype":"venue"
},
  "geometry": {"coordinates":[-119.13919799999999,55.164795],"type":"Point"}
}