{
  "type": "Feature",
  "properties": {
    "iso:country":"CA",
    "sg:city":"Calgary",
    "sg:classifiers":[
        {
            "category":"Restaurant",
            "type":"Food & Drink"
        }
    ],
    "sg:phone":"+1 403 233 0229",
    "sg:postcode":"T2R 1J8",
    "sg:province":"AB",
    "sg:tags":[
        "pizza"
    ],
    "wof:name":"Stardust Pizza",
    "wof:placetype":"venue"
},
  "geometry": {"coordinates":[-114.074348,51.042824],"type":"Point"}
}