{
  "type": "Feature",
  "properties": {
    "addr:full":"13 Rue Du Chene Sainte-Marguerite-Esterel QC J0T 1L0",
    "addr:housenumber":"13",
    "addr:postcode":"j0t 1l0",
    "addr:street":"Rue Du Chene Sainte-Marguerite-Esterel",
    "iso:country":"CA",
    "sg:address":"13 Rue Du Chene",
    "sg:city":"Sainte-Marguerite-Esterel",
    "sg:classifiers":[
        {
            "category":"Building & Trades",
            "subcategory":"Construction",
            "type":"Services"
        }
    ],
    "sg:phone":"+1 450 228 4410",
    "sg:postcode":"J0T 1L0",
    "sg:province":"QC",
    "sg:tags":[
        "repairing",
        "remodeling",
        "contractor"
    ],
    "wof:name":"Miron & Freres Renovations Enr",
    "wof:placetype":"venue"
},
  "geometry": {"coordinates":[-74.018959,46.042545],"type":"Point"}
}