{
  "type": "Feature",
  "properties": {
    "addr:full":"42587 Truman Line St Thomas ON N5P 3T1",
    "addr:housenumber":"42587",
    "addr:postcode":"n5p 3t1",
    "addr:street":"Truman Line",
    "iso:country":"CA",
    "sg:address":"42587 Truman Line",
    "sg:city":"St Thomas",
    "sg:classifiers":[
        {
            "category":"Building & Trades",
            "subcategory":"Construction",
            "type":"Services"
        }
    ],
    "sg:phone":"+1 519 633 2590",
    "sg:postcode":"N5P 3T1",
    "sg:province":"ON",
    "sg:tags":[
        "painter"
    ],
    "wof:name":"Lambeth Painting Inc",
    "wof:placetype":"venue"
},
  "geometry": {"coordinates":[-81.19314575200001,42.7789382935],"type":"Point"}
}