{
  "type": "Feature",
  "properties": {
    "addr:full":"2337 Rue DE L'Ile-Des-Lys Lachenaie QC J6W 6A2",
    "addr:housenumber":"2337",
    "addr:postcode":"j6w 6a2",
    "addr:street":"Rue De L'Ile-Des-Lys",
    "iso:country":"CA",
    "sg:address":"2337 Rue DE L'Ile-Des-Lys",
    "sg:city":"Lachenaie",
    "sg:classifiers":[
        {
            "category":"Professional",
            "subcategory":"Art Services",
            "type":"Services"
        }
    ],
    "sg:phone":"+1 450 492 4646",
    "sg:postcode":"J6W 6A2",
    "sg:province":"QC",
    "sg:tags":[
        "graphic",
        "designer"
    ],
    "wof:name":"Groupe Stylidee Inc",
    "wof:placetype":"venue"
},
  "geometry": {"coordinates":[-73.580406,45.702591],"type":"Point"}
}