{
  "type": "Feature",
  "properties": {
    "addr:full":"Mississauga ON L4T 1G1",
    "addr:postcode":"l4t 1g1",
    "iso:country":"CA",
    "sg:city":"Mississauga",
    "sg:classifiers":[
        {
            "category":"Manufacturing",
            "subcategory":"Rubber & Plastics",
            "type":"Manufacturing & Wholesale Goods"
        }
    ],
    "sg:phone":"+1 905 677 2777",
    "sg:postcode":"L4T 1G1",
    "sg:province":"ON",
    "wof:name":"Plexi Design",
    "wof:placetype":"venue"
},
  "geometry": {"coordinates":[-79.65705871580001,43.7016067505],"type":"Point"}
}