{
  "type": "Feature",
  "properties": {
    "addr:full":"Toronto ON M5E 1A7",
    "addr:postcode":"m5e 1a7",
    "iso:country":"CA",
    "sg:city":"Toronto",
    "sg:classifiers":[
        {
            "category":"Professional",
            "subcategory":"Art Services",
            "type":"Services"
        }
    ],
    "sg:phone":"+1 416 365 9898",
    "sg:postcode":"M5E 1A7",
    "sg:province":"ON",
    "sg:tags":[
        "photographer"
    ],
    "wof:name":"Hal Roth Photography Inc",
    "wof:placetype":"venue"
},
  "geometry": {"coordinates":[-79.3740386963,43.6470603943],"type":"Point"}
}