{
  "type": "Feature",
  "properties": {
    "addr:full":"1126 Eglinton Ave W Toronto ON M6C 2E2",
    "addr:housenumber":"1126",
    "addr:postcode":"m6c 2e2",
    "addr:street":"Eglinton Ave W",
    "iso:country":"CA",
    "sg:address":"1126 Eglinton Ave W",
    "sg:city":"Toronto",
    "sg:classifiers":[
        {
            "category":"Health Services",
            "subcategory":"Chiropractor",
            "type":"Services"
        }
    ],
    "sg:phone":"+1 416 782 2113",
    "sg:postcode":"M6C 2E2",
    "sg:province":"ON",
    "wof:name":"Forest Hill Chiropractor",
    "wof:placetype":"venue"
},
  "geometry": {"coordinates":[-79.432258606,43.6996879578],"type":"Point"}
}