{
  "type": "Feature",
  "properties": {
    "addr:full":"519 Mississauga St Niagara on the Lake ON L0S 1J0",
    "addr:housenumber":"519",
    "addr:postcode":"l0s 1j0",
    "addr:street":"Mississauga St;On",
    "iso:country":"CA",
    "sg:address":"519 Mississauga St",
    "sg:city":"Niagara on the Lake",
    "sg:classifiers":[
        {
            "category":"Health Services",
            "subcategory":"Chiropractor",
            "type":"Services"
        }
    ],
    "sg:phone":"+1 905 468 2442",
    "sg:postcode":"L0S 1J0",
    "sg:province":"ON",
    "wof:name":"Haigh Chiropractic Office",
    "wof:placetype":"venue"
},
  "geometry": {"coordinates":[-79.08538799999999,43.251507],"type":"Point"}
}