{
  "type": "Feature",
  "properties": {
    "iso:country":"CA",
    "sg:address":"4921 Rue Des Peupliers",
    "sg:city":"LA Dore",
    "sg:classifiers":[
        {
            "category":"Health Services",
            "subcategory":"Nursing And Care Facility",
            "type":"Services"
        }
    ],
    "sg:phone":"+1 418 256 3851",
    "sg:postcode":"G8J 1E7",
    "sg:province":"QC",
    "sg:tags":[
        "home",
        "rest"
    ],
    "wof:name":"Centre D'Accueil LA Dore Inc",
    "wof:placetype":"venue"
},
  "geometry": {"coordinates":[-72.64836883540001,48.7127342224],"type":"Point"}
}