{
  "type": "Feature",
  "properties": {
    "addr:full":"610 47th St E Saskatoon SK S7K 5X3",
    "addr:housenumber":"610",
    "addr:postcode":"s7k 5x3",
    "addr:street":"47Th St E",
    "iso:country":"CA",
    "sg:address":"610 47th St E",
    "sg:city":"Saskatoon",
    "sg:classifiers":[
        {
            "category":"Recreation",
            "type":"Entertainment"
        }
    ],
    "sg:phone":"+1 306 664 7030",
    "sg:postcode":"S7K 5X3",
    "sg:province":"SK",
    "sg:tags":[
        "instruction",
        "gymnastic"
    ],
    "wof:name":"Taiso Gymnastic Club",
    "wof:placetype":"venue"
},
  "geometry": {"coordinates":[-106.65992,52.166759],"type":"Point"}
}