{
  "type": "Feature",
  "properties": {
    "addr:full":"10713 125 St NW Edmonton AB T5M 0L3",
    "addr:housenumber":"10713",
    "addr:postcode":"t5m 0l3",
    "addr:street":"125 St Nw",
    "iso:country":"CA",
    "sg:address":"10713 125 St NW",
    "sg:city":"Edmonton",
    "sg:classifiers":[
        {
            "category":"Professional",
            "subcategory":"Art Services",
            "type":"Services"
        }
    ],
    "sg:phone":"+1 780 452 1767",
    "sg:postcode":"T5M 0L3",
    "sg:province":"AB",
    "sg:tags":[
        "graphic",
        "designer"
    ],
    "wof:name":"Jellyfish Design",
    "wof:placetype":"venue"
},
  "geometry": {"coordinates":[-113.537445068,53.5513343811],"type":"Point"}
}