{
  "type": "Feature",
  "properties": {
    "addr:full":"41 South Front St Belleville ON K8N 2Y5",
    "addr:housenumber":"41",
    "addr:postcode":"k8n 2y5",
    "addr:street":"South Front St",
    "iso:country":"CA",
    "sg:address":"41 South Front St",
    "sg:city":"Belleville",
    "sg:classifiers":[
        {
            "category":"Health Services",
            "subcategory":"Doctor",
            "type":"Services"
        }
    ],
    "sg:phone":"+1 613 962 8211",
    "sg:postcode":"K8N 2Y5",
    "sg:province":"ON",
    "sg:tags":[
        "physician",
        "surgeon"
    ],
    "wof:name":"Gwizdal, Mary MD",
    "wof:placetype":"venue"
},
  "geometry": {"coordinates":[-77.37776947019999,44.1554870605],"type":"Point"}
}