{
  "type": "Feature",
  "properties": {
    "addr:full":"320 W T Hill Blvd S #5 Lethbridge AB T1J 4W9",
    "addr:housenumber":"320",
    "addr:postcode":"t1j 4w9",
    "addr:street":"W T Hill Blvd S # 5",
    "iso:country":"CA",
    "sg:address":"320 W T Hill Blvd S #5",
    "sg:city":"Lethbridge",
    "sg:classifiers":[
        {
            "category":"Professional",
            "subcategory":"Business Services",
            "type":"Services"
        }
    ],
    "sg:phone":"+1 403 381 6111",
    "sg:postcode":"T1J 4W9",
    "sg:province":"AB",
    "sg:tags":[
        "inspection"
    ],
    "wof:name":"Alberta Permit Pro Inc",
    "wof:placetype":"venue"
},
  "geometry": {"coordinates":[-112.787674,49.695885],"type":"Point"}
}