{
  "type": "Feature",
  "properties": {
    "addr:full":"1111 Center Line Rd Elmsdale PE C0B 1K0",
    "addr:housenumber":"1111",
    "addr:postcode":"c0b 1k0",
    "addr:street":"Center Line Rd",
    "iso:country":"CA",
    "sg:address":"1111 Center Line Rd",
    "sg:city":"Elmsdale",
    "sg:classifiers":[
        {
            "category":"Building & Trades",
            "subcategory":"Construction",
            "type":"Services"
        }
    ],
    "sg:phone":"+1 902 853 3131",
    "sg:postcode":"C0B 1K0",
    "sg:province":"PE",
    "sg:tags":[
        "cabinet",
        "carpenter",
        "maker"
    ],
    "wof:name":"R Jeffrey's Carpentry",
    "wof:placetype":"venue"
},
  "geometry": {"coordinates":[-64.138412,46.820358],"type":"Point"}
}