{
  "type": "Feature",
  "properties": {
    "addr:full":"Winnipeg MB R3E 0B9",
    "addr:postcode":"r3e 0b9",
    "iso:country":"CA",
    "sg:city":"Winnipeg",
    "sg:classifiers":[
        {
            "category":"Health Services",
            "subcategory":"Doctor",
            "type":"Services"
        }
    ],
    "sg:phone":"+1 204 774 1655",
    "sg:postcode":"R3E 0B9",
    "sg:province":"MB",
    "sg:tags":[
        "dentist"
    ],
    "wof:name":"Sargent Dental Ctr",
    "wof:placetype":"venue"
},
  "geometry": {"coordinates":[-97.169593811,49.8970413208],"type":"Point"}
}