{
  "type": "Feature",
  "properties": {
    "iso:country":"CA",
    "sg:city":"Vancouver",
    "sg:classifiers":[
        {
            "category":"Shopping",
            "subcategory":"Jewelry",
            "type":"Retail Goods"
        }
    ],
    "sg:phone":"+1 604 266 2301",
    "sg:postcode":"V5Z 2M9",
    "sg:province":"BC",
    "sg:tags":[
        "jeweler"
    ],
    "wof:name":"Birks Jewellers",
    "wof:placetype":"venue"
},
  "geometry": {"coordinates":[-123.117675781,49.2335510254],"type":"Point"}
}