{
  "type": "Feature",
  "properties": {
    "addr:full":"Calgary AB T2T 1Z4",
    "addr:postcode":"t2t 1z4",
    "iso:country":"CA",
    "sg:city":"Calgary",
    "sg:classifiers":[
        {
            "category":"Health Services",
            "subcategory":"Optometrist",
            "type":"Services"
        }
    ],
    "sg:phone":"+1 403 685 5500",
    "sg:postcode":"T2T 1Z4",
    "sg:province":"AB",
    "wof:name":"Lebenhagen, Jan OD",
    "wof:placetype":"venue"
},
  "geometry": {"coordinates":[-114.107391357,51.0241241455],"type":"Point"}
}