{
  "type": "Feature",
  "properties": {
    "addr:full":"136 Bonaccord St Moncton NB E1C 5L5",
    "addr:housenumber":"136",
    "addr:postcode":"e1c 5l5",
    "addr:street":"Bonaccord St",
    "iso:country":"CA",
    "sg:address":"136 Bonaccord St",
    "sg:city":"Moncton",
    "sg:classifiers":[
        {
            "category":"Organizations",
            "subcategory":"Religious Organization",
            "type":"Services"
        }
    ],
    "sg:phone":"+1 506 389 3024",
    "sg:postcode":"E1C 5L5",
    "sg:province":"NB",
    "wof:name":"Freres DE L'Instruction",
    "wof:placetype":"venue"
},
  "geometry": {"coordinates":[-64.784271,46.091076],"type":"Point"}
}