{
  "type": "Feature",
  "properties": {
    "iso:country":"CA",
    "sg:address":"136 Bonaccord St",
    "sg:city":"Moncton",
    "sg:classifiers":[
        {
            "category":"Organizations",
            "subcategory":"Religious Organization",
            "type":"Services"
        }
    ],
    "sg:phone":"+1 506 389 3024",
    "sg:postcode":"E1C 5L5",
    "sg:province":"NB",
    "wof:name":"Freres DE L'Instruction",
    "wof:placetype":"venue"
},
  "geometry": {"coordinates":[-64.784271,46.091076],"type":"Point"}
}