{
  "type": "Feature",
  "properties": {
    "addr:full":"762 Rue Emile-Nelligan Roberval QC G8H 3E3",
    "addr:housenumber":"762",
    "addr:postcode":"g8h 3e3",
    "addr:street":"Rue Emile-Nelligan",
    "iso:country":"CA",
    "sg:address":"762 Rue Emile-Nelligan",
    "sg:city":"Roberval",
    "sg:classifiers":[
        {
            "category":"Building & Trades",
            "subcategory":"Electrical",
            "type":"Services"
        }
    ],
    "sg:phone":"+1 418 275 1674",
    "sg:postcode":"G8H 3E3",
    "sg:province":"QC",
    "sg:tags":[
        "electric",
        "contractor"
    ],
    "wof:name":"Alfred & Robert Lavoie",
    "wof:placetype":"venue"
},
  "geometry": {"coordinates":[-72.23412322999999,48.5105895996],"type":"Point"}
}