{
  "type": "Feature",
  "properties": {
    "addr:full":"1318 Centre St NE Calgary AB T2E 2R7",
    "addr:housenumber":"1318",
    "addr:postcode":"t2e 2r7",
    "addr:street":"Centre St Ne",
    "iso:country":"CA",
    "sg:address":"1318 Centre St NE",
    "sg:city":"Calgary",
    "sg:classifiers":[
        {
            "category":"Personal",
            "type":"Services"
        }
    ],
    "sg:phone":"+1 403 230 4191",
    "sg:postcode":"T2E 2R7",
    "sg:province":"AB",
    "sg:tags":[
        "therapist",
        "chiropractor",
        "massage"
    ],
    "wof:name":"Care Group Intern Inc",
    "wof:placetype":"venue"
},
  "geometry": {"coordinates":[-114.03289032000001,51.0524368286],"type":"Point"}
}