{
  "type": "Feature",
  "properties": {
    "addr:full":"720 Central St Centreville NB E7K 2M5",
    "addr:housenumber":"720",
    "addr:postcode":"e7k 2m5",
    "addr:street":"Central St",
    "iso:country":"CA",
    "sg:address":"720 Central St",
    "sg:city":"Centreville",
    "sg:classifiers":[
        {
            "category":"Shopping",
            "subcategory":"Catalog Store",
            "type":"Retail Goods"
        }
    ],
    "sg:phone":"+1 506 276 4534",
    "sg:postcode":"E7K 2M5",
    "sg:province":"NB",
    "sg:tags":[
        "mail",
        "order",
        "internet"
    ],
    "wof:name":"Sears Canada Inc",
    "wof:placetype":"venue"
},
  "geometry": {"coordinates":[-67.71124267579999,46.4308853149],"type":"Point"}
}