{
  "type": "Feature",
  "properties": {
    "addr:full":"10 Bath Rd Kingston ON K7L 1H4",
    "addr:housenumber":"10",
    "addr:postcode":"k7l 1h4",
    "addr:street":"Bath Rd",
    "iso:country":"CA",
    "sg:address":"10 Bath Rd",
    "sg:city":"Kingston",
    "sg:classifiers":[
        {
            "category":"Sports & Exercise",
            "subcategory":"Bowling",
            "type":"Entertainment"
        }
    ],
    "sg:phone":"+1 613 546 4239",
    "sg:postcode":"K7L 1H4",
    "sg:province":"ON",
    "sg:tags":[
        "center"
    ],
    "wof:name":"Cloverleaf Lanes",
    "wof:placetype":"venue"
},
  "geometry": {"coordinates":[-76.51183319090001,44.2408027649],"type":"Point"}
}