{
  "type": "Feature",
  "properties": {
    "addr:full":"630 Shannonville Rd Shannonville ON K0K 3A0",
    "addr:housenumber":"630",
    "addr:postcode":"k0k 3a0",
    "addr:street":"Shannonville Rd",
    "iso:country":"CA",
    "sg:address":"630 Shannonville Rd",
    "sg:city":"Shannonville",
    "sg:classifiers":[
        {
            "category":"Shopping",
            "subcategory":"Hobbies, Toys, & Games",
            "type":"Retail Goods"
        }
    ],
    "sg:phone":"+1 613 968 4271",
    "sg:postcode":"K0K 3A0",
    "sg:province":"ON",
    "sg:tags":[
        "craft",
        "supply"
    ],
    "wof:name":"Ecstasy Crafts Inc",
    "wof:placetype":"venue"
},
  "geometry": {"coordinates":[-77.232491,44.19875],"type":"Point"}
}