{
  "type": "Feature",
  "properties": {
    "addr:full":"2001 Nanton Ave Vancouver BC V6J 4A1",
    "addr:housenumber":"2001",
    "addr:postcode":"v6j 4a1",
    "addr:street":"Nanton Ave",
    "iso:country":"CA",
    "sg:address":"2001 Nanton Ave",
    "sg:city":"Vancouver",
    "sg:classifiers":[
        {
            "category":"Organizations",
            "subcategory":"Community Association",
            "type":"Services"
        }
    ],
    "sg:phone":"+1 604 266 7166",
    "sg:postcode":"V6J 4A1",
    "sg:province":"BC",
    "sg:tags":[
        "club"
    ],
    "wof:name":"Arbutus Club",
    "wof:placetype":"venue"
},
  "geometry": {"coordinates":[-123.150283813,49.2477607727],"type":"Point"}
}