{
  "type": "Feature",
  "properties": {
    "addr:full":"85 Quidi Vidi Rd St. John's NL A1A 1C2",
    "addr:housenumber":"85",
    "addr:postcode":"a1a 1c2",
    "addr:street":"Quidi Vidi Rd",
    "iso:country":"CA",
    "sg:address":"85 Quidi Vidi Rd",
    "sg:city":"St. John's",
    "sg:classifiers":[
        {
            "category":"Food & Beverages",
            "subcategory":"Groceries & Convenience Stores",
            "type":"Retail Goods"
        }
    ],
    "sg:phone":"+1 709 576 7640",
    "sg:postcode":"A1A 1C2",
    "sg:province":"NL",
    "sg:tags":[
        "grocer"
    ],
    "wof:name":"Belbin's Grocery",
    "wof:placetype":"venue"
},
  "geometry": {"coordinates":[-52.682838,47.57753],"type":"Point"}
}