{
  "type": "Feature",
  "properties": {
    "addr:full":"1910 St Laurent Blvd # 32A Ottawa ON K1G 1A4",
    "addr:housenumber":"1910;32a",
    "addr:postcode":"k1g 1a4",
    "addr:street":"St Laurent Blvd #",
    "iso:country":"CA",
    "sg:address":"1910 St Laurent Blvd # 32A",
    "sg:city":"Ottawa",
    "sg:classifiers":[
        {
            "category":"Shopping",
            "subcategory":"Florist",
            "type":"Retail Goods"
        }
    ],
    "sg:phone":"+1 613 521 4521",
    "sg:postcode":"K1G 1A4",
    "sg:province":"ON",
    "wof:name":"Elmvale Florist",
    "wof:placetype":"venue"
},
  "geometry": {"coordinates":[-75.62404632569999,45.4000587463],"type":"Point"}
}