{
  "type": "Feature",
  "properties": {
    "addr:full":"1426 Bloor St W Toronto ON M6P 3L5",
    "addr:housenumber":"1426",
    "addr:postcode":"m6p 3l5",
    "addr:street":"Bloor St W",
    "iso:country":"CA",
    "sg:address":"1426 Bloor St W",
    "sg:city":"Toronto",
    "sg:classifiers":[
        {
            "category":"Shopping",
            "subcategory":"Computers & Home Electronics",
            "type":"Retail Goods"
        }
    ],
    "sg:phone":"+1 416 531 1234",
    "sg:postcode":"M6P 3L5",
    "sg:province":"ON",
    "sg:tags":[
        "television",
        "radio"
    ],
    "wof:name":"Emergency Vcr & Tv Svc",
    "wof:placetype":"venue"
},
  "geometry": {"coordinates":[-79.448036,43.65728],"type":"Point"}
}