{
  "type": "Feature",
  "properties": {
    "addr:full":"Etobicoke ON M9W 4L6",
    "addr:postcode":"m9w 4l6",
    "iso:country":"CA",
    "sg:city":"Etobicoke",
    "sg:classifiers":[
        {
            "category":"Shopping",
            "subcategory":"Discount & Variety Stores",
            "type":"Retail Goods"
        }
    ],
    "sg:phone":"+1 416 741 8839",
    "sg:postcode":"M9W 4L6",
    "sg:province":"ON",
    "wof:name":"M & S Variety Store",
    "wof:placetype":"venue"
},
  "geometry": {"coordinates":[-79.57511901860001,43.7294578552],"type":"Point"}
}