{
  "type": "Feature",
  "properties": {
    "addr:full":"5308 50 St Grimshaw AB T0H 1W0",
    "addr:housenumber":"5308",
    "addr:postcode":"t0h 1w0",
    "addr:street":"50 St",
    "iso:country":"CA",
    "sg:address":"5308 50 St",
    "sg:city":"Grimshaw",
    "sg:classifiers":[
        {
            "category":"Food & Beverages",
            "subcategory":"Groceries & Convenience Stores",
            "type":"Retail Goods"
        }
    ],
    "sg:phone":"+1 780 332 4021",
    "sg:postcode":"T0H 1W0",
    "sg:province":"AB",
    "sg:tags":[
        "grocer"
    ],
    "wof:name":"Lucky Dollar Foods",
    "wof:placetype":"venue"
},
  "geometry": {"coordinates":[-117.606567,56.19038],"type":"Point"}
}