{
  "type": "Feature",
  "properties": {
    "addr:full":"2390 Hornes Rd Queensville ON L0G 1R0",
    "addr:housenumber":"2390",
    "addr:postcode":"l0g 1r0",
    "addr:street":"Hornes Rd",
    "iso:country":"CA",
    "sg:address":"2390 Hornes Rd",
    "sg:city":"Queensville",
    "sg:classifiers":[
        {
            "category":"Building & Trades",
            "subcategory":"Construction",
            "type":"Services"
        }
    ],
    "sg:phone":"+1 905 478 8583",
    "sg:postcode":"L0G 1R0",
    "sg:province":"ON",
    "sg:tags":[
        "masonry",
        "contractor"
    ],
    "wof:name":"Fleiner Construction Ltd",
    "wof:placetype":"venue"
},
  "geometry": {"coordinates":[-79.41887664790001,44.141784668],"type":"Point"}
}