{
  "type": "Feature",
  "properties": {
    "addr:full":"2050 Rue Power Drummondville QC J2C 7V6",
    "addr:housenumber":"2050",
    "addr:postcode":"j2c 7v6",
    "addr:street":"Rue Power",
    "iso:country":"CA",
    "sg:address":"2050 Rue Power",
    "sg:city":"Drummondville",
    "sg:classifiers":[
        {
            "category":"Manufacturing",
            "subcategory":"Textiles",
            "type":"Manufacturing & Wholesale Goods"
        }
    ],
    "sg:phone":"+1 819 477 0050",
    "sg:postcode":"J2C 7V6",
    "sg:province":"QC",
    "sg:tags":[
        "thread"
    ],
    "wof:name":"Textiflex",
    "wof:placetype":"venue"
},
  "geometry": {"coordinates":[-72.5227432251,45.8743095398],"type":"Point"}
}