{
  "type": "Feature",
  "properties": {
    "addr:full":"1672 Second Ave Trail BC V1R 1M5",
    "addr:housenumber":"1672",
    "addr:postcode":"bc v1r 1m5",
    "addr:street":"Second Ave Trail",
    "iso:country":"CA",
    "sg:address":"1672 Second Ave",
    "sg:city":"Trail",
    "sg:classifiers":[
        {
            "category":"Food & Beverages",
            "subcategory":"Bakery",
            "type":"Retail Goods"
        }
    ],
    "sg:phone":"+1 250 368 3018",
    "sg:postcode":"V1R 1M5",
    "sg:province":"BC",
    "sg:tags":[
        "baker"
    ],
    "wof:name":"Luigi Bakery East Trail",
    "wof:placetype":"venue"
},
  "geometry": {"coordinates":[-117.700974,49.096832],"type":"Point"}
}