{
  "type": "Feature",
  "properties": {
    "addr:full":"4016 Mountain Rd Beamsville ON L0R 1B7",
    "addr:housenumber":"4016",
    "addr:postcode":"l0r 1b7",
    "addr:street":"Mountain Rd",
    "iso:country":"CA",
    "sg:address":"4016 Mountain Rd",
    "sg:city":"Beamsville",
    "sg:classifiers":[
        {
            "category":"Manufacturing",
            "subcategory":"Food",
            "type":"Manufacturing & Wholesale Goods"
        }
    ],
    "sg:phone":"+1 905 563 0745",
    "sg:postcode":"L0R 1B7",
    "sg:province":"ON",
    "sg:tags":[
        "winery"
    ],
    "wof:name":"Mountain Road Wine CO",
    "wof:placetype":"venue"
},
  "geometry": {"coordinates":[-79.47811900000001,43.153236],"type":"Point"}
}