{
  "type": "Feature",
  "properties": {
    "addr:full":"624 Rue Saint-Francois Granby QC J2G 3K5",
    "addr:housenumber":"624",
    "addr:postcode":"j2g 3k5",
    "addr:street":"Rue Saint-Francois",
    "iso:country":"CA",
    "sg:address":"624 Rue Saint-Francois",
    "sg:city":"Granby",
    "sg:classifiers":[
        {
            "category":"Manufacturing",
            "subcategory":"Textiles",
            "type":"Manufacturing & Wholesale Goods"
        }
    ],
    "sg:phone":"+1 450 375 1507",
    "sg:postcode":"J2G 3K5",
    "sg:province":"QC",
    "sg:tags":[
        "dyer"
    ],
    "wof:name":"Nettoyeur Teinturier St Frncs",
    "wof:placetype":"venue"
},
  "geometry": {"coordinates":[-72.74411000000001,45.400517],"type":"Point"}
}