{
  "type": "Feature",
  "properties": {
    "addr:full":"4013 Frizzi Rd Williams Lake BC V2G 3P1",
    "addr:housenumber":"4013",
    "addr:postcode":"v2g 3p1",
    "addr:street":"Frizzi Rd",
    "iso:country":"CA",
    "sg:address":"4013 Frizzi Rd",
    "sg:city":"Williams Lake",
    "sg:classifiers":[
        {
            "category":"Wholesale",
            "subcategory":"Scrap",
            "type":"Manufacturing & Wholesale Goods"
        }
    ],
    "sg:phone":"+1 250 398 5716",
    "sg:postcode":"V2G 3P1",
    "sg:province":"BC",
    "sg:tags":[
        "recycling",
        "metal",
        "center",
        "iron"
    ],
    "wof:name":"Williams Lake Scrap Metal",
    "wof:placetype":"venue"
},
  "geometry": {"coordinates":[-122.172470093,52.1466674805],"type":"Point"}
}