{
  "type": "Feature",
  "properties": {
    "addr:full":"3346 Boul DE LA Grande-Baie S LA Baie QC G7B 1G2",
    "addr:housenumber":"3346",
    "addr:postcode":"g7b 1g2",
    "addr:street":"Boul De La Grande-Baie S La Baie",
    "iso:country":"CA",
    "sg:address":"3346 Boul DE LA Grande-Baie S",
    "sg:city":"LA Baie",
    "sg:classifiers":[
        {
            "category":"Government",
            "subcategory":"Office",
            "type":"Public Place"
        }
    ],
    "sg:phone":"+1 418 697 5081",
    "sg:postcode":"G7B 1G2",
    "sg:province":"QC",
    "sg:tags":[
        "instruction",
        "dancing",
        "village"
    ],
    "wof:name":"Academie DE Ballet Du Saguenay",
    "wof:placetype":"venue"
},
  "geometry": {"coordinates":[-70.853714,48.317368],"type":"Point"}
}