{
  "type": "Feature",
  "properties": {
    "addr:full":"5328 Argyle St Port Alberni BC V9Y 1T8",
    "addr:housenumber":"5328",
    "addr:postcode":"v9y 1t8",
    "addr:street":"Argyle St",
    "iso:country":"CA",
    "sg:address":"5328 Argyle St",
    "sg:city":"Port Alberni",
    "sg:classifiers":[
        {
            "category":"Restaurant",
            "type":"Food & Drink"
        }
    ],
    "sg:phone":"+1 250 723 0777",
    "sg:postcode":"V9Y 1T8",
    "sg:province":"BC",
    "wof:name":"Swale Rock Cafe Ltd",
    "wof:placetype":"venue"
},
  "geometry": {"coordinates":[-124.812721252,49.234462738],"type":"Point"}
}