{
  "type": "Feature",
  "properties": {
    "addr:full":"5199 Rue Sherbrooke E # 3440 Montreal QC H1T 3X2",
    "addr:housenumber":"5199",
    "addr:postcode":"h1t 3x2",
    "addr:street":"Rue Sherbrooke E # 3440",
    "iso:country":"CA",
    "sg:address":"5199 Rue Sherbrooke E # 3440",
    "sg:city":"Montreal",
    "sg:classifiers":[
        {
            "category":"Organizations",
            "subcategory":"Professional Association",
            "type":"Services"
        }
    ],
    "sg:phone":"+1 514 257 0678",
    "sg:postcode":"H1T 3X2",
    "sg:province":"QC",
    "wof:name":"Club Age'd Village Olympique",
    "wof:placetype":"venue"
},
  "geometry": {"coordinates":[-73.552773,45.568336],"type":"Point"}
}