{
  "type": "Feature",
  "properties": {
    "iso:country":"CA",
    "sg:address":"1055 12E Av N",
    "sg:city":"Fleurimont",
    "sg:classifiers":[
        {
            "category":"Health Services",
            "subcategory":"Doctor",
            "type":"Services"
        }
    ],
    "sg:phone":"+1 819 563 2027",
    "sg:postcode":"J1E 2X4",
    "sg:province":"QC",
    "sg:tags":[
        "physician",
        "surgeon"
    ],
    "wof:name":"Clinique Obstetrique-Gynecolgy",
    "wof:placetype":"venue"
},
  "geometry": {"coordinates":[-71.87412999999999,45.422798],"type":"Point"}
}