{
  "type": "Feature",
  "properties": {
    "addr:full":"9705 Alaska Rd Fort St John BC V1J 1A4",
    "addr:housenumber":"9705",
    "addr:postcode":"v1j 1a4",
    "addr:street":"Alaska Rd",
    "iso:country":"CA",
    "sg:address":"9705 Alaska Rd",
    "sg:city":"Fort St John",
    "sg:classifiers":[
        {
            "category":"Travel",
            "subcategory":"Hotels & Motels",
            "type":"Entertainment"
        }
    ],
    "sg:phone":"+1 250 785 2613",
    "sg:postcode":"V1J 1A4",
    "sg:province":"BC",
    "wof:name":"Blue Belle Motel",
    "wof:placetype":"venue"
},
  "geometry": {"coordinates":[-120.841957092,56.234413147],"type":"Point"}
}