{
  "type": "Feature",
  "properties": {
    "iso:country":"CA",
    "sg:city":"Brampton",
    "sg:classifiers":[
        {
            "category":"Manufacturing",
            "subcategory":"Printing",
            "type":"Manufacturing & Wholesale Goods"
        }
    ],
    "sg:phone":"+1 905 793 8188",
    "sg:postcode":"L6T 4S9",
    "sg:province":"ON",
    "sg:tags":[
        "printer"
    ],
    "wof:name":"Kwik Kopy Printing",
    "wof:placetype":"venue"
},
  "geometry": {"coordinates":[-79.696075,43.693459],"type":"Point"}
}