{
  "type": "Feature",
  "properties": {
    "addr:full":"150 Logan Rd Bridgewater NS B4V 3J8",
    "addr:housenumber":"150",
    "addr:postcode":"b4v 3j8",
    "addr:street":"Logan Rd",
    "iso:country":"CA",
    "sg:address":"150 Logan Rd",
    "sg:city":"Bridgewater",
    "sg:classifiers":[
        {
            "category":"Autos & Motor Vehicles",
            "subcategory":"Auto Supplies",
            "type":"Retail Goods"
        }
    ],
    "sg:phone":"+1 902 543 2426",
    "sg:postcode":"B4V 3J8",
    "sg:province":"NS",
    "sg:tags":[
        "automobile",
        "parts"
    ],
    "wof:name":"Rafuse Auto Parts Ctr",
    "wof:placetype":"venue"
},
  "geometry": {"coordinates":[-64.541656,44.38855],"type":"Point"}
}