{
  "type": "Feature",
  "properties": {
    "addr:full":"8800 Eastlake Dr Burnaby BC V3J 7X5",
    "addr:housenumber":"8800",
    "addr:postcode":"v3j 7x5",
    "addr:street":"Eastlake Dr",
    "iso:country":"CA",
    "sg:address":"8800 Eastlake Dr",
    "sg:city":"Burnaby",
    "sg:classifiers":[
        {
            "category":"Education",
            "subcategory":"School",
            "type":"Public Place"
        }
    ],
    "sg:phone":"+1 604 664 8552",
    "sg:postcode":"V3J 7X5",
    "sg:province":"BC",
    "wof:name":"Burnaby Mountain NE Secondary",
    "wof:placetype":"venue"
},
  "geometry": {"coordinates":[-122.910461,49.256477],"type":"Point"}
}