{
  "type": "Feature",
  "properties": {
    "iso:country":"CA",
    "sg:address":"2991 Lougheed Hwy",
    "sg:city":"Coquitlam",
    "sg:classifiers":[
        {
            "category":"Recreation",
            "type":"Entertainment"
        }
    ],
    "sg:phone":"+1 604 468 0094",
    "sg:postcode":"V3B 6J6",
    "sg:province":"BC",
    "sg:tags":[
        "lottery",
        "agent"
    ],
    "wof:name":"Hana's Lottery Ctr",
    "wof:placetype":"venue"
},
  "geometry": {"coordinates":[-122.794288635,49.2752609253],"type":"Point"}
}