{
  "type": "Feature",
  "properties": {
    "addr:full":"56 Rue Notre-Dame E Victoriaville QC G6P 3Z6",
    "addr:housenumber":"56",
    "addr:postcode":"g6p 3z6",
    "addr:street":"Rue Notre-Dame E",
    "iso:country":"CA",
    "sg:address":"56 Rue Notre-Dame E",
    "sg:city":"Victoriaville",
    "sg:classifiers":[
        {
            "category":"Shopping",
            "subcategory":"Jewelry",
            "type":"Retail Goods"
        }
    ],
    "sg:phone":"+1 819 758 3944",
    "sg:postcode":"G6P 3Z6",
    "sg:province":"QC",
    "sg:tags":[
        "jeweler"
    ],
    "wof:name":"Ateliers Tp Inc",
    "wof:placetype":"venue"
},
  "geometry": {"coordinates":[-71.9574127197,46.0563163757],"type":"Point"}
}