{
  "type": "Feature",
  "properties": {
    "addr:full":"20 Boul Cremazie E Montreal QC H2P 1C8",
    "addr:housenumber":"20",
    "addr:postcode":"h2p 1c8",
    "addr:street":"Boul Cremazie E",
    "iso:country":"CA",
    "sg:address":"20 Boul Cremazie E",
    "sg:city":"Montreal",
    "sg:classifiers":[
        {
            "category":"Restaurant",
            "type":"Food & Drink"
        }
    ],
    "sg:phone":"+1 514 382 7325",
    "sg:postcode":"H2P 1C8",
    "sg:province":"QC",
    "wof:name":"Club DE Billard Le Break",
    "wof:placetype":"venue"
},
  "geometry": {"coordinates":[-73.64089199999999,45.542271],"type":"Point"}
}