{
  "type": "Feature",
  "properties": {
    "addr:full":"314 Rue Queen Lennoxville QC J1M 1K9",
    "addr:housenumber":"314",
    "addr:postcode":"j1m 1k9",
    "addr:street":"Rue Queen",
    "iso:country":"CA",
    "sg:address":"314 Rue Queen",
    "sg:city":"Lennoxville",
    "sg:classifiers":[
        {
            "category":"Manufacturing",
            "subcategory":"Apparel",
            "type":"Manufacturing & Wholesale Goods"
        }
    ],
    "sg:phone":"+1 819 564 3434",
    "sg:postcode":"J1M 1K9",
    "sg:province":"QC",
    "sg:tags":[
        "bag",
        "canvas"
    ],
    "wof:name":"Arkel Over Designs",
    "wof:placetype":"venue"
},
  "geometry": {"coordinates":[-71.86715700000001,45.378262],"type":"Point"}
}