{
  "type": "Feature",
  "properties": {
    "iso:country":"CA",
    "sg:address":"314 Rue Queen",
    "sg:city":"Lennoxville",
    "sg:classifiers":[
        {
            "category":"Manufacturing",
            "subcategory":"Apparel",
            "type":"Manufacturing & Wholesale Goods"
        }
    ],
    "sg:phone":"+1 819 564 3434",
    "sg:postcode":"J1M 1K9",
    "sg:province":"QC",
    "sg:tags":[
        "bag",
        "canvas"
    ],
    "wof:name":"Arkel Over Designs",
    "wof:placetype":"venue"
},
  "geometry": {"coordinates":[-71.867157,45.378262],"type":"Point"}
}