{
  "type": "Feature",
  "properties": {
    "addr:full":"3428 Bathurst St North York ON M6A 2C2",
    "addr:housenumber":"3428",
    "addr:postcode":"m6a 2c2",
    "addr:street":"Bathurst St",
    "iso:country":"CA",
    "sg:address":"3428 Bathurst St",
    "sg:city":"North York",
    "sg:classifiers":[
        {
            "category":"Building & Trades",
            "subcategory":"Construction",
            "type":"Services"
        }
    ],
    "sg:phone":"+1 416 784 9333",
    "sg:postcode":"M6A 2C2",
    "sg:province":"ON",
    "sg:tags":[
        "waterproofing",
        "contractor"
    ],
    "wof:name":"J D Caulking",
    "wof:placetype":"venue"
},
  "geometry": {"coordinates":[-79.43180084230001,43.7275123596],"type":"Point"}
}