{
  "type": "Feature",
  "properties": {
    "addr:full":"Montreal QC H2Z 1S5",
    "addr:postcode":"h2z 1s5",
    "iso:country":"CA",
    "sg:city":"Montreal",
    "sg:classifiers":[
        {
            "category":"Education",
            "subcategory":"School",
            "type":"Public Place"
        }
    ],
    "sg:phone":"+1 514 393 4131",
    "sg:postcode":"H2Z 1S5",
    "sg:province":"QC",
    "sg:tags":[
        "academic",
        "company",
        "telephone",
        "special"
    ],
    "wof:name":"Hi-Tel hi Data",
    "wof:placetype":"venue"
},
  "geometry": {"coordinates":[-73.56530761720001,45.5027236938],"type":"Point"}
}