{
  "type": "Feature",
  "properties": {
    "addr:full":"170 Montague St Lunenburg NS B0J 2C0",
    "addr:housenumber":"170",
    "addr:postcode":"b0j 2c0",
    "addr:street":"Montague St",
    "iso:country":"CA",
    "sg:address":"170 Montague St",
    "sg:city":"Lunenburg",
    "sg:classifiers":[
        {
            "category":"Manufacturing",
            "subcategory":"Food",
            "type":"Manufacturing & Wholesale Goods"
        }
    ],
    "sg:phone":"+1 902 634 4349",
    "sg:postcode":"B0J 2C0",
    "sg:province":"NS",
    "sg:tags":[
        "product",
        "seafood",
        "fish",
        "prepared"
    ],
    "wof:name":"Adams & Knickle Ltd",
    "wof:placetype":"venue"
},
  "geometry": {"coordinates":[-64.3078384399,44.3760108948],"type":"Point"}
}