{
  "type": "Feature",
  "properties": {
    "addr:full":"1611 Coulter Rd Campbell River BC V9W 7M1",
    "addr:housenumber":"1611",
    "addr:postcode":"v9w 7m1",
    "addr:street":"Coulter Rd",
    "iso:country":"CA",
    "sg:address":"1611 Coulter Rd",
    "sg:city":"Campbell River",
    "sg:classifiers":[
        {
            "category":"Freight",
            "type":"Transportation"
        }
    ],
    "sg:phone":"+1 250 287 7474",
    "sg:postcode":"V9W 7M1",
    "sg:province":"BC",
    "sg:tags":[
        "trucking"
    ],
    "wof:name":"Van-Kam Freightways Ltd",
    "wof:placetype":"venue"
},
  "geometry": {"coordinates":[-125.26545,50.044895],"type":"Point"}
}