{
  "type": "Feature",
  "properties": {
    "addr:full":"110 11th St E Prince Albert SK S6V 1A1",
    "addr:housenumber":"110",
    "addr:postcode":"s6v 1a1",
    "addr:street":"11Th St",
    "iso:country":"CA",
    "sg:address":"110 11th St E",
    "sg:city":"Prince Albert",
    "sg:classifiers":[
        {
            "category":"Professional",
            "subcategory":"Lawyer & Legal Services",
            "type":"Services"
        }
    ],
    "sg:phone":"+1 306 764 2222",
    "sg:postcode":"S6V 1A1",
    "sg:province":"SK",
    "sg:tags":[
        "attorney"
    ],
    "wof:name":"Parchomchuk, Ronald G",
    "wof:placetype":"venue"
},
  "geometry": {"coordinates":[-105.75103799999999,53.203201],"type":"Point"}
}