{
  "type": "Feature",
  "properties": {
    "addr:full":"65 Main St Riverton MB R0C 2R0",
    "addr:housenumber":"65",
    "addr:postcode":"r0c 2r0",
    "addr:street":"Main St",
    "iso:country":"CA",
    "sg:address":"65 Main St",
    "sg:city":"Riverton",
    "sg:classifiers":[
        {
            "category":"Food & Beverages",
            "subcategory":"Groceries & Convenience Stores",
            "type":"Retail Goods"
        }
    ],
    "sg:phone":"+1 204 378 2393",
    "sg:postcode":"R0C 2R0",
    "sg:province":"MB",
    "sg:tags":[
        "grocer"
    ],
    "wof:name":"Shop Easy Foods",
    "wof:placetype":"venue"
},
  "geometry": {"coordinates":[-96.99645200000001,50.998413],"type":"Point"}
}