{
  "type": "Feature",
  "properties": {
    "addr:full":"2237 Rue Fleury E Montreal QC H2B 1K5",
    "addr:housenumber":"2237",
    "addr:postcode":"h2b 1k5",
    "addr:street":"Rue Fleury E",
    "iso:country":"CA",
    "sg:address":"2237 Rue Fleury E",
    "sg:city":"Montreal",
    "sg:classifiers":[
        {
            "category":"Restaurant",
            "type":"Food & Drink"
        }
    ],
    "sg:phone":"+1 514 381 0658",
    "sg:postcode":"H2B 1K5",
    "sg:province":"QC",
    "wof:name":"Restaurant Le Particulier",
    "wof:placetype":"venue"
},
  "geometry": {"coordinates":[-73.64981079099999,45.573009491],"type":"Point"}
}