{
  "type": "Feature",
  "properties": {
    "addr:full":"Levis QC G6V 4Z6",
    "addr:postcode":"g6v 4z6",
    "iso:country":"CA",
    "sg:city":"Levis",
    "sg:classifiers":[
        {
            "category":"Professional",
            "subcategory":"Lawyer & Legal Services",
            "type":"Services"
        }
    ],
    "sg:phone":"+1 418 833 1065",
    "sg:postcode":"G6V 4Z6",
    "sg:province":"QC",
    "sg:tags":[
        "attorney"
    ],
    "wof:name":"Dallaire Poirier",
    "wof:placetype":"venue"
},
  "geometry": {"coordinates":[-71.184929,46.789383],"type":"Point"}
}