{
  "type": "Feature",
  "properties": {
    "addr:full":"Scarborough ON M1X 1M3",
    "addr:postcode":"m1x 1m3",
    "iso:country":"CA",
    "sg:city":"Scarborough",
    "sg:classifiers":[
        {
            "category":"Wholesale",
            "subcategory":"Chemicals & Plastics",
            "type":"Manufacturing & Wholesale Goods"
        }
    ],
    "sg:phone":"+1 416 321 1173",
    "sg:postcode":"M1X 1M3",
    "sg:province":"ON",
    "wof:name":"Sam's Plastic & Paper Whol",
    "wof:placetype":"venue"
},
  "geometry": {"coordinates":[-79.24754299999999,43.827286],"type":"Point"}
}