{
  "type": "Feature",
  "properties": {
    "iso:country":"CA",
    "sg:city":"Calgary",
    "sg:classifiers":[
        {
            "category":"Building & Trades",
            "subcategory":"Plumbing",
            "type":"Services"
        }
    ],
    "sg:phone":"+1 403 236 9627",
    "sg:postcode":"T2C 2J2",
    "sg:province":"AB",
    "sg:tags":[
        "heater",
        "work",
        "sheet",
        "metal",
        "contractor"
    ],
    "wof:name":"Northstar Flameless Ltd",
    "wof:placetype":"venue"
},
  "geometry": {"coordinates":[-113.972297669,50.9852676392],"type":"Point"}
}