{
  "type": "Feature",
  "properties": {
    "addr:full":"76 Pine St Bracebridge ON P1L 1N4",
    "addr:housenumber":"76",
    "addr:postcode":"p1l 1n4",
    "addr:street":"Pine St",
    "iso:country":"CA",
    "sg:address":"76 Pine St",
    "sg:city":"Bracebridge",
    "sg:classifiers":[
        {
            "category":"Education",
            "subcategory":"School",
            "type":"Public Place"
        }
    ],
    "sg:phone":"+1 705 645 8704",
    "sg:postcode":"P1L 1N4",
    "sg:province":"ON",
    "wof:name":"Trillium Lakelands School Brd",
    "wof:placetype":"venue"
},
  "geometry": {"coordinates":[-79.29922485349999,45.051990509],"type":"Point"}
}