{
  "type": "Feature",
  "properties": {
    "addr:full":"Bradford ON L3Z 2A7",
    "addr:postcode":"l3z 2a7",
    "iso:country":"CA",
    "sg:city":"Bradford",
    "sg:classifiers":[
        {
            "category":"Professional",
            "subcategory":"Employment Agencies",
            "type":"Services"
        }
    ],
    "sg:phone":"+1 905 778 9058",
    "sg:postcode":"L3Z 2A7",
    "sg:province":"ON",
    "sg:tags":[
        "co",
        "opportunity",
        "fraternal"
    ],
    "wof:name":"Bradford Assessment Ctr",
    "wof:placetype":"venue"
},
  "geometry": {"coordinates":[-79.56368255620001,44.1146850586],"type":"Point"}
}