{
  "type": "Feature",
  "properties": {
    "addr:full":"5924 Boul Henri-Bourassa O Saint-Laurent QC H4R 1V9",
    "addr:housenumber":"5924",
    "addr:postcode":"h4r 1v9",
    "addr:street":"Boul Henri-Bourassa O",
    "iso:country":"CA",
    "sg:address":"5924 Boul Henri-Bourassa O",
    "sg:city":"Saint-Laurent",
    "sg:classifiers":[
        {
            "category":"Wholesale",
            "subcategory":"Office Equipment",
            "type":"Manufacturing & Wholesale Goods"
        }
    ],
    "sg:phone":"+1 514 339 5000",
    "sg:postcode":"H4R 1V9",
    "sg:province":"QC",
    "sg:tags":[
        "machine",
        "duplicating",
        "copying"
    ],
    "wof:name":"Danka Mds",
    "wof:placetype":"venue"
},
  "geometry": {"coordinates":[-73.717682,45.516117],"type":"Point"}
}