{
  "type": "Feature",
  "properties": {
    "addr:full":"73 Rue Alexandre Salaberry-DE-Valleyfield QC J6S 3J7",
    "addr:housenumber":"73",
    "addr:postcode":"j6s 3j7",
    "addr:street":"Rue Alexandre",
    "iso:country":"CA",
    "sg:address":"73 Rue Alexandre",
    "sg:city":"Salaberry-DE-Valleyfield",
    "sg:classifiers":[
        {
            "category":"Retail",
            "subcategory":"Laundry & Dry Cleaning",
            "type":"Services"
        }
    ],
    "sg:phone":"+1 450 373 6860",
    "sg:postcode":"J6S 3J7",
    "sg:province":"QC",
    "sg:tags":[
        "cleaners"
    ],
    "wof:name":"Betty Brite",
    "wof:placetype":"venue"
},
  "geometry": {"coordinates":[-74.1343841553,45.2626457214],"type":"Point"}
}