{
  "type": "Feature",
  "properties": {
    "addr:full":"77 Boul Desjardins E Sainte-Therese QC J7E 1C5",
    "addr:housenumber":"77",
    "addr:postcode":"j7e 1c5",
    "addr:street":"Boul Desjardins E Sainte-Therese",
    "iso:country":"CA",
    "sg:address":"77 Boul Desjardins E",
    "sg:city":"Sainte-Therese",
    "sg:classifiers":[
        {
            "category":"Bars & Pubs",
            "type":"Food & Drink"
        }
    ],
    "sg:phone":"+1 450 435 5333",
    "sg:postcode":"J7E 1C5",
    "sg:province":"QC",
    "wof:name":"Brasserie Le Relais",
    "wof:placetype":"venue"
},
  "geometry": {"coordinates":[-73.8283,45.635113],"type":"Point"}
}