{
  "type": "Feature",
  "properties": {
    "iso:country":"CA",
    "sg:address":"3050 Boul DE Portland",
    "sg:city":"Sherbrooke",
    "sg:classifiers":[
        {
            "category":"Shopping",
            "type":"Retail Goods"
        }
    ],
    "sg:phone":"+1 819 569 2548",
    "sg:postcode":"J1L 1K1",
    "sg:province":"QC",
    "sg:tags":[
        "picture",
        "frame"
    ],
    "wof:name":"Grif & Graf",
    "wof:placetype":"venue"
},
  "geometry": {"coordinates":[-71.94931,45.403305],"type":"Point"}
}