{
  "type": "Feature",
  "properties": {
    "addr:full":"2953 4th Ave W Vancouver BC V6K 1R3",
    "addr:housenumber":"2953",
    "addr:postcode":"v6k 1r3",
    "addr:street":"4Th Ave W",
    "iso:country":"CA",
    "sg:address":"2953 4th Ave W",
    "sg:city":"Vancouver",
    "sg:classifiers":[
        {
            "category":"Retail",
            "subcategory":"Repair Shop",
            "type":"Services"
        }
    ],
    "sg:phone":"+1 604 737 2161",
    "sg:postcode":"V6K 1R3",
    "sg:province":"BC",
    "sg:tags":[
        "appliance"
    ],
    "wof:name":"A-Aabrams Garburetor Svc",
    "wof:placetype":"venue"
},
  "geometry": {"coordinates":[-123.17060852,49.2685279846],"type":"Point"}
}