{
  "type": "Feature",
  "properties": {
    "addr:full":"Burnaby BC V5C 3W1",
    "addr:postcode":"v5c 3w1",
    "iso:country":"CA",
    "sg:city":"Burnaby",
    "sg:classifiers":[
        {
            "category":"Retail",
            "subcategory":"Auto Repair",
            "type":"Services"
        }
    ],
    "sg:phone":"+1 604 299 2535",
    "sg:postcode":"V5C 3W1",
    "sg:province":"BC",
    "sg:tags":[
        "repairing",
        "automobile",
        "radiator"
    ],
    "wof:name":"Jo Nic Radiators",
    "wof:placetype":"venue"
},
  "geometry": {"coordinates":[-123.02073669400001,49.2691993713],"type":"Point"}
}