{
  "type": "Feature",
  "properties": {
    "addr:full":"Cranbrook BC V1C 2M1",
    "addr:postcode":"v1c 2m1",
    "iso:country":"CA",
    "sg:city":"Cranbrook",
    "sg:classifiers":[
        {
            "category":"Organizations",
            "subcategory":"Labor Organization",
            "type":"Services"
        }
    ],
    "sg:phone":"+1 250 426 2670",
    "sg:postcode":"V1C 2M1",
    "sg:province":"BC",
    "wof:name":"East Kootenay District Labour",
    "wof:placetype":"venue"
},
  "geometry": {"coordinates":[-115.76918000000001,49.510048],"type":"Point"}
}