{
  "type": "Feature",
  "properties": {
    "addr:full":"101 Scollard St Toronto ON M5R 1G4",
    "addr:housenumber":"101",
    "addr:postcode":"m5r 1g4",
    "addr:street":"Scollard St",
    "iso:country":"CA",
    "sg:address":"101 Scollard St",
    "sg:city":"Toronto",
    "sg:classifiers":[
        {
            "category":"Travel",
            "subcategory":"Travel Agent",
            "type":"Entertainment"
        }
    ],
    "sg:phone":"+1 416 960 3800",
    "sg:postcode":"M5R 1G4",
    "sg:province":"ON",
    "sg:tags":[
        "agency",
        "bureau"
    ],
    "wof:name":"Pilar International Travel Inc",
    "wof:placetype":"venue"
},
  "geometry": {"coordinates":[-79.3923110962,43.6716041565],"type":"Point"}
}