{
  "type": "Feature",
  "properties": {
    "iso:country":"CA",
    "sg:city":"Grandes-Bergeronnes",
    "sg:classifiers":[
        {
            "category":"Social Services",
            "type":"Services"
        }
    ],
    "sg:phone":"+1 418 232 2232",
    "sg:postcode":"G0T 1G0",
    "sg:province":"QC",
    "sg:tags":[
        "organization",
        "welfare"
    ],
    "wof:name":"Centre D'Activites DE LA Haute",
    "wof:placetype":"venue"
},
  "geometry": {"coordinates":[-69.542175293,48.2441368103],"type":"Point"}
}