{
  "type": "Feature",
  "properties": {
    "addr:full":"Windsor ON N9A 5W8",
    "addr:postcode":"n9a 5w8",
    "iso:country":"CA",
    "sg:city":"Windsor",
    "sg:classifiers":[
        {
            "category":"Real Estate",
            "subcategory":"Architect",
            "type":"Services"
        }
    ],
    "sg:phone":"+1 519 253 0684",
    "sg:postcode":"N9A 5W8",
    "sg:province":"ON",
    "wof:name":"St Clair Region Society",
    "wof:placetype":"venue"
},
  "geometry": {"coordinates":[-83.037979126,42.3135757446],"type":"Point"}
}