{
  "type": "Feature",
  "properties": {
    "iso:country":"CA",
    "sg:city":"Burks Falls",
    "sg:classifiers":[
        {
            "category":"Building & Trades",
            "subcategory":"Construction",
            "type":"Services"
        }
    ],
    "sg:phone":"+1 705 382 3241",
    "sg:postcode":"P0A 1C0",
    "sg:province":"ON",
    "sg:tags":[
        "excavating",
        "contractor"
    ],
    "wof:name":"Klink Enterprises",
    "wof:placetype":"venue"
},
  "geometry": {"coordinates":[-78.4808883667,45.0337142944],"type":"Point"}
}