{
  "type": "Feature",
  "properties": {
    "addr:full":"2844 Hwy 26 St Francois Xavier MB R4L 1B4",
    "addr:housenumber":"2844",
    "addr:postcode":"r4l 1b4",
    "addr:street":"Hwy 26 St Francois Xavier",
    "iso:country":"CA",
    "sg:address":"2844 Hwy 26",
    "sg:city":"St Francois Xavier",
    "sg:classifiers":[
        {
            "category":"Home & Garden",
            "subcategory":"Home Furnishings",
            "type":"Retail Goods"
        }
    ],
    "sg:phone":"+1 204 353 2565",
    "sg:postcode":"R4L 1B4",
    "sg:province":"MB",
    "sg:tags":[
        "stove",
        "wood",
        "burning"
    ],
    "wof:name":"Elf Industries Ltd",
    "wof:placetype":"venue"
},
  "geometry": {"coordinates":[-97.90888200000001,50.059078],"type":"Point"}
}