{
  "type": "Feature",
  "properties": {
    "addr:full":"Toronto ON M4E 2J4",
    "addr:postcode":"m4e 2j4",
    "iso:country":"CA",
    "sg:city":"Toronto",
    "sg:classifiers":[
        {
            "category":"Retail",
            "subcategory":"Laundry & Dry Cleaning",
            "type":"Services"
        }
    ],
    "sg:phone":"+1 416 693 0484",
    "sg:postcode":"M4E 2J4",
    "sg:province":"ON",
    "sg:tags":[
        "cleaners"
    ],
    "wof:name":"Sina Dry Cleaning",
    "wof:placetype":"venue"
},
  "geometry": {"coordinates":[-79.310478,43.680607],"type":"Point"}
}