{
  "type": "Feature",
  "properties": {
    "addr:full":"6 Guildford Crt London ON N6J 3Y1",
    "addr:housenumber":"6",
    "addr:postcode":"n6j 3y1",
    "addr:street":"Guildford Crt",
    "iso:country":"CA",
    "sg:address":"6 Guildford Crt",
    "sg:city":"London",
    "sg:classifiers":[
        {
            "category":"Manufacturing",
            "subcategory":"Tools & Machinery",
            "type":"Manufacturing & Wholesale Goods"
        }
    ],
    "sg:phone":"+1 519 474 3044",
    "sg:postcode":"N6J 3Y1",
    "sg:province":"ON",
    "sg:tags":[
        "scale"
    ],
    "wof:name":"Ovantum Sales Inc",
    "wof:placetype":"venue"
},
  "geometry": {"coordinates":[-81.2824478149,42.9539413452],"type":"Point"}
}