{
  "type": "Feature",
  "properties": {
    "addr:full":"5320 1A St SW Calgary AB T2H 1Y5",
    "addr:housenumber":"5320",
    "addr:postcode":"t2h 1y5",
    "addr:street":"1A St Sw",
    "iso:country":"CA",
    "sg:address":"5320 1A St SW",
    "sg:city":"Calgary",
    "sg:classifiers":[
        {
            "category":"Home & Garden",
            "subcategory":"Home Furnishings",
            "type":"Retail Goods"
        }
    ],
    "sg:phone":"+1 403 243 4511",
    "sg:postcode":"T2H 1Y5",
    "sg:province":"AB",
    "sg:tags":[
        "fireplace"
    ],
    "wof:name":"Western Fresh Air Fireplaces",
    "wof:placetype":"venue"
},
  "geometry": {"coordinates":[-114.066917,51.006729],"type":"Point"}
}