{
  "type": "Feature",
  "properties": {
    "iso:country":"CA",
    "sg:address":"4415 Rue Royal",
    "sg:city":"Pierrefonds",
    "sg:classifiers":[
        {
            "category":"Building & Trades",
            "subcategory":"Landscaping Services",
            "type":"Services"
        }
    ],
    "sg:phone":"+1 514 626 8183",
    "sg:postcode":"H9H 2H6",
    "sg:province":"QC",
    "sg:tags":[
        "designer",
        "landscape"
    ],
    "wof:name":"Christian Beaulieu & Assoc",
    "wof:placetype":"venue"
},
  "geometry": {"coordinates":[-73.85572052000001,45.4814338684],"type":"Point"}
}