{
  "type": "Feature",
  "properties": {
    "addr:full":"5060 Ch Du Lac Saint-Gabriel-DE-Brandon QC J0K 2N0",
    "addr:postcode":"5060;j0k 2n0",
    "addr:street":"Ch Du Lac",
    "iso:country":"CA",
    "sg:address":"5060 Ch Du Lac",
    "sg:city":"Saint-Gabriel-DE-Brandon",
    "sg:classifiers":[
        {
            "category":"Retail",
            "subcategory":"Auto Repair",
            "type":"Services"
        }
    ],
    "sg:phone":"+1 450 835 0792",
    "sg:postcode":"J0K 2N0",
    "sg:province":"QC",
    "sg:tags":[
        "automobile",
        "electric"
    ],
    "wof:name":"Rsm Auto Electrique Enr",
    "wof:placetype":"venue"
},
  "geometry": {"coordinates":[-73.362572,46.284283],"type":"Point"}
}