{
  "type": "Feature",
  "properties": {
    "addr:full":"385 Bloor St W Oshawa ON L1J 5Y5",
    "addr:housenumber":"385",
    "addr:postcode":"l1j 5y5",
    "addr:street":"Bloor St W",
    "iso:country":"CA",
    "sg:address":"385 Bloor St W",
    "sg:city":"Oshawa",
    "sg:classifiers":[
        {
            "category":"Shopping",
            "subcategory":"Bicycles & Sporting Goods",
            "type":"Retail Goods"
        }
    ],
    "sg:phone":"+1 905 725 5798",
    "sg:postcode":"L1J 5Y5",
    "sg:province":"ON",
    "wof:name":"Gagnon Sports",
    "wof:placetype":"venue"
},
  "geometry": {"coordinates":[-78.870018,43.877121],"type":"Point"}
}