{
  "type": "Feature",
  "properties": {
    "addr:full":"19500 River Rd Richmond BC V6V 1M3",
    "addr:housenumber":"19500",
    "addr:postcode":"v6v 1m3",
    "addr:street":"River Rd",
    "iso:country":"CA",
    "sg:address":"19500 River Rd",
    "sg:city":"Richmond",
    "sg:classifiers":[
        {
            "category":"Autos & Motor Vehicles",
            "subcategory":"Fuel & Gas Station",
            "type":"Retail Goods"
        }
    ],
    "sg:phone":"+1 604 273 7552",
    "sg:postcode":"V6V 1M3",
    "sg:province":"BC",
    "sg:tags":[
        "oil"
    ],
    "wof:name":"Sprite Motors Ltd",
    "wof:placetype":"venue"
},
  "geometry": {"coordinates":[-123.00400500000001,49.190861],"type":"Point"}
}