{
  "type": "Feature",
  "properties": {
    "addr:full":"RR 1 Limehouse ON L0P 1H0",
    "addr:postcode":"l0p 1h0",
    "addr:street":"Rr 1",
    "iso:country":"CA",
    "sg:address":"RR 1",
    "sg:city":"Limehouse",
    "sg:classifiers":[
        {
            "category":"Building & Trades",
            "subcategory":"Landscaping Services",
            "type":"Services"
        }
    ],
    "sg:phone":"+1 905 877 8591",
    "sg:postcode":"L0P 1H0",
    "sg:province":"ON",
    "sg:tags":[
        "tree"
    ],
    "wof:name":"Colonial Tree Svc",
    "wof:placetype":"venue"
},
  "geometry": {"coordinates":[-79.978951,43.638409],"type":"Point"}
}