{
  "type": "Feature",
  "properties": {
    "addr:full":"6183 Boul Royal Shawinigan QC G9N 8P3",
    "addr:housenumber":"6183",
    "addr:postcode":"g9n 8p3",
    "addr:street":"Boul Royal",
    "iso:country":"CA",
    "sg:address":"6183 Boul Royal",
    "sg:city":"Shawinigan",
    "sg:classifiers":[
        {
            "category":"Restaurant",
            "type":"Food & Drink"
        }
    ],
    "sg:phone":"+1 819 539 6233",
    "sg:postcode":"G9N 8P3",
    "sg:province":"QC",
    "wof:name":"Restaurant Casa Greque",
    "wof:placetype":"venue"
},
  "geometry": {"coordinates":[-72.72188568120001,46.5724411011],"type":"Point"}
}