{
  "type": "Feature",
  "properties": {
    "addr:full":"6996 Greenwood St Burnaby BC V5A 1X8",
    "addr:housenumber":"6996",
    "addr:postcode":"v5a 1x8",
    "addr:street":"Greenwood St",
    "iso:country":"CA",
    "sg:address":"6996 Greenwood St",
    "sg:city":"Burnaby",
    "sg:classifiers":[
        {
            "category":"Communications",
            "subcategory":"Film & Video Production",
            "type":"Services"
        }
    ],
    "sg:phone":"+1 604 299 2022",
    "sg:postcode":"V5A 1X8",
    "sg:province":"BC",
    "sg:tags":[
        "motion",
        "picture"
    ],
    "wof:name":"International Spfx Group",
    "wof:placetype":"venue"
},
  "geometry": {"coordinates":[-122.95823669400001,49.2560691833],"type":"Point"}
}