{
  "type": "Feature",
  "properties": {
    "addr:full":"2300 Lawrence Ave E Scarborough ON M1P 2P9",
    "addr:housenumber":"2300",
    "addr:postcode":"m1p 2p9",
    "addr:street":"Lawrence Ave E",
    "iso:country":"CA",
    "sg:address":"2300 Lawrence Ave E",
    "sg:city":"Scarborough",
    "sg:classifiers":[
        {
            "category":"Professional",
            "subcategory":"Lawyer & Legal Services",
            "type":"Services"
        }
    ],
    "sg:phone":"+1 416 701 9559",
    "sg:postcode":"M1P 2P9",
    "sg:province":"ON",
    "sg:tags":[
        "attorney"
    ],
    "wof:name":"Bandara, Rina",
    "wof:placetype":"venue"
},
  "geometry": {"coordinates":[-79.27741241459999,43.7491645813],"type":"Point"}
}