{
  "type": "Feature",
  "properties": {
    "addr:full":"5215 Boul Saint-Laurent Montreal QC H2T 1S4",
    "addr:housenumber":"5215",
    "addr:postcode":"h2t 1s4",
    "addr:street":"Boul Saint-Laurent",
    "iso:country":"CA",
    "sg:address":"5215 Boul Saint-Laurent",
    "sg:city":"Montreal",
    "sg:classifiers":[
        {
            "category":"Restaurant",
            "type":"Food & Drink"
        }
    ],
    "sg:phone":"+1 514 278 8211",
    "sg:postcode":"H2T 1S4",
    "sg:province":"QC",
    "wof:name":"Restaurant Royal Cari",
    "wof:placetype":"venue"
},
  "geometry": {"coordinates":[-73.59484863279999,45.5241317749],"type":"Point"}
}