{
  "type": "Feature",
  "properties": {
    "iso:country":"CA",
    "sg:city":"Contrecoeur",
    "sg:classifiers":[
        {
            "category":"Home & Garden",
            "subcategory":"Building Materials",
            "type":"Retail Goods"
        }
    ],
    "sg:phone":"+1 450 587 5001",
    "sg:postcode":"J0L 1C0",
    "sg:province":"QC",
    "sg:tags":[
        "lock",
        "window",
        "locksmith",
        "plate"
    ],
    "wof:name":"Vitrerie Serrurier Hamel Inc",
    "wof:placetype":"venue"
},
  "geometry": {"coordinates":[-73.2307357788,45.855632782],"type":"Point"}
}