{
  "type": "Feature",
  "properties": {
    "addr:full":"99 Midale Rd London ON N5X 2R2",
    "addr:housenumber":"99",
    "addr:postcode":"n5x 2r2",
    "addr:street":"Midale Rd",
    "iso:country":"CA",
    "sg:address":"99 Midale Rd",
    "sg:city":"London",
    "sg:classifiers":[
        {
            "category":"Professional",
            "subcategory":"Advertising",
            "type":"Services"
        }
    ],
    "sg:phone":"+1 519 433 7496",
    "sg:postcode":"N5X 2R2",
    "sg:province":"ON",
    "sg:tags":[
        "counselor"
    ],
    "wof:name":"Rob Mackintosh & Assoc",
    "wof:placetype":"venue"
},
  "geometry": {"coordinates":[-81.25097700000001,43.039974],"type":"Point"}
}