{
  "type": "Feature",
  "properties": {
    "addr:full":"4205 Rue Des Roses # 6289 Charlesbourg QC G1G 1N9",
    "addr:housenumber":"4205",
    "addr:postcode":"g1g 1n9",
    "addr:street":"Rue Des Roses # 6289",
    "iso:country":"CA",
    "sg:address":"4205 Rue Des Roses # 6289",
    "sg:city":"Charlesbourg",
    "sg:classifiers":[
        {
            "category":"Organizations",
            "subcategory":"Professional Association",
            "type":"Services"
        }
    ],
    "sg:phone":"+1 418 623 2475",
    "sg:postcode":"G1G 1N9",
    "sg:province":"QC",
    "wof:name":"Chevaliers DE Colomb",
    "wof:placetype":"venue"
},
  "geometry": {"coordinates":[-71.286629,46.881264],"type":"Point"}
}