{
  "type": "Feature",
  "properties": {
    "addr:full":"681 Rue Notre-Dame Charette QC G0X 1E0",
    "addr:housenumber":"681",
    "addr:postcode":"g0x 1e0",
    "addr:street":"Rue Notre-Dame",
    "iso:country":"CA",
    "sg:address":"681 Rue Notre-Dame",
    "sg:city":"Charette",
    "sg:classifiers":[
        {
            "category":"Personal",
            "subcategory":"Beauty Salon",
            "type":"Services"
        }
    ],
    "sg:phone":"+1 819 221 2042",
    "sg:postcode":"G0X 1E0",
    "sg:province":"QC",
    "wof:name":"Salon Danielle Enrg",
    "wof:placetype":"venue"
},
  "geometry": {"coordinates":[-72.90889,46.448395],"type":"Point"}
}