{
  "type": "Feature",
  "properties": {
    "addr:full":"15 Rue Deschenes Saint-Quentin NB E8A 1M2",
    "addr:housenumber":"15",
    "addr:postcode":"e8a 1m2",
    "addr:street":"Rue Deschenes",
    "iso:country":"CA",
    "sg:address":"15 Rue Deschenes",
    "sg:city":"Saint-Quentin",
    "sg:classifiers":[
        {
            "category":"Education",
            "subcategory":"School",
            "type":"Public Place"
        }
    ],
    "sg:phone":"+1 506 235 6002",
    "sg:postcode":"E8A 1M2",
    "sg:province":"NB",
    "wof:name":"Mgr Martin Ecole",
    "wof:placetype":"venue"
},
  "geometry": {"coordinates":[-67.39134199999999,47.511539],"type":"Point"}
}