{
  "type": "Feature",
  "properties": {
    "iso:country":"CA",
    "sg:city":"London",
    "sg:classifiers":[
        {
            "category":"Shopping",
            "subcategory":"Gifts & Souvenirs",
            "type":"Retail Goods"
        }
    ],
    "sg:phone":"+1 519 432 0434",
    "sg:postcode":"N6C 3P7",
    "sg:province":"ON",
    "sg:tags":[
        "shop"
    ],
    "wof:name":"Curiosities Gift Shoppe",
    "wof:placetype":"venue"
},
  "geometry": {"coordinates":[-81.25249481199999,42.9719734192],"type":"Point"}
}