{
  "type": "Feature",
  "properties": {
    "addr:full":"166 Main St W Listowel ON N4W 1A1",
    "addr:housenumber":"166",
    "addr:postcode":"n4w 1a1",
    "addr:street":"Main St W",
    "iso:country":"CA",
    "sg:address":"166 Main St W",
    "sg:city":"Listowel",
    "sg:classifiers":[
        {
            "category":"Shopping",
            "subcategory":"Department Store",
            "type":"Retail Goods"
        }
    ],
    "sg:phone":"+1 519 291 4140",
    "sg:postcode":"N4W 1A1",
    "sg:province":"ON",
    "sg:tags":[
        "shop"
    ],
    "wof:name":"Target Discount",
    "wof:placetype":"venue"
},
  "geometry": {"coordinates":[-80.954025,43.731758],"type":"Point"}
}