{
  "type": "Feature",
  "properties": {
    "addr:full":"4631 Graham Ave Terrace BC V8G 1A6",
    "addr:housenumber":"4631",
    "addr:postcode":"v8g 1a6",
    "addr:street":"Graham Ave",
    "iso:country":"CA",
    "sg:address":"4631 Graham Ave",
    "sg:city":"Terrace",
    "sg:classifiers":[
        {
            "category":"Real Estate",
            "subcategory":"Real Estate Operator",
            "type":"Services"
        }
    ],
    "sg:phone":"+1 250 635 7773",
    "sg:postcode":"V8G 1A6",
    "sg:province":"BC",
    "sg:tags":[
        "mobile",
        "home",
        "community"
    ],
    "wof:name":"Terrace Trailer Court",
    "wof:placetype":"venue"
},
  "geometry": {"coordinates":[-128.58917236299999,54.5058288574],"type":"Point"}
}