{
  "type": "Feature",
  "properties": {
    "iso:country":"CA",
    "sg:address":"10723 98 St NW",
    "sg:city":"Edmonton",
    "sg:classifiers":[
        {
            "category":"Building & Trades",
            "subcategory":"Equipment Rental",
            "type":"Services"
        }
    ],
    "sg:phone":"+1 780 425 0359",
    "sg:postcode":"T5H 2N8",
    "sg:province":"AB",
    "sg:tags":[
        "player",
        "recorder",
        "video"
    ],
    "wof:name":"Viet Hoa Video Rental",
    "wof:placetype":"venue"
},
  "geometry": {"coordinates":[-113.490722656,53.5521888733],"type":"Point"}
}