{
  "type": "Feature",
  "properties": {
    "addr:full":"40 Nelson St Brantford ON N3T 2M8",
    "addr:housenumber":"40",
    "addr:postcode":"n3t 2m8",
    "addr:street":"Nelson St",
    "iso:country":"CA",
    "sg:address":"40 Nelson St",
    "sg:city":"Brantford",
    "sg:classifiers":[
        {
            "category":"Professional",
            "subcategory":"Lawyer & Legal Services",
            "type":"Services"
        }
    ],
    "sg:phone":"+1 519 759 1910",
    "sg:postcode":"N3T 2M8",
    "sg:province":"ON",
    "sg:tags":[
        "attorney"
    ],
    "wof:name":"Calder, Donald C",
    "wof:placetype":"venue"
},
  "geometry": {"coordinates":[-80.2654418945,43.1421661377],"type":"Point"}
}