{
  "type": "Feature",
  "properties": {
    "iso:country":"CA",
    "sg:address":"4343 Heritage Dr",
    "sg:city":"Tracy",
    "sg:classifiers":[
        {
            "category":"Building & Trades",
            "subcategory":"Construction",
            "type":"Services"
        }
    ],
    "sg:phone":"+1 506 368 2551",
    "sg:postcode":"E5L 1B4",
    "sg:province":"NB",
    "sg:tags":[
        "general",
        "contractor"
    ],
    "wof:name":"M E Phillips & Son Ltd",
    "wof:placetype":"venue"
},
  "geometry": {"coordinates":[-66.683899,45.683743],"type":"Point"}
}