{
  "type": "Feature",
  "properties": {
    "addr:full":"2280 Dundas St W Toronto ON M6R 1X3",
    "addr:housenumber":"2280",
    "addr:postcode":"m6r 1x3",
    "addr:street":"Dundas St W",
    "iso:country":"CA",
    "sg:address":"2280 Dundas St W",
    "sg:city":"Toronto",
    "sg:classifiers":[
        {
            "category":"Shopping",
            "subcategory":"Pharmacy",
            "type":"Retail Goods"
        }
    ],
    "sg:phone":"+1 416 533 0770",
    "sg:postcode":"M6R 1X3",
    "sg:province":"ON",
    "wof:name":"Drug Store Pharmacy",
    "wof:placetype":"venue"
},
  "geometry": {"coordinates":[-79.4519729614,43.6552848816],"type":"Point"}
}