{
  "type": "Feature",
  "properties": {
    "addr:full":"176 Yonge St Toronto ON M5C 2L7",
    "addr:housenumber":"176",
    "addr:postcode":"m5c 2l7",
    "addr:street":"Yonge St",
    "iso:country":"CA",
    "sg:address":"176 Yonge St",
    "sg:city":"Toronto",
    "sg:classifiers":[
        {
            "category":"Shopping",
            "subcategory":"Pharmacy",
            "type":"Retail Goods"
        }
    ],
    "sg:phone":"+1 416 861 6335",
    "sg:postcode":"M5C 2L7",
    "sg:province":"ON",
    "wof:name":"Bay Pharmacy",
    "wof:placetype":"venue"
},
  "geometry": {"coordinates":[-79.3792953491,43.6520271301],"type":"Point"}
}