{
  "type": "Feature",
  "properties": {
    "addr:full":"128 Eleanor Cir Richmond Hill ON L4C 6K7",
    "addr:housenumber":"128",
    "addr:postcode":"l4c 6k7",
    "addr:street":"Eleanor Cir",
    "iso:country":"CA",
    "sg:address":"128 Eleanor Cir",
    "sg:city":"Richmond Hill",
    "sg:classifiers":[
        {
            "category":"Communications",
            "subcategory":"Film & Video Production",
            "type":"Services"
        }
    ],
    "sg:phone":"+1 416 902 1032",
    "sg:postcode":"L4C 6K7",
    "sg:province":"ON",
    "sg:tags":[
        "consultant",
        "audio"
    ],
    "wof:name":"Nabel Communication Systems",
    "wof:placetype":"venue"
},
  "geometry": {"coordinates":[-79.43222,43.840759],"type":"Point"}
}