{
  "type": "Feature",
  "properties": {
    "addr:full":"Edmonton AB T5J 1V9",
    "addr:postcode":"t5j 1v9",
    "iso:country":"CA",
    "sg:city":"Edmonton",
    "sg:classifiers":[
        {
            "category":"Health Services",
            "subcategory":"Doctor",
            "type":"Services"
        }
    ],
    "sg:phone":"+1 780 423 6940",
    "sg:postcode":"T5J 1V9",
    "sg:province":"AB",
    "sg:tags":[
        "dentist"
    ],
    "wof:name":"Devevc, Teresa DDS",
    "wof:placetype":"venue"
},
  "geometry": {"coordinates":[-113.493118286,53.54114151],"type":"Point"}
}