{
  "type": "Feature",
  "properties": {
    "addr:full":"740 Hot Springs Rd Harrison Hot Springs BC V0M 1K0",
    "addr:housenumber":"740",
    "addr:postcode":"v0m 1k0",
    "addr:street":"Hot Springs Rd",
    "iso:country":"CA",
    "sg:address":"740 Hot Springs Rd",
    "sg:city":"Harrison Hot Springs",
    "sg:classifiers":[
        {
            "category":"Travel",
            "subcategory":"Campground",
            "type":"Entertainment"
        }
    ],
    "sg:phone":"+1 604 796 8900",
    "sg:postcode":"V0M 1K0",
    "sg:province":"BC",
    "wof:name":"Harrison Springs Camping & Rv",
    "wof:placetype":"venue"
},
  "geometry": {"coordinates":[-121.780289,49.29007],"type":"Point"}
}