{
  "type": "Feature",
  "properties": {
    "iso:country":"CA",
    "sg:city":"Kitchener",
    "sg:classifiers":[
        {
            "category":"Professional",
            "subcategory":"Employment Agencies",
            "type":"Services"
        }
    ],
    "sg:phone":"+1 519 894 3030",
    "sg:postcode":"N2A 3Y4",
    "sg:province":"ON",
    "sg:tags":[
        "consultant",
        "search",
        "executive",
        "opportunity"
    ],
    "wof:name":"Kitchener Executive Conslnts",
    "wof:placetype":"venue"
},
  "geometry": {"coordinates":[-80.42068481450001,43.4284934998],"type":"Point"}
}