{
  "type": "Feature",
  "properties": {
    "addr:full":"12510 128 St NW Edmonton AB T5L 1C8",
    "addr:housenumber":"12510",
    "addr:postcode":"t5l 1c8",
    "addr:street":"128 St Nw",
    "iso:country":"CA",
    "sg:address":"12510 128 St NW",
    "sg:city":"Edmonton",
    "sg:classifiers":[
        {
            "category":"Manufacturing",
            "subcategory":"Tools & Machinery",
            "type":"Manufacturing & Wholesale Goods"
        }
    ],
    "sg:phone":"+1 780 460 0599",
    "sg:postcode":"T5L 1C8",
    "sg:province":"AB",
    "sg:tags":[
        "equipment",
        "welding",
        "supply"
    ],
    "wof:name":"Saballoy Inc",
    "wof:placetype":"venue"
},
  "geometry": {"coordinates":[-113.543091,53.581406],"type":"Point"}
}