{
  "type": "Feature",
  "properties": {
    "addr:full":"38 King St Saint John NB E2L 1G3",
    "addr:housenumber":"38",
    "addr:postcode":"nb e2l 1g3",
    "addr:street":"King St",
    "iso:country":"CA",
    "sg:address":"38 King St",
    "sg:city":"Saint John",
    "sg:classifiers":[
        {
            "category":"Food & Beverages",
            "subcategory":"Groceries & Convenience Stores",
            "type":"Retail Goods"
        }
    ],
    "sg:phone":"+1 506 634 1827",
    "sg:postcode":"E2L 1G3",
    "sg:province":"NB",
    "wof:name":"Quality Convenience Store",
    "wof:placetype":"venue"
},
  "geometry": {"coordinates":[-66.0607757568,45.2729911804],"type":"Point"}
}