{
  "type": "Feature",
  "properties": {
    "iso:country":"CA",
    "sg:city":"London",
    "sg:classifiers":[
        {
            "category":"Wholesale",
            "subcategory":"Durable Goods & Equipment",
            "type":"Manufacturing & Wholesale Goods"
        }
    ],
    "sg:phone":"+1 519 652 6913",
    "sg:postcode":"N6L 1A8",
    "sg:province":"ON",
    "sg:tags":[
        "fire",
        "extinguisher"
    ],
    "wof:name":"London Fire Equipment Ltd",
    "wof:placetype":"venue"
},
  "geometry": {"coordinates":[-81.27899169920001,42.9291725159],"type":"Point"}
}