{
  "type": "Feature",
  "properties": {
    "addr:full":"116 Main St S Kenora ON P9N 1S9",
    "addr:housenumber":"116",
    "addr:postcode":"p9n 1s9",
    "addr:street":"Main St S",
    "iso:country":"CA",
    "sg:address":"116 Main St S",
    "sg:city":"Kenora",
    "sg:classifiers":[
        {
            "category":"Shopping",
            "subcategory":"Pharmacy",
            "type":"Retail Goods"
        }
    ],
    "sg:phone":"+1 807 468 7412",
    "sg:postcode":"P9N 1S9",
    "sg:province":"ON",
    "wof:name":"Johnson's Pharmacy",
    "wof:placetype":"venue"
},
  "geometry": {"coordinates":[-94.490471,49.76746],"type":"Point"}
}