{
  "type": "Feature",
  "properties": {
    "addr:full":"Burnaby BC V5J 1G1",
    "addr:postcode":"v5j 1g1",
    "iso:country":"CA",
    "sg:city":"Burnaby",
    "sg:classifiers":[
        {
            "category":"Personal",
            "subcategory":"Massage",
            "type":"Services"
        }
    ],
    "sg:phone":"+1 604 438 8979",
    "sg:postcode":"V5J 1G1",
    "sg:province":"BC",
    "wof:name":"Imperial Shiatsu Ctr",
    "wof:placetype":"venue"
},
  "geometry": {"coordinates":[-122.982491,49.222137],"type":"Point"}
}