{
  "type": "Feature",
  "properties": {
    "addr:full":"2416 16 Ave NW Calgary AB T2M 0M5",
    "addr:housenumber":"2416",
    "addr:postcode":"t2m 0m5",
    "addr:street":"16 Ave Nw",
    "iso:country":"CA",
    "sg:address":"2416 16 Ave NW",
    "sg:city":"Calgary",
    "sg:classifiers":[
        {
            "category":"Travel",
            "subcategory":"Hotels & Motels",
            "type":"Entertainment"
        }
    ],
    "sg:phone":"+1 403 289 6651",
    "sg:postcode":"T2M 0M5",
    "sg:province":"AB",
    "wof:name":"Royal Wayne Motor Inn",
    "wof:placetype":"venue"
},
  "geometry": {"coordinates":[-114.115638733,51.067363739],"type":"Point"}
}