{
  "type": "Feature",
  "properties": {
    "iso:country":"CA",
    "sg:address":"120 Holland Park Ave",
    "sg:city":"York",
    "sg:classifiers":[
        {
            "category":"Building & Trades",
            "subcategory":"Construction",
            "type":"Services"
        }
    ],
    "sg:phone":"+1 416 653 9268",
    "sg:postcode":"M6E 1L6",
    "sg:province":"ON",
    "sg:tags":[
        "resurfacing",
        "laying",
        "refinishing",
        "floor"
    ],
    "wof:name":"Demitris Floor Sanding",
    "wof:placetype":"venue"
},
  "geometry": {"coordinates":[-79.4400253296,43.6861953735],"type":"Point"}
}