{
  "type": "Feature",
  "properties": {
    "addr:full":"Coquitlam BC V3K 6V2",
    "addr:postcode":"v3k 6v2",
    "iso:country":"CA",
    "sg:city":"Coquitlam",
    "sg:classifiers":[
        {
            "category":"Professional",
            "subcategory":"Business Services",
            "type":"Services"
        }
    ],
    "sg:phone":"+1 604 526 5112",
    "sg:postcode":"V3K 6V2",
    "sg:province":"BC",
    "sg:tags":[
        "embroidery"
    ],
    "wof:name":"Accupunch Enterprises Inc",
    "wof:placetype":"venue"
},
  "geometry": {"coordinates":[-122.83386993400001,49.2240257263],"type":"Point"}
}