{
  "type": "Feature",
  "properties": {
    "addr:full":"1950 Forbes St Whitby ON L1N 7B7",
    "addr:housenumber":"1950",
    "addr:postcode":"l1n 7b7",
    "addr:street":"Forbes St",
    "iso:country":"CA",
    "sg:address":"1950 Forbes St",
    "sg:city":"Whitby",
    "sg:classifiers":[
        {
            "category":"Manufacturing",
            "subcategory":"Metals",
            "type":"Manufacturing & Wholesale Goods"
        }
    ],
    "sg:phone":"+1 905 571 2200",
    "sg:postcode":"L1N 7B7",
    "sg:province":"ON",
    "sg:tags":[
        "tool"
    ],
    "wof:name":"Makita Canada Inc",
    "wof:placetype":"venue"
},
  "geometry": {"coordinates":[-78.895401001,43.8626365662],"type":"Point"}
}