{
  "type": "Feature",
  "properties": {
    "addr:full":"12221 Boundary Dr N Surrey BC V3X 1Z5",
    "addr:housenumber":"12221",
    "addr:postcode":"v3x 1z5",
    "addr:street":"Boundary Dr N",
    "iso:country":"CA",
    "sg:address":"12221 Boundary Dr N",
    "sg:city":"Surrey",
    "sg:classifiers":[
        {
            "category":"Retail",
            "subcategory":"Portrait Studio",
            "type":"Services"
        }
    ],
    "sg:phone":"+1 604 501 6688",
    "sg:postcode":"V3X 1Z5",
    "sg:province":"BC",
    "sg:tags":[
        "photographer"
    ],
    "wof:name":"Cooper's Photography",
    "wof:placetype":"venue"
},
  "geometry": {"coordinates":[-122.884963989,49.1175689697],"type":"Point"}
}