{
  "type": "Feature",
  "properties": {
    "iso:country":"CA",
    "sg:city":"New Westminster",
    "sg:classifiers":[
        {
            "category":"Wholesale",
            "subcategory":"Hardware",
            "type":"Manufacturing & Wholesale Goods"
        }
    ],
    "sg:phone":"+1 604 527 7777",
    "sg:postcode":"V3L 5H4",
    "sg:province":"BC",
    "sg:tags":[
        "fastener"
    ],
    "wof:name":"Lily Fasteners",
    "wof:placetype":"venue"
},
  "geometry": {"coordinates":[-122.887245,49.231705],"type":"Point"}
}