{
  "type": "Feature",
  "properties": {
    "addr:full":"Stoney Creek ON L8G 2C5",
    "addr:postcode":"l8g 2c5",
    "iso:country":"CA",
    "sg:city":"Stoney Creek",
    "sg:classifiers":[
        {
            "category":"Shopping",
            "subcategory":"Pharmacy",
            "type":"Retail Goods"
        }
    ],
    "sg:phone":"+1 905 664 4005",
    "sg:postcode":"L8G 2C5",
    "sg:province":"ON",
    "wof:name":"Healthcare Plus Pharmacy",
    "wof:placetype":"venue"
},
  "geometry": {"coordinates":[-79.774506,43.177597],"type":"Point"}
}