{
  "type": "Feature",
  "properties": {
    "addr:full":"4601 Kingston Rd Scarborough ON M1E 2P3",
    "addr:housenumber":"4601",
    "addr:postcode":"m1e 2p3",
    "addr:street":"Kingston Rd",
    "iso:country":"CA",
    "sg:address":"4601 Kingston Rd",
    "sg:city":"Scarborough",
    "sg:classifiers":[
        {
            "category":"Restaurant",
            "type":"Food & Drink"
        }
    ],
    "sg:phone":"+1 416 282 1171",
    "sg:postcode":"M1E 2P3",
    "sg:province":"ON",
    "wof:name":"House of Wong",
    "wof:placetype":"venue"
},
  "geometry": {"coordinates":[-79.18319700000001,43.773846],"type":"Point"}
}