{
  "type": "Feature",
  "properties": {
    "addr:full":"4254 Bethesda Rd Stouffville ON L4A 7X5",
    "addr:housenumber":"4254",
    "addr:postcode":"l4a 7x5",
    "addr:street":"Bethesda Rd",
    "iso:country":"CA",
    "sg:address":"4254 Bethesda Rd",
    "sg:city":"Stouffville",
    "sg:classifiers":[
        {
            "category":"Building & Trades",
            "subcategory":"Landscaping Services",
            "type":"Services"
        }
    ],
    "sg:phone":"+1 905 642 8873",
    "sg:postcode":"L4A 7X5",
    "sg:province":"ON",
    "sg:tags":[
        "lawn",
        "maintenance",
        "grounds"
    ],
    "wof:name":"Lawn Rangers Ltd",
    "wof:placetype":"venue"
},
  "geometry": {"coordinates":[-79.31560500000001,43.975712],"type":"Point"}
}