{
  "type": "Feature",
  "properties": {
    "iso:country":"CA",
    "sg:address":"119 Rue Bertrand",
    "sg:city":"Beauport",
    "sg:classifiers":[
        {
            "category":"Food & Beverages",
            "subcategory":"Groceries & Convenience Stores",
            "type":"Retail Goods"
        }
    ],
    "sg:phone":"+1 418 663 6052",
    "sg:postcode":"G1B 1H8",
    "sg:province":"QC",
    "sg:tags":[
        "grocer"
    ],
    "wof:name":"Marche Fleuri Enr",
    "wof:placetype":"venue"
},
  "geometry": {"coordinates":[-71.1899185181,46.9015083313],"type":"Point"}
}