{
  "type": "Feature",
  "properties": {
    "addr:full":"4709 27 St Vernon BC V1T 4Y8",
    "addr:housenumber":"4709",
    "addr:postcode":"v1t 4y8",
    "addr:street":"27 St",
    "iso:country":"CA",
    "sg:address":"4709 27 St",
    "sg:city":"Vernon",
    "sg:classifiers":[
        {
            "category":"Autos & Motor Vehicles",
            "subcategory":"Fuel & Gas Station",
            "type":"Retail Goods"
        }
    ],
    "sg:phone":"+1 250 542 1255",
    "sg:postcode":"V1T 4Y8",
    "sg:province":"BC",
    "sg:tags":[
        "oil"
    ],
    "wof:name":"Mike's Village Green Petro-Can",
    "wof:placetype":"venue"
},
  "geometry": {"coordinates":[-119.266251,50.280766],"type":"Point"}
}