{
  "type": "Feature",
  "properties": {
    "addr:full":"189 Laurier Ave E Ottawa ON K1N 6P1",
    "addr:housenumber":"189",
    "addr:postcode":"k1n 6p1",
    "addr:street":"Laurier Ave E",
    "iso:country":"CA",
    "sg:address":"189 Laurier Ave E",
    "sg:city":"Ottawa",
    "sg:classifiers":[
        {
            "category":"Government",
            "subcategory":"Office",
            "type":"Public Place"
        }
    ],
    "sg:phone":"+1 613 234 1152",
    "sg:postcode":"K1N 6P1",
    "sg:province":"ON",
    "sg:tags":[
        "federal",
        "affairs"
    ],
    "wof:name":"Embassy of Republic of Angola",
    "wof:placetype":"venue"
},
  "geometry": {"coordinates":[-75.6828155518,45.4254188538],"type":"Point"}
}