{
  "type": "Feature",
  "properties": {
    "addr:full":"368 Kings Rd Sydney NS B1S 1A8",
    "addr:housenumber":"368",
    "addr:postcode":"b1s 1a8",
    "addr:street":"Kings Rd",
    "iso:country":"CA",
    "sg:address":"368 Kings Rd",
    "sg:city":"Sydney",
    "sg:classifiers":[
        {
            "category":"Travel",
            "subcategory":"Hotels & Motels",
            "type":"Entertainment"
        }
    ],
    "sg:phone":"+1 902 562 0200",
    "sg:postcode":"B1S 1A8",
    "sg:province":"NS",
    "wof:name":"Comfort Inn",
    "wof:placetype":"venue"
},
  "geometry": {"coordinates":[-60.200706,46.123817],"type":"Point"}
}