{
  "type": "Feature",
  "properties": {
    "addr:full":"1170 Pitt St #2 Cornwall ON K6J 3T2",
    "addr:housenumber":"1170",
    "addr:postcode":"k6j 3t2",
    "addr:street":"Pitt St # 2",
    "iso:country":"CA",
    "sg:address":"1170 Pitt St #2",
    "sg:city":"Cornwall",
    "sg:classifiers":[
        {
            "category":"Banks & Credit Unions",
            "subcategory":"Bank",
            "type":"Services"
        }
    ],
    "sg:phone":"+1 613 936 1855",
    "sg:postcode":"K6J 3T2",
    "sg:province":"ON",
    "sg:tags":[
        "loan",
        "real estate"
    ],
    "wof:name":"Citi Financial",
    "wof:placetype":"venue"
},
  "geometry": {"coordinates":[-74.7390823364,45.0324058533],"type":"Point"}
}