{
  "type": "Feature",
  "properties": {
    "addr:full":"401 Weston Rd York ON M6N 3P7",
    "addr:housenumber":"401",
    "addr:postcode":"m6n 3p7",
    "addr:street":"Weston Rd",
    "iso:country":"CA",
    "sg:address":"401 Weston Rd",
    "sg:city":"York",
    "sg:classifiers":[
        {
            "category":"Autos & Motor Vehicles",
            "subcategory":"Fuel & Gas Station",
            "type":"Retail Goods"
        }
    ],
    "sg:phone":"+1 416 767 5440",
    "sg:postcode":"M6N 3P7",
    "sg:province":"ON",
    "sg:tags":[
        "oil"
    ],
    "wof:name":"Weston Management",
    "wof:placetype":"venue"
},
  "geometry": {"coordinates":[-79.476128,43.681213],"type":"Point"}
}