{
  "type": "Feature",
  "properties": {
    "addr:full":"644 Partington Ave Windsor ON N9B 2N7",
    "addr:housenumber":"644",
    "addr:postcode":"n9b 2n7",
    "addr:street":"Partington Ave",
    "iso:country":"CA",
    "sg:address":"644 Partington Ave",
    "sg:city":"Windsor",
    "sg:classifiers":[
        {
            "category":"Organizations",
            "subcategory":"Religious Organization",
            "type":"Services"
        }
    ],
    "sg:phone":"+1 519 969 6347",
    "sg:postcode":"N9B 2N7",
    "sg:province":"ON",
    "sg:tags":[
        "church"
    ],
    "wof:name":"Gospel Hall",
    "wof:placetype":"venue"
},
  "geometry": {"coordinates":[-83.05838775629999,42.3056259155],"type":"Point"}
}