{
  "type": "Feature",
  "properties": {
    "addr:full":"141 Sturdies Bay Rd Galiano BC V0N 1P0",
    "addr:housenumber":"141",
    "addr:postcode":"v0n 1p0",
    "addr:street":"Sturdies Bay Rd",
    "iso:country":"CA",
    "sg:address":"141 Sturdies Bay Rd",
    "sg:city":"Galiano",
    "sg:classifiers":[
        {
            "category":"Museum",
            "type":"Entertainment"
        }
    ],
    "sg:phone":"+1 250 539 5904",
    "sg:postcode":"V0N 1P0",
    "sg:province":"BC",
    "sg:tags":[
        "organization",
        "arts",
        "information"
    ],
    "wof:name":"Access To Media Education Soc",
    "wof:placetype":"venue"
},
  "geometry": {"coordinates":[-123.34214782700001,48.8897094727],"type":"Point"}
}