{
  "type": "Feature",
  "properties": {
    "iso:country":"CA",
    "sg:city":"Caledon East",
    "sg:classifiers":[
        {
            "category":"Home & Garden",
            "subcategory":"Garden Supply",
            "type":"Retail Goods"
        }
    ],
    "sg:phone":"+1 905 584 1867",
    "sg:postcode":"L0N 1E0",
    "sg:province":"ON",
    "sg:tags":[
        "sprinkler"
    ],
    "wof:name":"Thirsty Lawn Inc",
    "wof:placetype":"venue"
},
  "geometry": {"coordinates":[-79.8599472046,43.8752670288],"type":"Point"}
}