{
  "type": "Feature",
  "properties": {
    "addr:full":"Botwood NL A0H 1E0",
    "iso:country":"CA",
    "sg:city":"Botwood",
    "sg:classifiers":[
        {
            "category":"Food & Beverages",
            "subcategory":"Bakery",
            "type":"Retail Goods"
        }
    ],
    "sg:phone":"+1 709 257 2210",
    "sg:postcode":"A0H 1E0",
    "sg:province":"NL",
    "sg:tags":[
        "baker"
    ],
    "wof:name":"Family Bake Shoppe",
    "wof:placetype":"venue"
},
  "geometry": {"coordinates":[-55.3608207703,49.1424560547],"type":"Point"}
}