{
  "type": "Feature",
  "properties": {
    "addr:full":"408 Broadway St W Nakusp BC V0G 1R0",
    "addr:housenumber":"408",
    "addr:postcode":"v0g 1r0",
    "addr:street":"Broadway St W",
    "iso:country":"CA",
    "sg:address":"408 Broadway St W",
    "sg:city":"Nakusp",
    "sg:classifiers":[
        {
            "category":"Restaurant",
            "type":"Food & Drink"
        }
    ],
    "sg:phone":"+1 250 265 3767",
    "sg:postcode":"V0G 1R0",
    "sg:province":"BC",
    "sg:tags":[
        "delicatessen"
    ],
    "wof:name":"Broadway Deli Bistro",
    "wof:placetype":"venue"
},
  "geometry": {"coordinates":[-117.80296300000001,50.238865],"type":"Point"}
}