{
  "type": "Feature",
  "properties": {
    "iso:country":"CA",
    "sg:address":"8278 Rue Pascal-Gagnon",
    "sg:city":"Saint-Leonard",
    "sg:classifiers":[
        {
            "category":"Building & Trades",
            "subcategory":"Equipment Rental",
            "type":"Services"
        }
    ],
    "sg:phone":"+1 514 328 4888",
    "sg:postcode":"H1P 1Y4",
    "sg:province":"QC",
    "sg:tags":[
        "crane"
    ],
    "wof:name":"Lecavalier Transfer Inc",
    "wof:placetype":"venue"
},
  "geometry": {"coordinates":[-73.5824508667,45.599811554],"type":"Point"}
}