{
  "type": "Feature",
  "properties": {
    "addr:full":"Victoria BC V9A 2Y9",
    "addr:postcode":"v9a 2y9",
    "iso:country":"CA",
    "sg:city":"Victoria",
    "sg:classifiers":[
        {
            "category":"Banks & Credit Unions",
            "subcategory":"Bank",
            "type":"Services"
        }
    ],
    "sg:phone":"+1 250 382 8934",
    "sg:postcode":"V9A 2Y9",
    "sg:province":"BC",
    "sg:tags":[
        "financing"
    ],
    "wof:name":"Sumida & Assoc",
    "wof:placetype":"venue"
},
  "geometry": {"coordinates":[-123.393936,48.439781],"type":"Point"}
}