{
  "type": "Feature",
  "properties": {
    "addr:full":"3412 Kalum St Terrace BC V8G 4T2",
    "addr:housenumber":"3412",
    "addr:postcode":"v8g 4t2",
    "addr:street":"Kalum St Terrace",
    "iso:country":"CA",
    "sg:address":"3412 Kalum St",
    "sg:city":"Terrace",
    "sg:classifiers":[
        {
            "category":"Government",
            "subcategory":"Office",
            "type":"Public Place"
        }
    ],
    "sg:phone":"+1 250 638 2220",
    "sg:postcode":"V8G 4T2",
    "sg:province":"BC",
    "wof:name":"British Columbia Health Svc",
    "wof:placetype":"venue"
},
  "geometry": {"coordinates":[-128.58624267600001,54.5211219788],"type":"Point"}
}