{
  "type": "Feature",
  "properties": {
    "addr:full":"8927 Commercial St New Minas NS B4N 3E1",
    "addr:housenumber":"8927",
    "addr:postcode":"b4n 3e1",
    "addr:street":"Commercial St",
    "iso:country":"CA",
    "sg:address":"8927 Commercial St",
    "sg:city":"New Minas",
    "sg:classifiers":[
        {
            "category":"Cinema",
            "subcategory":"Movie Rental",
            "type":"Entertainment"
        }
    ],
    "sg:phone":"+1 902 681 0281",
    "sg:postcode":"B4N 3E1",
    "sg:province":"NS",
    "sg:tags":[
        "leasing",
        "video",
        "disc",
        "tape"
    ],
    "wof:name":"Blockbuster Video",
    "wof:placetype":"venue"
},
  "geometry": {"coordinates":[-64.46436300000001,45.068466],"type":"Point"}
}