{
  "type": "Feature",
  "properties": {
    "iso:country":"CA",
    "sg:address":"434 2E Av",
    "sg:city":"Sainte-Marie",
    "sg:classifiers":[
        {
            "category":"Manufacturing",
            "subcategory":"Apparel",
            "type":"Manufacturing & Wholesale Goods"
        }
    ],
    "sg:phone":"+1 418 387 5247",
    "sg:postcode":"G6E 1B6",
    "sg:province":"QC",
    "sg:tags":[
        "tarpaulin"
    ],
    "wof:name":"Toiles Industrielles DE Beauce",
    "wof:placetype":"venue"
},
  "geometry": {"coordinates":[-65.98382599999999,48.172626],"type":"Point"}
}