{
  "type": "Feature",
  "properties": {
    "addr:full":"119 Main St Invermay SK S0A 1M0",
    "addr:housenumber":"119",
    "addr:postcode":"s0a 1m0",
    "addr:street":"Main St",
    "iso:country":"CA",
    "sg:address":"119 Main St",
    "sg:city":"Invermay",
    "sg:classifiers":[
        {
            "category":"Shopping",
            "subcategory":"Catalog Store",
            "type":"Retail Goods"
        }
    ],
    "sg:phone":"+1 306 593 2025",
    "sg:postcode":"S0A 1M0",
    "sg:province":"SK",
    "sg:tags":[
        "mail",
        "order",
        "internet"
    ],
    "wof:name":"Sears Canada Inc",
    "wof:placetype":"venue"
},
  "geometry": {"coordinates":[-103.153221,51.805794],"type":"Point"}
}