{
  "type": "Feature",
  "properties": {
    "addr:full":"50 Rue Du Souvenir Sainte-Melanie QC J0K 3A0",
    "addr:housenumber":"50",
    "addr:postcode":"j0k 3a0",
    "addr:street":"Rue Du Souvenir Sainte-Melanie",
    "iso:country":"CA",
    "sg:address":"50 Rue Du Souvenir",
    "sg:city":"Sainte-Melanie",
    "sg:classifiers":[
        {
            "category":"Retail",
            "subcategory":"Laundry & Dry Cleaning",
            "type":"Services"
        }
    ],
    "sg:phone":"+1 450 889 8664",
    "sg:postcode":"J0K 3A0",
    "sg:province":"QC",
    "sg:tags":[
        "cleaners",
        "rug",
        "carpet"
    ],
    "wof:name":"Services D'Entretien Fany Inc",
    "wof:placetype":"venue"
},
  "geometry": {"coordinates":[-73.50965118409999,46.1317443848],"type":"Point"}
}