{
  "type": "Feature",
  "properties": {
    "addr:full":"North York ON M3H 3N2",
    "addr:postcode":"m3h 3n2",
    "iso:country":"CA",
    "sg:city":"North York",
    "sg:classifiers":[
        {
            "category":"Organizations",
            "subcategory":"Religious Organization",
            "type":"Services"
        }
    ],
    "sg:phone":"+1 416 630 0375",
    "sg:postcode":"M3H 3N2",
    "sg:province":"ON",
    "wof:name":"Ccrj",
    "wof:placetype":"venue"
},
  "geometry": {"coordinates":[-79.434555,43.740383],"type":"Point"}
}