{
  "type": "Feature",
  "properties": {
    "addr:full":"Saint-Adalbert QC G0R 2M0",
    "addr:postcode":"g0r 2m0",
    "iso:country":"CA",
    "sg:city":"Saint-Adalbert",
    "sg:classifiers":[
        {
            "category":"Retail",
            "subcategory":"Auto Repair",
            "type":"Services"
        }
    ],
    "sg:phone":"+1 418 356 2212",
    "sg:postcode":"G0R 2M0",
    "sg:province":"QC",
    "sg:tags":[
        "repairing",
        "automobile"
    ],
    "wof:name":"Garage Alain Bourgault",
    "wof:placetype":"venue"
},
  "geometry": {"coordinates":[-69.89669000000001,46.864746],"type":"Point"}
}