{
  "type": "Feature",
  "properties": {
    "iso:country":"CA",
    "sg:city":"Port Coquitlam",
    "sg:classifiers":[
        {
            "category":"Retail",
            "subcategory":"Auto Repair",
            "type":"Services"
        }
    ],
    "sg:phone":"+1 604 941 1975",
    "sg:postcode":"V3B 1H7",
    "sg:province":"BC",
    "sg:tags":[
        "body",
        "automobile",
        "painting"
    ],
    "wof:name":"Coast Collision",
    "wof:placetype":"venue"
},
  "geometry": {"coordinates":[-122.763473511,49.2671890259],"type":"Point"}
}