{
  "type": "Feature",
  "properties": {
    "addr:full":"3919 Ch DE LA Lievre N Mont-Laurier QC J9L 3G4",
    "addr:postcode":"3919;j9l 3g4",
    "addr:street":"Ch De La Lievre N",
    "iso:country":"CA",
    "sg:address":"3919 Ch DE LA Lievre N",
    "sg:city":"Mont-Laurier",
    "sg:classifiers":[
        {
            "category":"Retail",
            "subcategory":"Auto Repair",
            "type":"Services"
        }
    ],
    "sg:phone":"+1 819 623 2793",
    "sg:postcode":"J9L 3G4",
    "sg:province":"QC",
    "sg:tags":[
        "repairing",
        "automobile",
        "body"
    ],
    "wof:name":"Auto Pro-Renovation Inc",
    "wof:placetype":"venue"
},
  "geometry": {"coordinates":[-75.4818572998,46.5759353638],"type":"Point"}
}