{
  "type": "Feature",
  "properties": {
    "iso:country":"CA",
    "sg:city":"Peterborough",
    "sg:classifiers":[
        {
            "category":"Wholesale",
            "subcategory":"Electrical",
            "type":"Manufacturing & Wholesale Goods"
        }
    ],
    "sg:phone":"+1 705 745 5017",
    "sg:postcode":"K9J 6X3",
    "sg:province":"ON",
    "sg:tags":[
        "control",
        "security",
        "door"
    ],
    "wof:name":"Central Aluminum",
    "wof:placetype":"venue"
},
  "geometry": {"coordinates":[-78.321312,44.300732],"type":"Point"}
}