{
  "type": "Feature",
  "properties": {
    "addr:full":"70 Rte Sainte-Marie Champlain QC G0X 1C0",
    "addr:housenumber":"70",
    "addr:postcode":"g0x 1c0",
    "addr:street":"Rte Sainte-Marie",
    "iso:country":"CA",
    "sg:address":"70 Rte Sainte-Marie",
    "sg:city":"Champlain",
    "sg:classifiers":[
        {
            "category":"Building & Trades",
            "subcategory":"Electrical",
            "type":"Services"
        }
    ],
    "sg:phone":"+1 819 295 3437",
    "sg:postcode":"G0X 1C0",
    "sg:province":"QC",
    "sg:tags":[
        "electric",
        "contractor"
    ],
    "wof:name":"R Beaudoin Electrique Ltee",
    "wof:placetype":"venue"
},
  "geometry": {"coordinates":[-72.320892,46.452793],"type":"Point"}
}