{
  "type": "Feature",
  "properties": {
    "addr:full":"1233 Woodbine Ave East York ON M4C 4E5",
    "addr:housenumber":"1233",
    "addr:postcode":"m4c 4e5",
    "addr:street":"Woodbine Ave",
    "iso:country":"CA",
    "sg:address":"1233 Woodbine Ave",
    "sg:city":"East York",
    "sg:classifiers":[
        {
            "category":"Cinema",
            "subcategory":"Movie Rental",
            "type":"Entertainment"
        }
    ],
    "sg:phone":"+1 416 421 8373",
    "sg:postcode":"M4C 4E5",
    "sg:province":"ON",
    "sg:tags":[
        "leasing",
        "video",
        "disc",
        "tape"
    ],
    "wof:name":"New Star Video",
    "wof:placetype":"venue"
},
  "geometry": {"coordinates":[-79.315765,43.692917],"type":"Point"}
}