{
  "type": "Feature",
  "properties": {
    "iso:country":"CA",
    "sg:city":"Toronto",
    "sg:classifiers":[
        {
            "category":"Shopping",
            "subcategory":"Shoes",
            "type":"Retail Goods"
        }
    ],
    "sg:phone":"+1 416 691 6706",
    "sg:postcode":"M4L 1H9",
    "sg:province":"ON",
    "wof:name":"Nature's Footwear",
    "wof:placetype":"venue"
},
  "geometry": {"coordinates":[-79.3011474609,43.6696624756],"type":"Point"}
}