{
  "type": "Feature",
  "properties": {
    "iso:country":"CA",
    "sg:address":"312 Snyder's Rd E",
    "sg:city":"Baden",
    "sg:classifiers":[
        {
            "category":"Retail",
            "subcategory":"Auto Repair",
            "type":"Services"
        }
    ],
    "sg:phone":"+1 519 634 8526",
    "sg:postcode":"N3A 2V7",
    "sg:province":"ON",
    "sg:tags":[
        "automobile",
        "painting",
        "truck"
    ],
    "wof:name":"Rick's Custom Body & Paint",
    "wof:placetype":"venue"
},
  "geometry": {"coordinates":[-80.66796875,43.4029083252],"type":"Point"}
}