{
  "type": "Feature",
  "properties": {
    "addr:full":"718 Railway Ave Rocanville SK S0A 3L0",
    "addr:housenumber":"718",
    "addr:postcode":"s0a 3l0",
    "addr:street":"Railway Ave",
    "iso:country":"CA",
    "sg:address":"718 Railway Ave",
    "sg:city":"Rocanville",
    "sg:classifiers":[
        {
            "category":"Food & Beverages",
            "subcategory":"Groceries & Convenience Stores",
            "type":"Retail Goods"
        }
    ],
    "sg:phone":"+1 306 645 2101",
    "sg:postcode":"S0A 3L0",
    "sg:province":"SK",
    "wof:name":"Highway 8 Gas Bar",
    "wof:placetype":"venue"
},
  "geometry": {"coordinates":[-101.699920654,50.3824424744],"type":"Point"}
}