{
  "type": "Feature",
  "properties": {
    "addr:full":"Vancouver BC V5L 2G1",
    "addr:postcode":"v5l 2g1",
    "iso:country":"CA",
    "sg:city":"Vancouver",
    "sg:classifiers":[
        {
            "category":"Home & Garden",
            "subcategory":"Furniture",
            "type":"Retail Goods"
        }
    ],
    "sg:phone":"+1 604 255 2113",
    "sg:postcode":"V5L 2G1",
    "sg:province":"BC",
    "sg:tags":[
        "mattress"
    ],
    "wof:name":"Mr Mattress",
    "wof:placetype":"venue"
},
  "geometry": {"coordinates":[-123.076897,49.27692],"type":"Point"}
}