{
  "type": "Feature",
  "properties": {
    "iso:country":"CA",
    "sg:city":"Regina",
    "sg:classifiers":[
        {
            "category":"Freight",
            "type":"Transportation"
        }
    ],
    "sg:phone":"+1 306 757 2700",
    "sg:postcode":"S4N 5H4",
    "sg:province":"SK",
    "sg:tags":[
        "trucking"
    ],
    "wof:name":"Robert Antoniazzi Holdings Ltd",
    "wof:placetype":"venue"
},
  "geometry": {"coordinates":[-104.572075,50.462345],"type":"Point"}
}