{
  "type": "Feature",
  "properties": {
    "iso:country":"CA",
    "sg:city":"Nisku",
    "sg:classifiers":[
        {
            "category":"Professional",
            "subcategory":"Computer Services",
            "type":"Services"
        }
    ],
    "sg:phone":"+1 780 955 8090",
    "sg:postcode":"T9E 7N3",
    "sg:province":"AB",
    "sg:tags":[
        "consultant"
    ],
    "wof:name":"Form Soft Solutions Ltd",
    "wof:placetype":"venue"
},
  "geometry": {"coordinates":[-113.532745361,53.3101577759],"type":"Point"}
}