{
  "type": "Feature",
  "properties": {
    "addr:full":"142 Rue Merry N Magog QC J1X 2E8",
    "addr:housenumber":"142",
    "addr:postcode":"j1x 2e8",
    "addr:street":"Rue Merry N",
    "iso:country":"CA",
    "sg:address":"142 Rue Merry N",
    "sg:city":"Magog",
    "sg:classifiers":[
        {
            "category":"Travel",
            "subcategory":"Hotels & Motels",
            "type":"Entertainment"
        }
    ],
    "sg:phone":"+1 819 847 0476",
    "sg:postcode":"J1X 2E8",
    "sg:province":"QC",
    "sg:tags":[
        "breakfast",
        "accommodation",
        "bed"
    ],
    "wof:name":"Belle Victorienne",
    "wof:placetype":"venue"
},
  "geometry": {"coordinates":[-72.1551437378,45.2686195374],"type":"Point"}
}