{
  "type": "Feature",
  "properties": {
    "addr:full":"L'Annonciation QC J0T 1T0",
    "addr:postcode":"j0t 1t0",
    "iso:country":"CA",
    "sg:city":"L'Annonciation",
    "sg:classifiers":[
        {
            "category":"Professional",
            "subcategory":"Accounting & Tax Preparation",
            "type":"Services"
        }
    ],
    "sg:phone":"+1 819 275 3115",
    "sg:postcode":"J0T 1T0",
    "sg:province":"QC",
    "sg:tags":[
        "accountant",
        "bookkeeping",
        "system"
    ],
    "wof:name":"Lapointe Jean Comptable Baa",
    "wof:placetype":"venue"
},
  "geometry": {"coordinates":[-74.8690109253,46.4084358215],"type":"Point"}
}