{
  "type": "Feature",
  "properties": {
    "addr:full":"2210 Bromsgrove Rd Mississauga ON L5J 1L4",
    "addr:housenumber":"2210",
    "addr:postcode":"l5j 1l4",
    "addr:street":"Bromsgrove Rd",
    "iso:country":"CA",
    "sg:address":"2210 Bromsgrove Rd",
    "sg:city":"Mississauga",
    "sg:classifiers":[
        {
            "category":"Wholesale",
            "subcategory":"Chemicals & Plastics",
            "type":"Manufacturing & Wholesale Goods"
        }
    ],
    "sg:phone":"+1 905 822 1627",
    "sg:postcode":"L5J 1L4",
    "sg:province":"ON",
    "wof:name":"Baker Petrolite",
    "wof:placetype":"venue"
},
  "geometry": {"coordinates":[-79.63854980470001,43.510723114],"type":"Point"}
}