{
  "type": "Feature",
  "properties": {
    "addr:full":"113 Boul Saint-Joseph Hull QC J8Y 3W7",
    "addr:housenumber":"113",
    "addr:postcode":"j8y 3w7",
    "addr:street":"Boul Saint-Joseph",
    "iso:country":"CA",
    "sg:address":"113 Boul Saint-Joseph",
    "sg:city":"Hull",
    "sg:classifiers":[
        {
            "category":"Personal",
            "subcategory":"Beauty Salon",
            "type":"Services"
        }
    ],
    "sg:phone":"+1 819 776 1015",
    "sg:postcode":"J8Y 3W7",
    "sg:province":"QC",
    "wof:name":"Coiffure Luigi",
    "wof:placetype":"venue"
},
  "geometry": {"coordinates":[-75.7335281372,45.4303627014],"type":"Point"}
}