{
  "type": "Feature",
  "properties": {
    "addr:full":"420 York St London ON N6B 1R1",
    "addr:housenumber":"420",
    "addr:postcode":"n6b 1r1",
    "addr:street":"York St",
    "iso:country":"CA",
    "sg:address":"420 York St",
    "sg:city":"London",
    "sg:classifiers":[
        {
            "category":"Real Estate",
            "subcategory":"Real Estate Agent",
            "type":"Services"
        }
    ],
    "sg:phone":"+1 519 673 3390",
    "sg:postcode":"N6B 1R1",
    "sg:province":"ON",
    "wof:name":"Lauckner, John",
    "wof:placetype":"venue"
},
  "geometry": {"coordinates":[-81.23788500000001,42.984383],"type":"Point"}
}