{
  "type": "Feature",
  "properties": {
    "addr:full":"141 Sandwich St S Amherstburg ON N9V 1Z9",
    "addr:housenumber":"141",
    "addr:postcode":"n9v 1z9",
    "addr:street":"Sandwich St S",
    "iso:country":"CA",
    "sg:address":"141 Sandwich St S",
    "sg:city":"Amherstburg",
    "sg:classifiers":[
        {
            "category":"Professional",
            "subcategory":"Accounting & Tax Preparation",
            "type":"Services"
        }
    ],
    "sg:phone":"+1 519 736 3932",
    "sg:postcode":"N9V 1Z9",
    "sg:province":"ON",
    "sg:tags":[
        "accountant"
    ],
    "wof:name":"Sovran & Greenaway",
    "wof:placetype":"venue"
},
  "geometry": {"coordinates":[-83.1099014282,42.105922699],"type":"Point"}
}