{
  "type": "Feature",
  "properties": {
    "addr:full":"966 5th Ave Prince George BC V2L 3K8",
    "addr:housenumber":"966",
    "addr:postcode":"v2l 3k8",
    "addr:street":"5Th Ave",
    "iso:country":"CA",
    "sg:address":"966 5th Ave",
    "sg:city":"Prince George",
    "sg:classifiers":[
        {
            "category":"Utilities",
            "subcategory":"Water",
            "type":"Services"
        }
    ],
    "sg:phone":"+1 250 563 4222",
    "sg:postcode":"V2L 3K8",
    "sg:province":"BC",
    "sg:tags":[
        "company",
        "sewage"
    ],
    "wof:name":"Grandview Water Hauling",
    "wof:placetype":"venue"
},
  "geometry": {"coordinates":[-122.741547,53.913986],"type":"Point"}
}