{
  "type": "Feature",
  "properties": {
    "iso:country":"CA",
    "sg:address":"2417 Rue Guenette",
    "sg:city":"Saint-Laurent",
    "sg:classifiers":[
        {
            "category":"Professional",
            "subcategory":"Business Services",
            "type":"Services"
        }
    ],
    "sg:phone":"+1 514 339 5551",
    "sg:postcode":"H4R 2E9",
    "sg:province":"QC",
    "sg:tags":[
        "event"
    ],
    "wof:name":"Promo Team Inc",
    "wof:placetype":"venue"
},
  "geometry": {"coordinates":[-73.728386,45.50024],"type":"Point"}
}