{
  "type": "Feature",
  "properties": {
    "addr:full":"221 Queen St S Kitchener ON N2G 1W5",
    "addr:housenumber":"221",
    "addr:postcode":"n2g 1w5",
    "addr:street":"Queen St S",
    "iso:country":"CA",
    "sg:address":"221 Queen St S",
    "sg:city":"Kitchener",
    "sg:classifiers":[
        {
            "category":"Shopping",
            "subcategory":"Discount & Variety Stores",
            "type":"Retail Goods"
        }
    ],
    "sg:phone":"+1 519 745 8112",
    "sg:postcode":"N2G 1W5",
    "sg:province":"ON",
    "wof:name":"Little Dutch Pantry",
    "wof:placetype":"venue"
},
  "geometry": {"coordinates":[-80.491646,43.447121],"type":"Point"}
}