{
  "type": "Feature",
  "properties": {
    "iso:country":"CA",
    "sg:address":"333 Main St",
    "sg:city":"Mattawa",
    "sg:classifiers":[
        {
            "category":"Home & Garden",
            "subcategory":"Hardware",
            "type":"Retail Goods"
        }
    ],
    "sg:phone":"+1 705 744 2719",
    "sg:postcode":"P0H 1V0",
    "sg:province":"ON",
    "wof:name":"True Value Hardware",
    "wof:placetype":"venue"
},
  "geometry": {"coordinates":[-78.7049789429,46.3182792664],"type":"Point"}
}