{
  "type": "Feature",
  "properties": {
    "iso:country":"CA",
    "sg:address":"459 Broad St N",
    "sg:city":"Regina",
    "sg:classifiers":[
        {
            "category":"Personal",
            "subcategory":"Beauty Salon",
            "type":"Services"
        }
    ],
    "sg:phone":"+1 306 949 9707",
    "sg:postcode":"S4R 2X8",
    "sg:province":"SK",
    "wof:name":"Image 1 Hair Team",
    "wof:placetype":"venue"
},
  "geometry": {"coordinates":[-104.606201172,50.4830322266],"type":"Point"}
}