{
  "type": "Feature",
  "properties": {
    "addr:full":"Zeballos BC V0P 2A0",
    "addr:postcode":"v0p 2a0",
    "iso:country":"CA",
    "sg:city":"Zeballos",
    "sg:classifiers":[
        {
            "category":"Recreation",
            "type":"Entertainment"
        }
    ],
    "sg:phone":"+1 250 761 2045",
    "sg:postcode":"V0P 2A0",
    "sg:province":"BC",
    "sg:tags":[
        "government",
        "hall",
        "auditorium"
    ],
    "wof:name":"Zeballo Community Hall",
    "wof:placetype":"venue"
},
  "geometry": {"coordinates":[-126.845749,49.983242],"type":"Point"}
}