{
  "type": "Feature",
  "properties": {
    "addr:full":"302 Scott St Fort Frances ON P9A 1G9",
    "addr:housenumber":"302",
    "addr:postcode":"p9a 1g9",
    "addr:street":"Scott St",
    "iso:country":"CA",
    "sg:address":"302 Scott St",
    "sg:city":"Fort Frances",
    "sg:classifiers":[
        {
            "category":"Organizations",
            "subcategory":"Professional Association",
            "type":"Services"
        }
    ],
    "sg:phone":"+1 807 274 5251",
    "sg:postcode":"P9A 1G9",
    "sg:province":"ON",
    "wof:name":"Masonic Lodge",
    "wof:placetype":"venue"
},
  "geometry": {"coordinates":[-93.395241,48.610203],"type":"Point"}
}