{
  "type": "Feature",
  "properties": {
    "addr:full":"214 Egan St Thunder Bay ON P7A 2W7",
    "addr:housenumber":"214",
    "addr:postcode":"p7a 2w7",
    "addr:street":"Egan St",
    "iso:country":"CA",
    "sg:address":"214 Egan St",
    "sg:city":"Thunder Bay",
    "sg:classifiers":[
        {
            "category":"Restaurant",
            "type":"Food & Drink"
        }
    ],
    "sg:phone":"+1 807 344 1441",
    "sg:postcode":"P7A 2W7",
    "sg:province":"ON",
    "wof:name":"Ling Lee's Chinese Cuisine Inc",
    "wof:placetype":"venue"
},
  "geometry": {"coordinates":[-89.20703899999999,48.445095],"type":"Point"}
}