{
  "type": "Feature",
  "properties": {
    "addr:full":"Brampton ON L6T 4J3",
    "addr:postcode":"l6t 4j3",
    "iso:country":"CA",
    "sg:city":"Brampton",
    "sg:classifiers":[
        {
            "category":"Building & Trades",
            "subcategory":"Plumbing",
            "type":"Services"
        }
    ],
    "sg:phone":"+1 905 457 2665",
    "sg:postcode":"L6T 4J3",
    "sg:province":"ON",
    "sg:tags":[
        "conditioning",
        "air",
        "system",
        "contractor"
    ],
    "wof:name":"Reliable Mechanical Svc Inc",
    "wof:placetype":"venue"
},
  "geometry": {"coordinates":[-79.69812774659999,43.6883850098],"type":"Point"}
}