{
  "type": "Feature",
  "properties": {
    "addr:full":"Ellershouse NS B0N 1L0",
    "addr:postcode":"b0n 1l0",
    "iso:country":"CA",
    "sg:city":"Ellershouse",
    "sg:classifiers":[
        {
            "category":"Retail",
            "subcategory":"Auto Repair",
            "type":"Services"
        }
    ],
    "sg:phone":"+1 902 757 3849",
    "sg:postcode":"B0N 1L0",
    "sg:province":"NS",
    "sg:tags":[
        "repairing",
        "automobile"
    ],
    "wof:name":"Dale Young's Auto Repair",
    "wof:placetype":"venue"
},
  "geometry": {"coordinates":[-64.01700599999999,44.962845],"type":"Point"}
}