{
  "type": "Feature",
  "properties": {
    "addr:full":"Saint-Alexandre-DE-Kamouraska QC G0L 2G0",
    "addr:postcode":"g0l 2g0",
    "iso:country":"CA",
    "sg:city":"Saint-Alexandre-DE-Kamouraska",
    "sg:classifiers":[
        {
            "category":"Food & Beverages",
            "subcategory":"Groceries & Convenience Stores",
            "type":"Retail Goods"
        }
    ],
    "sg:phone":"+1 418 495 2872",
    "sg:postcode":"G0L 2G0",
    "sg:province":"QC",
    "sg:tags":[
        "grocer"
    ],
    "wof:name":"Epicerie Du Coin",
    "wof:placetype":"venue"
},
  "geometry": {"coordinates":[-69.86264801030001,47.5639762878],"type":"Point"}
}