{
  "type": "Feature",
  "properties": {
    "addr:full":"4835 Kent Ave Niagara Falls ON L2H 1J5",
    "addr:housenumber":"4835",
    "addr:postcode":"l2h 1j5",
    "addr:street":"Kent Ave",
    "iso:country":"CA",
    "sg:address":"4835 Kent Ave",
    "sg:city":"Niagara Falls",
    "sg:classifiers":[
        {
            "category":"Retail",
            "subcategory":"Auto Repair",
            "type":"Services"
        }
    ],
    "sg:phone":"+1 905 374 2265",
    "sg:postcode":"L2H 1J5",
    "sg:province":"ON",
    "sg:tags":[
        "lock",
        "wrecker",
        "locksmith"
    ],
    "wof:name":"Gary's Towing",
    "wof:placetype":"venue"
},
  "geometry": {"coordinates":[-79.120186,43.101597],"type":"Point"}
}