{
  "type": "Feature",
  "properties": {
    "addr:full":"Saint-Alexandre-DE-Kamouraska QC G0L 2G0",
    "addr:postcode":"g0l 2g0",
    "iso:country":"CA",
    "sg:city":"Saint-Alexandre-DE-Kamouraska",
    "sg:classifiers":[
        {
            "category":"Home & Garden",
            "subcategory":"Garden Supply",
            "type":"Retail Goods"
        }
    ],
    "sg:phone":"+1 418 495 2536",
    "sg:postcode":"G0L 2G0",
    "sg:province":"QC",
    "sg:tags":[
        "peat",
        "moss"
    ],
    "wof:name":"Tourbiere St Alexandre Inc",
    "wof:placetype":"venue"
},
  "geometry": {"coordinates":[-69.86264799999999,47.563976],"type":"Point"}
}