{
  "type": "Feature",
  "properties": {
    "addr:full":"Port Alberni BC V9Y 7W8",
    "addr:postcode":"v9y 7w8",
    "iso:country":"CA",
    "sg:city":"Port Alberni",
    "sg:classifiers":[
        {
            "category":"Health Services",
            "subcategory":"Clinic",
            "type":"Services"
        }
    ],
    "sg:phone":"+1 250 724 2912",
    "sg:postcode":"V9Y 7W8",
    "sg:province":"BC",
    "sg:tags":[
        "agency",
        "welfare"
    ],
    "wof:name":"Canadian Cancer Society",
    "wof:placetype":"venue"
},
  "geometry": {"coordinates":[-124.78608699999999,49.265972],"type":"Point"}
}