{
  "type": "Feature",
  "properties": {
    "addr:full":"582 College St Toronto ON M6G 1B3",
    "addr:housenumber":"582",
    "addr:postcode":"m6g 1b3",
    "addr:street":"College St",
    "iso:country":"CA",
    "sg:address":"582 College St",
    "sg:city":"Toronto",
    "sg:classifiers":[
        {
            "category":"Restaurant",
            "type":"Food & Drink"
        }
    ],
    "sg:phone":"+1 416 535 3621",
    "sg:postcode":"M6G 1B3",
    "sg:province":"ON",
    "sg:tags":[
        "parlor",
        "billiard"
    ],
    "wof:name":"Bar Italia & Billiards",
    "wof:placetype":"venue"
},
  "geometry": {"coordinates":[-79.4133224487,43.6554794312],"type":"Point"}
}