{
  "type": "Feature",
  "properties": {
    "addr:full":"Chemainus BC V0R 1K0",
    "addr:postcode":"v0r 1k0",
    "iso:country":"CA",
    "sg:city":"Chemainus",
    "sg:classifiers":[
        {
            "category":"Shopping",
            "subcategory":"Jewelry",
            "type":"Retail Goods"
        }
    ],
    "sg:phone":"+1 250 416 0388",
    "sg:postcode":"V0R 1K0",
    "sg:province":"BC",
    "sg:tags":[
        "shop",
        "gift"
    ],
    "wof:name":"Moonliting",
    "wof:placetype":"venue"
},
  "geometry": {"coordinates":[-123.717758,48.922653],"type":"Point"}
}