{
  "type": "Feature",
  "properties": {
    "addr:full":"137 Brodie St S Thunder Bay ON P7E 1B8",
    "addr:housenumber":"137",
    "addr:postcode":"p7e 1b8",
    "addr:street":"Brodie St S",
    "iso:country":"CA",
    "sg:address":"137 Brodie St S",
    "sg:city":"Thunder Bay",
    "sg:classifiers":[
        {
            "category":"Social Services",
            "subcategory":"Job Training",
            "type":"Services"
        }
    ],
    "sg:phone":"+1 807 624 7243",
    "sg:postcode":"P7E 1B8",
    "sg:province":"ON",
    "sg:tags":[
        "rehabilitation"
    ],
    "wof:name":"Boreal Health Svc",
    "wof:placetype":"venue"
},
  "geometry": {"coordinates":[-89.2468261719,48.3834533691],"type":"Point"}
}