{
  "type": "Feature",
  "properties": {
    "addr:full":"345 Pond Mills Rd London ON N5Z 3X7",
    "addr:housenumber":"345",
    "addr:postcode":"n5z 3x7",
    "addr:street":"Pond Mills Rd",
    "iso:country":"CA",
    "sg:address":"345 Pond Mills Rd",
    "sg:city":"London",
    "sg:classifiers":[
        {
            "category":"Organizations",
            "subcategory":"Religious Organization",
            "type":"Services"
        }
    ],
    "sg:phone":"+1 519 681 8121",
    "sg:postcode":"N5Z 3X7",
    "sg:province":"ON",
    "sg:tags":[
        "church"
    ],
    "wof:name":"Glen Cairn Baptist Church",
    "wof:placetype":"venue"
},
  "geometry": {"coordinates":[-81.20040130620001,42.9602165222],"type":"Point"}
}