{
  "type": "Feature",
  "properties": {
    "addr:full":"255 Sherbrook St Winnipeg MB R3C 2B8",
    "addr:housenumber":"255",
    "addr:postcode":"r3c 2b8",
    "addr:street":"Sherbrook St",
    "iso:country":"CA",
    "sg:address":"255 Sherbrook St",
    "sg:city":"Winnipeg",
    "sg:classifiers":[
        {
            "category":"Shopping",
            "type":"Retail Goods"
        }
    ],
    "sg:phone":"+1 204 775 1199",
    "sg:postcode":"R3C 2B8",
    "sg:province":"MB",
    "sg:tags":[
        "equipment",
        "telephone",
        "supply"
    ],
    "wof:name":"Easton Communication Svc",
    "wof:placetype":"venue"
},
  "geometry": {"coordinates":[-97.15898900000001,49.886482],"type":"Point"}
}