{
  "type": "Feature",
  "properties": {
    "addr:full":"263 Durham Rd RR 4 Walkerton ON N0G 2V0",
    "addr:housenumber":"263",
    "addr:postcode":"n0g 2v0",
    "addr:street":"Durham Rd",
    "iso:country":"CA",
    "sg:address":"263 Durham Rd RR 4",
    "sg:city":"Walkerton",
    "sg:classifiers":[
        {
            "category":"Wholesale",
            "subcategory":"Fruits & Vegetables",
            "type":"Manufacturing & Wholesale Goods"
        }
    ],
    "sg:phone":"+1 519 881 2944",
    "sg:postcode":"N0G 2V0",
    "sg:province":"ON",
    "wof:name":"Ralph Pitt Produce",
    "wof:placetype":"venue"
},
  "geometry": {"coordinates":[-81.149208,44.133102],"type":"Point"}
}