{
  "type": "Feature",
  "properties": {
    "addr:full":"7618 102 St Grande Prairie AB T8W 1Y7",
    "addr:housenumber":"7618",
    "addr:postcode":"t8w 1y7",
    "addr:street":"102 St",
    "iso:country":"CA",
    "sg:address":"7618 102 St",
    "sg:city":"Grande Prairie",
    "sg:classifiers":[
        {
            "category":"Professional",
            "subcategory":"Management & Consulting",
            "type":"Services"
        }
    ],
    "sg:phone":"+1 780 539 0852",
    "sg:postcode":"T8W 1Y7",
    "sg:province":"AB",
    "sg:tags":[
        "agricultural",
        "consultant"
    ],
    "wof:name":"Agri-Link Corp",
    "wof:placetype":"venue"
},
  "geometry": {"coordinates":[-118.803467,55.150085],"type":"Point"}
}