{
  "type": "Feature",
  "properties": {
    "addr:full":"6540 50 Ave SW Salmon Arm BC V1E 4M1",
    "addr:housenumber":"6540",
    "addr:postcode":"v1e 4m1",
    "addr:street":"50 Ave Sw",
    "iso:country":"CA",
    "sg:address":"6540 50 Ave SW",
    "sg:city":"Salmon Arm",
    "sg:classifiers":[
        {
            "category":"Organizations",
            "subcategory":"Professional Association",
            "type":"Services"
        }
    ],
    "sg:phone":"+1 250 832 1163",
    "sg:postcode":"V1E 4M1",
    "sg:province":"BC",
    "wof:name":"Canoe Youth Ctr Time Out",
    "wof:placetype":"venue"
},
  "geometry": {"coordinates":[-119.213615417,50.6632461548],"type":"Point"}
}