{
  "type": "Feature",
  "properties": {
    "addr:full":"11 Douglas Ave Halifax NS B3M 3C9",
    "addr:housenumber":"11",
    "addr:postcode":"b3m 3c9",
    "addr:street":"Douglas Ave",
    "iso:country":"CA",
    "sg:address":"11 Douglas Ave",
    "sg:city":"Halifax",
    "sg:classifiers":[
        {
            "category":"Professional",
            "subcategory":"Engineering",
            "type":"Services"
        }
    ],
    "sg:phone":"+1 902 443 3020",
    "sg:postcode":"B3M 3C9",
    "sg:province":"NS",
    "sg:tags":[
        "engineer",
        "general",
        "contractor"
    ],
    "wof:name":"Sherwood Enterprises Inc",
    "wof:placetype":"venue"
},
  "geometry": {"coordinates":[-63.665955,44.676685],"type":"Point"}
}