{
  "type": "Feature",
  "properties": {
    "addr:full":"Ranchland Mall Pincher Creek AB T0K 1W0",
    "addr:postcode":"t0k 1w0",
    "iso:country":"CA",
    "sg:address":"Ranchland Mall",
    "sg:city":"Pincher Creek",
    "sg:classifiers":[
        {
            "category":"Home & Garden",
            "subcategory":"Furniture",
            "type":"Retail Goods"
        }
    ],
    "sg:phone":"+1 403 627 4330",
    "sg:postcode":"T0K 1W0",
    "sg:province":"AB",
    "wof:name":"Pincher Creek CO-OP Assn Ltd",
    "wof:placetype":"venue"
},
  "geometry": {"coordinates":[-113.95009613000001,49.4856681824],"type":"Point"}
}