{
  "type": "Feature",
  "properties": {
    "addr:full":"209 Boul Bourque Omerville QC J1X 4E7",
    "addr:housenumber":"209",
    "addr:postcode":"j1x 4e7",
    "addr:street":"Boul Bourque",
    "iso:country":"CA",
    "sg:address":"209 Boul Bourque",
    "sg:city":"Omerville",
    "sg:classifiers":[
        {
            "category":"Wholesale",
            "subcategory":"Auto Parts",
            "type":"Manufacturing & Wholesale Goods"
        }
    ],
    "sg:phone":"+1 819 868 1001",
    "sg:postcode":"J1X 4E7",
    "sg:province":"QC",
    "sg:tags":[
        "body",
        "automobile",
        "shop"
    ],
    "wof:name":"Peinture & Pieces D'Autos Dr",
    "wof:placetype":"venue"
},
  "geometry": {"coordinates":[-72.116737,45.287289],"type":"Point"}
}