{
  "type": "Feature",
  "properties": {
    "addr:full":"206 Broadway St N Deloraine MB R0M 0M0",
    "addr:housenumber":"206",
    "addr:postcode":"r0m 0m0",
    "addr:street":"Broadway St N Deloraine",
    "iso:country":"CA",
    "sg:address":"206 Broadway St N",
    "sg:city":"Deloraine",
    "sg:classifiers":[
        {
            "category":"Wholesale",
            "subcategory":"Farm Supplies",
            "type":"Manufacturing & Wholesale Goods"
        }
    ],
    "sg:phone":"+1 204 747 2904",
    "sg:postcode":"R0M 0M0",
    "sg:province":"MB",
    "sg:tags":[
        "seed",
        "grain",
        "cleaning"
    ],
    "wof:name":"Nestibo Agra Inc",
    "wof:placetype":"venue"
},
  "geometry": {"coordinates":[-100.496071,49.193336],"type":"Point"}
}