{
  "type": "Feature",
  "properties": {
    "addr:full":"456 Rue Niverville Trois-Rivieres QC G9A 2A2",
    "addr:housenumber":"456",
    "addr:postcode":"g9a 2a2",
    "addr:street":"Rue Niverville Trois-Rivieres",
    "iso:country":"CA",
    "sg:address":"456 Rue Niverville",
    "sg:city":"Trois-Rivieres",
    "sg:classifiers":[
        {
            "category":"Health Services",
            "subcategory":"Nursing And Care Facility",
            "type":"Services"
        }
    ],
    "sg:phone":"+1 819 379 2144",
    "sg:postcode":"G9A 2A2",
    "sg:province":"QC",
    "sg:tags":[
        "house",
        "retirement",
        "retreat",
        "community",
        "home"
    ],
    "wof:name":"Residences Niverville Enr",
    "wof:placetype":"venue"
},
  "geometry": {"coordinates":[-72.543762207,46.3450012207],"type":"Point"}
}