{
  "type": "Feature",
  "properties": {
    "addr:full":"Niagara Falls ON L2G 5X7",
    "addr:postcode":"l2g 5x7",
    "iso:country":"CA",
    "sg:city":"Niagara Falls",
    "sg:classifiers":[
        {
            "category":"Health Services",
            "subcategory":"Medical Lab",
            "type":"Services"
        }
    ],
    "sg:phone":"+1 905 356 8691",
    "sg:postcode":"L2G 5X7",
    "sg:province":"ON",
    "sg:tags":[
        "laboratory"
    ],
    "wof:name":"Canadian Medical Laboratories",
    "wof:placetype":"venue"
},
  "geometry": {"coordinates":[-79.0908050537,43.0959663391],"type":"Point"}
}