{
  "type": "Feature",
  "properties": {
    "iso:country":"CA",
    "sg:address":"127 21st St E",
    "sg:city":"Saskatoon",
    "sg:classifiers":[
        {
            "category":"Shopping",
            "subcategory":"Jewelry",
            "type":"Retail Goods"
        }
    ],
    "sg:phone":"+1 306 652 2553",
    "sg:postcode":"S7K 0B2",
    "sg:province":"SK",
    "sg:tags":[
        "jeweler"
    ],
    "wof:name":"Etceteras",
    "wof:placetype":"venue"
},
  "geometry": {"coordinates":[-106.66582489,52.1272735596],"type":"Point"}
}