{
  "type": "Feature",
  "properties": {
    "addr:full":"100 Rue Victoria E Salaberry-DE-Valleyfield QC J6S 5Y9",
    "addr:housenumber":"100",
    "addr:postcode":"j6s 5y9",
    "addr:street":"Rue Victoria E",
    "iso:country":"CA",
    "sg:address":"100 Rue Victoria E",
    "sg:city":"Salaberry-DE-Valleyfield",
    "sg:classifiers":[
        {
            "category":"Government",
            "subcategory":"Office",
            "type":"Public Place"
        }
    ],
    "sg:phone":"+1 450 370 4820",
    "sg:postcode":"J6S 5Y9",
    "sg:province":"QC",
    "sg:tags":[
        "village"
    ],
    "wof:name":"Salaberry-Valleyfield Travaux",
    "wof:placetype":"venue"
},
  "geometry": {"coordinates":[-74.111542,45.257648],"type":"Point"}
}