{
  "type": "Feature",
  "properties": {
    "addr:full":"1 Rue Beausoleil Saint-Gabriel-DE-Brandon QC J0K 2N0",
    "addr:housenumber":"1",
    "addr:postcode":"j0k 2n0",
    "addr:street":"Rue Beausoleil",
    "iso:country":"CA",
    "sg:address":"1 Rue Beausoleil",
    "sg:city":"Saint-Gabriel-DE-Brandon",
    "sg:classifiers":[
        {
            "category":"Insurance",
            "subcategory":"Insurance Agent",
            "type":"Services"
        }
    ],
    "sg:phone":"+1 450 835 2288",
    "sg:postcode":"J0K 2N0",
    "sg:province":"QC",
    "wof:name":"Jette Frechette & Assoc",
    "wof:placetype":"venue"
},
  "geometry": {"coordinates":[-73.383804,46.294281],"type":"Point"}
}