{
  "type": "Feature",
  "properties": {
    "addr:full":"Levis QC G6V 4Z4",
    "addr:postcode":"g6v 4z4",
    "iso:country":"CA",
    "sg:city":"Levis",
    "sg:classifiers":[
        {
            "category":"Professional",
            "subcategory":"Management & Consulting",
            "type":"Services"
        }
    ],
    "sg:phone":"+1 418 839 1815",
    "sg:postcode":"G6V 4Z4",
    "sg:province":"QC",
    "sg:tags":[
        "communications",
        "consultant"
    ],
    "wof:name":"Consulcom Communication",
    "wof:placetype":"venue"
},
  "geometry": {"coordinates":[-71.181541,46.792202],"type":"Point"}
}