{
  "type": "Feature",
  "properties": {
    "addr:full":"2895 Saint Paul Ave Niagara Falls ON L2J 2L3",
    "addr:housenumber":"2895",
    "addr:postcode":"l2j 2l3",
    "addr:street":"Saint Paul Ave",
    "iso:country":"CA",
    "sg:address":"2895 Saint Paul Ave",
    "sg:city":"Niagara Falls",
    "sg:classifiers":[
        {
            "category":"Food & Beverages",
            "subcategory":"Groceries & Convenience Stores",
            "type":"Retail Goods"
        }
    ],
    "sg:phone":"+1 905 354 9555",
    "sg:postcode":"L2J 2L3",
    "sg:province":"ON",
    "wof:name":"Avondale Stores Ltd",
    "wof:placetype":"venue"
},
  "geometry": {"coordinates":[-79.10011299999999,43.130478],"type":"Point"}
}