{
  "type": "Feature",
  "properties": {
    "addr:full":"Markham ON L3R 4C2",
    "addr:postcode":"l3r 4c2",
    "iso:country":"CA",
    "sg:city":"Markham",
    "sg:classifiers":[
        {
            "category":"Wholesale",
            "subcategory":"Non-durable Goods",
            "type":"Manufacturing & Wholesale Goods"
        }
    ],
    "sg:phone":"+1 905 479 9739",
    "sg:postcode":"L3R 4C2",
    "sg:province":"ON",
    "wof:name":"Spreadink Limited",
    "wof:placetype":"venue"
},
  "geometry": {"coordinates":[-79.3277664185,43.8236274719],"type":"Point"}
}