{
  "type": "Feature",
  "properties": {
    "addr:full":"NW 30-14-13W Arden MB R0J 0B0",
    "addr:postcode":"30-14-13w;r0j 0b0",
    "addr:street":"Nw",
    "iso:country":"CA",
    "sg:address":"NW 30-14-13W",
    "sg:city":"Arden",
    "sg:classifiers":[
        {
            "category":"Professional",
            "subcategory":"Business Services",
            "type":"Services"
        }
    ],
    "sg:phone":"+1 204 368 2333",
    "sg:postcode":"R0J 0B0",
    "sg:province":"MB",
    "sg:tags":[
        "auctioneer"
    ],
    "wof:name":"Meyers Auction & Appraisal Svc",
    "wof:placetype":"venue"
},
  "geometry": {"coordinates":[-99.2694015503,50.2765007019],"type":"Point"}
}