{
  "type": "Feature",
  "properties": {
    "addr:full":"1150 Rue Saint-Jean Quebec QC G1R 1S6",
    "addr:housenumber":"1150",
    "addr:postcode":"g1r 1s6",
    "addr:street":"Rue Saint-Jean",
    "iso:country":"CA",
    "sg:address":"1150 Rue Saint-Jean",
    "sg:city":"Quebec",
    "sg:classifiers":[
        {
            "category":"Shopping",
            "subcategory":"Clothing, Apparel, & Fashions",
            "type":"Retail Goods"
        }
    ],
    "sg:phone":"+1 418 692 0398",
    "sg:postcode":"G1R 1S6",
    "sg:province":"QC",
    "wof:name":"Boutique LA Cache",
    "wof:placetype":"venue"
},
  "geometry": {"coordinates":[-71.2099533081,46.8143081665],"type":"Point"}
}