{
  "type": "Feature",
  "properties": {
    "addr:full":"Edmonton AB T6N 1G1",
    "addr:postcode":"t6n 1g1",
    "iso:country":"CA",
    "sg:city":"Edmonton",
    "sg:classifiers":[
        {
            "category":"Professional",
            "subcategory":"Research",
            "type":"Services"
        }
    ],
    "sg:phone":"+1 780 448 7424",
    "sg:postcode":"T6N 1G1",
    "sg:province":"AB",
    "sg:tags":[
        "development",
        "electronic"
    ],
    "wof:name":"Synodon",
    "wof:placetype":"venue"
},
  "geometry": {"coordinates":[-113.477203,53.450314],"type":"Point"}
}