{
  "type": "Feature",
  "properties": {
    "addr:full":"Edson AB T7E 1N4",
    "addr:postcode":"t7e 1n4",
    "iso:country":"CA",
    "sg:city":"Edson",
    "sg:classifiers":[
        {
            "category":"Real Estate",
            "subcategory":"Developer",
            "type":"Services"
        }
    ],
    "sg:phone":"+1 780 723 3819",
    "sg:postcode":"T7E 1N4",
    "sg:province":"AB",
    "sg:tags":[
        "mobile",
        "home"
    ],
    "wof:name":"Poplar Place Trailer Park Ltd",
    "wof:placetype":"venue"
},
  "geometry": {"coordinates":[-116.454582,53.590542],"type":"Point"}
}