{
  "type": "Feature",
  "properties": {
    "addr:full":"1359 Rue Manning Verdun QC H4H 2A1",
    "addr:housenumber":"1359",
    "addr:postcode":"h4h 2a1",
    "addr:street":"Rue Manning",
    "iso:country":"CA",
    "sg:address":"1359 Rue Manning",
    "sg:city":"Verdun",
    "sg:classifiers":[
        {
            "category":"Building & Trades",
            "subcategory":"Plumbing",
            "type":"Services"
        }
    ],
    "sg:phone":"+1 514 762 2612",
    "sg:postcode":"H4H 2A1",
    "sg:province":"QC",
    "sg:tags":[
        "contractor"
    ],
    "wof:name":"Entreprises S Forest Inc",
    "wof:placetype":"venue"
},
  "geometry": {"coordinates":[-73.5849456787,45.4500007629],"type":"Point"}
}