{
  "type": "Feature",
  "properties": {
    "addr:full":"629 7th Ave Keremeos BC V0X 1N0",
    "addr:housenumber":"629",
    "addr:postcode":"v0x 1n0",
    "addr:street":"7Th Ave",
    "iso:country":"CA",
    "sg:address":"629 7th Ave",
    "sg:city":"Keremeos",
    "sg:classifiers":[
        {
            "category":"Restaurant",
            "type":"Food & Drink"
        }
    ],
    "sg:phone":"+1 250 499 2933",
    "sg:postcode":"V0X 1N0",
    "sg:province":"BC",
    "wof:name":"Pasta Trading Post",
    "wof:placetype":"venue"
},
  "geometry": {"coordinates":[-119.82448599999999,49.204933],"type":"Point"}
}