{
  "type": "Feature",
  "properties": {
    "addr:full":"Montreal QC H3A 3M8",
    "addr:postcode":"h3a 3m8",
    "iso:country":"CA",
    "sg:city":"Montreal",
    "sg:classifiers":[
        {
            "category":"Banks & Credit Unions",
            "subcategory":"Investment Brokerage",
            "type":"Services"
        }
    ],
    "sg:phone":"+1 514 288 3647",
    "sg:postcode":"H3A 3M8",
    "sg:province":"QC",
    "sg:tags":[
        "funds",
        "mutual"
    ],
    "wof:name":"Aim",
    "wof:placetype":"venue"
},
  "geometry": {"coordinates":[-73.57151,45.502453],"type":"Point"}
}