{
  "type": "Feature",
  "properties": {
    "addr:full":"48 Spadina Ave Toronto ON M5V 2H8",
    "addr:housenumber":"48",
    "addr:postcode":"m5v 2h8",
    "addr:street":"Spadina Ave",
    "iso:country":"CA",
    "sg:address":"48 Spadina Ave",
    "sg:city":"Toronto",
    "sg:classifiers":[
        {
            "category":"Retail",
            "subcategory":"Animal Services",
            "type":"Services"
        }
    ],
    "sg:phone":"+1 416 593 4777",
    "sg:postcode":"M5V 2H8",
    "sg:province":"ON",
    "sg:tags":[
        "pet",
        "food",
        "grooming",
        "washing",
        "supply"
    ],
    "wof:name":"Umbrella Pet Svc Inc",
    "wof:placetype":"venue"
},
  "geometry": {"coordinates":[-79.3949050903,43.6445617676],"type":"Point"}
}