{
  "type": "Feature",
  "properties": {
    "addr:full":"100 Golden Dr Coquitlam BC V3K 6T1",
    "addr:housenumber":"100",
    "addr:postcode":"v3k 6t1",
    "addr:street":"Golden Dr",
    "iso:country":"CA",
    "sg:address":"100 Golden Dr",
    "sg:city":"Coquitlam",
    "sg:classifiers":[
        {
            "category":"Retail",
            "subcategory":"Auto Rental",
            "type":"Services"
        }
    ],
    "sg:phone":"+1 604 945 3718",
    "sg:postcode":"V3K 6T1",
    "sg:province":"BC",
    "sg:tags":[
        "renting",
        "leasing",
        "trailer"
    ],
    "wof:name":"Ocean Trailer Rentals",
    "wof:placetype":"venue"
},
  "geometry": {"coordinates":[-122.82463836700001,49.2318954468],"type":"Point"}
}