{
  "type": "Feature",
  "properties": {
    "addr:full":"North York ON M3K 2A8",
    "addr:postcode":"m3k 2a8",
    "iso:country":"CA",
    "sg:city":"North York",
    "sg:classifiers":[
        {
            "category":"Organizations",
            "subcategory":"Labor Organization",
            "type":"Services"
        }
    ],
    "sg:phone":"+1 416 630 1160",
    "sg:postcode":"M3K 2A8",
    "sg:province":"ON",
    "wof:name":"Sheet Metal Workers Union",
    "wof:placetype":"venue"
},
  "geometry": {"coordinates":[-79.4745635986,43.7287750244],"type":"Point"}
}