{
  "type": "Feature",
  "properties": {
    "addr:full":"Fort Mcmurray AB T9H 4B6",
    "addr:postcode":"t9h 4b6",
    "iso:country":"CA",
    "sg:city":"Fort Mcmurray",
    "sg:classifiers":[
        {
            "category":"Manufacturing",
            "subcategory":"Metals",
            "type":"Manufacturing & Wholesale Goods"
        }
    ],
    "sg:phone":"+1 780 743 4339",
    "sg:postcode":"T9H 4B6",
    "sg:province":"AB",
    "sg:tags":[
        "steel"
    ],
    "wof:name":"Northern Arc Lubrication",
    "wof:placetype":"venue"
},
  "geometry": {"coordinates":[-111.34101867699999,56.6676902771],"type":"Point"}
}