{
  "type": "Feature",
  "properties": {
    "addr:full":"5828 Macleod Trail SW Calgary AB T2H 0J8",
    "addr:housenumber":"5828",
    "addr:postcode":"t2h 0j8",
    "addr:street":"Macleod Trail Sw",
    "iso:country":"CA",
    "sg:address":"5828 Macleod Trail SW",
    "sg:city":"Calgary",
    "sg:classifiers":[
        {
            "category":"Professional",
            "subcategory":"Printing & Photocopies",
            "type":"Services"
        }
    ],
    "sg:phone":"+1 403 258 0086",
    "sg:postcode":"T2H 0J8",
    "sg:province":"AB",
    "sg:tags":[
        "printer",
        "duplicating",
        "copying"
    ],
    "wof:name":"Kinkos 24 Hour Copy Ctr",
    "wof:placetype":"venue"
},
  "geometry": {"coordinates":[-114.07125854500001,51.0021400452],"type":"Point"}
}