{
  "type": "Feature",
  "properties": {
    "addr:full":"448 Main St E Shelburne ON L0N 1S2",
    "addr:housenumber":"448",
    "addr:postcode":"l0n 1s2",
    "addr:street":"Main St E",
    "iso:country":"CA",
    "sg:address":"448 Main St E",
    "sg:city":"Shelburne",
    "sg:classifiers":[
        {
            "category":"Food & Beverages",
            "subcategory":"Meat & Fish",
            "type":"Retail Goods"
        }
    ],
    "sg:phone":"+1 519 925 5850",
    "sg:postcode":"L0N 1S2",
    "sg:province":"ON",
    "sg:tags":[
        "frozen"
    ],
    "wof:name":"M & M Meat Shops",
    "wof:placetype":"venue"
},
  "geometry": {"coordinates":[-80.1969909668,44.0798835754],"type":"Point"}
}