{
  "type": "Feature",
  "properties": {
    "addr:full":"Vernon BC V1T 9R1",
    "addr:postcode":"v1t 9r1",
    "iso:country":"CA",
    "sg:city":"Vernon",
    "sg:classifiers":[
        {
            "category":"Shopping",
            "type":"Retail Goods"
        }
    ],
    "sg:phone":"+1 250 558 5832",
    "sg:postcode":"V1T 9R1",
    "sg:province":"BC",
    "sg:tags":[
        "equipment",
        "supply",
        "wine"
    ],
    "wof:name":"Wine Kitz",
    "wof:placetype":"venue"
},
  "geometry": {"coordinates":[-119.305740356,50.256149292],"type":"Point"}
}