{
  "type": "Feature",
  "properties": {
    "addr:full":"12325 Rue April Pointe-Aux-Trembles QC H1B 5L8",
    "addr:housenumber":"12325",
    "addr:postcode":"h1b 5l8",
    "addr:street":"Rue April",
    "iso:country":"CA",
    "sg:address":"12325 Rue April",
    "sg:city":"Pointe-Aux-Trembles",
    "sg:classifiers":[
        {
            "category":"Wholesale",
            "subcategory":"Stationery",
            "type":"Manufacturing & Wholesale Goods"
        }
    ],
    "sg:phone":"+1 514 640 0674",
    "sg:postcode":"H1B 5L8",
    "sg:province":"QC",
    "sg:tags":[
        "packaging",
        "material"
    ],
    "wof:name":"Emballages Starflex Inc",
    "wof:placetype":"venue"
},
  "geometry": {"coordinates":[-73.51537322999999,45.6489372253],"type":"Point"}
}