{
  "type": "Feature",
  "properties": {
    "iso:country":"CA",
    "sg:address":"2350 Boul Du Cure-Labelle",
    "sg:city":"Saint-Jerome",
    "sg:classifiers":[
        {
            "category":"Restaurant",
            "type":"Food & Drink"
        }
    ],
    "sg:phone":"+1 450 436 6411",
    "sg:postcode":"J7Y 5E9",
    "sg:province":"QC",
    "wof:name":"Restaurant Nicholas",
    "wof:placetype":"venue"
},
  "geometry": {"coordinates":[-74.03312683110001,45.8142662048],"type":"Point"}
}