{
  "type": "Feature",
  "properties": {
    "addr:full":"452 Dovercourt Dr Winnipeg MB R3Y 1G4",
    "addr:housenumber":"452",
    "addr:postcode":"r3y 1g4",
    "addr:street":"Dovercourt Dr",
    "iso:country":"CA",
    "sg:address":"452 Dovercourt Dr",
    "sg:city":"Winnipeg",
    "sg:classifiers":[
        {
            "category":"Manufacturing",
            "subcategory":"Rubber & Plastics",
            "type":"Manufacturing & Wholesale Goods"
        }
    ],
    "sg:phone":"+1 204 944 8104",
    "sg:postcode":"R3Y 1G4",
    "sg:province":"MB",
    "sg:tags":[
        "mold",
        "maker"
    ],
    "wof:name":"Springwell Manufacturing Inc",
    "wof:placetype":"venue"
},
  "geometry": {"coordinates":[-97.1895446777,49.8167572021],"type":"Point"}
}