{
  "type": "Feature",
  "properties": {
    "addr:full":"6273 Paddler Way Orleans ON K1C 2G5",
    "addr:housenumber":"6273",
    "addr:postcode":"k1c 2g5",
    "addr:street":"Paddler Way",
    "iso:country":"CA",
    "sg:address":"6273 Paddler Way",
    "sg:city":"Orleans",
    "sg:classifiers":[
        {
            "category":"Autos & Motor Vehicles",
            "subcategory":"Automobile Sales",
            "type":"Retail Goods"
        }
    ],
    "sg:phone":"+1 613 834 9313",
    "sg:postcode":"K1C 2G5",
    "sg:province":"ON",
    "sg:tags":[
        "equipment",
        "aircraft",
        "parts",
        "supply"
    ],
    "wof:name":"Norleans Technologies Inc",
    "wof:placetype":"venue"
},
  "geometry": {"coordinates":[-75.54639400000001,45.477863],"type":"Point"}
}