{
  "type": "Feature",
  "properties": {
    "addr:full":"Burnaby BC V5H 4P1",
    "addr:postcode":"v5h 4p1",
    "iso:country":"CA",
    "sg:city":"Burnaby",
    "sg:classifiers":[
        {
            "category":"Food & Beverages",
            "subcategory":"Specialty",
            "type":"Retail Goods"
        }
    ],
    "sg:phone":"+1 604 435 1505",
    "sg:postcode":"V5H 4P1",
    "sg:province":"BC",
    "sg:tags":[
        "oriental"
    ],
    "wof:name":"Utsuwa-No-Yakata",
    "wof:placetype":"venue"
},
  "geometry": {"coordinates":[-122.972763062,49.2444343567],"type":"Point"}
}