{
  "type": "Feature",
  "properties": {
    "addr:full":"301 11th Ave Campbell River BC V9W 4G2",
    "addr:housenumber":"301",
    "addr:postcode":"v9w 4g2",
    "addr:street":"11Th Ave",
    "iso:country":"CA",
    "sg:address":"301 11th Ave",
    "sg:city":"Campbell River",
    "sg:classifiers":[
        {
            "category":"Organizations",
            "subcategory":"Community Association",
            "type":"Services"
        }
    ],
    "sg:phone":"+1 250 286 6831",
    "sg:postcode":"V9W 4G2",
    "sg:province":"BC",
    "sg:tags":[
        "fraternal"
    ],
    "wof:name":"Royal Canadian Legion Br 137",
    "wof:placetype":"venue"
},
  "geometry": {"coordinates":[-125.245293,50.026264],"type":"Point"}
}