{
  "type": "Feature",
  "properties": {
    "addr:full":"1809 Mountain Rd Moncton NB E1G 1A7",
    "addr:housenumber":"1809",
    "addr:postcode":"e1g 1a7",
    "addr:street":"Mountain Rd",
    "iso:country":"CA",
    "sg:address":"1809 Mountain Rd",
    "sg:city":"Moncton",
    "sg:classifiers":[
        {
            "category":"Real Estate",
            "subcategory":"Real Estate Operator",
            "type":"Services"
        }
    ],
    "sg:phone":"+1 506 858 0641",
    "sg:postcode":"E1G 1A7",
    "sg:province":"NB",
    "sg:tags":[
        "mobile",
        "home",
        "community"
    ],
    "wof:name":"Ryder Park Ltd",
    "wof:placetype":"venue"
},
  "geometry": {"coordinates":[-64.847763,46.121799],"type":"Point"}
}