{
  "type": "Feature",
  "properties": {
    "addr:full":"Campbell River BC V9W 8C9",
    "addr:postcode":"v9w 8c9",
    "iso:country":"CA",
    "sg:city":"Campbell River",
    "sg:classifiers":[
        {
            "category":"Manufacturing",
            "subcategory":"Food",
            "type":"Manufacturing & Wholesale Goods"
        }
    ],
    "sg:phone":"+1 250 850 1199",
    "sg:postcode":"V9W 8C9",
    "sg:province":"BC",
    "sg:tags":[
        "confectionery",
        "candy",
        "chocolate"
    ],
    "wof:name":"Rocky Mountain Chocolate Fctry",
    "wof:placetype":"venue"
},
  "geometry": {"coordinates":[-125.254272461,50.0346183777],"type":"Point"}
}