{
  "type": "Feature",
  "properties": {
    "addr:full":"207 Edgeley Blvd Concord ON L4K 4B5",
    "addr:housenumber":"207",
    "addr:postcode":"l4k 4b5",
    "addr:street":"Edgeley Blvd",
    "iso:country":"CA",
    "sg:address":"207 Edgeley Blvd",
    "sg:city":"Concord",
    "sg:classifiers":[
        {
            "category":"Restaurant",
            "type":"Food & Drink"
        }
    ],
    "sg:phone":"+1 905 660 3354",
    "sg:postcode":"L4K 4B5",
    "sg:province":"ON",
    "sg:tags":[
        "delicatessen"
    ],
    "wof:name":"Deli Deli",
    "wof:placetype":"venue"
},
  "geometry": {"coordinates":[-79.532928,43.797764],"type":"Point"}
}