{
  "type": "Feature",
  "properties": {
    "addr:full":"413 Tom St Buffalo Narrows SK S0M 0J0",
    "addr:housenumber":"413",
    "addr:postcode":"s0m 0j0",
    "addr:street":"Tom St",
    "iso:country":"CA",
    "sg:address":"413 Tom St",
    "sg:city":"Buffalo Narrows",
    "sg:classifiers":[
        {
            "category":"Social Services",
            "subcategory":"Child Care",
            "type":"Services"
        }
    ],
    "sg:phone":"+1 306 235 4226",
    "sg:postcode":"S0M 0J0",
    "sg:province":"SK",
    "wof:name":"Day-Care Ctr",
    "wof:placetype":"venue"
},
  "geometry": {"coordinates":[-108.48188018800001,55.8651046753],"type":"Point"}
}