{
  "type": "Feature",
  "properties": {
    "addr:full":"250 Davis Dr Newmarket ON L3Y 7T7",
    "addr:housenumber":"250",
    "addr:postcode":"l3y 7t7",
    "addr:street":"Davis Dr",
    "iso:country":"CA",
    "sg:address":"250 Davis Dr",
    "sg:city":"Newmarket",
    "sg:classifiers":[
        {
            "category":"Real Estate",
            "subcategory":"Real Estate Operator",
            "type":"Services"
        }
    ],
    "sg:phone":"+1 905 853 3625",
    "sg:postcode":"L3Y 7T7",
    "sg:province":"ON",
    "sg:tags":[
        "condominium"
    ],
    "wof:name":"York Region Condominium Corp",
    "wof:placetype":"venue"
},
  "geometry": {"coordinates":[-79.4692764282,44.0571632385],"type":"Point"}
}