{
  "type": "Feature",
  "properties": {
    "addr:full":"Devereaux Petit-Rocher NB E8J 3E7",
    "addr:postcode":"e8j 3e7",
    "iso:country":"CA",
    "sg:address":"Devereaux",
    "sg:city":"Petit-Rocher",
    "sg:classifiers":[
        {
            "category":"Travel",
            "subcategory":"Campground",
            "type":"Entertainment"
        }
    ],
    "sg:phone":"+1 506 783 2894",
    "sg:postcode":"E8J 3E7",
    "sg:province":"NB",
    "sg:tags":[
        "camp"
    ],
    "wof:name":"Camp Ectus",
    "wof:placetype":"venue"
},
  "geometry": {"coordinates":[-65.717995,47.782681],"type":"Point"}
}