{
  "type": "Feature",
  "properties": {
    "addr:full":"Richmond Hill ON L4C 9Y5",
    "addr:postcode":"l4c 9y5",
    "iso:country":"CA",
    "sg:city":"Richmond Hill",
    "sg:classifiers":[
        {
            "category":"Retail",
            "subcategory":"Repair Shop",
            "type":"Services"
        }
    ],
    "sg:phone":"+1 905 884 0881",
    "sg:postcode":"L4C 9Y5",
    "sg:province":"ON",
    "sg:tags":[
        "upholsterer"
    ],
    "wof:name":"Handcraft Upholstery Ltd",
    "wof:placetype":"venue"
},
  "geometry": {"coordinates":[-79.429237,43.897236],"type":"Point"}
}