{
  "type": "Feature",
  "properties": {
    "addr:full":"3115 Rte Marie-Victorin Sorel-Tracy QC J3R 1N8",
    "addr:housenumber":"3115",
    "addr:postcode":"j3r 1n8",
    "addr:street":"Rte Marie-Victorin",
    "iso:country":"CA",
    "sg:address":"3115 Rte Marie-Victorin",
    "sg:city":"Sorel-Tracy",
    "sg:classifiers":[
        {
            "category":"Restaurant",
            "type":"Food & Drink"
        }
    ],
    "sg:phone":"+1 450 746 5876",
    "sg:postcode":"J3R 1N8",
    "sg:province":"QC",
    "sg:tags":[
        "caterer"
    ],
    "wof:name":"Broue Sur Roues",
    "wof:placetype":"venue"
},
  "geometry": {"coordinates":[-73.153847,46.031071],"type":"Point"}
}