{
  "type": "Feature",
  "properties": {
    "addr:full":"36 Church St Markham ON L3P 2L8",
    "addr:housenumber":"36",
    "addr:postcode":"l3p 2l8",
    "addr:street":"Church St",
    "iso:country":"CA",
    "sg:address":"36 Church St",
    "sg:city":"Markham",
    "sg:classifiers":[
        {
            "category":"Professional",
            "subcategory":"Management & Consulting",
            "type":"Services"
        }
    ],
    "sg:phone":"+1 905 471 4398",
    "sg:postcode":"L3P 2L8",
    "sg:province":"ON",
    "sg:tags":[
        "marketing",
        "consultant"
    ],
    "wof:name":"Segmentation Marketing Ltd",
    "wof:placetype":"venue"
},
  "geometry": {"coordinates":[-79.257851,43.879131],"type":"Point"}
}