{
  "type": "Feature",
  "properties": {
    "addr:full":"115 31 Ave NE Calgary AB T2E 2E8",
    "addr:housenumber":"115",
    "addr:postcode":"t2e 2e8",
    "addr:street":"31 Ave Ne",
    "iso:country":"CA",
    "sg:address":"115 31 Ave NE",
    "sg:city":"Calgary",
    "sg:classifiers":[
        {
            "category":"Freight",
            "type":"Transportation"
        }
    ],
    "sg:phone":"+1 403 277 3511",
    "sg:postcode":"T2E 2E8",
    "sg:province":"AB",
    "sg:tags":[
        "delivery"
    ],
    "wof:name":"Gifford's Transfer",
    "wof:placetype":"venue"
},
  "geometry": {"coordinates":[-114.061965942,51.0804023743],"type":"Point"}
}