{
  "type": "Feature",
  "properties": {
    "addr:full":"10408 Hwy 17 W Verner ON P0H 2M0",
    "addr:housenumber":"10408",
    "addr:postcode":"p0h 2m0",
    "addr:street":"Hwy 17 W Verner",
    "iso:country":"CA",
    "sg:address":"10408 Hwy 17 W",
    "sg:city":"Verner",
    "sg:classifiers":[
        {
            "category":"Autos & Motor Vehicles",
            "subcategory":"Automobile Sales",
            "type":"Retail Goods"
        }
    ],
    "sg:phone":"+1 705 594 9559",
    "sg:postcode":"P0H 2M0",
    "sg:province":"ON",
    "sg:tags":[
        "snowmobile"
    ],
    "wof:name":"Northern Sports & Svc",
    "wof:placetype":"venue"
},
  "geometry": {"coordinates":[-80.132729,46.414246],"type":"Point"}
}