{
  "type": "Feature",
  "properties": {
    "addr:full":"8434 Wellington Road 8 Drayton ON N0G 1P0",
    "addr:housenumber":"8434",
    "addr:postcode":"n0g 1p0",
    "addr:street":"Wellington Road 8",
    "iso:country":"CA",
    "sg:address":"8434 Wellington Road 8",
    "sg:city":"Drayton",
    "sg:classifiers":[
        {
            "category":"Wholesale",
            "subcategory":"Machinery & Supplies",
            "type":"Manufacturing & Wholesale Goods"
        }
    ],
    "sg:phone":"+1 519 638 5505",
    "sg:postcode":"N0G 1P0",
    "sg:province":"ON",
    "sg:tags":[
        "equipment",
        "safety",
        "clothing"
    ],
    "wof:name":"Murray Safety Supply",
    "wof:placetype":"venue"
},
  "geometry": {"coordinates":[-80.671677,43.754581],"type":"Point"}
}