{
  "type": "Feature",
  "properties": {
    "addr:full":"780 Innisfil Beach Rd Innisfil ON L9S 2C3",
    "addr:housenumber":"780",
    "addr:postcode":"l9s 2c3",
    "addr:street":"Innisfil Beach Rd",
    "iso:country":"CA",
    "sg:address":"780 Innisfil Beach Rd",
    "sg:city":"Innisfil",
    "sg:classifiers":[
        {
            "category":"Government",
            "subcategory":"Fire Station",
            "type":"Public Place"
        }
    ],
    "sg:phone":"+1 ",
    "sg:postcode":"L9S 2C3",
    "sg:province":"ON",
    "sg:tags":[
        "department"
    ],
    "wof:name":"Innisfil Fire Dept",
    "wof:placetype":"venue"
},
  "geometry": {"coordinates":[-79.5390548706,44.3170547485],"type":"Point"}
}