{
  "type": "Feature",
  "properties": {
    "iso:country":"CA",
    "sg:address":"86 Windham Trail",
    "sg:city":"Aurora",
    "sg:classifiers":[
        {
            "category":"Professional",
            "subcategory":"Accounting & Tax Preparation",
            "type":"Services"
        }
    ],
    "sg:phone":"+1 905 841 3094",
    "sg:postcode":"L4G 5L5",
    "sg:province":"ON",
    "sg:tags":[
        "accountant"
    ],
    "wof:name":"Steffan, K CA",
    "wof:placetype":"venue"
},
  "geometry": {"coordinates":[-79.491364,43.993523],"type":"Point"}
}