{
  "type": "Feature",
  "properties": {
    "addr:full":"1174 Woodbine Ave East York ON M4C 4E2",
    "addr:housenumber":"1174",
    "addr:postcode":"m4c 4e2",
    "addr:street":"Woodbine Ave",
    "iso:country":"CA",
    "sg:address":"1174 Woodbine Ave",
    "sg:city":"East York",
    "sg:classifiers":[
        {
            "category":"Autos & Motor Vehicles",
            "subcategory":"Automobile Sales",
            "type":"Retail Goods"
        }
    ],
    "sg:phone":"+1 416 429 5220",
    "sg:postcode":"M4C 4E2",
    "sg:province":"ON",
    "sg:tags":[
        "car",
        "dealer"
    ],
    "wof:name":"Woodbine Auto Sales & Svc",
    "wof:placetype":"venue"
},
  "geometry": {"coordinates":[-79.31536865229999,43.691242218],"type":"Point"}
}