{
  "type": "Feature",
  "properties": {
    "iso:country":"CA",
    "sg:address":"30 Macallum St",
    "sg:city":"Hamilton",
    "sg:classifiers":[
        {
            "category":"Manufacturing",
            "subcategory":"Metals",
            "type":"Manufacturing & Wholesale Goods"
        }
    ],
    "sg:phone":"+1 905 527 2242",
    "sg:postcode":"L8L 4E8",
    "sg:province":"ON",
    "sg:tags":[
        "work",
        "sheet",
        "heating",
        "contractor"
    ],
    "wof:name":"Hammond Metal Systems",
    "wof:placetype":"venue"
},
  "geometry": {"coordinates":[-79.843201,43.267403],"type":"Point"}
}