{
  "type": "Feature",
  "properties": {
    "addr:full":"30 Macallum St Hamilton ON L8L 4E8",
    "addr:housenumber":"30",
    "addr:postcode":"l8l 4e8",
    "addr:street":"Macallum St",
    "iso:country":"CA",
    "sg:address":"30 Macallum St",
    "sg:city":"Hamilton",
    "sg:classifiers":[
        {
            "category":"Manufacturing",
            "subcategory":"Metals",
            "type":"Manufacturing & Wholesale Goods"
        }
    ],
    "sg:phone":"+1 905 527 2242",
    "sg:postcode":"L8L 4E8",
    "sg:province":"ON",
    "sg:tags":[
        "work",
        "sheet",
        "heating",
        "contractor"
    ],
    "wof:name":"Hammond Metal Systems",
    "wof:placetype":"venue"
},
  "geometry": {"coordinates":[-79.84320099999999,43.267403],"type":"Point"}
}