{
  "type": "Feature",
  "properties": {
    "addr:full":"Concord ON L4K 3A7",
    "addr:postcode":"l4k 3a7",
    "iso:country":"CA",
    "sg:city":"Concord",
    "sg:classifiers":[
        {
            "category":"Manufacturing",
            "subcategory":"Building Materials",
            "type":"Manufacturing & Wholesale Goods"
        }
    ],
    "sg:phone":"+1 905 669 0368",
    "sg:postcode":"L4K 3A7",
    "sg:province":"ON",
    "sg:tags":[
        "molding"
    ],
    "wof:name":"Entablature Frieze & Pillars",
    "wof:placetype":"venue"
},
  "geometry": {"coordinates":[-79.47943100000001,43.786987],"type":"Point"}
}