{
  "type": "Feature",
  "properties": {
    "addr:full":"2820 Victoria Park Ave North York ON M2J 4A8",
    "addr:housenumber":"2820",
    "addr:postcode":"m2j 4a8",
    "addr:street":"Victoria Park Ave",
    "iso:country":"CA",
    "sg:address":"2820 Victoria Park Ave",
    "sg:city":"North York",
    "sg:classifiers":[
        {
            "category":"Retail",
            "subcategory":"Veterinary Services",
            "type":"Services"
        }
    ],
    "sg:phone":"+1 416 491 5393",
    "sg:postcode":"M2J 4A8",
    "sg:province":"ON",
    "sg:tags":[
        "veterinarian"
    ],
    "wof:name":"Bowhill Animal Clinic",
    "wof:placetype":"venue"
},
  "geometry": {"coordinates":[-79.328934,43.787472],"type":"Point"}
}