{
  "type": "Feature",
  "properties": {
    "iso:country":"CA",
    "sg:city":"Langley",
    "sg:classifiers":[
        {
            "category":"Professional",
            "subcategory":"Management & Consulting",
            "type":"Services"
        }
    ],
    "sg:phone":"+1 604 533 2650",
    "sg:postcode":"V3A 7R3",
    "sg:province":"BC",
    "sg:tags":[
        "consultant",
        "business"
    ],
    "wof:name":"Community Futures Dev Corp",
    "wof:placetype":"venue"
},
  "geometry": {"coordinates":[-122.652206421,49.1056747437],"type":"Point"}
}