{
  "type": "Feature",
  "properties": {
    "iso:country":"CA",
    "sg:address":"7785 Hwy 3",
    "sg:city":"Mahone Bay",
    "sg:classifiers":[
        {
            "category":"Retail",
            "subcategory":"Auto Repair",
            "type":"Services"
        }
    ],
    "sg:phone":"+1 902 624 8214",
    "sg:postcode":"B0J 2E0",
    "sg:province":"NS",
    "sg:tags":[
        "repairing",
        "automobile"
    ],
    "wof:name":"Hiltz's Service Station",
    "wof:placetype":"venue"
},
  "geometry": {"coordinates":[-64.3778381348,44.4484519958],"type":"Point"}
}