{
  "type": "Feature",
  "properties": {
    "addr:full":"853 Rue Sainte-Genevieve Trois-Rivieres QC G9A 3X4",
    "addr:housenumber":"853",
    "addr:postcode":"g9a 3x4",
    "addr:street":"Rue Sainte-Genevieve Trois-Rivieres",
    "iso:country":"CA",
    "sg:address":"853 Rue Sainte-Genevieve",
    "sg:city":"Trois-Rivieres",
    "sg:classifiers":[
        {
            "category":"Social Services",
            "subcategory":"Job Training",
            "type":"Services"
        }
    ],
    "sg:phone":"+1 819 378 5180",
    "sg:postcode":"G9A 3X4",
    "sg:province":"QC",
    "sg:tags":[
        "rehabilitation"
    ],
    "wof:name":"Arche Mauricie Inc",
    "wof:placetype":"venue"
},
  "geometry": {"coordinates":[-72.541786,46.347103],"type":"Point"}
}