{
  "type": "Feature",
  "properties": {
    "iso:country":"CA",
    "sg:address":"206 Laird Dr",
    "sg:city":"East York",
    "sg:classifiers":[
        {
            "category":"Communications",
            "subcategory":"Film & Video Production",
            "type":"Services"
        }
    ],
    "sg:phone":"+1 416 260 7544",
    "sg:postcode":"M4G 3W4",
    "sg:province":"ON",
    "sg:tags":[
        "taping"
    ],
    "wof:name":"Reflections on Islam",
    "wof:placetype":"venue"
},
  "geometry": {"coordinates":[-79.36399841310001,43.7111320496],"type":"Point"}
}