{
  "type": "Feature",
  "properties": {
    "addr:full":"2405 Dundas St London ON N5V 3C8",
    "addr:housenumber":"2405",
    "addr:postcode":"n5v 3c8",
    "addr:street":"Dundas St",
    "iso:country":"CA",
    "sg:address":"2405 Dundas St",
    "sg:city":"London",
    "sg:classifiers":[
        {
            "category":"Restaurant",
            "type":"Food & Drink"
        }
    ],
    "sg:phone":"+1 519 455 3540",
    "sg:postcode":"N5V 3C8",
    "sg:province":"ON",
    "wof:name":"Friendly's Fred & Ted",
    "wof:placetype":"venue"
},
  "geometry": {"coordinates":[-81.1474533081,43.0122795105],"type":"Point"}
}