{
  "type": "Feature",
  "properties": {
    "addr:full":"Fall River NS B2T 1J5",
    "addr:postcode":"b2t 1j5",
    "iso:country":"CA",
    "sg:city":"Fall River",
    "sg:classifiers":[
        {
            "category":"Retail",
            "subcategory":"Veterinary Services",
            "type":"Services"
        }
    ],
    "sg:phone":"+1 902 861 4003",
    "sg:postcode":"B2T 1J5",
    "sg:province":"NS",
    "sg:tags":[
        "veterinarian"
    ],
    "wof:name":"Coxhead, Brian DVM",
    "wof:placetype":"venue"
},
  "geometry": {"coordinates":[-63.6114387512,44.8163299561],"type":"Point"}
}