{
  "type": "Feature",
  "properties": {
    "addr:full":"Montreal QC H2X 3P9",
    "addr:postcode":"h2x 3p9",
    "iso:country":"CA",
    "sg:city":"Montreal",
    "sg:classifiers":[
        {
            "category":"Shopping",
            "subcategory":"Tobacco",
            "type":"Retail Goods"
        }
    ],
    "sg:phone":"+1 514 844 5479",
    "sg:postcode":"H2X 3P9",
    "sg:province":"QC",
    "sg:tags":[
        "cigarette",
        "cigar",
        "dealer"
    ],
    "wof:name":"Tabagie LA Cite",
    "wof:placetype":"venue"
},
  "geometry": {"coordinates":[-73.574966,45.510269],"type":"Point"}
}