{
  "type": "Feature",
  "properties": {
    "iso:country":"CA",
    "sg:address":"10 Starrs Rd",
    "sg:city":"Yarmouth",
    "sg:classifiers":[
        {
            "category":"Social Services",
            "type":"Services"
        }
    ],
    "sg:phone":"+1 902 742 8262",
    "sg:postcode":"B5A 2T1",
    "sg:province":"NS",
    "sg:tags":[
        "organization",
        "welfare"
    ],
    "wof:name":"Southwest Community Justice",
    "wof:placetype":"venue"
},
  "geometry": {"coordinates":[-66.1122055054,43.8460350037],"type":"Point"}
}