{
  "type": "Feature",
  "properties": {
    "addr:full":"2727 Boul Taschereau Saint-Hubert QC J4T 2E6",
    "addr:housenumber":"2727",
    "addr:postcode":"j4t 2e6",
    "addr:street":"Boul Taschereau",
    "iso:country":"CA",
    "sg:address":"2727 Boul Taschereau",
    "sg:city":"Saint-Hubert",
    "sg:classifiers":[
        {
            "category":"Manufacturing",
            "subcategory":"Toys & Sporting Goods",
            "type":"Manufacturing & Wholesale Goods"
        }
    ],
    "sg:phone":"+1 450 923 0880",
    "sg:postcode":"J4T 2E6",
    "sg:province":"QC",
    "sg:tags":[
        "athletic"
    ],
    "wof:name":"F 3 Distribution Inc",
    "wof:placetype":"venue"
},
  "geometry": {"coordinates":[-73.4872207642,45.5008049011],"type":"Point"}
}