{
  "type": "Feature",
  "properties": {
    "addr:full":"272 Waterloo Ave North York ON M3H 3Z7",
    "addr:housenumber":"272",
    "addr:postcode":"m3h 3z7",
    "addr:street":"Waterloo Ave",
    "iso:country":"CA",
    "sg:address":"272 Waterloo Ave",
    "sg:city":"North York",
    "sg:classifiers":[
        {
            "category":"Banks & Credit Unions",
            "subcategory":"Bank",
            "type":"Services"
        }
    ],
    "sg:phone":"+1 416 398 4125",
    "sg:postcode":"M3H 3Z7",
    "sg:province":"ON",
    "sg:tags":[
        "loan",
        "real estate"
    ],
    "wof:name":"Mazzocca Financial Svc Inc",
    "wof:placetype":"venue"
},
  "geometry": {"coordinates":[-79.457863,43.755905],"type":"Point"}
}