{
  "type": "Feature",
  "properties": {
    "addr:full":"43479 Blyth Rd Walton ON N0K 1Z0",
    "addr:postcode":"43479;n0k 1z0",
    "addr:street":"Blyth Rd",
    "iso:country":"CA",
    "sg:address":"43479 Blyth Rd",
    "sg:city":"Walton",
    "sg:classifiers":[
        {
            "category":"Building & Trades",
            "subcategory":"Construction",
            "type":"Services"
        }
    ],
    "sg:phone":"+1 519 887 6428",
    "sg:postcode":"N0K 1Z0",
    "sg:province":"ON",
    "sg:tags":[
        "contractor",
        "sewer",
        "drainage"
    ],
    "wof:name":"Kmm Farm Drainage",
    "wof:placetype":"venue"
},
  "geometry": {"coordinates":[-81.3007278442,43.6768302917],"type":"Point"}
}