{
  "type": "Feature",
  "properties": {
    "addr:full":"255 Boul DE LA Concorde O # 201 Laval QC H7N 5T1",
    "addr:housenumber":"255",
    "addr:postcode":"h7n 5t1",
    "addr:street":"Boul De La Concorde O # 201",
    "iso:country":"CA",
    "sg:address":"255 Boul DE LA Concorde O # 201",
    "sg:city":"Laval",
    "sg:classifiers":[
        {
            "category":"Health Services",
            "subcategory":"Doctor",
            "type":"Services"
        }
    ],
    "sg:phone":"+1 450 668 3333",
    "sg:postcode":"H7N 5T1",
    "sg:province":"QC",
    "sg:tags":[
        "clinic"
    ],
    "wof:name":"Centre DE Sante Dentaire Ag",
    "wof:placetype":"venue"
},
  "geometry": {"coordinates":[-73.70114898680001,45.565700531],"type":"Point"}
}