{
  "type": "Feature",
  "properties": {
    "addr:full":"2465 Ch Sainte-Marie Mascouche QC J7K 1M7",
    "addr:postcode":"2465;j7k 1m7",
    "addr:street":"Ch Sainte-Marie",
    "iso:country":"CA",
    "sg:address":"2465 Ch Sainte-Marie",
    "sg:city":"Mascouche",
    "sg:classifiers":[
        {
            "category":"Organizations",
            "subcategory":"Professional Association",
            "type":"Services"
        }
    ],
    "sg:phone":"+1 450 474 0385",
    "sg:postcode":"J7K 1M7",
    "sg:province":"QC",
    "wof:name":"Club Optimiste Mascouche Inc",
    "wof:placetype":"venue"
},
  "geometry": {"coordinates":[-73.61788900000001,45.753166],"type":"Point"}
}