{
  "type": "Feature",
  "properties": {
    "iso:country":"CA",
    "sg:address":"2465 Ch Sainte-Marie",
    "sg:city":"Mascouche",
    "sg:classifiers":[
        {
            "category":"Organizations",
            "subcategory":"Professional Association",
            "type":"Services"
        }
    ],
    "sg:phone":"+1 450 474 0385",
    "sg:postcode":"J7K 1M7",
    "sg:province":"QC",
    "wof:name":"Club Optimiste Mascouche Inc",
    "wof:placetype":"venue"
},
  "geometry": {"coordinates":[-73.617889,45.753166],"type":"Point"}
}