{
  "type": "Feature",
  "properties": {
    "addr:full":"23 Robb Blvd #1 Orangeville ON L9W 3L1",
    "addr:housenumber":"23",
    "addr:postcode":"l9w 3l1",
    "addr:street":"Robb Blvd # 1",
    "iso:country":"CA",
    "sg:address":"23 Robb Blvd #1",
    "sg:city":"Orangeville",
    "sg:classifiers":[
        {
            "category":"Building & Trades",
            "subcategory":"Construction",
            "type":"Services"
        }
    ],
    "sg:phone":"+1 519 928 5773",
    "sg:postcode":"L9W 3L1",
    "sg:province":"ON",
    "sg:tags":[
        "excavating",
        "contractor",
        "general"
    ],
    "wof:name":"Allto Construction",
    "wof:placetype":"venue"
},
  "geometry": {"coordinates":[-80.1105041504,43.9064025879],"type":"Point"}
}