{
  "type": "Feature",
  "properties": {
    "addr:full":"1798 Greenwood Rd Pembroke ON K8A 6W3",
    "addr:housenumber":"1798",
    "addr:postcode":"k8a 6w3",
    "addr:street":"Greenwood Rd",
    "iso:country":"CA",
    "sg:address":"1798 Greenwood Rd",
    "sg:city":"Pembroke",
    "sg:classifiers":[
        {
            "category":"Shopping",
            "subcategory":"Clothing, Apparel, & Fashions",
            "type":"Retail Goods"
        }
    ],
    "sg:phone":"+1 613 638 5609",
    "sg:postcode":"K8A 6W3",
    "sg:province":"ON",
    "wof:name":"Belly Dancers",
    "wof:placetype":"venue"
},
  "geometry": {"coordinates":[-77.112213,45.826481],"type":"Point"}
}