{
  "type": "Feature",
  "properties": {
    "addr:full":"9231 Fitzpatrick St Vankleek Hill ON K0B 1R0",
    "addr:housenumber":"9231",
    "addr:postcode":"k0b 1r0",
    "addr:street":"Fitzpatrick St",
    "iso:country":"CA",
    "sg:address":"9231 Fitzpatrick St",
    "sg:city":"Vankleek Hill",
    "sg:classifiers":[
        {
            "category":"Farming",
            "subcategory":"Farm",
            "type":"Manufacturing & Wholesale Goods"
        }
    ],
    "sg:phone":"+1 613 678 3007",
    "sg:postcode":"K0B 1R0",
    "sg:province":"ON",
    "sg:tags":[
        "mushroom"
    ],
    "wof:name":"Cory Champignon Mushroom Inc",
    "wof:placetype":"venue"
},
  "geometry": {"coordinates":[-74.651443,45.521],"type":"Point"}
}