{
  "type": "Feature",
  "properties": {
    "addr:full":"170 5th Ave Rougemont QC J0L 1M0",
    "addr:housenumber":"170",
    "addr:postcode":"j0l 1m0",
    "addr:street":"5Th Ave",
    "iso:country":"CA",
    "sg:address":"170 5th Ave",
    "sg:city":"Rougemont",
    "sg:classifiers":[
        {
            "category":"Manufacturing",
            "subcategory":"Food",
            "type":"Manufacturing & Wholesale Goods"
        }
    ],
    "sg:phone":"+1 450 469 4926",
    "sg:postcode":"J0L 1M0",
    "sg:province":"QC",
    "sg:tags":[
        "grocer",
        "product",
        "manufacturer"
    ],
    "wof:name":"Mont-Rouge Foods",
    "wof:placetype":"venue"
},
  "geometry": {"coordinates":[-73.052230835,45.433681488],"type":"Point"}
}