{
  "type": "Feature",
  "properties": {
    "addr:full":"45 216 St Langley BC V2Z 1S3",
    "addr:housenumber":"216",
    "addr:postcode":"v2z 1s3",
    "addr:street":"45",
    "iso:country":"CA",
    "sg:address":"45 216 St",
    "sg:city":"Langley",
    "sg:classifiers":[
        {
            "category":"Retail",
            "subcategory":"Veterinary Services",
            "type":"Services"
        }
    ],
    "sg:phone":"+1 604 530 1409",
    "sg:postcode":"V2Z 1S3",
    "sg:province":"BC",
    "sg:tags":[
        "veterinarian"
    ],
    "wof:name":"Hilts, Drew DVM",
    "wof:placetype":"venue"
},
  "geometry": {"coordinates":[-122.625305,49.003487],"type":"Point"}
}