{
  "type": "Feature",
  "properties": {
    "iso:country":"CA",
    "sg:address":"3595 Keele St",
    "sg:city":"North York",
    "sg:classifiers":[
        {
            "category":"Health Services",
            "subcategory":"Nursing And Care Facility",
            "type":"Services"
        }
    ],
    "sg:phone":"+1 416 633 3431",
    "sg:postcode":"M3J 1M7",
    "sg:province":"ON",
    "sg:tags":[
        "home",
        "retirement",
        "community"
    ],
    "wof:name":"Casa Verde Retirement",
    "wof:placetype":"venue"
},
  "geometry": {"coordinates":[-79.487885,43.751732],"type":"Point"}
}