{
  "type": "Feature",
  "properties": {
    "iso:country":"CA",
    "sg:address":"84 Lynden Rd",
    "sg:city":"Brantford",
    "sg:classifiers":[
        {
            "category":"Shopping",
            "subcategory":"Clothing, Apparel, & Fashions",
            "type":"Retail Goods"
        }
    ],
    "sg:phone":"+1 519 750 0556",
    "sg:postcode":"N3R 6B8",
    "sg:province":"ON",
    "wof:name":"Winners Apparel Ltd",
    "wof:placetype":"venue"
},
  "geometry": {"coordinates":[-80.24392700200001,43.172870636],"type":"Point"}
}