{
  "type": "Feature",
  "properties": {
    "addr:full":"6100 Ferry Rd Delta BC V4K 3M9",
    "addr:housenumber":"6100",
    "addr:postcode":"v4k 3m9",
    "addr:street":"Ferry Rd",
    "iso:country":"CA",
    "sg:address":"6100 Ferry Rd",
    "sg:city":"Delta",
    "sg:classifiers":[
        {
            "category":"Bars & Pubs",
            "type":"Food & Drink"
        }
    ],
    "sg:phone":"+1 604 946 2727",
    "sg:postcode":"V4K 3M9",
    "sg:province":"BC",
    "wof:name":"Rusty Anchor Pub",
    "wof:placetype":"venue"
},
  "geometry": {"coordinates":[-123.07798,49.112438],"type":"Point"}
}