{
  "type": "Feature",
  "properties": {
    "addr:full":"12415 99 St Grande Prairie AB T8V 6Y5",
    "addr:housenumber":"12415",
    "addr:postcode":"t8v 6y5",
    "addr:street":"99 St",
    "iso:country":"CA",
    "sg:address":"12415 99 St",
    "sg:city":"Grande Prairie",
    "sg:classifiers":[
        {
            "category":"Health Services",
            "subcategory":"Doctor",
            "type":"Services"
        }
    ],
    "sg:phone":"+1 780 539 1151",
    "sg:postcode":"T8V 6Y5",
    "sg:province":"AB",
    "sg:tags":[
        "dentist"
    ],
    "wof:name":"Grande Prairie Family Dental",
    "wof:placetype":"venue"
},
  "geometry": {"coordinates":[-118.79162599999999,55.194931],"type":"Point"}
}