{
  "type": "Feature",
  "properties": {
    "addr:full":"630 Boul Casavant O Saint-Hyacinthe QC J2S 7S3",
    "addr:housenumber":"630",
    "addr:postcode":"j2s 7s3",
    "addr:street":"Boul Casavant O",
    "iso:country":"CA",
    "sg:address":"630 Boul Casavant O",
    "sg:city":"Saint-Hyacinthe",
    "sg:classifiers":[
        {
            "category":"Personal",
            "subcategory":"Tanning Parlor",
            "type":"Services"
        }
    ],
    "sg:phone":"+1 450 774 1474",
    "sg:postcode":"J2S 7S3",
    "sg:province":"QC",
    "sg:tags":[
        "salon"
    ],
    "wof:name":"Bronzage Marie-Soleil Enr",
    "wof:placetype":"venue"
},
  "geometry": {"coordinates":[-72.958389,45.641773],"type":"Point"}
}