{
  "type": "Feature",
  "properties": {
    "addr:full":"3330 Rte Marie-Victorin Sorel-Tracy QC J3R 1N9",
    "addr:housenumber":"3330",
    "addr:postcode":"j3r 1n9",
    "addr:street":"Rte Marie-Victorin",
    "iso:country":"CA",
    "sg:address":"3330 Rte Marie-Victorin",
    "sg:city":"Sorel-Tracy",
    "sg:classifiers":[
        {
            "category":"Travel",
            "subcategory":"Hotels & Motels",
            "type":"Entertainment"
        }
    ],
    "sg:phone":"+1 450 742 4565",
    "sg:postcode":"J3R 1N9",
    "sg:province":"QC",
    "sg:tags":[
        "tourist",
        "accommodation"
    ],
    "wof:name":"Motel Tracy Enrg",
    "wof:placetype":"venue"
},
  "geometry": {"coordinates":[-73.15394592289999,46.0301971436],"type":"Point"}
}