{
  "type": "Feature",
  "properties": {
    "addr:full":"441 Rue Faverel Cap-DE-LA-Madeleine QC G8T 3H1",
    "addr:housenumber":"441",
    "addr:postcode":"g8t 3h1",
    "addr:street":"Rue Faverel",
    "iso:country":"CA",
    "sg:address":"441 Rue Faverel",
    "sg:city":"Cap-DE-LA-Madeleine",
    "sg:classifiers":[
        {
            "category":"Building & Trades",
            "subcategory":"Construction",
            "type":"Services"
        }
    ],
    "sg:phone":"+1 819 375 4865",
    "sg:postcode":"G8T 3H1",
    "sg:province":"QC",
    "sg:tags":[
        "general",
        "contractor"
    ],
    "wof:name":"Construction Jd Morin Inc",
    "wof:placetype":"venue"
},
  "geometry": {"coordinates":[-72.50369262700001,46.3727073669],"type":"Point"}
}