{
  "type": "Feature",
  "properties": {
    "addr:full":"1916 Wyandotte St W Windsor ON N9B 1J5",
    "addr:housenumber":"1916",
    "addr:postcode":"n9b 1j5",
    "addr:street":"Wyandotte St W",
    "iso:country":"CA",
    "sg:address":"1916 Wyandotte St W",
    "sg:city":"Windsor",
    "sg:classifiers":[
        {
            "category":"Restaurant",
            "type":"Food & Drink"
        }
    ],
    "sg:phone":"+1 519 252 0481",
    "sg:postcode":"N9B 1J5",
    "sg:province":"ON",
    "wof:name":"Kfc",
    "wof:placetype":"venue"
},
  "geometry": {"coordinates":[-83.0583496094,42.3066864014],"type":"Point"}
}