{
  "type": "Feature",
  "properties": {
    "addr:full":"230 Rue Du Pere-Rheaume Neuville QC G0A 2R0",
    "addr:housenumber":"230",
    "addr:postcode":"g0a 2r0",
    "addr:street":"Rue Du Pere-Rheaume",
    "iso:country":"CA",
    "sg:address":"230 Rue Du Pere-Rheaume",
    "sg:city":"Neuville",
    "sg:classifiers":[
        {
            "category":"Government",
            "subcategory":"Office",
            "type":"Public Place"
        }
    ],
    "sg:phone":"+1 418 876 2280",
    "sg:postcode":"G0A 2R0",
    "sg:province":"QC",
    "sg:tags":[
        "village"
    ],
    "wof:name":"Neuville Secretaire Tresorier",
    "wof:placetype":"venue"
},
  "geometry": {"coordinates":[-71.58532700000001,46.696613],"type":"Point"}
}