{
  "type": "Feature",
  "properties": {
    "addr:full":"Rossburn MB R0J 1V0",
    "addr:postcode":"r0j 1v0",
    "iso:country":"CA",
    "sg:city":"Rossburn",
    "sg:classifiers":[
        {
            "category":"Education",
            "subcategory":"Library",
            "type":"Public Place"
        }
    ],
    "sg:phone":"+1 204 859 2687",
    "sg:postcode":"R0J 1V0",
    "sg:province":"MB",
    "wof:name":"Rossburn Regional Library",
    "wof:placetype":"venue"
},
  "geometry": {"coordinates":[-100.81082916299999,50.6689682007],"type":"Point"}
}