{
  "type": "Feature",
  "properties": {
    "addr:full":"524 Rue Principale Eastman QC J0E 1P0",
    "addr:housenumber":"524",
    "addr:postcode":"j0e 1p0",
    "addr:street":"Rue Principale",
    "iso:country":"CA",
    "sg:address":"524 Rue Principale",
    "sg:city":"Eastman",
    "sg:classifiers":[
        {
            "category":"Travel",
            "subcategory":"Hotels & Motels",
            "type":"Entertainment"
        }
    ],
    "sg:phone":"+1 450 297 3826",
    "sg:postcode":"J0E 1P0",
    "sg:province":"QC",
    "wof:name":"Motel Du Village",
    "wof:placetype":"venue"
},
  "geometry": {"coordinates":[-72.3083572388,45.3022537231],"type":"Point"}
}