{
  "type": "Feature",
  "properties": {
    "addr:full":"407 William Ave Winnipeg MB R3A 0J2",
    "addr:housenumber":"407",
    "addr:postcode":"r3a 0j2",
    "addr:street":"William Ave",
    "iso:country":"CA",
    "sg:address":"407 William Ave",
    "sg:city":"Winnipeg",
    "sg:classifiers":[
        {
            "category":"Wholesale",
            "subcategory":"Machinery & Supplies",
            "type":"Manufacturing & Wholesale Goods"
        }
    ],
    "sg:phone":"+1 204 943 3455",
    "sg:postcode":"R3A 0J2",
    "sg:province":"MB",
    "sg:tags":[
        "janitor"
    ],
    "wof:name":"Diamond Wax & Sanitary Supply",
    "wof:placetype":"venue"
},
  "geometry": {"coordinates":[-97.145775,49.901176],"type":"Point"}
}