{
  "type": "Feature",
  "properties": {
    "addr:full":"272 Jane St Toronto ON M6S 3Z2",
    "addr:housenumber":"272",
    "addr:postcode":"m6s 3z2",
    "addr:street":"Jane St",
    "iso:country":"CA",
    "sg:address":"272 Jane St",
    "sg:city":"Toronto",
    "sg:classifiers":[
        {
            "category":"Home & Garden",
            "subcategory":"Furniture",
            "type":"Retail Goods"
        }
    ],
    "sg:phone":"+1 416 762 8271",
    "sg:postcode":"M6S 3Z2",
    "sg:province":"ON",
    "wof:name":"Iron Store",
    "wof:placetype":"venue"
},
  "geometry": {"coordinates":[-79.487167,43.655781],"type":"Point"}
}