{
  "type": "Feature",
  "properties": {
    "addr:full":"13181 116 Ave Surrey BC V3R 2S8",
    "addr:housenumber":"13181",
    "addr:postcode":"v3r 2s8",
    "addr:street":"116 Ave",
    "iso:country":"CA",
    "sg:address":"13181 116 Ave",
    "sg:city":"Surrey",
    "sg:classifiers":[
        {
            "category":"Building & Trades",
            "subcategory":"Plumbing",
            "type":"Services"
        }
    ],
    "sg:phone":"+1 604 580 2132",
    "sg:postcode":"V3R 2S8",
    "sg:province":"BC",
    "sg:tags":[
        "environmental",
        "ecological",
        "tank",
        "installation"
    ],
    "wof:name":"United Enviro Svc",
    "wof:placetype":"venue"
},
  "geometry": {"coordinates":[-122.857269,49.213676],"type":"Point"}
}