{
  "type": "Feature",
  "properties": {
    "iso:country":"CA",
    "sg:city":"Mississauga",
    "sg:classifiers":[
        {
            "category":"Wholesale",
            "subcategory":"Home Furnishings",
            "type":"Manufacturing & Wholesale Goods"
        }
    ],
    "sg:phone":"+1 905 795 1667",
    "sg:postcode":"L5T 1P6",
    "sg:province":"ON",
    "sg:tags":[
        "glassware",
        "chinaware"
    ],
    "wof:name":"D & K Imports",
    "wof:placetype":"venue"
},
  "geometry": {"coordinates":[-79.65087890620001,43.6586914062],"type":"Point"}
}