{
  "type": "Feature",
  "properties": {
    "addr:full":"Hwy 6 Lake Francis MB R0C 1T0",
    "addr:postcode":"r0c 1t0",
    "addr:street":"Hwy 6 Lake Francis",
    "iso:country":"CA",
    "sg:address":"Hwy 6",
    "sg:city":"Lake Francis",
    "sg:classifiers":[
        {
            "category":"Autos & Motor Vehicles",
            "subcategory":"Automobile Sales",
            "type":"Retail Goods"
        }
    ],
    "sg:phone":"+1 204 383 5858",
    "sg:postcode":"R0C 1T0",
    "sg:province":"MB",
    "sg:tags":[
        "car",
        "dealer"
    ],
    "wof:name":"Good Used Stuff Store",
    "wof:placetype":"venue"
},
  "geometry": {"coordinates":[-97.806206,50.301491],"type":"Point"}
}