{
  "type": "Feature",
  "properties": {
    "addr:full":"40 Rue Saint-Georges Saint-Jerome QC J7Z 4Y9",
    "addr:housenumber":"40",
    "addr:postcode":"j7z 4y9",
    "addr:street":"Rue Saint-Georges Saint-Jerome",
    "iso:country":"CA",
    "sg:address":"40 Rue Saint-Georges",
    "sg:city":"Saint-Jerome",
    "sg:classifiers":[
        {
            "category":"Shopping",
            "type":"Retail Goods"
        }
    ],
    "sg:phone":"+1 450 569 5535",
    "sg:postcode":"J7Z 4Y9",
    "sg:province":"QC",
    "sg:tags":[
        "candle"
    ],
    "wof:name":"Magnetic",
    "wof:placetype":"venue"
},
  "geometry": {"coordinates":[-74.0014801025,45.7693939209],"type":"Point"}
}