{
  "type": "Feature",
  "properties": {
    "addr:full":"St Catharines ON L2R 6V6",
    "addr:postcode":"l2r 6v6",
    "iso:country":"CA",
    "sg:city":"St Catharines",
    "sg:classifiers":[
        {
            "category":"Education",
            "subcategory":"Special Training",
            "type":"Public Place"
        }
    ],
    "sg:phone":"+1 905 682 2222",
    "sg:postcode":"L2R 6V6",
    "sg:province":"ON",
    "sg:tags":[
        "reading",
        "instruction",
        "improvement"
    ],
    "wof:name":"Literacy Link Niagara",
    "wof:placetype":"venue"
},
  "geometry": {"coordinates":[-79.26243591310001,43.1606636047],"type":"Point"}
}