{
  "type": "Feature",
  "properties": {
    "addr:full":"3955 Rue Saint-Jacques Montreal QC H4C 1H9",
    "addr:housenumber":"3955",
    "addr:postcode":"h4c 1h9",
    "addr:street":"Rue Saint-Jacques",
    "iso:country":"CA",
    "sg:address":"3955 Rue Saint-Jacques",
    "sg:city":"Montreal",
    "sg:classifiers":[
        {
            "category":"Restaurant",
            "type":"Food & Drink"
        }
    ],
    "sg:phone":"+1 514 938 9398",
    "sg:postcode":"H4C 1H9",
    "sg:province":"QC",
    "sg:tags":[
        "caterer"
    ],
    "wof:name":"Maitre & Chef Traiteur Enr",
    "wof:placetype":"venue"
},
  "geometry": {"coordinates":[-73.5849,45.478786],"type":"Point"}
}