{
  "type": "Feature",
  "properties": {
    "addr:full":"4920 112 Rte Ascot Corner QC J0B 1A0",
    "addr:housenumber":"4920",
    "addr:postcode":"j0b 1a0",
    "addr:street":"112 Rte",
    "iso:country":"CA",
    "sg:address":"4920 112 Rte",
    "sg:city":"Ascot Corner",
    "sg:classifiers":[
        {
            "category":"Bars & Pubs",
            "type":"Food & Drink"
        }
    ],
    "sg:phone":"+1 819 566 4533",
    "sg:postcode":"J0B 1A0",
    "sg:province":"QC",
    "sg:tags":[
        "club",
        "lounge",
        "cocktail",
        "night"
    ],
    "wof:name":"Bar Nouveau Broadway Sep",
    "wof:placetype":"venue"
},
  "geometry": {"coordinates":[-71.7992324829,45.4370536804],"type":"Point"}
}