{
  "type": "Feature",
  "properties": {
    "addr:full":"33 Carlton St St Catharines ON L2R 1P6",
    "addr:housenumber":"33",
    "addr:postcode":"l2r 1p6",
    "addr:street":"Carlton St",
    "iso:country":"CA",
    "sg:address":"33 Carlton St",
    "sg:city":"St Catharines",
    "sg:classifiers":[
        {
            "category":"Home & Garden",
            "subcategory":"Building Materials",
            "type":"Retail Goods"
        }
    ],
    "sg:phone":"+1 905 682 8659",
    "sg:postcode":"L2R 1P6",
    "sg:province":"ON",
    "wof:name":"Hamilton Builders Supply",
    "wof:placetype":"venue"
},
  "geometry": {"coordinates":[-79.2603607178,43.1685142517],"type":"Point"}
}