{
  "type": "Feature",
  "properties": {
    "addr:full":"Scarborough ON M1V 4T5",
    "addr:postcode":"m1v 4t5",
    "iso:country":"CA",
    "sg:city":"Scarborough",
    "sg:classifiers":[
        {
            "category":"Retail",
            "subcategory":"Repair Shop",
            "type":"Services"
        }
    ],
    "sg:phone":"+1 416 291 8939",
    "sg:postcode":"M1V 4T5",
    "sg:province":"ON",
    "sg:tags":[
        "antique",
        "chinaware"
    ],
    "wof:name":"Kingsmen Antique Restoration",
    "wof:placetype":"venue"
},
  "geometry": {"coordinates":[-79.30304700000001,43.818676],"type":"Point"}
}