{
  "type": "Feature",
  "properties": {
    "iso:country":"CA",
    "sg:address":"4957 Newton St # 102",
    "sg:city":"Burnaby",
    "sg:classifiers":[
        {
            "category":"Real Estate",
            "subcategory":"Real Estate Operator",
            "type":"Services"
        }
    ],
    "sg:phone":"+1 604 435 9101",
    "sg:postcode":"V5H 4B9",
    "sg:province":"BC",
    "sg:tags":[
        "apartment"
    ],
    "wof:name":"Nelson Towers",
    "wof:placetype":"venue"
},
  "geometry": {"coordinates":[-122.993095,49.227116],"type":"Point"}
}