{
  "type": "Feature",
  "properties": {
    "addr:full":"Rocky Mountain House AB T4T 1A9",
    "addr:postcode":"t4t 1a9",
    "iso:country":"CA",
    "sg:city":"Rocky Mountain House",
    "sg:classifiers":[
        {
            "category":"Mining & Drilling",
            "type":"Manufacturing & Wholesale Goods"
        }
    ],
    "sg:phone":"+1 403 845 3787",
    "sg:postcode":"T4T 1A9",
    "sg:province":"AB",
    "sg:tags":[
        "field",
        "oil"
    ],
    "wof:name":"Terroco Oilfield Svc",
    "wof:placetype":"venue"
},
  "geometry": {"coordinates":[-114.90376999999999,52.370483],"type":"Point"}
}