{
  "type": "Feature",
  "properties": {
    "addr:full":"107 Rte Du Fleuve E Sainte-Luce QC G0K 1P0",
    "addr:housenumber":"107",
    "addr:postcode":"g0k 1p0",
    "addr:street":"Rte Du Fleuve E Sainte-Luce",
    "iso:country":"CA",
    "sg:address":"107 Rte Du Fleuve E",
    "sg:city":"Sainte-Luce",
    "sg:classifiers":[
        {
            "category":"Travel",
            "subcategory":"Hotels & Motels",
            "type":"Entertainment"
        }
    ],
    "sg:phone":"+1 418 739 4362",
    "sg:postcode":"G0K 1P0",
    "sg:province":"QC",
    "wof:name":"Motel Au Bec Fin Inc",
    "wof:placetype":"venue"
},
  "geometry": {"coordinates":[-68.35590362550001,48.5470581055],"type":"Point"}
}