{
  "type": "Feature",
  "properties": {
    "iso:country":"CA",
    "sg:address":"360 Main St # 4",
    "sg:city":"Winnipeg",
    "sg:classifiers":[
        {
            "category":"Shopping",
            "subcategory":"Florist",
            "type":"Retail Goods"
        }
    ],
    "sg:phone":"+1 204 957 1146",
    "sg:postcode":"R3C 3Z3",
    "sg:province":"MB",
    "wof:name":"Orchid Florists",
    "wof:placetype":"venue"
},
  "geometry": {"coordinates":[-97.138206,49.894695],"type":"Point"}
}