{
  "type": "Feature",
  "properties": {
    "addr:full":"451 18th St Brandon MB R7A 5A9",
    "addr:housenumber":"451",
    "addr:postcode":"r7a 5a9",
    "addr:street":"18Th St",
    "iso:country":"CA",
    "sg:address":"451 18th St",
    "sg:city":"Brandon",
    "sg:classifiers":[
        {
            "category":"Organizations",
            "subcategory":"Religious Organization",
            "type":"Services"
        }
    ],
    "sg:phone":"+1 204 727 6975",
    "sg:postcode":"R7A 5A9",
    "sg:province":"MB",
    "sg:tags":[
        "church"
    ],
    "wof:name":"Knox United Church",
    "wof:placetype":"venue"
},
  "geometry": {"coordinates":[-99.96165466310001,49.8430862427],"type":"Point"}
}