{
  "type": "Feature",
  "properties": {
    "addr:full":"152 Rue Centrale Memramcook NB E4K 3S2",
    "addr:housenumber":"152",
    "addr:postcode":"e4k 3s2",
    "addr:street":"Rue Centrale",
    "iso:country":"CA",
    "sg:address":"152 Rue Centrale",
    "sg:city":"Memramcook",
    "sg:classifiers":[
        {
            "category":"Shopping",
            "subcategory":"Pharmacy",
            "type":"Retail Goods"
        }
    ],
    "sg:phone":"+1 506 758 2880",
    "sg:postcode":"E4K 3S2",
    "sg:province":"NB",
    "wof:name":"Pharmacie LA Vallee",
    "wof:placetype":"venue"
},
  "geometry": {"coordinates":[-64.572411,45.996246],"type":"Point"}
}