{
  "type": "Feature",
  "properties": {
    "addr:full":"110 Byng Ave Scarborough ON M1L 3P1",
    "addr:housenumber":"110",
    "addr:postcode":"m1l 3p1",
    "addr:street":"Byng Ave",
    "iso:country":"CA",
    "sg:address":"110 Byng Ave",
    "sg:city":"Scarborough",
    "sg:classifiers":[
        {
            "category":"Education",
            "subcategory":"School",
            "type":"Public Place"
        }
    ],
    "sg:phone":"+1 416 396 6505",
    "sg:postcode":"M1L 3P1",
    "sg:province":"ON",
    "wof:name":"Oakridge Junior Public School",
    "wof:placetype":"venue"
},
  "geometry": {"coordinates":[-79.28113555909999,43.6951446533],"type":"Point"}
}