{
  "type": "Feature",
  "properties": {
    "iso:country":"CA",
    "sg:address":"725 Conlin Rd",
    "sg:city":"Whitby",
    "sg:classifiers":[
        {
            "category":"Organizations",
            "subcategory":"Professional Association",
            "type":"Services"
        }
    ],
    "sg:phone":"+1 905 655 5566",
    "sg:postcode":"L1R 2W8",
    "sg:province":"ON",
    "wof:name":"Durham Regional Police Assn",
    "wof:placetype":"venue"
},
  "geometry": {"coordinates":[-78.939392,43.938488],"type":"Point"}
}