{
  "type": "Feature",
  "properties": {
    "addr:full":"455 Rue Rolland Saint-Jerome QC J7Z 5S2",
    "addr:housenumber":"455",
    "addr:postcode":"j7z 5s2",
    "addr:street":"Rue Rolland",
    "iso:country":"CA",
    "sg:address":"455 Rue Rolland",
    "sg:city":"Saint-Jerome",
    "sg:classifiers":[
        {
            "category":"Manufacturing",
            "subcategory":"Paper Products",
            "type":"Manufacturing & Wholesale Goods"
        }
    ],
    "sg:phone":"+1 450 569 3900",
    "sg:postcode":"J7Z 5S2",
    "sg:province":"QC",
    "wof:name":"Division Saint Jerome",
    "wof:placetype":"venue"
},
  "geometry": {"coordinates":[-74.014565,45.764225],"type":"Point"}
}