{
  "type": "Feature",
  "properties": {
    "addr:full":"407 Boul Saint-Laurent # 902 Montreal QC H2Y 2Y5",
    "addr:housenumber":"407;902",
    "addr:postcode":"h2y 2y5",
    "addr:street":"Boul Saint-Laurent #",
    "iso:country":"CA",
    "sg:address":"407 Boul Saint-Laurent # 902",
    "sg:city":"Montreal",
    "sg:classifiers":[
        {
            "category":"Professional",
            "subcategory":"Accounting & Tax Preparation",
            "type":"Services"
        }
    ],
    "sg:phone":"+1 514 393 9339",
    "sg:postcode":"H2Y 2Y5",
    "sg:province":"QC",
    "sg:tags":[
        "accountant"
    ],
    "wof:name":"Payette & Assoc",
    "wof:placetype":"venue"
},
  "geometry": {"coordinates":[-73.55390199999999,45.505711],"type":"Point"}
}