{
  "type": "Feature",
  "properties": {
    "addr:full":"140 Queensway E # 1745 Simcoe ON N3Y 4Y7",
    "addr:housenumber":"140",
    "addr:postcode":"n3y 4y7",
    "addr:street":"Queensway E # 1745",
    "iso:country":"CA",
    "sg:address":"140 Queensway E # 1745",
    "sg:city":"Simcoe",
    "sg:classifiers":[
        {
            "category":"Autos & Motor Vehicles",
            "subcategory":"Auto Supplies",
            "type":"Retail Goods"
        }
    ],
    "sg:phone":"+1 519 426 8160",
    "sg:postcode":"N3Y 4Y7",
    "sg:province":"ON",
    "sg:tags":[
        "automobile",
        "parts"
    ],
    "wof:name":"Canadian Tire Gas Bar",
    "wof:placetype":"venue"
},
  "geometry": {"coordinates":[-80.29170999999999,42.848316],"type":"Point"}
}