{
  "type": "Feature",
  "properties": {
    "addr:full":"6249 Johnson Dr Niagara Falls ON L2J 3J6",
    "addr:housenumber":"6249",
    "addr:postcode":"l2j 3j6",
    "addr:street":"Johnson Dr",
    "iso:country":"CA",
    "sg:address":"6249 Johnson Dr",
    "sg:city":"Niagara Falls",
    "sg:classifiers":[
        {
            "category":"Wholesale",
            "subcategory":"Machinery & Supplies",
            "type":"Manufacturing & Wholesale Goods"
        }
    ],
    "sg:phone":"+1 905 358 7213",
    "sg:postcode":"L2J 3J6",
    "sg:province":"ON",
    "sg:tags":[
        "repairing"
    ],
    "wof:name":"Cullen's Machine Repair Ltd",
    "wof:placetype":"venue"
},
  "geometry": {"coordinates":[-79.094223,43.1287],"type":"Point"}
}