{
  "type": "Feature",
  "properties": {
    "addr:full":"Ottawa ON K1T 3Y2",
    "addr:postcode":"k1t 3y2",
    "iso:country":"CA",
    "sg:city":"Ottawa",
    "sg:classifiers":[
        {
            "category":"Professional",
            "subcategory":"Computer Services",
            "type":"Services"
        }
    ],
    "sg:phone":"+1 613 523 3415",
    "sg:postcode":"K1T 3Y2",
    "sg:province":"ON",
    "wof:name":"Impendo Solutions Inc",
    "wof:placetype":"venue"
},
  "geometry": {"coordinates":[-75.634529,45.366425],"type":"Point"}
}