{
  "type": "Feature",
  "properties": {
    "addr:full":"Terrebonne QC J6W 3Z5",
    "addr:postcode":"j6w 3z5",
    "iso:country":"CA",
    "sg:city":"Terrebonne",
    "sg:classifiers":[
        {
            "category":"Real Estate",
            "subcategory":"Real Estate Operator",
            "type":"Services"
        }
    ],
    "sg:phone":"+1 450 471 9726",
    "sg:postcode":"J6W 3Z5",
    "sg:province":"QC",
    "sg:tags":[
        "mall",
        "shopping",
        "center"
    ],
    "wof:name":"Galeries DE Terrebonne",
    "wof:placetype":"venue"
},
  "geometry": {"coordinates":[-73.64804077150001,45.7021827698],"type":"Point"}
}