{
  "type": "Feature",
  "properties": {
    "addr:full":"766 King St W Toronto ON M5V 1N6",
    "addr:housenumber":"766",
    "addr:postcode":"m5v 1n6",
    "addr:street":"King St W",
    "iso:country":"CA",
    "sg:address":"766 King St W",
    "sg:city":"Toronto",
    "sg:classifiers":[
        {
            "category":"Food & Beverages",
            "subcategory":"Bakery",
            "type":"Retail Goods"
        }
    ],
    "sg:phone":"+1 416 603 0369",
    "sg:postcode":"M5V 1N6",
    "sg:province":"ON",
    "sg:tags":[
        "baker"
    ],
    "wof:name":"Wagamama Pastries & Cafe",
    "wof:placetype":"venue"
},
  "geometry": {"coordinates":[-79.40557099999999,43.643463],"type":"Point"}
}