{
  "type": "Feature",
  "properties": {
    "addr:full":"Ottawa ON K2P 1W5",
    "addr:postcode":"k2p 1w5",
    "iso:country":"CA",
    "sg:city":"Ottawa",
    "sg:classifiers":[
        {
            "category":"Shopping",
            "subcategory":"Tobacco",
            "type":"Retail Goods"
        }
    ],
    "sg:phone":"+1 613 567 8855",
    "sg:postcode":"K2P 1W5",
    "sg:province":"ON",
    "sg:tags":[
        "cigarette",
        "cigar",
        "dealer"
    ],
    "wof:name":"Gcnc Lesplande Laurier",
    "wof:placetype":"venue"
},
  "geometry": {"coordinates":[-75.69854736329999,45.4181632996],"type":"Point"}
}