{
  "type": "Feature",
  "properties": {
    "addr:full":"North York ON M3N 1X6",
    "addr:postcode":"m3n 1x6",
    "iso:country":"CA",
    "sg:city":"North York",
    "sg:classifiers":[
        {
            "category":"Wholesale",
            "subcategory":"Machinery & Supplies",
            "type":"Manufacturing & Wholesale Goods"
        }
    ],
    "sg:phone":"+1 416 736 6365",
    "sg:postcode":"M3N 1X6",
    "sg:province":"ON",
    "sg:tags":[
        "repairing"
    ],
    "wof:name":"B & David Ind Machinery Inc",
    "wof:placetype":"venue"
},
  "geometry": {"coordinates":[-79.52916,43.76009],"type":"Point"}
}