{
  "type": "Feature",
  "properties": {
    "addr:full":"Timberlea NS B3T 1C9",
    "addr:postcode":"b3t 1c9",
    "iso:country":"CA",
    "sg:city":"Timberlea",
    "sg:classifiers":[
        {
            "category":"Building & Trades",
            "subcategory":"Equipment Rental",
            "type":"Services"
        }
    ],
    "sg:phone":"+1 902 876 7368",
    "sg:postcode":"B3T 1C9",
    "sg:province":"NS",
    "sg:tags":[
        "party",
        "garden",
        "center"
    ],
    "wof:name":"Oxner's Rentals Sales & Svc",
    "wof:placetype":"venue"
},
  "geometry": {"coordinates":[-63.7231330872,44.6496925354],"type":"Point"}
}