{
  "type": "Feature",
  "properties": {
    "addr:full":"Edmonton AB T6J 4R6",
    "addr:postcode":"t6j 4r6",
    "iso:country":"CA",
    "sg:city":"Edmonton",
    "sg:classifiers":[
        {
            "category":"Personal",
            "subcategory":"Tanning Parlor",
            "type":"Services"
        }
    ],
    "sg:phone":"+1 780 413 9790",
    "sg:postcode":"T6J 4R6",
    "sg:province":"AB",
    "sg:tags":[
        "salon"
    ],
    "wof:name":"Sun City Tanning Ctr",
    "wof:placetype":"venue"
},
  "geometry": {"coordinates":[-113.53173099999999,53.460533],"type":"Point"}
}