{
  "type": "Feature",
  "properties": {
    "addr:full":"38 Av Du Pont O Saint-Martin QC G0M 1B0",
    "addr:postcode":"g0m 1b0",
    "addr:street":"38 Av Du Pont O Saint-Martin",
    "iso:country":"CA",
    "sg:address":"38 Av Du Pont O",
    "sg:city":"Saint-Martin",
    "sg:classifiers":[
        {
            "category":"Wholesale",
            "subcategory":"Toys & Hobbies",
            "type":"Manufacturing & Wholesale Goods"
        }
    ],
    "sg:phone":"+1 418 582 6262",
    "sg:postcode":"G0M 1B0",
    "sg:province":"QC",
    "sg:tags":[
        "wholesaler",
        "mold",
        "maker"
    ],
    "wof:name":"Bch Unique Inc",
    "wof:placetype":"venue"
},
  "geometry": {"coordinates":[-70.6640930176,45.9594078064],"type":"Point"}
}