{
  "type": "Feature",
  "properties": {
    "addr:full":"1555 Dublin Ave #4 Winnipeg MB R3E 3M8",
    "addr:housenumber":"1555",
    "addr:postcode":"r3e 3m8",
    "addr:street":"Dublin Ave # 4",
    "iso:country":"CA",
    "sg:address":"1555 Dublin Ave #4",
    "sg:city":"Winnipeg",
    "sg:classifiers":[
        {
            "category":"Freight",
            "type":"Transportation"
        }
    ],
    "sg:phone":"+1 204 633 7207",
    "sg:postcode":"R3E 3M8",
    "sg:province":"MB",
    "sg:tags":[
        "broker",
        "customs"
    ],
    "wof:name":"A D Rutherford & CO Ltd",
    "wof:placetype":"venue"
},
  "geometry": {"coordinates":[-97.197029,49.911522],"type":"Point"}
}