{
  "type": "Feature",
  "properties": {
    "addr:full":"9557 Walker Rd Mcgregor ON N0R 1J0",
    "addr:housenumber":"9557",
    "addr:postcode":"n0r 1j0",
    "addr:street":"Walker Rd",
    "iso:country":"CA",
    "sg:address":"9557 Walker Rd",
    "sg:city":"Mcgregor",
    "sg:classifiers":[
        {
            "category":"Education",
            "subcategory":"Library",
            "type":"Public Place"
        }
    ],
    "sg:phone":"+1 519 726 6311",
    "sg:postcode":"N0R 1J0",
    "sg:province":"ON",
    "wof:name":"Mc Gregor Library",
    "wof:placetype":"venue"
},
  "geometry": {"coordinates":[-82.969643,42.144703],"type":"Point"}
}