{
  "type": "Feature",
  "properties": {
    "addr:full":"336 6th Ave N Saskatoon SK S7K 2S5",
    "addr:housenumber":"336",
    "addr:postcode":"s7k 2s5",
    "addr:street":"6Th Ave N",
    "iso:country":"CA",
    "sg:address":"336 6th Ave N",
    "sg:city":"Saskatoon",
    "sg:classifiers":[
        {
            "category":"Health Services",
            "subcategory":"Medical Lab",
            "type":"Services"
        }
    ],
    "sg:phone":"+1 306 665 8815",
    "sg:postcode":"S7K 2S5",
    "sg:province":"SK",
    "sg:tags":[
        "laboratory"
    ],
    "wof:name":"Aurum Ceramic Dental Lab Ltd",
    "wof:placetype":"venue"
},
  "geometry": {"coordinates":[-106.654854,52.131256],"type":"Point"}
}