{
  "type": "Feature",
  "properties": {
    "addr:full":"455 Elmwood Ave North Bay ON P1B 9N4",
    "addr:housenumber":"455",
    "addr:postcode":"p1b 9n4",
    "addr:street":"Elmwood Ave",
    "iso:country":"CA",
    "sg:address":"455 Elmwood Ave",
    "sg:city":"North Bay",
    "sg:classifiers":[
        {
            "category":"Building & Trades",
            "subcategory":"Construction",
            "type":"Services"
        }
    ],
    "sg:phone":"+1 705 474 3805",
    "sg:postcode":"P1B 9N4",
    "sg:province":"ON",
    "sg:tags":[
        "contractor"
    ],
    "wof:name":"Rfg Construction",
    "wof:placetype":"venue"
},
  "geometry": {"coordinates":[-79.47251900000001,46.326935],"type":"Point"}
}