{
  "type": "Feature",
  "properties": {
    "addr:full":"250 The East Mall Ste 1264 Toronto M9B 6L3",
    "addr:housenumber":"250",
    "addr:postcode":"m9b 6l3",
    "addr:street":"The East Mall Ste 1264",
    "iso:country":"CA",
    "sg:address":"250 The East Mall Ste 1264",
    "sg:city":"Toronto",
    "sg:classifiers":[
        {
            "category":"Professional",
            "subcategory":"Management & Consulting",
            "type":"Services"
        }
    ],
    "sg:postcode":"M9B 6L3",
    "sg:tags":[
        "seo",
        "sem",
        "search-engine-optimization"
    ],
    "sg:website":"http://striderseo.com",
    "wof:name":"Strider SEO",
    "wof:placetype":"venue"
},
  "geometry": {"coordinates":[-79.554784,43.632844],"type":"Point"}
}