{
  "type": "Feature",
  "properties": {
    "addr:full":"23 Perth St Elgin ON K0G 1E0",
    "addr:housenumber":"23",
    "addr:postcode":"k0g 1e0",
    "addr:street":"Perth St",
    "iso:country":"CA",
    "sg:address":"23 Perth St",
    "sg:city":"Elgin",
    "sg:classifiers":[
        {
            "category":"Retail",
            "subcategory":"Auto Repair",
            "type":"Services"
        }
    ],
    "sg:phone":"+1 613 359 5588",
    "sg:postcode":"K0G 1E0",
    "sg:province":"ON",
    "sg:tags":[
        "repairing",
        "automobile"
    ],
    "wof:name":"O'Hearn's Shell Garage",
    "wof:placetype":"venue"
},
  "geometry": {"coordinates":[-76.22386899999999,44.60854],"type":"Point"}
}