{
  "type": "Feature",
  "properties": {
    "addr:full":"Etobicoke ON M9B 6E3",
    "addr:postcode":"m9b 6e3",
    "iso:country":"CA",
    "sg:city":"Etobicoke",
    "sg:classifiers":[
        {
            "category":"Professional",
            "subcategory":"Business Services",
            "type":"Services"
        }
    ],
    "sg:phone":"+1 416 233 7440",
    "sg:postcode":"M9B 6E3",
    "sg:province":"ON",
    "sg:tags":[
        "box",
        "mail"
    ],
    "wof:name":"Cross Canada Mailbox Inc",
    "wof:placetype":"venue"
},
  "geometry": {"coordinates":[-79.54444122309999,43.6324577332],"type":"Point"}
}