{
  "type": "Feature",
  "properties": {
    "addr:full":"2101 Teston Rd Maple ON L6A 1R3",
    "addr:housenumber":"2101",
    "addr:postcode":"l6a 1r3",
    "addr:street":"Teston Rd",
    "iso:country":"CA",
    "sg:address":"2101 Teston Rd",
    "sg:city":"Maple",
    "sg:classifiers":[
        {
            "category":"Manufacturing",
            "subcategory":"Building Materials",
            "type":"Manufacturing & Wholesale Goods"
        }
    ],
    "sg:phone":"+1 905 832 4307",
    "sg:postcode":"L6A 1R3",
    "sg:province":"ON",
    "wof:name":"Precast Fabricator Global Corp",
    "wof:placetype":"venue"
},
  "geometry": {"coordinates":[-79.5113983154,43.8747787476],"type":"Point"}
}