{
  "type": "Feature",
  "properties": {
    "addr:full":"113 Charles St W Kitchener ON N2G 1H6",
    "addr:housenumber":"113",
    "addr:postcode":"n2g 1h6",
    "addr:street":"Charles St W",
    "iso:country":"CA",
    "sg:address":"113 Charles St W",
    "sg:city":"Kitchener",
    "sg:classifiers":[
        {
            "category":"Manufacturing",
            "subcategory":"Signs",
            "type":"Manufacturing & Wholesale Goods"
        }
    ],
    "sg:phone":"+1 519 579 1977",
    "sg:postcode":"N2G 1H6",
    "sg:province":"ON",
    "wof:name":"Jaz Integrated Graphics Inc",
    "wof:placetype":"venue"
},
  "geometry": {"coordinates":[-80.495796,43.450798],"type":"Point"}
}