{
  "type": "Feature",
  "properties": {
    "addr:full":"31 Axford Pky St Thomas ON N5R 6E6",
    "addr:housenumber":"31",
    "addr:postcode":"n5r 6e6",
    "addr:street":"Axford Pky",
    "iso:country":"CA",
    "sg:address":"31 Axford Pky",
    "sg:city":"St Thomas",
    "sg:classifiers":[
        {
            "category":"Arts & Performance",
            "subcategory":"Theater",
            "type":"Entertainment"
        }
    ],
    "sg:phone":"+1 519 637 1404",
    "sg:postcode":"N5R 6E6",
    "sg:province":"ON",
    "sg:tags":[
        "live",
        "music"
    ],
    "wof:name":"Sound & Motion Productions",
    "wof:placetype":"venue"
},
  "geometry": {"coordinates":[-81.1690750122,42.7563285828],"type":"Point"}
}