{
  "type": "Feature",
  "properties": {
    "addr:full":"89 Riverview Dr #206 Chatham ON N7M 6A4",
    "addr:housenumber":"89",
    "addr:postcode":"n7m 6a4",
    "addr:street":"Riverview Dr # 206",
    "iso:country":"CA",
    "sg:address":"89 Riverview Dr #206",
    "sg:city":"Chatham",
    "sg:classifiers":[
        {
            "category":"Real Estate",
            "subcategory":"Real Estate Agent",
            "type":"Services"
        }
    ],
    "sg:phone":"+1 519 354 0050",
    "sg:postcode":"N7M 6A4",
    "sg:province":"ON",
    "sg:tags":[
        "appraiser"
    ],
    "wof:name":"W L Preston Real Estate Ltd",
    "wof:placetype":"venue"
},
  "geometry": {"coordinates":[-82.20697021479999,42.3960952759],"type":"Point"}
}