{
  "type": "Feature",
  "properties": {
    "addr:full":"102 1st Ave Paradise Hill SK S0M 2G0",
    "addr:housenumber":"102",
    "addr:postcode":"s0m 2g0",
    "addr:street":"1St Ave Paradise Hill",
    "iso:country":"CA",
    "sg:address":"102 1st Ave",
    "sg:city":"Paradise Hill",
    "sg:classifiers":[
        {
            "category":"Autos & Motor Vehicles",
            "subcategory":"Fuel & Gas Station",
            "type":"Retail Goods"
        }
    ],
    "sg:phone":"+1 306 344 2092",
    "sg:postcode":"S0M 2G0",
    "sg:province":"SK",
    "sg:tags":[
        "repairing",
        "automobile",
        "oil"
    ],
    "wof:name":"R/T Auto Ltd",
    "wof:placetype":"venue"
},
  "geometry": {"coordinates":[-109.45829773,53.5379142761],"type":"Point"}
}