{
  "type": "Feature",
  "properties": {
    "addr:full":"Brampton ON L6Y 4M3",
    "addr:postcode":"l6y 4m3",
    "iso:country":"CA",
    "sg:city":"Brampton",
    "sg:classifiers":[
        {
            "category":"Education",
            "subcategory":"Special Training",
            "type":"Public Place"
        }
    ],
    "sg:phone":"+1 905 457 5094",
    "sg:postcode":"L6Y 4M3",
    "sg:province":"ON",
    "sg:tags":[
        "tutoring"
    ],
    "wof:name":"Oxford Learning Ctr",
    "wof:placetype":"venue"
},
  "geometry": {"coordinates":[-79.7126083374,43.6507492065],"type":"Point"}
}