{
  "type": "Feature",
  "properties": {
    "addr:full":"7059 Farrell Rd SE Calgary AB T2H 0T3",
    "addr:housenumber":"7059",
    "addr:postcode":"t2h 0t3",
    "addr:street":"Farrell Rd Se",
    "iso:country":"CA",
    "sg:address":"7059 Farrell Rd SE",
    "sg:city":"Calgary",
    "sg:classifiers":[
        {
            "category":"Professional",
            "subcategory":"Advertising",
            "type":"Services"
        }
    ],
    "sg:phone":"+1 403 252 3367",
    "sg:postcode":"T2H 0T3",
    "sg:province":"AB",
    "sg:tags":[
        "bench"
    ],
    "wof:name":"Far West Advertising Ltd",
    "wof:placetype":"venue"
},
  "geometry": {"coordinates":[-114.057114,50.991901],"type":"Point"}
}