{
  "type": "Feature",
  "properties": {
    "iso:country":"CA",
    "sg:address":"35 Rue DE LA Fabrique",
    "sg:city":"Varennes",
    "sg:classifiers":[
        {
            "category":"Government",
            "subcategory":"Office",
            "type":"Public Place"
        }
    ],
    "sg:phone":"+1 450 652 9130",
    "sg:postcode":"J3X 1R1",
    "sg:province":"QC",
    "sg:tags":[
        "village"
    ],
    "wof:name":"Varennes Maison St Louis",
    "wof:placetype":"venue"
},
  "geometry": {"coordinates":[-73.44090300000001,45.682896],"type":"Point"}
}