{
  "type": "Feature",
  "properties": {
    "addr:full":"141 Toryork Dr North York ON M9L 1X9",
    "addr:housenumber":"141",
    "addr:postcode":"m9l 1x9",
    "addr:street":"Toryork Dr",
    "iso:country":"CA",
    "sg:address":"141 Toryork Dr",
    "sg:city":"North York",
    "sg:classifiers":[
        {
            "category":"Retail",
            "subcategory":"Auto Rental",
            "type":"Services"
        }
    ],
    "sg:phone":"+1 416 310 2277",
    "sg:postcode":"M9L 1X9",
    "sg:province":"ON",
    "sg:tags":[
        "renting",
        "automobile"
    ],
    "wof:name":"Discount Car & Truck Rentals",
    "wof:placetype":"venue"
},
  "geometry": {"coordinates":[-79.5539779663,43.7574996948],"type":"Point"}
}