{
  "type": "Feature",
  "properties": {
    "addr:full":"218 Rang Saint-Antoine Saint-Elphege QC J0G 1J0",
    "addr:housenumber":"218",
    "addr:postcode":"j0g 1j0",
    "addr:street":"Rang Saint-Antoine",
    "iso:country":"CA",
    "sg:address":"218 Rang Saint-Antoine",
    "sg:city":"Saint-Elphege",
    "sg:classifiers":[
        {
            "category":"Retail",
            "subcategory":"Auto Repair",
            "type":"Services"
        }
    ],
    "sg:phone":"+1 450 568 1082",
    "sg:postcode":"J0G 1J0",
    "sg:province":"QC",
    "sg:tags":[
        "body",
        "automobile",
        "painting"
    ],
    "wof:name":"Carrosserie Y Plus",
    "wof:placetype":"venue"
},
  "geometry": {"coordinates":[-72.69918800000001,46.062325],"type":"Point"}
}