{
  "type": "Feature",
  "properties": {
    "iso:country":"CA",
    "sg:address":"1485 55E Av",
    "sg:city":"Laval",
    "sg:classifiers":[
        {
            "category":"Building & Trades",
            "subcategory":"Electrical",
            "type":"Services"
        }
    ],
    "sg:phone":"+1 450 962 4021",
    "sg:postcode":"H7R 4C7",
    "sg:province":"QC",
    "sg:tags":[
        "consultant",
        "electric",
        "contractor"
    ],
    "wof:name":"Grenier Inc",
    "wof:placetype":"venue"
},
  "geometry": {"coordinates":[-73.8677978516,45.5571632385],"type":"Point"}
}