{
  "type": "Feature",
  "properties": {
    "addr:full":"1881 Yonge St Toronto ON M4S 3C4",
    "addr:housenumber":"1881",
    "addr:postcode":"m4s 3c4",
    "addr:street":"Yonge St",
    "iso:country":"CA",
    "sg:address":"1881 Yonge St",
    "sg:city":"Toronto",
    "sg:classifiers":[
        {
            "category":"Shopping",
            "subcategory":"Pharmacy",
            "type":"Retail Goods"
        }
    ],
    "sg:phone":"+1 416 480 1420",
    "sg:postcode":"M4S 3C4",
    "sg:province":"ON",
    "wof:name":"Welcome Guardian Drugs",
    "wof:placetype":"venue"
},
  "geometry": {"coordinates":[-79.396286,43.697594],"type":"Point"}
}