{
  "type": "Feature",
  "properties": {
    "addr:full":"158 Rue Principale Grenville QC J0V 1J0",
    "addr:housenumber":"158",
    "addr:postcode":"j0v 1j0",
    "addr:street":"Rue Principale",
    "iso:country":"CA",
    "sg:address":"158 Rue Principale",
    "sg:city":"Grenville",
    "sg:classifiers":[
        {
            "category":"Organizations",
            "subcategory":"Religious Organization",
            "type":"Services"
        }
    ],
    "sg:phone":"+1 819 242 4004",
    "sg:postcode":"J0V 1J0",
    "sg:province":"QC",
    "sg:tags":[
        "church"
    ],
    "wof:name":"Hawkesbury Ouest Temoins",
    "wof:placetype":"venue"
},
  "geometry": {"coordinates":[-74.598541,45.63382],"type":"Point"}
}