{
  "type": "Feature",
  "properties": {
    "addr:full":"332 Central Ave London ON N6B 2C8",
    "addr:housenumber":"332",
    "addr:postcode":"n6b 2c8",
    "addr:street":"Central Ave",
    "iso:country":"CA",
    "sg:address":"332 Central Ave",
    "sg:city":"London",
    "sg:classifiers":[
        {
            "category":"Professional",
            "subcategory":"Computer Services",
            "type":"Services"
        }
    ],
    "sg:phone":"+1 519 642 0555",
    "sg:postcode":"N6B 2C8",
    "sg:province":"ON",
    "sg:tags":[
        "consultant"
    ],
    "wof:name":"Synergy Solutions",
    "wof:placetype":"venue"
},
  "geometry": {"coordinates":[-81.24617000000001,42.991711],"type":"Point"}
}