{
  "type": "Feature",
  "properties": {
    "addr:full":"251 Rue Turgeon Hebertville QC G8N 1S2",
    "addr:housenumber":"251",
    "addr:postcode":"g8n 1s2",
    "addr:street":"Rue Turgeon Hebertville",
    "iso:country":"CA",
    "sg:address":"251 Rue Turgeon",
    "sg:city":"Hebertville",
    "sg:classifiers":[
        {
            "category":"Organizations",
            "subcategory":"Religious Organization",
            "type":"Services"
        }
    ],
    "sg:phone":"+1 418 344 1803",
    "sg:postcode":"G8N 1S2",
    "sg:province":"QC",
    "sg:tags":[
        "church"
    ],
    "wof:name":"Presbytere N-D D'Hebertville",
    "wof:placetype":"venue"
},
  "geometry": {"coordinates":[-71.679642,48.39193],"type":"Point"}
}