{
  "type": "Feature",
  "properties": {
    "addr:full":"1350 Rue Beaubien E Montreal QC H2G 1K9",
    "addr:housenumber":"1350",
    "addr:postcode":"h2g 1k9",
    "addr:street":"Rue Beaubien E",
    "iso:country":"CA",
    "sg:address":"1350 Rue Beaubien E",
    "sg:city":"Montreal",
    "sg:classifiers":[
        {
            "category":"Retail",
            "subcategory":"Funeral Services",
            "type":"Services"
        }
    ],
    "sg:phone":"+1 514 271 4533",
    "sg:postcode":"H2G 1K9",
    "sg:province":"QC",
    "sg:tags":[
        "director"
    ],
    "wof:name":"Omer Duquette Inc",
    "wof:placetype":"venue"
},
  "geometry": {"coordinates":[-73.59876300000001,45.54073],"type":"Point"}
}