{
  "type": "Feature",
  "properties": {
    "addr:full":"1630 5th Ave W Vancouver BC V6J 1N8",
    "addr:housenumber":"1630",
    "addr:postcode":"v6j 1n8",
    "addr:street":"5Th Ave W",
    "iso:country":"CA",
    "sg:address":"1630 5th Ave W",
    "sg:city":"Vancouver",
    "sg:classifiers":[
        {
            "category":"Recreation",
            "type":"Entertainment"
        }
    ],
    "sg:phone":"+1 604 736 7946",
    "sg:postcode":"V6J 1N8",
    "sg:province":"BC",
    "sg:tags":[
        "club",
        "instruction",
        "sport",
        "swimming"
    ],
    "wof:name":"Aquaventures Swim Ctr",
    "wof:placetype":"venue"
},
  "geometry": {"coordinates":[-123.14170799999999,49.266949],"type":"Point"}
}