{
  "type": "Feature",
  "properties": {
    "addr:full":"PO Box 120 Cape Dorset NU X0A 0C0",
    "addr:housenumber":"po",
    "addr:postcode":"x0a 0c0",
    "addr:street":"Box 120",
    "iso:country":"CA",
    "sg:address":"PO Box 120",
    "sg:city":"Cape Dorset",
    "sg:classifiers":[
        {
            "category":"Government",
            "subcategory":"Office",
            "type":"Public Place"
        }
    ],
    "sg:phone":"+1 867 897 8260",
    "sg:postcode":"X0A 0C0",
    "sg:province":"NU",
    "sg:tags":[
        "village"
    ],
    "wof:name":"Cape Dorset By-Law Office",
    "wof:placetype":"venue"
},
  "geometry": {"coordinates":[-76.54080999999999,64.231346],"type":"Point"}
}