{
  "type": "Feature",
  "properties": {
    "addr:full":"1 Gardenia Crt North York ON M2M 4G2",
    "addr:housenumber":"1",
    "addr:postcode":"m2m 4g2",
    "addr:street":"Gardenia Crt",
    "iso:country":"CA",
    "sg:address":"1 Gardenia Crt",
    "sg:city":"North York",
    "sg:classifiers":[
        {
            "category":"Social Services",
            "type":"Services"
        }
    ],
    "sg:phone":"+1 416 250 8965",
    "sg:postcode":"M2M 4G2",
    "sg:province":"ON",
    "sg:tags":[
        "health",
        "instruction",
        "appliance",
        "care"
    ],
    "wof:name":"Sage Care Inc",
    "wof:placetype":"venue"
},
  "geometry": {"coordinates":[-79.43145800000001,43.783939],"type":"Point"}
}