{
  "type": "Feature",
  "properties": {
    "iso:country":"CA",
    "sg:address":"677 Princess St",
    "sg:city":"Kingston",
    "sg:classifiers":[
        {
            "category":"Autos & Motor Vehicles",
            "subcategory":"Automobile Sales",
            "type":"Retail Goods"
        }
    ],
    "sg:phone":"+1 613 544 4872",
    "sg:postcode":"K7L 1E6",
    "sg:province":"ON",
    "sg:tags":[
        "car",
        "dealer"
    ],
    "wof:name":"Jackson Motor Sales",
    "wof:placetype":"venue"
},
  "geometry": {"coordinates":[-76.5052719116,44.2385749817],"type":"Point"}
}