{
  "type": "Feature",
  "properties": {
    "addr:full":"5720 Silver Ridge Dr NW Calgary AB T3B 5E5",
    "addr:housenumber":"5720",
    "addr:postcode":"t3b 5e5",
    "addr:street":"Silver Ridge Dr Nw",
    "iso:country":"CA",
    "sg:address":"5720 Silver Ridge Dr NW",
    "sg:city":"Calgary",
    "sg:classifiers":[
        {
            "category":"Organizations",
            "subcategory":"Religious Organization",
            "type":"Services"
        }
    ],
    "sg:phone":"+1 403 819 9555",
    "sg:postcode":"T3B 5E5",
    "sg:province":"AB",
    "sg:tags":[
        "church"
    ],
    "wof:name":"North Calgary Community Church",
    "wof:placetype":"venue"
},
  "geometry": {"coordinates":[-114.19014,51.10368],"type":"Point"}
}