{
  "type": "Feature",
  "properties": {
    "addr:full":"5 Jonagold Pl Osoyoos BC V0H 1V0",
    "addr:housenumber":"5",
    "addr:postcode":"v0h 1v0",
    "addr:street":"Jonagold Pl",
    "iso:country":"CA",
    "sg:address":"5 Jonagold Pl",
    "sg:city":"Osoyoos",
    "sg:classifiers":[
        {
            "category":"Health Services",
            "subcategory":"Nursing And Care Facility",
            "type":"Services"
        }
    ],
    "sg:phone":"+1 250 495 6666",
    "sg:postcode":"V0H 1V0",
    "sg:province":"BC",
    "sg:tags":[
        "home",
        "retirement",
        "community"
    ],
    "wof:name":"Elk's Golden Villa",
    "wof:placetype":"venue"
},
  "geometry": {"coordinates":[-119.46616400000001,49.035355],"type":"Point"}
}