{
  "type": "Feature",
  "properties": {
    "addr:full":"Scarborough ON M1P 2X5",
    "addr:postcode":"m1p 2x5",
    "iso:country":"CA",
    "sg:city":"Scarborough",
    "sg:classifiers":[
        {
            "category":"Manufacturing",
            "subcategory":"Signs",
            "type":"Manufacturing & Wholesale Goods"
        }
    ],
    "sg:phone":"+1 416 291 7090",
    "sg:postcode":"M1P 2X5",
    "sg:province":"ON",
    "wof:name":"Precision Signs Ltd",
    "wof:placetype":"venue"
},
  "geometry": {"coordinates":[-79.26812700000001,43.768745],"type":"Point"}
}