{
  "type": "Feature",
  "properties": {
    "addr:full":"51 Cobequid Rd Lower Sackville NS B4C 2N1",
    "addr:housenumber":"51",
    "addr:postcode":"b4c 2n1",
    "addr:street":"Cobequid Rd Lower",
    "iso:country":"CA",
    "sg:address":"51 Cobequid Rd",
    "sg:city":"Lower Sackville",
    "sg:classifiers":[
        {
            "category":"Government",
            "subcategory":"Office",
            "type":"Public Place"
        }
    ],
    "sg:phone":"+1 902 865 2311",
    "sg:postcode":"B4C 2N1",
    "sg:province":"NS",
    "sg:tags":[
        "member",
        "legislative",
        "assembly"
    ],
    "wof:name":"Peter Soffer Sackville Eastern",
    "wof:placetype":"venue"
},
  "geometry": {"coordinates":[-63.662804,44.753922],"type":"Point"}
}