{
  "type": "Feature",
  "properties": {
    "addr:full":"1548 Broadway W Vancouver BC V6J 5K9",
    "addr:housenumber":"1548",
    "addr:postcode":"v6j 5k9",
    "addr:street":"Broadway W",
    "iso:country":"CA",
    "sg:address":"1548 Broadway W",
    "sg:city":"Vancouver",
    "sg:classifiers":[
        {
            "category":"Home & Garden",
            "subcategory":"Home Furnishings",
            "type":"Retail Goods"
        }
    ],
    "sg:phone":"+1 604 731 1148",
    "sg:postcode":"V6J 5K9",
    "sg:province":"BC",
    "sg:tags":[
        "utensil",
        "cooking",
        "kitchen",
        "accessory"
    ],
    "wof:name":"Cookworks",
    "wof:placetype":"venue"
},
  "geometry": {"coordinates":[-123.139923,49.263538],"type":"Point"}
}