{
  "type": "Feature",
  "properties": {
    "addr:full":"Metcalfe ON K0A 2P0",
    "addr:postcode":"k0a 2p0",
    "iso:country":"CA",
    "sg:city":"Metcalfe",
    "sg:classifiers":[
        {
            "category":"Recreation",
            "type":"Entertainment"
        }
    ],
    "sg:phone":"+1 613 821 1237",
    "sg:postcode":"K0A 2P0",
    "sg:province":"ON",
    "sg:tags":[
        "government",
        "hall",
        "auditorium"
    ],
    "wof:name":"Metcalfe Centres Communautaire",
    "wof:placetype":"venue"
},
  "geometry": {"coordinates":[-75.4691619873,45.229385376],"type":"Point"}
}