{
  "type": "Feature",
  "properties": {
    "addr:full":"3800 Rue Saint-Patrick Montreal QC H4E 1A4",
    "addr:housenumber":"3800",
    "addr:postcode":"h4e 1a4",
    "addr:street":"Rue Saint-Patrick",
    "iso:country":"CA",
    "sg:address":"3800 Rue Saint-Patrick",
    "sg:city":"Montreal",
    "sg:classifiers":[
        {
            "category":"Professional",
            "subcategory":"Advertising",
            "type":"Services"
        }
    ],
    "sg:phone":"+1 514 939 5743",
    "sg:postcode":"H4E 1A4",
    "sg:province":"QC",
    "sg:tags":[
        "distribution"
    ],
    "wof:name":"Bennett Little Group",
    "wof:placetype":"venue"
},
  "geometry": {"coordinates":[-73.58223700000001,45.469807],"type":"Point"}
}