{
  "type": "Feature",
  "properties": {
    "addr:full":"4205 Shipp Dr # 101 Mississauga ON L4Z 2Y9",
    "addr:housenumber":"4205",
    "addr:postcode":"l4z 2y9",
    "addr:street":"Shipp Dr # 101",
    "iso:country":"CA",
    "sg:address":"4205 Shipp Dr # 101",
    "sg:city":"Mississauga",
    "sg:classifiers":[
        {
            "category":"Real Estate",
            "subcategory":"Real Estate Operator",
            "type":"Services"
        }
    ],
    "sg:phone":"+1 905 897 1038",
    "sg:postcode":"L4Z 2Y9",
    "sg:province":"ON",
    "sg:tags":[
        "apartment"
    ],
    "wof:name":"Chelsea Towers Rental Office",
    "wof:placetype":"venue"
},
  "geometry": {"coordinates":[-79.6379852295,43.5991897583],"type":"Point"}
}