{
  "type": "Feature",
  "properties": {
    "addr:full":"4824 Yonge St North York ON M2N 5M9",
    "addr:housenumber":"4824",
    "addr:postcode":"m2n 5m9",
    "addr:street":"Yonge St",
    "iso:country":"CA",
    "sg:address":"4824 Yonge St",
    "sg:city":"North York",
    "sg:classifiers":[
        {
            "category":"Banks & Credit Unions",
            "subcategory":"Investment Brokerage",
            "type":"Services"
        }
    ],
    "sg:phone":"+1 416 222 2333",
    "sg:postcode":"M2N 5M9",
    "sg:province":"ON",
    "wof:name":"Cet Marketing Corp",
    "wof:placetype":"venue"
},
  "geometry": {"coordinates":[-79.4112243652,43.7619895935],"type":"Point"}
}