{
  "type": "Feature",
  "properties": {
    "addr:full":"5214 47 Ave Red Deer AB T4N 3P7",
    "addr:housenumber":"5214",
    "addr:postcode":"t4n 3p7",
    "addr:street":"47 Ave",
    "iso:country":"CA",
    "sg:address":"5214 47 Ave",
    "sg:city":"Red Deer",
    "sg:classifiers":[
        {
            "category":"Cinema",
            "subcategory":"Movie Theater",
            "type":"Entertainment"
        }
    ],
    "sg:phone":"+1 403 347 6440",
    "sg:postcode":"T4N 3P7",
    "sg:province":"AB",
    "wof:name":"Park Plaza Theatre 7",
    "wof:placetype":"venue"
},
  "geometry": {"coordinates":[-113.80521400000001,52.271111],"type":"Point"}
}