{
  "type": "Feature",
  "properties": {
    "addr:full":"20 Rue Jacques-Cartier Salaberry-DE-Valleyfield QC J6T 4P6",
    "addr:housenumber":"20",
    "addr:postcode":"j6t 4p6",
    "addr:street":"Rue Jacques-Cartier",
    "iso:country":"CA",
    "sg:address":"20 Rue Jacques-Cartier",
    "sg:city":"Salaberry-DE-Valleyfield",
    "sg:classifiers":[
        {
            "category":"Personal",
            "subcategory":"Beauty Salon",
            "type":"Services"
        }
    ],
    "sg:phone":"+1 450 373 4347",
    "sg:postcode":"J6T 4P6",
    "sg:province":"QC",
    "wof:name":"Salon Scrupules II",
    "wof:placetype":"venue"
},
  "geometry": {"coordinates":[-74.12995100000001,45.25555],"type":"Point"}
}