{
  "type": "Feature",
  "properties": {
    "addr:full":"55 Bathurst Dr Waterloo ON N2V 1N2",
    "addr:housenumber":"55",
    "addr:postcode":"n2v 1n2",
    "addr:street":"Bathurst Dr",
    "iso:country":"CA",
    "sg:address":"55 Bathurst Dr",
    "sg:city":"Waterloo",
    "sg:classifiers":[
        {
            "category":"Autos & Motor Vehicles",
            "subcategory":"Auto Supplies",
            "type":"Retail Goods"
        }
    ],
    "sg:phone":"+1 519 886 0749",
    "sg:postcode":"N2V 1N2",
    "sg:province":"ON",
    "sg:tags":[
        "filter",
        "gas"
    ],
    "wof:name":"Dynamic Filtration Ltd",
    "wof:placetype":"venue"
},
  "geometry": {"coordinates":[-80.537796,43.507835],"type":"Point"}
}