{
  "type": "Feature",
  "properties": {
    "addr:full":"1331 Rue Denault Sherbrooke QC J1H 2P6",
    "addr:housenumber":"1331",
    "addr:postcode":"j1h 2p6",
    "addr:street":"Rue Denault",
    "iso:country":"CA",
    "sg:address":"1331 Rue Denault",
    "sg:city":"Sherbrooke",
    "sg:classifiers":[
        {
            "category":"Building & Trades",
            "subcategory":"Plumbing",
            "type":"Services"
        }
    ],
    "sg:phone":"+1 819 565 0817",
    "sg:postcode":"J1H 2P6",
    "sg:province":"QC",
    "sg:tags":[
        "conditioning",
        "air",
        "system",
        "contractor"
    ],
    "wof:name":"Climatisation Roger Demers Inc",
    "wof:placetype":"venue"
},
  "geometry": {"coordinates":[-71.9087905884,45.389087677],"type":"Point"}
}