{
  "type": "Feature",
  "properties": {
    "addr:full":"4824 Commercial St Vancouver BC V5N 4H1",
    "addr:housenumber":"4824",
    "addr:postcode":"v5n 4h1",
    "addr:street":"Commercial St",
    "iso:country":"CA",
    "sg:address":"4824 Commercial St",
    "sg:city":"Vancouver",
    "sg:classifiers":[
        {
            "category":"Social Services",
            "type":"Services"
        }
    ],
    "sg:phone":"+1 604 872 4431",
    "sg:postcode":"V5N 4H1",
    "sg:province":"BC",
    "sg:tags":[
        "community"
    ],
    "wof:name":"Hispanic Community Ctr of BC",
    "wof:placetype":"venue"
},
  "geometry": {"coordinates":[-123.067795,49.241127],"type":"Point"}
}