{
  "type": "Feature",
  "properties": {
    "addr:full":"181 Tecumseh Ave E London ON N6C 1S3",
    "addr:housenumber":"181",
    "addr:postcode":"n6c 1s3",
    "addr:street":"Tecumseh Ave E",
    "iso:country":"CA",
    "sg:address":"181 Tecumseh Ave E",
    "sg:city":"London",
    "sg:classifiers":[
        {
            "category":"Health Services",
            "subcategory":"Doctor",
            "type":"Services"
        }
    ],
    "sg:phone":"+1 519 433 9541",
    "sg:postcode":"N6C 1S3",
    "sg:province":"ON",
    "sg:tags":[
        "physician",
        "surgeon"
    ],
    "wof:name":"Odegaard, Paul MD",
    "wof:placetype":"venue"
},
  "geometry": {"coordinates":[-81.25142700000001,42.96814],"type":"Point"}
}