{
  "type": "Feature",
  "properties": {
    "addr:full":"354 113 Rte N Senneterre QC J0Y 2M0",
    "addr:housenumber":"113",
    "addr:postcode":"j0y 2m0",
    "addr:street":"Rte N",
    "iso:country":"CA",
    "sg:address":"354 113 Rte N",
    "sg:city":"Senneterre",
    "sg:classifiers":[
        {
            "category":"Travel",
            "subcategory":"Campground",
            "type":"Entertainment"
        }
    ],
    "sg:phone":"+1 819 737 4580",
    "sg:postcode":"J0Y 2M0",
    "sg:province":"QC",
    "sg:tags":[
        "camp",
        "fishing"
    ],
    "wof:name":"Parent Lake Lodge",
    "wof:placetype":"venue"
},
  "geometry": {"coordinates":[-77.242271,48.390732],"type":"Point"}
}