{
  "type": "Feature",
  "properties": {
    "iso:country":"CA",
    "sg:address":"354 113 Rte N",
    "sg:city":"Senneterre",
    "sg:classifiers":[
        {
            "category":"Travel",
            "subcategory":"Campground",
            "type":"Entertainment"
        }
    ],
    "sg:phone":"+1 819 737 4580",
    "sg:postcode":"J0Y 2M0",
    "sg:province":"QC",
    "sg:tags":[
        "camp",
        "fishing"
    ],
    "wof:name":"Parent Lake Lodge",
    "wof:placetype":"venue"
},
  "geometry": {"coordinates":[-77.242271,48.390732],"type":"Point"}
}