{
  "type": "Feature",
  "properties": {
    "addr:full":"7440 10 St NW Calgary AB T2K 1H6",
    "addr:housenumber":"7440",
    "addr:postcode":"t2k 1h6",
    "addr:street":"10 St Nw",
    "iso:country":"CA",
    "sg:address":"7440 10 St NW",
    "sg:city":"Calgary",
    "sg:classifiers":[
        {
            "category":"Education",
            "subcategory":"School",
            "type":"Public Place"
        }
    ],
    "sg:phone":"+1 403 777 6640",
    "sg:postcode":"T2K 1H6",
    "sg:province":"AB",
    "wof:name":"J K Mulloy Elementary Sch",
    "wof:placetype":"venue"
},
  "geometry": {"coordinates":[-114.080406,51.118568],"type":"Point"}
}