{
  "type": "Feature",
  "properties": {
    "addr:full":"10930 Mayfield Rd NW Edmonton AB T5P 4B6",
    "addr:housenumber":"10930",
    "addr:postcode":"t5p 4b6",
    "addr:street":"Mayfield Rd Nw",
    "iso:country":"CA",
    "sg:address":"10930 Mayfield Rd NW",
    "sg:city":"Edmonton",
    "sg:classifiers":[
        {
            "category":"Home & Garden",
            "subcategory":"Furniture",
            "type":"Retail Goods"
        }
    ],
    "sg:phone":"+1 780 486 1401",
    "sg:postcode":"T5P 4B6",
    "sg:province":"AB",
    "wof:name":"Dinette & Patio Showplace",
    "wof:placetype":"venue"
},
  "geometry": {"coordinates":[-113.605507,53.556435],"type":"Point"}
}