{
  "type": "Feature",
  "properties": {
    "addr:full":"9350 Yonge St #H19 Richmond Hill ON L4C 5G2",
    "addr:housenumber":"9350",
    "addr:postcode":"l4c 5g2",
    "addr:street":"Yonge St # H19",
    "iso:country":"CA",
    "sg:address":"9350 Yonge St #H19",
    "sg:city":"Richmond Hill",
    "sg:classifiers":[
        {
            "category":"Shopping",
            "subcategory":"Clothing, Apparel, & Fashions",
            "type":"Retail Goods"
        }
    ],
    "sg:phone":"+1 905 508 4919",
    "sg:postcode":"L4C 5G2",
    "sg:province":"ON",
    "sg:tags":[
        "hair",
        "salon",
        "beauty"
    ],
    "wof:name":"Trade Secrets",
    "wof:placetype":"venue"
},
  "geometry": {"coordinates":[-79.425911,43.822536],"type":"Point"}
}