{
  "type": "Feature",
  "properties": {
    "addr:full":"5196 Richmond Rd SW Calgary AB T3E 6M9",
    "addr:housenumber":"5196",
    "addr:postcode":"t3e 6m9",
    "addr:street":"Richmond Rd Sw",
    "iso:country":"CA",
    "sg:address":"5196 Richmond Rd SW",
    "sg:city":"Calgary",
    "sg:classifiers":[
        {
            "category":"Autos & Motor Vehicles",
            "subcategory":"Auto Supplies",
            "type":"Retail Goods"
        }
    ],
    "sg:phone":"+1 403 246 6849",
    "sg:postcode":"T3E 6M9",
    "sg:province":"AB",
    "sg:tags":[
        "automobile",
        "parts"
    ],
    "wof:name":"Canadian Tire Gas Bar",
    "wof:placetype":"venue"
},
  "geometry": {"coordinates":[-114.161545,51.018047],"type":"Point"}
}