{
  "type": "Feature",
  "properties": {
    "addr:full":"Kamloops BC V2C 5P4",
    "addr:postcode":"bc v2c 5p4",
    "iso:country":"CA",
    "sg:city":"Kamloops",
    "sg:classifiers":[
        {
            "category":"Home & Garden",
            "subcategory":"Carpets & Floor Coverings",
            "type":"Retail Goods"
        }
    ],
    "sg:phone":"+1 250 828 1662",
    "sg:postcode":"V2C 5P4",
    "sg:province":"BC",
    "sg:tags":[
        "material"
    ],
    "wof:name":"Floors Galore",
    "wof:placetype":"venue"
},
  "geometry": {"coordinates":[-120.362976,50.659454],"type":"Point"}
}