{
  "type": "Feature",
  "properties": {
    "addr:full":"Calgary AB T2S 1W7",
    "addr:postcode":"t2s 1w7",
    "iso:country":"CA",
    "sg:city":"Calgary",
    "sg:classifiers":[
        {
            "category":"Bars & Pubs",
            "type":"Food & Drink"
        }
    ],
    "sg:phone":"+1 403 245 6585",
    "sg:postcode":"T2S 1W7",
    "sg:province":"AB",
    "wof:name":"Ducky's Pub & Restaurant",
    "wof:placetype":"venue"
},
  "geometry": {"coordinates":[-114.07138824499999,51.0341453552],"type":"Point"}
}