{
  "type": "Feature",
  "properties": {
    "addr:full":"2103 Galetta Side Rd Fitzroy Harbour ON K0A 1X0",
    "addr:housenumber":"2103",
    "addr:postcode":"k0a 1x0",
    "addr:street":"Galetta Side Rd",
    "iso:country":"CA",
    "sg:address":"2103 Galetta Side Rd",
    "sg:city":"Fitzroy Harbour",
    "sg:classifiers":[
        {
            "category":"Shopping",
            "subcategory":"Computers & Home Electronics",
            "type":"Retail Goods"
        }
    ],
    "sg:phone":"+1 613 623 8686",
    "sg:postcode":"K0A 1X0",
    "sg:province":"ON",
    "sg:tags":[
        "software"
    ],
    "wof:name":"Brainwaves Software",
    "wof:placetype":"venue"
},
  "geometry": {"coordinates":[-76.182343,45.469627],"type":"Point"}
}