{
  "type": "Feature",
  "properties": {
    "addr:full":"62 Rue DE LA Greve LA Malbaie QC G5A 2R3",
    "addr:housenumber":"62",
    "addr:postcode":"g5a 2r3",
    "addr:street":"Rue De La Greve",
    "iso:country":"CA",
    "sg:address":"62 Rue DE LA Greve",
    "sg:city":"LA Malbaie",
    "sg:classifiers":[
        {
            "category":"Organizations",
            "subcategory":"Professional Association",
            "type":"Services"
        }
    ],
    "sg:phone":"+1 418 665 7459",
    "sg:postcode":"G5A 2R3",
    "sg:province":"QC",
    "wof:name":"Centre Femmes Aux Plurielles",
    "wof:placetype":"venue"
},
  "geometry": {"coordinates":[-70.0987625122,47.6627960205],"type":"Point"}
}