{
  "type": "Feature",
  "properties": {
    "addr:full":"1004 Dundas St W Toronto ON M6J 1W6",
    "addr:housenumber":"1004",
    "addr:postcode":"m6j 1w6",
    "addr:street":"Dundas St W",
    "iso:country":"CA",
    "sg:address":"1004 Dundas St W",
    "sg:city":"Toronto",
    "sg:classifiers":[
        {
            "category":"Food & Beverages",
            "subcategory":"Meat & Fish",
            "type":"Retail Goods"
        }
    ],
    "sg:phone":"+1 416 531 8422",
    "sg:postcode":"M6J 1W6",
    "sg:province":"ON",
    "sg:tags":[
        "sausage"
    ],
    "wof:name":"Superior Sausage CO",
    "wof:placetype":"venue"
},
  "geometry": {"coordinates":[-79.41566467289999,43.6504707336],"type":"Point"}
}