{
  "type": "Feature",
  "properties": {
    "addr:full":"115 Boul Rene-Levesque O Quebec QC G1R 2A6",
    "addr:housenumber":"115",
    "addr:postcode":"g1r 2a6",
    "addr:street":"Boul Rene-Levesque O",
    "iso:country":"CA",
    "sg:address":"115 Boul Rene-Levesque O",
    "sg:city":"Quebec",
    "sg:classifiers":[
        {
            "category":"Retail",
            "subcategory":"Auto Repair",
            "type":"Services"
        }
    ],
    "sg:phone":"+1 418 522 7273",
    "sg:postcode":"G1R 2A6",
    "sg:province":"QC",
    "sg:tags":[
        "repairing",
        "automobile"
    ],
    "wof:name":"Centre DE L'Auto Shell Cartier",
    "wof:placetype":"venue"
},
  "geometry": {"coordinates":[-71.22411346440001,46.8055610657],"type":"Point"}
}