{
  "type": "Feature",
  "properties": {
    "addr:full":"Toronto ON M4S 2B9",
    "addr:postcode":"m4s 2b9",
    "iso:country":"CA",
    "sg:city":"Toronto",
    "sg:classifiers":[
        {
            "category":"Travel",
            "subcategory":"Travel Agent",
            "type":"Entertainment"
        }
    ],
    "sg:phone":"+1 416 487 1146",
    "sg:postcode":"M4S 2B9",
    "sg:province":"ON",
    "sg:tags":[
        "agency",
        "bureau"
    ],
    "wof:name":"G G Travel Agency Ltd",
    "wof:placetype":"venue"
},
  "geometry": {"coordinates":[-79.398117,43.704601],"type":"Point"}
}