{
  "type": "Feature",
  "properties": {
    "addr:full":"20 Willow Dr Brantford ON N3R 2W4",
    "addr:housenumber":"20",
    "addr:postcode":"n3r 2w4",
    "addr:street":"Willow Dr",
    "iso:country":"CA",
    "sg:address":"20 Willow Dr",
    "sg:city":"Brantford",
    "sg:classifiers":[
        {
            "category":"Wholesale",
            "subcategory":"Office Equipment",
            "type":"Manufacturing & Wholesale Goods"
        }
    ],
    "sg:phone":"+1 519 753 9282",
    "sg:postcode":"N3R 2W4",
    "sg:province":"ON",
    "sg:tags":[
        "accounting",
        "bookkeeping",
        "system"
    ],
    "wof:name":"C P Business Svc",
    "wof:placetype":"venue"
},
  "geometry": {"coordinates":[-80.271255,43.167374],"type":"Point"}
}