{
  "type": "Feature",
  "properties": {
    "addr:full":"St Catharines ON L2R 2Z4",
    "addr:postcode":"l2r 2z4",
    "iso:country":"CA",
    "sg:city":"St Catharines",
    "sg:classifiers":[
        {
            "category":"Health Services",
            "subcategory":"Health Practitioner",
            "type":"Services"
        }
    ],
    "sg:phone":"+1 905 641 2775",
    "sg:postcode":"L2R 2Z4",
    "sg:province":"ON",
    "sg:tags":[
        "psychologist"
    ],
    "wof:name":"Mac Niven, Elaine PhD",
    "wof:placetype":"venue"
},
  "geometry": {"coordinates":[-79.23326900000001,43.163361],"type":"Point"}
}