{
  "type": "Feature",
  "properties": {
    "addr:full":"355 Hespeler Rd # 340 Cambridge ON N1R 6B3",
    "addr:housenumber":"355",
    "addr:postcode":"n1r 6b3",
    "addr:street":"Hespeler Rd # 340",
    "iso:country":"CA",
    "sg:address":"355 Hespeler Rd # 340",
    "sg:city":"Cambridge",
    "sg:classifiers":[
        {
            "category":"Shopping",
            "subcategory":"Clothing, Apparel, & Fashions",
            "type":"Retail Goods"
        }
    ],
    "sg:phone":"+1 519 620 0860",
    "sg:postcode":"N1R 6B3",
    "sg:province":"ON",
    "sg:tags":[
        "furnishing"
    ],
    "wof:name":"Tip Top Tailors",
    "wof:placetype":"venue"
},
  "geometry": {"coordinates":[-80.32270050050001,43.3920707703],"type":"Point"}
}