{
  "type": "Feature",
  "properties": {
    "addr:full":"518 Musgrave Pl Prince Rupert BC V8J 3M1",
    "addr:housenumber":"518",
    "addr:postcode":"v8j 3m1",
    "addr:street":"Musgrave Pl",
    "iso:country":"CA",
    "sg:address":"518 Musgrave Pl",
    "sg:city":"Prince Rupert",
    "sg:classifiers":[
        {
            "category":"Government",
            "subcategory":"Office",
            "type":"Public Place"
        }
    ],
    "sg:phone":"+1 250 624 6380",
    "sg:postcode":"V8J 3M1",
    "sg:province":"BC",
    "sg:tags":[
        "village"
    ],
    "wof:name":"Prince Rupert Civic Pride Mgr",
    "wof:placetype":"venue"
},
  "geometry": {"coordinates":[-130.32562300000001,54.309338],"type":"Point"}
}