{
  "type": "Feature",
  "properties": {
    "addr:full":"Sooke BC V0S 1N0",
    "addr:postcode":"v0s 1n0",
    "iso:country":"CA",
    "sg:city":"Sooke",
    "sg:classifiers":[
        {
            "category":"Travel",
            "subcategory":"Hotels & Motels",
            "type":"Entertainment"
        }
    ],
    "sg:phone":"+1 250 646 2020",
    "sg:postcode":"V0S 1N0",
    "sg:province":"BC",
    "sg:tags":[
        "resort"
    ],
    "wof:name":"Point No Point Resort Ltd",
    "wof:placetype":"venue"
},
  "geometry": {"coordinates":[-123.72384599999999,48.377289],"type":"Point"}
}