{
  "type": "Feature",
  "properties": {
    "iso:country":"CA",
    "sg:address":"750 Cote Joyeuse",
    "sg:city":"Saint-Raymond",
    "sg:classifiers":[
        {
            "category":"Sports & Exercise",
            "subcategory":"Bowling",
            "type":"Entertainment"
        }
    ],
    "sg:phone":"+1 418 337 8090",
    "sg:postcode":"G3L 4B1",
    "sg:province":"QC",
    "sg:tags":[
        "center"
    ],
    "wof:name":"Salle DE Quilles St-Raymond",
    "wof:placetype":"venue"
},
  "geometry": {"coordinates":[-71.8345947266,46.8695602417],"type":"Point"}
}