{
  "type": "Feature",
  "properties": {
    "addr:full":"174 Queen St E St Marys ON N4X 1A4",
    "addr:housenumber":"174",
    "addr:postcode":"n4x 1a4",
    "addr:street":"Queen St E",
    "iso:country":"CA",
    "sg:address":"174 Queen St E",
    "sg:city":"St Marys",
    "sg:classifiers":[
        {
            "category":"Health Services",
            "subcategory":"Doctor",
            "type":"Services"
        }
    ],
    "sg:phone":"+1 519 284 1571",
    "sg:postcode":"N4X 1A4",
    "sg:province":"ON",
    "sg:tags":[
        "dentist"
    ],
    "wof:name":"Pellow, John E DDS",
    "wof:placetype":"venue"
},
  "geometry": {"coordinates":[-81.140869,43.259453],"type":"Point"}
}