{
  "type": "Feature",
  "properties": {
    "addr:full":"112 Market Ave Winnipeg MB R3B 0P4",
    "addr:housenumber":"112",
    "addr:postcode":"r3b 0p4",
    "addr:street":"Market Ave",
    "iso:country":"CA",
    "sg:address":"112 Market Ave",
    "sg:city":"Winnipeg",
    "sg:classifiers":[
        {
            "category":"Professional",
            "subcategory":"Detective & Security Services",
            "type":"Services"
        }
    ],
    "sg:phone":"+1 204 927 1200",
    "sg:postcode":"R3B 0P4",
    "sg:province":"MB",
    "sg:tags":[
        "guard",
        "patrol"
    ],
    "wof:name":"Obo",
    "wof:placetype":"venue"
},
  "geometry": {"coordinates":[-97.1357727051,49.8983650208],"type":"Point"}
}