{
  "type": "Feature",
  "properties": {
    "addr:full":"220 Royal Crest Crt Markham ON L3R 9Y2",
    "addr:housenumber":"220",
    "addr:postcode":"l3r 9y2",
    "addr:street":"Royal Crest Crt",
    "iso:country":"CA",
    "sg:address":"220 Royal Crest Crt",
    "sg:city":"Markham",
    "sg:classifiers":[
        {
            "category":"Professional",
            "subcategory":"Computer Services",
            "type":"Services"
        }
    ],
    "sg:phone":"+1 905 479 6525",
    "sg:postcode":"L3R 9Y2",
    "sg:province":"ON",
    "wof:name":"Piff Computer",
    "wof:placetype":"venue"
},
  "geometry": {"coordinates":[-79.32353973390001,43.8419380188],"type":"Point"}
}