{
  "type": "Feature",
  "properties": {
    "addr:full":"Saskatoon SK S7K 7H9",
    "addr:postcode":"s7k 7h9",
    "iso:country":"CA",
    "sg:city":"Saskatoon",
    "sg:classifiers":[
        {
            "category":"Health Services",
            "subcategory":"Chiropractor",
            "type":"Services"
        }
    ],
    "sg:phone":"+1 306 934 6066",
    "sg:postcode":"S7K 7H9",
    "sg:province":"SK",
    "wof:name":"Lenore Chiropractic Clinic",
    "wof:placetype":"venue"
},
  "geometry": {"coordinates":[-106.63516199999999,52.17289],"type":"Point"}
}