{
  "type": "Feature",
  "properties": {
    "addr:full":"441 10th St Brandon MB R7A 4G3",
    "addr:housenumber":"441",
    "addr:postcode":"r7a 4g3",
    "addr:street":"10Th St",
    "iso:country":"CA",
    "sg:address":"441 10th St",
    "sg:city":"Brandon",
    "sg:classifiers":[
        {
            "category":"Autos & Motor Vehicles",
            "subcategory":"Automobile Sales",
            "type":"Retail Goods"
        }
    ],
    "sg:phone":"+1 204 571 5455",
    "sg:postcode":"R7A 4G3",
    "sg:province":"MB",
    "sg:tags":[
        "car",
        "dealer"
    ],
    "wof:name":"J & J Auto Sales",
    "wof:placetype":"venue"
},
  "geometry": {"coordinates":[-99.951302,49.843147],"type":"Point"}
}