{
  "type": "Feature",
  "properties": {
    "addr:full":"386 Market Ave Grand Forks BC V0H 1H0",
    "addr:housenumber":"386",
    "addr:postcode":"v0h 1h0",
    "addr:street":"Market Ave",
    "iso:country":"CA",
    "sg:address":"386 Market Ave",
    "sg:city":"Grand Forks",
    "sg:classifiers":[
        {
            "category":"Insurance",
            "subcategory":"Insurance Agent",
            "type":"Services"
        }
    ],
    "sg:phone":"+1 250 442 2174",
    "sg:postcode":"V0H 1H0",
    "sg:province":"BC",
    "wof:name":"Dave Dale Insurance",
    "wof:placetype":"venue"
},
  "geometry": {"coordinates":[-118.43907900000001,49.031521],"type":"Point"}
}