{
  "type": "Feature",
  "properties": {
    "iso:country":"CA",
    "sg:address":"54 Rue Saint-Jean-Baptiste",
    "sg:city":"Baie-Saint-Paul",
    "sg:classifiers":[
        {
            "category":"Restaurant",
            "type":"Food & Drink"
        }
    ],
    "sg:phone":"+1 418 240 4949",
    "sg:postcode":"G3Z 1L9",
    "sg:province":"QC",
    "wof:name":"Joe Smoked Meat",
    "wof:placetype":"venue"
},
  "geometry": {"coordinates":[-70.50671386720001,47.4428062439],"type":"Point"}
}