{
  "type": "Feature",
  "properties": {
    "addr:full":"31278 Douglas St Yale BC V0K 2S0",
    "addr:housenumber":"31278",
    "addr:postcode":"v0k 2s0",
    "addr:street":"Douglas St",
    "iso:country":"CA",
    "sg:address":"31278 Douglas St",
    "sg:city":"Yale",
    "sg:classifiers":[
        {
            "category":"Travel",
            "subcategory":"Hotels & Motels",
            "type":"Entertainment"
        }
    ],
    "sg:phone":"+1 604 863 0055",
    "sg:postcode":"V0K 2S0",
    "sg:province":"BC",
    "sg:tags":[
        "breakfast",
        "accommodation",
        "bed"
    ],
    "wof:name":"Chrysalis Retreat",
    "wof:placetype":"venue"
},
  "geometry": {"coordinates":[-121.427757,49.561668],"type":"Point"}
}