{
  "type": "Feature",
  "properties": {
    "iso:country":"CA",
    "sg:address":"1370 Boul Monseigneur-Langlois",
    "sg:city":"Salaberry-DE-Valleyfield",
    "sg:classifiers":[
        {
            "category":"Restaurant",
            "type":"Food & Drink"
        }
    ],
    "sg:phone":"+1 450 371 9222",
    "sg:postcode":"J6S 1E3",
    "sg:province":"QC",
    "wof:name":"St-Hubert",
    "wof:placetype":"venue"
},
  "geometry": {"coordinates":[-74.1328201294,45.2704925537],"type":"Point"}
}