{
  "type": "Feature",
  "properties": {
    "addr:full":"Vernon BC V1T 5M6",
    "addr:postcode":"v1t 5m6",
    "iso:country":"CA",
    "sg:city":"Vernon",
    "sg:classifiers":[
        {
            "category":"Restaurant",
            "type":"Food & Drink"
        }
    ],
    "sg:phone":"+1 250 558 4646",
    "sg:postcode":"V1T 5M6",
    "sg:province":"BC",
    "wof:name":"Eclectic Med's Restaurant Inc",
    "wof:placetype":"venue"
},
  "geometry": {"coordinates":[-119.27359008800001,50.2647590637],"type":"Point"}
}