{
  "type": "Feature",
  "properties": {
    "iso:country":"CA",
    "sg:address":"36 Elizabeth Dr",
    "sg:city":"Gander",
    "sg:classifiers":[
        {
            "category":"Professional",
            "subcategory":"Business Services",
            "type":"Services"
        }
    ],
    "sg:phone":"+1 709 651 3777",
    "sg:postcode":"A1V 1G6",
    "sg:province":"NL",
    "sg:tags":[
        "attorney"
    ],
    "wof:name":"Jeffrey Keefe Law Offices",
    "wof:placetype":"venue"
},
  "geometry": {"coordinates":[-54.6043167114,48.9588432312],"type":"Point"}
}