{
  "type": "Feature",
  "properties": {
    "addr:full":"Highway 35 Minden ON K0M 2K0",
    "addr:postcode":"k0m 2k0",
    "addr:street":"Highway 35",
    "iso:country":"CA",
    "sg:address":"Highway 35",
    "sg:city":"Minden",
    "sg:classifiers":[
        {
            "category":"Government",
            "subcategory":"Police Station",
            "type":"Public Place"
        }
    ],
    "sg:phone":"+1 705 286 1431",
    "sg:postcode":"K0M 2K0",
    "sg:province":"ON",
    "sg:tags":[
        "department"
    ],
    "wof:name":"Ontario Provincial Police",
    "wof:placetype":"venue"
},
  "geometry": {"coordinates":[-78.7258987427,44.9261245728],"type":"Point"}
}