{
  "type": "Feature",
  "properties": {
    "addr:full":"439 Fairview Dr Brantford ON N3R 6X3",
    "addr:housenumber":"439",
    "addr:postcode":"n3r 6x3",
    "addr:street":"Fairview Dr",
    "iso:country":"CA",
    "sg:address":"439 Fairview Dr",
    "sg:city":"Brantford",
    "sg:classifiers":[
        {
            "category":"Retail",
            "subcategory":"Auto Repair",
            "type":"Services"
        }
    ],
    "sg:phone":"+1 519 756 4370",
    "sg:postcode":"N3R 6X3",
    "sg:province":"ON",
    "sg:tags":[
        "repairing",
        "automobile"
    ],
    "wof:name":"Midas Auto Svc Experts",
    "wof:placetype":"venue"
},
  "geometry": {"coordinates":[-80.24787902830001,43.1725616455],"type":"Point"}
}