{
  "type": "Feature",
  "properties": {
    "addr:full":"North York ON M2N 5R2",
    "addr:postcode":"m2n 5r2",
    "iso:country":"CA",
    "sg:city":"North York",
    "sg:classifiers":[
        {
            "category":"Real Estate",
            "subcategory":"Real Estate Agent",
            "type":"Services"
        }
    ],
    "sg:phone":"+1 416 225 2296",
    "sg:postcode":"M2N 5R2",
    "sg:province":"ON",
    "sg:tags":[
        "appraiser"
    ],
    "wof:name":"Mc Mahon & Assoc Ltd",
    "wof:placetype":"venue"
},
  "geometry": {"coordinates":[-79.413895,43.772541],"type":"Point"}
}