{
  "type": "Feature",
  "properties": {
    "addr:full":"2010 7th Ave # 5 Regina SK S4R 1C2",
    "addr:housenumber":"2010",
    "addr:postcode":"s4r 1c2",
    "addr:street":"7Th Ave # 5",
    "iso:country":"CA",
    "sg:address":"2010 7th Ave # 5",
    "sg:city":"Regina",
    "sg:classifiers":[
        {
            "category":"Banks & Credit Unions",
            "subcategory":"Financial Services",
            "type":"Services"
        }
    ],
    "sg:phone":"+1 306 525 9552",
    "sg:postcode":"S4R 1C2",
    "sg:province":"SK",
    "sg:tags":[
        "educational",
        "plan",
        "scholarship"
    ],
    "wof:name":"Canadian Scholarship Trust",
    "wof:placetype":"venue"
},
  "geometry": {"coordinates":[-104.609673,50.458492],"type":"Point"}
}