{
  "type": "Feature",
  "properties": {
    "iso:country":"CA",
    "sg:city":"Saint-Timothee",
    "sg:classifiers":[
        {
            "category":"Health Services",
            "subcategory":"Doctor",
            "type":"Services"
        }
    ],
    "sg:phone":"+1 450 373 3365",
    "sg:postcode":"J6S 5Y5",
    "sg:province":"QC",
    "sg:tags":[
        "physician",
        "surgeon"
    ],
    "wof:name":"Lareau, Ross MD",
    "wof:placetype":"venue"
},
  "geometry": {"coordinates":[-74.097229,45.268856],"type":"Point"}
}