{
  "type": "Feature",
  "properties": {
    "addr:full":"Hwy 1 E Richer MB R0E 1S0",
    "addr:postcode":"r0e 1s0",
    "addr:street":"Hwy 1 E Richer",
    "iso:country":"CA",
    "sg:address":"Hwy 1 E",
    "sg:city":"Richer",
    "sg:classifiers":[
        {
            "category":"Home & Garden",
            "subcategory":"Furniture",
            "type":"Retail Goods"
        }
    ],
    "sg:phone":"+1 204 422 8809",
    "sg:postcode":"R0E 1S0",
    "sg:province":"MB",
    "sg:tags":[
        "paint"
    ],
    "wof:name":"Geppetto's",
    "wof:placetype":"venue"
},
  "geometry": {"coordinates":[-96.456802,49.656384],"type":"Point"}
}