{
  "type": "Feature",
  "properties": {
    "addr:full":"Macamic QC J0Z 2S0",
    "addr:postcode":"j0z 2s0",
    "iso:country":"CA",
    "sg:city":"Macamic",
    "sg:classifiers":[
        {
            "category":"Autos & Motor Vehicles",
            "subcategory":"Automobile Sales",
            "type":"Retail Goods"
        }
    ],
    "sg:phone":"+1 819 782 4646",
    "sg:postcode":"J0Z 2S0",
    "sg:province":"QC",
    "sg:tags":[
        "car",
        "dealer"
    ],
    "wof:name":"Contact Chevrolet Geo Olds Inc",
    "wof:placetype":"venue"
},
  "geometry": {"coordinates":[-79.00655399999999,48.756538],"type":"Point"}
}