{
  "type": "Feature",
  "properties": {
    "addr:full":"20 Elliott St Cambridge ON N1R 2J2",
    "addr:housenumber":"20",
    "addr:postcode":"n1r 2j2",
    "addr:street":"Elliott St",
    "iso:country":"CA",
    "sg:address":"20 Elliott St",
    "sg:city":"Cambridge",
    "sg:classifiers":[
        {
            "category":"Health Services",
            "subcategory":"Nursing And Care Facility",
            "type":"Services"
        }
    ],
    "sg:phone":"+1 519 622 9147",
    "sg:postcode":"N1R 2J2",
    "sg:province":"ON",
    "sg:tags":[
        "home",
        "retirement",
        "community"
    ],
    "wof:name":"St James Place",
    "wof:placetype":"venue"
},
  "geometry": {"coordinates":[-80.3113861084,43.3528671265],"type":"Point"}
}