{
  "type": "Feature",
  "properties": {
    "addr:full":"1218 Ch DE Chambly Longueuil QC J4J 3W6",
    "addr:housenumber":"1218",
    "addr:postcode":"j4j 3w6",
    "addr:street":"Ch De Chambly",
    "iso:country":"CA",
    "sg:address":"1218 Ch DE Chambly",
    "sg:city":"Longueuil",
    "sg:classifiers":[
        {
            "category":"Shopping",
            "type":"Retail Goods"
        }
    ],
    "sg:phone":"+1 450 651 9802",
    "sg:postcode":"J4J 3W6",
    "sg:province":"QC",
    "sg:tags":[
        "material",
        "lamination",
        "artist",
        "supply"
    ],
    "wof:name":"Idee Fixe Laminages Inc",
    "wof:placetype":"venue"
},
  "geometry": {"coordinates":[-73.489639,45.53257],"type":"Point"}
}