{
  "type": "Feature",
  "properties": {
    "addr:full":"Calgary AB T2G 2S9",
    "addr:postcode":"t2g 2s9",
    "iso:country":"CA",
    "sg:city":"Calgary",
    "sg:classifiers":[
        {
            "category":"Manufacturing",
            "subcategory":"Printing",
            "type":"Manufacturing & Wholesale Goods"
        }
    ],
    "sg:phone":"+1 403 237 9327",
    "sg:postcode":"T2G 2S9",
    "sg:province":"AB",
    "sg:tags":[
        "photographer",
        "printer"
    ],
    "wof:name":"Csm Media Inc",
    "wof:placetype":"venue"
},
  "geometry": {"coordinates":[-114.055763,51.041012],"type":"Point"}
}