{
  "type": "Feature",
  "properties": {
    "addr:full":"544 St Vincent St Barrie ON L4M 7E8",
    "addr:housenumber":"544",
    "addr:postcode":"l4m 7e8",
    "addr:street":"St Vincent St",
    "iso:country":"CA",
    "sg:address":"544 St Vincent St",
    "sg:city":"Barrie",
    "sg:classifiers":[
        {
            "category":"Building & Trades",
            "subcategory":"Construction",
            "type":"Services"
        }
    ],
    "sg:phone":"+1 705 726 8362",
    "sg:postcode":"L4M 7E8",
    "sg:province":"ON",
    "sg:tags":[
        "water",
        "well",
        "drilling"
    ],
    "wof:name":"Mike Hammers Well Drilling",
    "wof:placetype":"venue"
},
  "geometry": {"coordinates":[-79.69454193120001,44.4177970886],"type":"Point"}
}