{
  "type": "Feature",
  "properties": {
    "iso:country":"CA",
    "sg:city":"Victoria",
    "sg:classifiers":[
        {
            "category":"Shopping",
            "subcategory":"Used Merchandise",
            "type":"Retail Goods"
        }
    ],
    "sg:phone":"+1 250 386 5978",
    "sg:postcode":"V8V 3X5",
    "sg:province":"BC",
    "sg:tags":[
        "antique"
    ],
    "wof:name":"Kay's Korner Experienced Goods",
    "wof:placetype":"venue"
},
  "geometry": {"coordinates":[-123.35623169,48.414806366],"type":"Point"}
}