{
  "type": "Feature",
  "properties": {
    "addr:full":"390 Coverdale Rd Riverview NB E1B 3J7",
    "addr:housenumber":"390",
    "addr:postcode":"e1b 3j7",
    "addr:street":"Coverdale Rd",
    "iso:country":"CA",
    "sg:address":"390 Coverdale Rd",
    "sg:city":"Riverview",
    "sg:classifiers":[
        {
            "category":"Restaurant",
            "type":"Food & Drink"
        }
    ],
    "sg:phone":"+1 506 387 8766",
    "sg:postcode":"E1B 3J7",
    "sg:province":"NB",
    "wof:name":"Four C's Dairy Bar",
    "wof:placetype":"venue"
},
  "geometry": {"coordinates":[-64.7976608276,46.0663909912],"type":"Point"}
}