{
  "type": "Feature",
  "properties": {
    "addr:full":"Toronto ON M4W 1A8",
    "addr:postcode":"m4w 1a8",
    "iso:country":"CA",
    "sg:city":"Toronto",
    "sg:classifiers":[
        {
            "category":"Shopping",
            "subcategory":"Jewelry",
            "type":"Retail Goods"
        }
    ],
    "sg:phone":"+1 416 925 6426",
    "sg:postcode":"M4W 1A8",
    "sg:province":"ON",
    "sg:tags":[
        "jeweler"
    ],
    "wof:name":"Ardene Holdings Inc",
    "wof:placetype":"venue"
},
  "geometry": {"coordinates":[-79.38665008540001,43.6703338623],"type":"Point"}
}