{
  "type": "Feature",
  "properties": {
    "addr:full":"79 Weir Cres Scarborough ON M1E 3B2",
    "addr:housenumber":"79",
    "addr:postcode":"m1e 3b2",
    "addr:street":"Weir Cres",
    "iso:country":"CA",
    "sg:address":"79 Weir Cres",
    "sg:city":"Scarborough",
    "sg:classifiers":[
        {
            "category":"Freight",
            "type":"Transportation"
        }
    ],
    "sg:phone":"+1 416 282 2266",
    "sg:postcode":"M1E 3B2",
    "sg:province":"ON",
    "sg:tags":[
        "consultant",
        "customs"
    ],
    "wof:name":"O'Hearn Logistics",
    "wof:placetype":"venue"
},
  "geometry": {"coordinates":[-79.19293999999999,43.775497],"type":"Point"}
}