{
  "type": "Feature",
  "properties": {
    "addr:full":"7912 125 Ave NW Edmonton AB T5B 1E5",
    "addr:housenumber":"7912",
    "addr:postcode":"t5b 1e5",
    "addr:street":"125 Ave Nw",
    "iso:country":"CA",
    "sg:address":"7912 125 Ave NW",
    "sg:city":"Edmonton",
    "sg:classifiers":[
        {
            "category":"Building & Trades",
            "subcategory":"Cleaning & Sanitation",
            "type":"Services"
        }
    ],
    "sg:phone":"+1 780 477 5566",
    "sg:postcode":"T5B 1E5",
    "sg:province":"AB",
    "sg:tags":[
        "janitor"
    ],
    "wof:name":"Stm Cleaning",
    "wof:placetype":"venue"
},
  "geometry": {"coordinates":[-113.46219635,53.581615448],"type":"Point"}
}