{
  "type": "Feature",
  "properties": {
    "addr:full":"Zurich ON N0M 2T0",
    "addr:postcode":"n0m 2t0",
    "iso:country":"CA",
    "sg:city":"Zurich",
    "sg:classifiers":[
        {
            "category":"Building & Trades",
            "subcategory":"Construction",
            "type":"Services"
        }
    ],
    "sg:phone":"+1 519 236 4441",
    "sg:postcode":"N0M 2T0",
    "sg:province":"ON",
    "sg:tags":[
        "contractor"
    ],
    "wof:name":"Jeffrey Brothers Ltd",
    "wof:placetype":"venue"
},
  "geometry": {"coordinates":[-81.6251525879,43.4211349487],"type":"Point"}
}