{
  "type": "Feature",
  "properties": {
    "addr:full":"500 Indian Creek Rd W Chatham ON N7M 5J5",
    "addr:housenumber":"500",
    "addr:postcode":"n7m 5j5",
    "addr:street":"Indian Creek Rd W",
    "iso:country":"CA",
    "sg:address":"500 Indian Creek Rd W",
    "sg:city":"Chatham",
    "sg:classifiers":[
        {
            "category":"Organizations",
            "subcategory":"Religious Organization",
            "type":"Services"
        }
    ],
    "sg:phone":"+1 519 351 2004",
    "sg:postcode":"N7M 5J5",
    "sg:province":"ON",
    "sg:tags":[
        "church"
    ],
    "wof:name":"Maple City Baptist Church",
    "wof:placetype":"venue"
},
  "geometry": {"coordinates":[-82.1800079346,42.3774719238],"type":"Point"}
}