{
  "type": "Feature",
  "properties": {
    "iso:country":"CA",
    "sg:city":"Guelph",
    "sg:classifiers":[
        {
            "category":"Building & Trades",
            "subcategory":"Construction",
            "type":"Services"
        }
    ],
    "sg:phone":"+1 519 763 5223",
    "sg:postcode":"N1E 5G6",
    "sg:province":"ON",
    "sg:tags":[
        "general",
        "contractor"
    ],
    "wof:name":"Mdma Inc",
    "wof:placetype":"venue"
},
  "geometry": {"coordinates":[-80.231476,43.55751],"type":"Point"}
}