{
  "type": "Feature",
  "properties": {
    "addr:full":"Abbotsford BC V2T 6S3",
    "addr:postcode":"v2t 6s3",
    "iso:country":"CA",
    "sg:city":"Abbotsford",
    "sg:classifiers":[
        {
            "category":"Shopping",
            "subcategory":"Pharmacy",
            "type":"Retail Goods"
        }
    ],
    "sg:phone":"+1 604 859 3300",
    "sg:postcode":"V2T 6S3",
    "sg:province":"BC",
    "wof:name":"Garden Park Pharmacy",
    "wof:placetype":"venue"
},
  "geometry": {"coordinates":[-122.33808136,49.0533599854],"type":"Point"}
}