{
  "type": "Feature",
  "properties": {
    "addr:full":"8257 Oak St Vancouver BC V6P 4A8",
    "addr:housenumber":"8257",
    "addr:postcode":"v6p 4a8",
    "addr:street":"Oak St",
    "iso:country":"CA",
    "sg:address":"8257 Oak St",
    "sg:city":"Vancouver",
    "sg:classifiers":[
        {
            "category":"Personal",
            "subcategory":"Beauty Salon",
            "type":"Services"
        }
    ],
    "sg:phone":"+1 604 266 2848",
    "sg:postcode":"V6P 4A8",
    "sg:province":"BC",
    "wof:name":"Happy Scissors",
    "wof:placetype":"venue"
},
  "geometry": {"coordinates":[-123.130371,49.211262],"type":"Point"}
}