{
  "type": "Feature",
  "properties": {
    "addr:full":"34677 7th Ave Abbotsford BC V2S 8C4",
    "addr:housenumber":"34677",
    "addr:postcode":"v2s 8c4",
    "addr:street":"7Th Ave",
    "iso:country":"CA",
    "sg:address":"34677 7th Ave",
    "sg:city":"Abbotsford",
    "sg:classifiers":[
        {
            "category":"Building & Trades",
            "subcategory":"Construction",
            "type":"Services"
        }
    ],
    "sg:phone":"+1 604 852 8571",
    "sg:postcode":"V2S 8C4",
    "sg:province":"BC",
    "sg:tags":[
        "general",
        "contractor"
    ],
    "wof:name":"Vriend Painting Inc",
    "wof:placetype":"venue"
},
  "geometry": {"coordinates":[-122.263595581,49.0089149475],"type":"Point"}
}