{
  "type": "Feature",
  "properties": {
    "addr:full":"24 Rue Trahan Pierreville QC J0G 1J0",
    "addr:housenumber":"24",
    "addr:postcode":"j0g 1j0",
    "addr:street":"Rue Trahan",
    "iso:country":"CA",
    "sg:address":"24 Rue Trahan",
    "sg:city":"Pierreville",
    "sg:classifiers":[
        {
            "category":"Social Services",
            "type":"Services"
        }
    ],
    "sg:phone":"+1 450 568 7444",
    "sg:postcode":"J0G 1J0",
    "sg:province":"QC",
    "sg:tags":[
        "organization",
        "welfare"
    ],
    "wof:name":"Mere-Veille Bas St-Francois",
    "wof:placetype":"venue"
},
  "geometry": {"coordinates":[-72.8110198975,46.0688285828],"type":"Point"}
}