{
  "type": "Feature",
  "properties": {
    "addr:full":"1690 Rue Poirier Saint-Laurent QC H4L 1J3",
    "addr:housenumber":"1690",
    "addr:postcode":"h4l 1j3",
    "addr:street":"Rue Poirier",
    "iso:country":"CA",
    "sg:address":"1690 Rue Poirier",
    "sg:city":"Saint-Laurent",
    "sg:classifiers":[
        {
            "category":"Shopping",
            "subcategory":"Jewelry",
            "type":"Retail Goods"
        }
    ],
    "sg:phone":"+1 514 747 3458",
    "sg:postcode":"H4L 1J3",
    "sg:province":"QC",
    "sg:tags":[
        "grocer"
    ],
    "wof:name":"Bijouterie Kim Say",
    "wof:placetype":"venue"
},
  "geometry": {"coordinates":[-73.697433,45.519302],"type":"Point"}
}