{
  "type": "Feature",
  "properties": {
    "iso:country":"CA",
    "sg:address":"15 Hwy 105 N",
    "sg:city":"Ear Falls",
    "sg:classifiers":[
        {
            "category":"Museum",
            "type":"Entertainment"
        }
    ],
    "sg:phone":"+1 807 222 3198",
    "sg:postcode":"P0V 1T0",
    "sg:province":"ON",
    "sg:tags":[
        "government"
    ],
    "wof:name":"Ear Falls Museum",
    "wof:placetype":"venue"
},
  "geometry": {"coordinates":[-93.4247207642,50.787021637],"type":"Point"}
}