{
  "type": "Feature",
  "properties": {
    "addr:full":"1216 Upper Wentworth St # 2 Hamilton ON L9A 4W2",
    "addr:housenumber":"1216",
    "addr:postcode":"l9a 4w2",
    "addr:street":"Upper Wentworth St # 2",
    "iso:country":"CA",
    "sg:address":"1216 Upper Wentworth St # 2",
    "sg:city":"Hamilton",
    "sg:classifiers":[
        {
            "category":"Social Services",
            "type":"Services"
        }
    ],
    "sg:phone":"+1 905 388 8728",
    "sg:postcode":"L9A 4W2",
    "sg:province":"ON",
    "sg:tags":[
        "counselor",
        "marriage",
        "family"
    ],
    "wof:name":"Brown, Carlton",
    "wof:placetype":"venue"
},
  "geometry": {"coordinates":[-79.867729,43.210247],"type":"Point"}
}