{
  "type": "Feature",
  "properties": {
    "iso:country":"CA",
    "sg:address":"32 Previn Crt",
    "sg:city":"Alliston",
    "sg:classifiers":[
        {
            "category":"Wholesale",
            "subcategory":"Non-durable Goods",
            "type":"Manufacturing & Wholesale Goods"
        }
    ],
    "sg:phone":"+1 705 435 2049",
    "sg:postcode":"L9R 1N8",
    "sg:province":"ON",
    "sg:tags":[
        "advertising"
    ],
    "wof:name":"Sterling Silver Promotions",
    "wof:placetype":"venue"
},
  "geometry": {"coordinates":[-79.877876,44.157566],"type":"Point"}
}