{
  "type": "Feature",
  "properties": {
    "iso:country":"CA",
    "sg:address":"2714 Rue Lapierre",
    "sg:city":"Lasalle",
    "sg:classifiers":[
        {
            "category":"Building & Trades",
            "subcategory":"Construction",
            "type":"Services"
        }
    ],
    "sg:phone":"+1 514 363 0863",
    "sg:postcode":"H8N 2W9",
    "sg:province":"QC",
    "sg:tags":[
        "concrete",
        "contractor"
    ],
    "wof:name":"Martellani & Brunet CO Ltd",
    "wof:placetype":"venue"
},
  "geometry": {"coordinates":[-73.6314315796,45.443447113],"type":"Point"}
}