{
  "type": "Feature",
  "properties": {
    "addr:full":"23 Rue Principale E Cookshire QC J0B 1M0",
    "addr:housenumber":"23",
    "addr:postcode":"j0b 1m0",
    "addr:street":"Rue Principale E Cookshire",
    "iso:country":"CA",
    "sg:address":"23 Rue Principale E",
    "sg:city":"Cookshire",
    "sg:classifiers":[
        {
            "category":"Bars & Pubs",
            "type":"Food & Drink"
        }
    ],
    "sg:phone":"+1 819 875 1694",
    "sg:postcode":"J0B 1M0",
    "sg:province":"QC",
    "sg:tags":[
        "lounge",
        "cocktail"
    ],
    "wof:name":"Bar Centre-Ville",
    "wof:placetype":"venue"
},
  "geometry": {"coordinates":[-71.628708,45.41264],"type":"Point"}
}