{
  "type": "Feature",
  "properties": {
    "addr:full":"3115 Stanford St Halifax NS B3L 4C9",
    "addr:housenumber":"3115",
    "addr:postcode":"b3l 4c9",
    "addr:street":"Stanford St",
    "iso:country":"CA",
    "sg:address":"3115 Stanford St",
    "sg:city":"Halifax",
    "sg:classifiers":[
        {
            "category":"Building & Trades",
            "subcategory":"Construction",
            "type":"Services"
        }
    ],
    "sg:phone":"+1 902 455 3181",
    "sg:postcode":"B3L 4C9",
    "sg:province":"NS",
    "sg:tags":[
        "roofing",
        "contractor"
    ],
    "wof:name":"Don & Son Contracting",
    "wof:placetype":"venue"
},
  "geometry": {"coordinates":[-63.6288414001,44.649143219],"type":"Point"}
}