{
  "type": "Feature",
  "properties": {
    "addr:full":"318 169 Rte Albanel QC G8M 3N8",
    "addr:housenumber":"169",
    "addr:postcode":"g8m 3n8",
    "addr:street":"Rte Albanel",
    "iso:country":"CA",
    "sg:address":"318 169 Rte",
    "sg:city":"Albanel",
    "sg:classifiers":[
        {
            "category":"Utilities",
            "subcategory":"Refuse",
            "type":"Services"
        }
    ],
    "sg:phone":"+1 418 276 5883",
    "sg:postcode":"G8M 3N8",
    "sg:province":"QC",
    "sg:tags":[
        "garbage",
        "collection"
    ],
    "wof:name":"Container M & M Inc",
    "wof:placetype":"venue"
},
  "geometry": {"coordinates":[-72.441185,48.88382],"type":"Point"}
}