{
  "type": "Feature",
  "properties": {
    "addr:full":"8 C 11 Powassan ON P0H 1Z0",
    "addr:housenumber":"8 c 11",
    "addr:postcode":"p0h 1z0",
    "iso:country":"CA",
    "sg:address":"8 C 11",
    "sg:city":"Powassan",
    "sg:classifiers":[
        {
            "category":"Travel",
            "subcategory":"Campground",
            "type":"Entertainment"
        }
    ],
    "sg:phone":"+1 705 724 1717",
    "sg:postcode":"P0H 1Z0",
    "sg:province":"ON",
    "sg:tags":[
        "camp",
        "fishing"
    ],
    "wof:name":"Ice Bungalows",
    "wof:placetype":"venue"
},
  "geometry": {"coordinates":[-79.364059,46.082016],"type":"Point"}
}