{
  "type": "Feature",
  "properties": {
    "addr:full":"1 Woodborough Ave York ON M6M 5A1",
    "addr:housenumber":"1",
    "addr:postcode":"m6m 5a1",
    "addr:street":"Woodborough Ave",
    "iso:country":"CA",
    "sg:address":"1 Woodborough Ave",
    "sg:city":"York",
    "sg:classifiers":[
        {
            "category":"Shopping",
            "subcategory":"Computers & Home Electronics",
            "type":"Retail Goods"
        }
    ],
    "sg:phone":"+1 416 657 8548",
    "sg:postcode":"M6M 5A1",
    "sg:province":"ON",
    "sg:tags":[
        "software"
    ],
    "wof:name":"Microforum Italia Spa",
    "wof:placetype":"venue"
},
  "geometry": {"coordinates":[-79.466385,43.695248],"type":"Point"}
}