{
  "type": "Feature",
  "properties": {
    "addr:full":"5600 Timberlea Blvd Mississauga ON L4W 4M6",
    "addr:housenumber":"5600",
    "addr:postcode":"l4w 4m6",
    "addr:street":"Timberlea Blvd",
    "iso:country":"CA",
    "sg:address":"5600 Timberlea Blvd",
    "sg:city":"Mississauga",
    "sg:classifiers":[
        {
            "category":"Wholesale",
            "subcategory":"Electrical",
            "type":"Manufacturing & Wholesale Goods"
        }
    ],
    "sg:phone":"+1 905 624 8516",
    "sg:postcode":"L4W 4M6",
    "sg:province":"ON",
    "sg:tags":[
        "equipment",
        "electronic",
        "supply"
    ],
    "wof:name":"Global Electronic Supplies",
    "wof:placetype":"venue"
},
  "geometry": {"coordinates":[-79.65016900000001,43.636074],"type":"Point"}
}