{
  "type": "Feature",
  "properties": {
    "addr:full":"1880 Assumption St Windsor ON N8Y 1C4",
    "addr:housenumber":"1880",
    "addr:postcode":"n8y 1c4",
    "addr:street":"Assumption St",
    "iso:country":"CA",
    "sg:address":"1880 Assumption St",
    "sg:city":"Windsor",
    "sg:classifiers":[
        {
            "category":"Professional",
            "subcategory":"Engineering",
            "type":"Services"
        }
    ],
    "sg:phone":"+1 519 977 6800",
    "sg:postcode":"N8Y 1C4",
    "sg:province":"ON",
    "sg:tags":[
        "engineer"
    ],
    "wof:name":"D C Mc Closkey Engineering",
    "wof:placetype":"venue"
},
  "geometry": {"coordinates":[-83.014397,42.324135],"type":"Point"}
}