{
  "type": "Feature",
  "properties": {
    "addr:full":"66 St Anne's Rd Winnipeg MB R2M 2Y5",
    "addr:housenumber":"66",
    "addr:postcode":"r2m 2y5",
    "addr:street":"St Anne'S Rd",
    "iso:country":"CA",
    "sg:address":"66 St Anne's Rd",
    "sg:city":"Winnipeg",
    "sg:classifiers":[
        {
            "category":"Professional",
            "subcategory":"Lawyer & Legal Services",
            "type":"Services"
        }
    ],
    "sg:phone":"+1 204 982 2050",
    "sg:postcode":"R2M 2Y5",
    "sg:province":"MB",
    "sg:tags":[
        "attorney"
    ],
    "wof:name":"Grant Clay Law Office",
    "wof:placetype":"venue"
},
  "geometry": {"coordinates":[-97.109421,49.861992],"type":"Point"}
}