{
  "type": "Feature",
  "properties": {
    "iso:country":"CA",
    "sg:address":"270 Gerrard St E",
    "sg:city":"Toronto",
    "sg:classifiers":[
        {
            "category":"Organizations",
            "subcategory":"Religious Organization",
            "type":"Services"
        }
    ],
    "sg:phone":"+1 416 929 9614",
    "sg:postcode":"M5A 2G4",
    "sg:province":"ON",
    "wof:name":"Yonge Street Mission",
    "wof:placetype":"venue"
},
  "geometry": {"coordinates":[-79.368477,43.662056],"type":"Point"}
}