{
  "type": "Feature",
  "properties": {
    "addr:full":"270 Gerrard St E Toronto ON M5A 2G4",
    "addr:housenumber":"270",
    "addr:postcode":"m5a 2g4",
    "addr:street":"Gerrard St E",
    "iso:country":"CA",
    "sg:address":"270 Gerrard St E",
    "sg:city":"Toronto",
    "sg:classifiers":[
        {
            "category":"Organizations",
            "subcategory":"Religious Organization",
            "type":"Services"
        }
    ],
    "sg:phone":"+1 416 929 9614",
    "sg:postcode":"M5A 2G4",
    "sg:province":"ON",
    "wof:name":"Yonge Street Mission",
    "wof:placetype":"venue"
},
  "geometry": {"coordinates":[-79.368477,43.662056],"type":"Point"}
}