{
  "type": "Feature",
  "properties": {
    "iso:country":"CA",
    "sg:city":"Orillia",
    "sg:classifiers":[
        {
            "category":"Shopping",
            "subcategory":"Pharmacy",
            "type":"Retail Goods"
        }
    ],
    "sg:phone":"+1 705 325 5555",
    "sg:postcode":"L3V 5S2",
    "sg:province":"ON",
    "wof:name":"Orillia Pharmacy Ltd",
    "wof:placetype":"venue"
},
  "geometry": {"coordinates":[-79.418228,44.60659],"type":"Point"}
}