{
  "type": "Feature",
  "properties": {
    "addr:full":"2784 Rue Notre-Dame Saint-Hyacinthe QC J2S 2R6",
    "addr:housenumber":"2784",
    "addr:postcode":"j2s 2r6",
    "addr:street":"Rue Notre-Dame",
    "iso:country":"CA",
    "sg:address":"2784 Rue Notre-Dame",
    "sg:city":"Saint-Hyacinthe",
    "sg:classifiers":[
        {
            "category":"Building & Trades",
            "subcategory":"Pest Control",
            "type":"Services"
        }
    ],
    "sg:phone":"+1 450 773 1800",
    "sg:postcode":"J2S 2R6",
    "sg:province":"QC",
    "wof:name":"Agro-Alimentaire Techno Cntrle",
    "wof:placetype":"venue"
},
  "geometry": {"coordinates":[-72.957862854,45.6203918457],"type":"Point"}
}