{
  "type": "Feature",
  "properties": {
    "addr:full":"220 Royal Crest Crt Markham ON L3R 9Y2",
    "addr:housenumber":"220",
    "addr:postcode":"l3r 9y2",
    "addr:street":"Royal Crest Crt",
    "iso:country":"CA",
    "sg:address":"220 Royal Crest Crt",
    "sg:city":"Markham",
    "sg:classifiers":[
        {
            "category":"Professional",
            "subcategory":"Advertising",
            "type":"Services"
        }
    ],
    "sg:phone":"+1 905 474 3144",
    "sg:postcode":"L3R 9Y2",
    "sg:province":"ON",
    "sg:tags":[
        "designer",
        "display",
        "producer"
    ],
    "wof:name":"Interface Exhibits Inc",
    "wof:placetype":"venue"
},
  "geometry": {"coordinates":[-79.32353999999999,43.841938],"type":"Point"}
}