{
  "type": "Feature",
  "properties": {
    "addr:full":"271 Main St Antigonish NS B2G 2C3",
    "addr:housenumber":"271",
    "addr:postcode":"b2g 2c3",
    "addr:street":"Main St",
    "iso:country":"CA",
    "sg:address":"271 Main St",
    "sg:city":"Antigonish",
    "sg:classifiers":[
        {
            "category":"Shopping",
            "subcategory":"Clothing, Apparel, & Fashions",
            "type":"Retail Goods"
        }
    ],
    "sg:phone":"+1 902 863 4246",
    "sg:postcode":"B2G 2C3",
    "sg:province":"NS",
    "sg:tags":[
        "furnishing"
    ],
    "wof:name":"Oak Manor Men's Wear Ltd",
    "wof:placetype":"venue"
},
  "geometry": {"coordinates":[-61.9918708801,45.622341156],"type":"Point"}
}