{
  "type": "Feature",
  "properties": {
    "addr:full":"2845 Acacia Dr Victoria BC V9B 5A2",
    "addr:housenumber":"2845",
    "addr:postcode":"v9b 5a2",
    "addr:street":"Acacia Dr",
    "iso:country":"CA",
    "sg:address":"2845 Acacia Dr",
    "sg:city":"Victoria",
    "sg:classifiers":[
        {
            "category":"Building & Trades",
            "subcategory":"Construction",
            "type":"Services"
        }
    ],
    "sg:phone":"+1 250 474 2942",
    "sg:postcode":"V9B 5A2",
    "sg:province":"BC",
    "sg:tags":[
        "resurfacing",
        "laying",
        "refinishing",
        "floor"
    ],
    "wof:name":"S & I Hardwood Floors",
    "wof:placetype":"venue"
},
  "geometry": {"coordinates":[-123.36451700000001,48.428314],"type":"Point"}
}