{
  "type": "Feature",
  "properties": {
    "iso:country":"CA",
    "sg:address":"1076 Boul Vachon N # 602",
    "sg:city":"Sainte-Marie",
    "sg:classifiers":[
        {
            "category":"Manufacturing",
            "subcategory":"Printing",
            "type":"Manufacturing & Wholesale Goods"
        }
    ],
    "sg:phone":"+1 418 387 5250",
    "sg:postcode":"G6E 3P5",
    "sg:province":"QC",
    "sg:tags":[
        "printer",
        "duplicating",
        "copying"
    ],
    "wof:name":"Copie Extra",
    "wof:placetype":"venue"
},
  "geometry": {"coordinates":[-71.03536200000001,46.454197],"type":"Point"}
}