{
  "type": "Feature",
  "properties": {
    "addr:full":"595 Bay St Toronto ON M5G 2C2",
    "addr:housenumber":"595",
    "addr:postcode":"m5g 2c2",
    "addr:street":"Bay St",
    "iso:country":"CA",
    "sg:address":"595 Bay St",
    "sg:city":"Toronto",
    "sg:classifiers":[
        {
            "category":"Restaurant",
            "type":"Food & Drink"
        }
    ],
    "sg:phone":"+1 416 598 2510",
    "sg:postcode":"M5G 2C2",
    "sg:province":"ON",
    "sg:tags":[
        "cafe"
    ],
    "wof:name":"Croissant Tree",
    "wof:placetype":"venue"
},
  "geometry": {"coordinates":[-79.38372039790001,43.6561431885],"type":"Point"}
}