{
  "type": "Feature",
  "properties": {
    "addr:full":"840 Rue Bombardier Mascouche QC J7K 1X9",
    "addr:housenumber":"840",
    "addr:postcode":"j7k 1x9",
    "addr:street":"Rue Bombardier",
    "iso:country":"CA",
    "sg:address":"840 Rue Bombardier",
    "sg:city":"Mascouche",
    "sg:classifiers":[
        {
            "category":"Bus Charters",
            "type":"Transportation"
        }
    ],
    "sg:phone":"+1 450 474 3284",
    "sg:postcode":"J7K 1X9",
    "sg:province":"QC",
    "sg:tags":[
        "rental"
    ],
    "wof:name":"Autobus Lachapelle Inc",
    "wof:placetype":"venue"
},
  "geometry": {"coordinates":[-73.59271200000001,45.739086],"type":"Point"}
}