{
  "type": "Feature",
  "properties": {
    "iso:country":"CA",
    "sg:address":"485 Des Bosquets",
    "sg:city":"Sainte-Marie-DE-Blandford",
    "sg:classifiers":[
        {
            "category":"Government",
            "subcategory":"Office",
            "type":"Public Place"
        }
    ],
    "sg:phone":"+1 819 283 2127",
    "sg:postcode":"G0X 2W0",
    "sg:province":"QC",
    "sg:tags":[
        "village"
    ],
    "wof:name":"Ste-Marie-DE-Blandford Mncplt",
    "wof:placetype":"venue"
},
  "geometry": {"coordinates":[-72.1418685913,46.3541793823],"type":"Point"}
}