{
  "type": "Feature",
  "properties": {
    "addr:full":"31 Boul Charest O Quebec QC G1K 1X1",
    "addr:housenumber":"31",
    "addr:postcode":"g1k 1x1",
    "addr:street":"Boul Charest O",
    "iso:country":"CA",
    "sg:address":"31 Boul Charest O",
    "sg:city":"Quebec",
    "sg:classifiers":[
        {
            "category":"Professional",
            "subcategory":"Art Services",
            "type":"Services"
        }
    ],
    "sg:phone":"+1 514 990 0312",
    "sg:postcode":"G1K 1X1",
    "sg:province":"QC",
    "sg:tags":[
        "graphic",
        "designer"
    ],
    "wof:name":"Tremblay & Litalien Inc",
    "wof:placetype":"venue"
},
  "geometry": {"coordinates":[-71.2300949097,46.8113746643],"type":"Point"}
}