{
  "type": "Feature",
  "properties": {
    "addr:full":"2655 Rue Saint-Pierre Drummondville QC J2C 7Y2",
    "addr:housenumber":"2655",
    "addr:postcode":"j2c 7y2",
    "addr:street":"Rue Saint-Pierre",
    "iso:country":"CA",
    "sg:address":"2655 Rue Saint-Pierre",
    "sg:city":"Drummondville",
    "sg:classifiers":[
        {
            "category":"Manufacturing",
            "subcategory":"Paper Products",
            "type":"Manufacturing & Wholesale Goods"
        }
    ],
    "sg:phone":"+1 819 472 7665",
    "sg:postcode":"J2C 7Y2",
    "sg:province":"QC",
    "sg:tags":[
        "box"
    ],
    "wof:name":"Recuperation Drummond Inc",
    "wof:placetype":"venue"
},
  "geometry": {"coordinates":[-72.52293400000001,45.8661],"type":"Point"}
}