{
  "type": "Feature",
  "properties": {
    "addr:full":"1085 Millar Creek Rd # 2 Whistler BC V0N 1B1",
    "addr:housenumber":"1085",
    "addr:postcode":"v0n 1b1",
    "addr:street":"Millar Creek Rd # 2",
    "iso:country":"CA",
    "sg:address":"1085 Millar Creek Rd # 2",
    "sg:city":"Whistler",
    "sg:classifiers":[
        {
            "category":"Autos & Motor Vehicles",
            "subcategory":"Auto Supplies",
            "type":"Retail Goods"
        }
    ],
    "sg:phone":"+1 604 932 8986",
    "sg:postcode":"V0N 1B1",
    "sg:province":"BC",
    "sg:tags":[
        "automobile",
        "parts"
    ],
    "wof:name":"Napa Auto Parts",
    "wof:placetype":"venue"
},
  "geometry": {"coordinates":[-123.041633606,50.0875701904],"type":"Point"}
}