{
  "type": "Feature",
  "properties": {
    "addr:full":"140 Victoria St Beaverton ON L0K 1A0",
    "addr:housenumber":"140",
    "addr:postcode":"l0k 1a0",
    "addr:street":"Victoria St",
    "iso:country":"CA",
    "sg:address":"140 Victoria St",
    "sg:city":"Beaverton",
    "sg:classifiers":[
        {
            "category":"Building & Trades",
            "subcategory":"Construction",
            "type":"Services"
        }
    ],
    "sg:phone":"+1 705 426 7498",
    "sg:postcode":"L0K 1A0",
    "sg:province":"ON",
    "sg:tags":[
        "excavating",
        "contractor"
    ],
    "wof:name":"Stephen Dawson Haulage",
    "wof:placetype":"venue"
},
  "geometry": {"coordinates":[-79.16115570069999,44.4336929321],"type":"Point"}
}