{
  "type": "Feature",
  "properties": {
    "addr:full":"730 Memorial Ave Thunder Bay ON P7B 3Z5",
    "addr:housenumber":"730",
    "addr:postcode":"p7b 3z5",
    "addr:street":"Memorial Ave",
    "iso:country":"CA",
    "sg:address":"730 Memorial Ave",
    "sg:city":"Thunder Bay",
    "sg:classifiers":[
        {
            "category":"Shopping",
            "subcategory":"Computers & Home Electronics",
            "type":"Retail Goods"
        }
    ],
    "sg:phone":"+1 807 343 2600",
    "sg:postcode":"P7B 3Z5",
    "sg:province":"ON",
    "sg:tags":[
        "high",
        "equipment",
        "fidelity",
        "stereophonic",
        "satellite"
    ],
    "wof:name":"Bay City Sound & Vision",
    "wof:placetype":"venue"
},
  "geometry": {"coordinates":[-89.2434921265,48.4141387939],"type":"Point"}
}