{
  "type": "Feature",
  "properties": {
    "addr:full":"3209 Devon Dr Windsor ON N8X 4L5",
    "addr:housenumber":"3209",
    "addr:postcode":"n8x 4l5",
    "addr:street":"Devon Dr",
    "iso:country":"CA",
    "sg:address":"3209 Devon Dr",
    "sg:city":"Windsor",
    "sg:classifiers":[
        {
            "category":"Manufacturing",
            "subcategory":"Metals",
            "type":"Manufacturing & Wholesale Goods"
        }
    ],
    "sg:phone":"+1 519 966 0760",
    "sg:postcode":"N8X 4L5",
    "sg:province":"ON",
    "sg:tags":[
        "steel"
    ],
    "wof:name":"Border Steel Ltd",
    "wof:placetype":"venue"
},
  "geometry": {"coordinates":[-82.99488100000001,42.274559],"type":"Point"}
}