{
  "type": "Feature",
  "properties": {
    "addr:full":"355 Hespeler Rd # Vru206 Cambridge ON N1R 6B3",
    "addr:housenumber":"355",
    "addr:postcode":"n1r 6b3",
    "addr:street":"Hespeler Rd # Vru206",
    "iso:country":"CA",
    "sg:address":"355 Hespeler Rd # Vru206",
    "sg:city":"Cambridge",
    "sg:classifiers":[
        {
            "category":"Shopping",
            "subcategory":"Bicycles & Sporting Goods",
            "type":"Retail Goods"
        }
    ],
    "sg:phone":"+1 519 623 0220",
    "sg:postcode":"N1R 6B3",
    "sg:province":"ON",
    "sg:tags":[
        "sportswear"
    ],
    "wof:name":"Most Wanted",
    "wof:placetype":"venue"
},
  "geometry": {"coordinates":[-80.32270050050001,43.3920707703],"type":"Point"}
}