{
  "type": "Feature",
  "properties": {
    "addr:full":"29 Hull Ave Winnipeg MB R2M 0Y9",
    "addr:housenumber":"29",
    "addr:postcode":"r2m 0y9",
    "addr:street":"Hull Ave",
    "iso:country":"CA",
    "sg:address":"29 Hull Ave",
    "sg:city":"Winnipeg",
    "sg:classifiers":[
        {
            "category":"Building & Trades",
            "subcategory":"Construction",
            "type":"Services"
        }
    ],
    "sg:phone":"+1 204 254 3348",
    "sg:postcode":"R2M 0Y9",
    "sg:province":"MB",
    "sg:tags":[
        "downspouts",
        "gutter"
    ],
    "wof:name":"Winnipeg Exteriors",
    "wof:placetype":"venue"
},
  "geometry": {"coordinates":[-97.110016,49.850243],"type":"Point"}
}