{
  "type": "Feature",
  "properties": {
    "iso:country":"CA",
    "sg:address":"270 Adelaide St S",
    "sg:city":"London",
    "sg:classifiers":[
        {
            "category":"Wholesale",
            "subcategory":"Machinery & Supplies",
            "type":"Manufacturing & Wholesale Goods"
        }
    ],
    "sg:phone":"+1 519 681 4880",
    "sg:postcode":"N5Z 3L1",
    "sg:province":"ON",
    "sg:tags":[
        "plate",
        "printing",
        "printer"
    ],
    "wof:name":"Colour Shop",
    "wof:placetype":"venue"
},
  "geometry": {"coordinates":[-81.21938323969999,42.9622154236],"type":"Point"}
}