{
  "type": "Feature",
  "properties": {
    "addr:full":"350 Main St N Russell MB R0J 1W0",
    "addr:housenumber":"350",
    "addr:postcode":"r0j 1w0",
    "addr:street":"Main St N",
    "iso:country":"CA",
    "sg:address":"350 Main St N",
    "sg:city":"Russell",
    "sg:classifiers":[
        {
            "category":"Shopping",
            "subcategory":"Catalog Store",
            "type":"Retail Goods"
        }
    ],
    "sg:phone":"+1 204 773 2192",
    "sg:postcode":"R0J 1W0",
    "sg:province":"MB",
    "sg:tags":[
        "mail",
        "order",
        "internet"
    ],
    "wof:name":"Sears Canada Inc",
    "wof:placetype":"venue"
},
  "geometry": {"coordinates":[-101.287597656,50.7819061279],"type":"Point"}
}