{
  "type": "Feature",
  "properties": {
    "addr:full":"479 Av Champlain Disraeli QC G0N 1E0",
    "addr:postcode":"g0n 1e0",
    "addr:street":"479 Av Champlain",
    "iso:country":"CA",
    "sg:address":"479 Av Champlain",
    "sg:city":"Disraeli",
    "sg:classifiers":[
        {
            "category":"Autos & Motor Vehicles",
            "subcategory":"Fuel & Gas Station",
            "type":"Retail Goods"
        }
    ],
    "sg:phone":"+1 418 449 4238",
    "sg:postcode":"G0N 1E0",
    "sg:province":"QC",
    "sg:tags":[
        "oil"
    ],
    "wof:name":"Shell Canada Ltd",
    "wof:placetype":"venue"
},
  "geometry": {"coordinates":[-71.3584442139,45.9008216858],"type":"Point"}
}