{
  "type": "Feature",
  "properties": {
    "addr:full":"1453 Henry Whitby ON L1N 5R7",
    "addr:housenumber":"1453",
    "addr:postcode":"l1n 5r7",
    "addr:street":"Henry",
    "iso:country":"CA",
    "sg:address":"1453 Henry",
    "sg:city":"Whitby",
    "sg:classifiers":[
        {
            "category":"Shopping",
            "type":"Retail Goods"
        }
    ],
    "sg:phone":"+1 905 668 4185",
    "sg:postcode":"L1N 5R7",
    "sg:province":"ON",
    "sg:tags":[
        "art",
        "gallery",
        "dealer"
    ],
    "wof:name":"Station Gallery",
    "wof:placetype":"venue"
},
  "geometry": {"coordinates":[-78.9396362305,43.8620529175],"type":"Point"}
}