{
  "type": "Feature",
  "properties": {
    "addr:full":"190 John St Moncton NB E1C 2H9",
    "addr:housenumber":"190",
    "addr:postcode":"e1c 2h9",
    "addr:street":"John St",
    "iso:country":"CA",
    "sg:address":"190 John St",
    "sg:city":"Moncton",
    "sg:classifiers":[
        {
            "category":"Autos & Motor Vehicles",
            "subcategory":"Auto Supplies",
            "type":"Retail Goods"
        }
    ],
    "sg:phone":"+1 506 853 0555",
    "sg:postcode":"E1C 2H9",
    "sg:province":"NB",
    "sg:tags":[
        "repairing",
        "automobile"
    ],
    "wof:name":"Tire Shack",
    "wof:placetype":"venue"
},
  "geometry": {"coordinates":[-64.792732,46.09309],"type":"Point"}
}