{
  "type": "Feature",
  "properties": {
    "addr:full":"1526 Ch DE LA Riviere-Aux-Outa Ormstown QC J0S 1K0",
    "addr:postcode":"1526;j0s 1k0",
    "addr:street":"Ch De La Riviere-Aux-Outa",
    "iso:country":"CA",
    "sg:address":"1526 Ch DE LA Riviere-Aux-Outa",
    "sg:city":"Ormstown",
    "sg:classifiers":[
        {
            "category":"Building & Trades",
            "subcategory":"Construction",
            "type":"Services"
        }
    ],
    "sg:phone":"+1 450 829 3802",
    "sg:postcode":"J0S 1K0",
    "sg:province":"QC",
    "sg:tags":[
        "contractor",
        "general"
    ],
    "wof:name":"Jacques Theoret Construction",
    "wof:placetype":"venue"
},
  "geometry": {"coordinates":[-74.000557,45.120293],"type":"Point"}
}