{
  "type": "Feature",
  "properties": {
    "addr:full":"136 2nd Ave S Saskatoon SK S7K 1K5",
    "addr:housenumber":"136",
    "addr:postcode":"s7k 1k5",
    "addr:street":"2Nd Ave S",
    "iso:country":"CA",
    "sg:address":"136 2nd Ave S",
    "sg:city":"Saskatoon",
    "sg:classifiers":[
        {
            "category":"Restaurant",
            "type":"Food & Drink"
        }
    ],
    "sg:phone":"+1 306 665 5959",
    "sg:postcode":"S7K 1K5",
    "sg:province":"SK",
    "wof:name":"Saskatoon Asian Restaurant",
    "wof:placetype":"venue"
},
  "geometry": {"coordinates":[-106.66394,52.128113],"type":"Point"}
}