{
  "type": "Feature",
  "properties": {
    "addr:full":"255 32E Rue Saint-Georges QC G5Y 4G8",
    "addr:housenumber":"255",
    "addr:postcode":"g5y 4g8",
    "addr:street":"32E Rue",
    "iso:country":"CA",
    "sg:address":"255 32E Rue",
    "sg:city":"Saint-Georges",
    "sg:classifiers":[
        {
            "category":"Retail",
            "subcategory":"Auto Repair",
            "type":"Services"
        }
    ],
    "sg:phone":"+1 418 228 5684",
    "sg:postcode":"G5Y 4G8",
    "sg:province":"QC",
    "sg:tags":[
        "repairing",
        "automobile"
    ],
    "wof:name":"Garage Claude Veilleux",
    "wof:placetype":"venue"
},
  "geometry": {"coordinates":[-70.67115020750001,46.1233482361],"type":"Point"}
}