{
  "type": "Feature",
  "properties": {
    "addr:full":"Sundre AB T0M 1X0",
    "addr:postcode":"t0m 1x0",
    "iso:country":"CA",
    "sg:city":"Sundre",
    "sg:classifiers":[
        {
            "category":"Food & Beverages",
            "subcategory":"Specialty",
            "type":"Retail Goods"
        }
    ],
    "sg:phone":"+1 403 638 3585",
    "sg:postcode":"T0M 1X0",
    "sg:province":"AB",
    "sg:tags":[
        "water",
        "bulk",
        "company"
    ],
    "wof:name":"Pro-Water Conditioning",
    "wof:placetype":"venue"
},
  "geometry": {"coordinates":[-114.639549,51.800144],"type":"Point"}
}