{
  "type": "Feature",
  "properties": {
    "addr:full":"360 Pleasant St Miramichi NB E1V 2N3",
    "addr:housenumber":"360",
    "addr:postcode":"e1v 2n3",
    "addr:street":"Pleasant St",
    "iso:country":"CA",
    "sg:address":"360 Pleasant St",
    "sg:city":"Miramichi",
    "sg:classifiers":[
        {
            "category":"Government",
            "subcategory":"Office",
            "type":"Public Place"
        }
    ],
    "sg:phone":"+1 506 627 4040",
    "sg:postcode":"E1V 2N3",
    "sg:province":"NB",
    "wof:name":"New Brunswick Svc Ctr",
    "wof:placetype":"venue"
},
  "geometry": {"coordinates":[-65.56531524659999,47.002658844],"type":"Point"}
}