{
  "type": "Feature",
  "properties": {
    "addr:full":"183 Palmerston St Southampton ON N0H 2L0",
    "addr:housenumber":"183",
    "addr:postcode":"n0h 2l0",
    "addr:street":"Palmerston St",
    "iso:country":"CA",
    "sg:address":"183 Palmerston St",
    "sg:city":"Southampton",
    "sg:classifiers":[
        {
            "category":"Travel",
            "subcategory":"Hotels & Motels",
            "type":"Entertainment"
        }
    ],
    "sg:phone":"+1 519 797 2216",
    "sg:postcode":"N0H 2L0",
    "sg:province":"ON",
    "wof:name":"Manor Motel",
    "wof:placetype":"venue"
},
  "geometry": {"coordinates":[-81.37329099999999,44.494102],"type":"Point"}
}