{
  "type": "Feature",
  "properties": {
    "addr:full":"3230 Rue King E Fleurimont QC J1E 3Y7",
    "addr:housenumber":"3230",
    "addr:postcode":"j1e 3y7",
    "addr:street":"Rue King E Fleurimont",
    "iso:country":"CA",
    "sg:address":"3230 Rue King E",
    "sg:city":"Fleurimont",
    "sg:classifiers":[
        {
            "category":"Manufacturing",
            "subcategory":"Tools & Machinery",
            "type":"Manufacturing & Wholesale Goods"
        }
    ],
    "sg:phone":"+1 819 569 6407",
    "sg:postcode":"J1E 3Y7",
    "sg:province":"QC",
    "sg:tags":[
        "repairing",
        "automobile"
    ],
    "wof:name":"Secure Auto Engr",
    "wof:placetype":"venue"
},
  "geometry": {"coordinates":[-71.8275756836,45.4213256836],"type":"Point"}
}