{
  "type": "Feature",
  "properties": {
    "addr:full":"Highway 20 Anahim Lake BC V0L 1C0",
    "addr:postcode":"v0l 1c0",
    "addr:street":"Highway 20 Anahim",
    "iso:country":"CA",
    "sg:address":"Highway 20",
    "sg:city":"Anahim Lake",
    "sg:classifiers":[
        {
            "category":"Freight",
            "type":"Transportation"
        }
    ],
    "sg:phone":"+1 250 742 3774",
    "sg:postcode":"V0L 1C0",
    "sg:province":"BC",
    "sg:tags":[
        "hauling",
        "log",
        "trucking"
    ],
    "wof:name":"Drico Transport Ltd",
    "wof:placetype":"venue"
},
  "geometry": {"coordinates":[-125.30149078399999,52.4591064453],"type":"Point"}
}