{
  "type": "Feature",
  "properties": {
    "addr:full":"Brighton ON K0K 1H0",
    "addr:postcode":"k0k 1h0",
    "iso:country":"CA",
    "sg:city":"Brighton",
    "sg:classifiers":[
        {
            "category":"Health Services",
            "subcategory":"Optometrist",
            "type":"Services"
        }
    ],
    "sg:phone":"+1 613 475 3900",
    "sg:postcode":"K0K 1H0",
    "sg:province":"ON",
    "wof:name":"Renaud, Nathalie",
    "wof:placetype":"venue"
},
  "geometry": {"coordinates":[-77.73259,44.04245],"type":"Point"}
}