{
  "type": "Feature",
  "properties": {
    "addr:full":"PO Box 2350 Iqaluit NU X0A 0H0",
    "addr:housenumber":"po",
    "addr:postcode":"2350;x0a 0h0",
    "addr:street":"Box",
    "iso:country":"CA",
    "sg:address":"PO Box 2350",
    "sg:city":"Iqaluit",
    "sg:classifiers":[
        {
            "category":"Education",
            "subcategory":"School",
            "type":"Public Place"
        }
    ],
    "sg:phone":"+1 867 979 3900",
    "sg:postcode":"X0A 0H0",
    "sg:province":"NU",
    "wof:name":"Aqsarniit School",
    "wof:placetype":"venue"
},
  "geometry": {"coordinates":[-68.5190200806,63.7514762878],"type":"Point"}
}