{
  "type": "Feature",
  "properties": {
    "addr:full":"1011 School Rd Hwy 648 Wilberforce ON K0L 3C0",
    "addr:housenumber":"1011",
    "addr:postcode":"k0l 3c0",
    "addr:street":"School Rd Hwy 648",
    "iso:country":"CA",
    "sg:address":"1011 School Rd Hwy 648",
    "sg:city":"Wilberforce",
    "sg:classifiers":[
        {
            "category":"Education",
            "subcategory":"School",
            "type":"Public Place"
        }
    ],
    "sg:phone":"+1 705 448 2421",
    "sg:postcode":"K0L 3C0",
    "sg:province":"ON",
    "wof:name":"Wilberforce Elementary School",
    "wof:placetype":"venue"
},
  "geometry": {"coordinates":[-78.2234573364,45.0383071899],"type":"Point"}
}