{
  "type": "Feature",
  "properties": {
    "addr:full":"346 Rang Dumas Ormstown QC J0S 1K0",
    "addr:housenumber":"346",
    "addr:postcode":"j0s 1k0",
    "addr:street":"Rang Dumas",
    "iso:country":"CA",
    "sg:address":"346 Rang Dumas",
    "sg:city":"Ormstown",
    "sg:classifiers":[
        {
            "category":"Autos & Motor Vehicles",
            "subcategory":"Auto Supplies",
            "type":"Retail Goods"
        }
    ],
    "sg:phone":"+1 450 829 2167",
    "sg:postcode":"J0S 1K0",
    "sg:province":"QC",
    "sg:tags":[
        "alternator",
        "automobile",
        "parts",
        "generator"
    ],
    "wof:name":"G F Demarreurs",
    "wof:placetype":"venue"
},
  "geometry": {"coordinates":[-73.99582700000001,45.12759],"type":"Point"}
}