{
  "type": "Feature",
  "properties": {
    "addr:full":"Sudbury ON P3E 2H2",
    "addr:postcode":"p3e 2h2",
    "iso:country":"CA",
    "sg:city":"Sudbury",
    "sg:classifiers":[
        {
            "category":"Health Services",
            "subcategory":"Doctor",
            "type":"Services"
        }
    ],
    "sg:phone":"+1 705 523 5589",
    "sg:postcode":"P3E 2H2",
    "sg:province":"ON",
    "sg:tags":[
        "physician",
        "surgeon"
    ],
    "wof:name":"Kalu, Uduma O MD",
    "wof:placetype":"venue"
},
  "geometry": {"coordinates":[-81.00016784669999,46.4638442993],"type":"Point"}
}