{
  "type": "Feature",
  "properties": {
    "addr:full":"2034 Currie Blvd Brandon MB R7A 5Y1",
    "addr:housenumber":"2034",
    "addr:postcode":"r7a 5y1",
    "addr:street":"Currie Blvd",
    "iso:country":"CA",
    "sg:address":"2034 Currie Blvd",
    "sg:city":"Brandon",
    "sg:classifiers":[
        {
            "category":"Real Estate",
            "subcategory":"Real Estate Operator",
            "type":"Services"
        }
    ],
    "sg:phone":"+1 204 727 7987",
    "sg:postcode":"R7A 5Y1",
    "sg:province":"MB",
    "sg:tags":[
        "management",
        "apartment"
    ],
    "wof:name":"Multiplex Management Ltd",
    "wof:placetype":"venue"
},
  "geometry": {"coordinates":[-99.96270800000001,49.818951],"type":"Point"}
}