{
  "type": "Feature",
  "properties": {
    "iso:country":"CA",
    "sg:address":"101 Tillson Ave",
    "sg:city":"Tillsonburg",
    "sg:classifiers":[
        {
            "category":"Home & Garden",
            "subcategory":"Building Materials",
            "type":"Retail Goods"
        }
    ],
    "sg:phone":"+1 519 842 8461",
    "sg:postcode":"N4G 3A4",
    "sg:province":"ON",
    "sg:tags":[
        "hardware"
    ],
    "wof:name":"Home Building Ctr",
    "wof:placetype":"venue"
},
  "geometry": {"coordinates":[-80.723815918,42.8662185669],"type":"Point"}
}