{
  "type": "Feature",
  "properties": {
    "addr:full":"Blenheim ON N0P 1A0",
    "addr:postcode":"n0p 1a0",
    "iso:country":"CA",
    "sg:city":"Blenheim",
    "sg:classifiers":[
        {
            "category":"Restaurant",
            "type":"Food & Drink"
        }
    ],
    "sg:phone":"+1 519 676 5559",
    "sg:postcode":"N0P 1A0",
    "sg:province":"ON",
    "sg:tags":[
        "pizza"
    ],
    "wof:name":"Naples Pizza",
    "wof:placetype":"venue"
},
  "geometry": {"coordinates":[-82.001953,42.330139],"type":"Point"}
}