{
  "type": "Feature",
  "properties": {
    "iso:country":"CA",
    "sg:city":"Saint-Eustache",
    "sg:classifiers":[
        {
            "category":"Insurance",
            "subcategory":"Insurance Agent",
            "type":"Services"
        }
    ],
    "sg:phone":"+1 450 473 2811",
    "sg:postcode":"J7R 2L6",
    "sg:province":"QC",
    "wof:name":"Assurances M St Georges Inc",
    "wof:placetype":"venue"
},
  "geometry": {"coordinates":[-73.89302062989999,45.5587310791],"type":"Point"}
}