{
  "type": "Feature",
  "properties": {
    "addr:full":"760 Topsail Rd Mount Pearl NL A1N 3J5",
    "addr:housenumber":"760",
    "addr:postcode":"a1n 3j5",
    "addr:street":"Topsail Rd",
    "iso:country":"CA",
    "sg:address":"760 Topsail Rd",
    "sg:city":"Mount Pearl",
    "sg:classifiers":[
        {
            "category":"Bars & Pubs",
            "type":"Food & Drink"
        }
    ],
    "sg:phone":"+1 709 364 1254",
    "sg:postcode":"A1N 3J5",
    "sg:province":"NL",
    "sg:tags":[
        "lounge",
        "cocktail"
    ],
    "wof:name":"Frosty's Lounge",
    "wof:placetype":"venue"
},
  "geometry": {"coordinates":[-52.778191,47.523132],"type":"Point"}
}