{
  "type": "Feature",
  "properties": {
    "iso:country":"CA",
    "sg:address":"768 Robson St",
    "sg:city":"Vancouver",
    "sg:classifiers":[
        {
            "category":"Shopping",
            "subcategory":"Tobacco",
            "type":"Retail Goods"
        }
    ],
    "sg:phone":"+1 604 684 1150",
    "sg:postcode":"V6Z 1A1",
    "sg:province":"BC",
    "sg:tags":[
        "cigarette",
        "cigar",
        "dealer"
    ],
    "wof:name":"Tobacco Patch",
    "wof:placetype":"venue"
},
  "geometry": {"coordinates":[-123.12055206300001,49.2816734314],"type":"Point"}
}