{
  "type": "Feature",
  "properties": {
    "addr:full":"76 Seventh Conc E Millgrove ON L0R 1V0",
    "addr:housenumber":"76",
    "addr:postcode":"l0r 1v0",
    "addr:street":"Seventh Conc E Millgrove",
    "iso:country":"CA",
    "sg:address":"76 Seventh Conc E",
    "sg:city":"Millgrove",
    "sg:classifiers":[
        {
            "category":"Recreation",
            "type":"Entertainment"
        }
    ],
    "sg:phone":"+1 905 689 0683",
    "sg:postcode":"L0R 1V0",
    "sg:province":"ON",
    "sg:tags":[
        "riding",
        "academy",
        "stable"
    ],
    "wof:name":"Foxcroft Equestrian Ctr",
    "wof:placetype":"venue"
},
  "geometry": {"coordinates":[-79.9580230713,43.3357696533],"type":"Point"}
}