{
  "type": "Feature",
  "properties": {
    "addr:full":"10 Resort Lane Omemee ON K0L 2W0",
    "addr:housenumber":"10",
    "addr:postcode":"k0l 2w0",
    "addr:street":"Resort Lane",
    "iso:country":"CA",
    "sg:address":"10 Resort Lane",
    "sg:city":"Omemee",
    "sg:classifiers":[
        {
            "category":"Travel",
            "subcategory":"Hotels & Motels",
            "type":"Entertainment"
        }
    ],
    "sg:phone":"+1 705 799 2316",
    "sg:postcode":"K0L 2W0",
    "sg:province":"ON",
    "sg:tags":[
        "resort"
    ],
    "wof:name":"Triple T Cedar Resort Ltd",
    "wof:placetype":"venue"
},
  "geometry": {"coordinates":[-78.5383987427,44.3428993225],"type":"Point"}
}