{
  "type": "Feature",
  "properties": {
    "iso:country":"CA",
    "sg:city":"Sainte-Thecle",
    "sg:classifiers":[
        {
            "category":"Government",
            "subcategory":"Office",
            "type":"Public Place"
        }
    ],
    "sg:phone":"+1 418 289 2335",
    "sg:postcode":"G0X 3G0",
    "sg:province":"QC",
    "sg:tags":[
        "village"
    ],
    "wof:name":"St-Thecle Garage Municipal",
    "wof:placetype":"venue"
},
  "geometry": {"coordinates":[-72.50424957280001,46.8118667603],"type":"Point"}
}