{
  "type": "Feature",
  "properties": {
    "addr:full":"3044 Sawmill Rd St Jacobs ON N0B 2N0",
    "addr:housenumber":"3044",
    "addr:postcode":"n0b 2n0",
    "addr:street":"Sawmill Rd St",
    "iso:country":"CA",
    "sg:address":"3044 Sawmill Rd",
    "sg:city":"St Jacobs",
    "sg:classifiers":[
        {
            "category":"Manufacturing",
            "subcategory":"Buildings",
            "type":"Manufacturing & Wholesale Goods"
        }
    ],
    "sg:phone":"+1 519 664 3823",
    "sg:postcode":"N0B 2N0",
    "sg:province":"ON",
    "sg:tags":[
        "home",
        "log",
        "cabin"
    ],
    "wof:name":"Pioneer Log Homes",
    "wof:placetype":"venue"
},
  "geometry": {"coordinates":[-80.5420455933,43.5437240601],"type":"Point"}
}