{
  "type": "Feature",
  "properties": {
    "addr:full":"Calgary AB T3K 5J6",
    "addr:postcode":"t3k 5j6",
    "iso:country":"CA",
    "sg:city":"Calgary",
    "sg:classifiers":[
        {
            "category":"Shopping",
            "subcategory":"Florist",
            "type":"Retail Goods"
        }
    ],
    "sg:phone":"+1 403 226 7673",
    "sg:postcode":"T3K 5J6",
    "sg:province":"AB",
    "wof:name":"Panda Flowers",
    "wof:placetype":"venue"
},
  "geometry": {"coordinates":[-114.061843872,51.1544647217],"type":"Point"}
}