{
  "type": "Feature",
  "properties": {
    "addr:full":"3 Winnifred St N Smiths Falls ON K7A 2M9",
    "addr:housenumber":"3",
    "addr:postcode":"k7a 2m9",
    "addr:street":"Winnifred St N",
    "iso:country":"CA",
    "sg:address":"3 Winnifred St N",
    "sg:city":"Smiths Falls",
    "sg:classifiers":[
        {
            "category":"Building & Trades",
            "subcategory":"Equipment Rental",
            "type":"Services"
        }
    ],
    "sg:phone":"+1 613 283 0441",
    "sg:postcode":"K7A 2M9",
    "sg:province":"ON",
    "sg:tags":[
        "recorder",
        "video"
    ],
    "wof:name":"S & S Electronics",
    "wof:placetype":"venue"
},
  "geometry": {"coordinates":[-76.014107,44.902035],"type":"Point"}
}