{
  "type": "Feature",
  "properties": {
    "addr:full":"Calgary AB T2P 2R9",
    "addr:postcode":"t2p 2r9",
    "iso:country":"CA",
    "sg:city":"Calgary",
    "sg:classifiers":[
        {
            "category":"Organizations",
            "subcategory":"Professional Association",
            "type":"Services"
        }
    ],
    "sg:phone":"+1 403 266 7565",
    "sg:postcode":"T2P 2R9",
    "sg:province":"AB",
    "wof:name":"Canadian Petroleum Products",
    "wof:placetype":"venue"
},
  "geometry": {"coordinates":[-114.065612793,51.0476341248],"type":"Point"}
}