{
  "type": "Feature",
  "properties": {
    "iso:country":"CA",
    "sg:address":"175 Osborne St",
    "sg:city":"Winnipeg",
    "sg:classifiers":[
        {
            "category":"Personal",
            "subcategory":"Beauty Salon",
            "type":"Services"
        }
    ],
    "sg:phone":"+1 204 284 6300",
    "sg:postcode":"R3L 1Z2",
    "sg:province":"MB",
    "wof:name":"Koil Hair Studio",
    "wof:placetype":"venue"
},
  "geometry": {"coordinates":[-97.143913269,49.8766326904],"type":"Point"}
}