{
  "type": "Feature",
  "properties": {
    "addr:full":"2262 Phillips Rd Sooke BC V0S 1N0",
    "addr:housenumber":"2262",
    "addr:postcode":"v0s 1n0",
    "addr:street":"Phillips Rd",
    "iso:country":"CA",
    "sg:address":"2262 Phillips Rd",
    "sg:city":"Sooke",
    "sg:classifiers":[
        {
            "category":"Building & Trades",
            "subcategory":"Construction",
            "type":"Services"
        }
    ],
    "sg:phone":"+1 250 642 3080",
    "sg:postcode":"V0S 1N0",
    "sg:province":"BC",
    "sg:tags":[
        "maker",
        "cabinet"
    ],
    "wof:name":"Sooke Cabinet & Refacing",
    "wof:placetype":"venue"
},
  "geometry": {"coordinates":[-123.71579,48.411472],"type":"Point"}
}