{
  "type": "Feature",
  "properties": {
    "iso:country":"CA",
    "sg:address":"840 Boul Saint-Joseph",
    "sg:city":"Hull",
    "sg:classifiers":[
        {
            "category":"Autos & Motor Vehicles",
            "subcategory":"Auto Supplies",
            "type":"Retail Goods"
        }
    ],
    "sg:phone":"+1 819 770 3370",
    "sg:postcode":"J8Z 1S9",
    "sg:province":"QC",
    "sg:tags":[
        "automobile",
        "parts"
    ],
    "wof:name":"Uap Napa Auto Parts",
    "wof:placetype":"venue"
},
  "geometry": {"coordinates":[-75.7398452759,45.4631843567],"type":"Point"}
}