{
  "type": "Feature",
  "properties": {
    "iso:country":"CA",
    "sg:address":"130 Industry St",
    "sg:city":"North York",
    "sg:classifiers":[
        {
            "category":"Organizations",
            "subcategory":"Professional Association",
            "type":"Services"
        }
    ],
    "sg:phone":"+1 416 762 9148",
    "sg:postcode":"M6M 5G3",
    "sg:province":"ON",
    "wof:name":"Club Aprigliano Ltd",
    "wof:placetype":"venue"
},
  "geometry": {"coordinates":[-79.4936904907,43.6939125061],"type":"Point"}
}