{
  "type": "Feature",
  "properties": {
    "addr:full":"43 Queen St W Brampton ON L6Y 1L9",
    "addr:housenumber":"43",
    "addr:postcode":"l6y 1l9",
    "addr:street":"Queen St W",
    "iso:country":"CA",
    "sg:address":"43 Queen St W",
    "sg:city":"Brampton",
    "sg:classifiers":[
        {
            "category":"Professional",
            "subcategory":"Lawyer & Legal Services",
            "type":"Services"
        }
    ],
    "sg:phone":"+1 905 451 3040",
    "sg:postcode":"L6Y 1L9",
    "sg:province":"ON",
    "sg:tags":[
        "attorney"
    ],
    "wof:name":"Lawrence Lawrence Stevenson",
    "wof:placetype":"venue"
},
  "geometry": {"coordinates":[-79.760513,43.685131],"type":"Point"}
}