{
  "type": "Feature",
  "properties": {
    "addr:full":"Brampton ON L6T 4K9",
    "addr:postcode":"l6t 4k9",
    "iso:country":"CA",
    "sg:city":"Brampton",
    "sg:classifiers":[
        {
            "category":"Manufacturing",
            "subcategory":"Tools & Machinery",
            "type":"Manufacturing & Wholesale Goods"
        }
    ],
    "sg:phone":"+1 905 792 7905",
    "sg:postcode":"L6T 4K9",
    "sg:province":"ON",
    "sg:tags":[
        "machine",
        "shop"
    ],
    "wof:name":"Kaz Industrial Hydraulics",
    "wof:placetype":"venue"
},
  "geometry": {"coordinates":[-79.67990899999999,43.709873],"type":"Point"}
}