{
  "type": "Feature",
  "properties": {
    "iso:country":"CA",
    "sg:address":"2956 Danforth Ave",
    "sg:city":"East York",
    "sg:classifiers":[
        {
            "category":"Personal",
            "subcategory":"Beauty Salon",
            "type":"Services"
        }
    ],
    "sg:phone":"+1 416 694 1962",
    "sg:postcode":"M4C 1M6",
    "sg:province":"ON",
    "wof:name":"Carousel Hair Stylists",
    "wof:placetype":"venue"
},
  "geometry": {"coordinates":[-79.2923812866,43.6904258728],"type":"Point"}
}