{
  "type": "Feature",
  "properties": {
    "addr:full":"Mildmay ON N0G 2J0",
    "addr:postcode":"n0g 2j0",
    "iso:country":"CA",
    "sg:city":"Mildmay",
    "sg:classifiers":[
        {
            "category":"Retail",
            "subcategory":"Auto Repair",
            "type":"Services"
        }
    ],
    "sg:phone":"+1 519 367 2839",
    "sg:postcode":"N0G 2J0",
    "sg:province":"ON",
    "sg:tags":[
        "repairing",
        "automobile"
    ],
    "wof:name":"Carrick Auto Repair",
    "wof:placetype":"venue"
},
  "geometry": {"coordinates":[-81.11934661870001,44.0420036316],"type":"Point"}
}