{
  "type": "Feature",
  "properties": {
    "addr:full":"292 Fourth Ave Kamloops BC V2C 3N5",
    "addr:housenumber":"292",
    "addr:postcode":"bc v2c 3n5",
    "addr:street":"Fourth Ave",
    "iso:country":"CA",
    "sg:address":"292 Fourth Ave",
    "sg:city":"Kamloops",
    "sg:classifiers":[
        {
            "category":"Professional",
            "subcategory":"Accounting & Tax Preparation",
            "type":"Services"
        }
    ],
    "sg:phone":"+1 250 374 0654",
    "sg:postcode":"V2C 3N5",
    "sg:province":"BC",
    "sg:tags":[
        "accountant"
    ],
    "wof:name":"Cunliffe Schreurs Tupper",
    "wof:placetype":"venue"
},
  "geometry": {"coordinates":[-120.332161,50.675083],"type":"Point"}
}