{
  "type": "Feature",
  "properties": {
    "iso:country":"CA",
    "sg:address":"581 Ch Herve",
    "sg:city":"Piedmont",
    "sg:classifiers":[
        {
            "category":"Retail",
            "subcategory":"Repair Shop",
            "type":"Services"
        }
    ],
    "sg:phone":"+1 450 227 2879",
    "sg:postcode":"J0R 1K0",
    "sg:province":"QC",
    "sg:tags":[
        "welding"
    ],
    "wof:name":"Monette Jp Soudure Inc",
    "wof:placetype":"venue"
},
  "geometry": {"coordinates":[-74.1256942749,45.896396637],"type":"Point"}
}