{
  "type": "Feature",
  "properties": {
    "addr:full":"Richmond BC V6V 1N3",
    "addr:postcode":"v6v 1n3",
    "iso:country":"CA",
    "sg:city":"Richmond",
    "sg:classifiers":[
        {
            "category":"Manufacturing",
            "subcategory":"Tools & Machinery",
            "type":"Manufacturing & Wholesale Goods"
        }
    ],
    "sg:phone":"+1 604 278 4118",
    "sg:postcode":"V6V 1N3",
    "sg:province":"BC",
    "sg:tags":[
        "refrigeration",
        "refrigerating"
    ],
    "wof:name":"Aero Heat Exchanger Inc",
    "wof:placetype":"venue"
},
  "geometry": {"coordinates":[-123.073532105,49.1956787109],"type":"Point"}
}