{
  "type": "Feature",
  "properties": {
    "addr:full":"11603 Ross St Hudson's Hope BC V0C 1V0",
    "addr:housenumber":"11603",
    "addr:postcode":"bc v0c 1v0",
    "addr:street":"Ross St",
    "iso:country":"CA",
    "sg:address":"11603 Ross St",
    "sg:city":"Hudson's Hope",
    "sg:classifiers":[
        {
            "category":"Building & Trades",
            "subcategory":"Construction",
            "type":"Services"
        }
    ],
    "sg:phone":"+1 250 783 5367",
    "sg:postcode":"V0C 1V0",
    "sg:province":"BC",
    "sg:tags":[
        "road",
        "contractor"
    ],
    "wof:name":"Yellowhead Road & Bridge Ltd",
    "wof:placetype":"venue"
},
  "geometry": {"coordinates":[-121.901314,56.037758],"type":"Point"}
}