{
  "type": "Feature",
  "properties": {
    "iso:country":"CA",
    "sg:address":"9847 Willow St # A",
    "sg:city":"Chemainus",
    "sg:classifiers":[
        {
            "category":"Personal",
            "subcategory":"Tanning Parlor",
            "type":"Services"
        }
    ],
    "sg:phone":"+1 250 246 9926",
    "sg:postcode":"V0R 1K0",
    "sg:province":"BC",
    "sg:tags":[
        "salon"
    ],
    "wof:name":"Beach Bums Tanning Boutique",
    "wof:placetype":"venue"
},
  "geometry": {"coordinates":[-123.71886444099999,48.9250106812],"type":"Point"}
}