{
  "type": "Feature",
  "properties": {
    "addr:full":"Grande Prairie AB T8V 5M4",
    "addr:postcode":"t8v 5m4",
    "iso:country":"CA",
    "sg:city":"Grande Prairie",
    "sg:classifiers":[
        {
            "category":"Wholesale",
            "subcategory":"Construction Materials",
            "type":"Manufacturing & Wholesale Goods"
        }
    ],
    "sg:phone":"+1 780 532 9299",
    "sg:postcode":"T8V 5M4",
    "sg:province":"AB",
    "sg:tags":[
        "equipment",
        "roofing",
        "supply",
        "contractor"
    ],
    "wof:name":"Roofmart Alberta Inc",
    "wof:placetype":"venue"
},
  "geometry": {"coordinates":[-118.842529297,55.1645698547],"type":"Point"}
}