{
  "type": "Feature",
  "properties": {
    "addr:full":"681 LA Verendrye Dr Gloucester ON K1J 7X5",
    "addr:housenumber":"681",
    "addr:postcode":"k1j 7x5",
    "addr:street":"La Verendrye Dr",
    "iso:country":"CA",
    "sg:address":"681 LA Verendrye Dr",
    "sg:city":"Gloucester",
    "sg:classifiers":[
        {
            "category":"Retail",
            "subcategory":"Portrait Studio",
            "type":"Services"
        }
    ],
    "sg:phone":"+1 613 745 5928",
    "sg:postcode":"K1J 7X5",
    "sg:province":"ON",
    "sg:tags":[
        "photographer"
    ],
    "wof:name":"G C Image Productions",
    "wof:placetype":"venue"
},
  "geometry": {"coordinates":[-75.6013793945,45.4526405334],"type":"Point"}
}