{
  "type": "Feature",
  "properties": {
    "iso:country":"CA",
    "sg:address":"593 Av DE LA Vallee",
    "sg:city":"Sainte-Angele-DE-Merici",
    "sg:classifiers":[
        {
            "category":"Local Transit",
            "type":"Transportation"
        }
    ],
    "sg:phone":"+1 418 775 8482",
    "sg:postcode":"G0J 2H0",
    "sg:province":"QC",
    "sg:tags":[
        "bus",
        "line"
    ],
    "wof:name":"Autobus-Autocars Orleans Exp",
    "wof:placetype":"venue"
},
  "geometry": {"coordinates":[-68.0802307129,48.525352478],"type":"Point"}
}