{
  "type": "Feature",
  "properties": {
    "addr:full":"593 Av DE LA Vallee Sainte-Angele-DE-Merici QC G0J 2H0",
    "addr:postcode":"g0j 2h0",
    "addr:street":"593 Av De La Vallee Sainte-Angele-De-Merici",
    "iso:country":"CA",
    "sg:address":"593 Av DE LA Vallee",
    "sg:city":"Sainte-Angele-DE-Merici",
    "sg:classifiers":[
        {
            "category":"Local Transit",
            "type":"Transportation"
        }
    ],
    "sg:phone":"+1 418 775 8482",
    "sg:postcode":"G0J 2H0",
    "sg:province":"QC",
    "sg:tags":[
        "bus",
        "line"
    ],
    "wof:name":"Autobus-Autocars Orleans Exp",
    "wof:placetype":"venue"
},
  "geometry": {"coordinates":[-68.0802307129,48.525352478],"type":"Point"}
}