{
  "type": "Feature",
  "properties": {
    "addr:full":"461 Sackville St Toronto ON M4X 1T3",
    "addr:housenumber":"461",
    "addr:postcode":"m4x 1t3",
    "addr:street":"Sackville St",
    "iso:country":"CA",
    "sg:address":"461 Sackville St",
    "sg:city":"Toronto",
    "sg:classifiers":[
        {
            "category":"Professional",
            "type":"Services"
        }
    ],
    "sg:phone":"+1 416 975 1440",
    "sg:postcode":"M4X 1T3",
    "sg:province":"ON",
    "sg:tags":[
        "arranger",
        "music",
        "composer"
    ],
    "wof:name":"Modular Music",
    "wof:placetype":"venue"
},
  "geometry": {"coordinates":[-79.366028,43.667843],"type":"Point"}
}