{
  "type": "Feature",
  "properties": {
    "addr:full":"9125 Rue Pascal-Gagnon # 108 Saint-Leonard QC H1P 1Z4",
    "addr:housenumber":"9125",
    "addr:postcode":"h1p 1z4",
    "addr:street":"Rue Pascal-Gagnon # 108",
    "iso:country":"CA",
    "sg:address":"9125 Rue Pascal-Gagnon # 108",
    "sg:city":"Saint-Leonard",
    "sg:classifiers":[
        {
            "category":"Shopping",
            "subcategory":"Clothing, Apparel, & Fashions",
            "type":"Retail Goods"
        }
    ],
    "sg:phone":"+1 514 327 7070",
    "sg:postcode":"H1P 1Z4",
    "sg:province":"QC",
    "sg:tags":[
        "shoes"
    ],
    "wof:name":"Agences DE Michel",
    "wof:placetype":"venue"
},
  "geometry": {"coordinates":[-73.5979,45.606594],"type":"Point"}
}