{
  "type": "Feature",
  "properties": {
    "addr:full":"858 College St Toronto ON M6H 1A2",
    "addr:housenumber":"858",
    "addr:postcode":"m6h 1a2",
    "addr:street":"College St",
    "iso:country":"CA",
    "sg:address":"858 College St",
    "sg:city":"Toronto",
    "sg:classifiers":[
        {
            "category":"Restaurant",
            "type":"Food & Drink"
        }
    ],
    "sg:phone":"+1 416 536 1877",
    "sg:postcode":"M6H 1A2",
    "sg:province":"ON",
    "wof:name":"Black Knight Restaurant & Tvrn",
    "wof:placetype":"venue"
},
  "geometry": {"coordinates":[-79.423767,43.654308],"type":"Point"}
}