{
  "type": "Feature",
  "properties": {
    "addr:full":"4231 Hazelbridge Way # 136 Richmond BC V6X 3L7",
    "addr:housenumber":"4231;136",
    "addr:postcode":"v6x 3l7",
    "addr:street":"Hazelbridge Way #",
    "iso:country":"CA",
    "sg:address":"4231 Hazelbridge Way # 136",
    "sg:city":"Richmond",
    "sg:classifiers":[
        {
            "category":"Shopping",
            "subcategory":"Clothing, Apparel, & Fashions",
            "type":"Retail Goods"
        }
    ],
    "sg:phone":"+1 604 273 8133",
    "sg:postcode":"V6X 3L7",
    "sg:province":"BC",
    "sg:tags":[
        "dressmaker",
        "tailor"
    ],
    "wof:name":"Shanghai Tailor",
    "wof:placetype":"venue"
},
  "geometry": {"coordinates":[-123.13362100000001,49.182148],"type":"Point"}
}