{
  "type": "Feature",
  "properties": {
    "addr:full":"204 Rue Chabanel O Montreal QC H2N 1G2",
    "addr:housenumber":"204",
    "addr:postcode":"h2n 1g2",
    "addr:street":"Rue Chabanel O",
    "iso:country":"CA",
    "sg:address":"204 Rue Chabanel O",
    "sg:city":"Montreal",
    "sg:classifiers":[
        {
            "category":"Food & Beverages",
            "subcategory":"Bakery",
            "type":"Retail Goods"
        }
    ],
    "sg:phone":"+1 514 383 1980",
    "sg:postcode":"H2N 1G2",
    "sg:province":"QC",
    "sg:tags":[
        "baker"
    ],
    "wof:name":"Arc-En-Ciel DE Chabanel",
    "wof:placetype":"venue"
},
  "geometry": {"coordinates":[-73.65300000000001,45.540977],"type":"Point"}
}