{
  "type": "Feature",
  "properties": {
    "addr:full":"Monkton ON N0K 1P0",
    "addr:postcode":"n0k 1p0",
    "iso:country":"CA",
    "sg:city":"Monkton",
    "sg:classifiers":[
        {
            "category":"Wholesale",
            "subcategory":"Machinery & Supplies",
            "type":"Manufacturing & Wholesale Goods"
        }
    ],
    "sg:phone":"+1 519 347 2341",
    "sg:postcode":"N0K 1P0",
    "sg:province":"ON",
    "sg:tags":[
        "truck"
    ],
    "wof:name":"Jeni Mobile Wash",
    "wof:placetype":"venue"
},
  "geometry": {"coordinates":[-81.0817642212,43.5873832703],"type":"Point"}
}