{
  "type": "Feature",
  "properties": {
    "iso:country":"CA",
    "sg:city":"Burnaby",
    "sg:classifiers":[
        {
            "category":"Building & Trades",
            "subcategory":"Electrical",
            "type":"Services"
        }
    ],
    "sg:phone":"+1 604 430 4777",
    "sg:postcode":"V5J 5E6",
    "sg:province":"BC",
    "sg:tags":[
        "electric",
        "contractor"
    ],
    "wof:name":"Harbourview Electric Ltd",
    "wof:placetype":"venue"
},
  "geometry": {"coordinates":[-122.980857849,49.2172966003],"type":"Point"}
}