{
  "type": "Feature",
  "properties": {
    "iso:country":"CA",
    "sg:address":"45 Penetang St",
    "sg:city":"Barrie",
    "sg:classifiers":[
        {
            "category":"Retail",
            "subcategory":"Laundry & Dry Cleaning",
            "type":"Services"
        }
    ],
    "sg:phone":"+1 705 726 5579",
    "sg:postcode":"L4M 1V5",
    "sg:province":"ON",
    "sg:tags":[
        "cleaners",
        "rug",
        "carpet"
    ],
    "wof:name":"Rug Mobile System Inc",
    "wof:placetype":"venue"
},
  "geometry": {"coordinates":[-79.6831359863,44.3956031799],"type":"Point"}
}