{
  "type": "Feature",
  "properties": {
    "addr:full":"600 Princess St Woodstock ON N4S 4H4",
    "addr:housenumber":"600",
    "addr:postcode":"n4s 4h4",
    "addr:street":"Princess St",
    "iso:country":"CA",
    "sg:address":"600 Princess St",
    "sg:city":"Woodstock",
    "sg:classifiers":[
        {
            "category":"Social Services",
            "type":"Services"
        }
    ],
    "sg:phone":"+1 519 539 6399",
    "sg:postcode":"N4S 4H4",
    "sg:province":"ON",
    "sg:tags":[
        "counselor",
        "marriage",
        "family"
    ],
    "wof:name":"Mc Namara & Assoc",
    "wof:placetype":"venue"
},
  "geometry": {"coordinates":[-80.75252500000001,43.132248],"type":"Point"}
}