{
  "type": "Feature",
  "properties": {
    "iso:country":"CA",
    "sg:address":"148 York St",
    "sg:city":"London",
    "sg:classifiers":[
        {
            "category":"Professional",
            "subcategory":"Detective & Security Services",
            "type":"Services"
        }
    ],
    "sg:phone":"+1 519 660 8188",
    "sg:postcode":"N6A 1A9",
    "sg:province":"ON",
    "sg:tags":[
        "guard",
        "patrol"
    ],
    "wof:name":"Garrison Corporate Sec Specs",
    "wof:placetype":"venue"
},
  "geometry": {"coordinates":[-81.249443,42.981186],"type":"Point"}
}