{
  "type": "Feature",
  "properties": {
    "addr:full":"2010 5 Ave N Lethbridge AB T1H 0N5",
    "addr:housenumber":"2010",
    "addr:postcode":"t1h 0n5",
    "addr:street":"5 Ave N",
    "iso:country":"CA",
    "sg:address":"2010 5 Ave N",
    "sg:city":"Lethbridge",
    "sg:classifiers":[
        {
            "category":"Education",
            "subcategory":"School",
            "type":"Public Place"
        }
    ],
    "sg:phone":"+1 403 317 7860",
    "sg:postcode":"T1H 0N5",
    "sg:province":"AB",
    "wof:name":"Immanuel Christian Elementary",
    "wof:placetype":"venue"
},
  "geometry": {"coordinates":[-112.81291198700001,49.7056121826],"type":"Point"}
}