{
  "type": "Feature",
  "properties": {
    "addr:full":"89 Rue Saint-Irenee Cap-DE-LA-Madeleine QC G8T 7C3",
    "addr:housenumber":"89",
    "addr:postcode":"g8t 7c3",
    "addr:street":"Rue Saint-Irenee",
    "iso:country":"CA",
    "sg:address":"89 Rue Saint-Irenee",
    "sg:city":"Cap-DE-LA-Madeleine",
    "sg:classifiers":[
        {
            "category":"Organizations",
            "subcategory":"Professional Association",
            "type":"Services"
        }
    ],
    "sg:phone":"+1 819 375 3476",
    "sg:postcode":"G8T 7C3",
    "sg:province":"QC",
    "wof:name":"Rdds",
    "wof:placetype":"venue"
},
  "geometry": {"coordinates":[-72.521522522,46.3638305664],"type":"Point"}
}