{
  "type": "Feature",
  "properties": {
    "addr:full":"Mississauga ON L5L 5R5",
    "addr:postcode":"l5l 5r5",
    "iso:country":"CA",
    "sg:city":"Mississauga",
    "sg:classifiers":[
        {
            "category":"Arena",
            "subcategory":"Sports Club",
            "type":"Entertainment"
        }
    ],
    "sg:phone":"+1 905 608 1300",
    "sg:postcode":"L5L 5R5",
    "sg:province":"ON",
    "sg:tags":[
        "soccer"
    ],
    "wof:name":"South Region Soccer League",
    "wof:placetype":"venue"
},
  "geometry": {"coordinates":[-79.693314,43.518383],"type":"Point"}
}