{
  "type": "Feature",
  "properties": {
    "addr:full":"Prince George BC V2N 6X4",
    "addr:postcode":"v2n 6x4",
    "iso:country":"CA",
    "sg:city":"Prince George",
    "sg:classifiers":[
        {
            "category":"Real Estate",
            "subcategory":"Real Estate Agent",
            "type":"Services"
        }
    ],
    "sg:phone":"+1 250 964 9179",
    "sg:postcode":"V2N 6X4",
    "sg:province":"BC",
    "sg:tags":[
        "authorities",
        "housing"
    ],
    "wof:name":"Ospika Heights",
    "wof:placetype":"venue"
},
  "geometry": {"coordinates":[-122.784973145,53.8769493103],"type":"Point"}
}