{
  "type": "Feature",
  "properties": {
    "addr:full":"Montreal QC H5B 1B4",
    "addr:postcode":"h5b 1b4",
    "iso:country":"CA",
    "sg:city":"Montreal",
    "sg:classifiers":[
        {
            "category":"Shopping",
            "subcategory":"Clothing, Apparel, & Fashions",
            "type":"Retail Goods"
        }
    ],
    "sg:phone":"+1 514 848 0867",
    "sg:postcode":"H5B 1B4",
    "sg:province":"QC",
    "sg:tags":[
        "item",
        "boutique"
    ],
    "wof:name":"Vie En Rose",
    "wof:placetype":"venue"
},
  "geometry": {"coordinates":[-73.56255299999999,45.511166],"type":"Point"}
}