{
  "type": "Feature",
  "properties": {
    "iso:country":"CA",
    "sg:address":"2180 Yonge St",
    "sg:city":"Toronto",
    "sg:classifiers":[
        {
            "category":"Shopping",
            "subcategory":"Discount & Variety Stores",
            "type":"Retail Goods"
        }
    ],
    "sg:phone":"+1 416 487 5991",
    "sg:postcode":"M4S 2B9",
    "sg:province":"ON",
    "wof:name":"M & M Shoppes",
    "wof:placetype":"venue"
},
  "geometry": {"coordinates":[-79.3981170654,43.7046012878],"type":"Point"}
}