{
  "type": "Feature",
  "properties": {
    "addr:full":"1425 Kensington Rd NW Calgary AB T2N 3R1",
    "addr:housenumber":"1425",
    "addr:postcode":"t2n 3r1",
    "addr:street":"Kensington Rd Nw",
    "iso:country":"CA",
    "sg:address":"1425 Kensington Rd NW",
    "sg:city":"Calgary",
    "sg:classifiers":[
        {
            "category":"Real Estate",
            "subcategory":"Developer",
            "type":"Services"
        }
    ],
    "sg:phone":"+1 403 265 3200",
    "sg:postcode":"T2N 3R1",
    "sg:province":"AB",
    "wof:name":"Spartacus Holdings Ltd",
    "wof:placetype":"venue"
},
  "geometry": {"coordinates":[-114.093132,51.052418],"type":"Point"}
}