{
  "type": "Feature",
  "properties": {
    "addr:full":"3710 Chesswood Dr North York ON M3J 2W4",
    "addr:housenumber":"3710",
    "addr:postcode":"m3j 2w4",
    "addr:street":"Chesswood Dr",
    "iso:country":"CA",
    "sg:address":"3710 Chesswood Dr",
    "sg:city":"North York",
    "sg:classifiers":[
        {
            "category":"Arts & Performance",
            "subcategory":"Theater",
            "type":"Entertainment"
        }
    ],
    "sg:phone":"+1 416 398 3137",
    "sg:postcode":"M3J 2W4",
    "sg:province":"ON",
    "sg:tags":[
        "bureau"
    ],
    "wof:name":"1328212 Ontario Ltd",
    "wof:placetype":"venue"
},
  "geometry": {"coordinates":[-79.47444915769999,43.7557792664],"type":"Point"}
}