{
  "type": "Feature",
  "properties": {
    "addr:full":"615 Rue Des Loisirs Saint-Prime QC G8J 1W1",
    "addr:housenumber":"615",
    "addr:postcode":"g8j 1w1",
    "addr:street":"Rue Des Loisirs",
    "iso:country":"CA",
    "sg:address":"615 Rue Des Loisirs",
    "sg:city":"Saint-Prime",
    "sg:classifiers":[
        {
            "category":"Organizations",
            "subcategory":"Membership Organization",
            "type":"Services"
        }
    ],
    "sg:phone":"+1 418 251 3220",
    "sg:postcode":"G8J 1W1",
    "sg:province":"QC",
    "sg:tags":[
        "recreation",
        "center",
        "government"
    ],
    "wof:name":"St-Prime Centre-Loisirs Ofc",
    "wof:placetype":"venue"
},
  "geometry": {"coordinates":[-72.337891,48.592682],"type":"Point"}
}