{
  "type": "Feature",
  "properties": {
    "addr:full":"468 Boul Cure-Poirier O Longueuil QC J4J 2H6",
    "addr:housenumber":"468",
    "addr:postcode":"j4j 2h6",
    "addr:street":"Boul Cure-Poirier O",
    "iso:country":"CA",
    "sg:address":"468 Boul Cure-Poirier O",
    "sg:city":"Longueuil",
    "sg:classifiers":[
        {
            "category":"Food & Beverages",
            "subcategory":"Groceries & Convenience Stores",
            "type":"Retail Goods"
        }
    ],
    "sg:phone":"+1 450 677 2742",
    "sg:postcode":"J4J 2H6",
    "sg:province":"QC",
    "wof:name":"Depan-Escompte Couche-Tard",
    "wof:placetype":"venue"
},
  "geometry": {"coordinates":[-73.47878300000001,45.534302],"type":"Point"}
}