{
  "type": "Feature",
  "properties": {
    "addr:full":"1991 Custer Crt Coquitlam BC V3J 6R2",
    "addr:housenumber":"1991",
    "addr:postcode":"v3j 6r2",
    "addr:street":"Custer Crt",
    "iso:country":"CA",
    "sg:address":"1991 Custer Crt",
    "sg:city":"Coquitlam",
    "sg:classifiers":[
        {
            "category":"Building & Trades",
            "subcategory":"Plumbing",
            "type":"Services"
        }
    ],
    "sg:phone":"+1 604 939 7852",
    "sg:postcode":"V3J 6R2",
    "sg:province":"BC",
    "sg:tags":[
        "contractor"
    ],
    "wof:name":"Rolly's Plumbing & Heating",
    "wof:placetype":"venue"
},
  "geometry": {"coordinates":[-122.837745666,49.2636871338],"type":"Point"}
}