{
  "type": "Feature",
  "properties": {
    "addr:full":"7578 Main St Louisbourg NS B1C 1K1",
    "addr:housenumber":"7578",
    "addr:postcode":"b1c 1k1",
    "addr:street":"Main St",
    "iso:country":"CA",
    "sg:address":"7578 Main St",
    "sg:city":"Louisbourg",
    "sg:classifiers":[
        {
            "category":"Building & Trades",
            "subcategory":"Construction",
            "type":"Services"
        }
    ],
    "sg:phone":"+1 902 733 2623",
    "sg:postcode":"B1C 1K1",
    "sg:province":"NS",
    "sg:tags":[
        "general",
        "contractor"
    ],
    "wof:name":"Beaver's Transfer Ltd",
    "wof:placetype":"venue"
},
  "geometry": {"coordinates":[-59.9762878418,45.9189910889],"type":"Point"}
}