{
  "type": "Feature",
  "properties": {
    "addr:full":"1651 Rue Denault Sherbrooke QC J1K 1E7",
    "addr:housenumber":"1651",
    "addr:postcode":"j1k 1e7",
    "addr:street":"Rue Denault",
    "iso:country":"CA",
    "sg:address":"1651 Rue Denault",
    "sg:city":"Sherbrooke",
    "sg:classifiers":[
        {
            "category":"Autos & Motor Vehicles",
            "subcategory":"Fuel & Gas Station",
            "type":"Retail Goods"
        }
    ],
    "sg:phone":"+1 819 562 2524",
    "sg:postcode":"J1K 1E7",
    "sg:province":"QC",
    "sg:tags":[
        "oil"
    ],
    "wof:name":"Olco",
    "wof:placetype":"venue"
},
  "geometry": {"coordinates":[-71.91575622560001,45.3887176514],"type":"Point"}
}