{
  "type": "Feature",
  "properties": {
    "addr:full":"855 Acadian Gdns Orleans ON K1C 2V7",
    "addr:housenumber":"855",
    "addr:postcode":"k1c 2v7",
    "addr:street":"Acadian Gdns",
    "iso:country":"CA",
    "sg:address":"855 Acadian Gdns",
    "sg:city":"Orleans",
    "sg:classifiers":[
        {
            "category":"Retail",
            "subcategory":"Portrait Studio",
            "type":"Services"
        }
    ],
    "sg:phone":"+1 613 830 0176",
    "sg:postcode":"K1C 2V7",
    "sg:province":"ON",
    "sg:tags":[
        "photographer"
    ],
    "wof:name":"Reno Video & Photo",
    "wof:placetype":"venue"
},
  "geometry": {"coordinates":[-75.5543746948,45.4774246216],"type":"Point"}
}