{
  "type": "Feature",
  "properties": {
    "addr:full":"113 Montee Mooney Cowansville QC J2K 3W1",
    "addr:housenumber":"113",
    "addr:postcode":"j2k 3w1",
    "addr:street":"Montee Mooney",
    "iso:country":"CA",
    "sg:address":"113 Montee Mooney",
    "sg:city":"Cowansville",
    "sg:classifiers":[
        {
            "category":"Building & Trades",
            "subcategory":"Construction",
            "type":"Services"
        }
    ],
    "sg:phone":"+1 450 263 3018",
    "sg:postcode":"J2K 3W1",
    "sg:province":"QC",
    "sg:tags":[
        "masonry",
        "contractor"
    ],
    "wof:name":"Maconnerie Noiseux & Frere Inc",
    "wof:placetype":"venue"
},
  "geometry": {"coordinates":[-72.71423299999999,45.211533],"type":"Point"}
}