{
  "type": "Feature",
  "properties": {
    "addr:full":"106 March Ave E Langenburg SK S0A 2A0",
    "addr:housenumber":"106",
    "addr:postcode":"s0a 2a0",
    "addr:street":"March Ave E",
    "iso:country":"CA",
    "sg:address":"106 March Ave E",
    "sg:city":"Langenburg",
    "sg:classifiers":[
        {
            "category":"Organizations",
            "subcategory":"Religious Organization",
            "type":"Services"
        }
    ],
    "sg:phone":"+1 306 743 5266",
    "sg:postcode":"S0A 2A0",
    "sg:province":"SK",
    "sg:tags":[
        "church"
    ],
    "wof:name":"St Joseph's Parish Ctr",
    "wof:placetype":"venue"
},
  "geometry": {"coordinates":[-101.699691773,50.8387336731],"type":"Point"}
}