{
  "type": "Feature",
  "properties": {
    "addr:full":"1268 St Clair Ave W Toronto ON M6E 1B9",
    "addr:housenumber":"1268",
    "addr:postcode":"m6e 1b9",
    "addr:street":"St Clair Ave W",
    "iso:country":"CA",
    "sg:address":"1268 St Clair Ave W",
    "sg:city":"Toronto",
    "sg:classifiers":[
        {
            "category":"Utilities",
            "subcategory":"Mobile Phone",
            "type":"Services"
        }
    ],
    "sg:phone":"+1 416 652 2288",
    "sg:postcode":"M6E 1B9",
    "sg:province":"ON",
    "sg:tags":[
        "equipment",
        "telephone",
        "cellular",
        "telecommunication"
    ],
    "wof:name":"Abo Business Machines",
    "wof:placetype":"venue"
},
  "geometry": {"coordinates":[-79.446907,43.677246],"type":"Point"}
}