{
  "type": "Feature",
  "properties": {
    "iso:country":"CA",
    "sg:address":"6146 Malden Rd",
    "sg:city":"Windsor",
    "sg:classifiers":[
        {
            "category":"Restaurant",
            "type":"Food & Drink"
        }
    ],
    "sg:phone":"+1 519 734 1239",
    "sg:postcode":"N9H 1S8",
    "sg:province":"ON",
    "wof:name":"Catalano's Pizzeria",
    "wof:placetype":"venue"
},
  "geometry": {"coordinates":[-83.060509,42.252739],"type":"Point"}
}