{
  "type": "Feature",
  "properties": {
    "addr:full":"13915 52 St NE Calgary AB T3N 1B5",
    "addr:housenumber":"13915",
    "addr:postcode":"t3n 1b5",
    "addr:street":"52 St Ne",
    "iso:country":"CA",
    "sg:address":"13915 52 St NE",
    "sg:city":"Calgary",
    "sg:classifiers":[
        {
            "category":"Retail",
            "subcategory":"Repair Shop",
            "type":"Services"
        }
    ],
    "sg:phone":"+1 403 226 1650",
    "sg:postcode":"T3N 1B5",
    "sg:province":"AB",
    "sg:tags":[
        "scale"
    ],
    "wof:name":"Standard Scale Svc Ltd",
    "wof:placetype":"venue"
},
  "geometry": {"coordinates":[-113.958648682,51.17420578],"type":"Point"}
}