{
  "type": "Feature",
  "properties": {
    "addr:full":"100 Mile House BC V0K 2E0",
    "addr:postcode":"v0k 2e0",
    "iso:country":"CA",
    "sg:city":"100 Mile House",
    "sg:classifiers":[
        {
            "category":"Retail",
            "subcategory":"Auto Repair",
            "type":"Services"
        }
    ],
    "sg:phone":"+1 250 395 3910",
    "sg:postcode":"V0K 2E0",
    "sg:province":"BC",
    "sg:tags":[
        "repairing",
        "automobile"
    ],
    "wof:name":"Mike & Jo's Auto Svc",
    "wof:placetype":"venue"
},
  "geometry": {"coordinates":[-121.299278,51.636246],"type":"Point"}
}