{
  "type": "Feature",
  "properties": {
    "addr:full":"239 Church St Iroquois Falls A ON P0K 1G0",
    "addr:housenumber":"239",
    "addr:postcode":"p0k 1g0",
    "addr:street":"Church St",
    "iso:country":"CA",
    "sg:address":"239 Church St",
    "sg:city":"Iroquois Falls A",
    "sg:classifiers":[
        {
            "category":"Health Services",
            "subcategory":"Hospital",
            "type":"Services"
        }
    ],
    "sg:phone":"+1 705 232 5656",
    "sg:postcode":"P0K 1G0",
    "sg:province":"ON",
    "sg:tags":[
        "mental"
    ],
    "wof:name":"Sal Timmins Consumer Network",
    "wof:placetype":"venue"
},
  "geometry": {"coordinates":[-80.68589,48.756672],"type":"Point"}
}