{
  "type": "Feature",
  "properties": {
    "addr:full":"79 Livingston Rd Scarborough ON M1E 1K7",
    "addr:housenumber":"79",
    "addr:postcode":"m1e 1k7",
    "addr:street":"Livingston Rd",
    "iso:country":"CA",
    "sg:address":"79 Livingston Rd",
    "sg:city":"Scarborough",
    "sg:classifiers":[
        {
            "category":"Restaurant",
            "type":"Food & Drink"
        }
    ],
    "sg:phone":"+1 416 264 3436",
    "sg:postcode":"M1E 1K7",
    "sg:province":"ON",
    "sg:tags":[
        "pizza"
    ],
    "wof:name":"Guildwood Pizza & Burgers",
    "wof:placetype":"venue"
},
  "geometry": {"coordinates":[-79.19864699999999,43.746559],"type":"Point"}
}