{
  "type": "Feature",
  "properties": {
    "addr:full":"87 Folger St Kingston ON K7K 5Y7",
    "addr:housenumber":"87",
    "addr:postcode":"k7k 5y7",
    "addr:street":"Folger St",
    "iso:country":"CA",
    "sg:address":"87 Folger St",
    "sg:city":"Kingston",
    "sg:classifiers":[
        {
            "category":"Building & Trades",
            "subcategory":"Construction",
            "type":"Services"
        }
    ],
    "sg:phone":"+1 613 544 9251",
    "sg:postcode":"K7K 5Y7",
    "sg:province":"ON",
    "sg:tags":[
        "roofing",
        "contractor"
    ],
    "wof:name":"Bishop's Roofing",
    "wof:placetype":"venue"
},
  "geometry": {"coordinates":[-76.48034667970001,44.2679901123],"type":"Point"}
}