{
  "type": "Feature",
  "properties": {
    "addr:full":"1819 Rue Saint-Cleophas Saint-Gabriel-DE-Brandon QC J0K 2N0",
    "addr:housenumber":"1819",
    "addr:postcode":"j0k 2n0",
    "addr:street":"Rue Saint-Cleophas",
    "iso:country":"CA",
    "sg:address":"1819 Rue Saint-Cleophas",
    "sg:city":"Saint-Gabriel-DE-Brandon",
    "sg:classifiers":[
        {
            "category":"Manufacturing",
            "subcategory":"Motor Vehicles & Parts",
            "type":"Manufacturing & Wholesale Goods"
        }
    ],
    "sg:phone":"+1 450 835 2363",
    "sg:postcode":"J0K 2N0",
    "sg:province":"QC",
    "sg:tags":[
        "body",
        "equipment",
        "truck"
    ],
    "wof:name":"L D Rainville & Fils Enrg",
    "wof:placetype":"venue"
},
  "geometry": {"coordinates":[-73.38371276860001,46.2853431702],"type":"Point"}
}