{
  "type": "Feature",
  "properties": {
    "addr:full":"11650 199 St NW Edmonton AB T5S 2C6",
    "addr:housenumber":"11650",
    "addr:postcode":"t5s 2c6",
    "addr:street":"199 St Nw",
    "iso:country":"CA",
    "sg:address":"11650 199 St NW",
    "sg:city":"Edmonton",
    "sg:classifiers":[
        {
            "category":"Wholesale",
            "subcategory":"Auto Parts",
            "type":"Manufacturing & Wholesale Goods"
        }
    ],
    "sg:phone":"+1 780 447 4545",
    "sg:postcode":"T5S 2C6",
    "sg:province":"AB",
    "sg:tags":[
        "automobile",
        "rebuilt",
        "crushing"
    ],
    "wof:name":"Lund's Auto & Truck Parts Ltd",
    "wof:placetype":"venue"
},
  "geometry": {"coordinates":[-113.664421081,53.5659294128],"type":"Point"}
}