{
  "type": "Feature",
  "properties": {
    "iso:country":"CA",
    "sg:address":"660 Hardwick Rd",
    "sg:city":"Bolton",
    "sg:classifiers":[
        {
            "category":"Shopping",
            "subcategory":"Gifts & Souvenirs",
            "type":"Retail Goods"
        }
    ],
    "sg:phone":"+1 905 857 5207",
    "sg:postcode":"L7E 5R5",
    "sg:province":"ON",
    "sg:tags":[
        "balloon",
        "artist"
    ],
    "wof:name":"Gayla Canada Inc",
    "wof:placetype":"venue"
},
  "geometry": {"coordinates":[-79.721519,43.866356],"type":"Point"}
}