{
  "type": "Feature",
  "properties": {
    "addr:full":"34 Rue Fleury O Montreal QC H3L 1S9",
    "addr:housenumber":"34",
    "addr:postcode":"h3l 1s9",
    "addr:street":"Rue Fleury O",
    "iso:country":"CA",
    "sg:address":"34 Rue Fleury O",
    "sg:city":"Montreal",
    "sg:classifiers":[
        {
            "category":"Shopping",
            "subcategory":"Books",
            "type":"Retail Goods"
        }
    ],
    "sg:phone":"+1 514 745 7472",
    "sg:postcode":"H3L 1S9",
    "sg:province":"QC",
    "sg:tags":[
        "dealer"
    ],
    "wof:name":"Institut DE Recherches Psych",
    "wof:placetype":"venue"
},
  "geometry": {"coordinates":[-73.664925,45.548061],"type":"Point"}
}