{
  "type": "Feature",
  "properties": {
    "addr:full":"Burlington ON L7R 4J1",
    "addr:postcode":"l7r 4j1",
    "iso:country":"CA",
    "sg:city":"Burlington",
    "sg:classifiers":[
        {
            "category":"Wholesale",
            "subcategory":"Electrical",
            "type":"Manufacturing & Wholesale Goods"
        }
    ],
    "sg:phone":"+1 905 634 3755",
    "sg:postcode":"L7R 4J1",
    "sg:province":"ON",
    "sg:tags":[
        "communication",
        "duplicating",
        "machine",
        "equipment",
        "facsimile",
        "copying"
    ],
    "wof:name":"Centennial Business Machines",
    "wof:placetype":"venue"
},
  "geometry": {"coordinates":[-79.8145980835,43.3369903564],"type":"Point"}
}