{
  "type": "Feature",
  "properties": {
    "addr:full":"405 Bayfield St Barrie ON L4M 3C5",
    "addr:housenumber":"405",
    "addr:postcode":"l4m 3c5",
    "addr:street":"Bayfield St",
    "iso:country":"CA",
    "sg:address":"405 Bayfield St",
    "sg:city":"Barrie",
    "sg:classifiers":[
        {
            "category":"Restaurant",
            "type":"Food & Drink"
        }
    ],
    "sg:phone":"+1 705 728 8811",
    "sg:postcode":"L4M 3C5",
    "sg:province":"ON",
    "wof:name":"C K Chinese Food",
    "wof:placetype":"venue"
},
  "geometry": {"coordinates":[-79.7060394287,44.4078598022],"type":"Point"}
}