{
  "type": "Feature",
  "properties": {
    "addr:full":"6300 Rue Sherbrooke O Montreal QC H4B 1M7",
    "addr:housenumber":"6300",
    "addr:postcode":"h4b 1m7",
    "addr:street":"Rue Sherbrooke O",
    "iso:country":"CA",
    "sg:address":"6300 Rue Sherbrooke O",
    "sg:city":"Montreal",
    "sg:classifiers":[
        {
            "category":"Food & Beverages",
            "subcategory":"Groceries & Convenience Stores",
            "type":"Retail Goods"
        }
    ],
    "sg:phone":"+1 514 489 1928",
    "sg:postcode":"H4B 1M7",
    "sg:province":"QC",
    "sg:tags":[
        "grocer"
    ],
    "wof:name":"Couche-Tard",
    "wof:placetype":"venue"
},
  "geometry": {"coordinates":[-73.5446853638,45.5796318054],"type":"Point"}
}