{
  "type": "Feature",
  "properties": {
    "addr:full":"187 Front St Belleville ON K8N 2Y9",
    "addr:housenumber":"187",
    "addr:postcode":"k8n 2y9",
    "addr:street":"Front St",
    "iso:country":"CA",
    "sg:address":"187 Front St",
    "sg:city":"Belleville",
    "sg:classifiers":[
        {
            "category":"Organizations",
            "subcategory":"Professional Association",
            "type":"Services"
        }
    ],
    "sg:phone":"+1 613 968 9116",
    "sg:postcode":"K8N 2Y9",
    "sg:province":"ON",
    "wof:name":"Army Navy & Airforce Veterans",
    "wof:placetype":"venue"
},
  "geometry": {"coordinates":[-77.38371276860001,44.1632728577],"type":"Point"}
}