{
  "type": "Feature",
  "properties": {
    "addr:full":"1535 Ch Des Patriotes Sainte-Victoire-DE-Sorel QC J0G 1T0",
    "addr:postcode":"1535;j0g 1t0",
    "addr:street":"Ch Des Patriotes",
    "iso:country":"CA",
    "sg:address":"1535 Ch Des Patriotes",
    "sg:city":"Sainte-Victoire-DE-Sorel",
    "sg:classifiers":[
        {
            "category":"Building & Trades",
            "subcategory":"Construction",
            "type":"Services"
        }
    ],
    "sg:phone":"+1 450 743 7824",
    "sg:postcode":"J0G 1T0",
    "sg:province":"QC",
    "sg:tags":[
        "insulation",
        "heat",
        "contractor"
    ],
    "wof:name":"Isolation Sorel Inc",
    "wof:placetype":"venue"
},
  "geometry": {"coordinates":[-73.136375,45.987965],"type":"Point"}
}