{
  "type": "Feature",
  "properties": {
    "iso:country":"CA",
    "sg:address":"889 King St W",
    "sg:city":"Hamilton",
    "sg:classifiers":[
        {
            "category":"Wholesale",
            "subcategory":"Meat",
            "type":"Manufacturing & Wholesale Goods"
        }
    ],
    "sg:phone":"+1 905 527 5762",
    "sg:postcode":"L8S 1K5",
    "sg:province":"ON",
    "sg:tags":[
        "butchering"
    ],
    "wof:name":"Hamilton Kosher Meat Market",
    "wof:placetype":"venue"
},
  "geometry": {"coordinates":[-79.9013366699,43.2630119324],"type":"Point"}
}