{
  "type": "Feature",
  "properties": {
    "addr:full":"227 Rue Racine E # 202 Chicoutimi QC G7H 7B4",
    "addr:housenumber":"227",
    "addr:postcode":"g7h 7b4",
    "addr:street":"Rue Racine E # 202",
    "iso:country":"CA",
    "sg:address":"227 Rue Racine E # 202",
    "sg:city":"Chicoutimi",
    "sg:classifiers":[
        {
            "category":"Government",
            "subcategory":"Office",
            "type":"Public Place"
        }
    ],
    "sg:phone":"+1 418 696 9947",
    "sg:postcode":"G7H 7B4",
    "sg:province":"QC",
    "wof:name":"Quebec Substitut Procureur",
    "wof:placetype":"venue"
},
  "geometry": {"coordinates":[-71.061852,48.427814],"type":"Point"}
}