{
  "type": "Feature",
  "properties": {
    "iso:country":"CA",
    "sg:address":"3781 Av DE Courtrai",
    "sg:city":"Montreal",
    "sg:classifiers":[
        {
            "category":"Organizations",
            "subcategory":"Professional Association",
            "type":"Services"
        }
    ],
    "sg:phone":"+1 514 735 9425",
    "sg:postcode":"H3S 1B8",
    "sg:province":"QC",
    "wof:name":"Societe Bouddhique Quan-am",
    "wof:placetype":"venue"
},
  "geometry": {"coordinates":[-73.640266,45.503311],"type":"Point"}
}