{
  "type": "Feature",
  "properties": {
    "addr:full":"106 Lock St E Dunnville ON N1A 1J7",
    "addr:housenumber":"106",
    "addr:postcode":"n1a 1j7",
    "addr:street":"Lock St E",
    "iso:country":"CA",
    "sg:address":"106 Lock St E",
    "sg:city":"Dunnville",
    "sg:classifiers":[
        {
            "category":"Professional",
            "subcategory":"Lawyer & Legal Services",
            "type":"Services"
        }
    ],
    "sg:phone":"+1 905 774 7485",
    "sg:postcode":"N1A 1J7",
    "sg:province":"ON",
    "sg:tags":[
        "attorney"
    ],
    "wof:name":"Chambers, G Donald",
    "wof:placetype":"venue"
},
  "geometry": {"coordinates":[-79.619354,42.902798],"type":"Point"}
}