{
  "type": "Feature",
  "properties": {
    "addr:full":"7545 Yonge St Thornhill ON L3T 2C2",
    "addr:housenumber":"7545",
    "addr:postcode":"l3t 2c2",
    "addr:street":"Yonge St",
    "iso:country":"CA",
    "sg:address":"7545 Yonge St",
    "sg:city":"Thornhill",
    "sg:classifiers":[
        {
            "category":"Retail",
            "subcategory":"Auto Rental",
            "type":"Services"
        }
    ],
    "sg:phone":"+1 905 707 0522",
    "sg:postcode":"L3T 2C2",
    "sg:province":"ON",
    "sg:tags":[
        "renting",
        "automobile"
    ],
    "wof:name":"Hertz",
    "wof:placetype":"venue"
},
  "geometry": {"coordinates":[-79.4233627319,43.8117141724],"type":"Point"}
}