{
  "type": "Feature",
  "properties": {
    "addr:full":"237 Elgin St Brantford ON N3S 5A8",
    "addr:housenumber":"237",
    "addr:postcode":"n3s 5a8",
    "addr:street":"Elgin St",
    "iso:country":"CA",
    "sg:address":"237 Elgin St",
    "sg:city":"Brantford",
    "sg:classifiers":[
        {
            "category":"Professional",
            "subcategory":"Business Services",
            "type":"Services"
        }
    ],
    "sg:phone":"+1 519 753 3266",
    "sg:postcode":"N3S 5A8",
    "sg:province":"ON",
    "sg:tags":[
        "water",
        "treatment"
    ],
    "wof:name":"Paules Wetside Boiler Svc",
    "wof:placetype":"venue"
},
  "geometry": {"coordinates":[-80.244308,43.1497],"type":"Point"}
}