{
  "type": "Feature",
  "properties": {
    "addr:full":"71 Carleton Triangle Rd Carleton NS B0W 1L0",
    "addr:housenumber":"71",
    "addr:postcode":"b0w 1l0",
    "addr:street":"Carleton Triangle Rd",
    "iso:country":"CA",
    "sg:address":"71 Carleton Triangle Rd",
    "sg:city":"Carleton",
    "sg:classifiers":[
        {
            "category":"Building & Trades",
            "subcategory":"Construction",
            "type":"Services"
        }
    ],
    "sg:phone":"+1 902 761 2313",
    "sg:postcode":"B0W 1L0",
    "sg:province":"NS",
    "sg:tags":[
        "excavating",
        "contractor"
    ],
    "wof:name":"Gary Allen Trucking & Backhoe",
    "wof:placetype":"venue"
},
  "geometry": {"coordinates":[-65.925926,44.005009],"type":"Point"}
}