{
  "type": "Feature",
  "properties": {
    "addr:full":"796 Lasalle Blvd Sudbury ON P3A 4V4",
    "addr:housenumber":"796",
    "addr:postcode":"p3a 4v4",
    "addr:street":"Lasalle Blvd",
    "iso:country":"CA",
    "sg:address":"796 Lasalle Blvd",
    "sg:city":"Sudbury",
    "sg:classifiers":[
        {
            "category":"Education",
            "subcategory":"Special Training",
            "type":"Public Place"
        }
    ],
    "sg:phone":"+1 705 897 1305",
    "sg:postcode":"P3A 4V4",
    "sg:province":"ON",
    "sg:tags":[
        "instruction",
        "driving"
    ],
    "wof:name":"Laurentian Driving School",
    "wof:placetype":"venue"
},
  "geometry": {"coordinates":[-80.964958,46.522255],"type":"Point"}
}