{
  "type": "Feature",
  "properties": {
    "addr:full":"11339 84 Ave Delta BC V4C 2L9",
    "addr:housenumber":"11339",
    "addr:postcode":"v4c 2l9",
    "addr:street":"84 Ave",
    "iso:country":"CA",
    "sg:address":"11339 84 Ave",
    "sg:city":"Delta",
    "sg:classifiers":[
        {
            "category":"Social Services",
            "type":"Services"
        }
    ],
    "sg:phone":"+1 604 596 9595",
    "sg:postcode":"V4C 2L9",
    "sg:province":"BC",
    "sg:tags":[
        "youth",
        "organization",
        "center"
    ],
    "wof:name":"Boys' & Girls' Club-N Delta",
    "wof:placetype":"venue"
},
  "geometry": {"coordinates":[-122.909302,49.156166],"type":"Point"}
}