{
  "type": "Feature",
  "properties": {
    "addr:full":"2505 Boul Des Recollets Trois-Rivieres QC G8Z 4G1",
    "addr:housenumber":"2505",
    "addr:postcode":"g8z 4g1",
    "addr:street":"Boul Des Recollets Trois-Rivieres",
    "iso:country":"CA",
    "sg:address":"2505 Boul Des Recollets",
    "sg:city":"Trois-Rivieres",
    "sg:classifiers":[
        {
            "category":"Home & Garden",
            "subcategory":"Furniture",
            "type":"Retail Goods"
        }
    ],
    "sg:phone":"+1 819 370 3278",
    "sg:postcode":"G8Z 4G1",
    "sg:province":"QC",
    "sg:tags":[
        "hardware",
        "top",
        "counter"
    ],
    "wof:name":"Module Concept",
    "wof:placetype":"venue"
},
  "geometry": {"coordinates":[-72.578484,46.337536],"type":"Point"}
}