{
  "type": "Feature",
  "properties": {
    "addr:full":"8 Industrial Pky S Aurora ON L4G 3W1",
    "addr:housenumber":"8",
    "addr:postcode":"l4g 3w1",
    "addr:street":"Industrial Pky",
    "iso:country":"CA",
    "sg:address":"8 Industrial Pky S",
    "sg:city":"Aurora",
    "sg:classifiers":[
        {
            "category":"Retail",
            "subcategory":"Auto Repair",
            "type":"Services"
        }
    ],
    "sg:phone":"+1 905 726 2646",
    "sg:postcode":"L4G 3W1",
    "sg:province":"ON",
    "sg:tags":[
        "repairing",
        "automobile",
        "body"
    ],
    "wof:name":"Craig's Performance Imports",
    "wof:placetype":"venue"
},
  "geometry": {"coordinates":[-79.4566650391,44.0012283325],"type":"Point"}
}