{
  "type": "Feature",
  "properties": {
    "addr:full":"133 Cronkwoods Rd Mallorytown ON K0E 1R0",
    "addr:housenumber":"133",
    "addr:postcode":"k0e 1r0",
    "addr:street":"Cronkwoods Rd",
    "iso:country":"CA",
    "sg:address":"133 Cronkwoods Rd",
    "sg:city":"Mallorytown",
    "sg:classifiers":[
        {
            "category":"Home & Garden",
            "subcategory":"Furniture",
            "type":"Retail Goods"
        }
    ],
    "sg:phone":"+1 613 342 4735",
    "sg:postcode":"K0E 1R0",
    "sg:province":"ON",
    "sg:tags":[
        "kitchen",
        "maker",
        "cabinet"
    ],
    "wof:name":"Custom Home Improvements",
    "wof:placetype":"venue"
},
  "geometry": {"coordinates":[-75.8799362183,44.4781455994],"type":"Point"}
}