{
  "type": "Feature",
  "properties": {
    "addr:full":"147 Connell St Woodstock NB E7M 1K7",
    "addr:housenumber":"147",
    "addr:postcode":"e7m 1k7",
    "addr:street":"Connell St",
    "iso:country":"CA",
    "sg:address":"147 Connell St",
    "sg:city":"Woodstock",
    "sg:classifiers":[
        {
            "category":"Real Estate",
            "subcategory":"Real Estate Agent",
            "type":"Services"
        }
    ],
    "sg:phone":"+1 506 328 3371",
    "sg:postcode":"E7M 1K7",
    "sg:province":"NB",
    "wof:name":"Wishart Real Estate Ltd",
    "wof:placetype":"venue"
},
  "geometry": {"coordinates":[-67.5779876709,46.1511116028],"type":"Point"}
}