{
  "type": "Feature",
  "properties": {
    "addr:full":"37 Cumberland St S Thunder Bay ON P7B 2T4",
    "addr:housenumber":"37",
    "addr:postcode":"p7b 2t4",
    "addr:street":"Cumberland St S",
    "iso:country":"CA",
    "sg:address":"37 Cumberland St S",
    "sg:city":"Thunder Bay",
    "sg:classifiers":[
        {
            "category":"Bars & Pubs",
            "type":"Food & Drink"
        }
    ],
    "sg:phone":"+1 807 345 5199",
    "sg:postcode":"P7B 2T4",
    "sg:province":"ON",
    "sg:tags":[
        "club",
        "amusement",
        "night"
    ],
    "wof:name":"Kilroy's Sports Pub",
    "wof:placetype":"venue"
},
  "geometry": {"coordinates":[-89.2206039429,48.4333992004],"type":"Point"}
}