{
  "type": "Feature",
  "properties": {
    "addr:full":"5519 6 St SE Calgary AB T2H 1L6",
    "addr:housenumber":"5519 6",
    "addr:postcode":"t2h 1l6",
    "addr:street":"St Se",
    "iso:country":"CA",
    "sg:address":"5519 6 St SE",
    "sg:city":"Calgary",
    "sg:classifiers":[
        {
            "category":"Retail",
            "subcategory":"Auto Rental",
            "type":"Services"
        }
    ],
    "sg:phone":"+1 403 253 4335",
    "sg:postcode":"T2H 1L6",
    "sg:province":"AB",
    "sg:tags":[
        "renting",
        "truck",
        "leasing"
    ],
    "wof:name":"U-Haul CO Ltd",
    "wof:placetype":"venue"
},
  "geometry": {"coordinates":[-114.07897199999999,51.004902],"type":"Point"}
}