{
  "type": "Feature",
  "properties": {
    "addr:full":"361 Colborne St Chatham ON N7M 5J4",
    "addr:housenumber":"361",
    "addr:postcode":"n7m 5j4",
    "addr:street":"Colborne St",
    "iso:country":"CA",
    "sg:address":"361 Colborne St",
    "sg:city":"Chatham",
    "sg:classifiers":[
        {
            "category":"Home & Garden",
            "subcategory":"Building Materials",
            "type":"Retail Goods"
        }
    ],
    "sg:phone":"+1 519 354 5398",
    "sg:postcode":"N7M 5J4",
    "sg:province":"ON",
    "sg:tags":[
        "type",
        "door"
    ],
    "wof:name":"Custom Door Sales & Svc",
    "wof:placetype":"venue"
},
  "geometry": {"coordinates":[-82.16677900000001,42.412254],"type":"Point"}
}