{
  "type": "Feature",
  "properties": {
    "addr:full":"828 Chemong Rd Peterborough ON K9H 5Z9",
    "addr:housenumber":"828",
    "addr:postcode":"k9h 5z9",
    "addr:street":"Chemong Rd",
    "iso:country":"CA",
    "sg:address":"828 Chemong Rd",
    "sg:city":"Peterborough",
    "sg:classifiers":[
        {
            "category":"Restaurant",
            "type":"Food & Drink"
        }
    ],
    "sg:phone":"+1 705 745 1936",
    "sg:postcode":"K9H 5Z9",
    "sg:province":"ON",
    "sg:tags":[
        "shop",
        "coffee"
    ],
    "wof:name":"Country Style",
    "wof:placetype":"venue"
},
  "geometry": {"coordinates":[-78.3302764893,44.3179740906],"type":"Point"}
}