{
  "type": "Feature",
  "properties": {
    "addr:full":"Farm White Fox SK S0J 3B0",
    "addr:postcode":"s0j 3b0",
    "addr:street":"Fox",
    "iso:country":"CA",
    "sg:address":"Farm",
    "sg:city":"White Fox",
    "sg:classifiers":[
        {
            "category":"Recreation",
            "type":"Entertainment"
        }
    ],
    "sg:phone":"+1 306 276 2055",
    "sg:postcode":"S0J 3B0",
    "sg:province":"SK",
    "sg:tags":[
        "party",
        "fishing"
    ],
    "wof:name":"North Sask Frontier Adventures",
    "wof:placetype":"venue"
},
  "geometry": {"coordinates":[-104.086387634,53.4528045654],"type":"Point"}
}