{
  "type": "Feature",
  "properties": {
    "addr:full":"1689 Rue Poirier Saint-Laurent QC H4L 1J2",
    "addr:housenumber":"1689",
    "addr:postcode":"h4l 1j2",
    "addr:street":"Rue Poirier",
    "iso:country":"CA",
    "sg:address":"1689 Rue Poirier",
    "sg:city":"Saint-Laurent",
    "sg:classifiers":[
        {
            "category":"Food & Beverages",
            "subcategory":"Groceries & Convenience Stores",
            "type":"Retail Goods"
        }
    ],
    "sg:phone":"+1 514 748 1160",
    "sg:postcode":"H4L 1J2",
    "sg:province":"QC",
    "sg:tags":[
        "grocer"
    ],
    "wof:name":"Epicerie Orient Poirier Inc",
    "wof:placetype":"venue"
},
  "geometry": {"coordinates":[-73.6976852417,45.5194129944],"type":"Point"}
}