{
  "type": "Feature",
  "properties": {
    "addr:full":"1400 Ritson Rd S Oshawa ON L1J 6N5",
    "addr:housenumber":"1400",
    "addr:postcode":"l1j 6n5",
    "addr:street":"Ritson Rd",
    "iso:country":"CA",
    "sg:address":"1400 Ritson Rd S",
    "sg:city":"Oshawa",
    "sg:classifiers":[
        {
            "category":"Social Services",
            "subcategory":"Child Care",
            "type":"Services"
        }
    ],
    "sg:phone":"+1 905 438 1771",
    "sg:postcode":"L1J 6N5",
    "sg:province":"ON",
    "wof:name":"Caw Child Care Svc",
    "wof:placetype":"venue"
},
  "geometry": {"coordinates":[-78.838081,43.862949],"type":"Point"}
}