{
  "type": "Feature",
  "properties": {
    "iso:country":"CA",
    "sg:address":"12360 121 St NW",
    "sg:city":"Edmonton",
    "sg:classifiers":[
        {
            "category":"Railroad",
            "type":"Transportation"
        }
    ],
    "sg:phone":"+1 780 448 2575",
    "sg:postcode":"T5L 5C3",
    "sg:province":"AB",
    "wof:name":"Via Rail Canada Inc",
    "wof:placetype":"venue"
},
  "geometry": {"coordinates":[-113.535186768,53.5753479004],"type":"Point"}
}