{
  "type": "Feature",
  "properties": {
    "addr:full":"340 White Rd Avondale NB E7K 1Y5",
    "addr:housenumber":"340",
    "addr:postcode":"e7k 1y5",
    "addr:street":"White Rd",
    "iso:country":"CA",
    "sg:address":"340 White Rd",
    "sg:city":"Avondale",
    "sg:classifiers":[
        {
            "category":"Retail",
            "subcategory":"Auto Repair",
            "type":"Services"
        }
    ],
    "sg:phone":"+1 506 375 8769",
    "sg:postcode":"E7K 1Y5",
    "sg:province":"NB",
    "sg:tags":[
        "repairing",
        "automobile"
    ],
    "wof:name":"Avondale Auto Svc",
    "wof:placetype":"venue"
},
  "geometry": {"coordinates":[-67.648201,46.321007],"type":"Point"}
}