{
  "type": "Feature",
  "properties": {
    "addr:full":"353 Alfred St Kingston ON K7K 4H6",
    "addr:housenumber":"353",
    "addr:postcode":"k7k 4h6",
    "addr:street":"Alfred St",
    "iso:country":"CA",
    "sg:address":"353 Alfred St",
    "sg:city":"Kingston",
    "sg:classifiers":[
        {
            "category":"Professional",
            "subcategory":"Accounting & Tax Preparation",
            "type":"Services"
        }
    ],
    "sg:phone":"+1 613 544 6160",
    "sg:postcode":"K7K 4H6",
    "sg:province":"ON",
    "sg:tags":[
        "accountant"
    ],
    "wof:name":"Secker Ross & Perry",
    "wof:placetype":"venue"
},
  "geometry": {"coordinates":[-76.497383,44.235794],"type":"Point"}
}