{
  "type": "Feature",
  "properties": {
    "iso:country":"CA",
    "sg:address":"423 Woolwich St",
    "sg:city":"Guelph",
    "sg:classifiers":[
        {
            "category":"Real Estate",
            "subcategory":"Surveying",
            "type":"Services"
        }
    ],
    "sg:phone":"+1 519 821 2763",
    "sg:postcode":"N1H 3X3",
    "sg:province":"ON",
    "sg:tags":[
        "surveyor"
    ],
    "wof:name":"Van Harten Surveying Ltd",
    "wof:placetype":"venue"
},
  "geometry": {"coordinates":[-80.2610626221,43.5532531738],"type":"Point"}
}