{
  "type": "Feature",
  "properties": {
    "addr:full":"18 Rydberg St Hughenden AB T0B 2E0",
    "addr:housenumber":"18",
    "addr:postcode":"t0b 2e0",
    "addr:street":"Rydberg St",
    "iso:country":"CA",
    "sg:address":"18 Rydberg St",
    "sg:city":"Hughenden",
    "sg:classifiers":[
        {
            "category":"Organizations",
            "subcategory":"Religious Organization",
            "type":"Services"
        }
    ],
    "sg:phone":"+1 780 856 3650",
    "sg:postcode":"T0B 2E0",
    "sg:province":"AB",
    "sg:tags":[
        "church"
    ],
    "wof:name":"Hughenden Pentecostal Church",
    "wof:placetype":"venue"
},
  "geometry": {"coordinates":[-110.965363,52.512482],"type":"Point"}
}