{
  "type": "Feature",
  "properties": {
    "addr:full":"19839 28 Ave Langley BC V2Z 1Y2",
    "addr:housenumber":"19839",
    "addr:postcode":"v2z 1y2",
    "addr:street":"28 Ave",
    "iso:country":"CA",
    "sg:address":"19839 28 Ave",
    "sg:city":"Langley",
    "sg:classifiers":[
        {
            "category":"Professional",
            "type":"Services"
        }
    ],
    "sg:phone":"+1 604 534 5620",
    "sg:postcode":"V2Z 1Y2",
    "sg:province":"BC",
    "sg:tags":[
        "hair",
        "good",
        "establishment",
        "supply"
    ],
    "wof:name":"Neways Independent Distr",
    "wof:placetype":"venue"
},
  "geometry": {"coordinates":[-122.673568726,49.0531349182],"type":"Point"}
}