{
  "type": "Feature",
  "properties": {
    "addr:full":"PO Box 227 Water Valley AB T0M 2E0",
    "addr:housenumber":"po",
    "addr:postcode":"t0m 2e0",
    "addr:street":"Box 227 Water",
    "iso:country":"CA",
    "sg:address":"PO Box 227",
    "sg:city":"Water Valley",
    "sg:classifiers":[
        {
            "category":"Building & Trades",
            "subcategory":"Plumbing",
            "type":"Services"
        }
    ],
    "sg:phone":"+1 403 637 2191",
    "sg:postcode":"T0M 2E0",
    "sg:province":"AB",
    "sg:tags":[
        "contractor"
    ],
    "wof:name":"Salai's Plumbing & Gas Ltd",
    "wof:placetype":"venue"
},
  "geometry": {"coordinates":[-114.605553,51.503891],"type":"Point"}
}