{
  "type": "Feature",
  "properties": {
    "addr:full":"PO Box 1897 STN Main Athabasca AB T9S 2B5",
    "addr:housenumber":"po",
    "addr:postcode":"t9s 2b5",
    "addr:street":"Box 1897 Stn Main",
    "iso:country":"CA",
    "sg:address":"PO Box 1897 STN Main",
    "sg:city":"Athabasca",
    "sg:classifiers":[
        {
            "category":"Retail",
            "subcategory":"Laundry & Dry Cleaning",
            "type":"Services"
        }
    ],
    "sg:phone":"+1 780 675 5378",
    "sg:postcode":"T9S 2B5",
    "sg:province":"AB",
    "sg:tags":[
        "cleaners",
        "rug",
        "carpet"
    ],
    "wof:name":"Home & Office Carpet Cleaning",
    "wof:placetype":"venue"
},
  "geometry": {"coordinates":[-113.28351600000001,54.721233],"type":"Point"}
}