{
  "type": "Feature",
  "properties": {
    "iso:country":"CA",
    "sg:address":"2745 Hastings St E",
    "sg:city":"Vancouver",
    "sg:classifiers":[
        {
            "category":"Retail",
            "subcategory":"Laundry & Dry Cleaning",
            "type":"Services"
        }
    ],
    "sg:phone":"+1 604 254 1394",
    "sg:postcode":"V5K 1Z8",
    "sg:province":"BC",
    "sg:tags":[
        "cleaners"
    ],
    "wof:name":"Skye Cleaners",
    "wof:placetype":"venue"
},
  "geometry": {"coordinates":[-123.048058,49.281338],"type":"Point"}
}