{
  "type": "Feature",
  "properties": {
    "iso:country":"CA",
    "sg:city":"Quesnel",
    "sg:classifiers":[
        {
            "category":"Manufacturing",
            "subcategory":"Printing",
            "type":"Manufacturing & Wholesale Goods"
        }
    ],
    "sg:phone":"+1 250 747 2939",
    "sg:postcode":"V2J 6N7",
    "sg:province":"BC",
    "sg:tags":[
        "screen",
        "printer"
    ],
    "wof:name":"Achieve Advertising",
    "wof:placetype":"venue"
},
  "geometry": {"coordinates":[-122.416450501,52.9714393616],"type":"Point"}
}