{
  "type": "Feature",
  "properties": {
    "iso:country":"CA",
    "sg:address":"64 Grand Ave S",
    "sg:city":"Cambridge",
    "sg:classifiers":[
        {
            "category":"Shopping",
            "subcategory":"Clothing, Apparel, & Fashions",
            "type":"Retail Goods"
        }
    ],
    "sg:phone":"+1 519 622 6111",
    "sg:postcode":"N1S 2L8",
    "sg:province":"ON",
    "sg:tags":[
        "infant",
        "wear"
    ],
    "wof:name":"Jack Rabbits Clothing CO",
    "wof:placetype":"venue"
},
  "geometry": {"coordinates":[-80.3177108765,43.3554153442],"type":"Point"}
}