{
  "type": "Feature",
  "properties": {
    "addr:full":"482 Rue Du Quai Val-D'Or QC J9P 4Z5",
    "addr:housenumber":"482",
    "addr:postcode":"j9p 4z5",
    "addr:street":"Rue Du Quai",
    "iso:country":"CA",
    "sg:address":"482 Rue Du Quai",
    "sg:city":"Val-D'Or",
    "sg:classifiers":[
        {
            "category":"Building & Trades",
            "subcategory":"Construction",
            "type":"Services"
        }
    ],
    "sg:phone":"+1 819 825 5035",
    "sg:postcode":"J9P 4Z5",
    "sg:province":"QC",
    "sg:tags":[
        "layer",
        "carpet"
    ],
    "wof:name":"Denis Boucher Couvre-Planchers",
    "wof:placetype":"venue"
},
  "geometry": {"coordinates":[-70.5804138184,48.394405365],"type":"Point"}
}