{
  "type": "Feature",
  "properties": {
    "addr:full":"2519 Ludgate St Victoria BC V8T 4S2",
    "addr:housenumber":"2519",
    "addr:postcode":"v8t 4s2",
    "addr:street":"Ludgate St",
    "iso:country":"CA",
    "sg:address":"2519 Ludgate St",
    "sg:city":"Victoria",
    "sg:classifiers":[
        {
            "category":"Building & Trades",
            "subcategory":"Plumbing",
            "type":"Services"
        }
    ],
    "sg:phone":"+1 250 748 5720",
    "sg:postcode":"V8T 4S2",
    "sg:province":"BC",
    "sg:tags":[
        "contractor"
    ],
    "wof:name":"Miles Plumbing Svc Ltd",
    "wof:placetype":"venue"
},
  "geometry": {"coordinates":[-123.370162964,48.4361724854],"type":"Point"}
}