{
  "type": "Feature",
  "properties": {
    "addr:full":"380 Chrislea Rd Woodbridge ON L4L 8A8",
    "addr:housenumber":"380",
    "addr:postcode":"l4l 8a8",
    "addr:street":"Chrislea Rd",
    "iso:country":"CA",
    "sg:address":"380 Chrislea Rd",
    "sg:city":"Woodbridge",
    "sg:classifiers":[
        {
            "category":"Manufacturing",
            "subcategory":"Tools & Machinery",
            "type":"Manufacturing & Wholesale Goods"
        }
    ],
    "sg:phone":"+1 905 850 1800",
    "sg:postcode":"L4L 8A8",
    "sg:province":"ON",
    "sg:tags":[
        "equipment",
        "baker"
    ],
    "wof:name":"G Cinelli Mfg Corp",
    "wof:placetype":"venue"
},
  "geometry": {"coordinates":[-79.544815,43.800453],"type":"Point"}
}