{
  "type": "Feature",
  "properties": {
    "addr:full":"29989 Dewdney Trunk Rd Mission BC V4S 1B7",
    "addr:housenumber":"29989",
    "addr:postcode":"v4s 1b7",
    "addr:street":"Dewdney Trunk Rd",
    "iso:country":"CA",
    "sg:address":"29989 Dewdney Trunk Rd",
    "sg:city":"Mission",
    "sg:classifiers":[
        {
            "category":"Wholesale",
            "subcategory":"Auto Parts",
            "type":"Manufacturing & Wholesale Goods"
        }
    ],
    "sg:phone":"+1 604 462 7000",
    "sg:postcode":"V4S 1B7",
    "sg:province":"BC",
    "sg:tags":[
        "automobile",
        "wrecking"
    ],
    "wof:name":"Stave Falls Auto Wrecking",
    "wof:placetype":"venue"
},
  "geometry": {"coordinates":[-122.39375305199999,49.2200965881],"type":"Point"}
}