{
  "type": "Feature",
  "properties": {
    "addr:full":"NW 9-26-28W Roblin MB R0L 1P0",
    "addr:postcode":"9-26-28w;r0l 1p0",
    "addr:street":"Nw",
    "iso:country":"CA",
    "sg:address":"NW 9-26-28W",
    "sg:city":"Roblin",
    "sg:classifiers":[
        {
            "category":"Recreation",
            "type":"Entertainment"
        }
    ],
    "sg:phone":"+1 204 937 2463",
    "sg:postcode":"R0L 1P0",
    "sg:province":"MB",
    "sg:tags":[
        "hall",
        "auditorium"
    ],
    "wof:name":"Holy Redeemer Church Parish",
    "wof:placetype":"venue"
},
  "geometry": {"coordinates":[-101.352852,51.228153],"type":"Point"}
}