{
  "type": "Feature",
  "properties": {
    "addr:full":"501 Rideau St Ottawa ON K1N 5Z5",
    "addr:housenumber":"501",
    "addr:postcode":"k1n 5z5",
    "addr:street":"Rideau St",
    "iso:country":"CA",
    "sg:address":"501 Rideau St",
    "sg:city":"Ottawa",
    "sg:classifiers":[
        {
            "category":"Personal",
            "subcategory":"Beauty Salon",
            "type":"Services"
        }
    ],
    "sg:phone":"+1 613 789 6969",
    "sg:postcode":"K1N 5Z5",
    "sg:province":"ON",
    "sg:tags":[
        "school"
    ],
    "wof:name":"Regine",
    "wof:placetype":"venue"
},
  "geometry": {"coordinates":[-75.679039,45.431725],"type":"Point"}
}