{
  "type": "Feature",
  "properties": {
    "iso:country":"CA",
    "sg:address":"12555 Tenth Line N",
    "sg:city":"Stouffville",
    "sg:classifiers":[
        {
            "category":"Wholesale",
            "subcategory":"Meat",
            "type":"Manufacturing & Wholesale Goods"
        }
    ],
    "sg:phone":"+1 905 640 6328",
    "sg:postcode":"L4A 7X3",
    "sg:province":"ON",
    "sg:tags":[
        "butchering"
    ],
    "wof:name":"Country Choice Meats",
    "wof:placetype":"venue"
},
  "geometry": {"coordinates":[-79.232628,43.981766],"type":"Point"}
}