{
  "type": "Feature",
  "properties": {
    "addr:full":"Etobicoke ON M9A 3T7",
    "addr:postcode":"m9a 3t7",
    "iso:country":"CA",
    "sg:city":"Etobicoke",
    "sg:classifiers":[
        {
            "category":"Personal",
            "subcategory":"Tanning Parlor",
            "type":"Services"
        }
    ],
    "sg:phone":"+1 416 234 5599",
    "sg:postcode":"M9A 3T7",
    "sg:province":"ON",
    "sg:tags":[
        "salon",
        "cosmetic",
        "perfume"
    ],
    "wof:name":"Royal Tanning Salon",
    "wof:placetype":"venue"
},
  "geometry": {"coordinates":[-79.52010300000001,43.662872],"type":"Point"}
}