{
  "type": "Feature",
  "properties": {
    "addr:full":"Farm Maidstone SK S0M 1M0",
    "addr:postcode":"s0m 1m0",
    "iso:country":"CA",
    "sg:address":"Farm",
    "sg:city":"Maidstone",
    "sg:classifiers":[
        {
            "category":"Recreation",
            "type":"Entertainment"
        }
    ],
    "sg:phone":"+1 306 893 2730",
    "sg:postcode":"S0M 1M0",
    "sg:province":"SK",
    "sg:tags":[
        "hall",
        "auditorium"
    ],
    "wof:name":"Milliton Community Hall",
    "wof:placetype":"venue"
},
  "geometry": {"coordinates":[-109.29660800000001,53.08746],"type":"Point"}
}