{
  "type": "Feature",
  "properties": {
    "addr:full":"Fort Mcmurray AB T9H 4A6",
    "addr:postcode":"t9h 4a6",
    "iso:country":"CA",
    "sg:city":"Fort Mcmurray",
    "sg:classifiers":[
        {
            "category":"Recreation",
            "type":"Entertainment"
        }
    ],
    "sg:phone":"+1 780 790 1240",
    "sg:postcode":"T9H 4A6",
    "sg:province":"AB",
    "sg:tags":[
        "bingo",
        "game"
    ],
    "wof:name":"Bingo Palace",
    "wof:placetype":"venue"
},
  "geometry": {"coordinates":[-111.336067,56.660988],"type":"Point"}
}