{
  "type": "Feature",
  "properties": {
    "addr:full":"780 Cordova St E Vancouver BC V6A 1M3",
    "addr:housenumber":"780",
    "addr:postcode":"v6a 1m3",
    "addr:street":"Cordova St E",
    "iso:country":"CA",
    "sg:address":"780 Cordova St E",
    "sg:city":"Vancouver",
    "sg:classifiers":[
        {
            "category":"Manufacturing",
            "subcategory":"Musical Instruments",
            "type":"Manufacturing & Wholesale Goods"
        }
    ],
    "sg:phone":"+1 604 253 7111",
    "sg:postcode":"V6A 1M3",
    "sg:province":"BC",
    "wof:name":"Larrivee Guitars",
    "wof:placetype":"venue"
},
  "geometry": {"coordinates":[-123.08767700200001,49.2819442749],"type":"Point"}
}