{
  "type": "Feature",
  "properties": {
    "addr:full":"Vankleek Hill ON K0B 1R0",
    "addr:postcode":"k0b 1r0",
    "iso:country":"CA",
    "sg:city":"Vankleek Hill",
    "sg:classifiers":[
        {
            "category":"Manufacturing",
            "subcategory":"Printing",
            "type":"Manufacturing & Wholesale Goods"
        }
    ],
    "sg:phone":"+1 613 678 3327",
    "sg:postcode":"K0B 1R0",
    "sg:province":"ON",
    "sg:tags":[
        "newspaper"
    ],
    "wof:name":"Review",
    "wof:placetype":"venue"
},
  "geometry": {"coordinates":[-74.6532287598,45.5183982849],"type":"Point"}
}