{
  "type": "Feature",
  "properties": {
    "addr:full":"460 Osborne Beaverton ON L0K 1A0",
    "addr:housenumber":"460",
    "addr:postcode":"l0k 1a0",
    "addr:street":"Osborne",
    "iso:country":"CA",
    "sg:address":"460 Osborne",
    "sg:city":"Beaverton",
    "sg:classifiers":[
        {
            "category":"Food & Beverages",
            "subcategory":"Groceries & Convenience Stores",
            "type":"Retail Goods"
        }
    ],
    "sg:phone":"+1 705 426 2380",
    "sg:postcode":"L0K 1A0",
    "sg:province":"ON",
    "sg:tags":[
        "grocer"
    ],
    "wof:name":"Olde Tyme Northern",
    "wof:placetype":"venue"
},
  "geometry": {"coordinates":[-79.153137207,44.4249382019],"type":"Point"}
}