{
  "type": "Feature",
  "properties": {
    "addr:full":"119 Colborne St W Brantford ON N3T 1K8",
    "addr:housenumber":"119",
    "addr:postcode":"n3t 1k8",
    "addr:street":"Colborne St W",
    "iso:country":"CA",
    "sg:address":"119 Colborne St W",
    "sg:city":"Brantford",
    "sg:classifiers":[
        {
            "category":"Retail",
            "subcategory":"Photofinishing",
            "type":"Services"
        }
    ],
    "sg:phone":"+1 519 759 8133",
    "sg:postcode":"N3T 1K8",
    "sg:province":"ON",
    "sg:tags":[
        "photo",
        "finishing"
    ],
    "wof:name":"Cowell Big V Drug Store",
    "wof:placetype":"venue"
},
  "geometry": {"coordinates":[-80.275307,43.133392],"type":"Point"}
}