{
  "type": "Feature",
  "properties": {
    "addr:full":"28 Rte LA Vallee Memramcook NB E4K 2A8",
    "addr:housenumber":"28",
    "addr:postcode":"e4k 2a8",
    "addr:street":"Rte La Vallee",
    "iso:country":"CA",
    "sg:address":"28 Rte LA Vallee",
    "sg:city":"Memramcook",
    "sg:classifiers":[
        {
            "category":"Retail",
            "subcategory":"Auto Repair",
            "type":"Services"
        }
    ],
    "sg:phone":"+1 506 758 9772",
    "sg:postcode":"E4K 2A8",
    "sg:province":"NB",
    "sg:tags":[
        "repairing",
        "automobile"
    ],
    "wof:name":"Memramcook Auto Svc Ltd",
    "wof:placetype":"venue"
},
  "geometry": {"coordinates":[-64.5568237305,46.002872467],"type":"Point"}
}