{
  "type": "Feature",
  "properties": {
    "addr:full":"537 Rue Notre-Dame O Victoriaville QC G6P 1T2",
    "addr:housenumber":"537",
    "addr:postcode":"g6p 1t2",
    "addr:street":"Rue Notre-Dame O",
    "iso:country":"CA",
    "sg:address":"537 Rue Notre-Dame O",
    "sg:city":"Victoriaville",
    "sg:classifiers":[
        {
            "category":"Education",
            "subcategory":"Dance Studio",
            "type":"Public Place"
        }
    ],
    "sg:phone":"+1 819 758 4053",
    "sg:postcode":"G6P 1T2",
    "sg:province":"QC",
    "sg:tags":[
        "instruction",
        "dancing"
    ],
    "wof:name":"Ecole DE Danse Daniel Moreau",
    "wof:placetype":"venue"
},
  "geometry": {"coordinates":[-71.9436035156,46.0610275269],"type":"Point"}
}