{
  "type": "Feature",
  "properties": {
    "addr:full":"626 Vaughan Rd York ON M6E 2Y3",
    "addr:housenumber":"626",
    "addr:postcode":"m6e 2y3",
    "addr:street":"Vaughan Rd",
    "iso:country":"CA",
    "sg:address":"626 Vaughan Rd",
    "sg:city":"York",
    "sg:classifiers":[
        {
            "category":"Wholesale",
            "subcategory":"Durable Goods & Equipment",
            "type":"Manufacturing & Wholesale Goods"
        }
    ],
    "sg:phone":"+1 416 651 5555",
    "sg:postcode":"M6E 2Y3",
    "sg:province":"ON",
    "sg:tags":[
        "compact",
        "record",
        "disc",
        "tape"
    ],
    "wof:name":"Talento Italiano Gifts Records",
    "wof:placetype":"venue"
},
  "geometry": {"coordinates":[-79.44115447999999,43.6926193237],"type":"Point"}
}