{
  "type": "Feature",
  "properties": {
    "addr:full":"439 Rue DE Bigarre Victoriaville QC G6P 8P1",
    "addr:housenumber":"439",
    "addr:postcode":"g6p 8p1",
    "addr:street":"Rue De Bigarre",
    "iso:country":"CA",
    "sg:address":"439 Rue DE Bigarre",
    "sg:city":"Victoriaville",
    "sg:classifiers":[
        {
            "category":"Autos & Motor Vehicles",
            "subcategory":"Auto Supplies",
            "type":"Retail Goods"
        }
    ],
    "sg:phone":"+1 819 758 5447",
    "sg:postcode":"G6P 8P1",
    "sg:province":"QC",
    "sg:tags":[
        "automobile",
        "parts"
    ],
    "wof:name":"Victo Freins Demarreurs Inc",
    "wof:placetype":"venue"
},
  "geometry": {"coordinates":[-71.947945,46.067883],"type":"Point"}
}