{
  "type": "Feature",
  "properties": {
    "addr:full":"4411 56 St Wetaskiwin AB T9A 1V4",
    "addr:housenumber":"4411",
    "addr:postcode":"t9a 1v4",
    "addr:street":"56 St",
    "iso:country":"CA",
    "sg:address":"4411 56 St",
    "sg:city":"Wetaskiwin",
    "sg:classifiers":[
        {
            "category":"Food & Beverages",
            "subcategory":"Groceries & Convenience Stores",
            "type":"Retail Goods"
        }
    ],
    "sg:phone":"+1 780 352 8700",
    "sg:postcode":"T9A 1V4",
    "sg:province":"AB",
    "wof:name":"Wetaskiwin Shell",
    "wof:placetype":"venue"
},
  "geometry": {"coordinates":[-113.389961243,52.9644889832],"type":"Point"}
}