{
  "type": "Feature",
  "properties": {
    "addr:full":"52 Boul Pabos Pabos QC G0C 2H0",
    "addr:housenumber":"52",
    "addr:postcode":"g0c 2h0",
    "addr:street":"Boul Pabos Pabos",
    "iso:country":"CA",
    "sg:address":"52 Boul Pabos",
    "sg:city":"Pabos",
    "sg:classifiers":[
        {
            "category":"Home & Garden",
            "subcategory":"Building Materials",
            "type":"Retail Goods"
        }
    ],
    "sg:phone":"+1 418 689 2162",
    "sg:postcode":"G0C 2H0",
    "sg:province":"QC",
    "sg:tags":[
        "glass",
        "window",
        "plate"
    ],
    "wof:name":"Duro Vitres & Acces D'Autos",
    "wof:placetype":"venue"
},
  "geometry": {"coordinates":[-64.6541976929,48.3520889282],"type":"Point"}
}