{
  "type": "Feature",
  "properties": {
    "addr:full":"Maple Ridge BC V2X 0T4",
    "addr:postcode":"v2x 0t4",
    "iso:country":"CA",
    "sg:city":"Maple Ridge",
    "sg:classifiers":[
        {
            "category":"Manufacturing",
            "subcategory":"Lumber",
            "type":"Manufacturing & Wholesale Goods"
        }
    ],
    "sg:phone":"+1 604 460 7288",
    "sg:postcode":"V2X 0T4",
    "sg:province":"BC",
    "wof:name":"Modern Pacific Enterprises Inc",
    "wof:placetype":"venue"
},
  "geometry": {"coordinates":[-122.666046143,49.215057373],"type":"Point"}
}