{
  "type": "Feature",
  "properties": {
    "iso:country":"CA",
    "sg:address":"202 Burrows Ave W",
    "sg:city":"Melfort",
    "sg:classifiers":[
        {
            "category":"Government",
            "subcategory":"Office",
            "type":"Public Place"
        }
    ],
    "sg:phone":"+1 306 752 4177",
    "sg:postcode":"S0E 1A0",
    "sg:province":"SK",
    "sg:tags":[
        "village"
    ],
    "wof:name":"Melfort North East Leisure Ctr",
    "wof:placetype":"venue"
},
  "geometry": {"coordinates":[-104.613578796,52.8614044189],"type":"Point"}
}