{
  "type": "Feature",
  "properties": {
    "addr:full":"15 Waller Ave Toronto ON M6S 4Z9",
    "addr:housenumber":"15",
    "addr:postcode":"m6s 4z9",
    "addr:street":"Waller Ave",
    "iso:country":"CA",
    "sg:address":"15 Waller Ave",
    "sg:city":"Toronto",
    "sg:classifiers":[
        {
            "category":"Recreation",
            "type":"Entertainment"
        }
    ],
    "sg:phone":"+1 416 392 6796",
    "sg:postcode":"M6S 4Z9",
    "sg:province":"ON",
    "sg:tags":[
        "pool",
        "swimming"
    ],
    "wof:name":"Toronto Swansea Pool",
    "wof:placetype":"venue"
},
  "geometry": {"coordinates":[-79.47704299999999,43.644135],"type":"Point"}
}