{
  "type": "Feature",
  "properties": {
    "addr:full":"Sault Ste Marie ON P6A 1X3",
    "addr:postcode":"p6a 1x3",
    "iso:country":"CA",
    "sg:city":"Sault Ste Marie",
    "sg:classifiers":[
        {
            "category":"Professional",
            "subcategory":"Accounting & Tax Preparation",
            "type":"Services"
        }
    ],
    "sg:phone":"+1 705 945 9700",
    "sg:postcode":"P6A 1X3",
    "sg:province":"ON",
    "sg:tags":[
        "accountant"
    ],
    "wof:name":"Grant Thornton Llp",
    "wof:placetype":"venue"
},
  "geometry": {"coordinates":[-84.335083,46.51104],"type":"Point"}
}