{
  "type": "Feature",
  "properties": {
    "addr:full":"571 Arlington Ave York ON M6C 3A6",
    "addr:housenumber":"571",
    "addr:postcode":"m6c 3a6",
    "addr:street":"Arlington Ave",
    "iso:country":"CA",
    "sg:address":"571 Arlington Ave",
    "sg:city":"York",
    "sg:classifiers":[
        {
            "category":"Organizations",
            "subcategory":"Non-profit Organization",
            "type":"Services"
        }
    ],
    "sg:phone":"+1 416 654 5494",
    "sg:postcode":"M6C 3A6",
    "sg:province":"ON",
    "sg:tags":[
        "disability"
    ],
    "wof:name":"Avta",
    "wof:placetype":"venue"
},
  "geometry": {"coordinates":[-79.43438,43.694637],"type":"Point"}
}