{
  "type": "Feature",
  "properties": {
    "iso:country":"CA",
    "sg:address":"150 Rue Leonard",
    "sg:city":"Mont-Tremblant",
    "sg:classifiers":[
        {
            "category":"Social Services",
            "type":"Services"
        }
    ],
    "sg:phone":"+1 819 425 9521",
    "sg:postcode":"J8E 3K1",
    "sg:province":"QC",
    "sg:tags":[
        "senior",
        "citizen"
    ],
    "wof:name":"Residences Leonard",
    "wof:placetype":"venue"
},
  "geometry": {"coordinates":[-74.59586334230001,46.1199531555],"type":"Point"}
}