{
  "type": "Feature",
  "properties": {
    "iso:country":"CA",
    "sg:address":"810 Rue Bombardier",
    "sg:city":"Mascouche",
    "sg:classifiers":[
        {
            "category":"Home & Garden",
            "subcategory":"Building Materials",
            "type":"Retail Goods"
        }
    ],
    "sg:phone":"+1 450 966 9970",
    "sg:postcode":"J7K 1X9",
    "sg:province":"QC",
    "sg:tags":[
        "door",
        "gate",
        "operating",
        "devices"
    ],
    "wof:name":"Entra-Matic Inc",
    "wof:placetype":"venue"
},
  "geometry": {"coordinates":[-73.59354400629999,45.7391967773],"type":"Point"}
}