{
  "type": "Feature",
  "properties": {
    "addr:full":"Woodstock ON N4S 4Y3",
    "addr:postcode":"n4s 4y3",
    "iso:country":"CA",
    "sg:city":"Woodstock",
    "sg:classifiers":[
        {
            "category":"Health Services",
            "subcategory":"Doctor",
            "type":"Services"
        }
    ],
    "sg:phone":"+1 519 537 3871",
    "sg:postcode":"N4S 4Y3",
    "sg:province":"ON",
    "sg:tags":[
        "physician",
        "surgeon"
    ],
    "wof:name":"Szasz, John MD",
    "wof:placetype":"venue"
},
  "geometry": {"coordinates":[-80.755028,43.13699],"type":"Point"}
}