{
  "type": "Feature",
  "properties": {
    "iso:country":"CA",
    "sg:address":"555 Rexdale Blvd",
    "sg:city":"Etobicoke",
    "sg:classifiers":[
        {
            "category":"Retail",
            "subcategory":"Animal Services",
            "type":"Services"
        }
    ],
    "sg:phone":"+1 416 675 4546",
    "sg:postcode":"M9W 7G3",
    "sg:province":"ON",
    "sg:tags":[
        "horse",
        "training"
    ],
    "wof:name":"M J Doyle Racing Stables Ltd",
    "wof:placetype":"venue"
},
  "geometry": {"coordinates":[-79.603195,43.718903],"type":"Point"}
}