{
  "type": "Feature",
  "properties": {
    "addr:full":"4898 Boul Taschereau Greenfield Park QC J4V 2J2",
    "addr:housenumber":"4898",
    "addr:postcode":"j4v 2j2",
    "addr:street":"Boul Taschereau",
    "iso:country":"CA",
    "sg:address":"4898 Boul Taschereau",
    "sg:city":"Greenfield Park",
    "sg:classifiers":[
        {
            "category":"Manufacturing",
            "subcategory":"Tools & Machinery",
            "type":"Manufacturing & Wholesale Goods"
        }
    ],
    "sg:phone":"+1 450 466 2166",
    "sg:postcode":"J4V 2J2",
    "sg:province":"QC",
    "sg:tags":[
        "optical",
        "optician"
    ],
    "wof:name":"Lunetterie New Look Inc",
    "wof:placetype":"venue"
},
  "geometry": {"coordinates":[-73.46558400000001,45.483463],"type":"Point"}
}