{
  "type": "Feature",
  "properties": {
    "addr:full":"12516 124 St NW Edmonton AB T5L 0N5",
    "addr:housenumber":"12516",
    "addr:postcode":"t5l 0n5",
    "addr:street":"124 St Nw",
    "iso:country":"CA",
    "sg:address":"12516 124 St NW",
    "sg:city":"Edmonton",
    "sg:classifiers":[
        {
            "category":"Retail",
            "subcategory":"Auto Repair",
            "type":"Services"
        }
    ],
    "sg:phone":"+1 780 452 6477",
    "sg:postcode":"T5L 0N5",
    "sg:province":"AB",
    "sg:tags":[
        "repairing",
        "automobile"
    ],
    "wof:name":"Toptech Automotive Ltd",
    "wof:placetype":"venue"
},
  "geometry": {"coordinates":[-113.536163,53.581085],"type":"Point"}
}