{
  "type": "Feature",
  "properties": {
    "addr:full":"Halifax NS B3L 2H8",
    "addr:postcode":"b3l 2h8",
    "iso:country":"CA",
    "sg:city":"Halifax",
    "sg:classifiers":[
        {
            "category":"Personal",
            "subcategory":"Beauty Salon",
            "type":"Services"
        }
    ],
    "sg:phone":"+1 902 455 6356",
    "sg:postcode":"B3L 2H8",
    "sg:province":"NS",
    "wof:name":"Hair Trends",
    "wof:placetype":"venue"
},
  "geometry": {"coordinates":[-63.619663,44.647785],"type":"Point"}
}