{
  "type": "Feature",
  "properties": {
    "addr:full":"12 Kettle Crt Maple ON L6A 2M2",
    "addr:housenumber":"12",
    "addr:postcode":"l6a 2m2",
    "addr:street":"Kettle Crt",
    "iso:country":"CA",
    "sg:address":"12 Kettle Crt",
    "sg:city":"Maple",
    "sg:classifiers":[
        {
            "category":"Building & Trades",
            "subcategory":"Construction",
            "type":"Services"
        }
    ],
    "sg:phone":"+1 905 303 9009",
    "sg:postcode":"L6A 2M2",
    "sg:province":"ON",
    "sg:tags":[
        "home",
        "improvement"
    ],
    "wof:name":"Mkcc Renovations",
    "wof:placetype":"venue"
},
  "geometry": {"coordinates":[-79.53299,43.864029],"type":"Point"}
}