{
  "type": "Feature",
  "properties": {
    "addr:full":"1885 Rue Skiroule Wickham QC J0C 1S0",
    "addr:housenumber":"1885",
    "addr:postcode":"j0c 1s0",
    "addr:street":"Rue Skiroule",
    "iso:country":"CA",
    "sg:address":"1885 Rue Skiroule",
    "sg:city":"Wickham",
    "sg:classifiers":[
        {
            "category":"Wholesale",
            "subcategory":"Construction Materials",
            "type":"Manufacturing & Wholesale Goods"
        }
    ],
    "sg:phone":"+1 819 398 6999",
    "sg:postcode":"J0C 1S0",
    "sg:province":"QC",
    "sg:tags":[
        "pallet",
        "skid",
        "business"
    ],
    "wof:name":"Enterprises Gmo",
    "wof:placetype":"venue"
},
  "geometry": {"coordinates":[-72.49890136720001,45.7596511841],"type":"Point"}
}