{
  "type": "Feature",
  "properties": {
    "addr:full":"7 Rue DE LA Mer Baie-Des-Sables QC G0J 1C0",
    "addr:housenumber":"7",
    "addr:postcode":"g0j 1c0",
    "addr:street":"Rue De La Mer",
    "iso:country":"CA",
    "sg:address":"7 Rue DE LA Mer",
    "sg:city":"Baie-Des-Sables",
    "sg:classifiers":[
        {
            "category":"Freight",
            "type":"Transportation"
        }
    ],
    "sg:phone":"+1 418 772 6261",
    "sg:postcode":"G0J 1C0",
    "sg:province":"QC",
    "sg:tags":[
        "building",
        "house",
        "mover"
    ],
    "wof:name":"Entreprises Gabriel Raymond",
    "wof:placetype":"venue"
},
  "geometry": {"coordinates":[-67.910416,48.711689],"type":"Point"}
}