{
  "type": "Feature",
  "properties": {
    "addr:full":"1810 Boul Cardinal-Villeneuve Quebec QC G1L 3H1",
    "addr:housenumber":"1810",
    "addr:postcode":"g1l 3h1",
    "addr:street":"Boul Cardinal-Villeneuve",
    "iso:country":"CA",
    "sg:address":"1810 Boul Cardinal-Villeneuve",
    "sg:city":"Quebec",
    "sg:classifiers":[
        {
            "category":"Shopping",
            "subcategory":"Computers & Home Electronics",
            "type":"Retail Goods"
        }
    ],
    "sg:phone":"+1 418 522 1444",
    "sg:postcode":"G1L 3H1",
    "sg:province":"QC",
    "sg:tags":[
        "video",
        "disc",
        "tape",
        "equipment"
    ],
    "wof:name":"Video Eclair",
    "wof:placetype":"venue"
},
  "geometry": {"coordinates":[-71.23569488530001,46.8313446045],"type":"Point"}
}