{
  "type": "Feature",
  "properties": {
    "addr:full":"73 Queen St Charlottetown PE C1A 4A8",
    "addr:housenumber":"73",
    "addr:postcode":"c1a 4a8",
    "addr:street":"Queen St",
    "iso:country":"CA",
    "sg:address":"73 Queen St",
    "sg:city":"Charlottetown",
    "sg:classifiers":[
        {
            "category":"Restaurant",
            "type":"Food & Drink"
        }
    ],
    "sg:phone":"+1 902 892 2527",
    "sg:postcode":"C1A 4A8",
    "sg:province":"PE",
    "wof:name":"Canton Cafe",
    "wof:placetype":"venue"
},
  "geometry": {"coordinates":[-63.125992,46.232742],"type":"Point"}
}