{
  "type": "Feature",
  "properties": {
    "addr:full":"2757 20 Ave Saint-Prosper-DE-Dorchester QC G0M 1Y0",
    "addr:housenumber":"2757",
    "addr:postcode":"g0m 1y0",
    "addr:street":"20 Ave",
    "iso:country":"CA",
    "sg:address":"2757 20 Ave",
    "sg:city":"Saint-Prosper-DE-Dorchester",
    "sg:classifiers":[
        {
            "category":"Health Services",
            "subcategory":"Doctor",
            "type":"Services"
        }
    ],
    "sg:phone":"+1 418 594 8262",
    "sg:postcode":"G0M 1Y0",
    "sg:province":"QC",
    "sg:tags":[
        "dentist"
    ],
    "wof:name":"Leblanc, Daniel DDS",
    "wof:placetype":"venue"
},
  "geometry": {"coordinates":[-70.49774932859999,46.2215538025],"type":"Point"}
}