{
  "type": "Feature",
  "properties": {
    "addr:full":"6750 88 Ave NW Edmonton AB T6B 0M2",
    "addr:housenumber":"6750",
    "addr:postcode":"t6b 0m2",
    "addr:street":"88 Ave Nw",
    "iso:country":"CA",
    "sg:address":"6750 88 Ave NW",
    "sg:city":"Edmonton",
    "sg:classifiers":[
        {
            "category":"Recreation",
            "type":"Entertainment"
        }
    ],
    "sg:phone":"+1 780 466 8166",
    "sg:postcode":"T6B 0M2",
    "sg:province":"AB",
    "sg:tags":[
        "hall",
        "auditorium"
    ],
    "wof:name":"Argyll Community League",
    "wof:placetype":"venue"
},
  "geometry": {"coordinates":[-113.431,53.523586],"type":"Point"}
}