{
  "type": "Feature",
  "properties": {
    "addr:full":"1830 Main St Winnipeg MB R2V 3H2",
    "addr:housenumber":"1830",
    "addr:postcode":"r2v 3h2",
    "addr:street":"Main St",
    "iso:country":"CA",
    "sg:address":"1830 Main St",
    "sg:city":"Winnipeg",
    "sg:classifiers":[
        {
            "category":"Retail",
            "subcategory":"Veterinary Services",
            "type":"Services"
        }
    ],
    "sg:phone":"+1 204 334 7531",
    "sg:postcode":"R2V 3H2",
    "sg:province":"MB",
    "sg:tags":[
        "veterinarian"
    ],
    "wof:name":"Seven Oaks Veterinary Hospital",
    "wof:placetype":"venue"
},
  "geometry": {"coordinates":[-97.11647033689999,49.9386177063],"type":"Point"}
}