{
  "type": "Feature",
  "properties": {
    "iso:country":"CA",
    "sg:address":"10523 108 St NW",
    "sg:city":"Edmonton",
    "sg:classifiers":[
        {
            "category":"Local Transit",
            "type":"Transportation"
        }
    ],
    "sg:phone":"+1 780 429 6191",
    "sg:postcode":"T5H 2Z8",
    "sg:province":"AB",
    "sg:tags":[
        "ambulance"
    ],
    "wof:name":"Inter-Hospital Ambulance Svc",
    "wof:placetype":"venue"
},
  "geometry": {"coordinates":[-113.50654602,53.548210144],"type":"Point"}
}