{
  "type": "Feature",
  "properties": {
    "addr:full":"134 Lakeshore Blvd Kingston ON K7M 6R5",
    "addr:housenumber":"134",
    "addr:postcode":"k7m 6r5",
    "addr:street":"Lakeshore Blvd",
    "iso:country":"CA",
    "sg:address":"134 Lakeshore Blvd",
    "sg:city":"Kingston",
    "sg:classifiers":[
        {
            "category":"Building & Trades",
            "subcategory":"Construction",
            "type":"Services"
        }
    ],
    "sg:phone":"+1 613 389 8079",
    "sg:postcode":"K7M 6R5",
    "sg:province":"ON",
    "sg:tags":[
        "masonry",
        "contractor",
        "general"
    ],
    "wof:name":"Salavatore Reino Mason Contrs",
    "wof:placetype":"venue"
},
  "geometry": {"coordinates":[-76.5748214722,44.2155075073],"type":"Point"}
}