{
  "type": "Feature",
  "properties": {
    "iso:country":"CA",
    "sg:address":"545 Rang Saint-Louis",
    "sg:city":"Dolbeau-Mistassini",
    "sg:classifiers":[
        {
            "category":"Utilities",
            "subcategory":"Refuse",
            "type":"Services"
        }
    ],
    "sg:phone":"+1 418 276 1100",
    "sg:postcode":"G8L 5H6",
    "sg:province":"QC",
    "sg:tags":[
        "garbage",
        "collection"
    ],
    "wof:name":"Transports Sanitaires Ml",
    "wof:placetype":"venue"
},
  "geometry": {"coordinates":[-72.20924377439999,48.9078407288],"type":"Point"}
}