{
  "type": "Feature",
  "properties": {
    "iso:country":"CA",
    "sg:city":"Aylmer",
    "sg:classifiers":[
        {
            "category":"Health Services",
            "subcategory":"Doctor",
            "type":"Services"
        }
    ],
    "sg:phone":"+1 819 682 7952",
    "sg:postcode":"J9H 3M7",
    "sg:province":"QC",
    "sg:tags":[
        "physician",
        "surgeon"
    ],
    "wof:name":"Quintal",
    "wof:placetype":"venue"
},
  "geometry": {"coordinates":[-75.841331,45.395287],"type":"Point"}
}