{
  "type": "Feature",
  "properties": {
    "addr:full":"62 Elgin Ave E Goderich ON N7A 1K2",
    "addr:housenumber":"62",
    "addr:postcode":"n7a 1k2",
    "addr:street":"Elgin Ave E",
    "iso:country":"CA",
    "sg:address":"62 Elgin Ave E",
    "sg:city":"Goderich",
    "sg:classifiers":[
        {
            "category":"Shopping",
            "type":"Retail Goods"
        }
    ],
    "sg:phone":"+1 519 524 8457",
    "sg:postcode":"N7A 1K2",
    "sg:province":"ON",
    "sg:tags":[
        "monument"
    ],
    "wof:name":"Stratford Memorials Ltd",
    "wof:placetype":"venue"
},
  "geometry": {"coordinates":[-81.70871,43.740414],"type":"Point"}
}