{
  "type": "Feature",
  "properties": {
    "addr:full":"PO Box 505 Vilna AB T0A 3L0",
    "addr:housenumber":"po",
    "addr:postcode":"t0a 3l0",
    "addr:street":"Box 505",
    "iso:country":"CA",
    "sg:address":"PO Box 505",
    "sg:city":"Vilna",
    "sg:classifiers":[
        {
            "category":"Wholesale",
            "subcategory":"Scrap",
            "type":"Manufacturing & Wholesale Goods"
        }
    ],
    "sg:phone":"+1 780 636 3632",
    "sg:postcode":"T0A 3L0",
    "sg:province":"AB",
    "sg:tags":[
        "recycling",
        "can",
        "bottle",
        "depot"
    ],
    "wof:name":"Vilna Bottle Depot",
    "wof:placetype":"venue"
},
  "geometry": {"coordinates":[-111.91909,54.114029],"type":"Point"}
}