{
  "type": "Feature",
  "properties": {
    "addr:full":"Waterloo ON N2L 2R5",
    "addr:postcode":"n2l 2r5",
    "iso:country":"CA",
    "sg:city":"Waterloo",
    "sg:classifiers":[
        {
            "category":"Health Services",
            "subcategory":"Doctor",
            "type":"Services"
        }
    ],
    "sg:phone":"+1 519 886 2760",
    "sg:postcode":"N2L 2R5",
    "sg:province":"ON",
    "sg:tags":[
        "physician",
        "surgeon"
    ],
    "wof:name":"Bateman, Charles R MD",
    "wof:placetype":"venue"
},
  "geometry": {"coordinates":[-80.5383529663,43.4614562988],"type":"Point"}
}