{
  "type": "Feature",
  "properties": {
    "addr:full":"Highway 50 Alonsa MB R0H 0A0",
    "addr:postcode":"r0h 0a0",
    "addr:street":"Highway 50 Alonsa",
    "iso:country":"CA",
    "sg:address":"Highway 50",
    "sg:city":"Alonsa",
    "sg:classifiers":[
        {
            "category":"Retail",
            "subcategory":"Veterinary Services",
            "type":"Services"
        }
    ],
    "sg:phone":"+1 204 767 2286",
    "sg:postcode":"R0H 0A0",
    "sg:province":"MB",
    "sg:tags":[
        "veterinarian"
    ],
    "wof:name":"Inter-Ridge Veterinary Clinic",
    "wof:placetype":"venue"
},
  "geometry": {"coordinates":[-99.084671,50.879143],"type":"Point"}
}