{
  "type": "Feature",
  "properties": {
    "addr:full":"Bonnyville AB T9N 2G8",
    "addr:postcode":"t9n 2g8",
    "iso:country":"CA",
    "sg:city":"Bonnyville",
    "sg:classifiers":[
        {
            "category":"Organizations",
            "subcategory":"Religious Organization",
            "type":"Services"
        }
    ],
    "sg:phone":"+1 780 826 3542",
    "sg:postcode":"T9N 2G8",
    "sg:province":"AB",
    "sg:tags":[
        "church"
    ],
    "wof:name":"Alliance Church",
    "wof:placetype":"venue"
},
  "geometry": {"coordinates":[-110.713058,54.268108],"type":"Point"}
}