{
  "type": "Feature",
  "properties": {
    "iso:country":"CA",
    "sg:address":"5 Race St",
    "sg:city":"St Catharines",
    "sg:classifiers":[
        {
            "category":"Insurance",
            "subcategory":"Insurance Agent",
            "type":"Services"
        }
    ],
    "sg:phone":"+1 905 704 0812",
    "sg:postcode":"L2R 3M1",
    "sg:province":"ON",
    "wof:name":"B & G Life Brokerage Inc",
    "wof:placetype":"venue"
},
  "geometry": {"coordinates":[-79.240852,43.158672],"type":"Point"}
}