{
  "type": "Feature",
  "properties": {
    "addr:full":"33 Centre St Gimli MB R0C 1B0",
    "addr:housenumber":"33",
    "addr:postcode":"r0c 1b0",
    "addr:street":"Centre St",
    "iso:country":"CA",
    "sg:address":"33 Centre St",
    "sg:city":"Gimli",
    "sg:classifiers":[
        {
            "category":"Real Estate",
            "subcategory":"Surveying",
            "type":"Services"
        }
    ],
    "sg:phone":"+1 204 642 5341",
    "sg:postcode":"R0C 1B0",
    "sg:province":"MB",
    "sg:tags":[
        "surveyor"
    ],
    "wof:name":"Isaac & Denchuk",
    "wof:placetype":"venue"
},
  "geometry": {"coordinates":[-96.985527,50.631985],"type":"Point"}
}