{
  "type": "Feature",
  "properties": {
    "addr:full":"100 Castlehill Rd Brampton ON L6X 4C7",
    "addr:housenumber":"100",
    "addr:postcode":"l6x 4c7",
    "addr:street":"Castlehill Rd",
    "iso:country":"CA",
    "sg:address":"100 Castlehill Rd",
    "sg:city":"Brampton",
    "sg:classifiers":[
        {
            "category":"Freight",
            "type":"Transportation"
        }
    ],
    "sg:phone":"+1 905 457 0858",
    "sg:postcode":"L6X 4C7",
    "sg:province":"ON",
    "sg:tags":[
        "automobile",
        "transporter",
        "drive",
        "trucking"
    ],
    "wof:name":"B & H Transfer",
    "wof:placetype":"venue"
},
  "geometry": {"coordinates":[-79.788055,43.679825],"type":"Point"}
}