{
  "type": "Feature",
  "properties": {
    "addr:full":"1 Highway 28 Gold River BC V0P 1G0",
    "addr:housenumber":"1",
    "addr:postcode":"v0p 1g0",
    "addr:street":"Highway 28",
    "iso:country":"CA",
    "sg:address":"1 Highway 28",
    "sg:city":"Gold River",
    "sg:classifiers":[
        {
            "category":"Government",
            "subcategory":"Office",
            "type":"Public Place"
        }
    ],
    "sg:phone":"+1 250 283 2418",
    "sg:postcode":"V0P 1G0",
    "sg:province":"BC",
    "sg:tags":[
        "village"
    ],
    "wof:name":"Gold River Tourist Infocentre",
    "wof:placetype":"venue"
},
  "geometry": {"coordinates":[-126.050186157,49.7768363953],"type":"Point"}
}