{
  "type": "Feature",
  "properties": {
    "iso:country":"CA",
    "sg:city":"Hamilton",
    "sg:classifiers":[
        {
            "category":"Shopping",
            "subcategory":"Clothing, Apparel, & Fashions",
            "type":"Retail Goods"
        }
    ],
    "sg:phone":"+1 905 526 1455",
    "sg:postcode":"L8P 1A1",
    "sg:province":"ON",
    "wof:name":"Kimberly Fashions",
    "wof:placetype":"venue"
},
  "geometry": {"coordinates":[-79.869217,43.256809],"type":"Point"}
}