{
  "type": "Feature",
  "properties": {
    "addr:full":"2 Louise St Tilbury ON N0P 2L0",
    "addr:housenumber":"2",
    "addr:postcode":"n0p 2l0",
    "addr:street":"Louise St",
    "iso:country":"CA",
    "sg:address":"2 Louise St",
    "sg:city":"Tilbury",
    "sg:classifiers":[
        {
            "category":"Retail",
            "subcategory":"Veterinary Services",
            "type":"Services"
        }
    ],
    "sg:phone":"+1 519 682 3556",
    "sg:postcode":"N0P 2L0",
    "sg:province":"ON",
    "sg:tags":[
        "veterinarian"
    ],
    "wof:name":"Tilbury Veterinary Clinic",
    "wof:placetype":"venue"
},
  "geometry": {"coordinates":[-82.4323730469,42.2629051208],"type":"Point"}
}