{
  "type": "Feature",
  "properties": {
    "addr:full":"Kincardine ON N2Z 2Z4",
    "addr:postcode":"n2z 2z4",
    "iso:country":"CA",
    "sg:city":"Kincardine",
    "sg:classifiers":[
        {
            "category":"Social Services",
            "type":"Services"
        }
    ],
    "sg:phone":"+1 519 396 9655",
    "sg:postcode":"N2Z 2Z4",
    "sg:province":"ON",
    "sg:tags":[
        "organization",
        "welfare"
    ],
    "wof:name":"Women's House of Bruce County",
    "wof:placetype":"venue"
},
  "geometry": {"coordinates":[-81.6317367554,44.1816139221],"type":"Point"}
}