{
  "type": "Feature",
  "properties": {
    "addr:full":"220 George St Sarnia ON N7T 4N9",
    "addr:housenumber":"220",
    "addr:postcode":"n7t 4n9",
    "addr:street":"George St",
    "iso:country":"CA",
    "sg:address":"220 George St",
    "sg:city":"Sarnia",
    "sg:classifiers":[
        {
            "category":"Organizations",
            "subcategory":"Religious Organization",
            "type":"Services"
        }
    ],
    "sg:phone":"+1 519 344 4561",
    "sg:postcode":"N7T 4N9",
    "sg:province":"ON",
    "sg:tags":[
        "church"
    ],
    "wof:name":"Central United Church",
    "wof:placetype":"venue"
},
  "geometry": {"coordinates":[-82.402962,42.974598],"type":"Point"}
}