{
  "type": "Feature",
  "properties": {
    "addr:full":"571 Vaughan Rd York ON M6C 2R4",
    "addr:housenumber":"571",
    "addr:postcode":"m6c 2r4",
    "addr:street":"Vaughan Rd",
    "iso:country":"CA",
    "sg:address":"571 Vaughan Rd",
    "sg:city":"York",
    "sg:classifiers":[
        {
            "category":"Restaurant",
            "type":"Food & Drink"
        }
    ],
    "sg:phone":"+1 416 651 6727",
    "sg:postcode":"M6C 2R4",
    "sg:province":"ON",
    "wof:name":"Paradise Place",
    "wof:placetype":"venue"
},
  "geometry": {"coordinates":[-79.438949585,43.6917190552],"type":"Point"}
}