{
  "type": "Feature",
  "properties": {
    "iso:country":"CA",
    "sg:address":"578 Maryland St",
    "sg:city":"Winnipeg",
    "sg:classifiers":[
        {
            "category":"Personal",
            "subcategory":"Barber",
            "type":"Services"
        }
    ],
    "sg:phone":"+1 204 775 7443",
    "sg:postcode":"R3G 1M5",
    "sg:province":"MB",
    "wof:name":"Jeffrey's Barber Shop",
    "wof:placetype":"venue"
},
  "geometry": {"coordinates":[-97.1602020264,49.8957939148],"type":"Point"}
}