{
  "type": "Feature",
  "properties": {
    "addr:full":"6415 Main St Vancouver BC V5W 2V5",
    "addr:housenumber":"6415",
    "addr:postcode":"v5w 2v5",
    "addr:street":"Main St",
    "iso:country":"CA",
    "sg:address":"6415 Main St",
    "sg:city":"Vancouver",
    "sg:classifiers":[
        {
            "category":"Personal",
            "subcategory":"Beauty Salon",
            "type":"Services"
        }
    ],
    "sg:phone":"+1 604 324 9792",
    "sg:postcode":"V5W 2V5",
    "sg:province":"BC",
    "wof:name":"Meenus Beauty Salon",
    "wof:placetype":"venue"
},
  "geometry": {"coordinates":[-123.101707,49.226521],"type":"Point"}
}