{
  "type": "Feature",
  "properties": {
    "iso:country":"CA",
    "sg:city":"Westbank",
    "sg:classifiers":[
        {
            "category":"Social Services",
            "type":"Services"
        }
    ],
    "sg:phone":"+1 250 768 4838",
    "sg:postcode":"V4T 2H3",
    "sg:province":"BC",
    "sg:tags":[
        "youth",
        "organization",
        "center"
    ],
    "wof:name":"Okanagan Youth Society",
    "wof:placetype":"venue"
},
  "geometry": {"coordinates":[-119.59452819800001,49.8404464722],"type":"Point"}
}