{
  "type": "Feature",
  "properties": {
    "addr:full":"3980 North Fraser Way Burnaby BC V5J 5K5",
    "addr:housenumber":"3980",
    "addr:postcode":"v5j 5k5",
    "addr:street":"North Fraser Way",
    "iso:country":"CA",
    "sg:address":"3980 North Fraser Way",
    "sg:city":"Burnaby",
    "sg:classifiers":[
        {
            "category":"Wholesale",
            "subcategory":"Hardware",
            "type":"Manufacturing & Wholesale Goods"
        }
    ],
    "sg:phone":"+1 604 419 4300",
    "sg:postcode":"V5J 5K5",
    "sg:province":"BC",
    "sg:tags":[
        "lock",
        "locksmith"
    ],
    "wof:name":"Weiser Inc",
    "wof:placetype":"venue"
},
  "geometry": {"coordinates":[-123.013000488,49.2000923157],"type":"Point"}
}