{
  "type": "Feature",
  "properties": {
    "addr:full":"276 George St E Bothwell ON N0P 1C0",
    "addr:housenumber":"276",
    "addr:postcode":"n0p 1c0",
    "addr:street":"George St",
    "iso:country":"CA",
    "sg:address":"276 George St E",
    "sg:city":"Bothwell",
    "sg:classifiers":[
        {
            "category":"Building & Trades",
            "subcategory":"Construction",
            "type":"Services"
        }
    ],
    "sg:phone":"+1 519 695 2847",
    "sg:postcode":"N0P 1C0",
    "sg:province":"ON",
    "sg:tags":[
        "excavating",
        "contractor"
    ],
    "wof:name":"Ross Mc Donald Trenching Svc",
    "wof:placetype":"venue"
},
  "geometry": {"coordinates":[-81.865585,42.632133],"type":"Point"}
}