{
  "type": "Feature",
  "properties": {
    "addr:full":"North Island Hwy Campbell River BC V9W 5C1",
    "addr:postcode":"v9w 5c1",
    "addr:street":"North Island Hwy",
    "iso:country":"CA",
    "sg:address":"North Island Hwy",
    "sg:city":"Campbell River",
    "sg:classifiers":[
        {
            "category":"Manufacturing",
            "subcategory":"Watercraft",
            "type":"Manufacturing & Wholesale Goods"
        }
    ],
    "sg:phone":"+1 250 286 3370",
    "sg:postcode":"V9W 5C1",
    "sg:province":"BC",
    "sg:tags":[
        "barge"
    ],
    "wof:name":"Campbell River Marine Terminal",
    "wof:placetype":"venue"
},
  "geometry": {"coordinates":[-125.287857,50.066353],"type":"Point"}
}