{
  "type": "Feature",
  "properties": {
    "addr:full":"10727 107 Ave NW Edmonton AB T5H 0W6",
    "addr:housenumber":"10727",
    "addr:postcode":"t5h 0w6",
    "addr:street":"107 Ave Nw",
    "iso:country":"CA",
    "sg:address":"10727 107 Ave NW",
    "sg:city":"Edmonton",
    "sg:classifiers":[
        {
            "category":"Personal",
            "subcategory":"Beauty Salon",
            "type":"Services"
        }
    ],
    "sg:phone":"+1 780 425 6216",
    "sg:postcode":"T5H 0W6",
    "sg:province":"AB",
    "wof:name":"Lina Hair Design",
    "wof:placetype":"venue"
},
  "geometry": {"coordinates":[-113.505318,53.551292],"type":"Point"}
}