{
  "type": "Feature",
  "properties": {
    "iso:country":"CA",
    "sg:address":"10423 79 Ave NW",
    "sg:city":"Edmonton",
    "sg:classifiers":[
        {
            "category":"Shopping",
            "subcategory":"Bicycles & Sporting Goods",
            "type":"Retail Goods"
        }
    ],
    "sg:phone":"+1 780 432 0711",
    "sg:postcode":"T6E 1R7",
    "sg:province":"AB",
    "sg:tags":[
        "equipment",
        "skiing"
    ],
    "wof:name":"Sundance Ski & Snowboard",
    "wof:placetype":"venue"
},
  "geometry": {"coordinates":[-113.498481751,53.5149421692],"type":"Point"}
}