{
  "type": "Feature",
  "properties": {
    "addr:full":"93 Hastings St N Bancroft ON K0L 1C0",
    "addr:housenumber":"93",
    "addr:postcode":"k0l 1c0",
    "addr:street":"Hastings St N",
    "iso:country":"CA",
    "sg:address":"93 Hastings St N",
    "sg:city":"Bancroft",
    "sg:classifiers":[
        {
            "category":"Manufacturing",
            "subcategory":"Printing",
            "type":"Manufacturing & Wholesale Goods"
        }
    ],
    "sg:phone":"+1 613 332 2300",
    "sg:postcode":"K0L 1C0",
    "sg:province":"ON",
    "sg:tags":[
        "newspaper"
    ],
    "wof:name":"Bancroft Times",
    "wof:placetype":"venue"
},
  "geometry": {"coordinates":[-77.8546218872,45.0591659546],"type":"Point"}
}