{
  "type": "Feature",
  "properties": {
    "addr:full":"518 Sackville Dr Lower Sackville NS B4C 2R8",
    "addr:housenumber":"518",
    "addr:postcode":"b4c 2r8",
    "addr:street":"Sackville Dr",
    "iso:country":"CA",
    "sg:address":"518 Sackville Dr",
    "sg:city":"Lower Sackville",
    "sg:classifiers":[
        {
            "category":"Banks & Credit Unions",
            "subcategory":"Bank",
            "type":"Services"
        }
    ],
    "sg:phone":"+1 902 864 2228",
    "sg:postcode":"B4C 2R8",
    "sg:province":"NS",
    "wof:name":"Scotiabank",
    "wof:placetype":"venue"
},
  "geometry": {"coordinates":[-63.682007,44.766155],"type":"Point"}
}