{
  "type": "Feature",
  "properties": {
    "iso:country":"CA",
    "sg:city":"Richmond",
    "sg:classifiers":[
        {
            "category":"Restaurant",
            "type":"Food & Drink"
        }
    ],
    "sg:phone":"+1 604 278 3990",
    "sg:postcode":"V6X 3X2",
    "sg:province":"BC",
    "sg:tags":[
        "shop",
        "coffee"
    ],
    "wof:name":"Kampery Coffee Chateau",
    "wof:placetype":"venue"
},
  "geometry": {"coordinates":[-123.13401794400001,49.1868286133],"type":"Point"}
}