{
  "type": "Feature",
  "properties": {
    "addr:full":"200 Ronson Dr Etobicoke ON M9W 5Z9",
    "addr:housenumber":"200",
    "addr:postcode":"m9w 5z9",
    "addr:street":"Ronson Dr",
    "iso:country":"CA",
    "sg:address":"200 Ronson Dr",
    "sg:city":"Etobicoke",
    "sg:classifiers":[
        {
            "category":"Building & Trades",
            "subcategory":"Construction",
            "type":"Services"
        }
    ],
    "sg:phone":"+1 416 243 3434",
    "sg:postcode":"M9W 5Z9",
    "sg:province":"ON",
    "sg:tags":[
        "contractor"
    ],
    "wof:name":"Coram Construction Group",
    "wof:placetype":"venue"
},
  "geometry": {"coordinates":[-79.568344,43.694363],"type":"Point"}
}