{
  "type": "Feature",
  "properties": {
    "addr:full":"48 Fairway Cres Amherstburg ON N9V 3T6",
    "addr:housenumber":"48",
    "addr:postcode":"n9v 3t6",
    "addr:street":"Fairway Cres",
    "iso:country":"CA",
    "sg:address":"48 Fairway Cres",
    "sg:city":"Amherstburg",
    "sg:classifiers":[
        {
            "category":"Professional",
            "subcategory":"Accounting & Tax Preparation",
            "type":"Services"
        }
    ],
    "sg:phone":"+1 519 736 8659",
    "sg:postcode":"N9V 3T6",
    "sg:province":"ON",
    "sg:tags":[
        "accountant"
    ],
    "wof:name":"Anderdon Financial Svc",
    "wof:placetype":"venue"
},
  "geometry": {"coordinates":[-83.10404200000001,42.140362],"type":"Point"}
}