{
  "type": "Feature",
  "properties": {
    "addr:full":"4625 59 St Stettler AB T0C 2L1",
    "addr:housenumber":"4625",
    "addr:postcode":"t0c 2l1",
    "addr:street":"59 St",
    "iso:country":"CA",
    "sg:address":"4625 59 St",
    "sg:city":"Stettler",
    "sg:classifiers":[
        {
            "category":"Travel",
            "subcategory":"Hotels & Motels",
            "type":"Entertainment"
        }
    ],
    "sg:phone":"+1 403 742 3401",
    "sg:postcode":"T0C 2L1",
    "sg:province":"AB",
    "wof:name":"Heartland Lodge",
    "wof:placetype":"venue"
},
  "geometry": {"coordinates":[-112.718666,52.320637],"type":"Point"}
}