{
  "type": "Feature",
  "properties": {
    "addr:full":"Calgary AB T2C 2N4",
    "addr:postcode":"t2c 2n4",
    "iso:country":"CA",
    "sg:city":"Calgary",
    "sg:classifiers":[
        {
            "category":"Manufacturing",
            "subcategory":"Metals",
            "type":"Manufacturing & Wholesale Goods"
        }
    ],
    "sg:phone":"+1 403 279 2275",
    "sg:postcode":"T2C 2N4",
    "sg:province":"AB",
    "sg:tags":[
        "barrels",
        "drum"
    ],
    "wof:name":"Alberta Drum Inc",
    "wof:placetype":"venue"
},
  "geometry": {"coordinates":[-113.96985599999999,50.969406],"type":"Point"}
}