{
  "type": "Feature",
  "properties": {
    "addr:full":"2122 Highview Dr Burlington ON L7R 3X4",
    "addr:housenumber":"2122",
    "addr:postcode":"l7r 3x4",
    "addr:street":"Highview Dr",
    "iso:country":"CA",
    "sg:address":"2122 Highview Dr",
    "sg:city":"Burlington",
    "sg:classifiers":[
        {
            "category":"Manufacturing",
            "subcategory":"Printing",
            "type":"Manufacturing & Wholesale Goods"
        }
    ],
    "sg:phone":"+1 905 335 3359",
    "sg:postcode":"L7R 3X4",
    "sg:province":"ON",
    "sg:tags":[
        "publisher"
    ],
    "wof:name":"Brendan Kelly Publishing Inc",
    "wof:placetype":"venue"
},
  "geometry": {"coordinates":[-79.86039,43.371429],"type":"Point"}
}