{
  "type": "Feature",
  "properties": {
    "addr:full":"Rouyn-Noranda QC J9X 3B4",
    "addr:postcode":"j9x 3b4",
    "iso:country":"CA",
    "sg:city":"Rouyn-Noranda",
    "sg:classifiers":[
        {
            "category":"Health Services",
            "subcategory":"Doctor",
            "type":"Services"
        }
    ],
    "sg:phone":"+1 819 764 6185",
    "sg:postcode":"J9X 3B4",
    "sg:province":"QC",
    "sg:tags":[
        "physician",
        "clinic",
        "surgeon"
    ],
    "wof:name":"Clinique Medicale Fleur DE Lys",
    "wof:placetype":"venue"
},
  "geometry": {"coordinates":[-79.019897,48.241646],"type":"Point"}
}