{
  "type": "Feature",
  "properties": {
    "addr:full":"Saskatoon SK S7N 0W5",
    "addr:postcode":"s7n 0w5",
    "iso:country":"CA",
    "sg:city":"Saskatoon",
    "sg:classifiers":[
        {
            "category":"Health Services",
            "subcategory":"Health Practitioner",
            "type":"Services"
        }
    ],
    "sg:phone":"+1 306 664 6647",
    "sg:postcode":"S7N 0W5",
    "sg:province":"SK",
    "sg:tags":[
        "psychologist"
    ],
    "wof:name":"Chartier, Brian PhD",
    "wof:placetype":"venue"
},
  "geometry": {"coordinates":[-106.63813,52.128693],"type":"Point"}
}