{
  "type": "Feature",
  "properties": {
    "addr:full":"15 Crammond Pl Winnipeg MB R2C 3V3",
    "addr:housenumber":"15",
    "addr:postcode":"r2c 3v3",
    "addr:street":"Crammond Pl",
    "iso:country":"CA",
    "sg:address":"15 Crammond Pl",
    "sg:city":"Winnipeg",
    "sg:classifiers":[
        {
            "category":"Building & Trades",
            "subcategory":"Construction",
            "type":"Services"
        }
    ],
    "sg:phone":"+1 204 224 0110",
    "sg:postcode":"R2C 3V3",
    "sg:province":"MB",
    "sg:tags":[
        "painter"
    ],
    "wof:name":"City Wide Decorating Ltd",
    "wof:placetype":"venue"
},
  "geometry": {"coordinates":[-96.976624,49.903004],"type":"Point"}
}