{
  "type": "Feature",
  "properties": {
    "addr:full":"553 Boul Charest O Quebec QC G1N 2B6",
    "addr:housenumber":"553",
    "addr:postcode":"g1n 2b6",
    "addr:street":"Boul Charest O",
    "iso:country":"CA",
    "sg:address":"553 Boul Charest O",
    "sg:city":"Quebec",
    "sg:classifiers":[
        {
            "category":"Wholesale",
            "subcategory":"Hardware",
            "type":"Manufacturing & Wholesale Goods"
        }
    ],
    "sg:phone":"+1 418 522 2222",
    "sg:postcode":"G1N 2B6",
    "sg:province":"QC",
    "sg:tags":[
        "parts",
        "appliance",
        "refrigerating"
    ],
    "wof:name":"Midbec Limitee",
    "wof:placetype":"venue"
},
  "geometry": {"coordinates":[-71.222122,46.814098],"type":"Point"}
}