{
  "type": "Feature",
  "properties": {
    "addr:full":"17 10th Ave S Cranbrook BC V1C 2M9",
    "addr:housenumber":"17",
    "addr:postcode":"bc v1c 2m9",
    "addr:street":"10Th Ave S",
    "iso:country":"CA",
    "sg:address":"17 10th Ave S",
    "sg:city":"Cranbrook",
    "sg:classifiers":[
        {
            "category":"Wholesale",
            "subcategory":"Non-durable Goods",
            "type":"Manufacturing & Wholesale Goods"
        }
    ],
    "sg:phone":"+1 250 489 4864",
    "sg:postcode":"V1C 2M9",
    "sg:province":"BC",
    "sg:tags":[
        "advertising"
    ],
    "wof:name":"Mega Silk Screening",
    "wof:placetype":"venue"
},
  "geometry": {"coordinates":[-115.76776886,49.5117111206],"type":"Point"}
}