{
  "type": "Feature",
  "properties": {
    "iso:country":"CA",
    "sg:address":"4545 Rue Sherbrooke O",
    "sg:city":"Westmount",
    "sg:classifiers":[
        {
            "category":"Wholesale",
            "subcategory":"Drugs",
            "type":"Manufacturing & Wholesale Goods"
        }
    ],
    "sg:phone":"+1 514 931 3133",
    "sg:postcode":"H3Z 1E8",
    "sg:province":"QC",
    "sg:tags":[
        "pharmaceutical",
        "product"
    ],
    "wof:name":"Ciderfa",
    "wof:placetype":"venue"
},
  "geometry": {"coordinates":[-73.59930419920001,45.4828071594],"type":"Point"}
}