{
  "type": "Feature",
  "properties": {
    "iso:country":"CA",
    "sg:address":"32 Albro Lake Rd",
    "sg:city":"Dartmouth",
    "sg:classifiers":[
        {
            "category":"Restaurant",
            "type":"Food & Drink"
        }
    ],
    "sg:phone":"+1 902 463 1071",
    "sg:postcode":"B3A 3X8",
    "sg:province":"NS",
    "wof:name":"Yum Yum Restaurant",
    "wof:placetype":"venue"
},
  "geometry": {"coordinates":[-63.5881385803,44.6762771606],"type":"Point"}
}