{
  "type": "Feature",
  "properties": {
    "addr:full":"140 Botsford St Moncton NB E1C 4X5",
    "addr:housenumber":"140",
    "addr:postcode":"e1c 4x5",
    "addr:street":"Botsford St",
    "iso:country":"CA",
    "sg:address":"140 Botsford St",
    "sg:city":"Moncton",
    "sg:classifiers":[
        {
            "category":"Social Services",
            "subcategory":"Child Care",
            "type":"Services"
        }
    ],
    "sg:phone":"+1 506 859 1498",
    "sg:postcode":"E1C 4X5",
    "sg:province":"NB",
    "wof:name":"Club 6-12",
    "wof:placetype":"venue"
},
  "geometry": {"coordinates":[-64.77754974370001,46.0924720764],"type":"Point"}
}