{
  "type": "Feature",
  "properties": {
    "iso:country":"CA",
    "sg:address":"3030 Don Mills Rd",
    "sg:city":"North York",
    "sg:classifiers":[
        {
            "category":"Home & Garden",
            "subcategory":"Furniture",
            "type":"Retail Goods"
        }
    ],
    "sg:phone":"+1 416 494 2215",
    "sg:postcode":"M2J 3C1",
    "sg:province":"ON",
    "wof:name":"Rhonda Furniture & Mattress",
    "wof:placetype":"venue"
},
  "geometry": {"coordinates":[-79.353416,43.787819],"type":"Point"}
}