{
  "type": "Feature",
  "properties": {
    "addr:full":"Cnr Right-of-Way Raymore SK S0A 3J0",
    "addr:postcode":"s0a 3j0",
    "addr:street":"Cnr Right-Of-Way",
    "iso:country":"CA",
    "sg:address":"Cnr Right-of-Way",
    "sg:city":"Raymore",
    "sg:classifiers":[
        {
            "category":"Freight",
            "type":"Transportation"
        }
    ],
    "sg:phone":"+1 306 746 2055",
    "sg:postcode":"S0A 3J0",
    "sg:province":"SK",
    "sg:tags":[
        "grain",
        "elevator"
    ],
    "wof:name":"Cargill Ag Horizons",
    "wof:placetype":"venue"
},
  "geometry": {"coordinates":[-104.538025,51.409729],"type":"Point"}
}