{
  "type": "Feature",
  "properties": {
    "iso:country":"CA",
    "sg:address":"4111 13A St SE",
    "sg:city":"Calgary",
    "sg:classifiers":[
        {
            "category":"Freight",
            "type":"Transportation"
        }
    ],
    "sg:phone":"+1 403 292 0111",
    "sg:postcode":"T2G 3J6",
    "sg:province":"AB",
    "sg:tags":[
        "trucking"
    ],
    "wof:name":"Mountain Parks Express Inc",
    "wof:placetype":"venue"
},
  "geometry": {"coordinates":[-114.02898407000001,51.0184593201],"type":"Point"}
}