{
  "type": "Feature",
  "properties": {
    "iso:country":"CA",
    "sg:address":"120 9th St E #200",
    "sg:city":"Cornwall",
    "sg:classifiers":[
        {
            "category":"Sports & Exercise",
            "subcategory":"Gym",
            "type":"Entertainment"
        }
    ],
    "sg:phone":"+1 613 932 4766",
    "sg:postcode":"K6H 2T9",
    "sg:province":"ON",
    "sg:tags":[
        "club",
        "health",
        "studio",
        "gymnasium"
    ],
    "wof:name":"Physical Limits Fitness Club",
    "wof:placetype":"venue"
},
  "geometry": {"coordinates":[-74.7322235107,45.0292778015],"type":"Point"}
}