{
  "type": "Feature",
  "properties": {
    "addr:full":"Creston BC V0B 1G0",
    "addr:postcode":"bc v0b 1g0",
    "iso:country":"CA",
    "sg:city":"Creston",
    "sg:classifiers":[
        {
            "category":"Health Services",
            "subcategory":"Doctor",
            "type":"Services"
        }
    ],
    "sg:phone":"+1 250 428 9111",
    "sg:postcode":"V0B 1G0",
    "sg:province":"BC",
    "sg:tags":[
        "dentist"
    ],
    "wof:name":"Creston Valley Dental Ctr",
    "wof:placetype":"venue"
},
  "geometry": {"coordinates":[-116.511383,49.095348],"type":"Point"}
}