{
  "type": "Feature",
  "properties": {
    "addr:full":"270 Pierre Rd Sturgeon Falls ON P2B 2W8",
    "addr:housenumber":"270",
    "addr:postcode":"p2b 2w8",
    "addr:street":"Pierre Rd",
    "iso:country":"CA",
    "sg:address":"270 Pierre Rd",
    "sg:city":"Sturgeon Falls",
    "sg:classifiers":[
        {
            "category":"Travel",
            "subcategory":"Hotels & Motels",
            "type":"Entertainment"
        }
    ],
    "sg:phone":"+1 705 753 2419",
    "sg:postcode":"P2B 2W8",
    "sg:province":"ON",
    "sg:tags":[
        "tourist",
        "accommodation"
    ],
    "wof:name":"Dutrisac Cottages",
    "wof:placetype":"venue"
},
  "geometry": {"coordinates":[-79.929565,46.366653],"type":"Point"}
}