{
  "type": "Feature",
  "properties": {
    "addr:full":"1958 158A St Surrey BC V4A 8G9",
    "addr:housenumber":"1958",
    "addr:postcode":"v4a 8g9",
    "addr:street":"158A St",
    "iso:country":"CA",
    "sg:address":"1958 158A St",
    "sg:city":"Surrey",
    "sg:classifiers":[
        {
            "category":"Social Services",
            "type":"Services"
        }
    ],
    "sg:phone":"+1 604 541 5417",
    "sg:postcode":"V4A 8G9",
    "sg:province":"BC",
    "sg:tags":[
        "counselor",
        "marriage",
        "family"
    ],
    "wof:name":"A Friend in Need",
    "wof:placetype":"venue"
},
  "geometry": {"coordinates":[-122.830215,49.105179],"type":"Point"}
}