{
  "type": "Feature",
  "properties": {
    "addr:full":"North York ON M2J 4R4",
    "addr:postcode":"m2j 4r4",
    "iso:country":"CA",
    "sg:city":"North York",
    "sg:classifiers":[
        {
            "category":"Banks & Credit Unions",
            "subcategory":"Investment Brokerage",
            "type":"Services"
        }
    ],
    "sg:phone":"+1 416 499 5105",
    "sg:postcode":"M2J 4R4",
    "sg:province":"ON",
    "sg:tags":[
        "consultant",
        "planning",
        "financial"
    ],
    "wof:name":"Gribben Group Financial Bnft",
    "wof:placetype":"venue"
},
  "geometry": {"coordinates":[-79.33168000000001,43.772587],"type":"Point"}
}