{
  "type": "Feature",
  "properties": {
    "addr:full":"23 Ivanhoe Crt Scarborough ON M1R 3G8",
    "addr:housenumber":"23",
    "addr:postcode":"m1r 3g8",
    "addr:street":"Ivanhoe Crt",
    "iso:country":"CA",
    "sg:address":"23 Ivanhoe Crt",
    "sg:city":"Scarborough",
    "sg:classifiers":[
        {
            "category":"Building & Trades",
            "subcategory":"Electrical",
            "type":"Services"
        }
    ],
    "sg:phone":"+1 416 759 6661",
    "sg:postcode":"M1R 3G8",
    "sg:province":"ON",
    "sg:tags":[
        "electric",
        "contractor"
    ],
    "wof:name":"Costa Electric",
    "wof:placetype":"venue"
},
  "geometry": {"coordinates":[-79.30381,43.745014],"type":"Point"}
}