{
  "type": "Feature",
  "properties": {
    "addr:full":"423 Kelly Cres Newmarket ON L3Y 7K4",
    "addr:housenumber":"423",
    "addr:postcode":"l3y 7k4",
    "addr:street":"Kelly Cres",
    "iso:country":"CA",
    "sg:address":"423 Kelly Cres",
    "sg:city":"Newmarket",
    "sg:classifiers":[
        {
            "category":"Building & Trades",
            "subcategory":"Construction",
            "type":"Services"
        }
    ],
    "sg:phone":"+1 905 853 6093",
    "sg:postcode":"L3Y 7K4",
    "sg:province":"ON",
    "sg:tags":[
        "painter"
    ],
    "wof:name":"Arboreus Home Improvements",
    "wof:placetype":"venue"
},
  "geometry": {"coordinates":[-79.449226,44.075119],"type":"Point"}
}