{
  "type": "Feature",
  "properties": {
    "addr:full":"1830 Lower Prospect Rd Terence Bay NS B3T 1Y6",
    "addr:housenumber":"1830",
    "addr:postcode":"b3t 1y6",
    "addr:street":"Lower Prospect Rd",
    "iso:country":"CA",
    "sg:address":"1830 Lower Prospect Rd",
    "sg:city":"Terence Bay",
    "sg:classifiers":[
        {
            "category":"Organizations",
            "subcategory":"Religious Organization",
            "type":"Services"
        }
    ],
    "sg:phone":"+1 902 852 4212",
    "sg:postcode":"B3T 1Y6",
    "sg:province":"NS",
    "sg:tags":[
        "house",
        "retreat"
    ],
    "wof:name":"Seton Spirituality Ctr",
    "wof:placetype":"venue"
},
  "geometry": {"coordinates":[-63.7217788696,44.4692077637],"type":"Point"}
}