{
  "type": "Feature",
  "properties": {
    "addr:full":"6100 Doumont Rd Nanaimo BC V9T 6G7",
    "addr:housenumber":"6100",
    "addr:postcode":"v9t 6g7",
    "addr:street":"Doumont Rd",
    "iso:country":"CA",
    "sg:address":"6100 Doumont Rd",
    "sg:city":"Nanaimo",
    "sg:classifiers":[
        {
            "category":"Recreation",
            "type":"Entertainment"
        }
    ],
    "sg:phone":"+1 250 390 4513",
    "sg:postcode":"V9T 6G7",
    "sg:province":"BC",
    "sg:tags":[
        "hall",
        "auditorium"
    ],
    "wof:name":"Pleasant Valley Social Ctr",
    "wof:placetype":"venue"
},
  "geometry": {"coordinates":[-124.047127,49.224358],"type":"Point"}
}