{
  "type": "Feature",
  "properties": {
    "addr:full":"573 Mccurrach Pl Kamloops BC V2B 8R1",
    "addr:housenumber":"573",
    "addr:postcode":"bc v2b 8r1",
    "addr:street":"Mccurrach Pl",
    "iso:country":"CA",
    "sg:address":"573 Mccurrach Pl",
    "sg:city":"Kamloops",
    "sg:classifiers":[
        {
            "category":"Building & Trades",
            "subcategory":"Electrical",
            "type":"Services"
        }
    ],
    "sg:phone":"+1 250 579 1800",
    "sg:postcode":"V2B 8R1",
    "sg:province":"BC",
    "sg:tags":[
        "electric",
        "contractor"
    ],
    "wof:name":"Mike Funk Electrical Ltd",
    "wof:placetype":"venue"
},
  "geometry": {"coordinates":[-120.336532593,50.7695159912],"type":"Point"}
}