{
  "type": "Feature",
  "properties": {
    "addr:full":"55 Mountainash Rd Brampton ON L6R 1W4",
    "addr:housenumber":"55",
    "addr:postcode":"l6r 1w4",
    "addr:street":"Mountainash Rd",
    "iso:country":"CA",
    "sg:address":"55 Mountainash Rd",
    "sg:city":"Brampton",
    "sg:classifiers":[
        {
            "category":"Food & Beverages",
            "subcategory":"Groceries & Convenience Stores",
            "type":"Retail Goods"
        }
    ],
    "sg:phone":"+1 905 793 8200",
    "sg:postcode":"L6R 1W4",
    "sg:province":"ON",
    "sg:tags":[
        "grocer"
    ],
    "wof:name":"Fortinos",
    "wof:placetype":"venue"
},
  "geometry": {"coordinates":[-79.7313613892,43.759601593],"type":"Point"}
}