{
  "type": "Feature",
  "properties": {
    "addr:full":"1001 Low Level Rd North Vancouver BC V7L 1A7",
    "addr:housenumber":"1001",
    "addr:postcode":"v7l 1a7",
    "addr:street":"Low Level Rd",
    "iso:country":"CA",
    "sg:address":"1001 Low Level Rd",
    "sg:city":"North Vancouver",
    "sg:classifiers":[
        {
            "category":"Building & Trades",
            "subcategory":"Construction",
            "type":"Services"
        }
    ],
    "sg:phone":"+1 604 985 7461",
    "sg:postcode":"V7L 1A7",
    "sg:province":"BC",
    "sg:tags":[
        "dock"
    ],
    "wof:name":"Neptune Bulk Terminals Ltd",
    "wof:placetype":"venue"
},
  "geometry": {"coordinates":[-123.049102783,49.3080596924],"type":"Point"}
}