{
  "type": "Feature",
  "properties": {
    "addr:full":"194 King St W Dundas ON L9H 1V4",
    "addr:housenumber":"194",
    "addr:postcode":"l9h 1v4",
    "addr:street":"King St W",
    "iso:country":"CA",
    "sg:address":"194 King St W",
    "sg:city":"Dundas",
    "sg:classifiers":[
        {
            "category":"Shopping",
            "type":"Retail Goods"
        }
    ],
    "sg:phone":"+1 905 628 9381",
    "sg:postcode":"L9H 1V4",
    "sg:province":"ON",
    "sg:tags":[
        "equipment",
        "wine",
        "supply"
    ],
    "wof:name":"Taylor's Wine & Beer",
    "wof:placetype":"venue"
},
  "geometry": {"coordinates":[-79.9621963501,43.2672958374],"type":"Point"}
}