{
  "type": "Feature",
  "properties": {
    "addr:full":"1161 Pettit Rd Burlington ON L7P 2K3",
    "addr:housenumber":"1161",
    "addr:postcode":"l7p 2k3",
    "addr:street":"Pettit Rd",
    "iso:country":"CA",
    "sg:address":"1161 Pettit Rd",
    "sg:city":"Burlington",
    "sg:classifiers":[
        {
            "category":"Building & Trades",
            "subcategory":"Construction",
            "type":"Services"
        }
    ],
    "sg:phone":"+1 905 335 9227",
    "sg:postcode":"L7P 2K3",
    "sg:province":"ON",
    "sg:tags":[
        "painter"
    ],
    "wof:name":"Professional Painting & Decor",
    "wof:placetype":"venue"
},
  "geometry": {"coordinates":[-79.815727,43.3489],"type":"Point"}
}