{
  "type": "Feature",
  "properties": {
    "addr:full":"2797 White St Val Caron ON P3N 1B2",
    "addr:housenumber":"2797",
    "addr:postcode":"p3n 1b2",
    "addr:street":"White St",
    "iso:country":"CA",
    "sg:address":"2797 White St",
    "sg:city":"Val Caron",
    "sg:classifiers":[
        {
            "category":"Mining & Drilling",
            "type":"Manufacturing & Wholesale Goods"
        }
    ],
    "sg:phone":"+1 705 897 1932",
    "sg:postcode":"P3N 1B2",
    "sg:province":"ON",
    "sg:tags":[
        "contractor"
    ],
    "wof:name":"Scr Mine Technology",
    "wof:placetype":"venue"
},
  "geometry": {"coordinates":[-81.0318145752,46.6045455933],"type":"Point"}
}