{
  "type": "Feature",
  "properties": {
    "addr:full":"899 Tungsten St Thunder Bay ON P7B 6H2",
    "addr:housenumber":"899",
    "addr:postcode":"p7b 6h2",
    "addr:street":"Tungsten St",
    "iso:country":"CA",
    "sg:address":"899 Tungsten St",
    "sg:city":"Thunder Bay",
    "sg:classifiers":[
        {
            "category":"Manufacturing",
            "subcategory":"Food",
            "type":"Manufacturing & Wholesale Goods"
        }
    ],
    "sg:phone":"+1 807 344 1632",
    "sg:postcode":"P7B 6H2",
    "sg:province":"ON",
    "sg:tags":[
        "baker",
        "cookie",
        "bakery"
    ],
    "wof:name":"Bennett's Bakery Ltd",
    "wof:placetype":"venue"
},
  "geometry": {"coordinates":[-89.25376900000001,48.412071],"type":"Point"}
}