{
  "type": "Feature",
  "properties": {
    "iso:country":"CA",
    "sg:address":"370 Boul Cure-Labelle",
    "sg:city":"Fabreville",
    "sg:classifiers":[
        {
            "category":"Banks & Credit Unions",
            "subcategory":"Bank",
            "type":"Services"
        }
    ],
    "sg:phone":"+1 450 622 8130",
    "sg:postcode":"H7P 2P1",
    "sg:province":"QC",
    "wof:name":"Caisses Desjardins Ctr DE Svc",
    "wof:placetype":"venue"
},
  "geometry": {"coordinates":[-73.7870788574,45.575717926],"type":"Point"}
}