{
  "type": "Feature",
  "properties": {
    "addr:full":"Port Sydney ON P0B 1L0",
    "addr:postcode":"p0b 1l0",
    "addr:street":"Port",
    "iso:country":"CA",
    "sg:city":"Port Sydney",
    "sg:classifiers":[
        {
            "category":"Autos & Motor Vehicles",
            "subcategory":"Fuel & Gas Station",
            "type":"Retail Goods"
        }
    ],
    "sg:phone":"+1 705 385 2718",
    "sg:postcode":"P0B 1L0",
    "sg:province":"ON",
    "sg:tags":[
        "oil"
    ],
    "wof:name":"Smith's Servicentre & Rstrnt",
    "wof:placetype":"venue"
},
  "geometry": {"coordinates":[-79.312355,45.186413],"type":"Point"}
}