{
  "type": "Feature",
  "properties": {
    "addr:full":"181 Wellington St London ON N6B 2K9",
    "addr:housenumber":"181",
    "addr:postcode":"n6b 2k9",
    "addr:street":"Wellington St",
    "iso:country":"CA",
    "sg:address":"181 Wellington St",
    "sg:city":"London",
    "sg:classifiers":[
        {
            "category":"Social Services",
            "type":"Services"
        }
    ],
    "sg:phone":"+1 519 667 3325",
    "sg:postcode":"N6B 2K9",
    "sg:province":"ON",
    "sg:tags":[
        "organization",
        "welfare",
        "deaf",
        "facility"
    ],
    "wof:name":"Canadian Hearing Society",
    "wof:placetype":"venue"
},
  "geometry": {"coordinates":[-81.242058,42.97818],"type":"Point"}
}