{
  "type": "Feature",
  "properties": {
    "addr:full":"7391 Boul Saint-Michel Montreal QC H2A 3A1",
    "addr:housenumber":"7391",
    "addr:postcode":"h2a 3a1",
    "addr:street":"Boul Saint-Michel",
    "iso:country":"CA",
    "sg:address":"7391 Boul Saint-Michel",
    "sg:city":"Montreal",
    "sg:classifiers":[
        {
            "category":"Health Services",
            "subcategory":"Doctor",
            "type":"Services"
        }
    ],
    "sg:phone":"+1 514 376 2626",
    "sg:postcode":"H2A 3A1",
    "sg:province":"QC",
    "sg:tags":[
        "physiotherapist",
        "surgeon",
        "physician"
    ],
    "wof:name":"Centre Algotech",
    "wof:placetype":"venue"
},
  "geometry": {"coordinates":[-73.601135,45.560314],"type":"Point"}
}