{
  "type": "Feature",
  "properties": {
    "addr:full":"6736 Hwy 11 Temagami ON P0H 2H0",
    "addr:housenumber":"6736",
    "addr:postcode":"p0h 2h0",
    "addr:street":"Hwy 11 Temagami",
    "iso:country":"CA",
    "sg:address":"6736 Hwy 11",
    "sg:city":"Temagami",
    "sg:classifiers":[
        {
            "category":"Retail",
            "subcategory":"Auto Repair",
            "type":"Services"
        }
    ],
    "sg:phone":"+1 705 569 2800",
    "sg:postcode":"P0H 2H0",
    "sg:province":"ON",
    "sg:tags":[
        "repairing",
        "automobile"
    ],
    "wof:name":"Temagami Auto Clinic",
    "wof:placetype":"venue"
},
  "geometry": {"coordinates":[-79.78994,47.062721],"type":"Point"}
}