{
  "type": "Feature",
  "properties": {
    "addr:full":"1530 Angus St Regina SK S4T 1Z1",
    "addr:housenumber":"1530",
    "addr:postcode":"s4t 1z1",
    "addr:street":"Angus St",
    "iso:country":"CA",
    "sg:address":"1530 Angus St",
    "sg:city":"Regina",
    "sg:classifiers":[
        {
            "category":"Professional",
            "subcategory":"Lawyer & Legal Services",
            "type":"Services"
        }
    ],
    "sg:phone":"+1 306 525 6125",
    "sg:postcode":"S4T 1Z1",
    "sg:province":"SK",
    "sg:tags":[
        "attorney"
    ],
    "wof:name":"Griffin, Michael B",
    "wof:placetype":"venue"
},
  "geometry": {"coordinates":[-104.619843,50.454521],"type":"Point"}
}