{
  "type": "Feature",
  "properties": {
    "addr:full":"2043 Eglinton Ave E Scarborough ON M1L 2M9",
    "addr:housenumber":"2043",
    "addr:postcode":"m1l 2m9",
    "addr:street":"Eglinton Ave E",
    "iso:country":"CA",
    "sg:address":"2043 Eglinton Ave E",
    "sg:city":"Scarborough",
    "sg:classifiers":[
        {
            "category":"Banks & Credit Unions",
            "subcategory":"Bank",
            "type":"Services"
        }
    ],
    "sg:phone":"+1 416 751 2600",
    "sg:postcode":"M1L 2M9",
    "sg:province":"ON",
    "wof:name":"Royal Bank Financial Group",
    "wof:placetype":"venue"
},
  "geometry": {"coordinates":[-79.2810745239,43.7292442322],"type":"Point"}
}