{
  "type": "Feature",
  "properties": {
    "addr:full":"554 Rue Sauriol E Montreal QC H2C 3L1",
    "addr:housenumber":"554",
    "addr:postcode":"h2c 3l1",
    "addr:street":"Rue Sauriol E",
    "iso:country":"CA",
    "sg:address":"554 Rue Sauriol E",
    "sg:city":"Montreal",
    "sg:classifiers":[
        {
            "category":"Personal",
            "type":"Services"
        }
    ],
    "sg:phone":"+1 514 389 2361",
    "sg:postcode":"H2C 3L1",
    "sg:province":"QC",
    "sg:tags":[
        "bureau"
    ],
    "wof:name":"Garderie Le Pissenlit",
    "wof:placetype":"venue"
},
  "geometry": {"coordinates":[-73.6584320068,45.5528335571],"type":"Point"}
}