{
  "type": "Feature",
  "properties": {
    "addr:full":"210 Main St Loon Lake SK S0M 1L0",
    "addr:housenumber":"210",
    "addr:postcode":"s0m 1l0",
    "addr:street":"Main St",
    "iso:country":"CA",
    "sg:address":"210 Main St",
    "sg:city":"Loon Lake",
    "sg:classifiers":[
        {
            "category":"Home & Garden",
            "subcategory":"Hardware",
            "type":"Retail Goods"
        }
    ],
    "sg:phone":"+1 306 837 4440",
    "sg:postcode":"S0M 1L0",
    "sg:province":"SK",
    "wof:name":"Parkland Hardware",
    "wof:placetype":"venue"
},
  "geometry": {"coordinates":[-109.159965515,54.0264854431],"type":"Point"}
}