{
  "type": "Feature",
  "properties": {
    "iso:country":"CA",
    "sg:address":"3171 Bellamy Rd",
    "sg:city":"Prince George",
    "sg:classifiers":[
        {
            "category":"Freight",
            "type":"Transportation"
        }
    ],
    "sg:phone":"+1 250 962 2049",
    "sg:postcode":"V2K 4H6",
    "sg:province":"BC",
    "sg:tags":[
        "recreational",
        "commercial",
        "vehicle"
    ],
    "wof:name":"Celeste's Rv Ctr Ltd",
    "wof:placetype":"venue"
},
  "geometry": {"coordinates":[-122.76256561300001,53.9544639587],"type":"Point"}
}