{
  "type": "Feature",
  "properties": {
    "addr:full":"3615 Ch Du Souvenir Laval QC H7V 1X5",
    "addr:postcode":"3615;h7v 1x5",
    "addr:street":"Ch Du Souvenir",
    "iso:country":"CA",
    "sg:address":"3615 Ch Du Souvenir",
    "sg:city":"Laval",
    "sg:classifiers":[
        {
            "category":"Personal",
            "type":"Services"
        }
    ],
    "sg:phone":"+1 450 681 8181",
    "sg:postcode":"H7V 1X5",
    "sg:province":"QC",
    "sg:tags":[
        "therapist",
        "massage"
    ],
    "wof:name":"Au Centre DE Massotherapie",
    "wof:placetype":"venue"
},
  "geometry": {"coordinates":[-73.750191,45.550575],"type":"Point"}
}