{
  "type": "Feature",
  "properties": {
    "iso:country":"CA",
    "sg:address":"13490 104 Ave",
    "sg:city":"Surrey",
    "sg:classifiers":[
        {
            "category":"Health Services",
            "subcategory":"Doctor",
            "type":"Services"
        }
    ],
    "sg:phone":"+1 604 585 6414",
    "sg:postcode":"V3T 1V8",
    "sg:province":"BC",
    "sg:tags":[
        "physician",
        "surgeon"
    ],
    "wof:name":"R G Woods Inc",
    "wof:placetype":"venue"
},
  "geometry": {"coordinates":[-122.834205627,49.1914787292],"type":"Point"}
}