{
  "type": "Feature",
  "properties": {
    "addr:full":"Matagami QC J0Y 2A0",
    "addr:postcode":"j0y 2a0",
    "iso:country":"CA",
    "sg:city":"Matagami",
    "sg:classifiers":[
        {
            "category":"Personal",
            "subcategory":"Beauty Salon",
            "type":"Services"
        }
    ],
    "sg:phone":"+1 819 739 4535",
    "sg:postcode":"J0Y 2A0",
    "sg:province":"QC",
    "wof:name":"Coiffure Annie Gilbert",
    "wof:placetype":"venue"
},
  "geometry": {"coordinates":[-77.639816,49.7663],"type":"Point"}
}