{
  "type": "Feature",
  "properties": {
    "addr:full":"19050 Lougheed Hwy Pitt Meadows BC V3Y 2J2",
    "addr:housenumber":"19050",
    "addr:postcode":"v3y 2j2",
    "addr:street":"Lougheed Hwy",
    "iso:country":"CA",
    "sg:address":"19050 Lougheed Hwy",
    "sg:city":"Pitt Meadows",
    "sg:classifiers":[
        {
            "category":"Home & Garden",
            "subcategory":"Furniture",
            "type":"Retail Goods"
        }
    ],
    "sg:phone":"+1 604 465 9422",
    "sg:postcode":"V3Y 2J2",
    "sg:province":"BC",
    "sg:tags":[
        "mattress"
    ],
    "wof:name":"United Furniture Warehouse",
    "wof:placetype":"venue"
},
  "geometry": {"coordinates":[-122.693687,49.232517],"type":"Point"}
}