{
  "type": "Feature",
  "properties": {
    "addr:full":"Brampton ON L6W 3X3",
    "addr:postcode":"l6w 3x3",
    "iso:country":"CA",
    "sg:city":"Brampton",
    "sg:classifiers":[
        {
            "category":"Home & Garden",
            "subcategory":"Furniture",
            "type":"Retail Goods"
        }
    ],
    "sg:phone":"+1 905 451 0835",
    "sg:postcode":"L6W 3X3",
    "sg:province":"ON",
    "sg:tags":[
        "bed"
    ],
    "wof:name":"Dominion Therapy CO Ltd",
    "wof:placetype":"venue"
},
  "geometry": {"coordinates":[-79.7260894775,43.6869430542],"type":"Point"}
}