{
  "type": "Feature",
  "properties": {
    "addr:full":"5027 49 St # A Innisfail AB T4G 1M1",
    "addr:housenumber":"5027",
    "addr:postcode":"t4g 1m1",
    "addr:street":"49 St # A",
    "iso:country":"CA",
    "sg:address":"5027 49 St # A",
    "sg:city":"Innisfail",
    "sg:classifiers":[
        {
            "category":"Shopping",
            "subcategory":"Pharmacy",
            "type":"Retail Goods"
        }
    ],
    "sg:phone":"+1 403 227 3488",
    "sg:postcode":"T4G 1M1",
    "sg:province":"AB",
    "wof:name":"Parkland Ida Pharmacy Ltd",
    "wof:placetype":"venue"
},
  "geometry": {"coordinates":[-113.95079,52.026382],"type":"Point"}
}