{
  "type": "Feature",
  "properties": {
    "iso:country":"CA",
    "sg:city":"Winnipeg",
    "sg:classifiers":[
        {
            "category":"Health Services",
            "subcategory":"Doctor",
            "type":"Services"
        }
    ],
    "sg:phone":"+1 204 942 6217",
    "sg:postcode":"R3C 1T7",
    "sg:province":"MB",
    "sg:tags":[
        "dentist"
    ],
    "wof:name":"Mc Intyre, Mike DDS",
    "wof:placetype":"venue"
},
  "geometry": {"coordinates":[-97.1485443115,49.8899459839],"type":"Point"}
}