{
  "type": "Feature",
  "properties": {
    "addr:full":"7811 Argyll Rd NW Edmonton AB T6C 4A9",
    "addr:housenumber":"7811",
    "addr:postcode":"t6c 4a9",
    "addr:street":"Argyll Rd Nw",
    "iso:country":"CA",
    "sg:address":"7811 Argyll Rd NW",
    "sg:city":"Edmonton",
    "sg:classifiers":[
        {
            "category":"Manufacturing",
            "subcategory":"Signs",
            "type":"Manufacturing & Wholesale Goods"
        }
    ],
    "sg:phone":"+1 780 461 4455",
    "sg:postcode":"T6C 4A9",
    "sg:province":"AB",
    "wof:name":"West-Star Signs & Graphics",
    "wof:placetype":"venue"
},
  "geometry": {"coordinates":[-113.44579315199999,53.5064888],"type":"Point"}
}