{
  "type": "Feature",
  "properties": {
    "addr:full":"400 Sidney St Trenton ON K8V 2V2",
    "addr:housenumber":"400",
    "addr:postcode":"k8v 2v2",
    "addr:street":"Sidney St",
    "iso:country":"CA",
    "sg:address":"400 Sidney St",
    "sg:city":"Trenton",
    "sg:classifiers":[
        {
            "category":"Wholesale",
            "subcategory":"Auto Parts",
            "type":"Manufacturing & Wholesale Goods"
        }
    ],
    "sg:phone":"+1 613 392 5201",
    "sg:postcode":"K8V 2V2",
    "sg:province":"ON",
    "sg:tags":[
        "automobile",
        "wrecking"
    ],
    "wof:name":"Sidney Auto Wreckers",
    "wof:placetype":"venue"
},
  "geometry": {"coordinates":[-77.580872,44.127964],"type":"Point"}
}