{
  "type": "Feature",
  "properties": {
    "addr:full":"325 Deerhide Cres North York ON M9M 2Z2",
    "addr:housenumber":"325",
    "addr:postcode":"m9m 2z2",
    "addr:street":"Deerhide Cres",
    "iso:country":"CA",
    "sg:address":"325 Deerhide Cres",
    "sg:city":"North York",
    "sg:classifiers":[
        {
            "category":"Wholesale",
            "subcategory":"Electrical",
            "type":"Manufacturing & Wholesale Goods"
        }
    ],
    "sg:phone":"+1 416 745 3806",
    "sg:postcode":"M9M 2Z2",
    "sg:province":"ON",
    "sg:tags":[
        "light",
        "tube",
        "bulb"
    ],
    "wof:name":"Litemor Distributors Ltd",
    "wof:placetype":"venue"
},
  "geometry": {"coordinates":[-79.5346908569,43.7489738464],"type":"Point"}
}