{
  "type": "Feature",
  "properties": {
    "addr:full":"111 Robinson St Peterborough ON K9H 1G1",
    "addr:housenumber":"111",
    "addr:postcode":"k9h 1g1",
    "addr:street":"Robinson St",
    "iso:country":"CA",
    "sg:address":"111 Robinson St",
    "sg:city":"Peterborough",
    "sg:classifiers":[
        {
            "category":"Building & Trades",
            "subcategory":"Electrical",
            "type":"Services"
        }
    ],
    "sg:phone":"+1 705 743 5847",
    "sg:postcode":"K9H 1G1",
    "sg:province":"ON",
    "sg:tags":[
        "electric",
        "contractor"
    ],
    "wof:name":"Andy Electric",
    "wof:placetype":"venue"
},
  "geometry": {"coordinates":[-78.308601,44.304382],"type":"Point"}
}