{
  "type": "Feature",
  "properties": {
    "addr:full":"11695 2nd Line Roseneath ON K0K 2X0",
    "addr:housenumber":"11695",
    "addr:postcode":"k0k 2x0",
    "addr:street":"2Nd Line",
    "iso:country":"CA",
    "sg:address":"11695 2nd Line",
    "sg:city":"Roseneath",
    "sg:classifiers":[
        {
            "category":"Professional",
            "subcategory":"Employment Agencies",
            "type":"Services"
        }
    ],
    "sg:phone":"+1 905 352 2793",
    "sg:postcode":"K0K 2X0",
    "sg:province":"ON",
    "sg:tags":[
        "opportunity"
    ],
    "wof:name":"Alderville Student Employment",
    "wof:placetype":"venue"
},
  "geometry": {"coordinates":[-78.0572357178,44.1935386658],"type":"Point"}
}