{
  "type": "Feature",
  "properties": {
    "addr:full":"7290 Rue Frederick-Banting Saint-Laurent QC H4S 2A1",
    "addr:housenumber":"7290",
    "addr:postcode":"h4s 2a1",
    "addr:street":"Rue Frederick-Banting",
    "iso:country":"CA",
    "sg:address":"7290 Rue Frederick-Banting",
    "sg:city":"Saint-Laurent",
    "sg:classifiers":[
        {
            "category":"Professional",
            "subcategory":"Research",
            "type":"Services"
        }
    ],
    "sg:phone":"+1 514 336 2700",
    "sg:postcode":"H4S 2A1",
    "sg:province":"QC",
    "sg:tags":[
        "development",
        "laboratory"
    ],
    "wof:name":"Ecopia Biosciences Inc",
    "wof:placetype":"venue"
},
  "geometry": {"coordinates":[-73.7697753906,45.4814224243],"type":"Point"}
}