{
  "type": "Feature",
  "properties": {
    "addr:full":"1060 County Rd 8 Staples ON N0P 2J0",
    "addr:housenumber":"1060;8",
    "addr:postcode":"n0p 2j0",
    "addr:street":"County Rd",
    "iso:country":"CA",
    "sg:address":"1060 County Rd 8",
    "sg:city":"Staples",
    "sg:classifiers":[
        {
            "category":"Wholesale",
            "subcategory":"Farm Supplies",
            "type":"Manufacturing & Wholesale Goods"
        }
    ],
    "sg:phone":"+1 519 687 3012",
    "sg:postcode":"N0P 2J0",
    "sg:province":"ON",
    "sg:tags":[
        "grain"
    ],
    "wof:name":"Cargill Limited",
    "wof:placetype":"venue"
},
  "geometry": {"coordinates":[-82.55647999999999,42.175552],"type":"Point"}
}