{
  "type": "Feature",
  "properties": {
    "addr:full":"8650 Av Chaumont Anjou QC H1K 1N5",
    "addr:housenumber":"8650",
    "addr:postcode":"h1k 1n5",
    "addr:street":"Av Chaumont",
    "iso:country":"CA",
    "sg:address":"8650 Av Chaumont",
    "sg:city":"Anjou",
    "sg:classifiers":[
        {
            "category":"Personal",
            "subcategory":"Beauty Salon",
            "type":"Services"
        }
    ],
    "sg:phone":"+1 514 352 5600",
    "sg:postcode":"H1K 1N5",
    "sg:province":"QC",
    "wof:name":"Salon Vincent & Michelle",
    "wof:placetype":"venue"
},
  "geometry": {"coordinates":[-73.547394,45.610039],"type":"Point"}
}