{
  "type": "Feature",
  "properties": {
    "addr:full":"Surrey BC V3W 9G2",
    "addr:postcode":"v3w 9g2",
    "iso:country":"CA",
    "sg:city":"Surrey",
    "sg:classifiers":[
        {
            "category":"Manufacturing",
            "subcategory":"Food",
            "type":"Manufacturing & Wholesale Goods"
        }
    ],
    "sg:phone":"+1 604 597 3497",
    "sg:postcode":"V3W 9G2",
    "sg:province":"BC",
    "sg:tags":[
        "baker",
        "cookie",
        "bakery"
    ],
    "wof:name":"Cakeworks",
    "wof:placetype":"venue"
},
  "geometry": {"coordinates":[-122.879272,49.153988],"type":"Point"}
}