{
  "type": "Feature",
  "properties": {
    "addr:full":"RR 1 Norwood ON K0L 2V0",
    "addr:postcode":"k0l 2v0",
    "addr:street":"Rr 1",
    "iso:country":"CA",
    "sg:address":"RR 1",
    "sg:city":"Norwood",
    "sg:classifiers":[
        {
            "category":"Organizations",
            "subcategory":"Religious Organization",
            "type":"Services"
        }
    ],
    "sg:phone":"+1 705 639 2187",
    "sg:postcode":"K0L 2V0",
    "sg:province":"ON",
    "sg:tags":[
        "church"
    ],
    "wof:name":"Norwood Pentecostal Church",
    "wof:placetype":"venue"
},
  "geometry": {"coordinates":[-77.979133606,44.3830337524],"type":"Point"}
}