{
  "type": "Feature",
  "properties": {
    "addr:full":"118 Humphrey Rd Labrador City NL A2V 2J8",
    "addr:housenumber":"118",
    "addr:postcode":"a2v 2j8",
    "addr:street":"Humphrey Rd",
    "iso:country":"CA",
    "sg:address":"118 Humphrey Rd",
    "sg:city":"Labrador City",
    "sg:classifiers":[
        {
            "category":"Government",
            "subcategory":"Office",
            "type":"Public Place"
        }
    ],
    "sg:phone":"+1 709 944 5859",
    "sg:postcode":"A2V 2J8",
    "sg:province":"NL",
    "wof:name":"Newfoundland Certificates",
    "wof:placetype":"venue"
},
  "geometry": {"coordinates":[-66.89933776860001,52.9481506348],"type":"Point"}
}