{
  "type": "Feature",
  "properties": {
    "addr:full":"9184 Yonge St Richmond Hill ON L4C 7A1",
    "addr:housenumber":"9184",
    "addr:postcode":"l4c 7a1",
    "addr:street":"Yonge St",
    "iso:country":"CA",
    "sg:address":"9184 Yonge St",
    "sg:city":"Richmond Hill",
    "sg:classifiers":[
        {
            "category":"Shopping",
            "subcategory":"Optical Goods",
            "type":"Retail Goods"
        }
    ],
    "sg:phone":"+1 905 764 6538",
    "sg:postcode":"L4C 7A1",
    "sg:province":"ON",
    "sg:tags":[
        "optician"
    ],
    "wof:name":"Optical Shop of Richmond Hill",
    "wof:placetype":"venue"
},
  "geometry": {"coordinates":[-79.43274700000001,43.851173],"type":"Point"}
}