{
  "type": "Feature",
  "properties": {
    "addr:full":"521 Village Green Ave London ON N6K 1G3",
    "addr:housenumber":"521",
    "addr:postcode":"n6k 1g3",
    "addr:street":"Village Green Ave",
    "iso:country":"CA",
    "sg:address":"521 Village Green Ave",
    "sg:city":"London",
    "sg:classifiers":[
        {
            "category":"Organizations",
            "subcategory":"Religious Organization",
            "type":"Services"
        }
    ],
    "sg:phone":"+1 519 472 3443",
    "sg:postcode":"N6K 1G3",
    "sg:province":"ON",
    "sg:tags":[
        "church"
    ],
    "wof:name":"Westmount Presbyterian Church",
    "wof:placetype":"venue"
},
  "geometry": {"coordinates":[-81.29010009770001,42.9508361816],"type":"Point"}
}