{
  "type": "Feature",
  "properties": {
    "addr:full":"27 Av Philippe Notre-Dame-Des-Prairies QC J6E 1X2",
    "addr:postcode":"j6e 1x2",
    "addr:street":"27 Av Philippe",
    "iso:country":"CA",
    "sg:address":"27 Av Philippe",
    "sg:city":"Notre-Dame-Des-Prairies",
    "sg:classifiers":[
        {
            "category":"Professional",
            "subcategory":"Accounting & Tax Preparation",
            "type":"Services"
        }
    ],
    "sg:phone":"+1 450 753 5450",
    "sg:postcode":"J6E 1X2",
    "sg:province":"QC",
    "sg:tags":[
        "bookkeeping",
        "return",
        "system",
        "filing"
    ],
    "wof:name":"Services D'Informatique Inc",
    "wof:placetype":"venue"
},
  "geometry": {"coordinates":[-73.430305,46.050816],"type":"Point"}
}