{
  "type": "Feature",
  "properties": {
    "addr:full":"3305 Cambie St Vancouver BC V5Z 2W6",
    "addr:housenumber":"3305",
    "addr:postcode":"v5z 2w6",
    "addr:street":"Cambie St",
    "iso:country":"CA",
    "sg:address":"3305 Cambie St",
    "sg:city":"Vancouver",
    "sg:classifiers":[
        {
            "category":"Restaurant",
            "type":"Food & Drink"
        }
    ],
    "sg:phone":"+1 604 874 6020",
    "sg:postcode":"V5Z 2W6",
    "sg:province":"BC",
    "wof:name":"Tomato Fresh Food Cafe",
    "wof:placetype":"venue"
},
  "geometry": {"coordinates":[-123.11528800000001,49.255844],"type":"Point"}
}