{
  "type": "Feature",
  "properties": {
    "addr:full":"225 Boul DE LA Gappe # 13 Gatineau QC J8T 7Y3",
    "addr:housenumber":"225",
    "addr:postcode":"j8t 7y3",
    "addr:street":"Boul De La Gappe # 13",
    "iso:country":"CA",
    "sg:address":"225 Boul DE LA Gappe # 13",
    "sg:city":"Gatineau",
    "sg:classifiers":[
        {
            "category":"Shopping",
            "subcategory":"Computers & Home Electronics",
            "type":"Retail Goods"
        }
    ],
    "sg:phone":"+1 819 243 1918",
    "sg:postcode":"J8T 7Y3",
    "sg:province":"QC",
    "sg:tags":[
        "game",
        "video"
    ],
    "wof:name":"Super Jeux Video",
    "wof:placetype":"venue"
},
  "geometry": {"coordinates":[-75.706795,45.475986],"type":"Point"}
}