{
  "type": "Feature",
  "properties": {
    "addr:full":"2985 Vivian Sideroad Newmarket ON L3Y 4W1",
    "addr:housenumber":"2985",
    "addr:postcode":"l3y 4w1",
    "addr:street":"Vivian Sideroad",
    "iso:country":"CA",
    "sg:address":"2985 Vivian Sideroad",
    "sg:city":"Newmarket",
    "sg:classifiers":[
        {
            "category":"Retail",
            "subcategory":"Auto Repair",
            "type":"Services"
        }
    ],
    "sg:phone":"+1 905 853 4758",
    "sg:postcode":"L3Y 4W1",
    "sg:province":"ON",
    "sg:tags":[
        "repairing",
        "automobile"
    ],
    "wof:name":"Tms Total Motor Svc",
    "wof:placetype":"venue"
},
  "geometry": {"coordinates":[-79.458572,44.04018],"type":"Point"}
}