{
  "type": "Feature",
  "properties": {
    "addr:full":"1402 College Dr Saskatoon SK S7N 0W7",
    "addr:housenumber":"1402",
    "addr:postcode":"s7n 0w7",
    "addr:street":"College Dr",
    "iso:country":"CA",
    "sg:address":"1402 College Dr",
    "sg:city":"Saskatoon",
    "sg:classifiers":[
        {
            "category":"Shopping",
            "subcategory":"Books",
            "type":"Retail Goods"
        }
    ],
    "sg:phone":"+1 306 652 0244",
    "sg:postcode":"S7N 0W7",
    "sg:province":"SK",
    "sg:tags":[
        "dealer"
    ],
    "wof:name":"Books Unlimited",
    "wof:placetype":"venue"
},
  "geometry": {"coordinates":[-106.636139,52.128796],"type":"Point"}
}