{
  "type": "Feature",
  "properties": {
    "iso:country":"CA",
    "sg:city":"Grande Prairie",
    "sg:classifiers":[
        {
            "category":"Government",
            "subcategory":"Office",
            "type":"Public Place"
        }
    ],
    "sg:phone":"+1 780 538 5230",
    "sg:postcode":"T8V 6J4",
    "sg:province":"AB",
    "wof:name":"Alberta Economic Development",
    "wof:placetype":"venue"
},
  "geometry": {"coordinates":[-118.79158,55.173569],"type":"Point"}
}