{
  "type": "Feature",
  "properties": {
    "addr:full":"Toulinquet Twillingate NL A0G 4M0",
    "addr:postcode":"a0g 4m0",
    "addr:street":"Twillingate",
    "iso:country":"CA",
    "sg:address":"Toulinquet",
    "sg:city":"Twillingate",
    "sg:classifiers":[
        {
            "category":"Professional",
            "subcategory":"Accounting & Tax Preparation",
            "type":"Services"
        }
    ],
    "sg:phone":"+1 709 884 5517",
    "sg:postcode":"A0G 4M0",
    "sg:province":"NL",
    "sg:tags":[
        "return",
        "filing"
    ],
    "wof:name":"H & R Block Canada Inc",
    "wof:placetype":"venue"
},
  "geometry": {"coordinates":[-54.775974,49.656921],"type":"Point"}
}