{
  "type": "Feature",
  "properties": {
    "iso:country":"CA",
    "sg:city":"Vancouver",
    "sg:classifiers":[
        {
            "category":"Shopping",
            "type":"Retail Goods"
        }
    ],
    "sg:phone":"+1 604 438 1111",
    "sg:postcode":"V6C 1A1",
    "sg:province":"BC",
    "sg:tags":[
        "art",
        "gallery",
        "dealer"
    ],
    "wof:name":"Native Spirits Arts Alliance",
    "wof:placetype":"venue"
},
  "geometry": {"coordinates":[-123.114319,49.285721],"type":"Point"}
}