{
  "type": "Feature",
  "properties": {
    "iso:country":"CA",
    "sg:address":"2412 Cleroux Cres",
    "sg:city":"Gloucester",
    "sg:classifiers":[
        {
            "category":"Health Services",
            "subcategory":"Nursing And Care Facility",
            "type":"Services"
        }
    ],
    "sg:phone":"+1 613 837 7467",
    "sg:postcode":"K1W 1A3",
    "sg:province":"ON",
    "sg:tags":[
        "home",
        "retirement",
        "community"
    ],
    "wof:name":"Blackburn Lodge Seniors Res",
    "wof:placetype":"venue"
},
  "geometry": {"coordinates":[-75.55113220210001,45.436630249],"type":"Point"}
}