{
  "type": "Feature",
  "properties": {
    "addr:full":"Calgary AB T2L 1V9",
    "addr:postcode":"t2l 1v9",
    "iso:country":"CA",
    "sg:city":"Calgary",
    "sg:classifiers":[
        {
            "category":"Health Services",
            "subcategory":"Doctor",
            "type":"Services"
        }
    ],
    "sg:phone":"+1 403 282 9445",
    "sg:postcode":"T2L 1V9",
    "sg:province":"AB",
    "sg:tags":[
        "physician",
        "surgeon"
    ],
    "wof:name":"Vant, Ted MD",
    "wof:placetype":"venue"
},
  "geometry": {"coordinates":[-114.13908386200001,51.1010894775],"type":"Point"}
}