{
  "type": "Feature",
  "properties": {
    "addr:full":"4923 52nd St Thorsby AB T0C 2P0",
    "addr:housenumber":"4923",
    "addr:postcode":"t0c 2p0",
    "addr:street":"52Nd St",
    "iso:country":"CA",
    "sg:address":"4923 52nd St",
    "sg:city":"Thorsby",
    "sg:classifiers":[
        {
            "category":"Retail",
            "subcategory":"Auto Repair",
            "type":"Services"
        }
    ],
    "sg:phone":"+1 780 789 3975",
    "sg:postcode":"T0C 2P0",
    "sg:province":"AB",
    "sg:tags":[
        "repairing",
        "tire"
    ],
    "wof:name":"Thorsby Tire Shop Ltd",
    "wof:placetype":"venue"
},
  "geometry": {"coordinates":[-114.046905518,53.2296104431],"type":"Point"}
}