{
  "type": "Feature",
  "properties": {
    "addr:full":"PO Box 355 Caroline AB T0M 0M0",
    "addr:housenumber":"po;355",
    "addr:postcode":"t0m 0m0",
    "addr:street":"Box",
    "iso:country":"CA",
    "sg:address":"PO Box 355",
    "sg:city":"Caroline",
    "sg:classifiers":[
        {
            "category":"Mining & Drilling",
            "type":"Manufacturing & Wholesale Goods"
        }
    ],
    "sg:phone":"+1 403 722 2250",
    "sg:postcode":"T0M 0M0",
    "sg:province":"AB",
    "sg:tags":[
        "consultant",
        "oil",
        "gas"
    ],
    "wof:name":"Log-Ber Enterprises Inc",
    "wof:placetype":"venue"
},
  "geometry": {"coordinates":[-114.740707,52.09359],"type":"Point"}
}