{
  "type": "Feature",
  "properties": {
    "addr:full":"Concord ON L4K 1A3",
    "addr:postcode":"l4k 1a3",
    "iso:country":"CA",
    "sg:city":"Concord",
    "sg:classifiers":[
        {
            "category":"Retail",
            "subcategory":"Auto Repair",
            "type":"Services"
        }
    ],
    "sg:phone":"+1 905 738 3531",
    "sg:postcode":"L4K 1A3",
    "sg:province":"ON",
    "sg:tags":[
        "body",
        "automobile",
        "painting"
    ],
    "wof:name":"Fine Line Auto Ctr",
    "wof:placetype":"venue"
},
  "geometry": {"coordinates":[-79.517563,43.788891],"type":"Point"}
}