{
  "type": "Feature",
  "properties": {
    "iso:country":"CA",
    "sg:address":"9 Rue Mathurin",
    "sg:city":"Gaspe",
    "sg:classifiers":[
        {
            "category":"Education",
            "subcategory":"Library",
            "type":"Public Place"
        }
    ],
    "sg:phone":"+1 418 269 3988",
    "sg:postcode":"G4X 4A8",
    "sg:province":"QC",
    "wof:name":"Biblio Anse-A-Valleau",
    "wof:placetype":"venue"
},
  "geometry": {"coordinates":[-64.4806671143,48.831451416],"type":"Point"}
}