{
  "type": "Feature",
  "properties": {
    "addr:full":"North York ON M3B 3N7",
    "addr:postcode":"m3b 3n7",
    "iso:country":"CA",
    "sg:city":"North York",
    "sg:classifiers":[
        {
            "category":"Real Estate",
            "subcategory":"Real Estate Agent",
            "type":"Services"
        }
    ],
    "sg:phone":"+1 416 443 9275",
    "sg:postcode":"M3B 3N7",
    "sg:province":"ON",
    "wof:name":"Associates International",
    "wof:placetype":"venue"
},
  "geometry": {"coordinates":[-79.34624481199999,43.7471199036],"type":"Point"}
}