{
  "type": "Feature",
  "properties": {
    "addr:full":"1675 Tenth Line Rd Orleans ON K1E 3P6",
    "addr:housenumber":"1675",
    "addr:postcode":"k1e 3p6",
    "addr:street":"Tenth Line Rd",
    "iso:country":"CA",
    "sg:address":"1675 Tenth Line Rd",
    "sg:city":"Orleans",
    "sg:classifiers":[
        {
            "category":"Retail",
            "subcategory":"Laundry & Dry Cleaning",
            "type":"Services"
        }
    ],
    "sg:phone":"+1 613 837 5807",
    "sg:postcode":"K1E 3P6",
    "sg:province":"ON",
    "sg:tags":[
        "cleaners"
    ],
    "wof:name":"Brown's Cleaners",
    "wof:placetype":"venue"
},
  "geometry": {"coordinates":[-75.511414,45.480122],"type":"Point"}
}