{
  "type": "Feature",
  "properties": {
    "addr:full":"245 Third St Kitimat BC V8C 2N8",
    "addr:housenumber":"245",
    "addr:postcode":"bc v8c 2n8",
    "addr:street":"Third St",
    "iso:country":"CA",
    "sg:address":"245 Third St",
    "sg:city":"Kitimat",
    "sg:classifiers":[
        {
            "category":"Manufacturing",
            "subcategory":"Metals",
            "type":"Manufacturing & Wholesale Goods"
        }
    ],
    "sg:phone":"+1 250 632 6859",
    "sg:postcode":"V8C 2N8",
    "sg:province":"BC",
    "sg:tags":[
        "machine",
        "shop"
    ],
    "wof:name":"101 Industries Ltd",
    "wof:placetype":"venue"
},
  "geometry": {"coordinates":[-128.690979,54.057907],"type":"Point"}
}