{
  "type": "Feature",
  "properties": {
    "addr:full":"180 Ch DE LA Grande-Grillade Saint-Henri-DE-Levis QC G0R 3E0",
    "addr:housenumber":"180",
    "addr:postcode":"g0r 3e0",
    "addr:street":"Ch De La Grande-Grillade Saint-Henri-De-Levis",
    "iso:country":"CA",
    "sg:address":"180 Ch DE LA Grande-Grillade",
    "sg:city":"Saint-Henri-DE-Levis",
    "sg:classifiers":[
        {
            "category":"Building & Trades",
            "subcategory":"Electrical",
            "type":"Services"
        }
    ],
    "sg:phone":"+1 418 882 2504",
    "sg:postcode":"G0R 3E0",
    "sg:province":"QC",
    "sg:tags":[
        "electric",
        "contractor"
    ],
    "wof:name":"Roy Georges-Etienne Inc",
    "wof:placetype":"venue"
},
  "geometry": {"coordinates":[-71.176940918,46.80286026],"type":"Point"}
}