{
  "type": "Feature",
  "properties": {
    "addr:full":"1301 4E Av # A LA Pocatiere QC G0R 1Z0",
    "addr:housenumber":"1301",
    "addr:postcode":"g0r 1z0",
    "addr:street":"4E Av # A La Pocatiere",
    "iso:country":"CA",
    "sg:address":"1301 4E Av # A",
    "sg:city":"LA Pocatiere",
    "sg:classifiers":[
        {
            "category":"Retail",
            "subcategory":"Veterinary Services",
            "type":"Services"
        }
    ],
    "sg:phone":"+1 418 856 3648",
    "sg:postcode":"G0R 1Z0",
    "sg:province":"QC",
    "sg:tags":[
        "veterinarian"
    ],
    "wof:name":"Veilleux, Isabelle DVM",
    "wof:placetype":"venue"
},
  "geometry": {"coordinates":[-70.3518066406,47.1060943604],"type":"Point"}
}