{
  "type": "Feature",
  "properties": {
    "addr:full":"Calgary AB T3K 1J7",
    "addr:postcode":"t3k 1j7",
    "iso:country":"CA",
    "sg:city":"Calgary",
    "sg:classifiers":[
        {
            "category":"Health Services",
            "subcategory":"Doctor",
            "type":"Services"
        }
    ],
    "sg:phone":"+1 403 275 1141",
    "sg:postcode":"T3K 1J7",
    "sg:province":"AB",
    "sg:tags":[
        "physician",
        "surgeon"
    ],
    "wof:name":"Hoy, Wayne K MD",
    "wof:placetype":"venue"
},
  "geometry": {"coordinates":[-114.07118199999999,51.127377],"type":"Point"}
}