{
  "type": "Feature",
  "properties": {
    "addr:full":"2247 Kipling St Ottawa ON K1H 6T4",
    "addr:housenumber":"2247",
    "addr:postcode":"k1h 6t4",
    "addr:street":"Kipling St",
    "iso:country":"CA",
    "sg:address":"2247 Kipling St",
    "sg:city":"Ottawa",
    "sg:classifiers":[
        {
            "category":"Professional",
            "subcategory":"Management & Consulting",
            "type":"Services"
        }
    ],
    "sg:phone":"+1 613 738 9088",
    "sg:postcode":"K1H 6T4",
    "sg:province":"ON",
    "sg:tags":[
        "consultant",
        "business"
    ],
    "wof:name":"Tom Egan & Assoc",
    "wof:placetype":"venue"
},
  "geometry": {"coordinates":[-75.63867999999999,45.38625],"type":"Point"}
}