{
  "type": "Feature",
  "properties": {
    "addr:full":"1860 Sutherland Ave North Vancouver BC V7L 4C2",
    "addr:housenumber":"1860",
    "addr:postcode":"v7l 4c2",
    "addr:street":"Sutherland Ave",
    "iso:country":"CA",
    "sg:address":"1860 Sutherland Ave",
    "sg:city":"North Vancouver",
    "sg:classifiers":[
        {
            "category":"Education",
            "subcategory":"School",
            "type":"Public Place"
        }
    ],
    "sg:phone":"+1 604 903 3500",
    "sg:postcode":"V7L 4C2",
    "sg:province":"BC",
    "wof:name":"Sutherland Secondary School",
    "wof:placetype":"venue"
},
  "geometry": {"coordinates":[-123.05444300000001,49.325615],"type":"Point"}
}