{
  "type": "Feature",
  "properties": {
    "iso:country":"CA",
    "sg:address":"1860 Sutherland Ave",
    "sg:city":"North Vancouver",
    "sg:classifiers":[
        {
            "category":"Education",
            "subcategory":"School",
            "type":"Public Place"
        }
    ],
    "sg:phone":"+1 604 903 3500",
    "sg:postcode":"V7L 4C2",
    "sg:province":"BC",
    "wof:name":"Sutherland Secondary School",
    "wof:placetype":"venue"
},
  "geometry": {"coordinates":[-123.054443,49.325615],"type":"Point"}
}