{
  "type": "Feature",
  "properties": {
    "addr:full":"100 City Centre Dr # 2 Mississauga ON L5B 2C9",
    "addr:housenumber":"100",
    "addr:postcode":"l5b 2c9",
    "addr:street":"City Centre Dr # 2",
    "iso:country":"CA",
    "sg:address":"100 City Centre Dr # 2",
    "sg:city":"Mississauga",
    "sg:classifiers":[
        {
            "category":"Shopping",
            "subcategory":"Clothing, Apparel, & Fashions",
            "type":"Retail Goods"
        }
    ],
    "sg:phone":"+1 905 949 0600",
    "sg:postcode":"L5B 2C9",
    "sg:province":"ON",
    "wof:name":"Aritzia",
    "wof:placetype":"venue"
},
  "geometry": {"coordinates":[-79.6395111084,43.5920944214],"type":"Point"}
}