{
  "type": "Feature",
  "properties": {
    "addr:full":"1035 Gerrard St E Toronto ON M4M 1Z6",
    "addr:housenumber":"1035",
    "addr:postcode":"m4m 1z6",
    "addr:street":"Gerrard St E",
    "iso:country":"CA",
    "sg:address":"1035 Gerrard St E",
    "sg:city":"Toronto",
    "sg:classifiers":[
        {
            "category":"Arts & Performance",
            "subcategory":"Theater",
            "type":"Entertainment"
        }
    ],
    "sg:phone":"+1 416 466 3636",
    "sg:postcode":"M4M 1Z6",
    "sg:province":"ON",
    "wof:name":"Sri Lakshmi Theatre",
    "wof:placetype":"venue"
},
  "geometry": {"coordinates":[-79.336853,43.6688],"type":"Point"}
}