{
  "type": "Feature",
  "properties": {
    "iso:country":"CA",
    "sg:address":"612 Av Bloomfield",
    "sg:city":"Outremont",
    "sg:classifiers":[
        {
            "category":"Personal",
            "subcategory":"Beauty Salon",
            "type":"Services"
        }
    ],
    "sg:phone":"+1 514 273 8181",
    "sg:postcode":"H2V 3S1",
    "sg:province":"QC",
    "wof:name":"Coiffure Koula",
    "wof:placetype":"venue"
},
  "geometry": {"coordinates":[-73.608818,45.520599],"type":"Point"}
}