{
  "type": "Feature",
  "properties": {
    "addr:full":"1020 Ch Du Golf L'Assomption QC J5W 1K3",
    "addr:postcode":"1020;j5w 1k3",
    "addr:street":"Ch Du Golf",
    "iso:country":"CA",
    "sg:address":"1020 Ch Du Golf",
    "sg:city":"L'Assomption",
    "sg:classifiers":[
        {
            "category":"Sports & Exercise",
            "subcategory":"Golf",
            "type":"Entertainment"
        }
    ],
    "sg:phone":"+1 450 589 5687",
    "sg:postcode":"J5W 1K3",
    "sg:province":"QC",
    "sg:tags":[
        "course"
    ],
    "wof:name":"Club DE Golf Le Portage Inc",
    "wof:placetype":"venue"
},
  "geometry": {"coordinates":[-73.43939208979999,45.8314323425],"type":"Point"}
}