{
  "type": "Feature",
  "properties": {
    "iso:country":"CA",
    "sg:city":"Larrys River",
    "sg:classifiers":[
        {
            "category":"Travel",
            "subcategory":"Hotels & Motels",
            "type":"Entertainment"
        }
    ],
    "sg:phone":"+1 902 358 2605",
    "sg:postcode":"B0H 1T0",
    "sg:province":"NS",
    "sg:tags":[
        "breakfast",
        "accommodation",
        "bed"
    ],
    "wof:name":"Foxberry By the Sea",
    "wof:placetype":"venue"
},
  "geometry": {"coordinates":[-61.3761558533,45.2202339172],"type":"Point"}
}