{
  "type": "Feature",
  "properties": {
    "addr:full":"3651 10th Ave W Vancouver BC V6R 2G2",
    "addr:housenumber":"3651",
    "addr:postcode":"v6r 2g2",
    "addr:street":"10Th Ave W",
    "iso:country":"CA",
    "sg:address":"3651 10th Ave W",
    "sg:city":"Vancouver",
    "sg:classifiers":[
        {
            "category":"Shopping",
            "subcategory":"Used Merchandise",
            "type":"Retail Goods"
        }
    ],
    "sg:phone":"+1 604 731 7576",
    "sg:postcode":"V6R 2G2",
    "sg:province":"BC",
    "sg:tags":[
        "furniture"
    ],
    "wof:name":"Folkart Interiors",
    "wof:placetype":"venue"
},
  "geometry": {"coordinates":[-123.184776,49.263592],"type":"Point"}
}