{
  "type": "Feature",
  "properties": {
    "addr:full":"Vancouver BC V6E 4A4",
    "addr:postcode":"v6e 4a4",
    "iso:country":"CA",
    "sg:city":"Vancouver",
    "sg:classifiers":[
        {
            "category":"Professional",
            "subcategory":"Management & Consulting",
            "type":"Services"
        }
    ],
    "sg:phone":"+1 604 681 0776",
    "sg:postcode":"V6E 4A4",
    "sg:province":"BC",
    "sg:tags":[
        "consultant",
        "business"
    ],
    "wof:name":"Peta Consultants Ltd",
    "wof:placetype":"venue"
},
  "geometry": {"coordinates":[-123.121910095,49.2878952026],"type":"Point"}
}