{
  "type": "Feature",
  "properties": {
    "iso:country":"CA",
    "sg:city":"Kamloops",
    "sg:classifiers":[
        {
            "category":"Health Services",
            "subcategory":"Doctor",
            "type":"Services"
        }
    ],
    "sg:phone":"+1 250 372 2535",
    "sg:postcode":"V2C 5R9",
    "sg:province":"BC",
    "sg:tags":[
        "physician",
        "surgeon"
    ],
    "wof:name":"Simpson, Terry MD",
    "wof:placetype":"venue"
},
  "geometry": {"coordinates":[-120.349845886,50.6653556824],"type":"Point"}
}