{
  "type": "Feature",
  "properties": {
    "addr:full":"5114 Aa Mcdonald Hwy Montague PE C0A 1R0",
    "addr:postcode":"5114 aa;c0a 1r0",
    "addr:street":"Mcdonald Hwy",
    "iso:country":"CA",
    "sg:address":"5114 Aa Mcdonald Hwy",
    "sg:city":"Montague",
    "sg:classifiers":[
        {
            "category":"Wholesale",
            "subcategory":"Machinery & Supplies",
            "type":"Manufacturing & Wholesale Goods"
        }
    ],
    "sg:phone":"+1 902 838 3903",
    "sg:postcode":"C0A 1R0",
    "sg:province":"PE",
    "sg:tags":[
        "polishing",
        "car",
        "washing",
        "cleaning"
    ],
    "wof:name":"Provincial Mobile Wash",
    "wof:placetype":"venue"
},
  "geometry": {"coordinates":[-62.6497192383,46.1671638489],"type":"Point"}
}