{
  "type": "Feature",
  "properties": {
    "iso:country":"CA",
    "sg:address":"107 Winchester St",
    "sg:city":"Toronto",
    "sg:classifiers":[
        {
            "category":"Building & Trades",
            "subcategory":"Construction",
            "type":"Services"
        }
    ],
    "sg:phone":"+1 416 924 4275",
    "sg:postcode":"M4X 1B3",
    "sg:province":"ON",
    "sg:tags":[
        "tunneling",
        "contractor"
    ],
    "wof:name":"Armagh Contractors Ltd",
    "wof:placetype":"venue"
},
  "geometry": {"coordinates":[-79.3651504517,43.6664848328],"type":"Point"}
}