{
  "type": "Feature",
  "properties": {
    "iso:country":"CA",
    "sg:city":"Bolton",
    "sg:classifiers":[
        {
            "category":"Social Services",
            "subcategory":"Child Care",
            "type":"Services"
        }
    ],
    "sg:phone":"+1 905 857 7214",
    "sg:postcode":"L7E 1E8",
    "sg:province":"ON",
    "wof:name":"Children's Castle Day Care",
    "wof:placetype":"venue"
},
  "geometry": {"coordinates":[-79.737747,43.879833],"type":"Point"}
}