{
  "type": "Feature",
  "properties": {
    "addr:full":"Toronto ON M6K 1X9",
    "addr:postcode":"m6k 1x9",
    "iso:country":"CA",
    "sg:city":"Toronto",
    "sg:classifiers":[
        {
            "category":"Arts & Performance",
            "subcategory":"Theater",
            "type":"Entertainment"
        }
    ],
    "sg:phone":"+1 416 532 3019",
    "sg:postcode":"M6K 1X9",
    "sg:province":"ON",
    "sg:tags":[
        "musician"
    ],
    "wof:name":"Arraymusic",
    "wof:placetype":"venue"
},
  "geometry": {"coordinates":[-79.420776,43.638416],"type":"Point"}
}