{
  "type": "Feature",
  "properties": {
    "addr:full":"Delta BC V4C 6R8",
    "addr:postcode":"v4c 6r8",
    "iso:country":"CA",
    "sg:city":"Delta",
    "sg:classifiers":[
        {
            "category":"Professional",
            "subcategory":"Business Services",
            "type":"Services"
        }
    ],
    "sg:phone":"+1 604 953 0500",
    "sg:postcode":"V4C 6R8",
    "sg:province":"BC",
    "sg:tags":[
        "notary"
    ],
    "wof:name":"Del Virk Notary Corp",
    "wof:placetype":"venue"
},
  "geometry": {"coordinates":[-122.890464783,49.1724967957],"type":"Point"}
}