{
  "type": "Feature",
  "properties": {
    "addr:full":"Calgary AB T3G 3N7",
    "addr:postcode":"t3g 3n7",
    "iso:country":"CA",
    "sg:city":"Calgary",
    "sg:classifiers":[
        {
            "category":"Home & Garden",
            "subcategory":"Furniture",
            "type":"Retail Goods"
        }
    ],
    "sg:phone":"+1 403 208 9190",
    "sg:postcode":"T3G 3N7",
    "sg:province":"AB",
    "wof:name":"Living Room",
    "wof:placetype":"venue"
},
  "geometry": {"coordinates":[-114.197182,51.126465],"type":"Point"}
}