{
  "type": "Feature",
  "properties": {
    "iso:country":"CA",
    "sg:address":"101 Main",
    "sg:city":"Sauble Beach",
    "sg:classifiers":[
        {
            "category":"Shopping",
            "subcategory":"Crafts & Fabrics",
            "type":"Retail Goods"
        }
    ],
    "sg:phone":"+1 519 422 0049",
    "sg:postcode":"N0H 2G0",
    "sg:province":"ON",
    "sg:tags":[
        "shop"
    ],
    "wof:name":"Tropical Trends",
    "wof:placetype":"venue"
},
  "geometry": {"coordinates":[-81.270324707,44.6294975281],"type":"Point"}
}