{
  "type": "Feature",
  "properties": {
    "addr:full":"20 Steelcase Rd W Markham ON L3R 1B2",
    "addr:housenumber":"20",
    "addr:postcode":"l3r 1b2",
    "addr:street":"Steelcase Rd W",
    "iso:country":"CA",
    "sg:address":"20 Steelcase Rd W",
    "sg:city":"Markham",
    "sg:classifiers":[
        {
            "category":"Bars & Pubs",
            "type":"Food & Drink"
        }
    ],
    "sg:phone":"+1 905 947 4444",
    "sg:postcode":"L3R 1B2",
    "sg:province":"ON",
    "wof:name":"Firkin Hospitality Group",
    "wof:placetype":"venue"
},
  "geometry": {"coordinates":[-79.351799,43.819206],"type":"Point"}
}