{
  "type": "Feature",
  "properties": {
    "iso:country":"CA",
    "sg:address":"182 Rue Queen",
    "sg:city":"Lennoxville",
    "sg:classifiers":[
        {
            "category":"Food & Beverages",
            "subcategory":"Groceries & Convenience Stores",
            "type":"Retail Goods"
        }
    ],
    "sg:phone":"+1 819 565 0211",
    "sg:postcode":"J1M 1J9",
    "sg:province":"QC",
    "wof:name":"Accommodation Pml Enr",
    "wof:placetype":"venue"
},
  "geometry": {"coordinates":[-71.856918,45.369755],"type":"Point"}
}