{
  "type": "Feature",
  "properties": {
    "addr:full":"815 1st Ave W Prince Rupert BC V8J 1B3",
    "addr:housenumber":"815",
    "addr:postcode":"v8j 1b3",
    "addr:street":"1St Ave W",
    "iso:country":"CA",
    "sg:address":"815 1st Ave W",
    "sg:city":"Prince Rupert",
    "sg:classifiers":[
        {
            "category":"Government",
            "subcategory":"Office",
            "type":"Public Place"
        }
    ],
    "sg:phone":"+1 250 624 7510",
    "sg:postcode":"V8J 1B3",
    "sg:province":"BC",
    "wof:name":"BC Mental Health",
    "wof:placetype":"venue"
},
  "geometry": {"coordinates":[-130.33116149899999,54.3111724854],"type":"Point"}
}