{
  "type": "Feature",
  "properties": {
    "iso:country":"CA",
    "sg:address":"PO Box 131",
    "sg:city":"Goodfish Lake",
    "sg:classifiers":[
        {
            "category":"Social Services",
            "type":"Services"
        }
    ],
    "sg:phone":"+1 780 636 3450",
    "sg:postcode":"T0A 1R0",
    "sg:province":"AB",
    "sg:tags":[
        "information",
        "organization",
        "treatment",
        "alcoholism",
        "welfare"
    ],
    "wof:name":"Goodfish Lake Counselling Svc",
    "wof:placetype":"venue"
},
  "geometry": {"coordinates":[-111.877555847,54.3183403015],"type":"Point"}
}