{
  "type": "Feature",
  "properties": {
    "iso:country":"CA",
    "sg:address":"1117 Morin Rd",
    "sg:city":"Cumberland",
    "sg:classifiers":[
        {
            "category":"Recreation",
            "type":"Entertainment"
        }
    ],
    "sg:phone":"+1 613 833 7414",
    "sg:postcode":"K4C 1A5",
    "sg:province":"ON",
    "sg:tags":[
        "youth",
        "information",
        "activity",
        "center",
        "organization"
    ],
    "wof:name":"Sonshine Families",
    "wof:placetype":"venue"
},
  "geometry": {"coordinates":[-75.384239,45.520786],"type":"Point"}
}