{
  "type": "Feature",
  "properties": {
    "addr:full":"10 Fieldrow St Nepean ON K2G 2Y7",
    "addr:housenumber":"10",
    "addr:postcode":"k2g 2y7",
    "addr:street":"Fieldrow St",
    "iso:country":"CA",
    "sg:address":"10 Fieldrow St",
    "sg:city":"Nepean",
    "sg:classifiers":[
        {
            "category":"Education",
            "subcategory":"School",
            "type":"Public Place"
        }
    ],
    "sg:phone":"+1 613 224 1733",
    "sg:postcode":"K2G 2Y7",
    "sg:province":"ON",
    "wof:name":"Meadowlands Public School",
    "wof:placetype":"venue"
},
  "geometry": {"coordinates":[-75.737236,45.34523],"type":"Point"}
}