{
  "type": "Feature",
  "properties": {
    "iso:country":"CA",
    "sg:address":"10153 Resthaven Dr",
    "sg:city":"Sidney",
    "sg:classifiers":[
        {
            "category":"Food & Beverages",
            "subcategory":"Groceries & Convenience Stores",
            "type":"Retail Goods"
        }
    ],
    "sg:phone":"+1 250 656 1912",
    "sg:postcode":"V8L 3G8",
    "sg:province":"BC",
    "sg:tags":[
        "grocer"
    ],
    "wof:name":"Queens Pay-Less Grocery",
    "wof:placetype":"venue"
},
  "geometry": {"coordinates":[-123.402832031,48.6572189331],"type":"Point"}
}