{
  "type": "Feature",
  "properties": {
    "addr:full":"3744 Rue Pollack Sainte-Foy QC G1X 4Z2",
    "addr:housenumber":"3744",
    "addr:postcode":"g1x 4z2",
    "addr:street":"Rue Pollack",
    "iso:country":"CA",
    "sg:address":"3744 Rue Pollack",
    "sg:city":"Sainte-Foy",
    "sg:classifiers":[
        {
            "category":"Health Services",
            "subcategory":"Health Practitioner",
            "type":"Services"
        }
    ],
    "sg:phone":"+1 418 682 3362",
    "sg:postcode":"G1X 4Z2",
    "sg:province":"QC",
    "sg:tags":[
        "psychologist"
    ],
    "wof:name":"Beaulieu, Pauline",
    "wof:placetype":"venue"
},
  "geometry": {"coordinates":[-71.333694458,46.7582893372],"type":"Point"}
}