{
  "type": "Feature",
  "properties": {
    "addr:full":"723 Front St Hearst ON P0L 1N0",
    "addr:housenumber":"723",
    "addr:postcode":"p0l 1n0",
    "addr:street":"Front St",
    "iso:country":"CA",
    "sg:address":"723 Front St",
    "sg:city":"Hearst",
    "sg:classifiers":[
        {
            "category":"Taxi",
            "type":"Transportation"
        }
    ],
    "sg:phone":"+1 705 362 6600",
    "sg:postcode":"P0L 1N0",
    "sg:province":"ON",
    "sg:tags":[
        "taxicab"
    ],
    "wof:name":"Hearst Taxi",
    "wof:placetype":"venue"
},
  "geometry": {"coordinates":[-83.66114,49.689148],"type":"Point"}
}