{
  "type": "Feature",
  "properties": {
    "addr:full":"PO Box 55 Chateh AB T0H 0S0",
    "addr:housenumber":"po box 55",
    "addr:postcode":"t0h 0s0",
    "addr:street":"Chateh Ab",
    "iso:country":"CA",
    "sg:address":"PO Box 55",
    "sg:city":"Chateh",
    "sg:classifiers":[
        {
            "category":"Utilities",
            "subcategory":"Natural Gas",
            "type":"Services"
        }
    ],
    "sg:phone":"+1 780 321 3761",
    "sg:postcode":"T0H 0S0",
    "sg:province":"AB",
    "sg:tags":[
        "company"
    ],
    "wof:name":"Dene Tha Natural Gas Utility",
    "wof:placetype":"venue"
},
  "geometry": {"coordinates":[-118.66029399999999,58.684052],"type":"Point"}
}