{
  "type": "Feature",
  "properties": {
    "iso:country":"CA",
    "sg:address":"3919 8th St E",
    "sg:city":"Saskatoon",
    "sg:classifiers":[
        {
            "category":"Health Services",
            "subcategory":"Doctor",
            "type":"Services"
        }
    ],
    "sg:phone":"+1 306 374 6884",
    "sg:postcode":"S7H 5M7",
    "sg:province":"SK",
    "sg:tags":[
        "physician",
        "surgeon"
    ],
    "wof:name":"Reiniger, R M MD",
    "wof:placetype":"venue"
},
  "geometry": {"coordinates":[-106.590942383,52.1149177551],"type":"Point"}
}