{
  "type": "Feature",
  "properties": {
    "iso:country":"CA",
    "sg:address":"1290 Clark Dr",
    "sg:city":"Vancouver",
    "sg:classifiers":[
        {
            "category":"Retail",
            "subcategory":"Auto Repair",
            "type":"Services"
        }
    ],
    "sg:phone":"+1 604 253 6341",
    "sg:postcode":"V5L 3K7",
    "sg:province":"BC",
    "sg:tags":[
        "automobile",
        "top",
        "upholstery"
    ],
    "wof:name":"Seat Cover Ctr Ltd",
    "wof:placetype":"venue"
},
  "geometry": {"coordinates":[-123.077163696,49.2733383179],"type":"Point"}
}