{
  "type": "Feature",
  "properties": {
    "addr:full":"31 Toboggan Hill Dr Orillia ON L3V 7R1",
    "addr:housenumber":"31",
    "addr:postcode":"l3v 7r1",
    "addr:street":"Toboggan Hill Dr",
    "iso:country":"CA",
    "sg:address":"31 Toboggan Hill Dr",
    "sg:city":"Orillia",
    "sg:classifiers":[
        {
            "category":"Banks & Credit Unions",
            "subcategory":"Bank",
            "type":"Services"
        }
    ],
    "sg:phone":"+1 705 329 2200",
    "sg:postcode":"L3V 7R1",
    "sg:province":"ON",
    "sg:tags":[
        "consultant",
        "financing",
        "planning",
        "financial"
    ],
    "wof:name":"Stratagem Financial Svc",
    "wof:placetype":"venue"
},
  "geometry": {"coordinates":[-79.442543,44.604862],"type":"Point"}
}