{
  "type": "Feature",
  "properties": {
    "iso:country":"CA",
    "sg:address":"912 Centre St NE",
    "sg:city":"Calgary",
    "sg:classifiers":[
        {
            "category":"Shopping",
            "subcategory":"Computers & Home Electronics",
            "type":"Retail Goods"
        }
    ],
    "sg:phone":"+1 403 230 7022",
    "sg:postcode":"T2E 2P7",
    "sg:province":"AB",
    "sg:tags":[
        "radio",
        "video",
        "equipment"
    ],
    "wof:name":"Jensen Radio & Television CO",
    "wof:placetype":"venue"
},
  "geometry": {"coordinates":[-114.04206085200001,51.0525894165],"type":"Point"}
}