{
  "type": "Feature",
  "properties": {
    "addr:full":"735 12 Ave SW Calgary AB T2R 1J7",
    "addr:postcode":"735;t2r 1j7",
    "addr:street":"12 Ave Sw",
    "iso:country":"CA",
    "sg:address":"735 12 Ave SW",
    "sg:city":"Calgary",
    "sg:classifiers":[
        {
            "category":"Restaurant",
            "type":"Food & Drink"
        }
    ],
    "sg:phone":"+1 403 244 3838",
    "sg:postcode":"T2R 1J7",
    "sg:province":"AB",
    "wof:name":"Eddy's Nest Restaurant & Pizza",
    "wof:placetype":"venue"
},
  "geometry": {"coordinates":[-114.077538,51.041672],"type":"Point"}
}