{
  "type": "Feature",
  "properties": {
    "addr:full":"455 Giles Blvd E Windsor ON N9A 7B1",
    "addr:housenumber":"455",
    "addr:postcode":"n9a 7b1",
    "addr:street":"Giles Blvd E",
    "iso:country":"CA",
    "sg:address":"455 Giles Blvd E",
    "sg:city":"Windsor",
    "sg:classifiers":[
        {
            "category":"Real Estate",
            "subcategory":"Developer",
            "type":"Services"
        }
    ],
    "sg:phone":"+1 519 969 4146",
    "sg:postcode":"N9A 7B1",
    "sg:province":"ON",
    "sg:tags":[
        "cemetery"
    ],
    "wof:name":"Windsor Grove Cemetery",
    "wof:placetype":"venue"
},
  "geometry": {"coordinates":[-83.024559,42.307919],"type":"Point"}
}