{
  "type": "Feature",
  "properties": {
    "iso:country":"CA",
    "sg:address":"3272 Main St",
    "sg:city":"Vancouver",
    "sg:classifiers":[
        {
            "category":"Building & Trades",
            "subcategory":"Plumbing",
            "type":"Services"
        }
    ],
    "sg:phone":"+1 604 879 5301",
    "sg:postcode":"V5V 3M5",
    "sg:province":"BC",
    "sg:tags":[
        "contractor"
    ],
    "wof:name":"Hillcrest Plumbing & Heating",
    "wof:placetype":"venue"
},
  "geometry": {"coordinates":[-123.100998,49.256016],"type":"Point"}
}