{
  "type": "Feature",
  "properties": {
    "addr:full":"731 Ellice Ave Winnipeg MB R3G 0B3",
    "addr:housenumber":"731",
    "addr:postcode":"r3g 0b3",
    "addr:street":"Ellice Ave",
    "iso:country":"CA",
    "sg:address":"731 Ellice Ave",
    "sg:city":"Winnipeg",
    "sg:classifiers":[
        {
            "category":"Retail",
            "subcategory":"Auto Repair",
            "type":"Services"
        }
    ],
    "sg:phone":"+1 204 775 2886",
    "sg:postcode":"R3G 0B3",
    "sg:province":"MB",
    "sg:tags":[
        "repairing",
        "automobile"
    ],
    "wof:name":"Beverley Auto Ctr",
    "wof:placetype":"venue"
},
  "geometry": {"coordinates":[-97.164787,49.893261],"type":"Point"}
}