{
  "type": "Feature",
  "properties": {
    "addr:full":"15355 111 Ave NW Edmonton AB T5M 2R3",
    "addr:housenumber":"15355",
    "addr:postcode":"t5m 2r3",
    "addr:street":"111 Ave Nw",
    "iso:country":"CA",
    "sg:address":"15355 111 Ave NW",
    "sg:city":"Edmonton",
    "sg:classifiers":[
        {
            "category":"Retail",
            "subcategory":"Auto Repair",
            "type":"Services"
        }
    ],
    "sg:phone":"+1 780 487 8034",
    "sg:postcode":"T5M 2R3",
    "sg:province":"AB",
    "sg:tags":[
        "automobile",
        "lubrication"
    ],
    "wof:name":"Lube-X Service Ctr",
    "wof:placetype":"venue"
},
  "geometry": {"coordinates":[-113.585845947,53.5585708618],"type":"Point"}
}