{
  "type": "Feature",
  "properties": {
    "addr:full":"990 Fraser Dr Burlington ON L7L 5P5",
    "addr:housenumber":"990",
    "addr:postcode":"l7l 5p5",
    "addr:street":"Fraser Dr",
    "iso:country":"CA",
    "sg:address":"990 Fraser Dr",
    "sg:city":"Burlington",
    "sg:classifiers":[
        {
            "category":"Home & Garden",
            "subcategory":"Furniture",
            "type":"Retail Goods"
        }
    ],
    "sg:phone":"+1 905 333 5533",
    "sg:postcode":"L7L 5P5",
    "sg:province":"ON",
    "sg:tags":[
        "appliance"
    ],
    "wof:name":"Brick Warehouse Corp",
    "wof:placetype":"venue"
},
  "geometry": {"coordinates":[-79.784691,43.367397],"type":"Point"}
}