{
  "type": "Feature",
  "properties": {
    "addr:full":"Main St Springdale NL A0J 1T0",
    "addr:postcode":"a0j 1t0",
    "addr:street":"Main St",
    "iso:country":"CA",
    "sg:address":"Main St",
    "sg:city":"Springdale",
    "sg:classifiers":[
        {
            "category":"Shopping",
            "subcategory":"Used Merchandise",
            "type":"Retail Goods"
        }
    ],
    "sg:phone":"+1 709 673 3216",
    "sg:postcode":"A0J 1T0",
    "sg:province":"NL",
    "sg:tags":[
        "second",
        "store",
        "hand"
    ],
    "wof:name":"Salvation Army Thrift Store",
    "wof:placetype":"venue"
},
  "geometry": {"coordinates":[-56.0667572021,49.5018081665],"type":"Point"}
}