{
  "type": "Feature",
  "properties": {
    "addr:full":"652 Eramosa Cres Pickering ON L1V 5M9",
    "addr:housenumber":"652",
    "addr:postcode":"l1v 5m9",
    "addr:street":"Eramosa Cres",
    "iso:country":"CA",
    "sg:address":"652 Eramosa Cres",
    "sg:city":"Pickering",
    "sg:classifiers":[
        {
            "category":"Freight",
            "type":"Transportation"
        }
    ],
    "sg:phone":"+1 905 420 4824",
    "sg:postcode":"L1V 5M9",
    "sg:province":"ON",
    "sg:tags":[
        "trucking"
    ],
    "wof:name":"Sea Drive Transportaton",
    "wof:placetype":"venue"
},
  "geometry": {"coordinates":[-79.126717,43.834213],"type":"Point"}
}