{
  "type": "Feature",
  "properties": {
    "addr:full":"37 Industrial Dr Sussex NB E4E 2R7",
    "addr:housenumber":"37",
    "addr:postcode":"e4e 2r7",
    "addr:street":"Industrial Dr",
    "iso:country":"CA",
    "sg:address":"37 Industrial Dr",
    "sg:city":"Sussex",
    "sg:classifiers":[
        {
            "category":"Wholesale",
            "subcategory":"Electrical",
            "type":"Manufacturing & Wholesale Goods"
        }
    ],
    "sg:phone":"+1 506 433 1334",
    "sg:postcode":"E4E 2R7",
    "sg:province":"NB",
    "sg:tags":[
        "equipment",
        "electric",
        "supply"
    ],
    "wof:name":"Liteco",
    "wof:placetype":"venue"
},
  "geometry": {"coordinates":[-65.492249,45.72858],"type":"Point"}
}