{
  "type": "Feature",
  "properties": {
    "addr:full":"1933 W Island Hwy Qualicum Beach BC V9K 2B3",
    "addr:housenumber":"1933",
    "addr:postcode":"v9k 2b3",
    "addr:street":"W Island Hwy",
    "iso:country":"CA",
    "sg:address":"1933 W Island Hwy",
    "sg:city":"Qualicum Beach",
    "sg:classifiers":[
        {
            "category":"Travel",
            "subcategory":"Hotels & Motels",
            "type":"Entertainment"
        }
    ],
    "sg:phone":"+1 250 752 6652",
    "sg:postcode":"V9K 2B3",
    "sg:province":"BC",
    "sg:tags":[
        "resort"
    ],
    "wof:name":"St Andrew's Lodge & Glen Cttgs",
    "wof:placetype":"venue"
},
  "geometry": {"coordinates":[-124.403015,49.350193],"type":"Point"}
}