{
  "type": "Feature",
  "properties": {
    "addr:full":"8641 Boul Cloutier Charlesbourg QC G1G 4Z7",
    "addr:housenumber":"8641",
    "addr:postcode":"g1g 4z7",
    "addr:street":"Boul Cloutier",
    "iso:country":"CA",
    "sg:address":"8641 Boul Cloutier",
    "sg:city":"Charlesbourg",
    "sg:classifiers":[
        {
            "category":"Organizations",
            "subcategory":"Non-profit Organization",
            "type":"Services"
        }
    ],
    "sg:phone":"+1 418 623 0971",
    "sg:postcode":"G1G 4Z7",
    "sg:province":"QC",
    "sg:tags":[
        "breastfeeding",
        "information",
        "supply"
    ],
    "wof:name":"Allaitement Quebec Inc",
    "wof:placetype":"venue"
},
  "geometry": {"coordinates":[-71.276794,46.863907],"type":"Point"}
}