{
  "type": "Feature",
  "properties": {
    "addr:full":"West Vancouver BC V7T 1A8",
    "addr:postcode":"v7t 1a8",
    "iso:country":"CA",
    "sg:city":"West Vancouver",
    "sg:classifiers":[
        {
            "category":"Professional",
            "subcategory":"Lawyer & Legal Services",
            "type":"Services"
        }
    ],
    "sg:phone":"+1 604 926 1120",
    "sg:postcode":"V7T 1A8",
    "sg:province":"BC",
    "sg:tags":[
        "attorney"
    ],
    "wof:name":"Sikula, M Michael",
    "wof:placetype":"venue"
},
  "geometry": {"coordinates":[-123.141693,49.326996],"type":"Point"}
}