{
  "type": "Feature",
  "properties": {
    "addr:full":"1439 Rue Saint-Mathieu # B Montreal QC H3H 2M4",
    "addr:housenumber":"1439;# b",
    "addr:postcode":"h3h 2m4",
    "addr:street":"Rue Saint-Mathieu",
    "iso:country":"CA",
    "sg:address":"1439 Rue Saint-Mathieu # B",
    "sg:city":"Montreal",
    "sg:classifiers":[
        {
            "category":"Health Services",
            "subcategory":"Doctor",
            "type":"Services"
        }
    ],
    "sg:phone":"+1 514 939 3368",
    "sg:postcode":"H3H 2M4",
    "sg:province":"QC",
    "sg:tags":[
        "dentist"
    ],
    "wof:name":"Clinique Dentaire Qualite",
    "wof:placetype":"venue"
},
  "geometry": {"coordinates":[-73.579643,45.49424],"type":"Point"}
}