{
  "type": "Feature",
  "properties": {
    "addr:full":"3714 Rue Ontario E Montreal QC H1W 1R9",
    "addr:housenumber":"3714",
    "addr:postcode":"h1w 1r9",
    "addr:street":"Rue Ontario E",
    "iso:country":"CA",
    "sg:address":"3714 Rue Ontario E",
    "sg:city":"Montreal",
    "sg:classifiers":[
        {
            "category":"Professional",
            "subcategory":"Business Services",
            "type":"Services"
        }
    ],
    "sg:phone":"+1 514 526 5519",
    "sg:postcode":"H1W 1R9",
    "sg:province":"QC",
    "sg:tags":[
        "notary"
    ],
    "wof:name":"Boucher & Champagne",
    "wof:placetype":"venue"
},
  "geometry": {"coordinates":[-73.54393,45.546215],"type":"Point"}
}