{
  "type": "Feature",
  "properties": {
    "addr:full":"4093 Temperance Rd Wallenstein ON N0B 2S0",
    "addr:housenumber":"4093",
    "addr:postcode":"n0b 2s0",
    "addr:street":"Temperance Rd",
    "iso:country":"CA",
    "sg:address":"4093 Temperance Rd",
    "sg:city":"Wallenstein",
    "sg:classifiers":[
        {
            "category":"Farming",
            "subcategory":"Farm",
            "type":"Manufacturing & Wholesale Goods"
        }
    ],
    "sg:phone":"+1 519 669 2123",
    "sg:postcode":"N0B 2S0",
    "sg:province":"ON",
    "wof:name":"Wideman Farms Ltd",
    "wof:placetype":"venue"
},
  "geometry": {"coordinates":[-80.634216,43.599659],"type":"Point"}
}