{
  "type": "Feature",
  "properties": {
    "addr:full":"7700 Av DE L'Epee Montreal QC H3N 2E6",
    "addr:housenumber":"7700",
    "addr:postcode":"h3n 2e6",
    "addr:street":"Av De L'Epee",
    "iso:country":"CA",
    "sg:address":"7700 Av DE L'Epee",
    "sg:city":"Montreal",
    "sg:classifiers":[
        {
            "category":"Organizations",
            "subcategory":"Professional Association",
            "type":"Services"
        }
    ],
    "sg:phone":"+1 514 273 9120",
    "sg:postcode":"H3N 2E6",
    "sg:province":"QC",
    "wof:name":"Communaute Hellenique DE Mntrl",
    "wof:placetype":"venue"
},
  "geometry": {"coordinates":[-73.621887,45.527435],"type":"Point"}
}