{
  "type": "Feature",
  "properties": {
    "addr:full":"3031 Boul Laurier Sainte-Foy QC G1V 2M2",
    "addr:housenumber":"3031",
    "addr:postcode":"g1v 2m2",
    "addr:street":"Boul Laurier",
    "iso:country":"CA",
    "sg:address":"3031 Boul Laurier",
    "sg:city":"Sainte-Foy",
    "sg:classifiers":[
        {
            "category":"Travel",
            "subcategory":"Hotels & Motels",
            "type":"Entertainment"
        }
    ],
    "sg:phone":"+1 418 658 2727",
    "sg:postcode":"G1V 2M2",
    "sg:province":"QC",
    "wof:name":"Hotel Plaza Quebec",
    "wof:placetype":"venue"
},
  "geometry": {"coordinates":[-71.293076,46.764515],"type":"Point"}
}