{
  "type": "Feature",
  "properties": {
    "addr:full":"6875 Ch DE LA Cote-DE-Liesse Saint-Laurent QC H4T 1E5",
    "addr:postcode":"6875;h4t 1e5",
    "addr:street":"Ch De La Cote-De-Liesse",
    "iso:country":"CA",
    "sg:address":"6875 Ch DE LA Cote-DE-Liesse",
    "sg:city":"Saint-Laurent",
    "sg:classifiers":[
        {
            "category":"Manufacturing",
            "subcategory":"Tools & Machinery",
            "type":"Manufacturing & Wholesale Goods"
        }
    ],
    "sg:phone":"+1 514 342 0800",
    "sg:postcode":"H4T 1E5",
    "sg:province":"QC",
    "sg:tags":[
        "machine",
        "shop",
        "system",
        "automation"
    ],
    "wof:name":"Mechtronix Systems Inc",
    "wof:placetype":"venue"
},
  "geometry": {"coordinates":[-73.6957244873,45.4830322266],"type":"Point"}
}