{
  "type": "Feature",
  "properties": {
    "addr:full":"95 Howard St Lynden ON L0R 1T0",
    "addr:housenumber":"95",
    "addr:postcode":"l0r 1t0",
    "addr:street":"Howard St",
    "iso:country":"CA",
    "sg:address":"95 Howard St",
    "sg:city":"Lynden",
    "sg:classifiers":[
        {
            "category":"Education",
            "subcategory":"School",
            "type":"Public Place"
        }
    ],
    "sg:phone":"+1 519 647 3951",
    "sg:postcode":"L0R 1T0",
    "sg:province":"ON",
    "wof:name":"Lynden Public School",
    "wof:placetype":"venue"
},
  "geometry": {"coordinates":[-80.145729,43.235409],"type":"Point"}
}