{
  "type": "Feature",
  "properties": {
    "addr:full":"23 Centre St Chatham ON N7M 4W1",
    "addr:housenumber":"23",
    "addr:postcode":"n7m 4w1",
    "addr:street":"Centre St",
    "iso:country":"CA",
    "sg:address":"23 Centre St",
    "sg:city":"Chatham",
    "sg:classifiers":[
        {
            "category":"Organizations",
            "subcategory":"Religious Organization",
            "type":"Services"
        }
    ],
    "sg:phone":"+1 519 351 4447",
    "sg:postcode":"N7M 4W1",
    "sg:province":"ON",
    "sg:tags":[
        "church"
    ],
    "wof:name":"Cornerstone Church",
    "wof:placetype":"venue"
},
  "geometry": {"coordinates":[-82.1848068237,42.4040298462],"type":"Point"}
}