{
  "type": "Feature",
  "properties": {
    "iso:country":"CA",
    "sg:address":"2800 Av Dalton",
    "sg:city":"Sainte-Foy",
    "sg:classifiers":[
        {
            "category":"Professional",
            "subcategory":"Art Services",
            "type":"Services"
        }
    ],
    "sg:phone":"+1 418 657 2225",
    "sg:postcode":"G1P 3S4",
    "sg:province":"QC",
    "sg:tags":[
        "photographer"
    ],
    "wof:name":"Photographe Marc Couture",
    "wof:placetype":"venue"
},
  "geometry": {"coordinates":[-71.309105,46.78735],"type":"Point"}
}