{
  "type": "Feature",
  "properties": {
    "addr:full":"695 Boul Saint-Joseph Drummondville QC J2C 2B6",
    "addr:housenumber":"695",
    "addr:postcode":"j2c 2b6",
    "addr:street":"Boul Saint-Joseph",
    "iso:country":"CA",
    "sg:address":"695 Boul Saint-Joseph",
    "sg:city":"Drummondville",
    "sg:classifiers":[
        {
            "category":"Food & Beverages",
            "subcategory":"Liquor & Beverages",
            "type":"Retail Goods"
        }
    ],
    "sg:phone":"+1 819 478 8184",
    "sg:postcode":"J2C 2B6",
    "sg:province":"QC",
    "sg:tags":[
        "store"
    ],
    "wof:name":"Saq Selection",
    "wof:placetype":"venue"
},
  "geometry": {"coordinates":[-72.51245900000001,45.891811],"type":"Point"}
}