{
  "type": "Feature",
  "properties": {
    "iso:country":"CA",
    "sg:address":"3901 Sissibo Rd",
    "sg:city":"Barton",
    "sg:classifiers":[
        {
            "category":"Organizations",
            "subcategory":"Religious Organization",
            "type":"Services"
        }
    ],
    "sg:phone":"+1 902 837 5003",
    "sg:postcode":"B0W 1H0",
    "sg:province":"NS",
    "sg:tags":[
        "church"
    ],
    "wof:name":"South Range Christian Church",
    "wof:placetype":"venue"
},
  "geometry": {"coordinates":[-65.8696060181,44.5409507751],"type":"Point"}
}