{
  "type": "Feature",
  "properties": {
    "addr:full":"1312 75 Ave SW Calgary AB T2V 0S6",
    "addr:housenumber":"1312",
    "addr:postcode":"t2v 0s6",
    "addr:street":"75 Ave Sw",
    "iso:country":"CA",
    "sg:address":"1312 75 Ave SW",
    "sg:city":"Calgary",
    "sg:classifiers":[
        {
            "category":"Education",
            "subcategory":"School",
            "type":"Public Place"
        }
    ],
    "sg:phone":"+1 403 777 8480",
    "sg:postcode":"T2V 0S6",
    "sg:province":"AB",
    "wof:name":"Chinook Park Elementary School",
    "wof:placetype":"venue"
},
  "geometry": {"coordinates":[-114.090416,50.986073],"type":"Point"}
}