{
  "type": "Feature",
  "properties": {
    "addr:full":"40 Ilsley Ave Dartmouth NS B3B 1L3",
    "addr:housenumber":"40",
    "addr:postcode":"b3b 1l3",
    "addr:street":"Ilsley Ave",
    "iso:country":"CA",
    "sg:address":"40 Ilsley Ave",
    "sg:city":"Dartmouth",
    "sg:classifiers":[
        {
            "category":"Building & Trades",
            "subcategory":"Construction",
            "type":"Services"
        }
    ],
    "sg:phone":"+1 902 468 5510",
    "sg:postcode":"B3B 1L3",
    "sg:province":"NS",
    "sg:tags":[
        "contractor",
        "sewer",
        "general"
    ],
    "wof:name":"Harbour Construction CO Ltd",
    "wof:placetype":"venue"
},
  "geometry": {"coordinates":[-63.592037,44.702656],"type":"Point"}
}