{
  "type": "Feature",
  "properties": {
    "addr:full":"1443 8th Ave W Vancouver BC V6H 1C9",
    "addr:housenumber":"1443",
    "addr:postcode":"v6h 1c9",
    "addr:street":"8Th Ave W",
    "iso:country":"CA",
    "sg:address":"1443 8th Ave W",
    "sg:city":"Vancouver",
    "sg:classifiers":[
        {
            "category":"Organizations",
            "subcategory":"Professional Association",
            "type":"Services"
        }
    ],
    "sg:phone":"+1 604 738 7525",
    "sg:postcode":"V6H 1C9",
    "sg:province":"BC",
    "sg:tags":[
        "club"
    ],
    "wof:name":"Odd Fellows Independent Order",
    "wof:placetype":"venue"
},
  "geometry": {"coordinates":[-123.13717699999999,49.264648],"type":"Point"}
}