{
  "type": "Feature",
  "properties": {
    "addr:full":"Mont-Saint-Hilaire QC J3H 5V3",
    "addr:postcode":"j3h 5v3",
    "iso:country":"CA",
    "sg:city":"Mont-Saint-Hilaire",
    "sg:classifiers":[
        {
            "category":"Recreation",
            "type":"Entertainment"
        }
    ],
    "sg:phone":"+1 450 446 7688",
    "sg:postcode":"J3H 5V3",
    "sg:province":"QC",
    "sg:tags":[
        "parlor",
        "billiard"
    ],
    "wof:name":"Club DE Billard L'Impact Inc",
    "wof:placetype":"venue"
},
  "geometry": {"coordinates":[-73.18483000000001,45.564388],"type":"Point"}
}