{
  "type": "Feature",
  "properties": {
    "addr:full":"112 Regent Ave W Winnipeg MB R2C 1P9",
    "addr:housenumber":"112",
    "addr:postcode":"r2c 1p9",
    "addr:street":"Regent Ave W",
    "iso:country":"CA",
    "sg:address":"112 Regent Ave W",
    "sg:city":"Winnipeg",
    "sg:classifiers":[
        {
            "category":"Insurance",
            "subcategory":"Insurance Agent",
            "type":"Services"
        }
    ],
    "sg:phone":"+1 204 222 7771",
    "sg:postcode":"R2C 1P9",
    "sg:province":"MB",
    "wof:name":"Ball Insurance",
    "wof:placetype":"venue"
},
  "geometry": {"coordinates":[-97.003197,49.894936],"type":"Point"}
}