{
  "type": "Feature",
  "properties": {
    "addr:full":"Calgary AB T2P 0L6",
    "addr:postcode":"t2p 0l6",
    "iso:country":"CA",
    "sg:city":"Calgary",
    "sg:classifiers":[
        {
            "category":"Mining & Drilling",
            "type":"Manufacturing & Wholesale Goods"
        }
    ],
    "sg:phone":"+1 403 269 5556",
    "sg:postcode":"T2P 0L6",
    "sg:province":"AB",
    "sg:tags":[
        "consultant",
        "oil",
        "gas"
    ],
    "wof:name":"Kade Technologies Inc",
    "wof:placetype":"venue"
},
  "geometry": {"coordinates":[-114.070281982,51.0486335754],"type":"Point"}
}