{
  "type": "Feature",
  "properties": {
    "iso:country":"CA",
    "sg:address":"1400 Boul Saint-Jean-Baptiste # 23",
    "sg:city":"Pointe-Aux-Trembles",
    "sg:classifiers":[
        {
            "category":"Home & Garden",
            "subcategory":"Furniture",
            "type":"Retail Goods"
        }
    ],
    "sg:phone":"+1 514 640 5617",
    "sg:postcode":"H1B 4A5",
    "sg:province":"QC",
    "sg:tags":[
        "bedding"
    ],
    "wof:name":"Literie Charlene",
    "wof:placetype":"venue"
},
  "geometry": {"coordinates":[-73.50312,45.641926],"type":"Point"}
}