{
  "type": "Feature",
  "properties": {
    "addr:full":"101 Champagne Ave S Ottawa ON K1S 4P3",
    "addr:housenumber":"101",
    "addr:postcode":"k1s 4p3",
    "addr:street":"Champagne Ave S",
    "iso:country":"CA",
    "sg:address":"101 Champagne Ave S",
    "sg:city":"Ottawa",
    "sg:classifiers":[
        {
            "category":"Government",
            "subcategory":"Office",
            "type":"Public Place"
        }
    ],
    "sg:phone":"+1 613 725 3166",
    "sg:postcode":"K1S 4P3",
    "sg:province":"ON",
    "sg:tags":[
        "organization",
        "protection",
        "animal",
        "village"
    ],
    "wof:name":"Ottawa Humane Society",
    "wof:placetype":"venue"
},
  "geometry": {"coordinates":[-75.711578,45.3988],"type":"Point"}
}