{
  "type": "Feature",
  "properties": {
    "addr:full":"10081 136A St Surrey BC V3T 4G1",
    "addr:housenumber":"10081",
    "addr:postcode":"v3t 4g1",
    "addr:street":"136A St",
    "iso:country":"CA",
    "sg:address":"10081 136A St",
    "sg:city":"Surrey",
    "sg:classifiers":[
        {
            "category":"Food & Beverages",
            "subcategory":"Groceries & Convenience Stores",
            "type":"Retail Goods"
        }
    ],
    "sg:phone":"+1 604 930 0786",
    "sg:postcode":"V3T 4G1",
    "sg:province":"BC",
    "sg:tags":[
        "grocer"
    ],
    "wof:name":"Express Convenience Store",
    "wof:placetype":"venue"
},
  "geometry": {"coordinates":[-122.830215,49.105179],"type":"Point"}
}