{
  "type": "Feature",
  "properties": {
    "addr:full":"155 Lock St E Dunnville ON N1A 1J6",
    "addr:housenumber":"155",
    "addr:postcode":"n1a 1j6",
    "addr:street":"Lock St E",
    "iso:country":"CA",
    "sg:address":"155 Lock St E",
    "sg:city":"Dunnville",
    "sg:classifiers":[
        {
            "category":"Shopping",
            "type":"Retail Goods"
        }
    ],
    "sg:phone":"+1 905 774 6222",
    "sg:postcode":"N1A 1J6",
    "sg:province":"ON",
    "sg:tags":[
        "equipment",
        "care",
        "health",
        "pharmacy",
        "home"
    ],
    "wof:name":"Dell Pharmacy",
    "wof:placetype":"venue"
},
  "geometry": {"coordinates":[-79.61832427980001,42.902797699],"type":"Point"}
}