{
  "type": "Feature",
  "properties": {
    "addr:full":"129 Kam Lake Rd Yellowknife NT X1A 2P7",
    "addr:housenumber":"129",
    "addr:postcode":"x1a 2p7",
    "addr:street":"Kam Lake Rd",
    "iso:country":"CA",
    "sg:address":"129 Kam Lake Rd",
    "sg:city":"Yellowknife",
    "sg:classifiers":[
        {
            "category":"Retail",
            "subcategory":"Veterinary Services",
            "type":"Services"
        }
    ],
    "sg:phone":"+1 867 873 4252",
    "sg:postcode":"X1A 2P7",
    "sg:province":"NT",
    "sg:tags":[
        "veterinarian"
    ],
    "wof:name":"Elkin, Kim DVM",
    "wof:placetype":"venue"
},
  "geometry": {"coordinates":[-114.42040252699999,62.4279289246],"type":"Point"}
}