{
  "type": "Feature",
  "properties": {
    "addr:full":"29 Ch D'En-Haut Natashquan QC G0G 2E0",
    "addr:housenumber":"29",
    "addr:postcode":"g0g 2e0",
    "addr:street":"Ch D'En-Haut",
    "iso:country":"CA",
    "sg:address":"29 Ch D'En-Haut",
    "sg:city":"Natashquan",
    "sg:classifiers":[
        {
            "category":"Communications",
            "subcategory":"Radio Station",
            "type":"Services"
        }
    ],
    "sg:phone":"+1 418 726 3284",
    "sg:postcode":"G0G 2E0",
    "sg:province":"QC",
    "sg:tags":[
        "company",
        "broadcasting"
    ],
    "wof:name":"Ckna",
    "wof:placetype":"venue"
},
  "geometry": {"coordinates":[-68.10275300000001,49.287754],"type":"Point"}
}