{
  "type": "Feature",
  "properties": {
    "iso:country":"CA",
    "sg:address":"62 Stanley St",
    "sg:city":"Ayr",
    "sg:classifiers":[
        {
            "category":"Health Services",
            "subcategory":"Doctor",
            "type":"Services"
        }
    ],
    "sg:phone":"+1 519 632 7915",
    "sg:postcode":"N0B 1E0",
    "sg:province":"ON",
    "sg:tags":[
        "dentist"
    ],
    "wof:name":"Salo, Karl DDS",
    "wof:placetype":"venue"
},
  "geometry": {"coordinates":[-80.45003509519999,43.2856674194],"type":"Point"}
}