{
  "type": "Feature",
  "properties": {
    "addr:full":"Etobicoke ON M9V 5G4",
    "addr:postcode":"m9v 5g4",
    "iso:country":"CA",
    "sg:city":"Etobicoke",
    "sg:classifiers":[
        {
            "category":"Health Services",
            "subcategory":"Doctor",
            "type":"Services"
        }
    ],
    "sg:phone":"+1 416 747 7122",
    "sg:postcode":"M9V 5G4",
    "sg:province":"ON",
    "sg:tags":[
        "physician",
        "surgeon"
    ],
    "wof:name":"Zakhary, Liliane MD",
    "wof:placetype":"venue"
},
  "geometry": {"coordinates":[-79.599327,43.731102],"type":"Point"}
}