{
  "type": "Feature",
  "properties": {
    "addr:full":"Hwy 108 Elliot Lake ON P5A 2R5",
    "addr:postcode":"p5a 2r5",
    "addr:street":"Hwy 108",
    "iso:country":"CA",
    "sg:address":"Hwy 108",
    "sg:city":"Elliot Lake",
    "sg:classifiers":[
        {
            "category":"Manufacturing",
            "subcategory":"Lumber",
            "type":"Manufacturing & Wholesale Goods"
        }
    ],
    "sg:phone":"+1 705 848 7266",
    "sg:postcode":"P5A 2R5",
    "sg:province":"ON",
    "sg:tags":[
        "company",
        "logging"
    ],
    "wof:name":"H & R Fabris Industries Ltd",
    "wof:placetype":"venue"
},
  "geometry": {"coordinates":[-82.64032,46.381485],"type":"Point"}
}