{
  "type": "Feature",
  "properties": {
    "iso:country":"CA",
    "sg:address":"374 Rue Saint-Jacques N",
    "sg:city":"Causapscal",
    "sg:classifiers":[
        {
            "category":"Autos & Motor Vehicles",
            "subcategory":"Fuel & Gas Station",
            "type":"Retail Goods"
        }
    ],
    "sg:phone":"+1 418 756 3790",
    "sg:postcode":"G0J 1J0",
    "sg:province":"QC",
    "sg:tags":[
        "oil"
    ],
    "wof:name":"Garage Valois & Fils",
    "wof:placetype":"venue"
},
  "geometry": {"coordinates":[-67.2337722778,48.3650245667],"type":"Point"}
}