{
  "type": "Feature",
  "properties": {
    "addr:full":"7901 Rue Saint-Dominique Montreal QC H2R 1X8",
    "addr:housenumber":"7901",
    "addr:postcode":"h2r 1x8",
    "addr:street":"Rue Saint-Dominique",
    "iso:country":"CA",
    "sg:address":"7901 Rue Saint-Dominique",
    "sg:city":"Montreal",
    "sg:classifiers":[
        {
            "category":"Restaurant",
            "type":"Food & Drink"
        }
    ],
    "sg:phone":"+1 514 382 2129",
    "sg:postcode":"H2R 1X8",
    "sg:province":"QC",
    "wof:name":"Restaurant Polleria Melchorita",
    "wof:placetype":"venue"
},
  "geometry": {"coordinates":[-73.6281585693,45.5389022827],"type":"Point"}
}