{
  "type": "Feature",
  "properties": {
    "iso:country":"CA",
    "sg:address":"735 Montreal Rd",
    "sg:city":"Cornwall",
    "sg:classifiers":[
        {
            "category":"Personal",
            "subcategory":"Beauty Salon",
            "type":"Services"
        }
    ],
    "sg:phone":"+1 613 933 2310",
    "sg:postcode":"K6H 1C5",
    "sg:province":"ON",
    "wof:name":"Peggy's Place",
    "wof:placetype":"venue"
},
  "geometry": {"coordinates":[-74.706245,45.018303],"type":"Point"}
}