{
  "type": "Feature",
  "properties": {
    "addr:full":"1072 102nd St North Battleford SK S9A 1E6",
    "addr:housenumber":"1072",
    "addr:postcode":"s9a 1e6",
    "addr:street":"102Nd St",
    "iso:country":"CA",
    "sg:address":"1072 102nd St",
    "sg:city":"North Battleford",
    "sg:classifiers":[
        {
            "category":"Taxi",
            "type":"Transportation"
        }
    ],
    "sg:phone":"+1 306 445 8155",
    "sg:postcode":"S9A 1E6",
    "sg:province":"SK",
    "sg:tags":[
        "taxicab"
    ],
    "wof:name":"Crown Cab",
    "wof:placetype":"venue"
},
  "geometry": {"coordinates":[-108.295860291,52.7729225159],"type":"Point"}
}