{
  "type": "Feature",
  "properties": {
    "addr:full":"North York ON M2J 5C2",
    "addr:postcode":"m2j 5c2",
    "iso:country":"CA",
    "sg:city":"North York",
    "sg:classifiers":[
        {
            "category":"Airline",
            "type":"Transportation"
        }
    ],
    "sg:phone":"+1 416 492 9282",
    "sg:postcode":"M2J 5C2",
    "sg:province":"ON",
    "sg:tags":[
        "company"
    ],
    "wof:name":"Saudi Arabian Airlines",
    "wof:placetype":"venue"
},
  "geometry": {"coordinates":[-79.32971999999999,43.774776],"type":"Point"}
}