{
  "type": "Feature",
  "properties": {
    "addr:full":"332 Spadina Ave Toronto ON M5T 2G2",
    "addr:housenumber":"332",
    "addr:postcode":"m5t 2g2",
    "addr:street":"Spadina Ave",
    "iso:country":"CA",
    "sg:address":"332 Spadina Ave",
    "sg:city":"Toronto",
    "sg:classifiers":[
        {
            "category":"Restaurant",
            "type":"Food & Drink"
        }
    ],
    "sg:phone":"+1 416 971 9719",
    "sg:postcode":"M5T 2G2",
    "sg:province":"ON",
    "wof:name":"Kim Hoa",
    "wof:placetype":"venue"
},
  "geometry": {"coordinates":[-79.398712,43.653934],"type":"Point"}
}