{
  "type": "Feature",
  "properties": {
    "addr:full":"675 Progress Ave Scarborough ON M1H 2W9",
    "addr:housenumber":"675",
    "addr:postcode":"m1h 2w9",
    "addr:street":"Progress Ave",
    "iso:country":"CA",
    "sg:address":"675 Progress Ave",
    "sg:city":"Scarborough",
    "sg:classifiers":[
        {
            "category":"Manufacturing",
            "subcategory":"Metals",
            "type":"Manufacturing & Wholesale Goods"
        }
    ],
    "sg:phone":"+1 416 438 6650",
    "sg:postcode":"M1H 2W9",
    "sg:province":"ON",
    "sg:tags":[
        "stamping"
    ],
    "wof:name":"A G Simpson CO Ltd",
    "wof:placetype":"venue"
},
  "geometry": {"coordinates":[-79.24733000000001,43.777576],"type":"Point"}
}