{
  "type": "Feature",
  "properties": {
    "addr:full":"210 Mobrae Ave # 2 Salt Spring Island BC V8K 1J8",
    "addr:housenumber":"210",
    "addr:postcode":"v8k 1j8",
    "addr:street":"Mobrae Ave # 2",
    "iso:country":"CA",
    "sg:address":"210 Mobrae Ave # 2",
    "sg:city":"Salt Spring Island",
    "sg:classifiers":[
        {
            "category":"Real Estate",
            "subcategory":"Real Estate Agent",
            "type":"Services"
        }
    ],
    "sg:phone":"+1 250 537 5568",
    "sg:postcode":"V8K 1J8",
    "sg:province":"BC",
    "wof:name":"Arvid Chalmers Ltd",
    "wof:placetype":"venue"
},
  "geometry": {"coordinates":[-123.54331970200001,48.8742141724],"type":"Point"}
}