{
  "type": "Feature",
  "properties": {
    "addr:full":"1545 Av DE LA Mauricie Laval QC H7E 4H9",
    "addr:housenumber":"1545",
    "addr:postcode":"h7e 4h9",
    "addr:street":"Av De La Mauricie",
    "iso:country":"CA",
    "sg:address":"1545 Av DE LA Mauricie",
    "sg:city":"Laval",
    "sg:classifiers":[
        {
            "category":"Real Estate",
            "subcategory":"Real Estate Agent",
            "type":"Services"
        }
    ],
    "sg:phone":"+1 450 629 3043",
    "sg:postcode":"H7E 4H9",
    "sg:province":"QC",
    "wof:name":"Immeubles Vision 2000 Inc",
    "wof:placetype":"venue"
},
  "geometry": {"coordinates":[-73.68078613279999,45.591884613],"type":"Point"}
}