{
  "type": "Feature",
  "properties": {
    "iso:country":"CA",
    "sg:address":"640 Manawagonish Rd",
    "sg:city":"Saint John",
    "sg:classifiers":[
        {
            "category":"Shopping",
            "subcategory":"Pharmacy",
            "type":"Retail Goods"
        }
    ],
    "sg:phone":"+1 506 635 1126",
    "sg:postcode":"E2M 3W5",
    "sg:province":"NB",
    "wof:name":"Lawton's Drugs",
    "wof:placetype":"venue"
},
  "geometry": {"coordinates":[-66.100761,45.256718],"type":"Point"}
}