{
  "type": "Feature",
  "properties": {
    "iso:country":"CA",
    "sg:address":"557 Chartwell Rd",
    "sg:city":"Oakville",
    "sg:classifiers":[
        {
            "category":"Manufacturing",
            "subcategory":"Tools & Machinery",
            "type":"Manufacturing & Wholesale Goods"
        }
    ],
    "sg:phone":"+1 905 822 0956",
    "sg:postcode":"L6J 4A8",
    "sg:province":"ON",
    "sg:tags":[
        "conditioning",
        "air",
        "system",
        "contractor"
    ],
    "wof:name":"Messenger Mechanical",
    "wof:placetype":"venue"
},
  "geometry": {"coordinates":[-79.674522,43.465607],"type":"Point"}
}