{
  "type": "Feature",
  "properties": {
    "iso:country":"CA",
    "sg:address":"18 Lord Crt",
    "sg:city":"Hamilton",
    "sg:classifiers":[
        {
            "category":"Education",
            "subcategory":"Special Training",
            "type":"Public Place"
        }
    ],
    "sg:phone":"+1 905 561 1877",
    "sg:postcode":"L8E 4V8",
    "sg:province":"ON",
    "sg:tags":[
        "tutoring"
    ],
    "wof:name":"Abc Tutoring",
    "wof:placetype":"venue"
},
  "geometry": {"coordinates":[-79.7683334351,43.2314987183],"type":"Point"}
}