{
  "type": "Feature",
  "properties": {
    "addr:full":"2446 Main St Westbank BC V4T 1Z1",
    "addr:housenumber":"2446",
    "addr:postcode":"v4t 1z1",
    "addr:street":"Main St",
    "iso:country":"CA",
    "sg:address":"2446 Main St",
    "sg:city":"Westbank",
    "sg:classifiers":[
        {
            "category":"Health Services",
            "subcategory":"Doctor",
            "type":"Services"
        }
    ],
    "sg:phone":"+1 250 768 3984",
    "sg:postcode":"V4T 1Z1",
    "sg:province":"BC",
    "sg:tags":[
        "dentist"
    ],
    "wof:name":"Westbank Dental Ctr",
    "wof:placetype":"venue"
},
  "geometry": {"coordinates":[-119.627937317,49.8297080994],"type":"Point"}
}