{
  "type": "Feature",
  "properties": {
    "iso:country":"CA",
    "sg:address":"1745 Rue Decarie",
    "sg:city":"Saint-Laurent",
    "sg:classifiers":[
        {
            "category":"Social Services",
            "type":"Services"
        }
    ],
    "sg:phone":"+1 514 747 3375",
    "sg:postcode":"H4L 3N5",
    "sg:province":"QC",
    "sg:tags":[
        "organization",
        "welfare"
    ],
    "wof:name":"Programme Pair",
    "wof:placetype":"venue"
},
  "geometry": {"coordinates":[-73.692047,45.520412],"type":"Point"}
}