{
  "type": "Feature",
  "properties": {
    "addr:full":"4920 50 St Alix AB T0C 0B0",
    "addr:housenumber":"4920",
    "addr:postcode":"t0c 0b0",
    "addr:street":"50 St",
    "iso:country":"CA",
    "sg:address":"4920 50 St",
    "sg:city":"Alix",
    "sg:classifiers":[
        {
            "category":"Restaurant",
            "type":"Food & Drink"
        }
    ],
    "sg:phone":"+1 403 747 2165",
    "sg:postcode":"T0C 0B0",
    "sg:province":"AB",
    "wof:name":"Jeanne's Pizza Pantry",
    "wof:placetype":"venue"
},
  "geometry": {"coordinates":[-113.192719,52.399265],"type":"Point"}
}