{
  "type": "Feature",
  "properties": {
    "addr:full":"154 Hendrie Ave Burlington ON L7T 4C2",
    "addr:housenumber":"154",
    "addr:postcode":"l7t 4c2",
    "addr:street":"Hendrie Ave",
    "iso:country":"CA",
    "sg:address":"154 Hendrie Ave",
    "sg:city":"Burlington",
    "sg:classifiers":[
        {
            "category":"Freight",
            "type":"Transportation"
        }
    ],
    "sg:phone":"+1 905 631 7400",
    "sg:postcode":"L7T 4C2",
    "sg:province":"ON",
    "sg:tags":[
        "consultant"
    ],
    "wof:name":"H B Skidmore & Assoc",
    "wof:placetype":"venue"
},
  "geometry": {"coordinates":[-79.85438499999999,43.301296],"type":"Point"}
}