{
  "type": "Feature",
  "properties": {
    "addr:full":"46 Rue Sainte-Marie Saint-Constant QC J5A 1C2",
    "addr:housenumber":"46",
    "addr:postcode":"j5a 1c2",
    "addr:street":"Rue Sainte-Marie",
    "iso:country":"CA",
    "sg:address":"46 Rue Sainte-Marie",
    "sg:city":"Saint-Constant",
    "sg:classifiers":[
        {
            "category":"Building & Trades",
            "subcategory":"Construction",
            "type":"Services"
        }
    ],
    "sg:phone":"+1 450 632 3495",
    "sg:postcode":"J5A 1C2",
    "sg:province":"QC",
    "sg:tags":[
        "roofing",
        "contractor"
    ],
    "wof:name":"Toitures N Legault Inc",
    "wof:placetype":"venue"
},
  "geometry": {"coordinates":[-73.56193500000001,45.382633],"type":"Point"}
}