{
  "type": "Feature",
  "properties": {
    "addr:full":"15775 Main St Cheticamp NS B0E 1H0",
    "addr:housenumber":"15775",
    "addr:postcode":"b0e 1h0",
    "addr:street":"Main St",
    "iso:country":"CA",
    "sg:address":"15775 Main St",
    "sg:city":"Cheticamp",
    "sg:classifiers":[
        {
            "category":"Travel",
            "subcategory":"Hotels & Motels",
            "type":"Entertainment"
        }
    ],
    "sg:phone":"+1 902 224 1040",
    "sg:postcode":"B0E 1H0",
    "sg:province":"NS",
    "sg:tags":[
        "cottage",
        "bed",
        "breakfast",
        "accommodation",
        "cabin"
    ],
    "wof:name":"Pilot Whale Chalet",
    "wof:placetype":"venue"
},
  "geometry": {"coordinates":[-61.009186,46.634281],"type":"Point"}
}