{
  "type": "Feature",
  "properties": {
    "addr:full":"New Westminster BC V3L 5H1",
    "addr:postcode":"v3l 5h1",
    "iso:country":"CA",
    "sg:city":"New Westminster",
    "sg:classifiers":[
        {
            "category":"Professional",
            "subcategory":"Lawyer & Legal Services",
            "type":"Services"
        }
    ],
    "sg:phone":"+1 604 522 2785",
    "sg:postcode":"V3L 5H1",
    "sg:province":"BC",
    "sg:tags":[
        "attorney"
    ],
    "wof:name":"Coulter, Lawrence W",
    "wof:placetype":"venue"
},
  "geometry": {"coordinates":[-122.91954040500001,49.2126960754],"type":"Point"}
}