{
  "type": "Feature",
  "properties": {
    "addr:full":"Montreal QC H2N 2J4",
    "addr:postcode":"h2n 2j4",
    "iso:country":"CA",
    "sg:city":"Montreal",
    "sg:classifiers":[
        {
            "category":"Shopping",
            "subcategory":"Clothing, Apparel, & Fashions",
            "type":"Retail Goods"
        }
    ],
    "sg:phone":"+1 514 383 1011",
    "sg:postcode":"H2N 2J4",
    "sg:province":"QC",
    "sg:tags":[
        "girl"
    ],
    "wof:name":"Body Guard Intl",
    "wof:placetype":"venue"
},
  "geometry": {"coordinates":[-73.6488647461,45.5484313965],"type":"Point"}
}