{
  "type": "Feature",
  "properties": {
    "addr:full":"460 Saint Marys St Fredericton NB E3A 8H5",
    "addr:housenumber":"460",
    "addr:postcode":"e3a 8h5",
    "addr:street":"Saint Marys St",
    "iso:country":"CA",
    "sg:address":"460 Saint Marys St",
    "sg:city":"Fredericton",
    "sg:classifiers":[
        {
            "category":"Wholesale",
            "subcategory":"Construction Materials",
            "type":"Manufacturing & Wholesale Goods"
        }
    ],
    "sg:phone":"+1 506 472 2023",
    "sg:postcode":"E3A 8H5",
    "sg:province":"NB",
    "sg:tags":[
        "concrete",
        "product"
    ],
    "wof:name":"Leeuw Concrete",
    "wof:placetype":"venue"
},
  "geometry": {"coordinates":[-66.6391220093,45.9606399536],"type":"Point"}
}