{
  "type": "Feature",
  "properties": {
    "iso:country":"CA",
    "sg:address":"1002 Rue Sherbrooke O",
    "sg:city":"Montreal",
    "sg:classifiers":[
        {
            "category":"Government",
            "subcategory":"Office",
            "type":"Public Place"
        }
    ],
    "sg:phone":"+1 514 849 4247",
    "sg:postcode":"H3A 3L6",
    "sg:province":"QC",
    "sg:tags":[
        "federal",
        "affairs"
    ],
    "wof:name":"Consulat General Des Pays-Bas",
    "wof:placetype":"venue"
},
  "geometry": {"coordinates":[-73.56560500000001,45.520851],"type":"Point"}
}