{
  "type": "Feature",
  "properties": {
    "addr:full":"5111 57th Ave Provost AB T0B 3S0",
    "addr:housenumber":"5111",
    "addr:postcode":"t0b 3s0",
    "addr:street":"57Th Ave",
    "iso:country":"CA",
    "sg:address":"5111 57th Ave",
    "sg:city":"Provost",
    "sg:classifiers":[
        {
            "category":"Freight",
            "type":"Transportation"
        }
    ],
    "sg:phone":"+1 780 753 2408",
    "sg:postcode":"T0B 3S0",
    "sg:province":"AB",
    "sg:tags":[
        "courier"
    ],
    "wof:name":"Greyhound Lines of Canada Ltd",
    "wof:placetype":"venue"
},
  "geometry": {"coordinates":[-110.267906189,52.360786438],"type":"Point"}
}