{
  "type": "Feature",
  "properties": {
    "addr:full":"653 Ch Des Patriotes N Mont-Saint-Hilaire QC J3H 3H7",
    "addr:housenumber":"653",
    "addr:postcode":"j3h 3h7",
    "addr:street":"Ch Des Patriotes N Mont-Saint-Hilaire",
    "iso:country":"CA",
    "sg:address":"653 Ch Des Patriotes N",
    "sg:city":"Mont-Saint-Hilaire",
    "sg:classifiers":[
        {
            "category":"Real Estate",
            "subcategory":"Architect",
            "type":"Services"
        }
    ],
    "sg:phone":"+1 450 464 3687",
    "sg:postcode":"J3H 3H7",
    "sg:province":"QC",
    "wof:name":"Messier, Antoine",
    "wof:placetype":"venue"
},
  "geometry": {"coordinates":[-73.190269,45.581017],"type":"Point"}
}