{
  "type": "Feature",
  "properties": {
    "addr:full":"1133 Rue Fleury E Montreal QC H2C 1P9",
    "addr:housenumber":"1133",
    "addr:postcode":"h2c 1p9",
    "addr:street":"Rue Fleury E",
    "iso:country":"CA",
    "sg:address":"1133 Rue Fleury E",
    "sg:city":"Montreal",
    "sg:classifiers":[
        {
            "category":"Food & Beverages",
            "subcategory":"Specialty",
            "type":"Retail Goods"
        }
    ],
    "sg:phone":"+1 514 384 1555",
    "sg:postcode":"H2C 1P9",
    "sg:province":"QC",
    "sg:tags":[
        "gourmet",
        "shop"
    ],
    "wof:name":"L'Aromate",
    "wof:placetype":"venue"
},
  "geometry": {"coordinates":[-73.6589813232,45.5586929321],"type":"Point"}
}