{
  "type": "Feature",
  "properties": {
    "addr:full":"Anjou QC H1J 2C8",
    "addr:postcode":"h1j 2c8",
    "iso:country":"CA",
    "sg:city":"Anjou",
    "sg:classifiers":[
        {
            "category":"Professional",
            "subcategory":"Accounting & Tax Preparation",
            "type":"Services"
        }
    ],
    "sg:phone":"+1 514 354 2311",
    "sg:postcode":"H1J 2C8",
    "sg:province":"QC",
    "sg:tags":[
        "accountant"
    ],
    "wof:name":"Guertin, Real CA",
    "wof:placetype":"venue"
},
  "geometry": {"coordinates":[-73.5716094971,45.6114807129],"type":"Point"}
}