{
  "type": "Feature",
  "properties": {
    "addr:full":"6098 Rue Paulin Laval QC H7H 3E1",
    "addr:housenumber":"6098",
    "addr:postcode":"h7h 3e1",
    "addr:street":"Rue Paulin",
    "iso:country":"CA",
    "sg:address":"6098 Rue Paulin",
    "sg:city":"Laval",
    "sg:classifiers":[
        {
            "category":"Real Estate",
            "subcategory":"Surveying",
            "type":"Services"
        }
    ],
    "sg:phone":"+1 450 628 8326",
    "sg:postcode":"H7H 3E1",
    "sg:province":"QC",
    "sg:tags":[
        "surveyor"
    ],
    "wof:name":"Services Genicad Inc",
    "wof:placetype":"venue"
},
  "geometry": {"coordinates":[-73.7466201782,45.6369895935],"type":"Point"}
}