{
  "type": "Feature",
  "properties": {
    "addr:full":"Scarborough ON M1H 2X1",
    "addr:postcode":"m1h 2x1",
    "iso:country":"CA",
    "sg:city":"Scarborough",
    "sg:classifiers":[
        {
            "category":"Wholesale",
            "subcategory":"Office Equipment",
            "type":"Manufacturing & Wholesale Goods"
        }
    ],
    "sg:phone":"+1 416 438 6470",
    "sg:postcode":"M1H 2X1",
    "sg:province":"ON",
    "sg:tags":[
        "machine",
        "duplicating",
        "copying"
    ],
    "wof:name":"Allcopy Equipment Ltd",
    "wof:placetype":"venue"
},
  "geometry": {"coordinates":[-79.246628,43.778156],"type":"Point"}
}