{
  "type": "Feature",
  "properties": {
    "addr:full":"760 Great Northern Rd Sault Ste Marie ON P6A 5K7",
    "addr:housenumber":"760",
    "addr:postcode":"p6a 5k7",
    "addr:street":"Great Northern Rd",
    "iso:country":"CA",
    "sg:address":"760 Great Northern Rd",
    "sg:city":"Sault Ste Marie",
    "sg:classifiers":[
        {
            "category":"Health Services",
            "subcategory":"Nursing And Care Facility",
            "type":"Services"
        }
    ],
    "sg:phone":"+1 705 945 9405",
    "sg:postcode":"P6A 5K7",
    "sg:province":"ON",
    "sg:tags":[
        "home",
        "retirement",
        "community"
    ],
    "wof:name":"Great Northern Retirement Home",
    "wof:placetype":"venue"
},
  "geometry": {"coordinates":[-84.31925964360001,46.5496406555],"type":"Point"}
}