{
  "type": "Feature",
  "properties": {
    "addr:full":"Main St Buchans NL A0H 1G0",
    "addr:postcode":"a0h 1g0",
    "addr:street":"Main St",
    "iso:country":"CA",
    "sg:address":"Main St",
    "sg:city":"Buchans",
    "sg:classifiers":[
        {
            "category":"Personal",
            "subcategory":"Beauty Salon",
            "type":"Services"
        }
    ],
    "sg:phone":"+1 709 672 3319",
    "sg:postcode":"A0H 1G0",
    "sg:province":"NL",
    "wof:name":"Gail's Beauty Salon",
    "wof:placetype":"venue"
},
  "geometry": {"coordinates":[-56.8551979065,48.825553894],"type":"Point"}
}