{
  "type": "Feature",
  "properties": {
    "addr:full":"Vancouver BC V5X 4N6",
    "addr:postcode":"v5x 4n6",
    "iso:country":"CA",
    "sg:city":"Vancouver",
    "sg:classifiers":[
        {
            "category":"Wholesale",
            "subcategory":"Machinery & Supplies",
            "type":"Manufacturing & Wholesale Goods"
        }
    ],
    "sg:phone":"+1 604 687 1301",
    "sg:postcode":"V5X 4N6",
    "sg:province":"BC",
    "sg:tags":[
        "janitor"
    ],
    "wof:name":"Pro-Bel Enterprises",
    "wof:placetype":"venue"
},
  "geometry": {"coordinates":[-123.11403656,49.2604408264],"type":"Point"}
}