{
  "type": "Feature",
  "properties": {
    "addr:full":"5541 Ch Upper Lachine Montreal QC H4A 2A5",
    "addr:postcode":"5541;h4a 2a5",
    "addr:street":"Ch Upper",
    "iso:country":"CA",
    "sg:address":"5541 Ch Upper Lachine",
    "sg:city":"Montreal",
    "sg:classifiers":[
        {
            "category":"Building & Trades",
            "subcategory":"Electrical",
            "type":"Services"
        }
    ],
    "sg:phone":"+1 514 481 0251",
    "sg:postcode":"H4A 2A5",
    "sg:province":"QC",
    "sg:tags":[
        "electric",
        "contractor"
    ],
    "wof:name":"Electrique Transbec Ltee",
    "wof:placetype":"venue"
},
  "geometry": {"coordinates":[-73.60817,45.470219],"type":"Point"}
}