{
  "type": "Feature",
  "properties": {
    "addr:full":"Shoe Cove LA Scie NL A0K 3M0",
    "addr:postcode":"a0k 3m0",
    "addr:street":"Shoe Cove La",
    "iso:country":"CA",
    "sg:address":"Shoe Cove",
    "sg:city":"LA Scie",
    "sg:classifiers":[
        {
            "category":"Organizations",
            "subcategory":"Religious Organization",
            "type":"Services"
        }
    ],
    "sg:phone":"+1 709 675 2166",
    "sg:postcode":"A0K 3M0",
    "sg:province":"NL",
    "sg:tags":[
        "church"
    ],
    "wof:name":"First United Church",
    "wof:placetype":"venue"
},
  "geometry": {"coordinates":[-55.59483,49.954182],"type":"Point"}
}