{
  "type": "Feature",
  "properties": {
    "addr:full":"Surrey BC V3W 0T7",
    "addr:postcode":"v3w 0t7",
    "iso:country":"CA",
    "sg:city":"Surrey",
    "sg:classifiers":[
        {
            "category":"Building & Trades",
            "subcategory":"Construction",
            "type":"Services"
        }
    ],
    "sg:phone":"+1 604 502 8042",
    "sg:postcode":"V3W 0T7",
    "sg:province":"BC",
    "sg:tags":[
        "maker",
        "cabinet"
    ],
    "wof:name":"P M Woodcraft Ltd",
    "wof:placetype":"venue"
},
  "geometry": {"coordinates":[-122.830215,49.105179],"type":"Point"}
}