{
  "type": "Feature",
  "properties": {
    "addr:full":"677 Rue Des Merles Longueuil QC J4G 2L1",
    "addr:housenumber":"677",
    "addr:postcode":"j4g 2l1",
    "addr:street":"Rue Des Merles",
    "iso:country":"CA",
    "sg:address":"677 Rue Des Merles",
    "sg:city":"Longueuil",
    "sg:classifiers":[
        {
            "category":"Professional",
            "subcategory":"Business Services",
            "type":"Services"
        }
    ],
    "sg:phone":"+1 450 679 9797",
    "sg:postcode":"J4G 2L1",
    "sg:province":"QC",
    "sg:tags":[
        "translator",
        "interpreter"
    ],
    "wof:name":"Communications Jpf Inc",
    "wof:placetype":"venue"
},
  "geometry": {"coordinates":[-73.4941329956,45.5418815613],"type":"Point"}
}