{
  "type": "Feature",
  "properties": {
    "addr:full":"11650 145 St NW Edmonton AB T5M 1V8",
    "addr:housenumber":"11650",
    "addr:postcode":"t5m 1v8",
    "addr:street":"145 St Nw",
    "iso:country":"CA",
    "sg:address":"11650 145 St NW",
    "sg:city":"Edmonton",
    "sg:classifiers":[
        {
            "category":"Building & Trades",
            "subcategory":"Construction",
            "type":"Services"
        }
    ],
    "sg:phone":"+1 780 455 0455",
    "sg:postcode":"T5M 1V8",
    "sg:province":"AB",
    "sg:tags":[
        "dry wall",
        "contractor"
    ],
    "wof:name":"Twin Eagle Management Ltd",
    "wof:placetype":"venue"
},
  "geometry": {"coordinates":[-113.57081599999999,53.568367],"type":"Point"}
}