{
  "type": "Feature",
  "properties": {
    "addr:full":"Victoria BC V8R 1J5",
    "addr:postcode":"v8r 1j5",
    "iso:country":"CA",
    "sg:city":"Victoria",
    "sg:classifiers":[
        {
            "category":"Health Services",
            "subcategory":"Medical Lab",
            "type":"Services"
        }
    ],
    "sg:phone":"+1 250 595 1314",
    "sg:postcode":"V8R 1J5",
    "sg:province":"BC",
    "sg:tags":[
        "laboratory"
    ],
    "wof:name":"Creative Dental Ltd",
    "wof:placetype":"venue"
},
  "geometry": {"coordinates":[-123.330704,48.429413],"type":"Point"}
}