{
  "type": "Feature",
  "properties": {
    "iso:country":"CA",
    "sg:city":"Etobicoke",
    "sg:classifiers":[
        {
            "category":"Shopping",
            "type":"Retail Goods"
        }
    ],
    "sg:phone":"+1 416 741 2934",
    "sg:postcode":"M9V 5E2",
    "sg:province":"ON",
    "sg:tags":[
        "awning",
        "canopy"
    ],
    "wof:name":"Century Awning CO",
    "wof:placetype":"venue"
},
  "geometry": {"coordinates":[-79.601532,43.735371],"type":"Point"}
}