{
  "type": "Feature",
  "properties": {
    "addr:full":"11360 256 St Maple Ridge BC V2W 1H1",
    "addr:housenumber":"11360",
    "addr:postcode":"v2w 1h1",
    "addr:street":"256 St",
    "iso:country":"CA",
    "sg:address":"11360 256 St",
    "sg:city":"Maple Ridge",
    "sg:classifiers":[
        {
            "category":"Building & Trades",
            "subcategory":"Landscaping Services",
            "type":"Services"
        }
    ],
    "sg:phone":"+1 604 462 9144",
    "sg:postcode":"V2W 1H1",
    "sg:province":"BC",
    "sg:tags":[
        "landscape",
        "contractor"
    ],
    "wof:name":"Blasig Landscape & Constr Ltd",
    "wof:placetype":"venue"
},
  "geometry": {"coordinates":[-122.508476257,49.2085609436],"type":"Point"}
}