{
  "type": "Feature",
  "properties": {
    "addr:full":"Winnipeg MB R3C 1T2",
    "addr:postcode":"r3c 1t2",
    "iso:country":"CA",
    "sg:city":"Winnipeg",
    "sg:classifiers":[
        {
            "category":"Personal",
            "subcategory":"Beauty Salon",
            "type":"Services"
        }
    ],
    "sg:phone":"+1 204 943 2145",
    "sg:postcode":"R3C 1T2",
    "sg:province":"MB",
    "sg:tags":[
        "school"
    ],
    "wof:name":"Scientific Marvel School",
    "wof:placetype":"venue"
},
  "geometry": {"coordinates":[-97.147896,49.891361],"type":"Point"}
}