{
  "type": "Feature",
  "properties": {
    "addr:full":"236 Commercial St North Sydney NS B2A 1B7",
    "addr:housenumber":"236",
    "addr:postcode":"b2a 1b7",
    "addr:street":"Commercial St",
    "iso:country":"CA",
    "sg:address":"236 Commercial St",
    "sg:city":"North Sydney",
    "sg:classifiers":[
        {
            "category":"Restaurant",
            "type":"Food & Drink"
        }
    ],
    "sg:phone":"+1 902 794 8308",
    "sg:postcode":"B2A 1B7",
    "sg:province":"NS",
    "wof:name":"Main Street Restaurant",
    "wof:placetype":"venue"
},
  "geometry": {"coordinates":[-60.2499427795,46.2082138062],"type":"Point"}
}