{
  "type": "Feature",
  "properties": {
    "addr:full":"705 Carrier St Kamloops BC V2H 1G1",
    "addr:housenumber":"705",
    "addr:postcode":"bc v2h 1g1",
    "addr:street":"Carrier St",
    "iso:country":"CA",
    "sg:address":"705 Carrier St",
    "sg:city":"Kamloops",
    "sg:classifiers":[
        {
            "category":"Retail",
            "subcategory":"Auto Repair",
            "type":"Services"
        }
    ],
    "sg:phone":"+1 250 372 5975",
    "sg:postcode":"V2H 1G1",
    "sg:province":"BC",
    "sg:tags":[
        "body",
        "automobile",
        "painting"
    ],
    "wof:name":"Blaine's Auto Body",
    "wof:placetype":"venue"
},
  "geometry": {"coordinates":[-120.32185363799999,50.6859207153],"type":"Point"}
}