{
  "type": "Feature",
  "properties": {
    "addr:full":"2411 23 St NW Calgary AB T2M 3Y3",
    "addr:housenumber":"2411",
    "addr:postcode":"t2m 3y3",
    "addr:street":"23 St Nw",
    "iso:country":"CA",
    "sg:address":"2411 23 St NW",
    "sg:city":"Calgary",
    "sg:classifiers":[
        {
            "category":"Professional",
            "subcategory":"Lawyer & Legal Services",
            "type":"Services"
        }
    ],
    "sg:phone":"+1 403 289 1991",
    "sg:postcode":"T2M 3Y3",
    "sg:province":"AB",
    "sg:tags":[
        "attorney"
    ],
    "wof:name":"Boothman, V L",
    "wof:placetype":"venue"
},
  "geometry": {"coordinates":[-114.114952,51.072243],"type":"Point"}
}