{
  "type": "Feature",
  "properties": {
    "addr:full":"1703 Victoria Park Ave Scarborough ON M1R 1R9",
    "addr:housenumber":"1703",
    "addr:postcode":"m1r 1r9",
    "addr:street":"Victoria Park Ave",
    "iso:country":"CA",
    "sg:address":"1703 Victoria Park Ave",
    "sg:city":"Scarborough",
    "sg:classifiers":[
        {
            "category":"Health Services",
            "subcategory":"Medical Lab",
            "type":"Services"
        }
    ],
    "sg:phone":"+1 416 759 3462",
    "sg:postcode":"M1R 1R9",
    "sg:province":"ON",
    "sg:tags":[
        "clinic"
    ],
    "wof:name":"Victoria Park Mammography Ctr",
    "wof:placetype":"venue"
},
  "geometry": {"coordinates":[-79.30688499999999,43.735489],"type":"Point"}
}