{
  "type": "Feature",
  "properties": {
    "iso:country":"CA",
    "sg:city":"Candiac",
    "sg:classifiers":[
        {
            "category":"Manufacturing",
            "subcategory":"Electronics",
            "type":"Manufacturing & Wholesale Goods"
        }
    ],
    "sg:phone":"+1 450 632 3030",
    "sg:postcode":"J5R 3X8",
    "sg:province":"QC",
    "sg:tags":[
        "equipment",
        "electronic",
        "supply"
    ],
    "wof:name":"Elrex Manufactures Inc",
    "wof:placetype":"venue"
},
  "geometry": {"coordinates":[-73.535103,45.377857],"type":"Point"}
}