{
  "type": "Feature",
  "properties": {
    "addr:full":"395 Heritage Dr SE Calgary AB T2H 1M8",
    "addr:housenumber":"395",
    "addr:postcode":"t2h 1m8",
    "addr:street":"Heritage Dr Se",
    "iso:country":"CA",
    "sg:address":"395 Heritage Dr SE",
    "sg:city":"Calgary",
    "sg:classifiers":[
        {
            "category":"Restaurant",
            "type":"Food & Drink"
        }
    ],
    "sg:phone":"+1 403 640 9844",
    "sg:postcode":"T2H 1M8",
    "sg:province":"AB",
    "wof:name":"Taco Time",
    "wof:placetype":"venue"
},
  "geometry": {"coordinates":[-114.060371,50.979443],"type":"Point"}
}