{
  "type": "Feature",
  "properties": {
    "addr:full":"8995 Boul Saint-Michel Montreal QC H1Z 3G3",
    "addr:housenumber":"8995",
    "addr:postcode":"h1z 3g3",
    "addr:street":"Boul Saint-Michel",
    "iso:country":"CA",
    "sg:address":"8995 Boul Saint-Michel",
    "sg:city":"Montreal",
    "sg:classifiers":[
        {
            "category":"Banks & Credit Unions",
            "subcategory":"Bank",
            "type":"Services"
        }
    ],
    "sg:phone":"+1 514 394 5555",
    "sg:postcode":"H1Z 3G3",
    "sg:province":"QC",
    "wof:name":"Banque National Du Canada",
    "wof:placetype":"venue"
},
  "geometry": {"coordinates":[-73.62641143800001,45.5714530945],"type":"Point"}
}