{
  "type": "Feature",
  "properties": {
    "addr:full":"1430 Coteau Des Hetres N Saint-Andre-D'Argenteuil QC J0V 1X0",
    "addr:housenumber":"1430",
    "addr:postcode":"j0v 1x0",
    "addr:street":"Coteau Des Hetres N",
    "iso:country":"CA",
    "sg:address":"1430 Coteau Des Hetres N",
    "sg:city":"Saint-Andre-D'Argenteuil",
    "sg:classifiers":[
        {
            "category":"Building & Trades",
            "subcategory":"Construction",
            "type":"Services"
        }
    ],
    "sg:phone":"+1 450 562 7111",
    "sg:postcode":"J0V 1X0",
    "sg:province":"QC",
    "sg:tags":[
        "excavating",
        "contractor"
    ],
    "wof:name":"Thomas Spiroux Excavation Inc",
    "wof:placetype":"venue"
},
  "geometry": {"coordinates":[-74.317894,45.626919],"type":"Point"}
}