{
  "type": "Feature",
  "properties": {
    "iso:country":"CA",
    "sg:city":"Quebec",
    "sg:classifiers":[
        {
            "category":"Travel",
            "subcategory":"Campground",
            "type":"Entertainment"
        }
    ],
    "sg:phone":"+1 418 877 5191",
    "sg:postcode":"G2E 2H2",
    "sg:province":"QC",
    "sg:tags":[
        "camp",
        "fishing"
    ],
    "wof:name":"Federation Des Pourvoyeurs Du",
    "wof:placetype":"venue"
},
  "geometry": {"coordinates":[-71.334663,46.80151],"type":"Point"}
}