{
  "type": "Feature",
  "properties": {
    "addr:full":"5321 11 St NE Calgary AB T2E 8N4",
    "addr:housenumber":"5321",
    "addr:postcode":"t2e 8n4",
    "addr:street":"11 St Ne",
    "iso:country":"CA",
    "sg:address":"5321 11 St NE",
    "sg:city":"Calgary",
    "sg:classifiers":[
        {
            "category":"Shopping",
            "subcategory":"Computers & Home Electronics",
            "type":"Retail Goods"
        }
    ],
    "sg:phone":"+1 403 274 9100",
    "sg:postcode":"T2E 8N4",
    "sg:province":"AB",
    "sg:tags":[
        "processing",
        "datum",
        "software"
    ],
    "wof:name":"Seitel Solutions Canada Ltd",
    "wof:placetype":"venue"
},
  "geometry": {"coordinates":[-114.036674,51.098022],"type":"Point"}
}