{
  "type": "Feature",
  "properties": {
    "addr:full":"Surrey BC V3W 3E9",
    "addr:postcode":"v3w 3e9",
    "iso:country":"CA",
    "sg:city":"Surrey",
    "sg:classifiers":[
        {
            "category":"Shopping",
            "subcategory":"Hobbies, Toys, & Games",
            "type":"Retail Goods"
        }
    ],
    "sg:phone":"+1 604 599 1998",
    "sg:postcode":"V3W 3E9",
    "sg:province":"BC",
    "sg:tags":[
        "equipment",
        "ceramic",
        "supply"
    ],
    "wof:name":"Calderella Ceramics Mfr Gftwr",
    "wof:placetype":"venue"
},
  "geometry": {"coordinates":[-122.87664032000001,49.1519393921],"type":"Point"}
}