{
  "type": "Feature",
  "properties": {
    "addr:full":"319 South Railway St W Minto MB R0K 1M0",
    "addr:housenumber":"319",
    "addr:postcode":"r0k 1m0",
    "addr:street":"South Railway St W",
    "iso:country":"CA",
    "sg:address":"319 South Railway St W",
    "sg:city":"Minto",
    "sg:classifiers":[
        {
            "category":"Organizations",
            "subcategory":"Religious Organization",
            "type":"Services"
        }
    ],
    "sg:phone":"+1 204 776 2106",
    "sg:postcode":"R0K 1M0",
    "sg:province":"MB",
    "sg:tags":[
        "church"
    ],
    "wof:name":"Minto United Church",
    "wof:placetype":"venue"
},
  "geometry": {"coordinates":[-100.02291870099999,49.406879425],"type":"Point"}
}