{
  "type": "Feature",
  "properties": {
    "addr:full":"515 Park Rd N Brantford ON N3R 7K8",
    "addr:housenumber":"515",
    "addr:postcode":"n3r 7k8",
    "addr:street":"Park Rd N",
    "iso:country":"CA",
    "sg:address":"515 Park Rd N",
    "sg:city":"Brantford",
    "sg:classifiers":[
        {
            "category":"Real Estate",
            "subcategory":"Real Estate Agent",
            "type":"Services"
        }
    ],
    "sg:phone":"+1 519 756 8053",
    "sg:postcode":"N3R 7K8",
    "sg:province":"ON",
    "sg:tags":[
        "management"
    ],
    "wof:name":"Executive Property Management",
    "wof:placetype":"venue"
},
  "geometry": {"coordinates":[-80.251121521,43.1854324341],"type":"Point"}
}