{
  "type": "Feature",
  "properties": {
    "iso:country":"CA",
    "sg:city":"Grand Valley",
    "sg:classifiers":[
        {
            "category":"Building & Trades",
            "subcategory":"Construction",
            "type":"Services"
        }
    ],
    "sg:phone":"+1 519 928 3344",
    "sg:postcode":"L0N 1G0",
    "sg:province":"ON",
    "sg:tags":[
        "general",
        "contractor"
    ],
    "wof:name":"Fuller's Roofing",
    "wof:placetype":"venue"
},
  "geometry": {"coordinates":[-80.3152542114,43.8980712891],"type":"Point"}
}