{
  "type": "Feature",
  "properties": {
    "iso:country":"CA",
    "sg:address":"670 Duncan Ave W",
    "sg:city":"Penticton",
    "sg:classifiers":[
        {
            "category":"Home & Garden",
            "subcategory":"Garden Supply",
            "type":"Retail Goods"
        }
    ],
    "sg:phone":"+1 250 492 5703",
    "sg:postcode":"V2A 7N1",
    "sg:province":"BC",
    "sg:tags":[
        "nurseryman",
        "center"
    ],
    "wof:name":"Art Knapp's Plantland",
    "wof:placetype":"venue"
},
  "geometry": {"coordinates":[-119.60470581,49.4870109558],"type":"Point"}
}