{
  "type": "Feature",
  "properties": {
    "addr:full":"500 Rue Labelle Mont-Tremblant QC J8E 3H2",
    "addr:housenumber":"500",
    "addr:postcode":"j8e 3h2",
    "addr:street":"Rue Labelle",
    "iso:country":"CA",
    "sg:address":"500 Rue Labelle",
    "sg:city":"Mont-Tremblant",
    "sg:classifiers":[
        {
            "category":"Personal",
            "subcategory":"Beauty Salon",
            "type":"Services"
        }
    ],
    "sg:phone":"+1 819 425 7171",
    "sg:postcode":"J8E 3H2",
    "sg:province":"QC",
    "wof:name":"Salon DE Bronzage 500",
    "wof:placetype":"venue"
},
  "geometry": {"coordinates":[-74.59227,46.120369],"type":"Point"}
}