{
  "type": "Feature",
  "properties": {
    "addr:full":"1005 Skyview Dr Burlington ON L7P 5B1",
    "addr:housenumber":"1005",
    "addr:postcode":"l7p 5b1",
    "addr:street":"Skyview Dr",
    "iso:country":"CA",
    "sg:address":"1005 Skyview Dr",
    "sg:city":"Burlington",
    "sg:classifiers":[
        {
            "category":"Professional",
            "subcategory":"Management & Consulting",
            "type":"Services"
        }
    ],
    "sg:phone":"+1 905 331 5548",
    "sg:postcode":"L7P 5B1",
    "sg:province":"ON",
    "sg:tags":[
        "consultant",
        "electrical"
    ],
    "wof:name":"Canada Energy Corp",
    "wof:placetype":"venue"
},
  "geometry": {"coordinates":[-79.83767700200001,43.3347358704],"type":"Point"}
}