{
  "type": "Feature",
  "properties": {
    "addr:full":"999 Dundas St E Toronto ON M4M 1R6",
    "addr:housenumber":"999",
    "addr:postcode":"m4m 1r6",
    "addr:street":"Dundas St E",
    "iso:country":"CA",
    "sg:address":"999 Dundas St E",
    "sg:city":"Toronto",
    "sg:classifiers":[
        {
            "category":"Retail",
            "subcategory":"Auto Repair",
            "type":"Services"
        }
    ],
    "sg:phone":"+1 416 469 2244",
    "sg:postcode":"M4M 1R6",
    "sg:province":"ON",
    "sg:tags":[
        "repairing",
        "automobile"
    ],
    "wof:name":"S T United Motors",
    "wof:placetype":"venue"
},
  "geometry": {"coordinates":[-79.34628295900001,43.6634559631],"type":"Point"}
}