{
  "type": "Feature",
  "properties": {
    "addr:full":"Abbotsford BC V2T 3L2",
    "addr:postcode":"v2t 3l2",
    "iso:country":"CA",
    "sg:city":"Abbotsford",
    "sg:classifiers":[
        {
            "category":"Restaurant",
            "type":"Food & Drink"
        }
    ],
    "sg:phone":"+1 604 850 1613",
    "sg:postcode":"V2T 3L2",
    "sg:province":"BC",
    "wof:name":"Greek Islands Restaurant",
    "wof:placetype":"venue"
},
  "geometry": {"coordinates":[-122.330544,49.051151],"type":"Point"}
}