{
  "type": "Feature",
  "properties": {
    "addr:full":"465 Rue Principale Ile-Aux-Noix QC J0J 1G0",
    "addr:housenumber":"465",
    "addr:postcode":"j0j 1g0",
    "addr:street":"Rue Principale",
    "iso:country":"CA",
    "sg:address":"465 Rue Principale",
    "sg:city":"Ile-Aux-Noix",
    "sg:classifiers":[
        {
            "category":"Professional",
            "subcategory":"Art Services",
            "type":"Services"
        }
    ],
    "sg:phone":"+1 450 246 3223",
    "sg:postcode":"J0J 1G0",
    "sg:province":"QC",
    "sg:tags":[
        "graphic",
        "designer"
    ],
    "wof:name":"Vincent Deguire Enr",
    "wof:placetype":"venue"
},
  "geometry": {"coordinates":[-73.313621521,45.0959892273],"type":"Point"}
}