{
  "type": "Feature",
  "properties": {
    "addr:full":"828 Legion Rd Burlington ON L7S 1T5",
    "addr:housenumber":"828",
    "addr:postcode":"l7s 1t5",
    "addr:street":"Legion Rd",
    "iso:country":"CA",
    "sg:address":"828 Legion Rd",
    "sg:city":"Burlington",
    "sg:classifiers":[
        {
            "category":"Organizations",
            "subcategory":"Community Association",
            "type":"Services"
        }
    ],
    "sg:phone":"+1 905 639 6060",
    "sg:postcode":"L7S 1T5",
    "sg:province":"ON",
    "sg:tags":[
        "club"
    ],
    "wof:name":"Royal Canadian Legion",
    "wof:placetype":"venue"
},
  "geometry": {"coordinates":[-79.8120880127,43.3334236145],"type":"Point"}
}