{
  "type": "Feature",
  "properties": {
    "addr:full":"Lachine QC H8R 1R4",
    "addr:postcode":"h8r 1r4",
    "iso:country":"CA",
    "sg:city":"Lachine",
    "sg:classifiers":[
        {
            "category":"Professional",
            "subcategory":"Business Services",
            "type":"Services"
        }
    ],
    "sg:phone":"+1 514 485 0482",
    "sg:postcode":"H8R 1R4",
    "sg:province":"QC",
    "sg:tags":[
        "repairing",
        "sign"
    ],
    "wof:name":"Y S Maintenance",
    "wof:placetype":"venue"
},
  "geometry": {"coordinates":[-73.66464999999999,45.450043],"type":"Point"}
}