{
  "type": "Feature",
  "properties": {
    "addr:full":"Clyde River NU X0A 0E0",
    "addr:postcode":"x0a 0e0",
    "iso:country":"CA",
    "sg:city":"Clyde River",
    "sg:classifiers":[
        {
            "category":"Government",
            "subcategory":"Office",
            "type":"Public Place"
        }
    ],
    "sg:phone":"+1 867 924 6375",
    "sg:postcode":"X0A 0E0",
    "sg:province":"NU",
    "sg:tags":[
        "village"
    ],
    "wof:name":"Clyde River Employment Asstnt",
    "wof:placetype":"venue"
},
  "geometry": {"coordinates":[-68.5860366821,70.47291564939999],"type":"Point"}
}