{
  "type": "Feature",
  "properties": {
    "iso:country":"CA",
    "sg:address":"120 Jackson St S",
    "sg:city":"Walkerton",
    "sg:classifiers":[
        {
            "category":"Real Estate",
            "subcategory":"Real Estate Agent",
            "type":"Services"
        }
    ],
    "sg:phone":"+1 519 881 2551",
    "sg:postcode":"N0G 2V0",
    "sg:province":"ON",
    "wof:name":"Coldwell Banker Saugeen Rl Est",
    "wof:placetype":"venue"
},
  "geometry": {"coordinates":[-81.1494445801,44.134677887],"type":"Point"}
}