{
  "type": "Feature",
  "properties": {
    "addr:full":"Beauport QC G1C 3K6",
    "addr:postcode":"qc g1c 3k6",
    "iso:country":"CA",
    "sg:city":"Beauport",
    "sg:classifiers":[
        {
            "category":"Building & Trades",
            "subcategory":"Construction",
            "type":"Services"
        }
    ],
    "sg:phone":"+1 418 664 1477",
    "sg:postcode":"G1C 3K6",
    "sg:province":"QC",
    "sg:tags":[
        "masonry",
        "contractor"
    ],
    "wof:name":"Briquetal Limitee",
    "wof:placetype":"venue"
},
  "geometry": {"coordinates":[-71.16761,46.876812],"type":"Point"}
}