{
  "type": "Feature",
  "properties": {
    "addr:full":"First St S Milo AB T0L 1L0",
    "addr:postcode":"t0l 1l0",
    "addr:street":"First St S",
    "iso:country":"CA",
    "sg:address":"First St S",
    "sg:city":"Milo",
    "sg:classifiers":[
        {
            "category":"Education",
            "subcategory":"Library",
            "type":"Public Place"
        }
    ],
    "sg:phone":"+1 403 599 3850",
    "sg:postcode":"T0L 1L0",
    "sg:province":"AB",
    "wof:name":"Milo Municipal Library",
    "wof:placetype":"venue"
},
  "geometry": {"coordinates":[-112.88332366900001,50.5685005188],"type":"Point"}
}