{
  "type": "Feature",
  "properties": {
    "addr:full":"369 Maria St Sarnia ON N7T 4T7",
    "addr:housenumber":"369",
    "addr:postcode":"n7t 4t7",
    "addr:street":"Maria St",
    "iso:country":"CA",
    "sg:address":"369 Maria St",
    "sg:city":"Sarnia",
    "sg:classifiers":[
        {
            "category":"Education",
            "subcategory":"School",
            "type":"Public Place"
        }
    ],
    "sg:phone":"+1 519 344 7631",
    "sg:postcode":"N7T 4T7",
    "sg:province":"ON",
    "wof:name":"Hanna Memorial School",
    "wof:placetype":"venue"
},
  "geometry": {"coordinates":[-82.39104500000001,42.976044],"type":"Point"}
}