{
  "type": "Feature",
  "properties": {
    "addr:full":"3573 Rue Ashby Saint-Laurent QC H4R 2K3",
    "addr:housenumber":"3573",
    "addr:postcode":"h4r 2k3",
    "addr:street":"Rue Ashby",
    "iso:country":"CA",
    "sg:address":"3573 Rue Ashby",
    "sg:city":"Saint-Laurent",
    "sg:classifiers":[
        {
            "category":"Shopping",
            "subcategory":"Music",
            "type":"Retail Goods"
        }
    ],
    "sg:phone":"+1 514 337 9500",
    "sg:postcode":"H4R 2K3",
    "sg:province":"QC",
    "sg:tags":[
        "compact",
        "record",
        "disc",
        "tape"
    ],
    "wof:name":"Distribution DE Disques Merite",
    "wof:placetype":"venue"
},
  "geometry": {"coordinates":[-73.71640014650001,45.4988708496],"type":"Point"}
}