{
  "type": "Feature",
  "properties": {
    "addr:full":"4020 Boul Le Corbusier Laval QC H7L 5R2",
    "addr:housenumber":"4020",
    "addr:postcode":"h7l 5r2",
    "addr:street":"Boul Le Corbusier",
    "iso:country":"CA",
    "sg:address":"4020 Boul Le Corbusier",
    "sg:city":"Laval",
    "sg:classifiers":[
        {
            "category":"Professional",
            "subcategory":"Management & Consulting",
            "type":"Services"
        }
    ],
    "sg:phone":"+1 450 624 0334",
    "sg:postcode":"H7L 5R2",
    "sg:province":"QC",
    "sg:tags":[
        "consultant",
        "welding"
    ],
    "wof:name":"Consultarc Inc",
    "wof:placetype":"venue"
},
  "geometry": {"coordinates":[-73.7605438232,45.5926322937],"type":"Point"}
}