{
  "type": "Feature",
  "properties": {
    "addr:full":"1593 128 St Surrey BC V4A 3V1",
    "addr:housenumber":"1593",
    "addr:postcode":"v4a 3v1",
    "addr:street":"128 St",
    "iso:country":"CA",
    "sg:address":"1593 128 St",
    "sg:city":"Surrey",
    "sg:classifiers":[
        {
            "category":"Banks & Credit Unions",
            "subcategory":"Investment Brokerage",
            "type":"Services"
        }
    ],
    "sg:phone":"+1 604 542 6280",
    "sg:postcode":"V4A 3V1",
    "sg:province":"BC",
    "wof:name":"Edward Jones",
    "wof:placetype":"venue"
},
  "geometry": {"coordinates":[-122.867660523,49.0311088562],"type":"Point"}
}