{
  "type": "Feature",
  "properties": {
    "addr:full":"Edmonton AB T5S 2C4",
    "addr:postcode":"t5s 2c4",
    "iso:country":"CA",
    "sg:city":"Edmonton",
    "sg:classifiers":[
        {
            "category":"Recreation",
            "type":"Entertainment"
        }
    ],
    "sg:phone":"+1 780 447 3564",
    "sg:postcode":"T5S 2C4",
    "sg:province":"AB",
    "sg:tags":[
        "campground",
        "hall",
        "auditorium"
    ],
    "wof:name":"Shakers Acres Banquet Hall",
    "wof:placetype":"venue"
},
  "geometry": {"coordinates":[-113.690673828,53.5441322327],"type":"Point"}
}