{
  "type": "Feature",
  "properties": {
    "addr:full":"4 Nohaway St Matagami QC J0Y 2A0",
    "addr:housenumber":"4",
    "addr:postcode":"j0y 2a0",
    "addr:street":"Nohaway St",
    "iso:country":"CA",
    "sg:address":"4 Nohaway St",
    "sg:city":"Matagami",
    "sg:classifiers":[
        {
            "category":"Shopping",
            "subcategory":"Bicycles & Sporting Goods",
            "type":"Retail Goods"
        }
    ],
    "sg:phone":"+1 819 739 3883",
    "sg:postcode":"J0Y 2A0",
    "sg:province":"QC",
    "sg:tags":[
        "gun",
        "gunsmith"
    ],
    "wof:name":"Nord Select",
    "wof:placetype":"venue"
},
  "geometry": {"coordinates":[-77.630821,49.767475],"type":"Point"}
}