{
  "type": "Feature",
  "properties": {
    "addr:full":"300 Lorne St Kamloops BC V2C 1W3",
    "addr:housenumber":"300",
    "addr:postcode":"bc v2c 1w3",
    "addr:street":"Lorne St",
    "iso:country":"CA",
    "sg:address":"300 Lorne St",
    "sg:city":"Kamloops",
    "sg:classifiers":[
        {
            "category":"Recreation",
            "type":"Entertainment"
        }
    ],
    "sg:phone":"+1 250 828 1144",
    "sg:postcode":"V2C 1W3",
    "sg:province":"BC",
    "sg:tags":[
        "club",
        "hockey"
    ],
    "wof:name":"Kamloops Blazers Hockey Club",
    "wof:placetype":"venue"
},
  "geometry": {"coordinates":[-120.33417511,50.6781806946],"type":"Point"}
}