{
  "type": "Feature",
  "properties": {
    "addr:full":"267 Mountain Ave Winnipeg MB R2W 1J7",
    "addr:housenumber":"267",
    "addr:postcode":"r2w 1j7",
    "addr:street":"Mountain Ave",
    "iso:country":"CA",
    "sg:address":"267 Mountain Ave",
    "sg:city":"Winnipeg",
    "sg:classifiers":[
        {
            "category":"Professional",
            "subcategory":"Lawyer & Legal Services",
            "type":"Services"
        }
    ],
    "sg:phone":"+1 204 586 5588",
    "sg:postcode":"R2W 1J7",
    "sg:province":"MB",
    "sg:tags":[
        "attorney"
    ],
    "wof:name":"Chuchman, Martha I",
    "wof:placetype":"venue"
},
  "geometry": {"coordinates":[-97.1302947998,49.9200019836],"type":"Point"}
}