{
  "type": "Feature",
  "properties": {
    "addr:full":"1775 Ch Saint-Roch Sorel-Tracy QC J3R 3L3",
    "addr:housenumber":"1775",
    "addr:postcode":"j3r 3l3",
    "addr:street":"Ch Saint-Roch",
    "iso:country":"CA",
    "sg:address":"1775 Ch Saint-Roch",
    "sg:city":"Sorel-Tracy",
    "sg:classifiers":[
        {
            "category":"Autos & Motor Vehicles",
            "subcategory":"Automobile Sales",
            "type":"Retail Goods"
        }
    ],
    "sg:phone":"+1 450 746 7800",
    "sg:postcode":"J3R 3L3",
    "sg:province":"QC",
    "sg:tags":[
        "car",
        "dealer"
    ],
    "wof:name":"Christian Tremblay Autos",
    "wof:placetype":"venue"
},
  "geometry": {"coordinates":[-73.129372,46.0354],"type":"Point"}
}