{
  "type": "Feature",
  "properties": {
    "addr:full":"100 Mile House BC V0K 2E3",
    "addr:postcode":"v0k 2e3",
    "iso:country":"CA",
    "sg:city":"100 Mile House",
    "sg:classifiers":[
        {
            "category":"Insurance",
            "subcategory":"Insurance Agent",
            "type":"Services"
        }
    ],
    "sg:phone":"+1 250 395 2315",
    "sg:postcode":"V0K 2E3",
    "sg:province":"BC",
    "sg:tags":[
        "consultant"
    ],
    "wof:name":"Industrial Alliance Pacific",
    "wof:placetype":"venue"
},
  "geometry": {"coordinates":[-121.391159058,51.3140258789],"type":"Point"}
}