{
  "type": "Feature",
  "properties": {
    "addr:full":"410 Island Hwy W Parksville BC V9P 1K8",
    "addr:housenumber":"410",
    "addr:postcode":"v9p 1k8",
    "addr:street":"Island Hwy W",
    "iso:country":"CA",
    "sg:address":"410 Island Hwy W",
    "sg:city":"Parksville",
    "sg:classifiers":[
        {
            "category":"Autos & Motor Vehicles",
            "subcategory":"Automobile Sales",
            "type":"Retail Goods"
        }
    ],
    "sg:phone":"+1 250 248 2062",
    "sg:postcode":"V9P 1K8",
    "sg:province":"BC",
    "sg:tags":[
        "car",
        "dealer"
    ],
    "wof:name":"Joe Cunningham Ford Mercury",
    "wof:placetype":"venue"
},
  "geometry": {"coordinates":[-124.32433319099999,49.3233985901],"type":"Point"}
}