{
  "type": "Feature",
  "properties": {
    "addr:full":"255 S Government Greenwood BC V0H 1J0",
    "addr:housenumber":"255",
    "addr:postcode":"v0h 1j0",
    "addr:street":"S Government",
    "iso:country":"CA",
    "sg:address":"255 S Government",
    "sg:city":"Greenwood",
    "sg:classifiers":[
        {
            "category":"Government",
            "subcategory":"Office",
            "type":"Public Place"
        }
    ],
    "sg:phone":"+1 250 445 6424",
    "sg:postcode":"V0H 1J0",
    "sg:province":"BC",
    "wof:name":"BC Health Unit",
    "wof:placetype":"venue"
},
  "geometry": {"coordinates":[-118.67617,49.088959],"type":"Point"}
}