{
  "type": "Feature",
  "properties": {
    "addr:full":"1919 8th Ave Humboldt SK S0K 2A0",
    "addr:housenumber":"1919",
    "addr:postcode":"s0k 2a0",
    "addr:street":"8Th Ave",
    "iso:country":"CA",
    "sg:address":"1919 8th Ave",
    "sg:city":"Humboldt",
    "sg:classifiers":[
        {
            "category":"Home & Garden",
            "subcategory":"Household Appliances",
            "type":"Retail Goods"
        }
    ],
    "sg:phone":"+1 306 682 3585",
    "sg:postcode":"S0K 2A0",
    "sg:province":"SK",
    "sg:tags":[
        "cleaners",
        "vacuum"
    ],
    "wof:name":"Humboldt Vacuum",
    "wof:placetype":"venue"
},
  "geometry": {"coordinates":[-105.12226867699999,52.2018966675],"type":"Point"}
}