{
  "type": "Feature",
  "properties": {
    "addr:full":"1075 Yamaska Abbotsford QC J0E 1A0",
    "addr:housenumber":"1075",
    "addr:postcode":"j0e 1a0",
    "addr:street":"Yamaska",
    "iso:country":"CA",
    "sg:address":"1075 Yamaska",
    "sg:city":"Abbotsford",
    "sg:classifiers":[
        {
            "category":"Social Services",
            "subcategory":"Child Care",
            "type":"Services"
        }
    ],
    "sg:phone":"+1 450 379 9695",
    "sg:postcode":"J0E 1A0",
    "sg:province":"QC",
    "wof:name":"Cpe L'Amus'Ailes",
    "wof:placetype":"venue"
},
  "geometry": {"coordinates":[-72.8919143677,45.4360122681],"type":"Point"}
}