{
  "type": "Feature",
  "properties": {
    "addr:full":"217 Fairyview Dr Huntsville ON P1H 1C1",
    "addr:housenumber":"217",
    "addr:postcode":"p1h 1c1",
    "addr:street":"Fairyview Dr",
    "iso:country":"CA",
    "sg:address":"217 Fairyview Dr",
    "sg:city":"Huntsville",
    "sg:classifiers":[
        {
            "category":"Home & Garden",
            "subcategory":"Household Appliances",
            "type":"Retail Goods"
        }
    ],
    "sg:phone":"+1 705 789 4118",
    "sg:postcode":"P1H 1C1",
    "sg:province":"ON",
    "wof:name":"Johnson Appliance Repair",
    "wof:placetype":"venue"
},
  "geometry": {"coordinates":[-79.192566,45.340084],"type":"Point"}
}