{
  "type": "Feature",
  "properties": {
    "addr:full":"14240 29A Ave Surrey BC V4P 2H6",
    "addr:housenumber":"14240",
    "addr:postcode":"v4p 2h6",
    "addr:street":"29A Ave",
    "iso:country":"CA",
    "sg:address":"14240 29A Ave",
    "sg:city":"Surrey",
    "sg:classifiers":[
        {
            "category":"Wholesale",
            "subcategory":"Machinery & Supplies",
            "type":"Manufacturing & Wholesale Goods"
        }
    ],
    "sg:phone":"+1 604 541 7254",
    "sg:postcode":"V4P 2H6",
    "sg:province":"BC",
    "sg:tags":[
        "pulverizing",
        "crushing"
    ],
    "wof:name":"Metso Minerals",
    "wof:placetype":"venue"
},
  "geometry": {"coordinates":[-122.830215454,49.105178833],"type":"Point"}
}