{
  "type": "Feature",
  "properties": {
    "addr:full":"320 Fairview Dr Brantford ON N3R 2X6",
    "addr:housenumber":"320",
    "addr:postcode":"n3r 2x6",
    "addr:street":"Fairview Dr",
    "iso:country":"CA",
    "sg:address":"320 Fairview Dr",
    "sg:city":"Brantford",
    "sg:classifiers":[
        {
            "category":"Education",
            "subcategory":"School",
            "type":"Public Place"
        }
    ],
    "sg:phone":"+1 519 759 0380",
    "sg:postcode":"N3R 2X6",
    "sg:province":"ON",
    "wof:name":"St Patrick's School",
    "wof:placetype":"venue"
},
  "geometry": {"coordinates":[-80.258499,43.170418],"type":"Point"}
}