{
  "type": "Feature",
  "properties": {
    "addr:full":"9010 Boul Maurice-Duplessis Montreal QC H1E 6P7",
    "addr:housenumber":"9010",
    "addr:postcode":"h1e 6p7",
    "addr:street":"Boul Maurice-Duplessis",
    "iso:country":"CA",
    "sg:address":"9010 Boul Maurice-Duplessis",
    "sg:city":"Montreal",
    "sg:classifiers":[
        {
            "category":"Retail",
            "subcategory":"Laundry & Dry Cleaning",
            "type":"Services"
        }
    ],
    "sg:phone":"+1 514 648 7822",
    "sg:postcode":"H1E 6P7",
    "sg:province":"QC",
    "sg:tags":[
        "cleaners"
    ],
    "wof:name":"Nettoyeur Vimont",
    "wof:placetype":"venue"
},
  "geometry": {"coordinates":[-73.574158,45.642864],"type":"Point"}
}