{
  "type": "Feature",
  "properties": {
    "addr:full":"45 Morgans Rd Newmarket ON L3Y 4V8",
    "addr:housenumber":"45",
    "addr:postcode":"l3y 4v8",
    "addr:street":"Morgans Rd",
    "iso:country":"CA",
    "sg:address":"45 Morgans Rd",
    "sg:city":"Newmarket",
    "sg:classifiers":[
        {
            "category":"Autos & Motor Vehicles",
            "subcategory":"Boat Sales",
            "type":"Retail Goods"
        }
    ],
    "sg:phone":"+1 905 853 1335",
    "sg:postcode":"L3Y 4V8",
    "sg:province":"ON",
    "sg:tags":[
        "marina",
        "equipment",
        "supply"
    ],
    "wof:name":"Lillie's Marina",
    "wof:placetype":"venue"
},
  "geometry": {"coordinates":[-79.458572,44.04018],"type":"Point"}
}