{
  "type": "Feature",
  "properties": {
    "addr:full":"930 Fleming Ave Penhold AB T0M 1R0",
    "addr:housenumber":"930",
    "addr:postcode":"t0m 1r0",
    "addr:street":"Fleming Ave",
    "iso:country":"CA",
    "sg:address":"930 Fleming Ave",
    "sg:city":"Penhold",
    "sg:classifiers":[
        {
            "category":"Manufacturing",
            "subcategory":"Building Materials",
            "type":"Manufacturing & Wholesale Goods"
        }
    ],
    "sg:phone":"+1 403 886 4852",
    "sg:postcode":"T0M 1R0",
    "sg:province":"AB",
    "wof:name":"Bar S Concrete Products",
    "wof:placetype":"venue"
},
  "geometry": {"coordinates":[-113.876152,52.132671],"type":"Point"}
}