{
  "type": "Feature",
  "properties": {
    "addr:full":"712 Hochelaga St W Moose Jaw SK S6H 2H6",
    "addr:housenumber":"712",
    "addr:postcode":"s6h 2h6",
    "addr:street":"Hochelaga St W",
    "iso:country":"CA",
    "sg:address":"712 Hochelaga St W",
    "sg:city":"Moose Jaw",
    "sg:classifiers":[
        {
            "category":"Building & Trades",
            "subcategory":"Construction",
            "type":"Services"
        }
    ],
    "sg:phone":"+1 306 693 4490",
    "sg:postcode":"S6H 2H6",
    "sg:province":"SK",
    "sg:tags":[
        "painter"
    ],
    "wof:name":"Shamrock Painting",
    "wof:placetype":"venue"
},
  "geometry": {"coordinates":[-105.552444458,50.3964500427],"type":"Point"}
}