{
  "type": "Feature",
  "properties": {
    "iso:country":"CA",
    "sg:city":"Brantford",
    "sg:classifiers":[
        {
            "category":"Insurance",
            "subcategory":"Insurance Agent",
            "type":"Services"
        }
    ],
    "sg:phone":"+1 519 753 7745",
    "sg:postcode":"N3R 2G8",
    "sg:province":"ON",
    "wof:name":"Doug Swanson Assurances",
    "wof:placetype":"venue"
},
  "geometry": {"coordinates":[-80.2726898193,43.1613845825],"type":"Point"}
}