{
  "type": "Feature",
  "properties": {
    "addr:full":"Dolbeau-Mistassini QC G8L 5K6",
    "addr:postcode":"g8l 5k6",
    "iso:country":"CA",
    "sg:city":"Dolbeau-Mistassini",
    "sg:classifiers":[
        {
            "category":"Freight",
            "type":"Transportation"
        }
    ],
    "sg:phone":"+1 418 276 1911",
    "sg:postcode":"G8L 5K6",
    "sg:province":"QC",
    "sg:tags":[
        "repairing",
        "automobile",
        "trucking"
    ],
    "wof:name":"Garage Raymond Lambert",
    "wof:placetype":"venue"
},
  "geometry": {"coordinates":[-72.224327,48.889465],"type":"Point"}
}