{
  "type": "Feature",
  "properties": {
    "addr:full":"355 Wellington St W Sault Ste Marie ON P6A 1H9",
    "addr:housenumber":"355",
    "addr:postcode":"p6a 1h9",
    "addr:street":"Wellington St W",
    "iso:country":"CA",
    "sg:address":"355 Wellington St W",
    "sg:city":"Sault Ste Marie",
    "sg:classifiers":[
        {
            "category":"Organizations",
            "subcategory":"Religious Organization",
            "type":"Services"
        }
    ],
    "sg:phone":"+1 705 256 5381",
    "sg:postcode":"P6A 1H9",
    "sg:province":"ON",
    "sg:tags":[
        "church"
    ],
    "wof:name":"St Mary's Lutheran Church",
    "wof:placetype":"venue"
},
  "geometry": {"coordinates":[-84.34796142579999,46.5264854431],"type":"Point"}
}