{
  "type": "Feature",
  "properties": {
    "addr:full":"4100 Princess St Regina SK S4S 3N3",
    "addr:housenumber":"4100",
    "addr:postcode":"s4s 3n3",
    "addr:street":"Princess St",
    "iso:country":"CA",
    "sg:address":"4100 Princess St",
    "sg:city":"Regina",
    "sg:classifiers":[
        {
            "category":"Manufacturing",
            "subcategory":"Metals",
            "type":"Manufacturing & Wholesale Goods"
        }
    ],
    "sg:phone":"+1 306 565 8787",
    "sg:postcode":"S4S 3N3",
    "sg:province":"SK",
    "sg:tags":[
        "plumbing",
        "fixture",
        "supply"
    ],
    "wof:name":"Crane Canada Inc",
    "wof:placetype":"venue"
},
  "geometry": {"coordinates":[-104.635658264,50.4136123657],"type":"Point"}
}