{
  "type": "Feature",
  "properties": {
    "iso:country":"CA",
    "sg:address":"71 Gordon St",
    "sg:city":"Moncton",
    "sg:classifiers":[
        {
            "category":"Social Services",
            "subcategory":"Child Care",
            "type":"Services"
        }
    ],
    "sg:phone":"+1 506 383 1106",
    "sg:postcode":"E1C 1M3",
    "sg:province":"NB",
    "wof:name":"Playcenter",
    "wof:placetype":"venue"
},
  "geometry": {"coordinates":[-64.78634643549999,46.0885124207],"type":"Point"}
}