{
  "type": "Feature",
  "properties": {
    "addr:full":"1 Southworth St N Welland ON L3B 1X8",
    "addr:housenumber":"1",
    "addr:postcode":"l3b 1x8",
    "addr:street":"Southworth St N",
    "iso:country":"CA",
    "sg:address":"1 Southworth St N",
    "sg:city":"Welland",
    "sg:classifiers":[
        {
            "category":"Autos & Motor Vehicles",
            "subcategory":"Auto Supplies",
            "type":"Retail Goods"
        }
    ],
    "sg:phone":"+1 905 734 7570",
    "sg:postcode":"L3B 1X8",
    "sg:province":"ON",
    "sg:tags":[
        "repairing",
        "automobile",
        "parts"
    ],
    "wof:name":"Papp's Automotive",
    "wof:placetype":"venue"
},
  "geometry": {"coordinates":[-79.23601499999999,42.983986],"type":"Point"}
}