{
  "type": "Feature",
  "properties": {
    "addr:full":"Barrhead AB T7N 1A3",
    "addr:postcode":"t7n 1a3",
    "iso:country":"CA",
    "sg:city":"Barrhead",
    "sg:classifiers":[
        {
            "category":"Banks & Credit Unions",
            "subcategory":"Bank",
            "type":"Services"
        }
    ],
    "sg:phone":"+1 780 674 8400",
    "sg:postcode":"T7N 1A3",
    "sg:province":"AB",
    "wof:name":"Scotiabank",
    "wof:placetype":"venue"
},
  "geometry": {"coordinates":[-114.404045,54.120552],"type":"Point"}
}