{
  "type": "Feature",
  "properties": {
    "iso:country":"CA",
    "sg:address":"365 Rue Saint-Jean",
    "sg:city":"Longueuil",
    "sg:classifiers":[
        {
            "category":"Restaurant",
            "type":"Food & Drink"
        }
    ],
    "sg:phone":"+1 450 670 5609",
    "sg:postcode":"J4H 2X7",
    "sg:province":"QC",
    "wof:name":"Mc Donald's",
    "wof:placetype":"venue"
},
  "geometry": {"coordinates":[-73.507736,45.53574],"type":"Point"}
}