{
  "type": "Feature",
  "properties": {
    "iso:country":"CA",
    "sg:city":"Dawson Creek",
    "sg:classifiers":[
        {
            "category":"Shopping",
            "subcategory":"Gifts & Souvenirs",
            "type":"Retail Goods"
        }
    ],
    "sg:phone":"+1 250 782 3377",
    "sg:postcode":"V1G 4K6",
    "sg:province":"BC",
    "sg:tags":[
        "shop",
        "party",
        "supply"
    ],
    "wof:name":"Your Dollar Store With More",
    "wof:placetype":"venue"
},
  "geometry": {"coordinates":[-120.22423553500001,55.7505989075],"type":"Point"}
}