{
  "type": "Feature",
  "properties": {
    "addr:full":"15 Rue Saint-Antoine # A Metabetchouan-Lac-A-LA-Croix QC G8G 1H2",
    "addr:housenumber":"15",
    "addr:postcode":"g8g 1h2",
    "addr:street":"Rue Saint-Antoine # A Metabetchouan-Lac-A-La-Croix",
    "iso:country":"CA",
    "sg:address":"15 Rue Saint-Antoine # A",
    "sg:city":"Metabetchouan-Lac-A-LA-Croix",
    "sg:classifiers":[
        {
            "category":"Home & Garden",
            "subcategory":"Garden Supply",
            "type":"Retail Goods"
        }
    ],
    "sg:phone":"+1 418 349 2054",
    "sg:postcode":"G8G 1H2",
    "sg:province":"QC",
    "sg:tags":[
        "engine"
    ],
    "wof:name":"Au Coin Des Pieces Enr",
    "wof:placetype":"venue"
},
  "geometry": {"coordinates":[-71.872124,48.425579],"type":"Point"}
}