{
  "type": "Feature",
  "properties": {
    "addr:full":"14 Loraine St Winnipeg MB R2M 0K4",
    "addr:housenumber":"14",
    "addr:postcode":"r2m 0k4",
    "addr:street":"Loraine St",
    "iso:country":"CA",
    "sg:address":"14 Loraine St",
    "sg:city":"Winnipeg",
    "sg:classifiers":[
        {
            "category":"Building & Trades",
            "subcategory":"Electrical",
            "type":"Services"
        }
    ],
    "sg:phone":"+1 204 453 2070",
    "sg:postcode":"R2M 0K4",
    "sg:province":"MB",
    "sg:tags":[
        "communications",
        "computer",
        "datum",
        "rooms"
    ],
    "wof:name":"Lan Mind Network Cabling Inc",
    "wof:placetype":"venue"
},
  "geometry": {"coordinates":[-97.1109237671,49.8609390259],"type":"Point"}
}