{
  "type": "Feature",
  "properties": {
    "addr:full":"1234 Boul Saint-Joseph Quebec QC G2K 1G1",
    "addr:housenumber":"1234",
    "addr:postcode":"g2k 1g1",
    "addr:street":"Boul Saint-Joseph",
    "iso:country":"CA",
    "sg:address":"1234 Boul Saint-Joseph",
    "sg:city":"Quebec",
    "sg:classifiers":[
        {
            "category":"Autos & Motor Vehicles",
            "subcategory":"Fuel & Gas Station",
            "type":"Retail Goods"
        }
    ],
    "sg:phone":"+1 418 626 3511",
    "sg:postcode":"G2K 1G1",
    "sg:province":"QC",
    "sg:tags":[
        "oil"
    ],
    "wof:name":"Olco",
    "wof:placetype":"venue"
},
  "geometry": {"coordinates":[-71.283699,46.85347],"type":"Point"}
}