{
  "type": "Feature",
  "properties": {
    "addr:full":"101 Veats Ave Hinton AB T7V 1S8",
    "addr:housenumber":"101",
    "addr:postcode":"t7v 1s8",
    "addr:street":"Veats Ave",
    "iso:country":"CA",
    "sg:address":"101 Veats Ave",
    "sg:city":"Hinton",
    "sg:classifiers":[
        {
            "category":"Retail",
            "subcategory":"Laundry & Dry Cleaning",
            "type":"Services"
        }
    ],
    "sg:phone":"+1 780 865 2274",
    "sg:postcode":"T7V 1S8",
    "sg:province":"AB",
    "sg:tags":[
        "cleaners",
        "carpet",
        "dealer",
        "rug"
    ],
    "wof:name":"Sears Floor Covering Ctr",
    "wof:placetype":"venue"
},
  "geometry": {"coordinates":[-117.60553,53.395283],"type":"Point"}
}