{
  "type": "Feature",
  "properties": {
    "addr:full":"53 Rue Notre-Dame Aylmer QC J9H 3C8",
    "addr:housenumber":"53",
    "addr:postcode":"j9h 3c8",
    "addr:street":"Rue Notre-Dame",
    "iso:country":"CA",
    "sg:address":"53 Rue Notre-Dame",
    "sg:city":"Aylmer",
    "sg:classifiers":[
        {
            "category":"Organizations",
            "subcategory":"Membership Organization",
            "type":"Services"
        }
    ],
    "sg:phone":"+1 819 684 0163",
    "sg:postcode":"J9H 3C8",
    "sg:province":"QC",
    "sg:tags":[
        "association"
    ],
    "wof:name":"Centre Alimentaire Aylmer Food",
    "wof:placetype":"venue"
},
  "geometry": {"coordinates":[-75.844872,45.394909],"type":"Point"}
}