{
  "type": "Feature",
  "properties": {
    "addr:full":"1500 Av Atwater Montreal QC H3Z 1X5",
    "addr:housenumber":"1500",
    "addr:postcode":"h3z 1x5",
    "addr:street":"Av Atwater",
    "iso:country":"CA",
    "sg:address":"1500 Av Atwater",
    "sg:city":"Montreal",
    "sg:classifiers":[
        {
            "category":"Wholesale",
            "subcategory":"Durable Goods & Equipment",
            "type":"Manufacturing & Wholesale Goods"
        }
    ],
    "sg:phone":"+1 514 931 6018",
    "sg:postcode":"H3Z 1X5",
    "sg:province":"QC",
    "sg:tags":[
        "importer"
    ],
    "wof:name":"Eldorado Import",
    "wof:placetype":"venue"
},
  "geometry": {"coordinates":[-73.585319519,45.4897117615],"type":"Point"}
}