{
  "type": "Feature",
  "properties": {
    "addr:full":"610 Bay St Toronto ON M5G 1M5",
    "addr:housenumber":"610",
    "addr:postcode":"m5g 1m5",
    "addr:street":"Bay St",
    "iso:country":"CA",
    "sg:address":"610 Bay St",
    "sg:city":"Toronto",
    "sg:classifiers":[
        {
            "category":"Food & Beverages",
            "subcategory":"Groceries & Convenience Stores",
            "type":"Retail Goods"
        }
    ],
    "sg:phone":"+1 416 971 9452",
    "sg:postcode":"M5G 1M5",
    "sg:province":"ON",
    "wof:name":"United Cigar Stores",
    "wof:placetype":"venue"
},
  "geometry": {"coordinates":[-79.3841094971,43.6561393738],"type":"Point"}
}