{
  "type": "Feature",
  "properties": {
    "iso:country":"CA",
    "sg:city":"Vancouver",
    "sg:classifiers":[
        {
            "category":"Organizations",
            "subcategory":"Professional Association",
            "type":"Services"
        }
    ],
    "sg:phone":"+1 604 688 1488",
    "sg:postcode":"V6B 1N2",
    "sg:province":"BC",
    "wof:name":"International Sailors' Society",
    "wof:placetype":"venue"
},
  "geometry": {"coordinates":[-123.11333500000001,49.285206],"type":"Point"}
}