{
  "type": "Feature",
  "properties": {
    "iso:country":"CA",
    "sg:address":"859 15th St W",
    "sg:city":"Prince Albert",
    "sg:classifiers":[
        {
            "category":"Building & Trades",
            "subcategory":"Construction",
            "type":"Services"
        }
    ],
    "sg:phone":"+1 306 922 4192",
    "sg:postcode":"S6V 3S1",
    "sg:province":"SK",
    "sg:tags":[
        "roofing",
        "contractor"
    ],
    "wof:name":"Al-Pro Roofing",
    "wof:placetype":"venue"
},
  "geometry": {"coordinates":[-105.777107239,53.1990852356],"type":"Point"}
}