{
  "type": "Feature",
  "properties": {
    "addr:full":"80 Devon Rd Brampton ON L6T 5B3",
    "addr:housenumber":"80",
    "addr:postcode":"l6t 5b3",
    "addr:street":"Devon Rd",
    "iso:country":"CA",
    "sg:address":"80 Devon Rd",
    "sg:city":"Brampton",
    "sg:classifiers":[
        {
            "category":"Building & Trades",
            "subcategory":"Plumbing",
            "type":"Services"
        }
    ],
    "sg:phone":"+1 905 799 8815",
    "sg:postcode":"L6T 5B3",
    "sg:province":"ON",
    "sg:tags":[
        "sheet",
        "work",
        "metal",
        "contractor"
    ],
    "wof:name":"Vac Developments Ltd",
    "wof:placetype":"venue"
},
  "geometry": {"coordinates":[-79.6804656982,43.733745575],"type":"Point"}
}