{
  "type": "Feature",
  "properties": {
    "addr:full":"39 Capilano Way New Westminster BC V3L 5G3",
    "addr:housenumber":"39",
    "addr:postcode":"v3l 5g3",
    "addr:street":"Capilano Way",
    "iso:country":"CA",
    "sg:address":"39 Capilano Way",
    "sg:city":"New Westminster",
    "sg:classifiers":[
        {
            "category":"Manufacturing",
            "subcategory":"Tools & Machinery",
            "type":"Manufacturing & Wholesale Goods"
        }
    ],
    "sg:phone":"+1 604 520 0556",
    "sg:postcode":"V3L 5G3",
    "sg:province":"BC",
    "sg:tags":[
        "machine",
        "shop"
    ],
    "wof:name":"Elco Engineering Ltd",
    "wof:placetype":"venue"
},
  "geometry": {"coordinates":[-122.88449900000001,49.225269],"type":"Point"}
}