{
  "type": "Feature",
  "properties": {
    "addr:full":"437 Rue Sainte-Anne # B Chicoutimi QC G7J 2N2",
    "addr:housenumber":"437",
    "addr:postcode":"g7j 2n2",
    "addr:street":"Rue Sainte-Anne # B",
    "iso:country":"CA",
    "sg:address":"437 Rue Sainte-Anne # B",
    "sg:city":"Chicoutimi",
    "sg:classifiers":[
        {
            "category":"Organizations",
            "subcategory":"Professional Association",
            "type":"Services"
        }
    ],
    "sg:phone":"+1 418 545 8373",
    "sg:postcode":"G7J 2N2",
    "sg:province":"QC",
    "wof:name":"Porte Ouverte Au Passant",
    "wof:placetype":"venue"
},
  "geometry": {"coordinates":[-71.068726,48.424648],"type":"Point"}
}