{
  "type": "Feature",
  "properties": {
    "iso:country":"CA",
    "sg:address":"SW 24-23-2E",
    "sg:city":"Arborg",
    "sg:classifiers":[
        {
            "category":"Building & Trades",
            "subcategory":"Construction",
            "type":"Services"
        }
    ],
    "sg:phone":"+1 204 376 5194",
    "sg:postcode":"R0C 0A0",
    "sg:province":"MB",
    "sg:tags":[
        "general",
        "contractor"
    ],
    "wof:name":"Glacier North Ltd",
    "wof:placetype":"venue"
},
  "geometry": {"coordinates":[-97.21824646,50.9083518982],"type":"Point"}
}