{
  "type": "Feature",
  "properties": {
    "addr:full":"609 Rooks Ave Estevan SK S4A 0B4",
    "addr:housenumber":"609",
    "addr:postcode":"s4a 0b4",
    "addr:street":"Rooks Ave",
    "iso:country":"CA",
    "sg:address":"609 Rooks Ave",
    "sg:city":"Estevan",
    "sg:classifiers":[
        {
            "category":"Education",
            "subcategory":"School",
            "type":"Public Place"
        }
    ],
    "sg:phone":"+1 306 634 4931",
    "sg:postcode":"S4A 0B4",
    "sg:province":"SK",
    "wof:name":"Hillcrest Public Schools",
    "wof:placetype":"venue"
},
  "geometry": {"coordinates":[-102.98389434800001,49.1293106079],"type":"Point"}
}