{
  "type": "Feature",
  "properties": {
    "addr:full":"Brucefield ON N0M 1J0",
    "addr:postcode":"n0m 1j0",
    "iso:country":"CA",
    "sg:city":"Brucefield",
    "sg:classifiers":[
        {
            "category":"Home & Garden",
            "subcategory":"Furniture",
            "type":"Retail Goods"
        }
    ],
    "sg:phone":"+1 519 233 7232",
    "sg:postcode":"N0M 1J0",
    "sg:province":"ON",
    "sg:tags":[
        "top",
        "counter"
    ],
    "wof:name":"Custom Counterworks",
    "wof:placetype":"venue"
},
  "geometry": {"coordinates":[-81.5179977417,43.5255012512],"type":"Point"}
}