{
  "type": "Feature",
  "properties": {
    "addr:full":"484 Garrison Rd Fort Erie ON L2A 1N2",
    "addr:housenumber":"484",
    "addr:postcode":"l2a 1n2",
    "addr:street":"Garrison Rd",
    "iso:country":"CA",
    "sg:address":"484 Garrison Rd",
    "sg:city":"Fort Erie",
    "sg:classifiers":[
        {
            "category":"Restaurant",
            "type":"Food & Drink"
        }
    ],
    "sg:phone":"+1 905 871 4431",
    "sg:postcode":"L2A 1N2",
    "sg:province":"ON",
    "wof:name":"Lee's Golden Palace Chinese",
    "wof:placetype":"venue"
},
  "geometry": {"coordinates":[-78.9331817627,42.9055709839],"type":"Point"}
}