{
  "type": "Feature",
  "properties": {
    "addr:full":"2095 Granby Dr Oakville ON L6H 3Y4",
    "addr:housenumber":"2095",
    "addr:postcode":"l6h 3y4",
    "addr:street":"Granby Dr",
    "iso:country":"CA",
    "sg:address":"2095 Granby Dr",
    "sg:city":"Oakville",
    "sg:classifiers":[
        {
            "category":"Insurance",
            "subcategory":"Insurance Agent",
            "type":"Services"
        }
    ],
    "sg:phone":"+1 905 338 5000",
    "sg:postcode":"L6H 3Y4",
    "sg:province":"ON",
    "wof:name":"Hartland Insurance Brokers Ltd",
    "wof:placetype":"venue"
},
  "geometry": {"coordinates":[-79.700233,43.481693],"type":"Point"}
}