{
  "type": "Feature",
  "properties": {
    "addr:full":"6808 Cameo Dr N Vernon BC V1H 1N9",
    "addr:housenumber":"6808",
    "addr:postcode":"v1h 1n9",
    "addr:street":"Cameo Dr N",
    "iso:country":"CA",
    "sg:address":"6808 Cameo Dr N",
    "sg:city":"Vernon",
    "sg:classifiers":[
        {
            "category":"Home & Garden",
            "subcategory":"Building Materials",
            "type":"Retail Goods"
        }
    ],
    "sg:phone":"+1 250 558 9206",
    "sg:postcode":"V1H 1N9",
    "sg:province":"BC",
    "sg:tags":[
        "door"
    ],
    "wof:name":"Casa Overhead Doors Ltd",
    "wof:placetype":"venue"
},
  "geometry": {"coordinates":[-119.34229999999999,50.251087],"type":"Point"}
}