{
  "type": "Feature",
  "properties": {
    "addr:full":"Montreal QC H3W 3E7",
    "addr:postcode":"h3w 3e7",
    "iso:country":"CA",
    "sg:city":"Montreal",
    "sg:classifiers":[
        {
            "category":"Wholesale",
            "subcategory":"Medical Equipment & Supplies",
            "type":"Manufacturing & Wholesale Goods"
        }
    ],
    "sg:phone":"+1 514 488 8334",
    "sg:postcode":"H3W 3E7",
    "sg:province":"QC",
    "sg:tags":[
        "dental"
    ],
    "wof:name":"Distribution Dentaire Intl Inc",
    "wof:placetype":"venue"
},
  "geometry": {"coordinates":[-73.62813568120001,45.4846839905],"type":"Point"}
}