{
  "type": "Feature",
  "properties": {
    "iso:country":"CA",
    "sg:address":"33 Morehouse Corner Rd",
    "sg:city":"Zealand",
    "sg:classifiers":[
        {
            "category":"Organizations",
            "subcategory":"Religious Organization",
            "type":"Services"
        }
    ],
    "sg:phone":"+1 506 363 3317",
    "sg:postcode":"E6L 2K6",
    "sg:province":"NB",
    "sg:tags":[
        "church"
    ],
    "wof:name":"Zealand Sda Church",
    "wof:placetype":"venue"
},
  "geometry": {"coordinates":[-66.9350967407,46.0536689758],"type":"Point"}
}