{
  "type": "Feature",
  "properties": {
    "addr:full":"Cargill ON N0G 1J0",
    "addr:postcode":"n0g 1j0",
    "iso:country":"CA",
    "sg:city":"Cargill",
    "sg:classifiers":[
        {
            "category":"Shopping",
            "type":"Retail Goods"
        }
    ],
    "sg:phone":"+1 519 366 2249",
    "sg:postcode":"N0G 1J0",
    "sg:province":"ON",
    "sg:tags":[
        "equipment",
        "telephone",
        "supply"
    ],
    "wof:name":"Cargill Telephone CO",
    "wof:placetype":"venue"
},
  "geometry": {"coordinates":[-81.24530799999999,44.196098],"type":"Point"}
}