{
  "type": "Feature",
  "properties": {
    "addr:full":"9909 102 St Grande Prairie AB T8V 2V4",
    "addr:housenumber":"9909",
    "addr:postcode":"t8v 2v4",
    "addr:street":"102 St",
    "iso:country":"CA",
    "sg:address":"9909 102 St",
    "sg:city":"Grande Prairie",
    "sg:classifiers":[
        {
            "category":"Restaurant",
            "type":"Food & Drink"
        }
    ],
    "sg:phone":"+1 780 539 3454",
    "sg:postcode":"T8V 2V4",
    "sg:province":"AB",
    "sg:tags":[
        "caterer"
    ],
    "wof:name":"Rick's Place",
    "wof:placetype":"venue"
},
  "geometry": {"coordinates":[-118.801124573,55.1699523926],"type":"Point"}
}