{
  "type": "Feature",
  "properties": {
    "addr:full":"188 Boul Alexandre-Tache Hull QC J8Y 3L5",
    "addr:housenumber":"188",
    "addr:postcode":"j8y 3l5",
    "addr:street":"Boul Alexandre-Tache",
    "iso:country":"CA",
    "sg:address":"188 Boul Alexandre-Tache",
    "sg:city":"Hull",
    "sg:classifiers":[
        {
            "category":"Government",
            "subcategory":"Office",
            "type":"Public Place"
        }
    ],
    "sg:phone":"+1 819 777 9994",
    "sg:postcode":"J8Y 3L5",
    "sg:province":"QC",
    "sg:tags":[
        "recruiting"
    ],
    "wof:name":"Corps DE Cadets",
    "wof:placetype":"venue"
},
  "geometry": {"coordinates":[-75.7334060669,45.4235115051],"type":"Point"}
}