{
  "type": "Feature",
  "properties": {
    "addr:full":"137 Rue Centrale Yamaska-Est QC J0G 1X0",
    "addr:housenumber":"137",
    "addr:postcode":"j0g 1x0",
    "addr:street":"Rue Centrale",
    "iso:country":"CA",
    "sg:address":"137 Rue Centrale",
    "sg:city":"Yamaska-Est",
    "sg:classifiers":[
        {
            "category":"Building & Trades",
            "subcategory":"Plumbing",
            "type":"Services"
        }
    ],
    "sg:phone":"+1 450 789 0677",
    "sg:postcode":"J0G 1X0",
    "sg:province":"QC",
    "sg:tags":[
        "refrigeration",
        "appliance",
        "contractor"
    ],
    "wof:name":"Cml Svc",
    "wof:placetype":"venue"
},
  "geometry": {"coordinates":[-72.90645600000001,46.0047],"type":"Point"}
}