{
  "type": "Feature",
  "properties": {
    "iso:country":"CA",
    "sg:address":"34 Fraser Rd",
    "sg:city":"Gander",
    "sg:classifiers":[
        {
            "category":"Sports & Exercise",
            "subcategory":"Bowling",
            "type":"Entertainment"
        }
    ],
    "sg:phone":"+1 709 651 2695",
    "sg:postcode":"A1V 2E8",
    "sg:province":"NL",
    "sg:tags":[
        "center"
    ],
    "wof:name":"Peyton's Pins",
    "wof:placetype":"venue"
},
  "geometry": {"coordinates":[-54.6167984009,48.9562416077],"type":"Point"}
}