{
  "type": "Feature",
  "properties": {
    "addr:full":"1040 Goderich St Port Elgin ON N0H 2C3",
    "addr:housenumber":"1040",
    "addr:postcode":"n0h 2c3",
    "addr:street":"Goderich St",
    "iso:country":"CA",
    "sg:address":"1040 Goderich St",
    "sg:city":"Port Elgin",
    "sg:classifiers":[
        {
            "category":"Autos & Motor Vehicles",
            "subcategory":"Automobile Sales",
            "type":"Retail Goods"
        }
    ],
    "sg:phone":"+1 519 832 2047",
    "sg:postcode":"N0H 2C3",
    "sg:province":"ON",
    "sg:tags":[
        "car",
        "dealer"
    ],
    "wof:name":"Fenton's Garage Ltd",
    "wof:placetype":"venue"
},
  "geometry": {"coordinates":[-81.381119,44.446243],"type":"Point"}
}