{
  "type": "Feature",
  "properties": {
    "addr:full":"19 Knaseboro St Mississauga ON L4T 1K8",
    "addr:housenumber":"19",
    "addr:postcode":"l4t 1k8",
    "addr:street":"Knaseboro St",
    "iso:country":"CA",
    "sg:address":"19 Knaseboro St",
    "sg:city":"Mississauga",
    "sg:classifiers":[
        {
            "category":"Building & Trades",
            "subcategory":"Construction",
            "type":"Services"
        }
    ],
    "sg:phone":"+1 905 672 3555",
    "sg:postcode":"L4T 1K8",
    "sg:province":"ON",
    "sg:tags":[
        "roofing",
        "contractor"
    ],
    "wof:name":"Seal Tite Roofing & Sheet Mtl",
    "wof:placetype":"venue"
},
  "geometry": {"coordinates":[-79.6504745483,43.7024230957],"type":"Point"}
}