{
  "type": "Feature",
  "properties": {
    "iso:country":"CA",
    "sg:address":"280 Sangster Blvd",
    "sg:city":"Regina",
    "sg:classifiers":[
        {
            "category":"Education",
            "subcategory":"School",
            "type":"Public Place"
        }
    ],
    "sg:phone":"+1 306 791 7395",
    "sg:postcode":"S4R 7H5",
    "sg:province":"SK",
    "wof:name":"St Timothy Elementary School",
    "wof:placetype":"venue"
},
  "geometry": {"coordinates":[-104.632278442,50.4913711548],"type":"Point"}
}