{
  "type": "Feature",
  "properties": {
    "addr:full":"Coquitlam BC V3K 3P3",
    "addr:postcode":"v3k 3p3",
    "iso:country":"CA",
    "sg:city":"Coquitlam",
    "sg:classifiers":[
        {
            "category":"Personal",
            "subcategory":"Shoe Repair & Shine",
            "type":"Services"
        }
    ],
    "sg:phone":"+1 604 936 7775",
    "sg:postcode":"V3K 3P3",
    "sg:province":"BC",
    "sg:tags":[
        "repairing",
        "boot"
    ],
    "wof:name":"Austin Shoe Repair",
    "wof:placetype":"venue"
},
  "geometry": {"coordinates":[-122.863708,49.248852],"type":"Point"}
}