{
  "type": "Feature",
  "properties": {
    "addr:full":"117 Main St Hillsburgh ON N0B 1Z0",
    "addr:housenumber":"117",
    "addr:postcode":"n0b 1z0",
    "addr:street":"Main St",
    "iso:country":"CA",
    "sg:address":"117 Main St",
    "sg:city":"Hillsburgh",
    "sg:classifiers":[
        {
            "category":"Retail",
            "subcategory":"Auto Repair",
            "type":"Services"
        }
    ],
    "sg:phone":"+1 519 855 4382",
    "sg:postcode":"N0B 1Z0",
    "sg:province":"ON",
    "sg:tags":[
        "repairing",
        "automobile"
    ],
    "wof:name":"Hillsburgh Motors",
    "wof:placetype":"venue"
},
  "geometry": {"coordinates":[-80.145287,43.791412],"type":"Point"}
}