{
  "type": "Feature",
  "properties": {
    "addr:full":"5946 Sprott St Burnaby BC V5G 1V1",
    "addr:housenumber":"5946",
    "addr:postcode":"v5g 1v1",
    "addr:street":"Sprott St",
    "iso:country":"CA",
    "sg:address":"5946 Sprott St",
    "sg:city":"Burnaby",
    "sg:classifiers":[
        {
            "category":"Building & Trades",
            "subcategory":"Construction",
            "type":"Services"
        }
    ],
    "sg:phone":"+1 604 291 0133",
    "sg:postcode":"V5G 1V1",
    "sg:province":"BC",
    "sg:tags":[
        "acoustical",
        "ceiling",
        "contractor"
    ],
    "wof:name":"Burnaby T-Bar 94 CO Ltd",
    "wof:placetype":"venue"
},
  "geometry": {"coordinates":[-122.977356,49.249805],"type":"Point"}
}