{
  "type": "Feature",
  "properties": {
    "addr:full":"Lefroy ON L0L 1W0",
    "addr:postcode":"l0l 1w0",
    "iso:country":"CA",
    "sg:city":"Lefroy",
    "sg:classifiers":[
        {
            "category":"Sports & Exercise",
            "subcategory":"Golf",
            "type":"Entertainment"
        }
    ],
    "sg:phone":"+1 705 456 2104",
    "sg:postcode":"L0L 1W0",
    "sg:province":"ON",
    "sg:tags":[
        "course"
    ],
    "wof:name":"Big Cedar Golf & Country Club",
    "wof:placetype":"venue"
},
  "geometry": {"coordinates":[-79.552727,44.262585],"type":"Point"}
}