{
  "type": "Feature",
  "properties": {
    "addr:full":"Kitimat Village Rd Kitimat BC V8C 2G7",
    "addr:postcode":"bc v8c 2g7",
    "addr:street":"Village Rd",
    "iso:country":"CA",
    "sg:address":"Kitimat Village Rd",
    "sg:city":"Kitimat",
    "sg:classifiers":[
        {
            "category":"Recreation",
            "subcategory":"Marina",
            "type":"Entertainment"
        }
    ],
    "sg:phone":"+1 250 632 6401",
    "sg:postcode":"V8C 2G7",
    "sg:province":"BC",
    "sg:tags":[
        "government"
    ],
    "wof:name":"M K Bay Marina",
    "wof:placetype":"venue"
},
  "geometry": {"coordinates":[-128.61262500000001,54.050827],"type":"Point"}
}