{
  "type": "Feature",
  "properties": {
    "addr:full":"Saint-Felicien QC G8K 1A2",
    "addr:postcode":"g8k 1a2",
    "iso:country":"CA",
    "sg:city":"Saint-Felicien",
    "sg:classifiers":[
        {
            "category":"Banks & Credit Unions",
            "subcategory":"Bank",
            "type":"Services"
        }
    ],
    "sg:phone":"+1 418 679 0725",
    "sg:postcode":"G8K 1A2",
    "sg:province":"QC",
    "wof:name":"Banque Royale",
    "wof:placetype":"venue"
},
  "geometry": {"coordinates":[-72.444199,48.651379],"type":"Point"}
}