{
  "type": "Feature",
  "properties": {
    "addr:full":"Toronto ON M5A 4K2",
    "addr:postcode":"m5a 4k2",
    "iso:country":"CA",
    "sg:city":"Toronto",
    "sg:classifiers":[
        {
            "category":"Professional",
            "subcategory":"Lawyer & Legal Services",
            "type":"Services"
        }
    ],
    "sg:phone":"+1 416 323 3741",
    "sg:postcode":"M5A 4K2",
    "sg:province":"ON",
    "sg:tags":[
        "attorney"
    ],
    "wof:name":"Robert J Bassermann Law Office",
    "wof:placetype":"venue"
},
  "geometry": {"coordinates":[-79.37661,43.662506],"type":"Point"}
}