{
  "type": "Feature",
  "properties": {
    "addr:full":"92 Cypress Way SE Medicine Hat AB T1B 1G8",
    "addr:housenumber":"92",
    "addr:postcode":"t1b 1g8",
    "addr:street":"Cypress Way Se",
    "iso:country":"CA",
    "sg:address":"92 Cypress Way SE",
    "sg:city":"Medicine Hat",
    "sg:classifiers":[
        {
            "category":"Professional",
            "subcategory":"Engineering",
            "type":"Services"
        }
    ],
    "sg:phone":"+1 403 527 0575",
    "sg:postcode":"T1B 1G8",
    "sg:province":"AB",
    "sg:tags":[
        "engineer"
    ],
    "wof:name":"R F Manuel Engineering Ltd",
    "wof:placetype":"venue"
},
  "geometry": {"coordinates":[-110.642707825,50.0124778748],"type":"Point"}
}