{
  "type": "Feature",
  "properties": {
    "addr:full":"3570 Old Okanagan Hwy Westbank BC V4T 1P3",
    "addr:housenumber":"3570",
    "addr:postcode":"v4t 1p3",
    "addr:street":"Old Okanagan Hwy",
    "iso:country":"CA",
    "sg:address":"3570 Old Okanagan Hwy",
    "sg:city":"Westbank",
    "sg:classifiers":[
        {
            "category":"Health Services",
            "subcategory":"Clinic",
            "type":"Services"
        }
    ],
    "sg:phone":"+1 250 768 4911",
    "sg:postcode":"V4T 1P3",
    "sg:province":"BC",
    "sg:tags":[
        "therapist",
        "massage"
    ],
    "wof:name":"Westside Therapeutic Massage",
    "wof:placetype":"venue"
},
  "geometry": {"coordinates":[-119.62564086899999,49.8341407776],"type":"Point"}
}