{
  "type": "Feature",
  "properties": {
    "addr:full":"Saint-Ulric QC G0J 3H0",
    "addr:postcode":"g0j 3h0",
    "iso:country":"CA",
    "sg:city":"Saint-Ulric",
    "sg:classifiers":[
        {
            "category":"Organizations",
            "subcategory":"Professional Association",
            "type":"Services"
        }
    ],
    "sg:phone":"+1 418 737 9120",
    "sg:postcode":"G0J 3H0",
    "sg:province":"QC",
    "sg:tags":[
        "club"
    ],
    "wof:name":"Club L'Age D'Or St-Ulric",
    "wof:placetype":"venue"
},
  "geometry": {"coordinates":[-67.6990814209,48.7873382568],"type":"Point"}
}