{
  "type": "Feature",
  "properties": {
    "addr:full":"573 Mcarthur Ave Ottawa ON K1K 1G3",
    "addr:housenumber":"573",
    "addr:postcode":"k1k 1g3",
    "addr:street":"Mcarthur Ave",
    "iso:country":"CA",
    "sg:address":"573 Mcarthur Ave",
    "sg:city":"Ottawa",
    "sg:classifiers":[
        {
            "category":"Retail",
            "subcategory":"Repair Shop",
            "type":"Services"
        }
    ],
    "sg:phone":"+1 613 745 6014",
    "sg:postcode":"K1K 1G3",
    "sg:province":"ON",
    "sg:tags":[
        "upholsterer"
    ],
    "wof:name":"Da Silva Upholsterers",
    "wof:placetype":"venue"
},
  "geometry": {"coordinates":[-75.643372,45.432663],"type":"Point"}
}