{
  "type": "Feature",
  "properties": {
    "addr:full":"1500 Marine Dr North Vancouver BC V7P 1T7",
    "addr:housenumber":"1500",
    "addr:postcode":"v7p 1t7",
    "addr:street":"Marine Dr",
    "iso:country":"CA",
    "sg:address":"1500 Marine Dr",
    "sg:city":"North Vancouver",
    "sg:classifiers":[
        {
            "category":"Banks & Credit Unions",
            "subcategory":"Bank",
            "type":"Services"
        }
    ],
    "sg:phone":"+1 604 981 7570",
    "sg:postcode":"V7P 1T7",
    "sg:province":"BC",
    "wof:name":"Scotiabank",
    "wof:placetype":"venue"
},
  "geometry": {"coordinates":[-123.20562,49.273529],"type":"Point"}
}