{
  "type": "Feature",
  "properties": {
    "addr:full":"6801 50 Ave Red Deer AB T4N 4E2",
    "addr:housenumber":"6801",
    "addr:postcode":"t4n 4e2",
    "addr:street":"50 Ave",
    "iso:country":"CA",
    "sg:address":"6801 50 Ave",
    "sg:city":"Red Deer",
    "sg:classifiers":[
        {
            "category":"Autos & Motor Vehicles",
            "subcategory":"Automobile Sales",
            "type":"Retail Goods"
        }
    ],
    "sg:phone":"+1 403 314 5421",
    "sg:postcode":"T4N 4E2",
    "sg:province":"AB",
    "sg:tags":[
        "car",
        "dealer"
    ],
    "wof:name":"Scott Kia",
    "wof:placetype":"venue"
},
  "geometry": {"coordinates":[-113.81362900000001,52.292446],"type":"Point"}
}