{
  "type": "Feature",
  "properties": {
    "addr:full":"5384 Inglis St Halifax NS B3H 1J5",
    "addr:housenumber":"5384",
    "addr:postcode":"b3h 1j5",
    "addr:street":"Inglis St",
    "iso:country":"CA",
    "sg:address":"5384 Inglis St",
    "sg:city":"Halifax",
    "sg:classifiers":[
        {
            "category":"Food & Beverages",
            "subcategory":"Bakery",
            "type":"Retail Goods"
        }
    ],
    "sg:phone":"+1 902 423 7618",
    "sg:postcode":"B3H 1J5",
    "sg:province":"NS",
    "sg:tags":[
        "baker"
    ],
    "wof:name":"Continental Bakery",
    "wof:placetype":"venue"
},
  "geometry": {"coordinates":[-63.570930481,44.6356201172],"type":"Point"}
}