{
  "type": "Feature",
  "properties": {
    "addr:full":"1100 Pembroke St E # 9770 Pembroke ON K8A 6Y7",
    "addr:housenumber":"1100",
    "addr:postcode":"k8a 6y7",
    "addr:street":"Pembroke St E # 9770",
    "iso:country":"CA",
    "sg:address":"1100 Pembroke St E # 9770",
    "sg:city":"Pembroke",
    "sg:classifiers":[
        {
            "category":"Shopping",
            "subcategory":"Photographic Equipment",
            "type":"Retail Goods"
        }
    ],
    "sg:phone":"+1 613 735 0777",
    "sg:postcode":"K8A 6Y7",
    "sg:province":"ON",
    "sg:tags":[
        "picture",
        "frame"
    ],
    "wof:name":"Photo Metro Inc",
    "wof:placetype":"venue"
},
  "geometry": {"coordinates":[-77.085526,45.824032],"type":"Point"}
}