{
  "type": "Feature",
  "properties": {
    "addr:full":"16 Deercross Way SE Calgary AB T2J 6J6",
    "addr:housenumber":"16",
    "addr:postcode":"t2j 6j6",
    "addr:street":"Deercross Way Se",
    "iso:country":"CA",
    "sg:address":"16 Deercross Way SE",
    "sg:city":"Calgary",
    "sg:classifiers":[
        {
            "category":"Professional",
            "subcategory":"Management & Consulting",
            "type":"Services"
        }
    ],
    "sg:phone":"+1 403 292 0211",
    "sg:postcode":"T2J 6J6",
    "sg:province":"AB",
    "sg:tags":[
        "consultant",
        "telecommunication",
        "communications"
    ],
    "wof:name":"Network Resources Group Inc",
    "wof:placetype":"venue"
},
  "geometry": {"coordinates":[-114.009148,50.926109],"type":"Point"}
}