{
  "type": "Feature",
  "properties": {
    "addr:full":"885 Scarborough Golf Club Rd Scarborough ON M1G 1J6",
    "addr:housenumber":"885",
    "addr:postcode":"m1g 1j6",
    "addr:street":"Scarborough Golf Club Rd",
    "iso:country":"CA",
    "sg:address":"885 Scarborough Golf Club Rd",
    "sg:city":"Scarborough",
    "sg:classifiers":[
        {
            "category":"Organizations",
            "subcategory":"Religious Organization",
            "type":"Services"
        }
    ],
    "sg:phone":"+1 416 439 6933",
    "sg:postcode":"M1G 1J6",
    "sg:province":"ON",
    "sg:tags":[
        "church"
    ],
    "wof:name":"St John the Divine Anglican",
    "wof:placetype":"venue"
},
  "geometry": {"coordinates":[-79.219521,43.7724],"type":"Point"}
}