{
  "type": "Feature",
  "properties": {
    "addr:full":"710 6th Ave Ladysmith BC V9G 1A2",
    "addr:housenumber":"710",
    "addr:postcode":"v9g 1a2",
    "addr:street":"6Th Ave",
    "iso:country":"CA",
    "sg:address":"710 6th Ave",
    "sg:city":"Ladysmith",
    "sg:classifiers":[
        {
            "category":"Education",
            "subcategory":"School",
            "type":"Public Place"
        }
    ],
    "sg:phone":"+1 250 245 3043",
    "sg:postcode":"V9G 1A2",
    "sg:province":"BC",
    "wof:name":"Ladysmith Secondary School",
    "wof:placetype":"venue"
},
  "geometry": {"coordinates":[-123.826065,48.990406],"type":"Point"}
}