{
  "type": "Feature",
  "properties": {
    "addr:full":"7535 Flint Rd SE Calgary AB T2H 1G3",
    "addr:housenumber":"7535",
    "addr:postcode":"t2h 1g3",
    "addr:street":"Flint Rd Se",
    "iso:country":"CA",
    "sg:address":"7535 Flint Rd SE",
    "sg:city":"Calgary",
    "sg:classifiers":[
        {
            "category":"Mining & Drilling",
            "type":"Manufacturing & Wholesale Goods"
        }
    ],
    "sg:phone":"+1 403 253 4151",
    "sg:postcode":"T2H 1G3",
    "sg:province":"AB",
    "sg:tags":[
        "field",
        "oil"
    ],
    "wof:name":"Sunada Technology Corp",
    "wof:placetype":"venue"
},
  "geometry": {"coordinates":[-114.06738300000001,50.986053],"type":"Point"}
}