{
  "type": "Feature",
  "properties": {
    "addr:full":"Keremeos BC V0X 1N0",
    "addr:postcode":"v0x 1n0",
    "iso:country":"CA",
    "sg:city":"Keremeos",
    "sg:classifiers":[
        {
            "category":"Retail",
            "subcategory":"Auto Repair",
            "type":"Services"
        }
    ],
    "sg:phone":"+1 250 499 7077",
    "sg:postcode":"V0X 1N0",
    "sg:province":"BC",
    "sg:tags":[
        "repairing",
        "automobile"
    ],
    "wof:name":"K Mountain Auto Repair",
    "wof:placetype":"venue"
},
  "geometry": {"coordinates":[-119.824127197,49.2051391602],"type":"Point"}
}