{
  "type": "Feature",
  "properties": {
    "iso:country":"CA",
    "sg:address":"2803 Quinn Dr",
    "sg:city":"Regina",
    "sg:classifiers":[
        {
            "category":"Building & Trades",
            "subcategory":"Construction",
            "type":"Services"
        }
    ],
    "sg:phone":"+1 306 757 9317",
    "sg:postcode":"S4P 2W2",
    "sg:province":"SK",
    "sg:tags":[
        "painter"
    ],
    "wof:name":"Marchuk Decorating",
    "wof:placetype":"venue"
},
  "geometry": {"coordinates":[-104.596633911,50.4351387024],"type":"Point"}
}