{
  "type": "Feature",
  "properties": {
    "addr:full":"PO Box 455 Milverton ON N0K 1M0",
    "addr:housenumber":"po",
    "addr:postcode":"n0k 1m0",
    "addr:street":"Box 455 Milverton",
    "iso:country":"CA",
    "sg:address":"PO Box 455",
    "sg:city":"Milverton",
    "sg:classifiers":[
        {
            "category":"Organizations",
            "subcategory":"Religious Organization",
            "type":"Services"
        }
    ],
    "sg:phone":"+1 519 595 4902",
    "sg:postcode":"N0K 1M0",
    "sg:province":"ON",
    "sg:tags":[
        "church"
    ],
    "wof:name":"Burn's Presbyterian Church",
    "wof:placetype":"venue"
},
  "geometry": {"coordinates":[-80.920868,43.567513],"type":"Point"}
}