{
  "type": "Feature",
  "properties": {
    "addr:full":"1616 Rue Eiffel Boucherville QC J4B 8N3",
    "addr:housenumber":"1616",
    "addr:postcode":"j4b 8n3",
    "addr:street":"Rue Eiffel",
    "iso:country":"CA",
    "sg:address":"1616 Rue Eiffel",
    "sg:city":"Boucherville",
    "sg:classifiers":[
        {
            "category":"Shopping",
            "subcategory":"Stationery & Office Supplies",
            "type":"Retail Goods"
        }
    ],
    "sg:phone":"+1 450 449 4449",
    "sg:postcode":"J4B 8N3",
    "sg:province":"QC",
    "wof:name":"Corporate Express",
    "wof:placetype":"venue"
},
  "geometry": {"coordinates":[-73.3982162476,45.5697631836],"type":"Point"}
}