{
  "type": "Feature",
  "properties": {
    "addr:full":"90 Rue Du Commandeur Cantley QC J8V 3T5",
    "addr:housenumber":"90",
    "addr:postcode":"j8v 3t5",
    "addr:street":"Rue Du Commandeur",
    "iso:country":"CA",
    "sg:address":"90 Rue Du Commandeur",
    "sg:city":"Cantley",
    "sg:classifiers":[
        {
            "category":"Social Services",
            "subcategory":"Child Care",
            "type":"Services"
        }
    ],
    "sg:phone":"+1 819 827 5477",
    "sg:postcode":"J8V 3T5",
    "sg:province":"QC",
    "wof:name":"Cpe Aux Petits Carmpagnards",
    "wof:placetype":"venue"
},
  "geometry": {"coordinates":[-75.76234436039999,45.5433120728],"type":"Point"}
}