{
  "type": "Feature",
  "properties": {
    "addr:full":"1788 Main St N Moose Jaw SK S6J 1L4",
    "addr:housenumber":"1788",
    "addr:postcode":"s6j 1l4",
    "addr:street":"Main St N",
    "iso:country":"CA",
    "sg:address":"1788 Main St N",
    "sg:city":"Moose Jaw",
    "sg:classifiers":[
        {
            "category":"Autos & Motor Vehicles",
            "subcategory":"Automobile Sales",
            "type":"Retail Goods"
        }
    ],
    "sg:phone":"+1 306 692 1808",
    "sg:postcode":"S6J 1L4",
    "sg:province":"SK",
    "sg:tags":[
        "car",
        "dealer"
    ],
    "wof:name":"Western Dodge Chrysler Jeep",
    "wof:placetype":"venue"
},
  "geometry": {"coordinates":[-105.53504180900001,50.4165992737],"type":"Point"}
}