{
  "type": "Feature",
  "properties": {
    "addr:full":"12835 140 Ave NW Edmonton AB T6V 1P1",
    "addr:housenumber":"12835",
    "addr:postcode":"t6v 1p1",
    "addr:street":"140 Ave Nw",
    "iso:country":"CA",
    "sg:address":"12835 140 Ave NW",
    "sg:city":"Edmonton",
    "sg:classifiers":[
        {
            "category":"Banks & Credit Unions",
            "subcategory":"Bank",
            "type":"Services"
        }
    ],
    "sg:phone":"+1 780 456 5555",
    "sg:postcode":"T6V 1P1",
    "sg:province":"AB",
    "sg:tags":[
        "loan",
        "real estate"
    ],
    "wof:name":"Citi Financial",
    "wof:placetype":"venue"
},
  "geometry": {"coordinates":[-113.543395996,53.6018791199],"type":"Point"}
}