{
  "type": "Feature",
  "properties": {
    "addr:full":"525 Av Marshall Dorval QC H9P 1C8",
    "addr:postcode":"h9p 1c8",
    "addr:street":"525 Av Marshall",
    "iso:country":"CA",
    "sg:address":"525 Av Marshall",
    "sg:city":"Dorval",
    "sg:classifiers":[
        {
            "category":"Building & Trades",
            "subcategory":"Landscaping Services",
            "type":"Services"
        }
    ],
    "sg:phone":"+1 514 631 6867",
    "sg:postcode":"H9P 1C8",
    "sg:province":"QC",
    "sg:tags":[
        "landscape",
        "contractor"
    ],
    "wof:name":"Paysagistes Lgd Inc",
    "wof:placetype":"venue"
},
  "geometry": {"coordinates":[-73.7367477417,45.4491081238],"type":"Point"}
}