{
  "type": "Feature",
  "properties": {
    "addr:full":"6820 Rexwood Rd Mississauga ON L4V 1L8",
    "addr:housenumber":"6820",
    "addr:postcode":"l4v 1l8",
    "addr:street":"Rexwood Rd",
    "iso:country":"CA",
    "sg:address":"6820 Rexwood Rd",
    "sg:city":"Mississauga",
    "sg:classifiers":[
        {
            "category":"Wholesale",
            "subcategory":"Groceries",
            "type":"Manufacturing & Wholesale Goods"
        }
    ],
    "sg:phone":"+1 905 293 9932",
    "sg:postcode":"L4V 1L8",
    "sg:province":"ON",
    "sg:tags":[
        "food",
        "grocer",
        "broker"
    ],
    "wof:name":"Neate Roller",
    "wof:placetype":"venue"
},
  "geometry": {"coordinates":[-79.62267300000001,43.712521],"type":"Point"}
}