{
  "type": "Feature",
  "properties": {
    "iso:country":"CA",
    "sg:address":"8319 100 Ave",
    "sg:city":"Fort St John",
    "sg:classifiers":[
        {
            "category":"Retail",
            "subcategory":"Repair Shop",
            "type":"Services"
        }
    ],
    "sg:phone":"+1 250 785 3556",
    "sg:postcode":"V1J 1W7",
    "sg:province":"BC",
    "sg:tags":[
        "repairing",
        "lawn",
        "mower"
    ],
    "wof:name":"Budget Battery & Small Eng Rpr",
    "wof:placetype":"venue"
},
  "geometry": {"coordinates":[-120.815315247,56.246219635],"type":"Point"}
}