{
  "type": "Feature",
  "properties": {
    "addr:full":"205 Albert St Regina SK S4R 2N5",
    "addr:housenumber":"205",
    "addr:postcode":"s4r 2n5",
    "addr:street":"Albert St",
    "iso:country":"CA",
    "sg:address":"205 Albert St",
    "sg:city":"Regina",
    "sg:classifiers":[
        {
            "category":"Restaurant",
            "type":"Food & Drink"
        }
    ],
    "sg:phone":"+1 306 924 4180",
    "sg:postcode":"S4R 2N5",
    "sg:province":"SK",
    "wof:name":"Wendy's",
    "wof:placetype":"venue"
},
  "geometry": {"coordinates":[-104.617805,50.475285],"type":"Point"}
}