{
  "type": "Feature",
  "properties": {
    "iso:country":"CA",
    "sg:address":"2822 Dundas St W",
    "sg:city":"Toronto",
    "sg:classifiers":[
        {
            "category":"Social Services",
            "type":"Services"
        }
    ],
    "sg:phone":"+1 416 766 9108",
    "sg:postcode":"M6P 1Y7",
    "sg:province":"ON",
    "sg:tags":[
        "counselor",
        "therapist",
        "marriage",
        "family",
        "massage"
    ],
    "wof:name":"Toronto West Counselling",
    "wof:placetype":"venue"
},
  "geometry": {"coordinates":[-79.4634094238,43.6655311584],"type":"Point"}
}