{
  "type": "Feature",
  "properties": {
    "iso:country":"CA",
    "sg:city":"Matane",
    "sg:classifiers":[
        {
            "category":"Banks & Credit Unions",
            "subcategory":"Bank",
            "type":"Services"
        }
    ],
    "sg:phone":"+1 418 562 1205",
    "sg:postcode":"G4W 3W8",
    "sg:province":"QC",
    "wof:name":"Banque Nationale Du Canada",
    "wof:placetype":"venue"
},
  "geometry": {"coordinates":[-67.5010757446,48.8525123596],"type":"Point"}
}