{
  "type": "Feature",
  "properties": {
    "addr:full":"36 Industrial Dr Norwood ON K0L 2V0",
    "addr:housenumber":"36",
    "addr:postcode":"k0l 2v0",
    "addr:street":"Industrial Dr",
    "iso:country":"CA",
    "sg:address":"36 Industrial Dr",
    "sg:city":"Norwood",
    "sg:classifiers":[
        {
            "category":"Education",
            "subcategory":"School",
            "type":"Public Place"
        }
    ],
    "sg:phone":"+1 705 639 2121",
    "sg:postcode":"K0L 2V0",
    "sg:province":"ON",
    "sg:tags":[
        "academic",
        "special"
    ],
    "wof:name":"Eastern Ontario Fire Academy",
    "wof:placetype":"venue"
},
  "geometry": {"coordinates":[-77.979134,44.383034],"type":"Point"}
}