{
  "type": "Feature",
  "properties": {
    "addr:full":"4632 Sunshine Coast Hwy Sechelt BC V0N 3A2",
    "addr:housenumber":"4632",
    "addr:postcode":"v0n 3a2",
    "addr:street":"Sunshine Coast Hwy",
    "iso:country":"CA",
    "sg:address":"4632 Sunshine Coast Hwy",
    "sg:city":"Sechelt",
    "sg:classifiers":[
        {
            "category":"Travel",
            "subcategory":"Hotels & Motels",
            "type":"Entertainment"
        }
    ],
    "sg:phone":"+1 604 885 5404",
    "sg:postcode":"V0N 3A2",
    "sg:province":"BC",
    "sg:tags":[
        "breakfast",
        "accommodation",
        "bed"
    ],
    "wof:name":"Davis Bay Bed & Breakfast",
    "wof:placetype":"venue"
},
  "geometry": {"coordinates":[-123.72581481900001,49.4409561157],"type":"Point"}
}