{
  "type": "Feature",
  "properties": {
    "addr:full":"586 Eglinton Ave E # 812 Toronto ON M4P 1P2",
    "addr:housenumber":"586",
    "addr:postcode":"m4p 1p2",
    "addr:street":"Eglinton Ave E # 812",
    "iso:country":"CA",
    "sg:address":"586 Eglinton Ave E # 812",
    "sg:city":"Toronto",
    "sg:classifiers":[
        {
            "category":"Health Services",
            "subcategory":"Chiropractor",
            "type":"Services"
        }
    ],
    "sg:phone":"+1 416 487 1942",
    "sg:postcode":"M4P 1P2",
    "sg:province":"ON",
    "wof:name":"Leaside Chiropractic Clinic",
    "wof:placetype":"venue"
},
  "geometry": {"coordinates":[-79.3798522949,43.7106132507],"type":"Point"}
}