{
  "type": "Feature",
  "properties": {
    "addr:full":"454 Prince St Truro NS B2N 1E7",
    "addr:housenumber":"454",
    "addr:postcode":"b2n 1e7",
    "addr:street":"Prince St",
    "iso:country":"CA",
    "sg:address":"454 Prince St",
    "sg:city":"Truro",
    "sg:classifiers":[
        {
            "category":"Organizations",
            "subcategory":"Religious Organization",
            "type":"Services"
        }
    ],
    "sg:phone":"+1 902 895 6744",
    "sg:postcode":"B2N 1E7",
    "sg:province":"NS",
    "sg:tags":[
        "church"
    ],
    "wof:name":"Zion Baptist Church",
    "wof:placetype":"venue"
},
  "geometry": {"coordinates":[-63.289574,45.36594],"type":"Point"}
}