{
  "type": "Feature",
  "properties": {
    "addr:full":"Surrey BC V3W 2P2",
    "addr:postcode":"v3w 2p2",
    "iso:country":"CA",
    "sg:city":"Surrey",
    "sg:classifiers":[
        {
            "category":"Health Services",
            "subcategory":"Health Practitioner",
            "type":"Services"
        }
    ],
    "sg:phone":"+1 604 591 9228",
    "sg:postcode":"V3W 2P2",
    "sg:province":"BC",
    "sg:tags":[
        "supply",
        "equipment",
        "audiologists",
        "hearing",
        "impaired"
    ],
    "wof:name":"South West Hearing Clinic",
    "wof:placetype":"venue"
},
  "geometry": {"coordinates":[-122.841972,49.133701],"type":"Point"}
}