{
  "type": "Feature",
  "properties": {
    "addr:full":"Napierville QC J0J 1L0",
    "addr:postcode":"j0j 1l0",
    "iso:country":"CA",
    "sg:city":"Napierville",
    "sg:classifiers":[
        {
            "category":"Restaurant",
            "type":"Food & Drink"
        }
    ],
    "sg:phone":"+1 450 245 3358",
    "sg:postcode":"J0J 1L0",
    "sg:province":"QC",
    "sg:tags":[
        "parlor",
        "ice",
        "cream"
    ],
    "wof:name":"Bar Laitier Mickey",
    "wof:placetype":"venue"
},
  "geometry": {"coordinates":[-73.40784499999999,45.190983],"type":"Point"}
}