{
  "type": "Feature",
  "properties": {
    "addr:full":"1315 Av Godin Laval QC H7E 2T1",
    "addr:housenumber":"1315",
    "addr:postcode":"h7e 2t1",
    "addr:street":"Av Godin",
    "iso:country":"CA",
    "sg:address":"1315 Av Godin",
    "sg:city":"Laval",
    "sg:classifiers":[
        {
            "category":"Retail",
            "subcategory":"Auto Repair",
            "type":"Services"
        }
    ],
    "sg:phone":"+1 450 661 7438",
    "sg:postcode":"H7E 2T1",
    "sg:province":"QC",
    "sg:tags":[
        "repairing",
        "automobile"
    ],
    "wof:name":"Mecanique V-Tec Inc",
    "wof:placetype":"venue"
},
  "geometry": {"coordinates":[-73.666473,45.613869],"type":"Point"}
}