{
  "type": "Feature",
  "properties": {
    "addr:full":"172 Helen St Dashwood ON N0M 1N0",
    "addr:housenumber":"172",
    "addr:postcode":"n0m 1n0",
    "addr:street":"Helen St",
    "iso:country":"CA",
    "sg:address":"172 Helen St",
    "sg:city":"Dashwood",
    "sg:classifiers":[
        {
            "category":"Building & Trades",
            "subcategory":"Construction",
            "type":"Services"
        }
    ],
    "sg:phone":"+1 519 237 3412",
    "sg:postcode":"N0M 1N0",
    "sg:province":"ON",
    "sg:tags":[
        "general",
        "contractor"
    ],
    "wof:name":"Dave Rader Construction",
    "wof:placetype":"venue"
},
  "geometry": {"coordinates":[-81.6379318237,43.3467750549],"type":"Point"}
}