{
  "type": "Feature",
  "properties": {
    "addr:full":"166 Disco Rd Etobicoke ON M9W 1M4",
    "addr:housenumber":"166",
    "addr:postcode":"m9w 1m4",
    "addr:street":"Disco Rd",
    "iso:country":"CA",
    "sg:address":"166 Disco Rd",
    "sg:city":"Etobicoke",
    "sg:classifiers":[
        {
            "category":"Professional",
            "subcategory":"Engineering",
            "type":"Services"
        }
    ],
    "sg:phone":"+1 416 798 2126",
    "sg:postcode":"M9W 1M4",
    "sg:province":"ON",
    "sg:tags":[
        "engineer"
    ],
    "wof:name":"Bsg Engineering Ltd",
    "wof:placetype":"venue"
},
  "geometry": {"coordinates":[-79.608009,43.701107],"type":"Point"}
}