{
  "type": "Feature",
  "properties": {
    "iso:country":"CA",
    "sg:address":"2405 Rebecca St",
    "sg:city":"Oakville",
    "sg:classifiers":[
        {
            "category":"Education",
            "subcategory":"School",
            "type":"Public Place"
        }
    ],
    "sg:phone":"+1 905 827 4401",
    "sg:postcode":"L6L 2B1",
    "sg:province":"ON",
    "wof:name":"St Dominic's School",
    "wof:placetype":"venue"
},
  "geometry": {"coordinates":[-79.7182998657,43.3996620178],"type":"Point"}
}