{
  "type": "Feature",
  "properties": {
    "addr:full":"41 Algoma St Wawa ON P0S 1K0",
    "addr:housenumber":"41",
    "addr:postcode":"p0s 1k0",
    "addr:street":"Algoma St",
    "iso:country":"CA",
    "sg:address":"41 Algoma St",
    "sg:city":"Wawa",
    "sg:classifiers":[
        {
            "category":"Social Services",
            "subcategory":"Child Care",
            "type":"Services"
        }
    ],
    "sg:phone":"+1 705 856 2178",
    "sg:postcode":"P0S 1K0",
    "sg:province":"ON",
    "wof:name":"Superior Children's Ctr",
    "wof:placetype":"venue"
},
  "geometry": {"coordinates":[-84.773956,47.999378],"type":"Point"}
}