{
  "type": "Feature",
  "properties": {
    "addr:full":"14108 Hwy 7 Lake Charlotte NS B0J 1Y0",
    "addr:housenumber":"14108",
    "addr:postcode":"b0j 1y0",
    "addr:street":"Hwy 7",
    "iso:country":"CA",
    "sg:address":"14108 Hwy 7",
    "sg:city":"Lake Charlotte",
    "sg:classifiers":[
        {
            "category":"Farming",
            "subcategory":"Aquatic Farm",
            "type":"Manufacturing & Wholesale Goods"
        }
    ],
    "sg:phone":"+1 902 845 2993",
    "sg:postcode":"B0J 1Y0",
    "sg:province":"NS",
    "sg:tags":[
        "seafood",
        "aquaculture"
    ],
    "wof:name":"Aquaprime Musssel Ranch",
    "wof:placetype":"venue"
},
  "geometry": {"coordinates":[-62.9231,44.769169],"type":"Point"}
}