{
  "type": "Feature",
  "properties": {
    "addr:full":"2578 Marsdale Dr Peterborough ON K9L 1R4",
    "addr:housenumber":"2578",
    "addr:postcode":"k9l 1r4",
    "addr:street":"Marsdale Dr",
    "iso:country":"CA",
    "sg:address":"2578 Marsdale Dr",
    "sg:city":"Peterborough",
    "sg:classifiers":[
        {
            "category":"Organizations",
            "subcategory":"Religious Organization",
            "type":"Services"
        }
    ],
    "sg:phone":"+1 705 745 7877",
    "sg:postcode":"K9L 1R4",
    "sg:province":"ON",
    "wof:name":"Ora Intl",
    "wof:placetype":"venue"
},
  "geometry": {"coordinates":[-78.2955627441,44.2969818115],"type":"Point"}
}