{
  "type": "Feature",
  "properties": {
    "addr:full":"Granby QC J2G 9A7",
    "addr:postcode":"j2g 9a7",
    "iso:country":"CA",
    "sg:city":"Granby",
    "sg:classifiers":[
        {
            "category":"Professional",
            "subcategory":"Employment Agencies",
            "type":"Services"
        }
    ],
    "sg:phone":"+1 450 378 6371",
    "sg:postcode":"J2G 9A7",
    "sg:province":"QC",
    "sg:tags":[
        "opportunity"
    ],
    "wof:name":"Kelly Services",
    "wof:placetype":"venue"
},
  "geometry": {"coordinates":[-72.727104,45.397991],"type":"Point"}
}