{
  "type": "Feature",
  "properties": {
    "iso:country":"CA",
    "sg:address":"156 Malabar Dr",
    "sg:city":"Sault Ste Marie",
    "sg:classifiers":[
        {
            "category":"Building & Trades",
            "subcategory":"Construction",
            "type":"Services"
        }
    ],
    "sg:phone":"+1 705 254 3743",
    "sg:postcode":"P6B 4A7",
    "sg:province":"ON",
    "sg:tags":[
        "excavating",
        "contractor"
    ],
    "wof:name":"E L Baxter Backhoe",
    "wof:placetype":"venue"
},
  "geometry": {"coordinates":[-84.31177520750001,46.5306854248],"type":"Point"}
}