{
  "type": "Feature",
  "properties": {
    "iso:country":"CA",
    "sg:address":"860 Rue Saint-Desire",
    "sg:city":"Black Lake",
    "sg:classifiers":[
        {
            "category":"Bars & Pubs",
            "type":"Food & Drink"
        }
    ],
    "sg:phone":"+1 418 423 9062",
    "sg:postcode":"G6H 1M5",
    "sg:province":"QC",
    "sg:tags":[
        "lounge",
        "cocktail"
    ],
    "wof:name":"Bar Le Hazard",
    "wof:placetype":"venue"
},
  "geometry": {"coordinates":[-71.36900300000001,46.048088],"type":"Point"}
}