{
  "type": "Feature",
  "properties": {
    "addr:full":"155 Rue Principale Frampton QC G0R 1M0",
    "addr:housenumber":"155",
    "addr:postcode":"g0r 1m0",
    "addr:street":"Rue Principale",
    "iso:country":"CA",
    "sg:address":"155 Rue Principale",
    "sg:city":"Frampton",
    "sg:classifiers":[
        {
            "category":"Restaurant",
            "type":"Food & Drink"
        }
    ],
    "sg:phone":"+1 418 479 5229",
    "sg:postcode":"G0R 1M0",
    "sg:province":"QC",
    "wof:name":"Casse-Croute Gaston Perreault",
    "wof:placetype":"venue"
},
  "geometry": {"coordinates":[-70.808273,46.461922],"type":"Point"}
}