{
  "type": "Feature",
  "properties": {
    "addr:full":"66 Rue Du Marche Salaberry-DE-Valleyfield QC J6T 1P5",
    "addr:housenumber":"66",
    "addr:postcode":"j6t 1p5",
    "addr:street":"Rue Du Marche",
    "iso:country":"CA",
    "sg:address":"66 Rue Du Marche",
    "sg:city":"Salaberry-DE-Valleyfield",
    "sg:classifiers":[
        {
            "category":"Organizations",
            "subcategory":"Professional Association",
            "type":"Services"
        }
    ],
    "sg:phone":"+1 450 370 0824",
    "sg:postcode":"J6T 1P5",
    "sg:province":"QC",
    "wof:name":"Salles Des Zouaves",
    "wof:placetype":"venue"
},
  "geometry": {"coordinates":[-74.134743,45.25415],"type":"Point"}
}