{
  "type": "Feature",
  "properties": {
    "addr:full":"105 Railway Ave W Shellbrook SK S0J 2E0",
    "addr:housenumber":"105",
    "addr:postcode":"s0j 2e0",
    "addr:street":"Railway Ave W Shellbrook",
    "iso:country":"CA",
    "sg:address":"105 Railway Ave W",
    "sg:city":"Shellbrook",
    "sg:classifiers":[
        {
            "category":"Food & Beverages",
            "subcategory":"Liquor & Beverages",
            "type":"Retail Goods"
        }
    ],
    "sg:phone":"+1 306 747 4258",
    "sg:postcode":"S0J 2E0",
    "sg:province":"SK",
    "sg:tags":[
        "store"
    ],
    "wof:name":"Saskatchewan Liquor Stores",
    "wof:placetype":"venue"
},
  "geometry": {"coordinates":[-106.384468,53.218632],"type":"Point"}
}