{
  "type": "Feature",
  "properties": {
    "addr:full":"10912 96 St Fort St John BC V1J 3R7",
    "addr:housenumber":"10912",
    "addr:postcode":"v1j 3r7",
    "addr:street":"96 St",
    "iso:country":"CA",
    "sg:address":"10912 96 St",
    "sg:city":"Fort St John",
    "sg:classifiers":[
        {
            "category":"Building & Trades",
            "subcategory":"Electrical",
            "type":"Services"
        }
    ],
    "sg:phone":"+1 250 787 9770",
    "sg:postcode":"V1J 3R7",
    "sg:province":"BC",
    "sg:tags":[
        "electric",
        "contractor"
    ],
    "wof:name":"Achron Electric Ltd",
    "wof:placetype":"venue"
},
  "geometry": {"coordinates":[-120.84026299999999,56.254635],"type":"Point"}
}