{
  "type": "Feature",
  "properties": {
    "addr:full":"Dugald MB R0E 0K0",
    "addr:postcode":"r0e 0k0",
    "iso:country":"CA",
    "sg:city":"Dugald",
    "sg:classifiers":[
        {
            "category":"Autos & Motor Vehicles",
            "subcategory":"Automobile Sales",
            "type":"Retail Goods"
        }
    ],
    "sg:phone":"+1 204 222 1612",
    "sg:postcode":"R0E 0K0",
    "sg:province":"MB",
    "sg:tags":[
        "truck"
    ],
    "wof:name":"F & L Enterprises Truck Ctr",
    "wof:placetype":"venue"
},
  "geometry": {"coordinates":[-96.8401184082,49.8859062195],"type":"Point"}
}