{
  "type": "Feature",
  "properties": {
    "iso:country":"CA",
    "sg:address":"426 Van Horne St S",
    "sg:city":"Cranbrook",
    "sg:classifiers":[
        {
            "category":"Wholesale",
            "subcategory":"Machinery & Supplies",
            "type":"Manufacturing & Wholesale Goods"
        }
    ],
    "sg:phone":"+1 250 426 6628",
    "sg:postcode":"V1C 4W7",
    "sg:province":"BC",
    "sg:tags":[
        "engine"
    ],
    "wof:name":"Kootenay Fuel Injection Inc",
    "wof:placetype":"venue"
},
  "geometry": {"coordinates":[-115.784996033,49.5049667358],"type":"Point"}
}