{
  "type": "Feature",
  "properties": {
    "addr:full":"194 Wyse Rd Dartmouth NS B3A 1M9",
    "addr:housenumber":"194",
    "addr:postcode":"b3a 1m9",
    "addr:street":"Wyse Rd",
    "iso:country":"CA",
    "sg:address":"194 Wyse Rd",
    "sg:city":"Dartmouth",
    "sg:classifiers":[
        {
            "category":"Retail",
            "subcategory":"Animal Services",
            "type":"Services"
        }
    ],
    "sg:phone":"+1 902 463 6668",
    "sg:postcode":"B3A 1M9",
    "sg:province":"NS",
    "sg:tags":[
        "pet",
        "boarding",
        "sitting"
    ],
    "wof:name":"Petsmart Boarding Kennels",
    "wof:placetype":"venue"
},
  "geometry": {"coordinates":[-63.582851,44.673294],"type":"Point"}
}