{
  "type": "Feature",
  "properties": {
    "addr:full":"London ON N5V 3Z1",
    "addr:postcode":"n5v 3z1",
    "iso:country":"CA",
    "sg:city":"London",
    "sg:classifiers":[
        {
            "category":"Professional",
            "subcategory":"Accounting & Tax Preparation",
            "type":"Services"
        }
    ],
    "sg:phone":"+1 519 453 6025",
    "sg:postcode":"N5V 3Z1",
    "sg:province":"ON",
    "sg:tags":[
        "return",
        "filing"
    ],
    "wof:name":"H & R Block Canada Inc",
    "wof:placetype":"venue"
},
  "geometry": {"coordinates":[-81.1702880859,43.006439209],"type":"Point"}
}