{
  "type": "Feature",
  "properties": {
    "addr:full":"13985 Ilderton Rd Ilderton ON N0M 2A0",
    "addr:housenumber":"13985",
    "addr:postcode":"n0m 2a0",
    "addr:street":"Ilderton Rd",
    "iso:country":"CA",
    "sg:address":"13985 Ilderton Rd",
    "sg:city":"Ilderton",
    "sg:classifiers":[
        {
            "category":"Retail",
            "subcategory":"Veterinary Services",
            "type":"Services"
        }
    ],
    "sg:phone":"+1 519 666 0911",
    "sg:postcode":"N0M 2A0",
    "sg:province":"ON",
    "sg:tags":[
        "veterinarian"
    ],
    "wof:name":"Ilderton Equine Svc",
    "wof:placetype":"venue"
},
  "geometry": {"coordinates":[-81.3375015259,43.091884613],"type":"Point"}
}