{
  "type": "Feature",
  "properties": {
    "addr:full":"5730 Boul Pie-Ix Montreal QC H1X 2B9",
    "addr:housenumber":"5730",
    "addr:postcode":"h1x 2b9",
    "addr:street":"Boul Pie-Ix",
    "iso:country":"CA",
    "sg:address":"5730 Boul Pie-Ix",
    "sg:city":"Montreal",
    "sg:classifiers":[
        {
            "category":"Organizations",
            "subcategory":"Professional Association",
            "type":"Services"
        }
    ],
    "sg:phone":"+1 514 727 8483",
    "sg:postcode":"H1X 2B9",
    "sg:province":"QC",
    "wof:name":"Ordre Franciscain Seculier",
    "wof:placetype":"venue"
},
  "geometry": {"coordinates":[-73.572945,45.560295],"type":"Point"}
}