{
  "type": "Feature",
  "properties": {
    "addr:full":"197 May Ave Richmond Hill ON L4C 3S8",
    "addr:housenumber":"197",
    "addr:postcode":"l4c 3s8",
    "addr:street":"May Ave",
    "iso:country":"CA",
    "sg:address":"197 May Ave",
    "sg:city":"Richmond Hill",
    "sg:classifiers":[
        {
            "category":"Building & Trades",
            "subcategory":"Cleaning & Sanitation",
            "type":"Services"
        }
    ],
    "sg:phone":"+1 905 669 9127",
    "sg:postcode":"L4C 3S8",
    "sg:province":"ON",
    "sg:tags":[
        "removal",
        "snow",
        "landscape",
        "contractor"
    ],
    "wof:name":"B & L Mettel Ltd",
    "wof:placetype":"venue"
},
  "geometry": {"coordinates":[-79.449532,43.861725],"type":"Point"}
}