{
  "type": "Feature",
  "properties": {
    "addr:full":"2040 34 Ave SW Calgary AB T2T 2C3",
    "addr:housenumber":"2040",
    "addr:postcode":"t2t 2c3",
    "addr:street":"34 Ave Sw",
    "iso:country":"CA",
    "sg:address":"2040 34 Ave SW",
    "sg:city":"Calgary",
    "sg:classifiers":[
        {
            "category":"Food & Beverages",
            "subcategory":"Specialty",
            "type":"Retail Goods"
        }
    ],
    "sg:phone":"+1 403 242 6688",
    "sg:postcode":"T2T 2C3",
    "sg:province":"AB",
    "sg:tags":[
        "health",
        "diet"
    ],
    "wof:name":"Naturezone Vitamins & Therapy",
    "wof:placetype":"venue"
},
  "geometry": {"coordinates":[-114.108047485,51.0232887268],"type":"Point"}
}