{
  "type": "Feature",
  "properties": {
    "addr:full":"Prince George BC V2L 3G7",
    "addr:postcode":"v2l 3g7",
    "iso:country":"CA",
    "sg:city":"Prince George",
    "sg:classifiers":[
        {
            "category":"Insurance",
            "subcategory":"Hazard Insurance",
            "type":"Services"
        }
    ],
    "sg:phone":"+1 250 563 8223",
    "sg:postcode":"V2L 3G7",
    "sg:province":"BC",
    "sg:tags":[
        "profit",
        "sharing",
        "pension",
        "plan"
    ],
    "wof:name":"Benefits North Group Conslnts",
    "wof:placetype":"venue"
},
  "geometry": {"coordinates":[-122.753159,53.918907],"type":"Point"}
}