{
  "type": "Feature",
  "properties": {
    "addr:full":"3650 Albert St Halifax NS B3K 3N8",
    "addr:housenumber":"3650",
    "addr:postcode":"b3k 3n8",
    "addr:street":"Albert St",
    "iso:country":"CA",
    "sg:address":"3650 Albert St",
    "sg:city":"Halifax",
    "sg:classifiers":[
        {
            "category":"Building & Trades",
            "subcategory":"Construction",
            "type":"Services"
        }
    ],
    "sg:phone":"+1 902 431 9333",
    "sg:postcode":"B3K 3N8",
    "sg:province":"NS",
    "sg:tags":[
        "wallpaper",
        "dry wall",
        "contractor"
    ],
    "wof:name":"Allstar Drywall & Painting",
    "wof:placetype":"venue"
},
  "geometry": {"coordinates":[-63.6069488525,44.6711044312],"type":"Point"}
}