{
  "type": "Feature",
  "properties": {
    "addr:full":"2660 Trout Lake Rd North Bay ON P1B 7S7",
    "addr:housenumber":"2660",
    "addr:postcode":"p1b 7s7",
    "addr:street":"Trout Lake Rd",
    "iso:country":"CA",
    "sg:address":"2660 Trout Lake Rd",
    "sg:city":"North Bay",
    "sg:classifiers":[
        {
            "category":"Autos & Motor Vehicles",
            "subcategory":"Fuel & Gas Station",
            "type":"Retail Goods"
        }
    ],
    "sg:phone":"+1 705 476 7479",
    "sg:postcode":"P1B 7S7",
    "sg:province":"ON",
    "sg:tags":[
        "oil"
    ],
    "wof:name":"Mr Gas",
    "wof:placetype":"venue"
},
  "geometry": {"coordinates":[-79.429649,46.324097],"type":"Point"}
}