{
  "type": "Feature",
  "properties": {
    "iso:country":"CA",
    "sg:address":"244411 Airport Rd",
    "sg:city":"Tillsonburg",
    "sg:classifiers":[
        {
            "category":"Airport",
            "type":"Transportation"
        }
    ],
    "sg:phone":"+1 519 842 2929",
    "sg:postcode":"N4G 4H1",
    "sg:province":"ON",
    "wof:name":"Tillsonburg Regional Airport",
    "wof:placetype":"venue"
},
  "geometry": {"coordinates":[-80.7278671265,42.8606758118],"type":"Point"}
}