{
  "type": "Feature",
  "properties": {
    "addr:full":"Route 13 Hunter River PE C0A 1N0",
    "addr:postcode":"c0a 1n0",
    "addr:street":"Route 13",
    "iso:country":"CA",
    "sg:address":"Route 13",
    "sg:city":"Hunter River",
    "sg:classifiers":[
        {
            "category":"Travel",
            "subcategory":"Hotels & Motels",
            "type":"Entertainment"
        }
    ],
    "sg:phone":"+1 902 963 2380",
    "sg:postcode":"C0A 1N0",
    "sg:province":"PE",
    "sg:tags":[
        "campground"
    ],
    "wof:name":"Marco Polo Land",
    "wof:placetype":"venue"
},
  "geometry": {"coordinates":[-63.348316,46.357162],"type":"Point"}
}