{
  "type": "Feature",
  "properties": {
    "addr:full":"2704 Clarke St Port Moody BC V3H 1Z1",
    "addr:housenumber":"2704",
    "addr:postcode":"v3h 1z1",
    "addr:street":"Clarke St",
    "iso:country":"CA",
    "sg:address":"2704 Clarke St",
    "sg:city":"Port Moody",
    "sg:classifiers":[
        {
            "category":"Retail",
            "subcategory":"Animal Services",
            "type":"Services"
        }
    ],
    "sg:phone":"+1 604 936 6662",
    "sg:postcode":"V3H 1Z1",
    "sg:province":"BC",
    "sg:tags":[
        "pet",
        "grooming",
        "washing"
    ],
    "wof:name":"K9 Social Club Inc",
    "wof:placetype":"venue"
},
  "geometry": {"coordinates":[-122.852226,49.277905],"type":"Point"}
}