{
  "type": "Feature",
  "properties": {
    "addr:full":"636 Keefer St Vancouver BC V6A 1Y4",
    "addr:housenumber":"636",
    "addr:postcode":"v6a 1y4",
    "addr:street":"Keefer St",
    "iso:country":"CA",
    "sg:address":"636 Keefer St",
    "sg:city":"Vancouver",
    "sg:classifiers":[
        {
            "category":"Organizations",
            "subcategory":"Religious Organization",
            "type":"Services"
        }
    ],
    "sg:phone":"+1 604 251 7855",
    "sg:postcode":"V6A 1Y4",
    "sg:province":"BC",
    "sg:tags":[
        "church"
    ],
    "wof:name":"Vietnamese Alliance Church",
    "wof:placetype":"venue"
},
  "geometry": {"coordinates":[-123.09073600000001,49.279163],"type":"Point"}
}