{
  "type": "Feature",
  "properties": {
    "addr:full":"331 Strood Ave Winnipeg MB R2G 1A9",
    "addr:housenumber":"331",
    "addr:postcode":"r2g 1a9",
    "addr:street":"Strood Ave",
    "iso:country":"CA",
    "sg:address":"331 Strood Ave",
    "sg:city":"Winnipeg",
    "sg:classifiers":[
        {
            "category":"Manufacturing",
            "subcategory":"Paper Products",
            "type":"Manufacturing & Wholesale Goods"
        }
    ],
    "sg:phone":"+1 204 669 0331",
    "sg:postcode":"R2G 1A9",
    "sg:province":"MB",
    "sg:tags":[
        "bag"
    ],
    "wof:name":"A-Paks Bagging & Packaging CO",
    "wof:placetype":"venue"
},
  "geometry": {"coordinates":[-97.06536865229999,49.9529190063],"type":"Point"}
}