{
  "type": "Feature",
  "properties": {
    "addr:full":"472 Locust St Burlington ON L7S 1V1",
    "addr:housenumber":"472",
    "addr:postcode":"l7s 1v1",
    "addr:street":"Locust St",
    "iso:country":"CA",
    "sg:address":"472 Locust St",
    "sg:city":"Burlington",
    "sg:classifiers":[
        {
            "category":"Organizations",
            "subcategory":"Religious Organization",
            "type":"Services"
        }
    ],
    "sg:phone":"+1 905 634 1743",
    "sg:postcode":"L7S 1V1",
    "sg:province":"ON",
    "sg:tags":[
        "church"
    ],
    "wof:name":"Paroisse St Philippe",
    "wof:placetype":"venue"
},
  "geometry": {"coordinates":[-79.79950700000001,43.325371],"type":"Point"}
}