{
  "type": "Feature",
  "properties": {
    "addr:full":"740 Century St Winnipeg MB R3H 0M1",
    "addr:housenumber":"740",
    "addr:postcode":"r3h 0m1",
    "addr:street":"Century St",
    "iso:country":"CA",
    "sg:address":"740 Century St",
    "sg:city":"Winnipeg",
    "sg:classifiers":[
        {
            "category":"Manufacturing",
            "subcategory":"Signs",
            "type":"Manufacturing & Wholesale Goods"
        }
    ],
    "sg:phone":"+1 204 475 8844",
    "sg:postcode":"R3H 0M1",
    "sg:province":"MB",
    "wof:name":"Signcraft Display Ltd",
    "wof:placetype":"venue"
},
  "geometry": {"coordinates":[-97.20291900629999,49.8993644714],"type":"Point"}
}