{
  "type": "Feature",
  "properties": {
    "addr:full":"Beauport QC G1C 1B5",
    "addr:postcode":"qc g1c 1b5",
    "iso:country":"CA",
    "sg:city":"Beauport",
    "sg:classifiers":[
        {
            "category":"Wholesale",
            "subcategory":"Meat",
            "type":"Manufacturing & Wholesale Goods"
        }
    ],
    "sg:phone":"+1 418 661 2241",
    "sg:postcode":"G1C 1B5",
    "sg:province":"QC",
    "sg:tags":[
        "butchering"
    ],
    "wof:name":"Boucherie Serge Beaulieu Inc",
    "wof:placetype":"venue"
},
  "geometry": {"coordinates":[-71.1931381226,46.8592414856],"type":"Point"}
}