{
  "type": "Feature",
  "properties": {
    "addr:full":"Saint-Damien-DE-Buckland QC G0R 2Y0",
    "addr:postcode":"g0r 2y0",
    "iso:country":"CA",
    "sg:city":"Saint-Damien-DE-Buckland",
    "sg:classifiers":[
        {
            "category":"Wholesale",
            "subcategory":"Auto Parts",
            "type":"Manufacturing & Wholesale Goods"
        }
    ],
    "sg:phone":"+1 418 789 3069",
    "sg:postcode":"G0R 2Y0",
    "sg:province":"QC",
    "sg:tags":[
        "equipment",
        "truck"
    ],
    "wof:name":"Machinerie R Bissonnette Enr",
    "wof:placetype":"venue"
},
  "geometry": {"coordinates":[-70.67156199999999,46.61853],"type":"Point"}
}