{
  "type": "Feature",
  "properties": {
    "addr:full":"PO Box 149 Bonanza AB T0H 0K0",
    "addr:housenumber":"po;149",
    "addr:postcode":"bonanza ab t0h 0k0",
    "addr:street":"Box",
    "iso:country":"CA",
    "sg:address":"PO Box 149",
    "sg:city":"Bonanza",
    "sg:classifiers":[
        {
            "category":"Organizations",
            "subcategory":"Religious Organization",
            "type":"Services"
        }
    ],
    "sg:phone":"+1 780 353 2710",
    "sg:postcode":"T0H 0K0",
    "sg:province":"AB",
    "sg:tags":[
        "church"
    ],
    "wof:name":"Bonanza Gospel Chapel",
    "wof:placetype":"venue"
},
  "geometry": {"coordinates":[-119.814323425,55.9271316528],"type":"Point"}
}