{
  "type": "Feature",
  "properties": {
    "addr:full":"1600 Rue DE Drucourt Montreal QC H2G 1N6",
    "addr:housenumber":"1600",
    "addr:postcode":"h2g 1n6",
    "addr:street":"Rue De Drucourt",
    "iso:country":"CA",
    "sg:address":"1600 Rue DE Drucourt",
    "sg:city":"Montreal",
    "sg:classifiers":[
        {
            "category":"Government",
            "subcategory":"Office",
            "type":"Public Place"
        }
    ],
    "sg:phone":"+1 514 872 8705",
    "sg:postcode":"H2G 1N6",
    "sg:province":"QC",
    "sg:tags":[
        "village"
    ],
    "wof:name":"Montreal Centres DE Sports",
    "wof:placetype":"venue"
},
  "geometry": {"coordinates":[-73.59594,45.541195],"type":"Point"}
}