{
  "type": "Feature",
  "properties": {
    "addr:full":"Mcgowan Gogama ON P0M 1W0",
    "addr:postcode":"p0m 1w0",
    "iso:country":"CA",
    "sg:address":"Mcgowan",
    "sg:city":"Gogama",
    "sg:classifiers":[
        {
            "category":"Government",
            "subcategory":"Office",
            "type":"Public Place"
        }
    ],
    "sg:phone":"+1 705 894 2000",
    "sg:postcode":"P0M 1W0",
    "sg:province":"ON",
    "wof:name":"Ontario Richesses Naturelles",
    "wof:placetype":"venue"
},
  "geometry": {"coordinates":[-81.720985,47.674473],"type":"Point"}
}