{
  "type": "Feature",
  "properties": {
    "addr:full":"10 Mill W Tilbury ON N0P 2L0",
    "addr:housenumber":"10",
    "addr:postcode":"n0p 2l0",
    "addr:street":"Mill W",
    "iso:country":"CA",
    "sg:address":"10 Mill W",
    "sg:city":"Tilbury",
    "sg:classifiers":[
        {
            "category":"Personal",
            "subcategory":"Tanning Parlor",
            "type":"Services"
        }
    ],
    "sg:phone":"+1 519 682 0049",
    "sg:postcode":"N0P 2L0",
    "sg:province":"ON",
    "sg:tags":[
        "salon"
    ],
    "wof:name":"Tan Your Hide",
    "wof:placetype":"venue"
},
  "geometry": {"coordinates":[-82.43398999999999,42.263493],"type":"Point"}
}