{
  "type": "Feature",
  "properties": {
    "addr:full":"78 Montee Lafontaine Montpellier QC J0V 1M0",
    "addr:housenumber":"78",
    "addr:postcode":"j0v 1m0",
    "addr:street":"Montee Lafontaine",
    "iso:country":"CA",
    "sg:address":"78 Montee Lafontaine",
    "sg:city":"Montpellier",
    "sg:classifiers":[
        {
            "category":"Travel",
            "subcategory":"Campground",
            "type":"Entertainment"
        }
    ],
    "sg:phone":"+1 819 428 2247",
    "sg:postcode":"J0V 1M0",
    "sg:province":"QC",
    "wof:name":"Camping Du Lac Schryer",
    "wof:placetype":"venue"
},
  "geometry": {"coordinates":[-75.203636,45.851051],"type":"Point"}
}