{
  "type": "Feature",
  "properties": {
    "addr:full":"79 Tremaine Rd Milton ON L9T 2W8",
    "addr:housenumber":"79",
    "addr:postcode":"l9t 2w8",
    "addr:street":"Tremaine Rd",
    "iso:country":"CA",
    "sg:address":"79 Tremaine Rd",
    "sg:city":"Milton",
    "sg:classifiers":[
        {
            "category":"Utilities",
            "subcategory":"Refuse",
            "type":"Services"
        }
    ],
    "sg:phone":"+1 905 875 2455",
    "sg:postcode":"L9T 2W8",
    "sg:province":"ON",
    "sg:tags":[
        "garbage",
        "collection"
    ],
    "wof:name":"A W Svc",
    "wof:placetype":"venue"
},
  "geometry": {"coordinates":[-79.9228515625,43.513053894],"type":"Point"}
}