{
  "type": "Feature",
  "properties": {
    "addr:full":"89 Boul DE Bromont Bromont QC J2L 2K5",
    "addr:housenumber":"89",
    "addr:postcode":"j2l 2k5",
    "addr:street":"Boul De Bromont",
    "iso:country":"CA",
    "sg:address":"89 Boul DE Bromont",
    "sg:city":"Bromont",
    "sg:classifiers":[
        {
            "category":"Real Estate",
            "subcategory":"Architect",
            "type":"Services"
        }
    ],
    "sg:phone":"+1 450 534 1616",
    "sg:postcode":"J2L 2K5",
    "sg:province":"QC",
    "wof:name":"Atelier A Bellavance Architect",
    "wof:placetype":"venue"
},
  "geometry": {"coordinates":[-72.6469955444,45.3186683655],"type":"Point"}
}