{
  "type": "Feature",
  "properties": {
    "addr:full":"513 70 Ave SW Calgary AB T2V 0P5",
    "addr:housenumber":"513",
    "addr:postcode":"t2v 0p5",
    "addr:street":"70 Ave Sw",
    "iso:country":"CA",
    "sg:address":"513 70 Ave SW",
    "sg:city":"Calgary",
    "sg:classifiers":[
        {
            "category":"Professional",
            "subcategory":"Accounting & Tax Preparation",
            "type":"Services"
        }
    ],
    "sg:phone":"+1 403 209 5815",
    "sg:postcode":"T2V 0P5",
    "sg:province":"AB",
    "sg:tags":[
        "accountant"
    ],
    "wof:name":"Mc Kinnon, M Jane CA",
    "wof:placetype":"venue"
},
  "geometry": {"coordinates":[-114.072128296,50.9904098511],"type":"Point"}
}