{
  "type": "Feature",
  "properties": {
    "addr:full":"Scarborough ON M1T 3T6",
    "addr:postcode":"m1t 3t6",
    "iso:country":"CA",
    "sg:city":"Scarborough",
    "sg:classifiers":[
        {
            "category":"Health Services",
            "subcategory":"Doctor",
            "type":"Services"
        }
    ],
    "sg:phone":"+1 416 293 3464",
    "sg:postcode":"M1T 3T6",
    "sg:province":"ON",
    "sg:tags":[
        "dentist"
    ],
    "wof:name":"Shiozaki, Alan DDS",
    "wof:placetype":"venue"
},
  "geometry": {"coordinates":[-79.300522,43.800484],"type":"Point"}
}