{
  "type": "Feature",
  "properties": {
    "addr:full":"1551 Eagle St N Cambridge ON N3H 1E1",
    "addr:housenumber":"1551",
    "addr:postcode":"n3h 1e1",
    "addr:street":"Eagle St N",
    "iso:country":"CA",
    "sg:address":"1551 Eagle St N",
    "sg:city":"Cambridge",
    "sg:classifiers":[
        {
            "category":"Autos & Motor Vehicles",
            "subcategory":"Fuel & Gas Station",
            "type":"Retail Goods"
        }
    ],
    "sg:phone":"+1 519 653 1680",
    "sg:postcode":"N3H 1E1",
    "sg:province":"ON",
    "sg:tags":[
        "oil"
    ],
    "wof:name":"Cango Gas Bar",
    "wof:placetype":"venue"
},
  "geometry": {"coordinates":[-80.34599300000001,43.404827],"type":"Point"}
}