{
  "type": "Feature",
  "properties": {
    "addr:full":"907 Rue Mars LA Baie QC G7B 4K6",
    "addr:housenumber":"907",
    "addr:postcode":"g7b 4k6",
    "addr:street":"Rue Mars",
    "iso:country":"CA",
    "sg:address":"907 Rue Mars",
    "sg:city":"LA Baie",
    "sg:classifiers":[
        {
            "category":"Manufacturing",
            "subcategory":"Food",
            "type":"Manufacturing & Wholesale Goods"
        }
    ],
    "sg:phone":"+1 418 544 8417",
    "sg:postcode":"G7B 4K6",
    "sg:province":"QC",
    "sg:tags":[
        "shop",
        "coffee",
        "brewer"
    ],
    "wof:name":"Cafe Bistro Victoria",
    "wof:placetype":"venue"
},
  "geometry": {"coordinates":[-70.8808517456,48.3445472717],"type":"Point"}
}