{
  "type": "Feature",
  "properties": {
    "iso:country":"CA",
    "sg:address":"167 10th St W",
    "sg:city":"Owen Sound",
    "sg:classifiers":[
        {
            "category":"Professional",
            "subcategory":"Lawyer & Legal Services",
            "type":"Services"
        }
    ],
    "sg:phone":"+1 519 376 6700",
    "sg:postcode":"N4K 3R1",
    "sg:province":"ON",
    "sg:tags":[
        "attorney"
    ],
    "wof:name":"Lendon, Harold A",
    "wof:placetype":"venue"
},
  "geometry": {"coordinates":[-80.9457702637,44.5672950745],"type":"Point"}
}