{
  "type": "Feature",
  "properties": {
    "iso:country":"CA",
    "sg:city":"Kingston",
    "sg:classifiers":[
        {
            "category":"Professional",
            "subcategory":"Business Services",
            "type":"Services"
        }
    ],
    "sg:phone":"+1 613 544 2024",
    "sg:postcode":"K7K 6C3",
    "sg:province":"ON",
    "sg:tags":[
        "water",
        "treatment"
    ],
    "wof:name":"Mac Donald & Sons Ltd",
    "wof:placetype":"venue"
},
  "geometry": {"coordinates":[-76.5091705322,44.2678565979],"type":"Point"}
}