{
  "type": "Feature",
  "properties": {
    "iso:country":"CA",
    "sg:address":"5148 Still Creek Ave",
    "sg:city":"Burnaby",
    "sg:classifiers":[
        {
            "category":"Wholesale",
            "subcategory":"Machinery & Supplies",
            "type":"Manufacturing & Wholesale Goods"
        }
    ],
    "sg:phone":"+1 604 291 7676",
    "sg:postcode":"V5C 4E4",
    "sg:province":"BC",
    "sg:tags":[
        "director",
        "funeral"
    ],
    "wof:name":"Classic Caskets Distributors",
    "wof:placetype":"venue"
},
  "geometry": {"coordinates":[-122.98941803,49.2607192993],"type":"Point"}
}