{
  "type": "Feature",
  "properties": {
    "addr:full":"Ham-Nord QC G0P 1A0",
    "addr:postcode":"g0p 1a0",
    "iso:country":"CA",
    "sg:city":"Ham-Nord",
    "sg:classifiers":[
        {
            "category":"Manufacturing",
            "subcategory":"Glass & Minerals",
            "type":"Manufacturing & Wholesale Goods"
        }
    ],
    "sg:phone":"+1 819 344 2152",
    "sg:postcode":"G0P 1A0",
    "sg:province":"QC",
    "sg:tags":[
        "glassware"
    ],
    "wof:name":"Kheops Verre D'Art",
    "wof:placetype":"venue"
},
  "geometry": {"coordinates":[-71.654083,45.895519],"type":"Point"}
}