{
  "type": "Feature",
  "properties": {
    "addr:full":"Farm Grandora SK S0K 1V0",
    "addr:postcode":"s0k 1v0",
    "iso:country":"CA",
    "sg:address":"Farm",
    "sg:city":"Grandora",
    "sg:classifiers":[
        {
            "category":"Wholesale",
            "subcategory":"Poultry",
            "type":"Manufacturing & Wholesale Goods"
        }
    ],
    "sg:phone":"+1 306 329 4489",
    "sg:postcode":"S0K 1V0",
    "sg:province":"SK",
    "wof:name":"Chaudary Poultry Farm Ltd",
    "wof:placetype":"venue"
},
  "geometry": {"coordinates":[-106.979584,52.110088],"type":"Point"}
}