{
  "type": "Feature",
  "properties": {
    "addr:full":"241 Edwards Ave The Pas MB R9A 1K3",
    "addr:housenumber":"241",
    "addr:postcode":"r9a 1k3",
    "addr:street":"Edwards Ave",
    "iso:country":"CA",
    "sg:address":"241 Edwards Ave",
    "sg:city":"The Pas",
    "sg:classifiers":[
        {
            "category":"Organizations",
            "subcategory":"Professional Association",
            "type":"Services"
        }
    ],
    "sg:phone":"+1 204 627 4700",
    "sg:postcode":"R9A 1K3",
    "sg:province":"MB",
    "wof:name":"Pas Metis Assn Inc",
    "wof:placetype":"venue"
},
  "geometry": {"coordinates":[-101.251366,53.823872],"type":"Point"}
}