{
  "type": "Feature",
  "properties": {
    "addr:full":"1093 Ontario St Stratford ON N5A 6W6",
    "addr:housenumber":"1093",
    "addr:postcode":"n5a 6w6",
    "addr:street":"Ontario St",
    "iso:country":"CA",
    "sg:address":"1093 Ontario St",
    "sg:city":"Stratford",
    "sg:classifiers":[
        {
            "category":"Autos & Motor Vehicles",
            "subcategory":"Auto Supplies",
            "type":"Retail Goods"
        }
    ],
    "sg:phone":"+1 519 273 2080",
    "sg:postcode":"N5A 6W6",
    "sg:province":"ON",
    "sg:tags":[
        "repairing",
        "automobile",
        "parts"
    ],
    "wof:name":"Canadian Tire",
    "wof:placetype":"venue"
},
  "geometry": {"coordinates":[-80.943649292,43.37059021],"type":"Point"}
}