{
  "type": "Feature",
  "properties": {
    "addr:full":"PO Box 7277 STN Ancaster Ancaster ON L9G 3N6",
    "addr:housenumber":"po",
    "addr:postcode":"l9g 3n6",
    "addr:street":"Box 7277 Stn",
    "iso:country":"CA",
    "sg:address":"PO Box 7277 STN Ancaster",
    "sg:city":"Ancaster",
    "sg:classifiers":[
        {
            "category":"Building & Trades",
            "subcategory":"Construction",
            "type":"Services"
        }
    ],
    "sg:phone":"+1 905 648 6422",
    "sg:postcode":"L9G 3N6",
    "sg:province":"ON",
    "sg:tags":[
        "caulking",
        "contractor"
    ],
    "wof:name":"Cob Caulking",
    "wof:placetype":"venue"
},
  "geometry": {"coordinates":[-79.97737121580001,43.2250213623],"type":"Point"}
}