{
  "type": "Feature",
  "properties": {
    "addr:full":"3720 Broadway St Richmond BC V7E 4Y8",
    "addr:housenumber":"3720",
    "addr:postcode":"v7e 4y8",
    "addr:street":"Broadway St",
    "iso:country":"CA",
    "sg:address":"3720 Broadway St",
    "sg:city":"Richmond",
    "sg:classifiers":[
        {
            "category":"Organizations",
            "subcategory":"Religious Organization",
            "type":"Services"
        }
    ],
    "sg:phone":"+1 604 277 0508",
    "sg:postcode":"V7E 4Y8",
    "sg:province":"BC",
    "sg:tags":[
        "church"
    ],
    "wof:name":"Steveston United Church",
    "wof:placetype":"venue"
},
  "geometry": {"coordinates":[-123.183815,49.127163],"type":"Point"}
}