{
  "type": "Feature",
  "properties": {
    "iso:country":"CA",
    "sg:address":"1 Promenade Cir",
    "sg:city":"Thornhill",
    "sg:classifiers":[
        {
            "category":"Shopping",
            "subcategory":"Clothing, Apparel, & Fashions",
            "type":"Retail Goods"
        }
    ],
    "sg:phone":"+1 905 886 0103",
    "sg:postcode":"L4J 4P8",
    "sg:province":"ON",
    "sg:tags":[
        "furnishing"
    ],
    "wof:name":"Gentlemens Court",
    "wof:placetype":"venue"
},
  "geometry": {"coordinates":[-79.4529876709,43.8091545105],"type":"Point"}
}