{
  "type": "Feature",
  "properties": {
    "addr:full":"2605 Fairway Plaza Rd S Lethbridge AB T1K 6Z2",
    "addr:housenumber":"2605",
    "addr:postcode":"t1k 6z2",
    "addr:street":"Fairway Plaza Rd S",
    "iso:country":"CA",
    "sg:address":"2605 Fairway Plaza Rd S",
    "sg:city":"Lethbridge",
    "sg:classifiers":[
        {
            "category":"Food & Beverages",
            "subcategory":"Liquor & Beverages",
            "type":"Retail Goods"
        }
    ],
    "sg:phone":"+1 403 380 2614",
    "sg:postcode":"T1K 6Z2",
    "sg:province":"AB",
    "sg:tags":[
        "store"
    ],
    "wof:name":"Safeway Liquor Store",
    "wof:placetype":"venue"
},
  "geometry": {"coordinates":[-112.79498291,49.6677627563],"type":"Point"}
}