{
  "type": "Feature",
  "properties": {
    "addr:full":"4595 Av Belmore Montreal QC H4B 2C1",
    "addr:housenumber":"4595",
    "addr:postcode":"h4b 2c1",
    "addr:street":"Av Belmore",
    "iso:country":"CA",
    "sg:address":"4595 Av Belmore",
    "sg:city":"Montreal",
    "sg:classifiers":[
        {
            "category":"Food & Beverages",
            "subcategory":"Specialty",
            "type":"Retail Goods"
        }
    ],
    "sg:phone":"+1 514 481 7738",
    "sg:postcode":"H4B 2C1",
    "sg:province":"QC",
    "wof:name":"Matol A Botanical",
    "wof:placetype":"venue"
},
  "geometry": {"coordinates":[-73.64135,45.46072],"type":"Point"}
}