{
  "type": "Feature",
  "properties": {
    "iso:country":"CA",
    "sg:city":"Richmond",
    "sg:classifiers":[
        {
            "category":"Shopping",
            "subcategory":"Shoes",
            "type":"Retail Goods"
        }
    ],
    "sg:phone":"+1 604 273 3384",
    "sg:postcode":"V6Y 2V7",
    "sg:province":"BC",
    "wof:name":"Naturalizer",
    "wof:placetype":"venue"
},
  "geometry": {"coordinates":[-123.140045,49.169788],"type":"Point"}
}