{
  "type": "Feature",
  "properties": {
    "addr:full":"1451 Road 2 W Kingsville ON N9Y 2E4",
    "addr:housenumber":"1451",
    "addr:postcode":"n9y 2e4",
    "addr:street":"Road 2 W",
    "iso:country":"CA",
    "sg:address":"1451 Road 2 W",
    "sg:city":"Kingsville",
    "sg:classifiers":[
        {
            "category":"Building & Trades",
            "subcategory":"Electrical",
            "type":"Services"
        }
    ],
    "sg:phone":"+1 519 733 5325",
    "sg:postcode":"N9Y 2E4",
    "sg:province":"ON",
    "sg:tags":[
        "electric",
        "contractor"
    ],
    "wof:name":"Sun Electric",
    "wof:placetype":"venue"
},
  "geometry": {"coordinates":[-82.802261,42.05471],"type":"Point"}
}