{
  "type": "Feature",
  "properties": {
    "addr:full":"1141 Mainland St Vancouver BC V6B 5P2",
    "addr:housenumber":"1141",
    "addr:postcode":"bc v6b 5p2",
    "addr:street":"Mainland St",
    "iso:country":"CA",
    "sg:address":"1141 Mainland St",
    "sg:city":"Vancouver",
    "sg:classifiers":[
        {
            "category":"Personal",
            "subcategory":"Beauty Salon",
            "type":"Services"
        }
    ],
    "sg:phone":"+1 604 662 7701",
    "sg:postcode":"V6B 5P2",
    "sg:province":"BC",
    "wof:name":"Bambu the Salon",
    "wof:placetype":"venue"
},
  "geometry": {"coordinates":[-123.121368408,49.2752304077],"type":"Point"}
}