{
  "type": "Feature",
  "properties": {
    "addr:full":"9561 Clearview Rd Cranbrook BC V1C 7E2",
    "addr:housenumber":"9561",
    "addr:postcode":"bc v1c 7e2",
    "addr:street":"Clearview Rd",
    "iso:country":"CA",
    "sg:address":"9561 Clearview Rd",
    "sg:city":"Cranbrook",
    "sg:classifiers":[
        {
            "category":"Building & Trades",
            "subcategory":"Construction",
            "type":"Services"
        }
    ],
    "sg:phone":"+1 250 427 7272",
    "sg:postcode":"V1C 7E2",
    "sg:province":"BC",
    "sg:tags":[
        "resurfacing",
        "refinishing",
        "floor"
    ],
    "wof:name":"Country Hardwood Floors",
    "wof:placetype":"venue"
},
  "geometry": {"coordinates":[-115.7687,49.5135],"type":"Point"}
}