{
  "type": "Feature",
  "properties": {
    "addr:full":"1368 Loyalist Rd North Wiltshire PE C0A 1Y0",
    "addr:housenumber":"1368",
    "addr:postcode":"c0a 1y0",
    "addr:street":"Loyalist Rd",
    "iso:country":"CA",
    "sg:address":"1368 Loyalist Rd",
    "sg:city":"North Wiltshire",
    "sg:classifiers":[
        {
            "category":"Education",
            "subcategory":"School",
            "type":"Public Place"
        }
    ],
    "sg:phone":"+1 902 892 3445",
    "sg:postcode":"C0A 1Y0",
    "sg:province":"PE",
    "wof:name":"Community School Pei Assn",
    "wof:placetype":"venue"
},
  "geometry": {"coordinates":[-63.3350639343,46.302066803],"type":"Point"}
}