{
  "type": "Feature",
  "properties": {
    "addr:full":"1005 Bloor St W Toronto ON M6H 1M1",
    "addr:housenumber":"1005",
    "addr:postcode":"m6h 1m1",
    "addr:street":"Bloor St W",
    "iso:country":"CA",
    "sg:address":"1005 Bloor St W",
    "sg:city":"Toronto",
    "sg:classifiers":[
        {
            "category":"Restaurant",
            "type":"Food & Drink"
        }
    ],
    "sg:phone":"+1 416 531 1625",
    "sg:postcode":"M6H 1M1",
    "sg:province":"ON",
    "wof:name":"Toronto Swing Restaurant",
    "wof:placetype":"venue"
},
  "geometry": {"coordinates":[-79.430481,43.660824],"type":"Point"}
}