{
  "type": "Feature",
  "properties": {
    "addr:full":"280 Stradbrook Ave # 2 Winnipeg MB R3L 0J6",
    "addr:housenumber":"280",
    "addr:postcode":"r3l 0j6",
    "addr:street":"Stradbrook Ave # 2",
    "iso:country":"CA",
    "sg:address":"280 Stradbrook Ave # 2",
    "sg:city":"Winnipeg",
    "sg:classifiers":[
        {
            "category":"Professional",
            "subcategory":"Lawyer & Legal Services",
            "type":"Services"
        }
    ],
    "sg:phone":"+1 204 989 2775",
    "sg:postcode":"R3L 0J6",
    "sg:province":"MB",
    "sg:tags":[
        "attorney"
    ],
    "wof:name":"Richert, Dean",
    "wof:placetype":"venue"
},
  "geometry": {"coordinates":[-97.1380996704,49.879863739],"type":"Point"}
}