{
  "type": "Feature",
  "properties": {
    "iso:country":"CA",
    "sg:address":"18025 Yonge St",
    "sg:city":"Newmarket",
    "sg:classifiers":[
        {
            "category":"Personal",
            "subcategory":"Beauty Salon",
            "type":"Services"
        }
    ],
    "sg:phone":"+1 905 836 0251",
    "sg:postcode":"L3Y 8C9",
    "sg:province":"ON",
    "sg:tags":[
        "manicuring"
    ],
    "wof:name":"Crazy Nails",
    "wof:placetype":"venue"
},
  "geometry": {"coordinates":[-79.483039856,44.0664672852],"type":"Point"}
}