{
  "type": "Feature",
  "properties": {
    "addr:full":"958 Gauvin Sainte-Madeleine QC J0H 1S0",
    "addr:housenumber":"958",
    "addr:postcode":"j0h 1s0",
    "addr:street":"Gauvin Sainte-Madeleine",
    "iso:country":"CA",
    "sg:address":"958 Gauvin",
    "sg:city":"Sainte-Madeleine",
    "sg:classifiers":[
        {
            "category":"Personal",
            "subcategory":"Beauty Salon",
            "type":"Services"
        }
    ],
    "sg:phone":"+1 450 796 1247",
    "sg:postcode":"J0H 1S0",
    "sg:province":"QC",
    "wof:name":"Esthetique A Fleur DE Peau",
    "wof:placetype":"venue"
},
  "geometry": {"coordinates":[-65.341919,49.248344],"type":"Point"}
}