{
  "type": "Feature",
  "properties": {
    "addr:full":"335 Pembina Ave E Winkler MB R6W 3N4",
    "addr:housenumber":"335",
    "addr:postcode":"r6w 3n4",
    "addr:street":"Pembina Ave E Winkler",
    "iso:country":"CA",
    "sg:address":"335 Pembina Ave E",
    "sg:city":"Winkler",
    "sg:classifiers":[
        {
            "category":"Building & Trades",
            "subcategory":"Construction",
            "type":"Services"
        }
    ],
    "sg:phone":"+1 204 325 2898",
    "sg:postcode":"R6W 3N4",
    "sg:province":"MB",
    "sg:tags":[
        "excavating",
        "contractor"
    ],
    "wof:name":"Heide H Excavating",
    "wof:placetype":"venue"
},
  "geometry": {"coordinates":[-97.925758,49.177937],"type":"Point"}
}