{
  "type": "Feature",
  "properties": {
    "addr:full":"255 Dundas St Waterdown ON L0R 2H6",
    "addr:housenumber":"255",
    "addr:postcode":"l0r 2h6",
    "addr:street":"Dundas St",
    "iso:country":"CA",
    "sg:address":"255 Dundas St",
    "sg:city":"Waterdown",
    "sg:classifiers":[
        {
            "category":"Shopping",
            "subcategory":"Clothing, Apparel, & Fashions",
            "type":"Retail Goods"
        }
    ],
    "sg:phone":"+1 905 689 0468",
    "sg:postcode":"L0R 2H6",
    "sg:province":"ON",
    "sg:tags":[
        "department",
        "store"
    ],
    "wof:name":"Saan Stores Ltd",
    "wof:placetype":"venue"
},
  "geometry": {"coordinates":[-79.89720153810001,43.3298835754],"type":"Point"}
}