{
  "type": "Feature",
  "properties": {
    "addr:full":"4880 Av Van Horne Montreal QC H3W 1J3",
    "addr:housenumber":"4880",
    "addr:postcode":"h3w 1j3",
    "addr:street":"Av Van Horne",
    "iso:country":"CA",
    "sg:address":"4880 Av Van Horne",
    "sg:city":"Montreal",
    "sg:classifiers":[
        {
            "category":"Recreation",
            "type":"Entertainment"
        }
    ],
    "sg:phone":"+1 514 342 9988",
    "sg:postcode":"H3W 1J3",
    "sg:province":"QC",
    "sg:tags":[
        "pool",
        "swimming"
    ],
    "wof:name":"Cote Des Neige Sport Ctr",
    "wof:placetype":"venue"
},
  "geometry": {"coordinates":[-73.638527,45.493088],"type":"Point"}
}