{
  "type": "Feature",
  "properties": {
    "iso:country":"CA",
    "sg:address":"216 St. Paul St",
    "sg:city":"St Catharines",
    "sg:classifiers":[
        {
            "category":"Shopping",
            "subcategory":"Used Merchandise",
            "type":"Retail Goods"
        }
    ],
    "sg:phone":"+1 905 687 4843",
    "sg:postcode":"L2R 3M2",
    "sg:province":"ON",
    "sg:tags":[
        "second",
        "pawnbroker",
        "store",
        "hand"
    ],
    "wof:name":"King of Trade",
    "wof:placetype":"venue"
},
  "geometry": {"coordinates":[-79.24350699999999,43.158085],"type":"Point"}
}