{
  "type": "Feature",
  "properties": {
    "addr:full":"12112 67 St NW Edmonton AB T5B 1M7",
    "addr:housenumber":"12112",
    "addr:postcode":"t5b 1m7",
    "addr:street":"67 St Nw",
    "iso:country":"CA",
    "sg:address":"12112 67 St NW",
    "sg:city":"Edmonton",
    "sg:classifiers":[
        {
            "category":"Shopping",
            "subcategory":"Department Store",
            "type":"Retail Goods"
        }
    ],
    "sg:phone":"+1 780 477 5852",
    "sg:postcode":"T5B 1M7",
    "sg:province":"AB",
    "sg:tags":[
        "shop",
        "liquidator"
    ],
    "wof:name":"Bucksaver Limited",
    "wof:placetype":"venue"
},
  "geometry": {"coordinates":[-113.444771,53.575462],"type":"Point"}
}