{
  "type": "Feature",
  "properties": {
    "addr:full":"3000 Rue Saint-Prosper Saint-Hyacinthe QC J2S 2A4",
    "addr:housenumber":"3000",
    "addr:postcode":"j2s 2a4",
    "addr:street":"Rue Saint-Prosper",
    "iso:country":"CA",
    "sg:address":"3000 Rue Saint-Prosper",
    "sg:city":"Saint-Hyacinthe",
    "sg:classifiers":[
        {
            "category":"Shopping",
            "type":"Retail Goods"
        }
    ],
    "sg:phone":"+1 450 773 0901",
    "sg:postcode":"J2S 2A4",
    "sg:province":"QC",
    "sg:tags":[
        "whirlpool",
        "equipment",
        "bath",
        "supply"
    ],
    "wof:name":"Alcove Ltee",
    "wof:placetype":"venue"
},
  "geometry": {"coordinates":[-72.964279,45.622814],"type":"Point"}
}