{
  "type": "Feature",
  "properties": {
    "addr:full":"4425 Manitoba Rd SE Calgary AB T2G 4B9",
    "addr:housenumber":"4425",
    "addr:postcode":"t2g 4b9",
    "addr:street":"Manitoba Rd Se",
    "iso:country":"CA",
    "sg:address":"4425 Manitoba Rd SE",
    "sg:city":"Calgary",
    "sg:classifiers":[
        {
            "category":"Wholesale",
            "subcategory":"Sporting Goods",
            "type":"Manufacturing & Wholesale Goods"
        }
    ],
    "sg:phone":"+1 403 265 5688",
    "sg:postcode":"T2G 4B9",
    "sg:province":"AB",
    "sg:tags":[
        "equipment",
        "golf",
        "supply"
    ],
    "wof:name":"Golf Iq Inc",
    "wof:placetype":"venue"
},
  "geometry": {"coordinates":[-114.055122,51.013641],"type":"Point"}
}