{
  "type": "Feature",
  "properties": {
    "addr:full":"29 Industrial Dr Hay River NT X0E 0R6",
    "addr:housenumber":"29",
    "addr:postcode":"x0e 0r6",
    "addr:street":"Industrial Dr",
    "iso:country":"CA",
    "sg:address":"29 Industrial Dr",
    "sg:city":"Hay River",
    "sg:classifiers":[
        {
            "category":"Airport",
            "type":"Transportation"
        }
    ],
    "sg:phone":"+1 867 874 6999",
    "sg:postcode":"X0E 0R6",
    "sg:province":"NT",
    "sg:tags":[
        "helicopter",
        "maintenance"
    ],
    "wof:name":"Remote Helicopters Nwt Ltd",
    "wof:placetype":"venue"
},
  "geometry": {"coordinates":[-115.792434692,60.8109931946],"type":"Point"}
}