{
  "type": "Feature",
  "properties": {
    "iso:country":"CA",
    "sg:address":"1868 Dundas St E",
    "sg:city":"Mississauga",
    "sg:classifiers":[
        {
            "category":"Wholesale",
            "subcategory":"Electrical",
            "type":"Manufacturing & Wholesale Goods"
        }
    ],
    "sg:phone":"+1 905 233 7470",
    "sg:postcode":"L4X 1L9",
    "sg:province":"ON",
    "sg:tags":[
        "burglar",
        "cleaners",
        "alarm",
        "system",
        "contractor",
        "conditioning",
        "vacuum",
        "air"
    ],
    "wof:name":"Beam & Alarm Superstore",
    "wof:placetype":"venue"
},
  "geometry": {"coordinates":[-79.5720367432,43.6200828552],"type":"Point"}
}