{
  "type": "Feature",
  "properties": {
    "addr:full":"4833 47 St SE Calgary AB T2B 3S5",
    "addr:housenumber":"4833",
    "addr:postcode":"t2b 3s5",
    "addr:street":"47 St Se",
    "iso:country":"CA",
    "sg:address":"4833 47 St SE",
    "sg:city":"Calgary",
    "sg:classifiers":[
        {
            "category":"Shopping",
            "type":"Retail Goods"
        }
    ],
    "sg:phone":"+1 403 204 2332",
    "sg:postcode":"T2B 3S5",
    "sg:province":"AB",
    "sg:tags":[
        "pet",
        "shop",
        "supply"
    ],
    "wof:name":"Petcetera",
    "wof:placetype":"venue"
},
  "geometry": {"coordinates":[-113.965858,51.011723],"type":"Point"}
}