{
  "type": "Feature",
  "properties": {
    "addr:full":"1751 Stamps Rd Duncan BC V9L 5W2",
    "addr:housenumber":"1751",
    "addr:postcode":"v9l 5w2",
    "addr:street":"Stamps Rd",
    "iso:country":"CA",
    "sg:address":"1751 Stamps Rd",
    "sg:city":"Duncan",
    "sg:classifiers":[
        {
            "category":"Manufacturing",
            "subcategory":"Food",
            "type":"Manufacturing & Wholesale Goods"
        }
    ],
    "sg:phone":"+1 250 746 7122",
    "sg:postcode":"V9L 5W2",
    "sg:province":"BC",
    "sg:tags":[
        "winery"
    ],
    "wof:name":"Alderlea Vineyards",
    "wof:placetype":"venue"
},
  "geometry": {"coordinates":[-123.70738220200001,48.779094696],"type":"Point"}
}