{
  "type": "Feature",
  "properties": {
    "addr:full":"Hwy 10 E Yorkton SK S3N 2W7",
    "addr:postcode":"s3n 2w7",
    "addr:street":"Hwy 10 E",
    "iso:country":"CA",
    "sg:address":"Hwy 10 E",
    "sg:city":"Yorkton",
    "sg:classifiers":[
        {
            "category":"Autos & Motor Vehicles",
            "subcategory":"Boat Sales",
            "type":"Retail Goods"
        }
    ],
    "sg:phone":"+1 306 783 4566",
    "sg:postcode":"S3N 2W7",
    "sg:province":"SK",
    "sg:tags":[
        "dealer"
    ],
    "wof:name":"Ochs Motor Sports",
    "wof:placetype":"venue"
},
  "geometry": {"coordinates":[-102.43949890099999,51.2102890015],"type":"Point"}
}