{
  "type": "Feature",
  "properties": {
    "addr:full":"Saint-Pascal QC G0L 3Y0",
    "addr:postcode":"g0l 3y0",
    "iso:country":"CA",
    "sg:city":"Saint-Pascal",
    "sg:classifiers":[
        {
            "category":"Manufacturing",
            "subcategory":"Printing",
            "type":"Manufacturing & Wholesale Goods"
        }
    ],
    "sg:phone":"+1 418 492 1170",
    "sg:postcode":"G0L 3Y0",
    "sg:province":"QC",
    "sg:tags":[
        "printer"
    ],
    "wof:name":"Imprimerie Pre-Texte Enr",
    "wof:placetype":"venue"
},
  "geometry": {"coordinates":[-69.8370132446,47.5078620911],"type":"Point"}
}