{
  "type": "Feature",
  "properties": {
    "addr:full":"1978 Kirschner Rd Kelowna BC V1Y 4N6",
    "addr:housenumber":"1978",
    "addr:postcode":"v1y 4n6",
    "addr:street":"Kirschner Rd",
    "iso:country":"CA",
    "sg:address":"1978 Kirschner Rd",
    "sg:city":"Kelowna",
    "sg:classifiers":[
        {
            "category":"Bars & Pubs",
            "type":"Food & Drink"
        }
    ],
    "sg:phone":"+1 250 763 5554",
    "sg:postcode":"V1Y 4N6",
    "sg:province":"BC",
    "sg:tags":[
        "cabaret"
    ],
    "wof:name":"O K Corral Cabaret",
    "wof:placetype":"venue"
},
  "geometry": {"coordinates":[-119.4584198,49.8774719238],"type":"Point"}
}