{
  "type": "Feature",
  "properties": {
    "addr:full":"2675 Bedford St Port Coquitlam BC V3C 3K7",
    "addr:housenumber":"2675",
    "addr:postcode":"v3c 3k7",
    "addr:street":"Bedford St",
    "iso:country":"CA",
    "sg:address":"2675 Bedford St",
    "sg:city":"Port Coquitlam",
    "sg:classifiers":[
        {
            "category":"Freight",
            "type":"Transportation"
        }
    ],
    "sg:phone":"+1 604 942 7511",
    "sg:postcode":"V3C 3K7",
    "sg:province":"BC",
    "sg:tags":[
        "commercial",
        "storage"
    ],
    "wof:name":"Westwood Mini Storage",
    "wof:placetype":"venue"
},
  "geometry": {"coordinates":[-122.790252685,49.264541626],"type":"Point"}
}