{
  "type": "Feature",
  "properties": {
    "addr:full":"5025 Rue Ontario E Montreal QC H1V 1M6",
    "addr:housenumber":"5025",
    "addr:postcode":"h1v 1m6",
    "addr:street":"Rue Ontario E",
    "iso:country":"CA",
    "sg:address":"5025 Rue Ontario E",
    "sg:city":"Montreal",
    "sg:classifiers":[
        {
            "category":"Home & Garden",
            "subcategory":"Home Furnishings",
            "type":"Retail Goods"
        }
    ],
    "sg:phone":"+1 514 259 3771",
    "sg:postcode":"H1V 1M6",
    "sg:province":"QC",
    "sg:tags":[
        "upholstery",
        "fabric"
    ],
    "wof:name":"Carrier Remi Inc",
    "wof:placetype":"venue"
},
  "geometry": {"coordinates":[-73.535149,45.560146],"type":"Point"}
}