{
  "type": "Feature",
  "properties": {
    "addr:full":"30 1st Ave NE Dauphin MB R7N 1A4",
    "addr:housenumber":"30",
    "addr:postcode":"r7n 1a4",
    "addr:street":"1St Ave Ne",
    "iso:country":"CA",
    "sg:address":"30 1st Ave NE",
    "sg:city":"Dauphin",
    "sg:classifiers":[
        {
            "category":"Professional",
            "subcategory":"Accounting & Tax Preparation",
            "type":"Services"
        }
    ],
    "sg:phone":"+1 204 638 0909",
    "sg:postcode":"R7N 1A4",
    "sg:province":"MB",
    "sg:tags":[
        "accountant"
    ],
    "wof:name":"Pernarowski, Marion CA",
    "wof:placetype":"venue"
},
  "geometry": {"coordinates":[-100.049126,51.149479],"type":"Point"}
}