{
  "type": "Feature",
  "properties": {
    "addr:full":"4046 96 Ave SE Calgary AB T2C 4R5",
    "addr:housenumber":"4046",
    "addr:postcode":"t2c 4r5",
    "addr:street":"96 Ave Se",
    "iso:country":"CA",
    "sg:address":"4046 96 Ave SE",
    "sg:city":"Calgary",
    "sg:classifiers":[
        {
            "category":"Freight",
            "type":"Transportation"
        }
    ],
    "sg:phone":"+1 403 503 0738",
    "sg:postcode":"T2C 4R5",
    "sg:province":"AB",
    "sg:tags":[
        "commercial",
        "storage"
    ],
    "wof:name":"Asp Alberta Storage Place",
    "wof:placetype":"venue"
},
  "geometry": {"coordinates":[-113.977318,50.967068],"type":"Point"}
}