{
  "type": "Feature",
  "properties": {
    "iso:country":"CA",
    "sg:address":"20 Boul Sainte-Anne O",
    "sg:city":"Sainte-Anne-Des-Monts",
    "sg:classifiers":[
        {
            "category":"Shopping",
            "subcategory":"Discount & Variety Stores",
            "type":"Retail Goods"
        }
    ],
    "sg:phone":"+1 418 763 7354",
    "sg:postcode":"G4V 1P6",
    "sg:province":"QC",
    "sg:tags":[
        "merchandise",
        "general"
    ],
    "wof:name":"Dollarama",
    "wof:placetype":"venue"
},
  "geometry": {"coordinates":[-66.48639678959999,49.1292152405],"type":"Point"}
}