{
  "type": "Feature",
  "properties": {
    "addr:full":"212 Rue Champlain Saint-Jean-Sur-Richelieu QC J3B 6V8",
    "addr:housenumber":"212",
    "addr:postcode":"j3b 6v8",
    "addr:street":"Rue Champlain",
    "iso:country":"CA",
    "sg:address":"212 Rue Champlain",
    "sg:city":"Saint-Jean-Sur-Richelieu",
    "sg:classifiers":[
        {
            "category":"Shopping",
            "subcategory":"Clothing, Apparel, & Fashions",
            "type":"Retail Goods"
        }
    ],
    "sg:phone":"+1 450 347 1150",
    "sg:postcode":"J3B 6V8",
    "sg:province":"QC",
    "sg:tags":[
        "item",
        "boutique"
    ],
    "wof:name":"Salon Du Corset Inc",
    "wof:placetype":"venue"
},
  "geometry": {"coordinates":[-73.25229644780001,45.3066329956],"type":"Point"}
}