{
  "type": "Feature",
  "properties": {
    "addr:full":"PO Box 120 Schuler AB T0J 3B0",
    "addr:housenumber":"po",
    "addr:postcode":"t0j 3b0",
    "addr:street":"Box 120 Schuler",
    "iso:country":"CA",
    "sg:address":"PO Box 120",
    "sg:city":"Schuler",
    "sg:classifiers":[
        {
            "category":"Education",
            "subcategory":"School",
            "type":"Public Place"
        }
    ],
    "sg:phone":"+1 403 839 3732",
    "sg:postcode":"T0J 3B0",
    "sg:province":"AB",
    "wof:name":"Schuler School",
    "wof:placetype":"venue"
},
  "geometry": {"coordinates":[-110.094246,50.368176],"type":"Point"}
}