{
  "type": "Feature",
  "properties": {
    "addr:full":"265 Central Ave Grimsby ON L3M 1X6",
    "addr:housenumber":"265",
    "addr:postcode":"l3m 1x6",
    "addr:street":"Central Ave",
    "iso:country":"CA",
    "sg:address":"265 Central Ave",
    "sg:city":"Grimsby",
    "sg:classifiers":[
        {
            "category":"Home & Garden",
            "subcategory":"Garden Supply",
            "type":"Retail Goods"
        }
    ],
    "sg:phone":"+1 905 945 5949",
    "sg:postcode":"L3M 1X6",
    "sg:province":"ON",
    "sg:tags":[
        "center"
    ],
    "wof:name":"Central Greenhouses Grimsby",
    "wof:placetype":"venue"
},
  "geometry": {"coordinates":[-79.5303573608,43.1889915466],"type":"Point"}
}