{
  "type": "Feature",
  "properties": {
    "addr:full":"70 Vanier Dr Kitchener ON N2C 1J5",
    "addr:housenumber":"70",
    "addr:postcode":"n2c 1j5",
    "addr:street":"Vanier Dr",
    "iso:country":"CA",
    "sg:address":"70 Vanier Dr",
    "sg:city":"Kitchener",
    "sg:classifiers":[
        {
            "category":"Education",
            "subcategory":"School",
            "type":"Public Place"
        }
    ],
    "sg:phone":"+1 519 576 5730",
    "sg:postcode":"N2C 1J5",
    "sg:province":"ON",
    "wof:name":"Rockway Public School",
    "wof:placetype":"venue"
},
  "geometry": {"coordinates":[-80.46459197999999,43.4290885925],"type":"Point"}
}