{
  "type": "Feature",
  "properties": {
    "addr:full":"6 Bridge St W Kitchener ON N2K 1K4",
    "addr:housenumber":"6",
    "addr:postcode":"n2k 1k4",
    "addr:street":"Bridge St W",
    "iso:country":"CA",
    "sg:address":"6 Bridge St W",
    "sg:city":"Kitchener",
    "sg:classifiers":[
        {
            "category":"Bars & Pubs",
            "type":"Food & Drink"
        }
    ],
    "sg:phone":"+1 519 744 6367",
    "sg:postcode":"N2K 1K4",
    "sg:province":"ON",
    "sg:tags":[
        "club",
        "night"
    ],
    "wof:name":"Grand Tavern",
    "wof:placetype":"venue"
},
  "geometry": {"coordinates":[-80.48279599999999,43.482433],"type":"Point"}
}