{
  "type": "Feature",
  "properties": {
    "iso:country":"CA",
    "sg:address":"680 Boul Laure",
    "sg:city":"Sept-Iles",
    "sg:classifiers":[
        {
            "category":"Restaurant",
            "type":"Food & Drink"
        }
    ],
    "sg:phone":"+1 418 962 6888",
    "sg:postcode":"G4R 1X9",
    "sg:province":"QC",
    "wof:name":"Chez Carlos Restaurant",
    "wof:placetype":"venue"
},
  "geometry": {"coordinates":[-66.38060760499999,50.2174186707],"type":"Point"}
}