{
  "type": "Feature",
  "properties": {
    "iso:country":"CA",
    "sg:address":"1033 Notre Dame Ave",
    "sg:city":"Winnipeg",
    "sg:classifiers":[
        {
            "category":"Restaurant",
            "type":"Food & Drink"
        }
    ],
    "sg:phone":"+1 204 987 8427",
    "sg:postcode":"R3E 0N4",
    "sg:province":"MB",
    "wof:name":"Burger King",
    "wof:placetype":"venue"
},
  "geometry": {"coordinates":[-97.172668,49.905918],"type":"Point"}
}