{
  "type": "Feature",
  "properties": {
    "addr:full":"1033 Notre Dame Ave Winnipeg MB R3E 0N4",
    "addr:housenumber":"1033",
    "addr:postcode":"r3e 0n4",
    "addr:street":"Notre Dame Ave",
    "iso:country":"CA",
    "sg:address":"1033 Notre Dame Ave",
    "sg:city":"Winnipeg",
    "sg:classifiers":[
        {
            "category":"Restaurant",
            "type":"Food & Drink"
        }
    ],
    "sg:phone":"+1 204 987 8427",
    "sg:postcode":"R3E 0N4",
    "sg:province":"MB",
    "wof:name":"Burger King",
    "wof:placetype":"venue"
},
  "geometry": {"coordinates":[-97.172668,49.905918],"type":"Point"}
}