{
  "type": "Feature",
  "properties": {
    "addr:full":"Trois-Rivieres QC G8Y 1W1",
    "addr:postcode":"g8y 1w1",
    "iso:country":"CA",
    "sg:city":"Trois-Rivieres",
    "sg:classifiers":[
        {
            "category":"Shopping",
            "subcategory":"Luggage & Leather Goods",
            "type":"Retail Goods"
        }
    ],
    "sg:phone":"+1 819 373 3399",
    "sg:postcode":"G8Y 1W1",
    "sg:province":"QC",
    "wof:name":"Access",
    "wof:placetype":"venue"
},
  "geometry": {"coordinates":[-72.5861282349,46.3563766479],"type":"Point"}
}