{
  "type": "Feature",
  "properties": {
    "addr:full":"798 Rue Commerciale Saint-Jean-Chrysostome QC G6Z 2C9",
    "addr:housenumber":"798",
    "addr:postcode":"g6z 2c9",
    "addr:street":"Rue Commerciale Saint-Jean-Chrysostome",
    "iso:country":"CA",
    "sg:address":"798 Rue Commerciale",
    "sg:city":"Saint-Jean-Chrysostome",
    "sg:classifiers":[
        {
            "category":"Cinema",
            "subcategory":"Movie Rental",
            "type":"Entertainment"
        }
    ],
    "sg:phone":"+1 418 834 2000",
    "sg:postcode":"G6Z 2C9",
    "sg:province":"QC",
    "sg:tags":[
        "leasing",
        "video",
        "disc",
        "tape"
    ],
    "wof:name":"Club Video Eclair Inc",
    "wof:placetype":"venue"
},
  "geometry": {"coordinates":[-71.20752716059999,46.7309532166],"type":"Point"}
}