{
  "type": "Feature",
  "properties": {
    "addr:full":"PO Box 821 Carlyle SK S0C 0R0",
    "addr:housenumber":"po",
    "addr:postcode":"s0c 0r0",
    "addr:street":"Box 821 Carlyle",
    "iso:country":"CA",
    "sg:address":"PO Box 821",
    "sg:city":"Carlyle",
    "sg:classifiers":[
        {
            "category":"Utilities",
            "subcategory":"Fuel Oil & Lpg",
            "type":"Services"
        }
    ],
    "sg:phone":"+1 306 577 7192",
    "sg:postcode":"S0C 0R0",
    "sg:province":"SK",
    "sg:tags":[
        "propane",
        "gas"
    ],
    "wof:name":"Cal-Gas Inc",
    "wof:placetype":"venue"
},
  "geometry": {"coordinates":[-102.265388489,49.6365852356],"type":"Point"}
}