{
  "type": "Feature",
  "properties": {
    "iso:country":"CA",
    "sg:address":"130 Rue Principale",
    "sg:city":"Laval",
    "sg:classifiers":[
        {
            "category":"Wholesale",
            "subcategory":"Electrical",
            "type":"Manufacturing & Wholesale Goods"
        }
    ],
    "sg:phone":"+1 450 689 4572",
    "sg:postcode":"H7X 3V2",
    "sg:province":"QC",
    "sg:tags":[
        "instrument",
        "electronic"
    ],
    "wof:name":"Techmatron Instrument Inc",
    "wof:placetype":"venue"
},
  "geometry": {"coordinates":[-73.7978363037,45.536151886],"type":"Point"}
}