{
  "type": "Feature",
  "properties": {
    "iso:country":"CA",
    "sg:city":"Winnipeg",
    "sg:classifiers":[
        {
            "category":"Shopping",
            "subcategory":"Florist",
            "type":"Retail Goods"
        }
    ],
    "sg:phone":"+1 204 222 2741",
    "sg:postcode":"R2C 1R1",
    "sg:province":"MB",
    "wof:name":"Wreaths & Roses",
    "wof:placetype":"venue"
},
  "geometry": {"coordinates":[-97.0031738281,49.8952674866],"type":"Point"}
}