{
  "type": "Feature",
  "properties": {
    "addr:full":"4668 25 St SE Calgary AB T2B 3M2",
    "addr:housenumber":"4668",
    "addr:postcode":"t2b 3m2",
    "addr:street":"25 St Se",
    "iso:country":"CA",
    "sg:address":"4668 25 St SE",
    "sg:city":"Calgary",
    "sg:classifiers":[
        {
            "category":"Utilities",
            "subcategory":"Refuse",
            "type":"Services"
        }
    ],
    "sg:phone":"+1 403 720 7201",
    "sg:postcode":"T2B 3M2",
    "sg:province":"AB",
    "sg:tags":[
        "disposal",
        "waste",
        "garbage",
        "collection"
    ],
    "wof:name":"Canadian Waste Svc",
    "wof:placetype":"venue"
},
  "geometry": {"coordinates":[-113.998924,51.012657],"type":"Point"}
}