{
  "type": "Feature",
  "properties": {
    "iso:country":"CA",
    "sg:address":"525 Beresford Ave",
    "sg:city":"Winnipeg",
    "sg:classifiers":[
        {
            "category":"Organizations",
            "subcategory":"Religious Organization",
            "type":"Services"
        }
    ],
    "sg:phone":"+1 204 452 8561",
    "sg:postcode":"R3L 1J4",
    "sg:province":"MB",
    "sg:tags":[
        "church"
    ],
    "wof:name":"Churchill Park United Church",
    "wof:placetype":"venue"
},
  "geometry": {"coordinates":[-97.13446,49.860561],"type":"Point"}
}