{
  "type": "Feature",
  "properties": {
    "addr:full":"Burnaby BC V5G 1J9",
    "addr:postcode":"v5g 1j9",
    "iso:country":"CA",
    "sg:city":"Burnaby",
    "sg:classifiers":[
        {
            "category":"Wholesale",
            "subcategory":"Computers",
            "type":"Manufacturing & Wholesale Goods"
        }
    ],
    "sg:phone":"+1 604 291 7088",
    "sg:postcode":"V5G 1J9",
    "sg:province":"BC",
    "wof:name":"Sun Microsystems of Canada Inc",
    "wof:placetype":"venue"
},
  "geometry": {"coordinates":[-122.99945099999999,49.254768],"type":"Point"}
}