{
  "type": "Feature",
  "properties": {
    "addr:full":"9255 Woodbine Ave Markham ON L6C 1Y9",
    "addr:housenumber":"9255",
    "addr:postcode":"l6c 1y9",
    "addr:street":"Woodbine Ave",
    "iso:country":"CA",
    "sg:address":"9255 Woodbine Ave",
    "sg:city":"Markham",
    "sg:classifiers":[
        {
            "category":"Restaurant",
            "type":"Food & Drink"
        }
    ],
    "sg:phone":"+1 905 887 2511",
    "sg:postcode":"L6C 1Y9",
    "sg:province":"ON",
    "wof:name":"Mr Sub",
    "wof:placetype":"venue"
},
  "geometry": {"coordinates":[-79.362686,43.86842],"type":"Point"}
}