{
  "type": "Feature",
  "properties": {
    "addr:full":"5963 92 St NW Edmonton AB T6E 3A5",
    "addr:housenumber":"5963",
    "addr:postcode":"t6e 3a5",
    "addr:street":"92 St Nw",
    "iso:country":"CA",
    "sg:address":"5963 92 St NW",
    "sg:city":"Edmonton",
    "sg:classifiers":[
        {
            "category":"Autos & Motor Vehicles",
            "subcategory":"Automobile Sales",
            "type":"Retail Goods"
        }
    ],
    "sg:phone":"+1 780 944 9297",
    "sg:postcode":"T6E 3A5",
    "sg:province":"AB",
    "sg:tags":[
        "car",
        "dealer"
    ],
    "wof:name":"Smu Auto Brokers Inc",
    "wof:placetype":"venue"
},
  "geometry": {"coordinates":[-113.468513,53.495316],"type":"Point"}
}