{
  "type": "Feature",
  "properties": {
    "addr:full":"504 Rue Du Parc Saint-Eustache QC J7R 5B2",
    "addr:housenumber":"504",
    "addr:postcode":"j7r 5b2",
    "addr:street":"Rue Du Parc",
    "iso:country":"CA",
    "sg:address":"504 Rue Du Parc",
    "sg:city":"Saint-Eustache",
    "sg:classifiers":[
        {
            "category":"Professional",
            "type":"Services"
        }
    ],
    "sg:phone":"+1 450 491 2444",
    "sg:postcode":"J7R 5B2",
    "sg:province":"QC",
    "sg:tags":[
        "equipment",
        "hydroponics",
        "supply"
    ],
    "wof:name":"Ppm Hydroponique Inc",
    "wof:placetype":"venue"
},
  "geometry": {"coordinates":[-73.91246032710001,45.5678443909],"type":"Point"}
}