{
  "type": "Feature",
  "properties": {
    "addr:full":"899 Holmes Rd West St Paul MB R4A 7A7",
    "addr:housenumber":"899",
    "addr:postcode":"r4a 7a7",
    "addr:street":"Holmes Rd",
    "iso:country":"CA",
    "sg:address":"899 Holmes Rd",
    "sg:city":"West St Paul",
    "sg:classifiers":[
        {
            "category":"Building & Trades",
            "subcategory":"Landscaping Services",
            "type":"Services"
        }
    ],
    "sg:phone":"+1 204 338 0351",
    "sg:postcode":"R4A 7A7",
    "sg:province":"MB",
    "sg:tags":[
        "landscape",
        "contractor"
    ],
    "wof:name":"Mc Ewen Brothers Ltd",
    "wof:placetype":"venue"
},
  "geometry": {"coordinates":[-97.15743255620001,49.9906005859],"type":"Point"}
}