{
  "type": "Feature",
  "properties": {
    "addr:full":"3269 American Dr Mississauga ON L4V 1V4",
    "addr:housenumber":"3269",
    "addr:postcode":"l4v 1v4",
    "addr:street":"American Dr",
    "iso:country":"CA",
    "sg:address":"3269 American Dr",
    "sg:city":"Mississauga",
    "sg:classifiers":[
        {
            "category":"Banks & Credit Unions",
            "subcategory":"Bank",
            "type":"Services"
        }
    ],
    "sg:phone":"+1 905 678 7272",
    "sg:postcode":"L4V 1V4",
    "sg:province":"ON",
    "sg:tags":[
        "machine",
        "teller",
        "automated"
    ],
    "wof:name":"Versent Corp",
    "wof:placetype":"venue"
},
  "geometry": {"coordinates":[-79.6158981323,43.694683075],"type":"Point"}
}