{
  "type": "Feature",
  "properties": {
    "addr:full":"230 Queen St E Toronto ON M5A 1S3",
    "addr:housenumber":"230",
    "addr:postcode":"m5a 1s3",
    "addr:street":"Queen St E",
    "iso:country":"CA",
    "sg:address":"230 Queen St E",
    "sg:city":"Toronto",
    "sg:classifiers":[
        {
            "category":"Shopping",
            "type":"Retail Goods"
        }
    ],
    "sg:phone":"+1 416 363 1333",
    "sg:postcode":"M5A 1S3",
    "sg:province":"ON",
    "sg:tags":[
        "art",
        "gallery",
        "dealer"
    ],
    "wof:name":"Fran Hill Gallery Ltd",
    "wof:placetype":"venue"
},
  "geometry": {"coordinates":[-79.36876700000001,43.6548],"type":"Point"}
}