{
  "type": "Feature",
  "properties": {
    "addr:full":"106 Regent St Stratford ON N5A 3W1",
    "addr:housenumber":"106",
    "addr:postcode":"n5a 3w1",
    "addr:street":"Regent St",
    "iso:country":"CA",
    "sg:address":"106 Regent St",
    "sg:city":"Stratford",
    "sg:classifiers":[
        {
            "category":"Manufacturing",
            "subcategory":"Metals",
            "type":"Manufacturing & Wholesale Goods"
        }
    ],
    "sg:phone":"+1 519 271 5614",
    "sg:postcode":"N5A 3W1",
    "sg:province":"ON",
    "sg:tags":[
        "fiber",
        "optics",
        "system"
    ],
    "wof:name":"Lloyd's Electric of Stratford",
    "wof:placetype":"venue"
},
  "geometry": {"coordinates":[-80.9687194824,43.3651885986],"type":"Point"}
}