{
  "type": "Feature",
  "properties": {
    "addr:full":"11043 201 St NW Edmonton AB T5S 2N3",
    "addr:housenumber":"11043",
    "addr:postcode":"t5s 2n3",
    "addr:street":"201 St Nw",
    "iso:country":"CA",
    "sg:address":"11043 201 St NW",
    "sg:city":"Edmonton",
    "sg:classifiers":[
        {
            "category":"Manufacturing",
            "subcategory":"Wood Products",
            "type":"Manufacturing & Wholesale Goods"
        }
    ],
    "sg:phone":"+1 780 440 4037",
    "sg:postcode":"T5S 2N3",
    "sg:province":"AB",
    "sg:tags":[
        "pallet",
        "field",
        "oil"
    ],
    "wof:name":"Sea-Can Containers Ltd",
    "wof:placetype":"venue"
},
  "geometry": {"coordinates":[-113.666641235,53.5575637817],"type":"Point"}
}