{
  "type": "Feature",
  "properties": {
    "iso:country":"CA",
    "sg:address":"48 Rue Boivin",
    "sg:city":"Ville-Marie",
    "sg:classifiers":[
        {
            "category":"Freight",
            "type":"Transportation"
        }
    ],
    "sg:phone":"+1 819 629 3450",
    "sg:postcode":"J9V 1B5",
    "sg:province":"QC",
    "sg:tags":[
        "trucking"
    ],
    "wof:name":"Groupe Gibois Inc",
    "wof:placetype":"venue"
},
  "geometry": {"coordinates":[-79.4289855957,47.3286094666],"type":"Point"}
}