{
  "type": "Feature",
  "properties": {
    "iso:country":"CA",
    "sg:city":"Calgary",
    "sg:classifiers":[
        {
            "category":"Manufacturing",
            "subcategory":"Furniture",
            "type":"Manufacturing & Wholesale Goods"
        }
    ],
    "sg:phone":"+1 403 250 7887",
    "sg:postcode":"T2E 6V2",
    "sg:province":"AB",
    "sg:tags":[
        "upholsterer"
    ],
    "wof:name":"Academy of Upholstery",
    "wof:placetype":"venue"
},
  "geometry": {"coordinates":[-114.011543274,51.0861434937],"type":"Point"}
}