{
  "type": "Feature",
  "properties": {
    "addr:full":"140 4 Ave SW # 143 Calgary AB T2P 3N3",
    "addr:housenumber":"140",
    "addr:postcode":"t2p 3n3",
    "addr:street":"4 Ave Sw # 143",
    "iso:country":"CA",
    "sg:address":"140 4 Ave SW # 143",
    "sg:city":"Calgary",
    "sg:classifiers":[
        {
            "category":"Food & Beverages",
            "subcategory":"Groceries & Convenience Stores",
            "type":"Retail Goods"
        }
    ],
    "sg:phone":"+1 403 237 7677",
    "sg:postcode":"T2P 3N3",
    "sg:province":"AB",
    "wof:name":"Sprague Drug Inc",
    "wof:placetype":"venue"
},
  "geometry": {"coordinates":[-114.063812,51.049454],"type":"Point"}
}