{
  "type": "Feature",
  "properties": {
    "addr:full":"11411 40 Ave NW Edmonton AB T6J 0R4",
    "addr:housenumber":"11411",
    "addr:postcode":"t6j 0r4",
    "addr:street":"40 Ave Nw",
    "iso:country":"CA",
    "sg:address":"11411 40 Ave NW",
    "sg:city":"Edmonton",
    "sg:classifiers":[
        {
            "category":"Retail",
            "subcategory":"Auto Repair",
            "type":"Services"
        }
    ],
    "sg:phone":"+1 780 434 1914",
    "sg:postcode":"T6J 0R4",
    "sg:province":"AB",
    "sg:tags":[
        "repairing",
        "automobile"
    ],
    "wof:name":"Certigard",
    "wof:placetype":"venue"
},
  "geometry": {"coordinates":[-113.526886,53.475834],"type":"Point"}
}