{
  "type": "Feature",
  "properties": {
    "addr:full":"55 Bridgeport Rd E #A Waterloo ON N2J 2J7",
    "addr:housenumber":"55",
    "addr:postcode":"n2j 2j7",
    "addr:street":"Bridgeport Rd E # A",
    "iso:country":"CA",
    "sg:address":"55 Bridgeport Rd E #A",
    "sg:city":"Waterloo",
    "sg:classifiers":[
        {
            "category":"Insurance",
            "subcategory":"Insurance Agent",
            "type":"Services"
        }
    ],
    "sg:phone":"+1 519 746 5240",
    "sg:postcode":"N2J 2J7",
    "sg:province":"ON",
    "wof:name":"Pilot Insurance CO",
    "wof:placetype":"venue"
},
  "geometry": {"coordinates":[-80.5182189941,43.4681930542],"type":"Point"}
}