{
  "type": "Feature",
  "properties": {
    "addr:full":"5750 Timberlea Blvd # 4 Mississauga ON L4W 5N8",
    "addr:housenumber":"5750",
    "addr:postcode":"l4w 5n8",
    "addr:street":"Timberlea Blvd # 4",
    "iso:country":"CA",
    "sg:address":"5750 Timberlea Blvd # 4",
    "sg:city":"Mississauga",
    "sg:classifiers":[
        {
            "category":"Autos & Motor Vehicles",
            "subcategory":"Auto Supplies",
            "type":"Retail Goods"
        }
    ],
    "sg:phone":"+1 905 206 9788",
    "sg:postcode":"L4W 5N8",
    "sg:province":"ON",
    "sg:tags":[
        "automobile",
        "stereo",
        "radio"
    ],
    "wof:name":"Sound Theory",
    "wof:placetype":"venue"
},
  "geometry": {"coordinates":[-79.6509017944,43.6384506226],"type":"Point"}
}