{
  "type": "Feature",
  "properties": {
    "iso:country":"CA",
    "sg:address":"2911 Derry Rd E",
    "sg:city":"Mississauga",
    "sg:classifiers":[
        {
            "category":"Restaurant",
            "type":"Food & Drink"
        }
    ],
    "sg:phone":"+1 905 677 7441",
    "sg:postcode":"L4T 1A6",
    "sg:province":"ON",
    "wof:name":"Moon Garden Tavern",
    "wof:placetype":"venue"
},
  "geometry": {"coordinates":[-79.644112,43.70261],"type":"Point"}
}