{
  "type": "Feature",
  "properties": {
    "iso:country":"CA",
    "sg:address":"84 Russell St W",
    "sg:city":"Lindsay",
    "sg:classifiers":[
        {
            "category":"Food & Beverages",
            "subcategory":"Specialty",
            "type":"Retail Goods"
        }
    ],
    "sg:phone":"+1 705 328 3628",
    "sg:postcode":"K9V 6A5",
    "sg:province":"ON",
    "sg:tags":[
        "health",
        "diet"
    ],
    "wof:name":"Jo Anne's Place Health Foods",
    "wof:placetype":"venue"
},
  "geometry": {"coordinates":[-78.74109649659999,44.3527908325],"type":"Point"}
}