{
  "type": "Feature",
  "properties": {
    "addr:full":"339 Rue Rivard Rimouski QC G5L 7J6",
    "addr:housenumber":"339",
    "addr:postcode":"g5l 7j6",
    "addr:street":"Rue Rivard",
    "iso:country":"CA",
    "sg:address":"339 Rue Rivard",
    "sg:city":"Rimouski",
    "sg:classifiers":[
        {
            "category":"Autos & Motor Vehicles",
            "subcategory":"Auto Supplies",
            "type":"Retail Goods"
        }
    ],
    "sg:phone":"+1 418 722 0757",
    "sg:postcode":"G5L 7J6",
    "sg:province":"QC",
    "sg:tags":[
        "automobile",
        "parts",
        "electric"
    ],
    "wof:name":"L C Oto Electrique",
    "wof:placetype":"venue"
},
  "geometry": {"coordinates":[-68.50411200000001,48.455345],"type":"Point"}
}