{
  "type": "Feature",
  "properties": {
    "addr:full":"164 Rang Du 5E Saint-Stanislas-DE-Kostka QC J0S 1W0",
    "addr:housenumber":"164",
    "addr:postcode":"j0s 1w0",
    "addr:street":"Rang Du 5E",
    "iso:country":"CA",
    "sg:address":"164 Rang Du 5E",
    "sg:city":"Saint-Stanislas-DE-Kostka",
    "sg:classifiers":[
        {
            "category":"Building & Trades",
            "subcategory":"Construction",
            "type":"Services"
        }
    ],
    "sg:phone":"+1 450 373 1879",
    "sg:postcode":"J0S 1W0",
    "sg:province":"QC",
    "sg:tags":[
        "excavating",
        "paving",
        "contractor"
    ],
    "wof:name":"Asphalte Major & Fils Inc",
    "wof:placetype":"venue"
},
  "geometry": {"coordinates":[-74.12660980219999,45.1806716919],"type":"Point"}
}