{
  "type": "Feature",
  "properties": {
    "addr:full":"200 Mackenzie St Revelstoke BC V0E 2S0",
    "addr:housenumber":"200",
    "addr:postcode":"v0e 2s0",
    "addr:street":"Mackenzie St",
    "iso:country":"CA",
    "sg:address":"200 Mackenzie St",
    "sg:city":"Revelstoke",
    "sg:classifiers":[
        {
            "category":"Banks & Credit Unions",
            "subcategory":"Bank",
            "type":"Services"
        }
    ],
    "sg:phone":"+1 250 837 2151",
    "sg:postcode":"V0E 2S0",
    "sg:province":"BC",
    "wof:name":"Cibc",
    "wof:placetype":"venue"
},
  "geometry": {"coordinates":[-118.19526672400001,50.9986343384],"type":"Point"}
}