{
  "type": "Feature",
  "properties": {
    "addr:full":"105 2nd Ave W Kelvington SK S0A 1W0",
    "addr:housenumber":"105",
    "addr:postcode":"s0a 1w0",
    "addr:street":"2Nd Ave W Kelvington",
    "iso:country":"CA",
    "sg:address":"105 2nd Ave W",
    "sg:city":"Kelvington",
    "sg:classifiers":[
        {
            "category":"Organizations",
            "subcategory":"Religious Organization",
            "type":"Services"
        }
    ],
    "sg:phone":"+1 306 327 5131",
    "sg:postcode":"S0A 1W0",
    "sg:province":"SK",
    "sg:tags":[
        "church"
    ],
    "wof:name":"Kelvington United Church",
    "wof:placetype":"venue"
},
  "geometry": {"coordinates":[-103.529502869,52.16456604],"type":"Point"}
}