{
  "type": "Feature",
  "properties": {
    "addr:full":"398 Rte 172 N Sacre-Coeur-Saguenay QC G0T 1Y0",
    "addr:housenumber":"398",
    "addr:postcode":"g0t 1y0",
    "addr:street":"Rte 172 N",
    "iso:country":"CA",
    "sg:address":"398 Rte 172 N",
    "sg:city":"Sacre-Coeur-Saguenay",
    "sg:classifiers":[
        {
            "category":"Retail",
            "subcategory":"Auto Repair",
            "type":"Services"
        }
    ],
    "sg:phone":"+1 418 236 4675",
    "sg:postcode":"G0T 1Y0",
    "sg:province":"QC",
    "sg:tags":[
        "repairing",
        "automobile"
    ],
    "wof:name":"Garage Roger Savard Inc",
    "wof:placetype":"venue"
},
  "geometry": {"coordinates":[-69.7986907959,48.2297210693],"type":"Point"}
}