{
  "type": "Feature",
  "properties": {
    "addr:full":"2725 Rue Liebert Montreal QC H1L 5R5",
    "addr:housenumber":"2725",
    "addr:postcode":"h1l 5r5",
    "addr:street":"Rue Liebert",
    "iso:country":"CA",
    "sg:address":"2725 Rue Liebert",
    "sg:city":"Montreal",
    "sg:classifiers":[
        {
            "category":"Building & Trades",
            "subcategory":"Construction",
            "type":"Services"
        }
    ],
    "sg:phone":"+1 514 351 5677",
    "sg:postcode":"H1L 5R5",
    "sg:province":"QC",
    "sg:tags":[
        "excavating",
        "contractor"
    ],
    "wof:name":"Jacques Gauthier Excavation",
    "wof:placetype":"venue"
},
  "geometry": {"coordinates":[-73.52565002439999,45.5966720581],"type":"Point"}
}