{
  "type": "Feature",
  "properties": {
    "iso:country":"CA",
    "sg:address":"1725 Ch Gascon",
    "sg:city":"Terrebonne",
    "sg:classifiers":[
        {
            "category":"Shopping",
            "subcategory":"Clothing, Apparel, & Fashions",
            "type":"Retail Goods"
        }
    ],
    "sg:phone":"+1 450 471 2112",
    "sg:postcode":"J6X 2Z8",
    "sg:province":"QC",
    "sg:tags":[
        "infant",
        "wear"
    ],
    "wof:name":"Collection L'Enfant Unique",
    "wof:placetype":"venue"
},
  "geometry": {"coordinates":[-73.6557769775,45.7176437378],"type":"Point"}
}