{
  "type": "Feature",
  "properties": {
    "addr:full":"388 North Ch Austin QC J0B 1B0",
    "addr:housenumber":"388",
    "addr:postcode":"j0b 1b0",
    "addr:street":"North Ch",
    "iso:country":"CA",
    "sg:address":"388 North Ch",
    "sg:city":"Austin",
    "sg:classifiers":[
        {
            "category":"Professional",
            "type":"Services"
        }
    ],
    "sg:phone":"+1 450 297 9997",
    "sg:postcode":"J0B 1B0",
    "sg:province":"QC",
    "sg:tags":[
        "control",
        "vibration"
    ],
    "wof:name":"Jfl Ind Inc",
    "wof:placetype":"venue"
},
  "geometry": {"coordinates":[-72.25411224370001,45.2952651978],"type":"Point"}
}