{
  "type": "Feature",
  "properties": {
    "addr:full":"395 Av Marconi Sainte-Foy QC G1N 4A5",
    "addr:postcode":"g1n 4a5",
    "addr:street":"395 Av Marconi",
    "iso:country":"CA",
    "sg:address":"395 Av Marconi",
    "sg:city":"Sainte-Foy",
    "sg:classifiers":[
        {
            "category":"Manufacturing",
            "subcategory":"Tools & Machinery",
            "type":"Manufacturing & Wholesale Goods"
        }
    ],
    "sg:phone":"+1 418 683 2527",
    "sg:postcode":"G1N 4A5",
    "sg:province":"QC",
    "sg:tags":[
        "machine",
        "automobile",
        "shop"
    ],
    "wof:name":"Outillage Industriel Quebec",
    "wof:placetype":"venue"
},
  "geometry": {"coordinates":[-71.276878,46.798611],"type":"Point"}
}