{
  "type": "Feature",
  "properties": {
    "iso:country":"CA",
    "sg:address":"7584 Rue Centrale",
    "sg:city":"Lasalle",
    "sg:classifiers":[
        {
            "category":"Health Services",
            "subcategory":"Doctor",
            "type":"Services"
        }
    ],
    "sg:phone":"+1 514 368 4860",
    "sg:postcode":"H8P 1K5",
    "sg:province":"QC",
    "sg:tags":[
        "clinic"
    ],
    "wof:name":"Centre Medical Centrale",
    "wof:placetype":"venue"
},
  "geometry": {"coordinates":[-73.597183,45.43288],"type":"Point"}
}