{
  "type": "Feature",
  "properties": {
    "iso:country":"CA",
    "sg:address":"16 Fulton Lane",
    "sg:city":"Saint John",
    "sg:classifiers":[
        {
            "category":"Real Estate",
            "subcategory":"Surveying",
            "type":"Services"
        }
    ],
    "sg:phone":"+1 506 652 1522",
    "sg:postcode":"E2H 2W4",
    "sg:province":"NB",
    "sg:tags":[
        "surveyor"
    ],
    "wof:name":"Kierstead Quigley & Roberts",
    "wof:placetype":"venue"
},
  "geometry": {"coordinates":[-66.0278015137,45.328830719],"type":"Point"}
}