{
  "type": "Feature",
  "properties": {
    "addr:full":"114 Green St Whitby ON L1N 4C8",
    "addr:housenumber":"114",
    "addr:postcode":"l1n 4c8",
    "addr:street":"Green St",
    "iso:country":"CA",
    "sg:address":"114 Green St",
    "sg:city":"Whitby",
    "sg:classifiers":[
        {
            "category":"Professional",
            "subcategory":"Lawyer & Legal Services",
            "type":"Services"
        }
    ],
    "sg:phone":"+1 905 666 4396",
    "sg:postcode":"L1N 4C8",
    "sg:province":"ON",
    "sg:tags":[
        "attorney"
    ],
    "wof:name":"Mc Mackin, Alan J",
    "wof:placetype":"venue"
},
  "geometry": {"coordinates":[-78.94110870359999,43.8798599243],"type":"Point"}
}