{
  "type": "Feature",
  "properties": {
    "iso:country":"CA",
    "sg:city":"Nanaimo",
    "sg:classifiers":[
        {
            "category":"Professional",
            "subcategory":"Lawyer & Legal Services",
            "type":"Services"
        }
    ],
    "sg:phone":"+1 250 756 3823",
    "sg:postcode":"V9T 1X5",
    "sg:province":"BC",
    "sg:tags":[
        "attorney"
    ],
    "wof:name":"Johnston Lewis & Franklin",
    "wof:placetype":"venue"
},
  "geometry": {"coordinates":[-124.004348755,49.2072257996],"type":"Point"}
}