{
  "type": "Feature",
  "properties": {
    "iso:country":"CA",
    "sg:city":"Montreal",
    "sg:classifiers":[
        {
            "category":"Professional",
            "subcategory":"Computer Services",
            "type":"Services"
        }
    ],
    "sg:phone":"+1 514 878 0080",
    "sg:postcode":"H2Z 1S8",
    "sg:province":"QC",
    "sg:tags":[
        "internet"
    ],
    "wof:name":"Peer 1 Network Corp",
    "wof:placetype":"venue"
},
  "geometry": {"coordinates":[-73.565208,45.502392],"type":"Point"}
}