{
  "type": "Feature",
  "properties": {
    "addr:full":"Saanichton BC V8M 2B4",
    "addr:postcode":"v8m 2b4",
    "iso:country":"CA",
    "sg:city":"Saanichton",
    "sg:classifiers":[
        {
            "category":"Sports & Exercise",
            "subcategory":"Gym",
            "type":"Entertainment"
        }
    ],
    "sg:phone":"+1 250 544 1501",
    "sg:postcode":"V8M 2B4",
    "sg:province":"BC",
    "sg:tags":[
        "club",
        "health",
        "studio",
        "gymnasium"
    ],
    "wof:name":"Curves For Women",
    "wof:placetype":"venue"
},
  "geometry": {"coordinates":[-123.416687012,48.5955352783],"type":"Point"}
}