{
  "type": "Feature",
  "properties": {
    "addr:full":"Edmonton AB T5H 4E6",
    "addr:postcode":"t5h 4e6",
    "iso:country":"CA",
    "sg:city":"Edmonton",
    "sg:classifiers":[
        {
            "category":"Real Estate",
            "subcategory":"Real Estate Operator",
            "type":"Services"
        }
    ],
    "sg:phone":"+1 780 429 4809",
    "sg:postcode":"T5H 4E6",
    "sg:province":"AB",
    "sg:tags":[
        "apartment"
    ],
    "wof:name":"Clarke Street Apartments",
    "wof:placetype":"venue"
},
  "geometry": {"coordinates":[-113.47654724100001,53.5509262085],"type":"Point"}
}