{
  "type": "Feature",
  "properties": {
    "addr:full":"944 Barrydowne Rd Sudbury ON P3A 3V3",
    "addr:housenumber":"944",
    "addr:postcode":"p3a 3v3",
    "addr:street":"Barrydowne Rd",
    "iso:country":"CA",
    "sg:address":"944 Barrydowne Rd",
    "sg:city":"Sudbury",
    "sg:classifiers":[
        {
            "category":"Cinema",
            "subcategory":"Movie Rental",
            "type":"Entertainment"
        }
    ],
    "sg:phone":"+1 705 560 2999",
    "sg:postcode":"P3A 3V3",
    "sg:province":"ON",
    "sg:tags":[
        "leasing",
        "video",
        "disc",
        "tape"
    ],
    "wof:name":"Bianco's Movie Supercenters",
    "wof:placetype":"venue"
},
  "geometry": {"coordinates":[-80.943985,46.517639],"type":"Point"}
}