{
  "type": "Feature",
  "properties": {
    "addr:full":"2766 Victoria Park Ave North York ON M2J 4A8",
    "addr:housenumber":"2766",
    "addr:postcode":"m2j 4a8",
    "addr:street":"Victoria Park Ave",
    "iso:country":"CA",
    "sg:address":"2766 Victoria Park Ave",
    "sg:city":"North York",
    "sg:classifiers":[
        {
            "category":"Restaurant",
            "type":"Food & Drink"
        }
    ],
    "sg:phone":"+1 416 494 7373",
    "sg:postcode":"M2J 4A8",
    "sg:province":"ON",
    "wof:name":"Sammy's Pizza Restaurant",
    "wof:placetype":"venue"
},
  "geometry": {"coordinates":[-79.3284988403,43.7865333557],"type":"Point"}
}