{
  "type": "Feature",
  "properties": {
    "addr:full":"2725 St. Christophers Rd North Vancouver BC V7K 2B6",
    "addr:housenumber":"2725",
    "addr:postcode":"v7k 2b6",
    "addr:street":"St. Christophers Rd",
    "iso:country":"CA",
    "sg:address":"2725 St. Christophers Rd",
    "sg:city":"North Vancouver",
    "sg:classifiers":[
        {
            "category":"Education",
            "subcategory":"School",
            "type":"Public Place"
        }
    ],
    "sg:phone":"+1 604 985 7435",
    "sg:postcode":"V7K 2B6",
    "sg:province":"BC",
    "wof:name":"Waldorf School",
    "wof:placetype":"venue"
},
  "geometry": {"coordinates":[-123.04624939,49.3335189819],"type":"Point"}
}