{
  "type": "Feature",
  "properties": {
    "addr:full":"5251 Ch Du Quai Lac-Kenogami QC G7X 7V6",
    "addr:postcode":"5251;g7x 7v6",
    "addr:street":"Ch Du Quai Lac-Kenogami",
    "iso:country":"CA",
    "sg:address":"5251 Ch Du Quai",
    "sg:city":"Lac-Kenogami",
    "sg:classifiers":[
        {
            "category":"Food & Beverages",
            "subcategory":"Groceries & Convenience Stores",
            "type":"Retail Goods"
        }
    ],
    "sg:phone":"+1 418 542 0183",
    "sg:postcode":"G7X 7V6",
    "sg:province":"QC",
    "sg:tags":[
        "grocer"
    ],
    "wof:name":"Depanneur Le Baladeur Enr",
    "wof:placetype":"venue"
},
  "geometry": {"coordinates":[-71.3267288208,48.3538627625],"type":"Point"}
}