{
  "type": "Feature",
  "properties": {
    "iso:country":"CA",
    "sg:address":"3805 Richmond Rd SW",
    "sg:city":"Calgary",
    "sg:classifiers":[
        {
            "category":"Autos & Motor Vehicles",
            "subcategory":"Fuel & Gas Station",
            "type":"Retail Goods"
        }
    ],
    "sg:phone":"+1 403 249 6272",
    "sg:postcode":"T3E 4P2",
    "sg:province":"AB",
    "sg:tags":[
        "oil"
    ],
    "wof:name":"Glamorgan Shell",
    "wof:placetype":"venue"
},
  "geometry": {"coordinates":[-114.141602,51.022087],"type":"Point"}
}