{
  "type": "Feature",
  "properties": {
    "iso:country":"CA",
    "sg:city":"Mississauga",
    "sg:classifiers":[
        {
            "category":"Wholesale",
            "subcategory":"Chemicals & Plastics",
            "type":"Manufacturing & Wholesale Goods"
        }
    ],
    "sg:phone":"+1 905 822 0243",
    "sg:postcode":"L5J 2M4",
    "sg:province":"ON",
    "wof:name":"Canlox Chemicals Inc",
    "wof:placetype":"venue"
},
  "geometry": {"coordinates":[-79.6510543823,43.5205612183],"type":"Point"}
}