{
  "type": "Feature",
  "properties": {
    "addr:full":"583 Little Britain Rd Lockport MB R1A 3T1",
    "addr:housenumber":"583",
    "addr:postcode":"r1a 3t1",
    "addr:street":"Little Britain Rd",
    "iso:country":"CA",
    "sg:address":"583 Little Britain Rd",
    "sg:city":"Lockport",
    "sg:classifiers":[
        {
            "category":"Building & Trades",
            "subcategory":"Construction",
            "type":"Services"
        }
    ],
    "sg:phone":"+1 204 757 2295",
    "sg:postcode":"R1A 3T1",
    "sg:province":"MB",
    "sg:tags":[
        "home",
        "builder",
        "general",
        "contractor"
    ],
    "wof:name":"Aldinger Construction Ltd",
    "wof:placetype":"venue"
},
  "geometry": {"coordinates":[-96.948402,50.101875],"type":"Point"}
}