{
  "type": "Feature",
  "properties": {
    "addr:full":"55 Progress Ave Scarborough ON M1P 2Y7",
    "addr:housenumber":"55",
    "addr:postcode":"m1p 2y7",
    "addr:street":"Progress Ave",
    "iso:country":"CA",
    "sg:address":"55 Progress Ave",
    "sg:city":"Scarborough",
    "sg:classifiers":[
        {
            "category":"Manufacturing",
            "subcategory":"Paper Products",
            "type":"Manufacturing & Wholesale Goods"
        }
    ],
    "sg:phone":"+1 416 298 6551",
    "sg:postcode":"M1P 2Y7",
    "sg:province":"ON",
    "sg:tags":[
        "mailing",
        "container"
    ],
    "wof:name":"Caraustar",
    "wof:placetype":"venue"
},
  "geometry": {"coordinates":[-79.2769622803,43.7708206177],"type":"Point"}
}