{
  "type": "Feature",
  "properties": {
    "addr:full":"1180 Branion Dr Prince Albert SK S6V 2S8",
    "addr:housenumber":"1180",
    "addr:postcode":"s6v 2s8",
    "addr:street":"Branion Dr",
    "iso:country":"CA",
    "sg:address":"1180 Branion Dr",
    "sg:city":"Prince Albert",
    "sg:classifiers":[
        {
            "category":"Education",
            "subcategory":"School",
            "type":"Public Place"
        }
    ],
    "sg:phone":"+1 306 953 7558",
    "sg:postcode":"S6V 2S8",
    "sg:province":"SK",
    "wof:name":"Wfa Turgeon Catholic School",
    "wof:placetype":"venue"
},
  "geometry": {"coordinates":[-105.72177124,53.1896438599],"type":"Point"}
}