{
  "type": "Feature",
  "properties": {
    "addr:full":"12 Dufferin Ave Chatham ON N7M 4W5",
    "addr:housenumber":"12",
    "addr:postcode":"n7m 4w5",
    "addr:street":"Dufferin Ave",
    "iso:country":"CA",
    "sg:address":"12 Dufferin Ave",
    "sg:city":"Chatham",
    "sg:classifiers":[
        {
            "category":"Organizations",
            "subcategory":"Religious Organization",
            "type":"Services"
        }
    ],
    "sg:phone":"+1 519 354 1310",
    "sg:postcode":"N7M 4W5",
    "sg:province":"ON",
    "sg:tags":[
        "church"
    ],
    "wof:name":"Park St United Church",
    "wof:placetype":"venue"
},
  "geometry": {"coordinates":[-82.1815414429,42.4014625549],"type":"Point"}
}