{
  "type": "Feature",
  "properties": {
    "iso:country":"CA",
    "sg:address":"1906 Wilson Ave",
    "sg:city":"North York",
    "sg:classifiers":[
        {
            "category":"Restaurant",
            "type":"Food & Drink"
        }
    ],
    "sg:phone":"+1 416 746 7109",
    "sg:postcode":"M9M 1A8",
    "sg:province":"ON",
    "wof:name":"B C Squad",
    "wof:placetype":"venue"
},
  "geometry": {"coordinates":[-79.5273361206,43.7168617249],"type":"Point"}
}