{
  "type": "Feature",
  "properties": {
    "addr:full":"250 Av Des Pins E Montreal QC H2W 1P3",
    "addr:housenumber":"250",
    "addr:postcode":"h2w 1p3",
    "addr:street":"Av Des Pins E",
    "iso:country":"CA",
    "sg:address":"250 Av Des Pins E",
    "sg:city":"Montreal",
    "sg:classifiers":[
        {
            "category":"Restaurant",
            "type":"Food & Drink"
        }
    ],
    "sg:phone":"+1 514 287 9127",
    "sg:postcode":"H2W 1P3",
    "sg:province":"QC",
    "wof:name":"Restaurant Laloux",
    "wof:placetype":"venue"
},
  "geometry": {"coordinates":[-73.57302856450001,45.5174102783],"type":"Point"}
}