{
  "type": "Feature",
  "properties": {
    "addr:full":"1664 Lakeshore Rd Sarnia ON N7X 1B8",
    "addr:housenumber":"1664",
    "addr:postcode":"n7x 1b8",
    "addr:street":"Lakeshore Rd",
    "iso:country":"CA",
    "sg:address":"1664 Lakeshore Rd",
    "sg:city":"Sarnia",
    "sg:classifiers":[
        {
            "category":"Building & Trades",
            "subcategory":"Construction",
            "type":"Services"
        }
    ],
    "sg:phone":"+1 519 542 4476",
    "sg:postcode":"N7X 1B8",
    "sg:province":"ON",
    "sg:tags":[
        "general",
        "contractor"
    ],
    "wof:name":"Ganter Construction Ltd",
    "wof:placetype":"venue"
},
  "geometry": {"coordinates":[-82.33045199999999,43.0214],"type":"Point"}
}