{
  "type": "Feature",
  "properties": {
    "iso:country":"CA",
    "sg:address":"1664 Lakeshore Rd",
    "sg:city":"Sarnia",
    "sg:classifiers":[
        {
            "category":"Building & Trades",
            "subcategory":"Construction",
            "type":"Services"
        }
    ],
    "sg:phone":"+1 519 542 4476",
    "sg:postcode":"N7X 1B8",
    "sg:province":"ON",
    "sg:tags":[
        "general",
        "contractor"
    ],
    "wof:name":"Ganter Construction Ltd",
    "wof:placetype":"venue"
},
  "geometry": {"coordinates":[-82.330452,43.0214],"type":"Point"}
}