{
  "type": "Feature",
  "properties": {
    "addr:full":"2530 Chemong Rd Peterborough ON K9J 6X2",
    "addr:housenumber":"2530",
    "addr:postcode":"k9j 6x2",
    "addr:street":"Chemong Rd",
    "iso:country":"CA",
    "sg:address":"2530 Chemong Rd",
    "sg:city":"Peterborough",
    "sg:classifiers":[
        {
            "category":"Retail",
            "subcategory":"Auto Repair",
            "type":"Services"
        }
    ],
    "sg:phone":"+1 705 292 6574",
    "sg:postcode":"K9J 6X2",
    "sg:province":"ON",
    "sg:tags":[
        "repairing",
        "automobile"
    ],
    "wof:name":"Linkert Auto Repairs & Towing",
    "wof:placetype":"venue"
},
  "geometry": {"coordinates":[-78.341881,44.329762],"type":"Point"}
}