{
  "type": "Feature",
  "properties": {
    "addr:full":"2176 Av Chapdelaine Sainte-Foy QC G1V 1N1",
    "addr:housenumber":"2176",
    "addr:postcode":"g1v 1n1",
    "addr:street":"Av Chapdelaine",
    "iso:country":"CA",
    "sg:address":"2176 Av Chapdelaine",
    "sg:city":"Sainte-Foy",
    "sg:classifiers":[
        {
            "category":"Real Estate",
            "subcategory":"Developer",
            "type":"Services"
        }
    ],
    "sg:phone":"+1 418 527 2975",
    "sg:postcode":"G1V 1N1",
    "sg:province":"QC",
    "sg:tags":[
        "cemetery"
    ],
    "wof:name":"Cimetiere Notre-Dame-Belmont",
    "wof:placetype":"venue"
},
  "geometry": {"coordinates":[-71.2750167847,46.7904205322],"type":"Point"}
}