{
  "type": "Feature",
  "properties": {
    "addr:full":"PO Box 372 STN Q Toronto ON M4T 2M5",
    "addr:housenumber":"po",
    "addr:postcode":"m4t 2m5",
    "addr:street":"Box 372 Stn Q",
    "iso:country":"CA",
    "sg:address":"PO Box 372 STN Q",
    "sg:city":"Toronto",
    "sg:classifiers":[
        {
            "category":"Organizations",
            "subcategory":"Professional Association",
            "type":"Services"
        }
    ],
    "sg:phone":"+1 416 486 9333",
    "sg:postcode":"M4T 2M5",
    "sg:province":"ON",
    "wof:name":"Canadian International Inst",
    "wof:placetype":"venue"
},
  "geometry": {"coordinates":[-79.3853302002,43.648563385],"type":"Point"}
}