{
  "type": "Feature",
  "properties": {
    "addr:full":"365 Bayly St W Ajax ON L1S 6M3",
    "addr:housenumber":"365",
    "addr:postcode":"l1s 6m3",
    "addr:street":"Bayly St W",
    "iso:country":"CA",
    "sg:address":"365 Bayly St W",
    "sg:city":"Ajax",
    "sg:classifiers":[
        {
            "category":"Autos & Motor Vehicles",
            "subcategory":"Automobile Sales",
            "type":"Retail Goods"
        }
    ],
    "sg:phone":"+1 905 428 0088",
    "sg:postcode":"L1S 6M3",
    "sg:province":"ON",
    "sg:tags":[
        "car",
        "dealer"
    ],
    "wof:name":"Ajax Mazda",
    "wof:placetype":"venue"
},
  "geometry": {"coordinates":[-79.031914,43.840839],"type":"Point"}
}