{
  "type": "Feature",
  "properties": {
    "addr:full":"347 Yonge St Toronto ON M5B 1S1",
    "addr:housenumber":"347",
    "addr:postcode":"m5b 1s1",
    "addr:street":"Yonge St",
    "iso:country":"CA",
    "sg:address":"347 Yonge St",
    "sg:city":"Toronto",
    "sg:classifiers":[
        {
            "category":"Shopping",
            "subcategory":"Music",
            "type":"Retail Goods"
        }
    ],
    "sg:phone":"+1 416 646 2775",
    "sg:postcode":"M5B 1S1",
    "sg:province":"ON",
    "sg:tags":[
        "compact",
        "record",
        "disc",
        "tape"
    ],
    "wof:name":"Sam the Record Man",
    "wof:placetype":"venue"
},
  "geometry": {"coordinates":[-79.38127900000001,43.657692],"type":"Point"}
}