{
  "type": "Feature",
  "properties": {
    "addr:full":"1st Level Uni Ctr Ottawa ON K1S 5B6",
    "addr:postcode":"k1s 5b6",
    "iso:country":"CA",
    "sg:address":"1st Level Uni Ctr",
    "sg:city":"Ottawa",
    "sg:classifiers":[
        {
            "category":"Travel",
            "subcategory":"Travel Agent",
            "type":"Entertainment"
        }
    ],
    "sg:phone":"+1 613 526 8015",
    "sg:postcode":"K1S 5B6",
    "sg:province":"ON",
    "sg:tags":[
        "agency",
        "bureau"
    ],
    "wof:name":"Travel Cuts",
    "wof:placetype":"venue"
},
  "geometry": {"coordinates":[-75.69636535639999,45.4014663696],"type":"Point"}
}