{
  "type": "Feature",
  "properties": {
    "addr:full":"203 John St Simcoe ON N3Y 2Y6",
    "addr:housenumber":"203",
    "addr:postcode":"n3y 2y6",
    "addr:street":"John St",
    "iso:country":"CA",
    "sg:address":"203 John St",
    "sg:city":"Simcoe",
    "sg:classifiers":[
        {
            "category":"Social Services",
            "subcategory":"Child Care",
            "type":"Services"
        }
    ],
    "sg:phone":"+1 519 428 2668",
    "sg:postcode":"N3Y 2Y6",
    "sg:province":"ON",
    "sg:tags":[
        "kindergarten",
        "academic",
        "school"
    ],
    "wof:name":"Montessori Children's Ctr",
    "wof:placetype":"venue"
},
  "geometry": {"coordinates":[-80.3046722412,42.8322563171],"type":"Point"}
}