{
  "type": "Feature",
  "properties": {
    "iso:country":"CA",
    "sg:address":"16740 111 Ave NW",
    "sg:city":"Edmonton",
    "sg:classifiers":[
        {
            "category":"Manufacturing",
            "subcategory":"Furniture",
            "type":"Manufacturing & Wholesale Goods"
        }
    ],
    "sg:phone":"+1 780 444 9425",
    "sg:postcode":"T5M 2S5",
    "sg:province":"AB",
    "sg:tags":[
        "equipment",
        "supply"
    ],
    "wof:name":"Legault Furniture Mfg",
    "wof:placetype":"venue"
},
  "geometry": {"coordinates":[-113.60975646999999,53.5596542358],"type":"Point"}
}