{
  "type": "Feature",
  "properties": {
    "addr:full":"St Albert AB T8N 1E4",
    "addr:postcode":"t8n 1e4",
    "iso:country":"CA",
    "sg:city":"St Albert",
    "sg:classifiers":[
        {
            "category":"Shopping",
            "subcategory":"Gifts & Souvenirs",
            "type":"Retail Goods"
        }
    ],
    "sg:phone":"+1 780 418 7803",
    "sg:postcode":"T8N 1E4",
    "sg:province":"AB",
    "sg:tags":[
        "shop"
    ],
    "wof:name":"Crimson Quill Gifts Inc",
    "wof:placetype":"venue"
},
  "geometry": {"coordinates":[-113.62532,53.63348],"type":"Point"}
}