{
  "type": "Feature",
  "properties": {
    "iso:country":"CA",
    "sg:address":"329 Collishaw St",
    "sg:city":"Moncton",
    "sg:classifiers":[
        {
            "category":"Wholesale",
            "subcategory":"Construction Materials",
            "type":"Manufacturing & Wholesale Goods"
        }
    ],
    "sg:phone":"+1 506 857 8886",
    "sg:postcode":"E1C 9R2",
    "sg:province":"NB",
    "sg:tags":[
        "concrete",
        "shape",
        "common",
        "block",
        "face"
    ],
    "wof:name":"Shaw Brick Store",
    "wof:placetype":"venue"
},
  "geometry": {"coordinates":[-64.8128128052,46.0971031189],"type":"Point"}
}