{
  "type": "Feature",
  "properties": {
    "addr:full":"14 Pepperwood Pl Brampton ON L6S 3R9",
    "addr:housenumber":"14",
    "addr:postcode":"l6s 3r9",
    "addr:street":"Pepperwood Pl",
    "iso:country":"CA",
    "sg:address":"14 Pepperwood Pl",
    "sg:city":"Brampton",
    "sg:classifiers":[
        {
            "category":"Personal",
            "subcategory":"Beauty Salon",
            "type":"Services"
        }
    ],
    "sg:phone":"+1 905 799 2177",
    "sg:postcode":"L6S 3R9",
    "sg:province":"ON",
    "wof:name":"Hair By Hazel",
    "wof:placetype":"venue"
},
  "geometry": {"coordinates":[-79.739364624,43.7415885925],"type":"Point"}
}