{
  "type": "Feature",
  "properties": {
    "addr:full":"11751 Bridgeport Rd Richmond BC V6X 1T5",
    "addr:housenumber":"11751",
    "addr:postcode":"v6x 1t5",
    "addr:street":"Bridgeport Rd",
    "iso:country":"CA",
    "sg:address":"11751 Bridgeport Rd",
    "sg:city":"Richmond",
    "sg:classifiers":[
        {
            "category":"Home & Garden",
            "subcategory":"Furniture",
            "type":"Retail Goods"
        }
    ],
    "sg:phone":"+1 604 273 9228",
    "sg:postcode":"V6X 1T5",
    "sg:province":"BC",
    "wof:name":"Maple Glass Furniture",
    "wof:placetype":"venue"
},
  "geometry": {"coordinates":[-123.09395600000001,49.192196],"type":"Point"}
}