{
  "type": "Feature",
  "properties": {
    "addr:full":"35 Rue Bridge Ormstown QC J0S 1K0",
    "addr:housenumber":"35",
    "addr:postcode":"j0s 1k0",
    "addr:street":"Rue Bridge",
    "iso:country":"CA",
    "sg:address":"35 Rue Bridge",
    "sg:city":"Ormstown",
    "sg:classifiers":[
        {
            "category":"Real Estate",
            "subcategory":"Real Estate Agent",
            "type":"Services"
        }
    ],
    "sg:phone":"+1 450 829 3841",
    "sg:postcode":"J0S 1K0",
    "sg:province":"QC",
    "sg:tags":[
        "tool",
        "agency",
        "rental"
    ],
    "wof:name":"Location D'Outils Ormstown Inc",
    "wof:placetype":"venue"
},
  "geometry": {"coordinates":[-73.992233,45.123581],"type":"Point"}
}