{
  "type": "Feature",
  "properties": {
    "addr:full":"Ocean Drive English Harbour West NL A0H 1M0",
    "addr:postcode":"a0h 1m0",
    "addr:street":"Ocean Drive English Harbour West",
    "iso:country":"CA",
    "sg:address":"Ocean Drive",
    "sg:city":"English Harbour West",
    "sg:classifiers":[
        {
            "category":"Government",
            "subcategory":"Office",
            "type":"Public Place"
        }
    ],
    "sg:phone":"+1 709 888 6141",
    "sg:postcode":"A0H 1M0",
    "sg:province":"NL",
    "sg:tags":[
        "municipality"
    ],
    "wof:name":"English Harbour West Town Cncl",
    "wof:placetype":"venue"
},
  "geometry": {"coordinates":[-55.504688,47.465828],"type":"Point"}
}