{
  "type": "Feature",
  "properties": {
    "addr:full":"5118 50 Ave Wetaskiwin AB T9A 0S6",
    "addr:housenumber":"5118",
    "addr:postcode":"t9a 0s6",
    "addr:street":"50 Ave",
    "iso:country":"CA",
    "sg:address":"5118 50 Ave",
    "sg:city":"Wetaskiwin",
    "sg:classifiers":[
        {
            "category":"Professional",
            "subcategory":"Lawyer & Legal Services",
            "type":"Services"
        }
    ],
    "sg:phone":"+1 780 352 6691",
    "sg:postcode":"T9A 0S6",
    "sg:province":"AB",
    "sg:tags":[
        "attorney"
    ],
    "wof:name":"Snowden, James D",
    "wof:placetype":"venue"
},
  "geometry": {"coordinates":[-113.376694,52.969997],"type":"Point"}
}