{
  "type": "Feature",
  "properties": {
    "addr:full":"1033 Ironwood St Campbell River BC V9W 5L6",
    "addr:housenumber":"1033",
    "addr:postcode":"v9w 5l6",
    "addr:street":"Ironwood St",
    "iso:country":"CA",
    "sg:address":"1033 Ironwood St",
    "sg:city":"Campbell River",
    "sg:classifiers":[
        {
            "category":"Autos & Motor Vehicles",
            "subcategory":"Auto Supplies",
            "type":"Retail Goods"
        }
    ],
    "sg:phone":"+1 250 287 7121",
    "sg:postcode":"V9W 5L6",
    "sg:province":"BC",
    "sg:tags":[
        "automobile",
        "parts"
    ],
    "wof:name":"Uap Napa Auto Parts",
    "wof:placetype":"venue"
},
  "geometry": {"coordinates":[-125.254807,50.025501],"type":"Point"}
}