{
  "type": "Feature",
  "properties": {
    "iso:country":"CA",
    "sg:address":"995 Rue Saint-Prosper",
    "sg:city":"Trois-Rivieres",
    "sg:classifiers":[
        {
            "category":"Food & Beverages",
            "subcategory":"Bakery",
            "type":"Retail Goods"
        }
    ],
    "sg:phone":"+1 819 694 9520",
    "sg:postcode":"G9A 3V7",
    "sg:province":"QC",
    "sg:tags":[
        "baker"
    ],
    "wof:name":"Panetier Enr",
    "wof:placetype":"venue"
},
  "geometry": {"coordinates":[-72.54508209230001,46.3464546204],"type":"Point"}
}