{
  "type": "Feature",
  "properties": {
    "iso:country":"CA",
    "sg:address":"238 Main St",
    "sg:city":"Selkirk",
    "sg:classifiers":[
        {
            "category":"Restaurant",
            "type":"Food & Drink"
        }
    ],
    "sg:phone":"+1 204 482 5417",
    "sg:postcode":"R1A 1S2",
    "sg:province":"MB",
    "wof:name":"A & W Family Restaurant",
    "wof:placetype":"venue"
},
  "geometry": {"coordinates":[-96.8807601929,50.1376724243],"type":"Point"}
}