{
  "type": "Feature",
  "properties": {
    "addr:full":"5880 Boul Gouin O Montreal QC H4J 1E4",
    "addr:housenumber":"5880",
    "addr:postcode":"h4j 1e4",
    "addr:street":"Boul Gouin O",
    "iso:country":"CA",
    "sg:address":"5880 Boul Gouin O",
    "sg:city":"Montreal",
    "sg:classifiers":[
        {
            "category":"Real Estate",
            "subcategory":"Real Estate Agent",
            "type":"Services"
        }
    ],
    "sg:phone":"+1 514 336 6530",
    "sg:postcode":"H4J 1E4",
    "sg:province":"QC",
    "wof:name":"Societe Immobiliere Y Bastien",
    "wof:placetype":"venue"
},
  "geometry": {"coordinates":[-73.72086299999999,45.531826],"type":"Point"}
}