{
  "type": "Feature",
  "properties": {
    "iso:country":"CA",
    "sg:address":"5880 Boul Gouin O",
    "sg:city":"Montreal",
    "sg:classifiers":[
        {
            "category":"Real Estate",
            "subcategory":"Real Estate Agent",
            "type":"Services"
        }
    ],
    "sg:phone":"+1 514 336 6530",
    "sg:postcode":"H4J 1E4",
    "sg:province":"QC",
    "wof:name":"Societe Immobiliere Y Bastien",
    "wof:placetype":"venue"
},
  "geometry": {"coordinates":[-73.720863,45.531826],"type":"Point"}
}