{
  "type": "Feature",
  "properties": {
    "addr:full":"578 Sackville Dr Lower Sackville NS B4C 2S3",
    "addr:housenumber":"578",
    "addr:postcode":"b4c 2s3",
    "addr:street":"Sackville Dr",
    "iso:country":"CA",
    "sg:address":"578 Sackville Dr",
    "sg:city":"Lower Sackville",
    "sg:classifiers":[
        {
            "category":"Food & Beverages",
            "subcategory":"Groceries & Convenience Stores",
            "type":"Retail Goods"
        }
    ],
    "sg:phone":"+1 902 865 9704",
    "sg:postcode":"B4C 2S3",
    "sg:province":"NS",
    "sg:tags":[
        "grocer"
    ],
    "wof:name":"Ultramar Corner Store",
    "wof:placetype":"venue"
},
  "geometry": {"coordinates":[-63.684879303,44.7677688599],"type":"Point"}
}