{
  "type": "Feature",
  "properties": {
    "addr:full":"4295 Rue Durocher Lachenaie QC J6V 1H1",
    "addr:housenumber":"4295",
    "addr:postcode":"j6v 1h1",
    "addr:street":"Rue Durocher",
    "iso:country":"CA",
    "sg:address":"4295 Rue Durocher",
    "sg:city":"Lachenaie",
    "sg:phone":"+1 450 654 9271",
    "sg:postcode":"J6V 1H1",
    "sg:province":"QC",
    "sg:tags":[
        "lubricant"
    ],
    "wof:name":"Amsoil",
    "wof:placetype":"venue"
},
  "geometry": {"coordinates":[-73.5196762085,45.7108612061],"type":"Point"}
}