{
  "type": "Feature",
  "properties": {
    "addr:full":"2275 Lake Shore Blvd W Etobicoke ON M8V 3Y3",
    "addr:housenumber":"2275",
    "addr:postcode":"m8v 3y3",
    "addr:street":"Lake Shore Blvd W",
    "iso:country":"CA",
    "sg:address":"2275 Lake Shore Blvd W",
    "sg:city":"Etobicoke",
    "sg:classifiers":[
        {
            "category":"Shopping",
            "subcategory":"Computers & Home Electronics",
            "type":"Retail Goods"
        }
    ],
    "sg:phone":"+1 416 253 1851",
    "sg:postcode":"M8V 3Y3",
    "sg:province":"ON",
    "sg:tags":[
        "software"
    ],
    "wof:name":"Saltspring Software",
    "wof:placetype":"venue"
},
  "geometry": {"coordinates":[-79.485237,43.619774],"type":"Point"}
}