{
  "type": "Feature",
  "properties": {
    "addr:full":"530 Broadway E Vancouver BC V5T 1X5",
    "addr:housenumber":"530",
    "addr:postcode":"v5t 1x5",
    "addr:street":"Broadway E",
    "iso:country":"CA",
    "sg:address":"530 Broadway E",
    "sg:city":"Vancouver",
    "sg:classifiers":[
        {
            "category":"Retail",
            "subcategory":"Auto Repair",
            "type":"Services"
        }
    ],
    "sg:phone":"+1 604 872 2211",
    "sg:postcode":"V5T 1X5",
    "sg:province":"BC",
    "sg:tags":[
        "repairing",
        "automobile"
    ],
    "wof:name":"M & N Auto Repair",
    "wof:placetype":"venue"
},
  "geometry": {"coordinates":[-123.092201233,49.2623748779],"type":"Point"}
}