{
  "type": "Feature",
  "properties": {
    "addr:full":"Yarmouth NS B5A 3H5",
    "addr:postcode":"b5a 3h5",
    "iso:country":"CA",
    "sg:city":"Yarmouth",
    "sg:classifiers":[
        {
            "category":"Insurance",
            "subcategory":"Insurance Agent",
            "type":"Services"
        }
    ],
    "sg:phone":"+1 902 742 2444",
    "sg:postcode":"B5A 3H5",
    "sg:province":"NS",
    "sg:tags":[
        "adjuster"
    ],
    "wof:name":"Marsh Adjustment Bureau Ltd",
    "wof:placetype":"venue"
},
  "geometry": {"coordinates":[-66.1188583374,43.8355903625],"type":"Point"}
}