{
  "type": "Feature",
  "properties": {
    "addr:full":"94 Cumberland St # 604 Toronto ON M5R 1A3",
    "addr:housenumber":"94",
    "addr:postcode":"m5r 1a3",
    "addr:street":"Cumberland St # 604",
    "iso:country":"CA",
    "sg:address":"94 Cumberland St # 604",
    "sg:city":"Toronto",
    "sg:classifiers":[
        {
            "category":"Professional",
            "subcategory":"Management & Consulting",
            "type":"Services"
        }
    ],
    "sg:phone":"+1 416 360 0177",
    "sg:postcode":"M5R 1A3",
    "sg:province":"ON",
    "sg:tags":[
        "consultant",
        "business"
    ],
    "wof:name":"Pervin Family Business Advsrs",
    "wof:placetype":"venue"
},
  "geometry": {"coordinates":[-79.3907318115,43.6704978943],"type":"Point"}
}