{
  "type": "Feature",
  "properties": {
    "addr:full":"218 2E Rang Wotton QC J0A 1N0",
    "addr:housenumber":"218",
    "addr:postcode":"j0a 1n0",
    "addr:street":"2E Rang",
    "iso:country":"CA",
    "sg:address":"218 2E Rang",
    "sg:city":"Wotton",
    "sg:classifiers":[
        {
            "category":"Farming",
            "subcategory":"Farm",
            "type":"Manufacturing & Wholesale Goods"
        }
    ],
    "sg:phone":"+1 819 828 1557",
    "sg:postcode":"J0A 1N0",
    "sg:province":"QC",
    "wof:name":"Bleuetiere",
    "wof:placetype":"venue"
},
  "geometry": {"coordinates":[-71.76490020750001,45.7612991333],"type":"Point"}
}