{
  "type": "Feature",
  "properties": {
    "addr:full":"919 Main St N Moose Jaw SK S6H 0W9",
    "addr:housenumber":"919",
    "addr:postcode":"s6h 0w9",
    "addr:street":"Main St N",
    "iso:country":"CA",
    "sg:address":"919 Main St N",
    "sg:city":"Moose Jaw",
    "sg:classifiers":[
        {
            "category":"Restaurant",
            "type":"Food & Drink"
        }
    ],
    "sg:phone":"+1 306 693 6242",
    "sg:postcode":"S6H 0W9",
    "sg:province":"SK",
    "wof:name":"Mr Sub",
    "wof:placetype":"venue"
},
  "geometry": {"coordinates":[-105.534454346,50.398109436],"type":"Point"}
}