{
  "type": "Feature",
  "properties": {
    "addr:full":"1754 Garrison Rd Fort Erie ON L2A 5M4",
    "addr:housenumber":"1754",
    "addr:postcode":"l2a 5m4",
    "addr:street":"Garrison Rd",
    "iso:country":"CA",
    "sg:address":"1754 Garrison Rd",
    "sg:city":"Fort Erie",
    "sg:classifiers":[
        {
            "category":"Shopping",
            "subcategory":"Department Store",
            "type":"Retail Goods"
        }
    ],
    "sg:phone":"+1 905 871 1482",
    "sg:postcode":"L2A 5M4",
    "sg:province":"ON",
    "sg:tags":[
        "shop"
    ],
    "wof:name":"Rosehill Auction House",
    "wof:placetype":"venue"
},
  "geometry": {"coordinates":[-78.9798660278,42.9043655396],"type":"Point"}
}