{
  "type": "Feature",
  "properties": {
    "addr:full":"6003 104 St NW Edmonton AB T6H 2K6",
    "addr:housenumber":"6003",
    "addr:postcode":"t6h 2k6",
    "addr:street":"104 St Nw",
    "iso:country":"CA",
    "sg:address":"6003 104 St NW",
    "sg:city":"Edmonton",
    "sg:classifiers":[
        {
            "category":"Retail",
            "subcategory":"Veterinary Services",
            "type":"Services"
        }
    ],
    "sg:phone":"+1 780 434 6462",
    "sg:postcode":"T6H 2K6",
    "sg:province":"AB",
    "sg:tags":[
        "veterinarian"
    ],
    "wof:name":"South Side Animal Hospital Ltd",
    "wof:placetype":"venue"
},
  "geometry": {"coordinates":[-113.497513,53.497139],"type":"Point"}
}