{
  "type": "Feature",
  "properties": {
    "addr:full":"3515 Mainway Burlington ON L7M 1A9",
    "addr:housenumber":"3515",
    "addr:postcode":"l7m 1a9",
    "addr:street":"Mainway",
    "iso:country":"CA",
    "sg:address":"3515 Mainway",
    "sg:city":"Burlington",
    "sg:classifiers":[
        {
            "category":"Professional",
            "subcategory":"Accounting & Tax Preparation",
            "type":"Services"
        }
    ],
    "sg:phone":"+1 905 319 3515",
    "sg:postcode":"L7M 1A9",
    "sg:province":"ON",
    "sg:tags":[
        "accountant"
    ],
    "wof:name":"Jones, Stephen D CA",
    "wof:placetype":"venue"
},
  "geometry": {"coordinates":[-79.797653,43.370247],"type":"Point"}
}