{
  "type": "Feature",
  "properties": {
    "addr:full":"300 Mystery Lake Rd Thompson MB R8N 0M2",
    "addr:housenumber":"300",
    "addr:postcode":"r8n 0m2",
    "addr:street":"Mystery Lake Rd",
    "iso:country":"CA",
    "sg:address":"300 Mystery Lake Rd",
    "sg:city":"Thompson",
    "sg:classifiers":[
        {
            "category":"Real Estate",
            "subcategory":"Real Estate Operator",
            "type":"Services"
        }
    ],
    "sg:phone":"+1 204 677 2113",
    "sg:postcode":"R8N 0M2",
    "sg:province":"MB",
    "sg:tags":[
        "mall",
        "shopping",
        "center"
    ],
    "wof:name":"City Centre Mall",
    "wof:placetype":"venue"
},
  "geometry": {"coordinates":[-97.850616,55.744637],"type":"Point"}
}