{
  "type": "Feature",
  "properties": {
    "addr:full":"887 Notre Dame Ave Sudbury ON P3A 2T2",
    "addr:housenumber":"887",
    "addr:postcode":"p3a 2t2",
    "addr:street":"Notre Dame Ave",
    "iso:country":"CA",
    "sg:address":"887 Notre Dame Ave",
    "sg:city":"Sudbury",
    "sg:classifiers":[
        {
            "category":"Autos & Motor Vehicles",
            "subcategory":"Automobile Sales",
            "type":"Retail Goods"
        }
    ],
    "sg:phone":"+1 705 560 8697",
    "sg:postcode":"P3A 2T2",
    "sg:province":"ON",
    "sg:tags":[
        "car",
        "dealer"
    ],
    "wof:name":"Crocco's Auto Toy Store",
    "wof:placetype":"venue"
},
  "geometry": {"coordinates":[-80.985069,46.515285],"type":"Point"}
}