{
  "type": "Feature",
  "properties": {
    "addr:full":"280 Metcalfe St # 203 Ottawa ON K2P 1R7",
    "addr:housenumber":"280",
    "addr:postcode":"k2p 1r7",
    "addr:street":"Metcalfe St # 203",
    "iso:country":"CA",
    "sg:address":"280 Metcalfe St # 203",
    "sg:city":"Ottawa",
    "sg:classifiers":[
        {
            "category":"Real Estate",
            "subcategory":"Architect",
            "type":"Services"
        }
    ],
    "sg:phone":"+1 613 565 9479",
    "sg:postcode":"K2P 1R7",
    "sg:province":"ON",
    "wof:name":"Temprano Young & Ward Arch Inc",
    "wof:placetype":"venue"
},
  "geometry": {"coordinates":[-75.6914901733,45.4157409668],"type":"Point"}
}