{
  "type": "Feature",
  "properties": {
    "addr:full":"288 Rue Des Bouleaux Charlemagne QC J5Z 3Z6",
    "addr:housenumber":"288",
    "addr:postcode":"j5z 3z6",
    "addr:street":"Rue Des Bouleaux",
    "iso:country":"CA",
    "sg:address":"288 Rue Des Bouleaux",
    "sg:city":"Charlemagne",
    "sg:classifiers":[
        {
            "category":"Manufacturing",
            "subcategory":"Tools & Machinery",
            "type":"Manufacturing & Wholesale Goods"
        }
    ],
    "sg:phone":"+1 450 654 5273",
    "sg:postcode":"J5Z 3Z6",
    "sg:province":"QC",
    "sg:tags":[
        "equipment",
        "system",
        "automation"
    ],
    "wof:name":"Automatisation Cilco Inc",
    "wof:placetype":"venue"
},
  "geometry": {"coordinates":[-73.496803,45.73444],"type":"Point"}
}