{
  "type": "Feature",
  "properties": {
    "iso:country":"CA",
    "sg:address":"67 Wharncliffe Rd N",
    "sg:city":"London",
    "sg:classifiers":[
        {
            "category":"Shopping",
            "subcategory":"Bicycles & Sporting Goods",
            "type":"Retail Goods"
        }
    ],
    "sg:phone":"+1 519 434 2611",
    "sg:postcode":"N6H 2A5",
    "sg:province":"ON",
    "wof:name":"Travel Sports Equipment",
    "wof:placetype":"venue"
},
  "geometry": {"coordinates":[-81.2626571655,42.983997345],"type":"Point"}
}