{
  "type": "Feature",
  "properties": {
    "addr:full":"5111 Rue DE Verdun Verdun QC H4G 1N7",
    "addr:housenumber":"5111",
    "addr:postcode":"h4g 1n7",
    "addr:street":"Rue De Verdun",
    "iso:country":"CA",
    "sg:address":"5111 Rue DE Verdun",
    "sg:city":"Verdun",
    "sg:classifiers":[
        {
            "category":"Shopping",
            "subcategory":"Shoes",
            "type":"Retail Goods"
        }
    ],
    "sg:phone":"+1 514 761 7652",
    "sg:postcode":"H4G 1N7",
    "sg:province":"QC",
    "wof:name":"Chaussures Pitt Ltee",
    "wof:placetype":"venue"
},
  "geometry": {"coordinates":[-73.5721588135,45.4554443359],"type":"Point"}
}