{
  "type": "Feature",
  "properties": {
    "addr:full":"28 Freshwater Rd St. John's NL A1C 2N3",
    "addr:housenumber":"28",
    "addr:postcode":"a1c 2n3",
    "addr:street":"Freshwater Rd",
    "iso:country":"CA",
    "sg:address":"28 Freshwater Rd",
    "sg:city":"St. John's",
    "sg:classifiers":[
        {
            "category":"Shopping",
            "subcategory":"Clothing, Apparel, & Fashions",
            "type":"Retail Goods"
        }
    ],
    "sg:phone":"+1 709 753 0281",
    "sg:postcode":"A1C 2N3",
    "sg:province":"NL",
    "sg:tags":[
        "tailor"
    ],
    "wof:name":"Tony's Tailor Shop",
    "wof:placetype":"venue"
},
  "geometry": {"coordinates":[-52.717022,47.563889],"type":"Point"}
}