{
  "type": "Feature",
  "properties": {
    "addr:full":"North York ON M3H 2T5",
    "addr:postcode":"m3h 2t5",
    "iso:country":"CA",
    "sg:city":"North York",
    "sg:classifiers":[
        {
            "category":"Personal",
            "subcategory":"Beauty Salon",
            "type":"Services"
        }
    ],
    "sg:phone":"+1 416 633 0111",
    "sg:postcode":"M3H 2T5",
    "sg:province":"ON",
    "sg:tags":[
        "spa",
        "day"
    ],
    "wof:name":"Sunflower Spa & Salon",
    "wof:placetype":"venue"
},
  "geometry": {"coordinates":[-79.456237793,43.7518997192],"type":"Point"}
}