{
  "type": "Feature",
  "properties": {
    "addr:full":"428 Rue Du Baron-Louis-Empain Sainte-Marguerite-Esterel QC J0T 1L0",
    "addr:housenumber":"428",
    "addr:postcode":"j0t 1l0",
    "addr:street":"Rue Du Baron-Louis-Empain Sainte-Marguerite-Esterel",
    "iso:country":"CA",
    "sg:address":"428 Rue Du Baron-Louis-Empain",
    "sg:city":"Sainte-Marguerite-Esterel",
    "sg:classifiers":[
        {
            "category":"Social Services",
            "type":"Services"
        }
    ],
    "sg:phone":"+1 450 228 2502",
    "sg:postcode":"J0T 1L0",
    "sg:province":"QC",
    "sg:tags":[
        "organization",
        "wedding",
        "site",
        "reception",
        "welfare"
    ],
    "wof:name":"Clsc-Chsld Des Pays-D",
    "wof:placetype":"venue"
},
  "geometry": {"coordinates":[-74.018959,46.042545],"type":"Point"}
}