{
  "type": "Feature",
  "properties": {
    "addr:full":"PO Box 653 STN Main Leamington ON N8H 3X4",
    "addr:housenumber":"po",
    "addr:postcode":"n8h 3x4",
    "addr:street":"Box 653 Stn Main",
    "iso:country":"CA",
    "sg:address":"PO Box 653 STN Main",
    "sg:city":"Leamington",
    "sg:classifiers":[
        {
            "category":"Local Transit",
            "type":"Transportation"
        }
    ],
    "sg:phone":"+1 519 326 1945",
    "sg:postcode":"N8H 3X4",
    "sg:province":"ON",
    "sg:tags":[
        "limousine"
    ],
    "wof:name":"Red Rose Limousine Svc",
    "wof:placetype":"venue"
},
  "geometry": {"coordinates":[-82.599716,42.054153],"type":"Point"}
}