{
  "type": "Feature",
  "properties": {
    "addr:full":"Barrhead AB T7N 1N2",
    "addr:postcode":"t7n 1n2",
    "iso:country":"CA",
    "sg:city":"Barrhead",
    "sg:classifiers":[
        {
            "category":"Retail",
            "subcategory":"Veterinary Services",
            "type":"Services"
        }
    ],
    "sg:phone":"+1 780 674 5335",
    "sg:postcode":"T7N 1N2",
    "sg:province":"AB",
    "sg:tags":[
        "veterinarian"
    ],
    "wof:name":"Barrhead Veterinary Clinic",
    "wof:placetype":"venue"
},
  "geometry": {"coordinates":[-114.406005859,54.1209907532],"type":"Point"}
}