{
  "type": "Feature",
  "properties": {
    "addr:full":"13616 Hwy 1 Wilmot Station NS B0P 1W0",
    "addr:housenumber":"13616",
    "addr:postcode":"b0p 1w0",
    "addr:street":"Hwy 1 Wilmot Station",
    "iso:country":"CA",
    "sg:address":"13616 Hwy 1",
    "sg:city":"Wilmot Station",
    "sg:classifiers":[
        {
            "category":"Restaurant",
            "type":"Food & Drink"
        }
    ],
    "sg:phone":"+1 902 825 4526",
    "sg:postcode":"B0P 1W0",
    "sg:province":"NS",
    "wof:name":"Big Scoop Family Restaurant",
    "wof:placetype":"venue"
},
  "geometry": {"coordinates":[-65.06317138670001,44.9753684998],"type":"Point"}
}