{
  "type": "Feature",
  "properties": {
    "addr:full":"312 W 1st St Revelstoke BC V0E 2S0",
    "addr:housenumber":"312",
    "addr:postcode":"v0e 2s0",
    "addr:street":"W 1St St",
    "iso:country":"CA",
    "sg:address":"312 W 1st St",
    "sg:city":"Revelstoke",
    "sg:classifiers":[
        {
            "category":"Bars & Pubs",
            "type":"Food & Drink"
        }
    ],
    "sg:phone":"+1 250 837 5799",
    "sg:postcode":"V0E 2S0",
    "sg:province":"BC",
    "sg:tags":[
        "club",
        "night"
    ],
    "wof:name":"Rock Pit",
    "wof:placetype":"venue"
},
  "geometry": {"coordinates":[-118.196907044,50.999912262],"type":"Point"}
}