{
  "type": "Feature",
  "properties": {
    "addr:full":"4393 Av Bonaventure Shawinigan QC G9N 3G6",
    "addr:housenumber":"4393",
    "addr:postcode":"g9n 3g6",
    "addr:street":"Av Bonaventure",
    "iso:country":"CA",
    "sg:address":"4393 Av Bonaventure",
    "sg:city":"Shawinigan",
    "sg:classifiers":[
        {
            "category":"Social Services",
            "type":"Services"
        }
    ],
    "sg:phone":"+1 819 539 3034",
    "sg:postcode":"G9N 3G6",
    "sg:province":"QC",
    "sg:tags":[
        "senior",
        "citizen"
    ],
    "wof:name":"Centre Des Aines DE Shawinigan",
    "wof:placetype":"venue"
},
  "geometry": {"coordinates":[-72.735206604,46.5695953369],"type":"Point"}
}