{
  "type": "Feature",
  "properties": {
    "addr:full":"16 Rue Sainte-Anne Quebec QC G1R 3X2",
    "addr:housenumber":"16",
    "addr:postcode":"g1r 3x2",
    "addr:street":"Rue Sainte-Anne",
    "iso:country":"CA",
    "sg:address":"16 Rue Sainte-Anne",
    "sg:city":"Quebec",
    "sg:classifiers":[
        {
            "category":"Restaurant",
            "type":"Food & Drink"
        }
    ],
    "sg:phone":"+1 418 694 9063",
    "sg:postcode":"G1R 3X2",
    "sg:province":"QC",
    "wof:name":"Au Relais DE LA Place D'Armes",
    "wof:placetype":"venue"
},
  "geometry": {"coordinates":[-71.205696106,46.8130874634],"type":"Point"}
}