{
  "type": "Feature",
  "properties": {
    "iso:country":"CA",
    "sg:address":"766 14 St SW",
    "sg:city":"Medicine Hat",
    "sg:classifiers":[
        {
            "category":"Shopping",
            "subcategory":"Bicycles & Sporting Goods",
            "type":"Retail Goods"
        }
    ],
    "sg:phone":"+1 403 526 4170",
    "sg:postcode":"T1A 4V7",
    "sg:province":"AB",
    "sg:tags":[
        "equipment",
        "playground"
    ],
    "wof:name":"Blue Imp Playground Equipment",
    "wof:placetype":"venue"
},
  "geometry": {"coordinates":[-110.704093933,50.0262908936],"type":"Point"}
}