{
  "type": "Feature",
  "properties": {
    "addr:full":"293 Bay St Sault Ste Marie ON P6A 1X3",
    "addr:housenumber":"293",
    "addr:postcode":"p6a 1x3",
    "addr:street":"Bay St",
    "iso:country":"CA",
    "sg:address":"293 Bay St",
    "sg:city":"Sault Ste Marie",
    "sg:classifiers":[
        {
            "category":"Shopping",
            "subcategory":"Shoes",
            "type":"Retail Goods"
        }
    ],
    "sg:phone":"+1 705 945 0964",
    "sg:postcode":"P6A 1X3",
    "sg:province":"ON",
    "wof:name":"Foot Locker",
    "wof:placetype":"venue"
},
  "geometry": {"coordinates":[-84.3378448486,46.5131263733],"type":"Point"}
}