{
  "type": "Feature",
  "properties": {
    "addr:full":"1335 Draycott Rd North Vancouver BC V7J 1W1",
    "addr:housenumber":"1335",
    "addr:postcode":"v7j 1w1",
    "addr:street":"Draycott Rd",
    "iso:country":"CA",
    "sg:address":"1335 Draycott Rd",
    "sg:city":"North Vancouver",
    "sg:classifiers":[
        {
            "category":"Home & Garden",
            "subcategory":"Building Materials",
            "type":"Retail Goods"
        }
    ],
    "sg:phone":"+1 604 986 5281",
    "sg:postcode":"V7J 1W1",
    "sg:province":"BC",
    "sg:tags":[
        "lumber"
    ],
    "wof:name":"Woodstop Building Supplies Ltd",
    "wof:placetype":"venue"
},
  "geometry": {"coordinates":[-123.037468,49.33699],"type":"Point"}
}