{
  "type": "Feature",
  "properties": {
    "iso:country":"CA",
    "sg:address":"9017 Widder Rd",
    "sg:city":"Thedford",
    "sg:classifiers":[
        {
            "category":"Manufacturing",
            "subcategory":"Lumber",
            "type":"Manufacturing & Wholesale Goods"
        }
    ],
    "sg:phone":"+1 519 296 4760",
    "sg:postcode":"N0M 2N0",
    "sg:province":"ON",
    "wof:name":"Thompson Hardwoods of Thedfrd",
    "wof:placetype":"venue"
},
  "geometry": {"coordinates":[-81.84303283689999,43.1724128723],"type":"Point"}
}