{
  "type": "Feature",
  "properties": {
    "addr:full":"4780 50 Ave SE Calgary AB T2B 3R4",
    "addr:housenumber":"4780",
    "addr:postcode":"t2b 3r4",
    "addr:street":"50 Ave Se",
    "iso:country":"CA",
    "sg:address":"4780 50 Ave SE",
    "sg:city":"Calgary",
    "sg:classifiers":[
        {
            "category":"Building & Trades",
            "subcategory":"Electrical",
            "type":"Services"
        }
    ],
    "sg:phone":"+1 403 720 0505",
    "sg:postcode":"T2B 3R4",
    "sg:province":"AB",
    "sg:tags":[
        "electric",
        "contractor"
    ],
    "wof:name":"Pyramid Corp",
    "wof:placetype":"venue"
},
  "geometry": {"coordinates":[-113.963485718,51.008895874],"type":"Point"}
}