{
  "type": "Feature",
  "properties": {
    "addr:full":"Calgary AB T2P 4H4",
    "addr:postcode":"t2p 4h4",
    "iso:country":"CA",
    "sg:city":"Calgary",
    "sg:classifiers":[
        {
            "category":"Insurance",
            "subcategory":"Insurance Agent",
            "type":"Services"
        }
    ],
    "sg:phone":"+1 403 290 7900",
    "sg:postcode":"T2P 4H4",
    "sg:province":"AB",
    "wof:name":"Marsh Canada",
    "wof:placetype":"venue"
},
  "geometry": {"coordinates":[-114.066169739,51.0494995117],"type":"Point"}
}