{
  "type": "Feature",
  "properties": {
    "addr:full":"1140 Rue Paul-Courteau Joliette QC J6E 2J7",
    "addr:housenumber":"1140",
    "addr:postcode":"j6e 2j7",
    "addr:street":"Rue Paul-Courteau",
    "iso:country":"CA",
    "sg:address":"1140 Rue Paul-Courteau",
    "sg:city":"Joliette",
    "sg:classifiers":[
        {
            "category":"Building & Trades",
            "subcategory":"Construction",
            "type":"Services"
        }
    ],
    "sg:phone":"+1 450 756 4946",
    "sg:postcode":"J6E 2J7",
    "sg:province":"QC",
    "sg:tags":[
        "painter"
    ],
    "wof:name":"Remillard, Christian",
    "wof:placetype":"venue"
},
  "geometry": {"coordinates":[-73.46086120610001,46.0239677429],"type":"Point"}
}