{
  "type": "Feature",
  "properties": {
    "addr:full":"PO Box 816 Bon Accord AB T0A 0K0",
    "addr:housenumber":"po",
    "addr:postcode":"t0a 0k0",
    "addr:street":"Box 816",
    "iso:country":"CA",
    "sg:address":"PO Box 816",
    "sg:city":"Bon Accord",
    "sg:classifiers":[
        {
            "category":"Organizations",
            "subcategory":"Religious Organization",
            "type":"Services"
        }
    ],
    "sg:phone":"+1 403 921 2505",
    "sg:postcode":"T0A 0K0",
    "sg:province":"AB",
    "sg:tags":[
        "church"
    ],
    "wof:name":"St Mary Anglican Church",
    "wof:placetype":"venue"
},
  "geometry": {"coordinates":[-113.410797,53.837276],"type":"Point"}
}