{
  "type": "Feature",
  "properties": {
    "iso:country":"CA",
    "sg:address":"9 Smith Ave",
    "sg:city":"Guelph",
    "sg:classifiers":[
        {
            "category":"Retail",
            "subcategory":"Auto Repair",
            "type":"Services"
        }
    ],
    "sg:phone":"+1 519 821 0351",
    "sg:postcode":"N1E 5V4",
    "sg:province":"ON",
    "sg:tags":[
        "transmission"
    ],
    "wof:name":"M & N Motors",
    "wof:placetype":"venue"
},
  "geometry": {"coordinates":[-80.2292251587,43.5499153137],"type":"Point"}
}