{
  "type": "Feature",
  "properties": {
    "addr:full":"7 Main St Hwy 59 Tolstoi MB R0A 2E0",
    "addr:housenumber":"7",
    "addr:postcode":"r0a 2e0",
    "addr:street":"Main St Hwy 59 Tolstoi",
    "iso:country":"CA",
    "sg:address":"7 Main St Hwy 59",
    "sg:city":"Tolstoi",
    "sg:classifiers":[
        {
            "category":"Food & Beverages",
            "subcategory":"Groceries & Convenience Stores",
            "type":"Retail Goods"
        }
    ],
    "sg:phone":"+1 204 427 2155",
    "sg:postcode":"R0A 2E0",
    "sg:province":"MB",
    "sg:tags":[
        "grocer"
    ],
    "wof:name":"Tolstoi Super Mart",
    "wof:placetype":"venue"
},
  "geometry": {"coordinates":[-96.80847199999999,49.08762],"type":"Point"}
}