{
  "type": "Feature",
  "properties": {
    "addr:full":"710 Rue Des Veterans Pointe-Au-Pere QC G5M 1G9",
    "addr:housenumber":"710",
    "addr:postcode":"g5m 1g9",
    "addr:street":"Rue Des Veterans Pointe-Au-Pere",
    "iso:country":"CA",
    "sg:address":"710 Rue Des Veterans",
    "sg:city":"Pointe-Au-Pere",
    "sg:classifiers":[
        {
            "category":"Manufacturing",
            "subcategory":"Signs",
            "type":"Manufacturing & Wholesale Goods"
        }
    ],
    "sg:phone":"+1 418 722 6093",
    "sg:postcode":"G5M 1G9",
    "sg:province":"QC",
    "sg:tags":[
        "painter"
    ],
    "wof:name":"Paul Coulombe Enr",
    "wof:placetype":"venue"
},
  "geometry": {"coordinates":[-68.46928405760001,48.5021247864],"type":"Point"}
}