{
  "type": "Feature",
  "properties": {
    "addr:full":"1978 Ch Woburn Lac-Megantic QC G6B 2S1",
    "addr:housenumber":"1978",
    "addr:postcode":"g6b 2s1",
    "addr:street":"Ch Woburn Lac-Megantic",
    "iso:country":"CA",
    "sg:address":"1978 Ch Woburn",
    "sg:city":"Lac-Megantic",
    "sg:classifiers":[
        {
            "category":"Retail",
            "subcategory":"Portrait Studio",
            "type":"Services"
        }
    ],
    "sg:phone":"+1 819 583 4945",
    "sg:postcode":"G6B 2S1",
    "sg:province":"QC",
    "sg:tags":[
        "photographer"
    ],
    "wof:name":"Studio Pierre Tetrault",
    "wof:placetype":"venue"
},
  "geometry": {"coordinates":[-70.880173,45.572571],"type":"Point"}
}