{
  "type": "Feature",
  "properties": {
    "iso:country":"CA",
    "sg:address":"3460 39E Av",
    "sg:city":"Pointe-Aux-Trembles",
    "sg:classifiers":[
        {
            "category":"Manufacturing",
            "subcategory":"Soap",
            "type":"Manufacturing & Wholesale Goods"
        }
    ],
    "sg:phone":"+1 514 642 9920",
    "sg:postcode":"H1A 3V1",
    "sg:province":"QC",
    "sg:tags":[
        "detergent"
    ],
    "wof:name":"Savons Evy Inc",
    "wof:placetype":"venue"
},
  "geometry": {"coordinates":[-73.508789,45.66291],"type":"Point"}
}