{
  "type": "Feature",
  "properties": {
    "addr:full":"11131 Bridgeport Rd Richmond BC V6X 1T3",
    "addr:housenumber":"11131",
    "addr:postcode":"v6x 1t3",
    "addr:street":"Bridgeport Rd",
    "iso:country":"CA",
    "sg:address":"11131 Bridgeport Rd",
    "sg:city":"Richmond",
    "sg:classifiers":[
        {
            "category":"Organizations",
            "subcategory":"Community Association",
            "type":"Services"
        }
    ],
    "sg:phone":"+1 604 278 6423",
    "sg:postcode":"V6X 1T3",
    "sg:province":"BC",
    "sg:tags":[
        "fraternal"
    ],
    "wof:name":"Royal Canadian Legion 209",
    "wof:placetype":"venue"
},
  "geometry": {"coordinates":[-123.100662231,49.1921424866],"type":"Point"}
}