{
  "type": "Feature",
  "properties": {
    "addr:full":"St George Brant ON N0E 1N0",
    "addr:postcode":"n0e 1n0",
    "addr:street":"St",
    "iso:country":"CA",
    "sg:city":"St George Brant",
    "sg:classifiers":[
        {
            "category":"Professional",
            "subcategory":"Engineering",
            "type":"Services"
        }
    ],
    "sg:phone":"+1 519 448 1610",
    "sg:postcode":"N0E 1N0",
    "sg:province":"ON",
    "sg:tags":[
        "engineer"
    ],
    "wof:name":"David C Batchelor Engineering",
    "wof:placetype":"venue"
},
  "geometry": {"coordinates":[-80.4266586304,43.1024703979],"type":"Point"}
}