{
  "type": "Feature",
  "properties": {
    "addr:full":"3179 5 Ave N Lethbridge AB T1H 0P2",
    "addr:housenumber":"3179",
    "addr:postcode":"t1h 0p2",
    "addr:street":"5 Ave N",
    "iso:country":"CA",
    "sg:address":"3179 5 Ave N",
    "sg:city":"Lethbridge",
    "sg:classifiers":[
        {
            "category":"Building & Trades",
            "subcategory":"Equipment Rental",
            "type":"Services"
        }
    ],
    "sg:phone":"+1 403 380 2422",
    "sg:postcode":"T1H 0P2",
    "sg:province":"AB",
    "sg:tags":[
        "material",
        "yard",
        "handling"
    ],
    "wof:name":"R & B Forklift Svc",
    "wof:placetype":"venue"
},
  "geometry": {"coordinates":[-112.79413604699999,49.7056274414],"type":"Point"}
}