{
  "type": "Feature",
  "properties": {
    "addr:full":"2200 South Sheridan Way Mississauga ON L5J 2M4",
    "addr:housenumber":"2200",
    "addr:postcode":"l5j 2m4",
    "addr:street":"South Sheridan Way",
    "iso:country":"CA",
    "sg:address":"2200 South Sheridan Way",
    "sg:city":"Mississauga",
    "sg:classifiers":[
        {
            "category":"Shopping",
            "subcategory":"Books",
            "type":"Retail Goods"
        }
    ],
    "sg:phone":"+1 905 403 8406",
    "sg:postcode":"L5J 2M4",
    "sg:province":"ON",
    "sg:tags":[
        "dealer"
    ],
    "wof:name":"Isna Canada Islamic Book",
    "wof:placetype":"venue"
},
  "geometry": {"coordinates":[-79.6506347656,43.5209159851],"type":"Point"}
}