{
  "type": "Feature",
  "properties": {
    "addr:full":"Cap-DE-LA-Madeleine QC G8T 7B2",
    "addr:postcode":"g8t 7b2",
    "iso:country":"CA",
    "sg:city":"Cap-DE-LA-Madeleine",
    "sg:classifiers":[
        {
            "category":"Retail",
            "subcategory":"Auto Repair",
            "type":"Services"
        }
    ],
    "sg:phone":"+1 819 375 4106",
    "sg:postcode":"G8T 7B2",
    "sg:province":"QC",
    "sg:tags":[
        "transmission",
        "automobile",
        "repairing"
    ],
    "wof:name":"Garage Boissonneault Trnsmssn",
    "wof:placetype":"venue"
},
  "geometry": {"coordinates":[-72.554222,46.390392],"type":"Point"}
}