{
  "type": "Feature",
  "properties": {
    "iso:country":"CA",
    "sg:address":"1076 Topsail Rd",
    "sg:city":"Mount Pearl",
    "sg:classifiers":[
        {
            "category":"Wholesale",
            "subcategory":"Machinery & Supplies",
            "type":"Manufacturing & Wholesale Goods"
        }
    ],
    "sg:phone":"+1 709 747 2850",
    "sg:postcode":"A1N 5E7",
    "sg:province":"NL",
    "sg:tags":[
        "sprinkler"
    ],
    "wof:name":"Viking Fire Protection Inc",
    "wof:placetype":"venue"
},
  "geometry": {"coordinates":[-52.8149452209,47.5262756348],"type":"Point"}
}