{
  "type": "Feature",
  "properties": {
    "iso:country":"CA",
    "sg:address":"2685 Concession Rd",
    "sg:city":"Kemptville",
    "sg:classifiers":[
        {
            "category":"Social Services",
            "type":"Services"
        }
    ],
    "sg:phone":"+1 613 258 5941",
    "sg:postcode":"K0G 1J0",
    "sg:province":"ON",
    "sg:tags":[
        "organization",
        "welfare"
    ],
    "wof:name":"Leeds & Grenville Health Unit",
    "wof:placetype":"venue"
},
  "geometry": {"coordinates":[-75.6414108276,45.0095748901],"type":"Point"}
}