{
  "type": "Feature",
  "properties": {
    "addr:full":"652 Columbia St New Westminster BC V3M 1A9",
    "addr:housenumber":"652",
    "addr:postcode":"v3m 1a9",
    "addr:street":"Columbia",
    "iso:country":"CA",
    "sg:address":"652 Columbia St",
    "sg:city":"New Westminster",
    "sg:classifiers":[
        {
            "category":"Bars & Pubs",
            "type":"Food & Drink"
        }
    ],
    "sg:phone":"+1 604 526 8675",
    "sg:postcode":"V3M 1A9",
    "sg:province":"BC",
    "sg:tags":[
        "club",
        "night"
    ],
    "wof:name":"Paramount",
    "wof:placetype":"venue"
},
  "geometry": {"coordinates":[-122.908951,49.202423],"type":"Point"}
}