{
  "type": "Feature",
  "properties": {
    "addr:full":"2825 21st St S Cranbrook BC V1C 6Y9",
    "addr:housenumber":"2825",
    "addr:postcode":"v1c 6y9",
    "addr:street":"21St St S",
    "iso:country":"CA",
    "sg:address":"2825 21st St S",
    "sg:city":"Cranbrook",
    "sg:classifiers":[
        {
            "category":"Retail",
            "subcategory":"Repair Shop",
            "type":"Services"
        }
    ],
    "sg:phone":"+1 250 426 4210",
    "sg:postcode":"V1C 6Y9",
    "sg:province":"BC",
    "sg:tags":[
        "upholsterer"
    ],
    "wof:name":"Gold Creek Upholstery",
    "wof:placetype":"venue"
},
  "geometry": {"coordinates":[-115.752396,49.500332],"type":"Point"}
}