{
  "type": "Feature",
  "properties": {
    "addr:full":"Calgary AB T2K 5J4",
    "addr:postcode":"t2k 5j4",
    "iso:country":"CA",
    "sg:city":"Calgary",
    "sg:classifiers":[
        {
            "category":"Personal",
            "subcategory":"Beauty Salon",
            "type":"Services"
        }
    ],
    "sg:phone":"+1 403 274 3041",
    "sg:postcode":"T2K 5J4",
    "sg:province":"AB",
    "wof:name":"Ruth Elsasser Hair Care",
    "wof:placetype":"venue"
},
  "geometry": {"coordinates":[-114.076889038,51.1111946106],"type":"Point"}
}