{
  "type": "Feature",
  "properties": {
    "addr:full":"2300 Ch Sainte-Foy Sainte-Foy QC G1V 1S5",
    "addr:postcode":"2300;g1v 1s5",
    "addr:street":"Ch Sainte-Foy",
    "iso:country":"CA",
    "sg:address":"2300 Ch Sainte-Foy",
    "sg:city":"Sainte-Foy",
    "sg:classifiers":[
        {
            "category":"Travel",
            "subcategory":"Hotels & Motels",
            "type":"Entertainment"
        }
    ],
    "sg:phone":"+1 418 653 5250",
    "sg:postcode":"G1V 1S5",
    "sg:province":"QC",
    "wof:name":"Motel Universel Inc",
    "wof:placetype":"venue"
},
  "geometry": {"coordinates":[-71.2917633057,46.7692108154],"type":"Point"}
}