{
  "type": "Feature",
  "properties": {
    "addr:full":"7142 Fisher St SE Calgary AB T2H 0W5",
    "addr:housenumber":"7142",
    "addr:postcode":"t2h 0w5",
    "addr:street":"Fisher St Se",
    "iso:country":"CA",
    "sg:address":"7142 Fisher St SE",
    "sg:city":"Calgary",
    "sg:classifiers":[
        {
            "category":"Wholesale",
            "subcategory":"Auto Parts",
            "type":"Manufacturing & Wholesale Goods"
        }
    ],
    "sg:phone":"+1 403 252 2224",
    "sg:postcode":"T2H 0W5",
    "sg:province":"AB",
    "sg:tags":[
        "automobile",
        "supply"
    ],
    "wof:name":"Glenmore Auto Parts Ltd",
    "wof:placetype":"venue"
},
  "geometry": {"coordinates":[-114.069328,50.990875],"type":"Point"}
}