{
  "type": "Feature",
  "properties": {
    "addr:full":"975 Main St E Hawkesbury ON K6A 1B5",
    "addr:housenumber":"975",
    "addr:postcode":"k6a 1b5",
    "addr:street":"Main St E",
    "iso:country":"CA",
    "sg:address":"975 Main St E",
    "sg:city":"Hawkesbury",
    "sg:classifiers":[
        {
            "category":"Recreation",
            "subcategory":"Marina",
            "type":"Entertainment"
        }
    ],
    "sg:phone":"+1 613 632 7832",
    "sg:postcode":"K6A 1B5",
    "sg:province":"ON",
    "wof:name":"Golden Anchor Marina",
    "wof:placetype":"venue"
},
  "geometry": {"coordinates":[-74.5940856934,45.6105918884],"type":"Point"}
}