{
  "type": "Feature",
  "properties": {
    "addr:full":"52 Queen St W #2 Cookstown ON L0L 1L0",
    "addr:housenumber":"52",
    "addr:postcode":"l0l 1l0",
    "addr:street":"Queen St W # 2",
    "iso:country":"CA",
    "sg:address":"52 Queen St W #2",
    "sg:city":"Cookstown",
    "sg:classifiers":[
        {
            "category":"Shopping",
            "subcategory":"Pharmacy",
            "type":"Retail Goods"
        }
    ],
    "sg:phone":"+1 705 458 1292",
    "sg:postcode":"L0L 1L0",
    "sg:province":"ON",
    "wof:name":"Pharmasave",
    "wof:placetype":"venue"
},
  "geometry": {"coordinates":[-79.7076721191,44.1887588501],"type":"Point"}
}