{
  "type": "Feature",
  "properties": {
    "addr:full":"328 Lower Ganges Rd Salt Spring Island BC V8K 2V3",
    "addr:housenumber":"328",
    "addr:postcode":"v8k 2v3",
    "addr:street":"Lower Ganges Rd",
    "iso:country":"CA",
    "sg:address":"328 Lower Ganges Rd",
    "sg:city":"Salt Spring Island",
    "sg:classifiers":[
        {
            "category":"Manufacturing",
            "subcategory":"Printing",
            "type":"Manufacturing & Wholesale Goods"
        }
    ],
    "sg:phone":"+1 250 537 9933",
    "sg:postcode":"V8K 2V3",
    "sg:province":"BC",
    "sg:tags":[
        "newspaper"
    ],
    "wof:name":"Gulf Islands Driftwood",
    "wof:placetype":"venue"
},
  "geometry": {"coordinates":[-123.508499,48.859562],"type":"Point"}
}