{
  "type": "Feature",
  "properties": {
    "addr:full":"100 Goldeye Cres Thompson MB R8N 1L5",
    "addr:housenumber":"100",
    "addr:postcode":"r8n 1l5",
    "addr:street":"Goldeye Cres",
    "iso:country":"CA",
    "sg:address":"100 Goldeye Cres",
    "sg:city":"Thompson",
    "sg:classifiers":[
        {
            "category":"Organizations",
            "subcategory":"Professional Association",
            "type":"Services"
        }
    ],
    "sg:phone":"+1 204 778 7273",
    "sg:postcode":"R8N 1L5",
    "sg:province":"MB",
    "sg:tags":[
        "counselor",
        "marriage",
        "family"
    ],
    "wof:name":"Thompson Crisis Ctr",
    "wof:placetype":"venue"
},
  "geometry": {"coordinates":[-97.8761978149,55.7431907654],"type":"Point"}
}