{
  "type": "Feature",
  "properties": {
    "addr:full":"1193 Rue DE L'Escale Havre-Saint-Pierre QC G0G 1P0",
    "addr:housenumber":"1193",
    "addr:postcode":"g0g 1p0",
    "addr:street":"Rue De",
    "iso:country":"CA",
    "sg:address":"1193 Rue DE L'Escale",
    "sg:city":"Havre-Saint-Pierre",
    "sg:classifiers":[
        {
            "category":"Autos & Motor Vehicles",
            "subcategory":"Fuel & Gas Station",
            "type":"Retail Goods"
        }
    ],
    "sg:phone":"+1 418 538 3174",
    "sg:postcode":"G0G 1P0",
    "sg:province":"QC",
    "sg:tags":[
        "oil"
    ],
    "wof:name":"Garage Egb Inc",
    "wof:placetype":"venue"
},
  "geometry": {"coordinates":[-63.6045303345,50.2447509766],"type":"Point"}
}