{
  "type": "Feature",
  "properties": {
    "addr:full":"759 Dundas St London ON N5W 2Z6",
    "addr:housenumber":"759",
    "addr:postcode":"n5w 2z6",
    "addr:street":"Dundas St",
    "iso:country":"CA",
    "sg:address":"759 Dundas St",
    "sg:city":"London",
    "sg:classifiers":[
        {
            "category":"Retail",
            "subcategory":"Repair Shop",
            "type":"Services"
        }
    ],
    "sg:phone":"+1 519 432 9910",
    "sg:postcode":"N5W 2Z6",
    "sg:province":"ON",
    "sg:tags":[
        "upholsterer"
    ],
    "wof:name":"Canada Upholstery",
    "wof:placetype":"venue"
},
  "geometry": {"coordinates":[-81.2259979248,42.9903144836],"type":"Point"}
}