{
  "type": "Feature",
  "properties": {
    "iso:country":"CA",
    "sg:address":"46 13th Ave S",
    "sg:city":"Cranbrook",
    "sg:classifiers":[
        {
            "category":"Organizations",
            "subcategory":"Religious Organization",
            "type":"Services"
        }
    ],
    "sg:phone":"+1 250 426 2644",
    "sg:postcode":"V1C 2V3",
    "sg:province":"BC",
    "sg:tags":[
        "church"
    ],
    "wof:name":"Christ Anglican Church",
    "wof:placetype":"venue"
},
  "geometry": {"coordinates":[-115.763168335,49.5109710693],"type":"Point"}
}