{
  "type": "Feature",
  "properties": {
    "addr:full":"220 Midridge Cres SE Calgary AB T2X 1C6",
    "addr:housenumber":"220",
    "addr:postcode":"t2x 1c6",
    "addr:street":"Midridge Cres Se",
    "iso:country":"CA",
    "sg:address":"220 Midridge Cres SE",
    "sg:city":"Calgary",
    "sg:classifiers":[
        {
            "category":"Building & Trades",
            "subcategory":"Plumbing",
            "type":"Services"
        }
    ],
    "sg:phone":"+1 403 201 4160",
    "sg:postcode":"T2X 1C6",
    "sg:province":"AB",
    "sg:tags":[
        "contractor"
    ],
    "wof:name":"Kuharski Plumbing & Heating",
    "wof:placetype":"venue"
},
  "geometry": {"coordinates":[-114.05806,50.917065],"type":"Point"}
}