{
  "type": "Feature",
  "properties": {
    "addr:full":"3855 Rue DE Mentana Montreal QC H2L 3R7",
    "addr:housenumber":"3855",
    "addr:postcode":"h2l 3r7",
    "addr:street":"Rue De Mentana",
    "iso:country":"CA",
    "sg:address":"3855 Rue DE Mentana",
    "sg:city":"Montreal",
    "sg:classifiers":[
        {
            "category":"Professional",
            "subcategory":"Management & Consulting",
            "type":"Services"
        }
    ],
    "sg:phone":"+1 514 521 8583",
    "sg:postcode":"H2L 3R7",
    "sg:province":"QC",
    "sg:tags":[
        "consultant",
        "business"
    ],
    "wof:name":"Synergie-Gestion Inc",
    "wof:placetype":"venue"
},
  "geometry": {"coordinates":[-73.57028200000001,45.522743],"type":"Point"}
}