{
  "type": "Feature",
  "properties": {
    "iso:country":"CA",
    "sg:address":"3855 Rue DE Mentana",
    "sg:city":"Montreal",
    "sg:classifiers":[
        {
            "category":"Professional",
            "subcategory":"Management & Consulting",
            "type":"Services"
        }
    ],
    "sg:phone":"+1 514 521 8583",
    "sg:postcode":"H2L 3R7",
    "sg:province":"QC",
    "sg:tags":[
        "consultant",
        "business"
    ],
    "wof:name":"Synergie-Gestion Inc",
    "wof:placetype":"venue"
},
  "geometry": {"coordinates":[-73.570282,45.522743],"type":"Point"}
}