{
  "type": "Feature",
  "properties": {
    "addr:full":"20 South Water St Minden ON K0M 2K0",
    "addr:housenumber":"20",
    "addr:postcode":"k0m 2k0",
    "addr:street":"South Water St",
    "iso:country":"CA",
    "sg:address":"20 South Water St",
    "sg:city":"Minden",
    "sg:classifiers":[
        {
            "category":"Food & Beverages",
            "subcategory":"Liquor & Beverages",
            "type":"Retail Goods"
        }
    ],
    "sg:phone":"+1 705 286 1480",
    "sg:postcode":"K0M 2K0",
    "sg:province":"ON",
    "sg:tags":[
        "beer",
        "ale"
    ],
    "wof:name":"Beer Store",
    "wof:placetype":"venue"
},
  "geometry": {"coordinates":[-78.7227935791,44.9279708862],"type":"Point"}
}