{
  "type": "Feature",
  "properties": {
    "addr:full":"1640 Cedar Hill Cross Rd Victoria BC V8P 2P6",
    "addr:housenumber":"1640",
    "addr:postcode":"v8p 2p6",
    "addr:street":"Cedar Hill Cross Rd",
    "iso:country":"CA",
    "sg:address":"1640 Cedar Hill Cross Rd",
    "sg:city":"Victoria",
    "sg:classifiers":[
        {
            "category":"Shopping",
            "type":"Retail Goods"
        }
    ],
    "sg:phone":"+1 250 477 5621",
    "sg:postcode":"V8P 2P6",
    "sg:province":"BC",
    "sg:tags":[
        "picture",
        "frame",
        "art",
        "gallery",
        "dealer"
    ],
    "wof:name":"Framing & Art Ctr",
    "wof:placetype":"venue"
},
  "geometry": {"coordinates":[-123.36451700000001,48.428314],"type":"Point"}
}