{
  "type": "Feature",
  "properties": {
    "addr:full":"Carbonear NL A1Y 1A6",
    "addr:postcode":"a1y 1a6",
    "iso:country":"CA",
    "sg:city":"Carbonear",
    "sg:classifiers":[
        {
            "category":"Insurance",
            "subcategory":"Insurance Agent",
            "type":"Services"
        }
    ],
    "sg:phone":"+1 709 596 5031",
    "sg:postcode":"A1Y 1A6",
    "sg:province":"NL",
    "sg:tags":[
        "consultant"
    ],
    "wof:name":"Anthony Insurance Inc",
    "wof:placetype":"venue"
},
  "geometry": {"coordinates":[-53.2454719543,47.7262496948],"type":"Point"}
}