{
  "type": "Feature",
  "properties": {
    "addr:full":"6 Garland Ave Garland MB R0L 0W0",
    "addr:housenumber":"6",
    "addr:postcode":"r0l 0w0",
    "addr:street":"Garland Ave",
    "iso:country":"CA",
    "sg:address":"6 Garland Ave",
    "sg:city":"Garland",
    "sg:classifiers":[
        {
            "category":"Recreation",
            "type":"Entertainment"
        }
    ],
    "sg:phone":"+1 204 742 8853",
    "sg:postcode":"R0L 0W0",
    "sg:province":"MB",
    "sg:tags":[
        "hall",
        "auditorium"
    ],
    "wof:name":"Garland Community Ctr",
    "wof:placetype":"venue"
},
  "geometry": {"coordinates":[-100.459213257,51.6529045105],"type":"Point"}
}