{
  "type": "Feature",
  "properties": {
    "addr:full":"Toronto ON M4W 1A5",
    "addr:postcode":"m4w 1a5",
    "iso:country":"CA",
    "sg:city":"Toronto",
    "sg:classifiers":[
        {
            "category":"Shopping",
            "subcategory":"Optical Goods",
            "type":"Retail Goods"
        }
    ],
    "sg:phone":"+1 416 923 9585",
    "sg:postcode":"M4W 1A5",
    "sg:province":"ON",
    "sg:tags":[
        "optician"
    ],
    "wof:name":"Hollenberg Opticians",
    "wof:placetype":"venue"
},
  "geometry": {"coordinates":[-79.3886795044,43.6696853638],"type":"Point"}
}