{
  "type": "Feature",
  "properties": {
    "addr:full":"Mascouche QC J7L 1Z5",
    "addr:postcode":"j7l 1z5",
    "iso:country":"CA",
    "sg:city":"Mascouche",
    "sg:classifiers":[
        {
            "category":"Building & Trades",
            "subcategory":"Construction",
            "type":"Services"
        }
    ],
    "sg:phone":"+1 450 477 0542",
    "sg:postcode":"J7L 1Z5",
    "sg:province":"QC",
    "sg:tags":[
        "excavating",
        "contractor"
    ],
    "wof:name":"R Bouchard Excavation Inc",
    "wof:placetype":"venue"
},
  "geometry": {"coordinates":[-73.6650848389,45.7423324585],"type":"Point"}
}