{
  "type": "Feature",
  "properties": {
    "addr:full":"315 Mcallister Dr Saint John NB E2J 2S8",
    "addr:housenumber":"315",
    "addr:postcode":"e2j 2s8",
    "addr:street":"Mcallister Dr",
    "iso:country":"CA",
    "sg:address":"315 Mcallister Dr",
    "sg:city":"Saint John",
    "sg:classifiers":[
        {
            "category":"Retail",
            "subcategory":"Auto Rental",
            "type":"Services"
        }
    ],
    "sg:phone":"+1 506 648 1424",
    "sg:postcode":"E2J 2S8",
    "sg:province":"NB",
    "sg:tags":[
        "renting",
        "truck",
        "leasing"
    ],
    "wof:name":"Nagle Idealease",
    "wof:placetype":"venue"
},
  "geometry": {"coordinates":[-66.0136795044,45.3095474243],"type":"Point"}
}