{
  "type": "Feature",
  "properties": {
    "addr:full":"9803 63 Ave NW Edmonton AB T6E 0G7",
    "addr:housenumber":"9803",
    "addr:postcode":"t6e 0g7",
    "addr:street":"63 Ave Nw",
    "iso:country":"CA",
    "sg:address":"9803 63 Ave NW",
    "sg:city":"Edmonton",
    "sg:classifiers":[
        {
            "category":"Wholesale",
            "subcategory":"Sporting Goods",
            "type":"Manufacturing & Wholesale Goods"
        }
    ],
    "sg:phone":"+1 780 448 2606",
    "sg:postcode":"T6E 0G7",
    "sg:province":"AB",
    "sg:tags":[
        "equipment",
        "pool",
        "swimming"
    ],
    "wof:name":"Leisure World Distributors",
    "wof:placetype":"venue"
},
  "geometry": {"coordinates":[-113.483215,53.499611],"type":"Point"}
}