{
  "type": "Feature",
  "properties": {
    "addr:full":"6638 Bow Cres NW Calgary AB T3B 2B9",
    "addr:housenumber":"6638",
    "addr:postcode":"t3b 2b9",
    "addr:street":"Bow Cres Nw",
    "iso:country":"CA",
    "sg:address":"6638 Bow Cres NW",
    "sg:city":"Calgary",
    "sg:classifiers":[
        {
            "category":"Professional",
            "subcategory":"Lawyer & Legal Services",
            "type":"Services"
        }
    ],
    "sg:phone":"+1 403 286 6380",
    "sg:postcode":"T3B 2B9",
    "sg:province":"AB",
    "sg:tags":[
        "attorney"
    ],
    "wof:name":"Portigal, L S",
    "wof:placetype":"venue"
},
  "geometry": {"coordinates":[-114.183723,51.088573],"type":"Point"}
}