{
  "type": "Feature",
  "properties": {
    "addr:full":"3981 Rue Des Peupliers LA Dore QC G8J 1E4",
    "addr:housenumber":"3981",
    "addr:postcode":"g8j 1e4",
    "addr:street":"Rue Des Peupliers La Dore",
    "iso:country":"CA",
    "sg:address":"3981 Rue Des Peupliers",
    "sg:city":"LA Dore",
    "sg:classifiers":[
        {
            "category":"Restaurant",
            "type":"Food & Drink"
        }
    ],
    "sg:phone":"+1 418 256 3994",
    "sg:postcode":"G8J 1E4",
    "sg:province":"QC",
    "wof:name":"Restaurant Le Routier 167",
    "wof:placetype":"venue"
},
  "geometry": {"coordinates":[-72.63774100000001,48.703274],"type":"Point"}
}