{
  "type": "Feature",
  "properties": {
    "addr:full":"6 Rue Perreault Levis QC G6V 5J5",
    "addr:housenumber":"6",
    "addr:postcode":"g6v 5j5",
    "addr:street":"Rue Perreault",
    "iso:country":"CA",
    "sg:address":"6 Rue Perreault",
    "sg:city":"Levis",
    "sg:classifiers":[
        {
            "category":"Retail",
            "subcategory":"Funeral Services",
            "type":"Services"
        }
    ],
    "sg:phone":"+1 418 839 8823",
    "sg:postcode":"G6V 5J5",
    "sg:province":"QC",
    "sg:tags":[
        "director"
    ],
    "wof:name":"Claude Marcoux Ltee",
    "wof:placetype":"venue"
},
  "geometry": {"coordinates":[-71.17817687989999,46.8111877441],"type":"Point"}
}