{
  "type": "Feature",
  "properties": {
    "addr:full":"2049 Pine St Burlington ON L7R 1E9",
    "addr:housenumber":"2049",
    "addr:postcode":"l7r 1e9",
    "addr:street":"Pine St",
    "iso:country":"CA",
    "sg:address":"2049 Pine St",
    "sg:city":"Burlington",
    "sg:classifiers":[
        {
            "category":"Banks & Credit Unions",
            "subcategory":"Investment Brokerage",
            "type":"Services"
        }
    ],
    "sg:phone":"+1 905 631 9559",
    "sg:postcode":"L7R 1E9",
    "sg:province":"ON",
    "wof:name":"Edward Jones",
    "wof:placetype":"venue"
},
  "geometry": {"coordinates":[-79.79531860349999,43.326084137],"type":"Point"}
}