{
  "type": "Feature",
  "properties": {
    "iso:country":"CA",
    "sg:address":"270 Spadina Rd E",
    "sg:city":"Kitchener",
    "sg:classifiers":[
        {
            "category":"Building & Trades",
            "subcategory":"Construction",
            "type":"Services"
        }
    ],
    "sg:phone":"+1 519 578 7120",
    "sg:postcode":"N2M 3X8",
    "sg:province":"ON",
    "sg:tags":[
        "general",
        "contractor"
    ],
    "wof:name":"Reliable Construction",
    "wof:placetype":"venue"
},
  "geometry": {"coordinates":[-80.492111,43.43903],"type":"Point"}
}