{
  "type": "Feature",
  "properties": {
    "addr:full":"270 Spadina Rd E Kitchener ON N2M 3X8",
    "addr:housenumber":"270",
    "addr:postcode":"n2m 3x8",
    "addr:street":"Spadina Rd E",
    "iso:country":"CA",
    "sg:address":"270 Spadina Rd E",
    "sg:city":"Kitchener",
    "sg:classifiers":[
        {
            "category":"Building & Trades",
            "subcategory":"Construction",
            "type":"Services"
        }
    ],
    "sg:phone":"+1 519 578 7120",
    "sg:postcode":"N2M 3X8",
    "sg:province":"ON",
    "sg:tags":[
        "general",
        "contractor"
    ],
    "wof:name":"Reliable Construction",
    "wof:placetype":"venue"
},
  "geometry": {"coordinates":[-80.49211099999999,43.43903],"type":"Point"}
}