{
  "type": "Feature",
  "properties": {
    "addr:full":"1380 Rue Gilford Montreal QC H2J 1R7",
    "addr:housenumber":"1380",
    "addr:postcode":"h2j 1r7",
    "addr:street":"Rue Gilford",
    "iso:country":"CA",
    "sg:address":"1380 Rue Gilford",
    "sg:city":"Montreal",
    "sg:classifiers":[
        {
            "category":"Shopping",
            "subcategory":"Used Merchandise",
            "type":"Retail Goods"
        }
    ],
    "sg:phone":"+1 514 523 8280",
    "sg:postcode":"H2J 1R7",
    "sg:province":"QC",
    "sg:tags":[
        "item",
        "boutique"
    ],
    "wof:name":"Boutique Petits Freres Des",
    "wof:placetype":"venue"
},
  "geometry": {"coordinates":[-73.5801696777,45.5320243835],"type":"Point"}
}