{
  "type": "Feature",
  "properties": {
    "addr:full":"17600 Yonge St Newmarket ON L3Y 4Z1",
    "addr:housenumber":"17600",
    "addr:postcode":"l3y 4z1",
    "addr:street":"Yonge St",
    "iso:country":"CA",
    "sg:address":"17600 Yonge St",
    "sg:city":"Newmarket",
    "sg:classifiers":[
        {
            "category":"Shopping",
            "type":"Retail Goods"
        }
    ],
    "sg:phone":"+1 905 836 4934",
    "sg:postcode":"L3Y 4Z1",
    "sg:province":"ON",
    "sg:tags":[
        "pet",
        "food",
        "supply"
    ],
    "wof:name":"Doogan's Pet Ctr",
    "wof:placetype":"venue"
},
  "geometry": {"coordinates":[-79.4811096191,44.057056427],"type":"Point"}
}