{
  "type": "Feature",
  "properties": {
    "iso:country":"CA",
    "sg:city":"Kitchener",
    "sg:classifiers":[
        {
            "category":"Shopping",
            "subcategory":"Florist",
            "type":"Retail Goods"
        }
    ],
    "sg:phone":"+1 519 743 9812",
    "sg:postcode":"N2E 2M6",
    "sg:province":"ON",
    "wof:name":"Flowers By Sears",
    "wof:placetype":"venue"
},
  "geometry": {"coordinates":[-80.5013656616,43.418964386],"type":"Point"}
}