{
  "type": "Feature",
  "properties": {
    "iso:country":"CA",
    "sg:address":"53 Millview Pk SW",
    "sg:city":"Calgary",
    "sg:classifiers":[
        {
            "category":"Food & Beverages",
            "subcategory":"Specialty",
            "type":"Retail Goods"
        }
    ],
    "sg:phone":"+1 403 281 7924",
    "sg:postcode":"T2Y 3Y3",
    "sg:province":"AB",
    "sg:tags":[
        "health",
        "cleaning",
        "diet",
        "compound"
    ],
    "wof:name":"Ae Gladman & Assoc Shaklee",
    "wof:placetype":"venue"
},
  "geometry": {"coordinates":[-114.09734344500001,50.9192314148],"type":"Point"}
}