{
  "type": "Feature",
  "properties": {
    "iso:country":"CA",
    "sg:address":"280 Penetanguishene Rd",
    "sg:city":"Barrie",
    "sg:classifiers":[
        {
            "category":"Wholesale",
            "subcategory":"Machinery & Supplies",
            "type":"Manufacturing & Wholesale Goods"
        }
    ],
    "sg:phone":"+1 705 728 2752",
    "sg:postcode":"L4M 7C2",
    "sg:province":"ON",
    "sg:tags":[
        "farm",
        "equipment"
    ],
    "wof:name":"Partridge Tractor Svc",
    "wof:placetype":"venue"
},
  "geometry": {"coordinates":[-79.64692687989999,44.4114685059],"type":"Point"}
}