{
  "type": "Feature",
  "properties": {
    "addr:full":"367 Bering Ave Etobicoke ON M8Z 3B1",
    "addr:housenumber":"367",
    "addr:postcode":"m8z 3b1",
    "addr:street":"Bering Ave",
    "iso:country":"CA",
    "sg:address":"367 Bering Ave",
    "sg:city":"Etobicoke",
    "sg:classifiers":[
        {
            "category":"Retail",
            "subcategory":"Repair Shop",
            "type":"Services"
        }
    ],
    "sg:phone":"+1 416 231 7831",
    "sg:postcode":"M8Z 3B1",
    "sg:province":"ON",
    "sg:tags":[
        "ironwork",
        "railing"
    ],
    "wof:name":"Imperial Railing",
    "wof:placetype":"venue"
},
  "geometry": {"coordinates":[-79.5315628052,43.6369171143],"type":"Point"}
}