{
  "type": "Feature",
  "properties": {
    "addr:full":"1572 Rue Baillargeon Saint-Luc QC J2W 2B4",
    "addr:housenumber":"1572",
    "addr:postcode":"j2w 2b4",
    "addr:street":"Rue Baillargeon",
    "iso:country":"CA",
    "sg:address":"1572 Rue Baillargeon",
    "sg:city":"Saint-Luc",
    "sg:classifiers":[
        {
            "category":"Food & Beverages",
            "subcategory":"Groceries & Convenience Stores",
            "type":"Retail Goods"
        }
    ],
    "sg:phone":"+1 450 349 5272",
    "sg:postcode":"J2W 2B4",
    "sg:province":"QC",
    "sg:tags":[
        "grocer"
    ],
    "wof:name":"Depanneur Alimentation L'Ile",
    "wof:placetype":"venue"
},
  "geometry": {"coordinates":[-73.25463104249999,45.3749847412],"type":"Point"}
}