{
  "type": "Feature",
  "properties": {
    "addr:full":"29 Faulkland Rd Scarborough ON M1L 3S4",
    "addr:housenumber":"29",
    "addr:postcode":"m1l 3s4",
    "addr:street":"Faulkland Rd",
    "iso:country":"CA",
    "sg:address":"29 Faulkland Rd",
    "sg:city":"Scarborough",
    "sg:classifiers":[
        {
            "category":"Manufacturing",
            "subcategory":"Rubber & Plastics",
            "type":"Manufacturing & Wholesale Goods"
        }
    ],
    "sg:phone":"+1 416 757 6229",
    "sg:postcode":"M1L 3S4",
    "sg:province":"ON",
    "sg:tags":[
        "mold",
        "maker"
    ],
    "wof:name":"F & H Plastics Ltd",
    "wof:placetype":"venue"
},
  "geometry": {"coordinates":[-79.291321,43.718422],"type":"Point"}
}