{
  "type": "Feature",
  "properties": {
    "addr:full":"Delta BC V4G 1J5",
    "addr:postcode":"v4g 1j5",
    "iso:country":"CA",
    "sg:city":"Delta",
    "sg:classifiers":[
        {
            "category":"Wholesale",
            "subcategory":"Machinery & Supplies",
            "type":"Manufacturing & Wholesale Goods"
        }
    ],
    "sg:phone":"+1 604 930 2300",
    "sg:postcode":"V4G 1J5",
    "sg:province":"BC",
    "sg:tags":[
        "contractor"
    ],
    "wof:name":"Diamond Equipment Group Inc",
    "wof:placetype":"venue"
},
  "geometry": {"coordinates":[-122.940941,49.150291],"type":"Point"}
}