{
  "type": "Feature",
  "properties": {
    "addr:full":"59 Burnt Hill Rd Burnt Hill NB E3L 5T5",
    "addr:housenumber":"59",
    "addr:postcode":"e3l 5t5",
    "addr:street":"Burnt Hill Rd",
    "iso:country":"CA",
    "sg:address":"59 Burnt Hill Rd",
    "sg:city":"Burnt Hill",
    "sg:classifiers":[
        {
            "category":"Building & Trades",
            "subcategory":"Construction",
            "type":"Services"
        }
    ],
    "sg:phone":"+1 506 466 0114",
    "sg:postcode":"E3L 5T5",
    "sg:province":"NB",
    "sg:tags":[
        "general",
        "contractor"
    ],
    "wof:name":"W R Burns Construction Contr",
    "wof:placetype":"venue"
},
  "geometry": {"coordinates":[-67.35322600000001,45.160084],"type":"Point"}
}