{
  "type": "Feature",
  "properties": {
    "iso:country":"CA",
    "sg:city":"Brampton",
    "sg:classifiers":[
        {
            "category":"Wholesale",
            "subcategory":"Medical Equipment & Supplies",
            "type":"Manufacturing & Wholesale Goods"
        }
    ],
    "sg:phone":"+1 905 794 1112",
    "sg:postcode":"L6T 4S5",
    "sg:province":"ON",
    "sg:tags":[
        "home",
        "hospital",
        "health"
    ],
    "wof:name":"Cims Home Health Care",
    "wof:placetype":"venue"
},
  "geometry": {"coordinates":[-79.7182769775,43.7218399048],"type":"Point"}
}