{
  "type": "Feature",
  "properties": {
    "addr:full":"330 Dundurn St S Hamilton ON L8P 4L6",
    "addr:housenumber":"330",
    "addr:postcode":"l8p 4l6",
    "addr:street":"Dundurn St S",
    "iso:country":"CA",
    "sg:address":"330 Dundurn St S",
    "sg:city":"Hamilton",
    "sg:classifiers":[
        {
            "category":"Health Services",
            "subcategory":"Nursing And Care Facility",
            "type":"Services"
        }
    ],
    "sg:phone":"+1 905 529 3163",
    "sg:postcode":"L8P 4L6",
    "sg:province":"ON",
    "sg:tags":[
        "home",
        "retirement",
        "community"
    ],
    "wof:name":"Aberdeen Gardens",
    "wof:placetype":"venue"
},
  "geometry": {"coordinates":[-79.89269299999999,43.251671],"type":"Point"}
}