{
  "type": "Feature",
  "properties": {
    "addr:full":"North York ON M9L 2A5",
    "addr:postcode":"m9l 2a5",
    "iso:country":"CA",
    "sg:city":"North York",
    "sg:classifiers":[
        {
            "category":"Retail",
            "subcategory":"Auto Repair",
            "type":"Services"
        }
    ],
    "sg:phone":"+1 416 743 1303",
    "sg:postcode":"M9L 2A5",
    "sg:province":"ON",
    "sg:tags":[
        "repairing",
        "automobile"
    ],
    "wof:name":"S S Auto Repair",
    "wof:placetype":"venue"
},
  "geometry": {"coordinates":[-79.565918,43.760994],"type":"Point"}
}