{
  "type": "Feature",
  "properties": {
    "addr:full":"4542 14 St NE Calgary AB T2E 6T7",
    "addr:housenumber":"4542",
    "addr:postcode":"t2e 6t7",
    "addr:street":"14 St Ne",
    "iso:country":"CA",
    "sg:address":"4542 14 St NE",
    "sg:city":"Calgary",
    "sg:phone":"+1 403 250 7228",
    "sg:postcode":"T2E 6T7",
    "sg:province":"AB",
    "sg:tags":[
        "scale"
    ],
    "wof:name":"Pacific Industrial Scale CO",
    "wof:placetype":"venue"
},
  "geometry": {"coordinates":[-114.02866400000001,51.092426],"type":"Point"}
}