{
  "type": "Feature",
  "properties": {
    "addr:full":"Cranbrook BC V1C 1T5",
    "addr:postcode":"v1c 1t5",
    "iso:country":"CA",
    "sg:city":"Cranbrook",
    "sg:classifiers":[
        {
            "category":"Real Estate",
            "subcategory":"Real Estate Operator",
            "type":"Services"
        }
    ],
    "sg:phone":"+1 250 426 6419",
    "sg:postcode":"V1C 1T5",
    "sg:province":"BC",
    "sg:tags":[
        "mobile",
        "home",
        "community"
    ],
    "wof:name":"Hycrest Mobile Home Park",
    "wof:placetype":"venue"
},
  "geometry": {"coordinates":[-115.755554199,49.4998550415],"type":"Point"}
}