{
  "type": "Feature",
  "properties": {
    "addr:full":"5609 Birch Ave Vegreville AB T9C 1J7",
    "addr:housenumber":"5609",
    "addr:postcode":"t9c 1j7",
    "addr:street":"Birch Ave",
    "iso:country":"CA",
    "sg:address":"5609 Birch Ave",
    "sg:city":"Vegreville",
    "sg:classifiers":[
        {
            "category":"Retail",
            "subcategory":"Auto Repair",
            "type":"Services"
        }
    ],
    "sg:phone":"+1 780 632 3880",
    "sg:postcode":"T9C 1J7",
    "sg:province":"AB",
    "sg:tags":[
        "glass",
        "coating",
        "tinting"
    ],
    "wof:name":"A-Vegreville Glass & Mirror CO",
    "wof:placetype":"venue"
},
  "geometry": {"coordinates":[-112.060386658,53.5010948181],"type":"Point"}
}