{
  "type": "Feature",
  "properties": {
    "addr:full":"Fleurimont QC J1G 5G6",
    "addr:postcode":"j1g 5g6",
    "iso:country":"CA",
    "sg:city":"Fleurimont",
    "sg:classifiers":[
        {
            "category":"Insurance",
            "subcategory":"Insurance Agent",
            "type":"Services"
        }
    ],
    "sg:phone":"+1 819 569 7453",
    "sg:postcode":"J1G 5G6",
    "sg:province":"QC",
    "wof:name":"Assur Experts Estrie Inc",
    "wof:placetype":"venue"
},
  "geometry": {"coordinates":[-71.842567,45.411163],"type":"Point"}
}