{
  "type": "Feature",
  "properties": {
    "addr:full":"1035 Rue DE LA Visitation Saint-Charles-Borromee QC J6E 7Y8",
    "addr:housenumber":"1035",
    "addr:postcode":"j6e 7y8",
    "addr:street":"Rue De La Visitation Saint-Charles-Borromee",
    "iso:country":"CA",
    "sg:address":"1035 Rue DE LA Visitation",
    "sg:city":"Saint-Charles-Borromee",
    "sg:classifiers":[
        {
            "category":"Autos & Motor Vehicles",
            "subcategory":"Recreational Vehicle Sales",
            "type":"Retail Goods"
        }
    ],
    "sg:phone":"+1 450 759 5807",
    "sg:postcode":"J6E 7Y8",
    "sg:province":"QC",
    "sg:tags":[
        "automobile",
        "dealer"
    ],
    "wof:name":"Automobiles Mario Lafreniere",
    "wof:placetype":"venue"
},
  "geometry": {"coordinates":[-73.485382,46.062366],"type":"Point"}
}