{
  "type": "Feature",
  "properties": {
    "addr:full":"Hwy 2 Cudworth SK S0K 1B0",
    "addr:postcode":"s0k 1b0",
    "addr:street":"Hwy 2 Cudworth",
    "iso:country":"CA",
    "sg:address":"Hwy 2",
    "sg:city":"Cudworth",
    "sg:classifiers":[
        {
            "category":"Autos & Motor Vehicles",
            "subcategory":"Fuel & Gas Station",
            "type":"Retail Goods"
        }
    ],
    "sg:phone":"+1 306 256 3212",
    "sg:postcode":"S0K 1B0",
    "sg:province":"SK",
    "sg:tags":[
        "oil"
    ],
    "wof:name":"Bantle's Service",
    "wof:placetype":"venue"
},
  "geometry": {"coordinates":[-105.733291626,52.4929008484],"type":"Point"}
}