{
  "type": "Feature",
  "properties": {
    "addr:full":"131 Rue Principale N Windsor QC J1S 2E1",
    "addr:housenumber":"131",
    "addr:postcode":"j1s 2e1",
    "addr:street":"Rue Principale N",
    "iso:country":"CA",
    "sg:address":"131 Rue Principale N",
    "sg:city":"Windsor",
    "sg:classifiers":[
        {
            "category":"Building & Trades",
            "subcategory":"Electrical",
            "type":"Services"
        }
    ],
    "sg:phone":"+1 819 845 4995",
    "sg:postcode":"J1S 2E1",
    "sg:province":"QC",
    "sg:tags":[
        "electric",
        "contractor"
    ],
    "wof:name":"Gtl Electrique Inc",
    "wof:placetype":"venue"
},
  "geometry": {"coordinates":[-72.00839233400001,45.5729446411],"type":"Point"}
}