{
  "type": "Feature",
  "properties": {
    "addr:full":"Calgary AB T3J 3K9",
    "addr:postcode":"t3j 3k9",
    "iso:country":"CA",
    "sg:city":"Calgary",
    "sg:classifiers":[
        {
            "category":"Shopping",
            "subcategory":"Crafts & Fabrics",
            "type":"Retail Goods"
        }
    ],
    "sg:phone":"+1 403 280 4909",
    "sg:postcode":"T3J 3K9",
    "sg:province":"AB",
    "sg:tags":[
        "apparel",
        "shop"
    ],
    "wof:name":"Punjab Cloth House",
    "wof:placetype":"venue"
},
  "geometry": {"coordinates":[-113.958725,51.097881],"type":"Point"}
}