{
  "type": "Feature",
  "properties": {
    "addr:full":"8180 Macleod Trail SE #114 Calgary AB T2H 2B8",
    "addr:housenumber":"8180",
    "addr:postcode":"t2h 2b8",
    "addr:street":"Macleod Trail Se # 114",
    "iso:country":"CA",
    "sg:address":"8180 Macleod Trail SE #114",
    "sg:city":"Calgary",
    "sg:classifiers":[
        {
            "category":"Shopping",
            "subcategory":"Pharmacy",
            "type":"Retail Goods"
        }
    ],
    "sg:phone":"+1 403 253 7383",
    "sg:postcode":"T2H 2B8",
    "sg:province":"AB",
    "sg:tags":[
        "lottery",
        "agent"
    ],
    "wof:name":"Medicine Shoppe",
    "wof:placetype":"venue"
},
  "geometry": {"coordinates":[-114.071251,50.983475],"type":"Point"}
}