{
  "type": "Feature",
  "properties": {
    "addr:full":"Peterborough ON K9J 6X7",
    "addr:postcode":"k9j 6x7",
    "iso:country":"CA",
    "sg:city":"Peterborough",
    "sg:classifiers":[
        {
            "category":"Manufacturing",
            "subcategory":"Tools & Machinery",
            "type":"Manufacturing & Wholesale Goods"
        }
    ],
    "sg:phone":"+1 705 749 6688",
    "sg:postcode":"K9J 6X7",
    "sg:province":"ON",
    "sg:tags":[
        "machine",
        "shop"
    ],
    "wof:name":"Chilton Precision Inc",
    "wof:placetype":"venue"
},
  "geometry": {"coordinates":[-78.292946,44.275517],"type":"Point"}
}