{
  "type": "Feature",
  "properties": {
    "iso:country":"CA",
    "sg:address":"155 Augusta Ave",
    "sg:city":"Toronto",
    "sg:classifiers":[
        {
            "category":"Food & Beverages",
            "subcategory":"Groceries & Convenience Stores",
            "type":"Retail Goods"
        }
    ],
    "sg:phone":"+1 416 593 4749",
    "sg:postcode":"M5T 2L4",
    "sg:province":"ON",
    "sg:tags":[
        "grocer"
    ],
    "wof:name":"Gia Phat CO",
    "wof:placetype":"venue"
},
  "geometry": {"coordinates":[-79.40119934080001,43.6529541016],"type":"Point"}
}