{
  "type": "Feature",
  "properties": {
    "iso:country":"CA",
    "sg:address":"92 Main St",
    "sg:city":"Minden",
    "sg:classifiers":[
        {
            "category":"Shopping",
            "subcategory":"Gifts & Souvenirs",
            "type":"Retail Goods"
        }
    ],
    "sg:phone":"+1 705 286 3167",
    "sg:postcode":"K0M 2K0",
    "sg:province":"ON",
    "sg:tags":[
        "shop",
        "furniture"
    ],
    "wof:name":"Riverview Furniture & Appl",
    "wof:placetype":"venue"
},
  "geometry": {"coordinates":[-78.7258987427,44.9261245728],"type":"Point"}
}