{
  "type": "Feature",
  "properties": {
    "addr:full":"401 the West Mall Etobicoke ON M9C 5J5",
    "addr:housenumber":"401",
    "addr:postcode":"m9c 5j5",
    "addr:street":"The West Mall",
    "iso:country":"CA",
    "sg:address":"401 the West Mall",
    "sg:city":"Etobicoke",
    "sg:classifiers":[
        {
            "category":"Banks & Credit Unions",
            "subcategory":"Bank",
            "type":"Services"
        }
    ],
    "sg:phone":"+1 416 695 7025",
    "sg:postcode":"M9C 5J5",
    "sg:province":"ON",
    "wof:name":"Royal Bank Financial Group",
    "wof:placetype":"venue"
},
  "geometry": {"coordinates":[-79.567131,43.644756],"type":"Point"}
}