{
  "type": "Feature",
  "properties": {
    "addr:full":"125 Mcclintock Cres Thornhill ON L4J 2S8",
    "addr:housenumber":"125",
    "addr:postcode":"l4j 2s8",
    "addr:street":"Mcclintock Cres",
    "iso:country":"CA",
    "sg:address":"125 Mcclintock Cres",
    "sg:city":"Thornhill",
    "sg:classifiers":[
        {
            "category":"Building & Trades",
            "subcategory":"Plumbing",
            "type":"Services"
        }
    ],
    "sg:phone":"+1 905 669 6472",
    "sg:postcode":"L4J 2S8",
    "sg:province":"ON",
    "sg:tags":[
        "contractor"
    ],
    "wof:name":"Target Plumbing & Heating",
    "wof:placetype":"venue"
},
  "geometry": {"coordinates":[-79.459419,43.792645],"type":"Point"}
}