{
  "type": "Feature",
  "properties": {
    "addr:full":"383 Buchner Rd Welland ON L3B 5N4",
    "addr:housenumber":"383",
    "addr:postcode":"l3b 5n4",
    "addr:street":"Buchner Rd",
    "iso:country":"CA",
    "sg:address":"383 Buchner Rd",
    "sg:city":"Welland",
    "sg:classifiers":[
        {
            "category":"Building & Trades",
            "subcategory":"Landscaping Services",
            "type":"Services"
        }
    ],
    "sg:phone":"+1 905 227 7300",
    "sg:postcode":"L3B 5N4",
    "sg:province":"ON",
    "sg:tags":[
        "lawn",
        "maintenance",
        "grounds"
    ],
    "wof:name":"Weed Man",
    "wof:placetype":"venue"
},
  "geometry": {"coordinates":[-79.20124800000001,42.983936],"type":"Point"}
}