{
  "type": "Feature",
  "properties": {
    "addr:full":"991 Linthorpe Rd Kamloops BC V2B 7S3",
    "addr:housenumber":"991",
    "addr:postcode":"bc v2b 7s3",
    "addr:street":"Linthorpe Rd",
    "iso:country":"CA",
    "sg:address":"991 Linthorpe Rd",
    "sg:city":"Kamloops",
    "sg:classifiers":[
        {
            "category":"Building & Trades",
            "subcategory":"Equipment Rental",
            "type":"Services"
        }
    ],
    "sg:phone":"+1 250 554 3955",
    "sg:postcode":"V2B 7S3",
    "sg:province":"BC",
    "sg:tags":[
        "crane"
    ],
    "wof:name":"Sher Holdings Ltd",
    "wof:placetype":"venue"
},
  "geometry": {"coordinates":[-120.36816406200001,50.7136726379],"type":"Point"}
}