{
  "type": "Feature",
  "properties": {
    "addr:full":"360 Rue Saint-Jacques Montreal QC H2Y 1P5",
    "addr:housenumber":"360",
    "addr:postcode":"h2y 1p5",
    "addr:street":"Rue Saint-Jacques",
    "iso:country":"CA",
    "sg:address":"360 Rue Saint-Jacques",
    "sg:city":"Montreal",
    "sg:classifiers":[
        {
            "category":"Professional",
            "subcategory":"Computer Services",
            "type":"Services"
        }
    ],
    "sg:phone":"+1 514 286 9149",
    "sg:postcode":"H2Y 1P5",
    "sg:province":"QC",
    "sg:tags":[
        "information",
        "system",
        "consultant"
    ],
    "wof:name":"Brainware Limited",
    "wof:placetype":"venue"
},
  "geometry": {"coordinates":[-73.559425,45.502232],"type":"Point"}
}