{
  "type": "Feature",
  "properties": {
    "addr:full":"Highway 31 Plenty SK S0L 2R0",
    "addr:postcode":"s0l 2r0",
    "addr:street":"Highway 31",
    "iso:country":"CA",
    "sg:address":"Highway 31",
    "sg:city":"Plenty",
    "sg:classifiers":[
        {
            "category":"Freight",
            "type":"Transportation"
        }
    ],
    "sg:phone":"+1 306 932 4446",
    "sg:postcode":"S0L 2R0",
    "sg:province":"SK",
    "sg:tags":[
        "grain",
        "elevator"
    ],
    "wof:name":"Prairie West Terminals Ltd",
    "wof:placetype":"venue"
},
  "geometry": {"coordinates":[-108.650177,51.782951],"type":"Point"}
}