{
  "type": "Feature",
  "properties": {
    "addr:full":"815 Shelborne St London ON N5Z 4Z4",
    "addr:housenumber":"815",
    "addr:postcode":"n5z 4z4",
    "addr:street":"Shelborne St",
    "iso:country":"CA",
    "sg:address":"815 Shelborne St",
    "sg:city":"London",
    "sg:classifiers":[
        {
            "category":"Social Services",
            "subcategory":"Job Training",
            "type":"Services"
        }
    ],
    "sg:phone":"+1 519 668 0023",
    "sg:postcode":"N5Z 4Z4",
    "sg:province":"ON",
    "sg:tags":[
        "rehabilitation"
    ],
    "wof:name":"Dale Brain Injury Svc Inc",
    "wof:placetype":"venue"
},
  "geometry": {"coordinates":[-81.2004165649,42.9637451172],"type":"Point"}
}