{
  "type": "Feature",
  "properties": {
    "addr:full":"7981 Enterprise St Burnaby BC V5A 1V5",
    "addr:housenumber":"7981",
    "addr:postcode":"v5a 1v5",
    "addr:street":"Enterprise St",
    "iso:country":"CA",
    "sg:address":"7981 Enterprise St",
    "sg:city":"Burnaby",
    "sg:classifiers":[
        {
            "category":"Freight",
            "type":"Transportation"
        }
    ],
    "sg:phone":"+1 604 251 9555",
    "sg:postcode":"V5A 1V5",
    "sg:province":"BC",
    "sg:tags":[
        "trucking"
    ],
    "wof:name":"Cansea Transport Inc",
    "wof:placetype":"venue"
},
  "geometry": {"coordinates":[-122.93162536600001,49.2555923462],"type":"Point"}
}