{
  "type": "Feature",
  "properties": {
    "iso:country":"CA",
    "sg:city":"Montreal",
    "sg:classifiers":[
        {
            "category":"Real Estate",
            "subcategory":"Real Estate Operator",
            "type":"Services"
        }
    ],
    "sg:phone":"+1 514 845 3618",
    "sg:postcode":"H2X 1W7",
    "sg:province":"QC",
    "sg:tags":[
        "apartment"
    ],
    "wof:name":"Proprietes Rubin Zimmerman",
    "wof:placetype":"venue"
},
  "geometry": {"coordinates":[-73.576141,45.506973],"type":"Point"}
}