{
  "type": "Feature",
  "properties": {
    "addr:full":"Grandy Coboconk ON K0M 1K0",
    "addr:postcode":"k0m 1k0",
    "iso:country":"CA",
    "sg:address":"Grandy",
    "sg:city":"Coboconk",
    "sg:classifiers":[
        {
            "category":"Building & Trades",
            "subcategory":"Plumbing",
            "type":"Services"
        }
    ],
    "sg:phone":"+1 705 454 1212",
    "sg:postcode":"K0M 1K0",
    "sg:province":"ON",
    "sg:tags":[
        "conditioning",
        "air",
        "system",
        "contractor"
    ],
    "wof:name":"Cameron Charlie Heating & Cool",
    "wof:placetype":"venue"
},
  "geometry": {"coordinates":[-78.8031082153,44.6581764221],"type":"Point"}
}