{
  "type": "Feature",
  "properties": {
    "addr:full":"9315 96 St Fort St John BC V1J 6V5",
    "addr:housenumber":"9315",
    "addr:postcode":"v1j 6v5",
    "addr:street":"96 St",
    "iso:country":"CA",
    "sg:address":"9315 96 St",
    "sg:city":"Fort St John",
    "sg:classifiers":[
        {
            "category":"Shopping",
            "subcategory":"Clothing, Apparel, & Fashions",
            "type":"Retail Goods"
        }
    ],
    "sg:phone":"+1 250 785 9424",
    "sg:postcode":"V1J 6V5",
    "sg:province":"BC",
    "sg:tags":[
        "jean"
    ],
    "wof:name":"Warehouse One the Jean Store",
    "wof:placetype":"venue"
},
  "geometry": {"coordinates":[-120.840408,56.239883],"type":"Point"}
}