{
  "type": "Feature",
  "properties": {
    "iso:country":"CA",
    "sg:city":"Hull",
    "sg:classifiers":[
        {
            "category":"Professional",
            "subcategory":"Management & Consulting",
            "type":"Services"
        }
    ],
    "sg:phone":"+1 819 776 0007",
    "sg:postcode":"J8Y 4B1",
    "sg:province":"QC",
    "sg:tags":[
        "roofing",
        "consultant"
    ],
    "wof:name":"Gog Roofing Consultant",
    "wof:placetype":"venue"
},
  "geometry": {"coordinates":[-75.7408370972,45.4550209045],"type":"Point"}
}