{
  "type": "Feature",
  "properties": {
    "addr:full":"8460 Rue Saint-Jacques Mirabel QC J7N 2A3",
    "addr:housenumber":"8460",
    "addr:postcode":"j7n 2a3",
    "addr:street":"Rue Saint-Jacques",
    "iso:country":"CA",
    "sg:address":"8460 Rue Saint-Jacques",
    "sg:city":"Mirabel",
    "sg:classifiers":[
        {
            "category":"Freight",
            "type":"Transportation"
        }
    ],
    "sg:phone":"+1 450 475 8531",
    "sg:postcode":"J7N 2A3",
    "sg:province":"QC",
    "sg:tags":[
        "trucking"
    ],
    "wof:name":"Transport Meloche",
    "wof:placetype":"venue"
},
  "geometry": {"coordinates":[-73.98384900000001,45.633472],"type":"Point"}
}