{
  "type": "Feature",
  "properties": {
    "addr:full":"148 Front St N Sarnia ON N7T 5S3",
    "addr:housenumber":"148",
    "addr:postcode":"n7t 5s3",
    "addr:street":"Front St N",
    "iso:country":"CA",
    "sg:address":"148 Front St N",
    "sg:city":"Sarnia",
    "sg:classifiers":[
        {
            "category":"Home & Garden",
            "subcategory":"Home Furnishings",
            "type":"Retail Goods"
        }
    ],
    "sg:phone":"+1 519 336 1617",
    "sg:postcode":"N7T 5S3",
    "sg:province":"ON",
    "sg:tags":[
        "shop",
        "blanket",
        "gift"
    ],
    "wof:name":"Feather Your Nest",
    "wof:placetype":"venue"
},
  "geometry": {"coordinates":[-82.4081954956,42.9721832275],"type":"Point"}
}