{
  "type": "Feature",
  "properties": {
    "addr:full":"142 Av Greystone Pointe-Claire QC H9R 5T4",
    "addr:postcode":"h9r 5t4",
    "addr:street":"142 Av Greystone",
    "iso:country":"CA",
    "sg:address":"142 Av Greystone",
    "sg:city":"Pointe-Claire",
    "sg:classifiers":[
        {
            "category":"Social Services",
            "subcategory":"Child Care",
            "type":"Services"
        }
    ],
    "sg:phone":"+1 514 697 1481",
    "sg:postcode":"H9R 5T4",
    "sg:province":"QC",
    "wof:name":"Garderie West Island Daycare",
    "wof:placetype":"venue"
},
  "geometry": {"coordinates":[-73.8391952515,45.4640426636],"type":"Point"}
}