{
  "type": "Feature",
  "properties": {
    "addr:full":"412 Main St Foam Lake SK S0A 1A0",
    "addr:housenumber":"412",
    "addr:postcode":"s0a 1a0",
    "addr:street":"Main St",
    "iso:country":"CA",
    "sg:address":"412 Main St",
    "sg:city":"Foam Lake",
    "sg:classifiers":[
        {
            "category":"Shopping",
            "type":"Retail Goods"
        }
    ],
    "sg:phone":"+1 306 272 3611",
    "sg:postcode":"S0A 1A0",
    "sg:province":"SK",
    "sg:tags":[
        "monument"
    ],
    "wof:name":"Good Hall Memorials",
    "wof:placetype":"venue"
},
  "geometry": {"coordinates":[-103.533844,51.642914],"type":"Point"}
}