{
  "type": "Feature",
  "properties": {
    "addr:full":"718 Rue Gilford Montreal QC H2J 1N6",
    "addr:housenumber":"718",
    "addr:postcode":"h2j 1n6",
    "addr:street":"Rue Gilford",
    "iso:country":"CA",
    "sg:address":"718 Rue Gilford",
    "sg:city":"Montreal",
    "sg:classifiers":[
        {
            "category":"Personal",
            "subcategory":"Beauty Salon",
            "type":"Services"
        }
    ],
    "sg:phone":"+1 514 524 9555",
    "sg:postcode":"H2J 1N6",
    "sg:province":"QC",
    "wof:name":"Osmose Coiffure",
    "wof:placetype":"venue"
},
  "geometry": {"coordinates":[-73.585686,45.527184],"type":"Point"}
}