{
  "type": "Feature",
  "properties": {
    "addr:full":"13800 Vulcan Way Richmond BC V6V 1K6",
    "addr:housenumber":"13800",
    "addr:postcode":"v6v 1k6",
    "addr:street":"Vulcan Way",
    "iso:country":"CA",
    "sg:address":"13800 Vulcan Way",
    "sg:city":"Richmond",
    "sg:classifiers":[
        {
            "category":"Manufacturing",
            "subcategory":"Tools & Machinery",
            "type":"Manufacturing & Wholesale Goods"
        }
    ],
    "sg:phone":"+1 604 273 3791",
    "sg:postcode":"V6V 1K6",
    "sg:province":"BC",
    "sg:tags":[
        "ink"
    ],
    "wof:name":"Sun Chemical Ltd",
    "wof:placetype":"venue"
},
  "geometry": {"coordinates":[-123.072807,49.197601],"type":"Point"}
}