{
  "type": "Feature",
  "properties": {
    "iso:country":"CA",
    "sg:city":"Burnaby",
    "sg:classifiers":[
        {
            "category":"Manufacturing",
            "subcategory":"Metals",
            "type":"Manufacturing & Wholesale Goods"
        }
    ],
    "sg:phone":"+1 604 205 7121",
    "sg:postcode":"V5C 5W7",
    "sg:province":"BC",
    "sg:tags":[
        "coating"
    ],
    "wof:name":"Millenium Powder Coating",
    "wof:placetype":"venue"
},
  "geometry": {"coordinates":[-122.98479461700001,49.261428833],"type":"Point"}
}