{
  "type": "Feature",
  "properties": {
    "addr:full":"49 Carfrae Cres London ON N6C 4B2",
    "addr:housenumber":"49",
    "addr:postcode":"n6c 4b2",
    "addr:street":"Carfrae Cres",
    "iso:country":"CA",
    "sg:address":"49 Carfrae Cres",
    "sg:city":"London",
    "sg:classifiers":[
        {
            "category":"Health Services",
            "subcategory":"Doctor",
            "type":"Services"
        }
    ],
    "sg:phone":"+1 519 672 0741",
    "sg:postcode":"N6C 4B2",
    "sg:province":"ON",
    "sg:tags":[
        "dentist"
    ],
    "wof:name":"Thornton, Penelope DDS",
    "wof:placetype":"venue"
},
  "geometry": {"coordinates":[-81.2449798584,42.9723548889],"type":"Point"}
}