{
  "type": "Feature",
  "properties": {
    "addr:full":"1632 Upper James St Hamilton ON L9B 1K4",
    "addr:housenumber":"1632",
    "addr:postcode":"l9b 1k4",
    "addr:street":"Upper James St",
    "iso:country":"CA",
    "sg:address":"1632 Upper James St",
    "sg:city":"Hamilton",
    "sg:classifiers":[
        {
            "category":"Health Services",
            "subcategory":"Doctor",
            "type":"Services"
        }
    ],
    "sg:phone":"+1 905 383 4311",
    "sg:postcode":"L9B 1K4",
    "sg:province":"ON",
    "sg:tags":[
        "dentist"
    ],
    "wof:name":"Aceti, S DDS",
    "wof:placetype":"venue"
},
  "geometry": {"coordinates":[-79.893906,43.201847],"type":"Point"}
}