{
  "type": "Feature",
  "properties": {
    "iso:country":"CA",
    "sg:address":"4177 Rue Jarry E",
    "sg:city":"Montreal",
    "sg:classifiers":[
        {
            "category":"Retail",
            "subcategory":"Repair Shop",
            "type":"Services"
        }
    ],
    "sg:phone":"+1 514 729 0049",
    "sg:postcode":"H1Z 2H5",
    "sg:province":"QC",
    "sg:tags":[
        "jewelry"
    ],
    "wof:name":"Bijouterie Cite D'Or",
    "wof:placetype":"venue"
},
  "geometry": {"coordinates":[-73.602036,45.572449],"type":"Point"}
}