{
  "type": "Feature",
  "properties": {
    "addr:full":"Fort Mcmurray AB T9H 4B7",
    "addr:postcode":"t9h 4b7",
    "iso:country":"CA",
    "sg:city":"Fort Mcmurray",
    "sg:classifiers":[
        {
            "category":"Manufacturing",
            "subcategory":"Building Materials",
            "type":"Manufacturing & Wholesale Goods"
        }
    ],
    "sg:phone":"+1 780 791 7703",
    "sg:postcode":"T9H 4B7",
    "sg:province":"AB",
    "wof:name":"Jos-Will Millwork",
    "wof:placetype":"venue"
},
  "geometry": {"coordinates":[-111.341537,56.667946],"type":"Point"}
}