{
  "type": "Feature",
  "properties": {
    "addr:full":"9610 54 Ave NW Edmonton AB T6E 5V1",
    "addr:housenumber":"9610",
    "addr:postcode":"t6e 5v1",
    "addr:street":"54 Ave Nw",
    "iso:country":"CA",
    "sg:address":"9610 54 Ave NW",
    "sg:city":"Edmonton",
    "sg:classifiers":[
        {
            "category":"Home & Garden",
            "subcategory":"Building Materials",
            "type":"Retail Goods"
        }
    ],
    "sg:phone":"+1 780 437 7003",
    "sg:postcode":"T6E 5V1",
    "sg:province":"AB",
    "sg:tags":[
        "roofing"
    ],
    "wof:name":"Enercon Products Ltd",
    "wof:placetype":"venue"
},
  "geometry": {"coordinates":[-113.47764599999999,53.489697],"type":"Point"}
}