{
  "type": "Feature",
  "properties": {
    "addr:full":"Victoria BC V8V 1S9",
    "addr:postcode":"v8v 1s9",
    "iso:country":"CA",
    "sg:city":"Victoria",
    "sg:classifiers":[
        {
            "category":"Real Estate",
            "subcategory":"Real Estate Operator",
            "type":"Services"
        }
    ],
    "sg:phone":"+1 250 383 1185",
    "sg:postcode":"V8V 1S9",
    "sg:province":"BC",
    "sg:tags":[
        "apartment"
    ],
    "wof:name":"Orchard House",
    "wof:placetype":"venue"
},
  "geometry": {"coordinates":[-123.367493,48.417107],"type":"Point"}
}