{
  "type": "Feature",
  "properties": {
    "addr:full":"211 Church St St Catharines ON L2R 3E8",
    "addr:housenumber":"211",
    "addr:postcode":"l2r 3e8",
    "addr:street":"Church St",
    "iso:country":"CA",
    "sg:address":"211 Church St",
    "sg:city":"St Catharines",
    "sg:classifiers":[
        {
            "category":"Health Services",
            "subcategory":"Clinic",
            "type":"Services"
        }
    ],
    "sg:phone":"+1 905 680 1818",
    "sg:postcode":"L2R 3E8",
    "sg:province":"ON",
    "sg:tags":[
        "home"
    ],
    "wof:name":"Canadian Red Cross Comm Health",
    "wof:placetype":"venue"
},
  "geometry": {"coordinates":[-79.23690795900001,43.163936615],"type":"Point"}
}