{
  "type": "Feature",
  "properties": {
    "addr:full":"30 Rue Beaubien Longueuil QC J4L 1Y9",
    "addr:housenumber":"30",
    "addr:postcode":"j4l 1y9",
    "addr:street":"Rue Beaubien",
    "iso:country":"CA",
    "sg:address":"30 Rue Beaubien",
    "sg:city":"Longueuil",
    "sg:classifiers":[
        {
            "category":"Retail",
            "subcategory":"Auto Repair",
            "type":"Services"
        }
    ],
    "sg:phone":"+1 450 651 4790",
    "sg:postcode":"J4L 1Y9",
    "sg:province":"QC",
    "sg:tags":[
        "repairing",
        "automobile"
    ],
    "wof:name":"Beaubien Auto Electrique Ltee",
    "wof:placetype":"venue"
},
  "geometry": {"coordinates":[-73.4681854248,45.5232162476],"type":"Point"}
}