{
  "type": "Feature",
  "properties": {
    "addr:full":"4091 Bayridge Ave West Vancouver BC V7V 3J9",
    "addr:housenumber":"4091",
    "addr:postcode":"v7v 3j9",
    "addr:street":"Bayridge Ave",
    "iso:country":"CA",
    "sg:address":"4091 Bayridge Ave",
    "sg:city":"West Vancouver",
    "sg:classifiers":[
        {
            "category":"Real Estate",
            "subcategory":"Architect",
            "type":"Services"
        }
    ],
    "sg:phone":"+1 604 922 4062",
    "sg:postcode":"V7V 3J9",
    "sg:province":"BC",
    "wof:name":"Berthon, Paul",
    "wof:placetype":"venue"
},
  "geometry": {"coordinates":[-123.23250579800001,49.3449897766],"type":"Point"}
}