{
  "type": "Feature",
  "properties": {
    "addr:full":"180 Martha St Thunder Bay ON P7A 8C1",
    "addr:housenumber":"180",
    "addr:postcode":"p7a 8c1",
    "addr:street":"Martha St",
    "iso:country":"CA",
    "sg:address":"180 Martha St",
    "sg:city":"Thunder Bay",
    "sg:classifiers":[
        {
            "category":"Recreation",
            "type":"Entertainment"
        }
    ],
    "sg:phone":"+1 807 345 5143",
    "sg:postcode":"P7A 8C1",
    "sg:province":"ON",
    "sg:tags":[
        "pool",
        "swimming"
    ],
    "wof:name":"Volunteer Pool",
    "wof:placetype":"venue"
},
  "geometry": {"coordinates":[-89.23738899999999,48.446255],"type":"Point"}
}