{
  "type": "Feature",
  "properties": {
    "iso:country":"CA",
    "sg:city":"Calgary",
    "sg:classifiers":[
        {
            "category":"Shopping",
            "subcategory":"Florist",
            "type":"Retail Goods"
        }
    ],
    "sg:phone":"+1 403 285 0888",
    "sg:postcode":"T1Y 6Y7",
    "sg:province":"AB",
    "wof:name":"Oyster Bay Flowers",
    "wof:placetype":"venue"
},
  "geometry": {"coordinates":[-113.934844971,51.0711936951],"type":"Point"}
}