{
  "type": "Feature",
  "properties": {
    "addr:full":"18 William St W Smiths Falls ON K7A 1M9",
    "addr:housenumber":"18",
    "addr:postcode":"k7a 1m9",
    "addr:street":"William St W",
    "iso:country":"CA",
    "sg:address":"18 William St W",
    "sg:city":"Smiths Falls",
    "sg:classifiers":[
        {
            "category":"Organizations",
            "subcategory":"Labor Organization",
            "type":"Services"
        }
    ],
    "sg:phone":"+1 613 284 8096",
    "sg:postcode":"K7A 1M9",
    "sg:province":"ON",
    "wof:name":"Cupe",
    "wof:placetype":"venue"
},
  "geometry": {"coordinates":[-76.02259100000001,44.900536],"type":"Point"}
}