{
  "type": "Feature",
  "properties": {
    "addr:full":"550 Lyons Lane Oakville ON L6J 2Y1",
    "addr:housenumber":"550",
    "addr:postcode":"l6j 2y1",
    "addr:street":"Lyons Lane",
    "iso:country":"CA",
    "sg:address":"550 Lyons Lane",
    "sg:city":"Oakville",
    "sg:classifiers":[
        {
            "category":"Wholesale",
            "subcategory":"Machinery & Supplies",
            "type":"Manufacturing & Wholesale Goods"
        }
    ],
    "sg:phone":"+1 905 844 3371",
    "sg:postcode":"L6J 2Y1",
    "sg:province":"ON",
    "sg:tags":[
        "equipment",
        "caster",
        "industrial",
        "glide"
    ],
    "wof:name":"S B Simpson Group Inc",
    "wof:placetype":"venue"
},
  "geometry": {"coordinates":[-79.68656900000001,43.453445],"type":"Point"}
}