{
  "type": "Feature",
  "properties": {
    "addr:full":"254 Rue Main Hudson QC J0P 1H0",
    "addr:housenumber":"254",
    "addr:postcode":"j0p 1h0",
    "addr:street":"Rue Main",
    "iso:country":"CA",
    "sg:address":"254 Rue Main",
    "sg:city":"Hudson",
    "sg:classifiers":[
        {
            "category":"Recreation",
            "type":"Entertainment"
        }
    ],
    "sg:phone":"+1 450 458 5396",
    "sg:postcode":"J0P 1H0",
    "sg:province":"QC",
    "sg:tags":[
        "historical"
    ],
    "wof:name":"Greenwood Centre",
    "wof:placetype":"venue"
},
  "geometry": {"coordinates":[-74.1130065918,45.4518699646],"type":"Point"}
}