{
  "type": "Feature",
  "properties": {
    "addr:full":"610 Main St Yarmouth NS B5A 1J9",
    "addr:housenumber":"610",
    "addr:postcode":"b5a 1j9",
    "addr:street":"Main St",
    "iso:country":"CA",
    "sg:address":"610 Main St",
    "sg:city":"Yarmouth",
    "sg:classifiers":[
        {
            "category":"Shopping",
            "subcategory":"Clothing, Apparel, & Fashions",
            "type":"Retail Goods"
        }
    ],
    "sg:phone":"+1 902 742 0139",
    "sg:postcode":"B5A 1J9",
    "sg:province":"NS",
    "sg:tags":[
        "tailor"
    ],
    "wof:name":"K & K Fashion Design",
    "wof:placetype":"venue"
},
  "geometry": {"coordinates":[-66.1142654419,43.8519973755],"type":"Point"}
}