{
  "type": "Feature",
  "properties": {
    "addr:full":"1 King's Rd Botwood NL A0H 1E0",
    "addr:housenumber":"1",
    "addr:postcode":"a0h 1e0",
    "addr:street":"King'S Rd",
    "iso:country":"CA",
    "sg:address":"1 King's Rd",
    "sg:city":"Botwood",
    "sg:classifiers":[
        {
            "category":"Food & Beverages",
            "subcategory":"Groceries & Convenience Stores",
            "type":"Retail Goods"
        }
    ],
    "sg:phone":"+1 709 257 2241",
    "sg:postcode":"A0H 1E0",
    "sg:province":"NL",
    "sg:tags":[
        "grocer"
    ],
    "wof:name":"Gill's Store & Sports",
    "wof:placetype":"venue"
},
  "geometry": {"coordinates":[-55.3669013977,49.130859375],"type":"Point"}
}