{
  "type": "Feature",
  "properties": {
    "addr:full":"55 Victoria Ave N Hamilton ON L8L 5E3",
    "addr:housenumber":"55",
    "addr:postcode":"l8l 5e3",
    "addr:street":"Victoria Ave N",
    "iso:country":"CA",
    "sg:address":"55 Victoria Ave N",
    "sg:city":"Hamilton",
    "sg:classifiers":[
        {
            "category":"Organizations",
            "subcategory":"Religious Organization",
            "type":"Services"
        }
    ],
    "sg:phone":"+1 905 521 1244",
    "sg:postcode":"L8L 5E3",
    "sg:province":"ON",
    "sg:tags":[
        "church"
    ],
    "wof:name":"Apostolic Christian Church",
    "wof:placetype":"venue"
},
  "geometry": {"coordinates":[-79.856262207,43.2548027039],"type":"Point"}
}