{
  "type": "Feature",
  "properties": {
    "iso:country":"CA",
    "sg:address":"341 Bayfield St",
    "sg:city":"Barrie",
    "sg:classifiers":[
        {
            "category":"Retail",
            "subcategory":"Car Wash",
            "type":"Services"
        }
    ],
    "sg:phone":"+1 705 737 3488",
    "sg:postcode":"L4M 3C3",
    "sg:province":"ON",
    "sg:tags":[
        "polishing",
        "washing"
    ],
    "wof:name":"Bayfield Sunoco Car Wash",
    "wof:placetype":"venue"
},
  "geometry": {"coordinates":[-79.701859,44.403076],"type":"Point"}
}