{
  "type": "Feature",
  "properties": {
    "addr:full":"80 10th Ave Campbell River BC V9W 4E3",
    "addr:housenumber":"80",
    "addr:postcode":"v9w 4e3",
    "addr:street":"10Th Ave",
    "iso:country":"CA",
    "sg:address":"80 10th Ave",
    "sg:city":"Campbell River",
    "sg:classifiers":[
        {
            "category":"Restaurant",
            "type":"Food & Drink"
        }
    ],
    "sg:phone":"+1 250 286 1422",
    "sg:postcode":"V9W 4E3",
    "sg:province":"BC",
    "wof:name":"Koto Japanese Restaurant",
    "wof:placetype":"venue"
},
  "geometry": {"coordinates":[-125.24449199999999,50.025902],"type":"Point"}
}