{
  "type": "Feature",
  "properties": {
    "addr:full":"297 Rte Principale Saint-Eusebe QC G0L 2Y0",
    "addr:housenumber":"297",
    "addr:postcode":"g0l 2y0",
    "addr:street":"Rte Principale",
    "iso:country":"CA",
    "sg:address":"297 Rte Principale",
    "sg:city":"Saint-Eusebe",
    "sg:classifiers":[
        {
            "category":"Manufacturing",
            "subcategory":"Lumber",
            "type":"Manufacturing & Wholesale Goods"
        }
    ],
    "sg:phone":"+1 418 899 7161",
    "sg:postcode":"G0L 2Y0",
    "sg:province":"QC",
    "sg:tags":[
        "sawmill"
    ],
    "wof:name":"Pabaced Gds Inc",
    "wof:placetype":"venue"
},
  "geometry": {"coordinates":[-68.91095,47.545635],"type":"Point"}
}