{
  "type": "Feature",
  "properties": {
    "iso:country":"CA",
    "sg:address":"36 Douglas St",
    "sg:city":"Truro",
    "sg:classifiers":[
        {
            "category":"Education",
            "subcategory":"School",
            "type":"Public Place"
        }
    ],
    "sg:phone":"+1 902 896 5730",
    "sg:postcode":"B2N 2E7",
    "sg:province":"NS",
    "wof:name":"Douglas Street Elementary",
    "wof:placetype":"venue"
},
  "geometry": {"coordinates":[-63.2753143311,45.358631134],"type":"Point"}
}