{
  "type": "Feature",
  "properties": {
    "addr:full":"563 1st St Kamsack SK S0A 1S0",
    "addr:housenumber":"563",
    "addr:postcode":"s0a 1s0",
    "addr:street":"1St St",
    "iso:country":"CA",
    "sg:address":"563 1st St",
    "sg:city":"Kamsack",
    "sg:classifiers":[
        {
            "category":"Food & Beverages",
            "subcategory":"Groceries & Convenience Stores",
            "type":"Retail Goods"
        }
    ],
    "sg:phone":"+1 306 542 4128",
    "sg:postcode":"S0A 1S0",
    "sg:province":"SK",
    "sg:tags":[
        "grocer"
    ],
    "wof:name":"Kamsask Shop Easy",
    "wof:placetype":"venue"
},
  "geometry": {"coordinates":[-101.90431213399999,51.5642051697],"type":"Point"}
}