{
  "type": "Feature",
  "properties": {
    "addr:full":"Joliette QC J6E 2W5",
    "addr:postcode":"j6e 2w5",
    "iso:country":"CA",
    "sg:city":"Joliette",
    "sg:classifiers":[
        {
            "category":"Personal",
            "type":"Services"
        }
    ],
    "sg:phone":"+1 450 756 1118",
    "sg:postcode":"J6E 2W5",
    "sg:province":"QC",
    "sg:tags":[
        "therapist",
        "massage"
    ],
    "wof:name":"Salon D'Esthetique Corps & Ame",
    "wof:placetype":"venue"
},
  "geometry": {"coordinates":[-73.4419555664,46.0235710144],"type":"Point"}
}