{
  "type": "Feature",
  "properties": {
    "iso:country":"CA",
    "sg:address":"313 219 Rte",
    "sg:city":"Hemmingford",
    "sg:classifiers":[
        {
            "category":"Recreation",
            "type":"Entertainment"
        }
    ],
    "sg:phone":"+1 450 247 2445",
    "sg:postcode":"J0L 1H0",
    "sg:province":"QC",
    "sg:tags":[
        "course",
        "golf"
    ],
    "wof:name":"Club DE Golf Hemmingford",
    "wof:placetype":"venue"
},
  "geometry": {"coordinates":[-73.5807647705,45.0999412537],"type":"Point"}
}