{
  "type": "Feature",
  "properties": {
    "addr:full":"3259 Rue Saint-Jacques Montreal QC H4C 1G8",
    "addr:housenumber":"3259",
    "addr:postcode":"h4c 1g8",
    "addr:street":"Rue Saint-Jacques",
    "iso:country":"CA",
    "sg:address":"3259 Rue Saint-Jacques",
    "sg:city":"Montreal",
    "sg:classifiers":[
        {
            "category":"Professional",
            "subcategory":"Computer Services",
            "type":"Services"
        }
    ],
    "sg:phone":"+1 514 846 0181",
    "sg:postcode":"H4C 1G8",
    "sg:province":"QC",
    "sg:tags":[
        "information",
        "system",
        "consultant"
    ],
    "wof:name":"Sil Inc",
    "wof:placetype":"venue"
},
  "geometry": {"coordinates":[-73.58122253419999,45.4829826355],"type":"Point"}
}