{
  "type": "Feature",
  "properties": {
    "iso:country":"CA",
    "sg:address":"103 Grove Place",
    "sg:city":"Drumheller",
    "sg:classifiers":[
        {
            "category":"Restaurant",
            "type":"Food & Drink"
        }
    ],
    "sg:phone":"+1 403 823 6511",
    "sg:postcode":"T0J 0Y0",
    "sg:province":"AB",
    "wof:name":"Dino's Family Restaurant",
    "wof:placetype":"venue"
},
  "geometry": {"coordinates":[-112.712333679,51.4696922302],"type":"Point"}
}