{
  "type": "Feature",
  "properties": {
    "iso:country":"CA",
    "sg:address":"1200 24th St W",
    "sg:city":"Prince Albert",
    "sg:classifiers":[
        {
            "category":"Health Services",
            "subcategory":"Clinic",
            "type":"Services"
        }
    ],
    "sg:phone":"+1 306 765 6000",
    "sg:postcode":"S6V 4N9",
    "sg:province":"SK",
    "wof:name":"Prince Albert/Parkland Health",
    "wof:placetype":"venue"
},
  "geometry": {"coordinates":[-105.772941589,53.1915588379],"type":"Point"}
}