{
  "type": "Feature",
  "properties": {
    "addr:full":"92 Place Hochelaga Candiac QC J5R 3P8",
    "addr:housenumber":"92",
    "addr:postcode":"j5r 3p8",
    "addr:street":"Place Hochelaga",
    "iso:country":"CA",
    "sg:address":"92 Place Hochelaga",
    "sg:city":"Candiac",
    "sg:classifiers":[
        {
            "category":"Building & Trades",
            "subcategory":"Construction",
            "type":"Services"
        }
    ],
    "sg:phone":"+1 450 638 0023",
    "sg:postcode":"J5R 3P8",
    "sg:province":"QC",
    "sg:tags":[
        "stone",
        "pointing"
    ],
    "wof:name":"Gauthier, Francois",
    "wof:placetype":"venue"
},
  "geometry": {"coordinates":[-73.524529,45.389084],"type":"Point"}
}