{
  "type": "Feature",
  "properties": {
    "addr:full":"Crabtree QC J0K 1B0",
    "addr:postcode":"j0k 1b0",
    "iso:country":"CA",
    "sg:city":"Crabtree",
    "sg:classifiers":[
        {
            "category":"Restaurant",
            "type":"Food & Drink"
        }
    ],
    "sg:phone":"+1 450 754 2888",
    "sg:postcode":"J0K 1B0",
    "sg:province":"QC",
    "wof:name":"Crabtree Pizzeria",
    "wof:placetype":"venue"
},
  "geometry": {"coordinates":[-73.467941,45.967976],"type":"Point"}
}