{
  "type": "Feature",
  "properties": {
    "iso:country":"CA",
    "sg:address":"118 Hwy 97 S",
    "sg:city":"Quesnel",
    "sg:classifiers":[
        {
            "category":"Retail",
            "subcategory":"Auto Rental",
            "type":"Services"
        }
    ],
    "sg:phone":"+1 250 992 3734",
    "sg:postcode":"V2J 4C5",
    "sg:province":"BC",
    "sg:tags":[
        "renting",
        "truck",
        "leasing"
    ],
    "wof:name":"U-Haul CO Ltd",
    "wof:placetype":"venue"
},
  "geometry": {"coordinates":[-122.497513,52.975582],"type":"Point"}
}