{
  "type": "Feature",
  "properties": {
    "addr:full":"194 Kenneth St Duncan BC V9L 1N4",
    "addr:housenumber":"194",
    "addr:postcode":"v9l 1n4",
    "addr:street":"Kenneth St",
    "iso:country":"CA",
    "sg:address":"194 Kenneth St",
    "sg:city":"Duncan",
    "sg:classifiers":[
        {
            "category":"Shopping",
            "subcategory":"Used Merchandise",
            "type":"Retail Goods"
        }
    ],
    "sg:phone":"+1 250 748 2003",
    "sg:postcode":"V9L 1N4",
    "sg:province":"BC",
    "sg:tags":[
        "shop",
        "consignment"
    ],
    "wof:name":"Eclectic Avenue",
    "wof:placetype":"venue"
},
  "geometry": {"coordinates":[-123.71019,48.778339],"type":"Point"}
}