{
  "type": "Feature",
  "properties": {
    "iso:country":"CA",
    "sg:address":"111 Rue Beaucage",
    "sg:city":"Vanier",
    "sg:classifiers":[
        {
            "category":"Cinema",
            "subcategory":"Movie Rental",
            "type":"Entertainment"
        }
    ],
    "sg:phone":"+1 418 681 3434",
    "sg:postcode":"G1M 1G4",
    "sg:province":"QC",
    "sg:tags":[
        "leasing",
        "video",
        "disc",
        "tape"
    ],
    "wof:name":"Video Eclair Inc",
    "wof:placetype":"venue"
},
  "geometry": {"coordinates":[-71.25700378419999,46.8175735474],"type":"Point"}
}