{
  "type": "Feature",
  "properties": {
    "addr:full":"Truro NS B2N 5B3",
    "addr:postcode":"b2n 5b3",
    "iso:country":"CA",
    "sg:city":"Truro",
    "sg:classifiers":[
        {
            "category":"Autos & Motor Vehicles",
            "subcategory":"Recreational Vehicle Sales",
            "type":"Retail Goods"
        }
    ],
    "sg:phone":"+1 902 662 2516",
    "sg:postcode":"B2N 5B3",
    "sg:province":"NS",
    "sg:tags":[
        "tractor"
    ],
    "wof:name":"Mac Leod's Farm Machinery Ltd",
    "wof:placetype":"venue"
},
  "geometry": {"coordinates":[-63.291004,45.35907],"type":"Point"}
}