{
  "type": "Feature",
  "properties": {
    "addr:full":"20 Rue Principale N Sawyerville QC J0B 3A0",
    "addr:housenumber":"20",
    "addr:postcode":"j0b 3a0",
    "addr:street":"Rue Principale N Sawyerville",
    "iso:country":"CA",
    "sg:address":"20 Rue Principale N",
    "sg:city":"Sawyerville",
    "sg:classifiers":[
        {
            "category":"Home & Garden",
            "subcategory":"Garden Supply",
            "type":"Retail Goods"
        }
    ],
    "sg:phone":"+1 819 889 2202",
    "sg:postcode":"J0B 3A0",
    "sg:province":"QC",
    "sg:tags":[
        "tree",
        "christmas"
    ],
    "wof:name":"Plantations Crete Inc",
    "wof:placetype":"venue"
},
  "geometry": {"coordinates":[-71.567268,45.339035],"type":"Point"}
}