{
  "type": "Feature",
  "properties": {
    "iso:country":"CA",
    "sg:address":"45 Ochterloney St",
    "sg:city":"Dartmouth",
    "sg:classifiers":[
        {
            "category":"Organizations",
            "subcategory":"Professional Association",
            "type":"Services"
        }
    ],
    "sg:phone":"+1 902 465 5578",
    "sg:postcode":"B2Y 4M7",
    "sg:province":"NS",
    "wof:name":"Dartmouth Seniors Svc Ctr",
    "wof:placetype":"venue"
},
  "geometry": {"coordinates":[-63.5688743591,44.6664466858],"type":"Point"}
}