{
  "type": "Feature",
  "properties": {
    "addr:full":"9015 Ch Avon Montreal-Ouest QC H4X 2G8",
    "addr:postcode":"9015;h4x 2g8",
    "addr:street":"Ch Avon Montreal-Ouest",
    "iso:country":"CA",
    "sg:address":"9015 Ch Avon",
    "sg:city":"Montreal-Ouest",
    "sg:classifiers":[
        {
            "category":"Education",
            "subcategory":"Vocational School",
            "type":"Public Place"
        }
    ],
    "sg:phone":"+1 514 488 6118",
    "sg:postcode":"H4X 2G8",
    "sg:province":"QC",
    "sg:tags":[
        "correspondence"
    ],
    "wof:name":"Centre DE Perfectionnement",
    "wof:placetype":"venue"
},
  "geometry": {"coordinates":[-73.64398199999999,45.448475],"type":"Point"}
}