{
  "type": "Feature",
  "properties": {
    "addr:full":"3952 49 Ave Innisfail AB T4G 1J5",
    "addr:housenumber":"3952",
    "addr:postcode":"t4g 1j5",
    "addr:street":"49 Ave",
    "iso:country":"CA",
    "sg:address":"3952 49 Ave",
    "sg:city":"Innisfail",
    "sg:classifiers":[
        {
            "category":"Cinema",
            "subcategory":"Movie Rental",
            "type":"Entertainment"
        }
    ],
    "sg:phone":"+1 403 227 3711",
    "sg:postcode":"T4G 1J5",
    "sg:province":"AB",
    "sg:tags":[
        "video",
        "game",
        "leasing"
    ],
    "wof:name":"Just New Reeleases",
    "wof:placetype":"venue"
},
  "geometry": {"coordinates":[-113.946533203,52.015499115],"type":"Point"}
}