{
  "type": "Feature",
  "properties": {
    "addr:full":"Toronto ON M5G 1C4",
    "addr:postcode":"m5g 1c4",
    "iso:country":"CA",
    "sg:city":"Toronto",
    "sg:classifiers":[
        {
            "category":"Organizations",
            "subcategory":"Professional Association",
            "type":"Services"
        }
    ],
    "sg:phone":"+1 416 977 3430",
    "sg:postcode":"M5G 1C4",
    "sg:province":"ON",
    "sg:tags":[
        "club"
    ],
    "wof:name":"Lem Si Ho Tong Society",
    "wof:placetype":"venue"
},
  "geometry": {"coordinates":[-79.384415,43.655434],"type":"Point"}
}