{
  "type": "Feature",
  "properties": {
    "iso:country":"CA",
    "sg:address":"1234 Av Greene",
    "sg:city":"Westmount",
    "sg:classifiers":[
        {
            "category":"Travel",
            "subcategory":"Travel Agent",
            "type":"Entertainment"
        }
    ],
    "sg:phone":"+1 514 931 3843",
    "sg:postcode":"H3Z 2A3",
    "sg:province":"QC",
    "sg:tags":[
        "agency",
        "bureau"
    ],
    "wof:name":"Carlson Wagonlit Travel",
    "wof:placetype":"venue"
},
  "geometry": {"coordinates":[-73.588554,45.486305],"type":"Point"}
}