{
  "type": "Feature",
  "properties": {
    "addr:full":"5783 Ch DE LA Cote-Des-Neiges Montreal QC H3S 1Y7",
    "addr:postcode":"5783;h3s 1y7",
    "addr:street":"Ch De La Cote-Des-Neiges",
    "iso:country":"CA",
    "sg:address":"5783 Ch DE LA Cote-Des-Neiges",
    "sg:city":"Montreal",
    "sg:classifiers":[
        {
            "category":"Personal",
            "subcategory":"Beauty Salon",
            "type":"Services"
        }
    ],
    "sg:phone":"+1 514 738 2842",
    "sg:postcode":"H3S 1Y7",
    "sg:province":"QC",
    "wof:name":"Caruso Coiffure Unisexe",
    "wof:placetype":"venue"
},
  "geometry": {"coordinates":[-73.628777,45.499489],"type":"Point"}
}