{
  "type": "Feature",
  "properties": {
    "iso:country":"CA",
    "sg:address":"126 Main St S",
    "sg:city":"Rockwood",
    "sg:classifiers":[
        {
            "category":"Social Services",
            "type":"Services"
        }
    ],
    "sg:phone":"+1 519 856 2113",
    "sg:postcode":"N0B 2K0",
    "sg:province":"ON",
    "sg:tags":[
        "organization",
        "welfare"
    ],
    "wof:name":"Ewag Community Svc",
    "wof:placetype":"venue"
},
  "geometry": {"coordinates":[-80.1433639526,43.6183624268],"type":"Point"}
}