{
  "type": "Feature",
  "properties": {
    "addr:full":"SW 12 4 1W Morris MB R0G 1K0",
    "addr:housenumber":"4 1w",
    "addr:postcode":"r0g 1k0",
    "addr:street":"Sw 12",
    "iso:country":"CA",
    "sg:address":"SW 12 4 1W",
    "sg:city":"Morris",
    "sg:classifiers":[
        {
            "category":"Building & Trades",
            "subcategory":"Landscaping Services",
            "type":"Services"
        }
    ],
    "sg:phone":"+1 204 746 6890",
    "sg:postcode":"R0G 1K0",
    "sg:province":"MB",
    "sg:tags":[
        "landscape",
        "contractor"
    ],
    "wof:name":"Easy Street Landscaping",
    "wof:placetype":"venue"
},
  "geometry": {"coordinates":[-97.366043,49.354687],"type":"Point"}
}