{
  "type": "Feature",
  "properties": {
    "addr:full":"13637 Boul Du Cure-Labelle Mirabel QC J7J 1K3",
    "addr:housenumber":"13637",
    "addr:postcode":"j7j 1k3",
    "addr:street":"Boul Du Cure-Labelle",
    "iso:country":"CA",
    "sg:address":"13637 Boul Du Cure-Labelle",
    "sg:city":"Mirabel",
    "sg:classifiers":[
        {
            "category":"Food & Beverages",
            "subcategory":"Groceries & Convenience Stores",
            "type":"Retail Goods"
        }
    ],
    "sg:phone":"+1 450 435 5422",
    "sg:postcode":"J7J 1K3",
    "sg:province":"QC",
    "wof:name":"Petro Canada",
    "wof:placetype":"venue"
},
  "geometry": {"coordinates":[-73.924995,45.702492],"type":"Point"}
}