{
  "type": "Feature",
  "properties": {
    "addr:full":"Belwood ON N0B 1J0",
    "addr:postcode":"n0b 1j0",
    "iso:country":"CA",
    "sg:city":"Belwood",
    "sg:classifiers":[
        {
            "category":"Building & Trades",
            "subcategory":"Plumbing",
            "type":"Services"
        }
    ],
    "sg:phone":"+1 519 843 6397",
    "sg:postcode":"N0B 1J0",
    "sg:province":"ON",
    "sg:tags":[
        "conditioning",
        "air",
        "system",
        "refrigerating",
        "contractor"
    ],
    "wof:name":"Upper Grand Refrigeration Htg",
    "wof:placetype":"venue"
},
  "geometry": {"coordinates":[-80.3209152222,43.7776641846],"type":"Point"}
}