{
  "type": "Feature",
  "properties": {
    "addr:full":"582 Rue Richelieu Beloeil QC J3G 4P4",
    "addr:housenumber":"582",
    "addr:postcode":"j3g 4p4",
    "addr:street":"Rue Richelieu",
    "iso:country":"CA",
    "sg:address":"582 Rue Richelieu",
    "sg:city":"Beloeil",
    "sg:classifiers":[
        {
            "category":"Health Services",
            "subcategory":"Nursing And Care Facility",
            "type":"Services"
        }
    ],
    "sg:phone":"+1 450 467 8671",
    "sg:postcode":"J3G 4P4",
    "sg:province":"QC",
    "sg:tags":[
        "home",
        "retirement",
        "community"
    ],
    "wof:name":"Residence Ledoux",
    "wof:placetype":"venue"
},
  "geometry": {"coordinates":[-73.20497899999999,45.560051],"type":"Point"}
}