{
  "type": "Feature",
  "properties": {
    "addr:full":"2488 Rue Sainte-Anne Varennes QC J3X 1R7",
    "addr:housenumber":"2488",
    "addr:postcode":"j3x 1r7",
    "addr:street":"Rue Sainte-Anne",
    "iso:country":"CA",
    "sg:address":"2488 Rue Sainte-Anne",
    "sg:city":"Varennes",
    "sg:classifiers":[
        {
            "category":"Building & Trades",
            "subcategory":"Construction",
            "type":"Services"
        }
    ],
    "sg:phone":"+1 450 652 9760",
    "sg:postcode":"J3X 1R7",
    "sg:province":"QC",
    "sg:tags":[
        "excavating",
        "contractor"
    ],
    "wof:name":"Entreprises Rdl Inc",
    "wof:placetype":"venue"
},
  "geometry": {"coordinates":[-73.4369354248,45.6905517578],"type":"Point"}
}