{
  "type": "Feature",
  "properties": {
    "addr:full":"Richmond BC V6Y 2B3",
    "addr:postcode":"v6y 2b3",
    "iso:country":"CA",
    "sg:city":"Richmond",
    "sg:classifiers":[
        {
            "category":"Restaurant",
            "type":"Food & Drink"
        }
    ],
    "sg:phone":"+1 604 278 2637",
    "sg:postcode":"V6Y 2B3",
    "sg:province":"BC",
    "wof:name":"Topgold Restaurant",
    "wof:placetype":"venue"
},
  "geometry": {"coordinates":[-123.136383057,49.1670303345],"type":"Point"}
}