{
  "type": "Feature",
  "properties": {
    "addr:full":"6440 Main St Vancouver BC V5W 2V4",
    "addr:housenumber":"6440",
    "addr:postcode":"v5w 2v4",
    "addr:street":"Main St",
    "iso:country":"CA",
    "sg:address":"6440 Main St",
    "sg:city":"Vancouver",
    "sg:classifiers":[
        {
            "category":"Health Services",
            "subcategory":"Doctor",
            "type":"Services"
        }
    ],
    "sg:phone":"+1 604 321 4313",
    "sg:postcode":"V5W 2V4",
    "sg:province":"BC",
    "sg:tags":[
        "physician",
        "surgeon"
    ],
    "wof:name":"Main Family Practice",
    "wof:placetype":"venue"
},
  "geometry": {"coordinates":[-123.101303,49.226292],"type":"Point"}
}