{
  "type": "Feature",
  "properties": {
    "addr:full":"8579 120 St Delta BC V4C 6R2",
    "addr:housenumber":"8579",
    "addr:postcode":"v4c 6r2",
    "addr:street":"120 St",
    "iso:country":"CA",
    "sg:address":"8579 120 St",
    "sg:city":"Delta",
    "sg:classifiers":[
        {
            "category":"Autos & Motor Vehicles",
            "subcategory":"Fuel & Gas Station",
            "type":"Retail Goods"
        }
    ],
    "sg:phone":"+1 604 594 5151",
    "sg:postcode":"V4C 6R2",
    "sg:province":"BC",
    "sg:tags":[
        "oil"
    ],
    "wof:name":"Kennedy Heights Chevron Svc",
    "wof:placetype":"venue"
},
  "geometry": {"coordinates":[-122.890579,49.159103],"type":"Point"}
}