{
  "type": "Feature",
  "properties": {
    "iso:country":"CA",
    "sg:address":"100 Centennial Pky S",
    "sg:city":"Stoney Creek",
    "sg:classifiers":[
        {
            "category":"Personal",
            "type":"Services"
        }
    ],
    "sg:phone":"+1 905 560 7000",
    "sg:postcode":"L8G 2C8",
    "sg:province":"ON",
    "sg:tags":[
        "control",
        "weight",
        "program",
        "fitness",
        "exercise",
        "physical"
    ],
    "wof:name":"Premier Fitness Clubs",
    "wof:placetype":"venue"
},
  "geometry": {"coordinates":[-79.7644577026,43.2269554138],"type":"Point"}
}