{
  "type": "Feature",
  "properties": {
    "addr:full":"1955 Brideau Ave Bathurst NB E2A 2H1",
    "addr:housenumber":"1955",
    "addr:postcode":"e2a 2h1",
    "addr:street":"Brideau Ave",
    "iso:country":"CA",
    "sg:address":"1955 Brideau Ave",
    "sg:city":"Bathurst",
    "sg:classifiers":[
        {
            "category":"Retail",
            "subcategory":"Auto Repair",
            "type":"Services"
        }
    ],
    "sg:phone":"+1 506 546 6466",
    "sg:postcode":"E2A 2H1",
    "sg:province":"NB",
    "sg:tags":[
        "wrecker"
    ],
    "wof:name":"Causeway Towing",
    "wof:placetype":"venue"
},
  "geometry": {"coordinates":[-65.62050600000001,47.605141],"type":"Point"}
}