{
  "type": "Feature",
  "properties": {
    "iso:country":"CA",
    "sg:address":"205 Franktown Rd",
    "sg:city":"Carleton Place",
    "sg:classifiers":[
        {
            "category":"Personal",
            "subcategory":"Beauty Salon",
            "type":"Services"
        }
    ],
    "sg:phone":"+1 613 257 1281",
    "sg:postcode":"K7C 2N9",
    "sg:province":"ON",
    "wof:name":"Shairs Hair Salon",
    "wof:placetype":"venue"
},
  "geometry": {"coordinates":[-76.1342163086,45.1343765259],"type":"Point"}
}