{
  "type": "Feature",
  "properties": {
    "addr:full":"Calgary AB T2T 0B4",
    "addr:postcode":"t2t 0b4",
    "iso:country":"CA",
    "sg:city":"Calgary",
    "sg:classifiers":[
        {
            "category":"Recreation",
            "type":"Entertainment"
        }
    ],
    "sg:phone":"+1 403 244 5554",
    "sg:postcode":"T2T 0B4",
    "sg:province":"AB",
    "sg:tags":[
        "psychic",
        "medium"
    ],
    "wof:name":"New Vision",
    "wof:placetype":"venue"
},
  "geometry": {"coordinates":[-114.087807,51.03796],"type":"Point"}
}