{
  "type": "Feature",
  "properties": {
    "addr:full":"2700 Dewdney Ave Regina SK S4T 0X5",
    "addr:housenumber":"2700",
    "addr:postcode":"s4t 0x5",
    "addr:street":"Dewdney Ave",
    "iso:country":"CA",
    "sg:address":"2700 Dewdney Ave",
    "sg:city":"Regina",
    "sg:classifiers":[
        {
            "category":"Autos & Motor Vehicles",
            "subcategory":"Fuel & Gas Station",
            "type":"Retail Goods"
        }
    ],
    "sg:phone":"+1 306 352 1734",
    "sg:postcode":"S4T 0X5",
    "sg:province":"SK",
    "sg:tags":[
        "oil"
    ],
    "wof:name":"Dewdney Shell",
    "wof:placetype":"venue"
},
  "geometry": {"coordinates":[-104.61979700000001,50.455177],"type":"Point"}
}