{
  "type": "Feature",
  "properties": {
    "addr:full":"1386 Ch Ozias-Leduc Mont-Saint-Hilaire QC J3G 4S6",
    "addr:postcode":"1386;j3g 4s6",
    "addr:street":"Ch Ozias-Leduc",
    "iso:country":"CA",
    "sg:address":"1386 Ch Ozias-Leduc",
    "sg:city":"Mont-Saint-Hilaire",
    "sg:classifiers":[
        {
            "category":"Home & Garden",
            "subcategory":"Garden Supply",
            "type":"Retail Goods"
        }
    ],
    "sg:phone":"+1 450 467 3832",
    "sg:postcode":"J3G 4S6",
    "sg:province":"QC",
    "sg:tags":[
        "nurseryman"
    ],
    "wof:name":"Y Yvon Auclair & Fils Enrg",
    "wof:placetype":"venue"
},
  "geometry": {"coordinates":[-73.206085,45.531139],"type":"Point"}
}