{
  "type": "Feature",
  "properties": {
    "iso:country":"CA",
    "sg:city":"Charlesbourg",
    "sg:classifiers":[
        {
            "category":"Personal",
            "subcategory":"Beauty Salon",
            "type":"Services"
        }
    ],
    "sg:phone":"+1 418 623 0613",
    "sg:postcode":"G1H 2S5",
    "sg:province":"QC",
    "sg:tags":[
        "barber"
    ],
    "wof:name":"Salon Figaro Veilleux",
    "wof:placetype":"venue"
},
  "geometry": {"coordinates":[-71.2494049072,46.8427772522],"type":"Point"}
}