{
  "type": "Feature",
  "properties": {
    "addr:full":"1202 Dunsmure Rd Hamilton ON L8H 1L4",
    "addr:housenumber":"1202",
    "addr:postcode":"l8h 1l4",
    "addr:street":"Dunsmure Rd",
    "iso:country":"CA",
    "sg:address":"1202 Dunsmure Rd",
    "sg:city":"Hamilton",
    "sg:classifiers":[
        {
            "category":"Organizations",
            "subcategory":"Religious Organization",
            "type":"Services"
        }
    ],
    "sg:phone":"+1 905 544 5956",
    "sg:postcode":"L8H 1L4",
    "sg:province":"ON",
    "sg:tags":[
        "church"
    ],
    "wof:name":"St Mark's Syrian Orthodox Chr",
    "wof:placetype":"venue"
},
  "geometry": {"coordinates":[-79.7891998291,43.2372589111],"type":"Point"}
}