{
  "type": "Feature",
  "properties": {
    "addr:full":"5703 48 Ave Camrose AB T4V 0J9",
    "addr:housenumber":"5703",
    "addr:postcode":"t4v 0j9",
    "addr:street":"48 Ave",
    "iso:country":"CA",
    "sg:address":"5703 48 Ave",
    "sg:city":"Camrose",
    "sg:classifiers":[
        {
            "category":"Organizations",
            "subcategory":"Community Association",
            "type":"Services"
        }
    ],
    "sg:phone":"+1 780 672 3325",
    "sg:postcode":"T4V 0J9",
    "sg:province":"AB",
    "sg:tags":[
        "club"
    ],
    "wof:name":"Royal Canadian Legion",
    "wof:placetype":"venue"
},
  "geometry": {"coordinates":[-112.837913513,53.0178108215],"type":"Point"}
}