{
  "type": "Feature",
  "properties": {
    "addr:full":"5360 Airport Rd S Richmond BC V7B 1B4",
    "addr:housenumber":"5360",
    "addr:postcode":"v7b 1b4",
    "addr:street":"Airport Rd",
    "iso:country":"CA",
    "sg:address":"5360 Airport Rd S",
    "sg:city":"Richmond",
    "sg:classifiers":[
        {
            "category":"Manufacturing",
            "subcategory":"Lumber",
            "type":"Manufacturing & Wholesale Goods"
        }
    ],
    "sg:phone":"+1 604 273 7375",
    "sg:postcode":"V7B 1B4",
    "sg:province":"BC",
    "wof:name":"West Fraser Timber CO Ltd",
    "wof:placetype":"venue"
},
  "geometry": {"coordinates":[-123.16560363799999,49.1805000305],"type":"Point"}
}