{
  "type": "Feature",
  "properties": {
    "addr:full":"50 Hastings St N Bancroft ON K0L 1C0",
    "addr:housenumber":"50",
    "addr:postcode":"k0l 1c0",
    "addr:street":"Hastings St N",
    "iso:country":"CA",
    "sg:address":"50 Hastings St N",
    "sg:city":"Bancroft",
    "sg:classifiers":[
        {
            "category":"Banks & Credit Unions",
            "subcategory":"Bank",
            "type":"Services"
        }
    ],
    "sg:phone":"+1 613 332 2040",
    "sg:postcode":"K0L 1C0",
    "sg:province":"ON",
    "wof:name":"Scotiabank",
    "wof:placetype":"venue"
},
  "geometry": {"coordinates":[-77.85436199999999,45.057987],"type":"Point"}
}