{
  "type": "Feature",
  "properties": {
    "addr:full":"Vanier QC G1M 3L2",
    "addr:postcode":"g1m 3l2",
    "iso:country":"CA",
    "sg:city":"Vanier",
    "sg:classifiers":[
        {
            "category":"Retail",
            "subcategory":"Auto Rental",
            "type":"Services"
        }
    ],
    "sg:phone":"+1 418 681 0131",
    "sg:postcode":"G1M 3L2",
    "sg:province":"QC",
    "sg:tags":[
        "renting",
        "automobile"
    ],
    "wof:name":"Discount Location D'Autos",
    "wof:placetype":"venue"
},
  "geometry": {"coordinates":[-71.27276611329999,46.8251533508],"type":"Point"}
}