{
  "type": "Feature",
  "properties": {
    "addr:full":"730 Rue Principale Beresford NB E8K 2B7",
    "addr:housenumber":"730",
    "addr:postcode":"e8k 2b7",
    "addr:street":"Rue Principale",
    "iso:country":"CA",
    "sg:address":"730 Rue Principale",
    "sg:city":"Beresford",
    "sg:classifiers":[
        {
            "category":"Food & Beverages",
            "subcategory":"Groceries & Convenience Stores",
            "type":"Retail Goods"
        }
    ],
    "sg:phone":"+1 506 542 1515",
    "sg:postcode":"E8K 2B7",
    "sg:province":"NB",
    "wof:name":"Depanneur L'Exit Convenience",
    "wof:placetype":"venue"
},
  "geometry": {"coordinates":[-65.706001,47.710335],"type":"Point"}
}