{
  "type": "Feature",
  "properties": {
    "addr:full":"7070 Market St Port Hardy BC V0N 2P0",
    "addr:housenumber":"7070",
    "addr:postcode":"v0n 2p0",
    "addr:street":"Market St",
    "iso:country":"CA",
    "sg:address":"7070 Market St",
    "sg:city":"Port Hardy",
    "sg:classifiers":[
        {
            "category":"Sports & Exercise",
            "subcategory":"Gym",
            "type":"Entertainment"
        }
    ],
    "sg:phone":"+1 250 949 6446",
    "sg:postcode":"V0N 2P0",
    "sg:province":"BC",
    "sg:tags":[
        "club",
        "health",
        "studio",
        "gymnasium"
    ],
    "wof:name":"First Choice Fitness",
    "wof:placetype":"venue"
},
  "geometry": {"coordinates":[-127.492454529,50.7204971313],"type":"Point"}
}