{
  "type": "Feature",
  "properties": {
    "iso:country":"CA",
    "sg:city":"Gores Landing",
    "sg:classifiers":[
        {
            "category":"Travel",
            "subcategory":"Hotels & Motels",
            "type":"Entertainment"
        }
    ],
    "sg:phone":"+1 905 342 3400",
    "sg:postcode":"K0K 2E0",
    "sg:province":"ON",
    "sg:tags":[
        "cottage",
        "cabin"
    ],
    "wof:name":"Adventure Bay",
    "wof:placetype":"venue"
},
  "geometry": {"coordinates":[-78.23249053959999,44.1192054749],"type":"Point"}
}