{
  "type": "Feature",
  "properties": {
    "iso:country":"CA",
    "sg:city":"Mississauga",
    "sg:classifiers":[
        {
            "category":"Personal",
            "subcategory":"Tanning Parlor",
            "type":"Services"
        }
    ],
    "sg:phone":"+1 905 897 0643",
    "sg:postcode":"L4Y 4G4",
    "sg:province":"ON",
    "sg:tags":[
        "salon"
    ],
    "wof:name":"R X Soleil Pro Sun Tanning",
    "wof:placetype":"venue"
},
  "geometry": {"coordinates":[-79.584724,43.608334],"type":"Point"}
}