{
  "type": "Feature",
  "properties": {
    "addr:full":"223 Main St N Morris MB R0G 1K0",
    "addr:housenumber":"223",
    "addr:postcode":"r0g 1k0",
    "addr:street":"Main St N",
    "iso:country":"CA",
    "sg:address":"223 Main St N",
    "sg:city":"Morris",
    "sg:classifiers":[
        {
            "category":"Recreation",
            "type":"Entertainment"
        }
    ],
    "sg:phone":"+1 204 746 6300",
    "sg:postcode":"R0G 1K0",
    "sg:province":"MB",
    "sg:tags":[
        "lottery",
        "agent"
    ],
    "wof:name":"Manitoba Lotteries Corp",
    "wof:placetype":"venue"
},
  "geometry": {"coordinates":[-97.36483800000001,49.356838],"type":"Point"}
}