{
  "type": "Feature",
  "properties": {
    "addr:full":"5911 5 St SE Calgary AB T2H 1L5",
    "addr:housenumber":"5911 5",
    "addr:postcode":"t2h 1l5",
    "addr:street":"St Se",
    "iso:country":"CA",
    "sg:address":"5911 5 St SE",
    "sg:city":"Calgary",
    "sg:classifiers":[
        {
            "category":"Retail",
            "subcategory":"Auto Rental",
            "type":"Services"
        }
    ],
    "sg:phone":"+1 403 253 7555",
    "sg:postcode":"T2H 1L5",
    "sg:province":"AB",
    "sg:tags":[
        "renting",
        "truck",
        "leasing"
    ],
    "wof:name":"Pac Lease",
    "wof:placetype":"venue"
},
  "geometry": {"coordinates":[-114.05127,51.000706],"type":"Point"}
}