{
  "type": "Feature",
  "properties": {
    "addr:full":"835 Topsail Rd Mount Pearl NL A1N 3J6",
    "addr:housenumber":"835",
    "addr:postcode":"a1n 3j6",
    "addr:street":"Topsail Rd",
    "iso:country":"CA",
    "sg:address":"835 Topsail Rd",
    "sg:city":"Mount Pearl",
    "sg:classifiers":[
        {
            "category":"Health Services",
            "subcategory":"Doctor",
            "type":"Services"
        }
    ],
    "sg:phone":"+1 709 364 4281",
    "sg:postcode":"A1N 3J6",
    "sg:province":"NL",
    "sg:tags":[
        "dentist"
    ],
    "wof:name":"Easton, E DDS",
    "wof:placetype":"venue"
},
  "geometry": {"coordinates":[-52.7914466858,47.5240516663],"type":"Point"}
}