{
  "type": "Feature",
  "properties": {
    "addr:full":"1555 Midland Ave Scarborough ON M1P 3C1",
    "addr:housenumber":"1555",
    "addr:postcode":"m1p 3c1",
    "addr:street":"Midland Ave",
    "iso:country":"CA",
    "sg:address":"1555 Midland Ave",
    "sg:city":"Scarborough",
    "sg:classifiers":[
        {
            "category":"Education",
            "subcategory":"School",
            "type":"Public Place"
        }
    ],
    "sg:phone":"+1 416 396 6695",
    "sg:postcode":"M1P 3C1",
    "sg:province":"ON",
    "wof:name":"Bendale Bti",
    "wof:placetype":"venue"
},
  "geometry": {"coordinates":[-79.2658004761,43.7541885376],"type":"Point"}
}