{
  "type": "Feature",
  "properties": {
    "addr:full":"94 Huron St Ripley ON N0G 2R0",
    "addr:housenumber":"94",
    "addr:postcode":"n0g 2r0",
    "addr:street":"Huron St",
    "iso:country":"CA",
    "sg:address":"94 Huron St",
    "sg:city":"Ripley",
    "sg:classifiers":[
        {
            "category":"Wholesale",
            "subcategory":"Farm Supplies",
            "type":"Manufacturing & Wholesale Goods"
        }
    ],
    "sg:phone":"+1 519 395 5955",
    "sg:postcode":"N0G 2R0",
    "sg:province":"ON",
    "sg:tags":[
        "feed"
    ],
    "wof:name":"Thompson Feed & Supply",
    "wof:placetype":"venue"
},
  "geometry": {"coordinates":[-81.57751500000001,44.07201],"type":"Point"}
}