{
  "type": "Feature",
  "properties": {
    "addr:full":"354 9th St E Owen Sound ON N4K 1P1",
    "addr:housenumber":"354",
    "addr:postcode":"n4k 1p1",
    "addr:street":"9Th St E",
    "iso:country":"CA",
    "sg:address":"354 9th St E",
    "sg:city":"Owen Sound",
    "sg:classifiers":[
        {
            "category":"Personal",
            "subcategory":"Beauty Salon",
            "type":"Services"
        }
    ],
    "sg:phone":"+1 519 376 9204",
    "sg:postcode":"N4K 1P1",
    "sg:province":"ON",
    "wof:name":"Hairs To You",
    "wof:placetype":"venue"
},
  "geometry": {"coordinates":[-80.94001799999999,44.566296],"type":"Point"}
}