{
  "type": "Feature",
  "properties": {
    "addr:full":"377 Donlands Ave East York ON M4J 3S2",
    "addr:housenumber":"377",
    "addr:postcode":"m4j 3s2",
    "addr:street":"Donlands Ave",
    "iso:country":"CA",
    "sg:address":"377 Donlands Ave",
    "sg:city":"East York",
    "sg:classifiers":[
        {
            "category":"Restaurant",
            "type":"Food & Drink"
        }
    ],
    "sg:phone":"+1 416 425 6685",
    "sg:postcode":"M4J 3S2",
    "sg:province":"ON",
    "wof:name":"Raj Kapuri Paan & Snacks",
    "wof:placetype":"venue"
},
  "geometry": {"coordinates":[-79.34242999999999,43.693497],"type":"Point"}
}