{
  "type": "Feature",
  "properties": {
    "addr:full":"34 Brunswick St Stratford ON N5A 3L8",
    "addr:housenumber":"34",
    "addr:postcode":"n5a 3l8",
    "addr:street":"Brunswick St",
    "iso:country":"CA",
    "sg:address":"34 Brunswick St",
    "sg:city":"Stratford",
    "sg:classifiers":[
        {
            "category":"Restaurant",
            "type":"Food & Drink"
        }
    ],
    "sg:phone":"+1 519 271 5645",
    "sg:postcode":"N5A 3L8",
    "sg:province":"ON",
    "wof:name":"Keystone Alley Cafe",
    "wof:placetype":"venue"
},
  "geometry": {"coordinates":[-80.98080400000001,43.369884],"type":"Point"}
}