{
  "type": "Feature",
  "properties": {
    "addr:full":"Nanaimo BC V9T 4B5",
    "addr:postcode":"v9t 4b5",
    "iso:country":"CA",
    "sg:city":"Nanaimo",
    "sg:classifiers":[
        {
            "category":"Health Services",
            "subcategory":"Doctor",
            "type":"Services"
        }
    ],
    "sg:phone":"+1 250 751 7850",
    "sg:postcode":"V9T 4B5",
    "sg:province":"BC",
    "sg:tags":[
        "physician",
        "surgeon"
    ],
    "wof:name":"Medicine Cabinet Medical Clnc",
    "wof:placetype":"venue"
},
  "geometry": {"coordinates":[-124.001693726,49.2077102661],"type":"Point"}
}