{
  "type": "Feature",
  "properties": {
    "addr:full":"Edmonton AB T5V 1M8",
    "addr:postcode":"t5v 1m8",
    "iso:country":"CA",
    "sg:city":"Edmonton",
    "sg:classifiers":[
        {
            "category":"Freight",
            "type":"Transportation"
        }
    ],
    "sg:phone":"+1 780 455 1224",
    "sg:postcode":"T5V 1M8",
    "sg:province":"AB",
    "wof:name":"Intra-West Transportation Syst",
    "wof:placetype":"venue"
},
  "geometry": {"coordinates":[-113.61170199999999,53.570641],"type":"Point"}
}