{
  "type": "Feature",
  "properties": {
    "iso:country":"CA",
    "sg:address":"896 Innisfil Beach Rd",
    "sg:city":"Innisfil",
    "sg:classifiers":[
        {
            "category":"Health Services",
            "subcategory":"Chiropractor",
            "type":"Services"
        }
    ],
    "sg:phone":"+1 705 431 0505",
    "sg:postcode":"L9S 2C2",
    "sg:province":"ON",
    "wof:name":"Alcona Chiropractic & Natural",
    "wof:placetype":"venue"
},
  "geometry": {"coordinates":[-79.54452514650001,44.3157958984],"type":"Point"}
}