{
  "type": "Feature",
  "properties": {
    "addr:full":"Cheticamp NS B0E 1H0",
    "addr:postcode":"b0e 1h0",
    "iso:country":"CA",
    "sg:city":"Cheticamp",
    "sg:classifiers":[
        {
            "category":"Health Services",
            "subcategory":"Doctor",
            "type":"Services"
        }
    ],
    "sg:phone":"+1 902 224 3110",
    "sg:postcode":"B0E 1H0",
    "sg:province":"NS",
    "sg:tags":[
        "physician",
        "surgeon"
    ],
    "wof:name":"Aucoin, Mercel MD",
    "wof:placetype":"venue"
},
  "geometry": {"coordinates":[-61.0166702271,46.6245193481],"type":"Point"}
}