{
  "type": "Feature",
  "properties": {
    "addr:full":"40 Boul Joubert E Sayabec QC G0J 3K0",
    "addr:housenumber":"40",
    "addr:postcode":"g0j 3k0",
    "addr:street":"Boul Joubert E",
    "iso:country":"CA",
    "sg:address":"40 Boul Joubert E",
    "sg:city":"Sayabec",
    "sg:classifiers":[
        {
            "category":"Restaurant",
            "type":"Food & Drink"
        }
    ],
    "sg:phone":"+1 418 536 3387",
    "sg:postcode":"G0J 3K0",
    "sg:province":"QC",
    "wof:name":"Casse-Croute Ginette Beaudoin",
    "wof:placetype":"venue"
},
  "geometry": {"coordinates":[-67.679924,48.566193],"type":"Point"}
}