{
  "type": "Feature",
  "properties": {
    "iso:country":"CA",
    "sg:address":"4227 Rue Saint-Jacques",
    "sg:city":"Montreal",
    "sg:classifiers":[
        {
            "category":"Health Services",
            "subcategory":"Doctor",
            "type":"Services"
        }
    ],
    "sg:phone":"+1 514 935 4330",
    "sg:postcode":"H4C 1J5",
    "sg:province":"QC",
    "sg:tags":[
        "clinic"
    ],
    "wof:name":"Clinique Medicale St-Henri",
    "wof:placetype":"venue"
},
  "geometry": {"coordinates":[-73.587646,45.477112],"type":"Point"}
}