{
  "type": "Feature",
  "properties": {
    "iso:country":"CA",
    "sg:address":"6880 11 St SE",
    "sg:city":"Calgary",
    "sg:classifiers":[
        {
            "category":"Utilities",
            "subcategory":"Mobile Phone",
            "type":"Services"
        }
    ],
    "sg:phone":"+1 403 681 1655",
    "sg:postcode":"T2H 2T9",
    "sg:province":"AB",
    "sg:tags":[
        "telephone",
        "cellular"
    ],
    "wof:name":"Rogers At & T Wireless",
    "wof:placetype":"venue"
},
  "geometry": {"coordinates":[-114.040031433,50.9924201965],"type":"Point"}
}