{
  "type": "Feature",
  "properties": {
    "iso:country":"CA",
    "sg:address":"8111 43 St NW",
    "sg:city":"Edmonton",
    "sg:classifiers":[
        {
            "category":"Education",
            "subcategory":"Dance Studio",
            "type":"Public Place"
        }
    ],
    "sg:phone":"+1 780 466 4231",
    "sg:postcode":"T6B 2M3",
    "sg:province":"AB",
    "sg:tags":[
        "instruction",
        "dancing"
    ],
    "wof:name":"Strathcona School of Dancing",
    "wof:placetype":"venue"
},
  "geometry": {"coordinates":[-113.407531738,53.5166778564],"type":"Point"}
}