{
  "type": "Feature",
  "properties": {
    "iso:country":"CA",
    "sg:address":"245 Riviera Dr # 12",
    "sg:city":"Markham",
    "sg:classifiers":[
        {
            "category":"Wholesale",
            "subcategory":"Machinery & Supplies",
            "type":"Manufacturing & Wholesale Goods"
        }
    ],
    "sg:phone":"+1 905 940 5577",
    "sg:postcode":"L3R 5J9",
    "sg:province":"ON",
    "sg:tags":[
        "equipment",
        "plastic"
    ],
    "wof:name":"Stephen Sales Group",
    "wof:placetype":"venue"
},
  "geometry": {"coordinates":[-79.337952,43.833412],"type":"Point"}
}