{
  "type": "Feature",
  "properties": {
    "addr:full":"Laval QC H7W 1T7",
    "addr:postcode":"h7w 1t7",
    "iso:country":"CA",
    "sg:city":"Laval",
    "sg:classifiers":[
        {
            "category":"Health Services",
            "subcategory":"Podiatrist",
            "type":"Services"
        }
    ],
    "sg:phone":"+1 450 682 7800",
    "sg:postcode":"H7W 1T7",
    "sg:province":"QC",
    "sg:tags":[
        "clinic"
    ],
    "wof:name":"Clinique Podiatrique Chomedey",
    "wof:placetype":"venue"
},
  "geometry": {"coordinates":[-73.7600784302,45.5375518799],"type":"Point"}
}