{
  "type": "Feature",
  "properties": {
    "addr:full":"355 Rue Sainte-Catherine O Montreal QC H3B 1A5",
    "addr:housenumber":"355",
    "addr:postcode":"h3b 1a5",
    "addr:street":"Rue Sainte-Catherine O",
    "iso:country":"CA",
    "sg:address":"355 Rue Sainte-Catherine O",
    "sg:city":"Montreal",
    "sg:classifiers":[
        {
            "category":"Real Estate",
            "subcategory":"Real Estate Operator",
            "type":"Services"
        }
    ],
    "sg:phone":"+1 514 843 4987",
    "sg:postcode":"H3B 1A5",
    "sg:province":"QC",
    "sg:tags":[
        "building",
        "parks"
    ],
    "wof:name":"3081699 Canada Inc",
    "wof:placetype":"venue"
},
  "geometry": {"coordinates":[-73.56098175050001,45.5133514404],"type":"Point"}
}