{
  "type": "Feature",
  "properties": {
    "addr:full":"85 Little John Rd Dundas ON L9H 4H1",
    "addr:housenumber":"85",
    "addr:postcode":"l9h 4h1",
    "addr:street":"Little John Rd",
    "iso:country":"CA",
    "sg:address":"85 Little John Rd",
    "sg:city":"Dundas",
    "sg:classifiers":[
        {
            "category":"Personal",
            "subcategory":"Beauty Salon",
            "type":"Services"
        }
    ],
    "sg:phone":"+1 905 628 4287",
    "sg:postcode":"L9H 4H1",
    "sg:province":"ON",
    "wof:name":"Curlco Industries Inc",
    "wof:placetype":"venue"
},
  "geometry": {"coordinates":[-79.949127,43.256638],"type":"Point"}
}