{
  "type": "Feature",
  "properties": {
    "addr:full":"6695 Dover Rd Nanaimo BC V9V 1A6",
    "addr:housenumber":"6695",
    "addr:postcode":"v9v 1a6",
    "addr:street":"Dover Rd",
    "iso:country":"CA",
    "sg:address":"6695 Dover Rd",
    "sg:city":"Nanaimo",
    "sg:classifiers":[
        {
            "category":"Wholesale",
            "subcategory":"Toys & Hobbies",
            "type":"Manufacturing & Wholesale Goods"
        }
    ],
    "sg:phone":"+1 250 390 7450",
    "sg:postcode":"V9V 1A6",
    "sg:province":"BC",
    "wof:name":"Marianne's Collectibles",
    "wof:placetype":"venue"
},
  "geometry": {"coordinates":[-124.050713,49.241566],"type":"Point"}
}