{
  "type": "Feature",
  "properties": {
    "addr:full":"Regina SK S4N 0S2",
    "addr:postcode":"s4n 0s2",
    "iso:country":"CA",
    "sg:city":"Regina",
    "sg:classifiers":[
        {
            "category":"Food & Beverages",
            "subcategory":"Bakery",
            "type":"Retail Goods"
        }
    ],
    "sg:phone":"+1 306 525 9121",
    "sg:postcode":"S4N 0S2",
    "sg:province":"SK",
    "sg:tags":[
        "doughnut"
    ],
    "wof:name":"Douglas Park Esso",
    "wof:placetype":"venue"
},
  "geometry": {"coordinates":[-104.570198,50.440281],"type":"Point"}
}