{
  "type": "Feature",
  "properties": {
    "addr:full":"111 Front St Niagara on the Lake ON L0S 1J0",
    "addr:housenumber":"111",
    "addr:postcode":"l0s 1j0",
    "addr:street":"Front St;On",
    "iso:country":"CA",
    "sg:address":"111 Front St",
    "sg:city":"Niagara on the Lake",
    "sg:classifiers":[
        {
            "category":"Travel",
            "subcategory":"Hotels & Motels",
            "type":"Entertainment"
        }
    ],
    "sg:phone":"+1 905 468 5565",
    "sg:postcode":"L0S 1J0",
    "sg:province":"ON",
    "sg:tags":[
        "breakfast",
        "accommodation",
        "bed"
    ],
    "wof:name":"Somerset Bed & Breakfast",
    "wof:placetype":"venue"
},
  "geometry": {"coordinates":[-79.07214355470001,43.2589035034],"type":"Point"}
}