{
  "type": "Feature",
  "properties": {
    "addr:full":"1850 Jane St York ON M9N 2T4",
    "addr:housenumber":"1850",
    "addr:postcode":"m9n 2t4",
    "addr:street":"Jane St",
    "iso:country":"CA",
    "sg:address":"1850 Jane St",
    "sg:city":"York",
    "sg:classifiers":[
        {
            "category":"Health Services",
            "subcategory":"Doctor",
            "type":"Services"
        }
    ],
    "sg:phone":"+1 416 247 7401",
    "sg:postcode":"M9N 2T4",
    "sg:province":"ON",
    "sg:tags":[
        "physician",
        "surgeon"
    ],
    "wof:name":"Waisberg, Jon MD",
    "wof:placetype":"venue"
},
  "geometry": {"coordinates":[-79.5054321289,43.7082557678],"type":"Point"}
}