{
  "type": "Feature",
  "properties": {
    "addr:full":"Hepworth ON N0H 1P0",
    "addr:postcode":"n0h 1p0",
    "iso:country":"CA",
    "sg:city":"Hepworth",
    "sg:classifiers":[
        {
            "category":"Manufacturing",
            "subcategory":"Wood Products",
            "type":"Manufacturing & Wholesale Goods"
        }
    ],
    "sg:phone":"+1 519 935 2652",
    "sg:postcode":"N0H 1P0",
    "sg:province":"ON",
    "sg:tags":[
        "pallet",
        "company",
        "logging"
    ],
    "wof:name":"David Mc Nabb Pallet Mfg Inc",
    "wof:placetype":"venue"
},
  "geometry": {"coordinates":[-81.13426971440001,44.6472892761],"type":"Point"}
}