{
  "type": "Feature",
  "properties": {
    "addr:full":"Niagara Falls ON L2E 7H3",
    "addr:postcode":"l2e 7h3",
    "iso:country":"CA",
    "sg:city":"Niagara Falls",
    "sg:classifiers":[
        {
            "category":"Wholesale",
            "subcategory":"Auto Parts",
            "type":"Manufacturing & Wholesale Goods"
        }
    ],
    "sg:phone":"+1 905 358 6335",
    "sg:postcode":"L2E 7H3",
    "sg:province":"ON",
    "sg:tags":[
        "body",
        "automobile",
        "shop"
    ],
    "wof:name":"Painters Supply & Equipment",
    "wof:placetype":"venue"
},
  "geometry": {"coordinates":[-79.086189,43.114124],"type":"Point"}
}