{
  "type": "Feature",
  "properties": {
    "addr:full":"476 Main St Selkirk MB R1A 1W2",
    "addr:housenumber":"476",
    "addr:postcode":"r1a 1w2",
    "addr:street":"Main St",
    "iso:country":"CA",
    "sg:address":"476 Main St",
    "sg:city":"Selkirk",
    "sg:classifiers":[
        {
            "category":"Restaurant",
            "type":"Food & Drink"
        }
    ],
    "sg:phone":"+1 204 785 8501",
    "sg:postcode":"R1A 1W2",
    "sg:province":"MB",
    "wof:name":"Chicken Delight",
    "wof:placetype":"venue"
},
  "geometry": {"coordinates":[-96.867980957,50.1475219727],"type":"Point"}
}