{
  "type": "Feature",
  "properties": {
    "addr:full":"24 Queens Ave Leamington ON N8H 3G8",
    "addr:housenumber":"24",
    "addr:postcode":"n8h 3g8",
    "addr:street":"Queens Ave",
    "iso:country":"CA",
    "sg:address":"24 Queens Ave",
    "sg:city":"Leamington",
    "sg:classifiers":[
        {
            "category":"Professional",
            "subcategory":"Lawyer & Legal Services",
            "type":"Services"
        }
    ],
    "sg:phone":"+1 519 322 1144",
    "sg:postcode":"N8H 3G8",
    "sg:province":"ON",
    "sg:tags":[
        "attorney"
    ],
    "wof:name":"Raphael Partners",
    "wof:placetype":"venue"
},
  "geometry": {"coordinates":[-82.60180699999999,42.054119],"type":"Point"}
}