{
  "type": "Feature",
  "properties": {
    "addr:full":"8 Churchill Pl Woodstock ON N4S 7V9",
    "addr:housenumber":"8",
    "addr:postcode":"n4s 7v9",
    "addr:street":"Churchill Pl",
    "iso:country":"CA",
    "sg:address":"8 Churchill Pl",
    "sg:city":"Woodstock",
    "sg:phone":"+1 519 539 8191",
    "sg:postcode":"N4S 7V9",
    "sg:province":"ON",
    "sg:tags":[
        "oil"
    ],
    "wof:name":"Dave Lippert Fuels Ltd",
    "wof:placetype":"venue"
},
  "geometry": {"coordinates":[-80.72695922849999,43.1342353821],"type":"Point"}
}