{
  "type": "Feature",
  "properties": {
    "iso:country":"CA",
    "sg:address":"152 Boul Barrette",
    "sg:city":"Chicoutimi",
    "sg:classifiers":[
        {
            "category":"Health Services",
            "subcategory":"Doctor",
            "type":"Services"
        }
    ],
    "sg:phone":"+1 418 543 3838",
    "sg:postcode":"G7H 7W8",
    "sg:province":"QC",
    "sg:tags":[
        "clinic"
    ],
    "wof:name":"Clinique DE Medicine Familiale",
    "wof:placetype":"venue"
},
  "geometry": {"coordinates":[-71.077644,48.396748],"type":"Point"}
}