{
  "type": "Feature",
  "properties": {
    "addr:full":"281 Greenbank Rd Nepean ON K2H 8K9",
    "addr:housenumber":"281",
    "addr:postcode":"k2h 8k9",
    "addr:street":"Greenbank Rd",
    "iso:country":"CA",
    "sg:address":"281 Greenbank Rd",
    "sg:city":"Nepean",
    "sg:classifiers":[
        {
            "category":"Personal",
            "subcategory":"Tanning Parlor",
            "type":"Services"
        }
    ],
    "sg:phone":"+1 613 820 9122",
    "sg:postcode":"K2H 8K9",
    "sg:province":"ON",
    "sg:tags":[
        "salon"
    ],
    "wof:name":"Sun City Tanning Studio",
    "wof:placetype":"venue"
},
  "geometry": {"coordinates":[-75.77784,45.324059],"type":"Point"}
}