{
  "type": "Feature",
  "properties": {
    "iso:country":"CA",
    "sg:address":"200 Adelaide St S",
    "sg:city":"London",
    "sg:classifiers":[
        {
            "category":"Professional",
            "subcategory":"Business Services",
            "type":"Services"
        }
    ],
    "sg:phone":"+1 519 681 8782",
    "sg:postcode":"N5Z 3L1",
    "sg:province":"ON",
    "sg:tags":[
        "planner",
        "space",
        "furniture"
    ],
    "wof:name":"Atwork Office Interiors Inc",
    "wof:placetype":"venue"
},
  "geometry": {"coordinates":[-81.221031,42.964958],"type":"Point"}
}