{
  "type": "Feature",
  "properties": {
    "addr:full":"7250 Rue Durocher Montreal QC H3N 1Z9",
    "addr:housenumber":"7250",
    "addr:postcode":"h3n 1z9",
    "addr:street":"Rue Durocher",
    "iso:country":"CA",
    "sg:address":"7250 Rue Durocher",
    "sg:city":"Montreal",
    "sg:classifiers":[
        {
            "category":"Wholesale",
            "subcategory":"Durable Goods & Equipment",
            "type":"Manufacturing & Wholesale Goods"
        }
    ],
    "sg:phone":"+1 514 274 9793",
    "sg:postcode":"H3N 1Z9",
    "sg:province":"QC",
    "sg:tags":[
        "instrument",
        "musical"
    ],
    "wof:name":"Entreprises Frm",
    "wof:placetype":"venue"
},
  "geometry": {"coordinates":[-73.6240310669,45.5292510986],"type":"Point"}
}