{
  "type": "Feature",
  "properties": {
    "iso:country":"CA",
    "sg:city":"Delta",
    "sg:classifiers":[
        {
            "category":"Manufacturing",
            "subcategory":"Toys & Sporting Goods",
            "type":"Manufacturing & Wholesale Goods"
        }
    ],
    "sg:phone":"+1 604 946 1512",
    "sg:postcode":"V4G 1E2",
    "sg:province":"BC",
    "sg:tags":[
        "tackle",
        "fishing"
    ],
    "wof:name":"Delta Tackle CO Ltd",
    "wof:placetype":"venue"
},
  "geometry": {"coordinates":[-123.01895141599999,49.1323280334],"type":"Point"}
}