{
  "type": "Feature",
  "properties": {
    "addr:full":"Highway 310 Sprague MB R0A 1Z0",
    "addr:postcode":"r0a 1z0",
    "addr:street":"Highway 310",
    "iso:country":"CA",
    "sg:address":"Highway 310",
    "sg:city":"Sprague",
    "sg:classifiers":[
        {
            "category":"Government",
            "subcategory":"Office",
            "type":"Public Place"
        }
    ],
    "sg:phone":"+1 204 437 2266",
    "sg:postcode":"R0A 1Z0",
    "sg:province":"MB",
    "wof:name":"Canada South Junction Customs",
    "wof:placetype":"venue"
},
  "geometry": {"coordinates":[-95.642876,49.035049],"type":"Point"}
}