{
  "type": "Feature",
  "properties": {
    "addr:full":"557 Cambridge St S Ottawa ON K1S 4J4",
    "addr:housenumber":"557",
    "addr:postcode":"k1s 4j4",
    "addr:street":"Cambridge St S",
    "iso:country":"CA",
    "sg:address":"557 Cambridge St S",
    "sg:city":"Ottawa",
    "sg:classifiers":[
        {
            "category":"Building & Trades",
            "subcategory":"Plumbing",
            "type":"Services"
        }
    ],
    "sg:phone":"+1 613 231 4307",
    "sg:postcode":"K1S 4J4",
    "sg:province":"ON",
    "sg:tags":[
        "mechanical",
        "contractor"
    ],
    "wof:name":"Tesc Contracting Ltd",
    "wof:placetype":"venue"
},
  "geometry": {"coordinates":[-75.700478,45.399849],"type":"Point"}
}