{
  "type": "Feature",
  "properties": {
    "iso:country":"CA",
    "sg:address":"6021 Yonge St",
    "sg:city":"North York",
    "sg:classifiers":[
        {
            "category":"Wholesale",
            "subcategory":"Machinery & Supplies",
            "type":"Manufacturing & Wholesale Goods"
        }
    ],
    "sg:phone":"+1 416 733 0777",
    "sg:postcode":"M2M 3W2",
    "sg:province":"ON",
    "sg:tags":[
        "packaging",
        "bag"
    ],
    "wof:name":"Shirriff Packaging Inc",
    "wof:placetype":"venue"
},
  "geometry": {"coordinates":[-79.4177703857,43.7892723083],"type":"Point"}
}