{
  "type": "Feature",
  "properties": {
    "addr:full":"620 Simpson St Thunder Bay ON P7C 3J7",
    "addr:housenumber":"620",
    "addr:postcode":"p7c 3j7",
    "addr:street":"Simpson St",
    "iso:country":"CA",
    "sg:address":"620 Simpson St",
    "sg:city":"Thunder Bay",
    "sg:classifiers":[
        {
            "category":"Home & Garden",
            "subcategory":"Hardware",
            "type":"Retail Goods"
        }
    ],
    "sg:phone":"+1 807 623 6052",
    "sg:postcode":"P7C 3J7",
    "sg:province":"ON",
    "wof:name":"Maier Hardware Ltd",
    "wof:placetype":"venue"
},
  "geometry": {"coordinates":[-89.236031,48.392418],"type":"Point"}
}