{
  "type": "Feature",
  "properties": {
    "iso:country":"CA",
    "sg:address":"243 Commercial St",
    "sg:city":"Berwick",
    "sg:classifiers":[
        {
            "category":"Social Services",
            "subcategory":"Child Care",
            "type":"Services"
        }
    ],
    "sg:phone":"+1 902 538 7790",
    "sg:postcode":"B0P 1E0",
    "sg:province":"NS",
    "wof:name":"Orchard Away Day Care",
    "wof:placetype":"venue"
},
  "geometry": {"coordinates":[-64.7353668213,45.0433082581],"type":"Point"}
}