{
  "type": "Feature",
  "properties": {
    "addr:full":"1320 Rue Chabanel O Montreal QC H4N 1H4",
    "addr:housenumber":"1320",
    "addr:postcode":"h4n 1h4",
    "addr:street":"Rue Chabanel O",
    "iso:country":"CA",
    "sg:address":"1320 Rue Chabanel O",
    "sg:city":"Montreal",
    "sg:classifiers":[
        {
            "category":"Wholesale",
            "subcategory":"Meat",
            "type":"Manufacturing & Wholesale Goods"
        }
    ],
    "sg:phone":"+1 514 381 6447",
    "sg:postcode":"H4N 1H4",
    "sg:province":"QC",
    "sg:tags":[
        "butchering"
    ],
    "wof:name":"Thessalia Meat Market Enr",
    "wof:placetype":"venue"
},
  "geometry": {"coordinates":[-73.6408996582,45.5593986511],"type":"Point"}
}