{
  "type": "Feature",
  "properties": {
    "addr:full":"160 Hudson Ave NE Salmon Arm BC V1E 4N5",
    "addr:housenumber":"160",
    "addr:postcode":"v1e 4n5",
    "addr:street":"Hudson Ave Ne",
    "iso:country":"CA",
    "sg:address":"160 Hudson Ave NE",
    "sg:city":"Salmon Arm",
    "sg:classifiers":[
        {
            "category":"Shopping",
            "type":"Retail Goods"
        }
    ],
    "sg:phone":"+1 250 832 1855",
    "sg:postcode":"V1E 4N5",
    "sg:province":"BC",
    "sg:tags":[
        "picture",
        "frame"
    ],
    "wof:name":"Frame's By Filliatrault",
    "wof:placetype":"venue"
},
  "geometry": {"coordinates":[-119.281403,50.70203],"type":"Point"}
}