{
  "type": "Feature",
  "properties": {
    "addr:full":"44 Rue Saint-Nicolas Quebec QC G1K 6T2",
    "addr:housenumber":"44",
    "addr:postcode":"g1k 6t2",
    "addr:street":"Rue Saint-Nicolas",
    "iso:country":"CA",
    "sg:address":"44 Rue Saint-Nicolas",
    "sg:city":"Quebec",
    "sg:classifiers":[
        {
            "category":"Building & Trades",
            "subcategory":"Construction",
            "type":"Services"
        }
    ],
    "sg:phone":"+1 418 692 0580",
    "sg:postcode":"G1K 6T2",
    "sg:province":"QC",
    "sg:tags":[
        "designer"
    ],
    "wof:name":"Advanta Design Group Inc",
    "wof:placetype":"venue"
},
  "geometry": {"coordinates":[-71.213425,46.816208],"type":"Point"}
}