{
  "type": "Feature",
  "properties": {
    "addr:full":"15 Rue Waterman Saint-Lambert QC J4P 1R7",
    "addr:housenumber":"15",
    "addr:postcode":"j4p 1r7",
    "addr:street":"Rue Waterman",
    "iso:country":"CA",
    "sg:address":"15 Rue Waterman",
    "sg:city":"Saint-Lambert",
    "sg:classifiers":[
        {
            "category":"Professional",
            "subcategory":"Management & Consulting",
            "type":"Services"
        }
    ],
    "sg:phone":"+1 450 923 7970",
    "sg:postcode":"J4P 1R7",
    "sg:province":"QC",
    "sg:tags":[
        "communications",
        "consultant"
    ],
    "wof:name":"Stratege Idees",
    "wof:placetype":"venue"
},
  "geometry": {"coordinates":[-73.511696,45.498276],"type":"Point"}
}