{
  "type": "Feature",
  "properties": {
    "addr:full":"2500 Lawrence Ave E # 5 Scarborough ON M1P 2R7",
    "addr:housenumber":"2500",
    "addr:postcode":"m1p 2r7",
    "addr:street":"Lawrence Ave E # 5",
    "iso:country":"CA",
    "sg:address":"2500 Lawrence Ave E # 5",
    "sg:city":"Scarborough",
    "sg:classifiers":[
        {
            "category":"Autos & Motor Vehicles",
            "subcategory":"Auto Supplies",
            "type":"Retail Goods"
        }
    ],
    "sg:phone":"+1 416 750 9221",
    "sg:postcode":"M1P 2R7",
    "sg:province":"ON",
    "sg:tags":[
        "tire"
    ],
    "wof:name":"Tirecraft",
    "wof:placetype":"venue"
},
  "geometry": {"coordinates":[-79.26808200000001,43.751343],"type":"Point"}
}