{
  "type": "Feature",
  "properties": {
    "addr:full":"1221 Boul Marcotte Roberval QC G8H 3B8",
    "addr:housenumber":"1221",
    "addr:postcode":"g8h 3b8",
    "addr:street":"Boul Marcotte",
    "iso:country":"CA",
    "sg:address":"1221 Boul Marcotte",
    "sg:city":"Roberval",
    "sg:classifiers":[
        {
            "category":"Shopping",
            "subcategory":"Clothing, Apparel, & Fashions",
            "type":"Retail Goods"
        }
    ],
    "sg:phone":"+1 418 275 7439",
    "sg:postcode":"G8H 3B8",
    "sg:province":"QC",
    "sg:tags":[
        "item",
        "boutique"
    ],
    "wof:name":"Boutique Pentagone Inc",
    "wof:placetype":"venue"
},
  "geometry": {"coordinates":[-72.23406982420001,48.524269104],"type":"Point"}
}