{
  "type": "Feature",
  "properties": {
    "iso:country":"CA",
    "sg:address":"101 Rue Lachapelle E # F",
    "sg:city":"Saint-Remi",
    "sg:classifiers":[
        {
            "category":"Cinema",
            "subcategory":"Movie Rental",
            "type":"Entertainment"
        }
    ],
    "sg:phone":"+1 450 454 6167",
    "sg:postcode":"J0L 2L0",
    "sg:province":"QC",
    "sg:tags":[
        "leasing",
        "video",
        "disc",
        "tape"
    ],
    "wof:name":"Cine Video Jfd Enrg",
    "wof:placetype":"venue"
},
  "geometry": {"coordinates":[-73.61325836180001,45.2599334717],"type":"Point"}
}