{
  "type": "Feature",
  "properties": {
    "addr:full":"Winnipeg MB R2J 2M7",
    "addr:postcode":"r2j 2m7",
    "iso:country":"CA",
    "sg:city":"Winnipeg",
    "sg:classifiers":[
        {
            "category":"Building & Trades",
            "subcategory":"Construction",
            "type":"Services"
        }
    ],
    "sg:phone":"+1 204 982 5920",
    "sg:postcode":"R2J 2M7",
    "sg:province":"MB",
    "sg:tags":[
        "home",
        "builder"
    ],
    "wof:name":"Ladco Homes",
    "wof:placetype":"venue"
},
  "geometry": {"coordinates":[-97.078926,49.854237],"type":"Point"}
}