{
  "type": "Feature",
  "properties": {
    "addr:full":"1151 Rue Principale Canton-DE-Granby QC J2G 8C8",
    "addr:housenumber":"1151",
    "addr:postcode":"j2g 8c8",
    "addr:street":"Rue Principale",
    "iso:country":"CA",
    "sg:address":"1151 Rue Principale",
    "sg:city":"Canton-DE-Granby",
    "sg:classifiers":[
        {
            "category":"Wholesale",
            "subcategory":"Machinery & Supplies",
            "type":"Manufacturing & Wholesale Goods"
        }
    ],
    "sg:phone":"+1 450 378 4740",
    "sg:postcode":"J2G 8C8",
    "sg:province":"QC",
    "sg:tags":[
        "repairing",
        "automobile",
        "flat"
    ],
    "wof:name":"Ressorts D'Autos Menard Inc",
    "wof:placetype":"venue"
},
  "geometry": {"coordinates":[-72.77179,45.419769],"type":"Point"}
}