{
  "type": "Feature",
  "properties": {
    "addr:full":"Victoria BC V8P 2L5",
    "addr:postcode":"v8p 2l5",
    "iso:country":"CA",
    "sg:city":"Victoria",
    "sg:classifiers":[
        {
            "category":"Professional",
            "subcategory":"Computer Services",
            "type":"Services"
        }
    ],
    "sg:phone":"+1 250 479 8646",
    "sg:postcode":"V8P 2L5",
    "sg:province":"BC",
    "sg:tags":[
        "consultant",
        "designer"
    ],
    "wof:name":"Acquired Intelligence Inc",
    "wof:placetype":"venue"
},
  "geometry": {"coordinates":[-123.356338501,48.414981842],"type":"Point"}
}