{
  "type": "Feature",
  "properties": {
    "addr:full":"550 Alden Rd #111 Markham ON L3R 6A8",
    "addr:housenumber":"550",
    "addr:postcode":"l3r 6a8",
    "addr:street":"Alden Rd # 111",
    "iso:country":"CA",
    "sg:address":"550 Alden Rd #111",
    "sg:city":"Markham",
    "sg:classifiers":[
        {
            "category":"Utilities",
            "subcategory":"Mobile Phone",
            "type":"Services"
        }
    ],
    "sg:phone":"+1 905 940 6460",
    "sg:postcode":"L3R 6A8",
    "sg:province":"ON",
    "sg:tags":[
        "radio",
        "telephone",
        "cellular"
    ],
    "wof:name":"Verizon Wireless",
    "wof:placetype":"venue"
},
  "geometry": {"coordinates":[-79.3320770264,43.836681366],"type":"Point"}
}