{
  "type": "Feature",
  "properties": {
    "addr:full":"60 Commerce Valley Dr E Thornhill ON L3T 7P9",
    "addr:housenumber":"60",
    "addr:postcode":"l3t 7p9",
    "addr:street":"Commerce Valley Dr E",
    "iso:country":"CA",
    "sg:address":"60 Commerce Valley Dr E",
    "sg:city":"Thornhill",
    "sg:classifiers":[
        {
            "category":"Travel",
            "subcategory":"Travel Agent",
            "type":"Entertainment"
        }
    ],
    "sg:phone":"+1 905 771 3120",
    "sg:postcode":"L3T 7P9",
    "sg:province":"ON",
    "sg:tags":[
        "instruction",
        "bureau",
        "agency",
        "driving"
    ],
    "wof:name":"Caa South Central Ontario",
    "wof:placetype":"venue"
},
  "geometry": {"coordinates":[-79.377403,43.8405],"type":"Point"}
}