{
  "type": "Feature",
  "properties": {
    "addr:full":"Victoria BC V8Z 5T7",
    "addr:postcode":"v8z 5t7",
    "iso:country":"CA",
    "sg:city":"Victoria",
    "sg:classifiers":[
        {
            "category":"Building & Trades",
            "subcategory":"Plumbing",
            "type":"Services"
        }
    ],
    "sg:phone":"+1 250 652 0613",
    "sg:postcode":"V8Z 5T7",
    "sg:province":"BC",
    "sg:tags":[
        "contractor"
    ],
    "wof:name":"Mark's Plumbing & Heating CO",
    "wof:placetype":"venue"
},
  "geometry": {"coordinates":[-123.40361799999999,48.554916],"type":"Point"}
}