{
  "type": "Feature",
  "properties": {
    "iso:country":"CA",
    "sg:address":"415 May St N",
    "sg:city":"Thunder Bay",
    "sg:classifiers":[
        {
            "category":"Autos & Motor Vehicles",
            "subcategory":"Automobile Sales",
            "type":"Retail Goods"
        }
    ],
    "sg:phone":"+1 807 623 0643",
    "sg:postcode":"P7C 3R4",
    "sg:province":"ON",
    "sg:tags":[
        "car",
        "dealer"
    ],
    "wof:name":"Ken Peterson Sales & Leasing",
    "wof:placetype":"venue"
},
  "geometry": {"coordinates":[-89.2456665039,48.390586853],"type":"Point"}
}