{
  "type": "Feature",
  "properties": {
    "addr:full":"Peterborough ON K9J 7H8",
    "addr:postcode":"k9j 7h8",
    "iso:country":"CA",
    "sg:city":"Peterborough",
    "sg:classifiers":[
        {
            "category":"Health Services",
            "subcategory":"Doctor",
            "type":"Services"
        }
    ],
    "sg:phone":"+1 705 743 3851",
    "sg:postcode":"K9J 7H8",
    "sg:province":"ON",
    "sg:tags":[
        "physician",
        "surgeon"
    ],
    "wof:name":"Doris, F MD",
    "wof:placetype":"venue"
},
  "geometry": {"coordinates":[-78.3440628052,44.2987670898],"type":"Point"}
}