{
  "type": "Feature",
  "properties": {
    "addr:full":"638 Middlewoods Dr London ON N6G 1W8",
    "addr:housenumber":"638",
    "addr:postcode":"n6g 1w8",
    "addr:street":"Middlewoods Dr",
    "iso:country":"CA",
    "sg:address":"638 Middlewoods Dr",
    "sg:city":"London",
    "sg:classifiers":[
        {
            "category":"Building & Trades",
            "subcategory":"Landscaping Services",
            "type":"Services"
        }
    ],
    "sg:phone":"+1 519 474 0234",
    "sg:postcode":"N6G 1W8",
    "sg:province":"ON",
    "sg:tags":[
        "landscape",
        "contractor"
    ],
    "wof:name":"Modern Landscaping CO",
    "wof:placetype":"venue"
},
  "geometry": {"coordinates":[-81.29988899999999,42.999313],"type":"Point"}
}