{
  "type": "Feature",
  "properties": {
    "iso:country":"CA",
    "sg:address":"638 Middlewoods Dr",
    "sg:city":"London",
    "sg:classifiers":[
        {
            "category":"Building & Trades",
            "subcategory":"Landscaping Services",
            "type":"Services"
        }
    ],
    "sg:phone":"+1 519 474 0234",
    "sg:postcode":"N6G 1W8",
    "sg:province":"ON",
    "sg:tags":[
        "landscape",
        "contractor"
    ],
    "wof:name":"Modern Landscaping CO",
    "wof:placetype":"venue"
},
  "geometry": {"coordinates":[-81.299889,42.999313],"type":"Point"}
}