{
  "type": "Feature",
  "properties": {
    "addr:full":"185 Rue Godard Mont-Laurier QC J9L 3T5",
    "addr:housenumber":"185",
    "addr:postcode":"j9l 3t5",
    "addr:street":"Rue Godard",
    "iso:country":"CA",
    "sg:address":"185 Rue Godard",
    "sg:city":"Mont-Laurier",
    "sg:phone":"+1 819 623 2750",
    "sg:postcode":"J9L 3T5",
    "sg:province":"QC",
    "sg:tags":[
        "oil"
    ],
    "wof:name":"Petroles Esso Canada",
    "wof:placetype":"venue"
},
  "geometry": {"coordinates":[-75.4799575806,46.5460586548],"type":"Point"}
}