{
  "type": "Feature",
  "properties": {
    "addr:full":"1745 Ralph St North Vancouver BC V7K 1V8",
    "addr:housenumber":"1745",
    "addr:postcode":"v7k 1v8",
    "addr:street":"Ralph St",
    "iso:country":"CA",
    "sg:address":"1745 Ralph St",
    "sg:city":"North Vancouver",
    "sg:classifiers":[
        {
            "category":"Professional",
            "subcategory":"Accounting & Tax Preparation",
            "type":"Services"
        }
    ],
    "sg:phone":"+1 604 986 0751",
    "sg:postcode":"V7K 1V8",
    "sg:province":"BC",
    "sg:tags":[
        "accountant"
    ],
    "wof:name":"Jang, Norm",
    "wof:placetype":"venue"
},
  "geometry": {"coordinates":[-123.023674,49.34948],"type":"Point"}
}