{
  "type": "Feature",
  "properties": {
    "addr:full":"4894 Boul Des Sources Dollard-Des-Ormeaux QC H8Y 3C7",
    "addr:housenumber":"4894",
    "addr:postcode":"h8y 3c7",
    "addr:street":"Boul Des Sources",
    "iso:country":"CA",
    "sg:address":"4894 Boul Des Sources",
    "sg:city":"Dollard-Des-Ormeaux",
    "sg:classifiers":[
        {
            "category":"Shopping",
            "subcategory":"Pharmacy",
            "type":"Retail Goods"
        }
    ],
    "sg:phone":"+1 514 684 6131",
    "sg:postcode":"H8Y 3C7",
    "sg:province":"QC",
    "wof:name":"Jean Coutu",
    "wof:placetype":"venue"
},
  "geometry": {"coordinates":[-73.818558,45.505013],"type":"Point"}
}