{
  "type": "Feature",
  "properties": {
    "addr:full":"Hwy 21 Port Elgin ON N0H 2C5",
    "addr:postcode":"n0h 2c5",
    "addr:street":"Hwy 21 Port",
    "iso:country":"CA",
    "sg:address":"Hwy 21",
    "sg:city":"Port Elgin",
    "sg:classifiers":[
        {
            "category":"Retail",
            "subcategory":"Animal Services",
            "type":"Services"
        }
    ],
    "sg:phone":"+1 519 389 2031",
    "sg:postcode":"N0H 2C5",
    "sg:province":"ON",
    "sg:tags":[
        "pet",
        "grooming",
        "washing"
    ],
    "wof:name":"Heather's Poodle Care Ltd",
    "wof:placetype":"venue"
},
  "geometry": {"coordinates":[-81.3901138306,44.4346618652],"type":"Point"}
}