{
  "type": "Feature",
  "properties": {
    "addr:full":"5360 Av Du Marechal-Joffre Charny QC G6X 3C7",
    "addr:housenumber":"5360",
    "addr:postcode":"g6x 3c7",
    "addr:street":"Av Du Marechal-Joffre",
    "iso:country":"CA",
    "sg:address":"5360 Av Du Marechal-Joffre",
    "sg:city":"Charny",
    "sg:classifiers":[
        {
            "category":"Real Estate",
            "subcategory":"Real Estate Agent",
            "type":"Services"
        }
    ],
    "sg:phone":"+1 418 832 0443",
    "sg:postcode":"G6X 3C7",
    "sg:province":"QC",
    "sg:tags":[
        "tool",
        "desk"
    ],
    "wof:name":"Location D'Outils Abc Inc",
    "wof:placetype":"venue"
},
  "geometry": {"coordinates":[-71.26010894780001,46.7163619995],"type":"Point"}
}