{
  "type": "Feature",
  "properties": {
    "addr:full":"3001 Solandt Rd Kanata ON K2K 2M8",
    "addr:housenumber":"3001",
    "addr:postcode":"k2k 2m8",
    "addr:street":"Solandt Rd",
    "iso:country":"CA",
    "sg:address":"3001 Solandt Rd",
    "sg:city":"Kanata",
    "sg:classifiers":[
        {
            "category":"Manufacturing",
            "subcategory":"Electronics",
            "type":"Manufacturing & Wholesale Goods"
        }
    ],
    "sg:phone":"+1 613 599 3270",
    "sg:postcode":"K2K 2M8",
    "sg:province":"ON",
    "sg:tags":[
        "equipment",
        "electronic",
        "supply"
    ],
    "wof:name":"Lockheed Martin Canada Inc",
    "wof:placetype":"venue"
},
  "geometry": {"coordinates":[-75.91683999999999,45.343155],"type":"Point"}
}