{
  "type": "Feature",
  "properties": {
    "addr:full":"943 Rte DE LA Seigneurie Saint-Roch-Des-Aulnaies QC G0R 4E0",
    "addr:housenumber":"943",
    "addr:postcode":"g0r 4e0",
    "addr:street":"Rte De La Seigneurie",
    "iso:country":"CA",
    "sg:address":"943 Rte DE LA Seigneurie",
    "sg:city":"Saint-Roch-Des-Aulnaies",
    "sg:classifiers":[
        {
            "category":"Food & Beverages",
            "subcategory":"Groceries & Convenience Stores",
            "type":"Retail Goods"
        }
    ],
    "sg:phone":"+1 418 354 2518",
    "sg:postcode":"G0R 4E0",
    "sg:province":"QC",
    "sg:tags":[
        "grocer"
    ],
    "wof:name":"Alimentation St-Roch Enr",
    "wof:placetype":"venue"
},
  "geometry": {"coordinates":[-70.1741943359,47.3106536865],"type":"Point"}
}