{
  "type": "Feature",
  "properties": {
    "addr:full":"46 Poupore St Gogama ON P0M 1W0",
    "addr:housenumber":"46",
    "addr:postcode":"p0m 1w0",
    "addr:street":"Poupore St",
    "iso:country":"CA",
    "sg:address":"46 Poupore St",
    "sg:city":"Gogama",
    "sg:classifiers":[
        {
            "category":"Shopping",
            "subcategory":"Discount & Variety Stores",
            "type":"Retail Goods"
        }
    ],
    "sg:phone":"+1 705 894 9980",
    "sg:postcode":"P0M 1W0",
    "sg:province":"ON",
    "sg:tags":[
        "merchandise",
        "general"
    ],
    "wof:name":"Gogama General Store",
    "wof:placetype":"venue"
},
  "geometry": {"coordinates":[-81.723816,47.675583],"type":"Point"}
}