{
  "type": "Feature",
  "properties": {
    "iso:country":"CA",
    "sg:city":"London",
    "sg:classifiers":[
        {
            "category":"Restaurant",
            "type":"Food & Drink"
        }
    ],
    "sg:phone":"+1 519 672 4819",
    "sg:postcode":"N5W 6A8",
    "sg:province":"ON",
    "wof:name":"Bud's Restaurant",
    "wof:placetype":"venue"
},
  "geometry": {"coordinates":[-81.2236251831,42.9876480103],"type":"Point"}
}