{
  "type": "Feature",
  "properties": {
    "addr:full":"1680 50E Av Lachine QC H8T 2V5",
    "addr:housenumber":"1680",
    "addr:postcode":"h8t 2v5",
    "addr:street":"50E Av",
    "iso:country":"CA",
    "sg:address":"1680 50E Av",
    "sg:city":"Lachine",
    "sg:classifiers":[
        {
            "category":"Wholesale",
            "subcategory":"Plants",
            "type":"Manufacturing & Wholesale Goods"
        }
    ],
    "sg:phone":"+1 514 733 6087",
    "sg:postcode":"H8T 2V5",
    "sg:province":"QC",
    "sg:tags":[
        "florist"
    ],
    "wof:name":"Savoir Fleur",
    "wof:placetype":"venue"
},
  "geometry": {"coordinates":[-73.71584320069999,45.4547080994],"type":"Point"}
}