{
  "type": "Feature",
  "properties": {
    "addr:full":"1014 2nd Ave E Owen Sound ON N4K 2H7",
    "addr:housenumber":"1014",
    "addr:postcode":"n4k 2h7",
    "addr:street":"2Nd Ave E",
    "iso:country":"CA",
    "sg:address":"1014 2nd Ave E",
    "sg:city":"Owen Sound",
    "sg:classifiers":[
        {
            "category":"Shopping",
            "subcategory":"Clothing, Apparel, & Fashions",
            "type":"Retail Goods"
        }
    ],
    "sg:phone":"+1 519 376 3017",
    "sg:postcode":"N4K 2H7",
    "sg:province":"ON",
    "sg:tags":[
        "furnishing"
    ],
    "wof:name":"Kornblum's Department Store",
    "wof:placetype":"venue"
},
  "geometry": {"coordinates":[-80.9431762695,44.568321228],"type":"Point"}
}