{
  "type": "Feature",
  "properties": {
    "iso:country":"CA",
    "sg:address":"132 Norfolk St S",
    "sg:city":"Simcoe",
    "sg:classifiers":[
        {
            "category":"Health Services",
            "subcategory":"Doctor",
            "type":"Services"
        }
    ],
    "sg:phone":"+1 519 426 2273",
    "sg:postcode":"N3Y 2W2",
    "sg:province":"ON",
    "sg:tags":[
        "dentist"
    ],
    "wof:name":"W Janushewski & Assoc",
    "wof:placetype":"venue"
},
  "geometry": {"coordinates":[-80.30317687989999,42.8343391418],"type":"Point"}
}