{
  "type": "Feature",
  "properties": {
    "iso:country":"CA",
    "sg:city":"London",
    "sg:classifiers":[
        {
            "category":"Wholesale",
            "subcategory":"Machinery & Supplies",
            "type":"Manufacturing & Wholesale Goods"
        }
    ],
    "sg:phone":"+1 519 652 3353",
    "sg:postcode":"N6L 1C2",
    "sg:province":"ON",
    "sg:tags":[
        "equipment",
        "welding"
    ],
    "wof:name":"Contact Welding Supplies Ltd",
    "wof:placetype":"venue"
},
  "geometry": {"coordinates":[-81.249924,42.919125],"type":"Point"}
}