{
  "type": "Feature",
  "properties": {
    "addr:full":"884 Division St Cobourg ON K9A 5V2",
    "addr:housenumber":"884",
    "addr:postcode":"k9a 5v2",
    "addr:street":"Division St",
    "iso:country":"CA",
    "sg:address":"884 Division St",
    "sg:city":"Cobourg",
    "sg:classifiers":[
        {
            "category":"Home & Garden",
            "subcategory":"Carpets & Floor Coverings",
            "type":"Retail Goods"
        }
    ],
    "sg:phone":"+1 905 372 9117",
    "sg:postcode":"K9A 5V2",
    "sg:province":"ON",
    "sg:tags":[
        "dealer",
        "rug"
    ],
    "wof:name":"Sine's Flooring",
    "wof:placetype":"venue"
},
  "geometry": {"coordinates":[-78.172417,43.975704],"type":"Point"}
}