{
  "type": "Feature",
  "properties": {
    "addr:full":"2952 4th Ave W Vancouver BC V6K 1R4",
    "addr:housenumber":"2952",
    "addr:postcode":"v6k 1r4",
    "addr:street":"4Th Ave W",
    "iso:country":"CA",
    "sg:address":"2952 4th Ave W",
    "sg:city":"Vancouver",
    "sg:classifiers":[
        {
            "category":"Shopping",
            "subcategory":"Clothing, Apparel, & Fashions",
            "type":"Retail Goods"
        }
    ],
    "sg:phone":"+1 604 732 0199",
    "sg:postcode":"V6K 1R4",
    "sg:province":"BC",
    "wof:name":"Twist Fashions Inc",
    "wof:placetype":"venue"
},
  "geometry": {"coordinates":[-123.171287537,49.2682685852],"type":"Point"}
}