{
  "type": "Feature",
  "properties": {
    "iso:country":"CA",
    "sg:address":"201 Kensington Ave",
    "sg:city":"Burnaby",
    "sg:classifiers":[
        {
            "category":"Professional",
            "subcategory":"Research",
            "type":"Services"
        }
    ],
    "sg:phone":"+1 604 294 6001",
    "sg:postcode":"V5B 4B2",
    "sg:province":"BC",
    "sg:tags":[
        "environmental",
        "ecological"
    ],
    "wof:name":"Burrard Clean Operations Ltd",
    "wof:placetype":"venue"
},
  "geometry": {"coordinates":[-122.969940185,49.2816314697],"type":"Point"}
}