{
  "type": "Feature",
  "properties": {
    "addr:full":"15 Sparling Rd St Thomas ON N5P 4A4",
    "addr:housenumber":"15",
    "addr:postcode":"n5p 4a4",
    "addr:street":"Sparling Rd",
    "iso:country":"CA",
    "sg:address":"15 Sparling Rd",
    "sg:city":"St Thomas",
    "sg:classifiers":[
        {
            "category":"Retail",
            "subcategory":"Auto Repair",
            "type":"Services"
        }
    ],
    "sg:phone":"+1 519 633 2890",
    "sg:postcode":"N5P 4A4",
    "sg:province":"ON",
    "sg:tags":[
        "body",
        "automobile",
        "painting"
    ],
    "wof:name":"Rupple Auto Paint & Collision",
    "wof:placetype":"venue"
},
  "geometry": {"coordinates":[-81.156357,42.786915],"type":"Point"}
}