{
  "type": "Feature",
  "properties": {
    "addr:full":"Hannon ON L0R 1P0",
    "addr:postcode":"l0r 1p0",
    "iso:country":"CA",
    "sg:city":"Hannon",
    "sg:classifiers":[
        {
            "category":"Building & Trades",
            "subcategory":"Construction",
            "type":"Services"
        }
    ],
    "sg:phone":"+1 905 575 9540",
    "sg:postcode":"L0R 1P0",
    "sg:province":"ON",
    "sg:tags":[
        "excavating",
        "contractor"
    ],
    "wof:name":"Glanbrook Paving & Excavating",
    "wof:placetype":"venue"
},
  "geometry": {"coordinates":[-79.837738,43.19854],"type":"Point"}
}