{
  "type": "Feature",
  "properties": {
    "addr:full":"7423 10 St NW Calgary AB T2K 1H5",
    "addr:housenumber":"7423",
    "addr:postcode":"t2k 1h5",
    "addr:street":"10 St Nw",
    "iso:country":"CA",
    "sg:address":"7423 10 St NW",
    "sg:city":"Calgary",
    "sg:classifiers":[
        {
            "category":"Education",
            "subcategory":"School",
            "type":"Public Place"
        }
    ],
    "sg:phone":"+1 403 275 5600",
    "sg:postcode":"T2K 1H5",
    "sg:province":"AB",
    "wof:name":"St Henry Elementary School",
    "wof:placetype":"venue"
},
  "geometry": {"coordinates":[-114.07939910899999,51.1174049377],"type":"Point"}
}