{
  "type": "Feature",
  "properties": {
    "addr:full":"15 Guildpark Ptway Scarborough ON M1J 3P1",
    "addr:housenumber":"15",
    "addr:postcode":"m1j 3p1",
    "addr:street":"Guildpark Ptway",
    "iso:country":"CA",
    "sg:address":"15 Guildpark Ptway",
    "sg:city":"Scarborough",
    "sg:classifiers":[
        {
            "category":"Professional",
            "subcategory":"Engineering",
            "type":"Services"
        }
    ],
    "sg:phone":"+1 416 266 3340",
    "sg:postcode":"M1J 3P1",
    "sg:province":"ON",
    "sg:tags":[
        "acoustical",
        "consultant"
    ],
    "wof:name":"Orchestral Arts",
    "wof:placetype":"venue"
},
  "geometry": {"coordinates":[-79.20751199999999,43.749615],"type":"Point"}
}