{
  "type": "Feature",
  "properties": {
    "addr:full":"Montreal QC H3G 1W1",
    "addr:postcode":"h3g 1w1",
    "iso:country":"CA",
    "sg:city":"Montreal",
    "sg:classifiers":[
        {
            "category":"Health Services",
            "subcategory":"Medical Lab",
            "type":"Services"
        }
    ],
    "sg:phone":"+1 514 285 0202",
    "sg:postcode":"H3G 1W1",
    "sg:province":"QC",
    "sg:tags":[
        "laboratory"
    ],
    "wof:name":"Laboratoire Dentaire Daye",
    "wof:placetype":"venue"
},
  "geometry": {"coordinates":[-73.5749053955,45.4988136292],"type":"Point"}
}