{
  "type": "Feature",
  "properties": {
    "iso:country":"CA",
    "sg:address":"6505 Mississauga Rd",
    "sg:city":"Mississauga",
    "sg:classifiers":[
        {
            "category":"Autos & Motor Vehicles",
            "subcategory":"Auto Supplies",
            "type":"Retail Goods"
        }
    ],
    "sg:phone":"+1 905 875 4606",
    "sg:postcode":"L5N 1A6",
    "sg:province":"ON",
    "sg:tags":[
        "automobile",
        "stereo",
        "radio"
    ],
    "wof:name":"Sivart Distribution Svc Inc",
    "wof:placetype":"venue"
},
  "geometry": {"coordinates":[-79.7374954224,43.5980606079],"type":"Point"}
}