{
  "type": "Feature",
  "properties": {
    "addr:full":"351 Victoria St N Tweed ON K0K 3J0",
    "addr:housenumber":"351",
    "addr:postcode":"k0k 3j0",
    "addr:street":"Victoria St N",
    "iso:country":"CA",
    "sg:address":"351 Victoria St N",
    "sg:city":"Tweed",
    "sg:classifiers":[
        {
            "category":"Restaurant",
            "type":"Food & Drink"
        }
    ],
    "sg:phone":"+1 613 478 2616",
    "sg:postcode":"K0K 3J0",
    "sg:province":"ON",
    "sg:tags":[
        "pizza"
    ],
    "wof:name":"Vito's Pizza",
    "wof:placetype":"venue"
},
  "geometry": {"coordinates":[-77.31452899999999,44.479183],"type":"Point"}
}