{
  "type": "Feature",
  "properties": {
    "addr:full":"49-51 Main St Channel-Port-Aux-Basques NL A0M 1C0",
    "addr:housenumber":"49-51",
    "addr:postcode":"a0m 1c0",
    "addr:street":"Main St",
    "iso:country":"CA",
    "sg:address":"49-51 Main St",
    "sg:city":"Channel-Port-Aux-Basques",
    "sg:classifiers":[
        {
            "category":"Government",
            "subcategory":"Office",
            "type":"Public Place"
        }
    ],
    "sg:phone":"+1 709 695 7367",
    "sg:postcode":"A0M 1C0",
    "sg:province":"NL",
    "wof:name":"Newfoundland Social Svc",
    "wof:placetype":"venue"
},
  "geometry": {"coordinates":[-59.1423721313,47.5735206604],"type":"Point"}
}