{
  "type": "Feature",
  "properties": {
    "addr:full":"57 Rue Denonville Dolbeau-Mistassini QC G8L 5B1",
    "addr:housenumber":"57",
    "addr:postcode":"g8l 5b1",
    "addr:street":"Rue Denonville",
    "iso:country":"CA",
    "sg:address":"57 Rue Denonville",
    "sg:city":"Dolbeau-Mistassini",
    "sg:classifiers":[
        {
            "category":"Health Services",
            "subcategory":"Nursing And Care Facility",
            "type":"Services"
        }
    ],
    "sg:phone":"+1 418 276 3630",
    "sg:postcode":"G8L 5B1",
    "sg:province":"QC",
    "sg:tags":[
        "home",
        "retirement",
        "community"
    ],
    "wof:name":"Villa Des Chutes",
    "wof:placetype":"venue"
},
  "geometry": {"coordinates":[-72.2067947388,48.8942565918],"type":"Point"}
}