{
  "type": "Feature",
  "properties": {
    "addr:full":"2450 Av Raymond Saint-Hyacinthe QC J2S 5W3",
    "addr:housenumber":"2450",
    "addr:postcode":"j2s 5w3",
    "addr:street":"Av Raymond",
    "iso:country":"CA",
    "sg:address":"2450 Av Raymond",
    "sg:city":"Saint-Hyacinthe",
    "sg:classifiers":[
        {
            "category":"Arena",
            "subcategory":"Sports Club",
            "type":"Entertainment"
        }
    ],
    "sg:phone":"+1 450 250 3668",
    "sg:postcode":"J2S 5W3",
    "sg:province":"QC",
    "sg:tags":[
        "sporting",
        "soccer",
        "good"
    ],
    "wof:name":"Soccer Action",
    "wof:placetype":"venue"
},
  "geometry": {"coordinates":[-72.9593505859,45.6291503906],"type":"Point"}
}