{
  "type": "Feature",
  "properties": {
    "iso:country":"CA",
    "sg:address":"55 King St N",
    "sg:city":"Waterloo",
    "sg:classifiers":[
        {
            "category":"Taxi",
            "type":"Transportation"
        }
    ],
    "sg:phone":"+1 519 886 1200",
    "sg:postcode":"N2J 2W9",
    "sg:province":"ON",
    "sg:tags":[
        "taxicab"
    ],
    "wof:name":"Waterloo Taxi Ltd",
    "wof:placetype":"venue"
},
  "geometry": {"coordinates":[-80.5229110718,43.4666938782],"type":"Point"}
}