{
  "type": "Feature",
  "properties": {
    "iso:country":"CA",
    "sg:address":"791 Rue Charles-Aubert",
    "sg:city":"Lachenaie",
    "sg:classifiers":[
        {
            "category":"Freight",
            "type":"Transportation"
        }
    ],
    "sg:phone":"+1 450 961 1074",
    "sg:postcode":"J6W 5Y7",
    "sg:province":"QC",
    "sg:tags":[
        "trucking"
    ],
    "wof:name":"Transport Bgh Inc",
    "wof:placetype":"venue"
},
  "geometry": {"coordinates":[-73.5872344971,45.7108802795],"type":"Point"}
}