{
  "type": "Feature",
  "properties": {
    "iso:country":"CA",
    "sg:address":"647 2nd Ave E",
    "sg:city":"Owen Sound",
    "sg:classifiers":[
        {
            "category":"Professional",
            "subcategory":"Engineering",
            "type":"Services"
        }
    ],
    "sg:phone":"+1 519 376 6941",
    "sg:postcode":"N4K 2G7",
    "sg:province":"ON",
    "sg:tags":[
        "engineer"
    ],
    "wof:name":"V J Nash & Assoc Ltd",
    "wof:placetype":"venue"
},
  "geometry": {"coordinates":[-80.94156646730001,44.5610694885],"type":"Point"}
}