{
  "type": "Feature",
  "properties": {
    "addr:full":"550 Fennell Ave E Hamilton ON L8V 4S9",
    "addr:housenumber":"550",
    "addr:postcode":"l8v 4s9",
    "addr:street":"Fennell Ave E",
    "iso:country":"CA",
    "sg:address":"550 Fennell Ave E",
    "sg:city":"Hamilton",
    "sg:classifiers":[
        {
            "category":"Restaurant",
            "type":"Food & Drink"
        }
    ],
    "sg:phone":"+1 905 383 3855",
    "sg:postcode":"L8V 4S9",
    "sg:province":"ON",
    "wof:name":"Harvey's",
    "wof:placetype":"venue"
},
  "geometry": {"coordinates":[-79.85661315919999,43.2321548462],"type":"Point"}
}