{
  "type": "Feature",
  "properties": {
    "addr:full":"1290 Rue Prefontaine Longueuil QC J4K 3W8",
    "addr:housenumber":"1290",
    "addr:postcode":"j4k 3w8",
    "addr:street":"Rue Prefontaine",
    "iso:country":"CA",
    "sg:address":"1290 Rue Prefontaine",
    "sg:city":"Longueuil",
    "sg:classifiers":[
        {
            "category":"Building & Trades",
            "subcategory":"Construction",
            "type":"Services"
        }
    ],
    "sg:phone":"+1 450 646 3667",
    "sg:postcode":"J4K 3W8",
    "sg:province":"QC",
    "sg:tags":[
        "roofing",
        "consultant"
    ],
    "wof:name":"Toiture Jd Boisvert Inc",
    "wof:placetype":"venue"
},
  "geometry": {"coordinates":[-73.498695,45.518414],"type":"Point"}
}