{
  "type": "Feature",
  "properties": {
    "addr:full":"79 Huntingwood Dr Belleville ON K8N 4Z5",
    "addr:housenumber":"79",
    "addr:postcode":"k8n 4z5",
    "addr:street":"Huntingwood Dr",
    "iso:country":"CA",
    "sg:address":"79 Huntingwood Dr",
    "sg:city":"Belleville",
    "sg:classifiers":[
        {
            "category":"Personal",
            "subcategory":"Beauty Salon",
            "type":"Services"
        }
    ],
    "sg:phone":"+1 613 969 7771",
    "sg:postcode":"K8N 4Z5",
    "sg:province":"ON",
    "wof:name":"Golden Shear",
    "wof:placetype":"venue"
},
  "geometry": {"coordinates":[-77.381897,44.161045],"type":"Point"}
}