{
  "type": "Feature",
  "properties": {
    "iso:country":"CA",
    "sg:address":"35 Oakes Blvd",
    "sg:city":"Vittoria",
    "sg:classifiers":[
        {
            "category":"Recreation",
            "type":"Entertainment"
        }
    ],
    "sg:phone":"+1 519 426 0465",
    "sg:postcode":"N0E 1W0",
    "sg:province":"ON",
    "sg:tags":[
        "hall",
        "auditorium"
    ],
    "wof:name":"Vittoria & District Community",
    "wof:placetype":"venue"
},
  "geometry": {"coordinates":[-80.3234405518,42.7627067566],"type":"Point"}
}