{
  "type": "Feature",
  "properties": {
    "addr:full":"28 First Ave Sioux Lookout ON P8T 1E8",
    "addr:housenumber":"28",
    "addr:postcode":"p8t 1e8",
    "addr:street":"First Ave",
    "iso:country":"CA",
    "sg:address":"28 First Ave",
    "sg:city":"Sioux Lookout",
    "sg:classifiers":[
        {
            "category":"Organizations",
            "subcategory":"Religious Organization",
            "type":"Services"
        }
    ],
    "sg:phone":"+1 807 737 2843",
    "sg:postcode":"P8T 1E8",
    "sg:province":"ON",
    "sg:tags":[
        "church"
    ],
    "wof:name":"New Life Assembley",
    "wof:placetype":"venue"
},
  "geometry": {"coordinates":[-91.908478,50.101097],"type":"Point"}
}