{
  "type": "Feature",
  "properties": {
    "addr:full":"51 Lyndhurst Cres Whitby ON L1R 1C9",
    "addr:housenumber":"51",
    "addr:postcode":"l1r 1c9",
    "addr:street":"Lyndhurst Cres",
    "iso:country":"CA",
    "sg:address":"51 Lyndhurst Cres",
    "sg:city":"Whitby",
    "sg:classifiers":[
        {
            "category":"Building & Trades",
            "subcategory":"Plumbing",
            "type":"Services"
        }
    ],
    "sg:phone":"+1 905 477 5391",
    "sg:postcode":"L1R 1C9",
    "sg:province":"ON",
    "sg:tags":[
        "tank",
        "septic",
        "contractor"
    ],
    "wof:name":"Roboject Inc",
    "wof:placetype":"venue"
},
  "geometry": {"coordinates":[-78.95951100000001,43.897263],"type":"Point"}
}