{
  "type": "Feature",
  "properties": {
    "addr:full":"12700 Keele St King City ON L7B 1H5",
    "addr:housenumber":"12700",
    "addr:postcode":"l7b 1h5",
    "addr:street":"Keele St",
    "iso:country":"CA",
    "sg:address":"12700 Keele St",
    "sg:city":"King City",
    "sg:classifiers":[
        {
            "category":"Bus Charters",
            "type":"Transportation"
        }
    ],
    "sg:phone":"+1 905 833 5351",
    "sg:postcode":"L7B 1H5",
    "sg:province":"ON",
    "sg:tags":[
        "rental"
    ],
    "wof:name":"Langdon's Coach Lines CO Ltd",
    "wof:placetype":"venue"
},
  "geometry": {"coordinates":[-79.5263137817,43.921081543],"type":"Point"}
}