{
  "type": "Feature",
  "properties": {
    "addr:full":"Swastika ON P0K 1T0",
    "addr:postcode":"p0k 1t0",
    "iso:country":"CA",
    "sg:city":"Swastika",
    "sg:classifiers":[
        {
            "category":"Wholesale",
            "subcategory":"Scrap",
            "type":"Manufacturing & Wholesale Goods"
        }
    ],
    "sg:phone":"+1 705 642 9314",
    "sg:postcode":"P0K 1T0",
    "sg:province":"ON",
    "sg:tags":[
        "recycling",
        "center",
        "garden"
    ],
    "wof:name":"Floral Scapes",
    "wof:placetype":"venue"
},
  "geometry": {"coordinates":[-80.103821,48.109501],"type":"Point"}
}