{
  "type": "Feature",
  "properties": {
    "addr:full":"PO Box 112 Oak River MB R0K 1T0",
    "addr:housenumber":"po",
    "addr:postcode":"r0k 1t0",
    "addr:street":"Box 112 Oak",
    "iso:country":"CA",
    "sg:address":"PO Box 112",
    "sg:city":"Oak River",
    "sg:classifiers":[
        {
            "category":"Organizations",
            "subcategory":"Religious Organization",
            "type":"Services"
        }
    ],
    "sg:phone":"+1 204 566 2432",
    "sg:postcode":"R0K 1T0",
    "sg:province":"MB",
    "sg:tags":[
        "church"
    ],
    "wof:name":"Oak River United Church",
    "wof:placetype":"venue"
},
  "geometry": {"coordinates":[-100.429276,50.137806],"type":"Point"}
}