{
  "type": "Feature",
  "properties": {
    "iso:country":"CA",
    "sg:address":"10815 Boul Saint-Michel",
    "sg:city":"Montreal-Nord",
    "sg:classifiers":[
        {
            "category":"Real Estate",
            "subcategory":"Real Estate Agent",
            "type":"Services"
        }
    ],
    "sg:phone":"+1 514 328 1219",
    "sg:postcode":"H1H 5H7",
    "sg:province":"QC",
    "sg:tags":[
        "cooperative"
    ],
    "wof:name":"Cooperative D'Habitation Rouet",
    "wof:placetype":"venue"
},
  "geometry": {"coordinates":[-73.649193,45.58345],"type":"Point"}
}