{
  "type": "Feature",
  "properties": {
    "addr:full":"Saskatoon SK S7M 0K7",
    "addr:postcode":"s7m 0k7",
    "iso:country":"CA",
    "sg:city":"Saskatoon",
    "sg:classifiers":[
        {
            "category":"Building & Trades",
            "subcategory":"Plumbing",
            "type":"Services"
        }
    ],
    "sg:phone":"+1 306 653 1899",
    "sg:postcode":"S7M 0K7",
    "sg:province":"SK",
    "sg:tags":[
        "heating",
        "contractor"
    ],
    "wof:name":"Nickel Plumbing & Heating Ltd",
    "wof:placetype":"venue"
},
  "geometry": {"coordinates":[-106.673531,52.105068],"type":"Point"}
}