{
  "type": "Feature",
  "properties": {
    "addr:full":"1917 Av D'Assise Quebec QC G1L 3V5",
    "addr:housenumber":"1917",
    "addr:postcode":"g1l 3v5",
    "addr:street":"Av D'Assise",
    "iso:country":"CA",
    "sg:address":"1917 Av D'Assise",
    "sg:city":"Quebec",
    "sg:classifiers":[
        {
            "category":"Building & Trades",
            "subcategory":"Construction",
            "type":"Services"
        }
    ],
    "sg:phone":"+1 418 522 7178",
    "sg:postcode":"G1L 3V5",
    "sg:province":"QC",
    "sg:tags":[
        "excavating",
        "contractor"
    ],
    "wof:name":"Deneigement Excavation Lr Inc",
    "wof:placetype":"venue"
},
  "geometry": {"coordinates":[-71.238342,46.827271],"type":"Point"}
}