{
  "type": "Feature",
  "properties": {
    "addr:full":"63 Garden St Gananoque ON K7G 1H8",
    "addr:housenumber":"63",
    "addr:postcode":"k7g 1h8",
    "addr:street":"Garden St",
    "iso:country":"CA",
    "sg:address":"63 Garden St",
    "sg:city":"Gananoque",
    "sg:classifiers":[
        {
            "category":"Retail",
            "subcategory":"Funeral Services",
            "type":"Services"
        }
    ],
    "sg:phone":"+1 613 382 3088",
    "sg:postcode":"K7G 1H8",
    "sg:province":"ON",
    "sg:tags":[
        "director"
    ],
    "wof:name":"Tompkins Funeral Home",
    "wof:placetype":"venue"
},
  "geometry": {"coordinates":[-76.164078,44.329639],"type":"Point"}
}