{
  "type": "Feature",
  "properties": {
    "iso:country":"CA",
    "sg:address":"873 Hamilton Rd",
    "sg:city":"London",
    "sg:classifiers":[
        {
            "category":"Shopping",
            "subcategory":"Pharmacy",
            "type":"Retail Goods"
        }
    ],
    "sg:phone":"+1 519 451 3590",
    "sg:postcode":"N5Z 1V8",
    "sg:province":"ON",
    "wof:name":"Ealing Pharmacy Ltd",
    "wof:placetype":"venue"
},
  "geometry": {"coordinates":[-81.199104,42.978249],"type":"Point"}
}