{
  "type": "Feature",
  "properties": {
    "addr:full":"2375 37th Ave W Vancouver BC V6M 1P4",
    "addr:housenumber":"2375",
    "addr:postcode":"v6m 1p4",
    "addr:street":"37Th Ave W",
    "iso:country":"CA",
    "sg:address":"2375 37th Ave W",
    "sg:city":"Vancouver",
    "sg:classifiers":[
        {
            "category":"Professional",
            "subcategory":"Lawyer & Legal Services",
            "type":"Services"
        }
    ],
    "sg:phone":"+1 604 684 6301",
    "sg:postcode":"V6M 1P4",
    "sg:province":"BC",
    "sg:tags":[
        "attorney"
    ],
    "wof:name":"Hartley E Cramer Personal Law",
    "wof:placetype":"venue"
},
  "geometry": {"coordinates":[-123.160736,49.238579],"type":"Point"}
}