{
  "type": "Feature",
  "properties": {
    "addr:full":"103 Richmond St E Toronto ON M5C 1N9",
    "addr:housenumber":"103",
    "addr:postcode":"m5c 1n9",
    "addr:street":"Richmond St E",
    "iso:country":"CA",
    "sg:address":"103 Richmond St E",
    "sg:city":"Toronto",
    "sg:classifiers":[
        {
            "category":"Professional",
            "subcategory":"Credit Reporting & Collection",
            "type":"Services"
        }
    ],
    "sg:phone":"+1 416 955 4650",
    "sg:postcode":"M5C 1N9",
    "sg:province":"ON",
    "sg:tags":[
        "agency"
    ],
    "wof:name":"Security Recovery Group Inc",
    "wof:placetype":"venue"
},
  "geometry": {"coordinates":[-79.3742141724,43.6525993347],"type":"Point"}
}