{
  "type": "Feature",
  "properties": {
    "addr:full":"Mount Hope ON L0R 1W0",
    "addr:postcode":"l0r 1w0",
    "iso:country":"CA",
    "sg:city":"Mount Hope",
    "sg:classifiers":[
        {
            "category":"Organizations",
            "subcategory":"Professional Association",
            "type":"Services"
        }
    ],
    "sg:phone":"+1 905 679 3853",
    "sg:postcode":"L0R 1W0",
    "sg:province":"ON",
    "sg:tags":[
        "environmental",
        "ecological"
    ],
    "wof:name":"Glycol Management Inc",
    "wof:placetype":"venue"
},
  "geometry": {"coordinates":[-79.92841300000001,43.159676],"type":"Point"}
}