{
  "type": "Feature",
  "properties": {
    "addr:full":"2622 13 Ave N Lethbridge AB T1H 4A3",
    "addr:housenumber":"2622",
    "addr:postcode":"t1h 4a3",
    "addr:street":"13 Ave N",
    "iso:country":"CA",
    "sg:address":"2622 13 Ave N",
    "sg:city":"Lethbridge",
    "sg:classifiers":[
        {
            "category":"Building & Trades",
            "subcategory":"Construction",
            "type":"Services"
        }
    ],
    "sg:phone":"+1 403 320 6015",
    "sg:postcode":"T1H 4A3",
    "sg:province":"AB",
    "sg:tags":[
        "excavating",
        "contractor"
    ],
    "wof:name":"Cox Excavating Ltd",
    "wof:placetype":"venue"
},
  "geometry": {"coordinates":[-112.80481,49.717403],"type":"Point"}
}