{
  "type": "Feature",
  "properties": {
    "addr:full":"2164 Boul Lapiniere Brossard QC J4W 1M2",
    "addr:housenumber":"2164",
    "addr:postcode":"j4w 1m2",
    "addr:street":"Boul Lapiniere",
    "iso:country":"CA",
    "sg:address":"2164 Boul Lapiniere",
    "sg:city":"Brossard",
    "sg:classifiers":[
        {
            "category":"Real Estate",
            "subcategory":"Real Estate Agent",
            "type":"Services"
        }
    ],
    "sg:phone":"+1 450 678 2000",
    "sg:postcode":"J4W 1M2",
    "sg:province":"QC",
    "wof:name":"Trans-Action Pro 2000",
    "wof:placetype":"venue"
},
  "geometry": {"coordinates":[-73.470924,45.474339],"type":"Point"}
}