{
  "type": "Feature",
  "properties": {
    "addr:full":"10637 Boundary Line Kent Bridge ON N0P 1V0",
    "addr:housenumber":"10637",
    "addr:postcode":"n0p 1v0",
    "addr:street":"Boundary Line",
    "iso:country":"CA",
    "sg:address":"10637 Boundary Line",
    "sg:city":"Kent Bridge",
    "sg:classifiers":[
        {
            "category":"Retail",
            "subcategory":"Animal Services",
            "type":"Services"
        }
    ],
    "sg:phone":"+1 519 351 1428",
    "sg:postcode":"N0P 1V0",
    "sg:province":"ON",
    "sg:tags":[
        "pet",
        "boarding",
        "grooming",
        "washing",
        "sitting"
    ],
    "wof:name":"Bodres Kennels",
    "wof:placetype":"venue"
},
  "geometry": {"coordinates":[-82.07303619379999,42.5150604248],"type":"Point"}
}