{
  "type": "Feature",
  "properties": {
    "iso:country":"CA",
    "sg:address":"3427 Wiltshire Blvd",
    "sg:city":"Niagara Falls",
    "sg:classifiers":[
        {
            "category":"Local Transit",
            "type":"Transportation"
        }
    ],
    "sg:phone":"+1 905 356 3737",
    "sg:postcode":"L2J 3M1",
    "sg:province":"ON",
    "sg:tags":[
        "limousine"
    ],
    "wof:name":"Century Enterprise",
    "wof:placetype":"venue"
},
  "geometry": {"coordinates":[-79.1206207275,43.1236534119],"type":"Point"}
}