{
  "type": "Feature",
  "properties": {
    "addr:full":"3414 Rue Joseph Verdun QC H4G 1H9",
    "addr:housenumber":"3414",
    "addr:postcode":"h4g 1h9",
    "addr:street":"Rue Joseph Verdun",
    "iso:country":"CA",
    "sg:address":"3414 Rue Joseph",
    "sg:city":"Verdun",
    "sg:classifiers":[
        {
            "category":"Real Estate",
            "subcategory":"Real Estate Agent",
            "type":"Services"
        }
    ],
    "sg:phone":"+1 514 765 3040",
    "sg:postcode":"H4G 1H9",
    "sg:province":"QC",
    "sg:tags":[
        "management"
    ],
    "wof:name":"Gestion Immobiliere Bel-Air",
    "wof:placetype":"venue"
},
  "geometry": {"coordinates":[-73.57165500000001,45.4697],"type":"Point"}
}