{
  "type": "Feature",
  "properties": {
    "iso:country":"CA",
    "sg:address":"3414 Rue Joseph",
    "sg:city":"Verdun",
    "sg:classifiers":[
        {
            "category":"Real Estate",
            "subcategory":"Real Estate Agent",
            "type":"Services"
        }
    ],
    "sg:phone":"+1 514 765 3040",
    "sg:postcode":"H4G 1H9",
    "sg:province":"QC",
    "sg:tags":[
        "management"
    ],
    "wof:name":"Gestion Immobiliere Bel-Air",
    "wof:placetype":"venue"
},
  "geometry": {"coordinates":[-73.571655,45.4697],"type":"Point"}
}