{
  "type": "Feature",
  "properties": {
    "iso:country":"CA",
    "sg:address":"72 Northern Ave E",
    "sg:city":"Sault Ste Marie",
    "sg:classifiers":[
        {
            "category":"Social Services",
            "subcategory":"Child Care",
            "type":"Services"
        }
    ],
    "sg:phone":"+1 705 945 9244",
    "sg:postcode":"P6B 4H4",
    "sg:province":"ON",
    "wof:name":"Northridge Montessori School",
    "wof:placetype":"venue"
},
  "geometry": {"coordinates":[-84.3332519531,46.5341720581],"type":"Point"}
}