{
  "type": "Feature",
  "properties": {
    "addr:full":"Vanscoy SK S0L 3J0",
    "addr:postcode":"s0l 3j0",
    "iso:country":"CA",
    "sg:city":"Vanscoy",
    "sg:classifiers":[
        {
            "category":"Real Estate",
            "subcategory":"Real Estate Operator",
            "type":"Services"
        }
    ],
    "sg:phone":"+1 306 668 2155",
    "sg:postcode":"S0L 3J0",
    "sg:province":"SK",
    "sg:tags":[
        "mobile",
        "home",
        "community"
    ],
    "wof:name":"Vanscoy Trailer Court",
    "wof:placetype":"venue"
},
  "geometry": {"coordinates":[-106.971169,52.001968],"type":"Point"}
}