{
  "type": "Feature",
  "properties": {
    "addr:full":"750 Boul Charest O Quebec QC G1N 2C5",
    "addr:housenumber":"750",
    "addr:postcode":"g1n 2c5",
    "addr:street":"Boul Charest O",
    "iso:country":"CA",
    "sg:address":"750 Boul Charest O",
    "sg:city":"Quebec",
    "sg:classifiers":[
        {
            "category":"Food & Beverages",
            "subcategory":"Groceries & Convenience Stores",
            "type":"Retail Goods"
        }
    ],
    "sg:phone":"+1 418 681 9262",
    "sg:postcode":"G1N 2C5",
    "sg:province":"QC",
    "wof:name":"Couche-Tard",
    "wof:placetype":"venue"
},
  "geometry": {"coordinates":[-71.21959699999999,46.81522],"type":"Point"}
}