{
  "type": "Feature",
  "properties": {
    "addr:full":"3815 T C Hwy Cobble Hill BC V0R 1L0",
    "addr:housenumber":"3815",
    "addr:postcode":"bc v0r 1l0",
    "addr:street":"T C Hwy",
    "iso:country":"CA",
    "sg:address":"3815 T C Hwy",
    "sg:city":"Cobble Hill",
    "sg:classifiers":[
        {
            "category":"Government",
            "subcategory":"Office",
            "type":"Public Place"
        }
    ],
    "sg:phone":"+1 250 743 3554",
    "sg:postcode":"V0R 1L0",
    "sg:province":"BC",
    "wof:name":"BC Seed Orchard",
    "wof:placetype":"venue"
},
  "geometry": {"coordinates":[-123.603928,48.686958],"type":"Point"}
}