{
  "type": "Feature",
  "properties": {
    "addr:full":"Peterborough ON K9J 7S8",
    "addr:postcode":"k9j 7s8",
    "iso:country":"CA",
    "sg:city":"Peterborough",
    "sg:classifiers":[
        {
            "category":"Retail",
            "subcategory":"Repair Shop",
            "type":"Services"
        }
    ],
    "sg:phone":"+1 705 745 3931",
    "sg:postcode":"K9J 7S8",
    "sg:province":"ON",
    "sg:tags":[
        "upholsterer"
    ],
    "wof:name":"Mc Call's Upholstering",
    "wof:placetype":"venue"
},
  "geometry": {"coordinates":[-78.3342132568,44.2782897949],"type":"Point"}
}