{
  "type": "Feature",
  "properties": {
    "addr:full":"1910 Yonge St Toronto ON M4S 3B2",
    "addr:housenumber":"1910",
    "addr:postcode":"m4s 3b2",
    "addr:street":"Yonge St",
    "iso:country":"CA",
    "sg:address":"1910 Yonge St",
    "sg:city":"Toronto",
    "sg:classifiers":[
        {
            "category":"Education",
            "subcategory":"Dance Studio",
            "type":"Public Place"
        }
    ],
    "sg:phone":"+1 416 485 9305",
    "sg:postcode":"M4S 3B2",
    "sg:province":"ON",
    "sg:tags":[
        "instruction",
        "dancing"
    ],
    "wof:name":"A Dance Studio By Pollock",
    "wof:placetype":"venue"
},
  "geometry": {"coordinates":[-79.39679,43.698421],"type":"Point"}
}