{
  "type": "Feature",
  "properties": {
    "addr:full":"17331 107 Ave NW Edmonton AB T5S 1E5",
    "addr:housenumber":"17331",
    "addr:postcode":"t5s 1e5",
    "addr:street":"107 Ave Nw",
    "iso:country":"CA",
    "sg:address":"17331 107 Ave NW",
    "sg:city":"Edmonton",
    "sg:classifiers":[
        {
            "category":"Professional",
            "subcategory":"Research",
            "type":"Services"
        }
    ],
    "sg:phone":"+1 780 484 3377",
    "sg:postcode":"T5S 1E5",
    "sg:province":"AB",
    "sg:tags":[
        "environmental",
        "ecological"
    ],
    "wof:name":"Nichols Environmental Canada",
    "wof:placetype":"venue"
},
  "geometry": {"coordinates":[-113.620223999,53.5531311035],"type":"Point"}
}