{
  "type": "Feature",
  "properties": {
    "addr:full":"Nanaimo BC V9R 5C5",
    "addr:postcode":"v9r 5c5",
    "iso:country":"CA",
    "sg:city":"Nanaimo",
    "sg:classifiers":[
        {
            "category":"Autos & Motor Vehicles",
            "subcategory":"Auto Supplies",
            "type":"Retail Goods"
        }
    ],
    "sg:phone":"+1 250 753 1711",
    "sg:postcode":"V9R 5C5",
    "sg:province":"BC",
    "sg:tags":[
        "automobile",
        "parts"
    ],
    "wof:name":"Lordco Parts Ltd",
    "wof:placetype":"venue"
},
  "geometry": {"coordinates":[-123.940071106,49.1682624817],"type":"Point"}
}