{
  "type": "Feature",
  "properties": {
    "addr:full":"8810 118 Ave NW Edmonton AB T5B 0T4",
    "addr:housenumber":"8810",
    "addr:postcode":"t5b 0t4",
    "addr:street":"118 Ave Nw",
    "iso:country":"CA",
    "sg:address":"8810 118 Ave NW",
    "sg:city":"Edmonton",
    "sg:classifiers":[
        {
            "category":"Professional",
            "subcategory":"Accounting & Tax Preparation",
            "type":"Services"
        }
    ],
    "sg:phone":"+1 780 471 3882",
    "sg:postcode":"T5B 0T4",
    "sg:province":"AB",
    "sg:tags":[
        "accountant"
    ],
    "wof:name":"Accounting & Computer Svc",
    "wof:placetype":"venue"
},
  "geometry": {"coordinates":[-113.476624,53.570461],"type":"Point"}
}