{
  "type": "Feature",
  "properties": {
    "addr:full":"268 Grosvenor St London ON N6A 4L6",
    "addr:housenumber":"268",
    "addr:postcode":"n6a 4l6",
    "addr:street":"Grosvenor St",
    "iso:country":"CA",
    "sg:address":"268 Grosvenor St",
    "sg:city":"London",
    "sg:classifiers":[
        {
            "category":"Health Services",
            "subcategory":"Doctor",
            "type":"Services"
        }
    ],
    "sg:phone":"+1 519 646 6048",
    "sg:postcode":"N6A 4L6",
    "sg:province":"ON",
    "sg:tags":[
        "physician",
        "surgeon"
    ],
    "wof:name":"Hand & Upper Limb Ctr",
    "wof:placetype":"venue"
},
  "geometry": {"coordinates":[-81.25348700000001,43.000294],"type":"Point"}
}