{
  "type": "Feature",
  "properties": {
    "addr:full":"200 Cochrane Dr Markham ON L3R 8E8",
    "addr:housenumber":"200",
    "addr:postcode":"l3r 8e8",
    "addr:street":"Cochrane Dr",
    "iso:country":"CA",
    "sg:address":"200 Cochrane Dr",
    "sg:city":"Markham",
    "sg:classifiers":[
        {
            "category":"Wholesale",
            "subcategory":"Durable Goods & Equipment",
            "type":"Manufacturing & Wholesale Goods"
        }
    ],
    "sg:phone":"+1 905 475 0115",
    "sg:postcode":"L3R 8E8",
    "sg:province":"ON",
    "sg:tags":[
        "representative",
        "manufacturer"
    ],
    "wof:name":"Multi Mark Agents Ltd",
    "wof:placetype":"venue"
},
  "geometry": {"coordinates":[-79.359566,43.845749],"type":"Point"}
}