{
  "type": "Feature",
  "properties": {
    "addr:full":"366 Denison St Markham ON L3R 1B9",
    "addr:housenumber":"366",
    "addr:postcode":"l3r 1b9",
    "addr:street":"Denison St",
    "iso:country":"CA",
    "sg:address":"366 Denison St",
    "sg:city":"Markham",
    "sg:classifiers":[
        {
            "category":"Wholesale",
            "subcategory":"Furniture",
            "type":"Manufacturing & Wholesale Goods"
        }
    ],
    "sg:phone":"+1 905 305 9955",
    "sg:postcode":"L3R 1B9",
    "sg:province":"ON",
    "wof:name":"Office Shop",
    "wof:placetype":"venue"
},
  "geometry": {"coordinates":[-79.348,43.822723],"type":"Point"}
}