{
  "type": "Feature",
  "properties": {
    "iso:country":"CA",
    "sg:address":"14530 123 Ave NW",
    "sg:city":"Edmonton",
    "sg:classifiers":[
        {
            "category":"Professional",
            "subcategory":"Detective & Security Services",
            "type":"Services"
        }
    ],
    "sg:phone":"+1 780 453 5280",
    "sg:postcode":"T5L 2Y3",
    "sg:province":"AB",
    "sg:tags":[
        "control",
        "signal",
        "traffic",
        "sign"
    ],
    "wof:name":"Trafco",
    "wof:placetype":"venue"
},
  "geometry": {"coordinates":[-113.572235107,53.5769767761],"type":"Point"}
}