{
  "type": "Feature",
  "properties": {
    "addr:full":"Farm Canwood SK S0J 0K0",
    "addr:postcode":"s0j 0k0",
    "iso:country":"CA",
    "sg:address":"Farm",
    "sg:city":"Canwood",
    "sg:classifiers":[
        {
            "category":"Recreation",
            "type":"Entertainment"
        }
    ],
    "sg:phone":"+1 306 468 2663",
    "sg:postcode":"S0J 0K0",
    "sg:province":"SK",
    "sg:tags":[
        "provincial",
        "parks"
    ],
    "wof:name":"Canwood Regional Park",
    "wof:placetype":"venue"
},
  "geometry": {"coordinates":[-106.60481299999999,53.359676],"type":"Point"}
}