{
  "type": "Feature",
  "properties": {
    "addr:full":"899 Queen St E # 3 Toronto ON M4M 1J4",
    "addr:housenumber":"899",
    "addr:postcode":"m4m 1j4",
    "addr:street":"Queen St E # 3",
    "iso:country":"CA",
    "sg:address":"899 Queen St E # 3",
    "sg:city":"Toronto",
    "sg:classifiers":[
        {
            "category":"Retail",
            "subcategory":"Auto Repair",
            "type":"Services"
        }
    ],
    "sg:phone":"+1 416 406 4356",
    "sg:postcode":"M4M 1J4",
    "sg:province":"ON",
    "sg:tags":[
        "repairing",
        "automobile"
    ],
    "wof:name":"Kabul Auto",
    "wof:placetype":"venue"
},
  "geometry": {"coordinates":[-79.341927,43.660503],"type":"Point"}
}