{
  "type": "Feature",
  "properties": {
    "addr:full":"54 Main St Stephenville Crossing NL A0N 2C0",
    "addr:housenumber":"54",
    "addr:postcode":"a0n 2c0",
    "addr:street":"Main St",
    "iso:country":"CA",
    "sg:address":"54 Main St",
    "sg:city":"Stephenville Crossing",
    "sg:classifiers":[
        {
            "category":"Health Services",
            "subcategory":"Doctor",
            "type":"Services"
        }
    ],
    "sg:phone":"+1 709 646 5810",
    "sg:postcode":"A0N 2C0",
    "sg:province":"NL",
    "sg:tags":[
        "dentist"
    ],
    "wof:name":"Crossing Dental Clinic",
    "wof:placetype":"venue"
},
  "geometry": {"coordinates":[-58.4369506836,48.5048408508],"type":"Point"}
}