{
  "type": "Feature",
  "properties": {
    "addr:full":"Etobicoke ON M9A 3T7",
    "addr:postcode":"m9a 3t7",
    "iso:country":"CA",
    "sg:city":"Etobicoke",
    "sg:classifiers":[
        {
            "category":"Restaurant",
            "type":"Food & Drink"
        }
    ],
    "sg:phone":"+1 416 231 4011",
    "sg:postcode":"M9A 3T7",
    "sg:province":"ON",
    "sg:tags":[
        "gourmet",
        "shop",
        "caterer"
    ],
    "wof:name":"Absolutely Fine Foods",
    "wof:placetype":"venue"
},
  "geometry": {"coordinates":[-79.5201034546,43.6628723145],"type":"Point"}
}