{
  "type": "Feature",
  "properties": {
    "addr:full":"38 Bateman Cres Saskatoon SK S7H 3C4",
    "addr:housenumber":"38",
    "addr:postcode":"s7h 3c4",
    "addr:street":"Bateman Cres",
    "iso:country":"CA",
    "sg:address":"38 Bateman Cres",
    "sg:city":"Saskatoon",
    "sg:classifiers":[
        {
            "category":"Organizations",
            "subcategory":"Religious Organization",
            "type":"Services"
        }
    ],
    "sg:phone":"+1 306 477 2363",
    "sg:postcode":"S7H 3C4",
    "sg:province":"SK",
    "sg:tags":[
        "church"
    ],
    "wof:name":"Saskatoon Temple Community",
    "wof:placetype":"venue"
},
  "geometry": {"coordinates":[-106.614761,52.117527],"type":"Point"}
}