{
  "type": "Feature",
  "properties": {
    "iso:country":"CA",
    "sg:address":"6360 Rue Pascal",
    "sg:city":"Montreal-Nord",
    "sg:classifiers":[
        {
            "category":"Food & Beverages",
            "subcategory":"Fruits & Vegetables",
            "type":"Retail Goods"
        }
    ],
    "sg:phone":"+1 514 322 3391",
    "sg:postcode":"H1G 1T6",
    "sg:province":"QC",
    "sg:tags":[
        "produce"
    ],
    "wof:name":"Fruiterie Pascale",
    "wof:placetype":"venue"
},
  "geometry": {"coordinates":[-73.619957,45.617779],"type":"Point"}
}