{
  "type": "Feature",
  "properties": {
    "iso:country":"CA",
    "sg:address":"317 Columbia St",
    "sg:city":"New Westminster",
    "sg:classifiers":[
        {
            "category":"Education",
            "subcategory":"Special Training",
            "type":"Public Place"
        }
    ],
    "sg:phone":"+1 604 515 9380",
    "sg:postcode":"V3L 1A7",
    "sg:province":"BC",
    "sg:tags":[
        "school",
        "language"
    ],
    "wof:name":"Columbia School of Languages",
    "wof:placetype":"venue"
},
  "geometry": {"coordinates":[-122.904266,49.205162],"type":"Point"}
}