{
  "type": "Feature",
  "properties": {
    "addr:full":"1396 Harmsworth Sq Oakville ON L6H 3E7",
    "addr:housenumber":"1396",
    "addr:postcode":"l6h 3e7",
    "addr:street":"Harmsworth Sq",
    "iso:country":"CA",
    "sg:address":"1396 Harmsworth Sq",
    "sg:city":"Oakville",
    "sg:classifiers":[
        {
            "category":"Professional",
            "subcategory":"Secretarial Services",
            "type":"Services"
        }
    ],
    "sg:phone":"+1 905 845 2102",
    "sg:postcode":"L6H 3E7",
    "sg:province":"ON",
    "sg:tags":[
        "reporting",
        "court"
    ],
    "wof:name":"Walker's Work Processing",
    "wof:placetype":"venue"
},
  "geometry": {"coordinates":[-79.68775939939999,43.4863166809],"type":"Point"}
}