{
  "type": "Feature",
  "properties": {
    "iso:country":"CA",
    "sg:address":"4522 50 Ave",
    "sg:city":"St Paul",
    "sg:classifiers":[
        {
            "category":"Restaurant",
            "type":"Food & Drink"
        }
    ],
    "sg:phone":"+1 780 645 4144",
    "sg:postcode":"T0A 3A2",
    "sg:province":"AB",
    "wof:name":"Burger Baron",
    "wof:placetype":"venue"
},
  "geometry": {"coordinates":[-111.28327179,53.9916191101],"type":"Point"}
}