{
  "type": "Feature",
  "properties": {
    "addr:full":"6 Westpark Cres Battleford SK S0M 0E0",
    "addr:housenumber":"6",
    "addr:postcode":"s0m 0e0",
    "addr:street":"Westpark Cres",
    "iso:country":"CA",
    "sg:address":"6 Westpark Cres",
    "sg:city":"Battleford",
    "sg:classifiers":[
        {
            "category":"Professional",
            "subcategory":"Engineering",
            "type":"Services"
        }
    ],
    "sg:phone":"+1 306 937 2333",
    "sg:postcode":"S0M 0E0",
    "sg:province":"SK",
    "sg:tags":[
        "engineer"
    ],
    "wof:name":"Schafer Engineering",
    "wof:placetype":"venue"
},
  "geometry": {"coordinates":[-108.31314086899999,52.7362365723],"type":"Point"}
}