{
  "type": "Feature",
  "properties": {
    "addr:full":"1560 Carrington Rd Mississauga ON L5M 2K1",
    "addr:housenumber":"1560",
    "addr:postcode":"l5m 2k1",
    "addr:street":"Carrington Rd",
    "iso:country":"CA",
    "sg:address":"1560 Carrington Rd",
    "sg:city":"Mississauga",
    "sg:classifiers":[
        {
            "category":"Professional",
            "subcategory":"Computer Services",
            "type":"Services"
        }
    ],
    "sg:phone":"+1 905 812 8282",
    "sg:postcode":"L5M 2K1",
    "sg:province":"ON",
    "sg:tags":[
        "internet"
    ],
    "wof:name":"Working Sites",
    "wof:placetype":"venue"
},
  "geometry": {"coordinates":[-79.695114,43.582375],"type":"Point"}
}