{
  "type": "Feature",
  "properties": {
    "iso:country":"CA",
    "sg:address":"34 Birch Hill Lane",
    "sg:city":"Oakville",
    "sg:classifiers":[
        {
            "category":"Professional",
            "subcategory":"Management & Consulting",
            "type":"Services"
        }
    ],
    "sg:phone":"+1 905 338 2626",
    "sg:postcode":"L6K 2N9",
    "sg:province":"ON",
    "sg:tags":[
        "consultant",
        "business"
    ],
    "wof:name":"Jenny Gonzalez & Assoc",
    "wof:placetype":"venue"
},
  "geometry": {"coordinates":[-79.68148,43.427563],"type":"Point"}
}