{
  "type": "Feature",
  "properties": {
    "addr:full":"85 Thorncliffe Park Dr # 1001 East York ON M4H 1L6",
    "addr:housenumber":"85",
    "addr:postcode":"m4h 1l6",
    "addr:street":"Thorncliffe Park Dr # 1001",
    "iso:country":"CA",
    "sg:address":"85 Thorncliffe Park Dr # 1001",
    "sg:city":"East York",
    "sg:classifiers":[
        {
            "category":"Professional",
            "subcategory":"Lawyer & Legal Services",
            "type":"Services"
        }
    ],
    "sg:phone":"+1 416 410 0312",
    "sg:postcode":"M4H 1L6",
    "sg:province":"ON",
    "sg:tags":[
        "attorney"
    ],
    "wof:name":"Zbarsky, M David",
    "wof:placetype":"venue"
},
  "geometry": {"coordinates":[-79.34296399999999,43.706409],"type":"Point"}
}