{
  "type": "Feature",
  "properties": {
    "iso:country":"CA",
    "sg:address":"2533 Rue Sainte-Catherine E",
    "sg:city":"Montreal",
    "sg:classifiers":[
        {
            "category":"Restaurant",
            "type":"Food & Drink"
        }
    ],
    "sg:phone":"+1 514 523 3170",
    "sg:postcode":"H2K 2K1",
    "sg:province":"QC",
    "wof:name":"Resto Bistro Les Courtisanes",
    "wof:placetype":"venue"
},
  "geometry": {"coordinates":[-73.545906,45.529877],"type":"Point"}
}