{
  "type": "Feature",
  "properties": {
    "iso:country":"CA",
    "sg:address":"20771 Fraser Hwy",
    "sg:city":"Langley",
    "sg:classifiers":[
        {
            "category":"Personal",
            "subcategory":"Tattoo Parlor",
            "type":"Services"
        }
    ],
    "sg:phone":"+1 604 533 6683",
    "sg:postcode":"V3A 4G4",
    "sg:province":"BC",
    "sg:tags":[
        "tattooing"
    ],
    "wof:name":"Lady Luck Tattoo",
    "wof:placetype":"venue"
},
  "geometry": {"coordinates":[-122.647453308,49.1026000977],"type":"Point"}
}