{
  "type": "Feature",
  "properties": {
    "addr:full":"6686 Sliammon Rd Powell River BC V8A 4Z3",
    "addr:housenumber":"6686",
    "addr:postcode":"v8a 4z3",
    "addr:street":"Sliammon Rd",
    "iso:country":"CA",
    "sg:address":"6686 Sliammon Rd",
    "sg:city":"Powell River",
    "sg:classifiers":[
        {
            "category":"Organizations",
            "subcategory":"Professional Association",
            "type":"Services"
        }
    ],
    "sg:phone":"+1 604 483 9646",
    "sg:postcode":"V8A 4Z3",
    "sg:province":"BC",
    "sg:tags":[
        "native"
    ],
    "wof:name":"Sliammon Band Council",
    "wof:placetype":"venue"
},
  "geometry": {"coordinates":[-124.60777299999999,49.898022],"type":"Point"}
}