{
  "type": "Feature",
  "properties": {
    "iso:country":"CA",
    "sg:city":"Aurora",
    "sg:classifiers":[
        {
            "category":"Personal",
            "subcategory":"Beauty Salon",
            "type":"Services"
        }
    ],
    "sg:phone":"+1 905 727 4561",
    "sg:postcode":"L4G 1N5",
    "sg:province":"ON",
    "wof:name":"Chimes Hair Group",
    "wof:placetype":"venue"
},
  "geometry": {"coordinates":[-79.467468,44.000084],"type":"Point"}
}