{
  "type": "Feature",
  "properties": {
    "addr:full":"3648 Rue Monselet Montreal-Nord QC H1H 2A8",
    "addr:housenumber":"3648",
    "addr:postcode":"h1h 2a8",
    "addr:street":"Rue Monselet",
    "iso:country":"CA",
    "sg:address":"3648 Rue Monselet",
    "sg:city":"Montreal-Nord",
    "sg:classifiers":[
        {
            "category":"Food & Beverages",
            "subcategory":"Groceries & Convenience Stores",
            "type":"Retail Goods"
        }
    ],
    "sg:phone":"+1 514 326 8970",
    "sg:postcode":"H1H 2A8",
    "sg:province":"QC",
    "wof:name":"Depanneur Chez Nenette",
    "wof:placetype":"venue"
},
  "geometry": {"coordinates":[-73.6428985596,45.5867996216],"type":"Point"}
}