{
  "type": "Feature",
  "properties": {
    "addr:full":"2180 Bloor St W Toronto ON M6S 1N3",
    "addr:housenumber":"2180",
    "addr:postcode":"m6s 1n3",
    "addr:street":"Bloor St W",
    "iso:country":"CA",
    "sg:address":"2180 Bloor St W",
    "sg:city":"Toronto",
    "sg:classifiers":[
        {
            "category":"Food & Beverages",
            "subcategory":"Liquor & Beverages",
            "type":"Retail Goods"
        }
    ],
    "sg:phone":"+1 416 767 8931",
    "sg:postcode":"M6S 1N3",
    "sg:province":"ON",
    "sg:tags":[
        "store"
    ],
    "wof:name":"Liquor Control Board",
    "wof:placetype":"venue"
},
  "geometry": {"coordinates":[-79.47429700000001,43.651672],"type":"Point"}
}