{
  "type": "Feature",
  "properties": {
    "addr:full":"Delta ON K0E 1G0",
    "addr:postcode":"k0e 1g0",
    "iso:country":"CA",
    "sg:city":"Delta",
    "sg:classifiers":[
        {
            "category":"Health Services",
            "subcategory":"Hospital",
            "type":"Services"
        }
    ],
    "sg:phone":"+1 613 928 3460",
    "sg:postcode":"K0E 1G0",
    "sg:province":"ON",
    "sg:tags":[
        "organization",
        "social",
        "mental",
        "welfare"
    ],
    "wof:name":"Leeds & Grenville Rehab",
    "wof:placetype":"venue"
},
  "geometry": {"coordinates":[-76.120773,44.615196],"type":"Point"}
}