{
  "type": "Feature",
  "properties": {
    "addr:full":"North York ON M6L 3C9",
    "addr:postcode":"m6l 3c9",
    "iso:country":"CA",
    "sg:city":"North York",
    "sg:classifiers":[
        {
            "category":"Shopping",
            "subcategory":"Pharmacy",
            "type":"Retail Goods"
        }
    ],
    "sg:phone":"+1 416 242 6377",
    "sg:postcode":"M6L 3C9",
    "sg:province":"ON",
    "wof:name":"Dupont Pharmacy Inc",
    "wof:placetype":"venue"
},
  "geometry": {"coordinates":[-79.49205000000001,43.705273],"type":"Point"}
}