{
  "type": "Feature",
  "properties": {
    "iso:country":"CA",
    "sg:address":"363 Rue Charles-Marchand",
    "sg:city":"Le Gardeur",
    "sg:classifiers":[
        {
            "category":"Manufacturing",
            "subcategory":"Tools & Machinery",
            "type":"Manufacturing & Wholesale Goods"
        }
    ],
    "sg:phone":"+1 450 585 9833",
    "sg:postcode":"J5Z 4N8",
    "sg:province":"QC",
    "sg:tags":[
        "equipment",
        "safety",
        "clothing"
    ],
    "wof:name":"Travex Equipements DE Securite",
    "wof:placetype":"venue"
},
  "geometry": {"coordinates":[-73.485229,45.757984],"type":"Point"}
}