{
  "type": "Feature",
  "properties": {
    "iso:country":"CA",
    "sg:address":"1 Goodmark Pl",
    "sg:city":"Etobicoke",
    "sg:classifiers":[
        {
            "category":"Wholesale",
            "subcategory":"Machinery & Supplies",
            "type":"Manufacturing & Wholesale Goods"
        }
    ],
    "sg:phone":"+1 416 213 0277",
    "sg:postcode":"M9W 6M1",
    "sg:province":"ON",
    "sg:tags":[
        "repairing"
    ],
    "wof:name":"K L Machinery & Maintenance",
    "wof:placetype":"venue"
},
  "geometry": {"coordinates":[-79.619148,43.752857],"type":"Point"}
}