{
  "type": "Feature",
  "properties": {
    "addr:full":"PO Box 1227 Fort Macleod AB T0L 0Z0",
    "addr:housenumber":"po",
    "addr:postcode":"t0l 0z0",
    "addr:street":"Box 1227 Fort",
    "iso:country":"CA",
    "sg:address":"PO Box 1227",
    "sg:city":"Fort Macleod",
    "sg:classifiers":[
        {
            "category":"Farming",
            "subcategory":"Livestock Farm",
            "type":"Manufacturing & Wholesale Goods"
        }
    ],
    "sg:phone":"+1 403 553 3110",
    "sg:postcode":"T0L 0Z0",
    "sg:province":"AB",
    "sg:tags":[
        "feeding"
    ],
    "wof:name":"Larson Custom Feeders Ltd",
    "wof:placetype":"venue"
},
  "geometry": {"coordinates":[-113.395584,49.726074],"type":"Point"}
}