{
  "type": "Feature",
  "properties": {
    "addr:full":"571 Ch DE Normandie Saint-Felix-DE-Valois QC J0K 2M0",
    "addr:housenumber":"571",
    "addr:postcode":"j0k 2m0",
    "addr:street":"Ch De Normandie Saint-Felix-De-Valois",
    "iso:country":"CA",
    "sg:address":"571 Ch DE Normandie",
    "sg:city":"Saint-Felix-DE-Valois",
    "sg:classifiers":[
        {
            "category":"Building & Trades",
            "subcategory":"Construction",
            "type":"Services"
        }
    ],
    "sg:phone":"+1 450 889 5248",
    "sg:postcode":"J0K 2M0",
    "sg:province":"QC",
    "sg:tags":[
        "contractor"
    ],
    "wof:name":"Constructions Marc Aubin Inc",
    "wof:placetype":"venue"
},
  "geometry": {"coordinates":[-73.479904,46.167313],"type":"Point"}
}