{
  "type": "Feature",
  "properties": {
    "addr:full":"Sec 62 Port DE Montreal Montreal QC H1N 3L3",
    "addr:housenumber":"sec 62",
    "addr:postcode":"h1n 3l3",
    "addr:street":"Port De Montreal",
    "iso:country":"CA",
    "sg:address":"Sec 62 Port DE Montreal",
    "sg:city":"Montreal",
    "sg:classifiers":[
        {
            "category":"Professional",
            "subcategory":"Employment Agencies",
            "type":"Services"
        }
    ],
    "sg:phone":"+1 514 257 3040",
    "sg:postcode":"H1N 3L3",
    "sg:province":"QC",
    "sg:tags":[
        "contractor"
    ],
    "wof:name":"Terminus Racine Ltee",
    "wof:placetype":"venue"
},
  "geometry": {"coordinates":[-73.55438995359999,45.5122871399],"type":"Point"}
}