{
  "type": "Feature",
  "properties": {
    "addr:full":"Norman Wells NT X0E 0V0",
    "addr:postcode":"x0e 0v0",
    "iso:country":"CA",
    "sg:city":"Norman Wells",
    "sg:classifiers":[
        {
            "category":"Government",
            "subcategory":"Office",
            "type":"Public Place"
        }
    ],
    "sg:phone":"+1 867 587 2632",
    "sg:postcode":"X0E 0V0",
    "sg:province":"NT",
    "wof:name":"Norman Wells Community Social",
    "wof:placetype":"venue"
},
  "geometry": {"coordinates":[-126.706688,65.306335],"type":"Point"}
}