{
  "type": "Feature",
  "properties": {
    "iso:country":"CA",
    "sg:address":"1586 the Queensway",
    "sg:city":"Etobicoke",
    "sg:classifiers":[
        {
            "category":"Wholesale",
            "subcategory":"Hardware",
            "type":"Manufacturing & Wholesale Goods"
        }
    ],
    "sg:phone":"+1 416 259 9396",
    "sg:postcode":"M8Z 1V1",
    "sg:province":"ON",
    "sg:tags":[
        "tool"
    ],
    "wof:name":"Annual Rings Import Export Ltd",
    "wof:placetype":"venue"
},
  "geometry": {"coordinates":[-79.54187774659999,43.6176338196],"type":"Point"}
}