{
  "type": "Feature",
  "properties": {
    "addr:full":"198 Maple Leaf Lane Wellington Station PE C0B 2E0",
    "addr:housenumber":"198",
    "addr:postcode":"c0b 2e0",
    "addr:street":"Maple Leaf Lane",
    "iso:country":"CA",
    "sg:address":"198 Maple Leaf Lane",
    "sg:city":"Wellington Station",
    "sg:classifiers":[
        {
            "category":"Freight",
            "type":"Transportation"
        }
    ],
    "sg:phone":"+1 902 854 2409",
    "sg:postcode":"C0B 2E0",
    "sg:province":"PE",
    "sg:tags":[
        "trucking"
    ],
    "wof:name":"Prince Freight Lines Inc",
    "wof:placetype":"venue"
},
  "geometry": {"coordinates":[-64.0004501343,46.4499511719],"type":"Point"}
}