{
  "type": "Feature",
  "properties": {
    "addr:full":"10720 97 St NW Edmonton AB T5H 2L8",
    "addr:housenumber":"10720",
    "addr:postcode":"t5h 2l8",
    "addr:street":"97 St Nw",
    "iso:country":"CA",
    "sg:address":"10720 97 St NW",
    "sg:city":"Edmonton",
    "sg:classifiers":[
        {
            "category":"Restaurant",
            "type":"Food & Drink"
        }
    ],
    "sg:phone":"+1 780 423 7708",
    "sg:postcode":"T5H 2L8",
    "sg:province":"AB",
    "wof:name":"Khanh Hoa",
    "wof:placetype":"venue"
},
  "geometry": {"coordinates":[-113.489807,53.552097],"type":"Point"}
}