{
  "type": "Feature",
  "properties": {
    "addr:full":"4093 Ogden Rd SE Calgary AB T2G 4P9",
    "addr:housenumber":"4093",
    "addr:postcode":"t2g 4p9",
    "addr:street":"Ogden Rd Se",
    "iso:country":"CA",
    "sg:address":"4093 Ogden Rd SE",
    "sg:city":"Calgary",
    "sg:classifiers":[
        {
            "category":"Manufacturing",
            "subcategory":"Tools & Machinery",
            "type":"Manufacturing & Wholesale Goods"
        }
    ],
    "sg:phone":"+1 403 216 8439",
    "sg:postcode":"T2G 4P9",
    "sg:province":"AB",
    "sg:tags":[
        "plumbing",
        "contractor"
    ],
    "wof:name":"Clearview Plumbing & Heating",
    "wof:placetype":"venue"
},
  "geometry": {"coordinates":[-114.020423889,51.0184669495],"type":"Point"}
}