{
  "type": "Feature",
  "properties": {
    "addr:full":"31 Maplecrete Rd Concord ON L4K 1A5",
    "addr:housenumber":"31",
    "addr:postcode":"l4k 1a5",
    "addr:street":"Maplecrete Rd",
    "iso:country":"CA",
    "sg:address":"31 Maplecrete Rd",
    "sg:city":"Concord",
    "sg:classifiers":[
        {
            "category":"Manufacturing",
            "subcategory":"Metals",
            "type":"Manufacturing & Wholesale Goods"
        }
    ],
    "sg:phone":"+1 905 669 2266",
    "sg:postcode":"L4K 1A5",
    "sg:province":"ON",
    "sg:tags":[
        "steel"
    ],
    "wof:name":"Dynahyd Equipment Ltd",
    "wof:placetype":"venue"
},
  "geometry": {"coordinates":[-79.519516,43.789677],"type":"Point"}
}