{
  "type": "Feature",
  "properties": {
    "addr:full":"1560 Gamble Pl Winnipeg MB R3T 1N6",
    "addr:housenumber":"1560",
    "addr:postcode":"r3t 1n6",
    "addr:street":"Gamble Pl",
    "iso:country":"CA",
    "sg:address":"1560 Gamble Pl",
    "sg:city":"Winnipeg",
    "sg:classifiers":[
        {
            "category":"Wholesale",
            "subcategory":"Machinery & Supplies",
            "type":"Manufacturing & Wholesale Goods"
        }
    ],
    "sg:phone":"+1 204 453 8909",
    "sg:postcode":"R3T 1N6",
    "sg:province":"MB",
    "sg:tags":[
        "contractor"
    ],
    "wof:name":"Delta Industrial Supply Ltd",
    "wof:placetype":"venue"
},
  "geometry": {"coordinates":[-97.1751403809,49.8335609436],"type":"Point"}
}