{
  "type": "Feature",
  "properties": {
    "addr:full":"Hwy 1 E Regina SK S4P 2Z5",
    "addr:postcode":"s4p 2z5",
    "addr:street":"Hwy 1 E",
    "iso:country":"CA",
    "sg:address":"Hwy 1 E",
    "sg:city":"Regina",
    "sg:classifiers":[
        {
            "category":"Personal",
            "subcategory":"Shoe Repair & Shine",
            "type":"Services"
        }
    ],
    "sg:phone":"+1 306 546 4844",
    "sg:postcode":"S4P 2Z5",
    "sg:province":"SK",
    "sg:tags":[
        "repairing",
        "boot"
    ],
    "wof:name":"K M Brice Boot & Saddle Repair",
    "wof:placetype":"venue"
},
  "geometry": {"coordinates":[-104.58442688,50.4471168518],"type":"Point"}
}