{
  "type": "Feature",
  "properties": {
    "addr:full":"20 Batteaux Rd Nottawa ON L0M 1P0",
    "addr:housenumber":"20",
    "addr:postcode":"l0m 1p0",
    "addr:street":"Batteaux Rd",
    "iso:country":"CA",
    "sg:address":"20 Batteaux Rd",
    "sg:city":"Nottawa",
    "sg:classifiers":[
        {
            "category":"Organizations",
            "subcategory":"Religious Organization",
            "type":"Services"
        }
    ],
    "sg:phone":"+1 705 445 1412",
    "sg:postcode":"L0M 1P0",
    "sg:province":"ON",
    "sg:tags":[
        "church"
    ],
    "wof:name":"Cornerstone Pentecostal Flwshp",
    "wof:placetype":"venue"
},
  "geometry": {"coordinates":[-80.2029266357,44.4613990784],"type":"Point"}
}