{
  "type": "Feature",
  "properties": {
    "addr:full":"64 Robertson Rd Nepean ON K2H 5Y8",
    "addr:housenumber":"64",
    "addr:postcode":"k2h 5y8",
    "addr:street":"Robertson Rd",
    "iso:country":"CA",
    "sg:address":"64 Robertson Rd",
    "sg:city":"Nepean",
    "sg:classifiers":[
        {
            "category":"Shopping",
            "subcategory":"Catalog Store",
            "type":"Retail Goods"
        }
    ],
    "sg:phone":"+1 613 829 1071",
    "sg:postcode":"K2H 5Y8",
    "sg:province":"ON",
    "sg:tags":[
        "mail",
        "order",
        "internet"
    ],
    "wof:name":"Sears Catalog Store",
    "wof:placetype":"venue"
},
  "geometry": {"coordinates":[-75.831497,45.322647],"type":"Point"}
}