{
  "type": "Feature",
  "properties": {
    "addr:full":"7975 49 Ave Red Deer AB T4P 2V5",
    "addr:housenumber":"7975",
    "addr:postcode":"t4p 2v5",
    "addr:street":"49 Ave",
    "iso:country":"CA",
    "sg:address":"7975 49 Ave",
    "sg:city":"Red Deer",
    "sg:classifiers":[
        {
            "category":"Wholesale",
            "subcategory":"Machinery & Supplies",
            "type":"Manufacturing & Wholesale Goods"
        }
    ],
    "sg:phone":"+1 403 309 6366",
    "sg:postcode":"T4P 2V5",
    "sg:province":"AB",
    "sg:tags":[
        "equipment",
        "oil",
        "well"
    ],
    "wof:name":"Panther Probe Inc",
    "wof:placetype":"venue"
},
  "geometry": {"coordinates":[-113.813827515,52.2885017395],"type":"Point"}
}