{
  "type": "Feature",
  "properties": {
    "iso:country":"CA",
    "sg:address":"790 Swallowtail Cres",
    "sg:city":"Orleans",
    "sg:classifiers":[
        {
            "category":"Building & Trades",
            "subcategory":"Construction",
            "type":"Services"
        }
    ],
    "sg:phone":"+1 613 837 1511",
    "sg:postcode":"K4A 4M2",
    "sg:province":"ON",
    "sg:tags":[
        "general",
        "contractor"
    ],
    "wof:name":"Tamarack Development Corp",
    "wof:placetype":"venue"
},
  "geometry": {"coordinates":[-75.4652557373,45.4644393921],"type":"Point"}
}