{
  "type": "Feature",
  "properties": {
    "addr:full":"Calgary AB T2E 7M8",
    "addr:postcode":"t2e 7m8",
    "iso:country":"CA",
    "sg:city":"Calgary",
    "sg:classifiers":[
        {
            "category":"Government",
            "subcategory":"Office",
            "type":"Public Place"
        }
    ],
    "sg:phone":"+1 403 297 6311",
    "sg:postcode":"T2E 7M8",
    "sg:province":"AB",
    "wof:name":"Alberta Transportation-Utlts",
    "wof:placetype":"venue"
},
  "geometry": {"coordinates":[-114.018836975,51.0567474365],"type":"Point"}
}