{
  "type": "Feature",
  "properties": {
    "addr:full":"3405 21st Ave Blairmore AB T0K 0E0",
    "addr:housenumber":"3405",
    "addr:postcode":"t0k 0e0",
    "addr:street":"21St Ave",
    "iso:country":"CA",
    "sg:address":"3405 21st Ave",
    "sg:city":"Blairmore",
    "sg:classifiers":[
        {
            "category":"Organizations",
            "subcategory":"Religious Organization",
            "type":"Services"
        }
    ],
    "sg:phone":"+1 403 562 2745",
    "sg:postcode":"T0K 0E0",
    "sg:province":"AB",
    "sg:tags":[
        "church"
    ],
    "wof:name":"Crowsnest Comm Baptist Church",
    "wof:placetype":"venue"
},
  "geometry": {"coordinates":[-114.459312,49.61298],"type":"Point"}
}