{
  "type": "Feature",
  "properties": {
    "addr:full":"289 Bay St Sault Ste Marie ON P6A 1W7",
    "addr:housenumber":"289",
    "addr:postcode":"p6a 1w7",
    "addr:street":"Bay St",
    "iso:country":"CA",
    "sg:address":"289 Bay St",
    "sg:city":"Sault Ste Marie",
    "sg:classifiers":[
        {
            "category":"Restaurant",
            "type":"Food & Drink"
        }
    ],
    "sg:phone":"+1 705 256 6995",
    "sg:postcode":"P6A 1W7",
    "sg:province":"ON",
    "sg:tags":[
        "pizza"
    ],
    "wof:name":"Ricardo's Big Slice Pizza",
    "wof:placetype":"venue"
},
  "geometry": {"coordinates":[-84.339417,46.514305],"type":"Point"}
}