{
  "type": "Feature",
  "properties": {
    "addr:full":"539 Barton St E Hamilton ON L8L 2Y9",
    "addr:housenumber":"539",
    "addr:postcode":"l8l 2y9",
    "addr:street":"Barton St E",
    "iso:country":"CA",
    "sg:address":"539 Barton St E",
    "sg:city":"Hamilton",
    "sg:classifiers":[
        {
            "category":"Restaurant",
            "type":"Food & Drink"
        }
    ],
    "sg:phone":"+1 905 529 6379",
    "sg:postcode":"L8L 2Y9",
    "sg:province":"ON",
    "wof:name":"Golden Dragon Restaurant",
    "wof:placetype":"venue"
},
  "geometry": {"coordinates":[-79.842613,43.258316],"type":"Point"}
}