{
  "type": "Feature",
  "properties": {
    "addr:full":"Winnipeg MB R3H 1B3",
    "addr:postcode":"r3h 1b3",
    "iso:country":"CA",
    "sg:city":"Winnipeg",
    "sg:classifiers":[
        {
            "category":"Professional",
            "type":"Services"
        }
    ],
    "sg:phone":"+1 204 954 7300",
    "sg:postcode":"R3H 1B3",
    "sg:province":"MB",
    "sg:tags":[
        "actuary"
    ],
    "wof:name":"Ellement & Ellement Ltd",
    "wof:placetype":"venue"
},
  "geometry": {"coordinates":[-97.207718,49.901314],"type":"Point"}
}