{
  "type": "Feature",
  "properties": {
    "iso:country":"CA",
    "sg:address":"50 King St",
    "sg:city":"London",
    "sg:classifiers":[
        {
            "category":"Organizations",
            "subcategory":"Religious Organization",
            "type":"Services"
        }
    ],
    "sg:phone":"+1 519 461 1771",
    "sg:postcode":"N6A 5L7",
    "sg:province":"ON",
    "sg:tags":[
        "church"
    ],
    "wof:name":"Thorndale Zion United Church",
    "wof:placetype":"venue"
},
  "geometry": {"coordinates":[-81.25369262700001,42.9813919067],"type":"Point"}
}