{
  "type": "Feature",
  "properties": {
    "addr:full":"Drummondville QC J2C 1J7",
    "addr:postcode":"j2c 1j7",
    "iso:country":"CA",
    "sg:city":"Drummondville",
    "sg:classifiers":[
        {
            "category":"Shopping",
            "subcategory":"Shoes",
            "type":"Retail Goods"
        }
    ],
    "sg:phone":"+1 819 474 1130",
    "sg:postcode":"J2C 1J7",
    "sg:province":"QC",
    "wof:name":"Chaussures Medico Plus",
    "wof:placetype":"venue"
},
  "geometry": {"coordinates":[-72.491158,45.886326],"type":"Point"}
}