{
  "type": "Feature",
  "properties": {
    "addr:full":"53 Robinson Dr Okotoks AB T1S 1M6",
    "addr:housenumber":"53",
    "addr:postcode":"t1s 1m6",
    "addr:street":"Robinson Dr Okotoks Ab",
    "iso:country":"CA",
    "sg:address":"53 Robinson Dr",
    "sg:city":"Okotoks",
    "sg:classifiers":[
        {
            "category":"Wholesale",
            "subcategory":"Groceries",
            "type":"Manufacturing & Wholesale Goods"
        }
    ],
    "sg:phone":"+1 403 254 1776",
    "sg:postcode":"T1S 1M6",
    "sg:province":"AB",
    "sg:tags":[
        "therapist",
        "massage"
    ],
    "wof:name":"Better Health Therapy Ctr",
    "wof:placetype":"venue"
},
  "geometry": {"coordinates":[-113.970169067,50.7365608215],"type":"Point"}
}