{
  "type": "Feature",
  "properties": {
    "addr:full":"Scarborough ON M1V 4Z6",
    "addr:postcode":"m1v 4z6",
    "iso:country":"CA",
    "sg:city":"Scarborough",
    "sg:classifiers":[
        {
            "category":"Manufacturing",
            "subcategory":"Apparel",
            "type":"Manufacturing & Wholesale Goods"
        }
    ],
    "sg:phone":"+1 416 299 4383",
    "sg:postcode":"M1V 4Z6",
    "sg:province":"ON",
    "wof:name":"Fashion Valley",
    "wof:placetype":"venue"
},
  "geometry": {"coordinates":[-79.26219940190001,43.8213729858],"type":"Point"}
}