{
  "type": "Feature",
  "properties": {
    "addr:full":"Saint-Constant QC J5A 2L5",
    "addr:postcode":"j5a 2l5",
    "iso:country":"CA",
    "sg:city":"Saint-Constant",
    "sg:classifiers":[
        {
            "category":"Restaurant",
            "type":"Food & Drink"
        }
    ],
    "sg:phone":"+1 450 638 6975",
    "sg:postcode":"J5A 2L5",
    "sg:province":"QC",
    "wof:name":"Subway Sandwiches & Salades",
    "wof:placetype":"venue"
},
  "geometry": {"coordinates":[-73.570999,45.371037],"type":"Point"}
}