{
  "type": "Feature",
  "properties": {
    "addr:full":"Courtenay BC V9N 1P5",
    "addr:postcode":"v9n 1p5",
    "iso:country":"CA",
    "sg:city":"Courtenay",
    "sg:classifiers":[
        {
            "category":"Home & Garden",
            "subcategory":"Carpets & Floor Coverings",
            "type":"Retail Goods"
        }
    ],
    "sg:phone":"+1 250 338 5511",
    "sg:postcode":"V9N 1P5",
    "sg:province":"BC",
    "sg:tags":[
        "dealer",
        "rug"
    ],
    "wof:name":"United Carpet",
    "wof:placetype":"venue"
},
  "geometry": {"coordinates":[-124.99646799999999,49.68784],"type":"Point"}
}