{
  "type": "Feature",
  "properties": {
    "iso:country":"CA",
    "sg:address":"820 Tower St S",
    "sg:city":"Fergus",
    "sg:classifiers":[
        {
            "category":"Restaurant",
            "type":"Food & Drink"
        }
    ],
    "sg:phone":"+1 519 787 2891",
    "sg:postcode":"N1M 2R3",
    "sg:province":"ON",
    "wof:name":"Subway Sandwiches & Salads",
    "wof:placetype":"venue"
},
  "geometry": {"coordinates":[-80.36902600000001,43.697289],"type":"Point"}
}