{
  "type": "Feature",
  "properties": {
    "iso:country":"CA",
    "sg:address":"68 Simcoe St N",
    "sg:city":"Oshawa",
    "sg:classifiers":[
        {
            "category":"Retail",
            "subcategory":"Laundry & Dry Cleaning",
            "type":"Services"
        }
    ],
    "sg:phone":"+1 905 725 0643",
    "sg:postcode":"L1G 4S2",
    "sg:province":"ON",
    "sg:tags":[
        "cleaners"
    ],
    "wof:name":"Maple Cleaners",
    "wof:placetype":"venue"
},
  "geometry": {"coordinates":[-78.864716,43.89949],"type":"Point"}
}