{
  "type": "Feature",
  "properties": {
    "addr:full":"104 6th St W Carlyle SK S0C 0R0",
    "addr:housenumber":"104",
    "addr:postcode":"s0c 0r0",
    "addr:street":"6Th St W Carlyle",
    "iso:country":"CA",
    "sg:address":"104 6th St W",
    "sg:city":"Carlyle",
    "sg:classifiers":[
        {
            "category":"Organizations",
            "subcategory":"Religious Organization",
            "type":"Services"
        }
    ],
    "sg:phone":"+1 306 453 6255",
    "sg:postcode":"S0C 0R0",
    "sg:province":"SK",
    "sg:tags":[
        "church"
    ],
    "wof:name":"Christian Community Chapel",
    "wof:placetype":"venue"
},
  "geometry": {"coordinates":[-102.274315,49.637234],"type":"Point"}
}