{
  "type": "Feature",
  "properties": {
    "addr:full":"6518 Chebucto Rd Halifax NS B3L 1L7",
    "addr:housenumber":"6518",
    "addr:postcode":"b3l 1l7",
    "addr:street":"Chebucto Rd",
    "iso:country":"CA",
    "sg:address":"6518 Chebucto Rd",
    "sg:city":"Halifax",
    "sg:classifiers":[
        {
            "category":"Retail",
            "subcategory":"Laundry & Dry Cleaning",
            "type":"Services"
        }
    ],
    "sg:phone":"+1 902 422 5571",
    "sg:postcode":"B3L 1L7",
    "sg:province":"NS",
    "sg:tags":[
        "cleaners"
    ],
    "wof:name":"Olympic Laundromat",
    "wof:placetype":"venue"
},
  "geometry": {"coordinates":[-63.605682,44.647751],"type":"Point"}
}