{
  "type": "Feature",
  "properties": {
    "addr:full":"11 Oakmount Pl SW Calgary AB T2V 4Y2",
    "addr:housenumber":"11",
    "addr:postcode":"t2v 4y2",
    "addr:street":"Oakmount Pl Sw",
    "iso:country":"CA",
    "sg:address":"11 Oakmount Pl SW",
    "sg:city":"Calgary",
    "sg:classifiers":[
        {
            "category":"Wholesale",
            "subcategory":"Office Equipment",
            "type":"Manufacturing & Wholesale Goods"
        }
    ],
    "sg:phone":"+1 403 238 3555",
    "sg:postcode":"T2V 4Y2",
    "sg:province":"AB",
    "sg:tags":[
        "blueprinting",
        "supply"
    ],
    "wof:name":"Measure Masters Calgary",
    "wof:placetype":"venue"
},
  "geometry": {"coordinates":[-114.137856,50.973476],"type":"Point"}
}