{
  "type": "Feature",
  "properties": {
    "iso:country":"CA",
    "sg:address":"1780 Rue Bagot",
    "sg:city":"LA Baie",
    "sg:classifiers":[
        {
            "category":"Building & Trades",
            "subcategory":"Construction",
            "type":"Services"
        }
    ],
    "sg:phone":"+1 418 544 7353",
    "sg:postcode":"G7B 2R1",
    "sg:province":"QC",
    "sg:tags":[
        "carpet",
        "rug",
        "dealer"
    ],
    "wof:name":"Peinture LA Baie",
    "wof:placetype":"venue"
},
  "geometry": {"coordinates":[-70.89134979249999,48.336391449],"type":"Point"}
}