{
  "type": "Feature",
  "properties": {
    "iso:country":"CA",
    "sg:address":"75 Sq Sir-G.-Etienne-Cartier",
    "sg:city":"Montreal",
    "sg:classifiers":[
        {
            "category":"Education",
            "subcategory":"School",
            "type":"Public Place"
        }
    ],
    "sg:phone":"+1 514 596 4769",
    "sg:postcode":"H4C 3A1",
    "sg:province":"QC",
    "wof:name":"Acces Ouest",
    "wof:placetype":"venue"
},
  "geometry": {"coordinates":[-73.583809,45.472794],"type":"Point"}
}