{
  "type": "Feature",
  "properties": {
    "addr:full":"Humboldt SK S0K 2A0",
    "addr:postcode":"s0k 2a0",
    "addr:street":"Humboldt",
    "iso:country":"CA",
    "sg:city":"Humboldt",
    "sg:classifiers":[
        {
            "category":"Travel",
            "subcategory":"Hotels & Motels",
            "type":"Entertainment"
        }
    ],
    "sg:phone":"+1 306 682 3733",
    "sg:postcode":"S0K 2A0",
    "sg:province":"SK",
    "wof:name":"Carmel Hotel",
    "wof:placetype":"venue"
},
  "geometry": {"coordinates":[-105.12146758999999,52.2019004822],"type":"Point"}
}