{
  "type": "Feature",
  "properties": {
    "addr:full":"PO Box 525 Burin NL A0E 1E0",
    "addr:housenumber":"po",
    "addr:postcode":"a0e 1e0",
    "addr:street":"Box 525",
    "iso:country":"CA",
    "sg:address":"PO Box 525",
    "sg:city":"Burin",
    "sg:classifiers":[
        {
            "category":"Organizations",
            "subcategory":"Membership Organization",
            "type":"Services"
        }
    ],
    "sg:phone":"+1 709 891 8000",
    "sg:postcode":"A0E 1E0",
    "sg:province":"NL",
    "sg:tags":[
        "protection",
        "animal"
    ],
    "wof:name":"Burin Peninsula Spca",
    "wof:placetype":"venue"
},
  "geometry": {"coordinates":[-55.163105,47.050446],"type":"Point"}
}