{
  "type": "Feature",
  "properties": {
    "addr:full":"1008 20th St W Saskatoon SK S7M 0Y7",
    "addr:housenumber":"1008",
    "addr:postcode":"s7m 0y7",
    "addr:street":"20Th St W",
    "iso:country":"CA",
    "sg:address":"1008 20th St W",
    "sg:city":"Saskatoon",
    "sg:classifiers":[
        {
            "category":"Wholesale",
            "subcategory":"Hardware",
            "type":"Manufacturing & Wholesale Goods"
        }
    ],
    "sg:phone":"+1 306 242 0717",
    "sg:postcode":"S7M 0Y7",
    "sg:province":"SK",
    "sg:tags":[
        "fastener"
    ],
    "wof:name":"Ti-Ten Distributors",
    "wof:placetype":"venue"
},
  "geometry": {"coordinates":[-106.68465399999999,52.126316],"type":"Point"}
}