{
  "type": "Feature",
  "properties": {
    "addr:full":"73 Rue Gamelin Hull QC J8Y 1V5",
    "addr:housenumber":"73",
    "addr:postcode":"j8y 1v5",
    "addr:street":"Rue Gamelin",
    "iso:country":"CA",
    "sg:address":"73 Rue Gamelin",
    "sg:city":"Hull",
    "sg:classifiers":[
        {
            "category":"Health Services",
            "subcategory":"Chiropractor",
            "type":"Services"
        }
    ],
    "sg:phone":"+1 819 595 1319",
    "sg:postcode":"J8Y 1V5",
    "sg:province":"QC",
    "wof:name":"Clinique Chiropratique Gamelin",
    "wof:placetype":"venue"
},
  "geometry": {"coordinates":[-75.736603,45.443516],"type":"Point"}
}