{
  "type": "Feature",
  "properties": {
    "addr:full":"375 Finley Ave Ajax ON L1S 2E2",
    "addr:housenumber":"375",
    "addr:postcode":"l1s 2e2",
    "addr:street":"Finley Ave",
    "iso:country":"CA",
    "sg:address":"375 Finley Ave",
    "sg:city":"Ajax",
    "sg:classifiers":[
        {
            "category":"Shopping",
            "subcategory":"Computers & Home Electronics",
            "type":"Retail Goods"
        }
    ],
    "sg:phone":"+1 905 683 7536",
    "sg:postcode":"L1S 2E2",
    "sg:province":"ON",
    "sg:tags":[
        "health",
        "clinic",
        "safety",
        "occupational",
        "software"
    ],
    "wof:name":"Mobile Industrial Health Svc",
    "wof:placetype":"venue"
},
  "geometry": {"coordinates":[-79.0294952393,43.8388786316],"type":"Point"}
}