{
  "type": "Feature",
  "properties": {
    "iso:country":"CA",
    "sg:city":"Woodbridge",
    "sg:classifiers":[
        {
            "category":"Personal",
            "type":"Services"
        }
    ],
    "sg:phone":"+1 905 850 0770",
    "sg:postcode":"L4L 4Y5",
    "sg:province":"ON",
    "sg:tags":[
        "wear",
        "formal"
    ],
    "wof:name":"Syd Silver Formals Ltd",
    "wof:placetype":"venue"
},
  "geometry": {"coordinates":[-79.552521,43.769196],"type":"Point"}
}