{
  "type": "Feature",
  "properties": {
    "iso:country":"CA",
    "sg:address":"570 Av Beaumont",
    "sg:city":"Montreal",
    "sg:classifiers":[
        {
            "category":"Shopping",
            "subcategory":"Clothing, Apparel, & Fashions",
            "type":"Retail Goods"
        }
    ],
    "sg:phone":"+1 514 272 9000",
    "sg:postcode":"H3N 1T7",
    "sg:province":"QC",
    "sg:tags":[
        "item",
        "boutique"
    ],
    "wof:name":"Rose Ladies Wear",
    "wof:placetype":"venue"
},
  "geometry": {"coordinates":[-73.6196975708,45.5269851685],"type":"Point"}
}