{
  "type": "Feature",
  "properties": {
    "addr:full":"135 109th St Saskatoon SK S7N 1R3",
    "addr:housenumber":"135",
    "addr:postcode":"s7n 1r3",
    "addr:street":"109Th St",
    "iso:country":"CA",
    "sg:address":"135 109th St",
    "sg:city":"Saskatoon",
    "sg:classifiers":[
        {
            "category":"Organizations",
            "subcategory":"Religious Organization",
            "type":"Services"
        }
    ],
    "sg:phone":"+1 306 374 8808",
    "sg:postcode":"S7N 1R3",
    "sg:province":"SK",
    "sg:tags":[
        "church"
    ],
    "wof:name":"St Matthew's Anglican Church",
    "wof:placetype":"venue"
},
  "geometry": {"coordinates":[-106.60086800000001,52.137489],"type":"Point"}
}