{
  "type": "Feature",
  "properties": {
    "addr:full":"11461 Rue Hamon Montreal QC H3M 3E4",
    "addr:housenumber":"11461",
    "addr:postcode":"h3m 3e4",
    "addr:street":"Rue Hamon",
    "iso:country":"CA",
    "sg:address":"11461 Rue Hamon",
    "sg:city":"Montreal",
    "sg:classifiers":[
        {
            "category":"Communications",
            "subcategory":"Film & Video Production",
            "type":"Services"
        }
    ],
    "sg:phone":"+1 514 331 6636",
    "sg:postcode":"H3M 3E4",
    "sg:province":"QC",
    "sg:tags":[
        "motion",
        "picture",
        "effects",
        "special"
    ],
    "wof:name":"Productions DE L'Intrigue Inc",
    "wof:placetype":"venue"
},
  "geometry": {"coordinates":[-73.6833190918,45.5411224365],"type":"Point"}
}