{
  "type": "Feature",
  "properties": {
    "addr:full":"Toronto ON M5R 1N4",
    "addr:postcode":"m5r 1n4",
    "iso:country":"CA",
    "sg:city":"Toronto",
    "sg:classifiers":[
        {
            "category":"Professional",
            "subcategory":"Management & Consulting",
            "type":"Services"
        }
    ],
    "sg:phone":"+1 416 920 0017",
    "sg:postcode":"M5R 1N4",
    "sg:province":"ON",
    "sg:tags":[
        "consultant",
        "business"
    ],
    "wof:name":"Two Seas Ltd",
    "wof:placetype":"venue"
},
  "geometry": {"coordinates":[-79.396393,43.673164],"type":"Point"}
}