{
  "type": "Feature",
  "properties": {
    "addr:full":"2868 Belisle Dr Val Caron ON P3N 1B3",
    "addr:housenumber":"2868",
    "addr:postcode":"p3n 1b3",
    "addr:street":"Belisle Dr",
    "iso:country":"CA",
    "sg:address":"2868 Belisle Dr",
    "sg:city":"Val Caron",
    "sg:classifiers":[
        {
            "category":"Retail",
            "subcategory":"Auto Repair",
            "type":"Services"
        }
    ],
    "sg:phone":"+1 705 897 1320",
    "sg:postcode":"P3N 1B3",
    "sg:province":"ON",
    "sg:tags":[
        "repairing",
        "automobile"
    ],
    "wof:name":"Rene's Auto Svc",
    "wof:placetype":"venue"
},
  "geometry": {"coordinates":[-81.02852630620001,46.6060714722],"type":"Point"}
}