{
  "type": "Feature",
  "properties": {
    "addr:full":"8275 Rue Mayrand Montreal QC H4P 2C7",
    "addr:housenumber":"8275",
    "addr:postcode":"h4p 2c7",
    "addr:street":"Rue Mayrand",
    "iso:country":"CA",
    "sg:address":"8275 Rue Mayrand",
    "sg:city":"Montreal",
    "sg:classifiers":[
        {
            "category":"Retail",
            "subcategory":"Auto Repair",
            "type":"Services"
        }
    ],
    "sg:phone":"+1 514 735 6494",
    "sg:postcode":"H4P 2C7",
    "sg:province":"QC",
    "sg:tags":[
        "repairing",
        "automobile"
    ],
    "wof:name":"B Express",
    "wof:placetype":"venue"
},
  "geometry": {"coordinates":[-73.65888214109999,45.5004959106],"type":"Point"}
}