{
  "type": "Feature",
  "properties": {
    "addr:full":"211 Center St Nipawin SK S0E 1E0",
    "addr:housenumber":"211",
    "addr:postcode":"s0e 1e0",
    "addr:street":"Center St",
    "iso:country":"CA",
    "sg:address":"211 Center St",
    "sg:city":"Nipawin",
    "sg:classifiers":[
        {
            "category":"Food & Beverages",
            "subcategory":"Meat & Fish",
            "type":"Retail Goods"
        }
    ],
    "sg:phone":"+1 306 862 2556",
    "sg:postcode":"S0E 1E0",
    "sg:province":"SK",
    "wof:name":"B J's Sausage & Meats",
    "wof:placetype":"venue"
},
  "geometry": {"coordinates":[-104.026283264,53.3567428589],"type":"Point"}
}