{
  "type": "Feature",
  "properties": {
    "addr:full":"6455 Boul Des Chenaux Trois-Rivieres QC G8Y 5A9",
    "addr:housenumber":"6455",
    "addr:postcode":"g8y 5a9",
    "addr:street":"Boul Des Chenaux Trois-Rivieres",
    "iso:country":"CA",
    "sg:address":"6455 Boul Des Chenaux",
    "sg:city":"Trois-Rivieres",
    "sg:classifiers":[
        {
            "category":"Food & Beverages",
            "subcategory":"Groceries & Convenience Stores",
            "type":"Retail Goods"
        }
    ],
    "sg:phone":"+1 819 373 1034",
    "sg:postcode":"G8Y 5A9",
    "sg:province":"QC",
    "wof:name":"Depanneur Des Chenaux",
    "wof:placetype":"venue"
},
  "geometry": {"coordinates":[-72.608315,46.3577],"type":"Point"}
}