{
  "type": "Feature",
  "properties": {
    "addr:full":"185 Rue Du Roi Asbestos QC J1T 1S4",
    "addr:housenumber":"185",
    "addr:postcode":"j1t 1s4",
    "addr:street":"Rue Du Roi",
    "iso:country":"CA",
    "sg:address":"185 Rue Du Roi",
    "sg:city":"Asbestos",
    "sg:classifiers":[
        {
            "category":"Government",
            "subcategory":"Office",
            "type":"Public Place"
        }
    ],
    "sg:phone":"+1 819 879 7171",
    "sg:postcode":"J1T 1S4",
    "sg:province":"QC",
    "sg:tags":[
        "village"
    ],
    "wof:name":"Asbestos Hotel DE Ville",
    "wof:placetype":"venue"
},
  "geometry": {"coordinates":[-71.9368438721,45.7758560181],"type":"Point"}
}