{
  "type": "Feature",
  "properties": {
    "addr:full":"2960 Walton Ave Coquitlam BC V3B 6V6",
    "addr:housenumber":"2960",
    "addr:postcode":"v3b 6v6",
    "addr:street":"Walton Ave",
    "iso:country":"CA",
    "sg:address":"2960 Walton Ave",
    "sg:city":"Coquitlam",
    "sg:classifiers":[
        {
            "category":"Education",
            "subcategory":"School",
            "type":"Public Place"
        }
    ],
    "sg:phone":"+1 604 941 1962",
    "sg:postcode":"V3B 6V6",
    "sg:province":"BC",
    "wof:name":"Walton Elementary School",
    "wof:placetype":"venue"
},
  "geometry": {"coordinates":[-122.79669199999999,49.289768],"type":"Point"}
}