{
  "type": "Feature",
  "properties": {
    "addr:full":"3607 Wolfedale Rd Mississauga ON L5C 1V8",
    "addr:housenumber":"3607",
    "addr:postcode":"l5c 1v8",
    "addr:street":"Wolfedale Rd",
    "iso:country":"CA",
    "sg:address":"3607 Wolfedale Rd",
    "sg:city":"Mississauga",
    "sg:classifiers":[
        {
            "category":"Manufacturing",
            "subcategory":"Glass & Minerals",
            "type":"Manufacturing & Wholesale Goods"
        }
    ],
    "sg:phone":"+1 905 270 0096",
    "sg:postcode":"L5C 1V8",
    "sg:province":"ON",
    "sg:tags":[
        "geophysical",
        "scientific",
        "apparatus"
    ],
    "wof:name":"Crone Geophysics & Exploration",
    "wof:placetype":"venue"
},
  "geometry": {"coordinates":[-79.653053,43.574932],"type":"Point"}
}