{
  "type": "Feature",
  "properties": {
    "addr:full":"15 Beaver Lane Limoges ON K0A 2M0",
    "addr:housenumber":"15",
    "addr:postcode":"k0a 2m0",
    "addr:street":"Beaver Lane",
    "iso:country":"CA",
    "sg:address":"15 Beaver Lane",
    "sg:city":"Limoges",
    "sg:classifiers":[
        {
            "category":"Shopping",
            "subcategory":"Computers & Home Electronics",
            "type":"Retail Goods"
        }
    ],
    "sg:phone":"+1 613 443 3196",
    "sg:postcode":"K0A 2M0",
    "sg:province":"ON",
    "sg:tags":[
        "equipment",
        "satellite",
        "system"
    ],
    "wof:name":"R & R Satellite Antennas",
    "wof:placetype":"venue"
},
  "geometry": {"coordinates":[-75.252808,45.360455],"type":"Point"}
}