{
  "type": "Feature",
  "properties": {
    "addr:full":"Quebec QC G2C 1S9",
    "addr:postcode":"qc g2c 1s9",
    "iso:country":"CA",
    "sg:city":"Quebec",
    "sg:classifiers":[
        {
            "category":"Shopping",
            "subcategory":"Computers & Home Electronics",
            "type":"Retail Goods"
        }
    ],
    "sg:phone":"+1 418 843 6603",
    "sg:postcode":"G2C 1S9",
    "sg:province":"QC",
    "sg:tags":[
        "equipment",
        "school",
        "dealer"
    ],
    "wof:name":"Services Informatiques M Roy",
    "wof:placetype":"venue"
},
  "geometry": {"coordinates":[-71.3137588501,46.8208885193],"type":"Point"}
}