{
  "type": "Feature",
  "properties": {
    "addr:full":"Huntingdon QC J0S 1H0",
    "addr:postcode":"j0s 1h0",
    "iso:country":"CA",
    "sg:city":"Huntingdon",
    "sg:classifiers":[
        {
            "category":"Bars & Pubs",
            "type":"Food & Drink"
        }
    ],
    "sg:phone":"+1 450 264 6455",
    "sg:postcode":"J0S 1H0",
    "sg:province":"QC",
    "sg:tags":[
        "lounge",
        "cocktail"
    ],
    "wof:name":"Bam-Bou Bar",
    "wof:placetype":"venue"
},
  "geometry": {"coordinates":[-74.172173,45.089306],"type":"Point"}
}