{
  "type": "Feature",
  "properties": {
    "iso:country":"CA",
    "sg:address":"843 Seymour St",
    "sg:city":"Kamloops",
    "sg:classifiers":[
        {
            "category":"Health Services",
            "subcategory":"Doctor",
            "type":"Services"
        }
    ],
    "sg:phone":"+1 250 374 3012",
    "sg:postcode":"V2C 2H6",
    "sg:province":"BC",
    "sg:tags":[
        "physician",
        "surgeon"
    ],
    "wof:name":"Mohamed, S N MD",
    "wof:placetype":"venue"
},
  "geometry": {"coordinates":[-120.32036590600001,50.6747703552],"type":"Point"}
}