{
  "type": "Feature",
  "properties": {
    "addr:full":"51 Grafton St Charlottetown PE C1A 1K8",
    "addr:housenumber":"51",
    "addr:postcode":"c1a 1k8",
    "addr:street":"Grafton St",
    "iso:country":"CA",
    "sg:address":"51 Grafton St",
    "sg:city":"Charlottetown",
    "sg:classifiers":[
        {
            "category":"Restaurant",
            "type":"Food & Drink"
        }
    ],
    "sg:phone":"+1 902 892 0609",
    "sg:postcode":"C1A 1K8",
    "sg:province":"PE",
    "wof:name":"Golden Wok Restaurant",
    "wof:placetype":"venue"
},
  "geometry": {"coordinates":[-63.129581,46.233685],"type":"Point"}
}