{
  "type": "Feature",
  "properties": {
    "iso:country":"CA",
    "sg:city":"St Francois Xavier",
    "sg:classifiers":[
        {
            "category":"Food & Beverages",
            "subcategory":"Groceries & Convenience Stores",
            "type":"Retail Goods"
        }
    ],
    "sg:phone":"+1 204 864 2428",
    "sg:postcode":"R4L 1A4",
    "sg:province":"MB",
    "sg:tags":[
        "grocer"
    ],
    "wof:name":"St Francois Xavier Country Str",
    "wof:placetype":"venue"
},
  "geometry": {"coordinates":[-97.5473251343,49.9155578613],"type":"Point"}
}