{
  "type": "Feature",
  "properties": {
    "addr:full":"63 Place Bourget S Joliette QC J6E 5E9",
    "addr:housenumber":"63",
    "addr:postcode":"j6e 5e9",
    "addr:street":"Place Bourget S",
    "iso:country":"CA",
    "sg:address":"63 Place Bourget S",
    "sg:city":"Joliette",
    "sg:classifiers":[
        {
            "category":"Shopping",
            "subcategory":"Clothing, Apparel, & Fashions",
            "type":"Retail Goods"
        }
    ],
    "sg:phone":"+1 450 756 6132",
    "sg:postcode":"J6E 5E9",
    "sg:province":"QC",
    "sg:tags":[
        "furnishing"
    ],
    "wof:name":"Boulard LA Mercerie Inc",
    "wof:placetype":"venue"
},
  "geometry": {"coordinates":[-73.439987,46.024006],"type":"Point"}
}