{
  "type": "Feature",
  "properties": {
    "iso:country":"CA",
    "sg:address":"1071 Midland Ave",
    "sg:city":"Scarborough",
    "sg:classifiers":[
        {
            "category":"Education",
            "subcategory":"Special Training",
            "type":"Public Place"
        }
    ],
    "sg:phone":"+1 416 285 4990",
    "sg:postcode":"M1K 4G7",
    "sg:province":"ON",
    "sg:tags":[
        "instruction",
        "music"
    ],
    "wof:name":"Music Trends",
    "wof:placetype":"venue"
},
  "geometry": {"coordinates":[-79.26108551030001,43.7421340942],"type":"Point"}
}