{
  "type": "Feature",
  "properties": {
    "addr:full":"436 Bryne Dr Barrie ON L4N 9R1",
    "addr:housenumber":"436",
    "addr:postcode":"l4n 9r1",
    "addr:street":"Bryne Dr",
    "iso:country":"CA",
    "sg:address":"436 Bryne Dr",
    "sg:city":"Barrie",
    "sg:classifiers":[
        {
            "category":"Shopping",
            "subcategory":"Department Store",
            "type":"Retail Goods"
        }
    ],
    "sg:phone":"+1 705 734 0793",
    "sg:postcode":"L4N 9R1",
    "sg:province":"ON",
    "wof:name":"Bay Home Outfitters",
    "wof:placetype":"venue"
},
  "geometry": {"coordinates":[-79.6906204224,44.3351516724],"type":"Point"}
}