{
  "type": "Feature",
  "properties": {
    "iso:country":"CA",
    "sg:address":"4333 Bath Rd",
    "sg:city":"Kingston",
    "sg:classifiers":[
        {
            "category":"Organizations",
            "subcategory":"Religious Organization",
            "type":"Services"
        }
    ],
    "sg:phone":"+1 613 384 1782",
    "sg:postcode":"K7M 4Z1",
    "sg:province":"ON",
    "sg:tags":[
        "church"
    ],
    "wof:name":"St Peters Anglican Church",
    "wof:placetype":"venue"
},
  "geometry": {"coordinates":[-76.6280593872,44.2273292542],"type":"Point"}
}