{
  "type": "Feature",
  "properties": {
    "iso:country":"CA",
    "sg:address":"1315 Avenue S",
    "sg:city":"Ottawa",
    "sg:classifiers":[
        {
            "category":"Building & Trades",
            "subcategory":"Landscaping Services",
            "type":"Services"
        }
    ],
    "sg:phone":"+1 613 749 9481",
    "sg:postcode":"K1G 0C4",
    "sg:province":"ON",
    "sg:tags":[
        "landscape",
        "contractor"
    ],
    "wof:name":"Construction V Provost Inc",
    "wof:placetype":"venue"
},
  "geometry": {"coordinates":[-75.64134979249999,45.4186019897],"type":"Point"}
}