{
  "type": "Feature",
  "properties": {
    "addr:full":"250 Metivier Saint-Damien-DE-Buckland QC G0R 2Y0",
    "addr:housenumber":"250",
    "addr:postcode":"g0r 2y0",
    "addr:street":"Metivier",
    "iso:country":"CA",
    "sg:address":"250 Metivier",
    "sg:city":"Saint-Damien-DE-Buckland",
    "sg:classifiers":[
        {
            "category":"Government",
            "subcategory":"Office",
            "type":"Public Place"
        }
    ],
    "sg:phone":"+1 418 789 3104",
    "sg:postcode":"G0R 2Y0",
    "sg:province":"QC",
    "sg:tags":[
        "village"
    ],
    "wof:name":"St-Damien Garage",
    "wof:placetype":"venue"
},
  "geometry": {"coordinates":[-70.651008606,46.6264152527],"type":"Point"}
}