{
  "type": "Feature",
  "properties": {
    "addr:full":"Saint-Ephrem-DE-Beauce QC G0M 1R0",
    "addr:postcode":"g0m 1r0",
    "iso:country":"CA",
    "sg:city":"Saint-Ephrem-DE-Beauce",
    "sg:classifiers":[
        {
            "category":"Manufacturing",
            "subcategory":"Glass & Minerals",
            "type":"Manufacturing & Wholesale Goods"
        }
    ],
    "sg:phone":"+1 418 484 2055",
    "sg:postcode":"G0M 1R0",
    "sg:province":"QC",
    "sg:tags":[
        "concrete",
        "brick",
        "block"
    ],
    "wof:name":"Beton St-Ephrem Inc",
    "wof:placetype":"venue"
},
  "geometry": {"coordinates":[-70.953171,46.069275],"type":"Point"}
}