{
  "type": "Feature",
  "properties": {
    "addr:full":"838 St Mary's Rd Winnipeg MB R2M 3P4",
    "addr:housenumber":"838",
    "addr:postcode":"r2m 3p4",
    "addr:street":"St Mary'S Rd",
    "iso:country":"CA",
    "sg:address":"838 St Mary's Rd",
    "sg:city":"Winnipeg",
    "sg:classifiers":[
        {
            "category":"Manufacturing",
            "subcategory":"Tools & Machinery",
            "type":"Manufacturing & Wholesale Goods"
        }
    ],
    "sg:phone":"+1 204 253 5662",
    "sg:postcode":"R2M 3P4",
    "sg:province":"MB",
    "sg:tags":[
        "refrigerator",
        "freezer"
    ],
    "wof:name":"Northland Appliance Svc",
    "wof:placetype":"venue"
},
  "geometry": {"coordinates":[-97.11274,49.848713],"type":"Point"}
}