{
  "type": "Feature",
  "properties": {
    "addr:full":"RR 1 Thedford ON N0M 2N0",
    "addr:postcode":"n0m 2n0",
    "addr:street":"Rr 1",
    "iso:country":"CA",
    "sg:address":"RR 1",
    "sg:city":"Thedford",
    "sg:classifiers":[
        {
            "category":"Real Estate",
            "subcategory":"Real Estate Operator",
            "type":"Services"
        }
    ],
    "sg:phone":"+1 519 243 2920",
    "sg:postcode":"N0M 2N0",
    "sg:province":"ON",
    "sg:tags":[
        "mobile",
        "home",
        "community"
    ],
    "wof:name":"Pinehurst Trailer Park",
    "wof:placetype":"venue"
},
  "geometry": {"coordinates":[-81.8551483154,43.1639633179],"type":"Point"}
}