{
  "type": "Feature",
  "properties": {
    "addr:full":"1745 Victoria St Prince George BC V2L 2L6",
    "addr:housenumber":"1745",
    "addr:postcode":"v2l 2l6",
    "addr:street":"Victoria St",
    "iso:country":"CA",
    "sg:address":"1745 Victoria St",
    "sg:city":"Prince George",
    "sg:classifiers":[
        {
            "category":"Retail",
            "subcategory":"Auto Rental",
            "type":"Services"
        }
    ],
    "sg:phone":"+1 250 564 6378",
    "sg:postcode":"V2L 2L6",
    "sg:province":"BC",
    "sg:tags":[
        "renting",
        "automobile",
        "leasing"
    ],
    "wof:name":"Key Lease Ltd",
    "wof:placetype":"venue"
},
  "geometry": {"coordinates":[-122.755432129,53.9079551697],"type":"Point"}
}