{
  "type": "Feature",
  "properties": {
    "iso:country":"CA",
    "sg:address":"1 Water St",
    "sg:city":"Pictou",
    "sg:classifiers":[
        {
            "category":"Personal",
            "subcategory":"Beauty Salon",
            "type":"Services"
        }
    ],
    "sg:phone":"+1 902 485 8588",
    "sg:postcode":"B0K 1H0",
    "sg:province":"NS",
    "wof:name":"Ahead of Hair",
    "wof:placetype":"venue"
},
  "geometry": {"coordinates":[-62.709587,45.676071],"type":"Point"}
}