{
  "type": "Feature",
  "properties": {
    "addr:full":"1198 Bloor St W Toronto ON M6H 1N2",
    "addr:housenumber":"1198",
    "addr:postcode":"m6h 1n2",
    "addr:street":"Bloor St W",
    "iso:country":"CA",
    "sg:address":"1198 Bloor St W",
    "sg:city":"Toronto",
    "sg:classifiers":[
        {
            "category":"Health Services",
            "subcategory":"Doctor",
            "type":"Services"
        }
    ],
    "sg:phone":"+1 416 536 8523",
    "sg:postcode":"M6H 1N2",
    "sg:province":"ON",
    "sg:tags":[
        "dentist"
    ],
    "wof:name":"Nguyen, Tang Tri DDS",
    "wof:placetype":"venue"
},
  "geometry": {"coordinates":[-79.4382019043,43.6594238281],"type":"Point"}
}