{
  "type": "Feature",
  "properties": {
    "addr:full":"30 Ste. Anne Rd Sudbury ON P3C 5E1",
    "addr:housenumber":"30",
    "addr:postcode":"p3c 5e1",
    "addr:street":"Ste. Anne Rd",
    "iso:country":"CA",
    "sg:address":"30 Ste. Anne Rd",
    "sg:city":"Sudbury",
    "sg:classifiers":[
        {
            "category":"Shopping",
            "subcategory":"Books",
            "type":"Retail Goods"
        }
    ],
    "sg:phone":"+1 705 674 2777",
    "sg:postcode":"P3C 5E1",
    "sg:province":"ON",
    "sg:tags":[
        "dealer"
    ],
    "wof:name":"Librairie Emmanuel Bookstore",
    "wof:placetype":"venue"
},
  "geometry": {"coordinates":[-80.996056,46.495228],"type":"Point"}
}