{
  "type": "Feature",
  "properties": {
    "addr:full":"5520 Rue Laurendeau Montreal QC H4E 3W1",
    "addr:housenumber":"5520",
    "addr:postcode":"h4e 3w1",
    "addr:street":"Rue Laurendeau",
    "iso:country":"CA",
    "sg:address":"5520 Rue Laurendeau",
    "sg:city":"Montreal",
    "sg:classifiers":[
        {
            "category":"Personal",
            "subcategory":"Beauty Salon",
            "type":"Services"
        }
    ],
    "sg:phone":"+1 514 768 9188",
    "sg:postcode":"H4E 3W1",
    "sg:province":"QC",
    "wof:name":"Pierre Richard Coiffure",
    "wof:placetype":"venue"
},
  "geometry": {"coordinates":[-73.5877075195,45.4631004333],"type":"Point"}
}