{
  "type": "Feature",
  "properties": {
    "addr:full":"Victoria BC V8X 1G8",
    "addr:postcode":"v8x 1g8",
    "iso:country":"CA",
    "sg:city":"Victoria",
    "sg:classifiers":[
        {
            "category":"Shopping",
            "subcategory":"Used Merchandise",
            "type":"Retail Goods"
        }
    ],
    "sg:phone":"+1 250 480 4006",
    "sg:postcode":"V8X 1G8",
    "sg:province":"BC",
    "sg:tags":[
        "shop",
        "second",
        "hand",
        "store",
        "thrift"
    ],
    "wof:name":"Win Thrift Store",
    "wof:placetype":"venue"
},
  "geometry": {"coordinates":[-123.36200714100001,48.448890686],"type":"Point"}
}