{
  "type": "Feature",
  "properties": {
    "addr:full":"Mississauga ON L4W 4K4",
    "addr:postcode":"l4w 4k4",
    "iso:country":"CA",
    "sg:city":"Mississauga",
    "sg:classifiers":[
        {
            "category":"Manufacturing",
            "subcategory":"Tools & Machinery",
            "type":"Manufacturing & Wholesale Goods"
        }
    ],
    "sg:phone":"+1 905 629 1017",
    "sg:postcode":"L4W 4K4",
    "sg:province":"ON",
    "sg:tags":[
        "machine",
        "shop"
    ],
    "wof:name":"Borik Tool & Die CO Ltd",
    "wof:placetype":"venue"
},
  "geometry": {"coordinates":[-79.611588,43.639118],"type":"Point"}
}