{
  "type": "Feature",
  "properties": {
    "iso:country":"CA",
    "sg:address":"366 Talbot St",
    "sg:city":"London",
    "sg:classifiers":[
        {
            "category":"Personal",
            "subcategory":"Beauty Salon",
            "type":"Services"
        }
    ],
    "sg:phone":"+1 519 667 1971",
    "sg:postcode":"N6A 2R6",
    "sg:province":"ON",
    "wof:name":"Bombay Hair",
    "wof:placetype":"venue"
},
  "geometry": {"coordinates":[-81.25090026860001,42.9816436768],"type":"Point"}
}