{
  "type": "Feature",
  "properties": {
    "addr:full":"Bolton ON L7E 1H1",
    "addr:postcode":"l7e 1h1",
    "iso:country":"CA",
    "sg:city":"Bolton",
    "sg:classifiers":[
        {
            "category":"Insurance",
            "subcategory":"Insurance Agent",
            "type":"Services"
        }
    ],
    "sg:phone":"+1 905 857 6915",
    "sg:postcode":"L7E 1H1",
    "sg:province":"ON",
    "wof:name":"Mc Creary & Assoc",
    "wof:placetype":"venue"
},
  "geometry": {"coordinates":[-79.712509,43.862061],"type":"Point"}
}