{
  "type": "Feature",
  "properties": {
    "addr:full":"Saint-Vital-DE-Clermont QC J0Z 3M0",
    "addr:postcode":"j0z 3m0",
    "iso:country":"CA",
    "sg:city":"Saint-Vital-DE-Clermont",
    "sg:classifiers":[
        {
            "category":"Government",
            "subcategory":"Office",
            "type":"Public Place"
        }
    ],
    "sg:phone":"+1 819 333 6129",
    "sg:postcode":"J0Z 3M0",
    "sg:province":"QC",
    "sg:tags":[
        "municipality"
    ],
    "wof:name":"Clermont Canton Municipale",
    "wof:placetype":"venue"
},
  "geometry": {"coordinates":[-79.18621826170001,48.9323768616],"type":"Point"}
}