{
  "type": "Feature",
  "properties": {
    "addr:full":"Richmond BC V6V 2K3",
    "addr:postcode":"v6v 2k3",
    "iso:country":"CA",
    "sg:city":"Richmond",
    "sg:classifiers":[
        {
            "category":"Wholesale",
            "subcategory":"Durable Goods & Equipment",
            "type":"Manufacturing & Wholesale Goods"
        }
    ],
    "sg:phone":"+1 604 304 0105",
    "sg:postcode":"V6V 2K3",
    "sg:province":"BC",
    "sg:tags":[
        "importer"
    ],
    "wof:name":"Eagle Products CO Ltd",
    "wof:placetype":"venue"
},
  "geometry": {"coordinates":[-123.069984436,49.1846122742],"type":"Point"}
}