{
  "type": "Feature",
  "properties": {
    "addr:full":"610 Connaught Dr Jasper AB T0E 1E0",
    "addr:housenumber":"610",
    "addr:postcode":"t0e 1e0",
    "addr:street":"Connaught Dr",
    "iso:country":"CA",
    "sg:address":"610 Connaught Dr",
    "sg:city":"Jasper",
    "sg:classifiers":[
        {
            "category":"Government",
            "subcategory":"Office",
            "type":"Public Place"
        }
    ],
    "sg:phone":"+1 780 852 3185",
    "sg:postcode":"T0E 1E0",
    "sg:province":"AB",
    "wof:name":"Canada Environment",
    "wof:placetype":"venue"
},
  "geometry": {"coordinates":[-118.082649,52.87365],"type":"Point"}
}