{
  "type": "Feature",
  "properties": {
    "iso:country":"CA",
    "sg:address":"75 Neville St",
    "sg:city":"Moncton",
    "sg:classifiers":[
        {
            "category":"Shopping",
            "subcategory":"Stationery & Office Supplies",
            "type":"Retail Goods"
        }
    ],
    "sg:phone":"+1 506 854 2226",
    "sg:postcode":"E1A 6K9",
    "sg:province":"NB",
    "sg:tags":[
        "rubber",
        "stamp",
        "printer",
        "plastic"
    ],
    "wof:name":"Barn's Rubber Stamps",
    "wof:placetype":"venue"
},
  "geometry": {"coordinates":[-64.7537231445,46.1141242981],"type":"Point"}
}