{
  "type": "Feature",
  "properties": {
    "addr:full":"17740 62 Ave Surrey BC V3S 1W7",
    "addr:housenumber":"17740",
    "addr:postcode":"v3s 1w7",
    "addr:street":"62 Ave",
    "iso:country":"CA",
    "sg:address":"17740 62 Ave",
    "sg:city":"Surrey",
    "sg:classifiers":[
        {
            "category":"Shopping",
            "subcategory":"Bicycles & Sporting Goods",
            "type":"Retail Goods"
        }
    ],
    "sg:phone":"+1 604 576 2269",
    "sg:postcode":"V3S 1W7",
    "sg:province":"BC",
    "sg:tags":[
        "saddlery",
        "harness"
    ],
    "wof:name":"Track Tack Harness & Equipment",
    "wof:placetype":"venue"
},
  "geometry": {"coordinates":[-122.765381,49.114738],"type":"Point"}
}