{
  "type": "Feature",
  "properties": {
    "addr:full":"78 Bond St W Oshawa ON L1G 1A5",
    "addr:housenumber":"78",
    "addr:postcode":"l1g 1a5",
    "addr:street":"Bond St W",
    "iso:country":"CA",
    "sg:address":"78 Bond St W",
    "sg:city":"Oshawa",
    "sg:classifiers":[
        {
            "category":"Retail",
            "subcategory":"Auto Rental",
            "type":"Services"
        }
    ],
    "sg:phone":"+1 905 576 2672",
    "sg:postcode":"L1G 1A5",
    "sg:province":"ON",
    "sg:tags":[
        "renting",
        "automobile"
    ],
    "wof:name":"Budget Car & Truck Rental",
    "wof:placetype":"venue"
},
  "geometry": {"coordinates":[-78.867149353,43.8978767395],"type":"Point"}
}