{
  "type": "Feature",
  "properties": {
    "addr:full":"439 Rg St-Pascal Les Eboulements QC G0A 2M0",
    "addr:housenumber":"439",
    "addr:postcode":"g0a 2m0",
    "iso:country":"CA",
    "sg:address":"439 Rg St-Pascal",
    "sg:city":"Les Eboulements",
    "sg:classifiers":[
        {
            "category":"Farming",
            "subcategory":"Farm",
            "type":"Manufacturing & Wholesale Goods"
        }
    ],
    "sg:phone":"+1 418 635 2223",
    "sg:postcode":"G0A 2M0",
    "sg:province":"QC",
    "wof:name":"Azp Inc",
    "wof:placetype":"venue"
},
  "geometry": {"coordinates":[-70.2925109863,47.4859466553],"type":"Point"}
}