{
  "type": "Feature",
  "properties": {
    "addr:full":"1372 Rue DE Saint-Julien Saint-Emile QC G3E 1V3",
    "addr:housenumber":"1372",
    "addr:postcode":"g3e 1v3",
    "addr:street":"Rue De Saint-Julien Saint-Emile",
    "iso:country":"CA",
    "sg:address":"1372 Rue DE Saint-Julien",
    "sg:city":"Saint-Emile",
    "sg:classifiers":[
        {
            "category":"Professional",
            "subcategory":"Detective & Security Services",
            "type":"Services"
        }
    ],
    "sg:phone":"+1 418 845 6026",
    "sg:postcode":"G3E 1V3",
    "sg:province":"QC",
    "sg:tags":[
        "burglary",
        "protective",
        "robbery"
    ],
    "wof:name":"Securite Alarme Videophone",
    "wof:placetype":"venue"
},
  "geometry": {"coordinates":[-71.31929,46.873009],"type":"Point"}
}