{
  "type": "Feature",
  "properties": {
    "addr:full":"736 Mcdougall Crt NE Calgary AB T2E 2W6",
    "addr:housenumber":"736",
    "addr:postcode":"t2e 2w6",
    "addr:street":"Mcdougall Crt Ne",
    "iso:country":"CA",
    "sg:address":"736 Mcdougall Crt NE",
    "sg:city":"Calgary",
    "sg:classifiers":[
        {
            "category":"Social Services",
            "subcategory":"Child Care",
            "type":"Services"
        }
    ],
    "sg:phone":"+1 403 261 7650",
    "sg:postcode":"T2E 2W6",
    "sg:province":"AB",
    "wof:name":"Bridgland Day Care Program",
    "wof:placetype":"venue"
},
  "geometry": {"coordinates":[-114.046318,51.050854],"type":"Point"}
}