{
  "type": "Feature",
  "properties": {
    "addr:full":"9085 King George Hwy Surrey BC V3V 5V7",
    "addr:housenumber":"9085",
    "addr:postcode":"v3v 5v7",
    "addr:street":"King George Hwy",
    "iso:country":"CA",
    "sg:address":"9085 King George Hwy",
    "sg:city":"Surrey",
    "sg:classifiers":[
        {
            "category":"Retail",
            "subcategory":"Auto Rental",
            "type":"Services"
        }
    ],
    "sg:phone":"+1 604 501 0848",
    "sg:postcode":"V3V 5V7",
    "sg:province":"BC",
    "sg:tags":[
        "renting",
        "truck",
        "leasing"
    ],
    "wof:name":"U-Haul CO Ltd",
    "wof:placetype":"venue"
},
  "geometry": {"coordinates":[-122.846046448,49.167049408],"type":"Point"}
}