{
  "type": "Feature",
  "properties": {
    "addr:full":"15 Main St St George NB E5C 3H9",
    "addr:housenumber":"15",
    "addr:postcode":"e5c 3h9",
    "addr:street":"Main St",
    "iso:country":"CA",
    "sg:address":"15 Main St",
    "sg:city":"St George",
    "sg:classifiers":[
        {
            "category":"Insurance",
            "subcategory":"Insurance Agent",
            "type":"Services"
        }
    ],
    "sg:phone":"+1 506 755 3381",
    "sg:postcode":"E5C 3H9",
    "sg:province":"NB",
    "wof:name":"Groom Insurance Ltd",
    "wof:placetype":"venue"
},
  "geometry": {"coordinates":[-66.8240737915,45.130065918],"type":"Point"}
}