{
  "type": "Feature",
  "properties": {
    "addr:full":"703 Mill Ave Enderby BC V0E 1V0",
    "addr:housenumber":"703",
    "addr:postcode":"v0e 1v0",
    "addr:street":"Mill Ave",
    "iso:country":"CA",
    "sg:address":"703 Mill Ave",
    "sg:city":"Enderby",
    "sg:classifiers":[
        {
            "category":"Banks & Credit Unions",
            "subcategory":"Bank",
            "type":"Services"
        }
    ],
    "sg:phone":"+1 250 838 6841",
    "sg:postcode":"V0E 1V0",
    "sg:province":"BC",
    "wof:name":"Enderby & District Credit Un",
    "wof:placetype":"venue"
},
  "geometry": {"coordinates":[-119.1404953,50.5512466431],"type":"Point"}
}