{
  "type": "Feature",
  "properties": {
    "addr:full":"280 Plains Rd W Burlington ON L7T 1G4",
    "addr:housenumber":"280",
    "addr:postcode":"l7t 1g4",
    "addr:street":"Plains Rd W",
    "iso:country":"CA",
    "sg:address":"280 Plains Rd W",
    "sg:city":"Burlington",
    "sg:classifiers":[
        {
            "category":"Social Services",
            "type":"Services"
        }
    ],
    "sg:phone":"+1 905 527 8881",
    "sg:postcode":"L7T 1G4",
    "sg:province":"ON",
    "sg:tags":[
        "counselor",
        "marriage",
        "family"
    ],
    "wof:name":"Smith, J Martin PhD",
    "wof:placetype":"venue"
},
  "geometry": {"coordinates":[-79.86206799999999,43.29937],"type":"Point"}
}