{
  "type": "Feature",
  "properties": {
    "addr:full":"2919 Richmond Rd SW Calgary AB T3E 4N3",
    "addr:housenumber":"2919",
    "addr:postcode":"t3e 4n3",
    "addr:street":"Richmond Rd Sw",
    "iso:country":"CA",
    "sg:address":"2919 Richmond Rd SW",
    "sg:city":"Calgary",
    "sg:classifiers":[
        {
            "category":"Food & Beverages",
            "subcategory":"Liquor & Beverages",
            "type":"Retail Goods"
        }
    ],
    "sg:phone":"+1 403 686 4576",
    "sg:postcode":"T3E 4N3",
    "sg:province":"AB",
    "sg:tags":[
        "store"
    ],
    "wof:name":"Mann's Liquor Store No 2",
    "wof:placetype":"venue"
},
  "geometry": {"coordinates":[-114.128356934,51.0261573792],"type":"Point"}
}