{
  "type": "Feature",
  "properties": {
    "addr:full":"340 Rue Principale Granby QC J2G 2W4",
    "addr:housenumber":"340",
    "addr:postcode":"j2g 2w4",
    "addr:street":"Rue Principale",
    "iso:country":"CA",
    "sg:address":"340 Rue Principale",
    "sg:city":"Granby",
    "sg:classifiers":[
        {
            "category":"Home & Garden",
            "subcategory":"Household Appliances",
            "type":"Retail Goods"
        }
    ],
    "sg:phone":"+1 450 372 5427",
    "sg:postcode":"J2G 2W4",
    "sg:province":"QC",
    "sg:tags":[
        "cleaners",
        "vacuum"
    ],
    "wof:name":"Electrolux Canada",
    "wof:placetype":"venue"
},
  "geometry": {"coordinates":[-72.731689,45.401962],"type":"Point"}
}