{
  "type": "Feature",
  "properties": {
    "iso:country":"CA",
    "sg:address":"1744 Huron Church Rd",
    "sg:city":"Windsor",
    "sg:classifiers":[
        {
            "category":"Health Services",
            "subcategory":"Chiropractor",
            "type":"Services"
        }
    ],
    "sg:phone":"+1 519 258 8544",
    "sg:postcode":"N9C 2L4",
    "sg:province":"ON",
    "wof:name":"Huron Church Chiropractic Ctr",
    "wof:placetype":"venue"
},
  "geometry": {"coordinates":[-83.0559005737,42.2843399048],"type":"Point"}
}