{
  "type": "Feature",
  "properties": {
    "addr:full":"1771 Rue Principale E Farnham QC J2N 1N5",
    "addr:housenumber":"1771",
    "addr:postcode":"j2n 1n5",
    "addr:street":"Rue Principale E",
    "iso:country":"CA",
    "sg:address":"1771 Rue Principale E",
    "sg:city":"Farnham",
    "sg:classifiers":[
        {
            "category":"Building & Trades",
            "subcategory":"Electrical",
            "type":"Services"
        }
    ],
    "sg:phone":"+1 450 293 2268",
    "sg:postcode":"J2N 1N5",
    "sg:province":"QC",
    "sg:tags":[
        "electric",
        "contractor"
    ],
    "wof:name":"Seney Electrique Inc",
    "wof:placetype":"venue"
},
  "geometry": {"coordinates":[-72.95658874510001,45.2734642029],"type":"Point"}
}