{
  "type": "Feature",
  "properties": {
    "addr:full":"358 Rue Lafontaine Riviere-Du-Loup QC G5R 3B3",
    "addr:housenumber":"358",
    "addr:postcode":"g5r 3b3",
    "addr:street":"Rue Lafontaine",
    "iso:country":"CA",
    "sg:address":"358 Rue Lafontaine",
    "sg:city":"Riviere-Du-Loup",
    "sg:classifiers":[
        {
            "category":"Shopping",
            "subcategory":"Musical Instruments",
            "type":"Retail Goods"
        }
    ],
    "sg:phone":"+1 418 862 1596",
    "sg:postcode":"G5R 3B3",
    "sg:province":"QC",
    "wof:name":"Sonotheque Inc",
    "wof:placetype":"venue"
},
  "geometry": {"coordinates":[-69.5362625122,47.8312721252],"type":"Point"}
}