{
  "type": "Feature",
  "properties": {
    "addr:full":"50 Spruce Ave Espanola ON P5E 1A1",
    "addr:housenumber":"50",
    "addr:postcode":"p5e 1a1",
    "addr:street":"Spruce Ave",
    "iso:country":"CA",
    "sg:address":"50 Spruce Ave",
    "sg:city":"Espanola",
    "sg:classifiers":[
        {
            "category":"Professional",
            "subcategory":"Accounting & Tax Preparation",
            "type":"Services"
        }
    ],
    "sg:phone":"+1 705 869 1415",
    "sg:postcode":"P5E 1A1",
    "sg:province":"ON",
    "sg:tags":[
        "bookkeeping",
        "general"
    ],
    "wof:name":"Master Services",
    "wof:placetype":"venue"
},
  "geometry": {"coordinates":[-81.772293,46.265015],"type":"Point"}
}