{
  "type": "Feature",
  "properties": {
    "addr:full":"321 Queenston Rd Hamilton ON L8K 1H3",
    "addr:housenumber":"321",
    "addr:postcode":"l8k 1h3",
    "addr:street":"Queenston Rd",
    "iso:country":"CA",
    "sg:address":"321 Queenston Rd",
    "sg:city":"Hamilton",
    "sg:classifiers":[
        {
            "category":"Health Services",
            "subcategory":"Doctor",
            "type":"Services"
        }
    ],
    "sg:phone":"+1 905 547 0324",
    "sg:postcode":"L8K 1H3",
    "sg:province":"ON",
    "sg:tags":[
        "dentist"
    ],
    "wof:name":"Mlekuz, Nick H DDS",
    "wof:placetype":"venue"
},
  "geometry": {"coordinates":[-79.790108,43.233894],"type":"Point"}
}