{
  "type": "Feature",
  "properties": {
    "addr:full":"1280 Boul Moody Terrebonne QC J6W 3K9",
    "addr:housenumber":"1280",
    "addr:postcode":"j6w 3k9",
    "addr:street":"Boul Moody",
    "iso:country":"CA",
    "sg:address":"1280 Boul Moody",
    "sg:city":"Terrebonne",
    "sg:classifiers":[
        {
            "category":"Personal",
            "subcategory":"Beauty Salon",
            "type":"Services"
        }
    ],
    "sg:phone":"+1 450 964 1709",
    "sg:postcode":"J6W 3K9",
    "sg:province":"QC",
    "wof:name":"Entracte Coiffure Inc",
    "wof:placetype":"venue"
},
  "geometry": {"coordinates":[-73.648796,45.702881],"type":"Point"}
}