{
  "type": "Feature",
  "properties": {
    "iso:country":"CA",
    "sg:address":"2324 Yolanda Dr",
    "sg:city":"Oakville",
    "sg:classifiers":[
        {
            "category":"Manufacturing",
            "subcategory":"Leather Goods",
            "type":"Manufacturing & Wholesale Goods"
        }
    ],
    "sg:phone":"+1 905 847 5541",
    "sg:postcode":"L6L 2H8",
    "sg:province":"ON",
    "sg:tags":[
        "shoes",
        "supply"
    ],
    "wof:name":"Intertrade Canada",
    "wof:placetype":"venue"
},
  "geometry": {"coordinates":[-79.7186126709,43.4040298462],"type":"Point"}
}