{
  "type": "Feature",
  "properties": {
    "addr:full":"439 Boul DE Petit-Cap Gaspe QC G4X 4L1",
    "addr:housenumber":"439",
    "addr:postcode":"g4x 4l1",
    "addr:street":"Boul De Petit-Cap",
    "iso:country":"CA",
    "sg:address":"439 Boul DE Petit-Cap",
    "sg:city":"Gaspe",
    "sg:classifiers":[
        {
            "category":"Education",
            "subcategory":"Library",
            "type":"Public Place"
        }
    ],
    "sg:phone":"+1 418 269 3889",
    "sg:postcode":"G4X 4L1",
    "sg:province":"QC",
    "wof:name":"Biblio Petit-Cap",
    "wof:placetype":"venue"
},
  "geometry": {"coordinates":[-64.437782,49.025894],"type":"Point"}
}