{
  "type": "Feature",
  "properties": {
    "addr:full":"385 Rue Principale Daveluyville QC G0Z 1C0",
    "addr:housenumber":"385",
    "addr:postcode":"g0z 1c0",
    "addr:street":"Rue Principale",
    "iso:country":"CA",
    "sg:address":"385 Rue Principale",
    "sg:city":"Daveluyville",
    "sg:classifiers":[
        {
            "category":"Health Services",
            "subcategory":"Doctor",
            "type":"Services"
        }
    ],
    "sg:phone":"+1 819 367 2714",
    "sg:postcode":"G0Z 1C0",
    "sg:province":"QC",
    "sg:tags":[
        "clinic"
    ],
    "wof:name":"Clinique Medicale Daveluyville",
    "wof:placetype":"venue"
},
  "geometry": {"coordinates":[-72.1376800537,46.2043647766],"type":"Point"}
}