{
  "type": "Feature",
  "properties": {
    "iso:country":"CA",
    "sg:address":"2675 Matthew Rd",
    "sg:city":"Nanoose Bay",
    "sg:classifiers":[
        {
            "category":"Building & Trades",
            "subcategory":"Plumbing",
            "type":"Services"
        }
    ],
    "sg:phone":"+1 250 468 5230",
    "sg:postcode":"V9P 9B2",
    "sg:province":"BC",
    "sg:tags":[
        "contractor"
    ],
    "wof:name":"Cameron Plumbing",
    "wof:placetype":"venue"
},
  "geometry": {"coordinates":[-124.198249817,49.2660598755],"type":"Point"}
}