{
  "type": "Feature",
  "properties": {
    "iso:country":"CA",
    "sg:city":"Calgary",
    "sg:classifiers":[
        {
            "category":"Building & Trades",
            "subcategory":"Construction",
            "type":"Services"
        }
    ],
    "sg:phone":"+1 403 275 2377",
    "sg:postcode":"T2K 5X7",
    "sg:province":"AB",
    "sg:tags":[
        "repairing",
        "remodeling",
        "contractor"
    ],
    "wof:name":"Triune Construction Crdntrs",
    "wof:placetype":"venue"
},
  "geometry": {"coordinates":[-114.044197,51.097355],"type":"Point"}
}