{
  "type": "Feature",
  "properties": {
    "addr:full":"Mississauga ON L5T 1W9",
    "addr:postcode":"l5t 1w9",
    "iso:country":"CA",
    "sg:city":"Mississauga",
    "sg:classifiers":[
        {
            "category":"Retail",
            "subcategory":"Auto Repair",
            "type":"Services"
        }
    ],
    "sg:phone":"+1 905 565 9947",
    "sg:postcode":"L5T 1W9",
    "sg:province":"ON",
    "sg:tags":[
        "repairing",
        "automobile"
    ],
    "wof:name":"Bob Perkins Automotive",
    "wof:placetype":"venue"
},
  "geometry": {"coordinates":[-79.6487579346,43.6605033875],"type":"Point"}
}