{
  "type": "Feature",
  "properties": {
    "iso:country":"CA",
    "sg:address":"109 Boul Perrot",
    "sg:city":"L'Ile-Perrot",
    "sg:classifiers":[
        {
            "category":"Restaurant",
            "type":"Food & Drink"
        }
    ],
    "sg:phone":"+1 514 425 5169",
    "sg:postcode":"J7V 3G3",
    "sg:province":"QC",
    "wof:name":"Restaurant Sheng Wah",
    "wof:placetype":"venue"
},
  "geometry": {"coordinates":[-73.9555511475,45.393913269],"type":"Point"}
}