{
  "type": "Feature",
  "properties": {
    "addr:full":"NE 30 7 4E Niverville MB R0A 1E0",
    "addr:housenumber":"7",
    "addr:postcode":"r0a 1e0",
    "addr:street":"Ne 30",
    "iso:country":"CA",
    "sg:address":"NE 30 7 4E",
    "sg:city":"Niverville",
    "sg:classifiers":[
        {
            "category":"Food & Beverages",
            "subcategory":"Specialty",
            "type":"Retail Goods"
        }
    ],
    "sg:phone":"+1 204 388 4986",
    "sg:postcode":"R0A 1E0",
    "sg:province":"MB",
    "sg:tags":[
        "poultry"
    ],
    "wof:name":"Apex Farms Ltd",
    "wof:placetype":"venue"
},
  "geometry": {"coordinates":[-97.041443,49.605919],"type":"Point"}
}