{
  "type": "Feature",
  "properties": {
    "iso:country":"CA",
    "sg:address":"172 Rue Lafortune",
    "sg:city":"Le Gardeur",
    "sg:classifiers":[
        {
            "category":"Building & Trades",
            "subcategory":"Plumbing",
            "type":"Services"
        }
    ],
    "sg:phone":"+1 450 585 8690",
    "sg:postcode":"J5Z 4Z7",
    "sg:province":"QC",
    "sg:tags":[
        "contractor"
    ],
    "wof:name":"Plomberie Msn",
    "wof:placetype":"venue"
},
  "geometry": {"coordinates":[-73.4559173584,45.7693252563],"type":"Point"}
}