{
  "type": "Feature",
  "properties": {
    "addr:full":"174 Main St Dutton ON N0L 1J0",
    "addr:housenumber":"174",
    "addr:postcode":"n0l 1j0",
    "addr:street":"Main St",
    "iso:country":"CA",
    "sg:address":"174 Main St",
    "sg:city":"Dutton",
    "sg:classifiers":[
        {
            "category":"Shopping",
            "subcategory":"Catalog Store",
            "type":"Retail Goods"
        }
    ],
    "sg:phone":"+1 519 762 3535",
    "sg:postcode":"N0L 1J0",
    "sg:province":"ON",
    "sg:tags":[
        "mail",
        "order",
        "internet"
    ],
    "wof:name":"Sears Canada Inc",
    "wof:placetype":"venue"
},
  "geometry": {"coordinates":[-81.502022,42.662979],"type":"Point"}
}