{
  "type": "Feature",
  "properties": {
    "addr:full":"68 Boul Gerard-D.-Levesque O Paspebiac QC G0C 2K0",
    "addr:housenumber":"68",
    "addr:postcode":"g0c 2k0",
    "addr:street":"Boul Gerard-D.-Levesque O Paspebiac",
    "iso:country":"CA",
    "sg:address":"68 Boul Gerard-D.-Levesque O",
    "sg:city":"Paspebiac",
    "sg:classifiers":[
        {
            "category":"Travel",
            "subcategory":"Hotels & Motels",
            "type":"Entertainment"
        }
    ],
    "sg:phone":"+1 418 752 3355",
    "sg:postcode":"G0C 2K0",
    "sg:province":"QC",
    "wof:name":"Hotel Auberge Du Parc Inn",
    "wof:placetype":"venue"
},
  "geometry": {"coordinates":[-65.241066,48.029797],"type":"Point"}
}