{
  "type": "Feature",
  "properties": {
    "addr:full":"661 Rang Sainte-Marie Saint-Sebastien QC J0J 2C0",
    "addr:housenumber":"661",
    "addr:postcode":"j0j 2c0",
    "addr:street":"Rang Sainte-Marie",
    "iso:country":"CA",
    "sg:address":"661 Rang Sainte-Marie",
    "sg:city":"Saint-Sebastien",
    "sg:classifiers":[
        {
            "category":"Wholesale",
            "subcategory":"Auto Parts",
            "type":"Manufacturing & Wholesale Goods"
        }
    ],
    "sg:phone":"+1 450 244 8817",
    "sg:postcode":"J0J 2C0",
    "sg:province":"QC",
    "sg:tags":[
        "automobile",
        "rebuilt",
        "metal",
        "scrap",
        "iron"
    ],
    "wof:name":"Marcel Duval Fer & Metaux",
    "wof:placetype":"venue"
},
  "geometry": {"coordinates":[-73.108093,45.149193],"type":"Point"}
}