{
  "type": "Feature",
  "properties": {
    "iso:country":"CA",
    "sg:address":"1525 20 Ave S",
    "sg:city":"Lethbridge",
    "sg:classifiers":[
        {
            "category":"Professional",
            "subcategory":"Management & Consulting",
            "type":"Services"
        }
    ],
    "sg:phone":"+1 403 381 6608",
    "sg:postcode":"T1K 1G2",
    "sg:province":"AB",
    "sg:tags":[
        "party",
        "planning"
    ],
    "wof:name":"Astro Jump of Chinook Country",
    "wof:placetype":"venue"
},
  "geometry": {"coordinates":[-112.820762634,49.6723976135],"type":"Point"}
}