{
  "type": "Feature",
  "properties": {
    "addr:full":"London ON N6J 3T9",
    "addr:postcode":"n6j 3t9",
    "iso:country":"CA",
    "sg:city":"London",
    "sg:classifiers":[
        {
            "category":"Real Estate",
            "subcategory":"Real Estate Operator",
            "type":"Services"
        }
    ],
    "sg:phone":"+1 519 471 6110",
    "sg:postcode":"N6J 3T9",
    "sg:province":"ON",
    "sg:tags":[
        "apartment"
    ],
    "wof:name":"Capitol Hill Apartments",
    "wof:placetype":"venue"
},
  "geometry": {"coordinates":[-81.278976,42.957844],"type":"Point"}
}