{
  "type": "Feature",
  "properties": {
    "addr:full":"Nepean ON K2E 7W6",
    "addr:postcode":"k2e 7w6",
    "iso:country":"CA",
    "sg:city":"Nepean",
    "sg:classifiers":[
        {
            "category":"Building & Trades",
            "subcategory":"Construction",
            "type":"Services"
        }
    ],
    "sg:phone":"+1 613 225 7661",
    "sg:postcode":"K2E 7W6",
    "sg:province":"ON",
    "sg:tags":[
        "fiber",
        "optics"
    ],
    "wof:name":"Luminos Industries Ltd",
    "wof:placetype":"venue"
},
  "geometry": {"coordinates":[-75.709328,45.330666],"type":"Point"}
}