{
  "type": "Feature",
  "properties": {
    "addr:full":"4030 Rue Masson Montreal QC H1X 1T8",
    "addr:housenumber":"4030",
    "addr:postcode":"h1x 1t8",
    "addr:street":"Rue Masson",
    "iso:country":"CA",
    "sg:address":"4030 Rue Masson",
    "sg:city":"Montreal",
    "sg:classifiers":[
        {
            "category":"Bars & Pubs",
            "type":"Food & Drink"
        }
    ],
    "sg:phone":"+1 514 725 8409",
    "sg:postcode":"H1X 1T8",
    "sg:province":"QC",
    "sg:tags":[
        "lounge",
        "cocktail"
    ],
    "wof:name":"Cafe Sport Alex",
    "wof:placetype":"venue"
},
  "geometry": {"coordinates":[-73.56861877439999,45.5584869385],"type":"Point"}
}