{
  "type": "Feature",
  "properties": {
    "addr:full":"912 9th Ave E Owen Sound ON N4K 3E7",
    "addr:housenumber":"912",
    "addr:postcode":"n4k 3e7",
    "addr:street":"9Th Ave E",
    "iso:country":"CA",
    "sg:address":"912 9th Ave E",
    "sg:city":"Owen Sound",
    "sg:classifiers":[
        {
            "category":"Organizations",
            "subcategory":"Religious Organization",
            "type":"Services"
        }
    ],
    "sg:phone":"+1 519 376 6040",
    "sg:postcode":"N4K 3E7",
    "sg:province":"ON",
    "sg:tags":[
        "church"
    ],
    "wof:name":"Gospel Hall",
    "wof:placetype":"venue"
},
  "geometry": {"coordinates":[-80.92822265620001,44.5680274963],"type":"Point"}
}