{
  "type": "Feature",
  "properties": {
    "addr:full":"122 Center St Milo AB T0L 1L0",
    "addr:housenumber":"122",
    "addr:postcode":"t0l 1l0",
    "addr:street":"Center St",
    "iso:country":"CA",
    "sg:address":"122 Center St",
    "sg:city":"Milo",
    "sg:classifiers":[
        {
            "category":"Restaurant",
            "type":"Food & Drink"
        }
    ],
    "sg:phone":"+1 403 599 3832",
    "sg:postcode":"T0L 1L0",
    "sg:province":"AB",
    "wof:name":"Milo Cafe",
    "wof:placetype":"venue"
},
  "geometry": {"coordinates":[-112.884040833,50.5721702576],"type":"Point"}
}