{
  "type": "Feature",
  "properties": {
    "addr:full":"4456 Ontario St Beamsville ON L0R 1B5",
    "addr:housenumber":"4456",
    "addr:postcode":"l0r 1b5",
    "addr:street":"Ontario St",
    "iso:country":"CA",
    "sg:address":"4456 Ontario St",
    "sg:city":"Beamsville",
    "sg:classifiers":[
        {
            "category":"Food & Beverages",
            "subcategory":"Specialty",
            "type":"Retail Goods"
        }
    ],
    "sg:phone":"+1 905 563 0154",
    "sg:postcode":"L0R 1B5",
    "sg:province":"ON",
    "sg:tags":[
        "water",
        "bulk",
        "company"
    ],
    "wof:name":"Aspen Water",
    "wof:placetype":"venue"
},
  "geometry": {"coordinates":[-79.4771194458,43.1768989563],"type":"Point"}
}