{
  "type": "Feature",
  "properties": {
    "addr:full":"4937 Boul Du Royaume Jonquiere QC G7X 7V5",
    "addr:housenumber":"4937",
    "addr:postcode":"g7x 7v5",
    "addr:street":"Boul Du Royaume",
    "iso:country":"CA",
    "sg:address":"4937 Boul Du Royaume",
    "sg:city":"Jonquiere",
    "sg:classifiers":[
        {
            "category":"Real Estate",
            "subcategory":"Real Estate Operator",
            "type":"Services"
        }
    ],
    "sg:phone":"+1 418 695 3405",
    "sg:postcode":"G7X 7V5",
    "sg:province":"QC",
    "sg:tags":[
        "boarding",
        "house"
    ],
    "wof:name":"Maison Du Royaume",
    "wof:placetype":"venue"
},
  "geometry": {"coordinates":[-71.35540771479999,48.4261512756],"type":"Point"}
}