{
  "type": "Feature",
  "properties": {
    "iso:country":"CA",
    "sg:city":"Mississauga",
    "sg:classifiers":[
        {
            "category":"Health Services",
            "subcategory":"Podiatrist",
            "type":"Services"
        }
    ],
    "sg:phone":"+1 905 848 2929",
    "sg:postcode":"L5B 1N1",
    "sg:province":"ON",
    "wof:name":"Cooksville Foot Care Clinic",
    "wof:placetype":"venue"
},
  "geometry": {"coordinates":[-79.609177,43.575005],"type":"Point"}
}