{
  "type": "Feature",
  "properties": {
    "addr:full":"3710 Richmond Rd Nepean ON K2H 5B8",
    "addr:housenumber":"3710",
    "addr:postcode":"k2h 5b8",
    "addr:street":"Richmond Rd",
    "iso:country":"CA",
    "sg:address":"3710 Richmond Rd",
    "sg:city":"Nepean",
    "sg:classifiers":[
        {
            "category":"Personal",
            "subcategory":"Beauty Salon",
            "type":"Services"
        }
    ],
    "sg:phone":"+1 613 829 7804",
    "sg:postcode":"K2H 5B8",
    "sg:province":"ON",
    "wof:name":"C K Hair Studio",
    "wof:placetype":"venue"
},
  "geometry": {"coordinates":[-75.8216934204,45.3266639709],"type":"Point"}
}