{
  "type": "Feature",
  "properties": {
    "iso:country":"CA",
    "sg:address":"245 Pellatt Ave",
    "sg:city":"North York",
    "sg:classifiers":[
        {
            "category":"Building & Trades",
            "subcategory":"Electrical",
            "type":"Services"
        }
    ],
    "sg:phone":"+1 416 242 9854",
    "sg:postcode":"M9N 2P8",
    "sg:province":"ON",
    "sg:tags":[
        "electric",
        "contractor"
    ],
    "wof:name":"Electrical & Controls Guyphil",
    "wof:placetype":"venue"
},
  "geometry": {"coordinates":[-79.524658,43.713375],"type":"Point"}
}