{
  "type": "Feature",
  "properties": {
    "iso:country":"CA",
    "sg:address":"858 Brodie St N",
    "sg:city":"Thunder Bay",
    "sg:classifiers":[
        {
            "category":"Wholesale",
            "subcategory":"Electrical",
            "type":"Manufacturing & Wholesale Goods"
        }
    ],
    "sg:phone":"+1 807 622 7733",
    "sg:postcode":"P7C 3V2",
    "sg:province":"ON",
    "sg:tags":[
        "electric",
        "motor"
    ],
    "wof:name":"National Electric Carbon",
    "wof:placetype":"venue"
},
  "geometry": {"coordinates":[-89.24676513670001,48.3981781006],"type":"Point"}
}