{
  "type": "Feature",
  "properties": {
    "addr:full":"13542 97 St NW Edmonton AB T5E 4E2",
    "addr:housenumber":"13542",
    "addr:postcode":"t5e 4e2",
    "addr:street":"97 St Nw",
    "iso:country":"CA",
    "sg:address":"13542 97 St NW",
    "sg:city":"Edmonton",
    "sg:classifiers":[
        {
            "category":"Professional",
            "subcategory":"Accounting & Tax Preparation",
            "type":"Services"
        }
    ],
    "sg:phone":"+1 780 448 2119",
    "sg:postcode":"T5E 4E2",
    "sg:province":"AB",
    "sg:tags":[
        "return",
        "filing"
    ],
    "wof:name":"H & R Block Canada Inc",
    "wof:placetype":"venue"
},
  "geometry": {"coordinates":[-113.492302,53.597347],"type":"Point"}
}