{
  "type": "Feature",
  "properties": {
    "addr:full":"122 Rue Guilbault Longueuil QC J4H 2T2",
    "addr:housenumber":"122",
    "addr:postcode":"j4h 2t2",
    "addr:street":"Rue Guilbault",
    "iso:country":"CA",
    "sg:address":"122 Rue Guilbault",
    "sg:city":"Longueuil",
    "sg:classifiers":[
        {
            "category":"Real Estate",
            "subcategory":"Architect",
            "type":"Services"
        }
    ],
    "sg:phone":"+1 450 463 3257",
    "sg:postcode":"J4H 2T2",
    "sg:province":"QC",
    "wof:name":"Le Groupe Des Sept Atelier",
    "wof:placetype":"venue"
},
  "geometry": {"coordinates":[-73.512199,45.535625],"type":"Point"}
}