{
  "type": "Feature",
  "properties": {
    "addr:full":"2833 16th Ave # 11 Markham ON L3R 0P8",
    "addr:housenumber":"2833",
    "addr:postcode":"l3r 0p8",
    "addr:street":"16Th Ave # 11",
    "iso:country":"CA",
    "sg:address":"2833 16th Ave # 11",
    "sg:city":"Markham",
    "sg:classifiers":[
        {
            "category":"Airline",
            "type":"Transportation"
        }
    ],
    "sg:phone":"+1 905 415 3960",
    "sg:postcode":"L3R 0P8",
    "sg:province":"ON",
    "sg:tags":[
        "rental",
        "aircraft",
        "leasing",
        "charter"
    ],
    "wof:name":"Helicopter Transport Svc",
    "wof:placetype":"venue"
},
  "geometry": {"coordinates":[-79.368522644,43.8666572571],"type":"Point"}
}