{
  "type": "Feature",
  "properties": {
    "addr:full":"155 Rue DE LA Station Laval QC H7M 3W1",
    "addr:housenumber":"155",
    "addr:postcode":"h7m 3w1",
    "addr:street":"Rue De La Station",
    "iso:country":"CA",
    "sg:address":"155 Rue DE LA Station",
    "sg:city":"Laval",
    "sg:classifiers":[
        {
            "category":"Wholesale",
            "subcategory":"Hardware",
            "type":"Manufacturing & Wholesale Goods"
        }
    ],
    "sg:phone":"+1 450 967 9880",
    "sg:postcode":"H7M 3W1",
    "sg:province":"QC",
    "sg:tags":[
        "ventilating",
        "equipment"
    ],
    "wof:name":"Ateliers Fabtech Inc",
    "wof:placetype":"venue"
},
  "geometry": {"coordinates":[-73.7226715088,45.5875930786],"type":"Point"}
}