{
  "type": "Feature",
  "properties": {
    "addr:full":"285 Weber St N # 2 Waterloo ON N2J 3H8",
    "addr:housenumber":"285",
    "addr:postcode":"n2j 3h8",
    "addr:street":"Weber St N # 2",
    "iso:country":"CA",
    "sg:address":"285 Weber St N # 2",
    "sg:city":"Waterloo",
    "sg:classifiers":[
        {
            "category":"Cinema",
            "subcategory":"Movie Rental",
            "type":"Entertainment"
        }
    ],
    "sg:phone":"+1 519 746 0062",
    "sg:postcode":"N2J 3H8",
    "sg:province":"ON",
    "sg:tags":[
        "leasing",
        "video",
        "disc",
        "tape"
    ],
    "wof:name":"Sheer Fancy Adult Video",
    "wof:placetype":"venue"
},
  "geometry": {"coordinates":[-80.5218963623,43.4800567627],"type":"Point"}
}