{
  "type": "Feature",
  "properties": {
    "iso:country":"CA",
    "sg:address":"101 Spinnaker Way",
    "sg:city":"Concord",
    "sg:classifiers":[
        {
            "category":"Manufacturing",
            "subcategory":"Petroleum Products",
            "type":"Manufacturing & Wholesale Goods"
        }
    ],
    "sg:phone":"+1 905 738 8272",
    "sg:postcode":"L4K 2T2",
    "sg:province":"ON",
    "sg:tags":[
        "lubricant"
    ],
    "wof:name":"Tonalex Lubricants Canada Inc",
    "wof:placetype":"venue"
},
  "geometry": {"coordinates":[-79.4915313721,43.8243103027],"type":"Point"}
}