{
  "type": "Feature",
  "properties": {
    "addr:full":"255 Av Saint-Sacrement Quebec QC G1N 3X9",
    "addr:postcode":"g1n 3x9",
    "addr:street":"255 Av Saint-Sacrement",
    "iso:country":"CA",
    "sg:address":"255 Av Saint-Sacrement",
    "sg:city":"Quebec",
    "sg:classifiers":[
        {
            "category":"Building & Trades",
            "subcategory":"Plumbing",
            "type":"Services"
        }
    ],
    "sg:phone":"+1 418 651 9306",
    "sg:postcode":"G1N 3X9",
    "sg:province":"QC",
    "sg:tags":[
        "septic"
    ],
    "wof:name":"Laboratoire DE Canalisations",
    "wof:placetype":"venue"
},
  "geometry": {"coordinates":[-71.2621078491,46.8026313782],"type":"Point"}
}