{
  "type": "Feature",
  "properties": {
    "addr:full":"279 Foord St Stellarton NS B0K 1S0",
    "addr:housenumber":"279",
    "addr:postcode":"b0k 1s0",
    "addr:street":"Foord St",
    "iso:country":"CA",
    "sg:address":"279 Foord St",
    "sg:city":"Stellarton",
    "sg:classifiers":[
        {
            "category":"Shopping",
            "subcategory":"Used Merchandise",
            "type":"Retail Goods"
        }
    ],
    "sg:phone":"+1 902 755 5343",
    "sg:postcode":"B0K 1S0",
    "sg:province":"NS",
    "sg:tags":[
        "book",
        "rare",
        "dealer"
    ],
    "wof:name":"Second Addition Used Book Str",
    "wof:placetype":"venue"
},
  "geometry": {"coordinates":[-62.6599769592,45.5576210022],"type":"Point"}
}