{
  "type": "Feature",
  "properties": {
    "addr:full":"3490 Mavis Rd Mississauga ON L5C 1T8",
    "addr:housenumber":"3490",
    "addr:postcode":"l5c 1t8",
    "addr:street":"Mavis Rd",
    "iso:country":"CA",
    "sg:address":"3490 Mavis Rd",
    "sg:city":"Mississauga",
    "sg:classifiers":[
        {
            "category":"Retail",
            "subcategory":"Veterinary Services",
            "type":"Services"
        }
    ],
    "sg:phone":"+1 905 273 9335",
    "sg:postcode":"L5C 1T8",
    "sg:province":"ON",
    "sg:tags":[
        "veterinarian"
    ],
    "wof:name":"Mississauga Vet Emergency Clnc",
    "wof:placetype":"venue"
},
  "geometry": {"coordinates":[-79.647064,43.575726],"type":"Point"}
}