{
  "type": "Feature",
  "properties": {
    "addr:full":"12881 16 Ave Surrey BC V4A 1N5",
    "addr:housenumber":"12881",
    "addr:postcode":"v4a 1n5",
    "addr:street":"16 Ave",
    "iso:country":"CA",
    "sg:address":"12881 16 Ave",
    "sg:city":"Surrey",
    "sg:classifiers":[
        {
            "category":"Food & Beverages",
            "subcategory":"Liquor & Beverages",
            "type":"Retail Goods"
        }
    ],
    "sg:phone":"+1 604 531 7711",
    "sg:postcode":"V4A 1N5",
    "sg:province":"BC",
    "sg:tags":[
        "store"
    ],
    "wof:name":"Liquor Stores-Government",
    "wof:placetype":"venue"
},
  "geometry": {"coordinates":[-122.86475372300001,49.0314102173],"type":"Point"}
}