{
  "type": "Feature",
  "properties": {
    "addr:full":"384 Fort William Rd Thunder Bay ON P7B 2Z3",
    "addr:housenumber":"384",
    "addr:postcode":"p7b 2z3",
    "addr:street":"Fort William Rd",
    "iso:country":"CA",
    "sg:address":"384 Fort William Rd",
    "sg:city":"Thunder Bay",
    "sg:classifiers":[
        {
            "category":"Health Services",
            "subcategory":"Doctor",
            "type":"Services"
        }
    ],
    "sg:phone":"+1 807 344 7799",
    "sg:postcode":"P7B 2Z3",
    "sg:province":"ON",
    "sg:tags":[
        "laboratory",
        "clinic"
    ],
    "wof:name":"Cliks Medical Research",
    "wof:placetype":"venue"
},
  "geometry": {"coordinates":[-89.23342132569999,48.4244537354],"type":"Point"}
}