{
  "type": "Feature",
  "properties": {
    "iso:country":"CA",
    "sg:address":"442 Hazeldean Rd",
    "sg:city":"Kanata",
    "sg:classifiers":[
        {
            "category":"Personal",
            "subcategory":"Beauty Salon",
            "type":"Services"
        }
    ],
    "sg:phone":"+1 613 831 0969",
    "sg:postcode":"K2L 1V2",
    "sg:province":"ON",
    "wof:name":"First Choice Haircutters",
    "wof:placetype":"venue"
},
  "geometry": {"coordinates":[-75.8847198486,45.3002548218],"type":"Point"}
}