{
  "type": "Feature",
  "properties": {
    "addr:full":"North York ON M5M 3Z2",
    "addr:postcode":"m5m 3z2",
    "iso:country":"CA",
    "sg:city":"North York",
    "sg:classifiers":[
        {
            "category":"Professional",
            "subcategory":"Business Services",
            "type":"Services"
        }
    ],
    "sg:phone":"+1 416 781 3500",
    "sg:postcode":"M5M 3Z2",
    "sg:province":"ON",
    "sg:tags":[
        "interior",
        "consultant",
        "design",
        "decorator"
    ],
    "wof:name":"Jean Akerman Interior Design",
    "wof:placetype":"venue"
},
  "geometry": {"coordinates":[-79.419121,43.730488],"type":"Point"}
}