{
  "type": "Feature",
  "properties": {
    "addr:full":"65 Rue Fleury O Montreal QC H3L 1T1",
    "addr:housenumber":"65",
    "addr:postcode":"h3l 1t1",
    "addr:street":"Rue Fleury O",
    "iso:country":"CA",
    "sg:address":"65 Rue Fleury O",
    "sg:city":"Montreal",
    "sg:classifiers":[
        {
            "category":"Building & Trades",
            "subcategory":"Construction",
            "type":"Services"
        }
    ],
    "sg:phone":"+1 514 383 1643",
    "sg:postcode":"H3L 1T1",
    "sg:province":"QC",
    "sg:tags":[
        "contractor"
    ],
    "wof:name":"Services DE Gestion Boisclair",
    "wof:placetype":"venue"
},
  "geometry": {"coordinates":[-73.6656951904,45.5474815369],"type":"Point"}
}