{
  "type": "Feature",
  "properties": {
    "iso:country":"CA",
    "sg:address":"715 Viscount Rd",
    "sg:city":"London",
    "sg:classifiers":[
        {
            "category":"Real Estate",
            "subcategory":"Real Estate Agent",
            "type":"Services"
        }
    ],
    "sg:phone":"+1 519 472 4996",
    "sg:postcode":"N6J 4H7",
    "sg:province":"ON",
    "sg:tags":[
        "cooperative"
    ],
    "wof:name":"Westmount Community Housing",
    "wof:placetype":"venue"
},
  "geometry": {"coordinates":[-81.275383,42.947475],"type":"Point"}
}