{
  "type": "Feature",
  "properties": {
    "addr:full":"Sidney BC V8L 1X7",
    "addr:postcode":"v8l 1x7",
    "iso:country":"CA",
    "sg:city":"Sidney",
    "sg:classifiers":[
        {
            "category":"Shopping",
            "subcategory":"Gifts & Souvenirs",
            "type":"Retail Goods"
        }
    ],
    "sg:phone":"+1 250 656 4316",
    "sg:postcode":"V8L 1X7",
    "sg:province":"BC",
    "sg:tags":[
        "cards",
        "greeting"
    ],
    "wof:name":"Thought Shop",
    "wof:placetype":"venue"
},
  "geometry": {"coordinates":[-123.39846799999999,48.648811],"type":"Point"}
}