{
  "type": "Feature",
  "properties": {
    "iso:country":"CA",
    "sg:address":"114 2nd St E",
    "sg:city":"Carnduff",
    "sg:classifiers":[
        {
            "category":"Mining & Drilling",
            "type":"Manufacturing & Wholesale Goods"
        }
    ],
    "sg:phone":"+1 306 482 3917",
    "sg:postcode":"S0C 0S0",
    "sg:province":"SK",
    "sg:tags":[
        "consultant",
        "oil",
        "gas"
    ],
    "wof:name":"Southline Inspections Ltd",
    "wof:placetype":"venue"
},
  "geometry": {"coordinates":[-101.799049377,49.1772232056],"type":"Point"}
}