{
  "type": "Feature",
  "properties": {
    "addr:full":"NW 27 24 19W Hwy 10 S Dauphin MB R7N 3B3",
    "addr:housenumber":"24",
    "addr:postcode":"r7n 3b3",
    "addr:street":"Nw 27;19W Hwy 10 S",
    "iso:country":"CA",
    "sg:address":"NW 27 24 19W Hwy 10 S",
    "sg:city":"Dauphin",
    "sg:classifiers":[
        {
            "category":"Building & Trades",
            "subcategory":"Equipment Rental",
            "type":"Services"
        }
    ],
    "sg:phone":"+1 204 638 6383",
    "sg:postcode":"R7N 3B3",
    "sg:province":"MB",
    "sg:tags":[
        "leasing",
        "charter",
        "instruction",
        "flight",
        "aircraft"
    ],
    "wof:name":"Dauphin Air Svc Ltd",
    "wof:placetype":"venue"
},
  "geometry": {"coordinates":[-100.049446,51.150043],"type":"Point"}
}