{
  "type": "Feature",
  "properties": {
    "addr:full":"Calgary AB T2H 0H9",
    "addr:postcode":"t2h 0h9",
    "iso:country":"CA",
    "sg:city":"Calgary",
    "sg:classifiers":[
        {
            "category":"Professional",
            "subcategory":"Accounting & Tax Preparation",
            "type":"Services"
        }
    ],
    "sg:phone":"+1 403 252 6698",
    "sg:postcode":"T2H 0H9",
    "sg:province":"AB",
    "sg:tags":[
        "accountant"
    ],
    "wof:name":"B C Accounting & Management",
    "wof:placetype":"venue"
},
  "geometry": {"coordinates":[-114.06933593799999,50.999671936],"type":"Point"}
}