{
  "type": "Feature",
  "properties": {
    "addr:full":"5015 44 St St Paul AB T0A 3A2",
    "addr:housenumber":"5015",
    "addr:postcode":"t0a 3a2",
    "addr:street":"44 St",
    "iso:country":"CA",
    "sg:address":"5015 44 St",
    "sg:city":"St Paul",
    "sg:classifiers":[
        {
            "category":"Autos & Motor Vehicles",
            "subcategory":"Automobile Sales",
            "type":"Retail Goods"
        }
    ],
    "sg:phone":"+1 780 645 4414",
    "sg:postcode":"T0A 3A2",
    "sg:province":"AB",
    "sg:tags":[
        "car",
        "dealer"
    ],
    "wof:name":"Smyl Motors Ltd",
    "wof:placetype":"venue"
},
  "geometry": {"coordinates":[-111.27919,53.991589],"type":"Point"}
}