{
  "type": "Feature",
  "properties": {
    "iso:country":"CA",
    "sg:address":"10122 Ivan Dr",
    "sg:city":"Ilderton",
    "sg:classifiers":[
        {
            "category":"Retail",
            "subcategory":"Repair Shop",
            "type":"Services"
        }
    ],
    "sg:phone":"+1 519 666 1542",
    "sg:postcode":"N0M 2A0",
    "sg:province":"ON",
    "sg:tags":[
        "upholsterer"
    ],
    "wof:name":"Windmill Upholstery",
    "wof:placetype":"venue"
},
  "geometry": {"coordinates":[-81.4931945801,43.0041847229],"type":"Point"}
}