{
  "type": "Feature",
  "properties": {
    "addr:full":"Outremont QC H2V 4T5",
    "addr:postcode":"h2v 4t5",
    "iso:country":"CA",
    "sg:city":"Outremont",
    "sg:classifiers":[
        {
            "category":"Professional",
            "subcategory":"Advertising",
            "type":"Services"
        }
    ],
    "sg:phone":"+1 514 270 6061",
    "sg:postcode":"H2V 4T5",
    "sg:province":"QC",
    "sg:tags":[
        "counselor"
    ],
    "wof:name":"Cpm Cartier Promotion Mrktng",
    "wof:placetype":"venue"
},
  "geometry": {"coordinates":[-73.624634,45.517979],"type":"Point"}
}