{
  "type": "Feature",
  "properties": {
    "addr:full":"500 Douglas St Sudbury ON P3C 1H7",
    "addr:housenumber":"500",
    "addr:postcode":"p3c 1h7",
    "addr:street":"Douglas St",
    "iso:country":"CA",
    "sg:address":"500 Douglas St",
    "sg:city":"Sudbury",
    "sg:classifiers":[
        {
            "category":"Social Services",
            "subcategory":"Child Care",
            "type":"Services"
        }
    ],
    "sg:phone":"+1 705 698 0265",
    "sg:postcode":"P3C 1H7",
    "sg:province":"ON",
    "wof:name":"Larch Street Kids",
    "wof:placetype":"venue"
},
  "geometry": {"coordinates":[-81.0116729736,46.4860839844],"type":"Point"}
}