{
  "type": "Feature",
  "properties": {
    "addr:full":"800 Main St S Slave Lake AB T0G 2A3",
    "addr:housenumber":"800",
    "addr:postcode":"t0g 2a3",
    "addr:street":"Main St S Slave",
    "iso:country":"CA",
    "sg:address":"800 Main St S",
    "sg:city":"Slave Lake",
    "sg:classifiers":[
        {
            "category":"Autos & Motor Vehicles",
            "subcategory":"Auto Supplies",
            "type":"Retail Goods"
        }
    ],
    "sg:phone":"+1 780 849 4220",
    "sg:postcode":"T0G 2A3",
    "sg:province":"AB",
    "sg:tags":[
        "automobile",
        "parts"
    ],
    "wof:name":"Motormania Parts & Svc Ltd",
    "wof:placetype":"venue"
},
  "geometry": {"coordinates":[-114.774315,55.277668],"type":"Point"}
}