{
  "type": "Feature",
  "properties": {
    "addr:full":"62 Edmonton City Centre NW Edmonton AB T5J 2Y7",
    "addr:housenumber":"62",
    "addr:postcode":"t5j 2y7",
    "addr:street":"Edmonton;Nw",
    "iso:country":"CA",
    "sg:address":"62 Edmonton City Centre NW",
    "sg:city":"Edmonton",
    "sg:classifiers":[
        {
            "category":"Professional",
            "subcategory":"Credit Reporting & Collection",
            "type":"Services"
        }
    ],
    "sg:phone":"+1 780 496 9566",
    "sg:postcode":"T5J 2Y7",
    "sg:province":"AB",
    "sg:tags":[
        "agency"
    ],
    "wof:name":"Independent Debt Recovery",
    "wof:placetype":"venue"
},
  "geometry": {"coordinates":[-113.490371704,53.5462188721],"type":"Point"}
}