{
  "type": "Feature",
  "properties": {
    "addr:full":"1427 Yonge St Toronto ON M4T 1Y7",
    "addr:housenumber":"1427",
    "addr:postcode":"m4t 1y7",
    "addr:street":"Yonge St",
    "iso:country":"CA",
    "sg:address":"1427 Yonge St",
    "sg:city":"Toronto",
    "sg:classifiers":[
        {
            "category":"Bars & Pubs",
            "type":"Food & Drink"
        }
    ],
    "sg:phone":"+1 416 323 3421",
    "sg:postcode":"M4T 1Y7",
    "sg:province":"ON",
    "wof:name":"Jester Pub & Grill",
    "wof:placetype":"venue"
},
  "geometry": {"coordinates":[-79.393784,43.687759],"type":"Point"}
}