{
  "type": "Feature",
  "properties": {
    "addr:full":"2801 Rue Ontario E Montreal QC H2K 1X5",
    "addr:housenumber":"2801",
    "addr:postcode":"h2k 1x5",
    "addr:street":"Rue Ontario E",
    "iso:country":"CA",
    "sg:address":"2801 Rue Ontario E",
    "sg:city":"Montreal",
    "sg:classifiers":[
        {
            "category":"Bars & Pubs",
            "type":"Food & Drink"
        }
    ],
    "sg:phone":"+1 514 598 5052",
    "sg:postcode":"H2K 1X5",
    "sg:province":"QC",
    "wof:name":"Bar 2801",
    "wof:placetype":"venue"
},
  "geometry": {"coordinates":[-73.55059799999999,45.535988],"type":"Point"}
}