{
  "type": "Feature",
  "properties": {
    "addr:full":"High Level AB T0H 1Z0",
    "addr:postcode":"t0h 1z0",
    "iso:country":"CA",
    "sg:city":"High Level",
    "sg:classifiers":[
        {
            "category":"Arena",
            "subcategory":"Sports Club",
            "type":"Entertainment"
        }
    ],
    "sg:phone":"+1 780 926 4074",
    "sg:postcode":"T0H 1Z0",
    "sg:province":"AB",
    "sg:tags":[
        "athletic",
        "fields",
        "stadium"
    ],
    "wof:name":"High Level Sports Complex",
    "wof:placetype":"venue"
},
  "geometry": {"coordinates":[-117.126091003,58.5167198181],"type":"Point"}
}