{
  "type": "Feature",
  "properties": {
    "addr:full":"9 Kingsborough Crt St Albert AB T8N 5M4",
    "addr:housenumber":"9",
    "addr:postcode":"t8n 5m4",
    "addr:street":"Kingsborough Crt",
    "iso:country":"CA",
    "sg:address":"9 Kingsborough Crt",
    "sg:city":"St Albert",
    "sg:classifiers":[
        {
            "category":"Building & Trades",
            "subcategory":"Construction",
            "type":"Services"
        }
    ],
    "sg:phone":"+1 780 459 4195",
    "sg:postcode":"T8N 5M4",
    "sg:province":"AB",
    "sg:tags":[
        "painter"
    ],
    "wof:name":"R & S Painting Ltd",
    "wof:placetype":"venue"
},
  "geometry": {"coordinates":[-113.594009399,53.6558113098],"type":"Point"}
}