{
  "type": "Feature",
  "properties": {
    "addr:full":"2205 14 Ave Castlegar BC V1N 3Z1",
    "addr:housenumber":"2205",
    "addr:postcode":"v1n 3z1",
    "addr:street":"14 Ave",
    "iso:country":"CA",
    "sg:address":"2205 14 Ave",
    "sg:city":"Castlegar",
    "sg:classifiers":[
        {
            "category":"Local Transit",
            "type":"Transportation"
        }
    ],
    "sg:phone":"+1 250 365 3100",
    "sg:postcode":"V1N 3Z1",
    "sg:province":"BC",
    "sg:tags":[
        "bus",
        "line"
    ],
    "wof:name":"Castlegar Regional Transit Sys",
    "wof:placetype":"venue"
},
  "geometry": {"coordinates":[-117.665031433,49.2916069031],"type":"Point"}
}