{
  "type": "Feature",
  "properties": {
    "addr:full":"24 Jefferson Ave Toronto ON M6K 1Y4",
    "addr:housenumber":"24",
    "addr:postcode":"m6k 1y4",
    "addr:street":"Jefferson Ave",
    "iso:country":"CA",
    "sg:address":"24 Jefferson Ave",
    "sg:city":"Toronto",
    "sg:classifiers":[
        {
            "category":"Freight",
            "type":"Transportation"
        }
    ],
    "sg:phone":"+1 416 533 7572",
    "sg:postcode":"M6K 1Y4",
    "sg:province":"ON",
    "sg:tags":[
        "box",
        "commercial"
    ],
    "wof:name":"Public Storage",
    "wof:placetype":"venue"
},
  "geometry": {"coordinates":[-79.4211883545,43.6365737915],"type":"Point"}
}