{
  "type": "Feature",
  "properties": {
    "addr:full":"164 Athabasca Ave Hinton AB T7V 2A5",
    "addr:housenumber":"164",
    "addr:postcode":"t7v 2a5",
    "addr:street":"Athabasca Ave",
    "iso:country":"CA",
    "sg:address":"164 Athabasca Ave",
    "sg:city":"Hinton",
    "sg:classifiers":[
        {
            "category":"Health Services",
            "subcategory":"Doctor",
            "type":"Services"
        }
    ],
    "sg:phone":"+1 780 865 7121",
    "sg:postcode":"T7V 2A5",
    "sg:province":"AB",
    "sg:tags":[
        "dentist"
    ],
    "wof:name":"Valley Dental Clinic",
    "wof:placetype":"venue"
},
  "geometry": {"coordinates":[-117.54567,53.42429],"type":"Point"}
}