{
  "type": "Feature",
  "properties": {
    "addr:full":"11541 87 Ave Delta BC V4C 2Z6",
    "addr:housenumber":"11541",
    "addr:postcode":"v4c 2z6",
    "addr:street":"87 Ave",
    "iso:country":"CA",
    "sg:address":"11541 87 Ave",
    "sg:city":"Delta",
    "sg:classifiers":[
        {
            "category":"Building & Trades",
            "subcategory":"Construction",
            "type":"Services"
        }
    ],
    "sg:phone":"+1 604 590 2603",
    "sg:postcode":"V4C 2Z6",
    "sg:province":"BC",
    "sg:tags":[
        "concrete",
        "contractor"
    ],
    "wof:name":"Total Concrete",
    "wof:placetype":"venue"
},
  "geometry": {"coordinates":[-122.903053,49.161278],"type":"Point"}
}