{
  "type": "Feature",
  "properties": {
    "addr:full":"Richmond Hill ON L4C 9S6",
    "addr:postcode":"l4c 9s6",
    "iso:country":"CA",
    "sg:city":"Richmond Hill",
    "sg:classifiers":[
        {
            "category":"Shopping",
            "subcategory":"Computers & Home Electronics",
            "type":"Retail Goods"
        }
    ],
    "sg:phone":"+1 905 763 7828",
    "sg:postcode":"L4C 9S6",
    "sg:province":"ON",
    "sg:tags":[
        "software"
    ],
    "wof:name":"Pyr Software",
    "wof:placetype":"venue"
},
  "geometry": {"coordinates":[-79.431923,43.847813],"type":"Point"}
}