{
  "type": "Feature",
  "properties": {
    "iso:country":"CA",
    "sg:address":"658 Rte Du President-Kennedy",
    "sg:city":"Pintendre",
    "sg:classifiers":[
        {
            "category":"Retail",
            "subcategory":"Auto Repair",
            "type":"Services"
        }
    ],
    "sg:phone":"+1 418 837 2491",
    "sg:postcode":"G6C 1K1",
    "sg:province":"QC",
    "sg:tags":[
        "brake"
    ],
    "wof:name":"Freins Embrayage Kennedy Inc",
    "wof:placetype":"venue"
},
  "geometry": {"coordinates":[-71.13464355470001,46.7656326294],"type":"Point"}
}