{
  "type": "Feature",
  "properties": {
    "addr:full":"RR 1 STN Main Port Hope ON L1A 3V5",
    "addr:postcode":"l1a 3v5",
    "addr:street":"Rr 1 Stn Main",
    "iso:country":"CA",
    "sg:address":"RR 1 STN Main",
    "sg:city":"Port Hope",
    "sg:classifiers":[
        {
            "category":"Wholesale",
            "subcategory":"Fruits & Vegetables",
            "type":"Manufacturing & Wholesale Goods"
        }
    ],
    "sg:phone":"+1 905 753 2302",
    "sg:postcode":"L1A 3V5",
    "sg:province":"ON",
    "sg:tags":[
        "shipper"
    ],
    "wof:name":"Welcome Produce Market",
    "wof:placetype":"venue"
},
  "geometry": {"coordinates":[-78.291611,43.950119],"type":"Point"}
}