{
  "type": "Feature",
  "properties": {
    "addr:full":"55 Talbot St N Essex ON N8M 1A3",
    "addr:housenumber":"55",
    "addr:postcode":"n8m 1a3",
    "addr:street":"Talbot St N",
    "iso:country":"CA",
    "sg:address":"55 Talbot St N",
    "sg:city":"Essex",
    "sg:classifiers":[
        {
            "category":"Real Estate",
            "subcategory":"Real Estate Agent",
            "type":"Services"
        }
    ],
    "sg:phone":"+1 519 776 8377",
    "sg:postcode":"N8M 1A3",
    "sg:province":"ON",
    "wof:name":"Burstyn Realty Inc",
    "wof:placetype":"venue"
},
  "geometry": {"coordinates":[-82.822487,42.175194],"type":"Point"}
}