{
  "type": "Feature",
  "properties": {
    "addr:full":"26 Milltown Blvd St Stephen NB E3L 1G3",
    "addr:housenumber":"26",
    "addr:postcode":"e3l 1g3",
    "addr:street":"Milltown Blvd",
    "iso:country":"CA",
    "sg:address":"26 Milltown Blvd",
    "sg:city":"St Stephen",
    "sg:classifiers":[
        {
            "category":"Banks & Credit Unions",
            "subcategory":"Bank",
            "type":"Services"
        }
    ],
    "sg:phone":"+1 506 466 2127",
    "sg:postcode":"E3L 1G3",
    "sg:province":"NB",
    "wof:name":"Royal Bank Financial Group",
    "wof:placetype":"venue"
},
  "geometry": {"coordinates":[-67.276726,45.19252],"type":"Point"}
}