{
  "type": "Feature",
  "properties": {
    "addr:full":"505 18 Ave SW Calgary AB T2S 0C6",
    "addr:postcode":"t2s 0c6",
    "addr:street":"505 18 Ave Sw",
    "iso:country":"CA",
    "sg:address":"505 18 Ave SW",
    "sg:city":"Calgary",
    "sg:classifiers":[
        {
            "category":"Manufacturing",
            "subcategory":"Jewelry",
            "type":"Manufacturing & Wholesale Goods"
        }
    ],
    "sg:phone":"+1 403 228 2206",
    "sg:postcode":"T2S 0C6",
    "sg:province":"AB",
    "sg:tags":[
        "jeweler"
    ],
    "wof:name":"Artistic Metal Creations",
    "wof:placetype":"venue"
},
  "geometry": {"coordinates":[-114.071877,51.036808],"type":"Point"}
}