{
  "type": "Feature",
  "properties": {
    "addr:full":"842 138 Rte Cap-Sante QC G0A 1L0",
    "addr:housenumber":"138",
    "addr:postcode":"g0a 1l0",
    "addr:street":"Rte Cap-Sante",
    "iso:country":"CA",
    "sg:address":"842 138 Rte",
    "sg:city":"Cap-Sante",
    "sg:classifiers":[
        {
            "category":"Travel",
            "subcategory":"Hotels & Motels",
            "type":"Entertainment"
        }
    ],
    "sg:phone":"+1 418 286 3391",
    "sg:postcode":"G0A 1L0",
    "sg:province":"QC",
    "wof:name":"Motel Sous Les Charmilles",
    "wof:placetype":"venue"
},
  "geometry": {"coordinates":[-71.849571228,46.6929512024],"type":"Point"}
}