{
  "type": "Feature",
  "properties": {
    "addr:full":"4811 50th Ave Lamont AB T0B 2R0",
    "addr:housenumber":"4811",
    "addr:postcode":"t0b 2r0",
    "addr:street":"50Th Ave",
    "iso:country":"CA",
    "sg:address":"4811 50th Ave",
    "sg:city":"Lamont",
    "sg:classifiers":[
        {
            "category":"Education",
            "subcategory":"School",
            "type":"Public Place"
        }
    ],
    "sg:phone":"+1 780 895 2228",
    "sg:postcode":"T0B 2R0",
    "sg:province":"AB",
    "wof:name":"Lamont High School",
    "wof:placetype":"venue"
},
  "geometry": {"coordinates":[-112.77773999999999,53.759815],"type":"Point"}
}