{
  "type": "Feature",
  "properties": {
    "iso:country":"CA",
    "sg:address":"7001 Mumford Rd",
    "sg:city":"Halifax",
    "sg:classifiers":[
        {
            "category":"Shopping",
            "subcategory":"Clothing, Apparel, & Fashions",
            "type":"Retail Goods"
        }
    ],
    "sg:phone":"+1 902 453 1444",
    "sg:postcode":"B3L 2H8",
    "sg:province":"NS",
    "wof:name":"Braemar",
    "wof:placetype":"venue"
},
  "geometry": {"coordinates":[-63.6196632385,44.6477851868],"type":"Point"}
}