{
  "type": "Feature",
  "properties": {
    "addr:full":"1122 Vidal St White Rock BC V4B 3T3",
    "addr:housenumber":"1122",
    "addr:postcode":"v4b 3t3",
    "addr:street":"Vidal St",
    "iso:country":"CA",
    "sg:address":"1122 Vidal St",
    "sg:city":"White Rock",
    "sg:classifiers":[
        {
            "category":"Professional",
            "subcategory":"Business Services",
            "type":"Services"
        }
    ],
    "sg:phone":"+1 604 535 8842",
    "sg:postcode":"V4B 3T3",
    "sg:province":"BC",
    "sg:tags":[
        "recording",
        "studio"
    ],
    "wof:name":"Turtle Recording Ltd",
    "wof:placetype":"venue"
},
  "geometry": {"coordinates":[-122.808494568,49.0226211548],"type":"Point"}
}