{
  "type": "Feature",
  "properties": {
    "iso:country":"CA",
    "sg:address":"6675 Montevideo Rd",
    "sg:city":"Mississauga",
    "sg:classifiers":[
        {
            "category":"Education",
            "subcategory":"School",
            "type":"Public Place"
        }
    ],
    "sg:phone":"+1 905 858 3462",
    "sg:postcode":"L5N 4E8",
    "sg:province":"ON",
    "wof:name":"St Teresa of Avila School",
    "wof:placetype":"venue"
},
  "geometry": {"coordinates":[-79.75560760499999,43.5904350281],"type":"Point"}
}