{
  "type": "Feature",
  "properties": {
    "addr:full":"4795 Rue DE LA Promenade-Des-S Cap-Rouge QC G1Y 2W2",
    "addr:housenumber":"4795",
    "addr:postcode":"g1y 2w2",
    "addr:street":"Rue De La Promenade-Des-S",
    "iso:country":"CA",
    "sg:address":"4795 Rue DE LA Promenade-Des-S",
    "sg:city":"Cap-Rouge",
    "sg:classifiers":[
        {
            "category":"Restaurant",
            "type":"Food & Drink"
        }
    ],
    "sg:phone":"+1 418 657 5816",
    "sg:postcode":"G1Y 2W2",
    "sg:province":"QC",
    "wof:name":"Restaurant Chez Madame Li",
    "wof:placetype":"venue"
},
  "geometry": {"coordinates":[-71.3599395752,46.7467346191],"type":"Point"}
}