{
  "type": "Feature",
  "properties": {
    "iso:country":"CA",
    "sg:address":"576 Ritson Rd S",
    "sg:city":"Oshawa",
    "sg:classifiers":[
        {
            "category":"Retail",
            "subcategory":"Laundry & Dry Cleaning",
            "type":"Services"
        }
    ],
    "sg:phone":"+1 905 576 4288",
    "sg:postcode":"L1H 5K7",
    "sg:province":"ON",
    "sg:tags":[
        "cleaners"
    ],
    "wof:name":"Lucy's Dry Cleaning & Altrtns",
    "wof:placetype":"venue"
},
  "geometry": {"coordinates":[-78.847298,43.885128],"type":"Point"}
}