{
  "type": "Feature",
  "properties": {
    "addr:full":"Winnipeg MB R2G 1P3",
    "addr:postcode":"r2g 1p3",
    "iso:country":"CA",
    "sg:city":"Winnipeg",
    "sg:classifiers":[
        {
            "category":"Shopping",
            "subcategory":"Discount & Variety Stores",
            "type":"Retail Goods"
        }
    ],
    "sg:phone":"+1 204 338 7773",
    "sg:postcode":"R2G 1P3",
    "sg:province":"MB",
    "sg:tags":[
        "merchandise",
        "general"
    ],
    "wof:name":"Bargains For Dollars",
    "wof:placetype":"venue"
},
  "geometry": {"coordinates":[-97.07610321040001,49.9536895752],"type":"Point"}
}