{
  "type": "Feature",
  "properties": {
    "addr:full":"4904 51 St Wetaskiwin AB T9A 1L2",
    "addr:housenumber":"4904",
    "addr:postcode":"t9a 1l2",
    "addr:street":"51 St",
    "iso:country":"CA",
    "sg:address":"4904 51 St",
    "sg:city":"Wetaskiwin",
    "sg:classifiers":[
        {
            "category":"Government",
            "subcategory":"Fire Station",
            "type":"Public Place"
        }
    ],
    "sg:phone":"+1 780 361 4429",
    "sg:postcode":"T9A 1L2",
    "sg:province":"AB",
    "sg:tags":[
        "department"
    ],
    "wof:name":"City of Wetaskiwin Fire Dept",
    "wof:placetype":"venue"
},
  "geometry": {"coordinates":[-113.376564,52.96907],"type":"Point"}
}