{
  "type": "Feature",
  "properties": {
    "addr:full":"Mattawa ON P0H 1V0",
    "addr:postcode":"p0h 1v0",
    "iso:country":"CA",
    "sg:city":"Mattawa",
    "sg:classifiers":[
        {
            "category":"Government",
            "subcategory":"Office",
            "type":"Public Place"
        }
    ],
    "sg:phone":"+1 705 744 5680",
    "sg:postcode":"P0H 1V0",
    "sg:province":"ON",
    "sg:tags":[
        "village"
    ],
    "wof:name":"Mattawan Office",
    "wof:placetype":"venue"
},
  "geometry": {"coordinates":[-78.70315600000001,46.317749],"type":"Point"}
}