{
  "type": "Feature",
  "properties": {
    "iso:country":"CA",
    "sg:city":"Keswick",
    "sg:classifiers":[
        {
            "category":"Health Services",
            "subcategory":"Doctor",
            "type":"Services"
        }
    ],
    "sg:phone":"+1 905 476 0308",
    "sg:postcode":"L4P 2C7",
    "sg:province":"ON",
    "sg:tags":[
        "physician",
        "clinic",
        "surgeon"
    ],
    "wof:name":"Queensway Medical Ctr",
    "wof:placetype":"venue"
},
  "geometry": {"coordinates":[-79.464371,44.215542],"type":"Point"}
}