{
  "type": "Feature",
  "properties": {
    "addr:full":"Saint-Pamphile QC G0R 3X0",
    "addr:postcode":"g0r 3x0",
    "iso:country":"CA",
    "sg:city":"Saint-Pamphile",
    "sg:classifiers":[
        {
            "category":"Government",
            "subcategory":"Office",
            "type":"Public Place"
        }
    ],
    "sg:phone":"+1 418 356 2121",
    "sg:postcode":"G0R 3X0",
    "sg:province":"QC",
    "sg:tags":[
        "village"
    ],
    "wof:name":"St-Pamphile Pompiers",
    "wof:placetype":"venue"
},
  "geometry": {"coordinates":[-69.7786407471,46.960811615],"type":"Point"}
}