{
  "type": "Feature",
  "properties": {
    "iso:country":"CA",
    "sg:address":"7040 Torbram Rd",
    "sg:city":"Mississauga",
    "sg:classifiers":[
        {
            "category":"Airport",
            "type":"Transportation"
        }
    ],
    "sg:phone":"+1 905 877 7567",
    "sg:postcode":"L4T 3Z4",
    "sg:province":"ON",
    "sg:tags":[
        "aircraft",
        "maintenance"
    ],
    "wof:name":"Aircon",
    "wof:placetype":"venue"
},
  "geometry": {"coordinates":[-79.65432,43.695183],"type":"Point"}
}