{
  "type": "Feature",
  "properties": {
    "addr:full":"96 Glencoe Dr Mount Pearl NL A1N 4S9",
    "addr:housenumber":"96",
    "addr:postcode":"a1n 4s9",
    "addr:street":"Glencoe Dr",
    "iso:country":"CA",
    "sg:address":"96 Glencoe Dr",
    "sg:city":"Mount Pearl",
    "sg:classifiers":[
        {
            "category":"Freight",
            "type":"Transportation"
        }
    ],
    "sg:phone":"+1 709 747 0665",
    "sg:postcode":"A1N 4S9",
    "sg:province":"NL",
    "sg:tags":[
        "warehouse",
        "storage"
    ],
    "wof:name":"Atlas Cold Storage",
    "wof:placetype":"venue"
},
  "geometry": {"coordinates":[-52.844921,47.520527],"type":"Point"}
}