{
  "type": "Feature",
  "properties": {
    "addr:full":"1 Victoria St S Tweed ON K0K 3J0",
    "addr:housenumber":"1",
    "addr:postcode":"k0k 3j0",
    "addr:street":"Victoria St S",
    "iso:country":"CA",
    "sg:address":"1 Victoria St S",
    "sg:city":"Tweed",
    "sg:classifiers":[
        {
            "category":"Retail",
            "subcategory":"Auto Repair",
            "type":"Services"
        }
    ],
    "sg:phone":"+1 613 478 2609",
    "sg:postcode":"K0K 3J0",
    "sg:province":"ON",
    "sg:tags":[
        "wrecker"
    ],
    "wof:name":"Holmes Towing Svc",
    "wof:placetype":"venue"
},
  "geometry": {"coordinates":[-77.3097915649,44.4746131897],"type":"Point"}
}