{
  "type": "Feature",
  "properties": {
    "addr:full":"584290 Beachville Rd Beachville ON N0J 1A0",
    "addr:housenumber":"584290",
    "addr:postcode":"n0j 1a0",
    "addr:street":"Beachville Rd",
    "iso:country":"CA",
    "sg:address":"584290 Beachville Rd",
    "sg:city":"Beachville",
    "sg:classifiers":[
        {
            "category":"Building & Trades",
            "subcategory":"Construction",
            "type":"Services"
        }
    ],
    "sg:phone":"+1 519 423 9415",
    "sg:postcode":"N0J 1A0",
    "sg:province":"ON",
    "sg:tags":[
        "breaking",
        "contractor",
        "concrete",
        "cutting",
        "drilling",
        "sawing"
    ],
    "wof:name":"Doubil Inc",
    "wof:placetype":"venue"
},
  "geometry": {"coordinates":[-80.84571099999999,43.071236],"type":"Point"}
}