{
  "type": "Feature",
  "properties": {
    "addr:full":"1029 Brodie Dr Orillia ON L3V 6H4",
    "addr:housenumber":"1029",
    "addr:postcode":"l3v 6h4",
    "addr:street":"Brodie Dr",
    "iso:country":"CA",
    "sg:address":"1029 Brodie Dr",
    "sg:city":"Orillia",
    "sg:classifiers":[
        {
            "category":"Shopping",
            "type":"Retail Goods"
        }
    ],
    "sg:phone":"+1 705 327 3232",
    "sg:postcode":"L3V 6H4",
    "sg:province":"ON",
    "sg:tags":[
        "telephone",
        "cellular"
    ],
    "wof:name":"Bell World",
    "wof:placetype":"venue"
},
  "geometry": {"coordinates":[-79.41822814939999,44.606590271],"type":"Point"}
}