{
  "type": "Feature",
  "properties": {
    "iso:country":"CA",
    "sg:address":"600 Rue Jean-Talon E # 103",
    "sg:city":"Montreal",
    "sg:classifiers":[
        {
            "category":"Retail",
            "subcategory":"Photofinishing",
            "type":"Services"
        }
    ],
    "sg:phone":"+1 514 270 4539",
    "sg:postcode":"H2R 3A8",
    "sg:province":"QC",
    "sg:tags":[
        "photo",
        "finishing"
    ],
    "wof:name":"Photometro",
    "wof:placetype":"venue"
},
  "geometry": {"coordinates":[-73.613464,45.539661],"type":"Point"}
}