{
  "type": "Feature",
  "properties": {
    "addr:full":"5869 Hudson St Vancouver BC V6M 2Z2",
    "addr:housenumber":"5869",
    "addr:postcode":"v6m 2z2",
    "addr:street":"Hudson St",
    "iso:country":"CA",
    "sg:address":"5869 Hudson St",
    "sg:city":"Vancouver",
    "sg:classifiers":[
        {
            "category":"Professional",
            "subcategory":"Lawyer & Legal Services",
            "type":"Services"
        }
    ],
    "sg:phone":"+1 604 263 4043",
    "sg:postcode":"V6M 2Z2",
    "sg:province":"BC",
    "sg:tags":[
        "attorney"
    ],
    "wof:name":"Peter Watts Law Corp",
    "wof:placetype":"venue"
},
  "geometry": {"coordinates":[-123.13504791299999,49.2327842712],"type":"Point"}
}