{
  "type": "Feature",
  "properties": {
    "addr:full":"Richmond BC V6V 2E4",
    "addr:postcode":"v6v 2e4",
    "iso:country":"CA",
    "sg:city":"Richmond",
    "sg:classifiers":[
        {
            "category":"Wholesale",
            "subcategory":"Durable Goods & Equipment",
            "type":"Manufacturing & Wholesale Goods"
        }
    ],
    "sg:phone":"+1 604 273 8777",
    "sg:postcode":"V6V 2E4",
    "sg:province":"BC",
    "sg:tags":[
        "importer"
    ],
    "wof:name":"Jarvis Imports Ltd",
    "wof:placetype":"venue"
},
  "geometry": {"coordinates":[-123.072784,49.181576],"type":"Point"}
}