{
  "type": "Feature",
  "properties": {
    "addr:full":"8140 Rue Lafrenaie Saint-Leonard QC H1P 2A9",
    "addr:housenumber":"8140",
    "addr:postcode":"h1p 2a9",
    "addr:street":"Rue Lafrenaie",
    "iso:country":"CA",
    "sg:address":"8140 Rue Lafrenaie",
    "sg:city":"Saint-Leonard",
    "sg:classifiers":[
        {
            "category":"Manufacturing",
            "subcategory":"Tools & Machinery",
            "type":"Manufacturing & Wholesale Goods"
        }
    ],
    "sg:phone":"+1 514 327 3613",
    "sg:postcode":"H1P 2A9",
    "sg:province":"QC",
    "sg:tags":[
        "machine",
        "shop"
    ],
    "wof:name":"Claro Precision Inc",
    "wof:placetype":"venue"
},
  "geometry": {"coordinates":[-73.58306884770001,45.5966453552],"type":"Point"}
}