{
  "type": "Feature",
  "properties": {
    "addr:full":"Ange-Gardien QC J0E 1E0",
    "addr:postcode":"j0e 1e0",
    "addr:street":"Ange-Gardien",
    "iso:country":"CA",
    "sg:city":"Ange-Gardien",
    "sg:classifiers":[
        {
            "category":"Wholesale",
            "subcategory":"Meat",
            "type":"Manufacturing & Wholesale Goods"
        }
    ],
    "sg:phone":"+1 450 293 6464",
    "sg:postcode":"J0E 1E0",
    "sg:province":"QC",
    "sg:tags":[
        "packer"
    ],
    "wof:name":"Abattoir & Boucherie Cameron",
    "wof:placetype":"venue"
},
  "geometry": {"coordinates":[-72.905495,45.342548],"type":"Point"}
}