{
  "type": "Feature",
  "properties": {
    "addr:full":"10 Four Seasons Pl # 12 Etobicoke ON M9B 6H7",
    "addr:housenumber":"10",
    "addr:postcode":"m9b 6h7",
    "addr:street":"Four Seasons Pl # 12",
    "iso:country":"CA",
    "sg:address":"10 Four Seasons Pl # 12",
    "sg:city":"Etobicoke",
    "sg:classifiers":[
        {
            "category":"Manufacturing",
            "subcategory":"Food",
            "type":"Manufacturing & Wholesale Goods"
        }
    ],
    "sg:phone":"+1 416 622 2040",
    "sg:postcode":"M9B 6H7",
    "sg:province":"ON",
    "sg:tags":[
        "baker",
        "cookie",
        "bakery"
    ],
    "wof:name":"Canada Bread CO Ltd",
    "wof:placetype":"venue"
},
  "geometry": {"coordinates":[-79.56017300000001,43.648018],"type":"Point"}
}