{
  "type": "Feature",
  "properties": {
    "addr:full":"105 Prince William St Saint John NB E2L 2B2",
    "addr:housenumber":"105",
    "addr:postcode":"nb e2l 2b2",
    "addr:street":"Prince William St",
    "iso:country":"CA",
    "sg:address":"105 Prince William St",
    "sg:city":"Saint John",
    "sg:classifiers":[
        {
            "category":"Professional",
            "subcategory":"Computer Services",
            "type":"Services"
        }
    ],
    "sg:phone":"+1 506 632 0185",
    "sg:postcode":"E2L 2B2",
    "sg:province":"NB",
    "sg:tags":[
        "repair",
        "internet"
    ],
    "wof:name":"Fundy Computer Svc Ltd",
    "wof:placetype":"venue"
},
  "geometry": {"coordinates":[-66.062119,45.271564],"type":"Point"}
}