{
  "type": "Feature",
  "properties": {
    "addr:full":"3403 32 Ave Vernon BC V1T 2M9",
    "addr:housenumber":"3403",
    "addr:postcode":"v1t 2m9",
    "addr:street":"32 Ave",
    "iso:country":"CA",
    "sg:address":"3403 32 Ave",
    "sg:city":"Vernon",
    "sg:classifiers":[
        {
            "category":"Professional",
            "subcategory":"Business Services",
            "type":"Services"
        }
    ],
    "sg:phone":"+1 250 542 3384",
    "sg:postcode":"V1T 2M9",
    "sg:province":"BC",
    "sg:tags":[
        "orthopedic",
        "appliance",
        "made"
    ],
    "wof:name":"B C Prosthetic & Orthotic Svc",
    "wof:placetype":"venue"
},
  "geometry": {"coordinates":[-119.27724499999999,50.26553],"type":"Point"}
}