{
  "type": "Feature",
  "properties": {
    "addr:full":"Victoria BC V8N 6J1",
    "addr:postcode":"v8n 6j1",
    "iso:country":"CA",
    "sg:city":"Victoria",
    "sg:classifiers":[
        {
            "category":"Sports & Exercise",
            "subcategory":"Gym",
            "type":"Entertainment"
        }
    ],
    "sg:phone":"+1 250 477 9299",
    "sg:postcode":"V8N 6J1",
    "sg:province":"BC",
    "sg:tags":[
        "club",
        "health",
        "studio",
        "gymnasium"
    ],
    "wof:name":"Women Zone Fitness & Aerobic",
    "wof:placetype":"venue"
},
  "geometry": {"coordinates":[-123.333237,48.448151],"type":"Point"}
}