{
  "type": "Feature",
  "properties": {
    "iso:country":"CA",
    "sg:address":"72 Orchard Rd",
    "sg:city":"Ajax",
    "sg:classifiers":[
        {
            "category":"Manufacturing",
            "subcategory":"Metals",
            "type":"Manufacturing & Wholesale Goods"
        }
    ],
    "sg:phone":"+1 905 686 2277",
    "sg:postcode":"L1S 6L1",
    "sg:province":"ON",
    "sg:tags":[
        "plating"
    ],
    "wof:name":"General Magnaplate Canada Ltd",
    "wof:placetype":"venue"
},
  "geometry": {"coordinates":[-79.060204,43.847046],"type":"Point"}
}