{
  "type": "Feature",
  "properties": {
    "addr:full":"5270 46 Ave SE Salmon Arm BC V1E 1X2",
    "addr:housenumber":"5270",
    "addr:postcode":"v1e 1x2",
    "addr:street":"46 Ave Se",
    "iso:country":"CA",
    "sg:address":"5270 46 Ave SE",
    "sg:city":"Salmon Arm",
    "sg:classifiers":[
        {
            "category":"Freight",
            "type":"Transportation"
        }
    ],
    "sg:phone":"+1 250 832 2010",
    "sg:postcode":"V1E 1X2",
    "sg:province":"BC",
    "sg:tags":[
        "trucking"
    ],
    "wof:name":"West Line Trucking Ltd",
    "wof:placetype":"venue"
},
  "geometry": {"coordinates":[-119.224701,50.665977],"type":"Point"}
}