{
  "type": "Feature",
  "properties": {
    "addr:full":"Surrey BC V3W 7Z7",
    "addr:postcode":"v3w 7z7",
    "iso:country":"CA",
    "sg:city":"Surrey",
    "sg:classifiers":[
        {
            "category":"Shopping",
            "subcategory":"Computers & Home Electronics",
            "type":"Retail Goods"
        }
    ],
    "sg:phone":"+1 604 590 2590",
    "sg:postcode":"V3W 7Z7",
    "sg:province":"BC",
    "sg:tags":[
        "equipment",
        "dealer"
    ],
    "wof:name":"Western Networks & Consulting",
    "wof:placetype":"venue"
},
  "geometry": {"coordinates":[-122.854057,49.132256],"type":"Point"}
}