{
  "type": "Feature",
  "properties": {
    "addr:full":"100 Hoka St Winnipeg MB R2C 3N2",
    "addr:housenumber":"100",
    "addr:postcode":"r2c 3n2",
    "addr:street":"Hoka St",
    "iso:country":"CA",
    "sg:address":"100 Hoka St",
    "sg:city":"Winnipeg",
    "sg:classifiers":[
        {
            "category":"Home & Garden",
            "subcategory":"Furniture",
            "type":"Retail Goods"
        }
    ],
    "sg:phone":"+1 204 224 2286",
    "sg:postcode":"R2C 3N2",
    "sg:province":"MB",
    "sg:tags":[
        "top",
        "counter"
    ],
    "wof:name":"Canital Granite Ltd",
    "wof:placetype":"venue"
},
  "geometry": {"coordinates":[-97.015923,49.891483],"type":"Point"}
}