{
  "type": "Feature",
  "properties": {
    "addr:full":"305 Rutherford Rd S Brampton ON L6W 3R5",
    "addr:housenumber":"305",
    "addr:postcode":"l6w 3r5",
    "addr:street":"Rutherford Rd S",
    "iso:country":"CA",
    "sg:address":"305 Rutherford Rd S",
    "sg:city":"Brampton",
    "sg:classifiers":[
        {
            "category":"Home & Garden",
            "subcategory":"Building Materials",
            "type":"Retail Goods"
        }
    ],
    "sg:phone":"+1 905 453 9689",
    "sg:postcode":"L6W 3R5",
    "sg:province":"ON",
    "sg:tags":[
        "roofing"
    ],
    "wof:name":"Roofmart Limited",
    "wof:placetype":"venue"
},
  "geometry": {"coordinates":[-79.7194061279,43.6819190979],"type":"Point"}
}