{
  "type": "Feature",
  "properties": {
    "iso:country":"CA",
    "sg:address":"395 Kingston Rd",
    "sg:city":"Pickering",
    "sg:classifiers":[
        {
            "category":"Wholesale",
            "subcategory":"Auto Parts",
            "type":"Manufacturing & Wholesale Goods"
        }
    ],
    "sg:phone":"+1 905 509 2466",
    "sg:postcode":"L1V 1A3",
    "sg:province":"ON",
    "sg:tags":[
        "automobile",
        "wrecking"
    ],
    "wof:name":"Allison Greenwood Auto Wrecker",
    "wof:placetype":"venue"
},
  "geometry": {"coordinates":[-79.127716,43.810051],"type":"Point"}
}