{
  "type": "Feature",
  "properties": {
    "addr:full":"90 Rue Augusta Sorel-Tracy QC J3P 1A7",
    "addr:housenumber":"90",
    "addr:postcode":"j3p 1a7",
    "addr:street":"Rue Augusta",
    "iso:country":"CA",
    "sg:address":"90 Rue Augusta",
    "sg:city":"Sorel-Tracy",
    "sg:classifiers":[
        {
            "category":"Bars & Pubs",
            "type":"Food & Drink"
        }
    ],
    "sg:phone":"+1 450 743 8132",
    "sg:postcode":"J3P 1A7",
    "sg:province":"QC",
    "sg:tags":[
        "lounge",
        "cocktail"
    ],
    "wof:name":"Bar Le Voltage",
    "wof:placetype":"venue"
},
  "geometry": {"coordinates":[-73.11318199999999,46.046097],"type":"Point"}
}