{
  "type": "Feature",
  "properties": {
    "addr:full":"401 Riverside Dr W Windsor ON N9A 7J1",
    "addr:housenumber":"401",
    "addr:postcode":"n9a 7j1",
    "addr:street":"Riverside Dr W",
    "iso:country":"CA",
    "sg:address":"401 Riverside Dr W",
    "sg:city":"Windsor",
    "sg:classifiers":[
        {
            "category":"Shopping",
            "subcategory":"Gifts & Souvenirs",
            "type":"Retail Goods"
        }
    ],
    "sg:phone":"+1 519 977 1400",
    "sg:postcode":"N9A 7J1",
    "sg:province":"ON",
    "sg:tags":[
        "shop"
    ],
    "wof:name":"Uncommon Market Gift Shop",
    "wof:placetype":"venue"
},
  "geometry": {"coordinates":[-83.044464,42.31863],"type":"Point"}
}