{
  "type": "Feature",
  "properties": {
    "addr:full":"1932 Rue Decoste Sept-Iles QC G4R 4K7",
    "addr:housenumber":"1932",
    "addr:postcode":"g4r 4k7",
    "addr:street":"Rue Decoste Sept-Iles",
    "iso:country":"CA",
    "sg:address":"1932 Rue Decoste",
    "sg:city":"Sept-Iles",
    "sg:classifiers":[
        {
            "category":"Manufacturing",
            "subcategory":"Tools & Machinery",
            "type":"Manufacturing & Wholesale Goods"
        }
    ],
    "sg:phone":"+1 418 968 8611",
    "sg:postcode":"G4R 4K7",
    "sg:province":"QC",
    "sg:tags":[
        "machine",
        "shop"
    ],
    "wof:name":"Industries Mingan Inc",
    "wof:placetype":"venue"
},
  "geometry": {"coordinates":[-66.39428700000001,50.284943],"type":"Point"}
}