{
  "type": "Feature",
  "properties": {
    "addr:full":"30 Main St Stanley NB E6B 1A4",
    "addr:housenumber":"30",
    "addr:postcode":"e6b 1a4",
    "addr:street":"Main St",
    "iso:country":"CA",
    "sg:address":"30 Main St",
    "sg:city":"Stanley",
    "sg:classifiers":[
        {
            "category":"Food & Beverages",
            "subcategory":"Liquor & Beverages",
            "type":"Retail Goods"
        }
    ],
    "sg:phone":"+1 506 367 2598",
    "sg:postcode":"E6B 1A4",
    "sg:province":"NB",
    "sg:tags":[
        "convenience",
        "store"
    ],
    "wof:name":"Hillside Convenience",
    "wof:placetype":"venue"
},
  "geometry": {"coordinates":[-66.741829,46.282612],"type":"Point"}
}