{
  "type": "Feature",
  "properties": {
    "iso:country":"CA",
    "sg:address":"605 132 Rte",
    "sg:city":"Cloridorme",
    "sg:classifiers":[
        {
            "category":"Home & Garden",
            "subcategory":"Furniture",
            "type":"Retail Goods"
        }
    ],
    "sg:phone":"+1 418 395 2335",
    "sg:postcode":"G0E 1G0",
    "sg:province":"QC",
    "sg:tags":[
        "equipment",
        "kitchen",
        "cabinet"
    ],
    "wof:name":"Atelier Mc Enr",
    "wof:placetype":"venue"
},
  "geometry": {"coordinates":[-64.85288199999999,49.185135],"type":"Point"}
}