{
  "type": "Feature",
  "properties": {
    "addr:full":"1615 Renfrew St Vancouver BC V5K 4C9",
    "addr:housenumber":"1615",
    "addr:postcode":"v5k 4c9",
    "addr:street":"Renfrew St",
    "iso:country":"CA",
    "sg:address":"1615 Renfrew St",
    "sg:city":"Vancouver",
    "sg:classifiers":[
        {
            "category":"Health Services",
            "subcategory":"Doctor",
            "type":"Services"
        }
    ],
    "sg:phone":"+1 604 253 3828",
    "sg:postcode":"V5K 4C9",
    "sg:province":"BC",
    "sg:tags":[
        "dentist"
    ],
    "wof:name":"Chen, Mike S DDS",
    "wof:placetype":"venue"
},
  "geometry": {"coordinates":[-123.044395447,49.2702445984],"type":"Point"}
}