{
  "type": "Feature",
  "properties": {
    "addr:full":"29 Victoria St S Tweed ON K0K 3J0",
    "addr:housenumber":"29",
    "addr:postcode":"k0k 3j0",
    "addr:street":"Victoria St S",
    "iso:country":"CA",
    "sg:address":"29 Victoria St S",
    "sg:city":"Tweed",
    "sg:classifiers":[
        {
            "category":"Autos & Motor Vehicles",
            "subcategory":"Motorcycle Sales",
            "type":"Retail Goods"
        }
    ],
    "sg:phone":"+1 613 478 1602",
    "sg:postcode":"K0K 3J0",
    "sg:province":"ON",
    "sg:tags":[
        "engine",
        "all",
        "terrain"
    ],
    "wof:name":"Total Rental-All",
    "wof:placetype":"venue"
},
  "geometry": {"coordinates":[-77.30938,44.474358],"type":"Point"}
}