{
  "type": "Feature",
  "properties": {
    "iso:country":"CA",
    "sg:address":"1925 Boul Saint-Martin O",
    "sg:city":"Laval",
    "sg:classifiers":[
        {
            "category":"Restaurant",
            "type":"Food & Drink"
        }
    ],
    "sg:phone":"+1 450 687 6575",
    "sg:postcode":"H7S 1N2",
    "sg:province":"QC",
    "wof:name":"Harvey's",
    "wof:placetype":"venue"
},
  "geometry": {"coordinates":[-73.731277,45.566307],"type":"Point"}
}