{
  "type": "Feature",
  "properties": {
    "iso:country":"CA",
    "sg:address":"159 Main St E",
    "sg:city":"Milton",
    "sg:classifiers":[
        {
            "category":"Health Services",
            "subcategory":"Medical Lab",
            "type":"Services"
        }
    ],
    "sg:phone":"+1 905 876 2000",
    "sg:postcode":"L9T 1N7",
    "sg:province":"ON",
    "wof:name":"Milton Denture Clinic",
    "wof:placetype":"venue"
},
  "geometry": {"coordinates":[-79.884476,43.512138],"type":"Point"}
}