{
  "type": "Feature",
  "properties": {
    "addr:full":"159 Main St E Milton ON L9T 1N7",
    "addr:housenumber":"159",
    "addr:postcode":"l9t 1n7",
    "addr:street":"Main St E",
    "iso:country":"CA",
    "sg:address":"159 Main St E",
    "sg:city":"Milton",
    "sg:classifiers":[
        {
            "category":"Health Services",
            "subcategory":"Medical Lab",
            "type":"Services"
        }
    ],
    "sg:phone":"+1 905 876 2000",
    "sg:postcode":"L9T 1N7",
    "sg:province":"ON",
    "wof:name":"Milton Denture Clinic",
    "wof:placetype":"venue"
},
  "geometry": {"coordinates":[-79.88447600000001,43.512138],"type":"Point"}
}