{
  "type": "Feature",
  "properties": {
    "addr:full":"182 Rue DE LA Colombiere Saint-Romuald QC G6W 5R5",
    "addr:housenumber":"182",
    "addr:postcode":"g6w 5r5",
    "addr:street":"Rue De La Colombiere",
    "iso:country":"CA",
    "sg:address":"182 Rue DE LA Colombiere",
    "sg:city":"Saint-Romuald",
    "sg:classifiers":[
        {
            "category":"Shopping",
            "subcategory":"Used Merchandise",
            "type":"Retail Goods"
        }
    ],
    "sg:phone":"+1 418 834 7717",
    "sg:postcode":"G6W 5R5",
    "sg:province":"QC",
    "sg:tags":[
        "antique"
    ],
    "wof:name":"Hotel Des Ventes Universelles",
    "wof:placetype":"venue"
},
  "geometry": {"coordinates":[-71.25727844239999,46.7455787659],"type":"Point"}
}