{
  "type": "Feature",
  "properties": {
    "addr:full":"111 Elora St N Clifford ON N0G 1M0",
    "addr:housenumber":"111",
    "addr:postcode":"n0g 1m0",
    "addr:street":"Elora St N",
    "iso:country":"CA",
    "sg:address":"111 Elora St N",
    "sg:city":"Clifford",
    "sg:classifiers":[
        {
            "category":"Wholesale",
            "subcategory":"Apparel",
            "type":"Manufacturing & Wholesale Goods"
        }
    ],
    "sg:phone":"+1 519 327 8091",
    "sg:postcode":"N0G 1M0",
    "sg:province":"ON",
    "sg:tags":[
        "dry"
    ],
    "wof:name":"W C Smith Wholesale Distr Inc",
    "wof:placetype":"venue"
},
  "geometry": {"coordinates":[-80.98505401609999,43.9724617004],"type":"Point"}
}