{
  "type": "Feature",
  "properties": {
    "addr:full":"700 Watt St Winnipeg MB R2K 2S7",
    "addr:housenumber":"700",
    "addr:postcode":"r2k 2s7",
    "addr:street":"Watt St",
    "iso:country":"CA",
    "sg:address":"700 Watt St",
    "sg:city":"Winnipeg",
    "sg:classifiers":[
        {
            "category":"Organizations",
            "subcategory":"Religious Organization",
            "type":"Services"
        }
    ],
    "sg:phone":"+1 204 669 0415",
    "sg:postcode":"R2K 2S7",
    "sg:province":"MB",
    "sg:tags":[
        "church"
    ],
    "wof:name":"East Kildonan Baptist Church",
    "wof:placetype":"venue"
},
  "geometry": {"coordinates":[-97.091866,49.922749],"type":"Point"}
}