{
  "type": "Feature",
  "properties": {
    "addr:full":"967 Ordze Rd # A Sherwood Park AB T8A 4L7",
    "addr:housenumber":"967",
    "addr:postcode":"t8a 4l7",
    "addr:street":"Ordze Rd # A;Park",
    "iso:country":"CA",
    "sg:address":"967 Ordze Rd # A",
    "sg:city":"Sherwood Park",
    "sg:classifiers":[
        {
            "category":"Restaurant",
            "type":"Food & Drink"
        }
    ],
    "sg:phone":"+1 780 467 2223",
    "sg:postcode":"T8A 4L7",
    "sg:province":"AB",
    "wof:name":"Boston Pizza",
    "wof:placetype":"venue"
},
  "geometry": {"coordinates":[-113.329926,53.513248],"type":"Point"}
}