{
  "type": "Feature",
  "properties": {
    "iso:country":"CA",
    "sg:address":"2927 Dufferin St",
    "sg:city":"North York",
    "sg:classifiers":[
        {
            "category":"Wholesale",
            "subcategory":"Meat",
            "type":"Manufacturing & Wholesale Goods"
        }
    ],
    "sg:phone":"+1 416 789 0635",
    "sg:postcode":"M6B 3S7",
    "sg:province":"ON",
    "wof:name":"Dufferin Meat Market",
    "wof:placetype":"venue"
},
  "geometry": {"coordinates":[-79.4534912109,43.7089538574],"type":"Point"}
}