{
  "type": "Feature",
  "properties": {
    "addr:full":"349 Rue Beauvilliers Saint-Gabriel-DE-Brandon QC J0K 2N0",
    "addr:housenumber":"349",
    "addr:postcode":"j0k 2n0",
    "addr:street":"Rue Beauvilliers",
    "iso:country":"CA",
    "sg:address":"349 Rue Beauvilliers",
    "sg:city":"Saint-Gabriel-DE-Brandon",
    "sg:classifiers":[
        {
            "category":"Restaurant",
            "type":"Food & Drink"
        }
    ],
    "sg:phone":"+1 450 835 4821",
    "sg:postcode":"J0K 2N0",
    "sg:province":"QC",
    "wof:name":"Restaurant Le Mistral Enrg",
    "wof:placetype":"venue"
},
  "geometry": {"coordinates":[-73.3752288818,46.2973442078],"type":"Point"}
}