{
  "type": "Feature",
  "properties": {
    "addr:full":"5072 Joyce St Vancouver BC V5R 4G6",
    "addr:housenumber":"5072",
    "addr:postcode":"v5r 4g6",
    "addr:street":"Joyce St",
    "iso:country":"CA",
    "sg:address":"5072 Joyce St",
    "sg:city":"Vancouver",
    "sg:classifiers":[
        {
            "category":"Restaurant",
            "type":"Food & Drink"
        }
    ],
    "sg:phone":"+1 604 436 4217",
    "sg:postcode":"V5R 4G6",
    "sg:province":"BC",
    "wof:name":"May Cafe",
    "wof:placetype":"venue"
},
  "geometry": {"coordinates":[-123.03134900000001,49.238544],"type":"Point"}
}