{
  "type": "Feature",
  "properties": {
    "iso:country":"CA",
    "sg:address":"628 Manitou Rd SE",
    "sg:city":"Calgary",
    "sg:classifiers":[
        {
            "category":"Shopping",
            "subcategory":"Bicycles & Sporting Goods",
            "type":"Retail Goods"
        }
    ],
    "sg:phone":"+1 403 277 2166",
    "sg:postcode":"T2G 4C5",
    "sg:province":"AB",
    "sg:tags":[
        "equipment",
        "exercise"
    ],
    "wof:name":"Physique Fitness Store",
    "wof:placetype":"venue"
},
  "geometry": {"coordinates":[-114.051254273,51.0106277466],"type":"Point"}
}