{
  "type": "Feature",
  "properties": {
    "iso:country":"CA",
    "sg:address":"RR 2",
    "sg:city":"Albany",
    "sg:classifiers":[
        {
            "category":"Building & Trades",
            "subcategory":"Construction",
            "type":"Services"
        }
    ],
    "sg:phone":"+1 902 855 2415",
    "sg:postcode":"C0B 1A0",
    "sg:province":"PE",
    "sg:tags":[
        "general",
        "contractor"
    ],
    "wof:name":"Midway Custom Construction",
    "wof:placetype":"venue"
},
  "geometry": {"coordinates":[-63.643021,46.285759],"type":"Point"}
}