{
  "type": "Feature",
  "properties": {
    "addr:full":"248 Manitoba St # 5 Bracebridge ON P1L 2E1",
    "addr:housenumber":"248",
    "addr:postcode":"p1l 2e1",
    "addr:street":"Manitoba St # 5",
    "iso:country":"CA",
    "sg:address":"248 Manitoba St # 5",
    "sg:city":"Bracebridge",
    "sg:classifiers":[
        {
            "category":"Banks & Credit Unions",
            "subcategory":"Bank",
            "type":"Services"
        }
    ],
    "sg:phone":"+1 705 645 2289",
    "sg:postcode":"P1L 2E1",
    "sg:province":"ON",
    "wof:name":"Scotiabank",
    "wof:placetype":"venue"
},
  "geometry": {"coordinates":[-79.31847381590001,45.0449447632],"type":"Point"}
}