{
  "type": "Feature",
  "properties": {
    "addr:full":"2085 Rue Munro Trois-Rivieres QC G8Y 4K4",
    "addr:housenumber":"2085",
    "addr:postcode":"g8y 4k4",
    "addr:street":"Rue Munro Trois-Rivieres",
    "iso:country":"CA",
    "sg:address":"2085 Rue Munro",
    "sg:city":"Trois-Rivieres",
    "sg:classifiers":[
        {
            "category":"Building & Trades",
            "subcategory":"Construction",
            "type":"Services"
        }
    ],
    "sg:phone":"+1 819 372 7815",
    "sg:postcode":"G8Y 4K4",
    "sg:province":"QC",
    "sg:tags":[
        "excavating",
        "contractor"
    ],
    "wof:name":"Excavation Cote",
    "wof:placetype":"venue"
},
  "geometry": {"coordinates":[-72.65439600000001,46.390331],"type":"Point"}
}