{
  "type": "Feature",
  "properties": {
    "addr:full":"2836 Rue Springland Montreal QC H4E 2H1",
    "addr:housenumber":"2836",
    "addr:postcode":"h4e 2h1",
    "addr:street":"Rue Springland",
    "iso:country":"CA",
    "sg:address":"2836 Rue Springland",
    "sg:city":"Montreal",
    "sg:classifiers":[
        {
            "category":"Food & Beverages",
            "subcategory":"Groceries & Convenience Stores",
            "type":"Retail Goods"
        }
    ],
    "sg:phone":"+1 514 767 0574",
    "sg:postcode":"H4E 2H1",
    "sg:province":"QC",
    "wof:name":"Depanneur F Esposito",
    "wof:placetype":"venue"
},
  "geometry": {"coordinates":[-73.59889200000001,45.453079],"type":"Point"}
}