{
  "type": "Feature",
  "properties": {
    "iso:country":"CA",
    "sg:address":"2836 Rue Springland",
    "sg:city":"Montreal",
    "sg:classifiers":[
        {
            "category":"Food & Beverages",
            "subcategory":"Groceries & Convenience Stores",
            "type":"Retail Goods"
        }
    ],
    "sg:phone":"+1 514 767 0574",
    "sg:postcode":"H4E 2H1",
    "sg:province":"QC",
    "wof:name":"Depanneur F Esposito",
    "wof:placetype":"venue"
},
  "geometry": {"coordinates":[-73.598892,45.453079],"type":"Point"}
}