{
  "type": "Feature",
  "properties": {
    "addr:full":"11 Av Rodney Pointe-Claire QC H9R 4L8",
    "addr:postcode":"h9r 4l8",
    "addr:street":"11 Av Rodney",
    "iso:country":"CA",
    "sg:address":"11 Av Rodney",
    "sg:city":"Pointe-Claire",
    "sg:classifiers":[
        {
            "category":"Organizations",
            "subcategory":"Religious Organization",
            "type":"Services"
        }
    ],
    "sg:phone":"+1 514 697 2091",
    "sg:postcode":"H9R 4L8",
    "sg:province":"QC",
    "sg:tags":[
        "church"
    ],
    "wof:name":"St-Columba-By-the-Lake Pres",
    "wof:placetype":"venue"
},
  "geometry": {"coordinates":[-73.7836151123,45.4551048279],"type":"Point"}
}