{
  "type": "Feature",
  "properties": {
    "iso:country":"CA",
    "sg:address":"111 Woodland Dr",
    "sg:city":"Cutler",
    "sg:classifiers":[
        {
            "category":"Food & Beverages",
            "subcategory":"Groceries & Convenience Stores",
            "type":"Retail Goods"
        }
    ],
    "sg:phone":"+1 705 844 2067",
    "sg:postcode":"P0P 1B0",
    "sg:province":"ON",
    "wof:name":"Kenabutch Gas & Convenience",
    "wof:placetype":"venue"
},
  "geometry": {"coordinates":[-82.4797286987,46.2075538635],"type":"Point"}
}