{
  "type": "Feature",
  "properties": {
    "addr:full":"30 Second Hudson ON P0V 1X0",
    "addr:housenumber":"30",
    "addr:postcode":"p0v 1x0",
    "addr:street":"Second Hudson",
    "iso:country":"CA",
    "sg:address":"30 Second",
    "sg:city":"Hudson",
    "sg:classifiers":[
        {
            "category":"Education",
            "subcategory":"School",
            "type":"Public Place"
        }
    ],
    "sg:phone":"+1 807 582 3311",
    "sg:postcode":"P0V 1X0",
    "sg:province":"ON",
    "wof:name":"Hudson Public School",
    "wof:placetype":"venue"
},
  "geometry": {"coordinates":[-92.169304,50.090839],"type":"Point"}
}