{
  "type": "Feature",
  "properties": {
    "iso:country":"CA",
    "sg:address":"2127 Keele St",
    "sg:city":"York",
    "sg:classifiers":[
        {
            "category":"Freight",
            "type":"Transportation"
        }
    ],
    "sg:phone":"+1 416 252 9169",
    "sg:postcode":"M6M 3Z3",
    "sg:province":"ON",
    "sg:tags":[
        "broker",
        "customs"
    ],
    "wof:name":"General Customs Brokers Inc",
    "wof:placetype":"venue"
},
  "geometry": {"coordinates":[-79.47479199999999,43.695213],"type":"Point"}
}