{
  "type": "Feature",
  "properties": {
    "addr:full":"35 Earl St Hamilton ON L8L 6L1",
    "addr:housenumber":"35",
    "addr:postcode":"l8l 6l1",
    "addr:street":"Earl St",
    "iso:country":"CA",
    "sg:address":"35 Earl St",
    "sg:city":"Hamilton",
    "sg:classifiers":[
        {
            "category":"Wholesale",
            "subcategory":"Vending Machines",
            "type":"Manufacturing & Wholesale Goods"
        }
    ],
    "sg:phone":"+1 905 543 0606",
    "sg:postcode":"L8L 6L1",
    "sg:province":"ON",
    "wof:name":"Vendal Dundas Ltd",
    "wof:placetype":"venue"
},
  "geometry": {"coordinates":[-79.8372497559,43.2579269409],"type":"Point"}
}