{
  "type": "Feature",
  "properties": {
    "addr:full":"980 Westminster Dr S Cambridge ON N3H 1V2",
    "addr:housenumber":"980",
    "addr:postcode":"n3h 1v2",
    "addr:street":"Westminster Dr S",
    "iso:country":"CA",
    "sg:address":"980 Westminster Dr S",
    "sg:city":"Cambridge",
    "sg:classifiers":[
        {
            "category":"Education",
            "subcategory":"School",
            "type":"Public Place"
        }
    ],
    "sg:phone":"+1 519 653 4482",
    "sg:postcode":"N3H 1V2",
    "sg:province":"ON",
    "wof:name":"St Joseph School",
    "wof:placetype":"venue"
},
  "geometry": {"coordinates":[-80.36634100000001,43.388592],"type":"Point"}
}