{
  "type": "Feature",
  "properties": {
    "addr:full":"4416 Bath Rd Amherstview ON K7N 1A2",
    "addr:housenumber":"4416",
    "addr:postcode":"k7n 1a2",
    "addr:street":"Bath Rd",
    "iso:country":"CA",
    "sg:address":"4416 Bath Rd",
    "sg:city":"Amherstview",
    "sg:classifiers":[
        {
            "category":"Wholesale",
            "subcategory":"Machinery & Supplies",
            "type":"Manufacturing & Wholesale Goods"
        }
    ],
    "sg:phone":"+1 613 389 6211",
    "sg:postcode":"K7N 1A2",
    "sg:province":"ON",
    "sg:tags":[
        "machine",
        "shredding",
        "paper"
    ],
    "wof:name":"Allied Office Suppliers",
    "wof:placetype":"venue"
},
  "geometry": {"coordinates":[-76.634888,44.221134],"type":"Point"}
}