{
  "type": "Feature",
  "properties": {
    "addr:full":"634 Victoria St Strathroy ON N7G 3C1",
    "addr:housenumber":"634",
    "addr:postcode":"n7g 3c1",
    "addr:street":"Victoria St",
    "iso:country":"CA",
    "sg:address":"634 Victoria St",
    "sg:city":"Strathroy",
    "sg:classifiers":[
        {
            "category":"Restaurant",
            "type":"Food & Drink"
        }
    ],
    "sg:phone":"+1 519 245 8666",
    "sg:postcode":"N7G 3C1",
    "sg:province":"ON",
    "wof:name":"New Orleans Pizza",
    "wof:placetype":"venue"
},
  "geometry": {"coordinates":[-81.63104199999999,42.967361],"type":"Point"}
}