{
  "type": "Feature",
  "properties": {
    "addr:full":"1107 Rue Hyman Dollard-Des-Ormeaux QC H9B 1M5",
    "addr:housenumber":"1107",
    "addr:postcode":"h9b 1m5",
    "addr:street":"Rue Hyman",
    "iso:country":"CA",
    "sg:address":"1107 Rue Hyman",
    "sg:city":"Dollard-Des-Ormeaux",
    "sg:classifiers":[
        {
            "category":"Health Services",
            "subcategory":"Doctor",
            "type":"Services"
        }
    ],
    "sg:phone":"+1 514 683 4155",
    "sg:postcode":"H9B 1M5",
    "sg:province":"QC",
    "sg:tags":[
        "dentist"
    ],
    "wof:name":"Lord, Charles DDS",
    "wof:placetype":"venue"
},
  "geometry": {"coordinates":[-73.78499603269999,45.4977226257],"type":"Point"}
}