{
  "type": "Feature",
  "properties": {
    "addr:full":"Brandon MB R7A 5C2",
    "addr:postcode":"r7a 5c2",
    "iso:country":"CA",
    "sg:city":"Brandon",
    "sg:classifiers":[
        {
            "category":"Autos & Motor Vehicles",
            "subcategory":"Auto Supplies",
            "type":"Retail Goods"
        }
    ],
    "sg:phone":"+1 204 727 7181",
    "sg:postcode":"R7A 5C2",
    "sg:province":"MB",
    "sg:tags":[
        "battery"
    ],
    "wof:name":"Prairie Battery",
    "wof:placetype":"venue"
},
  "geometry": {"coordinates":[-99.96219600000001,49.832546],"type":"Point"}
}