{
  "type": "Feature",
  "properties": {
    "addr:full":"1050 Boul Saint-Laurent Montreal QC H2Z 1J5",
    "addr:housenumber":"1050",
    "addr:postcode":"h2z 1j5",
    "addr:street":"Boul Saint-Laurent",
    "iso:country":"CA",
    "sg:address":"1050 Boul Saint-Laurent",
    "sg:city":"Montreal",
    "sg:classifiers":[
        {
            "category":"Food & Beverages",
            "subcategory":"Groceries & Convenience Stores",
            "type":"Retail Goods"
        }
    ],
    "sg:phone":"+1 514 866 8110",
    "sg:postcode":"H2Z 1J5",
    "sg:province":"QC",
    "sg:tags":[
        "grocer"
    ],
    "wof:name":"Sung Hing",
    "wof:placetype":"venue"
},
  "geometry": {"coordinates":[-73.5602111816,45.5081138611],"type":"Point"}
}