{
  "type": "Feature",
  "properties": {
    "addr:full":"3200 Boul Pitfield Saint-Laurent QC H4S 1K6",
    "addr:housenumber":"3200",
    "addr:postcode":"h4s 1k6",
    "addr:street":"Boul Pitfield",
    "iso:country":"CA",
    "sg:address":"3200 Boul Pitfield",
    "sg:city":"Saint-Laurent",
    "sg:classifiers":[
        {
            "category":"Professional",
            "type":"Services"
        }
    ],
    "sg:phone":"+1 514 337 6000",
    "sg:postcode":"H4S 1K6",
    "sg:province":"QC",
    "sg:tags":[
        "dry",
        "establishment",
        "ice"
    ],
    "wof:name":"Liquid Carbonic Inc",
    "wof:placetype":"venue"
},
  "geometry": {"coordinates":[-73.75003100000001,45.498207],"type":"Point"}
}