{
  "type": "Feature",
  "properties": {
    "addr:full":"10550 Av Pelletier Montreal-Nord QC H1H 3R5",
    "addr:housenumber":"10550",
    "addr:postcode":"h1h 3r5",
    "addr:street":"Av Pelletier",
    "iso:country":"CA",
    "sg:address":"10550 Av Pelletier",
    "sg:city":"Montreal-Nord",
    "sg:classifiers":[
        {
            "category":"Education",
            "subcategory":"School",
            "type":"Public Place"
        }
    ],
    "sg:phone":"+1 514 321 9551",
    "sg:postcode":"H1H 3R5",
    "sg:province":"QC",
    "wof:name":"Ecole Michelet Inc",
    "wof:placetype":"venue"
},
  "geometry": {"coordinates":[-73.6308441162,45.5897026062],"type":"Point"}
}