{
  "type": "Feature",
  "properties": {
    "addr:full":"1 Mississauga Manitouwadge ON P0T 2C0",
    "addr:housenumber":"1",
    "addr:postcode":"p0t 2c0",
    "iso:country":"CA",
    "sg:address":"1 Mississauga",
    "sg:city":"Manitouwadge",
    "sg:classifiers":[
        {
            "category":"Government",
            "subcategory":"Fire Station",
            "type":"Public Place"
        }
    ],
    "sg:phone":"+1 ",
    "sg:postcode":"P0T 2C0",
    "sg:province":"ON",
    "sg:tags":[
        "department"
    ],
    "wof:name":"Manitouwadge Fire Dept",
    "wof:placetype":"venue"
},
  "geometry": {"coordinates":[-85.830551,49.125607],"type":"Point"}
}