{
  "type": "Feature",
  "properties": {
    "addr:full":"2410 Aviation Lane London ON N5V 3Z9",
    "addr:housenumber":"2410",
    "addr:postcode":"n5v 3z9",
    "addr:street":"Aviation Lane",
    "iso:country":"CA",
    "sg:address":"2410 Aviation Lane",
    "sg:city":"London",
    "sg:classifiers":[
        {
            "category":"Airport",
            "type":"Transportation"
        }
    ],
    "sg:phone":"+1 519 453 1222",
    "sg:postcode":"N5V 3Z9",
    "sg:province":"ON",
    "sg:tags":[
        "rental",
        "aircraft",
        "leasing",
        "charter",
        "maintenance"
    ],
    "wof:name":"Air London",
    "wof:placetype":"venue"
},
  "geometry": {"coordinates":[-81.156677,43.031319],"type":"Point"}
}