{
  "type": "Feature",
  "properties": {
    "addr:full":"10361 Boul Gouin O Roxboro QC H8Y 1S1",
    "addr:housenumber":"10361",
    "addr:postcode":"h8y 1s1",
    "addr:street":"Boul Gouin O",
    "iso:country":"CA",
    "sg:address":"10361 Boul Gouin O",
    "sg:city":"Roxboro",
    "sg:classifiers":[
        {
            "category":"Retail",
            "subcategory":"Auto Repair",
            "type":"Services"
        }
    ],
    "sg:phone":"+1 514 683 1146",
    "sg:postcode":"H8Y 1S1",
    "sg:province":"QC",
    "sg:tags":[
        "muffler",
        "exhaust",
        "system"
    ],
    "wof:name":"Silencieux G & L Roxboro Inc",
    "wof:placetype":"venue"
},
  "geometry": {"coordinates":[-73.80658,45.509548],"type":"Point"}
}