{
  "type": "Feature",
  "properties": {
    "addr:full":"2238 Western Rd Bloomfield Station PE C0B 1E0",
    "addr:housenumber":"2238",
    "addr:postcode":"c0b 1e0",
    "addr:street":"Western Rd",
    "iso:country":"CA",
    "sg:address":"2238 Western Rd",
    "sg:city":"Bloomfield Station",
    "sg:classifiers":[
        {
            "category":"Restaurant",
            "type":"Food & Drink"
        }
    ],
    "sg:phone":"+1 902 859 1861",
    "sg:postcode":"C0B 1E0",
    "sg:province":"PE",
    "sg:tags":[
        "shop",
        "coffee"
    ],
    "wof:name":"Bakin' Donuts Ltd",
    "wof:placetype":"venue"
},
  "geometry": {"coordinates":[-64.235153,46.776337],"type":"Point"}
}