{
  "type": "Feature",
  "properties": {
    "addr:full":"96081 Road 13E Teulon MB R0C 3B0",
    "addr:housenumber":"96081;13e",
    "addr:postcode":"teulon;r0c 3b0",
    "addr:street":"Road",
    "iso:country":"CA",
    "sg:address":"96081 Road 13E",
    "sg:city":"Teulon",
    "sg:classifiers":[
        {
            "category":"Education",
            "subcategory":"School",
            "type":"Public Place"
        }
    ],
    "sg:phone":"+1 204 886 3327",
    "sg:postcode":"R0C 3B0",
    "sg:province":"MB",
    "wof:name":"Omega School",
    "wof:placetype":"venue"
},
  "geometry": {"coordinates":[-97.26309204099999,50.3857460022],"type":"Point"}
}