{
  "type": "Feature",
  "properties": {
    "addr:full":"Shubenacadie NS B0N 2H0",
    "addr:postcode":"b0n 2h0",
    "iso:country":"CA",
    "sg:city":"Shubenacadie",
    "sg:classifiers":[
        {
            "category":"Autos & Motor Vehicles",
            "subcategory":"Fuel & Gas Station",
            "type":"Retail Goods"
        }
    ],
    "sg:phone":"+1 902 758 2659",
    "sg:postcode":"B0N 2H0",
    "sg:province":"NS",
    "sg:tags":[
        "oil"
    ],
    "wof:name":"Shane's Service Ctr Ltd",
    "wof:placetype":"venue"
},
  "geometry": {"coordinates":[-63.4074325562,45.0872535706],"type":"Point"}
}