{
  "type": "Feature",
  "properties": {
    "addr:full":"52 Rue Robillard Notre-Dame-Des-Prairies QC J6E 1J2",
    "addr:housenumber":"52",
    "addr:postcode":"j6e 1j2",
    "addr:street":"Rue Robillard",
    "iso:country":"CA",
    "sg:address":"52 Rue Robillard",
    "sg:city":"Notre-Dame-Des-Prairies",
    "sg:classifiers":[
        {
            "category":"Personal",
            "subcategory":"Beauty Salon",
            "type":"Services"
        }
    ],
    "sg:phone":"+1 450 759 3210",
    "sg:postcode":"J6E 1J2",
    "sg:province":"QC",
    "wof:name":"Salon DE Coiffure Retro",
    "wof:placetype":"venue"
},
  "geometry": {"coordinates":[-73.42315673829999,46.0436592102],"type":"Point"}
}