{
  "type": "Feature",
  "properties": {
    "addr:full":"6307 Boul Monk Montreal QC H4E 3H8",
    "addr:housenumber":"6307",
    "addr:postcode":"h4e 3h8",
    "addr:street":"Boul Monk",
    "iso:country":"CA",
    "sg:address":"6307 Boul Monk",
    "sg:city":"Montreal",
    "sg:classifiers":[
        {
            "category":"Shopping",
            "type":"Retail Goods"
        }
    ],
    "sg:phone":"+1 514 762 9349",
    "sg:postcode":"H4E 3H8",
    "sg:province":"QC",
    "sg:tags":[
        "picture",
        "frame"
    ],
    "wof:name":"Centre-Laminage & D'Encdrmnt",
    "wof:placetype":"venue"
},
  "geometry": {"coordinates":[-73.5951080322,45.4555053711],"type":"Point"}
}