{
  "type": "Feature",
  "properties": {
    "addr:full":"2221 Rue Fleury E Montreal QC H2B 1K5",
    "addr:housenumber":"2221",
    "addr:postcode":"h2b 1k5",
    "addr:street":"Rue Fleury E",
    "iso:country":"CA",
    "sg:address":"2221 Rue Fleury E",
    "sg:city":"Montreal",
    "sg:classifiers":[
        {
            "category":"Food & Beverages",
            "subcategory":"Groceries & Convenience Stores",
            "type":"Retail Goods"
        }
    ],
    "sg:phone":"+1 514 381 5241",
    "sg:postcode":"H2B 1K5",
    "sg:province":"QC",
    "sg:tags":[
        "grocer"
    ],
    "wof:name":"Depanneur Pr Sigouin",
    "wof:placetype":"venue"
},
  "geometry": {"coordinates":[-73.65001700000001,45.572861],"type":"Point"}
}