{
  "type": "Feature",
  "properties": {
    "addr:full":"743 Laidlaw Cres Kingston ON K7M 5M3",
    "addr:housenumber":"743",
    "addr:postcode":"k7m 5m3",
    "addr:street":"Laidlaw Cres",
    "iso:country":"CA",
    "sg:address":"743 Laidlaw Cres",
    "sg:city":"Kingston",
    "sg:classifiers":[
        {
            "category":"Manufacturing",
            "subcategory":"Musical Instruments",
            "type":"Manufacturing & Wholesale Goods"
        }
    ],
    "sg:phone":"+1 613 389 8780",
    "sg:postcode":"K7M 5M3",
    "sg:province":"ON",
    "wof:name":"Violin Workshop",
    "wof:placetype":"venue"
},
  "geometry": {"coordinates":[-76.58717346189999,44.2470283508],"type":"Point"}
}