{
  "type": "Feature",
  "properties": {
    "addr:full":"PO Box 450 Arviat NU X0C 0E0",
    "addr:housenumber":"po",
    "addr:postcode":"x0c 0e0",
    "addr:street":"Box 450",
    "iso:country":"CA",
    "sg:address":"PO Box 450",
    "sg:city":"Arviat",
    "sg:classifiers":[
        {
            "category":"Education",
            "subcategory":"School",
            "type":"Public Place"
        }
    ],
    "sg:phone":"+1 867 857 2778",
    "sg:postcode":"X0C 0E0",
    "sg:province":"NU",
    "wof:name":"Qitqliq Secondary School",
    "wof:placetype":"venue"
},
  "geometry": {"coordinates":[-94.058998,61.109707],"type":"Point"}
}