{
  "type": "Feature",
  "properties": {
    "addr:full":"476 Main St Shawville QC J0X 2Y0",
    "addr:housenumber":"476",
    "addr:postcode":"j0x 2y0",
    "addr:street":"Main St",
    "iso:country":"CA",
    "sg:address":"476 Main St",
    "sg:city":"Shawville",
    "sg:phone":"+1 819 647 3831",
    "sg:postcode":"J0X 2Y0",
    "sg:province":"QC",
    "sg:tags":[
        "oil"
    ],
    "wof:name":"Shawville Milling CO Ltd",
    "wof:placetype":"venue"
},
  "geometry": {"coordinates":[-76.49603999999999,45.605469],"type":"Point"}
}