{
  "type": "Feature",
  "properties": {
    "addr:full":"302 Corrigan Rd Lampman SK S0C 1N0",
    "addr:housenumber":"302",
    "addr:postcode":"s0c 1n0",
    "addr:street":"Corrigan Rd",
    "iso:country":"CA",
    "sg:address":"302 Corrigan Rd",
    "sg:city":"Lampman",
    "sg:classifiers":[
        {
            "category":"Organizations",
            "subcategory":"Religious Organization",
            "type":"Services"
        }
    ],
    "sg:phone":"+1 306 487 2497",
    "sg:postcode":"S0C 1N0",
    "sg:province":"SK",
    "sg:tags":[
        "church"
    ],
    "wof:name":"Catholic Church Rectory",
    "wof:placetype":"venue"
},
  "geometry": {"coordinates":[-102.764145,49.377258],"type":"Point"}
}