{
  "type": "Feature",
  "properties": {
    "iso:country":"CA",
    "sg:address":"1118 3rd St E",
    "sg:city":"North Vancouver",
    "sg:classifiers":[
        {
            "category":"Retail",
            "subcategory":"Auto Repair",
            "type":"Services"
        }
    ],
    "sg:phone":"+1 604 980 4542",
    "sg:postcode":"V7J 1B8",
    "sg:province":"BC",
    "sg:tags":[
        "repairing",
        "automobile"
    ],
    "wof:name":"Scan Automotive Inc",
    "wof:placetype":"venue"
},
  "geometry": {"coordinates":[-123.04576873800001,49.3083381653],"type":"Point"}
}