{
  "type": "Feature",
  "properties": {
    "iso:country":"CA",
    "sg:address":"325 107E Rue",
    "sg:city":"Saint-Georges",
    "sg:classifiers":[
        {
            "category":"Autos & Motor Vehicles",
            "subcategory":"Auto Supplies",
            "type":"Retail Goods"
        }
    ],
    "sg:phone":"+1 418 228 8817",
    "sg:postcode":"G5Y 3J8",
    "sg:province":"QC",
    "sg:tags":[
        "automobile",
        "parts"
    ],
    "wof:name":"Beauce Auto Accessoires Ltee",
    "wof:placetype":"venue"
},
  "geometry": {"coordinates":[-70.6845626831,46.1258811951],"type":"Point"}
}