{
  "type": "Feature",
  "properties": {
    "iso:country":"CA",
    "sg:city":"Kingston",
    "sg:classifiers":[
        {
            "category":"Health Services",
            "subcategory":"Chiropractor",
            "type":"Services"
        }
    ],
    "sg:phone":"+1 613 542 5802",
    "sg:postcode":"K7M 3E1",
    "sg:province":"ON",
    "wof:name":"Peach Tree Family Chiropractic",
    "wof:placetype":"venue"
},
  "geometry": {"coordinates":[-76.5218887329,44.2461662292],"type":"Point"}
}