{
  "type": "Feature",
  "properties": {
    "addr:full":"Scarborough ON M1H 1H5",
    "addr:postcode":"m1h 1h5",
    "iso:country":"CA",
    "sg:city":"Scarborough",
    "sg:classifiers":[
        {
            "category":"Wholesale",
            "subcategory":"Machinery & Supplies",
            "type":"Manufacturing & Wholesale Goods"
        }
    ],
    "sg:phone":"+1 416 289 0042",
    "sg:postcode":"M1H 1H5",
    "sg:province":"ON",
    "sg:tags":[
        "equipment",
        "screen",
        "printing"
    ],
    "wof:name":"Applied Stretch Tech Ltd",
    "wof:placetype":"venue"
},
  "geometry": {"coordinates":[-79.24279799999999,43.77795],"type":"Point"}
}