{
  "type": "Feature",
  "properties": {
    "addr:full":"5215 Rue DE LA Savane Montreal QC H4P 1V4",
    "addr:housenumber":"5215",
    "addr:postcode":"h4p 1v4",
    "addr:street":"Rue De La Savane",
    "iso:country":"CA",
    "sg:address":"5215 Rue DE LA Savane",
    "sg:city":"Montreal",
    "sg:classifiers":[
        {
            "category":"Professional",
            "type":"Services"
        }
    ],
    "sg:phone":"+1 514 738 4212",
    "sg:postcode":"H4P 1V4",
    "sg:province":"QC",
    "sg:tags":[
        "equipment",
        "computer",
        "establishment",
        "dealer"
    ],
    "wof:name":"Canadien Data",
    "wof:placetype":"venue"
},
  "geometry": {"coordinates":[-73.659149,45.499405],"type":"Point"}
}