{
  "type": "Feature",
  "properties": {
    "iso:country":"CA",
    "sg:address":"89 Greengable Way",
    "sg:city":"Kitchener",
    "sg:classifiers":[
        {
            "category":"Shopping",
            "subcategory":"Used Merchandise",
            "type":"Retail Goods"
        }
    ],
    "sg:phone":"+1 519 744 4463",
    "sg:postcode":"N2N 3B1",
    "sg:province":"ON",
    "sg:tags":[
        "antique"
    ],
    "wof:name":"Pioneer Tower Antiques",
    "wof:placetype":"venue"
},
  "geometry": {"coordinates":[-80.54435,43.434883],"type":"Point"}
}