{
  "type": "Feature",
  "properties": {
    "addr:full":"Wendover ON K0A 3K0",
    "addr:postcode":"k0a 3k0",
    "iso:country":"CA",
    "sg:city":"Wendover",
    "sg:classifiers":[
        {
            "category":"Mining & Drilling",
            "type":"Manufacturing & Wholesale Goods"
        }
    ],
    "sg:phone":"+1 613 673 2377",
    "sg:postcode":"K0A 3K0",
    "sg:province":"ON",
    "sg:tags":[
        "quarry"
    ],
    "wof:name":"Bertrand Construction",
    "wof:placetype":"venue"
},
  "geometry": {"coordinates":[-75.0822982788,45.559928894],"type":"Point"}
}