{
  "type": "Feature",
  "properties": {
    "addr:full":"515 Goderich St Port Elgin ON N0H 2C4",
    "addr:housenumber":"515",
    "addr:postcode":"n0h 2c4",
    "addr:street":"Goderich St",
    "iso:country":"CA",
    "sg:address":"515 Goderich St",
    "sg:city":"Port Elgin",
    "sg:classifiers":[
        {
            "category":"Manufacturing",
            "subcategory":"Printing",
            "type":"Manufacturing & Wholesale Goods"
        }
    ],
    "sg:phone":"+1 519 832 2002",
    "sg:postcode":"N0H 2C4",
    "sg:province":"ON",
    "sg:tags":[
        "printer"
    ],
    "wof:name":"Wired Mouse",
    "wof:placetype":"venue"
},
  "geometry": {"coordinates":[-81.39063299999999,44.433716],"type":"Point"}
}