{
  "type": "Feature",
  "properties": {
    "iso:country":"CA",
    "sg:address":"3453 Boul Saint-Martin O",
    "sg:city":"Laval",
    "sg:classifiers":[
        {
            "category":"Restaurant",
            "type":"Food & Drink"
        }
    ],
    "sg:phone":"+1 450 680 1691",
    "sg:postcode":"H7T 1A2",
    "sg:province":"QC",
    "wof:name":"Cafe Univers",
    "wof:placetype":"venue"
},
  "geometry": {"coordinates":[-73.750397,45.556164],"type":"Point"}
}