{
  "type": "Feature",
  "properties": {
    "addr:full":"7 Clark St Welland ON L3B 5W6",
    "addr:housenumber":"7",
    "addr:postcode":"l3b 5w6",
    "addr:street":"Clark St",
    "iso:country":"CA",
    "sg:address":"7 Clark St",
    "sg:city":"Welland",
    "sg:classifiers":[
        {
            "category":"Wholesale",
            "subcategory":"Machinery & Supplies",
            "type":"Manufacturing & Wholesale Goods"
        }
    ],
    "sg:phone":"+1 905 735 1542",
    "sg:postcode":"L3B 5W6",
    "sg:province":"ON",
    "sg:tags":[
        "rental"
    ],
    "wof:name":"Welland Equipment Rentals Ltd",
    "wof:placetype":"venue"
},
  "geometry": {"coordinates":[-79.26128387449999,42.9636116028],"type":"Point"}
}