{
  "type": "Feature",
  "properties": {
    "addr:full":"1726 Rue Berlier Laval QC H7L 4A1",
    "addr:housenumber":"1726",
    "addr:postcode":"h7l 4a1",
    "addr:street":"Rue Berlier",
    "iso:country":"CA",
    "sg:address":"1726 Rue Berlier",
    "sg:city":"Laval",
    "sg:classifiers":[
        {
            "category":"Retail",
            "subcategory":"Auto Repair",
            "type":"Services"
        }
    ],
    "sg:phone":"+1 450 973 8819",
    "sg:postcode":"H7L 4A1",
    "sg:province":"QC",
    "sg:tags":[
        "body",
        "automobile",
        "painting"
    ],
    "wof:name":"Auto Tech",
    "wof:placetype":"venue"
},
  "geometry": {"coordinates":[-73.744331,45.584015],"type":"Point"}
}