{
  "type": "Feature",
  "properties": {
    "addr:full":"699 Ash St Winnipeg MB R3N 0R5",
    "addr:housenumber":"699",
    "addr:postcode":"r3n 0r5",
    "addr:street":"Ash St",
    "iso:country":"CA",
    "sg:address":"699 Ash St",
    "sg:city":"Winnipeg",
    "sg:classifiers":[
        {
            "category":"Professional",
            "subcategory":"Management & Consulting",
            "type":"Services"
        }
    ],
    "sg:phone":"+1 204 489 9755",
    "sg:postcode":"R3N 0R5",
    "sg:province":"MB",
    "sg:tags":[
        "consultant",
        "business"
    ],
    "wof:name":"Ocean Tides Performance Group",
    "wof:placetype":"venue"
},
  "geometry": {"coordinates":[-97.1839141846,49.8582954407],"type":"Point"}
}