{
  "type": "Feature",
  "properties": {
    "addr:full":"742 Broadview Ave Toronto ON M4K 2P1",
    "addr:housenumber":"742",
    "addr:postcode":"m4k 2p1",
    "addr:street":"Broadview Ave",
    "iso:country":"CA",
    "sg:address":"742 Broadview Ave",
    "sg:city":"Toronto",
    "sg:classifiers":[
        {
            "category":"Personal",
            "subcategory":"Beauty Salon",
            "type":"Services"
        }
    ],
    "sg:phone":"+1 416 469 2006",
    "sg:postcode":"M4K 2P1",
    "sg:province":"ON",
    "wof:name":"Johns Barber Salon",
    "wof:placetype":"venue"
},
  "geometry": {"coordinates":[-79.35861199999999,43.675705],"type":"Point"}
}