{
  "type": "Feature",
  "properties": {
    "addr:full":"11301 100 Ave Grande Prairie AB T8V 5M6",
    "addr:housenumber":"11301",
    "addr:postcode":"t8v 5m6",
    "addr:street":"100 Ave",
    "iso:country":"CA",
    "sg:address":"11301 100 Ave",
    "sg:city":"Grande Prairie",
    "sg:classifiers":[
        {
            "category":"Travel",
            "subcategory":"Hotels & Motels",
            "type":"Entertainment"
        }
    ],
    "sg:phone":"+1 780 532 4100",
    "sg:postcode":"T8V 5M6",
    "sg:province":"AB",
    "wof:name":"Westport Inn",
    "wof:placetype":"venue"
},
  "geometry": {"coordinates":[-118.83797454800001,55.170375824],"type":"Point"}
}