{
  "type": "Feature",
  "properties": {
    "iso:country":"CA",
    "sg:address":"131 Easson St",
    "sg:city":"Stratford",
    "sg:classifiers":[
        {
            "category":"Organizations",
            "subcategory":"Religious Organization",
            "type":"Services"
        }
    ],
    "sg:phone":"+1 519 273 1162",
    "sg:postcode":"N5A 1N4",
    "sg:province":"ON",
    "sg:tags":[
        "church"
    ],
    "wof:name":"Faith Bible Church",
    "wof:placetype":"venue"
},
  "geometry": {"coordinates":[-80.9957199097,43.3643608093],"type":"Point"}
}