{
  "type": "Feature",
  "properties": {
    "addr:full":"Brampton ON L6V 4A4",
    "addr:postcode":"l6v 4a4",
    "iso:country":"CA",
    "sg:city":"Brampton",
    "sg:classifiers":[
        {
            "category":"Banks & Credit Unions",
            "subcategory":"Bank",
            "type":"Services"
        }
    ],
    "sg:phone":"+1 905 453 4547",
    "sg:postcode":"L6V 4A4",
    "sg:province":"ON",
    "sg:tags":[
        "loan",
        "real estate"
    ],
    "wof:name":"Citi Financial Canada Inc",
    "wof:placetype":"venue"
},
  "geometry": {"coordinates":[-79.771233,43.694504],"type":"Point"}
}