{
  "type": "Feature",
  "properties": {
    "addr:full":"3500 Pipeline Rd West St Paul MB R4A 7A9",
    "addr:housenumber":"3500",
    "addr:postcode":"r4a 7a9",
    "addr:street":"Pipeline Rd",
    "iso:country":"CA",
    "sg:address":"3500 Pipeline Rd",
    "sg:city":"West St Paul",
    "sg:classifiers":[
        {
            "category":"Retail",
            "subcategory":"Auto Repair",
            "type":"Services"
        }
    ],
    "sg:phone":"+1 204 338 8581",
    "sg:postcode":"R4A 7A9",
    "sg:province":"MB",
    "sg:tags":[
        "exchanging",
        "engine"
    ],
    "wof:name":"Turbo Automotive",
    "wof:placetype":"venue"
},
  "geometry": {"coordinates":[-97.1611709595,50.0226325989],"type":"Point"}
}