{
  "type": "Feature",
  "properties": {
    "addr:full":"Main St Marys Harbour NL A0K 3P0",
    "addr:postcode":"a0k 3p0",
    "addr:street":"Main St",
    "iso:country":"CA",
    "sg:address":"Main St",
    "sg:city":"Marys Harbour",
    "sg:classifiers":[
        {
            "category":"Food & Beverages",
            "subcategory":"Groceries & Convenience Stores",
            "type":"Retail Goods"
        }
    ],
    "sg:phone":"+1 709 921 6915",
    "sg:postcode":"A0K 3P0",
    "sg:province":"NL",
    "sg:tags":[
        "grocer"
    ],
    "wof:name":"S & R Variety",
    "wof:placetype":"venue"
},
  "geometry": {"coordinates":[-57.988827,48.957024],"type":"Point"}
}