{
  "type": "Feature",
  "properties": {
    "addr:full":"Tecumseh ON N8N 2L9",
    "addr:postcode":"n8n 2l9",
    "iso:country":"CA",
    "sg:city":"Tecumseh",
    "sg:classifiers":[
        {
            "category":"Building & Trades",
            "subcategory":"Construction",
            "type":"Services"
        }
    ],
    "sg:phone":"+1 519 727 4567",
    "sg:postcode":"N8N 2L9",
    "sg:province":"ON",
    "sg:tags":[
        "fire",
        "restoration",
        "damage",
        "painter"
    ],
    "wof:name":"Service Master of Windsor",
    "wof:placetype":"venue"
},
  "geometry": {"coordinates":[-82.823662,42.304077],"type":"Point"}
}