{
  "type": "Feature",
  "properties": {
    "addr:full":"Abbotsford BC V2T 3S4",
    "addr:postcode":"v2t 3s4",
    "iso:country":"CA",
    "sg:city":"Abbotsford",
    "sg:classifiers":[
        {
            "category":"Shopping",
            "subcategory":"Pharmacy",
            "type":"Retail Goods"
        }
    ],
    "sg:phone":"+1 604 852 4466",
    "sg:postcode":"V2T 3S4",
    "sg:province":"BC",
    "wof:name":"Clearbrook Pharmacy Ltd",
    "wof:placetype":"venue"
},
  "geometry": {"coordinates":[-122.33570899999999,49.049793],"type":"Point"}
}