{
  "type": "Feature",
  "properties": {
    "addr:full":"Waverley Oxford NS B0M 1P0",
    "addr:postcode":"b0m 1p0",
    "iso:country":"CA",
    "sg:address":"Waverley",
    "sg:city":"Oxford",
    "sg:classifiers":[
        {
            "category":"Organizations",
            "subcategory":"Religious Organization",
            "type":"Services"
        }
    ],
    "sg:phone":"+1 902 447 2449",
    "sg:postcode":"B0M 1P0",
    "sg:province":"NS",
    "sg:tags":[
        "church"
    ],
    "wof:name":"Oxford Gospel Hall",
    "wof:placetype":"venue"
},
  "geometry": {"coordinates":[-63.8678245544,45.7359542847],"type":"Point"}
}