{
  "type": "Feature",
  "properties": {
    "addr:full":"181 Front St New Dundee ON N0B 2E0",
    "addr:housenumber":"181",
    "addr:postcode":"n0b 2e0",
    "addr:street":"Front St",
    "iso:country":"CA",
    "sg:address":"181 Front St",
    "sg:city":"New Dundee",
    "sg:classifiers":[
        {
            "category":"Personal",
            "subcategory":"Beauty Salon",
            "type":"Services"
        }
    ],
    "sg:phone":"+1 519 696 2115",
    "sg:postcode":"N0B 2E0",
    "sg:province":"ON",
    "wof:name":"Scissors",
    "wof:placetype":"venue"
},
  "geometry": {"coordinates":[-80.5356140137,43.351650238],"type":"Point"}
}