{
  "type": "Feature",
  "properties": {
    "addr:full":"20 Regina St S Waterloo ON N2J 4W9",
    "addr:housenumber":"20",
    "addr:postcode":"n2j 4w9",
    "addr:street":"Regina St S",
    "iso:country":"CA",
    "sg:address":"20 Regina St S",
    "sg:city":"Waterloo",
    "sg:classifiers":[
        {
            "category":"Shopping",
            "subcategory":"Clothing, Apparel, & Fashions",
            "type":"Retail Goods"
        }
    ],
    "sg:phone":"+1 519 885 5657",
    "sg:postcode":"N2J 4W9",
    "sg:province":"ON",
    "sg:tags":[
        "tailor"
    ],
    "wof:name":"Pace John Master Tailor",
    "wof:placetype":"venue"
},
  "geometry": {"coordinates":[-80.52095799999999,43.464642],"type":"Point"}
}