{
  "type": "Feature",
  "properties": {
    "iso:country":"CA",
    "sg:address":"20 Regina St S",
    "sg:city":"Waterloo",
    "sg:classifiers":[
        {
            "category":"Shopping",
            "subcategory":"Clothing, Apparel, & Fashions",
            "type":"Retail Goods"
        }
    ],
    "sg:phone":"+1 519 885 5657",
    "sg:postcode":"N2J 4W9",
    "sg:province":"ON",
    "sg:tags":[
        "tailor"
    ],
    "wof:name":"Pace John Master Tailor",
    "wof:placetype":"venue"
},
  "geometry": {"coordinates":[-80.520958,43.464642],"type":"Point"}
}