{
  "type": "Feature",
  "properties": {
    "iso:country":"CA",
    "sg:address":"5827 Rue Foster",
    "sg:city":"Waterloo",
    "sg:classifiers":[
        {
            "category":"Local Transit",
            "type":"Transportation"
        }
    ],
    "sg:phone":"+1 450 539 4711",
    "sg:postcode":"J0E 2N0",
    "sg:province":"QC",
    "sg:tags":[
        "handicapped"
    ],
    "wof:name":"Transport Adapte Pour Nous Inc",
    "wof:placetype":"venue"
},
  "geometry": {"coordinates":[-72.5161437988,45.3490066528],"type":"Point"}
}