{
  "type": "Feature",
  "properties": {
    "addr:full":"1207 Rte 335 Middle West Pubnico NS B0W 2M0",
    "addr:housenumber":"1207",
    "addr:postcode":"b0w 2m0",
    "addr:street":"Rte 335",
    "iso:country":"CA",
    "sg:address":"1207 Rte 335",
    "sg:city":"Middle West Pubnico",
    "sg:classifiers":[
        {
            "category":"Travel",
            "subcategory":"Hotels & Motels",
            "type":"Entertainment"
        }
    ],
    "sg:phone":"+1 902 762 3388",
    "sg:postcode":"B0W 2M0",
    "sg:province":"NS",
    "wof:name":"Baronnie Motel",
    "wof:placetype":"venue"
},
  "geometry": {"coordinates":[-65.7825012207,43.7030334473],"type":"Point"}
}