{
  "type": "Feature",
  "properties": {
    "addr:full":"415 First St Collingwood ON L9Y 1B7",
    "addr:housenumber":"415",
    "addr:postcode":"l9y 1b7",
    "addr:street":"First St",
    "iso:country":"CA",
    "sg:address":"415 First St",
    "sg:city":"Collingwood",
    "sg:classifiers":[
        {
            "category":"Food & Beverages",
            "subcategory":"Liquor & Beverages",
            "type":"Retail Goods"
        }
    ],
    "sg:phone":"+1 705 445 4051",
    "sg:postcode":"L9Y 1B7",
    "sg:province":"ON",
    "sg:tags":[
        "beer",
        "ale"
    ],
    "wof:name":"Brewers Retail Store",
    "wof:placetype":"venue"
},
  "geometry": {"coordinates":[-80.229935,44.501747],"type":"Point"}
}