{
  "type": "Feature",
  "properties": {
    "iso:country":"CA",
    "sg:address":"2489 Nanoose Rd",
    "sg:city":"Nanoose Bay",
    "sg:classifiers":[
        {
            "category":"Education",
            "subcategory":"Library",
            "type":"Public Place"
        }
    ],
    "sg:phone":"+1 250 468 9977",
    "sg:postcode":"V9P 9E6",
    "sg:province":"BC",
    "wof:name":"Nanoose Library Ctr",
    "wof:placetype":"venue"
},
  "geometry": {"coordinates":[-124.191711426,49.2753791809],"type":"Point"}
}