{
  "type": "Feature",
  "properties": {
    "addr:full":"2363 Front Rd Vittoria ON N0E 1W0",
    "addr:housenumber":"2363",
    "addr:postcode":"n0e 1w0",
    "addr:street":"Front Rd",
    "iso:country":"CA",
    "sg:address":"2363 Front Rd",
    "sg:city":"Vittoria",
    "sg:classifiers":[
        {
            "category":"Professional",
            "subcategory":"Business Services",
            "type":"Services"
        }
    ],
    "sg:phone":"+1 519 428 3063",
    "sg:postcode":"N0E 1W0",
    "sg:province":"ON",
    "sg:tags":[
        "water",
        "company",
        "swimming"
    ],
    "wof:name":"Vp's Water Svc",
    "wof:placetype":"venue"
},
  "geometry": {"coordinates":[-80.32357,42.76215],"type":"Point"}
}