{
  "type": "Feature",
  "properties": {
    "addr:full":"3873 Memorial Dr Halifax NS B3K 5A4",
    "addr:housenumber":"3873",
    "addr:postcode":"b3k 5a4",
    "addr:street":"Memorial Dr",
    "iso:country":"CA",
    "sg:address":"3873 Memorial Dr",
    "sg:city":"Halifax",
    "sg:classifiers":[
        {
            "category":"Professional",
            "subcategory":"Business Services",
            "type":"Services"
        }
    ],
    "sg:phone":"+1 902 454 9889",
    "sg:postcode":"B3K 5A4",
    "sg:province":"NS",
    "sg:tags":[
        "interior",
        "consultant",
        "design",
        "decorator"
    ],
    "wof:name":"K A Designs",
    "wof:placetype":"venue"
},
  "geometry": {"coordinates":[-63.6183509827,44.668056488],"type":"Point"}
}