{
  "type": "Feature",
  "properties": {
    "iso:country":"CA",
    "sg:city":"Calgary",
    "sg:classifiers":[
        {
            "category":"Social Services",
            "subcategory":"Child Care",
            "type":"Services"
        }
    ],
    "sg:phone":"+1 403 250 5211",
    "sg:postcode":"T2E 6W9",
    "sg:province":"AB",
    "wof:name":"Davar Child Care Society",
    "wof:placetype":"venue"
},
  "geometry": {"coordinates":[-114.004913,51.089466],"type":"Point"}
}