{
  "type": "Feature",
  "properties": {
    "addr:full":"Brantford ON N3R 6B8",
    "addr:postcode":"n3r 6b8",
    "iso:country":"CA",
    "sg:city":"Brantford",
    "sg:classifiers":[
        {
            "category":"Shopping",
            "subcategory":"Tobacco",
            "type":"Retail Goods"
        }
    ],
    "sg:phone":"+1 519 752 1502",
    "sg:postcode":"N3R 6B8",
    "sg:province":"ON",
    "sg:tags":[
        "cigarette",
        "cigar",
        "dealer"
    ],
    "wof:name":"Shefield & Sons",
    "wof:placetype":"venue"
},
  "geometry": {"coordinates":[-80.243927,43.172871],"type":"Point"}
}