{
  "type": "Feature",
  "properties": {
    "addr:full":"39 Preston St N Souris MB R0K 2C0",
    "addr:housenumber":"39",
    "addr:postcode":"r0k 2c0",
    "addr:street":"Preston St N",
    "iso:country":"CA",
    "sg:address":"39 Preston St N",
    "sg:city":"Souris",
    "sg:classifiers":[
        {
            "category":"Retail",
            "subcategory":"Veterinary Services",
            "type":"Services"
        }
    ],
    "sg:phone":"+1 204 483 2193",
    "sg:postcode":"R0K 2C0",
    "sg:province":"MB",
    "sg:tags":[
        "veterinarian"
    ],
    "wof:name":"Souris Veterinary Clinic",
    "wof:placetype":"venue"
},
  "geometry": {"coordinates":[-100.258865,49.620834],"type":"Point"}
}