{
  "type": "Feature",
  "properties": {
    "addr:full":"2840 Clapperton St Prince George BC V2L 5G9",
    "addr:housenumber":"2840",
    "addr:postcode":"v2l 5g9",
    "addr:street":"Clapperton St",
    "iso:country":"CA",
    "sg:address":"2840 Clapperton St",
    "sg:city":"Prince George",
    "sg:classifiers":[
        {
            "category":"Organizations",
            "subcategory":"Religious Organization",
            "type":"Services"
        }
    ],
    "sg:phone":"+1 250 563 4473",
    "sg:postcode":"V2L 5G9",
    "sg:province":"BC",
    "sg:tags":[
        "church"
    ],
    "wof:name":"Central Fellowship Baptist Chr",
    "wof:placetype":"venue"
},
  "geometry": {"coordinates":[-122.75494399999999,53.8932],"type":"Point"}
}