{
  "type": "Feature",
  "properties": {
    "addr:full":"Henryville QC J0J 1E0",
    "addr:postcode":"j0j 1e0",
    "iso:country":"CA",
    "sg:city":"Henryville",
    "sg:classifiers":[
        {
            "category":"Personal",
            "subcategory":"Beauty Salon",
            "type":"Services"
        }
    ],
    "sg:phone":"+1 450 299 2633",
    "sg:postcode":"J0J 1E0",
    "sg:province":"QC",
    "wof:name":"Salon Carole",
    "wof:placetype":"venue"
},
  "geometry": {"coordinates":[-73.180161,45.137951],"type":"Point"}
}