{
  "type": "Feature",
  "properties": {
    "addr:full":"211 Rue Merry S Magog QC J1X 3L2",
    "addr:housenumber":"211",
    "addr:postcode":"j1x 3l2",
    "addr:street":"Rue Merry S",
    "iso:country":"CA",
    "sg:address":"211 Rue Merry S",
    "sg:city":"Magog",
    "sg:classifiers":[
        {
            "category":"Restaurant",
            "type":"Food & Drink"
        }
    ],
    "sg:phone":"+1 819 843 2017",
    "sg:postcode":"J1X 3L2",
    "sg:province":"QC",
    "wof:name":"Saint-Tropez Restaurant",
    "wof:placetype":"venue"
},
  "geometry": {"coordinates":[-72.1584243774,45.2617263794],"type":"Point"}
}