{
  "type": "Feature",
  "properties": {
    "addr:full":"487 Linden Ave Kamloops BC V2B 2N4",
    "addr:housenumber":"487",
    "addr:postcode":"bc v2b 2n4",
    "addr:street":"Linden Ave",
    "iso:country":"CA",
    "sg:address":"487 Linden Ave",
    "sg:city":"Kamloops",
    "sg:classifiers":[
        {
            "category":"Building & Trades",
            "subcategory":"Construction",
            "type":"Services"
        }
    ],
    "sg:phone":"+1 250 376 8030",
    "sg:postcode":"V2B 2N4",
    "sg:province":"BC",
    "sg:tags":[
        "painter"
    ],
    "wof:name":"Canada West Paint Contrs Ltd",
    "wof:placetype":"venue"
},
  "geometry": {"coordinates":[-120.355125427,50.691860199],"type":"Point"}
}