{
  "type": "Feature",
  "properties": {
    "iso:country":"CA",
    "sg:address":"479 Warsaw Ave # C",
    "sg:city":"Winnipeg",
    "sg:classifiers":[
        {
            "category":"Building & Trades",
            "subcategory":"Construction",
            "type":"Services"
        }
    ],
    "sg:phone":"+1 204 927 0400",
    "sg:postcode":"R3L 0R2",
    "sg:province":"MB",
    "sg:tags":[
        "maker",
        "cabinet"
    ],
    "wof:name":"Woodcharm Cabinet Design",
    "wof:placetype":"venue"
},
  "geometry": {"coordinates":[-97.1429443359,49.8724212646],"type":"Point"}
}