{
  "type": "Feature",
  "properties": {
    "addr:full":"432 Gertrude Ave Beausejour MB R0E 0C0",
    "addr:housenumber":"432",
    "addr:postcode":"r0e 0c0",
    "addr:street":"Gertrude Ave",
    "iso:country":"CA",
    "sg:address":"432 Gertrude Ave",
    "sg:city":"Beausejour",
    "sg:classifiers":[
        {
            "category":"Building & Trades",
            "subcategory":"Plumbing",
            "type":"Services"
        }
    ],
    "sg:phone":"+1 204 268 2286",
    "sg:postcode":"R0E 0C0",
    "sg:province":"MB",
    "sg:tags":[
        "conditioning",
        "air",
        "system",
        "contractor"
    ],
    "wof:name":"Beausejour Sheet Metal",
    "wof:placetype":"venue"
},
  "geometry": {"coordinates":[-96.5051116943,50.0629692078],"type":"Point"}
}