{
  "type": "Feature",
  "properties": {
    "addr:full":"Burnaby BC V5H 4V8",
    "addr:postcode":"v5h 4v8",
    "iso:country":"CA",
    "sg:city":"Burnaby",
    "sg:classifiers":[
        {
            "category":"Government",
            "subcategory":"Office",
            "type":"Public Place"
        }
    ],
    "sg:phone":"+1 604 433 1711",
    "sg:postcode":"V5H 4V8",
    "sg:province":"BC",
    "wof:name":"BC Housing Mgmt Commission",
    "wof:placetype":"venue"
},
  "geometry": {"coordinates":[-123.00335699999999,49.229858],"type":"Point"}
}