{
  "type": "Feature",
  "properties": {
    "addr:full":"Medicine Hat AB T1B 3N3",
    "addr:postcode":"t1b 3n3",
    "iso:country":"CA",
    "sg:city":"Medicine Hat",
    "sg:classifiers":[
        {
            "category":"Autos & Motor Vehicles",
            "subcategory":"Auto Supplies",
            "type":"Retail Goods"
        }
    ],
    "sg:phone":"+1 403 504 8439",
    "sg:postcode":"T1B 3N3",
    "sg:province":"AB",
    "sg:tags":[
        "automobile",
        "parts"
    ],
    "wof:name":"Tidy Truck Box Liners",
    "wof:placetype":"venue"
},
  "geometry": {"coordinates":[-110.71019,50.011463],"type":"Point"}
}