{
  "type": "Feature",
  "properties": {
    "addr:full":"111 Topflight Dr Mississauga ON L5S 1Y1",
    "addr:housenumber":"111",
    "addr:postcode":"l5s 1y1",
    "addr:street":"Topflight Dr",
    "iso:country":"CA",
    "sg:address":"111 Topflight Dr",
    "sg:city":"Mississauga",
    "sg:classifiers":[
        {
            "category":"Manufacturing",
            "subcategory":"Tools & Machinery",
            "type":"Manufacturing & Wholesale Goods"
        }
    ],
    "sg:phone":"+1 905 565 8058",
    "sg:postcode":"L5S 1Y1",
    "sg:province":"ON",
    "sg:tags":[
        "equipment",
        "system",
        "vacuum"
    ],
    "wof:name":"Busch Vacuum Technics Inc",
    "wof:placetype":"venue"
},
  "geometry": {"coordinates":[-79.709412,43.65181],"type":"Point"}
}