{
  "type": "Feature",
  "properties": {
    "addr:full":"5025 Orbitor Dr Mississauga ON L4W 4Y5",
    "addr:housenumber":"5025",
    "addr:postcode":"l4w 4y5",
    "addr:street":"Orbitor Dr",
    "iso:country":"CA",
    "sg:address":"5025 Orbitor Dr",
    "sg:city":"Mississauga",
    "sg:classifiers":[
        {
            "category":"Shopping",
            "subcategory":"Computers & Home Electronics",
            "type":"Retail Goods"
        }
    ],
    "sg:phone":"+1 905 624 5015",
    "sg:postcode":"L4W 4Y5",
    "sg:province":"ON",
    "sg:tags":[
        "software"
    ],
    "wof:name":"Recruitsoft.com",
    "wof:placetype":"venue"
},
  "geometry": {"coordinates":[-79.5988693237,43.6562805176],"type":"Point"}
}