{
  "type": "Feature",
  "properties": {
    "addr:full":"119 Jail St Miramichi NB E1V 1Z6",
    "addr:housenumber":"119",
    "addr:postcode":"e1v 1z6",
    "addr:street":"Jail St",
    "iso:country":"CA",
    "sg:address":"119 Jail St",
    "sg:city":"Miramichi",
    "sg:classifiers":[
        {
            "category":"Personal",
            "subcategory":"Barber",
            "type":"Services"
        }
    ],
    "sg:phone":"+1 506 622 2097",
    "sg:postcode":"E1V 1Z6",
    "sg:province":"NB",
    "wof:name":"Norm's Hair Care & Barber Shop",
    "wof:placetype":"venue"
},
  "geometry": {"coordinates":[-65.564781,47.000877],"type":"Point"}
}