{
  "type": "Feature",
  "properties": {
    "iso:country":"CA",
    "sg:address":"3046 White Oak Rd",
    "sg:city":"London",
    "sg:classifiers":[
        {
            "category":"Education",
            "subcategory":"School",
            "type":"Public Place"
        }
    ],
    "sg:phone":"+1 519 681 1196",
    "sg:postcode":"N6E 1L8",
    "sg:province":"ON",
    "wof:name":"Covenant Christian School",
    "wof:placetype":"venue"
},
  "geometry": {"coordinates":[-81.251518,42.939648],"type":"Point"}
}