{
  "type": "Feature",
  "properties": {
    "addr:full":"3046 White Oak Rd London ON N6E 1L8",
    "addr:housenumber":"3046",
    "addr:postcode":"n6e 1l8",
    "addr:street":"White Oak Rd",
    "iso:country":"CA",
    "sg:address":"3046 White Oak Rd",
    "sg:city":"London",
    "sg:classifiers":[
        {
            "category":"Education",
            "subcategory":"School",
            "type":"Public Place"
        }
    ],
    "sg:phone":"+1 519 681 1196",
    "sg:postcode":"N6E 1L8",
    "sg:province":"ON",
    "wof:name":"Covenant Christian School",
    "wof:placetype":"venue"
},
  "geometry": {"coordinates":[-81.251518,42.939648],"type":"Point"}
}