{
  "type": "Feature",
  "properties": {
    "addr:full":"5800 Rue Du Campagnol Saint-Emile QC G3E 1R2",
    "addr:housenumber":"5800",
    "addr:postcode":"g3e 1r2",
    "addr:street":"Rue Du Campagnol Saint-Emile",
    "iso:country":"CA",
    "sg:address":"5800 Rue Du Campagnol",
    "sg:city":"Saint-Emile",
    "sg:classifiers":[
        {
            "category":"Personal",
            "subcategory":"Beauty Salon",
            "type":"Services"
        }
    ],
    "sg:phone":"+1 418 842 5166",
    "sg:postcode":"G3E 1R2",
    "sg:province":"QC",
    "wof:name":"Salon Nicole",
    "wof:placetype":"venue"
},
  "geometry": {"coordinates":[-71.344673,46.87545],"type":"Point"}
}