{
  "type": "Feature",
  "properties": {
    "addr:full":"648 Portland St Dartmouth NS B2W 2M3",
    "addr:housenumber":"648",
    "addr:postcode":"b2w 2m3",
    "addr:street":"Portland St",
    "iso:country":"CA",
    "sg:address":"648 Portland St",
    "sg:city":"Dartmouth",
    "sg:classifiers":[
        {
            "category":"Retail",
            "subcategory":"Auto Repair",
            "type":"Services"
        }
    ],
    "sg:phone":"+1 902 435 5457",
    "sg:postcode":"B2W 2M3",
    "sg:province":"NS",
    "sg:tags":[
        "automobile",
        "lubrication"
    ],
    "wof:name":"Mr Lube",
    "wof:placetype":"venue"
},
  "geometry": {"coordinates":[-63.526836,44.671337],"type":"Point"}
}