{
  "type": "Feature",
  "properties": {
    "addr:full":"1861 Park St Regina SK S4N 2G4",
    "addr:housenumber":"1861",
    "addr:postcode":"s4n 2g4",
    "addr:street":"Park St",
    "iso:country":"CA",
    "sg:address":"1861 Park St",
    "sg:city":"Regina",
    "sg:classifiers":[
        {
            "category":"Building & Trades",
            "subcategory":"Plumbing",
            "type":"Services"
        }
    ],
    "sg:phone":"+1 306 757 9111",
    "sg:postcode":"S4N 2G4",
    "sg:province":"SK",
    "sg:tags":[
        "sheet",
        "work",
        "metal",
        "heating",
        "contractor"
    ],
    "wof:name":"Gaetz Mechanical Inc",
    "wof:placetype":"venue"
},
  "geometry": {"coordinates":[-104.57197600000001,50.449482],"type":"Point"}
}