{
  "type": "Feature",
  "properties": {
    "addr:full":"11632 149 St NW Edmonton AB T5M 3R3",
    "addr:housenumber":"11632",
    "addr:postcode":"t5m 3r3",
    "addr:street":"149 St Nw",
    "iso:country":"CA",
    "sg:address":"11632 149 St NW",
    "sg:city":"Edmonton",
    "sg:classifiers":[
        {
            "category":"Building & Trades",
            "subcategory":"Equipment Rental",
            "type":"Services"
        }
    ],
    "sg:phone":"+1 780 452 3487",
    "sg:postcode":"T5M 3R3",
    "sg:province":"AB",
    "sg:tags":[
        "player",
        "recorder",
        "video"
    ],
    "wof:name":"Video Movie House",
    "wof:placetype":"venue"
},
  "geometry": {"coordinates":[-113.578247,53.568516],"type":"Point"}
}