{
  "type": "Feature",
  "properties": {
    "addr:full":"Toronto ON M5V 2Y9",
    "addr:postcode":"m5v 2y9",
    "iso:country":"CA",
    "sg:city":"Toronto",
    "sg:classifiers":[
        {
            "category":"Manufacturing",
            "subcategory":"Electronics",
            "type":"Manufacturing & Wholesale Goods"
        }
    ],
    "sg:phone":"+1 416 260 6688",
    "sg:postcode":"M5V 2Y9",
    "sg:province":"ON",
    "sg:tags":[
        "record"
    ],
    "wof:name":"Silverbirch Productions",
    "wof:placetype":"venue"
},
  "geometry": {"coordinates":[-79.399345,43.635242],"type":"Point"}
}