{
  "type": "Feature",
  "properties": {
    "addr:full":"673 Boul Henri-Bourassa E Montreal QC H2C 1E4",
    "addr:housenumber":"673",
    "addr:postcode":"h2c 1e4",
    "addr:street":"Boul Henri-Bourassa E",
    "iso:country":"CA",
    "sg:address":"673 Boul Henri-Bourassa E",
    "sg:city":"Montreal",
    "sg:classifiers":[
        {
            "category":"Shopping",
            "subcategory":"Bicycles & Sporting Goods",
            "type":"Retail Goods"
        }
    ],
    "sg:phone":"+1 514 383 8356",
    "sg:postcode":"H2C 1E4",
    "sg:province":"QC",
    "wof:name":"Coppi LA Boutique Du Pro Inc",
    "wof:placetype":"venue"
},
  "geometry": {"coordinates":[-73.6675796509,45.5571136475],"type":"Point"}
}