{
  "type": "Feature",
  "properties": {
    "addr:full":"Timberlea NS B3T 1B8",
    "addr:postcode":"b3t 1b8",
    "iso:country":"CA",
    "sg:city":"Timberlea",
    "sg:classifiers":[
        {
            "category":"Travel",
            "subcategory":"Hotels & Motels",
            "type":"Entertainment"
        }
    ],
    "sg:phone":"+1 902 876 2301",
    "sg:postcode":"B3T 1B8",
    "sg:province":"NS",
    "wof:name":"Stardust",
    "wof:placetype":"venue"
},
  "geometry": {"coordinates":[-63.723133,44.649693],"type":"Point"}
}