{
  "type": "Feature",
  "properties": {
    "addr:full":"Calgary AB T2C 1R4",
    "addr:postcode":"t2c 1r4",
    "iso:country":"CA",
    "sg:city":"Calgary",
    "sg:classifiers":[
        {
            "category":"Manufacturing",
            "subcategory":"Glass & Minerals",
            "type":"Manufacturing & Wholesale Goods"
        }
    ],
    "sg:phone":"+1 403 236 5889",
    "sg:postcode":"T2C 1R4",
    "sg:province":"AB",
    "sg:tags":[
        "refractory"
    ],
    "wof:name":"Wesmat Refractories",
    "wof:placetype":"venue"
},
  "geometry": {"coordinates":[-113.986351013,50.9977989197],"type":"Point"}
}