{
  "type": "Feature",
  "properties": {
    "addr:full":"8298 Boul Pie-Ix Montreal QC H1Z 4E8",
    "addr:housenumber":"8298",
    "addr:postcode":"h1z 4e8",
    "addr:street":"Boul Pie-Ix",
    "iso:country":"CA",
    "sg:address":"8298 Boul Pie-Ix",
    "sg:city":"Montreal",
    "sg:classifiers":[
        {
            "category":"Insurance",
            "subcategory":"Insurance Agent",
            "type":"Services"
        }
    ],
    "sg:phone":"+1 514 721 6220",
    "sg:postcode":"H1Z 4E8",
    "sg:province":"QC",
    "wof:name":"L'Industrielle-Alliance CO",
    "wof:placetype":"venue"
},
  "geometry": {"coordinates":[-73.608543,45.573917],"type":"Point"}
}