{
  "type": "Feature",
  "properties": {
    "iso:country":"CA",
    "sg:address":"571 Shiloh Ave",
    "sg:city":"Kingston",
    "sg:classifiers":[
        {
            "category":"Building & Trades",
            "subcategory":"Construction",
            "type":"Services"
        }
    ],
    "sg:phone":"+1 613 389 6697",
    "sg:postcode":"K7M 8W1",
    "sg:province":"ON",
    "sg:tags":[
        "contractor",
        "general"
    ],
    "wof:name":"John Maas Builder Ltd",
    "wof:placetype":"venue"
},
  "geometry": {"coordinates":[-76.59995269780001,44.2352714539],"type":"Point"}
}