{
  "type": "Feature",
  "properties": {
    "addr:full":"43 Cherrywood Cres Sudbury ON P3B 4A2",
    "addr:housenumber":"43",
    "addr:postcode":"p3b 4a2",
    "addr:street":"Cherrywood Cres",
    "iso:country":"CA",
    "sg:address":"43 Cherrywood Cres",
    "sg:city":"Sudbury",
    "sg:classifiers":[
        {
            "category":"Home & Garden",
            "subcategory":"Garden Supply",
            "type":"Retail Goods"
        }
    ],
    "sg:phone":"+1 705 566 0888",
    "sg:postcode":"P3B 4A2",
    "sg:province":"ON",
    "sg:tags":[
        "sprinkler"
    ],
    "wof:name":"Northern Lawn Sprinklers",
    "wof:placetype":"venue"
},
  "geometry": {"coordinates":[-80.92491099999999,46.491226],"type":"Point"}
}