{
  "type": "Feature",
  "properties": {
    "addr:full":"Halifax NS B3J 1H6",
    "addr:postcode":"ns b3j 1h6",
    "iso:country":"CA",
    "sg:city":"Halifax",
    "sg:classifiers":[
        {
            "category":"Shopping",
            "subcategory":"Used Merchandise",
            "type":"Retail Goods"
        }
    ],
    "sg:phone":"+1 902 463 3444",
    "sg:postcode":"B3J 1H6",
    "sg:province":"NS",
    "sg:tags":[
        "clothing"
    ],
    "wof:name":"Dressed in Time",
    "wof:placetype":"venue"
},
  "geometry": {"coordinates":[-63.579044342,44.6423339844],"type":"Point"}
}