{
  "type": "Feature",
  "properties": {
    "addr:full":"Salmon Arm BC V1E 1S9",
    "addr:postcode":"v1e 1s9",
    "iso:country":"CA",
    "sg:city":"Salmon Arm",
    "sg:classifiers":[
        {
            "category":"Professional",
            "subcategory":"Art Services",
            "type":"Services"
        }
    ],
    "sg:phone":"+1 250 832 8261",
    "sg:postcode":"V1E 1S9",
    "sg:province":"BC",
    "sg:tags":[
        "graphic",
        "designer"
    ],
    "wof:name":"Toliver Advertising & Design",
    "wof:placetype":"venue"
},
  "geometry": {"coordinates":[-119.291901,50.696491],"type":"Point"}
}