{
  "type": "Feature",
  "properties": {
    "addr:full":"Red Deer AB T4N 6V7",
    "addr:postcode":"t4n 6v7",
    "iso:country":"CA",
    "sg:city":"Red Deer",
    "sg:classifiers":[
        {
            "category":"Shopping",
            "subcategory":"Pharmacy",
            "type":"Retail Goods"
        }
    ],
    "sg:phone":"+1 403 341 4488",
    "sg:postcode":"T4N 6V7",
    "sg:province":"AB",
    "wof:name":"Hilltop Pharmacy",
    "wof:placetype":"venue"
},
  "geometry": {"coordinates":[-113.816383,52.260559],"type":"Point"}
}