{
  "type": "Feature",
  "properties": {
    "addr:full":"Scotia St & Hwy 16 W Smithers BC V0J 2N0",
    "addr:postcode":"v0j 2n0",
    "addr:street":"Scotia St & Hwy 16 W",
    "iso:country":"CA",
    "sg:address":"Scotia St & Hwy 16 W",
    "sg:city":"Smithers",
    "sg:classifiers":[
        {
            "category":"Sports & Exercise",
            "subcategory":"Golf",
            "type":"Entertainment"
        }
    ],
    "sg:phone":"+1 250 847 3591",
    "sg:postcode":"V0J 2N0",
    "sg:province":"BC",
    "sg:tags":[
        "course"
    ],
    "wof:name":"Smithers Golf Course",
    "wof:placetype":"venue"
},
  "geometry": {"coordinates":[-127.18615,54.796219],"type":"Point"}
}