{
  "type": "Feature",
  "properties": {
    "addr:full":"10011 100th St Hythe AB T0H 2C0",
    "addr:housenumber":"10011",
    "addr:postcode":"t0h 2c0",
    "addr:street":"100Th St",
    "iso:country":"CA",
    "sg:address":"10011 100th St",
    "sg:city":"Hythe",
    "sg:classifiers":[
        {
            "category":"Government",
            "subcategory":"Office",
            "type":"Public Place"
        }
    ],
    "sg:phone":"+1 780 356 3888",
    "sg:postcode":"T0H 2C0",
    "sg:province":"AB",
    "sg:tags":[
        "municipality"
    ],
    "wof:name":"Village of Hythe",
    "wof:placetype":"venue"
},
  "geometry": {"coordinates":[-119.556099,55.326473],"type":"Point"}
}