{
  "type": "Feature",
  "properties": {
    "addr:full":"5760 Av Royalmount # 201 Mont-Royal QC H4P 1K5",
    "addr:housenumber":"5760;# 201",
    "addr:postcode":"h4p 1k5",
    "addr:street":"Av Royalmount",
    "iso:country":"CA",
    "sg:address":"5760 Av Royalmount # 201",
    "sg:city":"Mont-Royal",
    "sg:classifiers":[
        {
            "category":"Banks & Credit Unions",
            "subcategory":"Investment Brokerage",
            "type":"Services"
        }
    ],
    "sg:phone":"+1 514 343 3984",
    "sg:postcode":"H4P 1K5",
    "sg:province":"QC",
    "sg:tags":[
        "consultant",
        "planning",
        "financial"
    ],
    "wof:name":"Icc Capital Management",
    "wof:placetype":"venue"
},
  "geometry": {"coordinates":[-73.670456,45.490955],"type":"Point"}
}