{
  "type": "Feature",
  "properties": {
    "iso:country":"CA",
    "sg:address":"4416 20 Ave NW",
    "sg:city":"Calgary",
    "sg:classifiers":[
        {
            "category":"Building & Trades",
            "subcategory":"Landscaping Services",
            "type":"Services"
        }
    ],
    "sg:phone":"+1 403 247 6577",
    "sg:postcode":"T3B 0T6",
    "sg:province":"AB",
    "sg:tags":[
        "landscape",
        "contractor"
    ],
    "wof:name":"Allan Industries CO Ltd",
    "wof:placetype":"venue"
},
  "geometry": {"coordinates":[-114.15387725799999,51.0705986023],"type":"Point"}
}