{
  "type": "Feature",
  "properties": {
    "addr:full":"57 Henderson St Miramichi NB E1N 2R4",
    "addr:housenumber":"57",
    "addr:postcode":"e1n 2r4",
    "addr:street":"Henderson St",
    "iso:country":"CA",
    "sg:address":"57 Henderson St",
    "sg:city":"Miramichi",
    "sg:classifiers":[
        {
            "category":"Personal",
            "subcategory":"Tanning Parlor",
            "type":"Services"
        }
    ],
    "sg:phone":"+1 506 773 0083",
    "sg:postcode":"E1N 2R4",
    "sg:province":"NB",
    "sg:tags":[
        "salon"
    ],
    "wof:name":"Tan Stand",
    "wof:placetype":"venue"
},
  "geometry": {"coordinates":[-65.464478,47.028851],"type":"Point"}
}