{
  "type": "Feature",
  "properties": {
    "addr:full":"124 Hastings St N Bancroft ON K0L 1C0",
    "addr:housenumber":"124",
    "addr:postcode":"k0l 1c0",
    "addr:street":"Hastings St N",
    "iso:country":"CA",
    "sg:address":"124 Hastings St N",
    "sg:city":"Bancroft",
    "sg:classifiers":[
        {
            "category":"Home & Garden",
            "subcategory":"Building Materials",
            "type":"Retail Goods"
        }
    ],
    "sg:phone":"+1 613 332 1765",
    "sg:postcode":"K0L 1C0",
    "sg:province":"ON",
    "sg:tags":[
        "paint"
    ],
    "wof:name":"Northern Carpet Sales Ltd",
    "wof:placetype":"venue"
},
  "geometry": {"coordinates":[-77.856461,45.062553],"type":"Point"}
}