{
  "type": "Feature",
  "properties": {
    "addr:full":"1027 Finch Ave W North York ON M3J 2C7",
    "addr:housenumber":"1027",
    "addr:postcode":"m3j 2c7",
    "addr:street":"Finch Ave W",
    "iso:country":"CA",
    "sg:address":"1027 Finch Ave W",
    "sg:city":"North York",
    "sg:classifiers":[
        {
            "category":"Home & Garden",
            "subcategory":"Home Furnishings",
            "type":"Retail Goods"
        }
    ],
    "sg:phone":"+1 416 630 9882",
    "sg:postcode":"M3J 2C7",
    "sg:province":"ON",
    "sg:tags":[
        "venetian",
        "blind"
    ],
    "wof:name":"Geosam Blinds",
    "wof:placetype":"venue"
},
  "geometry": {"coordinates":[-79.4699935913,43.7680358887],"type":"Point"}
}