{
  "type": "Feature",
  "properties": {
    "addr:full":"600 10E Chemin Metabetchouan-Lac-A-LA-Croix QC G8G 1P1",
    "addr:housenumber":"600",
    "addr:postcode":"g8g 1p1",
    "addr:street":"10E Chemin Metabetchouan-Lac-A-La-Croix",
    "iso:country":"CA",
    "sg:address":"600 10E Chemin",
    "sg:city":"Metabetchouan-Lac-A-LA-Croix",
    "sg:classifiers":[
        {
            "category":"Travel",
            "subcategory":"Campground",
            "type":"Entertainment"
        }
    ],
    "sg:phone":"+1 418 345 2655",
    "sg:postcode":"G8G 1P1",
    "sg:province":"QC",
    "wof:name":"Camping Villa Des Sables",
    "wof:placetype":"venue"
},
  "geometry": {"coordinates":[-71.812515,48.472698],"type":"Point"}
}