{
  "type": "Feature",
  "properties": {
    "iso:country":"CA",
    "sg:address":"116 Thomas St",
    "sg:city":"Oakville",
    "sg:classifiers":[
        {
            "category":"Health Services",
            "subcategory":"Health Practitioner",
            "type":"Services"
        }
    ],
    "sg:phone":"+1 905 849 4242",
    "sg:postcode":"L6J 3A8",
    "sg:province":"ON",
    "sg:tags":[
        "psychologist"
    ],
    "wof:name":"Chartwell Institute For Care",
    "wof:placetype":"venue"
},
  "geometry": {"coordinates":[-79.669884,43.445137],"type":"Point"}
}