{
  "type": "Feature",
  "properties": {
    "addr:full":"1165 Rothesay St Winnipeg MB R2G 1T6",
    "addr:housenumber":"1165",
    "addr:postcode":"r2g 1t6",
    "addr:street":"Rothesay St",
    "iso:country":"CA",
    "sg:address":"1165 Rothesay St",
    "sg:city":"Winnipeg",
    "sg:classifiers":[
        {
            "category":"Personal",
            "subcategory":"Beauty Salon",
            "type":"Services"
        }
    ],
    "sg:phone":"+1 204 663 5055",
    "sg:postcode":"R2G 1T6",
    "sg:province":"MB",
    "wof:name":"Shelley-Lynn Hair Fashions",
    "wof:placetype":"venue"
},
  "geometry": {"coordinates":[-97.080589,49.936508],"type":"Point"}
}