{
  "type": "Feature",
  "properties": {
    "addr:full":"Scarborough ON M1P 4Y9",
    "addr:postcode":"m1p 4y9",
    "iso:country":"CA",
    "sg:city":"Scarborough",
    "sg:classifiers":[
        {
            "category":"Professional",
            "subcategory":"Advertising",
            "type":"Services"
        }
    ],
    "sg:phone":"+1 416 751 1889",
    "sg:postcode":"M1P 4Y9",
    "sg:province":"ON",
    "sg:tags":[
        "flag",
        "banner"
    ],
    "wof:name":"Print Ink Network",
    "wof:placetype":"venue"
},
  "geometry": {"coordinates":[-79.27169799799999,43.762512207],"type":"Point"}
}