{
  "type": "Feature",
  "properties": {
    "addr:full":"33 Saint Paul St Toronto ON M5A 3H2",
    "addr:housenumber":"33",
    "addr:postcode":"m5a 3h2",
    "addr:street":"Saint Paul St",
    "iso:country":"CA",
    "sg:address":"33 Saint Paul St",
    "sg:city":"Toronto",
    "sg:classifiers":[
        {
            "category":"Professional",
            "subcategory":"Art Services",
            "type":"Services"
        }
    ],
    "sg:phone":"+1 416 362 5223",
    "sg:postcode":"M5A 3H2",
    "sg:province":"ON",
    "sg:tags":[
        "photographer"
    ],
    "wof:name":"Reeves, John",
    "wof:placetype":"venue"
},
  "geometry": {"coordinates":[-79.36013,43.655853],"type":"Point"}
}