{
  "type": "Feature",
  "properties": {
    "addr:full":"851 Johnson St Victoria BC V8W 1N4",
    "addr:housenumber":"851",
    "addr:postcode":"v8w 1n4",
    "addr:street":"Johnson St",
    "iso:country":"CA",
    "sg:address":"851 Johnson St",
    "sg:city":"Victoria",
    "sg:classifiers":[
        {
            "category":"Home & Garden",
            "subcategory":"Carpets & Floor Coverings",
            "type":"Retail Goods"
        }
    ],
    "sg:phone":"+1 250 380 4030",
    "sg:postcode":"V8W 1N4",
    "sg:province":"BC",
    "sg:tags":[
        "dealer",
        "rug"
    ],
    "wof:name":"House of Fine Carpets",
    "wof:placetype":"venue"
},
  "geometry": {"coordinates":[-123.36041299999999,48.426636],"type":"Point"}
}