{
  "type": "Feature",
  "properties": {
    "addr:full":"2860 Dewdney Trunk Rd Coquitlam BC V3C 2H9",
    "addr:housenumber":"2860",
    "addr:postcode":"bc v3c 2h9",
    "addr:street":"Dewdney Trunk Rd",
    "iso:country":"CA",
    "sg:address":"2860 Dewdney Trunk Rd",
    "sg:city":"Coquitlam",
    "sg:classifiers":[
        {
            "category":"Organizations",
            "subcategory":"Religious Organization",
            "type":"Services"
        }
    ],
    "sg:phone":"+1 604 552 7221",
    "sg:postcode":"V3C 2H9",
    "sg:province":"BC",
    "sg:tags":[
        "synagogue"
    ],
    "wof:name":"Burquest Jewish Community Assn",
    "wof:placetype":"venue"
},
  "geometry": {"coordinates":[-122.80361175500001,49.2723274231],"type":"Point"}
}