{
  "type": "Feature",
  "properties": {
    "iso:country":"CA",
    "sg:address":"3 Beaverbrook Rd",
    "sg:city":"Kanata",
    "sg:classifiers":[
        {
            "category":"Government",
            "subcategory":"Office",
            "type":"Public Place"
        }
    ],
    "sg:phone":"+1 613 592 4435",
    "sg:postcode":"K2K 1L2",
    "sg:province":"ON",
    "sg:tags":[
        "village"
    ],
    "wof:name":"Beaverbrook Centre D'Achat",
    "wof:placetype":"venue"
},
  "geometry": {"coordinates":[-75.90101623539999,45.3299751282],"type":"Point"}
}