{
  "type": "Feature",
  "properties": {
    "iso:country":"CA",
    "sg:address":"1290 Boul Saint-Laurent E",
    "sg:city":"Louiseville",
    "sg:classifiers":[
        {
            "category":"Retail",
            "subcategory":"Auto Repair",
            "type":"Services"
        }
    ],
    "sg:phone":"+1 819 228 8881",
    "sg:postcode":"J5V 2L4",
    "sg:province":"QC",
    "sg:tags":[
        "body",
        "automobile",
        "painting"
    ],
    "wof:name":"Decor Automobile Jean Milot",
    "wof:placetype":"venue"
},
  "geometry": {"coordinates":[-72.8927764893,46.2618331909],"type":"Point"}
}