{
  "type": "Feature",
  "properties": {
    "addr:full":"7330 Goreway Dr Mississauga ON L4T 4J2",
    "addr:housenumber":"7330",
    "addr:postcode":"l4t 4j2",
    "addr:street":"Goreway Dr",
    "iso:country":"CA",
    "sg:address":"7330 Goreway Dr",
    "sg:city":"Mississauga",
    "sg:classifiers":[
        {
            "category":"Health Services",
            "subcategory":"Doctor",
            "type":"Services"
        }
    ],
    "sg:phone":"+1 905 677 7700",
    "sg:postcode":"L4T 4J2",
    "sg:province":"ON",
    "sg:tags":[
        "dentist"
    ],
    "wof:name":"Sax, Lawrence DDS",
    "wof:placetype":"venue"
},
  "geometry": {"coordinates":[-79.64028167719999,43.7197036743],"type":"Point"}
}