{
  "type": "Feature",
  "properties": {
    "addr:full":"10 Mascarin Pl Torbay NL A1K 1A5",
    "addr:housenumber":"10",
    "addr:postcode":"a1k 1a5",
    "addr:street":"Mascarin Pl",
    "iso:country":"CA",
    "sg:address":"10 Mascarin Pl",
    "sg:city":"Torbay",
    "sg:classifiers":[
        {
            "category":"Building & Trades",
            "subcategory":"Construction",
            "type":"Services"
        }
    ],
    "sg:phone":"+1 709 437 5868",
    "sg:postcode":"A1K 1A5",
    "sg:province":"NL",
    "sg:tags":[
        "contractor"
    ],
    "wof:name":"Nino Construction Ltd",
    "wof:placetype":"venue"
},
  "geometry": {"coordinates":[-52.728146,47.645985],"type":"Point"}
}