{
  "type": "Feature",
  "properties": {
    "iso:country":"CA",
    "sg:address":"3090 Jefferson Blvd",
    "sg:city":"Windsor",
    "sg:classifiers":[
        {
            "category":"Retail",
            "subcategory":"Auto Repair",
            "type":"Services"
        }
    ],
    "sg:phone":"+1 519 944 2600",
    "sg:postcode":"N8T 3G9",
    "sg:province":"ON",
    "sg:tags":[
        "transmission",
        "automobile",
        "repairing"
    ],
    "wof:name":"Countrywide Transmissions",
    "wof:placetype":"venue"
},
  "geometry": {"coordinates":[-82.94250488279999,42.2959022522],"type":"Point"}
}