{
  "type": "Feature",
  "properties": {
    "addr:full":"246 East St Napanee ON K7R 1T2",
    "addr:housenumber":"246",
    "addr:postcode":"k7r 1t2",
    "addr:street":"East St",
    "iso:country":"CA",
    "sg:address":"246 East St",
    "sg:city":"Napanee",
    "sg:classifiers":[
        {
            "category":"Retail",
            "subcategory":"Portrait Studio",
            "type":"Services"
        }
    ],
    "sg:phone":"+1 613 354 3232",
    "sg:postcode":"K7R 1T2",
    "sg:province":"ON",
    "sg:tags":[
        "photographer"
    ],
    "wof:name":"Mjm Vinyl Lettering",
    "wof:placetype":"venue"
},
  "geometry": {"coordinates":[-76.95224,44.252441],"type":"Point"}
}