{
  "type": "Feature",
  "properties": {
    "addr:full":"320 Edmon Deseronto ON K0K 1X0",
    "addr:housenumber":"320",
    "addr:postcode":"k0k 1x0",
    "addr:street":"Edmon",
    "iso:country":"CA",
    "sg:address":"320 Edmon",
    "sg:city":"Deseronto",
    "sg:classifiers":[
        {
            "category":"Government",
            "subcategory":"Police Station",
            "type":"Public Place"
        }
    ],
    "sg:phone":"+1 613 396 2968",
    "sg:postcode":"K0K 1X0",
    "sg:province":"ON",
    "sg:tags":[
        "department"
    ],
    "wof:name":"Deseronto Police Dept",
    "wof:placetype":"venue"
},
  "geometry": {"coordinates":[-77.050034,44.195045],"type":"Point"}
}