{
  "type": "Feature",
  "properties": {
    "addr:full":"Winnipeg MB R3C 0S5",
    "addr:postcode":"r3c 0s5",
    "iso:country":"CA",
    "sg:city":"Winnipeg",
    "sg:classifiers":[
        {
            "category":"Professional",
            "subcategory":"Lawyer & Legal Services",
            "type":"Services"
        }
    ],
    "sg:phone":"+1 204 927 1620",
    "sg:postcode":"R3C 0S5",
    "sg:province":"MB",
    "sg:tags":[
        "attorney"
    ],
    "wof:name":"N H Kravetsky Law Office",
    "wof:placetype":"venue"
},
  "geometry": {"coordinates":[-97.13962554930001,49.887550354],"type":"Point"}
}