{
  "type": "Feature",
  "properties": {
    "iso:country":"CA",
    "sg:address":"351 Clarke Rd",
    "sg:city":"London",
    "sg:classifiers":[
        {
            "category":"Personal",
            "subcategory":"Beauty Salon",
            "type":"Services"
        }
    ],
    "sg:phone":"+1 519 457 3866",
    "sg:postcode":"N5W 5G4",
    "sg:province":"ON",
    "wof:name":"Zackary's Hair Design",
    "wof:placetype":"venue"
},
  "geometry": {"coordinates":[-81.17469,43.002098],"type":"Point"}
}