{
  "type": "Feature",
  "properties": {
    "addr:full":"1043 W Shore Rd Pelee Island ON N0R 1M0",
    "addr:housenumber":"1043",
    "addr:postcode":"n0r 1m0",
    "addr:street":"W Shore Rd",
    "iso:country":"CA",
    "sg:address":"1043 W Shore Rd",
    "sg:city":"Pelee Island",
    "sg:classifiers":[
        {
            "category":"Shopping",
            "subcategory":"Clothing, Apparel, & Fashions",
            "type":"Retail Goods"
        }
    ],
    "sg:phone":"+1 519 724 1121",
    "sg:postcode":"N0R 1M0",
    "sg:province":"ON",
    "wof:name":"Down the Lane Clothing Boutiqu",
    "wof:placetype":"venue"
},
  "geometry": {"coordinates":[-82.68869018549999,41.7649230957],"type":"Point"}
}