{
  "type": "Feature",
  "properties": {
    "iso:country":"CA",
    "sg:address":"490 3E Rue",
    "sg:city":"Chibougamau",
    "sg:classifiers":[
        {
            "category":"Shopping",
            "subcategory":"Department Store",
            "type":"Retail Goods"
        }
    ],
    "sg:phone":"+1 418 748 6487",
    "sg:postcode":"G8P 1N7",
    "sg:province":"QC",
    "wof:name":"Zellers",
    "wof:placetype":"venue"
},
  "geometry": {"coordinates":[-74.3623428345,49.9135055542],"type":"Point"}
}