{
  "type": "Feature",
  "properties": {
    "addr:full":"Candiac QC J5R 1C3",
    "addr:postcode":"j5r 1c3",
    "iso:country":"CA",
    "sg:city":"Candiac",
    "sg:classifiers":[
        {
            "category":"Retail",
            "subcategory":"Laundry & Dry Cleaning",
            "type":"Services"
        }
    ],
    "sg:phone":"+1 450 444 9551",
    "sg:postcode":"J5R 1C3",
    "sg:province":"QC",
    "sg:tags":[
        "cleaners"
    ],
    "wof:name":"Place Canpiac",
    "wof:placetype":"venue"
},
  "geometry": {"coordinates":[-73.5263366699,45.3983726501],"type":"Point"}
}