{
  "type": "Feature",
  "properties": {
    "addr:full":"7507 Main St Louisbourg NS B1C 1H8",
    "addr:housenumber":"7507",
    "addr:postcode":"b1c 1h8",
    "addr:street":"Main St",
    "iso:country":"CA",
    "sg:address":"7507 Main St",
    "sg:city":"Louisbourg",
    "sg:classifiers":[
        {
            "category":"Food & Beverages",
            "subcategory":"Groceries & Convenience Stores",
            "type":"Retail Goods"
        }
    ],
    "sg:phone":"+1 902 733 2212",
    "sg:postcode":"B1C 1H8",
    "sg:province":"NS",
    "sg:tags":[
        "grocer"
    ],
    "wof:name":"Town Dairy",
    "wof:placetype":"venue"
},
  "geometry": {"coordinates":[-59.970531,45.921047],"type":"Point"}
}