{
  "type": "Feature",
  "properties": {
    "addr:full":"36217 97th St Oliver BC V0H 1T0",
    "addr:housenumber":"36217",
    "addr:postcode":"bc v0h 1t0",
    "addr:street":"97Th St",
    "iso:country":"CA",
    "sg:address":"36217 97th St",
    "sg:city":"Oliver",
    "sg:classifiers":[
        {
            "category":"Organizations",
            "subcategory":"Community Association",
            "type":"Services"
        }
    ],
    "sg:phone":"+1 250 498 3868",
    "sg:postcode":"V0H 1T0",
    "sg:province":"BC",
    "sg:tags":[
        "club"
    ],
    "wof:name":"Royal Canadian Legion",
    "wof:placetype":"venue"
},
  "geometry": {"coordinates":[-119.550186157,49.1856536865],"type":"Point"}
}