{
  "type": "Feature",
  "properties": {
    "addr:full":"456 Parliament St Toronto ON M5A 3A2",
    "addr:housenumber":"456",
    "addr:postcode":"m5a 3a2",
    "addr:street":"Parliament St",
    "iso:country":"CA",
    "sg:address":"456 Parliament St",
    "sg:city":"Toronto",
    "sg:classifiers":[
        {
            "category":"Restaurant",
            "type":"Food & Drink"
        }
    ],
    "sg:phone":"+1 416 925 4074",
    "sg:postcode":"M5A 3A2",
    "sg:province":"ON",
    "sg:tags":[
        "pub"
    ],
    "wof:name":"House of Parliament St",
    "wof:placetype":"venue"
},
  "geometry": {"coordinates":[-79.36792,43.663685],"type":"Point"}
}