{
  "type": "Feature",
  "properties": {
    "addr:full":"24 Ch DE LA Montagne Messines QC J0X 2J0",
    "addr:housenumber":"24",
    "addr:postcode":"j0x 2j0",
    "addr:street":"Ch De La Montagne",
    "iso:country":"CA",
    "sg:address":"24 Ch DE LA Montagne",
    "sg:city":"Messines",
    "sg:classifiers":[
        {
            "category":"Travel",
            "subcategory":"Hotels & Motels",
            "type":"Entertainment"
        }
    ],
    "sg:phone":"+1 819 465 2202",
    "sg:postcode":"J0X 2J0",
    "sg:province":"QC",
    "sg:tags":[
        "breakfast",
        "inn",
        "bed",
        "accommodation"
    ],
    "wof:name":"Auberge Maison LA Cremaillere",
    "wof:placetype":"venue"
},
  "geometry": {"coordinates":[-76.03336299999999,46.259163],"type":"Point"}
}