{
  "type": "Feature",
  "properties": {
    "addr:full":"2325 Boul Rome Brossard QC J4Y 1P8",
    "addr:housenumber":"2325",
    "addr:postcode":"j4y 1p8",
    "addr:street":"Boul Rome",
    "iso:country":"CA",
    "sg:address":"2325 Boul Rome",
    "sg:city":"Brossard",
    "sg:classifiers":[
        {
            "category":"Real Estate",
            "subcategory":"Developer",
            "type":"Services"
        }
    ],
    "sg:phone":"+1 450 676 7755",
    "sg:postcode":"J4Y 1P8",
    "sg:province":"QC",
    "sg:tags":[
        "company",
        "land"
    ],
    "wof:name":"Aster Corp",
    "wof:placetype":"venue"
},
  "geometry": {"coordinates":[-73.464539,45.454605],"type":"Point"}
}