{
  "type": "Feature",
  "properties": {
    "addr:full":"17 Carson St Moorefield ON N0G 2K0",
    "addr:housenumber":"17",
    "addr:postcode":"n0g 2k0",
    "addr:street":"Carson St",
    "iso:country":"CA",
    "sg:address":"17 Carson St",
    "sg:city":"Moorefield",
    "sg:classifiers":[
        {
            "category":"Building & Trades",
            "subcategory":"Construction",
            "type":"Services"
        }
    ],
    "sg:phone":"+1 519 638 3513",
    "sg:postcode":"N0G 2K0",
    "sg:province":"ON",
    "sg:tags":[
        "home",
        "improvement"
    ],
    "wof:name":"Grant Morgan Carpentry",
    "wof:placetype":"venue"
},
  "geometry": {"coordinates":[-80.748856,43.760681],"type":"Point"}
}