{
  "type": "Feature",
  "properties": {
    "addr:full":"20 S Plains Rd Emerald Park SK S4L 1B7",
    "addr:housenumber":"20",
    "addr:postcode":"s4l 1b7",
    "addr:street":"S Plains Rd;Park",
    "iso:country":"CA",
    "sg:address":"20 S Plains Rd",
    "sg:city":"Emerald Park",
    "sg:classifiers":[
        {
            "category":"Wholesale",
            "subcategory":"Electrical",
            "type":"Manufacturing & Wholesale Goods"
        }
    ],
    "sg:phone":"+1 306 781 4451",
    "sg:postcode":"S4L 1B7",
    "sg:province":"SK",
    "sg:tags":[
        "assembler",
        "electronic",
        "parts",
        "manufacturer"
    ],
    "wof:name":"Digital Communications Inc",
    "wof:placetype":"venue"
},
  "geometry": {"coordinates":[-104.388901,50.451626],"type":"Point"}
}