{
  "type": "Feature",
  "properties": {
    "addr:full":"Kingston ON K7K 5W7",
    "addr:postcode":"k7k 5w7",
    "iso:country":"CA",
    "sg:city":"Kingston",
    "sg:classifiers":[
        {
            "category":"Professional",
            "subcategory":"Lawyer & Legal Services",
            "type":"Services"
        }
    ],
    "sg:phone":"+1 613 542 6510",
    "sg:postcode":"K7K 5W7",
    "sg:province":"ON",
    "sg:tags":[
        "attorney"
    ],
    "wof:name":"Hodkinson, Sharon M",
    "wof:placetype":"venue"
},
  "geometry": {"coordinates":[-76.483932,44.232182],"type":"Point"}
}