{
  "type": "Feature",
  "properties": {
    "addr:full":"15 Rue Saint-Pierre Quebec QC G1K 3Z3",
    "addr:housenumber":"15",
    "addr:postcode":"g1k 3z3",
    "addr:street":"Rue Saint-Pierre",
    "iso:country":"CA",
    "sg:address":"15 Rue Saint-Pierre",
    "sg:city":"Quebec",
    "sg:classifiers":[
        {
            "category":"Shopping",
            "subcategory":"Hobbies, Toys, & Games",
            "type":"Retail Goods"
        }
    ],
    "sg:phone":"+1 418 692 0239",
    "sg:postcode":"G1K 3Z3",
    "sg:province":"QC",
    "sg:tags":[
        "craft"
    ],
    "wof:name":"Boutique Tradition",
    "wof:placetype":"venue"
},
  "geometry": {"coordinates":[-71.202499,46.813347],"type":"Point"}
}