{
  "type": "Feature",
  "properties": {
    "addr:full":"5284 Ferry St Niagara Falls ON L2G 1R5",
    "addr:housenumber":"5284",
    "addr:postcode":"l2g 1r5",
    "addr:street":"Ferry St",
    "iso:country":"CA",
    "sg:address":"5284 Ferry St",
    "sg:city":"Niagara Falls",
    "sg:classifiers":[
        {
            "category":"Travel",
            "subcategory":"Hotels & Motels",
            "type":"Entertainment"
        }
    ],
    "sg:phone":"+1 905 354 2632",
    "sg:postcode":"L2G 1R5",
    "sg:province":"ON",
    "wof:name":"AAA Royal Motel",
    "wof:placetype":"venue"
},
  "geometry": {"coordinates":[-79.080269,43.089588],"type":"Point"}
}