{
  "type": "Feature",
  "properties": {
    "addr:full":"Farm Maymont SK S0M 1T0",
    "addr:postcode":"s0m 1t0",
    "iso:country":"CA",
    "sg:address":"Farm",
    "sg:city":"Maymont",
    "sg:classifiers":[
        {
            "category":"Farming",
            "subcategory":"Farm & Veterinary Services",
            "type":"Manufacturing & Wholesale Goods"
        }
    ],
    "sg:phone":"+1 306 389 2434",
    "sg:postcode":"S0M 1T0",
    "sg:province":"SK",
    "sg:tags":[
        "seed",
        "grain",
        "cleaning"
    ],
    "wof:name":"Welford Seed Cleaning",
    "wof:placetype":"venue"
},
  "geometry": {"coordinates":[-107.707359314,52.5624656677],"type":"Point"}
}