{
  "type": "Feature",
  "properties": {
    "addr:full":"Ile Cote Daveluyville QC G0Z 1C0",
    "addr:postcode":"g0z 1c0",
    "addr:street":"Ile Cote",
    "iso:country":"CA",
    "sg:address":"Ile Cote",
    "sg:city":"Daveluyville",
    "sg:classifiers":[
        {
            "category":"Government",
            "subcategory":"Office",
            "type":"Public Place"
        }
    ],
    "sg:phone":"+1 819 367 2214",
    "sg:postcode":"G0Z 1C0",
    "sg:province":"QC",
    "sg:tags":[
        "village"
    ],
    "wof:name":"Daveluyville Usine-Filtration",
    "wof:placetype":"venue"
},
  "geometry": {"coordinates":[-72.136787,46.20293],"type":"Point"}
}