{
  "type": "Feature",
  "properties": {
    "addr:full":"144 Fifth Ave Brantford ON N3S 7T7",
    "addr:housenumber":"144",
    "addr:postcode":"n3s 7t7",
    "addr:street":"Fifth Ave",
    "iso:country":"CA",
    "sg:address":"144 Fifth Ave",
    "sg:city":"Brantford",
    "sg:classifiers":[
        {
            "category":"Real Estate",
            "subcategory":"Real Estate Operator",
            "type":"Services"
        }
    ],
    "sg:phone":"+1 519 756 2444",
    "sg:postcode":"N3S 7T7",
    "sg:province":"ON",
    "sg:tags":[
        "apartment"
    ],
    "wof:name":"Slovak Village Brantford",
    "wof:placetype":"venue"
},
  "geometry": {"coordinates":[-80.2495269775,43.1198501587],"type":"Point"}
}