{
  "type": "Feature",
  "properties": {
    "addr:full":"1400 Boul Saint-Jean-Baptiste # 9 Pointe-Aux-Trembles QC H1B 4A5",
    "addr:housenumber":"1400",
    "addr:postcode":"h1b 4a5",
    "addr:street":"Boul Saint-Jean-Baptiste # 9 Pointe-Aux-Trembles",
    "iso:country":"CA",
    "sg:address":"1400 Boul Saint-Jean-Baptiste # 9",
    "sg:city":"Pointe-Aux-Trembles",
    "sg:classifiers":[
        {
            "category":"Restaurant",
            "type":"Food & Drink"
        }
    ],
    "sg:phone":"+1 514 645 8843",
    "sg:postcode":"H1B 4A5",
    "sg:province":"QC",
    "wof:name":"Restaurant LA Gironde",
    "wof:placetype":"venue"
},
  "geometry": {"coordinates":[-73.5031204224,45.6419258118],"type":"Point"}
}