{
  "type": "Feature",
  "properties": {
    "addr:full":"400 Bloor St W Toronto ON M5S 1X5",
    "addr:housenumber":"400",
    "addr:postcode":"m5s 1x5",
    "addr:street":"Bloor St W",
    "iso:country":"CA",
    "sg:address":"400 Bloor St W",
    "sg:city":"Toronto",
    "sg:classifiers":[
        {
            "category":"Restaurant",
            "type":"Food & Drink"
        }
    ],
    "sg:phone":"+1 416 967 4295",
    "sg:postcode":"M5S 1X5",
    "sg:province":"ON",
    "wof:name":"By the Way Cafe",
    "wof:placetype":"venue"
},
  "geometry": {"coordinates":[-79.407616,43.665947],"type":"Point"}
}