{
  "type": "Feature",
  "properties": {
    "addr:full":"105 Fairview Ave St Thomas ON N5R 4X7",
    "addr:housenumber":"105",
    "addr:postcode":"n5r 4x7",
    "addr:street":"Fairview Ave",
    "iso:country":"CA",
    "sg:address":"105 Fairview Ave",
    "sg:city":"St Thomas",
    "sg:classifiers":[
        {
            "category":"Organizations",
            "subcategory":"Religious Organization",
            "type":"Services"
        }
    ],
    "sg:phone":"+1 519 633 2370",
    "sg:postcode":"N5R 4X7",
    "sg:province":"ON",
    "sg:tags":[
        "church"
    ],
    "wof:name":"Church of Jesus Christ of Lds",
    "wof:placetype":"venue"
},
  "geometry": {"coordinates":[-81.1661529541,42.7667388916],"type":"Point"}
}