{
  "type": "Feature",
  "properties": {
    "addr:full":"1051 111 Rte E Amos QC J9T 1N2",
    "addr:housenumber":"1051",
    "addr:postcode":"j9t 1n2",
    "addr:street":"111 Rte E Amos",
    "iso:country":"CA",
    "sg:address":"1051 111 Rte E",
    "sg:city":"Amos",
    "sg:classifiers":[
        {
            "category":"Autos & Motor Vehicles",
            "subcategory":"Automobile Sales",
            "type":"Retail Goods"
        }
    ],
    "sg:phone":"+1 819 732 0404",
    "sg:postcode":"J9T 1N2",
    "sg:province":"QC",
    "sg:tags":[
        "car",
        "dealer"
    ],
    "wof:name":"Cloutier Automobiles Inc",
    "wof:placetype":"venue"
},
  "geometry": {"coordinates":[-78.101906,48.560261],"type":"Point"}
}