{
  "type": "Feature",
  "properties": {
    "addr:full":"25 Brunetville Rd Kapuskasing ON P5N 2E9",
    "addr:housenumber":"25",
    "addr:postcode":"p5n 2e9",
    "addr:street":"Brunetville Rd",
    "iso:country":"CA",
    "sg:address":"25 Brunetville Rd",
    "sg:city":"Kapuskasing",
    "sg:classifiers":[
        {
            "category":"Shopping",
            "subcategory":"Florist",
            "type":"Retail Goods"
        }
    ],
    "sg:phone":"+1 705 335 4235",
    "sg:postcode":"P5N 2E9",
    "sg:province":"ON",
    "wof:name":"Blooming Bouquet Flower & Gift",
    "wof:placetype":"venue"
},
  "geometry": {"coordinates":[-82.41963199999999,49.419945],"type":"Point"}
}