{
  "type": "Feature",
  "properties": {
    "iso:country":"CA",
    "sg:address":"2522 Rue Beaubien E",
    "sg:city":"Montreal",
    "sg:classifiers":[
        {
            "category":"Retail",
            "subcategory":"Self-service Laundry",
            "type":"Services"
        }
    ],
    "sg:phone":"+1 514 376 8265",
    "sg:postcode":"H1Y 1G2",
    "sg:province":"QC",
    "wof:name":"Buanderie Mousse Cafe",
    "wof:placetype":"venue"
},
  "geometry": {"coordinates":[-73.5916213989,45.5489883423],"type":"Point"}
}