{
  "type": "Feature",
  "properties": {
    "addr:full":"North York ON M9L 1N6",
    "addr:postcode":"m9l 1n6",
    "iso:country":"CA",
    "sg:city":"North York",
    "sg:classifiers":[
        {
            "category":"Wholesale",
            "subcategory":"Hardware",
            "type":"Manufacturing & Wholesale Goods"
        }
    ],
    "sg:phone":"+1 416 744 2634",
    "sg:postcode":"M9L 1N6",
    "sg:province":"ON",
    "wof:name":"Tiip International Inc",
    "wof:placetype":"venue"
},
  "geometry": {"coordinates":[-79.537468,43.766384],"type":"Point"}
}