{
  "type": "Feature",
  "properties": {
    "addr:full":"3154 Hurontario St Mississauga ON L5B 1N9",
    "addr:housenumber":"3154",
    "addr:postcode":"l5b 1n9",
    "addr:street":"Hurontario St",
    "iso:country":"CA",
    "sg:address":"3154 Hurontario St",
    "sg:city":"Mississauga",
    "sg:classifiers":[
        {
            "category":"Food & Beverages",
            "subcategory":"Groceries & Convenience Stores",
            "type":"Retail Goods"
        }
    ],
    "sg:phone":"+1 905 273 4000",
    "sg:postcode":"L5B 1N9",
    "sg:province":"ON",
    "wof:name":"Hasty Market",
    "wof:placetype":"venue"
},
  "geometry": {"coordinates":[-79.62097167970001,43.5834159851],"type":"Point"}
}