{
  "type": "Feature",
  "properties": {
    "iso:country":"CA",
    "sg:city":"Calgary",
    "sg:classifiers":[
        {
            "category":"Professional",
            "subcategory":"Lawyer & Legal Services",
            "type":"Services"
        }
    ],
    "sg:phone":"+1 403 232 8300",
    "sg:postcode":"T2P 3S8",
    "sg:province":"AB",
    "sg:tags":[
        "attorney"
    ],
    "wof:name":"Yasui, Dennis K",
    "wof:placetype":"venue"
},
  "geometry": {"coordinates":[-114.07231903100001,51.0459480286],"type":"Point"}
}