{
  "type": "Feature",
  "properties": {
    "addr:full":"501 4th Ave E Assiniboia SK S0H 0B0",
    "addr:housenumber":"501",
    "addr:postcode":"s0h 0b0",
    "addr:street":"4Th Ave E Assiniboia",
    "iso:country":"CA",
    "sg:address":"501 4th Ave E",
    "sg:city":"Assiniboia",
    "sg:classifiers":[
        {
            "category":"Social Services",
            "subcategory":"Child Care",
            "type":"Services"
        }
    ],
    "sg:phone":"+1 306 642 3337",
    "sg:postcode":"S0H 0B0",
    "sg:province":"SK",
    "wof:name":"Assiniboia Child Care Svc",
    "wof:placetype":"venue"
},
  "geometry": {"coordinates":[-105.98747299999999,49.630386],"type":"Point"}
}