{
  "type": "Feature",
  "properties": {
    "addr:full":"Charlesbourg QC G1H 3L2",
    "addr:postcode":"g1h 3l2",
    "iso:country":"CA",
    "sg:city":"Charlesbourg",
    "sg:classifiers":[
        {
            "category":"Professional",
            "subcategory":"Art Services",
            "type":"Services"
        }
    ],
    "sg:phone":"+1 418 622 2259",
    "sg:postcode":"G1H 3L2",
    "sg:province":"QC",
    "sg:tags":[
        "graphic",
        "designer"
    ],
    "wof:name":"Perfection Design",
    "wof:placetype":"venue"
},
  "geometry": {"coordinates":[-71.2568817139,46.8558883667],"type":"Point"}
}