{
  "type": "Feature",
  "properties": {
    "addr:full":"1135 Hwy 132 Rd Renfrew ON K7V 3Z5",
    "addr:housenumber":"1135",
    "addr:postcode":"k7v 3z5",
    "addr:street":"Hwy 132 Rd",
    "iso:country":"CA",
    "sg:address":"1135 Hwy 132 Rd",
    "sg:city":"Renfrew",
    "sg:classifiers":[
        {
            "category":"Building & Trades",
            "subcategory":"Plumbing",
            "type":"Services"
        }
    ],
    "sg:phone":"+1 613 432 2882",
    "sg:postcode":"K7V 3Z5",
    "sg:province":"ON",
    "sg:tags":[
        "refrigeration",
        "contractor"
    ],
    "wof:name":"Hill Refrigeration",
    "wof:placetype":"venue"
},
  "geometry": {"coordinates":[-76.6880874634,45.4744987488],"type":"Point"}
}