{
  "type": "Feature",
  "properties": {
    "addr:full":"1057 Rue Principale E Magog QC J1X 1Z6",
    "addr:housenumber":"1057",
    "addr:postcode":"j1x 1z6",
    "addr:street":"Rue Principale E",
    "iso:country":"CA",
    "sg:address":"1057 Rue Principale E",
    "sg:city":"Magog",
    "sg:classifiers":[
        {
            "category":"Retail",
            "subcategory":"Auto Repair",
            "type":"Services"
        }
    ],
    "sg:phone":"+1 819 843 2918",
    "sg:postcode":"J1X 1Z6",
    "sg:province":"QC",
    "sg:tags":[
        "repairing",
        "automobile"
    ],
    "wof:name":"M D Cote Inc",
    "wof:placetype":"venue"
},
  "geometry": {"coordinates":[-72.13092041020001,45.2606468201],"type":"Point"}
}