{
  "type": "Feature",
  "properties": {
    "addr:full":"1590 Av Jules-Verne Sainte-Foy QC G2G 2R5",
    "addr:housenumber":"1590",
    "addr:postcode":"g2g 2r5",
    "addr:street":"Av Jules-Verne",
    "iso:country":"CA",
    "sg:address":"1590 Av Jules-Verne",
    "sg:city":"Sainte-Foy",
    "sg:classifiers":[
        {
            "category":"Sports & Exercise",
            "subcategory":"Bowling",
            "type":"Entertainment"
        }
    ],
    "sg:phone":"+1 418 877 8866",
    "sg:postcode":"G2G 2R5",
    "sg:province":"QC",
    "sg:tags":[
        "center"
    ],
    "wof:name":"Quillorama Duplessis",
    "wof:placetype":"venue"
},
  "geometry": {"coordinates":[-71.3513412476,46.7785072327],"type":"Point"}
}