{
  "type": "Feature",
  "properties": {
    "addr:full":"2301 Clark Rd Courtenay BC V9J 1T1",
    "addr:housenumber":"2301",
    "addr:postcode":"v9j 1t1",
    "addr:street":"Clark Rd",
    "iso:country":"CA",
    "sg:address":"2301 Clark Rd",
    "sg:city":"Courtenay",
    "sg:classifiers":[
        {
            "category":"Farming",
            "subcategory":"Poultry Farm",
            "type":"Manufacturing & Wholesale Goods"
        }
    ],
    "sg:phone":"+1 250 338 8227",
    "sg:postcode":"V9J 1T1",
    "sg:province":"BC",
    "sg:tags":[
        "emu",
        "ostrich"
    ],
    "wof:name":"Outback Emuzing Ranch",
    "wof:placetype":"venue"
},
  "geometry": {"coordinates":[-124.993141174,49.6867218018],"type":"Point"}
}