{
  "type": "Feature",
  "properties": {
    "addr:full":"78 7E Rue Montmagny QC G5V 3H1",
    "addr:housenumber":"78",
    "addr:postcode":"g5v 3h1",
    "addr:street":"7E Rue Montmagny",
    "iso:country":"CA",
    "sg:address":"78 7E Rue",
    "sg:city":"Montmagny",
    "sg:classifiers":[
        {
            "category":"Personal",
            "subcategory":"Beauty Salon",
            "type":"Services"
        }
    ],
    "sg:phone":"+1 418 248 6043",
    "sg:postcode":"G5V 3H1",
    "sg:province":"QC",
    "wof:name":"Salon Audrey",
    "wof:placetype":"venue"
},
  "geometry": {"coordinates":[-70.566177,46.975342],"type":"Point"}
}