{
  "type": "Feature",
  "properties": {
    "addr:full":"187 1Er Boulevard Terrasse-Vaudreuil QC J7V 5T8",
    "addr:housenumber":"187",
    "addr:postcode":"j7v 5t8",
    "addr:street":"1Er Boulevard",
    "iso:country":"CA",
    "sg:address":"187 1Er Boulevard",
    "sg:city":"Terrasse-Vaudreuil",
    "sg:classifiers":[
        {
            "category":"Professional",
            "subcategory":"Business Services",
            "type":"Services"
        }
    ],
    "sg:phone":"+1 514 453 1661",
    "sg:postcode":"J7V 5T8",
    "sg:province":"QC",
    "sg:tags":[
        "translator",
        "interpreter"
    ],
    "wof:name":"Lyne Gagnon Svc D'Affaires",
    "wof:placetype":"venue"
},
  "geometry": {"coordinates":[-73.988083,45.393089],"type":"Point"}
}