{
  "type": "Feature",
  "properties": {
    "addr:full":"407 Eighth St New Westminster BC V3M 3R5",
    "addr:housenumber":"407",
    "addr:postcode":"v3m 3r5",
    "addr:street":"Eighth St",
    "iso:country":"CA",
    "sg:address":"407 Eighth St",
    "sg:city":"New Westminster",
    "sg:classifiers":[
        {
            "category":"Retail",
            "subcategory":"Laundry & Dry Cleaning",
            "type":"Services"
        }
    ],
    "sg:phone":"+1 604 522 7991",
    "sg:postcode":"V3M 3R5",
    "sg:province":"BC",
    "sg:tags":[
        "cleaners"
    ],
    "wof:name":"Star Cleaners Ltd",
    "wof:placetype":"venue"
},
  "geometry": {"coordinates":[-122.92049408,49.2086448669],"type":"Point"}
}