{
  "type": "Feature",
  "properties": {
    "addr:full":"Calgary AB T2P 0Z3",
    "addr:postcode":"t2p 0z3",
    "iso:country":"CA",
    "sg:city":"Calgary",
    "sg:classifiers":[
        {
            "category":"Shopping",
            "subcategory":"Tobacco",
            "type":"Retail Goods"
        }
    ],
    "sg:phone":"+1 403 265 8756",
    "sg:postcode":"T2P 0Z3",
    "sg:province":"AB",
    "sg:tags":[
        "cigarette",
        "cigar",
        "dealer"
    ],
    "wof:name":"Aladdins News & Smoke Shop",
    "wof:placetype":"venue"
},
  "geometry": {"coordinates":[-114.076843262,51.0467338562],"type":"Point"}
}