{
  "type": "Feature",
  "properties": {
    "iso:country":"CA",
    "sg:address":"5 Miles Ave",
    "sg:city":"Kingston",
    "sg:classifiers":[
        {
            "category":"Social Services",
            "subcategory":"Child Care",
            "type":"Services"
        }
    ],
    "sg:phone":"+1 613 546 2911",
    "sg:postcode":"K7M 7G7",
    "sg:province":"ON",
    "wof:name":"West End Childrens' Ctr",
    "wof:placetype":"venue"
},
  "geometry": {"coordinates":[-76.52755737299999,44.2348175049],"type":"Point"}
}