{
  "type": "Feature",
  "properties": {
    "addr:full":"Rothesay NB E2E 2N6",
    "addr:postcode":"e2e 2n6",
    "iso:country":"CA",
    "sg:city":"Rothesay",
    "sg:classifiers":[
        {
            "category":"Food & Beverages",
            "subcategory":"Bakery",
            "type":"Retail Goods"
        }
    ],
    "sg:phone":"+1 506 849 1437",
    "sg:postcode":"E2E 2N6",
    "sg:province":"NB",
    "sg:tags":[
        "baker"
    ],
    "wof:name":"Mc Phee's Home Bakery",
    "wof:placetype":"venue"
},
  "geometry": {"coordinates":[-65.97726400000001,45.40041],"type":"Point"}
}