{
  "type": "Feature",
  "properties": {
    "addr:full":"806 3rd St W Meadow Lake SK S9X 1C3",
    "addr:housenumber":"806",
    "addr:postcode":"s9x 1c3",
    "addr:street":"3Rd St W Meadow",
    "iso:country":"CA",
    "sg:address":"806 3rd St W",
    "sg:city":"Meadow Lake",
    "sg:classifiers":[
        {
            "category":"Building & Trades",
            "subcategory":"Electrical",
            "type":"Services"
        }
    ],
    "sg:phone":"+1 306 236 5562",
    "sg:postcode":"S9X 1C3",
    "sg:province":"SK",
    "sg:tags":[
        "electric",
        "contractor"
    ],
    "wof:name":"Lawrence Dubray Electric Ltd",
    "wof:placetype":"venue"
},
  "geometry": {"coordinates":[-108.43782,54.130974],"type":"Point"}
}