{
  "type": "Feature",
  "properties": {
    "addr:full":"1141 Rue Notre-Dame Saint-Sulpice QC J5W 3W2",
    "addr:housenumber":"1141",
    "addr:postcode":"j5w 3w2",
    "addr:street":"Rue Notre-Dame",
    "iso:country":"CA",
    "sg:address":"1141 Rue Notre-Dame",
    "sg:city":"Saint-Sulpice",
    "sg:classifiers":[
        {
            "category":"Food & Beverages",
            "subcategory":"Groceries & Convenience Stores",
            "type":"Retail Goods"
        }
    ],
    "sg:phone":"+1 450 589 4466",
    "sg:postcode":"J5W 3W2",
    "sg:province":"QC",
    "sg:tags":[
        "grocer"
    ],
    "wof:name":"Marche D'Alimentation",
    "wof:placetype":"venue"
},
  "geometry": {"coordinates":[-73.354141,45.827312],"type":"Point"}
}