{
  "type": "Feature",
  "properties": {
    "addr:full":"Salt Spring Island BC V8K 2M4",
    "addr:postcode":"v8k 2m4",
    "iso:country":"CA",
    "sg:city":"Salt Spring Island",
    "sg:classifiers":[
        {
            "category":"Building & Trades",
            "subcategory":"Equipment Rental",
            "type":"Services"
        }
    ],
    "sg:phone":"+1 250 538 0388",
    "sg:postcode":"V8K 2M4",
    "sg:province":"BC",
    "sg:tags":[
        "yard"
    ],
    "wof:name":"Rental Stop",
    "wof:placetype":"venue"
},
  "geometry": {"coordinates":[-123.516067505,48.8540611267],"type":"Point"}
}