{
  "type": "Feature",
  "properties": {
    "addr:full":"48 Main St Courtland ON N0J 1E0",
    "addr:housenumber":"48",
    "addr:postcode":"n0j 1e0",
    "addr:street":"Main St",
    "iso:country":"CA",
    "sg:address":"48 Main St",
    "sg:city":"Courtland",
    "sg:classifiers":[
        {
            "category":"Home & Garden",
            "subcategory":"Garden Supply",
            "type":"Retail Goods"
        }
    ],
    "sg:phone":"+1 519 688 0370",
    "sg:postcode":"N0J 1E0",
    "sg:province":"ON",
    "sg:tags":[
        "equipment",
        "snow",
        "removal"
    ],
    "wof:name":"Trackless Vehicles Ltd",
    "wof:placetype":"venue"
},
  "geometry": {"coordinates":[-80.6463851929,42.8436660767],"type":"Point"}
}