{
  "type": "Feature",
  "properties": {
    "addr:full":"101 Old Beaverbank Rd Lower Sackville NS B4E 1V4",
    "addr:housenumber":"101",
    "addr:postcode":"ns b4e 1v4",
    "addr:street":"Old Beaverbank Rd Lower",
    "iso:country":"CA",
    "sg:address":"101 Old Beaverbank Rd",
    "sg:city":"Lower Sackville",
    "sg:classifiers":[
        {
            "category":"Organizations",
            "subcategory":"Community Association",
            "type":"Services"
        }
    ],
    "sg:phone":"+1 902 865 2039",
    "sg:postcode":"B4E 1V4",
    "sg:province":"NS",
    "sg:tags":[
        "club"
    ],
    "wof:name":"Sackville Lions Club",
    "wof:placetype":"venue"
},
  "geometry": {"coordinates":[-63.689926,44.774502],"type":"Point"}
}