{
  "type": "Feature",
  "properties": {
    "iso:country":"CA",
    "sg:address":"2470 Rebecca St",
    "sg:city":"Oakville",
    "sg:classifiers":[
        {
            "category":"Real Estate",
            "subcategory":"Architect",
            "type":"Services"
        }
    ],
    "sg:phone":"+1 905 825 3359",
    "sg:postcode":"L6L 2B2",
    "sg:province":"ON",
    "sg:tags":[
        "specification",
        "architectural"
    ],
    "wof:name":"Brian Ballantyne Specification",
    "wof:placetype":"venue"
},
  "geometry": {"coordinates":[-79.71981,43.397896],"type":"Point"}
}