{
  "type": "Feature",
  "properties": {
    "iso:country":"CA",
    "sg:city":"Sayabec",
    "sg:classifiers":[
        {
            "category":"Professional",
            "subcategory":"Business Services",
            "type":"Services"
        }
    ],
    "sg:phone":"+1 418 536 5461",
    "sg:postcode":"G0J 3K0",
    "sg:province":"QC",
    "sg:tags":[
        "notary"
    ],
    "wof:name":"Chabot, Pierre",
    "wof:placetype":"venue"
},
  "geometry": {"coordinates":[-67.68143463129999,48.5662612915],"type":"Point"}
}