{
  "type": "Feature",
  "properties": {
    "addr:full":"2828 Saint Paul Ave Niagara Falls ON L2J 2L4",
    "addr:housenumber":"2828",
    "addr:postcode":"l2j 2l4",
    "addr:street":"Saint Paul Ave",
    "iso:country":"CA",
    "sg:address":"2828 Saint Paul Ave",
    "sg:city":"Niagara Falls",
    "sg:classifiers":[
        {
            "category":"Autos & Motor Vehicles",
            "subcategory":"Automobile Sales",
            "type":"Retail Goods"
        }
    ],
    "sg:phone":"+1 905 356 9131",
    "sg:postcode":"L2J 2L4",
    "sg:province":"ON",
    "sg:tags":[
        "car",
        "dealer"
    ],
    "wof:name":"Little Brothers Car Sales",
    "wof:placetype":"venue"
},
  "geometry": {"coordinates":[-79.0998,43.13179],"type":"Point"}
}