{
  "type": "Feature",
  "properties": {
    "iso:country":"CA",
    "sg:city":"Saint-Laurent",
    "sg:classifiers":[
        {
            "category":"Freight",
            "type":"Transportation"
        }
    ],
    "sg:phone":"+1 514 748 2110",
    "sg:postcode":"H4M 2P5",
    "sg:province":"QC",
    "wof:name":"Premier Cargo Inc",
    "wof:placetype":"venue"
},
  "geometry": {"coordinates":[-73.676857,45.496281],"type":"Point"}
}