{
  "type": "Feature",
  "properties": {
    "addr:full":"North Vancouver BC V7J 2C2",
    "addr:postcode":"v7j 2c2",
    "iso:country":"CA",
    "sg:city":"North Vancouver",
    "sg:classifiers":[
        {
            "category":"Autos & Motor Vehicles",
            "subcategory":"Auto Supplies",
            "type":"Retail Goods"
        }
    ],
    "sg:phone":"+1 604 985 4221",
    "sg:postcode":"V7J 2C2",
    "sg:province":"BC",
    "sg:tags":[
        "tire"
    ],
    "wof:name":"Kal Tire",
    "wof:placetype":"venue"
},
  "geometry": {"coordinates":[-123.04022999999999,49.309872],"type":"Point"}
}