{
  "type": "Feature",
  "properties": {
    "addr:full":"110 Blair Ave Tatamagouche NS B0K 1V0",
    "addr:housenumber":"110",
    "addr:postcode":"b0k 1v0",
    "addr:street":"Blair Ave",
    "iso:country":"CA",
    "sg:address":"110 Blair Ave",
    "sg:city":"Tatamagouche",
    "sg:classifiers":[
        {
            "category":"Health Services",
            "subcategory":"Hospital",
            "type":"Services"
        }
    ],
    "sg:phone":"+1 902 657 2382",
    "sg:postcode":"B0K 1V0",
    "sg:province":"NS",
    "wof:name":"Lillian Fraser Memorial Hsptl",
    "wof:placetype":"venue"
},
  "geometry": {"coordinates":[-63.296295,45.711887],"type":"Point"}
}