{
  "type": "Feature",
  "properties": {
    "addr:full":"211 Gallagher Ridge Rd Gallagher Ridge NB E1G 3A6",
    "addr:housenumber":"211",
    "addr:postcode":"e1g 3a6",
    "addr:street":"Gallagher Ridge Rd",
    "iso:country":"CA",
    "sg:address":"211 Gallagher Ridge Rd",
    "sg:city":"Gallagher Ridge",
    "sg:classifiers":[
        {
            "category":"Manufacturing",
            "subcategory":"Lumber",
            "type":"Manufacturing & Wholesale Goods"
        }
    ],
    "sg:phone":"+1 506 857 2294",
    "sg:postcode":"E1G 3A6",
    "sg:province":"NB",
    "wof:name":"Two By Four Lumber Sales Ltd",
    "wof:placetype":"venue"
},
  "geometry": {"coordinates":[-65.046585083,46.201965332],"type":"Point"}
}