{
  "type": "Feature",
  "properties": {
    "addr:full":"649 Hastings St E Vancouver BC V6A 1R2",
    "addr:housenumber":"649",
    "addr:postcode":"v6a 1r2",
    "addr:street":"Hastings St E",
    "iso:country":"CA",
    "sg:address":"649 Hastings St E",
    "sg:city":"Vancouver",
    "sg:classifiers":[
        {
            "category":"Wholesale",
            "subcategory":"Apparel",
            "type":"Manufacturing & Wholesale Goods"
        }
    ],
    "sg:phone":"+1 604 253 7711",
    "sg:postcode":"V6A 1R2",
    "sg:province":"BC",
    "wof:name":"Mecca Enterprises",
    "wof:placetype":"venue"
},
  "geometry": {"coordinates":[-123.090462,49.281281],"type":"Point"}
}