{
  "type": "Feature",
  "properties": {
    "iso:country":"CA",
    "sg:address":"1171 Broder St",
    "sg:city":"Regina",
    "sg:classifiers":[
        {
            "category":"Organizations",
            "subcategory":"Religious Organization",
            "type":"Services"
        }
    ],
    "sg:phone":"+1 306 569 0794",
    "sg:postcode":"S4N 3R1",
    "sg:province":"SK",
    "sg:tags":[
        "church"
    ],
    "wof:name":"St Charles Church & Rectory",
    "wof:placetype":"venue"
},
  "geometry": {"coordinates":[-104.590637207,50.4603614807],"type":"Point"}
}