{
  "type": "Feature",
  "properties": {
    "iso:country":"CA",
    "sg:address":"295 DE L Eglise",
    "sg:city":"Saint-Claude",
    "sg:classifiers":[
        {
            "category":"Health Services",
            "subcategory":"Doctor",
            "type":"Services"
        }
    ],
    "sg:phone":"+1 819 845 4800",
    "sg:postcode":"J0B 2N0",
    "sg:province":"QC",
    "sg:tags":[
        "physician",
        "surgeon"
    ],
    "wof:name":"Jacot, Francis MD",
    "wof:placetype":"venue"
},
  "geometry": {"coordinates":[-71.97621917719999,45.659236908],"type":"Point"}
}