{
  "type": "Feature",
  "properties": {
    "addr:full":"5725 Ch DE Chambly Saint-Hubert QC J3Y 3R2",
    "addr:postcode":"5725;j3y 3r2",
    "addr:street":"Ch De Chambly",
    "iso:country":"CA",
    "sg:address":"5725 Ch DE Chambly",
    "sg:city":"Saint-Hubert",
    "sg:classifiers":[
        {
            "category":"Restaurant",
            "type":"Food & Drink"
        }
    ],
    "sg:phone":"+1 450 676 1423",
    "sg:postcode":"J3Y 3R2",
    "sg:province":"QC",
    "sg:tags":[
        "parlor",
        "ice",
        "cream"
    ],
    "wof:name":"Dairy Queen",
    "wof:placetype":"venue"
},
  "geometry": {"coordinates":[-73.41246,45.500465],"type":"Point"}
}