{
  "type": "Feature",
  "properties": {
    "addr:full":"135 South Ave Spruce Grove AB T7X 4G2",
    "addr:housenumber":"135",
    "addr:postcode":"t7x 4g2",
    "addr:street":"South Ave",
    "iso:country":"CA",
    "sg:address":"135 South Ave",
    "sg:city":"Spruce Grove",
    "sg:classifiers":[
        {
            "category":"Home & Garden",
            "subcategory":"Building Materials",
            "type":"Retail Goods"
        }
    ],
    "sg:phone":"+1 780 962 2575",
    "sg:postcode":"T7X 4G2",
    "sg:province":"AB",
    "sg:tags":[
        "lumber"
    ],
    "wof:name":"Mc Leod Home Building Ctr",
    "wof:placetype":"venue"
},
  "geometry": {"coordinates":[-118.862190247,55.0251312256],"type":"Point"}
}