{
  "type": "Feature",
  "properties": {
    "iso:country":"CA",
    "sg:city":"Newcastle",
    "sg:classifiers":[
        {
            "category":"Health Services",
            "subcategory":"Chiropractor",
            "type":"Services"
        }
    ],
    "sg:phone":"+1 905 987 9900",
    "sg:postcode":"L1B 1H6",
    "sg:province":"ON",
    "wof:name":"Clark Family Chiropractic Ctr",
    "wof:placetype":"venue"
},
  "geometry": {"coordinates":[-78.5886001587,43.9176826477],"type":"Point"}
}