{
  "type": "Feature",
  "properties": {
    "addr:full":"4727 Tebo Ave Port Alberni BC V9Y 8A9",
    "addr:housenumber":"4727",
    "addr:postcode":"v9y 8a9",
    "addr:street":"Tebo Ave",
    "iso:country":"CA",
    "sg:address":"4727 Tebo Ave",
    "sg:city":"Port Alberni",
    "sg:classifiers":[
        {
            "category":"Building & Trades",
            "subcategory":"Electrical",
            "type":"Services"
        }
    ],
    "sg:phone":"+1 250 724 6133",
    "sg:postcode":"V9Y 8A9",
    "sg:province":"BC",
    "sg:tags":[
        "electric",
        "contractor"
    ],
    "wof:name":"Aines & Tyler Electric CO Ltd",
    "wof:placetype":"venue"
},
  "geometry": {"coordinates":[-124.79136699999999,49.262024],"type":"Point"}
}