{
  "type": "Feature",
  "properties": {
    "addr:full":"3530 Rue Saint-Urbain Montreal QC H2X 2N7",
    "addr:housenumber":"3530",
    "addr:postcode":"h2x 2n7",
    "addr:street":"Rue Saint-Urbain",
    "iso:country":"CA",
    "sg:address":"3530 Rue Saint-Urbain",
    "sg:city":"Montreal",
    "sg:classifiers":[
        {
            "category":"Education",
            "subcategory":"School",
            "type":"Public Place"
        }
    ],
    "sg:phone":"+1 514 596 4288",
    "sg:postcode":"H2X 2N7",
    "sg:province":"QC",
    "wof:name":"Centre Dollard-Cormier",
    "wof:placetype":"venue"
},
  "geometry": {"coordinates":[-73.572311,45.511921],"type":"Point"}
}