{
  "type": "Feature",
  "properties": {
    "iso:country":"CA",
    "sg:address":"1464 Adelaide St N",
    "sg:city":"London",
    "sg:classifiers":[
        {
            "category":"Education",
            "subcategory":"Special Training",
            "type":"Public Place"
        }
    ],
    "sg:phone":"+1 519 661 0196",
    "sg:postcode":"N5X 1K4",
    "sg:province":"ON",
    "sg:tags":[
        "tutoring"
    ],
    "wof:name":"Sylvan Learning Ctr",
    "wof:placetype":"venue"
},
  "geometry": {"coordinates":[-81.252434,43.030674],"type":"Point"}
}