{
  "type": "Feature",
  "properties": {
    "addr:full":"Hamilton ON L8N 3W4",
    "addr:postcode":"l8n 3w4",
    "iso:country":"CA",
    "sg:city":"Hamilton",
    "sg:classifiers":[
        {
            "category":"Travel",
            "subcategory":"Travel Agent",
            "type":"Entertainment"
        }
    ],
    "sg:phone":"+1 905 572 7353",
    "sg:postcode":"L8N 3W4",
    "sg:province":"ON",
    "sg:tags":[
        "agency",
        "bureau"
    ],
    "wof:name":"Delta Travel Inc",
    "wof:placetype":"venue"
},
  "geometry": {"coordinates":[-79.865578,43.25423],"type":"Point"}
}