{
  "type": "Feature",
  "properties": {
    "addr:full":"269 Queen St E Brampton ON L6W 2C2",
    "addr:housenumber":"269",
    "addr:postcode":"l6w 2c2",
    "addr:street":"Queen St E",
    "iso:country":"CA",
    "sg:address":"269 Queen St E",
    "sg:city":"Brampton",
    "sg:classifiers":[
        {
            "category":"Restaurant",
            "type":"Food & Drink"
        }
    ],
    "sg:phone":"+1 905 453 9971",
    "sg:postcode":"L6W 2C2",
    "sg:province":"ON",
    "wof:name":"Swiss Chalet Rotisserie/Grill",
    "wof:placetype":"venue"
},
  "geometry": {"coordinates":[-79.741913,43.702122],"type":"Point"}
}