{
  "type": "Feature",
  "properties": {
    "addr:full":"11 Doxsee Ave S Campbellford ON K0L 1L0",
    "addr:housenumber":"11",
    "addr:postcode":"k0l 1l0",
    "addr:street":"Doxsee Ave S Campbellford",
    "iso:country":"CA",
    "sg:address":"11 Doxsee Ave S",
    "sg:city":"Campbellford",
    "sg:classifiers":[
        {
            "category":"Restaurant",
            "type":"Food & Drink"
        }
    ],
    "sg:phone":"+1 705 653 4900",
    "sg:postcode":"K0L 1L0",
    "sg:province":"ON",
    "wof:name":"Dixie Lee",
    "wof:placetype":"venue"
},
  "geometry": {"coordinates":[-77.796318,44.307629],"type":"Point"}
}