{
  "type": "Feature",
  "properties": {
    "addr:full":"133 Rue Alexandre Sherbrooke QC J1H 4S5",
    "addr:housenumber":"133",
    "addr:postcode":"j1h 4s5",
    "addr:street":"Rue Alexandre",
    "iso:country":"CA",
    "sg:address":"133 Rue Alexandre",
    "sg:city":"Sherbrooke",
    "sg:classifiers":[
        {
            "category":"Wholesale",
            "subcategory":"Non-durable Goods",
            "type":"Manufacturing & Wholesale Goods"
        }
    ],
    "sg:phone":"+1 819 562 2109",
    "sg:postcode":"J1H 4S5",
    "sg:province":"QC",
    "sg:tags":[
        "venetian",
        "blind",
        "interior"
    ],
    "wof:name":"Atelier Du Store",
    "wof:placetype":"venue"
},
  "geometry": {"coordinates":[-71.89316599999999,45.398067],"type":"Point"}
}