{
  "type": "Feature",
  "properties": {
    "iso:country":"CA",
    "sg:address":"1202 Mayor Magrath Dr S",
    "sg:city":"Lethbridge",
    "sg:classifiers":[
        {
            "category":"Autos & Motor Vehicles",
            "subcategory":"Fuel & Gas Station",
            "type":"Retail Goods"
        }
    ],
    "sg:phone":"+1 403 329 1555",
    "sg:postcode":"T1K 2R2",
    "sg:province":"AB",
    "sg:tags":[
        "oil"
    ],
    "wof:name":"Mohawk Mayor Magrath",
    "wof:placetype":"venue"
},
  "geometry": {"coordinates":[-112.803894043,49.6797409058],"type":"Point"}
}