{
  "type": "Feature",
  "properties": {
    "addr:full":"383 Rue Saint-Jacques Montreal QC H2Y 1N9",
    "addr:housenumber":"383",
    "addr:postcode":"h2y 1n9",
    "addr:street":"Rue Saint-Jacques",
    "iso:country":"CA",
    "sg:address":"383 Rue Saint-Jacques",
    "sg:city":"Montreal",
    "sg:classifiers":[
        {
            "category":"Restaurant",
            "type":"Food & Drink"
        }
    ],
    "sg:phone":"+1 514 840 1011",
    "sg:postcode":"H2Y 1N9",
    "sg:province":"QC",
    "wof:name":"Cafe Depot",
    "wof:placetype":"venue"
},
  "geometry": {"coordinates":[-73.559898,45.502075],"type":"Point"}
}