{
  "type": "Feature",
  "properties": {
    "addr:full":"2610 Ross Rd Kelowna BC V1Z 1M3",
    "addr:housenumber":"2610",
    "addr:postcode":"v1z 1m3",
    "addr:street":"Ross Rd",
    "iso:country":"CA",
    "sg:address":"2610 Ross Rd",
    "sg:city":"Kelowna",
    "sg:classifiers":[
        {
            "category":"Autos & Motor Vehicles",
            "subcategory":"Fuel & Gas Station",
            "type":"Retail Goods"
        }
    ],
    "sg:phone":"+1 250 769 5233",
    "sg:postcode":"V1Z 1M3",
    "sg:province":"BC",
    "sg:tags":[
        "oil"
    ],
    "wof:name":"Ross Road Mohawk",
    "wof:placetype":"venue"
},
  "geometry": {"coordinates":[-119.576179504,49.8622360229],"type":"Point"}
}