{
  "type": "Feature",
  "properties": {
    "addr:full":"216 Crocus Swan River MB R0L 1Z0",
    "addr:housenumber":"216",
    "addr:postcode":"r0l 1z0",
    "addr:street":"Crocus Swan",
    "iso:country":"CA",
    "sg:address":"216 Crocus",
    "sg:city":"Swan River",
    "sg:classifiers":[
        {
            "category":"Shopping",
            "type":"Retail Goods"
        }
    ],
    "sg:phone":"+1 204 734 9418",
    "sg:postcode":"R0L 1Z0",
    "sg:province":"MB",
    "sg:tags":[
        "orthopedic",
        "appliance",
        "breast",
        "artificial"
    ],
    "wof:name":"Just For You By Heather",
    "wof:placetype":"venue"
},
  "geometry": {"coordinates":[-101.25812500000001,52.11636],"type":"Point"}
}