{
  "type": "Feature",
  "properties": {
    "addr:full":"Sainte-Henedine QC G0S 2R0",
    "addr:postcode":"g0s 2r0",
    "iso:country":"CA",
    "sg:city":"Sainte-Henedine",
    "sg:classifiers":[
        {
            "category":"Wholesale",
            "subcategory":"Machinery & Supplies",
            "type":"Manufacturing & Wholesale Goods"
        }
    ],
    "sg:phone":"+1 418 935 3351",
    "sg:postcode":"G0S 2R0",
    "sg:province":"QC",
    "sg:tags":[
        "farm",
        "equipment"
    ],
    "wof:name":"Equipements Dallaire Inc",
    "wof:placetype":"venue"
},
  "geometry": {"coordinates":[-70.970619,46.542503],"type":"Point"}
}