{
  "type": "Feature",
  "properties": {
    "addr:full":"73 Dundas St W Mississauga ON L5B 1H7",
    "addr:housenumber":"73",
    "addr:postcode":"l5b 1h7",
    "addr:street":"Dundas St W",
    "iso:country":"CA",
    "sg:address":"73 Dundas St W",
    "sg:city":"Mississauga",
    "sg:classifiers":[
        {
            "category":"Personal",
            "subcategory":"Beauty Salon",
            "type":"Services"
        }
    ],
    "sg:phone":"+1 905 272 1299",
    "sg:postcode":"L5B 1H7",
    "sg:province":"ON",
    "sg:tags":[
        "manicuring"
    ],
    "wof:name":"Nail Art",
    "wof:placetype":"venue"
},
  "geometry": {"coordinates":[-79.6184463501,43.57862854],"type":"Point"}
}