{
  "type": "Feature",
  "properties": {
    "addr:full":"194 Rue Guillaume Longueuil QC J4H 1R8",
    "addr:housenumber":"194",
    "addr:postcode":"j4h 1r8",
    "addr:street":"Rue Guillaume",
    "iso:country":"CA",
    "sg:address":"194 Rue Guillaume",
    "sg:city":"Longueuil",
    "sg:classifiers":[
        {
            "category":"Personal",
            "subcategory":"Beauty Salon",
            "type":"Services"
        }
    ],
    "sg:phone":"+1 450 677 3945",
    "sg:postcode":"J4H 1R8",
    "sg:province":"QC",
    "wof:name":"Revolution Studio Coiffure Inc",
    "wof:placetype":"venue"
},
  "geometry": {"coordinates":[-73.50535600000001,45.536697],"type":"Point"}
}