{
  "type": "Feature",
  "properties": {
    "addr:full":"Kugaaruk NU X0B 1K0",
    "addr:postcode":"x0b 1k0",
    "iso:country":"CA",
    "sg:city":"Kugaaruk",
    "sg:classifiers":[
        {
            "category":"Education",
            "subcategory":"School",
            "type":"Public Place"
        }
    ],
    "sg:phone":"+1 867 769 6116",
    "sg:postcode":"X0B 1K0",
    "sg:province":"NU",
    "wof:name":"Pelly Bay Community Education",
    "wof:placetype":"venue"
},
  "geometry": {"coordinates":[-89.8267211914,68.5329818726],"type":"Point"}
}