{
  "type": "Feature",
  "properties": {
    "addr:full":"108 Ch Du Tremblay Boucherville QC J4B 6Z6",
    "addr:housenumber":"108",
    "addr:postcode":"j4b 6z6",
    "addr:street":"Ch Du Tremblay",
    "iso:country":"CA",
    "sg:address":"108 Ch Du Tremblay",
    "sg:city":"Boucherville",
    "sg:classifiers":[
        {
            "category":"Manufacturing",
            "subcategory":"Tools & Machinery",
            "type":"Manufacturing & Wholesale Goods"
        }
    ],
    "sg:phone":"+1 450 641 3622",
    "sg:postcode":"J4B 6Z6",
    "sg:province":"QC",
    "sg:tags":[
        "machine",
        "shop"
    ],
    "wof:name":"Regent Precision Inc",
    "wof:placetype":"venue"
},
  "geometry": {"coordinates":[-73.4270324707,45.5598258972],"type":"Point"}
}