{
  "type": "Feature",
  "properties": {
    "addr:full":"503 Lillie St N Thunder Bay ON P7C 4Y8",
    "addr:housenumber":"503",
    "addr:postcode":"p7c 4y8",
    "addr:street":"Lillie St N",
    "iso:country":"CA",
    "sg:address":"503 Lillie St N",
    "sg:city":"Thunder Bay",
    "sg:classifiers":[
        {
            "category":"Organizations",
            "subcategory":"Non-profit Organization",
            "type":"Services"
        }
    ],
    "sg:phone":"+1 807 622 3821",
    "sg:postcode":"P7C 4Y8",
    "sg:province":"ON",
    "sg:tags":[
        "addiction",
        "treatment",
        "center"
    ],
    "wof:name":"Crossroads Centre Inc",
    "wof:placetype":"venue"
},
  "geometry": {"coordinates":[-89.27057600000001,48.387028],"type":"Point"}
}