{
  "type": "Feature",
  "properties": {
    "addr:full":"9534 120 St Surrey BC V3V 4C1",
    "addr:housenumber":"9534",
    "addr:postcode":"v3v 4c1",
    "addr:street":"120 St",
    "iso:country":"CA",
    "sg:address":"9534 120 St",
    "sg:city":"Surrey",
    "sg:classifiers":[
        {
            "category":"Personal",
            "subcategory":"Barber",
            "type":"Services"
        }
    ],
    "sg:phone":"+1 604 584 9524",
    "sg:postcode":"V3V 4C1",
    "sg:province":"BC",
    "wof:name":"Moni's Plaza Barber Styling",
    "wof:placetype":"venue"
},
  "geometry": {"coordinates":[-122.890091,49.175831],"type":"Point"}
}