{
  "type": "Feature",
  "properties": {
    "iso:country":"CA",
    "sg:address":"303 Ardal St",
    "sg:city":"Arborg",
    "sg:classifiers":[
        {
            "category":"Building & Trades",
            "subcategory":"Construction",
            "type":"Services"
        }
    ],
    "sg:phone":"+1 204 376 5961",
    "sg:postcode":"R0C 0A0",
    "sg:province":"MB",
    "sg:tags":[
        "roofing",
        "contractor"
    ],
    "wof:name":"Pro-Tac Construction",
    "wof:placetype":"venue"
},
  "geometry": {"coordinates":[-97.219581604,50.9088096619],"type":"Point"}
}