{
  "type": "Feature",
  "properties": {
    "addr:full":"6 Speers Blvd Amherstview ON K7N 1Z6",
    "addr:housenumber":"6",
    "addr:postcode":"k7n 1z6",
    "addr:street":"Speers Blvd",
    "iso:country":"CA",
    "sg:address":"6 Speers Blvd",
    "sg:city":"Amherstview",
    "sg:classifiers":[
        {
            "category":"Shopping",
            "subcategory":"Computers & Home Electronics",
            "type":"Retail Goods"
        }
    ],
    "sg:phone":"+1 613 384 5200",
    "sg:postcode":"K7N 1Z6",
    "sg:province":"ON",
    "sg:tags":[
        "video",
        "game",
        "disc",
        "tape"
    ],
    "wof:name":"Jumbo Video",
    "wof:placetype":"venue"
},
  "geometry": {"coordinates":[-76.6603546143,44.2152633667],"type":"Point"}
}