{
  "type": "Feature",
  "properties": {
    "iso:country":"CA",
    "sg:city":"Bois-Des-Filion",
    "sg:classifiers":[
        {
            "category":"Professional",
            "subcategory":"Business Services",
            "type":"Services"
        }
    ],
    "sg:phone":"+1 450 965 6859",
    "sg:postcode":"J6Z 2M8",
    "sg:province":"QC",
    "wof:name":"Hebert, Jocelyne",
    "wof:placetype":"venue"
},
  "geometry": {"coordinates":[-73.760582,45.66058],"type":"Point"}
}