{
  "type": "Feature",
  "properties": {
    "iso:country":"CA",
    "sg:address":"4 9E Rue",
    "sg:city":"Rouyn-Noranda",
    "sg:classifiers":[
        {
            "category":"Health Services",
            "subcategory":"Doctor",
            "type":"Services"
        }
    ],
    "sg:phone":"+1 819 797 8816",
    "sg:postcode":"J9X 2B2",
    "sg:province":"QC",
    "sg:tags":[
        "clinic"
    ],
    "wof:name":"Clinique Regionale Vih/Sida",
    "wof:placetype":"venue"
},
  "geometry": {"coordinates":[-79.0145111084,48.2370758057],"type":"Point"}
}