{
  "type": "Feature",
  "properties": {
    "addr:full":"North York ON M3J 3E5",
    "addr:postcode":"m3j 3e5",
    "iso:country":"CA",
    "sg:city":"North York",
    "sg:classifiers":[
        {
            "category":"Manufacturing",
            "subcategory":"Tools & Machinery",
            "type":"Manufacturing & Wholesale Goods"
        }
    ],
    "sg:phone":"+1 416 635 8200",
    "sg:postcode":"M3J 3E5",
    "sg:province":"ON",
    "sg:tags":[
        "cleaners",
        "household",
        "janitor",
        "vacuum"
    ],
    "wof:name":"Comfort Vacuum Svc CO Ltd",
    "wof:placetype":"venue"
},
  "geometry": {"coordinates":[-79.46663665769999,43.7553482056],"type":"Point"}
}