{
  "type": "Feature",
  "properties": {
    "addr:full":"232 Camelot St Thunder Bay ON P7A 4B1",
    "addr:housenumber":"232",
    "addr:postcode":"p7a 4b1",
    "addr:street":"Camelot St",
    "iso:country":"CA",
    "sg:address":"232 Camelot St",
    "sg:city":"Thunder Bay",
    "sg:classifiers":[
        {
            "category":"Shopping",
            "type":"Retail Goods"
        }
    ],
    "sg:phone":"+1 807 345 0452",
    "sg:postcode":"P7A 4B1",
    "sg:province":"ON",
    "sg:tags":[
        "picture",
        "frame"
    ],
    "wof:name":"Framing Post",
    "wof:placetype":"venue"
},
  "geometry": {"coordinates":[-89.2184143066,48.4371833801],"type":"Point"}
}