{
  "type": "Feature",
  "properties": {
    "addr:full":"Toronto ON M4T 2S3",
    "addr:postcode":"m4t 2s3",
    "iso:country":"CA",
    "sg:city":"Toronto",
    "sg:classifiers":[
        {
            "category":"Manufacturing",
            "subcategory":"Printing",
            "type":"Manufacturing & Wholesale Goods"
        }
    ],
    "sg:phone":"+1 416 968 9314",
    "sg:postcode":"M4T 2S3",
    "sg:province":"ON",
    "sg:tags":[
        "broker"
    ],
    "wof:name":"Jbo Productions Inc",
    "wof:placetype":"venue"
},
  "geometry": {"coordinates":[-79.3932876587,43.6883773804],"type":"Point"}
}