{
  "type": "Feature",
  "properties": {
    "addr:full":"PO Box 608 Fort Vermilion AB T0H 1N0",
    "addr:housenumber":"po",
    "addr:postcode":"t0h 1n0",
    "addr:street":"Box 608 Fort",
    "iso:country":"CA",
    "sg:address":"PO Box 608",
    "sg:city":"Fort Vermilion",
    "sg:classifiers":[
        {
            "category":"Organizations",
            "subcategory":"Religious Organization",
            "type":"Services"
        }
    ],
    "sg:phone":"+1 403 759 3992",
    "sg:postcode":"T0H 1N0",
    "sg:province":"AB",
    "sg:tags":[
        "church"
    ],
    "wof:name":"St Joseph Catholic Church",
    "wof:placetype":"venue"
},
  "geometry": {"coordinates":[-110.858521,53.351669],"type":"Point"}
}