{
  "type": "Feature",
  "properties": {
    "iso:country":"CA",
    "sg:address":"11 Welshpool St",
    "sg:city":"Welshpool",
    "sg:classifiers":[
        {
            "category":"Travel",
            "subcategory":"Hotels & Motels",
            "type":"Entertainment"
        }
    ],
    "sg:phone":"+1 506 752 2977",
    "sg:postcode":"E5E 1G3",
    "sg:province":"NB",
    "sg:tags":[
        "breakfast",
        "inn",
        "bed",
        "accommodation"
    ],
    "wof:name":"Owen House B & B",
    "wof:placetype":"venue"
},
  "geometry": {"coordinates":[-66.95709991459999,44.8903923035],"type":"Point"}
}