{
  "type": "Feature",
  "properties": {
    "addr:full":"178 Bathurst St Toronto ON M5V 2R4",
    "addr:housenumber":"178",
    "addr:postcode":"m5v 2r4",
    "addr:street":"Bathurst St",
    "iso:country":"CA",
    "sg:address":"178 Bathurst St",
    "sg:city":"Toronto",
    "sg:classifiers":[
        {
            "category":"Bars & Pubs",
            "type":"Food & Drink"
        }
    ],
    "sg:phone":"+1 416 703 5882",
    "sg:postcode":"M5V 2R4",
    "sg:province":"ON",
    "sg:tags":[
        "club",
        "night"
    ],
    "wof:name":"Healey's",
    "wof:placetype":"venue"
},
  "geometry": {"coordinates":[-79.4040679932,43.6468811035],"type":"Point"}
}