{
  "type": "Feature",
  "properties": {
    "addr:full":"710 14th St W North Vancouver BC V7M 1R4",
    "addr:housenumber":"710",
    "addr:postcode":"v7m 1r4",
    "addr:street":"14Th St W",
    "iso:country":"CA",
    "sg:address":"710 14th St W",
    "sg:city":"North Vancouver",
    "sg:classifiers":[
        {
            "category":"Shopping",
            "subcategory":"Department Store",
            "type":"Retail Goods"
        }
    ],
    "sg:phone":"+1 604 924 9422",
    "sg:postcode":"V7M 1R4",
    "sg:province":"BC",
    "sg:tags":[
        "shop"
    ],
    "wof:name":"Liquidation World Inc",
    "wof:placetype":"venue"
},
  "geometry": {"coordinates":[-123.09174299999999,49.321369],"type":"Point"}
}