{
  "type": "Feature",
  "properties": {
    "addr:full":"8945 Granville St Port Hardy BC V0N 2P0",
    "addr:housenumber":"8945",
    "addr:postcode":"v0n 2p0",
    "addr:street":"Granville St",
    "iso:country":"CA",
    "sg:address":"8945 Granville St",
    "sg:city":"Port Hardy",
    "sg:classifiers":[
        {
            "category":"Autos & Motor Vehicles",
            "subcategory":"Fuel & Gas Station",
            "type":"Retail Goods"
        }
    ],
    "sg:phone":"+1 250 949 8535",
    "sg:postcode":"V0N 2P0",
    "sg:province":"BC",
    "sg:tags":[
        "oil"
    ],
    "wof:name":"Esso",
    "wof:placetype":"venue"
},
  "geometry": {"coordinates":[-127.499526977,50.7208976746],"type":"Point"}
}