{
  "type": "Feature",
  "properties": {
    "addr:full":"79 Collegiate Ave Stoney Creek ON L8G 3L5",
    "addr:housenumber":"79",
    "addr:postcode":"l8g 3l5",
    "addr:street":"Collegiate Ave",
    "iso:country":"CA",
    "sg:address":"79 Collegiate Ave",
    "sg:city":"Stoney Creek",
    "sg:classifiers":[
        {
            "category":"Organizations",
            "subcategory":"Religious Organization",
            "type":"Services"
        }
    ],
    "sg:phone":"+1 905 662 3336",
    "sg:postcode":"L8G 3L5",
    "sg:province":"ON",
    "sg:tags":[
        "church"
    ],
    "wof:name":"Stoney Creek Baptist Church",
    "wof:placetype":"venue"
},
  "geometry": {"coordinates":[-79.746414,43.219963],"type":"Point"}
}