{
  "type": "Feature",
  "properties": {
    "addr:full":"2057 Royal Windsor Dr Mississauga ON L5J 1K5",
    "addr:housenumber":"2057",
    "addr:postcode":"l5j 1k5",
    "addr:street":"Royal Windsor Dr",
    "iso:country":"CA",
    "sg:address":"2057 Royal Windsor Dr",
    "sg:city":"Mississauga",
    "sg:classifiers":[
        {
            "category":"Banks & Credit Unions",
            "subcategory":"Bank",
            "type":"Services"
        }
    ],
    "sg:phone":"+1 905 822 8941",
    "sg:postcode":"L5J 1K5",
    "sg:province":"ON",
    "wof:name":"Bank of Montreal",
    "wof:placetype":"venue"
},
  "geometry": {"coordinates":[-79.631866,43.509434],"type":"Point"}
}