{
  "type": "Feature",
  "properties": {
    "iso:country":"CA",
    "sg:address":"66 Church St",
    "sg:city":"Brockville",
    "sg:classifiers":[
        {
            "category":"Organizations",
            "subcategory":"Religious Organization",
            "type":"Services"
        }
    ],
    "sg:phone":"+1 613 342 2993",
    "sg:postcode":"K6V 3X6",
    "sg:province":"ON",
    "sg:tags":[
        "church"
    ],
    "wof:name":"St Francis Xavier Church",
    "wof:placetype":"venue"
},
  "geometry": {"coordinates":[-75.68881988530001,44.5891799927],"type":"Point"}
}