{
  "type": "Feature",
  "properties": {
    "iso:country":"CA",
    "sg:city":"Ottawa",
    "sg:classifiers":[
        {
            "category":"Personal",
            "type":"Services"
        }
    ],
    "sg:phone":"+1 613 567 0037",
    "sg:postcode":"K1N 9J7",
    "sg:province":"ON",
    "sg:tags":[
        "control",
        "weight",
        "club",
        "gymnasium",
        "health",
        "studio"
    ],
    "wof:name":"Goodlife Fitness Club",
    "wof:placetype":"venue"
},
  "geometry": {"coordinates":[-75.691765,45.444431],"type":"Point"}
}