{
  "type": "Feature",
  "properties": {
    "addr:full":"Chilliwack BC V2R 1A1",
    "addr:postcode":"v2r 1a1",
    "iso:country":"CA",
    "sg:city":"Chilliwack",
    "sg:classifiers":[
        {
            "category":"Shopping",
            "subcategory":"Computers & Home Electronics",
            "type":"Retail Goods"
        }
    ],
    "sg:phone":"+1 604 858 7694",
    "sg:postcode":"V2R 1A1",
    "sg:province":"BC",
    "sg:tags":[
        "equipment",
        "dealer",
        "pharmacy"
    ],
    "wof:name":"London Drugs Ltd",
    "wof:placetype":"venue"
},
  "geometry": {"coordinates":[-121.961967,49.140892],"type":"Point"}
}