{
  "type": "Feature",
  "properties": {
    "addr:full":"2733 41st Ave W Vancouver BC V6N 3C5",
    "addr:housenumber":"2733",
    "addr:postcode":"v6n 3c5",
    "addr:street":"41St Ave W",
    "iso:country":"CA",
    "sg:address":"2733 41st Ave W",
    "sg:city":"Vancouver",
    "sg:classifiers":[
        {
            "category":"Organizations",
            "subcategory":"Religious Organization",
            "type":"Services"
        }
    ],
    "sg:phone":"+1 604 261 1434",
    "sg:postcode":"V6N 3C5",
    "sg:province":"BC",
    "sg:tags":[
        "church"
    ],
    "wof:name":"Kerrisdale Presbyterian Church",
    "wof:placetype":"venue"
},
  "geometry": {"coordinates":[-123.16636699999999,49.234867],"type":"Point"}
}