{
  "type": "Feature",
  "properties": {
    "addr:full":"308 Harbour Ave North Vancouver BC V7J 2E9",
    "addr:housenumber":"308",
    "addr:postcode":"v7j 2e9",
    "addr:street":"Harbour Ave",
    "iso:country":"CA",
    "sg:address":"308 Harbour Ave",
    "sg:city":"North Vancouver",
    "sg:classifiers":[
        {
            "category":"Manufacturing",
            "subcategory":"Tools & Machinery",
            "type":"Manufacturing & Wholesale Goods"
        }
    ],
    "sg:phone":"+1 604 983 2995",
    "sg:postcode":"V7J 2E9",
    "sg:province":"BC",
    "sg:tags":[
        "machine",
        "shop"
    ],
    "wof:name":"Core Tool & Mold Ltd",
    "wof:placetype":"venue"
},
  "geometry": {"coordinates":[-123.034004211,49.3069381714],"type":"Point"}
}