{
  "type": "Feature",
  "properties": {
    "addr:full":"Laval QC H7N 2K3",
    "addr:postcode":"h7n 2k3",
    "iso:country":"CA",
    "sg:city":"Laval",
    "sg:classifiers":[
        {
            "category":"Health Services",
            "subcategory":"Chiropractor",
            "type":"Services"
        }
    ],
    "sg:phone":"+1 450 669 8604",
    "sg:postcode":"H7N 2K3",
    "sg:province":"QC",
    "wof:name":"Gareau, Michel DC",
    "wof:placetype":"venue"
},
  "geometry": {"coordinates":[-73.71063232420001,45.5507087708],"type":"Point"}
}