{
  "type": "Feature",
  "properties": {
    "addr:full":"Val-D'Or QC J9P 1T2",
    "addr:postcode":"j9p 1t2",
    "iso:country":"CA",
    "sg:city":"Val-D'Or",
    "sg:classifiers":[
        {
            "category":"Manufacturing",
            "subcategory":"Metals",
            "type":"Manufacturing & Wholesale Goods"
        }
    ],
    "sg:phone":"+1 819 825 3000",
    "sg:postcode":"J9P 1T2",
    "sg:province":"QC",
    "sg:tags":[
        "jeweler"
    ],
    "wof:name":"Creations Calior Inc",
    "wof:placetype":"venue"
},
  "geometry": {"coordinates":[-71.667419,48.689545],"type":"Point"}
}