{
  "type": "Feature",
  "properties": {
    "addr:full":"Fulford QC J0E 1S0",
    "addr:postcode":"j0e 1s0",
    "iso:country":"CA",
    "sg:city":"Fulford",
    "sg:classifiers":[
        {
            "category":"Organizations",
            "subcategory":"Professional Association",
            "type":"Services"
        }
    ],
    "sg:phone":"+1 450 539 4763",
    "sg:postcode":"J0E 1S0",
    "sg:province":"QC",
    "wof:name":"Fulford Recreation Club",
    "wof:placetype":"venue"
},
  "geometry": {"coordinates":[-72.556313,45.298145],"type":"Point"}
}