{
  "type": "Feature",
  "properties": {
    "iso:country":"CA",
    "sg:address":"5804 45 Ave",
    "sg:city":"Lacombe",
    "sg:classifiers":[
        {
            "category":"Organizations",
            "subcategory":"Religious Organization",
            "type":"Services"
        }
    ],
    "sg:phone":"+1 403 782 6699",
    "sg:postcode":"T4L 1M6",
    "sg:province":"AB",
    "sg:tags":[
        "church"
    ],
    "wof:name":"Lacombe Community Seventh Day",
    "wof:placetype":"venue"
},
  "geometry": {"coordinates":[-113.74775699999999,52.459023],"type":"Point"}
}