{
  "type": "Feature",
  "properties": {
    "addr:full":"1208 Rue Valiquette Sainte-Adele QC J8B 2M5",
    "addr:housenumber":"1208",
    "addr:postcode":"j8b 2m5",
    "addr:street":"Rue Valiquette Sainte-Adele",
    "iso:country":"CA",
    "sg:address":"1208 Rue Valiquette",
    "sg:city":"Sainte-Adele",
    "sg:classifiers":[
        {
            "category":"Shopping",
            "subcategory":"Pharmacy",
            "type":"Retail Goods"
        }
    ],
    "sg:phone":"+1 450 229 6608",
    "sg:postcode":"J8B 2M5",
    "sg:province":"QC",
    "wof:name":"Brunet",
    "wof:placetype":"venue"
},
  "geometry": {"coordinates":[-74.1366729736,45.9521598816],"type":"Point"}
}