{
  "type": "Feature",
  "properties": {
    "addr:full":"St Thomas ON N5R 5J5",
    "addr:postcode":"n5r 5j5",
    "iso:country":"CA",
    "sg:city":"St Thomas",
    "sg:classifiers":[
        {
            "category":"Shopping",
            "subcategory":"Clothing, Apparel, & Fashions",
            "type":"Retail Goods"
        }
    ],
    "sg:phone":"+1 519 633 1336",
    "sg:postcode":"N5R 5J5",
    "sg:province":"ON",
    "wof:name":"Suzy Shier",
    "wof:placetype":"venue"
},
  "geometry": {"coordinates":[-81.1623840332,42.7747917175],"type":"Point"}
}