{
  "type": "Feature",
  "properties": {
    "iso:country":"CA",
    "sg:address":"4392 Steeles Ave E",
    "sg:city":"Markham",
    "sg:classifiers":[
        {
            "category":"Shopping",
            "subcategory":"Pharmacy",
            "type":"Retail Goods"
        }
    ],
    "sg:phone":"+1 905 513 8686",
    "sg:postcode":"L3R 9V8",
    "sg:province":"ON",
    "wof:name":"Advanced Pharmacy",
    "wof:placetype":"venue"
},
  "geometry": {"coordinates":[-79.30394,43.824543],"type":"Point"}
}