{
  "type": "Feature",
  "properties": {
    "addr:full":"1271 Rue Principale Saint-Zotique QC J0P 1Z0",
    "addr:housenumber":"1271",
    "addr:postcode":"j0p 1z0",
    "addr:street":"Rue Principale",
    "iso:country":"CA",
    "sg:address":"1271 Rue Principale",
    "sg:city":"Saint-Zotique",
    "sg:classifiers":[
        {
            "category":"Restaurant",
            "type":"Food & Drink"
        }
    ],
    "sg:phone":"+1 450 267 9211",
    "sg:postcode":"J0P 1Z0",
    "sg:province":"QC",
    "sg:tags":[
        "cafeteria"
    ],
    "wof:name":"Cuisinerie Alain Inc",
    "wof:placetype":"venue"
},
  "geometry": {"coordinates":[-74.248627,45.241375],"type":"Point"}
}