{
  "type": "Feature",
  "properties": {
    "addr:full":"132 Adams Blvd Brantford ON N3S 7V2",
    "addr:housenumber":"132",
    "addr:postcode":"n3s 7v2",
    "addr:street":"Adams Blvd",
    "iso:country":"CA",
    "sg:address":"132 Adams Blvd",
    "sg:city":"Brantford",
    "sg:classifiers":[
        {
            "category":"Manufacturing",
            "subcategory":"Furniture",
            "type":"Manufacturing & Wholesale Goods"
        }
    ],
    "sg:phone":"+1 519 753 2227",
    "sg:postcode":"N3S 7V2",
    "sg:province":"ON",
    "sg:tags":[
        "rack"
    ],
    "wof:name":"Enrack Systems Inc",
    "wof:placetype":"venue"
},
  "geometry": {"coordinates":[-80.2270278931,43.1642189026],"type":"Point"}
}