{
  "type": "Feature",
  "properties": {
    "addr:full":"5440 Ch Queen-Mary Montreal QC H3X 1V6",
    "addr:postcode":"5440;h3x 1v6",
    "addr:street":"Ch Queen-Mary",
    "iso:country":"CA",
    "sg:address":"5440 Ch Queen-Mary",
    "sg:city":"Montreal",
    "sg:classifiers":[
        {
            "category":"Education",
            "subcategory":"School",
            "type":"Public Place"
        }
    ],
    "sg:phone":"+1 514 482 9899",
    "sg:postcode":"H3X 1V6",
    "sg:province":"QC",
    "wof:name":"Mto Shahmaghsoudi",
    "wof:placetype":"venue"
},
  "geometry": {"coordinates":[-73.6305236816,45.4817237854],"type":"Point"}
}