{
  "type": "Feature",
  "properties": {
    "addr:full":"505 Queen St Newmarket ON L3Y 2H3",
    "addr:housenumber":"505",
    "addr:postcode":"l3y 2h3",
    "addr:street":"Queen St",
    "iso:country":"CA",
    "sg:address":"505 Queen St",
    "sg:city":"Newmarket",
    "sg:classifiers":[
        {
            "category":"Building & Trades",
            "subcategory":"Construction",
            "type":"Services"
        }
    ],
    "sg:phone":"+1 905 895 4649",
    "sg:postcode":"L3Y 2H3",
    "sg:province":"ON",
    "sg:tags":[
        "general",
        "contractor"
    ],
    "wof:name":"Mawhinney Contracting",
    "wof:placetype":"venue"
},
  "geometry": {"coordinates":[-79.456993103,44.0571708679],"type":"Point"}
}