{
  "type": "Feature",
  "properties": {
    "iso:country":"CA",
    "sg:address":"600 Grandview St S",
    "sg:city":"Oshawa",
    "sg:classifiers":[
        {
            "category":"Retail",
            "subcategory":"Laundry & Dry Cleaning",
            "type":"Services"
        }
    ],
    "sg:phone":"+1 905 404 1395",
    "sg:postcode":"L1H 8P4",
    "sg:province":"ON",
    "sg:tags":[
        "cleaners"
    ],
    "wof:name":"Sketchley Cleaners",
    "wof:placetype":"venue"
},
  "geometry": {"coordinates":[-78.814331,43.891178],"type":"Point"}
}