{
  "type": "Feature",
  "properties": {
    "iso:country":"CA",
    "sg:address":"6154 Kestrel Rd",
    "sg:city":"Mississauga",
    "sg:classifiers":[
        {
            "category":"Manufacturing",
            "subcategory":"Tools & Machinery",
            "type":"Manufacturing & Wholesale Goods"
        }
    ],
    "sg:phone":"+1 905 670 7200",
    "sg:postcode":"L5T 1Z2",
    "sg:province":"ON",
    "sg:tags":[
        "packaging"
    ],
    "wof:name":"Langen Packaging Inc",
    "wof:placetype":"venue"
},
  "geometry": {"coordinates":[-79.66519927980001,43.6468772888],"type":"Point"}
}