{
  "type": "Feature",
  "properties": {
    "addr:full":"57 Boul D'Anjou Chateauguay QC J6J 2P9",
    "addr:housenumber":"57",
    "addr:postcode":"j6j 2p9",
    "addr:street":"Boul D'Anjou",
    "iso:country":"CA",
    "sg:address":"57 Boul D'Anjou",
    "sg:city":"Chateauguay",
    "sg:classifiers":[
        {
            "category":"Health Services",
            "subcategory":"Doctor",
            "type":"Services"
        }
    ],
    "sg:phone":"+1 450 692 8225",
    "sg:postcode":"J6J 2P9",
    "sg:province":"QC",
    "sg:tags":[
        "dentist"
    ],
    "wof:name":"Clinique Dentaire Chateauguay",
    "wof:placetype":"venue"
},
  "geometry": {"coordinates":[-73.74011230470001,45.3614845276],"type":"Point"}
}