{
  "type": "Feature",
  "properties": {
    "addr:full":"1380 Mountain Rd Moncton NB E1C 2T8",
    "addr:housenumber":"1380",
    "addr:postcode":"e1c 2t8",
    "addr:street":"Mountain Rd",
    "iso:country":"CA",
    "sg:address":"1380 Mountain Rd",
    "sg:city":"Moncton",
    "sg:classifiers":[
        {
            "category":"Shopping",
            "subcategory":"Department Store",
            "type":"Retail Goods"
        }
    ],
    "sg:phone":"+1 506 858 7200",
    "sg:postcode":"E1C 2T8",
    "sg:province":"NB",
    "wof:name":"Zellers",
    "wof:placetype":"venue"
},
  "geometry": {"coordinates":[-64.832855,46.111053],"type":"Point"}
}