{
  "type": "Feature",
  "properties": {
    "addr:full":"15 Bramsteele Rd Brampton ON L6W 3K6",
    "addr:housenumber":"15",
    "addr:postcode":"l6w 3k6",
    "addr:street":"Bramsteele Rd",
    "iso:country":"CA",
    "sg:address":"15 Bramsteele Rd",
    "sg:city":"Brampton",
    "sg:classifiers":[
        {
            "category":"Retail",
            "subcategory":"Auto Repair",
            "type":"Services"
        }
    ],
    "sg:phone":"+1 905 451 6478",
    "sg:postcode":"L6W 3K6",
    "sg:province":"ON",
    "sg:tags":[
        "repairing",
        "automobile"
    ],
    "wof:name":"Hansen Automotive Svc",
    "wof:placetype":"venue"
},
  "geometry": {"coordinates":[-79.718468,43.682976],"type":"Point"}
}