{
  "type": "Feature",
  "properties": {
    "addr:full":"70 Church St Nanaimo BC V9R 5H4",
    "addr:housenumber":"70",
    "addr:postcode":"v9r 5h4",
    "addr:street":"Church St",
    "iso:country":"CA",
    "sg:address":"70 Church St",
    "sg:city":"Nanaimo",
    "sg:classifiers":[
        {
            "category":"Travel",
            "subcategory":"Hotels & Motels",
            "type":"Entertainment"
        }
    ],
    "sg:phone":"+1 250 754 6835",
    "sg:postcode":"V9R 5H4",
    "sg:province":"BC",
    "wof:name":"Best Western Dorchester Hotel",
    "wof:placetype":"venue"
},
  "geometry": {"coordinates":[-123.936645508,49.1679039001],"type":"Point"}
}