{
  "type": "Feature",
  "properties": {
    "addr:full":"1665 56 St Delta BC V4L 2B2",
    "addr:housenumber":"1665",
    "addr:postcode":"v4l 2b2",
    "addr:street":"56 St",
    "iso:country":"CA",
    "sg:address":"1665 56 St",
    "sg:city":"Delta",
    "sg:classifiers":[
        {
            "category":"Shopping",
            "subcategory":"Clothing, Apparel, & Fashions",
            "type":"Retail Goods"
        }
    ],
    "sg:phone":"+1 604 943 8088",
    "sg:postcode":"V4L 2B2",
    "sg:province":"BC",
    "wof:name":"Boutique Blanche",
    "wof:placetype":"venue"
},
  "geometry": {"coordinates":[-123.06886299999999,49.033127],"type":"Point"}
}