{
  "type": "Feature",
  "properties": {
    "iso:country":"CA",
    "sg:address":"8202 Victoria St",
    "sg:city":"Metcalfe",
    "sg:classifiers":[
        {
            "category":"Restaurant",
            "type":"Food & Drink"
        }
    ],
    "sg:phone":"+1 613 821 1509",
    "sg:postcode":"K0A 2P0",
    "sg:province":"ON",
    "sg:tags":[
        "pizza"
    ],
    "wof:name":"Metcalfe Pizza & Grocery",
    "wof:placetype":"venue"
},
  "geometry": {"coordinates":[-75.4738235474,45.2352714539],"type":"Point"}
}