{
  "type": "Feature",
  "properties": {
    "iso:country":"CA",
    "sg:address":"500 Boul Iberville # 19",
    "sg:city":"Repentigny",
    "sg:classifiers":[
        {
            "category":"Personal",
            "subcategory":"Tanning Parlor",
            "type":"Services"
        }
    ],
    "sg:phone":"+1 450 585 8929",
    "sg:postcode":"J6A 6H9",
    "sg:province":"QC",
    "sg:tags":[
        "salon"
    ],
    "wof:name":"Bronzage Midi Soleil",
    "wof:placetype":"venue"
},
  "geometry": {"coordinates":[-73.447151,45.745384],"type":"Point"}
}