{
  "type": "Feature",
  "properties": {
    "iso:country":"CA",
    "sg:city":"Mayerthorpe",
    "sg:classifiers":[
        {
            "category":"Wholesale",
            "subcategory":"Construction Materials",
            "type":"Manufacturing & Wholesale Goods"
        }
    ],
    "sg:phone":"+1 780 786 4236",
    "sg:postcode":"T0E 1N0",
    "sg:province":"AB",
    "sg:tags":[
        "sand",
        "gravel"
    ],
    "wof:name":"Hagman Enterprises",
    "wof:placetype":"venue"
},
  "geometry": {"coordinates":[-115.142242432,53.9603157043],"type":"Point"}
}