{
  "type": "Feature",
  "properties": {
    "addr:full":"St-Barnabe-Nord QC G0X 2K0",
    "addr:postcode":"g0x 2k0",
    "iso:country":"CA",
    "sg:city":"St-Barnabe-Nord",
    "sg:classifiers":[
        {
            "category":"Government",
            "subcategory":"Fire Station",
            "type":"Public Place"
        }
    ],
    "sg:phone":"+1 819 264 2222",
    "sg:postcode":"G0X 2K0",
    "sg:province":"QC",
    "sg:tags":[
        "department"
    ],
    "wof:name":"St Barnabe Nord Svc-Incendies",
    "wof:placetype":"venue"
},
  "geometry": {"coordinates":[-72.88002,46.393902],"type":"Point"}
}