{
  "type": "Feature",
  "properties": {
    "addr:full":"180 Boul Begin Sainte-Claire QC G0R 2V0",
    "addr:housenumber":"180",
    "addr:postcode":"g0r 2v0",
    "addr:street":"Boul Begin",
    "iso:country":"CA",
    "sg:address":"180 Boul Begin",
    "sg:city":"Sainte-Claire",
    "sg:classifiers":[
        {
            "category":"Wholesale",
            "subcategory":"Machinery & Supplies",
            "type":"Manufacturing & Wholesale Goods"
        }
    ],
    "sg:phone":"+1 418 883 3322",
    "sg:postcode":"G0R 2V0",
    "sg:province":"QC",
    "sg:tags":[
        "pulley"
    ],
    "wof:name":"Poulies Maska Inc",
    "wof:placetype":"venue"
},
  "geometry": {"coordinates":[-70.862953186,46.6009292603],"type":"Point"}
}