{
  "type": "Feature",
  "properties": {
    "iso:country":"CA",
    "sg:address":"Douglas Lk Rd",
    "sg:city":"Westwold",
    "sg:classifiers":[
        {
            "category":"Farming",
            "subcategory":"Livestock Farm",
            "type":"Manufacturing & Wholesale Goods"
        }
    ],
    "sg:phone":"+1 250 375 2359",
    "sg:postcode":"V0E 3B0",
    "sg:province":"BC",
    "sg:tags":[
        "ranch"
    ],
    "wof:name":"Red Rock Farm Ltd",
    "wof:placetype":"venue"
},
  "geometry": {"coordinates":[-119.748931885,50.46824646],"type":"Point"}
}