{
  "type": "Feature",
  "properties": {
    "addr:full":"3199 Massey Dr Prince George BC V2N 3M7",
    "addr:housenumber":"3199",
    "addr:postcode":"v2n 3m7",
    "addr:street":"Massey Dr",
    "iso:country":"CA",
    "sg:address":"3199 Massey Dr",
    "sg:city":"Prince George",
    "sg:classifiers":[
        {
            "category":"Shopping",
            "subcategory":"Department Store",
            "type":"Retail Goods"
        }
    ],
    "sg:phone":"+1 250 564 8111",
    "sg:postcode":"V2N 3M7",
    "sg:province":"BC",
    "wof:name":"Sears Canada Inc",
    "wof:placetype":"venue"
},
  "geometry": {"coordinates":[-122.78062439,53.8994293213],"type":"Point"}
}