{
  "type": "Feature",
  "properties": {
    "addr:full":"North York ON M3A 1B2",
    "addr:postcode":"m3a 1b2",
    "iso:country":"CA",
    "sg:city":"North York",
    "sg:classifiers":[
        {
            "category":"Wholesale",
            "subcategory":"Apparel",
            "type":"Manufacturing & Wholesale Goods"
        }
    ],
    "sg:phone":"+1 416 391 1013",
    "sg:postcode":"M3A 1B2",
    "sg:province":"ON",
    "sg:tags":[
        "label"
    ],
    "wof:name":"Labelcraft Industries",
    "wof:placetype":"venue"
},
  "geometry": {"coordinates":[-79.32287599999999,43.737152],"type":"Point"}
}