{
  "type": "Feature",
  "properties": {
    "iso:country":"CA",
    "sg:address":"414 11A St NE",
    "sg:city":"Calgary",
    "sg:classifiers":[
        {
            "category":"Education",
            "subcategory":"School",
            "type":"Public Place"
        }
    ],
    "sg:phone":"+1 403 290 0767",
    "sg:postcode":"T2E 4P3",
    "sg:province":"AB",
    "wof:name":"Delta West Academy",
    "wof:placetype":"venue"
},
  "geometry": {"coordinates":[-114.034851074,51.0554389954],"type":"Point"}
}