{
  "type": "Feature",
  "properties": {
    "addr:full":"554 7th Ave Hanover ON N4N 2J7",
    "addr:housenumber":"554",
    "addr:postcode":"n4n 2j7",
    "addr:street":"7Th Ave",
    "iso:country":"CA",
    "sg:address":"554 7th Ave",
    "sg:city":"Hanover",
    "sg:classifiers":[
        {
            "category":"Professional",
            "subcategory":"Management & Consulting",
            "type":"Services"
        }
    ],
    "sg:phone":"+1 519 364 3694",
    "sg:postcode":"N4N 2J7",
    "sg:province":"ON",
    "sg:tags":[
        "consultant",
        "business"
    ],
    "wof:name":"Saugeen Business Development",
    "wof:placetype":"venue"
},
  "geometry": {"coordinates":[-81.031738,44.153862],"type":"Point"}
}