{
  "type": "Feature",
  "properties": {
    "addr:full":"283 Morningside Ave Scarborough ON M1E 3G1",
    "addr:housenumber":"283",
    "addr:postcode":"m1e 3g1",
    "addr:street":"Morningside Ave",
    "iso:country":"CA",
    "sg:address":"283 Morningside Ave",
    "sg:city":"Scarborough",
    "sg:classifiers":[
        {
            "category":"Restaurant",
            "type":"Food & Drink"
        }
    ],
    "sg:phone":"+1 416 208 6037",
    "sg:postcode":"M1E 3G1",
    "sg:province":"ON",
    "wof:name":"King of Samosa & Grocery",
    "wof:placetype":"venue"
},
  "geometry": {"coordinates":[-79.18701171879999,43.7713317871],"type":"Point"}
}