{
  "type": "Feature",
  "properties": {
    "addr:full":"200 Acadia Dr Hamilton ON L8W 1B8",
    "addr:housenumber":"200",
    "addr:postcode":"l8w 1b8",
    "addr:street":"Acadia Dr",
    "iso:country":"CA",
    "sg:address":"200 Acadia Dr",
    "sg:city":"Hamilton",
    "sg:classifiers":[
        {
            "category":"Professional",
            "subcategory":"Management & Consulting",
            "type":"Services"
        }
    ],
    "sg:phone":"+1 905 575 8229",
    "sg:postcode":"L8W 1B8",
    "sg:province":"ON",
    "sg:tags":[
        "food"
    ],
    "wof:name":"Chartwells",
    "wof:placetype":"venue"
},
  "geometry": {"coordinates":[-79.86346399999999,43.201874],"type":"Point"}
}