{
  "type": "Feature",
  "properties": {
    "iso:country":"CA",
    "sg:address":"104 Church St",
    "sg:city":"Amherst",
    "sg:classifiers":[
        {
            "category":"Health Services",
            "subcategory":"Doctor",
            "type":"Services"
        }
    ],
    "sg:phone":"+1 902 661 0953",
    "sg:postcode":"B4H 3B4",
    "sg:province":"NS",
    "sg:tags":[
        "clinic"
    ],
    "wof:name":"Nova Denture Clinic",
    "wof:placetype":"venue"
},
  "geometry": {"coordinates":[-64.20695499999999,45.830898],"type":"Point"}
}