{
  "type": "Feature",
  "properties": {
    "addr:full":"Pointe-Claire QC H9R 3J1",
    "addr:postcode":"h9r 3j1",
    "iso:country":"CA",
    "sg:city":"Pointe-Claire",
    "sg:classifiers":[
        {
            "category":"Shopping",
            "subcategory":"Gifts & Souvenirs",
            "type":"Retail Goods"
        }
    ],
    "sg:phone":"+1 514 697 5050",
    "sg:postcode":"H9R 3J1",
    "sg:province":"QC",
    "sg:tags":[
        "shop"
    ],
    "wof:name":"Boutique Belles Choses",
    "wof:placetype":"venue"
},
  "geometry": {"coordinates":[-73.816154,45.445614],"type":"Point"}
}