{
  "type": "Feature",
  "properties": {
    "addr:full":"Saint-Laurent QC H4L 3Y8",
    "addr:postcode":"h4l 3y8",
    "iso:country":"CA",
    "sg:city":"Saint-Laurent",
    "sg:classifiers":[
        {
            "category":"Health Services",
            "subcategory":"Doctor",
            "type":"Services"
        }
    ],
    "sg:phone":"+1 514 747 2555",
    "sg:postcode":"H4L 3Y8",
    "sg:province":"QC",
    "sg:tags":[
        "clinic"
    ],
    "wof:name":"Clinique Sans Rendez Vous",
    "wof:placetype":"venue"
},
  "geometry": {"coordinates":[-73.6794891357,45.5157661438],"type":"Point"}
}