{
  "type": "Feature",
  "properties": {
    "iso:country":"CA",
    "sg:address":"5012 50 Ave",
    "sg:city":"Millet",
    "sg:classifiers":[
        {
            "category":"Shopping",
            "subcategory":"Florist",
            "type":"Retail Goods"
        }
    ],
    "sg:phone":"+1 780 387 0007",
    "sg:postcode":"T0C 1Z0",
    "sg:province":"AB",
    "wof:name":"Daisy Lane Flowers Giftware",
    "wof:placetype":"venue"
},
  "geometry": {"coordinates":[-113.472564697,53.0956344604],"type":"Point"}
}