{
  "type": "Feature",
  "properties": {
    "addr:full":"3250 2nd Ave W Prince Albert SK S6V 5E9",
    "addr:housenumber":"3250",
    "addr:postcode":"s6v 5e9",
    "addr:street":"2Nd Ave W",
    "iso:country":"CA",
    "sg:address":"3250 2nd Ave W",
    "sg:city":"Prince Albert",
    "sg:classifiers":[
        {
            "category":"Restaurant",
            "type":"Food & Drink"
        }
    ],
    "sg:phone":"+1 306 764 8877",
    "sg:postcode":"S6V 5E9",
    "sg:province":"SK",
    "wof:name":"Boston Pizza",
    "wof:placetype":"venue"
},
  "geometry": {"coordinates":[-105.759872437,53.1835289001],"type":"Point"}
}