{
  "type": "Feature",
  "properties": {
    "addr:full":"Montreal QC H2A 1G1",
    "addr:postcode":"h2a 1g1",
    "iso:country":"CA",
    "sg:city":"Montreal",
    "sg:classifiers":[
        {
            "category":"Personal",
            "subcategory":"Beauty Salon",
            "type":"Services"
        }
    ],
    "sg:phone":"+1 514 722 6753",
    "sg:postcode":"H2A 1G1",
    "sg:province":"QC",
    "wof:name":"Salon Odette Enrg",
    "wof:placetype":"venue"
},
  "geometry": {"coordinates":[-73.60034899999999,45.564758],"type":"Point"}
}