{
  "type": "Feature",
  "properties": {
    "iso:country":"CA",
    "sg:address":"57 Elisia Dr",
    "sg:city":"Moose Jaw",
    "sg:classifiers":[
        {
            "category":"Recreation",
            "type":"Entertainment"
        }
    ],
    "sg:phone":"+1 306 693 3775",
    "sg:postcode":"S6J 1G9",
    "sg:province":"SK",
    "sg:tags":[
        "karate",
        "judo",
        "instr"
    ],
    "wof:name":"Kwan's School of Kempo Karate",
    "wof:placetype":"venue"
},
  "geometry": {"coordinates":[-105.547973633,50.419303894],"type":"Point"}
}