{
  "type": "Feature",
  "properties": {
    "addr:full":"333 College St Toronto ON M5T 1S2",
    "addr:housenumber":"333",
    "addr:postcode":"m5t 1s2",
    "addr:street":"College St",
    "iso:country":"CA",
    "sg:address":"333 College St",
    "sg:city":"Toronto",
    "sg:classifiers":[
        {
            "category":"Retail",
            "subcategory":"Auto Rental",
            "type":"Services"
        }
    ],
    "sg:phone":"+1 416 963 9496",
    "sg:postcode":"M5T 1S2",
    "sg:province":"ON",
    "sg:tags":[
        "renting",
        "automobile"
    ],
    "wof:name":"Budget Car & Truck Rentals",
    "wof:placetype":"venue"
},
  "geometry": {"coordinates":[-79.402534,43.657372],"type":"Point"}
}