{
  "type": "Feature",
  "properties": {
    "addr:full":"London ON N6E 3V8",
    "addr:postcode":"n6e 3v8",
    "iso:country":"CA",
    "sg:city":"London",
    "sg:classifiers":[
        {
            "category":"Home & Garden",
            "subcategory":"Home Furnishings",
            "type":"Retail Goods"
        }
    ],
    "sg:phone":"+1 519 680 0915",
    "sg:postcode":"N6E 3V8",
    "sg:province":"ON",
    "sg:tags":[
        "housewares"
    ],
    "wof:name":"Benix & CO",
    "wof:placetype":"venue"
},
  "geometry": {"coordinates":[-81.2232971191,42.934337616],"type":"Point"}
}