{
  "type": "Feature",
  "properties": {
    "addr:full":"6977 Boul Saint-Laurent Montreal QC H2S 3E1",
    "addr:housenumber":"6977",
    "addr:postcode":"h2s 3e1",
    "addr:street":"Boul Saint-Laurent",
    "iso:country":"CA",
    "sg:address":"6977 Boul Saint-Laurent",
    "sg:city":"Montreal",
    "sg:classifiers":[
        {
            "category":"Professional",
            "subcategory":"Lawyer & Legal Services",
            "type":"Services"
        }
    ],
    "sg:phone":"+1 514 939 3621",
    "sg:postcode":"H2S 3E1",
    "sg:province":"QC",
    "sg:tags":[
        "attorney"
    ],
    "wof:name":"Cavaliere & Associates",
    "wof:placetype":"venue"
},
  "geometry": {"coordinates":[-73.615219,45.53339],"type":"Point"}
}