{
  "type": "Feature",
  "properties": {
    "iso:country":"CA",
    "sg:address":"209 Simcoe St N",
    "sg:city":"Oshawa",
    "sg:classifiers":[
        {
            "category":"Health Services",
            "subcategory":"Doctor",
            "type":"Services"
        }
    ],
    "sg:phone":"+1 905 576 5311",
    "sg:postcode":"L1G 4T1",
    "sg:province":"ON",
    "sg:tags":[
        "dentist"
    ],
    "wof:name":"Ballard, A J DDS",
    "wof:placetype":"venue"
},
  "geometry": {"coordinates":[-78.865852,43.90313],"type":"Point"}
}