{
  "type": "Feature",
  "properties": {
    "addr:full":"95 Smith Ave Truro NS B2N 1C6",
    "addr:housenumber":"95",
    "addr:postcode":"b2n 1c6",
    "addr:street":"Smith Ave",
    "iso:country":"CA",
    "sg:address":"95 Smith Ave",
    "sg:city":"Truro",
    "sg:classifiers":[
        {
            "category":"Manufacturing",
            "subcategory":"Lumber",
            "type":"Manufacturing & Wholesale Goods"
        }
    ],
    "sg:phone":"+1 902 895 8641",
    "sg:postcode":"B2N 1C6",
    "sg:province":"NS",
    "sg:tags":[
        "syrup",
        "maple",
        "sugar"
    ],
    "wof:name":"Cook's Maple Ridge Maple Prods",
    "wof:placetype":"venue"
},
  "geometry": {"coordinates":[-63.291134,45.364067],"type":"Point"}
}