{
  "type": "Feature",
  "properties": {
    "addr:full":"375 Hardy Rd Brantford ON N3T 5L8",
    "addr:housenumber":"375",
    "addr:postcode":"n3t 5l8",
    "addr:street":"Hardy Rd",
    "iso:country":"CA",
    "sg:address":"375 Hardy Rd",
    "sg:city":"Brantford",
    "sg:classifiers":[
        {
            "category":"Building & Trades",
            "subcategory":"Construction",
            "type":"Services"
        }
    ],
    "sg:phone":"+1 519 770 0200",
    "sg:postcode":"N3T 5L8",
    "sg:province":"ON",
    "sg:tags":[
        "sand",
        "gravel",
        "paving",
        "contractor"
    ],
    "wof:name":"Tcg Asphalt & Construction",
    "wof:placetype":"venue"
},
  "geometry": {"coordinates":[-80.31999999999999,43.160553],"type":"Point"}
}