{
  "type": "Feature",
  "properties": {
    "iso:country":"CA",
    "sg:address":"658 Topsail Rd",
    "sg:city":"St. John's",
    "sg:classifiers":[
        {
            "category":"Food & Beverages",
            "subcategory":"Liquor & Beverages",
            "type":"Retail Goods"
        }
    ],
    "sg:phone":"+1 709 368 5883",
    "sg:postcode":"A1E 2E2",
    "sg:province":"NL",
    "sg:tags":[
        "beer",
        "ale"
    ],
    "wof:name":"Fitz's Cold Beer",
    "wof:placetype":"venue"
},
  "geometry": {"coordinates":[-52.7710113525,47.5246543884],"type":"Point"}
}