{
  "type": "Feature",
  "properties": {
    "addr:full":"6014 Rue DE Jumonville Montreal QC H1M 1R6",
    "addr:housenumber":"6014",
    "addr:postcode":"h1m 1r6",
    "addr:street":"Rue De Jumonville",
    "iso:country":"CA",
    "sg:address":"6014 Rue DE Jumonville",
    "sg:city":"Montreal",
    "sg:classifiers":[
        {
            "category":"Health Services",
            "subcategory":"Health Practitioner",
            "type":"Services"
        }
    ],
    "sg:phone":"+1 514 253 7099",
    "sg:postcode":"H1M 1R6",
    "sg:province":"QC",
    "sg:tags":[
        "psychologist"
    ],
    "wof:name":"Fontaine, Francine S",
    "wof:placetype":"venue"
},
  "geometry": {"coordinates":[-73.549446106,45.5780792236],"type":"Point"}
}