{
  "type": "Feature",
  "properties": {
    "iso:country":"CA",
    "sg:address":"633 Rue Laurent",
    "sg:city":"Granby",
    "sg:classifiers":[
        {
            "category":"Manufacturing",
            "subcategory":"Tools & Machinery",
            "type":"Manufacturing & Wholesale Goods"
        }
    ],
    "sg:phone":"+1 450 375 1375",
    "sg:postcode":"J2G 8P4",
    "sg:province":"QC",
    "sg:tags":[
        "machine",
        "shop"
    ],
    "wof:name":"Usinage Feeley Inc",
    "wof:placetype":"venue"
},
  "geometry": {"coordinates":[-72.754288,45.391785],"type":"Point"}
}