{
  "type": "Feature",
  "properties": {
    "addr:full":"905 Rymal Rd E Hamilton ON L8W 3M2",
    "addr:housenumber":"905",
    "addr:postcode":"l8w 3m2",
    "addr:street":"Rymal Rd E",
    "iso:country":"CA",
    "sg:address":"905 Rymal Rd E",
    "sg:city":"Hamilton",
    "sg:classifiers":[
        {
            "category":"Personal",
            "type":"Services"
        }
    ],
    "sg:phone":"+1 905 383 9774",
    "sg:postcode":"L8W 3M2",
    "sg:province":"ON",
    "sg:tags":[
        "control",
        "weight"
    ],
    "wof:name":"Beverly Hills Weight Mgmt Ctr",
    "wof:placetype":"venue"
},
  "geometry": {"coordinates":[-79.852432251,43.1925697327],"type":"Point"}
}