{
  "type": "Feature",
  "properties": {
    "addr:full":"70 Rue Des Fauvettes Saint-Basile-Le-Grand QC J3N 1P4",
    "addr:housenumber":"70",
    "addr:postcode":"j3n 1p4",
    "addr:street":"Rue Des Fauvettes",
    "iso:country":"CA",
    "sg:address":"70 Rue Des Fauvettes",
    "sg:city":"Saint-Basile-Le-Grand",
    "sg:classifiers":[
        {
            "category":"Personal",
            "subcategory":"Beauty Salon",
            "type":"Services"
        }
    ],
    "sg:phone":"+1 450 441 6313",
    "sg:postcode":"J3N 1P4",
    "sg:province":"QC",
    "wof:name":"Ambiance Coiffure",
    "wof:placetype":"venue"
},
  "geometry": {"coordinates":[-73.281853,45.5144],"type":"Point"}
}