{
  "type": "Feature",
  "properties": {
    "iso:country":"CA",
    "sg:address":"5622 Horsefly Lake Rd",
    "sg:city":"Horsefly",
    "sg:classifiers":[
        {
            "category":"Government",
            "subcategory":"Office",
            "type":"Public Place"
        }
    ],
    "sg:phone":"+1 250 620 3200",
    "sg:postcode":"V0L 1L0",
    "sg:province":"BC",
    "wof:name":"BC Forests",
    "wof:placetype":"venue"
},
  "geometry": {"coordinates":[-121.407501221,52.3313446045],"type":"Point"}
}