{
  "type": "Feature",
  "properties": {
    "addr:full":"RR 3 Princeton ON N0J 1V0",
    "addr:postcode":"n0j 1v0",
    "addr:street":"Rr 3",
    "iso:country":"CA",
    "sg:address":"RR 3",
    "sg:city":"Princeton",
    "sg:classifiers":[
        {
            "category":"Shopping",
            "subcategory":"Computers & Home Electronics",
            "type":"Retail Goods"
        }
    ],
    "sg:phone":"+1 519 458 4146",
    "sg:postcode":"N0J 1V0",
    "sg:province":"ON",
    "sg:tags":[
        "equipment",
        "satellite",
        "system",
        "antenna"
    ],
    "wof:name":"Wight Electronic Svc",
    "wof:placetype":"venue"
},
  "geometry": {"coordinates":[-80.52752700000001,43.172009],"type":"Point"}
}