{
  "type": "Feature",
  "properties": {
    "addr:full":"11222 Rue Hamon Montreal QC H3M 3A3",
    "addr:housenumber":"11222",
    "addr:postcode":"h3m 3a3",
    "addr:street":"Rue Hamon",
    "iso:country":"CA",
    "sg:address":"11222 Rue Hamon",
    "sg:city":"Montreal",
    "sg:classifiers":[
        {
            "category":"Wholesale",
            "subcategory":"Electrical",
            "type":"Manufacturing & Wholesale Goods"
        }
    ],
    "sg:phone":"+1 514 331 6833",
    "sg:postcode":"H3M 3A3",
    "sg:province":"QC",
    "sg:tags":[
        "lighting",
        "fixture"
    ],
    "wof:name":"Lampes Du Nord DE LA Metropole",
    "wof:placetype":"venue"
},
  "geometry": {"coordinates":[-73.682014,45.540405],"type":"Point"}
}