{
  "type": "Feature",
  "properties": {
    "addr:full":"1711 Simcoe St N Oshawa ON L1G 4Y1",
    "addr:housenumber":"1711",
    "addr:postcode":"l1g 4y1",
    "addr:street":"Simcoe St N",
    "iso:country":"CA",
    "sg:address":"1711 Simcoe St N",
    "sg:city":"Oshawa",
    "sg:classifiers":[
        {
            "category":"Organizations",
            "subcategory":"Professional Association",
            "type":"Services"
        }
    ],
    "sg:phone":"+1 905 725 5722",
    "sg:postcode":"L1G 4Y1",
    "sg:province":"ON",
    "wof:name":"Scouts Canada",
    "wof:placetype":"venue"
},
  "geometry": {"coordinates":[-78.8867340088,43.9416313171],"type":"Point"}
}