{
  "type": "Feature",
  "properties": {
    "addr:full":"St Catharines ON L2S 3P2",
    "addr:postcode":"l2s 3p2",
    "iso:country":"CA",
    "sg:city":"St Catharines",
    "sg:classifiers":[
        {
            "category":"Shopping",
            "subcategory":"Florist",
            "type":"Retail Goods"
        }
    ],
    "sg:phone":"+1 905 641 2331",
    "sg:postcode":"L2S 3P2",
    "sg:province":"ON",
    "wof:name":"Ambassador's Ridley Flowers",
    "wof:placetype":"venue"
},
  "geometry": {"coordinates":[-79.2608947754,43.1561698914],"type":"Point"}
}