{
  "type": "Feature",
  "properties": {
    "addr:full":"1281 Great Northern Rd Sault Ste Marie ON P6A 5K7",
    "addr:housenumber":"1281",
    "addr:postcode":"p6a 5k7",
    "addr:street":"Great Northern Rd",
    "iso:country":"CA",
    "sg:address":"1281 Great Northern Rd",
    "sg:city":"Sault Ste Marie",
    "sg:classifiers":[
        {
            "category":"Shopping",
            "type":"Retail Goods"
        }
    ],
    "sg:phone":"+1 705 946 2866",
    "sg:postcode":"P6A 5K7",
    "sg:province":"ON",
    "sg:tags":[
        "monument"
    ],
    "wof:name":"Eternal Monuments",
    "wof:placetype":"venue"
},
  "geometry": {"coordinates":[-84.32092299999999,46.565788],"type":"Point"}
}