{
  "type": "Feature",
  "properties": {
    "addr:full":"560 Av Royale St-Joachim-DE-Montmorency QC G0A 3X0",
    "addr:housenumber":"560",
    "addr:postcode":"g0a 3x0",
    "addr:street":"Av Royale",
    "iso:country":"CA",
    "sg:address":"560 Av Royale",
    "sg:city":"St-Joachim-DE-Montmorency",
    "sg:classifiers":[
        {
            "category":"Government",
            "subcategory":"Office",
            "type":"Public Place"
        }
    ],
    "sg:phone":"+1 418 827 5172",
    "sg:postcode":"G0A 3X0",
    "sg:province":"QC",
    "sg:tags":[
        "village"
    ],
    "wof:name":"St-Joachim DE Montmorency Grge",
    "wof:placetype":"venue"
},
  "geometry": {"coordinates":[-70.84567300000001,47.061188],"type":"Point"}
}