{
  "type": "Feature",
  "properties": {
    "addr:full":"108 13E Av Deux-Montagnes QC J7R 3T8",
    "addr:housenumber":"108",
    "addr:postcode":"j7r 3t8",
    "addr:street":"13E Av Deux-Montagnes",
    "iso:country":"CA",
    "sg:address":"108 13E Av",
    "sg:city":"Deux-Montagnes",
    "sg:classifiers":[
        {
            "category":"Social Services",
            "type":"Services"
        }
    ],
    "sg:phone":"+1 450 491 3958",
    "sg:postcode":"J7R 3T8",
    "sg:province":"QC",
    "sg:tags":[
        "organization",
        "welfare"
    ],
    "wof:name":"Maison Des Jeunes DE Deux",
    "wof:placetype":"venue"
},
  "geometry": {"coordinates":[-73.892456,45.536572],"type":"Point"}
}