{
  "type": "Feature",
  "properties": {
    "iso:country":"CA",
    "sg:city":"Teslin",
    "sg:classifiers":[
        {
            "category":"Travel",
            "subcategory":"Campground",
            "type":"Entertainment"
        }
    ],
    "sg:phone":"+1 867 390 2600",
    "sg:postcode":"Y0A 1B0",
    "sg:province":"YT",
    "wof:name":"Mukluk Annie's Motel",
    "wof:placetype":"venue"
},
  "geometry": {"coordinates":[-132.711959839,60.1686248779],"type":"Point"}
}