{
  "type": "Feature",
  "properties": {
    "addr:full":"770 Great Northern Rd RR 2 Sault Ste Marie ON P6A 5K7",
    "addr:housenumber":"770",
    "addr:postcode":"p6a 5k7",
    "addr:street":"Great Northern Rd;2",
    "iso:country":"CA",
    "sg:address":"770 Great Northern Rd RR 2",
    "sg:city":"Sault Ste Marie",
    "sg:classifiers":[
        {
            "category":"Health Services",
            "subcategory":"Nursing And Care Facility",
            "type":"Services"
        }
    ],
    "sg:phone":"+1 705 949 3611",
    "sg:postcode":"P6A 5K7",
    "sg:province":"ON",
    "sg:tags":[
        "home",
        "convalescent"
    ],
    "wof:name":"Extendicare Tendercare Nursing",
    "wof:placetype":"venue"
},
  "geometry": {"coordinates":[-84.319267,46.549828],"type":"Point"}
}