{
  "type": "Feature",
  "properties": {
    "addr:full":"SW-9-6-1E Rosenort MB R0G 1W0",
    "addr:postcode":"r0g 1w0",
    "iso:country":"CA",
    "sg:address":"SW-9-6-1E",
    "sg:city":"Rosenort",
    "sg:classifiers":[
        {
            "category":"Home & Garden",
            "subcategory":"Building Materials",
            "type":"Retail Goods"
        }
    ],
    "sg:phone":"+1 204 746 8824",
    "sg:postcode":"R0G 1W0",
    "sg:province":"MB",
    "sg:tags":[
        "lumber"
    ],
    "wof:name":"Valley Enterprises Rosenort",
    "wof:placetype":"venue"
},
  "geometry": {"coordinates":[-97.43461600000001,49.464806],"type":"Point"}
}