{
  "type": "Feature",
  "properties": {
    "addr:full":"119 Rue Principale O Farnham QC J2N 1K3",
    "addr:housenumber":"119",
    "addr:postcode":"j2n 1k3",
    "addr:street":"Rue Principale O",
    "iso:country":"CA",
    "sg:address":"119 Rue Principale O",
    "sg:city":"Farnham",
    "sg:classifiers":[
        {
            "category":"Restaurant",
            "type":"Food & Drink"
        }
    ],
    "sg:phone":"+1 450 293 3831",
    "sg:postcode":"J2N 1K3",
    "sg:province":"QC",
    "wof:name":"Ben Pizzeria",
    "wof:placetype":"venue"
},
  "geometry": {"coordinates":[-72.9792175293,45.2853012085],"type":"Point"}
}