{
  "type": "Feature",
  "properties": {
    "iso:country":"CA",
    "sg:address":"201 Weston Rd",
    "sg:city":"Toronto",
    "sg:classifiers":[
        {
            "category":"Building & Trades",
            "subcategory":"Construction",
            "type":"Services"
        }
    ],
    "sg:phone":"+1 416 760 8141",
    "sg:postcode":"M6N 3P1",
    "sg:province":"ON",
    "sg:tags":[
        "apartment",
        "general",
        "contractor"
    ],
    "wof:name":"Chuchem Corp",
    "wof:placetype":"venue"
},
  "geometry": {"coordinates":[-79.4715042114,43.6771469116],"type":"Point"}
}