{
  "type": "Feature",
  "properties": {
    "addr:full":"Vancouver BC V6E 2V2",
    "addr:postcode":"v6e 2v2",
    "iso:country":"CA",
    "sg:city":"Vancouver",
    "sg:classifiers":[
        {
            "category":"Travel",
            "subcategory":"Travel Agent",
            "type":"Entertainment"
        }
    ],
    "sg:phone":"+1 604 669 2521",
    "sg:postcode":"V6E 2V2",
    "sg:province":"BC",
    "sg:tags":[
        "bureau",
        "agency",
        "tours"
    ],
    "wof:name":"Skyland Tours Ltd",
    "wof:placetype":"venue"
},
  "geometry": {"coordinates":[-123.12344400000001,49.288631],"type":"Point"}
}