{
  "type": "Feature",
  "properties": {
    "addr:full":"44 Main St E Ridgetown ON N0P 2C0",
    "addr:housenumber":"44",
    "addr:postcode":"n0p 2c0",
    "addr:street":"Main St E",
    "iso:country":"CA",
    "sg:address":"44 Main St E",
    "sg:city":"Ridgetown",
    "sg:classifiers":[
        {
            "category":"Professional",
            "subcategory":"Accounting & Tax Preparation",
            "type":"Services"
        }
    ],
    "sg:phone":"+1 519 674 3020",
    "sg:postcode":"N0P 2C0",
    "sg:province":"ON",
    "sg:tags":[
        "accountant",
        "return",
        "filing"
    ],
    "wof:name":"Padgett Business Svc of Kent",
    "wof:placetype":"venue"
},
  "geometry": {"coordinates":[-81.8859405518,42.4401893616],"type":"Point"}
}