{
  "type": "Feature",
  "properties": {
    "addr:full":"3232 Burroughs Manor NE Calgary AB T1Y 6K2",
    "addr:housenumber":"3232",
    "addr:postcode":"t1y 6k2",
    "addr:street":"Burroughs Manor Ne",
    "iso:country":"CA",
    "sg:address":"3232 Burroughs Manor NE",
    "sg:city":"Calgary",
    "sg:classifiers":[
        {
            "category":"Real Estate",
            "subcategory":"Developer",
            "type":"Services"
        }
    ],
    "sg:phone":"+1 403 293 3333",
    "sg:postcode":"T1Y 6K2",
    "sg:province":"AB",
    "sg:tags":[
        "mobile",
        "home"
    ],
    "wof:name":"Parkridges Estates",
    "wof:placetype":"venue"
},
  "geometry": {"coordinates":[-113.928619385,51.0805168152],"type":"Point"}
}