{
  "type": "Feature",
  "properties": {
    "addr:full":"5111 51st St Redwater AB T0A 2W0",
    "addr:housenumber":"5111",
    "addr:postcode":"t0a 2w0",
    "addr:street":"51St St",
    "iso:country":"CA",
    "sg:address":"5111 51st St",
    "sg:city":"Redwater",
    "sg:classifiers":[
        {
            "category":"Organizations",
            "subcategory":"Religious Organization",
            "type":"Services"
        }
    ],
    "sg:phone":"+1 780 942 3674",
    "sg:postcode":"T0A 2W0",
    "sg:province":"AB",
    "sg:tags":[
        "church"
    ],
    "wof:name":"United Church of Canada",
    "wof:placetype":"venue"
},
  "geometry": {"coordinates":[-113.11203765899999,53.9524612427],"type":"Point"}
}