{
  "type": "Feature",
  "properties": {
    "addr:full":"Chambord QC G0W 1G0",
    "addr:postcode":"g0w 1g0",
    "iso:country":"CA",
    "sg:city":"Chambord",
    "sg:classifiers":[
        {
            "category":"Personal",
            "subcategory":"Barber",
            "type":"Services"
        }
    ],
    "sg:phone":"+1 418 342 6764",
    "sg:postcode":"G0W 1G0",
    "sg:province":"QC",
    "wof:name":"Salon Clement",
    "wof:placetype":"venue"
},
  "geometry": {"coordinates":[-71.98957799999999,48.31575],"type":"Point"}
}