{
  "type": "Feature",
  "properties": {
    "addr:full":"419 Fairway Rd S Kitchener ON N2C 1X4",
    "addr:housenumber":"419",
    "addr:postcode":"n2c 1x4",
    "addr:street":"Fairway Rd",
    "iso:country":"CA",
    "sg:address":"419 Fairway Rd S",
    "sg:city":"Kitchener",
    "sg:classifiers":[
        {
            "category":"Shopping",
            "subcategory":"Hobbies, Toys, & Games",
            "type":"Retail Goods"
        }
    ],
    "sg:phone":"+1 519 894 8697",
    "sg:postcode":"N2C 1X4",
    "sg:province":"ON",
    "wof:name":"Toys R US",
    "wof:placetype":"venue"
},
  "geometry": {"coordinates":[-80.44393920900001,43.4207000732],"type":"Point"}
}