{
  "type": "Feature",
  "properties": {
    "addr:full":"47 Kenneth Ave Toronto ON M6P 1J1",
    "addr:housenumber":"47",
    "addr:postcode":"m6p 1j1",
    "addr:street":"Kenneth Ave",
    "iso:country":"CA",
    "sg:address":"47 Kenneth Ave",
    "sg:city":"Toronto",
    "sg:classifiers":[
        {
            "category":"Professional",
            "type":"Services"
        }
    ],
    "sg:phone":"+1 416 410 7792",
    "sg:postcode":"M6P 1J1",
    "sg:province":"ON",
    "sg:tags":[
        "inventor"
    ],
    "wof:name":"Inventor's Alliance of Canada",
    "wof:placetype":"venue"
},
  "geometry": {"coordinates":[-79.457329,43.66169],"type":"Point"}
}