{
  "type": "Feature",
  "properties": {
    "addr:full":"Winnipeg MB R3B 1V9",
    "addr:postcode":"r3b 1v9",
    "iso:country":"CA",
    "sg:city":"Winnipeg",
    "sg:classifiers":[
        {
            "category":"Health Services",
            "subcategory":"Doctor",
            "type":"Services"
        }
    ],
    "sg:phone":"+1 204 772 2927",
    "sg:postcode":"R3B 1V9",
    "sg:province":"MB",
    "sg:tags":[
        "physician",
        "surgeon"
    ],
    "wof:name":"Sargent Walk-In Medical Clinic",
    "wof:placetype":"venue"
},
  "geometry": {"coordinates":[-97.153946,49.896488],"type":"Point"}
}