{
  "type": "Feature",
  "properties": {
    "addr:full":"6769 Rue Marquette Montreal QC H2G 2Y9",
    "addr:housenumber":"6769",
    "addr:postcode":"h2g 2y9",
    "addr:street":"Rue Marquette",
    "iso:country":"CA",
    "sg:address":"6769 Rue Marquette",
    "sg:city":"Montreal",
    "sg:classifiers":[
        {
            "category":"Retail",
            "subcategory":"Laundry & Dry Cleaning",
            "type":"Services"
        }
    ],
    "sg:phone":"+1 514 376 6140",
    "sg:postcode":"H2G 2Y9",
    "sg:province":"QC",
    "sg:tags":[
        "cleaners",
        "rug",
        "carpet"
    ],
    "wof:name":"Nettoyage DE Tapis Le Quebec",
    "wof:placetype":"venue"
},
  "geometry": {"coordinates":[-73.60163900000001,45.544796],"type":"Point"}
}