{
  "type": "Feature",
  "properties": {
    "iso:country":"CA",
    "sg:address":"56 Bentley Ave",
    "sg:city":"Nepean",
    "sg:classifiers":[
        {
            "category":"Building & Trades",
            "subcategory":"Construction",
            "type":"Services"
        }
    ],
    "sg:phone":"+1 613 226 1550",
    "sg:postcode":"K2E 6T8",
    "sg:province":"ON",
    "sg:tags":[
        "masonry",
        "contractor"
    ],
    "wof:name":"DE Marinis Inc",
    "wof:placetype":"venue"
},
  "geometry": {"coordinates":[-75.71705627439999,45.3337516785],"type":"Point"}
}