{
  "type": "Feature",
  "properties": {
    "addr:full":"Mascouche QC J7K 1S8",
    "addr:postcode":"j7k 1s8",
    "iso:country":"CA",
    "sg:city":"Mascouche",
    "sg:classifiers":[
        {
            "category":"Building & Trades",
            "subcategory":"Plumbing",
            "type":"Services"
        }
    ],
    "sg:phone":"+1 450 474 4084",
    "sg:postcode":"J7K 1S8",
    "sg:province":"QC",
    "sg:tags":[
        "contractor"
    ],
    "wof:name":"Francois Henault Enr",
    "wof:placetype":"venue"
},
  "geometry": {"coordinates":[-73.58566999999999,45.745068],"type":"Point"}
}