{
  "type": "Feature",
  "properties": {
    "addr:full":"Winnipeg MB R3M 0X9",
    "addr:postcode":"r3m 0x9",
    "iso:country":"CA",
    "sg:city":"Winnipeg",
    "sg:classifiers":[
        {
            "category":"Building & Trades",
            "subcategory":"Construction",
            "type":"Services"
        }
    ],
    "sg:phone":"+1 204 477 0101",
    "sg:postcode":"R3M 0X9",
    "sg:province":"MB",
    "sg:tags":[
        "concrete",
        "contractor"
    ],
    "wof:name":"Gibraltar Concrete Ltd",
    "wof:placetype":"venue"
},
  "geometry": {"coordinates":[-97.15144348139999,49.8712882996],"type":"Point"}
}