{
  "type": "Feature",
  "properties": {
    "addr:full":"23 11th St Weyburn SK S4H 1J1",
    "addr:housenumber":"23",
    "addr:postcode":"s4h 1j1",
    "addr:street":"11Th St",
    "iso:country":"CA",
    "sg:address":"23 11th St",
    "sg:city":"Weyburn",
    "sg:classifiers":[
        {
            "category":"Building & Trades",
            "subcategory":"Construction",
            "type":"Services"
        }
    ],
    "sg:phone":"+1 306 842 2900",
    "sg:postcode":"S4H 1J1",
    "sg:province":"SK",
    "sg:tags":[
        "maker",
        "cabinet"
    ],
    "wof:name":"Maas Made Woodworks",
    "wof:placetype":"venue"
},
  "geometry": {"coordinates":[-103.843063,49.65826],"type":"Point"}
}