{
  "type": "Feature",
  "properties": {
    "addr:full":"6255 Fernbank Rd Stittsville ON K2S 1X5",
    "addr:housenumber":"6255",
    "addr:postcode":"k2s 1x5",
    "addr:street":"Fernbank Rd",
    "iso:country":"CA",
    "sg:address":"6255 Fernbank Rd",
    "sg:city":"Stittsville",
    "sg:classifiers":[
        {
            "category":"Organizations",
            "subcategory":"Religious Organization",
            "type":"Services"
        }
    ],
    "sg:phone":"+1 613 836 4962",
    "sg:postcode":"K2S 1X5",
    "sg:province":"ON",
    "sg:tags":[
        "church"
    ],
    "wof:name":"Stittsville United Church",
    "wof:placetype":"venue"
},
  "geometry": {"coordinates":[-75.913506,45.24733],"type":"Point"}
}