{
  "type": "Feature",
  "properties": {
    "addr:full":"752 Runnymede Ave Coquitlam BC V3J 2V1",
    "addr:housenumber":"752",
    "addr:postcode":"v3j 2v1",
    "addr:street":"Runnymede Ave",
    "iso:country":"CA",
    "sg:address":"752 Runnymede Ave",
    "sg:city":"Coquitlam",
    "sg:classifiers":[
        {
            "category":"Organizations",
            "subcategory":"Non-profit Organization",
            "type":"Services"
        }
    ],
    "sg:phone":"+1 604 939 2400",
    "sg:postcode":"V3J 2V1",
    "sg:province":"BC",
    "sg:tags":[
        "disability",
        "live",
        "music",
        "entertainment"
    ],
    "wof:name":"Classic Mobile Music",
    "wof:placetype":"venue"
},
  "geometry": {"coordinates":[-122.877731,49.258961],"type":"Point"}
}