{
  "type": "Feature",
  "properties": {
    "addr:full":"2740 Commercial Dr Vancouver BC V5N 5P4",
    "addr:housenumber":"2740",
    "addr:postcode":"v5n 5p4",
    "addr:street":"Commercial Dr",
    "iso:country":"CA",
    "sg:address":"2740 Commercial Dr",
    "sg:city":"Vancouver",
    "sg:classifiers":[
        {
            "category":"Travel",
            "subcategory":"Travel Agent",
            "type":"Entertainment"
        }
    ],
    "sg:phone":"+1 604 876 2212",
    "sg:postcode":"V5N 5P4",
    "sg:province":"BC",
    "sg:tags":[
        "agency",
        "bureau"
    ],
    "wof:name":"Star Travel Holidays Ltd",
    "wof:placetype":"venue"
},
  "geometry": {"coordinates":[-123.069588,49.26009],"type":"Point"}
}