{
  "type": "Feature",
  "properties": {
    "addr:full":"107 Aspen St Leroy SK S0K 2P0",
    "addr:housenumber":"107",
    "addr:postcode":"s0k 2p0",
    "addr:street":"Aspen St",
    "iso:country":"CA",
    "sg:address":"107 Aspen St",
    "sg:city":"Leroy",
    "sg:classifiers":[
        {
            "category":"Building & Trades",
            "subcategory":"Construction",
            "type":"Services"
        }
    ],
    "sg:phone":"+1 306 286 3289",
    "sg:postcode":"S0K 2P0",
    "sg:province":"SK",
    "sg:tags":[
        "maker",
        "cabinet"
    ],
    "wof:name":"Country Wood",
    "wof:placetype":"venue"
},
  "geometry": {"coordinates":[-104.744072,52.003365],"type":"Point"}
}