{
  "type": "Feature",
  "properties": {
    "iso:country":"CA",
    "sg:address":"638 Sheppard Ave W # A",
    "sg:city":"North York",
    "sg:classifiers":[
        {
            "category":"Food & Beverages",
            "subcategory":"Specialty",
            "type":"Retail Goods"
        }
    ],
    "sg:phone":"+1 416 636 7790",
    "sg:postcode":"M3H 2S1",
    "sg:province":"ON",
    "sg:tags":[
        "supplement"
    ],
    "wof:name":"Knowledge Products",
    "wof:placetype":"venue"
},
  "geometry": {"coordinates":[-79.441002,43.75515],"type":"Point"}
}