{
  "type": "Feature",
  "properties": {
    "addr:full":"2 Rue Elie-Rochefort Port-Cartier QC G5B 2N2",
    "addr:housenumber":"2",
    "addr:postcode":"g5b 2n2",
    "addr:street":"Rue Elie-Rochefort",
    "iso:country":"CA",
    "sg:address":"2 Rue Elie-Rochefort",
    "sg:city":"Port-Cartier",
    "sg:classifiers":[
        {
            "category":"Health Services",
            "subcategory":"Health Practitioner",
            "type":"Services"
        }
    ],
    "sg:phone":"+1 418 766 3508",
    "sg:postcode":"G5B 2N2",
    "sg:province":"QC",
    "sg:tags":[
        "physiotherapist"
    ],
    "wof:name":"Clinique Physio-Massage-Port",
    "wof:placetype":"venue"
},
  "geometry": {"coordinates":[-66.880943,50.029186],"type":"Point"}
}