{
  "type": "Feature",
  "properties": {
    "iso:country":"CA",
    "sg:address":"379 St. Paul St",
    "sg:city":"St Catharines",
    "sg:classifiers":[
        {
            "category":"Restaurant",
            "type":"Food & Drink"
        }
    ],
    "sg:phone":"+1 905 682 1885",
    "sg:postcode":"L2R 3N1",
    "sg:province":"ON",
    "sg:tags":[
        "good",
        "oriental"
    ],
    "wof:name":"Oriental Food Mart",
    "wof:placetype":"venue"
},
  "geometry": {"coordinates":[-79.241425,43.160572],"type":"Point"}
}