{
  "type": "Feature",
  "properties": {
    "iso:country":"CA",
    "sg:address":"1223 45 Ave NE",
    "sg:city":"Calgary",
    "sg:classifiers":[
        {
            "category":"Building & Trades",
            "subcategory":"Construction",
            "type":"Services"
        }
    ],
    "sg:phone":"+1 403 250 1258",
    "sg:postcode":"T2E 2P2",
    "sg:province":"AB",
    "sg:tags":[
        "general",
        "contractor"
    ],
    "wof:name":"Waycrest Construction Ltd",
    "wof:placetype":"venue"
},
  "geometry": {"coordinates":[-114.03582,51.093163],"type":"Point"}
}