{
  "type": "Feature",
  "properties": {
    "iso:country":"CA",
    "sg:address":"4435 Grange St",
    "sg:city":"Burnaby",
    "sg:classifiers":[
        {
            "category":"Health Services",
            "subcategory":"Nursing And Care Facility",
            "type":"Services"
        }
    ],
    "sg:phone":"+1 604 433 2455",
    "sg:postcode":"V5H 1P4",
    "sg:province":"BC",
    "sg:tags":[
        "home",
        "hospital",
        "convalescent"
    ],
    "wof:name":"Willingdon Park Hospital Ltd",
    "wof:placetype":"venue"
},
  "geometry": {"coordinates":[-123.005256653,49.2321166992],"type":"Point"}
}