{
  "type": "Feature",
  "properties": {
    "iso:country":"CA",
    "sg:address":"191 St David St",
    "sg:city":"Lindsay",
    "sg:classifiers":[
        {
            "category":"Building & Trades",
            "subcategory":"Pest Control",
            "type":"Services"
        }
    ],
    "sg:phone":"+1 705 328 3305",
    "sg:postcode":"K9V 5K7",
    "sg:province":"ON",
    "sg:tags":[
        "deodorizing",
        "disinfecting"
    ],
    "wof:name":"Environmental Odour Control",
    "wof:placetype":"venue"
},
  "geometry": {"coordinates":[-78.73239898680001,44.3726654053],"type":"Point"}
}