{
  "type": "Feature",
  "properties": {
    "addr:full":"5116 50 Ave Whitecourt AB T7S 1A1",
    "addr:housenumber":"5116",
    "addr:postcode":"t7s 1a1",
    "addr:street":"50 Ave",
    "iso:country":"CA",
    "sg:address":"5116 50 Ave",
    "sg:city":"Whitecourt",
    "sg:classifiers":[
        {
            "category":"Sports & Exercise",
            "subcategory":"Bowling",
            "type":"Entertainment"
        }
    ],
    "sg:phone":"+1 780 778 2917",
    "sg:postcode":"T7S 1A1",
    "sg:province":"AB",
    "sg:tags":[
        "center"
    ],
    "wof:name":"Millside Place",
    "wof:placetype":"venue"
},
  "geometry": {"coordinates":[-115.687622,54.140671],"type":"Point"}
}