{
  "type": "Feature",
  "properties": {
    "addr:full":"3008 106 St NW Edmonton AB T6J 5M5",
    "addr:housenumber":"3008",
    "addr:postcode":"t6j 5m5",
    "addr:street":"106 St Nw",
    "iso:country":"CA",
    "sg:address":"3008 106 St NW",
    "sg:city":"Edmonton",
    "sg:classifiers":[
        {
            "category":"Food & Beverages",
            "subcategory":"Liquor & Beverages",
            "type":"Retail Goods"
        }
    ],
    "sg:phone":"+1 780 435 1379",
    "sg:postcode":"T6J 5M5",
    "sg:province":"AB",
    "sg:tags":[
        "store"
    ],
    "wof:name":"106 Street Liquor Store",
    "wof:placetype":"venue"
},
  "geometry": {"coordinates":[-113.501755,53.461941],"type":"Point"}
}