{
  "type": "Feature",
  "properties": {
    "addr:full":"1140 Rue Hodge Saint-Laurent QC H4N 2B7",
    "addr:housenumber":"1140",
    "addr:postcode":"h4n 2b7",
    "addr:street":"Rue Hodge",
    "iso:country":"CA",
    "sg:address":"1140 Rue Hodge",
    "sg:city":"Saint-Laurent",
    "sg:classifiers":[
        {
            "category":"Building & Trades",
            "subcategory":"Construction",
            "type":"Services"
        }
    ],
    "sg:phone":"+1 514 744 1813",
    "sg:postcode":"H4N 2B7",
    "sg:province":"QC",
    "sg:tags":[
        "roofing",
        "contractor"
    ],
    "wof:name":"Toitures Gerry Inc",
    "wof:placetype":"venue"
},
  "geometry": {"coordinates":[-73.66558074949999,45.5118751526],"type":"Point"}
}