{
  "type": "Feature",
  "properties": {
    "iso:country":"CA",
    "sg:city":"Revelstoke",
    "sg:classifiers":[
        {
            "category":"Food & Beverages",
            "subcategory":"Bakery",
            "type":"Retail Goods"
        }
    ],
    "sg:phone":"+1 250 837 4556",
    "sg:postcode":"V0E 2S0",
    "sg:province":"BC",
    "sg:tags":[
        "baker"
    ],
    "wof:name":"Chalet Bakery",
    "wof:placetype":"venue"
},
  "geometry": {"coordinates":[-118.19277954099999,50.9934234619],"type":"Point"}
}