{
  "type": "Feature",
  "properties": {
    "addr:full":"130 Sunrise Ave North York ON M4A 1B3",
    "addr:housenumber":"130",
    "addr:postcode":"m4a 1b3",
    "addr:street":"Sunrise Ave",
    "iso:country":"CA",
    "sg:address":"130 Sunrise Ave",
    "sg:city":"North York",
    "sg:classifiers":[
        {
            "category":"Manufacturing",
            "subcategory":"Printing",
            "type":"Manufacturing & Wholesale Goods"
        }
    ],
    "sg:phone":"+1 416 752 8212",
    "sg:postcode":"M4A 1B3",
    "sg:province":"ON",
    "sg:tags":[
        "bookbinder"
    ],
    "wof:name":"O'Connor Bindery Svc",
    "wof:placetype":"venue"
},
  "geometry": {"coordinates":[-79.3105926514,43.7176933289],"type":"Point"}
}