{
  "type": "Feature",
  "properties": {
    "iso:country":"CA",
    "sg:address":"1199 Rue Saint-Jean",
    "sg:city":"Quebec",
    "sg:classifiers":[
        {
            "category":"Banks & Credit Unions",
            "subcategory":"Bank",
            "type":"Services"
        }
    ],
    "sg:phone":"+1 418 647 6986",
    "sg:postcode":"G1R 1S3",
    "sg:province":"QC",
    "wof:name":"Banque Nationale Du Canada",
    "wof:placetype":"venue"
},
  "geometry": {"coordinates":[-71.20906066889999,46.8146133423],"type":"Point"}
}