{
  "type": "Feature",
  "properties": {
    "addr:full":"Smithville ON L0R 2A0",
    "addr:postcode":"l0r 2a0",
    "iso:country":"CA",
    "sg:city":"Smithville",
    "sg:classifiers":[
        {
            "category":"Manufacturing",
            "subcategory":"Tools & Machinery",
            "type":"Manufacturing & Wholesale Goods"
        }
    ],
    "sg:phone":"+1 905 957 3381",
    "sg:postcode":"L0R 2A0",
    "sg:province":"ON",
    "sg:tags":[
        "farm",
        "equipment"
    ],
    "wof:name":"Green Line Equipment",
    "wof:placetype":"venue"
},
  "geometry": {"coordinates":[-79.5524520874,43.1117935181],"type":"Point"}
}