{
  "type": "Feature",
  "properties": {
    "iso:country":"CA",
    "sg:address":"24 Rowse Cres",
    "sg:city":"Etobicoke",
    "sg:classifiers":[
        {
            "category":"Real Estate",
            "subcategory":"Architect",
            "type":"Services"
        }
    ],
    "sg:phone":"+1 416 244 6322",
    "sg:postcode":"M9P 3L5",
    "sg:province":"ON",
    "sg:tags":[
        "specification",
        "architectural"
    ],
    "wof:name":"Dgs Consulting Svc",
    "wof:placetype":"venue"
},
  "geometry": {"coordinates":[-79.54275512700001,43.690826416],"type":"Point"}
}