{
  "type": "Feature",
  "properties": {
    "addr:full":"13 North St Lockeport NS B0T 1L0",
    "addr:housenumber":"13",
    "addr:postcode":"b0t 1l0",
    "addr:street":"North St",
    "iso:country":"CA",
    "sg:address":"13 North St",
    "sg:city":"Lockeport",
    "sg:classifiers":[
        {
            "category":"Food & Beverages",
            "subcategory":"Groceries & Convenience Stores",
            "type":"Retail Goods"
        }
    ],
    "sg:phone":"+1 902 656 2514",
    "sg:postcode":"B0T 1L0",
    "sg:province":"NS",
    "sg:tags":[
        "grocer"
    ],
    "wof:name":"Town Market Ltd",
    "wof:placetype":"venue"
},
  "geometry": {"coordinates":[-65.115334,43.697021],"type":"Point"}
}