{
  "type": "Feature",
  "properties": {
    "addr:full":"293 Rue Notre-Dame Est Cap-DE-LA-Madeleine QC G8T 4C9",
    "addr:housenumber":"293",
    "addr:postcode":"g8t 4c9",
    "addr:street":"Rue Notre-Dame Est",
    "iso:country":"CA",
    "sg:address":"293 Rue Notre-Dame Est",
    "sg:city":"Cap-DE-LA-Madeleine",
    "sg:classifiers":[
        {
            "category":"Building & Trades",
            "subcategory":"Equipment Rental",
            "type":"Services"
        }
    ],
    "sg:phone":"+1 819 374 2300",
    "sg:postcode":"G8T 4C9",
    "sg:province":"QC",
    "sg:tags":[
        "audio",
        "leasing"
    ],
    "wof:name":"Arc-En-Scene Enr",
    "wof:placetype":"venue"
},
  "geometry": {"coordinates":[-72.51061199999999,46.359627],"type":"Point"}
}