{
  "type": "Feature",
  "properties": {
    "addr:full":"138 Rue Principale Sainte-Anne-DE-Madawaska NB E7E 1B8",
    "addr:housenumber":"138",
    "addr:postcode":"e7e 1b8",
    "addr:street":"Rue Principale",
    "iso:country":"CA",
    "sg:address":"138 Rue Principale",
    "sg:city":"Sainte-Anne-DE-Madawaska",
    "sg:classifiers":[
        {
            "category":"Shopping",
            "subcategory":"Catalog Store",
            "type":"Retail Goods"
        }
    ],
    "sg:phone":"+1 506 445 2926",
    "sg:postcode":"E7E 1B8",
    "sg:province":"NB",
    "sg:tags":[
        "mail",
        "order",
        "internet"
    ],
    "wof:name":"Sears Canada Inc",
    "wof:placetype":"venue"
},
  "geometry": {"coordinates":[-68.0409088135,47.254070282],"type":"Point"}
}