{
  "type": "Feature",
  "properties": {
    "addr:full":"4741 North Park Dr Port Alberni BC V9Y 3H6",
    "addr:housenumber":"4741",
    "addr:postcode":"v9y 3h6",
    "addr:street":"North Park Dr",
    "iso:country":"CA",
    "sg:address":"4741 North Park Dr",
    "sg:city":"Port Alberni",
    "sg:classifiers":[
        {
            "category":"Building & Trades",
            "subcategory":"Construction",
            "type":"Services"
        }
    ],
    "sg:phone":"+1 250 724 4295",
    "sg:postcode":"V9Y 3H6",
    "sg:province":"BC",
    "sg:tags":[
        "painter"
    ],
    "wof:name":"Trenholme Renovations & Paint",
    "wof:placetype":"venue"
},
  "geometry": {"coordinates":[-124.803962708,49.2408218384],"type":"Point"}
}