{
  "type": "Feature",
  "properties": {
    "addr:full":"121 Mccormack St York ON M6N 1X8",
    "addr:housenumber":"121",
    "addr:postcode":"m6n 1x8",
    "addr:street":"Mccormack St",
    "iso:country":"CA",
    "sg:address":"121 Mccormack St",
    "sg:city":"York",
    "sg:classifiers":[
        {
            "category":"Autos & Motor Vehicles",
            "subcategory":"Auto Supplies",
            "type":"Retail Goods"
        }
    ],
    "sg:phone":"+1 416 604 9333",
    "sg:postcode":"M6N 1X8",
    "sg:province":"ON",
    "sg:tags":[
        "equipment",
        "racing",
        "car",
        "automobile"
    ],
    "wof:name":"Spectrum Performance Tuning",
    "wof:placetype":"venue"
},
  "geometry": {"coordinates":[-79.47732499999999,43.675781],"type":"Point"}
}