{
  "type": "Feature",
  "properties": {
    "addr:full":"33 Wellington Springfield ON N0L 2J0",
    "addr:housenumber":"33",
    "addr:postcode":"n0l 2j0",
    "addr:street":"Wellington",
    "iso:country":"CA",
    "sg:address":"33 Wellington",
    "sg:city":"Springfield",
    "sg:classifiers":[
        {
            "category":"Government",
            "subcategory":"Office",
            "type":"Public Place"
        }
    ],
    "sg:phone":"+1 519 765 4044",
    "sg:postcode":"N0L 2J0",
    "sg:province":"ON",
    "sg:tags":[
        "village"
    ],
    "wof:name":"Springfield Lions Comm Hall",
    "wof:placetype":"venue"
},
  "geometry": {"coordinates":[-80.936378,42.829491],"type":"Point"}
}