{
  "type": "Feature",
  "properties": {
    "addr:full":"336 Main St Stonewall MB R0C 2Z0",
    "addr:housenumber":"336",
    "addr:postcode":"r0c 2z0",
    "addr:street":"Main St",
    "iso:country":"CA",
    "sg:address":"336 Main St",
    "sg:city":"Stonewall",
    "sg:classifiers":[
        {
            "category":"Government",
            "subcategory":"Office",
            "type":"Public Place"
        }
    ],
    "sg:phone":"+1 204 467 4702",
    "sg:postcode":"R0C 2Z0",
    "sg:province":"MB",
    "wof:name":"Manitoba Agricultural Rep",
    "wof:placetype":"venue"
},
  "geometry": {"coordinates":[-97.326424,50.135117],"type":"Point"}
}