{
  "type": "Feature",
  "properties": {
    "addr:full":"26830 25 Ave Aldergrove BC V4W 2Y4",
    "addr:housenumber":"26830",
    "addr:postcode":"v4w 2y4",
    "addr:street":"25 Ave",
    "iso:country":"CA",
    "sg:address":"26830 25 Ave",
    "sg:city":"Aldergrove",
    "sg:classifiers":[
        {
            "category":"Education",
            "subcategory":"Vocational School",
            "type":"Public Place"
        }
    ],
    "sg:phone":"+1 604 857 1873",
    "sg:postcode":"V4W 2Y4",
    "sg:province":"BC",
    "sg:tags":[
        "technical",
        "trade"
    ],
    "wof:name":"Hi-Tek Training",
    "wof:placetype":"venue"
},
  "geometry": {"coordinates":[-122.480644,49.047485],"type":"Point"}
}