{
  "type": "Feature",
  "properties": {
    "iso:country":"CA",
    "sg:city":"Lac LA Biche",
    "sg:classifiers":[
        {
            "category":"Government",
            "subcategory":"Office",
            "type":"Public Place"
        }
    ],
    "sg:phone":"+1 780 623 5247",
    "sg:postcode":"T0A 2C0",
    "sg:province":"AB",
    "wof:name":"Albert Fish & Wildlife Dept",
    "wof:placetype":"venue"
},
  "geometry": {"coordinates":[-111.974457,54.771107],"type":"Point"}
}