{
  "type": "Feature",
  "properties": {
    "addr:full":"Troy ON L0R 2B0",
    "addr:postcode":"l0r 2b0",
    "iso:country":"CA",
    "sg:city":"Troy",
    "sg:classifiers":[
        {
            "category":"Wholesale",
            "subcategory":"Machinery & Supplies",
            "type":"Manufacturing & Wholesale Goods"
        }
    ],
    "sg:phone":"+1 905 628 2873",
    "sg:postcode":"L0R 2B0",
    "sg:province":"ON",
    "wof:name":"Cvs Industries Inc",
    "wof:placetype":"venue"
},
  "geometry": {"coordinates":[-80.1836471558,43.2612953186],"type":"Point"}
}