{
  "type": "Feature",
  "properties": {
    "iso:country":"CA",
    "sg:address":"40 Taggart St",
    "sg:city":"Guelph",
    "sg:classifiers":[
        {
            "category":"Building & Trades",
            "subcategory":"Construction",
            "type":"Services"
        }
    ],
    "sg:phone":"+1 519 837 2506",
    "sg:postcode":"N1L 1M5",
    "sg:province":"ON",
    "sg:tags":[
        "paving",
        "contractor"
    ],
    "wof:name":"Northern Paving Ltd",
    "wof:placetype":"venue"
},
  "geometry": {"coordinates":[-80.20520019529999,43.5615081787],"type":"Point"}
}