{
  "type": "Feature",
  "properties": {
    "addr:full":"Edmonton AB T6B 0A7",
    "addr:postcode":"t6b 0a7",
    "iso:country":"CA",
    "sg:city":"Edmonton",
    "sg:classifiers":[
        {
            "category":"Manufacturing",
            "subcategory":"Tools & Machinery",
            "type":"Manufacturing & Wholesale Goods"
        }
    ],
    "sg:phone":"+1 780 466 2121",
    "sg:postcode":"T6B 0A7",
    "sg:province":"AB",
    "sg:tags":[
        "machine"
    ],
    "wof:name":"Apl Machine Tool Ltd",
    "wof:placetype":"venue"
},
  "geometry": {"coordinates":[-113.426277161,53.512298584],"type":"Point"}
}