{
  "type": "Feature",
  "properties": {
    "addr:full":"284 Partridge Hollow Rd Consecon ON K0K 1T0",
    "addr:housenumber":"284",
    "addr:postcode":"k0k 1t0",
    "addr:street":"Partridge Hollow Rd",
    "iso:country":"CA",
    "sg:address":"284 Partridge Hollow Rd",
    "sg:city":"Consecon",
    "sg:classifiers":[
        {
            "category":"Shopping",
            "subcategory":"Crafts & Fabrics",
            "type":"Retail Goods"
        }
    ],
    "sg:phone":"+1 613 392 4131",
    "sg:postcode":"K0K 1T0",
    "sg:province":"ON",
    "sg:tags":[
        "yarn"
    ],
    "wof:name":"Mission Falls",
    "wof:placetype":"venue"
},
  "geometry": {"coordinates":[-77.5215,43.991421],"type":"Point"}
}