{
  "type": "Feature",
  "properties": {
    "addr:full":"2237 Royal Windsor Dr Oakville ON L6J 7X8",
    "addr:housenumber":"2237",
    "addr:postcode":"l6j 7x8",
    "addr:street":"Royal Windsor Dr",
    "iso:country":"CA",
    "sg:address":"2237 Royal Windsor Dr",
    "sg:city":"Oakville",
    "sg:classifiers":[
        {
            "category":"Retail",
            "subcategory":"Auto Repair",
            "type":"Services"
        }
    ],
    "sg:phone":"+1 905 844 8416",
    "sg:postcode":"L6J 7X8",
    "sg:province":"ON",
    "sg:tags":[
        "body",
        "automobile",
        "painting"
    ],
    "wof:name":"Two Brothers Auto Body",
    "wof:placetype":"venue"
},
  "geometry": {"coordinates":[-79.6541519165,43.4887695312],"type":"Point"}
}