{
  "type": "Feature",
  "properties": {
    "addr:full":"216 Main St Melfort SK S0E 1A0",
    "addr:housenumber":"216",
    "addr:postcode":"s0e 1a0",
    "addr:street":"Main St",
    "iso:country":"CA",
    "sg:address":"216 Main St",
    "sg:city":"Melfort",
    "sg:classifiers":[
        {
            "category":"Insurance",
            "subcategory":"Insurance Agent",
            "type":"Services"
        }
    ],
    "sg:phone":"+1 306 752 2794",
    "sg:postcode":"S0E 1A0",
    "sg:province":"SK",
    "wof:name":"Melfort Agencies Ltd",
    "wof:placetype":"venue"
},
  "geometry": {"coordinates":[-104.610336,52.860664],"type":"Point"}
}