{
  "type": "Feature",
  "properties": {
    "iso:country":"CA",
    "sg:city":"Scarborough",
    "sg:classifiers":[
        {
            "category":"Professional",
            "subcategory":"Accounting & Tax Preparation",
            "type":"Services"
        }
    ],
    "sg:phone":"+1 416 609 0890",
    "sg:postcode":"M1V 5E6",
    "sg:province":"ON",
    "sg:tags":[
        "accountant"
    ],
    "wof:name":"Anthony Yim & CO",
    "wof:placetype":"venue"
},
  "geometry": {"coordinates":[-79.2890930176,43.8072967529],"type":"Point"}
}