{
  "type": "Feature",
  "properties": {
    "addr:full":"506 Av Saint-Alphonse Saint-Bruno-Lac-Saint-Jean QC G0W 2L0",
    "addr:postcode":"g0w 2l0",
    "addr:street":"506 Av Saint-Alphonse Saint-Bruno-Lac-Saint-Jean",
    "iso:country":"CA",
    "sg:address":"506 Av Saint-Alphonse",
    "sg:city":"Saint-Bruno-Lac-Saint-Jean",
    "sg:classifiers":[
        {
            "category":"Health Services",
            "subcategory":"Doctor",
            "type":"Services"
        }
    ],
    "sg:phone":"+1 418 343 2191",
    "sg:postcode":"G0W 2L0",
    "sg:province":"QC",
    "sg:tags":[
        "dentist"
    ],
    "wof:name":"Clinique Dentaire Duranleau",
    "wof:placetype":"venue"
},
  "geometry": {"coordinates":[-71.65451,48.470036],"type":"Point"}
}