{
  "type": "Feature",
  "properties": {
    "iso:country":"CA",
    "sg:address":"1054 Rue Thibault",
    "sg:city":"Ascot",
    "sg:classifiers":[
        {
            "category":"Building & Trades",
            "subcategory":"Cleaning & Sanitation",
            "type":"Services"
        }
    ],
    "sg:phone":"+1 819 346 6656",
    "sg:postcode":"J1H 5X5",
    "sg:province":"QC",
    "sg:tags":[
        "removal",
        "snow",
        "topsoil"
    ],
    "wof:name":"Robert Lessard Inc",
    "wof:placetype":"venue"
},
  "geometry": {"coordinates":[-71.907684,45.37674],"type":"Point"}
}