{
  "type": "Feature",
  "properties": {
    "addr:full":"130 Rosewell Ave Toronto ON M4R 2A4",
    "addr:housenumber":"130",
    "addr:postcode":"m4r 2a4",
    "addr:street":"Rosewell Ave",
    "iso:country":"CA",
    "sg:address":"130 Rosewell Ave",
    "sg:city":"Toronto",
    "sg:classifiers":[
        {
            "category":"Communications",
            "subcategory":"Film & Video Production",
            "type":"Services"
        }
    ],
    "sg:phone":"+1 416 484 1947",
    "sg:postcode":"M4R 2A4",
    "sg:province":"ON",
    "sg:tags":[
        "television",
        "producer"
    ],
    "wof:name":"Remerowski Productions Ltd",
    "wof:placetype":"venue"
},
  "geometry": {"coordinates":[-79.4063491821,43.7131271362],"type":"Point"}
}