{
  "type": "Feature",
  "properties": {
    "addr:full":"Coquitlam BC V3K 4S8",
    "addr:postcode":"v3k 4s8",
    "iso:country":"CA",
    "sg:city":"Coquitlam",
    "sg:classifiers":[
        {
            "category":"Shopping",
            "subcategory":"Shoes",
            "type":"Retail Goods"
        }
    ],
    "sg:phone":"+1 604 515 9922",
    "sg:postcode":"V3K 4S8",
    "sg:province":"BC",
    "wof:name":"Shoe Warehouse",
    "wof:placetype":"venue"
},
  "geometry": {"coordinates":[-122.861251831,49.2311019897],"type":"Point"}
}