{
  "type": "Feature",
  "properties": {
    "addr:full":"Woodstock ON N4S 3A5",
    "addr:postcode":"n4s 3a5",
    "iso:country":"CA",
    "sg:city":"Woodstock",
    "sg:classifiers":[
        {
            "category":"Retail",
            "subcategory":"Repair Shop",
            "type":"Services"
        }
    ],
    "sg:phone":"+1 519 537 5051",
    "sg:postcode":"N4S 3A5",
    "sg:province":"ON",
    "sg:tags":[
        "tool",
        "grinding"
    ],
    "wof:name":"Gildsmen Equipment",
    "wof:placetype":"venue"
},
  "geometry": {"coordinates":[-80.7603,43.125153],"type":"Point"}
}