{
  "type": "Feature",
  "properties": {
    "addr:full":"21 Royal Rd S Portage LA Prairie MB R1N 1T8",
    "addr:housenumber":"21",
    "addr:postcode":"r1n 1t8",
    "addr:street":"Royal Rd S",
    "iso:country":"CA",
    "sg:address":"21 Royal Rd S",
    "sg:city":"Portage LA Prairie",
    "sg:classifiers":[
        {
            "category":"Social Services",
            "type":"Services"
        }
    ],
    "sg:phone":"+1 204 239 4898",
    "sg:postcode":"R1N 1T8",
    "sg:province":"MB",
    "sg:tags":[
        "organization",
        "welfare"
    ],
    "wof:name":"Alzheimer Society of Manitoba",
    "wof:placetype":"venue"
},
  "geometry": {"coordinates":[-98.2902755737,49.9718170166],"type":"Point"}
}