{
  "type": "Feature",
  "properties": {
    "addr:full":"932 Ward St Bridgenorth ON K0L 1H0",
    "addr:housenumber":"932",
    "addr:postcode":"k0l 1h0",
    "addr:street":"Ward St",
    "iso:country":"CA",
    "sg:address":"932 Ward St",
    "sg:city":"Bridgenorth",
    "sg:classifiers":[
        {
            "category":"Health Services",
            "subcategory":"Chiropractor",
            "type":"Services"
        }
    ],
    "sg:phone":"+1 705 292 7869",
    "sg:postcode":"K0L 1H0",
    "sg:province":"ON",
    "wof:name":"Bridgenorth Chiropractic",
    "wof:placetype":"venue"
},
  "geometry": {"coordinates":[-78.38298034669999,44.3871192932],"type":"Point"}
}