{
  "type": "Feature",
  "properties": {
    "addr:full":"Eganville ON K0J 1T0",
    "addr:postcode":"k0j 1t0",
    "iso:country":"CA",
    "sg:city":"Eganville",
    "sg:classifiers":[
        {
            "category":"Restaurant",
            "type":"Food & Drink"
        }
    ],
    "sg:phone":"+1 613 628 1627",
    "sg:postcode":"K0J 1T0",
    "sg:province":"ON",
    "sg:tags":[
        "bars"
    ],
    "wof:name":"Sloopy Joe's Intl Meeting Pl",
    "wof:placetype":"venue"
},
  "geometry": {"coordinates":[-77.10082199999999,45.541],"type":"Point"}
}