{
  "type": "Feature",
  "properties": {
    "addr:full":"43 Rue Guenette Levis QC G6V 5M9",
    "addr:housenumber":"43",
    "addr:postcode":"g6v 5m9",
    "addr:street":"Rue Guenette",
    "iso:country":"CA",
    "sg:address":"43 Rue Guenette",
    "sg:city":"Levis",
    "sg:classifiers":[
        {
            "category":"Health Services",
            "subcategory":"Nursing And Care Facility",
            "type":"Services"
        }
    ],
    "sg:phone":"+1 418 837 2613",
    "sg:postcode":"G6V 5M9",
    "sg:province":"QC",
    "sg:tags":[
        "home",
        "retirement",
        "community"
    ],
    "wof:name":"Residence Le Bel Age/La Rive",
    "wof:placetype":"venue"
},
  "geometry": {"coordinates":[-71.180069,46.808681],"type":"Point"}
}