{
  "type": "Feature",
  "properties": {
    "iso:country":"CA",
    "sg:city":"Notre-Dame-Des-Bois",
    "sg:classifiers":[
        {
            "category":"Travel",
            "subcategory":"Hotels & Motels",
            "type":"Entertainment"
        }
    ],
    "sg:phone":"+1 819 888 2809",
    "sg:postcode":"J0B 2E0",
    "sg:province":"QC",
    "wof:name":"Au Vieux Manoir Mont Megantic",
    "wof:placetype":"venue"
},
  "geometry": {"coordinates":[-71.05871582029999,45.3871650696],"type":"Point"}
}