{
  "type": "Feature",
  "properties": {
    "addr:full":"309 Scotia St Schreiber ON P0T 2S0",
    "addr:housenumber":"309",
    "addr:postcode":"p0t 2s0",
    "addr:street":"Scotia St",
    "iso:country":"CA",
    "sg:address":"309 Scotia St",
    "sg:city":"Schreiber",
    "sg:classifiers":[
        {
            "category":"Personal",
            "subcategory":"Beauty Salon",
            "type":"Services"
        }
    ],
    "sg:phone":"+1 807 824 3399",
    "sg:postcode":"P0T 2S0",
    "sg:province":"ON",
    "wof:name":"Superior Hairstyling",
    "wof:placetype":"venue"
},
  "geometry": {"coordinates":[-87.26747899999999,48.808014],"type":"Point"}
}