{
  "type": "Feature",
  "properties": {
    "addr:full":"900 Boul Saint-Joseph Drummondville QC J2C 2C5",
    "addr:housenumber":"900",
    "addr:postcode":"j2c 2c5",
    "addr:street":"Boul Saint-Joseph",
    "iso:country":"CA",
    "sg:address":"900 Boul Saint-Joseph",
    "sg:city":"Drummondville",
    "sg:classifiers":[
        {
            "category":"Building & Trades",
            "subcategory":"Plumbing",
            "type":"Services"
        }
    ],
    "sg:phone":"+1 819 474 7667",
    "sg:postcode":"J2C 2C5",
    "sg:province":"QC",
    "sg:tags":[
        "conditioning",
        "air",
        "system",
        "contractor"
    ],
    "wof:name":"Services Thermosun Inc",
    "wof:placetype":"venue"
},
  "geometry": {"coordinates":[-72.50876617430001,45.8900718689],"type":"Point"}
}