{
  "type": "Feature",
  "properties": {
    "addr:full":"985 Elgin St W Cobourg ON K9A 5J3",
    "addr:housenumber":"985",
    "addr:postcode":"k9a 5j3",
    "addr:street":"Elgin St W",
    "iso:country":"CA",
    "sg:address":"985 Elgin St W",
    "sg:city":"Cobourg",
    "sg:classifiers":[
        {
            "category":"Restaurant",
            "type":"Food & Drink"
        }
    ],
    "sg:phone":"+1 905 372 7077",
    "sg:postcode":"K9A 5J3",
    "sg:province":"ON",
    "wof:name":"Burger King",
    "wof:placetype":"venue"
},
  "geometry": {"coordinates":[-78.19652600000001,43.971844],"type":"Point"}
}