{
  "type": "Feature",
  "properties": {
    "addr:full":"427 Willow Ave New Glasgow NS B2H 2A1",
    "addr:housenumber":"427",
    "addr:postcode":"b2h 2a1",
    "addr:street":"Willow Ave",
    "iso:country":"CA",
    "sg:address":"427 Willow Ave",
    "sg:city":"New Glasgow",
    "sg:classifiers":[
        {
            "category":"Building & Trades",
            "subcategory":"Electrical",
            "type":"Services"
        }
    ],
    "sg:phone":"+1 902 752 8405",
    "sg:postcode":"B2H 2A1",
    "sg:province":"NS",
    "sg:tags":[
        "electric",
        "contractor"
    ],
    "wof:name":"Russell Electric",
    "wof:placetype":"venue"
},
  "geometry": {"coordinates":[-62.6622924805,45.5902023315],"type":"Point"}
}