{
  "type": "Feature",
  "properties": {
    "iso:country":"CA",
    "sg:address":"1409 Malibou Terr",
    "sg:city":"Mississauga",
    "sg:classifiers":[
        {
            "category":"Communications",
            "subcategory":"Film & Video Production",
            "type":"Services"
        }
    ],
    "sg:phone":"+1 905 855 1510",
    "sg:postcode":"L5J 4B9",
    "sg:province":"ON",
    "sg:tags":[
        "motion",
        "picture",
        "studio",
        "producer"
    ],
    "wof:name":"Goldi Productions Ltd",
    "wof:placetype":"venue"
},
  "geometry": {"coordinates":[-79.612121582,43.5217590332],"type":"Point"}
}