{
  "type": "Feature",
  "properties": {
    "addr:full":"1604 2 Ave S Lethbridge AB T1J 0G2",
    "addr:housenumber":"1604",
    "addr:postcode":"t1j 0g2",
    "addr:street":"2 Ave S",
    "iso:country":"CA",
    "sg:address":"1604 2 Ave S",
    "sg:city":"Lethbridge",
    "sg:classifiers":[
        {
            "category":"Autos & Motor Vehicles",
            "subcategory":"Fuel & Gas Station",
            "type":"Retail Goods"
        }
    ],
    "sg:phone":"+1 403 320 2142",
    "sg:postcode":"T1J 0G2",
    "sg:province":"AB",
    "sg:tags":[
        "oil"
    ],
    "wof:name":"Gas King Oil CO Ltd",
    "wof:placetype":"venue"
},
  "geometry": {"coordinates":[-112.81912199999999,49.697338],"type":"Point"}
}