{
  "type": "Feature",
  "properties": {
    "addr:full":"Clyde AB T0G 0P0",
    "addr:postcode":"t0g 0p0",
    "iso:country":"CA",
    "sg:city":"Clyde",
    "sg:classifiers":[
        {
            "category":"Wholesale",
            "subcategory":"Construction Materials",
            "type":"Manufacturing & Wholesale Goods"
        }
    ],
    "sg:phone":"+1 780 348 5252",
    "sg:postcode":"T0G 0P0",
    "sg:province":"AB",
    "sg:tags":[
        "sand",
        "gravel"
    ],
    "wof:name":"Westlock Sand & Gravel",
    "wof:placetype":"venue"
},
  "geometry": {"coordinates":[-113.635498,54.145676],"type":"Point"}
}