{
  "type": "Feature",
  "properties": {
    "addr:full":"917 Glasgow St Saskatoon SK S7J 0N9",
    "addr:housenumber":"917",
    "addr:postcode":"s7j 0n9",
    "addr:street":"Glasgow St",
    "iso:country":"CA",
    "sg:address":"917 Glasgow St",
    "sg:city":"Saskatoon",
    "sg:classifiers":[
        {
            "category":"Professional",
            "subcategory":"Engineering",
            "type":"Services"
        }
    ],
    "sg:phone":"+1 306 934 1481",
    "sg:postcode":"S7J 0N9",
    "sg:province":"SK",
    "sg:tags":[
        "engineer"
    ],
    "wof:name":"Dobchuck Engineering",
    "wof:placetype":"venue"
},
  "geometry": {"coordinates":[-106.6483078,52.0931167603],"type":"Point"}
}