{
  "type": "Feature",
  "properties": {
    "addr:full":"11908 132 Ave NW Edmonton AB T5E 1A9",
    "addr:housenumber":"11908",
    "addr:postcode":"t5e 1a9",
    "addr:street":"132 Ave Nw",
    "iso:country":"CA",
    "sg:address":"11908 132 Ave NW",
    "sg:city":"Edmonton",
    "sg:classifiers":[
        {
            "category":"Organizations",
            "subcategory":"Religious Organization",
            "type":"Services"
        }
    ],
    "sg:phone":"+1 780 454 1347",
    "sg:postcode":"T5E 1A9",
    "sg:province":"AB",
    "sg:tags":[
        "church"
    ],
    "wof:name":"Zion Baptist Church-Kensington",
    "wof:placetype":"venue"
},
  "geometry": {"coordinates":[-113.52724499999999,53.592407],"type":"Point"}
}