{
  "type": "Feature",
  "properties": {
    "addr:full":"55 Lawson Crt Fredericton NB E3A 5G3",
    "addr:housenumber":"55",
    "addr:postcode":"e3a 5g3",
    "addr:street":"Lawson Crt",
    "iso:country":"CA",
    "sg:address":"55 Lawson Crt",
    "sg:city":"Fredericton",
    "sg:classifiers":[
        {
            "category":"Building & Trades",
            "subcategory":"Construction",
            "type":"Services"
        }
    ],
    "sg:phone":"+1 506 472 3490",
    "sg:postcode":"E3A 5G3",
    "sg:province":"NB",
    "sg:tags":[
        "contractor"
    ],
    "wof:name":"Flinn Construction Ltd",
    "wof:placetype":"venue"
},
  "geometry": {"coordinates":[-66.6135635376,45.9666099548],"type":"Point"}
}