{
  "type": "Feature",
  "properties": {
    "iso:country":"CA",
    "sg:address":"333 Wilson Ave # 300",
    "sg:city":"North York",
    "sg:classifiers":[
        {
            "category":"Social Services",
            "subcategory":"Child Care",
            "type":"Services"
        }
    ],
    "sg:phone":"+1 416 636 3000",
    "sg:postcode":"M3H 1T2",
    "sg:province":"ON",
    "sg:tags":[
        "kindergarten",
        "academic",
        "school"
    ],
    "wof:name":"Kinder Connection",
    "wof:placetype":"venue"
},
  "geometry": {"coordinates":[-79.4360580444,43.736831665],"type":"Point"}
}