{
  "type": "Feature",
  "properties": {
    "addr:full":"900 Stanton Ave Coquitlam BC V3J 4V2",
    "addr:housenumber":"900",
    "addr:postcode":"v3j 4v2",
    "addr:street":"Stanton Ave",
    "iso:country":"CA",
    "sg:address":"900 Stanton Ave",
    "sg:city":"Coquitlam",
    "sg:classifiers":[
        {
            "category":"Professional",
            "subcategory":"Management & Consulting",
            "type":"Services"
        }
    ],
    "sg:phone":"+1 604 230 5494",
    "sg:postcode":"V3J 4V2",
    "sg:province":"BC",
    "sg:tags":[
        "consultant",
        "elevator"
    ],
    "wof:name":"Equity Elevator Svc Consulting",
    "wof:placetype":"venue"
},
  "geometry": {"coordinates":[-122.871231079,49.2644615173],"type":"Point"}
}