{
  "type": "Feature",
  "properties": {
    "addr:full":"201 Ch Du Lac Varennes QC J3X 1P7",
    "addr:housenumber":"201",
    "addr:postcode":"j3x 1p7",
    "addr:street":"Ch Du Lac",
    "iso:country":"CA",
    "sg:address":"201 Ch Du Lac",
    "sg:city":"Varennes",
    "sg:classifiers":[
        {
            "category":"Manufacturing",
            "subcategory":"Metals",
            "type":"Manufacturing & Wholesale Goods"
        }
    ],
    "sg:phone":"+1 450 929 3999",
    "sg:postcode":"J3X 1P7",
    "sg:province":"QC",
    "sg:tags":[
        "ironwork"
    ],
    "wof:name":"Mometal Inc",
    "wof:placetype":"venue"
},
  "geometry": {"coordinates":[-73.3867111206,45.6338500977],"type":"Point"}
}