{
  "type": "Feature",
  "properties": {
    "addr:full":"5412 Av Du Parc Montreal QC H2V 4G7",
    "addr:housenumber":"5412",
    "addr:postcode":"h2v 4g7",
    "addr:street":"Av Du Parc",
    "iso:country":"CA",
    "sg:address":"5412 Av Du Parc",
    "sg:city":"Montreal",
    "sg:classifiers":[
        {
            "category":"Food & Beverages",
            "subcategory":"Specialty",
            "type":"Retail Goods"
        }
    ],
    "sg:phone":"+1 514 277 3434",
    "sg:postcode":"H2V 4G7",
    "sg:province":"QC",
    "wof:name":"P'Tit Bonheur Au Naturel",
    "wof:placetype":"venue"
},
  "geometry": {"coordinates":[-73.60084533689999,45.5214500427],"type":"Point"}
}