{
  "type": "Feature",
  "properties": {
    "addr:full":"4269 Saunders Ave Wells BC V0K 2R0",
    "addr:housenumber":"4269",
    "addr:postcode":"v0k 2r0",
    "addr:street":"Saunders Ave",
    "iso:country":"CA",
    "sg:address":"4269 Saunders Ave",
    "sg:city":"Wells",
    "sg:classifiers":[
        {
            "category":"Education",
            "subcategory":"Library",
            "type":"Public Place"
        }
    ],
    "sg:phone":"+1 250 994 3424",
    "sg:postcode":"V0K 2R0",
    "sg:province":"BC",
    "wof:name":"Wells Library",
    "wof:placetype":"venue"
},
  "geometry": {"coordinates":[-121.572441,53.104889],"type":"Point"}
}