{
  "type": "Feature",
  "properties": {
    "addr:full":"130 Queen St Longlac ON P0T 2A0",
    "addr:housenumber":"130",
    "addr:postcode":"p0t 2a0",
    "addr:street":"Queen St",
    "iso:country":"CA",
    "sg:address":"130 Queen St",
    "sg:city":"Longlac",
    "sg:classifiers":[
        {
            "category":"Professional",
            "subcategory":"Business Services",
            "type":"Services"
        }
    ],
    "sg:phone":"+1 807 876 2264",
    "sg:postcode":"P0T 2A0",
    "sg:province":"ON",
    "sg:tags":[
        "reservation",
        "motel",
        "hotel"
    ],
    "wof:name":"Woodlands Inn Motor Hotel",
    "wof:placetype":"venue"
},
  "geometry": {"coordinates":[-86.53620147709999,49.7823181152],"type":"Point"}
}