{
  "type": "Feature",
  "properties": {
    "addr:full":"Salmon Arm BC V1E 1S9",
    "addr:postcode":"v1e 1s9",
    "iso:country":"CA",
    "sg:city":"Salmon Arm",
    "sg:classifiers":[
        {
            "category":"Home & Garden",
            "subcategory":"Building Materials",
            "type":"Retail Goods"
        }
    ],
    "sg:phone":"+1 250 832 7068",
    "sg:postcode":"V1E 1S9",
    "sg:province":"BC",
    "sg:tags":[
        "glass",
        "window",
        "plate"
    ],
    "wof:name":"Crystal Glass Canada Ltd",
    "wof:placetype":"venue"
},
  "geometry": {"coordinates":[-119.29332700000001,50.697372],"type":"Point"}
}