{
  "type": "Feature",
  "properties": {
    "addr:full":"1380 London Rd Sarnia ON N7S 1P8",
    "addr:housenumber":"1380",
    "addr:postcode":"n7s 1p8",
    "addr:street":"London Rd",
    "iso:country":"CA",
    "sg:address":"1380 London Rd",
    "sg:city":"Sarnia",
    "sg:classifiers":[
        {
            "category":"Shopping",
            "subcategory":"Shoes",
            "type":"Retail Goods"
        }
    ],
    "sg:phone":"+1 519 542 9716",
    "sg:postcode":"N7S 1P8",
    "sg:province":"ON",
    "wof:name":"Payless Shoe Source",
    "wof:placetype":"venue"
},
  "geometry": {"coordinates":[-82.3530502319,42.9804458618],"type":"Point"}
}