{
  "type": "Feature",
  "properties": {
    "addr:full":"5421 Slaters Rd Gormley ON L0H 1G0",
    "addr:housenumber":"5421",
    "addr:postcode":"l0h 1g0",
    "addr:street":"Slaters Rd",
    "iso:country":"CA",
    "sg:address":"5421 Slaters Rd",
    "sg:city":"Gormley",
    "sg:classifiers":[
        {
            "category":"Retail",
            "subcategory":"Animal Services",
            "type":"Services"
        }
    ],
    "sg:phone":"+1 905 713 2779",
    "sg:postcode":"L0H 1G0",
    "sg:province":"ON",
    "sg:tags":[
        "pet",
        "boarding",
        "grooming",
        "washing",
        "sitting"
    ],
    "wof:name":"Country Estate Kennels",
    "wof:placetype":"venue"
},
  "geometry": {"coordinates":[-79.3790054321,43.9433898926],"type":"Point"}
}