{
  "type": "Feature",
  "properties": {
    "iso:country":"CA",
    "sg:city":"Ottawa",
    "sg:classifiers":[
        {
            "category":"Professional",
            "subcategory":"Management & Consulting",
            "type":"Services"
        }
    ],
    "sg:phone":"+1 613 234 3559",
    "sg:postcode":"K2P 2G3",
    "sg:province":"ON",
    "sg:tags":[
        "patent",
        "consultant",
        "trademark",
        "agent"
    ],
    "wof:name":"Mac Rae & CO",
    "wof:placetype":"venue"
},
  "geometry": {"coordinates":[-75.691551,45.417217],"type":"Point"}
}