{
  "type": "Feature",
  "properties": {
    "addr:full":"107 Erb St W Waterloo ON N2L 1T4",
    "addr:housenumber":"107",
    "addr:postcode":"n2l 1t4",
    "addr:street":"Erb St W",
    "iso:country":"CA",
    "sg:address":"107 Erb St W",
    "sg:city":"Waterloo",
    "sg:classifiers":[
        {
            "category":"Health Services",
            "subcategory":"Optometrist",
            "type":"Services"
        }
    ],
    "sg:phone":"+1 519 886 4170",
    "sg:postcode":"N2L 1T4",
    "sg:province":"ON",
    "wof:name":"Ellison, Patricia OD",
    "wof:placetype":"venue"
},
  "geometry": {"coordinates":[-80.528442,43.462837],"type":"Point"}
}