{
  "type": "Feature",
  "properties": {
    "addr:full":"Montreal QC H2W 1Z8",
    "addr:postcode":"h2w 1z8",
    "iso:country":"CA",
    "sg:city":"Montreal",
    "sg:classifiers":[
        {
            "category":"Professional",
            "subcategory":"Art Services",
            "type":"Services"
        }
    ],
    "sg:phone":"+1 514 285 1356",
    "sg:postcode":"H2W 1Z8",
    "sg:province":"QC",
    "sg:tags":[
        "graphic",
        "designer"
    ],
    "wof:name":"Contractuelle Comms-Conseils",
    "wof:placetype":"venue"
},
  "geometry": {"coordinates":[-73.58569300000001,45.519974],"type":"Point"}
}