{
  "type": "Feature",
  "properties": {
    "iso:country":"CA",
    "sg:address":"153 Langstaff Rd E",
    "sg:city":"Thornhill",
    "sg:classifiers":[
        {
            "category":"Building & Trades",
            "subcategory":"Construction",
            "type":"Services"
        }
    ],
    "sg:phone":"+1 905 763 8119",
    "sg:postcode":"L3T 3M6",
    "sg:province":"ON",
    "sg:tags":[
        "contractor",
        "general"
    ],
    "wof:name":"Platinum Construction Corp",
    "wof:placetype":"venue"
},
  "geometry": {"coordinates":[-79.4150390625,43.837436676],"type":"Point"}
}