{
  "type": "Feature",
  "properties": {
    "addr:full":"Calgary AB T2E 7E1",
    "addr:postcode":"t2e 7e1",
    "iso:country":"CA",
    "sg:city":"Calgary",
    "sg:classifiers":[
        {
            "category":"Manufacturing",
            "subcategory":"Tools & Machinery",
            "type":"Manufacturing & Wholesale Goods"
        }
    ],
    "sg:phone":"+1 403 291 5143",
    "sg:postcode":"T2E 7E1",
    "sg:province":"AB",
    "sg:tags":[
        "motion",
        "picture",
        "audio"
    ],
    "wof:name":"Applied Electronics Ltd",
    "wof:placetype":"venue"
},
  "geometry": {"coordinates":[-114.016464,51.076767],"type":"Point"}
}