{
  "type": "Feature",
  "properties": {
    "addr:full":"5050 Dufferin St North York ON M3H 5T5",
    "addr:housenumber":"5050",
    "addr:postcode":"m3h 5t5",
    "addr:street":"Dufferin St",
    "iso:country":"CA",
    "sg:address":"5050 Dufferin St",
    "sg:city":"North York",
    "sg:classifiers":[
        {
            "category":"Insurance",
            "subcategory":"Insurance Agent",
            "type":"Services"
        }
    ],
    "sg:phone":"+1 416 661 9155",
    "sg:postcode":"M3H 5T5",
    "sg:province":"ON",
    "wof:name":"Leading Edge Insurance Svc",
    "wof:placetype":"venue"
},
  "geometry": {"coordinates":[-79.470161,43.781483],"type":"Point"}
}