{
  "type": "Feature",
  "properties": {
    "addr:full":"112 Front St Wolfville NS B4P 1A4",
    "addr:housenumber":"112",
    "addr:postcode":"b4p 1a4",
    "addr:street":"Front St",
    "iso:country":"CA",
    "sg:address":"112 Front St",
    "sg:city":"Wolfville",
    "sg:classifiers":[
        {
            "category":"Health Services",
            "subcategory":"Health Practitioner",
            "type":"Services"
        }
    ],
    "sg:phone":"+1 902 542 4600",
    "sg:postcode":"B4P 1A4",
    "sg:province":"NS",
    "sg:tags":[
        "psychotherapist",
        "counselor",
        "marriage",
        "family"
    ],
    "wof:name":"Kerr, Gail",
    "wof:placetype":"venue"
},
  "geometry": {"coordinates":[-64.3632965088,45.0920791626],"type":"Point"}
}