{
  "type": "Feature",
  "properties": {
    "addr:full":"1896 Guthrie Rd Comox BC V9M 3X7",
    "addr:housenumber":"1896",
    "addr:postcode":"v9m 3x7",
    "addr:street":"Guthrie Rd",
    "iso:country":"CA",
    "sg:address":"1896 Guthrie Rd",
    "sg:city":"Comox",
    "sg:classifiers":[
        {
            "category":"Retail",
            "subcategory":"Veterinary Services",
            "type":"Services"
        }
    ],
    "sg:phone":"+1 250 339 2026",
    "sg:postcode":"V9M 3X7",
    "sg:province":"BC",
    "sg:tags":[
        "veterinarian"
    ],
    "wof:name":"Vanden Bosch, S DVM",
    "wof:placetype":"venue"
},
  "geometry": {"coordinates":[-124.932091,49.68824],"type":"Point"}
}