{
  "type": "Feature",
  "properties": {
    "addr:full":"Joliette QC J6E 4Y7",
    "addr:postcode":"j6e 4y7",
    "iso:country":"CA",
    "sg:city":"Joliette",
    "sg:classifiers":[
        {
            "category":"Health Services",
            "subcategory":"Medical Lab",
            "type":"Services"
        }
    ],
    "sg:phone":"+1 450 759 0394",
    "sg:postcode":"J6E 4Y7",
    "sg:province":"QC",
    "wof:name":"Rocheleau, Ronald",
    "wof:placetype":"venue"
},
  "geometry": {"coordinates":[-73.43898799999999,46.025925],"type":"Point"}
}