{
  "type": "Feature",
  "properties": {
    "iso:country":"CA",
    "sg:address":"6 Edenbrook Crt",
    "sg:city":"Nepean",
    "sg:classifiers":[
        {
            "category":"Building & Trades",
            "subcategory":"Construction",
            "type":"Services"
        }
    ],
    "sg:phone":"+1 613 225 1558",
    "sg:postcode":"K2E 7H4",
    "sg:province":"ON",
    "sg:tags":[
        "roofing",
        "contractor"
    ],
    "wof:name":"Metro Ottawa Roofing",
    "wof:placetype":"venue"
},
  "geometry": {"coordinates":[-75.70491027830001,45.3212623596],"type":"Point"}
}