{
  "type": "Feature",
  "properties": {
    "addr:full":"89 1st Ave NE Swift Current SK S9H 2A9",
    "addr:housenumber":"89",
    "addr:postcode":"s9h 2a9",
    "addr:street":"1St Ave Ne",
    "iso:country":"CA",
    "sg:address":"89 1st Ave NE",
    "sg:city":"Swift Current",
    "sg:classifiers":[
        {
            "category":"Professional",
            "subcategory":"Management & Consulting",
            "type":"Services"
        }
    ],
    "sg:phone":"+1 306 773 1501",
    "sg:postcode":"S9H 2A9",
    "sg:province":"SK",
    "sg:tags":[
        "project",
        "architect"
    ],
    "wof:name":"Eldred Architect",
    "wof:placetype":"venue"
},
  "geometry": {"coordinates":[-107.79838599999999,50.283203],"type":"Point"}
}