{
  "type": "Feature",
  "properties": {
    "iso:country":"CA",
    "sg:address":"4820 50th Ave",
    "sg:city":"Myrnam",
    "sg:classifiers":[
        {
            "category":"Food & Beverages",
            "subcategory":"Groceries & Convenience Stores",
            "type":"Retail Goods"
        }
    ],
    "sg:phone":"+1 780 366 3777",
    "sg:postcode":"T0B 3K0",
    "sg:province":"AB",
    "wof:name":"M & T Corner Food Stop",
    "wof:placetype":"venue"
},
  "geometry": {"coordinates":[-111.22769165,53.6612892151],"type":"Point"}
}