{
  "type": "Feature",
  "properties": {
    "addr:full":"47 Lewis Rd Guelph ON N1H 1E9",
    "addr:housenumber":"47",
    "addr:postcode":"n1h 1e9",
    "addr:street":"Lewis Rd",
    "iso:country":"CA",
    "sg:address":"47 Lewis Rd",
    "sg:city":"Guelph",
    "sg:classifiers":[
        {
            "category":"Professional",
            "subcategory":"Computer Services",
            "type":"Services"
        }
    ],
    "sg:phone":"+1 519 763 7756",
    "sg:postcode":"N1H 1E9",
    "sg:province":"ON",
    "sg:tags":[
        "equipment",
        "dealer",
        "consultant"
    ],
    "wof:name":"Synergenics",
    "wof:placetype":"venue"
},
  "geometry": {"coordinates":[-80.29341100000001,43.545448],"type":"Point"}
}