{
  "type": "Feature",
  "properties": {
    "addr:full":"177 St. Peters Rd Charlottetown PE C1A 5P6",
    "addr:housenumber":"177",
    "addr:postcode":"c1a 5p6",
    "addr:street":"St. Peters Rd",
    "iso:country":"CA",
    "sg:address":"177 St. Peters Rd",
    "sg:city":"Charlottetown",
    "sg:classifiers":[
        {
            "category":"Social Services",
            "subcategory":"Child Care",
            "type":"Services"
        }
    ],
    "sg:phone":"+1 902 566 5800",
    "sg:postcode":"C1A 5P6",
    "sg:province":"PE",
    "wof:name":"Sherwood Day Care & Kndrgrtn",
    "wof:placetype":"venue"
},
  "geometry": {"coordinates":[-63.11845,46.262089],"type":"Point"}
}