{
  "type": "Feature",
  "properties": {
    "addr:full":"956 Grieve Ave Courtenay BC V9N 2T9",
    "addr:housenumber":"956",
    "addr:postcode":"v9n 2t9",
    "addr:street":"Grieve Ave",
    "iso:country":"CA",
    "sg:address":"956 Grieve Ave",
    "sg:city":"Courtenay",
    "sg:classifiers":[
        {
            "category":"Organizations",
            "subcategory":"Professional Association",
            "type":"Services"
        }
    ],
    "sg:phone":"+1 250 334 2477",
    "sg:postcode":"V9N 2T9",
    "sg:province":"BC",
    "wof:name":"Comox Valley Abrgnl Head Start",
    "wof:placetype":"venue"
},
  "geometry": {"coordinates":[-125.000114,49.686699],"type":"Point"}
}