{
  "type": "Feature",
  "properties": {
    "iso:country":"CA",
    "sg:city":"Vancouver",
    "sg:classifiers":[
        {
            "category":"Building & Trades",
            "subcategory":"Construction",
            "type":"Services"
        }
    ],
    "sg:phone":"+1 604 801 5171",
    "sg:postcode":"V6A 1R9",
    "sg:province":"BC",
    "sg:tags":[
        "maker",
        "cabinet"
    ],
    "wof:name":"Quality Cabinets Mfg",
    "wof:placetype":"venue"
},
  "geometry": {"coordinates":[-123.08363342299999,49.2811813354],"type":"Point"}
}