{
  "type": "Feature",
  "properties": {
    "iso:country":"CA",
    "sg:address":"35 Campbell Ave",
    "sg:city":"Campbellville",
    "sg:classifiers":[
        {
            "category":"Shopping",
            "subcategory":"Gifts & Souvenirs",
            "type":"Retail Goods"
        }
    ],
    "sg:phone":"+1 905 854 0089",
    "sg:postcode":"L0P 1B0",
    "sg:province":"ON",
    "sg:tags":[
        "shop",
        "upholsterer"
    ],
    "wof:name":"Daphne's Place",
    "wof:placetype":"venue"
},
  "geometry": {"coordinates":[-79.9813613892,43.4879837036],"type":"Point"}
}