{
  "type": "Feature",
  "properties": {
    "addr:full":"960 Glenmore Dr Kelowna BC V1Y 4P1",
    "addr:housenumber":"960",
    "addr:postcode":"v1y 4p1",
    "addr:street":"Glenmore Dr",
    "iso:country":"CA",
    "sg:address":"960 Glenmore Dr",
    "sg:city":"Kelowna",
    "sg:classifiers":[
        {
            "category":"Education",
            "subcategory":"School",
            "type":"Public Place"
        }
    ],
    "sg:phone":"+1 250 762 3209",
    "sg:postcode":"V1Y 4P1",
    "sg:province":"BC",
    "wof:name":"Glenmore Elementary",
    "wof:placetype":"venue"
},
  "geometry": {"coordinates":[-119.454697,49.897236],"type":"Point"}
}