{
  "type": "Feature",
  "properties": {
    "addr:full":"91 George St S Brampton ON L6Y 1P4",
    "addr:housenumber":"91",
    "addr:postcode":"l6y 1p4",
    "addr:street":"George St S",
    "iso:country":"CA",
    "sg:address":"91 George St S",
    "sg:city":"Brampton",
    "sg:classifiers":[
        {
            "category":"Restaurant",
            "type":"Food & Drink"
        }
    ],
    "sg:phone":"+1 905 459 0511",
    "sg:postcode":"L6Y 1P4",
    "sg:province":"ON",
    "wof:name":"Vesuvio Ristorante",
    "wof:placetype":"venue"
},
  "geometry": {"coordinates":[-79.7594985962,43.6840324402],"type":"Point"}
}