{
  "type": "Feature",
  "properties": {
    "addr:full":"432 Queen St S Kitchener ON N2G 1W7",
    "addr:housenumber":"432",
    "addr:postcode":"n2g 1w7",
    "addr:street":"Queen St S",
    "iso:country":"CA",
    "sg:address":"432 Queen St S",
    "sg:city":"Kitchener",
    "sg:classifiers":[
        {
            "category":"Food & Beverages",
            "subcategory":"Groceries & Convenience Stores",
            "type":"Retail Goods"
        }
    ],
    "sg:phone":"+1 519 744 5932",
    "sg:postcode":"N2G 1W7",
    "sg:province":"ON",
    "wof:name":"Little Short Stop Stores Ltd",
    "wof:placetype":"venue"
},
  "geometry": {"coordinates":[-80.494156,43.445133],"type":"Point"}
}