{
  "type": "Feature",
  "properties": {
    "addr:full":"385 Main St Weaver NB E7G 2E9",
    "addr:housenumber":"385",
    "addr:postcode":"e7g 2e9",
    "addr:street":"Main St",
    "iso:country":"CA",
    "sg:address":"385 Main St",
    "sg:city":"Weaver",
    "sg:classifiers":[
        {
            "category":"Home & Garden",
            "subcategory":"Building Materials",
            "type":"Retail Goods"
        }
    ],
    "sg:phone":"+1 506 356 2778",
    "sg:postcode":"E7G 2E9",
    "sg:province":"NB",
    "sg:tags":[
        "lumber"
    ],
    "wof:name":"Tobique Valley Lumber Sales",
    "wof:placetype":"venue"
},
  "geometry": {"coordinates":[-67.4054641724,46.9320373535],"type":"Point"}
}