{
  "type": "Feature",
  "properties": {
    "iso:country":"CA",
    "sg:address":"5316 56 St",
    "sg:city":"Rocky Mountain House",
    "sg:classifiers":[
        {
            "category":"Professional",
            "subcategory":"Accounting & Tax Preparation",
            "type":"Services"
        }
    ],
    "sg:phone":"+1 403 845 3557",
    "sg:postcode":"T4T 1H4",
    "sg:province":"AB",
    "sg:tags":[
        "bookkeeping",
        "return",
        "filing",
        "general"
    ],
    "wof:name":"Jim Kelly Accounting Svc",
    "wof:placetype":"venue"
},
  "geometry": {"coordinates":[-114.928817749,52.3801841736],"type":"Point"}
}