{
  "type": "Feature",
  "properties": {
    "addr:full":"8301 Boul Newman Lasalle QC H8N 1Y4",
    "addr:housenumber":"8301",
    "addr:postcode":"h8n 1y4",
    "addr:street":"Boul Newman",
    "iso:country":"CA",
    "sg:address":"8301 Boul Newman",
    "sg:city":"Lasalle",
    "sg:classifiers":[
        {
            "category":"Autos & Motor Vehicles",
            "subcategory":"Fuel & Gas Station",
            "type":"Retail Goods"
        }
    ],
    "sg:phone":"+1 514 368 0462",
    "sg:postcode":"H8N 1Y4",
    "sg:province":"QC",
    "sg:tags":[
        "oil"
    ],
    "wof:name":"Petro-Canada",
    "wof:placetype":"venue"
},
  "geometry": {"coordinates":[-73.62911200000001,45.43335],"type":"Point"}
}