{
  "type": "Feature",
  "properties": {
    "addr:full":"22 Roseberry St Campbellton NB E3N 2G2",
    "addr:housenumber":"22",
    "addr:postcode":"e3n 2g2",
    "addr:street":"Roseberry St",
    "iso:country":"CA",
    "sg:address":"22 Roseberry St",
    "sg:city":"Campbellton",
    "sg:classifiers":[
        {
            "category":"Retail",
            "subcategory":"Auto Repair",
            "type":"Services"
        }
    ],
    "sg:phone":"+1 506 789 1609",
    "sg:postcode":"E3N 2G2",
    "sg:province":"NB",
    "sg:tags":[
        "repairing",
        "automobile"
    ],
    "wof:name":"Imports Auto Specialist",
    "wof:placetype":"venue"
},
  "geometry": {"coordinates":[-66.674492,48.004902],"type":"Point"}
}