{
  "type": "Feature",
  "properties": {
    "addr:full":"PO Box 1656 Valleyview AB T0H 3N0",
    "addr:housenumber":"po;1656",
    "addr:postcode":"ab t0h 3n0",
    "addr:street":"Box",
    "iso:country":"CA",
    "sg:address":"PO Box 1656",
    "sg:city":"Valleyview",
    "sg:classifiers":[
        {
            "category":"Recreation",
            "type":"Entertainment"
        }
    ],
    "sg:phone":"+1 780 524 3237",
    "sg:postcode":"T0H 3N0",
    "sg:province":"AB",
    "sg:tags":[
        "hall",
        "auditorium"
    ],
    "wof:name":"New Fish Creek Hall",
    "wof:placetype":"venue"
},
  "geometry": {"coordinates":[-117.271774292,55.0686416626],"type":"Point"}
}