{
  "type": "Feature",
  "properties": {
    "iso:country":"CA",
    "sg:address":"160 Rue Sylvain-Meunier",
    "sg:city":"Terrebonne",
    "sg:classifiers":[
        {
            "category":"Building & Trades",
            "subcategory":"Landscaping Services",
            "type":"Services"
        }
    ],
    "sg:phone":"+1 450 961 9036",
    "sg:postcode":"J6Y 1E3",
    "sg:province":"QC",
    "sg:tags":[
        "landscape",
        "contractor"
    ],
    "wof:name":"Jardins Phenix Les",
    "wof:placetype":"venue"
},
  "geometry": {"coordinates":[-73.668533,45.694347],"type":"Point"}
}