{
  "type": "Feature",
  "properties": {
    "addr:full":"851 Gibsons Way Gibsons BC V0N 1V8",
    "addr:housenumber":"851",
    "addr:postcode":"v0n 1v8",
    "addr:street":"Gibsons Way",
    "iso:country":"CA",
    "sg:address":"851 Gibsons Way",
    "sg:city":"Gibsons",
    "sg:classifiers":[
        {
            "category":"Restaurant",
            "type":"Food & Drink"
        }
    ],
    "sg:phone":"+1 604 886 9090",
    "sg:postcode":"V0N 1V8",
    "sg:province":"BC",
    "wof:name":"Robbie's Pancake House",
    "wof:placetype":"venue"
},
  "geometry": {"coordinates":[-123.516822815,49.4066238403],"type":"Point"}
}