{
  "type": "Feature",
  "properties": {
    "addr:full":"237 Av Desgagnes Sainte-Marie QC G6E 2A9",
    "addr:postcode":"g6e 2a9",
    "addr:street":"237 Av Desgagnes",
    "iso:country":"CA",
    "sg:address":"237 Av Desgagnes",
    "sg:city":"Sainte-Marie",
    "sg:classifiers":[
        {
            "category":"Personal",
            "subcategory":"Beauty Salon",
            "type":"Services"
        }
    ],
    "sg:phone":"+1 418 387 6366",
    "sg:postcode":"G6E 2A9",
    "sg:province":"QC",
    "wof:name":"Clinique D'Electrolyse",
    "wof:placetype":"venue"
},
  "geometry": {"coordinates":[-71.0446395874,46.4551239014],"type":"Point"}
}