{
  "type": "Feature",
  "properties": {
    "addr:full":"9945 Av Du Parc-Georges Montreal-Nord QC H1H 4X6",
    "addr:housenumber":"9945",
    "addr:postcode":"h1h 4x6",
    "addr:street":"Av Du Parc-Georges",
    "iso:country":"CA",
    "sg:address":"9945 Av Du Parc-Georges",
    "sg:city":"Montreal-Nord",
    "sg:classifiers":[
        {
            "category":"Freight",
            "type":"Transportation"
        }
    ],
    "sg:phone":"+1 514 321 5623",
    "sg:postcode":"H1H 4X6",
    "sg:province":"QC",
    "sg:tags":[
        "trucking"
    ],
    "wof:name":"Donnan Transport Inc",
    "wof:placetype":"venue"
},
  "geometry": {"coordinates":[-73.63711547849999,45.578704834],"type":"Point"}
}