{
  "type": "Feature",
  "properties": {
    "iso:country":"CA",
    "sg:city":"Roland",
    "sg:classifiers":[
        {
            "category":"Wholesale",
            "subcategory":"Construction Materials",
            "type":"Manufacturing & Wholesale Goods"
        }
    ],
    "sg:phone":"+1 204 343 2005",
    "sg:postcode":"R0G 1T0",
    "sg:province":"MB",
    "sg:tags":[
        "sand",
        "gravel"
    ],
    "wof:name":"B G Gravel Ltd",
    "wof:placetype":"venue"
},
  "geometry": {"coordinates":[-97.9299316406,49.3562393188],"type":"Point"}
}