{
  "type": "Feature",
  "properties": {
    "addr:full":"991 Kenaston Blvd Winnipeg MB R3P 1J9",
    "addr:housenumber":"991",
    "addr:postcode":"r3p 1j9",
    "addr:street":"Kenaston Blvd",
    "iso:country":"CA",
    "sg:address":"991 Kenaston Blvd",
    "sg:city":"Winnipeg",
    "sg:classifiers":[
        {
            "category":"Freight",
            "type":"Transportation"
        }
    ],
    "sg:phone":"+1 204 453 6042",
    "sg:postcode":"R3P 1J9",
    "sg:province":"MB",
    "sg:tags":[
        "trucking"
    ],
    "wof:name":"Clarke Transport",
    "wof:placetype":"venue"
},
  "geometry": {"coordinates":[-97.211296,49.843971],"type":"Point"}
}