{
  "type": "Feature",
  "properties": {
    "addr:full":"2282 Nicholson St S Prince George BC V2N 1V8",
    "addr:housenumber":"2282",
    "addr:postcode":"v2n 1v8",
    "addr:street":"Nicholson St S",
    "iso:country":"CA",
    "sg:address":"2282 Nicholson St S",
    "sg:city":"Prince George",
    "sg:classifiers":[
        {
            "category":"Building & Trades",
            "subcategory":"Cleaning & Sanitation",
            "type":"Services"
        }
    ],
    "sg:phone":"+1 250 564 0700",
    "sg:postcode":"V2N 1V8",
    "sg:province":"BC",
    "sg:tags":[
        "janitor"
    ],
    "wof:name":"Jani-King",
    "wof:placetype":"venue"
},
  "geometry": {"coordinates":[-122.787842,53.901478],"type":"Point"}
}