{
  "type": "Feature",
  "properties": {
    "addr:full":"53 St Aubin Ave Moonbeam ON P0L 1V0",
    "addr:housenumber":"53",
    "addr:postcode":"p0l 1v0",
    "addr:street":"St Aubin Ave",
    "iso:country":"CA",
    "sg:address":"53 St Aubin Ave",
    "sg:city":"Moonbeam",
    "sg:classifiers":[
        {
            "category":"Education",
            "subcategory":"Library",
            "type":"Public Place"
        }
    ],
    "sg:phone":"+1 705 367 2462",
    "sg:postcode":"P0L 1V0",
    "sg:province":"ON",
    "wof:name":"Bibliotheque Publique-Moonbeam",
    "wof:placetype":"venue"
},
  "geometry": {"coordinates":[-82.157768,49.345161],"type":"Point"}
}