{
  "type": "Feature",
  "properties": {
    "addr:full":"Guelph ON N1G 4S1",
    "addr:postcode":"n1g 4s1",
    "iso:country":"CA",
    "sg:city":"Guelph",
    "sg:classifiers":[
        {
            "category":"Restaurant",
            "type":"Food & Drink"
        }
    ],
    "sg:phone":"+1 519 767 1818",
    "sg:postcode":"N1G 4S1",
    "sg:province":"ON",
    "sg:tags":[
        "pizza"
    ],
    "wof:name":"New Orlean's Pizza",
    "wof:placetype":"venue"
},
  "geometry": {"coordinates":[-80.21389007569999,43.5225143433],"type":"Point"}
}