{
  "type": "Feature",
  "properties": {
    "iso:country":"CA",
    "sg:address":"4094 Ch DE LA Cote-Des-Neiges",
    "sg:city":"Montreal",
    "sg:classifiers":[
        {
            "category":"Organizations",
            "subcategory":"Community Association",
            "type":"Services"
        }
    ],
    "sg:phone":"+1 514 935 4466",
    "sg:postcode":"H3H 1W8",
    "sg:province":"QC",
    "sg:tags":[
        "club"
    ],
    "wof:name":"Montreal Indoor Tennis Club",
    "wof:placetype":"venue"
},
  "geometry": {"coordinates":[-73.599503,45.495285],"type":"Point"}
}