{
  "type": "Feature",
  "properties": {
    "addr:full":"1270 Wilson Ave North York ON M3M 1H5",
    "addr:housenumber":"1270",
    "addr:postcode":"m3m 1h5",
    "addr:street":"Wilson Ave",
    "iso:country":"CA",
    "sg:address":"1270 Wilson Ave",
    "sg:city":"North York",
    "sg:classifiers":[
        {
            "category":"Education",
            "subcategory":"School",
            "type":"Public Place"
        }
    ],
    "sg:phone":"+1 416 395 3070",
    "sg:postcode":"M3M 1H5",
    "sg:province":"ON",
    "wof:name":"Pierre Laporte Middle School",
    "wof:placetype":"venue"
},
  "geometry": {"coordinates":[-79.4921722412,43.7245521545],"type":"Point"}
}