{
  "type": "Feature",
  "properties": {
    "addr:full":"1744 Pioneer Rd Sudbury ON P3G 1A9",
    "addr:housenumber":"1744",
    "addr:postcode":"p3g 1a9",
    "addr:street":"Pioneer Rd",
    "iso:country":"CA",
    "sg:address":"1744 Pioneer Rd",
    "sg:city":"Sudbury",
    "sg:classifiers":[
        {
            "category":"Home & Garden",
            "subcategory":"Building Materials",
            "type":"Retail Goods"
        }
    ],
    "sg:phone":"+1 705 522 1531",
    "sg:postcode":"P3G 1A9",
    "sg:province":"ON",
    "sg:tags":[
        "lumber"
    ],
    "wof:name":"Richard Lake Lumber & Builders",
    "wof:placetype":"venue"
},
  "geometry": {"coordinates":[-80.935181,46.435177],"type":"Point"}
}