{
  "type": "Feature",
  "properties": {
    "iso:country":"CA",
    "sg:city":"Quebec",
    "sg:classifiers":[
        {
            "category":"Health Services",
            "subcategory":"Doctor",
            "type":"Services"
        }
    ],
    "sg:phone":"+1 418 688 0040",
    "sg:postcode":"G1S 2M5",
    "sg:province":"QC",
    "sg:tags":[
        "physician",
        "surgeon"
    ],
    "wof:name":"Clinique Pediatrique Jeff Hale",
    "wof:placetype":"venue"
},
  "geometry": {"coordinates":[-71.251671,46.79615],"type":"Point"}
}