{
  "type": "Feature",
  "properties": {
    "iso:country":"CA",
    "sg:address":"408 8 St E",
    "sg:city":"Drumheller",
    "sg:classifiers":[
        {
            "category":"Building & Trades",
            "subcategory":"Plumbing",
            "type":"Services"
        }
    ],
    "sg:phone":"+1 403 823 3500",
    "sg:postcode":"T0J 0Y5",
    "sg:province":"AB",
    "sg:tags":[
        "contractor"
    ],
    "wof:name":"Bereski Plumbing & Heating Ltd",
    "wof:placetype":"venue"
},
  "geometry": {"coordinates":[-112.694114685,51.4587249756],"type":"Point"}
}