{
  "type": "Feature",
  "properties": {
    "addr:full":"211 Yonge St Toronto ON M5B 1M4",
    "addr:housenumber":"211",
    "addr:postcode":"m5b 1m4",
    "addr:street":"Yonge St",
    "iso:country":"CA",
    "sg:address":"211 Yonge St",
    "sg:city":"Toronto",
    "sg:classifiers":[
        {
            "category":"Manufacturing",
            "subcategory":"Jewelry",
            "type":"Manufacturing & Wholesale Goods"
        }
    ],
    "sg:phone":"+1 416 368 5107",
    "sg:postcode":"M5B 1M4",
    "sg:province":"ON",
    "wof:name":"Chantel Jewelry Inc",
    "wof:placetype":"venue"
},
  "geometry": {"coordinates":[-79.379578,43.653587],"type":"Point"}
}