{
  "type": "Feature",
  "properties": {
    "iso:country":"CA",
    "sg:city":"London",
    "sg:classifiers":[
        {
            "category":"Health Services",
            "subcategory":"Health Practitioner",
            "type":"Services"
        }
    ],
    "sg:phone":"+1 519 472 3746",
    "sg:postcode":"N6K 1E1",
    "sg:province":"ON",
    "sg:tags":[
        "psychologist"
    ],
    "wof:name":"Byron Village Child Ctr",
    "wof:placetype":"venue"
},
  "geometry": {"coordinates":[-81.333893,42.959919],"type":"Point"}
}