{
  "type": "Feature",
  "properties": {
    "addr:full":"L'Islet QC G0R 2B0",
    "addr:postcode":"g0r 2b0",
    "iso:country":"CA",
    "sg:city":"L'Islet",
    "sg:classifiers":[
        {
            "category":"Organizations",
            "subcategory":"Professional Association",
            "type":"Services"
        }
    ],
    "sg:phone":"+1 418 247 3716",
    "sg:postcode":"G0R 2B0",
    "sg:province":"QC",
    "wof:name":"Chevaliers DE Colomb L'Islet",
    "wof:placetype":"venue"
},
  "geometry": {"coordinates":[-70.331535,47.089802],"type":"Point"}
}