{
  "type": "Feature",
  "properties": {
    "addr:full":"Waswanipi QC J0Y 3C0",
    "addr:postcode":"j0y 3c0",
    "iso:country":"CA",
    "sg:city":"Waswanipi",
    "sg:classifiers":[
        {
            "category":"Wholesale",
            "subcategory":"Machinery & Supplies",
            "type":"Manufacturing & Wholesale Goods"
        }
    ],
    "sg:phone":"+1 819 753 4001",
    "sg:postcode":"J0Y 3C0",
    "sg:province":"QC",
    "sg:tags":[
        "contractor"
    ],
    "wof:name":"Jerry's Makaheegan",
    "wof:placetype":"venue"
},
  "geometry": {"coordinates":[-75.892426,49.743309],"type":"Point"}
}