{
  "type": "Feature",
  "properties": {
    "iso:country":"CA",
    "sg:address":"235 Estey Rd",
    "sg:city":"Waterville Carleton CO",
    "sg:classifiers":[
        {
            "category":"Wholesale",
            "subcategory":"Hardware",
            "type":"Manufacturing & Wholesale Goods"
        }
    ],
    "sg:phone":"+1 506 375 6779",
    "sg:postcode":"E7P 1H5",
    "sg:province":"NB",
    "sg:tags":[
        "equipment",
        "heating",
        "system"
    ],
    "wof:name":"Woodchuck Heating Ltd",
    "wof:placetype":"venue"
},
  "geometry": {"coordinates":[-67.5839538574,46.2647705078],"type":"Point"}
}