{
  "type": "Feature",
  "properties": {
    "addr:full":"169 Av Roberval Roberval QC G8H 1H4",
    "addr:postcode":"g8h 1h4",
    "addr:street":"169 Av Roberval",
    "iso:country":"CA",
    "sg:address":"169 Av Roberval",
    "sg:city":"Roberval",
    "sg:classifiers":[
        {
            "category":"Professional",
            "subcategory":"Management & Consulting",
            "type":"Services"
        }
    ],
    "sg:phone":"+1 418 275 7171",
    "sg:postcode":"G8H 1H4",
    "sg:province":"QC",
    "sg:tags":[
        "consultant",
        "business"
    ],
    "wof:name":"Groupe Tanguay",
    "wof:placetype":"venue"
},
  "geometry": {"coordinates":[-72.223572,48.514542],"type":"Point"}
}