{
  "type": "Feature",
  "properties": {
    "iso:country":"CA",
    "sg:address":"2810 Ch Gauthier",
    "sg:city":"LA Plaine",
    "sg:classifiers":[
        {
            "category":"Building & Trades",
            "subcategory":"Construction",
            "type":"Services"
        }
    ],
    "sg:phone":"+1 450 478 6740",
    "sg:postcode":"J7M 1R8",
    "sg:province":"QC",
    "sg:tags":[
        "maker",
        "cabinet"
    ],
    "wof:name":"Ebenisterie DE LA Rive Nord",
    "wof:placetype":"venue"
},
  "geometry": {"coordinates":[-73.77629089360001,45.7856063843],"type":"Point"}
}