{
  "type": "Feature",
  "properties": {
    "iso:country":"CA",
    "sg:address":"515 Rue Pigeon",
    "sg:city":"Victoriaville",
    "sg:classifiers":[
        {
            "category":"Real Estate",
            "subcategory":"Real Estate Agent",
            "type":"Services"
        }
    ],
    "sg:phone":"+1 819 752 4170",
    "sg:postcode":"G6P 2K9",
    "sg:province":"QC",
    "sg:tags":[
        "authorities",
        "housing"
    ],
    "wof:name":"Gestion Arho Inc",
    "wof:placetype":"venue"
},
  "geometry": {"coordinates":[-71.9707336426,46.0575904846],"type":"Point"}
}