{
  "type": "Feature",
  "properties": {
    "iso:country":"CA",
    "sg:address":"5486 Rue Orchard",
    "sg:city":"Saint-Hubert",
    "sg:classifiers":[
        {
            "category":"Retail",
            "subcategory":"Laundry & Dry Cleaning",
            "type":"Services"
        }
    ],
    "sg:phone":"+1 450 676 6561",
    "sg:postcode":"J3Y 2H1",
    "sg:province":"QC",
    "sg:tags":[
        "cleaners"
    ],
    "wof:name":"Buanderie St-Hubert Enr",
    "wof:placetype":"venue"
},
  "geometry": {"coordinates":[-73.44319152830001,45.4753761292],"type":"Point"}
}