{
  "type": "Feature",
  "properties": {
    "addr:full":"PO Box 539 STN Main Kamloops BC V2C 5L2",
    "addr:housenumber":"po",
    "addr:postcode":"bc v2c 5l2",
    "addr:street":"Box 539 Stn Main",
    "iso:country":"CA",
    "sg:address":"PO Box 539 STN Main",
    "sg:city":"Kamloops",
    "sg:classifiers":[
        {
            "category":"Organizations",
            "subcategory":"Religious Organization",
            "type":"Services"
        }
    ],
    "sg:phone":"+1 250 374 5594",
    "sg:postcode":"V2C 5L2",
    "sg:province":"BC",
    "sg:tags":[
        "church"
    ],
    "wof:name":"Unitarian Universalist Fllshp",
    "wof:placetype":"venue"
},
  "geometry": {"coordinates":[-120.337890625,50.6761245728],"type":"Point"}
}