{
  "type": "Feature",
  "properties": {
    "iso:country":"CA",
    "sg:city":"Lasalle",
    "sg:classifiers":[
        {
            "category":"Wholesale",
            "subcategory":"Durable Goods & Equipment",
            "type":"Manufacturing & Wholesale Goods"
        }
    ],
    "sg:phone":"+1 514 368 2662",
    "sg:postcode":"H8N 1A5",
    "sg:province":"QC",
    "sg:tags":[
        "laboratory",
        "supply"
    ],
    "wof:name":"Service & Certification",
    "wof:placetype":"venue"
},
  "geometry": {"coordinates":[-73.60609436039999,45.4377326965],"type":"Point"}
}