{
  "type": "Feature",
  "properties": {
    "addr:full":"Ear Falls ON P0V 1T0",
    "addr:postcode":"p0v 1t0",
    "iso:country":"CA",
    "sg:city":"Ear Falls",
    "sg:classifiers":[
        {
            "category":"Travel",
            "subcategory":"Hotels & Motels",
            "type":"Entertainment"
        }
    ],
    "sg:phone":"+1 807 222 3126",
    "sg:postcode":"P0V 1T0",
    "sg:province":"ON",
    "sg:tags":[
        "resort"
    ],
    "wof:name":"Trillium Motel Ltd",
    "wof:placetype":"venue"
},
  "geometry": {"coordinates":[-93.42472100000001,50.787022],"type":"Point"}
}