{
  "type": "Feature",
  "properties": {
    "addr:full":"5300 Boul Saint-Martin O Laval QC H7T 2Y1",
    "addr:housenumber":"5300",
    "addr:postcode":"h7t 2y1",
    "addr:street":"Boul Saint-Martin O",
    "iso:country":"CA",
    "sg:address":"5300 Boul Saint-Martin O",
    "sg:city":"Laval",
    "sg:classifiers":[
        {
            "category":"Food & Beverages",
            "subcategory":"Groceries & Convenience Stores",
            "type":"Retail Goods"
        }
    ],
    "sg:phone":"+1 450 681 7518",
    "sg:postcode":"H7T 2Y1",
    "sg:province":"QC",
    "wof:name":"Depanneur Blue",
    "wof:placetype":"venue"
},
  "geometry": {"coordinates":[-73.78726959230001,45.5421791077],"type":"Point"}
}