{
  "type": "Feature",
  "properties": {
    "addr:full":"18 Champlain Blvd North York ON M3H 2Z1",
    "addr:housenumber":"18",
    "addr:postcode":"m3h 2z1",
    "addr:street":"Champlain Blvd",
    "iso:country":"CA",
    "sg:address":"18 Champlain Blvd",
    "sg:city":"North York",
    "sg:classifiers":[
        {
            "category":"Professional",
            "subcategory":"Engineering",
            "type":"Services"
        }
    ],
    "sg:phone":"+1 416 398 6020",
    "sg:postcode":"M3H 2Z1",
    "sg:province":"ON",
    "sg:tags":[
        "engineer"
    ],
    "wof:name":"Rybka Smith & Ginsler Ltd",
    "wof:placetype":"venue"
},
  "geometry": {"coordinates":[-79.444351,43.734203],"type":"Point"}
}