{
  "type": "Feature",
  "properties": {
    "iso:country":"CA",
    "sg:address":"370 Bloor St E",
    "sg:city":"Toronto",
    "sg:classifiers":[
        {
            "category":"Professional",
            "subcategory":"Lawyer & Legal Services",
            "type":"Services"
        }
    ],
    "sg:phone":"+1 416 962 1717",
    "sg:postcode":"M4W 3M6",
    "sg:province":"ON",
    "sg:tags":[
        "attorney"
    ],
    "wof:name":"Bennett, Paul",
    "wof:placetype":"venue"
},
  "geometry": {"coordinates":[-79.3781661987,43.6722145081],"type":"Point"}
}