{
  "type": "Feature",
  "properties": {
    "addr:full":"835 Rue DE Saint-Jovite Mont-Tremblant QC J8E 3J8",
    "addr:housenumber":"835",
    "addr:postcode":"j8e 3j8",
    "addr:street":"Rue De Saint-Jovite",
    "iso:country":"CA",
    "sg:address":"835 Rue DE Saint-Jovite",
    "sg:city":"Mont-Tremblant",
    "sg:classifiers":[
        {
            "category":"Manufacturing",
            "subcategory":"Food",
            "type":"Manufacturing & Wholesale Goods"
        }
    ],
    "sg:phone":"+1 819 425 8987",
    "sg:postcode":"J8E 3J8",
    "sg:province":"QC",
    "sg:tags":[
        "baker",
        "chocolate"
    ],
    "wof:name":"Patisserie Le Montagnard",
    "wof:placetype":"venue"
},
  "geometry": {"coordinates":[-74.59107208250001,46.1185035706],"type":"Point"}
}