{
  "type": "Feature",
  "properties": {
    "addr:full":"8603 Kelly Rd N Prince George BC V2K 2W7",
    "addr:housenumber":"8603",
    "addr:postcode":"v2k 2w7",
    "addr:street":"Kelly Rd N",
    "iso:country":"CA",
    "sg:address":"8603 Kelly Rd N",
    "sg:city":"Prince George",
    "sg:classifiers":[
        {
            "category":"Manufacturing",
            "subcategory":"Glass & Minerals",
            "type":"Manufacturing & Wholesale Goods"
        }
    ],
    "sg:phone":"+1 250 962 2322",
    "sg:postcode":"V2K 2W7",
    "sg:province":"BC",
    "sg:tags":[
        "fabricator",
        "fiber"
    ],
    "wof:name":"Chem-Star Industries Ltd",
    "wof:placetype":"venue"
},
  "geometry": {"coordinates":[-122.801331,54.010303],"type":"Point"}
}