{
  "type": "Feature",
  "properties": {
    "addr:full":"Baldonnel BC V0C 1C0",
    "addr:postcode":"bc v0c 1c0",
    "iso:country":"CA",
    "sg:city":"Baldonnel",
    "sg:classifiers":[
        {
            "category":"Mining & Drilling",
            "type":"Manufacturing & Wholesale Goods"
        }
    ],
    "sg:phone":"+1 250 789 3051",
    "sg:postcode":"V0C 1C0",
    "sg:province":"BC",
    "sg:tags":[
        "field",
        "oil"
    ],
    "wof:name":"Newalta Corp",
    "wof:placetype":"venue"
},
  "geometry": {"coordinates":[-120.71172332800001,56.2132949829],"type":"Point"}
}