{
  "type": "Feature",
  "properties": {
    "addr:full":"Lloydminster SK S9V 0P4",
    "addr:postcode":"s9v 0p4",
    "iso:country":"CA",
    "sg:city":"Lloydminster",
    "sg:classifiers":[
        {
            "category":"Travel",
            "subcategory":"Hotels & Motels",
            "type":"Entertainment"
        }
    ],
    "sg:phone":"+1 306 825 5591",
    "sg:postcode":"S9V 0P4",
    "sg:province":"SK",
    "wof:name":"Lloydminster Motor Inn",
    "wof:placetype":"venue"
},
  "geometry": {"coordinates":[-110.005295,53.280018],"type":"Point"}
}