{
  "type": "Feature",
  "properties": {
    "addr:full":"1730 Corydon Ave Winnipeg MB R3N 0K3",
    "addr:housenumber":"1730",
    "addr:postcode":"r3n 0k3",
    "addr:street":"Corydon Ave",
    "iso:country":"CA",
    "sg:address":"1730 Corydon Ave",
    "sg:city":"Winnipeg",
    "sg:classifiers":[
        {
            "category":"Shopping",
            "subcategory":"Clothing, Apparel, & Fashions",
            "type":"Retail Goods"
        }
    ],
    "sg:phone":"+1 204 489 1001",
    "sg:postcode":"R3N 0K3",
    "sg:province":"MB",
    "sg:tags":[
        "furnishing"
    ],
    "wof:name":"Vittorio-Rossi Clothiers",
    "wof:placetype":"venue"
},
  "geometry": {"coordinates":[-97.200928,49.863766],"type":"Point"}
}