{
  "type": "Feature",
  "properties": {
    "addr:full":"12355 Davison St Maple Ridge BC V2X 5N5",
    "addr:housenumber":"12355",
    "addr:postcode":"v2x 5n5",
    "addr:street":"Davison St",
    "iso:country":"CA",
    "sg:address":"12355 Davison St",
    "sg:city":"Maple Ridge",
    "sg:classifiers":[
        {
            "category":"Retail",
            "subcategory":"Laundry & Dry Cleaning",
            "type":"Services"
        }
    ],
    "sg:phone":"+1 604 463 6644",
    "sg:postcode":"V2X 5N5",
    "sg:province":"BC",
    "sg:tags":[
        "cleaners",
        "rug",
        "carpet"
    ],
    "wof:name":"Magi-Care Carpet & Upholstery",
    "wof:placetype":"venue"
},
  "geometry": {"coordinates":[-122.615707,49.22699],"type":"Point"}
}