{
  "type": "Feature",
  "properties": {
    "iso:country":"CA",
    "sg:address":"7004 Ch Guelph",
    "sg:city":"Cote Saint-Luc",
    "sg:classifiers":[
        {
            "category":"Professional",
            "subcategory":"Management & Consulting",
            "type":"Services"
        }
    ],
    "sg:phone":"+1 514 488 5214",
    "sg:postcode":"H4W 1G7",
    "sg:province":"QC",
    "sg:tags":[
        "break",
        "coffee",
        "supply"
    ],
    "wof:name":"Cafe Ritz",
    "wof:placetype":"venue"
},
  "geometry": {"coordinates":[-73.6625747681,45.4695625305],"type":"Point"}
}