{
  "type": "Feature",
  "properties": {
    "addr:full":"668 Rue Belanger Notre-Dame-Du-Lac QC G0L 1X0",
    "addr:housenumber":"668",
    "addr:postcode":"g0l 1x0",
    "addr:street":"Rue Belanger",
    "iso:country":"CA",
    "sg:address":"668 Rue Belanger",
    "sg:city":"Notre-Dame-Du-Lac",
    "sg:classifiers":[
        {
            "category":"Travel",
            "subcategory":"Hotels & Motels",
            "type":"Entertainment"
        }
    ],
    "sg:phone":"+1 418 899 6545",
    "sg:postcode":"G0L 1X0",
    "sg:province":"QC",
    "wof:name":"Restaurant LA Vision",
    "wof:placetype":"venue"
},
  "geometry": {"coordinates":[-68.798935,47.610409],"type":"Point"}
}