{
  "type": "Feature",
  "properties": {
    "iso:country":"CA",
    "sg:city":"Scarborough",
    "sg:classifiers":[
        {
            "category":"Home & Garden",
            "subcategory":"Hardware",
            "type":"Retail Goods"
        }
    ],
    "sg:phone":"+1 416 773 0317",
    "sg:postcode":"M1W 2S8",
    "sg:province":"ON",
    "wof:name":"Rizvi's Home Hardware",
    "wof:placetype":"venue"
},
  "geometry": {"coordinates":[-79.31596374510001,43.7968978882],"type":"Point"}
}