{
  "type": "Feature",
  "properties": {
    "addr:full":"1293 Main St Smithers BC V0J 2N0",
    "addr:housenumber":"1293",
    "addr:postcode":"v0j 2n0",
    "addr:street":"Main St",
    "iso:country":"CA",
    "sg:address":"1293 Main St",
    "sg:city":"Smithers",
    "sg:classifiers":[
        {
            "category":"Restaurant",
            "type":"Food & Drink"
        }
    ],
    "sg:phone":"+1 250 847 2547",
    "sg:postcode":"V0J 2N0",
    "sg:province":"BC",
    "sg:tags":[
        "caterer"
    ],
    "wof:name":"Louise's Kitchen",
    "wof:placetype":"venue"
},
  "geometry": {"coordinates":[-127.168899536,54.7811393738],"type":"Point"}
}