{
  "type": "Feature",
  "properties": {
    "addr:full":"7130 Rue Beaubien E Anjou QC H1M 1B2",
    "addr:housenumber":"7130",
    "addr:postcode":"h1m 1b2",
    "addr:street":"Rue Beaubien E",
    "iso:country":"CA",
    "sg:address":"7130 Rue Beaubien E",
    "sg:city":"Anjou",
    "sg:classifiers":[
        {
            "category":"Real Estate",
            "subcategory":"Real Estate Agent",
            "type":"Services"
        }
    ],
    "sg:phone":"+1 514 354 6240",
    "sg:postcode":"H1M 1B2",
    "sg:province":"QC",
    "wof:name":"Remax Excellence Inc",
    "wof:placetype":"venue"
},
  "geometry": {"coordinates":[-73.5567321777,45.5941696167],"type":"Point"}
}