{
  "type": "Feature",
  "properties": {
    "addr:full":"2300 Haines Rd Mississauga ON L4Y 1Y6",
    "addr:housenumber":"2300",
    "addr:postcode":"l4y 1y6",
    "addr:street":"Haines Rd",
    "iso:country":"CA",
    "sg:address":"2300 Haines Rd",
    "sg:city":"Mississauga",
    "sg:classifiers":[
        {
            "category":"Manufacturing",
            "subcategory":"Food",
            "type":"Manufacturing & Wholesale Goods"
        }
    ],
    "sg:phone":"+1 905 896 8512",
    "sg:postcode":"L4Y 1Y6",
    "sg:province":"ON",
    "sg:tags":[
        "winery",
        "wine"
    ],
    "wof:name":"Colio Estate Wines of Canada",
    "wof:placetype":"venue"
},
  "geometry": {"coordinates":[-79.58905,43.591862],"type":"Point"}
}