{
  "type": "Feature",
  "properties": {
    "addr:full":"Toronto ON M4R 1B9",
    "addr:postcode":"m4r 1b9",
    "iso:country":"CA",
    "sg:city":"Toronto",
    "sg:classifiers":[
        {
            "category":"Organizations",
            "subcategory":"Membership Organization",
            "type":"Services"
        }
    ],
    "sg:phone":"+1 416 515 1559",
    "sg:postcode":"M4R 1B9",
    "sg:province":"ON",
    "wof:name":"Canadian Society of Children's",
    "wof:placetype":"venue"
},
  "geometry": {"coordinates":[-79.39990997309999,43.7080802917],"type":"Point"}
}