{
  "type": "Feature",
  "properties": {
    "addr:full":"Ottawa ON K1B 5N1",
    "addr:postcode":"k1b 5n1",
    "iso:country":"CA",
    "sg:city":"Ottawa",
    "sg:classifiers":[
        {
            "category":"Shopping",
            "subcategory":"Hobbies, Toys, & Games",
            "type":"Retail Goods"
        }
    ],
    "sg:phone":"+1 613 733 2844",
    "sg:postcode":"K1B 5N1",
    "sg:province":"ON",
    "sg:tags":[
        "supply"
    ],
    "wof:name":"Chess Federation of Canada",
    "wof:placetype":"venue"
},
  "geometry": {"coordinates":[-75.624855,45.405392],"type":"Point"}
}