{
  "type": "Feature",
  "properties": {
    "addr:full":"1121 Boul Camille Marcoux Lourdes-DE-Blanc-Sablon QC G0G 1W0",
    "addr:housenumber":"1121",
    "addr:postcode":"g0g 1w0",
    "addr:street":"Boul Camille Marcoux",
    "iso:country":"CA",
    "sg:address":"1121 Boul Camille Marcoux",
    "sg:city":"Lourdes-DE-Blanc-Sablon",
    "sg:classifiers":[
        {
            "category":"Food & Beverages",
            "subcategory":"Groceries & Convenience Stores",
            "type":"Retail Goods"
        }
    ],
    "sg:phone":"+1 418 461 2521",
    "sg:postcode":"G0G 1W0",
    "sg:province":"QC",
    "sg:tags":[
        "grocer"
    ],
    "wof:name":"Epicerie Chez Jl Joncas Inc",
    "wof:placetype":"venue"
},
  "geometry": {"coordinates":[-57.1934051514,51.4144210815],"type":"Point"}
}