{
  "type": "Feature",
  "properties": {
    "iso:country":"CA",
    "sg:city":"Saint-Laurent",
    "sg:classifiers":[
        {
            "category":"Freight",
            "type":"Transportation"
        }
    ],
    "sg:phone":"+1 514 342 7117",
    "sg:postcode":"H4T 2B3",
    "sg:province":"QC",
    "sg:tags":[
        "mover"
    ],
    "wof:name":"Mina Transport",
    "wof:placetype":"venue"
},
  "geometry": {"coordinates":[-73.697296,45.485764],"type":"Point"}
}