{
  "type": "Feature",
  "properties": {
    "addr:full":"Mississauga ON L5N 7C7",
    "addr:postcode":"l5n 7c7",
    "iso:country":"CA",
    "sg:city":"Mississauga",
    "sg:classifiers":[
        {
            "category":"Retail",
            "subcategory":"Laundry & Dry Cleaning",
            "type":"Services"
        }
    ],
    "sg:phone":"+1 905 824 7045",
    "sg:postcode":"L5N 7C7",
    "sg:province":"ON",
    "sg:tags":[
        "cleaners"
    ],
    "wof:name":"Top Hat Cleaners",
    "wof:placetype":"venue"
},
  "geometry": {"coordinates":[-79.779495,43.595211],"type":"Point"}
}