{
  "type": "Feature",
  "properties": {
    "addr:full":"3003 Boul Le Carrefour Laval QC H7T 1C7",
    "addr:housenumber":"3003",
    "addr:postcode":"h7t 1c7",
    "addr:street":"Boul Le Carrefour",
    "iso:country":"CA",
    "sg:address":"3003 Boul Le Carrefour",
    "sg:city":"Laval",
    "sg:classifiers":[
        {
            "category":"Home & Garden",
            "subcategory":"Furniture",
            "type":"Retail Goods"
        }
    ],
    "sg:phone":"+1 450 978 5362",
    "sg:postcode":"H7T 1C7",
    "sg:province":"QC",
    "wof:name":"Bombay CO",
    "wof:placetype":"venue"
},
  "geometry": {"coordinates":[-73.747925,45.569653],"type":"Point"}
}