{
  "type": "Feature",
  "properties": {
    "addr:full":"101 Main St Herschel SK S0L 1L0",
    "addr:housenumber":"101",
    "addr:postcode":"s0l 1l0",
    "addr:street":"Main St",
    "iso:country":"CA",
    "sg:address":"101 Main St",
    "sg:city":"Herschel",
    "sg:classifiers":[
        {
            "category":"Travel",
            "subcategory":"Hotels & Motels",
            "type":"Entertainment"
        }
    ],
    "sg:phone":"+1 306 377 4770",
    "sg:postcode":"S0L 1L0",
    "sg:province":"SK",
    "wof:name":"Herschel Hotel",
    "wof:placetype":"venue"
},
  "geometry": {"coordinates":[-108.35534668,51.6375808716],"type":"Point"}
}