{
  "type": "Feature",
  "properties": {
    "addr:full":"15779 Cranley Dr Surrey BC V4A 5C3",
    "addr:housenumber":"15779",
    "addr:postcode":"v4a 5c3",
    "addr:street":"Cranley Dr",
    "iso:country":"CA",
    "sg:address":"15779 Cranley Dr",
    "sg:city":"Surrey",
    "sg:classifiers":[
        {
            "category":"Building & Trades",
            "subcategory":"Construction",
            "type":"Services"
        }
    ],
    "sg:phone":"+1 604 535 7194",
    "sg:postcode":"V4A 5C3",
    "sg:province":"BC",
    "sg:tags":[
        "roofing",
        "contractor"
    ],
    "wof:name":"Sunnyside Enterprises",
    "wof:placetype":"venue"
},
  "geometry": {"coordinates":[-122.78742200000001,49.044479],"type":"Point"}
}