{
  "type": "Feature",
  "properties": {
    "addr:full":"Morden MB R6M 1W3",
    "addr:postcode":"r6m 1w3",
    "iso:country":"CA",
    "sg:city":"Morden",
    "sg:classifiers":[
        {
            "category":"Social Services",
            "type":"Services"
        }
    ],
    "sg:phone":"+1 204 822 6622",
    "sg:postcode":"R6M 1W3",
    "sg:province":"MB",
    "sg:tags":[
        "counselor",
        "marriage",
        "family"
    ],
    "wof:name":"Pembina Counselling Ctr",
    "wof:placetype":"venue"
},
  "geometry": {"coordinates":[-98.10325622560001,49.1897392273],"type":"Point"}
}