{
  "type": "Feature",
  "properties": {
    "addr:full":"355 Rue Des Forges Trois-Rivieres QC G9A 2G9",
    "addr:housenumber":"355",
    "addr:postcode":"g9a 2g9",
    "addr:street":"Rue Des Forges Trois-Rivieres",
    "iso:country":"CA",
    "sg:address":"355 Rue Des Forges",
    "sg:city":"Trois-Rivieres",
    "sg:classifiers":[
        {
            "category":"Wholesale",
            "subcategory":"Meat",
            "type":"Manufacturing & Wholesale Goods"
        }
    ],
    "sg:phone":"+1 819 374 7500",
    "sg:postcode":"G9A 2G9",
    "sg:province":"QC",
    "sg:tags":[
        "butchering"
    ],
    "wof:name":"Boucherie Alex Lamy Inc",
    "wof:placetype":"venue"
},
  "geometry": {"coordinates":[-72.543098,46.342045],"type":"Point"}
}