{
  "type": "Feature",
  "properties": {
    "addr:full":"855 Algonquin Blvd E Timmins ON P4N 7H1",
    "addr:housenumber":"855",
    "addr:postcode":"p4n 7h1",
    "addr:street":"Algonquin Blvd E",
    "iso:country":"CA",
    "sg:address":"855 Algonquin Blvd E",
    "sg:city":"Timmins",
    "sg:classifiers":[
        {
            "category":"Wholesale",
            "subcategory":"Chemicals & Plastics",
            "type":"Manufacturing & Wholesale Goods"
        }
    ],
    "sg:phone":"+1 705 268 6466",
    "sg:postcode":"P4N 7H1",
    "sg:province":"ON",
    "sg:tags":[
        "equipment",
        "welding",
        "gas",
        "supply"
    ],
    "wof:name":"Boc Gases",
    "wof:placetype":"venue"
},
  "geometry": {"coordinates":[-81.316231,48.476624],"type":"Point"}
}