{
  "type": "Feature",
  "properties": {
    "addr:full":"32 Ryan Pl Brantford ON N3S 7S1",
    "addr:housenumber":"32",
    "addr:postcode":"n3s 7s1",
    "addr:street":"Ryan Pl",
    "iso:country":"CA",
    "sg:address":"32 Ryan Pl",
    "sg:city":"Brantford",
    "sg:classifiers":[
        {
            "category":"Manufacturing",
            "subcategory":"Tools & Machinery",
            "type":"Manufacturing & Wholesale Goods"
        }
    ],
    "sg:phone":"+1 519 756 4150",
    "sg:postcode":"N3S 7S1",
    "sg:province":"ON",
    "sg:tags":[
        "machine",
        "shop",
        "mechanical",
        "contractor"
    ],
    "wof:name":"Bml Multi Trades Group Ltd",
    "wof:placetype":"venue"
},
  "geometry": {"coordinates":[-80.2260055542,43.1526870728],"type":"Point"}
}