{
  "type": "Feature",
  "properties": {
    "addr:full":"25 Gibson Ave Toronto ON M5R 1T4",
    "addr:housenumber":"25",
    "addr:postcode":"m5r 1t4",
    "addr:street":"Gibson Ave",
    "iso:country":"CA",
    "sg:address":"25 Gibson Ave",
    "sg:city":"Toronto",
    "sg:classifiers":[
        {
            "category":"Building & Trades",
            "subcategory":"Construction",
            "type":"Services"
        }
    ],
    "sg:phone":"+1 416 749 5978",
    "sg:postcode":"M5R 1T4",
    "sg:province":"ON",
    "sg:tags":[
        "excavating",
        "contractor"
    ],
    "wof:name":"Vemar Construction Ltd",
    "wof:placetype":"venue"
},
  "geometry": {"coordinates":[-79.39044199999999,43.677071],"type":"Point"}
}