{
  "type": "Feature",
  "properties": {
    "addr:full":"25189 Dewdney Trunk Rd Maple Ridge BC V4R 1X6",
    "addr:housenumber":"25189",
    "addr:postcode":"bc v4r 1x6",
    "addr:street":"Dewdney Trunk Rd",
    "iso:country":"CA",
    "sg:address":"25189 Dewdney Trunk Rd",
    "sg:city":"Maple Ridge",
    "sg:classifiers":[
        {
            "category":"Building & Trades",
            "subcategory":"Construction",
            "type":"Services"
        }
    ],
    "sg:phone":"+1 604 463 6444",
    "sg:postcode":"V4R 1X6",
    "sg:province":"BC",
    "sg:tags":[
        "roofing",
        "contractor"
    ],
    "wof:name":"A Super Roofing Inc",
    "wof:placetype":"venue"
},
  "geometry": {"coordinates":[-122.524353,49.220474],"type":"Point"}
}