{
  "type": "Feature",
  "properties": {
    "addr:full":"10620 Yonge St Richmond Hill ON L4C 3C8",
    "addr:housenumber":"10620",
    "addr:postcode":"l4c 3c8",
    "addr:street":"Yonge St",
    "iso:country":"CA",
    "sg:address":"10620 Yonge St",
    "sg:city":"Richmond Hill",
    "sg:classifiers":[
        {
            "category":"Education",
            "subcategory":"Special Training",
            "type":"Public Place"
        }
    ],
    "sg:phone":"+1 905 883 0844",
    "sg:postcode":"L4C 3C8",
    "sg:province":"ON",
    "sg:tags":[
        "instruction",
        "music"
    ],
    "wof:name":"Arcadia Academy of Music",
    "wof:placetype":"venue"
},
  "geometry": {"coordinates":[-79.440842,43.885998],"type":"Point"}
}