{
  "type": "Feature",
  "properties": {
    "addr:full":"5027 Lakeshore Dr Sylvan Lake AB T4S 1R3",
    "addr:housenumber":"5027",
    "addr:postcode":"t4s 1r3",
    "addr:street":"Lakeshore Dr",
    "iso:country":"CA",
    "sg:address":"5027 Lakeshore Dr",
    "sg:city":"Sylvan Lake",
    "sg:classifiers":[
        {
            "category":"Real Estate",
            "subcategory":"Developer",
            "type":"Services"
        }
    ],
    "sg:phone":"+1 403 887 2888",
    "sg:postcode":"T4S 1R3",
    "sg:province":"AB",
    "sg:tags":[
        "company",
        "land"
    ],
    "wof:name":"Bear Development Corp",
    "wof:placetype":"venue"
},
  "geometry": {"coordinates":[-114.098732,52.309975],"type":"Point"}
}