{
  "type": "Feature",
  "properties": {
    "addr:full":"520 Rue Du Sud Cowansville QC J2K 2X8",
    "addr:housenumber":"520",
    "addr:postcode":"j2k 2x8",
    "addr:street":"Rue Du Sud",
    "iso:country":"CA",
    "sg:address":"520 Rue Du Sud",
    "sg:city":"Cowansville",
    "sg:classifiers":[
        {
            "category":"Restaurant",
            "type":"Food & Drink"
        }
    ],
    "sg:phone":"+1 450 263 8666",
    "sg:postcode":"J2K 2X8",
    "sg:province":"QC",
    "sg:tags":[
        "caterer"
    ],
    "wof:name":"Traiteur Topinambours Inc",
    "wof:placetype":"venue"
},
  "geometry": {"coordinates":[-72.74715399999999,45.20359],"type":"Point"}
}