{
  "type": "Feature",
  "properties": {
    "addr:full":"1850 Baseline Rd Ottawa ON K2C 0C6",
    "addr:housenumber":"1850",
    "addr:postcode":"k2c 0c6",
    "addr:street":"Baseline Rd",
    "iso:country":"CA",
    "sg:address":"1850 Baseline Rd",
    "sg:city":"Ottawa",
    "sg:classifiers":[
        {
            "category":"Restaurant",
            "type":"Food & Drink"
        }
    ],
    "sg:phone":"+1 613 723 5719",
    "sg:postcode":"K2C 0C6",
    "sg:province":"ON",
    "wof:name":"Mc Donald's",
    "wof:placetype":"venue"
},
  "geometry": {"coordinates":[-75.757668,45.353455],"type":"Point"}
}