{
  "type": "Feature",
  "properties": {
    "addr:full":"638 16 Ave NW Calgary AB T2M 0J7",
    "addr:postcode":"t2m 0j7",
    "addr:street":"638 16 Ave Nw",
    "iso:country":"CA",
    "sg:address":"638 16 Ave NW",
    "sg:city":"Calgary",
    "sg:classifiers":[
        {
            "category":"Shopping",
            "subcategory":"Used Merchandise",
            "type":"Retail Goods"
        }
    ],
    "sg:phone":"+1 403 282 4405",
    "sg:postcode":"T2M 0J7",
    "sg:province":"AB",
    "sg:tags":[
        "shop",
        "consignment",
        "clothing"
    ],
    "wof:name":"Indah Imports",
    "wof:placetype":"venue"
},
  "geometry": {"coordinates":[-114.07493599999999,51.067097],"type":"Point"}
}