{
  "type": "Feature",
  "properties": {
    "addr:full":"193 Rue Canada Saint-Quentin NB E8A 1J8",
    "addr:housenumber":"193",
    "addr:postcode":"e8a 1j8",
    "addr:street":"Rue",
    "iso:country":"CA",
    "sg:address":"193 Rue Canada",
    "sg:city":"Saint-Quentin",
    "sg:classifiers":[
        {
            "category":"Government",
            "subcategory":"Office",
            "type":"Public Place"
        }
    ],
    "sg:phone":"+1 506 789 4500",
    "sg:postcode":"E8A 1J8",
    "sg:province":"NB",
    "wof:name":"Canada Human Resource Ctr",
    "wof:placetype":"venue"
},
  "geometry": {"coordinates":[-67.392349,47.510284],"type":"Point"}
}