{
  "type": "Feature",
  "properties": {
    "addr:full":"89098 Road 7E Gunton MB R0C 1H0",
    "addr:housenumber":"89098;7e",
    "addr:postcode":"r0c 1h0",
    "addr:street":"Road",
    "iso:country":"CA",
    "sg:address":"89098 Road 7E",
    "sg:city":"Gunton",
    "sg:classifiers":[
        {
            "category":"Farming",
            "subcategory":"Poultry Farm",
            "type":"Manufacturing & Wholesale Goods"
        }
    ],
    "sg:phone":"+1 204 886 2922",
    "sg:postcode":"R0C 1H0",
    "sg:province":"MB",
    "wof:name":"Charison's Turkey Hatchery Ltd",
    "wof:placetype":"venue"
},
  "geometry": {"coordinates":[-97.26657899999999,50.317371],"type":"Point"}
}