{
  "type": "Feature",
  "properties": {
    "iso:country":"CA",
    "sg:address":"450 Boul Poliquin",
    "sg:city":"Sorel-Tracy",
    "sg:classifiers":[
        {
            "category":"Shopping",
            "subcategory":"Clothing, Apparel, & Fashions",
            "type":"Retail Goods"
        }
    ],
    "sg:phone":"+1 450 746 5867",
    "sg:postcode":"J3P 7R5",
    "sg:province":"QC",
    "wof:name":"Lindor Inc",
    "wof:placetype":"venue"
},
  "geometry": {"coordinates":[-73.0897140503,46.0351371765],"type":"Point"}
}