{
  "type": "Feature",
  "properties": {
    "addr:full":"955 Maginot St Winnipeg MB R2J 0Z7",
    "addr:housenumber":"955",
    "addr:postcode":"r2j 0z7",
    "addr:street":"Maginot St",
    "iso:country":"CA",
    "sg:address":"955 Maginot St",
    "sg:city":"Winnipeg",
    "sg:classifiers":[
        {
            "category":"Freight",
            "type":"Transportation"
        }
    ],
    "sg:phone":"+1 204 233 8945",
    "sg:postcode":"R2J 0Z7",
    "sg:province":"MB",
    "sg:tags":[
        "trucking"
    ],
    "wof:name":"Trimac Transportation Svc Inc",
    "wof:placetype":"venue"
},
  "geometry": {"coordinates":[-97.0768585205,49.8737106323],"type":"Point"}
}