{
  "type": "Feature",
  "properties": {
    "iso:country":"CA",
    "sg:address":"1023 Royal Ave",
    "sg:city":"New Westminster",
    "sg:classifiers":[
        {
            "category":"Professional",
            "type":"Services"
        }
    ],
    "sg:phone":"+1 604 524 6653",
    "sg:postcode":"V3M 1K3",
    "sg:province":"BC",
    "sg:tags":[
        "automobile",
        "top",
        "upholstery",
        "establishment"
    ],
    "wof:name":"Rags To Riches Top Shop",
    "wof:placetype":"venue"
},
  "geometry": {"coordinates":[-122.918113709,49.2018051147],"type":"Point"}
}