{
  "type": "Feature",
  "properties": {
    "addr:full":"3531 Highway Dr Trail BC V1R 2T9",
    "addr:housenumber":"3531",
    "addr:postcode":"bc v1r 2t9",
    "addr:street":"Highway Dr Trail",
    "iso:country":"CA",
    "sg:address":"3531 Highway Dr",
    "sg:city":"Trail",
    "sg:classifiers":[
        {
            "category":"Personal",
            "type":"Services"
        }
    ],
    "sg:phone":"+1 250 364 2028",
    "sg:postcode":"V1R 2T9",
    "sg:province":"BC",
    "sg:tags":[
        "electrolysis"
    ],
    "wof:name":"Elite Electrolysis",
    "wof:placetype":"venue"
},
  "geometry": {"coordinates":[-117.664726,49.097687],"type":"Point"}
}