{
  "type": "Feature",
  "properties": {
    "addr:full":"261 Mcarthur Ave Vanier ON K1L 6P3",
    "addr:housenumber":"261",
    "addr:postcode":"k1l 6p3",
    "addr:street":"Mcarthur Ave",
    "iso:country":"CA",
    "sg:address":"261 Mcarthur Ave",
    "sg:city":"Vanier",
    "sg:classifiers":[
        {
            "category":"Retail",
            "subcategory":"Veterinary Services",
            "type":"Services"
        }
    ],
    "sg:phone":"+1 613 741 3874",
    "sg:postcode":"K1L 6P3",
    "sg:province":"ON",
    "sg:tags":[
        "veterinarian"
    ],
    "wof:name":"Eastview Animal Hospital",
    "wof:placetype":"venue"
},
  "geometry": {"coordinates":[-75.658379,45.43161],"type":"Point"}
}