{
  "type": "Feature",
  "properties": {
    "addr:full":"4619 Lakelse Ave Terrace BC V8G 1P9",
    "addr:housenumber":"4619",
    "addr:postcode":"v8g 1p9",
    "addr:street":"Lakelse Ave",
    "iso:country":"CA",
    "sg:address":"4619 Lakelse Ave",
    "sg:city":"Terrace",
    "sg:classifiers":[
        {
            "category":"Shopping",
            "subcategory":"Florist",
            "type":"Retail Goods"
        }
    ],
    "sg:phone":"+1 250 635 5920",
    "sg:postcode":"V8G 1P9",
    "sg:province":"BC",
    "wof:name":"Central Flowers",
    "wof:placetype":"venue"
},
  "geometry": {"coordinates":[-128.58819600000001,54.516476],"type":"Point"}
}