{
  "type": "Feature",
  "properties": {
    "addr:full":"13 Mount Pleasant St Brantford ON N3T 1S4",
    "addr:housenumber":"13",
    "addr:postcode":"n3t 1s4",
    "addr:street":"Mount Pleasant St",
    "iso:country":"CA",
    "sg:address":"13 Mount Pleasant St",
    "sg:city":"Brantford",
    "sg:classifiers":[
        {
            "category":"Retail",
            "subcategory":"Auto Repair",
            "type":"Services"
        }
    ],
    "sg:phone":"+1 519 756 6966",
    "sg:postcode":"N3T 1S4",
    "sg:province":"ON",
    "sg:tags":[
        "transmission",
        "automobile",
        "repairing"
    ],
    "wof:name":"Mister Transmission",
    "wof:placetype":"venue"
},
  "geometry": {"coordinates":[-80.27602400000001,43.13176],"type":"Point"}
}