{
  "type": "Feature",
  "properties": {
    "addr:full":"1596 London Line Sarnia ON N7W 1A8",
    "addr:housenumber":"1596",
    "addr:postcode":"n7w 1a8",
    "addr:street":"London Line",
    "iso:country":"CA",
    "sg:address":"1596 London Line",
    "sg:city":"Sarnia",
    "sg:classifiers":[
        {
            "category":"Home & Garden",
            "subcategory":"Carpets & Floor Coverings",
            "type":"Retail Goods"
        }
    ],
    "sg:phone":"+1 519 541 1800",
    "sg:postcode":"N7W 1A8",
    "sg:province":"ON",
    "sg:tags":[
        "material"
    ],
    "wof:name":"Magic Carpet",
    "wof:placetype":"venue"
},
  "geometry": {"coordinates":[-82.3353347778,42.9841346741],"type":"Point"}
}