{
  "type": "Feature",
  "properties": {
    "addr:full":"869 Rue DE Claire-Fontaine # 2 Quebec QC G1R 3A8",
    "addr:housenumber":"869",
    "addr:postcode":"g1r 3a8",
    "addr:street":"Rue De Claire-Fontaine # 2",
    "iso:country":"CA",
    "sg:address":"869 Rue DE Claire-Fontaine # 2",
    "sg:city":"Quebec",
    "sg:classifiers":[
        {
            "category":"Real Estate",
            "subcategory":"Architect",
            "type":"Services"
        }
    ],
    "sg:phone":"+1 418 523 9108",
    "sg:postcode":"G1R 3A8",
    "sg:province":"QC",
    "wof:name":"Marquis, Pierre-A",
    "wof:placetype":"venue"
},
  "geometry": {"coordinates":[-71.221672,46.808414],"type":"Point"}
}