{
  "type": "Feature",
  "properties": {
    "addr:full":"897 Mackenzie Hwy Hay River NT X0E 0R8",
    "addr:housenumber":"897",
    "addr:postcode":"x0e 0r8",
    "addr:street":"Mackenzie Hwy",
    "iso:country":"CA",
    "sg:address":"897 Mackenzie Hwy",
    "sg:city":"Hay River",
    "sg:classifiers":[
        {
            "category":"Travel",
            "subcategory":"Hotels & Motels",
            "type":"Entertainment"
        }
    ],
    "sg:phone":"+1 867 874 6792",
    "sg:postcode":"X0E 0R8",
    "sg:province":"NT",
    "wof:name":"Migrator Motel",
    "wof:placetype":"venue"
},
  "geometry": {"coordinates":[-115.782166,60.82058],"type":"Point"}
}