{
  "type": "Feature",
  "properties": {
    "addr:full":"2430 Crowchild Trail NW Calgary AB T2M 4N5",
    "addr:housenumber":"2430",
    "addr:postcode":"t2m 4n5",
    "addr:street":"Crowchild Trail Nw",
    "iso:country":"CA",
    "sg:address":"2430 Crowchild Trail NW",
    "sg:city":"Calgary",
    "sg:classifiers":[
        {
            "category":"Restaurant",
            "type":"Food & Drink"
        }
    ],
    "sg:phone":"+1 403 282 9278",
    "sg:postcode":"T2M 4N5",
    "sg:province":"AB",
    "wof:name":"Nick's Steak House & Pizza",
    "wof:placetype":"venue"
},
  "geometry": {"coordinates":[-114.117302,51.072006],"type":"Point"}
}