{
  "type": "Feature",
  "properties": {
    "addr:full":"128 Rue Principale Brownsburg-Chatham QC J8G 2Z7",
    "addr:housenumber":"128",
    "addr:postcode":"j8g 2z7",
    "addr:street":"Rue Principale",
    "iso:country":"CA",
    "sg:address":"128 Rue Principale",
    "sg:city":"Brownsburg-Chatham",
    "sg:classifiers":[
        {
            "category":"Home & Garden",
            "subcategory":"Building Materials",
            "type":"Retail Goods"
        }
    ],
    "sg:phone":"+1 450 533 4226",
    "sg:postcode":"J8G 2Z7",
    "sg:province":"QC",
    "sg:tags":[
        "door"
    ],
    "wof:name":"Portes Mirabel Inc",
    "wof:placetype":"venue"
},
  "geometry": {"coordinates":[-74.394188,45.674809],"type":"Point"}
}