{
  "type": "Feature",
  "properties": {
    "addr:full":"506 Deancourt Cres Orleans ON K4A 3G4",
    "addr:housenumber":"506",
    "addr:postcode":"k4a 3g4",
    "addr:street":"Deancourt Cres",
    "iso:country":"CA",
    "sg:address":"506 Deancourt Cres",
    "sg:city":"Orleans",
    "sg:classifiers":[
        {
            "category":"Personal",
            "subcategory":"Beauty Salon",
            "type":"Services"
        }
    ],
    "sg:phone":"+1 613 837 7580",
    "sg:postcode":"K4A 3G4",
    "sg:province":"ON",
    "wof:name":"Muriel Charron Esthetique",
    "wof:placetype":"venue"
},
  "geometry": {"coordinates":[-75.487709,45.479336],"type":"Point"}
}