{
  "type": "Feature",
  "properties": {
    "iso:country":"CA",
    "sg:address":"156 Rue Racine",
    "sg:city":"Loretteville",
    "sg:classifiers":[
        {
            "category":"Personal",
            "subcategory":"Beauty Salon",
            "type":"Services"
        }
    ],
    "sg:phone":"+1 418 843 1620",
    "sg:postcode":"G2B 1E3",
    "sg:province":"QC",
    "wof:name":"Escompte-Coiffe",
    "wof:placetype":"venue"
},
  "geometry": {"coordinates":[-71.35736083979999,46.8533935547],"type":"Point"}
}