{
  "type": "Feature",
  "properties": {
    "addr:full":"185 Plains Rd E # 1 Burlington ON L7T 2C4",
    "addr:housenumber":"185",
    "addr:postcode":"l7t 2c4",
    "addr:street":"Plains Rd E # 1",
    "iso:country":"CA",
    "sg:address":"185 Plains Rd E # 1",
    "sg:city":"Burlington",
    "sg:classifiers":[
        {
            "category":"Professional",
            "subcategory":"Accounting & Tax Preparation",
            "type":"Services"
        }
    ],
    "sg:phone":"+1 905 632 3851",
    "sg:postcode":"L7T 2C4",
    "sg:province":"ON",
    "sg:tags":[
        "accountant",
        "bookkeeping",
        "system"
    ],
    "wof:name":"Cino Accounting & Bookkeeping",
    "wof:placetype":"venue"
},
  "geometry": {"coordinates":[-79.846947,43.311279],"type":"Point"}
}