{
  "type": "Feature",
  "properties": {
    "addr:full":"6414 Boul Monk Montreal QC H4E 3H9",
    "addr:housenumber":"6414",
    "addr:postcode":"h4e 3h9",
    "addr:street":"Boul Monk",
    "iso:country":"CA",
    "sg:address":"6414 Boul Monk",
    "sg:city":"Montreal",
    "sg:classifiers":[
        {
            "category":"Restaurant",
            "type":"Food & Drink"
        }
    ],
    "sg:phone":"+1 514 765 9077",
    "sg:postcode":"H4E 3H9",
    "sg:province":"QC",
    "wof:name":"Shooter's Cafe",
    "wof:placetype":"venue"
},
  "geometry": {"coordinates":[-73.5943984985,45.4546966553],"type":"Point"}
}