{
  "type": "Feature",
  "properties": {
    "iso:country":"CA",
    "sg:address":"70 Bartor Rd",
    "sg:city":"North York",
    "sg:classifiers":[
        {
            "category":"Manufacturing",
            "subcategory":"Furniture",
            "type":"Manufacturing & Wholesale Goods"
        }
    ],
    "sg:phone":"+1 416 743 3380",
    "sg:postcode":"M9M 2G5",
    "sg:province":"ON",
    "wof:name":"Alca Designs Ltd",
    "wof:placetype":"venue"
},
  "geometry": {"coordinates":[-79.523903,43.722858],"type":"Point"}
}