{
  "type": "Feature",
  "properties": {
    "addr:full":"1982 Danforth Ave Toronto ON M4C 1J6",
    "addr:housenumber":"1982",
    "addr:postcode":"m4c 1j6",
    "addr:street":"Danforth Ave",
    "iso:country":"CA",
    "sg:address":"1982 Danforth Ave",
    "sg:city":"Toronto",
    "sg:classifiers":[
        {
            "category":"Restaurant",
            "type":"Food & Drink"
        }
    ],
    "sg:phone":"+1 416 422 4276",
    "sg:postcode":"M4C 1J6",
    "sg:province":"ON",
    "sg:tags":[
        "cafe"
    ],
    "wof:name":"Ilgatto Cafe",
    "wof:placetype":"venue"
},
  "geometry": {"coordinates":[-79.3148422241,43.6853713989],"type":"Point"}
}