{
  "type": "Feature",
  "properties": {
    "iso:country":"CA",
    "sg:city":"Red Deer",
    "sg:classifiers":[
        {
            "category":"Home & Garden",
            "subcategory":"Building Materials",
            "type":"Retail Goods"
        }
    ],
    "sg:phone":"+1 403 346 8611",
    "sg:postcode":"T4N 2R7",
    "sg:province":"AB",
    "sg:tags":[
        "front",
        "plate",
        "window",
        "store"
    ],
    "wof:name":"Leyden's Glass & Mirror Ltd",
    "wof:placetype":"venue"
},
  "geometry": {"coordinates":[-113.815071106,52.2921218872],"type":"Point"}
}