{
  "type": "Feature",
  "properties": {
    "addr:full":"6303A 76 Ave NW Edmonton AB T6B 0A7",
    "addr:housenumber":"6303a",
    "addr:postcode":"t6b 0a7",
    "addr:street":"76 Ave Nw",
    "iso:country":"CA",
    "sg:address":"6303A 76 Ave NW",
    "sg:city":"Edmonton",
    "sg:classifiers":[
        {
            "category":"Bus Charters",
            "type":"Transportation"
        }
    ],
    "sg:phone":"+1 780 465 7374",
    "sg:postcode":"T6B 0A7",
    "sg:province":"AB",
    "sg:tags":[
        "rental"
    ],
    "wof:name":"Cimmaron Passenger Line Inc",
    "wof:placetype":"venue"
},
  "geometry": {"coordinates":[-113.426239,53.512299],"type":"Point"}
}