{
  "type": "Feature",
  "properties": {
    "addr:full":"Calgary AB T2P 3T7",
    "addr:postcode":"t2p 3t7",
    "iso:country":"CA",
    "sg:city":"Calgary",
    "sg:classifiers":[
        {
            "category":"Banks & Credit Unions",
            "subcategory":"Investment Brokerage",
            "type":"Services"
        }
    ],
    "sg:phone":"+1 403 777 1170",
    "sg:postcode":"T2P 3T7",
    "sg:province":"AB",
    "wof:name":"Investment Planning Counsel",
    "wof:placetype":"venue"
},
  "geometry": {"coordinates":[-114.077140808,51.0479660034],"type":"Point"}
}