{
  "type": "Feature",
  "properties": {
    "addr:full":"5925 Cassino Rd Duncan BC V9L 4G5",
    "addr:housenumber":"5925",
    "addr:postcode":"v9l 4g5",
    "addr:street":"Cassino Rd",
    "iso:country":"CA",
    "sg:address":"5925 Cassino Rd",
    "sg:city":"Duncan",
    "sg:classifiers":[
        {
            "category":"Building & Trades",
            "subcategory":"Electrical",
            "type":"Services"
        }
    ],
    "sg:phone":"+1 250 748 9245",
    "sg:postcode":"V9L 4G5",
    "sg:province":"BC",
    "sg:tags":[
        "electric",
        "contractor"
    ],
    "wof:name":"H B Electric Ltd",
    "wof:placetype":"venue"
},
  "geometry": {"coordinates":[-123.707382,48.779095],"type":"Point"}
}