{
  "type": "Feature",
  "properties": {
    "addr:full":"1183 Finch Ave W # 200 North York ON M3J 2G2",
    "addr:housenumber":"1183",
    "addr:postcode":"m3j 2g2",
    "addr:street":"Finch Ave W # 200",
    "iso:country":"CA",
    "sg:address":"1183 Finch Ave W # 200",
    "sg:city":"North York",
    "sg:classifiers":[
        {
            "category":"Professional",
            "subcategory":"Lawyer & Legal Services",
            "type":"Services"
        }
    ],
    "sg:phone":"+1 416 398 9292",
    "sg:postcode":"M3J 2G2",
    "sg:province":"ON",
    "sg:tags":[
        "attorney"
    ],
    "wof:name":"Zanini, Marisa",
    "wof:placetype":"venue"
},
  "geometry": {"coordinates":[-79.48181200000001,43.765377],"type":"Point"}
}