{
  "type": "Feature",
  "properties": {
    "iso:country":"CA",
    "sg:city":"Brockville",
    "sg:classifiers":[
        {
            "category":"Food & Beverages",
            "subcategory":"Specialty",
            "type":"Retail Goods"
        }
    ],
    "sg:phone":"+1 613 342 3131",
    "sg:postcode":"K6V 6C3",
    "sg:province":"ON",
    "sg:tags":[
        "health",
        "diet"
    ],
    "wof:name":"Health & Harmony",
    "wof:placetype":"venue"
},
  "geometry": {"coordinates":[-75.7139129639,44.6079940796],"type":"Point"}
}