{
  "type": "Feature",
  "properties": {
    "iso:country":"CA",
    "sg:address":"6995 Rue Jeanne-Mance",
    "sg:city":"Montreal",
    "sg:classifiers":[
        {
            "category":"Wholesale",
            "subcategory":"Hardware",
            "type":"Manufacturing & Wholesale Goods"
        }
    ],
    "sg:phone":"+1 514 270 5770",
    "sg:postcode":"H3N 1W5",
    "sg:province":"QC",
    "sg:tags":[
        "equipment",
        "energy",
        "solar"
    ],
    "wof:name":"Icp Global Technologies Inc",
    "wof:placetype":"venue"
},
  "geometry": {"coordinates":[-73.618912,45.530235],"type":"Point"}
}