{
  "type": "Feature",
  "properties": {
    "addr:full":"6995 Rue Jeanne-Mance Montreal QC H3N 1W5",
    "addr:housenumber":"6995",
    "addr:postcode":"h3n 1w5",
    "addr:street":"Rue Jeanne-Mance",
    "iso:country":"CA",
    "sg:address":"6995 Rue Jeanne-Mance",
    "sg:city":"Montreal",
    "sg:classifiers":[
        {
            "category":"Wholesale",
            "subcategory":"Hardware",
            "type":"Manufacturing & Wholesale Goods"
        }
    ],
    "sg:phone":"+1 514 270 5770",
    "sg:postcode":"H3N 1W5",
    "sg:province":"QC",
    "sg:tags":[
        "equipment",
        "energy",
        "solar"
    ],
    "wof:name":"Icp Global Technologies Inc",
    "wof:placetype":"venue"
},
  "geometry": {"coordinates":[-73.61891199999999,45.530235],"type":"Point"}
}