{
  "type": "Feature",
  "properties": {
    "addr:full":"4850 Irmin St Burnaby BC V5J 1Y2",
    "addr:housenumber":"4850",
    "addr:postcode":"v5j 1y2",
    "addr:street":"Irmin St",
    "iso:country":"CA",
    "sg:address":"4850 Irmin St",
    "sg:city":"Burnaby",
    "sg:classifiers":[
        {
            "category":"Education",
            "subcategory":"School",
            "type":"Public Place"
        }
    ],
    "sg:phone":"+1 604 664 8784",
    "sg:postcode":"V5J 1Y2",
    "sg:province":"BC",
    "wof:name":"Nelson Elementary School",
    "wof:placetype":"venue"
},
  "geometry": {"coordinates":[-122.99485,49.215595],"type":"Point"}
}