{
  "type": "Feature",
  "properties": {
    "addr:full":"1092 107th St North Battleford SK S9A 1Z1",
    "addr:housenumber":"1092",
    "addr:postcode":"s9a 1z1",
    "addr:street":"107Th St",
    "iso:country":"CA",
    "sg:address":"1092 107th St",
    "sg:city":"North Battleford",
    "sg:classifiers":[
        {
            "category":"Health Services",
            "subcategory":"Clinic",
            "type":"Services"
        }
    ],
    "sg:phone":"+1 306 446 6445",
    "sg:postcode":"S9A 1Z1",
    "sg:province":"SK",
    "sg:tags":[
        "home"
    ],
    "wof:name":"Battlefords District Home Care",
    "wof:placetype":"venue"
},
  "geometry": {"coordinates":[-108.28874999999999,52.773411],"type":"Point"}
}