{
  "type": "Feature",
  "properties": {
    "addr:full":"Scarborough ON M1X 1M9",
    "addr:postcode":"m1x 1m9",
    "iso:country":"CA",
    "sg:city":"Scarborough",
    "sg:classifiers":[
        {
            "category":"Building & Trades",
            "subcategory":"Construction",
            "type":"Services"
        }
    ],
    "sg:phone":"+1 416 291 2900",
    "sg:postcode":"M1X 1M9",
    "sg:province":"ON",
    "sg:tags":[
        "general",
        "contractor"
    ],
    "wof:name":"Noran Industries Ltd",
    "wof:placetype":"venue"
},
  "geometry": {"coordinates":[-79.247658,43.827545],"type":"Point"}
}