{
  "type": "Feature",
  "properties": {
    "addr:full":"1200 248 Rd Goodlow BC V0C 1S0",
    "addr:housenumber":"1200",
    "addr:postcode":"bc v0c 1s0",
    "addr:street":"248 Rd",
    "iso:country":"CA",
    "sg:address":"1200 248 Rd",
    "sg:city":"Goodlow",
    "sg:classifiers":[
        {
            "category":"Mining & Drilling",
            "type":"Manufacturing & Wholesale Goods"
        }
    ],
    "sg:phone":"+1 250 781 3315",
    "sg:postcode":"V0C 1S0",
    "sg:province":"BC",
    "sg:tags":[
        "company",
        "oil"
    ],
    "wof:name":"Imperial Oil Resources Ltd",
    "wof:placetype":"venue"
},
  "geometry": {"coordinates":[-120.071830749,56.3336753845],"type":"Point"}
}