{
  "type": "Feature",
  "properties": {
    "addr:full":"961 Meadow Lane Cavan ON L0A 1C0",
    "addr:housenumber":"961",
    "addr:postcode":"l0a 1c0",
    "addr:street":"Meadow Lane",
    "iso:country":"CA",
    "sg:address":"961 Meadow Lane",
    "sg:city":"Cavan",
    "sg:classifiers":[
        {
            "category":"Wholesale",
            "subcategory":"Electrical",
            "type":"Manufacturing & Wholesale Goods"
        }
    ],
    "sg:phone":"+1 705 799 1401",
    "sg:postcode":"L0A 1C0",
    "sg:province":"ON",
    "sg:tags":[
        "fire",
        "equipment",
        "alarm",
        "protection",
        "system"
    ],
    "wof:name":"Mcc Fire Equipment",
    "wof:placetype":"venue"
},
  "geometry": {"coordinates":[-78.47023799999999,44.203602],"type":"Point"}
}