{
  "type": "Feature",
  "properties": {
    "iso:country":"CA",
    "sg:address":"36 Elora St S",
    "sg:city":"Harriston",
    "sg:classifiers":[
        {
            "category":"Personal",
            "subcategory":"Beauty Salon",
            "type":"Services"
        }
    ],
    "sg:phone":"+1 519 338 2101",
    "sg:postcode":"N0G 1Z0",
    "sg:province":"ON",
    "wof:name":"Reica's Hair Styling",
    "wof:placetype":"venue"
},
  "geometry": {"coordinates":[-80.8702011108,43.9124412537],"type":"Point"}
}