{
  "type": "Feature",
  "properties": {
    "addr:full":"1560 Rue Laurier Rockland ON K4K 1P7",
    "addr:housenumber":"1560",
    "addr:postcode":"k4k 1p7",
    "addr:street":"Rue Laurier",
    "iso:country":"CA",
    "sg:address":"1560 Rue Laurier",
    "sg:city":"Rockland",
    "sg:classifiers":[
        {
            "category":"Government",
            "subcategory":"Office",
            "type":"Public Place"
        }
    ],
    "sg:phone":"+1 613 446 5853",
    "sg:postcode":"K4K 1P7",
    "sg:province":"ON",
    "sg:tags":[
        "village"
    ],
    "wof:name":"Rockland Day Care Ctr",
    "wof:placetype":"venue"
},
  "geometry": {"coordinates":[-75.28894042970001,45.5509223938],"type":"Point"}
}