{
  "type": "Feature",
  "properties": {
    "addr:full":"2130 Airport Dr Saskatoon SK S7L 6M6",
    "addr:housenumber":"2130",
    "addr:postcode":"s7l 6m6",
    "addr:street":"Airport Dr",
    "iso:country":"CA",
    "sg:address":"2130 Airport Dr",
    "sg:city":"Saskatoon",
    "sg:classifiers":[
        {
            "category":"Government",
            "subcategory":"Office",
            "type":"Public Place"
        }
    ],
    "sg:phone":"+1 306 975 4755",
    "sg:postcode":"S7L 6M6",
    "sg:province":"SK",
    "wof:name":"Canada Customs & Revenue",
    "wof:placetype":"venue"
},
  "geometry": {"coordinates":[-106.6866,52.156998],"type":"Point"}
}