{
  "type": "Feature",
  "properties": {
    "addr:full":"8245 Rue Notre-Dame E Montreal QC H1L 3L2",
    "addr:housenumber":"8245",
    "addr:postcode":"h1l 3l2",
    "addr:street":"Rue Notre-Dame E",
    "iso:country":"CA",
    "sg:address":"8245 Rue Notre-Dame E",
    "sg:city":"Montreal",
    "sg:classifiers":[
        {
            "category":"Food & Beverages",
            "subcategory":"Liquor & Beverages",
            "type":"Retail Goods"
        }
    ],
    "sg:phone":"+1 514 351 0636",
    "sg:postcode":"H1L 3L2",
    "sg:province":"QC",
    "sg:tags":[
        "store"
    ],
    "wof:name":"Saq",
    "wof:placetype":"venue"
},
  "geometry": {"coordinates":[-73.51085662840001,45.5929298401],"type":"Point"}
}