{
  "type": "Feature",
  "properties": {
    "addr:full":"North York ON M6A 3B6",
    "addr:postcode":"m6a 3b6",
    "iso:country":"CA",
    "sg:city":"North York",
    "sg:classifiers":[
        {
            "category":"Building & Trades",
            "subcategory":"Construction",
            "type":"Services"
        }
    ],
    "sg:phone":"+1 416 785 3243",
    "sg:postcode":"M6A 3B6",
    "sg:province":"ON",
    "sg:tags":[
        "masonry",
        "contractor"
    ],
    "wof:name":"Gimar Masonry Contractors",
    "wof:placetype":"venue"
},
  "geometry": {"coordinates":[-79.4580993652,43.7135391235],"type":"Point"}
}