{
  "type": "Feature",
  "properties": {
    "addr:full":"East York ON M4G 2K2",
    "addr:postcode":"m4g 2k2",
    "iso:country":"CA",
    "sg:city":"East York",
    "sg:classifiers":[
        {
            "category":"Wholesale",
            "subcategory":"Durable Goods & Equipment",
            "type":"Manufacturing & Wholesale Goods"
        }
    ],
    "sg:phone":"+1 416 487 5338",
    "sg:postcode":"M4G 2K2",
    "sg:province":"ON",
    "sg:tags":[
        "importer"
    ],
    "wof:name":"Thomes Limited",
    "wof:placetype":"venue"
},
  "geometry": {"coordinates":[-79.37687683110001,43.7112731934],"type":"Point"}
}