{
  "type": "Feature",
  "properties": {
    "addr:full":"West Vancouver BC V7V 1P8",
    "addr:postcode":"v7v 1p8",
    "iso:country":"CA",
    "sg:city":"West Vancouver",
    "sg:classifiers":[
        {
            "category":"Wholesale",
            "subcategory":"Non-durable Goods",
            "type":"Manufacturing & Wholesale Goods"
        }
    ],
    "sg:phone":"+1 604 925 8715",
    "sg:postcode":"V7V 1P8",
    "sg:province":"BC",
    "sg:tags":[
        "advertising"
    ],
    "wof:name":"U P Unique Promotion",
    "wof:placetype":"venue"
},
  "geometry": {"coordinates":[-123.16130099999999,49.329868],"type":"Point"}
}