{
  "type": "Feature",
  "properties": {
    "addr:full":"4762 Boul Samson # 105 Laval QC H7W 2H7",
    "addr:housenumber":"4762",
    "addr:postcode":"h7w 2h7",
    "addr:street":"Boul Samson # 105",
    "iso:country":"CA",
    "sg:address":"4762 Boul Samson # 105",
    "sg:city":"Laval",
    "sg:classifiers":[
        {
            "category":"Insurance",
            "subcategory":"Insurance Agent",
            "type":"Services"
        }
    ],
    "sg:phone":"+1 450 681 1010",
    "sg:postcode":"H7W 2H7",
    "sg:province":"QC",
    "wof:name":"Allstate Insurance",
    "wof:placetype":"venue"
},
  "geometry": {"coordinates":[-73.7611694336,45.5277671814],"type":"Point"}
}