{
  "type": "Feature",
  "properties": {
    "iso:country":"CA",
    "sg:address":"199 Toryork Dr",
    "sg:city":"North York",
    "sg:classifiers":[
        {
            "category":"Building & Trades",
            "subcategory":"Construction",
            "type":"Services"
        }
    ],
    "sg:phone":"+1 416 749 3391",
    "sg:postcode":"M9L 1X9",
    "sg:province":"ON",
    "sg:tags":[
        "tile",
        "dealer"
    ],
    "wof:name":"Dan Mor Tile & Marble",
    "wof:placetype":"venue"
},
  "geometry": {"coordinates":[-79.5595550537,43.7604484558],"type":"Point"}
}