{
  "type": "Feature",
  "properties": {
    "addr:full":"10525 Boul DE L'Ormiere Quebec QC G2B 3L2",
    "addr:housenumber":"10525",
    "addr:postcode":"g2b 3l2",
    "addr:street":"Boul De L'Ormiere",
    "iso:country":"CA",
    "sg:address":"10525 Boul DE L'Ormiere",
    "sg:city":"Quebec",
    "sg:classifiers":[
        {
            "category":"Personal",
            "subcategory":"Beauty Salon",
            "type":"Services"
        }
    ],
    "sg:phone":"+1 418 842 0191",
    "sg:postcode":"G2B 3L2",
    "sg:province":"QC",
    "wof:name":"Salon Petit Pier Enr",
    "wof:placetype":"venue"
},
  "geometry": {"coordinates":[-71.339935,46.824921],"type":"Point"}
}