{
  "type": "Feature",
  "properties": {
    "addr:full":"8836 62 Ave NW Edmonton AB T6E 0C8",
    "addr:housenumber":"8836",
    "addr:postcode":"t6e 0c8",
    "addr:street":"62 Ave Nw",
    "iso:country":"CA",
    "sg:address":"8836 62 Ave NW",
    "sg:city":"Edmonton",
    "sg:classifiers":[
        {
            "category":"Retail",
            "subcategory":"Auto Repair",
            "type":"Services"
        }
    ],
    "sg:phone":"+1 780 469 3996",
    "sg:postcode":"T6E 0C8",
    "sg:province":"AB",
    "sg:tags":[
        "body",
        "automobile",
        "painting"
    ],
    "wof:name":"Dan's Auto Body Ltd",
    "wof:placetype":"venue"
},
  "geometry": {"coordinates":[-113.463768,53.498585],"type":"Point"}
}