{
  "type": "Feature",
  "properties": {
    "addr:full":"New Hwy 6 Owen Sound ON N4K 5P1",
    "addr:postcode":"n4k 5p1",
    "addr:street":"New Hwy 6",
    "iso:country":"CA",
    "sg:address":"New Hwy 6",
    "sg:city":"Owen Sound",
    "sg:classifiers":[
        {
            "category":"Autos & Motor Vehicles",
            "subcategory":"Recreational Vehicle Sales",
            "type":"Retail Goods"
        }
    ],
    "sg:phone":"+1 519 372 3485",
    "sg:postcode":"N4K 5P1",
    "sg:province":"ON",
    "wof:name":"Springmount Rv Ctr",
    "wof:placetype":"venue"
},
  "geometry": {"coordinates":[-80.9426040649,44.5648765564],"type":"Point"}
}