{
  "type": "Feature",
  "properties": {
    "addr:full":"1926 Rue Sainte-Helene Longueuil QC J4K 3T3",
    "addr:housenumber":"1926",
    "addr:postcode":"j4k 3t3",
    "addr:street":"Rue Sainte-Helene",
    "iso:country":"CA",
    "sg:address":"1926 Rue Sainte-Helene",
    "sg:city":"Longueuil",
    "sg:classifiers":[
        {
            "category":"Health Services",
            "subcategory":"Doctor",
            "type":"Services"
        }
    ],
    "sg:phone":"+1 450 928 4650",
    "sg:postcode":"J4K 3T3",
    "sg:province":"QC",
    "sg:tags":[
        "clinic"
    ],
    "wof:name":"Ste Helene Clinique",
    "wof:placetype":"venue"
},
  "geometry": {"coordinates":[-73.49021148680001,45.5149307251],"type":"Point"}
}