{
  "type": "Feature",
  "properties": {
    "addr:full":"70 Rue Adrien-Robert Hull QC J8Y 3S2",
    "addr:housenumber":"70",
    "addr:postcode":"j8y 3s2",
    "addr:street":"Rue Adrien-Robert",
    "iso:country":"CA",
    "sg:address":"70 Rue Adrien-Robert",
    "sg:city":"Hull",
    "sg:classifiers":[
        {
            "category":"Manufacturing",
            "subcategory":"Tools & Machinery",
            "type":"Manufacturing & Wholesale Goods"
        }
    ],
    "sg:phone":"+1 819 776 5548",
    "sg:postcode":"J8Y 3S2",
    "sg:province":"QC",
    "sg:tags":[
        "machine",
        "shop"
    ],
    "wof:name":"Eastview Machine Shop Enr",
    "wof:placetype":"venue"
},
  "geometry": {"coordinates":[-75.7341308594,45.4566078186],"type":"Point"}
}