{
  "type": "Feature",
  "properties": {
    "addr:full":"Edmonton AB T6E 5P3",
    "addr:postcode":"t6e 5p3",
    "iso:country":"CA",
    "sg:city":"Edmonton",
    "sg:classifiers":[
        {
            "category":"Building & Trades",
            "subcategory":"Construction",
            "type":"Services"
        }
    ],
    "sg:phone":"+1 780 439 4519",
    "sg:postcode":"T6E 5P3",
    "sg:province":"AB",
    "sg:tags":[
        "contractor",
        "dry wall",
        "general"
    ],
    "wof:name":"B Wright Drywall Inc",
    "wof:placetype":"venue"
},
  "geometry": {"coordinates":[-113.483039856,53.4849967957],"type":"Point"}
}