{
  "type": "Feature",
  "properties": {
    "addr:full":"32 Cromer Ave Grand Falls-Windsor NL A2A 1X2",
    "addr:housenumber":"32",
    "addr:postcode":"a2a 1x2",
    "addr:street":"Cromer Ave",
    "iso:country":"CA",
    "sg:address":"32 Cromer Ave",
    "sg:city":"Grand Falls-Windsor",
    "sg:classifiers":[
        {
            "category":"Restaurant",
            "type":"Food & Drink"
        }
    ],
    "sg:phone":"+1 709 489 4002",
    "sg:postcode":"A2A 1X2",
    "sg:province":"NL",
    "wof:name":"Mary Brown's Fried Chicken",
    "wof:placetype":"venue"
},
  "geometry": {"coordinates":[-55.654366,48.954113],"type":"Point"}
}