{
  "type": "Feature",
  "properties": {
    "addr:full":"4617 63 St Red Deer AB T4N 7A6",
    "addr:housenumber":"4617",
    "addr:postcode":"t4n 7a6",
    "addr:street":"63 St",
    "iso:country":"CA",
    "sg:address":"4617 63 St",
    "sg:city":"Red Deer",
    "sg:classifiers":[
        {
            "category":"Manufacturing",
            "subcategory":"Metals",
            "type":"Manufacturing & Wholesale Goods"
        }
    ],
    "sg:phone":"+1 403 343 3222",
    "sg:postcode":"T4N 7A6",
    "sg:province":"AB",
    "sg:tags":[
        "coating",
        "powder"
    ],
    "wof:name":"Metalstrip & Coatings Inc",
    "wof:placetype":"venue"
},
  "geometry": {"coordinates":[-113.805603027,52.2860412598],"type":"Point"}
}