{
  "type": "Feature",
  "properties": {
    "addr:full":"5964 Main St Niagara Falls ON L2G 5Z8",
    "addr:housenumber":"5964",
    "addr:postcode":"l2g 5z8",
    "addr:street":"Main St",
    "iso:country":"CA",
    "sg:address":"5964 Main St",
    "sg:city":"Niagara Falls",
    "sg:classifiers":[
        {
            "category":"Wholesale",
            "subcategory":"Hardware",
            "type":"Manufacturing & Wholesale Goods"
        }
    ],
    "sg:phone":"+1 905 356 8151",
    "sg:postcode":"L2G 5Z8",
    "sg:province":"ON",
    "sg:tags":[
        "fastener"
    ],
    "wof:name":"Bickle Main Ind Supply",
    "wof:placetype":"venue"
},
  "geometry": {"coordinates":[-79.0921173096,43.0883331299],"type":"Point"}
}