{
  "type": "Feature",
  "properties": {
    "addr:full":"450 Boul Poliquin # 523 Sorel-Tracy QC J3P 7R5",
    "addr:housenumber":"450",
    "addr:postcode":"j3p 7r5",
    "addr:street":"Boul Poliquin # 523",
    "iso:country":"CA",
    "sg:address":"450 Boul Poliquin # 523",
    "sg:city":"Sorel-Tracy",
    "sg:classifiers":[
        {
            "category":"Shopping",
            "subcategory":"Clothing, Apparel, & Fashions",
            "type":"Retail Goods"
        }
    ],
    "sg:phone":"+1 450 742 1747",
    "sg:postcode":"J3P 7R5",
    "sg:province":"QC",
    "sg:tags":[
        "item",
        "boutique"
    ],
    "wof:name":"Suzy Shier",
    "wof:placetype":"venue"
},
  "geometry": {"coordinates":[-73.0897140503,46.0351371765],"type":"Point"}
}