{
  "type": "Feature",
  "properties": {
    "iso:country":"CA",
    "sg:city":"Saint-Amable",
    "sg:classifiers":[
        {
            "category":"Professional",
            "subcategory":"Advertising",
            "type":"Services"
        }
    ],
    "sg:phone":"+1 450 922 5019",
    "sg:postcode":"J0L 1N0",
    "sg:province":"QC",
    "wof:name":"Promotion Msg",
    "wof:placetype":"venue"
},
  "geometry": {"coordinates":[-73.2980422974,45.6502418518],"type":"Point"}
}