{
  "type": "Feature",
  "properties": {
    "iso:country":"CA",
    "sg:address":"18 Bolger Dr",
    "sg:city":"Charlottetown",
    "sg:classifiers":[
        {
            "category":"Manufacturing",
            "subcategory":"Glass & Minerals",
            "type":"Manufacturing & Wholesale Goods"
        }
    ],
    "sg:phone":"+1 902 629 5000",
    "sg:postcode":"C1A 7W2",
    "sg:province":"PE",
    "sg:tags":[
        "concrete",
        "brick",
        "block",
        "form"
    ],
    "wof:name":"Mac Pherson Concrete Form",
    "wof:placetype":"venue"
},
  "geometry": {"coordinates":[-63.1096496582,46.2621231079],"type":"Point"}
}