{
  "type": "Feature",
  "properties": {
    "iso:country":"CA",
    "sg:address":"140 Dundas St",
    "sg:city":"London",
    "sg:classifiers":[
        {
            "category":"Shopping",
            "subcategory":"Department Store",
            "type":"Retail Goods"
        }
    ],
    "sg:phone":"+1 519 645 1861",
    "sg:postcode":"N6A 1G1",
    "sg:province":"ON",
    "wof:name":"Red Apple Clearance Ctr",
    "wof:placetype":"venue"
},
  "geometry": {"coordinates":[-81.250725,42.983566],"type":"Point"}
}