{
  "type": "Feature",
  "properties": {
    "addr:full":"110 Rte Clemville Port-Daniel QC G0C 2N0",
    "addr:housenumber":"110",
    "addr:postcode":"g0c 2n0",
    "addr:street":"Rte Clemville",
    "iso:country":"CA",
    "sg:address":"110 Rte Clemville",
    "sg:city":"Port-Daniel",
    "sg:classifiers":[
        {
            "category":"Education",
            "subcategory":"School",
            "type":"Public Place"
        }
    ],
    "sg:phone":"+1 418 396 5343",
    "sg:postcode":"G0C 2N0",
    "sg:province":"QC",
    "wof:name":"Ecole Le Phare",
    "wof:placetype":"venue"
},
  "geometry": {"coordinates":[-64.981041,48.165943],"type":"Point"}
}