{
  "type": "Feature",
  "properties": {
    "addr:full":"Montreal QC H2B 1K1",
    "addr:postcode":"h2b 1k1",
    "iso:country":"CA",
    "sg:city":"Montreal",
    "sg:classifiers":[
        {
            "category":"Health Services",
            "subcategory":"Doctor",
            "type":"Services"
        }
    ],
    "sg:phone":"+1 514 383 8389",
    "sg:postcode":"H2B 1K1",
    "sg:province":"QC",
    "sg:tags":[
        "physiotherapist",
        "clinic"
    ],
    "wof:name":"A LA Clinique Physio Extra",
    "wof:placetype":"venue"
},
  "geometry": {"coordinates":[-73.65078699999999,45.571949],"type":"Point"}
}