{
  "type": "Feature",
  "properties": {
    "addr:full":"22811 Dewdney Trunk Rd Maple Ridge BC V2X 9J7",
    "addr:housenumber":"22811",
    "addr:postcode":"v2x 9j7",
    "addr:street":"Dewdney Trunk Rd",
    "iso:country":"CA",
    "sg:address":"22811 Dewdney Trunk Rd",
    "sg:city":"Maple Ridge",
    "sg:classifiers":[
        {
            "category":"Insurance",
            "subcategory":"Insurance Agent",
            "type":"Services"
        }
    ],
    "sg:phone":"+1 604 463 3999",
    "sg:postcode":"V2X 9J7",
    "sg:province":"BC",
    "wof:name":"Icbc",
    "wof:placetype":"venue"
},
  "geometry": {"coordinates":[-122.58983600000001,49.220577],"type":"Point"}
}