{
  "type": "Feature",
  "properties": {
    "addr:full":"1340 Ch Lac Paquin Val-David QC J0T 2N0",
    "addr:housenumber":"1340",
    "addr:postcode":"j0t 2n0",
    "addr:street":"Ch Lac Paquin",
    "iso:country":"CA",
    "sg:address":"1340 Ch Lac Paquin",
    "sg:city":"Val-David",
    "sg:classifiers":[
        {
            "category":"Travel",
            "subcategory":"Hotels & Motels",
            "type":"Entertainment"
        }
    ],
    "sg:phone":"+1 819 322 2026",
    "sg:postcode":"J0T 2N0",
    "sg:province":"QC",
    "wof:name":"Parker's Lodge",
    "wof:placetype":"venue"
},
  "geometry": {"coordinates":[-74.2049331665,46.0316238403],"type":"Point"}
}