{
  "type": "Feature",
  "properties": {
    "addr:full":"233 Carlaw Ave Toronto ON M4M 3N6",
    "addr:housenumber":"233",
    "addr:postcode":"m4m 3n6",
    "addr:street":"Carlaw Ave",
    "iso:country":"CA",
    "sg:address":"233 Carlaw Ave",
    "sg:city":"Toronto",
    "sg:classifiers":[
        {
            "category":"Manufacturing",
            "subcategory":"Apparel",
            "type":"Manufacturing & Wholesale Goods"
        }
    ],
    "sg:phone":"+1 416 462 1850",
    "sg:postcode":"M4M 3N6",
    "sg:province":"ON",
    "sg:tags":[
        "clothing"
    ],
    "wof:name":"Dash Manufacturing Ltd",
    "wof:placetype":"venue"
},
  "geometry": {"coordinates":[-79.3403625488,43.6621742249],"type":"Point"}
}