{
  "type": "Feature",
  "properties": {
    "addr:full":"1801 Hall St Nelson BC V1L 2A5",
    "addr:housenumber":"1801",
    "addr:postcode":"bc v1l 2a5",
    "addr:street":"Hall St",
    "iso:country":"CA",
    "sg:address":"1801 Hall St",
    "sg:city":"Nelson",
    "sg:classifiers":[
        {
            "category":"Restaurant",
            "type":"Food & Drink"
        }
    ],
    "sg:phone":"+1 250 352 6115",
    "sg:postcode":"V1L 2A5",
    "sg:province":"BC",
    "sg:tags":[
        "caterer"
    ],
    "wof:name":"Alligator Pie Catering",
    "wof:placetype":"venue"
},
  "geometry": {"coordinates":[-117.282448,49.483047],"type":"Point"}
}