{
  "type": "Feature",
  "properties": {
    "addr:full":"1733 Ch DE LA Riviere Sainte-Clotilde-DE-Chateauguay QC J0L 1W0",
    "addr:housenumber":"1733",
    "addr:postcode":"j0l 1w0",
    "addr:street":"Ch De La;Sainte-Clotilde-De-Chateauguay",
    "iso:country":"CA",
    "sg:address":"1733 Ch DE LA Riviere",
    "sg:city":"Sainte-Clotilde-DE-Chateauguay",
    "sg:classifiers":[
        {
            "category":"Retail",
            "subcategory":"Auto Repair",
            "type":"Services"
        }
    ],
    "sg:phone":"+1 450 826 3500",
    "sg:postcode":"J0L 1W0",
    "sg:province":"QC",
    "sg:tags":[
        "repairing",
        "automobile"
    ],
    "wof:name":"Garage Ravary & Fils Enr",
    "wof:placetype":"venue"
},
  "geometry": {"coordinates":[-73.657478,45.184586],"type":"Point"}
}