{
  "type": "Feature",
  "properties": {
    "addr:full":"8 Boul Saint-Jean-Baptiste Chateauguay QC J6K 3A2",
    "addr:housenumber":"8",
    "addr:postcode":"j6k 3a2",
    "addr:street":"Boul Saint-Jean-Baptiste",
    "iso:country":"CA",
    "sg:address":"8 Boul Saint-Jean-Baptiste",
    "sg:city":"Chateauguay",
    "sg:classifiers":[
        {
            "category":"Retail",
            "subcategory":"Auto Repair",
            "type":"Services"
        }
    ],
    "sg:phone":"+1 450 691 1803",
    "sg:postcode":"J6K 3A2",
    "sg:province":"QC",
    "sg:tags":[
        "repairing",
        "automobile"
    ],
    "wof:name":"Garage DE Castris Enr",
    "wof:placetype":"venue"
},
  "geometry": {"coordinates":[-73.7101593018,45.3678741455],"type":"Point"}
}