{
  "type": "Feature",
  "properties": {
    "addr:full":"85 Lynden Rd Brantford ON N3R 7J9",
    "addr:housenumber":"85",
    "addr:postcode":"n3r 7j9",
    "addr:street":"Lynden Rd",
    "iso:country":"CA",
    "sg:address":"85 Lynden Rd",
    "sg:city":"Brantford",
    "sg:classifiers":[
        {
            "category":"Autos & Motor Vehicles",
            "subcategory":"Automobile Sales",
            "type":"Retail Goods"
        }
    ],
    "sg:phone":"+1 519 756 6191",
    "sg:postcode":"N3R 7J9",
    "sg:province":"ON",
    "sg:tags":[
        "car",
        "dealer"
    ],
    "wof:name":"Brant County Ford Sales Ltd",
    "wof:placetype":"venue"
},
  "geometry": {"coordinates":[-80.24292,43.173378],"type":"Point"}
}