{
  "type": "Feature",
  "properties": {
    "addr:full":"734 King George Hwy Miramichi NB E1V 1P8",
    "addr:housenumber":"734",
    "addr:postcode":"e1v 1p8",
    "addr:street":"King George Hwy",
    "iso:country":"CA",
    "sg:address":"734 King George Hwy",
    "sg:city":"Miramichi",
    "sg:classifiers":[
        {
            "category":"Manufacturing",
            "subcategory":"Electronics",
            "type":"Manufacturing & Wholesale Goods"
        }
    ],
    "sg:phone":"+1 506 622 8890",
    "sg:postcode":"E1V 1P8",
    "sg:province":"NB",
    "sg:tags":[
        "equipment",
        "satellite",
        "burglar",
        "alarm",
        "system"
    ],
    "wof:name":"Sky-Tec Satellite",
    "wof:placetype":"venue"
},
  "geometry": {"coordinates":[-65.56244700000001,47.009499],"type":"Point"}
}