{
  "type": "Feature",
  "properties": {
    "addr:full":"10104 105th Ave Fairview AB T0H 1L0",
    "addr:housenumber":"10104",
    "addr:postcode":"t0h 1l0",
    "addr:street":"105Th Ave",
    "iso:country":"CA",
    "sg:address":"10104 105th Ave",
    "sg:city":"Fairview",
    "sg:classifiers":[
        {
            "category":"Travel",
            "subcategory":"Campground",
            "type":"Entertainment"
        }
    ],
    "sg:phone":"+1 780 835 5577",
    "sg:postcode":"T0H 1L0",
    "sg:province":"AB",
    "wof:name":"Fairview Rv Park & Storage",
    "wof:placetype":"venue"
},
  "geometry": {"coordinates":[-118.366035461,56.0697174072],"type":"Point"}
}