{
  "type": "Feature",
  "properties": {
    "addr:full":"1260 Rae St Regina SK S4T 2C1",
    "addr:housenumber":"1260",
    "addr:postcode":"s4t 2c1",
    "addr:street":"Rae St",
    "iso:country":"CA",
    "sg:address":"1260 Rae St",
    "sg:city":"Regina",
    "sg:classifiers":[
        {
            "category":"Professional",
            "subcategory":"Management & Consulting",
            "type":"Services"
        }
    ],
    "sg:phone":"+1 306 781 6001",
    "sg:postcode":"S4T 2C1",
    "sg:province":"SK",
    "sg:tags":[
        "marketing",
        "publishing",
        "consultant"
    ],
    "wof:name":"Between the Lines Design",
    "wof:placetype":"venue"
},
  "geometry": {"coordinates":[-104.621299744,50.4589385986],"type":"Point"}
}