{
  "type": "Feature",
  "properties": {
    "addr:full":"6175 Rue Sherbrooke O Montreal QC H4B 1L9",
    "addr:housenumber":"6175",
    "addr:postcode":"h4b 1l9",
    "addr:street":"Rue Sherbrooke O",
    "iso:country":"CA",
    "sg:address":"6175 Rue Sherbrooke O",
    "sg:city":"Montreal",
    "sg:classifiers":[
        {
            "category":"Food & Beverages",
            "subcategory":"Fruits & Vegetables",
            "type":"Retail Goods"
        }
    ],
    "sg:phone":"+1 514 484 0820",
    "sg:postcode":"H4B 1L9",
    "sg:province":"QC",
    "sg:tags":[
        "produce"
    ],
    "wof:name":"Fruiterie Shaana",
    "wof:placetype":"venue"
},
  "geometry": {"coordinates":[-73.545998,45.578423],"type":"Point"}
}