{
  "type": "Feature",
  "properties": {
    "addr:full":"389 Catherine St Dalhousie NB E8C 1K1",
    "addr:housenumber":"389",
    "addr:postcode":"e8c 1k1",
    "addr:street":"Catherine St",
    "iso:country":"CA",
    "sg:address":"389 Catherine St",
    "sg:city":"Dalhousie",
    "sg:classifiers":[
        {
            "category":"Social Services",
            "subcategory":"Adult Care",
            "type":"Services"
        }
    ],
    "sg:phone":"+1 506 684 3650",
    "sg:postcode":"E8C 1K1",
    "sg:province":"NB",
    "sg:tags":[
        "home",
        "rest",
        "residential"
    ],
    "wof:name":"Foyer DE Soins Speciaux",
    "wof:placetype":"venue"
},
  "geometry": {"coordinates":[-66.371925354,48.061050415],"type":"Point"}
}