{
  "type": "Feature",
  "properties": {
    "addr:full":"Barrington NS B0W 1E0",
    "addr:postcode":"b0w 1e0",
    "iso:country":"CA",
    "sg:city":"Barrington",
    "sg:classifiers":[
        {
            "category":"Organizations",
            "subcategory":"Religious Organization",
            "type":"Services"
        }
    ],
    "sg:phone":"+1 902 637 2452",
    "sg:postcode":"B0W 1E0",
    "sg:province":"NS",
    "sg:tags":[
        "church"
    ],
    "wof:name":"Barrington United Church",
    "wof:placetype":"venue"
},
  "geometry": {"coordinates":[-65.563225,43.563828],"type":"Point"}
}