{
  "type": "Feature",
  "properties": {
    "iso:country":"CA",
    "sg:address":"1330 Jerseyville Rd W",
    "sg:city":"Jerseyville",
    "sg:classifiers":[
        {
            "category":"Manufacturing",
            "subcategory":"Tools & Machinery",
            "type":"Manufacturing & Wholesale Goods"
        }
    ],
    "sg:phone":"+1 905 304 8171",
    "sg:postcode":"L0R 1R0",
    "sg:province":"ON",
    "wof:name":"Surfmet Canada Inc",
    "wof:placetype":"venue"
},
  "geometry": {"coordinates":[-80.1041793823,43.2004318237],"type":"Point"}
}