{
  "type": "Feature",
  "properties": {
    "addr:full":"8 West St S Huntsville ON P1H 1P2",
    "addr:housenumber":"8",
    "addr:postcode":"p1h 1p2",
    "addr:street":"West St S",
    "iso:country":"CA",
    "sg:address":"8 West St S",
    "sg:city":"Huntsville",
    "sg:classifiers":[
        {
            "category":"Utilities",
            "subcategory":"Refuse",
            "type":"Services"
        }
    ],
    "sg:phone":"+1 705 789 1233",
    "sg:postcode":"P1H 1P2",
    "sg:province":"ON",
    "sg:tags":[
        "garbage",
        "collection"
    ],
    "wof:name":"Muskoka Environmental",
    "wof:placetype":"venue"
},
  "geometry": {"coordinates":[-79.217972,45.325874],"type":"Point"}
}