{
  "type": "Feature",
  "properties": {
    "addr:full":"5 Thirtieth St Etobicoke ON M8W 3B7",
    "addr:housenumber":"5",
    "addr:postcode":"m8w 3b7",
    "addr:street":"Thirtieth St",
    "iso:country":"CA",
    "sg:address":"5 Thirtieth St",
    "sg:city":"Etobicoke",
    "sg:classifiers":[
        {
            "category":"Social Services",
            "type":"Services"
        }
    ],
    "sg:phone":"+1 416 251 8372",
    "sg:postcode":"M8W 3B7",
    "sg:province":"ON",
    "sg:tags":[
        "organization",
        "welfare",
        "church"
    ],
    "wof:name":"Salvation Army",
    "wof:placetype":"venue"
},
  "geometry": {"coordinates":[-79.52986900000001,43.59602],"type":"Point"}
}