{
  "type": "Feature",
  "properties": {
    "addr:full":"Nepean ON K2E 1A3",
    "addr:postcode":"k2e 1a3",
    "iso:country":"CA",
    "sg:city":"Nepean",
    "sg:classifiers":[
        {
            "category":"Professional",
            "subcategory":"Lawyer & Legal Services",
            "type":"Services"
        }
    ],
    "sg:phone":"+1 613 228 9676",
    "sg:postcode":"K2E 1A3",
    "sg:province":"ON",
    "sg:tags":[
        "attorney"
    ],
    "wof:name":"Good, Donald R",
    "wof:placetype":"venue"
},
  "geometry": {"coordinates":[-75.722488,45.338963],"type":"Point"}
}