{
  "type": "Feature",
  "properties": {
    "iso:country":"CA",
    "sg:city":"Scarborough",
    "sg:classifiers":[
        {
            "category":"Home & Garden",
            "subcategory":"Building Materials",
            "type":"Retail Goods"
        }
    ],
    "sg:phone":"+1 416 750 3343",
    "sg:postcode":"M1R 3B7",
    "sg:province":"ON",
    "sg:tags":[
        "roofing"
    ],
    "wof:name":"Roofers Edge Roofing Supply",
    "wof:placetype":"venue"
},
  "geometry": {"coordinates":[-79.2886505127,43.7409057617],"type":"Point"}
}