{
  "type": "Feature",
  "properties": {
    "addr:full":"Hull QC J8Y 2V5",
    "addr:postcode":"j8y 2v5",
    "iso:country":"CA",
    "sg:city":"Hull",
    "sg:classifiers":[
        {
            "category":"Real Estate",
            "subcategory":"Real Estate Agent",
            "type":"Services"
        }
    ],
    "sg:phone":"+1 819 771 3517",
    "sg:postcode":"J8Y 2V5",
    "sg:province":"QC",
    "sg:tags":[
        "management"
    ],
    "wof:name":"Gestion 4 Taschereau",
    "wof:placetype":"venue"
},
  "geometry": {"coordinates":[-75.7333145142,45.4352684021],"type":"Point"}
}