{
  "type": "Feature",
  "properties": {
    "addr:full":"94 King St E Forest ON N0N 1J0",
    "addr:housenumber":"94",
    "addr:postcode":"n0n 1j0",
    "addr:street":"King St E",
    "iso:country":"CA",
    "sg:address":"94 King St E",
    "sg:city":"Forest",
    "sg:classifiers":[
        {
            "category":"Restaurant",
            "type":"Food & Drink"
        }
    ],
    "sg:phone":"+1 519 786 2418",
    "sg:postcode":"N0N 1J0",
    "sg:province":"ON",
    "wof:name":"King's 21 Family Restaurant",
    "wof:placetype":"venue"
},
  "geometry": {"coordinates":[-81.99201965330001,43.1015701294],"type":"Point"}
}