{
  "type": "Feature",
  "properties": {
    "addr:full":"62 Rue Saint-Florent Laval QC H7G 2H9",
    "addr:housenumber":"62",
    "addr:postcode":"qc h7g 2h9",
    "addr:street":"Rue Saint-Florent",
    "iso:country":"CA",
    "sg:address":"62 Rue Saint-Florent",
    "sg:city":"Laval",
    "sg:classifiers":[
        {
            "category":"Organizations",
            "subcategory":"Professional Association",
            "type":"Services"
        }
    ],
    "sg:phone":"+1 450 669 9924",
    "sg:postcode":"H7G 2H9",
    "sg:province":"QC",
    "wof:name":"Club Age D'Or Saint Maurice",
    "wof:placetype":"venue"
},
  "geometry": {"coordinates":[-73.69324493409999,45.5729408264],"type":"Point"}
}