{
  "type": "Feature",
  "properties": {
    "addr:full":"158 Jones Rd New Minas NS B4N 3N4",
    "addr:housenumber":"158",
    "addr:postcode":"b4n 3n4",
    "addr:street":"Jones Rd",
    "iso:country":"CA",
    "sg:address":"158 Jones Rd",
    "sg:city":"New Minas",
    "sg:classifiers":[
        {
            "category":"Manufacturing",
            "subcategory":"Metals",
            "type":"Manufacturing & Wholesale Goods"
        }
    ],
    "sg:phone":"+1 902 681 7812",
    "sg:postcode":"B4N 3N4",
    "sg:province":"NS",
    "sg:tags":[
        "welding"
    ],
    "wof:name":"Archie's Welding Ltd",
    "wof:placetype":"venue"
},
  "geometry": {"coordinates":[-64.4499130249,45.0684051514],"type":"Point"}
}