{
  "type": "Feature",
  "properties": {
    "addr:full":"3817 Alfred Ave Smithers BC V0J 2N0",
    "addr:housenumber":"3817",
    "addr:postcode":"v0j 2n0",
    "addr:street":"Alfred Ave",
    "iso:country":"CA",
    "sg:address":"3817 Alfred Ave",
    "sg:city":"Smithers",
    "sg:classifiers":[
        {
            "category":"Education",
            "subcategory":"Library",
            "type":"Public Place"
        }
    ],
    "sg:phone":"+1 250 847 3043",
    "sg:postcode":"V0J 2N0",
    "sg:province":"BC",
    "wof:name":"Smither Public Library",
    "wof:placetype":"venue"
},
  "geometry": {"coordinates":[-127.17536163299999,54.779045105],"type":"Point"}
}