{
  "type": "Feature",
  "properties": {
    "addr:full":"115 Brunswick St Truro NS B2N 2H3",
    "addr:housenumber":"115",
    "addr:postcode":"b2n 2h3",
    "addr:street":"Brunswick St",
    "iso:country":"CA",
    "sg:address":"115 Brunswick St",
    "sg:city":"Truro",
    "sg:classifiers":[
        {
            "category":"Wholesale",
            "subcategory":"Non-durable Goods",
            "type":"Manufacturing & Wholesale Goods"
        }
    ],
    "sg:phone":"+1 902 895 2511",
    "sg:postcode":"B2N 2H3",
    "sg:province":"NS",
    "sg:tags":[
        "fur",
        "broker"
    ],
    "wof:name":"Furafee Trading Inc",
    "wof:placetype":"venue"
},
  "geometry": {"coordinates":[-63.271858,45.362282],"type":"Point"}
}