{
  "type": "Feature",
  "properties": {
    "addr:full":"8920 Woodbine Ave # 104 Markham ON L3R 9W9",
    "addr:housenumber":"8920",
    "addr:postcode":"l3r 9w9",
    "addr:street":"Woodbine Ave # 104",
    "iso:country":"CA",
    "sg:address":"8920 Woodbine Ave # 104",
    "sg:city":"Markham",
    "sg:classifiers":[
        {
            "category":"Retail",
            "subcategory":"Auto Rental",
            "type":"Services"
        }
    ],
    "sg:phone":"+1 905 477 3477",
    "sg:postcode":"L3R 9W9",
    "sg:province":"ON",
    "sg:tags":[
        "renting",
        "automobile",
        "leasing"
    ],
    "wof:name":"Landmark Leasing Corp",
    "wof:placetype":"venue"
},
  "geometry": {"coordinates":[-79.3627624512,43.867931366],"type":"Point"}
}