{
  "type": "Feature",
  "properties": {
    "addr:full":"85 School St Maria QC G0C 1Y0",
    "addr:housenumber":"85",
    "addr:postcode":"g0c 1y0",
    "addr:street":"School St Maria",
    "iso:country":"CA",
    "sg:address":"85 School St",
    "sg:city":"Maria",
    "sg:classifiers":[
        {
            "category":"Organizations",
            "subcategory":"Non-profit Organization",
            "type":"Services"
        }
    ],
    "sg:phone":"+1 418 759 3522",
    "sg:postcode":"G0C 1Y0",
    "sg:province":"QC",
    "sg:tags":[
        "info",
        "addiction",
        "abuse",
        "treatment",
        "drug"
    ],
    "wof:name":"Services DE Traitements Inc",
    "wof:placetype":"venue"
},
  "geometry": {"coordinates":[-65.925072,48.198448],"type":"Point"}
}