{
  "type": "Feature",
  "properties": {
    "iso:country":"CA",
    "sg:address":"731 Victoria Rd",
    "sg:city":"Sydney",
    "sg:classifiers":[
        {
            "category":"Professional",
            "subcategory":"Employment Agencies",
            "type":"Services"
        }
    ],
    "sg:phone":"+1 902 562 6656",
    "sg:postcode":"B1N 1J3",
    "sg:province":"NS",
    "sg:tags":[
        "co",
        "fraternal"
    ],
    "wof:name":"Cape Breton Black Employment",
    "wof:placetype":"venue"
},
  "geometry": {"coordinates":[-60.183216095,46.1554603577],"type":"Point"}
}