{
  "type": "Feature",
  "properties": {
    "addr:full":"6655 Kingsway Burnaby BC V5E 1E2",
    "addr:housenumber":"6655",
    "addr:postcode":"v5e 1e2",
    "addr:street":"Kingsway",
    "iso:country":"CA",
    "sg:address":"6655 Kingsway",
    "sg:city":"Burnaby",
    "sg:classifiers":[
        {
            "category":"Autos & Motor Vehicles",
            "subcategory":"Automobile Sales",
            "type":"Retail Goods"
        }
    ],
    "sg:phone":"+1 604 435 9900",
    "sg:postcode":"V5E 1E2",
    "sg:province":"BC",
    "sg:tags":[
        "car",
        "dealer"
    ],
    "wof:name":"Seawest Auto Lease & Sales",
    "wof:placetype":"venue"
},
  "geometry": {"coordinates":[-122.966179,49.218784],"type":"Point"}
}