{
  "type": "Feature",
  "properties": {
    "iso:country":"CA",
    "sg:address":"32 Jakeman St",
    "sg:city":"Bethany",
    "sg:classifiers":[
        {
            "category":"Insurance",
            "subcategory":"Insurance Agent",
            "type":"Services"
        }
    ],
    "sg:phone":"+1 705 277 2011",
    "sg:postcode":"L0A 1A0",
    "sg:province":"ON",
    "wof:name":"James W Kloepfer Insurance",
    "wof:placetype":"venue"
},
  "geometry": {"coordinates":[-78.5668716431,44.1817855835],"type":"Point"}
}