{
  "type": "Feature",
  "properties": {
    "iso:country":"CA",
    "sg:address":"2225 Coquitlam Ave",
    "sg:city":"Port Coquitlam",
    "sg:classifiers":[
        {
            "category":"Manufacturing",
            "subcategory":"Signs",
            "type":"Manufacturing & Wholesale Goods"
        }
    ],
    "sg:phone":"+1 604 942 6636",
    "sg:postcode":"V3B 1J6",
    "sg:province":"BC",
    "wof:name":"Superior Signs",
    "wof:placetype":"venue"
},
  "geometry": {"coordinates":[-122.775467,49.267597],"type":"Point"}
}