{
  "type": "Feature",
  "properties": {
    "addr:full":"2225 Coquitlam Ave Port Coquitlam BC V3B 1J6",
    "addr:housenumber":"2225",
    "addr:postcode":"v3b 1j6",
    "addr:street":"Coquitlam Ave",
    "iso:country":"CA",
    "sg:address":"2225 Coquitlam Ave",
    "sg:city":"Port Coquitlam",
    "sg:classifiers":[
        {
            "category":"Manufacturing",
            "subcategory":"Signs",
            "type":"Manufacturing & Wholesale Goods"
        }
    ],
    "sg:phone":"+1 604 942 6636",
    "sg:postcode":"V3B 1J6",
    "sg:province":"BC",
    "wof:name":"Superior Signs",
    "wof:placetype":"venue"
},
  "geometry": {"coordinates":[-122.77546700000001,49.267597],"type":"Point"}
}