{
  "type": "Feature",
  "properties": {
    "addr:full":"Maple ON L6A 1W3",
    "addr:postcode":"l6a 1w3",
    "iso:country":"CA",
    "sg:city":"Maple",
    "sg:classifiers":[
        {
            "category":"Food & Beverages",
            "subcategory":"Groceries & Convenience Stores",
            "type":"Retail Goods"
        }
    ],
    "sg:phone":"+1 905 832 6293",
    "sg:postcode":"L6A 1W3",
    "sg:province":"ON",
    "wof:name":"Mac's Convenience Stores Ltd",
    "wof:placetype":"venue"
},
  "geometry": {"coordinates":[-79.509262085,43.8420639038],"type":"Point"}
}