{
  "type": "Feature",
  "properties": {
    "addr:full":"Olds AB T4H 1H2",
    "addr:postcode":"t4h 1h2",
    "iso:country":"CA",
    "sg:city":"Olds",
    "sg:classifiers":[
        {
            "category":"Health Services",
            "subcategory":"Medical Lab",
            "type":"Services"
        }
    ],
    "sg:phone":"+1 403 556 3833",
    "sg:postcode":"T4H 1H2",
    "sg:province":"AB",
    "wof:name":"Mountain View Denture Clinic",
    "wof:placetype":"venue"
},
  "geometry": {"coordinates":[-114.10806274399999,51.79271698],"type":"Point"}
}