{
  "type": "Feature",
  "properties": {
    "addr:full":"85 Bloor St W Toronto ON M5S 1M1",
    "addr:housenumber":"85",
    "addr:postcode":"m5s 1m1",
    "addr:street":"Bloor St W",
    "iso:country":"CA",
    "sg:address":"85 Bloor St W",
    "sg:city":"Toronto",
    "sg:classifiers":[
        {
            "category":"Shopping",
            "subcategory":"Jewelry",
            "type":"Retail Goods"
        }
    ],
    "sg:phone":"+1 416 921 3900",
    "sg:postcode":"M5S 1M1",
    "sg:province":"ON",
    "sg:tags":[
        "jeweler"
    ],
    "wof:name":"Tiffany & CO",
    "wof:placetype":"venue"
},
  "geometry": {"coordinates":[-79.3902053833,43.6693687439],"type":"Point"}
}