{
  "type": "Feature",
  "properties": {
    "addr:full":"12922 97 St NW Edmonton AB T5E 4C3",
    "addr:housenumber":"12922",
    "addr:postcode":"t5e 4c3",
    "addr:street":"97 St Nw",
    "iso:country":"CA",
    "sg:address":"12922 97 St NW",
    "sg:city":"Edmonton",
    "sg:classifiers":[
        {
            "category":"Personal",
            "subcategory":"Barber",
            "type":"Services"
        }
    ],
    "sg:phone":"+1 780 478 3113",
    "sg:postcode":"T5E 4C3",
    "sg:province":"AB",
    "wof:name":"Ernie's Barber Shop",
    "wof:placetype":"venue"
},
  "geometry": {"coordinates":[-113.49211099999999,53.588142],"type":"Point"}
}