{
  "type": "Feature",
  "properties": {
    "iso:country":"CA",
    "sg:city":"Nepean",
    "sg:classifiers":[
        {
            "category":"Retail",
            "subcategory":"Laundry & Dry Cleaning",
            "type":"Services"
        }
    ],
    "sg:phone":"+1 613 224 6905",
    "sg:postcode":"K2G 5X3",
    "sg:province":"ON",
    "sg:tags":[
        "cleaners"
    ],
    "wof:name":"Pro Sketch Cleaners",
    "wof:placetype":"venue"
},
  "geometry": {"coordinates":[-75.76327514650001,45.3432006836],"type":"Point"}
}