{
  "type": "Feature",
  "properties": {
    "addr:full":"9010 9E Allee # 9 Saint-Nicephore QC J2A 2E9",
    "addr:housenumber":"9010;# 9",
    "addr:postcode":"j2a 2e9",
    "addr:street":"9E Allee;Saint-Nicephore",
    "iso:country":"CA",
    "sg:address":"9010 9E Allee # 9",
    "sg:city":"Saint-Nicephore",
    "sg:classifiers":[
        {
            "category":"Personal",
            "subcategory":"Beauty Salon",
            "type":"Services"
        }
    ],
    "sg:phone":"+1 819 478 0765",
    "sg:postcode":"J2A 2E9",
    "sg:province":"QC",
    "wof:name":"Coiffure 2000 Enr",
    "wof:placetype":"venue"
},
  "geometry": {"coordinates":[-72.4250946045,45.8354988098],"type":"Point"}
}