{
  "type": "Feature",
  "properties": {
    "addr:full":"858 Rue Saint-Alphonse O Thetford Mines QC G6G 3X2",
    "addr:housenumber":"858",
    "addr:postcode":"g6g 3x2",
    "addr:street":"Rue Saint-Alphonse O",
    "iso:country":"CA",
    "sg:address":"858 Rue Saint-Alphonse O",
    "sg:city":"Thetford Mines",
    "sg:classifiers":[
        {
            "category":"Wholesale",
            "subcategory":"Hardware",
            "type":"Manufacturing & Wholesale Goods"
        }
    ],
    "sg:phone":"+1 418 338 3489",
    "sg:postcode":"G6G 3X2",
    "sg:province":"QC",
    "sg:tags":[
        "water",
        "cooler",
        "fountain",
        "appliance",
        "filter"
    ],
    "wof:name":"Michel Service Enr",
    "wof:placetype":"venue"
},
  "geometry": {"coordinates":[-71.29052,46.082687],"type":"Point"}
}