{
  "type": "Feature",
  "properties": {
    "iso:country":"CA",
    "sg:address":"27 Cumberland St S",
    "sg:city":"Thunder Bay",
    "sg:classifiers":[
        {
            "category":"Restaurant",
            "type":"Food & Drink"
        }
    ],
    "sg:phone":"+1 807 345 5833",
    "sg:postcode":"P7B 2T3",
    "sg:province":"ON",
    "wof:name":"Prospector Steak House",
    "wof:placetype":"venue"
},
  "geometry": {"coordinates":[-89.22026824949999,48.4338264465],"type":"Point"}
}