{
  "type": "Feature",
  "properties": {
    "addr:full":"Saint-Lazare QC J7T 2X9",
    "addr:postcode":"j7t 2x9",
    "iso:country":"CA",
    "sg:city":"Saint-Lazare",
    "sg:classifiers":[
        {
            "category":"Personal",
            "subcategory":"Beauty Salon",
            "type":"Services"
        }
    ],
    "sg:phone":"+1 450 455 3430",
    "sg:postcode":"J7T 2X9",
    "sg:province":"QC",
    "wof:name":"Coiffure Johanne",
    "wof:placetype":"venue"
},
  "geometry": {"coordinates":[-74.142151,45.400349],"type":"Point"}
}