{
  "type": "Feature",
  "properties": {
    "addr:full":"Coquitlam BC V3K 3P4",
    "addr:postcode":"v3k 3p4",
    "iso:country":"CA",
    "sg:city":"Coquitlam",
    "sg:classifiers":[
        {
            "category":"Building & Trades",
            "subcategory":"Equipment Rental",
            "type":"Services"
        }
    ],
    "sg:phone":"+1 604 931 1990",
    "sg:postcode":"V3K 3P4",
    "sg:province":"BC",
    "sg:tags":[
        "tool",
        "yard"
    ],
    "wof:name":"Austin Tool Rentals Ltd",
    "wof:placetype":"venue"
},
  "geometry": {"coordinates":[-122.860389709,49.2491188049],"type":"Point"}
}