{
  "type": "Feature",
  "properties": {
    "addr:full":"Grand Bank NL A0E 1W0",
    "addr:postcode":"a0e 1w0",
    "iso:country":"CA",
    "sg:city":"Grand Bank",
    "sg:classifiers":[
        {
            "category":"Shopping",
            "subcategory":"Catalog Store",
            "type":"Retail Goods"
        }
    ],
    "sg:phone":"+1 709 832 1320",
    "sg:postcode":"A0E 1W0",
    "sg:province":"NL",
    "sg:tags":[
        "mail",
        "order",
        "internet"
    ],
    "wof:name":"Sears Canada Inc",
    "wof:placetype":"venue"
},
  "geometry": {"coordinates":[-55.757942,47.094414],"type":"Point"}
}