{
  "type": "Feature",
  "properties": {
    "iso:country":"CA",
    "sg:address":"RR 2 Box 38105",
    "sg:city":"Bloomfield Station",
    "sg:classifiers":[
        {
            "category":"Wholesale",
            "subcategory":"Machinery & Supplies",
            "type":"Manufacturing & Wholesale Goods"
        }
    ],
    "sg:phone":"+1 902 859 3887",
    "sg:postcode":"C0B 1E0",
    "sg:province":"PE",
    "sg:tags":[
        "farm",
        "equipment"
    ],
    "wof:name":"D & M Tools Ltd",
    "wof:placetype":"venue"
},
  "geometry": {"coordinates":[-64.2351531982,46.7763366699],"type":"Point"}
}