{
  "type": "Feature",
  "properties": {
    "addr:full":"98 Rue Denison E Granby QC J2G 4C6",
    "addr:housenumber":"98",
    "addr:postcode":"j2g 4c6",
    "addr:street":"Rue Denison E",
    "iso:country":"CA",
    "sg:address":"98 Rue Denison E",
    "sg:city":"Granby",
    "sg:classifiers":[
        {
            "category":"Manufacturing",
            "subcategory":"Tools & Machinery",
            "type":"Manufacturing & Wholesale Goods"
        }
    ],
    "sg:phone":"+1 450 372 7572",
    "sg:postcode":"J2G 4C6",
    "sg:province":"QC",
    "sg:tags":[
        "machine",
        "shop"
    ],
    "wof:name":"Atelier D'Usinage Morris Inc",
    "wof:placetype":"venue"
},
  "geometry": {"coordinates":[-72.71514129640001,45.3962783813],"type":"Point"}
}