{
  "type": "Feature",
  "properties": {
    "addr:full":"18840 Beaverbrook Rd Martintown ON K0C 1S0",
    "addr:housenumber":"18840",
    "addr:postcode":"k0c 1s0",
    "addr:street":"Beaverbrook Rd",
    "iso:country":"CA",
    "sg:address":"18840 Beaverbrook Rd",
    "sg:city":"Martintown",
    "sg:classifiers":[
        {
            "category":"Health Services",
            "subcategory":"Doctor",
            "type":"Services"
        }
    ],
    "sg:phone":"+1 613 528 4402",
    "sg:postcode":"K0C 1S0",
    "sg:province":"ON",
    "sg:tags":[
        "physician",
        "surgeon"
    ],
    "wof:name":"Toop, J MD",
    "wof:placetype":"venue"
},
  "geometry": {"coordinates":[-74.68408203120001,45.1700897217],"type":"Point"}
}