{
  "type": "Feature",
  "properties": {
    "iso:country":"CA",
    "sg:address":"55 Rue Richelieu",
    "sg:city":"Saint-Jean-Sur-Richelieu",
    "sg:classifiers":[
        {
            "category":"Recreation",
            "subcategory":"Marina",
            "type":"Entertainment"
        }
    ],
    "sg:phone":"+1 450 347 2341",
    "sg:postcode":"J3B 6X2",
    "sg:province":"QC",
    "wof:name":"Nautique St-Jean",
    "wof:placetype":"venue"
},
  "geometry": {"coordinates":[-73.250656,45.302792],"type":"Point"}
}