{
  "type": "Feature",
  "properties": {
    "addr:full":"5810 Hugh Cres Osgoode ON K0A 2W0",
    "addr:housenumber":"5810",
    "addr:postcode":"k0a 2w0",
    "addr:street":"Hugh Cres",
    "iso:country":"CA",
    "sg:address":"5810 Hugh Cres",
    "sg:city":"Osgoode",
    "sg:classifiers":[
        {
            "category":"Building & Trades",
            "subcategory":"Construction",
            "type":"Services"
        }
    ],
    "sg:phone":"+1 613 826 2680",
    "sg:postcode":"K0A 2W0",
    "sg:province":"ON",
    "sg:tags":[
        "painter"
    ],
    "wof:name":"W Schmidt Painting Inc",
    "wof:placetype":"venue"
},
  "geometry": {"coordinates":[-75.59108000000001,45.149223],"type":"Point"}
}