{
  "type": "Feature",
  "properties": {
    "addr:full":"Edmonton AB T6P 1R8",
    "addr:postcode":"t6p 1r8",
    "iso:country":"CA",
    "sg:city":"Edmonton",
    "sg:classifiers":[
        {
            "category":"Retail",
            "subcategory":"Portrait Studio",
            "type":"Services"
        }
    ],
    "sg:phone":"+1 780 440 4050",
    "sg:postcode":"T6P 1R8",
    "sg:province":"AB",
    "sg:tags":[
        "photographer"
    ],
    "wof:name":"Cunningham Photographers",
    "wof:placetype":"venue"
},
  "geometry": {"coordinates":[-113.490371704,53.5462188721],"type":"Point"}
}