{
  "type": "Feature",
  "properties": {
    "addr:full":"232 Torbay Rd St. John's NL A1A 2H4",
    "addr:housenumber":"232",
    "addr:postcode":"a1a 2h4",
    "addr:street":"Torbay Rd",
    "iso:country":"CA",
    "sg:address":"232 Torbay Rd",
    "sg:city":"St. John's",
    "sg:classifiers":[
        {
            "category":"Health Services",
            "subcategory":"Health Practitioner",
            "type":"Services"
        }
    ],
    "sg:phone":"+1 709 754 6929",
    "sg:postcode":"A1A 2H4",
    "sg:province":"NL",
    "sg:tags":[
        "psychologist"
    ],
    "wof:name":"Gamba, Sandy",
    "wof:placetype":"venue"
},
  "geometry": {"coordinates":[-52.710247,47.597019],"type":"Point"}
}