{
  "type": "Feature",
  "properties": {
    "addr:full":"5185 Boul DE Port-Royal Becancour QC G9H 1Z8",
    "addr:housenumber":"5185",
    "addr:postcode":"g9h 1z8",
    "addr:street":"Boul De Port-Royal Becancour",
    "iso:country":"CA",
    "sg:address":"5185 Boul DE Port-Royal",
    "sg:city":"Becancour",
    "sg:classifiers":[
        {
            "category":"Personal",
            "subcategory":"Beauty Salon",
            "type":"Services"
        }
    ],
    "sg:phone":"+1 819 233 2373",
    "sg:postcode":"G9H 1Z8",
    "sg:province":"QC",
    "wof:name":"Salon Les Coiffures Jean-Pierr",
    "wof:placetype":"venue"
},
  "geometry": {"coordinates":[-72.507194519,46.268825531],"type":"Point"}
}