{
  "type": "Feature",
  "properties": {
    "addr:full":"362 Rte DE L'Eglise Saint-Jean-Port-Joli QC G0R 3G0",
    "addr:housenumber":"362",
    "addr:postcode":"g0r 3g0",
    "addr:street":"Rte De L'Eglise",
    "iso:country":"CA",
    "sg:address":"362 Rte DE L'Eglise",
    "sg:city":"Saint-Jean-Port-Joli",
    "sg:classifiers":[
        {
            "category":"Personal",
            "subcategory":"Beauty Salon",
            "type":"Services"
        }
    ],
    "sg:phone":"+1 418 598 9920",
    "sg:postcode":"G0R 3G0",
    "sg:province":"QC",
    "wof:name":"Salon DE Coiffure Zapp",
    "wof:placetype":"venue"
},
  "geometry": {"coordinates":[-70.26676940919999,47.2121009827],"type":"Point"}
}