{
  "type": "Feature",
  "properties": {
    "addr:full":"527 Queen Alexandra Way SE Calgary AB T2J 4C7",
    "addr:housenumber":"527",
    "addr:postcode":"t2j 4c7",
    "addr:street":"Queen Alexandra Way Se",
    "iso:country":"CA",
    "sg:address":"527 Queen Alexandra Way SE",
    "sg:city":"Calgary",
    "sg:classifiers":[
        {
            "category":"Building & Trades",
            "subcategory":"Construction",
            "type":"Services"
        }
    ],
    "sg:phone":"+1 403 271 4600",
    "sg:postcode":"T2J 4C7",
    "sg:province":"AB",
    "sg:tags":[
        "general",
        "fixture",
        "store",
        "contractor"
    ],
    "wof:name":"Copper Bear Enterprises Inc",
    "wof:placetype":"venue"
},
  "geometry": {"coordinates":[-114.028702,50.93951],"type":"Point"}
}