{
  "type": "Feature",
  "properties": {
    "addr:full":"Calgary AB T2H 2S8",
    "addr:postcode":"t2h 2s8",
    "iso:country":"CA",
    "sg:city":"Calgary",
    "sg:classifiers":[
        {
            "category":"Building & Trades",
            "subcategory":"Construction",
            "type":"Services"
        }
    ],
    "sg:phone":"+1 403 253 9693",
    "sg:postcode":"T2H 2S8",
    "sg:province":"AB",
    "sg:tags":[
        "contractor"
    ],
    "wof:name":"Gallery Homes",
    "wof:placetype":"venue"
},
  "geometry": {"coordinates":[-114.033424,50.989113],"type":"Point"}
}