{
  "type": "Feature",
  "properties": {
    "addr:full":"Calgary AB T2P 0C5",
    "addr:postcode":"t2p 0c5",
    "iso:country":"CA",
    "sg:city":"Calgary",
    "sg:classifiers":[
        {
            "category":"Professional",
            "subcategory":"Research",
            "type":"Services"
        }
    ],
    "sg:phone":"+1 403 237 0606",
    "sg:postcode":"T2P 0C5",
    "sg:province":"AB",
    "sg:tags":[
        "environmental",
        "ecological"
    ],
    "wof:name":"Matrix Solutions Inc",
    "wof:placetype":"venue"
},
  "geometry": {"coordinates":[-114.068108,51.051174],"type":"Point"}
}