{
  "type": "Feature",
  "properties": {
    "addr:full":"4191 Mcconnell Dr Burnaby BC V5A 3J7",
    "addr:housenumber":"4191",
    "addr:postcode":"v5a 3j7",
    "addr:street":"Mcconnell Dr",
    "iso:country":"CA",
    "sg:address":"4191 Mcconnell Dr",
    "sg:city":"Burnaby",
    "sg:classifiers":[
        {
            "category":"Restaurant",
            "type":"Food & Drink"
        }
    ],
    "sg:phone":"+1 604 420 6434",
    "sg:postcode":"V5A 3J7",
    "sg:province":"BC",
    "sg:tags":[
        "caterer"
    ],
    "wof:name":"Chef's Catering & Cafe",
    "wof:placetype":"venue"
},
  "geometry": {"coordinates":[-122.941277,49.246799],"type":"Point"}
}