{
  "type": "Feature",
  "properties": {
    "addr:full":"225 Ch DE LA Grande-Cote Boisbriand QC J7G 1B6",
    "addr:housenumber":"225",
    "addr:postcode":"j7g 1b6",
    "addr:street":"Ch De La Grande-Cote",
    "iso:country":"CA",
    "sg:address":"225 Ch DE LA Grande-Cote",
    "sg:city":"Boisbriand",
    "sg:classifiers":[
        {
            "category":"Health Services",
            "subcategory":"Medical Lab",
            "type":"Services"
        }
    ],
    "sg:phone":"+1 450 437 8345",
    "sg:postcode":"J7G 1B6",
    "sg:province":"QC",
    "wof:name":"Yvon, Jean F",
    "wof:placetype":"venue"
},
  "geometry": {"coordinates":[-73.8259277344,45.6128997803],"type":"Point"}
}