{
  "type": "Feature",
  "properties": {
    "addr:full":"8523 132 St Surrey BC V3W 4N8",
    "addr:housenumber":"8523",
    "addr:postcode":"v3w 4n8",
    "addr:street":"132 St",
    "iso:country":"CA",
    "sg:address":"8523 132 St",
    "sg:city":"Surrey",
    "sg:classifiers":[
        {
            "category":"Freight",
            "type":"Transportation"
        }
    ],
    "sg:phone":"+1 604 572 1157",
    "sg:postcode":"V3W 4N8",
    "sg:province":"BC",
    "sg:tags":[
        "trucking"
    ],
    "wof:name":"Trans Border",
    "wof:placetype":"venue"
},
  "geometry": {"coordinates":[-122.856994629,49.1579360962],"type":"Point"}
}