{
  "type": "Feature",
  "properties": {
    "addr:full":"101 Southpoint Close Trochu AB T0M 2C0",
    "addr:housenumber":"101",
    "addr:postcode":"t0m 2c0",
    "addr:street":"Southpoint Close",
    "iso:country":"CA",
    "sg:address":"101 Southpoint Close",
    "sg:city":"Trochu",
    "sg:classifiers":[
        {
            "category":"Building & Trades",
            "subcategory":"Construction",
            "type":"Services"
        }
    ],
    "sg:phone":"+1 403 442 4288",
    "sg:postcode":"T0M 2C0",
    "sg:province":"AB",
    "sg:tags":[
        "excavating",
        "contractor"
    ],
    "wof:name":"Allan Ross Excavating Inc",
    "wof:placetype":"venue"
},
  "geometry": {"coordinates":[-113.237633,51.823704],"type":"Point"}
}