{
  "type": "Feature",
  "properties": {
    "addr:full":"29 Queen St Niagara on the Lake ON L0S 1J0",
    "addr:housenumber":"29",
    "addr:postcode":"l0s 1j0",
    "addr:street":"Queen St;On",
    "iso:country":"CA",
    "sg:address":"29 Queen St",
    "sg:city":"Niagara on the Lake",
    "sg:classifiers":[
        {
            "category":"Restaurant",
            "type":"Food & Drink"
        }
    ],
    "sg:phone":"+1 905 468 0197",
    "sg:postcode":"L0S 1J0",
    "sg:province":"ON",
    "sg:tags":[
        "delicatessen"
    ],
    "wof:name":"Theatre Deli & Gourmet Shoppe",
    "wof:placetype":"venue"
},
  "geometry": {"coordinates":[-79.0718917847,43.2553749084],"type":"Point"}
}