{
  "type": "Feature",
  "properties": {
    "addr:full":"275 Tache Ave Winnipeg MB R2H 1Z8",
    "addr:housenumber":"275",
    "addr:postcode":"r2h 1z8",
    "addr:street":"Tache Ave",
    "iso:country":"CA",
    "sg:address":"275 Tache Ave",
    "sg:city":"Winnipeg",
    "sg:classifiers":[
        {
            "category":"Health Services",
            "subcategory":"Doctor",
            "type":"Services"
        }
    ],
    "sg:phone":"+1 204 233 7726",
    "sg:postcode":"R2H 1Z8",
    "sg:province":"MB",
    "sg:tags":[
        "dentist"
    ],
    "wof:name":"Lachance-Piche, Christine DDS",
    "wof:placetype":"venue"
},
  "geometry": {"coordinates":[-97.123459,49.880386],"type":"Point"}
}