{
  "type": "Feature",
  "properties": {
    "addr:full":"119 Main St Invermay SK S0A 1M0",
    "addr:housenumber":"119",
    "addr:postcode":"s0a 1m0",
    "addr:street":"Main St",
    "iso:country":"CA",
    "sg:address":"119 Main St",
    "sg:city":"Invermay",
    "sg:classifiers":[
        {
            "category":"Shopping",
            "subcategory":"Gifts & Souvenirs",
            "type":"Retail Goods"
        }
    ],
    "sg:phone":"+1 306 593 4802",
    "sg:postcode":"S0A 1M0",
    "sg:province":"SK",
    "sg:tags":[
        "shop"
    ],
    "wof:name":"And Everything Nice Boutique",
    "wof:placetype":"venue"
},
  "geometry": {"coordinates":[-103.15322113000001,51.8057937622],"type":"Point"}
}