{
  "type": "Feature",
  "properties": {
    "addr:full":"30 Av William-Dobell Baie-Comeau QC G4Z 1T7",
    "addr:postcode":"g4z 1t7",
    "addr:street":"30 Av William-Dobell",
    "iso:country":"CA",
    "sg:address":"30 Av William-Dobell",
    "sg:city":"Baie-Comeau",
    "sg:classifiers":[
        {
            "category":"Manufacturing",
            "subcategory":"Metals",
            "type":"Manufacturing & Wholesale Goods"
        }
    ],
    "sg:phone":"+1 418 296 3077",
    "sg:postcode":"G4Z 1T7",
    "sg:province":"QC",
    "sg:tags":[
        "shop",
        "garage",
        "temporary",
        "fabric",
        "shelter"
    ],
    "wof:name":"Toiles Industrielles",
    "wof:placetype":"venue"
},
  "geometry": {"coordinates":[-68.183769,49.217545],"type":"Point"}
}