{
  "type": "Feature",
  "properties": {
    "addr:full":"762 Fraser Ave Hope BC V0X 1L0",
    "addr:housenumber":"762",
    "addr:postcode":"v0x 1l0",
    "addr:street":"Fraser Ave",
    "iso:country":"CA",
    "sg:address":"762 Fraser Ave",
    "sg:city":"Hope",
    "sg:classifiers":[
        {
            "category":"Restaurant",
            "type":"Food & Drink"
        }
    ],
    "sg:phone":"+1 604 869 5774",
    "sg:postcode":"V0X 1L0",
    "sg:province":"BC",
    "sg:tags":[
        "grocer",
        "out"
    ],
    "wof:name":"Peters Food Market & Deli",
    "wof:placetype":"venue"
},
  "geometry": {"coordinates":[-121.44360399999999,49.379642],"type":"Point"}
}