{
  "type": "Feature",
  "properties": {
    "addr:full":"105011 Road 40E Grand Marais MB R0E 0T0",
    "addr:housenumber":"105011;40e",
    "addr:postcode":"r0e 0t0",
    "addr:street":"Road",
    "iso:country":"CA",
    "sg:address":"105011 Road 40E",
    "sg:city":"Grand Marais",
    "sg:classifiers":[
        {
            "category":"Sports & Exercise",
            "subcategory":"Golf",
            "type":"Entertainment"
        }
    ],
    "sg:phone":"+1 204 754 8789",
    "sg:postcode":"R0E 0T0",
    "sg:province":"MB",
    "sg:tags":[
        "course"
    ],
    "wof:name":"Beaches Golf Course",
    "wof:placetype":"venue"
},
  "geometry": {"coordinates":[-96.6255569458,50.5451431274],"type":"Point"}
}