{
  "type": "Feature",
  "properties": {
    "addr:full":"Chatham ON N7M 5J5",
    "addr:postcode":"n7m 5j5",
    "iso:country":"CA",
    "sg:city":"Chatham",
    "sg:classifiers":[
        {
            "category":"Manufacturing",
            "subcategory":"Building Materials",
            "type":"Manufacturing & Wholesale Goods"
        }
    ],
    "sg:phone":"+1 519 380 9265",
    "sg:postcode":"N7M 5J5",
    "sg:province":"ON",
    "wof:name":"Wellington Polymer Technology",
    "wof:placetype":"venue"
},
  "geometry": {"coordinates":[-82.22532699999999,42.389568],"type":"Point"}
}