{
  "type": "Feature",
  "properties": {
    "addr:full":"10633 Rowland Rd NW Edmonton AB T6A 3V9",
    "addr:housenumber":"10633",
    "addr:postcode":"t6a 3v9",
    "addr:street":"Rowland Rd Nw",
    "iso:country":"CA",
    "sg:address":"10633 Rowland Rd NW",
    "sg:city":"Edmonton",
    "sg:classifiers":[
        {
            "category":"Professional",
            "subcategory":"Accounting & Tax Preparation",
            "type":"Services"
        }
    ],
    "sg:phone":"+1 780 448 1567",
    "sg:postcode":"T6A 3V9",
    "sg:province":"AB",
    "sg:tags":[
        "equipment",
        "laboratory",
        "accountant",
        "supply"
    ],
    "wof:name":"Terry P Jeske Prof Corp",
    "wof:placetype":"venue"
},
  "geometry": {"coordinates":[-113.439842,53.55077],"type":"Point"}
}