{
  "type": "Feature",
  "properties": {
    "addr:full":"4756 Lougheed Hwy Burnaby BC V5C 4A8",
    "addr:housenumber":"4756",
    "addr:postcode":"v5c 4a8",
    "addr:street":"Lougheed Hwy",
    "iso:country":"CA",
    "sg:address":"4756 Lougheed Hwy",
    "sg:city":"Burnaby",
    "sg:classifiers":[
        {
            "category":"Autos & Motor Vehicles",
            "subcategory":"Automobile Sales",
            "type":"Retail Goods"
        }
    ],
    "sg:phone":"+1 604 525 7227",
    "sg:postcode":"V5C 4A8",
    "sg:province":"BC",
    "sg:tags":[
        "car",
        "dealer"
    ],
    "wof:name":"Mario Motors Ltd",
    "wof:placetype":"venue"
},
  "geometry": {"coordinates":[-122.996078,49.265831],"type":"Point"}
}