{
  "type": "Feature",
  "properties": {
    "addr:full":"5301 Boul Cleroux # A Laval QC H7T 2E5",
    "addr:housenumber":"5301",
    "addr:postcode":"h7t 2e5",
    "addr:street":"Boul Cleroux # A",
    "iso:country":"CA",
    "sg:address":"5301 Boul Cleroux # A",
    "sg:city":"Laval",
    "sg:classifiers":[
        {
            "category":"Building & Trades",
            "subcategory":"Construction",
            "type":"Services"
        }
    ],
    "sg:phone":"+1 450 688 9004",
    "sg:postcode":"H7T 2E5",
    "sg:province":"QC",
    "sg:tags":[
        "excavating",
        "contractor"
    ],
    "wof:name":"Nepcon Inc",
    "wof:placetype":"venue"
},
  "geometry": {"coordinates":[-73.79992675779999,45.5512428284],"type":"Point"}
}