{
  "type": "Feature",
  "properties": {
    "addr:full":"Calgary AB T2X 1M2",
    "addr:postcode":"t2x 1m2",
    "iso:country":"CA",
    "sg:city":"Calgary",
    "sg:classifiers":[
        {
            "category":"Professional",
            "subcategory":"Management & Consulting",
            "type":"Services"
        }
    ],
    "sg:phone":"+1 403 253 2121",
    "sg:postcode":"T2X 1M2",
    "sg:province":"AB",
    "sg:tags":[
        "consultant",
        "safety"
    ],
    "wof:name":"Gravitec Systems Inc",
    "wof:placetype":"venue"
},
  "geometry": {"coordinates":[-114.063926697,50.9113578796],"type":"Point"}
}