{
  "type": "Feature",
  "properties": {
    "addr:full":"3516 8 Ave NE Calgary AB T2A 6K5",
    "addr:housenumber":"3516",
    "addr:postcode":"t2a 6k5",
    "addr:street":"8 Ave Ne",
    "iso:country":"CA",
    "sg:address":"3516 8 Ave NE",
    "sg:city":"Calgary",
    "sg:classifiers":[
        {
            "category":"Cinema",
            "subcategory":"Movie Theater",
            "type":"Entertainment"
        }
    ],
    "sg:phone":"+1 403 248 2000",
    "sg:postcode":"T2A 6K5",
    "sg:province":"AB",
    "wof:name":"Moviedome By Carnival",
    "wof:placetype":"venue"
},
  "geometry": {"coordinates":[-113.983688355,51.0596885681],"type":"Point"}
}