{
  "type": "Feature",
  "properties": {
    "iso:country":"CA",
    "sg:address":"717 Brock Ave",
    "sg:city":"Toronto",
    "sg:classifiers":[
        {
            "category":"Education",
            "subcategory":"School",
            "type":"Public Place"
        }
    ],
    "sg:phone":"+1 416 393 5354",
    "sg:postcode":"M6H 3P1",
    "sg:province":"ON",
    "wof:name":"Saint Sebastian Elementary",
    "wof:placetype":"venue"
},
  "geometry": {"coordinates":[-79.4393539429,43.661403656],"type":"Point"}
}