{
  "type": "Feature",
  "properties": {
    "addr:full":"Toronto ON M4R 1B9",
    "addr:postcode":"m4r 1b9",
    "iso:country":"CA",
    "sg:city":"Toronto",
    "sg:classifiers":[
        {
            "category":"Social Services",
            "type":"Services"
        }
    ],
    "sg:phone":"+1 416 482 0081",
    "sg:postcode":"M4R 1B9",
    "sg:province":"ON",
    "sg:tags":[
        "organization",
        "welfare"
    ],
    "wof:name":"Delisle Youth Svc",
    "wof:placetype":"venue"
},
  "geometry": {"coordinates":[-79.39991000000001,43.70808],"type":"Point"}
}