{
  "type": "Feature",
  "properties": {
    "addr:full":"41810 Rayburn Rd Brackendale BC V0N 1H0",
    "addr:postcode":"41810;v0n 1h0",
    "addr:street":"Rayburn Rd",
    "iso:country":"CA",
    "sg:address":"41810 Rayburn Rd",
    "sg:city":"Brackendale",
    "sg:classifiers":[
        {
            "category":"Building & Trades",
            "subcategory":"Plumbing",
            "type":"Services"
        }
    ],
    "sg:phone":"+1 604 898 4666",
    "sg:postcode":"V0N 1H0",
    "sg:province":"BC",
    "sg:tags":[
        "contractor"
    ],
    "wof:name":"Sea To Sky Plumbing & Heating",
    "wof:placetype":"venue"
},
  "geometry": {"coordinates":[-123.13948059099999,49.7659301758],"type":"Point"}
}