{
  "type": "Feature",
  "properties": {
    "iso:country":"CA",
    "sg:address":"1336 Nanaimo St",
    "sg:city":"Vancouver",
    "sg:classifiers":[
        {
            "category":"Food & Beverages",
            "subcategory":"Bakery",
            "type":"Retail Goods"
        }
    ],
    "sg:phone":"+1 604 216 0889",
    "sg:postcode":"V5L 4T6",
    "sg:province":"BC",
    "sg:tags":[
        "baker"
    ],
    "wof:name":"Angelicus Bakery",
    "wof:placetype":"venue"
},
  "geometry": {"coordinates":[-123.05648803699999,49.272983551],"type":"Point"}
}