{
  "type": "Feature",
  "properties": {
    "iso:country":"CA",
    "sg:city":"Trail",
    "sg:classifiers":[
        {
            "category":"Sports & Exercise",
            "subcategory":"Golf",
            "type":"Entertainment"
        }
    ],
    "sg:phone":"+1 250 693 2255",
    "sg:postcode":"V1R 4L5",
    "sg:province":"BC",
    "sg:tags":[
        "course"
    ],
    "wof:name":"Birchbank Pro Shop",
    "wof:placetype":"venue"
},
  "geometry": {"coordinates":[-117.715873718,49.0972442627],"type":"Point"}
}