{
  "type": "Feature",
  "properties": {
    "addr:full":"40 Elgin St Quill Lake SK S0A 3E0",
    "addr:housenumber":"40",
    "addr:postcode":"s0a 3e0",
    "addr:street":"Elgin St",
    "iso:country":"CA",
    "sg:address":"40 Elgin St",
    "sg:city":"Quill Lake",
    "sg:classifiers":[
        {
            "category":"Wholesale",
            "subcategory":"Machinery & Supplies",
            "type":"Manufacturing & Wholesale Goods"
        }
    ],
    "sg:phone":"+1 306 383 2336",
    "sg:postcode":"S0A 3E0",
    "sg:province":"SK",
    "sg:tags":[
        "equipment",
        "industrial"
    ],
    "wof:name":"C D Finlayson Painting",
    "wof:placetype":"venue"
},
  "geometry": {"coordinates":[-104.256980896,52.069934845],"type":"Point"}
}