{
  "type": "Feature",
  "properties": {
    "iso:country":"CA",
    "sg:address":"5654 Strathcona St",
    "sg:city":"Port Alberni",
    "sg:classifiers":[
        {
            "category":"Building & Trades",
            "subcategory":"Plumbing",
            "type":"Services"
        }
    ],
    "sg:phone":"+1 250 724 3887",
    "sg:postcode":"V9Y 6X5",
    "sg:province":"BC",
    "sg:tags":[
        "heating",
        "contractor"
    ],
    "wof:name":"Dann Higgins Gas Svc",
    "wof:placetype":"venue"
},
  "geometry": {"coordinates":[-124.79724883999999,49.2737464905],"type":"Point"}
}