{
  "type": "Feature",
  "properties": {
    "addr:full":"206 4th Ave E Regina SK S4N 4Z6",
    "addr:housenumber":"206",
    "addr:postcode":"s4n 4z6",
    "addr:street":"4Th Ave E",
    "iso:country":"CA",
    "sg:address":"206 4th Ave E",
    "sg:city":"Regina",
    "sg:classifiers":[
        {
            "category":"Home & Garden",
            "subcategory":"Carpets & Floor Coverings",
            "type":"Retail Goods"
        }
    ],
    "sg:phone":"+1 306 359 6300",
    "sg:postcode":"S4N 4Z6",
    "sg:province":"SK",
    "wof:name":"Floors By Design",
    "wof:placetype":"venue"
},
  "geometry": {"coordinates":[-104.580185,50.463097],"type":"Point"}
}