{
  "type": "Feature",
  "properties": {
    "iso:country":"CA",
    "sg:address":"272 Codsell Ave",
    "sg:city":"North York",
    "sg:classifiers":[
        {
            "category":"Organizations",
            "subcategory":"Professional Association",
            "type":"Services"
        }
    ],
    "sg:phone":"+1 416 633 2511",
    "sg:postcode":"M3H 3X2",
    "sg:province":"ON",
    "sg:tags":[
        "club"
    ],
    "wof:name":"Camp Gesher",
    "wof:placetype":"venue"
},
  "geometry": {"coordinates":[-79.458862,43.754345],"type":"Point"}
}