{
  "type": "Feature",
  "properties": {
    "addr:full":"13313 Niagara Pky Niagara Falls ON L2E 6S6",
    "addr:housenumber":"13313",
    "addr:postcode":"l2e 6s6",
    "addr:street":"Niagara Pky",
    "iso:country":"CA",
    "sg:address":"13313 Niagara Pky",
    "sg:city":"Niagara Falls",
    "sg:classifiers":[
        {
            "category":"Organizations",
            "subcategory":"Religious Organization",
            "type":"Services"
        }
    ],
    "sg:phone":"+1 905 382 1118",
    "sg:postcode":"L2E 6S6",
    "sg:province":"ON",
    "wof:name":"Missionaries of Precious Blood",
    "wof:placetype":"venue"
},
  "geometry": {"coordinates":[-79.0280990601,42.9891586304],"type":"Point"}
}