{
  "type": "Feature",
  "properties": {
    "iso:country":"CA",
    "sg:city":"Ottawa",
    "sg:classifiers":[
        {
            "category":"Personal",
            "subcategory":"Beauty Salon",
            "type":"Services"
        }
    ],
    "sg:phone":"+1 613 820 5209",
    "sg:postcode":"K2B 7Z2",
    "sg:province":"ON",
    "wof:name":"Tweezer's Unisex Hair Design",
    "wof:placetype":"venue"
},
  "geometry": {"coordinates":[-75.785194397,45.3640632629],"type":"Point"}
}