{
  "type": "Feature",
  "properties": {
    "iso:country":"CA",
    "sg:address":"975 Fraser Dr",
    "sg:city":"Burlington",
    "sg:classifiers":[
        {
            "category":"Manufacturing",
            "subcategory":"Building Materials",
            "type":"Manufacturing & Wholesale Goods"
        }
    ],
    "sg:phone":"+1 905 631 8717",
    "sg:postcode":"L7L 4X8",
    "sg:province":"ON",
    "sg:tags":[
        "molding"
    ],
    "wof:name":"Bim Ltd",
    "wof:placetype":"venue"
},
  "geometry": {"coordinates":[-79.783867,43.367233],"type":"Point"}
}