{
  "type": "Feature",
  "properties": {
    "addr:full":"62 Eyre St Sudbury ON P3C 4A7",
    "addr:housenumber":"62",
    "addr:postcode":"p3c 4a7",
    "addr:street":"Eyre St",
    "iso:country":"CA",
    "sg:address":"62 Eyre St",
    "sg:city":"Sudbury",
    "sg:classifiers":[
        {
            "category":"Shopping",
            "subcategory":"Florist",
            "type":"Retail Goods"
        }
    ],
    "sg:phone":"+1 705 673 9561",
    "sg:postcode":"P3C 4A7",
    "sg:province":"ON",
    "sg:tags":[
        "plant"
    ],
    "wof:name":"Fleuriste Manhattan Flower",
    "wof:placetype":"venue"
},
  "geometry": {"coordinates":[-81.00824737550001,46.49168396],"type":"Point"}
}