{
  "type": "Feature",
  "properties": {
    "iso:country":"CA",
    "sg:address":"181 Livingstone St W",
    "sg:city":"Barrie",
    "sg:classifiers":[
        {
            "category":"Professional",
            "subcategory":"Business Services",
            "type":"Services"
        }
    ],
    "sg:phone":"+1 705 792 2093",
    "sg:postcode":"L4N 7J7",
    "sg:province":"ON",
    "sg:tags":[
        "water",
        "company",
        "treatment"
    ],
    "wof:name":"Water Depot",
    "wof:placetype":"venue"
},
  "geometry": {"coordinates":[-79.723145,44.404045],"type":"Point"}
}