{
  "type": "Feature",
  "properties": {
    "addr:full":"210 Boul Saint-Benoit O Amqui QC G5J 2E8",
    "addr:housenumber":"210",
    "addr:postcode":"g5j 2e8",
    "addr:street":"Boul Saint-Benoit O",
    "iso:country":"CA",
    "sg:address":"210 Boul Saint-Benoit O",
    "sg:city":"Amqui",
    "sg:classifiers":[
        {
            "category":"Travel",
            "subcategory":"Hotels & Motels",
            "type":"Entertainment"
        }
    ],
    "sg:phone":"+1 418 629 4575",
    "sg:postcode":"G5J 2E8",
    "sg:province":"QC",
    "wof:name":"Hotel Amqui",
    "wof:placetype":"venue"
},
  "geometry": {"coordinates":[-67.436317,48.467052],"type":"Point"}
}