{
  "type": "Feature",
  "properties": {
    "addr:full":"11952 224 St Maple Ridge BC V2X 6B3",
    "addr:housenumber":"11952",
    "addr:postcode":"v2x 6b3",
    "addr:street":"224 St",
    "iso:country":"CA",
    "sg:address":"11952 224 St",
    "sg:city":"Maple Ridge",
    "sg:classifiers":[
        {
            "category":"Restaurant",
            "type":"Food & Drink"
        }
    ],
    "sg:phone":"+1 604 467 6931",
    "sg:postcode":"V2X 6B3",
    "sg:province":"BC",
    "sg:tags":[
        "banquet",
        "rooms"
    ],
    "wof:name":"Look-Out Restaurant",
    "wof:placetype":"venue"
},
  "geometry": {"coordinates":[-122.601661682,49.2195625305],"type":"Point"}
}