{
  "type": "Feature",
  "properties": {
    "addr:full":"3925 Rue Bel-Air Saint-Hyacinthe QC J2S 7N8",
    "addr:housenumber":"3925",
    "addr:postcode":"j2s 7n8",
    "addr:street":"Rue Bel-Air",
    "iso:country":"CA",
    "sg:address":"3925 Rue Bel-Air",
    "sg:city":"Saint-Hyacinthe",
    "sg:classifiers":[
        {
            "category":"Organizations",
            "subcategory":"Religious Organization",
            "type":"Services"
        }
    ],
    "sg:phone":"+1 450 774 6996",
    "sg:postcode":"J2S 7N8",
    "sg:province":"QC",
    "sg:tags":[
        "church"
    ],
    "wof:name":"Eglise Betahnie Inc",
    "wof:placetype":"venue"
},
  "geometry": {"coordinates":[-72.97075700000001,45.607697],"type":"Point"}
}