{
  "type": "Feature",
  "properties": {
    "addr:full":"1131 Gordon St Guelph ON N1L 1H2",
    "addr:housenumber":"1131",
    "addr:postcode":"n1l 1h2",
    "addr:street":"Gordon St",
    "iso:country":"CA",
    "sg:address":"1131 Gordon St",
    "sg:city":"Guelph",
    "sg:classifiers":[
        {
            "category":"Utilities",
            "subcategory":"Water",
            "type":"Services"
        }
    ],
    "sg:phone":"+1 519 822 3039",
    "sg:postcode":"N1L 1H2",
    "sg:province":"ON",
    "sg:tags":[
        "system",
        "supply"
    ],
    "wof:name":"D M Davidson Water Pumping Eqp",
    "wof:placetype":"venue"
},
  "geometry": {"coordinates":[-80.20657300000001,43.518707],"type":"Point"}
}