{
  "type": "Feature",
  "properties": {
    "addr:full":"3088 42nd Ave W Vancouver BC V6N 3H2",
    "addr:housenumber":"3088",
    "addr:postcode":"v6n 3h2",
    "addr:street":"42Nd Ave W",
    "iso:country":"CA",
    "sg:address":"3088 42nd Ave W",
    "sg:city":"Vancouver",
    "sg:classifiers":[
        {
            "category":"Wholesale",
            "subcategory":"Construction Materials",
            "type":"Manufacturing & Wholesale Goods"
        }
    ],
    "sg:phone":"+1 604 264 9064",
    "sg:postcode":"V6N 3H2",
    "sg:province":"BC",
    "sg:tags":[
        "lumber"
    ],
    "wof:name":"Col-Pac Lumber CO",
    "wof:placetype":"venue"
},
  "geometry": {"coordinates":[-123.174194,49.233658],"type":"Point"}
}