{
  "type": "Feature",
  "properties": {
    "addr:full":"113 Main St Oyen AB T0J 2J0",
    "addr:housenumber":"113",
    "addr:postcode":"t0j 2j0",
    "addr:street":"Main St",
    "iso:country":"CA",
    "sg:address":"113 Main St",
    "sg:city":"Oyen",
    "sg:classifiers":[
        {
            "category":"Shopping",
            "subcategory":"Florist",
            "type":"Retail Goods"
        }
    ],
    "sg:phone":"+1 403 664 3827",
    "sg:postcode":"T0J 2J0",
    "sg:province":"AB",
    "wof:name":"Oyen Flowers & Giftware",
    "wof:placetype":"venue"
},
  "geometry": {"coordinates":[-110.483848572,51.3548049927],"type":"Point"}
}