{
  "type": "Feature",
  "properties": {
    "addr:full":"5606 Sixth Line Hillsburgh ON N0B 1Z0",
    "addr:housenumber":"5606",
    "addr:postcode":"n0b 1z0",
    "addr:street":"Sixth Line",
    "iso:country":"CA",
    "sg:address":"5606 Sixth Line",
    "sg:city":"Hillsburgh",
    "sg:classifiers":[
        {
            "category":"Retail",
            "subcategory":"Animal Services",
            "type":"Services"
        }
    ],
    "sg:phone":"+1 519 855 9588",
    "sg:postcode":"N0B 1Z0",
    "sg:province":"ON",
    "sg:tags":[
        "pet",
        "boarding",
        "sitting"
    ],
    "wof:name":"Houndhouse Boarding",
    "wof:placetype":"venue"
},
  "geometry": {"coordinates":[-80.1454772949,43.7913627625],"type":"Point"}
}