{
  "type": "Feature",
  "properties": {
    "addr:full":"40 Rue Sainte-Ursule Quebec QC G1R 4E2",
    "addr:housenumber":"40",
    "addr:postcode":"g1r 4e2",
    "addr:street":"Rue Sainte-Ursule",
    "iso:country":"CA",
    "sg:address":"40 Rue Sainte-Ursule",
    "sg:city":"Quebec",
    "sg:classifiers":[
        {
            "category":"Travel",
            "subcategory":"Hotels & Motels",
            "type":"Entertainment"
        }
    ],
    "sg:phone":"+1 418 694 9794",
    "sg:postcode":"G1R 4E2",
    "sg:province":"QC",
    "wof:name":"Hotel Maison Ste-Ursule",
    "wof:placetype":"venue"
},
  "geometry": {"coordinates":[-71.210587,46.811466],"type":"Point"}
}