{
  "type": "Feature",
  "properties": {
    "addr:full":"Toronto ON M5H 2Y4",
    "addr:postcode":"m5h 2y4",
    "iso:country":"CA",
    "sg:city":"Toronto",
    "sg:classifiers":[
        {
            "category":"Real Estate",
            "subcategory":"Real Estate Agent",
            "type":"Services"
        }
    ],
    "sg:phone":"+1 416 863 1215",
    "sg:postcode":"M5H 2Y4",
    "sg:province":"ON",
    "wof:name":"J J Barnicke Ltd",
    "wof:placetype":"venue"
},
  "geometry": {"coordinates":[-79.38149300000001,43.651821],"type":"Point"}
}