{
  "type": "Feature",
  "properties": {
    "addr:full":"Etobicoke ON M9B 1K8",
    "addr:postcode":"m9b 1k8",
    "iso:country":"CA",
    "sg:city":"Etobicoke",
    "sg:classifiers":[
        {
            "category":"Retail",
            "subcategory":"Portrait Studio",
            "type":"Services"
        }
    ],
    "sg:phone":"+1 416 231 6044",
    "sg:postcode":"M9B 1K8",
    "sg:province":"ON",
    "sg:tags":[
        "photographer"
    ],
    "wof:name":"Scuralli Photography",
    "wof:placetype":"venue"
},
  "geometry": {"coordinates":[-79.53780399999999,43.641403],"type":"Point"}
}