{
  "type": "Feature",
  "properties": {
    "addr:full":"2762 Rue DE LA Salle Jonquiere QC G7S 2A4",
    "addr:housenumber":"2762",
    "addr:postcode":"g7s 2a4",
    "addr:street":"Rue De La",
    "iso:country":"CA",
    "sg:address":"2762 Rue DE LA Salle",
    "sg:city":"Jonquiere",
    "sg:classifiers":[
        {
            "category":"Manufacturing",
            "subcategory":"Metals",
            "type":"Manufacturing & Wholesale Goods"
        }
    ],
    "sg:phone":"+1 418 548 4676",
    "sg:postcode":"G7S 2A4",
    "sg:province":"QC",
    "sg:tags":[
        "hardware"
    ],
    "wof:name":"Centre DE Renovation Fds Inc",
    "wof:placetype":"venue"
},
  "geometry": {"coordinates":[-71.17643,48.422035],"type":"Point"}
}