{
  "type": "Feature",
  "properties": {
    "iso:country":"CA",
    "sg:address":"231 Howey St",
    "sg:city":"Red Lake",
    "sg:classifiers":[
        {
            "category":"Shopping",
            "subcategory":"Bicycles & Sporting Goods",
            "type":"Retail Goods"
        }
    ],
    "sg:phone":"+1 807 727 2302",
    "sg:postcode":"P0V 2M0",
    "sg:province":"ON",
    "wof:name":"Northern Sporting Supplies",
    "wof:placetype":"venue"
},
  "geometry": {"coordinates":[-93.8296203613,51.0175323486],"type":"Point"}
}