{
  "type": "Feature",
  "properties": {
    "addr:full":"RR 3 Lcd 1 Cornwall ON K6H 5R7",
    "addr:housenumber":"1",
    "addr:postcode":"k6h 5r7",
    "addr:street":"Rr 3 Lcd",
    "iso:country":"CA",
    "sg:address":"RR 3 Lcd 1",
    "sg:city":"Cornwall",
    "sg:classifiers":[
        {
            "category":"Organizations",
            "subcategory":"Professional Association",
            "type":"Services"
        }
    ],
    "sg:phone":"+1 613 938 1176",
    "sg:postcode":"K6H 5R7",
    "sg:province":"ON",
    "wof:name":"Aboriginal Sport Circle",
    "wof:placetype":"venue"
},
  "geometry": {"coordinates":[-74.73569500000001,45.028435],"type":"Point"}
}