{
  "type": "Feature",
  "properties": {
    "addr:full":"2121 Carling Ave Ottawa ON K2A 1S3",
    "addr:housenumber":"2121",
    "addr:postcode":"k2a 1s3",
    "addr:street":"Carling Ave",
    "iso:country":"CA",
    "sg:address":"2121 Carling Ave",
    "sg:city":"Ottawa",
    "sg:classifiers":[
        {
            "category":"Shopping",
            "subcategory":"Jewelry",
            "type":"Retail Goods"
        }
    ],
    "sg:phone":"+1 613 728 2374",
    "sg:postcode":"K2A 1S3",
    "sg:province":"ON",
    "sg:tags":[
        "jeweler"
    ],
    "wof:name":"Ardene",
    "wof:placetype":"venue"
},
  "geometry": {"coordinates":[-75.76904296879999,45.3711280823],"type":"Point"}
}