{
  "type": "Feature",
  "properties": {
    "addr:full":"116 Rivercrest Cir SE Calgary AB T2C 4G4",
    "addr:housenumber":"116",
    "addr:postcode":"t2c 4g4",
    "addr:street":"Rivercrest Cir Se",
    "iso:country":"CA",
    "sg:address":"116 Rivercrest Cir SE",
    "sg:city":"Calgary",
    "sg:classifiers":[
        {
            "category":"Home & Garden",
            "subcategory":"Home Furnishings",
            "type":"Retail Goods"
        }
    ],
    "sg:phone":"+1 403 720 3207",
    "sg:postcode":"T2C 4G4",
    "sg:province":"AB",
    "sg:tags":[
        "venetian",
        "blind"
    ],
    "wof:name":"Aurora Blind Concepts",
    "wof:placetype":"venue"
},
  "geometry": {"coordinates":[-114.009254,50.978447],"type":"Point"}
}