{
  "type": "Feature",
  "properties": {
    "addr:full":"RR 3 STN Main Bracebridge ON P1L 1X1",
    "addr:postcode":"p1l 1x1",
    "addr:street":"Rr 3 Stn Main",
    "iso:country":"CA",
    "sg:address":"RR 3 STN Main",
    "sg:city":"Bracebridge",
    "sg:classifiers":[
        {
            "category":"Building & Trades",
            "subcategory":"Construction",
            "type":"Services"
        }
    ],
    "sg:phone":"+1 705 646 1303",
    "sg:postcode":"P1L 1X1",
    "sg:province":"ON",
    "sg:tags":[
        "insulation",
        "consultant",
        "contractor"
    ],
    "wof:name":"Muskoka Insulation Systems",
    "wof:placetype":"venue"
},
  "geometry": {"coordinates":[-79.2886352539,45.0555801392],"type":"Point"}
}