{
  "type": "Feature",
  "properties": {
    "iso:country":"CA",
    "sg:address":"180 Shirreff Ave # 100",
    "sg:city":"North Bay",
    "sg:classifiers":[
        {
            "category":"Cinema",
            "subcategory":"Movie Rental",
            "type":"Entertainment"
        }
    ],
    "sg:phone":"+1 705 472 3008",
    "sg:postcode":"P1B 7K9",
    "sg:province":"ON",
    "sg:tags":[
        "leasing",
        "video",
        "tape",
        "equipment"
    ],
    "wof:name":"Blockbuster Video",
    "wof:placetype":"venue"
},
  "geometry": {"coordinates":[-79.4643173218,46.3319664001],"type":"Point"}
}