{
  "type": "Feature",
  "properties": {
    "addr:full":"437 Rue Seigneuriale Beauport QC G1C 3R2",
    "addr:housenumber":"437",
    "addr:postcode":"qc g1c 3r2",
    "addr:street":"Rue Seigneuriale",
    "iso:country":"CA",
    "sg:address":"437 Rue Seigneuriale",
    "sg:city":"Beauport",
    "sg:classifiers":[
        {
            "category":"Professional",
            "subcategory":"Computer Services",
            "type":"Services"
        }
    ],
    "sg:phone":"+1 418 661 8172",
    "sg:postcode":"G1C 3R2",
    "sg:province":"QC",
    "sg:tags":[
        "repair",
        "television",
        "radio"
    ],
    "wof:name":"Audio Video Seigneuriale Enr",
    "wof:placetype":"venue"
},
  "geometry": {"coordinates":[-71.20933532710001,46.888092041],"type":"Point"}
}