{
  "type": "Feature",
  "properties": {
    "addr:full":"New Westminster BC V3L 5S5",
    "addr:postcode":"v3l 5s5",
    "iso:country":"CA",
    "sg:city":"New Westminster",
    "sg:classifiers":[
        {
            "category":"Real Estate",
            "subcategory":"Real Estate Agent",
            "type":"Services"
        }
    ],
    "sg:phone":"+1 604 525 3441",
    "sg:postcode":"V3L 5S5",
    "sg:province":"BC",
    "sg:tags":[
        "appraiser"
    ],
    "wof:name":"Penny & Keenleyside Appraisals",
    "wof:placetype":"venue"
},
  "geometry": {"coordinates":[-122.89471399999999,49.21843],"type":"Point"}
}