{
  "type": "Feature",
  "properties": {
    "iso:country":"CA",
    "sg:address":"7575 Rte Transcanadienne # 500",
    "sg:city":"Saint-Laurent",
    "sg:classifiers":[
        {
            "category":"Professional",
            "subcategory":"Management & Consulting",
            "type":"Services"
        }
    ],
    "sg:phone":"+1 514 337 1030",
    "sg:postcode":"H4T 1V6",
    "sg:province":"QC",
    "sg:tags":[
        "marketing",
        "consultant"
    ],
    "wof:name":"Vortex A1 Distributions",
    "wof:placetype":"venue"
},
  "geometry": {"coordinates":[-73.71087646479999,45.4893417358],"type":"Point"}
}