{
  "type": "Feature",
  "properties": {
    "addr:full":"2922 Eglinton Ave E Scarborough ON M1J 2E4",
    "addr:housenumber":"2922",
    "addr:postcode":"m1j 2e4",
    "addr:street":"Eglinton Ave E",
    "iso:country":"CA",
    "sg:address":"2922 Eglinton Ave E",
    "sg:city":"Scarborough",
    "sg:classifiers":[
        {
            "category":"Shopping",
            "subcategory":"Discount & Variety Stores",
            "type":"Retail Goods"
        }
    ],
    "sg:phone":"+1 416 431 4474",
    "sg:postcode":"M1J 2E4",
    "sg:province":"ON",
    "wof:name":"Top Milk Mart",
    "wof:placetype":"venue"
},
  "geometry": {"coordinates":[-79.236763,43.739376],"type":"Point"}
}