{
  "type": "Feature",
  "properties": {
    "addr:full":"1451 Av Royale Saint-Jean-D'Orleans QC G0A 3W0",
    "addr:housenumber":"1451",
    "addr:postcode":"g0a 3w0",
    "addr:street":"Av Royale",
    "iso:country":"CA",
    "sg:address":"1451 Av Royale",
    "sg:city":"Saint-Jean-D'Orleans",
    "sg:classifiers":[
        {
            "category":"Recreation",
            "type":"Entertainment"
        }
    ],
    "sg:phone":"+1 418 829 2630",
    "sg:postcode":"G0A 3W0",
    "sg:province":"QC",
    "sg:tags":[
        "historical"
    ],
    "wof:name":"Manoir Mauvide-Genest",
    "wof:placetype":"venue"
},
  "geometry": {"coordinates":[-70.8993,47.080978],"type":"Point"}
}