{
  "type": "Feature",
  "properties": {
    "addr:full":"12 Maitland Terr Strathroy ON N7G 1L1",
    "addr:housenumber":"12",
    "addr:postcode":"n7g 1l1",
    "addr:street":"Maitland Terr",
    "iso:country":"CA",
    "sg:address":"12 Maitland Terr",
    "sg:city":"Strathroy",
    "sg:classifiers":[
        {
            "category":"Building & Trades",
            "subcategory":"Construction",
            "type":"Services"
        }
    ],
    "sg:phone":"+1 519 245 5675",
    "sg:postcode":"N7G 1L1",
    "sg:province":"ON",
    "sg:tags":[
        "well",
        "drilling"
    ],
    "wof:name":"Ron Smith Well Drilling",
    "wof:placetype":"venue"
},
  "geometry": {"coordinates":[-81.62050600000001,42.953857],"type":"Point"}
}