{
  "type": "Feature",
  "properties": {
    "addr:full":"802 Rue Du Ruisseau Deux-Montagnes QC J7R 5X4",
    "addr:housenumber":"802",
    "addr:postcode":"j7r 5x4",
    "addr:street":"Rue Du Ruisseau",
    "iso:country":"CA",
    "sg:address":"802 Rue Du Ruisseau",
    "sg:city":"Deux-Montagnes",
    "sg:classifiers":[
        {
            "category":"Professional",
            "subcategory":"Computer Services",
            "type":"Services"
        }
    ],
    "sg:phone":"+1 450 491 7033",
    "sg:postcode":"J7R 5X4",
    "sg:province":"QC",
    "sg:tags":[
        "information",
        "system",
        "consultant"
    ],
    "wof:name":"Ddn Informatique Inc",
    "wof:placetype":"venue"
},
  "geometry": {"coordinates":[-73.905083,45.550465],"type":"Point"}
}