{
  "type": "Feature",
  "properties": {
    "addr:full":"1933 45 Ave SW Calgary AB T2T 2P4",
    "addr:housenumber":"1933",
    "addr:postcode":"t2t 2p4",
    "addr:street":"45 Ave Sw",
    "iso:country":"CA",
    "sg:address":"1933 45 Ave SW",
    "sg:city":"Calgary",
    "sg:classifiers":[
        {
            "category":"Building & Trades",
            "subcategory":"Cleaning & Sanitation",
            "type":"Services"
        }
    ],
    "sg:phone":"+1 403 243 7911",
    "sg:postcode":"T2T 2P4",
    "sg:province":"AB",
    "sg:tags":[
        "window"
    ],
    "wof:name":"A-Window Cleaners",
    "wof:placetype":"venue"
},
  "geometry": {"coordinates":[-114.105225,51.013126],"type":"Point"}
}