{
  "type": "Feature",
  "properties": {
    "addr:full":"48 Marine Dr Grand Bank NL A0E 1W0",
    "addr:housenumber":"48",
    "addr:postcode":"a0e 1w0",
    "addr:street":"Marine Dr",
    "iso:country":"CA",
    "sg:address":"48 Marine Dr",
    "sg:city":"Grand Bank",
    "sg:classifiers":[
        {
            "category":"Retail",
            "subcategory":"Funeral Services",
            "type":"Services"
        }
    ],
    "sg:phone":"+1 709 832 1992",
    "sg:postcode":"A0E 1W0",
    "sg:province":"NL",
    "sg:tags":[
        "director"
    ],
    "wof:name":"Warren's Funeral Home",
    "wof:placetype":"venue"
},
  "geometry": {"coordinates":[-55.74033,47.095806],"type":"Point"}
}