{
  "type": "Feature",
  "properties": {
    "addr:full":"Kingston ON K7P 2S6",
    "addr:postcode":"k7p 2s6",
    "iso:country":"CA",
    "sg:city":"Kingston",
    "sg:classifiers":[
        {
            "category":"Organizations",
            "subcategory":"Professional Association",
            "type":"Services"
        }
    ],
    "sg:phone":"+1 613 389 3921",
    "sg:postcode":"K7P 2S6",
    "sg:province":"ON",
    "wof:name":"Disability Consultants Inc",
    "wof:placetype":"venue"
},
  "geometry": {"coordinates":[-76.57722473139999,44.2574615479],"type":"Point"}
}