{
  "type": "Feature",
  "properties": {
    "addr:full":"Newmarket ON L3Y 2N1",
    "addr:postcode":"l3y 2n1",
    "iso:country":"CA",
    "sg:city":"Newmarket",
    "sg:classifiers":[
        {
            "category":"Personal",
            "type":"Services"
        }
    ],
    "sg:phone":"+1 905 836 5070",
    "sg:postcode":"L3Y 2N1",
    "sg:province":"ON",
    "sg:tags":[
        "program",
        "physical",
        "exercise",
        "fitness"
    ],
    "wof:name":"Curves For Women",
    "wof:placetype":"venue"
},
  "geometry": {"coordinates":[-79.47482299799999,44.0559196472],"type":"Point"}
}