{
  "type": "Feature",
  "properties": {
    "iso:country":"CA",
    "sg:city":"Thornhill",
    "sg:classifiers":[
        {
            "category":"Personal",
            "subcategory":"Shoe Repair & Shine",
            "type":"Services"
        }
    ],
    "sg:phone":"+1 905 886 8414",
    "sg:postcode":"L3T 4X1",
    "sg:province":"ON",
    "sg:tags":[
        "repairing",
        "boot"
    ],
    "wof:name":"Sole Perfection Shoe Repair",
    "wof:placetype":"venue"
},
  "geometry": {"coordinates":[-79.359207,43.811752],"type":"Point"}
}