{
  "type": "Feature",
  "properties": {
    "iso:country":"CA",
    "sg:address":"327 Boul Labelle",
    "sg:city":"Sainte-Therese",
    "sg:classifiers":[
        {
            "category":"Restaurant",
            "type":"Food & Drink"
        }
    ],
    "sg:phone":"+1 450 430 2988",
    "sg:postcode":"J7E 2Y2",
    "sg:province":"QC",
    "wof:name":"Pasta Express",
    "wof:placetype":"venue"
},
  "geometry": {"coordinates":[-73.8417053223,45.648475647],"type":"Point"}
}