{
  "type": "Feature",
  "properties": {
    "addr:full":"1727 Boul DE Perigny Chambly QC J3L 4C3",
    "addr:housenumber":"1727",
    "addr:postcode":"j3l 4c3",
    "addr:street":"Boul De Perigny",
    "iso:country":"CA",
    "sg:address":"1727 Boul DE Perigny",
    "sg:city":"Chambly",
    "sg:classifiers":[
        {
            "category":"Home & Garden",
            "subcategory":"Building Materials",
            "type":"Retail Goods"
        }
    ],
    "sg:phone":"+1 450 658 2043",
    "sg:postcode":"J3L 4C3",
    "sg:province":"QC",
    "sg:tags":[
        "plumbing",
        "fixture",
        "supply"
    ],
    "wof:name":"Plomberie Perigny Inc",
    "wof:placetype":"venue"
},
  "geometry": {"coordinates":[-73.27647399999999,45.443298],"type":"Point"}
}