{
  "type": "Feature",
  "properties": {
    "iso:country":"CA",
    "sg:city":"Lloydminster",
    "sg:classifiers":[
        {
            "category":"Retail",
            "subcategory":"Auto Repair",
            "type":"Services"
        }
    ],
    "sg:phone":"+1 780 875 1721",
    "sg:postcode":"T9V 2V3",
    "sg:province":"AB",
    "sg:tags":[
        "body",
        "automobile",
        "painting"
    ],
    "wof:name":"All-NU Autobody Ltd",
    "wof:placetype":"venue"
},
  "geometry": {"coordinates":[-110.03073120099999,53.2770271301],"type":"Point"}
}