{
  "type": "Feature",
  "properties": {
    "addr:full":"74 Market St Seaforth ON N0K 1W0",
    "addr:housenumber":"74",
    "addr:postcode":"n0k 1w0",
    "addr:street":"Market St",
    "iso:country":"CA",
    "sg:address":"74 Market St",
    "sg:city":"Seaforth",
    "sg:classifiers":[
        {
            "category":"Building & Trades",
            "subcategory":"Plumbing",
            "type":"Services"
        }
    ],
    "sg:phone":"+1 519 527 0284",
    "sg:postcode":"N0K 1W0",
    "sg:province":"ON",
    "sg:tags":[
        "septic"
    ],
    "wof:name":"H T Dale Septic Tank Svc",
    "wof:placetype":"venue"
},
  "geometry": {"coordinates":[-81.3985824585,43.553314209],"type":"Point"}
}