{
  "type": "Feature",
  "properties": {
    "iso:country":"CA",
    "sg:address":"5539 38 St",
    "sg:city":"Red Deer",
    "sg:classifiers":[
        {
            "category":"Wholesale",
            "subcategory":"Hardware",
            "type":"Manufacturing & Wholesale Goods"
        }
    ],
    "sg:phone":"+1 403 343 6804",
    "sg:postcode":"T4N 0X7",
    "sg:province":"AB",
    "sg:tags":[
        "furnace"
    ],
    "wof:name":"Rhodes Sheet Metal & Furnace",
    "wof:placetype":"venue"
},
  "geometry": {"coordinates":[-113.828155518,52.2583312988],"type":"Point"}
}