{
  "type": "Feature",
  "properties": {
    "addr:full":"4288 Village Centre Crt Mississauga ON L4Z 1S2",
    "addr:housenumber":"4288",
    "addr:postcode":"l4z 1s2",
    "addr:street":"Village Centre Crt",
    "iso:country":"CA",
    "sg:address":"4288 Village Centre Crt",
    "sg:city":"Mississauga",
    "sg:classifiers":[
        {
            "category":"Health Services",
            "subcategory":"Doctor",
            "type":"Services"
        }
    ],
    "sg:phone":"+1 905 275 0058",
    "sg:postcode":"L4Z 1S2",
    "sg:province":"ON",
    "sg:tags":[
        "dentist"
    ],
    "wof:name":"Lamantia, Peter D DDS",
    "wof:placetype":"venue"
},
  "geometry": {"coordinates":[-79.6405792236,43.6009788513],"type":"Point"}
}