{
  "type": "Feature",
  "properties": {
    "addr:full":"18 Rue Saint-Basile Metabetchouan-Lac-A-LA-Croix QC G8G 1S7",
    "addr:housenumber":"18",
    "addr:postcode":"g8g 1s7",
    "addr:street":"Rue Saint-Basile",
    "iso:country":"CA",
    "sg:address":"18 Rue Saint-Basile",
    "sg:city":"Metabetchouan-Lac-A-LA-Croix",
    "sg:classifiers":[
        {
            "category":"Shopping",
            "subcategory":"Pharmacy",
            "type":"Retail Goods"
        }
    ],
    "sg:phone":"+1 418 349 2853",
    "sg:postcode":"G8G 1S7",
    "sg:province":"QC",
    "wof:name":"Jean Cloutier Pharmacien",
    "wof:placetype":"venue"
},
  "geometry": {"coordinates":[-71.87139892579999,48.426738739],"type":"Point"}
}