{
  "type": "Feature",
  "properties": {
    "addr:full":"7621 Edmonds St Burnaby BC V3N 1B6",
    "addr:housenumber":"7621",
    "addr:postcode":"v3n 1b6",
    "addr:street":"Edmonds St",
    "iso:country":"CA",
    "sg:address":"7621 Edmonds St",
    "sg:city":"Burnaby",
    "sg:classifiers":[
        {
            "category":"Autos & Motor Vehicles",
            "subcategory":"Automobile Sales",
            "type":"Retail Goods"
        }
    ],
    "sg:phone":"+1 604 521 6300",
    "sg:postcode":"V3N 1B6",
    "sg:province":"BC",
    "sg:tags":[
        "car",
        "dealer"
    ],
    "wof:name":"Elegant Motors Ltd",
    "wof:placetype":"venue"
},
  "geometry": {"coordinates":[-122.942581,49.223381],"type":"Point"}
}