{
  "type": "Feature",
  "properties": {
    "addr:full":"20 Ed Connelly Dr Perkinsfield ON L0L 2J0",
    "addr:housenumber":"20",
    "addr:postcode":"l0l 2j0",
    "addr:street":"Ed Connelly Dr",
    "iso:country":"CA",
    "sg:address":"20 Ed Connelly Dr",
    "sg:city":"Perkinsfield",
    "sg:classifiers":[
        {
            "category":"Government",
            "subcategory":"Office",
            "type":"Public Place"
        }
    ],
    "sg:phone":"+1 705 526 8086",
    "sg:postcode":"L0L 2J0",
    "sg:province":"ON",
    "sg:tags":[
        "airport",
        "village"
    ],
    "wof:name":"Huronia Airport",
    "wof:placetype":"venue"
},
  "geometry": {"coordinates":[-79.930756,44.691265],"type":"Point"}
}