{
  "type": "Feature",
  "properties": {
    "addr:full":"62 Hymus Rd Scarborough ON M1L 2C7",
    "addr:housenumber":"62",
    "addr:postcode":"m1l 2c7",
    "addr:street":"Hymus Rd",
    "iso:country":"CA",
    "sg:address":"62 Hymus Rd",
    "sg:city":"Scarborough",
    "sg:classifiers":[
        {
            "category":"Manufacturing",
            "subcategory":"Printing",
            "type":"Manufacturing & Wholesale Goods"
        }
    ],
    "sg:phone":"+1 416 288 1857",
    "sg:postcode":"M1L 2C7",
    "sg:province":"ON",
    "sg:tags":[
        "screen"
    ],
    "wof:name":"Tung Fat Brush Mfg Ltd",
    "wof:placetype":"venue"
},
  "geometry": {"coordinates":[-79.28513336180001,43.7194786072],"type":"Point"}
}