{
  "type": "Feature",
  "properties": {
    "addr:full":"Trois-Rivieres QC G9A 3P1",
    "addr:postcode":"g9a 3p1",
    "iso:country":"CA",
    "sg:city":"Trois-Rivieres",
    "sg:classifiers":[
        {
            "category":"Recreation",
            "type":"Entertainment"
        }
    ],
    "sg:phone":"+1 819 694 4585",
    "sg:postcode":"G9A 3P1",
    "sg:province":"QC",
    "sg:tags":[
        "bingo",
        "game"
    ],
    "wof:name":"Regroupement Bingos Tr Inc",
    "wof:placetype":"venue"
},
  "geometry": {"coordinates":[-72.543098,46.353718],"type":"Point"}
}