{
  "type": "Feature",
  "properties": {
    "addr:full":"100 Bruce St Haileybury ON P0J 1K0",
    "addr:housenumber":"100",
    "addr:postcode":"p0j 1k0",
    "addr:street":"Bruce St",
    "iso:country":"CA",
    "sg:address":"100 Bruce St",
    "sg:city":"Haileybury",
    "sg:classifiers":[
        {
            "category":"Health Services",
            "subcategory":"Nursing And Care Facility",
            "type":"Services"
        }
    ],
    "sg:phone":"+1 705 672 2123",
    "sg:postcode":"P0J 1K0",
    "sg:province":"ON",
    "sg:tags":[
        "home",
        "convalescent"
    ],
    "wof:name":"Temiskaming Lodge",
    "wof:placetype":"venue"
},
  "geometry": {"coordinates":[-79.630341,47.43914],"type":"Point"}
}