{
  "type": "Feature",
  "properties": {
    "addr:full":"792 107th St North Battleford SK S9A 4A7",
    "addr:housenumber":"792",
    "addr:postcode":"s9a 4a7",
    "addr:street":"107Th St",
    "iso:country":"CA",
    "sg:address":"792 107th St",
    "sg:city":"North Battleford",
    "sg:classifiers":[
        {
            "category":"Organizations",
            "subcategory":"Religious Organization",
            "type":"Services"
        }
    ],
    "sg:phone":"+1 306 446 0440",
    "sg:postcode":"S9A 4A7",
    "sg:province":"SK",
    "sg:tags":[
        "church"
    ],
    "wof:name":"Jesus Is Alive",
    "wof:placetype":"venue"
},
  "geometry": {"coordinates":[-108.288628,52.768684],"type":"Point"}
}