{
  "type": "Feature",
  "properties": {
    "addr:full":"2120 Vincent Massey Dr Cornwall ON K6H 5R6",
    "addr:housenumber":"2120",
    "addr:postcode":"k6h 5r6",
    "addr:street":"Vincent Massey Dr",
    "iso:country":"CA",
    "sg:address":"2120 Vincent Massey Dr",
    "sg:city":"Cornwall",
    "sg:classifiers":[
        {
            "category":"Travel",
            "subcategory":"Hotels & Motels",
            "type":"Entertainment"
        }
    ],
    "sg:phone":"+1 613 932 9623",
    "sg:postcode":"K6H 5R6",
    "sg:province":"ON",
    "wof:name":"Nites Inn",
    "wof:placetype":"venue"
},
  "geometry": {"coordinates":[-74.780357,45.031639],"type":"Point"}
}