{
  "type": "Feature",
  "properties": {
    "addr:full":"48 1st Ave NE Preeceville SK S0A 3B0",
    "addr:housenumber":"48",
    "addr:postcode":"s0a 3b0",
    "addr:street":"1St Ave Ne",
    "iso:country":"CA",
    "sg:address":"48 1st Ave NE",
    "sg:city":"Preeceville",
    "sg:classifiers":[
        {
            "category":"Professional",
            "subcategory":"Accounting & Tax Preparation",
            "type":"Services"
        }
    ],
    "sg:phone":"+1 306 547 3130",
    "sg:postcode":"S0A 3B0",
    "sg:province":"SK",
    "sg:tags":[
        "accountant"
    ],
    "wof:name":"Active Accounting Ltd",
    "wof:placetype":"venue"
},
  "geometry": {"coordinates":[-102.66686199999999,51.955147],"type":"Point"}
}