{
  "type": "Feature",
  "properties": {
    "addr:full":"6252 Cedar Creek Rd Likely BC V0L 1N0",
    "addr:housenumber":"6252",
    "addr:postcode":"v0l 1n0",
    "addr:street":"Cedar Creek Rd",
    "iso:country":"CA",
    "sg:address":"6252 Cedar Creek Rd",
    "sg:city":"Likely",
    "sg:classifiers":[
        {
            "category":"Travel",
            "subcategory":"Hotels & Motels",
            "type":"Entertainment"
        }
    ],
    "sg:phone":"+1 250 790 2218",
    "sg:postcode":"V0L 1N0",
    "sg:province":"BC",
    "wof:name":"High Country Inn",
    "wof:placetype":"venue"
},
  "geometry": {"coordinates":[-121.569847107,52.617023468],"type":"Point"}
}