{
  "type": "Feature",
  "properties": {
    "addr:full":"96 Terminal Ave N Nanaimo BC V9S 4J2",
    "addr:housenumber":"96",
    "addr:postcode":"v9s 4j2",
    "addr:street":"Terminal Ave N",
    "iso:country":"CA",
    "sg:address":"96 Terminal Ave N",
    "sg:city":"Nanaimo",
    "sg:classifiers":[
        {
            "category":"Travel",
            "subcategory":"Hotels & Motels",
            "type":"Entertainment"
        }
    ],
    "sg:phone":"+1 250 754 6355",
    "sg:postcode":"V9S 4J2",
    "sg:province":"BC",
    "wof:name":"Travelodge-Nanaimo",
    "wof:placetype":"venue"
},
  "geometry": {"coordinates":[-123.941711,49.171829],"type":"Point"}
}