{
  "type": "Feature",
  "properties": {
    "addr:full":"Etobicoke ON M9W 6M6",
    "addr:postcode":"m9w 6m6",
    "iso:country":"CA",
    "sg:city":"Etobicoke",
    "sg:classifiers":[
        {
            "category":"Building & Trades",
            "subcategory":"Plumbing",
            "type":"Services"
        }
    ],
    "sg:phone":"+1 416 674 1947",
    "sg:postcode":"M9W 6M6",
    "sg:province":"ON",
    "sg:tags":[
        "conditioning",
        "air",
        "system",
        "contractor"
    ],
    "wof:name":"Field Temperature Control Ltd",
    "wof:placetype":"venue"
},
  "geometry": {"coordinates":[-79.620087,43.752445],"type":"Point"}
}