{
  "type": "Feature",
  "properties": {
    "addr:full":"518 Victoria Ave Windsor ON N9A 4M8",
    "addr:housenumber":"518",
    "addr:postcode":"n9a 4m8",
    "addr:street":"Victoria Ave",
    "iso:country":"CA",
    "sg:address":"518 Victoria Ave",
    "sg:city":"Windsor",
    "sg:classifiers":[
        {
            "category":"Professional",
            "subcategory":"Lawyer & Legal Services",
            "type":"Services"
        }
    ],
    "sg:phone":"+1 519 255 9442",
    "sg:postcode":"N9A 4M8",
    "sg:province":"ON",
    "sg:tags":[
        "attorney"
    ],
    "wof:name":"Perfect, Edward A",
    "wof:placetype":"venue"
},
  "geometry": {"coordinates":[-83.039299,42.314533],"type":"Point"}
}