{
  "type": "Feature",
  "properties": {
    "addr:full":"4309 Skiers Approach Whistler BC V0N 1B4",
    "addr:housenumber":"4309",
    "addr:postcode":"v0n 1b4",
    "addr:street":"Skiers Approach",
    "iso:country":"CA",
    "sg:address":"4309 Skiers Approach",
    "sg:city":"Whistler",
    "sg:classifiers":[
        {
            "category":"Shopping",
            "subcategory":"Bicycles & Sporting Goods",
            "type":"Retail Goods"
        }
    ],
    "sg:phone":"+1 604 932 3659",
    "sg:postcode":"V0N 1B4",
    "sg:province":"BC",
    "wof:name":"Mountain Riders",
    "wof:placetype":"venue"
},
  "geometry": {"coordinates":[-122.954345703,50.1136627197],"type":"Point"}
}