{
  "type": "Feature",
  "properties": {
    "addr:full":"Penticton Airport Penticton BC V2A 6J7",
    "addr:postcode":"v2a 6j7",
    "iso:country":"CA",
    "sg:address":"Penticton Airport",
    "sg:city":"Penticton",
    "sg:classifiers":[
        {
            "category":"Retail",
            "subcategory":"Auto Rental",
            "type":"Services"
        }
    ],
    "sg:phone":"+1 250 493 0212",
    "sg:postcode":"V2A 6J7",
    "sg:province":"BC",
    "sg:tags":[
        "renting",
        "automobile"
    ],
    "wof:name":"Budget Car & Truck Rental",
    "wof:placetype":"venue"
},
  "geometry": {"coordinates":[-119.605507,49.46143],"type":"Point"}
}