{
  "type": "Feature",
  "properties": {
    "addr:full":"1970 Brock Rd Pickering ON L1V 1Y3",
    "addr:housenumber":"1970",
    "addr:postcode":"l1v 1y3",
    "addr:street":"Brock Rd",
    "iso:country":"CA",
    "sg:address":"1970 Brock Rd",
    "sg:city":"Pickering",
    "sg:classifiers":[
        {
            "category":"Real Estate",
            "subcategory":"Real Estate Agent",
            "type":"Services"
        }
    ],
    "sg:phone":"+1 905 427 6522",
    "sg:postcode":"L1V 1Y3",
    "sg:province":"ON",
    "wof:name":"Royal Le Page Connect Realty",
    "wof:placetype":"venue"
},
  "geometry": {"coordinates":[-79.0746231079,43.8487472534],"type":"Point"}
}