{
  "type": "Feature",
  "properties": {
    "addr:full":"9880 Rue Verville Montreal QC H3L 3E2",
    "addr:housenumber":"9880",
    "addr:postcode":"h3l 3e2",
    "addr:street":"Rue Verville",
    "iso:country":"CA",
    "sg:address":"9880 Rue Verville",
    "sg:city":"Montreal",
    "sg:classifiers":[
        {
            "category":"Manufacturing",
            "subcategory":"Apparel",
            "type":"Manufacturing & Wholesale Goods"
        }
    ],
    "sg:phone":"+1 514 384 8080",
    "sg:postcode":"H3L 3E2",
    "sg:province":"QC",
    "sg:tags":[
        "costume"
    ],
    "wof:name":"Productions Bizz-Art",
    "wof:placetype":"venue"
},
  "geometry": {"coordinates":[-73.662971,45.541332],"type":"Point"}
}