{
  "type": "Feature",
  "properties": {
    "iso:country":"CA",
    "sg:city":"Vancouver",
    "sg:classifiers":[
        {
            "category":"Communications",
            "subcategory":"Film & Video Production",
            "type":"Services"
        }
    ],
    "sg:phone":"+1 604 707 0636",
    "sg:postcode":"V5T 1B7",
    "sg:province":"BC",
    "sg:tags":[
        "motion",
        "picture",
        "studio",
        "producer"
    ],
    "wof:name":"Quixote Films Inc",
    "wof:placetype":"venue"
},
  "geometry": {"coordinates":[-123.099525,49.268372],"type":"Point"}
}