{
  "type": "Feature",
  "properties": {
    "addr:full":"6030 Whitehall Rd Grand Forks BC V0H 1H9",
    "addr:housenumber":"6030",
    "addr:postcode":"v0h 1h9",
    "addr:street":"Whitehall Rd",
    "iso:country":"CA",
    "sg:address":"6030 Whitehall Rd",
    "sg:city":"Grand Forks",
    "sg:classifiers":[
        {
            "category":"Building & Trades",
            "subcategory":"Construction",
            "type":"Services"
        }
    ],
    "sg:phone":"+1 250 442 2797",
    "sg:postcode":"V0H 1H9",
    "sg:province":"BC",
    "sg:tags":[
        "maker",
        "cabinet"
    ],
    "wof:name":"Cascade Custom Cabinetry",
    "wof:placetype":"venue"
},
  "geometry": {"coordinates":[-118.443260193,49.032371521],"type":"Point"}
}