{
  "type": "Feature",
  "properties": {
    "addr:full":"232 Rue Panneton Asbestos QC J1T 2K1",
    "addr:housenumber":"232",
    "addr:postcode":"j1t 2k1",
    "addr:street":"Rue Panneton",
    "iso:country":"CA",
    "sg:address":"232 Rue Panneton",
    "sg:city":"Asbestos",
    "sg:classifiers":[
        {
            "category":"Building & Trades",
            "subcategory":"Electrical",
            "type":"Services"
        }
    ],
    "sg:phone":"+1 819 879 2414",
    "sg:postcode":"J1T 2K1",
    "sg:province":"QC",
    "sg:tags":[
        "electric",
        "contractor"
    ],
    "wof:name":"Lussier Electrique Inc",
    "wof:placetype":"venue"
},
  "geometry": {"coordinates":[-71.940659,45.768993],"type":"Point"}
}