{
  "type": "Feature",
  "properties": {
    "iso:country":"CA",
    "sg:city":"Cap-DE-LA-Madeleine",
    "sg:classifiers":[
        {
            "category":"Personal",
            "subcategory":"Beauty Salon",
            "type":"Services"
        }
    ],
    "sg:phone":"+1 819 375 5752",
    "sg:postcode":"G8T 7A4",
    "sg:province":"QC",
    "wof:name":"Coiffures Les Plateaux Enr",
    "wof:placetype":"venue"
},
  "geometry": {"coordinates":[-72.548653,46.385128],"type":"Point"}
}