{
  "type": "Feature",
  "properties": {
    "iso:country":"CA",
    "sg:address":"100 Rue Saint-Hilaire",
    "sg:city":"Saint-Cyrille-DE-Wendover",
    "sg:classifiers":[
        {
            "category":"Wholesale",
            "subcategory":"Construction Materials",
            "type":"Manufacturing & Wholesale Goods"
        }
    ],
    "sg:phone":"+1 819 397 5445",
    "sg:postcode":"J1Z 1T5",
    "sg:province":"QC",
    "sg:tags":[
        "lumber"
    ],
    "wof:name":"Materiaux Berfranc Inc",
    "wof:placetype":"venue"
},
  "geometry": {"coordinates":[-72.4247512817,45.9301452637],"type":"Point"}
}