{
  "type": "Feature",
  "properties": {
    "addr:full":"Sooke BC V0S 1N0",
    "addr:postcode":"v0s 1n0",
    "iso:country":"CA",
    "sg:city":"Sooke",
    "sg:classifiers":[
        {
            "category":"Travel",
            "subcategory":"Travel Agent",
            "type":"Entertainment"
        }
    ],
    "sg:phone":"+1 250 642 6331",
    "sg:postcode":"V0S 1N0",
    "sg:province":"BC",
    "sg:tags":[
        "agency",
        "bureau"
    ],
    "wof:name":"Sooke Travel Ltd",
    "wof:placetype":"venue"
},
  "geometry": {"coordinates":[-123.721664,48.378365],"type":"Point"}
}