{
  "type": "Feature",
  "properties": {
    "addr:full":"1185 Rue Saint-Mathieu Montreal QC H3H 2P7",
    "addr:housenumber":"1185",
    "addr:postcode":"h3h 2p7",
    "addr:street":"Rue Saint-Mathieu",
    "iso:country":"CA",
    "sg:address":"1185 Rue Saint-Mathieu",
    "sg:city":"Montreal",
    "sg:classifiers":[
        {
            "category":"Social Services",
            "type":"Services"
        }
    ],
    "sg:phone":"+1 514 932 7656",
    "sg:postcode":"H3H 2P7",
    "sg:province":"QC",
    "sg:tags":[
        "organization",
        "association",
        "welfare"
    ],
    "wof:name":"Bureau Intl Des Droits Des",
    "wof:placetype":"venue"
},
  "geometry": {"coordinates":[-73.577309,45.492912],"type":"Point"}
}