{
  "type": "Feature",
  "properties": {
    "addr:full":"36 Wellington St N Woodstock ON N4S 6P3",
    "addr:housenumber":"36",
    "addr:postcode":"n4s 6p3",
    "addr:street":"Wellington St N",
    "iso:country":"CA",
    "sg:address":"36 Wellington St N",
    "sg:city":"Woodstock",
    "sg:classifiers":[
        {
            "category":"Health Services",
            "subcategory":"Doctor",
            "type":"Services"
        }
    ],
    "sg:phone":"+1 519 539 4712",
    "sg:postcode":"N4S 6P3",
    "sg:province":"ON",
    "sg:tags":[
        "dentist"
    ],
    "wof:name":"Lail, Bob DDS",
    "wof:placetype":"venue"
},
  "geometry": {"coordinates":[-80.754822,43.131596],"type":"Point"}
}