{
  "type": "Feature",
  "properties": {
    "addr:full":"PO Box 2317 STN Main Athabasca AB T9S 2B8",
    "addr:housenumber":"po",
    "addr:postcode":"2317;t9s 2b8",
    "addr:street":"Box;Stn Main",
    "iso:country":"CA",
    "sg:address":"PO Box 2317 STN Main",
    "sg:city":"Athabasca",
    "sg:classifiers":[
        {
            "category":"Organizations",
            "subcategory":"Religious Organization",
            "type":"Services"
        }
    ],
    "sg:phone":"+1 403 675 2477",
    "sg:postcode":"T9S 2B8",
    "sg:province":"AB",
    "sg:tags":[
        "church"
    ],
    "wof:name":"Zion Lutheran Church",
    "wof:placetype":"venue"
},
  "geometry": {"coordinates":[-113.28351592999999,54.7212333679],"type":"Point"}
}