{
  "type": "Feature",
  "properties": {
    "addr:full":"104 East Lake Rd NE Airdrie AB T4A 2J8",
    "addr:housenumber":"104",
    "addr:postcode":"t4a 2j8",
    "addr:street":"East Lake Rd Ne",
    "iso:country":"CA",
    "sg:address":"104 East Lake Rd NE",
    "sg:city":"Airdrie",
    "sg:classifiers":[
        {
            "category":"Mining & Drilling",
            "type":"Manufacturing & Wholesale Goods"
        }
    ],
    "sg:phone":"+1 403 912 3690",
    "sg:postcode":"T4A 2J8",
    "sg:province":"AB",
    "sg:tags":[
        "field",
        "oil"
    ],
    "wof:name":"United Safety Ltd",
    "wof:placetype":"venue"
},
  "geometry": {"coordinates":[-113.978363,51.295269],"type":"Point"}
}