{
  "type": "Feature",
  "properties": {
    "addr:full":"263 Bryson Rd Rusagonis NB E3B 8E2",
    "addr:housenumber":"263",
    "addr:postcode":"e3b 8e2",
    "addr:street":"Bryson Rd",
    "iso:country":"CA",
    "sg:address":"263 Bryson Rd",
    "sg:city":"Rusagonis",
    "sg:classifiers":[
        {
            "category":"Building & Trades",
            "subcategory":"Construction",
            "type":"Services"
        }
    ],
    "sg:phone":"+1 506 455 5057",
    "sg:postcode":"E3B 8E2",
    "sg:province":"NB",
    "sg:tags":[
        "general",
        "contractor"
    ],
    "wof:name":"Donald Noble & Sons Ltd",
    "wof:placetype":"venue"
},
  "geometry": {"coordinates":[-66.6260147095,45.8012924194],"type":"Point"}
}