{
  "type": "Feature",
  "properties": {
    "iso:country":"CA",
    "sg:address":"11020 Fairmount Dr SE",
    "sg:city":"Calgary",
    "sg:classifiers":[
        {
            "category":"Education",
            "subcategory":"School",
            "type":"Public Place"
        }
    ],
    "sg:phone":"+1 403 271 9781",
    "sg:postcode":"T2J 0T1",
    "sg:province":"AB",
    "wof:name":"St William Elementary School",
    "wof:placetype":"venue"
},
  "geometry": {"coordinates":[-114.059708,50.953739],"type":"Point"}
}