{
  "type": "Feature",
  "properties": {
    "addr:full":"Vancouver BC V6H 3V1",
    "addr:postcode":"v6h 3v1",
    "iso:country":"CA",
    "sg:city":"Vancouver",
    "sg:classifiers":[
        {
            "category":"Real Estate",
            "subcategory":"Real Estate Agent",
            "type":"Services"
        }
    ],
    "sg:phone":"+1 604 682 2631",
    "sg:postcode":"V6H 3V1",
    "sg:province":"BC",
    "sg:tags":[
        "mall",
        "shopping",
        "center"
    ],
    "wof:name":"Greenwood Realty Group",
    "wof:placetype":"venue"
},
  "geometry": {"coordinates":[-123.13185900000001,49.263363],"type":"Point"}
}