{
  "type": "Feature",
  "properties": {
    "addr:full":"57 St-Francois Saint-Noel QC G0J 3A0",
    "addr:housenumber":"57",
    "addr:postcode":"g0j 3a0",
    "addr:street":"St-Francois Saint-Noel",
    "iso:country":"CA",
    "sg:address":"57 St-Francois",
    "sg:city":"Saint-Noel",
    "sg:classifiers":[
        {
            "category":"Retail",
            "subcategory":"Funeral Services",
            "type":"Services"
        }
    ],
    "sg:phone":"+1 418 776 2988",
    "sg:postcode":"G0J 3A0",
    "sg:province":"QC",
    "sg:tags":[
        "director"
    ],
    "wof:name":"George Fournier & Fils Inc",
    "wof:placetype":"venue"
},
  "geometry": {"coordinates":[-67.83628845210001,48.5844116211],"type":"Point"}
}