{
  "type": "Feature",
  "properties": {
    "addr:full":"785 16th Ave W Vancouver BC V5Z 1S8",
    "addr:housenumber":"785",
    "addr:postcode":"v5z 1s8",
    "addr:street":"16Th Ave W",
    "iso:country":"CA",
    "sg:address":"785 16th Ave W",
    "sg:city":"Vancouver",
    "sg:classifiers":[
        {
            "category":"Organizations",
            "subcategory":"Religious Organization",
            "type":"Services"
        }
    ],
    "sg:phone":"+1 604 873 2700",
    "sg:postcode":"V5Z 1S8",
    "sg:province":"BC",
    "sg:tags":[
        "synagogue"
    ],
    "wof:name":"Shaarey Tefilah Synagogue",
    "wof:placetype":"venue"
},
  "geometry": {"coordinates":[-123.121490478,49.2572250366],"type":"Point"}
}