{
  "type": "Feature",
  "properties": {
    "addr:full":"Scarborough ON M1V 5E4",
    "addr:postcode":"m1v 5e4",
    "iso:country":"CA",
    "sg:city":"Scarborough",
    "sg:classifiers":[
        {
            "category":"Retail",
            "subcategory":"Laundry & Dry Cleaning",
            "type":"Services"
        }
    ],
    "sg:phone":"+1 416 292 1179",
    "sg:postcode":"M1V 5E4",
    "sg:province":"ON",
    "sg:tags":[
        "cleaners",
        "fur",
        "business"
    ],
    "wof:name":"Atlantic Fur CO Ltd",
    "wof:placetype":"venue"
},
  "geometry": {"coordinates":[-79.256767,43.818161],"type":"Point"}
}