{
  "type": "Feature",
  "properties": {
    "addr:full":"Drayton Valley AB T7A 1S3",
    "addr:postcode":"t7a 1s3",
    "addr:street":"Drayton",
    "iso:country":"CA",
    "sg:city":"Drayton Valley",
    "sg:classifiers":[
        {
            "category":"Health Services",
            "subcategory":"Chiropractor",
            "type":"Services"
        }
    ],
    "sg:phone":"+1 780 542 5690",
    "sg:postcode":"T7A 1S3",
    "sg:province":"AB",
    "wof:name":"Greg Wademan Chiropractor Clnc",
    "wof:placetype":"venue"
},
  "geometry": {"coordinates":[-114.97809600799999,53.2224273682],"type":"Point"}
}