{
  "type": "Feature",
  "properties": {
    "addr:full":"77 Starrs Rd Yarmouth NS B5A 2T6",
    "addr:housenumber":"77",
    "addr:postcode":"b5a 2t6",
    "addr:street":"Starrs Rd",
    "iso:country":"CA",
    "sg:address":"77 Starrs Rd",
    "sg:city":"Yarmouth",
    "sg:classifiers":[
        {
            "category":"Restaurant",
            "type":"Food & Drink"
        }
    ],
    "sg:phone":"+1 902 742 9393",
    "sg:postcode":"B5A 2T6",
    "sg:province":"NS",
    "sg:tags":[
        "pizza"
    ],
    "wof:name":"Pizza Delight",
    "wof:placetype":"venue"
},
  "geometry": {"coordinates":[-66.09657300000001,43.840328],"type":"Point"}
}