{
  "type": "Feature",
  "properties": {
    "iso:country":"CA",
    "sg:city":"Scarborough",
    "sg:classifiers":[
        {
            "category":"Shopping",
            "type":"Retail Goods"
        }
    ],
    "sg:phone":"+1 416 291 2695",
    "sg:postcode":"M1S 2C1",
    "sg:province":"ON",
    "sg:tags":[
        "equipment",
        "wine",
        "supply"
    ],
    "wof:name":"Magic Wine",
    "wof:placetype":"venue"
},
  "geometry": {"coordinates":[-79.2761764526,43.7865715027],"type":"Point"}
}