{
  "type": "Feature",
  "properties": {
    "addr:full":"2412 Granville St Vancouver BC V6H 3G6",
    "addr:housenumber":"2412",
    "addr:postcode":"v6h 3g6",
    "addr:street":"Granville St",
    "iso:country":"CA",
    "sg:address":"2412 Granville St",
    "sg:city":"Vancouver",
    "sg:classifiers":[
        {
            "category":"Home & Garden",
            "subcategory":"Home Furnishings",
            "type":"Retail Goods"
        }
    ],
    "sg:phone":"+1 604 730 9110",
    "sg:postcode":"V6H 3G6",
    "sg:province":"BC",
    "sg:tags":[
        "lighting",
        "fixture"
    ],
    "wof:name":"Light Effects",
    "wof:placetype":"venue"
},
  "geometry": {"coordinates":[-123.13835907000001,49.2643356323],"type":"Point"}
}