{
  "type": "Feature",
  "properties": {
    "addr:full":"Calgary AB T2C 2B3",
    "addr:postcode":"t2c 2b3",
    "iso:country":"CA",
    "sg:city":"Calgary",
    "sg:classifiers":[
        {
            "category":"Shopping",
            "subcategory":"Bicycles & Sporting Goods",
            "type":"Retail Goods"
        }
    ],
    "sg:phone":"+1 403 236 5979",
    "sg:postcode":"T2C 2B3",
    "sg:province":"AB",
    "wof:name":"Marshall Sport Sales Agencies",
    "wof:placetype":"venue"
},
  "geometry": {"coordinates":[-113.975319,50.996746],"type":"Point"}
}