{
  "type": "Feature",
  "properties": {
    "addr:full":"2711 Rue Papineau Longueuil QC J4K 3M6",
    "addr:housenumber":"2711",
    "addr:postcode":"j4k 3m6",
    "addr:street":"Rue Papineau",
    "iso:country":"CA",
    "sg:address":"2711 Rue Papineau",
    "sg:city":"Longueuil",
    "sg:classifiers":[
        {
            "category":"Building & Trades",
            "subcategory":"Construction",
            "type":"Services"
        }
    ],
    "sg:phone":"+1 450 679 3131",
    "sg:postcode":"J4K 3M6",
    "sg:province":"QC",
    "sg:tags":[
        "excavating",
        "contractor"
    ],
    "wof:name":"Entreprises Cr Menard Inc",
    "wof:placetype":"venue"
},
  "geometry": {"coordinates":[-73.473511,45.508564],"type":"Point"}
}