{
  "type": "Feature",
  "properties": {
    "addr:full":"13650 50 St NW Edmonton AB T5A 4Y3",
    "addr:housenumber":"13650",
    "addr:postcode":"t5a 4y3",
    "addr:street":"50 St Nw",
    "iso:country":"CA",
    "sg:address":"13650 50 St NW",
    "sg:city":"Edmonton",
    "sg:classifiers":[
        {
            "category":"Shopping",
            "subcategory":"Department Store",
            "type":"Retail Goods"
        }
    ],
    "sg:phone":"+1 780 478 0066",
    "sg:postcode":"T5A 4Y3",
    "sg:province":"AB",
    "sg:tags":[
        "grocer"
    ],
    "wof:name":"Costco Wholesale",
    "wof:placetype":"venue"
},
  "geometry": {"coordinates":[-113.413902283,53.5961418152],"type":"Point"}
}