{
  "type": "Feature",
  "properties": {
    "addr:full":"2584 Boul Pere-Lelievre Quebec QC G1P 2X8",
    "addr:housenumber":"2584",
    "addr:postcode":"g1p 2x8",
    "addr:street":"Boul Pere-Lelievre",
    "iso:country":"CA",
    "sg:address":"2584 Boul Pere-Lelievre",
    "sg:city":"Quebec",
    "sg:classifiers":[
        {
            "category":"Food & Beverages",
            "subcategory":"Liquor & Beverages",
            "type":"Retail Goods"
        }
    ],
    "sg:phone":"+1 418 683 1454",
    "sg:postcode":"G1P 2X8",
    "sg:province":"QC",
    "sg:tags":[
        "equipment",
        "beer",
        "wine",
        "supply"
    ],
    "wof:name":"Boutique Du Vin",
    "wof:placetype":"venue"
},
  "geometry": {"coordinates":[-71.3052368164,46.812664032],"type":"Point"}
}