{
  "type": "Feature",
  "properties": {
    "iso:country":"CA",
    "sg:address":"10507 King George Hwy",
    "sg:city":"Surrey",
    "sg:classifiers":[
        {
            "category":"Professional",
            "subcategory":"Accounting & Tax Preparation",
            "type":"Services"
        }
    ],
    "sg:phone":"+1 604 585 1955",
    "sg:postcode":"V3T 2X1",
    "sg:province":"BC",
    "sg:tags":[
        "consultant"
    ],
    "wof:name":"David Ingram Cen-Ta Group",
    "wof:placetype":"venue"
},
  "geometry": {"coordinates":[-122.845466614,49.1916389465],"type":"Point"}
}