{
  "type": "Feature",
  "properties": {
    "iso:country":"CA",
    "sg:address":"3745 Rue Saint-Jacques",
    "sg:city":"Montreal",
    "sg:classifiers":[
        {
            "category":"Organizations",
            "subcategory":"Professional Association",
            "type":"Services"
        }
    ],
    "sg:phone":"+1 514 933 4118",
    "sg:postcode":"H4C 1H3",
    "sg:province":"QC",
    "wof:name":"Aper Sante Svc Sociaux",
    "wof:placetype":"venue"
},
  "geometry": {"coordinates":[-73.5837402344,45.4804115295],"type":"Point"}
}