{
  "type": "Feature",
  "properties": {
    "addr:full":"9 Laidlaw Blvd Markham ON L3P 1W5",
    "addr:housenumber":"9",
    "addr:postcode":"l3p 1w5",
    "addr:street":"Laidlaw Blvd",
    "iso:country":"CA",
    "sg:address":"9 Laidlaw Blvd",
    "sg:city":"Markham",
    "sg:classifiers":[
        {
            "category":"Wholesale",
            "subcategory":"Electrical",
            "type":"Manufacturing & Wholesale Goods"
        }
    ],
    "sg:phone":"+1 905 477 3113",
    "sg:postcode":"L3P 1W5",
    "sg:province":"ON",
    "sg:tags":[
        "equipment",
        "electric",
        "supply"
    ],
    "wof:name":"Supreme Light & Elect Supl Ltd",
    "wof:placetype":"venue"
},
  "geometry": {"coordinates":[-79.2780303955,43.8712654114],"type":"Point"}
}