{
  "type": "Feature",
  "properties": {
    "addr:full":"1000 Rue Saint-Georges Drummondville QC J2C 4H9",
    "addr:housenumber":"1000",
    "addr:postcode":"j2c 4h9",
    "addr:street":"Rue Saint-Georges",
    "iso:country":"CA",
    "sg:address":"1000 Rue Saint-Georges",
    "sg:city":"Drummondville",
    "sg:classifiers":[
        {
            "category":"Social Services",
            "subcategory":"Child Care",
            "type":"Services"
        }
    ],
    "sg:phone":"+1 819 478 7886",
    "sg:postcode":"J2C 4H9",
    "sg:province":"QC",
    "wof:name":"Cpe Plumeau Soleil",
    "wof:placetype":"venue"
},
  "geometry": {"coordinates":[-72.50709533689999,45.8740577698],"type":"Point"}
}