{
  "type": "Feature",
  "properties": {
    "iso:country":"CA",
    "sg:address":"84 Callander Dr",
    "sg:city":"Guelph",
    "sg:classifiers":[
        {
            "category":"Professional",
            "subcategory":"Management & Consulting",
            "type":"Services"
        }
    ],
    "sg:phone":"+1 519 822 0750",
    "sg:postcode":"N1E 4H8",
    "sg:province":"ON",
    "sg:tags":[
        "agricultural",
        "consultant"
    ],
    "wof:name":"Ag Plan Ltd",
    "wof:placetype":"venue"
},
  "geometry": {"coordinates":[-80.25073999999999,43.566364],"type":"Point"}
}