{
  "type": "Feature",
  "properties": {
    "addr:full":"9104 88 Ave NW Edmonton AB T6C 1M3",
    "addr:housenumber":"9104",
    "addr:postcode":"t6c 1m3",
    "addr:street":"88 Ave Nw",
    "iso:country":"CA",
    "sg:address":"9104 88 Ave NW",
    "sg:city":"Edmonton",
    "sg:classifiers":[
        {
            "category":"Food & Beverages",
            "subcategory":"Groceries & Convenience Stores",
            "type":"Retail Goods"
        }
    ],
    "sg:phone":"+1 780 466 6242",
    "sg:postcode":"T6C 1M3",
    "sg:province":"AB",
    "sg:tags":[
        "grocer"
    ],
    "wof:name":"Bonnie Doon Food Mart",
    "wof:placetype":"venue"
},
  "geometry": {"coordinates":[-113.46714799999999,53.523609],"type":"Point"}
}