{
  "type": "Feature",
  "properties": {
    "addr:full":"229 Margueretta St Toronto ON M6H 3S4",
    "addr:housenumber":"229",
    "addr:postcode":"m6h 3s4",
    "addr:street":"Margueretta St",
    "iso:country":"CA",
    "sg:address":"229 Margueretta St",
    "sg:city":"Toronto",
    "sg:classifiers":[
        {
            "category":"Building & Trades",
            "subcategory":"Cleaning & Sanitation",
            "type":"Services"
        }
    ],
    "sg:phone":"+1 416 536 2159",
    "sg:postcode":"M6H 3S4",
    "sg:province":"ON",
    "sg:tags":[
        "janitor"
    ],
    "wof:name":"J & S Cleaning Maintenance",
    "wof:placetype":"venue"
},
  "geometry": {"coordinates":[-79.43905599999999,43.655834],"type":"Point"}
}