{
  "type": "Feature",
  "properties": {
    "addr:full":"393 Rue Deslauriers Saint-Laurent QC H4N 1W2",
    "addr:housenumber":"393",
    "addr:postcode":"h4n 1w2",
    "addr:street":"Rue Deslauriers",
    "iso:country":"CA",
    "sg:address":"393 Rue Deslauriers",
    "sg:city":"Saint-Laurent",
    "sg:classifiers":[
        {
            "category":"Wholesale",
            "subcategory":"Groceries",
            "type":"Manufacturing & Wholesale Goods"
        }
    ],
    "sg:phone":"+1 514 331 2099",
    "sg:postcode":"H4N 1W2",
    "sg:province":"QC",
    "sg:tags":[
        "food",
        "product"
    ],
    "wof:name":"Nutrifresh Foods Ltd",
    "wof:placetype":"venue"
},
  "geometry": {"coordinates":[-73.663094,45.52396],"type":"Point"}
}