{
  "type": "Feature",
  "properties": {
    "addr:full":"2346 Ch Lucerne Mont-Royal QC H3R 2J8",
    "addr:housenumber":"2346",
    "addr:postcode":"h3r 2j8",
    "addr:street":"Ch Lucerne",
    "iso:country":"CA",
    "sg:address":"2346 Ch Lucerne",
    "sg:city":"Mont-Royal",
    "sg:classifiers":[
        {
            "category":"Shopping",
            "subcategory":"Shoes",
            "type":"Retail Goods"
        }
    ],
    "sg:phone":"+1 514 738 1919",
    "sg:postcode":"H3R 2J8",
    "sg:province":"QC",
    "wof:name":"Entrepot DE Chaussures Porto",
    "wof:placetype":"venue"
},
  "geometry": {"coordinates":[-73.66143,45.507256],"type":"Point"}
}