{
  "type": "Feature",
  "properties": {
    "iso:country":"CA",
    "sg:address":"495 6E Rang",
    "sg:city":"Courcelles",
    "sg:classifiers":[
        {
            "category":"Travel",
            "subcategory":"Hotels & Motels",
            "type":"Entertainment"
        }
    ],
    "sg:phone":"+1 418 483 5442",
    "sg:postcode":"G0M 1C0",
    "sg:province":"QC",
    "sg:tags":[
        "inn"
    ],
    "wof:name":"Auberge D'Andromede",
    "wof:placetype":"venue"
},
  "geometry": {"coordinates":[-70.9906082153,45.8565368652],"type":"Point"}
}