{
  "type": "Feature",
  "properties": {
    "addr:full":"1160 Rue Saint-Mathieu Montreal QC H3H 2P4",
    "addr:housenumber":"1160",
    "addr:postcode":"h3h 2p4",
    "addr:street":"Rue Saint-Mathieu",
    "iso:country":"CA",
    "sg:address":"1160 Rue Saint-Mathieu",
    "sg:city":"Montreal",
    "sg:classifiers":[
        {
            "category":"Freight",
            "type":"Transportation"
        }
    ],
    "sg:phone":"+1 514 933 3379",
    "sg:postcode":"H3H 2P4",
    "sg:province":"QC",
    "sg:tags":[
        "mover"
    ],
    "wof:name":"Entreprises Minard",
    "wof:placetype":"venue"
},
  "geometry": {"coordinates":[-73.5773239136,45.4925765991],"type":"Point"}
}