{
  "type": "Feature",
  "properties": {
    "addr:full":"148 Rue Frontenac Saint-Jean-Sur-Richelieu QC J3B 2Y9",
    "addr:housenumber":"148",
    "addr:postcode":"j3b 2y9",
    "addr:street":"Rue Frontenac",
    "iso:country":"CA",
    "sg:address":"148 Rue Frontenac",
    "sg:city":"Saint-Jean-Sur-Richelieu",
    "sg:classifiers":[
        {
            "category":"Personal",
            "subcategory":"Beauty Salon",
            "type":"Services"
        }
    ],
    "sg:phone":"+1 450 347 0188",
    "sg:postcode":"J3B 2Y9",
    "sg:province":"QC",
    "sg:tags":[
        "barber"
    ],
    "wof:name":"Salon Denis",
    "wof:placetype":"venue"
},
  "geometry": {"coordinates":[-73.26006317140001,45.3027915955],"type":"Point"}
}