{
  "type": "Feature",
  "properties": {
    "addr:full":"960 Boul Saint-Joseph Hull QC J8Z 1T3",
    "addr:housenumber":"960",
    "addr:postcode":"j8z 1t3",
    "addr:street":"Boul Saint-Joseph",
    "iso:country":"CA",
    "sg:address":"960 Boul Saint-Joseph",
    "sg:city":"Hull",
    "sg:classifiers":[
        {
            "category":"Autos & Motor Vehicles",
            "subcategory":"Automobile Sales",
            "type":"Retail Goods"
        }
    ],
    "sg:phone":"+1 819 777 5261",
    "sg:postcode":"J8Z 1T3",
    "sg:province":"QC",
    "sg:tags":[
        "car",
        "dealer"
    ],
    "wof:name":"J Baillot & Fils Ltee",
    "wof:placetype":"venue"
},
  "geometry": {"coordinates":[-75.73775500000001,45.468094],"type":"Point"}
}