{
  "type": "Feature",
  "properties": {
    "addr:full":"3091 Appleby Line Burlington ON L7R 3X4",
    "addr:housenumber":"3091",
    "addr:postcode":"l7r 3x4",
    "addr:street":"Appleby Line",
    "iso:country":"CA",
    "sg:address":"3091 Appleby Line",
    "sg:city":"Burlington",
    "sg:classifiers":[
        {
            "category":"Freight",
            "type":"Transportation"
        }
    ],
    "sg:phone":"+1 905 632 1661",
    "sg:postcode":"L7R 3X4",
    "sg:province":"ON",
    "sg:tags":[
        "trucking"
    ],
    "wof:name":"Chuck's Trucks Transportation",
    "wof:placetype":"venue"
},
  "geometry": {"coordinates":[-79.809746,43.408001],"type":"Point"}
}