{
  "type": "Feature",
  "properties": {
    "addr:full":"283 Rue Jacques-Cartier Salaberry-DE-Valleyfield QC J6T 4S9",
    "addr:housenumber":"283",
    "addr:postcode":"j6t 4s9",
    "addr:street":"Rue Jacques-Cartier",
    "iso:country":"CA",
    "sg:address":"283 Rue Jacques-Cartier",
    "sg:city":"Salaberry-DE-Valleyfield",
    "sg:classifiers":[
        {
            "category":"Food & Beverages",
            "subcategory":"Bakery",
            "type":"Retail Goods"
        }
    ],
    "sg:phone":"+1 450 371 5393",
    "sg:postcode":"J6T 4S9",
    "sg:province":"QC",
    "sg:tags":[
        "delicatessen"
    ],
    "wof:name":"Charcuterie Jacques-Cartier",
    "wof:placetype":"venue"
},
  "geometry": {"coordinates":[-74.1214599609,45.2454147339],"type":"Point"}
}