{
  "type": "Feature",
  "properties": {
    "addr:full":"Surrey BC V3R 1N5",
    "addr:postcode":"v3r 1n5",
    "iso:country":"CA",
    "sg:city":"Surrey",
    "sg:classifiers":[
        {
            "category":"Real Estate",
            "subcategory":"Real Estate Agent",
            "type":"Services"
        }
    ],
    "sg:phone":"+1 604 581 8400",
    "sg:postcode":"V3R 1N5",
    "sg:province":"BC",
    "wof:name":"Ali, Francis",
    "wof:placetype":"venue"
},
  "geometry": {"coordinates":[-122.796402,49.191624],"type":"Point"}
}