{
  "type": "Feature",
  "properties": {
    "addr:full":"Toronto ON M4P 1G8",
    "addr:postcode":"m4p 1g8",
    "iso:country":"CA",
    "sg:city":"Toronto",
    "sg:classifiers":[
        {
            "category":"Professional",
            "subcategory":"Employment Agencies",
            "type":"Services"
        }
    ],
    "sg:phone":"+1 416 483 7424",
    "sg:postcode":"M4P 1G8",
    "sg:province":"ON",
    "sg:tags":[
        "opportunity"
    ],
    "wof:name":"Datalist",
    "wof:placetype":"venue"
},
  "geometry": {"coordinates":[-79.396317,43.70705],"type":"Point"}
}