{
  "type": "Feature",
  "properties": {
    "addr:full":"1440 Corkery Rd Carp ON K0A 1L0",
    "addr:housenumber":"1440",
    "addr:postcode":"k0a 1l0",
    "addr:street":"Corkery Rd",
    "iso:country":"CA",
    "sg:address":"1440 Corkery Rd",
    "sg:city":"Carp",
    "sg:classifiers":[
        {
            "category":"Personal",
            "type":"Services"
        }
    ],
    "sg:phone":"+1 613 256 8282",
    "sg:postcode":"K0A 1L0",
    "sg:province":"ON",
    "sg:tags":[
        "locker"
    ],
    "wof:name":"Actt Installation",
    "wof:placetype":"venue"
},
  "geometry": {"coordinates":[-76.092056,45.277309],"type":"Point"}
}