{
  "type": "Feature",
  "properties": {
    "addr:full":"Calgary AB T2A 2R1",
    "addr:postcode":"t2a 2r1",
    "iso:country":"CA",
    "sg:city":"Calgary",
    "sg:classifiers":[
        {
            "category":"Retail",
            "subcategory":"Repair Shop",
            "type":"Services"
        }
    ],
    "sg:phone":"+1 403 273 1919",
    "sg:postcode":"T2A 2R1",
    "sg:province":"AB",
    "sg:tags":[
        "radio",
        "television",
        "video"
    ],
    "wof:name":"Ace Tv & Electronics",
    "wof:placetype":"venue"
},
  "geometry": {"coordinates":[-113.95682499999999,51.053364],"type":"Point"}
}