{
  "type": "Feature",
  "properties": {
    "addr:full":"Les Eboulements QC G0A 2M0",
    "addr:postcode":"g0a 2m0",
    "iso:country":"CA",
    "sg:city":"Les Eboulements",
    "sg:classifiers":[
        {
            "category":"Wholesale",
            "subcategory":"Poultry",
            "type":"Manufacturing & Wholesale Goods"
        }
    ],
    "sg:phone":"+1 418 635 2472",
    "sg:postcode":"G0A 2M0",
    "sg:province":"QC",
    "sg:tags":[
        "vegetable",
        "eggs",
        "fruit"
    ],
    "wof:name":"Gravel & Tremblay Inc",
    "wof:placetype":"venue"
},
  "geometry": {"coordinates":[-70.32191467289999,47.4784545898],"type":"Point"}
}