{
  "type": "Feature",
  "properties": {
    "addr:full":"1730 Ellerslie Rd SW Edmonton AB T6X 1A7",
    "addr:housenumber":"1730",
    "addr:postcode":"t6x 1a7",
    "addr:street":"Ellerslie Rd",
    "iso:country":"CA",
    "sg:address":"1730 Ellerslie Rd SW",
    "sg:city":"Edmonton",
    "sg:classifiers":[
        {
            "category":"Building & Trades",
            "subcategory":"Landscaping Services",
            "type":"Services"
        }
    ],
    "sg:phone":"+1 780 433 6671",
    "sg:postcode":"T6X 1A7",
    "sg:province":"AB",
    "sg:tags":[
        "center",
        "garden",
        "landscape",
        "contractor"
    ],
    "wof:name":"Water Works Ponds Ltd",
    "wof:placetype":"venue"
},
  "geometry": {"coordinates":[-113.371635,53.425011],"type":"Point"}
}