{
  "type": "Feature",
  "properties": {
    "addr:full":"151 Garafraxa St S Durham ON N0G 1R0",
    "addr:housenumber":"151",
    "addr:postcode":"n0g 1r0",
    "addr:street":"Garafraxa St S",
    "iso:country":"CA",
    "sg:address":"151 Garafraxa St S",
    "sg:city":"Durham",
    "sg:classifiers":[
        {
            "category":"Manufacturing",
            "subcategory":"Printing",
            "type":"Manufacturing & Wholesale Goods"
        }
    ],
    "sg:phone":"+1 519 369 5187",
    "sg:postcode":"N0G 1R0",
    "sg:province":"ON",
    "sg:tags":[
        "printer"
    ],
    "wof:name":"Printing For Everyone",
    "wof:placetype":"venue"
},
  "geometry": {"coordinates":[-80.81802399999999,44.175354],"type":"Point"}
}