{
  "type": "Feature",
  "properties": {
    "addr:full":"110 Main St Nokomis SK S0G 3R0",
    "addr:housenumber":"110",
    "addr:postcode":"s0g 3r0",
    "addr:street":"Main St",
    "iso:country":"CA",
    "sg:address":"110 Main St",
    "sg:city":"Nokomis",
    "sg:classifiers":[
        {
            "category":"Insurance",
            "subcategory":"Insurance Agent",
            "type":"Services"
        }
    ],
    "sg:phone":"+1 306 528 2911",
    "sg:postcode":"S0G 3R0",
    "sg:province":"SK",
    "wof:name":"CO-Operators Jerry Decker Ins",
    "wof:placetype":"venue"
},
  "geometry": {"coordinates":[-105.007972717,51.5091514587],"type":"Point"}
}