{
  "type": "Feature",
  "properties": {
    "addr:full":"Warman SK S0K 4S0",
    "addr:postcode":"s0k 4s0",
    "iso:country":"CA",
    "sg:city":"Warman",
    "sg:classifiers":[
        {
            "category":"Manufacturing",
            "subcategory":"Printing",
            "type":"Manufacturing & Wholesale Goods"
        }
    ],
    "sg:phone":"+1 306 934 6191",
    "sg:postcode":"S0K 4S0",
    "sg:province":"SK",
    "sg:tags":[
        "newspaper"
    ],
    "wof:name":"Country Press",
    "wof:placetype":"venue"
},
  "geometry": {"coordinates":[-106.585159,52.318722],"type":"Point"}
}