{
  "type": "Feature",
  "properties": {
    "iso:country":"CA",
    "sg:city":"Burnaby",
    "sg:classifiers":[
        {
            "category":"Health Services",
            "subcategory":"Chiropractor",
            "type":"Services"
        }
    ],
    "sg:phone":"+1 604 876 0220",
    "sg:postcode":"V5H 2E3",
    "sg:province":"BC",
    "wof:name":"Burnaby Metrotown Chiropractic",
    "wof:placetype":"venue"
},
  "geometry": {"coordinates":[-122.994026,49.226509],"type":"Point"}
}