{
  "type": "Feature",
  "properties": {
    "iso:country":"CA",
    "sg:address":"47 Crown Dr",
    "sg:city":"Halifax",
    "sg:classifiers":[
        {
            "category":"Professional",
            "subcategory":"Computer Services",
            "type":"Services"
        }
    ],
    "sg:phone":"+1 902 429 8292",
    "sg:postcode":"B3N 1L2",
    "sg:province":"NS",
    "sg:tags":[
        "website",
        "graphic",
        "design",
        "designer"
    ],
    "wof:name":"Design House",
    "wof:placetype":"venue"
},
  "geometry": {"coordinates":[-63.6281242371,44.6400985718],"type":"Point"}
}