{
  "type": "Feature",
  "properties": {
    "iso:country":"CA",
    "sg:address":"2 Herald Ave",
    "sg:city":"Corner Brook",
    "sg:classifiers":[
        {
            "category":"Shopping",
            "subcategory":"Pharmacy",
            "type":"Retail Goods"
        }
    ],
    "sg:phone":"+1 709 634 8875",
    "sg:postcode":"A2H 4B5",
    "sg:province":"NL",
    "wof:name":"Shoppers Drug Mart",
    "wof:placetype":"venue"
},
  "geometry": {"coordinates":[-57.9549446106,48.9514732361],"type":"Point"}
}