{
  "type": "Feature",
  "properties": {
    "addr:full":"2383 Jefferson Ave West Vancouver BC V7V 2B1",
    "addr:housenumber":"2383",
    "addr:postcode":"v7v 2b1",
    "addr:street":"Jefferson Ave",
    "iso:country":"CA",
    "sg:address":"2383 Jefferson Ave",
    "sg:city":"West Vancouver",
    "sg:classifiers":[
        {
            "category":"Manufacturing",
            "subcategory":"Printing",
            "type":"Manufacturing & Wholesale Goods"
        }
    ],
    "sg:phone":"+1 604 925 3612",
    "sg:postcode":"V7V 2B1",
    "sg:province":"BC",
    "sg:tags":[
        "publisher"
    ],
    "wof:name":"Nelson Canada Ltd",
    "wof:placetype":"venue"
},
  "geometry": {"coordinates":[-123.17811584499999,49.3357772827],"type":"Point"}
}