{
  "type": "Feature",
  "properties": {
    "iso:country":"CA",
    "sg:address":"2300 Rue Tupper",
    "sg:city":"Montreal",
    "sg:classifiers":[
        {
            "category":"Health Services",
            "subcategory":"Hospital",
            "type":"Services"
        }
    ],
    "sg:phone":"+1 514 412 4400",
    "sg:postcode":"H3H 1P3",
    "sg:province":"QC",
    "sg:tags":[
        "school"
    ],
    "wof:name":"Hopital DE Montreal Pour Enfnt",
    "wof:placetype":"venue"
},
  "geometry": {"coordinates":[-73.58271026609999,45.4894523621],"type":"Point"}
}