{
  "type": "Feature",
  "properties": {
    "addr:full":"5993 Rue Jean-Talon E Saint-Leonard QC H1S 1M5",
    "addr:housenumber":"5993",
    "addr:postcode":"h1s 1m5",
    "addr:street":"Rue Jean-Talon E",
    "iso:country":"CA",
    "sg:address":"5993 Rue Jean-Talon E",
    "sg:city":"Saint-Leonard",
    "sg:classifiers":[
        {
            "category":"Health Services",
            "subcategory":"Doctor",
            "type":"Services"
        }
    ],
    "sg:phone":"+1 514 255 2234",
    "sg:postcode":"H1S 1M5",
    "sg:province":"QC",
    "sg:tags":[
        "dentist"
    ],
    "wof:name":"Arasimowicz, Robert DDS",
    "wof:placetype":"venue"
},
  "geometry": {"coordinates":[-73.579239,45.586914],"type":"Point"}
}