{
  "type": "Feature",
  "properties": {
    "iso:country":"CA",
    "sg:address":"557 Kingston Rd",
    "sg:city":"Pickering",
    "sg:classifiers":[
        {
            "category":"Autos & Motor Vehicles",
            "subcategory":"Automobile Sales",
            "type":"Retail Goods"
        }
    ],
    "sg:phone":"+1 416 798 4800",
    "sg:postcode":"L1V 3N7",
    "sg:province":"ON",
    "sg:tags":[
        "car",
        "dealer"
    ],
    "wof:name":"Pickering Toyota Ltd",
    "wof:placetype":"venue"
},
  "geometry": {"coordinates":[-79.11892700200001,43.816368103],"type":"Point"}
}