{
  "type": "Feature",
  "properties": {
    "addr:full":"Prevost QC J0R 1T0",
    "addr:postcode":"j0r 1t0",
    "addr:street":"Prevost",
    "iso:country":"CA",
    "sg:city":"Prevost",
    "sg:classifiers":[
        {
            "category":"Health Services",
            "subcategory":"Health Practitioner",
            "type":"Services"
        }
    ],
    "sg:phone":"+1 450 224 5514",
    "sg:postcode":"J0R 1T0",
    "sg:province":"QC",
    "sg:tags":[
        "homeopath"
    ],
    "wof:name":"Studio Harmonie Sante Dl",
    "wof:placetype":"venue"
},
  "geometry": {"coordinates":[-74.054276,45.855751],"type":"Point"}
}