{
  "type": "Feature",
  "properties": {
    "addr:full":"1760 Rue Du Boulevard Laterriere QC G7N 1K1",
    "addr:housenumber":"1760",
    "addr:postcode":"g7n 1k1",
    "addr:street":"Rue Du Boulevard Laterriere",
    "iso:country":"CA",
    "sg:address":"1760 Rue Du Boulevard",
    "sg:city":"Laterriere",
    "sg:classifiers":[
        {
            "category":"Wholesale",
            "subcategory":"Construction Materials",
            "type":"Manufacturing & Wholesale Goods"
        }
    ],
    "sg:phone":"+1 418 678 2883",
    "sg:postcode":"G7N 1K1",
    "sg:province":"QC",
    "sg:tags":[
        "concrete",
        "general",
        "form",
        "contractor"
    ],
    "wof:name":"Coffrages Bouchard Pierre Inc",
    "wof:placetype":"venue"
},
  "geometry": {"coordinates":[-71.13623,48.318825],"type":"Point"}
}