{
  "type": "Feature",
  "properties": {
    "addr:full":"452 Rue DE LA Garonne E Alma QC G8C 1H9",
    "addr:housenumber":"452",
    "addr:postcode":"g8c 1h9",
    "addr:street":"Rue De La Garonne E",
    "iso:country":"CA",
    "sg:address":"452 Rue DE LA Garonne E",
    "sg:city":"Alma",
    "sg:classifiers":[
        {
            "category":"Professional",
            "subcategory":"Detective & Security Services",
            "type":"Services"
        }
    ],
    "sg:phone":"+1 418 668 6151",
    "sg:postcode":"G8C 1H9",
    "sg:province":"QC",
    "sg:tags":[
        "burglary",
        "protective",
        "robbery"
    ],
    "wof:name":"Alarme Detectra Enr",
    "wof:placetype":"venue"
},
  "geometry": {"coordinates":[-71.643776,48.529175],"type":"Point"}
}