{
  "type": "Feature",
  "properties": {
    "addr:full":"Quesnel BC V2J 3K2",
    "addr:postcode":"v2j 3k2",
    "iso:country":"CA",
    "sg:city":"Quesnel",
    "sg:classifiers":[
        {
            "category":"Food & Beverages",
            "subcategory":"Groceries & Convenience Stores",
            "type":"Retail Goods"
        }
    ],
    "sg:phone":"+1 250 992 8718",
    "sg:postcode":"V2J 3K2",
    "sg:province":"BC",
    "sg:tags":[
        "grocer"
    ],
    "wof:name":"Save-On-Foods",
    "wof:placetype":"venue"
},
  "geometry": {"coordinates":[-122.50664500000001,52.973442],"type":"Point"}
}