{
  "type": "Feature",
  "properties": {
    "iso:country":"CA",
    "sg:address":"2525 Boul Des Mille-Iles",
    "sg:city":"Laval",
    "sg:classifiers":[
        {
            "category":"Professional",
            "subcategory":"Business Services",
            "type":"Services"
        }
    ],
    "sg:phone":"+1 450 666 7144",
    "sg:postcode":"H7J 1E6",
    "sg:province":"QC",
    "sg:tags":[
        "appraiser"
    ],
    "wof:name":"Gilles Boucher & Assoc",
    "wof:placetype":"venue"
},
  "geometry": {"coordinates":[-73.714333,45.678608],"type":"Point"}
}