{
  "type": "Feature",
  "properties": {
    "addr:full":"Mississauga ON L5K 2K8",
    "addr:postcode":"l5k 2k8",
    "iso:country":"CA",
    "sg:city":"Mississauga",
    "sg:classifiers":[
        {
            "category":"Social Services",
            "subcategory":"Job Training",
            "type":"Services"
        }
    ],
    "sg:phone":"+1 905 823 8895",
    "sg:postcode":"L5K 2K8",
    "sg:province":"ON",
    "sg:tags":[
        "rehabilitation"
    ],
    "wof:name":"Independent Rehabilitation Svc",
    "wof:placetype":"venue"
},
  "geometry": {"coordinates":[-79.6530838013,43.5261993408],"type":"Point"}
}