{
  "type": "Feature",
  "properties": {
    "addr:full":"Olds AB T4H 1P3",
    "addr:postcode":"t4h 1p3",
    "iso:country":"CA",
    "sg:city":"Olds",
    "sg:classifiers":[
        {
            "category":"Farming",
            "subcategory":"Farm & Veterinary Services",
            "type":"Manufacturing & Wholesale Goods"
        }
    ],
    "sg:phone":"+1 403 335 4327",
    "sg:postcode":"T4H 1P3",
    "sg:province":"AB",
    "wof:name":"Champion Hay Processors",
    "wof:placetype":"venue"
},
  "geometry": {"coordinates":[-114.110610962,51.7916259766],"type":"Point"}
}