{
  "type": "Feature",
  "properties": {
    "addr:full":"Chateauguay QC J6K 3J9",
    "addr:postcode":"j6k 3j9",
    "iso:country":"CA",
    "sg:city":"Chateauguay",
    "sg:classifiers":[
        {
            "category":"Shopping",
            "subcategory":"Books",
            "type":"Retail Goods"
        }
    ],
    "sg:phone":"+1 450 699 4376",
    "sg:postcode":"J6K 3J9",
    "sg:province":"QC",
    "sg:tags":[
        "comic"
    ],
    "wof:name":"Village Des Heroes",
    "wof:placetype":"venue"
},
  "geometry": {"coordinates":[-73.732147,45.349068],"type":"Point"}
}