{
  "type": "Feature",
  "properties": {
    "addr:full":"35 Trehorne Dr Etobicoke ON M9P 1N8",
    "addr:housenumber":"35",
    "addr:postcode":"m9p 1n8",
    "addr:street":"Trehorne Dr",
    "iso:country":"CA",
    "sg:address":"35 Trehorne Dr",
    "sg:city":"Etobicoke",
    "sg:classifiers":[
        {
            "category":"Education",
            "subcategory":"School",
            "type":"Public Place"
        }
    ],
    "sg:phone":"+1 416 394 8701",
    "sg:postcode":"M9P 1N8",
    "sg:province":"ON",
    "wof:name":"Hilltop Community School",
    "wof:placetype":"venue"
},
  "geometry": {"coordinates":[-79.532883,43.689686],"type":"Point"}
}