{
  "type": "Feature",
  "properties": {
    "addr:full":"5013 50th St Olds AB T4H 1P5",
    "addr:housenumber":"5013",
    "addr:postcode":"t4h 1p5",
    "addr:street":"50Th St",
    "iso:country":"CA",
    "sg:address":"5013 50th St",
    "sg:city":"Olds",
    "sg:classifiers":[
        {
            "category":"Health Services",
            "subcategory":"Clinic",
            "type":"Services"
        }
    ],
    "sg:phone":"+1 403 556 6090",
    "sg:postcode":"T4H 1P5",
    "sg:province":"AB",
    "sg:tags":[
        "food",
        "herbalist",
        "diet"
    ],
    "wof:name":"Stang's Health Ctr Ltd",
    "wof:placetype":"venue"
},
  "geometry": {"coordinates":[-114.105537,51.791927],"type":"Point"}
}