{
  "type": "Feature",
  "properties": {
    "addr:full":"PO Box 135 Wareham-Centreville NL A0G 4P0",
    "addr:housenumber":"po",
    "addr:postcode":"a0g 4p0",
    "addr:street":"Box 135",
    "iso:country":"CA",
    "sg:address":"PO Box 135",
    "sg:city":"Wareham-Centreville",
    "sg:classifiers":[
        {
            "category":"Manufacturing",
            "subcategory":"Watercraft",
            "type":"Manufacturing & Wholesale Goods"
        }
    ],
    "sg:phone":"+1 709 678 6227",
    "sg:postcode":"A0G 4P0",
    "sg:province":"NL",
    "sg:tags":[
        "boat"
    ],
    "wof:name":"Fiberglass Works Ltd",
    "wof:placetype":"venue"
},
  "geometry": {"coordinates":[-53.8889694214,49.0124320984],"type":"Point"}
}