{
  "type": "Feature",
  "properties": {
    "addr:full":"5670 Av Victoria Montreal QC H3W 2P8",
    "addr:housenumber":"5670",
    "addr:postcode":"h3w 2p8",
    "addr:street":"Av Victoria",
    "iso:country":"CA",
    "sg:address":"5670 Av Victoria",
    "sg:city":"Montreal",
    "sg:classifiers":[
        {
            "category":"Food & Beverages",
            "subcategory":"Fruits & Vegetables",
            "type":"Retail Goods"
        }
    ],
    "sg:phone":"+1 514 342 6529",
    "sg:postcode":"H3W 2P8",
    "sg:province":"QC",
    "sg:tags":[
        "produce"
    ],
    "wof:name":"Nouveau Le Monde DE Fruits",
    "wof:placetype":"venue"
},
  "geometry": {"coordinates":[-73.632935,45.492123],"type":"Point"}
}