{
  "type": "Feature",
  "properties": {
    "addr:full":"104 1st Ave E St Walburg SK S0M 2T0",
    "addr:housenumber":"104",
    "addr:postcode":"s0m 2t0",
    "addr:street":"1St Ave E St",
    "iso:country":"CA",
    "sg:address":"104 1st Ave E",
    "sg:city":"St Walburg",
    "sg:classifiers":[
        {
            "category":"Retail",
            "subcategory":"Auto Repair",
            "type":"Services"
        }
    ],
    "sg:phone":"+1 306 248 3422",
    "sg:postcode":"S0M 2T0",
    "sg:province":"SK",
    "sg:tags":[
        "repairing",
        "automobile",
        "carburetor"
    ],
    "wof:name":"St Walburg Motors Ltd",
    "wof:placetype":"venue"
},
  "geometry": {"coordinates":[-109.200081,53.635201],"type":"Point"}
}