{
  "type": "Feature",
  "properties": {
    "addr:full":"Etobicoke ON M9W 5X3",
    "addr:postcode":"m9w 5x3",
    "iso:country":"CA",
    "sg:city":"Etobicoke",
    "sg:classifiers":[
        {
            "category":"Building & Trades",
            "subcategory":"Construction",
            "type":"Services"
        }
    ],
    "sg:phone":"+1 416 675 0565",
    "sg:postcode":"M9W 5X3",
    "sg:province":"ON",
    "sg:tags":[
        "railroad",
        "contractor"
    ],
    "wof:name":"Hulcher Services Canada",
    "wof:placetype":"venue"
},
  "geometry": {"coordinates":[-79.619423,43.741154],"type":"Point"}
}