{
  "type": "Feature",
  "properties": {
    "addr:full":"91 Victoria St W Exeter ON N0M 1S2",
    "addr:housenumber":"91",
    "addr:postcode":"n0m 1s2",
    "addr:street":"Victoria St W",
    "iso:country":"CA",
    "sg:address":"91 Victoria St W",
    "sg:city":"Exeter",
    "sg:classifiers":[
        {
            "category":"Building & Trades",
            "subcategory":"Plumbing",
            "type":"Services"
        }
    ],
    "sg:phone":"+1 519 235 1404",
    "sg:postcode":"N0M 1S2",
    "sg:province":"ON",
    "sg:tags":[
        "contractor"
    ],
    "wof:name":"A B Case Plumbing & Heating",
    "wof:placetype":"venue"
},
  "geometry": {"coordinates":[-81.4845123291,43.3503761292],"type":"Point"}
}