{
  "type": "Feature",
  "properties": {
    "addr:full":"Vancouver BC V6G 1C7",
    "addr:postcode":"v6g 1c7",
    "iso:country":"CA",
    "sg:city":"Vancouver",
    "sg:classifiers":[
        {
            "category":"Food & Beverages",
            "subcategory":"Fruits & Vegetables",
            "type":"Retail Goods"
        }
    ],
    "sg:phone":"+1 604 688 6696",
    "sg:postcode":"V6G 1C7",
    "sg:province":"BC",
    "sg:tags":[
        "produce"
    ],
    "wof:name":"Hyrise Produce Boutique",
    "wof:placetype":"venue"
},
  "geometry": {"coordinates":[-123.132812,49.289539],"type":"Point"}
}