{
  "type": "Feature",
  "properties": {
    "addr:full":"6031 103A St NW Edmonton AB T6H 2J7",
    "addr:housenumber":"6031",
    "addr:postcode":"t6h 2j7",
    "addr:street":"103A St Nw",
    "iso:country":"CA",
    "sg:address":"6031 103A St NW",
    "sg:city":"Edmonton",
    "sg:classifiers":[
        {
            "category":"Professional",
            "subcategory":"Research",
            "type":"Services"
        }
    ],
    "sg:phone":"+1 780 438 3028",
    "sg:postcode":"T6H 2J7",
    "sg:province":"AB",
    "sg:tags":[
        "environmental",
        "ecological"
    ],
    "wof:name":"Safety Instruments Ltd",
    "wof:placetype":"venue"
},
  "geometry": {"coordinates":[-113.494796753,53.4973526001],"type":"Point"}
}