{
  "type": "Feature",
  "properties": {
    "addr:full":"35 Rue Saint-Joseph Maskinonge QC J0K 1N0",
    "addr:housenumber":"35",
    "addr:postcode":"j0k 1n0",
    "addr:street":"Rue Saint-Joseph",
    "iso:country":"CA",
    "sg:address":"35 Rue Saint-Joseph",
    "sg:city":"Maskinonge",
    "sg:classifiers":[
        {
            "category":"Food & Beverages",
            "subcategory":"Groceries & Convenience Stores",
            "type":"Retail Goods"
        }
    ],
    "sg:phone":"+1 819 227 4565",
    "sg:postcode":"J0K 1N0",
    "sg:province":"QC",
    "wof:name":"Depanneur Paul-Andre Lajoie",
    "wof:placetype":"venue"
},
  "geometry": {"coordinates":[-73.01551055909999,46.226234436],"type":"Point"}
}