{
  "type": "Feature",
  "properties": {
    "addr:full":"47 Erie St S Leamington ON N8H 3A8",
    "addr:housenumber":"47",
    "addr:postcode":"n8h 3a8",
    "addr:street":"Erie St S",
    "iso:country":"CA",
    "sg:address":"47 Erie St S",
    "sg:city":"Leamington",
    "sg:classifiers":[
        {
            "category":"Restaurant",
            "type":"Food & Drink"
        }
    ],
    "sg:phone":"+1 519 326 4461",
    "sg:postcode":"N8H 3A8",
    "sg:province":"ON",
    "sg:tags":[
        "club",
        "night"
    ],
    "wof:name":"Village Inn",
    "wof:placetype":"venue"
},
  "geometry": {"coordinates":[-82.60005200000001,42.051933],"type":"Point"}
}