{
  "type": "Feature",
  "properties": {
    "addr:full":"4120 Boul Saint-Joseph Drummondville QC J2B 1T5",
    "addr:housenumber":"4120",
    "addr:postcode":"j2b 1t5",
    "addr:street":"Boul Saint-Joseph",
    "iso:country":"CA",
    "sg:address":"4120 Boul Saint-Joseph",
    "sg:city":"Drummondville",
    "sg:classifiers":[
        {
            "category":"Restaurant",
            "type":"Food & Drink"
        }
    ],
    "sg:phone":"+1 819 471 5050",
    "sg:postcode":"J2B 1T5",
    "sg:province":"QC",
    "sg:tags":[
        "cafe"
    ],
    "wof:name":"Rosie Cafe",
    "wof:placetype":"venue"
},
  "geometry": {"coordinates":[-72.45193500000001,45.84959],"type":"Point"}
}