{
  "type": "Feature",
  "properties": {
    "addr:full":"5 Moselle Dr Etobicoke ON M9V 5A6",
    "addr:housenumber":"5",
    "addr:postcode":"m9v 5a6",
    "addr:street":"Moselle Dr",
    "iso:country":"CA",
    "sg:address":"5 Moselle Dr",
    "sg:city":"Etobicoke",
    "sg:classifiers":[
        {
            "category":"Autos & Motor Vehicles",
            "subcategory":"Automobile Sales",
            "type":"Retail Goods"
        }
    ],
    "sg:phone":"+1 416 741 8880",
    "sg:postcode":"M9V 5A6",
    "sg:province":"ON",
    "sg:tags":[
        "car",
        "dealer"
    ],
    "wof:name":"Msd Motors",
    "wof:placetype":"venue"
},
  "geometry": {"coordinates":[-79.603424,43.754902],"type":"Point"}
}