{
  "type": "Feature",
  "properties": {
    "addr:full":"Vancouver BC V6B 1R8",
    "addr:postcode":"v6b 1r8",
    "iso:country":"CA",
    "sg:city":"Vancouver",
    "sg:classifiers":[
        {
            "category":"Real Estate",
            "subcategory":"Architect",
            "type":"Services"
        }
    ],
    "sg:phone":"+1 604 669 4166",
    "sg:postcode":"V6B 1R8",
    "sg:province":"BC",
    "wof:name":"Colborne Architectural Group",
    "wof:placetype":"venue"
},
  "geometry": {"coordinates":[-123.10779571499999,49.281047821],"type":"Point"}
}