{
  "type": "Feature",
  "properties": {
    "addr:full":"Scarborough ON M1J 2C7",
    "addr:postcode":"m1j 2c7",
    "iso:country":"CA",
    "sg:city":"Scarborough",
    "sg:classifiers":[
        {
            "category":"Health Services",
            "subcategory":"Clinic",
            "type":"Services"
        }
    ],
    "sg:phone":"+1 416 269 0151",
    "sg:postcode":"M1J 2C7",
    "sg:province":"ON",
    "sg:tags":[
        "acupuncture",
        "holistic",
        "practitioner"
    ],
    "wof:name":"Rad Ads Acupuncture",
    "wof:placetype":"venue"
},
  "geometry": {"coordinates":[-79.2471694946,43.7367782593],"type":"Point"}
}