{
  "type": "Feature",
  "properties": {
    "addr:full":"12626 Ilderton Rd Ilderton ON N0M 2A0",
    "addr:housenumber":"12626",
    "addr:postcode":"n0m 2a0",
    "addr:street":"Ilderton Rd",
    "iso:country":"CA",
    "sg:address":"12626 Ilderton Rd",
    "sg:city":"Ilderton",
    "sg:classifiers":[
        {
            "category":"Building & Trades",
            "subcategory":"Construction",
            "type":"Services"
        }
    ],
    "sg:phone":"+1 519 666 0262",
    "sg:postcode":"N0M 2A0",
    "sg:province":"ON",
    "sg:tags":[
        "contractor"
    ],
    "wof:name":"Bakker Construction Ltd",
    "wof:placetype":"venue"
},
  "geometry": {"coordinates":[-81.41703,43.069065],"type":"Point"}
}