{
  "type": "Feature",
  "properties": {
    "addr:full":"27 Rupert St Amherst NS B4H 3R5",
    "addr:housenumber":"27",
    "addr:postcode":"b4h 3r5",
    "addr:street":"Rupert St",
    "iso:country":"CA",
    "sg:address":"27 Rupert St",
    "sg:city":"Amherst",
    "sg:classifiers":[
        {
            "category":"Wholesale",
            "subcategory":"Hardware",
            "type":"Manufacturing & Wholesale Goods"
        }
    ],
    "sg:phone":"+1 902 661 0102",
    "sg:postcode":"B4H 3R5",
    "sg:province":"NS",
    "sg:tags":[
        "equipment",
        "heating",
        "system"
    ],
    "wof:name":"Harris Atlantic Sales Ltd",
    "wof:placetype":"venue"
},
  "geometry": {"coordinates":[-64.204697,45.834637],"type":"Point"}
}