{
  "type": "Feature",
  "properties": {
    "addr:full":"219 York St Glace Bay NS B1A 2L9",
    "addr:housenumber":"219",
    "addr:postcode":"b1a 2l9",
    "addr:street":"York St",
    "iso:country":"CA",
    "sg:address":"219 York St",
    "sg:city":"Glace Bay",
    "sg:classifiers":[
        {
            "category":"Health Services",
            "subcategory":"Doctor",
            "type":"Services"
        }
    ],
    "sg:phone":"+1 902 849 4565",
    "sg:postcode":"B1A 2L9",
    "sg:province":"NS",
    "sg:tags":[
        "dentist"
    ],
    "wof:name":"Turner, Gerald G DDS",
    "wof:placetype":"venue"
},
  "geometry": {"coordinates":[-59.956303,46.19479],"type":"Point"}
}