{
  "type": "Feature",
  "properties": {
    "addr:full":"5030 Northland Dr NW Calgary AB T2L 2J6",
    "addr:housenumber":"5030",
    "addr:postcode":"t2l 2j6",
    "addr:street":"Northland Dr Nw",
    "iso:country":"CA",
    "sg:address":"5030 Northland Dr NW",
    "sg:city":"Calgary",
    "sg:classifiers":[
        {
            "category":"Education",
            "subcategory":"School",
            "type":"Public Place"
        }
    ],
    "sg:phone":"+1 403 289 8456",
    "sg:postcode":"T2L 2J6",
    "sg:province":"AB",
    "wof:name":"St Jean Brebauf Jr High School",
    "wof:placetype":"venue"
},
  "geometry": {"coordinates":[-114.140984,51.097687],"type":"Point"}
}