{
  "type": "Feature",
  "properties": {
    "addr:full":"251 Rue Dorchester Quebec QC G1K 5Z6",
    "addr:housenumber":"251",
    "addr:postcode":"g1k 5z6",
    "addr:street":"Rue Dorchester",
    "iso:country":"CA",
    "sg:address":"251 Rue Dorchester",
    "sg:city":"Quebec",
    "sg:classifiers":[
        {
            "category":"Bars & Pubs",
            "type":"Food & Drink"
        }
    ],
    "sg:phone":"+1 418 522 6133",
    "sg:postcode":"G1K 5Z6",
    "sg:province":"QC",
    "wof:name":"Taverne Dorchester",
    "wof:placetype":"venue"
},
  "geometry": {"coordinates":[-71.22867599999999,46.815613],"type":"Point"}
}