{
  "type": "Feature",
  "properties": {
    "addr:full":"4317 Rue Wellington Verdun QC H4G 1W3",
    "addr:housenumber":"4317",
    "addr:postcode":"h4g 1w3",
    "addr:street":"Rue Wellington",
    "iso:country":"CA",
    "sg:address":"4317 Rue Wellington",
    "sg:city":"Verdun",
    "sg:classifiers":[
        {
            "category":"Bars & Pubs",
            "type":"Food & Drink"
        }
    ],
    "sg:phone":"+1 514 762 5546",
    "sg:postcode":"H4G 1W3",
    "sg:province":"QC",
    "sg:tags":[
        "lounge",
        "cocktail"
    ],
    "wof:name":"Bar Pino",
    "wof:placetype":"venue"
},
  "geometry": {"coordinates":[-73.567429,45.460773],"type":"Point"}
}