{
  "type": "Feature",
  "properties": {
    "addr:full":"605 Rennie St Hamilton ON L8H 3P8",
    "addr:housenumber":"605",
    "addr:postcode":"l8h 3p8",
    "addr:street":"Rennie St",
    "iso:country":"CA",
    "sg:address":"605 Rennie St",
    "sg:city":"Hamilton",
    "sg:classifiers":[
        {
            "category":"Building & Trades",
            "subcategory":"Construction",
            "type":"Services"
        }
    ],
    "sg:phone":"+1 905 549 9300",
    "sg:postcode":"L8H 3P8",
    "sg:province":"ON",
    "sg:tags":[
        "elevator"
    ],
    "wof:name":"Global Elevator Mfg CO",
    "wof:placetype":"venue"
},
  "geometry": {"coordinates":[-79.7787322998,43.2480926514],"type":"Point"}
}