{
  "type": "Feature",
  "properties": {
    "addr:full":"11089 Petty St Ailsa Craig ON N0M 1A0",
    "addr:housenumber":"11089",
    "addr:postcode":"n0m 1a0",
    "addr:street":"Petty St",
    "iso:country":"CA",
    "sg:address":"11089 Petty St",
    "sg:city":"Ailsa Craig",
    "sg:classifiers":[
        {
            "category":"Wholesale",
            "subcategory":"Machinery & Supplies",
            "type":"Manufacturing & Wholesale Goods"
        }
    ],
    "sg:phone":"+1 519 232 4879",
    "sg:postcode":"N0M 1A0",
    "sg:province":"ON",
    "sg:tags":[
        "farm",
        "equipment"
    ],
    "wof:name":"Andrew Hemming Farm Equipment",
    "wof:placetype":"venue"
},
  "geometry": {"coordinates":[-81.55239899999999,43.108532],"type":"Point"}
}