{
  "type": "Feature",
  "properties": {
    "iso:country":"CA",
    "sg:city":"Blind River",
    "sg:classifiers":[
        {
            "category":"Autos & Motor Vehicles",
            "subcategory":"Automobile Sales",
            "type":"Retail Goods"
        }
    ],
    "sg:phone":"+1 705 356 2974",
    "sg:postcode":"P0R 1B0",
    "sg:province":"ON",
    "sg:tags":[
        "car",
        "dealer"
    ],
    "wof:name":"Lawson Motors",
    "wof:placetype":"venue"
},
  "geometry": {"coordinates":[-82.96147918699999,46.1882514954],"type":"Point"}
}