{
  "type": "Feature",
  "properties": {
    "addr:full":"Winnipeg MB R3H 0N1",
    "addr:postcode":"r3h 0n1",
    "iso:country":"CA",
    "sg:city":"Winnipeg",
    "sg:classifiers":[
        {
            "category":"Retail",
            "subcategory":"Auto Repair",
            "type":"Services"
        }
    ],
    "sg:phone":"+1 204 632 4592",
    "sg:postcode":"R3H 0N1",
    "sg:province":"MB",
    "sg:tags":[
        "repairing",
        "automobile",
        "radiator"
    ],
    "wof:name":"Spi Heat Transfer Div",
    "wof:placetype":"venue"
},
  "geometry": {"coordinates":[-97.2012252808,49.914024353],"type":"Point"}
}