{
  "type": "Feature",
  "properties": {
    "iso:country":"CA",
    "sg:address":"327 Stewart St",
    "sg:city":"Renfrew",
    "sg:classifiers":[
        {
            "category":"Autos & Motor Vehicles",
            "subcategory":"Automobile Sales",
            "type":"Retail Goods"
        }
    ],
    "sg:phone":"+1 613 432 3748",
    "sg:postcode":"K7V 1Y2",
    "sg:province":"ON",
    "sg:tags":[
        "car",
        "dealer"
    ],
    "wof:name":"George Jackson Toyota Ltd",
    "wof:placetype":"venue"
},
  "geometry": {"coordinates":[-76.69585418699999,45.4779548645],"type":"Point"}
}