{
  "type": "Feature",
  "properties": {
    "addr:full":"60 Rue DE L'Eglise Edmundston NB E3V 1J5",
    "addr:housenumber":"60",
    "addr:postcode":"e3v 1j5",
    "addr:street":"Rue De L'Eglise",
    "iso:country":"CA",
    "sg:address":"60 Rue DE L'Eglise",
    "sg:city":"Edmundston",
    "sg:classifiers":[
        {
            "category":"Retail",
            "subcategory":"Laundry & Dry Cleaning",
            "type":"Services"
        }
    ],
    "sg:phone":"+1 506 735 6135",
    "sg:postcode":"E3V 1J5",
    "sg:province":"NB",
    "sg:tags":[
        "cleaners"
    ],
    "wof:name":"Nettoyeurs Dubourg",
    "wof:placetype":"venue"
},
  "geometry": {"coordinates":[-68.3267745972,47.3665542603],"type":"Point"}
}