{
  "type": "Feature",
  "properties": {
    "addr:full":"1601 Rue Coulombe Sainte-Julie QC J3E 1Y1",
    "addr:housenumber":"1601",
    "addr:postcode":"j3e 1y1",
    "addr:street":"Rue Coulombe",
    "iso:country":"CA",
    "sg:address":"1601 Rue Coulombe",
    "sg:city":"Sainte-Julie",
    "sg:classifiers":[
        {
            "category":"Building & Trades",
            "subcategory":"Construction",
            "type":"Services"
        }
    ],
    "sg:phone":"+1 450 649 1419",
    "sg:postcode":"J3E 1Y1",
    "sg:province":"QC",
    "sg:tags":[
        "excavating",
        "contractor"
    ],
    "wof:name":"Excavations Roger Gauthier Inc",
    "wof:placetype":"venue"
},
  "geometry": {"coordinates":[-73.323784,45.606789],"type":"Point"}
}