{
  "type": "Feature",
  "properties": {
    "addr:full":"1111 9 Ave SW Calgary AB T2P 1L3",
    "addr:housenumber":"1111",
    "addr:postcode":"t2p 1l3",
    "addr:street":"9 Ave Sw",
    "iso:country":"CA",
    "sg:address":"1111 9 Ave SW",
    "sg:city":"Calgary",
    "sg:classifiers":[
        {
            "category":"Autos & Motor Vehicles",
            "subcategory":"Automobile Sales",
            "type":"Retail Goods"
        }
    ],
    "sg:phone":"+1 403 263 4530",
    "sg:postcode":"T2P 1L3",
    "sg:province":"AB",
    "sg:tags":[
        "car",
        "dealer"
    ],
    "wof:name":"Metro-Ford Sales Ltd",
    "wof:placetype":"venue"
},
  "geometry": {"coordinates":[-114.08669999999999,51.045151],"type":"Point"}
}