{
  "type": "Feature",
  "properties": {
    "addr:full":"81 Oxford St W London ON N6H 1R8",
    "addr:housenumber":"81",
    "addr:postcode":"n6h 1r8",
    "addr:street":"Oxford St W",
    "iso:country":"CA",
    "sg:address":"81 Oxford St W",
    "sg:city":"London",
    "sg:classifiers":[
        {
            "category":"Health Services",
            "subcategory":"Doctor",
            "type":"Services"
        }
    ],
    "sg:phone":"+1 519 661 0042",
    "sg:postcode":"N6H 1R8",
    "sg:province":"ON",
    "sg:tags":[
        "dentist"
    ],
    "wof:name":"Complete Family Dental Care",
    "wof:placetype":"venue"
},
  "geometry": {"coordinates":[-81.2662277222,42.9917373657],"type":"Point"}
}