{
  "type": "Feature",
  "properties": {
    "addr:full":"8116 Forbes St Mission BC V2V 6L6",
    "addr:housenumber":"8116",
    "addr:postcode":"v2v 6l6",
    "addr:street":"Forbes St",
    "iso:country":"CA",
    "sg:address":"8116 Forbes St",
    "sg:city":"Mission",
    "sg:classifiers":[
        {
            "category":"Personal",
            "subcategory":"Beauty Salon",
            "type":"Services"
        }
    ],
    "sg:phone":"+1 604 217 0229",
    "sg:postcode":"V2V 6L6",
    "sg:province":"BC",
    "wof:name":"Preferred Cuts",
    "wof:placetype":"venue"
},
  "geometry": {"coordinates":[-122.294288635,49.1497116089],"type":"Point"}
}