{
  "type": "Feature",
  "properties": {
    "addr:full":"Saskatoon SK S7H 2B7",
    "addr:postcode":"s7h 2b7",
    "iso:country":"CA",
    "sg:city":"Saskatoon",
    "sg:classifiers":[
        {
            "category":"Health Services",
            "subcategory":"Clinic",
            "type":"Services"
        }
    ],
    "sg:phone":"+1 306 343 0041",
    "sg:postcode":"S7H 2B7",
    "sg:province":"SK",
    "sg:tags":[
        "aid",
        "first"
    ],
    "wof:name":"St John Ambulance",
    "wof:placetype":"venue"
},
  "geometry": {"coordinates":[-106.656982,52.108128],"type":"Point"}
}