{
  "type": "Feature",
  "properties": {
    "addr:full":"1650 Argyle St Halifax NS B3J 2B4",
    "addr:housenumber":"1650",
    "addr:postcode":"ns b3j 2b4",
    "addr:street":"Argyle St",
    "iso:country":"CA",
    "sg:address":"1650 Argyle St",
    "sg:city":"Halifax",
    "sg:classifiers":[
        {
            "category":"Shopping",
            "subcategory":"News",
            "type":"Retail Goods"
        }
    ],
    "sg:phone":"+1 902 426 2811",
    "sg:postcode":"B3J 2B4",
    "sg:province":"NS",
    "sg:tags":[
        "newspaper",
        "dealer"
    ],
    "wof:name":"Chronicle-Herald",
    "wof:placetype":"venue"
},
  "geometry": {"coordinates":[-63.574471,44.646152],"type":"Point"}
}