{
  "type": "Feature",
  "properties": {
    "addr:full":"13 Chambers St Smiths Falls ON K7A 2Y2",
    "addr:housenumber":"13",
    "addr:postcode":"k7a 2y2",
    "addr:street":"Chambers St",
    "iso:country":"CA",
    "sg:address":"13 Chambers St",
    "sg:city":"Smiths Falls",
    "sg:classifiers":[
        {
            "category":"Personal",
            "subcategory":"Beauty Salon",
            "type":"Services"
        }
    ],
    "sg:phone":"+1 613 284 2664",
    "sg:postcode":"K7A 2Y2",
    "sg:province":"ON",
    "sg:tags":[
        "shop",
        "consignment"
    ],
    "wof:name":"Dawn's Closet",
    "wof:placetype":"venue"
},
  "geometry": {"coordinates":[-76.0203781128,44.8986434937],"type":"Point"}
}