{
  "type": "Feature",
  "properties": {
    "addr:full":"Macamic QC J0Z 2S0",
    "addr:postcode":"j0z 2s0",
    "iso:country":"CA",
    "sg:city":"Macamic",
    "sg:classifiers":[
        {
            "category":"Restaurant",
            "type":"Food & Drink"
        }
    ],
    "sg:phone":"+1 819 782 5567",
    "sg:postcode":"J0Z 2S0",
    "sg:province":"QC",
    "wof:name":"P'Tits Mets Gourmets",
    "wof:placetype":"venue"
},
  "geometry": {"coordinates":[-79.001915,48.757271],"type":"Point"}
}