{
  "type": "Feature",
  "properties": {
    "addr:full":"1218 133 Rte Sabrevois QC J0J 2G0",
    "addr:housenumber":"1218",
    "addr:postcode":"j0j 2g0",
    "addr:street":"133 Rte Sabrevois",
    "iso:country":"CA",
    "sg:address":"1218 133 Rte",
    "sg:city":"Sabrevois",
    "sg:classifiers":[
        {
            "category":"Government",
            "subcategory":"Office",
            "type":"Public Place"
        }
    ],
    "sg:phone":"+1 450 347 0066",
    "sg:postcode":"J0J 2G0",
    "sg:province":"QC",
    "sg:tags":[
        "village"
    ],
    "wof:name":"Salle Municipale DE Sabrevois",
    "wof:placetype":"venue"
},
  "geometry": {"coordinates":[-73.2304992676,45.2063903809],"type":"Point"}
}