{
  "type": "Feature",
  "properties": {
    "addr:full":"10601 Av Georges-Pichet Montreal-Nord QC H1G 5K2",
    "addr:housenumber":"10601",
    "addr:postcode":"h1g 5k2",
    "addr:street":"Av Georges-Pichet",
    "iso:country":"CA",
    "sg:address":"10601 Av Georges-Pichet",
    "sg:city":"Montreal-Nord",
    "sg:classifiers":[
        {
            "category":"Wholesale",
            "subcategory":"Durable Goods & Equipment",
            "type":"Manufacturing & Wholesale Goods"
        }
    ],
    "sg:phone":"+1 514 382 3877",
    "sg:postcode":"H1G 5K2",
    "sg:province":"QC",
    "sg:tags":[
        "representative",
        "real estate"
    ],
    "wof:name":"Importations Casa Vivendi",
    "wof:placetype":"venue"
},
  "geometry": {"coordinates":[-73.6220550537,45.5950317383],"type":"Point"}
}