{
  "type": "Feature",
  "properties": {
    "addr:full":"227 Humber Ave Labrador City NL A2V 2Y3",
    "addr:housenumber":"227",
    "addr:postcode":"a2v 2y3",
    "addr:street":"Humber Ave",
    "iso:country":"CA",
    "sg:address":"227 Humber Ave",
    "sg:city":"Labrador City",
    "sg:classifiers":[
        {
            "category":"Personal",
            "subcategory":"Beauty Salon",
            "type":"Services"
        }
    ],
    "sg:phone":"+1 709 944 5058",
    "sg:postcode":"A2V 2Y3",
    "sg:province":"NL",
    "wof:name":"Hair Masters",
    "wof:placetype":"venue"
},
  "geometry": {"coordinates":[-66.90934753419999,52.943523407],"type":"Point"}
}