{
  "type": "Feature",
  "properties": {
    "iso:country":"CA",
    "sg:address":"11146 Clairmont Subdiv",
    "sg:city":"Fort St John",
    "sg:classifiers":[
        {
            "category":"Freight",
            "type":"Transportation"
        }
    ],
    "sg:phone":"+1 250 785 8432",
    "sg:postcode":"V1J 4M7",
    "sg:province":"BC",
    "sg:tags":[
        "field",
        "oil",
        "hauling"
    ],
    "wof:name":"Peace Hotshots & Picker Svc",
    "wof:placetype":"venue"
},
  "geometry": {"coordinates":[-120.847457886,56.2524642944],"type":"Point"}
}