{
  "type": "Feature",
  "properties": {
    "addr:full":"Delta BC V4K 2V6",
    "addr:postcode":"v4k 2v6",
    "iso:country":"CA",
    "sg:city":"Delta",
    "sg:classifiers":[
        {
            "category":"Education",
            "subcategory":"Special Training",
            "type":"Public Place"
        }
    ],
    "sg:phone":"+1 604 946 1280",
    "sg:postcode":"V4K 2V6",
    "sg:province":"BC",
    "sg:tags":[
        "instruction",
        "music"
    ],
    "wof:name":"Delta Community Music School",
    "wof:placetype":"venue"
},
  "geometry": {"coordinates":[-123.084068,49.090214],"type":"Point"}
}