{
  "type": "Feature",
  "properties": {
    "addr:full":"4 Shaughnessy Cres Kanata ON K2K 2P1",
    "addr:housenumber":"4",
    "addr:postcode":"k2k 2p1",
    "addr:street":"Shaughnessy Cres",
    "iso:country":"CA",
    "sg:address":"4 Shaughnessy Cres",
    "sg:city":"Kanata",
    "sg:classifiers":[
        {
            "category":"Wholesale",
            "subcategory":"Machinery & Supplies",
            "type":"Manufacturing & Wholesale Goods"
        }
    ],
    "sg:phone":"+1 613 591 6506",
    "sg:postcode":"K2K 2P1",
    "sg:province":"ON",
    "sg:tags":[
        "sprinkler"
    ],
    "wof:name":"Royal Fire Protection Inc",
    "wof:placetype":"venue"
},
  "geometry": {"coordinates":[-75.914497,45.322323],"type":"Point"}
}