{
  "type": "Feature",
  "properties": {
    "addr:full":"225 Fourth Ave N Yorkton SK S3N 1A9",
    "addr:housenumber":"225",
    "addr:postcode":"s3n 1a9",
    "addr:street":"Fourth Ave N",
    "iso:country":"CA",
    "sg:address":"225 Fourth Ave N",
    "sg:city":"Yorkton",
    "sg:classifiers":[
        {
            "category":"Building & Trades",
            "subcategory":"Plumbing",
            "type":"Services"
        }
    ],
    "sg:phone":"+1 306 783 4020",
    "sg:postcode":"S3N 1A9",
    "sg:province":"SK",
    "sg:tags":[
        "contractor"
    ],
    "wof:name":"R Miller's Plumbing & Heating",
    "wof:placetype":"venue"
},
  "geometry": {"coordinates":[-102.45844268800001,51.2182273865],"type":"Point"}
}