{
  "type": "Feature",
  "properties": {
    "addr:full":"537 Av Du Quebec Sept-Iles QC G4R 1K1",
    "addr:postcode":"g4r 1k1",
    "addr:street":"537 Av Du Quebec Sept-Iles",
    "iso:country":"CA",
    "sg:address":"537 Av Du Quebec",
    "sg:city":"Sept-Iles",
    "sg:classifiers":[
        {
            "category":"Freight",
            "type":"Transportation"
        }
    ],
    "sg:phone":"+1 418 962 3456",
    "sg:postcode":"G4R 1K1",
    "sg:province":"QC",
    "sg:tags":[
        "trucking"
    ],
    "wof:name":"Messageries Du Nord",
    "wof:placetype":"venue"
},
  "geometry": {"coordinates":[-66.371002,50.216476],"type":"Point"}
}