{
  "type": "Feature",
  "properties": {
    "addr:full":"1629 Yew St Vancouver BC V6K 3E6",
    "addr:housenumber":"1629",
    "addr:postcode":"v6k 3e6",
    "addr:street":"Yew St",
    "iso:country":"CA",
    "sg:address":"1629 Yew St",
    "sg:city":"Vancouver",
    "sg:classifiers":[
        {
            "category":"Restaurant",
            "type":"Food & Drink"
        }
    ],
    "sg:phone":"+1 604 224 2241",
    "sg:postcode":"V6K 3E6",
    "sg:province":"BC",
    "wof:name":"Wokman's Restaurant",
    "wof:placetype":"venue"
},
  "geometry": {"coordinates":[-123.155197,49.27142],"type":"Point"}
}