{
  "type": "Feature",
  "properties": {
    "addr:full":"Fort Mcpherson NT X0E 0J0",
    "addr:postcode":"x0e 0j0",
    "iso:country":"CA",
    "sg:city":"Fort Mcpherson",
    "sg:classifiers":[
        {
            "category":"Manufacturing",
            "subcategory":"Apparel",
            "type":"Manufacturing & Wholesale Goods"
        }
    ],
    "sg:phone":"+1 867 952 2179",
    "sg:postcode":"X0E 0J0",
    "sg:province":"NT",
    "sg:tags":[
        "canvas",
        "product",
        "related"
    ],
    "wof:name":"Fort Mc Pherson Tent & Canvas",
    "wof:placetype":"venue"
},
  "geometry": {"coordinates":[-134.76582300000001,67.45753499999999],"type":"Point"}
}