{
  "type": "Feature",
  "properties": {
    "addr:full":"975 James St Woodstock ON N4S 8P6",
    "addr:housenumber":"975",
    "addr:postcode":"n4s 8p6",
    "addr:street":"James St",
    "iso:country":"CA",
    "sg:address":"975 James St",
    "sg:city":"Woodstock",
    "sg:classifiers":[
        {
            "category":"Social Services",
            "type":"Services"
        }
    ],
    "sg:phone":"+1 519 539 4811",
    "sg:postcode":"N4S 8P6",
    "sg:province":"ON",
    "sg:tags":[
        "organization",
        "welfare"
    ],
    "wof:name":"Women's Emergency Ctr",
    "wof:placetype":"venue"
},
  "geometry": {"coordinates":[-80.731087,43.132164],"type":"Point"}
}