{
  "type": "Feature",
  "properties": {
    "addr:full":"Vernon BC V1T 9T3",
    "addr:postcode":"v1t 9t3",
    "iso:country":"CA",
    "sg:city":"Vernon",
    "sg:classifiers":[
        {
            "category":"Shopping",
            "subcategory":"Clothing, Apparel, & Fashions",
            "type":"Retail Goods"
        }
    ],
    "sg:phone":"+1 250 542 2380",
    "sg:postcode":"V1T 9T3",
    "sg:province":"BC",
    "sg:tags":[
        "work"
    ],
    "wof:name":"Mark's Work Wearhouse Ltd",
    "wof:placetype":"venue"
},
  "geometry": {"coordinates":[-119.262817,50.287697],"type":"Point"}
}