{
  "type": "Feature",
  "properties": {
    "iso:country":"CA",
    "sg:address":"RR 4",
    "sg:city":"Mount Brydges",
    "sg:classifiers":[
        {
            "category":"Building & Trades",
            "subcategory":"Construction",
            "type":"Services"
        }
    ],
    "sg:phone":"+1 519 264 2760",
    "sg:postcode":"N0L 1W0",
    "sg:province":"ON",
    "sg:tags":[
        "contractor"
    ],
    "wof:name":"Bluestone Design Build Inc",
    "wof:placetype":"venue"
},
  "geometry": {"coordinates":[-81.4964065552,42.9099998474],"type":"Point"}
}