{
  "type": "Feature",
  "properties": {
    "addr:full":"Oliver BC V0H 1T0",
    "addr:postcode":"bc v0h 1t0",
    "iso:country":"CA",
    "sg:city":"Oliver",
    "sg:classifiers":[
        {
            "category":"Travel",
            "subcategory":"Hotels & Motels",
            "type":"Entertainment"
        }
    ],
    "sg:phone":"+1 250 498 4665",
    "sg:postcode":"V0H 1T0",
    "sg:province":"BC",
    "wof:name":"Honky Tonk Hotel",
    "wof:placetype":"venue"
},
  "geometry": {"coordinates":[-119.670464,49.848694],"type":"Point"}
}