{
  "type": "Feature",
  "properties": {
    "iso:country":"CA",
    "sg:address":"3243 Dovetail Mews",
    "sg:city":"Mississauga",
    "sg:classifiers":[
        {
            "category":"Banks & Credit Unions",
            "subcategory":"Investment Brokerage",
            "type":"Services"
        }
    ],
    "sg:phone":"+1 905 820 3111",
    "sg:postcode":"L5L 5G8",
    "sg:province":"ON",
    "sg:tags":[
        "consultant",
        "planning",
        "financial"
    ],
    "wof:name":"Norlyn Financial Group Inc",
    "wof:placetype":"venue"
},
  "geometry": {"coordinates":[-79.69254302980001,43.5217514038],"type":"Point"}
}