{
  "type": "Feature",
  "properties": {
    "addr:full":"3092 Danforth Ave Scarborough ON M1L 1B1",
    "addr:housenumber":"3092",
    "addr:postcode":"m1l 1b1",
    "addr:street":"Danforth Ave",
    "iso:country":"CA",
    "sg:address":"3092 Danforth Ave",
    "sg:city":"Scarborough",
    "sg:classifiers":[
        {
            "category":"Professional",
            "subcategory":"Accounting & Tax Preparation",
            "type":"Services"
        }
    ],
    "sg:phone":"+1 416 690 0400",
    "sg:postcode":"M1L 1B1",
    "sg:province":"ON",
    "sg:tags":[
        "return",
        "filing"
    ],
    "wof:name":"Banner Tax & Accounting Svc",
    "wof:placetype":"venue"
},
  "geometry": {"coordinates":[-79.28769699999999,43.691502],"type":"Point"}
}