{
  "type": "Feature",
  "properties": {
    "addr:full":"385 Alliford Bay Sandspit BC V0T 1T0",
    "addr:housenumber":"385",
    "addr:postcode":"v0t 1t0",
    "addr:street":"Alliford Bay",
    "iso:country":"CA",
    "sg:address":"385 Alliford Bay",
    "sg:city":"Sandspit",
    "sg:classifiers":[
        {
            "category":"Travel",
            "subcategory":"Hotels & Motels",
            "type":"Entertainment"
        }
    ],
    "sg:phone":"+1 250 637 5300",
    "sg:postcode":"V0T 1T0",
    "sg:province":"BC",
    "sg:tags":[
        "breakfast",
        "accommodation",
        "bed"
    ],
    "wof:name":"Moresby Island Guest House",
    "wof:placetype":"venue"
},
  "geometry": {"coordinates":[-131.838348,53.238579],"type":"Point"}
}