{
  "type": "Feature",
  "properties": {
    "addr:full":"Canora SK S0A 0L0",
    "addr:postcode":"s0a 0l0",
    "addr:street":"Canora",
    "iso:country":"CA",
    "sg:city":"Canora",
    "sg:classifiers":[
        {
            "category":"Wholesale",
            "subcategory":"Motor Vehicles",
            "type":"Manufacturing & Wholesale Goods"
        }
    ],
    "sg:phone":"+1 306 563 5625",
    "sg:postcode":"S0A 0L0",
    "sg:province":"SK",
    "sg:tags":[
        "hearse",
        "ambulance"
    ],
    "wof:name":"Canora Ambulance Care Ltd",
    "wof:placetype":"venue"
},
  "geometry": {"coordinates":[-102.432434082,51.6354560852],"type":"Point"}
}