{
  "type": "Feature",
  "properties": {
    "addr:full":"195 Wilkinson Rd Brampton ON L6T 4X1",
    "addr:housenumber":"195",
    "addr:postcode":"l6t 4x1",
    "addr:street":"Wilkinson Rd",
    "iso:country":"CA",
    "sg:address":"195 Wilkinson Rd",
    "sg:city":"Brampton",
    "sg:classifiers":[
        {
            "category":"Wholesale",
            "subcategory":"Electrical",
            "type":"Manufacturing & Wholesale Goods"
        }
    ],
    "sg:phone":"+1 905 453 8297",
    "sg:postcode":"L6T 4X1",
    "sg:province":"ON",
    "sg:tags":[
        "control"
    ],
    "wof:name":"Jbs Svc Inc",
    "wof:placetype":"venue"
},
  "geometry": {"coordinates":[-79.69803619379999,43.6900749207],"type":"Point"}
}