{
  "type": "Feature",
  "properties": {
    "addr:full":"4570 Rue Jean-Talon E #101 Saint-Leonard QC H1S 1K2",
    "addr:housenumber":"4570",
    "addr:postcode":"h1s 1k2",
    "addr:street":"Rue Jean-Talon E # 101",
    "iso:country":"CA",
    "sg:address":"4570 Rue Jean-Talon E #101",
    "sg:city":"Saint-Leonard",
    "sg:classifiers":[
        {
            "category":"Professional",
            "subcategory":"Lawyer & Legal Services",
            "type":"Services"
        }
    ],
    "sg:phone":"+1 514 723 1130",
    "sg:postcode":"H1S 1K2",
    "sg:province":"QC",
    "sg:tags":[
        "attorney"
    ],
    "wof:name":"Francischiello & Assoc",
    "wof:placetype":"venue"
},
  "geometry": {"coordinates":[-73.58689117430001,45.5715522766],"type":"Point"}
}