{
  "type": "Feature",
  "properties": {
    "iso:country":"CA",
    "sg:city":"New Westminster",
    "sg:classifiers":[
        {
            "category":"Wholesale",
            "subcategory":"Farm Supplies",
            "type":"Manufacturing & Wholesale Goods"
        }
    ],
    "sg:phone":"+1 604 520 9900",
    "sg:postcode":"V3L 5T8",
    "sg:province":"BC",
    "sg:tags":[
        "control",
        "equipment",
        "pest"
    ],
    "wof:name":"Integrated Pest Supplies",
    "wof:placetype":"venue"
},
  "geometry": {"coordinates":[-122.88507842999999,49.2240753174],"type":"Point"}
}