{
  "type": "Feature",
  "properties": {
    "addr:full":"Etobicoke ON M9W 6N8",
    "addr:postcode":"m9w 6n8",
    "iso:country":"CA",
    "sg:city":"Etobicoke",
    "sg:classifiers":[
        {
            "category":"Building & Trades",
            "subcategory":"Landscaping Services",
            "type":"Services"
        }
    ],
    "sg:phone":"+1 416 674 1331",
    "sg:postcode":"M9W 6N8",
    "sg:province":"ON",
    "sg:tags":[
        "excavating",
        "contractor",
        "sodding",
        "sod"
    ],
    "wof:name":"Silma Excavating Ltd",
    "wof:placetype":"venue"
},
  "geometry": {"coordinates":[-79.617661,43.753193],"type":"Point"}
}