{
  "type": "Feature",
  "properties": {
    "addr:full":"Red Deer AB T4P 1N5",
    "addr:postcode":"t4p 1n5",
    "iso:country":"CA",
    "sg:city":"Red Deer",
    "sg:classifiers":[
        {
            "category":"Autos & Motor Vehicles",
            "subcategory":"Auto Supplies",
            "type":"Retail Goods"
        }
    ],
    "sg:phone":"+1 403 340 8777",
    "sg:postcode":"T4P 1N5",
    "sg:province":"AB",
    "sg:tags":[
        "battery"
    ],
    "wof:name":"Battery Doctors",
    "wof:placetype":"venue"
},
  "geometry": {"coordinates":[-113.808083,52.307961],"type":"Point"}
}