{
  "type": "Feature",
  "properties": {
    "iso:country":"CA",
    "sg:city":"Coquitlam",
    "sg:classifiers":[
        {
            "category":"Retail",
            "subcategory":"Auto Repair",
            "type":"Services"
        }
    ],
    "sg:phone":"+1 604 525 5823",
    "sg:postcode":"V3K 6V9",
    "sg:province":"BC",
    "sg:tags":[
        "repairing",
        "automobile"
    ],
    "wof:name":"Great Canadian Oil Change",
    "wof:placetype":"venue"
},
  "geometry": {"coordinates":[-122.852745,49.233212],"type":"Point"}
}