{
  "type": "Feature",
  "properties": {
    "addr:full":"37 Rue Savaria Saint-Basile-Le-Grand QC J3N 1P7",
    "addr:housenumber":"37",
    "addr:postcode":"j3n 1p7",
    "addr:street":"Rue Savaria",
    "iso:country":"CA",
    "sg:address":"37 Rue Savaria",
    "sg:city":"Saint-Basile-Le-Grand",
    "sg:classifiers":[
        {
            "category":"Government",
            "subcategory":"Fire Station",
            "type":"Public Place"
        }
    ],
    "sg:phone":"+1 450 461 8065",
    "sg:postcode":"J3N 1P7",
    "sg:province":"QC",
    "sg:tags":[
        "department"
    ],
    "wof:name":"Saint-Basile-Le-Grand Prvntn",
    "wof:placetype":"venue"
},
  "geometry": {"coordinates":[-73.285027,45.526546],"type":"Point"}
}