{
  "type": "Feature",
  "properties": {
    "addr:full":"St Thomas ON N5R 4P5",
    "addr:postcode":"n5r 4p5",
    "iso:country":"CA",
    "sg:city":"St Thomas",
    "sg:classifiers":[
        {
            "category":"Health Services",
            "subcategory":"Podiatrist",
            "type":"Services"
        }
    ],
    "sg:phone":"+1 519 637 8006",
    "sg:postcode":"N5R 4P5",
    "sg:province":"ON",
    "wof:name":"Arbour, Carol DPM",
    "wof:placetype":"venue"
},
  "geometry": {"coordinates":[-81.17617,42.762672],"type":"Point"}
}