{
  "type": "Feature",
  "properties": {
    "addr:full":"113 Bruce St Stratford ON N5A 4A2",
    "addr:housenumber":"113",
    "addr:postcode":"n5a 4a2",
    "addr:street":"Bruce St",
    "iso:country":"CA",
    "sg:address":"113 Bruce St",
    "sg:city":"Stratford",
    "sg:classifiers":[
        {
            "category":"Organizations",
            "subcategory":"Religious Organization",
            "type":"Services"
        }
    ],
    "sg:phone":"+1 519 271 2196",
    "sg:postcode":"N5A 4A2",
    "sg:province":"ON",
    "sg:tags":[
        "church"
    ],
    "wof:name":"Memorial Baptist Church",
    "wof:placetype":"venue"
},
  "geometry": {"coordinates":[-80.970642,43.357719],"type":"Point"}
}