{
  "type": "Feature",
  "properties": {
    "iso:country":"CA",
    "sg:address":"8520 Cambie Rd",
    "sg:city":"Richmond",
    "sg:classifiers":[
        {
            "category":"Freight",
            "type":"Transportation"
        }
    ],
    "sg:phone":"+1 604 270 1432",
    "sg:postcode":"V6X 1K1",
    "sg:province":"BC",
    "sg:tags":[
        "commercial",
        "storage"
    ],
    "wof:name":"Self Storage Depot",
    "wof:placetype":"venue"
},
  "geometry": {"coordinates":[-123.12921900000001,49.184475],"type":"Point"}
}