{
  "type": "Feature",
  "properties": {
    "addr:full":"5831 Wyandotte St E Windsor ON N8S 1M7",
    "addr:housenumber":"5831",
    "addr:postcode":"n8s 1m7",
    "addr:street":"Wyandotte St E",
    "iso:country":"CA",
    "sg:address":"5831 Wyandotte St E",
    "sg:city":"Windsor",
    "sg:classifiers":[
        {
            "category":"Shopping",
            "subcategory":"Clothing, Apparel, & Fashions",
            "type":"Retail Goods"
        }
    ],
    "sg:phone":"+1 519 948 1771",
    "sg:postcode":"N8S 1M7",
    "sg:province":"ON",
    "sg:tags":[
        "cleaners",
        "tailor"
    ],
    "wof:name":"Hilda's Alterations & Dry Clng",
    "wof:placetype":"venue"
},
  "geometry": {"coordinates":[-82.967224,42.328724],"type":"Point"}
}