{
  "type": "Feature",
  "properties": {
    "addr:full":"17 Rue Kent Saint-Timothee QC J6S 4T4",
    "addr:housenumber":"17",
    "addr:postcode":"j6s 4t4",
    "addr:street":"Rue Kent Saint-Timothee",
    "iso:country":"CA",
    "sg:address":"17 Rue Kent",
    "sg:city":"Saint-Timothee",
    "sg:classifiers":[
        {
            "category":"Building & Trades",
            "subcategory":"Construction",
            "type":"Services"
        }
    ],
    "sg:phone":"+1 450 373 5805",
    "sg:postcode":"J6S 4T4",
    "sg:province":"QC",
    "sg:tags":[
        "designer",
        "dealer",
        "pool",
        "swimming"
    ],
    "wof:name":"R & F Distributeur Enrg",
    "wof:placetype":"venue"
},
  "geometry": {"coordinates":[-74.0820007324,45.2778205872],"type":"Point"}
}