{
  "type": "Feature",
  "properties": {
    "addr:full":"182 Ch Des Outaouais L'Ile-Du-Grand-Calumet QC J0X 1J0",
    "addr:housenumber":"182",
    "addr:postcode":"j0x 1j0",
    "addr:street":"Ch Des Outaouais L'Ile-Du-Grand-Calumet",
    "iso:country":"CA",
    "sg:address":"182 Ch Des Outaouais",
    "sg:city":"L'Ile-Du-Grand-Calumet",
    "sg:classifiers":[
        {
            "category":"Organizations",
            "subcategory":"Religious Organization",
            "type":"Services"
        }
    ],
    "sg:phone":"+1 819 648 2122",
    "sg:postcode":"J0X 1J0",
    "sg:province":"QC",
    "sg:tags":[
        "church"
    ],
    "wof:name":"Paroisse Ste-Anne",
    "wof:placetype":"venue"
},
  "geometry": {"coordinates":[-76.6097412109,45.719707489],"type":"Point"}
}