{
  "type": "Feature",
  "properties": {
    "addr:full":"150 Commercial St Nanaimo BC V9R 5G6",
    "addr:housenumber":"150",
    "addr:postcode":"v9r 5g6",
    "addr:street":"Commercial St",
    "iso:country":"CA",
    "sg:address":"150 Commercial St",
    "sg:city":"Nanaimo",
    "sg:classifiers":[
        {
            "category":"Arts & Performance",
            "subcategory":"Theater",
            "type":"Entertainment"
        }
    ],
    "sg:phone":"+1 250 714 0203",
    "sg:postcode":"V9R 5G6",
    "sg:province":"BC",
    "wof:name":"Theatre BC",
    "wof:placetype":"venue"
},
  "geometry": {"coordinates":[-123.936661,49.166103],"type":"Point"}
}