{
  "type": "Feature",
  "properties": {
    "iso:country":"CA",
    "sg:address":"8291 120 St",
    "sg:city":"Delta",
    "sg:classifiers":[
        {
            "category":"Education",
            "subcategory":"Special Training",
            "type":"Public Place"
        }
    ],
    "sg:phone":"+1 604 591 8355",
    "sg:postcode":"V4C 6R1",
    "sg:province":"BC",
    "sg:tags":[
        "instruction",
        "music"
    ],
    "wof:name":"R & R School of Music",
    "wof:placetype":"venue"
},
  "geometry": {"coordinates":[-122.89051055900001,49.1540336609],"type":"Point"}
}