{
  "type": "Feature",
  "properties": {
    "addr:full":"Ottawa ON K2A 3G9",
    "addr:postcode":"k2a 3g9",
    "iso:country":"CA",
    "sg:city":"Ottawa",
    "sg:classifiers":[
        {
            "category":"Social Services",
            "subcategory":"Child Care",
            "type":"Services"
        }
    ],
    "sg:phone":"+1 613 759 8364",
    "sg:postcode":"K2A 3G9",
    "sg:province":"ON",
    "wof:name":"White Haven Kindergarten Age",
    "wof:placetype":"venue"
},
  "geometry": {"coordinates":[-75.77034,45.365196],"type":"Point"}
}