{
  "type": "Feature",
  "properties": {
    "addr:full":"4043 Carling Ave Kanata ON K2K 2A4",
    "addr:housenumber":"4043",
    "addr:postcode":"k2k 2a4",
    "addr:street":"Carling Ave",
    "iso:country":"CA",
    "sg:address":"4043 Carling Ave",
    "sg:city":"Kanata",
    "sg:classifiers":[
        {
            "category":"Manufacturing",
            "subcategory":"Electronics",
            "type":"Manufacturing & Wholesale Goods"
        }
    ],
    "sg:phone":"+1 613 592 4501",
    "sg:postcode":"K2K 2A4",
    "sg:province":"ON",
    "sg:tags":[
        "semiconductor",
        "devices"
    ],
    "wof:name":"Potentia Telecom Power Inc",
    "wof:placetype":"venue"
},
  "geometry": {"coordinates":[-75.90476200000001,45.338413],"type":"Point"}
}