{
  "type": "Feature",
  "properties": {
    "addr:full":"8689 5 Side Rd Milton ON L9T 2X7",
    "addr:housenumber":"8689 5",
    "addr:postcode":"l9t 2x7",
    "addr:street":"Side Rd",
    "iso:country":"CA",
    "sg:address":"8689 5 Side Rd",
    "sg:city":"Milton",
    "sg:classifiers":[
        {
            "category":"Home & Garden",
            "subcategory":"Garden Supply",
            "type":"Retail Goods"
        }
    ],
    "sg:phone":"+1 905 878 0223",
    "sg:postcode":"L9T 2X7",
    "sg:province":"ON",
    "sg:tags":[
        "nurseryman",
        "center"
    ],
    "wof:name":"Crawford Country Gardens",
    "wof:placetype":"venue"
},
  "geometry": {"coordinates":[-79.883888,43.511036],"type":"Point"}
}