{
  "type": "Feature",
  "properties": {
    "iso:country":"CA",
    "sg:address":"123 Ramsay St",
    "sg:city":"Dalhousie",
    "sg:classifiers":[
        {
            "category":"Organizations",
            "subcategory":"Professional Association",
            "type":"Services"
        }
    ],
    "sg:phone":"+1 506 684 3036",
    "sg:postcode":"E8C 2G8",
    "sg:province":"NB",
    "sg:tags":[
        "club"
    ],
    "wof:name":"Royal Canadian Legion Br 17",
    "wof:placetype":"venue"
},
  "geometry": {"coordinates":[-66.37645721440001,48.064201355],"type":"Point"}
}