{
  "type": "Feature",
  "properties": {
    "addr:full":"789 Cecile Blvd Hawkesbury ON K6A 1P4",
    "addr:housenumber":"789",
    "addr:postcode":"k6a 1p4",
    "addr:street":"Cecile Blvd",
    "iso:country":"CA",
    "sg:address":"789 Cecile Blvd",
    "sg:city":"Hawkesbury",
    "sg:classifiers":[
        {
            "category":"Personal",
            "subcategory":"Beauty Salon",
            "type":"Services"
        }
    ],
    "sg:phone":"+1 613 632 1312",
    "sg:postcode":"K6A 1P4",
    "sg:province":"ON",
    "wof:name":"Salon Tropical Unisex",
    "wof:placetype":"venue"
},
  "geometry": {"coordinates":[-74.6001358032,45.6040344238],"type":"Point"}
}