{
  "type": "Feature",
  "properties": {
    "addr:full":"280 153 Rte Saint-Tite QC G0X 3H0",
    "addr:housenumber":"153",
    "addr:postcode":"g0x 3h0",
    "addr:street":"Rte",
    "iso:country":"CA",
    "sg:address":"280 153 Rte",
    "sg:city":"Saint-Tite",
    "sg:classifiers":[
        {
            "category":"Shopping",
            "subcategory":"Gifts & Souvenirs",
            "type":"Retail Goods"
        }
    ],
    "sg:phone":"+1 418 365 3232",
    "sg:postcode":"G0X 3H0",
    "sg:province":"QC",
    "sg:tags":[
        "party",
        "supply"
    ],
    "wof:name":"Decor Cyrel Inc",
    "wof:placetype":"venue"
},
  "geometry": {"coordinates":[-72.5780410767,46.7193565369],"type":"Point"}
}