{
  "type": "Feature",
  "properties": {
    "iso:country":"CA",
    "sg:address":"2613 St. Johns St",
    "sg:city":"Port Moody",
    "sg:classifiers":[
        {
            "category":"Professional",
            "subcategory":"Accounting & Tax Preparation",
            "type":"Services"
        }
    ],
    "sg:phone":"+1 604 939 2929",
    "sg:postcode":"V3H 2B5",
    "sg:province":"BC",
    "sg:tags":[
        "accountant"
    ],
    "wof:name":"David Gregory Ltd",
    "wof:placetype":"venue"
},
  "geometry": {"coordinates":[-122.85426330599999,49.2765045166],"type":"Point"}
}