{
  "type": "Feature",
  "properties": {
    "addr:full":"7071 Airport Rd #210B Mississauga ON L4T 4J3",
    "addr:housenumber":"7071",
    "addr:postcode":"l4t 4j3",
    "addr:street":"Airport Rd # 210B",
    "iso:country":"CA",
    "sg:address":"7071 Airport Rd #210B",
    "sg:city":"Mississauga",
    "sg:classifiers":[
        {
            "category":"Professional",
            "subcategory":"Accounting & Tax Preparation",
            "type":"Services"
        }
    ],
    "sg:phone":"+1 905 612 8144",
    "sg:postcode":"L4T 4J3",
    "sg:province":"ON",
    "sg:tags":[
        "consultant",
        "return",
        "filing"
    ],
    "wof:name":"Tax Audit Canada.com",
    "wof:placetype":"venue"
},
  "geometry": {"coordinates":[-79.64324951170001,43.7044258118],"type":"Point"}
}