{
  "type": "Feature",
  "properties": {
    "addr:full":"1691 Boul Pie-Ix Montreal QC H1V 2C3",
    "addr:housenumber":"1691",
    "addr:postcode":"h1v 2c3",
    "addr:street":"Boul Pie-Ix",
    "iso:country":"CA",
    "sg:address":"1691 Boul Pie-Ix",
    "sg:city":"Montreal",
    "sg:classifiers":[
        {
            "category":"Education",
            "subcategory":"School",
            "type":"Public Place"
        }
    ],
    "sg:phone":"+1 514 596 4488",
    "sg:postcode":"H1V 2C3",
    "sg:province":"QC",
    "wof:name":"Pavillon D'Education Comm",
    "wof:placetype":"venue"
},
  "geometry": {"coordinates":[-73.5381240845,45.5495109558],"type":"Point"}
}