{
  "type": "Feature",
  "properties": {
    "addr:full":"3326 Wells Ave Saskatoon SK S7K 5W7",
    "addr:housenumber":"3326",
    "addr:postcode":"s7k 5w7",
    "addr:street":"Wells Ave",
    "iso:country":"CA",
    "sg:address":"3326 Wells Ave",
    "sg:city":"Saskatoon",
    "sg:classifiers":[
        {
            "category":"Wholesale",
            "subcategory":"Electrical",
            "type":"Manufacturing & Wholesale Goods"
        }
    ],
    "sg:phone":"+1 306 955 1288",
    "sg:postcode":"S7K 5W7",
    "sg:province":"SK",
    "sg:tags":[
        "control"
    ],
    "wof:name":"Prairie Controls",
    "wof:placetype":"venue"
},
  "geometry": {"coordinates":[-106.64838409399999,52.1845855713],"type":"Point"}
}