{
  "type": "Feature",
  "properties": {
    "addr:full":"2053 Line 3 N Shanty Bay ON L0L 2L0",
    "addr:housenumber":"2053",
    "addr:postcode":"l0l 2l0",
    "addr:street":"Line 3 N",
    "iso:country":"CA",
    "sg:address":"2053 Line 3 N",
    "sg:city":"Shanty Bay",
    "sg:classifiers":[
        {
            "category":"Manufacturing",
            "subcategory":"Wood Products",
            "type":"Manufacturing & Wholesale Goods"
        }
    ],
    "sg:phone":"+1 705 733 0507",
    "sg:postcode":"L0L 2L0",
    "sg:province":"ON",
    "sg:tags":[
        "pallet",
        "skid"
    ],
    "wof:name":"Pallets North Inc",
    "wof:placetype":"venue"
},
  "geometry": {"coordinates":[-79.61666099999999,44.478722],"type":"Point"}
}