{
  "type": "Feature",
  "properties": {
    "addr:full":"10219 100 Ave Morinville AB T8R 1P9",
    "addr:housenumber":"10219",
    "addr:postcode":"t8r 1p9",
    "addr:street":"100 Ave",
    "iso:country":"CA",
    "sg:address":"10219 100 Ave",
    "sg:city":"Morinville",
    "sg:classifiers":[
        {
            "category":"Restaurant",
            "type":"Food & Drink"
        }
    ],
    "sg:phone":"+1 780 939 3907",
    "sg:postcode":"T8R 1P9",
    "sg:province":"AB",
    "sg:tags":[
        "pizza"
    ],
    "wof:name":"Chef's Pizza",
    "wof:placetype":"venue"
},
  "geometry": {"coordinates":[-113.649742,53.801674],"type":"Point"}
}