{
  "type": "Feature",
  "properties": {
    "addr:full":"664 Rue Martin Saint-Amable QC J0L 1N0",
    "addr:housenumber":"664",
    "addr:postcode":"j0l 1n0",
    "addr:street":"Rue Martin",
    "iso:country":"CA",
    "sg:address":"664 Rue Martin",
    "sg:city":"Saint-Amable",
    "sg:classifiers":[
        {
            "category":"Wholesale",
            "subcategory":"Auto Parts",
            "type":"Manufacturing & Wholesale Goods"
        }
    ],
    "sg:phone":"+1 450 649 2955",
    "sg:postcode":"J0L 1N0",
    "sg:province":"QC",
    "sg:tags":[
        "automobile",
        "rebuilt"
    ],
    "wof:name":"Centre Du Recyclage NJ Enr",
    "wof:placetype":"venue"
},
  "geometry": {"coordinates":[-73.29434204099999,45.634929657],"type":"Point"}
}