{
  "type": "Feature",
  "properties": {
    "addr:full":"50 Bathurst Dr # 3 Waterloo ON N2V 2C5",
    "addr:housenumber":"50",
    "addr:postcode":"n2v 2c5",
    "addr:street":"Bathurst Dr # 3",
    "iso:country":"CA",
    "sg:address":"50 Bathurst Dr # 3",
    "sg:city":"Waterloo",
    "sg:classifiers":[
        {
            "category":"Shopping",
            "subcategory":"Stationery & Office Supplies",
            "type":"Retail Goods"
        }
    ],
    "sg:phone":"+1 519 747 5777",
    "sg:postcode":"N2V 2C5",
    "sg:province":"ON",
    "sg:tags":[
        "equipment",
        "filing",
        "system"
    ],
    "wof:name":"Brenneman Filing Systems Ltd",
    "wof:placetype":"venue"
},
  "geometry": {"coordinates":[-80.537926,43.507523],"type":"Point"}
}