{
  "type": "Feature",
  "properties": {
    "addr:full":"7860 River Rd Richmond BC V6X 1X7",
    "addr:housenumber":"7860",
    "addr:postcode":"v6x 1x7",
    "addr:street":"River Rd",
    "iso:country":"CA",
    "sg:address":"7860 River Rd",
    "sg:city":"Richmond",
    "sg:classifiers":[
        {
            "category":"Education",
            "subcategory":"Dance Studio",
            "type":"Public Place"
        }
    ],
    "sg:phone":"+1 604 278 7816",
    "sg:postcode":"V6X 1X7",
    "sg:province":"BC",
    "sg:tags":[
        "instruction",
        "dancing"
    ],
    "wof:name":"Richmond Academy of Dance",
    "wof:placetype":"venue"
},
  "geometry": {"coordinates":[-123.136932,49.186718],"type":"Point"}
}