{
  "type": "Feature",
  "properties": {
    "addr:full":"36 Rue DE L'Eglise Edmundston NB E3V 1J2",
    "addr:housenumber":"36",
    "addr:postcode":"e3v 1j2",
    "addr:street":"Rue De L'Eglise",
    "iso:country":"CA",
    "sg:address":"36 Rue DE L'Eglise",
    "sg:city":"Edmundston",
    "sg:classifiers":[
        {
            "category":"Health Services",
            "subcategory":"Doctor",
            "type":"Services"
        }
    ],
    "sg:phone":"+1 506 735 4004",
    "sg:postcode":"E3V 1J2",
    "sg:province":"NB",
    "sg:tags":[
        "physician",
        "surgeon"
    ],
    "wof:name":"Martin, Pierre MD",
    "wof:placetype":"venue"
},
  "geometry": {"coordinates":[-68.326775,47.366554],"type":"Point"}
}