{
  "type": "Feature",
  "properties": {
    "addr:full":"St Albert AB T8N 1E4",
    "addr:postcode":"t8n 1e4",
    "iso:country":"CA",
    "sg:city":"St Albert",
    "sg:classifiers":[
        {
            "category":"Professional",
            "subcategory":"Business Services",
            "type":"Services"
        }
    ],
    "sg:phone":"+1 780 460 4500",
    "sg:postcode":"T8N 1E4",
    "sg:province":"AB",
    "sg:tags":[
        "interior",
        "consultant",
        "design",
        "decorator"
    ],
    "wof:name":"Di Giuseppe Interior Design",
    "wof:placetype":"venue"
},
  "geometry": {"coordinates":[-113.62505340600001,53.6332244873],"type":"Point"}
}