{
  "type": "Feature",
  "properties": {
    "addr:full":"2750 Granville St Vancouver BC V6H 3J3",
    "addr:housenumber":"2750",
    "addr:postcode":"v6h 3j3",
    "addr:street":"Granville St",
    "iso:country":"CA",
    "sg:address":"2750 Granville St",
    "sg:city":"Vancouver",
    "sg:classifiers":[
        {
            "category":"Arts & Performance",
            "subcategory":"Theater",
            "type":"Entertainment"
        }
    ],
    "sg:phone":"+1 604 687 1644",
    "sg:postcode":"V6H 3J3",
    "sg:province":"BC",
    "wof:name":"Stanley Theatre",
    "wof:placetype":"venue"
},
  "geometry": {"coordinates":[-123.138458,49.261253],"type":"Point"}
}