{
  "type": "Feature",
  "properties": {
    "addr:full":"55 Carscadden Dr #303 North York ON M2R 2A6",
    "addr:housenumber":"55",
    "addr:postcode":"m2r 2a6",
    "addr:street":"Carscadden Dr # 303",
    "iso:country":"CA",
    "sg:address":"55 Carscadden Dr #303",
    "sg:city":"North York",
    "sg:phone":"+1 416 638 0200",
    "sg:postcode":"M2R 2A6",
    "sg:province":"ON",
    "sg:tags":[
        "material",
        "fixture",
        "display"
    ],
    "wof:name":"Barnacle Canada Ltd",
    "wof:placetype":"venue"
},
  "geometry": {"coordinates":[-79.4421386719,43.76745224],"type":"Point"}
}