{
  "type": "Feature",
  "properties": {
    "addr:full":"204 Conestoga Crt Oshawa ON L1G 8B7",
    "addr:housenumber":"204",
    "addr:postcode":"l1g 8b7",
    "addr:street":"Conestoga Crt",
    "iso:country":"CA",
    "sg:address":"204 Conestoga Crt",
    "sg:city":"Oshawa",
    "sg:classifiers":[
        {
            "category":"Education",
            "subcategory":"Special Training",
            "type":"Public Place"
        }
    ],
    "sg:phone":"+1 905 723 2834",
    "sg:postcode":"L1G 8B7",
    "sg:province":"ON",
    "sg:tags":[
        "instruction",
        "music"
    ],
    "wof:name":"Brian's Guitar Studio",
    "wof:placetype":"venue"
},
  "geometry": {"coordinates":[-78.892906189,43.9381523132],"type":"Point"}
}