{
  "type": "Feature",
  "properties": {
    "addr:full":"32943 South Fraser Way Abbotsford BC V2S 2A6",
    "addr:housenumber":"32943",
    "addr:postcode":"v2s 2a6",
    "addr:street":"South Fraser Way",
    "iso:country":"CA",
    "sg:address":"32943 South Fraser Way",
    "sg:city":"Abbotsford",
    "sg:classifiers":[
        {
            "category":"Retail",
            "subcategory":"Auto Repair",
            "type":"Services"
        }
    ],
    "sg:phone":"+1 604 853 5926",
    "sg:postcode":"V2S 2A6",
    "sg:province":"BC",
    "sg:tags":[
        "repairing",
        "automobile",
        "brake"
    ],
    "wof:name":"Midas Auto Svc Experts",
    "wof:placetype":"venue"
},
  "geometry": {"coordinates":[-122.31102,49.051025],"type":"Point"}
}