{
  "type": "Feature",
  "properties": {
    "addr:full":"425 Queensway W Simcoe ON N3Y 2N4",
    "addr:housenumber":"425",
    "addr:postcode":"n3y 2n4",
    "addr:street":"Queensway W",
    "iso:country":"CA",
    "sg:address":"425 Queensway W",
    "sg:city":"Simcoe",
    "sg:classifiers":[
        {
            "category":"Autos & Motor Vehicles",
            "subcategory":"Automobile Sales",
            "type":"Retail Goods"
        }
    ],
    "sg:phone":"+1 519 428 1150",
    "sg:postcode":"N3Y 2N4",
    "sg:province":"ON",
    "sg:tags":[
        "repairing",
        "car"
    ],
    "wof:name":"Koncir Automotive",
    "wof:placetype":"venue"
},
  "geometry": {"coordinates":[-80.322174,42.843513],"type":"Point"}
}