{
  "type": "Feature",
  "properties": {
    "addr:full":"4400 Rue Radisson Montreal QC H1M 1X6",
    "addr:housenumber":"4400",
    "addr:postcode":"h1m 1x6",
    "addr:street":"Rue Radisson",
    "iso:country":"CA",
    "sg:address":"4400 Rue Radisson",
    "sg:city":"Montreal",
    "sg:classifiers":[
        {
            "category":"Building & Trades",
            "subcategory":"Electrical",
            "type":"Services"
        }
    ],
    "sg:phone":"+1 514 255 6126",
    "sg:postcode":"H1M 1X6",
    "sg:province":"QC",
    "sg:tags":[
        "electric",
        "contractor"
    ],
    "wof:name":"Entreprises D'Elec Janson Inc",
    "wof:placetype":"venue"
},
  "geometry": {"coordinates":[-73.5422134399,45.5892524719],"type":"Point"}
}