{
  "type": "Feature",
  "properties": {
    "addr:full":"11711 No. 5 Rd # 6 Richmond BC V7A 4E8",
    "addr:housenumber":"11711",
    "addr:postcode":"v7a 4e8",
    "addr:street":"No. 5 Rd # 6",
    "iso:country":"CA",
    "sg:address":"11711 No. 5 Rd # 6",
    "sg:city":"Richmond",
    "sg:classifiers":[
        {
            "category":"Retail",
            "subcategory":"Auto Repair",
            "type":"Services"
        }
    ],
    "sg:phone":"+1 604 241 4483",
    "sg:postcode":"V7A 4E8",
    "sg:province":"BC",
    "sg:tags":[
        "brake"
    ],
    "wof:name":"Predator Performance Repairs",
    "wof:placetype":"venue"
},
  "geometry": {"coordinates":[-123.092155456,49.1274490356],"type":"Point"}
}