{
  "type": "Feature",
  "properties": {
    "addr:full":"PO Box 775 Berwick NS B0P 1E0",
    "addr:housenumber":"po",
    "addr:postcode":"b0p 1e0",
    "addr:street":"Box 775",
    "iso:country":"CA",
    "sg:address":"PO Box 775",
    "sg:city":"Berwick",
    "sg:classifiers":[
        {
            "category":"Professional",
            "type":"Services"
        }
    ],
    "sg:phone":"+1 902 538 0745",
    "sg:postcode":"B0P 1E0",
    "sg:province":"NS",
    "sg:tags":[
        "establishment",
        "art",
        "gallery",
        "dealer"
    ],
    "wof:name":"Tilltop Press Inc",
    "wof:placetype":"venue"
},
  "geometry": {"coordinates":[-64.737724,45.049816],"type":"Point"}
}