{
  "type": "Feature",
  "properties": {
    "iso:country":"CA",
    "sg:address":"6405 Boul Leger",
    "sg:city":"Montreal-Nord",
    "sg:classifiers":[
        {
            "category":"Shopping",
            "subcategory":"Pharmacy",
            "type":"Retail Goods"
        }
    ],
    "sg:phone":"+1 514 323 6270",
    "sg:postcode":"H1G 1L4",
    "sg:province":"QC",
    "wof:name":"Pharmacie Jean Coutu",
    "wof:placetype":"venue"
},
  "geometry": {"coordinates":[-73.623077,45.623039],"type":"Point"}
}