{
  "type": "Feature",
  "properties": {
    "addr:full":"6405 Boul Leger Montreal-Nord QC H1G 1L4",
    "addr:housenumber":"6405",
    "addr:postcode":"h1g 1l4",
    "addr:street":"Boul Leger",
    "iso:country":"CA",
    "sg:address":"6405 Boul Leger",
    "sg:city":"Montreal-Nord",
    "sg:classifiers":[
        {
            "category":"Shopping",
            "subcategory":"Pharmacy",
            "type":"Retail Goods"
        }
    ],
    "sg:phone":"+1 514 323 6270",
    "sg:postcode":"H1G 1L4",
    "sg:province":"QC",
    "wof:name":"Pharmacie Jean Coutu",
    "wof:placetype":"venue"
},
  "geometry": {"coordinates":[-73.62307699999999,45.623039],"type":"Point"}
}