{
  "type": "Feature",
  "properties": {
    "iso:country":"CA",
    "sg:address":"6601 Mcleod Rd",
    "sg:city":"Niagara Falls",
    "sg:classifiers":[
        {
            "category":"Real Estate",
            "subcategory":"Real Estate Operator",
            "type":"Services"
        }
    ],
    "sg:phone":"+1 905 357 1393",
    "sg:postcode":"L2G 3G3",
    "sg:province":"ON",
    "sg:tags":[
        "apartment"
    ],
    "wof:name":"Mc Leod Apartments",
    "wof:placetype":"venue"
},
  "geometry": {"coordinates":[-79.1045455933,43.0707817078],"type":"Point"}
}