{
  "type": "Feature",
  "properties": {
    "addr:full":"785 Av DE Grande-Ile Grande-Ile QC J6S 3N9",
    "addr:housenumber":"785",
    "addr:postcode":"j6s 3n9",
    "addr:street":"Av De Grande-Ile Grande-Ile",
    "iso:country":"CA",
    "sg:address":"785 Av DE Grande-Ile",
    "sg:city":"Grande-Ile",
    "sg:classifiers":[
        {
            "category":"Government",
            "subcategory":"Office",
            "type":"Public Place"
        }
    ],
    "sg:phone":"+1 450 371 5546",
    "sg:postcode":"J6S 3N9",
    "sg:province":"QC",
    "sg:tags":[
        "village"
    ],
    "wof:name":"Grande-Ile Usine Ofc",
    "wof:placetype":"venue"
},
  "geometry": {"coordinates":[-74.144386,45.279236],"type":"Point"}
}