{
  "type": "Feature",
  "properties": {
    "addr:full":"121 Rang Du Bas DE LA Riv Saint-Cesaire QC J0L 1T0",
    "addr:housenumber":"121",
    "addr:postcode":"j0l 1t0",
    "addr:street":"Rang Du Bas De La Riv Saint-Cesaire",
    "iso:country":"CA",
    "sg:address":"121 Rang Du Bas DE LA Riv",
    "sg:city":"Saint-Cesaire",
    "sg:classifiers":[
        {
            "category":"Retail",
            "subcategory":"Portrait Studio",
            "type":"Services"
        }
    ],
    "sg:phone":"+1 450 469 4755",
    "sg:postcode":"J0L 1T0",
    "sg:province":"QC",
    "sg:tags":[
        "photographer"
    ],
    "wof:name":"Studio Ghis Maitre Photographe",
    "wof:placetype":"venue"
},
  "geometry": {"coordinates":[-72.9831542969,45.4636726379],"type":"Point"}
}