{
  "type": "Feature",
  "properties": {
    "addr:full":"2247 Midland Ave #7 Scarborough ON M1P 4R1",
    "addr:housenumber":"2247",
    "addr:postcode":"m1p 4r1",
    "addr:street":"Midland Ave # 7",
    "iso:country":"CA",
    "sg:address":"2247 Midland Ave #7",
    "sg:city":"Scarborough",
    "sg:classifiers":[
        {
            "category":"Professional",
            "type":"Services"
        }
    ],
    "sg:phone":"+1 416 335 1766",
    "sg:postcode":"M1P 4R1",
    "sg:province":"ON",
    "sg:tags":[
        "exporter",
        "establishment"
    ],
    "wof:name":"Juve International Supplies",
    "wof:placetype":"venue"
},
  "geometry": {"coordinates":[-79.2736206055,43.7749099731],"type":"Point"}
}