{
  "type": "Feature",
  "properties": {
    "addr:full":"271 Spadina Rd Toronto ON M5R 2V3",
    "addr:housenumber":"271",
    "addr:postcode":"m5r 2v3",
    "addr:street":"Spadina Rd",
    "iso:country":"CA",
    "sg:address":"271 Spadina Rd",
    "sg:city":"Toronto",
    "sg:classifiers":[
        {
            "category":"Health Services",
            "subcategory":"Doctor",
            "type":"Services"
        }
    ],
    "sg:phone":"+1 416 920 1717",
    "sg:postcode":"M5R 2V3",
    "sg:province":"ON",
    "sg:tags":[
        "physician",
        "surgeon"
    ],
    "wof:name":"Wade, Phillip MD",
    "wof:placetype":"venue"
},
  "geometry": {"coordinates":[-79.4076919556,43.6768569946],"type":"Point"}
}