{
  "type": "Feature",
  "properties": {
    "iso:country":"CA",
    "sg:address":"440 Boul Saint-Joseph",
    "sg:city":"Hull",
    "sg:classifiers":[
        {
            "category":"Insurance",
            "subcategory":"Insurance Agent",
            "type":"Services"
        }
    ],
    "sg:phone":"+1 819 771 3241",
    "sg:postcode":"J8Y 3Y7",
    "sg:province":"QC",
    "wof:name":"Wawanesa D'Assurance",
    "wof:placetype":"venue"
},
  "geometry": {"coordinates":[-75.732483,45.445778],"type":"Point"}
}