{
  "type": "Feature",
  "properties": {
    "addr:full":"582 10E Av O Amos QC J9T 1X3",
    "addr:housenumber":"582",
    "addr:postcode":"j9t 1x3",
    "addr:street":"10E Av O Amos",
    "iso:country":"CA",
    "sg:address":"582 10E Av O",
    "sg:city":"Amos",
    "sg:classifiers":[
        {
            "category":"Shopping",
            "subcategory":"Computers & Home Electronics",
            "type":"Retail Goods"
        }
    ],
    "sg:phone":"+1 819 732 8263",
    "sg:postcode":"J9T 1X3",
    "sg:province":"QC",
    "sg:tags":[
        "equipment",
        "dealer"
    ],
    "wof:name":"Centre D'Informatique Abitibi",
    "wof:placetype":"venue"
},
  "geometry": {"coordinates":[-78.1246643066,48.5695610046],"type":"Point"}
}