{
  "type": "Feature",
  "properties": {
    "addr:full":"381 Rte 148 Shawville QC J0X 2Y0",
    "addr:housenumber":"381",
    "addr:postcode":"j0x 2y0",
    "addr:street":"Rte 148",
    "iso:country":"CA",
    "sg:address":"381 Rte 148",
    "sg:city":"Shawville",
    "sg:classifiers":[
        {
            "category":"Education",
            "subcategory":"Special Training",
            "type":"Public Place"
        }
    ],
    "sg:phone":"+1 819 647 3112",
    "sg:postcode":"J0X 2Y0",
    "sg:province":"QC",
    "sg:tags":[
        "instruction",
        "tutoring",
        "reading",
        "improvement"
    ],
    "wof:name":"Western Quebec Literacy Cncl",
    "wof:placetype":"venue"
},
  "geometry": {"coordinates":[-76.498047,45.60146],"type":"Point"}
}