{
  "type": "Feature",
  "properties": {
    "addr:full":"2285 Howard Ave Windsor ON N8X 3V2",
    "addr:housenumber":"2285",
    "addr:postcode":"n8x 3v2",
    "addr:street":"Howard Ave",
    "iso:country":"CA",
    "sg:address":"2285 Howard Ave",
    "sg:city":"Windsor",
    "sg:classifiers":[
        {
            "category":"Manufacturing",
            "subcategory":"Tools & Machinery",
            "type":"Manufacturing & Wholesale Goods"
        }
    ],
    "sg:phone":"+1 519 254 8000",
    "sg:postcode":"N8X 3V2",
    "sg:province":"ON",
    "sg:tags":[
        "equipment",
        "safety",
        "shoes"
    ],
    "wof:name":"Brian's Footwear",
    "wof:placetype":"venue"
},
  "geometry": {"coordinates":[-83.0160369873,42.2955474854],"type":"Point"}
}