{
  "type": "Feature",
  "properties": {
    "iso:country":"CA",
    "sg:address":"332 East River Rd",
    "sg:city":"St George Brant",
    "sg:classifiers":[
        {
            "category":"Wholesale",
            "subcategory":"Construction Materials",
            "type":"Manufacturing & Wholesale Goods"
        }
    ],
    "sg:phone":"+1 519 442 6089",
    "sg:postcode":"N0E 1N0",
    "sg:province":"ON",
    "sg:tags":[
        "fence"
    ],
    "wof:name":"Hoog's Installations Ltd",
    "wof:placetype":"venue"
},
  "geometry": {"coordinates":[-80.3437347412,43.25182724],"type":"Point"}
}