{
  "type": "Feature",
  "properties": {
    "addr:full":"42 Hartfield Rd Etobicoke ON M9A 3C9",
    "addr:housenumber":"42",
    "addr:postcode":"m9a 3c9",
    "addr:street":"Hartfield Rd",
    "iso:country":"CA",
    "sg:address":"42 Hartfield Rd",
    "sg:city":"Etobicoke",
    "sg:classifiers":[
        {
            "category":"Professional",
            "subcategory":"Business Services",
            "type":"Services"
        }
    ],
    "sg:phone":"+1 416 234 2789",
    "sg:postcode":"M9A 3C9",
    "sg:province":"ON",
    "sg:tags":[
        "auctioneer"
    ],
    "wof:name":"Next Move",
    "wof:placetype":"venue"
},
  "geometry": {"coordinates":[-79.524956,43.666866],"type":"Point"}
}