{
  "type": "Feature",
  "properties": {
    "addr:full":"101 Boul Tache O Montmagny QC G5V 3T8",
    "addr:housenumber":"101",
    "addr:postcode":"g5v 3t8",
    "addr:street":"Boul Tache O",
    "iso:country":"CA",
    "sg:address":"101 Boul Tache O",
    "sg:city":"Montmagny",
    "sg:classifiers":[
        {
            "category":"Real Estate",
            "subcategory":"Real Estate Operator",
            "type":"Services"
        }
    ],
    "sg:phone":"+1 418 248 4910",
    "sg:postcode":"G5V 3T8",
    "sg:province":"QC",
    "sg:tags":[
        "mall",
        "shopping",
        "center"
    ],
    "wof:name":"Galeries Montmagny",
    "wof:placetype":"venue"
},
  "geometry": {"coordinates":[-70.559631,46.983158],"type":"Point"}
}