{
  "type": "Feature",
  "properties": {
    "addr:full":"Bridgewater NS B4V 2N1",
    "addr:postcode":"b4v 2n1",
    "iso:country":"CA",
    "sg:city":"Bridgewater",
    "sg:classifiers":[
        {
            "category":"Real Estate",
            "subcategory":"Real Estate Agent",
            "type":"Services"
        }
    ],
    "sg:phone":"+1 902 543 0136",
    "sg:postcode":"B4V 2N1",
    "sg:province":"NS",
    "wof:name":"People First",
    "wof:placetype":"venue"
},
  "geometry": {"coordinates":[-64.52299499999999,44.380367],"type":"Point"}
}