{
  "type": "Feature",
  "properties": {
    "addr:full":"Winnipeg MB R2C 3B4",
    "addr:postcode":"r2c 3b4",
    "iso:country":"CA",
    "sg:city":"Winnipeg",
    "sg:classifiers":[
        {
            "category":"Health Services",
            "subcategory":"Doctor",
            "type":"Services"
        }
    ],
    "sg:phone":"+1 204 663 4888",
    "sg:postcode":"R2C 3B4",
    "sg:province":"MB",
    "sg:tags":[
        "dentist"
    ],
    "wof:name":"Regent Avenue Dental Ctr",
    "wof:placetype":"venue"
},
  "geometry": {"coordinates":[-97.05714399999999,49.89603],"type":"Point"}
}