{
  "type": "Feature",
  "properties": {
    "addr:full":"72 Walts St Welland ON L3C 4J3",
    "addr:housenumber":"72",
    "addr:postcode":"l3c 4j3",
    "addr:street":"Walts St",
    "iso:country":"CA",
    "sg:address":"72 Walts St",
    "sg:city":"Welland",
    "sg:classifiers":[
        {
            "category":"Building & Trades",
            "subcategory":"Electrical",
            "type":"Services"
        }
    ],
    "sg:phone":"+1 905 735 3751",
    "sg:postcode":"L3C 4J3",
    "sg:province":"ON",
    "sg:tags":[
        "electric",
        "contractor"
    ],
    "wof:name":"Zavarella Electric",
    "wof:placetype":"venue"
},
  "geometry": {"coordinates":[-79.28424800000001,42.998043],"type":"Point"}
}