{
  "type": "Feature",
  "properties": {
    "addr:full":"614 Grand Ave Young SK S0K 4Y0",
    "addr:housenumber":"614",
    "addr:postcode":"s0k 4y0",
    "addr:street":"Grand Ave",
    "iso:country":"CA",
    "sg:address":"614 Grand Ave",
    "sg:city":"Young",
    "sg:classifiers":[
        {
            "category":"Education",
            "subcategory":"School",
            "type":"Public Place"
        }
    ],
    "sg:phone":"+1 306 259 2141",
    "sg:postcode":"S0K 4Y0",
    "sg:province":"SK",
    "wof:name":"Mc Clellan School",
    "wof:placetype":"venue"
},
  "geometry": {"coordinates":[-105.746826,51.766701],"type":"Point"}
}