{
  "type": "Feature",
  "properties": {
    "addr:full":"2526 Bevan Ave Sidney BC V8L 1W3",
    "addr:housenumber":"2526",
    "addr:postcode":"v8l 1w3",
    "addr:street":"Bevan Ave",
    "iso:country":"CA",
    "sg:address":"2526 Bevan Ave",
    "sg:city":"Sidney",
    "sg:classifiers":[
        {
            "category":"Autos & Motor Vehicles",
            "subcategory":"Fuel & Gas Station",
            "type":"Retail Goods"
        }
    ],
    "sg:phone":"+1 250 656 5003",
    "sg:postcode":"V8L 1W3",
    "sg:province":"BC",
    "sg:tags":[
        "oil"
    ],
    "wof:name":"Save on Gas",
    "wof:placetype":"venue"
},
  "geometry": {"coordinates":[-123.395591736,48.647808075],"type":"Point"}
}