{
  "type": "Feature",
  "properties": {
    "iso:country":"CA",
    "sg:address":"67 Willow Glen Dr",
    "sg:city":"Kanata",
    "sg:classifiers":[
        {
            "category":"Professional",
            "subcategory":"Computer Services",
            "type":"Services"
        }
    ],
    "sg:phone":"+1 613 591 0079",
    "sg:postcode":"K2M 1T1",
    "sg:province":"ON",
    "sg:tags":[
        "consultant"
    ],
    "wof:name":"Procomputer Systems",
    "wof:placetype":"venue"
},
  "geometry": {"coordinates":[-75.86822509770001,45.2916603088],"type":"Point"}
}