{
  "type": "Feature",
  "properties": {
    "addr:full":"231 Rue Lauzon Saint-Eustache QC J7R 4N4",
    "addr:housenumber":"231",
    "addr:postcode":"j7r 4n4",
    "addr:street":"Rue Lauzon",
    "iso:country":"CA",
    "sg:address":"231 Rue Lauzon",
    "sg:city":"Saint-Eustache",
    "sg:classifiers":[
        {
            "category":"Building & Trades",
            "subcategory":"Construction",
            "type":"Services"
        }
    ],
    "sg:phone":"+1 450 491 5023",
    "sg:postcode":"J7R 4N4",
    "sg:province":"QC",
    "sg:tags":[
        "resurfacing",
        "laying",
        "refinishing",
        "floor"
    ],
    "wof:name":"Plancher Locas Enr",
    "wof:placetype":"venue"
},
  "geometry": {"coordinates":[-73.899147,45.556206],"type":"Point"}
}