{
  "type": "Feature",
  "properties": {
    "addr:full":"London ON N6B 1V5",
    "addr:postcode":"n6b 1v5",
    "iso:country":"CA",
    "sg:city":"London",
    "sg:classifiers":[
        {
            "category":"Social Services",
            "type":"Services"
        }
    ],
    "sg:phone":"+1 519 439 0844",
    "sg:postcode":"N6B 1V5",
    "sg:province":"ON",
    "sg:tags":[
        "organization",
        "welfare"
    ],
    "wof:name":"Sexual Assault Ctr London",
    "wof:placetype":"venue"
},
  "geometry": {"coordinates":[-81.240753,42.986073],"type":"Point"}
}