{
  "type": "Feature",
  "properties": {
    "iso:country":"CA",
    "sg:address":"2000 Rue Notre-Dame E",
    "sg:city":"Montreal",
    "sg:classifiers":[
        {
            "category":"Retail",
            "subcategory":"Auto Rental",
            "type":"Services"
        }
    ],
    "sg:phone":"+1 514 526 9189",
    "sg:postcode":"H2K 2N3",
    "sg:province":"QC",
    "sg:tags":[
        "renting",
        "leasing",
        "truck",
        "trailer"
    ],
    "wof:name":"U-Haul Cie Ltee",
    "wof:placetype":"venue"
},
  "geometry": {"coordinates":[-73.54676055909999,45.5205078125],"type":"Point"}
}