{
  "type": "Feature",
  "properties": {
    "addr:full":"7399 River Rd Delta BC V4G 1B2",
    "addr:housenumber":"7399",
    "addr:postcode":"v4g 1b2",
    "addr:street":"River Rd",
    "iso:country":"CA",
    "sg:address":"7399 River Rd",
    "sg:city":"Delta",
    "sg:classifiers":[
        {
            "category":"Building & Trades",
            "subcategory":"Construction",
            "type":"Services"
        }
    ],
    "sg:phone":"+1 604 946 5414",
    "sg:postcode":"V4G 1B2",
    "sg:province":"BC",
    "sg:tags":[
        "system",
        "blower"
    ],
    "wof:name":"Vancouver Blower Ltd",
    "wof:placetype":"venue"
},
  "geometry": {"coordinates":[-123.012268066,49.1407546997],"type":"Point"}
}