{
  "type": "Feature",
  "properties": {
    "addr:full":"8242 Hwy 97A Mara BC V0E 2K0",
    "addr:housenumber":"8242",
    "addr:postcode":"v0e 2k0",
    "addr:street":"Hwy 97A",
    "iso:country":"CA",
    "sg:address":"8242 Hwy 97A",
    "sg:city":"Mara",
    "sg:classifiers":[
        {
            "category":"Recreation",
            "subcategory":"Marina",
            "type":"Entertainment"
        }
    ],
    "sg:phone":"+1 250 838 2035",
    "sg:postcode":"V0E 2K0",
    "sg:province":"BC",
    "wof:name":"Club Mara Marina",
    "wof:placetype":"venue"
},
  "geometry": {"coordinates":[-119.032188416,50.719543457],"type":"Point"}
}