{
  "type": "Feature",
  "properties": {
    "addr:full":"Lockport MB R1A 2R6",
    "addr:postcode":"r1a 2r6",
    "iso:country":"CA",
    "sg:city":"Lockport",
    "sg:classifiers":[
        {
            "category":"Insurance",
            "subcategory":"Insurance Agent",
            "type":"Services"
        }
    ],
    "sg:phone":"+1 204 757 7965",
    "sg:postcode":"R1A 2R6",
    "sg:province":"MB",
    "wof:name":"Graves Insurance",
    "wof:placetype":"venue"
},
  "geometry": {"coordinates":[-96.954887,50.089245],"type":"Point"}
}