{
  "type": "Feature",
  "properties": {
    "addr:full":"152 Rte Du Pont Saint-Nicolas QC G7A 2T4",
    "addr:housenumber":"152",
    "addr:postcode":"g7a 2t4",
    "addr:street":"Rte Du Pont",
    "iso:country":"CA",
    "sg:address":"152 Rte Du Pont",
    "sg:city":"Saint-Nicolas",
    "sg:classifiers":[
        {
            "category":"Travel",
            "subcategory":"Campground",
            "type":"Entertainment"
        }
    ],
    "sg:phone":"+1 418 831 2969",
    "sg:postcode":"G7A 2T4",
    "sg:province":"QC",
    "wof:name":"Camping Imperial Enr",
    "wof:placetype":"venue"
},
  "geometry": {"coordinates":[-71.290977,46.739201],"type":"Point"}
}