{
  "type": "Feature",
  "properties": {
    "addr:full":"34 29 Ave SW Calgary AB T2S 2Y3",
    "addr:postcode":"t2s 2y3",
    "addr:street":"29 Ave Sw",
    "iso:country":"CA",
    "sg:address":"34 29 Ave SW",
    "sg:city":"Calgary",
    "sg:classifiers":[
        {
            "category":"Professional",
            "subcategory":"Art Services",
            "type":"Services"
        }
    ],
    "sg:phone":"+1 403 262 3115",
    "sg:postcode":"T2S 2Y3",
    "sg:province":"AB",
    "sg:tags":[
        "photographer"
    ],
    "wof:name":"John Dean Photographs Inc",
    "wof:placetype":"venue"
},
  "geometry": {"coordinates":[-114.06076,51.027908],"type":"Point"}
}