{
  "type": "Feature",
  "properties": {
    "addr:full":"937 Wyld St North Bay ON P1B 2A7",
    "addr:housenumber":"937",
    "addr:postcode":"p1b 2a7",
    "addr:street":"Wyld St",
    "iso:country":"CA",
    "sg:address":"937 Wyld St",
    "sg:city":"North Bay",
    "sg:classifiers":[
        {
            "category":"Social Services",
            "type":"Services"
        }
    ],
    "sg:phone":"+1 705 476 5117",
    "sg:postcode":"P1B 2A7",
    "sg:province":"ON",
    "sg:tags":[
        "organization",
        "welfare"
    ],
    "wof:name":"Respite Services",
    "wof:placetype":"venue"
},
  "geometry": {"coordinates":[-79.4558563232,46.3117103577],"type":"Point"}
}