{
  "type": "Feature",
  "properties": {
    "iso:country":"CA",
    "sg:address":"301 Oxford St W",
    "sg:city":"London",
    "sg:classifiers":[
        {
            "category":"Personal",
            "subcategory":"Shoe Repair & Shine",
            "type":"Services"
        }
    ],
    "sg:phone":"+1 519 433 6791",
    "sg:postcode":"N6H 1S6",
    "sg:province":"ON",
    "sg:tags":[
        "repairing",
        "boot"
    ],
    "wof:name":"Westown Shoe Clinic",
    "wof:placetype":"venue"
},
  "geometry": {"coordinates":[-81.275581,42.988998],"type":"Point"}
}