{
  "type": "Feature",
  "properties": {
    "addr:full":"250 Rue Dupont Pont-Rouge QC G3H 1P7",
    "addr:housenumber":"250",
    "addr:postcode":"g3h 1p7",
    "addr:street":"Rue Dupont",
    "iso:country":"CA",
    "sg:address":"250 Rue Dupont",
    "sg:city":"Pont-Rouge",
    "sg:classifiers":[
        {
            "category":"Restaurant",
            "type":"Food & Drink"
        }
    ],
    "sg:phone":"+1 418 873 4529",
    "sg:postcode":"G3H 1P7",
    "sg:province":"QC",
    "wof:name":"Restaurant Buffet Central",
    "wof:placetype":"venue"
},
  "geometry": {"coordinates":[-71.700439,46.755997],"type":"Point"}
}