{
  "type": "Feature",
  "properties": {
    "addr:full":"1 Hospitality Dr Fort Erie ON L2A 6G1",
    "addr:housenumber":"1",
    "addr:postcode":"l2a 6g1",
    "addr:street":"Hospitality Dr",
    "iso:country":"CA",
    "sg:address":"1 Hospitality Dr",
    "sg:city":"Fort Erie",
    "sg:classifiers":[
        {
            "category":"Travel",
            "subcategory":"Hotels & Motels",
            "type":"Entertainment"
        }
    ],
    "sg:phone":"+1 905 871 8500",
    "sg:postcode":"L2A 6G1",
    "sg:province":"ON",
    "wof:name":"Comfort Inn",
    "wof:placetype":"venue"
},
  "geometry": {"coordinates":[-78.93161000000001,42.908852],"type":"Point"}
}