{
  "type": "Feature",
  "properties": {
    "addr:full":"310 12th St Hanover ON N4N 1V6",
    "addr:housenumber":"310",
    "addr:postcode":"n4n 1v6",
    "addr:street":"12Th St",
    "iso:country":"CA",
    "sg:address":"310 12th St",
    "sg:city":"Hanover",
    "sg:classifiers":[
        {
            "category":"Organizations",
            "subcategory":"Religious Organization",
            "type":"Services"
        }
    ],
    "sg:phone":"+1 519 364 3550",
    "sg:postcode":"N4N 1V6",
    "sg:province":"ON",
    "sg:tags":[
        "church"
    ],
    "wof:name":"Grace United Church",
    "wof:placetype":"venue"
},
  "geometry": {"coordinates":[-81.02816799999999,44.153843],"type":"Point"}
}