{
  "type": "Feature",
  "properties": {
    "addr:full":"7212 Rue Saint-Hubert Montreal QC H2R 2N1",
    "addr:housenumber":"7212",
    "addr:postcode":"h2r 2n1",
    "addr:street":"Rue Saint-Hubert",
    "iso:country":"CA",
    "sg:address":"7212 Rue Saint-Hubert",
    "sg:city":"Montreal",
    "sg:classifiers":[
        {
            "category":"Home & Garden",
            "subcategory":"Furniture",
            "type":"Retail Goods"
        }
    ],
    "sg:phone":"+1 514 495 3893",
    "sg:postcode":"H2R 2N1",
    "sg:province":"QC",
    "wof:name":"Au Palais Du Matelas",
    "wof:placetype":"venue"
},
  "geometry": {"coordinates":[-73.61409759519999,45.5410003662],"type":"Point"}
}