{
  "type": "Feature",
  "properties": {
    "addr:full":"2740 17 Ave SE Calgary AB T2A 0P6",
    "addr:housenumber":"2740",
    "addr:postcode":"t2a 0p6",
    "addr:street":"17 Ave Se",
    "iso:country":"CA",
    "sg:address":"2740 17 Ave SE",
    "sg:city":"Calgary",
    "sg:classifiers":[
        {
            "category":"Autos & Motor Vehicles",
            "subcategory":"Auto Supplies",
            "type":"Retail Goods"
        }
    ],
    "sg:phone":"+1 403 273 5243",
    "sg:postcode":"T2A 0P6",
    "sg:province":"AB",
    "sg:tags":[
        "tire"
    ],
    "wof:name":"Fair Deal Tire",
    "wof:placetype":"venue"
},
  "geometry": {"coordinates":[-113.99477400000001,51.037895],"type":"Point"}
}