{
  "type": "Feature",
  "properties": {
    "addr:full":"Edmonton AB T6H 0L3",
    "addr:postcode":"t6h 0l3",
    "iso:country":"CA",
    "sg:city":"Edmonton",
    "sg:classifiers":[
        {
            "category":"Social Services",
            "subcategory":"Child Care",
            "type":"Services"
        }
    ],
    "sg:phone":"+1 780 436 0036",
    "sg:postcode":"T6H 0L3",
    "sg:province":"AB",
    "wof:name":"Mc Kee Child Care Ctr Ltd",
    "wof:placetype":"venue"
},
  "geometry": {"coordinates":[-113.508407593,53.4880599976],"type":"Point"}
}