{
  "type": "Feature",
  "properties": {
    "addr:full":"135 Highland Rd W Kitchener ON N2M 3B9",
    "addr:housenumber":"135",
    "addr:postcode":"n2m 3b9",
    "addr:street":"Highland Rd W",
    "iso:country":"CA",
    "sg:address":"135 Highland Rd W",
    "sg:city":"Kitchener",
    "sg:classifiers":[
        {
            "category":"Organizations",
            "subcategory":"Religious Organization",
            "type":"Services"
        }
    ],
    "sg:phone":"+1 519 745 9461",
    "sg:postcode":"N2M 3B9",
    "sg:province":"ON",
    "sg:tags":[
        "church"
    ],
    "wof:name":"Highland Baptist Church",
    "wof:placetype":"venue"
},
  "geometry": {"coordinates":[-80.5033569336,43.4408531189],"type":"Point"}
}