{
  "type": "Feature",
  "properties": {
    "addr:full":"1 Main St Grand Bank NL A0E 1W0",
    "addr:housenumber":"1",
    "addr:postcode":"a0e 1w0",
    "addr:street":"Main St",
    "iso:country":"CA",
    "sg:address":"1 Main St",
    "sg:city":"Grand Bank",
    "sg:classifiers":[
        {
            "category":"Insurance",
            "subcategory":"Insurance Agent",
            "type":"Services"
        }
    ],
    "sg:phone":"+1 709 832 2459",
    "sg:postcode":"A0E 1W0",
    "sg:province":"NL",
    "wof:name":"Stoodley Financial",
    "wof:placetype":"venue"
},
  "geometry": {"coordinates":[-55.756557,47.100784],"type":"Point"}
}