{
  "type": "Feature",
  "properties": {
    "addr:full":"393 Boul Marcotte Roberval QC G8H 1Z5",
    "addr:housenumber":"393",
    "addr:postcode":"g8h 1z5",
    "addr:street":"Boul Marcotte",
    "iso:country":"CA",
    "sg:address":"393 Boul Marcotte",
    "sg:city":"Roberval",
    "sg:classifiers":[
        {
            "category":"Health Services",
            "subcategory":"Doctor",
            "type":"Services"
        }
    ],
    "sg:phone":"+1 418 275 2935",
    "sg:postcode":"G8H 1Z5",
    "sg:province":"QC",
    "sg:tags":[
        "physician",
        "surgeon"
    ],
    "wof:name":"Abinader, Naji MD",
    "wof:placetype":"venue"
},
  "geometry": {"coordinates":[-72.2238082886,48.5051727295],"type":"Point"}
}