{
  "type": "Feature",
  "properties": {
    "iso:country":"CA",
    "sg:address":"3575 40th Ave W",
    "sg:city":"Vancouver",
    "sg:classifiers":[
        {
            "category":"Organizations",
            "subcategory":"Religious Organization",
            "type":"Services"
        }
    ],
    "sg:phone":"+1 604 263 9314",
    "sg:postcode":"V6N 3B7",
    "sg:province":"BC",
    "sg:tags":[
        "church"
    ],
    "wof:name":"Baychurch Southern Baptist Ch",
    "wof:placetype":"venue"
},
  "geometry": {"coordinates":[-123.184318542,49.2358322144],"type":"Point"}
}