{
  "type": "Feature",
  "properties": {
    "addr:full":"7088 Financial Dr Mississauga ON L5N 7H5",
    "addr:housenumber":"7088",
    "addr:postcode":"l5n 7h5",
    "addr:street":"Financial Dr",
    "iso:country":"CA",
    "sg:address":"7088 Financial Dr",
    "sg:city":"Mississauga",
    "sg:classifiers":[
        {
            "category":"Wholesale",
            "subcategory":"Construction Materials",
            "type":"Manufacturing & Wholesale Goods"
        }
    ],
    "sg:phone":"+1 905 814 8000",
    "sg:postcode":"L5N 7H5",
    "sg:province":"ON",
    "sg:tags":[
        "lumber"
    ],
    "wof:name":"Upper Canada Forest Products",
    "wof:placetype":"venue"
},
  "geometry": {"coordinates":[-79.75160217289999,43.6147727966],"type":"Point"}
}