{
  "type": "Feature",
  "properties": {
    "addr:full":"58 Lisgar St Sudbury ON P3E 3L7",
    "addr:housenumber":"58",
    "addr:postcode":"p3e 3l7",
    "addr:street":"Lisgar St",
    "iso:country":"CA",
    "sg:address":"58 Lisgar St",
    "sg:city":"Sudbury",
    "sg:classifiers":[
        {
            "category":"Professional",
            "subcategory":"Lawyer & Legal Services",
            "type":"Services"
        }
    ],
    "sg:phone":"+1 705 671 2020",
    "sg:postcode":"P3E 3L7",
    "sg:province":"ON",
    "sg:tags":[
        "attorney"
    ],
    "wof:name":"Hennessy & CO Law Office",
    "wof:placetype":"venue"
},
  "geometry": {"coordinates":[-80.99269104,46.4920272827],"type":"Point"}
}