{
  "type": "Feature",
  "properties": {
    "addr:full":"989 Columbia Blvd W Lethbridge AB T1K 4M5",
    "addr:housenumber":"989",
    "addr:postcode":"t1k 4m5",
    "addr:street":"Columbia Blvd W",
    "iso:country":"CA",
    "sg:address":"989 Columbia Blvd W",
    "sg:city":"Lethbridge",
    "sg:classifiers":[
        {
            "category":"Health Services",
            "subcategory":"Doctor",
            "type":"Services"
        }
    ],
    "sg:phone":"+1 403 381 2644",
    "sg:postcode":"T1K 4M5",
    "sg:province":"AB",
    "sg:tags":[
        "dentist"
    ],
    "wof:name":"Mountain Heights Dental",
    "wof:placetype":"venue"
},
  "geometry": {"coordinates":[-112.879471,49.663811],"type":"Point"}
}