{
  "type": "Feature",
  "properties": {
    "addr:full":"22 Main St Winnipeg Beach MB R0C 3G0",
    "addr:housenumber":"22",
    "addr:postcode":"r0c 3g0",
    "addr:street":"Main St",
    "iso:country":"CA",
    "sg:address":"22 Main St",
    "sg:city":"Winnipeg Beach",
    "sg:classifiers":[
        {
            "category":"Travel",
            "subcategory":"Hotels & Motels",
            "type":"Entertainment"
        }
    ],
    "sg:phone":"+1 204 389 9949",
    "sg:postcode":"R0C 3G0",
    "sg:province":"MB",
    "wof:name":"Winnipeg Beach Hotel",
    "wof:placetype":"venue"
},
  "geometry": {"coordinates":[-96.96642300000001,50.497181],"type":"Point"}
}