{
  "type": "Feature",
  "properties": {
    "addr:full":"452 George St Sydney NS B1P 1K3",
    "addr:housenumber":"452",
    "addr:postcode":"b1p 1k3",
    "addr:street":"George St",
    "iso:country":"CA",
    "sg:address":"452 George St",
    "sg:city":"Sydney",
    "sg:phone":"+1 902 736 8502",
    "sg:postcode":"B1P 1K3",
    "sg:province":"NS",
    "sg:tags":[
        "oil"
    ],
    "wof:name":"Sydco Fuels",
    "wof:placetype":"venue"
},
  "geometry": {"coordinates":[-60.1925544739,46.137802124],"type":"Point"}
}