{
  "type": "Feature",
  "properties": {
    "addr:full":"1668 Rue Saint-Louis Sainte-Julie QC J3E 1W9",
    "addr:housenumber":"1668",
    "addr:postcode":"j3e 1w9",
    "addr:street":"Rue Saint-Louis",
    "iso:country":"CA",
    "sg:address":"1668 Rue Saint-Louis",
    "sg:city":"Sainte-Julie",
    "sg:classifiers":[
        {
            "category":"Restaurant",
            "type":"Food & Drink"
        }
    ],
    "sg:phone":"+1 450 649 5656",
    "sg:postcode":"J3E 1W9",
    "sg:province":"QC",
    "wof:name":"Med Pizza",
    "wof:placetype":"venue"
},
  "geometry": {"coordinates":[-73.33734893800001,45.593460083],"type":"Point"}
}