{
  "type": "Feature",
  "properties": {
    "addr:full":"411 8th Ave Stewart BC V0T 1W0",
    "addr:housenumber":"411",
    "addr:postcode":"v0t 1w0",
    "addr:street":"8Th Ave",
    "iso:country":"CA",
    "sg:address":"411 8th Ave",
    "sg:city":"Stewart",
    "sg:classifiers":[
        {
            "category":"Recreation",
            "type":"Entertainment"
        }
    ],
    "sg:phone":"+1 250 636 9133",
    "sg:postcode":"V0T 1W0",
    "sg:province":"BC",
    "sg:tags":[
        "guide"
    ],
    "wof:name":"Portland Charters",
    "wof:placetype":"venue"
},
  "geometry": {"coordinates":[-129.99194299999999,55.938656],"type":"Point"}
}