{
  "type": "Feature",
  "properties": {
    "iso:country":"CA",
    "sg:address":"64 Main St",
    "sg:city":"Corner Brook",
    "sg:classifiers":[
        {
            "category":"Professional",
            "subcategory":"Accounting & Tax Preparation",
            "type":"Services"
        }
    ],
    "sg:phone":"+1 709 639 7501",
    "sg:postcode":"A2H 1C6",
    "sg:province":"NL",
    "sg:tags":[
        "accountant"
    ],
    "wof:name":"Bonnell Cole Janes",
    "wof:placetype":"venue"
},
  "geometry": {"coordinates":[-57.947517395,48.952129364],"type":"Point"}
}