{
  "type": "Feature",
  "properties": {
    "iso:country":"CA",
    "sg:address":"178 Ch Du Roi",
    "sg:city":"L'Isle-Aux-Grues",
    "sg:classifiers":[
        {
            "category":"Banks & Credit Unions",
            "subcategory":"Bank",
            "type":"Services"
        }
    ],
    "sg:phone":"+1 418 248 5789",
    "sg:postcode":"G0R 1P0",
    "sg:province":"QC",
    "wof:name":"Caisses Desjardins",
    "wof:placetype":"venue"
},
  "geometry": {"coordinates":[-70.555015564,47.0566520691],"type":"Point"}
}