{
  "type": "Feature",
  "properties": {
    "iso:country":"CA",
    "sg:address":"1589 Ellesmere Rd",
    "sg:city":"Scarborough",
    "sg:classifiers":[
        {
            "category":"Restaurant",
            "type":"Food & Drink"
        }
    ],
    "sg:phone":"+1 416 431 6574",
    "sg:postcode":"M1P 2Y3",
    "sg:province":"ON",
    "wof:name":"St Andrews Fish & Chips",
    "wof:placetype":"venue"
},
  "geometry": {"coordinates":[-79.2528915405,43.7716636658],"type":"Point"}
}