{
  "type": "Feature",
  "properties": {
    "addr:full":"3242 Route 117 Pointe-Sapin NB E9A 1T3",
    "addr:housenumber":"3242",
    "addr:postcode":"e9a 1t3",
    "addr:street":"Route 117",
    "iso:country":"CA",
    "sg:address":"3242 Route 117",
    "sg:city":"Pointe-Sapin",
    "sg:classifiers":[
        {
            "category":"Building & Trades",
            "subcategory":"Construction",
            "type":"Services"
        }
    ],
    "sg:phone":"+1 506 876 2072",
    "sg:postcode":"E9A 1T3",
    "sg:province":"NB",
    "sg:tags":[
        "dock"
    ],
    "wof:name":"Pointe Sapin Administration",
    "wof:placetype":"venue"
},
  "geometry": {"coordinates":[-64.8468704224,46.9554290771],"type":"Point"}
}