{
  "type": "Feature",
  "properties": {
    "addr:full":"137 Rue Principale Courcelles QC G0M 1C0",
    "addr:housenumber":"137",
    "addr:postcode":"g0m 1c0",
    "addr:street":"Rue Principale",
    "iso:country":"CA",
    "sg:address":"137 Rue Principale",
    "sg:city":"Courcelles",
    "sg:classifiers":[
        {
            "category":"Health Services",
            "subcategory":"Doctor",
            "type":"Services"
        }
    ],
    "sg:phone":"+1 418 483 5346",
    "sg:postcode":"G0M 1C0",
    "sg:province":"QC",
    "sg:tags":[
        "physician",
        "surgeon"
    ],
    "wof:name":"Hamann, Richard MD",
    "wof:placetype":"venue"
},
  "geometry": {"coordinates":[-70.9868011475,45.8771247864],"type":"Point"}
}