{
  "type": "Feature",
  "properties": {
    "addr:full":"Surrey BC V4A 2J5",
    "addr:postcode":"v4a 2j5",
    "iso:country":"CA",
    "sg:city":"Surrey",
    "sg:classifiers":[
        {
            "category":"Shopping",
            "type":"Retail Goods"
        }
    ],
    "sg:phone":"+1 604 541 0995",
    "sg:postcode":"V4A 2J5",
    "sg:province":"BC",
    "sg:tags":[
        "equipment",
        "wine",
        "supply"
    ],
    "wof:name":"D Vine Wine",
    "wof:placetype":"venue"
},
  "geometry": {"coordinates":[-122.791451,49.045452],"type":"Point"}
}