{
  "type": "Feature",
  "properties": {
    "addr:full":"Farm Southey SK S0G 4P0",
    "addr:postcode":"s0g 4p0",
    "iso:country":"CA",
    "sg:address":"Farm",
    "sg:city":"Southey",
    "sg:classifiers":[
        {
            "category":"Manufacturing",
            "subcategory":"Food",
            "type":"Manufacturing & Wholesale Goods"
        }
    ],
    "sg:phone":"+1 306 726 4683",
    "sg:postcode":"S0G 4P0",
    "sg:province":"SK",
    "sg:tags":[
        "product",
        "manufacturer"
    ],
    "wof:name":"Last Mountain Berry Farms",
    "wof:placetype":"venue"
},
  "geometry": {"coordinates":[-104.49604034399999,50.940410614],"type":"Point"}
}