{
  "type": "Feature",
  "properties": {
    "addr:full":"210 Ingalls Head Rd Grand Manan NB E5G 3G6",
    "addr:housenumber":"210",
    "addr:postcode":"e5g 3g6",
    "addr:street":"Ingalls Head Rd",
    "iso:country":"CA",
    "sg:address":"210 Ingalls Head Rd",
    "sg:city":"Grand Manan",
    "sg:classifiers":[
        {
            "category":"Home & Garden",
            "subcategory":"Hardware",
            "type":"Retail Goods"
        }
    ],
    "sg:phone":"+1 506 662 3508",
    "sg:postcode":"E5G 3G6",
    "sg:province":"NB",
    "sg:tags":[
        "saw"
    ],
    "wof:name":"Bonny Brook Sales & Svc",
    "wof:placetype":"venue"
},
  "geometry": {"coordinates":[-66.798149,44.675453],"type":"Point"}
}