{
  "type": "Feature",
  "properties": {
    "addr:full":"2511 Rue Alice Baie-Comeau QC G5C 1B1",
    "addr:housenumber":"2511",
    "addr:postcode":"g5c 1b1",
    "addr:street":"Rue Alice",
    "iso:country":"CA",
    "sg:address":"2511 Rue Alice",
    "sg:city":"Baie-Comeau",
    "sg:classifiers":[
        {
            "category":"Building & Trades",
            "subcategory":"Construction",
            "type":"Services"
        }
    ],
    "sg:phone":"+1 418 589 4636",
    "sg:postcode":"G5C 1B1",
    "sg:province":"QC",
    "sg:tags":[
        "general",
        "contractor"
    ],
    "wof:name":"Menuiserie Bertin Inc",
    "wof:placetype":"venue"
},
  "geometry": {"coordinates":[-68.293999,49.194908],"type":"Point"}
}