{
  "type": "Feature",
  "properties": {
    "iso:country":"CA",
    "sg:address":"707 Downie St",
    "sg:city":"Stratford",
    "sg:classifiers":[
        {
            "category":"Organizations",
            "subcategory":"Religious Organization",
            "type":"Services"
        }
    ],
    "sg:phone":"+1 519 273 4441",
    "sg:postcode":"N5A 1Y8",
    "sg:province":"ON",
    "sg:tags":[
        "church"
    ],
    "wof:name":"Jubilee Christian Fellowship",
    "wof:placetype":"venue"
},
  "geometry": {"coordinates":[-80.9738616943,43.3559379578],"type":"Point"}
}