{
  "type": "Feature",
  "properties": {
    "addr:full":"30 West St Stephenville NL A2N 1C6",
    "addr:housenumber":"30",
    "addr:postcode":"a2n 1c6",
    "addr:street":"West St",
    "iso:country":"CA",
    "sg:address":"30 West St",
    "sg:city":"Stephenville",
    "sg:classifiers":[
        {
            "category":"Social Services",
            "subcategory":"Child Care",
            "type":"Services"
        }
    ],
    "sg:phone":"+1 709 643 4206",
    "sg:postcode":"A2N 1C6",
    "sg:province":"NL",
    "wof:name":"Care-A-Lot Day Care",
    "wof:placetype":"venue"
},
  "geometry": {"coordinates":[-58.595589,48.547394],"type":"Point"}
}