{
  "type": "Feature",
  "properties": {
    "addr:full":"579 Cook St Boissevain MB R0K 0E0",
    "addr:housenumber":"579",
    "addr:postcode":"r0k 0e0",
    "addr:street":"Cook St",
    "iso:country":"CA",
    "sg:address":"579 Cook St",
    "sg:city":"Boissevain",
    "sg:classifiers":[
        {
            "category":"Professional",
            "subcategory":"Lawyer & Legal Services",
            "type":"Services"
        }
    ],
    "sg:phone":"+1 204 534 2431",
    "sg:postcode":"R0K 0E0",
    "sg:province":"MB",
    "sg:tags":[
        "attorney"
    ],
    "wof:name":"Jah George Law Office",
    "wof:placetype":"venue"
},
  "geometry": {"coordinates":[-100.059456,49.229626],"type":"Point"}
}