{
  "type": "Feature",
  "properties": {
    "addr:full":"166 Allanford Rd Scarborough ON M1T 2N9",
    "addr:housenumber":"166",
    "addr:postcode":"m1t 2n9",
    "addr:street":"Allanford Rd",
    "iso:country":"CA",
    "sg:address":"166 Allanford Rd",
    "sg:city":"Scarborough",
    "sg:classifiers":[
        {
            "category":"Real Estate",
            "subcategory":"Developer",
            "type":"Services"
        }
    ],
    "sg:phone":"+1 416 291 5177",
    "sg:postcode":"M1T 2N9",
    "sg:province":"ON",
    "wof:name":"Shannon Properties Ltd",
    "wof:placetype":"venue"
},
  "geometry": {"coordinates":[-79.29289245610001,43.7802696228],"type":"Point"}
}