{
  "type": "Feature",
  "properties": {
    "iso:country":"CA",
    "sg:city":"Kamloops",
    "sg:classifiers":[
        {
            "category":"Home & Garden",
            "subcategory":"Building Materials",
            "type":"Retail Goods"
        }
    ],
    "sg:phone":"+1 250 374 1119",
    "sg:postcode":"V2C 6K2",
    "sg:province":"BC",
    "sg:tags":[
        "door"
    ],
    "wof:name":"Gienow Windows & Doors",
    "wof:placetype":"venue"
},
  "geometry": {"coordinates":[-120.374206543,50.6715011597],"type":"Point"}
}