{
  "type": "Feature",
  "properties": {
    "addr:full":"2605 Carling Ave Ottawa ON K2B 6V3",
    "addr:housenumber":"2605",
    "addr:postcode":"k2b 6v3",
    "addr:street":"Carling Ave",
    "iso:country":"CA",
    "sg:address":"2605 Carling Ave",
    "sg:city":"Ottawa",
    "sg:classifiers":[
        {
            "category":"Health Services",
            "subcategory":"Clinic",
            "type":"Services"
        }
    ],
    "sg:phone":"+1 613 820 0421",
    "sg:postcode":"K2B 6V3",
    "sg:province":"ON",
    "sg:tags":[
        "holistic",
        "practitioner"
    ],
    "wof:name":"Natural Health Ctr",
    "wof:placetype":"venue"
},
  "geometry": {"coordinates":[-75.7889251709,45.3624305725],"type":"Point"}
}