{
  "type": "Feature",
  "properties": {
    "addr:full":"752 Broadview Ave Toronto ON M4K 2P1",
    "addr:housenumber":"752",
    "addr:postcode":"m4k 2p1",
    "addr:street":"Broadview Ave",
    "iso:country":"CA",
    "sg:address":"752 Broadview Ave",
    "sg:city":"Toronto",
    "sg:classifiers":[
        {
            "category":"Health Services",
            "subcategory":"Chiropractor",
            "type":"Services"
        }
    ],
    "sg:phone":"+1 416 465 8737",
    "sg:postcode":"M4K 2P1",
    "sg:province":"ON",
    "wof:name":"Academy Chiropractic Clinics",
    "wof:placetype":"venue"
},
  "geometry": {"coordinates":[-79.35874938960001,43.6758460999],"type":"Point"}
}