{
  "type": "Feature",
  "properties": {
    "iso:country":"CA",
    "sg:city":"Madoc",
    "sg:classifiers":[
        {
            "category":"Organizations",
            "subcategory":"Religious Organization",
            "type":"Services"
        }
    ],
    "sg:phone":"+1 613 473 4480",
    "sg:postcode":"K0K 2K0",
    "sg:province":"ON",
    "sg:tags":[
        "church"
    ],
    "wof:name":"Madoc Pentecostal Church",
    "wof:placetype":"venue"
},
  "geometry": {"coordinates":[-77.4691543579,44.5080070496],"type":"Point"}
}