{
  "type": "Feature",
  "properties": {
    "addr:full":"1 Benito Dr Pukatawagan MB R0B 1G0",
    "addr:housenumber":"1",
    "addr:postcode":"r0b 1g0",
    "addr:street":"Benito Dr Pukatawagan",
    "iso:country":"CA",
    "sg:address":"1 Benito Dr",
    "sg:city":"Pukatawagan",
    "sg:classifiers":[
        {
            "category":"Organizations",
            "subcategory":"Professional Association",
            "type":"Services"
        }
    ],
    "sg:phone":"+1 204 553 2089",
    "sg:postcode":"R0B 1G0",
    "sg:province":"MB",
    "sg:tags":[
        "native"
    ],
    "wof:name":"Mathias Colomb Band Government",
    "wof:placetype":"venue"
},
  "geometry": {"coordinates":[-101.314552307,55.7427101135],"type":"Point"}
}