{
  "type": "Feature",
  "properties": {
    "addr:full":"107 Fort Rd Perth-Andover NB E7H 2B6",
    "addr:housenumber":"107",
    "addr:postcode":"e7h 2b6",
    "addr:street":"Fort Rd",
    "iso:country":"CA",
    "sg:address":"107 Fort Rd",
    "sg:city":"Perth-Andover",
    "sg:classifiers":[
        {
            "category":"Shopping",
            "subcategory":"Florist",
            "type":"Retail Goods"
        }
    ],
    "sg:phone":"+1 506 273 2097",
    "sg:postcode":"E7H 2B6",
    "sg:province":"NB",
    "wof:name":"Hoyt's Flowers & Gifts",
    "wof:placetype":"venue"
},
  "geometry": {"coordinates":[-67.7169342041,46.7491607666],"type":"Point"}
}