{
  "type": "Feature",
  "properties": {
    "addr:full":"214 King St E Oshawa ON L1H 1C7",
    "addr:housenumber":"214",
    "addr:postcode":"l1h 1c7",
    "addr:street":"King St E",
    "iso:country":"CA",
    "sg:address":"214 King St E",
    "sg:city":"Oshawa",
    "sg:classifiers":[
        {
            "category":"Banks & Credit Unions",
            "subcategory":"Bank",
            "type":"Services"
        }
    ],
    "sg:phone":"+1 905 576 4200",
    "sg:postcode":"L1H 1C7",
    "sg:province":"ON",
    "wof:name":"Oshawa Comm Credit Union Ltd",
    "wof:placetype":"venue"
},
  "geometry": {"coordinates":[-78.85586499999999,43.899506],"type":"Point"}
}