{
  "type": "Feature",
  "properties": {
    "addr:full":"14 Rue St Jean Squatec QC G0L 4H0",
    "addr:housenumber":"14",
    "addr:postcode":"g0l 4h0",
    "addr:street":"Rue St Jean Squatec",
    "iso:country":"CA",
    "sg:address":"14 Rue St Jean",
    "sg:city":"Squatec",
    "sg:classifiers":[
        {
            "category":"Retail",
            "subcategory":"Funeral Services",
            "type":"Services"
        }
    ],
    "sg:phone":"+1 418 855 2767",
    "sg:postcode":"G0L 4H0",
    "sg:province":"QC",
    "sg:tags":[
        "director"
    ],
    "wof:name":"Funerarium Claude Caron Ltee",
    "wof:placetype":"venue"
},
  "geometry": {"coordinates":[-68.721206665,47.8808784485],"type":"Point"}
}