{
  "type": "Feature",
  "properties": {
    "addr:full":"4560 Adelaide St Port Alberni BC V9Y 6N3",
    "addr:housenumber":"4560",
    "addr:postcode":"v9y 6n3",
    "addr:street":"Adelaide St",
    "iso:country":"CA",
    "sg:address":"4560 Adelaide St",
    "sg:city":"Port Alberni",
    "sg:classifiers":[
        {
            "category":"Cinema",
            "subcategory":"Movie Rental",
            "type":"Entertainment"
        }
    ],
    "sg:phone":"+1 250 724 2314",
    "sg:postcode":"V9Y 6N3",
    "sg:province":"BC",
    "sg:tags":[
        "leasing",
        "video",
        "disc",
        "tape"
    ],
    "wof:name":"Mort's Video",
    "wof:placetype":"venue"
},
  "geometry": {"coordinates":[-124.808097839,49.2589378357],"type":"Point"}
}