{
  "type": "Feature",
  "properties": {
    "iso:country":"CA",
    "sg:city":"Delta",
    "sg:classifiers":[
        {
            "category":"Shopping",
            "subcategory":"Clothing, Apparel, & Fashions",
            "type":"Retail Goods"
        }
    ],
    "sg:phone":"+1 604 940 1149",
    "sg:postcode":"V4K 1W4",
    "sg:province":"BC",
    "wof:name":"Hot Cotton",
    "wof:placetype":"venue"
},
  "geometry": {"coordinates":[-123.07758331300001,49.0903778076],"type":"Point"}
}