{
  "type": "Feature",
  "properties": {
    "addr:full":"2932 Chesterfield Ave North Vancouver BC V7N 3M6",
    "addr:housenumber":"2932",
    "addr:postcode":"v7n 3m6",
    "addr:street":"Chesterfield Ave",
    "iso:country":"CA",
    "sg:address":"2932 Chesterfield Ave",
    "sg:city":"North Vancouver",
    "sg:classifiers":[
        {
            "category":"Building & Trades",
            "subcategory":"Construction",
            "type":"Services"
        }
    ],
    "sg:phone":"+1 604 987 4954",
    "sg:postcode":"V7N 3M6",
    "sg:province":"BC",
    "sg:tags":[
        "excavating",
        "bulldozing",
        "contractor"
    ],
    "wof:name":"Arne Sorensen Bulldozing Ltd",
    "wof:placetype":"venue"
},
  "geometry": {"coordinates":[-123.07508900000001,49.335629],"type":"Point"}
}