{
  "type": "Feature",
  "properties": {
    "addr:full":"1241 Plank Rd Sarnia ON N7T 7H3",
    "addr:housenumber":"1241",
    "addr:postcode":"n7t 7h3",
    "addr:street":"Plank Rd",
    "iso:country":"CA",
    "sg:address":"1241 Plank Rd",
    "sg:city":"Sarnia",
    "sg:classifiers":[
        {
            "category":"Manufacturing",
            "subcategory":"Motor Vehicles & Parts",
            "type":"Manufacturing & Wholesale Goods"
        }
    ],
    "sg:phone":"+1 519 344 2489",
    "sg:postcode":"N7T 7H3",
    "sg:province":"ON",
    "sg:tags":[
        "automobile",
        "wrecker"
    ],
    "wof:name":"Sarnia Auto Wreckers Ltd",
    "wof:placetype":"venue"
},
  "geometry": {"coordinates":[-82.3727264404,42.9536514282],"type":"Point"}
}