{
  "type": "Feature",
  "properties": {
    "iso:country":"CA",
    "sg:address":"9210 Williams St",
    "sg:city":"Chilliwack",
    "sg:classifiers":[
        {
            "category":"Organizations",
            "subcategory":"Religious Organization",
            "type":"Services"
        }
    ],
    "sg:phone":"+1 604 792 8181",
    "sg:postcode":"V2P 5E5",
    "sg:province":"BC",
    "sg:tags":[
        "church"
    ],
    "wof:name":"First Avenue Church of God",
    "wof:placetype":"venue"
},
  "geometry": {"coordinates":[-121.94535827599999,49.1691665649],"type":"Point"}
}