{
  "type": "Feature",
  "properties": {
    "addr:full":"500 Rte Du Bois-Blanc Saint-Justin QC J0K 2V0",
    "addr:housenumber":"500",
    "addr:postcode":"j0k 2v0",
    "addr:street":"Rte Du Bois-Blanc",
    "iso:country":"CA",
    "sg:address":"500 Rte Du Bois-Blanc",
    "sg:city":"Saint-Justin",
    "sg:classifiers":[
        {
            "category":"Local Transit",
            "type":"Transportation"
        }
    ],
    "sg:phone":"+1 819 227 4639",
    "sg:postcode":"J0K 2V0",
    "sg:province":"QC",
    "sg:tags":[
        "bus",
        "line"
    ],
    "wof:name":"Autobus Scolaires Bellemare",
    "wof:placetype":"venue"
},
  "geometry": {"coordinates":[-73.11399841310001,46.2377891541],"type":"Point"}
}