{
  "type": "Feature",
  "properties": {
    "addr:full":"3032 Dougall Ave Windsor ON N9E 1S4",
    "addr:housenumber":"3032",
    "addr:postcode":"n9e 1s4",
    "addr:street":"Dougall Ave",
    "iso:country":"CA",
    "sg:address":"3032 Dougall Ave",
    "sg:city":"Windsor",
    "sg:classifiers":[
        {
            "category":"Travel",
            "subcategory":"Hotels & Motels",
            "type":"Entertainment"
        }
    ],
    "sg:phone":"+1 519 969 7600",
    "sg:postcode":"N9E 1S4",
    "sg:province":"ON",
    "wof:name":"Stonecroft Inn",
    "wof:placetype":"venue"
},
  "geometry": {"coordinates":[-83.01329800000001,42.272354],"type":"Point"}
}