{
  "type": "Feature",
  "properties": {
    "iso:country":"CA",
    "sg:address":"3032 Dougall Ave",
    "sg:city":"Windsor",
    "sg:classifiers":[
        {
            "category":"Travel",
            "subcategory":"Hotels & Motels",
            "type":"Entertainment"
        }
    ],
    "sg:phone":"+1 519 969 7600",
    "sg:postcode":"N9E 1S4",
    "sg:province":"ON",
    "wof:name":"Stonecroft Inn",
    "wof:placetype":"venue"
},
  "geometry": {"coordinates":[-83.013298,42.272354],"type":"Point"}
}