{
  "type": "Feature",
  "properties": {
    "addr:full":"Kamloops BC V2C 2A5",
    "addr:postcode":"bc v2c 2a5",
    "iso:country":"CA",
    "sg:city":"Kamloops",
    "sg:classifiers":[
        {
            "category":"Retail",
            "subcategory":"Photofinishing",
            "type":"Services"
        }
    ],
    "sg:phone":"+1 250 374 4611",
    "sg:postcode":"V2C 2A5",
    "sg:province":"BC",
    "sg:tags":[
        "photographic",
        "supply"
    ],
    "wof:name":"Kamloops Camera House Ltd",
    "wof:placetype":"venue"
},
  "geometry": {"coordinates":[-120.333747864,50.6759986877],"type":"Point"}
}