{
  "type": "Feature",
  "properties": {
    "addr:full":"Victoria BC V8S 1K9",
    "addr:postcode":"v8s 1k9",
    "iso:country":"CA",
    "sg:city":"Victoria",
    "sg:classifiers":[
        {
            "category":"Retail",
            "subcategory":"Animal Services",
            "type":"Services"
        }
    ],
    "sg:phone":"+1 250 598 7331",
    "sg:postcode":"V8S 1K9",
    "sg:province":"BC",
    "sg:tags":[
        "pet",
        "food",
        "grooming",
        "washing",
        "supply"
    ],
    "wof:name":"Hollywood Pet Ctr",
    "wof:placetype":"venue"
},
  "geometry": {"coordinates":[-123.333595,48.413296],"type":"Point"}
}