{
  "type": "Feature",
  "properties": {
    "addr:full":"712 Lalonde St Whitewood SK S0G 5C0",
    "addr:housenumber":"712",
    "addr:postcode":"s0g 5c0",
    "addr:street":"Lalonde St",
    "iso:country":"CA",
    "sg:address":"712 Lalonde St",
    "sg:city":"Whitewood",
    "sg:classifiers":[
        {
            "category":"Manufacturing",
            "subcategory":"Leather Goods",
            "type":"Manufacturing & Wholesale Goods"
        }
    ],
    "sg:phone":"+1 306 735 4248",
    "sg:postcode":"S0G 5C0",
    "sg:province":"SK",
    "sg:tags":[
        "clothes"
    ],
    "wof:name":"D & A Leathercraft Ltd",
    "wof:placetype":"venue"
},
  "geometry": {"coordinates":[-102.266876,50.325661],"type":"Point"}
}