{
  "type": "Feature",
  "properties": {
    "addr:full":"1980 Rue Le Chatelier Laval QC H7L 5B4",
    "addr:housenumber":"1980",
    "addr:postcode":"h7l 5b4",
    "addr:street":"Rue Le Chatelier",
    "iso:country":"CA",
    "sg:address":"1980 Rue Le Chatelier",
    "sg:city":"Laval",
    "sg:classifiers":[
        {
            "category":"Wholesale",
            "subcategory":"Stationery",
            "type":"Manufacturing & Wholesale Goods"
        }
    ],
    "sg:phone":"+1 450 686 5999",
    "sg:postcode":"H7L 5B4",
    "sg:province":"QC",
    "sg:tags":[
        "product",
        "paper"
    ],
    "wof:name":"Produits Comtech Inc",
    "wof:placetype":"venue"
},
  "geometry": {"coordinates":[-73.75862884519999,45.5871391296],"type":"Point"}
}