{
  "type": "Feature",
  "properties": {
    "addr:full":"225 Rue Saint-Germain O Rimouski QC G5L 4B9",
    "addr:housenumber":"225",
    "addr:postcode":"g5l 4b9",
    "addr:street":"Rue Saint-Germain O",
    "iso:country":"CA",
    "sg:address":"225 Rue Saint-Germain O",
    "sg:city":"Rimouski",
    "sg:classifiers":[
        {
            "category":"Health Services",
            "subcategory":"Nursing And Care Facility",
            "type":"Services"
        }
    ],
    "sg:phone":"+1 418 722 0074",
    "sg:postcode":"G5L 4B9",
    "sg:province":"QC",
    "sg:tags":[
        "home",
        "retirement",
        "community"
    ],
    "wof:name":"Residences DE L'Immaculee Enr",
    "wof:placetype":"venue"
},
  "geometry": {"coordinates":[-68.5188217163,48.4559211731],"type":"Point"}
}