{
  "type": "Feature",
  "properties": {
    "addr:full":"Hwy 1 W Moosomin SK S0G 3N0",
    "addr:postcode":"s0g 3n0",
    "addr:street":"Hwy 1 W",
    "iso:country":"CA",
    "sg:address":"Hwy 1 W",
    "sg:city":"Moosomin",
    "sg:classifiers":[
        {
            "category":"Wholesale",
            "subcategory":"Farm Supplies",
            "type":"Manufacturing & Wholesale Goods"
        }
    ],
    "sg:phone":"+1 306 435 3327",
    "sg:postcode":"S0G 3N0",
    "sg:province":"SK",
    "sg:tags":[
        "livestock"
    ],
    "wof:name":"Prairie Livestock",
    "wof:placetype":"venue"
},
  "geometry": {"coordinates":[-101.660782,50.146824],"type":"Point"}
}