{
  "type": "Feature",
  "properties": {
    "addr:full":"Saint-Emile QC G3E 1Z3",
    "addr:postcode":"g3e 1z3",
    "iso:country":"CA",
    "sg:city":"Saint-Emile",
    "sg:classifiers":[
        {
            "category":"Manufacturing",
            "subcategory":"Lumber",
            "type":"Manufacturing & Wholesale Goods"
        }
    ],
    "sg:phone":"+1 418 845 1532",
    "sg:postcode":"G3E 1Z3",
    "sg:province":"QC",
    "sg:tags":[
        "equipment",
        "stair"
    ],
    "wof:name":"Composantes Lab-CO",
    "wof:placetype":"venue"
},
  "geometry": {"coordinates":[-71.331337,46.863876],"type":"Point"}
}