{
  "type": "Feature",
  "properties": {
    "addr:full":"180 Sandalwood Pky E # 5 Brampton ON L6Z 1Y4",
    "addr:housenumber":"180",
    "addr:postcode":"l6z 1y4",
    "addr:street":"Sandalwood Pky E # 5",
    "iso:country":"CA",
    "sg:address":"180 Sandalwood Pky E # 5",
    "sg:city":"Brampton",
    "sg:classifiers":[
        {
            "category":"Retail",
            "subcategory":"Laundry & Dry Cleaning",
            "type":"Services"
        }
    ],
    "sg:phone":"+1 905 846 0705",
    "sg:postcode":"L6Z 1Y4",
    "sg:province":"ON",
    "sg:tags":[
        "cleaners"
    ],
    "wof:name":"Sketchley Cleaners",
    "wof:placetype":"venue"
},
  "geometry": {"coordinates":[-79.7944488525,43.7276382446],"type":"Point"}
}