{
  "type": "Feature",
  "properties": {
    "addr:full":"4582 Rue Traversy Saint-Nicephore QC J2A 1C8",
    "addr:housenumber":"4582",
    "addr:postcode":"j2a 1c8",
    "addr:street":"Rue Traversy Saint-Nicephore",
    "iso:country":"CA",
    "sg:address":"4582 Rue Traversy",
    "sg:city":"Saint-Nicephore",
    "sg:classifiers":[
        {
            "category":"Personal",
            "subcategory":"Beauty Salon",
            "type":"Services"
        }
    ],
    "sg:phone":"+1 819 472 4303",
    "sg:postcode":"J2A 1C8",
    "sg:province":"QC",
    "wof:name":"Salon Ginette",
    "wof:placetype":"venue"
},
  "geometry": {"coordinates":[-72.43441,45.835224],"type":"Point"}
}