{
  "type": "Feature",
  "properties": {
    "iso:country":"CA",
    "sg:address":"1 Pennywell Rd",
    "sg:city":"St. John's",
    "sg:classifiers":[
        {
            "category":"Manufacturing",
            "subcategory":"Food",
            "type":"Manufacturing & Wholesale Goods"
        }
    ],
    "sg:phone":"+1 709 739 8111",
    "sg:postcode":"A1C 2K8",
    "sg:province":"NL",
    "sg:tags":[
        "seafood",
        "product",
        "fish",
        "prepared"
    ],
    "wof:name":"Variety Foods Ltd",
    "wof:placetype":"venue"
},
  "geometry": {"coordinates":[-52.7169914246,47.5635986328],"type":"Point"}
}