{
  "type": "Feature",
  "properties": {
    "addr:full":"51 Laplanche St Amherst NS B4H 3H1",
    "addr:housenumber":"51",
    "addr:postcode":"b4h 3h1",
    "addr:street":"Laplanche St",
    "iso:country":"CA",
    "sg:address":"51 Laplanche St",
    "sg:city":"Amherst",
    "sg:classifiers":[
        {
            "category":"Professional",
            "subcategory":"Employment Agencies",
            "type":"Services"
        }
    ],
    "sg:phone":"+1 902 667 4182",
    "sg:postcode":"B4H 3H1",
    "sg:province":"NS",
    "sg:tags":[
        "help",
        "contractor"
    ],
    "wof:name":"Telnet International",
    "wof:placetype":"venue"
},
  "geometry": {"coordinates":[-64.2164764404,45.8358154297],"type":"Point"}
}