{
  "type": "Feature",
  "properties": {
    "iso:country":"CA",
    "sg:address":"8505 Boul Saint-Michel",
    "sg:city":"Montreal",
    "sg:classifiers":[
        {
            "category":"Food & Beverages",
            "subcategory":"Groceries & Convenience Stores",
            "type":"Retail Goods"
        }
    ],
    "sg:phone":"+1 514 728 6771",
    "sg:postcode":"H1Z 3E7",
    "sg:province":"QC",
    "sg:tags":[
        "grocer"
    ],
    "wof:name":"Foire Des Antilles",
    "wof:placetype":"venue"
},
  "geometry": {"coordinates":[-73.616501,45.567066],"type":"Point"}
}