{
  "type": "Feature",
  "properties": {
    "addr:full":"Burlington ON L7N 3P2",
    "addr:postcode":"l7n 3p2",
    "iso:country":"CA",
    "sg:city":"Burlington",
    "sg:classifiers":[
        {
            "category":"Banks & Credit Unions",
            "subcategory":"Investment Brokerage",
            "type":"Services"
        }
    ],
    "sg:phone":"+1 905 333 1995",
    "sg:postcode":"L7N 3P2",
    "sg:province":"ON",
    "wof:name":"Bellamy & Ball Ltd",
    "wof:placetype":"venue"
},
  "geometry": {"coordinates":[-79.78672,43.361034],"type":"Point"}
}