{
  "type": "Feature",
  "properties": {
    "addr:full":"180 Parsons Rd #35 Alliston ON L9R 1E8",
    "addr:housenumber":"180",
    "addr:postcode":"l9r 1e8",
    "addr:street":"Parsons Rd # 35 Alliston",
    "iso:country":"CA",
    "sg:address":"180 Parsons Rd #35",
    "sg:city":"Alliston",
    "sg:classifiers":[
        {
            "category":"Building & Trades",
            "subcategory":"Plumbing",
            "type":"Services"
        }
    ],
    "sg:phone":"+1 705 435 2319",
    "sg:postcode":"L9R 1E8",
    "sg:province":"ON",
    "sg:tags":[
        "heating",
        "cleaning",
        "contractor"
    ],
    "wof:name":"Tecumseth Heating & Air",
    "wof:placetype":"venue"
},
  "geometry": {"coordinates":[-79.85852050779999,44.149520874],"type":"Point"}
}