{
  "type": "Feature",
  "properties": {
    "addr:full":"Hull QC J8X 3N8",
    "addr:postcode":"j8x 3n8",
    "iso:country":"CA",
    "sg:city":"Hull",
    "sg:classifiers":[
        {
            "category":"Building & Trades",
            "subcategory":"Electrical",
            "type":"Services"
        }
    ],
    "sg:phone":"+1 819 777 7195",
    "sg:postcode":"J8X 3N8",
    "sg:province":"QC",
    "sg:tags":[
        "electric",
        "contractor"
    ],
    "wof:name":"Entreprises Electriques Yvan",
    "wof:placetype":"venue"
},
  "geometry": {"coordinates":[-75.71184539790001,45.4361419678],"type":"Point"}
}