{
  "type": "Feature",
  "properties": {
    "addr:full":"160 Rue Wolfe Levis QC G6V 3Z5",
    "addr:housenumber":"160",
    "addr:postcode":"g6v 3z5",
    "addr:street":"Rue Wolfe",
    "iso:country":"CA",
    "sg:address":"160 Rue Wolfe",
    "sg:city":"Levis",
    "sg:classifiers":[
        {
            "category":"Food & Beverages",
            "subcategory":"Groceries & Convenience Stores",
            "type":"Retail Goods"
        }
    ],
    "sg:phone":"+1 418 833 7900",
    "sg:postcode":"G6V 3Z5",
    "sg:province":"QC",
    "wof:name":"Depanneur Sonerco Levis Enr",
    "wof:placetype":"venue"
},
  "geometry": {"coordinates":[-71.1798858643,46.8150138855],"type":"Point"}
}