{
  "type": "Feature",
  "properties": {
    "addr:full":"177 Boland St Wingham ON N0G 2W0",
    "addr:housenumber":"177",
    "addr:postcode":"n0g 2w0",
    "addr:street":"Boland St",
    "iso:country":"CA",
    "sg:address":"177 Boland St",
    "sg:city":"Wingham",
    "sg:classifiers":[
        {
            "category":"Organizations",
            "subcategory":"Religious Organization",
            "type":"Services"
        }
    ],
    "sg:phone":"+1 519 357 1511",
    "sg:postcode":"N0G 2W0",
    "sg:province":"ON",
    "sg:tags":[
        "church"
    ],
    "wof:name":"Wingham Bible Chapel",
    "wof:placetype":"venue"
},
  "geometry": {"coordinates":[-81.305252,43.886684],"type":"Point"}
}