{
  "type": "Feature",
  "properties": {
    "addr:full":"Dartmouth NS B3B 1W2",
    "addr:postcode":"b3b 1w2",
    "iso:country":"CA",
    "sg:city":"Dartmouth",
    "sg:classifiers":[
        {
            "category":"Professional",
            "subcategory":"Accounting & Tax Preparation",
            "type":"Services"
        }
    ],
    "sg:phone":"+1 902 468 0282",
    "sg:postcode":"B3B 1W2",
    "sg:province":"NS",
    "sg:tags":[
        "accountant"
    ],
    "wof:name":"Chasse, Jean Marc",
    "wof:placetype":"venue"
},
  "geometry": {"coordinates":[-63.580925,44.6996],"type":"Point"}
}