{
  "type": "Feature",
  "properties": {
    "addr:full":"9259 Young Rd Chilliwack BC V2P 4R1",
    "addr:housenumber":"9259",
    "addr:postcode":"v2p 4r1",
    "addr:street":"Young Rd",
    "iso:country":"CA",
    "sg:address":"9259 Young Rd",
    "sg:city":"Chilliwack",
    "sg:classifiers":[
        {
            "category":"Organizations",
            "subcategory":"Religious Organization",
            "type":"Services"
        }
    ],
    "sg:phone":"+1 604 792 0306",
    "sg:postcode":"V2P 4R1",
    "sg:province":"BC",
    "wof:name":"Baha'i Book Store & Info Ctr",
    "wof:placetype":"venue"
},
  "geometry": {"coordinates":[-121.95277400000001,49.170277],"type":"Point"}
}