{
  "type": "Feature",
  "properties": {
    "addr:full":"1805 Cassburn Rd L'Orignal ON K0B 1K0",
    "addr:housenumber":"1805",
    "addr:postcode":"k0b 1k0",
    "addr:street":"Cassburn Rd",
    "iso:country":"CA",
    "sg:address":"1805 Cassburn Rd",
    "sg:city":"L'Orignal",
    "sg:classifiers":[
        {
            "category":"Retail",
            "subcategory":"Auto Repair",
            "type":"Services"
        }
    ],
    "sg:phone":"+1 613 675 2396",
    "sg:postcode":"K0B 1K0",
    "sg:province":"ON",
    "sg:tags":[
        "repairing",
        "automobile"
    ],
    "wof:name":"Purcell's Auto Repair",
    "wof:placetype":"venue"
},
  "geometry": {"coordinates":[-74.691116333,45.6204414368],"type":"Point"}
}