{
  "type": "Feature",
  "properties": {
    "iso:country":"CA",
    "sg:address":"1005 Av Saint-Jean-Baptiste",
    "sg:city":"Quebec",
    "sg:classifiers":[
        {
            "category":"Professional",
            "type":"Services"
        }
    ],
    "sg:phone":"+1 418 871 1466",
    "sg:postcode":"G2E 5L1",
    "sg:province":"QC",
    "sg:tags":[
        "establishment",
        "gas",
        "appliance"
    ],
    "wof:name":"Carmichael Ltee",
    "wof:placetype":"venue"
},
  "geometry": {"coordinates":[-71.327026,46.80022],"type":"Point"}
}