{
  "type": "Feature",
  "properties": {
    "addr:full":"24 Mountjoy Ave Toronto ON M4J 1J6",
    "addr:housenumber":"24",
    "addr:postcode":"m4j 1j6",
    "addr:street":"Mountjoy Ave",
    "iso:country":"CA",
    "sg:address":"24 Mountjoy Ave",
    "sg:city":"Toronto",
    "sg:classifiers":[
        {
            "category":"Education",
            "subcategory":"School",
            "type":"Public Place"
        }
    ],
    "sg:phone":"+1 416 393 0752",
    "sg:postcode":"M4J 1J6",
    "sg:province":"ON",
    "wof:name":"Greenwood Secondary School",
    "wof:placetype":"venue"
},
  "geometry": {"coordinates":[-79.3307189941,43.6804351807],"type":"Point"}
}