{
  "type": "Feature",
  "properties": {
    "iso:country":"CA",
    "sg:address":"366 Rue Mayor",
    "sg:city":"Montreal",
    "sg:classifiers":[
        {
            "category":"Restaurant",
            "type":"Food & Drink"
        }
    ],
    "sg:phone":"+1 514 844 6509",
    "sg:postcode":"H3A 1N8",
    "sg:province":"QC",
    "wof:name":"Restaurant Le Roi",
    "wof:placetype":"venue"
},
  "geometry": {"coordinates":[-73.5684585571,45.5061721802],"type":"Point"}
}