{
  "type": "Feature",
  "properties": {
    "addr:full":"55 Industrial Rd Dauphin MB R7N 2T9",
    "addr:housenumber":"55",
    "addr:postcode":"r7n 2t9",
    "addr:street":"Industrial Rd",
    "iso:country":"CA",
    "sg:address":"55 Industrial Rd",
    "sg:city":"Dauphin",
    "sg:classifiers":[
        {
            "category":"Wholesale",
            "subcategory":"Meat",
            "type":"Manufacturing & Wholesale Goods"
        }
    ],
    "sg:phone":"+1 204 638 6016",
    "sg:postcode":"R7N 2T9",
    "sg:province":"MB",
    "sg:tags":[
        "packer"
    ],
    "wof:name":"Dauphin Meat Processors",
    "wof:placetype":"venue"
},
  "geometry": {"coordinates":[-100.064857483,51.1586456299],"type":"Point"}
}