{
  "type": "Feature",
  "properties": {
    "addr:full":"Courtenay BC V9N 3N6",
    "addr:postcode":"v9n 3n6",
    "iso:country":"CA",
    "sg:city":"Courtenay",
    "sg:classifiers":[
        {
            "category":"Autos & Motor Vehicles",
            "subcategory":"Auto Supplies",
            "type":"Retail Goods"
        }
    ],
    "sg:phone":"+1 250 338 2294",
    "sg:postcode":"V9N 3N6",
    "sg:province":"BC",
    "sg:tags":[
        "tire"
    ],
    "wof:name":"R & B Tire",
    "wof:placetype":"venue"
},
  "geometry": {"coordinates":[-124.99839799999999,49.669537],"type":"Point"}
}