{
  "type": "Feature",
  "properties": {
    "addr:full":"181 W Douglas Vanderhoof BC V0J 3A0",
    "addr:housenumber":"181",
    "addr:postcode":"v0j 3a0",
    "addr:street":"W Douglas",
    "iso:country":"CA",
    "sg:address":"181 W Douglas",
    "sg:city":"Vanderhoof",
    "sg:classifiers":[
        {
            "category":"Organizations",
            "subcategory":"Religious Organization",
            "type":"Services"
        }
    ],
    "sg:phone":"+1 250 567 3802",
    "sg:postcode":"V0J 3A0",
    "sg:province":"BC",
    "sg:tags":[
        "church"
    ],
    "wof:name":"Vanderhoof Lutheran Church",
    "wof:placetype":"venue"
},
  "geometry": {"coordinates":[-124.01264999999999,54.020046],"type":"Point"}
}