{
  "type": "Feature",
  "properties": {
    "iso:country":"CA",
    "sg:address":"229 Welland Ave",
    "sg:city":"St Catharines",
    "sg:classifiers":[
        {
            "category":"Banks & Credit Unions",
            "subcategory":"Bank",
            "type":"Services"
        }
    ],
    "sg:phone":"+1 905 687 8841",
    "sg:postcode":"L2R 2P4",
    "sg:province":"ON",
    "wof:name":"Scotiabank",
    "wof:placetype":"venue"
},
  "geometry": {"coordinates":[-79.23654174799999,43.1672286987],"type":"Point"}
}