{
  "type": "Feature",
  "properties": {
    "addr:full":"6755 Rue D'Avila Saint-Leonard QC H1T 1J3",
    "addr:housenumber":"6755",
    "addr:postcode":"h1t 1j3",
    "addr:street":"Rue D'Avila",
    "iso:country":"CA",
    "sg:address":"6755 Rue D'Avila",
    "sg:city":"Saint-Leonard",
    "sg:classifiers":[
        {
            "category":"Manufacturing",
            "subcategory":"Printing",
            "type":"Manufacturing & Wholesale Goods"
        }
    ],
    "sg:phone":"+1 514 259 0095",
    "sg:postcode":"H1T 1J3",
    "sg:province":"QC",
    "sg:tags":[
        "multimedia"
    ],
    "wof:name":"Accessite Inc",
    "wof:placetype":"venue"
},
  "geometry": {"coordinates":[-73.5953369141,45.589389801],"type":"Point"}
}