{
  "type": "Feature",
  "properties": {
    "addr:full":"11 Laurentian Dr Kitchener ON N2E 1C1",
    "addr:housenumber":"11",
    "addr:postcode":"n2e 1c1",
    "addr:street":"Laurentian Dr",
    "iso:country":"CA",
    "sg:address":"11 Laurentian Dr",
    "sg:city":"Kitchener",
    "sg:classifiers":[
        {
            "category":"Education",
            "subcategory":"School",
            "type":"Public Place"
        }
    ],
    "sg:phone":"+1 519 576 6700",
    "sg:postcode":"N2E 1C1",
    "sg:province":"ON",
    "wof:name":"Laurentian Hills Christian",
    "wof:placetype":"venue"
},
  "geometry": {"coordinates":[-80.500275,43.417114],"type":"Point"}
}