{
  "type": "Feature",
  "properties": {
    "addr:full":"27 Boul DE Lucerne Aylmer QC J9H 1M2",
    "addr:housenumber":"27",
    "addr:postcode":"j9h 1m2",
    "addr:street":"Boul De Lucerne",
    "iso:country":"CA",
    "sg:address":"27 Boul DE Lucerne",
    "sg:city":"Aylmer",
    "sg:classifiers":[
        {
            "category":"Food & Beverages",
            "subcategory":"Groceries & Convenience Stores",
            "type":"Retail Goods"
        }
    ],
    "sg:phone":"+1 819 682 2535",
    "sg:postcode":"J9H 1M2",
    "sg:province":"QC",
    "sg:tags":[
        "grocer"
    ],
    "wof:name":"Depanneur Deschenes",
    "wof:placetype":"venue"
},
  "geometry": {"coordinates":[-75.80397000000001,45.386768],"type":"Point"}
}