{
  "type": "Feature",
  "properties": {
    "addr:full":"36 Mechanic St Paris ON N3L 1K2",
    "addr:housenumber":"36",
    "addr:postcode":"n3l 1k2",
    "addr:street":"Mechanic St",
    "iso:country":"CA",
    "sg:address":"36 Mechanic St",
    "sg:city":"Paris",
    "sg:classifiers":[
        {
            "category":"Health Services",
            "subcategory":"Chiropractor",
            "type":"Services"
        }
    ],
    "sg:phone":"+1 519 442 7100",
    "sg:postcode":"N3L 1K2",
    "sg:province":"ON",
    "wof:name":"Paris Chiropractic Ctr",
    "wof:placetype":"venue"
},
  "geometry": {"coordinates":[-80.385643,43.192089],"type":"Point"}
}