{
  "type": "Feature",
  "properties": {
    "addr:full":"Rocky Mountain House AB T4T 1A4",
    "addr:postcode":"t4t 1a4",
    "iso:country":"CA",
    "sg:city":"Rocky Mountain House",
    "sg:classifiers":[
        {
            "category":"Mining & Drilling",
            "type":"Manufacturing & Wholesale Goods"
        }
    ],
    "sg:phone":"+1 403 845 7115",
    "sg:postcode":"T4T 1A4",
    "sg:province":"AB",
    "sg:tags":[
        "field",
        "oil"
    ],
    "wof:name":"Weatherford Drilling & Inter",
    "wof:placetype":"venue"
},
  "geometry": {"coordinates":[-114.903770447,52.3719100952],"type":"Point"}
}