{
  "type": "Feature",
  "properties": {
    "addr:full":"119 East Dr Brampton ON L6T 1B5",
    "addr:housenumber":"119",
    "addr:postcode":"l6t 1b5",
    "addr:street":"East Dr",
    "iso:country":"CA",
    "sg:address":"119 East Dr",
    "sg:city":"Brampton",
    "sg:classifiers":[
        {
            "category":"Building & Trades",
            "subcategory":"Construction",
            "type":"Services"
        }
    ],
    "sg:phone":"+1 905 791 5011",
    "sg:postcode":"L6T 1B5",
    "sg:province":"ON",
    "sg:tags":[
        "paving",
        "contractor"
    ],
    "wof:name":"Park Lans Paving",
    "wof:placetype":"venue"
},
  "geometry": {"coordinates":[-79.691765,43.709785],"type":"Point"}
}