{
  "type": "Feature",
  "properties": {
    "iso:country":"CA",
    "sg:city":"Saskatoon",
    "sg:classifiers":[
        {
            "category":"Food & Beverages",
            "subcategory":"Meat & Fish",
            "type":"Retail Goods"
        }
    ],
    "sg:phone":"+1 306 477 1959",
    "sg:postcode":"S7H 5M2",
    "sg:province":"SK",
    "wof:name":"Prairie Meats",
    "wof:placetype":"venue"
},
  "geometry": {"coordinates":[-106.59052276600001,52.1149139404],"type":"Point"}
}