{
  "type": "Feature",
  "properties": {
    "addr:full":"671 St. Anne St Bathurst NB E2A 2N5",
    "addr:housenumber":"671",
    "addr:postcode":"e2a 2n5",
    "addr:street":"St. Anne St",
    "iso:country":"CA",
    "sg:address":"671 St. Anne St",
    "sg:city":"Bathurst",
    "sg:classifiers":[
        {
            "category":"Building & Trades",
            "subcategory":"Cleaning & Sanitation",
            "type":"Services"
        }
    ],
    "sg:phone":"+1 506 548 1121",
    "sg:postcode":"E2A 2N5",
    "sg:province":"NB",
    "sg:tags":[
        "fireplace",
        "chimney"
    ],
    "wof:name":"Ramonage Jean Marie Gagnon",
    "wof:placetype":"venue"
},
  "geometry": {"coordinates":[-65.6741638184,47.62733078],"type":"Point"}
}