{
  "type": "Feature",
  "properties": {
    "addr:full":"1280 Boul Saint-Luc L'Acadie QC J2Y 1A5",
    "addr:housenumber":"1280",
    "addr:postcode":"j2y 1a5",
    "addr:street":"Boul Saint-Luc",
    "iso:country":"CA",
    "sg:address":"1280 Boul Saint-Luc",
    "sg:city":"L'Acadie",
    "sg:classifiers":[
        {
            "category":"Restaurant",
            "type":"Food & Drink"
        }
    ],
    "sg:phone":"+1 450 348 7961",
    "sg:postcode":"J2Y 1A5",
    "sg:province":"QC",
    "wof:name":"Frite Dali",
    "wof:placetype":"venue"
},
  "geometry": {"coordinates":[-73.3804092407,45.3804702759],"type":"Point"}
}