{
  "type": "Feature",
  "properties": {
    "addr:full":"Wishart SK S0A 4R0",
    "addr:postcode":"s0a 4r0",
    "iso:country":"CA",
    "sg:city":"Wishart",
    "sg:classifiers":[
        {
            "category":"Autos & Motor Vehicles",
            "subcategory":"Fuel & Gas Station",
            "type":"Retail Goods"
        }
    ],
    "sg:phone":"+1 306 576 2203",
    "sg:postcode":"S0A 4R0",
    "sg:province":"SK",
    "sg:tags":[
        "oil"
    ],
    "wof:name":"Gord's Corner Svc",
    "wof:placetype":"venue"
},
  "geometry": {"coordinates":[-103.977936,51.549568],"type":"Point"}
}