{
  "type": "Feature",
  "properties": {
    "addr:full":"876 Concession Rd Fort Erie ON L2A 6B9",
    "addr:housenumber":"876",
    "addr:postcode":"l2a 6b9",
    "addr:street":"Concession Rd",
    "iso:country":"CA",
    "sg:address":"876 Concession Rd",
    "sg:city":"Fort Erie",
    "sg:classifiers":[
        {
            "category":"Building & Trades",
            "subcategory":"Construction",
            "type":"Services"
        }
    ],
    "sg:phone":"+1 905 871 3051",
    "sg:postcode":"L2A 6B9",
    "sg:province":"ON",
    "sg:tags":[
        "dry wall",
        "contractor"
    ],
    "wof:name":"Da Costa Drywall",
    "wof:placetype":"venue"
},
  "geometry": {"coordinates":[-78.926689,42.900852],"type":"Point"}
}