{
  "type": "Feature",
  "properties": {
    "addr:full":"115 Rue Lartigue Vaudreuil-Dorion QC J7V 6G9",
    "addr:housenumber":"115",
    "addr:postcode":"j7v 6g9",
    "addr:street":"Rue Lartigue",
    "iso:country":"CA",
    "sg:address":"115 Rue Lartigue",
    "sg:city":"Vaudreuil-Dorion",
    "sg:classifiers":[
        {
            "category":"Personal",
            "subcategory":"Beauty Salon",
            "type":"Services"
        }
    ],
    "sg:phone":"+1 450 455 4730",
    "sg:postcode":"J7V 6G9",
    "sg:province":"QC",
    "wof:name":"Salon Pauly D'Or Enrg",
    "wof:placetype":"venue"
},
  "geometry": {"coordinates":[-74.0354003906,45.4049301147],"type":"Point"}
}