{
  "type": "Feature",
  "properties": {
    "addr:full":"Topley BC V0J 2Y0",
    "addr:postcode":"v0j 2y0",
    "iso:country":"CA",
    "sg:city":"Topley",
    "sg:classifiers":[
        {
            "category":"Education",
            "subcategory":"School",
            "type":"Public Place"
        }
    ],
    "sg:phone":"+1 250 696 3641",
    "sg:postcode":"V0J 2Y0",
    "sg:province":"BC",
    "wof:name":"Topley Elementary School",
    "wof:placetype":"venue"
},
  "geometry": {"coordinates":[-126.29946899399999,54.5065231323],"type":"Point"}
}