{
  "type": "Feature",
  "properties": {
    "addr:full":"Edmonton AB T5K 1L3",
    "addr:postcode":"t5k 1l3",
    "iso:country":"CA",
    "sg:city":"Edmonton",
    "sg:classifiers":[
        {
            "category":"Wholesale",
            "subcategory":"Chemicals & Plastics",
            "type":"Manufacturing & Wholesale Goods"
        }
    ],
    "sg:phone":"+1 780 488 6551",
    "sg:postcode":"T5K 1L3",
    "sg:province":"AB",
    "sg:tags":[
        "cleaning",
        "compound"
    ],
    "wof:name":"Amway Products Distributors",
    "wof:placetype":"venue"
},
  "geometry": {"coordinates":[-113.51371,53.535419],"type":"Point"}
}