{
  "type": "Feature",
  "properties": {
    "addr:full":"1000 Bathurst St Toronto ON M5R 3G7",
    "addr:housenumber":"1000",
    "addr:postcode":"m5r 3g7",
    "addr:street":"Bathurst St",
    "iso:country":"CA",
    "sg:address":"1000 Bathurst St",
    "sg:city":"Toronto",
    "sg:classifiers":[
        {
            "category":"Home & Garden",
            "subcategory":"Hardware",
            "type":"Retail Goods"
        }
    ],
    "sg:phone":"+1 416 531 0742",
    "sg:postcode":"M5R 3G7",
    "sg:province":"ON",
    "wof:name":"Spector's Hardware",
    "wof:placetype":"venue"
},
  "geometry": {"coordinates":[-79.413551,43.670631],"type":"Point"}
}