{
  "type": "Feature",
  "properties": {
    "addr:full":"Calgary AB T2G 2R7",
    "addr:postcode":"t2g 2r7",
    "iso:country":"CA",
    "sg:city":"Calgary",
    "sg:classifiers":[
        {
            "category":"Building & Trades",
            "subcategory":"Construction",
            "type":"Services"
        }
    ],
    "sg:phone":"+1 403 256 7708",
    "sg:postcode":"T2G 2R7",
    "sg:province":"AB",
    "sg:tags":[
        "general",
        "contractor"
    ],
    "wof:name":"Nalyd Construction Ltd",
    "wof:placetype":"venue"
},
  "geometry": {"coordinates":[-114.062644959,51.0182151794],"type":"Point"}
}