{
  "type": "Feature",
  "properties": {
    "addr:full":"410 Av Lafleur Lasalle QC H8R 3H6",
    "addr:housenumber":"410",
    "addr:postcode":"h8r 3h6",
    "addr:street":"Av Lafleur",
    "iso:country":"CA",
    "sg:address":"410 Av Lafleur",
    "sg:city":"Lasalle",
    "sg:classifiers":[
        {
            "category":"Professional",
            "subcategory":"Printing & Photocopies",
            "type":"Services"
        }
    ],
    "sg:phone":"+1 514 364 4006",
    "sg:postcode":"H8R 3H6",
    "sg:province":"QC",
    "sg:tags":[
        "duplicating",
        "copying"
    ],
    "wof:name":"Copycentre",
    "wof:placetype":"venue"
},
  "geometry": {"coordinates":[-73.646843,45.431919],"type":"Point"}
}