{
  "type": "Feature",
  "properties": {
    "addr:full":"354 Bonner Ave Winnipeg MB R2G 1B5",
    "addr:housenumber":"354",
    "addr:postcode":"r2g 1b5",
    "addr:street":"Bonner Ave",
    "iso:country":"CA",
    "sg:address":"354 Bonner Ave",
    "sg:city":"Winnipeg",
    "sg:classifiers":[
        {
            "category":"Building & Trades",
            "subcategory":"Construction",
            "type":"Services"
        }
    ],
    "sg:phone":"+1 204 669 1461",
    "sg:postcode":"R2G 1B5",
    "sg:province":"MB",
    "sg:tags":[
        "general",
        "contractor"
    ],
    "wof:name":"Holdnick Enterprises Ltd",
    "wof:placetype":"venue"
},
  "geometry": {"coordinates":[-97.05883,49.951698],"type":"Point"}
}