{
  "type": "Feature",
  "properties": {
    "iso:country":"CA",
    "sg:address":"4 Rue DE Gaspe",
    "sg:city":"Riviere-Du-Loup",
    "sg:classifiers":[
        {
            "category":"Social Services",
            "type":"Services"
        }
    ],
    "sg:phone":"+1 418 862 6622",
    "sg:postcode":"G5R 1A9",
    "sg:province":"QC",
    "sg:tags":[
        "info",
        "drug",
        "abuse",
        "treatment",
        "welfare",
        "organization",
        "addiction"
    ],
    "wof:name":"Unite Domremy-Riviere-Du-Loup",
    "wof:placetype":"venue"
},
  "geometry": {"coordinates":[-69.537468,47.843613],"type":"Point"}
}