{
  "type": "Feature",
  "properties": {
    "iso:country":"CA",
    "sg:address":"566 Main St",
    "sg:city":"Dartmouth",
    "sg:classifiers":[
        {
            "category":"Autos & Motor Vehicles",
            "subcategory":"Fuel & Gas Station",
            "type":"Retail Goods"
        }
    ],
    "sg:phone":"+1 902 435 3535",
    "sg:postcode":"B2W 4J9",
    "sg:province":"NS",
    "sg:tags":[
        "repairing",
        "automobile",
        "oil"
    ],
    "wof:name":"Number 7 Hwy Irving",
    "wof:placetype":"venue"
},
  "geometry": {"coordinates":[-63.501354,44.692871],"type":"Point"}
}