{
  "type": "Feature",
  "properties": {
    "addr:full":"4807 47 Ave Vermilion AB T9X 1J4",
    "addr:housenumber":"4807",
    "addr:postcode":"t9x 1j4",
    "addr:street":"47 Ave",
    "iso:country":"CA",
    "sg:address":"4807 47 Ave",
    "sg:city":"Vermilion",
    "sg:classifiers":[
        {
            "category":"Home & Garden",
            "subcategory":"Building Materials",
            "type":"Retail Goods"
        }
    ],
    "sg:phone":"+1 780 853 4818",
    "sg:postcode":"T9X 1J4",
    "sg:province":"AB",
    "sg:tags":[
        "mixed",
        "concrete"
    ],
    "wof:name":"Vermilion Ready Mix Concrete",
    "wof:placetype":"venue"
},
  "geometry": {"coordinates":[-110.844734,53.348885],"type":"Point"}
}