{
  "type": "Feature",
  "properties": {
    "addr:full":"Ottawa ON K2A 0E8",
    "addr:postcode":"k2a 0e8",
    "iso:country":"CA",
    "sg:city":"Ottawa",
    "sg:classifiers":[
        {
            "category":"Shopping",
            "type":"Retail Goods"
        }
    ],
    "sg:phone":"+1 613 722 9662",
    "sg:postcode":"K2A 0E8",
    "sg:province":"ON",
    "sg:tags":[
        "picture",
        "frame",
        "art",
        "gallery",
        "dealer"
    ],
    "wof:name":"Anne Hayes Studio 2 Framing",
    "wof:placetype":"venue"
},
  "geometry": {"coordinates":[-75.754662,45.391586],"type":"Point"}
}