{
  "type": "Feature",
  "properties": {
    "iso:country":"CA",
    "sg:city":"Napanee",
    "sg:classifiers":[
        {
            "category":"Wholesale",
            "subcategory":"Office Equipment",
            "type":"Manufacturing & Wholesale Goods"
        }
    ],
    "sg:phone":"+1 613 354 3076",
    "sg:postcode":"K7R 1R1",
    "sg:province":"ON",
    "sg:tags":[
        "accounting",
        "bookkeeping",
        "system"
    ],
    "wof:name":"Bill Peeters Accounting Svc",
    "wof:placetype":"venue"
},
  "geometry": {"coordinates":[-76.9501419067,44.2488670349],"type":"Point"}
}