{
  "type": "Feature",
  "properties": {
    "addr:full":"12261 163 St NW Edmonton AB T5V 1P9",
    "addr:housenumber":"12261",
    "addr:postcode":"t5v 1p9",
    "addr:street":"163 St Nw",
    "iso:country":"CA",
    "sg:address":"12261 163 St NW",
    "sg:city":"Edmonton",
    "sg:classifiers":[
        {
            "category":"Building & Trades",
            "subcategory":"Construction",
            "type":"Services"
        }
    ],
    "sg:phone":"+1 780 453 6944",
    "sg:postcode":"T5V 1P9",
    "sg:province":"AB",
    "sg:tags":[
        "general",
        "contractor"
    ],
    "wof:name":"Cormode & Dickson Construction",
    "wof:placetype":"venue"
},
  "geometry": {"coordinates":[-113.602524,53.575161],"type":"Point"}
}