{
  "type": "Feature",
  "properties": {
    "addr:full":"3960 Boulter Rd Boulter ON K0L 1G0",
    "addr:housenumber":"3960",
    "addr:postcode":"k0l 1g0",
    "addr:street":"Boulter Rd",
    "iso:country":"CA",
    "sg:address":"3960 Boulter Rd",
    "sg:city":"Boulter",
    "sg:classifiers":[
        {
            "category":"Food & Beverages",
            "subcategory":"Groceries & Convenience Stores",
            "type":"Retail Goods"
        }
    ],
    "sg:phone":"+1 613 332 2708",
    "sg:postcode":"K0L 1G0",
    "sg:province":"ON",
    "sg:tags":[
        "merchandise",
        "general"
    ],
    "wof:name":"Boulter General Store",
    "wof:placetype":"venue"
},
  "geometry": {"coordinates":[-77.63774100000001,45.21373],"type":"Point"}
}