{
  "type": "Feature",
  "properties": {
    "addr:full":"357 Rue Tessier Rimouski QC G5L 4K8",
    "addr:housenumber":"357",
    "addr:postcode":"g5l 4k8",
    "addr:street":"Rue Tessier",
    "iso:country":"CA",
    "sg:address":"357 Rue Tessier",
    "sg:city":"Rimouski",
    "sg:classifiers":[
        {
            "category":"Professional",
            "subcategory":"Computer Services",
            "type":"Services"
        }
    ],
    "sg:phone":"+1 418 724 2349",
    "sg:postcode":"G5L 4K8",
    "sg:province":"QC",
    "sg:tags":[
        "information",
        "system",
        "consultant"
    ],
    "wof:name":"Ecole Info-Matic Yvon Levesque",
    "wof:placetype":"venue"
},
  "geometry": {"coordinates":[-68.53420257569999,48.4383201599],"type":"Point"}
}