{
  "type": "Feature",
  "properties": {
    "addr:full":"164 Rue Commerciale Saint-Damien-DE-Buckland QC G0R 2Y0",
    "addr:housenumber":"164",
    "addr:postcode":"g0r 2y0",
    "addr:street":"Rue Commerciale",
    "iso:country":"CA",
    "sg:address":"164 Rue Commerciale",
    "sg:city":"Saint-Damien-DE-Buckland",
    "sg:classifiers":[
        {
            "category":"Health Services",
            "subcategory":"Hospital",
            "type":"Services"
        }
    ],
    "sg:phone":"+1 418 789 2262",
    "sg:postcode":"G0R 2Y0",
    "sg:province":"QC",
    "sg:tags":[
        "mental"
    ],
    "wof:name":"Pavillon Deblois Enr",
    "wof:placetype":"venue"
},
  "geometry": {"coordinates":[-70.65832519529999,46.6247711182],"type":"Point"}
}