{
  "type": "Feature",
  "properties": {
    "addr:full":"801 Selkirk Ave Winnipeg MB R2W 2N5",
    "addr:housenumber":"801",
    "addr:postcode":"r2w 2n5",
    "addr:street":"Selkirk Ave",
    "iso:country":"CA",
    "sg:address":"801 Selkirk Ave",
    "sg:city":"Winnipeg",
    "sg:classifiers":[
        {
            "category":"Shopping",
            "subcategory":"Pharmacy",
            "type":"Retail Goods"
        }
    ],
    "sg:phone":"+1 204 586 2212",
    "sg:postcode":"R2W 2N5",
    "sg:province":"MB",
    "wof:name":"Empire Drugs Ltd",
    "wof:placetype":"venue"
},
  "geometry": {"coordinates":[-97.1560974121,49.9193878174],"type":"Point"}
}