{
  "type": "Feature",
  "properties": {
    "addr:full":"15 High Ridge Cres Sherwood Park AB T8A 5E7",
    "addr:housenumber":"15",
    "addr:postcode":"t8a 5e7",
    "addr:street":"High Ridge Cres",
    "iso:country":"CA",
    "sg:address":"15 High Ridge Cres",
    "sg:city":"Sherwood Park",
    "sg:classifiers":[
        {
            "category":"Shopping",
            "type":"Retail Goods"
        }
    ],
    "sg:phone":"+1 780 464 2333",
    "sg:postcode":"T8A 5E7",
    "sg:province":"AB",
    "sg:tags":[
        "cosmetic",
        "perfume"
    ],
    "wof:name":"Mary Kay Cosmetics",
    "wof:placetype":"venue"
},
  "geometry": {"coordinates":[-113.251991272,53.5392723083],"type":"Point"}
}