{
  "type": "Feature",
  "properties": {
    "iso:country":"CA",
    "sg:address":"5040 50 St # A",
    "sg:city":"Rocky Mountain House",
    "sg:classifiers":[
        {
            "category":"Health Services",
            "subcategory":"Doctor",
            "type":"Services"
        }
    ],
    "sg:phone":"+1 403 845 7868",
    "sg:postcode":"T4T 1B4",
    "sg:province":"AB",
    "sg:tags":[
        "dentist"
    ],
    "wof:name":"Mountain View Dental Ctr",
    "wof:placetype":"venue"
},
  "geometry": {"coordinates":[-114.919555664,52.3750495911],"type":"Point"}
}