{
  "type": "Feature",
  "properties": {
    "addr:full":"922 Scott St Fort Frances ON P9A 1J4",
    "addr:housenumber":"922",
    "addr:postcode":"p9a 1j4",
    "addr:street":"Scott St",
    "iso:country":"CA",
    "sg:address":"922 Scott St",
    "sg:city":"Fort Frances",
    "sg:classifiers":[
        {
            "category":"Government",
            "subcategory":"Office",
            "type":"Public Place"
        }
    ],
    "sg:phone":"+1 807 274 5320",
    "sg:postcode":"P9A 1J4",
    "sg:province":"ON",
    "wof:name":"Ontario Northern Devel Offices",
    "wof:placetype":"venue"
},
  "geometry": {"coordinates":[-93.379036,48.610172],"type":"Point"}
}