{
  "type": "Feature",
  "properties": {
    "addr:full":"5585 1E Av Charlesbourg QC G1H 2V8",
    "addr:housenumber":"5585",
    "addr:postcode":"g1h 2v8",
    "addr:street":"1E Av",
    "iso:country":"CA",
    "sg:address":"5585 1E Av",
    "sg:city":"Charlesbourg",
    "sg:classifiers":[
        {
            "category":"Food & Beverages",
            "subcategory":"Specialty",
            "type":"Retail Goods"
        }
    ],
    "sg:phone":"+1 418 622 6971",
    "sg:postcode":"G1H 2V8",
    "sg:province":"QC",
    "sg:tags":[
        "water",
        "cooler",
        "bulk",
        "fountain",
        "filter"
    ],
    "wof:name":"Location Frig'Eau",
    "wof:placetype":"venue"
},
  "geometry": {"coordinates":[-71.256149292,46.8496742249],"type":"Point"}
}