{
  "type": "Feature",
  "properties": {
    "addr:full":"2666 Rue Masson Montreal QC H1Y 1W2",
    "addr:housenumber":"2666",
    "addr:postcode":"h1y 1w2",
    "addr:street":"Rue Masson",
    "iso:country":"CA",
    "sg:address":"2666 Rue Masson",
    "sg:city":"Montreal",
    "sg:classifiers":[
        {
            "category":"Restaurant",
            "type":"Food & Drink"
        }
    ],
    "sg:phone":"+1 514 526 2666",
    "sg:postcode":"H1Y 1W2",
    "sg:province":"QC",
    "wof:name":"Masson Hot Dog Enr",
    "wof:placetype":"venue"
},
  "geometry": {"coordinates":[-73.575874,45.546043],"type":"Point"}
}