{
  "type": "Feature",
  "properties": {
    "iso:country":"CA",
    "sg:address":"Centennial Park",
    "sg:city":"Courtright",
    "sg:classifiers":[
        {
            "category":"Organizations",
            "subcategory":"Professional Association",
            "type":"Services"
        }
    ],
    "sg:phone":"+1 519 867 3553",
    "sg:postcode":"N0N 1H0",
    "sg:province":"ON",
    "sg:tags":[
        "club"
    ],
    "wof:name":"Courtright Minor Athletic Assn",
    "wof:placetype":"venue"
},
  "geometry": {"coordinates":[-82.4742279053,42.8188858032],"type":"Point"}
}