{
  "type": "Feature",
  "properties": {
    "addr:full":"Saddle Lake AB T0A 3T0",
    "addr:postcode":"t0a 3t0",
    "iso:country":"CA",
    "sg:city":"Saddle Lake",
    "sg:classifiers":[
        {
            "category":"Health Services",
            "subcategory":"Doctor",
            "type":"Services"
        }
    ],
    "sg:phone":"+1 780 726 3930",
    "sg:postcode":"T0A 3T0",
    "sg:province":"AB",
    "sg:tags":[
        "clinic"
    ],
    "wof:name":"Saddle Lake Health Ctr",
    "wof:placetype":"venue"
},
  "geometry": {"coordinates":[-111.69999694800001,54.0029144287],"type":"Point"}
}