{
  "type": "Feature",
  "properties": {
    "addr:full":"8203 Hwy 6 Salmo BC V0G 1Z0",
    "addr:housenumber":"8203",
    "addr:postcode":"v0g 1z0",
    "addr:street":"Hwy 6",
    "iso:country":"CA",
    "sg:address":"8203 Hwy 6",
    "sg:city":"Salmo",
    "sg:classifiers":[
        {
            "category":"Home & Garden",
            "subcategory":"Building Materials",
            "type":"Retail Goods"
        }
    ],
    "sg:phone":"+1 250 357 2433",
    "sg:postcode":"V0G 1Z0",
    "sg:province":"BC",
    "wof:name":"Rae-Mark Veneers",
    "wof:placetype":"venue"
},
  "geometry": {"coordinates":[-117.279037,49.195312],"type":"Point"}
}