{
  "type": "Feature",
  "properties": {
    "addr:full":"5 Scenic View St Island View NB E3E 1A1",
    "addr:housenumber":"5",
    "addr:postcode":"e3e 1a1",
    "addr:street":"Scenic View St",
    "iso:country":"CA",
    "sg:address":"5 Scenic View St",
    "sg:city":"Island View",
    "sg:classifiers":[
        {
            "category":"Building & Trades",
            "subcategory":"Electrical",
            "type":"Services"
        }
    ],
    "sg:phone":"+1 506 450 1289",
    "sg:postcode":"E3E 1A1",
    "sg:province":"NB",
    "sg:tags":[
        "electric",
        "contractor"
    ],
    "wof:name":"Stairs Electric Inc",
    "wof:placetype":"venue"
},
  "geometry": {"coordinates":[-66.8127746582,45.9640159607],"type":"Point"}
}