{
  "type": "Feature",
  "properties": {
    "addr:full":"95 Church St St Catharines ON L2R 3C7",
    "addr:housenumber":"95",
    "addr:postcode":"l2r 3c7",
    "addr:street":"Church St",
    "iso:country":"CA",
    "sg:address":"95 Church St",
    "sg:city":"St Catharines",
    "sg:classifiers":[
        {
            "category":"Organizations",
            "subcategory":"Religious Organization",
            "type":"Services"
        }
    ],
    "sg:phone":"+1 905 684 8309",
    "sg:postcode":"L2R 3C7",
    "sg:province":"ON",
    "sg:tags":[
        "church"
    ],
    "wof:name":"First United Church",
    "wof:placetype":"venue"
},
  "geometry": {"coordinates":[-79.24537658689999,43.1619338989],"type":"Point"}
}