{
  "type": "Feature",
  "properties": {
    "addr:full":"940 Boul Du Seminaire N Saint-Jean-Sur-Richelieu QC J3A 1L2",
    "addr:housenumber":"940",
    "addr:postcode":"j3a 1l2",
    "addr:street":"Boul Du Seminaire N",
    "iso:country":"CA",
    "sg:address":"940 Boul Du Seminaire N",
    "sg:city":"Saint-Jean-Sur-Richelieu",
    "sg:classifiers":[
        {
            "category":"Food & Beverages",
            "subcategory":"Groceries & Convenience Stores",
            "type":"Retail Goods"
        }
    ],
    "sg:phone":"+1 450 348 9171",
    "sg:postcode":"J3A 1L2",
    "sg:province":"QC",
    "wof:name":"Couche-Tard",
    "wof:placetype":"venue"
},
  "geometry": {"coordinates":[-73.268196,45.334129],"type":"Point"}
}