{
  "type": "Feature",
  "properties": {
    "iso:country":"CA",
    "sg:city":"Mississauga",
    "sg:classifiers":[
        {
            "category":"Building & Trades",
            "subcategory":"Construction",
            "type":"Services"
        }
    ],
    "sg:phone":"+1 905 564 7510",
    "sg:postcode":"L5T 2S8",
    "sg:province":"ON",
    "sg:tags":[
        "product",
        "ceramic",
        "dealer"
    ],
    "wof:name":"Ptx Group Inc",
    "wof:placetype":"venue"
},
  "geometry": {"coordinates":[-79.673248,43.639626],"type":"Point"}
}