{
  "type": "Feature",
  "properties": {
    "addr:full":"4401 University Dr W Lethbridge AB T1K 3M4",
    "addr:housenumber":"4401",
    "addr:postcode":"t1k 3m4",
    "addr:street":"University Dr W",
    "iso:country":"CA",
    "sg:address":"4401 University Dr W",
    "sg:city":"Lethbridge",
    "sg:classifiers":[
        {
            "category":"Restaurant",
            "type":"Food & Drink"
        }
    ],
    "sg:phone":"+1 403 320 2877",
    "sg:postcode":"T1K 3M4",
    "sg:province":"AB",
    "wof:name":"Hiroba",
    "wof:placetype":"venue"
},
  "geometry": {"coordinates":[-112.868088,49.674995],"type":"Point"}
}