{
  "type": "Feature",
  "properties": {
    "iso:country":"CA",
    "sg:address":"687 Niagara St",
    "sg:city":"Welland",
    "sg:classifiers":[
        {
            "category":"Home & Garden",
            "subcategory":"Household Appliances",
            "type":"Retail Goods"
        }
    ],
    "sg:phone":"+1 905 734 9212",
    "sg:postcode":"L3C 1M2",
    "sg:province":"ON",
    "sg:tags":[
        "cleaners",
        "vacuum"
    ],
    "wof:name":"Bertrand Vacuum Cleaners Sls",
    "wof:placetype":"venue"
},
  "geometry": {"coordinates":[-79.2500076294,43.011806488],"type":"Point"}
}