{
  "type": "Feature",
  "properties": {
    "addr:full":"326 Highway 77 Leamington ON N8H 3V5",
    "addr:housenumber":"326",
    "addr:postcode":"n8h 3v5",
    "addr:street":"Highway 77",
    "iso:country":"CA",
    "sg:address":"326 Highway 77",
    "sg:city":"Leamington",
    "sg:classifiers":[
        {
            "category":"Manufacturing",
            "subcategory":"Metals",
            "type":"Manufacturing & Wholesale Goods"
        }
    ],
    "sg:phone":"+1 519 326 8157",
    "sg:postcode":"N8H 3V5",
    "sg:province":"ON",
    "sg:tags":[
        "foundry"
    ],
    "wof:name":"Leamington Ornamental Iron",
    "wof:placetype":"venue"
},
  "geometry": {"coordinates":[-82.599716,42.054153],"type":"Point"}
}