{
  "type": "Feature",
  "properties": {
    "addr:full":"153 Elm Ave New Liskeard ON P0J 1P0",
    "addr:housenumber":"153",
    "addr:postcode":"p0j 1p0",
    "addr:street":"Elm Ave",
    "iso:country":"CA",
    "sg:address":"153 Elm Ave",
    "sg:city":"New Liskeard",
    "sg:classifiers":[
        {
            "category":"Professional",
            "subcategory":"Art Services",
            "type":"Services"
        }
    ],
    "sg:phone":"+1 705 647 6904",
    "sg:postcode":"P0J 1P0",
    "sg:province":"ON",
    "sg:tags":[
        "website",
        "graphic",
        "design",
        "advertising",
        "designer"
    ],
    "wof:name":"Cameron Graphics",
    "wof:placetype":"venue"
},
  "geometry": {"coordinates":[-79.66748046879999,47.5133743286],"type":"Point"}
}