{
  "type": "Feature",
  "properties": {
    "iso:country":"CA",
    "sg:address":"130 Wellington St E",
    "sg:city":"Sault Ste Marie",
    "sg:classifiers":[
        {
            "category":"Education",
            "subcategory":"School",
            "type":"Public Place"
        }
    ],
    "sg:phone":"+1 705 945 5540",
    "sg:postcode":"P6A 2L5",
    "sg:province":"ON",
    "wof:name":"St Mary's College",
    "wof:placetype":"venue"
},
  "geometry": {"coordinates":[-84.3356552124,46.5174674988],"type":"Point"}
}