{
  "type": "Feature",
  "properties": {
    "iso:country":"CA",
    "sg:address":"358 Rue Saint-Jacques",
    "sg:city":"Lachine",
    "sg:classifiers":[
        {
            "category":"Personal",
            "subcategory":"Massage",
            "type":"Services"
        }
    ],
    "sg:phone":"+1 514 364 5550",
    "sg:postcode":"H8R 1E2",
    "sg:province":"QC",
    "sg:tags":[
        "salon",
        "beauty"
    ],
    "wof:name":"Ambiance Salon & Spa",
    "wof:placetype":"venue"
},
  "geometry": {"coordinates":[-73.647942,45.443684],"type":"Point"}
}