{
  "type": "Feature",
  "properties": {
    "addr:full":"3872 Carey Rd Victoria BC V8Z 4C7",
    "addr:housenumber":"3872",
    "addr:postcode":"v8z 4c7",
    "addr:street":"Carey Rd",
    "iso:country":"CA",
    "sg:address":"3872 Carey Rd",
    "sg:city":"Victoria",
    "sg:classifiers":[
        {
            "category":"Building & Trades",
            "subcategory":"Plumbing",
            "type":"Services"
        }
    ],
    "sg:phone":"+1 250 812 1173",
    "sg:postcode":"V8Z 4C7",
    "sg:province":"BC",
    "sg:tags":[
        "system",
        "heat",
        "air",
        "pump",
        "conditioning",
        "contractor"
    ],
    "wof:name":"Triple C Air Conditioning",
    "wof:placetype":"venue"
},
  "geometry": {"coordinates":[-123.364517212,48.428314209],"type":"Point"}
}