{
  "type": "Feature",
  "properties": {
    "addr:full":"5th Ave Scott SK S0K 4A0",
    "addr:postcode":"s0k 4a0",
    "addr:street":"5Th Ave",
    "iso:country":"CA",
    "sg:address":"5th Ave",
    "sg:city":"Scott",
    "sg:classifiers":[
        {
            "category":"Recreation",
            "type":"Entertainment"
        }
    ],
    "sg:phone":"+1 306 247 2102",
    "sg:postcode":"S0K 4A0",
    "sg:province":"SK",
    "sg:tags":[
        "club",
        "curling"
    ],
    "wof:name":"Scott Curling Rink",
    "wof:placetype":"venue"
},
  "geometry": {"coordinates":[-108.833763123,52.3649559021],"type":"Point"}
}