{
  "type": "Feature",
  "properties": {
    "addr:full":"2015 Lawrence Ave E Scarborough ON M1R 5H2",
    "addr:housenumber":"2015",
    "addr:postcode":"m1r 5h2",
    "addr:street":"Lawrence Ave E",
    "iso:country":"CA",
    "sg:address":"2015 Lawrence Ave E",
    "sg:city":"Scarborough",
    "sg:classifiers":[
        {
            "category":"Real Estate",
            "subcategory":"Real Estate Operator",
            "type":"Services"
        }
    ],
    "sg:phone":"+1 416 759 4143",
    "sg:postcode":"M1R 5H2",
    "sg:province":"ON",
    "sg:tags":[
        "apartment"
    ],
    "wof:name":"Grace Communities Corp",
    "wof:placetype":"venue"
},
  "geometry": {"coordinates":[-79.29496,43.745193],"type":"Point"}
}