{
  "type": "Feature",
  "properties": {
    "addr:full":"1 Irwin Ave Toronto ON M4Y 1L1",
    "addr:housenumber":"1",
    "addr:postcode":"m4y 1l1",
    "addr:street":"Irwin Ave",
    "iso:country":"CA",
    "sg:address":"1 Irwin Ave",
    "sg:city":"Toronto",
    "sg:classifiers":[
        {
            "category":"Personal",
            "type":"Services"
        }
    ],
    "sg:phone":"+1 416 921 2639",
    "sg:postcode":"M4Y 1L1",
    "sg:province":"ON",
    "sg:tags":[
        "control",
        "weight",
        "program",
        "fitness",
        "exercise",
        "physical"
    ],
    "wof:name":"Onebody Fitness",
    "wof:placetype":"venue"
},
  "geometry": {"coordinates":[-79.38539123539999,43.6665878296],"type":"Point"}
}