{
  "type": "Feature",
  "properties": {
    "addr:full":"14 Quinpool Cres Nepean ON K2H 6J1",
    "addr:housenumber":"14",
    "addr:postcode":"k2h 6j1",
    "addr:street":"Quinpool Cres",
    "iso:country":"CA",
    "sg:address":"14 Quinpool Cres",
    "sg:city":"Nepean",
    "sg:classifiers":[
        {
            "category":"Professional",
            "subcategory":"Management & Consulting",
            "type":"Services"
        }
    ],
    "sg:phone":"+1 613 721 2949",
    "sg:postcode":"K2H 6J1",
    "sg:province":"ON",
    "sg:tags":[
        "construction"
    ],
    "wof:name":"J M Almond Construction",
    "wof:placetype":"venue"
},
  "geometry": {"coordinates":[-75.824654,45.318066],"type":"Point"}
}