{
  "type": "Feature",
  "properties": {
    "addr:full":"59 Valecrest Dr Etobicoke ON M9A 4P5",
    "addr:housenumber":"59",
    "addr:postcode":"m9a 4p5",
    "addr:street":"Valecrest Dr",
    "iso:country":"CA",
    "sg:address":"59 Valecrest Dr",
    "sg:city":"Etobicoke",
    "sg:classifiers":[
        {
            "category":"Shopping",
            "subcategory":"Computers & Home Electronics",
            "type":"Retail Goods"
        }
    ],
    "sg:phone":"+1 416 236 4598",
    "sg:postcode":"M9A 4P5",
    "sg:province":"ON",
    "sg:tags":[
        "software"
    ],
    "wof:name":"Biznix Software Inc",
    "wof:placetype":"venue"
},
  "geometry": {"coordinates":[-79.517982,43.674393],"type":"Point"}
}