{
  "type": "Feature",
  "properties": {
    "iso:country":"CA",
    "sg:address":"283 Greenwood Rd",
    "sg:city":"Callander",
    "sg:classifiers":[
        {
            "category":"Organizations",
            "subcategory":"Professional Association",
            "type":"Services"
        }
    ],
    "sg:phone":"+1 705 752 5780",
    "sg:postcode":"P0H 1H0",
    "sg:province":"ON",
    "sg:tags":[
        "club"
    ],
    "wof:name":"North Bay Yacht Club",
    "wof:placetype":"venue"
},
  "geometry": {"coordinates":[-79.36600494379999,46.2080917358],"type":"Point"}
}