{
  "type": "Feature",
  "properties": {
    "iso:country":"CA",
    "sg:address":"4916 54 St",
    "sg:city":"Stettler",
    "sg:classifiers":[
        {
            "category":"Organizations",
            "subcategory":"Religious Organization",
            "type":"Services"
        }
    ],
    "sg:phone":"+1 403 742 2047",
    "sg:postcode":"T0C 2L2",
    "sg:province":"AB",
    "sg:tags":[
        "church"
    ],
    "wof:name":"Catholic Church",
    "wof:placetype":"venue"
},
  "geometry": {"coordinates":[-112.711303711,52.3246498108],"type":"Point"}
}