{
  "type": "Feature",
  "properties": {
    "addr:full":"1760 Boul Des Laurentides Laval QC H7M 2Y4",
    "addr:housenumber":"1760",
    "addr:postcode":"h7m 2y4",
    "addr:street":"Boul Des Laurentides",
    "iso:country":"CA",
    "sg:address":"1760 Boul Des Laurentides",
    "sg:city":"Laval",
    "sg:classifiers":[
        {
            "category":"Restaurant",
            "type":"Food & Drink"
        }
    ],
    "sg:phone":"+1 450 663 6112",
    "sg:postcode":"H7M 2Y4",
    "sg:province":"QC",
    "wof:name":"Restaurant Buffet LA Stanza",
    "wof:placetype":"venue"
},
  "geometry": {"coordinates":[-73.70715332029999,45.5829582214],"type":"Point"}
}