{
  "type": "Feature",
  "properties": {
    "iso:country":"CA",
    "sg:address":"520 17 Ave SW",
    "sg:city":"Calgary",
    "sg:classifiers":[
        {
            "category":"Restaurant",
            "type":"Food & Drink"
        }
    ],
    "sg:phone":"+1 403 229 1986",
    "sg:postcode":"T2S 0B1",
    "sg:province":"AB",
    "wof:name":"Ming",
    "wof:placetype":"venue"
},
  "geometry": {"coordinates":[-114.07221221899999,51.0379562378],"type":"Point"}
}