{
  "type": "Feature",
  "properties": {
    "addr:full":"5059 Av Du Parc Montreal QC H2V 4E9",
    "addr:housenumber":"5059",
    "addr:postcode":"h2v 4e9",
    "addr:street":"Av Du Parc",
    "iso:country":"CA",
    "sg:address":"5059 Av Du Parc",
    "sg:city":"Montreal",
    "sg:classifiers":[
        {
            "category":"Banks & Credit Unions",
            "subcategory":"Bank",
            "type":"Services"
        }
    ],
    "sg:phone":"+1 514 522 1846",
    "sg:postcode":"H2V 4E9",
    "sg:province":"QC",
    "wof:name":"Banque Laurentienne Du Canada",
    "wof:placetype":"venue"
},
  "geometry": {"coordinates":[-73.5952377319,45.5195655823],"type":"Point"}
}