{
  "type": "Feature",
  "properties": {
    "addr:full":"30 Grande Allee O Quebec QC G1R 2G6",
    "addr:housenumber":"30",
    "addr:postcode":"g1r 2g6",
    "addr:street":"Grande Allee O",
    "iso:country":"CA",
    "sg:address":"30 Grande Allee O",
    "sg:city":"Quebec",
    "sg:classifiers":[
        {
            "category":"Health Services",
            "subcategory":"Doctor",
            "type":"Services"
        }
    ],
    "sg:phone":"+1 418 527 6468",
    "sg:postcode":"G1R 2G6",
    "sg:province":"QC",
    "sg:tags":[
        "dentist"
    ],
    "wof:name":"Centres Lapointe",
    "wof:placetype":"venue"
},
  "geometry": {"coordinates":[-71.222656,46.802979],"type":"Point"}
}