{
  "type": "Feature",
  "properties": {
    "addr:full":"1 Honeywell Crt Hamilton ON L8E 3H8",
    "addr:housenumber":"1",
    "addr:postcode":"l8e 3h8",
    "addr:street":"Honeywell Crt",
    "iso:country":"CA",
    "sg:address":"1 Honeywell Crt",
    "sg:city":"Hamilton",
    "sg:classifiers":[
        {
            "category":"Real Estate",
            "subcategory":"Real Estate Agent",
            "type":"Services"
        }
    ],
    "sg:phone":"+1 905 578 1138",
    "sg:postcode":"L8E 3H8",
    "sg:province":"ON",
    "wof:name":"B Dowling Real Estate Ltd",
    "wof:placetype":"venue"
},
  "geometry": {"coordinates":[-79.74945831300001,43.230758667],"type":"Point"}
}