{
  "type": "Feature",
  "properties": {
    "addr:full":"1159 Rue Cote Thetford Mines QC G6G 7B7",
    "addr:housenumber":"1159",
    "addr:postcode":"g6g 7b7",
    "addr:street":"Rue Cote",
    "iso:country":"CA",
    "sg:address":"1159 Rue Cote",
    "sg:city":"Thetford Mines",
    "sg:classifiers":[
        {
            "category":"Retail",
            "subcategory":"Animal Services",
            "type":"Services"
        }
    ],
    "sg:phone":"+1 418 338 6767",
    "sg:postcode":"G6G 7B7",
    "sg:province":"QC",
    "sg:tags":[
        "pet",
        "grooming",
        "washing"
    ],
    "wof:name":"A Tout Poli Enr",
    "wof:placetype":"venue"
},
  "geometry": {"coordinates":[-71.2978668213,46.1159515381],"type":"Point"}
}