{
  "type": "Feature",
  "properties": {
    "addr:full":"435 Rue Principale Saint-Donat-DE-Montcalm QC J0T 2C0",
    "addr:housenumber":"435",
    "addr:postcode":"j0t 2c0",
    "addr:street":"Rue Principale",
    "iso:country":"CA",
    "sg:address":"435 Rue Principale",
    "sg:city":"Saint-Donat-DE-Montcalm",
    "sg:classifiers":[
        {
            "category":"Home & Garden",
            "subcategory":"Furniture",
            "type":"Retail Goods"
        }
    ],
    "sg:phone":"+1 819 424 2133",
    "sg:postcode":"J0T 2C0",
    "sg:province":"QC",
    "wof:name":"Barbeau & Garceau Ameublements",
    "wof:placetype":"venue"
},
  "geometry": {"coordinates":[-74.222244,46.31908],"type":"Point"}
}