{
  "type": "Feature",
  "properties": {
    "addr:full":"Beauceville QC G5X 3N4",
    "addr:postcode":"g5x 3n4",
    "iso:country":"CA",
    "sg:city":"Beauceville",
    "sg:classifiers":[
        {
            "category":"Manufacturing",
            "subcategory":"Lumber",
            "type":"Manufacturing & Wholesale Goods"
        }
    ],
    "sg:phone":"+1 418 774 3382",
    "sg:postcode":"G5X 3N4",
    "sg:province":"QC",
    "wof:name":"Rene Bernard Inc",
    "wof:placetype":"venue"
},
  "geometry": {"coordinates":[-70.8151397705,46.2372436523],"type":"Point"}
}