{
  "type": "Feature",
  "properties": {
    "addr:full":"7228 Boul Sainte-Anne E Chateau-Richer QC G0A 1N0",
    "addr:housenumber":"7228",
    "addr:postcode":"g0a 1n0",
    "addr:street":"Boul Sainte-Anne E Chateau-Richer",
    "iso:country":"CA",
    "sg:address":"7228 Boul Sainte-Anne E",
    "sg:city":"Chateau-Richer",
    "sg:classifiers":[
        {
            "category":"Professional",
            "subcategory":"Secretarial Services",
            "type":"Services"
        }
    ],
    "sg:phone":"+1 418 570 1238",
    "sg:postcode":"G0A 1N0",
    "sg:province":"QC",
    "sg:tags":[
        "resume"
    ],
    "wof:name":"Bureautique Trempe",
    "wof:placetype":"venue"
},
  "geometry": {"coordinates":[-71.050926,46.943272],"type":"Point"}
}