{
  "type": "Feature",
  "properties": {
    "addr:full":"8635 Boul Saint-Laurent Montreal QC H2P 2M9",
    "addr:housenumber":"8635",
    "addr:postcode":"h2p 2m9",
    "addr:street":"Boul Saint-Laurent",
    "iso:country":"CA",
    "sg:address":"8635 Boul Saint-Laurent",
    "sg:city":"Montreal",
    "sg:classifiers":[
        {
            "category":"Professional",
            "subcategory":"Business Services",
            "type":"Services"
        }
    ],
    "sg:phone":"+1 514 382 4037",
    "sg:postcode":"H2P 2M9",
    "sg:province":"QC",
    "sg:tags":[
        "notary"
    ],
    "wof:name":"Fontaine, Claude",
    "wof:placetype":"venue"
},
  "geometry": {"coordinates":[-73.639595,45.541508],"type":"Point"}
}