{
  "type": "Feature",
  "properties": {
    "iso:country":"CA",
    "sg:address":"430 King St # 101",
    "sg:city":"London",
    "sg:classifiers":[
        {
            "category":"Real Estate",
            "subcategory":"Real Estate Agent",
            "type":"Services"
        }
    ],
    "sg:phone":"+1 519 672 5633",
    "sg:postcode":"N6B 1S7",
    "sg:province":"ON",
    "sg:tags":[
        "management"
    ],
    "wof:name":"Ed Perl Holdings Ltd",
    "wof:placetype":"venue"
},
  "geometry": {"coordinates":[-81.2381439209,42.9856834412],"type":"Point"}
}