{
  "type": "Feature",
  "properties": {
    "addr:full":"4874 Ch DE LA Cote-Des-Neiges Montreal QC H3V 1H4",
    "addr:postcode":"4874;h3v 1h4",
    "addr:street":"Ch De La Cote-Des-Neiges",
    "iso:country":"CA",
    "sg:address":"4874 Ch DE LA Cote-Des-Neiges",
    "sg:city":"Montreal",
    "sg:classifiers":[
        {
            "category":"Personal",
            "subcategory":"Beauty Salon",
            "type":"Services"
        }
    ],
    "sg:phone":"+1 514 737 5869",
    "sg:postcode":"H3V 1H4",
    "sg:province":"QC",
    "wof:name":"Lina Mc Donald Esthetique",
    "wof:placetype":"venue"
},
  "geometry": {"coordinates":[-73.614548,45.495186],"type":"Point"}
}