{
  "type": "Feature",
  "properties": {
    "iso:country":"CA",
    "sg:address":"480 Cassells St",
    "sg:city":"North Bay",
    "sg:classifiers":[
        {
            "category":"Shopping",
            "subcategory":"Stationery & Office Supplies",
            "type":"Retail Goods"
        }
    ],
    "sg:phone":"+1 705 476 1000",
    "sg:postcode":"P1B 3Z5",
    "sg:province":"ON",
    "wof:name":"Grand & Toy",
    "wof:placetype":"venue"
},
  "geometry": {"coordinates":[-79.4648284912,46.3143348694],"type":"Point"}
}