{
  "type": "Feature",
  "properties": {
    "iso:country":"CA",
    "sg:address":"2786 Barnet Hwy",
    "sg:city":"Coquitlam",
    "sg:classifiers":[
        {
            "category":"Shopping",
            "type":"Retail Goods"
        }
    ],
    "sg:phone":"+1 604 941 1040",
    "sg:postcode":"V3B 1B9",
    "sg:province":"BC",
    "sg:tags":[
        "miscellaneous",
        "store"
    ],
    "wof:name":"X-Citement Video",
    "wof:placetype":"venue"
},
  "geometry": {"coordinates":[-122.80393219,49.2773933411],"type":"Point"}
}