{
  "type": "Feature",
  "properties": {
    "addr:full":"Markham ON L3R 1G7",
    "addr:postcode":"l3r 1g7",
    "iso:country":"CA",
    "sg:city":"Markham",
    "sg:classifiers":[
        {
            "category":"Wholesale",
            "subcategory":"Non-durable Goods",
            "type":"Manufacturing & Wholesale Goods"
        }
    ],
    "sg:phone":"+1 905 944 0044",
    "sg:postcode":"L3R 1G7",
    "sg:province":"ON",
    "sg:tags":[
        "advertising"
    ],
    "wof:name":"Promotional Way",
    "wof:placetype":"venue"
},
  "geometry": {"coordinates":[-79.346436,43.819092],"type":"Point"}
}