{
  "type": "Feature",
  "properties": {
    "addr:full":"4846 Athalmer Rd Invermere BC V0A 1K3",
    "addr:housenumber":"4846",
    "addr:postcode":"v0a 1k3",
    "addr:street":"Athalmer Rd",
    "iso:country":"CA",
    "sg:address":"4846 Athalmer Rd",
    "sg:city":"Invermere",
    "sg:classifiers":[
        {
            "category":"Utilities",
            "subcategory":"Fuel Oil & Lpg",
            "type":"Services"
        }
    ],
    "sg:phone":"+1 250 342 0123",
    "sg:postcode":"V0A 1K3",
    "sg:province":"BC",
    "sg:tags":[
        "propane",
        "gas"
    ],
    "wof:name":"Superior Propane Inc",
    "wof:placetype":"venue"
},
  "geometry": {"coordinates":[-116.030373,50.509171],"type":"Point"}
}