{
  "type": "Feature",
  "properties": {
    "addr:full":"Calgary AB T2J 4G4",
    "addr:postcode":"t2j 4g4",
    "iso:country":"CA",
    "sg:city":"Calgary",
    "sg:classifiers":[
        {
            "category":"Organizations",
            "subcategory":"Religious Organization",
            "type":"Services"
        }
    ],
    "sg:phone":"+1 403 201 5151",
    "sg:postcode":"T2J 4G4",
    "sg:province":"AB",
    "sg:tags":[
        "church"
    ],
    "wof:name":"Pavilion of Hope Church",
    "wof:placetype":"venue"
},
  "geometry": {"coordinates":[-114.025268555,50.9395370483],"type":"Point"}
}