{
  "type": "Feature",
  "properties": {
    "addr:full":"Claresholm AB T0L 0T0",
    "addr:postcode":"t0l 0t0",
    "iso:country":"CA",
    "sg:city":"Claresholm",
    "sg:classifiers":[
        {
            "category":"Organizations",
            "subcategory":"Religious Organization",
            "type":"Services"
        }
    ],
    "sg:phone":"+1 403 625 2448",
    "sg:postcode":"T0L 0T0",
    "sg:province":"AB",
    "sg:tags":[
        "church"
    ],
    "wof:name":"Victory Church of Claresholm",
    "wof:placetype":"venue"
},
  "geometry": {"coordinates":[-113.582946777,50.0220718384],"type":"Point"}
}