{
  "type": "Feature",
  "properties": {
    "addr:full":"3456 Rue Saint-Denis Montreal QC H2X 3L3",
    "addr:housenumber":"3456",
    "addr:postcode":"h2x 3l3",
    "addr:street":"Rue Saint-Denis",
    "iso:country":"CA",
    "sg:address":"3456 Rue Saint-Denis",
    "sg:city":"Montreal",
    "sg:classifiers":[
        {
            "category":"Shopping",
            "subcategory":"Clothing, Apparel, & Fashions",
            "type":"Retail Goods"
        }
    ],
    "sg:phone":"+1 514 281 0986",
    "sg:postcode":"H2X 3L3",
    "sg:province":"QC",
    "sg:tags":[
        "item",
        "boutique"
    ],
    "wof:name":"Boutique X2O",
    "wof:placetype":"venue"
},
  "geometry": {"coordinates":[-73.568344,45.517189],"type":"Point"}
}