{
  "type": "Feature",
  "properties": {
    "iso:country":"CA",
    "sg:address":"30 Rue Saint-Jean-Baptiste E",
    "sg:city":"Rigaud",
    "sg:classifiers":[
        {
            "category":"Shopping",
            "subcategory":"Clothing, Apparel, & Fashions",
            "type":"Retail Goods"
        }
    ],
    "sg:phone":"+1 450 451 9998",
    "sg:postcode":"J0P 1P0",
    "sg:province":"QC",
    "sg:tags":[
        "lingerie"
    ],
    "wof:name":"Lingerie Marilyn",
    "wof:placetype":"venue"
},
  "geometry": {"coordinates":[-74.2992095947,45.4791412354],"type":"Point"}
}