{
  "type": "Feature",
  "properties": {
    "addr:full":"Toronto ON M5G 1P5",
    "addr:postcode":"m5g 1p5",
    "iso:country":"CA",
    "sg:city":"Toronto",
    "sg:classifiers":[
        {
            "category":"Restaurant",
            "type":"Food & Drink"
        }
    ],
    "sg:phone":"+1 416 977 0933",
    "sg:postcode":"M5G 1P5",
    "sg:province":"ON",
    "wof:name":"Yueh Tung Restaurant",
    "wof:placetype":"venue"
},
  "geometry": {"coordinates":[-79.3852767944,43.6552085876],"type":"Point"}
}