{
  "type": "Feature",
  "properties": {
    "addr:full":"Terrace BC V8G 1R6",
    "addr:postcode":"v8g 1r6",
    "iso:country":"CA",
    "sg:city":"Terrace",
    "sg:classifiers":[
        {
            "category":"Food & Beverages",
            "subcategory":"Specialty",
            "type":"Retail Goods"
        }
    ],
    "sg:phone":"+1 250 635 5980",
    "sg:postcode":"V8G 1R6",
    "sg:province":"BC",
    "sg:tags":[
        "health",
        "diet"
    ],
    "wof:name":"Dynamic Health Svc",
    "wof:placetype":"venue"
},
  "geometry": {"coordinates":[-128.59520000000001,54.517185],"type":"Point"}
}