{
  "type": "Feature",
  "properties": {
    "addr:full":"3438 Rg 8 S Adstock QC G0N 1S0",
    "addr:housenumber":"3438;8",
    "addr:postcode":"g0n 1s0",
    "addr:street":"Rg;S",
    "iso:country":"CA",
    "sg:address":"3438 Rg 8 S",
    "sg:city":"Adstock",
    "sg:classifiers":[
        {
            "category":"Insurance",
            "subcategory":"Insurance Agent",
            "type":"Services"
        }
    ],
    "sg:phone":"+1 418 338 6282",
    "sg:postcode":"G0N 1S0",
    "sg:province":"QC",
    "sg:tags":[
        "adjuster"
    ],
    "wof:name":"Expertises & Evaluation",
    "wof:placetype":"venue"
},
  "geometry": {"coordinates":[-71.073273,46.044994],"type":"Point"}
}