{
  "type": "Feature",
  "properties": {
    "iso:country":"CA",
    "sg:city":"Green Valley",
    "sg:classifiers":[
        {
            "category":"Government",
            "subcategory":"Office",
            "type":"Public Place"
        }
    ],
    "sg:phone":"+1 613 525 2573",
    "sg:postcode":"K0C 1L0",
    "sg:province":"ON",
    "sg:tags":[
        "village"
    ],
    "wof:name":"Stormont Dundas & Glengarry",
    "wof:placetype":"venue"
},
  "geometry": {"coordinates":[-74.5981292725,45.2594833374],"type":"Point"}
}