{
  "type": "Feature",
  "properties": {
    "addr:full":"5500 North Service Rd Burlington ON L7L 6W6",
    "addr:housenumber":"5500",
    "addr:postcode":"l7l 6w6",
    "addr:street":"North Service Rd",
    "iso:country":"CA",
    "sg:address":"5500 North Service Rd",
    "sg:city":"Burlington",
    "sg:classifiers":[
        {
            "category":"Insurance",
            "subcategory":"Insurance Agent",
            "type":"Services"
        }
    ],
    "sg:phone":"+1 905 335 3091",
    "sg:postcode":"L7L 6W6",
    "sg:province":"ON",
    "wof:name":"Journey Man Travel Protection",
    "wof:placetype":"venue"
},
  "geometry": {"coordinates":[-79.761139,43.395374],"type":"Point"}
}