{
  "type": "Feature",
  "properties": {
    "addr:full":"2025 Bayswater St Vancouver BC V6K 4A9",
    "addr:housenumber":"2025",
    "addr:postcode":"v6k 4a9",
    "addr:street":"Bayswater St",
    "iso:country":"CA",
    "sg:address":"2025 Bayswater St",
    "sg:city":"Vancouver",
    "sg:classifiers":[
        {
            "category":"Real Estate",
            "subcategory":"Architect",
            "type":"Services"
        }
    ],
    "sg:phone":"+1 604 228 1243",
    "sg:postcode":"V6K 4A9",
    "sg:province":"BC",
    "wof:name":"Monica Baillie Architect Ltd",
    "wof:placetype":"venue"
},
  "geometry": {"coordinates":[-123.171181,49.268143],"type":"Point"}
}