{
  "type": "Feature",
  "properties": {
    "addr:full":"4703 50 Ave Leduc AB T9E 6Y5",
    "addr:housenumber":"4703",
    "addr:postcode":"t9e 6y5",
    "addr:street":"50 Ave",
    "iso:country":"CA",
    "sg:address":"4703 50 Ave",
    "sg:city":"Leduc",
    "sg:classifiers":[
        {
            "category":"Building & Trades",
            "subcategory":"Construction",
            "type":"Services"
        }
    ],
    "sg:phone":"+1 780 986 7534",
    "sg:postcode":"T9E 6Y5",
    "sg:province":"AB",
    "sg:tags":[
        "resurfacing",
        "material",
        "laying",
        "refinishing",
        "floor"
    ],
    "wof:name":"Quality Floor Coverings Ltd",
    "wof:placetype":"venue"
},
  "geometry": {"coordinates":[-113.546379089,53.2646598816],"type":"Point"}
}