{
  "type": "Feature",
  "properties": {
    "addr:full":"1569 Michael St Ottawa ON K1B 3T3",
    "addr:housenumber":"1569",
    "addr:postcode":"k1b 3t3",
    "addr:street":"Michael St",
    "iso:country":"CA",
    "sg:address":"1569 Michael St",
    "sg:city":"Ottawa",
    "sg:classifiers":[
        {
            "category":"Building & Trades",
            "subcategory":"Equipment Rental",
            "type":"Services"
        }
    ],
    "sg:phone":"+1 613 745 7081",
    "sg:postcode":"K1B 3T3",
    "sg:province":"ON",
    "sg:tags":[
        "scaffolding"
    ],
    "wof:name":"Aluma Systems Canada Inc",
    "wof:placetype":"venue"
},
  "geometry": {"coordinates":[-75.62623600000001,45.41161],"type":"Point"}
}