{
  "type": "Feature",
  "properties": {
    "addr:full":"3 Kevi Cres Richmond Hill ON L4B 3C7",
    "addr:housenumber":"3",
    "addr:postcode":"l4b 3c7",
    "addr:street":"Kevi Cres",
    "iso:country":"CA",
    "sg:address":"3 Kevi Cres",
    "sg:city":"Richmond Hill",
    "sg:classifiers":[
        {
            "category":"Building & Trades",
            "subcategory":"Construction",
            "type":"Services"
        }
    ],
    "sg:phone":"+1 905 709 9900",
    "sg:postcode":"L4B 3C7",
    "sg:province":"ON",
    "sg:tags":[
        "general",
        "contractor"
    ],
    "wof:name":"Nashid Construction Corp",
    "wof:placetype":"venue"
},
  "geometry": {"coordinates":[-79.403633,43.8578],"type":"Point"}
}