{
  "type": "Feature",
  "properties": {
    "addr:full":"1001 Westmount Shopping Ctr NW # 232 Edmonton AB T5M 3L7",
    "addr:housenumber":"1001",
    "addr:postcode":"t5m 3l7",
    "addr:street":"Westmount Shopping Ctr Nw # 232",
    "iso:country":"CA",
    "sg:address":"1001 Westmount Shopping Ctr NW # 232",
    "sg:city":"Edmonton",
    "sg:classifiers":[
        {
            "category":"Banks & Credit Unions",
            "subcategory":"Bank",
            "type":"Services"
        }
    ],
    "sg:phone":"+1 780 413 4333",
    "sg:postcode":"T5M 3L7",
    "sg:province":"AB",
    "wof:name":"Scotiabank",
    "wof:placetype":"venue"
},
  "geometry": {"coordinates":[-113.490371704,53.5462188721],"type":"Point"}
}