{
  "type": "Feature",
  "properties": {
    "iso:country":"CA",
    "sg:city":"Montreal",
    "sg:classifiers":[
        {
            "category":"Manufacturing",
            "subcategory":"Apparel",
            "type":"Manufacturing & Wholesale Goods"
        }
    ],
    "sg:phone":"+1 514 344 6662",
    "sg:postcode":"H2N 1C3",
    "sg:province":"QC",
    "sg:tags":[
        "sewing",
        "clothing",
        "contractor"
    ],
    "wof:name":"Service DE Finition Label Pro",
    "wof:placetype":"venue"
},
  "geometry": {"coordinates":[-73.65074157710001,45.5452651978],"type":"Point"}
}