{
  "type": "Feature",
  "properties": {
    "addr:full":"Moncton NB E1C 1H6",
    "addr:postcode":"e1c 1h6",
    "iso:country":"CA",
    "sg:city":"Moncton",
    "sg:classifiers":[
        {
            "category":"Health Services",
            "subcategory":"Doctor",
            "type":"Services"
        }
    ],
    "sg:phone":"+1 506 858 9180",
    "sg:postcode":"E1C 1H6",
    "sg:province":"NB",
    "sg:tags":[
        "clinic",
        "psychologist"
    ],
    "wof:name":"Clinique DE Psychologie",
    "wof:placetype":"venue"
},
  "geometry": {"coordinates":[-64.7871932983,46.0853843689],"type":"Point"}
}