{
  "type": "Feature",
  "properties": {
    "addr:full":"132 Broadway St W # G Yorkton SK S3N 0M4",
    "addr:housenumber":"132",
    "addr:postcode":"s3n 0m4",
    "addr:street":"Broadway St W # G",
    "iso:country":"CA",
    "sg:address":"132 Broadway St W # G",
    "sg:city":"Yorkton",
    "sg:classifiers":[
        {
            "category":"Professional",
            "subcategory":"Accounting & Tax Preparation",
            "type":"Services"
        }
    ],
    "sg:phone":"+1 306 782 2221",
    "sg:postcode":"S3N 0M4",
    "sg:province":"SK",
    "sg:tags":[
        "return",
        "filing"
    ],
    "wof:name":"Liberty Tax Svc",
    "wof:placetype":"venue"
},
  "geometry": {"coordinates":[-102.470611572,51.2099456787],"type":"Point"}
}