{
  "type": "Feature",
  "properties": {
    "addr:full":"Mississauga ON L5S 1T1",
    "addr:postcode":"l5s 1t1",
    "iso:country":"CA",
    "sg:city":"Mississauga",
    "sg:classifiers":[
        {
            "category":"Manufacturing",
            "subcategory":"Glass & Minerals",
            "type":"Manufacturing & Wholesale Goods"
        }
    ],
    "sg:phone":"+1 905 677 8539",
    "sg:postcode":"L5S 1T1",
    "sg:province":"ON",
    "sg:tags":[
        "product",
        "marble"
    ],
    "wof:name":"Viseu Natural Stone Ltd",
    "wof:placetype":"venue"
},
  "geometry": {"coordinates":[-79.66532100000001,43.685951],"type":"Point"}
}