{
  "type": "Feature",
  "properties": {
    "addr:full":"20 Rue DE L'Eglise Lac-Au-Saumon QC G0J 1M0",
    "addr:housenumber":"20",
    "addr:postcode":"g0j 1m0",
    "addr:street":"Rue De L'Eglise",
    "iso:country":"CA",
    "sg:address":"20 Rue DE L'Eglise",
    "sg:city":"Lac-Au-Saumon",
    "sg:classifiers":[
        {
            "category":"Building & Trades",
            "subcategory":"Electrical",
            "type":"Services"
        }
    ],
    "sg:phone":"+1 418 778 3355",
    "sg:postcode":"G0J 1M0",
    "sg:province":"QC",
    "sg:tags":[
        "electric",
        "contractor"
    ],
    "wof:name":"Gasse & Fils Enr",
    "wof:placetype":"venue"
},
  "geometry": {"coordinates":[-67.3433837891,48.4227485657],"type":"Point"}
}