{
  "type": "Feature",
  "properties": {
    "addr:full":"5262 Woodhaven Dr Burlington ON L7L 3T4",
    "addr:housenumber":"5262",
    "addr:postcode":"l7l 3t4",
    "addr:street":"Woodhaven Dr",
    "iso:country":"CA",
    "sg:address":"5262 Woodhaven Dr",
    "sg:city":"Burlington",
    "sg:classifiers":[
        {
            "category":"Building & Trades",
            "subcategory":"Electrical",
            "type":"Services"
        }
    ],
    "sg:phone":"+1 905 681 9604",
    "sg:postcode":"L7L 3T4",
    "sg:province":"ON",
    "sg:tags":[
        "electric",
        "contractor"
    ],
    "wof:name":"Soder Electric Inc",
    "wof:placetype":"venue"
},
  "geometry": {"coordinates":[-79.7460861206,43.3757514954],"type":"Point"}
}