{
  "type": "Feature",
  "properties": {
    "addr:full":"56 Edilcan Dr Concord ON L4K 3S6",
    "addr:housenumber":"56",
    "addr:postcode":"l4k 3s6",
    "addr:street":"Edilcan Dr",
    "iso:country":"CA",
    "sg:address":"56 Edilcan Dr",
    "sg:city":"Concord",
    "sg:classifiers":[
        {
            "category":"Manufacturing",
            "subcategory":"Tools & Machinery",
            "type":"Manufacturing & Wholesale Goods"
        }
    ],
    "sg:phone":"+1 905 738 5821",
    "sg:postcode":"L4K 3S6",
    "sg:province":"ON",
    "sg:tags":[
        "laboratory",
        "equipment",
        "scientific",
        "apparatus",
        "instrument"
    ],
    "wof:name":"Cif Furniture",
    "wof:placetype":"venue"
},
  "geometry": {"coordinates":[-79.5265655518,43.8159980774],"type":"Point"}
}