{
  "type": "Feature",
  "properties": {
    "addr:full":"720 Montee Saint-Amour Cantley QC J8V 3E4",
    "addr:housenumber":"720",
    "addr:postcode":"j8v 3e4",
    "addr:street":"Montee Saint-Amour",
    "iso:country":"CA",
    "sg:address":"720 Montee Saint-Amour",
    "sg:city":"Cantley",
    "sg:classifiers":[
        {
            "category":"Building & Trades",
            "subcategory":"Plumbing",
            "type":"Services"
        }
    ],
    "sg:phone":"+1 819 246 9080",
    "sg:postcode":"J8V 3E4",
    "sg:province":"QC",
    "sg:tags":[
        "heating",
        "contractor"
    ],
    "wof:name":"Chauffage Andre Rogier & Fils",
    "wof:placetype":"venue"
},
  "geometry": {"coordinates":[-75.7107009888,45.5522232056],"type":"Point"}
}