{
  "type": "Feature",
  "properties": {
    "addr:full":"Redcliff AB T0J 2P0",
    "addr:postcode":"t0j 2p0",
    "iso:country":"CA",
    "sg:city":"Redcliff",
    "sg:classifiers":[
        {
            "category":"Manufacturing",
            "subcategory":"Metals",
            "type":"Manufacturing & Wholesale Goods"
        }
    ],
    "sg:phone":"+1 403 548 0078",
    "sg:postcode":"T0J 2P0",
    "sg:province":"AB",
    "sg:tags":[
        "tank"
    ],
    "wof:name":"Remo Manufacturing Ltd",
    "wof:placetype":"venue"
},
  "geometry": {"coordinates":[-110.77413199999999,50.07991],"type":"Point"}
}