{
  "type": "Feature",
  "properties": {
    "addr:full":"188 George St Lucan ON N0M 2J0",
    "addr:housenumber":"188",
    "addr:postcode":"n0m 2j0",
    "addr:street":"George St",
    "iso:country":"CA",
    "sg:address":"188 George St",
    "sg:city":"Lucan",
    "sg:classifiers":[
        {
            "category":"Utilities",
            "subcategory":"Electric",
            "type":"Services"
        }
    ],
    "sg:phone":"+1 519 227 4862",
    "sg:postcode":"N0M 2J0",
    "sg:province":"ON",
    "sg:tags":[
        "company"
    ],
    "wof:name":"Lucan Hydro Commission",
    "wof:placetype":"venue"
},
  "geometry": {"coordinates":[-81.40716552729999,43.1872901917],"type":"Point"}
}