{
  "type": "Feature",
  "properties": {
    "addr:full":"16 Rue Du Petit-Champlain Quebec QC G1K 4H4",
    "addr:housenumber":"16",
    "addr:postcode":"g1k 4h4",
    "addr:street":"Rue Du Petit-Champlain",
    "iso:country":"CA",
    "sg:address":"16 Rue Du Petit-Champlain",
    "sg:city":"Quebec",
    "sg:classifiers":[
        {
            "category":"Recreation",
            "type":"Entertainment"
        }
    ],
    "sg:phone":"+1 418 692 1132",
    "sg:postcode":"G1K 4H4",
    "sg:province":"QC",
    "sg:tags":[
        "attraction",
        "tourist"
    ],
    "wof:name":"Funiculaire Du Vieux Quebec",
    "wof:placetype":"venue"
},
  "geometry": {"coordinates":[-71.203742981,46.8123016357],"type":"Point"}
}