{
  "type": "Feature",
  "properties": {
    "addr:full":"37 Rue Sainte-Anne Sainte-Anne-DE-Bellevue QC H9X 1L4",
    "addr:housenumber":"37",
    "addr:postcode":"h9x 1l4",
    "addr:street":"Rue Sainte-Anne",
    "iso:country":"CA",
    "sg:address":"37 Rue Sainte-Anne",
    "sg:city":"Sainte-Anne-DE-Bellevue",
    "sg:classifiers":[
        {
            "category":"Autos & Motor Vehicles",
            "subcategory":"Automobile Sales",
            "type":"Retail Goods"
        }
    ],
    "sg:phone":"+1 514 457 9797",
    "sg:postcode":"H9X 1L4",
    "sg:province":"QC",
    "sg:tags":[
        "car",
        "dealer"
    ],
    "wof:name":"Lavigne Garage Inc",
    "wof:placetype":"venue"
},
  "geometry": {"coordinates":[-73.95246899999999,45.403725],"type":"Point"}
}