{
  "type": "Feature",
  "properties": {
    "addr:full":"Oshawa ON L1G 7W4",
    "addr:postcode":"l1g 7w4",
    "iso:country":"CA",
    "sg:city":"Oshawa",
    "sg:classifiers":[
        {
            "category":"Health Services",
            "subcategory":"Doctor",
            "type":"Services"
        }
    ],
    "sg:phone":"+1 905 433 5026",
    "sg:postcode":"L1G 7W4",
    "sg:province":"ON",
    "sg:tags":[
        "physician",
        "clinic",
        "surgeon"
    ],
    "wof:name":"North Oshawa Medical Ctr",
    "wof:placetype":"venue"
},
  "geometry": {"coordinates":[-78.86979700000001,43.936481],"type":"Point"}
}