{
  "type": "Feature",
  "properties": {
    "addr:full":"3504 Rue Fleury E Montreal-Nord QC H1H 2S1",
    "addr:housenumber":"3504",
    "addr:postcode":"h1h 2s1",
    "addr:street":"Rue Fleury E",
    "iso:country":"CA",
    "sg:address":"3504 Rue Fleury E",
    "sg:city":"Montreal-Nord",
    "sg:classifiers":[
        {
            "category":"Professional",
            "subcategory":"Business Services",
            "type":"Services"
        }
    ],
    "sg:phone":"+1 514 852 2668",
    "sg:postcode":"H1H 2S1",
    "sg:province":"QC",
    "sg:tags":[
        "mattress"
    ],
    "wof:name":"Recuperation 2001 Enr",
    "wof:placetype":"venue"
},
  "geometry": {"coordinates":[-73.64014400000001,45.581493],"type":"Point"}
}