{
  "type": "Feature",
  "properties": {
    "addr:full":"655 3rd Ave Hope BC V0X 1L0",
    "addr:housenumber":"655",
    "addr:postcode":"v0x 1l0",
    "addr:street":"3Rd Ave",
    "iso:country":"CA",
    "sg:address":"655 3rd Ave",
    "sg:city":"Hope",
    "sg:classifiers":[
        {
            "category":"Travel",
            "subcategory":"Hotels & Motels",
            "type":"Entertainment"
        }
    ],
    "sg:phone":"+1 604 869 5220",
    "sg:postcode":"V0X 1L0",
    "sg:province":"BC",
    "wof:name":"Skagit Motel",
    "wof:placetype":"venue"
},
  "geometry": {"coordinates":[-121.443664551,49.3819923401],"type":"Point"}
}