{
  "type": "Feature",
  "properties": {
    "iso:country":"CA",
    "sg:city":"Kitchener",
    "sg:classifiers":[
        {
            "category":"Manufacturing",
            "subcategory":"Tools & Machinery",
            "type":"Manufacturing & Wholesale Goods"
        }
    ],
    "sg:phone":"+1 519 894 0440",
    "sg:postcode":"N2R 1H4",
    "sg:province":"ON",
    "sg:tags":[
        "machine",
        "shop"
    ],
    "wof:name":"Ottawa Machine Inc",
    "wof:placetype":"venue"
},
  "geometry": {"coordinates":[-80.480865,43.402973],"type":"Point"}
}