{
  "type": "Feature",
  "properties": {
    "addr:full":"345 New York Central Ave Embrun ON K0A 1W1",
    "addr:housenumber":"345",
    "addr:postcode":"k0a 1w1",
    "addr:street":"New York Central Ave",
    "iso:country":"CA",
    "sg:address":"345 New York Central Ave",
    "sg:city":"Embrun",
    "sg:classifiers":[
        {
            "category":"Building & Trades",
            "subcategory":"Equipment Rental",
            "type":"Services"
        }
    ],
    "sg:phone":"+1 613 443 5153",
    "sg:postcode":"K0A 1W1",
    "sg:province":"ON",
    "sg:tags":[
        "toilet"
    ],
    "wof:name":"Embrun Sanitation Svc",
    "wof:placetype":"venue"
},
  "geometry": {"coordinates":[-75.3055343628,45.2704162598],"type":"Point"}
}