{
  "type": "Feature",
  "properties": {
    "addr:full":"3 Orchard Dr Waterdown ON L0R 2H4",
    "addr:housenumber":"3",
    "addr:postcode":"l0r 2h4",
    "addr:street":"Orchard Dr",
    "iso:country":"CA",
    "sg:address":"3 Orchard Dr",
    "sg:city":"Waterdown",
    "sg:classifiers":[
        {
            "category":"Wholesale",
            "subcategory":"Chemicals & Plastics",
            "type":"Manufacturing & Wholesale Goods"
        }
    ],
    "sg:phone":"+1 905 689 4064",
    "sg:postcode":"L0R 2H4",
    "sg:province":"ON",
    "sg:tags":[
        "cleaning",
        "compound"
    ],
    "wof:name":"Amway Home Products Distrs",
    "wof:placetype":"venue"
},
  "geometry": {"coordinates":[-79.8960342407,43.3281822205],"type":"Point"}
}