{
  "type": "Feature",
  "properties": {
    "addr:full":"21 Woodlawn Rd E #204 Guelph ON N1H 1G6",
    "addr:housenumber":"21",
    "addr:postcode":"n1h 1g6",
    "addr:street":"Woodlawn Rd E # 204",
    "iso:country":"CA",
    "sg:address":"21 Woodlawn Rd E #204",
    "sg:city":"Guelph",
    "sg:classifiers":[
        {
            "category":"Real Estate",
            "subcategory":"Real Estate Operator",
            "type":"Services"
        }
    ],
    "sg:phone":"+1 519 821 3350",
    "sg:postcode":"N1H 1G6",
    "sg:province":"ON",
    "sg:tags":[
        "apartment"
    ],
    "wof:name":"Woodlawn Towers Apartments",
    "wof:placetype":"venue"
},
  "geometry": {"coordinates":[-80.27636,43.565613],"type":"Point"}
}