{
  "type": "Feature",
  "properties": {
    "addr:full":"5126 49 Ave Taber AB T1G 1T6",
    "addr:housenumber":"5126",
    "addr:postcode":"t1g 1t6",
    "addr:street":"49 Ave",
    "iso:country":"CA",
    "sg:address":"5126 49 Ave",
    "sg:city":"Taber",
    "sg:classifiers":[
        {
            "category":"Government",
            "subcategory":"Office",
            "type":"Public Place"
        }
    ],
    "sg:phone":"+1 403 223 7941",
    "sg:postcode":"T1G 1T6",
    "sg:province":"AB",
    "wof:name":"Alberta Provincial Courts",
    "wof:placetype":"venue"
},
  "geometry": {"coordinates":[-112.148117,49.784855],"type":"Point"}
}