{
  "type": "Feature",
  "properties": {
    "addr:full":"Stettler AB T0C 2L2",
    "addr:postcode":"t0c 2l2",
    "iso:country":"CA",
    "sg:city":"Stettler",
    "sg:classifiers":[
        {
            "category":"Real Estate",
            "subcategory":"Real Estate Agent",
            "type":"Services"
        }
    ],
    "sg:phone":"+1 403 742 6747",
    "sg:postcode":"T0C 2L2",
    "sg:province":"AB",
    "wof:name":"First Choice Realty",
    "wof:placetype":"venue"
},
  "geometry": {"coordinates":[-112.704582,52.327667],"type":"Point"}
}