{
  "type": "Feature",
  "properties": {
    "iso:country":"CA",
    "sg:address":"3635 4th Ave W",
    "sg:city":"Vancouver",
    "sg:classifiers":[
        {
            "category":"Shopping",
            "subcategory":"Used Merchandise",
            "type":"Retail Goods"
        }
    ],
    "sg:phone":"+1 604 730 5507",
    "sg:postcode":"V6R 1P2",
    "sg:province":"BC",
    "sg:tags":[
        "clothing"
    ],
    "wof:name":"Happy Kids Consignment Clothes",
    "wof:placetype":"venue"
},
  "geometry": {"coordinates":[-123.184334,49.26873],"type":"Point"}
}