{
  "type": "Feature",
  "properties": {
    "iso:country":"CA",
    "sg:address":"5777 Rue Sherbrooke E",
    "sg:city":"Montreal",
    "sg:classifiers":[
        {
            "category":"Health Services",
            "subcategory":"Health Practitioner",
            "type":"Services"
        }
    ],
    "sg:phone":"+1 514 251 8675",
    "sg:postcode":"H1N 3R5",
    "sg:province":"QC",
    "sg:tags":[
        "psychologist"
    ],
    "wof:name":"Des Rosiers, Jozett",
    "wof:placetype":"venue"
},
  "geometry": {"coordinates":[-73.54856100000001,45.574554],"type":"Point"}
}