{
  "type": "Feature",
  "properties": {
    "addr:full":"1619 20th Ave E Vancouver BC V5N 2K9",
    "addr:housenumber":"1619",
    "addr:postcode":"v5n 2k9",
    "addr:street":"20Th Ave E",
    "iso:country":"CA",
    "sg:address":"1619 20th Ave E",
    "sg:city":"Vancouver",
    "sg:classifiers":[
        {
            "category":"Professional",
            "type":"Services"
        }
    ],
    "sg:phone":"+1 604 253 2737",
    "sg:postcode":"V5N 2K9",
    "sg:province":"BC",
    "sg:tags":[
        "fire",
        "equipment",
        "arts",
        "protection"
    ],
    "wof:name":"William Thomson Ltd",
    "wof:placetype":"venue"
},
  "geometry": {"coordinates":[-123.07107499999999,49.252689],"type":"Point"}
}