{
  "type": "Feature",
  "properties": {
    "addr:full":"370 Rue Du College Sorel-Tracy QC J3P 6T7",
    "addr:housenumber":"370",
    "addr:postcode":"j3p 6t7",
    "addr:street":"Rue Du College",
    "iso:country":"CA",
    "sg:address":"370 Rue Du College",
    "sg:city":"Sorel-Tracy",
    "sg:classifiers":[
        {
            "category":"Real Estate",
            "subcategory":"Real Estate Agent",
            "type":"Services"
        }
    ],
    "sg:phone":"+1 450 742 3787",
    "sg:postcode":"J3P 6T7",
    "sg:province":"QC",
    "sg:tags":[
        "propane",
        "rental",
        "agency",
        "gas"
    ],
    "wof:name":"Propane Global",
    "wof:placetype":"venue"
},
  "geometry": {"coordinates":[-73.09271240229999,46.0351142883],"type":"Point"}
}