{
  "type": "Feature",
  "properties": {
    "addr:full":"1474 Ironwood St Campbell River BC V9W 5T5",
    "addr:housenumber":"1474",
    "addr:postcode":"v9w 5t5",
    "addr:street":"Ironwood St",
    "iso:country":"CA",
    "sg:address":"1474 Ironwood St",
    "sg:city":"Campbell River",
    "sg:classifiers":[
        {
            "category":"Shopping",
            "subcategory":"Books",
            "type":"Retail Goods"
        }
    ],
    "sg:phone":"+1 250 286 8344",
    "sg:postcode":"V9W 5T5",
    "sg:province":"BC",
    "sg:tags":[
        "dealer"
    ],
    "wof:name":"Book Bonanza",
    "wof:placetype":"venue"
},
  "geometry": {"coordinates":[-125.255157471,50.0288543701],"type":"Point"}
}