{
  "type": "Feature",
  "properties": {
    "addr:full":"9417 96A St NW Edmonton AB T6C 3Z6",
    "addr:housenumber":"9417",
    "addr:postcode":"t6c 3z6",
    "addr:street":"96A St Nw",
    "iso:country":"CA",
    "sg:address":"9417 96A St NW",
    "sg:city":"Edmonton",
    "sg:classifiers":[
        {
            "category":"Building & Trades",
            "subcategory":"Construction",
            "type":"Services"
        }
    ],
    "sg:phone":"+1 780 466 4206",
    "sg:postcode":"T6C 3Z6",
    "sg:province":"AB",
    "sg:tags":[
        "contractor"
    ],
    "wof:name":"Kora Construction Ltd",
    "wof:placetype":"venue"
},
  "geometry": {"coordinates":[-113.477081,53.531071],"type":"Point"}
}