{
  "type": "Feature",
  "properties": {
    "addr:full":"6867 Rue Saint-Denis Montreal QC H2S 2S3",
    "addr:housenumber":"6867",
    "addr:postcode":"h2s 2s3",
    "addr:street":"Rue Saint-Denis",
    "iso:country":"CA",
    "sg:address":"6867 Rue Saint-Denis",
    "sg:city":"Montreal",
    "sg:classifiers":[
        {
            "category":"Health Services",
            "subcategory":"Chiropractor",
            "type":"Services"
        }
    ],
    "sg:phone":"+1 514 278 0012",
    "sg:postcode":"H2S 2S3",
    "sg:province":"QC",
    "wof:name":"Lambert, Benoit DC",
    "wof:placetype":"venue"
},
  "geometry": {"coordinates":[-73.610542,45.536674],"type":"Point"}
}