{
  "type": "Feature",
  "properties": {
    "addr:full":"44 Wellesworth Dr # 200 Etobicoke ON M9C 4R1",
    "addr:housenumber":"44",
    "addr:postcode":"m9c 4r1",
    "addr:street":"Wellesworth Dr # 200",
    "iso:country":"CA",
    "sg:address":"44 Wellesworth Dr # 200",
    "sg:city":"Etobicoke",
    "sg:classifiers":[
        {
            "category":"Personal",
            "subcategory":"Beauty Salon",
            "type":"Services"
        }
    ],
    "sg:phone":"+1 416 626 1548",
    "sg:postcode":"M9C 4R1",
    "sg:province":"ON",
    "wof:name":"Tessie's Hair Studio",
    "wof:placetype":"venue"
},
  "geometry": {"coordinates":[-79.5787887573,43.6664810181],"type":"Point"}
}