{
  "type": "Feature",
  "properties": {
    "addr:full":"6 Cross St Dundas ON L9H 2R4",
    "addr:housenumber":"6",
    "addr:postcode":"l9h 2r4",
    "addr:street":"Cross St",
    "iso:country":"CA",
    "sg:address":"6 Cross St",
    "sg:city":"Dundas",
    "sg:classifiers":[
        {
            "category":"Education",
            "subcategory":"Special Training",
            "type":"Public Place"
        }
    ],
    "sg:phone":"+1 905 627 5880",
    "sg:postcode":"L9H 2R4",
    "sg:province":"ON",
    "sg:tags":[
        "school"
    ],
    "wof:name":"Open Kitchen Cooking School",
    "wof:placetype":"venue"
},
  "geometry": {"coordinates":[-79.953918,43.266396],"type":"Point"}
}