{
  "type": "Feature",
  "properties": {
    "addr:full":"399 Montague Ave Sudbury ON P3C 4G4",
    "addr:housenumber":"399",
    "addr:postcode":"p3c 4g4",
    "addr:street":"Montague Ave",
    "iso:country":"CA",
    "sg:address":"399 Montague Ave",
    "sg:city":"Sudbury",
    "sg:classifiers":[
        {
            "category":"Restaurant",
            "type":"Food & Drink"
        }
    ],
    "sg:phone":"+1 705 675 8585",
    "sg:postcode":"P3C 4G4",
    "sg:province":"ON",
    "sg:tags":[
        "pizza"
    ],
    "wof:name":"Papa Lou's Pizzeria & Pasta",
    "wof:placetype":"venue"
},
  "geometry": {"coordinates":[-81.005943,46.502228],"type":"Point"}
}