{
  "type": "Feature",
  "properties": {
    "addr:full":"28 Clements Ave Yarmouth NS B5A 4K4",
    "addr:housenumber":"28",
    "addr:postcode":"b5a 4k4",
    "addr:street":"Clements Ave",
    "iso:country":"CA",
    "sg:address":"28 Clements Ave",
    "sg:city":"Yarmouth",
    "sg:classifiers":[
        {
            "category":"Wholesale",
            "subcategory":"Machinery & Supplies",
            "type":"Manufacturing & Wholesale Goods"
        }
    ],
    "sg:phone":"+1 902 742 9737",
    "sg:postcode":"B5A 4K4",
    "sg:province":"NS",
    "sg:tags":[
        "equipment",
        "welding"
    ],
    "wof:name":"Nova Welding Supplies Ltd",
    "wof:placetype":"venue"
},
  "geometry": {"coordinates":[-66.114189,43.836369],"type":"Point"}
}