{
  "type": "Feature",
  "properties": {
    "addr:full":"106 Rue Western Sutton QC J0E 2K0",
    "addr:housenumber":"106",
    "addr:postcode":"j0e 2k0",
    "addr:street":"Rue Western",
    "iso:country":"CA",
    "sg:address":"106 Rue Western",
    "sg:city":"Sutton",
    "sg:classifiers":[
        {
            "category":"Freight",
            "type":"Transportation"
        }
    ],
    "sg:phone":"+1 450 538 2314",
    "sg:postcode":"J0E 2K0",
    "sg:province":"QC",
    "sg:tags":[
        "trucking"
    ],
    "wof:name":"Transport Larose & Fils Inc",
    "wof:placetype":"venue"
},
  "geometry": {"coordinates":[-72.6177749634,45.112991333],"type":"Point"}
}