{
  "type": "Feature",
  "properties": {
    "addr:full":"206 Parkhill Rd W Peterborough ON K9H 3H3",
    "addr:housenumber":"206",
    "addr:postcode":"k9h 3h3",
    "addr:street":"Parkhill Rd W",
    "iso:country":"CA",
    "sg:address":"206 Parkhill Rd W",
    "sg:city":"Peterborough",
    "sg:classifiers":[
        {
            "category":"Building & Trades",
            "subcategory":"Construction",
            "type":"Services"
        }
    ],
    "sg:phone":"+1 705 742 2702",
    "sg:postcode":"K9H 3H3",
    "sg:province":"ON",
    "sg:tags":[
        "general",
        "carpenter",
        "contractor"
    ],
    "wof:name":"Andreas Wolf Carpentry",
    "wof:placetype":"venue"
},
  "geometry": {"coordinates":[-78.3237609863,44.315071106],"type":"Point"}
}