{
  "type": "Feature",
  "properties": {
    "addr:full":"Etobicoke ON M8Z 5Y2",
    "addr:postcode":"m8z 5y2",
    "iso:country":"CA",
    "sg:city":"Etobicoke",
    "sg:classifiers":[
        {
            "category":"Manufacturing",
            "subcategory":"Printing",
            "type":"Manufacturing & Wholesale Goods"
        }
    ],
    "sg:phone":"+1 416 231 6966",
    "sg:postcode":"M8Z 5Y2",
    "sg:province":"ON",
    "sg:tags":[
        "printer",
        "envelope"
    ],
    "wof:name":"Performance Envelope Ltd",
    "wof:placetype":"venue"
},
  "geometry": {"coordinates":[-79.520432,43.63044],"type":"Point"}
}