{
  "type": "Feature",
  "properties": {
    "addr:full":"416 Maple St Maple Creek SK S0N 1N0",
    "addr:housenumber":"416",
    "addr:postcode":"s0n 1n0",
    "addr:street":"Maple St",
    "iso:country":"CA",
    "sg:address":"416 Maple St",
    "sg:city":"Maple Creek",
    "sg:classifiers":[
        {
            "category":"Building & Trades",
            "subcategory":"Landscaping Services",
            "type":"Services"
        }
    ],
    "sg:phone":"+1 306 662 3323",
    "sg:postcode":"S0N 1N0",
    "sg:province":"SK",
    "sg:tags":[
        "tree"
    ],
    "wof:name":"Lloyd's Tree Svc",
    "wof:placetype":"venue"
},
  "geometry": {"coordinates":[-109.480408,49.906586],"type":"Point"}
}