{
  "type": "Feature",
  "properties": {
    "addr:full":"15911 Patricia Dr NW Edmonton AB T5R 5N3",
    "addr:housenumber":"15911",
    "addr:postcode":"t5r 5n3",
    "addr:street":"Patricia Dr Nw",
    "iso:country":"CA",
    "sg:address":"15911 Patricia Dr NW",
    "sg:city":"Edmonton",
    "sg:classifiers":[
        {
            "category":"Banks & Credit Unions",
            "subcategory":"Investment Brokerage",
            "type":"Services"
        }
    ],
    "sg:phone":"+1 780 486 0711",
    "sg:postcode":"T5R 5N3",
    "sg:province":"AB",
    "sg:tags":[
        "advisory",
        "financial"
    ],
    "wof:name":"Wge Investments Ltd",
    "wof:placetype":"venue"
},
  "geometry": {"coordinates":[-113.595794678,53.5083465576],"type":"Point"}
}