{
  "type": "Feature",
  "properties": {
    "iso:country":"CA",
    "sg:address":"8887 Scurfield Dr NW",
    "sg:city":"Calgary",
    "sg:classifiers":[
        {
            "category":"Education",
            "subcategory":"School",
            "type":"Public Place"
        }
    ],
    "sg:phone":"+1 403 208 0242",
    "sg:postcode":"T3L 1H6",
    "sg:province":"AB",
    "wof:name":"Monsignor El Doyle Elem Schl",
    "wof:placetype":"venue"
},
  "geometry": {"coordinates":[-114.217133,51.122581],"type":"Point"}
}