{
  "type": "Feature",
  "properties": {
    "addr:full":"Prince George BC V2L 3X3",
    "addr:postcode":"v2l 3x3",
    "iso:country":"CA",
    "sg:city":"Prince George",
    "sg:classifiers":[
        {
            "category":"Shopping",
            "subcategory":"Bicycles & Sporting Goods",
            "type":"Retail Goods"
        }
    ],
    "sg:phone":"+1 250 563 9914",
    "sg:postcode":"V2L 3X3",
    "sg:province":"BC",
    "wof:name":"Coast Mountain Sports",
    "wof:placetype":"venue"
},
  "geometry": {"coordinates":[-122.758202,53.909946],"type":"Point"}
}