{
  "type": "Feature",
  "properties": {
    "addr:full":"735 Queen St E Toronto ON M4M 1H1",
    "addr:housenumber":"735",
    "addr:postcode":"m4m 1h1",
    "addr:street":"Queen St E",
    "iso:country":"CA",
    "sg:address":"735 Queen St E",
    "sg:city":"Toronto",
    "sg:classifiers":[
        {
            "category":"Bars & Pubs",
            "type":"Food & Drink"
        }
    ],
    "sg:phone":"+1 416 466 0313",
    "sg:postcode":"M4M 1H1",
    "sg:province":"ON",
    "sg:tags":[
        "club",
        "night"
    ],
    "wof:name":"Opera House",
    "wof:placetype":"venue"
},
  "geometry": {"coordinates":[-79.348793,43.658966],"type":"Point"}
}