{
  "type": "Feature",
  "properties": {
    "iso:country":"CA",
    "sg:address":"106 Sackville St",
    "sg:city":"Montague",
    "sg:classifiers":[
        {
            "category":"Restaurant",
            "type":"Food & Drink"
        }
    ],
    "sg:phone":"+1 902 838 2080",
    "sg:postcode":"C0A 1R0",
    "sg:province":"PE",
    "wof:name":"Windows on the Water Cafe",
    "wof:placetype":"venue"
},
  "geometry": {"coordinates":[-62.648323,46.16507],"type":"Point"}
}