{
  "type": "Feature",
  "properties": {
    "addr:full":"290 Picton Ave Ottawa ON K1Z 8P8",
    "addr:housenumber":"290",
    "addr:postcode":"k1z 8p8",
    "addr:street":"Picton Ave",
    "iso:country":"CA",
    "sg:address":"290 Picton Ave",
    "sg:city":"Ottawa",
    "sg:classifiers":[
        {
            "category":"Organizations",
            "subcategory":"Professional Association",
            "type":"Services"
        }
    ],
    "sg:phone":"+1 613 724 3003",
    "sg:postcode":"K1Z 8P8",
    "sg:province":"ON",
    "wof:name":"Cbc Pensioners Natl Assn",
    "wof:placetype":"venue"
},
  "geometry": {"coordinates":[-75.752861,45.393261],"type":"Point"}
}