{
  "type": "Feature",
  "properties": {
    "addr:full":"66 William St N Lindsay ON K9V 4A2",
    "addr:housenumber":"66",
    "addr:postcode":"k9v 4a2",
    "addr:street":"William St N",
    "iso:country":"CA",
    "sg:address":"66 William St N",
    "sg:city":"Lindsay",
    "sg:classifiers":[
        {
            "category":"Insurance",
            "subcategory":"Insurance Agent",
            "type":"Services"
        }
    ],
    "sg:phone":"+1 705 324 3744",
    "sg:postcode":"K9V 4A2",
    "sg:province":"ON",
    "wof:name":"Upper Canada Financial Ltd",
    "wof:placetype":"venue"
},
  "geometry": {"coordinates":[-78.73777771,44.3571357727],"type":"Point"}
}