{
  "type": "Feature",
  "properties": {
    "addr:full":"17468 Warden Ave Newmarket ON L3Y 4W1",
    "addr:housenumber":"17468",
    "addr:postcode":"l3y 4w1",
    "addr:street":"Warden Ave",
    "iso:country":"CA",
    "sg:address":"17468 Warden Ave",
    "sg:city":"Newmarket",
    "sg:classifiers":[
        {
            "category":"Building & Trades",
            "subcategory":"Landscaping Services",
            "type":"Services"
        }
    ],
    "sg:phone":"+1 905 773 5906",
    "sg:postcode":"L3Y 4W1",
    "sg:province":"ON",
    "sg:tags":[
        "tree",
        "landscape",
        "contractor"
    ],
    "wof:name":"Shady Lane Expert Tree Care",
    "wof:placetype":"venue"
},
  "geometry": {"coordinates":[-79.4585723877,44.0401802063],"type":"Point"}
}