{
  "type": "Feature",
  "properties": {
    "addr:full":"120 Morrell St Brantford ON N3T 4J7",
    "addr:housenumber":"120",
    "addr:postcode":"n3t 4j7",
    "addr:street":"Morrell St",
    "iso:country":"CA",
    "sg:address":"120 Morrell St",
    "sg:city":"Brantford",
    "sg:classifiers":[
        {
            "category":"Food & Beverages",
            "subcategory":"Groceries & Convenience Stores",
            "type":"Retail Goods"
        }
    ],
    "sg:phone":"+1 519 758 1533",
    "sg:postcode":"N3T 4J7",
    "sg:province":"ON",
    "sg:tags":[
        "grocer"
    ],
    "wof:name":"Top Convenience Store",
    "wof:placetype":"venue"
},
  "geometry": {"coordinates":[-80.2880935669,43.1450462341],"type":"Point"}
}