{
  "type": "Feature",
  "properties": {
    "iso:country":"CA",
    "sg:city":"Kingston",
    "sg:classifiers":[
        {
            "category":"Health Services",
            "subcategory":"Doctor",
            "type":"Services"
        }
    ],
    "sg:phone":"+1 613 549 8754",
    "sg:postcode":"K7L 5E4",
    "sg:province":"ON",
    "sg:tags":[
        "physician",
        "surgeon"
    ],
    "wof:name":"Iverson, Greg MD",
    "wof:placetype":"venue"
},
  "geometry": {"coordinates":[-76.50695,44.238998],"type":"Point"}
}