{
  "type": "Feature",
  "properties": {
    "addr:full":"RR 1 Grand Bend ON N0M 1T0",
    "addr:postcode":"n0m 1t0",
    "addr:street":"Rr 1",
    "iso:country":"CA",
    "sg:address":"RR 1",
    "sg:city":"Grand Bend",
    "sg:classifiers":[
        {
            "category":"Wholesale",
            "subcategory":"Construction Materials",
            "type":"Manufacturing & Wholesale Goods"
        }
    ],
    "sg:phone":"+1 519 238 8480",
    "sg:postcode":"N0M 1T0",
    "sg:province":"ON",
    "sg:tags":[
        "sand",
        "gravel"
    ],
    "wof:name":"Jennison Construction Ltd",
    "wof:placetype":"venue"
},
  "geometry": {"coordinates":[-81.75653076170001,43.3124732971],"type":"Point"}
}