{
  "type": "Feature",
  "properties": {
    "iso:country":"CA",
    "sg:city":"Barrie",
    "sg:classifiers":[
        {
            "category":"Home & Garden",
            "subcategory":"Furniture",
            "type":"Retail Goods"
        }
    ],
    "sg:phone":"+1 705 721 7333",
    "sg:postcode":"L4N 5R7",
    "sg:province":"ON",
    "wof:name":"Home Furniture",
    "wof:placetype":"venue"
},
  "geometry": {"coordinates":[-79.7119674683,44.3824462891],"type":"Point"}
}