{
  "type": "Feature",
  "properties": {
    "addr:full":"64 Rte 295 Lots-Renverses QC G0L 1V0",
    "addr:housenumber":"64",
    "addr:postcode":"g0l 1v0",
    "addr:street":"Rte 295 Lots-Renverses",
    "iso:country":"CA",
    "sg:address":"64 Rte 295",
    "sg:city":"Lots-Renverses",
    "sg:classifiers":[
        {
            "category":"Education",
            "subcategory":"School",
            "type":"Public Place"
        }
    ],
    "sg:phone":"+1 418 899 2356",
    "sg:postcode":"G0L 1V0",
    "sg:province":"QC",
    "wof:name":"Ecole Lots-Renverses",
    "wof:placetype":"venue"
},
  "geometry": {"coordinates":[-68.665527,47.661629],"type":"Point"}
}