{
  "type": "Feature",
  "properties": {
    "iso:country":"CA",
    "sg:address":"579 Richmond St W",
    "sg:city":"Toronto",
    "sg:classifiers":[
        {
            "category":"Professional",
            "subcategory":"Computer Services",
            "type":"Services"
        }
    ],
    "sg:phone":"+1 416 504 2551",
    "sg:postcode":"M5V 1Y6",
    "sg:province":"ON",
    "sg:tags":[
        "graphics"
    ],
    "wof:name":"Weave Communications",
    "wof:placetype":"venue"
},
  "geometry": {"coordinates":[-79.402695,43.646519],"type":"Point"}
}