{
  "type": "Feature",
  "properties": {
    "iso:country":"CA",
    "sg:address":"4841 Boul Arthur-Sauve",
    "sg:city":"Laval",
    "sg:classifiers":[
        {
            "category":"Home & Garden",
            "subcategory":"Carpets & Floor Coverings",
            "type":"Retail Goods"
        }
    ],
    "sg:phone":"+1 450 627 3474",
    "sg:postcode":"H7R 3X2",
    "sg:province":"QC",
    "sg:tags":[
        "dealer",
        "rug"
    ],
    "wof:name":"Peint-O-Theque Inc",
    "wof:placetype":"venue"
},
  "geometry": {"coordinates":[-73.86865234379999,45.5520133972],"type":"Point"}
}