{
  "type": "Feature",
  "properties": {
    "addr:full":"Lemoyne QC J4R 2L4",
    "addr:postcode":"j4r 2l4",
    "iso:country":"CA",
    "sg:city":"Lemoyne",
    "sg:classifiers":[
        {
            "category":"Wholesale",
            "subcategory":"Metals & Minerals",
            "type":"Manufacturing & Wholesale Goods"
        }
    ],
    "sg:phone":"+1 450 671 0026",
    "sg:postcode":"J4R 2L4",
    "sg:province":"QC",
    "sg:tags":[
        "aluminum"
    ],
    "wof:name":"Aluminium Pierre Enrg",
    "wof:placetype":"venue"
},
  "geometry": {"coordinates":[-73.49829099999999,45.496487],"type":"Point"}
}