{
  "type": "Feature",
  "properties": {
    "addr:full":"Nepean ON K2E 7K3",
    "addr:postcode":"k2e 7k3",
    "iso:country":"CA",
    "sg:city":"Nepean",
    "sg:classifiers":[
        {
            "category":"Banks & Credit Unions",
            "subcategory":"Investment Brokerage",
            "type":"Services"
        }
    ],
    "sg:phone":"+1 613 224 7737",
    "sg:postcode":"K2E 7K3",
    "sg:province":"ON",
    "sg:tags":[
        "retirement",
        "planning"
    ],
    "wof:name":"Mac Leod Financial Svc",
    "wof:placetype":"venue"
},
  "geometry": {"coordinates":[-75.713036,45.341728],"type":"Point"}
}