{
  "type": "Feature",
  "properties": {
    "addr:full":"93 Rue Papineau Hull QC J8X 1V1",
    "addr:housenumber":"93",
    "addr:postcode":"j8x 1v1",
    "addr:street":"Rue Papineau",
    "iso:country":"CA",
    "sg:address":"93 Rue Papineau",
    "sg:city":"Hull",
    "sg:classifiers":[
        {
            "category":"Personal",
            "subcategory":"Barber",
            "type":"Services"
        }
    ],
    "sg:phone":"+1 819 771 3124",
    "sg:postcode":"J8X 1V1",
    "sg:province":"QC",
    "wof:name":"Albert Mageau Barber Shop",
    "wof:placetype":"venue"
},
  "geometry": {"coordinates":[-75.72114562989999,45.4306678772],"type":"Point"}
}