{
  "type": "Feature",
  "properties": {
    "addr:full":"321 St. George St Moncton NB E1C 1W8",
    "addr:housenumber":"321",
    "addr:postcode":"e1c 1w8",
    "addr:street":"St. George St",
    "iso:country":"CA",
    "sg:address":"321 St. George St",
    "sg:city":"Moncton",
    "sg:classifiers":[
        {
            "category":"Professional",
            "subcategory":"Accounting & Tax Preparation",
            "type":"Services"
        }
    ],
    "sg:phone":"+1 506 853 3084",
    "sg:postcode":"E1C 1W8",
    "sg:province":"NB",
    "sg:tags":[
        "accountant"
    ],
    "wof:name":"Baker, J Douglas CA",
    "wof:placetype":"venue"
},
  "geometry": {"coordinates":[-64.786697,46.090515],"type":"Point"}
}