{
  "type": "Feature",
  "properties": {
    "iso:country":"CA",
    "sg:city":"Etobicoke",
    "sg:classifiers":[
        {
            "category":"Professional",
            "subcategory":"Lawyer & Legal Services",
            "type":"Services"
        }
    ],
    "sg:phone":"+1 416 234 8248",
    "sg:postcode":"M8X 1Y4",
    "sg:province":"ON",
    "sg:tags":[
        "attorney"
    ],
    "wof:name":"Morgan, Barbara",
    "wof:placetype":"venue"
},
  "geometry": {"coordinates":[-79.510848999,43.6603431702],"type":"Point"}
}