{
  "type": "Feature",
  "properties": {
    "addr:full":"338 Boul Sir-Wilfrid-Laurier Beloeil QC J3G 4G7",
    "addr:housenumber":"338",
    "addr:postcode":"j3g 4g7",
    "addr:street":"Boul Sir-Wilfrid-Laurier",
    "iso:country":"CA",
    "sg:address":"338 Boul Sir-Wilfrid-Laurier",
    "sg:city":"Beloeil",
    "sg:classifiers":[
        {
            "category":"Food & Beverages",
            "subcategory":"Meat & Fish",
            "type":"Retail Goods"
        }
    ],
    "sg:phone":"+1 450 446 2000",
    "sg:postcode":"J3G 4G7",
    "sg:province":"QC",
    "sg:tags":[
        "seafood"
    ],
    "wof:name":"Poissonnerie Odessa",
    "wof:placetype":"venue"
},
  "geometry": {"coordinates":[-73.212082,45.555737],"type":"Point"}
}