{
  "type": "Feature",
  "properties": {
    "addr:full":"10 Stanhope Rd Lewisporte NL A0G 3A0",
    "addr:housenumber":"10",
    "addr:postcode":"a0g 3a0",
    "addr:street":"Stanhope Rd",
    "iso:country":"CA",
    "sg:address":"10 Stanhope Rd",
    "sg:city":"Lewisporte",
    "sg:classifiers":[
        {
            "category":"Retail",
            "subcategory":"Auto Repair",
            "type":"Services"
        }
    ],
    "sg:phone":"+1 709 535 8677",
    "sg:postcode":"A0G 3A0",
    "sg:province":"NL",
    "sg:tags":[
        "repairing",
        "automobile"
    ],
    "wof:name":"A & M Automotive",
    "wof:placetype":"venue"
},
  "geometry": {"coordinates":[-55.059937,49.241798],"type":"Point"}
}