{
  "type": "Feature",
  "properties": {
    "iso:country":"CA",
    "sg:address":"7881 Boul Newman",
    "sg:city":"Lasalle",
    "sg:classifiers":[
        {
            "category":"Restaurant",
            "type":"Food & Drink"
        }
    ],
    "sg:phone":"+1 514 363 8616",
    "sg:postcode":"H8N 1X7",
    "sg:province":"QC",
    "wof:name":"Grill Newman Inc",
    "wof:placetype":"venue"
},
  "geometry": {"coordinates":[-73.62516021730001,45.4370727539],"type":"Point"}
}