{
  "type": "Feature",
  "properties": {
    "addr:full":"725 6E Rue Val-D'Or QC J9P 3Y1",
    "addr:housenumber":"725",
    "addr:postcode":"j9p 3y1",
    "addr:street":"6E Rue",
    "iso:country":"CA",
    "sg:address":"725 6E Rue",
    "sg:city":"Val-D'Or",
    "sg:classifiers":[
        {
            "category":"Organizations",
            "subcategory":"Labor Organization",
            "type":"Services"
        }
    ],
    "sg:phone":"+1 819 825 2224",
    "sg:postcode":"J9P 3Y1",
    "sg:province":"QC",
    "wof:name":"Syndicat Des Employes",
    "wof:placetype":"venue"
},
  "geometry": {"coordinates":[-65.495377,48.96125],"type":"Point"}
}