{
  "type": "Feature",
  "properties": {
    "iso:country":"CA",
    "sg:address":"590 Adams Rd # A",
    "sg:city":"Kelowna",
    "sg:classifiers":[
        {
            "category":"Building & Trades",
            "subcategory":"Construction",
            "type":"Services"
        }
    ],
    "sg:phone":"+1 250 765 3033",
    "sg:postcode":"V1X 7S1",
    "sg:province":"BC",
    "sg:tags":[
        "dry wall",
        "contractor"
    ],
    "wof:name":"Kodiak Drywall Ltd",
    "wof:placetype":"venue"
},
  "geometry": {"coordinates":[-119.388924,49.927502],"type":"Point"}
}