{
  "type": "Feature",
  "properties": {
    "addr:full":"11 Cross St Dundas ON L9H 2R3",
    "addr:housenumber":"11",
    "addr:postcode":"l9h 2r3",
    "addr:street":"Cross St",
    "iso:country":"CA",
    "sg:address":"11 Cross St",
    "sg:city":"Dundas",
    "sg:classifiers":[
        {
            "category":"Shopping",
            "subcategory":"Books",
            "type":"Retail Goods"
        }
    ],
    "sg:phone":"+1 905 627 5007",
    "sg:postcode":"L9H 2R3",
    "sg:province":"ON",
    "sg:tags":[
        "dealer"
    ],
    "wof:name":"Chapman Books",
    "wof:placetype":"venue"
},
  "geometry": {"coordinates":[-79.9535064697,43.2665672302],"type":"Point"}
}