{
  "type": "Feature",
  "properties": {
    "addr:full":"Kinmount ON K0M 2A0",
    "addr:postcode":"k0m 2a0",
    "iso:country":"CA",
    "sg:city":"Kinmount",
    "sg:classifiers":[
        {
            "category":"Organizations",
            "subcategory":"Professional Association",
            "type":"Services"
        }
    ],
    "sg:phone":"+1 705 488 2420",
    "sg:postcode":"K0M 2A0",
    "sg:province":"ON",
    "wof:name":"Royal Canadian Legion Ladies",
    "wof:placetype":"venue"
},
  "geometry": {"coordinates":[-78.651473999,44.7808914185],"type":"Point"}
}