{
  "type": "Feature",
  "properties": {
    "addr:full":"34 Edwards St # A Peterborough ON K9J 1X6",
    "addr:housenumber":"34",
    "addr:postcode":"k9j 1x6",
    "addr:street":"Edwards St # A",
    "iso:country":"CA",
    "sg:address":"34 Edwards St # A",
    "sg:city":"Peterborough",
    "sg:classifiers":[
        {
            "category":"Retail",
            "subcategory":"Auto Repair",
            "type":"Services"
        }
    ],
    "sg:phone":"+1 705 742 0111",
    "sg:postcode":"K9J 1X6",
    "sg:province":"ON",
    "sg:tags":[
        "brake"
    ],
    "wof:name":"Brake Shop",
    "wof:placetype":"venue"
},
  "geometry": {"coordinates":[-78.30877700000001,44.291142],"type":"Point"}
}