{
  "type": "Feature",
  "properties": {
    "addr:full":"PO Box 240 Igloolik NU X0A 0L0",
    "addr:housenumber":"po",
    "addr:postcode":"x0a 0l0",
    "addr:street":"Box 240",
    "iso:country":"CA",
    "sg:address":"PO Box 240",
    "sg:city":"Igloolik",
    "sg:classifiers":[
        {
            "category":"Health Services",
            "subcategory":"Clinic",
            "type":"Services"
        }
    ],
    "sg:phone":"+1 867 934 8837",
    "sg:postcode":"X0A 0L0",
    "sg:province":"NU",
    "wof:name":"Health Centre",
    "wof:placetype":"venue"
},
  "geometry": {"coordinates":[-81.7945327759,69.3772354126],"type":"Point"}
}