{
  "type": "Feature",
  "properties": {
    "iso:country":"CA",
    "sg:address":"31944 Sunrise Cres",
    "sg:city":"Abbotsford",
    "sg:classifiers":[
        {
            "category":"Social Services",
            "subcategory":"Adult Care",
            "type":"Services"
        }
    ],
    "sg:phone":"+1 604 859 8715",
    "sg:postcode":"V2T 1N5",
    "sg:province":"BC",
    "sg:tags":[
        "community",
        "facility"
    ],
    "wof:name":"Tabor Home Society",
    "wof:placetype":"venue"
},
  "geometry": {"coordinates":[-122.338378906,49.0467758179],"type":"Point"}
}