{
  "type": "Feature",
  "properties": {
    "addr:full":"365 Rue Notre-Dame Saint-Tite QC G0X 3H0",
    "addr:housenumber":"365",
    "addr:postcode":"g0x 3h0",
    "addr:street":"Rue Notre-Dame",
    "iso:country":"CA",
    "sg:address":"365 Rue Notre-Dame",
    "sg:city":"Saint-Tite",
    "sg:classifiers":[
        {
            "category":"Shopping",
            "subcategory":"Hobbies, Toys, & Games",
            "type":"Retail Goods"
        }
    ],
    "sg:phone":"+1 418 365 3936",
    "sg:postcode":"G0X 3H0",
    "sg:province":"QC",
    "sg:tags":[
        "craft",
        "supply"
    ],
    "wof:name":"Au Brin DE Laine Plus",
    "wof:placetype":"venue"
},
  "geometry": {"coordinates":[-72.565918,46.729252],"type":"Point"}
}