{
  "type": "Feature",
  "properties": {
    "addr:full":"102 Carson Ave Quesnel BC V2J 2A8",
    "addr:housenumber":"102",
    "addr:postcode":"v2j 2a8",
    "addr:street":"Carson Ave",
    "iso:country":"CA",
    "sg:address":"102 Carson Ave",
    "sg:city":"Quesnel",
    "sg:classifiers":[
        {
            "category":"Shopping",
            "subcategory":"Hobbies, Toys, & Games",
            "type":"Retail Goods"
        }
    ],
    "sg:phone":"+1 250 991 0419",
    "sg:postcode":"V2J 2A8",
    "sg:province":"BC",
    "sg:tags":[
        "shop",
        "craft",
        "gift"
    ],
    "wof:name":"Cariboo Keepsakes",
    "wof:placetype":"venue"
},
  "geometry": {"coordinates":[-122.497711,52.97562],"type":"Point"}
}