{
  "type": "Feature",
  "properties": {
    "addr:full":"24 Lakeview Ave Williams Lake BC V2G 1B2",
    "addr:housenumber":"24",
    "addr:postcode":"v2g 1b2",
    "addr:street":"Lakeview Ave",
    "iso:country":"CA",
    "sg:address":"24 Lakeview Ave",
    "sg:city":"Williams Lake",
    "sg:classifiers":[
        {
            "category":"Wholesale",
            "subcategory":"Machinery & Supplies",
            "type":"Manufacturing & Wholesale Goods"
        }
    ],
    "sg:phone":"+1 250 398 5495",
    "sg:postcode":"V2G 1B2",
    "sg:province":"BC",
    "sg:tags":[
        "equipment",
        "irrigation",
        "system"
    ],
    "wof:name":"Renegard Irrigation Ltd",
    "wof:placetype":"venue"
},
  "geometry": {"coordinates":[-122.12732699999999,52.129124],"type":"Point"}
}