{
  "type": "Feature",
  "properties": {
    "addr:full":"3305 Boul Pitfield Saint-Laurent QC H4S 1H3",
    "addr:housenumber":"3305",
    "addr:postcode":"h4s 1h3",
    "addr:street":"Boul Pitfield",
    "iso:country":"CA",
    "sg:address":"3305 Boul Pitfield",
    "sg:city":"Saint-Laurent",
    "sg:classifiers":[
        {
            "category":"Manufacturing",
            "subcategory":"Printing",
            "type":"Manufacturing & Wholesale Goods"
        }
    ],
    "sg:phone":"+1 514 337 2022",
    "sg:postcode":"H4S 1H3",
    "sg:province":"QC",
    "sg:tags":[
        "poster",
        "printer"
    ],
    "wof:name":"Imafiche",
    "wof:placetype":"venue"
},
  "geometry": {"coordinates":[-73.7527542114,45.5009040833],"type":"Point"}
}