{
  "type": "Feature",
  "properties": {
    "addr:full":"75 Charles St E Toronto ON M4Y 1V2",
    "addr:housenumber":"75",
    "addr:postcode":"m4y 1v2",
    "addr:street":"Charles St E",
    "iso:country":"CA",
    "sg:address":"75 Charles St E",
    "sg:city":"Toronto",
    "sg:classifiers":[
        {
            "category":"Personal",
            "subcategory":"Beauty Salon",
            "type":"Services"
        }
    ],
    "sg:phone":"+1 416 925 3200",
    "sg:postcode":"M4Y 1V2",
    "sg:province":"ON",
    "wof:name":"Simply Hair",
    "wof:placetype":"venue"
},
  "geometry": {"coordinates":[-79.38208770750001,43.6693344116],"type":"Point"}
}