{
  "type": "Feature",
  "properties": {
    "addr:full":"3825 Cadboro Bay Rd Victoria BC V8N 4G1",
    "addr:housenumber":"3825",
    "addr:postcode":"v8n 4g1",
    "addr:street":"Cadboro Bay Rd",
    "iso:country":"CA",
    "sg:address":"3825 Cadboro Bay Rd",
    "sg:city":"Victoria",
    "sg:classifiers":[
        {
            "category":"Shopping",
            "subcategory":"Pharmacy",
            "type":"Retail Goods"
        }
    ],
    "sg:phone":"+1 250 477 2131",
    "sg:postcode":"V8N 4G1",
    "sg:province":"BC",
    "wof:name":"Cadboro Bay Peoples Pharmacy",
    "wof:placetype":"venue"
},
  "geometry": {"coordinates":[-123.364517212,48.428314209],"type":"Point"}
}