{
  "type": "Feature",
  "properties": {
    "addr:full":"Waterloo ON N2L 5V4",
    "addr:postcode":"n2l 5v4",
    "iso:country":"CA",
    "sg:city":"Waterloo",
    "sg:classifiers":[
        {
            "category":"Retail",
            "subcategory":"Repair Shop",
            "type":"Services"
        }
    ],
    "sg:phone":"+1 519 886 3302",
    "sg:postcode":"N2L 5V4",
    "sg:province":"ON",
    "sg:tags":[
        "upholsterer"
    ],
    "wof:name":"Acadian Upholstery & Interior",
    "wof:placetype":"venue"
},
  "geometry": {"coordinates":[-80.54431200000001,43.493397],"type":"Point"}
}