{
  "type": "Feature",
  "properties": {
    "addr:full":"2212 Av Dollard Lasalle QC H8N 1S6",
    "addr:housenumber":"2212",
    "addr:postcode":"h8n 1s6",
    "addr:street":"Av Dollard",
    "iso:country":"CA",
    "sg:address":"2212 Av Dollard",
    "sg:city":"Lasalle",
    "sg:classifiers":[
        {
            "category":"Government",
            "subcategory":"Office",
            "type":"Public Place"
        }
    ],
    "sg:phone":"+1 514 365 4543",
    "sg:postcode":"H8N 1S6",
    "sg:province":"QC",
    "wof:name":"Quebec Centre Local D'Emploi",
    "wof:placetype":"venue"
},
  "geometry": {"coordinates":[-73.6360778809,45.4315567017],"type":"Point"}
}