{
  "type": "Feature",
  "properties": {
    "addr:full":"75 24th St E Saskatoon SK S7K 0K3",
    "addr:housenumber":"75",
    "addr:postcode":"s7k 0k3",
    "addr:street":"24Th St E",
    "iso:country":"CA",
    "sg:address":"75 24th St E",
    "sg:city":"Saskatoon",
    "sg:classifiers":[
        {
            "category":"Wholesale",
            "subcategory":"Apparel",
            "type":"Manufacturing & Wholesale Goods"
        }
    ],
    "sg:phone":"+1 306 652 1660",
    "sg:postcode":"S7K 0K3",
    "sg:province":"SK",
    "sg:tags":[
        "dry"
    ],
    "wof:name":"Buckwold's Limited",
    "wof:placetype":"venue"
},
  "geometry": {"coordinates":[-106.666245,52.132286],"type":"Point"}
}