{
  "type": "Feature",
  "properties": {
    "addr:full":"345 George St N Peterborough ON K9H 3P9",
    "addr:housenumber":"345",
    "addr:postcode":"k9h 3p9",
    "addr:street":"George St N",
    "iso:country":"CA",
    "sg:address":"345 George St N",
    "sg:city":"Peterborough",
    "sg:classifiers":[
        {
            "category":"Food & Beverages",
            "subcategory":"Candy",
            "type":"Retail Goods"
        }
    ],
    "sg:phone":"+1 705 740 1780",
    "sg:postcode":"K9H 3P9",
    "sg:province":"ON",
    "sg:tags":[
        "shop",
        "gift"
    ],
    "wof:name":"Nutty Chocolatier CO Ltd",
    "wof:placetype":"venue"
},
  "geometry": {"coordinates":[-78.3201141357,44.3041725159],"type":"Point"}
}