{
  "type": "Feature",
  "properties": {
    "iso:country":"CA",
    "sg:city":"Montreal",
    "sg:classifiers":[
        {
            "category":"Organizations",
            "subcategory":"Membership Organization",
            "type":"Services"
        }
    ],
    "sg:phone":"+1 514 499 1686",
    "sg:postcode":"H3A 1P8",
    "sg:province":"QC",
    "wof:name":"International Informatization",
    "wof:placetype":"venue"
},
  "geometry": {"coordinates":[-73.573921,45.499348],"type":"Point"}
}