{
  "type": "Feature",
  "properties": {
    "addr:full":"2 Rue Principale E Magog QC J1X 1Y3",
    "addr:housenumber":"2",
    "addr:postcode":"j1x 1y3",
    "addr:street":"Rue Principale E",
    "iso:country":"CA",
    "sg:address":"2 Rue Principale E",
    "sg:city":"Magog",
    "sg:classifiers":[
        {
            "category":"Health Services",
            "subcategory":"Doctor",
            "type":"Services"
        }
    ],
    "sg:phone":"+1 819 843 8440",
    "sg:postcode":"J1X 1Y3",
    "sg:province":"QC",
    "sg:tags":[
        "clinic",
        "dentist"
    ],
    "wof:name":"Clinique Dentaire Yann Patry",
    "wof:placetype":"venue"
},
  "geometry": {"coordinates":[-72.14771270750001,45.2648506165],"type":"Point"}
}