{
  "type": "Feature",
  "properties": {
    "addr:full":"PO Box 520 Pond Inlet NU X0A 0S0",
    "addr:housenumber":"po",
    "addr:postcode":"x0a 0s0",
    "addr:street":"Box 520 Pond Inlet",
    "iso:country":"CA",
    "sg:address":"PO Box 520",
    "sg:city":"Pond Inlet",
    "sg:classifiers":[
        {
            "category":"Education",
            "subcategory":"College",
            "type":"Public Place"
        }
    ],
    "sg:phone":"+1 867 899 8964",
    "sg:postcode":"X0A 0S0",
    "sg:province":"NU",
    "sg:tags":[
        "academic",
        "school"
    ],
    "wof:name":"Ulaajuk School",
    "wof:placetype":"venue"
},
  "geometry": {"coordinates":[-77.953941,72.698143],"type":"Point"}
}