{
  "type": "Feature",
  "properties": {
    "addr:full":"561 Main St Lillooet BC V0K 1V0",
    "addr:housenumber":"561",
    "addr:postcode":"v0k 1v0",
    "addr:street":"Main St",
    "iso:country":"CA",
    "sg:address":"561 Main St",
    "sg:city":"Lillooet",
    "sg:classifiers":[
        {
            "category":"Home & Garden",
            "subcategory":"Building Materials",
            "type":"Retail Goods"
        }
    ],
    "sg:phone":"+1 250 256 4111",
    "sg:postcode":"V0K 1V0",
    "sg:province":"BC",
    "sg:tags":[
        "glass",
        "window",
        "plate"
    ],
    "wof:name":"Lillooet Glass & Tire",
    "wof:placetype":"venue"
},
  "geometry": {"coordinates":[-121.932846,50.682789],"type":"Point"}
}