{
  "type": "Feature",
  "properties": {
    "addr:full":"164 Hull Rd Strathroy ON N7G 3P2",
    "addr:housenumber":"164",
    "addr:postcode":"n7g 3p2",
    "addr:street":"Hull Rd",
    "iso:country":"CA",
    "sg:address":"164 Hull Rd",
    "sg:city":"Strathroy",
    "sg:classifiers":[
        {
            "category":"Social Services",
            "type":"Services"
        }
    ],
    "sg:phone":"+1 519 246 1445",
    "sg:postcode":"N7G 3P2",
    "sg:province":"ON",
    "sg:tags":[
        "organization",
        "welfare"
    ],
    "wof:name":"Anago Resources Inc",
    "wof:placetype":"venue"
},
  "geometry": {"coordinates":[-81.624908,42.965199],"type":"Point"}
}