{
  "type": "Feature",
  "properties": {
    "addr:full":"1100 Rue Notre-Dame Centre Trois-Rivieres QC G9A 4W8",
    "addr:housenumber":"1100",
    "addr:postcode":"g9a 4w8",
    "addr:street":"Rue Notre-Dame Centre Trois-Rivieres",
    "iso:country":"CA",
    "sg:address":"1100 Rue Notre-Dame Centre",
    "sg:city":"Trois-Rivieres",
    "sg:classifiers":[
        {
            "category":"Professional",
            "subcategory":"Accounting & Tax Preparation",
            "type":"Services"
        }
    ],
    "sg:phone":"+1 819 693 0330",
    "sg:postcode":"G9A 4W8",
    "sg:province":"QC",
    "sg:tags":[
        "accountant"
    ],
    "wof:name":"Dumas, Paul CA",
    "wof:placetype":"venue"
},
  "geometry": {"coordinates":[-72.489403,46.378483],"type":"Point"}
}