{
  "type": "Feature",
  "properties": {
    "addr:full":"307 Pefferlaw Rd Pefferlaw ON L0E 1N0",
    "addr:housenumber":"307",
    "addr:postcode":"l0e 1n0",
    "addr:street":"Pefferlaw Rd",
    "iso:country":"CA",
    "sg:address":"307 Pefferlaw Rd",
    "sg:city":"Pefferlaw",
    "sg:classifiers":[
        {
            "category":"Shopping",
            "subcategory":"Used Merchandise",
            "type":"Retail Goods"
        }
    ],
    "sg:phone":"+1 705 437 2079",
    "sg:postcode":"L0E 1N0",
    "sg:province":"ON",
    "sg:tags":[
        "antique"
    ],
    "wof:name":"Pefferlaw Antique Shoppe",
    "wof:placetype":"venue"
},
  "geometry": {"coordinates":[-79.2047195435,44.3151397705],"type":"Point"}
}