{
  "type": "Feature",
  "properties": {
    "addr:full":"2525 Howard Ave Windsor ON N8X 3W1",
    "addr:housenumber":"2525",
    "addr:postcode":"n8x 3w1",
    "addr:street":"Howard Ave",
    "iso:country":"CA",
    "sg:address":"2525 Howard Ave",
    "sg:city":"Windsor",
    "sg:classifiers":[
        {
            "category":"Autos & Motor Vehicles",
            "subcategory":"Auto Supplies",
            "type":"Retail Goods"
        }
    ],
    "sg:phone":"+1 519 967 9965",
    "sg:postcode":"N8X 3W1",
    "sg:province":"ON",
    "sg:tags":[
        "automobile",
        "parts"
    ],
    "wof:name":"Part Source",
    "wof:placetype":"venue"
},
  "geometry": {"coordinates":[-83.01280975340001,42.2899932861],"type":"Point"}
}