{
  "type": "Feature",
  "properties": {
    "addr:full":"6934 Greenwood St Burnaby BC V5A 1X8",
    "addr:housenumber":"6934",
    "addr:postcode":"v5a 1x8",
    "addr:street":"Greenwood St",
    "iso:country":"CA",
    "sg:address":"6934 Greenwood St",
    "sg:city":"Burnaby",
    "sg:classifiers":[
        {
            "category":"Wholesale",
            "subcategory":"Groceries",
            "type":"Manufacturing & Wholesale Goods"
        }
    ],
    "sg:phone":"+1 604 420 5100",
    "sg:postcode":"V5A 1X8",
    "sg:province":"BC",
    "sg:tags":[
        "grocer"
    ],
    "wof:name":"Favorite Foods Ltd",
    "wof:placetype":"venue"
},
  "geometry": {"coordinates":[-122.95927399999999,49.256107],"type":"Point"}
}