{
  "type": "Feature",
  "properties": {
    "addr:full":"29 Portland St Dartmouth NS B2Y 1H1",
    "addr:housenumber":"29",
    "addr:postcode":"b2y 1h1",
    "addr:street":"Portland St",
    "iso:country":"CA",
    "sg:address":"29 Portland St",
    "sg:city":"Dartmouth",
    "sg:classifiers":[
        {
            "category":"Restaurant",
            "type":"Food & Drink"
        }
    ],
    "sg:phone":"+1 902 461 0000",
    "sg:postcode":"B2Y 1H1",
    "sg:province":"NS",
    "wof:name":"Revana Pizza",
    "wof:placetype":"venue"
},
  "geometry": {"coordinates":[-63.56772995,44.6648216248],"type":"Point"}
}