{
  "type": "Feature",
  "properties": {
    "addr:full":"1179 Denman St Vancouver BC V6G 2N1",
    "addr:housenumber":"1179",
    "addr:postcode":"v6g 2n1",
    "addr:street":"Denman St",
    "iso:country":"CA",
    "sg:address":"1179 Denman St",
    "sg:city":"Vancouver",
    "sg:classifiers":[
        {
            "category":"Shopping",
            "type":"Retail Goods"
        }
    ],
    "sg:phone":"+1 604 685 4550",
    "sg:postcode":"V6G 2N1",
    "sg:province":"BC",
    "sg:tags":[
        "picture",
        "frame"
    ],
    "wof:name":"Kimprints",
    "wof:placetype":"venue"
},
  "geometry": {"coordinates":[-123.14128100000001,49.287807],"type":"Point"}
}