{
  "type": "Feature",
  "properties": {
    "addr:full":"359 Yonge St Toronto ON M5B 1S1",
    "addr:housenumber":"359",
    "addr:postcode":"m5b 1s1",
    "addr:street":"Yonge St",
    "iso:country":"CA",
    "sg:address":"359 Yonge St",
    "sg:city":"Toronto",
    "sg:classifiers":[
        {
            "category":"Bars & Pubs",
            "type":"Food & Drink"
        }
    ],
    "sg:phone":"+1 416 977 4642",
    "sg:postcode":"M5B 1S1",
    "sg:province":"ON",
    "wof:name":"Zanzibar Tavern",
    "wof:placetype":"venue"
},
  "geometry": {"coordinates":[-79.381485,43.65815],"type":"Point"}
}