{
  "type": "Feature",
  "properties": {
    "addr:full":"1755 Carling Ave Ottawa ON K2A 1C9",
    "addr:housenumber":"1755",
    "addr:postcode":"k2a 1c9",
    "addr:street":"Carling Ave",
    "iso:country":"CA",
    "sg:address":"1755 Carling Ave",
    "sg:city":"Ottawa",
    "sg:classifiers":[
        {
            "category":"Health Services",
            "subcategory":"Chiropractor",
            "type":"Services"
        }
    ],
    "sg:phone":"+1 613 729 6405",
    "sg:postcode":"K2A 1C9",
    "sg:province":"ON",
    "wof:name":"Mc Cooey Chiropractic",
    "wof:placetype":"venue"
},
  "geometry": {"coordinates":[-75.75336456300001,45.3779335022],"type":"Point"}
}