{
  "type": "Feature",
  "properties": {
    "addr:full":"Sarnia ON N7T 7Y1",
    "addr:postcode":"n7t 7y1",
    "iso:country":"CA",
    "sg:city":"Sarnia",
    "sg:classifiers":[
        {
            "category":"Education",
            "subcategory":"Library",
            "type":"Public Place"
        }
    ],
    "sg:phone":"+1 519 337 7836",
    "sg:postcode":"N7T 7Y1",
    "sg:province":"ON",
    "wof:name":"Chippewa Branch Library",
    "wof:placetype":"venue"
},
  "geometry": {"coordinates":[-82.45286560060001,42.9146614075],"type":"Point"}
}