{
  "type": "Feature",
  "properties": {
    "addr:full":"Nelson BC V1L 2V1",
    "addr:postcode":"bc v1l 2v1",
    "iso:country":"CA",
    "sg:city":"Nelson",
    "sg:classifiers":[
        {
            "category":"Health Services",
            "subcategory":"Doctor",
            "type":"Services"
        }
    ],
    "sg:phone":"+1 250 352 9766",
    "sg:postcode":"V1L 2V1",
    "sg:province":"BC",
    "sg:tags":[
        "physician",
        "surgeon"
    ],
    "wof:name":"Fitzsimons, Carrie MD",
    "wof:placetype":"venue"
},
  "geometry": {"coordinates":[-117.285690308,49.4936256409],"type":"Point"}
}