{
  "type": "Feature",
  "properties": {
    "addr:full":"145 Rue Principale Cowansville QC J2K 1J3",
    "addr:housenumber":"145",
    "addr:postcode":"j2k 1j3",
    "addr:street":"Rue Principale",
    "iso:country":"CA",
    "sg:address":"145 Rue Principale",
    "sg:city":"Cowansville",
    "sg:classifiers":[
        {
            "category":"Professional",
            "subcategory":"Business Services",
            "type":"Services"
        }
    ],
    "sg:phone":"+1 450 263 7669",
    "sg:postcode":"J2K 1J3",
    "sg:province":"QC",
    "sg:tags":[
        "event"
    ],
    "wof:name":"Musique En Vue",
    "wof:placetype":"venue"
},
  "geometry": {"coordinates":[-72.7461853027,45.207901001],"type":"Point"}
}