{
  "type": "Feature",
  "properties": {
    "addr:full":"Hwy 200 S Dominion City MB R0A 0H0",
    "addr:postcode":"r0a 0h0",
    "addr:street":"Hwy 200 S Dominion",
    "iso:country":"CA",
    "sg:address":"Hwy 200 S",
    "sg:city":"Dominion City",
    "sg:classifiers":[
        {
            "category":"Freight",
            "type":"Transportation"
        }
    ],
    "sg:phone":"+1 204 427 2741",
    "sg:postcode":"R0A 0H0",
    "sg:province":"MB",
    "sg:tags":[
        "grain",
        "elevator"
    ],
    "wof:name":"Cargill Limited",
    "wof:placetype":"venue"
},
  "geometry": {"coordinates":[-97.150642,49.13345],"type":"Point"}
}