{
  "type": "Feature",
  "properties": {
    "addr:full":"Regina SK S4P 2C5",
    "addr:postcode":"s4p 2c5",
    "iso:country":"CA",
    "sg:city":"Regina",
    "sg:classifiers":[
        {
            "category":"Organizations",
            "subcategory":"Professional Association",
            "type":"Services"
        }
    ],
    "sg:phone":"+1 306 352 2555",
    "sg:postcode":"S4P 2C5",
    "sg:province":"SK",
    "sg:tags":[
        "counseling"
    ],
    "wof:name":"Brass & Assoc Consultation Svc",
    "wof:placetype":"venue"
},
  "geometry": {"coordinates":[-104.609604,50.448135],"type":"Point"}
}