{
  "type": "Feature",
  "properties": {
    "iso:country":"CA",
    "sg:address":"4900 Golf Course Rd",
    "sg:city":"Stony Plain",
    "sg:classifiers":[
        {
            "category":"Manufacturing",
            "subcategory":"Motor Vehicles & Parts",
            "type":"Manufacturing & Wholesale Goods"
        }
    ],
    "sg:phone":"+1 780 968 4679",
    "sg:postcode":"T7Z 1W4",
    "sg:province":"AB",
    "sg:tags":[
        "trailer"
    ],
    "wof:name":"Marcep Manufacturing Ltd",
    "wof:placetype":"venue"
},
  "geometry": {"coordinates":[-113.983818,53.533333],"type":"Point"}
}