{
  "type": "Feature",
  "properties": {
    "addr:full":"Montreal QC H3S 1Z4",
    "addr:postcode":"h3s 1z4",
    "iso:country":"CA",
    "sg:city":"Montreal",
    "sg:classifiers":[
        {
            "category":"Health Services",
            "subcategory":"Medical Lab",
            "type":"Services"
        }
    ],
    "sg:phone":"+1 514 341 6590",
    "sg:postcode":"H3S 1Z4",
    "sg:province":"QC",
    "sg:tags":[
        "laboratory"
    ],
    "wof:name":"Laboratoire Cyto-Stat",
    "wof:placetype":"venue"
},
  "geometry": {"coordinates":[-73.6300582886,45.4999961853],"type":"Point"}
}