{
  "type": "Feature",
  "properties": {
    "addr:full":"411 58 Ave SE Calgary AB T2H 0P5",
    "addr:postcode":"t2h 0p5",
    "addr:street":"411 58 Ave Se",
    "iso:country":"CA",
    "sg:address":"411 58 Ave SE",
    "sg:city":"Calgary",
    "sg:classifiers":[
        {
            "category":"Banks & Credit Unions",
            "subcategory":"Bank",
            "type":"Services"
        }
    ],
    "sg:phone":"+1 403 292 8200",
    "sg:postcode":"T2H 0P5",
    "sg:province":"AB",
    "wof:name":"Royal Bank Financial Group",
    "wof:placetype":"venue"
},
  "geometry": {"coordinates":[-114.056488,51.001205],"type":"Point"}
}