{
  "type": "Feature",
  "properties": {
    "addr:full":"Quebec QC G1S 4M6",
    "addr:postcode":"g1s 4m6",
    "iso:country":"CA",
    "sg:city":"Quebec",
    "sg:classifiers":[
        {
            "category":"Sports & Exercise",
            "subcategory":"Gym",
            "type":"Entertainment"
        }
    ],
    "sg:phone":"+1 418 527 2577",
    "sg:postcode":"G1S 4M6",
    "sg:province":"QC",
    "sg:tags":[
        "club",
        "health",
        "studio",
        "gymnasium"
    ],
    "wof:name":"Nautilus Plus Inc",
    "wof:placetype":"venue"
},
  "geometry": {"coordinates":[-71.25048099999999,46.795357],"type":"Point"}
}