{
  "type": "Feature",
  "properties": {
    "addr:full":"70 Crane Lake Dr Halifax NS B3S 1B4",
    "addr:housenumber":"70",
    "addr:postcode":"b3s 1b4",
    "addr:street":"Crane Lake Dr",
    "iso:country":"CA",
    "sg:address":"70 Crane Lake Dr",
    "sg:city":"Halifax",
    "sg:classifiers":[
        {
            "category":"Shopping",
            "subcategory":"Stationery & Office Supplies",
            "type":"Retail Goods"
        }
    ],
    "sg:phone":"+1 902 450 1258",
    "sg:postcode":"B3S 1B4",
    "sg:province":"NS",
    "wof:name":"Grand & Toy Custom Business",
    "wof:placetype":"venue"
},
  "geometry": {"coordinates":[-63.6681671143,44.6396331787],"type":"Point"}
}