{
  "type": "Feature",
  "properties": {
    "addr:full":"Toronto ON M4N 3N1",
    "addr:postcode":"m4n 3n1",
    "iso:country":"CA",
    "sg:city":"Toronto",
    "sg:classifiers":[
        {
            "category":"Food & Beverages",
            "subcategory":"Groceries & Convenience Stores",
            "type":"Retail Goods"
        }
    ],
    "sg:phone":"+1 416 489 1650",
    "sg:postcode":"M4N 3N1",
    "sg:province":"ON",
    "wof:name":"Village Shop",
    "wof:placetype":"venue"
},
  "geometry": {"coordinates":[-79.40245819090001,43.7254180908],"type":"Point"}
}