{
  "type": "Feature",
  "properties": {
    "addr:full":"Alliston ON L9R 1E6",
    "addr:postcode":"l9r 1e6",
    "addr:street":"Alliston",
    "iso:country":"CA",
    "sg:city":"Alliston",
    "sg:classifiers":[
        {
            "category":"Professional",
            "subcategory":"Accounting & Tax Preparation",
            "type":"Services"
        }
    ],
    "sg:phone":"+1 705 435 5585",
    "sg:postcode":"L9R 1E6",
    "sg:province":"ON",
    "sg:tags":[
        "accountant"
    ],
    "wof:name":"Bdo Dunwoody Ltd",
    "wof:placetype":"venue"
},
  "geometry": {"coordinates":[-79.8622055054,44.1479301453],"type":"Point"}
}