{
  "type": "Feature",
  "properties": {
    "addr:full":"Farm Hwy 6 N Southey SK S0G 4P0",
    "addr:postcode":"s0g 4p0",
    "addr:street":"Farm Hwy 6 N",
    "iso:country":"CA",
    "sg:address":"Farm Hwy 6 N",
    "sg:city":"Southey",
    "sg:classifiers":[
        {
            "category":"Autos & Motor Vehicles",
            "subcategory":"Recreational Vehicle Sales",
            "type":"Retail Goods"
        }
    ],
    "sg:phone":"+1 306 726 4403",
    "sg:postcode":"S0G 4P0",
    "sg:province":"SK",
    "sg:tags":[
        "parts",
        "trailer"
    ],
    "wof:name":"Flaman Sales Ltd",
    "wof:placetype":"venue"
},
  "geometry": {"coordinates":[-104.49604034399999,50.940410614],"type":"Point"}
}