{
  "type": "Feature",
  "properties": {
    "addr:full":"15686 Highway 97 Oyama BC V4V 2G4",
    "addr:housenumber":"15686",
    "addr:postcode":"v4v 2g4",
    "addr:street":"Highway 97",
    "iso:country":"CA",
    "sg:address":"15686 Highway 97",
    "sg:city":"Oyama",
    "sg:classifiers":[
        {
            "category":"Food & Beverages",
            "subcategory":"Fruits & Vegetables",
            "type":"Retail Goods"
        }
    ],
    "sg:phone":"+1 250 548 3444",
    "sg:postcode":"V4V 2G4",
    "sg:province":"BC",
    "sg:tags":[
        "produce"
    ],
    "wof:name":"Gatzke Orchards",
    "wof:placetype":"venue"
},
  "geometry": {"coordinates":[-119.372116089,50.1086273193],"type":"Point"}
}