{
  "type": "Feature",
  "properties": {
    "addr:full":"Owen Sound ON N4K 6A8",
    "addr:postcode":"n4k 6a8",
    "iso:country":"CA",
    "sg:city":"Owen Sound",
    "sg:classifiers":[
        {
            "category":"Professional",
            "subcategory":"Computer Services",
            "type":"Services"
        }
    ],
    "sg:phone":"+1 519 371 0203",
    "sg:postcode":"N4K 6A8",
    "sg:province":"ON",
    "sg:tags":[
        "repair",
        "dealer",
        "equipment"
    ],
    "wof:name":"Pci Computers Direct",
    "wof:placetype":"venue"
},
  "geometry": {"coordinates":[-80.925133,44.573654],"type":"Point"}
}