{
  "type": "Feature",
  "properties": {
    "addr:full":"1108 Rosedale Ave Thunder Bay ON P7C 2L5",
    "addr:housenumber":"1108",
    "addr:postcode":"p7c 2l5",
    "addr:street":"Rosedale Ave",
    "iso:country":"CA",
    "sg:address":"1108 Rosedale Ave",
    "sg:city":"Thunder Bay",
    "sg:classifiers":[
        {
            "category":"Building & Trades",
            "subcategory":"Landscaping Services",
            "type":"Services"
        }
    ],
    "sg:phone":"+1 807 622 3807",
    "sg:postcode":"P7C 2L5",
    "sg:province":"ON",
    "sg:tags":[
        "landscape",
        "contractor"
    ],
    "wof:name":"Woods Landscaping",
    "wof:placetype":"venue"
},
  "geometry": {"coordinates":[-89.25267028810001,48.3915672302],"type":"Point"}
}