{
  "type": "Feature",
  "properties": {
    "addr:full":"Harrowsmith ON K0H 1V0",
    "addr:postcode":"k0h 1v0",
    "iso:country":"CA",
    "sg:city":"Harrowsmith",
    "sg:classifiers":[
        {
            "category":"Autos & Motor Vehicles",
            "subcategory":"Motorcycle Sales",
            "type":"Retail Goods"
        }
    ],
    "sg:phone":"+1 613 372 1280",
    "sg:postcode":"K0H 1V0",
    "sg:province":"ON",
    "sg:tags":[
        "all",
        "terrain"
    ],
    "wof:name":"Performance Shed",
    "wof:placetype":"venue"
},
  "geometry": {"coordinates":[-76.66557299999999,44.404995],"type":"Point"}
}