{
  "type": "Feature",
  "properties": {
    "addr:full":"Thamesford ON N0M 2M0",
    "addr:postcode":"n0m 2m0",
    "iso:country":"CA",
    "sg:city":"Thamesford",
    "sg:classifiers":[
        {
            "category":"Insurance",
            "subcategory":"Insurance Agent",
            "type":"Services"
        }
    ],
    "sg:phone":"+1 519 285 3514",
    "sg:postcode":"N0M 2M0",
    "sg:province":"ON",
    "wof:name":"Greg Stewart Insurance",
    "wof:placetype":"venue"
},
  "geometry": {"coordinates":[-80.99859600000001,43.058342],"type":"Point"}
}