{
  "type": "Feature",
  "properties": {
    "iso:country":"CA",
    "sg:address":"4940 Rue Fisher",
    "sg:city":"Saint-Laurent",
    "sg:classifiers":[
        {
            "category":"Manufacturing",
            "subcategory":"Tools & Machinery",
            "type":"Manufacturing & Wholesale Goods"
        }
    ],
    "sg:phone":"+1 514 341 2004",
    "sg:postcode":"H4T 1J5",
    "sg:province":"QC",
    "sg:tags":[
        "refrigeration",
        "refrigerating"
    ],
    "wof:name":"Quebec Refrigeration Cie Inc",
    "wof:placetype":"venue"
},
  "geometry": {"coordinates":[-73.6986618042,45.47032547],"type":"Point"}
}