{
  "type": "Feature",
  "properties": {
    "addr:full":"156 Tupper Ave Yorkton SK S3N 1L5",
    "addr:housenumber":"156",
    "addr:postcode":"s3n 1l5",
    "addr:street":"Tupper Ave",
    "iso:country":"CA",
    "sg:address":"156 Tupper Ave",
    "sg:city":"Yorkton",
    "sg:classifiers":[
        {
            "category":"Building & Trades",
            "subcategory":"Electrical",
            "type":"Services"
        }
    ],
    "sg:phone":"+1 306 782 5500",
    "sg:postcode":"S3N 1L5",
    "sg:province":"SK",
    "sg:tags":[
        "electric",
        "contractor"
    ],
    "wof:name":"Yellowhead Electric",
    "wof:placetype":"venue"
},
  "geometry": {"coordinates":[-102.46294399999999,51.204193],"type":"Point"}
}