{
  "type": "Feature",
  "properties": {
    "addr:full":"1627 127 St Surrey BC V4A 9G2",
    "addr:housenumber":"1627",
    "addr:postcode":"v4a 9g2",
    "addr:street":"127 St",
    "iso:country":"CA",
    "sg:address":"1627 127 St",
    "sg:city":"Surrey",
    "sg:classifiers":[
        {
            "category":"Professional",
            "subcategory":"Management & Consulting",
            "type":"Services"
        }
    ],
    "sg:phone":"+1 604 535 5083",
    "sg:postcode":"V4A 9G2",
    "sg:province":"BC",
    "sg:tags":[
        "consultant",
        "business"
    ],
    "wof:name":"Western Economic Consulting",
    "wof:placetype":"venue"
},
  "geometry": {"coordinates":[-122.870544434,49.031879425],"type":"Point"}
}