{
  "type": "Feature",
  "properties": {
    "addr:full":"1213 Rue Labadie Longueuil QC J4N 1E2",
    "addr:housenumber":"1213",
    "addr:postcode":"j4n 1e2",
    "addr:street":"Rue Labadie",
    "iso:country":"CA",
    "sg:address":"1213 Rue Labadie",
    "sg:city":"Longueuil",
    "sg:classifiers":[
        {
            "category":"Wholesale",
            "subcategory":"Chemicals & Plastics",
            "type":"Manufacturing & Wholesale Goods"
        }
    ],
    "sg:phone":"+1 450 442 0603",
    "sg:postcode":"J4N 1E2",
    "sg:province":"QC",
    "sg:tags":[
        "concrete",
        "additive"
    ],
    "wof:name":"Altec Inc",
    "wof:placetype":"venue"
},
  "geometry": {"coordinates":[-73.45519256590001,45.5639152527],"type":"Point"}
}