{
  "type": "Feature",
  "properties": {
    "addr:full":"Mississauga ON L5B 2C9",
    "addr:postcode":"l5b 2c9",
    "iso:country":"CA",
    "sg:city":"Mississauga",
    "sg:classifiers":[
        {
            "category":"Shopping",
            "subcategory":"Clothing, Apparel, & Fashions",
            "type":"Retail Goods"
        }
    ],
    "sg:phone":"+1 905 848 0235",
    "sg:postcode":"L5B 2C9",
    "sg:province":"ON",
    "wof:name":"Femme DE Carriere",
    "wof:placetype":"venue"
},
  "geometry": {"coordinates":[-79.639511,43.592094],"type":"Point"}
}