{
  "type": "Feature",
  "properties": {
    "addr:full":"145 Castlefrank Rd Kanata ON K2L 3X9",
    "addr:housenumber":"145",
    "addr:postcode":"k2l 3x9",
    "addr:street":"Castlefrank Rd",
    "iso:country":"CA",
    "sg:address":"145 Castlefrank Rd",
    "sg:city":"Kanata",
    "sg:classifiers":[
        {
            "category":"Health Services",
            "subcategory":"Nursing And Care Facility",
            "type":"Services"
        }
    ],
    "sg:phone":"+1 613 831 3333",
    "sg:postcode":"K2L 3X9",
    "sg:province":"ON",
    "sg:tags":[
        "home",
        "retirement",
        "community"
    ],
    "wof:name":"Kanata Retirement Residence",
    "wof:placetype":"venue"
},
  "geometry": {"coordinates":[-75.879929,45.291557],"type":"Point"}
}