{
  "type": "Feature",
  "properties": {
    "addr:full":"Drummondville QC J2B 7Y9",
    "addr:postcode":"j2b 7y9",
    "iso:country":"CA",
    "sg:city":"Drummondville",
    "sg:classifiers":[
        {
            "category":"Real Estate",
            "subcategory":"Real Estate Operator",
            "type":"Services"
        }
    ],
    "sg:phone":"+1 819 478 8502",
    "sg:postcode":"J2B 7Y9",
    "sg:province":"QC",
    "sg:tags":[
        "home",
        "apartment",
        "community",
        "retirement"
    ],
    "wof:name":"Terrasses Imdrum",
    "wof:placetype":"venue"
},
  "geometry": {"coordinates":[-72.4825210571,45.8783378601],"type":"Point"}
}