{
  "type": "Feature",
  "properties": {
    "addr:full":"202 18 Ave NE Calgary AB T2E 1N2",
    "addr:housenumber":"202",
    "addr:postcode":"t2e 1n2",
    "addr:street":"18 Ave Ne",
    "iso:country":"CA",
    "sg:address":"202 18 Ave NE",
    "sg:city":"Calgary",
    "sg:classifiers":[
        {
            "category":"Building & Trades",
            "subcategory":"Construction",
            "type":"Services"
        }
    ],
    "sg:phone":"+1 403 288 4892",
    "sg:postcode":"T2E 1N2",
    "sg:province":"AB",
    "sg:tags":[
        "painter"
    ],
    "wof:name":"Van Putten Painting & Decor",
    "wof:placetype":"venue"
},
  "geometry": {"coordinates":[-114.05947876,51.0689353943],"type":"Point"}
}