{
  "type": "Feature",
  "properties": {
    "addr:full":"98 Broadway Corner Brook NL A2H 4C8",
    "addr:housenumber":"98",
    "addr:postcode":"a2h 4c8",
    "addr:street":"Broadway",
    "iso:country":"CA",
    "sg:address":"98 Broadway",
    "sg:city":"Corner Brook",
    "sg:classifiers":[
        {
            "category":"Professional",
            "subcategory":"Accounting & Tax Preparation",
            "type":"Services"
        }
    ],
    "sg:phone":"+1 709 639 7774",
    "sg:postcode":"A2H 4C8",
    "sg:province":"NL",
    "sg:tags":[
        "accountant"
    ],
    "wof:name":"J Pike & CO",
    "wof:placetype":"venue"
},
  "geometry": {"coordinates":[-57.955853,48.952999],"type":"Point"}
}