{
  "type": "Feature",
  "properties": {
    "addr:full":"11005 11th Conc Mcgregor ON N0R 1J0",
    "addr:housenumber":"11005",
    "addr:postcode":"n0r 1j0",
    "addr:street":"11Th Conc",
    "iso:country":"CA",
    "sg:address":"11005 11th Conc",
    "sg:city":"Mcgregor",
    "sg:classifiers":[
        {
            "category":"Personal",
            "subcategory":"Beauty Salon",
            "type":"Services"
        }
    ],
    "sg:phone":"+1 519 726 4449",
    "sg:postcode":"N0R 1J0",
    "sg:province":"ON",
    "wof:name":"Terri's Place of Haircare",
    "wof:placetype":"venue"
},
  "geometry": {"coordinates":[-82.969612,42.139332],"type":"Point"}
}