{
  "type": "Feature",
  "properties": {
    "addr:full":"440 Central Ave Thunder Bay ON P7B 6B4",
    "addr:housenumber":"440",
    "addr:postcode":"p7b 6b4",
    "addr:street":"Central Ave",
    "iso:country":"CA",
    "sg:address":"440 Central Ave",
    "sg:city":"Thunder Bay",
    "sg:classifiers":[
        {
            "category":"Freight",
            "type":"Transportation"
        }
    ],
    "sg:phone":"+1 807 626 4716",
    "sg:postcode":"P7B 6B4",
    "sg:province":"ON",
    "sg:tags":[
        "trucking",
        "general",
        "contractor"
    ],
    "wof:name":"G Stilla & Sons Contracting",
    "wof:placetype":"venue"
},
  "geometry": {"coordinates":[-89.231255,48.417233],"type":"Point"}
}