{
  "type": "Feature",
  "properties": {
    "addr:full":"396 Ch Du Grand-Bernier N Saint-Jean-Sur-Richelieu QC J3B 4R8",
    "addr:housenumber":"396",
    "addr:postcode":"j3b 4r8",
    "addr:street":"Ch Du Grand-Bernier N",
    "iso:country":"CA",
    "sg:address":"396 Ch Du Grand-Bernier N",
    "sg:city":"Saint-Jean-Sur-Richelieu",
    "sg:classifiers":[
        {
            "category":"Manufacturing",
            "subcategory":"Signs",
            "type":"Manufacturing & Wholesale Goods"
        }
    ],
    "sg:phone":"+1 450 347 0313",
    "sg:postcode":"J3B 4R8",
    "sg:province":"QC",
    "wof:name":"Enseignes Perfection Inc",
    "wof:placetype":"venue"
},
  "geometry": {"coordinates":[-73.293258667,45.3097000122],"type":"Point"}
}