{
  "type": "Feature",
  "properties": {
    "addr:full":"291 Ave Principale Lambton QC G0M 1H0",
    "addr:housenumber":"291",
    "addr:postcode":"g0m 1h0",
    "addr:street":"Ave Principale",
    "iso:country":"CA",
    "sg:address":"291 Ave Principale",
    "sg:city":"Lambton",
    "sg:classifiers":[
        {
            "category":"Home & Garden",
            "subcategory":"Carpets & Floor Coverings",
            "type":"Retail Goods"
        }
    ],
    "sg:phone":"+1 418 486 7165",
    "sg:postcode":"G0M 1H0",
    "sg:province":"QC",
    "sg:tags":[
        "resurfacing",
        "material",
        "laying",
        "refinishing"
    ],
    "wof:name":"Laurent Fortin Inc",
    "wof:placetype":"venue"
},
  "geometry": {"coordinates":[-71.0953292847,45.8294067383],"type":"Point"}
}