{
  "type": "Feature",
  "properties": {
    "addr:full":"77 Clarence St W Port Colborne ON L3K 3G2",
    "addr:housenumber":"77",
    "addr:postcode":"l3k 3g2",
    "addr:street":"Clarence St W",
    "iso:country":"CA",
    "sg:address":"77 Clarence St W",
    "sg:city":"Port Colborne",
    "sg:classifiers":[
        {
            "category":"Shopping",
            "subcategory":"Pharmacy",
            "type":"Retail Goods"
        }
    ],
    "sg:phone":"+1 905 835 0000",
    "sg:postcode":"L3K 3G2",
    "sg:province":"ON",
    "wof:name":"Matheson's Drug Store",
    "wof:placetype":"venue"
},
  "geometry": {"coordinates":[-79.25318145750001,42.8862571716],"type":"Point"}
}