{
  "type": "Feature",
  "properties": {
    "addr:full":"108 Niska Rd Guelph ON N1C 1A5",
    "addr:housenumber":"108",
    "addr:postcode":"n1c 1a5",
    "addr:street":"Niska Rd",
    "iso:country":"CA",
    "sg:address":"108 Niska Rd",
    "sg:city":"Guelph",
    "sg:classifiers":[
        {
            "category":"Professional",
            "subcategory":"Management & Consulting",
            "type":"Services"
        }
    ],
    "sg:phone":"+1 519 822 5490",
    "sg:postcode":"N1C 1A5",
    "sg:province":"ON",
    "sg:tags":[
        "consultant",
        "training",
        "sales",
        "business"
    ],
    "wof:name":"Performance Plus Training",
    "wof:placetype":"venue"
},
  "geometry": {"coordinates":[-80.24195899999999,43.504307],"type":"Point"}
}