{
  "type": "Feature",
  "properties": {
    "addr:full":"2575 Hwy 206 Arichat NS B0E 1A0",
    "addr:housenumber":"2575",
    "addr:postcode":"b0e 1a0",
    "addr:street":"Hwy 206",
    "iso:country":"CA",
    "sg:address":"2575 Hwy 206",
    "sg:city":"Arichat",
    "sg:classifiers":[
        {
            "category":"Government",
            "subcategory":"Office",
            "type":"Public Place"
        }
    ],
    "sg:phone":"+1 902 226 2818",
    "sg:postcode":"B0E 1A0",
    "sg:province":"NS",
    "wof:name":"Nova Scotia Registry of Deeds",
    "wof:placetype":"venue"
},
  "geometry": {"coordinates":[-61.016502,45.511856],"type":"Point"}
}