{
  "type": "Feature",
  "properties": {
    "addr:full":"3921 Seminole St Windsor ON N8Y 1Z1",
    "addr:housenumber":"3921",
    "addr:postcode":"n8y 1z1",
    "addr:street":"Seminole St",
    "iso:country":"CA",
    "sg:address":"3921 Seminole St",
    "sg:city":"Windsor",
    "sg:classifiers":[
        {
            "category":"Home & Garden",
            "subcategory":"Household Appliances",
            "type":"Retail Goods"
        }
    ],
    "sg:phone":"+1 519 945 5558",
    "sg:postcode":"N8Y 1Z1",
    "sg:province":"ON",
    "sg:tags":[
        "equipment",
        "satellite",
        "system"
    ],
    "wof:name":"Quick Tv Svc & Repair",
    "wof:placetype":"venue"
},
  "geometry": {"coordinates":[-82.9832000732,42.3156852722],"type":"Point"}
}