{
  "type": "Feature",
  "properties": {
    "iso:country":"CA",
    "sg:address":"274 Ch Bates",
    "sg:city":"Mont-Royal",
    "sg:classifiers":[
        {
            "category":"Manufacturing",
            "subcategory":"Tools & Machinery",
            "type":"Manufacturing & Wholesale Goods"
        }
    ],
    "sg:phone":"+1 514 737 4040",
    "sg:postcode":"H3S 1A3",
    "sg:province":"QC",
    "sg:tags":[
        "lighting",
        "fixture"
    ],
    "wof:name":"Shemoi Enterprises",
    "wof:placetype":"venue"
},
  "geometry": {"coordinates":[-73.628952,45.515564],"type":"Point"}
}