{
  "type": "Feature",
  "properties": {
    "addr:full":"Napierville QC J0J 1L0",
    "addr:postcode":"j0j 1l0",
    "iso:country":"CA",
    "sg:city":"Napierville",
    "sg:classifiers":[
        {
            "category":"Recreation",
            "type":"Entertainment"
        }
    ],
    "sg:phone":"+1 450 245 3464",
    "sg:postcode":"J0J 1L0",
    "sg:province":"QC",
    "sg:tags":[
        "club",
        "hockey"
    ],
    "wof:name":"Hockey Mineur DE Beaujeu",
    "wof:placetype":"venue"
},
  "geometry": {"coordinates":[-73.40199279789999,45.1931724548],"type":"Point"}
}