{
  "type": "Feature",
  "properties": {
    "addr:full":"Richmond BC V7E 3A6",
    "addr:postcode":"v7e 3a6",
    "iso:country":"CA",
    "sg:city":"Richmond",
    "sg:classifiers":[
        {
            "category":"Shopping",
            "type":"Retail Goods"
        }
    ],
    "sg:phone":"+1 604 275 5530",
    "sg:postcode":"V7E 3A6",
    "sg:province":"BC",
    "sg:tags":[
        "cards",
        "baseball",
        "toy",
        "sport",
        "memorabilia"
    ],
    "wof:name":"John's Collectibles & Sports",
    "wof:placetype":"venue"
},
  "geometry": {"coordinates":[-123.183136,49.12505],"type":"Point"}
}