{
  "type": "Feature",
  "properties": {
    "addr:full":"Vancouver BC V6C 1H2",
    "addr:postcode":"v6c 1h2",
    "iso:country":"CA",
    "sg:city":"Vancouver",
    "sg:classifiers":[
        {
            "category":"Banks & Credit Unions",
            "subcategory":"Investment Brokerage",
            "type":"Services"
        }
    ],
    "sg:phone":"+1 604 685 3193",
    "sg:postcode":"V6C 1H2",
    "sg:province":"BC",
    "sg:tags":[
        "funds",
        "mutual"
    ],
    "wof:name":"Sagit Investment Mgmnt Ltd",
    "wof:placetype":"venue"
},
  "geometry": {"coordinates":[-123.115478516,49.2852706909],"type":"Point"}
}