{
  "type": "Feature",
  "properties": {
    "addr:full":"2202 Cassiar St Vancouver BC V5M 3W9",
    "addr:housenumber":"2202",
    "addr:postcode":"v5m 3w9",
    "addr:street":"Cassiar St",
    "iso:country":"CA",
    "sg:address":"2202 Cassiar St",
    "sg:city":"Vancouver",
    "sg:classifiers":[
        {
            "category":"Organizations",
            "subcategory":"Professional Association",
            "type":"Services"
        }
    ],
    "sg:phone":"+1 604 255 0021",
    "sg:postcode":"V5M 3W9",
    "sg:province":"BC",
    "wof:name":"Skeena Terrace Tenants Assn",
    "wof:placetype":"venue"
},
  "geometry": {"coordinates":[-123.03078499999999,49.264565],"type":"Point"}
}