{
  "type": "Feature",
  "properties": {
    "addr:full":"21 Union St Brampton ON L6V 1R3",
    "addr:housenumber":"21",
    "addr:postcode":"l6v 1r3",
    "addr:street":"Union St",
    "iso:country":"CA",
    "sg:address":"21 Union St",
    "sg:city":"Brampton",
    "sg:classifiers":[
        {
            "category":"Retail",
            "subcategory":"Auto Repair",
            "type":"Services"
        }
    ],
    "sg:phone":"+1 905 451 3219",
    "sg:postcode":"L6V 1R3",
    "sg:province":"ON",
    "sg:tags":[
        "transmission",
        "automobile",
        "repairing"
    ],
    "wof:name":"Mc Cracken Auto Svc Ltd",
    "wof:placetype":"venue"
},
  "geometry": {"coordinates":[-79.76033,43.688328],"type":"Point"}
}