{
  "type": "Feature",
  "properties": {
    "addr:full":"400 Boul Saint-Martin O Laval QC H7M 3Y8",
    "addr:housenumber":"400",
    "addr:postcode":"h7m 3y8",
    "addr:street":"Boul Saint-Martin O",
    "iso:country":"CA",
    "sg:address":"400 Boul Saint-Martin O",
    "sg:city":"Laval",
    "sg:classifiers":[
        {
            "category":"Professional",
            "subcategory":"Business Services",
            "type":"Services"
        }
    ],
    "sg:phone":"+1 450 663 1905",
    "sg:postcode":"H7M 3Y8",
    "sg:province":"QC",
    "sg:tags":[
        "water",
        "treatment"
    ],
    "wof:name":"Prominent Fluid Controls Ltd",
    "wof:placetype":"venue"
},
  "geometry": {"coordinates":[-73.710579,45.577744],"type":"Point"}
}