{
  "type": "Feature",
  "properties": {
    "iso:country":"CA",
    "sg:address":"17912 107 Ave NW",
    "sg:city":"Edmonton",
    "sg:classifiers":[
        {
            "category":"Wholesale",
            "subcategory":"Electrical",
            "type":"Manufacturing & Wholesale Goods"
        }
    ],
    "sg:phone":"+1 780 484 1478",
    "sg:postcode":"T5S 1J1",
    "sg:province":"AB",
    "sg:tags":[
        "automobile",
        "parts",
        "supply"
    ],
    "wof:name":"Chrismar Battery Ltd",
    "wof:placetype":"venue"
},
  "geometry": {"coordinates":[-113.629005432,53.5534858704],"type":"Point"}
}