{
  "type": "Feature",
  "properties": {
    "addr:full":"Surrey BC V3W 0A6",
    "addr:postcode":"v3w 0a6",
    "iso:country":"CA",
    "sg:city":"Surrey",
    "sg:classifiers":[
        {
            "category":"Wholesale",
            "subcategory":"Apparel",
            "type":"Manufacturing & Wholesale Goods"
        }
    ],
    "sg:phone":"+1 604 592 7553",
    "sg:postcode":"V3W 0A6",
    "sg:province":"BC",
    "sg:tags":[
        "clothing"
    ],
    "wof:name":"J N Alvit Canada",
    "wof:placetype":"venue"
},
  "geometry": {"coordinates":[-122.865562439,49.1538543701],"type":"Point"}
}