{
  "type": "Feature",
  "properties": {
    "addr:full":"755 Boul Saint-Jean-Baptiste Mercier QC J6R 1G1",
    "addr:housenumber":"755",
    "addr:postcode":"j6r 1g1",
    "addr:street":"Boul Saint-Jean-Baptiste",
    "iso:country":"CA",
    "sg:address":"755 Boul Saint-Jean-Baptiste",
    "sg:city":"Mercier",
    "sg:classifiers":[
        {
            "category":"Education",
            "subcategory":"Dance Studio",
            "type":"Public Place"
        }
    ],
    "sg:phone":"+1 450 692 3465",
    "sg:postcode":"J6R 1G1",
    "sg:province":"QC",
    "sg:tags":[
        "instruction",
        "dancing"
    ],
    "wof:name":"Centre DE Danse Primeau",
    "wof:placetype":"venue"
},
  "geometry": {"coordinates":[-73.742165,45.316143],"type":"Point"}
}