{
  "type": "Feature",
  "properties": {
    "iso:country":"CA",
    "sg:address":"General Delivery",
    "sg:city":"Whiteway",
    "sg:classifiers":[
        {
            "category":"Government",
            "subcategory":"Office",
            "type":"Public Place"
        }
    ],
    "sg:phone":"+1 709 588 2948",
    "sg:postcode":"A0B 3L0",
    "sg:province":"NL",
    "sg:tags":[
        "village"
    ],
    "wof:name":"Community Council of Whiteway",
    "wof:placetype":"venue"
},
  "geometry": {"coordinates":[-53.4854507446,47.6654129028],"type":"Point"}
}