{
  "type": "Feature",
  "properties": {
    "addr:full":"44 Mount Pleasant St St George NB E5C 3K4",
    "addr:housenumber":"44",
    "addr:postcode":"e5c 3k4",
    "addr:street":"Mount Pleasant St",
    "iso:country":"CA",
    "sg:address":"44 Mount Pleasant St",
    "sg:city":"St George",
    "sg:classifiers":[
        {
            "category":"Education",
            "subcategory":"Vocational School",
            "type":"Public Place"
        }
    ],
    "sg:phone":"+1 506 755 7713",
    "sg:postcode":"E5C 3K4",
    "sg:province":"NB",
    "sg:tags":[
        "training",
        "computer"
    ],
    "wof:name":"St George Community Access",
    "wof:placetype":"venue"
},
  "geometry": {"coordinates":[-66.8196182251,45.130531311],"type":"Point"}
}