{
  "type": "Feature",
  "properties": {
    "iso:country":"CA",
    "sg:address":"165 County Rd 6 S",
    "sg:city":"Perkinsfield",
    "sg:classifiers":[
        {
            "category":"Home & Garden",
            "subcategory":"Furniture",
            "type":"Retail Goods"
        }
    ],
    "sg:phone":"+1 705 527 6116",
    "sg:postcode":"L0L 2J0",
    "sg:province":"ON",
    "sg:tags":[
        "equipment",
        "builder",
        "custom",
        "kitchen",
        "cabinet"
    ],
    "wof:name":"Perkinsfield Kitchen & Bath",
    "wof:placetype":"venue"
},
  "geometry": {"coordinates":[-79.96974945069999,44.7073822021],"type":"Point"}
}