{
  "type": "Feature",
  "properties": {
    "addr:full":"Saint-Remi QC J0L 2L0",
    "addr:postcode":"j0l 2l0",
    "iso:country":"CA",
    "sg:city":"Saint-Remi",
    "sg:classifiers":[
        {
            "category":"Food & Beverages",
            "subcategory":"Groceries & Convenience Stores",
            "type":"Retail Goods"
        }
    ],
    "sg:phone":"+1 450 454 2262",
    "sg:postcode":"J0L 2L0",
    "sg:province":"QC",
    "sg:tags":[
        "grocer"
    ],
    "wof:name":"Marche Favreau Iga Inc",
    "wof:placetype":"venue"
},
  "geometry": {"coordinates":[-73.61554700000001,45.262295],"type":"Point"}
}