{
  "type": "Feature",
  "properties": {
    "addr:full":"Nepean ON K2E 7J5",
    "addr:postcode":"k2e 7j5",
    "iso:country":"CA",
    "sg:city":"Nepean",
    "sg:classifiers":[
        {
            "category":"Professional",
            "subcategory":"Advertising",
            "type":"Services"
        }
    ],
    "sg:phone":"+1 613 723 1849",
    "sg:postcode":"K2E 7J5",
    "sg:province":"ON",
    "sg:tags":[
        "designer",
        "display",
        "producer"
    ],
    "wof:name":"Portables",
    "wof:placetype":"venue"
},
  "geometry": {"coordinates":[-75.711372,45.342182],"type":"Point"}
}