{
  "type": "Feature",
  "properties": {
    "addr:full":"Montmagny QC G5V 1E3",
    "addr:postcode":"g5v 1e3",
    "iso:country":"CA",
    "sg:city":"Montmagny",
    "sg:classifiers":[
        {
            "category":"Professional",
            "subcategory":"Management & Consulting",
            "type":"Services"
        }
    ],
    "sg:phone":"+1 418 248 7413",
    "sg:postcode":"G5V 1E3",
    "sg:province":"QC",
    "sg:tags":[
        "agricultural",
        "consultant"
    ],
    "wof:name":"Abri Aube Inc",
    "wof:placetype":"venue"
},
  "geometry": {"coordinates":[-70.53591900000001,46.987473],"type":"Point"}
}