{
  "type": "Feature",
  "properties": {
    "addr:full":"12815 Clarke Pl # 110 Richmond BC V6V 2H9",
    "addr:housenumber":"12815;110",
    "addr:postcode":"v6v 2h9",
    "addr:street":"Clarke Pl #",
    "iso:country":"CA",
    "sg:address":"12815 Clarke Pl # 110",
    "sg:city":"Richmond",
    "sg:classifiers":[
        {
            "category":"Professional",
            "type":"Services"
        }
    ],
    "sg:phone":"+1 604 214 0768",
    "sg:postcode":"V6V 2H9",
    "sg:province":"BC",
    "sg:tags":[
        "computer",
        "establishment",
        "parts",
        "supply"
    ],
    "wof:name":"Myco Marketing Corp",
    "wof:placetype":"venue"
},
  "geometry": {"coordinates":[-123.082603455,49.1858558655],"type":"Point"}
}