{
  "type": "Feature",
  "properties": {
    "iso:country":"CA",
    "sg:address":"903 Waskesiu Dr",
    "sg:city":"Waskesiu Lake",
    "sg:classifiers":[
        {
            "category":"Shopping",
            "subcategory":"Gifts & Souvenirs",
            "type":"Retail Goods"
        }
    ],
    "sg:phone":"+1 306 663 4666",
    "sg:postcode":"S0J 2Y0",
    "sg:province":"SK",
    "sg:tags":[
        "shop"
    ],
    "wof:name":"Wishing Well Gifts",
    "wof:placetype":"venue"
},
  "geometry": {"coordinates":[-106.0753479,53.9210700989],"type":"Point"}
}