{
  "type": "Feature",
  "properties": {
    "addr:full":"4259 23 Ave NW Edmonton AB T6L 5Z8",
    "addr:housenumber":"4259",
    "addr:postcode":"t6l 5z8",
    "addr:street":"23 Ave Nw",
    "iso:country":"CA",
    "sg:address":"4259 23 Ave NW",
    "sg:city":"Edmonton",
    "sg:classifiers":[
        {
            "category":"Restaurant",
            "type":"Food & Drink"
        }
    ],
    "sg:phone":"+1 780 448 3820",
    "sg:postcode":"T6L 5Z8",
    "sg:province":"AB",
    "wof:name":"Kfc",
    "wof:placetype":"venue"
},
  "geometry": {"coordinates":[-113.405639648,53.4548110962],"type":"Point"}
}