{
  "type": "Feature",
  "properties": {
    "addr:full":"1368 Rometown Dr Mississauga ON L5E 2T4",
    "addr:housenumber":"1368",
    "addr:postcode":"l5e 2t4",
    "addr:street":"Rometown Dr",
    "iso:country":"CA",
    "sg:address":"1368 Rometown Dr",
    "sg:city":"Mississauga",
    "sg:classifiers":[
        {
            "category":"Health Services",
            "subcategory":"Chiropractor",
            "type":"Services"
        }
    ],
    "sg:phone":"+1 905 274 3091",
    "sg:postcode":"L5E 2T4",
    "sg:province":"ON",
    "wof:name":"Orchard Heights Chiropractic",
    "wof:placetype":"venue"
},
  "geometry": {"coordinates":[-79.5642242432,43.5952682495],"type":"Point"}
}