{
  "type": "Feature",
  "properties": {
    "addr:full":"28 Talbot St E Leamington ON N8H 1L2",
    "addr:housenumber":"28",
    "addr:postcode":"n8h 1l2",
    "addr:street":"Talbot St E",
    "iso:country":"CA",
    "sg:address":"28 Talbot St E",
    "sg:city":"Leamington",
    "sg:classifiers":[
        {
            "category":"Shopping",
            "subcategory":"Gifts & Souvenirs",
            "type":"Retail Goods"
        }
    ],
    "sg:phone":"+1 519 322 0667",
    "sg:postcode":"N8H 1L2",
    "sg:province":"ON",
    "sg:tags":[
        "shop"
    ],
    "wof:name":"Teddy Bear Abbey",
    "wof:placetype":"venue"
},
  "geometry": {"coordinates":[-82.599075,42.053135],"type":"Point"}
}