{
  "type": "Feature",
  "properties": {
    "addr:full":"739 Boul Arthur-Sauve Saint-Eustache QC J7P 4X5",
    "addr:housenumber":"739",
    "addr:postcode":"j7p 4x5",
    "addr:street":"Boul Arthur-Sauve",
    "iso:country":"CA",
    "sg:address":"739 Boul Arthur-Sauve",
    "sg:city":"Saint-Eustache",
    "sg:classifiers":[
        {
            "category":"Banks & Credit Unions",
            "subcategory":"Investment Brokerage",
            "type":"Services"
        }
    ],
    "sg:phone":"+1 450 472 8222",
    "sg:postcode":"J7P 4X5",
    "sg:province":"QC",
    "sg:tags":[
        "consultant",
        "financing"
    ],
    "wof:name":"Gestion Ctms",
    "wof:placetype":"venue"
},
  "geometry": {"coordinates":[-73.9203033447,45.5801811218],"type":"Point"}
}