{
  "type": "Feature",
  "properties": {
    "addr:full":"16 8E Av E LA Sarre QC J9Z 1N6",
    "addr:housenumber":"16",
    "addr:postcode":"j9z 1n6",
    "addr:street":"8E Av E La Sarre",
    "iso:country":"CA",
    "sg:address":"16 8E Av E",
    "sg:city":"LA Sarre",
    "sg:classifiers":[
        {
            "category":"Autos & Motor Vehicles",
            "subcategory":"Fuel & Gas Station",
            "type":"Retail Goods"
        }
    ],
    "sg:phone":"+1 819 333 2970",
    "sg:postcode":"J9Z 1N6",
    "sg:province":"QC",
    "sg:tags":[
        "oil"
    ],
    "wof:name":"Gauthier Gaz Bar Inc",
    "wof:placetype":"venue"
},
  "geometry": {"coordinates":[-79.20398712159999,48.8018493652],"type":"Point"}
}