{
  "type": "Feature",
  "properties": {
    "addr:full":"5515 Stanley Ave Niagara Falls ON L2G 3X4",
    "addr:housenumber":"5515",
    "addr:postcode":"l2g 3x4",
    "addr:street":"Stanley Ave",
    "iso:country":"CA",
    "sg:address":"5515 Stanley Ave",
    "sg:city":"Niagara Falls",
    "sg:classifiers":[
        {
            "category":"Travel",
            "subcategory":"Travel Agent",
            "type":"Entertainment"
        }
    ],
    "sg:phone":"+1 905 356 6061",
    "sg:postcode":"L2G 3X4",
    "sg:province":"ON",
    "sg:tags":[
        "information",
        "tourist"
    ],
    "wof:name":"Niagara Falls Tourism",
    "wof:placetype":"venue"
},
  "geometry": {"coordinates":[-79.085335,43.09494],"type":"Point"}
}