{
  "type": "Feature",
  "properties": {
    "addr:full":"1276 32 St SW Medicine Hat AB T1B 3N7",
    "addr:housenumber":"1276",
    "addr:postcode":"t1b 3n7",
    "addr:street":"32 St Sw",
    "iso:country":"CA",
    "sg:address":"1276 32 St SW",
    "sg:city":"Medicine Hat",
    "sg:classifiers":[
        {
            "category":"Manufacturing",
            "subcategory":"Building Materials",
            "type":"Manufacturing & Wholesale Goods"
        }
    ],
    "sg:phone":"+1 403 527 7840",
    "sg:postcode":"T1B 3N7",
    "sg:province":"AB",
    "sg:tags":[
        "roof",
        "structure"
    ],
    "wof:name":"Timber-Tech Truss Systems Ltd",
    "wof:placetype":"venue"
},
  "geometry": {"coordinates":[-110.717018,50.009132],"type":"Point"}
}