{
  "type": "Feature",
  "properties": {
    "addr:full":"Saint-Felicien QC G8K 1R8",
    "addr:postcode":"g8k 1r8",
    "iso:country":"CA",
    "sg:city":"Saint-Felicien",
    "sg:classifiers":[
        {
            "category":"Food & Beverages",
            "subcategory":"Groceries & Convenience Stores",
            "type":"Retail Goods"
        }
    ],
    "sg:phone":"+1 418 630 3501",
    "sg:postcode":"G8K 1R8",
    "sg:province":"QC",
    "wof:name":"Depanneur Marie-Claire",
    "wof:placetype":"venue"
},
  "geometry": {"coordinates":[-72.4372558594,48.6466941833],"type":"Point"}
}