{
  "type": "Feature",
  "properties": {
    "addr:full":"1995 Boul Des Laurentides Laval QC H7M 2R2",
    "addr:housenumber":"1995",
    "addr:postcode":"h7m 2r2",
    "addr:street":"Boul Des Laurentides",
    "iso:country":"CA",
    "sg:address":"1995 Boul Des Laurentides",
    "sg:city":"Laval",
    "sg:classifiers":[
        {
            "category":"Real Estate",
            "subcategory":"Real Estate Agent",
            "type":"Services"
        }
    ],
    "sg:phone":"+1 514 381 4275",
    "sg:postcode":"H7M 2R2",
    "sg:province":"QC",
    "sg:tags":[
        "agency",
        "rental"
    ],
    "wof:name":"Location D'Outils Vimont Inc",
    "wof:placetype":"venue"
},
  "geometry": {"coordinates":[-73.731033,45.605598],"type":"Point"}
}