{
  "type": "Feature",
  "properties": {
    "iso:country":"CA",
    "sg:city":"Penticton",
    "sg:classifiers":[
        {
            "category":"Professional",
            "type":"Services"
        }
    ],
    "sg:phone":"+1 250 770 8978",
    "sg:postcode":"V2A 6M2",
    "sg:province":"BC",
    "sg:tags":[
        "equipment",
        "hydroponics",
        "supply"
    ],
    "wof:name":"Better Than Nature South",
    "wof:placetype":"venue"
},
  "geometry": {"coordinates":[-119.586532593,49.4799499512],"type":"Point"}
}