{
  "type": "Feature",
  "properties": {
    "addr:full":"Richmond BC V7E 2G1",
    "addr:postcode":"v7e 2g1",
    "iso:country":"CA",
    "sg:city":"Richmond",
    "sg:classifiers":[
        {
            "category":"Manufacturing",
            "subcategory":"Food",
            "type":"Manufacturing & Wholesale Goods"
        }
    ],
    "sg:phone":"+1 604 241 8568",
    "sg:postcode":"V7E 2G1",
    "sg:province":"BC",
    "sg:tags":[
        "cocoa",
        "chocolate"
    ],
    "wof:name":"O-Young Enterprises Ltd",
    "wof:placetype":"venue"
},
  "geometry": {"coordinates":[-123.158661,49.118736],"type":"Point"}
}