{
  "type": "Feature",
  "properties": {
    "addr:full":"Sainte-Martine QC J0S 1V0",
    "addr:postcode":"j0s 1v0",
    "iso:country":"CA",
    "sg:city":"Sainte-Martine",
    "sg:classifiers":[
        {
            "category":"Personal",
            "subcategory":"Beauty Salon",
            "type":"Services"
        }
    ],
    "sg:phone":"+1 450 427 3774",
    "sg:postcode":"J0S 1V0",
    "sg:province":"QC",
    "wof:name":"Salon Dimension-Elle Enr",
    "wof:placetype":"venue"
},
  "geometry": {"coordinates":[-73.787903,45.262241],"type":"Point"}
}