{
  "type": "Feature",
  "properties": {
    "addr:full":"2 Deering Cres North York ON M2M 2A3",
    "addr:housenumber":"2",
    "addr:postcode":"m2m 2a3",
    "addr:street":"Deering Cres",
    "iso:country":"CA",
    "sg:address":"2 Deering Cres",
    "sg:city":"North York",
    "sg:classifiers":[
        {
            "category":"Building & Trades",
            "subcategory":"Landscaping Services",
            "type":"Services"
        }
    ],
    "sg:phone":"+1 416 730 1581",
    "sg:postcode":"M2M 2A3",
    "sg:province":"ON",
    "sg:tags":[
        "tree"
    ],
    "wof:name":"Noble Tree Svc Ltd",
    "wof:placetype":"venue"
},
  "geometry": {"coordinates":[-79.412994,43.785332],"type":"Point"}
}