{
  "type": "Feature",
  "properties": {
    "addr:full":"Kensington PE C0B 1M0",
    "addr:postcode":"c0b 1m0",
    "iso:country":"CA",
    "sg:city":"Kensington",
    "sg:classifiers":[
        {
            "category":"Retail",
            "subcategory":"Veterinary Services",
            "type":"Services"
        }
    ],
    "sg:phone":"+1 902 836 3410",
    "sg:postcode":"C0B 1M0",
    "sg:province":"PE",
    "sg:tags":[
        "veterinarian"
    ],
    "wof:name":"Robblee, Frank DVM",
    "wof:placetype":"venue"
},
  "geometry": {"coordinates":[-63.633644,46.437351],"type":"Point"}
}