{
  "type": "Feature",
  "properties": {
    "addr:full":"766 Rue Saint-Georges Saint-Jerome QC J7Z 5C6",
    "addr:housenumber":"766",
    "addr:postcode":"j7z 5c6",
    "addr:street":"Rue Saint-Georges Saint-Jerome",
    "iso:country":"CA",
    "sg:address":"766 Rue Saint-Georges",
    "sg:city":"Saint-Jerome",
    "sg:classifiers":[
        {
            "category":"Manufacturing",
            "subcategory":"Printing",
            "type":"Manufacturing & Wholesale Goods"
        }
    ],
    "sg:phone":"+1 450 432 2322",
    "sg:postcode":"J7Z 5C6",
    "sg:province":"QC",
    "sg:tags":[
        "printer"
    ],
    "wof:name":"Imprimerie LA Paperasse Enr",
    "wof:placetype":"venue"
},
  "geometry": {"coordinates":[-74.0041351318,45.7882766724],"type":"Point"}
}