{
  "type": "Feature",
  "properties": {
    "addr:full":"182 1E Rue O Barraute QC J0Y 1A0",
    "addr:housenumber":"182",
    "addr:postcode":"j0y 1a0",
    "addr:street":"1E Rue O",
    "iso:country":"CA",
    "sg:address":"182 1E Rue O",
    "sg:city":"Barraute",
    "sg:classifiers":[
        {
            "category":"Personal",
            "type":"Services"
        }
    ],
    "sg:phone":"+1 819 734 6921",
    "sg:postcode":"J0Y 1A0",
    "sg:province":"QC",
    "sg:tags":[
        "electrolysis"
    ],
    "wof:name":"Salon D'Esthetique Michele",
    "wof:placetype":"venue"
},
  "geometry": {"coordinates":[-77.63726,48.431858],"type":"Point"}
}