{
  "type": "Feature",
  "properties": {
    "addr:full":"15221 Yonge St Aurora ON L4G 1L8",
    "addr:housenumber":"15221",
    "addr:postcode":"l4g 1l8",
    "addr:street":"Yonge St",
    "iso:country":"CA",
    "sg:address":"15221 Yonge St",
    "sg:city":"Aurora",
    "sg:classifiers":[
        {
            "category":"Building & Trades",
            "subcategory":"Construction",
            "type":"Services"
        }
    ],
    "sg:phone":"+1 905 727 5758",
    "sg:postcode":"L4G 1L8",
    "sg:province":"ON",
    "sg:tags":[
        "general",
        "contractor"
    ],
    "wof:name":"Gallaugher Contracting Ltd",
    "wof:placetype":"venue"
},
  "geometry": {"coordinates":[-79.4672012329,43.9989700317],"type":"Point"}
}