{
  "type": "Feature",
  "properties": {
    "addr:full":"361 Rue Saint-Jean Longueuil QC J4H 2X7",
    "addr:housenumber":"361",
    "addr:postcode":"j4h 2x7",
    "addr:street":"Rue Saint-Jean",
    "iso:country":"CA",
    "sg:address":"361 Rue Saint-Jean",
    "sg:city":"Longueuil",
    "sg:classifiers":[
        {
            "category":"Shopping",
            "subcategory":"Pharmacy",
            "type":"Retail Goods"
        }
    ],
    "sg:phone":"+1 450 677 6331",
    "sg:postcode":"J4H 2X7",
    "sg:province":"QC",
    "wof:name":"Famili-Prix",
    "wof:placetype":"venue"
},
  "geometry": {"coordinates":[-73.5077819824,45.5357551575],"type":"Point"}
}