{
  "type": "Feature",
  "properties": {
    "addr:full":"115 Main St Eatonia SK S0L 0Y0",
    "addr:housenumber":"115",
    "addr:postcode":"s0l 0y0",
    "addr:street":"Main St",
    "iso:country":"CA",
    "sg:address":"115 Main St",
    "sg:city":"Eatonia",
    "sg:classifiers":[
        {
            "category":"Food & Beverages",
            "subcategory":"Groceries & Convenience Stores",
            "type":"Retail Goods"
        }
    ],
    "sg:phone":"+1 306 967 2491",
    "sg:postcode":"S0L 0Y0",
    "sg:province":"SK",
    "sg:tags":[
        "grocer"
    ],
    "wof:name":"Bredy's Country Store",
    "wof:placetype":"venue"
},
  "geometry": {"coordinates":[-109.389267,51.221149],"type":"Point"}
}