{
  "type": "Feature",
  "properties": {
    "addr:full":"4602 49 Ave Camrose AB T4V 0M6",
    "addr:housenumber":"4602",
    "addr:postcode":"t4v 0m6",
    "addr:street":"49 Ave",
    "iso:country":"CA",
    "sg:address":"4602 49 Ave",
    "sg:city":"Camrose",
    "sg:classifiers":[
        {
            "category":"Professional",
            "subcategory":"Accounting & Tax Preparation",
            "type":"Services"
        }
    ],
    "sg:phone":"+1 780 672 8844",
    "sg:postcode":"T4V 0M6",
    "sg:province":"AB",
    "sg:tags":[
        "accountant"
    ],
    "wof:name":"Fossen Harberg Nikiforuk Wood",
    "wof:placetype":"venue"
},
  "geometry": {"coordinates":[-112.81888600000001,53.020226],"type":"Point"}
}