{
  "type": "Feature",
  "properties": {
    "iso:country":"CA",
    "sg:address":"2084 Yonge St",
    "sg:city":"Toronto",
    "sg:classifiers":[
        {
            "category":"Restaurant",
            "type":"Food & Drink"
        }
    ],
    "sg:phone":"+1 416 481 7111",
    "sg:postcode":"M4S 2A3",
    "sg:province":"ON",
    "wof:name":"Mariachi Restaurant",
    "wof:placetype":"venue"
},
  "geometry": {"coordinates":[-79.3975982666,43.7021636963],"type":"Point"}
}