{
  "type": "Feature",
  "properties": {
    "addr:full":"Brigden ON N0N 1B0",
    "addr:postcode":"n0n 1b0",
    "iso:country":"CA",
    "sg:city":"Brigden",
    "sg:classifiers":[
        {
            "category":"Wholesale",
            "subcategory":"Construction Materials",
            "type":"Manufacturing & Wholesale Goods"
        }
    ],
    "sg:phone":"+1 519 864 4449",
    "sg:postcode":"N0N 1B0",
    "sg:province":"ON",
    "sg:tags":[
        "fence"
    ],
    "wof:name":"Van Tam Fencing",
    "wof:placetype":"venue"
},
  "geometry": {"coordinates":[-82.28323399999999,42.808167],"type":"Point"}
}