{
  "type": "Feature",
  "properties": {
    "addr:full":"155 Main St S Russell MB R0J 1W0",
    "addr:housenumber":"155",
    "addr:postcode":"r0j 1w0",
    "addr:street":"Main St S",
    "iso:country":"CA",
    "sg:address":"155 Main St S",
    "sg:city":"Russell",
    "sg:classifiers":[
        {
            "category":"Home & Garden",
            "subcategory":"Hardware",
            "type":"Retail Goods"
        }
    ],
    "sg:phone":"+1 204 773 2056",
    "sg:postcode":"R0J 1W0",
    "sg:province":"MB",
    "wof:name":"Mac Leods True Value",
    "wof:placetype":"venue"
},
  "geometry": {"coordinates":[-101.28787199999999,50.77787],"type":"Point"}
}