{
  "type": "Feature",
  "properties": {
    "addr:full":"1822 16E Av Pointe-Aux-Trembles QC H1B 3P2",
    "addr:housenumber":"1822",
    "addr:postcode":"h1b 3p2",
    "addr:street":"16E Av Pointe-Aux-Trembles",
    "iso:country":"CA",
    "sg:address":"1822 16E Av",
    "sg:city":"Pointe-Aux-Trembles",
    "sg:classifiers":[
        {
            "category":"Wholesale",
            "subcategory":"Stationery",
            "type":"Manufacturing & Wholesale Goods"
        }
    ],
    "sg:phone":"+1 514 645 7791",
    "sg:postcode":"H1B 3P2",
    "sg:province":"QC",
    "sg:tags":[
        "sanitary",
        "product",
        "supply"
    ],
    "wof:name":"Transbec Canada Produits Enr",
    "wof:placetype":"venue"
},
  "geometry": {"coordinates":[-73.508064,45.646114],"type":"Point"}
}