{
  "type": "Feature",
  "properties": {
    "iso:country":"CA",
    "sg:address":"81 Penn Dr",
    "sg:city":"North York",
    "sg:classifiers":[
        {
            "category":"Building & Trades",
            "subcategory":"Plumbing",
            "type":"Services"
        }
    ],
    "sg:phone":"+1 416 742 1600",
    "sg:postcode":"M9L 2A6",
    "sg:province":"ON",
    "sg:tags":[
        "heating",
        "contractor"
    ],
    "wof:name":"Henry Heating Ltd",
    "wof:placetype":"venue"
},
  "geometry": {"coordinates":[-79.558265686,43.7533569336],"type":"Point"}
}