{
  "type": "Feature",
  "properties": {
    "iso:country":"CA",
    "sg:city":"Dawson Creek",
    "sg:classifiers":[
        {
            "category":"Food & Beverages",
            "subcategory":"Specialty",
            "type":"Retail Goods"
        }
    ],
    "sg:phone":"+1 250 784 1901",
    "sg:postcode":"V1G 4K6",
    "sg:province":"BC",
    "sg:tags":[
        "vitamin"
    ],
    "wof:name":"General Nutrition Ctr",
    "wof:placetype":"venue"
},
  "geometry": {"coordinates":[-120.22423553500001,55.7505989075],"type":"Point"}
}