{
  "type": "Feature",
  "properties": {
    "addr:full":"1795 Broadway W Vancouver BC V6J 1Y2",
    "addr:housenumber":"1795",
    "addr:postcode":"v6j 1y2",
    "addr:street":"Broadway W",
    "iso:country":"CA",
    "sg:address":"1795 Broadway W",
    "sg:city":"Vancouver",
    "sg:classifiers":[
        {
            "category":"Autos & Motor Vehicles",
            "subcategory":"Fuel & Gas Station",
            "type":"Retail Goods"
        }
    ],
    "sg:phone":"+1 604 731 4711",
    "sg:postcode":"V6J 1Y2",
    "sg:province":"BC",
    "sg:tags":[
        "oil"
    ],
    "wof:name":"Broadway & Burrard Esso",
    "wof:placetype":"venue"
},
  "geometry": {"coordinates":[-123.145431519,49.2638587952],"type":"Point"}
}