{
  "type": "Feature",
  "properties": {
    "addr:full":"891 Millstone Ave Nanaimo BC V9S 5B4",
    "addr:housenumber":"891",
    "addr:postcode":"v9s 5b4",
    "addr:street":"Millstone Ave",
    "iso:country":"CA",
    "sg:address":"891 Millstone Ave",
    "sg:city":"Nanaimo",
    "sg:classifiers":[
        {
            "category":"Personal",
            "subcategory":"Beauty Salon",
            "type":"Services"
        }
    ],
    "sg:phone":"+1 250 754 1113",
    "sg:postcode":"V9S 5B4",
    "sg:province":"BC",
    "sg:tags":[
        "consultant",
        "health"
    ],
    "wof:name":"Bella Donna Esthetics By Lisa",
    "wof:placetype":"venue"
},
  "geometry": {"coordinates":[-123.955108643,49.1801071167],"type":"Point"}
}