{
  "type": "Feature",
  "properties": {
    "addr:full":"1980 Rue Monterey Laval QC H7L 3S3",
    "addr:housenumber":"1980",
    "addr:postcode":"h7l 3s3",
    "addr:street":"Rue Monterey",
    "iso:country":"CA",
    "sg:address":"1980 Rue Monterey",
    "sg:city":"Laval",
    "sg:classifiers":[
        {
            "category":"Freight",
            "type":"Transportation"
        }
    ],
    "sg:phone":"+1 450 681 5115",
    "sg:postcode":"H7L 3S3",
    "sg:province":"QC",
    "sg:tags":[
        "mover"
    ],
    "wof:name":"Administration Brisson Demen",
    "wof:placetype":"venue"
},
  "geometry": {"coordinates":[-73.75342559809999,45.5842323303],"type":"Point"}
}