{
  "type": "Feature",
  "properties": {
    "addr:full":"3874 Ch Des Polices Lac-Kenogami QC G7X 7V6",
    "addr:postcode":"3874;g7x 7v6",
    "addr:street":"Ch Des Polices Lac-Kenogami",
    "iso:country":"CA",
    "sg:address":"3874 Ch Des Polices",
    "sg:city":"Lac-Kenogami",
    "sg:classifiers":[
        {
            "category":"Manufacturing",
            "subcategory":"Glass & Minerals",
            "type":"Manufacturing & Wholesale Goods"
        }
    ],
    "sg:phone":"+1 418 695 2940",
    "sg:postcode":"G7X 7V6",
    "sg:province":"QC",
    "sg:tags":[
        "fabricator",
        "fiber"
    ],
    "wof:name":"Fibres DE Verre Jr",
    "wof:placetype":"venue"
},
  "geometry": {"coordinates":[-71.359016,48.340172],"type":"Point"}
}