{
  "type": "Feature",
  "properties": {
    "addr:full":"511 Rue Jean-Rioux Trois-Pistoles QC G0L 4K0",
    "addr:housenumber":"511",
    "addr:postcode":"g0l 4k0",
    "addr:street":"Rue Jean-Rioux",
    "iso:country":"CA",
    "sg:address":"511 Rue Jean-Rioux",
    "sg:city":"Trois-Pistoles",
    "sg:classifiers":[
        {
            "category":"Retail",
            "subcategory":"Auto Repair",
            "type":"Services"
        }
    ],
    "sg:phone":"+1 418 851 2452",
    "sg:postcode":"G0L 4K0",
    "sg:province":"QC",
    "sg:tags":[
        "repairing",
        "automobile"
    ],
    "wof:name":"Viateur Mecanique Enr",
    "wof:placetype":"venue"
},
  "geometry": {"coordinates":[-69.169991,48.122074],"type":"Point"}
}