{
  "type": "Feature",
  "properties": {
    "addr:full":"Hwy 8 E Mitchell ON N0K 1N0",
    "addr:postcode":"n0k 1n0",
    "addr:street":"Hwy 8 E",
    "iso:country":"CA",
    "sg:address":"Hwy 8 E",
    "sg:city":"Mitchell",
    "sg:classifiers":[
        {
            "category":"Wholesale",
            "subcategory":"Auto Parts",
            "type":"Manufacturing & Wholesale Goods"
        }
    ],
    "sg:phone":"+1 519 348 4774",
    "sg:postcode":"N0K 1N0",
    "sg:province":"ON",
    "sg:tags":[
        "equipment",
        "truck"
    ],
    "wof:name":"Burchill Truck & Trailer Equip",
    "wof:placetype":"venue"
},
  "geometry": {"coordinates":[-81.210762,43.473759],"type":"Point"}
}