{
  "type": "Feature",
  "properties": {
    "addr:full":"124 Bannister Rd Winnipeg MB R2R 0S3",
    "addr:housenumber":"124",
    "addr:postcode":"r2r 0s3",
    "addr:street":"Bannister Rd",
    "iso:country":"CA",
    "sg:address":"124 Bannister Rd",
    "sg:city":"Winnipeg",
    "sg:classifiers":[
        {
            "category":"Food & Beverages",
            "subcategory":"Groceries & Convenience Stores",
            "type":"Retail Goods"
        }
    ],
    "sg:phone":"+1 204 694 2464",
    "sg:postcode":"R2R 0S3",
    "sg:province":"MB",
    "wof:name":"Mac's Convenience Stores Ltd",
    "wof:placetype":"venue"
},
  "geometry": {"coordinates":[-97.21221923829999,49.9226989746],"type":"Point"}
}