{
  "type": "Feature",
  "properties": {
    "addr:full":"Montreal QC H2Z 1L1",
    "addr:postcode":"h2z 1l1",
    "iso:country":"CA",
    "sg:city":"Montreal",
    "sg:classifiers":[
        {
            "category":"Organizations",
            "subcategory":"Professional Association",
            "type":"Services"
        }
    ],
    "sg:phone":"+1 514 861 5244",
    "sg:postcode":"H2Z 1L1",
    "sg:province":"QC",
    "wof:name":"Service A LA Famille Chinoise",
    "wof:placetype":"venue"
},
  "geometry": {"coordinates":[-73.560699,45.506119],"type":"Point"}
}