{
  "type": "Feature",
  "properties": {
    "addr:full":"2891 Coalmont Tulameen BC V0X 2L0",
    "addr:housenumber":"2891",
    "addr:postcode":"v0x 2l0",
    "addr:street":"Coalmont Tulameen",
    "iso:country":"CA",
    "sg:address":"2891 Coalmont",
    "sg:city":"Tulameen",
    "sg:classifiers":[
        {
            "category":"Travel",
            "subcategory":"Hotels & Motels",
            "type":"Entertainment"
        }
    ],
    "sg:phone":"+1 250 295 3433",
    "sg:postcode":"V0X 2L0",
    "sg:province":"BC",
    "sg:tags":[
        "resort"
    ],
    "wof:name":"Vermillion Lodge At Tulameen",
    "wof:placetype":"venue"
},
  "geometry": {"coordinates":[-120.761177,49.54871],"type":"Point"}
}