{
  "type": "Feature",
  "properties": {
    "addr:full":"4255 12th Ave W Vancouver BC V6R 2P8",
    "addr:housenumber":"4255",
    "addr:postcode":"v6r 2p8",
    "addr:street":"12Th Ave W",
    "iso:country":"CA",
    "sg:address":"4255 12th Ave W",
    "sg:city":"Vancouver",
    "sg:classifiers":[
        {
            "category":"Wholesale",
            "subcategory":"Durable Goods & Equipment",
            "type":"Manufacturing & Wholesale Goods"
        }
    ],
    "sg:phone":"+1 604 228 0605",
    "sg:postcode":"V6R 2P8",
    "sg:province":"BC",
    "sg:tags":[
        "compact",
        "record",
        "disc",
        "tape"
    ],
    "wof:name":"Skylark Music",
    "wof:placetype":"venue"
},
  "geometry": {"coordinates":[-123.20166,49.262062],"type":"Point"}
}