{
  "type": "Feature",
  "properties": {
    "addr:full":"32 Edgar Dr Brantford ON N3R 6X8",
    "addr:housenumber":"32",
    "addr:postcode":"n3r 6x8",
    "addr:street":"Edgar Dr",
    "iso:country":"CA",
    "sg:address":"32 Edgar Dr",
    "sg:city":"Brantford",
    "sg:classifiers":[
        {
            "category":"Professional",
            "subcategory":"Accounting & Tax Preparation",
            "type":"Services"
        }
    ],
    "sg:phone":"+1 519 758 0021",
    "sg:postcode":"N3R 6X8",
    "sg:province":"ON",
    "sg:tags":[
        "return",
        "filing"
    ],
    "wof:name":"Brantwood Tax",
    "wof:placetype":"venue"
},
  "geometry": {"coordinates":[-80.271919,43.180897],"type":"Point"}
}