{
  "type": "Feature",
  "properties": {
    "addr:full":"Rouyn-Noranda QC J9X 1S6",
    "addr:postcode":"j9x 1s6",
    "iso:country":"CA",
    "sg:city":"Rouyn-Noranda",
    "sg:classifiers":[
        {
            "category":"Food & Beverages",
            "subcategory":"Specialty",
            "type":"Retail Goods"
        }
    ],
    "sg:phone":"+1 819 762 8918",
    "sg:postcode":"J9X 1S6",
    "sg:province":"QC",
    "wof:name":"Semence Alimentation Saine",
    "wof:placetype":"venue"
},
  "geometry": {"coordinates":[-79.016777,48.248474],"type":"Point"}
}