{
  "type": "Feature",
  "properties": {
    "iso:country":"CA",
    "sg:city":"Durham",
    "sg:classifiers":[
        {
            "category":"Personal",
            "type":"Services"
        }
    ],
    "sg:phone":"+1 519 369 6361",
    "sg:postcode":"N0G 1R0",
    "sg:province":"ON",
    "sg:tags":[
        "program",
        "physical",
        "exercise",
        "fitness"
    ],
    "wof:name":"Durham Activity Ctr",
    "wof:placetype":"venue"
},
  "geometry": {"coordinates":[-80.8148803711,44.1676635742],"type":"Point"}
}