{
  "type": "Feature",
  "properties": {
    "addr:full":"32 Rue J.-K.-Laflamme Levis QC G6V 9M5",
    "addr:housenumber":"32",
    "addr:postcode":"g6v 9m5",
    "addr:street":"Rue J.-K.-Laflamme",
    "iso:country":"CA",
    "sg:address":"32 Rue J.-K.-Laflamme",
    "sg:city":"Levis",
    "sg:classifiers":[
        {
            "category":"Taxi",
            "type":"Transportation"
        }
    ],
    "sg:phone":"+1 418 833 3015",
    "sg:postcode":"G6V 9M5",
    "sg:province":"QC",
    "sg:tags":[
        "taxicab"
    ],
    "wof:name":"Taxi A LA Traverse DE Levis",
    "wof:placetype":"venue"
},
  "geometry": {"coordinates":[-71.181702,46.816811],"type":"Point"}
}