{
  "type": "Feature",
  "properties": {
    "addr:full":"321 Main St Wakaw SK S0K 4P0",
    "addr:housenumber":"321",
    "addr:postcode":"s0k 4p0",
    "addr:street":"Main St",
    "iso:country":"CA",
    "sg:address":"321 Main St",
    "sg:city":"Wakaw",
    "sg:classifiers":[
        {
            "category":"Education",
            "subcategory":"Library",
            "type":"Public Place"
        }
    ],
    "sg:phone":"+1 306 233 5552",
    "sg:postcode":"S0K 4P0",
    "sg:province":"SK",
    "wof:name":"Wakaw Public Library",
    "wof:placetype":"venue"
},
  "geometry": {"coordinates":[-105.742706,52.65295],"type":"Point"}
}