{
  "type": "Feature",
  "properties": {
    "addr:full":"13555 Boul Lacroix Saint-Georges QC G5Y 1P1",
    "addr:housenumber":"13555",
    "addr:postcode":"g5y 1p1",
    "addr:street":"Boul Lacroix",
    "iso:country":"CA",
    "sg:address":"13555 Boul Lacroix",
    "sg:city":"Saint-Georges",
    "sg:classifiers":[
        {
            "category":"Shopping",
            "subcategory":"Pharmacy",
            "type":"Retail Goods"
        }
    ],
    "sg:phone":"+1 418 228 0077",
    "sg:postcode":"G5Y 1P1",
    "sg:province":"QC",
    "wof:name":"Pharmacien Gerald Lambert",
    "wof:placetype":"venue"
},
  "geometry": {"coordinates":[-70.6598434448,46.115737915],"type":"Point"}
}