{
  "type": "Feature",
  "properties": {
    "addr:full":"520 10th St Humboldt SK S0K 2A0",
    "addr:housenumber":"520",
    "addr:postcode":"s0k 2a0",
    "addr:street":"10Th St",
    "iso:country":"CA",
    "sg:address":"520 10th St",
    "sg:city":"Humboldt",
    "sg:classifiers":[
        {
            "category":"Home & Garden",
            "subcategory":"Building Materials",
            "type":"Retail Goods"
        }
    ],
    "sg:phone":"+1 306 682 5288",
    "sg:postcode":"S0K 2A0",
    "sg:province":"SK",
    "sg:tags":[
        "glass",
        "window",
        "plate"
    ],
    "wof:name":"Midland Glass Ltd",
    "wof:placetype":"venue"
},
  "geometry": {"coordinates":[-105.126068,52.193081],"type":"Point"}
}