{
  "type": "Feature",
  "properties": {
    "addr:full":"130 Lansdowne Ave Carleton Place ON K7C 2T7",
    "addr:housenumber":"130",
    "addr:postcode":"k7c 2t7",
    "addr:street":"Lansdowne Ave",
    "iso:country":"CA",
    "sg:address":"130 Lansdowne Ave",
    "sg:city":"Carleton Place",
    "sg:classifiers":[
        {
            "category":"Health Services",
            "subcategory":"Doctor",
            "type":"Services"
        }
    ],
    "sg:phone":"+1 613 257 3173",
    "sg:postcode":"K7C 2T7",
    "sg:province":"ON",
    "sg:tags":[
        "dentist"
    ],
    "wof:name":"Trinka, Rita DDS",
    "wof:placetype":"venue"
},
  "geometry": {"coordinates":[-76.13954200000001,45.134491],"type":"Point"}
}