{
  "type": "Feature",
  "properties": {
    "addr:full":"650 17E Rue Saint-Georges QC G5Y 4V5",
    "addr:housenumber":"650",
    "addr:postcode":"g5y 4v5",
    "addr:street":"17E Rue",
    "iso:country":"CA",
    "sg:address":"650 17E Rue",
    "sg:city":"Saint-Georges",
    "sg:classifiers":[
        {
            "category":"Home & Garden",
            "subcategory":"Building Materials",
            "type":"Retail Goods"
        }
    ],
    "sg:phone":"+1 418 228 0478",
    "sg:postcode":"G5Y 4V5",
    "sg:province":"QC",
    "sg:tags":[
        "door"
    ],
    "wof:name":"Vitrerie Mobile Pro-Installatn",
    "wof:placetype":"venue"
},
  "geometry": {"coordinates":[-70.678078,46.114887],"type":"Point"}
}