{
  "type": "Feature",
  "properties": {
    "addr:full":"11475 87 Ave Delta BC V4C 2Z6",
    "addr:housenumber":"11475",
    "addr:postcode":"v4c 2z6",
    "addr:street":"87 Ave",
    "iso:country":"CA",
    "sg:address":"11475 87 Ave",
    "sg:city":"Delta",
    "sg:classifiers":[
        {
            "category":"Social Services",
            "subcategory":"Child Care",
            "type":"Services"
        }
    ],
    "sg:phone":"+1 604 594 0161",
    "sg:postcode":"V4C 2Z6",
    "sg:province":"BC",
    "wof:name":"Starlight Daycare",
    "wof:placetype":"venue"
},
  "geometry": {"coordinates":[-122.90504455599999,49.1612930298],"type":"Point"}
}