{
  "type": "Feature",
  "properties": {
    "iso:country":"CA",
    "sg:address":"160 Meadowvale Dr",
    "sg:city":"Etobicoke",
    "sg:classifiers":[
        {
            "category":"Health Services",
            "subcategory":"Doctor",
            "type":"Services"
        }
    ],
    "sg:phone":"+1 416 231 7231",
    "sg:postcode":"M8Z 3K7",
    "sg:province":"ON",
    "sg:tags":[
        "dentist"
    ],
    "wof:name":"Saturno, John DDS",
    "wof:placetype":"venue"
},
  "geometry": {"coordinates":[-79.5225067139,43.6430511475],"type":"Point"}
}