{
  "type": "Feature",
  "properties": {
    "addr:full":"182 Rue Wellington Cowansville QC J2K 3G6",
    "addr:housenumber":"182",
    "addr:postcode":"j2k 3g6",
    "addr:street":"Rue Wellington",
    "iso:country":"CA",
    "sg:address":"182 Rue Wellington",
    "sg:city":"Cowansville",
    "sg:classifiers":[
        {
            "category":"Communications",
            "subcategory":"Film & Video Production",
            "type":"Services"
        }
    ],
    "sg:phone":"+1 450 263 5492",
    "sg:postcode":"J2K 3G6",
    "sg:province":"QC",
    "sg:tags":[
        "taping"
    ],
    "wof:name":"Productions Video Pier-Clo",
    "wof:placetype":"venue"
},
  "geometry": {"coordinates":[-72.81141700000001,45.218773],"type":"Point"}
}