{
  "type": "Feature",
  "properties": {
    "addr:full":"432 Av Saint-Emile Sainte-Marie QC G6E 1E2",
    "addr:postcode":"g6e 1e2",
    "addr:street":"432 Av Saint-Emile",
    "iso:country":"CA",
    "sg:address":"432 Av Saint-Emile",
    "sg:city":"Sainte-Marie",
    "sg:classifiers":[
        {
            "category":"Personal",
            "subcategory":"Beauty Salon",
            "type":"Services"
        }
    ],
    "sg:phone":"+1 418 387 8022",
    "sg:postcode":"G6E 1E2",
    "sg:province":"QC",
    "wof:name":"Salon Jo-Ann",
    "wof:placetype":"venue"
},
  "geometry": {"coordinates":[-71.034744,46.454163],"type":"Point"}
}