{
  "type": "Feature",
  "properties": {
    "addr:full":"295 Gibson St Fredericton NB E3A 4E7",
    "addr:housenumber":"295",
    "addr:postcode":"e3a 4e7",
    "addr:street":"Gibson St",
    "iso:country":"CA",
    "sg:address":"295 Gibson St",
    "sg:city":"Fredericton",
    "sg:classifiers":[
        {
            "category":"Autos & Motor Vehicles",
            "subcategory":"Auto Supplies",
            "type":"Retail Goods"
        }
    ],
    "sg:phone":"+1 506 450 8911",
    "sg:postcode":"E3A 4E7",
    "sg:province":"NB",
    "sg:tags":[
        "automobile",
        "stereo",
        "parts",
        "radio"
    ],
    "wof:name":"Car Audio Advisers",
    "wof:placetype":"venue"
},
  "geometry": {"coordinates":[-66.615891,45.964169],"type":"Point"}
}