{
  "type": "Feature",
  "properties": {
    "iso:country":"CA",
    "sg:address":"85 Fitzroy St",
    "sg:city":"Charlottetown",
    "sg:classifiers":[
        {
            "category":"Government",
            "subcategory":"Office",
            "type":"Public Place"
        }
    ],
    "sg:phone":"+1 902 566 7794",
    "sg:postcode":"C1A 1R6",
    "sg:province":"PE",
    "wof:name":"Canada Human Resource Dev",
    "wof:placetype":"venue"
},
  "geometry": {"coordinates":[-63.1296768188,46.2365760803],"type":"Point"}
}