{
  "type": "Feature",
  "properties": {
    "addr:full":"Etobicoke ON M9C 2Y3",
    "addr:postcode":"m9c 2y3",
    "iso:country":"CA",
    "sg:city":"Etobicoke",
    "sg:classifiers":[
        {
            "category":"Insurance",
            "subcategory":"Insurance Agent",
            "type":"Services"
        }
    ],
    "sg:phone":"+1 416 626 8373",
    "sg:postcode":"M9C 2Y3",
    "sg:province":"ON",
    "wof:name":"M Lukic & Assoc Ins Brokers",
    "wof:placetype":"venue"
},
  "geometry": {"coordinates":[-79.568321,43.64447],"type":"Point"}
}