{
  "type": "Feature",
  "properties": {
    "iso:country":"CA",
    "sg:address":"4216 Av Gascon",
    "sg:city":"Montreal",
    "sg:classifiers":[
        {
            "category":"Building & Trades",
            "subcategory":"Construction",
            "type":"Services"
        }
    ],
    "sg:phone":"+1 514 523 8161",
    "sg:postcode":"H2H 2M9",
    "sg:province":"QC",
    "sg:tags":[
        "roofing",
        "contractor"
    ],
    "wof:name":"J H Talbot & Fils Inc",
    "wof:placetype":"venue"
},
  "geometry": {"coordinates":[-73.56298828120001,45.538028717],"type":"Point"}
}