{
  "type": "Feature",
  "properties": {
    "addr:full":"140 2E Av Lasalle QC H8P 2G5",
    "addr:housenumber":"140",
    "addr:postcode":"h8p 2g5",
    "addr:street":"2E Av",
    "iso:country":"CA",
    "sg:address":"140 2E Av",
    "sg:city":"Lasalle",
    "sg:classifiers":[
        {
            "category":"Building & Trades",
            "subcategory":"Plumbing",
            "type":"Services"
        }
    ],
    "sg:phone":"+1 514 366 0330",
    "sg:postcode":"H8P 2G5",
    "sg:province":"QC",
    "sg:tags":[
        "contractor"
    ],
    "wof:name":"Plomberie Allard Inc",
    "wof:placetype":"venue"
},
  "geometry": {"coordinates":[-73.6628189087,45.4286575317],"type":"Point"}
}