{
  "type": "Feature",
  "properties": {
    "addr:full":"3212 Lake City Way Burnaby BC V5A 3A4",
    "addr:housenumber":"3212",
    "addr:postcode":"v5a 3a4",
    "addr:street":"Lake City Way",
    "iso:country":"CA",
    "sg:address":"3212 Lake City Way",
    "sg:city":"Burnaby",
    "sg:classifiers":[
        {
            "category":"Manufacturing",
            "subcategory":"Printing",
            "type":"Manufacturing & Wholesale Goods"
        }
    ],
    "sg:phone":"+1 604 421 7778",
    "sg:postcode":"V5A 3A4",
    "sg:province":"BC",
    "sg:tags":[
        "printer",
        "business",
        "form",
        "system"
    ],
    "wof:name":"Westkey Graphic Communications",
    "wof:placetype":"venue"
},
  "geometry": {"coordinates":[-122.937606812,49.2561798096],"type":"Point"}
}