{
  "type": "Feature",
  "properties": {
    "iso:country":"CA",
    "sg:address":"470 Osborne St",
    "sg:city":"Winnipeg",
    "sg:classifiers":[
        {
            "category":"Restaurant",
            "type":"Food & Drink"
        }
    ],
    "sg:phone":"+1 204 452 7915",
    "sg:postcode":"R3L 2A5",
    "sg:province":"MB",
    "wof:name":"Diner's Choice",
    "wof:placetype":"venue"
},
  "geometry": {"coordinates":[-97.136680603,49.8682136536],"type":"Point"}
}