{
  "type": "Feature",
  "properties": {
    "addr:full":"595 Campbell St Nanaimo BC V9R 3G9",
    "addr:housenumber":"595",
    "addr:postcode":"v9r 3g9",
    "addr:street":"Campbell St",
    "iso:country":"CA",
    "sg:address":"595 Campbell St",
    "sg:city":"Nanaimo",
    "sg:classifiers":[
        {
            "category":"Health Services",
            "subcategory":"Health Practitioner",
            "type":"Services"
        }
    ],
    "sg:phone":"+1 250 753 0280",
    "sg:postcode":"V9R 3G9",
    "sg:province":"BC",
    "sg:tags":[
        "physician"
    ],
    "wof:name":"Pacific Holistic Ctr",
    "wof:placetype":"venue"
},
  "geometry": {"coordinates":[-123.943817,49.168381],"type":"Point"}
}