{
  "type": "Feature",
  "properties": {
    "iso:country":"CA",
    "sg:address":"2637 4th Ave W",
    "sg:city":"Vancouver",
    "sg:classifiers":[
        {
            "category":"Shopping",
            "type":"Retail Goods"
        }
    ],
    "sg:phone":"+1 604 733 3390",
    "sg:postcode":"V6K 1P8",
    "sg:province":"BC",
    "sg:tags":[
        "pet",
        "food",
        "shop",
        "supply"
    ],
    "wof:name":"Cat & Dog Shop",
    "wof:placetype":"venue"
},
  "geometry": {"coordinates":[-123.16513824499999,49.2685661316],"type":"Point"}
}