{
  "type": "Feature",
  "properties": {
    "addr:full":"70 Av Lussier Pincourt QC J7V 5B2",
    "addr:postcode":"j7v 5b2",
    "addr:street":"70 Av Lussier",
    "iso:country":"CA",
    "sg:address":"70 Av Lussier",
    "sg:city":"Pincourt",
    "sg:classifiers":[
        {
            "category":"Education",
            "subcategory":"School",
            "type":"Public Place"
        }
    ],
    "sg:phone":"+1 514 453 8581",
    "sg:postcode":"J7V 5B2",
    "sg:province":"QC",
    "wof:name":"Ecole Notre Dame DE Lorette",
    "wof:placetype":"venue"
},
  "geometry": {"coordinates":[-73.98904400000001,45.372414],"type":"Point"}
}