{
  "type": "Feature",
  "properties": {
    "addr:full":"5020 75 St NW Edmonton AB T6E 6P2",
    "addr:housenumber":"5020",
    "addr:postcode":"t6e 6p2",
    "addr:street":"75 St Nw",
    "iso:country":"CA",
    "sg:address":"5020 75 St NW",
    "sg:city":"Edmonton",
    "sg:classifiers":[
        {
            "category":"Wholesale",
            "subcategory":"Machinery & Supplies",
            "type":"Manufacturing & Wholesale Goods"
        }
    ],
    "sg:phone":"+1 780 461 2929",
    "sg:postcode":"T6E 6P2",
    "sg:province":"AB",
    "sg:tags":[
        "janitor",
        "appliance"
    ],
    "wof:name":"Amre Supply CO",
    "wof:placetype":"venue"
},
  "geometry": {"coordinates":[-113.442993164,53.4876365662],"type":"Point"}
}