{
  "type": "Feature",
  "properties": {
    "addr:full":"750 Boul Maloney E Gatineau QC J8P 1G4",
    "addr:housenumber":"750",
    "addr:postcode":"j8p 1g4",
    "addr:street":"Boul Maloney E",
    "iso:country":"CA",
    "sg:address":"750 Boul Maloney E",
    "sg:city":"Gatineau",
    "sg:classifiers":[
        {
            "category":"Retail",
            "subcategory":"Funeral Services",
            "type":"Services"
        }
    ],
    "sg:phone":"+1 819 663 2468",
    "sg:postcode":"J8P 1G4",
    "sg:province":"QC",
    "sg:tags":[
        "director"
    ],
    "wof:name":"Maison Funeraire A Gauvreau",
    "wof:placetype":"venue"
},
  "geometry": {"coordinates":[-75.62050600000001,45.482895],"type":"Point"}
}