{
  "type": "Feature",
  "properties": {
    "addr:full":"Bonnyville AB T9N 2H8",
    "addr:postcode":"t9n 2h8",
    "iso:country":"CA",
    "sg:city":"Bonnyville",
    "sg:classifiers":[
        {
            "category":"Mining & Drilling",
            "type":"Manufacturing & Wholesale Goods"
        }
    ],
    "sg:phone":"+1 780 826 2820",
    "sg:postcode":"T9N 2H8",
    "sg:province":"AB",
    "sg:tags":[
        "field",
        "oil"
    ],
    "wof:name":"Schlumberger Completion Sys",
    "wof:placetype":"venue"
},
  "geometry": {"coordinates":[-110.75505065900001,54.2739830017],"type":"Point"}
}