{
  "type": "Feature",
  "properties": {
    "iso:country":"CA",
    "sg:city":"Freelton",
    "sg:classifiers":[
        {
            "category":"Restaurant",
            "type":"Food & Drink"
        }
    ],
    "sg:phone":"+1 905 659 1556",
    "sg:postcode":"L0R 1K0",
    "sg:province":"ON",
    "wof:name":"Breezy Corners Restaurant",
    "wof:placetype":"venue"
},
  "geometry": {"coordinates":[-80.0269622803,43.3926391602],"type":"Point"}
}