{
  "type": "Feature",
  "properties": {
    "addr:full":"3079 Boul Des Sources Dollard-Des-Ormeaux QC H9B 1Z6",
    "addr:housenumber":"3079",
    "addr:postcode":"h9b 1z6",
    "addr:street":"Boul Des Sources",
    "iso:country":"CA",
    "sg:address":"3079 Boul Des Sources",
    "sg:city":"Dollard-Des-Ormeaux",
    "sg:classifiers":[
        {
            "category":"Autos & Motor Vehicles",
            "subcategory":"Auto Supplies",
            "type":"Retail Goods"
        }
    ],
    "sg:phone":"+1 514 684 9750",
    "sg:postcode":"H9B 1Z6",
    "sg:province":"QC",
    "sg:tags":[
        "automobile",
        "parts"
    ],
    "wof:name":"Canadian Tire",
    "wof:placetype":"venue"
},
  "geometry": {"coordinates":[-73.7950210571,45.4825515747],"type":"Point"}
}