{
  "type": "Feature",
  "properties": {
    "addr:full":"1706 36 Ave SW Calgary AB T2T 2G3",
    "addr:housenumber":"1706",
    "addr:postcode":"t2t 2g3",
    "addr:street":"36 Ave Sw",
    "iso:country":"CA",
    "sg:address":"1706 36 Ave SW",
    "sg:city":"Calgary",
    "sg:classifiers":[
        {
            "category":"Recreation",
            "type":"Entertainment"
        }
    ],
    "sg:phone":"+1 403 268 2300",
    "sg:postcode":"T2T 2G3",
    "sg:province":"AB",
    "sg:tags":[
        "pool",
        "swimming"
    ],
    "wof:name":"Forest Lawn Pool",
    "wof:placetype":"venue"
},
  "geometry": {"coordinates":[-114.10099,51.022133],"type":"Point"}
}