{
  "type": "Feature",
  "properties": {
    "addr:full":"200 Commander Blvd Scarborough ON M1S 3C8",
    "addr:housenumber":"200",
    "addr:postcode":"m1s 3c8",
    "addr:street":"Commander Blvd",
    "iso:country":"CA",
    "sg:address":"200 Commander Blvd",
    "sg:city":"Scarborough",
    "sg:classifiers":[
        {
            "category":"Organizations",
            "subcategory":"Religious Organization",
            "type":"Services"
        }
    ],
    "sg:phone":"+1 416 299 3855",
    "sg:postcode":"M1S 3C8",
    "sg:province":"ON",
    "sg:tags":[
        "church"
    ],
    "wof:name":"Toronto Simpson Chinese Allnc",
    "wof:placetype":"venue"
},
  "geometry": {"coordinates":[-79.268371582,43.7946662903],"type":"Point"}
}