{
  "type": "Feature",
  "properties": {
    "iso:country":"CA",
    "sg:city":"Les Eboulements",
    "sg:classifiers":[
        {
            "category":"Shopping",
            "subcategory":"Hobbies, Toys, & Games",
            "type":"Retail Goods"
        }
    ],
    "sg:phone":"+1 418 635 2346",
    "sg:postcode":"G0A 2M0",
    "sg:province":"QC",
    "sg:tags":[
        "craft"
    ],
    "wof:name":"Foins Sales",
    "wof:placetype":"venue"
},
  "geometry": {"coordinates":[-70.3170547485,47.4791564941],"type":"Point"}
}