{
  "type": "Feature",
  "properties": {
    "addr:full":"37 Water St # D Pictou NS B0K 1H0",
    "addr:housenumber":"37",
    "addr:postcode":"b0k 1h0",
    "addr:street":"Water St # D",
    "iso:country":"CA",
    "sg:address":"37 Water St # D",
    "sg:city":"Pictou",
    "sg:classifiers":[
        {
            "category":"Shopping",
            "subcategory":"Computers & Home Electronics",
            "type":"Retail Goods"
        }
    ],
    "sg:phone":"+1 902 485 3435",
    "sg:postcode":"B0K 1H0",
    "sg:province":"NS",
    "sg:tags":[
        "equipment",
        "dealer",
        "consultant"
    ],
    "wof:name":"Lucus Technology & Analytics",
    "wof:placetype":"venue"
},
  "geometry": {"coordinates":[-62.710445,45.675919],"type":"Point"}
}