{
  "type": "Feature",
  "properties": {
    "addr:full":"Calgary AB T2H 2K6",
    "addr:postcode":"t2h 2k6",
    "iso:country":"CA",
    "sg:city":"Calgary",
    "sg:classifiers":[
        {
            "category":"Health Services",
            "subcategory":"Medical Lab",
            "type":"Services"
        }
    ],
    "sg:phone":"+1 403 253 8500",
    "sg:postcode":"T2H 2K6",
    "sg:province":"AB",
    "wof:name":"Advanced/Glenmore Denture Clnc",
    "wof:placetype":"venue"
},
  "geometry": {"coordinates":[-114.07189200000001,50.991219],"type":"Point"}
}