{
  "type": "Feature",
  "properties": {
    "addr:full":"48 Memorial Park Dr Powassan ON P0H 1Z0",
    "addr:housenumber":"48",
    "addr:postcode":"p0h 1z0",
    "addr:street":"Memorial Park Dr",
    "iso:country":"CA",
    "sg:address":"48 Memorial Park Dr",
    "sg:city":"Powassan",
    "sg:classifiers":[
        {
            "category":"Retail",
            "subcategory":"Repair Shop",
            "type":"Services"
        }
    ],
    "sg:phone":"+1 705 724 2698",
    "sg:postcode":"P0H 1Z0",
    "sg:province":"ON",
    "sg:tags":[
        "welding"
    ],
    "wof:name":"Steve Crozier Welding",
    "wof:placetype":"venue"
},
  "geometry": {"coordinates":[-79.358192,46.082508],"type":"Point"}
}