{
  "type": "Feature",
  "properties": {
    "addr:full":"242 Jackson St E Hamilton ON L8N 1L9",
    "addr:housenumber":"242",
    "addr:postcode":"l8n 1l9",
    "addr:street":"Jackson St E",
    "iso:country":"CA",
    "sg:address":"242 Jackson St E",
    "sg:city":"Hamilton",
    "sg:classifiers":[
        {
            "category":"Personal",
            "subcategory":"Beauty Salon",
            "type":"Services"
        }
    ],
    "sg:phone":"+1 905 529 7933",
    "sg:postcode":"L8N 1L9",
    "sg:province":"ON",
    "wof:name":"Associates in Hair",
    "wof:placetype":"venue"
},
  "geometry": {"coordinates":[-79.8610153198,43.2519721985],"type":"Point"}
}