{
  "type": "Feature",
  "properties": {
    "addr:full":"112 Nottingham Dr Quispamsis NB E2E 1G8",
    "addr:housenumber":"112",
    "addr:postcode":"e2e 1g8",
    "addr:street":"Nottingham Dr",
    "iso:country":"CA",
    "sg:address":"112 Nottingham Dr",
    "sg:city":"Quispamsis",
    "sg:classifiers":[
        {
            "category":"Wholesale",
            "subcategory":"Office Equipment",
            "type":"Manufacturing & Wholesale Goods"
        }
    ],
    "sg:phone":"+1 506 847 1176",
    "sg:postcode":"E2E 1G8",
    "sg:province":"NB",
    "sg:tags":[
        "accounting",
        "bookkeeping",
        "system"
    ],
    "wof:name":"Jamie Kindred's Bookkeeping",
    "wof:placetype":"venue"
},
  "geometry": {"coordinates":[-65.99166099999999,45.4328],"type":"Point"}
}