{
  "type": "Feature",
  "properties": {
    "addr:full":"228 Aylmer Rd Chase BC V0E 1M0",
    "addr:housenumber":"228",
    "addr:postcode":"v0e 1m0",
    "addr:street":"Aylmer Rd",
    "iso:country":"CA",
    "sg:address":"228 Aylmer Rd",
    "sg:city":"Chase",
    "sg:classifiers":[
        {
            "category":"Building & Trades",
            "subcategory":"Construction",
            "type":"Services"
        }
    ],
    "sg:phone":"+1 250 679 5347",
    "sg:postcode":"V0E 1M0",
    "sg:province":"BC",
    "sg:tags":[
        "contractor"
    ],
    "wof:name":"K W Christ Construction Ltd",
    "wof:placetype":"venue"
},
  "geometry": {"coordinates":[-119.70034,50.820942],"type":"Point"}
}