{
  "type": "Feature",
  "properties": {
    "addr:full":"2179 Queen St E Toronto ON M4E 1E5",
    "addr:housenumber":"2179",
    "addr:postcode":"m4e 1e5",
    "addr:street":"Queen St E",
    "iso:country":"CA",
    "sg:address":"2179 Queen St E",
    "sg:city":"Toronto",
    "sg:classifiers":[
        {
            "category":"Wholesale",
            "subcategory":"Groceries",
            "type":"Manufacturing & Wholesale Goods"
        }
    ],
    "sg:phone":"+1 416 698 5548",
    "sg:postcode":"M4E 1E5",
    "sg:province":"ON",
    "sg:tags":[
        "cocoa",
        "confectionery",
        "candy",
        "chocolate"
    ],
    "wof:name":"Nutty Chocolatier",
    "wof:placetype":"venue"
},
  "geometry": {"coordinates":[-79.2975616455,43.6704330444],"type":"Point"}
}