{
  "type": "Feature",
  "properties": {
    "addr:full":"1229 Rue DE LA Montagne Montreal QC H3G 1Z2",
    "addr:housenumber":"1229",
    "addr:postcode":"h3g 1z2",
    "addr:street":"Rue De La Montagne",
    "iso:country":"CA",
    "sg:address":"1229 Rue DE LA Montagne",
    "sg:city":"Montreal",
    "sg:classifiers":[
        {
            "category":"Restaurant",
            "type":"Food & Drink"
        }
    ],
    "sg:phone":"+1 514 866 3234",
    "sg:postcode":"H3G 1Z2",
    "sg:province":"QC",
    "wof:name":"Bis Restaurant",
    "wof:placetype":"venue"
},
  "geometry": {"coordinates":[-73.573883,45.497524],"type":"Point"}
}