{
  "type": "Feature",
  "properties": {
    "addr:full":"Calgary AB T3C 0N4",
    "addr:postcode":"t3c 0n4",
    "iso:country":"CA",
    "sg:city":"Calgary",
    "sg:classifiers":[
        {
            "category":"Food & Beverages",
            "subcategory":"Groceries & Convenience Stores",
            "type":"Retail Goods"
        }
    ],
    "sg:phone":"+1 403 245 3111",
    "sg:postcode":"T3C 0N4",
    "sg:province":"AB",
    "sg:tags":[
        "grocer"
    ],
    "wof:name":"One Way Foods",
    "wof:placetype":"venue"
},
  "geometry": {"coordinates":[-114.100280762,51.043586731],"type":"Point"}
}