{
  "type": "Feature",
  "properties": {
    "addr:full":"221 Scott St Fort Frances ON P9A 1G8",
    "addr:housenumber":"221",
    "addr:postcode":"p9a 1g8",
    "addr:street":"Scott St",
    "iso:country":"CA",
    "sg:address":"221 Scott St",
    "sg:city":"Fort Frances",
    "sg:classifiers":[
        {
            "category":"Health Services",
            "subcategory":"Optometrist",
            "type":"Services"
        }
    ],
    "sg:phone":"+1 807 274 6655",
    "sg:postcode":"P9A 1G8",
    "sg:province":"ON",
    "wof:name":"Lidkea, Bruce OD",
    "wof:placetype":"venue"
},
  "geometry": {"coordinates":[-93.39782700000001,48.609844],"type":"Point"}
}