{
  "type": "Feature",
  "properties": {
    "addr:full":"158 Ch Des Commissaires L'Assomption QC J5W 2T7",
    "addr:housenumber":"158",
    "addr:postcode":"j5w 2t7",
    "addr:street":"Ch Des Commissaires",
    "iso:country":"CA",
    "sg:address":"158 Ch Des Commissaires",
    "sg:city":"L'Assomption",
    "sg:classifiers":[
        {
            "category":"Manufacturing",
            "subcategory":"Wood Products",
            "type":"Manufacturing & Wholesale Goods"
        }
    ],
    "sg:phone":"+1 450 589 3611",
    "sg:postcode":"J5W 2T7",
    "sg:province":"QC",
    "sg:tags":[
        "pallet",
        "skid"
    ],
    "wof:name":"Mailhot Palettes Inc",
    "wof:placetype":"venue"
},
  "geometry": {"coordinates":[-73.45320100000001,45.826763],"type":"Point"}
}