{
  "type": "Feature",
  "properties": {
    "addr:full":"1075 Mccurdy Rd Kelowna BC V1X 2P9",
    "addr:housenumber":"1075",
    "addr:postcode":"v1x 2p9",
    "addr:street":"Mccurdy Rd",
    "iso:country":"CA",
    "sg:address":"1075 Mccurdy Rd",
    "sg:city":"Kelowna",
    "sg:classifiers":[
        {
            "category":"Autos & Motor Vehicles",
            "subcategory":"Motorcycle Sales",
            "type":"Retail Goods"
        }
    ],
    "sg:phone":"+1 250 765 6666",
    "sg:postcode":"V1X 2P9",
    "sg:province":"BC",
    "sg:tags":[
        "scooter"
    ],
    "wof:name":"Kane's Harley Davidson",
    "wof:placetype":"venue"
},
  "geometry": {"coordinates":[-119.40784499999999,49.901051],"type":"Point"}
}