{
  "type": "Feature",
  "properties": {
    "addr:full":"195 Wellington St Wardsville ON N0L 2N0",
    "addr:housenumber":"195",
    "addr:postcode":"n0l 2n0",
    "addr:street":"Wellington St",
    "iso:country":"CA",
    "sg:address":"195 Wellington St",
    "sg:city":"Wardsville",
    "sg:classifiers":[
        {
            "category":"Manufacturing",
            "subcategory":"Wood Products",
            "type":"Manufacturing & Wholesale Goods"
        }
    ],
    "sg:phone":"+1 519 693 4812",
    "sg:postcode":"N0L 2N0",
    "sg:province":"ON",
    "sg:tags":[
        "pallet",
        "skid"
    ],
    "wof:name":"Quad County Support Svc",
    "wof:placetype":"venue"
},
  "geometry": {"coordinates":[-81.7576370239,42.658657074],"type":"Point"}
}