{
  "type": "Feature",
  "properties": {
    "addr:full":"4281 Rue Sainte-Catherine E Montreal QC H1V 1X7",
    "addr:housenumber":"4281",
    "addr:postcode":"h1v 1x7",
    "addr:street":"Rue Sainte-Catherine E",
    "iso:country":"CA",
    "sg:address":"4281 Rue Sainte-Catherine E",
    "sg:city":"Montreal",
    "sg:classifiers":[
        {
            "category":"Wholesale",
            "subcategory":"Meat",
            "type":"Manufacturing & Wholesale Goods"
        }
    ],
    "sg:phone":"+1 514 259 8554",
    "sg:postcode":"H1V 1X7",
    "sg:province":"QC",
    "sg:tags":[
        "packer",
        "butchering"
    ],
    "wof:name":"Salaison Viau Meat Market Enrg",
    "wof:placetype":"venue"
},
  "geometry": {"coordinates":[-73.53441599999999,45.550541],"type":"Point"}
}