{
  "type": "Feature",
  "properties": {
    "addr:full":"1390 Goulais Ave Sault Ste Marie ON P6A 5K8",
    "addr:housenumber":"1390",
    "addr:postcode":"p6a 5k8",
    "addr:street":"Goulais Ave",
    "iso:country":"CA",
    "sg:address":"1390 Goulais Ave",
    "sg:city":"Sault Ste Marie",
    "sg:classifiers":[
        {
            "category":"Manufacturing",
            "subcategory":"Buildings",
            "type":"Manufacturing & Wholesale Goods"
        }
    ],
    "sg:phone":"+1 705 946 2201",
    "sg:postcode":"P6A 5K8",
    "sg:province":"ON",
    "sg:tags":[
        "home",
        "log",
        "cabin"
    ],
    "wof:name":"Apex Log Homes",
    "wof:placetype":"venue"
},
  "geometry": {"coordinates":[-84.3830413818,46.5656433105],"type":"Point"}
}