{
  "type": "Feature",
  "properties": {
    "addr:full":"8330 Fairmount Dr SE # 201 Calgary AB T2H 0Y8",
    "addr:housenumber":"8330",
    "addr:postcode":"t2h 0y8",
    "addr:street":"Fairmount Dr Se # 201",
    "iso:country":"CA",
    "sg:address":"8330 Fairmount Dr SE # 201",
    "sg:city":"Calgary",
    "sg:classifiers":[
        {
            "category":"Health Services",
            "subcategory":"Doctor",
            "type":"Services"
        }
    ],
    "sg:phone":"+1 403 252 0303",
    "sg:postcode":"T2H 0Y8",
    "sg:province":"AB",
    "sg:tags":[
        "dentist"
    ],
    "wof:name":"Acadia Dental",
    "wof:placetype":"venue"
},
  "geometry": {"coordinates":[-114.05972300000001,50.979095],"type":"Point"}
}