{
  "type": "Feature",
  "properties": {
    "iso:country":"CA",
    "sg:address":"8777 96 Ave NW",
    "sg:city":"Edmonton",
    "sg:classifiers":[
        {
            "category":"Recreation",
            "type":"Entertainment"
        }
    ],
    "sg:phone":"+1 780 468 6556",
    "sg:postcode":"T6C 2B1",
    "sg:province":"AB",
    "sg:tags":[
        "center"
    ],
    "wof:name":"Strathearn Community League",
    "wof:placetype":"venue"
},
  "geometry": {"coordinates":[-113.46452331499999,53.5328903198],"type":"Point"}
}