{
  "type": "Feature",
  "properties": {
    "addr:full":"Winnipeg MB R2M 5E5",
    "addr:postcode":"r2m 5e5",
    "iso:country":"CA",
    "sg:city":"Winnipeg",
    "sg:classifiers":[
        {
            "category":"Insurance",
            "subcategory":"Insurance Agent",
            "type":"Services"
        }
    ],
    "sg:phone":"+1 204 255 9223",
    "sg:postcode":"R2M 5E5",
    "sg:province":"MB",
    "wof:name":"Union Insurance Ltd",
    "wof:placetype":"venue"
},
  "geometry": {"coordinates":[-97.136482,49.891891],"type":"Point"}
}