{
  "type": "Feature",
  "properties": {
    "iso:country":"CA",
    "sg:address":"15 1st Ave SW",
    "sg:city":"Carman",
    "sg:classifiers":[
        {
            "category":"Government",
            "subcategory":"Office",
            "type":"Public Place"
        }
    ],
    "sg:phone":"+1 204 745 2317",
    "sg:postcode":"R0G 0J0",
    "sg:province":"MB",
    "wof:name":"Manitoba Vocational Rehab Svc",
    "wof:placetype":"venue"
},
  "geometry": {"coordinates":[-98.0032958984,49.5070762634],"type":"Point"}
}