{
  "type": "Feature",
  "properties": {
    "iso:country":"CA",
    "sg:address":"109 Rue Bosse",
    "sg:city":"Chicoutimi",
    "sg:classifiers":[
        {
            "category":"Manufacturing",
            "subcategory":"Printing",
            "type":"Manufacturing & Wholesale Goods"
        }
    ],
    "sg:phone":"+1 418 543 1489",
    "sg:postcode":"G7J 1L5",
    "sg:province":"QC",
    "sg:tags":[
        "printer"
    ],
    "wof:name":"Imprimeur Serge Tremblay Inc",
    "wof:placetype":"venue"
},
  "geometry": {"coordinates":[-71.07233428959999,48.4244422913],"type":"Point"}
}