{
  "type": "Feature",
  "properties": {
    "addr:full":"3643 Boul Saint-Laurent Montreal QC H2X 2V5",
    "addr:housenumber":"3643",
    "addr:postcode":"h2x 2v5",
    "addr:street":"Boul Saint-Laurent",
    "iso:country":"CA",
    "sg:address":"3643 Boul Saint-Laurent",
    "sg:city":"Montreal",
    "sg:classifiers":[
        {
            "category":"Recreation",
            "type":"Entertainment"
        }
    ],
    "sg:phone":"+1 514 282 7665",
    "sg:postcode":"H2X 2V5",
    "sg:province":"QC",
    "sg:tags":[
        "parlor",
        "billiard"
    ],
    "wof:name":"Billard Le Swimming",
    "wof:placetype":"venue"
},
  "geometry": {"coordinates":[-73.573257,45.5144],"type":"Point"}
}