{
  "type": "Feature",
  "properties": {
    "iso:country":"CA",
    "sg:address":"617 Wellington St",
    "sg:city":"London",
    "sg:classifiers":[
        {
            "category":"Professional",
            "subcategory":"Research",
            "type":"Services"
        }
    ],
    "sg:phone":"+1 519 679 0641",
    "sg:postcode":"N6A 3R6",
    "sg:province":"ON",
    "sg:tags":[
        "philanthropic",
        "association"
    ],
    "wof:name":"Heart & Stroke Foundation",
    "wof:placetype":"venue"
},
  "geometry": {"coordinates":[-81.248886,42.9916],"type":"Point"}
}