{
  "type": "Feature",
  "properties": {
    "iso:country":"CA",
    "sg:address":"9 Pleasant Grove Terr",
    "sg:city":"Grimsby",
    "sg:classifiers":[
        {
            "category":"Wholesale",
            "subcategory":"Durable Goods & Equipment",
            "type":"Manufacturing & Wholesale Goods"
        }
    ],
    "sg:phone":"+1 905 945 9292",
    "sg:postcode":"L3M 5G8",
    "sg:province":"ON",
    "sg:tags":[
        "instrument",
        "scientific",
        "apparatus"
    ],
    "wof:name":"Kratos Analytical Canada Ltd",
    "wof:placetype":"venue"
},
  "geometry": {"coordinates":[-79.5399398804,43.1847724915],"type":"Point"}
}