{
  "type": "Feature",
  "properties": {
    "addr:full":"1723 Lonsdale Ave North Vancouver BC V7M 2J6",
    "addr:housenumber":"1723",
    "addr:postcode":"v7m 2j6",
    "addr:street":"Lonsdale Ave",
    "iso:country":"CA",
    "sg:address":"1723 Lonsdale Ave",
    "sg:city":"North Vancouver",
    "sg:classifiers":[
        {
            "category":"Personal",
            "subcategory":"Shoe Repair & Shine",
            "type":"Services"
        }
    ],
    "sg:phone":"+1 604 988 8610",
    "sg:postcode":"V7M 2J6",
    "sg:province":"BC",
    "sg:tags":[
        "repairing",
        "boot"
    ],
    "wof:name":"Modern Shoe Renew",
    "wof:placetype":"venue"
},
  "geometry": {"coordinates":[-123.072425842,49.3244361877],"type":"Point"}
}