{
  "type": "Feature",
  "properties": {
    "iso:country":"CA",
    "sg:address":"13 Aspen Rd",
    "sg:city":"Happy Valley-Goose Bay",
    "sg:classifiers":[
        {
            "category":"Retail",
            "subcategory":"Repair Shop",
            "type":"Services"
        }
    ],
    "sg:phone":"+1 709 896 5960",
    "sg:postcode":"A0P 1E0",
    "sg:province":"NL",
    "sg:tags":[
        "carpet",
        "dealer",
        "upholsterer",
        "rug"
    ],
    "wof:name":"Carpet Man",
    "wof:placetype":"venue"
},
  "geometry": {"coordinates":[-60.3864974976,53.3168373108],"type":"Point"}
}