{
  "type": "Feature",
  "properties": {
    "addr:full":"1600 Crois Brandon Lachine QC H8T 2M8",
    "addr:housenumber":"1600",
    "addr:postcode":"h8t 2m8",
    "addr:street":"Crois Brandon",
    "iso:country":"CA",
    "sg:address":"1600 Crois Brandon",
    "sg:city":"Lachine",
    "sg:classifiers":[
        {
            "category":"Wholesale",
            "subcategory":"Groceries",
            "type":"Manufacturing & Wholesale Goods"
        }
    ],
    "sg:phone":"+1 514 875 8866",
    "sg:postcode":"H8T 2M8",
    "sg:province":"QC",
    "sg:tags":[
        "food",
        "product"
    ],
    "wof:name":"Principal Marques Inc",
    "wof:placetype":"venue"
},
  "geometry": {"coordinates":[-73.707824707,45.4549293518],"type":"Point"}
}