{
  "type": "Feature",
  "properties": {
    "addr:full":"Keene ON K0L 2G0",
    "addr:postcode":"k0l 2g0",
    "iso:country":"CA",
    "sg:city":"Keene",
    "sg:classifiers":[
        {
            "category":"Government",
            "subcategory":"Office",
            "type":"Public Place"
        }
    ],
    "sg:phone":"+1 705 295 6852",
    "sg:postcode":"K0L 2G0",
    "sg:province":"ON",
    "sg:tags":[
        "village"
    ],
    "wof:name":"Otonabee Municipal Office",
    "wof:placetype":"venue"
},
  "geometry": {"coordinates":[-78.1632156372,44.240146637],"type":"Point"}
}