{
  "type": "Feature",
  "properties": {
    "addr:full":"3053 Lake Shore Blvd W Etobicoke ON M8V 1K6",
    "addr:housenumber":"3053",
    "addr:postcode":"m8v 1k6",
    "addr:street":"Lake Shore Blvd W",
    "iso:country":"CA",
    "sg:address":"3053 Lake Shore Blvd W",
    "sg:city":"Etobicoke",
    "sg:classifiers":[
        {
            "category":"Travel",
            "subcategory":"Travel Agent",
            "type":"Entertainment"
        }
    ],
    "sg:phone":"+1 416 252 8987",
    "sg:postcode":"M8V 1K6",
    "sg:province":"ON",
    "sg:tags":[
        "agency",
        "bureau"
    ],
    "wof:name":"Lucky Star Travel Ctr Ltd",
    "wof:placetype":"venue"
},
  "geometry": {"coordinates":[-79.5097503662,43.5997085571],"type":"Point"}
}