{
  "type": "Feature",
  "properties": {
    "addr:full":"76 Millersgrove Dr North York ON M2R 3R9",
    "addr:housenumber":"76",
    "addr:postcode":"m2r 3r9",
    "addr:street":"Millersgrove Dr",
    "iso:country":"CA",
    "sg:address":"76 Millersgrove Dr",
    "sg:city":"North York",
    "sg:classifiers":[
        {
            "category":"Professional",
            "subcategory":"Management & Consulting",
            "type":"Services"
        }
    ],
    "sg:phone":"+1 416 650 0389",
    "sg:postcode":"M2R 3R9",
    "sg:province":"ON",
    "sg:tags":[
        "consultant",
        "business"
    ],
    "wof:name":"Criterion Canada",
    "wof:placetype":"venue"
},
  "geometry": {"coordinates":[-79.459076,43.786457],"type":"Point"}
}