{
  "type": "Feature",
  "properties": {
    "addr:full":"577 Wellington St W Toronto ON M5V 1G3",
    "addr:housenumber":"577",
    "addr:postcode":"m5v 1g3",
    "addr:street":"Wellington St W",
    "iso:country":"CA",
    "sg:address":"577 Wellington St W",
    "sg:city":"Toronto",
    "sg:classifiers":[
        {
            "category":"Manufacturing",
            "subcategory":"Printing",
            "type":"Manufacturing & Wholesale Goods"
        }
    ],
    "sg:phone":"+1 416 703 9914",
    "sg:postcode":"M5V 1G3",
    "sg:province":"ON",
    "sg:tags":[
        "lithographer"
    ],
    "wof:name":"Quadratone Graphics Ltd",
    "wof:placetype":"venue"
},
  "geometry": {"coordinates":[-79.40306854249999,43.6422958374],"type":"Point"}
}