{
  "type": "Feature",
  "properties": {
    "addr:full":"425 Nathaniel St Winnipeg MB R3M 3X1",
    "addr:housenumber":"425",
    "addr:postcode":"r3m 3x1",
    "addr:street":"Nathaniel St",
    "iso:country":"CA",
    "sg:address":"425 Nathaniel St",
    "sg:city":"Winnipeg",
    "sg:classifiers":[
        {
            "category":"Restaurant",
            "type":"Food & Drink"
        }
    ],
    "sg:phone":"+1 204 949 6031",
    "sg:postcode":"R3M 3X1",
    "sg:province":"MB",
    "wof:name":"Mc Donald's",
    "wof:placetype":"venue"
},
  "geometry": {"coordinates":[-97.1697921753,49.8571014404],"type":"Point"}
}