{
  "type": "Feature",
  "properties": {
    "iso:country":"CA",
    "sg:address":"15777 Rue Sherbrooke E",
    "sg:city":"Pointe-Aux-Trembles",
    "sg:classifiers":[
        {
            "category":"Travel",
            "subcategory":"Hotels & Motels",
            "type":"Entertainment"
        }
    ],
    "sg:phone":"+1 514 642 2131",
    "sg:postcode":"H1A 3R1",
    "sg:province":"QC",
    "wof:name":"Motel Pignons Rouges",
    "wof:placetype":"venue"
},
  "geometry": {"coordinates":[-73.4954833984,45.6951713562],"type":"Point"}
}