{
  "type": "Feature",
  "properties": {
    "iso:country":"CA",
    "sg:address":"2848 Rue Hertel",
    "sg:city":"Sherbrooke",
    "sg:classifiers":[
        {
            "category":"Insurance",
            "subcategory":"Insurance Agent",
            "type":"Services"
        }
    ],
    "sg:phone":"+1 819 564 3030",
    "sg:postcode":"J1L 1E1",
    "sg:province":"QC",
    "sg:tags":[
        "adjuster",
        "appraiser"
    ],
    "wof:name":"Estimations Dionne Inc",
    "wof:placetype":"venue"
},
  "geometry": {"coordinates":[-71.9419708252,45.3946800232],"type":"Point"}
}