{
  "type": "Feature",
  "properties": {
    "addr:full":"47 King St Omemee ON K0L 2W0",
    "addr:housenumber":"47",
    "addr:postcode":"k0l 2w0",
    "addr:street":"King St",
    "iso:country":"CA",
    "sg:address":"47 King St",
    "sg:city":"Omemee",
    "sg:classifiers":[
        {
            "category":"Recreation",
            "type":"Entertainment"
        }
    ],
    "sg:phone":"+1 705 799 5095",
    "sg:postcode":"K0L 2W0",
    "sg:province":"ON",
    "sg:tags":[
        "hall",
        "auditorium"
    ],
    "wof:name":"Royal Canadian Legion Branch",
    "wof:placetype":"venue"
},
  "geometry": {"coordinates":[-78.55652600000001,44.299774],"type":"Point"}
}