{
  "type": "Feature",
  "properties": {
    "addr:full":"347 Willow St Truro NS B2N 5A6",
    "addr:housenumber":"347",
    "addr:postcode":"b2n 5a6",
    "addr:street":"Willow St",
    "iso:country":"CA",
    "sg:address":"347 Willow St",
    "sg:city":"Truro",
    "sg:classifiers":[
        {
            "category":"Banks & Credit Unions",
            "subcategory":"Bank",
            "type":"Services"
        }
    ],
    "sg:phone":"+1 902 893 7134",
    "sg:postcode":"B2N 5A6",
    "sg:province":"NS",
    "wof:name":"Community Credit Union",
    "wof:placetype":"venue"
},
  "geometry": {"coordinates":[-63.293674,45.353577],"type":"Point"}
}