{
  "type": "Feature",
  "properties": {
    "iso:country":"CA",
    "sg:address":"58 Centennial Pky N",
    "sg:city":"Hamilton",
    "sg:classifiers":[
        {
            "category":"Shopping",
            "subcategory":"Clothing, Apparel, & Fashions",
            "type":"Retail Goods"
        }
    ],
    "sg:phone":"+1 905 573 4242",
    "sg:postcode":"L8E 1H6",
    "sg:province":"ON",
    "sg:tags":[
        "lingerie"
    ],
    "wof:name":"Stag Shop",
    "wof:placetype":"venue"
},
  "geometry": {"coordinates":[-79.7633514404,43.2296981812],"type":"Point"}
}