{
  "type": "Feature",
  "properties": {
    "addr:full":"40 Dominion Rd Etobicoke ON M8W 1J7",
    "addr:housenumber":"40",
    "addr:postcode":"m8w 1j7",
    "addr:street":"Dominion Rd",
    "iso:country":"CA",
    "sg:address":"40 Dominion Rd",
    "sg:city":"Etobicoke",
    "sg:classifiers":[
        {
            "category":"Building & Trades",
            "subcategory":"Construction",
            "type":"Services"
        }
    ],
    "sg:phone":"+1 416 995 4022",
    "sg:postcode":"M8W 1J7",
    "sg:province":"ON",
    "sg:tags":[
        "painter"
    ],
    "wof:name":"Four Seasons Painting & Decor",
    "wof:placetype":"venue"
},
  "geometry": {"coordinates":[-79.53491200000001,43.592094],"type":"Point"}
}