{
  "type": "Feature",
  "properties": {
    "addr:full":"Charlesbourg QC G1G 4C6",
    "addr:postcode":"g1g 4c6",
    "iso:country":"CA",
    "sg:city":"Charlesbourg",
    "sg:classifiers":[
        {
            "category":"Personal",
            "subcategory":"Beauty Salon",
            "type":"Services"
        }
    ],
    "sg:phone":"+1 418 622 3036",
    "sg:postcode":"G1G 4C6",
    "sg:province":"QC",
    "wof:name":"Salon Signature Coiffure",
    "wof:placetype":"venue"
},
  "geometry": {"coordinates":[-71.273079,46.865932],"type":"Point"}
}