{
  "type": "Feature",
  "properties": {
    "addr:full":"568 Greenbriar Dr # 108 Sudbury ON P3B 3X5",
    "addr:housenumber":"568",
    "addr:postcode":"p3b 3x5",
    "addr:street":"Greenbriar Dr # 108",
    "iso:country":"CA",
    "sg:address":"568 Greenbriar Dr # 108",
    "sg:city":"Sudbury",
    "sg:classifiers":[
        {
            "category":"Real Estate",
            "subcategory":"Real Estate Operator",
            "type":"Services"
        }
    ],
    "sg:phone":"+1 705 566 7593",
    "sg:postcode":"P3B 3X5",
    "sg:province":"ON",
    "sg:tags":[
        "apartment"
    ],
    "wof:name":"Greenbriar Apartments",
    "wof:placetype":"venue"
},
  "geometry": {"coordinates":[-80.9332351685,46.499294281],"type":"Point"}
}