{
  "type": "Feature",
  "properties": {
    "iso:country":"CA",
    "sg:city":"Uxbridge",
    "sg:classifiers":[
        {
            "category":"Health Services",
            "subcategory":"Optometrist",
            "type":"Services"
        }
    ],
    "sg:phone":"+1 905 852 6733",
    "sg:postcode":"L9P 1H4",
    "sg:province":"ON",
    "wof:name":"Banh, VI Tu OD",
    "wof:placetype":"venue"
},
  "geometry": {"coordinates":[-79.124718,44.104328],"type":"Point"}
}