{
  "type": "Feature",
  "properties": {
    "addr:full":"Saint-Come-Liniere QC G0M 1J0",
    "addr:postcode":"g0m 1j0",
    "iso:country":"CA",
    "sg:city":"Saint-Come-Liniere",
    "sg:classifiers":[
        {
            "category":"Personal",
            "subcategory":"Beauty Salon",
            "type":"Services"
        }
    ],
    "sg:phone":"+1 418 685 3013",
    "sg:postcode":"G0M 1J0",
    "sg:province":"QC",
    "wof:name":"Champagne, Jovette",
    "wof:placetype":"venue"
},
  "geometry": {"coordinates":[-70.51285552980001,46.0483970642],"type":"Point"}
}