{
  "type": "Feature",
  "properties": {
    "iso:country":"CA",
    "sg:city":"North Bay",
    "sg:classifiers":[
        {
            "category":"Restaurant",
            "type":"Food & Drink"
        }
    ],
    "sg:phone":"+1 705 472 0032",
    "sg:postcode":"P1B 1G5",
    "sg:province":"ON",
    "wof:name":"Urban Deli & Cafe",
    "wof:placetype":"venue"
},
  "geometry": {"coordinates":[-79.46198272709999,46.3112792969],"type":"Point"}
}