{
  "type": "Feature",
  "properties": {
    "addr:full":"Edmonton AB T6C 0Z8",
    "addr:postcode":"t6c 0z8",
    "iso:country":"CA",
    "sg:city":"Edmonton",
    "sg:classifiers":[
        {
            "category":"Personal",
            "type":"Services"
        }
    ],
    "sg:phone":"+1 780 431 1925",
    "sg:postcode":"T6C 0Z8",
    "sg:province":"AB",
    "sg:tags":[
        "therapist",
        "massage"
    ],
    "wof:name":"Whyte Avenue Therapeautic",
    "wof:placetype":"venue"
},
  "geometry": {"coordinates":[-113.476265,53.518219],"type":"Point"}
}