{
  "type": "Feature",
  "properties": {
    "addr:full":"Vanderhoof BC V0J 3A0",
    "addr:postcode":"v0j 3a0",
    "iso:country":"CA",
    "sg:city":"Vanderhoof",
    "sg:classifiers":[
        {
            "category":"Shopping",
            "type":"Retail Goods"
        }
    ],
    "sg:phone":"+1 250 567 5101",
    "sg:postcode":"V0J 3A0",
    "sg:province":"BC",
    "sg:tags":[
        "hearing",
        "equipment",
        "supply",
        "impaired"
    ],
    "wof:name":"Canadian Hearing Care",
    "wof:placetype":"venue"
},
  "geometry": {"coordinates":[-124.00918579099999,54.0254898071],"type":"Point"}
}