{
  "type": "Feature",
  "properties": {
    "addr:full":"Mission BC V2V 1G2",
    "addr:postcode":"v2v 1g2",
    "iso:country":"CA",
    "sg:city":"Mission",
    "sg:classifiers":[
        {
            "category":"Health Services",
            "subcategory":"Clinic",
            "type":"Services"
        }
    ],
    "sg:phone":"+1 604 820 3166",
    "sg:postcode":"V2V 1G2",
    "sg:province":"BC",
    "sg:tags":[
        "agency",
        "welfare"
    ],
    "wof:name":"Canadian Cancer Society",
    "wof:placetype":"venue"
},
  "geometry": {"coordinates":[-122.28282165500001,49.1599884033],"type":"Point"}
}