{
  "type": "Feature",
  "properties": {
    "iso:country":"CA",
    "sg:city":"Saint-Hubert",
    "sg:classifiers":[
        {
            "category":"Wholesale",
            "subcategory":"Books, Periodicals, & Newspapers",
            "type":"Manufacturing & Wholesale Goods"
        }
    ],
    "sg:phone":"+1 450 926 8313",
    "sg:postcode":"J3Y 5T6",
    "sg:province":"QC",
    "sg:tags":[
        "distributor"
    ],
    "wof:name":"Medias Transcontinental Inc",
    "wof:placetype":"venue"
},
  "geometry": {"coordinates":[-73.44339,45.500755],"type":"Point"}
}