{
  "type": "Feature",
  "properties": {
    "addr:full":"Surrey BC V3S 6C4",
    "addr:postcode":"v3s 6c4",
    "iso:country":"CA",
    "sg:city":"Surrey",
    "sg:classifiers":[
        {
            "category":"Taxi",
            "type":"Transportation"
        }
    ],
    "sg:phone":"+1 604 596 6666",
    "sg:postcode":"V3S 6C4",
    "sg:province":"BC",
    "sg:tags":[
        "taxicab"
    ],
    "wof:name":"Pacific Cabs",
    "wof:placetype":"venue"
},
  "geometry": {"coordinates":[-122.72477000000001,49.102432],"type":"Point"}
}