{
  "type": "Feature",
  "properties": {
    "addr:full":"North York ON M6A 1J6",
    "addr:postcode":"m6a 1j6",
    "iso:country":"CA",
    "sg:city":"North York",
    "sg:classifiers":[
        {
            "category":"Professional",
            "subcategory":"Detective & Security Services",
            "type":"Services"
        }
    ],
    "sg:phone":"+1 416 781 7044",
    "sg:postcode":"M6A 1J6",
    "sg:province":"ON",
    "sg:tags":[
        "investigator"
    ],
    "wof:name":"Ais Svc",
    "wof:placetype":"venue"
},
  "geometry": {"coordinates":[-79.459236,43.717854],"type":"Point"}
}