{
  "type": "Feature",
  "properties": {
    "addr:full":"Gooderham ON K0M 1R0",
    "addr:postcode":"k0m 1r0",
    "iso:country":"CA",
    "sg:city":"Gooderham",
    "sg:classifiers":[
        {
            "category":"Manufacturing",
            "subcategory":"Furniture",
            "type":"Manufacturing & Wholesale Goods"
        }
    ],
    "sg:phone":"+1 705 447 2435",
    "sg:postcode":"K0M 1R0",
    "sg:province":"ON",
    "wof:name":"Wicker Works",
    "wof:placetype":"venue"
},
  "geometry": {"coordinates":[-78.37925720210001,44.9063415527],"type":"Point"}
}