{
  "type": "Feature",
  "properties": {
    "addr:full":"285 Eglinton Ave E Toronto ON M4P 1L3",
    "addr:housenumber":"285",
    "addr:postcode":"m4p 1l3",
    "addr:street":"Eglinton Ave E",
    "iso:country":"CA",
    "sg:address":"285 Eglinton Ave E",
    "sg:city":"Toronto",
    "sg:classifiers":[
        {
            "category":"Professional",
            "subcategory":"Accounting & Tax Preparation",
            "type":"Services"
        }
    ],
    "sg:phone":"+1 416 485 5502",
    "sg:postcode":"M4P 1L3",
    "sg:province":"ON",
    "sg:tags":[
        "accountant"
    ],
    "wof:name":"Freedman Gould Chartered Accts",
    "wof:placetype":"venue"
},
  "geometry": {"coordinates":[-79.3881225586,43.7086982727],"type":"Point"}
}