{
  "type": "Feature",
  "properties": {
    "iso:country":"CA",
    "sg:address":"601 Broadway W # U6",
    "sg:city":"Vancouver",
    "sg:classifiers":[
        {
            "category":"Health Services",
            "subcategory":"Doctor",
            "type":"Services"
        }
    ],
    "sg:phone":"+1 604 685 7516",
    "sg:postcode":"V5Z 4C2",
    "sg:province":"BC",
    "sg:tags":[
        "physician",
        "surgeon"
    ],
    "wof:name":"Chang, Terence A MD",
    "wof:placetype":"venue"
},
  "geometry": {"coordinates":[-123.117721558,49.263469696],"type":"Point"}
}