{
  "type": "Feature",
  "properties": {
    "addr:full":"West Vancouver BC V7W 3C5",
    "addr:postcode":"v7w 3c5",
    "iso:country":"CA",
    "sg:city":"West Vancouver",
    "sg:classifiers":[
        {
            "category":"Health Services",
            "subcategory":"Doctor",
            "type":"Services"
        }
    ],
    "sg:phone":"+1 604 922 1544",
    "sg:postcode":"V7W 3C5",
    "sg:province":"BC",
    "sg:tags":[
        "physician",
        "clinic",
        "surgeon"
    ],
    "wof:name":"Caulfield Village Med Clinic",
    "wof:placetype":"venue"
},
  "geometry": {"coordinates":[-123.253838,49.350281],"type":"Point"}
}