{
  "type": "Feature",
  "properties": {
    "iso:country":"CA",
    "sg:address":"491 Boul Lebeau",
    "sg:city":"Saint-Laurent",
    "sg:classifiers":[
        {
            "category":"Building & Trades",
            "subcategory":"Construction",
            "type":"Services"
        }
    ],
    "sg:phone":"+1 514 333 9083",
    "sg:postcode":"H4N 1S2",
    "sg:province":"QC",
    "sg:tags":[
        "contractor"
    ],
    "wof:name":"Construction Nasco Enr",
    "wof:placetype":"venue"
},
  "geometry": {"coordinates":[-73.660873,45.526726],"type":"Point"}
}