{
  "type": "Feature",
  "properties": {
    "addr:full":"445 Rue Saint-Jean Drummondville QC J2B 5L7",
    "addr:housenumber":"445",
    "addr:postcode":"j2b 5l7",
    "addr:street":"Rue Saint-Jean",
    "iso:country":"CA",
    "sg:address":"445 Rue Saint-Jean",
    "sg:city":"Drummondville",
    "sg:classifiers":[
        {
            "category":"Restaurant",
            "type":"Food & Drink"
        }
    ],
    "sg:phone":"+1 819 477 2127",
    "sg:postcode":"J2B 5L7",
    "sg:province":"QC",
    "sg:tags":[
        "delicatessen"
    ],
    "wof:name":"Charcuterie A Proulx",
    "wof:placetype":"venue"
},
  "geometry": {"coordinates":[-72.4857788086,45.8757247925],"type":"Point"}
}