{
  "type": "Feature",
  "properties": {
    "addr:full":"63 3 Av O Palmarolle QC J0Z 3C0",
    "addr:postcode":"j0z 3c0",
    "addr:street":"63 3 Av O",
    "iso:country":"CA",
    "sg:address":"63 3 Av O",
    "sg:city":"Palmarolle",
    "sg:classifiers":[
        {
            "category":"Personal",
            "subcategory":"Beauty Salon",
            "type":"Services"
        }
    ],
    "sg:phone":"+1 819 787 2496",
    "sg:postcode":"J0Z 3C0",
    "sg:province":"QC",
    "wof:name":"Macameau, Fernand",
    "wof:placetype":"venue"
},
  "geometry": {"coordinates":[-79.2017364502,48.6632957458],"type":"Point"}
}