{
  "type": "Feature",
  "properties": {
    "addr:full":"4727 Marine Ave Powell River BC V8A 2L2",
    "addr:housenumber":"4727",
    "addr:postcode":"v8a 2l2",
    "addr:street":"Marine Ave Powell",
    "iso:country":"CA",
    "sg:address":"4727 Marine Ave",
    "sg:city":"Powell River",
    "sg:classifiers":[
        {
            "category":"Social Services",
            "type":"Services"
        }
    ],
    "sg:phone":"+1 604 485 2004",
    "sg:postcode":"V8A 2L2",
    "sg:province":"BC",
    "sg:tags":[
        "organization",
        "welfare"
    ],
    "wof:name":"Powell River Employment Prgrms",
    "wof:placetype":"venue"
},
  "geometry": {"coordinates":[-124.52913700000001,49.843952],"type":"Point"}
}