{
  "type": "Feature",
  "properties": {
    "addr:full":"1820 Bayview Ave Toronto ON M4G 4G7",
    "addr:housenumber":"1820",
    "addr:postcode":"m4g 4g7",
    "addr:street":"Bayview Ave",
    "iso:country":"CA",
    "sg:address":"1820 Bayview Ave",
    "sg:city":"Toronto",
    "sg:classifiers":[
        {
            "category":"Home & Garden",
            "subcategory":"Building Materials",
            "type":"Retail Goods"
        }
    ],
    "sg:phone":"+1 416 485 1234",
    "sg:postcode":"M4G 4G7",
    "sg:province":"ON",
    "sg:tags":[
        "windows"
    ],
    "wof:name":"Pella Window & Door Store",
    "wof:placetype":"venue"
},
  "geometry": {"coordinates":[-79.377548,43.712582],"type":"Point"}
}