{
  "type": "Feature",
  "properties": {
    "addr:full":"1176 Rue Notre-Dame Chicoutimi QC G7H 1X6",
    "addr:housenumber":"1176",
    "addr:postcode":"g7h 1x6",
    "addr:street":"Rue Notre-Dame",
    "iso:country":"CA",
    "sg:address":"1176 Rue Notre-Dame",
    "sg:city":"Chicoutimi",
    "sg:classifiers":[
        {
            "category":"Health Services",
            "subcategory":"Nursing And Care Facility",
            "type":"Services"
        }
    ],
    "sg:phone":"+1 418 696 1176",
    "sg:postcode":"G7H 1X6",
    "sg:province":"QC",
    "sg:tags":[
        "home",
        "rest",
        "site",
        "reception",
        "wedding"
    ],
    "wof:name":"Maison Notre Dame Du Saguenay",
    "wof:placetype":"venue"
},
  "geometry": {"coordinates":[-71.033432,48.423355],"type":"Point"}
}