{
  "type": "Feature",
  "properties": {
    "iso:country":"CA",
    "sg:city":"Burnaby",
    "sg:classifiers":[
        {
            "category":"Shopping",
            "subcategory":"Musical Instruments",
            "type":"Retail Goods"
        }
    ],
    "sg:phone":"+1 604 294 1777",
    "sg:postcode":"V5C 2J6",
    "sg:province":"BC",
    "wof:name":"Massullo Music",
    "wof:placetype":"venue"
},
  "geometry": {"coordinates":[-123.010169983,49.2809867859],"type":"Point"}
}