{
  "type": "Feature",
  "properties": {
    "addr:full":"20 Rue Desbiens # 100A Amqui QC G5J 3P1",
    "addr:housenumber":"20",
    "addr:postcode":"g5j 3p1",
    "addr:street":"Rue Desbiens # 100A",
    "iso:country":"CA",
    "sg:address":"20 Rue Desbiens # 100A",
    "sg:city":"Amqui",
    "sg:classifiers":[
        {
            "category":"Professional",
            "subcategory":"Accounting & Tax Preparation",
            "type":"Services"
        }
    ],
    "sg:phone":"+1 418 629 2852",
    "sg:postcode":"G5J 3P1",
    "sg:province":"QC",
    "sg:tags":[
        "accountant"
    ],
    "wof:name":"Raymond Chabot Grant Thornton",
    "wof:placetype":"venue"
},
  "geometry": {"coordinates":[-67.426559,48.465149],"type":"Point"}
}