{
  "type": "Feature",
  "properties": {
    "addr:full":"Calgary AB T2H 2S3",
    "addr:postcode":"t2h 2s3",
    "iso:country":"CA",
    "sg:city":"Calgary",
    "sg:classifiers":[
        {
            "category":"Mining & Drilling",
            "type":"Manufacturing & Wholesale Goods"
        }
    ],
    "sg:phone":"+1 403 258 3630",
    "sg:postcode":"T2H 2S3",
    "sg:province":"AB",
    "sg:tags":[
        "company"
    ],
    "wof:name":"Stratabound Minerals Corp",
    "wof:placetype":"venue"
},
  "geometry": {"coordinates":[-114.067886352,51.0014686584],"type":"Point"}
}