{
  "type": "Feature",
  "properties": {
    "addr:full":"Saint-Adolphe-D'Howard QC J0T 2B0",
    "addr:postcode":"j0t 2b0",
    "iso:country":"CA",
    "sg:city":"Saint-Adolphe-D'Howard",
    "sg:classifiers":[
        {
            "category":"Cinema",
            "subcategory":"Movie Theater",
            "type":"Entertainment"
        }
    ],
    "sg:phone":"+1 450 226 7373",
    "sg:postcode":"J0T 2B0",
    "sg:province":"QC",
    "wof:name":"Theatre Medieval Cire D'Howard",
    "wof:placetype":"venue"
},
  "geometry": {"coordinates":[-71.003319,45.383507],"type":"Point"}
}