{
  "type": "Feature",
  "properties": {
    "iso:country":"CA",
    "sg:address":"534 Gormanville Rd",
    "sg:city":"North Bay",
    "sg:classifiers":[
        {
            "category":"Wholesale",
            "subcategory":"Auto Parts",
            "type":"Manufacturing & Wholesale Goods"
        }
    ],
    "sg:phone":"+1 705 472 6527",
    "sg:postcode":"P1B 4V5",
    "sg:province":"ON",
    "sg:tags":[
        "automobile",
        "rebuilt"
    ],
    "wof:name":"P & G Auto Parts",
    "wof:placetype":"venue"
},
  "geometry": {"coordinates":[-79.48732757569999,46.3256759644],"type":"Point"}
}