{
  "type": "Feature",
  "properties": {
    "addr:full":"800 Portage Ave Winnipeg MB R3G 0N4",
    "addr:housenumber":"800",
    "addr:postcode":"r3g 0n4",
    "addr:street":"Portage Ave",
    "iso:country":"CA",
    "sg:address":"800 Portage Ave",
    "sg:city":"Winnipeg",
    "sg:classifiers":[
        {
            "category":"Social Services",
            "subcategory":"Child Care",
            "type":"Services"
        }
    ],
    "sg:phone":"+1 204 945 0210",
    "sg:postcode":"R3G 0N4",
    "sg:province":"MB",
    "wof:name":"Provincial Employees Care",
    "wof:placetype":"venue"
},
  "geometry": {"coordinates":[-97.165764,49.88649],"type":"Point"}
}