{
  "type": "Feature",
  "properties": {
    "addr:full":"36363 Auguston Pky S Abbotsford BC V3G 2Y7",
    "addr:housenumber":"36363",
    "addr:postcode":"v3g 2y7",
    "addr:street":"Auguston Pky",
    "iso:country":"CA",
    "sg:address":"36363 Auguston Pky S",
    "sg:city":"Abbotsford",
    "sg:classifiers":[
        {
            "category":"Building & Trades",
            "subcategory":"Construction",
            "type":"Services"
        }
    ],
    "sg:phone":"+1 604 850 7882",
    "sg:postcode":"V3G 2Y7",
    "sg:province":"BC",
    "sg:tags":[
        "contractor"
    ],
    "wof:name":"Blauson Homes Inc",
    "wof:placetype":"venue"
},
  "geometry": {"coordinates":[-122.217834473,49.0828514099],"type":"Point"}
}