{
  "type": "Feature",
  "properties": {
    "addr:full":"614 Boul Manseau Joliette QC J6E 3E4",
    "addr:housenumber":"614",
    "addr:postcode":"j6e 3e4",
    "addr:street":"Boul Manseau",
    "iso:country":"CA",
    "sg:address":"614 Boul Manseau",
    "sg:city":"Joliette",
    "sg:classifiers":[
        {
            "category":"Government",
            "subcategory":"Office",
            "type":"Public Place"
        }
    ],
    "sg:phone":"+1 450 756 8055",
    "sg:postcode":"J6E 3E4",
    "sg:province":"QC",
    "sg:tags":[
        "village"
    ],
    "wof:name":"Joliette Hotel DE Ville & Svc",
    "wof:placetype":"venue"
},
  "geometry": {"coordinates":[-73.4424133301,46.0234413147],"type":"Point"}
}