{
  "type": "Feature",
  "properties": {
    "addr:full":"West Vancouver BC V7V 1L3",
    "addr:postcode":"v7v 1l3",
    "iso:country":"CA",
    "sg:city":"West Vancouver",
    "sg:classifiers":[
        {
            "category":"Professional",
            "subcategory":"Business Services",
            "type":"Services"
        }
    ],
    "sg:phone":"+1 604 926 4450",
    "sg:postcode":"V7V 1L3",
    "sg:province":"BC",
    "sg:tags":[
        "notary"
    ],
    "wof:name":"Russells",
    "wof:placetype":"venue"
},
  "geometry": {"coordinates":[-123.179497,49.334385],"type":"Point"}
}