{
  "type": "Feature",
  "properties": {
    "iso:country":"CA",
    "sg:city":"Saint-Anicet",
    "sg:classifiers":[
        {
            "category":"Shopping",
            "subcategory":"Computers & Home Electronics",
            "type":"Retail Goods"
        }
    ],
    "sg:phone":"+1 450 264 2565",
    "sg:postcode":"J0S 1M0",
    "sg:province":"QC",
    "sg:tags":[
        "equipment",
        "video"
    ],
    "wof:name":"Club Video Dancause Enr",
    "wof:placetype":"venue"
},
  "geometry": {"coordinates":[-74.3591918945,45.137134552],"type":"Point"}
}