{
  "type": "Feature",
  "properties": {
    "iso:country":"CA",
    "sg:address":"364 Belsize Dr",
    "sg:city":"Toronto",
    "sg:classifiers":[
        {
            "category":"Social Services",
            "subcategory":"Child Care",
            "type":"Services"
        }
    ],
    "sg:phone":"+1 416 484 4881",
    "sg:postcode":"M4S 1N2",
    "sg:province":"ON",
    "wof:name":"Maurice Cody Child Care",
    "wof:placetype":"venue"
},
  "geometry": {"coordinates":[-79.3778762817,43.7046356201],"type":"Point"}
}