{
  "type": "Feature",
  "properties": {
    "addr:full":"2401 99th St North Battleford SK S9A 0S7",
    "addr:housenumber":"2401",
    "addr:postcode":"s9a 0s7",
    "addr:street":"99Th St",
    "iso:country":"CA",
    "sg:address":"2401 99th St",
    "sg:city":"North Battleford",
    "sg:classifiers":[
        {
            "category":"Restaurant",
            "type":"Food & Drink"
        }
    ],
    "sg:phone":"+1 306 446 4555",
    "sg:postcode":"S9A 0S7",
    "sg:province":"SK",
    "wof:name":"Country Cuisine",
    "wof:placetype":"venue"
},
  "geometry": {"coordinates":[-108.301552,52.793995],"type":"Point"}
}