{
  "type": "Feature",
  "properties": {
    "addr:full":"76 Townsend St Sydney NS B1P 5C8",
    "addr:housenumber":"76",
    "addr:postcode":"b1p 5c8",
    "addr:street":"Townsend St",
    "iso:country":"CA",
    "sg:address":"76 Townsend St",
    "sg:city":"Sydney",
    "sg:classifiers":[
        {
            "category":"Personal",
            "subcategory":"Beauty Salon",
            "type":"Services"
        }
    ],
    "sg:phone":"+1 902 562 3149",
    "sg:postcode":"B1P 5C8",
    "sg:province":"NS",
    "wof:name":"Kathy Ann Hair Salon",
    "wof:placetype":"venue"
},
  "geometry": {"coordinates":[-60.1930274963,46.1345748901],"type":"Point"}
}