{
  "type": "Feature",
  "properties": {
    "addr:full":"37 Elizabeth St W Creemore ON L0M 1G0",
    "addr:housenumber":"37",
    "addr:postcode":"l0m 1g0",
    "addr:street":"Elizabeth St W Creemore",
    "iso:country":"CA",
    "sg:address":"37 Elizabeth St W",
    "sg:city":"Creemore",
    "sg:classifiers":[
        {
            "category":"Personal",
            "subcategory":"Beauty Salon",
            "type":"Services"
        }
    ],
    "sg:phone":"+1 705 466 2838",
    "sg:postcode":"L0M 1G0",
    "sg:province":"ON",
    "wof:name":"Linda's Hair Fashions",
    "wof:placetype":"venue"
},
  "geometry": {"coordinates":[-80.10949707029999,44.3241081238],"type":"Point"}
}