{
  "type": "Feature",
  "properties": {
    "addr:full":"81 Rue Onulphe-Peltier L'Epiphanie QC J5X 3W9",
    "addr:housenumber":"81",
    "addr:postcode":"j5x 3w9",
    "addr:street":"Rue Onulphe-Peltier L'Epiphanie",
    "iso:country":"CA",
    "sg:address":"81 Rue Onulphe-Peltier",
    "sg:city":"L'Epiphanie",
    "sg:classifiers":[
        {
            "category":"Manufacturing",
            "subcategory":"Furniture",
            "type":"Manufacturing & Wholesale Goods"
        }
    ],
    "sg:phone":"+1 450 588 2539",
    "sg:postcode":"J5X 3W9",
    "sg:province":"QC",
    "wof:name":"Meubles Poitras Inc",
    "wof:placetype":"venue"
},
  "geometry": {"coordinates":[-73.47905,45.845562],"type":"Point"}
}