{
  "type": "Feature",
  "properties": {
    "iso:country":"CA",
    "sg:city":"Concord",
    "sg:classifiers":[
        {
            "category":"Wholesale",
            "subcategory":"Hardware",
            "type":"Manufacturing & Wholesale Goods"
        }
    ],
    "sg:phone":"+1 905 738 8886",
    "sg:postcode":"L4K 4B4",
    "sg:province":"ON",
    "wof:name":"Canmade Furniture Products Inc",
    "wof:placetype":"venue"
},
  "geometry": {"coordinates":[-79.539253,43.807541],"type":"Point"}
}