{
  "type": "Feature",
  "properties": {
    "iso:country":"CA",
    "sg:address":"1169 Maidstone Cres",
    "sg:city":"Oakville",
    "sg:classifiers":[
        {
            "category":"Real Estate",
            "subcategory":"Real Estate Agent",
            "type":"Services"
        }
    ],
    "sg:phone":"+1 905 827 8729",
    "sg:postcode":"L6M 1C2",
    "sg:province":"ON",
    "sg:tags":[
        "cooperative"
    ],
    "wof:name":"Trafalgar CO Op",
    "wof:placetype":"venue"
},
  "geometry": {"coordinates":[-79.7105255127,43.4471206665],"type":"Point"}
}