{
  "type": "Feature",
  "properties": {
    "addr:full":"Winnipeg MB R2X 2Y3",
    "addr:postcode":"r2x 2y3",
    "iso:country":"CA",
    "sg:city":"Winnipeg",
    "sg:classifiers":[
        {
            "category":"Wholesale",
            "subcategory":"Construction Materials",
            "type":"Manufacturing & Wholesale Goods"
        }
    ],
    "sg:phone":"+1 204 786 3443",
    "sg:postcode":"R2X 2Y3",
    "sg:province":"MB",
    "sg:tags":[
        "tile"
    ],
    "wof:name":"B J Ceramic Tile",
    "wof:placetype":"venue"
},
  "geometry": {"coordinates":[-97.19536600000001,49.927036],"type":"Point"}
}