{
  "type": "Feature",
  "properties": {
    "addr:full":"32 Wellington St W Aurora ON L4G 2N8",
    "addr:housenumber":"32",
    "addr:postcode":"l4g 2n8",
    "addr:street":"Wellington St W",
    "iso:country":"CA",
    "sg:address":"32 Wellington St W",
    "sg:city":"Aurora",
    "sg:classifiers":[
        {
            "category":"Food & Beverages",
            "subcategory":"Liquor & Beverages",
            "type":"Retail Goods"
        }
    ],
    "sg:phone":"+1 905 726 9872",
    "sg:postcode":"L4G 2N8",
    "sg:province":"ON",
    "sg:tags":[
        "beer",
        "ale"
    ],
    "wof:name":"Rollick Beverage CO",
    "wof:placetype":"venue"
},
  "geometry": {"coordinates":[-79.4694137573,43.9993286133],"type":"Point"}
}