{
  "type": "Feature",
  "properties": {
    "iso:country":"CA",
    "sg:address":"444 5E Rue",
    "sg:city":"Shawinigan",
    "sg:classifiers":[
        {
            "category":"Government",
            "subcategory":"Office",
            "type":"Public Place"
        }
    ],
    "sg:phone":"+1 819 537 1820",
    "sg:postcode":"G9N 1E6",
    "sg:province":"QC",
    "sg:tags":[
        "member",
        "legislative",
        "assembly"
    ],
    "wof:name":"Jean Chretien Depute",
    "wof:placetype":"venue"
},
  "geometry": {"coordinates":[-72.7484970093,46.5406532288],"type":"Point"}
}