{
  "type": "Feature",
  "properties": {
    "addr:full":"201 Markham St Toronto ON M6J 2G7",
    "addr:housenumber":"201",
    "addr:postcode":"m6j 2g7",
    "addr:street":"Markham St",
    "iso:country":"CA",
    "sg:address":"201 Markham St",
    "sg:city":"Toronto",
    "sg:classifiers":[
        {
            "category":"Restaurant",
            "type":"Food & Drink"
        }
    ],
    "sg:phone":"+1 416 264 3345",
    "sg:postcode":"M6J 2G7",
    "sg:province":"ON",
    "wof:name":"Chandra's Take Out Restaurant",
    "wof:placetype":"venue"
},
  "geometry": {"coordinates":[-79.407623,43.653465],"type":"Point"}
}