{
  "type": "Feature",
  "properties": {
    "addr:full":"50 Rue Robitaille Victoriaville QC G6P 4N2",
    "addr:housenumber":"50",
    "addr:postcode":"g6p 4n2",
    "addr:street":"Rue Robitaille",
    "iso:country":"CA",
    "sg:address":"50 Rue Robitaille",
    "sg:city":"Victoriaville",
    "sg:classifiers":[
        {
            "category":"Organizations",
            "subcategory":"Religious Organization",
            "type":"Services"
        }
    ],
    "sg:phone":"+1 819 758 5474",
    "sg:postcode":"G6P 4N2",
    "sg:province":"QC",
    "sg:tags":[
        "house",
        "retreat"
    ],
    "wof:name":"Auberge DE LA Sagesse",
    "wof:placetype":"venue"
},
  "geometry": {"coordinates":[-71.94385528559999,46.053981781],"type":"Point"}
}