{
  "type": "Feature",
  "properties": {
    "addr:full":"23 Queen Rd Montague PE C0A 1R0",
    "addr:housenumber":"23",
    "addr:postcode":"c0a 1r0",
    "addr:street":"Queen Rd",
    "iso:country":"CA",
    "sg:address":"23 Queen Rd",
    "sg:city":"Montague",
    "sg:classifiers":[
        {
            "category":"Health Services",
            "subcategory":"Optometrist",
            "type":"Services"
        }
    ],
    "sg:phone":"+1 902 838 3338",
    "sg:postcode":"C0A 1R0",
    "sg:province":"PE",
    "wof:name":"Jinks, L W L OD",
    "wof:placetype":"venue"
},
  "geometry": {"coordinates":[-62.646858,46.16972],"type":"Point"}
}