{
  "type": "Feature",
  "properties": {
    "addr:full":"Vancouver BC V6E 2Y3",
    "addr:postcode":"v6e 2y3",
    "iso:country":"CA",
    "sg:city":"Vancouver",
    "sg:classifiers":[
        {
            "category":"Shopping",
            "subcategory":"Clothing, Apparel, & Fashions",
            "type":"Retail Goods"
        }
    ],
    "sg:phone":"+1 604 685 4241",
    "sg:postcode":"V6E 2Y3",
    "sg:province":"BC",
    "sg:tags":[
        "fur",
        "business"
    ],
    "wof:name":"Ultimo Furs",
    "wof:placetype":"venue"
},
  "geometry": {"coordinates":[-123.121849,49.284756],"type":"Point"}
}