{
  "type": "Feature",
  "properties": {
    "addr:full":"908 Kennedy Rd Scarborough ON M1K 2E8",
    "addr:housenumber":"908",
    "addr:postcode":"m1k 2e8",
    "addr:street":"Kennedy Rd",
    "iso:country":"CA",
    "sg:address":"908 Kennedy Rd",
    "sg:city":"Scarborough",
    "sg:classifiers":[
        {
            "category":"Building & Trades",
            "subcategory":"Construction",
            "type":"Services"
        }
    ],
    "sg:phone":"+1 416 752 8495",
    "sg:postcode":"M1K 2E8",
    "sg:province":"ON",
    "sg:tags":[
        "painter"
    ],
    "wof:name":"Aprile Painting & Decorating",
    "wof:placetype":"venue"
},
  "geometry": {"coordinates":[-79.271523,43.740402],"type":"Point"}
}