{
  "type": "Feature",
  "properties": {
    "addr:full":"Saint-Eustache QC J7R 2M4",
    "addr:postcode":"j7r 2m4",
    "iso:country":"CA",
    "sg:city":"Saint-Eustache",
    "sg:classifiers":[
        {
            "category":"Personal",
            "subcategory":"Beauty Salon",
            "type":"Services"
        }
    ],
    "sg:phone":"+1 450 472 1610",
    "sg:postcode":"J7R 2M4",
    "sg:province":"QC",
    "sg:tags":[
        "tanning"
    ],
    "wof:name":"Salon DE Coiffure L'Ambiance",
    "wof:placetype":"venue"
},
  "geometry": {"coordinates":[-73.90367126460001,45.5595092773],"type":"Point"}
}