{
  "type": "Feature",
  "properties": {
    "addr:full":"27 Wildwood St Saint John NB E2J 2V9",
    "addr:housenumber":"27",
    "addr:postcode":"e2j 2v9",
    "addr:street":"Wildwood St",
    "iso:country":"CA",
    "sg:address":"27 Wildwood St",
    "sg:city":"Saint John",
    "sg:classifiers":[
        {
            "category":"Real Estate",
            "subcategory":"Developer",
            "type":"Services"
        }
    ],
    "sg:phone":"+1 506 696 2222",
    "sg:postcode":"E2J 2V9",
    "sg:province":"NB",
    "wof:name":"Remax",
    "wof:placetype":"venue"
},
  "geometry": {"coordinates":[-66.010445,45.315445],"type":"Point"}
}