{
  "type": "Feature",
  "properties": {
    "addr:full":"5119 Lansdowne Dr NW Edmonton AB T6H 4L1",
    "addr:housenumber":"5119",
    "addr:postcode":"t6h 4l1",
    "addr:street":"Lansdowne Dr Nw",
    "iso:country":"CA",
    "sg:address":"5119 Lansdowne Dr NW",
    "sg:city":"Edmonton",
    "sg:classifiers":[
        {
            "category":"Professional",
            "subcategory":"Business Services",
            "type":"Services"
        }
    ],
    "sg:phone":"+1 780 413 9070",
    "sg:postcode":"T6H 4L1",
    "sg:province":"AB",
    "sg:tags":[
        "appraiser"
    ],
    "wof:name":"Gardner Appraisals Inc",
    "wof:placetype":"venue"
},
  "geometry": {"coordinates":[-113.55274199999999,53.487511],"type":"Point"}
}