{
  "type": "Feature",
  "properties": {
    "addr:full":"674 Dundas St London ON N5W 2Y8",
    "addr:housenumber":"674",
    "addr:postcode":"n5w 2y8",
    "addr:street":"Dundas St",
    "iso:country":"CA",
    "sg:address":"674 Dundas St",
    "sg:city":"London",
    "sg:classifiers":[
        {
            "category":"Shopping",
            "subcategory":"Discount & Variety Stores",
            "type":"Retail Goods"
        }
    ],
    "sg:phone":"+1 519 438 5952",
    "sg:postcode":"N5W 2Y8",
    "sg:province":"ON",
    "wof:name":"C & C Discount Variety",
    "wof:placetype":"venue"
},
  "geometry": {"coordinates":[-81.2295,42.989574],"type":"Point"}
}