{
  "type": "Feature",
  "properties": {
    "iso:country":"CA",
    "sg:address":"16 Corydon Pl",
    "sg:city":"Cambridge",
    "sg:classifiers":[
        {
            "category":"Shopping",
            "type":"Retail Goods"
        }
    ],
    "sg:phone":"+1 519 740 3880",
    "sg:postcode":"N1R 7L5",
    "sg:province":"ON",
    "sg:tags":[
        "webbing"
    ],
    "wof:name":"Swift Components Corp",
    "wof:placetype":"venue"
},
  "geometry": {"coordinates":[-80.3136291504,43.4022369385],"type":"Point"}
}