{
  "type": "Feature",
  "properties": {
    "iso:country":"CA",
    "sg:address":"574 College St",
    "sg:city":"Toronto",
    "sg:classifiers":[
        {
            "category":"Restaurant",
            "type":"Food & Drink"
        }
    ],
    "sg:phone":"+1 416 533 2417",
    "sg:postcode":"M6G 1B3",
    "sg:province":"ON",
    "wof:name":"College Street Bar",
    "wof:placetype":"venue"
},
  "geometry": {"coordinates":[-79.4130325317,43.6555366516],"type":"Point"}
}