{
  "type": "Feature",
  "properties": {
    "iso:country":"CA",
    "sg:address":"15 Mcculloch Ave # 1A",
    "sg:city":"Etobicoke",
    "sg:classifiers":[
        {
            "category":"Banks & Credit Unions",
            "subcategory":"Bank",
            "type":"Services"
        }
    ],
    "sg:phone":"+1 416 247 2167",
    "sg:postcode":"M9W 4M5",
    "sg:province":"ON",
    "sg:tags":[
        "financing"
    ],
    "wof:name":"Ridings Financial Svc",
    "wof:placetype":"venue"
},
  "geometry": {"coordinates":[-79.5709686279,43.6985855103],"type":"Point"}
}