{
  "type": "Feature",
  "properties": {
    "addr:full":"651 Rue Labelle Mont-Tremblant QC J8E 3H2",
    "addr:housenumber":"651",
    "addr:postcode":"j8e 3h2",
    "addr:street":"Rue Labelle",
    "iso:country":"CA",
    "sg:address":"651 Rue Labelle",
    "sg:city":"Mont-Tremblant",
    "sg:classifiers":[
        {
            "category":"Cinema",
            "subcategory":"Movie Rental",
            "type":"Entertainment"
        }
    ],
    "sg:phone":"+1 819 425 8661",
    "sg:postcode":"J8E 3H2",
    "sg:province":"QC",
    "sg:tags":[
        "leasing",
        "video",
        "disc",
        "tape"
    ],
    "wof:name":"Video 8",
    "wof:placetype":"venue"
},
  "geometry": {"coordinates":[-74.591774,46.123943],"type":"Point"}
}