{
  "type": "Feature",
  "properties": {
    "iso:country":"CA",
    "sg:address":"2111 Main St",
    "sg:city":"Cawston",
    "sg:classifiers":[
        {
            "category":"Food & Beverages",
            "subcategory":"Groceries & Convenience Stores",
            "type":"Retail Goods"
        }
    ],
    "sg:phone":"+1 250 499 2970",
    "sg:postcode":"V0X 1C0",
    "sg:province":"BC",
    "sg:tags":[
        "grocer"
    ],
    "wof:name":"Cawston Marketplace",
    "wof:placetype":"venue"
},
  "geometry": {"coordinates":[-119.759063721,49.1788101196],"type":"Point"}
}