{
  "type": "Feature",
  "properties": {
    "iso:country":"CA",
    "sg:address":"126 East Ave",
    "sg:city":"Brantford",
    "sg:classifiers":[
        {
            "category":"Professional",
            "subcategory":"Management & Consulting",
            "type":"Services"
        }
    ],
    "sg:phone":"+1 519 751 9491",
    "sg:postcode":"N3S 3M2",
    "sg:province":"ON",
    "sg:tags":[
        "consultant",
        "business"
    ],
    "wof:name":"John Crysler Inc",
    "wof:placetype":"venue"
},
  "geometry": {"coordinates":[-80.2498931885,43.1386489868],"type":"Point"}
}