{
  "type": "Feature",
  "properties": {
    "addr:full":"10 Industrial Dr Campbellford ON K0L 1L0",
    "addr:housenumber":"10",
    "addr:postcode":"k0l 1l0",
    "addr:street":"Industrial Dr",
    "iso:country":"CA",
    "sg:address":"10 Industrial Dr",
    "sg:city":"Campbellford",
    "sg:classifiers":[
        {
            "category":"Retail",
            "subcategory":"Auto Repair",
            "type":"Services"
        }
    ],
    "sg:phone":"+1 705 653 2112",
    "sg:postcode":"K0L 1L0",
    "sg:province":"ON",
    "sg:tags":[
        "body",
        "automobile",
        "painting"
    ],
    "wof:name":"Denny Ellis Body Repairs",
    "wof:placetype":"venue"
},
  "geometry": {"coordinates":[-77.80676269529999,44.2892684937],"type":"Point"}
}