{
  "type": "Feature",
  "properties": {
    "addr:full":"1950 Scott St Ottawa ON K1Z 8L8",
    "addr:housenumber":"1950",
    "addr:postcode":"k1z 8l8",
    "addr:street":"Scott St",
    "iso:country":"CA",
    "sg:address":"1950 Scott St",
    "sg:city":"Ottawa",
    "sg:classifiers":[
        {
            "category":"Organizations",
            "subcategory":"Religious Organization",
            "type":"Services"
        }
    ],
    "sg:phone":"+1 613 759 8111",
    "sg:postcode":"K1Z 8L8",
    "sg:province":"ON",
    "wof:name":"International Buddhist Prgrs",
    "wof:placetype":"venue"
},
  "geometry": {"coordinates":[-75.749115,45.397388],"type":"Point"}
}