{
  "type": "Feature",
  "properties": {
    "addr:full":"6654 W Island Hwy Bowser BC V0R 1G0",
    "addr:housenumber":"6654",
    "addr:postcode":"v0r 1g0",
    "addr:street":"W Island Hwy",
    "iso:country":"CA",
    "sg:address":"6654 W Island Hwy",
    "sg:city":"Bowser",
    "sg:classifiers":[
        {
            "category":"Building & Trades",
            "subcategory":"Construction",
            "type":"Services"
        }
    ],
    "sg:phone":"+1 250 757 8423",
    "sg:postcode":"V0R 1G0",
    "sg:province":"BC",
    "sg:tags":[
        "downspouts",
        "gutter"
    ],
    "wof:name":"Seabreeze Exteriors",
    "wof:placetype":"venue"
},
  "geometry": {"coordinates":[-124.686485291,49.4392242432],"type":"Point"}
}