{
  "type": "Feature",
  "properties": {
    "addr:full":"27 Chimo Dr Kanata ON K2L 1A3",
    "addr:housenumber":"27",
    "addr:postcode":"k2l 1a3",
    "addr:street":"Chimo Dr",
    "iso:country":"CA",
    "sg:address":"27 Chimo Dr",
    "sg:city":"Kanata",
    "sg:classifiers":[
        {
            "category":"Professional",
            "subcategory":"Computer Services",
            "type":"Services"
        }
    ],
    "sg:phone":"+1 613 254 5850",
    "sg:postcode":"K2L 1A3",
    "sg:province":"ON",
    "sg:tags":[
        "consultant"
    ],
    "wof:name":"Anisoft Group Inc",
    "wof:placetype":"venue"
},
  "geometry": {"coordinates":[-75.88516235349999,45.3125190735],"type":"Point"}
}