{
  "type": "Feature",
  "properties": {
    "addr:full":"2424 Av Watt Sainte-Foy QC G1P 3T3",
    "addr:housenumber":"2424",
    "addr:postcode":"g1p 3t3",
    "addr:street":"Av Watt",
    "iso:country":"CA",
    "sg:address":"2424 Av Watt",
    "sg:city":"Sainte-Foy",
    "sg:classifiers":[
        {
            "category":"Manufacturing",
            "subcategory":"Paper Products",
            "type":"Manufacturing & Wholesale Goods"
        }
    ],
    "sg:phone":"+1 418 653 2132",
    "sg:postcode":"G1P 3T3",
    "sg:province":"QC",
    "sg:tags":[
        "box"
    ],
    "wof:name":"A & R Belley Inc",
    "wof:placetype":"venue"
},
  "geometry": {"coordinates":[-71.29643249510001,46.7905082703],"type":"Point"}
}