{
  "type": "Feature",
  "properties": {
    "addr:full":"487 Parkview Rd Yorkton SK S3N 2L6",
    "addr:housenumber":"487",
    "addr:postcode":"s3n 2l6",
    "addr:street":"Parkview Rd",
    "iso:country":"CA",
    "sg:address":"487 Parkview Rd",
    "sg:city":"Yorkton",
    "sg:classifiers":[
        {
            "category":"Education",
            "subcategory":"School",
            "type":"Public Place"
        }
    ],
    "sg:phone":"+1 306 783 9212",
    "sg:postcode":"S3N 2L6",
    "sg:province":"SK",
    "wof:name":"St Paul's School",
    "wof:placetype":"venue"
},
  "geometry": {"coordinates":[-102.491905,51.201797],"type":"Point"}
}