{
  "type": "Feature",
  "properties": {
    "addr:full":"352 Nootka Dr Gold River BC V0P 1G0",
    "addr:housenumber":"352",
    "addr:postcode":"v0p 1g0",
    "addr:street":"Nootka Dr",
    "iso:country":"CA",
    "sg:address":"352 Nootka Dr",
    "sg:city":"Gold River",
    "sg:classifiers":[
        {
            "category":"Travel",
            "subcategory":"Hotels & Motels",
            "type":"Entertainment"
        }
    ],
    "sg:phone":"+1 250 283 7194",
    "sg:postcode":"V0P 1G0",
    "sg:province":"BC",
    "sg:tags":[
        "resort",
        "fishing",
        "party"
    ],
    "wof:name":"Nootka Sound Sports Fishing",
    "wof:placetype":"venue"
},
  "geometry": {"coordinates":[-126.04682159399999,49.7810630798],"type":"Point"}
}