{
  "type": "Feature",
  "properties": {
    "addr:full":"1049 Mcphee Ave Courtenay BC V9N 3A1",
    "addr:housenumber":"1049",
    "addr:postcode":"v9n 3a1",
    "addr:street":"Mcphee Ave",
    "iso:country":"CA",
    "sg:address":"1049 Mcphee Ave",
    "sg:city":"Courtenay",
    "sg:classifiers":[
        {
            "category":"Retail",
            "subcategory":"Auto Rental",
            "type":"Services"
        }
    ],
    "sg:phone":"+1 250 334 1546",
    "sg:postcode":"V9N 3A1",
    "sg:province":"BC",
    "sg:tags":[
        "renting",
        "leasing",
        "truck",
        "trailer"
    ],
    "wof:name":"U-Haul CO Ltd",
    "wof:placetype":"venue"
},
  "geometry": {"coordinates":[-125.00252533,49.6843986511],"type":"Point"}
}