{
  "type": "Feature",
  "properties": {
    "iso:country":"CA",
    "sg:address":"124 Ossington Ave",
    "sg:city":"Toronto",
    "sg:classifiers":[
        {
            "category":"Retail",
            "subcategory":"Auto Repair",
            "type":"Services"
        }
    ],
    "sg:phone":"+1 416 535 7940",
    "sg:postcode":"M6J 2Z5",
    "sg:province":"ON",
    "sg:tags":[
        "repairing",
        "automobile"
    ],
    "wof:name":"Rolly's Garage",
    "wof:placetype":"venue"
},
  "geometry": {"coordinates":[-79.4200744629,43.6470794678],"type":"Point"}
}