{
  "type": "Feature",
  "properties": {
    "addr:full":"4950 Ch Queen-Mary # 444 Montreal QC H3W 1X3",
    "addr:postcode":"4950;h3w 1x3",
    "addr:street":"Ch Queen-Mary # 444",
    "iso:country":"CA",
    "sg:address":"4950 Ch Queen-Mary # 444",
    "sg:city":"Montreal",
    "sg:classifiers":[
        {
            "category":"Insurance",
            "subcategory":"Insurance Agent",
            "type":"Services"
        }
    ],
    "sg:phone":"+1 514 738 8511",
    "sg:postcode":"H3W 1X3",
    "sg:province":"QC",
    "wof:name":"Courtiers Peck Groupe & Rente",
    "wof:placetype":"venue"
},
  "geometry": {"coordinates":[-73.6264801025,45.4864845276],"type":"Point"}
}