{
  "type": "Feature",
  "properties": {
    "addr:full":"46 Enterprise Dr Forest ON N0N 1J0",
    "addr:housenumber":"46",
    "addr:postcode":"n0n 1j0",
    "addr:street":"Enterprise Dr",
    "iso:country":"CA",
    "sg:address":"46 Enterprise Dr",
    "sg:city":"Forest",
    "sg:classifiers":[
        {
            "category":"Home & Garden",
            "subcategory":"Building Materials",
            "type":"Retail Goods"
        }
    ],
    "sg:phone":"+1 519 786 5781",
    "sg:postcode":"N0N 1J0",
    "sg:province":"ON",
    "sg:tags":[
        "mixed",
        "concrete"
    ],
    "wof:name":"Emc Ready Mixed Concrete",
    "wof:placetype":"venue"
},
  "geometry": {"coordinates":[-81.987556,43.107986],"type":"Point"}
}