{
  "type": "Feature",
  "properties": {
    "iso:country":"CA",
    "sg:address":"46 Blakney St",
    "sg:city":"Moncton",
    "sg:classifiers":[
        {
            "category":"Manufacturing",
            "subcategory":"Metals",
            "type":"Manufacturing & Wholesale Goods"
        }
    ],
    "sg:phone":"+1 506 857 0723",
    "sg:postcode":"E1A 4B7",
    "sg:province":"NB",
    "sg:tags":[
        "steel"
    ],
    "wof:name":"Mc Sheffery Industries Ltd",
    "wof:placetype":"venue"
},
  "geometry": {"coordinates":[-64.767372,46.114006],"type":"Point"}
}