{
  "type": "Feature",
  "properties": {
    "addr:full":"1740 Woodstock Rd Fredericton NB E3C 1L4",
    "addr:housenumber":"1740",
    "addr:postcode":"e3c 1l4",
    "addr:street":"Woodstock Rd",
    "iso:country":"CA",
    "sg:address":"1740 Woodstock Rd",
    "sg:city":"Fredericton",
    "sg:classifiers":[
        {
            "category":"Autos & Motor Vehicles",
            "subcategory":"Automobile Sales",
            "type":"Retail Goods"
        }
    ],
    "sg:phone":"+1 506 458 8917",
    "sg:postcode":"E3C 1L4",
    "sg:province":"NB",
    "sg:tags":[
        "car",
        "dealer"
    ],
    "wof:name":"G & K Auto Sales",
    "wof:placetype":"venue"
},
  "geometry": {"coordinates":[-66.718102,45.967033],"type":"Point"}
}