{
  "type": "Feature",
  "properties": {
    "addr:full":"679 Rue Adoncour Longueuil QC J4G 2M6",
    "addr:housenumber":"679",
    "addr:postcode":"j4g 2m6",
    "addr:street":"Rue Adoncour",
    "iso:country":"CA",
    "sg:address":"679 Rue Adoncour",
    "sg:city":"Longueuil",
    "sg:classifiers":[
        {
            "category":"Restaurant",
            "type":"Food & Drink"
        }
    ],
    "sg:phone":"+1 450 646 3660",
    "sg:postcode":"J4G 2M6",
    "sg:province":"QC",
    "wof:name":"Restaurant Olivier",
    "wof:placetype":"venue"
},
  "geometry": {"coordinates":[-73.484467,45.55183],"type":"Point"}
}