{
  "type": "Feature",
  "properties": {
    "addr:full":"5000 Crescent Rd W Portage LA Prairie MB R1N 3P1",
    "addr:housenumber":"5000",
    "addr:postcode":"r1n 3p1",
    "addr:street":"Crescent Rd W",
    "iso:country":"CA",
    "sg:address":"5000 Crescent Rd W",
    "sg:city":"Portage LA Prairie",
    "sg:classifiers":[
        {
            "category":"Organizations",
            "subcategory":"Community Association",
            "type":"Services"
        }
    ],
    "sg:phone":"+1 204 239 8650",
    "sg:postcode":"R1N 3P1",
    "sg:province":"MB",
    "sg:tags":[
        "native"
    ],
    "wof:name":"Dakota Ojibway Tribal Council",
    "wof:placetype":"venue"
},
  "geometry": {"coordinates":[-98.318657,49.966549],"type":"Point"}
}