{
  "type": "Feature",
  "properties": {
    "addr:full":"310 Wyandotte St E Windsor ON N9A 3H6",
    "addr:housenumber":"310",
    "addr:postcode":"n9a 3h6",
    "addr:street":"Wyandotte St E",
    "iso:country":"CA",
    "sg:address":"310 Wyandotte St E",
    "sg:city":"Windsor",
    "sg:classifiers":[
        {
            "category":"Professional",
            "subcategory":"Lawyer & Legal Services",
            "type":"Services"
        }
    ],
    "sg:phone":"+1 519 255 7595",
    "sg:postcode":"N9A 3H6",
    "sg:province":"ON",
    "sg:tags":[
        "attorney",
        "naturalization",
        "immigration"
    ],
    "wof:name":"Zaher, Sandra",
    "wof:placetype":"venue"
},
  "geometry": {"coordinates":[-83.0323638916,42.315826416],"type":"Point"}
}