{
  "type": "Feature",
  "properties": {
    "addr:full":"Hague SK S0K 1X0",
    "addr:postcode":"s0k 1x0",
    "iso:country":"CA",
    "sg:city":"Hague",
    "sg:classifiers":[
        {
            "category":"Manufacturing",
            "subcategory":"Tools & Machinery",
            "type":"Manufacturing & Wholesale Goods"
        }
    ],
    "sg:phone":"+1 306 225 4585",
    "sg:postcode":"S0K 1X0",
    "sg:province":"SK",
    "sg:tags":[
        "machine",
        "shop"
    ],
    "wof:name":"Accu-Tec Tool & Die",
    "wof:placetype":"venue"
},
  "geometry": {"coordinates":[-106.415924072,52.5117340088],"type":"Point"}
}