{
  "type": "Feature",
  "properties": {
    "addr:full":"Thompson MB R8N 0L6",
    "addr:postcode":"r8n 0l6",
    "iso:country":"CA",
    "sg:city":"Thompson",
    "sg:classifiers":[
        {
            "category":"Social Services",
            "type":"Services"
        }
    ],
    "sg:phone":"+1 204 677 2341",
    "sg:postcode":"R8N 0L6",
    "sg:province":"MB",
    "sg:tags":[
        "organization",
        "welfare"
    ],
    "wof:name":"Keewatin Tribal Council Inc",
    "wof:placetype":"venue"
},
  "geometry": {"coordinates":[-97.8521728516,55.7438659668],"type":"Point"}
}