{
  "type": "Feature",
  "properties": {
    "iso:country":"CA",
    "sg:address":"435 Brookside Dr #45",
    "sg:city":"Fredericton",
    "sg:classifiers":[
        {
            "category":"Shopping",
            "subcategory":"Gifts & Souvenirs",
            "type":"Retail Goods"
        }
    ],
    "sg:phone":"+1 506 451 7773",
    "sg:postcode":"E3A 8V4",
    "sg:province":"NB",
    "sg:tags":[
        "cards",
        "collectible",
        "sport",
        "baseball",
        "memorabilia"
    ],
    "wof:name":"Card Rack",
    "wof:placetype":"venue"
},
  "geometry": {"coordinates":[-66.65033,45.992214],"type":"Point"}
}