{
  "type": "Feature",
  "properties": {
    "addr:full":"Halifax NS B3L 4P1",
    "addr:postcode":"b3l 4p1",
    "iso:country":"CA",
    "sg:city":"Halifax",
    "sg:classifiers":[
        {
            "category":"Health Services",
            "subcategory":"Doctor",
            "type":"Services"
        }
    ],
    "sg:phone":"+1 902 455 1499",
    "sg:postcode":"B3L 4P1",
    "sg:province":"NS",
    "sg:tags":[
        "dentist"
    ],
    "wof:name":"Mumford Family Dental Ctr",
    "wof:placetype":"venue"
},
  "geometry": {"coordinates":[-63.617603302,44.646446228],"type":"Point"}
}