{
  "type": "Feature",
  "properties": {
    "addr:full":"120 Mcmillan St London ON N5W 6C6",
    "addr:housenumber":"120",
    "addr:postcode":"n5w 6c6",
    "addr:street":"Mcmillan St",
    "iso:country":"CA",
    "sg:address":"120 Mcmillan St",
    "sg:city":"London",
    "sg:classifiers":[
        {
            "category":"Manufacturing",
            "subcategory":"Metals",
            "type":"Manufacturing & Wholesale Goods"
        }
    ],
    "sg:phone":"+1 519 455 2540",
    "sg:postcode":"N5W 6C6",
    "sg:province":"ON",
    "sg:tags":[
        "steel",
        "concrete",
        "reinforcing",
        "reinforcement",
        "supply"
    ],
    "wof:name":"Dietrich Steel Ltd",
    "wof:placetype":"venue"
},
  "geometry": {"coordinates":[-81.154335022,42.978843689],"type":"Point"}
}