{
  "type": "Feature",
  "properties": {
    "addr:full":"1305 Boul Blanche Baie-Comeau QC G5C 3J3",
    "addr:housenumber":"1305",
    "addr:postcode":"g5c 3j3",
    "addr:street":"Boul Blanche",
    "iso:country":"CA",
    "sg:address":"1305 Boul Blanche",
    "sg:city":"Baie-Comeau",
    "sg:classifiers":[
        {
            "category":"Cinema",
            "subcategory":"Movie Rental",
            "type":"Entertainment"
        }
    ],
    "sg:phone":"+1 418 589 7703",
    "sg:postcode":"G5C 3J3",
    "sg:province":"QC",
    "sg:tags":[
        "leasing",
        "video",
        "disc",
        "tape"
    ],
    "wof:name":"Cine Centre Video",
    "wof:placetype":"venue"
},
  "geometry": {"coordinates":[-68.262428,49.198547],"type":"Point"}
}