{
  "type": "Feature",
  "properties": {
    "addr:full":"90 3rd Ave E Vancouver BC V5T 1C3",
    "addr:housenumber":"90",
    "addr:postcode":"v5t 1c3",
    "addr:street":"3Rd Ave E",
    "iso:country":"CA",
    "sg:address":"90 3rd Ave E",
    "sg:city":"Vancouver",
    "sg:classifiers":[
        {
            "category":"Retail",
            "subcategory":"Repair Shop",
            "type":"Services"
        }
    ],
    "sg:phone":"+1 604 879 5418",
    "sg:postcode":"V5T 1C3",
    "sg:province":"BC",
    "sg:tags":[
        "equipment",
        "hydraulic"
    ],
    "wof:name":"Hymach Industries Ltd",
    "wof:placetype":"venue"
},
  "geometry": {"coordinates":[-123.103111,49.268135],"type":"Point"}
}