{
  "type": "Feature",
  "properties": {
    "iso:country":"CA",
    "sg:address":"31 Ripley Ave",
    "sg:city":"Toronto",
    "sg:classifiers":[
        {
            "category":"Professional",
            "subcategory":"Business Services",
            "type":"Services"
        }
    ],
    "sg:phone":"+1 416 251 6101",
    "sg:postcode":"M6S 3P2",
    "sg:province":"ON",
    "sg:tags":[
        "interior",
        "consultant",
        "design",
        "decorator"
    ],
    "wof:name":"Designum Planning & Design",
    "wof:placetype":"venue"
},
  "geometry": {"coordinates":[-79.4745941162,43.6375694275],"type":"Point"}
}