{
  "type": "Feature",
  "properties": {
    "iso:country":"CA",
    "sg:city":"Montreal",
    "sg:classifiers":[
        {
            "category":"Retail",
            "subcategory":"Auto Repair",
            "type":"Services"
        }
    ],
    "sg:phone":"+1 514 274 3379",
    "sg:postcode":"H2S 2C6",
    "sg:province":"QC",
    "sg:tags":[
        "transmission"
    ],
    "wof:name":"Hung Yang Transmission",
    "wof:placetype":"venue"
},
  "geometry": {"coordinates":[-73.59288,45.534908],"type":"Point"}
}