{
  "type": "Feature",
  "properties": {
    "iso:country":"CA",
    "sg:address":"30 Front St W",
    "sg:city":"Strathroy",
    "sg:classifiers":[
        {
            "category":"Home & Garden",
            "subcategory":"Hardware",
            "type":"Retail Goods"
        }
    ],
    "sg:phone":"+1 519 245 2770",
    "sg:postcode":"N7G 1X4",
    "sg:province":"ON",
    "wof:name":"Mc Arthur Pro Hardware",
    "wof:placetype":"venue"
},
  "geometry": {"coordinates":[-81.6248092651,42.9580383301],"type":"Point"}
}