{
  "type": "Feature",
  "properties": {
    "addr:full":"Amqui QC G5J 2B7",
    "addr:postcode":"g5j 2b7",
    "iso:country":"CA",
    "sg:city":"Amqui",
    "sg:classifiers":[
        {
            "category":"Real Estate",
            "subcategory":"Real Estate Operator",
            "type":"Services"
        }
    ],
    "sg:phone":"+1 418 629 2952",
    "sg:postcode":"G5J 2B7",
    "sg:province":"QC",
    "sg:tags":[
        "mall",
        "shopping",
        "center"
    ],
    "wof:name":"Germain Pelletier Ltee",
    "wof:placetype":"venue"
},
  "geometry": {"coordinates":[-67.423759,48.464211],"type":"Point"}
}