{
  "type": "Feature",
  "properties": {
    "addr:full":"Repentigny QC J6A 2T8",
    "addr:postcode":"j6a 2t8",
    "iso:country":"CA",
    "sg:city":"Repentigny",
    "sg:classifiers":[
        {
            "category":"Health Services",
            "subcategory":"Doctor",
            "type":"Services"
        }
    ],
    "sg:phone":"+1 450 581 1750",
    "sg:postcode":"J6A 2T8",
    "sg:province":"QC",
    "sg:tags":[
        "dentist"
    ],
    "wof:name":"Duval, Francois DDS",
    "wof:placetype":"venue"
},
  "geometry": {"coordinates":[-73.440926,45.742424],"type":"Point"}
}