{
  "type": "Feature",
  "properties": {
    "addr:full":"Dartmouth NS B3B 1L3",
    "addr:postcode":"b3b 1l3",
    "iso:country":"CA",
    "sg:city":"Dartmouth",
    "sg:classifiers":[
        {
            "category":"Manufacturing",
            "subcategory":"Tools & Machinery",
            "type":"Manufacturing & Wholesale Goods"
        }
    ],
    "sg:phone":"+1 902 468 6590",
    "sg:postcode":"B3B 1L3",
    "sg:province":"NS",
    "sg:tags":[
        "equipment",
        "hospital",
        "supply"
    ],
    "wof:name":"Comfort Foam & Fibre",
    "wof:placetype":"venue"
},
  "geometry": {"coordinates":[-63.594349,44.703926],"type":"Point"}
}