{
  "type": "Feature",
  "properties": {
    "iso:country":"CA",
    "sg:address":"28 Gurney Rd",
    "sg:city":"Kapuskasing",
    "sg:classifiers":[
        {
            "category":"Organizations",
            "subcategory":"Religious Organization",
            "type":"Services"
        }
    ],
    "sg:phone":"+1 705 337 5144",
    "sg:postcode":"P5N 2S5",
    "sg:province":"ON",
    "sg:tags":[
        "church"
    ],
    "wof:name":"Word of Life Church",
    "wof:placetype":"venue"
},
  "geometry": {"coordinates":[-82.38316345210001,49.4060783386],"type":"Point"}
}