{
  "type": "Feature",
  "properties": {
    "iso:country":"CA",
    "sg:address":"PO Box 237",
    "sg:city":"Hay Lakes",
    "sg:classifiers":[
        {
            "category":"Wholesale",
            "subcategory":"Auto Parts",
            "type":"Manufacturing & Wholesale Goods"
        }
    ],
    "sg:phone":"+1 780 878 3263",
    "sg:postcode":"T0B 1W0",
    "sg:province":"AB",
    "sg:tags":[
        "automobile",
        "wrecking"
    ],
    "wof:name":"C R Auto",
    "wof:placetype":"venue"
},
  "geometry": {"coordinates":[-113.056915283,53.1971244812],"type":"Point"}
}