{
  "type": "Feature",
  "properties": {
    "addr:full":"Markham ON L3R 5E4",
    "addr:postcode":"l3r 5e4",
    "iso:country":"CA",
    "sg:city":"Markham",
    "sg:classifiers":[
        {
            "category":"Wholesale",
            "subcategory":"Non-durable Goods",
            "type":"Manufacturing & Wholesale Goods"
        }
    ],
    "sg:phone":"+1 905 305 8620",
    "sg:postcode":"L3R 5E4",
    "sg:province":"ON",
    "sg:tags":[
        "advertising"
    ],
    "wof:name":"Barry Skopit Sales Inc",
    "wof:placetype":"venue"
},
  "geometry": {"coordinates":[-79.3339538574,43.8256034851],"type":"Point"}
}