{
  "type": "Feature",
  "properties": {
    "addr:full":"Ponoka AB T4J 1J8",
    "addr:postcode":"t4j 1j8",
    "iso:country":"CA",
    "sg:city":"Ponoka",
    "sg:classifiers":[
        {
            "category":"Bars & Pubs",
            "type":"Food & Drink"
        }
    ],
    "sg:phone":"+1 403 783 6318",
    "sg:postcode":"T4J 1J8",
    "sg:province":"AB",
    "sg:tags":[
        "lounge",
        "cocktail"
    ],
    "wof:name":"Office Pub",
    "wof:placetype":"venue"
},
  "geometry": {"coordinates":[-113.60442352299999,52.669467926],"type":"Point"}
}