{
  "type": "Feature",
  "properties": {
    "addr:full":"1667 Miracle Beach Dr Black Creek BC V9J 1J5",
    "addr:housenumber":"1667",
    "addr:postcode":"v9j 1j5",
    "addr:street":"Miracle Beach Dr",
    "iso:country":"CA",
    "sg:address":"1667 Miracle Beach Dr",
    "sg:city":"Black Creek",
    "sg:classifiers":[
        {
            "category":"Building & Trades",
            "subcategory":"Construction",
            "type":"Services"
        }
    ],
    "sg:phone":"+1 250 337 8449",
    "sg:postcode":"V9J 1J5",
    "sg:province":"BC",
    "sg:tags":[
        "masonry",
        "contractor"
    ],
    "wof:name":"Steve Granger Masonry Ltd",
    "wof:placetype":"venue"
},
  "geometry": {"coordinates":[-125.135002,49.843006],"type":"Point"}
}