{
  "type": "Feature",
  "properties": {
    "addr:full":"228 Rue Du Foyer Vallee-Jonction QC G0S 3J0",
    "addr:housenumber":"228",
    "addr:postcode":"g0s 3j0",
    "addr:street":"Rue Du Foyer",
    "iso:country":"CA",
    "sg:address":"228 Rue Du Foyer",
    "sg:city":"Vallee-Jonction",
    "sg:classifiers":[
        {
            "category":"Health Services",
            "subcategory":"Nursing And Care Facility",
            "type":"Services"
        }
    ],
    "sg:phone":"+1 418 253 5469",
    "sg:postcode":"G0S 3J0",
    "sg:province":"QC",
    "sg:tags":[
        "home",
        "retirement",
        "community"
    ],
    "wof:name":"Residences DE LA Vallee",
    "wof:placetype":"venue"
},
  "geometry": {"coordinates":[-70.926422,46.37936],"type":"Point"}
}