{
  "type": "Feature",
  "properties": {
    "iso:country":"CA",
    "sg:address":"1600 Edward St",
    "sg:city":"Halifax",
    "sg:classifiers":[
        {
            "category":"Health Services",
            "subcategory":"Doctor",
            "type":"Services"
        }
    ],
    "sg:phone":"+1 902 429 0023",
    "sg:postcode":"B3H 3J1",
    "sg:province":"NS",
    "sg:tags":[
        "physician",
        "surgeon"
    ],
    "wof:name":"Wood, David C MD",
    "wof:placetype":"venue"
},
  "geometry": {"coordinates":[-63.588692,44.640987],"type":"Point"}
}