{
  "type": "Feature",
  "properties": {
    "addr:full":"2591 Morton St Alexis Creek BC V0L 1A0",
    "addr:housenumber":"2591",
    "addr:postcode":"v0l 1a0",
    "addr:street":"Morton St",
    "iso:country":"CA",
    "sg:address":"2591 Morton St",
    "sg:city":"Alexis Creek",
    "sg:classifiers":[
        {
            "category":"Health Services",
            "subcategory":"Hospital",
            "type":"Services"
        }
    ],
    "sg:phone":"+1 250 394 4313",
    "sg:postcode":"V0L 1A0",
    "sg:province":"BC",
    "wof:name":"Red Cross Outpost Hospital",
    "wof:placetype":"venue"
},
  "geometry": {"coordinates":[-123.28285217299999,52.0853118896],"type":"Point"}
}