{
  "type": "Feature",
  "properties": {
    "addr:full":"PO Box 128 STN Main Dryden ON P8N 2Y7",
    "addr:housenumber":"po",
    "addr:postcode":"p8n 2y7",
    "addr:street":"Box 128 Stn Main",
    "iso:country":"CA",
    "sg:address":"PO Box 128 STN Main",
    "sg:city":"Dryden",
    "sg:classifiers":[
        {
            "category":"Travel",
            "subcategory":"Hotels & Motels",
            "type":"Entertainment"
        }
    ],
    "sg:phone":"+1 807 223 1355",
    "sg:postcode":"P8N 2Y7",
    "sg:province":"ON",
    "sg:tags":[
        "resort"
    ],
    "wof:name":"Basket Lake Camp",
    "wof:placetype":"venue"
},
  "geometry": {"coordinates":[-92.837585,49.782051],"type":"Point"}
}