{
  "type": "Feature",
  "properties": {
    "addr:full":"635 Clark Ave Burlington ON L7S 1P1",
    "addr:housenumber":"635",
    "addr:postcode":"l7s 1p1",
    "addr:street":"Clark Ave",
    "iso:country":"CA",
    "sg:address":"635 Clark Ave",
    "sg:city":"Burlington",
    "sg:classifiers":[
        {
            "category":"Building & Trades",
            "subcategory":"Cleaning & Sanitation",
            "type":"Services"
        }
    ],
    "sg:phone":"+1 905 335 2239",
    "sg:postcode":"L7S 1P1",
    "sg:province":"ON",
    "sg:tags":[
        "window"
    ],
    "wof:name":"D J's Window & Exterior Clean",
    "wof:placetype":"venue"
},
  "geometry": {"coordinates":[-79.80641199999999,43.325756],"type":"Point"}
}