{
  "type": "Feature",
  "properties": {
    "iso:country":"CA",
    "sg:address":"2775 Commissioner St",
    "sg:city":"Vancouver",
    "sg:classifiers":[
        {
            "category":"Freight",
            "type":"Transportation"
        }
    ],
    "sg:phone":"+1 604 254 9461",
    "sg:postcode":"V5K 1A1",
    "sg:province":"BC",
    "sg:tags":[
        "grain",
        "elevator"
    ],
    "wof:name":"Columbia Containers Ltd",
    "wof:placetype":"venue"
},
  "geometry": {"coordinates":[-123.047325134,49.2926864624],"type":"Point"}
}