{
  "type": "Feature",
  "properties": {
    "addr:full":"350 Av Galilee Quebec QC G1P 4M9",
    "addr:housenumber":"350",
    "addr:postcode":"g1p 4m9",
    "addr:street":"Av Galilee",
    "iso:country":"CA",
    "sg:address":"350 Av Galilee",
    "sg:city":"Quebec",
    "sg:classifiers":[
        {
            "category":"Retail",
            "subcategory":"Animal Services",
            "type":"Services"
        }
    ],
    "sg:phone":"+1 418 688 8221",
    "sg:postcode":"G1P 4M9",
    "sg:province":"QC",
    "sg:tags":[
        "pet",
        "boarding",
        "sitting"
    ],
    "wof:name":"Pension Animale L'Arche DE Noe",
    "wof:placetype":"venue"
},
  "geometry": {"coordinates":[-71.29323599999999,46.800419],"type":"Point"}
}