{
  "type": "Feature",
  "properties": {
    "addr:full":"2490 Bedell Rd Kemptville ON K0G 1J0",
    "addr:housenumber":"2490",
    "addr:postcode":"k0g 1j0",
    "addr:street":"Bedell Rd",
    "iso:country":"CA",
    "sg:address":"2490 Bedell Rd",
    "sg:city":"Kemptville",
    "sg:classifiers":[
        {
            "category":"Professional",
            "subcategory":"Art Services",
            "type":"Services"
        }
    ],
    "sg:phone":"+1 613 258 3443",
    "sg:postcode":"K0G 1J0",
    "sg:province":"ON",
    "sg:tags":[
        "photographer"
    ],
    "wof:name":"Canadian Aerial Photo Corp",
    "wof:placetype":"venue"
},
  "geometry": {"coordinates":[-75.642174,44.990871],"type":"Point"}
}