{
  "type": "Feature",
  "properties": {
    "addr:full":"Timmins ON P4R 1M2",
    "addr:postcode":"p4r 1m2",
    "iso:country":"CA",
    "sg:city":"Timmins",
    "sg:classifiers":[
        {
            "category":"Social Services",
            "type":"Services"
        }
    ],
    "sg:phone":"+1 705 268 3248",
    "sg:postcode":"P4R 1M2",
    "sg:province":"ON",
    "sg:tags":[
        "housing",
        "assistance"
    ],
    "wof:name":"Maisons Cooperatives Des Pin",
    "wof:placetype":"venue"
},
  "geometry": {"coordinates":[-81.3783950806,48.4777069092],"type":"Point"}
}