{
  "type": "Feature",
  "properties": {
    "addr:full":"2421 Marine Dr Oakville ON L6L 1C6",
    "addr:housenumber":"2421",
    "addr:postcode":"l6l 1c6",
    "addr:street":"Marine Dr",
    "iso:country":"CA",
    "sg:address":"2421 Marine Dr",
    "sg:city":"Oakville",
    "sg:classifiers":[
        {
            "category":"Government",
            "subcategory":"Office",
            "type":"Public Place"
        }
    ],
    "sg:phone":"+1 905 827 2077",
    "sg:postcode":"L6L 1C6",
    "sg:province":"ON",
    "sg:tags":[
        "member",
        "legislative",
        "assembly"
    ],
    "wof:name":"Brown, Bonnie",
    "wof:placetype":"venue"
},
  "geometry": {"coordinates":[-79.709412,43.39481],"type":"Point"}
}