{
  "type": "Feature",
  "properties": {
    "iso:country":"CA",
    "sg:address":"4 Sterling Rd",
    "sg:city":"Glace Bay",
    "sg:classifiers":[
        {
            "category":"Restaurant",
            "type":"Food & Drink"
        }
    ],
    "sg:phone":"+1 902 849 1010",
    "sg:postcode":"B1A 3X3",
    "sg:province":"NS",
    "wof:name":"Mike's Lunch",
    "wof:placetype":"venue"
},
  "geometry": {"coordinates":[-59.9562225342,46.2028045654],"type":"Point"}
}