{
  "type": "Feature",
  "properties": {
    "addr:full":"240 Millidge Ave Saint John NB E2K 2M7",
    "addr:housenumber":"240",
    "addr:postcode":"e2k 2m7",
    "addr:street":"Millidge Ave",
    "iso:country":"CA",
    "sg:address":"240 Millidge Ave",
    "sg:city":"Saint John",
    "sg:classifiers":[
        {
            "category":"Wholesale",
            "subcategory":"Toys & Hobbies",
            "type":"Manufacturing & Wholesale Goods"
        }
    ],
    "sg:phone":"+1 506 634 1020",
    "sg:postcode":"E2K 2M7",
    "sg:province":"NB",
    "sg:tags":[
        "firework"
    ],
    "wof:name":"T W Graham Ltd",
    "wof:placetype":"venue"
},
  "geometry": {"coordinates":[-66.08772999999999,45.283703],"type":"Point"}
}