{
  "type": "Feature",
  "properties": {
    "iso:country":"CA",
    "sg:address":"221 Milvan Dr",
    "sg:city":"North York",
    "sg:classifiers":[
        {
            "category":"Wholesale",
            "subcategory":"Machinery & Supplies",
            "type":"Manufacturing & Wholesale Goods"
        }
    ],
    "sg:phone":"+1 416 749 0982",
    "sg:postcode":"M9L 2A3",
    "sg:province":"ON",
    "sg:tags":[
        "machine",
        "equipment",
        "grinding"
    ],
    "wof:name":"Hendriks Precision Grinding",
    "wof:placetype":"venue"
},
  "geometry": {"coordinates":[-79.5656280518,43.7608375549],"type":"Point"}
}