{
  "type": "Feature",
  "properties": {
    "addr:full":"12 Paula Blvd Etobicoke ON M8W 4B6",
    "addr:housenumber":"12",
    "addr:postcode":"m8w 4b6",
    "addr:street":"Paula Blvd",
    "iso:country":"CA",
    "sg:address":"12 Paula Blvd",
    "sg:city":"Etobicoke",
    "sg:classifiers":[
        {
            "category":"Building & Trades",
            "subcategory":"Construction",
            "type":"Services"
        }
    ],
    "sg:phone":"+1 416 695 9442",
    "sg:postcode":"M8W 4B6",
    "sg:province":"ON",
    "sg:tags":[
        "pavement",
        "marking"
    ],
    "wof:name":"Peel Pavement Marking",
    "wof:placetype":"venue"
},
  "geometry": {"coordinates":[-79.53443145750001,43.6118164062],"type":"Point"}
}