{
  "type": "Feature",
  "properties": {
    "addr:full":"5312 Barrett Dr NW Calgary AB T2L 1W3",
    "addr:housenumber":"5312",
    "addr:postcode":"t2l 1w3",
    "addr:street":"Barrett Dr Nw",
    "iso:country":"CA",
    "sg:address":"5312 Barrett Dr NW",
    "sg:city":"Calgary",
    "sg:classifiers":[
        {
            "category":"Building & Trades",
            "subcategory":"Construction",
            "type":"Services"
        }
    ],
    "sg:phone":"+1 403 284 5298",
    "sg:postcode":"T2L 1W3",
    "sg:province":"AB",
    "sg:tags":[
        "general",
        "contractor"
    ],
    "wof:name":"Pro-Built Contruction Ltd",
    "wof:placetype":"venue"
},
  "geometry": {"coordinates":[-114.13454400000001,51.101532],"type":"Point"}
}