{
  "type": "Feature",
  "properties": {
    "addr:full":"2213 Wilgress Rd Nanaimo BC V9S 4N3",
    "addr:housenumber":"2213",
    "addr:postcode":"v9s 4n3",
    "addr:street":"Wilgress Rd",
    "iso:country":"CA",
    "sg:address":"2213 Wilgress Rd",
    "sg:city":"Nanaimo",
    "sg:classifiers":[
        {
            "category":"Retail",
            "subcategory":"Auto Repair",
            "type":"Services"
        }
    ],
    "sg:phone":"+1 250 729 9235",
    "sg:postcode":"V9S 4N3",
    "sg:province":"BC",
    "sg:tags":[
        "body",
        "automobile",
        "painting"
    ],
    "wof:name":"Christensen Collision & Auto",
    "wof:placetype":"venue"
},
  "geometry": {"coordinates":[-123.976845,49.193222],"type":"Point"}
}