{
  "type": "Feature",
  "properties": {
    "addr:full":"6 Armstrong St New Liskeard ON P0J 1P0",
    "addr:housenumber":"6",
    "addr:postcode":"p0j 1p0",
    "addr:street":"Armstrong St",
    "iso:country":"CA",
    "sg:address":"6 Armstrong St",
    "sg:city":"New Liskeard",
    "sg:classifiers":[
        {
            "category":"Banks & Credit Unions",
            "subcategory":"Bank",
            "type":"Services"
        }
    ],
    "sg:phone":"+1 705 647 6877",
    "sg:postcode":"P0J 1P0",
    "sg:province":"ON",
    "wof:name":"Cibc",
    "wof:placetype":"venue"
},
  "geometry": {"coordinates":[-79.671753,47.508812],"type":"Point"}
}