{
  "type": "Feature",
  "properties": {
    "addr:full":"4600 Av Georges-Bornais Shawinigan-Sud QC G9N 6T5",
    "addr:housenumber":"4600",
    "addr:postcode":"g9n 6t5",
    "addr:street":"Av Georges-Bornais",
    "iso:country":"CA",
    "sg:address":"4600 Av Georges-Bornais",
    "sg:city":"Shawinigan-Sud",
    "sg:classifiers":[
        {
            "category":"Building & Trades",
            "subcategory":"Construction",
            "type":"Services"
        }
    ],
    "sg:phone":"+1 819 537 3371",
    "sg:postcode":"G9N 6T5",
    "sg:province":"QC",
    "sg:tags":[
        "maker",
        "cabinet"
    ],
    "wof:name":"Ebenisterie Pelletier Inc",
    "wof:placetype":"venue"
},
  "geometry": {"coordinates":[-72.7124786377,46.5026016235],"type":"Point"}
}