{
  "type": "Feature",
  "properties": {
    "addr:full":"Ottawa ON K1G 4H3",
    "addr:postcode":"k1g 4h3",
    "iso:country":"CA",
    "sg:city":"Ottawa",
    "sg:classifiers":[
        {
            "category":"Shopping",
            "subcategory":"Pharmacy",
            "type":"Retail Goods"
        }
    ],
    "sg:phone":"+1 613 247 7554",
    "sg:postcode":"K1G 4H3",
    "sg:province":"ON",
    "sg:tags":[
        "home",
        "health"
    ],
    "wof:name":"Quality Life Svc Inc",
    "wof:placetype":"venue"
},
  "geometry": {"coordinates":[-75.6346664429,45.4086761475],"type":"Point"}
}