{
  "type": "Feature",
  "properties": {
    "addr:full":"250 Watline Ave Mississauga ON L4Z 1P4",
    "addr:housenumber":"250",
    "addr:postcode":"l4z 1p4",
    "addr:street":"Watline Ave",
    "iso:country":"CA",
    "sg:address":"250 Watline Ave",
    "sg:city":"Mississauga",
    "sg:classifiers":[
        {
            "category":"Organizations",
            "subcategory":"Religious Organization",
            "type":"Services"
        }
    ],
    "sg:phone":"+1 905 507 1143",
    "sg:postcode":"L4Z 1P4",
    "sg:province":"ON",
    "sg:tags":[
        "church"
    ],
    "wof:name":"Gift of God Church",
    "wof:placetype":"venue"
},
  "geometry": {"coordinates":[-79.6660003662,43.6265029907],"type":"Point"}
}