{
  "type": "Feature",
  "properties": {
    "iso:country":"CA",
    "sg:city":"Kensington",
    "sg:classifiers":[
        {
            "category":"Travel",
            "subcategory":"Hotels & Motels",
            "type":"Entertainment"
        }
    ],
    "sg:phone":"+1 902 886 2995",
    "sg:postcode":"C0B 1M0",
    "sg:province":"PE",
    "sg:tags":[
        "antique",
        "breakfast",
        "accommodation",
        "bed"
    ],
    "wof:name":"Dawn's Gallery Antiques",
    "wof:placetype":"venue"
},
  "geometry": {"coordinates":[-63.6368484497,46.436882019],"type":"Point"}
}