{
  "type": "Feature",
  "properties": {
    "addr:full":"Scarborough ON M1X 1N3",
    "addr:postcode":"m1x 1n3",
    "iso:country":"CA",
    "sg:city":"Scarborough",
    "sg:phone":"+1 416 754 1852",
    "sg:postcode":"M1X 1N3",
    "sg:province":"ON",
    "sg:tags":[
        "equipment",
        "supply"
    ],
    "wof:name":"Kaldi's Enterprises Inc",
    "wof:placetype":"venue"
},
  "geometry": {"coordinates":[-79.2468032837,43.8264656067],"type":"Point"}
}