{
  "type": "Feature",
  "properties": {
    "addr:full":"Montreal QC H3A 2L1",
    "addr:postcode":"h3a 2l1",
    "iso:country":"CA",
    "sg:city":"Montreal",
    "sg:classifiers":[
        {
            "category":"Professional",
            "subcategory":"Employment Agencies",
            "type":"Services"
        }
    ],
    "sg:phone":"+1 514 845 6800",
    "sg:postcode":"H3A 2L1",
    "sg:province":"QC",
    "sg:tags":[
        "opportunity"
    ],
    "wof:name":"Simon-Tech Inc",
    "wof:placetype":"venue"
},
  "geometry": {"coordinates":[-73.572487,45.504601],"type":"Point"}
}