{
  "type": "Feature",
  "properties": {
    "addr:full":"300 Empress Ave S Thunder Bay ON P7B 4P2",
    "addr:housenumber":"300",
    "addr:postcode":"p7b 4p2",
    "addr:street":"Empress Ave S Thunder",
    "iso:country":"CA",
    "sg:address":"300 Empress Ave S",
    "sg:city":"Thunder Bay",
    "sg:classifiers":[
        {
            "category":"Wholesale",
            "subcategory":"Meat",
            "type":"Manufacturing & Wholesale Goods"
        }
    ],
    "sg:phone":"+1 807 344 0056",
    "sg:postcode":"P7B 4P2",
    "sg:province":"ON",
    "sg:tags":[
        "delicatessen",
        "butchering"
    ],
    "wof:name":"Tim's Meats Deli & Grocery",
    "wof:placetype":"venue"
},
  "geometry": {"coordinates":[-89.250298,48.434284],"type":"Point"}
}