{
  "type": "Feature",
  "properties": {
    "iso:country":"CA",
    "sg:address":"23 Rue Acadie",
    "sg:city":"Bouctouche",
    "sg:classifiers":[
        {
            "category":"Travel",
            "subcategory":"Hotels & Motels",
            "type":"Entertainment"
        }
    ],
    "sg:phone":"+1 506 743 1999",
    "sg:postcode":"E4S 2T6",
    "sg:province":"NB",
    "sg:tags":[
        "cottage",
        "cabin"
    ],
    "wof:name":"Chalets Chebooktoosk",
    "wof:placetype":"venue"
},
  "geometry": {"coordinates":[-64.7194519043,46.4720497131],"type":"Point"}
}