{
  "type": "Feature",
  "properties": {
    "addr:full":"237 Edward St Stirling ON K0K 3E0",
    "addr:housenumber":"237",
    "addr:postcode":"k0k 3e0",
    "addr:street":"Edward St",
    "iso:country":"CA",
    "sg:address":"237 Edward St",
    "sg:city":"Stirling",
    "sg:classifiers":[
        {
            "category":"Organizations",
            "subcategory":"Religious Organization",
            "type":"Services"
        }
    ],
    "sg:phone":"+1 613 395 5022",
    "sg:postcode":"K0K 3E0",
    "sg:province":"ON",
    "sg:tags":[
        "church"
    ],
    "wof:name":"Grace Chapel",
    "wof:placetype":"venue"
},
  "geometry": {"coordinates":[-77.546722,44.300186],"type":"Point"}
}