{
  "type": "Feature",
  "properties": {
    "addr:full":"737 Rue Victoria LA Baie QC G7B 3M8",
    "addr:housenumber":"737",
    "addr:postcode":"g7b 3m8",
    "addr:street":"Rue Victoria",
    "iso:country":"CA",
    "sg:address":"737 Rue Victoria",
    "sg:city":"LA Baie",
    "sg:classifiers":[
        {
            "category":"Education",
            "subcategory":"School",
            "type":"Public Place"
        }
    ],
    "sg:phone":"+1 418 544 3223",
    "sg:postcode":"G7B 3M8",
    "sg:province":"QC",
    "wof:name":"Ecole Ste-Therese",
    "wof:placetype":"venue"
},
  "geometry": {"coordinates":[-70.8801040649,48.3415336609],"type":"Point"}
}