{
  "type": "Feature",
  "properties": {
    "addr:full":"1399 Kennedy Rd Scarborough ON M1P 2L6",
    "addr:housenumber":"1399",
    "addr:postcode":"m1p 2l6",
    "addr:street":"Kennedy Rd",
    "iso:country":"CA",
    "sg:address":"1399 Kennedy Rd",
    "sg:city":"Scarborough",
    "sg:classifiers":[
        {
            "category":"Home & Garden",
            "subcategory":"Home Furnishings",
            "type":"Retail Goods"
        }
    ],
    "sg:phone":"+1 416 750 2414",
    "sg:postcode":"M1P 2L6",
    "sg:province":"ON",
    "sg:tags":[
        "bathroom",
        "supply",
        "fixture",
        "sauna",
        "equipment",
        "accessory"
    ],
    "wof:name":"Tubs the Ultimate Bath Store",
    "wof:placetype":"venue"
},
  "geometry": {"coordinates":[-79.2795639038,43.762260437],"type":"Point"}
}