{
  "type": "Feature",
  "properties": {
    "iso:country":"CA",
    "sg:city":"Prince Albert",
    "sg:classifiers":[
        {
            "category":"Professional",
            "subcategory":"Accounting & Tax Preparation",
            "type":"Services"
        }
    ],
    "sg:phone":"+1 306 922 3899",
    "sg:postcode":"S6V 1C6",
    "sg:province":"SK",
    "sg:tags":[
        "accountant"
    ],
    "wof:name":"Mc Leod, Reid J CA",
    "wof:placetype":"venue"
},
  "geometry": {"coordinates":[-105.751777649,53.2014961243],"type":"Point"}
}