{
  "type": "Feature",
  "properties": {
    "addr:full":"2 Rue Paiement Sainte-Genevieve QC H9H 2S5",
    "addr:housenumber":"2",
    "addr:postcode":"h9h 2s5",
    "addr:street":"Rue Paiement",
    "iso:country":"CA",
    "sg:address":"2 Rue Paiement",
    "sg:city":"Sainte-Genevieve",
    "sg:classifiers":[
        {
            "category":"Government",
            "subcategory":"Police Station",
            "type":"Public Place"
        }
    ],
    "sg:phone":"+1 514 280 0102",
    "sg:postcode":"H9H 2S5",
    "sg:province":"QC",
    "sg:tags":[
        "department"
    ],
    "wof:name":"Ste-Genevieve Poste-Quartier",
    "wof:placetype":"venue"
},
  "geometry": {"coordinates":[-73.8673400879,45.483089447],"type":"Point"}
}