{
  "type": "Feature",
  "properties": {
    "addr:full":"6080 Young St Halifax NS B3K 5L2",
    "addr:housenumber":"6080",
    "addr:postcode":"b3k 5l2",
    "addr:street":"Young St",
    "iso:country":"CA",
    "sg:address":"6080 Young St",
    "sg:city":"Halifax",
    "sg:classifiers":[
        {
            "category":"Government",
            "subcategory":"Office",
            "type":"Public Place"
        }
    ],
    "sg:phone":"+1 902 426 7400",
    "sg:postcode":"B3K 5L2",
    "sg:province":"NS",
    "wof:name":"Canada Bureau of Pensions",
    "wof:placetype":"venue"
},
  "geometry": {"coordinates":[-63.603573,44.658531],"type":"Point"}
}