{
  "type": "Feature",
  "properties": {
    "addr:full":"123 Des Continuations Rg Saint-Esprit QC J0K 2L0",
    "addr:housenumber":"123",
    "addr:postcode":"j0k 2l0",
    "addr:street":"Des Continuations Rg",
    "iso:country":"CA",
    "sg:address":"123 Des Continuations Rg",
    "sg:city":"Saint-Esprit",
    "sg:classifiers":[
        {
            "category":"Manufacturing",
            "subcategory":"Lumber",
            "type":"Manufacturing & Wholesale Goods"
        }
    ],
    "sg:phone":"+1 450 839 7142",
    "sg:postcode":"J0K 2L0",
    "sg:province":"QC",
    "sg:tags":[
        "syrup",
        "maple",
        "sugar"
    ],
    "wof:name":"Cabane A Sucre Normand Payette",
    "wof:placetype":"venue"
},
  "geometry": {"coordinates":[-73.6740951538,45.9283714294],"type":"Point"}
}