{
  "type": "Feature",
  "properties": {
    "addr:full":"64 Ch Des Patriotes E Saint-Jean-Sur-Richelieu QC J2X 5P9",
    "addr:housenumber":"64",
    "addr:postcode":"j2x 5p9",
    "addr:street":"Ch Des Patriotes E",
    "iso:country":"CA",
    "sg:address":"64 Ch Des Patriotes E",
    "sg:city":"Saint-Jean-Sur-Richelieu",
    "sg:classifiers":[
        {
            "category":"Building & Trades",
            "subcategory":"Construction",
            "type":"Services"
        }
    ],
    "sg:phone":"+1 450 347 2022",
    "sg:postcode":"J2X 5P9",
    "sg:province":"QC",
    "sg:tags":[
        "builder",
        "cistern"
    ],
    "wof:name":"Citernes Hebert & Fils Inc",
    "wof:placetype":"venue"
},
  "geometry": {"coordinates":[-73.253365,45.324501],"type":"Point"}
}