{
  "type": "Feature",
  "properties": {
    "addr:full":"1080 Lansdowne St W Peterborough ON K9J 1Z9",
    "addr:housenumber":"1080",
    "addr:postcode":"k9j 1z9",
    "addr:street":"Lansdowne St W",
    "iso:country":"CA",
    "sg:address":"1080 Lansdowne St W",
    "sg:city":"Peterborough",
    "sg:classifiers":[
        {
            "category":"Food & Beverages",
            "subcategory":"Meat & Fish",
            "type":"Retail Goods"
        }
    ],
    "sg:phone":"+1 705 740 9684",
    "sg:postcode":"K9J 1Z9",
    "sg:province":"ON",
    "sg:tags":[
        "frozen"
    ],
    "wof:name":"M & M Meats",
    "wof:placetype":"venue"
},
  "geometry": {"coordinates":[-78.3467330933,44.2816963196],"type":"Point"}
}