{
  "type": "Feature",
  "properties": {
    "addr:full":"503 3rd St N Beausejour MB R0E 0C0",
    "addr:housenumber":"503",
    "addr:postcode":"r0e 0c0",
    "addr:street":"3Rd St N",
    "iso:country":"CA",
    "sg:address":"503 3rd St N",
    "sg:city":"Beausejour",
    "sg:classifiers":[
        {
            "category":"Building & Trades",
            "subcategory":"Construction",
            "type":"Services"
        }
    ],
    "sg:phone":"+1 204 268 3724",
    "sg:postcode":"R0E 0C0",
    "sg:province":"MB",
    "sg:tags":[
        "general",
        "contractor"
    ],
    "wof:name":"Delgar Construction Ltd",
    "wof:placetype":"venue"
},
  "geometry": {"coordinates":[-96.51664700000001,50.062176],"type":"Point"}
}