{
  "type": "Feature",
  "properties": {
    "addr:full":"144 Pearl St Deseronto ON K0K 1X0",
    "addr:housenumber":"144",
    "addr:postcode":"k0k 1x0",
    "addr:street":"Pearl St",
    "iso:country":"CA",
    "sg:address":"144 Pearl St",
    "sg:city":"Deseronto",
    "sg:classifiers":[
        {
            "category":"Shopping",
            "subcategory":"Bicycles & Sporting Goods",
            "type":"Retail Goods"
        }
    ],
    "sg:phone":"+1 613 396 2208",
    "sg:postcode":"K0K 1X0",
    "sg:province":"ON",
    "sg:tags":[
        "bait",
        "fishing"
    ],
    "wof:name":"Moon's Bait & Tackle",
    "wof:placetype":"venue"
},
  "geometry": {"coordinates":[-77.057434,44.195141],"type":"Point"}
}