{
  "type": "Feature",
  "properties": {
    "addr:full":"Calgary AB T2A 0S5",
    "addr:postcode":"t2a 0s5",
    "iso:country":"CA",
    "sg:city":"Calgary",
    "sg:classifiers":[
        {
            "category":"Food & Beverages",
            "subcategory":"Meat & Fish",
            "type":"Retail Goods"
        }
    ],
    "sg:phone":"+1 403 272 1119",
    "sg:postcode":"T2A 0S5",
    "sg:province":"AB",
    "wof:name":"Mediterranean Meats & Grocery",
    "wof:placetype":"venue"
},
  "geometry": {"coordinates":[-113.97834,51.03772],"type":"Point"}
}