{
  "type": "Feature",
  "properties": {
    "iso:country":"CA",
    "sg:address":"Highway 39",
    "sg:city":"North Portal",
    "sg:classifiers":[
        {
            "category":"Government",
            "subcategory":"Office",
            "type":"Public Place"
        }
    ],
    "sg:phone":"+1 306 927 2455",
    "sg:postcode":"S0C 1W0",
    "sg:province":"SK",
    "wof:name":"Canada Customs & Excise Dept",
    "wof:placetype":"venue"
},
  "geometry": {"coordinates":[-102.548400879,49.0023498535],"type":"Point"}
}