{
  "type": "Feature",
  "properties": {
    "addr:full":"107 Rue Eddy Hull QC J8X 2W6",
    "addr:housenumber":"107",
    "addr:postcode":"j8x 2w6",
    "addr:street":"Rue Eddy",
    "iso:country":"CA",
    "sg:address":"107 Rue Eddy",
    "sg:city":"Hull",
    "sg:classifiers":[
        {
            "category":"Food & Beverages",
            "subcategory":"Groceries & Convenience Stores",
            "type":"Retail Goods"
        }
    ],
    "sg:phone":"+1 819 595 1011",
    "sg:postcode":"J8X 2W6",
    "sg:province":"QC",
    "wof:name":"Depanneur Los Andes",
    "wof:placetype":"venue"
},
  "geometry": {"coordinates":[-75.7202453613,45.4284095764],"type":"Point"}
}