{
  "type": "Feature",
  "properties": {
    "addr:full":"1032 Rue Saint-Cyrille Normandin QC G8M 4H5",
    "addr:housenumber":"1032",
    "addr:postcode":"g8m 4h5",
    "addr:street":"Rue Saint-Cyrille",
    "iso:country":"CA",
    "sg:address":"1032 Rue Saint-Cyrille",
    "sg:city":"Normandin",
    "sg:classifiers":[
        {
            "category":"Banks & Credit Unions",
            "subcategory":"Bank",
            "type":"Services"
        }
    ],
    "sg:phone":"+1 418 274 3007",
    "sg:postcode":"G8M 4H5",
    "sg:province":"QC",
    "wof:name":"Caisse Populaire Desjardins",
    "wof:placetype":"venue"
},
  "geometry": {"coordinates":[-72.5281295776,48.8357162476],"type":"Point"}
}