{
  "type": "Feature",
  "properties": {
    "addr:full":"2073 Av Branly Sainte-Foy QC G1N 4C7",
    "addr:housenumber":"2073",
    "addr:postcode":"g1n 4c7",
    "addr:street":"Av Branly",
    "iso:country":"CA",
    "sg:address":"2073 Av Branly",
    "sg:city":"Sainte-Foy",
    "sg:classifiers":[
        {
            "category":"Wholesale",
            "subcategory":"Machinery & Supplies",
            "type":"Manufacturing & Wholesale Goods"
        }
    ],
    "sg:phone":"+1 418 681 0129",
    "sg:postcode":"G1N 4C7",
    "sg:province":"QC",
    "sg:tags":[
        "equipment",
        "tag",
        "labeling"
    ],
    "wof:name":"Andre Morin Inc",
    "wof:placetype":"venue"
},
  "geometry": {"coordinates":[-71.27265199999999,46.793083],"type":"Point"}
}