{
  "type": "Feature",
  "properties": {
    "iso:country":"CA",
    "sg:city":"Nanaimo",
    "sg:classifiers":[
        {
            "category":"Retail",
            "subcategory":"Self-service Laundry",
            "type":"Services"
        }
    ],
    "sg:phone":"+1 250 753 6312",
    "sg:postcode":"V9R 1P1",
    "sg:province":"BC",
    "sg:tags":[
        "cleaners"
    ],
    "wof:name":"Harewood Laundromat",
    "wof:placetype":"venue"
},
  "geometry": {"coordinates":[-123.951241,49.155273],"type":"Point"}
}