{
  "type": "Feature",
  "properties": {
    "addr:full":"1216 Rue Jean-Talon E Montreal QC H2R 1W2",
    "addr:housenumber":"1216",
    "addr:postcode":"h2r 1w2",
    "addr:street":"Rue Jean-Talon E",
    "iso:country":"CA",
    "sg:address":"1216 Rue Jean-Talon E",
    "sg:city":"Montreal",
    "sg:classifiers":[
        {
            "category":"Health Services",
            "subcategory":"Medical Lab",
            "type":"Services"
        }
    ],
    "sg:phone":"+1 514 277 5628",
    "sg:postcode":"H2R 1W2",
    "sg:province":"QC",
    "wof:name":"Clinique-Denturologie Pilotte",
    "wof:placetype":"venue"
},
  "geometry": {"coordinates":[-73.6109390259,45.5434303284],"type":"Point"}
}