{
  "type": "Feature",
  "properties": {
    "addr:full":"40 Driveway Ottawa ON K2P 2C9",
    "addr:housenumber":"40",
    "addr:postcode":"k2p 2c9",
    "addr:street":"Driveway",
    "iso:country":"CA",
    "sg:address":"40 Driveway",
    "sg:city":"Ottawa",
    "sg:classifiers":[
        {
            "category":"Real Estate",
            "subcategory":"Real Estate Operator",
            "type":"Services"
        }
    ],
    "sg:phone":"+1 613 729 4115",
    "sg:postcode":"K2P 2C9",
    "sg:province":"ON",
    "sg:tags":[
        "apartment"
    ],
    "wof:name":"Lamplighter Apartments",
    "wof:placetype":"venue"
},
  "geometry": {"coordinates":[-75.6835784912,45.4193077087],"type":"Point"}
}