{
  "type": "Feature",
  "properties": {
    "iso:country":"CA",
    "sg:address":"13717 70 St # 299",
    "sg:city":"Edmonton",
    "sg:classifiers":[
        {
            "category":"Shopping",
            "subcategory":"Shoes",
            "type":"Retail Goods"
        }
    ],
    "sg:phone":"+1 780 472 1275",
    "sg:postcode":"T5C 3E6",
    "sg:province":"AB",
    "wof:name":"Aldo Shoes Inc",
    "wof:placetype":"venue"
},
  "geometry": {"coordinates":[-113.448776245,53.6001167297],"type":"Point"}
}