{
  "type": "Feature",
  "properties": {
    "addr:full":"78 Rue Lasalle Repentigny QC J6A 4V3",
    "addr:housenumber":"78",
    "addr:postcode":"j6a 4v3",
    "addr:street":"Rue Lasalle",
    "iso:country":"CA",
    "sg:address":"78 Rue Lasalle",
    "sg:city":"Repentigny",
    "sg:classifiers":[
        {
            "category":"Manufacturing",
            "subcategory":"Printing",
            "type":"Manufacturing & Wholesale Goods"
        }
    ],
    "sg:phone":"+1 450 581 5325",
    "sg:postcode":"J6A 4V3",
    "sg:province":"QC",
    "sg:tags":[
        "printer"
    ],
    "wof:name":"Pro Traduction & Imprimerie",
    "wof:placetype":"venue"
},
  "geometry": {"coordinates":[-73.4392089844,45.749584198],"type":"Point"}
}