{
  "type": "Feature",
  "properties": {
    "iso:country":"CA",
    "sg:address":"544 Rue Longtin",
    "sg:city":"LA Prairie",
    "sg:classifiers":[
        {
            "category":"Personal",
            "subcategory":"Beauty Salon",
            "type":"Services"
        }
    ],
    "sg:phone":"+1 450 444 5955",
    "sg:postcode":"J5R 2W5",
    "sg:province":"QC",
    "wof:name":"Salon Diane Langlois Coiffure",
    "wof:placetype":"venue"
},
  "geometry": {"coordinates":[-73.492996,45.410484],"type":"Point"}
}