{
  "type": "Feature",
  "properties": {
    "addr:full":"3147 Portage Ave Winnipeg MB R3K 0W4",
    "addr:housenumber":"3147",
    "addr:postcode":"r3k 0w4",
    "addr:street":"Portage Ave",
    "iso:country":"CA",
    "sg:address":"3147 Portage Ave",
    "sg:city":"Winnipeg",
    "sg:classifiers":[
        {
            "category":"Personal",
            "type":"Services"
        }
    ],
    "sg:phone":"+1 204 837 7200",
    "sg:postcode":"R3K 0W4",
    "sg:province":"MB",
    "sg:tags":[
        "control",
        "weight"
    ],
    "wof:name":"Herbal Magic Nutritional Ctr",
    "wof:placetype":"venue"
},
  "geometry": {"coordinates":[-97.284668,49.880611],"type":"Point"}
}