{
  "type": "Feature",
  "properties": {
    "addr:full":"146 Simcoe St N Oshawa ON L1G 4S7",
    "addr:housenumber":"146",
    "addr:postcode":"l1g 4s7",
    "addr:street":"Simcoe St N",
    "iso:country":"CA",
    "sg:address":"146 Simcoe St N",
    "sg:city":"Oshawa",
    "sg:classifiers":[
        {
            "category":"Banks & Credit Unions",
            "subcategory":"Financial Services",
            "type":"Services"
        }
    ],
    "sg:phone":"+1 905 728 9404",
    "sg:postcode":"L1G 4S7",
    "sg:province":"ON",
    "sg:tags":[
        "bankruptcy",
        "trustee"
    ],
    "wof:name":"Clark Henning Inc",
    "wof:placetype":"venue"
},
  "geometry": {"coordinates":[-78.865524292,43.9013633728],"type":"Point"}
}