{
  "type": "Feature",
  "properties": {
    "addr:full":"144 Prom Du Portage # 4 Hull QC J8X 2K3",
    "addr:housenumber":"144;# 4",
    "addr:postcode":"j8x 2k3",
    "addr:street":"Prom Du Portage",
    "iso:country":"CA",
    "sg:address":"144 Prom Du Portage # 4",
    "sg:city":"Hull",
    "sg:classifiers":[
        {
            "category":"Health Services",
            "subcategory":"Doctor",
            "type":"Services"
        }
    ],
    "sg:phone":"+1 819 771 3368",
    "sg:postcode":"J8X 2K3",
    "sg:province":"QC",
    "sg:tags":[
        "dentist"
    ],
    "wof:name":"Cooper, Barry DDS",
    "wof:placetype":"venue"
},
  "geometry": {"coordinates":[-75.7157897949,45.425945282],"type":"Point"}
}