{
  "type": "Feature",
  "properties": {
    "addr:full":"37 River St Kentville NS B4N 1G8",
    "addr:housenumber":"37",
    "addr:postcode":"b4n 1g8",
    "addr:street":"River St",
    "iso:country":"CA",
    "sg:address":"37 River St",
    "sg:city":"Kentville",
    "sg:classifiers":[
        {
            "category":"Organizations",
            "subcategory":"Professional Association",
            "type":"Services"
        }
    ],
    "sg:phone":"+1 902 678 8935",
    "sg:postcode":"B4N 1G8",
    "sg:province":"NS",
    "sg:tags":[
        "club"
    ],
    "wof:name":"Royal Canadian Legion",
    "wof:placetype":"venue"
},
  "geometry": {"coordinates":[-64.497345,45.079834],"type":"Point"}
}