{
  "type": "Feature",
  "properties": {
    "addr:full":"1115 Centre St NW Calgary AB T2E 2R1",
    "addr:housenumber":"1115",
    "addr:postcode":"t2e 2r1",
    "addr:street":"Centre St Nw",
    "iso:country":"CA",
    "sg:address":"1115 Centre St NW",
    "sg:city":"Calgary",
    "sg:classifiers":[
        {
            "category":"Restaurant",
            "type":"Food & Drink"
        }
    ],
    "sg:phone":"+1 403 230 2408",
    "sg:postcode":"T2E 2R1",
    "sg:province":"AB",
    "wof:name":"Trong Khanh Restaurant",
    "wof:placetype":"venue"
},
  "geometry": {"coordinates":[-114.062744141,51.0617752075],"type":"Point"}
}