{
  "type": "Feature",
  "properties": {
    "addr:full":"Winkler MB R6W 2S2",
    "addr:postcode":"r6w 2s2",
    "iso:country":"CA",
    "sg:city":"Winkler",
    "sg:classifiers":[
        {
            "category":"Banks & Credit Unions",
            "subcategory":"Bank",
            "type":"Services"
        }
    ],
    "sg:phone":"+1 204 325 9543",
    "sg:postcode":"R6W 2S2",
    "sg:province":"MB",
    "wof:name":"Scotiabank",
    "wof:placetype":"venue"
},
  "geometry": {"coordinates":[-97.93250999999999,49.190529],"type":"Point"}
}