{
  "type": "Feature",
  "properties": {
    "addr:full":"5190 Boul Saint-Laurent Montreal QC H2T 1R8",
    "addr:housenumber":"5190",
    "addr:postcode":"h2t 1r8",
    "addr:street":"Boul Saint-Laurent",
    "iso:country":"CA",
    "sg:address":"5190 Boul Saint-Laurent",
    "sg:city":"Montreal",
    "sg:classifiers":[
        {
            "category":"Shopping",
            "subcategory":"Bicycles & Sporting Goods",
            "type":"Retail Goods"
        }
    ],
    "sg:phone":"+1 514 271 0773",
    "sg:postcode":"H2T 1R8",
    "sg:province":"QC",
    "wof:name":"Yeti Boutique Plein Air",
    "wof:placetype":"venue"
},
  "geometry": {"coordinates":[-73.5943450928,45.5235939026],"type":"Point"}
}