{
  "type": "Feature",
  "properties": {
    "addr:full":"York ON M9N 3P5",
    "addr:postcode":"m9n 3p5",
    "iso:country":"CA",
    "sg:city":"York",
    "sg:classifiers":[
        {
            "category":"Shopping",
            "subcategory":"Optical Goods",
            "type":"Retail Goods"
        }
    ],
    "sg:phone":"+1 416 245 3418",
    "sg:postcode":"M9N 3P5",
    "sg:province":"ON",
    "sg:tags":[
        "optometrist",
        "optician"
    ],
    "wof:name":"Super Vision Optical Inc",
    "wof:placetype":"venue"
},
  "geometry": {"coordinates":[-79.516357,43.70031],"type":"Point"}
}