{
  "type": "Feature",
  "properties": {
    "iso:country":"CA",
    "sg:address":"117 Rue Laflamme",
    "sg:city":"Sainte-Claire",
    "sg:classifiers":[
        {
            "category":"Personal",
            "subcategory":"Beauty Salon",
            "type":"Services"
        }
    ],
    "sg:phone":"+1 418 883 2080",
    "sg:postcode":"G0R 2V0",
    "sg:province":"QC",
    "wof:name":"Salon D'Esthetique Rv",
    "wof:placetype":"venue"
},
  "geometry": {"coordinates":[-70.8663101196,46.6038169861],"type":"Point"}
}