{
  "type": "Feature",
  "properties": {
    "addr:full":"340 Wilson Ave North York ON M3H 1S9",
    "addr:housenumber":"340",
    "addr:postcode":"m3h 1s9",
    "addr:street":"Wilson Ave",
    "iso:country":"CA",
    "sg:address":"340 Wilson Ave",
    "sg:city":"North York",
    "sg:classifiers":[
        {
            "category":"Shopping",
            "subcategory":"Discount & Variety Stores",
            "type":"Retail Goods"
        }
    ],
    "sg:phone":"+1 416 638 7083",
    "sg:postcode":"M3H 1S9",
    "sg:province":"ON",
    "wof:name":"Discount Variety",
    "wof:placetype":"venue"
},
  "geometry": {"coordinates":[-79.437614,43.736797],"type":"Point"}
}