{
  "type": "Feature",
  "properties": {
    "addr:full":"19718 Yonge St Holland Landing ON L9N 1M4",
    "addr:housenumber":"19718",
    "addr:postcode":"l9n 1m4",
    "addr:street":"Yonge St",
    "iso:country":"CA",
    "sg:address":"19718 Yonge St",
    "sg:city":"Holland Landing",
    "sg:classifiers":[
        {
            "category":"Utilities",
            "subcategory":"Refuse",
            "type":"Services"
        }
    ],
    "sg:phone":"+1 905 836 7600",
    "sg:postcode":"L9N 1M4",
    "sg:province":"ON",
    "sg:tags":[
        "garbage",
        "collection"
    ],
    "wof:name":"Clean Up & Green Up",
    "wof:placetype":"venue"
},
  "geometry": {"coordinates":[-79.49372099999999,44.108929],"type":"Point"}
}