{
  "type": "Feature",
  "properties": {
    "addr:full":"1982 Kings Rd Victoria BC V8R 2P5",
    "addr:housenumber":"1982",
    "addr:postcode":"v8r 2p5",
    "addr:street":"Kings Rd",
    "iso:country":"CA",
    "sg:address":"1982 Kings Rd",
    "sg:city":"Victoria",
    "sg:classifiers":[
        {
            "category":"Wholesale",
            "subcategory":"Machinery & Supplies",
            "type":"Manufacturing & Wholesale Goods"
        }
    ],
    "sg:phone":"+1 250 598 5121",
    "sg:postcode":"V8R 2P5",
    "sg:province":"BC",
    "sg:tags":[
        "machine",
        "sewing"
    ],
    "wof:name":"All Sew",
    "wof:placetype":"venue"
},
  "geometry": {"coordinates":[-123.328262,48.437809],"type":"Point"}
}