{
  "type": "Feature",
  "properties": {
    "addr:full":"Atikokan ON P0T 1C0",
    "addr:postcode":"p0t 1c0",
    "iso:country":"CA",
    "sg:city":"Atikokan",
    "sg:classifiers":[
        {
            "category":"Home & Garden",
            "subcategory":"Building Materials",
            "type":"Retail Goods"
        }
    ],
    "sg:phone":"+1 807 597 1548",
    "sg:postcode":"P0T 1C0",
    "sg:province":"ON",
    "sg:tags":[
        "windows"
    ],
    "wof:name":"Sunset Windows & Doors",
    "wof:placetype":"venue"
},
  "geometry": {"coordinates":[-91.6276931763,48.7555351257],"type":"Point"}
}