{
  "type": "Feature",
  "properties": {
    "addr:full":"60 Rosedale Ave Halifax NS B3N 2J5",
    "addr:housenumber":"60",
    "addr:postcode":"b3n 2j5",
    "addr:street":"Rosedale Ave",
    "iso:country":"CA",
    "sg:address":"60 Rosedale Ave",
    "sg:city":"Halifax",
    "sg:classifiers":[
        {
            "category":"Food & Beverages",
            "subcategory":"Groceries & Convenience Stores",
            "type":"Retail Goods"
        }
    ],
    "sg:phone":"+1 902 457 7000",
    "sg:postcode":"B3N 2J5",
    "sg:province":"NS",
    "wof:name":"Super Mike's 2 Convenience Str",
    "wof:placetype":"venue"
},
  "geometry": {"coordinates":[-63.637489,44.65295],"type":"Point"}
}