{
  "type": "Feature",
  "properties": {
    "addr:full":"3 Queen St Kapuskasing ON P5N 1G5",
    "addr:housenumber":"3",
    "addr:postcode":"p5n 1g5",
    "addr:street":"Queen St",
    "iso:country":"CA",
    "sg:address":"3 Queen St",
    "sg:city":"Kapuskasing",
    "sg:classifiers":[
        {
            "category":"Health Services",
            "subcategory":"Chiropractor",
            "type":"Services"
        }
    ],
    "sg:phone":"+1 705 335 8551",
    "sg:postcode":"P5N 1G5",
    "sg:province":"ON",
    "wof:name":"Oldaker, K J DC",
    "wof:placetype":"venue"
},
  "geometry": {"coordinates":[-82.42392700000001,49.417355],"type":"Point"}
}