{
  "type": "Feature",
  "properties": {
    "addr:full":"Farm Carievale SK S0C 0P0",
    "addr:postcode":"s0c 0p0",
    "iso:country":"CA",
    "sg:address":"Farm",
    "sg:city":"Carievale",
    "sg:classifiers":[
        {
            "category":"Farming",
            "subcategory":"Farm",
            "type":"Manufacturing & Wholesale Goods"
        }
    ],
    "sg:phone":"+1 306 928 2011",
    "sg:postcode":"S0C 0P0",
    "sg:province":"SK",
    "wof:name":"Mc Millen Ranching Ltd",
    "wof:placetype":"venue"
},
  "geometry": {"coordinates":[-101.63078299999999,49.177414],"type":"Point"}
}