{
  "type": "Feature",
  "properties": {
    "addr:full":"590 Rue Daniel Saint-Amable QC J0L 1N0",
    "addr:housenumber":"590",
    "addr:postcode":"j0l 1n0",
    "addr:street":"Rue Daniel",
    "iso:country":"CA",
    "sg:address":"590 Rue Daniel",
    "sg:city":"Saint-Amable",
    "sg:classifiers":[
        {
            "category":"Building & Trades",
            "subcategory":"Electrical",
            "type":"Services"
        }
    ],
    "sg:phone":"+1 450 922 4507",
    "sg:postcode":"J0L 1N0",
    "sg:province":"QC",
    "sg:tags":[
        "electric",
        "contractor"
    ],
    "wof:name":"Sagemtech Inc",
    "wof:placetype":"venue"
},
  "geometry": {"coordinates":[-73.302368,45.652538],"type":"Point"}
}