{
  "type": "Feature",
  "properties": {
    "addr:full":"68 Schwanz Rd Petawawa ON K8H 1Y5",
    "addr:housenumber":"68",
    "addr:postcode":"k8h 1y5",
    "addr:street":"Schwanz Rd",
    "iso:country":"CA",
    "sg:address":"68 Schwanz Rd",
    "sg:city":"Petawawa",
    "sg:classifiers":[
        {
            "category":"Government",
            "subcategory":"Fire Station",
            "type":"Public Place"
        }
    ],
    "sg:phone":"+1 ",
    "sg:postcode":"K8H 1Y5",
    "sg:province":"ON",
    "sg:tags":[
        "department"
    ],
    "wof:name":"Petawawa Fire Station",
    "wof:placetype":"venue"
},
  "geometry": {"coordinates":[-77.28321099999999,45.899235],"type":"Point"}
}