{
  "type": "Feature",
  "properties": {
    "addr:full":"3031 30 Ave Red Deer AB T4R 2Z7",
    "addr:housenumber":"3031",
    "addr:postcode":"t4r 2z7",
    "addr:street":"30 Ave",
    "iso:country":"CA",
    "sg:address":"3031 30 Ave",
    "sg:city":"Red Deer",
    "sg:classifiers":[
        {
            "category":"Health Services",
            "subcategory":"Chiropractor",
            "type":"Services"
        }
    ],
    "sg:phone":"+1 403 314 4456",
    "sg:postcode":"T4R 2Z7",
    "sg:province":"AB",
    "wof:name":"Optimum Performance Ctr",
    "wof:placetype":"venue"
},
  "geometry": {"coordinates":[-113.766121,52.259796],"type":"Point"}
}