{
  "type": "Feature",
  "properties": {
    "iso:country":"CA",
    "sg:address":"Hoosier",
    "sg:city":"Smiley",
    "sg:classifiers":[
        {
            "category":"Government",
            "subcategory":"Office",
            "type":"Public Place"
        }
    ],
    "sg:phone":"+1 306 838 4508",
    "sg:postcode":"S0L 2Z0",
    "sg:province":"SK",
    "wof:name":"Canada Antelope Park Comm Past",
    "wof:placetype":"venue"
},
  "geometry": {"coordinates":[-109.47730255099999,51.6332435608],"type":"Point"}
}