{
  "type": "Feature",
  "properties": {
    "addr:full":"Etobicoke ON M9W 5X1",
    "addr:postcode":"m9w 5x1",
    "iso:country":"CA",
    "sg:city":"Etobicoke",
    "sg:classifiers":[
        {
            "category":"Manufacturing",
            "subcategory":"Apparel",
            "type":"Manufacturing & Wholesale Goods"
        }
    ],
    "sg:phone":"+1 416 675 7773",
    "sg:postcode":"M9W 5X1",
    "sg:province":"ON",
    "sg:tags":[
        "clothing"
    ],
    "wof:name":"Mc Cormick Textiles Ltd",
    "wof:placetype":"venue"
},
  "geometry": {"coordinates":[-79.6178436279,43.7364654541],"type":"Point"}
}