{
  "type": "Feature",
  "properties": {
    "addr:full":"1320 Rue Labadie Longueuil QC J4N 1C7",
    "addr:housenumber":"1320",
    "addr:postcode":"j4n 1c7",
    "addr:street":"Rue Labadie",
    "iso:country":"CA",
    "sg:address":"1320 Rue Labadie",
    "sg:city":"Longueuil",
    "sg:classifiers":[
        {
            "category":"Wholesale",
            "subcategory":"Machinery & Supplies",
            "type":"Manufacturing & Wholesale Goods"
        }
    ],
    "sg:phone":"+1 450 670 6555",
    "sg:postcode":"J4N 1C7",
    "sg:province":"QC",
    "sg:tags":[
        "baker"
    ],
    "wof:name":"Emballages Florisec Inc",
    "wof:placetype":"venue"
},
  "geometry": {"coordinates":[-73.453186,45.563843],"type":"Point"}
}