{
  "type": "Feature",
  "properties": {
    "addr:full":"2773 Central Ave Grand Forks BC V0H 1H2",
    "addr:housenumber":"2773",
    "addr:postcode":"v0h 1h2",
    "addr:street":"Central Ave",
    "iso:country":"CA",
    "sg:address":"2773 Central Ave",
    "sg:city":"Grand Forks",
    "sg:classifiers":[
        {
            "category":"Autos & Motor Vehicles",
            "subcategory":"Fuel & Gas Station",
            "type":"Retail Goods"
        }
    ],
    "sg:phone":"+1 250 442 3255",
    "sg:postcode":"V0H 1H2",
    "sg:province":"BC",
    "sg:tags":[
        "oil"
    ],
    "wof:name":"Super-Save Gas",
    "wof:placetype":"venue"
},
  "geometry": {"coordinates":[-118.472061,49.023495],"type":"Point"}
}