{
  "type": "Feature",
  "properties": {
    "iso:country":"CA",
    "sg:address":"43 Sunnylea Cres",
    "sg:city":"Guelph",
    "sg:classifiers":[
        {
            "category":"Professional",
            "subcategory":"Business Services",
            "type":"Services"
        }
    ],
    "sg:phone":"+1 519 763 7335",
    "sg:postcode":"N1E 1W3",
    "sg:province":"ON",
    "sg:tags":[
        "process",
        "server"
    ],
    "wof:name":"Ace Serve Process Server",
    "wof:placetype":"venue"
},
  "geometry": {"coordinates":[-80.255043,43.560158],"type":"Point"}
}