{
  "type": "Feature",
  "properties": {
    "addr:full":"Windsor ON N8X 3T5",
    "addr:postcode":"n8x 3t5",
    "iso:country":"CA",
    "sg:city":"Windsor",
    "sg:classifiers":[
        {
            "category":"Manufacturing",
            "subcategory":"Printing",
            "type":"Manufacturing & Wholesale Goods"
        }
    ],
    "sg:phone":"+1 519 254 1009",
    "sg:postcode":"N8X 3T5",
    "sg:province":"ON",
    "sg:tags":[
        "screen",
        "advertising"
    ],
    "wof:name":"Graphix Plus",
    "wof:placetype":"venue"
},
  "geometry": {"coordinates":[-83.02038574220001,42.3028526306],"type":"Point"}
}