{
  "type": "Feature",
  "properties": {
    "addr:full":"Scarborough ON M1V 5J6",
    "addr:postcode":"m1v 5j6",
    "iso:country":"CA",
    "sg:city":"Scarborough",
    "sg:classifiers":[
        {
            "category":"Professional",
            "subcategory":"Lawyer & Legal Services",
            "type":"Services"
        }
    ],
    "sg:phone":"+1 416 609 8200",
    "sg:postcode":"M1V 5J6",
    "sg:province":"ON",
    "sg:tags":[
        "attorney"
    ],
    "wof:name":"Mohan & Mohan",
    "wof:placetype":"venue"
},
  "geometry": {"coordinates":[-79.261932,43.820305],"type":"Point"}
}