{
  "type": "Feature",
  "properties": {
    "addr:full":"2204 Eglinton Ave W York ON M6E 2L1",
    "addr:housenumber":"2204",
    "addr:postcode":"m6e 2l1",
    "addr:street":"Eglinton Ave W",
    "iso:country":"CA",
    "sg:address":"2204 Eglinton Ave W",
    "sg:city":"York",
    "sg:classifiers":[
        {
            "category":"Building & Trades",
            "subcategory":"Plumbing",
            "type":"Services"
        }
    ],
    "sg:phone":"+1 416 782 9783",
    "sg:postcode":"M6E 2L1",
    "sg:province":"ON",
    "sg:tags":[
        "heating",
        "contractor"
    ],
    "wof:name":"Cutrone & Son Heating & Plbg",
    "wof:placetype":"venue"
},
  "geometry": {"coordinates":[-79.4616317749,43.6932983398],"type":"Point"}
}