{
  "type": "Feature",
  "properties": {
    "addr:full":"294 Riverview Pk SE Calgary AB T2C 3Z7",
    "addr:housenumber":"294",
    "addr:postcode":"t2c 3z7",
    "addr:street":"Riverview Pk Se",
    "iso:country":"CA",
    "sg:address":"294 Riverview Pk SE",
    "sg:city":"Calgary",
    "sg:classifiers":[
        {
            "category":"Building & Trades",
            "subcategory":"Electrical",
            "type":"Services"
        }
    ],
    "sg:phone":"+1 403 540 4110",
    "sg:postcode":"T2C 3Z7",
    "sg:province":"AB",
    "sg:tags":[
        "electric",
        "contractor"
    ],
    "wof:name":"A-1 Electric Inc",
    "wof:placetype":"venue"
},
  "geometry": {"coordinates":[-114.020241,50.971748],"type":"Point"}
}