{
  "type": "Feature",
  "properties": {
    "addr:full":"2855 Boul Matte Brossard QC J4Y 2P4",
    "addr:housenumber":"2855",
    "addr:postcode":"j4y 2p4",
    "addr:street":"Boul Matte",
    "iso:country":"CA",
    "sg:address":"2855 Boul Matte",
    "sg:city":"Brossard",
    "sg:classifiers":[
        {
            "category":"Wholesale",
            "subcategory":"Durable Goods & Equipment",
            "type":"Manufacturing & Wholesale Goods"
        }
    ],
    "sg:phone":"+1 450 444 4711",
    "sg:postcode":"J4Y 2P4",
    "sg:province":"QC",
    "sg:tags":[
        "laser"
    ],
    "wof:name":"Biophoton Canada Inc",
    "wof:placetype":"venue"
},
  "geometry": {"coordinates":[-73.471519,45.433208],"type":"Point"}
}