{
  "type": "Feature",
  "properties": {
    "addr:full":"Lloydminster AB T9V 0Y8",
    "addr:postcode":"t9v 0y8",
    "iso:country":"CA",
    "sg:city":"Lloydminster",
    "sg:classifiers":[
        {
            "category":"Organizations",
            "subcategory":"Professional Association",
            "type":"Services"
        }
    ],
    "sg:phone":"+1 780 875 9013",
    "sg:postcode":"T9V 0Y8",
    "sg:province":"AB",
    "sg:tags":[
        "chambers",
        "commerce"
    ],
    "wof:name":"Lloydminster Chamber-Commerce",
    "wof:placetype":"venue"
},
  "geometry": {"coordinates":[-110.010284,53.279728],"type":"Point"}
}