{
  "type": "Feature",
  "properties": {
    "addr:full":"350 Morningside Ave Scarborough ON M1E 3G3",
    "addr:housenumber":"350",
    "addr:postcode":"m1e 3g3",
    "addr:street":"Morningside Ave",
    "iso:country":"CA",
    "sg:address":"350 Morningside Ave",
    "sg:city":"Scarborough",
    "sg:classifiers":[
        {
            "category":"Education",
            "subcategory":"School",
            "type":"Public Place"
        }
    ],
    "sg:phone":"+1 416 396 6864",
    "sg:postcode":"M1E 3G3",
    "sg:province":"ON",
    "wof:name":"West Hill Collegiate Institute",
    "wof:placetype":"venue"
},
  "geometry": {"coordinates":[-79.189583,43.776222],"type":"Point"}
}