{
  "type": "Feature",
  "properties": {
    "addr:full":"171 Railway Ave Cypress River MB R0K 0P0",
    "addr:housenumber":"171",
    "addr:postcode":"r0k 0p0",
    "addr:street":"Railway Ave Cypress",
    "iso:country":"CA",
    "sg:address":"171 Railway Ave",
    "sg:city":"Cypress River",
    "sg:classifiers":[
        {
            "category":"Home & Garden",
            "subcategory":"Building Materials",
            "type":"Retail Goods"
        }
    ],
    "sg:phone":"+1 204 743 2085",
    "sg:postcode":"R0K 0P0",
    "sg:province":"MB",
    "wof:name":"Truelove Building Supplies",
    "wof:placetype":"venue"
},
  "geometry": {"coordinates":[-99.0869979858,49.5551185608],"type":"Point"}
}