{
  "type": "Feature",
  "properties": {
    "addr:full":"Hanmer ON P3P 1P7",
    "addr:postcode":"p3p 1p7",
    "iso:country":"CA",
    "sg:city":"Hanmer",
    "sg:classifiers":[
        {
            "category":"Health Services",
            "subcategory":"Chiropractor",
            "type":"Services"
        }
    ],
    "sg:phone":"+1 705 969 4475",
    "sg:postcode":"P3P 1P7",
    "sg:province":"ON",
    "wof:name":"Landry, Ghislaine DC",
    "wof:placetype":"venue"
},
  "geometry": {"coordinates":[-80.944801,46.652496],"type":"Point"}
}