{
  "type": "Feature",
  "properties": {
    "addr:full":"5280 Gainsburg Bowser BC V0R 1G0",
    "addr:housenumber":"5280",
    "addr:postcode":"v0r 1g0",
    "addr:street":"Gainsburg",
    "iso:country":"CA",
    "sg:address":"5280 Gainsburg",
    "sg:city":"Bowser",
    "sg:classifiers":[
        {
            "category":"Professional",
            "subcategory":"Business Services",
            "type":"Services"
        }
    ],
    "sg:phone":"+1 250 757 9495",
    "sg:postcode":"V0R 1G0",
    "sg:province":"BC",
    "sg:tags":[
        "drafting"
    ],
    "wof:name":"Christoffel Kuun Design",
    "wof:placetype":"venue"
},
  "geometry": {"coordinates":[-124.71126599999999,49.45319],"type":"Point"}
}