{
  "type": "Feature",
  "properties": {
    "addr:full":"148 Kenwood Ave York ON M6C 2S3",
    "addr:housenumber":"148",
    "addr:postcode":"m6c 2s3",
    "addr:street":"Kenwood Ave",
    "iso:country":"CA",
    "sg:address":"148 Kenwood Ave",
    "sg:city":"York",
    "sg:classifiers":[
        {
            "category":"Building & Trades",
            "subcategory":"Landscaping Services",
            "type":"Services"
        }
    ],
    "sg:phone":"+1 416 656 6665",
    "sg:postcode":"M6C 2S3",
    "sg:province":"ON",
    "sg:tags":[
        "designer",
        "landscape"
    ],
    "wof:name":"Janet Rosenberg & Assoc Inc",
    "wof:placetype":"venue"
},
  "geometry": {"coordinates":[-79.424049,43.687149],"type":"Point"}
}