{
  "type": "Feature",
  "properties": {
    "addr:full":"5461 Timberlea Blvd Mississauga ON L4W 2T6",
    "addr:housenumber":"5461",
    "addr:postcode":"l4w 2t6",
    "addr:street":"Timberlea Blvd",
    "iso:country":"CA",
    "sg:address":"5461 Timberlea Blvd",
    "sg:city":"Mississauga",
    "sg:classifiers":[
        {
            "category":"Manufacturing",
            "subcategory":"Metals",
            "type":"Manufacturing & Wholesale Goods"
        }
    ],
    "sg:phone":"+1 905 624 9235",
    "sg:postcode":"L4W 2T6",
    "sg:province":"ON",
    "sg:tags":[
        "stamping"
    ],
    "wof:name":"Lennox Tool & Die CO Ltd",
    "wof:placetype":"venue"
},
  "geometry": {"coordinates":[-79.64662199999999,43.633247],"type":"Point"}
}