{
  "type": "Feature",
  "properties": {
    "addr:full":"255 Ch DE LA Reserve Chicoutimi QC G7J 3N2",
    "addr:housenumber":"255",
    "addr:postcode":"g7j 3n2",
    "addr:street":"Ch De La Reserve",
    "iso:country":"CA",
    "sg:address":"255 Ch DE LA Reserve",
    "sg:city":"Chicoutimi",
    "sg:classifiers":[
        {
            "category":"Building & Trades",
            "subcategory":"Construction",
            "type":"Services"
        }
    ],
    "sg:phone":"+1 418 543 9384",
    "sg:postcode":"G7J 3N2",
    "sg:province":"QC",
    "sg:tags":[
        "excavating",
        "contractor"
    ],
    "wof:name":"Bouchard Rosaire & Fils",
    "wof:placetype":"venue"
},
  "geometry": {"coordinates":[-71.0793228149,48.4288406372],"type":"Point"}
}