{
  "type": "Feature",
  "properties": {
    "iso:country":"CA",
    "sg:address":"122 Main St",
    "sg:city":"Balcarres",
    "sg:classifiers":[
        {
            "category":"Food & Beverages",
            "subcategory":"Groceries & Convenience Stores",
            "type":"Retail Goods"
        }
    ],
    "sg:phone":"+1 306 334 2572",
    "sg:postcode":"S0G 0C0",
    "sg:province":"SK",
    "sg:tags":[
        "grocer"
    ],
    "wof:name":"L & J Country Foods",
    "wof:placetype":"venue"
},
  "geometry": {"coordinates":[-103.54434967,50.8021316528],"type":"Point"}
}