{
  "type": "Feature",
  "properties": {
    "addr:full":"848 Rue Principale Granby QC J2G 2Z2",
    "addr:housenumber":"848",
    "addr:postcode":"j2g 2z2",
    "addr:street":"Rue Principale",
    "iso:country":"CA",
    "sg:address":"848 Rue Principale",
    "sg:city":"Granby",
    "sg:classifiers":[
        {
            "category":"Shopping",
            "subcategory":"Clothing, Apparel, & Fashions",
            "type":"Retail Goods"
        }
    ],
    "sg:phone":"+1 450 378 1438",
    "sg:postcode":"J2G 2Z2",
    "sg:province":"QC",
    "wof:name":"Reitmans",
    "wof:placetype":"venue"
},
  "geometry": {"coordinates":[-72.75161,45.412907],"type":"Point"}
}