{
  "type": "Feature",
  "properties": {
    "addr:full":"2400 Boul Le Corbusier Laval QC H7S 2H2",
    "addr:housenumber":"2400",
    "addr:postcode":"h7s 2h2",
    "addr:street":"Boul Le Corbusier",
    "iso:country":"CA",
    "sg:address":"2400 Boul Le Corbusier",
    "sg:city":"Laval",
    "sg:classifiers":[
        {
            "category":"Professional",
            "subcategory":"Business Services",
            "type":"Services"
        }
    ],
    "sg:phone":"+1 450 687 4151",
    "sg:postcode":"H7S 2H2",
    "sg:province":"QC",
    "sg:tags":[
        "interior",
        "consultant",
        "design",
        "decorator"
    ],
    "wof:name":"Vaillancourt Associes Designer",
    "wof:placetype":"venue"
},
  "geometry": {"coordinates":[-73.741653,45.572666],"type":"Point"}
}