{
  "type": "Feature",
  "properties": {
    "addr:full":"355 Hartman Rd Kelowna BC V1X 2M9",
    "addr:housenumber":"355",
    "addr:postcode":"v1x 2m9",
    "addr:street":"Hartman Rd",
    "iso:country":"CA",
    "sg:address":"355 Hartman Rd",
    "sg:city":"Kelowna",
    "sg:classifiers":[
        {
            "category":"Social Services",
            "subcategory":"Child Care",
            "type":"Services"
        }
    ],
    "sg:phone":"+1 250 765 2223",
    "sg:postcode":"V1X 2M9",
    "sg:province":"BC",
    "wof:name":"Rutland Day Care Ctr",
    "wof:placetype":"venue"
},
  "geometry": {"coordinates":[-119.38137054400001,49.8997917175],"type":"Point"}
}