{
  "type": "Feature",
  "properties": {
    "addr:full":"Big River SK S0J 0E0",
    "addr:postcode":"s0j 0e0",
    "addr:street":"Big River",
    "iso:country":"CA",
    "sg:city":"Big River",
    "sg:classifiers":[
        {
            "category":"Travel",
            "subcategory":"Hotels & Motels",
            "type":"Entertainment"
        }
    ],
    "sg:phone":"+1 306 469 4462",
    "sg:postcode":"S0J 0E0",
    "sg:province":"SK",
    "sg:tags":[
        "resort"
    ],
    "wof:name":"Delaronde Resort",
    "wof:placetype":"venue"
},
  "geometry": {"coordinates":[-107.031936645,53.8341331482],"type":"Point"}
}