{
  "type": "Feature",
  "properties": {
    "addr:full":"25 Good Shepherd Crt North York ON M6B 4E7",
    "addr:housenumber":"25",
    "addr:postcode":"m6b 4e7",
    "addr:street":"Good Shepherd Crt",
    "iso:country":"CA",
    "sg:address":"25 Good Shepherd Crt",
    "sg:city":"North York",
    "sg:classifiers":[
        {
            "category":"Organizations",
            "subcategory":"Religious Organization",
            "type":"Services"
        }
    ],
    "sg:phone":"+1 416 787 4285",
    "sg:postcode":"M6B 4E7",
    "sg:province":"ON",
    "wof:name":"Sisters of the Good Shepherd",
    "wof:placetype":"venue"
},
  "geometry": {"coordinates":[-79.458023,43.712624],"type":"Point"}
}