{
  "type": "Feature",
  "properties": {
    "addr:full":"Green Island Cove NL A0K 2W0",
    "addr:postcode":"a0k 2w0",
    "addr:street":"Island",
    "iso:country":"CA",
    "sg:city":"Green Island Cove",
    "sg:classifiers":[
        {
            "category":"Organizations",
            "subcategory":"Professional Association",
            "type":"Services"
        }
    ],
    "sg:phone":"+1 709 475 4166",
    "sg:postcode":"A0K 2W0",
    "sg:province":"NL",
    "sg:tags":[
        "club"
    ],
    "wof:name":"Green Island Cove Lions Club",
    "wof:placetype":"venue"
},
  "geometry": {"coordinates":[-56.5781364441,51.3813285828],"type":"Point"}
}