{
  "type": "Feature",
  "properties": {
    "addr:full":"Charlesbourg QC G1G 5L7",
    "addr:postcode":"g1g 5l7",
    "iso:country":"CA",
    "sg:city":"Charlesbourg",
    "sg:classifiers":[
        {
            "category":"Wholesale",
            "subcategory":"Electrical",
            "type":"Manufacturing & Wholesale Goods"
        }
    ],
    "sg:phone":"+1 418 624 3055",
    "sg:postcode":"G1G 5L7",
    "sg:province":"QC",
    "sg:tags":[
        "equipment",
        "system",
        "business"
    ],
    "wof:name":"Louise Poitras Enr",
    "wof:placetype":"venue"
},
  "geometry": {"coordinates":[-71.28270000000001,46.855736],"type":"Point"}
}