{
  "type": "Feature",
  "properties": {
    "iso:country":"CA",
    "sg:address":"425 Attwell Dr",
    "sg:city":"Etobicoke",
    "sg:classifiers":[
        {
            "category":"Shopping",
            "subcategory":"Photographic Equipment",
            "type":"Retail Goods"
        }
    ],
    "sg:phone":"+1 416 745 2622",
    "sg:postcode":"M9W 5C4",
    "sg:province":"ON",
    "sg:tags":[
        "supply"
    ],
    "wof:name":"Nadel Enterprises Inc",
    "wof:placetype":"venue"
},
  "geometry": {"coordinates":[-79.6050109863,43.7031364441],"type":"Point"}
}