{
  "type": "Feature",
  "properties": {
    "addr:full":"784 Bank St Ottawa ON K1S 3V6",
    "addr:housenumber":"784",
    "addr:postcode":"k1s 3v6",
    "addr:street":"Bank St",
    "iso:country":"CA",
    "sg:address":"784 Bank St",
    "sg:city":"Ottawa",
    "sg:classifiers":[
        {
            "category":"Personal",
            "subcategory":"Beauty Salon",
            "type":"Services"
        }
    ],
    "sg:phone":"+1 613 235 7722",
    "sg:postcode":"K1S 3V6",
    "sg:province":"ON",
    "sg:tags":[
        "spa",
        "day"
    ],
    "wof:name":"Third Avenue Spa",
    "wof:placetype":"venue"
},
  "geometry": {"coordinates":[-75.68862900000001,45.403164],"type":"Point"}
}