{
  "type": "Feature",
  "properties": {
    "addr:full":"15 Easton St Cambridge ON N1R 1G3",
    "addr:housenumber":"15",
    "addr:postcode":"n1r 1g3",
    "addr:street":"Easton St",
    "iso:country":"CA",
    "sg:address":"15 Easton St",
    "sg:city":"Cambridge",
    "sg:classifiers":[
        {
            "category":"Wholesale",
            "subcategory":"Auto Parts",
            "type":"Manufacturing & Wholesale Goods"
        }
    ],
    "sg:phone":"+1 519 621 7311",
    "sg:postcode":"N1R 1G3",
    "sg:province":"ON",
    "sg:tags":[
        "body",
        "automobile",
        "shop",
        "supply"
    ],
    "wof:name":"Golden Mile Automotive",
    "wof:placetype":"venue"
},
  "geometry": {"coordinates":[-80.316704,43.372536],"type":"Point"}
}