{
  "type": "Feature",
  "properties": {
    "addr:full":"Dundas ON L9H 1W8",
    "addr:postcode":"l9h 1w8",
    "iso:country":"CA",
    "sg:city":"Dundas",
    "sg:classifiers":[
        {
            "category":"Building & Trades",
            "subcategory":"Plumbing",
            "type":"Services"
        }
    ],
    "sg:phone":"+1 905 628 1201",
    "sg:postcode":"L9H 1W8",
    "sg:province":"ON",
    "sg:tags":[
        "conditioning",
        "air",
        "system",
        "contractor"
    ],
    "wof:name":"Wilson Air",
    "wof:placetype":"venue"
},
  "geometry": {"coordinates":[-79.970032,43.271374],"type":"Point"}
}