{
  "type": "Feature",
  "properties": {
    "addr:full":"668 South Railway St SE Medicine Hat AB T1A 2V9",
    "addr:housenumber":"668",
    "addr:postcode":"t1a 2v9",
    "addr:street":"South Railway St Se",
    "iso:country":"CA",
    "sg:address":"668 South Railway St SE",
    "sg:city":"Medicine Hat",
    "sg:classifiers":[
        {
            "category":"Building & Trades",
            "subcategory":"Construction",
            "type":"Services"
        }
    ],
    "sg:phone":"+1 403 527 2888",
    "sg:postcode":"T1A 2V9",
    "sg:province":"AB",
    "sg:tags":[
        "insulation",
        "heat",
        "contractor"
    ],
    "wof:name":"Jack's Mechanical Insulation",
    "wof:placetype":"venue"
},
  "geometry": {"coordinates":[-110.66742706300001,50.033203125],"type":"Point"}
}