{
  "type": "Feature",
  "properties": {
    "iso:country":"CA",
    "sg:address":"1325 Cariboo Hwy N",
    "sg:city":"Quesnel",
    "sg:classifiers":[
        {
            "category":"Restaurant",
            "type":"Food & Drink"
        }
    ],
    "sg:phone":"+1 250 992 2239",
    "sg:postcode":"V2J 2Y5",
    "sg:province":"BC",
    "wof:name":"Quesnel Drive-In Restaurant",
    "wof:placetype":"venue"
},
  "geometry": {"coordinates":[-122.50690460200001,52.9940452576],"type":"Point"}
}