{
  "type": "Feature",
  "properties": {
    "addr:full":"4241 Boul Industriel Montreal-Nord QC H1H 2Z4",
    "addr:housenumber":"4241",
    "addr:postcode":"h1h 2z4",
    "addr:street":"Boul Industriel",
    "iso:country":"CA",
    "sg:address":"4241 Boul Industriel",
    "sg:city":"Montreal-Nord",
    "sg:classifiers":[
        {
            "category":"Wholesale",
            "subcategory":"Apparel",
            "type":"Manufacturing & Wholesale Goods"
        }
    ],
    "sg:phone":"+1 514 326 9897",
    "sg:postcode":"H1H 2Z4",
    "sg:province":"QC",
    "sg:tags":[
        "skating",
        "equipment",
        "supply"
    ],
    "wof:name":"Explosion Sports",
    "wof:placetype":"venue"
},
  "geometry": {"coordinates":[-73.6285476685,45.5857887268],"type":"Point"}
}