{
  "type": "Feature",
  "properties": {
    "addr:full":"3636 4th Ave E Vancouver BC V5M 1M3",
    "addr:housenumber":"3636",
    "addr:postcode":"v5m 1m3",
    "addr:street":"4Th Ave E",
    "iso:country":"CA",
    "sg:address":"3636 4th Ave E",
    "sg:city":"Vancouver",
    "sg:classifiers":[
        {
            "category":"Organizations",
            "subcategory":"Professional Association",
            "type":"Services"
        }
    ],
    "sg:phone":"+1 604 294 3766",
    "sg:postcode":"V5M 1M3",
    "sg:province":"BC",
    "wof:name":"Vancouver Regional Constr Assn",
    "wof:placetype":"venue"
},
  "geometry": {"coordinates":[-123.024956,49.266472],"type":"Point"}
}