{
  "type": "Feature",
  "properties": {
    "addr:full":"22 Glendale Ave Lower Sackville NS B4C 3M1",
    "addr:housenumber":"22",
    "addr:postcode":"b4c 3m1",
    "addr:street":"Glendale Ave",
    "iso:country":"CA",
    "sg:address":"22 Glendale Ave",
    "sg:city":"Lower Sackville",
    "sg:phone":"+1 902 864 1200",
    "sg:postcode":"B4C 3M1",
    "sg:province":"NS",
    "sg:tags":[
        "lubricant"
    ],
    "wof:name":"Glen Beigh Distribution Inc",
    "wof:placetype":"venue"
},
  "geometry": {"coordinates":[-63.658073,44.759113],"type":"Point"}
}