{
  "type": "Feature",
  "properties": {
    "addr:full":"3250 Commercial Dr Vancouver BC V5N 4E4",
    "addr:housenumber":"3250",
    "addr:postcode":"v5n 4e4",
    "addr:street":"Commercial Dr",
    "iso:country":"CA",
    "sg:address":"3250 Commercial Dr",
    "sg:city":"Vancouver",
    "sg:classifiers":[
        {
            "category":"Recreation",
            "type":"Entertainment"
        }
    ],
    "sg:phone":"+1 604 879 0154",
    "sg:postcode":"V5N 4E4",
    "sg:province":"BC",
    "sg:tags":[
        "auditorium",
        "rooms",
        "banquet",
        "hall"
    ],
    "wof:name":"Croatian Cultural Ctr",
    "wof:placetype":"venue"
},
  "geometry": {"coordinates":[-123.06925200000001,49.255692],"type":"Point"}
}