{
  "type": "Feature",
  "properties": {
    "addr:full":"PO Box 79 Hay Lakes AB T0B 1W0",
    "addr:housenumber":"po box 79",
    "addr:postcode":"t0b 1w0",
    "iso:country":"CA",
    "sg:address":"PO Box 79",
    "sg:city":"Hay Lakes",
    "sg:classifiers":[
        {
            "category":"Building & Trades",
            "subcategory":"Construction",
            "type":"Services"
        }
    ],
    "sg:phone":"+1 780 878 3969",
    "sg:postcode":"T0B 1W0",
    "sg:province":"AB",
    "sg:tags":[
        "general",
        "contractor"
    ],
    "wof:name":"Melsell Maintenance Ltd",
    "wof:placetype":"venue"
},
  "geometry": {"coordinates":[-113.056915283,53.1971244812],"type":"Point"}
}