{
  "type": "Feature",
  "properties": {
    "addr:full":"1301 Jackson Sideroad Hwy 3 E Tillsonburg ON N4G 4H3",
    "addr:housenumber":"1301",
    "addr:postcode":"n4g 4h3",
    "addr:street":"Jackson Sideroad Hwy 3 E",
    "iso:country":"CA",
    "sg:address":"1301 Jackson Sideroad Hwy 3 E",
    "sg:city":"Tillsonburg",
    "sg:classifiers":[
        {
            "category":"Manufacturing",
            "subcategory":"Tools & Machinery",
            "type":"Manufacturing & Wholesale Goods"
        }
    ],
    "sg:phone":"+1 519 842 7361",
    "sg:postcode":"N4G 4H3",
    "sg:province":"ON",
    "sg:tags":[
        "tobacco",
        "supply"
    ],
    "wof:name":"DE Cloet Ltd",
    "wof:placetype":"venue"
},
  "geometry": {"coordinates":[-80.727867,42.860676],"type":"Point"}
}