{
  "type": "Feature",
  "properties": {
    "addr:full":"6305 Av Macdonald Montreal QC H3X 2X3",
    "addr:housenumber":"6305",
    "addr:postcode":"h3x 2x3",
    "addr:street":"Av Macdonald",
    "iso:country":"CA",
    "sg:address":"6305 Av Macdonald",
    "sg:city":"Montreal",
    "sg:classifiers":[
        {
            "category":"Building & Trades",
            "subcategory":"Cleaning & Sanitation",
            "type":"Services"
        }
    ],
    "sg:phone":"+1 514 937 4062",
    "sg:postcode":"H3X 2X3",
    "sg:province":"QC",
    "sg:tags":[
        "snow",
        "removal"
    ],
    "wof:name":"Bdc",
    "wof:placetype":"venue"
},
  "geometry": {"coordinates":[-73.64619399999999,45.486916],"type":"Point"}
}