{
  "type": "Feature",
  "properties": {
    "addr:full":"10 Jill Crt Markham ON L3P 3R9",
    "addr:housenumber":"10",
    "addr:postcode":"l3p 3r9",
    "addr:street":"Jill Crt",
    "iso:country":"CA",
    "sg:address":"10 Jill Crt",
    "sg:city":"Markham",
    "sg:classifiers":[
        {
            "category":"Professional",
            "subcategory":"Computer Services",
            "type":"Services"
        }
    ],
    "sg:phone":"+1 905 201 8405",
    "sg:postcode":"L3P 3R9",
    "sg:province":"ON",
    "sg:tags":[
        "consultant"
    ],
    "wof:name":"Reedy Creek Consulting Inc",
    "wof:placetype":"venue"
},
  "geometry": {"coordinates":[-79.2456436157,43.881729126],"type":"Point"}
}