{
  "type": "Feature",
  "properties": {
    "addr:full":"RR 1 Alma ON N0B 1A0",
    "addr:postcode":"n0b 1a0",
    "addr:street":"Rr 1",
    "iso:country":"CA",
    "sg:address":"RR 1",
    "sg:city":"Alma",
    "sg:classifiers":[
        {
            "category":"Building & Trades",
            "subcategory":"Landscaping Services",
            "type":"Services"
        }
    ],
    "sg:phone":"+1 519 846 8039",
    "sg:postcode":"N0B 1A0",
    "sg:province":"ON",
    "sg:tags":[
        "tree"
    ],
    "wof:name":"Klt Tree Svc",
    "wof:placetype":"venue"
},
  "geometry": {"coordinates":[-80.5027008057,43.7297935486],"type":"Point"}
}