{
  "type": "Feature",
  "properties": {
    "iso:country":"CA",
    "sg:address":"251 Georgia St E",
    "sg:city":"Vancouver",
    "sg:classifiers":[
        {
            "category":"Food & Beverages",
            "subcategory":"Bakery",
            "type":"Retail Goods"
        }
    ],
    "sg:phone":"+1 604 685 2117",
    "sg:postcode":"V6A 1Z6",
    "sg:province":"BC",
    "sg:tags":[
        "baker"
    ],
    "wof:name":"Keefer Chinese Bakery",
    "wof:placetype":"venue"
},
  "geometry": {"coordinates":[-123.09833526600001,49.2786521912],"type":"Point"}
}