{
  "type": "Feature",
  "properties": {
    "iso:country":"CA",
    "sg:address":"95 Indian Rd S",
    "sg:city":"Sarnia",
    "sg:classifiers":[
        {
            "category":"Autos & Motor Vehicles",
            "subcategory":"Automobile Sales",
            "type":"Retail Goods"
        }
    ],
    "sg:phone":"+1 519 464 4022",
    "sg:postcode":"N7T 3W1",
    "sg:province":"ON",
    "sg:tags":[
        "car",
        "dealer"
    ],
    "wof:name":"Lambton Kia",
    "wof:placetype":"venue"
},
  "geometry": {"coordinates":[-82.37646484379999,42.9593696594],"type":"Point"}
}