{
  "type": "Feature",
  "properties": {
    "addr:full":"75 Main St E Ridgetown ON N0P 2C0",
    "addr:housenumber":"75",
    "addr:postcode":"n0p 2c0",
    "addr:street":"Main St E",
    "iso:country":"CA",
    "sg:address":"75 Main St E",
    "sg:city":"Ridgetown",
    "sg:classifiers":[
        {
            "category":"Organizations",
            "subcategory":"Professional Association",
            "type":"Services"
        }
    ],
    "sg:phone":"+1 519 674 3421",
    "sg:postcode":"N0P 2C0",
    "sg:province":"ON",
    "wof:name":"Royal Canadian Legion",
    "wof:placetype":"venue"
},
  "geometry": {"coordinates":[-81.8834991455,42.4415206909],"type":"Point"}
}