{
  "type": "Feature",
  "properties": {
    "iso:country":"CA",
    "sg:address":"33 Cork St W",
    "sg:city":"Guelph",
    "sg:classifiers":[
        {
            "category":"Health Services",
            "subcategory":"Doctor",
            "type":"Services"
        }
    ],
    "sg:phone":"+1 519 836 2420",
    "sg:postcode":"N1H 2W9",
    "sg:province":"ON",
    "sg:tags":[
        "dentist"
    ],
    "wof:name":"Cremasco, Steven F DDS",
    "wof:placetype":"venue"
},
  "geometry": {"coordinates":[-80.252456665,43.5437355042],"type":"Point"}
}