{
  "type": "Feature",
  "properties": {
    "iso:country":"CA",
    "sg:city":"Wapella",
    "sg:classifiers":[
        {
            "category":"Wholesale",
            "subcategory":"Farm Supplies",
            "type":"Manufacturing & Wholesale Goods"
        }
    ],
    "sg:phone":"+1 306 532 4372",
    "sg:postcode":"S0G 4Z0",
    "sg:province":"SK",
    "sg:tags":[
        "fertilizer"
    ],
    "wof:name":"Sharpe's Soil Svc Ltd",
    "wof:placetype":"venue"
},
  "geometry": {"coordinates":[-101.969985962,50.2609634399],"type":"Point"}
}