{
  "type": "Feature",
  "properties": {
    "addr:full":"Richmond Hill ON L4B 1J9",
    "addr:postcode":"l4b 1j9",
    "iso:country":"CA",
    "sg:city":"Richmond Hill",
    "sg:classifiers":[
        {
            "category":"Professional",
            "subcategory":"Computer Services",
            "type":"Services"
        }
    ],
    "sg:phone":"+1 905 738 0967",
    "sg:postcode":"L4B 1J9",
    "sg:province":"ON",
    "sg:tags":[
        "consultant"
    ],
    "wof:name":"M & M Computer Consultants Ltd",
    "wof:placetype":"venue"
},
  "geometry": {"coordinates":[-79.39228057859999,43.8506546021],"type":"Point"}
}