{
  "type": "Feature",
  "properties": {
    "iso:country":"CA",
    "sg:city":"Courtenay",
    "sg:classifiers":[
        {
            "category":"Building & Trades",
            "subcategory":"Construction",
            "type":"Services"
        }
    ],
    "sg:phone":"+1 250 334 8866",
    "sg:postcode":"V9N 9E7",
    "sg:province":"BC",
    "sg:tags":[
        "excavating",
        "contractor"
    ],
    "wof:name":"J R Edgett Excavating Ltd",
    "wof:placetype":"venue"
},
  "geometry": {"coordinates":[-124.969642639,49.7152442932],"type":"Point"}
}