{
  "type": "Feature",
  "properties": {
    "addr:full":"1568 Rue Baillargeon Saint-Luc QC J2W 2B4",
    "addr:housenumber":"1568",
    "addr:postcode":"j2w 2b4",
    "addr:street":"Rue Baillargeon",
    "iso:country":"CA",
    "sg:address":"1568 Rue Baillargeon",
    "sg:city":"Saint-Luc",
    "sg:classifiers":[
        {
            "category":"Bars & Pubs",
            "type":"Food & Drink"
        }
    ],
    "sg:phone":"+1 450 359 7740",
    "sg:postcode":"J2W 2B4",
    "sg:province":"QC",
    "sg:tags":[
        "lounge",
        "cocktail"
    ],
    "wof:name":"Bar Terrasse DE L'Ile",
    "wof:placetype":"venue"
},
  "geometry": {"coordinates":[-73.25464599999999,45.374943],"type":"Point"}
}