{
  "type": "Feature",
  "properties": {
    "iso:country":"CA",
    "sg:address":"752 9th St E",
    "sg:city":"Owen Sound",
    "sg:classifiers":[
        {
            "category":"Retail",
            "subcategory":"Repair Shop",
            "type":"Services"
        }
    ],
    "sg:phone":"+1 519 372 2184",
    "sg:postcode":"N4K 1R1",
    "sg:province":"ON",
    "sg:tags":[
        "sharpening",
        "skate",
        "golf",
        "equipment"
    ],
    "wof:name":"Surridge's Golf Club Repair",
    "wof:placetype":"venue"
},
  "geometry": {"coordinates":[-80.9313201904,44.5672531128],"type":"Point"}
}