{
  "type": "Feature",
  "properties": {
    "addr:full":"27173 Fraser Hwy Aldergrove BC V4W 3R1",
    "addr:housenumber":"27173",
    "addr:postcode":"v4w 3r1",
    "addr:street":"Fraser Hwy",
    "iso:country":"CA",
    "sg:address":"27173 Fraser Hwy",
    "sg:city":"Aldergrove",
    "sg:classifiers":[
        {
            "category":"Autos & Motor Vehicles",
            "subcategory":"Automobile Sales",
            "type":"Retail Goods"
        }
    ],
    "sg:phone":"+1 604 607 6606",
    "sg:postcode":"V4W 3R1",
    "sg:province":"BC",
    "sg:tags":[
        "car",
        "second",
        "store",
        "hand"
    ],
    "wof:name":"Usable Shop",
    "wof:placetype":"venue"
},
  "geometry": {"coordinates":[-122.4713974,49.0582504272],"type":"Point"}
}