{
  "type": "Feature",
  "properties": {
    "addr:full":"2589 Kingsway Vancouver BC V5R 5H3",
    "addr:housenumber":"2589",
    "addr:postcode":"v5r 5h3",
    "addr:street":"Kingsway",
    "iso:country":"CA",
    "sg:address":"2589 Kingsway",
    "sg:city":"Vancouver",
    "sg:classifiers":[
        {
            "category":"Wholesale",
            "subcategory":"Machinery & Supplies",
            "type":"Manufacturing & Wholesale Goods"
        }
    ],
    "sg:phone":"+1 604 609 0112",
    "sg:postcode":"V5R 5H3",
    "sg:province":"BC",
    "sg:tags":[
        "salon",
        "beauty"
    ],
    "wof:name":"Superior Beauty Supls & Equip",
    "wof:placetype":"venue"
},
  "geometry": {"coordinates":[-123.05274963399999,49.2395706177],"type":"Point"}
}