{
  "type": "Feature",
  "properties": {
    "addr:full":"3848 Ellesmere Rd Scarborough ON M1C 1J1",
    "addr:housenumber":"3848",
    "addr:postcode":"m1c 1j1",
    "addr:street":"Ellesmere Rd",
    "iso:country":"CA",
    "sg:address":"3848 Ellesmere Rd",
    "sg:city":"Scarborough",
    "sg:classifiers":[
        {
            "category":"Banks & Credit Unions",
            "subcategory":"Bank",
            "type":"Services"
        }
    ],
    "sg:phone":"+1 416 284 1900",
    "sg:postcode":"M1C 1J1",
    "sg:province":"ON",
    "sg:tags":[
        "financing"
    ],
    "wof:name":"Onestop Dealer Svc",
    "wof:placetype":"venue"
},
  "geometry": {"coordinates":[-79.1650543213,43.7922592163],"type":"Point"}
}