{
  "type": "Feature",
  "properties": {
    "iso:country":"CA",
    "sg:address":"1242 Ch Saint-Henri",
    "sg:city":"Mascouche",
    "sg:classifiers":[
        {
            "category":"Retail",
            "subcategory":"Auto Repair",
            "type":"Services"
        }
    ],
    "sg:phone":"+1 450 474 2027",
    "sg:postcode":"J7K 2N1",
    "sg:province":"QC",
    "sg:tags":[
        "repairing",
        "automobile"
    ],
    "wof:name":"Garage Gr Houle",
    "wof:placetype":"venue"
},
  "geometry": {"coordinates":[-73.598739624,45.7520256042],"type":"Point"}
}