{
  "type": "Feature",
  "properties": {
    "addr:full":"3919 106 St NW Edmonton AB T6J 2S3",
    "addr:housenumber":"3919",
    "addr:postcode":"t6j 2s3",
    "addr:street":"106 St Nw",
    "iso:country":"CA",
    "sg:address":"3919 106 St NW",
    "sg:city":"Edmonton",
    "sg:classifiers":[
        {
            "category":"Education",
            "subcategory":"Special Training",
            "type":"Public Place"
        }
    ],
    "sg:phone":"+1 780 434 3807",
    "sg:postcode":"T6J 2S3",
    "sg:province":"AB",
    "sg:tags":[
        "instruction",
        "music"
    ],
    "wof:name":"Heritage Music & School",
    "wof:placetype":"venue"
},
  "geometry": {"coordinates":[-113.50488300000001,53.474636],"type":"Point"}
}