{
  "type": "Feature",
  "properties": {
    "addr:full":"457 Ch Du Lac-Mercier Mont-Tremblant QC J8E 1K7",
    "addr:housenumber":"457",
    "addr:postcode":"j8e 1k7",
    "addr:street":"Ch Du Lac-Mercier",
    "iso:country":"CA",
    "sg:address":"457 Ch Du Lac-Mercier",
    "sg:city":"Mont-Tremblant",
    "sg:classifiers":[
        {
            "category":"Professional",
            "subcategory":"Engineering",
            "type":"Services"
        }
    ],
    "sg:phone":"+1 819 425 3848",
    "sg:postcode":"J8E 1K7",
    "sg:province":"QC",
    "sg:tags":[
        "engineer"
    ],
    "wof:name":"Laliberte, Luc PE",
    "wof:placetype":"venue"
},
  "geometry": {"coordinates":[-74.65450300000001,46.200817],"type":"Point"}
}