{
  "type": "Feature",
  "properties": {
    "addr:full":"2060 Richmond Arva ON N0M 1C0",
    "addr:housenumber":"2060",
    "addr:postcode":"n0m 1c0",
    "addr:street":"Richmond",
    "iso:country":"CA",
    "sg:address":"2060 Richmond",
    "sg:city":"Arva",
    "sg:classifiers":[
        {
            "category":"Manufacturing",
            "subcategory":"Pet Food",
            "type":"Manufacturing & Wholesale Goods"
        }
    ],
    "sg:phone":"+1 519 660 0199",
    "sg:postcode":"N0M 1C0",
    "sg:province":"ON",
    "sg:tags":[
        "flour",
        "mills"
    ],
    "wof:name":"Arva Flour Mills Ltd",
    "wof:placetype":"venue"
},
  "geometry": {"coordinates":[-81.29186199999999,43.044392],"type":"Point"}
}