{
  "type": "Feature",
  "properties": {
    "addr:full":"PO Box 274 STN Main Bradford ON L3Z 2A8",
    "addr:housenumber":"po",
    "addr:postcode":"l3z 2a8",
    "addr:street":"Box 274 Stn Main",
    "iso:country":"CA",
    "sg:address":"PO Box 274 STN Main",
    "sg:city":"Bradford",
    "sg:classifiers":[
        {
            "category":"Building & Trades",
            "subcategory":"Landscaping Services",
            "type":"Services"
        }
    ],
    "sg:phone":"+1 905 775 0618",
    "sg:postcode":"L3Z 2A8",
    "sg:province":"ON",
    "sg:tags":[
        "lawn",
        "maintenance",
        "grounds"
    ],
    "wof:name":"Apex Property Svc",
    "wof:placetype":"venue"
},
  "geometry": {"coordinates":[-79.56366,44.114552],"type":"Point"}
}