{
  "type": "Feature",
  "properties": {
    "addr:full":"3166 Cole Rd Queensville ON L0G 1R0",
    "addr:housenumber":"3166",
    "addr:postcode":"l0g 1r0",
    "addr:street":"Cole Rd",
    "iso:country":"CA",
    "sg:address":"3166 Cole Rd",
    "sg:city":"Queensville",
    "sg:classifiers":[
        {
            "category":"Manufacturing",
            "subcategory":"Metals",
            "type":"Manufacturing & Wholesale Goods"
        }
    ],
    "sg:phone":"+1 905 478 2276",
    "sg:postcode":"L0G 1R0",
    "sg:province":"ON",
    "sg:tags":[
        "door"
    ],
    "wof:name":"A & M Aluminum",
    "wof:placetype":"venue"
},
  "geometry": {"coordinates":[-79.4500656128,44.1368103027],"type":"Point"}
}