{
  "type": "Feature",
  "properties": {
    "addr:full":"5315 Boul Des Forges Trois-Rivieres QC G8Y 5L5",
    "addr:housenumber":"5315",
    "addr:postcode":"g8y 5l5",
    "addr:street":"Boul Des Forges Trois-Rivieres",
    "iso:country":"CA",
    "sg:address":"5315 Boul Des Forges",
    "sg:city":"Trois-Rivieres",
    "sg:classifiers":[
        {
            "category":"Personal",
            "subcategory":"Beauty Salon",
            "type":"Services"
        }
    ],
    "sg:phone":"+1 819 691 2172",
    "sg:postcode":"G8Y 5L5",
    "sg:province":"QC",
    "wof:name":"Coiffure Arlequin Inc",
    "wof:placetype":"venue"
},
  "geometry": {"coordinates":[-72.5949935913,46.3628845215],"type":"Point"}
}