{
  "type": "Feature",
  "properties": {
    "addr:full":"9 Ch Cambria Gore QC J0V 1K0",
    "addr:housenumber":"9",
    "addr:postcode":"j0v 1k0",
    "addr:street":"Ch Cambria",
    "iso:country":"CA",
    "sg:address":"9 Ch Cambria",
    "sg:city":"Gore",
    "sg:classifiers":[
        {
            "category":"Government",
            "subcategory":"Office",
            "type":"Public Place"
        }
    ],
    "sg:phone":"+1 450 562 2025",
    "sg:postcode":"J0V 1K0",
    "sg:province":"QC",
    "sg:tags":[
        "village"
    ],
    "wof:name":"Gore Municipalite Office",
    "wof:placetype":"venue"
},
  "geometry": {"coordinates":[-74.3149261475,45.7643356323],"type":"Point"}
}