{
  "type": "Feature",
  "properties": {
    "addr:full":"1300 Main St Stittsville ON K2S 1A3",
    "addr:housenumber":"1300",
    "addr:postcode":"k2s 1a3",
    "addr:street":"Main St",
    "iso:country":"CA",
    "sg:address":"1300 Main St",
    "sg:city":"Stittsville",
    "sg:classifiers":[
        {
            "category":"Restaurant",
            "type":"Food & Drink"
        }
    ],
    "sg:phone":"+1 613 836 7722",
    "sg:postcode":"K2S 1A3",
    "sg:province":"ON",
    "wof:name":"Napoli's Cafe & Grill",
    "wof:placetype":"venue"
},
  "geometry": {"coordinates":[-75.927216,45.263855],"type":"Point"}
}