{
  "type": "Feature",
  "properties": {
    "addr:full":"1557 Hastings Cres SE Calgary AB T2G 4C8",
    "addr:housenumber":"1557",
    "addr:postcode":"t2g 4c8",
    "addr:street":"Hastings Cres Se",
    "iso:country":"CA",
    "sg:address":"1557 Hastings Cres SE",
    "sg:city":"Calgary",
    "sg:classifiers":[
        {
            "category":"Manufacturing",
            "subcategory":"Tools & Machinery",
            "type":"Manufacturing & Wholesale Goods"
        }
    ],
    "sg:phone":"+1 403 287 3988",
    "sg:postcode":"T2G 4C8",
    "sg:province":"AB",
    "sg:tags":[
        "equipment",
        "nurseryman",
        "greenhouse",
        "supply"
    ],
    "wof:name":"Westgro Horticultural Supplies",
    "wof:placetype":"venue"
},
  "geometry": {"coordinates":[-114.031387,51.01516],"type":"Point"}
}