{
  "type": "Feature",
  "properties": {
    "addr:full":"2474 Champlain Rd Clarence Creek ON K0A 1N0",
    "addr:housenumber":"2474",
    "addr:postcode":"k0a 1n0",
    "addr:street":"Champlain Rd",
    "iso:country":"CA",
    "sg:address":"2474 Champlain Rd",
    "sg:city":"Clarence Creek",
    "sg:classifiers":[
        {
            "category":"Organizations",
            "subcategory":"Professional Association",
            "type":"Services"
        }
    ],
    "sg:phone":"+1 613 488 2929",
    "sg:postcode":"K0A 1N0",
    "sg:province":"ON",
    "wof:name":"Union Des Cultivateurs Franco",
    "wof:placetype":"venue"
},
  "geometry": {"coordinates":[-75.1883926392,45.485660553],"type":"Point"}
}