{
  "type": "Feature",
  "properties": {
    "iso:country":"CA",
    "sg:address":"313 Division St",
    "sg:city":"Cobourg",
    "sg:classifiers":[
        {
            "category":"Manufacturing",
            "subcategory":"Tools & Machinery",
            "type":"Manufacturing & Wholesale Goods"
        }
    ],
    "sg:phone":"+1 905 372 5479",
    "sg:postcode":"K9A 3R4",
    "sg:province":"ON",
    "sg:tags":[
        "plumbing",
        "purifying",
        "contractor",
        "cleaning",
        "air"
    ],
    "wof:name":"K S Cooper Ltd",
    "wof:placetype":"venue"
},
  "geometry": {"coordinates":[-78.1665802002,43.9619827271],"type":"Point"}
}