{
  "type": "Feature",
  "properties": {
    "addr:full":"3330 Hospital Dr NW Calgary AB T2N 4N1",
    "addr:housenumber":"3330",
    "addr:postcode":"t2n 4n1",
    "addr:street":"Hospital Dr Nw",
    "iso:country":"CA",
    "sg:address":"3330 Hospital Dr NW",
    "sg:city":"Calgary",
    "sg:classifiers":[
        {
            "category":"Health Services",
            "subcategory":"Doctor",
            "type":"Services"
        }
    ],
    "sg:phone":"+1 403 220 5951",
    "sg:postcode":"T2N 4N1",
    "sg:province":"AB",
    "sg:tags":[
        "physician",
        "surgeon"
    ],
    "wof:name":"Rabin, Harvey R MD",
    "wof:placetype":"venue"
},
  "geometry": {"coordinates":[-114.132988,51.066788],"type":"Point"}
}