{
  "type": "Feature",
  "properties": {
    "iso:country":"CA",
    "sg:city":"Calgary",
    "sg:classifiers":[
        {
            "category":"Professional",
            "subcategory":"Engineering",
            "type":"Services"
        }
    ],
    "sg:phone":"+1 403 995 9566",
    "sg:postcode":"T2H 0G3",
    "sg:province":"AB",
    "sg:tags":[
        "engineer"
    ],
    "wof:name":"Genesis Engineering",
    "wof:placetype":"venue"
},
  "geometry": {"coordinates":[-114.06739,51.001015],"type":"Point"}
}