{
  "type": "Feature",
  "properties": {
    "addr:full":"900 Water St Peterborough ON K9H 3P3",
    "addr:housenumber":"900",
    "addr:postcode":"k9h 3p3",
    "addr:street":"Water St",
    "iso:country":"CA",
    "sg:address":"900 Water St",
    "sg:city":"Peterborough",
    "sg:classifiers":[
        {
            "category":"Manufacturing",
            "subcategory":"Rubber & Plastics",
            "type":"Manufacturing & Wholesale Goods"
        }
    ],
    "sg:phone":"+1 705 743 4113",
    "sg:postcode":"K9H 3P3",
    "sg:province":"ON",
    "sg:tags":[
        "mold",
        "maker"
    ],
    "wof:name":"Craaytech Painted Plastics Inc",
    "wof:placetype":"venue"
},
  "geometry": {"coordinates":[-78.315613,44.322392],"type":"Point"}
}