{
  "type": "Feature",
  "properties": {
    "addr:full":"Surrey BC V3W 1A2",
    "addr:postcode":"v3w 1a2",
    "iso:country":"CA",
    "sg:city":"Surrey",
    "sg:classifiers":[
        {
            "category":"Building & Trades",
            "subcategory":"Cleaning & Sanitation",
            "type":"Services"
        }
    ],
    "sg:phone":"+1 604 507 5535",
    "sg:postcode":"V3W 1A2",
    "sg:province":"BC",
    "sg:tags":[
        "janitor"
    ],
    "wof:name":"Eleven Stars Cleaning",
    "wof:placetype":"venue"
},
  "geometry": {"coordinates":[-122.830215454,49.105178833],"type":"Point"}
}