{
  "type": "Feature",
  "properties": {
    "addr:full":"347 Old Airport Rd Yellowknife NT X1A 3T4",
    "addr:housenumber":"347",
    "addr:postcode":"x1a 3t4",
    "addr:street":"Old Airport Rd",
    "iso:country":"CA",
    "sg:address":"347 Old Airport Rd",
    "sg:city":"Yellowknife",
    "sg:classifiers":[
        {
            "category":"Wholesale",
            "subcategory":"Meat",
            "type":"Manufacturing & Wholesale Goods"
        }
    ],
    "sg:phone":"+1 867 873 2364",
    "sg:postcode":"X1A 3T4",
    "sg:province":"NT",
    "sg:tags":[
        "frozen",
        "food",
        "packer"
    ],
    "wof:name":"Northbest Distributors Ltd",
    "wof:placetype":"venue"
},
  "geometry": {"coordinates":[-114.41404,62.464108],"type":"Point"}
}