{
  "type": "Feature",
  "properties": {
    "addr:full":"53 Wilson St W Ancaster ON L9G 1N1",
    "addr:housenumber":"53",
    "addr:postcode":"l9g 1n1",
    "addr:street":"Wilson St W",
    "iso:country":"CA",
    "sg:address":"53 Wilson St W",
    "sg:city":"Ancaster",
    "sg:classifiers":[
        {
            "category":"Home & Garden",
            "subcategory":"Home Furnishings",
            "type":"Retail Goods"
        }
    ],
    "sg:phone":"+1 905 648 8221",
    "sg:postcode":"L9G 1N1",
    "sg:province":"ON",
    "sg:tags":[
        "venetian",
        "cleaners"
    ],
    "wof:name":"Wright's Cleaners",
    "wof:placetype":"venue"
},
  "geometry": {"coordinates":[-79.989532,43.216541],"type":"Point"}
}