{
  "type": "Feature",
  "properties": {
    "addr:full":"1000 6th Ave W Kindersley SK S0L 1S0",
    "addr:housenumber":"1000",
    "addr:postcode":"s0l 1s0",
    "addr:street":"6Th Ave W Kindersley",
    "iso:country":"CA",
    "sg:address":"1000 6th Ave W",
    "sg:city":"Kindersley",
    "sg:classifiers":[
        {
            "category":"Mining & Drilling",
            "type":"Manufacturing & Wholesale Goods"
        }
    ],
    "sg:phone":"+1 306 463 2750",
    "sg:postcode":"S0L 1S0",
    "sg:province":"SK",
    "sg:tags":[
        "company",
        "oil"
    ],
    "wof:name":"Ish Energy Ltd",
    "wof:placetype":"venue"
},
  "geometry": {"coordinates":[-109.17392700000001,51.467667],"type":"Point"}
}