{
  "type": "Feature",
  "properties": {
    "addr:full":"1380 Rue Des Braves L'Ancienne-Lorette QC G2E 2Z1",
    "addr:housenumber":"1380",
    "addr:postcode":"g2e 2z1",
    "addr:street":"Rue Des Braves",
    "iso:country":"CA",
    "sg:address":"1380 Rue Des Braves",
    "sg:city":"L'Ancienne-Lorette",
    "sg:classifiers":[
        {
            "category":"Wholesale",
            "subcategory":"Machinery & Supplies",
            "type":"Manufacturing & Wholesale Goods"
        }
    ],
    "sg:phone":"+1 418 877 6261",
    "sg:postcode":"G2E 2Z1",
    "sg:province":"QC",
    "sg:tags":[
        "car"
    ],
    "wof:name":"Entretien Lave-Auto Quebec",
    "wof:placetype":"venue"
},
  "geometry": {"coordinates":[-71.3519287109,46.7964897156],"type":"Point"}
}