{
  "type": "Feature",
  "properties": {
    "iso:country":"CA",
    "sg:address":"291 Main St",
    "sg:city":"Antigonish",
    "sg:classifiers":[
        {
            "category":"Cinema",
            "subcategory":"Movie Theater",
            "type":"Entertainment"
        }
    ],
    "sg:phone":"+1 902 863 4646",
    "sg:postcode":"B2G 2C3",
    "sg:province":"NS",
    "wof:name":"Capitol Theatre",
    "wof:placetype":"venue"
},
  "geometry": {"coordinates":[-61.99243927,45.6223602295],"type":"Point"}
}