{
  "type": "Feature",
  "properties": {
    "addr:full":"39 Maldon Rd London ON N6G 1W2",
    "addr:housenumber":"39",
    "addr:postcode":"n6g 1w2",
    "addr:street":"Maldon Rd",
    "iso:country":"CA",
    "sg:address":"39 Maldon Rd",
    "sg:city":"London",
    "sg:classifiers":[
        {
            "category":"Professional",
            "subcategory":"Computer Services",
            "type":"Services"
        }
    ],
    "sg:phone":"+1 519 473 5757",
    "sg:postcode":"N6G 1W2",
    "sg:province":"ON",
    "sg:tags":[
        "consultant"
    ],
    "wof:name":"Encompass Solutions",
    "wof:placetype":"venue"
},
  "geometry": {"coordinates":[-81.29763800000001,43.000057],"type":"Point"}
}