{
  "type": "Feature",
  "properties": {
    "iso:country":"CA",
    "sg:address":"2807 Gordon Rd",
    "sg:city":"Regina",
    "sg:classifiers":[
        {
            "category":"Shopping",
            "type":"Retail Goods"
        }
    ],
    "sg:phone":"+1 306 585 1977",
    "sg:postcode":"S4S 6H7",
    "sg:province":"SK",
    "sg:tags":[
        "cosmetic",
        "perfume"
    ],
    "wof:name":"Body Shop",
    "wof:placetype":"venue"
},
  "geometry": {"coordinates":[-104.62309265099999,50.4046173096],"type":"Point"}
}