{
  "type": "Feature",
  "properties": {
    "addr:full":"3459 Sheppard Ave E Scarborough ON M1T 3K5",
    "addr:housenumber":"3459",
    "addr:postcode":"m1t 3k5",
    "addr:street":"Sheppard Ave E",
    "iso:country":"CA",
    "sg:address":"3459 Sheppard Ave E",
    "sg:city":"Scarborough",
    "sg:classifiers":[
        {
            "category":"Real Estate",
            "subcategory":"Real Estate Agent",
            "type":"Services"
        }
    ],
    "sg:phone":"+1 416 543 4710",
    "sg:postcode":"M1T 3K5",
    "sg:province":"ON",
    "sg:tags":[
        "management"
    ],
    "wof:name":"Kenneth G Parker Mgmt Ltd",
    "wof:placetype":"venue"
},
  "geometry": {"coordinates":[-79.305244,43.779228],"type":"Point"}
}