{
  "type": "Feature",
  "properties": {
    "addr:full":"Vancouver BC V6Z 2A5",
    "addr:postcode":"v6z 2a5",
    "iso:country":"CA",
    "sg:city":"Vancouver",
    "sg:classifiers":[
        {
            "category":"Health Services",
            "subcategory":"Doctor",
            "type":"Services"
        }
    ],
    "sg:phone":"+1 604 684 5794",
    "sg:postcode":"V6Z 2A5",
    "sg:province":"BC",
    "sg:tags":[
        "physician",
        "surgeon"
    ],
    "wof:name":"Vickars, Linda MD",
    "wof:placetype":"venue"
},
  "geometry": {"coordinates":[-123.128136,49.279564],"type":"Point"}
}