{
  "type": "Feature",
  "properties": {
    "addr:full":"Montreal QC H2Y 3X7",
    "addr:postcode":"h2y 3x7",
    "iso:country":"CA",
    "sg:city":"Montreal",
    "sg:classifiers":[
        {
            "category":"Manufacturing",
            "subcategory":"Furniture",
            "type":"Manufacturing & Wholesale Goods"
        }
    ],
    "sg:phone":"+1 514 985 5313",
    "sg:postcode":"H2Y 3X7",
    "sg:province":"QC",
    "wof:name":"Lacasse Inc",
    "wof:placetype":"venue"
},
  "geometry": {"coordinates":[-73.5607833862,45.5024871826],"type":"Point"}
}