{
  "type": "Feature",
  "properties": {
    "addr:full":"Surrey BC V3W 3A7",
    "addr:postcode":"v3w 3a7",
    "iso:country":"CA",
    "sg:city":"Surrey",
    "sg:classifiers":[
        {
            "category":"Manufacturing",
            "subcategory":"Furniture",
            "type":"Manufacturing & Wholesale Goods"
        }
    ],
    "sg:phone":"+1 604 572 4160",
    "sg:postcode":"V3W 3A7",
    "sg:province":"BC",
    "wof:name":"BC Pine",
    "wof:placetype":"venue"
},
  "geometry": {"coordinates":[-122.869659,49.148083],"type":"Point"}
}