{
  "type": "Feature",
  "properties": {
    "addr:full":"651 Mountain Rd Moncton NB E1C 2P2",
    "addr:housenumber":"651",
    "addr:postcode":"e1c 2p2",
    "addr:street":"Mountain Rd",
    "iso:country":"CA",
    "sg:address":"651 Mountain Rd",
    "sg:city":"Moncton",
    "sg:classifiers":[
        {
            "category":"Shopping",
            "type":"Retail Goods"
        }
    ],
    "sg:phone":"+1 506 388 2226",
    "sg:postcode":"E1C 2P2",
    "sg:province":"NB",
    "sg:tags":[
        "miscellaneous",
        "store"
    ],
    "wof:name":"X-Citement For Adults Only",
    "wof:placetype":"venue"
},
  "geometry": {"coordinates":[-64.8014373779,46.0988311768],"type":"Point"}
}