{
  "type": "Feature",
  "properties": {
    "addr:full":"Calgary AB T2E 3S1",
    "addr:postcode":"t2e 3s1",
    "iso:country":"CA",
    "sg:city":"Calgary",
    "sg:classifiers":[
        {
            "category":"Restaurant",
            "type":"Food & Drink"
        }
    ],
    "sg:phone":"+1 403 237 0830",
    "sg:postcode":"T2E 3S1",
    "sg:province":"AB",
    "wof:name":"Spicy Hut",
    "wof:placetype":"venue"
},
  "geometry": {"coordinates":[-114.05191803,51.0535049438],"type":"Point"}
}