{
  "type": "Feature",
  "properties": {
    "addr:full":"4593 Marine Ave Powell River BC V8A 2K7",
    "addr:housenumber":"4593",
    "addr:postcode":"v8a 2k7",
    "addr:street":"Marine Ave Powell",
    "iso:country":"CA",
    "sg:address":"4593 Marine Ave",
    "sg:city":"Powell River",
    "sg:classifiers":[
        {
            "category":"Food & Beverages",
            "subcategory":"Groceries & Convenience Stores",
            "type":"Retail Goods"
        }
    ],
    "sg:phone":"+1 604 485 5560",
    "sg:postcode":"V8A 2K7",
    "sg:province":"BC",
    "sg:tags":[
        "grocer"
    ],
    "wof:name":"Italian Grocery Store",
    "wof:placetype":"venue"
},
  "geometry": {"coordinates":[-124.528328,49.840317],"type":"Point"}
}