{
  "type": "Feature",
  "properties": {
    "addr:full":"179 St. Paul Cres St Catharines ON L2S 1N4",
    "addr:housenumber":"179",
    "addr:postcode":"l2s 1n4",
    "addr:street":"St. Paul Cres",
    "iso:country":"CA",
    "sg:address":"179 St. Paul Cres",
    "sg:city":"St Catharines",
    "sg:classifiers":[
        {
            "category":"Retail",
            "subcategory":"Auto Repair",
            "type":"Services"
        }
    ],
    "sg:phone":"+1 905 704 1554",
    "sg:postcode":"L2S 1N4",
    "sg:province":"ON",
    "sg:tags":[
        "repairing",
        "automobile",
        "antique"
    ],
    "wof:name":"Garage Sale Store",
    "wof:placetype":"venue"
},
  "geometry": {"coordinates":[-79.25163999999999,43.147812],"type":"Point"}
}