{
  "type": "Feature",
  "properties": {
    "iso:country":"CA",
    "sg:address":"2 Rue Rolland",
    "sg:city":"Saint-Jerome",
    "sg:classifiers":[
        {
            "category":"Manufacturing",
            "subcategory":"Paper Products",
            "type":"Manufacturing & Wholesale Goods"
        }
    ],
    "sg:phone":"+1 450 569 3910",
    "sg:postcode":"J7Z 5S1",
    "sg:province":"QC",
    "wof:name":"Cascades Fine Paper Group Inc",
    "wof:placetype":"venue"
},
  "geometry": {"coordinates":[-74.0028839111,45.7690544128],"type":"Point"}
}