{
  "type": "Feature",
  "properties": {
    "addr:full":"2015 Rue Saint-Denis Montreal QC H2X 3K8",
    "addr:housenumber":"2015",
    "addr:postcode":"h2x 3k8",
    "addr:street":"Rue Saint-Denis",
    "iso:country":"CA",
    "sg:address":"2015 Rue Saint-Denis",
    "sg:city":"Montreal",
    "sg:classifiers":[
        {
            "category":"Shopping",
            "subcategory":"Hobbies, Toys, & Games",
            "type":"Retail Goods"
        }
    ],
    "sg:phone":"+1 514 843 8798",
    "sg:postcode":"H2X 3K8",
    "sg:province":"QC",
    "sg:tags":[
        "craft"
    ],
    "wof:name":"Boutique Lhasa Bhakor-Tibet",
    "wof:placetype":"venue"
},
  "geometry": {"coordinates":[-73.56549099999999,45.516197],"type":"Point"}
}