{
  "type": "Feature",
  "properties": {
    "iso:country":"CA",
    "sg:address":"103 Pender St E",
    "sg:city":"Vancouver",
    "sg:classifiers":[
        {
            "category":"Shopping",
            "type":"Retail Goods"
        }
    ],
    "sg:phone":"+1 604 682 3281",
    "sg:postcode":"V6A 1T6",
    "sg:province":"BC",
    "sg:tags":[
        "art",
        "gallery",
        "dealer"
    ],
    "wof:name":"Family Art Gallery",
    "wof:placetype":"venue"
},
  "geometry": {"coordinates":[-123.101936,49.28056],"type":"Point"}
}