{
  "type": "Feature",
  "properties": {
    "addr:full":"103 Pender St E Vancouver BC V6A 1T6",
    "addr:housenumber":"103",
    "addr:postcode":"v6a 1t6",
    "addr:street":"Pender St E",
    "iso:country":"CA",
    "sg:address":"103 Pender St E",
    "sg:city":"Vancouver",
    "sg:classifiers":[
        {
            "category":"Shopping",
            "type":"Retail Goods"
        }
    ],
    "sg:phone":"+1 604 682 3281",
    "sg:postcode":"V6A 1T6",
    "sg:province":"BC",
    "sg:tags":[
        "art",
        "gallery",
        "dealer"
    ],
    "wof:name":"Family Art Gallery",
    "wof:placetype":"venue"
},
  "geometry": {"coordinates":[-123.10193599999999,49.28056],"type":"Point"}
}