{
  "type": "Feature",
  "properties": {
    "addr:full":"6312 50 St NW Edmonton AB T6B 2N7",
    "addr:housenumber":"6312",
    "addr:postcode":"t6b 2n7",
    "addr:street":"50 St Nw",
    "iso:country":"CA",
    "sg:address":"6312 50 St NW",
    "sg:city":"Edmonton",
    "sg:classifiers":[
        {
            "category":"Wholesale",
            "subcategory":"Drugs",
            "type":"Manufacturing & Wholesale Goods"
        }
    ],
    "sg:phone":"+1 780 413 9832",
    "sg:postcode":"T6B 2N7",
    "sg:province":"AB",
    "sg:tags":[
        "pharmaceutical",
        "product"
    ],
    "wof:name":"Aims Fine Chemicals Inc",
    "wof:placetype":"venue"
},
  "geometry": {"coordinates":[-113.418502808,53.5001182556],"type":"Point"}
}