{
  "type": "Feature",
  "properties": {
    "addr:full":"5553 176 St Surrey BC V3S 4C2",
    "addr:housenumber":"5553",
    "addr:postcode":"v3s 4c2",
    "addr:street":"176 St",
    "iso:country":"CA",
    "sg:address":"5553 176 St",
    "sg:city":"Surrey",
    "sg:classifiers":[
        {
            "category":"Shopping",
            "subcategory":"Used Merchandise",
            "type":"Retail Goods"
        }
    ],
    "sg:phone":"+1 604 576 8737",
    "sg:postcode":"V3S 4C2",
    "sg:province":"BC",
    "sg:tags":[
        "antique"
    ],
    "wof:name":"Red Barn Antiques",
    "wof:placetype":"venue"
},
  "geometry": {"coordinates":[-122.73505400000001,49.103294],"type":"Point"}
}