{
  "type": "Feature",
  "properties": {
    "addr:full":"Etobicoke ON M9V 3Y7",
    "addr:postcode":"m9v 3y7",
    "iso:country":"CA",
    "sg:city":"Etobicoke",
    "sg:classifiers":[
        {
            "category":"Home & Garden",
            "subcategory":"Furniture",
            "type":"Retail Goods"
        }
    ],
    "sg:phone":"+1 416 747 0968",
    "sg:postcode":"M9V 3Y7",
    "sg:province":"ON",
    "sg:tags":[
        "mattress"
    ],
    "wof:name":"B B Bedding",
    "wof:placetype":"venue"
},
  "geometry": {"coordinates":[-79.60404200000001,43.742134],"type":"Point"}
}