{
  "type": "Feature",
  "properties": {
    "addr:full":"5299 Line 81 Listowel ON N4W 3G9",
    "addr:housenumber":"5299",
    "addr:postcode":"n4w 3g9",
    "addr:street":"Line 81",
    "iso:country":"CA",
    "sg:address":"5299 Line 81",
    "sg:city":"Listowel",
    "sg:classifiers":[
        {
            "category":"Building & Trades",
            "subcategory":"Construction",
            "type":"Services"
        }
    ],
    "sg:phone":"+1 519 291 3299",
    "sg:postcode":"N4W 3G9",
    "sg:province":"ON",
    "sg:tags":[
        "general",
        "contractor"
    ],
    "wof:name":"Rozendal Construction Ltd",
    "wof:placetype":"venue"
},
  "geometry": {"coordinates":[-80.9291763306,43.6792984009],"type":"Point"}
}