{
  "type": "Feature",
  "properties": {
    "iso:country":"CA",
    "sg:address":"101 Boul Henri-Bourassa O",
    "sg:city":"Montreal",
    "sg:classifiers":[
        {
            "category":"Health Services",
            "subcategory":"Doctor",
            "type":"Services"
        }
    ],
    "sg:phone":"+1 514 331 0867",
    "sg:postcode":"H3L 1M9",
    "sg:province":"QC",
    "sg:tags":[
        "physiotherapist",
        "clinic"
    ],
    "wof:name":"Physiotherapie S LA Rocque",
    "wof:placetype":"venue"
},
  "geometry": {"coordinates":[-73.670502,45.551403],"type":"Point"}
}