{
  "type": "Feature",
  "properties": {
    "iso:country":"CA",
    "sg:address":"336 Sovereign Rd",
    "sg:city":"London",
    "sg:classifiers":[
        {
            "category":"Manufacturing",
            "subcategory":"Tools & Machinery",
            "type":"Manufacturing & Wholesale Goods"
        }
    ],
    "sg:phone":"+1 519 659 4818",
    "sg:postcode":"N6M 1A8",
    "sg:province":"ON",
    "sg:tags":[
        "mold"
    ],
    "wof:name":"Mantec Tool & Mould",
    "wof:placetype":"venue"
},
  "geometry": {"coordinates":[-81.139793396,42.9906044006],"type":"Point"}
}