{
  "type": "Feature",
  "properties": {
    "addr:full":"10445 80 Ave NW Edmonton AB T6E 1V1",
    "addr:housenumber":"10445",
    "addr:postcode":"t6e 1v1",
    "addr:street":"80 Ave Nw",
    "iso:country":"CA",
    "sg:address":"10445 80 Ave NW",
    "sg:city":"Edmonton",
    "sg:classifiers":[
        {
            "category":"Banks & Credit Unions",
            "subcategory":"Bank",
            "type":"Services"
        }
    ],
    "sg:phone":"+1 780 433 5858",
    "sg:postcode":"T6E 1V1",
    "sg:province":"AB",
    "sg:tags":[
        "loan",
        "real estate"
    ],
    "wof:name":"Citi Financial",
    "wof:placetype":"venue"
},
  "geometry": {"coordinates":[-113.49892425500001,53.5159912109],"type":"Point"}
}