{
  "type": "Feature",
  "properties": {
    "addr:full":"54 Pine St Kitchener ON N2H 6A1",
    "addr:housenumber":"54",
    "addr:postcode":"n2h 6a1",
    "addr:street":"Pine St",
    "iso:country":"CA",
    "sg:address":"54 Pine St",
    "sg:city":"Kitchener",
    "sg:classifiers":[
        {
            "category":"Retail",
            "subcategory":"Repair Shop",
            "type":"Services"
        }
    ],
    "sg:phone":"+1 519 744 2744",
    "sg:postcode":"N2H 6A1",
    "sg:province":"ON",
    "sg:tags":[
        "repairing",
        "piano",
        "refinishing"
    ],
    "wof:name":"Wall's Piano Tuning",
    "wof:placetype":"venue"
},
  "geometry": {"coordinates":[-80.510666,43.458645],"type":"Point"}
}