{
  "type": "Feature",
  "properties": {
    "addr:full":"13625 Covered Wagon Trail Ladysmith BC V9G 1H1",
    "addr:housenumber":"13625",
    "addr:postcode":"v9g 1h1",
    "addr:street":"Covered Wagon Trail",
    "iso:country":"CA",
    "sg:address":"13625 Covered Wagon Trail",
    "sg:city":"Ladysmith",
    "sg:classifiers":[
        {
            "category":"Freight",
            "type":"Transportation"
        }
    ],
    "sg:phone":"+1 250 245 8814",
    "sg:postcode":"V9G 1H1",
    "sg:province":"BC",
    "sg:tags":[
        "trucking"
    ],
    "wof:name":"Hudson's Hauling & Hoe Svc",
    "wof:placetype":"venue"
},
  "geometry": {"coordinates":[-123.82054100000001,48.997356],"type":"Point"}
}