{
  "type": "Feature",
  "properties": {
    "iso:country":"CA",
    "sg:city":"Langley",
    "sg:classifiers":[
        {
            "category":"Health Services",
            "subcategory":"Doctor",
            "type":"Services"
        }
    ],
    "sg:phone":"+1 604 882 0887",
    "sg:postcode":"V1M 2K4",
    "sg:province":"BC",
    "sg:tags":[
        "dentist"
    ],
    "wof:name":"A D Mc Farlane Inc",
    "wof:placetype":"venue"
},
  "geometry": {"coordinates":[-122.657203674,49.163646698],"type":"Point"}
}