{
  "type": "Feature",
  "properties": {
    "addr:full":"153 Wellington St Kingston ON K7L 3E1",
    "addr:housenumber":"153",
    "addr:postcode":"k7l 3e1",
    "addr:street":"Wellington St",
    "iso:country":"CA",
    "sg:address":"153 Wellington St",
    "sg:city":"Kingston",
    "sg:classifiers":[
        {
            "category":"Banks & Credit Unions",
            "subcategory":"Bank",
            "type":"Services"
        }
    ],
    "sg:phone":"+1 613 531 8731",
    "sg:postcode":"K7L 3E1",
    "sg:province":"ON",
    "sg:tags":[
        "broker",
        "foreign",
        "dealer",
        "exchange"
    ],
    "wof:name":"Wellington Foreign Exchange",
    "wof:placetype":"venue"
},
  "geometry": {"coordinates":[-76.4828109741,44.2303543091],"type":"Point"}
}