{
  "type": "Feature",
  "properties": {
    "addr:full":"93 Rue Fusey Cap-DE-LA-Madeleine QC G8T 2V2",
    "addr:housenumber":"93",
    "addr:postcode":"g8t 2v2",
    "addr:street":"Rue Fusey",
    "iso:country":"CA",
    "sg:address":"93 Rue Fusey",
    "sg:city":"Cap-DE-LA-Madeleine",
    "sg:classifiers":[
        {
            "category":"Insurance",
            "subcategory":"Insurance Agent",
            "type":"Services"
        }
    ],
    "sg:phone":"+1 819 373 1402",
    "sg:postcode":"G8T 2V2",
    "sg:province":"QC",
    "wof:name":"Ahern, Micheline",
    "wof:placetype":"venue"
},
  "geometry": {"coordinates":[-72.5270309448,46.3657493591],"type":"Point"}
}