{
  "type": "Feature",
  "properties": {
    "addr:full":"12006 Diamond View SE Calgary AB T2J 7B6",
    "addr:housenumber":"12006",
    "addr:postcode":"t2j 7b6",
    "addr:street":"Diamond;Se",
    "iso:country":"CA",
    "sg:address":"12006 Diamond View SE",
    "sg:city":"Calgary",
    "sg:classifiers":[
        {
            "category":"Building & Trades",
            "subcategory":"Electrical",
            "type":"Services"
        }
    ],
    "sg:phone":"+1 403 271 1334",
    "sg:postcode":"T2J 7B6",
    "sg:province":"AB",
    "sg:tags":[
        "electric",
        "contractor"
    ],
    "wof:name":"Petersen Electric",
    "wof:placetype":"venue"
},
  "geometry": {"coordinates":[-114.024345,50.949326],"type":"Point"}
}