{
  "type": "Feature",
  "properties": {
    "iso:country":"CA",
    "sg:address":"670 Progress Ave #14",
    "sg:city":"Scarborough",
    "sg:classifiers":[
        {
            "category":"Social Services",
            "type":"Services"
        }
    ],
    "sg:phone":"+1 416 439 9009",
    "sg:postcode":"M1H 3A4",
    "sg:province":"ON",
    "sg:tags":[
        "organization",
        "welfare"
    ],
    "wof:name":"Tropicana Community Svc",
    "wof:placetype":"venue"
},
  "geometry": {"coordinates":[-79.2476730347,43.7777137756],"type":"Point"}
}