{
  "type": "Feature",
  "properties": {
    "iso:country":"CA",
    "sg:address":"143006 Superior St",
    "sg:city":"Owen Sound",
    "sg:classifiers":[
        {
            "category":"Shopping",
            "subcategory":"Computers & Home Electronics",
            "type":"Retail Goods"
        }
    ],
    "sg:phone":"+1 519 376 7979",
    "sg:postcode":"N4K 5N8",
    "sg:province":"ON",
    "sg:tags":[
        "equipment",
        "dealer"
    ],
    "wof:name":"E C Technologies Inc",
    "wof:placetype":"venue"
},
  "geometry": {"coordinates":[-80.92301940919999,44.5584068298],"type":"Point"}
}