{
  "type": "Feature",
  "properties": {
    "iso:country":"CA",
    "sg:city":"Gloucester",
    "sg:classifiers":[
        {
            "category":"Manufacturing",
            "subcategory":"Signs",
            "type":"Manufacturing & Wholesale Goods"
        }
    ],
    "sg:phone":"+1 613 740 9992",
    "sg:postcode":"K1J 9C8",
    "sg:province":"ON",
    "wof:name":"Image Signs & Graphics",
    "wof:placetype":"venue"
},
  "geometry": {"coordinates":[-75.584815979,45.4538383484],"type":"Point"}
}