{
  "type": "Feature",
  "properties": {
    "iso:country":"CA",
    "sg:address":"2070 Dundas St",
    "sg:city":"London",
    "sg:classifiers":[
        {
            "category":"Autos & Motor Vehicles",
            "subcategory":"Automobile Sales",
            "type":"Retail Goods"
        }
    ],
    "sg:phone":"+1 519 451 1360",
    "sg:postcode":"N5V 1R2",
    "sg:province":"ON",
    "sg:tags":[
        "car",
        "dealer"
    ],
    "wof:name":"Jfj Auto Sales",
    "wof:placetype":"venue"
},
  "geometry": {"coordinates":[-81.162697,43.008545],"type":"Point"}
}