{
  "type": "Feature",
  "properties": {
    "addr:full":"888 Nairn Ave Winnipeg MB R2L 0X8",
    "addr:housenumber":"888",
    "addr:postcode":"r2l 0x8",
    "addr:street":"Nairn Ave",
    "iso:country":"CA",
    "sg:address":"888 Nairn Ave",
    "sg:city":"Winnipeg",
    "sg:classifiers":[
        {
            "category":"Manufacturing",
            "subcategory":"Tools & Machinery",
            "type":"Manufacturing & Wholesale Goods"
        }
    ],
    "sg:phone":"+1 204 982 4900",
    "sg:postcode":"R2L 0X8",
    "sg:province":"MB",
    "sg:tags":[
        "machine",
        "equipment",
        "pneumatic",
        "shop"
    ],
    "wof:name":"Dynamic Machine Corp",
    "wof:placetype":"venue"
},
  "geometry": {"coordinates":[-97.08599100000001,49.901234],"type":"Point"}
}