{
  "type": "Feature",
  "properties": {
    "addr:full":"8764 Rue Lajeunesse Montreal QC H2M 1R6",
    "addr:housenumber":"8764",
    "addr:postcode":"h2m 1r6",
    "addr:street":"Rue Lajeunesse",
    "iso:country":"CA",
    "sg:address":"8764 Rue Lajeunesse",
    "sg:city":"Montreal",
    "sg:classifiers":[
        {
            "category":"Personal",
            "subcategory":"Beauty Salon",
            "type":"Services"
        }
    ],
    "sg:phone":"+1 514 389 9544",
    "sg:postcode":"H2M 1R6",
    "sg:province":"QC",
    "wof:name":"Version Beaute",
    "wof:placetype":"venue"
},
  "geometry": {"coordinates":[-73.63911437989999,45.5466423035],"type":"Point"}
}