{
  "type": "Feature",
  "properties": {
    "addr:full":"37 King St E Gananoque ON K7G 1E8",
    "addr:housenumber":"37",
    "addr:postcode":"k7g 1e8",
    "addr:street":"King St E",
    "iso:country":"CA",
    "sg:address":"37 King St E",
    "sg:city":"Gananoque",
    "sg:classifiers":[
        {
            "category":"Restaurant",
            "type":"Food & Drink"
        }
    ],
    "sg:phone":"+1 613 382 3575",
    "sg:postcode":"K7G 1E8",
    "sg:province":"ON",
    "wof:name":"Anthony's Restaurant",
    "wof:placetype":"venue"
},
  "geometry": {"coordinates":[-76.16394042970001,44.3285064697],"type":"Point"}
}