{
  "type": "Feature",
  "properties": {
    "iso:country":"CA",
    "sg:city":"Calgary",
    "sg:classifiers":[
        {
            "category":"Education",
            "subcategory":"Special Training",
            "type":"Public Place"
        }
    ],
    "sg:phone":"+1 403 272 4246",
    "sg:postcode":"T2B 1N1",
    "sg:province":"AB",
    "sg:tags":[
        "school",
        "instruction",
        "driving"
    ],
    "wof:name":"Derek Brown Academy of Driving",
    "wof:placetype":"venue"
},
  "geometry": {"coordinates":[-113.95810699499999,51.0374488831],"type":"Point"}
}