{
  "type": "Feature",
  "properties": {
    "addr:full":"300 Grand River St N Paris ON N3L 3R7",
    "addr:housenumber":"300",
    "addr:postcode":"n3l 3r7",
    "addr:street":"Grand River St N",
    "iso:country":"CA",
    "sg:address":"300 Grand River St N",
    "sg:city":"Paris",
    "sg:classifiers":[
        {
            "category":"Personal",
            "type":"Services"
        }
    ],
    "sg:phone":"+1 519 442 7551",
    "sg:postcode":"N3L 3R7",
    "sg:province":"ON",
    "sg:tags":[
        "program",
        "physical",
        "exercise",
        "fitness"
    ],
    "wof:name":"Curves For Women",
    "wof:placetype":"venue"
},
  "geometry": {"coordinates":[-80.38938899999999,43.21146],"type":"Point"}
}