{
  "type": "Feature",
  "properties": {
    "addr:full":"19 Rue Notre Dame Cap-Chat QC G0J 1E0",
    "addr:housenumber":"19",
    "addr:postcode":"g0j 1e0",
    "addr:street":"Rue Notre Dame",
    "iso:country":"CA",
    "sg:address":"19 Rue Notre Dame",
    "sg:city":"Cap-Chat",
    "sg:classifiers":[
        {
            "category":"Home & Garden",
            "subcategory":"Furniture",
            "type":"Retail Goods"
        }
    ],
    "sg:phone":"+1 418 786 5515",
    "sg:postcode":"G0J 1E0",
    "sg:province":"QC",
    "wof:name":"Meubles R Richard Inc",
    "wof:placetype":"venue"
},
  "geometry": {"coordinates":[-66.6875,49.0973129272],"type":"Point"}
}