{
  "type": "Feature",
  "properties": {
    "addr:full":"3073 Boul Des Sources Dollard-Des-Ormeaux QC H9B 1Z6",
    "addr:housenumber":"3073",
    "addr:postcode":"h9b 1z6",
    "addr:street":"Boul Des Sources",
    "iso:country":"CA",
    "sg:address":"3073 Boul Des Sources",
    "sg:city":"Dollard-Des-Ormeaux",
    "sg:classifiers":[
        {
            "category":"Professional",
            "subcategory":"Employment Agencies",
            "type":"Services"
        }
    ],
    "sg:phone":"+1 514 683 1057",
    "sg:postcode":"H9B 1Z6",
    "sg:province":"QC",
    "sg:tags":[
        "opportunity"
    ],
    "wof:name":"Optimum",
    "wof:placetype":"venue"
},
  "geometry": {"coordinates":[-73.795006,45.482536],"type":"Point"}
}