{
  "type": "Feature",
  "properties": {
    "addr:full":"Calgary AB T2J 7E4",
    "addr:postcode":"t2j 7e4",
    "iso:country":"CA",
    "sg:city":"Calgary",
    "sg:classifiers":[
        {
            "category":"Government",
            "subcategory":"Office",
            "type":"Public Place"
        }
    ],
    "sg:phone":"+1 403 225 3480",
    "sg:postcode":"T2J 7E4",
    "sg:province":"AB",
    "wof:name":"Calgary SE",
    "wof:placetype":"venue"
},
  "geometry": {"coordinates":[-114.069023132,50.9596862793],"type":"Point"}
}