{
  "type": "Feature",
  "properties": {
    "addr:full":"299 Rue Olivier Sherbrooke QC J1H 1X4",
    "addr:housenumber":"299",
    "addr:postcode":"j1h 1x4",
    "addr:street":"Rue Olivier",
    "iso:country":"CA",
    "sg:address":"299 Rue Olivier",
    "sg:city":"Sherbrooke",
    "sg:classifiers":[
        {
            "category":"Government",
            "subcategory":"Office",
            "type":"Public Place"
        }
    ],
    "sg:phone":"+1 819 564 5702",
    "sg:postcode":"J1H 1X4",
    "sg:province":"QC",
    "wof:name":"Canada Service Environnement",
    "wof:placetype":"venue"
},
  "geometry": {"coordinates":[-71.890404,45.394711],"type":"Point"}
}