{
  "type": "Feature",
  "properties": {
    "addr:full":"Tillsonburg ON N4G 2J5",
    "addr:postcode":"n4g 2j5",
    "iso:country":"CA",
    "sg:city":"Tillsonburg",
    "sg:classifiers":[
        {
            "category":"Shopping",
            "subcategory":"Discount & Variety Stores",
            "type":"Retail Goods"
        }
    ],
    "sg:phone":"+1 519 842 6553",
    "sg:postcode":"N4G 2J5",
    "sg:province":"ON",
    "wof:name":"Noco Express Shop",
    "wof:placetype":"venue"
},
  "geometry": {"coordinates":[-80.70027899999999,42.855797],"type":"Point"}
}