{
  "type": "Feature",
  "properties": {
    "addr:full":"11434 154 St NW Edmonton AB T5M 3R4",
    "addr:housenumber":"11434",
    "addr:postcode":"t5m 3r4",
    "addr:street":"154 St Nw",
    "iso:country":"CA",
    "sg:address":"11434 154 St NW",
    "sg:city":"Edmonton",
    "sg:classifiers":[
        {
            "category":"Manufacturing",
            "subcategory":"Motor Vehicles & Parts",
            "type":"Manufacturing & Wholesale Goods"
        }
    ],
    "sg:phone":"+1 780 454 4880",
    "sg:postcode":"T5M 3R4",
    "sg:province":"AB",
    "sg:tags":[
        "equipment",
        "truck"
    ],
    "wof:name":"Fort Garry Industries Ltd",
    "wof:placetype":"venue"
},
  "geometry": {"coordinates":[-113.58747099999999,53.563988],"type":"Point"}
}