{
  "type": "Feature",
  "properties": {
    "addr:full":"Pitt Meadows BC V3Y 2E9",
    "addr:postcode":"v3y 2e9",
    "iso:country":"CA",
    "sg:city":"Pitt Meadows",
    "sg:classifiers":[
        {
            "category":"Health Services",
            "subcategory":"Medical Lab",
            "type":"Services"
        }
    ],
    "sg:phone":"+1 604 465 7873",
    "sg:postcode":"V3Y 2E9",
    "sg:province":"BC",
    "sg:tags":[
        "laboratory"
    ],
    "wof:name":"B C Bio-Medical Laboratories",
    "wof:placetype":"venue"
},
  "geometry": {"coordinates":[-122.689819,49.224297],"type":"Point"}
}