{
  "type": "Feature",
  "properties": {
    "addr:full":"701 Gordon St Whitby ON L1N 5S4",
    "addr:housenumber":"701",
    "addr:postcode":"l1n 5s4",
    "addr:street":"Gordon St",
    "iso:country":"CA",
    "sg:address":"701 Gordon St",
    "sg:city":"Whitby",
    "sg:classifiers":[
        {
            "category":"Organizations",
            "subcategory":"Professional Association",
            "type":"Services"
        }
    ],
    "sg:phone":"+1 905 668 1391",
    "sg:postcode":"L1N 5S4",
    "sg:province":"ON",
    "sg:tags":[
        "club"
    ],
    "wof:name":"Whitby Yacht Club",
    "wof:placetype":"venue"
},
  "geometry": {"coordinates":[-78.94051399999999,43.851475],"type":"Point"}
}