{
  "type": "Feature",
  "properties": {
    "addr:full":"3945 Helen Rd Victoria BC V8Z 5C6",
    "addr:housenumber":"3945",
    "addr:postcode":"v8z 5c6",
    "addr:street":"Helen Rd",
    "iso:country":"CA",
    "sg:address":"3945 Helen Rd",
    "sg:city":"Victoria",
    "sg:classifiers":[
        {
            "category":"Real Estate",
            "subcategory":"Architect",
            "type":"Services"
        }
    ],
    "sg:phone":"+1 250 479 0960",
    "sg:postcode":"V8Z 5C6",
    "sg:province":"BC",
    "wof:name":"Lee, Andrew J",
    "wof:placetype":"venue"
},
  "geometry": {"coordinates":[-123.36451700000001,48.428314],"type":"Point"}
}