{
  "type": "Feature",
  "properties": {
    "iso:country":"CA",
    "sg:address":"451 Ofield Rd S",
    "sg:city":"Dundas",
    "sg:classifiers":[
        {
            "category":"Shopping",
            "type":"Retail Goods"
        }
    ],
    "sg:phone":"+1 905 627 0993",
    "sg:postcode":"L9H 5E2",
    "sg:province":"ON",
    "sg:tags":[
        "stone",
        "monument"
    ],
    "wof:name":"Hgh Granite Inc",
    "wof:placetype":"venue"
},
  "geometry": {"coordinates":[-79.9523773193,43.2637786865],"type":"Point"}
}