{
  "type": "Feature",
  "properties": {
    "addr:full":"10801 102 St High Level AB T0H 1Z0",
    "addr:housenumber":"10801",
    "addr:postcode":"t0h 1z0",
    "addr:street":"102 St",
    "iso:country":"CA",
    "sg:address":"10801 102 St",
    "sg:city":"High Level",
    "sg:classifiers":[
        {
            "category":"Education",
            "subcategory":"School",
            "type":"Public Place"
        }
    ],
    "sg:phone":"+1 780 841 7200",
    "sg:postcode":"T0H 1Z0",
    "sg:province":"AB",
    "wof:name":"Spirit of the North Community",
    "wof:placetype":"venue"
},
  "geometry": {"coordinates":[-117.141983032,58.5152053833],"type":"Point"}
}