{
  "type": "Feature",
  "properties": {
    "addr:full":"1334 Rue Saint-Zotique E Montreal QC H2G 1G5",
    "addr:housenumber":"1334",
    "addr:postcode":"h2g 1g5",
    "addr:street":"Rue Saint-Zotique E",
    "iso:country":"CA",
    "sg:address":"1334 Rue Saint-Zotique E",
    "sg:city":"Montreal",
    "sg:classifiers":[
        {
            "category":"Food & Beverages",
            "subcategory":"Groceries & Convenience Stores",
            "type":"Retail Goods"
        }
    ],
    "sg:phone":"+1 514 276 7016",
    "sg:postcode":"H2G 1G5",
    "sg:province":"QC",
    "wof:name":"Marche Du Bon Jour",
    "wof:placetype":"venue"
},
  "geometry": {"coordinates":[-73.60245500000001,45.541962],"type":"Point"}
}