{
  "type": "Feature",
  "properties": {
    "addr:full":"3750 Rue Sicotte Quebec QC G2B 3X4",
    "addr:housenumber":"3750",
    "addr:postcode":"g2b 3x4",
    "addr:street":"Rue Sicotte",
    "iso:country":"CA",
    "sg:address":"3750 Rue Sicotte",
    "sg:city":"Quebec",
    "sg:classifiers":[
        {
            "category":"Personal",
            "subcategory":"Beauty Salon",
            "type":"Services"
        }
    ],
    "sg:phone":"+1 418 843 0650",
    "sg:postcode":"G2B 3X4",
    "sg:province":"QC",
    "wof:name":"Coiffure Marie Sue Enr",
    "wof:placetype":"venue"
},
  "geometry": {"coordinates":[-71.354294,46.838425],"type":"Point"}
}