{
  "type": "Feature",
  "properties": {
    "iso:country":"CA",
    "sg:address":"430 Gorham Rd",
    "sg:city":"Ridgeway",
    "sg:classifiers":[
        {
            "category":"Building & Trades",
            "subcategory":"Electrical",
            "type":"Services"
        }
    ],
    "sg:phone":"+1 905 894 2229",
    "sg:postcode":"L0S 1N0",
    "sg:province":"ON",
    "sg:tags":[
        "electric",
        "contractor"
    ],
    "wof:name":"K Riel Electric Ltd",
    "wof:placetype":"venue"
},
  "geometry": {"coordinates":[-79.0591049194,42.8863334656],"type":"Point"}
}