{
  "type": "Feature",
  "properties": {
    "addr:full":"Kitwanga BC V0J 2A0",
    "addr:postcode":"v0j 2a0",
    "iso:country":"CA",
    "sg:city":"Kitwanga",
    "sg:classifiers":[
        {
            "category":"Building & Trades",
            "subcategory":"Construction",
            "type":"Services"
        }
    ],
    "sg:phone":"+1 250 849 5571",
    "sg:postcode":"V0J 2A0",
    "sg:province":"BC",
    "sg:tags":[
        "accountant",
        "general",
        "contractor"
    ],
    "wof:name":"Dcr Contracting",
    "wof:placetype":"venue"
},
  "geometry": {"coordinates":[-128.071731567,55.103931427],"type":"Point"}
}