{
  "type": "Feature",
  "properties": {
    "addr:full":"133 Rue Bellevue O Les Mechins QC G0J 1T0",
    "addr:housenumber":"133",
    "addr:postcode":"g0j 1t0",
    "addr:street":"Rue Bellevue O Les Mechins",
    "iso:country":"CA",
    "sg:address":"133 Rue Bellevue O",
    "sg:city":"Les Mechins",
    "sg:classifiers":[
        {
            "category":"Food & Beverages",
            "subcategory":"Dairy",
            "type":"Retail Goods"
        }
    ],
    "sg:phone":"+1 418 729 3855",
    "sg:postcode":"G0J 1T0",
    "sg:province":"QC",
    "sg:tags":[
        "cheese"
    ],
    "wof:name":"Fromagerie Les Mechins Inc",
    "wof:placetype":"venue"
},
  "geometry": {"coordinates":[-66.97022200000001,49.002403],"type":"Point"}
}