{
  "type": "Feature",
  "properties": {
    "addr:full":"2277 Kingston Rd Scarborough ON M1N 1T8",
    "addr:housenumber":"2277",
    "addr:postcode":"m1n 1t8",
    "addr:street":"Kingston Rd",
    "iso:country":"CA",
    "sg:address":"2277 Kingston Rd",
    "sg:city":"Scarborough",
    "sg:classifiers":[
        {
            "category":"Bars & Pubs",
            "type":"Food & Drink"
        }
    ],
    "sg:phone":"+1 416 261 5441",
    "sg:postcode":"M1N 1T8",
    "sg:province":"ON",
    "sg:tags":[
        "lounge",
        "cocktail"
    ],
    "wof:name":"Fanny's Sports Lounge",
    "wof:placetype":"venue"
},
  "geometry": {"coordinates":[-79.251549,43.70546],"type":"Point"}
}