{
  "type": "Feature",
  "properties": {
    "iso:country":"CA",
    "sg:city":"Orleans",
    "sg:classifiers":[
        {
            "category":"Shopping",
            "subcategory":"Clothing, Apparel, & Fashions",
            "type":"Retail Goods"
        }
    ],
    "sg:phone":"+1 613 837 8291",
    "sg:postcode":"K1C 2L9",
    "sg:province":"ON",
    "sg:tags":[
        "leather"
    ],
    "wof:name":"Leather Ranch",
    "wof:placetype":"venue"
},
  "geometry": {"coordinates":[-75.5059432983,45.4832611084],"type":"Point"}
}