{
  "type": "Feature",
  "properties": {
    "addr:full":"71 Market St Paris ON N3L 3B1",
    "addr:housenumber":"71",
    "addr:postcode":"n3l 3b1",
    "addr:street":"Market St",
    "iso:country":"CA",
    "sg:address":"71 Market St",
    "sg:city":"Paris",
    "sg:classifiers":[
        {
            "category":"Building & Trades",
            "subcategory":"Construction",
            "type":"Services"
        }
    ],
    "sg:phone":"+1 519 442 6662",
    "sg:postcode":"N3L 3B1",
    "sg:province":"ON",
    "sg:tags":[
        "resurfacing",
        "laying",
        "refinishing",
        "floor"
    ],
    "wof:name":"Pike & Son Floors",
    "wof:placetype":"venue"
},
  "geometry": {"coordinates":[-80.397766,43.208038],"type":"Point"}
}