{
  "type": "Feature",
  "properties": {
    "iso:country":"CA",
    "sg:address":"96 Ch DE LA Ferme-Joseph",
    "sg:city":"Deleage",
    "sg:classifiers":[
        {
            "category":"Home & Garden",
            "subcategory":"Building Materials",
            "type":"Retail Goods"
        }
    ],
    "sg:phone":"+1 819 441 0909",
    "sg:postcode":"J9E 3A8",
    "sg:province":"QC",
    "sg:tags":[
        "lumber"
    ],
    "wof:name":"Makibois Inc",
    "wof:placetype":"venue"
},
  "geometry": {"coordinates":[-75.8850326538,46.3998947144],"type":"Point"}
}