{
  "type": "Feature",
  "properties": {
    "iso:country":"CA",
    "sg:address":"Alumni Cres",
    "sg:city":"Halifax",
    "sg:classifiers":[
        {
            "category":"Restaurant",
            "type":"Food & Drink"
        }
    ],
    "sg:phone":"+1 902 494 6511",
    "sg:postcode":"B3H 3J5",
    "sg:province":"NS",
    "sg:tags":[
        "caterer"
    ],
    "wof:name":"Dalhousie University Club",
    "wof:placetype":"venue"
},
  "geometry": {"coordinates":[-63.5913391113,44.6361160278],"type":"Point"}
}