{
  "type": "Feature",
  "properties": {
    "addr:full":"Whistler BC V0N 1B4",
    "addr:postcode":"v0n 1b4",
    "iso:country":"CA",
    "sg:city":"Whistler",
    "sg:classifiers":[
        {
            "category":"Shopping",
            "subcategory":"Bicycles & Sporting Goods",
            "type":"Retail Goods"
        }
    ],
    "sg:phone":"+1 604 932 7221",
    "sg:postcode":"V0N 1B4",
    "sg:province":"BC",
    "sg:tags":[
        "party",
        "fishing"
    ],
    "wof:name":"Whistler Fly Fishing Ltd",
    "wof:placetype":"venue"
},
  "geometry": {"coordinates":[-122.95637499999999,50.120224],"type":"Point"}
}