{
  "type": "Feature",
  "properties": {
    "iso:country":"CA",
    "sg:address":"3479 St. Andrews Ave",
    "sg:city":"Halifax",
    "sg:classifiers":[
        {
            "category":"Professional",
            "subcategory":"Business Services",
            "type":"Services"
        }
    ],
    "sg:phone":"+1 902 454 3480",
    "sg:postcode":"B3L 3Y3",
    "sg:province":"NS",
    "sg:tags":[
        "translator",
        "interpreter"
    ],
    "wof:name":"Georges Merinfeld Translations",
    "wof:placetype":"venue"
},
  "geometry": {"coordinates":[-63.6225662231,44.6575202942],"type":"Point"}
}