{
  "type": "Feature",
  "properties": {
    "iso:country":"CA",
    "sg:city":"Drayton Valley",
    "sg:classifiers":[
        {
            "category":"Social Services",
            "type":"Services"
        }
    ],
    "sg:phone":"+1 780 621 1800",
    "sg:postcode":"T7A 1S6",
    "sg:province":"AB",
    "sg:tags":[
        "counseling",
        "counselor",
        "marriage",
        "family"
    ],
    "wof:name":"Human Services Ctr",
    "wof:placetype":"venue"
},
  "geometry": {"coordinates":[-114.986694336,53.2238540649],"type":"Point"}
}