{
  "type": "Feature",
  "properties": {
    "addr:full":"Montreal QC H4P 1W7",
    "addr:postcode":"h4p 1w7",
    "iso:country":"CA",
    "sg:city":"Montreal",
    "sg:classifiers":[
        {
            "category":"Professional",
            "subcategory":"Employment Agencies",
            "type":"Services"
        }
    ],
    "sg:phone":"+1 514 733 2114",
    "sg:postcode":"H4P 1W7",
    "sg:province":"QC",
    "sg:tags":[
        "opportunity"
    ],
    "wof:name":"Tis Svc Ind Temporaire",
    "wof:placetype":"venue"
},
  "geometry": {"coordinates":[-73.648911,45.498154],"type":"Point"}
}