{
  "type": "Feature",
  "properties": {
    "addr:full":"137 Idylwyld Dr N Saskatoon SK S7L 0Y6",
    "addr:housenumber":"137",
    "addr:postcode":"s7l 0y6",
    "addr:street":"Idylwyld Dr N",
    "iso:country":"CA",
    "sg:address":"137 Idylwyld Dr N",
    "sg:city":"Saskatoon",
    "sg:classifiers":[
        {
            "category":"Retail",
            "subcategory":"Auto Repair",
            "type":"Services"
        }
    ],
    "sg:phone":"+1 306 244 6633",
    "sg:postcode":"S7L 0Y6",
    "sg:province":"SK",
    "sg:tags":[
        "wheel",
        "brake",
        "alignment"
    ],
    "wof:name":"Keith & Herb Alignment & Brake",
    "wof:placetype":"venue"
},
  "geometry": {"coordinates":[-106.670563,52.129967],"type":"Point"}
}