{
  "type": "Feature",
  "properties": {
    "iso:country":"CA",
    "sg:address":"4839 Boul Gouin O",
    "sg:city":"Montreal",
    "sg:classifiers":[
        {
            "category":"Retail",
            "subcategory":"Laundry & Dry Cleaning",
            "type":"Services"
        }
    ],
    "sg:phone":"+1 514 322 1220",
    "sg:postcode":"H4J 1B9",
    "sg:province":"QC",
    "sg:tags":[
        "cleaners",
        "steam"
    ],
    "wof:name":"Nettoyeur Ideal Montreal N",
    "wof:placetype":"venue"
},
  "geometry": {"coordinates":[-73.7130661011,45.5370330811],"type":"Point"}
}