{
  "type": "Feature",
  "properties": {
    "addr:full":"365 Rue Chasles Mont-Laurier QC J9L 2T7",
    "addr:housenumber":"365",
    "addr:postcode":"j9l 2t7",
    "addr:street":"Rue Chasles",
    "iso:country":"CA",
    "sg:address":"365 Rue Chasles",
    "sg:city":"Mont-Laurier",
    "sg:classifiers":[
        {
            "category":"Restaurant",
            "type":"Food & Drink"
        }
    ],
    "sg:phone":"+1 819 623 7031",
    "sg:postcode":"J9L 2T7",
    "sg:province":"QC",
    "wof:name":"Restaurant Aux Grills",
    "wof:placetype":"venue"
},
  "geometry": {"coordinates":[-75.49629974370001,46.5505180359],"type":"Point"}
}