{
  "type": "Feature",
  "properties": {
    "addr:full":"685 Boul Sainte-Foy Longueuil QC J4J 1Z1",
    "addr:housenumber":"685",
    "addr:postcode":"j4j 1z1",
    "addr:street":"Boul Sainte-Foy",
    "iso:country":"CA",
    "sg:address":"685 Boul Sainte-Foy",
    "sg:city":"Longueuil",
    "sg:classifiers":[
        {
            "category":"Professional",
            "subcategory":"Business Services",
            "type":"Services"
        }
    ],
    "sg:phone":"+1 450 679 8529",
    "sg:postcode":"J4J 1Z1",
    "sg:province":"QC",
    "sg:tags":[
        "notary"
    ],
    "wof:name":"St Onge & Aumais",
    "wof:placetype":"venue"
},
  "geometry": {"coordinates":[-73.494682,45.524475],"type":"Point"}
}