{
  "type": "Feature",
  "properties": {
    "addr:full":"161 Central Ave Fort Erie ON L2A 3S5",
    "addr:housenumber":"161",
    "addr:postcode":"l2a 3s5",
    "addr:street":"Central Ave",
    "iso:country":"CA",
    "sg:address":"161 Central Ave",
    "sg:city":"Fort Erie",
    "sg:classifiers":[
        {
            "category":"Restaurant",
            "type":"Food & Drink"
        }
    ],
    "sg:phone":"+1 905 871 4333",
    "sg:postcode":"L2A 3S5",
    "sg:province":"ON",
    "sg:tags":[
        "pizza"
    ],
    "wof:name":"Central Pizzeria & Restaurant",
    "wof:placetype":"venue"
},
  "geometry": {"coordinates":[-78.91886100000001,42.912655],"type":"Point"}
}