{
  "type": "Feature",
  "properties": {
    "addr:full":"Abbotsford BC V2S 7C4",
    "addr:postcode":"v2s 7c4",
    "iso:country":"CA",
    "sg:city":"Abbotsford",
    "sg:classifiers":[
        {
            "category":"Real Estate",
            "subcategory":"Real Estate Operator",
            "type":"Services"
        }
    ],
    "sg:phone":"+1 604 854 5716",
    "sg:postcode":"V2S 7C4",
    "sg:province":"BC",
    "sg:tags":[
        "apartment"
    ],
    "wof:name":"Bridgeport Properties",
    "wof:placetype":"venue"
},
  "geometry": {"coordinates":[-122.299743652,49.0483131409],"type":"Point"}
}