{
  "type": "Feature",
  "properties": {
    "addr:full":"29 Red Robin Pl Winnipeg MB R3J 3L9",
    "addr:housenumber":"29",
    "addr:postcode":"r3j 3l9",
    "addr:street":"Red Robin Pl",
    "iso:country":"CA",
    "sg:address":"29 Red Robin Pl",
    "sg:city":"Winnipeg",
    "sg:classifiers":[
        {
            "category":"Professional",
            "subcategory":"Accounting & Tax Preparation",
            "type":"Services"
        }
    ],
    "sg:phone":"+1 204 889 2485",
    "sg:postcode":"R3J 3L9",
    "sg:province":"MB",
    "sg:tags":[
        "accountant"
    ],
    "wof:name":"Bingham, William O",
    "wof:placetype":"venue"
},
  "geometry": {"coordinates":[-97.2713546753,49.8848419189],"type":"Point"}
}