{
  "type": "Feature",
  "properties": {
    "addr:full":"8 Des Pionniers Ch O Cap-Saint-Ignace QC G0R 1H0",
    "addr:housenumber":"8",
    "addr:postcode":"g0r 1h0",
    "addr:street":"Des Pionniers Ch O",
    "iso:country":"CA",
    "sg:address":"8 Des Pionniers Ch O",
    "sg:city":"Cap-Saint-Ignace",
    "sg:classifiers":[
        {
            "category":"Health Services",
            "subcategory":"Doctor",
            "type":"Services"
        }
    ],
    "sg:phone":"+1 418 246 5071",
    "sg:postcode":"G0R 1H0",
    "sg:province":"QC",
    "sg:tags":[
        "physician",
        "surgeon"
    ],
    "wof:name":"Proulx, Clement MD",
    "wof:placetype":"venue"
},
  "geometry": {"coordinates":[-70.45829000000001,47.036671],"type":"Point"}
}