{
  "type": "Feature",
  "properties": {
    "iso:country":"CA",
    "sg:city":"Terrace",
    "sg:classifiers":[
        {
            "category":"Retail",
            "subcategory":"Auto Repair",
            "type":"Services"
        }
    ],
    "sg:phone":"+1 250 635 8100",
    "sg:postcode":"V8G 1M5",
    "sg:province":"BC",
    "sg:tags":[
        "repairing",
        "automobile",
        "radiator"
    ],
    "wof:name":"Pinedale Radiator",
    "wof:placetype":"venue"
},
  "geometry": {"coordinates":[-128.583084106,54.5156402588],"type":"Point"}
}