{
  "type": "Feature",
  "properties": {
    "iso:country":"CA",
    "sg:address":"1617 5 Ave",
    "sg:city":"Wainwright",
    "sg:classifiers":[
        {
            "category":"Organizations",
            "subcategory":"Religious Organization",
            "type":"Services"
        }
    ],
    "sg:phone":"+1 780 842 4361",
    "sg:postcode":"T9W 1J3",
    "sg:province":"AB",
    "sg:tags":[
        "church"
    ],
    "wof:name":"Evangelical Free Church",
    "wof:placetype":"venue"
},
  "geometry": {"coordinates":[-110.846595764,52.8327674866],"type":"Point"}
}