{
  "type": "Feature",
  "properties": {
    "addr:full":"325 Pinedale Rd Gravenhurst ON P1P 1L8",
    "addr:housenumber":"325",
    "addr:postcode":"p1p 1l8",
    "addr:street":"Pinedale Rd",
    "iso:country":"CA",
    "sg:address":"325 Pinedale Rd",
    "sg:city":"Gravenhurst",
    "sg:classifiers":[
        {
            "category":"Utilities",
            "subcategory":"Electric",
            "type":"Services"
        }
    ],
    "sg:phone":"+1 705 687 6551",
    "sg:postcode":"P1P 1L8",
    "sg:province":"ON",
    "sg:tags":[
        "company"
    ],
    "wof:name":"Ontario Power Generation Inc",
    "wof:placetype":"venue"
},
  "geometry": {"coordinates":[-79.368347168,44.9153175354],"type":"Point"}
}