{
  "type": "Feature",
  "properties": {
    "iso:country":"CA",
    "sg:address":"835 Eastriver St",
    "sg:city":"New Glasgow",
    "sg:classifiers":[
        {
            "category":"Health Services",
            "subcategory":"Health Practitioner",
            "type":"Services"
        }
    ],
    "sg:phone":"+1 902 752 3184",
    "sg:postcode":"B2H 5C8",
    "sg:province":"NS",
    "sg:tags":[
        "physician",
        "nurse",
        "surgeon",
        "registry"
    ],
    "wof:name":"Von",
    "wof:placetype":"venue"
},
  "geometry": {"coordinates":[-62.6434135437,45.5918388367],"type":"Point"}
}