{
  "type": "Feature",
  "properties": {
    "iso:country":"CA",
    "sg:city":"Scarborough",
    "sg:classifiers":[
        {
            "category":"Home & Garden",
            "subcategory":"Furniture",
            "type":"Retail Goods"
        }
    ],
    "sg:phone":"+1 416 281 3978",
    "sg:postcode":"M1B 3L6",
    "sg:province":"ON",
    "sg:tags":[
        "cabinet"
    ],
    "wof:name":"King Component Ltd",
    "wof:placetype":"venue"
},
  "geometry": {"coordinates":[-79.199226,43.806751],"type":"Point"}
}