{
  "type": "Feature",
  "properties": {
    "addr:full":"Airdrie AB T4B 2B7",
    "addr:postcode":"t4b 2b7",
    "iso:country":"CA",
    "sg:city":"Airdrie",
    "sg:classifiers":[
        {
            "category":"Personal",
            "subcategory":"Barber",
            "type":"Services"
        }
    ],
    "sg:phone":"+1 403 948 5006",
    "sg:postcode":"T4B 2B7",
    "sg:province":"AB",
    "wof:name":"Main Street Barber Shop",
    "wof:placetype":"venue"
},
  "geometry": {"coordinates":[-114.013237,51.291718],"type":"Point"}
}