{
  "type": "Feature",
  "properties": {
    "iso:country":"CA",
    "sg:address":"16 Ontario St",
    "sg:city":"Stratford",
    "sg:classifiers":[
        {
            "category":"Shopping",
            "subcategory":"Jewelry",
            "type":"Retail Goods"
        }
    ],
    "sg:phone":"+1 519 272 2328",
    "sg:postcode":"N5A 3G8",
    "sg:province":"ON",
    "sg:tags":[
        "jeweler"
    ],
    "wof:name":"Konrad's Gold & Gems",
    "wof:placetype":"venue"
},
  "geometry": {"coordinates":[-80.9838027954,43.3716239929],"type":"Point"}
}