{
  "type": "Feature",
  "properties": {
    "addr:full":"429 William St London ON N6B 3E1",
    "addr:housenumber":"429",
    "addr:postcode":"n6b 3e1",
    "addr:street":"William St",
    "iso:country":"CA",
    "sg:address":"429 William St",
    "sg:city":"London",
    "sg:classifiers":[
        {
            "category":"Shopping",
            "subcategory":"Clothing, Apparel, & Fashions",
            "type":"Retail Goods"
        }
    ],
    "sg:phone":"+1 519 434 9315",
    "sg:postcode":"N6B 3E1",
    "sg:province":"ON",
    "sg:tags":[
        "dressmaker"
    ],
    "wof:name":"Martine Haute Couture",
    "wof:placetype":"venue"
},
  "geometry": {"coordinates":[-81.2345581055,42.9884376526],"type":"Point"}
}