{
  "type": "Feature",
  "properties": {
    "addr:full":"197 Boul J D Gauthier Shippagan NB E8S 1M9",
    "addr:housenumber":"197",
    "addr:postcode":"e8s 1m9",
    "addr:street":"Boul J D Gauthier Shippagan",
    "iso:country":"CA",
    "sg:address":"197 Boul J D Gauthier",
    "sg:city":"Shippagan",
    "sg:classifiers":[
        {
            "category":"Recreation",
            "type":"Entertainment"
        }
    ],
    "sg:phone":"+1 506 336 2272",
    "sg:postcode":"E8S 1M9",
    "sg:province":"NB",
    "sg:tags":[
        "parlor",
        "billiard"
    ],
    "wof:name":"Dooly's Shippagan",
    "wof:placetype":"venue"
},
  "geometry": {"coordinates":[-64.71425600000001,47.744598],"type":"Point"}
}