{
  "type": "Feature",
  "properties": {
    "addr:full":"253 3E Rue Shawinigan QC G9N 1H5",
    "addr:housenumber":"253",
    "addr:postcode":"g9n 1h5",
    "addr:street":"3E Rue",
    "iso:country":"CA",
    "sg:address":"253 3E Rue",
    "sg:city":"Shawinigan",
    "sg:classifiers":[
        {
            "category":"Organizations",
            "subcategory":"Non-profit Organization",
            "type":"Services"
        }
    ],
    "sg:phone":"+1 819 539 5225",
    "sg:postcode":"G9N 1H5",
    "sg:province":"QC",
    "sg:tags":[
        "breastfeeding",
        "information",
        "supply"
    ],
    "wof:name":"Allaitement Soleil",
    "wof:placetype":"venue"
},
  "geometry": {"coordinates":[-72.74527,46.53912],"type":"Point"}
}