{
  "type": "Feature",
  "properties": {
    "addr:full":"2 Carleton St St George NB E5C 3B3",
    "addr:housenumber":"2",
    "addr:postcode":"e5c 3b3",
    "addr:street":"Carleton St",
    "iso:country":"CA",
    "sg:address":"2 Carleton St",
    "sg:city":"St George",
    "sg:classifiers":[
        {
            "category":"Organizations",
            "subcategory":"Community Association",
            "type":"Services"
        }
    ],
    "sg:phone":"+1 506 755 2805",
    "sg:postcode":"E5C 3B3",
    "sg:province":"NB",
    "wof:name":"St George Masonic Lodge",
    "wof:placetype":"venue"
},
  "geometry": {"coordinates":[-66.82253300000001,45.128761],"type":"Point"}
}