{
  "type": "Feature",
  "properties": {
    "addr:full":"66032 Park Ave Hope BC V0X 1L1",
    "addr:housenumber":"66032",
    "addr:postcode":"v0x 1l1",
    "addr:street":"Park Ave",
    "iso:country":"CA",
    "sg:address":"66032 Park Ave",
    "sg:city":"Hope",
    "sg:classifiers":[
        {
            "category":"Professional",
            "subcategory":"Engineering",
            "type":"Services"
        }
    ],
    "sg:phone":"+1 604 869 7518",
    "sg:postcode":"V0X 1L1",
    "sg:province":"BC",
    "sg:tags":[
        "engineer"
    ],
    "wof:name":"Valley Surveys",
    "wof:placetype":"venue"
},
  "geometry": {"coordinates":[-121.40366400000001,49.382614],"type":"Point"}
}