{
  "type": "Feature",
  "properties": {
    "addr:full":"Kelowna BC V1Y 2K4",
    "addr:postcode":"v1y 2k4",
    "iso:country":"CA",
    "sg:city":"Kelowna",
    "sg:classifiers":[
        {
            "category":"Retail",
            "subcategory":"Portrait Studio",
            "type":"Services"
        }
    ],
    "sg:phone":"+1 250 868 2196",
    "sg:postcode":"V1Y 2K4",
    "sg:province":"BC",
    "sg:tags":[
        "photographer"
    ],
    "wof:name":"Free Spirit Studio",
    "wof:placetype":"venue"
},
  "geometry": {"coordinates":[-119.488456726,49.8976593018],"type":"Point"}
}