{
  "type": "Feature",
  "properties": {
    "iso:country":"CA",
    "sg:city":"Richmond",
    "sg:classifiers":[
        {
            "category":"Organizations",
            "subcategory":"Professional Association",
            "type":"Services"
        }
    ],
    "sg:phone":"+1 819 826 6166",
    "sg:postcode":"J0B 2H0",
    "sg:province":"QC",
    "wof:name":"Centre DE Benevolat DE Richmnd",
    "wof:placetype":"venue"
},
  "geometry": {"coordinates":[-72.1497421265,45.6679801941],"type":"Point"}
}