{
  "type": "Feature",
  "properties": {
    "addr:full":"10 Ryerson Ave Winnipeg MB R3T 3P9",
    "addr:housenumber":"10",
    "addr:postcode":"r3t 3p9",
    "addr:street":"Ryerson Ave",
    "iso:country":"CA",
    "sg:address":"10 Ryerson Ave",
    "sg:city":"Winnipeg",
    "sg:classifiers":[
        {
            "category":"Social Services",
            "subcategory":"Child Care",
            "type":"Services"
        }
    ],
    "sg:phone":"+1 204 261 5882",
    "sg:postcode":"R3T 3P9",
    "sg:province":"MB",
    "wof:name":"Ryerson School Age Ctr",
    "wof:placetype":"venue"
},
  "geometry": {"coordinates":[-97.1465,49.78548],"type":"Point"}
}