{
  "type": "Feature",
  "properties": {
    "addr:full":"95 D'Aubigny Rd Brantford ON N3T 6J4",
    "addr:housenumber":"95",
    "addr:postcode":"n3t 6j4",
    "addr:street":"D'Aubigny Rd",
    "iso:country":"CA",
    "sg:address":"95 D'Aubigny Rd",
    "sg:city":"Brantford",
    "sg:classifiers":[
        {
            "category":"Building & Trades",
            "subcategory":"Construction",
            "type":"Services"
        }
    ],
    "sg:phone":"+1 519 756 1310",
    "sg:postcode":"N3T 6J4",
    "sg:province":"ON",
    "sg:tags":[
        "painter"
    ],
    "wof:name":"Ace Contractors",
    "wof:placetype":"venue"
},
  "geometry": {"coordinates":[-80.30513000000001,43.128063],"type":"Point"}
}