{
  "type": "Feature",
  "properties": {
    "addr:full":"375 Rue Principale O Magog QC J1X 2B1",
    "addr:housenumber":"375",
    "addr:postcode":"j1x 2b1",
    "addr:street":"Rue Principale O",
    "iso:country":"CA",
    "sg:address":"375 Rue Principale O",
    "sg:city":"Magog",
    "sg:classifiers":[
        {
            "category":"Organizations",
            "subcategory":"Professional Association",
            "type":"Services"
        }
    ],
    "sg:phone":"+1 819 868 6779",
    "sg:postcode":"J1X 2B1",
    "sg:province":"QC",
    "wof:name":"Societe D'Histoire DE Magog",
    "wof:placetype":"venue"
},
  "geometry": {"coordinates":[-72.137016,45.262203],"type":"Point"}
}