{
  "type": "Feature",
  "properties": {
    "iso:country":"CA",
    "sg:address":"2010 Harrison",
    "sg:city":"Masset",
    "sg:phone":"+1 250 626 3328",
    "sg:postcode":"V0T 1M0",
    "sg:province":"BC",
    "sg:tags":[
        "oil"
    ],
    "wof:name":"North Arm Transportation Ltd",
    "wof:placetype":"venue"
},
  "geometry": {"coordinates":[-132.14662170400001,54.0094146729],"type":"Point"}
}