{
  "type": "Feature",
  "properties": {
    "addr:full":"Sparwood BC V0B 2G0",
    "addr:postcode":"bc v0b 2g0",
    "iso:country":"CA",
    "sg:city":"Sparwood",
    "sg:classifiers":[
        {
            "category":"Autos & Motor Vehicles",
            "subcategory":"Auto Supplies",
            "type":"Retail Goods"
        }
    ],
    "sg:phone":"+1 250 425 2077",
    "sg:postcode":"V0B 2G0",
    "sg:province":"BC",
    "sg:tags":[
        "automobile",
        "parts"
    ],
    "wof:name":"Uap Napa Auto Parts",
    "wof:placetype":"venue"
},
  "geometry": {"coordinates":[-114.89411926299999,49.7166099548],"type":"Point"}
}