{
  "type": "Feature",
  "properties": {
    "addr:full":"7171 Rue Bombardier Anjou QC H1J 2E9",
    "addr:housenumber":"7171",
    "addr:postcode":"h1j 2e9",
    "addr:street":"Rue Bombardier",
    "iso:country":"CA",
    "sg:address":"7171 Rue Bombardier",
    "sg:city":"Anjou",
    "sg:classifiers":[
        {
            "category":"Government",
            "subcategory":"Office",
            "type":"Public Place"
        }
    ],
    "sg:phone":"+1 514 493 5161",
    "sg:postcode":"H1J 2E9",
    "sg:province":"QC",
    "sg:tags":[
        "village"
    ],
    "wof:name":"Anjou Approvisionnements",
    "wof:placetype":"venue"
},
  "geometry": {"coordinates":[-73.58566999999999,45.607338],"type":"Point"}
}