{
  "type": "Feature",
  "properties": {
    "addr:full":"3015 Gordon Rd Regina SK S4S 6H7",
    "addr:housenumber":"3015",
    "addr:postcode":"s4s 6h7",
    "addr:street":"Gordon Rd",
    "iso:country":"CA",
    "sg:address":"3015 Gordon Rd",
    "sg:city":"Regina",
    "sg:classifiers":[
        {
            "category":"Shopping",
            "subcategory":"Clothing, Apparel, & Fashions",
            "type":"Retail Goods"
        }
    ],
    "sg:phone":"+1 306 584 0766",
    "sg:postcode":"S4S 6H7",
    "sg:province":"SK",
    "wof:name":"Tabi International",
    "wof:placetype":"venue"
},
  "geometry": {"coordinates":[-104.62443500000001,50.404755],"type":"Point"}
}