{
  "type": "Feature",
  "properties": {
    "addr:full":"Digby NS B0V 1A0",
    "addr:postcode":"b0v 1a0",
    "iso:country":"CA",
    "sg:city":"Digby",
    "sg:classifiers":[
        {
            "category":"Restaurant",
            "type":"Food & Drink"
        }
    ],
    "sg:phone":"+1 902 245 5411",
    "sg:postcode":"B0V 1A0",
    "sg:province":"NS",
    "wof:name":"Royal Fundy Fish Market",
    "wof:placetype":"venue"
},
  "geometry": {"coordinates":[-65.75505099999999,44.626709],"type":"Point"}
}