{
  "type": "Feature",
  "properties": {
    "addr:full":"121 Rue Saint-Aime Louiseville QC J5V 2B2",
    "addr:housenumber":"121",
    "addr:postcode":"j5v 2b2",
    "addr:street":"Rue Saint-Aime",
    "iso:country":"CA",
    "sg:address":"121 Rue Saint-Aime",
    "sg:city":"Louiseville",
    "sg:classifiers":[
        {
            "category":"Bars & Pubs",
            "type":"Food & Drink"
        }
    ],
    "sg:phone":"+1 819 228 2909",
    "sg:postcode":"J5V 2B2",
    "sg:province":"QC",
    "sg:tags":[
        "tattooing"
    ],
    "wof:name":"Taverne Jm",
    "wof:placetype":"venue"
},
  "geometry": {"coordinates":[-72.94354199999999,46.257599],"type":"Point"}
}