{
  "type": "Feature",
  "properties": {
    "addr:full":"4165 Kahn Rd Cranbrook BC V1C 6S8",
    "addr:housenumber":"4165",
    "addr:postcode":"bc v1c 6s8",
    "addr:street":"Kahn Rd",
    "iso:country":"CA",
    "sg:address":"4165 Kahn Rd",
    "sg:city":"Cranbrook",
    "sg:classifiers":[
        {
            "category":"Retail",
            "subcategory":"Repair Shop",
            "type":"Services"
        }
    ],
    "sg:phone":"+1 250 426 7359",
    "sg:postcode":"V1C 6S8",
    "sg:province":"BC",
    "sg:tags":[
        "taxidermist"
    ],
    "wof:name":"Maurer's Taxidermy",
    "wof:placetype":"venue"
},
  "geometry": {"coordinates":[-115.768699646,49.5135002136],"type":"Point"}
}