{
  "type": "Feature",
  "properties": {
    "addr:full":"220 Rue Principale Saint-Gabriel-DE-Rimouski QC G0K 1M0",
    "addr:housenumber":"220",
    "addr:postcode":"g0k 1m0",
    "addr:street":"Rue Principale",
    "iso:country":"CA",
    "sg:address":"220 Rue Principale",
    "sg:city":"Saint-Gabriel-DE-Rimouski",
    "sg:classifiers":[
        {
            "category":"Manufacturing",
            "subcategory":"Lumber",
            "type":"Manufacturing & Wholesale Goods"
        }
    ],
    "sg:phone":"+1 418 798 8851",
    "sg:postcode":"G0K 1M0",
    "sg:province":"QC",
    "sg:tags":[
        "forester"
    ],
    "wof:name":"Societe D'Exploitation",
    "wof:placetype":"venue"
},
  "geometry": {"coordinates":[-68.15819500000001,48.434483],"type":"Point"}
}