{
  "type": "Feature",
  "properties": {
    "addr:full":"963 Warbler Bay Orleans ON K1E 2A3",
    "addr:housenumber":"963",
    "addr:postcode":"k1e 2a3",
    "addr:street":"Warbler Bay",
    "iso:country":"CA",
    "sg:address":"963 Warbler Bay",
    "sg:city":"Orleans",
    "sg:classifiers":[
        {
            "category":"Building & Trades",
            "subcategory":"Landscaping Services",
            "type":"Services"
        }
    ],
    "sg:phone":"+1 613 830 3157",
    "sg:postcode":"K1E 2A3",
    "sg:province":"ON",
    "sg:tags":[
        "landscape",
        "contractor"
    ],
    "wof:name":"Eastern Valley Landscaping Inc",
    "wof:placetype":"venue"
},
  "geometry": {"coordinates":[-75.509041,45.485371],"type":"Point"}
}