{
  "type": "Feature",
  "properties": {
    "addr:full":"1877 Eglinton Ave W York ON M6E 2J5",
    "addr:housenumber":"1877",
    "addr:postcode":"m6e 2j5",
    "addr:street":"Eglinton Ave W",
    "iso:country":"CA",
    "sg:address":"1877 Eglinton Ave W",
    "sg:city":"York",
    "sg:classifiers":[
        {
            "category":"Home & Garden",
            "subcategory":"Furniture",
            "type":"Retail Goods"
        }
    ],
    "sg:phone":"+1 416 782 0793",
    "sg:postcode":"M6E 2J5",
    "sg:province":"ON",
    "wof:name":"Dynevor Furniture & Appls Ltd",
    "wof:placetype":"venue"
},
  "geometry": {"coordinates":[-79.45127100000001,43.695415],"type":"Point"}
}