{
  "type": "Feature",
  "properties": {
    "iso:country":"CA",
    "sg:city":"Vancouver",
    "sg:classifiers":[
        {
            "category":"Professional",
            "subcategory":"Business Services",
            "type":"Services"
        }
    ],
    "sg:phone":"+1 604 873 6772",
    "sg:postcode":"V5Y 1K1",
    "sg:province":"BC",
    "sg:tags":[
        "embroidery"
    ],
    "wof:name":"Western Embroidery CO",
    "wof:placetype":"venue"
},
  "geometry": {"coordinates":[-123.106216,49.265476],"type":"Point"}
}