{
  "type": "Feature",
  "properties": {
    "addr:full":"425 Place Jacques-Cartier #300 Montreal QC H2Y 3B1",
    "addr:housenumber":"425",
    "addr:postcode":"h2y 3b1",
    "addr:street":"Place Jacques-Cartier # 300",
    "iso:country":"CA",
    "sg:address":"425 Place Jacques-Cartier #300",
    "sg:city":"Montreal",
    "sg:classifiers":[
        {
            "category":"Professional",
            "subcategory":"Computer Services",
            "type":"Services"
        }
    ],
    "sg:phone":"+1 514 399 9999",
    "sg:postcode":"H2Y 3B1",
    "sg:province":"QC",
    "sg:tags":[
        "information",
        "system",
        "consultant"
    ],
    "wof:name":"Gestisoft",
    "wof:placetype":"venue"
},
  "geometry": {"coordinates":[-73.55280303959999,45.5080375671],"type":"Point"}
}