{
  "type": "Feature",
  "properties": {
    "addr:full":"2721 Jane St North York ON M3L 1S3",
    "addr:housenumber":"2721",
    "addr:postcode":"m3l 1s3",
    "addr:street":"Jane St",
    "iso:country":"CA",
    "sg:address":"2721 Jane St",
    "sg:city":"North York",
    "sg:classifiers":[
        {
            "category":"Personal",
            "subcategory":"Beauty Salon",
            "type":"Services"
        }
    ],
    "sg:phone":"+1 416 743 0133",
    "sg:postcode":"M3L 1S3",
    "sg:province":"ON",
    "wof:name":"Hair Plus",
    "wof:placetype":"venue"
},
  "geometry": {"coordinates":[-79.5132980347,43.7405166626],"type":"Point"}
}