{
  "type": "Feature",
  "properties": {
    "iso:country":"CA",
    "sg:address":"16 Rue Racine E",
    "sg:city":"Chicoutimi",
    "sg:classifiers":[
        {
            "category":"Shopping",
            "subcategory":"Used Merchandise",
            "type":"Retail Goods"
        }
    ],
    "sg:phone":"+1 418 693 0965",
    "sg:postcode":"G7H 1P5",
    "sg:province":"QC",
    "sg:tags":[
        "antique"
    ],
    "wof:name":"Grenier DE Mon Pere",
    "wof:placetype":"venue"
},
  "geometry": {"coordinates":[-71.067909,48.427872],"type":"Point"}
}