{
  "type": "Feature",
  "properties": {
    "addr:full":"9350 Highway 48 Markham ON L3P 3J3",
    "addr:housenumber":"9350",
    "addr:postcode":"l3p 3j3",
    "addr:street":"Highway 48",
    "iso:country":"CA",
    "sg:address":"9350 Highway 48",
    "sg:city":"Markham",
    "sg:classifiers":[
        {
            "category":"Museum",
            "type":"Entertainment"
        }
    ],
    "sg:phone":"+1 905 294 4576",
    "sg:postcode":"L3P 3J3",
    "sg:province":"ON",
    "sg:tags":[
        "government"
    ],
    "wof:name":"Markham Museum",
    "wof:placetype":"venue"
},
  "geometry": {"coordinates":[-79.33994300000001,43.856033],"type":"Point"}
}