{
  "type": "Feature",
  "properties": {
    "addr:full":"375 Horton St E London ON N6B 1L6",
    "addr:housenumber":"375",
    "addr:postcode":"n6b 1l6",
    "addr:street":"Horton St E",
    "iso:country":"CA",
    "sg:address":"375 Horton St E",
    "sg:city":"London",
    "sg:classifiers":[
        {
            "category":"Restaurant",
            "type":"Food & Drink"
        }
    ],
    "sg:phone":"+1 519 434 8787",
    "sg:postcode":"N6B 1L6",
    "sg:province":"ON",
    "wof:name":"Kambie Chinese Restaurant",
    "wof:placetype":"venue"
},
  "geometry": {"coordinates":[-81.23821258540001,42.9813079834],"type":"Point"}
}