{
  "type": "Feature",
  "properties": {
    "addr:full":"Louiseville QC J5V 1H4",
    "addr:postcode":"j5v 1h4",
    "iso:country":"CA",
    "sg:city":"Louiseville",
    "sg:classifiers":[
        {
            "category":"Health Services",
            "subcategory":"Doctor",
            "type":"Services"
        }
    ],
    "sg:phone":"+1 819 228 7171",
    "sg:postcode":"J5V 1H4",
    "sg:province":"QC",
    "sg:tags":[
        "clinic"
    ],
    "wof:name":"Clinique Medicale St-Laurent",
    "wof:placetype":"venue"
},
  "geometry": {"coordinates":[-72.9360733032,46.256072998],"type":"Point"}
}