{
  "type": "Feature",
  "properties": {
    "iso:country":"CA",
    "sg:address":"335 7th Ave",
    "sg:city":"Regina",
    "sg:classifiers":[
        {
            "category":"Building & Trades",
            "subcategory":"Construction",
            "type":"Services"
        }
    ],
    "sg:phone":"+1 306 949 8411",
    "sg:postcode":"S4N 5B8",
    "sg:province":"SK",
    "sg:tags":[
        "pile",
        "driving"
    ],
    "wof:name":"Agra Foundations Ltd",
    "wof:placetype":"venue"
},
  "geometry": {"coordinates":[-104.58565521200001,50.4581604004],"type":"Point"}
}