{
  "type": "Feature",
  "properties": {
    "iso:country":"CA",
    "sg:address":"81 Ponderosa Cres",
    "sg:city":"London",
    "sg:classifiers":[
        {
            "category":"Professional",
            "subcategory":"Business Services",
            "type":"Services"
        }
    ],
    "sg:phone":"+1 519 680 7939",
    "sg:postcode":"N6E 2L5",
    "sg:province":"ON",
    "sg:tags":[
        "water",
        "treatment"
    ],
    "wof:name":"Phoenix Environmental Techs",
    "wof:placetype":"venue"
},
  "geometry": {"coordinates":[-81.2314605713,42.9376106262],"type":"Point"}
}