{
  "type": "Feature",
  "properties": {
    "addr:full":"6242 Pitton Rd Niagara Falls ON L2H 1S3",
    "addr:housenumber":"6242",
    "addr:postcode":"l2h 1s3",
    "addr:street":"Pitton Rd",
    "iso:country":"CA",
    "sg:address":"6242 Pitton Rd",
    "sg:city":"Niagara Falls",
    "sg:classifiers":[
        {
            "category":"Building & Trades",
            "subcategory":"Electrical",
            "type":"Services"
        }
    ],
    "sg:phone":"+1 905 356 0515",
    "sg:postcode":"L2H 1S3",
    "sg:province":"ON",
    "sg:tags":[
        "electric",
        "contractor"
    ],
    "wof:name":"Westlane Electric",
    "wof:placetype":"venue"
},
  "geometry": {"coordinates":[-79.132034,43.083431],"type":"Point"}
}