{
  "type": "Feature",
  "properties": {
    "addr:full":"600 18E Av Lachine QC H8S 3R4",
    "addr:housenumber":"600",
    "addr:postcode":"h8s 3r4",
    "addr:street":"18E Av",
    "iso:country":"CA",
    "sg:address":"600 18E Av",
    "sg:city":"Lachine",
    "sg:classifiers":[
        {
            "category":"Social Services",
            "type":"Services"
        }
    ],
    "sg:phone":"+1 514 637 8425",
    "sg:postcode":"H8S 3R4",
    "sg:province":"QC",
    "sg:tags":[
        "home",
        "senior",
        "retirement",
        "community",
        "citizen"
    ],
    "wof:name":"Residence Marguerite",
    "wof:placetype":"venue"
},
  "geometry": {"coordinates":[-73.680015564,45.4401397705],"type":"Point"}
}