{
  "type": "Feature",
  "properties": {
    "addr:full":"156 Highland Rd W Stoney Creek ON L8J 2S6",
    "addr:housenumber":"156",
    "addr:postcode":"l8j 2s6",
    "addr:street":"Highland Rd W",
    "iso:country":"CA",
    "sg:address":"156 Highland Rd W",
    "sg:city":"Stoney Creek",
    "sg:classifiers":[
        {
            "category":"Wholesale",
            "subcategory":"Construction Materials",
            "type":"Manufacturing & Wholesale Goods"
        }
    ],
    "sg:phone":"+1 905 561 6734",
    "sg:postcode":"L8J 2S6",
    "sg:province":"ON",
    "sg:tags":[
        "fence"
    ],
    "wof:name":"Ehler Contracting Inc",
    "wof:placetype":"venue"
},
  "geometry": {"coordinates":[-79.78368377690001,43.184009552],"type":"Point"}
}