{
  "type": "Feature",
  "properties": {
    "addr:full":"288 Balfour Ave Winnipeg MB R3L 1N6",
    "addr:housenumber":"288",
    "addr:postcode":"r3l 1n6",
    "addr:street":"Balfour Ave",
    "iso:country":"CA",
    "sg:address":"288 Balfour Ave",
    "sg:city":"Winnipeg",
    "sg:classifiers":[
        {
            "category":"Building & Trades",
            "subcategory":"Construction",
            "type":"Services"
        }
    ],
    "sg:phone":"+1 204 452 5725",
    "sg:postcode":"R3L 1N6",
    "sg:province":"MB",
    "sg:tags":[
        "general",
        "contractor"
    ],
    "wof:name":"Consolidated Design & Build",
    "wof:placetype":"venue"
},
  "geometry": {"coordinates":[-97.1269454956,49.8612060547],"type":"Point"}
}