{
  "type": "Feature",
  "properties": {
    "iso:country":"CA",
    "sg:address":"NE 1/4 121223 W of 1/4",
    "sg:city":"Barons",
    "sg:classifiers":[
        {
            "category":"Education",
            "subcategory":"School",
            "type":"Public Place"
        }
    ],
    "sg:phone":"+1 403 757 2100",
    "sg:postcode":"T0L 0G0",
    "sg:province":"AB",
    "wof:name":"Keho Lake School",
    "wof:placetype":"venue"
},
  "geometry": {"coordinates":[-113.087234497,49.9989395142],"type":"Point"}
}