{
  "type": "Feature",
  "properties": {
    "addr:full":"London ON N6A 5J7",
    "addr:postcode":"n6a 5j7",
    "iso:country":"CA",
    "sg:city":"London",
    "sg:classifiers":[
        {
            "category":"Professional",
            "subcategory":"Lawyer & Legal Services",
            "type":"Services"
        }
    ],
    "sg:phone":"+1 519 439 4015",
    "sg:postcode":"N6A 5J7",
    "sg:province":"ON",
    "sg:tags":[
        "attorney"
    ],
    "wof:name":"Corrigan, Edward C",
    "wof:placetype":"venue"
},
  "geometry": {"coordinates":[-81.25003100000001,42.984947],"type":"Point"}
}