{
  "type": "Feature",
  "properties": {
    "addr:full":"237 Second St Midland ON L4R 3P7",
    "addr:housenumber":"237",
    "addr:postcode":"l4r 3p7",
    "addr:street":"Second St",
    "iso:country":"CA",
    "sg:address":"237 Second St",
    "sg:city":"Midland",
    "sg:classifiers":[
        {
            "category":"Health Services",
            "subcategory":"Hospital",
            "type":"Services"
        }
    ],
    "sg:phone":"+1 705 526 1305",
    "sg:postcode":"L4R 3P7",
    "sg:province":"ON",
    "sg:tags":[
        "mental"
    ],
    "wof:name":"Wendat Community Support Progm",
    "wof:placetype":"venue"
},
  "geometry": {"coordinates":[-79.8889007568,44.7500991821],"type":"Point"}
}