{
  "type": "Feature",
  "properties": {
    "addr:full":"Saint-Felix-DE-Valois QC J0K 2M0",
    "addr:postcode":"j0k 2m0",
    "iso:country":"CA",
    "sg:city":"Saint-Felix-DE-Valois",
    "sg:classifiers":[
        {
            "category":"Health Services",
            "subcategory":"Health Practitioner",
            "type":"Services"
        }
    ],
    "sg:phone":"+1 450 889 5577",
    "sg:postcode":"J0K 2M0",
    "sg:province":"QC",
    "sg:tags":[
        "psychologist"
    ],
    "wof:name":"Chamberland, Doris",
    "wof:placetype":"venue"
},
  "geometry": {"coordinates":[-73.4315567017,46.1544380188],"type":"Point"}
}