{
  "type": "Feature",
  "properties": {
    "addr:full":"12395 Rue Lachapelle Montreal QC H4J 2P7",
    "addr:housenumber":"12395",
    "addr:postcode":"h4j 2p7",
    "addr:street":"Rue Lachapelle",
    "iso:country":"CA",
    "sg:address":"12395 Rue Lachapelle",
    "sg:city":"Montreal",
    "sg:classifiers":[
        {
            "category":"Restaurant",
            "type":"Food & Drink"
        }
    ],
    "sg:phone":"+1 514 337 4980",
    "sg:postcode":"H4J 2P7",
    "sg:province":"QC",
    "wof:name":"Rotisserie St-Hubert",
    "wof:placetype":"venue"
},
  "geometry": {"coordinates":[-73.7221298218,45.5314025879],"type":"Point"}
}