{
  "type": "Feature",
  "properties": {
    "addr:full":"Fredericton NB E3B 5X8",
    "addr:postcode":"e3b 5x8",
    "iso:country":"CA",
    "sg:city":"Fredericton",
    "sg:classifiers":[
        {
            "category":"Health Services",
            "subcategory":"Doctor",
            "type":"Services"
        }
    ],
    "sg:phone":"+1 506 450 4867",
    "sg:postcode":"E3B 5X8",
    "sg:province":"NB",
    "sg:tags":[
        "dentist"
    ],
    "wof:name":"Mkd Holdings",
    "wof:placetype":"venue"
},
  "geometry": {"coordinates":[-66.6573562622,45.941619873],"type":"Point"}
}