{
  "type": "Feature",
  "properties": {
    "addr:full":"3279 Chaucer Ave North Vancouver BC V7K 2C2",
    "addr:housenumber":"3279",
    "addr:postcode":"v7k 2c2",
    "addr:street":"Chaucer Ave",
    "iso:country":"CA",
    "sg:address":"3279 Chaucer Ave",
    "sg:city":"North Vancouver",
    "sg:classifiers":[
        {
            "category":"Professional",
            "subcategory":"Accounting & Tax Preparation",
            "type":"Services"
        }
    ],
    "sg:phone":"+1 604 984 7583",
    "sg:postcode":"V7K 2C2",
    "sg:province":"BC",
    "sg:tags":[
        "accountant"
    ],
    "wof:name":"Dixon, J Lea",
    "wof:placetype":"venue"
},
  "geometry": {"coordinates":[-123.045257568,49.3394546509],"type":"Point"}
}