{
  "type": "Feature",
  "properties": {
    "addr:full":"9520 Rue Main Richibucto NB E4W 4E4",
    "addr:housenumber":"9520",
    "addr:postcode":"e4w 4e4",
    "addr:street":"Rue Main",
    "iso:country":"CA",
    "sg:address":"9520 Rue Main",
    "sg:city":"Richibucto",
    "sg:classifiers":[
        {
            "category":"Retail",
            "subcategory":"Auto Repair",
            "type":"Services"
        }
    ],
    "sg:phone":"+1 506 523 9098",
    "sg:postcode":"E4W 4E4",
    "sg:province":"NB",
    "sg:tags":[
        "repairing",
        "automobile"
    ],
    "wof:name":"Jgp Garage Ltd",
    "wof:placetype":"venue"
},
  "geometry": {"coordinates":[-64.8677444458,46.6923141479],"type":"Point"}
}