{
  "type": "Feature",
  "properties": {
    "addr:full":"Winnipeg MB R2W 3E4",
    "addr:postcode":"r2w 3e4",
    "iso:country":"CA",
    "sg:city":"Winnipeg",
    "sg:classifiers":[
        {
            "category":"Manufacturing",
            "subcategory":"Metals",
            "type":"Manufacturing & Wholesale Goods"
        }
    ],
    "sg:phone":"+1 204 946 5223",
    "sg:postcode":"R2W 3E4",
    "sg:province":"MB",
    "sg:tags":[
        "welding"
    ],
    "wof:name":"Ed's Wrought Iron Welding",
    "wof:placetype":"venue"
},
  "geometry": {"coordinates":[-97.131165,49.906193],"type":"Point"}
}