{
  "type": "Feature",
  "properties": {
    "addr:full":"1755 Burlington St E Hamilton ON L8H 3L5",
    "addr:housenumber":"1755",
    "addr:postcode":"l8h 3l5",
    "addr:street":"Burlington St E",
    "iso:country":"CA",
    "sg:address":"1755 Burlington St E",
    "sg:city":"Hamilton",
    "sg:classifiers":[
        {
            "category":"Wholesale",
            "subcategory":"Machinery & Supplies",
            "type":"Manufacturing & Wholesale Goods"
        }
    ],
    "sg:phone":"+1 905 547 1951",
    "sg:postcode":"L8H 3L5",
    "sg:province":"ON",
    "sg:tags":[
        "valve"
    ],
    "wof:name":"Crane Supply",
    "wof:placetype":"venue"
},
  "geometry": {"coordinates":[-79.789536,43.25713],"type":"Point"}
}