{
  "type": "Feature",
  "properties": {
    "iso:country":"CA",
    "sg:address":"373 Roachville Rd",
    "sg:city":"Roachville",
    "sg:classifiers":[
        {
            "category":"Building & Trades",
            "subcategory":"Construction",
            "type":"Services"
        }
    ],
    "sg:phone":"+1 506 433 1366",
    "sg:postcode":"E4G 2K1",
    "sg:province":"NB",
    "sg:tags":[
        "contractor"
    ],
    "wof:name":"Professional Builders Ltd",
    "wof:placetype":"venue"
},
  "geometry": {"coordinates":[-65.53968811039999,45.7306098938],"type":"Point"}
}