{
  "type": "Feature",
  "properties": {
    "addr:full":"2397 Rue Alice Baie-Comeau QC G5C 1B1",
    "addr:housenumber":"2397",
    "addr:postcode":"g5c 1b1",
    "addr:street":"Rue Alice",
    "iso:country":"CA",
    "sg:address":"2397 Rue Alice",
    "sg:city":"Baie-Comeau",
    "sg:classifiers":[
        {
            "category":"Building & Trades",
            "subcategory":"Construction",
            "type":"Services"
        }
    ],
    "sg:phone":"+1 418 589 4778",
    "sg:postcode":"G5C 1B1",
    "sg:province":"QC",
    "sg:tags":[
        "masonry",
        "contractor"
    ],
    "wof:name":"Maconnerie Mingan Inc",
    "wof:placetype":"venue"
},
  "geometry": {"coordinates":[-68.2916030884,49.1951446533],"type":"Point"}
}