{
  "type": "Feature",
  "properties": {
    "addr:full":"990 Boul Saint-Luc Saint-Luc QC J2W 2G6",
    "addr:housenumber":"990",
    "addr:postcode":"j2w 2g6",
    "addr:street":"Boul Saint-Luc",
    "iso:country":"CA",
    "sg:address":"990 Boul Saint-Luc",
    "sg:city":"Saint-Luc",
    "sg:classifiers":[
        {
            "category":"Manufacturing",
            "subcategory":"Tools & Machinery",
            "type":"Manufacturing & Wholesale Goods"
        }
    ],
    "sg:phone":"+1 450 349 0027",
    "sg:postcode":"J2W 2G6",
    "sg:province":"QC",
    "sg:tags":[
        "contractor"
    ],
    "wof:name":"Pompe Hydraulique Levesque Inc",
    "wof:placetype":"venue"
},
  "geometry": {"coordinates":[-73.358833,45.37561],"type":"Point"}
}