{
  "type": "Feature",
  "properties": {
    "addr:full":"198 Donaldson St Shaughnessy AB T0K 2A0",
    "addr:housenumber":"198",
    "addr:postcode":"t0k 2a0",
    "addr:street":"Donaldson St",
    "iso:country":"CA",
    "sg:address":"198 Donaldson St",
    "sg:city":"Shaughnessy",
    "sg:classifiers":[
        {
            "category":"Travel",
            "subcategory":"Hotels & Motels",
            "type":"Entertainment"
        }
    ],
    "sg:phone":"+1 403 381 3220",
    "sg:postcode":"T0K 2A0",
    "sg:province":"AB",
    "wof:name":"Shaughnessy Hotel Ltd",
    "wof:placetype":"venue"
},
  "geometry": {"coordinates":[-112.84618377699999,49.8608512878],"type":"Point"}
}