{
  "type": "Feature",
  "properties": {
    "addr:full":"1249 Rue DE Conde Montreal QC H3K 2E4",
    "addr:housenumber":"1249",
    "addr:postcode":"h3k 2e4",
    "addr:street":"Rue De Conde",
    "iso:country":"CA",
    "sg:address":"1249 Rue DE Conde",
    "sg:city":"Montreal",
    "sg:classifiers":[
        {
            "category":"Building & Trades",
            "subcategory":"Pest Control",
            "type":"Services"
        }
    ],
    "sg:phone":"+1 514 937 6565",
    "sg:postcode":"H3K 2E4",
    "sg:province":"QC",
    "sg:tags":[
        "deodorizing",
        "disinfecting"
    ],
    "wof:name":"Airex Manufacturing",
    "wof:placetype":"venue"
},
  "geometry": {"coordinates":[-73.5591430664,45.4859428406],"type":"Point"}
}