{
  "type": "Feature",
  "properties": {
    "addr:full":"263 Lakeshore Rd E Oakville ON L6J 1H9",
    "addr:housenumber":"263",
    "addr:postcode":"l6j 1h9",
    "addr:street":"Lakeshore Rd E",
    "iso:country":"CA",
    "sg:address":"263 Lakeshore Rd E",
    "sg:city":"Oakville",
    "sg:classifiers":[
        {
            "category":"Restaurant",
            "type":"Food & Drink"
        }
    ],
    "sg:phone":"+1 905 842 2906",
    "sg:postcode":"L6J 1H9",
    "sg:province":"ON",
    "wof:name":"Trattoria IL Timone",
    "wof:placetype":"venue"
},
  "geometry": {"coordinates":[-79.66703,43.447079],"type":"Point"}
}