{
  "type": "Feature",
  "properties": {
    "addr:full":"415 1 St SE High River AB T1V 1G2",
    "addr:housenumber":"415 1",
    "addr:postcode":"t1v 1g2",
    "addr:street":"St Se",
    "iso:country":"CA",
    "sg:address":"415 1 St SE",
    "sg:city":"High River",
    "sg:classifiers":[
        {
            "category":"Real Estate",
            "subcategory":"Real Estate Agent",
            "type":"Services"
        }
    ],
    "sg:phone":"+1 403 652 3432",
    "sg:postcode":"T1V 1G2",
    "sg:province":"AB",
    "wof:name":"Lenchucha, Todd",
    "wof:placetype":"venue"
},
  "geometry": {"coordinates":[-113.868537903,50.5791664124],"type":"Point"}
}