{
  "type": "Feature",
  "properties": {
    "iso:country":"CA",
    "sg:address":"Hwy 22 E",
    "sg:city":"Esterhazy",
    "sg:classifiers":[
        {
            "category":"Manufacturing",
            "subcategory":"Tools & Machinery",
            "type":"Manufacturing & Wholesale Goods"
        }
    ],
    "sg:phone":"+1 306 745 2240",
    "sg:postcode":"S0A 0X0",
    "sg:province":"SK",
    "sg:tags":[
        "equipment",
        "product",
        "industrial",
        "manufacturer",
        "supply"
    ],
    "wof:name":"Welco Expediting Ltd",
    "wof:placetype":"venue"
},
  "geometry": {"coordinates":[-102.088378906,50.6539611816],"type":"Point"}
}