{
  "type": "Feature",
  "properties": {
    "addr:full":"134 Dufferin St Lunenburg NS B0J 2C0",
    "addr:housenumber":"134",
    "addr:postcode":"b0j 2c0",
    "addr:street":"Dufferin St",
    "iso:country":"CA",
    "sg:address":"134 Dufferin St",
    "sg:city":"Lunenburg",
    "sg:classifiers":[
        {
            "category":"Taxi",
            "type":"Transportation"
        }
    ],
    "sg:phone":"+1 902 634 3037",
    "sg:postcode":"B0J 2C0",
    "sg:province":"NS",
    "sg:tags":[
        "taxicab"
    ],
    "wof:name":"D K's Taxi",
    "wof:placetype":"venue"
},
  "geometry": {"coordinates":[-64.32144927980001,44.3814849854],"type":"Point"}
}