{
  "type": "Feature",
  "properties": {
    "iso:country":"CA",
    "sg:address":"1038 Ch Du Rivage",
    "sg:city":"Saint-Antoine-Sur-Richelieu",
    "sg:classifiers":[
        {
            "category":"Food & Beverages",
            "subcategory":"Groceries & Convenience Stores",
            "type":"Retail Goods"
        }
    ],
    "sg:phone":"+1 450 787 2446",
    "sg:postcode":"J0L 1R0",
    "sg:province":"QC",
    "sg:tags":[
        "grocer"
    ],
    "wof:name":"Marche St-Antoine",
    "wof:placetype":"venue"
},
  "geometry": {"coordinates":[-73.1724395752,45.7787055969],"type":"Point"}
}