{
  "type": "Feature",
  "properties": {
    "addr:full":"2249 Granite Ave Merritt BC V1K 1B8",
    "addr:housenumber":"2249",
    "addr:postcode":"v1k 1b8",
    "addr:street":"Granite Ave",
    "iso:country":"CA",
    "sg:address":"2249 Granite Ave",
    "sg:city":"Merritt",
    "sg:classifiers":[
        {
            "category":"Professional",
            "subcategory":"Accounting & Tax Preparation",
            "type":"Services"
        }
    ],
    "sg:phone":"+1 250 378 4695",
    "sg:postcode":"V1K 1B8",
    "sg:province":"BC",
    "sg:tags":[
        "return",
        "filing"
    ],
    "wof:name":"H & R Block Canada Inc",
    "wof:placetype":"venue"
},
  "geometry": {"coordinates":[-120.783394,50.109718],"type":"Point"}
}