{
  "type": "Feature",
  "properties": {
    "addr:full":"RR 1 DE Winton AB T0L 0X0",
    "addr:postcode":"t0l 0x0",
    "addr:street":"Rr 1 De Winton",
    "iso:country":"CA",
    "sg:address":"RR 1",
    "sg:city":"DE Winton",
    "sg:classifiers":[
        {
            "category":"Building & Trades",
            "subcategory":"Construction",
            "type":"Services"
        }
    ],
    "sg:phone":"+1 403 256 7015",
    "sg:postcode":"T0L 0X0",
    "sg:province":"AB",
    "sg:tags":[
        "excavating",
        "contractor"
    ],
    "wof:name":"Wire Construction Ltd",
    "wof:placetype":"venue"
},
  "geometry": {"coordinates":[-114.01475499999999,50.822979],"type":"Point"}
}