{
  "type": "Feature",
  "properties": {
    "addr:full":"RR 1 Norwich ON N0J 1P0",
    "addr:postcode":"n0j 1p0",
    "addr:street":"Rr 1",
    "iso:country":"CA",
    "sg:address":"RR 1",
    "sg:city":"Norwich",
    "sg:classifiers":[
        {
            "category":"Building & Trades",
            "subcategory":"Construction",
            "type":"Services"
        }
    ],
    "sg:phone":"+1 519 468 6691",
    "sg:postcode":"N0J 1P0",
    "sg:province":"ON",
    "sg:tags":[
        "concrete",
        "contractor"
    ],
    "wof:name":"Johnstone's Concrete Inc",
    "wof:placetype":"venue"
},
  "geometry": {"coordinates":[-80.5969467163,42.9876861572],"type":"Point"}
}