{
  "type": "Feature",
  "properties": {
    "addr:full":"Midland ON L4R 4K4",
    "addr:postcode":"l4r 4k4",
    "iso:country":"CA",
    "sg:city":"Midland",
    "sg:classifiers":[
        {
            "category":"Building & Trades",
            "subcategory":"Landscaping Services",
            "type":"Services"
        }
    ],
    "sg:phone":"+1 705 526 5785",
    "sg:postcode":"L4R 4K4",
    "sg:province":"ON",
    "sg:tags":[
        "tree"
    ],
    "wof:name":"Huronia Tree Svc",
    "wof:placetype":"venue"
},
  "geometry": {"coordinates":[-79.904602,44.733608],"type":"Point"}
}