{
  "type": "Feature",
  "properties": {
    "addr:full":"12820 97 St NW Edmonton AB T5E 4C3",
    "addr:housenumber":"12820",
    "addr:postcode":"t5e 4c3",
    "addr:street":"97 St Nw",
    "iso:country":"CA",
    "sg:address":"12820 97 St NW",
    "sg:city":"Edmonton",
    "sg:classifiers":[
        {
            "category":"Autos & Motor Vehicles",
            "subcategory":"Automobile Sales",
            "type":"Retail Goods"
        }
    ],
    "sg:phone":"+1 780 478 8300",
    "sg:postcode":"T5E 4C3",
    "sg:province":"AB",
    "sg:tags":[
        "car",
        "dealer"
    ],
    "wof:name":"Kingsway Lexus Toyota",
    "wof:placetype":"venue"
},
  "geometry": {"coordinates":[-113.492195,53.586582],"type":"Point"}
}