{
  "type": "Feature",
  "properties": {
    "addr:full":"2160 Willis Rd Campbell River BC V9W 6X2",
    "addr:housenumber":"2160",
    "addr:postcode":"v9w 6x2",
    "addr:street":"Willis Rd",
    "iso:country":"CA",
    "sg:address":"2160 Willis Rd",
    "sg:city":"Campbell River",
    "sg:classifiers":[
        {
            "category":"Home & Garden",
            "subcategory":"Building Materials",
            "type":"Retail Goods"
        }
    ],
    "sg:phone":"+1 250 287 2760",
    "sg:postcode":"V9W 6X2",
    "sg:province":"BC",
    "sg:tags":[
        "shingles",
        "shake"
    ],
    "wof:name":"Comox Valley Shakes Ltd",
    "wof:placetype":"venue"
},
  "geometry": {"coordinates":[-125.27776336700001,50.0141372681],"type":"Point"}
}