{
  "type": "Feature",
  "properties": {
    "addr:full":"225 Front St W Toronto ON M5V 2X3",
    "addr:housenumber":"225",
    "addr:postcode":"m5v 2x3",
    "addr:street":"Front St W",
    "iso:country":"CA",
    "sg:address":"225 Front St W",
    "sg:city":"Toronto",
    "sg:classifiers":[
        {
            "category":"Personal",
            "subcategory":"Beauty Salon",
            "type":"Services"
        }
    ],
    "sg:phone":"+1 416 413 9100",
    "sg:postcode":"M5V 2X3",
    "sg:province":"ON",
    "sg:tags":[
        "spa",
        "day"
    ],
    "wof:name":"Victoria Spa",
    "wof:placetype":"venue"
},
  "geometry": {"coordinates":[-79.38603973390001,43.6443824768],"type":"Point"}
}