{
  "type": "Feature",
  "properties": {
    "addr:full":"1228 Woodbine Ave Sudbury ON P3A 2M1",
    "addr:housenumber":"1228",
    "addr:postcode":"p3a 2m1",
    "addr:street":"Woodbine Ave",
    "iso:country":"CA",
    "sg:address":"1228 Woodbine Ave",
    "sg:city":"Sudbury",
    "sg:classifiers":[
        {
            "category":"Retail",
            "subcategory":"Animal Services",
            "type":"Services"
        }
    ],
    "sg:phone":"+1 705 688 2680",
    "sg:postcode":"P3A 2M1",
    "sg:province":"ON",
    "sg:tags":[
        "pet",
        "grooming",
        "washing"
    ],
    "wof:name":"S & S Pet Svc",
    "wof:placetype":"venue"
},
  "geometry": {"coordinates":[-80.95085899999999,46.527576],"type":"Point"}
}