{
  "type": "Feature",
  "properties": {
    "iso:country":"CA",
    "sg:city":"Kinkora",
    "sg:classifiers":[
        {
            "category":"Building & Trades",
            "subcategory":"Electrical",
            "type":"Services"
        }
    ],
    "sg:phone":"+1 902 887 2989",
    "sg:postcode":"C0B 1N0",
    "sg:province":"PE",
    "sg:tags":[
        "electric",
        "contractor"
    ],
    "wof:name":"Duffy's Electric",
    "wof:placetype":"venue"
},
  "geometry": {"coordinates":[-63.6027374268,46.3227500916],"type":"Point"}
}