{
  "type": "Feature",
  "properties": {
    "addr:full":"128 Lasalle Rd Sarnia ON N7T 7H5",
    "addr:housenumber":"128",
    "addr:postcode":"n7t 7h5",
    "addr:street":"Lasalle Rd",
    "iso:country":"CA",
    "sg:address":"128 Lasalle Rd",
    "sg:city":"Sarnia",
    "sg:classifiers":[
        {
            "category":"Freight",
            "type":"Transportation"
        }
    ],
    "sg:phone":"+1 519 383 0017",
    "sg:postcode":"N7T 7H5",
    "sg:province":"ON",
    "sg:tags":[
        "mover"
    ],
    "wof:name":"Viking Movers",
    "wof:placetype":"venue"
},
  "geometry": {"coordinates":[-82.454605,42.912632],"type":"Point"}
}