{
  "type": "Feature",
  "properties": {
    "addr:full":"Kamloops BC V2C 5P5",
    "addr:postcode":"bc v2c 5p5",
    "iso:country":"CA",
    "sg:city":"Kamloops",
    "sg:classifiers":[
        {
            "category":"Wholesale",
            "subcategory":"Machinery & Supplies",
            "type":"Manufacturing & Wholesale Goods"
        }
    ],
    "sg:phone":"+1 250 374 2833",
    "sg:postcode":"V2C 5P5",
    "sg:province":"BC",
    "wof:name":"Lance Bissett Ltd",
    "wof:placetype":"venue"
},
  "geometry": {"coordinates":[-120.36350299999999,50.659565],"type":"Point"}
}