{
  "type": "Feature",
  "properties": {
    "addr:full":"151 Hwy 20 E Fonthill ON L0S 1E0",
    "addr:housenumber":"151",
    "addr:postcode":"l0s 1e0",
    "addr:street":"Hwy 20 E Fonthill",
    "iso:country":"CA",
    "sg:address":"151 Hwy 20 E",
    "sg:city":"Fonthill",
    "sg:classifiers":[
        {
            "category":"Autos & Motor Vehicles",
            "subcategory":"Fuel & Gas Station",
            "type":"Retail Goods"
        }
    ],
    "sg:phone":"+1 905 892 3906",
    "sg:postcode":"L0S 1E0",
    "sg:province":"ON",
    "sg:tags":[
        "oil"
    ],
    "wof:name":"Pelham Auto Repairs Ltd",
    "wof:placetype":"venue"
},
  "geometry": {"coordinates":[-79.273689,43.04995],"type":"Point"}
}