{
  "type": "Feature",
  "properties": {
    "addr:full":"3643 115 Ave NW Edmonton AB T5W 0V1",
    "addr:housenumber":"3643",
    "addr:postcode":"t5w 0v1",
    "addr:street":"115 Ave Nw",
    "iso:country":"CA",
    "sg:address":"3643 115 Ave NW",
    "sg:city":"Edmonton",
    "sg:classifiers":[
        {
            "category":"Education",
            "subcategory":"School",
            "type":"Public Place"
        }
    ],
    "sg:phone":"+1 780 474 3713",
    "sg:postcode":"T5W 0V1",
    "sg:province":"AB",
    "wof:name":"St Nicholas Catholic Junior",
    "wof:placetype":"venue"
},
  "geometry": {"coordinates":[-113.397994995,53.5674629211],"type":"Point"}
}