{
  "type": "Feature",
  "properties": {
    "addr:full":"Thorhild AB T0A 3J0",
    "addr:postcode":"t0a 3j0",
    "iso:country":"CA",
    "sg:city":"Thorhild",
    "sg:classifiers":[
        {
            "category":"Utilities",
            "subcategory":"Electric",
            "type":"Services"
        }
    ],
    "sg:phone":"+1 780 398 2000",
    "sg:postcode":"T0A 3J0",
    "sg:province":"AB",
    "sg:tags":[
        "company"
    ],
    "wof:name":"North Parkland Power Rural",
    "wof:placetype":"venue"
},
  "geometry": {"coordinates":[-113.12387085,54.1608428955],"type":"Point"}
}