{
  "type": "Feature",
  "properties": {
    "addr:full":"5200 N Access Rd Chetwynd BC V0C 1J0",
    "addr:housenumber":"5200",
    "addr:postcode":"bc v0c 1j0",
    "addr:street":"N Access Rd",
    "iso:country":"CA",
    "sg:address":"5200 N Access Rd",
    "sg:city":"Chetwynd",
    "sg:classifiers":[
        {
            "category":"Government",
            "subcategory":"Office",
            "type":"Public Place"
        }
    ],
    "sg:phone":"+1 250 788 1943",
    "sg:postcode":"V0C 1J0",
    "sg:province":"BC",
    "sg:tags":[
        "information",
        "tourist",
        "village"
    ],
    "wof:name":"Chetwynd Tourist Information",
    "wof:placetype":"venue"
},
  "geometry": {"coordinates":[-121.63359800000001,55.697266],"type":"Point"}
}