{
  "type": "Feature",
  "properties": {
    "iso:country":"CA",
    "sg:address":"825 Rue Saint-Louis",
    "sg:city":"Terrebonne",
    "sg:classifiers":[
        {
            "category":"Organizations",
            "subcategory":"Religious Organization",
            "type":"Services"
        }
    ],
    "sg:phone":"+1 450 471 3451",
    "sg:postcode":"J6W 1J7",
    "sg:province":"QC",
    "sg:tags":[
        "church"
    ],
    "wof:name":"St Louis DE France Presbytere",
    "wof:placetype":"venue"
},
  "geometry": {"coordinates":[-73.6364974976,45.6950073242],"type":"Point"}
}