{
  "type": "Feature",
  "properties": {
    "iso:country":"CA",
    "sg:address":"10600 Av Larose",
    "sg:city":"Montreal",
    "sg:classifiers":[
        {
            "category":"Education",
            "subcategory":"School",
            "type":"Public Place"
        }
    ],
    "sg:phone":"+1 514 596 5435",
    "sg:postcode":"H2B 2Z3",
    "sg:province":"QC",
    "wof:name":"Ecole St-Antoine-Marie-Claret",
    "wof:placetype":"venue"
},
  "geometry": {"coordinates":[-73.648491,45.579437],"type":"Point"}
}