{
  "type": "Feature",
  "properties": {
    "addr:full":"10600 Av Larose Montreal QC H2B 2Z3",
    "addr:housenumber":"10600",
    "addr:postcode":"h2b 2z3",
    "addr:street":"Av Larose",
    "iso:country":"CA",
    "sg:address":"10600 Av Larose",
    "sg:city":"Montreal",
    "sg:classifiers":[
        {
            "category":"Education",
            "subcategory":"School",
            "type":"Public Place"
        }
    ],
    "sg:phone":"+1 514 596 5435",
    "sg:postcode":"H2B 2Z3",
    "sg:province":"QC",
    "wof:name":"Ecole St-Antoine-Marie-Claret",
    "wof:placetype":"venue"
},
  "geometry": {"coordinates":[-73.64849100000001,45.579437],"type":"Point"}
}