{
  "type": "Feature",
  "properties": {
    "addr:full":"4296 Hartfield Grove Mississauga ON L4W 2Y7",
    "addr:housenumber":"4296",
    "addr:postcode":"l4w 2y7",
    "addr:street":"Hartfield Grove",
    "iso:country":"CA",
    "sg:address":"4296 Hartfield Grove",
    "sg:city":"Mississauga",
    "sg:classifiers":[
        {
            "category":"Building & Trades",
            "subcategory":"Landscaping Services",
            "type":"Services"
        }
    ],
    "sg:phone":"+1 905 629 2583",
    "sg:postcode":"L4W 2Y7",
    "sg:province":"ON",
    "sg:tags":[
        "landscape",
        "contractor"
    ],
    "wof:name":"Entire Landscapes Inc",
    "wof:placetype":"venue"
},
  "geometry": {"coordinates":[-79.6078872681,43.6306762695],"type":"Point"}
}