{
  "type": "Feature",
  "properties": {
    "iso:country":"CA",
    "sg:address":"2528 Rue Laval",
    "sg:city":"Nantes",
    "sg:classifiers":[
        {
            "category":"Retail",
            "subcategory":"Repair Shop",
            "type":"Services"
        }
    ],
    "sg:phone":"+1 819 583 3131",
    "sg:postcode":"G6B 1A1",
    "sg:province":"QC",
    "sg:tags":[
        "repairing",
        "automobile",
        "welding"
    ],
    "wof:name":"Service DE Ressorts Robert",
    "wof:placetype":"venue"
},
  "geometry": {"coordinates":[-70.92069244379999,45.5985984802],"type":"Point"}
}