{
  "type": "Feature",
  "properties": {
    "addr:full":"225 Rte 132 LA Pocatiere QC G0R 1Z0",
    "addr:housenumber":"225",
    "addr:postcode":"g0r 1z0",
    "addr:street":"Rte 132 La Pocatiere",
    "iso:country":"CA",
    "sg:address":"225 Rte 132",
    "sg:city":"LA Pocatiere",
    "sg:classifiers":[
        {
            "category":"Restaurant",
            "type":"Food & Drink"
        }
    ],
    "sg:phone":"+1 418 856 5454",
    "sg:postcode":"G0R 1Z0",
    "sg:province":"QC",
    "wof:name":"Mikes Restaurant",
    "wof:placetype":"venue"
},
  "geometry": {"coordinates":[-70.04939299999999,47.367077],"type":"Point"}
}