{
  "type": "Feature",
  "properties": {
    "addr:full":"Calgary AB T3C 2G3",
    "addr:postcode":"t3c 2g3",
    "iso:country":"CA",
    "sg:city":"Calgary",
    "sg:classifiers":[
        {
            "category":"Building & Trades",
            "subcategory":"Construction",
            "type":"Services"
        }
    ],
    "sg:phone":"+1 403 686 0092",
    "sg:postcode":"T3C 2G3",
    "sg:province":"AB",
    "sg:tags":[
        "roof",
        "structure"
    ],
    "wof:name":"Gang-Nail Trusses",
    "wof:placetype":"venue"
},
  "geometry": {"coordinates":[-114.15128300000001,51.048134],"type":"Point"}
}