{
  "type": "Feature",
  "properties": {
    "addr:full":"202 Ch DE LA Grande-Cote Rosemere QC J7A 1H4",
    "addr:housenumber":"202",
    "addr:postcode":"j7a 1h4",
    "addr:street":"Ch De La Grande-Cote Rosemere",
    "iso:country":"CA",
    "sg:address":"202 Ch DE LA Grande-Cote",
    "sg:city":"Rosemere",
    "sg:classifiers":[
        {
            "category":"Recreation",
            "type":"Entertainment"
        }
    ],
    "sg:phone":"+1 450 430 5775",
    "sg:postcode":"J7A 1H4",
    "sg:province":"QC",
    "sg:tags":[
        "government",
        "hall",
        "auditorium"
    ],
    "wof:name":"Centre Communautaire",
    "wof:placetype":"venue"
},
  "geometry": {"coordinates":[-73.79811096189999,45.6285629272],"type":"Point"}
}