{
  "type": "Feature",
  "properties": {
    "addr:full":"1551 Dundas St London ON N5W 5Y5",
    "addr:housenumber":"1551",
    "addr:postcode":"n5w 5y5",
    "addr:street":"Dundas St",
    "iso:country":"CA",
    "sg:address":"1551 Dundas St",
    "sg:city":"London",
    "sg:classifiers":[
        {
            "category":"Restaurant",
            "type":"Food & Drink"
        }
    ],
    "sg:phone":"+1 519 457 3960",
    "sg:postcode":"N5W 5Y5",
    "sg:province":"ON",
    "wof:name":"Arby's",
    "wof:placetype":"venue"
},
  "geometry": {"coordinates":[-81.1948547363,42.9992332458],"type":"Point"}
}