{
  "type": "Feature",
  "properties": {
    "addr:full":"Gaspe QC G4X 5M4",
    "addr:postcode":"g4x 5m4",
    "iso:country":"CA",
    "sg:city":"Gaspe",
    "sg:classifiers":[
        {
            "category":"Autos & Motor Vehicles",
            "subcategory":"Recreational Vehicle Sales",
            "type":"Retail Goods"
        }
    ],
    "sg:phone":"+1 418 269 3350",
    "sg:postcode":"G4X 5M4",
    "sg:province":"QC",
    "wof:name":"Roulottes Real Blouin Enr",
    "wof:placetype":"venue"
},
  "geometry": {"coordinates":[-64.406609,48.992966],"type":"Point"}
}