{
  "type": "Feature",
  "properties": {
    "addr:full":"8991 River Rd Richmond BC V6X 1Y6",
    "addr:housenumber":"8991",
    "addr:postcode":"v6x 1y6",
    "addr:street":"River Rd",
    "iso:country":"CA",
    "sg:address":"8991 River Rd",
    "sg:city":"Richmond",
    "sg:classifiers":[
        {
            "category":"Recreation",
            "subcategory":"Marina",
            "type":"Entertainment"
        }
    ],
    "sg:phone":"+1 604 231 0599",
    "sg:postcode":"V6X 1Y6",
    "sg:province":"BC",
    "sg:tags":[
        "repairing",
        "yard",
        "boat"
    ],
    "wof:name":"Shannon Buoys Marina-Boatyard",
    "wof:placetype":"venue"
},
  "geometry": {"coordinates":[-123.125214,49.196983],"type":"Point"}
}