{
  "type": "Feature",
  "properties": {
    "addr:full":"Mississauga ON L5L 3T5",
    "addr:postcode":"l5l 3t5",
    "iso:country":"CA",
    "sg:city":"Mississauga",
    "sg:classifiers":[
        {
            "category":"Professional",
            "subcategory":"Management & Consulting",
            "type":"Services"
        }
    ],
    "sg:phone":"+1 905 820 4145",
    "sg:postcode":"L5L 3T5",
    "sg:province":"ON",
    "sg:tags":[
        "consultant",
        "dental",
        "practice"
    ],
    "wof:name":"Roi Corp",
    "wof:placetype":"venue"
},
  "geometry": {"coordinates":[-79.682152,43.527954],"type":"Point"}
}