{
  "type": "Feature",
  "properties": {
    "addr:full":"Red Deer AB T4N 4C9",
    "addr:postcode":"t4n 4c9",
    "iso:country":"CA",
    "sg:city":"Red Deer",
    "sg:classifiers":[
        {
            "category":"Shopping",
            "subcategory":"Used Merchandise",
            "type":"Retail Goods"
        }
    ],
    "sg:phone":"+1 403 342 4883",
    "sg:postcode":"T4N 4C9",
    "sg:province":"AB",
    "sg:tags":[
        "book",
        "rare",
        "dealer"
    ],
    "wof:name":"Red Deer Book Exchange",
    "wof:placetype":"venue"
},
  "geometry": {"coordinates":[-113.81326300000001,52.291721],"type":"Point"}
}