{
  "type": "Feature",
  "properties": {
    "addr:full":"1801 Rue Lavoisier Sainte-Julie QC J3E 1Y6",
    "addr:housenumber":"1801",
    "addr:postcode":"j3e 1y6",
    "addr:street":"Rue Lavoisier",
    "iso:country":"CA",
    "sg:address":"1801 Rue Lavoisier",
    "sg:city":"Sainte-Julie",
    "sg:classifiers":[
        {
            "category":"Retail",
            "subcategory":"Repair Shop",
            "type":"Services"
        }
    ],
    "sg:phone":"+1 450 922 1605",
    "sg:postcode":"J3E 1Y6",
    "sg:province":"QC",
    "sg:tags":[
        "sharpening"
    ],
    "wof:name":"Aiguisage Tout Usage Enr",
    "wof:placetype":"venue"
},
  "geometry": {"coordinates":[-73.322029,45.579334],"type":"Point"}
}