{
  "type": "Feature",
  "properties": {
    "addr:full":"Edmonton AB T6E 6E6",
    "addr:postcode":"t6e 6e6",
    "iso:country":"CA",
    "sg:city":"Edmonton",
    "sg:classifiers":[
        {
            "category":"Banks & Credit Unions",
            "subcategory":"Investment Brokerage",
            "type":"Services"
        }
    ],
    "sg:phone":"+1 780 466 3715",
    "sg:postcode":"T6E 6E6",
    "sg:province":"AB",
    "sg:tags":[
        "advisory",
        "financial"
    ],
    "wof:name":"Hendrickson Financial Inc",
    "wof:placetype":"venue"
},
  "geometry": {"coordinates":[-113.455765,53.488266],"type":"Point"}
}