{
  "type": "Feature",
  "properties": {
    "iso:country":"CA",
    "sg:city":"Kitchener",
    "sg:classifiers":[
        {
            "category":"Building & Trades",
            "subcategory":"Construction",
            "type":"Services"
        }
    ],
    "sg:phone":"+1 519 749 0462",
    "sg:postcode":"N2H 6R4",
    "sg:province":"ON",
    "sg:tags":[
        "dry wall",
        "contractor",
        "maintenance",
        "property"
    ],
    "wof:name":"Mr Hammer",
    "wof:placetype":"venue"
},
  "geometry": {"coordinates":[-80.486412,43.458904],"type":"Point"}
}