{
  "type": "Feature",
  "properties": {
    "addr:full":"253 Main Ave Plum Coulee MB R0G 1R0",
    "addr:housenumber":"253",
    "addr:postcode":"r0g 1r0",
    "addr:street":"Main Ave",
    "iso:country":"CA",
    "sg:address":"253 Main Ave",
    "sg:city":"Plum Coulee",
    "sg:classifiers":[
        {
            "category":"Government",
            "subcategory":"Office",
            "type":"Public Place"
        }
    ],
    "sg:phone":"+1 204 829 3419",
    "sg:postcode":"R0G 1R0",
    "sg:province":"MB",
    "sg:tags":[
        "village"
    ],
    "wof:name":"Plum Coulee Village",
    "wof:placetype":"venue"
},
  "geometry": {"coordinates":[-97.7672042847,49.1894493103],"type":"Point"}
}