{
  "type": "Feature",
  "properties": {
    "addr:full":"1453 Prince Rd Windsor ON N9C 3Z4",
    "addr:housenumber":"1453",
    "addr:postcode":"n9c 3z4",
    "addr:street":"Prince Rd",
    "iso:country":"CA",
    "sg:address":"1453 Prince Rd",
    "sg:city":"Windsor",
    "sg:classifiers":[
        {
            "category":"Health Services",
            "subcategory":"Hospital",
            "type":"Services"
        }
    ],
    "sg:phone":"+1 519 254 5577",
    "sg:postcode":"N9C 3Z4",
    "sg:province":"ON",
    "wof:name":"Windsor Regional Hospital",
    "wof:placetype":"venue"
},
  "geometry": {"coordinates":[-83.063301,42.286621],"type":"Point"}
}