{
  "type": "Feature",
  "properties": {
    "addr:full":"330 Rue Du-Square-Saint-Louis Montreal QC H2X 1A5",
    "addr:housenumber":"330",
    "addr:postcode":"h2x 1a5",
    "addr:street":"Rue Du-Square-Saint-Louis",
    "iso:country":"CA",
    "sg:address":"330 Rue Du-Square-Saint-Louis",
    "sg:city":"Montreal",
    "sg:classifiers":[
        {
            "category":"Professional",
            "subcategory":"Business Services",
            "type":"Services"
        }
    ],
    "sg:phone":"+1 514 286 9869",
    "sg:postcode":"H2X 1A5",
    "sg:province":"QC",
    "sg:tags":[
        "interior",
        "consultant",
        "design",
        "decorator"
    ],
    "wof:name":"Andree Villemaire Design",
    "wof:placetype":"venue"
},
  "geometry": {"coordinates":[-73.569221,45.51685],"type":"Point"}
}