{
  "type": "Feature",
  "properties": {
    "addr:full":"244 Main St Sussex NB E4E 1R3",
    "addr:housenumber":"244",
    "addr:postcode":"e4e 1r3",
    "addr:street":"Main St",
    "iso:country":"CA",
    "sg:address":"244 Main St",
    "sg:city":"Sussex",
    "sg:classifiers":[
        {
            "category":"Retail",
            "subcategory":"Car Wash",
            "type":"Services"
        }
    ],
    "sg:phone":"+1 506 432 9589",
    "sg:postcode":"E4E 1R3",
    "sg:province":"NB",
    "sg:tags":[
        "polishing",
        "washing"
    ],
    "wof:name":"Kings Car Wash",
    "wof:placetype":"venue"
},
  "geometry": {"coordinates":[-65.52383399999999,45.724419],"type":"Point"}
}