{
  "type": "Feature",
  "properties": {
    "addr:full":"79 Lawlor Ave Toronto ON M4E 3L8",
    "addr:housenumber":"79",
    "addr:postcode":"m4e 3l8",
    "addr:street":"Lawlor Ave",
    "iso:country":"CA",
    "sg:address":"79 Lawlor Ave",
    "sg:city":"Toronto",
    "sg:classifiers":[
        {
            "category":"Recreation",
            "type":"Entertainment"
        }
    ],
    "sg:phone":"+1 416 392 0741",
    "sg:postcode":"M4E 3L8",
    "sg:province":"ON",
    "sg:tags":[
        "government",
        "hall",
        "auditorium"
    ],
    "wof:name":"Toronto Adam Beck Comm Ctr",
    "wof:placetype":"venue"
},
  "geometry": {"coordinates":[-79.28898599999999,43.682346],"type":"Point"}
}