{
  "type": "Feature",
  "properties": {
    "addr:full":"301 Ellor St Strathroy ON N7G 2L5",
    "addr:housenumber":"301",
    "addr:postcode":"n7g 2l5",
    "addr:street":"Ellor St",
    "iso:country":"CA",
    "sg:address":"301 Ellor St",
    "sg:city":"Strathroy",
    "sg:classifiers":[
        {
            "category":"Wholesale",
            "subcategory":"Poultry",
            "type":"Manufacturing & Wholesale Goods"
        }
    ],
    "sg:phone":"+1 519 245 1630",
    "sg:postcode":"N7G 2L5",
    "sg:province":"ON",
    "sg:tags":[
        "eggs"
    ],
    "wof:name":"Maple Lynn Foods Ltd",
    "wof:placetype":"venue"
},
  "geometry": {"coordinates":[-81.611824,42.952072],"type":"Point"}
}