{
  "type": "Feature",
  "properties": {
    "addr:full":"Fenelon Falls ON K0M 1N0",
    "addr:postcode":"k0m 1n0",
    "iso:country":"CA",
    "sg:city":"Fenelon Falls",
    "sg:classifiers":[
        {
            "category":"Food & Beverages",
            "subcategory":"Groceries & Convenience Stores",
            "type":"Retail Goods"
        }
    ],
    "sg:phone":"+1 705 887 3372",
    "sg:postcode":"K0M 1N0",
    "sg:province":"ON",
    "wof:name":"Stop 4 Variety",
    "wof:placetype":"venue"
},
  "geometry": {"coordinates":[-78.7390594482,44.5322265625],"type":"Point"}
}