{
  "type": "Feature",
  "properties": {
    "iso:country":"CA",
    "sg:address":"8629 Av Chaumont",
    "sg:city":"Anjou",
    "sg:classifiers":[
        {
            "category":"Personal",
            "subcategory":"Barber",
            "type":"Services"
        }
    ],
    "sg:phone":"+1 514 353 1840",
    "sg:postcode":"H1K 1N3",
    "sg:province":"QC",
    "sg:tags":[
        "salon",
        "beauty"
    ],
    "wof:name":"Salon Gerald",
    "wof:placetype":"venue"
},
  "geometry": {"coordinates":[-73.54801177980001,45.6098442078],"type":"Point"}
}