{
  "type": "Feature",
  "properties": {
    "addr:full":"3885 Boul Harvey # 402 Jonquiere QC G7X 9B1",
    "addr:housenumber":"3885",
    "addr:postcode":"g7x 9b1",
    "addr:street":"Boul Harvey # 402",
    "iso:country":"CA",
    "sg:address":"3885 Boul Harvey # 402",
    "sg:city":"Jonquiere",
    "sg:classifiers":[
        {
            "category":"Insurance",
            "subcategory":"Insurance Agent",
            "type":"Services"
        }
    ],
    "sg:phone":"+1 418 542 9004",
    "sg:postcode":"G7X 9B1",
    "sg:province":"QC",
    "wof:name":"Industrielle Alliance",
    "wof:placetype":"venue"
},
  "geometry": {"coordinates":[-71.25196800000001,48.413036],"type":"Point"}
}