{
  "type": "Feature",
  "properties": {
    "iso:country":"CA",
    "sg:address":"3885 Boul Harvey # 402",
    "sg:city":"Jonquiere",
    "sg:classifiers":[
        {
            "category":"Insurance",
            "subcategory":"Insurance Agent",
            "type":"Services"
        }
    ],
    "sg:phone":"+1 418 542 9004",
    "sg:postcode":"G7X 9B1",
    "sg:province":"QC",
    "wof:name":"Industrielle Alliance",
    "wof:placetype":"venue"
},
  "geometry": {"coordinates":[-71.251968,48.413036],"type":"Point"}
}