{
  "type": "Feature",
  "properties": {
    "iso:country":"CA",
    "sg:address":"58 Main Shore Rd",
    "sg:city":"Yarmouth",
    "sg:classifiers":[
        {
            "category":"Building & Trades",
            "subcategory":"Landscaping Services",
            "type":"Services"
        }
    ],
    "sg:phone":"+1 902 742 0331",
    "sg:postcode":"B5A 4K2",
    "sg:province":"NS",
    "sg:tags":[
        "landscape",
        "contractor"
    ],
    "wof:name":"Western Landscaping",
    "wof:placetype":"venue"
},
  "geometry": {"coordinates":[-66.11885100000001,43.841282],"type":"Point"}
}