{
  "type": "Feature",
  "properties": {
    "addr:full":"2747 Jane St North York ON M3L 2E8",
    "addr:housenumber":"2747",
    "addr:postcode":"m3l 2e8",
    "addr:street":"Jane St",
    "iso:country":"CA",
    "sg:address":"2747 Jane St",
    "sg:city":"North York",
    "sg:classifiers":[
        {
            "category":"Organizations",
            "subcategory":"Religious Organization",
            "type":"Services"
        }
    ],
    "sg:phone":"+1 416 741 1463",
    "sg:postcode":"M3L 2E8",
    "sg:province":"ON",
    "sg:tags":[
        "church"
    ],
    "wof:name":"St Jane Frances Parish",
    "wof:placetype":"venue"
},
  "geometry": {"coordinates":[-79.513786,43.742489],"type":"Point"}
}