{
  "type": "Feature",
  "properties": {
    "iso:country":"CA",
    "sg:address":"74 Rue Rabeau",
    "sg:city":"Notre-Dame-DE-L'Ile-Perrot",
    "sg:classifiers":[
        {
            "category":"Organizations",
            "subcategory":"Religious Organization",
            "type":"Services"
        }
    ],
    "sg:phone":"+1 514 453 4794",
    "sg:postcode":"J7V 8N3",
    "sg:province":"QC",
    "sg:tags":[
        "church"
    ],
    "wof:name":"First Church of God",
    "wof:placetype":"venue"
},
  "geometry": {"coordinates":[-73.955368042,45.3937644958],"type":"Point"}
}