{
  "type": "Feature",
  "properties": {
    "addr:full":"1021 Rue Marcelin Desbiens QC G0W 1N0",
    "addr:housenumber":"1021",
    "addr:postcode":"g0w 1n0",
    "addr:street":"Rue Marcelin",
    "iso:country":"CA",
    "sg:address":"1021 Rue Marcelin",
    "sg:city":"Desbiens",
    "sg:classifiers":[
        {
            "category":"Organizations",
            "subcategory":"Professional Association",
            "type":"Services"
        }
    ],
    "sg:phone":"+1 418 346 5581",
    "sg:postcode":"G0W 1N0",
    "sg:province":"QC",
    "wof:name":"Chevaliers DE Colomb Desbiens",
    "wof:placetype":"venue"
},
  "geometry": {"coordinates":[-71.948143,48.418434],"type":"Point"}
}