{
  "type": "Feature",
  "properties": {
    "addr:full":"PO Box 563 Bashaw AB T0B 0H0",
    "addr:housenumber":"po",
    "addr:postcode":"t0b 0h0",
    "addr:street":"Box 563 Bashaw",
    "iso:country":"CA",
    "sg:address":"PO Box 563",
    "sg:city":"Bashaw",
    "sg:classifiers":[
        {
            "category":"Wholesale",
            "subcategory":"Construction Materials",
            "type":"Manufacturing & Wholesale Goods"
        }
    ],
    "sg:phone":"+1 780 372 3504",
    "sg:postcode":"T0B 0H0",
    "sg:province":"AB",
    "sg:tags":[
        "sand",
        "gravel"
    ],
    "wof:name":"Bolduc Trucking",
    "wof:placetype":"venue"
},
  "geometry": {"coordinates":[-112.970878601,52.5837783813],"type":"Point"}
}