{
  "type": "Feature",
  "properties": {
    "addr:full":"4450 Boul Des Forges Trois-Rivieres QC G8Y 1W5",
    "addr:housenumber":"4450",
    "addr:postcode":"g8y 1w5",
    "addr:street":"Boul Des Forges Trois-Rivieres",
    "iso:country":"CA",
    "sg:address":"4450 Boul Des Forges",
    "sg:city":"Trois-Rivieres",
    "sg:classifiers":[
        {
            "category":"Travel",
            "subcategory":"Travel Agent",
            "type":"Entertainment"
        }
    ],
    "sg:phone":"+1 819 376 9394",
    "sg:postcode":"G8Y 1W5",
    "sg:province":"QC",
    "sg:tags":[
        "agency",
        "bureau"
    ],
    "wof:name":"Voyages Caa",
    "wof:placetype":"venue"
},
  "geometry": {"coordinates":[-72.588722229,46.3586502075],"type":"Point"}
}