{
  "type": "Feature",
  "properties": {
    "addr:full":"700 Main St E Hamilton ON L8M 1K7",
    "addr:housenumber":"700",
    "addr:postcode":"l8m 1k7",
    "addr:street":"Main St E",
    "iso:country":"CA",
    "sg:address":"700 Main St E",
    "sg:city":"Hamilton",
    "sg:classifiers":[
        {
            "category":"Shopping",
            "subcategory":"Pharmacy",
            "type":"Retail Goods"
        }
    ],
    "sg:phone":"+1 905 544 0040",
    "sg:postcode":"L8M 1K7",
    "sg:province":"ON",
    "sg:tags":[
        "home",
        "health"
    ],
    "wof:name":"700 Main Pharmacy",
    "wof:placetype":"venue"
},
  "geometry": {"coordinates":[-79.8420181274,43.2481994629],"type":"Point"}
}