{
  "type": "Feature",
  "properties": {
    "addr:full":"506 Rue Des Erables Cap-DE-LA-Madeleine QC G8T 7Z6",
    "addr:housenumber":"506",
    "addr:postcode":"g8t 7z6",
    "addr:street":"Rue Des Erables",
    "iso:country":"CA",
    "sg:address":"506 Rue Des Erables",
    "sg:city":"Cap-DE-LA-Madeleine",
    "sg:classifiers":[
        {
            "category":"Wholesale",
            "subcategory":"Machinery & Supplies",
            "type":"Manufacturing & Wholesale Goods"
        }
    ],
    "sg:phone":"+1 819 694 7018",
    "sg:postcode":"G8T 7Z6",
    "sg:province":"QC",
    "sg:tags":[
        "equipment",
        "welding"
    ],
    "wof:name":"Oxygene Pro-Tech Inc",
    "wof:placetype":"venue"
},
  "geometry": {"coordinates":[-72.52489471440001,46.380443573],"type":"Point"}
}