{
  "type": "Feature",
  "properties": {
    "addr:full":"570 Admiral Crt London ON N5V 4L3",
    "addr:housenumber":"570",
    "addr:postcode":"n5v 4l3",
    "addr:street":"Admiral Crt",
    "iso:country":"CA",
    "sg:address":"570 Admiral Crt",
    "sg:city":"London",
    "sg:classifiers":[
        {
            "category":"Freight",
            "type":"Transportation"
        }
    ],
    "sg:phone":"+1 519 659 3333",
    "sg:postcode":"N5V 4L3",
    "sg:province":"ON",
    "sg:tags":[
        "mover"
    ],
    "wof:name":"Amj Campbell Van Lines",
    "wof:placetype":"venue"
},
  "geometry": {"coordinates":[-81.14672899999999,43.005154],"type":"Point"}
}