{
  "type": "Feature",
  "properties": {
    "addr:full":"Mcmahon SK S0N 1M0",
    "addr:postcode":"s0n 1m0",
    "iso:country":"CA",
    "sg:city":"Mcmahon",
    "sg:classifiers":[
        {
            "category":"Retail",
            "subcategory":"Auto Repair",
            "type":"Services"
        }
    ],
    "sg:phone":"+1 306 627 3436",
    "sg:postcode":"S0N 1M0",
    "sg:province":"SK",
    "sg:tags":[
        "repairing",
        "automobile"
    ],
    "wof:name":"Mc Mahon Motors",
    "wof:placetype":"venue"
},
  "geometry": {"coordinates":[-107.55659484900001,50.0741882324],"type":"Point"}
}