{
  "type": "Feature",
  "properties": {
    "addr:full":"936 Park St Kenora ON P9N 1B7",
    "addr:housenumber":"936",
    "addr:postcode":"p9n 1b7",
    "addr:street":"Park St",
    "iso:country":"CA",
    "sg:address":"936 Park St",
    "sg:city":"Kenora",
    "sg:classifiers":[
        {
            "category":"Wholesale",
            "subcategory":"Durable Goods & Equipment",
            "type":"Manufacturing & Wholesale Goods"
        }
    ],
    "sg:phone":"+1 807 468 1802",
    "sg:postcode":"P9N 1B7",
    "sg:province":"ON",
    "sg:tags":[
        "fire",
        "extinguisher"
    ],
    "wof:name":"Kenora District Fire & Safety",
    "wof:placetype":"venue"
},
  "geometry": {"coordinates":[-94.474327,49.767521],"type":"Point"}
}