{
  "type": "Feature",
  "properties": {
    "iso:country":"CA",
    "sg:address":"1048 Balmoral St",
    "sg:city":"Thunder Bay",
    "sg:classifiers":[
        {
            "category":"Wholesale",
            "subcategory":"Machinery & Supplies",
            "type":"Manufacturing & Wholesale Goods"
        }
    ],
    "sg:phone":"+1 807 623 4355",
    "sg:postcode":"P7B 5T9",
    "sg:province":"ON",
    "sg:tags":[
        "contractor"
    ],
    "wof:name":"Surplus Equipment Ctr",
    "wof:placetype":"venue"
},
  "geometry": {"coordinates":[-89.2580108643,48.4041786194],"type":"Point"}
}