{
  "type": "Feature",
  "properties": {
    "addr:full":"Chase BC V0E 1M0",
    "addr:postcode":"v0e 1m0",
    "iso:country":"CA",
    "sg:city":"Chase",
    "sg:classifiers":[
        {
            "category":"Shopping",
            "subcategory":"Computers & Home Electronics",
            "type":"Retail Goods"
        }
    ],
    "sg:phone":"+1 250 679 8722",
    "sg:postcode":"V0E 1M0",
    "sg:province":"BC",
    "sg:tags":[
        "equipment",
        "dealer"
    ],
    "wof:name":"Datason Computers",
    "wof:placetype":"venue"
},
  "geometry": {"coordinates":[-119.696365,50.811539],"type":"Point"}
}