{
  "type": "Feature",
  "properties": {
    "addr:full":"159 Vespra St Barrie ON L4N 2H1",
    "addr:housenumber":"159",
    "addr:postcode":"l4n 2h1",
    "addr:street":"Vespra St",
    "iso:country":"CA",
    "sg:address":"159 Vespra St",
    "sg:city":"Barrie",
    "sg:classifiers":[
        {
            "category":"Building & Trades",
            "subcategory":"Construction",
            "type":"Services"
        }
    ],
    "sg:phone":"+1 705 725 8898",
    "sg:postcode":"L4N 2H1",
    "sg:province":"ON",
    "sg:tags":[
        "product",
        "asphalt"
    ],
    "wof:name":"Don's Driveway Depot",
    "wof:placetype":"venue"
},
  "geometry": {"coordinates":[-79.70086669920001,44.3806190491],"type":"Point"}
}