{
  "type": "Feature",
  "properties": {
    "addr:full":"1660 18th St N Brandon MB R7C 1A5",
    "addr:housenumber":"1660",
    "addr:postcode":"r7c 1a5",
    "addr:street":"18Th St N",
    "iso:country":"CA",
    "sg:address":"1660 18th St N",
    "sg:city":"Brandon",
    "sg:classifiers":[
        {
            "category":"Wholesale",
            "subcategory":"Machinery & Supplies",
            "type":"Manufacturing & Wholesale Goods"
        }
    ],
    "sg:phone":"+1 204 728 7043",
    "sg:postcode":"R7C 1A5",
    "sg:province":"MB",
    "sg:tags":[
        "farm",
        "equipment"
    ],
    "wof:name":"Countryside Equipment",
    "wof:placetype":"venue"
},
  "geometry": {"coordinates":[-99.962097,49.876759],"type":"Point"}
}