{
  "type": "Feature",
  "properties": {
    "addr:full":"Nanaimo BC V9S 3Y3",
    "addr:postcode":"v9s 3y3",
    "iso:country":"CA",
    "sg:city":"Nanaimo",
    "sg:classifiers":[
        {
            "category":"Shopping",
            "subcategory":"Stationery & Office Supplies",
            "type":"Retail Goods"
        }
    ],
    "sg:phone":"+1 250 753 5354",
    "sg:postcode":"V9S 3Y3",
    "sg:province":"BC",
    "sg:tags":[
        "stationer"
    ],
    "wof:name":"Terminal Park Stationery & Svc",
    "wof:placetype":"venue"
},
  "geometry": {"coordinates":[-123.955269,49.185131],"type":"Point"}
}