{
  "type": "Feature",
  "properties": {
    "addr:full":"Calgary AB T2V 4V4",
    "addr:postcode":"t2v 4v4",
    "iso:country":"CA",
    "sg:city":"Calgary",
    "sg:classifiers":[
        {
            "category":"Shopping",
            "subcategory":"Optical Goods",
            "type":"Retail Goods"
        }
    ],
    "sg:phone":"+1 403 259 3824",
    "sg:postcode":"T2V 4V4",
    "sg:province":"AB",
    "sg:tags":[
        "optician"
    ],
    "wof:name":"Crown Contact Lens Ctr",
    "wof:placetype":"venue"
},
  "geometry": {"coordinates":[-114.072257996,50.9897422791],"type":"Point"}
}