{
  "type": "Feature",
  "properties": {
    "addr:full":"930 Jacques-Cartier Est suite D-102 Chicoutimi G7H 7K9",
    "addr:housenumber":"930",
    "addr:postcode":"g7h 7k9",
    "addr:street":"Jacques-Cartier Est Suite D-102",
    "iso:country":"CA",
    "sg:address":"930 Jacques-Cartier Est suite D-102",
    "sg:city":"Chicoutimi",
    "sg:classifiers":[
        {
            "category":"Professional",
            "subcategory":"Computer Services",
            "type":"Services"
        }
    ],
    "sg:postcode":"G7H 7K9",
    "sg:tags":[
        "employee-scheduling",
        "workforce-management",
        "demand-based-scheduling",
        "employee-replacement-tools",
        "scheduling",
        "labor-management"
    ],
    "sg:website":"http://www.hrscheduling.com/",
    "wof:name":"Horasphere",
    "wof:placetype":"venue"
},
  "geometry": {"coordinates":[-73.55649,45.502732],"type":"Point"}
}