{
  "type": "Feature",
  "properties": {
    "addr:full":"2980 Fredericton Rd Salisbury NB E4J 2G1",
    "addr:postcode":"2980;e4j 2g1",
    "addr:street":"Fredericton Rd",
    "iso:country":"CA",
    "sg:address":"2980 Fredericton Rd",
    "sg:city":"Salisbury",
    "sg:classifiers":[
        {
            "category":"Food & Beverages",
            "subcategory":"Bakery",
            "type":"Retail Goods"
        }
    ],
    "sg:phone":"+1 506 372 4522",
    "sg:postcode":"E4J 2G1",
    "sg:province":"NB",
    "sg:tags":[
        "doughnut"
    ],
    "wof:name":"Tim Hortons",
    "wof:placetype":"venue"
},
  "geometry": {"coordinates":[-65.055862,46.046951],"type":"Point"}
}