{
  "type": "Feature",
  "properties": {
    "addr:full":"506 Churchill St Midale SK S0C 1S0",
    "addr:housenumber":"506",
    "addr:postcode":"s0c 1s0",
    "addr:street":"Churchill St",
    "iso:country":"CA",
    "sg:address":"506 Churchill St",
    "sg:city":"Midale",
    "sg:classifiers":[
        {
            "category":"Building & Trades",
            "subcategory":"Electrical",
            "type":"Services"
        }
    ],
    "sg:phone":"+1 306 458 2380",
    "sg:postcode":"S0C 1S0",
    "sg:province":"SK",
    "sg:tags":[
        "electric",
        "contractor"
    ],
    "wof:name":"L & D Thompson Electric",
    "wof:placetype":"venue"
},
  "geometry": {"coordinates":[-103.4105,49.394676],"type":"Point"}
}