{
  "type": "Feature",
  "properties": {
    "addr:full":"RR 1 Carstairs AB T0M 0N0",
    "addr:postcode":"t0m 0n0",
    "addr:street":"Rr 1",
    "iso:country":"CA",
    "sg:address":"RR 1",
    "sg:city":"Carstairs",
    "sg:classifiers":[
        {
            "category":"Education",
            "subcategory":"School",
            "type":"Public Place"
        }
    ],
    "sg:phone":"+1 403 337 3326",
    "sg:postcode":"T0M 0N0",
    "sg:province":"AB",
    "wof:name":"Hugh Sutherland School",
    "wof:placetype":"venue"
},
  "geometry": {"coordinates":[-114.095428,51.562595],"type":"Point"}
}