{
  "type": "Feature",
  "properties": {
    "iso:country":"CA",
    "sg:address":"437 Averill Cres",
    "sg:city":"London",
    "sg:classifiers":[
        {
            "category":"Retail",
            "subcategory":"Repair Shop",
            "type":"Services"
        }
    ],
    "sg:phone":"+1 519 439 5862",
    "sg:postcode":"N6C 2R8",
    "sg:province":"ON",
    "sg:tags":[
        "repairing",
        "piano",
        "refinishing"
    ],
    "wof:name":"Godfrey, Lynn",
    "wof:placetype":"venue"
},
  "geometry": {"coordinates":[-81.2401809692,42.9596595764],"type":"Point"}
}