{
  "type": "Feature",
  "properties": {
    "addr:full":"Sherbrooke QC J1H 5A9",
    "addr:postcode":"j1h 5a9",
    "iso:country":"CA",
    "sg:city":"Sherbrooke",
    "sg:classifiers":[
        {
            "category":"Professional",
            "subcategory":"Lawyer & Legal Services",
            "type":"Services"
        }
    ],
    "sg:phone":"+1 819 569 9933",
    "sg:postcode":"J1H 5A9",
    "sg:province":"QC",
    "sg:tags":[
        "attorney"
    ],
    "wof:name":"Boutin & Boutin",
    "wof:placetype":"venue"
},
  "geometry": {"coordinates":[-71.891242981,45.4026145935],"type":"Point"}
}