{
  "type": "Feature",
  "properties": {
    "addr:full":"54 Rue Ranger Ripon QC J0V 1V0",
    "addr:housenumber":"54",
    "addr:postcode":"j0v 1v0",
    "addr:street":"Rue Ranger",
    "iso:country":"CA",
    "sg:address":"54 Rue Ranger",
    "sg:city":"Ripon",
    "sg:classifiers":[
        {
            "category":"Health Services",
            "subcategory":"Doctor",
            "type":"Services"
        }
    ],
    "sg:phone":"+1 819 983 2048",
    "sg:postcode":"J0V 1V0",
    "sg:province":"QC",
    "sg:tags":[
        "physician",
        "surgeon"
    ],
    "wof:name":"Beauregard, M MD",
    "wof:placetype":"venue"
},
  "geometry": {"coordinates":[-75.103371,45.781796],"type":"Point"}
}