{
  "type": "Feature",
  "properties": {
    "iso:country":"CA",
    "sg:address":"1 Parkers Cove",
    "sg:city":"Burns Cove",
    "sg:classifiers":[
        {
            "category":"Food & Beverages",
            "subcategory":"Groceries & Convenience Stores",
            "type":"Retail Goods"
        }
    ],
    "sg:phone":"+1 709 443 2322",
    "sg:postcode":"A0E 1H0",
    "sg:province":"NL",
    "wof:name":"H Murphy Convenience Store",
    "wof:placetype":"venue"
},
  "geometry": {"coordinates":[-54.8600349426,47.3967514038],"type":"Point"}
}