{
  "type": "Feature",
  "properties": {
    "addr:full":"7845 Tecumseh Rd E Windsor ON N8T 1G3",
    "addr:housenumber":"7845",
    "addr:postcode":"n8t 1g3",
    "addr:street":"Tecumseh Rd E",
    "iso:country":"CA",
    "sg:address":"7845 Tecumseh Rd E",
    "sg:city":"Windsor",
    "sg:classifiers":[
        {
            "category":"Wholesale",
            "subcategory":"Groceries",
            "type":"Manufacturing & Wholesale Goods"
        }
    ],
    "sg:phone":"+1 519 945 0575",
    "sg:postcode":"N8T 1G3",
    "sg:province":"ON",
    "sg:tags":[
        "grocer"
    ],
    "wof:name":"Edge Nutrition",
    "wof:placetype":"venue"
},
  "geometry": {"coordinates":[-82.933899,42.313717],"type":"Point"}
}