{
  "type": "Feature",
  "properties": {
    "addr:full":"713 Rue Principale Lac-Drolet QC G0Y 1C0",
    "addr:housenumber":"713",
    "addr:postcode":"g0y 1c0",
    "addr:street":"Rue Principale",
    "iso:country":"CA",
    "sg:address":"713 Rue Principale",
    "sg:city":"Lac-Drolet",
    "sg:classifiers":[
        {
            "category":"Government",
            "subcategory":"Office",
            "type":"Public Place"
        }
    ],
    "sg:phone":"+1 819 549 2444",
    "sg:postcode":"G0Y 1C0",
    "sg:province":"QC",
    "sg:tags":[
        "village"
    ],
    "wof:name":"Lac Drolet Garage",
    "wof:placetype":"venue"
},
  "geometry": {"coordinates":[-70.850655,45.719444],"type":"Point"}
}