{
  "type": "Feature",
  "properties": {
    "addr:full":"PO Box 69 Kimmirut NU X0A 0N0",
    "addr:housenumber":"po box 69",
    "addr:postcode":"x0a 0n0",
    "iso:country":"CA",
    "sg:address":"PO Box 69",
    "sg:city":"Kimmirut",
    "sg:classifiers":[
        {
            "category":"Travel",
            "subcategory":"Hotels & Motels",
            "type":"Entertainment"
        }
    ],
    "sg:phone":"+1 867 939 2322",
    "sg:postcode":"X0A 0N0",
    "sg:province":"NU",
    "wof:name":"Kimik CO-OP Ltd",
    "wof:placetype":"venue"
},
  "geometry": {"coordinates":[-69.868927,62.846863],"type":"Point"}
}