{
  "type": "Feature",
  "properties": {
    "addr:full":"11617 Rue Joseph-Casavant Montreal QC H3M 2B9",
    "addr:housenumber":"11617",
    "addr:postcode":"h3m 2b9",
    "addr:street":"Rue Joseph-Casavant",
    "iso:country":"CA",
    "sg:address":"11617 Rue Joseph-Casavant",
    "sg:city":"Montreal",
    "sg:classifiers":[
        {
            "category":"Wholesale",
            "subcategory":"Office Equipment",
            "type":"Manufacturing & Wholesale Goods"
        }
    ],
    "sg:phone":"+1 514 856 2239",
    "sg:postcode":"H3M 2B9",
    "sg:province":"QC",
    "sg:tags":[
        "machine",
        "duplicating",
        "copying"
    ],
    "wof:name":"Equipement DE Bureau Balco",
    "wof:placetype":"venue"
},
  "geometry": {"coordinates":[-73.692581,45.533714],"type":"Point"}
}