{
  "type": "Feature",
  "properties": {
    "iso:country":"CA",
    "sg:address":"39 Main St",
    "sg:city":"Morrisburg",
    "sg:classifiers":[
        {
            "category":"Restaurant",
            "type":"Food & Drink"
        }
    ],
    "sg:phone":"+1 613 543 3145",
    "sg:postcode":"K0C 1X0",
    "sg:province":"ON",
    "wof:name":"Lee's Tavern Dining Lounge",
    "wof:placetype":"venue"
},
  "geometry": {"coordinates":[-75.18287658689999,44.9008483887],"type":"Point"}
}