{
  "type": "Feature",
  "properties": {
    "addr:full":"1186 Rue Du Lac Thetford Mines QC G6G 6J1",
    "addr:housenumber":"1186",
    "addr:postcode":"g6g 6j1",
    "addr:street":"Rue Du Lac",
    "iso:country":"CA",
    "sg:address":"1186 Rue Du Lac",
    "sg:city":"Thetford Mines",
    "sg:classifiers":[
        {
            "category":"Building & Trades",
            "subcategory":"Construction",
            "type":"Services"
        }
    ],
    "sg:phone":"+1 418 335 6487",
    "sg:postcode":"G6G 6J1",
    "sg:province":"QC",
    "sg:tags":[
        "excavating",
        "contractor"
    ],
    "wof:name":"Claude Perreault Excavation",
    "wof:placetype":"venue"
},
  "geometry": {"coordinates":[-71.33252716059999,46.0947227478],"type":"Point"}
}