{
  "type": "Feature",
  "properties": {
    "addr:full":"Waterville QC J0B 3H0",
    "addr:postcode":"j0b 3h0",
    "iso:country":"CA",
    "sg:city":"Waterville",
    "sg:classifiers":[
        {
            "category":"Organizations",
            "subcategory":"Labor Organization",
            "type":"Services"
        }
    ],
    "sg:phone":"+1 819 837 2933",
    "sg:postcode":"J0B 3H0",
    "sg:province":"QC",
    "wof:name":"Syndicat Des Metallos",
    "wof:placetype":"venue"
},
  "geometry": {"coordinates":[-71.890327,45.277077],"type":"Point"}
}