{
  "type": "Feature",
  "properties": {
    "addr:full":"625 Nairn Ave Winnipeg MB R2L 0X4",
    "addr:housenumber":"625",
    "addr:postcode":"r2l 0x4",
    "addr:street":"Nairn Ave",
    "iso:country":"CA",
    "sg:address":"625 Nairn Ave",
    "sg:city":"Winnipeg",
    "sg:classifiers":[
        {
            "category":"Professional",
            "subcategory":"Computer Services",
            "type":"Services"
        }
    ],
    "sg:phone":"+1 204 667 3871",
    "sg:postcode":"R2L 0X4",
    "sg:province":"MB",
    "sg:tags":[
        "processing",
        "datum"
    ],
    "wof:name":"Lor Ann Management Ltd",
    "wof:placetype":"venue"
},
  "geometry": {"coordinates":[-97.095207,49.903259],"type":"Point"}
}