{
  "type": "Feature",
  "properties": {
    "addr:full":"1410 Crown St North Vancouver BC V7J 1G5",
    "addr:housenumber":"1410",
    "addr:postcode":"v7j 1g5",
    "addr:street":"Crown St",
    "iso:country":"CA",
    "sg:address":"1410 Crown St",
    "sg:city":"North Vancouver",
    "sg:classifiers":[
        {
            "category":"Wholesale",
            "subcategory":"Electrical",
            "type":"Manufacturing & Wholesale Goods"
        }
    ],
    "sg:phone":"+1 604 985 4721",
    "sg:postcode":"V7J 1G5",
    "sg:province":"BC",
    "sg:tags":[
        "control"
    ],
    "wof:name":"Elmec Engineering Ltd",
    "wof:placetype":"venue"
},
  "geometry": {"coordinates":[-123.03413399999999,49.308968],"type":"Point"}
}