{
  "type": "Feature",
  "properties": {
    "iso:country":"CA",
    "sg:address":"1410 Crown St",
    "sg:city":"North Vancouver",
    "sg:classifiers":[
        {
            "category":"Wholesale",
            "subcategory":"Electrical",
            "type":"Manufacturing & Wholesale Goods"
        }
    ],
    "sg:phone":"+1 604 985 4721",
    "sg:postcode":"V7J 1G5",
    "sg:province":"BC",
    "sg:tags":[
        "control"
    ],
    "wof:name":"Elmec Engineering Ltd",
    "wof:placetype":"venue"
},
  "geometry": {"coordinates":[-123.034134,49.308968],"type":"Point"}
}