{
  "type": "Feature",
  "properties": {
    "addr:full":"1445 Hess Rd Gabriola BC V0R 1X6",
    "addr:housenumber":"1445",
    "addr:postcode":"v0r 1x6",
    "addr:street":"Hess Rd",
    "iso:country":"CA",
    "sg:address":"1445 Hess Rd",
    "sg:city":"Gabriola",
    "sg:classifiers":[
        {
            "category":"Building & Trades",
            "subcategory":"Plumbing",
            "type":"Services"
        }
    ],
    "sg:phone":"+1 250 247 9588",
    "sg:postcode":"V0R 1X6",
    "sg:province":"BC",
    "sg:tags":[
        "contractor"
    ],
    "wof:name":"Scotty's Plumbing",
    "wof:placetype":"venue"
},
  "geometry": {"coordinates":[-123.795547485,49.1529312134],"type":"Point"}
}