{
  "type": "Feature",
  "properties": {
    "addr:full":"1309 Hastings Cres SE Calgary AB T2G 4C8",
    "addr:housenumber":"1309",
    "addr:postcode":"t2g 4c8",
    "addr:street":"Hastings Cres Se",
    "iso:country":"CA",
    "sg:address":"1309 Hastings Cres SE",
    "sg:city":"Calgary",
    "sg:classifiers":[
        {
            "category":"Building & Trades",
            "subcategory":"Construction",
            "type":"Services"
        }
    ],
    "sg:phone":"+1 403 243 0082",
    "sg:postcode":"T2G 4C8",
    "sg:province":"AB",
    "sg:tags":[
        "maker",
        "cabinet"
    ],
    "wof:name":"Vision Woodworks",
    "wof:placetype":"venue"
},
  "geometry": {"coordinates":[-114.033424,51.013119],"type":"Point"}
}