{
  "type": "Feature",
  "properties": {
    "addr:full":"800 Tolmie Ave Victoria BC V8X 3W4",
    "addr:housenumber":"800",
    "addr:postcode":"v8x 3w4",
    "addr:street":"Tolmie Ave",
    "iso:country":"CA",
    "sg:address":"800 Tolmie Ave",
    "sg:city":"Victoria",
    "sg:classifiers":[
        {
            "category":"Restaurant",
            "type":"Food & Drink"
        }
    ],
    "sg:phone":"+1 250 386 4440",
    "sg:postcode":"V8X 3W4",
    "sg:province":"BC",
    "wof:name":"Red Robin Restaurants Ltd",
    "wof:placetype":"venue"
},
  "geometry": {"coordinates":[-123.364517212,48.428314209],"type":"Point"}
}