{
  "type": "Feature",
  "properties": {
    "addr:full":"2410 Malaview Ave Sidney BC V8L 2G3",
    "addr:housenumber":"2410",
    "addr:postcode":"v8l 2g3",
    "addr:street":"Malaview Ave",
    "iso:country":"CA",
    "sg:address":"2410 Malaview Ave",
    "sg:city":"Sidney",
    "sg:classifiers":[
        {
            "category":"Social Services",
            "subcategory":"Child Care",
            "type":"Services"
        }
    ],
    "sg:phone":"+1 250 655 3333",
    "sg:postcode":"V8L 2G3",
    "sg:province":"BC",
    "wof:name":"Sidney Pre-School",
    "wof:placetype":"venue"
},
  "geometry": {"coordinates":[-123.400085,48.657185],"type":"Point"}
}