{
  "type": "Feature",
  "properties": {
    "addr:full":"220 11th St E Cornwall ON K6H 2Y5",
    "addr:housenumber":"220",
    "addr:postcode":"k6h 2y5",
    "addr:street":"11Th St E",
    "iso:country":"CA",
    "sg:address":"220 11th St E",
    "sg:city":"Cornwall",
    "sg:classifiers":[
        {
            "category":"Retail",
            "subcategory":"Auto Repair",
            "type":"Services"
        }
    ],
    "sg:phone":"+1 613 933 2040",
    "sg:postcode":"K6H 2Y5",
    "sg:province":"ON",
    "sg:tags":[
        "body",
        "automobile",
        "painting"
    ],
    "wof:name":"J & A Auto Body",
    "wof:placetype":"venue"
},
  "geometry": {"coordinates":[-74.731697,45.032391],"type":"Point"}
}