{
  "type": "Feature",
  "properties": {
    "addr:full":"704 Copping St North Vancouver BC V7M 3G6",
    "addr:housenumber":"704",
    "addr:postcode":"v7m 3g6",
    "addr:street":"Copping St",
    "iso:country":"CA",
    "sg:address":"704 Copping St",
    "sg:city":"North Vancouver",
    "sg:classifiers":[
        {
            "category":"Building & Trades",
            "subcategory":"Construction",
            "type":"Services"
        }
    ],
    "sg:phone":"+1 604 929 3595",
    "sg:postcode":"V7M 3G6",
    "sg:province":"BC",
    "sg:tags":[
        "cabinet",
        "maker",
        "furniture"
    ],
    "wof:name":"Paul Tellier Fine Woodwork",
    "wof:placetype":"venue"
},
  "geometry": {"coordinates":[-123.091812,49.316559],"type":"Point"}
}