{
  "type": "Feature",
  "properties": {
    "addr:full":"47 Boul DE LA Seigneurie E Blainville QC J7C 4G6",
    "addr:housenumber":"47",
    "addr:postcode":"j7c 4g6",
    "addr:street":"Boul De La Seigneurie E",
    "iso:country":"CA",
    "sg:address":"47 Boul DE LA Seigneurie E",
    "sg:city":"Blainville",
    "sg:classifiers":[
        {
            "category":"Building & Trades",
            "subcategory":"Construction",
            "type":"Services"
        }
    ],
    "sg:phone":"+1 450 437 0202",
    "sg:postcode":"J7C 4G6",
    "sg:province":"QC",
    "sg:tags":[
        "roofing",
        "contractor"
    ],
    "wof:name":"Toiture S Belanger Inc",
    "wof:placetype":"venue"
},
  "geometry": {"coordinates":[-73.863495,45.671886],"type":"Point"}
}