{
  "type": "Feature",
  "properties": {
    "addr:full":"London ON N6A 1M6",
    "addr:postcode":"n6a 1m6",
    "iso:country":"CA",
    "sg:city":"London",
    "sg:classifiers":[
        {
            "category":"Education",
            "subcategory":"School",
            "type":"Public Place"
        }
    ],
    "sg:phone":"+1 519 439 3350",
    "sg:postcode":"N6A 1M6",
    "sg:province":"ON",
    "sg:tags":[
        "language"
    ],
    "wof:name":"London Language Institute",
    "wof:placetype":"venue"
},
  "geometry": {"coordinates":[-81.2524795532,42.9899749756],"type":"Point"}
}