{
  "type": "Feature",
  "properties": {
    "addr:full":"426 University Ave Toronto ON M5G 1S9",
    "addr:housenumber":"426",
    "addr:postcode":"m5g 1s9",
    "addr:street":"University Ave",
    "iso:country":"CA",
    "sg:address":"426 University Ave",
    "sg:city":"Toronto",
    "sg:classifiers":[
        {
            "category":"Organizations",
            "subcategory":"Professional Association",
            "type":"Services"
        }
    ],
    "sg:phone":"+1 416 597 0286",
    "sg:postcode":"M5G 1S9",
    "sg:province":"ON",
    "sg:tags":[
        "club"
    ],
    "wof:name":"Royal Canadian Military Inst",
    "wof:placetype":"venue"
},
  "geometry": {"coordinates":[-79.388381958,43.6541213989],"type":"Point"}
}