{
  "type": "Feature",
  "properties": {
    "addr:full":"Mission BC V2V 1G7",
    "addr:postcode":"v2v 1g7",
    "iso:country":"CA",
    "sg:city":"Mission",
    "sg:classifiers":[
        {
            "category":"Shopping",
            "subcategory":"Optical Goods",
            "type":"Retail Goods"
        }
    ],
    "sg:phone":"+1 604 820 1112",
    "sg:postcode":"V2V 1G7",
    "sg:province":"BC",
    "sg:tags":[
        "optician"
    ],
    "wof:name":"Swing Optical Ltd",
    "wof:placetype":"venue"
},
  "geometry": {"coordinates":[-122.30387878400001,49.1345863342],"type":"Point"}
}