{
  "type": "Feature",
  "properties": {
    "addr:full":"2086 Rue Sainte-Famille Jonquiere QC G7X 4X1",
    "addr:housenumber":"2086",
    "addr:postcode":"g7x 4x1",
    "addr:street":"Rue Sainte-Famille",
    "iso:country":"CA",
    "sg:address":"2086 Rue Sainte-Famille",
    "sg:city":"Jonquiere",
    "sg:classifiers":[
        {
            "category":"Personal",
            "subcategory":"Beauty Salon",
            "type":"Services"
        }
    ],
    "sg:phone":"+1 418 547 8300",
    "sg:postcode":"G7X 4X1",
    "sg:province":"QC",
    "wof:name":"Salon Louvain",
    "wof:placetype":"venue"
},
  "geometry": {"coordinates":[-71.24091300000001,48.424389],"type":"Point"}
}