{
  "type": "Feature",
  "properties": {
    "iso:country":"CA",
    "sg:address":"169 Hamilton River Rd",
    "sg:city":"Happy Valley-Goose Bay",
    "sg:classifiers":[
        {
            "category":"Professional",
            "subcategory":"Lawyer & Legal Services",
            "type":"Services"
        }
    ],
    "sg:phone":"+1 709 896 5440",
    "sg:postcode":"A0P 1E0",
    "sg:province":"NL",
    "sg:tags":[
        "attorney"
    ],
    "wof:name":"Singleton & CO Law Offices",
    "wof:placetype":"venue"
},
  "geometry": {"coordinates":[-60.3742980957,53.3064537048],"type":"Point"}
}