{
  "type": "Feature",
  "properties": {
    "iso:country":"CA",
    "sg:city":"Port Hawkesbury",
    "sg:classifiers":[
        {
            "category":"Shopping",
            "subcategory":"Clothing, Apparel, & Fashions",
            "type":"Retail Goods"
        }
    ],
    "sg:phone":"+1 902 625 1109",
    "sg:postcode":"B9A 3J9",
    "sg:province":"NS",
    "sg:tags":[
        "furnishing"
    ],
    "wof:name":"Images Men's Wear Ltd",
    "wof:placetype":"venue"
},
  "geometry": {"coordinates":[-61.3336334229,45.6178855896],"type":"Point"}
}