{
  "type": "Feature",
  "properties": {
    "iso:country":"CA",
    "sg:address":"185 High St",
    "sg:city":"Southampton",
    "sg:classifiers":[
        {
            "category":"Shopping",
            "subcategory":"Clothing, Apparel, & Fashions",
            "type":"Retail Goods"
        }
    ],
    "sg:phone":"+1 519 797 2551",
    "sg:postcode":"N0H 2L0",
    "sg:province":"ON",
    "wof:name":"Kelly Green",
    "wof:placetype":"venue"
},
  "geometry": {"coordinates":[-81.3721694946,44.4957275391],"type":"Point"}
}