{
  "type": "Feature",
  "properties": {
    "addr:full":"13 Rue DE Juan-Les-Pins Gatineau QC J8T 6B7",
    "addr:housenumber":"13",
    "addr:postcode":"j8t 6b7",
    "addr:street":"Rue De Juan-Les-Pins",
    "iso:country":"CA",
    "sg:address":"13 Rue DE Juan-Les-Pins",
    "sg:city":"Gatineau",
    "sg:classifiers":[
        {
            "category":"Professional",
            "subcategory":"Business Services",
            "type":"Services"
        }
    ],
    "sg:phone":"+1 819 568 4638",
    "sg:postcode":"J8T 6B7",
    "sg:province":"QC",
    "sg:tags":[
        "translator",
        "interpreter"
    ],
    "wof:name":"Perfectrad Enr",
    "wof:placetype":"venue"
},
  "geometry": {"coordinates":[-75.7390365601,45.4841384888],"type":"Point"}
}