{
  "type": "Feature",
  "properties": {
    "iso:country":"CA",
    "sg:address":"5 Rue Masse",
    "sg:city":"Saint-Hubert-Riviere-Du-Loup",
    "sg:classifiers":[
        {
            "category":"Manufacturing",
            "subcategory":"Lumber",
            "type":"Manufacturing & Wholesale Goods"
        }
    ],
    "sg:phone":"+1 418 497 1230",
    "sg:postcode":"G0L 3L0",
    "sg:province":"QC",
    "sg:tags":[
        "sawmill"
    ],
    "wof:name":"Masse & D'Amours Inc",
    "wof:placetype":"venue"
},
  "geometry": {"coordinates":[-69.53703308110001,47.8350410461],"type":"Point"}
}