{
  "type": "Feature",
  "properties": {
    "addr:full":"Tisdale Mall Tisdale SK S0E 1T0",
    "addr:postcode":"s0e 1t0",
    "addr:street":"Tisdale",
    "iso:country":"CA",
    "sg:address":"Tisdale Mall",
    "sg:city":"Tisdale",
    "sg:classifiers":[
        {
            "category":"Organizations",
            "subcategory":"Professional Association",
            "type":"Services"
        }
    ],
    "sg:phone":"+1 306 873 3539",
    "sg:postcode":"S0E 1T0",
    "sg:province":"SK",
    "sg:tags":[
        "club"
    ],
    "wof:name":"Tisdale Twisters Gymastics Clb",
    "wof:placetype":"venue"
},
  "geometry": {"coordinates":[-104.058228,52.846588],"type":"Point"}
}