{
  "type": "Feature",
  "properties": {
    "addr:full":"Richmond BC V6X 2R3",
    "addr:postcode":"v6x 2r3",
    "iso:country":"CA",
    "sg:city":"Richmond",
    "sg:classifiers":[
        {
            "category":"Retail",
            "subcategory":"Auto Repair",
            "type":"Services"
        }
    ],
    "sg:phone":"+1 604 207 8770",
    "sg:postcode":"V6X 2R3",
    "sg:province":"BC",
    "sg:tags":[
        "repairing",
        "automobile",
        "painting"
    ],
    "wof:name":"Lotus Auto Body",
    "wof:placetype":"venue"
},
  "geometry": {"coordinates":[-123.095596,49.19334],"type":"Point"}
}