{
  "type": "Feature",
  "properties": {
    "addr:full":"15324 123 Ave NW Edmonton AB T5V 1K8",
    "addr:housenumber":"15324",
    "addr:postcode":"t5v 1k8",
    "addr:street":"123 Ave Nw",
    "iso:country":"CA",
    "sg:address":"15324 123 Ave NW",
    "sg:city":"Edmonton",
    "sg:classifiers":[
        {
            "category":"Building & Trades",
            "subcategory":"Construction",
            "type":"Services"
        }
    ],
    "sg:phone":"+1 780 447 2650",
    "sg:postcode":"T5V 1K8",
    "sg:province":"AB",
    "sg:tags":[
        "excavating",
        "contractor"
    ],
    "wof:name":"Mike Chrapko & Sons Excavating",
    "wof:placetype":"venue"
},
  "geometry": {"coordinates":[-113.585182,53.5769],"type":"Point"}
}