{
  "type": "Feature",
  "properties": {
    "addr:full":"52 Nelson St W Meaford ON N4L 1R2",
    "addr:housenumber":"52",
    "addr:postcode":"n4l 1r2",
    "addr:street":"Nelson St W",
    "iso:country":"CA",
    "sg:address":"52 Nelson St W",
    "sg:city":"Meaford",
    "sg:classifiers":[
        {
            "category":"Restaurant",
            "type":"Food & Drink"
        }
    ],
    "sg:phone":"+1 519 538 5942",
    "sg:postcode":"N4L 1R2",
    "sg:province":"ON",
    "sg:tags":[
        "tea",
        "rooms"
    ],
    "wof:name":"Patti Page's Tea Shoppe",
    "wof:placetype":"venue"
},
  "geometry": {"coordinates":[-80.593842,44.607788],"type":"Point"}
}