{
  "type": "Feature",
  "properties": {
    "addr:full":"149 East 23rd St Hamilton ON L8V 2W9",
    "addr:housenumber":"149",
    "addr:postcode":"l8v 2w9",
    "addr:street":"East 23Rd St",
    "iso:country":"CA",
    "sg:address":"149 East 23rd St",
    "sg:city":"Hamilton",
    "sg:classifiers":[
        {
            "category":"Organizations",
            "subcategory":"Professional Association",
            "type":"Services"
        }
    ],
    "sg:phone":"+1 905 387 8875",
    "sg:postcode":"L8V 2W9",
    "sg:province":"ON",
    "wof:name":"Ontario Garage Assocs",
    "wof:placetype":"venue"
},
  "geometry": {"coordinates":[-79.85320299999999,43.23497],"type":"Point"}
}