{
  "type": "Feature",
  "properties": {
    "addr:full":"Saint-Tite QC G0X 3H0",
    "addr:postcode":"g0x 3h0",
    "iso:country":"CA",
    "sg:city":"Saint-Tite",
    "sg:classifiers":[
        {
            "category":"Personal",
            "subcategory":"Beauty Salon",
            "type":"Services"
        }
    ],
    "sg:phone":"+1 418 365 3395",
    "sg:postcode":"G0X 3H0",
    "sg:province":"QC",
    "wof:name":"Salon DE Coiffure Lacoursiere",
    "wof:placetype":"venue"
},
  "geometry": {"coordinates":[-72.5629577637,46.7326927185],"type":"Point"}
}