{
  "type": "Feature",
  "properties": {
    "addr:full":"Calgary AB T2C 2N5",
    "addr:postcode":"t2c 2n5",
    "iso:country":"CA",
    "sg:city":"Calgary",
    "sg:classifiers":[
        {
            "category":"Health Services",
            "subcategory":"Medical Lab",
            "type":"Services"
        }
    ],
    "sg:phone":"+1 403 236 2992",
    "sg:postcode":"T2C 2N5",
    "sg:province":"AB",
    "wof:name":"Gilmore Denture Clinic",
    "wof:placetype":"venue"
},
  "geometry": {"coordinates":[-114.015586853,50.9834861755],"type":"Point"}
}