{
  "type": "Feature",
  "properties": {
    "addr:full":"Mississauga ON L5N 6S2",
    "addr:postcode":"l5n 6s2",
    "iso:country":"CA",
    "sg:city":"Mississauga",
    "sg:classifiers":[
        {
            "category":"Education",
            "subcategory":"Special Training",
            "type":"Public Place"
        }
    ],
    "sg:phone":"+1 905 821 2444",
    "sg:postcode":"L5N 6S2",
    "sg:province":"ON",
    "sg:tags":[
        "management"
    ],
    "wof:name":"Cycle Time Management Inc",
    "wof:placetype":"venue"
},
  "geometry": {"coordinates":[-79.7736358643,43.6037864685],"type":"Point"}
}