{
  "type": "Feature",
  "properties": {
    "addr:full":"945 Av Des Bouleaux Plessisville QC G6L 2S1",
    "addr:postcode":"g6l 2s1",
    "addr:street":"945 Av Des Bouleaux",
    "iso:country":"CA",
    "sg:address":"945 Av Des Bouleaux",
    "sg:city":"Plessisville",
    "sg:classifiers":[
        {
            "category":"Building & Trades",
            "subcategory":"Construction",
            "type":"Services"
        }
    ],
    "sg:phone":"+1 819 362 3675",
    "sg:postcode":"G6L 2S1",
    "sg:province":"QC",
    "sg:tags":[
        "foundation"
    ],
    "wof:name":"Fondations Plessisville Inc",
    "wof:placetype":"venue"
},
  "geometry": {"coordinates":[-71.76332855219999,46.2145996094],"type":"Point"}
}