{
  "type": "Feature",
  "properties": {
    "addr:full":"310 Rue Principale Grenville QC J0V 1J0",
    "addr:housenumber":"310",
    "addr:postcode":"j0v 1j0",
    "addr:street":"Rue Principale",
    "iso:country":"CA",
    "sg:address":"310 Rue Principale",
    "sg:city":"Grenville",
    "sg:classifiers":[
        {
            "category":"Taxi",
            "type":"Transportation"
        }
    ],
    "sg:phone":"+1 819 242 3530",
    "sg:postcode":"J0V 1J0",
    "sg:province":"QC",
    "sg:tags":[
        "taxicab",
        "tours",
        "sightseeing"
    ],
    "wof:name":"Larocque Taxi Grenville",
    "wof:placetype":"venue"
},
  "geometry": {"coordinates":[-74.604271,45.627129],"type":"Point"}
}