{
  "type": "Feature",
  "properties": {
    "iso:country":"CA",
    "sg:address":"773098 Hwy 59 S",
    "sg:city":"Norwich",
    "sg:classifiers":[
        {
            "category":"Manufacturing",
            "subcategory":"Building Materials",
            "type":"Manufacturing & Wholesale Goods"
        }
    ],
    "sg:phone":"+1 519 468 6979",
    "sg:postcode":"N0J 1P0",
    "sg:province":"ON",
    "wof:name":"J & J Precast Ltd",
    "wof:placetype":"venue"
},
  "geometry": {"coordinates":[-80.7347335815,43.1078453064],"type":"Point"}
}