{
  "type": "Feature",
  "properties": {
    "addr:full":"8 Concorde Pl North York ON M3C 3K2",
    "addr:housenumber":"8",
    "addr:postcode":"m3c 3k2",
    "addr:street":"Concorde Pl",
    "iso:country":"CA",
    "sg:address":"8 Concorde Pl",
    "sg:city":"North York",
    "sg:classifiers":[
        {
            "category":"Real Estate",
            "subcategory":"Real Estate Operator",
            "type":"Services"
        }
    ],
    "sg:phone":"+1 416 445 2221",
    "sg:postcode":"M3C 3K2",
    "sg:province":"ON",
    "sg:tags":[
        "apartment"
    ],
    "wof:name":"Cadillac Fairview Corp Ltd",
    "wof:placetype":"venue"
},
  "geometry": {"coordinates":[-79.328506,43.729443],"type":"Point"}
}