{
  "type": "Feature",
  "properties": {
    "iso:country":"CA",
    "sg:address":"120 Jasper St",
    "sg:city":"Maple Creek",
    "sg:classifiers":[
        {
            "category":"Home & Garden",
            "subcategory":"Household Appliances",
            "type":"Retail Goods"
        }
    ],
    "sg:phone":"+1 306 662 3866",
    "sg:postcode":"S0N 1N0",
    "sg:province":"SK",
    "sg:tags":[
        "equipment",
        "satellite",
        "system"
    ],
    "wof:name":"Walter's Home Furnishings",
    "wof:placetype":"venue"
},
  "geometry": {"coordinates":[-109.47830200200001,49.9089622498],"type":"Point"}
}