{
  "type": "Feature",
  "properties": {
    "addr:full":"893 King St W Hamilton ON L8S 1K5",
    "addr:housenumber":"893",
    "addr:postcode":"l8s 1k5",
    "addr:street":"King St W",
    "iso:country":"CA",
    "sg:address":"893 King St W",
    "sg:city":"Hamilton",
    "sg:classifiers":[
        {
            "category":"Restaurant",
            "type":"Food & Drink"
        }
    ],
    "sg:phone":"+1 905 529 2605",
    "sg:postcode":"L8S 1K5",
    "sg:province":"ON",
    "sg:tags":[
        "delicatessen"
    ],
    "wof:name":"Westdale Delicatessen",
    "wof:placetype":"venue"
},
  "geometry": {"coordinates":[-79.901428,43.263035],"type":"Point"}
}