{
  "type": "Feature",
  "properties": {
    "addr:full":"Vancouver BC V6Z 2S7",
    "addr:postcode":"v6z 2s7",
    "iso:country":"CA",
    "sg:city":"Vancouver",
    "sg:classifiers":[
        {
            "category":"Restaurant",
            "type":"Food & Drink"
        }
    ],
    "sg:phone":"+1 604 683 6518",
    "sg:postcode":"V6Z 2S7",
    "sg:province":"BC",
    "wof:name":"88 Juice & More",
    "wof:placetype":"venue"
},
  "geometry": {"coordinates":[-123.126785278,49.277721405],"type":"Point"}
}