{
  "type": "Feature",
  "properties": {
    "iso:country":"CA",
    "sg:address":"2424 Ch Sainte-Marie",
    "sg:city":"Mascouche",
    "sg:classifiers":[
        {
            "category":"Retail",
            "subcategory":"Repair Shop",
            "type":"Services"
        }
    ],
    "sg:phone":"+1 450 474 3153",
    "sg:postcode":"J7K 1M5",
    "sg:province":"QC",
    "sg:tags":[
        "upholsterer"
    ],
    "wof:name":"Atelier Ld Enrg",
    "wof:placetype":"venue"
},
  "geometry": {"coordinates":[-73.6214981079,45.7538337708],"type":"Point"}
}