{
  "type": "Feature",
  "properties": {
    "addr:full":"510 2nd Ave Loon Lake SK S0M 1L0",
    "addr:housenumber":"510",
    "addr:postcode":"s0m 1l0",
    "addr:street":"2Nd Ave",
    "iso:country":"CA",
    "sg:address":"510 2nd Ave",
    "sg:city":"Loon Lake",
    "sg:classifiers":[
        {
            "category":"Health Services",
            "subcategory":"Hospital",
            "type":"Services"
        }
    ],
    "sg:phone":"+1 306 837 2114",
    "sg:postcode":"S0M 1L0",
    "sg:province":"SK",
    "wof:name":"Loon Lake Hospital & Special",
    "wof:placetype":"venue"
},
  "geometry": {"coordinates":[-109.158852,54.027138],"type":"Point"}
}