{
  "type": "Feature",
  "properties": {
    "addr:full":"Moose Jaw SK S6H 7J5",
    "addr:postcode":"s6h 7j5",
    "iso:country":"CA",
    "sg:city":"Moose Jaw",
    "sg:classifiers":[
        {
            "category":"Real Estate",
            "subcategory":"Real Estate Operator",
            "type":"Services"
        }
    ],
    "sg:phone":"+1 306 692 4419",
    "sg:postcode":"S6H 7J5",
    "sg:province":"SK",
    "sg:tags":[
        "apartment"
    ],
    "wof:name":"Prairie Meadows",
    "wof:placetype":"venue"
},
  "geometry": {"coordinates":[-105.56506299999999,50.382812],"type":"Point"}
}