{
  "type": "Feature",
  "properties": {
    "addr:full":"7700 Rue DE Lamartine Anjou QC H1J 2A8",
    "addr:housenumber":"7700",
    "addr:postcode":"h1j 2a8",
    "addr:street":"Rue De Lamartine",
    "iso:country":"CA",
    "sg:address":"7700 Rue DE Lamartine",
    "sg:city":"Anjou",
    "sg:classifiers":[
        {
            "category":"Manufacturing",
            "subcategory":"Tools & Machinery",
            "type":"Manufacturing & Wholesale Goods"
        }
    ],
    "sg:phone":"+1 514 355 3690",
    "sg:postcode":"H1J 2A8",
    "sg:province":"QC",
    "sg:tags":[
        "equipment",
        "die",
        "cutting",
        "supply"
    ],
    "wof:name":"Usm Canada Ltd",
    "wof:placetype":"venue"
},
  "geometry": {"coordinates":[-73.57880400000001,45.611511],"type":"Point"}
}