{
  "type": "Feature",
  "properties": {
    "iso:country":"CA",
    "sg:address":"2098 Robertson Rd",
    "sg:city":"Prince George",
    "sg:classifiers":[
        {
            "category":"Wholesale",
            "subcategory":"Auto Parts",
            "type":"Manufacturing & Wholesale Goods"
        }
    ],
    "sg:phone":"+1 250 561 2448",
    "sg:postcode":"V2N 1X6",
    "sg:province":"BC",
    "sg:tags":[
        "brakes"
    ],
    "wof:name":"Morgan Brake & Industrial Supl",
    "wof:placetype":"venue"
},
  "geometry": {"coordinates":[-122.79476928699999,53.9047431946],"type":"Point"}
}