{
  "type": "Feature",
  "properties": {
    "addr:full":"34 Midlake Blvd SE Calgary AB T2X 2X7",
    "addr:housenumber":"34",
    "addr:postcode":"t2x 2x7",
    "addr:street":"Midlake Blvd Se",
    "iso:country":"CA",
    "sg:address":"34 Midlake Blvd SE",
    "sg:city":"Calgary",
    "sg:classifiers":[
        {
            "category":"Banks & Credit Unions",
            "subcategory":"Bank",
            "type":"Services"
        }
    ],
    "sg:phone":"+1 403 221 6595",
    "sg:postcode":"T2X 2X7",
    "sg:province":"AB",
    "wof:name":"Scotiabank",
    "wof:placetype":"venue"
},
  "geometry": {"coordinates":[-114.06205,50.914879],"type":"Point"}
}