{
  "type": "Feature",
  "properties": {
    "addr:full":"10510 107 Ave NW Edmonton AB T5H 0W2",
    "addr:housenumber":"10510",
    "addr:postcode":"t5h 0w2",
    "addr:street":"107 Ave Nw",
    "iso:country":"CA",
    "sg:address":"10510 107 Ave NW",
    "sg:city":"Edmonton",
    "sg:classifiers":[
        {
            "category":"Organizations",
            "subcategory":"Professional Association",
            "type":"Services"
        }
    ],
    "sg:phone":"+1 780 420 6114",
    "sg:postcode":"T5H 0W2",
    "sg:province":"AB",
    "wof:name":"River City Athletic Club",
    "wof:placetype":"venue"
},
  "geometry": {"coordinates":[-113.501411,53.551544],"type":"Point"}
}