{
  "type": "Feature",
  "properties": {
    "addr:full":"449 Provencher Blvd. Winnipeg R2J 0B8",
    "addr:housenumber":"449",
    "addr:postcode":"r2j 0b8",
    "addr:street":"Provencher Blvd.",
    "iso:country":"CA",
    "sg:address":"449 Provencher Blvd.",
    "sg:city":"Winnipeg",
    "sg:classifiers":[
        {
            "category":"Professional",
            "subcategory":"Computer Services",
            "type":"Services"
        }
    ],
    "sg:postcode":"R2J 0B8",
    "sg:tags":[
        "website-monitoring",
        "free-website-monitoring",
        "server-monitoring",
        "uptime-monitoring",
        "ping-monitoring",
        "website-availability-monitoring"
    ],
    "sg:website":"http://binarycanary.com",
    "wof:name":"BinaryCanary.com",
    "wof:placetype":"venue"
},
  "geometry": {"coordinates":[-97.10889830000001,49.8955474],"type":"Point"}
}