{
  "type": "Feature",
  "properties": {
    "addr:full":"28 1/2 King St E Hamilton ON L8N 1A3",
    "addr:housenumber":"1 / 2",
    "addr:postcode":"l8n 1a3",
    "addr:street":"28;King St E",
    "iso:country":"CA",
    "sg:address":"28 1/2 King St E",
    "sg:city":"Hamilton",
    "sg:classifiers":[
        {
            "category":"Education",
            "subcategory":"Dance Studio",
            "type":"Public Place"
        }
    ],
    "sg:phone":"+1 905 527 8336",
    "sg:postcode":"L8N 1A3",
    "sg:province":"ON",
    "sg:tags":[
        "instruction",
        "dancing"
    ],
    "wof:name":"Bailey School of Dancing",
    "wof:placetype":"venue"
},
  "geometry": {"coordinates":[-79.86856079099999,43.2559738159],"type":"Point"}
}