{
  "type": "Feature",
  "properties": {
    "addr:full":"410 Industrial Road No A Cranbrook BC V1C 4Z3",
    "addr:housenumber":"410",
    "addr:postcode":"v1c 4z3",
    "addr:street":"Industrial Road No A",
    "iso:country":"CA",
    "sg:address":"410 Industrial Road No A",
    "sg:city":"Cranbrook",
    "sg:classifiers":[
        {
            "category":"Wholesale",
            "subcategory":"Machinery & Supplies",
            "type":"Manufacturing & Wholesale Goods"
        }
    ],
    "sg:phone":"+1 250 489 3341",
    "sg:postcode":"V1C 4Z3",
    "sg:province":"BC",
    "sg:tags":[
        "rubber",
        "product"
    ],
    "wof:name":"Goodall Rubber",
    "wof:placetype":"venue"
},
  "geometry": {"coordinates":[-115.762245178,49.5239677429],"type":"Point"}
}