{
  "type": "Feature",
  "properties": {
    "addr:full":"1445 Rue Tees Saint-Laurent QC H4R 2A7",
    "addr:housenumber":"1445",
    "addr:postcode":"h4r 2a7",
    "addr:street":"Rue Tees Saint-Laurent",
    "iso:country":"CA",
    "sg:address":"1445 Rue Tees",
    "sg:city":"Saint-Laurent",
    "sg:classifiers":[
        {
            "category":"Manufacturing",
            "subcategory":"Tools & Machinery",
            "type":"Manufacturing & Wholesale Goods"
        }
    ],
    "sg:phone":"+1 514 333 6393",
    "sg:postcode":"H4R 2A7",
    "sg:province":"QC",
    "sg:tags":[
        "product",
        "paper",
        "cash",
        "register"
    ],
    "wof:name":"Maxwell Quebec",
    "wof:placetype":"venue"
},
  "geometry": {"coordinates":[-73.715675,45.494034],"type":"Point"}
}