{
  "type": "Feature",
  "properties": {
    "iso:country":"CA",
    "sg:address":"33 Cameron St E",
    "sg:city":"Cannington",
    "sg:classifiers":[
        {
            "category":"Home & Garden",
            "subcategory":"Furniture",
            "type":"Retail Goods"
        }
    ],
    "sg:phone":"+1 705 432 2768",
    "sg:postcode":"L0E 1E0",
    "sg:province":"ON",
    "wof:name":"Patterson's Furniture CO Ltd",
    "wof:placetype":"venue"
},
  "geometry": {"coordinates":[-79.0373077393,44.3503875732],"type":"Point"}
}