{
  "type": "Feature",
  "properties": {
    "addr:full":"8005 King George Hwy Surrey BC V3W 5B4",
    "addr:housenumber":"8005",
    "addr:postcode":"v3w 5b4",
    "addr:street":"King George Hwy",
    "iso:country":"CA",
    "sg:address":"8005 King George Hwy",
    "sg:city":"Surrey",
    "sg:classifiers":[
        {
            "category":"Food & Beverages",
            "subcategory":"Bakery",
            "type":"Retail Goods"
        }
    ],
    "sg:phone":"+1 604 590 3122",
    "sg:postcode":"V3W 5B4",
    "sg:province":"BC",
    "sg:tags":[
        "doughnut"
    ],
    "wof:name":"Robin's Donuts",
    "wof:placetype":"venue"
},
  "geometry": {"coordinates":[-122.845932007,49.1484222412],"type":"Point"}
}