{
  "type": "Feature",
  "properties": {
    "addr:full":"Ancaster ON L9G 4A8",
    "addr:postcode":"l9g 4a8",
    "iso:country":"CA",
    "sg:city":"Ancaster",
    "sg:classifiers":[
        {
            "category":"Health Services",
            "subcategory":"Doctor",
            "type":"Services"
        }
    ],
    "sg:phone":"+1 905 648 1112",
    "sg:postcode":"L9G 4A8",
    "sg:province":"ON",
    "sg:tags":[
        "physician",
        "surgeon"
    ],
    "wof:name":"Stephenson, Michael MD",
    "wof:placetype":"venue"
},
  "geometry": {"coordinates":[-79.976685,43.226547],"type":"Point"}
}