{
  "type": "Feature",
  "properties": {
    "addr:full":"2220 Davis Dr Newmarket ON L3Y 4W1",
    "addr:housenumber":"2220",
    "addr:postcode":"l3y 4w1",
    "addr:street":"Davis Dr",
    "iso:country":"CA",
    "sg:address":"2220 Davis Dr",
    "sg:city":"Newmarket",
    "sg:phone":"+1 905 895 2222",
    "sg:postcode":"L3Y 4W1",
    "sg:province":"ON",
    "sg:tags":[
        "oil"
    ],
    "wof:name":"Esso Home Comfort Ctr",
    "wof:placetype":"venue"
},
  "geometry": {"coordinates":[-79.42456799999999,44.067451],"type":"Point"}
}