{
  "type": "Feature",
  "properties": {
    "iso:country":"CA",
    "sg:address":"339 River Rd",
    "sg:city":"Arborg",
    "sg:classifiers":[
        {
            "category":"Shopping",
            "subcategory":"Crafts & Fabrics",
            "type":"Retail Goods"
        }
    ],
    "sg:phone":"+1 204 376 2711",
    "sg:postcode":"R0C 0A0",
    "sg:province":"MB",
    "sg:tags":[
        "yarn"
    ],
    "wof:name":"Yarn Paradise",
    "wof:placetype":"venue"
},
  "geometry": {"coordinates":[-97.2188796997,50.9064788818],"type":"Point"}
}