{
  "type": "Feature",
  "properties": {
    "addr:full":"Calgary AB T2E 6V6",
    "addr:postcode":"t2e 6v6",
    "iso:country":"CA",
    "sg:city":"Calgary",
    "sg:classifiers":[
        {
            "category":"Wholesale",
            "subcategory":"Electrical",
            "type":"Manufacturing & Wholesale Goods"
        }
    ],
    "sg:phone":"+1 403 291 9337",
    "sg:postcode":"T2E 6V6",
    "sg:province":"AB",
    "sg:tags":[
        "electric",
        "motor"
    ],
    "wof:name":"Complete Electric Motor Repair",
    "wof:placetype":"venue"
},
  "geometry": {"coordinates":[-114.008422852,51.0843811035],"type":"Point"}
}