{
  "type": "Feature",
  "properties": {
    "iso:country":"CA",
    "sg:address":"1460 Sugar Rd # 4",
    "sg:city":"Gloucester",
    "sg:classifiers":[
        {
            "category":"Shopping",
            "type":"Retail Goods"
        }
    ],
    "sg:phone":"+1 613 744 7890",
    "sg:postcode":"K1B 3L9",
    "sg:province":"ON",
    "sg:tags":[
        "monument"
    ],
    "wof:name":"Bigras Granite Enrg",
    "wof:placetype":"venue"
},
  "geometry": {"coordinates":[-75.618523,45.420204],"type":"Point"}
}