{
  "type": "Feature",
  "properties": {
    "addr:full":"4339 50 St NW Edmonton AB T6L 7E8",
    "addr:housenumber":"4339",
    "addr:postcode":"t6l 7e8",
    "addr:street":"50 St Nw",
    "iso:country":"CA",
    "sg:address":"4339 50 St NW",
    "sg:city":"Edmonton",
    "sg:classifiers":[
        {
            "category":"Personal",
            "subcategory":"Beauty Salon",
            "type":"Services"
        }
    ],
    "sg:phone":"+1 780 440 9425",
    "sg:postcode":"T6L 7E8",
    "sg:province":"AB",
    "wof:name":"Vip Hair & Esthetics Inc",
    "wof:placetype":"venue"
},
  "geometry": {"coordinates":[-113.417778,53.480824],"type":"Point"}
}