{
  "type": "Feature",
  "properties": {
    "iso:country":"CA",
    "sg:address":"307 King St",
    "sg:city":"Bridgewater",
    "sg:classifiers":[
        {
            "category":"Organizations",
            "subcategory":"Religious Organization",
            "type":"Services"
        }
    ],
    "sg:phone":"+1 902 543 8230",
    "sg:postcode":"B4V 1A8",
    "sg:province":"NS",
    "sg:tags":[
        "church"
    ],
    "wof:name":"Bridgewater United Baptist Chr",
    "wof:placetype":"venue"
},
  "geometry": {"coordinates":[-64.5142593384,44.374370575],"type":"Point"}
}