{
  "type": "Feature",
  "properties": {
    "addr:full":"1231 Boul DE Montarville Boucherville QC J4B 8B2",
    "addr:housenumber":"1231",
    "addr:postcode":"j4b 8b2",
    "addr:street":"Boul De Montarville",
    "iso:country":"CA",
    "sg:address":"1231 Boul DE Montarville",
    "sg:city":"Boucherville",
    "sg:classifiers":[
        {
            "category":"Recreation",
            "type":"Entertainment"
        }
    ],
    "sg:phone":"+1 450 449 9140",
    "sg:postcode":"J4B 8B2",
    "sg:province":"QC",
    "sg:tags":[
        "range",
        "practice",
        "golf"
    ],
    "wof:name":"Centre DE Pratique DE Golf",
    "wof:placetype":"venue"
},
  "geometry": {"coordinates":[-73.425316,45.582275],"type":"Point"}
}