{
  "type": "Feature",
  "properties": {
    "addr:full":"177 Iroquois St W Moose Jaw SK S6H 5A6",
    "addr:housenumber":"177",
    "addr:postcode":"s6h 5a6",
    "addr:street":"Iroquois St W",
    "iso:country":"CA",
    "sg:address":"177 Iroquois St W",
    "sg:city":"Moose Jaw",
    "sg:classifiers":[
        {
            "category":"Education",
            "subcategory":"Dance Studio",
            "type":"Public Place"
        }
    ],
    "sg:phone":"+1 306 692 0515",
    "sg:postcode":"S6H 5A6",
    "sg:province":"SK",
    "sg:tags":[
        "school",
        "instruction",
        "dancing"
    ],
    "wof:name":"Dance Images By B J's",
    "wof:placetype":"venue"
},
  "geometry": {"coordinates":[-105.539085388,50.3831787109],"type":"Point"}
}