{
  "type": "Feature",
  "properties": {
    "addr:full":"1222 Lawrence Ave E North York ON M3A 1B9",
    "addr:housenumber":"1222",
    "addr:postcode":"m3a 1b9",
    "addr:street":"Lawrence Ave E",
    "iso:country":"CA",
    "sg:address":"1222 Lawrence Ave E",
    "sg:city":"North York",
    "sg:classifiers":[
        {
            "category":"Restaurant",
            "type":"Food & Drink"
        }
    ],
    "sg:phone":"+1 416 443 0616",
    "sg:postcode":"M3A 1B9",
    "sg:province":"ON",
    "wof:name":"Valley Fields Family Rstrnt",
    "wof:placetype":"venue"
},
  "geometry": {"coordinates":[-79.32191467289999,43.7411422729],"type":"Point"}
}