{
  "type": "Feature",
  "properties": {
    "addr:full":"83 Mary St Georgetown ON L7G 4V9",
    "addr:housenumber":"83",
    "addr:postcode":"l7g 4v9",
    "addr:street":"Mary St",
    "iso:country":"CA",
    "sg:address":"83 Mary St",
    "sg:city":"Georgetown",
    "sg:classifiers":[
        {
            "category":"Insurance",
            "subcategory":"Life Insurance",
            "type":"Services"
        }
    ],
    "sg:phone":"+1 905 877 4575",
    "sg:postcode":"L7G 4V9",
    "sg:province":"ON",
    "wof:name":"Triplus Financial Security",
    "wof:placetype":"venue"
},
  "geometry": {"coordinates":[-79.932655,43.646172],"type":"Point"}
}