{
  "type": "Feature",
  "properties": {
    "addr:full":"137 Londonderry Mall NW Edmonton AB T5C 3C8",
    "addr:housenumber":"137",
    "addr:postcode":"t5c 3c8",
    "addr:street":"Londonderry Mall Nw",
    "iso:country":"CA",
    "sg:address":"137 Londonderry Mall NW",
    "sg:city":"Edmonton",
    "sg:classifiers":[
        {
            "category":"Shopping",
            "subcategory":"Discount & Variety Stores",
            "type":"Retail Goods"
        }
    ],
    "sg:phone":"+1 780 406 5699",
    "sg:postcode":"T5C 3C8",
    "sg:province":"AB",
    "wof:name":"Everything For A Dollar Store",
    "wof:placetype":"venue"
},
  "geometry": {"coordinates":[-113.49037199999999,53.546219],"type":"Point"}
}