{
  "type": "Feature",
  "properties": {
    "addr:full":"349 Churchill Ave N Ottawa ON K1Z 5B8",
    "addr:housenumber":"349",
    "addr:postcode":"k1z 5b8",
    "addr:street":"Churchill Ave N",
    "iso:country":"CA",
    "sg:address":"349 Churchill Ave N",
    "sg:city":"Ottawa",
    "sg:classifiers":[
        {
            "category":"Building & Trades",
            "subcategory":"Electrical",
            "type":"Services"
        }
    ],
    "sg:phone":"+1 613 725 1790",
    "sg:postcode":"K1Z 5B8",
    "sg:province":"ON",
    "sg:tags":[
        "electric",
        "contractor"
    ],
    "wof:name":"Bradmoore Electric CO Ltd",
    "wof:placetype":"venue"
},
  "geometry": {"coordinates":[-75.75462341310001,45.3937072754],"type":"Point"}
}