{
  "type": "Feature",
  "properties": {
    "addr:full":"38 Av William-Dobell Baie-Comeau QC G4Z 1T7",
    "addr:postcode":"g4z 1t7",
    "addr:street":"38 Av William-Dobell",
    "iso:country":"CA",
    "sg:address":"38 Av William-Dobell",
    "sg:city":"Baie-Comeau",
    "sg:classifiers":[
        {
            "category":"Wholesale",
            "subcategory":"Chemicals & Plastics",
            "type":"Manufacturing & Wholesale Goods"
        }
    ],
    "sg:phone":"+1 418 296 5049",
    "sg:postcode":"G4Z 1T7",
    "sg:province":"QC",
    "sg:tags":[
        "sanitary",
        "product",
        "supply"
    ],
    "wof:name":"Hygipro Inc",
    "wof:placetype":"venue"
},
  "geometry": {"coordinates":[-68.1816940308,49.2174797058],"type":"Point"}
}