{
  "type": "Feature",
  "properties": {
    "addr:full":"PO Box 7 Worsley AB T0H 3W0",
    "addr:housenumber":"po;7",
    "addr:postcode":"t0h 3w0",
    "addr:street":"Box",
    "iso:country":"CA",
    "sg:address":"PO Box 7",
    "sg:city":"Worsley",
    "sg:classifiers":[
        {
            "category":"Mining & Drilling",
            "type":"Manufacturing & Wholesale Goods"
        }
    ],
    "sg:phone":"+1 780 685 3790",
    "sg:postcode":"T0H 3W0",
    "sg:province":"AB",
    "sg:tags":[
        "field",
        "oil"
    ],
    "wof:name":"D Shanks Grader Svc",
    "wof:placetype":"venue"
},
  "geometry": {"coordinates":[-119.13988500000001,56.508717],"type":"Point"}
}