{
  "type": "Feature",
  "properties": {
    "addr:full":"496 Garrison Rd Fort Erie ON L2A 1N2",
    "addr:housenumber":"496",
    "addr:postcode":"l2a 1n2",
    "addr:street":"Garrison Rd",
    "iso:country":"CA",
    "sg:address":"496 Garrison Rd",
    "sg:city":"Fort Erie",
    "sg:classifiers":[
        {
            "category":"Autos & Motor Vehicles",
            "subcategory":"Automobile Sales",
            "type":"Retail Goods"
        }
    ],
    "sg:phone":"+1 905 871 8848",
    "sg:postcode":"L2A 1N2",
    "sg:province":"ON",
    "sg:tags":[
        "car",
        "dealer"
    ],
    "wof:name":"Great Lakes Motors",
    "wof:placetype":"venue"
},
  "geometry": {"coordinates":[-78.9335098267,42.9055633545],"type":"Point"}
}