{
  "type": "Feature",
  "properties": {
    "addr:full":"633 Ready St Saint John NB E2M 3S4",
    "addr:housenumber":"633",
    "addr:postcode":"e2m 3s4",
    "addr:street":"Ready St",
    "iso:country":"CA",
    "sg:address":"633 Ready St",
    "sg:city":"Saint John",
    "sg:classifiers":[
        {
            "category":"Retail",
            "subcategory":"Car Wash",
            "type":"Services"
        }
    ],
    "sg:phone":"+1 506 635 2113",
    "sg:postcode":"E2M 3S4",
    "sg:province":"NB",
    "sg:tags":[
        "automobile",
        "detail",
        "clean"
    ],
    "wof:name":"Kelly's Wash Tech",
    "wof:placetype":"venue"
},
  "geometry": {"coordinates":[-66.09687,45.255051],"type":"Point"}
}