{
  "type": "Feature",
  "properties": {
    "addr:full":"188 Main St Central Butte SK S0H 0T0",
    "addr:housenumber":"188",
    "addr:postcode":"s0h 0t0",
    "addr:street":"Main St",
    "iso:country":"CA",
    "sg:address":"188 Main St",
    "sg:city":"Central Butte",
    "sg:classifiers":[
        {
            "category":"Travel",
            "subcategory":"Travel Agent",
            "type":"Entertainment"
        }
    ],
    "sg:phone":"+1 306 796 2000",
    "sg:postcode":"S0H 0T0",
    "sg:province":"SK",
    "sg:tags":[
        "agency",
        "bureau",
        "insurance"
    ],
    "wof:name":"Mc Gregor's Travel Agency",
    "wof:placetype":"venue"
},
  "geometry": {"coordinates":[-106.512497,50.796154],"type":"Point"}
}