{
  "type": "Feature",
  "properties": {
    "iso:country":"CA",
    "sg:address":"PO Box 99",
    "sg:city":"Fort Good Hope",
    "sg:classifiers":[
        {
            "category":"Education",
            "subcategory":"School",
            "type":"Public Place"
        }
    ],
    "sg:phone":"+1 867 598 2288",
    "sg:postcode":"X0E 0H0",
    "sg:province":"NT",
    "wof:name":"Chief Tselihye School",
    "wof:placetype":"venue"
},
  "geometry": {"coordinates":[-128.60774230999999,66.2466201782],"type":"Point"}
}