{
  "type": "Feature",
  "properties": {
    "iso:country":"CA",
    "sg:city":"Toronto",
    "sg:classifiers":[
        {
            "category":"Social Services",
            "type":"Services"
        }
    ],
    "sg:phone":"+1 416 703 5459",
    "sg:postcode":"M6J 1G1",
    "sg:province":"ON",
    "sg:tags":[
        "organization",
        "welfare"
    ],
    "wof:name":"761 Community Dev Corp",
    "wof:placetype":"venue"
},
  "geometry": {"coordinates":[-79.40786,43.64629],"type":"Point"}
}