{
  "type": "Feature",
  "properties": {
    "addr:full":"6143 Snowy Owl Cres Mississauga ON L5N 7B5",
    "addr:housenumber":"6143",
    "addr:postcode":"l5n 7b5",
    "addr:street":"Snowy Owl Cres",
    "iso:country":"CA",
    "sg:address":"6143 Snowy Owl Cres",
    "sg:city":"Mississauga",
    "sg:classifiers":[
        {
            "category":"Building & Trades",
            "subcategory":"Landscaping Services",
            "type":"Services"
        }
    ],
    "sg:phone":"+1 905 858 8003",
    "sg:postcode":"L5N 7B5",
    "sg:province":"ON",
    "sg:tags":[
        "lawn",
        "maintenance",
        "grounds"
    ],
    "wof:name":"Landmark Landscaping",
    "wof:placetype":"venue"
},
  "geometry": {"coordinates":[-79.75936889650001,43.5569000244],"type":"Point"}
}