{
  "type": "Feature",
  "properties": {
    "addr:full":"Etobicoke ON M9V 5G4",
    "addr:postcode":"m9v 5g4",
    "iso:country":"CA",
    "sg:city":"Etobicoke",
    "sg:classifiers":[
        {
            "category":"Shopping",
            "subcategory":"Pharmacy",
            "type":"Retail Goods"
        }
    ],
    "sg:phone":"+1 416 744 3434",
    "sg:postcode":"M9V 5G4",
    "sg:province":"ON",
    "wof:name":"Humber Green Pharmacy",
    "wof:placetype":"venue"
},
  "geometry": {"coordinates":[-79.599327,43.731102],"type":"Point"}
}