{
  "type": "Feature",
  "properties": {
    "addr:full":"6085 Rue Jean-Talon E Saint-Leonard QC H1S 1M6",
    "addr:housenumber":"6085",
    "addr:postcode":"h1s 1m6",
    "addr:street":"Rue Jean-Talon E",
    "iso:country":"CA",
    "sg:address":"6085 Rue Jean-Talon E",
    "sg:city":"Saint-Leonard",
    "sg:classifiers":[
        {
            "category":"Insurance",
            "subcategory":"Insurance Agent",
            "type":"Services"
        }
    ],
    "sg:phone":"+1 514 259 9521",
    "sg:postcode":"H1S 1M6",
    "sg:province":"QC",
    "wof:name":"Les Assurences A Di Giocchino",
    "wof:placetype":"venue"
},
  "geometry": {"coordinates":[-73.578377,45.588116],"type":"Point"}
}