{
  "type": "Feature",
  "properties": {
    "iso:country":"CA",
    "sg:address":"870 Campbell Ave",
    "sg:city":"Ottawa",
    "sg:classifiers":[
        {
            "category":"Building & Trades",
            "subcategory":"Cleaning & Sanitation",
            "type":"Services"
        }
    ],
    "sg:phone":"+1 613 722 3566",
    "sg:postcode":"K2A 2C5",
    "sg:province":"ON",
    "sg:tags":[
        "janitor"
    ],
    "wof:name":"Ability Janitorial Svc Ltd",
    "wof:placetype":"venue"
},
  "geometry": {"coordinates":[-75.75080871580001,45.3777313232],"type":"Point"}
}