{
  "type": "Feature",
  "properties": {
    "addr:full":"828 Rue Des Sapins Saint-Eustache QC J7R 6K7",
    "addr:housenumber":"828",
    "addr:postcode":"j7r 6k7",
    "addr:street":"Rue Des Sapins",
    "iso:country":"CA",
    "sg:address":"828 Rue Des Sapins",
    "sg:city":"Saint-Eustache",
    "sg:classifiers":[
        {
            "category":"Building & Trades",
            "subcategory":"Electrical",
            "type":"Services"
        }
    ],
    "sg:phone":"+1 450 974 7005",
    "sg:postcode":"J7R 6K7",
    "sg:province":"QC",
    "sg:tags":[
        "electric",
        "contractor"
    ],
    "wof:name":"Rene Pelletier Enrg",
    "wof:placetype":"venue"
},
  "geometry": {"coordinates":[-73.928543,45.583061],"type":"Point"}
}