{
  "type": "Feature",
  "properties": {
    "addr:full":"475 Av Dumont # 103 Dorval QC H9S 5W2",
    "addr:housenumber":"475",
    "addr:postcode":"h9s 5w2",
    "addr:street":"Av Dumont # 103",
    "iso:country":"CA",
    "sg:address":"475 Av Dumont # 103",
    "sg:city":"Dorval",
    "sg:classifiers":[
        {
            "category":"Cinema",
            "subcategory":"Movie Rental",
            "type":"Entertainment"
        }
    ],
    "sg:phone":"+1 514 633 9477",
    "sg:postcode":"H9S 5W2",
    "sg:province":"QC",
    "sg:tags":[
        "leasing",
        "video",
        "disc",
        "tape"
    ],
    "wof:name":"Club Video 29 Cents",
    "wof:placetype":"venue"
},
  "geometry": {"coordinates":[-73.751617,45.447742],"type":"Point"}
}