{
  "type": "Feature",
  "properties": {
    "addr:full":"2522 Finch Ave W North York ON M9M 2G3",
    "addr:housenumber":"2522",
    "addr:postcode":"m9m 2g3",
    "addr:street":"Finch Ave W",
    "iso:country":"CA",
    "sg:address":"2522 Finch Ave W",
    "sg:city":"North York",
    "sg:classifiers":[
        {
            "category":"Shopping",
            "subcategory":"Clothing, Apparel, & Fashions",
            "type":"Retail Goods"
        }
    ],
    "sg:phone":"+1 416 740 7218",
    "sg:postcode":"M9M 2G3",
    "sg:province":"ON",
    "wof:name":"Mondo Moda Ladies Fashion",
    "wof:placetype":"venue"
},
  "geometry": {"coordinates":[-79.559692,43.748497],"type":"Point"}
}