{
  "type": "Feature",
  "properties": {
    "addr:full":"149 Rue John-Nairne LA Malbaie QC G5A 1M5",
    "addr:housenumber":"149",
    "addr:postcode":"g5a 1m5",
    "addr:street":"Rue John-Nairne",
    "iso:country":"CA",
    "sg:address":"149 Rue John-Nairne",
    "sg:city":"LA Malbaie",
    "sg:classifiers":[
        {
            "category":"Cinema",
            "subcategory":"Movie Rental",
            "type":"Entertainment"
        }
    ],
    "sg:phone":"+1 418 665 2373",
    "sg:postcode":"G5A 1M5",
    "sg:province":"QC",
    "sg:tags":[
        "leasing",
        "video",
        "disc",
        "tape"
    ],
    "wof:name":"Club Video Pro",
    "wof:placetype":"venue"
},
  "geometry": {"coordinates":[-70.151573,47.654236],"type":"Point"}
}