{
  "type": "Feature",
  "properties": {
    "iso:country":"CA",
    "sg:address":"8241 154 St",
    "sg:city":"Surrey",
    "sg:classifiers":[
        {
            "category":"Building & Trades",
            "subcategory":"Plumbing",
            "type":"Services"
        }
    ],
    "sg:phone":"+1 604 572 9491",
    "sg:postcode":"V3S 8M1",
    "sg:province":"BC",
    "sg:tags":[
        "contractor"
    ],
    "wof:name":"Skyline Plumbing & Heating Ltd",
    "wof:placetype":"venue"
},
  "geometry": {"coordinates":[-122.795837402,49.1528739929],"type":"Point"}
}