{
  "type": "Feature",
  "properties": {
    "addr:full":"258 King St W Hamilton ON L8P 1A9",
    "addr:housenumber":"258",
    "addr:postcode":"l8p 1a9",
    "addr:street":"King St W",
    "iso:country":"CA",
    "sg:address":"258 King St W",
    "sg:city":"Hamilton",
    "sg:classifiers":[
        {
            "category":"Retail",
            "subcategory":"Repair Shop",
            "type":"Services"
        }
    ],
    "sg:phone":"+1 905 522 0950",
    "sg:postcode":"L8P 1A9",
    "sg:province":"ON",
    "sg:tags":[
        "leather",
        "cleaning"
    ],
    "wof:name":"Macnamara Dilar Ltd",
    "wof:placetype":"venue"
},
  "geometry": {"coordinates":[-79.87683868409999,43.2589645386],"type":"Point"}
}