{
  "type": "Feature",
  "properties": {
    "addr:full":"Thunder Lake Hwy Barrhead AB T7N 1A2",
    "addr:postcode":"t7n 1a2",
    "addr:street":"Thunder Lake Hwy",
    "iso:country":"CA",
    "sg:address":"Thunder Lake Hwy",
    "sg:city":"Barrhead",
    "sg:classifiers":[
        {
            "category":"Retail",
            "subcategory":"Repair Shop",
            "type":"Services"
        }
    ],
    "sg:phone":"+1 780 674 2105",
    "sg:postcode":"T7N 1A2",
    "sg:province":"AB",
    "sg:tags":[
        "welding"
    ],
    "wof:name":"West Tac Welding Ltd",
    "wof:placetype":"venue"
},
  "geometry": {"coordinates":[-114.406006,54.120991],"type":"Point"}
}