{
  "type": "Feature",
  "properties": {
    "addr:full":"3650 Mount Seymour Pky # 174 North Vancouver BC V7H 2Y5",
    "addr:housenumber":"3650",
    "addr:postcode":"v7h 2y5",
    "addr:street":"Mount Seymour Pky # 174",
    "iso:country":"CA",
    "sg:address":"3650 Mount Seymour Pky # 174",
    "sg:city":"North Vancouver",
    "sg:classifiers":[
        {
            "category":"Shopping",
            "subcategory":"Clothing, Apparel, & Fashions",
            "type":"Retail Goods"
        }
    ],
    "sg:phone":"+1 604 924 2600",
    "sg:postcode":"V7H 2Y5",
    "sg:province":"BC",
    "wof:name":"Get Dressed",
    "wof:placetype":"venue"
},
  "geometry": {"coordinates":[-122.97062699999999,49.316036],"type":"Point"}
}