{
  "type": "Feature",
  "properties": {
    "iso:country":"CA",
    "sg:address":"771 Wallbridge-Loyalist Rd",
    "sg:city":"Belleville",
    "sg:classifiers":[
        {
            "category":"Wholesale",
            "subcategory":"Machinery & Supplies",
            "type":"Manufacturing & Wholesale Goods"
        }
    ],
    "sg:phone":"+1 613 969 6246",
    "sg:postcode":"K8N 4Z5",
    "sg:province":"ON",
    "sg:tags":[
        "farm",
        "equipment"
    ],
    "wof:name":"Anderson Equipment Sales",
    "wof:placetype":"venue"
},
  "geometry": {"coordinates":[-77.38189697270001,44.1610450745],"type":"Point"}
}