{
  "type": "Feature",
  "properties": {
    "addr:full":"Milk River AB T0K 1M0",
    "addr:postcode":"t0k 1m0",
    "iso:country":"CA",
    "sg:city":"Milk River",
    "sg:classifiers":[
        {
            "category":"Recreation",
            "type":"Entertainment"
        }
    ],
    "sg:phone":"+1 403 647 2011",
    "sg:postcode":"T0K 1M0",
    "sg:province":"AB",
    "sg:tags":[
        "pool",
        "swimming"
    ],
    "wof:name":"Milk River Swimming Pool",
    "wof:placetype":"venue"
},
  "geometry": {"coordinates":[-112.090996,49.153141],"type":"Point"}
}