{
  "type": "Feature",
  "properties": {
    "addr:full":"1498 Rue Bergeron Saint-Emile QC G3E 1G5",
    "addr:housenumber":"1498",
    "addr:postcode":"g3e 1g5",
    "addr:street":"Rue Bergeron Saint-Emile",
    "iso:country":"CA",
    "sg:address":"1498 Rue Bergeron",
    "sg:city":"Saint-Emile",
    "sg:classifiers":[
        {
            "category":"Building & Trades",
            "subcategory":"Construction",
            "type":"Services"
        }
    ],
    "sg:phone":"+1 418 843 4396",
    "sg:postcode":"G3E 1G5",
    "sg:province":"QC",
    "sg:tags":[
        "painter"
    ],
    "wof:name":"Entreprises Moisan & Gauvin",
    "wof:placetype":"venue"
},
  "geometry": {"coordinates":[-71.33223,46.86882],"type":"Point"}
}