{
  "type": "Feature",
  "properties": {
    "addr:full":"4995 Ch Queen-Mary Montreal QC H3W 1X4",
    "addr:housenumber":"4995",
    "addr:postcode":"h3w 1x4",
    "addr:street":"Ch Queen-Mary",
    "iso:country":"CA",
    "sg:address":"4995 Ch Queen-Mary",
    "sg:city":"Montreal",
    "sg:classifiers":[
        {
            "category":"Utilities",
            "subcategory":"Mobile Phone",
            "type":"Services"
        }
    ],
    "sg:phone":"+1 514 344 2355",
    "sg:postcode":"H3W 1X4",
    "sg:province":"QC",
    "sg:tags":[
        "telephone",
        "cellular"
    ],
    "wof:name":"Boutique Cellulaire Queen Mary",
    "wof:placetype":"venue"
},
  "geometry": {"coordinates":[-73.6270446777,45.486366272],"type":"Point"}
}