{
  "type": "Feature",
  "properties": {
    "iso:country":"CA",
    "sg:address":"23 James St",
    "sg:city":"Antigonish",
    "sg:classifiers":[
        {
            "category":"Real Estate",
            "subcategory":"Real Estate Operator",
            "type":"Services"
        }
    ],
    "sg:phone":"+1 902 863 8377",
    "sg:postcode":"B2G 1R6",
    "sg:province":"NS",
    "sg:tags":[
        "mall",
        "shopping",
        "center"
    ],
    "wof:name":"James Street Plaza",
    "wof:placetype":"venue"
},
  "geometry": {"coordinates":[-62.0012168884,45.6158180237],"type":"Point"}
}