{
  "type": "Feature",
  "properties": {
    "addr:full":"8625 Coronet Rd NW Edmonton AB T6E 4P2",
    "addr:housenumber":"8625",
    "addr:postcode":"t6e 4p2",
    "addr:street":"Coronet Rd Nw",
    "iso:country":"CA",
    "sg:address":"8625 Coronet Rd NW",
    "sg:city":"Edmonton",
    "sg:classifiers":[
        {
            "category":"Manufacturing",
            "subcategory":"Glass & Minerals",
            "type":"Manufacturing & Wholesale Goods"
        }
    ],
    "sg:phone":"+1 780 468 4100",
    "sg:postcode":"T6E 4P2",
    "sg:province":"AB",
    "sg:tags":[
        "refractory"
    ],
    "wof:name":"Clayburn Refractories Ltd",
    "wof:placetype":"venue"
},
  "geometry": {"coordinates":[-113.457901001,53.499294281],"type":"Point"}
}