{
  "type": "Feature",
  "properties": {
    "addr:full":"123 William St Shelburne ON L0N 1S0",
    "addr:housenumber":"123",
    "addr:postcode":"l0n 1s0",
    "addr:street":"William St",
    "iso:country":"CA",
    "sg:address":"123 William St",
    "sg:city":"Shelburne",
    "sg:classifiers":[
        {
            "category":"Retail",
            "subcategory":"Laundry & Dry Cleaning",
            "type":"Services"
        }
    ],
    "sg:phone":"+1 519 925 3827",
    "sg:postcode":"L0N 1S0",
    "sg:province":"ON",
    "sg:tags":[
        "cleaners"
    ],
    "wof:name":"Dufferin Cleaners & Launderers",
    "wof:placetype":"venue"
},
  "geometry": {"coordinates":[-80.20302599999999,44.078911],"type":"Point"}
}