{
  "type": "Feature",
  "properties": {
    "addr:full":"70 Collier St Barrie ON L4M 4Z2",
    "addr:housenumber":"70",
    "addr:postcode":"l4m 4z2",
    "addr:street":"Collier St",
    "iso:country":"CA",
    "sg:address":"70 Collier St",
    "sg:city":"Barrie",
    "sg:classifiers":[
        {
            "category":"Government",
            "subcategory":"Office",
            "type":"Public Place"
        }
    ],
    "sg:phone":"+1 705 726 4242",
    "sg:postcode":"L4M 4Z2",
    "sg:province":"ON",
    "sg:tags":[
        "village"
    ],
    "wof:name":"Barrie City Administrator",
    "wof:placetype":"venue"
},
  "geometry": {"coordinates":[-79.6862335205,44.3905601501],"type":"Point"}
}