{
  "type": "Feature",
  "properties": {
    "addr:full":"370 2E Av Weedon QC J0B 3J0",
    "addr:housenumber":"370",
    "addr:postcode":"j0b 3j0",
    "addr:street":"2E Av",
    "iso:country":"CA",
    "sg:address":"370 2E Av",
    "sg:city":"Weedon",
    "sg:classifiers":[
        {
            "category":"Restaurant",
            "type":"Food & Drink"
        }
    ],
    "sg:phone":"+1 819 877 2262",
    "sg:postcode":"J0B 3J0",
    "sg:province":"QC",
    "wof:name":"Restaurant Rendez-Vous Des",
    "wof:placetype":"venue"
},
  "geometry": {"coordinates":[-71.463509,45.70372],"type":"Point"}
}