{
  "type": "Feature",
  "properties": {
    "addr:full":"2596 Oil Heritage Rd Oil Springs ON N0N 1P0",
    "addr:housenumber":"2596",
    "addr:postcode":"n0n 1p0",
    "addr:street":"Oil Heritage Rd",
    "iso:country":"CA",
    "sg:address":"2596 Oil Heritage Rd",
    "sg:city":"Oil Springs",
    "sg:classifiers":[
        {
            "category":"Autos & Motor Vehicles",
            "subcategory":"Fuel & Gas Station",
            "type":"Retail Goods"
        }
    ],
    "sg:phone":"+1 519 834 2263",
    "sg:postcode":"N0N 1P0",
    "sg:province":"ON",
    "sg:tags":[
        "oil"
    ],
    "wof:name":"Oil Springs Svc Ctr",
    "wof:placetype":"venue"
},
  "geometry": {"coordinates":[-82.126823,42.783573],"type":"Point"}
}