{
  "type": "Feature",
  "properties": {
    "iso:country":"CA",
    "sg:address":"811 Rue Victoria",
    "sg:city":"Edmundston",
    "sg:classifiers":[
        {
            "category":"Building & Trades",
            "subcategory":"Plumbing",
            "type":"Services"
        }
    ],
    "sg:phone":"+1 506 739 2030",
    "sg:postcode":"E3V 3T3",
    "sg:province":"NB",
    "sg:tags":[
        "contractor"
    ],
    "wof:name":"Beaulieu Plumbing & Mechanical",
    "wof:placetype":"venue"
},
  "geometry": {"coordinates":[-68.3444900513,47.3947906494],"type":"Point"}
}