{
  "type": "Feature",
  "properties": {
    "iso:country":"CA",
    "sg:address":"2 Rue Laval",
    "sg:city":"Laval",
    "sg:classifiers":[
        {
            "category":"Wholesale",
            "subcategory":"Drugs",
            "type":"Manufacturing & Wholesale Goods"
        }
    ],
    "sg:phone":"+1 450 668 1144",
    "sg:postcode":"H7C 1C1",
    "sg:province":"QC",
    "sg:tags":[
        "pharmaceutical",
        "product"
    ],
    "wof:name":"Validpro Inc",
    "wof:placetype":"venue"
},
  "geometry": {"coordinates":[-73.647315979,45.61510849],"type":"Point"}
}