{
  "type": "Feature",
  "properties": {
    "addr:full":"60 George St Apohaqui NB E5P 3N7",
    "addr:housenumber":"60",
    "addr:postcode":"e5p 3n7",
    "addr:street":"George St",
    "iso:country":"CA",
    "sg:address":"60 George St",
    "sg:city":"Apohaqui",
    "sg:classifiers":[
        {
            "category":"Education",
            "subcategory":"Special Training",
            "type":"Public Place"
        }
    ],
    "sg:phone":"+1 506 432 4913",
    "sg:postcode":"E5P 3N7",
    "sg:province":"NB",
    "sg:tags":[
        "instruction",
        "driving"
    ],
    "wof:name":"Atlantic Transport Training",
    "wof:placetype":"venue"
},
  "geometry": {"coordinates":[-65.5944595337,45.7005195618],"type":"Point"}
}