{
  "type": "Feature",
  "properties": {
    "iso:country":"CA",
    "sg:city":"Cap-DE-LA-Madeleine",
    "sg:classifiers":[
        {
            "category":"Wholesale",
            "subcategory":"Groceries",
            "type":"Manufacturing & Wholesale Goods"
        }
    ],
    "sg:phone":"+1 819 375 7757",
    "sg:postcode":"G8T 9S6",
    "sg:province":"QC",
    "sg:tags":[
        "beverage"
    ],
    "wof:name":"Alex Coulombe Ltee",
    "wof:placetype":"venue"
},
  "geometry": {"coordinates":[-72.5628662109,46.3962554932],"type":"Point"}
}