{
  "type": "Feature",
  "properties": {
    "iso:country":"CA",
    "sg:address":"57 Rowan Dr RR 1",
    "sg:city":"Huntsville",
    "sg:classifiers":[
        {
            "category":"Travel",
            "subcategory":"Hotels & Motels",
            "type":"Entertainment"
        }
    ],
    "sg:phone":"+1 705 788 7125",
    "sg:postcode":"P1H 2J2",
    "sg:province":"ON",
    "sg:tags":[
        "breakfast",
        "accommodation",
        "bed"
    ],
    "wof:name":"Muskoka Moments B & B",
    "wof:placetype":"venue"
},
  "geometry": {"coordinates":[-79.2180023193,45.3265647888],"type":"Point"}
}