{
  "type": "Feature",
  "properties": {
    "iso:country":"CA",
    "sg:address":"100 Bloor St E",
    "sg:city":"Oshawa",
    "sg:classifiers":[
        {
            "category":"Autos & Motor Vehicles",
            "subcategory":"Automobile Sales",
            "type":"Retail Goods"
        }
    ],
    "sg:phone":"+1 905 728 2542",
    "sg:postcode":"L1H 3M2",
    "sg:province":"ON",
    "sg:tags":[
        "car",
        "dealer"
    ],
    "wof:name":"Cousin's Used Cars",
    "wof:placetype":"venue"
},
  "geometry": {"coordinates":[-78.852196,43.881363],"type":"Point"}
}