{
  "type": "Feature",
  "properties": {
    "addr:full":"Nanaimo BC V9R 5C8",
    "addr:postcode":"v9r 5c8",
    "iso:country":"CA",
    "sg:city":"Nanaimo",
    "sg:classifiers":[
        {
            "category":"Professional",
            "subcategory":"Management & Consulting",
            "type":"Services"
        }
    ],
    "sg:phone":"+1 250 753 2888",
    "sg:postcode":"V9R 5C8",
    "sg:province":"BC",
    "sg:tags":[
        "consultant",
        "safety"
    ],
    "wof:name":"Petersen Safety Group Inc",
    "wof:placetype":"venue"
},
  "geometry": {"coordinates":[-123.938271,49.165878],"type":"Point"}
}