{
  "type": "Feature",
  "properties": {
    "addr:full":"1101 Rue Pelletier Roberval QC G8H 1Y7",
    "addr:housenumber":"1101",
    "addr:postcode":"g8h 1y7",
    "addr:street":"Rue Pelletier",
    "iso:country":"CA",
    "sg:address":"1101 Rue Pelletier",
    "sg:city":"Roberval",
    "sg:classifiers":[
        {
            "category":"Autos & Motor Vehicles",
            "subcategory":"Motorcycle Sales",
            "type":"Retail Goods"
        }
    ],
    "sg:phone":"+1 418 275 0996",
    "sg:postcode":"G8H 1Y7",
    "sg:province":"QC",
    "sg:tags":[
        "snowmobile"
    ],
    "wof:name":"Dany Girard Inc",
    "wof:placetype":"venue"
},
  "geometry": {"coordinates":[-72.2287826538,48.5226593018],"type":"Point"}
}