{
  "type": "Feature",
  "properties": {
    "addr:full":"435 Rue Labbe Thetford Mines QC G6G 1Z5",
    "addr:housenumber":"435",
    "addr:postcode":"g6g 1z5",
    "addr:street":"Rue Labbe",
    "iso:country":"CA",
    "sg:address":"435 Rue Labbe",
    "sg:city":"Thetford Mines",
    "sg:classifiers":[
        {
            "category":"Restaurant",
            "type":"Food & Drink"
        }
    ],
    "sg:phone":"+1 418 338 2770",
    "sg:postcode":"G6G 1Z5",
    "sg:province":"QC",
    "wof:name":"Casse-Croute Roulotte N Dame",
    "wof:placetype":"venue"
},
  "geometry": {"coordinates":[-71.2965164185,46.09923172],"type":"Point"}
}