{
  "type": "Feature",
  "properties": {
    "addr:full":"133 Gorge Rd E Victoria BC V9A 1L1",
    "addr:housenumber":"133",
    "addr:postcode":"v9a 1l1",
    "addr:street":"Gorge Rd E",
    "iso:country":"CA",
    "sg:address":"133 Gorge Rd E",
    "sg:city":"Victoria",
    "sg:classifiers":[
        {
            "category":"Travel",
            "subcategory":"Hotels & Motels",
            "type":"Entertainment"
        }
    ],
    "sg:phone":"+1 250 388 6431",
    "sg:postcode":"V9A 1L1",
    "sg:province":"BC",
    "wof:name":"Oxford Castle Inn",
    "wof:placetype":"venue"
},
  "geometry": {"coordinates":[-123.38488006599999,48.44323349],"type":"Point"}
}