{
  "type": "Feature",
  "properties": {
    "addr:full":"1191 Victoria Dr Vancouver BC V5L 4G4",
    "addr:housenumber":"1191",
    "addr:postcode":"v5l 4g4",
    "addr:street":"Victoria Dr",
    "iso:country":"CA",
    "sg:address":"1191 Victoria Dr",
    "sg:city":"Vancouver",
    "sg:classifiers":[
        {
            "category":"Food & Beverages",
            "subcategory":"Groceries & Convenience Stores",
            "type":"Retail Goods"
        }
    ],
    "sg:phone":"+1 604 254 2000",
    "sg:postcode":"V5L 4G4",
    "sg:province":"BC",
    "sg:tags":[
        "grocer"
    ],
    "wof:name":"K & K Grocery",
    "wof:placetype":"venue"
},
  "geometry": {"coordinates":[-123.06586456300001,49.2740745544],"type":"Point"}
}