{
  "type": "Feature",
  "properties": {
    "addr:full":"601 Victoria Ave E Thunder Bay ON P7C 1B1",
    "addr:housenumber":"601",
    "addr:postcode":"p7c 1b1",
    "addr:street":"Victoria Ave E",
    "iso:country":"CA",
    "sg:address":"601 Victoria Ave E",
    "sg:city":"Thunder Bay",
    "sg:classifiers":[
        {
            "category":"Shopping",
            "subcategory":"Department Store",
            "type":"Retail Goods"
        }
    ],
    "sg:phone":"+1 807 622 1365",
    "sg:postcode":"P7C 1B1",
    "sg:province":"ON",
    "wof:name":"Sann Stores Ltd",
    "wof:placetype":"venue"
},
  "geometry": {"coordinates":[-89.2460784912,48.3842811584],"type":"Point"}
}