{
  "type": "Feature",
  "properties": {
    "addr:full":"1200 Gilmore Rd Fort Erie ON L2A 5M4",
    "addr:housenumber":"1200",
    "addr:postcode":"l2a 5m4",
    "addr:street":"Gilmore Rd",
    "iso:country":"CA",
    "sg:address":"1200 Gilmore Rd",
    "sg:city":"Fort Erie",
    "sg:classifiers":[
        {
            "category":"Retail",
            "subcategory":"Auto Repair",
            "type":"Services"
        }
    ],
    "sg:phone":"+1 905 871 8010",
    "sg:postcode":"L2A 5M4",
    "sg:province":"ON",
    "sg:tags":[
        "repairing",
        "automobile",
        "muffler",
        "system",
        "exhaust"
    ],
    "wof:name":"Express Muffler",
    "wof:placetype":"venue"
},
  "geometry": {"coordinates":[-78.959816,42.919521],"type":"Point"}
}