{
  "type": "Feature",
  "properties": {
    "addr:full":"135 Livingston Ave Grimsby ON L3M 5J6",
    "addr:housenumber":"135",
    "addr:postcode":"l3m 5j6",
    "addr:street":"Livingston Ave",
    "iso:country":"CA",
    "sg:address":"135 Livingston Ave",
    "sg:city":"Grimsby",
    "sg:classifiers":[
        {
            "category":"Organizations",
            "subcategory":"Religious Organization",
            "type":"Services"
        }
    ],
    "sg:phone":"+1 905 945 2661",
    "sg:postcode":"L3M 5J6",
    "sg:province":"ON",
    "sg:tags":[
        "church"
    ],
    "wof:name":"St Joseph's Church",
    "wof:placetype":"venue"
},
  "geometry": {"coordinates":[-79.579948,43.197952],"type":"Point"}
}