{
  "type": "Feature",
  "properties": {
    "iso:country":"CA",
    "sg:city":"Prince Albert",
    "sg:classifiers":[
        {
            "category":"Communications",
            "subcategory":"Television Station",
            "type":"Services"
        }
    ],
    "sg:phone":"+1 306 922 5622",
    "sg:postcode":"S6V 7E9",
    "sg:province":"SK",
    "sg:tags":[
        "broadcasting",
        "co"
    ],
    "wof:name":"Shaw Cable Channel Ten",
    "wof:placetype":"venue"
},
  "geometry": {"coordinates":[-105.75978088399999,53.1860542297],"type":"Point"}
}