{
  "type": "Feature",
  "properties": {
    "iso:country":"CA",
    "sg:address":"20227 56 Ave",
    "sg:city":"Langley",
    "sg:classifiers":[
        {
            "category":"Restaurant",
            "type":"Food & Drink"
        }
    ],
    "sg:phone":"+1 604 533 0111",
    "sg:postcode":"V3A 3Y6",
    "sg:province":"BC",
    "wof:name":"Andreas Restaurant",
    "wof:placetype":"venue"
},
  "geometry": {"coordinates":[-122.662277,49.104469],"type":"Point"}
}