{
  "type": "Feature",
  "properties": {
    "addr:full":"49 Commerce Cres Acton ON L7J 2X2",
    "addr:housenumber":"49",
    "addr:postcode":"l7j 2x2",
    "addr:street":"Commerce Cres",
    "iso:country":"CA",
    "sg:address":"49 Commerce Cres",
    "sg:city":"Acton",
    "sg:classifiers":[
        {
            "category":"Manufacturing",
            "subcategory":"Metals",
            "type":"Manufacturing & Wholesale Goods"
        }
    ],
    "sg:phone":"+1 519 853 3540",
    "sg:postcode":"L7J 2X2",
    "sg:province":"ON",
    "sg:tags":[
        "galvanizing"
    ],
    "wof:name":"Galvcast Manufacturing",
    "wof:placetype":"venue"
},
  "geometry": {"coordinates":[-80.0500717163,43.6418037415],"type":"Point"}
}