{
  "type": "Feature",
  "properties": {
    "addr:full":"Laval QC H7V 2T8",
    "addr:postcode":"h7v 2t8",
    "iso:country":"CA",
    "sg:city":"Laval",
    "sg:classifiers":[
        {
            "category":"Health Services",
            "subcategory":"Doctor",
            "type":"Services"
        }
    ],
    "sg:phone":"+1 450 682 9944",
    "sg:postcode":"H7V 2T8",
    "sg:province":"QC",
    "sg:tags":[
        "dentist"
    ],
    "wof:name":"Poirier, Suzanne DDS",
    "wof:placetype":"venue"
},
  "geometry": {"coordinates":[-73.743988,45.537464],"type":"Point"}
}