{
  "type": "Feature",
  "properties": {
    "addr:full":"2079 Boul Du Jardin Saint-Felicien QC G8K 2T3",
    "addr:housenumber":"2079",
    "addr:postcode":"g8k 2t3",
    "addr:street":"Boul Du Jardin Saint-Felicien",
    "iso:country":"CA",
    "sg:address":"2079 Boul Du Jardin",
    "sg:city":"Saint-Felicien",
    "sg:classifiers":[
        {
            "category":"Autos & Motor Vehicles",
            "subcategory":"Automobile Sales",
            "type":"Retail Goods"
        }
    ],
    "sg:phone":"+1 418 679 0464",
    "sg:postcode":"G8K 2T3",
    "sg:province":"QC",
    "sg:tags":[
        "car",
        "dealer"
    ],
    "wof:name":"Garage Verreault Florent",
    "wof:placetype":"venue"
},
  "geometry": {"coordinates":[-72.48674,48.683846],"type":"Point"}
}