{
  "type": "Feature",
  "properties": {
    "iso:country":"CA",
    "sg:address":"10811 97 Ave",
    "sg:city":"Grande Prairie",
    "sg:classifiers":[
        {
            "category":"Wholesale",
            "subcategory":"Auto Parts",
            "type":"Manufacturing & Wholesale Goods"
        }
    ],
    "sg:phone":"+1 780 539 5528",
    "sg:postcode":"T8V 4Y9",
    "sg:province":"AB",
    "sg:tags":[
        "equipment",
        "truck",
        "accessory"
    ],
    "wof:name":"Victor Distributing",
    "wof:placetype":"venue"
},
  "geometry": {"coordinates":[-118.823234558,55.1684112549],"type":"Point"}
}