{
  "type": "Feature",
  "properties": {
    "iso:country":"CA",
    "sg:city":"Regina",
    "sg:classifiers":[
        {
            "category":"Professional",
            "subcategory":"Lawyer & Legal Services",
            "type":"Services"
        }
    ],
    "sg:phone":"+1 306 525 2191",
    "sg:postcode":"S4P 2J6",
    "sg:province":"SK",
    "sg:tags":[
        "attorney"
    ],
    "wof:name":"Orr, Donald G",
    "wof:placetype":"venue"
},
  "geometry": {"coordinates":[-104.610984802,50.4437217712],"type":"Point"}
}