{
  "type": "Feature",
  "properties": {
    "addr:full":"1272 Rue Des Faisans Prevost QC J0R 1T0",
    "addr:housenumber":"1272",
    "addr:postcode":"j0r 1t0",
    "addr:street":"Rue Des Faisans",
    "iso:country":"CA",
    "sg:address":"1272 Rue Des Faisans",
    "sg:city":"Prevost",
    "sg:classifiers":[
        {
            "category":"Home & Garden",
            "subcategory":"Building Materials",
            "type":"Retail Goods"
        }
    ],
    "sg:phone":"+1 450 565 1888",
    "sg:postcode":"J0R 1T0",
    "sg:province":"QC",
    "sg:tags":[
        "glass",
        "window",
        "plate"
    ],
    "wof:name":"Pelti Vitres Teintees",
    "wof:placetype":"venue"
},
  "geometry": {"coordinates":[-74.04492999999999,45.831333],"type":"Point"}
}