{
  "type": "Feature",
  "properties": {
    "addr:full":"66 Rue Saint-Jacques Saint-Jean-Sur-Richelieu QC J3B 2J9",
    "addr:housenumber":"66",
    "addr:postcode":"j3b 2j9",
    "addr:street":"Rue Saint-Jacques",
    "iso:country":"CA",
    "sg:address":"66 Rue Saint-Jacques",
    "sg:city":"Saint-Jean-Sur-Richelieu",
    "sg:classifiers":[
        {
            "category":"Shopping",
            "subcategory":"News",
            "type":"Retail Goods"
        }
    ],
    "sg:phone":"+1 450 347 5987",
    "sg:postcode":"J3B 2J9",
    "sg:province":"QC",
    "sg:tags":[
        "dealer"
    ],
    "wof:name":"Coin DE LA Revue Enr",
    "wof:placetype":"venue"
},
  "geometry": {"coordinates":[-73.252785,45.30592],"type":"Point"}
}