{
  "type": "Feature",
  "properties": {
    "iso:country":"CA",
    "sg:address":"300 Main St",
    "sg:city":"Bengough",
    "sg:classifiers":[
        {
            "category":"Education",
            "subcategory":"Library",
            "type":"Public Place"
        }
    ],
    "sg:phone":"+1 306 268 2022",
    "sg:postcode":"S0C 0K0",
    "sg:province":"SK",
    "wof:name":"Bengough Regional Library",
    "wof:placetype":"venue"
},
  "geometry": {"coordinates":[-105.12273407000001,49.3972854614],"type":"Point"}
}