{
  "type": "Feature",
  "properties": {
    "iso:country":"CA",
    "sg:address":"PO Box 374",
    "sg:city":"Beaverlodge",
    "sg:classifiers":[
        {
            "category":"Building & Trades",
            "subcategory":"Construction",
            "type":"Services"
        }
    ],
    "sg:phone":"+1 780 354 2385",
    "sg:postcode":"T0H 0C0",
    "sg:province":"AB",
    "sg:tags":[
        "general",
        "contractor"
    ],
    "wof:name":"O'Connell Contracting",
    "wof:placetype":"venue"
},
  "geometry": {"coordinates":[-119.436325,55.214813],"type":"Point"}
}