{
  "type": "Feature",
  "properties": {
    "addr:full":"136 Rue Des Saules Chicoutimi QC G7G 4C3",
    "addr:housenumber":"136",
    "addr:postcode":"g7g 4c3",
    "addr:street":"Rue Des Saules",
    "iso:country":"CA",
    "sg:address":"136 Rue Des Saules",
    "sg:city":"Chicoutimi",
    "sg:classifiers":[
        {
            "category":"Education",
            "subcategory":"School",
            "type":"Public Place"
        }
    ],
    "sg:phone":"+1 418 543 3680",
    "sg:postcode":"G7G 4C3",
    "sg:province":"QC",
    "wof:name":"Ecole Ste-Claire",
    "wof:placetype":"venue"
},
  "geometry": {"coordinates":[-71.094872,48.447121],"type":"Point"}
}