{
  "type": "Feature",
  "properties": {
    "iso:country":"CA",
    "sg:address":"4114 Boul Saint-Martin O",
    "sg:city":"Laval",
    "sg:classifiers":[
        {
            "category":"Banks & Credit Unions",
            "subcategory":"Bank",
            "type":"Services"
        }
    ],
    "sg:phone":"+1 450 688 6940",
    "sg:postcode":"H7T 1C1",
    "sg:province":"QC",
    "wof:name":"Caisses Desjardins St-Martin",
    "wof:placetype":"venue"
},
  "geometry": {"coordinates":[-73.764061,45.54987],"type":"Point"}
}