{
  "type": "Feature",
  "properties": {
    "iso:country":"CA",
    "sg:address":"1605 5th Ave W",
    "sg:city":"Vancouver",
    "sg:classifiers":[
        {
            "category":"Professional",
            "subcategory":"Business Services",
            "type":"Services"
        }
    ],
    "sg:phone":"+1 604 734 2507",
    "sg:postcode":"V6J 1N5",
    "sg:province":"BC",
    "wof:name":"Lazy Gourmet Inc",
    "wof:placetype":"venue"
},
  "geometry": {"coordinates":[-123.14120483400001,49.2672080994],"type":"Point"}
}