{
  "type": "Feature",
  "properties": {
    "addr:full":"1551 Birmingham St Halifax NS B3J 2J6",
    "addr:housenumber":"1551",
    "addr:postcode":"ns b3j 2j6",
    "addr:street":"Birmingham St",
    "iso:country":"CA",
    "sg:address":"1551 Birmingham St",
    "sg:city":"Halifax",
    "sg:classifiers":[
        {
            "category":"Manufacturing",
            "subcategory":"Jewelry",
            "type":"Manufacturing & Wholesale Goods"
        }
    ],
    "sg:phone":"+1 902 425 0121",
    "sg:postcode":"B3J 2J6",
    "sg:province":"NS",
    "sg:tags":[
        "goldsmith",
        "product",
        "silversmith"
    ],
    "wof:name":"James Bradshaw Goldsmith",
    "wof:placetype":"venue"
},
  "geometry": {"coordinates":[-63.577003,44.643673],"type":"Point"}
}