{
  "type": "Feature",
  "properties": {
    "iso:country":"CA",
    "sg:address":"1902 Kennedy Rd",
    "sg:city":"Scarborough",
    "sg:classifiers":[
        {
            "category":"Retail",
            "subcategory":"Photofinishing",
            "type":"Services"
        }
    ],
    "sg:phone":"+1 416 291 2115",
    "sg:postcode":"M1P 2L8",
    "sg:province":"ON",
    "sg:tags":[
        "photo",
        "finishing"
    ],
    "wof:name":"Mercury Color Lab Inc",
    "wof:placetype":"venue"
},
  "geometry": {"coordinates":[-79.2814941406,43.7668151855],"type":"Point"}
}