{
  "type": "Feature",
  "properties": {
    "addr:full":"940 Cobalt Cres Thunder Bay ON P7B 5W3",
    "addr:housenumber":"940",
    "addr:postcode":"p7b 5w3",
    "addr:street":"Cobalt Cres",
    "iso:country":"CA",
    "sg:address":"940 Cobalt Cres",
    "sg:city":"Thunder Bay",
    "sg:classifiers":[
        {
            "category":"Autos & Motor Vehicles",
            "subcategory":"Recreational Vehicle Sales",
            "type":"Retail Goods"
        }
    ],
    "sg:phone":"+1 807 346 9399",
    "sg:postcode":"P7B 5W3",
    "sg:province":"ON",
    "wof:name":"Smith's Rv Ctr",
    "wof:placetype":"venue"
},
  "geometry": {"coordinates":[-89.25631,48.410835],"type":"Point"}
}