{
  "type": "Feature",
  "properties": {
    "addr:full":"1548 Fischer-Hallman Rd Kitchener ON N2R 1P7",
    "addr:housenumber":"1548",
    "addr:postcode":"n2r 1p7",
    "addr:street":"Fischer-Hallman Rd",
    "iso:country":"CA",
    "sg:address":"1548 Fischer-Hallman Rd",
    "sg:city":"Kitchener",
    "sg:classifiers":[
        {
            "category":"Recreation",
            "type":"Entertainment"
        }
    ],
    "sg:phone":"+1 519 579 6960",
    "sg:postcode":"N2R 1P7",
    "sg:province":"ON",
    "sg:tags":[
        "auditorium",
        "rooms",
        "banquet",
        "hall"
    ],
    "wof:name":"Kitchener Portuguese Club Inc",
    "wof:placetype":"venue"
},
  "geometry": {"coordinates":[-80.490906,43.389477],"type":"Point"}
}