{
  "type": "Feature",
  "properties": {
    "addr:full":"151 Mapleton Ave Barrie ON L4N 9N7",
    "addr:housenumber":"151",
    "addr:postcode":"l4n 9n7",
    "addr:street":"Mapleton Ave",
    "iso:country":"CA",
    "sg:address":"151 Mapleton Ave",
    "sg:city":"Barrie",
    "sg:classifiers":[
        {
            "category":"Education",
            "subcategory":"School",
            "type":"Public Place"
        }
    ],
    "sg:phone":"+1 705 733 2633",
    "sg:postcode":"L4N 9N7",
    "sg:province":"ON",
    "wof:name":"Holly Meadows",
    "wof:placetype":"venue"
},
  "geometry": {"coordinates":[-79.7140655518,44.3403625488],"type":"Point"}
}