{
  "type": "Feature",
  "properties": {
    "iso:country":"CA",
    "sg:address":"1900 Dundas St E # 1",
    "sg:city":"Mississauga",
    "sg:classifiers":[
        {
            "category":"Restaurant",
            "type":"Food & Drink"
        }
    ],
    "sg:phone":"+1 905 270 6265",
    "sg:postcode":"L4X 2Z4",
    "sg:province":"ON",
    "wof:name":"Fregata Restaurant",
    "wof:placetype":"venue"
},
  "geometry": {"coordinates":[-79.571526,43.620567],"type":"Point"}
}