{
  "type": "Feature",
  "properties": {
    "addr:full":"385 Admiral Blvd # 16 Mississauga ON L5T 2M8",
    "addr:housenumber":"385",
    "addr:postcode":"l5t 2m8",
    "addr:street":"Admiral Blvd # 16",
    "iso:country":"CA",
    "sg:address":"385 Admiral Blvd # 16",
    "sg:city":"Mississauga",
    "sg:classifiers":[
        {
            "category":"Manufacturing",
            "subcategory":"Tools & Machinery",
            "type":"Manufacturing & Wholesale Goods"
        }
    ],
    "sg:phone":"+1 905 565 7494",
    "sg:postcode":"L5T 2M8",
    "sg:province":"ON",
    "sg:tags":[
        "equipment",
        "system",
        "automation"
    ],
    "wof:name":"Sprite Automation Inc",
    "wof:placetype":"venue"
},
  "geometry": {"coordinates":[-79.69408416749999,43.6501579285],"type":"Point"}
}