{
  "type": "Feature",
  "properties": {
    "addr:full":"287 Bridgeland Ave North York ON M6A 1Z6",
    "addr:housenumber":"287",
    "addr:postcode":"m6a 1z6",
    "addr:street":"Bridgeland Ave",
    "iso:country":"CA",
    "sg:address":"287 Bridgeland Ave",
    "sg:city":"North York",
    "sg:classifiers":[
        {
            "category":"Building & Trades",
            "subcategory":"Construction",
            "type":"Services"
        }
    ],
    "sg:phone":"+1 416 789 5066",
    "sg:postcode":"M6A 1Z6",
    "sg:province":"ON",
    "sg:tags":[
        "woodworker"
    ],
    "wof:name":"Tomalex Woods",
    "wof:placetype":"venue"
},
  "geometry": {"coordinates":[-79.47024500000001,43.723877],"type":"Point"}
}