{
  "type": "Feature",
  "properties": {
    "addr:full":"Pembroke ON K8A 6Y7",
    "addr:postcode":"k8a 6y7",
    "iso:country":"CA",
    "sg:city":"Pembroke",
    "sg:classifiers":[
        {
            "category":"Recreation",
            "type":"Entertainment"
        }
    ],
    "sg:phone":"+1 613 735 3441",
    "sg:postcode":"K8A 6Y7",
    "sg:province":"ON",
    "sg:tags":[
        "lottery",
        "agent"
    ],
    "wof:name":"Peeping Tom's",
    "wof:placetype":"venue"
},
  "geometry": {"coordinates":[-77.0855255127,45.8240318298],"type":"Point"}
}