{
  "type": "Feature",
  "properties": {
    "addr:full":"Mississauga ON L4Z 3K3",
    "addr:postcode":"l4z 3k3",
    "iso:country":"CA",
    "sg:city":"Mississauga",
    "sg:classifiers":[
        {
            "category":"Professional",
            "subcategory":"Computer Services",
            "type":"Services"
        }
    ],
    "sg:phone":"+1 905 276 8944",
    "sg:postcode":"L4Z 3K3",
    "sg:province":"ON",
    "sg:tags":[
        "consultant"
    ],
    "wof:name":"Blake Systems Inc",
    "wof:placetype":"venue"
},
  "geometry": {"coordinates":[-79.6316604614,43.5974197388],"type":"Point"}
}