{
  "type": "Feature",
  "properties": {
    "addr:full":"11303 104 Ave NW Edmonton AB T5K 2S1",
    "addr:housenumber":"11303",
    "addr:postcode":"t5k 2s1",
    "addr:street":"104 Ave Nw",
    "iso:country":"CA",
    "sg:address":"11303 104 Ave NW",
    "sg:city":"Edmonton",
    "sg:classifiers":[
        {
            "category":"Shopping",
            "subcategory":"Optical Goods",
            "type":"Retail Goods"
        }
    ],
    "sg:phone":"+1 780 425 5367",
    "sg:postcode":"T5K 2S1",
    "sg:province":"AB",
    "sg:tags":[
        "optician"
    ],
    "wof:name":"Thompson Optics",
    "wof:placetype":"venue"
},
  "geometry": {"coordinates":[-113.51583100000001,53.546066],"type":"Point"}
}