{
  "type": "Feature",
  "properties": {
    "iso:country":"CA",
    "sg:address":"3958 Rue Dandurand",
    "sg:city":"Montreal",
    "sg:classifiers":[
        {
            "category":"Social Services",
            "subcategory":"Job Training",
            "type":"Services"
        }
    ],
    "sg:phone":"+1 514 723 2003",
    "sg:postcode":"H1X 1P7",
    "sg:province":"QC",
    "sg:tags":[
        "rehabilitation"
    ],
    "wof:name":"Centre DE Readaptation G Major",
    "wof:placetype":"venue"
},
  "geometry": {"coordinates":[-73.571945,45.558453],"type":"Point"}
}