{
  "type": "Feature",
  "properties": {
    "addr:full":"7 Industrial Park Lewisporte NL A0G 3A0",
    "addr:housenumber":"7",
    "addr:postcode":"a0g 3a0",
    "addr:street":"Industrial Park",
    "iso:country":"CA",
    "sg:address":"7 Industrial Park",
    "sg:city":"Lewisporte",
    "sg:classifiers":[
        {
            "category":"Retail",
            "subcategory":"Auto Rental",
            "type":"Services"
        }
    ],
    "sg:phone":"+1 709 535 0050",
    "sg:postcode":"A0G 3A0",
    "sg:province":"NL",
    "sg:tags":[
        "renting",
        "leasing",
        "truck",
        "trailer"
    ],
    "wof:name":"U-Haul CO Ltd",
    "wof:placetype":"venue"
},
  "geometry": {"coordinates":[-55.059937,49.241798],"type":"Point"}
}