{
  "type": "Feature",
  "properties": {
    "addr:full":"332 Richmond St W Toronto ON M5V 1X2",
    "addr:housenumber":"332",
    "addr:postcode":"m5v 1x2",
    "addr:street":"Richmond St W",
    "iso:country":"CA",
    "sg:address":"332 Richmond St W",
    "sg:city":"Toronto",
    "sg:classifiers":[
        {
            "category":"Wholesale",
            "subcategory":"Apparel",
            "type":"Manufacturing & Wholesale Goods"
        }
    ],
    "sg:phone":"+1 416 593 8860",
    "sg:postcode":"M5V 1X2",
    "sg:province":"ON",
    "sg:tags":[
        "fur",
        "business"
    ],
    "wof:name":"Green Brothers Fur Mfg Ltd",
    "wof:placetype":"venue"
},
  "geometry": {"coordinates":[-79.392685,43.648796],"type":"Point"}
}