{
  "type": "Feature",
  "properties": {
    "addr:full":"2057 Main St Cawston BC V0X 1C0",
    "addr:housenumber":"2057",
    "addr:postcode":"v0x 1c0",
    "addr:street":"Main St",
    "iso:country":"CA",
    "sg:address":"2057 Main St",
    "sg:city":"Cawston",
    "sg:classifiers":[
        {
            "category":"Retail",
            "subcategory":"Auto Repair",
            "type":"Services"
        }
    ],
    "sg:phone":"+1 250 499 5552",
    "sg:postcode":"V0X 1C0",
    "sg:province":"BC",
    "sg:tags":[
        "repairing",
        "automobile"
    ],
    "wof:name":"Car Doctor",
    "wof:placetype":"venue"
},
  "geometry": {"coordinates":[-119.76103999999999,49.180897],"type":"Point"}
}