{
  "type": "Feature",
  "properties": {
    "iso:country":"CA",
    "sg:address":"475 Bevel Line Rd",
    "sg:city":"Leamington",
    "sg:classifiers":[
        {
            "category":"Organizations",
            "subcategory":"Religious Organization",
            "type":"Services"
        }
    ],
    "sg:phone":"+1 519 326 0876",
    "sg:postcode":"N8H 3V4",
    "sg:province":"ON",
    "sg:tags":[
        "church"
    ],
    "wof:name":"Calvary Baptist Church",
    "wof:placetype":"venue"
},
  "geometry": {"coordinates":[-82.5795516968,42.0266456604],"type":"Point"}
}