{
  "type": "Feature",
  "properties": {
    "addr:full":"4150 Jane St North York ON M3N 2K2",
    "addr:housenumber":"4150",
    "addr:postcode":"m3n 2k2",
    "addr:street":"Jane St",
    "iso:country":"CA",
    "sg:address":"4150 Jane St",
    "sg:city":"North York",
    "sg:classifiers":[
        {
            "category":"Recreation",
            "type":"Entertainment"
        }
    ],
    "sg:phone":"+1 416 736 4804",
    "sg:postcode":"M3N 2K2",
    "sg:province":"ON",
    "sg:tags":[
        "course",
        "golf"
    ],
    "wof:name":"Funstation Mini Golf",
    "wof:placetype":"venue"
},
  "geometry": {"coordinates":[-79.518501,43.75983],"type":"Point"}
}