{
  "type": "Feature",
  "properties": {
    "addr:full":"5324 Hwy 1 Waterville NS B0P 1V0",
    "addr:housenumber":"5324",
    "addr:postcode":"b0p 1v0",
    "addr:street":"Hwy 1",
    "iso:country":"CA",
    "sg:address":"5324 Hwy 1",
    "sg:city":"Waterville",
    "sg:classifiers":[
        {
            "category":"Retail",
            "subcategory":"Repair Shop",
            "type":"Services"
        }
    ],
    "sg:phone":"+1 902 538 9578",
    "sg:postcode":"B0P 1V0",
    "sg:province":"NS",
    "sg:tags":[
        "refinishing",
        "furniture"
    ],
    "wof:name":"Plank & Hammer Workshop",
    "wof:placetype":"venue"
},
  "geometry": {"coordinates":[-64.66984558110001,45.0513000488],"type":"Point"}
}