{
  "type": "Feature",
  "properties": {
    "iso:country":"CA",
    "sg:city":"Belleville",
    "sg:classifiers":[
        {
            "category":"Social Services",
            "type":"Services"
        }
    ],
    "sg:phone":"+1 613 969 0830",
    "sg:postcode":"K8N 2Z2",
    "sg:province":"ON",
    "sg:tags":[
        "organization",
        "welfare"
    ],
    "wof:name":"Youth Habilitation",
    "wof:placetype":"venue"
},
  "geometry": {"coordinates":[-77.384415,44.163914],"type":"Point"}
}