{
  "type": "Feature",
  "properties": {
    "iso:country":"CA",
    "sg:address":"20 Gate Ave",
    "sg:city":"St Albert",
    "sg:classifiers":[
        {
            "category":"Freight",
            "type":"Transportation"
        }
    ],
    "sg:phone":"+1 780 458 7351",
    "sg:postcode":"T8N 4K1",
    "sg:province":"AB",
    "sg:tags":[
        "courier"
    ],
    "wof:name":"Greyhound Canada",
    "wof:placetype":"venue"
},
  "geometry": {"coordinates":[-113.615898132,53.6220932007],"type":"Point"}
}