{
  "type": "Feature",
  "properties": {
    "addr:full":"PO Box 343 Marystown NL A0E 2M0",
    "addr:housenumber":"po",
    "addr:postcode":"a0e 2m0",
    "addr:street":"Box 343",
    "iso:country":"CA",
    "sg:address":"PO Box 343",
    "sg:city":"Marystown",
    "sg:classifiers":[
        {
            "category":"Organizations",
            "subcategory":"Labor Organization",
            "type":"Services"
        }
    ],
    "sg:phone":"+1 709 279 2500",
    "sg:postcode":"A0E 2M0",
    "sg:province":"NL",
    "wof:name":"Industrial Union Marine",
    "wof:placetype":"venue"
},
  "geometry": {"coordinates":[-55.157001,47.16375],"type":"Point"}
}