{
  "type": "Feature",
  "properties": {
    "addr:full":"57 Mann Ave Toronto ON M4S 2Y2",
    "addr:housenumber":"57",
    "addr:postcode":"m4s 2y2",
    "addr:street":"Mann Ave",
    "iso:country":"CA",
    "sg:address":"57 Mann Ave",
    "sg:city":"Toronto",
    "sg:classifiers":[
        {
            "category":"Social Services",
            "subcategory":"Job Training",
            "type":"Services"
        }
    ],
    "sg:phone":"+1 416 921 9915",
    "sg:postcode":"M4S 2Y2",
    "sg:province":"ON",
    "sg:tags":[
        "career",
        "counseling",
        "vocational"
    ],
    "wof:name":"Bel Esprit",
    "wof:placetype":"venue"
},
  "geometry": {"coordinates":[-79.377769,43.709808],"type":"Point"}
}