{
  "type": "Feature",
  "properties": {
    "addr:full":"542 Rue St-Philippe Alfred ON K0B 1A0",
    "addr:housenumber":"542",
    "addr:postcode":"k0b 1a0",
    "addr:street":"Rue St-Philippe Alfred",
    "iso:country":"CA",
    "sg:address":"542 Rue St-Philippe",
    "sg:city":"Alfred",
    "sg:classifiers":[
        {
            "category":"Shopping",
            "subcategory":"Pharmacy",
            "type":"Retail Goods"
        }
    ],
    "sg:phone":"+1 613 679 1212",
    "sg:postcode":"K0B 1A0",
    "sg:province":"ON",
    "wof:name":"Essaim Pharmacie Membre",
    "wof:placetype":"venue"
},
  "geometry": {"coordinates":[-74.88790893549999,45.556602478],"type":"Point"}
}