{
  "type": "Feature",
  "properties": {
    "addr:full":"120 Green Point Rd Penetanguishene ON L9M 2H7",
    "addr:housenumber":"120",
    "addr:postcode":"l9m 2h7",
    "addr:street":"Green Point Rd",
    "iso:country":"CA",
    "sg:address":"120 Green Point Rd",
    "sg:city":"Penetanguishene",
    "sg:classifiers":[
        {
            "category":"Food & Beverages",
            "subcategory":"Groceries & Convenience Stores",
            "type":"Retail Goods"
        }
    ],
    "sg:phone":"+1 705 533 4714",
    "sg:postcode":"L9M 2H7",
    "sg:province":"ON",
    "sg:tags":[
        "variety"
    ],
    "wof:name":"Friendly Corner Store",
    "wof:placetype":"venue"
},
  "geometry": {"coordinates":[-79.9353561401,44.768119812],"type":"Point"}
}