{
  "type": "Feature",
  "properties": {
    "addr:full":"3225 Lawrence Ave E Scarborough ON M1H 3C2",
    "addr:housenumber":"3225",
    "addr:postcode":"m1h 3c2",
    "addr:street":"Lawrence Ave E",
    "iso:country":"CA",
    "sg:address":"3225 Lawrence Ave E",
    "sg:city":"Scarborough",
    "sg:classifiers":[
        {
            "category":"Shopping",
            "subcategory":"Pharmacy",
            "type":"Retail Goods"
        }
    ],
    "sg:phone":"+1 416 439 3417",
    "sg:postcode":"M1H 3C2",
    "sg:province":"ON",
    "wof:name":"Burnview Drugs",
    "wof:placetype":"venue"
},
  "geometry": {"coordinates":[-79.240387,43.756466],"type":"Point"}
}