{
  "type": "Feature",
  "properties": {
    "addr:full":"609 12th St Fort Macleod AB T0L 0Z0",
    "addr:housenumber":"609",
    "addr:postcode":"t0l 0z0",
    "addr:street":"12Th St",
    "iso:country":"CA",
    "sg:address":"609 12th St",
    "sg:city":"Fort Macleod",
    "sg:classifiers":[
        {
            "category":"Retail",
            "subcategory":"Veterinary Services",
            "type":"Services"
        }
    ],
    "sg:phone":"+1 403 553 4887",
    "sg:postcode":"T0L 0Z0",
    "sg:province":"AB",
    "sg:tags":[
        "veterinarian"
    ],
    "wof:name":"Fort Macleod Veterinary Clinic",
    "wof:placetype":"venue"
},
  "geometry": {"coordinates":[-113.396805,49.716488],"type":"Point"}
}