{
  "type": "Feature",
  "properties": {
    "addr:full":"116 Rue East Gatineau QC J8P 4Z9",
    "addr:housenumber":"116",
    "addr:postcode":"j8p 4z9",
    "addr:street":"Rue East",
    "iso:country":"CA",
    "sg:address":"116 Rue East",
    "sg:city":"Gatineau",
    "sg:classifiers":[
        {
            "category":"Organizations",
            "subcategory":"Religious Organization",
            "type":"Services"
        }
    ],
    "sg:phone":"+1 819 478 2309",
    "sg:postcode":"J8P 4Z9",
    "sg:province":"QC",
    "sg:tags":[
        "church"
    ],
    "wof:name":"Le Centre Evangelique DE",
    "wof:placetype":"venue"
},
  "geometry": {"coordinates":[-75.6464996338,45.4808998108],"type":"Point"}
}