{
  "type": "Feature",
  "properties": {
    "addr:full":"1209 Mckeen Ave North Vancouver BC V7P 3H9",
    "addr:housenumber":"1209",
    "addr:postcode":"v7p 3h9",
    "addr:street":"Mckeen Ave",
    "iso:country":"CA",
    "sg:address":"1209 Mckeen Ave",
    "sg:city":"North Vancouver",
    "sg:classifiers":[
        {
            "category":"Retail",
            "subcategory":"Auto Rental",
            "type":"Services"
        }
    ],
    "sg:phone":"+1 604 980 6543",
    "sg:postcode":"V7P 3H9",
    "sg:province":"BC",
    "sg:tags":[
        "renting",
        "truck",
        "exporter",
        "leasing"
    ],
    "wof:name":"Fibreco Export Inc",
    "wof:placetype":"venue"
},
  "geometry": {"coordinates":[-123.108505249,49.3158950806],"type":"Point"}
}