{
  "type": "Feature",
  "properties": {
    "addr:full":"220 Grande Allee E # 105 Quebec QC G1R 2J1",
    "addr:housenumber":"220",
    "addr:postcode":"g1r 2j1",
    "addr:street":"Grande Allee E # 105",
    "iso:country":"CA",
    "sg:address":"220 Grande Allee E # 105",
    "sg:city":"Quebec",
    "sg:classifiers":[
        {
            "category":"Insurance",
            "subcategory":"Insurance Agent",
            "type":"Services"
        }
    ],
    "sg:phone":"+1 418 525 9554",
    "sg:postcode":"G1R 2J1",
    "sg:province":"QC",
    "wof:name":"Gourdeau, Claude S",
    "wof:placetype":"venue"
},
  "geometry": {"coordinates":[-71.2212219238,46.8037986755],"type":"Point"}
}