{
  "type": "Feature",
  "properties": {
    "iso:country":"CA",
    "sg:address":"3476 93 St NW # 204",
    "sg:city":"Edmonton",
    "sg:classifiers":[
        {
            "category":"Professional",
            "subcategory":"Accounting & Tax Preparation",
            "type":"Services"
        }
    ],
    "sg:phone":"+1 780 462 4343",
    "sg:postcode":"T6E 6A4",
    "sg:province":"AB",
    "sg:tags":[
        "accountant"
    ],
    "wof:name":"V J Accounting & Tax Svc",
    "wof:placetype":"venue"
},
  "geometry": {"coordinates":[-113.473594666,53.4679908752],"type":"Point"}
}