{
  "type": "Feature",
  "properties": {
    "addr:full":"Campbell River BC V9W 1P2",
    "addr:postcode":"v9w 1p2",
    "iso:country":"CA",
    "sg:city":"Campbell River",
    "sg:classifiers":[
        {
            "category":"Arts & Performance",
            "subcategory":"Theater",
            "type":"Entertainment"
        }
    ],
    "sg:phone":"+1 250 923 0411",
    "sg:postcode":"V9W 1P2",
    "sg:province":"BC",
    "sg:tags":[
        "live",
        "music"
    ],
    "wof:name":"Capital Sea Music",
    "wof:placetype":"venue"
},
  "geometry": {"coordinates":[-125.248168945,50.0246086121],"type":"Point"}
}