{
  "type": "Feature",
  "properties": {
    "addr:full":"7296 Wilson Ave Delta BC V4G 1H3",
    "addr:housenumber":"7296",
    "addr:postcode":"v4g 1h3",
    "addr:street":"Wilson Ave",
    "iso:country":"CA",
    "sg:address":"7296 Wilson Ave",
    "sg:city":"Delta",
    "sg:classifiers":[
        {
            "category":"Manufacturing",
            "subcategory":"Tools & Machinery",
            "type":"Manufacturing & Wholesale Goods"
        }
    ],
    "sg:phone":"+1 604 952 6666",
    "sg:postcode":"V4G 1H3",
    "sg:province":"BC",
    "sg:tags":[
        "equipment",
        "hydraulic"
    ],
    "wof:name":"Janox Fluid Power Ltd",
    "wof:placetype":"venue"
},
  "geometry": {"coordinates":[-123.02001199999999,49.129444],"type":"Point"}
}