{
  "type": "Feature",
  "properties": {
    "addr:full":"6071 Valley Way Niagara Falls ON L2E 1X9",
    "addr:housenumber":"6071",
    "addr:postcode":"l2e 1x9",
    "addr:street":"Valley Way",
    "iso:country":"CA",
    "sg:address":"6071 Valley Way",
    "sg:city":"Niagara Falls",
    "sg:classifiers":[
        {
            "category":"Social Services",
            "subcategory":"Child Care",
            "type":"Services"
        }
    ],
    "sg:phone":"+1 905 374 3057",
    "sg:postcode":"L2E 1X9",
    "sg:province":"ON",
    "wof:name":"Valley Way Day Care Inc",
    "wof:placetype":"venue"
},
  "geometry": {"coordinates":[-79.096092,43.097904],"type":"Point"}
}