{
  "type": "Feature",
  "properties": {
    "addr:full":"8630 105 St NW Edmonton AB T6E 4H7",
    "addr:housenumber":"8630",
    "addr:postcode":"t6e 4h7",
    "addr:street":"105 St Nw",
    "iso:country":"CA",
    "sg:address":"8630 105 St NW",
    "sg:city":"Edmonton",
    "sg:classifiers":[
        {
            "category":"Parking",
            "type":"Transportation"
        }
    ],
    "sg:phone":"+1 780 433 7593",
    "sg:postcode":"T6E 4H7",
    "sg:province":"AB",
    "sg:tags":[
        "garage"
    ],
    "wof:name":"Superior Parking Ltd",
    "wof:placetype":"venue"
},
  "geometry": {"coordinates":[-113.50057200000001,53.522076],"type":"Point"}
}