{
  "type": "Feature",
  "properties": {
    "addr:full":"Geraldton ON P0T 1M0",
    "addr:postcode":"p0t 1m0",
    "iso:country":"CA",
    "sg:city":"Geraldton",
    "sg:classifiers":[
        {
            "category":"Government",
            "subcategory":"Office",
            "type":"Public Place"
        }
    ],
    "sg:phone":"+1 807 854 1317",
    "sg:postcode":"P0T 1M0",
    "sg:province":"ON",
    "wof:name":"Canada Forestry Svc",
    "wof:placetype":"venue"
},
  "geometry": {"coordinates":[-86.9500198364,49.719581604],"type":"Point"}
}