{
  "type": "Feature",
  "properties": {
    "addr:full":"19 Rue Du Carrefour-Sportif Amqui QC G5J 3E3",
    "addr:housenumber":"19",
    "addr:postcode":"g5j 3e3",
    "addr:street":"Rue Du Carrefour-Sportif",
    "iso:country":"CA",
    "sg:address":"19 Rue Du Carrefour-Sportif",
    "sg:city":"Amqui",
    "sg:classifiers":[
        {
            "category":"Food & Beverages",
            "subcategory":"Groceries & Convenience Stores",
            "type":"Retail Goods"
        }
    ],
    "sg:phone":"+1 418 629 4535",
    "sg:postcode":"G5J 3E3",
    "sg:province":"QC",
    "sg:tags":[
        "grocer"
    ],
    "wof:name":"Epicerie Mario Roy Inc",
    "wof:placetype":"venue"
},
  "geometry": {"coordinates":[-67.436249,48.463871],"type":"Point"}
}