{
  "type": "Feature",
  "properties": {
    "addr:full":"Kamloops BC V2C 6G1",
    "addr:postcode":"bc v2c 6g1",
    "iso:country":"CA",
    "sg:city":"Kamloops",
    "sg:classifiers":[
        {
            "category":"Wholesale",
            "subcategory":"Electrical",
            "type":"Manufacturing & Wholesale Goods"
        }
    ],
    "sg:phone":"+1 250 374 3191",
    "sg:postcode":"V2C 6G1",
    "sg:province":"BC",
    "sg:tags":[
        "equipment",
        "electric",
        "supply"
    ],
    "wof:name":"E B Horsman & Son Ltd",
    "wof:placetype":"venue"
},
  "geometry": {"coordinates":[-120.368171692,50.6667022705],"type":"Point"}
}