{
  "type": "Feature",
  "properties": {
    "addr:full":"2944 Eglinton Ave E Scarborough ON M1J 2E7",
    "addr:housenumber":"2944",
    "addr:postcode":"m1j 2e7",
    "addr:street":"Eglinton Ave E",
    "iso:country":"CA",
    "sg:address":"2944 Eglinton Ave E",
    "sg:city":"Scarborough",
    "sg:classifiers":[
        {
            "category":"Retail",
            "subcategory":"Auto Rental",
            "type":"Services"
        }
    ],
    "sg:phone":"+1 416 438 5400",
    "sg:postcode":"M1J 2E7",
    "sg:province":"ON",
    "sg:tags":[
        "renting",
        "automobile",
        "leasing",
        "truck"
    ],
    "wof:name":"Budget Car & Truck Rental",
    "wof:placetype":"venue"
},
  "geometry": {"coordinates":[-79.23484000000001,43.739803],"type":"Point"}
}