{
  "type": "Feature",
  "properties": {
    "addr:full":"Winnipeg MB R2G 1N3",
    "addr:postcode":"r2g 1n3",
    "iso:country":"CA",
    "sg:city":"Winnipeg",
    "sg:classifiers":[
        {
            "category":"Shopping",
            "subcategory":"Catalog Store",
            "type":"Retail Goods"
        }
    ],
    "sg:phone":"+1 204 338 1399",
    "sg:postcode":"R2G 1N3",
    "sg:province":"MB",
    "sg:tags":[
        "mail",
        "order",
        "internet"
    ],
    "wof:name":"Sears Canada Inc",
    "wof:placetype":"venue"
},
  "geometry": {"coordinates":[-97.0864486694,49.9447593689],"type":"Point"}
}