{
  "type": "Feature",
  "properties": {
    "iso:country":"CA",
    "sg:address":"381 22E Ave",
    "sg:city":"LA Guadeloupe",
    "sg:classifiers":[
        {
            "category":"Manufacturing",
            "subcategory":"Apparel",
            "type":"Manufacturing & Wholesale Goods"
        }
    ],
    "sg:phone":"+1 418 459 3337",
    "sg:postcode":"G0M 1G0",
    "sg:province":"QC",
    "sg:tags":[
        "jean"
    ],
    "wof:name":"Delavage DE Beauce Inc",
    "wof:placetype":"venue"
},
  "geometry": {"coordinates":[-70.922668457,45.9580116272],"type":"Point"}
}