{
  "type": "Feature",
  "properties": {
    "addr:full":"223 St Clair Ave W #300 Toronto ON M4V 1R3",
    "addr:housenumber":"223",
    "addr:postcode":"m4v 1r3",
    "addr:street":"St Clair Ave W # 300",
    "iso:country":"CA",
    "sg:address":"223 St Clair Ave W #300",
    "sg:city":"Toronto",
    "sg:classifiers":[
        {
            "category":"Health Services",
            "subcategory":"Doctor",
            "type":"Services"
        }
    ],
    "sg:phone":"+1 416 961 9767",
    "sg:postcode":"M4V 1R3",
    "sg:province":"ON",
    "sg:tags":[
        "psychoanalyst"
    ],
    "wof:name":"C G Jung Foundation",
    "wof:placetype":"venue"
},
  "geometry": {"coordinates":[-79.404419,43.685925],"type":"Point"}
}