{
  "type": "Feature",
  "properties": {
    "iso:country":"CA",
    "sg:address":"312 Greenwood Ave",
    "sg:city":"North Bay",
    "sg:classifiers":[
        {
            "category":"Organizations",
            "subcategory":"Religious Organization",
            "type":"Services"
        }
    ],
    "sg:phone":"+1 705 474 0448",
    "sg:postcode":"P1B 5G4",
    "sg:province":"ON",
    "sg:tags":[
        "church"
    ],
    "wof:name":"Greenwood Avenue Baptist Chr",
    "wof:placetype":"venue"
},
  "geometry": {"coordinates":[-79.471352,46.326508],"type":"Point"}
}