{
  "type": "Feature",
  "properties": {
    "addr:full":"178 Jane St Eganville ON K0J 1T0",
    "addr:housenumber":"178",
    "addr:postcode":"k0j 1t0",
    "addr:street":"Jane St",
    "iso:country":"CA",
    "sg:address":"178 Jane St",
    "sg:city":"Eganville",
    "sg:classifiers":[
        {
            "category":"Arena",
            "subcategory":"Sports Club",
            "type":"Entertainment"
        }
    ],
    "sg:phone":"+1 613 628 2613",
    "sg:postcode":"K0J 1T0",
    "sg:province":"ON",
    "sg:tags":[
        "athletic",
        "fields",
        "stadium",
        "government"
    ],
    "wof:name":"Eganville Community Arena",
    "wof:placetype":"venue"
},
  "geometry": {"coordinates":[-77.105278,45.541939],"type":"Point"}
}