{
  "type": "Feature",
  "properties": {
    "addr:full":"673 College St Toronto ON M6G 1B9",
    "addr:housenumber":"673",
    "addr:postcode":"m6g 1b9",
    "addr:street":"College St",
    "iso:country":"CA",
    "sg:address":"673 College St",
    "sg:city":"Toronto",
    "sg:classifiers":[
        {
            "category":"Shopping",
            "subcategory":"Pharmacy",
            "type":"Retail Goods"
        }
    ],
    "sg:phone":"+1 416 516 4978",
    "sg:postcode":"M6G 1B9",
    "sg:province":"ON",
    "wof:name":"Nhatrang Pharmacy Ltd",
    "wof:placetype":"venue"
},
  "geometry": {"coordinates":[-79.417213,43.655098],"type":"Point"}
}