{
  "type": "Feature",
  "properties": {
    "iso:country":"CA",
    "sg:city":"Ajax",
    "sg:classifiers":[
        {
            "category":"Retail",
            "subcategory":"Auto Repair",
            "type":"Services"
        }
    ],
    "sg:phone":"+1 905 426 1593",
    "sg:postcode":"L1S 7G8",
    "sg:province":"ON",
    "sg:tags":[
        "body",
        "automobile",
        "painting"
    ],
    "wof:name":"Murray's Auto Body Inc",
    "wof:placetype":"venue"
},
  "geometry": {"coordinates":[-79.0325012207,43.8352394104],"type":"Point"}
}