{
  "type": "Feature",
  "properties": {
    "iso:country":"CA",
    "sg:address":"8065 Boul Levesque E",
    "sg:city":"Laval",
    "sg:classifiers":[
        {
            "category":"Social Services",
            "subcategory":"Child Care",
            "type":"Services"
        }
    ],
    "sg:phone":"+1 450 665 3831",
    "sg:postcode":"H7A 3W5",
    "sg:province":"QC",
    "wof:name":"Petits Soleils",
    "wof:placetype":"venue"
},
  "geometry": {"coordinates":[-73.5842056274,45.6634979248],"type":"Point"}
}