{
  "type": "Feature",
  "properties": {
    "iso:country":"CA",
    "sg:city":"Mississauga",
    "sg:classifiers":[
        {
            "category":"Professional",
            "subcategory":"Computer Services",
            "type":"Services"
        }
    ],
    "sg:phone":"+1 905 812 3009",
    "sg:postcode":"L5N 6J7",
    "sg:province":"ON",
    "sg:tags":[
        "consultant"
    ],
    "wof:name":"Envision It",
    "wof:placetype":"venue"
},
  "geometry": {"coordinates":[-79.755997,43.608707],"type":"Point"}
}