{
  "type": "Feature",
  "properties": {
    "addr:full":"1793 Boul Marie Saint-Hubert QC J4T 2A8",
    "addr:housenumber":"1793",
    "addr:postcode":"j4t 2a8",
    "addr:street":"Boul Marie",
    "iso:country":"CA",
    "sg:address":"1793 Boul Marie",
    "sg:city":"Saint-Hubert",
    "sg:classifiers":[
        {
            "category":"Freight",
            "type":"Transportation"
        }
    ],
    "sg:phone":"+1 450 671 7144",
    "sg:postcode":"J4T 2A8",
    "sg:province":"QC",
    "sg:tags":[
        "trucking"
    ],
    "wof:name":"Transport Mpj",
    "wof:placetype":"venue"
},
  "geometry": {"coordinates":[-73.478172,45.501122],"type":"Point"}
}