{
  "type": "Feature",
  "properties": {
    "addr:full":"1008 Dovercourt Rd Toronto ON M6H 2X8",
    "addr:housenumber":"1008",
    "addr:postcode":"m6h 2x8",
    "addr:street":"Dovercourt Rd",
    "iso:country":"CA",
    "sg:address":"1008 Dovercourt Rd",
    "sg:city":"Toronto",
    "sg:classifiers":[
        {
            "category":"Organizations",
            "subcategory":"Religious Organization",
            "type":"Services"
        }
    ],
    "sg:phone":"+1 416 536 4449",
    "sg:postcode":"M6H 2X8",
    "sg:province":"ON",
    "sg:tags":[
        "church"
    ],
    "wof:name":"Belarusian Greek Orthodox",
    "wof:placetype":"venue"
},
  "geometry": {"coordinates":[-79.432098,43.667656],"type":"Point"}
}