{
  "type": "Feature",
  "properties": {
    "addr:full":"2063 Yonge St Toronto ON M4S 2A2",
    "addr:housenumber":"2063",
    "addr:postcode":"m4s 2a2",
    "addr:street":"Yonge St",
    "iso:country":"CA",
    "sg:address":"2063 Yonge St",
    "sg:city":"Toronto",
    "sg:classifiers":[
        {
            "category":"Shopping",
            "subcategory":"Bicycles & Sporting Goods",
            "type":"Retail Goods"
        }
    ],
    "sg:phone":"+1 416 481 0249",
    "sg:postcode":"M4S 2A2",
    "sg:province":"ON",
    "wof:name":"Sport Swap",
    "wof:placetype":"venue"
},
  "geometry": {"coordinates":[-79.397232,43.702232],"type":"Point"}
}