{
  "type": "Feature",
  "properties": {
    "addr:full":"Peace & Elliot Cannington ON L0E 1E0",
    "addr:postcode":"l0e 1e0",
    "iso:country":"CA",
    "sg:address":"Peace & Elliot",
    "sg:city":"Cannington",
    "sg:classifiers":[
        {
            "category":"Recreation",
            "type":"Entertainment"
        }
    ],
    "sg:phone":"+1 705 432 2582",
    "sg:postcode":"L0E 1E0",
    "sg:province":"ON",
    "sg:tags":[
        "government",
        "hall",
        "auditorium"
    ],
    "wof:name":"Cannington Community Ctr",
    "wof:placetype":"venue"
},
  "geometry": {"coordinates":[-79.03475952150001,44.3483085632],"type":"Point"}
}