{
  "type": "Feature",
  "properties": {
    "addr:full":"340 College St # 501 Toronto ON M5T 3A9",
    "addr:housenumber":"340",
    "addr:postcode":"m5t 3a9",
    "addr:street":"College St # 501",
    "iso:country":"CA",
    "sg:address":"340 College St # 501",
    "sg:city":"Toronto",
    "sg:classifiers":[
        {
            "category":"Professional",
            "subcategory":"Lawyer & Legal Services",
            "type":"Services"
        }
    ],
    "sg:phone":"+1 416 591 8485",
    "sg:postcode":"M5T 3A9",
    "sg:province":"ON",
    "sg:tags":[
        "attorney"
    ],
    "wof:name":"Hacker, Harvey",
    "wof:placetype":"venue"
},
  "geometry": {"coordinates":[-79.40334300000001,43.657448],"type":"Point"}
}