{
  "type": "Feature",
  "properties": {
    "iso:country":"CA",
    "sg:city":"Ottawa",
    "sg:classifiers":[
        {
            "category":"Professional",
            "subcategory":"Business Services",
            "type":"Services"
        }
    ],
    "sg:phone":"+1 613 749 7800",
    "sg:postcode":"K1B 4E4",
    "sg:province":"ON",
    "sg:tags":[
        "carpet",
        "dealer",
        "rug"
    ],
    "wof:name":"Gavin Ritchie Carpet Repair",
    "wof:placetype":"venue"
},
  "geometry": {"coordinates":[-75.6091003418,45.4044075012],"type":"Point"}
}