{
  "type": "Feature",
  "properties": {
    "iso:country":"CA",
    "sg:city":"Nanaimo",
    "sg:classifiers":[
        {
            "category":"Insurance",
            "subcategory":"Insurance Agent",
            "type":"Services"
        }
    ],
    "sg:phone":"+1 250 755 1411",
    "sg:postcode":"V9R 1P1",
    "sg:province":"BC",
    "wof:name":"Bakes-Jarvie Insurance Brokers",
    "wof:placetype":"venue"
},
  "geometry": {"coordinates":[-123.95124054,49.1552734375],"type":"Point"}
}