{
  "type": "Feature",
  "properties": {
    "addr:full":"79 Millersgrove Dr North York ON M2R 3S1",
    "addr:housenumber":"79",
    "addr:postcode":"m2r 3s1",
    "addr:street":"Millersgrove Dr",
    "iso:country":"CA",
    "sg:address":"79 Millersgrove Dr",
    "sg:city":"North York",
    "sg:classifiers":[
        {
            "category":"Social Services",
            "subcategory":"Job Training",
            "type":"Services"
        }
    ],
    "sg:phone":"+1 416 736 8519",
    "sg:postcode":"M2R 3S1",
    "sg:province":"ON",
    "sg:tags":[
        "rehabilitation"
    ],
    "wof:name":"Rehabilitation Professionals",
    "wof:placetype":"venue"
},
  "geometry": {"coordinates":[-79.458748,43.786598],"type":"Point"}
}