{
  "type": "Feature",
  "properties": {
    "iso:country":"CA",
    "sg:address":"8 James St",
    "sg:city":"Georgetown",
    "sg:classifiers":[
        {
            "category":"Professional",
            "subcategory":"Advertising",
            "type":"Services"
        }
    ],
    "sg:phone":"+1 905 873 9200",
    "sg:postcode":"L7G 2H3",
    "sg:province":"ON",
    "sg:tags":[
        "counselor"
    ],
    "wof:name":"Lawlor & CO",
    "wof:placetype":"venue"
},
  "geometry": {"coordinates":[-79.9280700684,43.6500892639],"type":"Point"}
}