{
  "type": "Feature",
  "properties": {
    "iso:country":"CA",
    "sg:city":"Val Caron",
    "sg:classifiers":[
        {
            "category":"Shopping",
            "subcategory":"Computers & Home Electronics",
            "type":"Retail Goods"
        }
    ],
    "sg:phone":"+1 705 897 7228",
    "sg:postcode":"P3N 1R8",
    "sg:province":"ON",
    "sg:tags":[
        "equipment",
        "dealer"
    ],
    "wof:name":"Answers Consulting Inc",
    "wof:placetype":"venue"
},
  "geometry": {"coordinates":[-81.008644104,46.6104316711],"type":"Point"}
}