{
  "type": "Feature",
  "properties": {
    "iso:country":"CA",
    "sg:address":"10 Speedvale Ave E #D",
    "sg:city":"Guelph",
    "sg:classifiers":[
        {
            "category":"Autos & Motor Vehicles",
            "subcategory":"Auto Supplies",
            "type":"Retail Goods"
        }
    ],
    "sg:phone":"+1 519 837 9330",
    "sg:postcode":"N1H 1J3",
    "sg:province":"ON",
    "sg:tags":[
        "automobile",
        "stereo",
        "radio"
    ],
    "wof:name":"Autosonics",
    "wof:placetype":"venue"
},
  "geometry": {"coordinates":[-80.2676849365,43.5590171814],"type":"Point"}
}