{
  "type": "Feature",
  "properties": {
    "addr:full":"6 Grand St Happy Valley-Goose Bay NL A0P 1E0",
    "addr:housenumber":"6",
    "addr:postcode":"a0p 1e0",
    "addr:street":"Grand St",
    "iso:country":"CA",
    "sg:address":"6 Grand St",
    "sg:city":"Happy Valley-Goose Bay",
    "sg:classifiers":[
        {
            "category":"Bars & Pubs",
            "type":"Food & Drink"
        }
    ],
    "sg:phone":"+1 709 896 7330",
    "sg:postcode":"A0P 1E0",
    "sg:province":"NL",
    "sg:tags":[
        "lounge",
        "cocktail"
    ],
    "wof:name":"Hillbilly Ranch Bar & Grill",
    "wof:placetype":"venue"
},
  "geometry": {"coordinates":[-60.302006,53.301136],"type":"Point"}
}