{
  "type": "Feature",
  "properties": {
    "addr:full":"5003 50th Ave Provost AB T0B 3S0",
    "addr:housenumber":"5003",
    "addr:postcode":"t0b 3s0",
    "addr:street":"50Th Ave",
    "iso:country":"CA",
    "sg:address":"5003 50th Ave",
    "sg:city":"Provost",
    "sg:classifiers":[
        {
            "category":"Food & Beverages",
            "subcategory":"Groceries & Convenience Stores",
            "type":"Retail Goods"
        }
    ],
    "sg:phone":"+1 780 753 2097",
    "sg:postcode":"T0B 3S0",
    "sg:province":"AB",
    "sg:tags":[
        "grocer"
    ],
    "wof:name":"Provost Iga",
    "wof:placetype":"venue"
},
  "geometry": {"coordinates":[-110.26474761999999,52.350944519],"type":"Point"}
}