{
  "type": "Feature",
  "properties": {
    "addr:full":"1430 Kings St N St Jacobs ON N0B 2N0",
    "addr:housenumber":"1430",
    "addr:postcode":"n0b 2n0",
    "addr:street":"Kings St N St",
    "iso:country":"CA",
    "sg:address":"1430 Kings St N",
    "sg:city":"St Jacobs",
    "sg:classifiers":[
        {
            "category":"Restaurant",
            "type":"Food & Drink"
        }
    ],
    "sg:phone":"+1 519 664 3731",
    "sg:postcode":"N0B 2N0",
    "sg:province":"ON",
    "wof:name":"Benjamin's Restaurant & Inn",
    "wof:placetype":"venue"
},
  "geometry": {"coordinates":[-80.553268,43.540054],"type":"Point"}
}