{
  "type": "Feature",
  "properties": {
    "addr:full":"525 Rue Ellis Beauharnois QC J6N 1X8",
    "addr:housenumber":"525",
    "addr:postcode":"j6n 1x8",
    "addr:street":"Rue Ellis",
    "iso:country":"CA",
    "sg:address":"525 Rue Ellis",
    "sg:city":"Beauharnois",
    "sg:classifiers":[
        {
            "category":"Health Services",
            "subcategory":"Optometrist",
            "type":"Services"
        }
    ],
    "sg:phone":"+1 450 225 6752",
    "sg:postcode":"J6N 1X8",
    "sg:province":"QC",
    "wof:name":"Marchand, Robert OD",
    "wof:placetype":"venue"
},
  "geometry": {"coordinates":[-73.871773,45.315166],"type":"Point"}
}