{
  "type": "Feature",
  "properties": {
    "addr:full":"Brampton ON L6W 3P4",
    "addr:postcode":"l6w 3p4",
    "iso:country":"CA",
    "sg:city":"Brampton",
    "sg:classifiers":[
        {
            "category":"Retail",
            "subcategory":"Auto Repair",
            "type":"Services"
        }
    ],
    "sg:phone":"+1 905 459 5533",
    "sg:postcode":"L6W 3P4",
    "sg:province":"ON",
    "sg:tags":[
        "spring"
    ],
    "wof:name":"P & J Spring & Wheel Align Svc",
    "wof:placetype":"venue"
},
  "geometry": {"coordinates":[-79.7297134399,43.6891555786],"type":"Point"}
}