{
  "type": "Feature",
  "properties": {
    "addr:full":"Charlottetown PE C1E 2A6",
    "addr:postcode":"c1e 2a6",
    "iso:country":"CA",
    "sg:city":"Charlottetown",
    "sg:classifiers":[
        {
            "category":"Manufacturing",
            "subcategory":"Food",
            "type":"Manufacturing & Wholesale Goods"
        }
    ],
    "sg:phone":"+1 902 566 4144",
    "sg:postcode":"C1E 2A6",
    "sg:province":"PE",
    "sg:tags":[
        "packer",
        "equipment",
        "fish"
    ],
    "wof:name":"Atlantic Systems Mfg",
    "wof:placetype":"venue"
},
  "geometry": {"coordinates":[-63.1281700134,46.2365913391],"type":"Point"}
}