{
  "type": "Feature",
  "properties": {
    "addr:full":"1095 Fewster Dr Mississauga ON L4W 1A2",
    "addr:housenumber":"1095",
    "addr:postcode":"l4w 1a2",
    "addr:street":"Fewster Dr",
    "iso:country":"CA",
    "sg:address":"1095 Fewster Dr",
    "sg:city":"Mississauga",
    "sg:classifiers":[
        {
            "category":"Retail",
            "subcategory":"Auto Repair",
            "type":"Services"
        }
    ],
    "sg:phone":"+1 905 629 2227",
    "sg:postcode":"L4W 1A2",
    "sg:province":"ON",
    "sg:tags":[
        "body",
        "automobile",
        "painting"
    ],
    "wof:name":"City Auto Body",
    "wof:placetype":"venue"
},
  "geometry": {"coordinates":[-79.6221084595,43.6273651123],"type":"Point"}
}