{
  "type": "Feature",
  "properties": {
    "addr:full":"836 Ontario St Sarnia ON N7T 1N2",
    "addr:housenumber":"836",
    "addr:postcode":"n7t 1n2",
    "addr:street":"Ontario St",
    "iso:country":"CA",
    "sg:address":"836 Ontario St",
    "sg:city":"Sarnia",
    "sg:classifiers":[
        {
            "category":"Autos & Motor Vehicles",
            "subcategory":"Automobile Sales",
            "type":"Retail Goods"
        }
    ],
    "sg:phone":"+1 519 344 7473",
    "sg:postcode":"N7T 1N2",
    "sg:province":"ON",
    "sg:tags":[
        "car",
        "dealer"
    ],
    "wof:name":"Fenwick Motors Ltd",
    "wof:placetype":"venue"
},
  "geometry": {"coordinates":[-82.379639,42.958599],"type":"Point"}
}