{
  "type": "Feature",
  "properties": {
    "addr:full":"1181 Rue Chartrand LA Plaine QC J7M 2B1",
    "addr:housenumber":"1181",
    "addr:postcode":"j7m 2b1",
    "addr:street":"Rue Chartrand",
    "iso:country":"CA",
    "sg:address":"1181 Rue Chartrand",
    "sg:city":"LA Plaine",
    "sg:classifiers":[
        {
            "category":"Personal",
            "subcategory":"Barber",
            "type":"Services"
        }
    ],
    "sg:phone":"+1 450 477 0223",
    "sg:postcode":"J7M 2B1",
    "sg:province":"QC",
    "wof:name":"Barbiere Du Coin",
    "wof:placetype":"venue"
},
  "geometry": {"coordinates":[-73.705681,45.751709],"type":"Point"}
}