{
  "type": "Feature",
  "properties": {
    "addr:full":"442 Front St Trenton ON K8V 4P9",
    "addr:housenumber":"442",
    "addr:postcode":"k8v 4p9",
    "addr:street":"Front St",
    "iso:country":"CA",
    "sg:address":"442 Front St",
    "sg:city":"Trenton",
    "sg:classifiers":[
        {
            "category":"Freight",
            "type":"Transportation"
        }
    ],
    "sg:phone":"+1 613 392 4774",
    "sg:postcode":"K8V 4P9",
    "sg:province":"ON",
    "sg:tags":[
        "bus",
        "line",
        "courier"
    ],
    "wof:name":"Greyhound Lines of Canada Ltd",
    "wof:placetype":"venue"
},
  "geometry": {"coordinates":[-77.5903701782,44.1080818176],"type":"Point"}
}