{
  "type": "Feature",
  "properties": {
    "addr:full":"4009 2nd Ave E Waldheim SK S0K 4R0",
    "addr:housenumber":"4009",
    "addr:postcode":"s0k 4r0",
    "addr:street":"2Nd Ave E",
    "iso:country":"CA",
    "sg:address":"4009 2nd Ave E",
    "sg:city":"Waldheim",
    "sg:classifiers":[
        {
            "category":"Organizations",
            "subcategory":"Religious Organization",
            "type":"Services"
        }
    ],
    "sg:phone":"+1 306 945 2271",
    "sg:postcode":"S0K 4R0",
    "sg:province":"SK",
    "sg:tags":[
        "church"
    ],
    "wof:name":"Zoar Mennonite Church",
    "wof:placetype":"venue"
},
  "geometry": {"coordinates":[-106.647575,52.613106],"type":"Point"}
}