{
  "type": "Feature",
  "properties": {
    "iso:country":"CA",
    "sg:address":"218 Boul Pabos",
    "sg:city":"Pabos",
    "sg:classifiers":[
        {
            "category":"Food & Beverages",
            "subcategory":"Dairy",
            "type":"Retail Goods"
        }
    ],
    "sg:phone":"+1 418 689 4412",
    "sg:postcode":"G0C 2H0",
    "sg:province":"QC",
    "sg:tags":[
        "product"
    ],
    "wof:name":"Bar Laitier Pabos",
    "wof:placetype":"venue"
},
  "geometry": {"coordinates":[-64.63418579099999,48.3573913574],"type":"Point"}
}