{
  "type": "Feature",
  "properties": {
    "iso:country":"CA",
    "sg:address":"6049 Boul Thimens",
    "sg:city":"Saint-Laurent",
    "sg:classifiers":[
        {
            "category":"Manufacturing",
            "subcategory":"Food",
            "type":"Manufacturing & Wholesale Goods"
        }
    ],
    "sg:phone":"+1 514 338 1819",
    "sg:postcode":"H4S 1V8",
    "sg:province":"QC",
    "sg:tags":[
        "confectionery",
        "candy"
    ],
    "wof:name":"Aliments Candybec Inc",
    "wof:placetype":"venue"
},
  "geometry": {"coordinates":[-73.737449646,45.5035476685],"type":"Point"}
}