{
  "type": "Feature",
  "properties": {
    "iso:country":"CA",
    "sg:address":"50 Acadia Ave",
    "sg:city":"Markham",
    "sg:classifiers":[
        {
            "category":"Real Estate",
            "subcategory":"Developer",
            "type":"Services"
        }
    ],
    "sg:phone":"+1 905 940 9357",
    "sg:postcode":"L3R 0B3",
    "sg:province":"ON",
    "wof:name":"Bentall Real Estate Svc Ltd",
    "wof:placetype":"venue"
},
  "geometry": {"coordinates":[-79.329071,43.820801],"type":"Point"}
}