{
  "type": "Feature",
  "properties": {
    "addr:full":"20 Rue DE Carillon Sherbrooke QC J1J 2K8",
    "addr:housenumber":"20",
    "addr:postcode":"j1j 2k8",
    "addr:street":"Rue De Carillon",
    "iso:country":"CA",
    "sg:address":"20 Rue DE Carillon",
    "sg:city":"Sherbrooke",
    "sg:classifiers":[
        {
            "category":"Health Services",
            "subcategory":"Doctor",
            "type":"Services"
        }
    ],
    "sg:phone":"+1 819 564 1331",
    "sg:postcode":"J1J 2K8",
    "sg:province":"QC",
    "sg:tags":[
        "clinic"
    ],
    "wof:name":"Centre DE Sante Carillon",
    "wof:placetype":"venue"
},
  "geometry": {"coordinates":[-71.9346160889,45.3987770081],"type":"Point"}
}