{
  "type": "Feature",
  "properties": {
    "addr:full":"2492 Yonge St Toronto ON M4P 2H7",
    "addr:housenumber":"2492",
    "addr:postcode":"m4p 2h7",
    "addr:street":"Yonge St",
    "iso:country":"CA",
    "sg:address":"2492 Yonge St",
    "sg:city":"Toronto",
    "sg:classifiers":[
        {
            "category":"Arts & Performance",
            "subcategory":"Theater",
            "type":"Entertainment"
        }
    ],
    "sg:phone":"+1 416 322 3322",
    "sg:postcode":"M4P 2H7",
    "sg:province":"ON",
    "wof:name":"Capital Event Theatre",
    "wof:placetype":"venue"
},
  "geometry": {"coordinates":[-79.399567,43.711903],"type":"Point"}
}