{
  "type": "Feature",
  "properties": {
    "addr:full":"649 Franklin St Brandon MB R7A 5P9",
    "addr:housenumber":"649",
    "addr:postcode":"r7a 5p9",
    "addr:street":"Franklin St",
    "iso:country":"CA",
    "sg:address":"649 Franklin St",
    "sg:city":"Brandon",
    "sg:classifiers":[
        {
            "category":"Arts & Performance",
            "subcategory":"Theater",
            "type":"Entertainment"
        }
    ],
    "sg:phone":"+1 204 728 8158",
    "sg:postcode":"R7A 5P9",
    "sg:province":"MB",
    "sg:tags":[
        "dance",
        "music",
        "recorded"
    ],
    "wof:name":"Original Sound",
    "wof:placetype":"venue"
},
  "geometry": {"coordinates":[-99.930573,49.84],"type":"Point"}
}