{
  "type": "Feature",
  "properties": {
    "addr:full":"392 Ivor Rd Victoria BC V9E 2C1",
    "addr:housenumber":"392",
    "addr:postcode":"v9e 2c1",
    "addr:street":"Ivor Rd",
    "iso:country":"CA",
    "sg:address":"392 Ivor Rd",
    "sg:city":"Victoria",
    "sg:classifiers":[
        {
            "category":"Freight",
            "type":"Transportation"
        }
    ],
    "sg:phone":"+1 250 479 4422",
    "sg:postcode":"V9E 2C1",
    "sg:province":"BC",
    "sg:tags":[
        "excavating",
        "contractor",
        "trucking"
    ],
    "wof:name":"Law Contracting Ltd",
    "wof:placetype":"venue"
},
  "geometry": {"coordinates":[-123.364517212,48.428314209],"type":"Point"}
}