{
  "type": "Feature",
  "properties": {
    "addr:full":"809 Dundas St London ON N5W 5P6",
    "addr:housenumber":"809",
    "addr:postcode":"n5w 5p6",
    "addr:street":"Dundas St",
    "iso:country":"CA",
    "sg:address":"809 Dundas St",
    "sg:city":"London",
    "sg:classifiers":[
        {
            "category":"Organizations",
            "subcategory":"Non-profit Organization",
            "type":"Services"
        }
    ],
    "sg:phone":"+1 519 672 4532",
    "sg:postcode":"N5W 5P6",
    "sg:province":"ON",
    "sg:tags":[
        "fund",
        "counselor",
        "raising"
    ],
    "wof:name":"Show CO",
    "wof:placetype":"venue"
},
  "geometry": {"coordinates":[-81.22412872309999,42.9908561707],"type":"Point"}
}