{
  "type": "Feature",
  "properties": {
    "addr:full":"123 Main St Ottawa ON K1S 1B9",
    "addr:housenumber":"123",
    "addr:postcode":"k1s 1b9",
    "addr:street":"Main St",
    "iso:country":"CA",
    "sg:address":"123 Main St",
    "sg:city":"Ottawa",
    "sg:classifiers":[
        {
            "category":"Retail",
            "subcategory":"Auto Repair",
            "type":"Services"
        }
    ],
    "sg:phone":"+1 613 232 6659",
    "sg:postcode":"K1S 1B9",
    "sg:province":"ON",
    "sg:tags":[
        "repairing",
        "automobile"
    ],
    "wof:name":"Mike Galazka Svc Ctr Ltd",
    "wof:placetype":"venue"
},
  "geometry": {"coordinates":[-75.67877197270001,45.4105644226],"type":"Point"}
}