{
  "type": "Feature",
  "properties": {
    "addr:full":"Toronto ON M5V 2A4",
    "addr:postcode":"m5v 2a4",
    "iso:country":"CA",
    "sg:city":"Toronto",
    "sg:classifiers":[
        {
            "category":"Health Services",
            "subcategory":"Optometrist",
            "type":"Services"
        }
    ],
    "sg:phone":"+1 416 596 8378",
    "sg:postcode":"M5V 2A4",
    "sg:province":"ON",
    "wof:name":"Li, Albert OD",
    "wof:placetype":"venue"
},
  "geometry": {"coordinates":[-79.391418457,43.649684906],"type":"Point"}
}