{
  "type": "Feature",
  "properties": {
    "addr:full":"5241 Hwy 86 E Listowel ON N4W 3G8",
    "addr:housenumber":"5241",
    "addr:postcode":"n4w 3g8",
    "addr:street":"Hwy 86 E",
    "iso:country":"CA",
    "sg:address":"5241 Hwy 86 E",
    "sg:city":"Listowel",
    "sg:classifiers":[
        {
            "category":"Autos & Motor Vehicles",
            "subcategory":"Recreational Vehicle Sales",
            "type":"Retail Goods"
        }
    ],
    "sg:phone":"+1 519 291 1158",
    "sg:postcode":"N4W 3G8",
    "sg:province":"ON",
    "wof:name":"Jewell Trailer Sales",
    "wof:placetype":"venue"
},
  "geometry": {"coordinates":[-80.896553,43.708263],"type":"Point"}
}