{
  "type": "Feature",
  "properties": {
    "addr:full":"325 Rue Sainte-Therese Quebec QC G1K 1M9",
    "addr:housenumber":"325",
    "addr:postcode":"g1k 1m9",
    "addr:street":"Rue Sainte-Therese",
    "iso:country":"CA",
    "sg:address":"325 Rue Sainte-Therese",
    "sg:city":"Quebec",
    "sg:classifiers":[
        {
            "category":"Organizations",
            "subcategory":"Professional Association",
            "type":"Services"
        }
    ],
    "sg:phone":"+1 418 529 1979",
    "sg:postcode":"G1K 1M9",
    "sg:province":"QC",
    "wof:name":"Acsm",
    "wof:placetype":"venue"
},
  "geometry": {"coordinates":[-71.23737300000001,46.811375],"type":"Point"}
}