{
  "type": "Feature",
  "properties": {
    "addr:full":"100 Kings Rd Sydney NS B1S 1A1",
    "addr:housenumber":"100",
    "addr:postcode":"b1s 1a1",
    "addr:street":"Kings Rd",
    "iso:country":"CA",
    "sg:address":"100 Kings Rd",
    "sg:city":"Sydney",
    "sg:classifiers":[
        {
            "category":"Restaurant",
            "type":"Food & Drink"
        }
    ],
    "sg:phone":"+1 902 371 0226",
    "sg:postcode":"B1S 1A1",
    "sg:province":"NS",
    "sg:tags":[
        "caterer"
    ],
    "wof:name":"Savory Gourmet",
    "wof:placetype":"venue"
},
  "geometry": {"coordinates":[-60.1954193115,46.1309318542],"type":"Point"}
}