{
  "type": "Feature",
  "properties": {
    "addr:full":"Lodgepole AB T0E 1K0",
    "addr:postcode":"t0e 1k0",
    "iso:country":"CA",
    "sg:city":"Lodgepole",
    "sg:classifiers":[
        {
            "category":"Travel",
            "subcategory":"Hotels & Motels",
            "type":"Entertainment"
        }
    ],
    "sg:phone":"+1 780 894 2202",
    "sg:postcode":"T0E 1K0",
    "sg:province":"AB",
    "wof:name":"Lodgepole Pine Inn",
    "wof:placetype":"venue"
},
  "geometry": {"coordinates":[-115.31802399999999,53.098434],"type":"Point"}
}