{
  "type": "Feature",
  "properties": {
    "addr:full":"871 Chemong Rd Peterborough ON K9H 5Z5",
    "addr:housenumber":"871",
    "addr:postcode":"k9h 5z5",
    "addr:street":"Chemong Rd",
    "iso:country":"CA",
    "sg:address":"871 Chemong Rd",
    "sg:city":"Peterborough",
    "sg:classifiers":[
        {
            "category":"Personal",
            "type":"Services"
        }
    ],
    "sg:phone":"+1 705 749 0546",
    "sg:postcode":"K9H 5Z5",
    "sg:province":"ON",
    "sg:tags":[
        "arts",
        "instruction",
        "martial",
        "program",
        "fitness",
        "exercise",
        "physical"
    ],
    "wof:name":"Body & Soul Family Fitness",
    "wof:placetype":"venue"
},
  "geometry": {"coordinates":[-78.33200100000001,44.31929],"type":"Point"}
}