{
  "type": "Feature",
  "properties": {
    "iso:country":"CA",
    "sg:address":"44 Centre St N",
    "sg:city":"Brampton",
    "sg:classifiers":[
        {
            "category":"Shopping",
            "subcategory":"Books",
            "type":"Retail Goods"
        }
    ],
    "sg:phone":"+1 905 459 2665",
    "sg:postcode":"L6V 1S8",
    "sg:province":"ON",
    "sg:tags":[
        "cards",
        "comic",
        "sport",
        "baseball",
        "memorabilia"
    ],
    "wof:name":"Comic Book Connection",
    "wof:placetype":"venue"
},
  "geometry": {"coordinates":[-79.7574539185,43.6924667358],"type":"Point"}
}