{
  "type": "Feature",
  "properties": {
    "addr:full":"7364 Yellowhead Trail NW Edmonton AB T5B 1G3",
    "addr:housenumber":"7364",
    "addr:postcode":"t5b 1g3",
    "addr:street":"Yellowhead Trail Nw",
    "iso:country":"CA",
    "sg:address":"7364 Yellowhead Trail NW",
    "sg:city":"Edmonton",
    "sg:classifiers":[
        {
            "category":"Wholesale",
            "subcategory":"Machinery & Supplies",
            "type":"Manufacturing & Wholesale Goods"
        }
    ],
    "sg:phone":"+1 780 463 2458",
    "sg:postcode":"T5B 1G3",
    "sg:province":"AB",
    "sg:tags":[
        "rental"
    ],
    "wof:name":"P R Rentals",
    "wof:placetype":"venue"
},
  "geometry": {"coordinates":[-113.45496368400001,53.5824432373],"type":"Point"}
}