{
  "type": "Feature",
  "properties": {
    "addr:full":"Saint-Basile-Le-Grand QC J3N 1L7",
    "addr:postcode":"j3n 1l7",
    "iso:country":"CA",
    "sg:city":"Saint-Basile-Le-Grand",
    "sg:classifiers":[
        {
            "category":"Wholesale",
            "subcategory":"Meat",
            "type":"Manufacturing & Wholesale Goods"
        }
    ],
    "sg:phone":"+1 450 441 0500",
    "sg:postcode":"J3N 1L7",
    "sg:province":"QC",
    "sg:tags":[
        "butchering"
    ],
    "wof:name":"Boucherie Jean-Pierre Richard",
    "wof:placetype":"venue"
},
  "geometry": {"coordinates":[-73.286315918,45.5257949829],"type":"Point"}
}