{
  "type": "Feature",
  "properties": {
    "iso:country":"CA",
    "sg:address":"380 Boul Charest E",
    "sg:city":"Quebec",
    "sg:classifiers":[
        {
            "category":"Restaurant",
            "type":"Food & Drink"
        }
    ],
    "sg:phone":"+1 418 648 6666",
    "sg:postcode":"G1K 3H4",
    "sg:province":"QC",
    "wof:name":"Restaurant Le Sainte-Victoire",
    "wof:placetype":"venue"
},
  "geometry": {"coordinates":[-71.22468566889999,46.8135795593],"type":"Point"}
}