{
  "type": "Feature",
  "properties": {
    "addr:full":"169 Staines Ch Sutton QC J0E 2K0",
    "addr:housenumber":"169",
    "addr:postcode":"j0e 2k0",
    "iso:country":"CA",
    "sg:address":"169 Staines Ch",
    "sg:city":"Sutton",
    "sg:classifiers":[
        {
            "category":"Travel",
            "subcategory":"Hotels & Motels",
            "type":"Entertainment"
        }
    ],
    "sg:phone":"+1 450 538 5639",
    "sg:postcode":"J0E 2K0",
    "sg:province":"QC",
    "sg:tags":[
        "outing",
        "facility"
    ],
    "wof:name":"Au Diable Vert",
    "wof:placetype":"venue"
},
  "geometry": {"coordinates":[-72.56598700000001,45.040211],"type":"Point"}
}