{
  "type": "Feature",
  "properties": {
    "iso:country":"CA",
    "sg:address":"259 Doyon St",
    "sg:city":"Saint-Victor",
    "sg:classifiers":[
        {
            "category":"Health Services",
            "subcategory":"Doctor",
            "type":"Services"
        }
    ],
    "sg:phone":"+1 418 588 6611",
    "sg:postcode":"G0M 2B0",
    "sg:province":"QC",
    "sg:tags":[
        "clinic"
    ],
    "wof:name":"Clinique Familale St-Victor",
    "wof:placetype":"venue"
},
  "geometry": {"coordinates":[-70.902679,46.14061],"type":"Point"}
}