{
  "type": "Feature",
  "properties": {
    "addr:full":"3150 Bird St Port Alberni BC V9Y 4B7",
    "addr:housenumber":"3150",
    "addr:postcode":"v9y 4b7",
    "addr:street":"Bird St",
    "iso:country":"CA",
    "sg:address":"3150 Bird St",
    "sg:city":"Port Alberni",
    "sg:classifiers":[
        {
            "category":"Marine",
            "type":"Transportation"
        }
    ],
    "sg:phone":"+1 250 723 5602",
    "sg:postcode":"V9Y 4B7",
    "sg:province":"BC",
    "sg:tags":[
        "towing"
    ],
    "wof:name":"Pacific Towing Svc Ltd",
    "wof:placetype":"venue"
},
  "geometry": {"coordinates":[-124.813484,49.235191],"type":"Point"}
}