{
  "type": "Feature",
  "properties": {
    "addr:full":"42 Victoria Ave Belleville ON K8N 1Z7",
    "addr:housenumber":"42",
    "addr:postcode":"k8n 1z7",
    "addr:street":"Victoria Ave",
    "iso:country":"CA",
    "sg:address":"42 Victoria Ave",
    "sg:city":"Belleville",
    "sg:classifiers":[
        {
            "category":"Health Services",
            "subcategory":"Doctor",
            "type":"Services"
        }
    ],
    "sg:phone":"+1 613 968 4866",
    "sg:postcode":"K8N 1Z7",
    "sg:province":"ON",
    "sg:tags":[
        "dentist"
    ],
    "wof:name":"Victoria Dental Arts",
    "wof:placetype":"venue"
},
  "geometry": {"coordinates":[-77.383728,44.167019],"type":"Point"}
}