{
  "type": "Feature",
  "properties": {
    "addr:full":"1292 Av Maguire Sillery QC G1T 1Z3",
    "addr:housenumber":"1292",
    "addr:postcode":"g1t 1z3",
    "addr:street":"Av Maguire",
    "iso:country":"CA",
    "sg:address":"1292 Av Maguire",
    "sg:city":"Sillery",
    "sg:classifiers":[
        {
            "category":"Food & Beverages",
            "subcategory":"Bakery",
            "type":"Retail Goods"
        }
    ],
    "sg:phone":"+1 418 687 9420",
    "sg:postcode":"G1T 1Z3",
    "sg:province":"QC",
    "sg:tags":[
        "baker"
    ],
    "wof:name":"Aux Delices DE Picardie",
    "wof:placetype":"venue"
},
  "geometry": {"coordinates":[-71.2520370483,46.7816390991],"type":"Point"}
}