{
  "type": "Feature",
  "properties": {
    "iso:country":"CA",
    "sg:address":"2426 200 St",
    "sg:city":"Langley",
    "sg:classifiers":[
        {
            "category":"Autos & Motor Vehicles",
            "subcategory":"Fuel & Gas Station",
            "type":"Retail Goods"
        }
    ],
    "sg:phone":"+1 604 533 4212",
    "sg:postcode":"V2Z 1X1",
    "sg:province":"BC",
    "sg:tags":[
        "oil"
    ],
    "wof:name":"Fernridge Service-Convenience",
    "wof:placetype":"venue"
},
  "geometry": {"coordinates":[-122.66918182400001,49.0466842651],"type":"Point"}
}