{
  "type": "Feature",
  "properties": {
    "addr:full":"618 Twelfth St # A New Westminster BC V3M 4J2",
    "addr:housenumber":"618",
    "addr:postcode":"v3m 4j2",
    "addr:street":"Twelfth St # A",
    "iso:country":"CA",
    "sg:address":"618 Twelfth St # A",
    "sg:city":"New Westminster",
    "sg:classifiers":[
        {
            "category":"Shopping",
            "subcategory":"Used Merchandise",
            "type":"Retail Goods"
        }
    ],
    "sg:phone":"+1 604 521 4403",
    "sg:postcode":"V3M 4J2",
    "sg:province":"BC",
    "sg:tags":[
        "antique"
    ],
    "wof:name":"Carousel Art Glass",
    "wof:placetype":"venue"
},
  "geometry": {"coordinates":[-122.93132782000001,49.2081604004],"type":"Point"}
}