{
  "type": "Feature",
  "properties": {
    "addr:full":"221 Victoria St Edmundston NB E3V 2J2",
    "addr:housenumber":"221",
    "addr:postcode":"e3v 2j2",
    "addr:street":"Victoria St",
    "iso:country":"CA",
    "sg:address":"221 Victoria St",
    "sg:city":"Edmundston",
    "sg:classifiers":[
        {
            "category":"Personal",
            "subcategory":"Tattoo Parlor",
            "type":"Services"
        }
    ],
    "sg:phone":"+1 506 737 8240",
    "sg:postcode":"E3V 2J2",
    "sg:province":"NB",
    "sg:tags":[
        "tattooing"
    ],
    "wof:name":"Tattoo",
    "wof:placetype":"venue"
},
  "geometry": {"coordinates":[-68.32473,47.370239],"type":"Point"}
}