{
  "type": "Feature",
  "properties": {
    "addr:full":"7784 Martin Grove Rd Woodbridge ON L4L 2C6",
    "addr:housenumber":"7784",
    "addr:postcode":"l4l 2c6",
    "addr:street":"Martin Grove Rd",
    "iso:country":"CA",
    "sg:address":"7784 Martin Grove Rd",
    "sg:city":"Woodbridge",
    "sg:classifiers":[
        {
            "category":"Social Services",
            "subcategory":"Child Care",
            "type":"Services"
        }
    ],
    "sg:phone":"+1 905 851 2422",
    "sg:postcode":"L4L 2C6",
    "sg:province":"ON",
    "wof:name":"St Peter's Child Care Ctr",
    "wof:placetype":"venue"
},
  "geometry": {"coordinates":[-79.6101531982,43.777721405],"type":"Point"}
}