{
  "type": "Feature",
  "properties": {
    "addr:full":"Saint-Edmond-DE-Grantham QC J0C 1K0",
    "addr:postcode":"j0c 1k0",
    "iso:country":"CA",
    "sg:city":"Saint-Edmond-DE-Grantham",
    "sg:classifiers":[
        {
            "category":"Manufacturing",
            "subcategory":"Tools & Machinery",
            "type":"Manufacturing & Wholesale Goods"
        }
    ],
    "sg:phone":"+1 819 395 4380",
    "sg:postcode":"J0C 1K0",
    "sg:province":"QC",
    "sg:tags":[
        "farm",
        "equipment"
    ],
    "wof:name":"Fabrication S Houle Inc",
    "wof:placetype":"venue"
},
  "geometry": {"coordinates":[-72.66184997560001,45.8744926453],"type":"Point"}
}