{
  "type": "Feature",
  "properties": {
    "addr:full":"North York ON M2M 3V6",
    "addr:postcode":"m2m 3v6",
    "iso:country":"CA",
    "sg:city":"North York",
    "sg:classifiers":[
        {
            "category":"Professional",
            "subcategory":"Lawyer & Legal Services",
            "type":"Services"
        }
    ],
    "sg:phone":"+1 416 229 9327",
    "sg:postcode":"M2M 3V6",
    "sg:province":"ON",
    "sg:tags":[
        "naturalization",
        "immigration"
    ],
    "wof:name":"Immigration Assistance & Svc",
    "wof:placetype":"venue"
},
  "geometry": {"coordinates":[-79.41675600000001,43.785473],"type":"Point"}
}