{
  "type": "Feature",
  "properties": {
    "iso:country":"CA",
    "sg:city":"Edmonton",
    "sg:classifiers":[
        {
            "category":"Professional",
            "subcategory":"Lawyer & Legal Services",
            "type":"Services"
        }
    ],
    "sg:phone":"+1 780 473 7927",
    "sg:postcode":"T5A 4L8",
    "sg:province":"AB",
    "sg:tags":[
        "attorney"
    ],
    "wof:name":"Kitt, Jerry M",
    "wof:placetype":"venue"
},
  "geometry": {"coordinates":[-113.418029785,53.5870780945],"type":"Point"}
}