{
  "type": "Feature",
  "properties": {
    "addr:full":"490 Rue Principale Lachute QC J8H 1Y3",
    "addr:housenumber":"490",
    "addr:postcode":"j8h 1y3",
    "addr:street":"Rue Principale",
    "iso:country":"CA",
    "sg:address":"490 Rue Principale",
    "sg:city":"Lachute",
    "sg:classifiers":[
        {
            "category":"Restaurant",
            "type":"Food & Drink"
        }
    ],
    "sg:phone":"+1 450 562 9000",
    "sg:postcode":"J8H 1Y3",
    "sg:province":"QC",
    "wof:name":"Restaurant Carole",
    "wof:placetype":"venue"
},
  "geometry": {"coordinates":[-74.33521270750001,45.6565933228],"type":"Point"}
}