{
  "type": "Feature",
  "properties": {
    "iso:country":"CA",
    "sg:address":"31 Rue Audubon",
    "sg:city":"Port-Cartier",
    "sg:classifiers":[
        {
            "category":"Social Services",
            "subcategory":"Child Care",
            "type":"Services"
        }
    ],
    "sg:phone":"+1 418 766 5156",
    "sg:postcode":"G5B 1M2",
    "sg:province":"QC",
    "wof:name":"Cpe Touchatouille Inc",
    "wof:placetype":"venue"
},
  "geometry": {"coordinates":[-66.85704800000001,50.025421],"type":"Point"}
}