{
  "type": "Feature",
  "properties": {
    "addr:full":"470 Rue Tessier Rimouski QC G5L 4L4",
    "addr:housenumber":"470",
    "addr:postcode":"g5l 4l4",
    "addr:street":"Rue Tessier",
    "iso:country":"CA",
    "sg:address":"470 Rue Tessier",
    "sg:city":"Rimouski",
    "sg:classifiers":[
        {
            "category":"Shopping",
            "subcategory":"Clothing, Apparel, & Fashions",
            "type":"Retail Goods"
        }
    ],
    "sg:phone":"+1 418 723 2667",
    "sg:postcode":"G5L 4L4",
    "sg:province":"QC",
    "sg:tags":[
        "item",
        "boutique"
    ],
    "wof:name":"Boutique L'Ensemblier Inc",
    "wof:placetype":"venue"
},
  "geometry": {"coordinates":[-68.54132080079999,48.4326553345],"type":"Point"}
}