{
  "type": "Feature",
  "properties": {
    "addr:full":"4 Matthias Pl Maryhill ON N0B 2B0",
    "addr:housenumber":"4",
    "addr:postcode":"n0b 2b0",
    "addr:street":"Matthias Pl",
    "iso:country":"CA",
    "sg:address":"4 Matthias Pl",
    "sg:city":"Maryhill",
    "sg:classifiers":[
        {
            "category":"Building & Trades",
            "subcategory":"Electrical",
            "type":"Services"
        }
    ],
    "sg:phone":"+1 519 648 3403",
    "sg:postcode":"N0B 2B0",
    "sg:province":"ON",
    "sg:tags":[
        "electric",
        "contractor"
    ],
    "wof:name":"Busse Heinz Electric",
    "wof:placetype":"venue"
},
  "geometry": {"coordinates":[-80.39238,43.537968],"type":"Point"}
}