{
  "type": "Feature",
  "properties": {
    "addr:full":"Vancouver BC V5T 4N9",
    "addr:postcode":"v5t 4n9",
    "iso:country":"CA",
    "sg:city":"Vancouver",
    "sg:classifiers":[
        {
            "category":"Personal",
            "type":"Services"
        }
    ],
    "sg:phone":"+1 604 874 6555",
    "sg:postcode":"V5T 4N9",
    "sg:province":"BC",
    "sg:tags":[
        "bureau"
    ],
    "wof:name":"Maria Southwell Dating Svc",
    "wof:placetype":"venue"
},
  "geometry": {"coordinates":[-123.103218079,49.2628479004],"type":"Point"}
}