{
  "type": "Feature",
  "properties": {
    "addr:full":"120 Rue Turgeon Sainte-Therese QC J7E 3H8",
    "addr:housenumber":"120",
    "addr:postcode":"j7e 3h8",
    "addr:street":"Rue Turgeon Sainte-Therese",
    "iso:country":"CA",
    "sg:address":"120 Rue Turgeon",
    "sg:city":"Sainte-Therese",
    "sg:classifiers":[
        {
            "category":"Home & Garden",
            "subcategory":"Building Materials",
            "type":"Retail Goods"
        }
    ],
    "sg:phone":"+1 450 434 5050",
    "sg:postcode":"J7E 3H8",
    "sg:province":"QC",
    "sg:tags":[
        "hardware"
    ],
    "wof:name":"Liquidation Medrek Inc",
    "wof:placetype":"venue"
},
  "geometry": {"coordinates":[-73.83633399999999,45.635361],"type":"Point"}
}