{
  "type": "Feature",
  "properties": {
    "iso:country":"CA",
    "sg:city":"Saint-Nicolas",
    "sg:classifiers":[
        {
            "category":"Shopping",
            "subcategory":"Gifts & Souvenirs",
            "type":"Retail Goods"
        }
    ],
    "sg:phone":"+1 418 836 2895",
    "sg:postcode":"G7A 4X8",
    "sg:province":"QC",
    "sg:tags":[
        "shop",
        "infant",
        "wear"
    ],
    "wof:name":"Boutique LA Grenouillere",
    "wof:placetype":"venue"
},
  "geometry": {"coordinates":[-71.398293,46.700764],"type":"Point"}
}