{
  "type": "Feature",
  "properties": {
    "addr:full":"Concord ON L4K 1N6",
    "addr:postcode":"l4k 1n6",
    "iso:country":"CA",
    "sg:city":"Concord",
    "sg:classifiers":[
        {
            "category":"Retail",
            "subcategory":"Auto Repair",
            "type":"Services"
        }
    ],
    "sg:phone":"+1 905 738 1220",
    "sg:postcode":"L4K 1N6",
    "sg:province":"ON",
    "sg:tags":[
        "automobile",
        "rustproofing",
        "undercoating"
    ],
    "wof:name":"Krown Body Maintenance",
    "wof:placetype":"venue"
},
  "geometry": {"coordinates":[-79.517342,43.794521],"type":"Point"}
}