{
  "type": "Feature",
  "properties": {
    "addr:full":"6321 126 St Surrey BC V3X 1V1",
    "addr:housenumber":"6321",
    "addr:postcode":"v3x 1v1",
    "addr:street":"126 St",
    "iso:country":"CA",
    "sg:address":"6321 126 St",
    "sg:city":"Surrey",
    "sg:classifiers":[
        {
            "category":"Shopping",
            "subcategory":"Computers & Home Electronics",
            "type":"Retail Goods"
        }
    ],
    "sg:phone":"+1 604 597 6578",
    "sg:postcode":"V3X 1V1",
    "sg:province":"BC",
    "sg:tags":[
        "television",
        "radio"
    ],
    "wof:name":"K P Components",
    "wof:placetype":"venue"
},
  "geometry": {"coordinates":[-122.873383,49.119171],"type":"Point"}
}