{
  "type": "Feature",
  "properties": {
    "addr:full":"5001 53 St Killam AB T0B 2L0",
    "addr:housenumber":"5001",
    "addr:postcode":"t0b 2l0",
    "addr:street":"53 St",
    "iso:country":"CA",
    "sg:address":"5001 53 St",
    "sg:city":"Killam",
    "sg:classifiers":[
        {
            "category":"Organizations",
            "subcategory":"Religious Organization",
            "type":"Services"
        }
    ],
    "sg:phone":"+1 780 385 3503",
    "sg:postcode":"T0B 2L0",
    "sg:province":"AB",
    "sg:tags":[
        "church"
    ],
    "wof:name":"St Joseph's Catholic Church",
    "wof:placetype":"venue"
},
  "geometry": {"coordinates":[-111.859802246,52.7916603088],"type":"Point"}
}