{
  "type": "Feature",
  "properties": {
    "addr:full":"1417 Yonge St Toronto ON M4T 1Y7",
    "addr:housenumber":"1417",
    "addr:postcode":"m4t 1y7",
    "addr:street":"Yonge St",
    "iso:country":"CA",
    "sg:address":"1417 Yonge St",
    "sg:city":"Toronto",
    "sg:classifiers":[
        {
            "category":"Shopping",
            "subcategory":"Clothing, Apparel, & Fashions",
            "type":"Retail Goods"
        }
    ],
    "sg:phone":"+1 416 923 7842",
    "sg:postcode":"M4T 1Y7",
    "sg:province":"ON",
    "sg:tags":[
        "fur",
        "business"
    ],
    "wof:name":"Furs By Leonard",
    "wof:placetype":"venue"
},
  "geometry": {"coordinates":[-79.393692,43.687565],"type":"Point"}
}