{
  "type": "Feature",
  "properties": {
    "addr:full":"72 Boul Leveille Saint-Eustache QC J7R 6V2",
    "addr:housenumber":"72",
    "addr:postcode":"j7r 6v2",
    "addr:street":"Boul Leveille",
    "iso:country":"CA",
    "sg:address":"72 Boul Leveille",
    "sg:city":"Saint-Eustache",
    "sg:classifiers":[
        {
            "category":"Freight",
            "type":"Transportation"
        }
    ],
    "sg:phone":"+1 450 472 2916",
    "sg:postcode":"J7R 6V2",
    "sg:province":"QC",
    "sg:tags":[
        "trucking"
    ],
    "wof:name":"Poste DE Camionnage En Vrac",
    "wof:placetype":"venue"
},
  "geometry": {"coordinates":[-73.923683,45.581181],"type":"Point"}
}