{
  "type": "Feature",
  "properties": {
    "addr:full":"1958 Mapleridge Dr Peterborough ON K9K 2E4",
    "addr:housenumber":"1958",
    "addr:postcode":"k9k 2e4",
    "addr:street":"Mapleridge Dr",
    "iso:country":"CA",
    "sg:address":"1958 Mapleridge Dr",
    "sg:city":"Peterborough",
    "sg:classifiers":[
        {
            "category":"Travel",
            "subcategory":"Travel Agent",
            "type":"Entertainment"
        }
    ],
    "sg:phone":"+1 705 876 7711",
    "sg:postcode":"K9K 2E4",
    "sg:province":"ON",
    "sg:tags":[
        "information",
        "tourist"
    ],
    "wof:name":"Tourism CO",
    "wof:placetype":"venue"
},
  "geometry": {"coordinates":[-78.37856292719999,44.2778701782],"type":"Point"}
}