{
  "type": "Feature",
  "properties": {
    "addr:full":"Chambly QC J3L 1Z6",
    "addr:postcode":"j3l 1z6",
    "iso:country":"CA",
    "sg:city":"Chambly",
    "sg:classifiers":[
        {
            "category":"Real Estate",
            "subcategory":"Surveying",
            "type":"Services"
        }
    ],
    "sg:phone":"+1 450 658 3458",
    "sg:postcode":"J3L 1Z6",
    "sg:province":"QC",
    "sg:tags":[
        "surveyor"
    ],
    "wof:name":"Berard Tremblay Land Surveyor",
    "wof:placetype":"venue"
},
  "geometry": {"coordinates":[-73.27262899999999,45.447716],"type":"Point"}
}