{
  "type": "Feature",
  "properties": {
    "addr:full":"6230 Hazeldean Rd Stittsville ON K2S 1B9",
    "addr:housenumber":"6230",
    "addr:postcode":"k2s 1b9",
    "addr:street":"Hazeldean Rd",
    "iso:country":"CA",
    "sg:address":"6230 Hazeldean Rd",
    "sg:city":"Stittsville",
    "sg:classifiers":[
        {
            "category":"Retail",
            "subcategory":"Auto Rental",
            "type":"Services"
        }
    ],
    "sg:phone":"+1 613 836 3333",
    "sg:postcode":"K2S 1B9",
    "sg:province":"ON",
    "sg:tags":[
        "renting",
        "automobile"
    ],
    "wof:name":"Orr Motors",
    "wof:placetype":"venue"
},
  "geometry": {"coordinates":[-75.93795,45.268639],"type":"Point"}
}