{
  "type": "Feature",
  "properties": {
    "addr:full":"Calgary AB T2T 3S9",
    "addr:postcode":"t2t 3s9",
    "iso:country":"CA",
    "sg:city":"Calgary",
    "sg:classifiers":[
        {
            "category":"Building & Trades",
            "subcategory":"Cleaning & Sanitation",
            "type":"Services"
        }
    ],
    "sg:phone":"+1 403 229 2406",
    "sg:postcode":"T2T 3S9",
    "sg:province":"AB",
    "sg:tags":[
        "janitor"
    ],
    "wof:name":"Cleanmax Inc",
    "wof:placetype":"venue"
},
  "geometry": {"coordinates":[-114.094566345,51.0364494324],"type":"Point"}
}