{
  "type": "Feature",
  "properties": {
    "addr:full":"314-55 Water Street Vancouver V6B1A1",
    "addr:housenumber":"314-55",
    "addr:postcode":"v6b1a1",
    "addr:street":"Water Street",
    "iso:country":"CA",
    "sg:address":"314-55 Water Street",
    "sg:city":"Vancouver",
    "sg:classifiers":[
        {
            "category":"Professional",
            "subcategory":"Computer Services",
            "type":"Services"
        }
    ],
    "sg:postcode":"V6B1A1",
    "sg:tags":[
        "web",
        "community",
        "democracy",
        "share",
        "2-0",
        "development",
        "cfml",
        "campaign",
        "service",
        "vancouver"
    ],
    "sg:website":"http://surgenia.com",
    "wof:name":"Surgenia Productions",
    "wof:placetype":"venue"
},
  "geometry": {"coordinates":[-123.10913600000001,49.28437],"type":"Point"}
}