{
  "type": "Feature",
  "properties": {
    "addr:full":"15829 Simcoe St Port Perry ON L9L 1N5",
    "addr:housenumber":"15829",
    "addr:postcode":"l9l 1n5",
    "addr:street":"Simcoe St",
    "iso:country":"CA",
    "sg:address":"15829 Simcoe St",
    "sg:city":"Port Perry",
    "sg:classifiers":[
        {
            "category":"Autos & Motor Vehicles",
            "subcategory":"Fuel & Gas Station",
            "type":"Retail Goods"
        }
    ],
    "sg:phone":"+1 905 985 8177",
    "sg:postcode":"L9L 1N5",
    "sg:province":"ON",
    "sg:tags":[
        "oil"
    ],
    "wof:name":"Flieler North End Svc Station",
    "wof:placetype":"venue"
},
  "geometry": {"coordinates":[-78.949684,44.109783],"type":"Point"}
}