{
  "type": "Feature",
  "properties": {
    "addr:full":"613 Marion St Winnipeg MB R2J 0K2",
    "addr:housenumber":"613",
    "addr:postcode":"r2j 0k2",
    "addr:street":"Marion St",
    "iso:country":"CA",
    "sg:address":"613 Marion St",
    "sg:city":"Winnipeg",
    "sg:classifiers":[
        {
            "category":"Wholesale",
            "subcategory":"Home Furnishings",
            "type":"Manufacturing & Wholesale Goods"
        }
    ],
    "sg:phone":"+1 204 982 6363",
    "sg:postcode":"R2J 0K2",
    "sg:province":"MB",
    "sg:tags":[
        "picture",
        "frame"
    ],
    "wof:name":"Quadro Frames",
    "wof:placetype":"venue"
},
  "geometry": {"coordinates":[-97.0968704224,49.8820991516],"type":"Point"}
}