{
  "type": "Feature",
  "properties": {
    "addr:full":"410 Lillooet St W Moose Jaw SK S6H 7T1",
    "addr:housenumber":"410",
    "addr:postcode":"s6h 7t1",
    "addr:street":"Lillooet St W",
    "iso:country":"CA",
    "sg:address":"410 Lillooet St W",
    "sg:city":"Moose Jaw",
    "sg:classifiers":[
        {
            "category":"Restaurant",
            "type":"Food & Drink"
        }
    ],
    "sg:phone":"+1 306 692 5336",
    "sg:postcode":"S6H 7T1",
    "sg:province":"SK",
    "wof:name":"Family Pizza",
    "wof:placetype":"venue"
},
  "geometry": {"coordinates":[-105.545135,50.384361],"type":"Point"}
}