{
  "type": "Feature",
  "properties": {
    "addr:full":"216 Hunter St W Peterborough ON K9H 2L2",
    "addr:housenumber":"216",
    "addr:postcode":"k9h 2l2",
    "addr:street":"Hunter St W",
    "iso:country":"CA",
    "sg:address":"216 Hunter St W",
    "sg:city":"Peterborough",
    "sg:classifiers":[
        {
            "category":"Restaurant",
            "type":"Food & Drink"
        }
    ],
    "sg:phone":"+1 705 743 7591",
    "sg:postcode":"K9H 2L2",
    "sg:province":"ON",
    "wof:name":"Only Cafe",
    "wof:placetype":"venue"
},
  "geometry": {"coordinates":[-78.3223953247,44.3059387207],"type":"Point"}
}