{
  "type": "Feature",
  "properties": {
    "iso:country":"CA",
    "sg:address":"76 Hodgson Dr",
    "sg:city":"Barrie",
    "sg:classifiers":[
        {
            "category":"Arts & Performance",
            "subcategory":"Theater",
            "type":"Entertainment"
        }
    ],
    "sg:phone":"+1 705 728 7070",
    "sg:postcode":"L4N 7Z2",
    "sg:province":"ON",
    "sg:tags":[
        "entertainer",
        "clown"
    ],
    "wof:name":"Daisy the Clown",
    "wof:placetype":"venue"
},
  "geometry": {"coordinates":[-79.738823,44.392937],"type":"Point"}
}