{
  "type": "Feature",
  "properties": {
    "addr:full":"469 River Ave Winnipeg MB R3L 0C9",
    "addr:housenumber":"469",
    "addr:postcode":"r3l 0c9",
    "addr:street":"River Ave",
    "iso:country":"CA",
    "sg:address":"469 River Ave",
    "sg:city":"Winnipeg",
    "sg:classifiers":[
        {
            "category":"Food & Beverages",
            "subcategory":"Liquor & Beverages",
            "type":"Retail Goods"
        }
    ],
    "sg:phone":"+1 204 987 4012",
    "sg:postcode":"R3L 0C9",
    "sg:province":"MB",
    "sg:tags":[
        "store"
    ],
    "wof:name":"Manitoba Liquor Control Comm",
    "wof:placetype":"venue"
},
  "geometry": {"coordinates":[-97.1467971802,49.879196167],"type":"Point"}
}