{
  "type": "Feature",
  "properties": {
    "addr:full":"105 Lakeview Ave Middle Sackville NS B4E 3B5",
    "addr:housenumber":"105",
    "addr:postcode":"b4e 3b5",
    "addr:street":"Lakeview Ave",
    "iso:country":"CA",
    "sg:address":"105 Lakeview Ave",
    "sg:city":"Middle Sackville",
    "sg:classifiers":[
        {
            "category":"Building & Trades",
            "subcategory":"Construction",
            "type":"Services"
        }
    ],
    "sg:phone":"+1 902 865 5822",
    "sg:postcode":"B4E 3B5",
    "sg:province":"NS",
    "sg:tags":[
        "excavating",
        "contractor"
    ],
    "wof:name":"Tri-Ex Construction",
    "wof:placetype":"venue"
},
  "geometry": {"coordinates":[-63.7274856567,44.7955665588],"type":"Point"}
}