{
  "type": "Feature",
  "properties": {
    "addr:full":"Liverpool NS B0T 1K0",
    "addr:postcode":"b0t 1k0",
    "iso:country":"CA",
    "sg:city":"Liverpool",
    "sg:classifiers":[
        {
            "category":"Retail",
            "subcategory":"Auto Repair",
            "type":"Services"
        }
    ],
    "sg:phone":"+1 902 354 2381",
    "sg:postcode":"B0T 1K0",
    "sg:province":"NS",
    "sg:tags":[
        "repairing",
        "automobile"
    ],
    "wof:name":"Mick's Auto Repair",
    "wof:placetype":"venue"
},
  "geometry": {"coordinates":[-64.716049,44.040043],"type":"Point"}
}