{
  "type": "Feature",
  "properties": {
    "addr:full":"5951 92 St NW Edmonton AB T6E 3A5",
    "addr:housenumber":"5951",
    "addr:postcode":"t6e 3a5",
    "addr:street":"92 St Nw",
    "iso:country":"CA",
    "sg:address":"5951 92 St NW",
    "sg:city":"Edmonton",
    "sg:classifiers":[
        {
            "category":"Manufacturing",
            "subcategory":"Petroleum Products",
            "type":"Manufacturing & Wholesale Goods"
        }
    ],
    "sg:phone":"+1 780 435 0134",
    "sg:postcode":"T6E 3A5",
    "sg:province":"AB",
    "sg:tags":[
        "recycling",
        "center",
        "oil"
    ],
    "wof:name":"Doherty's Hydraulic Oil Rcyclg",
    "wof:placetype":"venue"
},
  "geometry": {"coordinates":[-113.468513,53.495228],"type":"Point"}
}