{
  "type": "Feature",
  "properties": {
    "addr:full":"936 Bedford Hwy Bedford NS B4A 3P1",
    "addr:housenumber":"936",
    "addr:postcode":"b4a 3p1",
    "addr:street":"Bedford Hwy",
    "iso:country":"CA",
    "sg:address":"936 Bedford Hwy",
    "sg:city":"Bedford",
    "sg:classifiers":[
        {
            "category":"Retail",
            "subcategory":"Laundry & Dry Cleaning",
            "type":"Services"
        }
    ],
    "sg:phone":"+1 902 832 1599",
    "sg:postcode":"B4A 3P1",
    "sg:province":"NS",
    "sg:tags":[
        "cleaners"
    ],
    "wof:name":"Same Day Dry Cleaners",
    "wof:placetype":"venue"
},
  "geometry": {"coordinates":[-63.678188324,44.71459198],"type":"Point"}
}