{
  "type": "Feature",
  "properties": {
    "addr:full":"11 Empire Lane Windsor NS B0N 2T0",
    "addr:housenumber":"11",
    "addr:postcode":"b0n 2t0",
    "addr:street":"Empire Lane",
    "iso:country":"CA",
    "sg:address":"11 Empire Lane",
    "sg:city":"Windsor",
    "sg:classifiers":[
        {
            "category":"Restaurant",
            "type":"Food & Drink"
        }
    ],
    "sg:phone":"+1 902 798 8088",
    "sg:postcode":"B0N 2T0",
    "sg:province":"NS",
    "sg:tags":[
        "out",
        "pizza"
    ],
    "wof:name":"Magic Pizza",
    "wof:placetype":"venue"
},
  "geometry": {"coordinates":[-64.1306762695,44.98985672],"type":"Point"}
}