{
  "type": "Feature",
  "properties": {
    "addr:full":"5907 4 Ave # A Edson AB T7E 1L9",
    "addr:housenumber":"5907",
    "addr:postcode":"t7e 1l9",
    "addr:street":"4 Ave # A Edson",
    "iso:country":"CA",
    "sg:address":"5907 4 Ave # A",
    "sg:city":"Edson",
    "sg:classifiers":[
        {
            "category":"Wholesale",
            "subcategory":"Machinery & Supplies",
            "type":"Manufacturing & Wholesale Goods"
        }
    ],
    "sg:phone":"+1 780 723 2691",
    "sg:postcode":"T7E 1L9",
    "sg:province":"AB",
    "sg:tags":[
        "equipment",
        "oil",
        "well"
    ],
    "wof:name":"Midfield Supply Ltd",
    "wof:placetype":"venue"
},
  "geometry": {"coordinates":[-116.45362854,53.5768890381],"type":"Point"}
}