{
  "type": "Feature",
  "properties": {
    "addr:full":"Calgary AB T2R 0W7",
    "addr:postcode":"t2r 0w7",
    "iso:country":"CA",
    "sg:city":"Calgary",
    "sg:classifiers":[
        {
            "category":"Professional",
            "subcategory":"Business Services",
            "type":"Services"
        }
    ],
    "sg:phone":"+1 403 263 1229",
    "sg:postcode":"T2R 0W7",
    "sg:province":"AB",
    "sg:tags":[
        "designer",
        "drafting"
    ],
    "wof:name":"Technical Graphics Ltd",
    "wof:placetype":"venue"
},
  "geometry": {"coordinates":[-114.068489,51.039551],"type":"Point"}
}