{
  "type": "Feature",
  "properties": {
    "addr:full":"RR 2 STN Main Welland ON L3B 5N5",
    "addr:postcode":"l3b 5n5",
    "addr:street":"Rr 2 Stn Main",
    "iso:country":"CA",
    "sg:address":"RR 2 STN Main",
    "sg:city":"Welland",
    "sg:classifiers":[
        {
            "category":"Building & Trades",
            "subcategory":"Construction",
            "type":"Services"
        }
    ],
    "sg:phone":"+1 905 892 5387",
    "sg:postcode":"L3B 5N5",
    "sg:province":"ON",
    "sg:tags":[
        "excavating",
        "contractor"
    ],
    "wof:name":"Duffin Contracting Inc",
    "wof:placetype":"venue"
},
  "geometry": {"coordinates":[-79.239243,42.99345],"type":"Point"}
}