{
  "type": "Feature",
  "properties": {
    "addr:full":"North Bay ON P1B 9P2",
    "addr:postcode":"p1b 9p2",
    "iso:country":"CA",
    "sg:city":"North Bay",
    "sg:classifiers":[
        {
            "category":"Wholesale",
            "subcategory":"Office Equipment",
            "type":"Manufacturing & Wholesale Goods"
        }
    ],
    "sg:phone":"+1 705 474 7331",
    "sg:postcode":"P1B 9P2",
    "sg:province":"ON",
    "sg:tags":[
        "machine",
        "duplicating",
        "copying"
    ],
    "wof:name":"Digital Office Solutions",
    "wof:placetype":"venue"
},
  "geometry": {"coordinates":[-79.472679,46.332844],"type":"Point"}
}