{
  "type": "Feature",
  "properties": {
    "addr:full":"1045 Boul Rene-Levesque O Sillery QC G1S 1V3",
    "addr:housenumber":"1045",
    "addr:postcode":"g1s 1v3",
    "addr:street":"Boul Rene-Levesque O",
    "iso:country":"CA",
    "sg:address":"1045 Boul Rene-Levesque O",
    "sg:city":"Sillery",
    "sg:classifiers":[
        {
            "category":"Health Services",
            "subcategory":"Nursing And Care Facility",
            "type":"Services"
        }
    ],
    "sg:phone":"+1 418 681 3561",
    "sg:postcode":"G1S 1V3",
    "sg:province":"QC",
    "sg:tags":[
        "home",
        "rest"
    ],
    "wof:name":"Pavillon St-Dominique",
    "wof:placetype":"venue"
},
  "geometry": {"coordinates":[-71.242195,46.795349],"type":"Point"}
}