{
  "type": "Feature",
  "properties": {
    "addr:full":"8154 Boxer Crt Mission BC V2V 5K7",
    "addr:housenumber":"8154",
    "addr:postcode":"v2v 5k7",
    "addr:street":"Boxer Crt",
    "iso:country":"CA",
    "sg:address":"8154 Boxer Crt",
    "sg:city":"Mission",
    "sg:classifiers":[
        {
            "category":"Shopping",
            "subcategory":"Computers & Home Electronics",
            "type":"Retail Goods"
        }
    ],
    "sg:phone":"+1 604 814 0306",
    "sg:postcode":"V2V 5K7",
    "sg:province":"BC",
    "sg:tags":[
        "equipment",
        "dealer"
    ],
    "wof:name":"A Plus Network Solutions",
    "wof:placetype":"venue"
},
  "geometry": {"coordinates":[-122.322387695,49.1500968933],"type":"Point"}
}