{
  "type": "Feature",
  "properties": {
    "addr:full":"1659 Nicholson St S Prince George BC V2N 1V7",
    "addr:housenumber":"1659",
    "addr:postcode":"v2n 1v7",
    "addr:street":"Nicholson St S",
    "iso:country":"CA",
    "sg:address":"1659 Nicholson St S",
    "sg:city":"Prince George",
    "sg:classifiers":[
        {
            "category":"Shopping",
            "subcategory":"Bicycles & Sporting Goods",
            "type":"Retail Goods"
        }
    ],
    "sg:phone":"+1 250 563 4828",
    "sg:postcode":"V2N 1V7",
    "sg:province":"BC",
    "wof:name":"Koops' Bike Shop Ltd",
    "wof:placetype":"venue"
},
  "geometry": {"coordinates":[-122.786507,53.908413],"type":"Point"}
}