{
  "type": "Feature",
  "properties": {
    "addr:full":"Montreal QC H2J 2L1",
    "addr:postcode":"h2j 2l1",
    "iso:country":"CA",
    "sg:city":"Montreal",
    "sg:classifiers":[
        {
            "category":"Manufacturing",
            "subcategory":"Printing",
            "type":"Manufacturing & Wholesale Goods"
        }
    ],
    "sg:phone":"+1 514 843 6888",
    "sg:postcode":"H2J 2L1",
    "sg:province":"QC",
    "sg:tags":[
        "publisher"
    ],
    "wof:name":"Quebec Science Le Magazine",
    "wof:placetype":"venue"
},
  "geometry": {"coordinates":[-73.58137499999999,45.523125],"type":"Point"}
}