{
  "type": "Feature",
  "properties": {
    "addr:full":"2668 Binbrook Rd Binbrook ON L0R 1C0",
    "addr:housenumber":"2668",
    "addr:postcode":"l0r 1c0",
    "addr:street":"Binbrook Rd",
    "iso:country":"CA",
    "sg:address":"2668 Binbrook Rd",
    "sg:city":"Binbrook",
    "sg:classifiers":[
        {
            "category":"Shopping",
            "subcategory":"Florist",
            "type":"Retail Goods"
        }
    ],
    "sg:phone":"+1 905 692 3674",
    "sg:postcode":"L0R 1C0",
    "sg:province":"ON",
    "wof:name":"Village Green Flowers",
    "wof:placetype":"venue"
},
  "geometry": {"coordinates":[-79.80497,43.121048],"type":"Point"}
}