{
  "type": "Feature",
  "properties": {
    "iso:country":"CA",
    "sg:address":"3181 Rue Delaunay",
    "sg:city":"Laval",
    "sg:classifiers":[
        {
            "category":"Manufacturing",
            "subcategory":"Printing",
            "type":"Manufacturing & Wholesale Goods"
        }
    ],
    "sg:phone":"+1 450 682 0263",
    "sg:postcode":"H7L 5A4",
    "sg:province":"QC",
    "sg:tags":[
        "printer"
    ],
    "wof:name":"Litho Cp Inc",
    "wof:placetype":"venue"
},
  "geometry": {"coordinates":[-73.75704956049999,45.5865516663],"type":"Point"}
}