{
  "type": "Feature",
  "properties": {
    "addr:full":"4999 43 St SE # 147 Calgary AB T2B 3N4",
    "addr:housenumber":"4999",
    "addr:postcode":"t2b 3n4",
    "addr:street":"43 St Se # 147",
    "iso:country":"CA",
    "sg:address":"4999 43 St SE # 147",
    "sg:city":"Calgary",
    "sg:classifiers":[
        {
            "category":"Wholesale",
            "subcategory":"Groceries",
            "type":"Manufacturing & Wholesale Goods"
        }
    ],
    "sg:phone":"+1 403 259 4477",
    "sg:postcode":"T2B 3N4",
    "sg:province":"AB",
    "sg:tags":[
        "broker"
    ],
    "wof:name":"International Pacific Sales",
    "wof:placetype":"venue"
},
  "geometry": {"coordinates":[-113.970252991,51.010093689],"type":"Point"}
}