{
  "type": "Feature",
  "properties": {
    "addr:full":"1614 Grey Nuns Dr Orleans ON K1C 1V2",
    "addr:housenumber":"1614",
    "addr:postcode":"k1c 1v2",
    "addr:street":"Grey Nuns Dr",
    "iso:country":"CA",
    "sg:address":"1614 Grey Nuns Dr",
    "sg:city":"Orleans",
    "sg:classifiers":[
        {
            "category":"Arts & Performance",
            "subcategory":"Theater",
            "type":"Entertainment"
        }
    ],
    "sg:phone":"+1 613 830 8463",
    "sg:postcode":"K1C 1V2",
    "sg:province":"ON",
    "sg:tags":[
        "live",
        "music"
    ],
    "wof:name":"Cheers Bj the Dj",
    "wof:placetype":"venue"
},
  "geometry": {"coordinates":[-75.542053,45.467464],"type":"Point"}
}