{
  "type": "Feature",
  "properties": {
    "addr:full":"1004 17 Ave SW Calgary AB T2T 0A5",
    "addr:housenumber":"1004",
    "addr:postcode":"t2t 0a5",
    "addr:street":"17 Ave Sw",
    "iso:country":"CA",
    "sg:address":"1004 17 Ave SW",
    "sg:city":"Calgary",
    "sg:classifiers":[
        {
            "category":"Shopping",
            "subcategory":"News",
            "type":"Retail Goods"
        }
    ],
    "sg:phone":"+1 403 244 2060",
    "sg:postcode":"T2T 0A5",
    "sg:province":"AB",
    "sg:tags":[
        "newspaper"
    ],
    "wof:name":"Daily Globe News",
    "wof:placetype":"venue"
},
  "geometry": {"coordinates":[-114.08467899999999,51.038006],"type":"Point"}
}