{
  "type": "Feature",
  "properties": {
    "addr:full":"Saskatoon SK S7J 2G2",
    "addr:postcode":"s7j 2g2",
    "iso:country":"CA",
    "sg:city":"Saskatoon",
    "sg:classifiers":[
        {
            "category":"Shopping",
            "subcategory":"Optical Goods",
            "type":"Retail Goods"
        }
    ],
    "sg:phone":"+1 306 955 6410",
    "sg:postcode":"S7J 2G2",
    "sg:province":"SK",
    "sg:tags":[
        "sun",
        "goggles",
        "sunglasses",
        "optician"
    ],
    "wof:name":"Shopper's Optical",
    "wof:placetype":"venue"
},
  "geometry": {"coordinates":[-106.62247467,52.1013145447],"type":"Point"}
}