{
  "type": "Feature",
  "properties": {
    "addr:full":"Vancouver BC V6J 1M9",
    "addr:postcode":"v6j 1m9",
    "iso:country":"CA",
    "sg:city":"Vancouver",
    "sg:classifiers":[
        {
            "category":"Wholesale",
            "subcategory":"Machinery & Supplies",
            "type":"Manufacturing & Wholesale Goods"
        }
    ],
    "sg:phone":"+1 604 731 5777",
    "sg:postcode":"V6J 1M9",
    "sg:province":"BC",
    "sg:tags":[
        "stock",
        "boards",
        "system",
        "quotation"
    ],
    "wof:name":"Independent Survey CO",
    "wof:placetype":"venue"
},
  "geometry": {"coordinates":[-123.15209197999999,49.2680206299],"type":"Point"}
}