{
  "type": "Feature",
  "properties": {
    "iso:country":"CA",
    "sg:city":"Edmonton",
    "sg:classifiers":[
        {
            "category":"Restaurant",
            "type":"Food & Drink"
        }
    ],
    "sg:phone":"+1 780 444 9464",
    "sg:postcode":"T5T 4M2",
    "sg:province":"AB",
    "wof:name":"Hooters Restaurant",
    "wof:placetype":"venue"
},
  "geometry": {"coordinates":[-113.615600586,53.5235862732],"type":"Point"}
}