{
  "type": "Feature",
  "properties": {
    "addr:full":"609 Helmcken St Vancouver BC V6B 5R1",
    "addr:housenumber":"609",
    "addr:postcode":"bc v6b 5r1",
    "addr:street":"Helmcken St",
    "iso:country":"CA",
    "sg:address":"609 Helmcken St",
    "sg:city":"Vancouver",
    "sg:classifiers":[
        {
            "category":"Education",
            "subcategory":"School",
            "type":"Public Place"
        }
    ],
    "sg:phone":"+1 604 257 3849",
    "sg:postcode":"V6B 5R1",
    "sg:province":"BC",
    "wof:name":"Gathering Place Educ Ctr",
    "wof:placetype":"venue"
},
  "geometry": {"coordinates":[-123.12365,49.277794],"type":"Point"}
}