{
  "type": "Feature",
  "properties": {
    "addr:full":"Orangeville ON L9W 2Z3",
    "addr:postcode":"l9w 2z3",
    "iso:country":"CA",
    "sg:city":"Orangeville",
    "sg:classifiers":[
        {
            "category":"Government",
            "subcategory":"Office",
            "type":"Public Place"
        }
    ],
    "sg:phone":"+1 519 941 1007",
    "sg:postcode":"L9W 2Z3",
    "sg:province":"ON",
    "sg:tags":[
        "village"
    ],
    "wof:name":"Amaranth Municipal Office",
    "wof:placetype":"venue"
},
  "geometry": {"coordinates":[-80.093491,43.920116],"type":"Point"}
}