{
  "type": "Feature",
  "properties": {
    "addr:full":"55 River St W Moose Jaw SK S6H 1R3",
    "addr:housenumber":"55",
    "addr:postcode":"s6h 1r3",
    "addr:street":"River St W",
    "iso:country":"CA",
    "sg:address":"55 River St W",
    "sg:city":"Moose Jaw",
    "sg:classifiers":[
        {
            "category":"Restaurant",
            "type":"Food & Drink"
        }
    ],
    "sg:phone":"+1 306 692 7827",
    "sg:postcode":"S6H 1R3",
    "sg:province":"SK",
    "wof:name":"Kfc",
    "wof:placetype":"venue"
},
  "geometry": {"coordinates":[-105.53604900000001,50.390495],"type":"Point"}
}