{
  "type": "Feature",
  "properties": {
    "iso:country":"CA",
    "sg:city":"Woodstock",
    "sg:classifiers":[
        {
            "category":"Banks & Credit Unions",
            "subcategory":"Bank",
            "type":"Services"
        }
    ],
    "sg:phone":"+1 506 324 9090",
    "sg:postcode":"E7M 2C8",
    "sg:province":"NB",
    "sg:tags":[
        "loan",
        "real estate"
    ],
    "wof:name":"Consolidated Lending Svc",
    "wof:placetype":"venue"
},
  "geometry": {"coordinates":[-67.5730895996,46.1507301331],"type":"Point"}
}