{
  "type": "Feature",
  "properties": {
    "addr:full":"Campbell River BC V9W 6H5",
    "addr:postcode":"v9w 6h5",
    "iso:country":"CA",
    "sg:city":"Campbell River",
    "sg:classifiers":[
        {
            "category":"Recreation",
            "subcategory":"Arcade",
            "type":"Entertainment"
        }
    ],
    "sg:phone":"+1 250 286 8827",
    "sg:postcode":"V9W 6H5",
    "sg:province":"BC",
    "wof:name":"Funtasia",
    "wof:placetype":"venue"
},
  "geometry": {"coordinates":[-125.25518035899999,50.0274963379],"type":"Point"}
}