{
  "type": "Feature",
  "properties": {
    "addr:full":"5035 49th Ave Mundare AB T0B 3H0",
    "addr:housenumber":"5035",
    "addr:postcode":"t0b 3h0",
    "addr:street":"49Th Ave",
    "iso:country":"CA",
    "sg:address":"5035 49th Ave",
    "sg:city":"Mundare",
    "sg:classifiers":[
        {
            "category":"Wholesale",
            "subcategory":"Machinery & Supplies",
            "type":"Manufacturing & Wholesale Goods"
        }
    ],
    "sg:phone":"+1 780 764 3863",
    "sg:postcode":"T0B 3H0",
    "sg:province":"AB",
    "sg:tags":[
        "farm",
        "equipment"
    ],
    "wof:name":"Mundare Farm Equipment Ltd",
    "wof:placetype":"venue"
},
  "geometry": {"coordinates":[-112.34219400000001,53.592262],"type":"Point"}
}