{
  "type": "Feature",
  "properties": {
    "addr:full":"Bonnyville AB T9N 2J1",
    "addr:postcode":"t9n 2j1",
    "iso:country":"CA",
    "sg:city":"Bonnyville",
    "sg:classifiers":[
        {
            "category":"Manufacturing",
            "subcategory":"Buildings",
            "type":"Manufacturing & Wholesale Goods"
        }
    ],
    "sg:phone":"+1 780 826 2226",
    "sg:postcode":"T9N 2J1",
    "sg:province":"AB",
    "sg:tags":[
        "prefab"
    ],
    "wof:name":"Lakeland Homes Inc",
    "wof:placetype":"venue"
},
  "geometry": {"coordinates":[-110.772888184,54.2674942017],"type":"Point"}
}