{
  "type": "Feature",
  "properties": {
    "addr:full":"61 Duncan Dr St Catharines ON L2N 3P3",
    "addr:housenumber":"61",
    "addr:postcode":"l2n 3p3",
    "addr:street":"Duncan Dr",
    "iso:country":"CA",
    "sg:address":"61 Duncan Dr",
    "sg:city":"St Catharines",
    "sg:classifiers":[
        {
            "category":"Education",
            "subcategory":"School",
            "type":"Public Place"
        }
    ],
    "sg:phone":"+1 905 934 3325",
    "sg:postcode":"L2N 3P3",
    "sg:province":"ON",
    "wof:name":"Dalewood Public School",
    "wof:placetype":"venue"
},
  "geometry": {"coordinates":[-79.23923499999999,43.201111],"type":"Point"}
}