{
  "type": "Feature",
  "properties": {
    "iso:country":"CA",
    "sg:address":"35 Main St E",
    "sg:city":"Grimsby",
    "sg:classifiers":[
        {
            "category":"Sports & Exercise",
            "subcategory":"Gym",
            "type":"Entertainment"
        }
    ],
    "sg:phone":"+1 905 309 6630",
    "sg:postcode":"L3M 1M7",
    "sg:province":"ON",
    "sg:tags":[
        "club",
        "gymnasium",
        "program",
        "health",
        "fitness",
        "studio",
        "physical"
    ],
    "wof:name":"Curves For Women",
    "wof:placetype":"venue"
},
  "geometry": {"coordinates":[-79.559273,43.192341],"type":"Point"}
}