{
  "type": "Feature",
  "properties": {
    "addr:full":"1726 Bank St Ottawa ON K1V 7Y6",
    "addr:housenumber":"1726",
    "addr:postcode":"k1v 7y6",
    "addr:street":"Bank St",
    "iso:country":"CA",
    "sg:address":"1726 Bank St",
    "sg:city":"Ottawa",
    "sg:classifiers":[
        {
            "category":"Building & Trades",
            "subcategory":"Plumbing",
            "type":"Services"
        }
    ],
    "sg:phone":"+1 613 733 2481",
    "sg:postcode":"K1V 7Y6",
    "sg:province":"ON",
    "sg:tags":[
        "conditioning",
        "air",
        "refrigeration",
        "system",
        "contractor"
    ],
    "wof:name":"J C Robinson & Sons Ltd",
    "wof:placetype":"venue"
},
  "geometry": {"coordinates":[-75.66552,45.374325],"type":"Point"}
}