{
  "type": "Feature",
  "properties": {
    "addr:full":"Three Hills AB T0M 2A0",
    "addr:postcode":"t0m 2a0",
    "iso:country":"CA",
    "sg:city":"Three Hills",
    "sg:classifiers":[
        {
            "category":"Retail",
            "subcategory":"Auto Repair",
            "type":"Services"
        }
    ],
    "sg:phone":"+1 403 443 3668",
    "sg:postcode":"T0M 2A0",
    "sg:province":"AB",
    "sg:tags":[
        "truck"
    ],
    "wof:name":"Bigfoot & CO Inc",
    "wof:placetype":"venue"
},
  "geometry": {"coordinates":[-113.24514770499999,51.7071495056],"type":"Point"}
}