{
  "type": "Feature",
  "properties": {
    "iso:country":"CA",
    "sg:address":"207 Hastings St W # 414",
    "sg:city":"Vancouver",
    "sg:classifiers":[
        {
            "category":"Professional",
            "subcategory":"Engineering",
            "type":"Services"
        }
    ],
    "sg:phone":"+1 604 681 6780",
    "sg:postcode":"V6B 1H7",
    "sg:province":"BC",
    "sg:tags":[
        "fire",
        "consultant",
        "protection",
        "engineer"
    ],
    "wof:name":"Pacific Fire Design",
    "wof:placetype":"venue"
},
  "geometry": {"coordinates":[-123.109589,49.282593],"type":"Point"}
}