{
  "type": "Feature",
  "properties": {
    "addr:full":"3472 Walker Rd Windsor ON N8W 3S3",
    "addr:housenumber":"3472",
    "addr:postcode":"n8w 3s3",
    "addr:street":"Walker Rd",
    "iso:country":"CA",
    "sg:address":"3472 Walker Rd",
    "sg:city":"Windsor",
    "sg:classifiers":[
        {
            "category":"Autos & Motor Vehicles",
            "subcategory":"Fuel & Gas Station",
            "type":"Retail Goods"
        }
    ],
    "sg:phone":"+1 519 966 3323",
    "sg:postcode":"N8W 3S3",
    "sg:province":"ON",
    "sg:tags":[
        "oil"
    ],
    "wof:name":"Pioneer Petroleums",
    "wof:placetype":"venue"
},
  "geometry": {"coordinates":[-82.976547,42.274818],"type":"Point"}
}