{
  "type": "Feature",
  "properties": {
    "addr:full":"655 Sydney Ave Windsor ON N8X 5C4",
    "addr:housenumber":"655",
    "addr:postcode":"n8x 5c4",
    "addr:street":"Sydney Ave",
    "iso:country":"CA",
    "sg:address":"655 Sydney Ave",
    "sg:city":"Windsor",
    "sg:classifiers":[
        {
            "category":"Restaurant",
            "type":"Food & Drink"
        }
    ],
    "sg:phone":"+1 519 969 6897",
    "sg:postcode":"N8X 5C4",
    "sg:province":"ON",
    "wof:name":"Harvey's",
    "wof:placetype":"venue"
},
  "geometry": {"coordinates":[-82.99890136720001,42.2723007202],"type":"Point"}
}