{
  "type": "Feature",
  "properties": {
    "addr:full":"10745 124 St NW Edmonton AB T5M 0H2",
    "addr:housenumber":"10745",
    "addr:postcode":"t5m 0h2",
    "addr:street":"124 St Nw",
    "iso:country":"CA",
    "sg:address":"10745 124 St NW",
    "sg:city":"Edmonton",
    "sg:classifiers":[
        {
            "category":"Shopping",
            "subcategory":"Computers & Home Electronics",
            "type":"Retail Goods"
        }
    ],
    "sg:phone":"+1 780 453 6747",
    "sg:postcode":"T5M 0H2",
    "sg:province":"AB",
    "sg:tags":[
        "high",
        "fidelity",
        "stereophonic",
        "system"
    ],
    "wof:name":"Audio Arkitect",
    "wof:placetype":"venue"
},
  "geometry": {"coordinates":[-113.53565999999999,53.551685],"type":"Point"}
}