{
  "type": "Feature",
  "properties": {
    "iso:country":"CA",
    "sg:address":"317314 Hwy 6 & 10",
    "sg:city":"Owen Sound",
    "sg:classifiers":[
        {
            "category":"Food & Beverages",
            "subcategory":"Fruits & Vegetables",
            "type":"Retail Goods"
        }
    ],
    "sg:phone":"+1 519 794 4271",
    "sg:postcode":"N4K 5N6",
    "sg:province":"ON",
    "sg:tags":[
        "produce"
    ],
    "wof:name":"Hill Farms Market",
    "wof:placetype":"venue"
},
  "geometry": {"coordinates":[-80.92417907710001,44.5513916016],"type":"Point"}
}