{
  "type": "Feature",
  "properties": {
    "addr:full":"10843 Hwy 2 Grafton ON K0K 2G0",
    "addr:housenumber":"10843",
    "addr:postcode":"k0k 2g0",
    "addr:street":"Hwy 2",
    "iso:country":"CA",
    "sg:address":"10843 Hwy 2",
    "sg:city":"Grafton",
    "sg:classifiers":[
        {
            "category":"Retail",
            "subcategory":"Auto Repair",
            "type":"Services"
        }
    ],
    "sg:phone":"+1 905 349 2330",
    "sg:postcode":"K0K 2G0",
    "sg:province":"ON",
    "sg:tags":[
        "repairing",
        "automobile"
    ],
    "wof:name":"Glen Prentice Garage",
    "wof:placetype":"venue"
},
  "geometry": {"coordinates":[-78.02430699999999,43.992386],"type":"Point"}
}