{
  "type": "Feature",
  "properties": {
    "iso:country":"CA",
    "sg:address":"1693 Dublin Ave",
    "sg:city":"Winnipeg",
    "sg:classifiers":[
        {
            "category":"Professional",
            "subcategory":"Art Services",
            "type":"Services"
        }
    ],
    "sg:phone":"+1 204 633 2800",
    "sg:postcode":"R3H 0H2",
    "sg:province":"MB",
    "sg:tags":[
        "photographer"
    ],
    "wof:name":"Brian Gould Photography",
    "wof:placetype":"venue"
},
  "geometry": {"coordinates":[-97.20323944090001,49.9117622375],"type":"Point"}
}