{
  "type": "Feature",
  "properties": {
    "addr:full":"3892 Rue Grignon Rock Forest QC J1N 2W1",
    "addr:housenumber":"3892",
    "addr:postcode":"j1n 2w1",
    "addr:street":"Rue Grignon",
    "iso:country":"CA",
    "sg:address":"3892 Rue Grignon",
    "sg:city":"Rock Forest",
    "sg:classifiers":[
        {
            "category":"Building & Trades",
            "subcategory":"Construction",
            "type":"Services"
        }
    ],
    "sg:phone":"+1 819 564 1296",
    "sg:postcode":"J1N 2W1",
    "sg:province":"QC",
    "sg:tags":[
        "excavating",
        "contractor"
    ],
    "wof:name":"Pavage Lavallee & Tanguay Inc",
    "wof:placetype":"venue"
},
  "geometry": {"coordinates":[-71.964027,45.363014],"type":"Point"}
}