{
  "type": "Feature",
  "properties": {
    "addr:full":"18 Arena St Chipman NB E4A 2J2",
    "addr:housenumber":"18",
    "addr:postcode":"e4a 2j2",
    "addr:street":"Arena St",
    "iso:country":"CA",
    "sg:address":"18 Arena St",
    "sg:city":"Chipman",
    "sg:classifiers":[
        {
            "category":"Recreation",
            "type":"Entertainment"
        }
    ],
    "sg:phone":"+1 506 339 6703",
    "sg:postcode":"E4A 2J2",
    "sg:province":"NB",
    "sg:tags":[
        "center"
    ],
    "wof:name":"Chipman Community Ctr",
    "wof:placetype":"venue"
},
  "geometry": {"coordinates":[-65.88073,46.175896],"type":"Point"}
}