{
  "type": "Feature",
  "properties": {
    "iso:country":"CA",
    "sg:address":"12843 County Rd 16",
    "sg:city":"Waubaushene",
    "sg:classifiers":[
        {
            "category":"Autos & Motor Vehicles",
            "subcategory":"Automobile Sales",
            "type":"Retail Goods"
        }
    ],
    "sg:phone":"+1 705 686 7209",
    "sg:postcode":"L0K 2C0",
    "sg:province":"ON",
    "sg:tags":[
        "dealer",
        "boat"
    ],
    "wof:name":"Fesserton Auto & Marine Sales",
    "wof:placetype":"venue"
},
  "geometry": {"coordinates":[-79.710724,44.75412],"type":"Point"}
}