{
  "type": "Feature",
  "properties": {
    "addr:full":"Greenwood BC V0H 1J0",
    "addr:postcode":"v0h 1j0",
    "iso:country":"CA",
    "sg:city":"Greenwood",
    "sg:classifiers":[
        {
            "category":"Organizations",
            "subcategory":"Professional Association",
            "type":"Services"
        }
    ],
    "sg:phone":"+1 250 445 6323",
    "sg:postcode":"V0H 1J0",
    "sg:province":"BC",
    "wof:name":"Greenwood Business Info Ctr",
    "wof:placetype":"venue"
},
  "geometry": {"coordinates":[-118.67617,49.088959],"type":"Point"}
}