{
  "type": "Feature",
  "properties": {
    "addr:full":"6024 Rue DE Bordeaux Montreal QC H2G 2R7",
    "addr:housenumber":"6024",
    "addr:postcode":"h2g 2r7",
    "addr:street":"Rue De Bordeaux",
    "iso:country":"CA",
    "sg:address":"6024 Rue DE Bordeaux",
    "sg:city":"Montreal",
    "sg:classifiers":[
        {
            "category":"Professional",
            "subcategory":"Business Services",
            "type":"Services"
        }
    ],
    "sg:phone":"+1 514 374 3121",
    "sg:postcode":"H2G 2R7",
    "sg:province":"QC",
    "sg:tags":[
        "consultant",
        "estate"
    ],
    "wof:name":"Laliberte & Larocque",
    "wof:placetype":"venue"
},
  "geometry": {"coordinates":[-73.59070587159999,45.5427322388],"type":"Point"}
}