{
  "type": "Feature",
  "properties": {
    "iso:country":"CA",
    "sg:address":"224 Main St",
    "sg:city":"Thessalon",
    "sg:classifiers":[
        {
            "category":"Organizations",
            "subcategory":"Religious Organization",
            "type":"Services"
        }
    ],
    "sg:phone":"+1 705 842 2304",
    "sg:postcode":"P0R 1L0",
    "sg:province":"ON",
    "sg:tags":[
        "church"
    ],
    "wof:name":"Zion United Church",
    "wof:placetype":"venue"
},
  "geometry": {"coordinates":[-83.5564117432,46.2580757141],"type":"Point"}
}