{
  "type": "Feature",
  "properties": {
    "addr:full":"609 7 Ave SW Calgary AB T2P 0Y9",
    "addr:housenumber":"609",
    "addr:postcode":"t2p 0y9",
    "addr:street":"7 Ave Sw",
    "iso:country":"CA",
    "sg:address":"609 7 Ave SW",
    "sg:city":"Calgary",
    "sg:classifiers":[
        {
            "category":"Restaurant",
            "type":"Food & Drink"
        }
    ],
    "sg:phone":"+1 403 264 8973",
    "sg:postcode":"T2P 0Y9",
    "sg:province":"AB",
    "wof:name":"Quincy's on Seventh",
    "wof:placetype":"venue"
},
  "geometry": {"coordinates":[-114.074196,51.04665],"type":"Point"}
}