{
  "type": "Feature",
  "properties": {
    "addr:full":"1625 Rue Bourget Sorel-Tracy QC J3R 4R9",
    "addr:housenumber":"1625",
    "addr:postcode":"j3r 4r9",
    "addr:street":"Rue Bourget",
    "iso:country":"CA",
    "sg:address":"1625 Rue Bourget",
    "sg:city":"Sorel-Tracy",
    "sg:classifiers":[
        {
            "category":"Manufacturing",
            "subcategory":"Tools & Machinery",
            "type":"Manufacturing & Wholesale Goods"
        }
    ],
    "sg:phone":"+1 450 742 3232",
    "sg:postcode":"J3R 4R9",
    "sg:province":"QC",
    "sg:tags":[
        "machine",
        "shop",
        "assembly",
        "fabricating"
    ],
    "wof:name":"Usinage Vincent Inc",
    "wof:placetype":"venue"
},
  "geometry": {"coordinates":[-73.13220200000001,46.03344],"type":"Point"}
}