{
  "type": "Feature",
  "properties": {
    "addr:full":"6368 Yonge St North York ON M2M 3X4",
    "addr:housenumber":"6368",
    "addr:postcode":"m2m 3x4",
    "addr:street":"Yonge St",
    "iso:country":"CA",
    "sg:address":"6368 Yonge St",
    "sg:city":"North York",
    "sg:classifiers":[
        {
            "category":"Shopping",
            "subcategory":"Music",
            "type":"Retail Goods"
        }
    ],
    "sg:phone":"+1 416 739 6505",
    "sg:postcode":"M2M 3X4",
    "sg:province":"ON",
    "sg:tags":[
        "compact",
        "record",
        "disc",
        "tape"
    ],
    "wof:name":"L A Music & Video",
    "wof:placetype":"venue"
},
  "geometry": {"coordinates":[-79.4196472168,43.7956581116],"type":"Point"}
}