{
  "type": "Feature",
  "properties": {
    "addr:full":"10022 Boul Des Hetres Shawinigan QC G9N 4Y4",
    "addr:housenumber":"10022",
    "addr:postcode":"g9n 4y4",
    "addr:street":"Boul Des Hetres",
    "iso:country":"CA",
    "sg:address":"10022 Boul Des Hetres",
    "sg:city":"Shawinigan",
    "sg:classifiers":[
        {
            "category":"Building & Trades",
            "subcategory":"Equipment Rental",
            "type":"Services"
        }
    ],
    "sg:phone":"+1 819 539 8225",
    "sg:postcode":"G9N 4Y4",
    "sg:province":"QC",
    "sg:tags":[
        "moving",
        "supply"
    ],
    "wof:name":"Discount Location D'Autos",
    "wof:placetype":"venue"
},
  "geometry": {"coordinates":[-72.70974,46.597569],"type":"Point"}
}