{
  "type": "Feature",
  "properties": {
    "addr:full":"2200 6E Av Saint-Georges QC G5Y 3X3",
    "addr:housenumber":"2200",
    "addr:postcode":"g5y 3x3",
    "addr:street":"6E Av",
    "iso:country":"CA",
    "sg:address":"2200 6E Av",
    "sg:city":"Saint-Georges",
    "sg:classifiers":[
        {
            "category":"Health Services",
            "subcategory":"Health Practitioner",
            "type":"Services"
        }
    ],
    "sg:phone":"+1 418 228 2024",
    "sg:postcode":"G5Y 3X3",
    "sg:province":"QC",
    "sg:tags":[
        "psychologist"
    ],
    "wof:name":"Lepage, Monique PhD",
    "wof:placetype":"venue"
},
  "geometry": {"coordinates":[-70.67115,46.123348],"type":"Point"}
}