{
  "type": "Feature",
  "properties": {
    "addr:full":"104 Rue Dupont Pont-Rouge QC G3H 1M6",
    "addr:housenumber":"104",
    "addr:postcode":"g3h 1m6",
    "addr:street":"Rue Dupont",
    "iso:country":"CA",
    "sg:address":"104 Rue Dupont",
    "sg:city":"Pont-Rouge",
    "sg:classifiers":[
        {
            "category":"Food & Beverages",
            "subcategory":"Groceries & Convenience Stores",
            "type":"Retail Goods"
        }
    ],
    "sg:phone":"+1 418 873 2149",
    "sg:postcode":"G3H 1M6",
    "sg:province":"QC",
    "sg:tags":[
        "grocer"
    ],
    "wof:name":"Depanneur Yves Enr",
    "wof:placetype":"venue"
},
  "geometry": {"coordinates":[-71.6885757446,46.7567176819],"type":"Point"}
}