{
  "type": "Feature",
  "properties": {
    "iso:country":"CA",
    "sg:city":"Dollard-Des-Ormeaux",
    "sg:classifiers":[
        {
            "category":"Wholesale",
            "subcategory":"Electrical",
            "type":"Manufacturing & Wholesale Goods"
        }
    ],
    "sg:phone":"+1 514 684 7444",
    "sg:postcode":"H9B 2J5",
    "sg:province":"QC",
    "sg:tags":[
        "lighting",
        "fixture"
    ],
    "wof:name":"Condaz Lighting Inc",
    "wof:placetype":"venue"
},
  "geometry": {"coordinates":[-73.811935,45.476677],"type":"Point"}
}