{
  "type": "Feature",
  "properties": {
    "addr:full":"203 Scott St Kennedy SK S0G 2R0",
    "addr:housenumber":"203",
    "addr:postcode":"s0g 2r0",
    "addr:street":"Scott St Kennedy",
    "iso:country":"CA",
    "sg:address":"203 Scott St",
    "sg:city":"Kennedy",
    "sg:classifiers":[
        {
            "category":"Mining & Drilling",
            "type":"Manufacturing & Wholesale Goods"
        }
    ],
    "sg:phone":"+1 306 538 4487",
    "sg:postcode":"S0G 2R0",
    "sg:province":"SK",
    "sg:tags":[
        "oil",
        "well",
        "steam",
        "cleaning"
    ],
    "wof:name":"Parkside Oilfield Svc Ltd",
    "wof:placetype":"venue"
},
  "geometry": {"coordinates":[-102.351006,50.01807],"type":"Point"}
}