{
  "type": "Feature",
  "properties": {
    "addr:full":"176 Foxwarren Dr Winnipeg MB R2P 2X4",
    "addr:housenumber":"176",
    "addr:postcode":"r2p 2x4",
    "addr:street":"Foxwarren Dr",
    "iso:country":"CA",
    "sg:address":"176 Foxwarren Dr",
    "sg:city":"Winnipeg",
    "sg:classifiers":[
        {
            "category":"Building & Trades",
            "subcategory":"Construction",
            "type":"Services"
        }
    ],
    "sg:phone":"+1 204 697 2808",
    "sg:postcode":"R2P 2X4",
    "sg:province":"MB",
    "sg:tags":[
        "home",
        "builder"
    ],
    "wof:name":"Randall Homes",
    "wof:placetype":"venue"
},
  "geometry": {"coordinates":[-97.1925811768,49.9661369324],"type":"Point"}
}