{
  "type": "Feature",
  "properties": {
    "addr:full":"2383 Guildford Town Ctr Surrey BC V3R 7B9",
    "addr:housenumber":"2383",
    "addr:postcode":"v3r 7b9",
    "addr:street":"Guildford Town Ctr",
    "iso:country":"CA",
    "sg:address":"2383 Guildford Town Ctr",
    "sg:city":"Surrey",
    "sg:classifiers":[
        {
            "category":"Shopping",
            "subcategory":"Shoes",
            "type":"Retail Goods"
        }
    ],
    "sg:phone":"+1 604 585 3411",
    "sg:postcode":"V3R 7B9",
    "sg:province":"BC",
    "wof:name":"Sterling Shoes",
    "wof:placetype":"venue"
},
  "geometry": {"coordinates":[-122.804024,49.187981],"type":"Point"}
}