{
  "type": "Feature",
  "properties": {
    "addr:full":"153 Kenogami Dr Longlac ON P0T 2A0",
    "addr:housenumber":"153",
    "addr:postcode":"p0t 2a0",
    "addr:street":"Kenogami Dr",
    "iso:country":"CA",
    "sg:address":"153 Kenogami Dr",
    "sg:city":"Longlac",
    "sg:classifiers":[
        {
            "category":"Social Services",
            "subcategory":"Child Care",
            "type":"Services"
        }
    ],
    "sg:phone":"+1 807 876 4675",
    "sg:postcode":"P0T 2A0",
    "sg:province":"ON",
    "sg:tags":[
        "government"
    ],
    "wof:name":"Longlac Day Care Ctr",
    "wof:placetype":"venue"
},
  "geometry": {"coordinates":[-86.53894805909999,49.7771835327],"type":"Point"}
}