{
  "type": "Feature",
  "properties": {
    "iso:country":"CA",
    "sg:address":"115 Carnarvon St",
    "sg:city":"York",
    "sg:classifiers":[
        {
            "category":"Manufacturing",
            "subcategory":"Printing",
            "type":"Manufacturing & Wholesale Goods"
        }
    ],
    "sg:phone":"+1 416 656 9446",
    "sg:postcode":"M6M 3C9",
    "sg:province":"ON",
    "sg:tags":[
        "printer"
    ],
    "wof:name":"Express Graphics",
    "wof:placetype":"venue"
},
  "geometry": {"coordinates":[-79.46631622309999,43.6946144104],"type":"Point"}
}