{
  "type": "Feature",
  "properties": {
    "addr:full":"140 Highland Rd W # 9 Kitchener ON N2M 3B8",
    "addr:housenumber":"140",
    "addr:postcode":"n2m 3b8",
    "addr:street":"Highland Rd W # 9",
    "iso:country":"CA",
    "sg:address":"140 Highland Rd W # 9",
    "sg:city":"Kitchener",
    "sg:classifiers":[
        {
            "category":"Real Estate",
            "subcategory":"Real Estate Agent",
            "type":"Services"
        }
    ],
    "sg:phone":"+1 519 570 6299",
    "sg:postcode":"N2M 3B8",
    "sg:province":"ON",
    "wof:name":"Reitzel, Jeff",
    "wof:placetype":"venue"
},
  "geometry": {"coordinates":[-80.503563,43.44109],"type":"Point"}
}