{
  "type": "Feature",
  "properties": {
    "addr:full":"1518 Mercer St Windsor ON N8X 3P5",
    "addr:housenumber":"1518",
    "addr:postcode":"n8x 3p5",
    "addr:street":"Mercer St",
    "iso:country":"CA",
    "sg:address":"1518 Mercer St",
    "sg:city":"Windsor",
    "sg:classifiers":[
        {
            "category":"Freight",
            "type":"Transportation"
        }
    ],
    "sg:phone":"+1 519 252 2653",
    "sg:postcode":"N8X 3P5",
    "sg:province":"ON",
    "sg:tags":[
        "warehouse",
        "storage"
    ],
    "wof:name":"Windsor Freezer Svc Ltd",
    "wof:placetype":"venue"
},
  "geometry": {"coordinates":[-83.021828,42.301876],"type":"Point"}
}