{
  "type": "Feature",
  "properties": {
    "iso:country":"CA",
    "sg:address":"235 Stafford Rd W",
    "sg:city":"Nepean",
    "sg:classifiers":[
        {
            "category":"Manufacturing",
            "subcategory":"Electronics",
            "type":"Manufacturing & Wholesale Goods"
        }
    ],
    "sg:phone":"+1 613 596 4244",
    "sg:postcode":"K2H 9C1",
    "sg:province":"ON",
    "sg:tags":[
        "printed",
        "circuit",
        "etched"
    ],
    "wof:name":"Pwb Interconnect Solutions",
    "wof:placetype":"venue"
},
  "geometry": {"coordinates":[-75.8338394165,45.3258972168],"type":"Point"}
}