{
  "type": "Feature",
  "properties": {
    "addr:full":"4625 40A St St Paul AB T0A 3A2",
    "addr:housenumber":"4625",
    "addr:postcode":"t0a 3a2",
    "addr:street":"40A St",
    "iso:country":"CA",
    "sg:address":"4625 40A St",
    "sg:city":"St Paul",
    "sg:classifiers":[
        {
            "category":"Building & Trades",
            "subcategory":"Plumbing",
            "type":"Services"
        }
    ],
    "sg:phone":"+1 780 645 3592",
    "sg:postcode":"T0A 3A2",
    "sg:province":"AB",
    "sg:tags":[
        "refrigeration",
        "refrigerating",
        "contractor"
    ],
    "wof:name":"Wally's Refrig & Appl Repair",
    "wof:placetype":"venue"
},
  "geometry": {"coordinates":[-111.268013,53.987854],"type":"Point"}
}