{
  "type": "Feature",
  "properties": {
    "addr:full":"15530 111 Ave NW Edmonton AB T5M 2R4",
    "addr:housenumber":"15530",
    "addr:postcode":"t5m 2r4",
    "addr:street":"111 Ave Nw",
    "iso:country":"CA",
    "sg:address":"15530 111 Ave NW",
    "sg:city":"Edmonton",
    "sg:classifiers":[
        {
            "category":"Retail",
            "subcategory":"Auto Repair",
            "type":"Services"
        }
    ],
    "sg:phone":"+1 780 453 6299",
    "sg:postcode":"T5M 2R4",
    "sg:province":"AB",
    "sg:tags":[
        "automobile",
        "lubrication"
    ],
    "wof:name":"Lube City",
    "wof:placetype":"venue"
},
  "geometry": {"coordinates":[-113.588455,53.559196],"type":"Point"}
}