{
  "type": "Feature",
  "properties": {
    "iso:country":"CA",
    "sg:address":"423 Glendale Ave",
    "sg:city":"St Catharines",
    "sg:classifiers":[
        {
            "category":"Manufacturing",
            "subcategory":"Tools & Machinery",
            "type":"Manufacturing & Wholesale Goods"
        }
    ],
    "sg:phone":"+1 905 227 5233",
    "sg:postcode":"L2P 3Y1",
    "sg:province":"ON",
    "sg:tags":[
        "machine",
        "shop"
    ],
    "wof:name":"Clark Machine CO Ltd",
    "wof:placetype":"venue"
},
  "geometry": {"coordinates":[-79.20449829099999,43.1407279968],"type":"Point"}
}