{
  "type": "Feature",
  "properties": {
    "addr:full":"Toronto ON M4S 3B1",
    "addr:postcode":"m4s 3b1",
    "iso:country":"CA",
    "sg:city":"Toronto",
    "sg:classifiers":[
        {
            "category":"Freight",
            "type":"Transportation"
        }
    ],
    "sg:phone":"+1 416 486 3476",
    "sg:postcode":"M4S 3B1",
    "sg:province":"ON",
    "sg:tags":[
        "trucking"
    ],
    "wof:name":"Firm Transportation & Distr",
    "wof:placetype":"venue"
},
  "geometry": {"coordinates":[-79.39634700000001,43.705303],"type":"Point"}
}