{
  "type": "Feature",
  "properties": {
    "addr:full":"Grande Prairie AB T8V 3Y2",
    "addr:postcode":"t8v 3y2",
    "iso:country":"CA",
    "sg:city":"Grande Prairie",
    "sg:classifiers":[
        {
            "category":"Shopping",
            "subcategory":"Shoes",
            "type":"Retail Goods"
        }
    ],
    "sg:phone":"+1 780 532 6933",
    "sg:postcode":"T8V 3Y2",
    "sg:province":"AB",
    "wof:name":"Sterling Shoes Inc",
    "wof:placetype":"venue"
},
  "geometry": {"coordinates":[-118.794456482,55.1868743896],"type":"Point"}
}