{
  "type": "Feature",
  "properties": {
    "iso:country":"CA",
    "sg:city":"Ottawa",
    "sg:classifiers":[
        {
            "category":"Building & Trades",
            "subcategory":"Construction",
            "type":"Services"
        }
    ],
    "sg:phone":"+1 613 733 9220",
    "sg:postcode":"K1V 1A4",
    "sg:province":"ON",
    "sg:tags":[
        "paint",
        "resurfacing",
        "laying",
        "refinishing",
        "floor"
    ],
    "wof:name":"Decorators Choice Paint Store",
    "wof:placetype":"venue"
},
  "geometry": {"coordinates":[-75.646492,45.353493],"type":"Point"}
}