{
  "type": "Feature",
  "properties": {
    "addr:full":"RR 3 Thamesville ON N0P 2K0",
    "addr:postcode":"n0p 2k0",
    "addr:street":"Rr 3",
    "iso:country":"CA",
    "sg:address":"RR 3",
    "sg:city":"Thamesville",
    "sg:classifiers":[
        {
            "category":"Building & Trades",
            "subcategory":"Construction",
            "type":"Services"
        }
    ],
    "sg:phone":"+1 519 692 9141",
    "sg:postcode":"N0P 2K0",
    "sg:province":"ON",
    "sg:tags":[
        "refinishing",
        "floor",
        "laying",
        "general",
        "resurfacing",
        "contractor"
    ],
    "wof:name":"Taylor Made Carpentry",
    "wof:placetype":"venue"
},
  "geometry": {"coordinates":[-81.976501,42.551853],"type":"Point"}
}