{
  "type": "Feature",
  "properties": {
    "addr:full":"9 Newfoundland Dr Carbonear NL A1Y 1A4",
    "addr:housenumber":"9",
    "addr:postcode":"a1y 1a4",
    "addr:street":"Newfoundland Dr",
    "iso:country":"CA",
    "sg:address":"9 Newfoundland Dr",
    "sg:city":"Carbonear",
    "sg:classifiers":[
        {
            "category":"Social Services",
            "type":"Services"
        }
    ],
    "sg:phone":"+1 709 596 0712",
    "sg:postcode":"A1Y 1A4",
    "sg:province":"NL",
    "sg:tags":[
        "organization",
        "welfare",
        "care",
        "child"
    ],
    "wof:name":"Trinity Conception Family Ctr",
    "wof:placetype":"venue"
},
  "geometry": {"coordinates":[-53.2295,47.736382],"type":"Point"}
}