{
  "type": "Feature",
  "properties": {
    "iso:country":"CA",
    "sg:city":"Quebec",
    "sg:classifiers":[
        {
            "category":"Professional",
            "subcategory":"Accounting & Tax Preparation",
            "type":"Services"
        }
    ],
    "sg:phone":"+1 418 627 3666",
    "sg:postcode":"G2J 1C2",
    "sg:province":"QC",
    "sg:tags":[
        "accountant"
    ],
    "wof:name":"Girard Lavoie Mooney",
    "wof:placetype":"venue"
},
  "geometry": {"coordinates":[-71.273109436,46.8340415955],"type":"Point"}
}