{
  "type": "Feature",
  "properties": {
    "addr:full":"45 Grist Mill Rd Holland Landing ON L9N 1M7",
    "addr:housenumber":"45",
    "addr:postcode":"l9n 1m7",
    "addr:street":"Grist Mill Rd",
    "iso:country":"CA",
    "sg:address":"45 Grist Mill Rd",
    "sg:city":"Holland Landing",
    "sg:classifiers":[
        {
            "category":"Arena",
            "subcategory":"Sports Club",
            "type":"Entertainment"
        }
    ],
    "sg:phone":"+1 905 898 7278",
    "sg:postcode":"L9N 1M7",
    "sg:province":"ON",
    "sg:tags":[
        "soccer"
    ],
    "wof:name":"East Gwillimbury Soccer Club",
    "wof:placetype":"venue"
},
  "geometry": {"coordinates":[-79.4739151001,44.0980567932],"type":"Point"}
}