{
  "type": "Feature",
  "properties": {
    "addr:full":"9350 Boul Lacordaire Saint-Leonard QC H1R 2B7",
    "addr:housenumber":"9350",
    "addr:postcode":"h1r 2b7",
    "addr:street":"Boul Lacordaire",
    "iso:country":"CA",
    "sg:address":"9350 Boul Lacordaire",
    "sg:city":"Saint-Leonard",
    "sg:classifiers":[
        {
            "category":"Restaurant",
            "type":"Food & Drink"
        }
    ],
    "sg:phone":"+1 514 323 8764",
    "sg:postcode":"H1R 2B7",
    "sg:province":"QC",
    "sg:tags":[
        "delicatessen"
    ],
    "wof:name":"Maison Du Parmesan",
    "wof:placetype":"venue"
},
  "geometry": {"coordinates":[-73.6112442017,45.5979309082],"type":"Point"}
}