{
  "type": "Feature",
  "properties": {
    "addr:full":"236 E Main St Welland ON L3B 3W9",
    "addr:housenumber":"236",
    "addr:postcode":"l3b 3w9",
    "addr:street":"E Main St",
    "iso:country":"CA",
    "sg:address":"236 E Main St",
    "sg:city":"Welland",
    "sg:classifiers":[
        {
            "category":"Food & Beverages",
            "subcategory":"Groceries & Convenience Stores",
            "type":"Retail Goods"
        }
    ],
    "sg:phone":"+1 905 735 4515",
    "sg:postcode":"L3B 3W9",
    "sg:province":"ON",
    "sg:tags":[
        "grocer"
    ],
    "wof:name":"Welland Food Mart",
    "wof:placetype":"venue"
},
  "geometry": {"coordinates":[-79.243584,42.993122],"type":"Point"}
}