{
  "type": "Feature",
  "properties": {
    "iso:country":"CA",
    "sg:address":"63 201 Rte",
    "sg:city":"Coteau-Du-Lac",
    "sg:classifiers":[
        {
            "category":"Travel",
            "subcategory":"Hotels & Motels",
            "type":"Entertainment"
        }
    ],
    "sg:phone":"+1 450 763 5721",
    "sg:postcode":"J0P 1B0",
    "sg:province":"QC",
    "wof:name":"Wilsonvale Hotel",
    "wof:placetype":"venue"
},
  "geometry": {"coordinates":[-74.177017,45.296982],"type":"Point"}
}