{
  "type": "Feature",
  "properties": {
    "iso:country":"CA",
    "sg:city":"Hamilton",
    "sg:classifiers":[
        {
            "category":"Health Services",
            "subcategory":"Doctor",
            "type":"Services"
        }
    ],
    "sg:phone":"+1 905 383 8338",
    "sg:postcode":"L8T 1R9",
    "sg:province":"ON",
    "sg:tags":[
        "dentist"
    ],
    "wof:name":"DE Stephanis, Jerry DDS",
    "wof:placetype":"venue"
},
  "geometry": {"coordinates":[-79.8304901123,43.2256660461],"type":"Point"}
}