{
  "type": "Feature",
  "properties": {
    "addr:full":"Verdun QC H3E 1J4",
    "addr:postcode":"h3e 1j4",
    "iso:country":"CA",
    "sg:city":"Verdun",
    "sg:classifiers":[
        {
            "category":"Insurance",
            "subcategory":"Insurance Agent",
            "type":"Services"
        }
    ],
    "sg:phone":"+1 514 761 5831",
    "sg:postcode":"H3E 1J4",
    "sg:province":"QC",
    "wof:name":"Desjardins Menard & Assoc Ltee",
    "wof:placetype":"venue"
},
  "geometry": {"coordinates":[-73.57176200000001,45.459019],"type":"Point"}
}