{
  "type": "Feature",
  "properties": {
    "iso:country":"CA",
    "sg:city":"Mississauga",
    "sg:classifiers":[
        {
            "category":"Retail",
            "subcategory":"Veterinary Services",
            "type":"Services"
        }
    ],
    "sg:phone":"+1 905 501 1514",
    "sg:postcode":"L5R 3V6",
    "sg:province":"ON",
    "sg:tags":[
        "veterinarian"
    ],
    "wof:name":"Terry, Gwen DVM",
    "wof:placetype":"venue"
},
  "geometry": {"coordinates":[-79.6896896362,43.6132774353],"type":"Point"}
}