{
  "type": "Feature",
  "properties": {
    "addr:full":"1994 Stevensville Rd Stevensville ON L0S 1S0",
    "addr:housenumber":"1994",
    "addr:postcode":"l0s 1s0",
    "addr:street":"Stevensville Rd",
    "iso:country":"CA",
    "sg:address":"1994 Stevensville Rd",
    "sg:city":"Stevensville",
    "sg:classifiers":[
        {
            "category":"Building & Trades",
            "subcategory":"Construction",
            "type":"Services"
        }
    ],
    "sg:phone":"+1 905 382 2464",
    "sg:postcode":"L0S 1S0",
    "sg:province":"ON",
    "sg:tags":[
        "paving",
        "contractor"
    ],
    "wof:name":"Circle P Paving Ltd",
    "wof:placetype":"venue"
},
  "geometry": {"coordinates":[-79.05441999999999,42.933151],"type":"Point"}
}