{
  "type": "Feature",
  "properties": {
    "addr:full":"390 North Front St Belleville ON K8P 3E1",
    "addr:housenumber":"390",
    "addr:postcode":"k8p 3e1",
    "addr:street":"North Front St",
    "iso:country":"CA",
    "sg:address":"390 North Front St",
    "sg:city":"Belleville",
    "sg:classifiers":[
        {
            "category":"Shopping",
            "subcategory":"Clothing, Apparel, & Fashions",
            "type":"Retail Goods"
        }
    ],
    "sg:phone":"+1 613 968 2725",
    "sg:postcode":"K8P 3E1",
    "sg:province":"ON",
    "sg:tags":[
        "infant",
        "wear"
    ],
    "wof:name":"Northern Getaway",
    "wof:placetype":"venue"
},
  "geometry": {"coordinates":[-77.396591,44.1884],"type":"Point"}
}