{
  "type": "Feature",
  "properties": {
    "addr:full":"Parksville BC V9P 2N4",
    "addr:postcode":"v9p 2n4",
    "iso:country":"CA",
    "sg:city":"Parksville",
    "sg:classifiers":[
        {
            "category":"Utilities",
            "subcategory":"Water",
            "type":"Services"
        }
    ],
    "sg:phone":"+1 250 248 8921",
    "sg:postcode":"V9P 2N4",
    "sg:province":"BC",
    "sg:tags":[
        "system",
        "supply"
    ],
    "wof:name":"Breakwater Enterprises Ltd",
    "wof:placetype":"venue"
},
  "geometry": {"coordinates":[-124.301186,49.315826],"type":"Point"}
}