{
  "type": "Feature",
  "properties": {
    "addr:full":"Lyster QC G0S 1V0",
    "addr:postcode":"g0s 1v0",
    "iso:country":"CA",
    "sg:city":"Lyster",
    "sg:classifiers":[
        {
            "category":"Manufacturing",
            "subcategory":"Tools & Machinery",
            "type":"Manufacturing & Wholesale Goods"
        }
    ],
    "sg:phone":"+1 819 389 2267",
    "sg:postcode":"G0S 1V0",
    "sg:province":"QC",
    "sg:tags":[
        "machine",
        "shop"
    ],
    "wof:name":"Big Tech Atelier D'Usinage",
    "wof:placetype":"venue"
},
  "geometry": {"coordinates":[-71.617638,46.371429],"type":"Point"}
}