{
  "type": "Feature",
  "properties": {
    "addr:full":"St-Francois-Montmagny QC G0R 3A0",
    "addr:postcode":"g0r 3a0",
    "iso:country":"CA",
    "sg:city":"St-Francois-Montmagny",
    "sg:classifiers":[
        {
            "category":"Health Services",
            "subcategory":"Doctor",
            "type":"Services"
        }
    ],
    "sg:phone":"+1 418 259 7317",
    "sg:postcode":"G0R 3A0",
    "sg:province":"QC",
    "sg:tags":[
        "physician",
        "surgeon"
    ],
    "wof:name":"Morin, Simon MD",
    "wof:placetype":"venue"
},
  "geometry": {"coordinates":[-70.715996,46.88559],"type":"Point"}
}