{
  "type": "Feature",
  "properties": {
    "addr:full":"1723 Hollis St Halifax NS B3J 1V9",
    "addr:housenumber":"1723",
    "addr:postcode":"ns b3j 1v9",
    "addr:street":"Hollis St",
    "iso:country":"CA",
    "sg:address":"1723 Hollis St",
    "sg:city":"Halifax",
    "sg:classifiers":[
        {
            "category":"Restaurant",
            "type":"Food & Drink"
        }
    ],
    "sg:phone":"+1 902 425 4494",
    "sg:postcode":"B3J 1V9",
    "sg:province":"NS",
    "wof:name":"Cheapside Cafe",
    "wof:placetype":"venue"
},
  "geometry": {"coordinates":[-63.5727577209,44.6478385925],"type":"Point"}
}