{
  "type": "Feature",
  "properties": {
    "addr:full":"2 Park Ave E Elmira ON N3B 2G8",
    "addr:housenumber":"2",
    "addr:postcode":"n3b 2g8",
    "addr:street":"Park Ave E",
    "iso:country":"CA",
    "sg:address":"2 Park Ave E",
    "sg:city":"Elmira",
    "sg:classifiers":[
        {
            "category":"Health Services",
            "subcategory":"Optometrist",
            "type":"Services"
        }
    ],
    "sg:phone":"+1 519 669 5546",
    "sg:postcode":"N3B 2G8",
    "sg:province":"ON",
    "wof:name":"Karidas, Anne OD",
    "wof:placetype":"venue"
},
  "geometry": {"coordinates":[-80.559235,43.597031],"type":"Point"}
}