{
  "type": "Feature",
  "properties": {
    "iso:country":"CA",
    "sg:city":"Toronto",
    "sg:classifiers":[
        {
            "category":"Food & Beverages",
            "subcategory":"Groceries & Convenience Stores",
            "type":"Retail Goods"
        }
    ],
    "sg:phone":"+1 416 928 1728",
    "sg:postcode":"M5T 3A9",
    "sg:province":"ON",
    "wof:name":"Starbank Convenience",
    "wof:placetype":"venue"
},
  "geometry": {"coordinates":[-79.40334320069999,43.6574478149],"type":"Point"}
}