{
  "type": "Feature",
  "properties": {
    "addr:full":"Strathmore AB T1P 1K3",
    "addr:postcode":"t1p 1k3",
    "iso:country":"CA",
    "sg:city":"Strathmore",
    "sg:classifiers":[
        {
            "category":"Professional",
            "subcategory":"Lawyer & Legal Services",
            "type":"Services"
        }
    ],
    "sg:phone":"+1 403 934 2500",
    "sg:postcode":"T1P 1K3",
    "sg:province":"AB",
    "sg:tags":[
        "attorney"
    ],
    "wof:name":"Hallett, Donna M",
    "wof:placetype":"venue"
},
  "geometry": {"coordinates":[-113.40007782000001,51.0417137146],"type":"Point"}
}