{
  "type": "Feature",
  "properties": {
    "iso:country":"CA",
    "sg:city":"Trois-Rivieres",
    "sg:classifiers":[
        {
            "category":"Restaurant",
            "type":"Food & Drink"
        }
    ],
    "sg:phone":"+1 819 378 2121",
    "sg:postcode":"G8Y 5N9",
    "sg:province":"QC",
    "wof:name":"Restaurant Orientales Inc",
    "wof:placetype":"venue"
},
  "geometry": {"coordinates":[-72.588509,46.358204],"type":"Point"}
}