{
  "type": "Feature",
  "properties": {
    "addr:full":"Hwy 59 Valhalla Centre AB T0H 3M0",
    "addr:postcode":"t0h 3m0",
    "addr:street":"Hwy 59 Valhalla",
    "iso:country":"CA",
    "sg:address":"Hwy 59",
    "sg:city":"Valhalla Centre",
    "sg:classifiers":[
        {
            "category":"Education",
            "subcategory":"Library",
            "type":"Public Place"
        }
    ],
    "sg:phone":"+1 780 356 3834",
    "sg:postcode":"T0H 3M0",
    "sg:province":"AB",
    "wof:name":"Valhalla Community Library",
    "wof:placetype":"venue"
},
  "geometry": {"coordinates":[-119.384697,55.392445],"type":"Point"}
}