{
  "type": "Feature",
  "properties": {
    "addr:full":"2006 Ridge Road W Shanty Bay ON L0L 2L0",
    "addr:housenumber":"2006",
    "addr:postcode":"l0l 2l0",
    "addr:street":"Ridge Road W Shanty",
    "iso:country":"CA",
    "sg:address":"2006 Ridge Road W",
    "sg:city":"Shanty Bay",
    "sg:classifiers":[
        {
            "category":"Building & Trades",
            "subcategory":"Plumbing",
            "type":"Services"
        }
    ],
    "sg:phone":"+1 705 722 6900",
    "sg:postcode":"L0L 2L0",
    "sg:province":"ON",
    "sg:tags":[
        "contractor"
    ],
    "wof:name":"Ron Young Plumbing & Heating",
    "wof:placetype":"venue"
},
  "geometry": {"coordinates":[-79.58187100000001,44.413078],"type":"Point"}
}