{
  "type": "Feature",
  "properties": {
    "addr:full":"PO Box 3588 STN D Edmonton AB T5L 4J6",
    "addr:housenumber":"po",
    "addr:postcode":"3588;t5l 4j6",
    "addr:street":"Box",
    "iso:country":"CA",
    "sg:address":"PO Box 3588 STN D",
    "sg:city":"Edmonton",
    "sg:classifiers":[
        {
            "category":"Manufacturing",
            "subcategory":"Signs",
            "type":"Manufacturing & Wholesale Goods"
        }
    ],
    "sg:phone":"+1 780 455 8541",
    "sg:postcode":"T5L 4J6",
    "sg:province":"AB",
    "wof:name":"Yellowhead Signs & Spec Ltd",
    "wof:placetype":"venue"
},
  "geometry": {"coordinates":[-113.49037199999999,53.546219],"type":"Point"}
}