{
  "type": "Feature",
  "properties": {
    "addr:full":"47 Av Marcoux Roberval QC G8H 1E8",
    "addr:postcode":"g8h 1e8",
    "addr:street":"47 Av Marcoux",
    "iso:country":"CA",
    "sg:address":"47 Av Marcoux",
    "sg:city":"Roberval",
    "sg:classifiers":[
        {
            "category":"Professional",
            "subcategory":"Business Services",
            "type":"Services"
        }
    ],
    "sg:phone":"+1 418 275 5301",
    "sg:postcode":"G8H 1E8",
    "sg:province":"QC",
    "sg:tags":[
        "notary"
    ],
    "wof:name":"Godin, Francoise",
    "wof:placetype":"venue"
},
  "geometry": {"coordinates":[-72.22112300000001,48.512714],"type":"Point"}
}