{
  "type": "Feature",
  "properties": {
    "addr:full":"Prince George BC V2L 1W6",
    "addr:postcode":"v2l 1w6",
    "iso:country":"CA",
    "sg:city":"Prince George",
    "sg:classifiers":[
        {
            "category":"Professional",
            "subcategory":"Accounting & Tax Preparation",
            "type":"Services"
        }
    ],
    "sg:phone":"+1 250 564 8602",
    "sg:postcode":"V2L 1W6",
    "sg:province":"BC",
    "sg:tags":[
        "consultant"
    ],
    "wof:name":"Tax Break",
    "wof:placetype":"venue"
},
  "geometry": {"coordinates":[-122.747917175,53.9149742126],"type":"Point"}
}