{
  "type": "Feature",
  "properties": {
    "iso:country":"CA",
    "sg:address":"91 Rue Laval",
    "sg:city":"Hull",
    "sg:classifiers":[
        {
            "category":"Professional",
            "subcategory":"Business Services",
            "type":"Services"
        }
    ],
    "sg:phone":"+1 819 777 8567",
    "sg:postcode":"J8X 3H4",
    "sg:province":"QC",
    "sg:tags":[
        "photo",
        "finishing"
    ],
    "wof:name":"Centre DE LA Diapo DE Inc",
    "wof:placetype":"venue"
},
  "geometry": {"coordinates":[-75.716164,45.428543],"type":"Point"}
}