{
  "type": "Feature",
  "properties": {
    "addr:full":"10249 Av Christophe-Colomb Montreal QC H2C 2T8",
    "addr:housenumber":"10249",
    "addr:postcode":"h2c 2t8",
    "addr:street":"Av Christophe-Colomb",
    "iso:country":"CA",
    "sg:address":"10249 Av Christophe-Colomb",
    "sg:city":"Montreal",
    "sg:classifiers":[
        {
            "category":"Social Services",
            "type":"Services"
        }
    ],
    "sg:phone":"+1 514 394 0041",
    "sg:postcode":"H2C 2T8",
    "sg:province":"QC",
    "sg:tags":[
        "organization",
        "welfare"
    ],
    "wof:name":"L'Arret-Source Inc",
    "wof:placetype":"venue"
},
  "geometry": {"coordinates":[-73.65650177000001,45.5610580444],"type":"Point"}
}