{
  "type": "Feature",
  "properties": {
    "addr:full":"7219 2nd St Grand Forks BC V0H 1H2",
    "addr:housenumber":"7219",
    "addr:postcode":"v0h 1h2",
    "addr:street":"2Nd St",
    "iso:country":"CA",
    "sg:address":"7219 2nd St",
    "sg:city":"Grand Forks",
    "sg:classifiers":[
        {
            "category":"Personal",
            "subcategory":"Beauty Salon",
            "type":"Services"
        }
    ],
    "sg:phone":"+1 250 442 8990",
    "sg:postcode":"V0H 1H2",
    "sg:province":"BC",
    "wof:name":"Hairworx Studio",
    "wof:placetype":"venue"
},
  "geometry": {"coordinates":[-118.437057495,49.0327301025],"type":"Point"}
}