{
  "type": "Feature",
  "properties": {
    "iso:country":"CA",
    "sg:city":"Burnaby",
    "sg:classifiers":[
        {
            "category":"Autos & Motor Vehicles",
            "subcategory":"Automobile Sales",
            "type":"Retail Goods"
        }
    ],
    "sg:phone":"+1 604 294 1944",
    "sg:postcode":"V5B 1R8",
    "sg:province":"BC",
    "sg:tags":[
        "car",
        "dealer"
    ],
    "wof:name":"G & M Auto Sales",
    "wof:placetype":"venue"
},
  "geometry": {"coordinates":[-122.97567,49.280445],"type":"Point"}
}