{
  "type": "Feature",
  "properties": {
    "addr:full":"811 Rue Notre Dame Berthierville QC J0K 1A0",
    "addr:housenumber":"811",
    "addr:postcode":"j0k 1a0",
    "addr:street":"Rue Notre Dame",
    "iso:country":"CA",
    "sg:address":"811 Rue Notre Dame",
    "sg:city":"Berthierville",
    "sg:classifiers":[
        {
            "category":"Retail",
            "subcategory":"Auto Repair",
            "type":"Services"
        }
    ],
    "sg:phone":"+1 450 836 2334",
    "sg:postcode":"J0K 1A0",
    "sg:province":"QC",
    "sg:tags":[
        "repairing",
        "automobile"
    ],
    "wof:name":"Centre Mecanique Jb",
    "wof:placetype":"venue"
},
  "geometry": {"coordinates":[-73.185028,46.083076],"type":"Point"}
}