{
  "type": "Feature",
  "properties": {
    "iso:country":"CA",
    "sg:city":"Montreal",
    "sg:classifiers":[
        {
            "category":"Shopping",
            "subcategory":"Clothing, Apparel, & Fashions",
            "type":"Retail Goods"
        }
    ],
    "sg:phone":"+1 514 844 4366",
    "sg:postcode":"H3B 1H9",
    "sg:province":"QC",
    "sg:tags":[
        "tailor"
    ],
    "wof:name":"Zaven Tailleur",
    "wof:placetype":"venue"
},
  "geometry": {"coordinates":[-73.5570449829,45.5177192688],"type":"Point"}
}