{
  "type": "Feature",
  "properties": {
    "addr:full":"266 Algoma St S Thunder Bay ON P7B 3C2",
    "addr:housenumber":"266",
    "addr:postcode":"p7b 3c2",
    "addr:street":"Algoma St S",
    "iso:country":"CA",
    "sg:address":"266 Algoma St S",
    "sg:city":"Thunder Bay",
    "sg:classifiers":[
        {
            "category":"Shopping",
            "subcategory":"Clothing, Apparel, & Fashions",
            "type":"Retail Goods"
        }
    ],
    "sg:phone":"+1 807 346 9292",
    "sg:postcode":"P7B 3C2",
    "sg:province":"ON",
    "sg:tags":[
        "shop",
        "bridal"
    ],
    "wof:name":"Eva's Boutique & Bridal",
    "wof:placetype":"venue"
},
  "geometry": {"coordinates":[-89.2323913574,48.4291496277],"type":"Point"}
}