{
  "type": "Feature",
  "properties": {
    "addr:full":"211 6 Ave NE Calgary AB T2E 0L8",
    "addr:housenumber":"211",
    "addr:postcode":"t2e 0l8",
    "addr:street":"6 Ave Ne",
    "iso:country":"CA",
    "sg:address":"211 6 Ave NE",
    "sg:city":"Calgary",
    "sg:classifiers":[
        {
            "category":"Wholesale",
            "subcategory":"Construction Materials",
            "type":"Manufacturing & Wholesale Goods"
        }
    ],
    "sg:phone":"+1 403 245 3331",
    "sg:postcode":"T2E 0L8",
    "sg:province":"AB",
    "sg:tags":[
        "fence"
    ],
    "wof:name":"Stady Bros Fence Works",
    "wof:placetype":"venue"
},
  "geometry": {"coordinates":[-114.059669,51.058102],"type":"Point"}
}