{
  "type": "Feature",
  "properties": {
    "iso:country":"CA",
    "sg:city":"Montreal",
    "sg:classifiers":[
        {
            "category":"Professional",
            "subcategory":"Research",
            "type":"Services"
        }
    ],
    "sg:phone":"+1 514 288 3888",
    "sg:postcode":"H2Y 2R6",
    "sg:province":"QC",
    "sg:tags":[
        "foundation",
        "philanthropic"
    ],
    "wof:name":"Foundation Paul Gerin Lajoie",
    "wof:placetype":"venue"
},
  "geometry": {"coordinates":[-73.557258606,45.5027618408],"type":"Point"}
}