{
  "type": "Feature",
  "properties": {
    "addr:full":"2150 Av Nicolas-Perrot Becancour QC G9H 3B9",
    "addr:housenumber":"2150",
    "addr:postcode":"g9h 3b9",
    "addr:street":"Av Nicolas-Perrot Becancour",
    "iso:country":"CA",
    "sg:address":"2150 Av Nicolas-Perrot",
    "sg:city":"Becancour",
    "sg:classifiers":[
        {
            "category":"Social Services",
            "type":"Services"
        }
    ],
    "sg:phone":"+1 819 294 9292",
    "sg:postcode":"G9H 3B9",
    "sg:province":"QC",
    "sg:tags":[
        "organization",
        "wedding",
        "site",
        "reception",
        "welfare"
    ],
    "wof:name":"Chrysalide",
    "wof:placetype":"venue"
},
  "geometry": {"coordinates":[-72.4372558594,46.3447036743],"type":"Point"}
}