{
  "type": "Feature",
  "properties": {
    "addr:full":"33 Octave St Shediac Bridge NB E4R 1P5",
    "addr:housenumber":"33",
    "addr:postcode":"e4r 1p5",
    "addr:street":"Octave St",
    "iso:country":"CA",
    "sg:address":"33 Octave St",
    "sg:city":"Shediac Bridge",
    "sg:classifiers":[
        {
            "category":"Building & Trades",
            "subcategory":"Construction",
            "type":"Services"
        }
    ],
    "sg:phone":"+1 506 532 2329",
    "sg:postcode":"E4R 1P5",
    "sg:province":"NB",
    "sg:tags":[
        "painter"
    ],
    "wof:name":"C & B Painting",
    "wof:placetype":"venue"
},
  "geometry": {"coordinates":[-64.58023834230001,46.2768440247],"type":"Point"}
}