{
  "type": "Feature",
  "properties": {
    "iso:country":"CA",
    "sg:address":"8845 Boul Pierre-Bertrand",
    "sg:city":"Quebec",
    "sg:classifiers":[
        {
            "category":"Manufacturing",
            "subcategory":"Glass & Minerals",
            "type":"Manufacturing & Wholesale Goods"
        }
    ],
    "sg:phone":"+1 418 622 3333",
    "sg:postcode":"G2K 1W2",
    "sg:province":"QC",
    "sg:tags":[
        "building",
        "material",
        "common"
    ],
    "wof:name":"Permacon Quebec",
    "wof:placetype":"venue"
},
  "geometry": {"coordinates":[-71.2985076904,46.8521690369],"type":"Point"}
}