{
  "type": "Feature",
  "properties": {
    "addr:full":"57 Rue DE LA Gauchetiere O Montreal QC H2Z 1C2",
    "addr:housenumber":"57",
    "addr:postcode":"h2z 1c2",
    "addr:street":"Rue De La Gauchetiere O",
    "iso:country":"CA",
    "sg:address":"57 Rue DE LA Gauchetiere O",
    "sg:city":"Montreal",
    "sg:classifiers":[
        {
            "category":"Restaurant",
            "type":"Food & Drink"
        }
    ],
    "sg:phone":"+1 514 861 4941",
    "sg:postcode":"H2Z 1C2",
    "sg:province":"QC",
    "wof:name":"Jardin DE Jade Poon Kai",
    "wof:placetype":"venue"
},
  "geometry": {"coordinates":[-73.55964660639999,45.5088768005],"type":"Point"}
}