{
  "type": "Feature",
  "properties": {
    "addr:full":"290 Clarence St Brampton ON L6W 1T4",
    "addr:housenumber":"290",
    "addr:postcode":"l6w 1t4",
    "addr:street":"Clarence St",
    "iso:country":"CA",
    "sg:address":"290 Clarence St",
    "sg:city":"Brampton",
    "sg:classifiers":[
        {
            "category":"Building & Trades",
            "subcategory":"Construction",
            "type":"Services"
        }
    ],
    "sg:phone":"+1 905 453 1200",
    "sg:postcode":"L6W 1T4",
    "sg:province":"ON",
    "sg:tags":[
        "paving",
        "contractor"
    ],
    "wof:name":"Graham Brothers Construction",
    "wof:placetype":"venue"
},
  "geometry": {"coordinates":[-79.73376500000001,43.691414],"type":"Point"}
}