{
  "type": "Feature",
  "properties": {
    "iso:country":"CA",
    "sg:address":"16 Crysdale Dr",
    "sg:city":"Mackenzie",
    "sg:classifiers":[
        {
            "category":"Manufacturing",
            "subcategory":"Lumber",
            "type":"Manufacturing & Wholesale Goods"
        }
    ],
    "sg:phone":"+1 250 997 5064",
    "sg:postcode":"V0J 2C0",
    "sg:province":"BC",
    "sg:tags":[
        "forester"
    ],
    "wof:name":"Mac Kenzie Forestry Svc",
    "wof:placetype":"venue"
},
  "geometry": {"coordinates":[-123.08909606900001,55.3351287842],"type":"Point"}
}