{
  "type": "Feature",
  "properties": {
    "addr:full":"999 Route 425 Whitney NB E1V 4K2",
    "addr:housenumber":"999",
    "addr:postcode":"e1v 4k2",
    "addr:street":"Route 425",
    "iso:country":"CA",
    "sg:address":"999 Route 425",
    "sg:city":"Whitney",
    "sg:classifiers":[
        {
            "category":"Home & Garden",
            "subcategory":"Furniture",
            "type":"Retail Goods"
        }
    ],
    "sg:phone":"+1 506 622 1939",
    "sg:postcode":"E1V 4K2",
    "sg:province":"NB",
    "wof:name":"Town & Country Furniture Ltd",
    "wof:placetype":"venue"
},
  "geometry": {"coordinates":[-65.73044586180001,46.9645614624],"type":"Point"}
}