{
  "type": "Feature",
  "properties": {
    "addr:full":"11665 6E Av Montreal QC H1E 1R8",
    "addr:housenumber":"11665",
    "addr:postcode":"h1e 1r8",
    "addr:street":"6E Av",
    "iso:country":"CA",
    "sg:address":"11665 6E Av",
    "sg:city":"Montreal",
    "sg:classifiers":[
        {
            "category":"Home & Garden",
            "subcategory":"Furniture",
            "type":"Retail Goods"
        }
    ],
    "sg:phone":"+1 514 648 8688",
    "sg:postcode":"H1E 1R8",
    "sg:province":"QC",
    "sg:tags":[
        "equipment",
        "kitchen",
        "cabinet"
    ],
    "wof:name":"Armoires Cardic Inc",
    "wof:placetype":"venue"
},
  "geometry": {"coordinates":[-73.5991897583,45.6220741272],"type":"Point"}
}