{
  "type": "Feature",
  "properties": {
    "addr:full":"5011 49 Ave Taber AB T1G 1V9",
    "addr:housenumber":"5011",
    "addr:postcode":"t1g 1v9",
    "addr:street":"49 Ave",
    "iso:country":"CA",
    "sg:address":"5011 49 Ave",
    "sg:city":"Taber",
    "sg:classifiers":[
        {
            "category":"Social Services",
            "type":"Services"
        }
    ],
    "sg:phone":"+1 403 223 7932",
    "sg:postcode":"T1G 1V9",
    "sg:province":"AB",
    "sg:tags":[
        "counseling"
    ],
    "wof:name":"Taber Mental Health Clinic",
    "wof:placetype":"venue"
},
  "geometry": {"coordinates":[-112.149055481,49.7849578857],"type":"Point"}
}