{
  "type": "Feature",
  "properties": {
    "addr:full":"195 King St E Mount Forest ON N0G 2L2",
    "addr:housenumber":"195",
    "addr:postcode":"n0g 2l2",
    "addr:street":"King St E",
    "iso:country":"CA",
    "sg:address":"195 King St E",
    "sg:city":"Mount Forest",
    "sg:classifiers":[
        {
            "category":"Food & Beverages",
            "subcategory":"Liquor & Beverages",
            "type":"Retail Goods"
        }
    ],
    "sg:phone":"+1 519 323 2190",
    "sg:postcode":"N0G 2L2",
    "sg:province":"ON",
    "sg:tags":[
        "store"
    ],
    "wof:name":"Liquor Control Board of Ont",
    "wof:placetype":"venue"
},
  "geometry": {"coordinates":[-80.73268899999999,43.981556],"type":"Point"}
}