{
  "type": "Feature",
  "properties": {
    "addr:full":"Thornhill ON L3T 7P5",
    "addr:postcode":"l3t 7p5",
    "iso:country":"CA",
    "sg:city":"Thornhill",
    "sg:classifiers":[
        {
            "category":"Manufacturing",
            "subcategory":"Food",
            "type":"Manufacturing & Wholesale Goods"
        }
    ],
    "sg:phone":"+1 905 731 1779",
    "sg:postcode":"L3T 7P5",
    "sg:province":"ON",
    "sg:tags":[
        "grocer",
        "product",
        "manufacturer"
    ],
    "wof:name":"Sedo Snax",
    "wof:placetype":"venue"
},
  "geometry": {"coordinates":[-79.39669036870001,43.8224029541],"type":"Point"}
}