{
  "type": "Feature",
  "properties": {
    "addr:full":"101 Victoria Rd Bridgewater NS B4V 2N5",
    "addr:housenumber":"101",
    "addr:postcode":"b4v 2n5",
    "addr:street":"Victoria Rd",
    "iso:country":"CA",
    "sg:address":"101 Victoria Rd",
    "sg:city":"Bridgewater",
    "sg:classifiers":[
        {
            "category":"Shopping",
            "type":"Retail Goods"
        }
    ],
    "sg:phone":"+1 902 543 4131",
    "sg:postcode":"B4V 2N5",
    "sg:province":"NS",
    "sg:tags":[
        "monument"
    ],
    "wof:name":"DE Mone's Monuments Ltd",
    "wof:placetype":"venue"
},
  "geometry": {"coordinates":[-64.52676391599999,44.3795089722],"type":"Point"}
}