{
  "type": "Feature",
  "properties": {
    "iso:country":"CA",
    "sg:city":"Blezard Valley",
    "sg:classifiers":[
        {
            "category":"Building & Trades",
            "subcategory":"Plumbing",
            "type":"Services"
        }
    ],
    "sg:phone":"+1 705 897 2381",
    "sg:postcode":"P0M 1E0",
    "sg:province":"ON",
    "sg:tags":[
        "conditioning",
        "air",
        "system",
        "contractor"
    ],
    "wof:name":"United Heating & Ac Inc",
    "wof:placetype":"venue"
},
  "geometry": {"coordinates":[-81.04986572270001,46.6092834473],"type":"Point"}
}