{
  "type": "Feature",
  "properties": {
    "addr:full":"679 25E Av Saint-Eustache QC J7R 4K3",
    "addr:housenumber":"679",
    "addr:postcode":"j7r 4k3",
    "addr:street":"25E Av Saint-Eustache",
    "iso:country":"CA",
    "sg:address":"679 25E Av",
    "sg:city":"Saint-Eustache",
    "sg:classifiers":[
        {
            "category":"Wholesale",
            "subcategory":"Scrap",
            "type":"Manufacturing & Wholesale Goods"
        }
    ],
    "sg:phone":"+1 450 472 0662",
    "sg:postcode":"J7R 4K3",
    "sg:province":"QC",
    "sg:tags":[
        "recycling",
        "metal",
        "center",
        "iron"
    ],
    "wof:name":"M M Metal",
    "wof:placetype":"venue"
},
  "geometry": {"coordinates":[-73.8889007568,45.5580482483],"type":"Point"}
}