{
  "type": "Feature",
  "properties": {
    "iso:country":"CA",
    "sg:address":"841 Wellington St # A2",
    "sg:city":"London",
    "sg:classifiers":[
        {
            "category":"Banks & Credit Unions",
            "subcategory":"Investment Brokerage",
            "type":"Services"
        }
    ],
    "sg:phone":"+1 519 681 5590",
    "sg:postcode":"N6A 3S6",
    "sg:province":"ON",
    "wof:name":"Edward Jones",
    "wof:placetype":"venue"
},
  "geometry": {"coordinates":[-81.252892,42.999409],"type":"Point"}
}