{
  "type": "Feature",
  "properties": {
    "addr:full":"1250 Trans Canada Hwy W Kamloops BC V2C 6R3",
    "addr:housenumber":"1250",
    "addr:postcode":"bc v2c 6r3",
    "addr:street":"Trans Canada Hwy W",
    "iso:country":"CA",
    "sg:address":"1250 Trans Canada Hwy W",
    "sg:city":"Kamloops",
    "sg:classifiers":[
        {
            "category":"Travel",
            "subcategory":"Hotels & Motels",
            "type":"Entertainment"
        }
    ],
    "sg:phone":"+1 250 374 9666",
    "sg:postcode":"V2C 6R3",
    "sg:province":"BC",
    "wof:name":"Maverick Motor Inn",
    "wof:placetype":"venue"
},
  "geometry": {"coordinates":[-120.36702699999999,50.655682],"type":"Point"}
}