{
  "type": "Feature",
  "properties": {
    "iso:country":"CA",
    "sg:address":"925 Danforth Ave",
    "sg:city":"Toronto",
    "sg:classifiers":[
        {
            "category":"Food & Beverages",
            "subcategory":"Groceries & Convenience Stores",
            "type":"Retail Goods"
        }
    ],
    "sg:phone":"+1 416 461 2788",
    "sg:postcode":"M4J 1L8",
    "sg:province":"ON",
    "sg:tags":[
        "variety"
    ],
    "wof:name":"Phillip Variety",
    "wof:placetype":"venue"
},
  "geometry": {"coordinates":[-79.3386459351,43.6800117493],"type":"Point"}
}