{
  "type": "Feature",
  "properties": {
    "addr:full":"1048 Davie St Vancouver BC V6E 1M3",
    "addr:housenumber":"1048",
    "addr:postcode":"v6e 1m3",
    "addr:street":"Davie St",
    "iso:country":"CA",
    "sg:address":"1048 Davie St",
    "sg:city":"Vancouver",
    "sg:classifiers":[
        {
            "category":"Recreation",
            "type":"Entertainment"
        }
    ],
    "sg:phone":"+1 604 689 9719",
    "sg:postcode":"V6E 1M3",
    "sg:province":"BC",
    "sg:tags":[
        "spa",
        "house",
        "sauna",
        "bath"
    ],
    "wof:name":"Fahrenheit 212",
    "wof:placetype":"venue"
},
  "geometry": {"coordinates":[-123.13033299999999,49.279629],"type":"Point"}
}