{
  "type": "Feature",
  "properties": {
    "addr:full":"Winnipeg MB R3R 0G7",
    "addr:postcode":"r3r 0g7",
    "iso:country":"CA",
    "sg:city":"Winnipeg",
    "sg:classifiers":[
        {
            "category":"Banks & Credit Unions",
            "subcategory":"Bank",
            "type":"Services"
        }
    ],
    "sg:phone":"+1 204 985 3776",
    "sg:postcode":"R3R 0G7",
    "sg:province":"MB",
    "wof:name":"Scotiabank",
    "wof:placetype":"venue"
},
  "geometry": {"coordinates":[-97.2830734253,49.8574981689],"type":"Point"}
}