{
  "type": "Feature",
  "properties": {
    "addr:full":"120 4th St W Owen Sound ON N4K 3J9",
    "addr:housenumber":"120",
    "addr:postcode":"n4k 3j9",
    "addr:street":"4Th St W",
    "iso:country":"CA",
    "sg:address":"120 4th St W",
    "sg:city":"Owen Sound",
    "sg:classifiers":[
        {
            "category":"Building & Trades",
            "subcategory":"Construction",
            "type":"Services"
        }
    ],
    "sg:phone":"+1 519 371 1476",
    "sg:postcode":"N4K 3J9",
    "sg:province":"ON",
    "sg:tags":[
        "roofing",
        "contractor"
    ],
    "wof:name":"Robert Baker Roofing Mntnc",
    "wof:placetype":"venue"
},
  "geometry": {"coordinates":[-80.941643,44.556835],"type":"Point"}
}