{
  "type": "Feature",
  "properties": {
    "addr:full":"96 Spadina Ave Toronto ON M5V 2J6",
    "addr:housenumber":"96",
    "addr:postcode":"m5v 2j6",
    "addr:street":"Spadina Ave",
    "iso:country":"CA",
    "sg:address":"96 Spadina Ave",
    "sg:city":"Toronto",
    "sg:classifiers":[
        {
            "category":"Arts & Performance",
            "subcategory":"Theater",
            "type":"Entertainment"
        }
    ],
    "sg:phone":"+1 416 866 2992",
    "sg:postcode":"M5V 2J6",
    "sg:province":"ON",
    "sg:tags":[
        "television",
        "program",
        "producer"
    ],
    "wof:name":"Indelible Inc",
    "wof:placetype":"venue"
},
  "geometry": {"coordinates":[-79.3956832886,43.6463546753],"type":"Point"}
}