{
  "type": "Feature",
  "properties": {
    "addr:full":"724 Sixth St New Westminster BC V3L 3C5",
    "addr:housenumber":"724",
    "addr:postcode":"v3l 3c5",
    "addr:street":"Sixth St",
    "iso:country":"CA",
    "sg:address":"724 Sixth St",
    "sg:city":"New Westminster",
    "sg:classifiers":[
        {
            "category":"Restaurant",
            "type":"Food & Drink"
        }
    ],
    "sg:phone":"+1 604 525 1457",
    "sg:postcode":"V3L 3C5",
    "sg:province":"BC",
    "wof:name":"New West Garden Restaurant Ltd",
    "wof:placetype":"venue"
},
  "geometry": {"coordinates":[-122.922653,49.214821],"type":"Point"}
}