{
  "type": "Feature",
  "properties": {
    "addr:full":"1175 Rue Franchere Marieville QC J3M 1J3",
    "addr:housenumber":"1175",
    "addr:postcode":"j3m 1j3",
    "addr:street":"Rue Franchere",
    "iso:country":"CA",
    "sg:address":"1175 Rue Franchere",
    "sg:city":"Marieville",
    "sg:classifiers":[
        {
            "category":"Manufacturing",
            "subcategory":"Metals",
            "type":"Manufacturing & Wholesale Goods"
        }
    ],
    "sg:phone":"+1 450 460 6753",
    "sg:postcode":"J3M 1J3",
    "sg:province":"QC",
    "sg:tags":[
        "nut",
        "bolt"
    ],
    "wof:name":"Boulons Industriels Rouville",
    "wof:placetype":"venue"
},
  "geometry": {"coordinates":[-73.16394042970001,45.430015564],"type":"Point"}
}