{
  "type": "Feature",
  "properties": {
    "addr:full":"St-Sauveur-Des-Monts QC J0R 1R0",
    "addr:postcode":"j0r 1r0",
    "iso:country":"CA",
    "sg:city":"St-Sauveur-Des-Monts",
    "sg:classifiers":[
        {
            "category":"Shopping",
            "subcategory":"Clothing, Apparel, & Fashions",
            "type":"Retail Goods"
        }
    ],
    "sg:phone":"+1 450 227 1234",
    "sg:postcode":"J0R 1R0",
    "sg:province":"QC",
    "sg:tags":[
        "item",
        "boutique"
    ],
    "wof:name":"Boutique Solo Mode",
    "wof:placetype":"venue"
},
  "geometry": {"coordinates":[-74.157898,45.894417],"type":"Point"}
}