{
  "type": "Feature",
  "properties": {
    "addr:full":"635 Rue Houssart Cap-DE-LA-Madeleine QC G8T 9C1",
    "addr:housenumber":"635",
    "addr:postcode":"g8t 9c1",
    "addr:street":"Rue Houssart",
    "iso:country":"CA",
    "sg:address":"635 Rue Houssart",
    "sg:city":"Cap-DE-LA-Madeleine",
    "sg:classifiers":[
        {
            "category":"Building & Trades",
            "subcategory":"Construction",
            "type":"Services"
        }
    ],
    "sg:phone":"+1 819 375 5337",
    "sg:postcode":"G8T 9C1",
    "sg:province":"QC",
    "sg:tags":[
        "maker",
        "cabinet"
    ],
    "wof:name":"Atelier Bruno Pichet",
    "wof:placetype":"venue"
},
  "geometry": {"coordinates":[-72.53337097169999,46.3785209656],"type":"Point"}
}