{
  "type": "Feature",
  "properties": {
    "addr:full":"Hemmingford QC J0L 1H0",
    "addr:postcode":"j0l 1h0",
    "iso:country":"CA",
    "sg:city":"Hemmingford",
    "sg:classifiers":[
        {
            "category":"Personal",
            "subcategory":"Beauty Salon",
            "type":"Services"
        }
    ],
    "sg:phone":"+1 450 247 3454",
    "sg:postcode":"J0L 1H0",
    "sg:province":"QC",
    "wof:name":"Salon Creations Jenn",
    "wof:placetype":"venue"
},
  "geometry": {"coordinates":[-73.5854263306,45.0517997742],"type":"Point"}
}