{
  "type": "Feature",
  "properties": {
    "addr:full":"Edmonton AB T5J 4G8",
    "addr:postcode":"t5j 4g8",
    "iso:country":"CA",
    "sg:city":"Edmonton",
    "sg:classifiers":[
        {
            "category":"Professional",
            "subcategory":"Lawyer & Legal Services",
            "type":"Services"
        }
    ],
    "sg:phone":"+1 780 429 1751",
    "sg:postcode":"T5J 4G8",
    "sg:province":"AB",
    "sg:tags":[
        "attorney"
    ],
    "wof:name":"Slator, Jordan A",
    "wof:placetype":"venue"
},
  "geometry": {"coordinates":[-113.49533099999999,53.542088],"type":"Point"}
}