{
  "type": "Feature",
  "properties": {
    "addr:full":"Miquelon QC J0Y 2B0",
    "addr:postcode":"j0y 2b0",
    "addr:street":"Miquelon",
    "iso:country":"CA",
    "sg:city":"Miquelon",
    "sg:classifiers":[
        {
            "category":"Farming",
            "subcategory":"Aquatic Farm",
            "type":"Manufacturing & Wholesale Goods"
        }
    ],
    "sg:phone":"+1 819 753 2381",
    "sg:postcode":"J0Y 2B0",
    "sg:province":"QC",
    "sg:tags":[
        "hatchery",
        "consultant",
        "fish",
        "fishery"
    ],
    "wof:name":"Pourvoyeur Portage Outfitter",
    "wof:placetype":"venue"
},
  "geometry": {"coordinates":[-76.4629058838,49.4026412964],"type":"Point"}
}