{
  "type": "Feature",
  "properties": {
    "addr:full":"264 Centre St Shaunavon SK S0N 2M0",
    "addr:housenumber":"264",
    "addr:postcode":"s0n 2m0",
    "addr:street":"Centre St",
    "iso:country":"CA",
    "sg:address":"264 Centre St",
    "sg:city":"Shaunavon",
    "sg:classifiers":[
        {
            "category":"Government",
            "subcategory":"Office",
            "type":"Public Place"
        }
    ],
    "sg:phone":"+1 306 297 2108",
    "sg:postcode":"S0N 2M0",
    "sg:province":"SK",
    "sg:tags":[
        "municipality"
    ],
    "wof:name":"Rural Municipality-Arlington",
    "wof:placetype":"venue"
},
  "geometry": {"coordinates":[-108.40791299999999,49.646564],"type":"Point"}
}