{
  "type": "Feature",
  "properties": {
    "iso:country":"CA",
    "sg:address":"6376 Rue Drolet",
    "sg:city":"Montreal",
    "sg:classifiers":[
        {
            "category":"Building & Trades",
            "subcategory":"Plumbing",
            "type":"Services"
        }
    ],
    "sg:phone":"+1 514 279 4758",
    "sg:postcode":"H2S 2S7",
    "sg:province":"QC",
    "sg:tags":[
        "contractor"
    ],
    "wof:name":"F Lavoie & Cie",
    "wof:placetype":"venue"
},
  "geometry": {"coordinates":[-73.6044616699,45.5325012207],"type":"Point"}
}