{
  "type": "Feature",
  "properties": {
    "addr:full":"20 Main Blvd Sherwood Park AB T8A 3W8",
    "addr:housenumber":"20",
    "addr:postcode":"t8a 3w8",
    "addr:street":"Main Blvd",
    "iso:country":"CA",
    "sg:address":"20 Main Blvd",
    "sg:city":"Sherwood Park",
    "sg:classifiers":[
        {
            "category":"Social Services",
            "subcategory":"Child Care",
            "type":"Services"
        }
    ],
    "sg:phone":"+1 780 417 3444",
    "sg:postcode":"T8A 3W8",
    "sg:province":"AB",
    "wof:name":"Town & Country Child Care",
    "wof:placetype":"venue"
},
  "geometry": {"coordinates":[-113.31711578399999,53.5372467041],"type":"Point"}
}