{
  "type": "Feature",
  "properties": {
    "addr:full":"838 Eastvale Dr Gloucester ON K1J 7A4",
    "addr:housenumber":"838",
    "addr:postcode":"k1j 7a4",
    "addr:street":"Eastvale Dr",
    "iso:country":"CA",
    "sg:address":"838 Eastvale Dr",
    "sg:city":"Gloucester",
    "sg:phone":"+1 613 749 1232",
    "sg:postcode":"K1J 7A4",
    "sg:province":"ON",
    "sg:tags":[
        "scoreboard"
    ],
    "wof:name":"Maccom Systems Ltd",
    "wof:placetype":"venue"
},
  "geometry": {"coordinates":[-75.5946731567,45.4522476196],"type":"Point"}
}