{
  "type": "Feature",
  "properties": {
    "addr:full":"18 1/2 Fifth St N Chatham ON N7L 2Z5",
    "addr:housenumber":"1 / 2",
    "addr:postcode":"n7l 2z5",
    "addr:street":"18;Fifth St N",
    "iso:country":"CA",
    "sg:address":"18 1/2 Fifth St N",
    "sg:city":"Chatham",
    "sg:classifiers":[
        {
            "category":"Real Estate",
            "subcategory":"Real Estate Agent",
            "type":"Services"
        }
    ],
    "sg:phone":"+1 519 351 8282",
    "sg:postcode":"N7L 2Z5",
    "sg:province":"ON",
    "wof:name":"George H Willson Realty Ltd",
    "wof:placetype":"venue"
},
  "geometry": {"coordinates":[-82.185799,42.40707],"type":"Point"}
}