{
  "type": "Feature",
  "properties": {
    "addr:full":"5506 238 St Langley BC V2Z 2P1",
    "addr:housenumber":"5506",
    "addr:postcode":"v2z 2p1",
    "addr:street":"238 St",
    "iso:country":"CA",
    "sg:address":"5506 238 St",
    "sg:city":"Langley",
    "sg:classifiers":[
        {
            "category":"Retail",
            "subcategory":"Repair Shop",
            "type":"Services"
        }
    ],
    "sg:phone":"+1 604 533 4400",
    "sg:postcode":"V2Z 2P1",
    "sg:province":"BC",
    "sg:tags":[
        "welding"
    ],
    "wof:name":"M C Welding Svc Ltd",
    "wof:placetype":"venue"
},
  "geometry": {"coordinates":[-122.564339,49.102837],"type":"Point"}
}