{
  "type": "Feature",
  "properties": {
    "addr:full":"Levis QC G6W 6N2",
    "addr:postcode":"g6w 6n2",
    "iso:country":"CA",
    "sg:city":"Levis",
    "sg:classifiers":[
        {
            "category":"Insurance",
            "subcategory":"Insurance Agent",
            "type":"Services"
        }
    ],
    "sg:phone":"+1 418 835 1212",
    "sg:postcode":"G6W 6N2",
    "sg:province":"QC",
    "wof:name":"Industrielle Alliance Assrnce",
    "wof:placetype":"venue"
},
  "geometry": {"coordinates":[-71.19573200000001,46.776104],"type":"Point"}
}