{
  "type": "Feature",
  "properties": {
    "addr:full":"320 Boul Saint-Joseph # 58 Hull QC J8Y 3Y8",
    "addr:housenumber":"320",
    "addr:postcode":"j8y 3y8",
    "addr:street":"Boul Saint-Joseph # 58",
    "iso:country":"CA",
    "sg:address":"320 Boul Saint-Joseph # 58",
    "sg:city":"Hull",
    "sg:classifiers":[
        {
            "category":"Shopping",
            "subcategory":"Clothing, Apparel, & Fashions",
            "type":"Retail Goods"
        }
    ],
    "sg:phone":"+1 819 771 5116",
    "sg:postcode":"J8Y 3Y8",
    "sg:province":"QC",
    "wof:name":"Charmante",
    "wof:placetype":"venue"
},
  "geometry": {"coordinates":[-75.73267364500001,45.4412155151],"type":"Point"}
}