{
  "type": "Feature",
  "properties": {
    "addr:full":"220 Midlake Blvd SE Calgary AB T2X 1K6",
    "addr:housenumber":"220",
    "addr:postcode":"t2x 1k6",
    "addr:street":"Midlake Blvd Se",
    "iso:country":"CA",
    "sg:address":"220 Midlake Blvd SE",
    "sg:city":"Calgary",
    "sg:classifiers":[
        {
            "category":"Wholesale",
            "subcategory":"Home Furnishings",
            "type":"Manufacturing & Wholesale Goods"
        }
    ],
    "sg:phone":"+1 403 254 0309",
    "sg:postcode":"T2X 1K6",
    "sg:province":"AB",
    "sg:tags":[
        "rug",
        "carpet"
    ],
    "wof:name":"Andrew J Miller & Assoc",
    "wof:placetype":"venue"
},
  "geometry": {"coordinates":[-114.04644,50.911705],"type":"Point"}
}