{
  "type": "Feature",
  "properties": {
    "iso:country":"CA",
    "sg:address":"220 Midlake Blvd SE",
    "sg:city":"Calgary",
    "sg:classifiers":[
        {
            "category":"Wholesale",
            "subcategory":"Home Furnishings",
            "type":"Manufacturing & Wholesale Goods"
        }
    ],
    "sg:phone":"+1 403 254 0309",
    "sg:postcode":"T2X 1K6",
    "sg:province":"AB",
    "sg:tags":[
        "rug",
        "carpet"
    ],
    "wof:name":"Andrew J Miller & Assoc",
    "wof:placetype":"venue"
},
  "geometry": {"coordinates":[-114.04644,50.911705],"type":"Point"}
}