{
  "type": "Feature",
  "properties": {
    "addr:full":"7476 49 Ave Red Deer AB T4P 1M2",
    "addr:housenumber":"7476",
    "addr:postcode":"t4p 1m2",
    "addr:street":"49 Ave",
    "iso:country":"CA",
    "sg:address":"7476 49 Ave",
    "sg:city":"Red Deer",
    "sg:classifiers":[
        {
            "category":"Retail",
            "subcategory":"Auto Repair",
            "type":"Services"
        }
    ],
    "sg:phone":"+1 403 347 5859",
    "sg:postcode":"T4P 1M2",
    "sg:province":"AB",
    "sg:tags":[
        "body",
        "automobile",
        "painting"
    ],
    "wof:name":"C & R Collision Ltd",
    "wof:placetype":"venue"
},
  "geometry": {"coordinates":[-113.813827515,52.2885017395],"type":"Point"}
}