{
  "type": "Feature",
  "properties": {
    "addr:full":"92 Ottawa St N Hamilton ON L8H 3Z1",
    "addr:housenumber":"92",
    "addr:postcode":"l8h 3z1",
    "addr:street":"Ottawa St N",
    "iso:country":"CA",
    "sg:address":"92 Ottawa St N",
    "sg:city":"Hamilton",
    "sg:classifiers":[
        {
            "category":"Organizations",
            "subcategory":"Religious Organization",
            "type":"Services"
        }
    ],
    "sg:phone":"+1 905 545 2002",
    "sg:postcode":"L8H 3Z1",
    "sg:province":"ON",
    "sg:tags":[
        "church"
    ],
    "wof:name":"First Church of the Nazarene",
    "wof:placetype":"venue"
},
  "geometry": {"coordinates":[-79.818504,43.24514],"type":"Point"}
}