{
  "type": "Feature",
  "properties": {
    "iso:country":"CA",
    "sg:city":"Richmond Hill",
    "sg:classifiers":[
        {
            "category":"Home & Garden",
            "subcategory":"Furniture",
            "type":"Retail Goods"
        }
    ],
    "sg:phone":"+1 905 709 1162",
    "sg:postcode":"L4B 3L4",
    "sg:province":"ON",
    "wof:name":"General Products Inc",
    "wof:placetype":"venue"
},
  "geometry": {"coordinates":[-79.377159,43.84922],"type":"Point"}
}