{
  "type": "Feature",
  "properties": {
    "addr:full":"110 River Rd Arnprior ON K7S 1R4",
    "addr:housenumber":"110",
    "addr:postcode":"k7s 1r4",
    "addr:street":"River Rd",
    "iso:country":"CA",
    "sg:address":"110 River Rd",
    "sg:city":"Arnprior",
    "sg:classifiers":[
        {
            "category":"Building & Trades",
            "subcategory":"Plumbing",
            "type":"Services"
        }
    ],
    "sg:phone":"+1 613 623 4081",
    "sg:postcode":"K7S 1R4",
    "sg:province":"ON",
    "sg:tags":[
        "air",
        "conditioning",
        "contractor",
        "system",
        "heating"
    ],
    "wof:name":"Anderson Heating Ltd",
    "wof:placetype":"venue"
},
  "geometry": {"coordinates":[-76.358368,45.435635],"type":"Point"}
}