{
  "type": "Feature",
  "properties": {
    "addr:full":"193 River Valley Dr Grand Bay-Westfield NB E5K 1A3",
    "addr:housenumber":"193",
    "addr:postcode":"e5k 1a3",
    "addr:street":"River Valley Dr",
    "iso:country":"CA",
    "sg:address":"193 River Valley Dr",
    "sg:city":"Grand Bay-Westfield",
    "sg:classifiers":[
        {
            "category":"Personal",
            "subcategory":"Beauty Salon",
            "type":"Services"
        }
    ],
    "sg:phone":"+1 506 738 3537",
    "sg:postcode":"E5K 1A3",
    "sg:province":"NB",
    "wof:name":"Totally You Skin Care Ctr",
    "wof:placetype":"venue"
},
  "geometry": {"coordinates":[-66.195274,45.302647],"type":"Point"}
}