{
  "type": "Feature",
  "properties": {
    "iso:country":"CA",
    "sg:address":"2138 Keating Cross Rd",
    "sg:city":"Saanichton",
    "sg:classifiers":[
        {
            "category":"Restaurant",
            "type":"Food & Drink"
        }
    ],
    "sg:phone":"+1 250 652 2513",
    "sg:postcode":"V8M 2A6",
    "sg:province":"BC",
    "wof:name":"Drifters Restaurant",
    "wof:placetype":"venue"
},
  "geometry": {"coordinates":[-123.41689300500001,48.595199585],"type":"Point"}
}