{
  "type": "Feature",
  "properties": {
    "addr:full":"School Cres Newtown NL A0G 3L0",
    "addr:postcode":"a0g 3l0",
    "addr:street":"School Cres",
    "iso:country":"CA",
    "sg:address":"School Cres",
    "sg:city":"Newtown",
    "sg:classifiers":[
        {
            "category":"Recreation",
            "type":"Entertainment"
        }
    ],
    "sg:phone":"+1 709 536 3220",
    "sg:postcode":"A0G 3L0",
    "sg:province":"NL",
    "sg:tags":[
        "attraction",
        "tourist"
    ],
    "wof:name":"Barbour Heritage Site",
    "wof:placetype":"venue"
},
  "geometry": {"coordinates":[-53.5144081116,49.2034873962],"type":"Point"}
}