{
  "type": "Feature",
  "properties": {
    "addr:full":"8 Oxford St Brantford ON N3R 5C6",
    "addr:housenumber":"8",
    "addr:postcode":"n3r 5c6",
    "addr:street":"Oxford St",
    "iso:country":"CA",
    "sg:address":"8 Oxford St",
    "sg:city":"Brantford",
    "sg:classifiers":[
        {
            "category":"Wholesale",
            "subcategory":"Chemicals & Plastics",
            "type":"Manufacturing & Wholesale Goods"
        }
    ],
    "sg:phone":"+1 519 759 2026",
    "sg:postcode":"N3R 5C6",
    "sg:province":"ON",
    "sg:tags":[
        "equipment",
        "pool",
        "swimming"
    ],
    "wof:name":"Crystal Clear Pool & Spa Home",
    "wof:placetype":"venue"
},
  "geometry": {"coordinates":[-80.282639,43.170937],"type":"Point"}
}