{
  "type": "Feature",
  "properties": {
    "addr:full":"2592 Birchmount Rd Scarborough ON M1T 2M5",
    "addr:housenumber":"2592",
    "addr:postcode":"m1t 2m5",
    "addr:street":"Birchmount Rd",
    "iso:country":"CA",
    "sg:address":"2592 Birchmount Rd",
    "sg:city":"Scarborough",
    "sg:classifiers":[
        {
            "category":"Retail",
            "subcategory":"Laundry & Dry Cleaning",
            "type":"Services"
        }
    ],
    "sg:phone":"+1 416 293 4913",
    "sg:postcode":"M1T 2M5",
    "sg:province":"ON",
    "sg:tags":[
        "cleaners"
    ],
    "wof:name":"Huntingwood Dry Cleaners",
    "wof:placetype":"venue"
},
  "geometry": {"coordinates":[-79.30201700000001,43.789352],"type":"Point"}
}