{
  "type": "Feature",
  "properties": {
    "addr:full":"Toronto ON M5T 3A5",
    "addr:postcode":"m5t 3a5",
    "iso:country":"CA",
    "sg:city":"Toronto",
    "sg:classifiers":[
        {
            "category":"Wholesale",
            "subcategory":"Durable Goods & Equipment",
            "type":"Manufacturing & Wholesale Goods"
        }
    ],
    "sg:phone":"+1 416 593 7290",
    "sg:postcode":"M5T 3A5",
    "sg:province":"ON",
    "sg:tags":[
        "accountant",
        "importer"
    ],
    "wof:name":"J Hwang & CO",
    "wof:placetype":"venue"
},
  "geometry": {"coordinates":[-79.3982162476,43.6525650024],"type":"Point"}
}