{
  "type": "Feature",
  "properties": {
    "addr:full":"887 Rang DE L'Eglise Saint-Eugene-DE-Grantham QC J0C 1J0",
    "addr:housenumber":"887",
    "addr:postcode":"j0c 1j0",
    "addr:street":"Rang De L'Eglise Saint-Eugene-De-Grantham",
    "iso:country":"CA",
    "sg:address":"887 Rang DE L'Eglise",
    "sg:city":"Saint-Eugene-DE-Grantham",
    "sg:classifiers":[
        {
            "category":"Manufacturing",
            "subcategory":"Metals",
            "type":"Manufacturing & Wholesale Goods"
        }
    ],
    "sg:phone":"+1 819 396 2813",
    "sg:postcode":"J0C 1J0",
    "sg:province":"QC",
    "sg:tags":[
        "solder"
    ],
    "wof:name":"Soudure Marshall Inc",
    "wof:placetype":"venue"
},
  "geometry": {"coordinates":[-72.774513,45.877846],"type":"Point"}
}