{
  "type": "Feature",
  "properties": {
    "addr:full":"690 Mcphillips St Winnipeg MB R2X 2H5",
    "addr:housenumber":"690",
    "addr:postcode":"r2x 2h5",
    "addr:street":"Mcphillips St",
    "iso:country":"CA",
    "sg:address":"690 Mcphillips St",
    "sg:city":"Winnipeg",
    "sg:classifiers":[
        {
            "category":"Personal",
            "subcategory":"Beauty Salon",
            "type":"Services"
        }
    ],
    "sg:phone":"+1 204 589 5006",
    "sg:postcode":"R2X 2H5",
    "sg:province":"MB",
    "wof:name":"Mc Phillips Hair Design",
    "wof:placetype":"venue"
},
  "geometry": {"coordinates":[-97.1697235107,49.9246292114],"type":"Point"}
}