{
  "type": "Feature",
  "properties": {
    "iso:country":"CA",
    "sg:address":"875 Park Royal N",
    "sg:city":"West Vancouver",
    "sg:classifiers":[
        {
            "category":"Professional",
            "subcategory":"Computer Services",
            "type":"Services"
        }
    ],
    "sg:phone":"+1 604 926 9258",
    "sg:postcode":"V7T 1H9",
    "sg:province":"BC",
    "sg:tags":[
        "repair",
        "dealer",
        "equipment"
    ],
    "wof:name":"London Drugs Ltd",
    "wof:placetype":"venue"
},
  "geometry": {"coordinates":[-123.139008,49.327362],"type":"Point"}
}