{
  "type": "Feature",
  "properties": {
    "iso:country":"CA",
    "sg:city":"Surrey",
    "sg:classifiers":[
        {
            "category":"Professional",
            "subcategory":"Research",
            "type":"Services"
        }
    ],
    "sg:phone":"+1 604 591 1128",
    "sg:postcode":"V3W 1K7",
    "sg:province":"BC",
    "sg:tags":[
        "development",
        "electronic"
    ],
    "wof:name":"Acr Systems Inc",
    "wof:placetype":"venue"
},
  "geometry": {"coordinates":[-122.863937378,49.1553192139],"type":"Point"}
}