{
  "type": "Feature",
  "properties": {
    "addr:full":"74 33rd St E Saskatoon SK S7K 0R9",
    "addr:housenumber":"74",
    "addr:postcode":"s7k 0r9",
    "addr:street":"33Rd St E",
    "iso:country":"CA",
    "sg:address":"74 33rd St E",
    "sg:city":"Saskatoon",
    "sg:classifiers":[
        {
            "category":"Home & Garden",
            "subcategory":"Carpets & Floor Coverings",
            "type":"Retail Goods"
        }
    ],
    "sg:phone":"+1 306 683 3600",
    "sg:postcode":"S7K 0R9",
    "sg:province":"SK",
    "sg:tags":[
        "rug"
    ],
    "wof:name":"End of the Roll",
    "wof:placetype":"venue"
},
  "geometry": {"coordinates":[-106.66687,52.14397],"type":"Point"}
}