{
  "type": "Feature",
  "properties": {
    "iso:country":"CA",
    "sg:address":"32 Sadler Ave",
    "sg:city":"Winnipeg",
    "sg:classifiers":[
        {
            "category":"Building & Trades",
            "subcategory":"Construction",
            "type":"Services"
        }
    ],
    "sg:phone":"+1 204 254 2222",
    "sg:postcode":"R2M 1N5",
    "sg:province":"MB",
    "sg:tags":[
        "home",
        "general",
        "improvement",
        "contractor"
    ],
    "wof:name":"Madsen Construction",
    "wof:placetype":"venue"
},
  "geometry": {"coordinates":[-97.1092224121,49.8412361145],"type":"Point"}
}