{
  "type": "Feature",
  "properties": {
    "iso:country":"CA",
    "sg:address":"62 King St W",
    "sg:city":"Dundas",
    "sg:classifiers":[
        {
            "category":"Health Services",
            "subcategory":"Doctor",
            "type":"Services"
        }
    ],
    "sg:phone":"+1 905 627 3526",
    "sg:postcode":"L9H 1T8",
    "sg:province":"ON",
    "sg:tags":[
        "physician",
        "surgeon"
    ],
    "wof:name":"Shankardass, K MD",
    "wof:placetype":"venue"
},
  "geometry": {"coordinates":[-79.9563293457,43.2662887573],"type":"Point"}
}