{
  "type": "Feature",
  "properties": {
    "iso:country":"CA",
    "sg:address":"133 Farmers Rd",
    "sg:city":"Pontypool",
    "sg:classifiers":[
        {
            "category":"Recreation",
            "type":"Entertainment"
        }
    ],
    "sg:phone":"+1 705 932 2226",
    "sg:postcode":"L0A 1K0",
    "sg:province":"ON",
    "sg:tags":[
        "riding",
        "academy"
    ],
    "wof:name":"Streamliner Horse Farm",
    "wof:placetype":"venue"
},
  "geometry": {"coordinates":[-78.5516586304,44.1178016663],"type":"Point"}
}