{
  "type": "Feature",
  "properties": {
    "addr:full":"Toronto ON M4M 3L1",
    "addr:postcode":"m4m 3l1",
    "iso:country":"CA",
    "sg:city":"Toronto",
    "sg:classifiers":[
        {
            "category":"Wholesale",
            "subcategory":"Construction Materials",
            "type":"Manufacturing & Wholesale Goods"
        }
    ],
    "sg:phone":"+1 416 686 2399",
    "sg:postcode":"M4M 3L1",
    "sg:province":"ON",
    "sg:tags":[
        "tile"
    ],
    "wof:name":"Fired Earth",
    "wof:placetype":"venue"
},
  "geometry": {"coordinates":[-79.34131600000001,43.663666],"type":"Point"}
}