{
  "type": "Feature",
  "properties": {
    "addr:full":"22242 48 Ave Langley BC V3A 3N5",
    "addr:housenumber":"22242",
    "addr:postcode":"v3a 3n5",
    "addr:street":"48 Ave",
    "iso:country":"CA",
    "sg:address":"22242 48 Ave",
    "sg:city":"Langley",
    "sg:classifiers":[
        {
            "category":"Banks & Credit Unions",
            "subcategory":"Investment Brokerage",
            "type":"Services"
        }
    ],
    "sg:phone":"+1 604 534 9581",
    "sg:postcode":"V3A 3N5",
    "sg:province":"BC",
    "sg:tags":[
        "consultant",
        "planning",
        "financial"
    ],
    "wof:name":"Aldergrove Insurance Svc Ltd",
    "wof:placetype":"venue"
},
  "geometry": {"coordinates":[-122.60717,49.089252],"type":"Point"}
}