{
  "type": "Feature",
  "properties": {
    "addr:full":"Port Hardy BC V0N 2P0",
    "addr:postcode":"v0n 2p0",
    "iso:country":"CA",
    "sg:city":"Port Hardy",
    "sg:classifiers":[
        {
            "category":"Manufacturing",
            "subcategory":"Food",
            "type":"Manufacturing & Wholesale Goods"
        }
    ],
    "sg:phone":"+1 250 949 6630",
    "sg:postcode":"V0N 2P0",
    "sg:province":"BC",
    "sg:tags":[
        "packer",
        "fish"
    ],
    "wof:name":"Scarlet Point Seafood Inc",
    "wof:placetype":"venue"
},
  "geometry": {"coordinates":[-127.4948349,50.716178894],"type":"Point"}
}