{
  "type": "Feature",
  "properties": {
    "addr:full":"Cochrane AB T4C 2C2",
    "addr:postcode":"t4c 2c2",
    "iso:country":"CA",
    "sg:city":"Cochrane",
    "sg:classifiers":[
        {
            "category":"Manufacturing",
            "subcategory":"Printing",
            "type":"Manufacturing & Wholesale Goods"
        }
    ],
    "sg:phone":"+1 403 932 6588",
    "sg:postcode":"T4C 2C2",
    "sg:province":"AB",
    "sg:tags":[
        "newspaper"
    ],
    "wof:name":"Cochrane Eagle",
    "wof:placetype":"venue"
},
  "geometry": {"coordinates":[-114.464179993,51.1863517761],"type":"Point"}
}