{
  "type": "Feature",
  "properties": {
    "addr:full":"Vancouver BC V5X 4M2",
    "addr:postcode":"v5x 4m2",
    "iso:country":"CA",
    "sg:city":"Vancouver",
    "sg:classifiers":[
        {
            "category":"Manufacturing",
            "subcategory":"Food",
            "type":"Manufacturing & Wholesale Goods"
        }
    ],
    "sg:phone":"+1 604 327 2221",
    "sg:postcode":"V5X 4M2",
    "sg:province":"BC",
    "sg:tags":[
        "product",
        "manufacturer"
    ],
    "wof:name":"New Century Food & Paper",
    "wof:placetype":"venue"
},
  "geometry": {"coordinates":[-123.09793853799999,49.2077827454],"type":"Point"}
}