{
  "type": "Feature",
  "properties": {
    "addr:full":"1717 3 Ave SE High River AB T1V 1Y3",
    "addr:housenumber":"1717",
    "addr:postcode":"t1v 1y3",
    "addr:street":"3 Ave Se",
    "iso:country":"CA",
    "sg:address":"1717 3 Ave SE",
    "sg:city":"High River",
    "sg:classifiers":[
        {
            "category":"Building & Trades",
            "subcategory":"Construction",
            "type":"Services"
        }
    ],
    "sg:phone":"+1 403 652 3428",
    "sg:postcode":"T1V 1Y3",
    "sg:province":"AB",
    "sg:tags":[
        "general",
        "contractor"
    ],
    "wof:name":"Timber Wolf Construction",
    "wof:placetype":"venue"
},
  "geometry": {"coordinates":[-113.840377808,50.5803070068],"type":"Point"}
}