{
  "type": "Feature",
  "properties": {
    "addr:full":"Woodbridge ON L4L 8N1",
    "addr:postcode":"l4l 8n1",
    "iso:country":"CA",
    "sg:city":"Woodbridge",
    "sg:classifiers":[
        {
            "category":"Wholesale",
            "subcategory":"Fruits & Vegetables",
            "type":"Manufacturing & Wholesale Goods"
        }
    ],
    "sg:phone":"+1 416 740 0111",
    "sg:postcode":"L4L 8N1",
    "sg:province":"ON",
    "wof:name":"Atlantis Produce",
    "wof:placetype":"venue"
},
  "geometry": {"coordinates":[-79.6122970581,43.7712135315],"type":"Point"}
}