{
  "type": "Feature",
  "properties": {
    "iso:country":"CA",
    "sg:address":"5101 Dundas St E",
    "sg:city":"Thorndale",
    "sg:classifiers":[
        {
            "category":"Wholesale",
            "subcategory":"Plants",
            "type":"Manufacturing & Wholesale Goods"
        }
    ],
    "sg:phone":"+1 519 268 7542",
    "sg:postcode":"N0M 2P0",
    "sg:province":"ON",
    "sg:tags":[
        "florist"
    ],
    "wof:name":"Jansen's Greenhouses Retail",
    "wof:placetype":"venue"
},
  "geometry": {"coordinates":[-81.1411819458,43.1051330566],"type":"Point"}
}