{
  "type": "Feature",
  "properties": {
    "addr:full":"1282 Av Maguire Sillery QC G1T 1Z3",
    "addr:housenumber":"1282",
    "addr:postcode":"g1t 1z3",
    "addr:street":"Av Maguire",
    "iso:country":"CA",
    "sg:address":"1282 Av Maguire",
    "sg:city":"Sillery",
    "sg:classifiers":[
        {
            "category":"Restaurant",
            "type":"Food & Drink"
        }
    ],
    "sg:phone":"+1 418 687 9725",
    "sg:postcode":"G1T 1Z3",
    "sg:province":"QC",
    "wof:name":"Rameau D'Olivier",
    "wof:placetype":"venue"
},
  "geometry": {"coordinates":[-71.25215900000001,46.781738],"type":"Point"}
}