{
  "type": "Feature",
  "properties": {
    "addr:full":"1850 Rue Le Caron Trois-Rivieres QC G9A 1M1",
    "addr:housenumber":"1850",
    "addr:postcode":"g9a 1m1",
    "addr:street":"Rue Le Caron Trois-Rivieres",
    "iso:country":"CA",
    "sg:address":"1850 Rue Le Caron",
    "sg:city":"Trois-Rivieres",
    "sg:classifiers":[
        {
            "category":"Education",
            "subcategory":"School",
            "type":"Public Place"
        }
    ],
    "sg:phone":"+1 819 374 4009",
    "sg:postcode":"G9A 1M1",
    "sg:province":"QC",
    "wof:name":"Ecole Des Petits Chanteurs",
    "wof:placetype":"venue"
},
  "geometry": {"coordinates":[-72.5506057739,46.3573036194],"type":"Point"}
}