{
  "type": "Feature",
  "properties": {
    "addr:full":"174 Rue Notre-Dame Repentigny QC J6A 2P7",
    "addr:housenumber":"174",
    "addr:postcode":"j6a 2p7",
    "addr:street":"Rue Notre-Dame",
    "iso:country":"CA",
    "sg:address":"174 Rue Notre-Dame",
    "sg:city":"Repentigny",
    "sg:classifiers":[
        {
            "category":"Professional",
            "subcategory":"Business Services",
            "type":"Services"
        }
    ],
    "sg:phone":"+1 450 654 8953",
    "sg:postcode":"J6A 2P7",
    "sg:province":"QC",
    "sg:tags":[
        "interior",
        "consultant",
        "design",
        "decorator",
        "furniture"
    ],
    "wof:name":"Meubles Claude Clermont",
    "wof:placetype":"venue"
},
  "geometry": {"coordinates":[-73.4683685303,45.7182998657],"type":"Point"}
}