{
  "type": "Feature",
  "properties": {
    "addr:full":"2447 Apollo Rd Westbank BC V4T 1P7",
    "addr:housenumber":"2447",
    "addr:postcode":"v4t 1p7",
    "addr:street":"Apollo Rd",
    "iso:country":"CA",
    "sg:address":"2447 Apollo Rd",
    "sg:city":"Westbank",
    "sg:classifiers":[
        {
            "category":"Retail",
            "subcategory":"Auto Repair",
            "type":"Services"
        }
    ],
    "sg:phone":"+1 250 768 4485",
    "sg:postcode":"V4T 1P7",
    "sg:province":"BC",
    "sg:tags":[
        "repairing",
        "automobile"
    ],
    "wof:name":"Fifth Avenue Auto",
    "wof:placetype":"venue"
},
  "geometry": {"coordinates":[-119.627235,49.83123],"type":"Point"}
}