{
  "type": "Feature",
  "properties": {
    "addr:full":"Carnduff SK S0C 0S0",
    "addr:postcode":"s0c 0s0",
    "addr:street":"Carnduff",
    "iso:country":"CA",
    "sg:city":"Carnduff",
    "sg:classifiers":[
        {
            "category":"Retail",
            "subcategory":"Laundry & Dry Cleaning",
            "type":"Services"
        }
    ],
    "sg:phone":"+1 306 482 5107",
    "sg:postcode":"S0C 0S0",
    "sg:province":"SK",
    "sg:tags":[
        "cleaners",
        "oil",
        "well",
        "rug",
        "carpet"
    ],
    "wof:name":"Greg Cousins Construction Ltd",
    "wof:placetype":"venue"
},
  "geometry": {"coordinates":[-101.799049,49.177223],"type":"Point"}
}