{
  "type": "Feature",
  "properties": {
    "addr:full":"314 Queenston Rd Hamilton ON L8K 1H5",
    "addr:housenumber":"314",
    "addr:postcode":"l8k 1h5",
    "addr:street":"Queenston Rd",
    "iso:country":"CA",
    "sg:address":"314 Queenston Rd",
    "sg:city":"Hamilton",
    "sg:classifiers":[
        {
            "category":"Shopping",
            "subcategory":"Computers & Home Electronics",
            "type":"Retail Goods"
        }
    ],
    "sg:phone":"+1 905 549 6060",
    "sg:postcode":"L8K 1H5",
    "sg:province":"ON",
    "sg:tags":[
        "video",
        "disc",
        "tape",
        "software"
    ],
    "wof:name":"Hollywood Star Video",
    "wof:placetype":"venue"
},
  "geometry": {"coordinates":[-79.790466,43.233704],"type":"Point"}
}