{
  "type": "Feature",
  "properties": {
    "addr:full":"1300 Bridge St Fort Erie ON L2A 5M4",
    "addr:housenumber":"1300",
    "addr:postcode":"l2a 5m4",
    "addr:street":"Bridge St",
    "iso:country":"CA",
    "sg:address":"1300 Bridge St",
    "sg:city":"Fort Erie",
    "sg:classifiers":[
        {
            "category":"Government",
            "subcategory":"Office",
            "type":"Public Place"
        }
    ],
    "sg:phone":"+1 905 871 3887",
    "sg:postcode":"L2A 5M4",
    "sg:province":"ON",
    "sg:tags":[
        "village"
    ],
    "wof:name":"Niagara Municipality Landfill",
    "wof:placetype":"venue"
},
  "geometry": {"coordinates":[-79.00412,42.925579],"type":"Point"}
}