{
  "type": "Feature",
  "properties": {
    "iso:country":"CA",
    "sg:city":"Lanigan",
    "sg:classifiers":[
        {
            "category":"Farming",
            "subcategory":"Livestock Farm",
            "type":"Manufacturing & Wholesale Goods"
        }
    ],
    "sg:phone":"+1 306 365 4281",
    "sg:postcode":"S0K 2M0",
    "sg:province":"SK",
    "sg:tags":[
        "feeding"
    ],
    "wof:name":"Pound-Maker Adventures Ltd",
    "wof:placetype":"venue"
},
  "geometry": {"coordinates":[-105.036155701,51.8458061218],"type":"Point"}
}