{
  "type": "Feature",
  "properties": {
    "addr:full":"840 9 Ave SW Calgary AB T2P 1L7",
    "addr:housenumber":"840",
    "addr:postcode":"t2p 1l7",
    "addr:street":"9 Ave Sw",
    "iso:country":"CA",
    "sg:address":"840 9 Ave SW",
    "sg:city":"Calgary",
    "sg:classifiers":[
        {
            "category":"Food & Beverages",
            "subcategory":"Groceries & Convenience Stores",
            "type":"Retail Goods"
        }
    ],
    "sg:phone":"+1 403 262 2662",
    "sg:postcode":"T2P 1L7",
    "sg:province":"AB",
    "sg:tags":[
        "grocer"
    ],
    "wof:name":"Handee Food Store",
    "wof:placetype":"venue"
},
  "geometry": {"coordinates":[-114.080124,51.045223],"type":"Point"}
}