{
  "type": "Feature",
  "properties": {
    "addr:full":"Balmertown ON P0V 1C0",
    "addr:postcode":"p0v 1c0",
    "iso:country":"CA",
    "sg:city":"Balmertown",
    "sg:classifiers":[
        {
            "category":"Travel",
            "subcategory":"Campground",
            "type":"Entertainment"
        }
    ],
    "sg:phone":"+1 807 735 2869",
    "sg:postcode":"P0V 1C0",
    "sg:province":"ON",
    "wof:name":"Chukuni River Tent & Trailer",
    "wof:placetype":"venue"
},
  "geometry": {"coordinates":[-93.7400970459,51.0598678589],"type":"Point"}
}