{
  "type": "Feature",
  "properties": {
    "addr:full":"390 Pleasant St Dartmouth NS B2Y 3S5",
    "addr:housenumber":"390",
    "addr:postcode":"b2y 3s5",
    "addr:street":"Pleasant St",
    "iso:country":"CA",
    "sg:address":"390 Pleasant St",
    "sg:city":"Dartmouth",
    "sg:classifiers":[
        {
            "category":"Autos & Motor Vehicles",
            "subcategory":"Fuel & Gas Station",
            "type":"Retail Goods"
        }
    ],
    "sg:phone":"+1 902 466 8570",
    "sg:postcode":"B2Y 3S5",
    "sg:province":"NS",
    "sg:tags":[
        "oil"
    ],
    "wof:name":"Pleasant Street Esso & Store",
    "wof:placetype":"venue"
},
  "geometry": {"coordinates":[-63.5454444885,44.6481132507],"type":"Point"}
}