{
  "type": "Feature",
  "properties": {
    "iso:country":"CA",
    "sg:city":"Burnaby",
    "sg:classifiers":[
        {
            "category":"Health Services",
            "subcategory":"Doctor",
            "type":"Services"
        }
    ],
    "sg:phone":"+1 604 299 8817",
    "sg:postcode":"V5C 2H7",
    "sg:province":"BC",
    "sg:tags":[
        "dentist"
    ],
    "wof:name":"Chow, Pearl DDS",
    "wof:placetype":"venue"
},
  "geometry": {"coordinates":[-123.020515,49.281284],"type":"Point"}
}