{
  "type": "Feature",
  "properties": {
    "addr:full":"109 St Princess Elizabeth Ave # 320 Edmonton AB T5G 3A6",
    "addr:housenumber":"109;320",
    "addr:postcode":"t5g 3a6",
    "addr:street":"St Princess Elizabeth Ave #",
    "iso:country":"CA",
    "sg:address":"109 St Princess Elizabeth Ave # 320",
    "sg:city":"Edmonton",
    "sg:classifiers":[
        {
            "category":"Real Estate",
            "subcategory":"Real Estate Operator",
            "type":"Services"
        }
    ],
    "sg:phone":"+1 780 479 5955",
    "sg:postcode":"T5G 3A6",
    "sg:province":"AB",
    "sg:tags":[
        "mall",
        "shopping",
        "center"
    ],
    "wof:name":"Kingsway Garden Mall",
    "wof:placetype":"venue"
},
  "geometry": {"coordinates":[-113.49037199999999,53.546219],"type":"Point"}
}