{
  "type": "Feature",
  "properties": {
    "addr:full":"Toronto ON M4T 2Y3",
    "addr:postcode":"m4t 2y3",
    "iso:country":"CA",
    "sg:city":"Toronto",
    "sg:classifiers":[
        {
            "category":"Professional",
            "subcategory":"Lawyer & Legal Services",
            "type":"Services"
        }
    ],
    "sg:phone":"+1 416 923 1776",
    "sg:postcode":"M4T 2Y3",
    "sg:province":"ON",
    "sg:tags":[
        "attorney"
    ],
    "wof:name":"Legge & Legge",
    "wof:placetype":"venue"
},
  "geometry": {"coordinates":[-79.390961,43.688591],"type":"Point"}
}