{
  "type": "Feature",
  "properties": {
    "addr:full":"1411 Northwest Blvd Creston BC V0B 1G6",
    "addr:housenumber":"1411",
    "addr:postcode":"bc v0b 1g6",
    "addr:street":"Northwest Blvd",
    "iso:country":"CA",
    "sg:address":"1411 Northwest Blvd",
    "sg:city":"Creston",
    "sg:phone":"+1 250 428 7131",
    "sg:postcode":"V0B 1G6",
    "sg:province":"BC",
    "sg:tags":[
        "oil"
    ],
    "wof:name":"Shell Canada Products Ltd",
    "wof:placetype":"venue"
},
  "geometry": {"coordinates":[-116.52381099999999,49.112648],"type":"Point"}
}