{
  "type": "Feature",
  "properties": {
    "addr:full":"259 Erie St Stratford ON N5A 2M9",
    "addr:housenumber":"259",
    "addr:postcode":"n5a 2m9",
    "addr:street":"Erie St",
    "iso:country":"CA",
    "sg:address":"259 Erie St",
    "sg:city":"Stratford",
    "sg:classifiers":[
        {
            "category":"Personal",
            "subcategory":"Barber",
            "type":"Services"
        }
    ],
    "sg:phone":"+1 519 273 0223",
    "sg:postcode":"N5A 2M9",
    "sg:province":"ON",
    "wof:name":"Gus Mc Cully Men's Salon",
    "wof:placetype":"venue"
},
  "geometry": {"coordinates":[-80.98745,43.365704],"type":"Point"}
}