{
  "type": "Feature",
  "properties": {
    "addr:full":"1701 Rue Berri Montreal QC H2L 4E9",
    "addr:housenumber":"1701",
    "addr:postcode":"h2l 4e9",
    "addr:street":"Rue Berri",
    "iso:country":"CA",
    "sg:address":"1701 Rue Berri",
    "sg:city":"Montreal",
    "sg:classifiers":[
        {
            "category":"Freight",
            "type":"Transportation"
        }
    ],
    "sg:phone":"+1 514 844 4040",
    "sg:postcode":"H2L 4E9",
    "sg:province":"QC",
    "sg:tags":[
        "courier"
    ],
    "wof:name":"Messageries Parbus",
    "wof:placetype":"venue"
},
  "geometry": {"coordinates":[-73.563309,45.516541],"type":"Point"}
}