{
  "type": "Feature",
  "properties": {
    "addr:full":"4916 Boul Saint-Jean Pierrefonds QC H9H 4B2",
    "addr:housenumber":"4916",
    "addr:postcode":"h9h 4b2",
    "addr:street":"Boul Saint-Jean",
    "iso:country":"CA",
    "sg:address":"4916 Boul Saint-Jean",
    "sg:city":"Pierrefonds",
    "sg:classifiers":[
        {
            "category":"Retail",
            "subcategory":"Laundry & Dry Cleaning",
            "type":"Services"
        }
    ],
    "sg:phone":"+1 514 626 2995",
    "sg:postcode":"H9H 4B2",
    "sg:province":"QC",
    "sg:tags":[
        "cleaners"
    ],
    "wof:name":"Nettoyeur Daoust 26",
    "wof:placetype":"venue"
},
  "geometry": {"coordinates":[-73.851479,45.490719],"type":"Point"}
}