{
  "type": "Feature",
  "properties": {
    "addr:full":"572 Rue Des Rapides Rimouski QC G5L 7V6",
    "addr:housenumber":"572",
    "addr:postcode":"g5l 7v6",
    "addr:street":"Rue Des Rapides",
    "iso:country":"CA",
    "sg:address":"572 Rue Des Rapides",
    "sg:city":"Rimouski",
    "sg:classifiers":[
        {
            "category":"Shopping",
            "subcategory":"Computers & Home Electronics",
            "type":"Retail Goods"
        }
    ],
    "sg:phone":"+1 418 721 4573",
    "sg:postcode":"G5L 7V6",
    "sg:province":"QC",
    "sg:tags":[
        "equipment",
        "television",
        "electronic",
        "supply"
    ],
    "wof:name":"Gagnon Radio Tv",
    "wof:placetype":"venue"
},
  "geometry": {"coordinates":[-68.5502166748,48.4289283752],"type":"Point"}
}