{
  "type": "Feature",
  "properties": {
    "iso:country":"CA",
    "sg:address":"200 Osborne St N",
    "sg:city":"Winnipeg",
    "sg:classifiers":[
        {
            "category":"Organizations",
            "subcategory":"Non-profit Organization",
            "type":"Services"
        }
    ],
    "sg:phone":"+1 204 944 6235",
    "sg:postcode":"R3C 1V4",
    "sg:province":"MB",
    "sg:tags":[
        "information",
        "addiction",
        "center",
        "alcoholism",
        "treatment"
    ],
    "wof:name":"Addictions Foundation of MB",
    "wof:placetype":"venue"
},
  "geometry": {"coordinates":[-97.1501922607,49.8856582642],"type":"Point"}
}