{
  "type": "Feature",
  "properties": {
    "addr:full":"2650 Bayview Ave North York ON M2L 1B9",
    "addr:housenumber":"2650",
    "addr:postcode":"m2l 1b9",
    "addr:street":"Bayview Ave",
    "iso:country":"CA",
    "sg:address":"2650 Bayview Ave",
    "sg:city":"North York",
    "sg:classifiers":[
        {
            "category":"Manufacturing",
            "subcategory":"Apparel",
            "type":"Manufacturing & Wholesale Goods"
        }
    ],
    "sg:phone":"+1 416 224 8083",
    "sg:postcode":"M2L 1B9",
    "sg:province":"ON",
    "sg:tags":[
        "swimwear",
        "accessory"
    ],
    "wof:name":"Sunsmart Inc",
    "wof:placetype":"venue"
},
  "geometry": {"coordinates":[-79.385864,43.755486],"type":"Point"}
}