{
  "type": "Feature",
  "properties": {
    "addr:full":"3524 Dutch Village Rd Halifax NS B3N 2S1",
    "addr:housenumber":"3524",
    "addr:postcode":"b3n 2s1",
    "addr:street":"Dutch Village Rd",
    "iso:country":"CA",
    "sg:address":"3524 Dutch Village Rd",
    "sg:city":"Halifax",
    "sg:classifiers":[
        {
            "category":"Organizations",
            "subcategory":"Religious Organization",
            "type":"Services"
        }
    ],
    "sg:phone":"+1 902 443 7123",
    "sg:postcode":"B3N 2S1",
    "sg:province":"NS",
    "sg:tags":[
        "church"
    ],
    "wof:name":"Fairview United Church",
    "wof:placetype":"venue"
},
  "geometry": {"coordinates":[-63.632221,44.656132],"type":"Point"}
}