{
  "type": "Feature",
  "properties": {
    "iso:country":"CA",
    "sg:address":"109 1st Ave W",
    "sg:city":"Kindersley",
    "sg:classifiers":[
        {
            "category":"Health Services",
            "subcategory":"Chiropractor",
            "type":"Services"
        }
    ],
    "sg:phone":"+1 306 463 2046",
    "sg:postcode":"S0L 1S0",
    "sg:province":"SK",
    "wof:name":"Kindersley Chiropractic Office",
    "wof:placetype":"venue"
},
  "geometry": {"coordinates":[-109.158180237,51.4640960693],"type":"Point"}
}