{
  "type": "Feature",
  "properties": {
    "addr:full":"190 Rue Tourigny Plessisville QC G6L 2Y4",
    "addr:housenumber":"190",
    "addr:postcode":"g6l 2y4",
    "addr:street":"Rue Tourigny",
    "iso:country":"CA",
    "sg:address":"190 Rue Tourigny",
    "sg:city":"Plessisville",
    "sg:classifiers":[
        {
            "category":"Home & Garden",
            "subcategory":"Household Appliances",
            "type":"Retail Goods"
        }
    ],
    "sg:phone":"+1 819 362 2823",
    "sg:postcode":"G6L 2Y4",
    "sg:province":"QC",
    "wof:name":"Caron Service Electromenager",
    "wof:placetype":"venue"
},
  "geometry": {"coordinates":[-71.77636699999999,46.243683],"type":"Point"}
}