{
  "type": "Feature",
  "properties": {
    "iso:country":"CA",
    "sg:address":"5275 John Lucas Dr",
    "sg:city":"Burlington",
    "sg:classifiers":[
        {
            "category":"Manufacturing",
            "subcategory":"Chemicals & Compounds",
            "type":"Manufacturing & Wholesale Goods"
        }
    ],
    "sg:phone":"+1 905 319 2234",
    "sg:postcode":"L7L 6A8",
    "sg:province":"ON",
    "wof:name":"Controlchem Canada Ltd",
    "wof:placetype":"venue"
},
  "geometry": {"coordinates":[-79.770652771,43.3925361633],"type":"Point"}
}