{
  "type": "Feature",
  "properties": {
    "addr:full":"299 1st St NW Minnedosa MB R0J 1E0",
    "addr:housenumber":"299",
    "addr:postcode":"r0j 1e0",
    "addr:street":"1St St Nw Minnedosa",
    "iso:country":"CA",
    "sg:address":"299 1st St NW",
    "sg:city":"Minnedosa",
    "sg:classifiers":[
        {
            "category":"Home & Garden",
            "subcategory":"Building Materials",
            "type":"Retail Goods"
        }
    ],
    "sg:phone":"+1 204 867 3853",
    "sg:postcode":"R0J 1E0",
    "sg:province":"MB",
    "sg:tags":[
        "mixed",
        "concrete"
    ],
    "wof:name":"Prairie Concrete",
    "wof:placetype":"venue"
},
  "geometry": {"coordinates":[-99.8386230469,50.2470207214],"type":"Point"}
}