{
  "type": "Feature",
  "properties": {
    "addr:full":"18 Sydney Rd Port Hawkesbury NS B9A 3A4",
    "addr:housenumber":"18",
    "addr:postcode":"b9a 3a4",
    "addr:street":"Sydney Rd",
    "iso:country":"CA",
    "sg:address":"18 Sydney Rd",
    "sg:city":"Port Hawkesbury",
    "sg:classifiers":[
        {
            "category":"Health Services",
            "subcategory":"Medical Lab",
            "type":"Services"
        }
    ],
    "sg:phone":"+1 902 625 1897",
    "sg:postcode":"B9A 3A4",
    "sg:province":"NS",
    "wof:name":"Boudreau Denture Clinic",
    "wof:placetype":"venue"
},
  "geometry": {"coordinates":[-61.355778,45.611362],"type":"Point"}
}