{
  "type": "Feature",
  "properties": {
    "addr:full":"25 2nd St SW Portage LA Prairie MB R1N 2A2",
    "addr:housenumber":"25",
    "addr:postcode":"r1n 2a2",
    "addr:street":"2Nd St Sw",
    "iso:country":"CA",
    "sg:address":"25 2nd St SW",
    "sg:city":"Portage LA Prairie",
    "sg:classifiers":[
        {
            "category":"Organizations",
            "subcategory":"Religious Organization",
            "type":"Services"
        }
    ],
    "sg:phone":"+1 204 857 6523",
    "sg:postcode":"R1N 2A2",
    "sg:province":"MB",
    "sg:tags":[
        "church"
    ],
    "wof:name":"Christ Church",
    "wof:placetype":"venue"
},
  "geometry": {"coordinates":[-98.2939453125,49.9725341797],"type":"Point"}
}