{
  "type": "Feature",
  "properties": {
    "iso:country":"CA",
    "sg:city":"White Rock",
    "sg:classifiers":[
        {
            "category":"Restaurant",
            "type":"Food & Drink"
        }
    ],
    "sg:phone":"+1 604 541 9010",
    "sg:postcode":"V4B 1P8",
    "sg:province":"BC",
    "wof:name":"Clancy's Tea Cosy",
    "wof:placetype":"venue"
},
  "geometry": {"coordinates":[-122.800338745,49.0237045288],"type":"Point"}
}