{
  "type": "Feature",
  "properties": {
    "addr:full":"63 Grand Ave N Cambridge ON N1S 2L1",
    "addr:housenumber":"63",
    "addr:postcode":"n1s 2l1",
    "addr:street":"Grand Ave N",
    "iso:country":"CA",
    "sg:address":"63 Grand Ave N",
    "sg:city":"Cambridge",
    "sg:classifiers":[
        {
            "category":"Organizations",
            "subcategory":"Religious Organization",
            "type":"Services"
        }
    ],
    "sg:phone":"+1 519 623 1604",
    "sg:postcode":"N1S 2L1",
    "sg:province":"ON",
    "sg:tags":[
        "church"
    ],
    "wof:name":"St Paul's Lutheran Church",
    "wof:placetype":"venue"
},
  "geometry": {"coordinates":[-80.31745147709999,43.3614234924],"type":"Point"}
}