{
  "type": "Feature",
  "properties": {
    "addr:full":"12 Maple Valley Rd Corner Brook NL A2H 6J3",
    "addr:housenumber":"12",
    "addr:postcode":"a2h 6j3",
    "addr:street":"Maple Valley Rd",
    "iso:country":"CA",
    "sg:address":"12 Maple Valley Rd",
    "sg:city":"Corner Brook",
    "sg:classifiers":[
        {
            "category":"Wholesale",
            "subcategory":"Groceries",
            "type":"Manufacturing & Wholesale Goods"
        }
    ],
    "sg:phone":"+1 709 634 5191",
    "sg:postcode":"A2H 6J3",
    "sg:province":"NL",
    "sg:tags":[
        "grocer"
    ],
    "wof:name":"Green Lantern Wholesalers Ltd",
    "wof:placetype":"venue"
},
  "geometry": {"coordinates":[-57.9180183411,48.9528274536],"type":"Point"}
}