{
  "type": "Feature",
  "properties": {
    "addr:full":"307 3rd St Hwy 48 E Wawota SK S0G 5A0",
    "addr:housenumber":"307",
    "addr:postcode":"s0g 5a0",
    "addr:street":"3Rd St Hwy 48 E Wawota",
    "iso:country":"CA",
    "sg:address":"307 3rd St Hwy 48 E",
    "sg:city":"Wawota",
    "sg:classifiers":[
        {
            "category":"Wholesale",
            "subcategory":"Machinery & Supplies",
            "type":"Manufacturing & Wholesale Goods"
        }
    ],
    "sg:phone":"+1 306 739 2377",
    "sg:postcode":"S0G 5A0",
    "sg:province":"SK",
    "sg:tags":[
        "agricultural",
        "implement"
    ],
    "wof:name":"Wawota Garage Ltd",
    "wof:placetype":"venue"
},
  "geometry": {"coordinates":[-102.028183,49.90321],"type":"Point"}
}