{
  "type": "Feature",
  "properties": {
    "addr:full":"80 Mclean St Red Deer AB T4R 1T7",
    "addr:housenumber":"80",
    "addr:postcode":"t4r 1t7",
    "addr:street":"Mclean St",
    "iso:country":"CA",
    "sg:address":"80 Mclean St",
    "sg:city":"Red Deer",
    "sg:classifiers":[
        {
            "category":"Retail",
            "subcategory":"Repair Shop",
            "type":"Services"
        }
    ],
    "sg:phone":"+1 403 342 6295",
    "sg:postcode":"T4R 1T7",
    "sg:province":"AB",
    "sg:tags":[
        "welding"
    ],
    "wof:name":"Wildrose Welding Ltd",
    "wof:placetype":"venue"
},
  "geometry": {"coordinates":[-113.77188099999999,52.256432],"type":"Point"}
}