{
  "type": "Feature",
  "properties": {
    "addr:full":"Mckenzie Portage Rd Keewatin ON P0X 1C0",
    "addr:postcode":"p0x 1c0",
    "addr:street":"Mckenzie Portage Rd",
    "iso:country":"CA",
    "sg:address":"Mckenzie Portage Rd",
    "sg:city":"Keewatin",
    "sg:classifiers":[
        {
            "category":"Travel",
            "subcategory":"Hotels & Motels",
            "type":"Entertainment"
        }
    ],
    "sg:phone":"+1 807 543 2229",
    "sg:postcode":"P0X 1C0",
    "sg:province":"ON",
    "sg:tags":[
        "resort"
    ],
    "wof:name":"Sun Valley Lodge",
    "wof:placetype":"venue"
},
  "geometry": {"coordinates":[-94.55727386469999,49.7577133179],"type":"Point"}
}