{
  "type": "Feature",
  "properties": {
    "addr:full":"7958 Rue Hochelaga Montreal QC H1L 2K8",
    "addr:housenumber":"7958",
    "addr:postcode":"h1l 2k8",
    "addr:street":"Rue Hochelaga",
    "iso:country":"CA",
    "sg:address":"7958 Rue Hochelaga",
    "sg:city":"Montreal",
    "sg:classifiers":[
        {
            "category":"Organizations",
            "subcategory":"Non-profit Organization",
            "type":"Services"
        }
    ],
    "sg:phone":"+1 514 354 5131",
    "sg:postcode":"H1L 2K8",
    "sg:province":"QC",
    "sg:tags":[
        "charitable",
        "institution",
        "association"
    ],
    "wof:name":"Chez-Nous DE Mercier-Est",
    "wof:placetype":"venue"
},
  "geometry": {"coordinates":[-73.52372,45.593792],"type":"Point"}
}