{
  "type": "Feature",
  "properties": {
    "addr:full":"86 Glencoe Dr Mount Pearl NL A1N 4S9",
    "addr:housenumber":"86",
    "addr:postcode":"a1n 4s9",
    "addr:street":"Glencoe Dr",
    "iso:country":"CA",
    "sg:address":"86 Glencoe Dr",
    "sg:city":"Mount Pearl",
    "sg:classifiers":[
        {
            "category":"Wholesale",
            "subcategory":"Machinery & Supplies",
            "type":"Manufacturing & Wholesale Goods"
        }
    ],
    "sg:phone":"+1 709 747 0377",
    "sg:postcode":"A1N 4S9",
    "sg:province":"NL",
    "sg:tags":[
        "salon",
        "beauty"
    ],
    "wof:name":"O'Keefe Agencies Ltd",
    "wof:placetype":"venue"
},
  "geometry": {"coordinates":[-52.8451881409,47.5201187134],"type":"Point"}
}