{
  "type": "Feature",
  "properties": {
    "addr:full":"500 Laurier Ave #330 Milton ON L9T 4R3",
    "addr:housenumber":"500",
    "addr:postcode":"l9t 4r3",
    "addr:street":"Laurier Ave # 330",
    "iso:country":"CA",
    "sg:address":"500 Laurier Ave #330",
    "sg:city":"Milton",
    "sg:classifiers":[
        {
            "category":"Food & Beverages",
            "subcategory":"Groceries & Convenience Stores",
            "type":"Retail Goods"
        }
    ],
    "sg:phone":"+1 905 876 1117",
    "sg:postcode":"L9T 4R3",
    "sg:province":"ON",
    "sg:tags":[
        "grocer"
    ],
    "wof:name":"A & P Food Stores",
    "wof:placetype":"venue"
},
  "geometry": {"coordinates":[-79.86199951170001,43.5090255737],"type":"Point"}
}