{
  "type": "Feature",
  "properties": {
    "addr:full":"3236 Mcbride Hwy 16 E Mcbride BC V0J 2E0",
    "addr:housenumber":"3236",
    "addr:postcode":"v0j 2e0",
    "addr:street":"Mcbride Hwy 16 E",
    "iso:country":"CA",
    "sg:address":"3236 Mcbride Hwy 16 E",
    "sg:city":"Mcbride",
    "sg:classifiers":[
        {
            "category":"Retail",
            "subcategory":"Animal Services",
            "type":"Services"
        }
    ],
    "sg:phone":"+1 250 569 3319",
    "sg:postcode":"V0J 2E0",
    "sg:province":"BC",
    "sg:tags":[
        "pet",
        "boarding",
        "sitting"
    ],
    "wof:name":"Robson Valley Pet Hostel",
    "wof:placetype":"venue"
},
  "geometry": {"coordinates":[-120.16211699999999,53.30442],"type":"Point"}
}