{
  "type": "Feature",
  "properties": {
    "addr:full":"485 Barrydowne Rd # A Sudbury ON P3A 3T4",
    "addr:housenumber":"485",
    "addr:postcode":"p3a 3t4",
    "addr:street":"Barrydowne Rd # A",
    "iso:country":"CA",
    "sg:address":"485 Barrydowne Rd # A",
    "sg:city":"Sudbury",
    "sg:classifiers":[
        {
            "category":"Retail",
            "subcategory":"Car Wash",
            "type":"Services"
        }
    ],
    "sg:phone":"+1 705 524 1257",
    "sg:postcode":"P3A 3T4",
    "sg:province":"ON",
    "sg:tags":[
        "polishing",
        "automobile",
        "washing",
        "detail"
    ],
    "wof:name":"Precision Car Care",
    "wof:placetype":"venue"
},
  "geometry": {"coordinates":[-80.9443435669,46.5075454712],"type":"Point"}
}