{
  "type": "Feature",
  "properties": {
    "addr:full":"750 Appleby Line Burlington ON L7L 2Y7",
    "addr:housenumber":"750",
    "addr:postcode":"l7l 2y7",
    "addr:street":"Appleby Line",
    "iso:country":"CA",
    "sg:address":"750 Appleby Line",
    "sg:city":"Burlington",
    "sg:classifiers":[
        {
            "category":"Manufacturing",
            "subcategory":"Metals",
            "type":"Manufacturing & Wholesale Goods"
        }
    ],
    "sg:phone":"+1 905 632 2121",
    "sg:postcode":"L7L 2Y7",
    "sg:province":"ON",
    "sg:tags":[
        "grating"
    ],
    "wof:name":"Fisher & Ludlow",
    "wof:placetype":"venue"
},
  "geometry": {"coordinates":[-79.763756,43.374561],"type":"Point"}
}