{
  "type": "Feature",
  "properties": {
    "addr:full":"Toronto ON M5R 2V1",
    "addr:postcode":"m5r 2v1",
    "iso:country":"CA",
    "sg:city":"Toronto",
    "sg:classifiers":[
        {
            "category":"Shopping",
            "subcategory":"Hobbies, Toys, & Games",
            "type":"Retail Goods"
        }
    ],
    "sg:phone":"+1 416 823 0497",
    "sg:postcode":"M5R 2V1",
    "sg:province":"ON",
    "sg:tags":[
        "model",
        "supply"
    ],
    "wof:name":"Ming Ming the Hobby Store",
    "wof:placetype":"venue"
},
  "geometry": {"coordinates":[-79.40789794920001,43.6764144897],"type":"Point"}
}