{
  "type": "Feature",
  "properties": {
    "iso:country":"CA",
    "sg:address":"Hwy 13 & 39",
    "sg:city":"Weyburn",
    "sg:classifiers":[
        {
            "category":"Wholesale",
            "subcategory":"Petroleum",
            "type":"Manufacturing & Wholesale Goods"
        }
    ],
    "sg:phone":"+1 306 848 3690",
    "sg:postcode":"S4H 0V1",
    "sg:province":"SK",
    "sg:tags":[
        "oil"
    ],
    "wof:name":"CO-OP Bulk",
    "wof:placetype":"venue"
},
  "geometry": {"coordinates":[-103.858192444,49.6680297852],"type":"Point"}
}