{
  "type": "Feature",
  "properties": {
    "addr:full":"8933 Cavendish Rd Hunter River PE C0A 1N0",
    "addr:housenumber":"8933",
    "addr:postcode":"c0a 1n0",
    "addr:street":"Cavendish Rd",
    "iso:country":"CA",
    "sg:address":"8933 Cavendish Rd",
    "sg:city":"Hunter River",
    "sg:classifiers":[
        {
            "category":"Travel",
            "subcategory":"Hotels & Motels",
            "type":"Entertainment"
        }
    ],
    "sg:phone":"+1 902 963 2439",
    "sg:postcode":"C0A 1N0",
    "sg:province":"PE",
    "wof:name":"Silverwood Motel",
    "wof:placetype":"venue"
},
  "geometry": {"coordinates":[-63.343147,46.351761],"type":"Point"}
}