{
  "type": "Feature",
  "properties": {
    "addr:full":"1728 Chalkdene Grove Mississauga ON L4W 2C3",
    "addr:housenumber":"1728",
    "addr:postcode":"l4w 2c3",
    "addr:street":"Chalkdene Grove",
    "iso:country":"CA",
    "sg:address":"1728 Chalkdene Grove",
    "sg:city":"Mississauga",
    "sg:classifiers":[
        {
            "category":"Wholesale",
            "subcategory":"Machinery & Supplies",
            "type":"Manufacturing & Wholesale Goods"
        }
    ],
    "sg:phone":"+1 905 624 9118",
    "sg:postcode":"L4W 2C3",
    "sg:province":"ON",
    "sg:tags":[
        "equipment",
        "printing"
    ],
    "wof:name":"Rockwood Services",
    "wof:placetype":"venue"
},
  "geometry": {"coordinates":[-79.603905,43.636311],"type":"Point"}
}