{
  "type": "Feature",
  "properties": {
    "addr:full":"270 Sheppard Ave W North York ON M2N 1N3",
    "addr:housenumber":"270",
    "addr:postcode":"m2n 1n3",
    "addr:street":"Sheppard Ave W",
    "iso:country":"CA",
    "sg:address":"270 Sheppard Ave W",
    "sg:city":"North York",
    "sg:classifiers":[
        {
            "category":"Professional",
            "subcategory":"Lawyer & Legal Services",
            "type":"Services"
        }
    ],
    "sg:phone":"+1 416 224 9452",
    "sg:postcode":"M2N 1N3",
    "sg:province":"ON",
    "sg:tags":[
        "attorney"
    ],
    "wof:name":"Abbott, John P",
    "wof:placetype":"venue"
},
  "geometry": {"coordinates":[-79.42413330079999,43.7587089539],"type":"Point"}
}