{
  "type": "Feature",
  "properties": {
    "addr:full":"1710 Dufferin St Toronto ON M6E 3P2",
    "addr:housenumber":"1710",
    "addr:postcode":"m6e 3p2",
    "addr:street":"Dufferin St",
    "iso:country":"CA",
    "sg:address":"1710 Dufferin St",
    "sg:city":"Toronto",
    "sg:classifiers":[
        {
            "category":"Social Services",
            "type":"Services"
        }
    ],
    "sg:phone":"+1 416 658 1600",
    "sg:postcode":"M6E 3P2",
    "sg:province":"ON",
    "sg:tags":[
        "organization",
        "welfare"
    ],
    "wof:name":"Costi",
    "wof:placetype":"venue"
},
  "geometry": {"coordinates":[-79.4435958862,43.6788597107],"type":"Point"}
}