{
  "type": "Feature",
  "properties": {
    "addr:full":"30 Timber Rd Elliot Lake ON P5A 2T1",
    "addr:housenumber":"30",
    "addr:postcode":"p5a 2t1",
    "addr:street":"Timber Rd",
    "iso:country":"CA",
    "sg:address":"30 Timber Rd",
    "sg:city":"Elliot Lake",
    "sg:classifiers":[
        {
            "category":"Wholesale",
            "subcategory":"Machinery & Supplies",
            "type":"Manufacturing & Wholesale Goods"
        }
    ],
    "sg:phone":"+1 705 848 6433",
    "sg:postcode":"P5A 2T1",
    "sg:province":"ON",
    "sg:tags":[
        "janitor"
    ],
    "wof:name":"Chemnorth Systems & Svc CO",
    "wof:placetype":"venue"
},
  "geometry": {"coordinates":[-82.668358,46.402161],"type":"Point"}
}