{
  "type": "Feature",
  "properties": {
    "addr:full":"79 Rue Du Marche Salaberry-DE-Valleyfield QC J6T 1P6",
    "addr:housenumber":"79",
    "addr:postcode":"j6t 1p6",
    "addr:street":"Rue Du Marche",
    "iso:country":"CA",
    "sg:address":"79 Rue Du Marche",
    "sg:city":"Salaberry-DE-Valleyfield",
    "sg:classifiers":[
        {
            "category":"Shopping",
            "subcategory":"Luggage & Leather Goods",
            "type":"Retail Goods"
        }
    ],
    "sg:phone":"+1 450 377 2393",
    "sg:postcode":"J6T 1P6",
    "sg:province":"QC",
    "wof:name":"Metrock Valley",
    "wof:placetype":"venue"
},
  "geometry": {"coordinates":[-74.1348495483,45.2538337708],"type":"Point"}
}