{
  "type": "Feature",
  "properties": {
    "addr:full":"520 Somerset St Saint John NB E2K 2Y7",
    "addr:housenumber":"520",
    "addr:postcode":"e2k 2y7",
    "addr:street":"Somerset St",
    "iso:country":"CA",
    "sg:address":"520 Somerset St",
    "sg:city":"Saint John",
    "sg:classifiers":[
        {
            "category":"Real Estate",
            "subcategory":"Architect",
            "type":"Services"
        }
    ],
    "sg:phone":"+1 506 646 8020",
    "sg:postcode":"E2K 2Y7",
    "sg:province":"NB",
    "wof:name":"Adi Ltd",
    "wof:placetype":"venue"
},
  "geometry": {"coordinates":[-66.081406,45.288162],"type":"Point"}
}