{
  "type": "Feature",
  "properties": {
    "addr:full":"17th Ave SE & South Railway St Swift Current SK S9H 3V5",
    "addr:postcode":"s9h 3v5",
    "addr:street":"17Th Ave Se & South Railway St",
    "iso:country":"CA",
    "sg:address":"17th Ave SE & South Railway St",
    "sg:city":"Swift Current",
    "sg:classifiers":[
        {
            "category":"Government",
            "subcategory":"Office",
            "type":"Public Place"
        }
    ],
    "sg:phone":"+1 306 773 2944",
    "sg:postcode":"S9H 3V5",
    "sg:province":"SK",
    "sg:tags":[
        "recreation",
        "amusement",
        "village"
    ],
    "wof:name":"Frontier Days",
    "wof:placetype":"venue"
},
  "geometry": {"coordinates":[-107.77699279799999,50.2808685303],"type":"Point"}
}