{
  "type": "Feature",
  "properties": {
    "addr:full":"610 Herald St Victoria BC V8W 1S7",
    "addr:housenumber":"610",
    "addr:postcode":"v8w 1s7",
    "addr:street":"Herald St",
    "iso:country":"CA",
    "sg:address":"610 Herald St",
    "sg:city":"Victoria",
    "sg:classifiers":[
        {
            "category":"Autos & Motor Vehicles",
            "subcategory":"Auto Supplies",
            "type":"Retail Goods"
        }
    ],
    "sg:phone":"+1 250 382 6184",
    "sg:postcode":"V8W 1S7",
    "sg:province":"BC",
    "sg:tags":[
        "repairing",
        "automobile"
    ],
    "wof:name":"Fountain Tire",
    "wof:placetype":"venue"
},
  "geometry": {"coordinates":[-123.366653442,48.4303474426],"type":"Point"}
}