{
  "type": "Feature",
  "properties": {
    "addr:full":"1740 Mcdermott Dr Denare Beach SK S0P 0B0",
    "addr:housenumber":"1740",
    "addr:postcode":"s0p 0b0",
    "addr:street":"Mcdermott Dr Denare Beach",
    "iso:country":"CA",
    "sg:address":"1740 Mcdermott Dr",
    "sg:city":"Denare Beach",
    "sg:classifiers":[
        {
            "category":"Building & Trades",
            "subcategory":"Construction",
            "type":"Services"
        }
    ],
    "sg:phone":"+1 306 362 2224",
    "sg:postcode":"S0P 0B0",
    "sg:province":"SK",
    "sg:tags":[
        "boring",
        "drilling",
        "contractor"
    ],
    "wof:name":"Britton Bros Diamond Drilling",
    "wof:placetype":"venue"
},
  "geometry": {"coordinates":[-102.079803,54.658913],"type":"Point"}
}