{
  "type": "Feature",
  "properties": {
    "addr:full":"4 Magaguadavic Dr St George NB E5C 3H8",
    "addr:housenumber":"4",
    "addr:postcode":"e5c 3h8",
    "addr:street":"Magaguadavic Dr",
    "iso:country":"CA",
    "sg:address":"4 Magaguadavic Dr",
    "sg:city":"St George",
    "sg:classifiers":[
        {
            "category":"Shopping",
            "subcategory":"Bicycles & Sporting Goods",
            "type":"Retail Goods"
        }
    ],
    "sg:phone":"+1 506 755 3584",
    "sg:postcode":"E5C 3H8",
    "sg:province":"NB",
    "sg:tags":[
        "tackle",
        "fishing"
    ],
    "wof:name":"Rainbow Net & Rigging Ltd",
    "wof:placetype":"venue"
},
  "geometry": {"coordinates":[-66.8237,45.111759],"type":"Point"}
}