{
  "type": "Feature",
  "properties": {
    "iso:country":"CA",
    "sg:city":"Edmonton",
    "sg:classifiers":[
        {
            "category":"Personal",
            "subcategory":"Beauty Salon",
            "type":"Services"
        }
    ],
    "sg:phone":"+1 780 944 9996",
    "sg:postcode":"T5G 3C8",
    "sg:province":"AB",
    "wof:name":"Corrective Skin Care Institute",
    "wof:placetype":"venue"
},
  "geometry": {"coordinates":[-113.50308200000001,53.558346],"type":"Point"}
}