{
  "type": "Feature",
  "properties": {
    "addr:full":"530 Industrial Ave Ottawa ON K1G 0Y9",
    "addr:housenumber":"530",
    "addr:postcode":"k1g 0y9",
    "addr:street":"Industrial Ave",
    "iso:country":"CA",
    "sg:address":"530 Industrial Ave",
    "sg:city":"Ottawa",
    "sg:classifiers":[
        {
            "category":"Food & Beverages",
            "subcategory":"Groceries & Convenience Stores",
            "type":"Retail Goods"
        }
    ],
    "sg:phone":"+1 613 737 1300",
    "sg:postcode":"K1G 0Y9",
    "sg:province":"ON",
    "sg:tags":[
        "grocer"
    ],
    "wof:name":"Loeb Canada Inc",
    "wof:placetype":"venue"
},
  "geometry": {"coordinates":[-75.646332,45.411575],"type":"Point"}
}