{
  "type": "Feature",
  "properties": {
    "addr:full":"223 Boul Saint-Jean-Baptiste Chateauguay QC J6K 3B9",
    "addr:housenumber":"223",
    "addr:postcode":"j6k 3b9",
    "addr:street":"Boul Saint-Jean-Baptiste",
    "iso:country":"CA",
    "sg:address":"223 Boul Saint-Jean-Baptiste",
    "sg:city":"Chateauguay",
    "sg:classifiers":[
        {
            "category":"Home & Garden",
            "subcategory":"Building Materials",
            "type":"Retail Goods"
        }
    ],
    "sg:phone":"+1 450 692 3876",
    "sg:postcode":"J6K 3B9",
    "sg:province":"QC",
    "sg:tags":[
        "glass",
        "window",
        "plate"
    ],
    "wof:name":"Duro Vitres & Acces D'Autos",
    "wof:placetype":"venue"
},
  "geometry": {"coordinates":[-73.7213668823,45.3499946594],"type":"Point"}
}