{
  "type": "Feature",
  "properties": {
    "iso:country":"CA",
    "sg:address":"1 Ch DE LA Rabastaliere E",
    "sg:city":"Saint-Bruno",
    "sg:classifiers":[
        {
            "category":"Professional",
            "subcategory":"Business Services",
            "type":"Services"
        }
    ],
    "sg:phone":"+1 450 441 4100",
    "sg:postcode":"J3V 2A4",
    "sg:province":"QC",
    "sg:tags":[
        "notary"
    ],
    "wof:name":"L'Ecuyer, Nancy",
    "wof:placetype":"venue"
},
  "geometry": {"coordinates":[-71.67552185060001,48.4717712402],"type":"Point"}
}