{
  "type": "Feature",
  "properties": {
    "addr:full":"824 Park Dr Golden BC V0A 1H0",
    "addr:housenumber":"824",
    "addr:postcode":"v0a 1h0",
    "addr:street":"Park Dr",
    "iso:country":"CA",
    "sg:address":"824 Park Dr",
    "sg:city":"Golden",
    "sg:classifiers":[
        {
            "category":"Travel",
            "subcategory":"Hotels & Motels",
            "type":"Entertainment"
        }
    ],
    "sg:phone":"+1 250 344 5295",
    "sg:postcode":"V0A 1H0",
    "sg:province":"BC",
    "wof:name":"Rondo Motel",
    "wof:placetype":"venue"
},
  "geometry": {"coordinates":[-116.96466100000001,51.297298],"type":"Point"}
}