{
  "type": "Feature",
  "properties": {
    "addr:full":"376 Ellershouse Rd Ellershouse NS B0N 1L0",
    "addr:housenumber":"376",
    "addr:postcode":"b0n 1l0",
    "addr:street":"Ellershouse Rd",
    "iso:country":"CA",
    "sg:address":"376 Ellershouse Rd",
    "sg:city":"Ellershouse",
    "sg:classifiers":[
        {
            "category":"Food & Beverages",
            "subcategory":"Groceries & Convenience Stores",
            "type":"Retail Goods"
        }
    ],
    "sg:phone":"+1 902 757 2182",
    "sg:postcode":"B0N 1L0",
    "sg:province":"NS",
    "sg:tags":[
        "grocer"
    ],
    "wof:name":"Ellershouse General Store",
    "wof:placetype":"venue"
},
  "geometry": {"coordinates":[-64.003647,44.960938],"type":"Point"}
}