{
  "type": "Feature",
  "properties": {
    "addr:full":"1 Ch DE Rouge Arundel QC J0T 1A0",
    "addr:housenumber":"1",
    "addr:postcode":"j0t 1a0",
    "addr:street":"Ch De Rouge",
    "iso:country":"CA",
    "sg:address":"1 Ch DE Rouge",
    "sg:city":"Arundel",
    "sg:classifiers":[
        {
            "category":"Retail",
            "subcategory":"Auto Repair",
            "type":"Services"
        }
    ],
    "sg:phone":"+1 819 687 3080",
    "sg:postcode":"J0T 1A0",
    "sg:province":"QC",
    "sg:tags":[
        "repairing",
        "automobile"
    ],
    "wof:name":"Garage M Boyer",
    "wof:placetype":"venue"
},
  "geometry": {"coordinates":[-74.618172,45.965805],"type":"Point"}
}