{
  "type": "Feature",
  "properties": {
    "iso:country":"CA",
    "sg:address":"440 Jarvis Ave",
    "sg:city":"Winnipeg",
    "sg:classifiers":[
        {
            "category":"Wholesale",
            "subcategory":"Groceries",
            "type":"Manufacturing & Wholesale Goods"
        }
    ],
    "sg:phone":"+1 204 989 5165",
    "sg:postcode":"R2W 3A6",
    "sg:province":"MB",
    "sg:tags":[
        "food",
        "product"
    ],
    "wof:name":"In Home Marketing",
    "wof:placetype":"venue"
},
  "geometry": {"coordinates":[-97.14544677729999,49.9110832214],"type":"Point"}
}