{
  "type": "Feature",
  "properties": {
    "addr:full":"385 the West Mall Etobicoke ON M9C 1E7",
    "addr:housenumber":"385",
    "addr:postcode":"m9c 1e7",
    "addr:street":"The West Mall",
    "iso:country":"CA",
    "sg:address":"385 the West Mall",
    "sg:city":"Etobicoke",
    "sg:classifiers":[
        {
            "category":"Health Services",
            "subcategory":"Doctor",
            "type":"Services"
        }
    ],
    "sg:phone":"+1 416 622 1864",
    "sg:postcode":"M9C 1E7",
    "sg:province":"ON",
    "sg:tags":[
        "physician",
        "surgeon"
    ],
    "wof:name":"Spencer, John A MD",
    "wof:placetype":"venue"
},
  "geometry": {"coordinates":[-79.56568908689999,43.6421012878],"type":"Point"}
}