{
  "type": "Feature",
  "properties": {
    "addr:full":"42 Main St Pasadena NL A0L 1K0",
    "addr:housenumber":"42",
    "addr:postcode":"a0l 1k0",
    "addr:street":"Main St",
    "iso:country":"CA",
    "sg:address":"42 Main St",
    "sg:city":"Pasadena",
    "sg:classifiers":[
        {
            "category":"Utilities",
            "subcategory":"Fuel Oil & Lpg",
            "type":"Services"
        }
    ],
    "sg:phone":"+1 709 686 2001",
    "sg:postcode":"A0L 1K0",
    "sg:province":"NL",
    "sg:tags":[
        "propane",
        "gas"
    ],
    "wof:name":"Superior Propane Inc",
    "wof:placetype":"venue"
},
  "geometry": {"coordinates":[-57.592213,49.019337],"type":"Point"}
}