{
  "type": "Feature",
  "properties": {
    "addr:full":"84 Rue Elizabeth Sorel-Tracy QC J3P 4G5",
    "addr:housenumber":"84",
    "addr:postcode":"j3p 4g5",
    "addr:street":"Rue Elizabeth",
    "iso:country":"CA",
    "sg:address":"84 Rue Elizabeth",
    "sg:city":"Sorel-Tracy",
    "sg:classifiers":[
        {
            "category":"Professional",
            "subcategory":"Business Services",
            "type":"Services"
        }
    ],
    "sg:phone":"+1 450 743 0071",
    "sg:postcode":"J3P 4G5",
    "sg:province":"QC",
    "sg:tags":[
        "notary"
    ],
    "wof:name":"Grondin & Denis",
    "wof:placetype":"venue"
},
  "geometry": {"coordinates":[-73.11261,46.044041],"type":"Point"}
}