{
  "type": "Feature",
  "properties": {
    "addr:full":"20440 46 Ave Langley BC V3A 3H6",
    "addr:housenumber":"20440",
    "addr:postcode":"v3a 3h6",
    "addr:street":"46 Ave",
    "iso:country":"CA",
    "sg:address":"20440 46 Ave",
    "sg:city":"Langley",
    "sg:classifiers":[
        {
            "category":"Home & Garden",
            "subcategory":"Garden Supply",
            "type":"Retail Goods"
        }
    ],
    "sg:phone":"+1 604 530 5433",
    "sg:postcode":"V3A 3H6",
    "sg:province":"BC",
    "sg:tags":[
        "sprinkler"
    ],
    "wof:name":"B C Rain Irrigation CO Ltd",
    "wof:placetype":"venue"
},
  "geometry": {"coordinates":[-122.656677246,49.0855522156],"type":"Point"}
}