{
  "type": "Feature",
  "properties": {
    "addr:full":"105 Harry Walker Pky N Newmarket ON L3Y 7B3",
    "addr:housenumber":"105",
    "addr:postcode":"l3y 7b3",
    "addr:street":"Harry Walker Pky N",
    "iso:country":"CA",
    "sg:address":"105 Harry Walker Pky N",
    "sg:city":"Newmarket",
    "sg:classifiers":[
        {
            "category":"Home & Garden",
            "subcategory":"Carpets & Floor Coverings",
            "type":"Retail Goods"
        }
    ],
    "sg:phone":"+1 905 773 9581",
    "sg:postcode":"L3Y 7B3",
    "sg:province":"ON",
    "sg:tags":[
        "dealer",
        "rug"
    ],
    "wof:name":"Triumph Newmarket Carpet",
    "wof:placetype":"venue"
},
  "geometry": {"coordinates":[-79.425499,44.070198],"type":"Point"}
}