{
  "type": "Feature",
  "properties": {
    "addr:full":"89 Stanley St Brantford ON N3S 6M7",
    "addr:housenumber":"89",
    "addr:postcode":"n3s 6m7",
    "addr:street":"Stanley St",
    "iso:country":"CA",
    "sg:address":"89 Stanley St",
    "sg:city":"Brantford",
    "sg:classifiers":[
        {
            "category":"Home & Garden",
            "subcategory":"Home Furnishings",
            "type":"Retail Goods"
        }
    ],
    "sg:phone":"+1 519 756 3193",
    "sg:postcode":"N3S 6M7",
    "sg:province":"ON",
    "sg:tags":[
        "fireplace"
    ],
    "wof:name":"Gas Fireplace Ctr",
    "wof:placetype":"venue"
},
  "geometry": {"coordinates":[-80.2437667847,43.1454124451],"type":"Point"}
}