{
  "type": "Feature",
  "properties": {
    "addr:full":"East York ON M4C 4X9",
    "addr:postcode":"m4c 4x9",
    "iso:country":"CA",
    "sg:city":"East York",
    "sg:classifiers":[
        {
            "category":"Professional",
            "subcategory":"Management & Consulting",
            "type":"Services"
        }
    ],
    "sg:phone":"+1 416 694 1244",
    "sg:postcode":"M4C 4X9",
    "sg:province":"ON",
    "sg:tags":[
        "employee",
        "consultant",
        "benefit"
    ],
    "wof:name":"Robert M Livie Insurance Inc",
    "wof:placetype":"venue"
},
  "geometry": {"coordinates":[-79.3030929565,43.6916885376],"type":"Point"}
}