{
  "type": "Feature",
  "properties": {
    "addr:full":"LA Crete AB T0H 2H0",
    "addr:postcode":"t0h 2h0",
    "iso:country":"CA",
    "sg:city":"LA Crete",
    "sg:classifiers":[
        {
            "category":"Food & Beverages",
            "subcategory":"Groceries & Convenience Stores",
            "type":"Retail Goods"
        }
    ],
    "sg:phone":"+1 780 928 4363",
    "sg:postcode":"T0H 2H0",
    "sg:province":"AB",
    "sg:tags":[
        "grocer"
    ],
    "wof:name":"Discount Foods",
    "wof:placetype":"venue"
},
  "geometry": {"coordinates":[-116.40510559099999,58.2071876526],"type":"Point"}
}