{
  "type": "Feature",
  "properties": {
    "addr:full":"1311 Rue Sainte-Catherine E Montreal QC H2L 2H4",
    "addr:housenumber":"1311",
    "addr:postcode":"h2l 2h4",
    "addr:street":"Rue Sainte-Catherine E",
    "iso:country":"CA",
    "sg:address":"1311 Rue Sainte-Catherine E",
    "sg:city":"Montreal",
    "sg:classifiers":[
        {
            "category":"Communications",
            "subcategory":"Film & Video Production",
            "type":"Services"
        }
    ],
    "sg:phone":"+1 514 525 7667",
    "sg:postcode":"H2L 2H4",
    "sg:province":"QC",
    "sg:tags":[
        "taping"
    ],
    "wof:name":"Priape Video",
    "wof:placetype":"venue"
},
  "geometry": {"coordinates":[-73.55535888670001,45.5195541382],"type":"Point"}
}