{
  "type": "Feature",
  "properties": {
    "addr:full":"8910 Macleod Trail SE Calgary AB T2H 0M4",
    "addr:housenumber":"8910",
    "addr:postcode":"t2h 0m4",
    "addr:street":"Macleod Trail Se",
    "iso:country":"CA",
    "sg:address":"8910 Macleod Trail SE",
    "sg:city":"Calgary",
    "sg:classifiers":[
        {
            "category":"Retail",
            "subcategory":"Veterinary Services",
            "type":"Services"
        }
    ],
    "sg:phone":"+1 403 255 1168",
    "sg:postcode":"T2H 0M4",
    "sg:province":"AB",
    "sg:tags":[
        "veterinarian"
    ],
    "wof:name":"Mc Carthy, S A DVM",
    "wof:placetype":"venue"
},
  "geometry": {"coordinates":[-114.07125854500001,50.9737434387],"type":"Point"}
}