{
  "type": "Feature",
  "properties": {
    "iso:country":"CA",
    "sg:city":"Repentigny",
    "sg:classifiers":[
        {
            "category":"Retail",
            "subcategory":"Auto Repair",
            "type":"Services"
        }
    ],
    "sg:phone":"+1 450 582 1871",
    "sg:postcode":"J6A 7N1",
    "sg:province":"QC",
    "sg:tags":[
        "repairing",
        "automobile"
    ],
    "wof:name":"Autos Experts Lanaudiere",
    "wof:placetype":"venue"
},
  "geometry": {"coordinates":[-73.451027,45.752697],"type":"Point"}
}