{
  "type": "Feature",
  "properties": {
    "addr:full":"Redcliff AB T0J 2P0",
    "addr:postcode":"t0j 2p0",
    "iso:country":"CA",
    "sg:city":"Redcliff",
    "sg:classifiers":[
        {
            "category":"Mining & Drilling",
            "type":"Manufacturing & Wholesale Goods"
        }
    ],
    "sg:phone":"+1 403 548 2700",
    "sg:postcode":"T0J 2P0",
    "sg:province":"AB",
    "sg:tags":[
        "equipment",
        "field",
        "oil",
        "well",
        "supply"
    ],
    "wof:name":"D & D Oilfield Rentals",
    "wof:placetype":"venue"
},
  "geometry": {"coordinates":[-110.776596,50.07716],"type":"Point"}
}