{
  "type": "Feature",
  "properties": {
    "iso:country":"CA",
    "sg:address":"1722 Jane St",
    "sg:city":"York",
    "sg:classifiers":[
        {
            "category":"Personal",
            "subcategory":"Beauty Salon",
            "type":"Services"
        }
    ],
    "sg:phone":"+1 416 243 0359",
    "sg:postcode":"M9N 2S4",
    "sg:province":"ON",
    "wof:name":"Nice One Nail Ltd",
    "wof:placetype":"venue"
},
  "geometry": {"coordinates":[-79.50425720210001,43.703918457],"type":"Point"}
}