{
  "type": "Feature",
  "properties": {
    "addr:full":"1450 5th Ave Valemount BC V0E 2Z0",
    "addr:housenumber":"1450",
    "addr:postcode":"v0e 2z0",
    "addr:street":"5Th Ave",
    "iso:country":"CA",
    "sg:address":"1450 5th Ave",
    "sg:city":"Valemount",
    "sg:classifiers":[
        {
            "category":"Travel",
            "subcategory":"Hotels & Motels",
            "type":"Entertainment"
        }
    ],
    "sg:phone":"+1 250 566 9787",
    "sg:postcode":"V0E 2Z0",
    "sg:province":"BC",
    "wof:name":"Chalet Continental",
    "wof:placetype":"venue"
},
  "geometry": {"coordinates":[-119.25743866000001,52.8321075439],"type":"Point"}
}