{
  "type": "Feature",
  "properties": {
    "addr:full":"528 Av Meloche Dorval QC H9P 2T2",
    "addr:postcode":"h9p 2t2",
    "addr:street":"528 Av Meloche",
    "iso:country":"CA",
    "sg:address":"528 Av Meloche",
    "sg:city":"Dorval",
    "sg:classifiers":[
        {
            "category":"Manufacturing",
            "subcategory":"Electronics",
            "type":"Manufacturing & Wholesale Goods"
        }
    ],
    "sg:phone":"+1 514 636 8277",
    "sg:postcode":"H9P 2T2",
    "sg:province":"QC",
    "sg:tags":[
        "instrument",
        "electronic"
    ],
    "wof:name":"Mesurina Limitee",
    "wof:placetype":"venue"
},
  "geometry": {"coordinates":[-73.726501,45.451233],"type":"Point"}
}