{
  "type": "Feature",
  "properties": {
    "addr:full":"5156 Av Patricia Montreal QC H4V 1Y8",
    "addr:housenumber":"5156",
    "addr:postcode":"h4v 1y8",
    "addr:street":"Av Patricia",
    "iso:country":"CA",
    "sg:address":"5156 Av Patricia",
    "sg:city":"Montreal",
    "sg:classifiers":[
        {
            "category":"Building & Trades",
            "subcategory":"Landscaping Services",
            "type":"Services"
        }
    ],
    "sg:phone":"+1 514 484 9752",
    "sg:postcode":"H4V 1Y8",
    "sg:province":"QC",
    "sg:tags":[
        "lawn",
        "contractor",
        "landscape",
        "maintenance",
        "grounds"
    ],
    "wof:name":"Nick & Mario Registered",
    "wof:placetype":"venue"
},
  "geometry": {"coordinates":[-73.6513824463,45.4590492249],"type":"Point"}
}