{
  "type": "Feature",
  "properties": {
    "addr:full":"11 George St S Cambridge ON N1S 2N3",
    "addr:housenumber":"11",
    "addr:postcode":"n1s 2n3",
    "addr:street":"George St S",
    "iso:country":"CA",
    "sg:address":"11 George St S",
    "sg:city":"Cambridge",
    "sg:classifiers":[
        {
            "category":"Health Services",
            "subcategory":"Doctor",
            "type":"Services"
        }
    ],
    "sg:phone":"+1 519 621 8351",
    "sg:postcode":"N1S 2N3",
    "sg:province":"ON",
    "sg:tags":[
        "physician",
        "surgeon"
    ],
    "wof:name":"Crosby, John W MD",
    "wof:placetype":"venue"
},
  "geometry": {"coordinates":[-80.3184890747,43.3577919006],"type":"Point"}
}