{
  "type": "Feature",
  "properties": {
    "addr:full":"620 Park Royal N West Vancouver BC V7T 1H9",
    "addr:housenumber":"620",
    "addr:postcode":"v7t 1h9",
    "addr:street":"Park Royal N",
    "iso:country":"CA",
    "sg:address":"620 Park Royal N",
    "sg:city":"West Vancouver",
    "sg:classifiers":[
        {
            "category":"Insurance",
            "subcategory":"Insurance Agent",
            "type":"Services"
        }
    ],
    "sg:phone":"+1 604 922 6102",
    "sg:postcode":"V7T 1H9",
    "sg:province":"BC",
    "wof:name":"Westland Insurance Svc Ltd",
    "wof:placetype":"venue"
},
  "geometry": {"coordinates":[-123.13545227,49.3277015686],"type":"Point"}
}