{
  "type": "Feature",
  "properties": {
    "addr:full":"1801 Boul DE Maisonneuve O Montreal QC H3H 1J9",
    "addr:housenumber":"1801",
    "addr:postcode":"h3h 1j9",
    "addr:street":"Boul De Maisonneuve O",
    "iso:country":"CA",
    "sg:address":"1801 Boul DE Maisonneuve O",
    "sg:city":"Montreal",
    "sg:classifiers":[
        {
            "category":"Social Services",
            "type":"Services"
        }
    ],
    "sg:phone":"+1 514 934 0552",
    "sg:postcode":"H3H 1J9",
    "sg:province":"QC",
    "sg:tags":[
        "organization",
        "clinic",
        "welfare"
    ],
    "wof:name":"Sida Ctr D'Intervention",
    "wof:placetype":"venue"
},
  "geometry": {"coordinates":[-73.55378723139999,45.5233726501],"type":"Point"}
}