{
  "type": "Feature",
  "properties": {
    "addr:full":"552 Little Britain Rd Lockport MB R1A 3S8",
    "addr:housenumber":"552",
    "addr:postcode":"r1a 3s8",
    "addr:street":"Little Britain Rd",
    "iso:country":"CA",
    "sg:address":"552 Little Britain Rd",
    "sg:city":"Lockport",
    "sg:classifiers":[
        {
            "category":"Farming",
            "subcategory":"Farm",
            "type":"Manufacturing & Wholesale Goods"
        }
    ],
    "sg:phone":"+1 204 757 2075",
    "sg:postcode":"R1A 3S8",
    "sg:province":"MB",
    "wof:name":"Bannisters's Dairy",
    "wof:placetype":"venue"
},
  "geometry": {"coordinates":[-96.94840240480001,50.1018753052],"type":"Point"}
}