{
  "type": "Feature",
  "properties": {
    "iso:country":"CA",
    "sg:address":"207 Boardman St",
    "sg:city":"LA Ronge",
    "sg:classifiers":[
        {
            "category":"Education",
            "subcategory":"Special Training",
            "type":"Public Place"
        }
    ],
    "sg:phone":"+1 306 425 4334",
    "sg:postcode":"S0J 1L0",
    "sg:province":"SK",
    "sg:tags":[
        "reading",
        "instruction",
        "improvement"
    ],
    "wof:name":"Northland College",
    "wof:placetype":"venue"
},
  "geometry": {"coordinates":[-105.295326233,55.1124954224],"type":"Point"}
}