{
  "type": "Feature",
  "properties": {
    "addr:full":"1308 Second St W # 13 Brooks AB T1R 0V5",
    "addr:housenumber":"1308;13",
    "addr:postcode":"t1r 0v5",
    "addr:street":"Second St W #;Brooks Ab",
    "iso:country":"CA",
    "sg:address":"1308 Second St W # 13",
    "sg:city":"Brooks",
    "sg:classifiers":[
        {
            "category":"Food & Beverages",
            "subcategory":"Liquor & Beverages",
            "type":"Retail Goods"
        }
    ],
    "sg:phone":"+1 403 501 3788",
    "sg:postcode":"T1R 0V5",
    "sg:province":"AB",
    "sg:tags":[
        "store"
    ],
    "wof:name":"Brooks North End Liquor Store",
    "wof:placetype":"venue"
},
  "geometry": {"coordinates":[-111.896935,50.584782],"type":"Point"}
}