{
  "type": "Feature",
  "properties": {
    "addr:full":"501 Imp Martin Grande-Ile QC J6S 4C6",
    "addr:housenumber":"501",
    "addr:postcode":"j6s 4c6",
    "addr:street":"Imp Martin Grande-Ile",
    "iso:country":"CA",
    "sg:address":"501 Imp Martin",
    "sg:city":"Grande-Ile",
    "sg:classifiers":[
        {
            "category":"Manufacturing",
            "subcategory":"Metals",
            "type":"Manufacturing & Wholesale Goods"
        }
    ],
    "sg:phone":"+1 450 373 9292",
    "sg:postcode":"J6S 4C6",
    "sg:province":"QC",
    "sg:tags":[
        "steel"
    ],
    "wof:name":"Industries B & X Inc",
    "wof:placetype":"venue"
},
  "geometry": {"coordinates":[-74.123604,45.273037],"type":"Point"}
}