{
  "type": "Feature",
  "properties": {
    "iso:country":"CA",
    "sg:address":"3290 Rue Fabien",
    "sg:city":"Laval",
    "sg:classifiers":[
        {
            "category":"Building & Trades",
            "subcategory":"Plumbing",
            "type":"Services"
        }
    ],
    "sg:phone":"+1 450 622 9393",
    "sg:postcode":"H7P 2B3",
    "sg:province":"QC",
    "sg:tags":[
        "contractor"
    ],
    "wof:name":"Plomberie Chauffage Samson",
    "wof:placetype":"venue"
},
  "geometry": {"coordinates":[-73.802032,45.577461],"type":"Point"}
}