{
  "type": "Feature",
  "properties": {
    "addr:full":"37 Heath St E Toronto ON M4T 1S2",
    "addr:housenumber":"37",
    "addr:postcode":"m4t 1s2",
    "addr:street":"Heath St E",
    "iso:country":"CA",
    "sg:address":"37 Heath St E",
    "sg:city":"Toronto",
    "sg:classifiers":[
        {
            "category":"Health Services",
            "subcategory":"Doctor",
            "type":"Services"
        }
    ],
    "sg:phone":"+1 416 921 4614",
    "sg:postcode":"M4T 1S2",
    "sg:province":"ON",
    "sg:tags":[
        "dentist"
    ],
    "wof:name":"Kivlichan, Bill DDS",
    "wof:placetype":"venue"
},
  "geometry": {"coordinates":[-79.392899,43.690262],"type":"Point"}
}