{
  "type": "Feature",
  "properties": {
    "addr:full":"Richmond BC V7C 5J8",
    "addr:postcode":"v7c 5j8",
    "iso:country":"CA",
    "sg:city":"Richmond",
    "sg:classifiers":[
        {
            "category":"Wholesale",
            "subcategory":"Groceries",
            "type":"Manufacturing & Wholesale Goods"
        }
    ],
    "sg:phone":"+1 604 275 1244",
    "sg:postcode":"V7C 5J8",
    "sg:province":"BC",
    "sg:tags":[
        "cocoa",
        "chocolate"
    ],
    "wof:name":"Bernard Callebaut Chocolaterie",
    "wof:placetype":"venue"
},
  "geometry": {"coordinates":[-123.15877500000001,49.154732],"type":"Point"}
}