{
  "type": "Feature",
  "properties": {
    "addr:full":"Nanaimo BC V9R 3X8",
    "addr:postcode":"v9r 3x8",
    "iso:country":"CA",
    "sg:city":"Nanaimo",
    "sg:classifiers":[
        {
            "category":"Health Services",
            "subcategory":"Nursing And Care Facility",
            "type":"Services"
        }
    ],
    "sg:phone":"+1 250 753 5031",
    "sg:postcode":"V9R 3X8",
    "sg:province":"BC",
    "sg:tags":[
        "home",
        "retirement",
        "community"
    ],
    "wof:name":"General George R Pearkes Snr",
    "wof:placetype":"venue"
},
  "geometry": {"coordinates":[-123.967873,49.17585],"type":"Point"}
}