{
  "type": "Feature",
  "properties": {
    "addr:full":"3032 Don Mills Rd North York ON M2J 3C1",
    "addr:housenumber":"3032",
    "addr:postcode":"m2j 3c1",
    "addr:street":"Don Mills Rd",
    "iso:country":"CA",
    "sg:address":"3032 Don Mills Rd",
    "sg:city":"North York",
    "sg:classifiers":[
        {
            "category":"Personal",
            "subcategory":"Beauty Salon",
            "type":"Services"
        }
    ],
    "sg:phone":"+1 416 491 3138",
    "sg:postcode":"M2J 3C1",
    "sg:province":"ON",
    "wof:name":"Moretti's Hair Place",
    "wof:placetype":"venue"
},
  "geometry": {"coordinates":[-79.353424,43.787834],"type":"Point"}
}