{
  "type": "Feature",
  "properties": {
    "iso:country":"CA",
    "sg:address":"Farm",
    "sg:city":"Moosomin",
    "sg:classifiers":[
        {
            "category":"Shopping",
            "subcategory":"Bicycles & Sporting Goods",
            "type":"Retail Goods"
        }
    ],
    "sg:phone":"+1 306 435 4242",
    "sg:postcode":"S0G 3N0",
    "sg:province":"SK",
    "sg:tags":[
        "ammunition",
        "gun",
        "gunsmith"
    ],
    "wof:name":"K & M Mc Leod Shooting Shop",
    "wof:placetype":"venue"
},
  "geometry": {"coordinates":[-101.663291931,50.1470336914],"type":"Point"}
}