{
  "type": "Feature",
  "properties": {
    "addr:full":"670 Queen St W Toronto ON M6J 1E5",
    "addr:housenumber":"670",
    "addr:postcode":"m6j 1e5",
    "addr:street":"Queen St W",
    "iso:country":"CA",
    "sg:address":"670 Queen St W",
    "sg:city":"Toronto",
    "sg:classifiers":[
        {
            "category":"Home & Garden",
            "subcategory":"Furniture",
            "type":"Retail Goods"
        }
    ],
    "sg:phone":"+1 416 681 0368",
    "sg:postcode":"M6J 1E5",
    "sg:province":"ON",
    "sg:tags":[
        "baby",
        "accessory"
    ],
    "wof:name":"Kol Kid",
    "wof:placetype":"venue"
},
  "geometry": {"coordinates":[-79.4072189331,43.6466903687],"type":"Point"}
}