{
  "type": "Feature",
  "properties": {
    "addr:full":"428 Av Saint-Charles Vaudreuil-Dorion QC J7V 2N1",
    "addr:postcode":"j7v 2n1",
    "addr:street":"428 Av Saint-Charles",
    "iso:country":"CA",
    "sg:address":"428 Av Saint-Charles",
    "sg:city":"Vaudreuil-Dorion",
    "sg:classifiers":[
        {
            "category":"Shopping",
            "type":"Retail Goods"
        }
    ],
    "sg:phone":"+1 450 424 4123",
    "sg:postcode":"J7V 2N1",
    "sg:province":"QC",
    "sg:tags":[
        "equipment",
        "wine",
        "supply"
    ],
    "wof:name":"Vignes DE Vaudreuil",
    "wof:placetype":"venue"
},
  "geometry": {"coordinates":[-74.02722199999999,45.399712],"type":"Point"}
}