{
  "type": "Feature",
  "properties": {
    "iso:country":"CA",
    "sg:city":"London",
    "sg:classifiers":[
        {
            "category":"Professional",
            "subcategory":"Computer Services",
            "type":"Services"
        }
    ],
    "sg:phone":"+1 519 439 0310",
    "sg:postcode":"N6A 1S2",
    "sg:province":"ON",
    "sg:tags":[
        "consultant"
    ],
    "wof:name":"P C Consulting",
    "wof:placetype":"venue"
},
  "geometry": {"coordinates":[-81.2529220581,42.9942741394],"type":"Point"}
}