{
  "type": "Feature",
  "properties": {
    "iso:country":"CA",
    "sg:city":"Nepean",
    "sg:classifiers":[
        {
            "category":"Autos & Motor Vehicles",
            "subcategory":"Automobile Sales",
            "type":"Retail Goods"
        }
    ],
    "sg:phone":"+1 613 274 0031",
    "sg:postcode":"K2E 6T7",
    "sg:province":"ON",
    "sg:tags":[
        "car",
        "dealer"
    ],
    "wof:name":"Bentley Auctions",
    "wof:placetype":"venue"
},
  "geometry": {"coordinates":[-75.7202453613,45.332649231],"type":"Point"}
}