{
  "type": "Feature",
  "properties": {
    "iso:country":"CA",
    "sg:city":"Estevan",
    "sg:classifiers":[
        {
            "category":"Mining & Drilling",
            "type":"Manufacturing & Wholesale Goods"
        }
    ],
    "sg:phone":"+1 306 634 2835",
    "sg:postcode":"S4A 2A6",
    "sg:province":"SK",
    "sg:tags":[
        "oil",
        "well"
    ],
    "wof:name":"Apex Distribution Inc",
    "wof:placetype":"venue"
},
  "geometry": {"coordinates":[-102.962547302,49.1356124878],"type":"Point"}
}