{
  "type": "Feature",
  "properties": {
    "addr:full":"312 Road 5 Leamington ON N8H 3V5",
    "addr:postcode":"n8h 3v5",
    "addr:street":"312 Road 5",
    "iso:country":"CA",
    "sg:address":"312 Road 5",
    "sg:city":"Leamington",
    "sg:classifiers":[
        {
            "category":"Wholesale",
            "subcategory":"Farm Supplies",
            "type":"Manufacturing & Wholesale Goods"
        }
    ],
    "sg:phone":"+1 519 326 7977",
    "sg:postcode":"N8H 3V5",
    "sg:province":"ON",
    "wof:name":"Adamson Farms",
    "wof:placetype":"venue"
},
  "geometry": {"coordinates":[-82.62493896479999,42.085647583],"type":"Point"}
}