{
  "type": "Feature",
  "properties": {
    "iso:country":"CA",
    "sg:address":"817 Main St",
    "sg:city":"Winnipeg",
    "sg:classifiers":[
        {
            "category":"Social Services",
            "subcategory":"Adult Care",
            "type":"Services"
        }
    ],
    "sg:phone":"+1 204 942 7486",
    "sg:postcode":"R2W 5J2",
    "sg:province":"MB",
    "sg:tags":[
        "organization",
        "senior",
        "citizen"
    ],
    "wof:name":"Main Street Senior Ctr",
    "wof:placetype":"venue"
},
  "geometry": {"coordinates":[-97.133507,49.907337],"type":"Point"}
}