{
  "type": "Feature",
  "properties": {
    "iso:country":"CA",
    "sg:address":"2 Court Terr",
    "sg:city":"Brockville",
    "sg:classifiers":[
        {
            "category":"Social Services",
            "type":"Services"
        }
    ],
    "sg:phone":"+1 613 342 4610",
    "sg:postcode":"K6V 4T4",
    "sg:province":"ON",
    "sg:tags":[
        "employee",
        "assistance",
        "program"
    ],
    "wof:name":"Eap Perspective Inc",
    "wof:placetype":"venue"
},
  "geometry": {"coordinates":[-75.684441,44.589558],"type":"Point"}
}