{
  "type": "Feature",
  "properties": {
    "addr:full":"Langton ON N0E 1G0",
    "addr:postcode":"n0e 1g0",
    "iso:country":"CA",
    "sg:city":"Langton",
    "sg:classifiers":[
        {
            "category":"Education",
            "subcategory":"School",
            "type":"Public Place"
        }
    ],
    "sg:phone":"+1 519 586 3522",
    "sg:postcode":"N0E 1G0",
    "sg:province":"ON",
    "wof:name":"Valley Heights Secondary Schl",
    "wof:placetype":"venue"
},
  "geometry": {"coordinates":[-80.5689697266,42.7311706543],"type":"Point"}
}