{
  "type": "Feature",
  "properties": {
    "addr:full":"12520 100 St Grande Prairie AB T8V 4H8",
    "addr:housenumber":"12520",
    "addr:postcode":"t8v 4h8",
    "addr:street":"100 St",
    "iso:country":"CA",
    "sg:address":"12520 100 St",
    "sg:city":"Grande Prairie",
    "sg:classifiers":[
        {
            "category":"Restaurant",
            "type":"Food & Drink"
        }
    ],
    "sg:phone":"+1 780 538 1991",
    "sg:postcode":"T8V 4H8",
    "sg:province":"AB",
    "wof:name":"Pizza Hut",
    "wof:placetype":"venue"
},
  "geometry": {"coordinates":[-118.795761,55.194233],"type":"Point"}
}