{
  "type": "Feature",
  "properties": {
    "iso:country":"CA",
    "sg:address":"208 Ch DE Saint-Jean",
    "sg:city":"LA Prairie",
    "sg:classifiers":[
        {
            "category":"Organizations",
            "subcategory":"Professional Association",
            "type":"Services"
        }
    ],
    "sg:phone":"+1 450 659 2015",
    "sg:postcode":"J5R 2K3",
    "sg:province":"QC",
    "wof:name":"Ordre Loyal Des Mooses",
    "wof:placetype":"venue"
},
  "geometry": {"coordinates":[-73.49370574949999,45.4193649292],"type":"Point"}
}