{
  "type": "Feature",
  "properties": {
    "addr:full":"5109 9th Ave Okanagan Falls BC V0H 1R0",
    "addr:housenumber":"5109",
    "addr:postcode":"v0h 1r0",
    "addr:street":"9Th Ave",
    "iso:country":"CA",
    "sg:address":"5109 9th Ave",
    "sg:city":"Okanagan Falls",
    "sg:classifiers":[
        {
            "category":"Food & Beverages",
            "subcategory":"Groceries & Convenience Stores",
            "type":"Retail Goods"
        }
    ],
    "sg:phone":"+1 250 497 8155",
    "sg:postcode":"V0H 1R0",
    "sg:province":"BC",
    "sg:tags":[
        "grocer"
    ],
    "wof:name":"Sims Grocery",
    "wof:placetype":"venue"
},
  "geometry": {"coordinates":[-119.57310485799999,49.3447952271],"type":"Point"}
}