{
  "type": "Feature",
  "properties": {
    "addr:full":"152 Rue DE LA Seigneurie Laurier-Station QC G0S 1N0",
    "addr:housenumber":"152",
    "addr:postcode":"g0s 1n0",
    "addr:street":"Rue De La Seigneurie",
    "iso:country":"CA",
    "sg:address":"152 Rue DE LA Seigneurie",
    "sg:city":"Laurier-Station",
    "sg:classifiers":[
        {
            "category":"Autos & Motor Vehicles",
            "subcategory":"Motorcycle Sales",
            "type":"Retail Goods"
        }
    ],
    "sg:phone":"+1 418 728 3545",
    "sg:postcode":"G0S 1N0",
    "sg:province":"QC",
    "sg:tags":[
        "all",
        "terrain",
        "snowmobile"
    ],
    "wof:name":"Bernier Sports Ltee",
    "wof:placetype":"venue"
},
  "geometry": {"coordinates":[-71.63990800000001,46.538158],"type":"Point"}
}