{
  "type": "Feature",
  "properties": {
    "addr:full":"Humboldt SK S0K 2A0",
    "addr:postcode":"s0k 2a0",
    "addr:street":"Humboldt",
    "iso:country":"CA",
    "sg:city":"Humboldt",
    "sg:classifiers":[
        {
            "category":"Manufacturing",
            "subcategory":"Motor Vehicles & Parts",
            "type":"Manufacturing & Wholesale Goods"
        }
    ],
    "sg:phone":"+1 306 682 2505",
    "sg:postcode":"S0K 2A0",
    "sg:province":"SK",
    "sg:tags":[
        "body",
        "equipment",
        "truck"
    ],
    "wof:name":"Commercial Industrial Mfg Ltd",
    "wof:placetype":"venue"
},
  "geometry": {"coordinates":[-105.11396000000001,52.198044],"type":"Point"}
}