{
  "type": "Feature",
  "properties": {
    "addr:full":"305 Norman St Palmerston ON N0G 2P0",
    "addr:housenumber":"305",
    "addr:postcode":"n0g 2p0",
    "addr:street":"Norman St",
    "iso:country":"CA",
    "sg:address":"305 Norman St",
    "sg:city":"Palmerston",
    "sg:classifiers":[
        {
            "category":"Building & Trades",
            "subcategory":"Construction",
            "type":"Services"
        }
    ],
    "sg:phone":"+1 519 343 2698",
    "sg:postcode":"N0G 2P0",
    "sg:province":"ON",
    "sg:tags":[
        "maker",
        "cabinet"
    ],
    "wof:name":"Robinson Cabinetry",
    "wof:placetype":"venue"
},
  "geometry": {"coordinates":[-80.84856414790001,43.8363037109],"type":"Point"}
}