{
  "type": "Feature",
  "properties": {
    "addr:full":"5740 175 St Surrey BC V3S 4T7",
    "addr:housenumber":"5740",
    "addr:postcode":"v3s 4t7",
    "addr:street":"175 St",
    "iso:country":"CA",
    "sg:address":"5740 175 St",
    "sg:city":"Surrey",
    "sg:classifiers":[
        {
            "category":"Recreation",
            "type":"Entertainment"
        }
    ],
    "sg:phone":"+1 604 576 0320",
    "sg:postcode":"V3S 4T7",
    "sg:province":"BC",
    "sg:tags":[
        "martial",
        "arts",
        "instruction"
    ],
    "wof:name":"Cloverdale Black Belt Academy",
    "wof:placetype":"venue"
},
  "geometry": {"coordinates":[-122.7379,49.107227],"type":"Point"}
}