{
  "type": "Feature",
  "properties": {
    "addr:full":"7001 Boul Les Galeries D'Anjou Anjou QC H1M 3V6",
    "addr:housenumber":"7001",
    "addr:postcode":"h1m 3v6",
    "addr:street":"Boul Les Galeries D'Anjou",
    "iso:country":"CA",
    "sg:address":"7001 Boul Les Galeries D'Anjou",
    "sg:city":"Anjou",
    "sg:classifiers":[
        {
            "category":"Personal",
            "subcategory":"Beauty Salon",
            "type":"Services"
        }
    ],
    "sg:phone":"+1 514 354 0065",
    "sg:postcode":"H1M 3V6",
    "sg:province":"QC",
    "wof:name":"Coiffure Epoca",
    "wof:placetype":"venue"
},
  "geometry": {"coordinates":[-73.538673,45.612267],"type":"Point"}
}