{
  "type": "Feature",
  "properties": {
    "addr:full":"24 Brewery St Baden ON N3A 2S7",
    "addr:housenumber":"24 brewery",
    "addr:postcode":"n3a 2s7",
    "addr:street":"St",
    "iso:country":"CA",
    "sg:address":"24 Brewery St",
    "sg:city":"Baden",
    "sg:classifiers":[
        {
            "category":"Travel",
            "subcategory":"Hotels & Motels",
            "type":"Entertainment"
        }
    ],
    "sg:phone":"+1 519 634 8652",
    "sg:postcode":"N3A 2S7",
    "sg:province":"ON",
    "sg:tags":[
        "breakfast",
        "accommodation",
        "bed"
    ],
    "wof:name":"Willow Springs Bed & Breakfast",
    "wof:placetype":"venue"
},
  "geometry": {"coordinates":[-80.66529083250001,43.4034576416],"type":"Point"}
}