{
  "type": "Feature",
  "properties": {
    "addr:full":"3101 Bathurst St North York ON M6A 2A6",
    "addr:housenumber":"3101",
    "addr:postcode":"m6a 2a6",
    "addr:street":"Bathurst St",
    "iso:country":"CA",
    "sg:address":"3101 Bathurst St",
    "sg:city":"North York",
    "sg:classifiers":[
        {
            "category":"Organizations",
            "subcategory":"Membership Organization",
            "type":"Services"
        }
    ],
    "sg:phone":"+1 416 783 6960",
    "sg:postcode":"M6A 2A6",
    "sg:province":"ON",
    "wof:name":"Canadian Friends of Yeshiva",
    "wof:placetype":"venue"
},
  "geometry": {"coordinates":[-79.43006099999999,43.720802],"type":"Point"}
}