{
  "type": "Feature",
  "properties": {
    "addr:full":"2803 Broadway W Vancouver BC V6K 2G6",
    "addr:housenumber":"2803",
    "addr:postcode":"v6k 2g6",
    "addr:street":"Broadway W",
    "iso:country":"CA",
    "sg:address":"2803 Broadway W",
    "sg:city":"Vancouver",
    "sg:classifiers":[
        {
            "category":"Shopping",
            "subcategory":"Clothing, Apparel, & Fashions",
            "type":"Retail Goods"
        }
    ],
    "sg:phone":"+1 604 736 4484",
    "sg:postcode":"V6K 2G6",
    "sg:province":"BC",
    "wof:name":"Plenty",
    "wof:placetype":"venue"
},
  "geometry": {"coordinates":[-123.168441773,49.264175415],"type":"Point"}
}