{
  "type": "Feature",
  "properties": {
    "addr:full":"8115 137 Ave NW Edmonton AB T5C 2L7",
    "addr:housenumber":"8115",
    "addr:postcode":"t5c 2l7",
    "addr:street":"137 Ave Nw",
    "iso:country":"CA",
    "sg:address":"8115 137 Ave NW",
    "sg:city":"Edmonton",
    "sg:classifiers":[
        {
            "category":"Retail",
            "subcategory":"Auto Rental",
            "type":"Services"
        }
    ],
    "sg:phone":"+1 780 472 7724",
    "sg:postcode":"T5C 2L7",
    "sg:province":"AB",
    "sg:tags":[
        "renting",
        "truck",
        "leasing"
    ],
    "wof:name":"U-Haul CO Ltd",
    "wof:placetype":"venue"
},
  "geometry": {"coordinates":[-113.46569100000001,53.599247],"type":"Point"}
}