{
  "type": "Feature",
  "properties": {
    "iso:country":"CA",
    "sg:address":"1273 Wellington St W",
    "sg:city":"Ottawa",
    "sg:classifiers":[
        {
            "category":"Shopping",
            "subcategory":"Department Store",
            "type":"Retail Goods"
        }
    ],
    "sg:phone":"+1 613 722 7166",
    "sg:postcode":"K1Y 3A6",
    "sg:province":"ON",
    "sg:tags":[
        "shop",
        "clothing"
    ],
    "wof:name":"St Vincent DE Paul Stores",
    "wof:placetype":"venue"
},
  "geometry": {"coordinates":[-75.7339172363,45.3993415833],"type":"Point"}
}