{
  "type": "Feature",
  "properties": {
    "addr:full":"1577 Main St Vancouver BC V6A 2W5",
    "addr:housenumber":"1577",
    "addr:postcode":"v6a 2w5",
    "addr:street":"Main St",
    "iso:country":"CA",
    "sg:address":"1577 Main St",
    "sg:city":"Vancouver",
    "sg:classifiers":[
        {
            "category":"Autos & Motor Vehicles",
            "subcategory":"Automobile Sales",
            "type":"Retail Goods"
        }
    ],
    "sg:phone":"+1 604 669 5337",
    "sg:postcode":"V6A 2W5",
    "sg:province":"BC",
    "sg:tags":[
        "car",
        "dealer"
    ],
    "wof:name":"Vancouver Dodge Jeep Ltd",
    "wof:placetype":"venue"
},
  "geometry": {"coordinates":[-123.100594,49.271183],"type":"Point"}
}