{
  "type": "Feature",
  "properties": {
    "iso:country":"CA",
    "sg:address":"75 Akerley Blvd",
    "sg:city":"Dartmouth",
    "sg:classifiers":[
        {
            "category":"Home & Garden",
            "subcategory":"Furniture",
            "type":"Retail Goods"
        }
    ],
    "sg:phone":"+1 902 468 1462",
    "sg:postcode":"B3B 1R7",
    "sg:province":"NS",
    "wof:name":"Aab Turner's Bedrooms",
    "wof:placetype":"venue"
},
  "geometry": {"coordinates":[-63.5990066528,44.7120819092],"type":"Point"}
}