{
  "type": "Feature",
  "properties": {
    "addr:full":"Fenelon Falls ON K0M 1N0",
    "addr:postcode":"k0m 1n0",
    "iso:country":"CA",
    "sg:city":"Fenelon Falls",
    "sg:classifiers":[
        {
            "category":"Real Estate",
            "subcategory":"Real Estate Agent",
            "type":"Services"
        }
    ],
    "sg:phone":"+1 705 887 5300",
    "sg:postcode":"K0M 1N0",
    "sg:province":"ON",
    "wof:name":"Laurie Jones Real Estate CO",
    "wof:placetype":"venue"
},
  "geometry": {"coordinates":[-78.74121100000001,44.539234],"type":"Point"}
}