{
  "type": "Feature",
  "properties": {
    "iso:country":"CA",
    "sg:address":"2205 Boul Des Chutes",
    "sg:city":"Beauport",
    "sg:classifiers":[
        {
            "category":"Restaurant",
            "type":"Food & Drink"
        }
    ],
    "sg:phone":"+1 418 661 0808",
    "sg:postcode":"G1C 1W6",
    "sg:province":"QC",
    "wof:name":"Pizza Mag",
    "wof:placetype":"venue"
},
  "geometry": {"coordinates":[-71.161186,46.881237],"type":"Point"}
}