{
  "type": "Feature",
  "properties": {
    "addr:full":"153 Boul Perron O New Richmond QC G0C 2B0",
    "addr:housenumber":"153",
    "addr:postcode":"g0c 2b0",
    "addr:street":"Boul Perron",
    "iso:country":"CA",
    "sg:address":"153 Boul Perron O",
    "sg:city":"New Richmond",
    "sg:classifiers":[
        {
            "category":"Shopping",
            "subcategory":"Bicycles & Sporting Goods",
            "type":"Retail Goods"
        }
    ],
    "sg:phone":"+1 418 392 6230",
    "sg:postcode":"G0C 2B0",
    "sg:province":"QC",
    "wof:name":"Pitre Rheal Sport",
    "wof:placetype":"venue"
},
  "geometry": {"coordinates":[-65.847641,48.155109],"type":"Point"}
}