{
  "type": "Feature",
  "properties": {
    "addr:full":"8207 Roper Rd NW Edmonton AB T6E 6S4",
    "addr:housenumber":"8207",
    "addr:postcode":"t6e 6s4",
    "addr:street":"Roper Rd Nw",
    "iso:country":"CA",
    "sg:address":"8207 Roper Rd NW",
    "sg:city":"Edmonton",
    "sg:classifiers":[
        {
            "category":"Professional",
            "subcategory":"Research",
            "type":"Services"
        }
    ],
    "sg:phone":"+1 780 462 0707",
    "sg:postcode":"T6E 6S4",
    "sg:province":"AB",
    "sg:tags":[
        "laboratory"
    ],
    "wof:name":"Quantiam Technologies Inc",
    "wof:placetype":"venue"
},
  "geometry": {"coordinates":[-113.446381,53.490829],"type":"Point"}
}