{
  "type": "Feature",
  "properties": {
    "iso:country":"CA",
    "sg:address":"2953 Bathurst St",
    "sg:city":"North York",
    "sg:classifiers":[
        {
            "category":"Real Estate",
            "subcategory":"Surveying",
            "type":"Services"
        }
    ],
    "sg:phone":"+1 416 781 4991",
    "sg:postcode":"M6B 3B2",
    "sg:province":"ON",
    "sg:tags":[
        "surveyor"
    ],
    "wof:name":"Stojanovic Land Surveys",
    "wof:placetype":"venue"
},
  "geometry": {"coordinates":[-79.4288864136,43.7163696289],"type":"Point"}
}