{
  "type": "Feature",
  "properties": {
    "addr:full":"20966 56 Ave Langley BC V3A 7Z2",
    "addr:housenumber":"20966",
    "addr:postcode":"v3a 7z2",
    "addr:street":"56 Ave",
    "iso:country":"CA",
    "sg:address":"20966 56 Ave",
    "sg:city":"Langley",
    "sg:classifiers":[
        {
            "category":"Retail",
            "subcategory":"Auto Repair",
            "type":"Services"
        }
    ],
    "sg:phone":"+1 604 530 4391",
    "sg:postcode":"V3A 7Z2",
    "sg:province":"BC",
    "sg:tags":[
        "repairing",
        "automobile"
    ],
    "wof:name":"Jiffy Lube",
    "wof:placetype":"venue"
},
  "geometry": {"coordinates":[-122.641914368,49.1044769287],"type":"Point"}
}