{
  "type": "Feature",
  "properties": {
    "addr:full":"34 Cedar Pointe Dr Barrie ON L4N 5R7",
    "addr:housenumber":"34",
    "addr:postcode":"l4n 5r7",
    "addr:street":"Cedar Pointe Dr",
    "iso:country":"CA",
    "sg:address":"34 Cedar Pointe Dr",
    "sg:city":"Barrie",
    "sg:classifiers":[
        {
            "category":"Wholesale",
            "subcategory":"Electrical",
            "type":"Manufacturing & Wholesale Goods"
        }
    ],
    "sg:phone":"+1 705 737 5771",
    "sg:postcode":"L4N 5R7",
    "sg:province":"ON",
    "sg:tags":[
        "equipment",
        "lighting",
        "fixture",
        "electric"
    ],
    "wof:name":"Darsco Distributors Ltd",
    "wof:placetype":"venue"
},
  "geometry": {"coordinates":[-79.712852,44.380981],"type":"Point"}
}