{
  "type": "Feature",
  "properties": {
    "iso:country":"CA",
    "sg:address":"Airport Rd Terminal 2",
    "sg:city":"Mississauga",
    "sg:classifiers":[
        {
            "category":"Shopping",
            "subcategory":"Optical Goods",
            "type":"Retail Goods"
        }
    ],
    "sg:phone":"+1 905 677 8599",
    "sg:postcode":"L5P 1B5",
    "sg:province":"ON",
    "sg:tags":[
        "sun",
        "goggles",
        "sunglasses"
    ],
    "wof:name":"Sunglass Hut Intl",
    "wof:placetype":"venue"
},
  "geometry": {"coordinates":[-79.64372253419999,43.5882835388],"type":"Point"}
}