{
  "type": "Feature",
  "properties": {
    "addr:full":"141 John St N Arnprior ON K7S 2N5",
    "addr:housenumber":"141",
    "addr:postcode":"k7s 2n5",
    "addr:street":"John St N",
    "iso:country":"CA",
    "sg:address":"141 John St N",
    "sg:city":"Arnprior",
    "sg:classifiers":[
        {
            "category":"Professional",
            "subcategory":"Lawyer & Legal Services",
            "type":"Services"
        }
    ],
    "sg:phone":"+1 613 623 3177",
    "sg:postcode":"K7S 2N5",
    "sg:province":"ON",
    "sg:tags":[
        "attorney"
    ],
    "wof:name":"Mc Lean & Moore",
    "wof:placetype":"venue"
},
  "geometry": {"coordinates":[-76.353477478,45.4342918396],"type":"Point"}
}