{
  "type": "Feature",
  "properties": {
    "addr:full":"9820 110 Ave Fort St John BC V1J 2T1",
    "addr:housenumber":"9820",
    "addr:postcode":"v1j 2t1",
    "addr:street":"110 Ave",
    "iso:country":"CA",
    "sg:address":"9820 110 Ave",
    "sg:city":"Fort St John",
    "sg:classifiers":[
        {
            "category":"Recreation",
            "type":"Entertainment"
        }
    ],
    "sg:phone":"+1 250 785 2736",
    "sg:postcode":"V1J 2T1",
    "sg:province":"BC",
    "sg:tags":[
        "martial",
        "arts",
        "instruction"
    ],
    "wof:name":"Red Dragon Taekwondo School",
    "wof:placetype":"venue"
},
  "geometry": {"coordinates":[-120.84469604500001,56.2554931641],"type":"Point"}
}