{
  "type": "Feature",
  "properties": {
    "addr:full":"5348 Rue Jean-Talon E Saint-Leonard QC H1S 1L5",
    "addr:housenumber":"5348",
    "addr:postcode":"h1s 1l5",
    "addr:street":"Rue Jean-Talon E",
    "iso:country":"CA",
    "sg:address":"5348 Rue Jean-Talon E",
    "sg:city":"Saint-Leonard",
    "sg:classifiers":[
        {
            "category":"Professional",
            "subcategory":"Business Services",
            "type":"Services"
        }
    ],
    "sg:phone":"+1 514 374 8065",
    "sg:postcode":"H1S 1L5",
    "sg:province":"QC",
    "wof:name":"Klm Records",
    "wof:placetype":"venue"
},
  "geometry": {"coordinates":[-73.5816650391,45.5795173645],"type":"Point"}
}