{
  "type": "Feature",
  "properties": {
    "addr:full":"131 North Port Rd Port Perry ON L9L 1B2",
    "addr:housenumber":"131",
    "addr:postcode":"l9l 1b2",
    "addr:street":"North Port Rd",
    "iso:country":"CA",
    "sg:address":"131 North Port Rd",
    "sg:city":"Port Perry",
    "sg:classifiers":[
        {
            "category":"Retail",
            "subcategory":"Repair Shop",
            "type":"Services"
        }
    ],
    "sg:phone":"+1 905 985 4741",
    "sg:postcode":"L9L 1B2",
    "sg:province":"ON",
    "sg:tags":[
        "welding"
    ],
    "wof:name":"Brewster's Reg Welding & Fab",
    "wof:placetype":"venue"
},
  "geometry": {"coordinates":[-78.976456,44.104095],"type":"Point"}
}