{
  "type": "Feature",
  "properties": {
    "addr:full":"Edmonton AB T5S 2H5",
    "addr:postcode":"t5s 2h5",
    "iso:country":"CA",
    "sg:city":"Edmonton",
    "sg:classifiers":[
        {
            "category":"Professional",
            "subcategory":"Accounting & Tax Preparation",
            "type":"Services"
        }
    ],
    "sg:phone":"+1 780 489 4855",
    "sg:postcode":"T5S 2H5",
    "sg:province":"AB",
    "sg:tags":[
        "accountant"
    ],
    "wof:name":"Collard, Edward W",
    "wof:placetype":"venue"
},
  "geometry": {"coordinates":[-113.629211426,53.548740387],"type":"Point"}
}