{
  "type": "Feature",
  "properties": {
    "addr:full":"540 Rue Belvedere S Sherbrooke QC J1H 4B5",
    "addr:housenumber":"540",
    "addr:postcode":"j1h 4b5",
    "addr:street":"Rue Belvedere S",
    "iso:country":"CA",
    "sg:address":"540 Rue Belvedere S",
    "sg:city":"Sherbrooke",
    "sg:classifiers":[
        {
            "category":"Personal",
            "subcategory":"Beauty Salon",
            "type":"Services"
        }
    ],
    "sg:phone":"+1 819 563 5663",
    "sg:postcode":"J1H 4B5",
    "sg:province":"QC",
    "wof:name":"Coiffurium",
    "wof:placetype":"venue"
},
  "geometry": {"coordinates":[-71.8959350586,45.3954429626],"type":"Point"}
}