{
  "type": "Feature",
  "properties": {
    "addr:full":"Mcadam NB E6J 1A1",
    "addr:postcode":"e6j 1a1",
    "iso:country":"CA",
    "sg:city":"Mcadam",
    "sg:classifiers":[
        {
            "category":"Shopping",
            "subcategory":"Bicycles & Sporting Goods",
            "type":"Retail Goods"
        }
    ],
    "sg:phone":"+1 506 784 3514",
    "sg:postcode":"E6J 1A1",
    "sg:province":"NB",
    "sg:tags":[
        "gun",
        "gunsmith"
    ],
    "wof:name":"Gun Dealer",
    "wof:placetype":"venue"
},
  "geometry": {"coordinates":[-67.31192799999999,45.594852],"type":"Point"}
}