{
  "type": "Feature",
  "properties": {
    "iso:country":"CA",
    "sg:address":"1803 Rue Gignac",
    "sg:city":"Shawinigan",
    "sg:classifiers":[
        {
            "category":"Bars & Pubs",
            "type":"Food & Drink"
        }
    ],
    "sg:phone":"+1 819 539 3515",
    "sg:postcode":"G9N 3W9",
    "sg:province":"QC",
    "sg:tags":[
        "lounge",
        "cocktail"
    ],
    "wof:name":"Bar Lido",
    "wof:placetype":"venue"
},
  "geometry": {"coordinates":[-72.7445678711,46.5612602234],"type":"Point"}
}