{
  "type": "Feature",
  "properties": {
    "addr:full":"313 7 Ave SE Calgary AB T2G 0J1",
    "addr:housenumber":"313",
    "addr:postcode":"t2g 0j1",
    "addr:street":"7 Ave Se",
    "iso:country":"CA",
    "sg:address":"313 7 Ave SE",
    "sg:city":"Calgary",
    "sg:classifiers":[
        {
            "category":"Government",
            "subcategory":"Office",
            "type":"Public Place"
        }
    ],
    "sg:phone":"+1 403 268 5861",
    "sg:postcode":"T2G 0J1",
    "sg:province":"AB",
    "sg:tags":[
        "village"
    ],
    "wof:name":"Calgary Secretariat & Corp",
    "wof:placetype":"venue"
},
  "geometry": {"coordinates":[-114.05754852299999,51.0461654663],"type":"Point"}
}