{
  "type": "Feature",
  "properties": {
    "addr:full":"1028 Canyon St Creston BC V0B 1G0",
    "addr:housenumber":"1028",
    "addr:postcode":"bc v0b 1g0",
    "addr:street":"Canyon St",
    "iso:country":"CA",
    "sg:address":"1028 Canyon St",
    "sg:city":"Creston",
    "sg:classifiers":[
        {
            "category":"Shopping",
            "subcategory":"Stationery & Office Supplies",
            "type":"Retail Goods"
        }
    ],
    "sg:phone":"+1 250 428 2568",
    "sg:postcode":"V0B 1G0",
    "sg:province":"BC",
    "sg:tags":[
        "stationer"
    ],
    "wof:name":"Creston Card & Stationery",
    "wof:placetype":"venue"
},
  "geometry": {"coordinates":[-116.512939,49.095596],"type":"Point"}
}