{
  "type": "Feature",
  "properties": {
    "iso:country":"CA",
    "sg:address":"751 3 St SW # 44",
    "sg:city":"Calgary",
    "sg:classifiers":[
        {
            "category":"Restaurant",
            "type":"Food & Drink"
        }
    ],
    "sg:phone":"+1 403 237 5317",
    "sg:postcode":"T2P 4K8",
    "sg:province":"AB",
    "wof:name":"Arby's",
    "wof:placetype":"venue"
},
  "geometry": {"coordinates":[-114.070564,51.046211],"type":"Point"}
}