{
  "type": "Feature",
  "properties": {
    "addr:full":"751 3 St SW # 44 Calgary AB T2P 4K8",
    "addr:housenumber":"751 3",
    "addr:postcode":"t2p 4k8",
    "addr:street":"St Sw # 44",
    "iso:country":"CA",
    "sg:address":"751 3 St SW # 44",
    "sg:city":"Calgary",
    "sg:classifiers":[
        {
            "category":"Restaurant",
            "type":"Food & Drink"
        }
    ],
    "sg:phone":"+1 403 237 5317",
    "sg:postcode":"T2P 4K8",
    "sg:province":"AB",
    "wof:name":"Arby's",
    "wof:placetype":"venue"
},
  "geometry": {"coordinates":[-114.070564,51.046211],"type":"Point"}
}