{
  "type": "Feature",
  "properties": {
    "addr:full":"2200 Martin Grove Rd Etobicoke ON M9V 5H9",
    "addr:housenumber":"2200",
    "addr:postcode":"m9v 5h9",
    "addr:street":"Martin Grove Rd",
    "iso:country":"CA",
    "sg:address":"2200 Martin Grove Rd",
    "sg:city":"Etobicoke",
    "sg:classifiers":[
        {
            "category":"Professional",
            "subcategory":"Management & Consulting",
            "type":"Services"
        }
    ],
    "sg:phone":"+1 416 748 7877",
    "sg:postcode":"M9V 5H9",
    "sg:province":"ON",
    "sg:tags":[
        "consultant",
        "agency",
        "employment",
        "opportunity",
        "business"
    ],
    "wof:name":"Shad Employment Corp",
    "wof:placetype":"venue"
},
  "geometry": {"coordinates":[-79.5992355347,43.7518157959],"type":"Point"}
}