{
  "type": "Feature",
  "properties": {
    "addr:full":"215 LA Ronge Ave LA Ronge SK S0J 1L0",
    "addr:housenumber":"215",
    "addr:postcode":"s0j 1l0",
    "addr:street":"La Ronge Ave",
    "iso:country":"CA",
    "sg:address":"215 LA Ronge Ave",
    "sg:city":"LA Ronge",
    "sg:classifiers":[
        {
            "category":"Organizations",
            "subcategory":"Labor Organization",
            "type":"Services"
        }
    ],
    "sg:phone":"+1 306 425 1201",
    "sg:postcode":"S0J 1L0",
    "sg:province":"SK",
    "wof:name":"Sgeu Missinipi Branch",
    "wof:placetype":"venue"
},
  "geometry": {"coordinates":[-105.295326233,55.1124954224],"type":"Point"}
}