{
  "type": "Feature",
  "properties": {
    "addr:full":"305 9th St W Cardston AB T0K 0K0",
    "addr:housenumber":"305",
    "addr:postcode":"t0k 0k0",
    "addr:street":"9Th St W Cardston",
    "iso:country":"CA",
    "sg:address":"305 9th St W",
    "sg:city":"Cardston",
    "sg:classifiers":[
        {
            "category":"Building & Trades",
            "subcategory":"Plumbing",
            "type":"Services"
        }
    ],
    "sg:phone":"+1 403 653 3000",
    "sg:postcode":"T0K 0K0",
    "sg:province":"AB",
    "sg:tags":[
        "fitter",
        "gas"
    ],
    "wof:name":"Larry's Plumbing & Heating",
    "wof:placetype":"venue"
},
  "geometry": {"coordinates":[-113.322891,49.19857],"type":"Point"}
}