{
  "type": "Feature",
  "properties": {
    "addr:full":"3000 Ch D'Oka Sainte-Marthe-Sur-Le-Lac QC J0N 1P0",
    "addr:postcode":"3000;j0n 1p0",
    "addr:street":"Ch D'Oka",
    "iso:country":"CA",
    "sg:address":"3000 Ch D'Oka",
    "sg:city":"Sainte-Marthe-Sur-Le-Lac",
    "sg:classifiers":[
        {
            "category":"Government",
            "subcategory":"Office",
            "type":"Public Place"
        }
    ],
    "sg:phone":"+1 450 472 7310",
    "sg:postcode":"J0N 1P0",
    "sg:province":"QC",
    "sg:tags":[
        "village"
    ],
    "wof:name":"Ste-Marthe-Sur-Le-Lac Hotel-Vl",
    "wof:placetype":"venue"
},
  "geometry": {"coordinates":[-73.99458300000001,45.501686],"type":"Point"}
}