{
  "type": "Feature",
  "properties": {
    "addr:full":"Kenora ON P9N 1L9",
    "addr:postcode":"p9n 1l9",
    "iso:country":"CA",
    "sg:city":"Kenora",
    "sg:classifiers":[
        {
            "category":"Travel",
            "subcategory":"Hotels & Motels",
            "type":"Entertainment"
        }
    ],
    "sg:phone":"+1 807 468 8845",
    "sg:postcode":"P9N 1L9",
    "sg:province":"ON",
    "wof:name":"Comfort Inn",
    "wof:placetype":"venue"
},
  "geometry": {"coordinates":[-94.471954,49.760063],"type":"Point"}
}