{
  "type": "Feature",
  "properties": {
    "addr:full":"258 Locke St S Hamilton ON L8P 4B9",
    "addr:housenumber":"258",
    "addr:postcode":"l8p 4b9",
    "addr:street":"Locke St S",
    "iso:country":"CA",
    "sg:address":"258 Locke St S",
    "sg:city":"Hamilton",
    "sg:classifiers":[
        {
            "category":"Personal",
            "subcategory":"Beauty Salon",
            "type":"Services"
        }
    ],
    "sg:phone":"+1 905 522 5468",
    "sg:postcode":"L8P 4B9",
    "sg:province":"ON",
    "wof:name":"Kasha",
    "wof:placetype":"venue"
},
  "geometry": {"coordinates":[-79.887024,43.252838],"type":"Point"}
}