{
  "type": "Feature",
  "properties": {
    "addr:full":"357 Main St Landmark MB R0A 0X0",
    "addr:housenumber":"357",
    "addr:postcode":"r0a 0x0",
    "addr:street":"Main St",
    "iso:country":"CA",
    "sg:address":"357 Main St",
    "sg:city":"Landmark",
    "sg:classifiers":[
        {
            "category":"Farming",
            "subcategory":"Nursery",
            "type":"Manufacturing & Wholesale Goods"
        }
    ],
    "sg:phone":"+1 204 355 9993",
    "sg:postcode":"R0A 0X0",
    "sg:province":"MB",
    "sg:tags":[
        "greenhouse"
    ],
    "wof:name":"Landmark Greenhouse & Garden",
    "wof:placetype":"venue"
},
  "geometry": {"coordinates":[-96.819969,49.664165],"type":"Point"}
}