{
  "type": "Feature",
  "properties": {
    "addr:full":"20 Ashwarren Rd North York ON M3J 1Z5",
    "addr:housenumber":"20",
    "addr:postcode":"m3j 1z5",
    "addr:street":"Ashwarren Rd",
    "iso:country":"CA",
    "sg:address":"20 Ashwarren Rd",
    "sg:city":"North York",
    "sg:classifiers":[
        {
            "category":"Manufacturing",
            "subcategory":"Furniture",
            "type":"Manufacturing & Wholesale Goods"
        }
    ],
    "sg:phone":"+1 416 636 3648",
    "sg:postcode":"M3J 1Z5",
    "sg:province":"ON",
    "wof:name":"Division Six",
    "wof:placetype":"venue"
},
  "geometry": {"coordinates":[-79.48204,43.758045],"type":"Point"}
}