{
  "type": "Feature",
  "properties": {
    "addr:full":"55 Boul Notre-Dame Clermont QC G4A 1C2",
    "addr:housenumber":"55",
    "addr:postcode":"g4a 1c2",
    "addr:street":"Boul Notre-Dame",
    "iso:country":"CA",
    "sg:address":"55 Boul Notre-Dame",
    "sg:city":"Clermont",
    "sg:classifiers":[
        {
            "category":"Autos & Motor Vehicles",
            "subcategory":"Fuel & Gas Station",
            "type":"Retail Goods"
        }
    ],
    "sg:phone":"+1 418 439 2141",
    "sg:postcode":"G4A 1C2",
    "sg:province":"QC",
    "sg:tags":[
        "oil"
    ],
    "wof:name":"Olco",
    "wof:placetype":"venue"
},
  "geometry": {"coordinates":[-70.2158203125,47.6887626648],"type":"Point"}
}