{
  "type": "Feature",
  "properties": {
    "iso:country":"CA",
    "sg:city":"York",
    "sg:classifiers":[
        {
            "category":"Health Services",
            "subcategory":"Health Practitioner",
            "type":"Services"
        }
    ],
    "sg:phone":"+1 416 929 9734",
    "sg:postcode":"M5P 2X7",
    "sg:province":"ON",
    "sg:tags":[
        "psychotherapist",
        "counselor",
        "marriage",
        "family"
    ],
    "wof:name":"Schatzky, David",
    "wof:placetype":"venue"
},
  "geometry": {"coordinates":[-79.4127120972,43.6849403381],"type":"Point"}
}