{
  "type": "Feature",
  "properties": {
    "addr:full":"2147 Hastings St E Vancouver BC V5L 1V2",
    "addr:housenumber":"2147",
    "addr:postcode":"v5l 1v2",
    "addr:street":"Hastings St E",
    "iso:country":"CA",
    "sg:address":"2147 Hastings St E",
    "sg:city":"Vancouver",
    "sg:classifiers":[
        {
            "category":"Shopping",
            "subcategory":"Bicycles & Sporting Goods",
            "type":"Retail Goods"
        }
    ],
    "sg:phone":"+1 604 254 0004",
    "sg:postcode":"V5L 1V2",
    "sg:province":"BC",
    "sg:tags":[
        "tackle",
        "fishing"
    ],
    "wof:name":"West Coast Fishing Tackle",
    "wof:placetype":"venue"
},
  "geometry": {"coordinates":[-123.06076049799999,49.2813301086],"type":"Point"}
}