{
  "type": "Feature",
  "properties": {
    "iso:country":"CA",
    "sg:city":"Barrie",
    "sg:classifiers":[
        {
            "category":"Personal",
            "subcategory":"Beauty Salon",
            "type":"Services"
        }
    ],
    "sg:phone":"+1 705 722 9696",
    "sg:postcode":"L4M 4Z8",
    "sg:province":"ON",
    "wof:name":"Natural Solutions",
    "wof:placetype":"venue"
},
  "geometry": {"coordinates":[-79.711395,44.41396],"type":"Point"}
}