{
  "type": "Feature",
  "properties": {
    "addr:full":"Scarborough ON M1J 2J1",
    "addr:postcode":"m1j 2j1",
    "iso:country":"CA",
    "sg:city":"Scarborough",
    "sg:classifiers":[
        {
            "category":"Social Services",
            "subcategory":"Child Care",
            "type":"Services"
        }
    ],
    "sg:phone":"+1 416 264 3158",
    "sg:postcode":"M1J 2J1",
    "sg:province":"ON",
    "wof:name":"Apple Day Care Ctr",
    "wof:placetype":"venue"
},
  "geometry": {"coordinates":[-79.21225738530001,43.7447547913],"type":"Point"}
}