{
  "type": "Feature",
  "properties": {
    "addr:full":"95 Front St E Toronto ON M5E 1C2",
    "addr:housenumber":"95",
    "addr:postcode":"m5e 1c2",
    "addr:street":"Front St E",
    "iso:country":"CA",
    "sg:address":"95 Front St E",
    "sg:city":"Toronto",
    "sg:classifiers":[
        {
            "category":"Wholesale",
            "subcategory":"Meat",
            "type":"Manufacturing & Wholesale Goods"
        }
    ],
    "sg:phone":"+1 416 363 7712",
    "sg:postcode":"M5E 1C2",
    "sg:province":"ON",
    "sg:tags":[
        "butchering"
    ],
    "wof:name":"Sausage King",
    "wof:placetype":"venue"
},
  "geometry": {"coordinates":[-79.371712,43.649162],"type":"Point"}
}