{
  "type": "Feature",
  "properties": {
    "addr:full":"500 Alden Rd Markham ON L3R 5H5",
    "addr:housenumber":"500",
    "addr:postcode":"l3r 5h5",
    "addr:street":"Alden Rd",
    "iso:country":"CA",
    "sg:address":"500 Alden Rd",
    "sg:city":"Markham",
    "sg:classifiers":[
        {
            "category":"Wholesale",
            "subcategory":"Machinery & Supplies",
            "type":"Manufacturing & Wholesale Goods"
        }
    ],
    "sg:phone":"+1 905 513 7831",
    "sg:postcode":"L3R 5H5",
    "sg:province":"ON",
    "sg:tags":[
        "printer",
        "printing",
        "cartridge"
    ],
    "wof:name":"Sogo Technologies Ltd",
    "wof:placetype":"venue"
},
  "geometry": {"coordinates":[-79.33307600000001,43.835419],"type":"Point"}
}