{
  "type": "Feature",
  "properties": {
    "addr:full":"3955 2nd Ave Smithers BC V0J 2N0",
    "addr:housenumber":"3955",
    "addr:postcode":"v0j 2n0",
    "addr:street":"2Nd Ave",
    "iso:country":"CA",
    "sg:address":"3955 2nd Ave",
    "sg:city":"Smithers",
    "sg:classifiers":[
        {
            "category":"Building & Trades",
            "subcategory":"Construction",
            "type":"Services"
        }
    ],
    "sg:phone":"+1 250 847 3179",
    "sg:postcode":"V0J 2N0",
    "sg:province":"BC",
    "sg:tags":[
        "general",
        "handyman",
        "contractor"
    ],
    "wof:name":"Don's Fix-It",
    "wof:placetype":"venue"
},
  "geometry": {"coordinates":[-127.17394256599999,54.7824058533],"type":"Point"}
}