{
  "type": "Feature",
  "properties": {
    "addr:full":"727 9th Ave Regina SK S4N 7P4",
    "addr:housenumber":"727",
    "addr:postcode":"s4n 7p4",
    "addr:street":"9Th Ave",
    "iso:country":"CA",
    "sg:address":"727 9th Ave",
    "sg:city":"Regina",
    "sg:classifiers":[
        {
            "category":"Wholesale",
            "subcategory":"Construction Materials",
            "type":"Manufacturing & Wholesale Goods"
        }
    ],
    "sg:phone":"+1 306 721 5071",
    "sg:postcode":"S4N 7P4",
    "sg:province":"SK",
    "sg:tags":[
        "lumber"
    ],
    "wof:name":"Hardwoods Inc",
    "wof:placetype":"venue"
},
  "geometry": {"coordinates":[-104.591606,50.453316],"type":"Point"}
}