{
  "type": "Feature",
  "properties": {
    "addr:full":"3480 Hurontario St Mississauga ON L5B 1P2",
    "addr:housenumber":"3480",
    "addr:postcode":"l5b 1p2",
    "addr:street":"Hurontario St",
    "iso:country":"CA",
    "sg:address":"3480 Hurontario St",
    "sg:city":"Mississauga",
    "sg:classifiers":[
        {
            "category":"Restaurant",
            "type":"Food & Drink"
        }
    ],
    "sg:phone":"+1 905 279 0975",
    "sg:postcode":"L5B 1P2",
    "sg:province":"ON",
    "wof:name":"Wally's Family Restaurant",
    "wof:placetype":"venue"
},
  "geometry": {"coordinates":[-79.629555,43.589432],"type":"Point"}
}