{
  "type": "Feature",
  "properties": {
    "iso:country":"CA",
    "sg:city":"Tweed",
    "sg:classifiers":[
        {
            "category":"Education",
            "subcategory":"School",
            "type":"Public Place"
        }
    ],
    "sg:phone":"+1 613 478 2719",
    "sg:postcode":"K0K 3J0",
    "sg:province":"ON",
    "wof:name":"Tweed Hungerford Senior Elem",
    "wof:placetype":"venue"
},
  "geometry": {"coordinates":[-77.3110198975,44.4754943848],"type":"Point"}
}