{
  "type": "Feature",
  "properties": {
    "addr:full":"2430 Rue Crevier Saint-Hyacinthe QC J2T 1S9",
    "addr:housenumber":"2430",
    "addr:postcode":"j2t 1s9",
    "addr:street":"Rue Crevier",
    "iso:country":"CA",
    "sg:address":"2430 Rue Crevier",
    "sg:city":"Saint-Hyacinthe",
    "sg:classifiers":[
        {
            "category":"Shopping",
            "subcategory":"Bicycles & Sporting Goods",
            "type":"Retail Goods"
        }
    ],
    "sg:phone":"+1 450 778 1199",
    "sg:postcode":"J2T 1S9",
    "sg:province":"QC",
    "sg:tags":[
        "equipment",
        "gymnasium",
        "supply"
    ],
    "wof:name":"Bellemare Reparations Equip",
    "wof:placetype":"venue"
},
  "geometry": {"coordinates":[-72.950417,45.618599],"type":"Point"}
}