{
  "type": "Feature",
  "properties": {
    "addr:full":"1040 Empress St Winnipeg MB R3G 3H4",
    "addr:housenumber":"1040",
    "addr:postcode":"r3g 3h4",
    "addr:street":"Empress St",
    "iso:country":"CA",
    "sg:address":"1040 Empress St",
    "sg:city":"Winnipeg",
    "sg:classifiers":[
        {
            "category":"Retail",
            "subcategory":"Repair Shop",
            "type":"Services"
        }
    ],
    "sg:phone":"+1 204 774 1624",
    "sg:postcode":"R3G 3H4",
    "sg:province":"MB",
    "sg:tags":[
        "refinishing",
        "furniture"
    ],
    "wof:name":"Cbi Used Office Furniture",
    "wof:placetype":"venue"
},
  "geometry": {"coordinates":[-97.19574,49.896755],"type":"Point"}
}