{
  "type": "Feature",
  "properties": {
    "iso:country":"CA",
    "sg:city":"Eckville",
    "sg:classifiers":[
        {
            "category":"Shopping",
            "subcategory":"Florist",
            "type":"Retail Goods"
        }
    ],
    "sg:phone":"+1 403 746 3592",
    "sg:postcode":"T0M 0X0",
    "sg:province":"AB",
    "wof:name":"Barnyard Floral & Gifts",
    "wof:placetype":"venue"
},
  "geometry": {"coordinates":[-114.361465454,52.3595733643],"type":"Point"}
}