{
  "type": "Feature",
  "properties": {
    "addr:full":"1039 Pritchard Ave Winnipeg MB R2X 0G3",
    "addr:housenumber":"1039",
    "addr:postcode":"r2x 0g3",
    "addr:street":"Pritchard Ave",
    "iso:country":"CA",
    "sg:address":"1039 Pritchard Ave",
    "sg:city":"Winnipeg",
    "sg:classifiers":[
        {
            "category":"Organizations",
            "subcategory":"Religious Organization",
            "type":"Services"
        }
    ],
    "sg:phone":"+1 204 582 2836",
    "sg:postcode":"R2X 0G3",
    "sg:province":"MB",
    "sg:tags":[
        "church"
    ],
    "wof:name":"Filipino United Comm Church",
    "wof:placetype":"venue"
},
  "geometry": {"coordinates":[-97.16678619379999,49.9236831665],"type":"Point"}
}