{
  "type": "Feature",
  "properties": {
    "iso:country":"CA",
    "sg:address":"1109 1st Ave # 2",
    "sg:city":"Whitehorse",
    "sg:classifiers":[
        {
            "category":"Organizations",
            "subcategory":"Professional Association",
            "type":"Services"
        }
    ],
    "sg:phone":"+1 867 668 4711",
    "sg:postcode":"Y1A 5G4",
    "sg:province":"YT",
    "wof:name":"Yukon Quest Intl Assn",
    "wof:placetype":"venue"
},
  "geometry": {"coordinates":[-135.04954528799999,60.7194404602],"type":"Point"}
}