{
  "type": "Feature",
  "properties": {
    "addr:full":"28 Ch DE LA Cote-Saint-Louis O # 12 Blainville QC J7C 1B8",
    "addr:housenumber":"28",
    "addr:postcode":"j7c 1b8",
    "addr:street":"Ch De La Cote-Saint-Louis O # 12",
    "iso:country":"CA",
    "sg:address":"28 Ch DE LA Cote-Saint-Louis O # 12",
    "sg:city":"Blainville",
    "sg:classifiers":[
        {
            "category":"Health Services",
            "subcategory":"Clinic",
            "type":"Services"
        }
    ],
    "sg:phone":"+1 450 435 1023",
    "sg:postcode":"J7C 1B8",
    "sg:province":"QC",
    "sg:tags":[
        "therapist",
        "holistic",
        "practitioner",
        "massage"
    ],
    "wof:name":"Clinique Naturopathique",
    "wof:placetype":"venue"
},
  "geometry": {"coordinates":[-73.845291,45.653545],"type":"Point"}
}