{
  "type": "Feature",
  "properties": {
    "iso:country":"CA",
    "sg:address":"4695 Montee Saint-Hubert",
    "sg:city":"Saint-Hubert",
    "sg:classifiers":[
        {
            "category":"Personal",
            "subcategory":"Beauty Salon",
            "type":"Services"
        }
    ],
    "sg:phone":"+1 450 445 3187",
    "sg:postcode":"J3Y 1V3",
    "sg:province":"QC",
    "wof:name":"Salon DE Coiffure Brin-Folie",
    "wof:placetype":"venue"
},
  "geometry": {"coordinates":[-73.43789672849999,45.4857406616],"type":"Point"}
}