{
  "type": "Feature",
  "properties": {
    "iso:country":"CA",
    "sg:address":"303 Bagot St # 309",
    "sg:city":"Kingston",
    "sg:classifiers":[
        {
            "category":"Professional",
            "subcategory":"Computer Services",
            "type":"Services"
        }
    ],
    "sg:phone":"+1 613 549 8667",
    "sg:postcode":"K7K 5W7",
    "sg:province":"ON",
    "sg:tags":[
        "internet"
    ],
    "wof:name":"Kingston Online Svc",
    "wof:placetype":"venue"
},
  "geometry": {"coordinates":[-76.48393249510001,44.2321815491],"type":"Point"}
}