{
  "type": "Feature",
  "properties": {
    "iso:country":"CA",
    "sg:address":"16050 Hwy 3A",
    "sg:city":"Crawford Bay",
    "sg:classifiers":[
        {
            "category":"Food & Beverages",
            "subcategory":"Groceries & Convenience Stores",
            "type":"Retail Goods"
        }
    ],
    "sg:phone":"+1 250 227 9322",
    "sg:postcode":"V0B 1E0",
    "sg:province":"BC",
    "sg:tags":[
        "grocer"
    ],
    "wof:name":"Crawford Bay Store",
    "wof:placetype":"venue"
},
  "geometry": {"coordinates":[-116.824378967,49.6722793579],"type":"Point"}
}