{
  "type": "Feature",
  "properties": {
    "addr:full":"105 Rue Fecteau Saint-Victor QC G0M 2B0",
    "addr:housenumber":"105",
    "addr:postcode":"g0m 2b0",
    "addr:street":"Rue Fecteau",
    "iso:country":"CA",
    "sg:address":"105 Rue Fecteau",
    "sg:city":"Saint-Victor",
    "sg:classifiers":[
        {
            "category":"Health Services",
            "subcategory":"Doctor",
            "type":"Services"
        }
    ],
    "sg:phone":"+1 418 588 6154",
    "sg:postcode":"G0M 2B0",
    "sg:province":"QC",
    "sg:tags":[
        "clinic"
    ],
    "wof:name":"Clinique Andre Rodrigue",
    "wof:placetype":"venue"
},
  "geometry": {"coordinates":[-70.903961,46.148182],"type":"Point"}
}