{
  "type": "Feature",
  "properties": {
    "addr:full":"SW 20-10-14W Carberry MB R0K 0H0",
    "addr:postcode":"r0k 0h0",
    "addr:street":"Sw 20-10-14W",
    "iso:country":"CA",
    "sg:address":"SW 20-10-14W",
    "sg:city":"Carberry",
    "sg:classifiers":[
        {
            "category":"Wholesale",
            "subcategory":"Chemicals & Plastics",
            "type":"Manufacturing & Wholesale Goods"
        }
    ],
    "sg:phone":"+1 204 834 2702",
    "sg:postcode":"R0K 0H0",
    "sg:province":"MB",
    "wof:name":"Manitoba Starch Products",
    "wof:placetype":"venue"
},
  "geometry": {"coordinates":[-99.3578491211,49.8711853027],"type":"Point"}
}