{
  "type": "Feature",
  "properties": {
    "addr:full":"1017 105 Ave Dawson Creek BC V1G 2L3",
    "addr:housenumber":"1017",
    "addr:postcode":"v1g 2l3",
    "addr:street":"105 Ave",
    "iso:country":"CA",
    "sg:address":"1017 105 Ave",
    "sg:city":"Dawson Creek",
    "sg:classifiers":[
        {
            "category":"Social Services",
            "subcategory":"Child Care",
            "type":"Services"
        }
    ],
    "sg:phone":"+1 250 782 1959",
    "sg:postcode":"V1G 2L3",
    "sg:province":"BC",
    "wof:name":"Parks & Rec Out of School Care",
    "wof:placetype":"venue"
},
  "geometry": {"coordinates":[-120.231438,55.755939],"type":"Point"}
}