{
  "type": "Feature",
  "properties": {
    "addr:full":"14 Taber Rd Etobicoke ON M9W 3A5",
    "addr:housenumber":"14",
    "addr:postcode":"m9w 3a5",
    "addr:street":"Taber Rd",
    "iso:country":"CA",
    "sg:address":"14 Taber Rd",
    "sg:city":"Etobicoke",
    "sg:classifiers":[
        {
            "category":"Retail",
            "subcategory":"Auto Repair",
            "type":"Services"
        }
    ],
    "sg:phone":"+1 416 743 2501",
    "sg:postcode":"M9W 3A5",
    "sg:province":"ON",
    "sg:tags":[
        "body",
        "automobile",
        "painting"
    ],
    "wof:name":"Super Carstar Collision",
    "wof:placetype":"venue"
},
  "geometry": {"coordinates":[-79.5733413696,43.7188262939],"type":"Point"}
}