{
  "type": "Feature",
  "properties": {
    "addr:full":"Sainte-Martine QC J0S 1V0",
    "addr:postcode":"j0s 1v0",
    "iso:country":"CA",
    "sg:city":"Sainte-Martine",
    "sg:classifiers":[
        {
            "category":"Retail",
            "subcategory":"Animal Services",
            "type":"Services"
        }
    ],
    "sg:phone":"+1 450 427 1592",
    "sg:postcode":"J0S 1V0",
    "sg:province":"QC",
    "sg:tags":[
        "pet",
        "grooming",
        "washing"
    ],
    "wof:name":"Patte Douce",
    "wof:placetype":"venue"
},
  "geometry": {"coordinates":[-73.805969,45.243847],"type":"Point"}
}