{
  "type": "Feature",
  "properties": {
    "addr:full":"6680 Springfield Rd Aylmer ON N5H 2R5",
    "addr:housenumber":"6680",
    "addr:postcode":"n5h 2r5",
    "addr:street":"Springfield Rd",
    "iso:country":"CA",
    "sg:address":"6680 Springfield Rd",
    "sg:city":"Aylmer",
    "sg:classifiers":[
        {
            "category":"Home & Garden",
            "subcategory":"Garden Supply",
            "type":"Retail Goods"
        }
    ],
    "sg:phone":"+1 519 773 8529",
    "sg:postcode":"N5H 2R5",
    "sg:province":"ON",
    "sg:tags":[
        "lawn",
        "mower"
    ],
    "wof:name":"Don Irwin Garage",
    "wof:placetype":"venue"
},
  "geometry": {"coordinates":[-80.983627,42.773006],"type":"Point"}
}