{
  "type": "Feature",
  "properties": {
    "addr:full":"2 Irwin Dr Red Lake ON P0V 2M0",
    "addr:housenumber":"2",
    "addr:postcode":"p0v 2m0",
    "addr:street":"Irwin Dr Red",
    "iso:country":"CA",
    "sg:address":"2 Irwin Dr",
    "sg:city":"Red Lake",
    "sg:classifiers":[
        {
            "category":"Organizations",
            "subcategory":"Religious Organization",
            "type":"Services"
        }
    ],
    "sg:phone":"+1 807 727 2291",
    "sg:postcode":"P0V 2M0",
    "sg:province":"ON",
    "sg:tags":[
        "church"
    ],
    "wof:name":"Impact North Ministries",
    "wof:placetype":"venue"
},
  "geometry": {"coordinates":[-93.8221664429,51.0190124512],"type":"Point"}
}