{
  "type": "Feature",
  "properties": {
    "iso:country":"CA",
    "sg:address":"403 Danforth Ave",
    "sg:city":"Toronto",
    "sg:classifiers":[
        {
            "category":"Travel",
            "subcategory":"Travel Agent",
            "type":"Entertainment"
        }
    ],
    "sg:phone":"+1 416 469 1161",
    "sg:postcode":"M4K 1P1",
    "sg:province":"ON",
    "sg:tags":[
        "agency",
        "bureau"
    ],
    "wof:name":"Britain Ireland Europe Ctr",
    "wof:placetype":"venue"
},
  "geometry": {"coordinates":[-79.3516693115,43.6774520874],"type":"Point"}
}