{
  "type": "Feature",
  "properties": {
    "addr:full":"23 Bluewater Rd Bedford NS B4B 1G8",
    "addr:housenumber":"23",
    "addr:postcode":"b4b 1g8",
    "addr:street":"Bluewater Rd",
    "iso:country":"CA",
    "sg:address":"23 Bluewater Rd",
    "sg:city":"Bedford",
    "sg:classifiers":[
        {
            "category":"Building & Trades",
            "subcategory":"Construction",
            "type":"Services"
        }
    ],
    "sg:phone":"+1 902 835 5460",
    "sg:postcode":"B4B 1G8",
    "sg:province":"NS",
    "sg:tags":[
        "excavating",
        "contractor",
        "general"
    ],
    "wof:name":"Lever Construction",
    "wof:placetype":"venue"
},
  "geometry": {"coordinates":[-63.7077102661,44.7260246277],"type":"Point"}
}