{
  "type": "Feature",
  "properties": {
    "iso:country":"CA",
    "sg:address":"1763 Upper James St",
    "sg:city":"Hamilton",
    "sg:classifiers":[
        {
            "category":"Organizations",
            "subcategory":"Religious Organization",
            "type":"Services"
        }
    ],
    "sg:phone":"+1 905 383 0905",
    "sg:postcode":"L9B 1K7",
    "sg:province":"ON",
    "sg:tags":[
        "church"
    ],
    "wof:name":"Harmony Baptist Church",
    "wof:placetype":"venue"
},
  "geometry": {"coordinates":[-79.895416,43.197754],"type":"Point"}
}