{
  "type": "Feature",
  "properties": {
    "addr:full":"153 Rue Seigneuriale Beauport QC G1E 4Y7",
    "addr:housenumber":"153",
    "addr:postcode":"qc g1e 4y7",
    "addr:street":"Rue Seigneuriale",
    "iso:country":"CA",
    "sg:address":"153 Rue Seigneuriale",
    "sg:city":"Beauport",
    "sg:classifiers":[
        {
            "category":"Personal",
            "subcategory":"Tattoo Parlor",
            "type":"Services"
        }
    ],
    "sg:phone":"+1 418 666 3434",
    "sg:postcode":"G1E 4Y7",
    "sg:province":"QC",
    "sg:tags":[
        "tattooing"
    ],
    "wof:name":"Tattoo Dom-Pierre",
    "wof:placetype":"venue"
},
  "geometry": {"coordinates":[-71.19323730470001,46.8687438965],"type":"Point"}
}