{
  "type": "Feature",
  "properties": {
    "addr:full":"272 23E Av E Venise-En-Quebec QC J0J 2K0",
    "addr:housenumber":"272",
    "addr:postcode":"j0j 2k0",
    "addr:street":"23E Av E Venise-En-Quebec",
    "iso:country":"CA",
    "sg:address":"272 23E Av E",
    "sg:city":"Venise-En-Quebec",
    "sg:classifiers":[
        {
            "category":"Travel",
            "subcategory":"Campground",
            "type":"Entertainment"
        }
    ],
    "sg:phone":"+1 450 244 5607",
    "sg:postcode":"J0J 2K0",
    "sg:province":"QC",
    "wof:name":"Domaine Florent",
    "wof:placetype":"venue"
},
  "geometry": {"coordinates":[-73.125275,45.081409],"type":"Point"}
}