{
  "type": "Feature",
  "properties": {
    "addr:full":"10560 98 St NW Edmonton AB T5H 2N4",
    "addr:housenumber":"10560",
    "addr:postcode":"t5h 2n4",
    "addr:street":"98 St Nw",
    "iso:country":"CA",
    "sg:address":"10560 98 St NW",
    "sg:city":"Edmonton",
    "sg:classifiers":[
        {
            "category":"Organizations",
            "subcategory":"Professional Association",
            "type":"Services"
        }
    ],
    "sg:phone":"+1 780 423 6897",
    "sg:postcode":"T5H 2N4",
    "sg:province":"AB",
    "sg:tags":[
        "hall",
        "auditorium"
    ],
    "wof:name":"Croatian Hall",
    "wof:placetype":"venue"
},
  "geometry": {"coordinates":[-113.489990234,53.5494155884],"type":"Point"}
}