{
  "type": "Feature",
  "properties": {
    "iso:country":"CA",
    "sg:address":"445 Edgeley Blvd",
    "sg:city":"Concord",
    "sg:classifiers":[
        {
            "category":"Manufacturing",
            "subcategory":"Printing",
            "type":"Manufacturing & Wholesale Goods"
        }
    ],
    "sg:phone":"+1 905 660 8888",
    "sg:postcode":"L4K 4G1",
    "sg:province":"ON",
    "sg:tags":[
        "printer"
    ],
    "wof:name":"Print on Time",
    "wof:placetype":"venue"
},
  "geometry": {"coordinates":[-79.535172,43.803921],"type":"Point"}
}