{
  "type": "Feature",
  "properties": {
    "iso:country":"CA",
    "sg:address":"169 Rue Alfred-Desrochers",
    "sg:city":"Saint-Augustin-DE-Desmaures",
    "sg:classifiers":[
        {
            "category":"Professional",
            "subcategory":"Business Services",
            "type":"Services"
        }
    ],
    "sg:phone":"+1 418 877 7250",
    "sg:postcode":"G3A 2T1",
    "sg:province":"QC",
    "sg:tags":[
        "translator",
        "interpreter"
    ],
    "wof:name":"Francois Poitras Traductions",
    "wof:placetype":"venue"
},
  "geometry": {"coordinates":[-71.4060058594,46.7404785156],"type":"Point"}
}