{
  "type": "Feature",
  "properties": {
    "addr:full":"6932 Bow Cres NW Calgary AB T3B 2B9",
    "addr:housenumber":"6932",
    "addr:postcode":"t3b 2b9",
    "addr:street":"Bow Cres Nw",
    "iso:country":"CA",
    "sg:address":"6932 Bow Cres NW",
    "sg:city":"Calgary",
    "sg:classifiers":[
        {
            "category":"Real Estate",
            "subcategory":"Architect",
            "type":"Services"
        }
    ],
    "sg:phone":"+1 403 247 5335",
    "sg:postcode":"T3B 2B9",
    "sg:province":"AB",
    "sg:tags":[
        "illustrator",
        "architectural"
    ],
    "wof:name":"Eldridge Design Partnership",
    "wof:placetype":"venue"
},
  "geometry": {"coordinates":[-114.188759,51.092484],"type":"Point"}
}