{
  "type": "Feature",
  "properties": {
    "addr:full":"302 Poplar Hartney MB R0M 0X0",
    "addr:housenumber":"302",
    "addr:postcode":"r0m 0x0",
    "addr:street":"Poplar",
    "iso:country":"CA",
    "sg:address":"302 Poplar",
    "sg:city":"Hartney",
    "sg:classifiers":[
        {
            "category":"Organizations",
            "subcategory":"Professional Association",
            "type":"Services"
        }
    ],
    "sg:phone":"+1 204 858 2289",
    "sg:postcode":"R0M 0X0",
    "sg:province":"MB",
    "sg:tags":[
        "club"
    ],
    "wof:name":"Royal Canadian Legion",
    "wof:placetype":"venue"
},
  "geometry": {"coordinates":[-100.528015,49.477478],"type":"Point"}
}