{
  "type": "Feature",
  "properties": {
    "addr:full":"555 Ennis Rd Ennismore ON K0L 1T0",
    "addr:housenumber":"555",
    "addr:postcode":"k0l 1t0",
    "addr:street":"Ennis Rd",
    "iso:country":"CA",
    "sg:address":"555 Ennis Rd",
    "sg:city":"Ennismore",
    "sg:classifiers":[
        {
            "category":"Restaurant",
            "type":"Food & Drink"
        }
    ],
    "sg:phone":"+1 705 292 5200",
    "sg:postcode":"K0L 1T0",
    "sg:province":"ON",
    "sg:tags":[
        "club",
        "rooms",
        "banquet",
        "curling"
    ],
    "wof:name":"Ennismore Curling Club & Hall",
    "wof:placetype":"venue"
},
  "geometry": {"coordinates":[-78.425377,44.41114],"type":"Point"}
}