{
  "type": "Feature",
  "properties": {
    "iso:country":"CA",
    "sg:city":"Vancouver",
    "sg:classifiers":[
        {
            "category":"Professional",
            "subcategory":"Management & Consulting",
            "type":"Services"
        }
    ],
    "sg:phone":"+1 604 669 2615",
    "sg:postcode":"V6C 2T7",
    "sg:province":"BC",
    "sg:tags":[
        "consultant",
        "business"
    ],
    "wof:name":"Carob Management Ltd",
    "wof:placetype":"venue"
},
  "geometry": {"coordinates":[-123.115371704,49.2849349976],"type":"Point"}
}