{
  "type": "Feature",
  "properties": {
    "addr:full":"89 Galaxy Blvd Etobicoke ON M9W 6A4",
    "addr:housenumber":"89",
    "addr:postcode":"m9w 6a4",
    "addr:street":"Galaxy Blvd",
    "iso:country":"CA",
    "sg:address":"89 Galaxy Blvd",
    "sg:city":"Etobicoke",
    "sg:classifiers":[
        {
            "category":"Manufacturing",
            "subcategory":"Tools & Machinery",
            "type":"Manufacturing & Wholesale Goods"
        }
    ],
    "sg:phone":"+1 416 674 6764",
    "sg:postcode":"M9W 6A4",
    "sg:province":"ON",
    "sg:tags":[
        "die",
        "maker"
    ],
    "wof:name":"Superior Punchmaster Inc",
    "wof:placetype":"venue"
},
  "geometry": {"coordinates":[-79.585007,43.67894],"type":"Point"}
}