{
  "type": "Feature",
  "properties": {
    "addr:full":"380 Van Wagners Beach Rd Hamilton ON L8E 3L8",
    "addr:housenumber":"380",
    "addr:postcode":"l8e 3l8",
    "addr:street":"Van Wagners Beach Rd",
    "iso:country":"CA",
    "sg:address":"380 Van Wagners Beach Rd",
    "sg:city":"Hamilton",
    "sg:classifiers":[
        {
            "category":"Restaurant",
            "type":"Food & Drink"
        }
    ],
    "sg:phone":"+1 905 544 7122",
    "sg:postcode":"L8E 3L8",
    "sg:province":"ON",
    "wof:name":"Baranga's on the Beach",
    "wof:placetype":"venue"
},
  "geometry": {"coordinates":[-79.76355700000001,43.256866],"type":"Point"}
}