{
  "type": "Feature",
  "properties": {
    "addr:full":"920 Rue Pierre-Caisse Saint-Jean-Sur-Richelieu QC J3B 7Y5",
    "addr:housenumber":"920",
    "addr:postcode":"j3b 7y5",
    "addr:street":"Rue Pierre-Caisse",
    "iso:country":"CA",
    "sg:address":"920 Rue Pierre-Caisse",
    "sg:city":"Saint-Jean-Sur-Richelieu",
    "sg:classifiers":[
        {
            "category":"Wholesale",
            "subcategory":"Metals & Minerals",
            "type":"Manufacturing & Wholesale Goods"
        }
    ],
    "sg:phone":"+1 450 349 5801",
    "sg:postcode":"J3B 7Y5",
    "sg:province":"QC",
    "sg:tags":[
        "steel",
        "warehouse"
    ],
    "wof:name":"Aciers H & H Inc",
    "wof:placetype":"venue"
},
  "geometry": {"coordinates":[-73.29686700000001,45.329445],"type":"Point"}
}