{
  "type": "Feature",
  "properties": {
    "addr:full":"383 Sixth Conc E Millgrove ON L0R 1V0",
    "addr:housenumber":"383",
    "addr:postcode":"l0r 1v0",
    "addr:street":"Sixth Conc E Millgrove",
    "iso:country":"CA",
    "sg:address":"383 Sixth Conc E",
    "sg:city":"Millgrove",
    "sg:classifiers":[
        {
            "category":"Manufacturing",
            "subcategory":"Metals",
            "type":"Manufacturing & Wholesale Goods"
        }
    ],
    "sg:phone":"+1 905 689 8815",
    "sg:postcode":"L0R 1V0",
    "sg:province":"ON",
    "sg:tags":[
        "steel"
    ],
    "wof:name":"Flamboro Technical Svc",
    "wof:placetype":"venue"
},
  "geometry": {"coordinates":[-79.939041,43.35725],"type":"Point"}
}