{
  "type": "Feature",
  "properties": {
    "iso:country":"CA",
    "sg:address":"1216 Brantford Hwy",
    "sg:city":"Cambridge",
    "sg:classifiers":[
        {
            "category":"Utilities",
            "subcategory":"Refuse",
            "type":"Services"
        }
    ],
    "sg:phone":"+1 519 624 8063",
    "sg:postcode":"N1R 5S6",
    "sg:province":"ON",
    "sg:tags":[
        "waste",
        "container",
        "garbage",
        "collection"
    ],
    "wof:name":"Somerton Container & Equipment",
    "wof:placetype":"venue"
},
  "geometry": {"coordinates":[-80.3153305054,43.3614082336],"type":"Point"}
}