{
  "type": "Feature",
  "properties": {
    "addr:full":"Vancouver BC V5T 4N9",
    "addr:postcode":"v5t 4n9",
    "iso:country":"CA",
    "sg:city":"Vancouver",
    "sg:classifiers":[
        {
            "category":"Organizations",
            "subcategory":"Professional Association",
            "type":"Services"
        }
    ],
    "sg:phone":"+1 604 873 1833",
    "sg:postcode":"V5T 4N9",
    "sg:province":"BC",
    "wof:name":"Pacific Ass/First Nation Wmn's",
    "wof:placetype":"venue"
},
  "geometry": {"coordinates":[-123.103218,49.262848],"type":"Point"}
}