{
  "type": "Feature",
  "properties": {
    "addr:full":"275 Main St E Stayner ON L0M 1S0",
    "addr:housenumber":"275",
    "addr:postcode":"l0m 1s0",
    "addr:street":"Main St E Stayner",
    "iso:country":"CA",
    "sg:address":"275 Main St E",
    "sg:city":"Stayner",
    "sg:classifiers":[
        {
            "category":"Manufacturing",
            "subcategory":"Signs",
            "type":"Manufacturing & Wholesale Goods"
        }
    ],
    "sg:phone":"+1 705 428 3888",
    "sg:postcode":"L0M 1S0",
    "sg:province":"ON",
    "wof:name":"Lasting Impression Design",
    "wof:placetype":"venue"
},
  "geometry": {"coordinates":[-80.07830800000001,44.422199],"type":"Point"}
}