{
  "type": "Feature",
  "properties": {
    "addr:full":"156 Maclean St New Glasgow NS B2H 5V5",
    "addr:housenumber":"156",
    "addr:postcode":"b2h 5v5",
    "addr:street":"Maclean St",
    "iso:country":"CA",
    "sg:address":"156 Maclean St",
    "sg:city":"New Glasgow",
    "sg:classifiers":[
        {
            "category":"Banks & Credit Unions",
            "subcategory":"Bank",
            "type":"Services"
        }
    ],
    "sg:phone":"+1 902 755 3944",
    "sg:postcode":"B2H 5V5",
    "sg:province":"NS",
    "sg:tags":[
        "loan",
        "real estate"
    ],
    "wof:name":"Mortgage Centre",
    "wof:placetype":"venue"
},
  "geometry": {"coordinates":[-62.644573,45.58712],"type":"Point"}
}