{
  "type": "Feature",
  "properties": {
    "addr:full":"17590 Boul Des Acadiens Becancour QC G9H 1M3",
    "addr:housenumber":"17590",
    "addr:postcode":"g9h 1m3",
    "addr:street":"Boul Des Acadiens Becancour",
    "iso:country":"CA",
    "sg:address":"17590 Boul Des Acadiens",
    "sg:city":"Becancour",
    "sg:classifiers":[
        {
            "category":"Retail",
            "subcategory":"Animal Services",
            "type":"Services"
        }
    ],
    "sg:phone":"+1 819 233 4401",
    "sg:postcode":"G9H 1M3",
    "sg:province":"QC",
    "sg:tags":[
        "pet",
        "grooming",
        "washing"
    ],
    "wof:name":"Centre DE L'Elegance Animale",
    "wof:placetype":"venue"
},
  "geometry": {"coordinates":[-72.51048299999999,46.270092],"type":"Point"}
}