{
  "type": "Feature",
  "properties": {
    "addr:full":"2160 Rue Letendre Drummondville QC J2C 7E9",
    "addr:housenumber":"2160",
    "addr:postcode":"j2c 7e9",
    "addr:street":"Rue Letendre",
    "iso:country":"CA",
    "sg:address":"2160 Rue Letendre",
    "sg:city":"Drummondville",
    "sg:classifiers":[
        {
            "category":"Manufacturing",
            "subcategory":"Tools & Machinery",
            "type":"Manufacturing & Wholesale Goods"
        }
    ],
    "sg:phone":"+1 819 478 7999",
    "sg:postcode":"J2C 7E9",
    "sg:province":"QC",
    "sg:tags":[
        "engine"
    ],
    "wof:name":"Rainville Injection Diesel Inc",
    "wof:placetype":"venue"
},
  "geometry": {"coordinates":[-72.52156066889999,45.8728713989],"type":"Point"}
}