{
  "type": "Feature",
  "properties": {
    "iso:country":"CA",
    "sg:address":"198 Boul Gendron",
    "sg:city":"Saint-Leon-Le-Grand",
    "sg:classifiers":[
        {
            "category":"Retail",
            "subcategory":"Auto Repair",
            "type":"Services"
        }
    ],
    "sg:phone":"+1 418 743 5210",
    "sg:postcode":"G0J 2W0",
    "sg:province":"QC",
    "sg:tags":[
        "repairing",
        "automobile"
    ],
    "wof:name":"Garage Dari Mecanique Esso",
    "wof:placetype":"venue"
},
  "geometry": {"coordinates":[-67.5004196167,48.3854446411],"type":"Point"}
}