{
  "type": "Feature",
  "properties": {
    "addr:full":"3153 Palmer Dr Burlington ON L7M 1L3",
    "addr:housenumber":"3153",
    "addr:postcode":"l7m 1l3",
    "addr:street":"Palmer Dr",
    "iso:country":"CA",
    "sg:address":"3153 Palmer Dr",
    "sg:city":"Burlington",
    "sg:classifiers":[
        {
            "category":"Health Services",
            "subcategory":"Health Practitioner",
            "type":"Services"
        }
    ],
    "sg:phone":"+1 905 336 9475",
    "sg:postcode":"L7M 1L3",
    "sg:province":"ON",
    "sg:tags":[
        "acupuncture"
    ],
    "wof:name":"Reawen Health Promotion Ctr",
    "wof:placetype":"venue"
},
  "geometry": {"coordinates":[-79.815758,43.366585],"type":"Point"}
}