{
  "type": "Feature",
  "properties": {
    "addr:full":"1911 Eglinton Ave E Scarborough ON M1L 2L6",
    "addr:housenumber":"1911",
    "addr:postcode":"m1l 2l6",
    "addr:street":"Eglinton Ave E",
    "iso:country":"CA",
    "sg:address":"1911 Eglinton Ave E",
    "sg:city":"Scarborough",
    "sg:classifiers":[
        {
            "category":"Government",
            "subcategory":"Office",
            "type":"Public Place"
        }
    ],
    "sg:phone":"+1 416 325 0312",
    "sg:postcode":"M1L 2L6",
    "sg:province":"ON",
    "wof:name":"Ontario Probation & Parole",
    "wof:placetype":"venue"
},
  "geometry": {"coordinates":[-79.2907791138,43.727016449],"type":"Point"}
}