{
  "type": "Feature",
  "properties": {
    "addr:full":"Buckland QC G0R 1G0",
    "addr:postcode":"g0r 1g0",
    "addr:street":"Buckland",
    "iso:country":"CA",
    "sg:city":"Buckland",
    "sg:classifiers":[
        {
            "category":"Wholesale",
            "subcategory":"Meat",
            "type":"Manufacturing & Wholesale Goods"
        }
    ],
    "sg:phone":"+1 418 789 2829",
    "sg:postcode":"G0R 1G0",
    "sg:province":"QC",
    "sg:tags":[
        "packer"
    ],
    "wof:name":"Abattoir Rene Bolduc",
    "wof:placetype":"venue"
},
  "geometry": {"coordinates":[-70.545891,46.620548],"type":"Point"}
}