{
  "type": "Feature",
  "properties": {
    "addr:full":"10416 46A St NW Edmonton AB T6A 1Z4",
    "addr:housenumber":"10416",
    "addr:postcode":"t6a 1z4",
    "addr:street":"46A St Nw",
    "iso:country":"CA",
    "sg:address":"10416 46A St NW",
    "sg:city":"Edmonton",
    "sg:classifiers":[
        {
            "category":"Building & Trades",
            "subcategory":"Plumbing",
            "type":"Services"
        }
    ],
    "sg:phone":"+1 780 440 2211",
    "sg:postcode":"T6A 1Z4",
    "sg:province":"AB",
    "sg:tags":[
        "air",
        "conditioning",
        "furnace",
        "system",
        "contractor"
    ],
    "wof:name":"Sundown Sheet Metal Ltd",
    "wof:placetype":"venue"
},
  "geometry": {"coordinates":[-113.41430699999999,53.546696],"type":"Point"}
}