{
  "type": "Feature",
  "properties": {
    "addr:full":"303 Ch Grande-Cote # 105 Rosemere QC J7A 1J7",
    "addr:housenumber":"303",
    "addr:postcode":"j7a 1j7",
    "addr:street":"Ch Grande-Cote # 105",
    "iso:country":"CA",
    "sg:address":"303 Ch Grande-Cote # 105",
    "sg:city":"Rosemere",
    "sg:classifiers":[
        {
            "category":"Professional",
            "subcategory":"Business Services",
            "type":"Services"
        }
    ],
    "sg:phone":"+1 450 621 4311",
    "sg:postcode":"J7A 1J7",
    "sg:province":"QC",
    "sg:tags":[
        "interior",
        "consultant",
        "design",
        "decorator"
    ],
    "wof:name":"Douce Harmonie Inc",
    "wof:placetype":"venue"
},
  "geometry": {"coordinates":[-73.79443359379999,45.634929657],"type":"Point"}
}