{
  "type": "Feature",
  "properties": {
    "addr:full":"141 3rd St W North Vancouver BC V7M 1E7",
    "addr:housenumber":"141",
    "addr:postcode":"v7m 1e7",
    "addr:street":"3Rd St W",
    "iso:country":"CA",
    "sg:address":"141 3rd St W",
    "sg:city":"North Vancouver",
    "sg:classifiers":[
        {
            "category":"Sports & Exercise",
            "subcategory":"Bowling",
            "type":"Entertainment"
        }
    ],
    "sg:phone":"+1 604 985 1212",
    "sg:postcode":"V7M 1E7",
    "sg:province":"BC",
    "sg:tags":[
        "center"
    ],
    "wof:name":"North Shore Sports Bowl",
    "wof:placetype":"venue"
},
  "geometry": {"coordinates":[-123.078453,49.313927],"type":"Point"}
}