{
  "type": "Feature",
  "properties": {
    "addr:full":"Delta BC V4G 1K7",
    "addr:postcode":"v4g 1k7",
    "iso:country":"CA",
    "sg:city":"Delta",
    "sg:classifiers":[
        {
            "category":"Manufacturing",
            "subcategory":"Signs",
            "type":"Manufacturing & Wholesale Goods"
        }
    ],
    "sg:phone":"+1 604 946 2110",
    "sg:postcode":"V4G 1K7",
    "sg:province":"BC",
    "wof:name":"Empire Signworks Inc",
    "wof:placetype":"venue"
},
  "geometry": {"coordinates":[-123.025794983,49.1356506348],"type":"Point"}
}