{
  "type": "Feature",
  "properties": {
    "addr:full":"SW 24 24 8W Ashern MB R0C 0E0",
    "addr:housenumber":"24 8w",
    "addr:postcode":"r0c 0e0",
    "addr:street":"Sw 24",
    "iso:country":"CA",
    "sg:address":"SW 24 24 8W",
    "sg:city":"Ashern",
    "sg:classifiers":[
        {
            "category":"Building & Trades",
            "subcategory":"Plumbing",
            "type":"Services"
        }
    ],
    "sg:phone":"+1 204 768 2156",
    "sg:postcode":"R0C 0E0",
    "sg:province":"MB",
    "sg:tags":[
        "septic"
    ],
    "wof:name":"Du-Rite Septic Svc",
    "wof:placetype":"venue"
},
  "geometry": {"coordinates":[-98.35010528559999,51.1798210144],"type":"Point"}
}