{
  "type": "Feature",
  "properties": {
    "addr:full":"4095 Baxandall Rd Campbell River BC V9H 1A3",
    "addr:housenumber":"4095",
    "addr:postcode":"v9h 1a3",
    "addr:street":"Baxandall Rd",
    "iso:country":"CA",
    "sg:address":"4095 Baxandall Rd",
    "sg:city":"Campbell River",
    "sg:classifiers":[
        {
            "category":"Manufacturing",
            "subcategory":"Lumber",
            "type":"Manufacturing & Wholesale Goods"
        }
    ],
    "sg:phone":"+1 250 926 6601",
    "sg:postcode":"V9H 1A3",
    "sg:province":"BC",
    "sg:tags":[
        "engineer"
    ],
    "wof:name":"Forest Resource Svc",
    "wof:placetype":"venue"
},
  "geometry": {"coordinates":[-125.248168945,50.0246086121],"type":"Point"}
}