{
  "type": "Feature",
  "properties": {
    "iso:country":"CA",
    "sg:address":"349 St-Luc",
    "sg:city":"LA Motte",
    "sg:classifiers":[
        {
            "category":"Government",
            "subcategory":"Office",
            "type":"Public Place"
        }
    ],
    "sg:phone":"+1 819 732 2878",
    "sg:postcode":"J0Y 1T0",
    "sg:province":"QC",
    "sg:tags":[
        "municipality"
    ],
    "wof:name":"Municipalite DE LA Motte",
    "wof:placetype":"venue"
},
  "geometry": {"coordinates":[-78.1151428223,48.3277702332],"type":"Point"}
}