{
  "type": "Feature",
  "properties": {
    "addr:full":"7359 First Line W Arthur ON N0G 1A0",
    "addr:housenumber":"7359",
    "addr:postcode":"n0g 1a0",
    "addr:street":"First Line W Arthur",
    "iso:country":"CA",
    "sg:address":"7359 First Line W",
    "sg:city":"Arthur",
    "sg:classifiers":[
        {
            "category":"Freight",
            "type":"Transportation"
        }
    ],
    "sg:phone":"+1 519 848 3402",
    "sg:postcode":"N0G 1A0",
    "sg:province":"ON",
    "sg:tags":[
        "trucking"
    ],
    "wof:name":"Richardson Transport Ltd",
    "wof:placetype":"venue"
},
  "geometry": {"coordinates":[-80.489006,43.810959],"type":"Point"}
}