{
  "type": "Feature",
  "properties": {
    "addr:full":"11220 26 St SW Calgary AB T2W 5A4",
    "addr:housenumber":"11220",
    "addr:postcode":"t2w 5a4",
    "addr:street":"26 St Sw",
    "iso:country":"CA",
    "sg:address":"11220 26 St SW",
    "sg:city":"Calgary",
    "sg:classifiers":[
        {
            "category":"Social Services",
            "subcategory":"Child Care",
            "type":"Services"
        }
    ],
    "sg:phone":"+1 403 281 0200",
    "sg:postcode":"T2W 5A4",
    "sg:province":"AB",
    "wof:name":"Cedarbrae Childcare",
    "wof:placetype":"venue"
},
  "geometry": {"coordinates":[-114.120811,50.953777],"type":"Point"}
}