{
  "type": "Feature",
  "properties": {
    "addr:full":"Port Coquitlam BC V3C 4L3",
    "addr:postcode":"v3c 4l3",
    "iso:country":"CA",
    "sg:city":"Port Coquitlam",
    "sg:classifiers":[
        {
            "category":"Wholesale",
            "subcategory":"Durable Goods & Equipment",
            "type":"Manufacturing & Wholesale Goods"
        }
    ],
    "sg:phone":"+1 604 942 2532",
    "sg:postcode":"V3C 4L3",
    "sg:province":"BC",
    "sg:tags":[
        "representative",
        "manufacturer"
    ],
    "wof:name":"General Sales Syndicate Ltd",
    "wof:placetype":"venue"
},
  "geometry": {"coordinates":[-122.76494598399999,49.2531661987],"type":"Point"}
}