{
  "type": "Feature",
  "properties": {
    "iso:country":"CA",
    "sg:city":"Winnipeg",
    "sg:classifiers":[
        {
            "category":"Food & Beverages",
            "subcategory":"Groceries & Convenience Stores",
            "type":"Retail Goods"
        }
    ],
    "sg:phone":"+1 204 947 3709",
    "sg:postcode":"R3C 4H8",
    "sg:province":"MB",
    "sg:tags":[
        "grocer"
    ],
    "wof:name":"Edmonton Convenience Store",
    "wof:placetype":"venue"
},
  "geometry": {"coordinates":[-97.143394,49.88588],"type":"Point"}
}