{
  "type": "Feature",
  "properties": {
    "addr:full":"98 Belmead Gdns NW Edmonton AB T5T 1J1",
    "addr:housenumber":"98",
    "addr:postcode":"t5t 1j1",
    "addr:street":"Belmead Gdns Nw",
    "iso:country":"CA",
    "sg:address":"98 Belmead Gdns NW",
    "sg:city":"Edmonton",
    "sg:classifiers":[
        {
            "category":"Real Estate",
            "subcategory":"Real Estate Operator",
            "type":"Services"
        }
    ],
    "sg:phone":"+1 780 487 7256",
    "sg:postcode":"T5T 1J1",
    "sg:province":"AB",
    "sg:tags":[
        "condominium"
    ],
    "wof:name":"Belmead Gardens",
    "wof:placetype":"venue"
},
  "geometry": {"coordinates":[-113.49037199999999,53.546219],"type":"Point"}
}