{
  "type": "Feature",
  "properties": {
    "addr:full":"226 St-Patrice Sherrington QC J0L 2N0",
    "addr:housenumber":"226",
    "addr:postcode":"j0l 2n0",
    "addr:street":"St-Patrice Sherrington",
    "iso:country":"CA",
    "sg:address":"226 St-Patrice",
    "sg:city":"Sherrington",
    "sg:classifiers":[
        {
            "category":"Retail",
            "subcategory":"Funeral Services",
            "type":"Services"
        }
    ],
    "sg:phone":"+1 450 454 9669",
    "sg:postcode":"J0L 2N0",
    "sg:province":"QC",
    "sg:tags":[
        "director"
    ],
    "wof:name":"Residence Funeraire R Fortin",
    "wof:placetype":"venue"
},
  "geometry": {"coordinates":[-73.5250778198,45.1661872864],"type":"Point"}
}