{
  "type": "Feature",
  "properties": {
    "iso:country":"CA",
    "sg:address":"1088 Gillett St",
    "sg:city":"Prince George",
    "sg:classifiers":[
        {
            "category":"Organizations",
            "subcategory":"Religious Organization",
            "type":"Services"
        }
    ],
    "sg:phone":"+1 250 564 4097",
    "sg:postcode":"V2M 2V3",
    "sg:province":"BC",
    "sg:tags":[
        "church"
    ],
    "wof:name":"St Mary's Catholic Church",
    "wof:placetype":"venue"
},
  "geometry": {"coordinates":[-122.77500915500001,53.9137763977],"type":"Point"}
}