{
  "type": "Feature",
  "properties": {
    "addr:full":"2 Rue Elie-Rochefort # 2 Port-Cartier QC G5B 2N2",
    "addr:housenumber":"2",
    "addr:postcode":"g5b 2n2",
    "addr:street":"Rue Elie-Rochefort # 2 Port-Cartier",
    "iso:country":"CA",
    "sg:address":"2 Rue Elie-Rochefort # 2",
    "sg:city":"Port-Cartier",
    "sg:classifiers":[
        {
            "category":"Personal",
            "subcategory":"Beauty Salon",
            "type":"Services"
        }
    ],
    "sg:phone":"+1 418 766 6462",
    "sg:postcode":"G5B 2N2",
    "sg:province":"QC",
    "wof:name":"Novostyle Enr",
    "wof:placetype":"venue"
},
  "geometry": {"coordinates":[-66.880943,50.029186],"type":"Point"}
}