{
  "type": "Feature",
  "properties": {
    "addr:full":"5362 Rue Mckenna Montreal QC H3T 1V1",
    "addr:housenumber":"5362",
    "addr:postcode":"h3t 1v1",
    "addr:street":"Rue Mckenna",
    "iso:country":"CA",
    "sg:address":"5362 Rue Mckenna",
    "sg:city":"Montreal",
    "sg:classifiers":[
        {
            "category":"Organizations",
            "subcategory":"Professional Association",
            "type":"Services"
        }
    ],
    "sg:phone":"+1 514 739 7629",
    "sg:postcode":"H3T 1V1",
    "sg:province":"QC",
    "wof:name":"Groupe Monde & Esperance",
    "wof:placetype":"venue"
},
  "geometry": {"coordinates":[-73.6197280884,45.5007514954],"type":"Point"}
}