{
  "type": "Feature",
  "properties": {
    "addr:full":"399 Knowlton Rd Knowlton QC J0E 1V0",
    "addr:housenumber":"399",
    "addr:postcode":"j0e 1v0",
    "addr:street":"Knowlton Rd",
    "iso:country":"CA",
    "sg:address":"399 Knowlton Rd",
    "sg:city":"Knowlton",
    "sg:classifiers":[
        {
            "category":"Health Services",
            "subcategory":"Nursing And Care Facility",
            "type":"Services"
        }
    ],
    "sg:phone":"+1 450 243 6455",
    "sg:postcode":"J0E 1V0",
    "sg:province":"QC",
    "sg:tags":[
        "home",
        "retirement",
        "community",
        "rest"
    ],
    "wof:name":"Knowlbanks",
    "wof:placetype":"venue"
},
  "geometry": {"coordinates":[-72.52122497560001,45.2166938782],"type":"Point"}
}