{
  "type": "Feature",
  "properties": {
    "addr:full":"7038 30 St SE Calgary AB T2C 1N9",
    "addr:housenumber":"7038",
    "addr:postcode":"t2c 1n9",
    "addr:street":"30 St Se",
    "iso:country":"CA",
    "sg:address":"7038 30 St SE",
    "sg:city":"Calgary",
    "sg:classifiers":[
        {
            "category":"Autos & Motor Vehicles",
            "subcategory":"Automobile Sales",
            "type":"Retail Goods"
        }
    ],
    "sg:phone":"+1 403 279 4118",
    "sg:postcode":"T2C 1N9",
    "sg:province":"AB",
    "sg:tags":[
        "contractor"
    ],
    "wof:name":"Trux & Equipment Sales",
    "wof:placetype":"venue"
},
  "geometry": {"coordinates":[-113.983421326,50.9912834167],"type":"Point"}
}