{
  "type": "Feature",
  "properties": {
    "addr:full":"Port Coquitlam BC V3B 1S9",
    "addr:postcode":"v3b 1s9",
    "iso:country":"CA",
    "sg:city":"Port Coquitlam",
    "sg:classifiers":[
        {
            "category":"Health Services",
            "subcategory":"Doctor",
            "type":"Services"
        }
    ],
    "sg:phone":"+1 604 944 8421",
    "sg:postcode":"V3B 1S9",
    "sg:province":"BC",
    "sg:tags":[
        "physician",
        "surgeon"
    ],
    "wof:name":"Prairie Medical",
    "wof:placetype":"venue"
},
  "geometry": {"coordinates":[-122.754211426,49.271270752],"type":"Point"}
}