{
  "type": "Feature",
  "properties": {
    "addr:full":"276 Linwell Rd St Catharines ON L2N 1S7",
    "addr:housenumber":"276",
    "addr:postcode":"l2n 1s7",
    "addr:street":"Linwell Rd",
    "iso:country":"CA",
    "sg:address":"276 Linwell Rd",
    "sg:city":"St Catharines",
    "sg:classifiers":[
        {
            "category":"Health Services",
            "subcategory":"Doctor",
            "type":"Services"
        }
    ],
    "sg:phone":"+1 905 934 9492",
    "sg:postcode":"L2N 1S7",
    "sg:province":"ON",
    "sg:tags":[
        "physician",
        "surgeon"
    ],
    "wof:name":"Teodorini, I MD",
    "wof:placetype":"venue"
},
  "geometry": {"coordinates":[-79.23885300000001,43.194923],"type":"Point"}
}