{
  "type": "Feature",
  "properties": {
    "addr:full":"34 Boul Cartier Riviere-Du-Loup QC G5R 5Z4",
    "addr:housenumber":"34",
    "addr:postcode":"g5r 5z4",
    "addr:street":"Boul Cartier Riviere-Du-Loup",
    "iso:country":"CA",
    "sg:address":"34 Boul Cartier",
    "sg:city":"Riviere-Du-Loup",
    "sg:classifiers":[
        {
            "category":"Farming",
            "subcategory":"Dairy Farm",
            "type":"Manufacturing & Wholesale Goods"
        }
    ],
    "sg:phone":"+1 418 862 8364",
    "sg:postcode":"G5R 5Z4",
    "sg:province":"QC",
    "wof:name":"Natrel Inc",
    "wof:placetype":"venue"
},
  "geometry": {"coordinates":[-69.548897,47.858074],"type":"Point"}
}