{
  "type": "Feature",
  "properties": {
    "addr:full":"9831 82 St NW Edmonton AB T6A 3L7",
    "addr:housenumber":"9831",
    "addr:postcode":"t6a 3l7",
    "addr:street":"82 St Nw",
    "iso:country":"CA",
    "sg:address":"9831 82 St NW",
    "sg:city":"Edmonton",
    "sg:classifiers":[
        {
            "category":"Professional",
            "subcategory":"Accounting & Tax Preparation",
            "type":"Services"
        }
    ],
    "sg:phone":"+1 780 469 3298",
    "sg:postcode":"T6A 3L7",
    "sg:province":"AB",
    "sg:tags":[
        "accountant"
    ],
    "wof:name":"Arial, Lynda A CA",
    "wof:placetype":"venue"
},
  "geometry": {"coordinates":[-113.453217,53.537998],"type":"Point"}
}