{
  "type": "Feature",
  "properties": {
    "addr:full":"Belleterre QC J0Z 1L0",
    "addr:postcode":"j0z 1l0",
    "iso:country":"CA",
    "sg:city":"Belleterre",
    "sg:classifiers":[
        {
            "category":"Government",
            "subcategory":"Office",
            "type":"Public Place"
        }
    ],
    "sg:phone":"+1 819 722 2440",
    "sg:postcode":"J0Z 1L0",
    "sg:province":"QC",
    "wof:name":"Canada Services Infirmiers",
    "wof:placetype":"venue"
},
  "geometry": {"coordinates":[-78.70253,47.388748],"type":"Point"}
}