{
  "type": "Feature",
  "properties": {
    "iso:country":"CA",
    "sg:address":"909 Pantera Dr",
    "sg:city":"Mississauga",
    "sg:classifiers":[
        {
            "category":"Manufacturing",
            "subcategory":"Tools & Machinery",
            "type":"Manufacturing & Wholesale Goods"
        }
    ],
    "sg:phone":"+1 905 625 9571",
    "sg:postcode":"L4W 2R9",
    "sg:province":"ON",
    "sg:tags":[
        "die",
        "maker"
    ],
    "wof:name":"J M Die Ltd",
    "wof:placetype":"venue"
},
  "geometry": {"coordinates":[-79.63994598390001,43.6296539307],"type":"Point"}
}