{
  "type": "Feature",
  "properties": {
    "addr:full":"1950 Boul DE LA Concorde E Laval QC H7G 4P5",
    "addr:housenumber":"1950",
    "addr:postcode":"qc h7g 4p5",
    "addr:street":"Boul De La Concorde E",
    "iso:country":"CA",
    "sg:address":"1950 Boul DE LA Concorde E",
    "sg:city":"Laval",
    "sg:classifiers":[
        {
            "category":"Food & Beverages",
            "subcategory":"Groceries & Convenience Stores",
            "type":"Retail Goods"
        }
    ],
    "sg:phone":"+1 450 629 8600",
    "sg:postcode":"H7G 4P5",
    "sg:province":"QC",
    "sg:tags":[
        "grocer"
    ],
    "wof:name":"Loblaws",
    "wof:placetype":"venue"
},
  "geometry": {"coordinates":[-73.6767959595,45.5812454224],"type":"Point"}
}