{
  "type": "Feature",
  "properties": {
    "iso:country":"CA",
    "sg:address":"300 Rue Alexis-Poirier",
    "sg:city":"Saint-Simeon-DE-Bonaventure",
    "sg:classifiers":[
        {
            "category":"Manufacturing",
            "subcategory":"Metals",
            "type":"Manufacturing & Wholesale Goods"
        }
    ],
    "sg:phone":"+1 418 534 2171",
    "sg:postcode":"G0C 3A0",
    "sg:province":"QC",
    "sg:tags":[
        "steel"
    ],
    "wof:name":"Fabrication Delta Inc",
    "wof:placetype":"venue"
},
  "geometry": {"coordinates":[-65.49444580079999,48.0454216003],"type":"Point"}
}