{
  "type": "Feature",
  "properties": {
    "addr:full":"601 Sixth Street Suite 400 New Westminster V3L 3C1",
    "addr:housenumber":"601;400",
    "addr:postcode":"v3l 3c1",
    "addr:street":"Sixth Street Suite",
    "iso:country":"CA",
    "sg:address":"601 Sixth Street Suite 400",
    "sg:city":"New Westminster",
    "sg:classifiers":[
        {
            "category":"Professional",
            "subcategory":"Computer Services",
            "type":"Services"
        }
    ],
    "sg:postcode":"V3L 3C1",
    "sg:tags":[
        "reverse-publishing",
        "dynamic-data-ads",
        "self-serve-classifieds"
    ],
    "sg:website":"http://site.adperfect.com",
    "wof:name":"AdPerfect\u2122",
    "wof:placetype":"venue"
},
  "geometry": {"coordinates":[-122.92037500000001,49.2131922],"type":"Point"}
}