{
  "type": "Feature",
  "properties": {
    "addr:full":"1883 Seldon St Halifax NS B3H 3X3",
    "addr:housenumber":"1883",
    "addr:postcode":"b3h 3x3",
    "addr:street":"Seldon St",
    "iso:country":"CA",
    "sg:address":"1883 Seldon St",
    "sg:city":"Halifax",
    "sg:classifiers":[
        {
            "category":"Professional",
            "subcategory":"Lawyer & Legal Services",
            "type":"Services"
        }
    ],
    "sg:phone":"+1 902 446 3424",
    "sg:postcode":"B3H 3X3",
    "sg:province":"NS",
    "sg:tags":[
        "attorney",
        "broker",
        "business"
    ],
    "wof:name":"Enterprise Brokerage Inc",
    "wof:placetype":"venue"
},
  "geometry": {"coordinates":[-63.5984649658,44.643989563],"type":"Point"}
}