{
  "type": "Feature",
  "properties": {
    "addr:full":"400 Boul Maloney E # 201 Gatineau QC J8P 1E6",
    "addr:housenumber":"400",
    "addr:postcode":"j8p 1e6",
    "addr:street":"Boul Maloney E # 201",
    "iso:country":"CA",
    "sg:address":"400 Boul Maloney E # 201",
    "sg:city":"Gatineau",
    "sg:classifiers":[
        {
            "category":"Health Services",
            "subcategory":"Health Practitioner",
            "type":"Services"
        }
    ],
    "sg:phone":"+1 819 643 3337",
    "sg:postcode":"J8P 1E6",
    "sg:province":"QC",
    "sg:tags":[
        "physiotherapist"
    ],
    "wof:name":"Physio Outaouais",
    "wof:placetype":"venue"
},
  "geometry": {"coordinates":[-75.63995361329999,45.4844818115],"type":"Point"}
}