{
  "type": "Feature",
  "properties": {
    "iso:country":"CA",
    "sg:address":"3457 Av Du Parc",
    "sg:city":"Montreal",
    "sg:classifiers":[
        {
            "category":"Retail",
            "subcategory":"Laundry & Dry Cleaning",
            "type":"Services"
        }
    ],
    "sg:phone":"+1 514 288 1218",
    "sg:postcode":"H2X 2H6",
    "sg:province":"QC",
    "sg:tags":[
        "cleaners",
        "rug",
        "carpet"
    ],
    "wof:name":"Ararat Tapis Cie Ltee",
    "wof:placetype":"venue"
},
  "geometry": {"coordinates":[-73.5725326538,45.5091133118],"type":"Point"}
}