{
  "type": "Feature",
  "properties": {
    "addr:full":"Kakabeka Falls ON P0T 1W0",
    "addr:postcode":"p0t 1w0",
    "addr:street":"Kakabeka Falls",
    "iso:country":"CA",
    "sg:city":"Kakabeka Falls",
    "sg:classifiers":[
        {
            "category":"Shopping",
            "subcategory":"Bicycles & Sporting Goods",
            "type":"Retail Goods"
        }
    ],
    "sg:phone":"+1 807 473 9321",
    "sg:postcode":"P0T 1W0",
    "sg:province":"ON",
    "sg:tags":[
        "bait",
        "fishing"
    ],
    "wof:name":"Larry's Village Bait Shop",
    "wof:placetype":"venue"
},
  "geometry": {"coordinates":[-89.61456298829999,48.4017410278],"type":"Point"}
}