{
  "type": "Feature",
  "properties": {
    "addr:full":"5 Av Renfrew Westmount QC H3Y 2X3",
    "addr:postcode":"h3y 2x3",
    "addr:street":"Av Renfrew",
    "iso:country":"CA",
    "sg:address":"5 Av Renfrew",
    "sg:city":"Westmount",
    "sg:classifiers":[
        {
            "category":"Professional",
            "subcategory":"Management & Consulting",
            "type":"Services"
        }
    ],
    "sg:phone":"+1 514 488 3003",
    "sg:postcode":"H3Y 2X3",
    "sg:province":"QC",
    "sg:tags":[
        "marketing",
        "consultant"
    ],
    "wof:name":"Vpb Marketing Inc",
    "wof:placetype":"venue"
},
  "geometry": {"coordinates":[-73.60715500000001,45.486713],"type":"Point"}
}