{
  "type": "Feature",
  "properties": {
    "addr:full":"7 Walker Rd Virgil ON L0S 1T0",
    "addr:housenumber":"7",
    "addr:postcode":"l0s 1t0",
    "addr:street":"Walker Rd",
    "iso:country":"CA",
    "sg:address":"7 Walker Rd",
    "sg:city":"Virgil",
    "sg:classifiers":[
        {
            "category":"Autos & Motor Vehicles",
            "subcategory":"Motorcycle Sales",
            "type":"Retail Goods"
        }
    ],
    "sg:phone":"+1 905 468 0076",
    "sg:postcode":"L0S 1T0",
    "sg:province":"ON",
    "sg:tags":[
        "scooter"
    ],
    "wof:name":"Niagara Race Crafters",
    "wof:placetype":"venue"
},
  "geometry": {"coordinates":[-79.1261062622,43.2155532837],"type":"Point"}
}