{
  "type": "Feature",
  "properties": {
    "addr:full":"2549 Montvue Ave Abbotsford BC V2S 3V2",
    "addr:housenumber":"2549",
    "addr:postcode":"v2s 3v2",
    "addr:street":"Montvue Ave",
    "iso:country":"CA",
    "sg:address":"2549 Montvue Ave",
    "sg:city":"Abbotsford",
    "sg:classifiers":[
        {
            "category":"Health Services",
            "subcategory":"Medical Lab",
            "type":"Services"
        }
    ],
    "sg:phone":"+1 604 859 9411",
    "sg:postcode":"V2S 3V2",
    "sg:province":"BC",
    "wof:name":"Shulba, Jerry",
    "wof:placetype":"venue"
},
  "geometry": {"coordinates":[-122.289146,49.048115],"type":"Point"}
}