{
  "type": "Feature",
  "properties": {
    "addr:full":"6594 Rue Clark Montreal QC H2S 3E7",
    "addr:housenumber":"6594",
    "addr:postcode":"h2s 3e7",
    "addr:street":"Rue Clark",
    "iso:country":"CA",
    "sg:address":"6594 Rue Clark",
    "sg:city":"Montreal",
    "sg:classifiers":[
        {
            "category":"Building & Trades",
            "subcategory":"Cleaning & Sanitation",
            "type":"Services"
        }
    ],
    "sg:phone":"+1 514 272 0392",
    "sg:postcode":"H2S 3E7",
    "sg:province":"QC",
    "sg:tags":[
        "janitor"
    ],
    "wof:name":"Atlas Building Svc Ltd",
    "wof:placetype":"venue"
},
  "geometry": {"coordinates":[-73.611412,45.530602],"type":"Point"}
}