{
  "type": "Feature",
  "properties": {
    "addr:full":"Markdale ON N0C 1H0",
    "addr:postcode":"n0c 1h0",
    "iso:country":"CA",
    "sg:city":"Markdale",
    "sg:classifiers":[
        {
            "category":"Autos & Motor Vehicles",
            "subcategory":"Auto Supplies",
            "type":"Retail Goods"
        }
    ],
    "sg:phone":"+1 519 986 9947",
    "sg:postcode":"N0C 1H0",
    "sg:province":"ON",
    "sg:tags":[
        "filter",
        "gas"
    ],
    "wof:name":"Anvil Air Filter Cleaning",
    "wof:placetype":"venue"
},
  "geometry": {"coordinates":[-80.744118,44.29121],"type":"Point"}
}