{
  "type": "Feature",
  "properties": {
    "addr:full":"1451 Island Hwy E Nanoose Bay BC V9P 9A3",
    "addr:housenumber":"1451",
    "addr:postcode":"v9p 9a3",
    "addr:street":"Island Hwy E",
    "iso:country":"CA",
    "sg:address":"1451 Island Hwy E",
    "sg:city":"Nanoose Bay",
    "sg:classifiers":[
        {
            "category":"Autos & Motor Vehicles",
            "subcategory":"Boat Sales",
            "type":"Retail Goods"
        }
    ],
    "sg:phone":"+1 250 468 5900",
    "sg:postcode":"V9P 9A3",
    "sg:province":"BC",
    "sg:tags":[
        "dealer"
    ],
    "wof:name":"Parksville Boathouse Ltd",
    "wof:placetype":"venue"
},
  "geometry": {"coordinates":[-124.249382,49.284012],"type":"Point"}
}