{
  "type": "Feature",
  "properties": {
    "addr:full":"1629 Canning Rd Severn Bridge ON P0E 1N0",
    "addr:housenumber":"1629",
    "addr:postcode":"p0e 1n0",
    "addr:street":"Canning Rd",
    "iso:country":"CA",
    "sg:address":"1629 Canning Rd",
    "sg:city":"Severn Bridge",
    "sg:classifiers":[
        {
            "category":"Travel",
            "subcategory":"Hotels & Motels",
            "type":"Entertainment"
        }
    ],
    "sg:phone":"+1 705 689 5222",
    "sg:postcode":"P0E 1N0",
    "sg:province":"ON",
    "sg:tags":[
        "resort"
    ],
    "wof:name":"Idylwild Resort",
    "wof:placetype":"venue"
},
  "geometry": {"coordinates":[-79.39386,44.782654],"type":"Point"}
}