{
  "type": "Feature",
  "properties": {
    "addr:full":"32 Main St N Rossburn MB R0J 1V0",
    "addr:housenumber":"32",
    "addr:postcode":"r0j 1v0",
    "addr:street":"Main St N Rossburn",
    "iso:country":"CA",
    "sg:address":"32 Main St N",
    "sg:city":"Rossburn",
    "sg:classifiers":[
        {
            "category":"Personal",
            "subcategory":"Beauty Salon",
            "type":"Services"
        }
    ],
    "sg:phone":"+1 204 859 2711",
    "sg:postcode":"R0J 1V0",
    "sg:province":"MB",
    "wof:name":"Marcel's Beauty Salon",
    "wof:placetype":"venue"
},
  "geometry": {"coordinates":[-100.81082916299999,50.6689682007],"type":"Point"}
}