{
  "type": "Feature",
  "properties": {
    "addr:full":"247 Yamaska Ch Saint-Germain-DE-Grantham QC J0C 1K0",
    "addr:housenumber":"247",
    "addr:postcode":"j0c 1k0",
    "iso:country":"CA",
    "sg:address":"247 Yamaska Ch",
    "sg:city":"Saint-Germain-DE-Grantham",
    "sg:classifiers":[
        {
            "category":"Autos & Motor Vehicles",
            "subcategory":"Automobile Sales",
            "type":"Retail Goods"
        }
    ],
    "sg:phone":"+1 819 395 4218",
    "sg:postcode":"J0C 1K0",
    "sg:province":"QC",
    "sg:tags":[
        "car",
        "dealer"
    ],
    "wof:name":"Nic Auto",
    "wof:placetype":"venue"
},
  "geometry": {"coordinates":[-72.56353799999999,45.844009],"type":"Point"}
}