{
  "type": "Feature",
  "properties": {
    "addr:full":"2813 Mill Woods Rd NW Edmonton AB T6K 4A9",
    "addr:housenumber":"2813",
    "addr:postcode":"t6k 4a9",
    "addr:street":"Mill Woods Rd Nw",
    "iso:country":"CA",
    "sg:address":"2813 Mill Woods Rd NW",
    "sg:city":"Edmonton",
    "sg:classifiers":[
        {
            "category":"Restaurant",
            "type":"Food & Drink"
        }
    ],
    "sg:phone":"+1 780 461 4005",
    "sg:postcode":"T6K 4A9",
    "sg:province":"AB",
    "wof:name":"Kfc",
    "wof:placetype":"venue"
},
  "geometry": {"coordinates":[-113.447914,53.459141],"type":"Point"}
}