{
  "type": "Feature",
  "properties": {
    "iso:country":"CA",
    "sg:city":"Brampton",
    "sg:classifiers":[
        {
            "category":"Building & Trades",
            "subcategory":"Landscaping Services",
            "type":"Services"
        }
    ],
    "sg:phone":"+1 905 792 7026",
    "sg:postcode":"L6T 5K9",
    "sg:province":"ON",
    "sg:tags":[
        "sod",
        "sodding"
    ],
    "wof:name":"Alpine Sodding CO",
    "wof:placetype":"venue"
},
  "geometry": {"coordinates":[-79.651169,43.735287],"type":"Point"}
}