{
  "type": "Feature",
  "properties": {
    "addr:full":"465 Rue Des Tilleuls Fleurimont QC J1G 4T8",
    "addr:housenumber":"465",
    "addr:postcode":"j1g 4t8",
    "addr:street":"Rue Des Tilleuls",
    "iso:country":"CA",
    "sg:address":"465 Rue Des Tilleuls",
    "sg:city":"Fleurimont",
    "sg:classifiers":[
        {
            "category":"Personal",
            "subcategory":"Beauty Salon",
            "type":"Services"
        }
    ],
    "sg:phone":"+1 819 566 4790",
    "sg:postcode":"J1G 4T8",
    "sg:province":"QC",
    "wof:name":"Salon Celine",
    "wof:placetype":"venue"
},
  "geometry": {"coordinates":[-71.84577899999999,45.402809],"type":"Point"}
}