{
  "type": "Feature",
  "properties": {
    "addr:full":"4631 Keith Ave Terrace BC V8G 1K3",
    "addr:housenumber":"4631",
    "addr:postcode":"v8g 1k3",
    "addr:street":"Keith Ave",
    "iso:country":"CA",
    "sg:address":"4631 Keith Ave",
    "sg:city":"Terrace",
    "sg:classifiers":[
        {
            "category":"Retail",
            "subcategory":"Auto Rental",
            "type":"Services"
        }
    ],
    "sg:phone":"+1 250 635 6866",
    "sg:postcode":"V8G 1K3",
    "sg:province":"BC",
    "sg:tags":[
        "renting",
        "automobile"
    ],
    "wof:name":"Hertz Rent A Car",
    "wof:placetype":"venue"
},
  "geometry": {"coordinates":[-128.602172852,54.5158576965],"type":"Point"}
}