{
  "type": "Feature",
  "properties": {
    "addr:full":"Rte Ayr Ayr ON N0B 1E0",
    "addr:postcode":"n0b 1e0",
    "addr:street":"Rte Ayr",
    "iso:country":"CA",
    "sg:address":"Rte Ayr",
    "sg:city":"Ayr",
    "sg:classifiers":[
        {
            "category":"Organizations",
            "subcategory":"Religious Organization",
            "type":"Services"
        }
    ],
    "sg:phone":"+1 519 696 3005",
    "sg:postcode":"N0B 1E0",
    "sg:province":"ON",
    "sg:tags":[
        "church"
    ],
    "wof:name":"Roseville United Brethren Chr",
    "wof:placetype":"venue"
},
  "geometry": {"coordinates":[-80.4499969482,43.2856559753],"type":"Point"}
}