{
  "type": "Feature",
  "properties": {
    "iso:country":"CA",
    "sg:address":"492 Welland Ave",
    "sg:city":"St Catharines",
    "sg:classifiers":[
        {
            "category":"Wholesale",
            "subcategory":"Metals & Minerals",
            "type":"Manufacturing & Wholesale Goods"
        }
    ],
    "sg:phone":"+1 905 687 7431",
    "sg:postcode":"L2M 5V5",
    "sg:province":"ON",
    "sg:tags":[
        "steel",
        "warehouse"
    ],
    "wof:name":"Public Metal Supply",
    "wof:placetype":"venue"
},
  "geometry": {"coordinates":[-79.2135543823,43.1751976013],"type":"Point"}
}