{
  "type": "Feature",
  "properties": {
    "addr:full":"RR 1 Emsdale ON P0A 1J0",
    "addr:postcode":"p0a 1j0",
    "addr:street":"Rr 1",
    "iso:country":"CA",
    "sg:address":"RR 1",
    "sg:city":"Emsdale",
    "sg:classifiers":[
        {
            "category":"Building & Trades",
            "subcategory":"Electrical",
            "type":"Services"
        }
    ],
    "sg:phone":"+1 705 636 1375",
    "sg:postcode":"P0A 1J0",
    "sg:province":"ON",
    "sg:tags":[
        "electric",
        "contractor"
    ],
    "wof:name":"Glenn R Love Electrical",
    "wof:placetype":"venue"
},
  "geometry": {"coordinates":[-79.31875599999999,45.528534],"type":"Point"}
}