{
  "type": "Feature",
  "properties": {
    "addr:full":"205 Amelia St Cornwall ON K6H 3P3",
    "addr:housenumber":"205",
    "addr:postcode":"k6h 3p3",
    "addr:street":"Amelia St",
    "iso:country":"CA",
    "sg:address":"205 Amelia St",
    "sg:city":"Cornwall",
    "sg:classifiers":[
        {
            "category":"Organizations",
            "subcategory":"Professional Association",
            "type":"Services"
        }
    ],
    "sg:phone":"+1 613 932 7600",
    "sg:postcode":"K6H 3P3",
    "sg:province":"ON",
    "wof:name":"Knights of Columbus",
    "wof:placetype":"venue"
},
  "geometry": {"coordinates":[-74.7243881226,45.0197257996],"type":"Point"}
}