{
  "type": "Feature",
  "properties": {
    "addr:full":"6 Rosewood Ave Guelph ON N1H 5Z9",
    "addr:housenumber":"6",
    "addr:postcode":"n1h 5z9",
    "addr:street":"Rosewood Ave",
    "iso:country":"CA",
    "sg:address":"6 Rosewood Ave",
    "sg:city":"Guelph",
    "sg:classifiers":[
        {
            "category":"Building & Trades",
            "subcategory":"Construction",
            "type":"Services"
        }
    ],
    "sg:phone":"+1 519 822 0027",
    "sg:postcode":"N1H 5Z9",
    "sg:province":"ON",
    "sg:tags":[
        "roofing",
        "contractor"
    ],
    "wof:name":"Dave Merkley Roofing",
    "wof:placetype":"venue"
},
  "geometry": {"coordinates":[-80.26885986329999,43.5375785828],"type":"Point"}
}