{
  "type": "Feature",
  "properties": {
    "addr:full":"388 St. George St Moncton NB E1C 1X4",
    "addr:housenumber":"388",
    "addr:postcode":"e1c 1x4",
    "addr:street":"St. George St",
    "iso:country":"CA",
    "sg:address":"388 St. George St",
    "sg:city":"Moncton",
    "sg:classifiers":[
        {
            "category":"Education",
            "subcategory":"Special Training",
            "type":"Public Place"
        }
    ],
    "sg:phone":"+1 506 854 4750",
    "sg:postcode":"E1C 1X4",
    "sg:province":"NB",
    "sg:tags":[
        "instruction",
        "music"
    ],
    "wof:name":"Ecole DE Musique Du Metro",
    "wof:placetype":"venue"
},
  "geometry": {"coordinates":[-64.7895736694,46.0896835327],"type":"Point"}
}