{
  "type": "Feature",
  "properties": {
    "iso:country":"CA",
    "sg:address":"1750 Steeles Ave W # 18",
    "sg:city":"Concord",
    "sg:classifiers":[
        {
            "category":"Manufacturing",
            "subcategory":"Printing",
            "type":"Manufacturing & Wholesale Goods"
        }
    ],
    "sg:phone":"+1 905 669 2110",
    "sg:postcode":"L4K 2L7",
    "sg:province":"ON",
    "sg:tags":[
        "printer"
    ],
    "wof:name":"Fesco Printing",
    "wof:placetype":"venue"
},
  "geometry": {"coordinates":[-79.477478,43.785667],"type":"Point"}
}