{
  "type": "Feature",
  "properties": {
    "addr:full":"35847 Talbot Line Shedden ON N0L 2E0",
    "addr:housenumber":"35847",
    "addr:postcode":"n0l 2e0",
    "addr:street":"Talbot Line",
    "iso:country":"CA",
    "sg:address":"35847 Talbot Line",
    "sg:city":"Shedden",
    "sg:classifiers":[
        {
            "category":"Food & Beverages",
            "subcategory":"Groceries & Convenience Stores",
            "type":"Retail Goods"
        }
    ],
    "sg:phone":"+1 519 764 2960",
    "sg:postcode":"N0L 2E0",
    "sg:province":"ON",
    "sg:tags":[
        "grocer"
    ],
    "wof:name":"Palmer's Supermarket",
    "wof:placetype":"venue"
},
  "geometry": {"coordinates":[-81.344887,42.739719],"type":"Point"}
}