{
  "type": "Feature",
  "properties": {
    "addr:full":"238 Railway St Eastend SK S0N 0T0",
    "addr:housenumber":"238",
    "addr:postcode":"s0n 0t0",
    "addr:street":"Railway St",
    "iso:country":"CA",
    "sg:address":"238 Railway St",
    "sg:city":"Eastend",
    "sg:classifiers":[
        {
            "category":"Freight",
            "type":"Transportation"
        }
    ],
    "sg:phone":"+1 306 295 3361",
    "sg:postcode":"S0N 0T0",
    "sg:province":"SK",
    "sg:tags":[
        "grain",
        "elevator"
    ],
    "wof:name":"Pioneer Grain CO Ltd",
    "wof:placetype":"venue"
},
  "geometry": {"coordinates":[-108.82870483400001,49.5136566162],"type":"Point"}
}