{
  "type": "Feature",
  "properties": {
    "addr:full":"3538 Ch DE LA Cote-Des-Neiges Montreal QC H3H 1T9",
    "addr:postcode":"3538;h3h 1t9",
    "addr:street":"Ch De La Cote-Des-Neiges",
    "iso:country":"CA",
    "sg:address":"3538 Ch DE LA Cote-Des-Neiges",
    "sg:city":"Montreal",
    "sg:classifiers":[
        {
            "category":"Health Services",
            "subcategory":"Doctor",
            "type":"Services"
        }
    ],
    "sg:phone":"+1 514 934 4554",
    "sg:postcode":"H3H 1T9",
    "sg:province":"QC",
    "sg:tags":[
        "dentist"
    ],
    "wof:name":"Stasinopoulos, Alexandra DDS",
    "wof:placetype":"venue"
},
  "geometry": {"coordinates":[-73.58521270750001,45.4962081909],"type":"Point"}
}