{
  "type": "Feature",
  "properties": {
    "addr:full":"Montreal QC H3B 3X1",
    "addr:postcode":"h3b 3x1",
    "iso:country":"CA",
    "sg:city":"Montreal",
    "sg:classifiers":[
        {
            "category":"Professional",
            "subcategory":"Lawyer & Legal Services",
            "type":"Services"
        }
    ],
    "sg:phone":"+1 514 866 1125",
    "sg:postcode":"H3B 3X1",
    "sg:province":"QC",
    "sg:tags":[
        "attorney"
    ],
    "wof:name":"Blank, Harry QC",
    "wof:placetype":"venue"
},
  "geometry": {"coordinates":[-73.5692977905,45.5029792786],"type":"Point"}
}