{
  "type": "Feature",
  "properties": {
    "addr:full":"2452 Yorks Corners Rd Edwards ON K0A 1V0",
    "addr:housenumber":"2452",
    "addr:postcode":"k0a 1v0",
    "addr:street":"Yorks Corners Rd",
    "iso:country":"CA",
    "sg:address":"2452 Yorks Corners Rd",
    "sg:city":"Edwards",
    "sg:classifiers":[
        {
            "category":"Manufacturing",
            "subcategory":"Lumber",
            "type":"Manufacturing & Wholesale Goods"
        }
    ],
    "sg:phone":"+1 613 821 2751",
    "sg:postcode":"K0A 1V0",
    "sg:province":"ON",
    "sg:tags":[
        "sugar",
        "syrup",
        "rooms",
        "maple",
        "banquet"
    ],
    "wof:name":"Stanley's Olde Maple Lane Farm",
    "wof:placetype":"venue"
},
  "geometry": {"coordinates":[-75.4582901001,45.3085479736],"type":"Point"}
}