{
  "type": "Feature",
  "properties": {
    "addr:full":"Pointe-Fortune QC J0P 1N0",
    "addr:postcode":"j0p 1n0",
    "iso:country":"CA",
    "sg:city":"Pointe-Fortune",
    "sg:classifiers":[
        {
            "category":"Recreation",
            "subcategory":"Marina",
            "type":"Entertainment"
        }
    ],
    "sg:phone":"+1 450 451 6665",
    "sg:postcode":"J0P 1N0",
    "sg:province":"QC",
    "wof:name":"Marina Pointe Fortune",
    "wof:placetype":"venue"
},
  "geometry": {"coordinates":[-74.377174,45.559998],"type":"Point"}
}