{
  "type": "Feature",
  "properties": {
    "addr:full":"2955 66 St NW Edmonton AB T6K 4C1",
    "addr:housenumber":"2955",
    "addr:postcode":"t6k 4c1",
    "addr:street":"66 St Nw",
    "iso:country":"CA",
    "sg:address":"2955 66 St NW",
    "sg:city":"Edmonton",
    "sg:classifiers":[
        {
            "category":"Health Services",
            "subcategory":"Optometrist",
            "type":"Services"
        }
    ],
    "sg:phone":"+1 780 450 3342",
    "sg:postcode":"T6K 4C1",
    "sg:province":"AB",
    "wof:name":"Chi, Charlie Y OD",
    "wof:placetype":"venue"
},
  "geometry": {"coordinates":[-113.433891296,53.4605827332],"type":"Point"}
}