{
  "type": "Feature",
  "properties": {
    "addr:full":"Rouyn-Noranda QC J9X 4P3",
    "addr:postcode":"j9x 4p3",
    "iso:country":"CA",
    "sg:city":"Rouyn-Noranda",
    "sg:classifiers":[
        {
            "category":"Health Services",
            "subcategory":"Health Practitioner",
            "type":"Services"
        }
    ],
    "sg:phone":"+1 819 797 8522",
    "sg:postcode":"J9X 4P3",
    "sg:province":"QC",
    "sg:tags":[
        "psychotherapist",
        "worker",
        "social"
    ],
    "wof:name":"Danielle Bordeleau Travailleus",
    "wof:placetype":"venue"
},
  "geometry": {"coordinates":[-79.01979799999999,48.2393],"type":"Point"}
}