{
  "type": "Feature",
  "properties": {
    "addr:full":"1351 Boul Des Laurentides Vimont QC H7M 2Y2",
    "addr:housenumber":"1351",
    "addr:postcode":"h7m 2y2",
    "addr:street":"Boul Des Laurentides",
    "iso:country":"CA",
    "sg:address":"1351 Boul Des Laurentides",
    "sg:city":"Vimont",
    "sg:classifiers":[
        {
            "category":"Social Services",
            "type":"Services"
        }
    ],
    "sg:phone":"+1 450 668 1803",
    "sg:postcode":"H7M 2Y2",
    "sg:province":"QC",
    "sg:tags":[
        "organization",
        "welfare"
    ],
    "wof:name":"Clsc-Chsld Du Marigot",
    "wof:placetype":"venue"
},
  "geometry": {"coordinates":[-73.710579,45.586826],"type":"Point"}
}