{
  "type": "Feature",
  "properties": {
    "addr:full":"4201 50th St Spirit River AB T0H 3G0",
    "addr:housenumber":"4201",
    "addr:postcode":"t0h 3g0",
    "addr:street":"50Th St",
    "iso:country":"CA",
    "sg:address":"4201 50th St",
    "sg:city":"Spirit River",
    "sg:classifiers":[
        {
            "category":"Freight",
            "type":"Transportation"
        }
    ],
    "sg:phone":"+1 780 864 4444",
    "sg:postcode":"T0H 3G0",
    "sg:province":"AB",
    "sg:tags":[
        "field",
        "oil"
    ],
    "wof:name":"Plains Marketing Canada",
    "wof:placetype":"venue"
},
  "geometry": {"coordinates":[-118.837227,55.77544],"type":"Point"}
}