{
  "type": "Feature",
  "properties": {
    "addr:full":"600 Nation Plantagenet ON K0B 1L0",
    "addr:housenumber":"600",
    "addr:postcode":"k0b 1l0",
    "iso:country":"CA",
    "sg:address":"600 Nation",
    "sg:city":"Plantagenet",
    "sg:classifiers":[
        {
            "category":"Manufacturing",
            "subcategory":"Printing",
            "type":"Manufacturing & Wholesale Goods"
        }
    ],
    "sg:phone":"+1 613 673 5186",
    "sg:postcode":"K0B 1L0",
    "sg:province":"ON",
    "sg:tags":[
        "printer"
    ],
    "wof:name":"Imprimerie Serge Printing",
    "wof:placetype":"venue"
},
  "geometry": {"coordinates":[-74.995216,45.53175],"type":"Point"}
}