{
  "type": "Feature",
  "properties": {
    "addr:full":"Ardrossan AB T8E 2H5",
    "addr:postcode":"t8e 2h5",
    "iso:country":"CA",
    "sg:city":"Ardrossan",
    "sg:classifiers":[
        {
            "category":"Professional",
            "subcategory":"Business Services",
            "type":"Services"
        }
    ],
    "sg:phone":"+1 780 922 2750",
    "sg:postcode":"T8E 2H5",
    "sg:province":"AB",
    "sg:tags":[
        "septic"
    ],
    "wof:name":"Ardralta Vacuum Truck Svc",
    "wof:placetype":"venue"
},
  "geometry": {"coordinates":[-113.148094,53.561554],"type":"Point"}
}