{
  "type": "Feature",
  "properties": {
    "addr:full":"Mississauga ON L5N 2R5",
    "addr:postcode":"l5n 2r5",
    "iso:country":"CA",
    "sg:city":"Mississauga",
    "sg:classifiers":[
        {
            "category":"Health Services",
            "subcategory":"Doctor",
            "type":"Services"
        }
    ],
    "sg:phone":"+1 905 826 4040",
    "sg:postcode":"L5N 2R5",
    "sg:province":"ON",
    "sg:tags":[
        "dentist"
    ],
    "wof:name":"Family Dental Ctr",
    "wof:placetype":"venue"
},
  "geometry": {"coordinates":[-79.75960499999999,43.581436],"type":"Point"}
}