{
  "type": "Feature",
  "properties": {
    "addr:full":"35 Teal Ave Stoney Creek ON L8E 3B1",
    "addr:housenumber":"35",
    "addr:postcode":"l8e 3b1",
    "addr:street":"Teal Ave",
    "iso:country":"CA",
    "sg:address":"35 Teal Ave",
    "sg:city":"Stoney Creek",
    "sg:classifiers":[
        {
            "category":"Manufacturing",
            "subcategory":"Tools & Machinery",
            "type":"Manufacturing & Wholesale Goods"
        }
    ],
    "sg:phone":"+1 905 662 5494",
    "sg:postcode":"L8E 3B1",
    "sg:province":"ON",
    "sg:tags":[
        "machine",
        "shop"
    ],
    "wof:name":"Winona Tool & Mfg",
    "wof:placetype":"venue"
},
  "geometry": {"coordinates":[-79.73165899999999,43.238731],"type":"Point"}
}