{
  "type": "Feature",
  "properties": {
    "addr:full":"372 Queen St S Kitchener ON N2G 1W7",
    "addr:housenumber":"372",
    "addr:postcode":"n2g 1w7",
    "addr:street":"Queen St S",
    "iso:country":"CA",
    "sg:address":"372 Queen St S",
    "sg:city":"Kitchener",
    "sg:classifiers":[
        {
            "category":"Professional",
            "subcategory":"Lawyer & Legal Services",
            "type":"Services"
        }
    ],
    "sg:phone":"+1 519 743 2670",
    "sg:postcode":"N2G 1W7",
    "sg:province":"ON",
    "sg:tags":[
        "attorney"
    ],
    "wof:name":"Opolko, John",
    "wof:placetype":"venue"
},
  "geometry": {"coordinates":[-80.493622,43.445667],"type":"Point"}
}