{
  "type": "Feature",
  "properties": {
    "addr:full":"11403 143 St NW Edmonton AB T5M 1V7",
    "addr:housenumber":"11403",
    "addr:postcode":"t5m 1v7",
    "addr:street":"143 St Nw",
    "iso:country":"CA",
    "sg:address":"11403 143 St NW",
    "sg:city":"Edmonton",
    "sg:classifiers":[
        {
            "category":"Retail",
            "subcategory":"Veterinary Services",
            "type":"Services"
        }
    ],
    "sg:phone":"+1 780 454 8691",
    "sg:postcode":"T5M 1V7",
    "sg:province":"AB",
    "sg:tags":[
        "veterinarian"
    ],
    "wof:name":"General Veterinary Hosp Ltd",
    "wof:placetype":"venue"
},
  "geometry": {"coordinates":[-113.567223,53.563152],"type":"Point"}
}