{
  "type": "Feature",
  "properties": {
    "addr:full":"33 Craigleith Cres Richmond Hill ON L4E 2S3",
    "addr:housenumber":"33",
    "addr:postcode":"l4e 2s3",
    "addr:street":"Craigleith Cres",
    "iso:country":"CA",
    "sg:address":"33 Craigleith Cres",
    "sg:city":"Richmond Hill",
    "sg:classifiers":[
        {
            "category":"Insurance",
            "subcategory":"Insurance Agent",
            "type":"Services"
        }
    ],
    "sg:phone":"+1 905 773 2995",
    "sg:postcode":"L4E 2S3",
    "sg:province":"ON",
    "wof:name":"Mc Auley Insurance Brokers",
    "wof:placetype":"venue"
},
  "geometry": {"coordinates":[-79.452415,43.956059],"type":"Point"}
}