{
  "type": "Feature",
  "properties": {
    "addr:full":"Moose Jaw SK S6H 0V9",
    "addr:postcode":"s6h 0v9",
    "iso:country":"CA",
    "sg:city":"Moose Jaw",
    "sg:classifiers":[
        {
            "category":"Personal",
            "subcategory":"Beauty Salon",
            "type":"Services"
        }
    ],
    "sg:phone":"+1 306 692 2164",
    "sg:postcode":"S6H 0V9",
    "sg:province":"SK",
    "wof:name":"Marvell's Coiffures",
    "wof:placetype":"venue"
},
  "geometry": {"coordinates":[-105.534363,50.390785],"type":"Point"}
}