{
  "type": "Feature",
  "properties": {
    "addr:full":"1406 84th St Coleman AB T0K 0M0",
    "addr:housenumber":"1406",
    "addr:postcode":"t0k 0m0",
    "addr:street":"84Th St",
    "iso:country":"CA",
    "sg:address":"1406 84th St",
    "sg:city":"Coleman",
    "sg:classifiers":[
        {
            "category":"Building & Trades",
            "subcategory":"Construction",
            "type":"Services"
        }
    ],
    "sg:phone":"+1 403 563 3861",
    "sg:postcode":"T0K 0M0",
    "sg:province":"AB",
    "sg:tags":[
        "general",
        "contractor"
    ],
    "wof:name":"Mountain Spirit Construction",
    "wof:placetype":"venue"
},
  "geometry": {"coordinates":[-114.494225,49.631706],"type":"Point"}
}