{
  "type": "Feature",
  "properties": {
    "addr:full":"5536 Rue Jean-Talon E Saint-Leonard QC H1S 1L9",
    "addr:housenumber":"5536",
    "addr:postcode":"h1s 1l9",
    "addr:street":"Rue Jean-Talon E",
    "iso:country":"CA",
    "sg:address":"5536 Rue Jean-Talon E",
    "sg:city":"Saint-Leonard",
    "sg:classifiers":[
        {
            "category":"Retail",
            "subcategory":"Laundry & Dry Cleaning",
            "type":"Services"
        }
    ],
    "sg:phone":"+1 514 256 0331",
    "sg:postcode":"H1S 1L9",
    "sg:province":"QC",
    "sg:tags":[
        "cleaners"
    ],
    "wof:name":"Nettoyeur Franc",
    "wof:placetype":"venue"
},
  "geometry": {"coordinates":[-73.5804519653,45.5817222595],"type":"Point"}
}