{
  "type": "Feature",
  "properties": {
    "addr:full":"5187 Fallingbrook Dr Mississauga ON L5V 1N7",
    "addr:housenumber":"5187",
    "addr:postcode":"l5v 1n7",
    "addr:street":"Fallingbrook Dr",
    "iso:country":"CA",
    "sg:address":"5187 Fallingbrook Dr",
    "sg:city":"Mississauga",
    "sg:classifiers":[
        {
            "category":"Education",
            "subcategory":"School",
            "type":"Public Place"
        }
    ],
    "sg:phone":"+1 905 812 7470",
    "sg:postcode":"L5V 1N7",
    "sg:province":"ON",
    "wof:name":"Fallingbrook Public School",
    "wof:placetype":"venue"
},
  "geometry": {"coordinates":[-79.684753,43.587074],"type":"Point"}
}