{
  "type": "Feature",
  "properties": {
    "iso:country":"CA",
    "sg:address":"45 Penetang St",
    "sg:city":"Barrie",
    "sg:classifiers":[
        {
            "category":"Real Estate",
            "subcategory":"Real Estate Agent",
            "type":"Services"
        }
    ],
    "sg:phone":"+1 705 721 0980",
    "sg:postcode":"L4M 1V5",
    "sg:province":"ON",
    "wof:name":"North Star Real Estate Ltd",
    "wof:placetype":"venue"
},
  "geometry": {"coordinates":[-79.683136,44.395603],"type":"Point"}
}