{
  "type": "Feature",
  "properties": {
    "addr:full":"North York ON M2P 2B8",
    "addr:postcode":"m2p 2b8",
    "iso:country":"CA",
    "sg:city":"North York",
    "sg:classifiers":[
        {
            "category":"Organizations",
            "subcategory":"Professional Association",
            "type":"Services"
        }
    ],
    "sg:phone":"+1 416 223 2333",
    "sg:postcode":"M2P 2B8",
    "sg:province":"ON",
    "wof:name":"Canadian Generic Pharmacutical",
    "wof:placetype":"venue"
},
  "geometry": {"coordinates":[-79.40724945069999,43.7464408875],"type":"Point"}
}