{
  "type": "Feature",
  "properties": {
    "iso:country":"CA",
    "sg:address":"PO Box 100",
    "sg:city":"Nakina",
    "sg:classifiers":[
        {
            "category":"Travel",
            "subcategory":"Hotels & Motels",
            "type":"Entertainment"
        }
    ],
    "sg:phone":"+1 807 329 5753",
    "sg:postcode":"P0T 2H0",
    "sg:province":"ON",
    "sg:tags":[
        "resort"
    ],
    "wof:name":"O'Sullivan Lake Outfitters",
    "wof:placetype":"venue"
},
  "geometry": {"coordinates":[-86.7118606567,50.1797599792],"type":"Point"}
}