{
  "type": "Feature",
  "properties": {
    "addr:full":"302 Lakeshore Rd E Oakville ON L6J 1J2",
    "addr:housenumber":"302",
    "addr:postcode":"l6j 1j2",
    "addr:street":"Lakeshore Rd E",
    "iso:country":"CA",
    "sg:address":"302 Lakeshore Rd E",
    "sg:city":"Oakville",
    "sg:classifiers":[
        {
            "category":"Shopping",
            "subcategory":"Clothing, Apparel, & Fashions",
            "type":"Retail Goods"
        }
    ],
    "sg:phone":"+1 905 844 6201",
    "sg:postcode":"L6J 1J2",
    "sg:province":"ON",
    "sg:tags":[
        "infant",
        "wear"
    ],
    "wof:name":"Top Kids Erin Mills Inc",
    "wof:placetype":"venue"
},
  "geometry": {"coordinates":[-79.6658630371,43.4477310181],"type":"Point"}
}