{
  "type": "Feature",
  "properties": {
    "addr:full":"Victoria BC V8W 1T2",
    "addr:postcode":"v8w 1t2",
    "iso:country":"CA",
    "sg:city":"Victoria",
    "sg:classifiers":[
        {
            "category":"Shopping",
            "type":"Retail Goods"
        }
    ],
    "sg:phone":"+1 250 386 0512",
    "sg:postcode":"V8W 1T2",
    "sg:province":"BC",
    "sg:tags":[
        "picture",
        "frame"
    ],
    "wof:name":"Harbour Trading CO",
    "wof:placetype":"venue"
},
  "geometry": {"coordinates":[-123.368606567,48.4229774475],"type":"Point"}
}