{
  "type": "Feature",
  "properties": {
    "addr:full":"2511 Rue Fiset Jonquiere QC G7S 5W8",
    "addr:housenumber":"2511",
    "addr:postcode":"g7s 5w8",
    "addr:street":"Rue Fiset",
    "iso:country":"CA",
    "sg:address":"2511 Rue Fiset",
    "sg:city":"Jonquiere",
    "sg:classifiers":[
        {
            "category":"Retail",
            "subcategory":"Auto Repair",
            "type":"Services"
        }
    ],
    "sg:phone":"+1 418 548 8073",
    "sg:postcode":"G7S 5W8",
    "sg:province":"QC",
    "sg:tags":[
        "repairing",
        "automobile"
    ],
    "wof:name":"Mecanique Dubose Enr",
    "wof:placetype":"venue"
},
  "geometry": {"coordinates":[-71.16089599999999,48.401196],"type":"Point"}
}