{
  "type": "Feature",
  "properties": {
    "iso:country":"CA",
    "sg:city":"Moonbeam",
    "sg:classifiers":[
        {
            "category":"Shopping",
            "subcategory":"Catalog Store",
            "type":"Retail Goods"
        }
    ],
    "sg:phone":"+1 705 367 2369",
    "sg:postcode":"P0L 1V0",
    "sg:province":"ON",
    "sg:tags":[
        "mail",
        "order",
        "internet"
    ],
    "wof:name":"Sears Canada Inc",
    "wof:placetype":"venue"
},
  "geometry": {"coordinates":[-82.1524810791,49.3414535522],"type":"Point"}
}