{
  "type": "Feature",
  "properties": {
    "addr:full":"96 Roxborough St W Toronto ON M5R 1V1",
    "addr:housenumber":"96",
    "addr:postcode":"m5r 1v1",
    "addr:street":"Roxborough St W",
    "iso:country":"CA",
    "sg:address":"96 Roxborough St W",
    "sg:city":"Toronto",
    "sg:classifiers":[
        {
            "category":"Real Estate",
            "subcategory":"Real Estate Agent",
            "type":"Services"
        }
    ],
    "sg:phone":"+1 416 926 9591",
    "sg:postcode":"M5R 1V1",
    "sg:province":"ON",
    "sg:tags":[
        "appraiser"
    ],
    "wof:name":"Appraisal Services Ltd",
    "wof:placetype":"venue"
},
  "geometry": {"coordinates":[-79.3946685791,43.6773834229],"type":"Point"}
}