{
  "type": "Feature",
  "properties": {
    "addr:full":"226 Livingstone St E Barrie ON L4M 6N6",
    "addr:housenumber":"226",
    "addr:postcode":"l4m 6n6",
    "addr:street":"Livingstone St E",
    "iso:country":"CA",
    "sg:address":"226 Livingstone St E",
    "sg:city":"Barrie",
    "sg:classifiers":[
        {
            "category":"Manufacturing",
            "subcategory":"Signs",
            "type":"Manufacturing & Wholesale Goods"
        }
    ],
    "sg:phone":"+1 705 725 1636",
    "sg:postcode":"L4M 6N6",
    "sg:province":"ON",
    "wof:name":"Dymond Design",
    "wof:placetype":"venue"
},
  "geometry": {"coordinates":[-79.69158899999999,44.420269],"type":"Point"}
}