{
  "type": "Feature",
  "properties": {
    "iso:country":"CA",
    "sg:address":"226 Livingstone St E",
    "sg:city":"Barrie",
    "sg:classifiers":[
        {
            "category":"Manufacturing",
            "subcategory":"Signs",
            "type":"Manufacturing & Wholesale Goods"
        }
    ],
    "sg:phone":"+1 705 725 1636",
    "sg:postcode":"L4M 6N6",
    "sg:province":"ON",
    "wof:name":"Dymond Design",
    "wof:placetype":"venue"
},
  "geometry": {"coordinates":[-79.691589,44.420269],"type":"Point"}
}