{
  "type": "Feature",
  "properties": {
    "addr:full":"Montreal QC H3C 1N8",
    "addr:postcode":"h3c 1n8",
    "iso:country":"CA",
    "sg:city":"Montreal",
    "sg:classifiers":[
        {
            "category":"Shopping",
            "subcategory":"Stationery & Office Supplies",
            "type":"Retail Goods"
        }
    ],
    "sg:phone":"+1 514 875 4200",
    "sg:postcode":"H3C 1N8",
    "sg:province":"QC",
    "wof:name":"Entrepot DE Produits DE Bureau",
    "wof:placetype":"venue"
},
  "geometry": {"coordinates":[-73.55849499999999,45.497807],"type":"Point"}
}