{
  "type": "Feature",
  "properties": {
    "addr:full":"North York ON M3J 3M2",
    "addr:postcode":"m3j 3m2",
    "iso:country":"CA",
    "sg:city":"North York",
    "sg:classifiers":[
        {
            "category":"Wholesale",
            "subcategory":"Hardware",
            "type":"Manufacturing & Wholesale Goods"
        }
    ],
    "sg:phone":"+1 416 650 9073",
    "sg:postcode":"M3J 3M2",
    "sg:province":"ON",
    "sg:tags":[
        "box",
        "mail",
        "duplicating",
        "copying"
    ],
    "wof:name":"Mail Boxes Etc",
    "wof:placetype":"venue"
},
  "geometry": {"coordinates":[-79.4759063721,43.7669868469],"type":"Point"}
}