{
  "type": "Feature",
  "properties": {
    "iso:country":"CA",
    "sg:city":"Ajax",
    "sg:classifiers":[
        {
            "category":"Retail",
            "subcategory":"Laundry & Dry Cleaning",
            "type":"Services"
        }
    ],
    "sg:phone":"+1 905 428 2233",
    "sg:postcode":"L1T 3A6",
    "sg:province":"ON",
    "sg:tags":[
        "cleaners",
        "fur"
    ],
    "wof:name":"Spiro's Furs",
    "wof:placetype":"venue"
},
  "geometry": {"coordinates":[-79.06000518800001,43.8541259766],"type":"Point"}
}