{
  "type": "Feature",
  "properties": {
    "iso:country":"CA",
    "sg:address":"11652 104 Ave NW",
    "sg:city":"Edmonton",
    "sg:classifiers":[
        {
            "category":"Health Services",
            "subcategory":"Doctor",
            "type":"Services"
        }
    ],
    "sg:phone":"+1 780 488 5600",
    "sg:postcode":"T5K 2T7",
    "sg:province":"AB",
    "sg:tags":[
        "physician",
        "surgeon"
    ],
    "wof:name":"Oliver Eye Ctr",
    "wof:placetype":"venue"
},
  "geometry": {"coordinates":[-113.522247315,53.5464477539],"type":"Point"}
}