{
  "type": "Feature",
  "properties": {
    "addr:full":"Concord ON L4K 4G9",
    "addr:postcode":"l4k 4g9",
    "iso:country":"CA",
    "sg:city":"Concord",
    "sg:classifiers":[
        {
            "category":"Professional",
            "subcategory":"Art Services",
            "type":"Services"
        }
    ],
    "sg:phone":"+1 905 669 3972",
    "sg:postcode":"L4K 4G9",
    "sg:province":"ON",
    "sg:tags":[
        "photographer"
    ],
    "wof:name":"Product Photo",
    "wof:placetype":"venue"
},
  "geometry": {"coordinates":[-79.504486,43.802456],"type":"Point"}
}