{
  "type": "Feature",
  "properties": {
    "addr:full":"1122 Rue Du Sud Cowansville QC J2K 2Y3",
    "addr:housenumber":"1122",
    "addr:postcode":"j2k 2y3",
    "addr:street":"Rue Du Sud",
    "iso:country":"CA",
    "sg:address":"1122 Rue Du Sud",
    "sg:city":"Cowansville",
    "sg:classifiers":[
        {
            "category":"Food & Beverages",
            "subcategory":"Groceries & Convenience Stores",
            "type":"Retail Goods"
        }
    ],
    "sg:phone":"+1 450 263 5439",
    "sg:postcode":"J2K 2Y3",
    "sg:province":"QC",
    "sg:tags":[
        "florist"
    ],
    "wof:name":"Loblaws",
    "wof:placetype":"venue"
},
  "geometry": {"coordinates":[-72.750175,45.197132],"type":"Point"}
}