{
  "type": "Feature",
  "properties": {
    "addr:full":"Rossburn MB R0J 1V0",
    "addr:postcode":"r0j 1v0",
    "iso:country":"CA",
    "sg:city":"Rossburn",
    "sg:classifiers":[
        {
            "category":"Organizations",
            "subcategory":"Professional Association",
            "type":"Services"
        }
    ],
    "sg:phone":"+1 204 422 8653",
    "sg:postcode":"R0J 1V0",
    "sg:province":"MB",
    "sg:tags":[
        "club"
    ],
    "wof:name":"Ross Community Ctr",
    "wof:placetype":"venue"
},
  "geometry": {"coordinates":[-100.810829,50.668968],"type":"Point"}
}