{
  "type": "Feature",
  "properties": {
    "addr:full":"233 Dundas St Waterdown ON L0R 2H6",
    "addr:housenumber":"233",
    "addr:postcode":"l0r 2h6",
    "addr:street":"Dundas St",
    "iso:country":"CA",
    "sg:address":"233 Dundas St",
    "sg:city":"Waterdown",
    "sg:classifiers":[
        {
            "category":"Restaurant",
            "type":"Food & Drink"
        }
    ],
    "sg:phone":"+1 905 689 8514",
    "sg:postcode":"L0R 2H6",
    "sg:province":"ON",
    "sg:tags":[
        "parlor",
        "ice",
        "cream"
    ],
    "wof:name":"Dairy Queen",
    "wof:placetype":"venue"
},
  "geometry": {"coordinates":[-79.89919999999999,43.328175],"type":"Point"}
}