{
  "type": "Feature",
  "properties": {
    "addr:full":"87 S Railway Ave Irvine AB T0J 1V0",
    "addr:housenumber":"87",
    "addr:postcode":"t0j 1v0",
    "addr:street":"S Railway Ave",
    "iso:country":"CA",
    "sg:address":"87 S Railway Ave",
    "sg:city":"Irvine",
    "sg:classifiers":[
        {
            "category":"Retail",
            "subcategory":"Auto Repair",
            "type":"Services"
        }
    ],
    "sg:phone":"+1 403 834 2231",
    "sg:postcode":"T0J 1V0",
    "sg:province":"AB",
    "sg:tags":[
        "repairing",
        "automobile"
    ],
    "wof:name":"Redneck Automotive Ltd",
    "wof:placetype":"venue"
},
  "geometry": {"coordinates":[-110.272964,49.956451],"type":"Point"}
}