{
  "type": "Feature",
  "properties": {
    "iso:country":"CA",
    "sg:address":"50 Douglas St",
    "sg:city":"Victoria",
    "sg:classifiers":[
        {
            "category":"Health Services",
            "subcategory":"Nursing And Care Facility",
            "type":"Services"
        }
    ],
    "sg:phone":"+1 250 383 6258",
    "sg:postcode":"V8V 2N8",
    "sg:province":"BC",
    "sg:tags":[
        "home",
        "retirement",
        "convalescent",
        "community"
    ],
    "wof:name":"Douglas House Retirement Lodge",
    "wof:placetype":"venue"
},
  "geometry": {"coordinates":[-123.36895752,48.4103164673],"type":"Point"}
}