{
  "type": "Feature",
  "properties": {
    "addr:full":"4599 Chateau Blvd Whistler BC V0N 1B4",
    "addr:housenumber":"4599",
    "addr:postcode":"v0n 1b4",
    "addr:street":"Chateau Blvd",
    "iso:country":"CA",
    "sg:address":"4599 Chateau Blvd",
    "sg:city":"Whistler",
    "sg:classifiers":[
        {
            "category":"Shopping",
            "subcategory":"Bicycles & Sporting Goods",
            "type":"Retail Goods"
        }
    ],
    "sg:phone":"+1 604 938 2017",
    "sg:postcode":"V0N 1B4",
    "sg:province":"BC",
    "wof:name":"Mountain Adventure Centre",
    "wof:placetype":"venue"
},
  "geometry": {"coordinates":[-122.94581599999999,50.11713],"type":"Point"}
}