{
  "type": "Feature",
  "properties": {
    "iso:country":"CA",
    "sg:city":"Montreal",
    "sg:classifiers":[
        {
            "category":"Organizations",
            "subcategory":"Professional Association",
            "type":"Services"
        }
    ],
    "sg:phone":"+1 514 735 2232",
    "sg:postcode":"H3W 2S5",
    "sg:province":"QC",
    "sg:tags":[
        "social",
        "welfare"
    ],
    "wof:name":"Caribbean Cultural Festivities",
    "wof:placetype":"venue"
},
  "geometry": {"coordinates":[-73.63910675050001,45.4948883057],"type":"Point"}
}