{
  "type": "Feature",
  "properties": {
    "addr:full":"2542 Keele St North York ON M6L 2N8",
    "addr:housenumber":"2542",
    "addr:postcode":"m6l 2n8",
    "addr:street":"Keele St",
    "iso:country":"CA",
    "sg:address":"2542 Keele St",
    "sg:city":"North York",
    "sg:classifiers":[
        {
            "category":"Food & Beverages",
            "subcategory":"Groceries & Convenience Stores",
            "type":"Retail Goods"
        }
    ],
    "sg:phone":"+1 416 249 9511",
    "sg:postcode":"M6L 2N8",
    "sg:province":"ON",
    "sg:tags":[
        "grocer"
    ],
    "wof:name":"Cataldi Supermarket Ltd",
    "wof:placetype":"venue"
},
  "geometry": {"coordinates":[-79.479851,43.715878],"type":"Point"}
}