{
  "type": "Feature",
  "properties": {
    "addr:full":"Calgary AB T2E 4B5",
    "addr:postcode":"t2e 4b5",
    "iso:country":"CA",
    "sg:city":"Calgary",
    "sg:classifiers":[
        {
            "category":"Restaurant",
            "type":"Food & Drink"
        }
    ],
    "sg:phone":"+1 403 276 9154",
    "sg:postcode":"T2E 4B5",
    "sg:province":"AB",
    "sg:tags":[
        "sandwich"
    ],
    "wof:name":"Greenview Deli",
    "wof:placetype":"venue"
},
  "geometry": {"coordinates":[-114.04652400000001,51.093227],"type":"Point"}
}