{
  "type": "Feature",
  "properties": {
    "addr:full":"575 1/2 Rue Des Meurons Winnipeg MB R2H 2P6",
    "addr:housenumber":"575 1 / 2",
    "addr:postcode":"r2h 2p6",
    "addr:street":"Rue Des Meurons",
    "iso:country":"CA",
    "sg:address":"575 1/2 Rue Des Meurons",
    "sg:city":"Winnipeg",
    "sg:classifiers":[
        {
            "category":"Personal",
            "subcategory":"Beauty Salon",
            "type":"Services"
        }
    ],
    "sg:phone":"+1 204 231 4663",
    "sg:postcode":"R2H 2P6",
    "sg:province":"MB",
    "wof:name":"DE Arcangelis Hair & Designs",
    "wof:placetype":"venue"
},
  "geometry": {"coordinates":[-97.112251,49.890942],"type":"Point"}
}