{
  "type": "Feature",
  "properties": {
    "addr:full":"1193 St. Paul St Kelowna BC V1Y 2C6",
    "addr:housenumber":"1193",
    "addr:postcode":"v1y 2c6",
    "addr:street":"St. Paul St",
    "iso:country":"CA",
    "sg:address":"1193 St. Paul St",
    "sg:city":"Kelowna",
    "sg:classifiers":[
        {
            "category":"Building & Trades",
            "subcategory":"Landscaping Services",
            "type":"Services"
        }
    ],
    "sg:phone":"+1 250 868 3855",
    "sg:postcode":"V1Y 2C6",
    "sg:province":"BC",
    "sg:tags":[
        "tree",
        "landscape",
        "contractor"
    ],
    "wof:name":"A-One Tree Svc",
    "wof:placetype":"venue"
},
  "geometry": {"coordinates":[-119.49168396,49.8938522339],"type":"Point"}
}