{
  "type": "Feature",
  "properties": {
    "iso:country":"CA",
    "sg:address":"3225 Boul Wilfrid-Hamel",
    "sg:city":"Quebec",
    "sg:classifiers":[
        {
            "category":"Travel",
            "subcategory":"Hotels & Motels",
            "type":"Entertainment"
        }
    ],
    "sg:phone":"+1 418 871 0846",
    "sg:postcode":"G1P 4C6",
    "sg:province":"QC",
    "wof:name":"Motel Lustre D'Or",
    "wof:placetype":"venue"
},
  "geometry": {"coordinates":[-71.3073272705,46.8062095642],"type":"Point"}
}