{
  "type": "Feature",
  "properties": {
    "iso:country":"CA",
    "sg:address":"249 Danforth Ave",
    "sg:city":"Toronto",
    "sg:classifiers":[
        {
            "category":"Health Services",
            "subcategory":"Doctor",
            "type":"Services"
        }
    ],
    "sg:phone":"+1 416 466 4422",
    "sg:postcode":"M4K 1N2",
    "sg:province":"ON",
    "sg:tags":[
        "dentist"
    ],
    "wof:name":"Dentistry on Danforth",
    "wof:placetype":"venue"
},
  "geometry": {"coordinates":[-79.35493469239999,43.6768722534],"type":"Point"}
}