{
  "type": "Feature",
  "properties": {
    "addr:full":"319 Boul Pierre-Le Gardeur Le Gardeur QC J5Z 3A7",
    "addr:housenumber":"319",
    "addr:postcode":"j5z 3a7",
    "addr:street":"Boul Pierre-Le Gardeur;Gardeur",
    "iso:country":"CA",
    "sg:address":"319 Boul Pierre-Le Gardeur",
    "sg:city":"Le Gardeur",
    "sg:classifiers":[
        {
            "category":"Building & Trades",
            "subcategory":"Electrical",
            "type":"Services"
        }
    ],
    "sg:phone":"+1 450 585 2868",
    "sg:postcode":"J5Z 3A7",
    "sg:province":"QC",
    "sg:tags":[
        "electric",
        "contractor"
    ],
    "wof:name":"Valko Electrique Inc",
    "wof:placetype":"venue"
},
  "geometry": {"coordinates":[-73.477645874,45.7513923645],"type":"Point"}
}