{
  "type": "Feature",
  "properties": {
    "addr:full":"6000 Av Fielding Montreal QC H3X 1T4",
    "addr:housenumber":"6000",
    "addr:postcode":"h3x 1t4",
    "addr:street":"Av Fielding",
    "iso:country":"CA",
    "sg:address":"6000 Av Fielding",
    "sg:city":"Montreal",
    "sg:classifiers":[
        {
            "category":"Education",
            "subcategory":"School",
            "type":"Public Place"
        }
    ],
    "sg:phone":"+1 514 483 7200",
    "sg:postcode":"H3X 1T4",
    "sg:province":"QC",
    "wof:name":"Commission Scolaire English MT",
    "wof:placetype":"venue"
},
  "geometry": {"coordinates":[-73.6364059448,45.4766426086],"type":"Point"}
}