{
  "type": "Feature",
  "properties": {
    "iso:country":"CA",
    "sg:address":"1665 Rue Bouvier",
    "sg:city":"Terrebonne",
    "sg:classifiers":[
        {
            "category":"Building & Trades",
            "subcategory":"Plumbing",
            "type":"Services"
        }
    ],
    "sg:phone":"+1 450 471 0891",
    "sg:postcode":"J6X 2A2",
    "sg:province":"QC",
    "sg:tags":[
        "refrigeration",
        "contractor"
    ],
    "wof:name":"Mc Gregor Refrigeration",
    "wof:placetype":"venue"
},
  "geometry": {"coordinates":[-73.6585922241,45.7161712646],"type":"Point"}
}