{
  "type": "Feature",
  "properties": {
    "addr:full":"770 11E Ave Senneterre QC J0Y 2M0",
    "addr:housenumber":"770",
    "addr:postcode":"j0y 2m0",
    "addr:street":"11E Ave",
    "iso:country":"CA",
    "sg:address":"770 11E Ave",
    "sg:city":"Senneterre",
    "sg:classifiers":[
        {
            "category":"Social Services",
            "subcategory":"Child Care",
            "type":"Services"
        }
    ],
    "sg:phone":"+1 819 737 2918",
    "sg:postcode":"J0Y 2M0",
    "sg:province":"QC",
    "wof:name":"Centre DE LA Petite Enfance",
    "wof:placetype":"venue"
},
  "geometry": {"coordinates":[-77.24714660639999,48.3911628723],"type":"Point"}
}