{
  "type": "Feature",
  "properties": {
    "addr:full":"155 Mcarthur Ave Vanier ON K1A 0R4",
    "addr:housenumber":"155",
    "addr:postcode":"k1a 0r4",
    "addr:street":"Mcarthur Ave",
    "iso:country":"CA",
    "sg:address":"155 Mcarthur Ave",
    "sg:city":"Vanier",
    "sg:classifiers":[
        {
            "category":"Government",
            "subcategory":"Police Station",
            "type":"Public Place"
        }
    ],
    "sg:phone":"+1 613 993 8887",
    "sg:postcode":"K1A 0R4",
    "sg:province":"ON",
    "sg:tags":[
        "department"
    ],
    "wof:name":"Royal Canadian Mounted Police",
    "wof:placetype":"venue"
},
  "geometry": {"coordinates":[-75.663551,45.431202],"type":"Point"}
}