{
  "type": "Feature",
  "properties": {
    "iso:country":"CA",
    "sg:address":"21894 Woodbine Ave",
    "sg:city":"Queensville",
    "sg:classifiers":[
        {
            "category":"Retail",
            "subcategory":"Veterinary Services",
            "type":"Services"
        }
    ],
    "sg:phone":"+1 905 478 1995",
    "sg:postcode":"L0G 1R0",
    "sg:province":"ON",
    "sg:tags":[
        "veterinarian"
    ],
    "wof:name":"Harcourt, Cynthia DVM",
    "wof:placetype":"venue"
},
  "geometry": {"coordinates":[-79.431038,44.164001],"type":"Point"}
}