{
  "type": "Feature",
  "properties": {
    "addr:full":"3613 Rue Fleury E Montreal-Nord QC H1H 2S5",
    "addr:housenumber":"3613",
    "addr:postcode":"h1h 2s5",
    "addr:street":"Rue Fleury E",
    "iso:country":"CA",
    "sg:address":"3613 Rue Fleury E",
    "sg:city":"Montreal-Nord",
    "sg:classifiers":[
        {
            "category":"Health Services",
            "subcategory":"Doctor",
            "type":"Services"
        }
    ],
    "sg:phone":"+1 514 326 3000",
    "sg:postcode":"H1H 2S5",
    "sg:province":"QC",
    "sg:tags":[
        "dentist"
    ],
    "wof:name":"Garberi, Riccardo DDS",
    "wof:placetype":"venue"
},
  "geometry": {"coordinates":[-73.639511,45.582943],"type":"Point"}
}