{
  "type": "Feature",
  "properties": {
    "addr:full":"528 Hudson St Winnipeg MB R3T 4E3",
    "addr:housenumber":"528",
    "addr:postcode":"r3t 4e3",
    "addr:street":"Hudson St",
    "iso:country":"CA",
    "sg:address":"528 Hudson St",
    "sg:city":"Winnipeg",
    "sg:classifiers":[
        {
            "category":"Real Estate",
            "subcategory":"Real Estate Operator",
            "type":"Services"
        }
    ],
    "sg:phone":"+1 204 284 7228",
    "sg:postcode":"R3T 4E3",
    "sg:province":"MB",
    "sg:tags":[
        "apartment"
    ],
    "wof:name":"Fort Garry Rotary Villa",
    "wof:placetype":"venue"
},
  "geometry": {"coordinates":[-97.15464,49.829494],"type":"Point"}
}