{
  "type": "Feature",
  "properties": {
    "addr:full":"2241 2nd Ave Whitehorse YT Y1A 5W1",
    "addr:housenumber":"2241",
    "addr:postcode":"y1a 5w1",
    "addr:street":"2Nd Ave",
    "iso:country":"CA",
    "sg:address":"2241 2nd Ave",
    "sg:city":"Whitehorse",
    "sg:classifiers":[
        {
            "category":"Restaurant",
            "type":"Food & Drink"
        }
    ],
    "sg:phone":"+1 867 667 4992",
    "sg:postcode":"Y1A 5W1",
    "sg:province":"YT",
    "sg:tags":[
        "pizza"
    ],
    "wof:name":"Boston Pizza",
    "wof:placetype":"venue"
},
  "geometry": {"coordinates":[-135.06092834500001,60.729724884],"type":"Point"}
}