{
  "type": "Feature",
  "properties": {
    "iso:country":"CA",
    "sg:address":"956 Paramount Dr",
    "sg:city":"Stoney Creek",
    "sg:classifiers":[
        {
            "category":"Organizations",
            "subcategory":"Religious Organization",
            "type":"Services"
        }
    ],
    "sg:phone":"+1 905 573 3275",
    "sg:postcode":"L8J 2M9",
    "sg:province":"ON",
    "sg:tags":[
        "church"
    ],
    "wof:name":"Heritage Green Baptist Church",
    "wof:placetype":"venue"
},
  "geometry": {"coordinates":[-79.7995376587,43.193195343],"type":"Point"}
}