{
  "type": "Feature",
  "properties": {
    "addr:full":"43 Durham St Sudbury ON P3E 3M2",
    "addr:housenumber":"43",
    "addr:postcode":"p3e 3m2",
    "addr:street":"Durham St",
    "iso:country":"CA",
    "sg:address":"43 Durham St",
    "sg:city":"Sudbury",
    "sg:classifiers":[
        {
            "category":"Restaurant",
            "type":"Food & Drink"
        }
    ],
    "sg:phone":"+1 705 673 2218",
    "sg:postcode":"P3E 3M2",
    "sg:province":"ON",
    "wof:name":"Subway Sandwiches & Salads",
    "wof:placetype":"venue"
},
  "geometry": {"coordinates":[-80.9952087402,46.4929542542],"type":"Point"}
}