{
  "type": "Feature",
  "properties": {
    "iso:country":"CA",
    "sg:city":"Stittsville",
    "sg:classifiers":[
        {
            "category":"Restaurant",
            "type":"Food & Drink"
        }
    ],
    "sg:phone":"+1 613 831 4440",
    "sg:postcode":"K2S 1S9",
    "sg:province":"ON",
    "wof:name":"Mc Donald's",
    "wof:placetype":"venue"
},
  "geometry": {"coordinates":[-75.9304656982,45.2688598633],"type":"Point"}
}