{
  "type": "Feature",
  "properties": {
    "addr:full":"922 Ryan St Moncton NB E1G 2V9",
    "addr:housenumber":"922",
    "addr:postcode":"e1g 2v9",
    "addr:street":"Ryan St",
    "iso:country":"CA",
    "sg:address":"922 Ryan St",
    "sg:city":"Moncton",
    "sg:classifiers":[
        {
            "category":"Manufacturing",
            "subcategory":"Glass & Minerals",
            "type":"Manufacturing & Wholesale Goods"
        }
    ],
    "sg:phone":"+1 506 384 9741",
    "sg:postcode":"E1G 2V9",
    "sg:province":"NB",
    "sg:tags":[
        "refractory"
    ],
    "wof:name":"Coastal Refractories Svc Ltd",
    "wof:placetype":"venue"
},
  "geometry": {"coordinates":[-64.857857,46.104923],"type":"Point"}
}