{
  "type": "Feature",
  "properties": {
    "addr:full":"1292 101st St North Battleford SK S9A 0Z8",
    "addr:housenumber":"1292",
    "addr:postcode":"s9a 0z8",
    "addr:street":"101St St",
    "iso:country":"CA",
    "sg:address":"1292 101st St",
    "sg:city":"North Battleford",
    "sg:classifiers":[
        {
            "category":"Restaurant",
            "type":"Food & Drink"
        }
    ],
    "sg:phone":"+1 306 445 7404",
    "sg:postcode":"S9A 0Z8",
    "sg:province":"SK",
    "wof:name":"Dragon Palace",
    "wof:placetype":"venue"
},
  "geometry": {"coordinates":[-108.297424316,52.7762680054],"type":"Point"}
}