{
  "type": "Feature",
  "properties": {
    "iso:country":"CA",
    "sg:address":"11 Church St E",
    "sg:city":"Elmira",
    "sg:classifiers":[
        {
            "category":"Shopping",
            "type":"Retail Goods"
        }
    ],
    "sg:phone":"+1 519 669 3030",
    "sg:postcode":"N3B 2K7",
    "sg:province":"ON",
    "sg:tags":[
        "orthopedic",
        "appliance"
    ],
    "wof:name":"Foot Foundation",
    "wof:placetype":"venue"
},
  "geometry": {"coordinates":[-80.5570983887,43.5998039246],"type":"Point"}
}