{
  "type": "Feature",
  "properties": {
    "addr:full":"2300 Silver King Rd Nelson BC V1L 1C9",
    "addr:housenumber":"2300",
    "addr:postcode":"bc v1l 1c9",
    "addr:street":"Silver King Rd",
    "iso:country":"CA",
    "sg:address":"2300 Silver King Rd",
    "sg:city":"Nelson",
    "sg:classifiers":[
        {
            "category":"Retail",
            "subcategory":"Auto Repair",
            "type":"Services"
        }
    ],
    "sg:phone":"+1 250 352 2133",
    "sg:postcode":"V1L 1C9",
    "sg:province":"BC",
    "sg:tags":[
        "repairing",
        "automobile"
    ],
    "wof:name":"Dave's Repair",
    "wof:placetype":"venue"
},
  "geometry": {"coordinates":[-117.29612,49.475288],"type":"Point"}
}