{
  "type": "Feature",
  "properties": {
    "addr:full":"89 Evans St Duncan BC V9L 1P5",
    "addr:housenumber":"89",
    "addr:postcode":"v9l 1p5",
    "addr:street":"Evans St",
    "iso:country":"CA",
    "sg:address":"89 Evans St",
    "sg:city":"Duncan",
    "sg:classifiers":[
        {
            "category":"Banks & Credit Unions",
            "subcategory":"Investment Brokerage",
            "type":"Services"
        }
    ],
    "sg:phone":"+1 250 715 3773",
    "sg:postcode":"V9L 1P5",
    "sg:province":"BC",
    "sg:tags":[
        "consultant",
        "planning",
        "financial"
    ],
    "wof:name":"Credential Securities",
    "wof:placetype":"venue"
},
  "geometry": {"coordinates":[-123.708473,48.779976],"type":"Point"}
}