{
  "type": "Feature",
  "properties": {
    "addr:full":"73 Superior St Devon AB T9G 1K9",
    "addr:housenumber":"73",
    "addr:postcode":"t9g 1k9",
    "addr:street":"Superior St",
    "iso:country":"CA",
    "sg:address":"73 Superior St",
    "sg:city":"Devon",
    "sg:classifiers":[
        {
            "category":"Food & Beverages",
            "subcategory":"Groceries & Convenience Stores",
            "type":"Retail Goods"
        }
    ],
    "sg:phone":"+1 780 987 3388",
    "sg:postcode":"T9G 1K9",
    "sg:province":"AB",
    "wof:name":"Mac's Convenience Stores Ltd",
    "wof:placetype":"venue"
},
  "geometry": {"coordinates":[-113.732322693,53.3611679077],"type":"Point"}
}