{
  "type": "Feature",
  "properties": {
    "addr:full":"2555 Range Rd Prince George BC V2N 4G8",
    "addr:housenumber":"2555",
    "addr:postcode":"v2n 4g8",
    "addr:street":"Range Rd",
    "iso:country":"CA",
    "sg:address":"2555 Range Rd",
    "sg:city":"Prince George",
    "sg:classifiers":[
        {
            "category":"Shopping",
            "subcategory":"Department Store",
            "type":"Retail Goods"
        }
    ],
    "sg:phone":"+1 250 561 1750",
    "sg:postcode":"V2N 4G8",
    "sg:province":"BC",
    "sg:tags":[
        "grocer"
    ],
    "wof:name":"Costco Wholesale",
    "wof:placetype":"venue"
},
  "geometry": {"coordinates":[-122.77153015099999,53.8843307495],"type":"Point"}
}