{
  "type": "Feature",
  "properties": {
    "addr:full":"Ottawa ON K2P 1V3",
    "addr:postcode":"k2p 1v3",
    "iso:country":"CA",
    "sg:city":"Ottawa",
    "sg:classifiers":[
        {
            "category":"Health Services",
            "subcategory":"Doctor",
            "type":"Services"
        }
    ],
    "sg:phone":"+1 613 237 7377",
    "sg:postcode":"K2P 1V3",
    "sg:province":"ON",
    "sg:tags":[
        "physician",
        "surgeon"
    ],
    "wof:name":"Daryawish, M MD",
    "wof:placetype":"venue"
},
  "geometry": {"coordinates":[-75.6918792725,45.4214782715],"type":"Point"}
}