{
  "type": "Feature",
  "properties": {
    "addr:full":"2260 Ch Sainte-Foy Sainte-Foy QC G1V 1S5",
    "addr:postcode":"2260;g1v 1s5",
    "addr:street":"Ch Sainte-Foy",
    "iso:country":"CA",
    "sg:address":"2260 Ch Sainte-Foy",
    "sg:city":"Sainte-Foy",
    "sg:classifiers":[
        {
            "category":"Restaurant",
            "type":"Food & Drink"
        }
    ],
    "sg:phone":"+1 418 653 6556",
    "sg:postcode":"G1V 1S5",
    "sg:province":"QC",
    "wof:name":"Restaurant Pacini",
    "wof:placetype":"venue"
},
  "geometry": {"coordinates":[-71.291763,46.769211],"type":"Point"}
}