{
  "type": "Feature",
  "properties": {
    "iso:country":"CA",
    "sg:address":"599 Brealey Dr",
    "sg:city":"Peterborough",
    "sg:classifiers":[
        {
            "category":"Education",
            "subcategory":"College",
            "type":"Public Place"
        }
    ],
    "sg:phone":"+1 705 749 5530",
    "sg:postcode":"K9J 7B1",
    "sg:province":"ON",
    "sg:tags":[
        "academic",
        "school"
    ],
    "wof:name":"Sir Sandford Fleming College",
    "wof:placetype":"venue"
},
  "geometry": {"coordinates":[-78.36804962159999,44.2668495178],"type":"Point"}
}