{
  "type": "Feature",
  "properties": {
    "iso:country":"CA",
    "sg:address":"320 Festubert St",
    "sg:city":"Duncan",
    "sg:classifiers":[
        {
            "category":"Retail",
            "subcategory":"Laundry & Dry Cleaning",
            "type":"Services"
        }
    ],
    "sg:phone":"+1 250 748 9613",
    "sg:postcode":"V9L 3S9",
    "sg:province":"BC",
    "sg:tags":[
        "cleaners"
    ],
    "wof:name":"Royal Cleaning Ctr",
    "wof:placetype":"venue"
},
  "geometry": {"coordinates":[-123.701843,48.777317],"type":"Point"}
}