{
  "type": "Feature",
  "properties": {
    "addr:full":"34 Av Carleton Baie-Comeau QC G4Z 1L7",
    "addr:postcode":"g4z 1l7",
    "addr:street":"34 Av Carleton",
    "iso:country":"CA",
    "sg:address":"34 Av Carleton",
    "sg:city":"Baie-Comeau",
    "sg:classifiers":[
        {
            "category":"Organizations",
            "subcategory":"Religious Organization",
            "type":"Services"
        }
    ],
    "sg:phone":"+1 418 296 2833",
    "sg:postcode":"G4Z 1L7",
    "sg:province":"QC",
    "sg:tags":[
        "church"
    ],
    "wof:name":"Church of St-Andrew St-George",
    "wof:placetype":"venue"
},
  "geometry": {"coordinates":[-68.14582799999999,49.218563],"type":"Point"}
}