{
  "type": "Feature",
  "properties": {
    "addr:full":"816 Muskoka Rd 3 N Huntsville ON P1H 1E2",
    "addr:housenumber":"816",
    "addr:postcode":"p1h 1e2",
    "addr:street":"Muskoka Rd 3 N",
    "iso:country":"CA",
    "sg:address":"816 Muskoka Rd 3 N",
    "sg:city":"Huntsville",
    "sg:classifiers":[
        {
            "category":"Professional",
            "subcategory":"Computer Services",
            "type":"Services"
        }
    ],
    "sg:phone":"+1 705 789 2128",
    "sg:postcode":"P1H 1E2",
    "sg:province":"ON",
    "sg:tags":[
        "equipment",
        "telephone",
        "supply"
    ],
    "wof:name":"Extel Communications",
    "wof:placetype":"venue"
},
  "geometry": {"coordinates":[-79.2903213501,45.2729225159],"type":"Point"}
}