{
  "type": "Feature",
  "properties": {
    "addr:full":"125 Rue Dalhousie Quebec QC G1K 4C5",
    "addr:housenumber":"125",
    "addr:postcode":"g1k 4c5",
    "addr:street":"Rue Dalhousie",
    "iso:country":"CA",
    "sg:address":"125 Rue Dalhousie",
    "sg:city":"Quebec",
    "sg:classifiers":[
        {
            "category":"Parking",
            "type":"Transportation"
        }
    ],
    "sg:phone":"+1 418 692 2050",
    "sg:postcode":"G1K 4C5",
    "sg:province":"QC",
    "sg:tags":[
        "garage"
    ],
    "wof:name":"Stationnement Promenade",
    "wof:placetype":"venue"
},
  "geometry": {"coordinates":[-71.20264434809999,46.8171234131],"type":"Point"}
}