{
  "type": "Feature",
  "properties": {
    "iso:country":"CA",
    "sg:address":"7 Metcalfe St",
    "sg:city":"Trenton",
    "sg:classifiers":[
        {
            "category":"Wholesale",
            "subcategory":"Medical Equipment & Supplies",
            "type":"Manufacturing & Wholesale Goods"
        }
    ],
    "sg:phone":"+1 613 394 1846",
    "sg:postcode":"K8V 6H3",
    "sg:province":"ON",
    "sg:tags":[
        "home",
        "hospital",
        "health"
    ],
    "wof:name":"Kelly's Home Care Ctr",
    "wof:placetype":"venue"
},
  "geometry": {"coordinates":[-77.581459,44.104702],"type":"Point"}
}