{
  "type": "Feature",
  "properties": {
    "iso:country":"CA",
    "sg:address":"42 Rue Noel",
    "sg:city":"Saint-Benoit-Labre",
    "sg:classifiers":[
        {
            "category":"Manufacturing",
            "subcategory":"Apparel",
            "type":"Manufacturing & Wholesale Goods"
        }
    ],
    "sg:phone":"+1 418 228 0214",
    "sg:postcode":"G0M 1P0",
    "sg:province":"QC",
    "sg:tags":[
        "clothing"
    ],
    "wof:name":"Industries DE Couture",
    "wof:placetype":"venue"
},
  "geometry": {"coordinates":[-70.792809,46.071175],"type":"Point"}
}