{
  "type": "Feature",
  "properties": {
    "addr:full":"42 Rue Noel Saint-Benoit-Labre QC G0M 1P0",
    "addr:housenumber":"42",
    "addr:postcode":"g0m 1p0",
    "addr:street":"Rue Noel Saint-Benoit-Labre",
    "iso:country":"CA",
    "sg:address":"42 Rue Noel",
    "sg:city":"Saint-Benoit-Labre",
    "sg:classifiers":[
        {
            "category":"Manufacturing",
            "subcategory":"Apparel",
            "type":"Manufacturing & Wholesale Goods"
        }
    ],
    "sg:phone":"+1 418 228 0214",
    "sg:postcode":"G0M 1P0",
    "sg:province":"QC",
    "sg:tags":[
        "clothing"
    ],
    "wof:name":"Industries DE Couture",
    "wof:placetype":"venue"
},
  "geometry": {"coordinates":[-70.79280900000001,46.071175],"type":"Point"}
}