{
  "type": "Feature",
  "properties": {
    "iso:country":"CA",
    "sg:address":"1100 Dundas St E",
    "sg:city":"Whitby",
    "sg:classifiers":[
        {
            "category":"Restaurant",
            "type":"Food & Drink"
        }
    ],
    "sg:phone":"+1 905 666 3939",
    "sg:postcode":"L1N 2K2",
    "sg:province":"ON",
    "wof:name":"East Side Mario's",
    "wof:placetype":"venue"
},
  "geometry": {"coordinates":[-78.9250030518,43.8839073181],"type":"Point"}
}