{
  "type": "Feature",
  "properties": {
    "iso:country":"CA",
    "sg:address":"702 Rue Bergeron",
    "sg:city":"Saint-Honore-DE-Chicoutimi",
    "sg:classifiers":[
        {
            "category":"Personal",
            "subcategory":"Beauty Salon",
            "type":"Services"
        }
    ],
    "sg:phone":"+1 418 673 3535",
    "sg:postcode":"G0V 1L0",
    "sg:province":"QC",
    "wof:name":"Salon D'Esthetique & D'Electrl",
    "wof:placetype":"venue"
},
  "geometry": {"coordinates":[-71.0613937378,48.428943634],"type":"Point"}
}