{
  "type": "Feature",
  "properties": {
    "iso:country":"CA",
    "sg:address":"805 Rue Scott O",
    "sg:city":"Alma",
    "sg:classifiers":[
        {
            "category":"Wholesale",
            "subcategory":"Chemicals & Plastics",
            "type":"Manufacturing & Wholesale Goods"
        }
    ],
    "sg:phone":"+1 418 662 3487",
    "sg:postcode":"G8B 1R9",
    "sg:province":"QC",
    "sg:tags":[
        "explosive"
    ],
    "wof:name":"Lac St-Jean Explosifs Enr",
    "wof:placetype":"venue"
},
  "geometry": {"coordinates":[-71.65692138670001,48.5493736267],"type":"Point"}
}