{
  "type": "Feature",
  "properties": {
    "addr:full":"New Westminster BC V3M 6B9",
    "addr:postcode":"v3m 6b9",
    "iso:country":"CA",
    "sg:city":"New Westminster",
    "sg:classifiers":[
        {
            "category":"Shopping",
            "subcategory":"Gifts & Souvenirs",
            "type":"Retail Goods"
        }
    ],
    "sg:phone":"+1 604 522 8004",
    "sg:postcode":"V3M 6B9",
    "sg:province":"BC",
    "sg:tags":[
        "shop"
    ],
    "wof:name":"Adrianas Place",
    "wof:placetype":"venue"
},
  "geometry": {"coordinates":[-122.911827,49.200249],"type":"Point"}
}