{
  "type": "Feature",
  "properties": {
    "addr:full":"Toronto ON M5S 3A7",
    "addr:postcode":"m5s 3a7",
    "iso:country":"CA",
    "sg:city":"Toronto",
    "sg:classifiers":[
        {
            "category":"Professional",
            "subcategory":"Accounting & Tax Preparation",
            "type":"Services"
        }
    ],
    "sg:phone":"+1 416 927 7949",
    "sg:postcode":"M5S 3A7",
    "sg:province":"ON",
    "sg:tags":[
        "accountant"
    ],
    "wof:name":"Lee, Young C",
    "wof:placetype":"venue"
},
  "geometry": {"coordinates":[-79.404312,43.666676],"type":"Point"}
}