{
  "type": "Feature",
  "properties": {
    "iso:country":"CA",
    "sg:address":"429 Seaview Dr",
    "sg:city":"North Sydney",
    "sg:classifiers":[
        {
            "category":"Home & Garden",
            "subcategory":"Garden Supply",
            "type":"Retail Goods"
        }
    ],
    "sg:phone":"+1 902 794 4146",
    "sg:postcode":"B2A 3N7",
    "sg:province":"NS",
    "sg:tags":[
        "nurseryman",
        "center"
    ],
    "wof:name":"Earl's Greenhouses",
    "wof:placetype":"venue"
},
  "geometry": {"coordinates":[-60.251434,46.207115],"type":"Point"}
}