{
  "type": "Feature",
  "properties": {
    "addr:full":"4182 Sunset Valley Crt Mississauga ON L4W 3L5",
    "addr:housenumber":"4182",
    "addr:postcode":"l4w 3l5",
    "addr:street":"Sunset Valley Crt",
    "iso:country":"CA",
    "sg:address":"4182 Sunset Valley Crt",
    "sg:city":"Mississauga",
    "sg:classifiers":[
        {
            "category":"Home & Garden",
            "subcategory":"Building Materials",
            "type":"Retail Goods"
        }
    ],
    "sg:phone":"+1 905 629 9898",
    "sg:postcode":"L4W 3L5",
    "sg:province":"ON",
    "sg:tags":[
        "coating"
    ],
    "wof:name":"Par Zee & Assoc Inc",
    "wof:placetype":"venue"
},
  "geometry": {"coordinates":[-79.6228942871,43.6120185852],"type":"Point"}
}