{
  "type": "Feature",
  "properties": {
    "iso:country":"CA",
    "sg:address":"85 Ellis Dr",
    "sg:city":"Barrie",
    "sg:classifiers":[
        {
            "category":"Freight",
            "type":"Transportation"
        }
    ],
    "sg:phone":"+1 705 739 1551",
    "sg:postcode":"L4N 8Z3",
    "sg:province":"ON",
    "sg:tags":[
        "trucking"
    ],
    "wof:name":"Larway Transportation",
    "wof:placetype":"venue"
},
  "geometry": {"coordinates":[-79.670807,44.348476],"type":"Point"}
}