{
  "type": "Feature",
  "properties": {
    "addr:full":"6120 Yonge St #A North York ON M2M 3W7",
    "addr:housenumber":"6120",
    "addr:postcode":"m2m 3w7",
    "addr:street":"Yonge St # A",
    "iso:country":"CA",
    "sg:address":"6120 Yonge St #A",
    "sg:city":"North York",
    "sg:classifiers":[
        {
            "category":"Banks & Credit Unions",
            "subcategory":"Bank",
            "type":"Services"
        }
    ],
    "sg:phone":"+1 416 221 1179",
    "sg:postcode":"M2M 3W7",
    "sg:province":"ON",
    "sg:tags":[
        "loan"
    ],
    "wof:name":"Autocash",
    "wof:placetype":"venue"
},
  "geometry": {"coordinates":[-79.41864776609999,43.7917251587],"type":"Point"}
}