{
  "type": "Feature",
  "properties": {
    "iso:country":"CA",
    "sg:address":"180 Provost St",
    "sg:city":"New Glasgow",
    "sg:classifiers":[
        {
            "category":"Shopping",
            "subcategory":"Shoes",
            "type":"Retail Goods"
        }
    ],
    "sg:phone":"+1 902 928 2229",
    "sg:postcode":"B2H 2R1",
    "sg:province":"NS",
    "wof:name":"Soley Shoes",
    "wof:placetype":"venue"
},
  "geometry": {"coordinates":[-62.6450958252,45.5867538452],"type":"Point"}
}