{
  "type": "Feature",
  "properties": {
    "addr:full":"4860 Boul DE Maisonneuve O Westmount QC H3Z 3G2",
    "addr:housenumber":"4860",
    "addr:postcode":"h3z 3g2",
    "addr:street":"Boul De Maisonneuve O",
    "iso:country":"CA",
    "sg:address":"4860 Boul DE Maisonneuve O",
    "sg:city":"Westmount",
    "sg:classifiers":[
        {
            "category":"Health Services",
            "subcategory":"Nursing And Care Facility",
            "type":"Services"
        }
    ],
    "sg:phone":"+1 514 369 3000",
    "sg:postcode":"H3Z 3G2",
    "sg:province":"QC",
    "sg:tags":[
        "home",
        "salon",
        "convalescent",
        "beauty"
    ],
    "wof:name":"Coiffure Chateau Westmount",
    "wof:placetype":"venue"
},
  "geometry": {"coordinates":[-73.6002502441,45.4773826599],"type":"Point"}
}