{
  "type": "Feature",
  "properties": {
    "addr:full":"46 Boulder Blvd Stony Plain AB T7Z 1V7",
    "addr:housenumber":"46",
    "addr:postcode":"t7z 1v7",
    "addr:street":"Boulder Blvd",
    "iso:country":"CA",
    "sg:address":"46 Boulder Blvd",
    "sg:city":"Stony Plain",
    "sg:classifiers":[
        {
            "category":"Home & Garden",
            "subcategory":"Household Appliances",
            "type":"Retail Goods"
        }
    ],
    "sg:phone":"+1 780 963 3119",
    "sg:postcode":"T7Z 1V7",
    "sg:province":"AB",
    "wof:name":"Stony Tv & Appliance Ctr Ltd",
    "wof:placetype":"venue"
},
  "geometry": {"coordinates":[-113.98886108400001,53.5421524048],"type":"Point"}
}