{
  "type": "Feature",
  "properties": {
    "iso:country":"CA",
    "sg:address":"2171 Dundas St E",
    "sg:city":"Mississauga",
    "sg:classifiers":[
        {
            "category":"Travel",
            "subcategory":"Hotels & Motels",
            "type":"Entertainment"
        }
    ],
    "sg:phone":"+1 905 624 6424",
    "sg:postcode":"L4X 1M3",
    "sg:province":"ON",
    "wof:name":"Super 5 Inn",
    "wof:placetype":"venue"
},
  "geometry": {"coordinates":[-79.56623840330001,43.6260299683],"type":"Point"}
}