{
  "type": "Feature",
  "properties": {
    "addr:full":"107 6A St NE Calgary AB T2E 0B7",
    "addr:housenumber":"107",
    "addr:postcode":"t2e 0b7",
    "addr:street":"6A St Ne",
    "iso:country":"CA",
    "sg:address":"107 6A St NE",
    "sg:city":"Calgary",
    "sg:classifiers":[
        {
            "category":"Education",
            "subcategory":"School",
            "type":"Public Place"
        }
    ],
    "sg:phone":"+1 403 777 7350",
    "sg:postcode":"T2E 0B7",
    "sg:province":"AB",
    "wof:name":"Langevin Elementary/Jr High",
    "wof:placetype":"venue"
},
  "geometry": {"coordinates":[-114.047134399,51.0524787903],"type":"Point"}
}