{
  "type": "Feature",
  "properties": {
    "iso:country":"CA",
    "sg:city":"Pickering",
    "sg:classifiers":[
        {
            "category":"Wholesale",
            "subcategory":"Hardware",
            "type":"Manufacturing & Wholesale Goods"
        }
    ],
    "sg:phone":"+1 905 839 4646",
    "sg:postcode":"L1W 3G7",
    "sg:province":"ON",
    "sg:tags":[
        "fastener"
    ],
    "wof:name":"Fastenal CO",
    "wof:placetype":"venue"
},
  "geometry": {"coordinates":[-79.06572,43.833344],"type":"Point"}
}