{
  "type": "Feature",
  "properties": {
    "addr:full":"3447 Rue Notre-Dame O Montreal QC H4C 1P3",
    "addr:housenumber":"3447",
    "addr:postcode":"h4c 1p3",
    "addr:street":"Rue Notre-Dame O",
    "iso:country":"CA",
    "sg:address":"3447 Rue Notre-Dame O",
    "sg:city":"Montreal",
    "sg:classifiers":[
        {
            "category":"Shopping",
            "subcategory":"Bicycles & Sporting Goods",
            "type":"Retail Goods"
        }
    ],
    "sg:phone":"+1 514 931 8931",
    "sg:postcode":"H4C 1P3",
    "sg:province":"QC",
    "sg:tags":[
        "equipment",
        "exercise"
    ],
    "wof:name":"Strata-Gym",
    "wof:placetype":"venue"
},
  "geometry": {"coordinates":[-73.5375366211,45.5414123535],"type":"Point"}
}