{
  "type": "Feature",
  "properties": {
    "addr:full":"Trail BC V1R 4N7",
    "addr:postcode":"bc v1r 4n7",
    "addr:street":"Trail",
    "iso:country":"CA",
    "sg:city":"Trail",
    "sg:classifiers":[
        {
            "category":"Recreation",
            "type":"Entertainment"
        }
    ],
    "sg:phone":"+1 250 368 8116",
    "sg:postcode":"V1R 4N7",
    "sg:province":"BC",
    "sg:tags":[
        "ticket"
    ],
    "wof:name":"Waneta Ticket Ctr",
    "wof:placetype":"venue"
},
  "geometry": {"coordinates":[-117.71221199999999,49.096451],"type":"Point"}
}