{
  "type": "Feature",
  "properties": {
    "iso:country":"CA",
    "sg:address":"279 Kelsey Blvd",
    "sg:city":"Churchill",
    "sg:classifiers":[
        {
            "category":"Retail",
            "subcategory":"Auto Repair",
            "type":"Services"
        }
    ],
    "sg:phone":"+1 204 675 2518",
    "sg:postcode":"R0B 0E0",
    "sg:province":"MB",
    "sg:tags":[
        "body",
        "automobile",
        "painting"
    ],
    "wof:name":"J & D Rentals",
    "wof:placetype":"venue"
},
  "geometry": {"coordinates":[-94.1679534912,58.7691192627],"type":"Point"}
}