{
  "type": "Feature",
  "properties": {
    "addr:full":"Sherwood Park AB T8A 4N5",
    "addr:postcode":"t8a 4n5",
    "iso:country":"CA",
    "sg:city":"Sherwood Park",
    "sg:classifiers":[
        {
            "category":"Autos & Motor Vehicles",
            "subcategory":"Fuel & Gas Station",
            "type":"Retail Goods"
        }
    ],
    "sg:phone":"+1 780 467 8028",
    "sg:postcode":"T8A 4N5",
    "sg:province":"AB",
    "sg:tags":[
        "oil"
    ],
    "wof:name":"Fas Gas",
    "wof:placetype":"venue"
},
  "geometry": {"coordinates":[-113.326714,53.513718],"type":"Point"}
}