{
  "type": "Feature",
  "properties": {
    "addr:full":"8650 Av Dubuisson Montreal QC H1L 2W3",
    "addr:housenumber":"8650",
    "addr:postcode":"h1l 2w3",
    "addr:street":"Av Dubuisson",
    "iso:country":"CA",
    "sg:address":"8650 Av Dubuisson",
    "sg:city":"Montreal",
    "sg:classifiers":[
        {
            "category":"Building & Trades",
            "subcategory":"Electrical",
            "type":"Services"
        }
    ],
    "sg:phone":"+1 514 351 7069",
    "sg:postcode":"H1L 2W3",
    "sg:province":"QC",
    "sg:tags":[
        "electric",
        "contractor"
    ],
    "wof:name":"Andre Desilets Enr",
    "wof:placetype":"venue"
},
  "geometry": {"coordinates":[-73.51763200000001,45.599869],"type":"Point"}
}