{
  "type": "Feature",
  "properties": {
    "addr:full":"Nepean ON K2G 1W2",
    "addr:postcode":"k2g 1w2",
    "iso:country":"CA",
    "sg:city":"Nepean",
    "sg:classifiers":[
        {
            "category":"Health Services",
            "subcategory":"Doctor",
            "type":"Services"
        }
    ],
    "sg:phone":"+1 613 723 3000",
    "sg:postcode":"K2G 1W2",
    "sg:province":"ON",
    "sg:tags":[
        "dentist"
    ],
    "wof:name":"Correia, M A DDS",
    "wof:placetype":"venue"
},
  "geometry": {"coordinates":[-75.749611,45.330318],"type":"Point"}
}