{
  "type": "Feature",
  "properties": {
    "iso:country":"CA",
    "sg:city":"Waterloo",
    "sg:classifiers":[
        {
            "category":"Health Services",
            "subcategory":"Health Practitioner",
            "type":"Services"
        }
    ],
    "sg:phone":"+1 519 725 4155",
    "sg:postcode":"N2J 2Y9",
    "sg:province":"ON",
    "sg:tags":[
        "psychologist"
    ],
    "wof:name":"Swanson, Lynn B",
    "wof:placetype":"venue"
},
  "geometry": {"coordinates":[-80.524918,43.476753],"type":"Point"}
}