{
  "type": "Feature",
  "properties": {
    "iso:country":"CA",
    "sg:city":"Edmonton",
    "sg:classifiers":[
        {
            "category":"Building & Trades",
            "subcategory":"Plumbing",
            "type":"Services"
        }
    ],
    "sg:phone":"+1 780 481 8873",
    "sg:postcode":"T5S 1V4",
    "sg:province":"AB",
    "sg:tags":[
        "contractor"
    ],
    "wof:name":"Star Mechanical Edm Ltd",
    "wof:placetype":"venue"
},
  "geometry": {"coordinates":[-113.62979126,53.550151825],"type":"Point"}
}