{
  "type": "Feature",
  "properties": {
    "addr:full":"Saint-Laurent QC H4R 2B7",
    "addr:postcode":"h4r 2b7",
    "iso:country":"CA",
    "sg:city":"Saint-Laurent",
    "sg:classifiers":[
        {
            "category":"Manufacturing",
            "subcategory":"Food",
            "type":"Manufacturing & Wholesale Goods"
        }
    ],
    "sg:phone":"+1 514 747 3571",
    "sg:postcode":"H4R 2B7",
    "sg:province":"QC",
    "sg:tags":[
        "chewing",
        "gum"
    ],
    "wof:name":"Wrigley Canada Inc",
    "wof:placetype":"venue"
},
  "geometry": {"coordinates":[-73.7041397095,45.496887207],"type":"Point"}
}