{
  "type": "Feature",
  "properties": {
    "addr:full":"Coleman AB T0K 0M0",
    "addr:postcode":"t0k 0m0",
    "iso:country":"CA",
    "sg:city":"Coleman",
    "sg:classifiers":[
        {
            "category":"Building & Trades",
            "subcategory":"Construction",
            "type":"Services"
        }
    ],
    "sg:phone":"+1 403 563 3259",
    "sg:postcode":"T0K 0M0",
    "sg:province":"AB",
    "sg:tags":[
        "general",
        "contractor"
    ],
    "wof:name":"Charles O Cox Construction",
    "wof:placetype":"venue"
},
  "geometry": {"coordinates":[-114.495239,49.631706],"type":"Point"}
}