{
  "type": "Feature",
  "properties": {
    "addr:full":"East Angus QC J0B 1R0",
    "addr:postcode":"j0b 1r0",
    "iso:country":"CA",
    "sg:city":"East Angus",
    "sg:classifiers":[
        {
            "category":"Social Services",
            "subcategory":"Job Training",
            "type":"Services"
        }
    ],
    "sg:phone":"+1 819 832 1750",
    "sg:postcode":"J0B 1R0",
    "sg:province":"QC",
    "sg:tags":[
        "employment"
    ],
    "wof:name":"Intro-Travail",
    "wof:placetype":"venue"
},
  "geometry": {"coordinates":[-71.66021000000001,45.487072],"type":"Point"}
}