{
  "type": "Feature",
  "properties": {
    "addr:full":"PO Box 22 Grassland AB T0A 1V0",
    "addr:housenumber":"po box 22",
    "addr:postcode":"t0a 1v0",
    "addr:street":"Grassland Ab",
    "iso:country":"CA",
    "sg:address":"PO Box 22",
    "sg:city":"Grassland",
    "sg:classifiers":[
        {
            "category":"Retail",
            "subcategory":"Auto Repair",
            "type":"Services"
        }
    ],
    "sg:phone":"+1 780 525 2386",
    "sg:postcode":"T0A 1V0",
    "sg:province":"AB",
    "sg:tags":[
        "truck"
    ],
    "wof:name":"Sworin Enterprises",
    "wof:placetype":"venue"
},
  "geometry": {"coordinates":[-112.71305099999999,54.820309],"type":"Point"}
}