{
  "type": "Feature",
  "properties": {
    "addr:full":"936 East Main St Welland ON L3B 3Y9",
    "addr:housenumber":"936",
    "addr:postcode":"l3b 3y9",
    "addr:street":"East Main St",
    "iso:country":"CA",
    "sg:address":"936 East Main St",
    "sg:city":"Welland",
    "sg:classifiers":[
        {
            "category":"Personal",
            "subcategory":"Beauty Salon",
            "type":"Services"
        }
    ],
    "sg:phone":"+1 905 734 6775",
    "sg:postcode":"L3B 3Y9",
    "sg:province":"ON",
    "wof:name":"Golden Razor",
    "wof:placetype":"venue"
},
  "geometry": {"coordinates":[-79.228561,42.99358],"type":"Point"}
}