{
  "type": "Feature",
  "properties": {
    "addr:full":"290 North Front St Belleville ON K8P 3C4",
    "addr:housenumber":"290",
    "addr:postcode":"k8p 3c4",
    "addr:street":"North Front St",
    "iso:country":"CA",
    "sg:address":"290 North Front St",
    "sg:city":"Belleville",
    "sg:classifiers":[
        {
            "category":"Bars & Pubs",
            "type":"Food & Drink"
        }
    ],
    "sg:phone":"+1 613 962 2888",
    "sg:postcode":"K8P 3C4",
    "sg:province":"ON",
    "sg:tags":[
        "club",
        "night"
    ],
    "wof:name":"Atlantis Night Club",
    "wof:placetype":"venue"
},
  "geometry": {"coordinates":[-77.394279,44.183647],"type":"Point"}
}