{
  "type": "Feature",
  "properties": {
    "iso:country":"CA",
    "sg:address":"4255 Weston Rd",
    "sg:city":"North York",
    "sg:classifiers":[
        {
            "category":"Retail",
            "subcategory":"Auto Rental",
            "type":"Services"
        }
    ],
    "sg:phone":"+1 416 746 2244",
    "sg:postcode":"M9L 1W8",
    "sg:province":"ON",
    "sg:tags":[
        "renting",
        "truck",
        "leasing"
    ],
    "wof:name":"Ryder Canada Ltd",
    "wof:placetype":"venue"
},
  "geometry": {"coordinates":[-79.5458145142,43.7680244446],"type":"Point"}
}