{
  "type": "Feature",
  "properties": {
    "addr:full":"715 Clements Dr Fredericton NB E3A 7J2",
    "addr:housenumber":"715",
    "addr:postcode":"e3a 7j2",
    "addr:street":"Clements Dr",
    "iso:country":"CA",
    "sg:address":"715 Clements Dr",
    "sg:city":"Fredericton",
    "sg:classifiers":[
        {
            "category":"Building & Trades",
            "subcategory":"Plumbing",
            "type":"Services"
        }
    ],
    "sg:phone":"+1 506 444 9003",
    "sg:postcode":"E3A 7J2",
    "sg:province":"NB",
    "sg:tags":[
        "contractor"
    ],
    "wof:name":"Spencers Plumbing & Heat Ltd",
    "wof:placetype":"venue"
},
  "geometry": {"coordinates":[-66.7185516357,45.9778137207],"type":"Point"}
}