{
  "type": "Feature",
  "properties": {
    "iso:country":"CA",
    "sg:address":"1221 Hudson Rd",
    "sg:city":"Kelowna",
    "sg:classifiers":[
        {
            "category":"Education",
            "subcategory":"School",
            "type":"Public Place"
        }
    ],
    "sg:phone":"+1 250 769 4666",
    "sg:postcode":"V1Z 1J5",
    "sg:province":"BC",
    "wof:name":"Hudson Road Elementary",
    "wof:placetype":"venue"
},
  "geometry": {"coordinates":[-119.56436920199999,49.8625183105],"type":"Point"}
}