{
  "type": "Feature",
  "properties": {
    "addr:full":"Victoria BC V8R 1H8",
    "addr:postcode":"v8r 1h8",
    "iso:country":"CA",
    "sg:city":"Victoria",
    "sg:classifiers":[
        {
            "category":"Restaurant",
            "type":"Food & Drink"
        }
    ],
    "sg:phone":"+1 250 592 1178",
    "sg:postcode":"V8R 1H8",
    "sg:province":"BC",
    "wof:name":"Dragon Gate Restaurant",
    "wof:placetype":"venue"
},
  "geometry": {"coordinates":[-123.336372376,48.4265480042],"type":"Point"}
}