{
  "type": "Feature",
  "properties": {
    "addr:full":"Box 17 Brome QC J0E 1K0",
    "addr:housenumber":"17",
    "addr:postcode":"j0e 1k0",
    "iso:country":"CA",
    "sg:address":"Box 17",
    "sg:city":"Brome",
    "sg:classifiers":[
        {
            "category":"Organizations",
            "subcategory":"Religious Organization",
            "type":"Services"
        }
    ],
    "sg:phone":"+1 450 243 6096",
    "sg:postcode":"J0E 1K0",
    "sg:province":"QC",
    "sg:tags":[
        "church"
    ],
    "wof:name":"St John Anglican Church",
    "wof:placetype":"venue"
},
  "geometry": {"coordinates":[-72.5720672607,45.194026947],"type":"Point"}
}