{
  "type": "Feature",
  "properties": {
    "iso:country":"CA",
    "sg:address":"1220 Ch Des Pionniers",
    "sg:city":"LA Tuque",
    "sg:classifiers":[
        {
            "category":"Government",
            "subcategory":"Office",
            "type":"Public Place"
        }
    ],
    "sg:phone":"+1 819 523 6928",
    "sg:postcode":"G9X 3N6",
    "sg:province":"QC",
    "sg:tags":[
        "landfill",
        "village"
    ],
    "wof:name":"Site Enfouissement Sanitaire",
    "wof:placetype":"venue"
},
  "geometry": {"coordinates":[-72.74146270750001,47.4639396667],"type":"Point"}
}