{
  "type": "Feature",
  "properties": {
    "addr:full":"111 Lake Village Rd Winnipeg MB R3T 4M7",
    "addr:housenumber":"111",
    "addr:postcode":"r3t 4m7",
    "addr:street":"Lake Village Rd",
    "iso:country":"CA",
    "sg:address":"111 Lake Village Rd",
    "sg:city":"Winnipeg",
    "sg:classifiers":[
        {
            "category":"Health Services",
            "subcategory":"Clinic",
            "type":"Services"
        }
    ],
    "sg:phone":"+1 204 275 2871",
    "sg:postcode":"R3T 4M7",
    "sg:province":"MB",
    "sg:tags":[
        "colonic",
        "irrigation"
    ],
    "wof:name":"Marg's Colon Therapy Clinic",
    "wof:placetype":"venue"
},
  "geometry": {"coordinates":[-97.158112,49.815861],"type":"Point"}
}