{
  "type": "Feature",
  "properties": {
    "iso:country":"CA",
    "sg:address":"5551 Richmond Rd SW # 100",
    "sg:city":"Calgary",
    "sg:classifiers":[
        {
            "category":"Restaurant",
            "type":"Food & Drink"
        }
    ],
    "sg:phone":"+1 403 246 1577",
    "sg:postcode":"T3H 3C8",
    "sg:province":"AB",
    "wof:name":"Mc Donald's",
    "wof:placetype":"venue"
},
  "geometry": {"coordinates":[-114.16739699999999,51.017616],"type":"Point"}
}