{
  "type": "Feature",
  "properties": {
    "addr:full":"1004 Bala Falls Rd Bala ON P0C 1A0",
    "addr:housenumber":"1004",
    "addr:postcode":"p0c 1a0",
    "addr:street":"Bala Falls Rd",
    "iso:country":"CA",
    "sg:address":"1004 Bala Falls Rd",
    "sg:city":"Bala",
    "sg:classifiers":[
        {
            "category":"Building & Trades",
            "subcategory":"Construction",
            "type":"Services"
        }
    ],
    "sg:phone":"+1 705 762 3317",
    "sg:postcode":"P0C 1A0",
    "sg:province":"ON",
    "sg:tags":[
        "woodworker"
    ],
    "wof:name":"Wooden Moon",
    "wof:placetype":"venue"
},
  "geometry": {"coordinates":[-79.61441000000001,45.010548],"type":"Point"}
}