{
  "type": "Feature",
  "properties": {
    "addr:full":"Montreal QC H3W 1H2",
    "addr:postcode":"h3w 1h2",
    "iso:country":"CA",
    "sg:city":"Montreal",
    "sg:classifiers":[
        {
            "category":"Manufacturing",
            "subcategory":"Printing",
            "type":"Manufacturing & Wholesale Goods"
        }
    ],
    "sg:phone":"+1 514 739 4884",
    "sg:postcode":"H3W 1H2",
    "sg:province":"QC",
    "sg:tags":[
        "publisher"
    ],
    "wof:name":"Allprime Properties Inc",
    "wof:placetype":"venue"
},
  "geometry": {"coordinates":[-73.63810700000001,45.495102],"type":"Point"}
}