{
  "type": "Feature",
  "properties": {
    "addr:full":"Brooks AB T1R 0R9",
    "addr:postcode":"t1r 0r9",
    "iso:country":"CA",
    "sg:city":"Brooks",
    "sg:classifiers":[
        {
            "category":"Restaurant",
            "type":"Food & Drink"
        }
    ],
    "sg:phone":"+1 403 362 7222",
    "sg:postcode":"T1R 0R9",
    "sg:province":"AB",
    "wof:name":"Athenai Dining Room",
    "wof:placetype":"venue"
},
  "geometry": {"coordinates":[-111.895386,50.564217],"type":"Point"}
}