{
  "type": "Feature",
  "properties": {
    "addr:full":"25 Kenmount Rd St. John's NL A1B 1W1",
    "addr:housenumber":"25",
    "addr:postcode":"a1b 1w1",
    "addr:street":"Kenmount Rd",
    "iso:country":"CA",
    "sg:address":"25 Kenmount Rd",
    "sg:city":"St. John's",
    "sg:classifiers":[
        {
            "category":"Recreation",
            "type":"Entertainment"
        }
    ],
    "sg:phone":"+1 709 738 4750",
    "sg:postcode":"A1B 1W1",
    "sg:province":"NL",
    "sg:tags":[
        "parlor",
        "billiard"
    ],
    "wof:name":"West Side Charlie's",
    "wof:placetype":"venue"
},
  "geometry": {"coordinates":[-52.750404,47.559586],"type":"Point"}
}