{
  "type": "Feature",
  "properties": {
    "addr:full":"8300 Woodbine Ave # 400 Markham ON L3R 9Y7",
    "addr:housenumber":"8300",
    "addr:postcode":"l3r 9y7",
    "addr:street":"Woodbine Ave # 400",
    "iso:country":"CA",
    "sg:address":"8300 Woodbine Ave # 400",
    "sg:city":"Markham",
    "sg:classifiers":[
        {
            "category":"Shopping",
            "subcategory":"Computers & Home Electronics",
            "type":"Retail Goods"
        }
    ],
    "sg:phone":"+1 905 940 9404",
    "sg:postcode":"L3R 9Y7",
    "sg:province":"ON",
    "sg:tags":[
        "software"
    ],
    "wof:name":"Mvs Solutions Inc",
    "wof:placetype":"venue"
},
  "geometry": {"coordinates":[-79.3569946289,43.8449935913],"type":"Point"}
}