{
  "type": "Feature",
  "properties": {
    "addr:full":"945 Av Belvedere Quebec QC G1S 3G2",
    "addr:postcode":"g1s 3g2",
    "addr:street":"945 Av",
    "iso:country":"CA",
    "sg:address":"945 Av Belvedere",
    "sg:city":"Quebec",
    "sg:classifiers":[
        {
            "category":"Education",
            "subcategory":"School",
            "type":"Public Place"
        }
    ],
    "sg:phone":"+1 418 683 1953",
    "sg:postcode":"G1S 3G2",
    "sg:province":"QC",
    "wof:name":"Quebec High School",
    "wof:placetype":"venue"
},
  "geometry": {"coordinates":[-71.239822,46.797703],"type":"Point"}
}