{
  "type": "Feature",
  "properties": {
    "addr:full":"258 Wallace Ave Toronto ON M6P 3M9",
    "addr:housenumber":"258",
    "addr:postcode":"m6p 3m9",
    "addr:street":"Wallace Ave",
    "iso:country":"CA",
    "sg:address":"258 Wallace Ave",
    "sg:city":"Toronto",
    "sg:classifiers":[
        {
            "category":"Professional",
            "subcategory":"Advertising",
            "type":"Services"
        }
    ],
    "sg:phone":"+1 416 531 7880",
    "sg:postcode":"M6P 3M9",
    "sg:province":"ON",
    "sg:tags":[
        "designer",
        "display",
        "producer"
    ],
    "wof:name":"Fresh Never Frozen Art",
    "wof:placetype":"venue"
},
  "geometry": {"coordinates":[-79.447182,43.661915],"type":"Point"}
}