{
  "type": "Feature",
  "properties": {
    "iso:country":"CA",
    "sg:city":"Winkler",
    "sg:classifiers":[
        {
            "category":"Real Estate",
            "subcategory":"Real Estate Operator",
            "type":"Services"
        }
    ],
    "sg:phone":"+1 204 325 0042",
    "sg:postcode":"R6W 4B2",
    "sg:province":"MB",
    "sg:tags":[
        "mobile",
        "home",
        "community"
    ],
    "wof:name":"Minnewasta Meadows",
    "wof:placetype":"venue"
},
  "geometry": {"coordinates":[-97.9231262207,49.1800804138],"type":"Point"}
}