{
  "type": "Feature",
  "properties": {
    "addr:full":"17038 90 Ave NW Edmonton AB T5T 1L6",
    "addr:housenumber":"17038",
    "addr:postcode":"t5t 1l6",
    "addr:street":"90 Ave Nw",
    "iso:country":"CA",
    "sg:address":"17038 90 Ave NW",
    "sg:city":"Edmonton",
    "sg:classifiers":[
        {
            "category":"Shopping",
            "subcategory":"Clothing, Apparel, & Fashions",
            "type":"Retail Goods"
        }
    ],
    "sg:phone":"+1 780 444 1610",
    "sg:postcode":"T5T 1L6",
    "sg:province":"AB",
    "sg:tags":[
        "furnishing"
    ],
    "wof:name":"Mr Big & Tall",
    "wof:placetype":"venue"
},
  "geometry": {"coordinates":[-113.61608099999999,53.524986],"type":"Point"}
}