{
  "type": "Feature",
  "properties": {
    "iso:country":"CA",
    "sg:address":"209 E Point Rd",
    "sg:city":"Saturna",
    "sg:classifiers":[
        {
            "category":"Building & Trades",
            "subcategory":"Construction",
            "type":"Services"
        }
    ],
    "sg:phone":"+1 604 461 3118",
    "sg:postcode":"V0N 2Y0",
    "sg:province":"BC",
    "sg:tags":[
        "contractor"
    ],
    "wof:name":"Charles Alp Construction",
    "wof:placetype":"venue"
},
  "geometry": {"coordinates":[-123.169998169,48.7929496765],"type":"Point"}
}