{
  "type": "Feature",
  "properties": {
    "addr:full":"181 Rue Principale Saint-Boniface-DE-Shawinigan QC G0X 2L0",
    "addr:housenumber":"181",
    "addr:postcode":"g0x 2l0",
    "addr:street":"Rue Principale",
    "iso:country":"CA",
    "sg:address":"181 Rue Principale",
    "sg:city":"Saint-Boniface-DE-Shawinigan",
    "sg:classifiers":[
        {
            "category":"Health Services",
            "subcategory":"Doctor",
            "type":"Services"
        }
    ],
    "sg:phone":"+1 819 535 3128",
    "sg:postcode":"G0X 2L0",
    "sg:province":"QC",
    "sg:tags":[
        "physician",
        "surgeon"
    ],
    "wof:name":"Dery, Richard MD",
    "wof:placetype":"venue"
},
  "geometry": {"coordinates":[-72.82756000000001,46.503815],"type":"Point"}
}