{
  "type": "Feature",
  "properties": {
    "addr:full":"2506 River John Station Rd River John NS B0K 1N0",
    "addr:housenumber":"2506",
    "addr:postcode":"b0k 1n0",
    "addr:street":"River John Station Rd",
    "iso:country":"CA",
    "sg:address":"2506 River John Station Rd",
    "sg:city":"River John",
    "sg:classifiers":[
        {
            "category":"Organizations",
            "subcategory":"Professional Association",
            "type":"Services"
        }
    ],
    "sg:phone":"+1 902 351 2966",
    "sg:postcode":"B0K 1N0",
    "sg:province":"NS",
    "wof:name":"Royal Canadian Legion",
    "wof:placetype":"venue"
},
  "geometry": {"coordinates":[-63.0590324402,45.7513961792],"type":"Point"}
}