{
  "type": "Feature",
  "properties": {
    "addr:full":"Surrey BC V3W 7X4",
    "addr:postcode":"v3w 7x4",
    "iso:country":"CA",
    "sg:city":"Surrey",
    "sg:classifiers":[
        {
            "category":"Building & Trades",
            "subcategory":"Electrical",
            "type":"Services"
        }
    ],
    "sg:phone":"+1 604 591 5117",
    "sg:postcode":"V3W 7X4",
    "sg:province":"BC",
    "sg:tags":[
        "electric",
        "contractor"
    ],
    "wof:name":"Gpr Electrical Ltd",
    "wof:placetype":"venue"
},
  "geometry": {"coordinates":[-122.86237335200001,49.1537590027],"type":"Point"}
}