{
  "type": "Feature",
  "properties": {
    "iso:country":"CA",
    "sg:address":"62 Richmond St",
    "sg:city":"Georgetown",
    "sg:classifiers":[
        {
            "category":"Travel",
            "subcategory":"Hotels & Motels",
            "type":"Entertainment"
        }
    ],
    "sg:phone":"+1 902 652 2511",
    "sg:postcode":"C0A 1L0",
    "sg:province":"PE",
    "sg:tags":[
        "breakfast",
        "accommodation",
        "bed"
    ],
    "wof:name":"Georgetown Inn",
    "wof:placetype":"venue"
},
  "geometry": {"coordinates":[-62.5319595337,46.1817131042],"type":"Point"}
}