{
  "type": "Feature",
  "properties": {
    "addr:full":"Kenora ON P9N 3W8",
    "addr:postcode":"p9n 3w8",
    "iso:country":"CA",
    "sg:city":"Kenora",
    "sg:classifiers":[
        {
            "category":"Wholesale",
            "subcategory":"Auto Parts",
            "type":"Manufacturing & Wholesale Goods"
        }
    ],
    "sg:phone":"+1 807 548 7827",
    "sg:postcode":"P9N 3W8",
    "sg:province":"ON",
    "sg:tags":[
        "automobile",
        "rebuilt"
    ],
    "wof:name":"Starter Exchange",
    "wof:placetype":"venue"
},
  "geometry": {"coordinates":[-94.45349899999999,49.775738],"type":"Point"}
}