{
  "type": "Feature",
  "properties": {
    "addr:full":"319 Carlaw Ave Toronto ON M4M 2S1",
    "addr:housenumber":"319",
    "addr:postcode":"m4m 2s1",
    "addr:street":"Carlaw Ave",
    "iso:country":"CA",
    "sg:address":"319 Carlaw Ave",
    "sg:city":"Toronto",
    "sg:classifiers":[
        {
            "category":"Manufacturing",
            "subcategory":"Apparel",
            "type":"Manufacturing & Wholesale Goods"
        }
    ],
    "sg:phone":"+1 416 465 9161",
    "sg:postcode":"M4M 2S1",
    "sg:province":"ON",
    "sg:tags":[
        "leather"
    ],
    "wof:name":"Leather Ranch Ltd",
    "wof:placetype":"venue"
},
  "geometry": {"coordinates":[-79.34114099999999,43.664207],"type":"Point"}
}