{
  "type": "Feature",
  "properties": {
    "addr:full":"76 Rue Philippe Chateauguay QC J6J 3C7",
    "addr:housenumber":"76",
    "addr:postcode":"j6j 3c7",
    "addr:street":"Rue Philippe Chateauguay",
    "iso:country":"CA",
    "sg:address":"76 Rue Philippe",
    "sg:city":"Chateauguay",
    "sg:classifiers":[
        {
            "category":"Wholesale",
            "subcategory":"Machinery & Supplies",
            "type":"Manufacturing & Wholesale Goods"
        }
    ],
    "sg:phone":"+1 450 699 4850",
    "sg:postcode":"J6J 3C7",
    "sg:province":"QC",
    "sg:tags":[
        "machine",
        "shredding",
        "paper"
    ],
    "wof:name":"Produits D'Affaires Massel",
    "wof:placetype":"venue"
},
  "geometry": {"coordinates":[-73.754311,45.362209],"type":"Point"}
}