{
  "type": "Feature",
  "properties": {
    "addr:full":"6962 Place D'Antioche Anjou QC H1M 1X1",
    "addr:housenumber":"6962",
    "addr:postcode":"h1m 1x1",
    "addr:street":"Place D'Antioche",
    "iso:country":"CA",
    "sg:address":"6962 Place D'Antioche",
    "sg:city":"Anjou",
    "sg:classifiers":[
        {
            "category":"Real Estate",
            "subcategory":"Real Estate Agent",
            "type":"Services"
        }
    ],
    "sg:phone":"+1 514 354 5753",
    "sg:postcode":"H1M 1X1",
    "sg:province":"QC",
    "wof:name":"Immeubles Vandelac Ltee",
    "wof:placetype":"venue"
},
  "geometry": {"coordinates":[-73.565322876,45.6125297546],"type":"Point"}
}