{
  "type": "Feature",
  "properties": {
    "addr:full":"3240 Langstaff Rd Concord ON L4K 4Z8",
    "addr:housenumber":"3240",
    "addr:postcode":"l4k 4z8",
    "addr:street":"Langstaff Rd",
    "iso:country":"CA",
    "sg:address":"3240 Langstaff Rd",
    "sg:city":"Concord",
    "sg:classifiers":[
        {
            "category":"Wholesale",
            "subcategory":"Construction Materials",
            "type":"Manufacturing & Wholesale Goods"
        }
    ],
    "sg:phone":"+1 905 760 1077",
    "sg:postcode":"L4K 4Z8",
    "sg:province":"ON",
    "sg:tags":[
        "stone"
    ],
    "wof:name":"Interstone Marble Granite Ltd",
    "wof:placetype":"venue"
},
  "geometry": {"coordinates":[-79.53461456300001,43.8112716675],"type":"Point"}
}