{
  "type": "Feature",
  "properties": {
    "addr:full":"8720 149 St NW Edmonton AB T5R 1B6",
    "addr:housenumber":"8720",
    "addr:postcode":"t5r 1b6",
    "addr:street":"149 St Nw",
    "iso:country":"CA",
    "sg:address":"8720 149 St NW",
    "sg:city":"Edmonton",
    "sg:classifiers":[
        {
            "category":"Food & Beverages",
            "subcategory":"Bakery",
            "type":"Retail Goods"
        }
    ],
    "sg:phone":"+1 780 489 7717",
    "sg:postcode":"T5R 1B6",
    "sg:province":"AB",
    "sg:tags":[
        "baker"
    ],
    "wof:name":"Bon Ton Bakery",
    "wof:placetype":"venue"
},
  "geometry": {"coordinates":[-113.578247,53.519836],"type":"Point"}
}