{
  "type": "Feature",
  "properties": {
    "addr:full":"17 Bronson Rd Deep River ON K0J 1P0",
    "addr:housenumber":"17",
    "addr:postcode":"k0j 1p0",
    "addr:street":"Bronson Rd",
    "iso:country":"CA",
    "sg:address":"17 Bronson Rd",
    "sg:city":"Deep River",
    "sg:classifiers":[
        {
            "category":"Retail",
            "subcategory":"Auto Repair",
            "type":"Services"
        }
    ],
    "sg:phone":"+1 613 584 9699",
    "sg:postcode":"K0J 1P0",
    "sg:province":"ON",
    "sg:tags":[
        "body",
        "automobile",
        "painting"
    ],
    "wof:name":"S S Auto Body",
    "wof:placetype":"venue"
},
  "geometry": {"coordinates":[-77.492653,46.098076],"type":"Point"}
}