{
  "type": "Feature",
  "properties": {
    "iso:country":"CA",
    "sg:address":"152 Ch DE LA Savane",
    "sg:city":"Gatineau",
    "sg:classifiers":[
        {
            "category":"Personal",
            "subcategory":"Beauty Salon",
            "type":"Services"
        }
    ],
    "sg:phone":"+1 819 561 2000",
    "sg:postcode":"J8T 5B9",
    "sg:province":"QC",
    "wof:name":"Estheti Ka",
    "wof:placetype":"venue"
},
  "geometry": {"coordinates":[-75.68966674799999,45.4744491577],"type":"Point"}
}