{
  "type": "Feature",
  "properties": {
    "addr:full":"1899 Grove Ave Windsor ON N9B 1P7",
    "addr:housenumber":"1899",
    "addr:postcode":"n9b 1p7",
    "addr:street":"Grove Ave",
    "iso:country":"CA",
    "sg:address":"1899 Grove Ave",
    "sg:city":"Windsor",
    "sg:classifiers":[
        {
            "category":"Recreation",
            "type":"Entertainment"
        }
    ],
    "sg:phone":"+1 519 252 1797",
    "sg:postcode":"N9B 1P7",
    "sg:province":"ON",
    "sg:tags":[
        "boxing",
        "instruction"
    ],
    "wof:name":"Windsor Amateur Boxing Club",
    "wof:placetype":"venue"
},
  "geometry": {"coordinates":[-83.05326100000001,42.299015],"type":"Point"}
}