{
  "type": "Feature",
  "properties": {
    "addr:full":"13 Autumn Pl Virgil ON L0S 1T0",
    "addr:housenumber":"13",
    "addr:postcode":"l0s 1t0",
    "addr:street":"Autumn Pl",
    "iso:country":"CA",
    "sg:address":"13 Autumn Pl",
    "sg:city":"Virgil",
    "sg:phone":"+1 905 468 2310",
    "sg:postcode":"L0S 1T0",
    "sg:province":"ON",
    "sg:tags":[
        "fixture",
        "store"
    ],
    "wof:name":"Dajune Inc",
    "wof:placetype":"venue"
},
  "geometry": {"coordinates":[-79.12809753419999,43.2226028442],"type":"Point"}
}