{
  "type": "Feature",
  "properties": {
    "addr:full":"673 Yonge St Toronto ON M4Y 1Z9",
    "addr:housenumber":"673",
    "addr:postcode":"m4y 1z9",
    "addr:street":"Yonge St",
    "iso:country":"CA",
    "sg:address":"673 Yonge St",
    "sg:city":"Toronto",
    "sg:classifiers":[
        {
            "category":"Shopping",
            "subcategory":"Shoes",
            "type":"Retail Goods"
        }
    ],
    "sg:phone":"+1 416 920 8377",
    "sg:postcode":"M4Y 1Z9",
    "sg:province":"ON",
    "wof:name":"Payless Shoe Source",
    "wof:placetype":"venue"
},
  "geometry": {"coordinates":[-79.38594818120001,43.6685562134],"type":"Point"}
}