{
  "type": "Feature",
  "properties": {
    "iso:country":"CA",
    "sg:address":"91 397 Rte N",
    "sg:city":"Barraute",
    "sg:classifiers":[
        {
            "category":"Utilities",
            "subcategory":"Fuel Oil & Lpg",
            "type":"Services"
        }
    ],
    "sg:phone":"+1 819 734 6755",
    "sg:postcode":"J0Y 1A0",
    "sg:province":"QC",
    "sg:tags":[
        "propane",
        "gas"
    ],
    "wof:name":"Barrette Gas Station",
    "wof:placetype":"venue"
},
  "geometry": {"coordinates":[-77.6380615234,48.5744743347],"type":"Point"}
}