{
  "type": "Feature",
  "properties": {
    "addr:full":"93 Church St Mississauga ON L5M 1M6",
    "addr:housenumber":"93",
    "addr:postcode":"l5m 1m6",
    "addr:street":"Church St",
    "iso:country":"CA",
    "sg:address":"93 Church St",
    "sg:city":"Mississauga",
    "sg:classifiers":[
        {
            "category":"Organizations",
            "subcategory":"Professional Association",
            "type":"Services"
        }
    ],
    "sg:phone":"+1 905 826 4214",
    "sg:postcode":"L5M 1M6",
    "sg:province":"ON",
    "sg:tags":[
        "club"
    ],
    "wof:name":"Navy League of Canada",
    "wof:placetype":"venue"
},
  "geometry": {"coordinates":[-79.717018,43.585392],"type":"Point"}
}