{
  "type": "Feature",
  "properties": {
    "addr:full":"1007 Douglas Ave Fredericton NB E3A 9M8",
    "addr:housenumber":"1007",
    "addr:postcode":"e3a 9m8",
    "addr:street":"Douglas Ave",
    "iso:country":"CA",
    "sg:address":"1007 Douglas Ave",
    "sg:city":"Fredericton",
    "sg:classifiers":[
        {
            "category":"Personal",
            "subcategory":"Beauty Salon",
            "type":"Services"
        }
    ],
    "sg:phone":"+1 506 454 3400",
    "sg:postcode":"E3A 9M8",
    "sg:province":"NB",
    "wof:name":"Nails By Karen",
    "wof:placetype":"venue"
},
  "geometry": {"coordinates":[-66.650238,45.988728],"type":"Point"}
}