{
  "type": "Feature",
  "properties": {
    "iso:country":"CA",
    "sg:address":"218 Rue Principale",
    "sg:city":"Saint-Prime",
    "sg:classifiers":[
        {
            "category":"Wholesale",
            "subcategory":"Auto Parts",
            "type":"Manufacturing & Wholesale Goods"
        }
    ],
    "sg:phone":"+1 418 251 3030",
    "sg:postcode":"G8J 1R8",
    "sg:province":"QC",
    "sg:tags":[
        "automobile",
        "rebuilt"
    ],
    "wof:name":"Pieces D'Auto Usagees Fg Inc",
    "wof:placetype":"venue"
},
  "geometry": {"coordinates":[-72.3077697754,48.5687026978],"type":"Point"}
}