{
  "type": "Feature",
  "properties": {
    "addr:full":"330 Universite Ave Moncton NB E1C 2Z3",
    "addr:housenumber":"330",
    "addr:postcode":"e1c 2z3",
    "addr:street":"Universite Ave",
    "iso:country":"CA",
    "sg:address":"330 Universite Ave",
    "sg:city":"Moncton",
    "sg:classifiers":[
        {
            "category":"Health Services",
            "subcategory":"Doctor",
            "type":"Services"
        }
    ],
    "sg:phone":"+1 506 869 2150",
    "sg:postcode":"E1C 2Z3",
    "sg:province":"NB",
    "sg:tags":[
        "physician",
        "surgeon"
    ],
    "wof:name":"Le Blanc, Nicole MD",
    "wof:placetype":"venue"
},
  "geometry": {"coordinates":[-64.78630065919999,46.0982894897],"type":"Point"}
}