{
  "type": "Feature",
  "properties": {
    "iso:country":"CA",
    "sg:city":"Red Bay",
    "sg:classifiers":[
        {
            "category":"Travel",
            "subcategory":"Campground",
            "type":"Entertainment"
        }
    ],
    "sg:phone":"+1 709 896 3301",
    "sg:postcode":"A0K 4K0",
    "sg:province":"NL",
    "sg:tags":[
        "camp",
        "fishing"
    ],
    "wof:name":"Park Lake Lodge Inc",
    "wof:placetype":"venue"
},
  "geometry": {"coordinates":[-56.4258308411,51.730796814],"type":"Point"}
}