{
  "type": "Feature",
  "properties": {
    "iso:country":"CA",
    "sg:address":"10746 Av Salk",
    "sg:city":"Montreal-Nord",
    "sg:classifiers":[
        {
            "category":"Manufacturing",
            "subcategory":"Rubber & Plastics",
            "type":"Manufacturing & Wholesale Goods"
        }
    ],
    "sg:phone":"+1 514 324 4960",
    "sg:postcode":"H1G 4Y1",
    "sg:province":"QC",
    "sg:tags":[
        "screen",
        "printing"
    ],
    "wof:name":"Trans-Form Exact",
    "wof:placetype":"venue"
},
  "geometry": {"coordinates":[-73.620155,45.598015],"type":"Point"}
}