{
  "type": "Feature",
  "properties": {
    "addr:full":"200 Boul Wallberg Dolbeau-Mistassini QC G8L 6A5",
    "addr:housenumber":"200",
    "addr:postcode":"g8l 6a5",
    "addr:street":"Boul Wallberg",
    "iso:country":"CA",
    "sg:address":"200 Boul Wallberg",
    "sg:city":"Dolbeau-Mistassini",
    "sg:classifiers":[
        {
            "category":"Education",
            "subcategory":"School",
            "type":"Public Place"
        }
    ],
    "sg:phone":"+1 418 276 3340",
    "sg:postcode":"G8L 6A5",
    "sg:province":"QC",
    "wof:name":"Freres-Instruction Chretienne",
    "wof:placetype":"venue"
},
  "geometry": {"coordinates":[-72.21470600000001,48.861504],"type":"Point"}
}