{
  "type": "Feature",
  "properties": {
    "addr:full":"2151 Park St Regina SK S4N 2G8",
    "addr:housenumber":"2151",
    "addr:postcode":"s4n 2g8",
    "addr:street":"Park St",
    "iso:country":"CA",
    "sg:address":"2151 Park St",
    "sg:city":"Regina",
    "sg:classifiers":[
        {
            "category":"Building & Trades",
            "subcategory":"Cleaning & Sanitation",
            "type":"Services"
        }
    ],
    "sg:phone":"+1 306 757 3562",
    "sg:postcode":"S4N 2G8",
    "sg:province":"SK",
    "sg:tags":[
        "janitor"
    ],
    "wof:name":"Kim Cleaning Svc",
    "wof:placetype":"venue"
},
  "geometry": {"coordinates":[-104.57196,50.444801],"type":"Point"}
}