{
  "type": "Feature",
  "properties": {
    "iso:country":"CA",
    "sg:address":"603 Ch Du Progres",
    "sg:city":"Chute-Saint-Philippe",
    "sg:classifiers":[
        {
            "category":"Organizations",
            "subcategory":"Religious Organization",
            "type":"Services"
        }
    ],
    "sg:phone":"+1 819 585 2733",
    "sg:postcode":"J0W 1A0",
    "sg:province":"QC",
    "wof:name":"Presbytere",
    "wof:placetype":"venue"
},
  "geometry": {"coordinates":[-75.2408065796,46.6520233154],"type":"Point"}
}