{
  "type": "Feature",
  "properties": {
    "addr:full":"6077 Trapp Ave Burnaby BC V3N 2V3",
    "addr:housenumber":"6077",
    "addr:postcode":"v3n 2v3",
    "addr:street":"Trapp Ave",
    "iso:country":"CA",
    "sg:address":"6077 Trapp Ave",
    "sg:city":"Burnaby",
    "sg:classifiers":[
        {
            "category":"Wholesale",
            "subcategory":"Auto Parts",
            "type":"Manufacturing & Wholesale Goods"
        }
    ],
    "sg:phone":"+1 604 526 0806",
    "sg:postcode":"V3N 2V3",
    "sg:province":"BC",
    "sg:tags":[
        "automobile",
        "wrecking"
    ],
    "wof:name":"Ace German Used Parts",
    "wof:placetype":"venue"
},
  "geometry": {"coordinates":[-122.96090700000001,49.194057],"type":"Point"}
}