{
  "type": "Feature",
  "properties": {
    "addr:full":"636 Shaw Rd Dorchester ON N0L 1G4",
    "addr:housenumber":"636",
    "addr:postcode":"n0l 1g4",
    "addr:street":"Shaw Rd",
    "iso:country":"CA",
    "sg:address":"636 Shaw Rd",
    "sg:city":"Dorchester",
    "sg:classifiers":[
        {
            "category":"Home & Garden",
            "subcategory":"Building Materials",
            "type":"Retail Goods"
        }
    ],
    "sg:phone":"+1 519 268 2440",
    "sg:postcode":"N0L 1G4",
    "sg:province":"ON",
    "sg:tags":[
        "siding"
    ],
    "wof:name":"G W Revesz Metal Fabrication",
    "wof:placetype":"venue"
},
  "geometry": {"coordinates":[-81.098175,43.009552],"type":"Point"}
}