{
  "type": "Feature",
  "properties": {
    "addr:full":"Toronto ON M4S 1Z9",
    "addr:postcode":"m4s 1z9",
    "iso:country":"CA",
    "sg:city":"Toronto",
    "sg:classifiers":[
        {
            "category":"Professional",
            "subcategory":"Lawyer & Legal Services",
            "type":"Services"
        }
    ],
    "sg:phone":"+1 416 482 3611",
    "sg:postcode":"M4S 1Z9",
    "sg:province":"ON",
    "sg:tags":[
        "attorney"
    ],
    "wof:name":"Prousky, Victor",
    "wof:placetype":"venue"
},
  "geometry": {"coordinates":[-79.397415,43.70129],"type":"Point"}
}