{
  "type": "Feature",
  "properties": {
    "addr:full":"Kimmirut NU X0A 0N0",
    "addr:postcode":"x0a 0n0",
    "iso:country":"CA",
    "sg:city":"Kimmirut",
    "sg:classifiers":[
        {
            "category":"Government",
            "subcategory":"Office",
            "type":"Public Place"
        }
    ],
    "sg:phone":"+1 867 939 2301",
    "sg:postcode":"X0A 0N0",
    "sg:province":"NU",
    "wof:name":"Canada Transport",
    "wof:placetype":"venue"
},
  "geometry": {"coordinates":[-69.86892700200001,62.846862793],"type":"Point"}
}