{
  "type": "Feature",
  "properties": {
    "iso:country":"CA",
    "sg:city":"Innerkip",
    "sg:classifiers":[
        {
            "category":"Food & Beverages",
            "subcategory":"Fruits & Vegetables",
            "type":"Retail Goods"
        }
    ],
    "sg:phone":"+1 519 469 3636",
    "sg:postcode":"N0J 1M0",
    "sg:province":"ON",
    "sg:tags":[
        "produce"
    ],
    "wof:name":"Thames River Berries",
    "wof:placetype":"venue"
},
  "geometry": {"coordinates":[-80.683555603,43.191368103],"type":"Point"}
}