{
  "type": "Feature",
  "properties": {
    "addr:full":"Bridgetown NS B0S 1C0",
    "addr:postcode":"b0s 1c0",
    "iso:country":"CA",
    "sg:city":"Bridgetown",
    "sg:classifiers":[
        {
            "category":"Recreation",
            "type":"Entertainment"
        }
    ],
    "sg:phone":"+1 902 665 4257",
    "sg:postcode":"B0S 1C0",
    "sg:province":"NS",
    "sg:tags":[
        "course",
        "golf"
    ],
    "wof:name":"Eden Golf & Country Club",
    "wof:placetype":"venue"
},
  "geometry": {"coordinates":[-65.2890472412,44.8413543701],"type":"Point"}
}