{
  "type": "Feature",
  "properties": {
    "addr:full":"211 Main St Central Butte SK S0H 0T0",
    "addr:housenumber":"211",
    "addr:postcode":"s0h 0t0",
    "addr:street":"Main St",
    "iso:country":"CA",
    "sg:address":"211 Main St",
    "sg:city":"Central Butte",
    "sg:classifiers":[
        {
            "category":"Banks & Credit Unions",
            "subcategory":"Bank",
            "type":"Services"
        }
    ],
    "sg:phone":"+1 306 796 2060",
    "sg:postcode":"S0H 0T0",
    "sg:province":"SK",
    "wof:name":"Cibc",
    "wof:placetype":"venue"
},
  "geometry": {"coordinates":[-106.51249694800001,50.7961540222],"type":"Point"}
}