{
  "type": "Feature",
  "properties": {
    "addr:full":"36 Wilson Rd Stirling ON K0K 3E0",
    "addr:housenumber":"36",
    "addr:postcode":"k0k 3e0",
    "addr:street":"Wilson Rd",
    "iso:country":"CA",
    "sg:address":"36 Wilson Rd",
    "sg:city":"Stirling",
    "sg:classifiers":[
        {
            "category":"Retail",
            "subcategory":"Veterinary Services",
            "type":"Services"
        }
    ],
    "sg:phone":"+1 613 395 2716",
    "sg:postcode":"K0K 3E0",
    "sg:province":"ON",
    "sg:tags":[
        "veterinarian"
    ],
    "wof:name":"Stirling Veterinary Svc",
    "wof:placetype":"venue"
},
  "geometry": {"coordinates":[-77.5467834473,44.2962989807],"type":"Point"}
}