{
  "type": "Feature",
  "properties": {
    "addr:full":"23 Allangrove Cres Scarborough ON M1W 1S4",
    "addr:housenumber":"23",
    "addr:postcode":"m1w 1s4",
    "addr:street":"Allangrove Cres",
    "iso:country":"CA",
    "sg:address":"23 Allangrove Cres",
    "sg:city":"Scarborough",
    "sg:classifiers":[
        {
            "category":"Professional",
            "subcategory":"Business Services",
            "type":"Services"
        }
    ],
    "sg:phone":"+1 416 495 8946",
    "sg:postcode":"M1W 1S4",
    "sg:province":"ON",
    "sg:tags":[
        "embroidery"
    ],
    "wof:name":"Sue's Monogram Shoppe",
    "wof:placetype":"venue"
},
  "geometry": {"coordinates":[-79.31287399999999,43.78812],"type":"Point"}
}