{
  "type": "Feature",
  "properties": {
    "addr:full":"3777 Ch DE LA Cote-Des-Neiges #100 Montreal QC H3H 1V8",
    "addr:housenumber":"3777;# 100",
    "addr:postcode":"h3h 1v8",
    "addr:street":"Ch De La Cote-Des-Neiges",
    "iso:country":"CA",
    "sg:address":"3777 Ch DE LA Cote-Des-Neiges #100",
    "sg:city":"Montreal",
    "sg:classifiers":[
        {
            "category":"Professional",
            "type":"Services"
        }
    ],
    "sg:phone":"+1 514 938 5117",
    "sg:postcode":"H3H 1V8",
    "sg:province":"QC",
    "sg:tags":[
        "apartment",
        "establishment"
    ],
    "wof:name":"Immeubles Bayside Lakeshore",
    "wof:placetype":"venue"
},
  "geometry": {"coordinates":[-73.5896,45.495495],"type":"Point"}
}