{
  "type": "Feature",
  "properties": {
    "addr:full":"215 Hempstead Dr Hamilton ON L8W 2E6",
    "addr:housenumber":"215",
    "addr:postcode":"l8w 2e6",
    "addr:street":"Hempstead Dr",
    "iso:country":"CA",
    "sg:address":"215 Hempstead Dr",
    "sg:city":"Hamilton",
    "sg:classifiers":[
        {
            "category":"Manufacturing",
            "subcategory":"Tools & Machinery",
            "type":"Manufacturing & Wholesale Goods"
        }
    ],
    "sg:phone":"+1 905 385 3201",
    "sg:postcode":"L8W 2E6",
    "sg:province":"ON",
    "sg:tags":[
        "packaging"
    ],
    "wof:name":"Edson Packaging Machinery Ltd",
    "wof:placetype":"venue"
},
  "geometry": {"coordinates":[-79.8349685669,43.1954193115],"type":"Point"}
}