{
  "type": "Feature",
  "properties": {
    "addr:full":"1555 Route 745 Canoose NB E5A 1H6",
    "addr:housenumber":"1555",
    "addr:postcode":"e5a 1h6",
    "addr:street":"Route 745",
    "iso:country":"CA",
    "sg:address":"1555 Route 745",
    "sg:city":"Canoose",
    "sg:classifiers":[
        {
            "category":"Home & Garden",
            "subcategory":"Garden Supply",
            "type":"Retail Goods"
        }
    ],
    "sg:phone":"+1 506 466 3439",
    "sg:postcode":"E5A 1H6",
    "sg:province":"NB",
    "sg:tags":[
        "lawn",
        "mower"
    ],
    "wof:name":"Hovey's Husky Sales & Svc",
    "wof:placetype":"venue"
},
  "geometry": {"coordinates":[-67.34674800000001,45.360489],"type":"Point"}
}