{
  "type": "Feature",
  "properties": {
    "iso:country":"CA",
    "sg:address":"3891 Hastings St",
    "sg:city":"Burnaby",
    "sg:classifiers":[
        {
            "category":"Restaurant",
            "type":"Food & Drink"
        }
    ],
    "sg:phone":"+1 604 298 8110",
    "sg:postcode":"V5C 2H7",
    "sg:province":"BC",
    "wof:name":"L'Artista Italian Restaurant",
    "wof:placetype":"venue"
},
  "geometry": {"coordinates":[-123.018920898,49.2812843323],"type":"Point"}
}