{
  "type": "Feature",
  "properties": {
    "addr:full":"159 Dupont St Toronto ON M5R 1V5",
    "addr:housenumber":"159",
    "addr:postcode":"m5r 1v5",
    "addr:street":"Dupont St",
    "iso:country":"CA",
    "sg:address":"159 Dupont St",
    "sg:city":"Toronto",
    "sg:classifiers":[
        {
            "category":"Retail",
            "subcategory":"Photofinishing",
            "type":"Services"
        }
    ],
    "sg:phone":"+1 416 961 8019",
    "sg:postcode":"M5R 1V5",
    "sg:province":"ON",
    "sg:tags":[
        "photo",
        "finishing"
    ],
    "wof:name":"George Photographic Studio Ltd",
    "wof:placetype":"venue"
},
  "geometry": {"coordinates":[-79.403008,43.675579],"type":"Point"}
}