{
  "type": "Feature",
  "properties": {
    "addr:full":"3521 Joseph Howe Dr Halifax NS B3L 4H6",
    "addr:housenumber":"3521",
    "addr:postcode":"b3l 4h6",
    "addr:street":"Joseph Howe Dr",
    "iso:country":"CA",
    "sg:address":"3521 Joseph Howe Dr",
    "sg:city":"Halifax",
    "sg:classifiers":[
        {
            "category":"Personal",
            "subcategory":"Beauty Salon",
            "type":"Services"
        }
    ],
    "sg:phone":"+1 902 453 5669",
    "sg:postcode":"B3L 4H6",
    "sg:province":"NS",
    "wof:name":"Anna's Unisex Hair Salon",
    "wof:placetype":"venue"
},
  "geometry": {"coordinates":[-63.629528,44.655777],"type":"Point"}
}