{
  "type": "Feature",
  "properties": {
    "addr:full":"3452 Rue Albert Rawdon QC J0K 1S0",
    "addr:housenumber":"3452",
    "addr:postcode":"j0k 1s0",
    "addr:street":"Rue Albert",
    "iso:country":"CA",
    "sg:address":"3452 Rue Albert",
    "sg:city":"Rawdon",
    "sg:classifiers":[
        {
            "category":"Retail",
            "subcategory":"Auto Repair",
            "type":"Services"
        }
    ],
    "sg:phone":"+1 450 834 1717",
    "sg:postcode":"J0K 1S0",
    "sg:province":"QC",
    "sg:tags":[
        "repairing",
        "automobile"
    ],
    "wof:name":"Garage Dominic Gregoire",
    "wof:placetype":"venue"
},
  "geometry": {"coordinates":[-73.702293396,46.0374565125],"type":"Point"}
}