{
  "type": "Feature",
  "properties": {
    "addr:full":"1300 Boul Jules-Poitras Saint-Laurent QC H4N 1X7",
    "addr:housenumber":"1300",
    "addr:postcode":"h4n 1x7",
    "addr:street":"Boul Jules-Poitras",
    "iso:country":"CA",
    "sg:address":"1300 Boul Jules-Poitras",
    "sg:city":"Saint-Laurent",
    "sg:classifiers":[
        {
            "category":"Wholesale",
            "subcategory":"Stationery",
            "type":"Manufacturing & Wholesale Goods"
        }
    ],
    "sg:phone":"+1 514 331 0083",
    "sg:postcode":"H4N 1X7",
    "sg:province":"QC",
    "sg:tags":[
        "packaging",
        "material"
    ],
    "wof:name":"Paramount Paper Products Ltd",
    "wof:placetype":"venue"
},
  "geometry": {"coordinates":[-73.67524719239999,45.5265884399],"type":"Point"}
}