{
  "type": "Feature",
  "properties": {
    "addr:full":"Toronto ON M5V 3A8",
    "addr:postcode":"m5v 3a8",
    "iso:country":"CA",
    "sg:city":"Toronto",
    "sg:classifiers":[
        {
            "category":"Professional",
            "subcategory":"Art Services",
            "type":"Services"
        }
    ],
    "sg:phone":"+1 416 506 0202",
    "sg:postcode":"M5V 3A8",
    "sg:province":"ON",
    "sg:tags":[
        "graphic",
        "designer"
    ],
    "wof:name":"Oxygen Design & Communications",
    "wof:placetype":"venue"
},
  "geometry": {"coordinates":[-79.395088,43.64785],"type":"Point"}
}