{
  "type": "Feature",
  "properties": {
    "addr:full":"1011 Upper Middle Rd E Oakville ON L6H 4L2",
    "addr:housenumber":"1011",
    "addr:postcode":"l6h 4l2",
    "addr:street":"Upper Middle Rd E",
    "iso:country":"CA",
    "sg:address":"1011 Upper Middle Rd E",
    "sg:city":"Oakville",
    "sg:classifiers":[
        {
            "category":"Shopping",
            "type":"Retail Goods"
        }
    ],
    "sg:phone":"+1 905 842 6114",
    "sg:postcode":"L6H 4L2",
    "sg:province":"ON",
    "sg:tags":[
        "picture",
        "frame"
    ],
    "wof:name":"Peach Tree Gallery",
    "wof:placetype":"venue"
},
  "geometry": {"coordinates":[-79.695053,43.48135],"type":"Point"}
}