{
  "type": "Feature",
  "properties": {
    "addr:full":"3510 Pharmacy Ave Scarborough ON M1W 2T7",
    "addr:housenumber":"3510",
    "addr:postcode":"m1w 2t7",
    "addr:street":"Pharmacy Ave",
    "iso:country":"CA",
    "sg:address":"3510 Pharmacy Ave",
    "sg:city":"Scarborough",
    "sg:classifiers":[
        {
            "category":"Freight",
            "type":"Transportation"
        }
    ],
    "sg:phone":"+1 416 498 9997",
    "sg:postcode":"M1W 2T7",
    "sg:province":"ON",
    "sg:tags":[
        "warehouse",
        "self",
        "storage"
    ],
    "wof:name":"1251639 Ontario Ltd",
    "wof:placetype":"venue"
},
  "geometry": {"coordinates":[-79.333626,43.810123],"type":"Point"}
}