{
  "type": "Feature",
  "properties": {
    "addr:full":"10636 Ch DE LA Cote-DE-Liesse Lachine QC H8T 1A5",
    "addr:housenumber":"10636",
    "addr:postcode":"h8t 1a5",
    "addr:street":"Ch De La Cote-De-Liesse",
    "iso:country":"CA",
    "sg:address":"10636 Ch DE LA Cote-DE-Liesse",
    "sg:city":"Lachine",
    "sg:classifiers":[
        {
            "category":"Professional",
            "subcategory":"Management & Consulting",
            "type":"Services"
        }
    ],
    "sg:phone":"+1 514 636 7252",
    "sg:postcode":"H8T 1A5",
    "sg:province":"QC",
    "sg:tags":[
        "consultant",
        "business"
    ],
    "wof:name":"Tradead",
    "wof:placetype":"venue"
},
  "geometry": {"coordinates":[-73.72123000000001,45.463078],"type":"Point"}
}