{
  "type": "Feature",
  "properties": {
    "iso:country":"CA",
    "sg:address":"971 Rue Neree-Duplessis",
    "sg:city":"Trois-Rivieres",
    "sg:classifiers":[
        {
            "category":"Building & Trades",
            "subcategory":"Equipment Rental",
            "type":"Services"
        }
    ],
    "sg:phone":"+1 819 375 5251",
    "sg:postcode":"G9A 1Z1",
    "sg:province":"QC",
    "sg:tags":[
        "sound",
        "leasing",
        "system"
    ],
    "wof:name":"Audi-C Sonorisation Inc",
    "wof:placetype":"venue"
},
  "geometry": {"coordinates":[-72.5481872559,46.3484115601],"type":"Point"}
}