{
  "type": "Feature",
  "properties": {
    "addr:full":"NE 8-56-25W The Pas MB R9A 1K2",
    "addr:postcode":"r9a 1k2",
    "addr:street":"Ne 8-56-25W",
    "iso:country":"CA",
    "sg:address":"NE 8-56-25W",
    "sg:city":"The Pas",
    "sg:classifiers":[
        {
            "category":"Building & Trades",
            "subcategory":"Plumbing",
            "type":"Services"
        }
    ],
    "sg:phone":"+1 204 623 3976",
    "sg:postcode":"R9A 1K2",
    "sg:province":"MB",
    "sg:tags":[
        "septic"
    ],
    "wof:name":"Atchy's Septic Svc",
    "wof:placetype":"venue"
},
  "geometry": {"coordinates":[-101.25035095200001,53.8134346008],"type":"Point"}
}