{
  "type": "Feature",
  "properties": {
    "addr:full":"2399 Mountainside Dr Burlington ON L7P 1C6",
    "addr:housenumber":"2399",
    "addr:postcode":"l7p 1c6",
    "addr:street":"Mountainside Dr",
    "iso:country":"CA",
    "sg:address":"2399 Mountainside Dr",
    "sg:city":"Burlington",
    "sg:classifiers":[
        {
            "category":"Education",
            "subcategory":"School",
            "type":"Public Place"
        }
    ],
    "sg:phone":"+1 905 335 5605",
    "sg:postcode":"L7P 1C6",
    "sg:province":"ON",
    "wof:name":"Clarksdale Elementary School",
    "wof:placetype":"venue"
},
  "geometry": {"coordinates":[-79.81261444090001,43.353553772],"type":"Point"}
}