{
  "type": "Feature",
  "properties": {
    "addr:full":"13514 97 St NW Edmonton AB T5E 4E2",
    "addr:housenumber":"13514",
    "addr:postcode":"t5e 4e2",
    "addr:street":"97 St Nw",
    "iso:country":"CA",
    "sg:address":"13514 97 St NW",
    "sg:city":"Edmonton",
    "sg:classifiers":[
        {
            "category":"Shopping",
            "subcategory":"Pharmacy",
            "type":"Retail Goods"
        }
    ],
    "sg:phone":"+1 780 406 7396",
    "sg:postcode":"T5E 4E2",
    "sg:province":"AB",
    "wof:name":"Shoppers Drug Mart",
    "wof:placetype":"venue"
},
  "geometry": {"coordinates":[-113.492294,53.597099],"type":"Point"}
}