{
  "type": "Feature",
  "properties": {
    "iso:country":"CA",
    "sg:city":"Ajax",
    "sg:classifiers":[
        {
            "category":"Home & Garden",
            "subcategory":"Garden Supply",
            "type":"Retail Goods"
        }
    ],
    "sg:phone":"+1 905 427 1969",
    "sg:postcode":"L1S 6M7",
    "sg:province":"ON",
    "sg:tags":[
        "lawn",
        "mower"
    ],
    "wof:name":"Ajax Small Engine Repairs",
    "wof:placetype":"venue"
},
  "geometry": {"coordinates":[-79.03527832029999,43.8387489319],"type":"Point"}
}