{
  "type": "Feature",
  "properties": {
    "iso:country":"CA",
    "sg:address":"1299 Oxford St E",
    "sg:city":"London",
    "sg:classifiers":[
        {
            "category":"Banks & Credit Unions",
            "subcategory":"Bank",
            "type":"Services"
        }
    ],
    "sg:phone":"+1 519 452 7400",
    "sg:postcode":"N5Y 4W5",
    "sg:province":"ON",
    "wof:name":"Cibc",
    "wof:placetype":"venue"
},
  "geometry": {"coordinates":[-81.210007,43.007927],"type":"Point"}
}