{
  "type": "Feature",
  "properties": {
    "iso:country":"CA",
    "sg:address":"298 1E Rg",
    "sg:city":"Saint-Hilarion",
    "sg:classifiers":[
        {
            "category":"Farming",
            "subcategory":"Farm",
            "type":"Manufacturing & Wholesale Goods"
        }
    ],
    "sg:phone":"+1 418 457 3393",
    "sg:postcode":"G0A 3V0",
    "sg:province":"QC",
    "wof:name":"Gauthier, Remy",
    "wof:placetype":"venue"
},
  "geometry": {"coordinates":[-70.3945007324,47.5674057007],"type":"Point"}
}