{
  "type": "Feature",
  "properties": {
    "addr:full":"419 Boul Jessop Rimouski QC G5L 7Y5",
    "addr:housenumber":"419",
    "addr:postcode":"g5l 7y5",
    "addr:street":"Boul Jessop",
    "iso:country":"CA",
    "sg:address":"419 Boul Jessop",
    "sg:city":"Rimouski",
    "sg:classifiers":[
        {
            "category":"Shopping",
            "subcategory":"Department Store",
            "type":"Retail Goods"
        }
    ],
    "sg:phone":"+1 418 722 8181",
    "sg:postcode":"G5L 7Y5",
    "sg:province":"QC",
    "wof:name":"Zellers",
    "wof:placetype":"venue"
},
  "geometry": {"coordinates":[-68.51559399999999,48.468117],"type":"Point"}
}