{
  "type": "Feature",
  "properties": {
    "addr:full":"Hamilton ON L8N 1Y2",
    "addr:postcode":"l8n 1y2",
    "iso:country":"CA",
    "sg:city":"Hamilton",
    "sg:classifiers":[
        {
            "category":"Health Services",
            "subcategory":"Medical Lab",
            "type":"Services"
        }
    ],
    "sg:phone":"+1 905 521 6052",
    "sg:postcode":"L8N 1Y2",
    "sg:province":"ON",
    "sg:tags":[
        "laboratory"
    ],
    "wof:name":"Community Laboratory Svc",
    "wof:placetype":"venue"
},
  "geometry": {"coordinates":[-79.871117,43.24966],"type":"Point"}
}