{
  "type": "Feature",
  "properties": {
    "addr:full":"56 Rue Notre Dame E Cap-Chat-Est QC G0J 1G0",
    "addr:housenumber":"56",
    "addr:postcode":"g0j 1g0",
    "addr:street":"Rue Notre Dame E Cap-Chat-Est",
    "iso:country":"CA",
    "sg:address":"56 Rue Notre Dame E",
    "sg:city":"Cap-Chat-Est",
    "sg:classifiers":[
        {
            "category":"Food & Beverages",
            "subcategory":"Groceries & Convenience Stores",
            "type":"Retail Goods"
        }
    ],
    "sg:phone":"+1 418 786 5911",
    "sg:postcode":"G0J 1G0",
    "sg:province":"QC",
    "sg:tags":[
        "grocer"
    ],
    "wof:name":"Epicerie Pelletier Marc",
    "wof:placetype":"venue"
},
  "geometry": {"coordinates":[-66.6672744751,49.100933075],"type":"Point"}
}