{
  "type": "Feature",
  "properties": {
    "addr:full":"Hearst ON P0L 1N0",
    "addr:postcode":"p0l 1n0",
    "iso:country":"CA",
    "sg:city":"Hearst",
    "sg:classifiers":[
        {
            "category":"Manufacturing",
            "subcategory":"Lumber",
            "type":"Manufacturing & Wholesale Goods"
        }
    ],
    "sg:phone":"+1 705 362 8182",
    "sg:postcode":"P0L 1N0",
    "sg:province":"ON",
    "sg:tags":[
        "forester"
    ],
    "wof:name":"Devitt Quarry Ltd",
    "wof:placetype":"venue"
},
  "geometry": {"coordinates":[-83.6675872803,49.6886749268],"type":"Point"}
}