{
  "type": "Feature",
  "properties": {
    "addr:full":"Burnaby BC V5B 3A6",
    "addr:postcode":"v5b 3a6",
    "iso:country":"CA",
    "sg:city":"Burnaby",
    "sg:classifiers":[
        {
            "category":"Building & Trades",
            "subcategory":"Construction",
            "type":"Services"
        }
    ],
    "sg:phone":"+1 604 299 2522",
    "sg:postcode":"V5B 3A6",
    "sg:province":"BC",
    "sg:tags":[
        "roofing",
        "contractor"
    ],
    "wof:name":"Tek Roofing & Sheet Metal",
    "wof:placetype":"venue"
},
  "geometry": {"coordinates":[-122.97547900000001,49.2556],"type":"Point"}
}