{
  "type": "Feature",
  "properties": {
    "addr:full":"727 2nd Ave E Owen Sound ON N4K 2G9",
    "addr:housenumber":"727",
    "addr:postcode":"n4k 2g9",
    "addr:street":"2Nd Ave E",
    "iso:country":"CA",
    "sg:address":"727 2nd Ave E",
    "sg:city":"Owen Sound",
    "sg:classifiers":[
        {
            "category":"Recreation",
            "type":"Entertainment"
        }
    ],
    "sg:phone":"+1 519 376 3407",
    "sg:postcode":"N4K 2G9",
    "sg:province":"ON",
    "sg:tags":[
        "hall",
        "auditorium"
    ],
    "wof:name":"Grey Granite Club",
    "wof:placetype":"venue"
},
  "geometry": {"coordinates":[-80.94190999999999,44.562656],"type":"Point"}
}