{
  "type": "Feature",
  "properties": {
    "addr:full":"615 Grande Allee E Quebec QC G1R 2K4",
    "addr:housenumber":"615",
    "addr:postcode":"g1r 2k4",
    "addr:street":"Grande Allee E",
    "iso:country":"CA",
    "sg:address":"615 Grande Allee E",
    "sg:city":"Quebec",
    "sg:classifiers":[
        {
            "category":"Shopping",
            "type":"Retail Goods"
        }
    ],
    "sg:phone":"+1 418 648 9292",
    "sg:postcode":"G1R 2K4",
    "sg:province":"QC",
    "sg:tags":[
        "art",
        "gallery",
        "dealer"
    ],
    "wof:name":"Galerie D'Art Les Peintres",
    "wof:placetype":"venue"
},
  "geometry": {"coordinates":[-71.216568,46.806152],"type":"Point"}
}