{
  "type": "Feature",
  "properties": {
    "addr:full":"Havre-Saint-Pierre QC G0G 1P0",
    "addr:postcode":"g0g 1p0",
    "iso:country":"CA",
    "sg:city":"Havre-Saint-Pierre",
    "sg:classifiers":[
        {
            "category":"Travel",
            "subcategory":"Travel Agent",
            "type":"Entertainment"
        }
    ],
    "sg:phone":"+1 418 538 3533",
    "sg:postcode":"G0G 1P0",
    "sg:province":"QC",
    "sg:tags":[
        "agency",
        "steamship"
    ],
    "wof:name":"Relais Nordik Quai DE Havre",
    "wof:placetype":"venue"
},
  "geometry": {"coordinates":[-63.6045341492,50.2447547913],"type":"Point"}
}