{
  "type": "Feature",
  "properties": {
    "addr:full":"1400 Coldrey Ave Ottawa ON K1Z 7P9",
    "addr:housenumber":"1400",
    "addr:postcode":"k1z 7p9",
    "addr:street":"Coldrey Ave",
    "iso:country":"CA",
    "sg:address":"1400 Coldrey Ave",
    "sg:city":"Ottawa",
    "sg:classifiers":[
        {
            "category":"Restaurant",
            "type":"Food & Drink"
        }
    ],
    "sg:phone":"+1 613 729 1782",
    "sg:postcode":"K1Z 7P9",
    "sg:province":"ON",
    "sg:tags":[
        "caterer"
    ],
    "wof:name":"Yudi Chein Kosher Catering",
    "wof:placetype":"venue"
},
  "geometry": {"coordinates":[-75.73904400000001,45.381302],"type":"Point"}
}