{
  "type": "Feature",
  "properties": {
    "addr:full":"Ottawa ON K1N 5M3",
    "addr:postcode":"k1n 5m3",
    "iso:country":"CA",
    "sg:city":"Ottawa",
    "sg:classifiers":[
        {
            "category":"Organizations",
            "subcategory":"Professional Association",
            "type":"Services"
        }
    ],
    "sg:phone":"+1 613 241 3600",
    "sg:postcode":"K1N 5M3",
    "sg:province":"ON",
    "wof:name":"Royal Architectural Institute",
    "wof:placetype":"venue"
},
  "geometry": {"coordinates":[-75.694458,45.429493],"type":"Point"}
}