{
  "type": "Feature",
  "properties": {
    "addr:full":"307 Cochrane St Port Perry ON L9L 1M4",
    "addr:housenumber":"307",
    "addr:postcode":"l9l 1m4",
    "addr:street":"Cochrane St",
    "iso:country":"CA",
    "sg:address":"307 Cochrane St",
    "sg:city":"Port Perry",
    "sg:classifiers":[
        {
            "category":"Freight",
            "type":"Transportation"
        }
    ],
    "sg:phone":"+1 905 985 1244",
    "sg:postcode":"L9L 1M4",
    "sg:province":"ON",
    "sg:tags":[
        "trucking"
    ],
    "wof:name":"Durham East Transportation",
    "wof:placetype":"venue"
},
  "geometry": {"coordinates":[-78.95153000000001,44.106987],"type":"Point"}
}