{
  "type": "Feature",
  "properties": {
    "iso:country":"CA",
    "sg:address":"47 Scott St W # 3A",
    "sg:city":"St Catharines",
    "sg:classifiers":[
        {
            "category":"Building & Trades",
            "subcategory":"Construction",
            "type":"Services"
        }
    ],
    "sg:phone":"+1 905 685 0688",
    "sg:postcode":"L2R 1E1",
    "sg:province":"ON",
    "sg:tags":[
        "contractor"
    ],
    "wof:name":"Park Lane Home Builders",
    "wof:placetype":"venue"
},
  "geometry": {"coordinates":[-79.262909,43.176945],"type":"Point"}
}