{
  "type": "Feature",
  "properties": {
    "addr:full":"Sherbrooke QC J1G 1B1",
    "addr:postcode":"j1g 1b1",
    "iso:country":"CA",
    "sg:city":"Sherbrooke",
    "sg:classifiers":[
        {
            "category":"Social Services",
            "type":"Services"
        }
    ],
    "sg:phone":"+1 819 566 1453",
    "sg:postcode":"J1G 1B1",
    "sg:province":"QC",
    "sg:tags":[
        "organization",
        "welfare"
    ],
    "wof:name":"Corporation D'Approvisionnemen",
    "wof:placetype":"venue"
},
  "geometry": {"coordinates":[-71.882019,45.406738],"type":"Point"}
}