{
  "type": "Feature",
  "properties": {
    "addr:full":"2767 Island Hwy W Qualicum Beach BC V9K 2C4",
    "addr:housenumber":"2767",
    "addr:postcode":"v9k 2c4",
    "addr:street":"Island Hwy W",
    "iso:country":"CA",
    "sg:address":"2767 Island Hwy W",
    "sg:city":"Qualicum Beach",
    "sg:classifiers":[
        {
            "category":"Travel",
            "subcategory":"Hotels & Motels",
            "type":"Entertainment"
        }
    ],
    "sg:phone":"+1 250 752 6974",
    "sg:postcode":"V9K 2C4",
    "sg:province":"BC",
    "wof:name":"Sand Pebbles Inn",
    "wof:placetype":"venue"
},
  "geometry": {"coordinates":[-124.444061,49.355202],"type":"Point"}
}