{
  "type": "Feature",
  "properties": {
    "addr:full":"27 Elm St Toronto ON M5G 1H1",
    "addr:housenumber":"27",
    "addr:postcode":"m5g 1h1",
    "addr:street":"Elm St",
    "iso:country":"CA",
    "sg:address":"27 Elm St",
    "sg:city":"Toronto",
    "sg:classifiers":[
        {
            "category":"Retail",
            "subcategory":"Laundry & Dry Cleaning",
            "type":"Services"
        }
    ],
    "sg:phone":"+1 416 593 4090",
    "sg:postcode":"M5G 1H1",
    "sg:province":"ON",
    "sg:tags":[
        "cleaners"
    ],
    "wof:name":"Main Garment Care",
    "wof:placetype":"venue"
},
  "geometry": {"coordinates":[-79.382965,43.657448],"type":"Point"}
}