{
  "type": "Feature",
  "properties": {
    "addr:full":"12160 27E Av Montreal QC H1E 1Z5",
    "addr:housenumber":"12160",
    "addr:postcode":"h1e 1z5",
    "addr:street":"27E Av",
    "iso:country":"CA",
    "sg:address":"12160 27E Av",
    "sg:city":"Montreal",
    "sg:classifiers":[
        {
            "category":"Education",
            "subcategory":"School",
            "type":"Public Place"
        }
    ],
    "sg:phone":"+1 514 881 7190",
    "sg:postcode":"H1E 1Z5",
    "sg:province":"QC",
    "wof:name":"Denise-Pelletier Ecole",
    "wof:placetype":"venue"
},
  "geometry": {"coordinates":[-73.5894165039,45.6375923157],"type":"Point"}
}