{
  "type": "Feature",
  "properties": {
    "addr:full":"82 Grande Allee O Quebec QC G1R 2G6",
    "addr:housenumber":"82",
    "addr:postcode":"g1r 2g6",
    "addr:street":"Grande Allee O",
    "iso:country":"CA",
    "sg:address":"82 Grande Allee O",
    "sg:city":"Quebec",
    "sg:classifiers":[
        {
            "category":"Museum",
            "type":"Entertainment"
        }
    ],
    "sg:phone":"+1 418 647 4347",
    "sg:postcode":"G1R 2G6",
    "sg:province":"QC",
    "wof:name":"Maison Henry-Stuart",
    "wof:placetype":"venue"
},
  "geometry": {"coordinates":[-71.2234802246,46.8023986816],"type":"Point"}
}