{
  "type": "Feature",
  "properties": {
    "addr:full":"Saint-Nazaire-D'Acton QC J0H 1V0",
    "addr:postcode":"j0h 1v0",
    "iso:country":"CA",
    "sg:city":"Saint-Nazaire-D'Acton",
    "sg:classifiers":[
        {
            "category":"Autos & Motor Vehicles",
            "subcategory":"Fuel & Gas Station",
            "type":"Retail Goods"
        }
    ],
    "sg:phone":"+1 819 392 2894",
    "sg:postcode":"J0H 1V0",
    "sg:province":"QC",
    "sg:tags":[
        "oil"
    ],
    "wof:name":"9064-5680 Quebec Inc",
    "wof:placetype":"venue"
},
  "geometry": {"coordinates":[-72.6890792847,45.6489753723],"type":"Point"}
}