{
  "type": "Feature",
  "properties": {
    "addr:full":"911 Maginot St Winnipeg MB R2J 3Y2",
    "addr:housenumber":"911",
    "addr:postcode":"r2j 3y2",
    "addr:street":"Maginot St",
    "iso:country":"CA",
    "sg:address":"911 Maginot St",
    "sg:city":"Winnipeg",
    "sg:classifiers":[
        {
            "category":"Building & Trades",
            "subcategory":"Plumbing",
            "type":"Services"
        }
    ],
    "sg:phone":"+1 204 231 5330",
    "sg:postcode":"R2J 3Y2",
    "sg:province":"MB",
    "sg:tags":[
        "sheet",
        "work",
        "metal",
        "contractor"
    ],
    "wof:name":"Laurin Sheet Metal Ltd",
    "wof:placetype":"venue"
},
  "geometry": {"coordinates":[-97.08015399999999,49.873608],"type":"Point"}
}