{
  "type": "Feature",
  "properties": {
    "addr:full":"3927 Grant St Burnaby BC V5C 3N4",
    "addr:housenumber":"3927",
    "addr:postcode":"v5c 3n4",
    "addr:street":"Grant St",
    "iso:country":"CA",
    "sg:address":"3927 Grant St",
    "sg:city":"Burnaby",
    "sg:classifiers":[
        {
            "category":"Building & Trades",
            "subcategory":"Construction",
            "type":"Services"
        }
    ],
    "sg:phone":"+1 604 293 1551",
    "sg:postcode":"V5C 3N4",
    "sg:province":"BC",
    "sg:tags":[
        "motion",
        "picture",
        "set",
        "design"
    ],
    "wof:name":"Avatar Prop & Design Inc",
    "wof:placetype":"venue"
},
  "geometry": {"coordinates":[-123.017974853,49.2713851929],"type":"Point"}
}