{
  "type": "Feature",
  "properties": {
    "iso:country":"CA",
    "sg:address":"217 Pembroke St E",
    "sg:city":"Pembroke",
    "sg:classifiers":[
        {
            "category":"Professional",
            "subcategory":"Accounting & Tax Preparation",
            "type":"Services"
        }
    ],
    "sg:phone":"+1 613 735 3981",
    "sg:postcode":"K8A 3J8",
    "sg:province":"ON",
    "sg:tags":[
        "accountant"
    ],
    "wof:name":"Rosien, D W CA",
    "wof:placetype":"venue"
},
  "geometry": {"coordinates":[-77.109085083,45.8270111084],"type":"Point"}
}