{
  "type": "Feature",
  "properties": {
    "addr:full":"608 86 Ave SW Calgary AB T2V 0V9",
    "addr:postcode":"t2v 0v9",
    "addr:street":"608 86 Ave Sw",
    "iso:country":"CA",
    "sg:address":"608 86 Ave SW",
    "sg:city":"Calgary",
    "sg:classifiers":[
        {
            "category":"Organizations",
            "subcategory":"Religious Organization",
            "type":"Services"
        }
    ],
    "sg:phone":"+1 403 255 6110",
    "sg:postcode":"T2V 0V9",
    "sg:province":"AB",
    "sg:tags":[
        "church"
    ],
    "wof:name":"Hope For Life Christian",
    "wof:placetype":"venue"
},
  "geometry": {"coordinates":[-114.077934,50.976067],"type":"Point"}
}