{
  "type": "Feature",
  "properties": {
    "addr:full":"133 the West Mall # 1 Etobicoke ON M9C 1C2",
    "addr:housenumber":"133",
    "addr:postcode":"m9c 1c2",
    "addr:street":"The West Mall # 1",
    "iso:country":"CA",
    "sg:address":"133 the West Mall # 1",
    "sg:city":"Etobicoke",
    "sg:classifiers":[
        {
            "category":"Food & Beverages",
            "subcategory":"Bakery",
            "type":"Retail Goods"
        }
    ],
    "sg:phone":"+1 416 622 4899",
    "sg:postcode":"M9C 1C2",
    "sg:province":"ON",
    "sg:tags":[
        "doughnut"
    ],
    "wof:name":"Tim Hortons",
    "wof:placetype":"venue"
},
  "geometry": {"coordinates":[-79.562363,43.619556],"type":"Point"}
}