{
  "type": "Feature",
  "properties": {
    "iso:country":"CA",
    "sg:address":"5917 1A St SW",
    "sg:city":"Calgary",
    "sg:classifiers":[
        {
            "category":"Real Estate",
            "subcategory":"Architect",
            "type":"Services"
        }
    ],
    "sg:phone":"+1 403 253 2853",
    "sg:postcode":"T2H 0G4",
    "sg:province":"AB",
    "wof:name":"Rick Balbi Architect Ltd",
    "wof:placetype":"venue"
},
  "geometry": {"coordinates":[-114.067818,51.001049],"type":"Point"}
}