{
  "type": "Feature",
  "properties": {
    "iso:country":"CA",
    "sg:address":"11230 107 Ave NW",
    "sg:city":"Edmonton",
    "sg:classifiers":[
        {
            "category":"Food & Beverages",
            "subcategory":"Groceries & Convenience Stores",
            "type":"Retail Goods"
        }
    ],
    "sg:phone":"+1 780 426 2652",
    "sg:postcode":"T5H 0Y1",
    "sg:province":"AB",
    "wof:name":"Central Park Shell",
    "wof:placetype":"venue"
},
  "geometry": {"coordinates":[-113.51457977299999,53.5516357422],"type":"Point"}
}