{
  "type": "Feature",
  "properties": {
    "iso:country":"CA",
    "sg:city":"Port Coquitlam",
    "sg:classifiers":[
        {
            "category":"Wholesale",
            "subcategory":"Durable Goods & Equipment",
            "type":"Manufacturing & Wholesale Goods"
        }
    ],
    "sg:phone":"+1 604 944 4035",
    "sg:postcode":"V3C 6G5",
    "sg:province":"BC",
    "sg:tags":[
        "environmental",
        "ecological",
        "prod"
    ],
    "wof:name":"Sandhack Equipment Ltd",
    "wof:placetype":"venue"
},
  "geometry": {"coordinates":[-122.756218,49.248741],"type":"Point"}
}