{
  "type": "Feature",
  "properties": {
    "addr:full":"132 Corstate Ave Concord ON L4K 4X2",
    "addr:housenumber":"132",
    "addr:postcode":"l4k 4x2",
    "addr:street":"Corstate Ave",
    "iso:country":"CA",
    "sg:address":"132 Corstate Ave",
    "sg:city":"Concord",
    "sg:classifiers":[
        {
            "category":"Building & Trades",
            "subcategory":"Construction",
            "type":"Services"
        }
    ],
    "sg:phone":"+1 905 760 9799",
    "sg:postcode":"L4K 4X2",
    "sg:province":"ON",
    "sg:tags":[
        "excavating",
        "contractor"
    ],
    "wof:name":"Anpro Excavating & Grading Ltd",
    "wof:placetype":"venue"
},
  "geometry": {"coordinates":[-79.53447723390001,43.8180618286],"type":"Point"}
}