{
  "type": "Feature",
  "properties": {
    "addr:full":"1140 Central Park Dr Brampton ON L6S 2C9",
    "addr:housenumber":"1140",
    "addr:postcode":"l6s 2c9",
    "addr:street":"Central Park Dr",
    "iso:country":"CA",
    "sg:address":"1140 Central Park Dr",
    "sg:city":"Brampton",
    "sg:classifiers":[
        {
            "category":"Education",
            "subcategory":"School",
            "type":"Public Place"
        }
    ],
    "sg:phone":"+1 905 791 2332",
    "sg:postcode":"L6S 2C9",
    "sg:province":"ON",
    "wof:name":"Greenbriar Sr Public School",
    "wof:placetype":"venue"
},
  "geometry": {"coordinates":[-79.71489699999999,43.736439],"type":"Point"}
}