{
  "type": "Feature",
  "properties": {
    "addr:full":"Calgary AB T2H 0T2",
    "addr:postcode":"t2h 0t2",
    "iso:country":"CA",
    "sg:city":"Calgary",
    "sg:classifiers":[
        {
            "category":"Manufacturing",
            "subcategory":"Tools & Machinery",
            "type":"Manufacturing & Wholesale Goods"
        }
    ],
    "sg:phone":"+1 403 252 9715",
    "sg:postcode":"T2H 0T2",
    "sg:province":"AB",
    "sg:tags":[
        "die",
        "maker"
    ],
    "wof:name":"Plastech",
    "wof:placetype":"venue"
},
  "geometry": {"coordinates":[-114.056183,50.991909],"type":"Point"}
}