{
  "type": "Feature",
  "properties": {
    "iso:country":"CA",
    "sg:address":"1416 4E Av E",
    "sg:city":"LA Pocatiere",
    "sg:classifiers":[
        {
            "category":"Organizations",
            "subcategory":"Religious Organization",
            "type":"Services"
        }
    ],
    "sg:phone":"+1 418 856 3802",
    "sg:postcode":"G0R 1Z0",
    "sg:province":"QC",
    "wof:name":"Societe Catholique-Missionnrs",
    "wof:placetype":"venue"
},
  "geometry": {"coordinates":[-70.03224945069999,47.36901474],"type":"Point"}
}