{
  "type": "Feature",
  "properties": {
    "addr:full":"PO Box 988 Garibaldi Highlands BC V0N 1T0",
    "addr:housenumber":"po",
    "addr:postcode":"v0n 1t0",
    "addr:street":"Box 988 Garibaldi",
    "iso:country":"CA",
    "sg:address":"PO Box 988",
    "sg:city":"Garibaldi Highlands",
    "sg:classifiers":[
        {
            "category":"Building & Trades",
            "subcategory":"Construction",
            "type":"Services"
        }
    ],
    "sg:phone":"+1 604 898 9575",
    "sg:postcode":"V0N 1T0",
    "sg:province":"BC",
    "sg:tags":[
        "excavating",
        "contractor"
    ],
    "wof:name":"Robcat Services Ltd",
    "wof:placetype":"venue"
},
  "geometry": {"coordinates":[-123.510520935,48.4851150513],"type":"Point"}
}