{
  "type": "Feature",
  "properties": {
    "iso:country":"CA",
    "sg:address":"2437 Central Ave",
    "sg:city":"Windsor",
    "sg:classifiers":[
        {
            "category":"Health Services",
            "subcategory":"Chiropractor",
            "type":"Services"
        }
    ],
    "sg:phone":"+1 519 945 8433",
    "sg:postcode":"N8W 4J4",
    "sg:province":"ON",
    "wof:name":"Central Chiropractic Prfrmnc",
    "wof:placetype":"venue"
},
  "geometry": {"coordinates":[-82.978012085,42.3010749817],"type":"Point"}
}