{
  "type": "Feature",
  "properties": {
    "iso:country":"CA",
    "sg:address":"31 Porterfield Cres",
    "sg:city":"Thornhill",
    "sg:classifiers":[
        {
            "category":"Real Estate",
            "subcategory":"Real Estate Operator",
            "type":"Services"
        }
    ],
    "sg:phone":"+1 905 731 7279",
    "sg:postcode":"L3T 5C3",
    "sg:province":"ON",
    "sg:tags":[
        "condominium"
    ],
    "wof:name":"York Condominium Corp 279",
    "wof:placetype":"venue"
},
  "geometry": {"coordinates":[-79.398537,43.816952],"type":"Point"}
}