{
  "type": "Feature",
  "properties": {
    "addr:full":"564 Gregory Dr E Chatham ON N7M 5J7",
    "addr:housenumber":"564",
    "addr:postcode":"n7m 5j7",
    "addr:street":"Gregory Dr E",
    "iso:country":"CA",
    "sg:address":"564 Gregory Dr E",
    "sg:city":"Chatham",
    "sg:classifiers":[
        {
            "category":"Building & Trades",
            "subcategory":"Electrical",
            "type":"Services"
        }
    ],
    "sg:phone":"+1 519 352 1097",
    "sg:postcode":"N7M 5J7",
    "sg:province":"ON",
    "sg:tags":[
        "electric",
        "contractor",
        "system",
        "heating"
    ],
    "wof:name":"Brad's Electric",
    "wof:placetype":"venue"
},
  "geometry": {"coordinates":[-82.191063,42.43808],"type":"Point"}
}