{
  "type": "Feature",
  "properties": {
    "addr:full":"3216 Danforth Ave Scarborough ON M1L 1C1",
    "addr:housenumber":"3216",
    "addr:postcode":"m1l 1c1",
    "addr:street":"Danforth Ave",
    "iso:country":"CA",
    "sg:address":"3216 Danforth Ave",
    "sg:city":"Scarborough",
    "sg:classifiers":[
        {
            "category":"Shopping",
            "subcategory":"Discount & Variety Stores",
            "type":"Retail Goods"
        }
    ],
    "sg:phone":"+1 416 690 3272",
    "sg:postcode":"M1L 1C1",
    "sg:province":"ON",
    "wof:name":"Elizabeth's Variety Store",
    "wof:placetype":"venue"
},
  "geometry": {"coordinates":[-79.282768,43.692581],"type":"Point"}
}