{
  "type": "Feature",
  "properties": {
    "iso:country":"CA",
    "sg:address":"509 8 Ave E",
    "sg:city":"Bow Island",
    "sg:classifiers":[
        {
            "category":"Manufacturing",
            "subcategory":"Food",
            "type":"Manufacturing & Wholesale Goods"
        }
    ],
    "sg:phone":"+1 403 545 2266",
    "sg:postcode":"T0K 0G0",
    "sg:province":"AB",
    "sg:tags":[
        "product",
        "manufacturer"
    ],
    "wof:name":"Classic Grains of Canada Inc",
    "wof:placetype":"venue"
},
  "geometry": {"coordinates":[-111.369613648,49.8663978577],"type":"Point"}
}