{
  "type": "Feature",
  "properties": {
    "iso:country":"CA",
    "sg:address":"2 George St S",
    "sg:city":"Smiths Falls",
    "sg:classifiers":[
        {
            "category":"Organizations",
            "subcategory":"Religious Organization",
            "type":"Services"
        }
    ],
    "sg:phone":"+1 613 283 1261",
    "sg:postcode":"K7A 1X4",
    "sg:province":"ON",
    "sg:tags":[
        "church"
    ],
    "wof:name":"St Johns Anglican Church",
    "wof:placetype":"venue"
},
  "geometry": {"coordinates":[-76.0246505737,44.8992347717],"type":"Point"}
}