{
  "type": "Feature",
  "properties": {
    "addr:full":"85 Rte Principale Saint-Jean-DE-Matha QC J0K 2S0",
    "addr:housenumber":"85",
    "addr:postcode":"j0k 2s0",
    "addr:street":"Rte Principale",
    "iso:country":"CA",
    "sg:address":"85 Rte Principale",
    "sg:city":"Saint-Jean-DE-Matha",
    "sg:classifiers":[
        {
            "category":"Social Services",
            "type":"Services"
        }
    ],
    "sg:phone":"+1 450 886 0185",
    "sg:postcode":"J0K 2S0",
    "sg:province":"QC",
    "sg:tags":[
        "youth",
        "organization",
        "center"
    ],
    "wof:name":"Maison Des Jeunes",
    "wof:placetype":"venue"
},
  "geometry": {"coordinates":[-73.532349,46.228699],"type":"Point"}
}