{
  "type": "Feature",
  "properties": {
    "addr:full":"2750 Ch Bois-Clair Saint-Antoine-DE-Tilly QC G0S 2C0",
    "addr:postcode":"2750;g0s 2c0",
    "addr:street":"Ch Bois-Clair",
    "iso:country":"CA",
    "sg:address":"2750 Ch Bois-Clair",
    "sg:city":"Saint-Antoine-DE-Tilly",
    "sg:classifiers":[
        {
            "category":"Retail",
            "subcategory":"Repair Shop",
            "type":"Services"
        }
    ],
    "sg:phone":"+1 418 886 2812",
    "sg:postcode":"G0S 2C0",
    "sg:province":"QC",
    "sg:tags":[
        "refinishing",
        "furniture"
    ],
    "wof:name":"Atelier Clement Berube",
    "wof:placetype":"venue"
},
  "geometry": {"coordinates":[-71.4858551025,46.6688423157],"type":"Point"}
}