{
  "type": "Feature",
  "properties": {
    "addr:full":"645 3 St SE Medicine Hat AB T1A 0H4",
    "addr:housenumber":"645 3",
    "addr:postcode":"t1a 0h4",
    "addr:street":"St Se",
    "iso:country":"CA",
    "sg:address":"645 3 St SE",
    "sg:city":"Medicine Hat",
    "sg:classifiers":[
        {
            "category":"Shopping",
            "subcategory":"Used Merchandise",
            "type":"Retail Goods"
        }
    ],
    "sg:phone":"+1 403 527 8370",
    "sg:postcode":"T1A 0H4",
    "sg:province":"AB",
    "sg:tags":[
        "second",
        "pawnbroker",
        "store",
        "hand"
    ],
    "wof:name":"King of Trade",
    "wof:placetype":"venue"
},
  "geometry": {"coordinates":[-110.67459100000001,50.040016],"type":"Point"}
}