{
  "type": "Feature",
  "properties": {
    "addr:full":"63 Briar Rd Barrie ON L4N 3M5",
    "addr:housenumber":"63",
    "addr:postcode":"l4n 3m5",
    "addr:street":"Briar Rd",
    "iso:country":"CA",
    "sg:address":"63 Briar Rd",
    "sg:city":"Barrie",
    "sg:classifiers":[
        {
            "category":"Professional",
            "subcategory":"Accounting & Tax Preparation",
            "type":"Services"
        }
    ],
    "sg:phone":"+1 705 739 7995",
    "sg:postcode":"L4N 3M5",
    "sg:province":"ON",
    "sg:tags":[
        "bookkeeping",
        "general"
    ],
    "wof:name":"Caldwell Accounting Svc",
    "wof:placetype":"venue"
},
  "geometry": {"coordinates":[-79.674576,44.367268],"type":"Point"}
}