{
  "type": "Feature",
  "properties": {
    "addr:full":"Hwy 37 Good Hope Lake BC V0C 2Z0",
    "addr:postcode":"bc v0c 2z0",
    "addr:street":"Hwy 37",
    "iso:country":"CA",
    "sg:address":"Hwy 37",
    "sg:city":"Good Hope Lake",
    "sg:classifiers":[
        {
            "category":"Autos & Motor Vehicles",
            "subcategory":"Fuel & Gas Station",
            "type":"Retail Goods"
        }
    ],
    "sg:phone":"+1 250 239 3500",
    "sg:postcode":"V0C 2Z0",
    "sg:province":"BC",
    "sg:tags":[
        "oil"
    ],
    "wof:name":"Kididza Services",
    "wof:placetype":"venue"
},
  "geometry": {"coordinates":[-129.293701,59.292423],"type":"Point"}
}