{
  "type": "Feature",
  "properties": {
    "addr:full":"429 Alexander St Vancouver BC V6A 1C6",
    "addr:housenumber":"429",
    "addr:postcode":"v6a 1c6",
    "addr:street":"Alexander St",
    "iso:country":"CA",
    "sg:address":"429 Alexander St",
    "sg:city":"Vancouver",
    "sg:classifiers":[
        {
            "category":"Social Services",
            "type":"Services"
        }
    ],
    "sg:phone":"+1 604 255 0340",
    "sg:postcode":"V6A 1C6",
    "sg:province":"BC",
    "sg:tags":[
        "organization",
        "welfare"
    ],
    "wof:name":"Lookout Emergency Aid Society",
    "wof:placetype":"venue"
},
  "geometry": {"coordinates":[-123.09453600000001,49.284176],"type":"Point"}
}