{
  "type": "Feature",
  "properties": {
    "addr:full":"1100 Harvie Heights Rd Harvie Heights AB T1W 2W2",
    "addr:housenumber":"1100",
    "addr:postcode":"t1w 2w2",
    "addr:street":"Harvie Heights Rd",
    "iso:country":"CA",
    "sg:address":"1100 Harvie Heights Rd",
    "sg:city":"Harvie Heights",
    "sg:classifiers":[
        {
            "category":"Travel",
            "subcategory":"Hotels & Motels",
            "type":"Entertainment"
        }
    ],
    "sg:phone":"+1 403 678 5387",
    "sg:postcode":"T1W 2W2",
    "sg:province":"AB",
    "wof:name":"Rundle Ridge Chalets Ltd",
    "wof:placetype":"venue"
},
  "geometry": {"coordinates":[-115.383811951,51.1229438782],"type":"Point"}
}