{
  "type": "Feature",
  "properties": {
    "addr:full":"1180 Av DE Bourlamaque Quebec QC G1R 2P8",
    "addr:housenumber":"1180",
    "addr:postcode":"g1r 2p8",
    "addr:street":"Av De Bourlamaque",
    "iso:country":"CA",
    "sg:address":"1180 Av DE Bourlamaque",
    "sg:city":"Quebec",
    "sg:classifiers":[
        {
            "category":"Food & Beverages",
            "subcategory":"Groceries & Convenience Stores",
            "type":"Retail Goods"
        }
    ],
    "sg:phone":"+1 418 525 4776",
    "sg:postcode":"G1R 2P8",
    "sg:province":"QC",
    "wof:name":"Tabagie St-Dominique",
    "wof:placetype":"venue"
},
  "geometry": {"coordinates":[-71.225998,46.801094],"type":"Point"}
}