{
  "type": "Feature",
  "properties": {
    "addr:full":"43 Main Springhill NS B0M 1X0",
    "addr:housenumber":"43",
    "addr:postcode":"b0m 1x0",
    "addr:street":"Main",
    "iso:country":"CA",
    "sg:address":"43 Main",
    "sg:city":"Springhill",
    "sg:classifiers":[
        {
            "category":"Government",
            "subcategory":"Police Station",
            "type":"Public Place"
        }
    ],
    "sg:phone":"+1 902 597 3779",
    "sg:postcode":"B0M 1X0",
    "sg:province":"NS",
    "sg:tags":[
        "department"
    ],
    "wof:name":"Springhill Police Office",
    "wof:placetype":"venue"
},
  "geometry": {"coordinates":[-64.055626,45.650944],"type":"Point"}
}