{
  "type": "Feature",
  "properties": {
    "iso:country":"CA",
    "sg:address":"17 King St W",
    "sg:city":"Oshawa",
    "sg:classifiers":[
        {
            "category":"Shopping",
            "subcategory":"News",
            "type":"Retail Goods"
        }
    ],
    "sg:phone":"+1 905 728 8964",
    "sg:postcode":"L1H 1A1",
    "sg:province":"ON",
    "sg:tags":[
        "magazine"
    ],
    "wof:name":"Mike's Place",
    "wof:placetype":"venue"
},
  "geometry": {"coordinates":[-78.864281,43.897297],"type":"Point"}
}