{
  "type": "Feature",
  "properties": {
    "addr:full":"206 Sims Ave Weyburn SK S4H 2H6",
    "addr:housenumber":"206",
    "addr:postcode":"s4h 2h6",
    "addr:street":"Sims Ave",
    "iso:country":"CA",
    "sg:address":"206 Sims Ave",
    "sg:city":"Weyburn",
    "sg:classifiers":[
        {
            "category":"Autos & Motor Vehicles",
            "subcategory":"Automobile Sales",
            "type":"Retail Goods"
        }
    ],
    "sg:phone":"+1 306 842 2645",
    "sg:postcode":"S4H 2H6",
    "sg:province":"SK",
    "sg:tags":[
        "car",
        "dealer"
    ],
    "wof:name":"Great Plains Ford Ltd",
    "wof:placetype":"venue"
},
  "geometry": {"coordinates":[-103.864318848,49.6597862244],"type":"Point"}
}