{
  "type": "Feature",
  "properties": {
    "iso:country":"CA",
    "sg:address":"1 Rue Monseigneur-Blanche",
    "sg:city":"Sept-Iles",
    "sg:classifiers":[
        {
            "category":"Government",
            "subcategory":"Office",
            "type":"Public Place"
        }
    ],
    "sg:phone":"+1 418 968 1231",
    "sg:postcode":"G4R 5P3",
    "sg:province":"QC",
    "sg:tags":[
        "trucking"
    ],
    "wof:name":"Port DE Sept-Iles",
    "wof:placetype":"venue"
},
  "geometry": {"coordinates":[-66.3816452026,50.1992263794],"type":"Point"}
}