{
  "type": "Feature",
  "properties": {
    "addr:full":"56 Sparks Street Suite 512 Ottawa K1P5A9",
    "addr:housenumber":"56",
    "addr:postcode":"k1p5a9",
    "addr:street":"Sparks Street Suite 512",
    "iso:country":"CA",
    "sg:address":"56 Sparks Street Suite 512",
    "sg:city":"Ottawa",
    "sg:classifiers":[
        {
            "category":"Professional",
            "subcategory":"Computer Services",
            "type":"Services"
        }
    ],
    "sg:postcode":"K1P5A9",
    "sg:tags":[
        "hosted-pbx",
        "pbx",
        "voip",
        "unlimited-calling",
        "business-phone",
        "business-pbx",
        "hosted-conferencing",
        "online-phone",
        "hosted-phone-system",
        "pbx-serverm",
        "skype",
        "onsip",
        "canada",
        "bell-canada",
        "rogers"
    ],
    "sg:website":"http://www.OctopusIP.com/hosted-pbx-server",
    "wof:name":"Octopus IP Hosted PBX",
    "wof:placetype":"venue"
},
  "geometry": {"coordinates":[-75.6967085,45.4231202],"type":"Point"}
}