{
  "type": "Feature",
  "properties": {
    "iso:country":"CA",
    "sg:city":"Montreal",
    "sg:classifiers":[
        {
            "category":"Wholesale",
            "subcategory":"Drugs",
            "type":"Manufacturing & Wholesale Goods"
        }
    ],
    "sg:phone":"+1 514 381 8551",
    "sg:postcode":"H2B 3A8",
    "sg:province":"QC",
    "sg:tags":[
        "cosmetic"
    ],
    "wof:name":"Babor Canada Inc",
    "wof:placetype":"venue"
},
  "geometry": {"coordinates":[-73.64727,45.565884],"type":"Point"}
}