{
  "type": "Feature",
  "properties": {
    "addr:full":"Montreal QC H2B 3A8",
    "addr:postcode":"h2b 3a8",
    "iso:country":"CA",
    "sg:city":"Montreal",
    "sg:classifiers":[
        {
            "category":"Wholesale",
            "subcategory":"Drugs",
            "type":"Manufacturing & Wholesale Goods"
        }
    ],
    "sg:phone":"+1 514 381 8551",
    "sg:postcode":"H2B 3A8",
    "sg:province":"QC",
    "sg:tags":[
        "cosmetic"
    ],
    "wof:name":"Babor Canada Inc",
    "wof:placetype":"venue"
},
  "geometry": {"coordinates":[-73.64727000000001,45.565884],"type":"Point"}
}