{
  "type": "Feature",
  "properties": {
    "iso:country":"CA",
    "sg:address":"10204 112 St NW",
    "sg:city":"Edmonton",
    "sg:classifiers":[
        {
            "category":"Health Services",
            "subcategory":"Chiropractor",
            "type":"Services"
        }
    ],
    "sg:phone":"+1 780 425 1133",
    "sg:postcode":"T5K 1M4",
    "sg:province":"AB",
    "wof:name":"Liberty Chiropractic",
    "wof:placetype":"venue"
},
  "geometry": {"coordinates":[-113.514160156,53.5432243347],"type":"Point"}
}