{
  "type": "Feature",
  "properties": {
    "addr:full":"7615 Boul Henri-Bourassa E Montreal QC H1E 1N9",
    "addr:housenumber":"7615",
    "addr:postcode":"h1e 1n9",
    "addr:street":"Boul Henri-Bourassa E",
    "iso:country":"CA",
    "sg:address":"7615 Boul Henri-Bourassa E",
    "sg:city":"Montreal",
    "sg:classifiers":[
        {
            "category":"Manufacturing",
            "subcategory":"Building Materials",
            "type":"Manufacturing & Wholesale Goods"
        }
    ],
    "sg:phone":"+1 514 648 7703",
    "sg:postcode":"H1E 1N9",
    "sg:province":"QC",
    "sg:tags":[
        "concrete",
        "product"
    ],
    "wof:name":"Centre Du Pave & Jardin Rdp",
    "wof:placetype":"venue"
},
  "geometry": {"coordinates":[-73.58749389650001,45.6215667725],"type":"Point"}
}