{
  "type": "Feature",
  "properties": {
    "iso:country":"CA",
    "sg:address":"25 Industry St",
    "sg:city":"Aurora",
    "sg:classifiers":[
        {
            "category":"Retail",
            "subcategory":"Auto Repair",
            "type":"Services"
        }
    ],
    "sg:phone":"+1 905 726 3736",
    "sg:postcode":"L4G 1X6",
    "sg:province":"ON",
    "sg:tags":[
        "transmission"
    ],
    "wof:name":"Aurora Transmission",
    "wof:placetype":"venue"
},
  "geometry": {"coordinates":[-79.4557647705,43.999370575],"type":"Point"}
}