{
  "type": "Feature",
  "properties": {
    "addr:full":"538 College St Toronto ON M6G 1A6",
    "addr:housenumber":"538",
    "addr:postcode":"m6g 1a6",
    "addr:street":"College St",
    "iso:country":"CA",
    "sg:address":"538 College St",
    "sg:city":"Toronto",
    "sg:classifiers":[
        {
            "category":"Personal",
            "subcategory":"Barber",
            "type":"Services"
        }
    ],
    "sg:phone":"+1 416 925 5677",
    "sg:postcode":"M6G 1A6",
    "sg:province":"ON",
    "wof:name":"Enzo's Barber Shop",
    "wof:placetype":"venue"
},
  "geometry": {"coordinates":[-79.411239624,43.6558952332],"type":"Point"}
}