{
  "type": "Feature",
  "properties": {
    "iso:country":"CA",
    "sg:address":"8646 10E Av",
    "sg:city":"Montreal",
    "sg:classifiers":[
        {
            "category":"Retail",
            "subcategory":"Auto Repair",
            "type":"Services"
        }
    ],
    "sg:phone":"+1 514 270 5985",
    "sg:postcode":"H1Z 3B8",
    "sg:province":"QC",
    "sg:tags":[
        "body",
        "automobile",
        "wrecker",
        "painting"
    ],
    "wof:name":"Deneigements & Remorquage Smgr",
    "wof:placetype":"venue"
},
  "geometry": {"coordinates":[-73.62009429930001,45.5674247742],"type":"Point"}
}