{
  "type": "Feature",
  "properties": {
    "addr:full":"Edmonton AB T6E 6N2",
    "addr:postcode":"t6e 6n2",
    "iso:country":"CA",
    "sg:city":"Edmonton",
    "sg:classifiers":[
        {
            "category":"Manufacturing",
            "subcategory":"Printing",
            "type":"Manufacturing & Wholesale Goods"
        }
    ],
    "sg:phone":"+1 780 438 0695",
    "sg:postcode":"T6E 6N2",
    "sg:province":"AB",
    "sg:tags":[
        "printer"
    ],
    "wof:name":"Universal Printing Press",
    "wof:placetype":"venue"
},
  "geometry": {"coordinates":[-113.479645,53.474422],"type":"Point"}
}