{
  "type": "Feature",
  "properties": {
    "addr:full":"107 Rue Des Grenadiers Boischatel QC G0A 1H0",
    "addr:housenumber":"107",
    "addr:postcode":"g0a 1h0",
    "addr:street":"Rue Des Grenadiers",
    "iso:country":"CA",
    "sg:address":"107 Rue Des Grenadiers",
    "sg:city":"Boischatel",
    "sg:classifiers":[
        {
            "category":"Professional",
            "subcategory":"Detective & Security Services",
            "type":"Services"
        }
    ],
    "sg:phone":"+1 418 569 4141",
    "sg:postcode":"G0A 1H0",
    "sg:province":"QC",
    "sg:tags":[
        "burglary",
        "protective",
        "robbery"
    ],
    "wof:name":"Alarme Protection Quebec",
    "wof:placetype":"venue"
},
  "geometry": {"coordinates":[-71.137665,46.894257],"type":"Point"}
}