{
  "type": "Feature",
  "properties": {
    "iso:country":"CA",
    "sg:address":"7584 Vantage Pl",
    "sg:city":"Delta",
    "sg:classifiers":[
        {
            "category":"Manufacturing",
            "subcategory":"Metals",
            "type":"Manufacturing & Wholesale Goods"
        }
    ],
    "sg:phone":"+1 604 940 4960",
    "sg:postcode":"V4G 1A5",
    "sg:province":"BC",
    "sg:tags":[
        "plumbing",
        "fixture",
        "supply"
    ],
    "wof:name":"Venco Products Ltd",
    "wof:placetype":"venue"
},
  "geometry": {"coordinates":[-123.008148,49.140572],"type":"Point"}
}