{
  "type": "Feature",
  "properties": {
    "addr:full":"2 Herald Ave #306 Corner Brook NL A2H 4B5",
    "addr:housenumber":"2",
    "addr:postcode":"a2h 4b5",
    "addr:street":"Herald Ave # 306",
    "iso:country":"CA",
    "sg:address":"2 Herald Ave #306",
    "sg:city":"Corner Brook",
    "sg:classifiers":[
        {
            "category":"Real Estate",
            "subcategory":"Real Estate Agent",
            "type":"Services"
        }
    ],
    "sg:phone":"+1 709 634 9400",
    "sg:postcode":"A2H 4B5",
    "sg:province":"NL",
    "wof:name":"Re/Max Realty Professional Ltd",
    "wof:placetype":"venue"
},
  "geometry": {"coordinates":[-57.954945,48.951473],"type":"Point"}
}