{
  "type": "Feature",
  "properties": {
    "addr:full":"Langley BC V2Y 2E3",
    "addr:postcode":"v2y 2e3",
    "iso:country":"CA",
    "sg:city":"Langley",
    "sg:classifiers":[
        {
            "category":"Health Services",
            "subcategory":"Doctor",
            "type":"Services"
        }
    ],
    "sg:phone":"+1 604 514 8200",
    "sg:postcode":"V2Y 2E3",
    "sg:province":"BC",
    "sg:tags":[
        "dentist"
    ],
    "wof:name":"Findlay, Jim DDS",
    "wof:placetype":"venue"
},
  "geometry": {"coordinates":[-122.674789,49.11874],"type":"Point"}
}