{
  "type": "Feature",
  "properties": {
    "addr:full":"284 Queen St S Bolton ON L7E 4Z5",
    "addr:housenumber":"284",
    "addr:postcode":"l7e 4z5",
    "addr:street":"Queen St S",
    "iso:country":"CA",
    "sg:address":"284 Queen St S",
    "sg:city":"Bolton",
    "sg:classifiers":[
        {
            "category":"Professional",
            "subcategory":"Lawyer & Legal Services",
            "type":"Services"
        }
    ],
    "sg:phone":"+1 905 951 0504",
    "sg:postcode":"L7E 4Z5",
    "sg:province":"ON",
    "sg:tags":[
        "attorney"
    ],
    "wof:name":"Conway Jones, Marilyn",
    "wof:placetype":"venue"
},
  "geometry": {"coordinates":[-79.7305679321,43.8739204407],"type":"Point"}
}