{
  "type": "Feature",
  "properties": {
    "addr:full":"225 Macpherson Ave Toronto ON M4V 1A1",
    "addr:housenumber":"225",
    "addr:postcode":"m4v 1a1",
    "addr:street":"Macpherson Ave",
    "iso:country":"CA",
    "sg:address":"225 Macpherson Ave",
    "sg:city":"Toronto",
    "sg:classifiers":[
        {
            "category":"Building & Trades",
            "subcategory":"Electrical",
            "type":"Services"
        }
    ],
    "sg:phone":"+1 416 925 9545",
    "sg:postcode":"M4V 1A1",
    "sg:province":"ON",
    "sg:tags":[
        "electric",
        "contractor"
    ],
    "wof:name":"Weenen Electric",
    "wof:placetype":"venue"
},
  "geometry": {"coordinates":[-79.398239,43.677979],"type":"Point"}
}