{
  "type": "Feature",
  "properties": {
    "addr:full":"731 Shaw Ave Coquitlam BC V3K 2R7",
    "addr:housenumber":"731",
    "addr:postcode":"v3k 2r7",
    "addr:street":"Shaw Ave",
    "iso:country":"CA",
    "sg:address":"731 Shaw Ave",
    "sg:city":"Coquitlam",
    "sg:classifiers":[
        {
            "category":"Building & Trades",
            "subcategory":"Construction",
            "type":"Services"
        }
    ],
    "sg:phone":"+1 604 939 4267",
    "sg:postcode":"V3K 2R7",
    "sg:province":"BC",
    "sg:tags":[
        "repairing",
        "remodeling",
        "contractor"
    ],
    "wof:name":"Maddalozzo Construction",
    "wof:placetype":"venue"
},
  "geometry": {"coordinates":[-122.880882263,49.2445259094],"type":"Point"}
}