{
  "type": "Feature",
  "properties": {
    "addr:full":"9 Paisch Cres Red Lake ON P0V 2M0",
    "addr:housenumber":"9",
    "addr:postcode":"p0v 2m0",
    "addr:street":"Paisch Cres",
    "iso:country":"CA",
    "sg:address":"9 Paisch Cres",
    "sg:city":"Red Lake",
    "sg:classifiers":[
        {
            "category":"Building & Trades",
            "subcategory":"Construction",
            "type":"Services"
        }
    ],
    "sg:phone":"+1 807 727 2869",
    "sg:postcode":"P0V 2M0",
    "sg:province":"ON",
    "sg:tags":[
        "general",
        "contractor"
    ],
    "wof:name":"Hasage Crane Rentals",
    "wof:placetype":"venue"
},
  "geometry": {"coordinates":[-93.81298099999999,51.017574],"type":"Point"}
}