{
  "type": "Feature",
  "properties": {
    "addr:full":"149 Rowntree Dairy Rd Woodbridge ON L4L 6E1",
    "addr:housenumber":"149",
    "addr:postcode":"l4l 6e1",
    "addr:street":"Rowntree Dairy Rd",
    "iso:country":"CA",
    "sg:address":"149 Rowntree Dairy Rd",
    "sg:city":"Woodbridge",
    "sg:classifiers":[
        {
            "category":"Manufacturing",
            "subcategory":"Food",
            "type":"Manufacturing & Wholesale Goods"
        }
    ],
    "sg:phone":"+1 905 850 3302",
    "sg:postcode":"L4L 6E1",
    "sg:province":"ON",
    "sg:tags":[
        "dry",
        "product",
        "prod",
        "dairy"
    ],
    "wof:name":"Ice Cream Patio Ltd",
    "wof:placetype":"venue"
},
  "geometry": {"coordinates":[-79.5527877808,43.7847328186],"type":"Point"}
}