{
  "type": "Feature",
  "properties": {
    "addr:full":"Ottawa ON K1K 3B8",
    "addr:postcode":"k1k 3b8",
    "iso:country":"CA",
    "sg:city":"Ottawa",
    "sg:classifiers":[
        {
            "category":"Shopping",
            "subcategory":"Clothing, Apparel, & Fashions",
            "type":"Retail Goods"
        }
    ],
    "sg:phone":"+1 613 746 3452",
    "sg:postcode":"K1K 3B8",
    "sg:province":"ON",
    "sg:tags":[
        "furnishing"
    ],
    "wof:name":"Vernini Uomo Men's Clothes",
    "wof:placetype":"venue"
},
  "geometry": {"coordinates":[-75.63739,45.423843],"type":"Point"}
}