{
  "type": "Feature",
  "properties": {
    "addr:full":"2607 Eglinton Ave E Scarborough ON M1K 2S2",
    "addr:housenumber":"2607",
    "addr:postcode":"m1k 2s2",
    "addr:street":"Eglinton Ave E",
    "iso:country":"CA",
    "sg:address":"2607 Eglinton Ave E",
    "sg:city":"Scarborough",
    "sg:classifiers":[
        {
            "category":"Personal",
            "subcategory":"Beauty Salon",
            "type":"Services"
        }
    ],
    "sg:phone":"+1 416 264 7555",
    "sg:postcode":"M1K 2S2",
    "sg:province":"ON",
    "wof:name":"Miller Salon",
    "wof:placetype":"venue"
},
  "geometry": {"coordinates":[-79.252876,43.735561],"type":"Point"}
}