{
  "type": "Feature",
  "properties": {
    "addr:full":"15151 112 Ave Surrey BC V3R 6G8",
    "addr:housenumber":"15151",
    "addr:postcode":"v3r 6g8",
    "addr:street":"112 Ave",
    "iso:country":"CA",
    "sg:address":"15151 112 Ave",
    "sg:city":"Surrey",
    "sg:classifiers":[
        {
            "category":"Travel",
            "subcategory":"Campground",
            "type":"Entertainment"
        }
    ],
    "sg:phone":"+1 604 583 5585",
    "sg:postcode":"V3R 6G8",
    "sg:province":"BC",
    "wof:name":"Dogwood Campground & Rv Park",
    "wof:placetype":"venue"
},
  "geometry": {"coordinates":[-122.800758,49.206081],"type":"Point"}
}