{
  "type": "Feature",
  "properties": {
    "addr:full":"Edmonton AB T6E 6A8",
    "addr:postcode":"t6e 6a8",
    "iso:country":"CA",
    "sg:city":"Edmonton",
    "sg:classifiers":[
        {
            "category":"Insurance",
            "subcategory":"Insurance Agent",
            "type":"Services"
        }
    ],
    "sg:phone":"+1 780 469 5700",
    "sg:postcode":"T6E 6A8",
    "sg:province":"AB",
    "wof:name":"Wawanesa Life Insurance CO",
    "wof:placetype":"venue"
},
  "geometry": {"coordinates":[-113.45629119900001,53.4878921509],"type":"Point"}
}