{
  "type": "Feature",
  "properties": {
    "addr:full":"201 Avenue Rd Cambridge ON N1R 7Z1",
    "addr:housenumber":"201",
    "addr:postcode":"n1r 7z1",
    "addr:street":"Avenue Rd",
    "iso:country":"CA",
    "sg:address":"201 Avenue Rd",
    "sg:city":"Cambridge",
    "sg:classifiers":[
        {
            "category":"Retail",
            "subcategory":"Animal Services",
            "type":"Services"
        }
    ],
    "sg:phone":"+1 519 623 5050",
    "sg:postcode":"N1R 7Z1",
    "sg:province":"ON",
    "sg:tags":[
        "pet",
        "grooming",
        "washing"
    ],
    "wof:name":"Pet Stop Ava",
    "wof:placetype":"venue"
},
  "geometry": {"coordinates":[-80.30242200000001,43.379974],"type":"Point"}
}