{
  "type": "Feature",
  "properties": {
    "addr:full":"Mississauga ON L4W 1V6",
    "addr:postcode":"l4w 1v6",
    "iso:country":"CA",
    "sg:city":"Mississauga",
    "sg:classifiers":[
        {
            "category":"Manufacturing",
            "subcategory":"Tools & Machinery",
            "type":"Manufacturing & Wholesale Goods"
        }
    ],
    "sg:phone":"+1 905 282 9408",
    "sg:postcode":"L4W 1V6",
    "sg:province":"ON",
    "sg:tags":[
        "machine",
        "shop"
    ],
    "wof:name":"K & M Precision Machine",
    "wof:placetype":"venue"
},
  "geometry": {"coordinates":[-79.6232452393,43.644203186],"type":"Point"}
}