{
  "type": "Feature",
  "properties": {
    "addr:full":"426 Av Principale Degelis QC G5T 1M7",
    "addr:postcode":"g5t 1m7",
    "addr:street":"426 Av Principale",
    "iso:country":"CA",
    "sg:address":"426 Av Principale",
    "sg:city":"Degelis",
    "sg:classifiers":[
        {
            "category":"Insurance",
            "subcategory":"Insurance Agent",
            "type":"Services"
        }
    ],
    "sg:phone":"+1 418 853 2350",
    "sg:postcode":"G5T 1M7",
    "sg:province":"QC",
    "wof:name":"Assurances DE L'Est Inc Svc",
    "wof:placetype":"venue"
},
  "geometry": {"coordinates":[-68.64287567140001,47.5469741821],"type":"Point"}
}