{
  "type": "Feature",
  "properties": {
    "addr:full":"Etobicoke ON M9W 6Y7",
    "addr:postcode":"m9w 6y7",
    "iso:country":"CA",
    "sg:city":"Etobicoke",
    "sg:classifiers":[
        {
            "category":"Home & Garden",
            "subcategory":"Furniture",
            "type":"Retail Goods"
        }
    ],
    "sg:phone":"+1 416 213 9342",
    "sg:postcode":"M9W 6Y7",
    "sg:province":"ON",
    "sg:tags":[
        "equipment",
        "kitchen",
        "cabinet"
    ],
    "wof:name":"Angelo Travanut Ltd",
    "wof:placetype":"venue"
},
  "geometry": {"coordinates":[-79.62340500000001,43.750835],"type":"Point"}
}