{
  "type": "Feature",
  "properties": {
    "iso:country":"CA",
    "sg:address":"19640 28 Ave",
    "sg:city":"Langley",
    "sg:classifiers":[
        {
            "category":"Building & Trades",
            "subcategory":"Construction",
            "type":"Services"
        }
    ],
    "sg:phone":"+1 604 533 5456",
    "sg:postcode":"V2Z 1Y1",
    "sg:province":"BC",
    "sg:tags":[
        "roofing",
        "contractor"
    ],
    "wof:name":"Claynor Roofing Ltd",
    "wof:placetype":"venue"
},
  "geometry": {"coordinates":[-122.679016113,49.0527915955],"type":"Point"}
}