{
  "type": "Feature",
  "properties": {
    "addr:full":"3180 Rue Principale Saint-Ferdinand QC G0N 1N0",
    "addr:housenumber":"3180",
    "addr:postcode":"g0n 1n0",
    "addr:street":"Rue Principale",
    "iso:country":"CA",
    "sg:address":"3180 Rue Principale",
    "sg:city":"Saint-Ferdinand",
    "sg:classifiers":[
        {
            "category":"Travel",
            "subcategory":"Hotels & Motels",
            "type":"Entertainment"
        }
    ],
    "sg:phone":"+1 418 428 9188",
    "sg:postcode":"G0N 1N0",
    "sg:province":"QC",
    "wof:name":"Manoir Du Lac William Inc",
    "wof:placetype":"venue"
},
  "geometry": {"coordinates":[-71.57996368409999,46.1258354187],"type":"Point"}
}