{
  "type": "Feature",
  "properties": {
    "iso:country":"CA",
    "sg:address":"5843 Av Du Parc # B",
    "sg:city":"Montreal",
    "sg:classifiers":[
        {
            "category":"Organizations",
            "subcategory":"Professional Association",
            "type":"Services"
        }
    ],
    "sg:phone":"+1 514 278 2867",
    "sg:postcode":"H2V 4H4",
    "sg:province":"QC",
    "wof:name":"Like Young",
    "wof:placetype":"venue"
},
  "geometry": {"coordinates":[-73.6062927246,45.5241699219],"type":"Point"}
}