{
  "type": "Feature",
  "properties": {
    "addr:full":"RR 1 Shallow Lake ON N0H 2K0",
    "addr:postcode":"n0h 2k0",
    "addr:street":"Rr 1 Shallow",
    "iso:country":"CA",
    "sg:address":"RR 1",
    "sg:city":"Shallow Lake",
    "sg:classifiers":[
        {
            "category":"Retail",
            "subcategory":"Auto Repair",
            "type":"Services"
        }
    ],
    "sg:phone":"+1 519 376 6234",
    "sg:postcode":"N0H 2K0",
    "sg:province":"ON",
    "sg:tags":[
        "wrecker"
    ],
    "wof:name":"A-70 Towing & Recovery",
    "wof:placetype":"venue"
},
  "geometry": {"coordinates":[-81.08488464360001,44.6150550842],"type":"Point"}
}