{
  "type": "Feature",
  "properties": {
    "addr:full":"401 Kent St W Lindsay ON K9V 4Z1",
    "addr:housenumber":"401",
    "addr:postcode":"k9v 4z1",
    "addr:street":"Kent St W",
    "iso:country":"CA",
    "sg:address":"401 Kent St W",
    "sg:city":"Lindsay",
    "sg:classifiers":[
        {
            "category":"Shopping",
            "subcategory":"Clothing, Apparel, & Fashions",
            "type":"Retail Goods"
        }
    ],
    "sg:phone":"+1 705 878 4380",
    "sg:postcode":"K9V 4Z1",
    "sg:province":"ON",
    "sg:tags":[
        "accessory"
    ],
    "wof:name":"Ardene",
    "wof:placetype":"venue"
},
  "geometry": {"coordinates":[-78.75933074949999,44.3500518799],"type":"Point"}
}