{
  "type": "Feature",
  "properties": {
    "iso:country":"CA",
    "sg:address":"30 Burlington Ave",
    "sg:city":"Moncton",
    "sg:classifiers":[
        {
            "category":"Health Services",
            "subcategory":"Nursing And Care Facility",
            "type":"Services"
        }
    ],
    "sg:phone":"+1 506 857 9863",
    "sg:postcode":"E1E 1Y7",
    "sg:province":"NB",
    "sg:tags":[
        "home",
        "convalescent",
        "rest"
    ],
    "wof:name":"Foyer Chez Nous Ltd",
    "wof:placetype":"venue"
},
  "geometry": {"coordinates":[-64.794769,46.086285],"type":"Point"}
}