{
  "type": "Feature",
  "properties": {
    "addr:full":"1919 Columbia Ave Rossland BC V0G 1Y0",
    "addr:housenumber":"1919",
    "addr:postcode":"v0g 1y0",
    "addr:street":"Columbia Ave",
    "iso:country":"CA",
    "sg:address":"1919 Columbia Ave",
    "sg:city":"Rossland",
    "sg:classifiers":[
        {
            "category":"Professional",
            "subcategory":"Business Services",
            "type":"Services"
        }
    ],
    "sg:phone":"+1 250 362 7375",
    "sg:postcode":"V0G 1Y0",
    "sg:province":"BC",
    "sg:tags":[
        "convention",
        "motel",
        "hotel",
        "meeting",
        "facility"
    ],
    "wof:name":"Uplander Hotel",
    "wof:placetype":"venue"
},
  "geometry": {"coordinates":[-117.801582,49.076889],"type":"Point"}
}