{
  "type": "Feature",
  "properties": {
    "addr:full":"252 Rue Gendron Saint-Leon-Le-Grand QC G0J 2W0",
    "addr:housenumber":"252",
    "addr:postcode":"g0j 2w0",
    "addr:street":"Rue Gendron Saint-Leon-Le-Grand",
    "iso:country":"CA",
    "sg:address":"252 Rue Gendron",
    "sg:city":"Saint-Leon-Le-Grand",
    "sg:classifiers":[
        {
            "category":"Food & Beverages",
            "subcategory":"Groceries & Convenience Stores",
            "type":"Retail Goods"
        }
    ],
    "sg:phone":"+1 418 743 5200",
    "sg:postcode":"G0J 2W0",
    "sg:province":"QC",
    "sg:tags":[
        "grocer"
    ],
    "wof:name":"Depanneur 252 Enr",
    "wof:placetype":"venue"
},
  "geometry": {"coordinates":[-67.50406599999999,48.381123],"type":"Point"}
}