{
  "type": "Feature",
  "properties": {
    "iso:country":"CA",
    "sg:address":"20 Lake Ave E",
    "sg:city":"Carleton Place",
    "sg:classifiers":[
        {
            "category":"Shopping",
            "type":"Retail Goods"
        }
    ],
    "sg:phone":"+1 613 253 1007",
    "sg:postcode":"K7C 4J1",
    "sg:province":"ON",
    "sg:tags":[
        "equipment",
        "wine",
        "supply"
    ],
    "wof:name":"Carleton Place Wineries",
    "wof:placetype":"venue"
},
  "geometry": {"coordinates":[-76.14154052729999,45.1372032166],"type":"Point"}
}