{
  "type": "Feature",
  "properties": {
    "addr:full":"2244 Queen St E Toronto ON M4E 1G2",
    "addr:housenumber":"2244",
    "addr:postcode":"m4e 1g2",
    "addr:street":"Queen St E",
    "iso:country":"CA",
    "sg:address":"2244 Queen St E",
    "sg:city":"Toronto",
    "sg:classifiers":[
        {
            "category":"Shopping",
            "subcategory":"Discount & Variety Stores",
            "type":"Retail Goods"
        }
    ],
    "sg:phone":"+1 416 694 7383",
    "sg:postcode":"M4E 1G2",
    "sg:province":"ON",
    "wof:name":"Beach Plaza Variety",
    "wof:placetype":"venue"
},
  "geometry": {"coordinates":[-79.28703299999999,43.672916],"type":"Point"}
}