{
  "type": "Feature",
  "properties": {
    "addr:full":"715 East Drive Saskatoon SK S7J 2X8",
    "addr:housenumber":"715",
    "addr:postcode":"s7j 2x8",
    "addr:street":"East Drive",
    "iso:country":"CA",
    "sg:address":"715 East Drive",
    "sg:city":"Saskatoon",
    "sg:classifiers":[
        {
            "category":"Education",
            "subcategory":"School",
            "type":"Public Place"
        }
    ],
    "sg:phone":"+1 306 683 7100",
    "sg:postcode":"S7J 2X8",
    "sg:province":"SK",
    "wof:name":"Alvin Buckwold School",
    "wof:placetype":"venue"
},
  "geometry": {"coordinates":[-106.615135193,52.0972442627],"type":"Point"}
}