{
  "type": "Feature",
  "properties": {
    "addr:full":"817 1st Ave Raymore SK S0A 3J0",
    "addr:housenumber":"817",
    "addr:postcode":"s0a 3j0",
    "addr:street":"1St Ave",
    "iso:country":"CA",
    "sg:address":"817 1st Ave",
    "sg:city":"Raymore",
    "sg:classifiers":[
        {
            "category":"Retail",
            "subcategory":"Auto Repair",
            "type":"Services"
        }
    ],
    "sg:phone":"+1 306 746 2232",
    "sg:postcode":"S0A 3J0",
    "sg:province":"SK",
    "sg:tags":[
        "wrecker"
    ],
    "wof:name":"Cars",
    "wof:placetype":"venue"
},
  "geometry": {"coordinates":[-104.538025,51.409729],"type":"Point"}
}