{
  "type": "Feature",
  "properties": {
    "addr:full":"317 Pope Rd Summerside PE C1N 6G4",
    "addr:housenumber":"317",
    "addr:postcode":"c1n 6g4",
    "addr:street":"Pope Rd",
    "iso:country":"CA",
    "sg:address":"317 Pope Rd",
    "sg:city":"Summerside",
    "sg:classifiers":[
        {
            "category":"Social Services",
            "subcategory":"Adult Care",
            "type":"Services"
        }
    ],
    "sg:phone":"+1 902 436 0859",
    "sg:postcode":"C1N 6G4",
    "sg:province":"PE",
    "sg:tags":[
        "home",
        "community",
        "rest"
    ],
    "wof:name":"Andrews Lodge",
    "wof:placetype":"venue"
},
  "geometry": {"coordinates":[-63.791687,46.411057],"type":"Point"}
}