{
  "type": "Feature",
  "properties": {
    "addr:full":"600 36E Av Saint-Jerome QC J7Z 5W2",
    "addr:housenumber":"600",
    "addr:postcode":"j7z 5w2",
    "addr:street":"36E Av Saint-Jerome",
    "iso:country":"CA",
    "sg:address":"600 36E Av",
    "sg:city":"Saint-Jerome",
    "sg:classifiers":[
        {
            "category":"Education",
            "subcategory":"School",
            "type":"Public Place"
        }
    ],
    "sg:phone":"+1 450 436 1858",
    "sg:postcode":"J7Z 5W2",
    "sg:province":"QC",
    "wof:name":"Ecole Secondaire Cap Jeunesse",
    "wof:placetype":"venue"
},
  "geometry": {"coordinates":[-74.00350952150001,45.7750091553],"type":"Point"}
}