{
  "type": "Feature",
  "properties": {
    "addr:full":"217 Centre St SW #300 Calgary AB T2G 2B7",
    "addr:housenumber":"217",
    "addr:postcode":"t2g 2b7",
    "addr:street":"Centre St Sw # 300",
    "iso:country":"CA",
    "sg:address":"217 Centre St SW #300",
    "sg:city":"Calgary",
    "sg:classifiers":[
        {
            "category":"Health Services",
            "subcategory":"Doctor",
            "type":"Services"
        }
    ],
    "sg:phone":"+1 403 541 1200",
    "sg:postcode":"T2G 2B7",
    "sg:province":"AB",
    "sg:tags":[
        "physician",
        "surgeon"
    ],
    "wof:name":"Efw Radiology",
    "wof:placetype":"venue"
},
  "geometry": {"coordinates":[-114.062912,51.050991],"type":"Point"}
}