{
  "type": "Feature",
  "properties": {
    "addr:full":"40 Main St N Alexandria ON K0C 1A0",
    "addr:housenumber":"40",
    "addr:postcode":"k0c 1a0",
    "addr:street":"Main St N",
    "iso:country":"CA",
    "sg:address":"40 Main St N",
    "sg:city":"Alexandria",
    "sg:classifiers":[
        {
            "category":"Professional",
            "subcategory":"Lawyer & Legal Services",
            "type":"Services"
        }
    ],
    "sg:phone":"+1 613 525 1055",
    "sg:postcode":"K0C 1A0",
    "sg:province":"ON",
    "sg:tags":[
        "attorney"
    ],
    "wof:name":"Mac Donald & Aubry",
    "wof:placetype":"venue"
},
  "geometry": {"coordinates":[-74.6371459961,45.3115234375],"type":"Point"}
}