{
  "type": "Feature",
  "properties": {
    "addr:full":"7603 Sideroad 10 W Arthur ON N0G 1A0",
    "addr:housenumber":"7603",
    "addr:postcode":"n0g 1a0",
    "addr:street":"Sideroad 10 W Arthur",
    "iso:country":"CA",
    "sg:address":"7603 Sideroad 10 W",
    "sg:city":"Arthur",
    "sg:classifiers":[
        {
            "category":"Professional",
            "subcategory":"Accounting & Tax Preparation",
            "type":"Services"
        }
    ],
    "sg:phone":"+1 519 848 2714",
    "sg:postcode":"N0G 1A0",
    "sg:province":"ON",
    "sg:tags":[
        "return",
        "filing"
    ],
    "wof:name":"Sherrie's Services",
    "wof:placetype":"venue"
},
  "geometry": {"coordinates":[-80.600403,43.842777],"type":"Point"}
}