{
  "type": "Feature",
  "properties": {
    "addr:full":"2387 Westcott Rd Windsor ON N8W 4K6",
    "addr:housenumber":"2387",
    "addr:postcode":"n8w 4k6",
    "addr:street":"Westcott Rd",
    "iso:country":"CA",
    "sg:address":"2387 Westcott Rd",
    "sg:city":"Windsor",
    "sg:classifiers":[
        {
            "category":"Building & Trades",
            "subcategory":"Landscaping Services",
            "type":"Services"
        }
    ],
    "sg:phone":"+1 519 945 8681",
    "sg:postcode":"N8W 4K6",
    "sg:province":"ON",
    "sg:tags":[
        "landscape",
        "contractor"
    ],
    "wof:name":"Valente Turf Contractors Ltd",
    "wof:placetype":"venue"
},
  "geometry": {"coordinates":[-82.977203,42.303116],"type":"Point"}
}