{
  "type": "Feature",
  "properties": {
    "iso:country":"CA",
    "sg:address":"233 Armstrong St",
    "sg:city":"Ottawa",
    "sg:classifiers":[
        {
            "category":"Shopping",
            "subcategory":"Computers & Home Electronics",
            "type":"Retail Goods"
        }
    ],
    "sg:phone":"+1 613 729 2331",
    "sg:postcode":"K1Y 2W5",
    "sg:province":"ON",
    "sg:tags":[
        "equipment",
        "electronic",
        "supply"
    ],
    "wof:name":"Add Electronics Inc",
    "wof:placetype":"venue"
},
  "geometry": {"coordinates":[-75.73025512700001,45.4020195007],"type":"Point"}
}