{
  "type": "Feature",
  "properties": {
    "addr:full":"Winnipeg MB R3P 1J3",
    "addr:postcode":"r3p 1j3",
    "iso:country":"CA",
    "sg:city":"Winnipeg",
    "sg:classifiers":[
        {
            "category":"Personal",
            "type":"Services"
        }
    ],
    "sg:phone":"+1 204 487 7500",
    "sg:postcode":"R3P 1J3",
    "sg:province":"MB",
    "sg:tags":[
        "miscellaneous"
    ],
    "wof:name":"Allmart Enterprises",
    "wof:placetype":"venue"
},
  "geometry": {"coordinates":[-97.1812667847,49.8471412659],"type":"Point"}
}