{
  "type": "Feature",
  "properties": {
    "iso:country":"CA",
    "sg:address":"30 Raddall Ave",
    "sg:city":"Dartmouth",
    "sg:classifiers":[
        {
            "category":"Building & Trades",
            "subcategory":"Construction",
            "type":"Services"
        }
    ],
    "sg:phone":"+1 902 468 2104",
    "sg:postcode":"B3B 1T2",
    "sg:province":"NS",
    "sg:tags":[
        "steel"
    ],
    "wof:name":"Maritime Structural Detailers",
    "wof:placetype":"venue"
},
  "geometry": {"coordinates":[-63.591385,44.704697],"type":"Point"}
}