{
  "type": "Feature",
  "properties": {
    "addr:full":"Vancouver BC V6B 1P2",
    "addr:postcode":"v6b 1p2",
    "iso:country":"CA",
    "sg:city":"Vancouver",
    "sg:classifiers":[
        {
            "category":"Shopping",
            "subcategory":"Computers & Home Electronics",
            "type":"Retail Goods"
        }
    ],
    "sg:phone":"+1 604 687 7182",
    "sg:postcode":"V6B 1P2",
    "sg:province":"BC",
    "sg:tags":[
        "software"
    ],
    "wof:name":"Centranet",
    "wof:placetype":"venue"
},
  "geometry": {"coordinates":[-123.113029,49.284672],"type":"Point"}
}