{
  "type": "Feature",
  "properties": {
    "addr:full":"444 Parkhill Terr Ladysmith BC V9G 1V6",
    "addr:housenumber":"444",
    "addr:postcode":"v9g 1v6",
    "addr:street":"Parkhill Terr",
    "iso:country":"CA",
    "sg:address":"444 Parkhill Terr",
    "sg:city":"Ladysmith",
    "sg:classifiers":[
        {
            "category":"Education",
            "subcategory":"School",
            "type":"Public Place"
        }
    ],
    "sg:phone":"+1 250 245 7187",
    "sg:postcode":"V9G 1V6",
    "sg:province":"BC",
    "wof:name":"Davis Road School",
    "wof:placetype":"venue"
},
  "geometry": {"coordinates":[-123.802970886,48.9731674194],"type":"Point"}
}