{
  "type": "Feature",
  "properties": {
    "addr:full":"632 Bloor St W Toronto ON M6G 1K7",
    "addr:housenumber":"632",
    "addr:postcode":"m6g 1k7",
    "addr:street":"Bloor St W",
    "iso:country":"CA",
    "sg:address":"632 Bloor St W",
    "sg:city":"Toronto",
    "sg:classifiers":[
        {
            "category":"Shopping",
            "subcategory":"Jewelry",
            "type":"Retail Goods"
        }
    ],
    "sg:phone":"+1 416 538 5874",
    "sg:postcode":"M6G 1K7",
    "sg:province":"ON",
    "sg:tags":[
        "jeweler"
    ],
    "wof:name":"Art Deco",
    "wof:placetype":"venue"
},
  "geometry": {"coordinates":[-79.4145355225,43.6645317078],"type":"Point"}
}