{
  "type": "Feature",
  "properties": {
    "addr:full":"147 Burcher Rd Ajax ON L1S 2R6",
    "addr:housenumber":"147",
    "addr:postcode":"l1s 2r6",
    "addr:street":"Burcher Rd",
    "iso:country":"CA",
    "sg:address":"147 Burcher Rd",
    "sg:city":"Ajax",
    "sg:classifiers":[
        {
            "category":"Retail",
            "subcategory":"Repair Shop",
            "type":"Services"
        }
    ],
    "sg:phone":"+1 905 683 5510",
    "sg:postcode":"L1S 2R6",
    "sg:province":"ON",
    "sg:tags":[
        "repairing",
        "organs",
        "refinishing"
    ],
    "wof:name":"Hiddink, Joseph",
    "wof:placetype":"venue"
},
  "geometry": {"coordinates":[-79.01106299999999,43.83873],"type":"Point"}
}