{
  "type": "Feature",
  "properties": {
    "addr:full":"2900 Steeles Ave E # 205 Thornhill ON L3T 4X1",
    "addr:housenumber":"2900",
    "addr:postcode":"l3t 4x1",
    "addr:street":"Steeles Ave E # 205",
    "iso:country":"CA",
    "sg:address":"2900 Steeles Ave E # 205",
    "sg:city":"Thornhill",
    "sg:classifiers":[
        {
            "category":"Professional",
            "subcategory":"Accounting & Tax Preparation",
            "type":"Services"
        }
    ],
    "sg:phone":"+1 905 881 2177",
    "sg:postcode":"L3T 4X1",
    "sg:province":"ON",
    "sg:tags":[
        "consultant",
        "financial",
        "planning",
        "return",
        "filing"
    ],
    "wof:name":"DE Thomas Financial Corp",
    "wof:placetype":"venue"
},
  "geometry": {"coordinates":[-79.359207,43.811752],"type":"Point"}
}