{
  "type": "Feature",
  "properties": {
    "iso:country":"CA",
    "sg:address":"84 Main St",
    "sg:city":"Canso",
    "sg:classifiers":[
        {
            "category":"Retail",
            "subcategory":"Auto Repair",
            "type":"Services"
        }
    ],
    "sg:phone":"+1 902 366 2611",
    "sg:postcode":"B0H 1H0",
    "sg:province":"NS",
    "sg:tags":[
        "repairing",
        "automobile"
    ],
    "wof:name":"Canso Garage Ltd",
    "wof:placetype":"venue"
},
  "geometry": {"coordinates":[-60.996685,45.335403],"type":"Point"}
}