{
  "type": "Feature",
  "properties": {
    "addr:full":"Belleville ON K8N 5B3",
    "addr:postcode":"k8n 5b3",
    "iso:country":"CA",
    "sg:city":"Belleville",
    "sg:classifiers":[
        {
            "category":"Professional",
            "subcategory":"Management & Consulting",
            "type":"Services"
        }
    ],
    "sg:phone":"+1 613 961 7990",
    "sg:postcode":"K8N 5B3",
    "sg:province":"ON",
    "sg:tags":[
        "development",
        "economic",
        "agency"
    ],
    "wof:name":"Quinte Economic Development",
    "wof:placetype":"venue"
},
  "geometry": {"coordinates":[-77.4315338135,44.1487312317],"type":"Point"}
}