{
  "type": "Feature",
  "properties": {
    "addr:full":"2900 Vigar Rd Campbell River BC V9W 6A3",
    "addr:housenumber":"2900",
    "addr:postcode":"v9w 6a3",
    "addr:street":"Vigar Rd",
    "iso:country":"CA",
    "sg:address":"2900 Vigar Rd",
    "sg:city":"Campbell River",
    "sg:classifiers":[
        {
            "category":"Freight",
            "type":"Transportation"
        }
    ],
    "sg:phone":"+1 250 287 7287",
    "sg:postcode":"V9W 6A3",
    "sg:province":"BC",
    "sg:tags":[
        "trucking"
    ],
    "wof:name":"AZ-Tec Freight",
    "wof:placetype":"venue"
},
  "geometry": {"coordinates":[-125.27338409399999,50.0456352234],"type":"Point"}
}