{
  "type": "Feature",
  "properties": {
    "iso:country":"CA",
    "sg:city":"Dollard-Des-Ormeaux",
    "sg:classifiers":[
        {
            "category":"Shopping",
            "subcategory":"Bicycles & Sporting Goods",
            "type":"Retail Goods"
        }
    ],
    "sg:phone":"+1 514 421 2302",
    "sg:postcode":"H9B 2N4",
    "sg:province":"QC",
    "sg:tags":[
        "equipment",
        "exercise"
    ],
    "wof:name":"Fitness Depot",
    "wof:placetype":"venue"
},
  "geometry": {"coordinates":[-73.7979049683,45.4825630188],"type":"Point"}
}