{
  "type": "Feature",
  "properties": {
    "addr:full":"1554 Av Du Mont-Royal E Montreal QC H2J 1Z2",
    "addr:housenumber":"1554",
    "addr:postcode":"h2j 1z2",
    "addr:street":"Av Du Mont-Royal E",
    "iso:country":"CA",
    "sg:address":"1554 Av Du Mont-Royal E",
    "sg:city":"Montreal",
    "sg:classifiers":[
        {
            "category":"Professional",
            "subcategory":"Lawyer & Legal Services",
            "type":"Services"
        }
    ],
    "sg:phone":"+1 514 596 2306",
    "sg:postcode":"H2J 1Z2",
    "sg:province":"QC",
    "sg:tags":[
        "attorney"
    ],
    "wof:name":"Desrosiers, Jean-M",
    "wof:placetype":"venue"
},
  "geometry": {"coordinates":[-73.575378418,45.531791687],"type":"Point"}
}