{
  "type": "Feature",
  "properties": {
    "iso:country":"CA",
    "sg:address":"3679 Weston Rd",
    "sg:city":"North York",
    "sg:classifiers":[
        {
            "category":"Retail",
            "subcategory":"Repair Shop",
            "type":"Services"
        }
    ],
    "sg:phone":"+1 416 745 6220",
    "sg:postcode":"M9L 1V8",
    "sg:province":"ON",
    "sg:tags":[
        "upholsterer"
    ],
    "wof:name":"Happy Home",
    "wof:placetype":"venue"
},
  "geometry": {"coordinates":[-79.544304,43.760914],"type":"Point"}
}