{
  "type": "Feature",
  "properties": {
    "addr:full":"425 8E Rue LA Pocatiere QC G0R 1Z0",
    "addr:housenumber":"425",
    "addr:postcode":"g0r 1z0",
    "addr:street":"8E Rue La Pocatiere",
    "iso:country":"CA",
    "sg:address":"425 8E Rue",
    "sg:city":"LA Pocatiere",
    "sg:classifiers":[
        {
            "category":"Organizations",
            "subcategory":"Professional Association",
            "type":"Services"
        }
    ],
    "sg:phone":"+1 418 856 3388",
    "sg:postcode":"G0R 1Z0",
    "sg:province":"QC",
    "wof:name":"Fondation-Jeunesse DE LA Cote",
    "wof:placetype":"venue"
},
  "geometry": {"coordinates":[-70.03224945069999,47.36901474],"type":"Point"}
}