{
  "type": "Feature",
  "properties": {
    "addr:full":"8046 Dixie Rd Brampton ON L6T 4W6",
    "addr:housenumber":"8046",
    "addr:postcode":"l6t 4w6",
    "addr:street":"Dixie Rd",
    "iso:country":"CA",
    "sg:address":"8046 Dixie Rd",
    "sg:city":"Brampton",
    "sg:classifiers":[
        {
            "category":"Autos & Motor Vehicles",
            "subcategory":"Automobile Sales",
            "type":"Retail Goods"
        }
    ],
    "sg:phone":"+1 416 798 7222",
    "sg:postcode":"L6T 4W6",
    "sg:province":"ON",
    "sg:tags":[
        "car",
        "dealer"
    ],
    "wof:name":"Saturn Saab Isuzu of Brampton",
    "wof:placetype":"venue"
},
  "geometry": {"coordinates":[-79.7046737671,43.6971702576],"type":"Point"}
}