{
  "type": "Feature",
  "properties": {
    "addr:full":"1295 North Service Rd Burlington ON L7R 4M2",
    "addr:housenumber":"1295",
    "addr:postcode":"l7r 4m2",
    "addr:street":"North Service Rd",
    "iso:country":"CA",
    "sg:address":"1295 North Service Rd",
    "sg:city":"Burlington",
    "sg:classifiers":[
        {
            "category":"Organizations",
            "subcategory":"Religious Organization",
            "type":"Services"
        }
    ],
    "sg:phone":"+1 905 845 5100",
    "sg:postcode":"L7R 4M2",
    "sg:province":"ON",
    "wof:name":"Crossroads Christian Comm Inc",
    "wof:placetype":"venue"
},
  "geometry": {"coordinates":[-79.83358764650001,43.3373146057],"type":"Point"}
}