{
  "type": "Feature",
  "properties": {
    "addr:full":"Medicine Hat AB T1A 4N3",
    "addr:postcode":"t1a 4n3",
    "iso:country":"CA",
    "sg:city":"Medicine Hat",
    "sg:classifiers":[
        {
            "category":"Travel",
            "subcategory":"Campground",
            "type":"Entertainment"
        }
    ],
    "sg:phone":"+1 403 526 2248",
    "sg:postcode":"T1A 4N3",
    "sg:province":"AB",
    "sg:tags":[
        "mobile",
        "home"
    ],
    "wof:name":"Wildrose Trailer Park",
    "wof:placetype":"venue"
},
  "geometry": {"coordinates":[-110.707527161,50.0309448242],"type":"Point"}
}