{
  "type": "Feature",
  "properties": {
    "iso:country":"CA",
    "sg:address":"74 Coldwater Rd",
    "sg:city":"Waubaushene",
    "sg:classifiers":[
        {
            "category":"Retail",
            "subcategory":"Auto Repair",
            "type":"Services"
        }
    ],
    "sg:phone":"+1 705 538 1372",
    "sg:postcode":"L0K 2C0",
    "sg:province":"ON",
    "sg:tags":[
        "repairing",
        "automobile"
    ],
    "wof:name":"Mackey's Automotive",
    "wof:placetype":"venue"
},
  "geometry": {"coordinates":[-79.7042541504,44.7566070557],"type":"Point"}
}