{
  "type": "Feature",
  "properties": {
    "addr:full":"Saint-Ubalde QC G0A 4L0",
    "addr:postcode":"g0a 4l0",
    "iso:country":"CA",
    "sg:city":"Saint-Ubalde",
    "sg:phone":"+1 418 277 2442",
    "sg:postcode":"G0A 4L0",
    "sg:province":"QC",
    "sg:tags":[
        "grower",
        "potato"
    ],
    "wof:name":"Patates Dolbec Inc",
    "wof:placetype":"venue"
},
  "geometry": {"coordinates":[-72.268738,46.75494],"type":"Point"}
}