{
  "type": "Feature",
  "properties": {
    "addr:full":"162 Nancy St Dutton ON N0L 1J0",
    "addr:housenumber":"162",
    "addr:postcode":"n0l 1j0",
    "addr:street":"Nancy St",
    "iso:country":"CA",
    "sg:address":"162 Nancy St",
    "sg:city":"Dutton",
    "sg:classifiers":[
        {
            "category":"Organizations",
            "subcategory":"Religious Organization",
            "type":"Services"
        }
    ],
    "sg:phone":"+1 519 762 0040",
    "sg:postcode":"N0L 1J0",
    "sg:province":"ON",
    "sg:tags":[
        "church"
    ],
    "wof:name":"Knox Presbyterian Church",
    "wof:placetype":"venue"
},
  "geometry": {"coordinates":[-81.500831604,42.6643180847],"type":"Point"}
}