{
  "type": "Feature",
  "properties": {
    "addr:full":"Harrington QC J8G 2S7",
    "addr:postcode":"j8g 2s7",
    "iso:country":"CA",
    "sg:city":"Harrington",
    "sg:classifiers":[
        {
            "category":"Home & Garden",
            "subcategory":"Garden Supply",
            "type":"Retail Goods"
        }
    ],
    "sg:phone":"+1 819 242 1947",
    "sg:postcode":"J8G 2S7",
    "sg:province":"QC",
    "sg:tags":[
        "nurseryman"
    ],
    "wof:name":"Pepiniere DE Harrington Inc",
    "wof:placetype":"venue"
},
  "geometry": {"coordinates":[-74.637253,45.837002],"type":"Point"}
}