{
  "type": "Feature",
  "properties": {
    "addr:full":"Nipigon ON P0T 2J0",
    "addr:postcode":"p0t 2j0",
    "iso:country":"CA",
    "sg:city":"Nipigon",
    "sg:classifiers":[
        {
            "category":"Travel",
            "subcategory":"Hotels & Motels",
            "type":"Entertainment"
        }
    ],
    "sg:phone":"+1 807 887 3032",
    "sg:postcode":"P0T 2J0",
    "sg:province":"ON",
    "sg:tags":[
        "tourist",
        "accommodation"
    ],
    "wof:name":"Sunnyside Cabins",
    "wof:placetype":"venue"
},
  "geometry": {"coordinates":[-88.258926,49.016636],"type":"Point"}
}