{
  "type": "Feature",
  "properties": {
    "iso:country":"CA",
    "sg:address":"1000 Gerrard St E",
    "sg:city":"Toronto",
    "sg:classifiers":[
        {
            "category":"Banks & Credit Unions",
            "subcategory":"Bank",
            "type":"Services"
        }
    ],
    "sg:phone":"+1 416 466 1147",
    "sg:postcode":"M4M 3G6",
    "sg:province":"ON",
    "wof:name":"Cibc",
    "wof:placetype":"venue"
},
  "geometry": {"coordinates":[-79.3385009766,43.6687164307],"type":"Point"}
}