{
  "type": "Feature",
  "properties": {
    "addr:full":"5618 55th St Drayton Valley AB T7A 1S5",
    "addr:housenumber":"5618",
    "addr:postcode":"t7a 1s5",
    "addr:street":"55Th St",
    "iso:country":"CA",
    "sg:address":"5618 55th St",
    "sg:city":"Drayton Valley",
    "sg:classifiers":[
        {
            "category":"Mining & Drilling",
            "type":"Manufacturing & Wholesale Goods"
        }
    ],
    "sg:phone":"+1 780 542 2900",
    "sg:postcode":"T7A 1S5",
    "sg:province":"AB",
    "sg:tags":[
        "field",
        "oil"
    ],
    "wof:name":"Firemaster Oilfield Svc Ltd",
    "wof:placetype":"venue"
},
  "geometry": {"coordinates":[-114.98299400000001,53.228676],"type":"Point"}
}