{
  "type": "Feature",
  "properties": {
    "addr:full":"345 Boul Brunswick Pointe-Claire QC H9R 4S1",
    "addr:housenumber":"345",
    "addr:postcode":"h9r 4s1",
    "addr:street":"Boul Brunswick",
    "iso:country":"CA",
    "sg:address":"345 Boul Brunswick",
    "sg:city":"Pointe-Claire",
    "sg:classifiers":[
        {
            "category":"Retail",
            "subcategory":"Auto Repair",
            "type":"Services"
        }
    ],
    "sg:phone":"+1 514 697 5222",
    "sg:postcode":"H9R 4S1",
    "sg:province":"QC",
    "sg:tags":[
        "repairing",
        "automobile",
        "dealer"
    ],
    "wof:name":"Spinelli Infiniti Nissan",
    "wof:placetype":"venue"
},
  "geometry": {"coordinates":[-73.833336,45.465618],"type":"Point"}
}