{
  "type": "Feature",
  "properties": {
    "addr:full":"11012 Jasper Ave NW Edmonton AB T5K 2N8",
    "addr:housenumber":"11012",
    "addr:postcode":"t5k 2n8",
    "addr:street":"Jasper Ave Nw",
    "iso:country":"CA",
    "sg:address":"11012 Jasper Ave NW",
    "sg:city":"Edmonton",
    "sg:classifiers":[
        {
            "category":"Professional",
            "subcategory":"Computer Services",
            "type":"Services"
        }
    ],
    "sg:phone":"+1 780 429 3442",
    "sg:postcode":"T5K 2N8",
    "sg:province":"AB",
    "sg:tags":[
        "internet"
    ],
    "wof:name":"Bohemia Cyber Cafe",
    "wof:placetype":"venue"
},
  "geometry": {"coordinates":[-113.51063499999999,53.541157],"type":"Point"}
}