{
  "type": "Feature",
  "properties": {
    "addr:full":"9017 Shaughnessy St Vancouver BC V6P 6R9",
    "addr:postcode":"9017;v6p 6r9",
    "addr:street":"Shaughnessy St",
    "iso:country":"CA",
    "sg:address":"9017 Shaughnessy St",
    "sg:city":"Vancouver",
    "sg:classifiers":[
        {
            "category":"Professional",
            "subcategory":"Business Services",
            "type":"Services"
        }
    ],
    "sg:phone":"+1 604 669 5595",
    "sg:postcode":"V6P 6R9",
    "sg:province":"BC",
    "sg:tags":[
        "pool",
        "swimming"
    ],
    "wof:name":"Canadian Pool Maintenance",
    "wof:placetype":"venue"
},
  "geometry": {"coordinates":[-123.128136,49.203358],"type":"Point"}
}