{
  "type": "Feature",
  "properties": {
    "addr:full":"410 Ch Rheaume Saint-Michel QC J0L 2J0",
    "addr:housenumber":"410",
    "addr:postcode":"j0l 2j0",
    "addr:street":"Ch Rheaume",
    "iso:country":"CA",
    "sg:address":"410 Ch Rheaume",
    "sg:city":"Saint-Michel",
    "sg:classifiers":[
        {
            "category":"Autos & Motor Vehicles",
            "subcategory":"Fuel & Gas Station",
            "type":"Retail Goods"
        }
    ],
    "sg:phone":"+1 450 454 4548",
    "sg:postcode":"J0L 2J0",
    "sg:province":"QC",
    "sg:tags":[
        "oil"
    ],
    "wof:name":"Station 221",
    "wof:placetype":"venue"
},
  "geometry": {"coordinates":[-73.567909,45.242504],"type":"Point"}
}