{
  "type": "Feature",
  "properties": {
    "addr:full":"Thornhill ON L4J 7R5",
    "addr:postcode":"l4j 7r5",
    "iso:country":"CA",
    "sg:city":"Thornhill",
    "sg:classifiers":[
        {
            "category":"Home & Garden",
            "subcategory":"Building Materials",
            "type":"Retail Goods"
        }
    ],
    "sg:phone":"+1 905 760 8118",
    "sg:postcode":"L4J 7R5",
    "sg:province":"ON",
    "sg:tags":[
        "paint"
    ],
    "wof:name":"Coulter's Mill Paint & Decor",
    "wof:placetype":"venue"
},
  "geometry": {"coordinates":[-79.4704742432,43.7978019714],"type":"Point"}
}