{
  "type": "Feature",
  "properties": {
    "addr:full":"705 Moose St Moosomin SK S0G 3N0",
    "addr:housenumber":"705",
    "addr:postcode":"s0g 3n0",
    "addr:street":"Moose St",
    "iso:country":"CA",
    "sg:address":"705 Moose St",
    "sg:city":"Moosomin",
    "sg:classifiers":[
        {
            "category":"Building & Trades",
            "subcategory":"Plumbing",
            "type":"Services"
        }
    ],
    "sg:phone":"+1 306 435 9242",
    "sg:postcode":"S0G 3N0",
    "sg:province":"SK",
    "sg:tags":[
        "contractor"
    ],
    "wof:name":"Skulmoski Plumbing & Heating",
    "wof:placetype":"venue"
},
  "geometry": {"coordinates":[-101.661087036,50.1443367004],"type":"Point"}
}