{
  "type": "Feature",
  "properties": {
    "addr:full":"263 Dundas St E Trenton ON K8V 1M1",
    "addr:housenumber":"263",
    "addr:postcode":"k8v 1m1",
    "addr:street":"Dundas St E",
    "iso:country":"CA",
    "sg:address":"263 Dundas St E",
    "sg:city":"Trenton",
    "sg:classifiers":[
        {
            "category":"Personal",
            "subcategory":"Beauty Salon",
            "type":"Services"
        }
    ],
    "sg:phone":"+1 613 392 3352",
    "sg:postcode":"K8V 1M1",
    "sg:province":"ON",
    "wof:name":"Park Plaza Beauty Salon",
    "wof:placetype":"venue"
},
  "geometry": {"coordinates":[-77.558243,44.104572],"type":"Point"}
}