{
  "type": "Feature",
  "properties": {
    "addr:full":"3609 Sheppard Ave E Scarborough ON M1T 3K8",
    "addr:housenumber":"3609",
    "addr:postcode":"m1t 3k8",
    "addr:street":"Sheppard Ave E",
    "iso:country":"CA",
    "sg:address":"3609 Sheppard Ave E",
    "sg:city":"Scarborough",
    "sg:classifiers":[
        {
            "category":"Education",
            "subcategory":"Special Training",
            "type":"Public Place"
        }
    ],
    "sg:phone":"+1 416 293 7997",
    "sg:postcode":"M1T 3K8",
    "sg:province":"ON",
    "sg:tags":[
        "instruction",
        "driving"
    ],
    "wof:name":"Pro Star Driving School",
    "wof:placetype":"venue"
},
  "geometry": {"coordinates":[-79.2994232178,43.7805938721],"type":"Point"}
}