{
  "type": "Feature",
  "properties": {
    "addr:full":"45 Rue Notre Dame O Trois-Pistoles QC G0L 4K0",
    "addr:housenumber":"45",
    "addr:postcode":"g0l 4k0",
    "addr:street":"Rue Notre Dame O",
    "iso:country":"CA",
    "sg:address":"45 Rue Notre Dame O",
    "sg:city":"Trois-Pistoles",
    "sg:classifiers":[
        {
            "category":"Retail",
            "subcategory":"Repair Shop",
            "type":"Services"
        }
    ],
    "sg:phone":"+1 418 851 4138",
    "sg:postcode":"G0L 4K0",
    "sg:province":"QC",
    "sg:tags":[
        "equipment",
        "electronic",
        "supply"
    ],
    "wof:name":"Bel Electronique",
    "wof:placetype":"venue"
},
  "geometry": {"coordinates":[-69.1744232178,48.125869751],"type":"Point"}
}