{
  "type": "Feature",
  "properties": {
    "addr:full":"87 Hawthorne St St Stephen NB E3L 1W8",
    "addr:housenumber":"87",
    "addr:postcode":"nb e3l 1w8",
    "addr:street":"Hawthorne St",
    "iso:country":"CA",
    "sg:address":"87 Hawthorne St",
    "sg:city":"St Stephen",
    "sg:classifiers":[
        {
            "category":"Utilities",
            "subcategory":"Fuel Oil & Lpg",
            "type":"Services"
        }
    ],
    "sg:phone":"+1 506 466 5900",
    "sg:postcode":"E3L 1W8",
    "sg:province":"NB",
    "sg:tags":[
        "firewood"
    ],
    "wof:name":"Woodman",
    "wof:placetype":"venue"
},
  "geometry": {"coordinates":[-67.275291,45.194553],"type":"Point"}
}