{
  "type": "Feature",
  "properties": {
    "addr:full":"605 16 Ave NE Calgary AB T2E 1K7",
    "addr:postcode":"t2e 1k7",
    "addr:street":"605 16 Ave Ne",
    "iso:country":"CA",
    "sg:address":"605 16 Ave NE",
    "sg:city":"Calgary",
    "sg:classifiers":[
        {
            "category":"Retail",
            "subcategory":"Car Wash",
            "type":"Services"
        }
    ],
    "sg:phone":"+1 403 250 1505",
    "sg:postcode":"T2E 1K7",
    "sg:province":"AB",
    "sg:tags":[
        "polishing",
        "automobile",
        "washing",
        "detail"
    ],
    "wof:name":"Cosmetic Car",
    "wof:placetype":"venue"
},
  "geometry": {"coordinates":[-114.050247,51.066902],"type":"Point"}
}