{
  "type": "Feature",
  "properties": {
    "addr:full":"197 Rue DE LA Baie Les Buissons QC G0H 1H0",
    "addr:housenumber":"197",
    "addr:postcode":"g0h 1h0",
    "addr:street":"Rue De La Baie Les Buissons",
    "iso:country":"CA",
    "sg:address":"197 Rue DE LA Baie",
    "sg:city":"Les Buissons",
    "sg:classifiers":[
        {
            "category":"Travel",
            "subcategory":"Campground",
            "type":"Entertainment"
        }
    ],
    "sg:phone":"+1 418 567 4021",
    "sg:postcode":"G0H 1H0",
    "sg:province":"QC",
    "wof:name":"Camping Parc DE LA Rive",
    "wof:placetype":"venue"
},
  "geometry": {"coordinates":[-68.376801,49.118931],"type":"Point"}
}