{
  "type": "Feature",
  "properties": {
    "iso:country":"CA",
    "sg:address":"8 Rue Paris",
    "sg:city":"Gatineau",
    "sg:classifiers":[
        {
            "category":"Building & Trades",
            "subcategory":"Plumbing",
            "type":"Services"
        }
    ],
    "sg:phone":"+1 819 669 5825",
    "sg:postcode":"J8P 1Y2",
    "sg:province":"QC",
    "sg:tags":[
        "conditioning",
        "air",
        "system",
        "contractor"
    ],
    "wof:name":"Ferblanterie pa Robillard Inc",
    "wof:placetype":"venue"
},
  "geometry": {"coordinates":[-75.6022186279,45.4908905029],"type":"Point"}
}