{
  "type": "Feature",
  "properties": {
    "addr:full":"Montreal QC H4Z 1A1",
    "addr:postcode":"h4z 1a1",
    "iso:country":"CA",
    "sg:city":"Montreal",
    "sg:classifiers":[
        {
            "category":"Banks & Credit Unions",
            "subcategory":"Investment Brokerage",
            "type":"Services"
        }
    ],
    "sg:phone":"+1 514 874 0070",
    "sg:postcode":"H4Z 1A1",
    "sg:province":"QC",
    "sg:tags":[
        "stock",
        "exchange"
    ],
    "wof:name":"Coporation Canadienne DE Comp",
    "wof:placetype":"venue"
},
  "geometry": {"coordinates":[-73.560776,45.500938],"type":"Point"}
}