{
  "type": "Feature",
  "properties": {
    "addr:full":"New Liskeard ON P0J 1P0",
    "addr:postcode":"p0j 1p0",
    "iso:country":"CA",
    "sg:city":"New Liskeard",
    "sg:classifiers":[
        {
            "category":"Freight",
            "type":"Transportation"
        }
    ],
    "sg:phone":"+1 705 647 5823",
    "sg:postcode":"P0J 1P0",
    "sg:province":"ON",
    "sg:tags":[
        "excavating",
        "contractor",
        "trucking"
    ],
    "wof:name":"A Miron Topsoil",
    "wof:placetype":"venue"
},
  "geometry": {"coordinates":[-79.699455,47.504883],"type":"Point"}
}