{
  "type": "Feature",
  "properties": {
    "addr:full":"6 Queen St W Mississauga ON L5H 1L4",
    "addr:housenumber":"6",
    "addr:postcode":"l5h 1l4",
    "addr:street":"Queen St W",
    "iso:country":"CA",
    "sg:address":"6 Queen St W",
    "sg:city":"Mississauga",
    "sg:classifiers":[
        {
            "category":"Manufacturing",
            "subcategory":"Food",
            "type":"Manufacturing & Wholesale Goods"
        }
    ],
    "sg:phone":"+1 905 271 9888",
    "sg:postcode":"L5H 1L4",
    "sg:province":"ON",
    "sg:tags":[
        "brewer"
    ],
    "wof:name":"Old Credit Brewing CO Ltd",
    "wof:placetype":"venue"
},
  "geometry": {"coordinates":[-79.59307861329999,43.5497398376],"type":"Point"}
}