{
  "type": "Feature",
  "properties": {
    "addr:full":"Mississauga ON L5A 4E7",
    "addr:postcode":"l5a 4e7",
    "iso:country":"CA",
    "sg:city":"Mississauga",
    "sg:classifiers":[
        {
            "category":"Cinema",
            "subcategory":"Movie Rental",
            "type":"Entertainment"
        }
    ],
    "sg:phone":"+1 905 270 2012",
    "sg:postcode":"L5A 4E7",
    "sg:province":"ON",
    "sg:tags":[
        "leasing",
        "video",
        "disc",
        "tape"
    ],
    "wof:name":"Via Video Intl",
    "wof:placetype":"venue"
},
  "geometry": {"coordinates":[-79.6257400513,43.5871047974],"type":"Point"}
}