{
  "type": "Feature",
  "properties": {
    "addr:full":"1831 Hamilton St New Westminster BC V3M 2P3",
    "addr:housenumber":"1831",
    "addr:postcode":"v3m 2p3",
    "addr:street":"Hamilton St",
    "iso:country":"CA",
    "sg:address":"1831 Hamilton St",
    "sg:city":"New Westminster",
    "sg:classifiers":[
        {
            "category":"Shopping",
            "subcategory":"Computers & Home Electronics",
            "type":"Retail Goods"
        }
    ],
    "sg:phone":"+1 604 522 6200",
    "sg:postcode":"V3M 2P3",
    "sg:province":"BC",
    "sg:tags":[
        "software"
    ],
    "wof:name":"Capilano Computing Systems Ltd",
    "wof:placetype":"venue"
},
  "geometry": {"coordinates":[-122.943893,49.204109],"type":"Point"}
}