{
  "type": "Feature",
  "properties": {
    "addr:full":"Government Rd Yorkton SK S3N 2V7",
    "addr:postcode":"s3n 2v7",
    "addr:street":"Rd",
    "iso:country":"CA",
    "sg:address":"Government Rd",
    "sg:city":"Yorkton",
    "sg:classifiers":[
        {
            "category":"Building & Trades",
            "subcategory":"Construction",
            "type":"Services"
        }
    ],
    "sg:phone":"+1 306 783 5137",
    "sg:postcode":"S3N 2V7",
    "sg:province":"SK",
    "sg:tags":[
        "excavating",
        "contractor",
        "general"
    ],
    "wof:name":"F & G Backhoe Svc",
    "wof:placetype":"venue"
},
  "geometry": {"coordinates":[-102.44987500000001,51.204056],"type":"Point"}
}