{
  "type": "Feature",
  "properties": {
    "addr:full":"1575 Queensway # 19 Prince George BC V2L 1L4",
    "addr:housenumber":"1575;# 19",
    "addr:postcode":"v2l 1l4",
    "addr:street":"Queensway",
    "iso:country":"CA",
    "sg:address":"1575 Queensway # 19",
    "sg:city":"Prince George",
    "sg:classifiers":[
        {
            "category":"Real Estate",
            "subcategory":"Real Estate Operator",
            "type":"Services"
        }
    ],
    "sg:phone":"+1 250 562 3375",
    "sg:postcode":"V2L 1L4",
    "sg:province":"BC",
    "sg:tags":[
        "apartment"
    ],
    "wof:name":"Hardwood Manor",
    "wof:placetype":"venue"
},
  "geometry": {"coordinates":[-122.74245500000001,53.909653],"type":"Point"}
}