{
  "type": "Feature",
  "properties": {
    "addr:full":"5677 Rue Hutchison Montreal QC H2V 4B5",
    "addr:housenumber":"5677",
    "addr:postcode":"h2v 4b5",
    "addr:street":"Rue Hutchison",
    "iso:country":"CA",
    "sg:address":"5677 Rue Hutchison",
    "sg:city":"Montreal",
    "sg:classifiers":[
        {
            "category":"Arts & Performance",
            "subcategory":"Theater",
            "type":"Entertainment"
        }
    ],
    "sg:phone":"+1 514 277 0992",
    "sg:postcode":"H2V 4B5",
    "sg:province":"QC",
    "sg:tags":[
        "talent",
        "agency",
        "casting"
    ],
    "wof:name":"Productions Erika Klusch",
    "wof:placetype":"venue"
},
  "geometry": {"coordinates":[-73.60437774659999,45.5223922729],"type":"Point"}
}