{
  "type": "Feature",
  "properties": {
    "addr:full":"4600 Rue DE Compiegne Saint-Leonard QC H1R 1S7",
    "addr:housenumber":"4600",
    "addr:postcode":"h1r 1s7",
    "addr:street":"Rue De Compiegne",
    "iso:country":"CA",
    "sg:address":"4600 Rue DE Compiegne",
    "sg:city":"Saint-Leonard",
    "sg:classifiers":[
        {
            "category":"Education",
            "subcategory":"School",
            "type":"Public Place"
        }
    ],
    "sg:phone":"+1 514 727 8915",
    "sg:postcode":"H1R 1S7",
    "sg:province":"QC",
    "wof:name":"Ecole Alphonse Pesant",
    "wof:placetype":"venue"
},
  "geometry": {"coordinates":[-73.60430100000001,45.579155],"type":"Point"}
}