{
  "type": "Feature",
  "properties": {
    "iso:country":"CA",
    "sg:address":"14 Church St S",
    "sg:city":"Richmond Hill",
    "sg:classifiers":[
        {
            "category":"Professional",
            "subcategory":"Lawyer & Legal Services",
            "type":"Services"
        }
    ],
    "sg:phone":"+1 905 884 1167",
    "sg:postcode":"L4C 1W2",
    "sg:province":"ON",
    "sg:tags":[
        "attorney"
    ],
    "wof:name":"May, Peter L",
    "wof:placetype":"venue"
},
  "geometry": {"coordinates":[-79.4368591309,43.8756904602],"type":"Point"}
}