{
  "type": "Feature",
  "properties": {
    "addr:full":"709 20th St W Saskatoon SK S7M 0X9",
    "addr:housenumber":"709",
    "addr:postcode":"s7m 0x9",
    "addr:street":"20Th St W",
    "iso:country":"CA",
    "sg:address":"709 20th St W",
    "sg:city":"Saskatoon",
    "sg:classifiers":[
        {
            "category":"Shopping",
            "subcategory":"Computers & Home Electronics",
            "type":"Retail Goods"
        }
    ],
    "sg:phone":"+1 306 933 4484",
    "sg:postcode":"S7M 0X9",
    "sg:province":"SK",
    "sg:tags":[
        "game",
        "video"
    ],
    "wof:name":"Hi-Tech Video Games Traders",
    "wof:placetype":"venue"
},
  "geometry": {"coordinates":[-106.68006099999999,52.126057],"type":"Point"}
}