{
  "type": "Feature",
  "properties": {
    "iso:country":"CA",
    "sg:address":"5929 Davey Dr",
    "sg:city":"Verona",
    "sg:classifiers":[
        {
            "category":"Professional",
            "subcategory":"Lawyer & Legal Services",
            "type":"Services"
        }
    ],
    "sg:phone":"+1 613 374 3362",
    "sg:postcode":"K0H 2W0",
    "sg:province":"ON",
    "sg:tags":[
        "attorney"
    ],
    "wof:name":"Thomson, Alan G",
    "wof:placetype":"venue"
},
  "geometry": {"coordinates":[-76.6942062378,44.4800605774],"type":"Point"}
}