{
  "type": "Feature",
  "properties": {
    "addr:full":"6303 Airport Rd Mississauga ON L4V 1R8",
    "addr:housenumber":"6303",
    "addr:postcode":"l4v 1r8",
    "addr:street":"Airport Rd",
    "iso:country":"CA",
    "sg:address":"6303 Airport Rd",
    "sg:city":"Mississauga",
    "sg:classifiers":[
        {
            "category":"Restaurant",
            "type":"Food & Drink"
        }
    ],
    "sg:phone":"+1 905 405 6700",
    "sg:postcode":"L4V 1R8",
    "sg:province":"ON",
    "sg:tags":[
        "shop",
        "tea",
        "coffee"
    ],
    "wof:name":"Second Cup Ltd",
    "wof:placetype":"venue"
},
  "geometry": {"coordinates":[-79.6246109009,43.6907958984],"type":"Point"}
}