{
  "type": "Feature",
  "properties": {
    "iso:country":"CA",
    "sg:address":"75 Glen Cameron Rd",
    "sg:city":"Thornhill",
    "sg:classifiers":[
        {
            "category":"Shopping",
            "subcategory":"Florist",
            "type":"Retail Goods"
        }
    ],
    "sg:phone":"+1 905 764 6332",
    "sg:postcode":"L3T 1N8",
    "sg:province":"ON",
    "wof:name":"Toronto Florist Shop Inc",
    "wof:placetype":"venue"
},
  "geometry": {"coordinates":[-79.4148635864,43.8067321777],"type":"Point"}
}