{
  "type": "Feature",
  "properties": {
    "iso:country":"CA",
    "sg:address":"770 Guelph Line",
    "sg:city":"Burlington",
    "sg:classifiers":[
        {
            "category":"Retail",
            "subcategory":"Laundry & Dry Cleaning",
            "type":"Services"
        }
    ],
    "sg:phone":"+1 905 632 7700",
    "sg:postcode":"L7R 3N5",
    "sg:province":"ON",
    "sg:tags":[
        "cleaners"
    ],
    "wof:name":"Pioneer Cleaners Ltd",
    "wof:placetype":"venue"
},
  "geometry": {"coordinates":[-79.7962799072,43.3462905884],"type":"Point"}
}