{
  "type": "Feature",
  "properties": {
    "addr:full":"29 Wilson St W Perth ON K7H 2M8",
    "addr:housenumber":"29",
    "addr:postcode":"k7h 2m8",
    "addr:street":"Wilson St W",
    "iso:country":"CA",
    "sg:address":"29 Wilson St W",
    "sg:city":"Perth",
    "sg:classifiers":[
        {
            "category":"Restaurant",
            "type":"Food & Drink"
        }
    ],
    "sg:phone":"+1 613 267 6767",
    "sg:postcode":"K7H 2M8",
    "sg:province":"ON",
    "sg:tags":[
        "out"
    ],
    "wof:name":"Thomasino's Pizza",
    "wof:placetype":"venue"
},
  "geometry": {"coordinates":[-76.253799,44.901657],"type":"Point"}
}