{
  "type": "Feature",
  "properties": {
    "addr:full":"Surrey BC V3W 0N6",
    "addr:postcode":"v3w 0n6",
    "iso:country":"CA",
    "sg:city":"Surrey",
    "sg:classifiers":[
        {
            "category":"Shopping",
            "type":"Retail Goods"
        }
    ],
    "sg:phone":"+1 604 501 2739",
    "sg:postcode":"V3W 0N6",
    "sg:province":"BC",
    "sg:tags":[
        "equipment",
        "beer",
        "supply"
    ],
    "wof:name":"Scott Road Brewing CO Ltd",
    "wof:placetype":"venue"
},
  "geometry": {"coordinates":[-122.848526001,49.139339447],"type":"Point"}
}