{
  "type": "Feature",
  "properties": {
    "addr:full":"167 Av Bernier Roberval QC G8H 1B5",
    "addr:postcode":"g8h 1b5",
    "addr:street":"167 Av Bernier",
    "iso:country":"CA",
    "sg:address":"167 Av Bernier",
    "sg:city":"Roberval",
    "sg:classifiers":[
        {
            "category":"Retail",
            "subcategory":"Laundry & Dry Cleaning",
            "type":"Services"
        }
    ],
    "sg:phone":"+1 418 275 1321",
    "sg:postcode":"G8H 1B5",
    "sg:province":"QC",
    "sg:tags":[
        "cleaners"
    ],
    "wof:name":"Buanerrie Beaudet Ltee",
    "wof:placetype":"venue"
},
  "geometry": {"coordinates":[-72.2223739624,48.5071144104],"type":"Point"}
}