{
  "type": "Feature",
  "properties": {
    "addr:full":"465 Rue Saint-Jean-Baptiste Beloeil QC J3G 2V9",
    "addr:housenumber":"465",
    "addr:postcode":"j3g 2v9",
    "addr:street":"Rue Saint-Jean-Baptiste",
    "iso:country":"CA",
    "sg:address":"465 Rue Saint-Jean-Baptiste",
    "sg:city":"Beloeil",
    "sg:classifiers":[
        {
            "category":"Real Estate",
            "subcategory":"Real Estate Agent",
            "type":"Services"
        }
    ],
    "sg:phone":"+1 450 467 0552",
    "sg:postcode":"J3G 2V9",
    "sg:province":"QC",
    "sg:tags":[
        "authorities",
        "housing"
    ],
    "wof:name":"Office Municipal D'Habitation",
    "wof:placetype":"venue"
},
  "geometry": {"coordinates":[-73.20611599999999,45.573921],"type":"Point"}
}