{
  "type": "Feature",
  "properties": {
    "addr:full":"Vancouver BC V6H 3N3",
    "addr:postcode":"v6h 3n3",
    "iso:country":"CA",
    "sg:city":"Vancouver",
    "sg:classifiers":[
        {
            "category":"Professional",
            "subcategory":"Management & Consulting",
            "type":"Services"
        }
    ],
    "sg:phone":"+1 604 732 1290",
    "sg:postcode":"V6H 3N3",
    "sg:province":"BC",
    "sg:tags":[
        "communications",
        "consultant"
    ],
    "wof:name":"Saperstein & Assoc Ltd",
    "wof:placetype":"venue"
},
  "geometry": {"coordinates":[-123.126907,49.260872],"type":"Point"}
}