{
  "type": "Feature",
  "properties": {
    "addr:full":"2020 Av Chauveau Quebec QC G2C 1V1",
    "addr:housenumber":"2020",
    "addr:postcode":"g2c 1v1",
    "addr:street":"Av Chauveau",
    "iso:country":"CA",
    "sg:address":"2020 Av Chauveau",
    "sg:city":"Quebec",
    "sg:classifiers":[
        {
            "category":"Personal",
            "type":"Services"
        }
    ],
    "sg:phone":"+1 418 847 3402",
    "sg:postcode":"G2C 1V1",
    "sg:province":"QC",
    "sg:tags":[
        "baby",
        "sitter"
    ],
    "wof:name":"Cpe Aux Poussinots D'Alakazou",
    "wof:placetype":"venue"
},
  "geometry": {"coordinates":[-71.32212800000001,46.845303],"type":"Point"}
}