{
  "type": "Feature",
  "properties": {
    "addr:full":"1991 Rue Leonard-DE Vinci Sainte-Julie QC J3E 1Y9",
    "addr:housenumber":"1991",
    "addr:postcode":"j3e 1y9",
    "addr:street":"Rue Leonard-De Vinci",
    "iso:country":"CA",
    "sg:address":"1991 Rue Leonard-DE Vinci",
    "sg:city":"Sainte-Julie",
    "sg:classifiers":[
        {
            "category":"Health Services",
            "subcategory":"Medical Lab",
            "type":"Services"
        }
    ],
    "sg:phone":"+1 450 922 2840",
    "sg:postcode":"J3E 1Y9",
    "sg:province":"QC",
    "wof:name":"Au Centre DE Denturologiste",
    "wof:placetype":"venue"
},
  "geometry": {"coordinates":[-73.331627,45.576508],"type":"Point"}
}