{
  "type": "Feature",
  "properties": {
    "addr:full":"930 Rue DE LA Mairie Blainville QC J7C 3B4",
    "addr:housenumber":"930",
    "addr:postcode":"j7c 3b4",
    "addr:street":"Rue De La Mairie",
    "iso:country":"CA",
    "sg:address":"930 Rue DE LA Mairie",
    "sg:city":"Blainville",
    "sg:classifiers":[
        {
            "category":"Education",
            "subcategory":"School",
            "type":"Public Place"
        }
    ],
    "sg:phone":"+1 450 433 5365",
    "sg:postcode":"J7C 3B4",
    "sg:province":"QC",
    "wof:name":"Ecole DE LA Seigneurie",
    "wof:placetype":"venue"
},
  "geometry": {"coordinates":[-73.87093400000001,45.678951],"type":"Point"}
}