{
  "type": "Feature",
  "properties": {
    "addr:full":"845 Regent St Sudbury ON P3E 4T3",
    "addr:housenumber":"845",
    "addr:postcode":"p3e 4t3",
    "addr:street":"Regent St",
    "iso:country":"CA",
    "sg:address":"845 Regent St",
    "sg:city":"Sudbury",
    "sg:classifiers":[
        {
            "category":"Shopping",
            "type":"Retail Goods"
        }
    ],
    "sg:phone":"+1 705 673 2885",
    "sg:postcode":"P3E 4T3",
    "sg:province":"ON",
    "sg:tags":[
        "supply",
        "equipment",
        "audiologists",
        "hearing",
        "impaired"
    ],
    "wof:name":"Sudbury Audiology Clinic",
    "wof:placetype":"venue"
},
  "geometry": {"coordinates":[-81.0072555542,46.4739341736],"type":"Point"}
}