{
  "type": "Feature",
  "properties": {
    "addr:full":"8300 Place Lorraine Anjou QC H1J 1E6",
    "addr:housenumber":"8300",
    "addr:postcode":"h1j 1e6",
    "addr:street":"Place Lorraine",
    "iso:country":"CA",
    "sg:address":"8300 Place Lorraine",
    "sg:city":"Anjou",
    "sg:classifiers":[
        {
            "category":"Building & Trades",
            "subcategory":"Construction",
            "type":"Services"
        }
    ],
    "sg:phone":"+1 514 493 9000",
    "sg:postcode":"H1J 1E6",
    "sg:province":"QC",
    "sg:tags":[
        "insulation",
        "heat",
        "contractor"
    ],
    "wof:name":"Nadeau Inc",
    "wof:placetype":"venue"
},
  "geometry": {"coordinates":[-73.567322,45.614395],"type":"Point"}
}