{
  "type": "Feature",
  "properties": {
    "iso:country":"CA",
    "sg:address":"602 Metler Rd RR 3",
    "sg:city":"Fenwick",
    "sg:classifiers":[
        {
            "category":"Organizations",
            "subcategory":"Religious Organization",
            "type":"Services"
        }
    ],
    "sg:phone":"+1 905 892 4716",
    "sg:postcode":"L0S 1C0",
    "sg:province":"ON",
    "sg:tags":[
        "church"
    ],
    "wof:name":"First Presbyterian Church",
    "wof:placetype":"venue"
},
  "geometry": {"coordinates":[-79.3574523926,43.0261611938],"type":"Point"}
}