{
  "type": "Feature",
  "properties": {
    "addr:full":"1345 Cheapside St London ON N5V 3N9",
    "addr:housenumber":"1345",
    "addr:postcode":"n5v 3n9",
    "addr:street":"Cheapside St",
    "iso:country":"CA",
    "sg:address":"1345 Cheapside St",
    "sg:city":"London",
    "sg:classifiers":[
        {
            "category":"Professional",
            "type":"Services"
        }
    ],
    "sg:phone":"+1 519 453 9900",
    "sg:postcode":"N5V 3N9",
    "sg:province":"ON",
    "sg:tags":[
        "consultant",
        "sport",
        "establishment"
    ],
    "wof:name":"London Sports Council-Hoop It",
    "wof:placetype":"venue"
},
  "geometry": {"coordinates":[-81.210526,43.014481],"type":"Point"}
}