{
  "type": "Feature",
  "properties": {
    "iso:country":"CA",
    "sg:address":"700 Broadway W",
    "sg:city":"Vancouver",
    "sg:classifiers":[
        {
            "category":"Shopping",
            "subcategory":"Clothing, Apparel, & Fashions",
            "type":"Retail Goods"
        }
    ],
    "sg:phone":"+1 604 873 6810",
    "sg:postcode":"V5Z 1G8",
    "sg:province":"BC",
    "sg:tags":[
        "lingerie"
    ],
    "wof:name":"Dressing Room",
    "wof:placetype":"venue"
},
  "geometry": {"coordinates":[-123.12014770499999,49.2631988525],"type":"Point"}
}