{
  "type": "Feature",
  "properties": {
    "addr:full":"4725 48th St Chetwynd BC V0C 1J0",
    "addr:housenumber":"4725",
    "addr:postcode":"bc v0c 1j0",
    "addr:street":"48Th St",
    "iso:country":"CA",
    "sg:address":"4725 48th St",
    "sg:city":"Chetwynd",
    "sg:classifiers":[
        {
            "category":"Government",
            "subcategory":"Office",
            "type":"Public Place"
        }
    ],
    "sg:phone":"+1 250 788 2407",
    "sg:postcode":"V0C 1J0",
    "sg:province":"BC",
    "sg:tags":[
        "snow",
        "removal"
    ],
    "wof:name":"Peace Country Maintenance Ltd",
    "wof:placetype":"venue"
},
  "geometry": {"coordinates":[-121.61982,55.699127],"type":"Point"}
}