{
  "type": "Feature",
  "properties": {
    "addr:full":"PO Box 134 STN Streetsville Mississauga ON L5M 2B7",
    "addr:housenumber":"po",
    "addr:postcode":"l5m 2b7",
    "addr:street":"Box 134 Stn",
    "iso:country":"CA",
    "sg:address":"PO Box 134 STN Streetsville",
    "sg:city":"Mississauga",
    "sg:classifiers":[
        {
            "category":"Building & Trades",
            "subcategory":"Construction",
            "type":"Services"
        }
    ],
    "sg:phone":"+1 905 821 0600",
    "sg:postcode":"L5M 2B7",
    "sg:province":"ON",
    "sg:tags":[
        "paving",
        "contractor"
    ],
    "wof:name":"Tony Battista Paving Inc",
    "wof:placetype":"venue"
},
  "geometry": {"coordinates":[-79.64372253419999,43.5882835388],"type":"Point"}
}