{
  "type": "Feature",
  "properties": {
    "iso:country":"CA",
    "sg:address":"3 Geneva St",
    "sg:city":"St Catharines",
    "sg:classifiers":[
        {
            "category":"Health Services",
            "subcategory":"Chiropractor",
            "type":"Services"
        }
    ],
    "sg:phone":"+1 905 641 3000",
    "sg:postcode":"L2R 4M2",
    "sg:province":"ON",
    "wof:name":"Drynan & Assoc",
    "wof:placetype":"venue"
},
  "geometry": {"coordinates":[-79.240067,43.159565],"type":"Point"}
}