{
  "type": "Feature",
  "properties": {
    "iso:country":"CA",
    "sg:address":"5 Cross St",
    "sg:city":"Riverside-Albert",
    "sg:classifiers":[
        {
            "category":"Organizations",
            "subcategory":"Religious Organization",
            "type":"Services"
        }
    ],
    "sg:phone":"+1 506 882 2820",
    "sg:postcode":"E4H 3Z4",
    "sg:province":"NB",
    "sg:tags":[
        "church"
    ],
    "wof:name":"United Church of Canada",
    "wof:placetype":"venue"
},
  "geometry": {"coordinates":[-64.7284164429,45.7519798279],"type":"Point"}
}