{
  "type": "Feature",
  "properties": {
    "iso:country":"CA",
    "sg:city":"Winnipeg",
    "sg:classifiers":[
        {
            "category":"Personal",
            "type":"Services"
        }
    ],
    "sg:phone":"+1 204 783 9139",
    "sg:postcode":"R3H 1B1",
    "sg:province":"MB",
    "sg:tags":[
        "genealogist"
    ],
    "wof:name":"Manitoba Genealogical Society",
    "wof:placetype":"venue"
},
  "geometry": {"coordinates":[-97.200317,49.895367],"type":"Point"}
}