{
  "type": "Feature",
  "properties": {
    "addr:full":"Vimont QC H7M 2P4",
    "addr:postcode":"h7m 2p4",
    "iso:country":"CA",
    "sg:city":"Vimont",
    "sg:classifiers":[
        {
            "category":"Health Services",
            "subcategory":"Doctor",
            "type":"Services"
        }
    ],
    "sg:phone":"+1 450 669 7421",
    "sg:postcode":"H7M 2P4",
    "sg:province":"QC",
    "sg:tags":[
        "dentist"
    ],
    "wof:name":"Clinique Dentaire Eric Lajoie",
    "wof:placetype":"venue"
},
  "geometry": {"coordinates":[-73.7230148315,45.5976600647],"type":"Point"}
}