{
  "type": "Feature",
  "properties": {
    "iso:country":"CA",
    "sg:address":"182 Boul Iberville",
    "sg:city":"Repentigny",
    "sg:classifiers":[
        {
            "category":"Banks & Credit Unions",
            "subcategory":"Bank",
            "type":"Services"
        }
    ],
    "sg:phone":"+1 450 585 5555",
    "sg:postcode":"J6A 1Y8",
    "sg:province":"QC",
    "wof:name":"Caisse Populaire Repentigny",
    "wof:placetype":"venue"
},
  "geometry": {"coordinates":[-73.4704742432,45.720199585],"type":"Point"}
}