{
  "type": "Feature",
  "properties": {
    "addr:full":"215 Rue Saint-Paul Beloeil QC J3G 2W8",
    "addr:housenumber":"215",
    "addr:postcode":"j3g 2w8",
    "addr:street":"Rue Saint-Paul",
    "iso:country":"CA",
    "sg:address":"215 Rue Saint-Paul",
    "sg:city":"Beloeil",
    "sg:classifiers":[
        {
            "category":"Building & Trades",
            "subcategory":"Construction",
            "type":"Services"
        }
    ],
    "sg:phone":"+1 450 467 2159",
    "sg:postcode":"J3G 2W8",
    "sg:province":"QC",
    "sg:tags":[
        "downspouts",
        "siding",
        "gutter",
        "contractor"
    ],
    "wof:name":"Prefontaine Aluminium",
    "wof:placetype":"venue"
},
  "geometry": {"coordinates":[-73.2027435303,45.5731506348],"type":"Point"}
}