{
  "type": "Feature",
  "properties": {
    "addr:full":"304 Guelph St Georgetown ON L7G 4B1",
    "addr:housenumber":"304",
    "addr:postcode":"l7g 4b1",
    "addr:street":"Guelph St",
    "iso:country":"CA",
    "sg:address":"304 Guelph St",
    "sg:city":"Georgetown",
    "sg:classifiers":[
        {
            "category":"Banks & Credit Unions",
            "subcategory":"Bank",
            "type":"Services"
        }
    ],
    "sg:phone":"+1 905 877 6995",
    "sg:postcode":"L7G 4B1",
    "sg:province":"ON",
    "wof:name":"Scotiabank",
    "wof:placetype":"venue"
},
  "geometry": {"coordinates":[-79.894188,43.649643],"type":"Point"}
}