{
  "type": "Feature",
  "properties": {
    "addr:full":"320 Av Laurendeau Montreal-Est QC H1B 5X6",
    "addr:housenumber":"320",
    "addr:postcode":"h1b 5x6",
    "addr:street":"Av Laurendeau",
    "iso:country":"CA",
    "sg:address":"320 Av Laurendeau",
    "sg:city":"Montreal-Est",
    "sg:classifiers":[
        {
            "category":"Local Transit",
            "type":"Transportation"
        }
    ],
    "sg:phone":"+1 514 640 4270",
    "sg:postcode":"H1B 5X6",
    "sg:province":"QC",
    "sg:tags":[
        "limousine"
    ],
    "wof:name":"Gestion Helene Maurice",
    "wof:placetype":"venue"
},
  "geometry": {"coordinates":[-73.50730896,45.6327590942],"type":"Point"}
}