{
  "type": "Feature",
  "properties": {
    "addr:full":"1060 116 Rte Acton Vale QC J0H 1A0",
    "addr:housenumber":"1060",
    "addr:postcode":"j0h 1a0",
    "addr:street":"116 Rte",
    "iso:country":"CA",
    "sg:address":"1060 116 Rte",
    "sg:city":"Acton Vale",
    "sg:classifiers":[
        {
            "category":"Building & Trades",
            "subcategory":"Landscaping Services",
            "type":"Services"
        }
    ],
    "sg:phone":"+1 450 549 4317",
    "sg:postcode":"J0H 1A0",
    "sg:province":"QC",
    "sg:tags":[
        "center",
        "garden",
        "landscape",
        "contractor"
    ],
    "wof:name":"Jardins Champetres",
    "wof:placetype":"venue"
},
  "geometry": {"coordinates":[-72.42334700000001,45.629257],"type":"Point"}
}