{
  "type": "Feature",
  "properties": {
    "iso:country":"CA",
    "sg:address":"370 Newcastle Blvd",
    "sg:city":"Miramichi",
    "sg:classifiers":[
        {
            "category":"Organizations",
            "subcategory":"Religious Organization",
            "type":"Services"
        }
    ],
    "sg:phone":"+1 506 622 5720",
    "sg:postcode":"E1V 2J9",
    "sg:province":"NB",
    "sg:tags":[
        "church"
    ],
    "wof:name":"St Mary's Roman Catholic",
    "wof:placetype":"venue"
},
  "geometry": {"coordinates":[-65.568489,47.005428],"type":"Point"}
}