{
  "type": "Feature",
  "properties": {
    "addr:full":"15 Manitoba St Bracebridge ON P1L 1S4",
    "addr:housenumber":"15",
    "addr:postcode":"p1l 1s4",
    "addr:street":"Manitoba St",
    "iso:country":"CA",
    "sg:address":"15 Manitoba St",
    "sg:city":"Bracebridge",
    "sg:classifiers":[
        {
            "category":"Government",
            "subcategory":"Police Station",
            "type":"Public Place"
        }
    ],
    "sg:phone":"+1 705 645 5765",
    "sg:postcode":"P1L 1S4",
    "sg:province":"ON",
    "sg:tags":[
        "department"
    ],
    "wof:name":"Community Policing Office",
    "wof:placetype":"venue"
},
  "geometry": {"coordinates":[-79.309074,45.040676],"type":"Point"}
}