{
  "type": "Feature",
  "properties": {
    "addr:full":"1016 Pleasant Park Rd Ottawa ON K1G 2A1",
    "addr:housenumber":"1016",
    "addr:postcode":"k1g 2a1",
    "addr:street":"Pleasant Park Rd",
    "iso:country":"CA",
    "sg:address":"1016 Pleasant Park Rd",
    "sg:city":"Ottawa",
    "sg:classifiers":[
        {
            "category":"Food & Beverages",
            "subcategory":"Groceries & Convenience Stores",
            "type":"Retail Goods"
        }
    ],
    "sg:phone":"+1 613 731 8258",
    "sg:postcode":"K1G 2A1",
    "sg:province":"ON",
    "wof:name":"Ainee's Convenience Store",
    "wof:placetype":"venue"
},
  "geometry": {"coordinates":[-75.6227798462,45.3951950073],"type":"Point"}
}