{
  "type": "Feature",
  "properties": {
    "iso:country":"CA",
    "sg:city":"Fitzroy Harbour",
    "sg:classifiers":[
        {
            "category":"Building & Trades",
            "subcategory":"Electrical",
            "type":"Services"
        }
    ],
    "sg:phone":"+1 613 769 5434",
    "sg:postcode":"K0A 1X0",
    "sg:province":"ON",
    "sg:tags":[
        "electric",
        "contractor"
    ],
    "wof:name":"Barry's Electric",
    "wof:placetype":"venue"
},
  "geometry": {"coordinates":[-76.2173156738,45.4731712341],"type":"Point"}
}