{
  "type": "Feature",
  "properties": {
    "addr:full":"8 Hazelton Rd Doaktown NB E9C 1N6",
    "addr:housenumber":"8",
    "addr:postcode":"e9c 1n6",
    "addr:street":"Hazelton Rd",
    "iso:country":"CA",
    "sg:address":"8 Hazelton Rd",
    "sg:city":"Doaktown",
    "sg:classifiers":[
        {
            "category":"Organizations",
            "subcategory":"Religious Organization",
            "type":"Services"
        }
    ],
    "sg:phone":"+1 506 365 7943",
    "sg:postcode":"E9C 1N6",
    "sg:province":"NB",
    "sg:tags":[
        "church"
    ],
    "wof:name":"First Pentecostal Church",
    "wof:placetype":"venue"
},
  "geometry": {"coordinates":[-66.12949399999999,46.570724],"type":"Point"}
}