{
  "type": "Feature",
  "properties": {
    "addr:full":"Delta BC V3M 6M4",
    "addr:postcode":"v3m 6m4",
    "iso:country":"CA",
    "sg:city":"Delta",
    "sg:classifiers":[
        {
            "category":"Shopping",
            "subcategory":"Bicycles & Sporting Goods",
            "type":"Retail Goods"
        }
    ],
    "sg:phone":"+1 604 527 9942",
    "sg:postcode":"V3M 6M4",
    "sg:province":"BC",
    "sg:tags":[
        "gun",
        "gunsmith"
    ],
    "wof:name":"Dlask Arms Corp",
    "wof:placetype":"venue"
},
  "geometry": {"coordinates":[-122.962738,49.162266],"type":"Point"}
}