{
  "type": "Feature",
  "properties": {
    "addr:full":"Pickering ON L1V 5R1",
    "addr:postcode":"l1v 5r1",
    "iso:country":"CA",
    "sg:city":"Pickering",
    "sg:classifiers":[
        {
            "category":"Autos & Motor Vehicles",
            "subcategory":"Fuel & Gas Station",
            "type":"Retail Goods"
        }
    ],
    "sg:phone":"+1 905 427 4002",
    "sg:postcode":"L1V 5R1",
    "sg:province":"ON",
    "sg:tags":[
        "oil"
    ],
    "wof:name":"Shell Canada Ltd",
    "wof:placetype":"venue"
},
  "geometry": {"coordinates":[-79.0757217407,43.8469467163],"type":"Point"}
}