{
  "type": "Feature",
  "properties": {
    "iso:country":"CA",
    "sg:address":"34 Cumberland St N # 400",
    "sg:city":"Thunder Bay",
    "sg:classifiers":[
        {
            "category":"Social Services",
            "subcategory":"Child Care",
            "type":"Services"
        }
    ],
    "sg:phone":"+1 807 684 2651",
    "sg:postcode":"P7A 8B9",
    "sg:province":"ON",
    "sg:tags":[
        "government"
    ],
    "wof:name":"Thunder Bay Children's Svc",
    "wof:placetype":"venue"
},
  "geometry": {"coordinates":[-89.2187194824,48.4356384277],"type":"Point"}
}