{
  "type": "Feature",
  "properties": {
    "addr:full":"62 Harbour Dr Conche NL A0K 1Y0",
    "addr:housenumber":"62",
    "addr:postcode":"a0k 1y0",
    "addr:street":"Harbour Dr",
    "iso:country":"CA",
    "sg:address":"62 Harbour Dr",
    "sg:city":"Conche",
    "sg:classifiers":[
        {
            "category":"Food & Beverages",
            "subcategory":"Groceries & Convenience Stores",
            "type":"Retail Goods"
        }
    ],
    "sg:phone":"+1 709 622 3100",
    "sg:postcode":"A0K 1Y0",
    "sg:province":"NL",
    "wof:name":"K & L Variety",
    "wof:placetype":"venue"
},
  "geometry": {"coordinates":[-55.894951,50.896282],"type":"Point"}
}