{
  "type": "Feature",
  "properties": {
    "addr:full":"107 4 Ave SW Manning AB T0H 2M0",
    "addr:housenumber":"107",
    "addr:postcode":"manning ab t0h 2m0",
    "addr:street":"4 Ave Sw",
    "iso:country":"CA",
    "sg:address":"107 4 Ave SW",
    "sg:city":"Manning",
    "sg:classifiers":[
        {
            "category":"Insurance",
            "subcategory":"Insurance Agent",
            "type":"Services"
        }
    ],
    "sg:phone":"+1 780 836 3061",
    "sg:postcode":"T0H 2M0",
    "sg:province":"AB",
    "wof:name":"Stone Insurance Brokers Ltd",
    "wof:placetype":"venue"
},
  "geometry": {"coordinates":[-117.631309509,56.9211425781],"type":"Point"}
}