{
  "type": "Feature",
  "properties": {
    "addr:full":"1000 Innovation Dr. Ottawa Ontario K2K 3E7",
    "addr:housenumber":"1000",
    "addr:postcode":"k2k 3e7",
    "addr:street":"Innovation Dr.",
    "iso:country":"CA",
    "sg:address":"1000 Innovation Dr.",
    "sg:city":"Ottawa Ontario",
    "sg:classifiers":[
        {
            "category":"Professional",
            "subcategory":"Computer Services",
            "type":"Services"
        }
    ],
    "sg:postcode":"K2K 3E7",
    "sg:tags":[
        "optical-networking-solutions",
        "multiprotocol-services",
        "ethernet-services"
    ],
    "sg:website":"http://www.btisystems.com/",
    "wof:name":"BTI Systems",
    "wof:placetype":"venue"
},
  "geometry": {"coordinates":[-75.817511,45.3281942],"type":"Point"}
}