{
  "type": "Feature",
  "properties": {
    "addr:full":"Winnipeg MB R2H 3G1",
    "addr:postcode":"r2h 3g1",
    "iso:country":"CA",
    "sg:city":"Winnipeg",
    "sg:classifiers":[
        {
            "category":"Health Services",
            "subcategory":"Nursing And Care Facility",
            "type":"Services"
        }
    ],
    "sg:phone":"+1 204 233 0501",
    "sg:postcode":"R2H 3G1",
    "sg:province":"MB",
    "sg:tags":[
        "home",
        "retirement",
        "community"
    ],
    "wof:name":"Accueil Colombien Inc",
    "wof:placetype":"venue"
},
  "geometry": {"coordinates":[-97.121094,49.891285],"type":"Point"}
}