{
  "type": "Feature",
  "properties": {
    "addr:full":"41 Mcclellan St Tweed ON K0K 3J0",
    "addr:housenumber":"41",
    "addr:postcode":"k0k 3j0",
    "addr:street":"Mcclellan St",
    "iso:country":"CA",
    "sg:address":"41 Mcclellan St",
    "sg:city":"Tweed",
    "sg:classifiers":[
        {
            "category":"Health Services",
            "subcategory":"Doctor",
            "type":"Services"
        }
    ],
    "sg:phone":"+1 613 478 1211",
    "sg:postcode":"K0K 3J0",
    "sg:province":"ON",
    "sg:tags":[
        "physician",
        "surgeon"
    ],
    "wof:name":"Moher, Kelly MD",
    "wof:placetype":"venue"
},
  "geometry": {"coordinates":[-77.316185,44.47393],"type":"Point"}
}