{
  "type": "Feature",
  "properties": {
    "addr:full":"1006 Hwy 16 Bypass North Battleford SK S9A 3W2",
    "addr:housenumber":"1006",
    "addr:postcode":"s9a 3w2",
    "addr:street":"Hwy 16 Bypass",
    "iso:country":"CA",
    "sg:address":"1006 Hwy 16 Bypass",
    "sg:city":"North Battleford",
    "sg:classifiers":[
        {
            "category":"Travel",
            "subcategory":"Hotels & Motels",
            "type":"Entertainment"
        }
    ],
    "sg:phone":"+1 306 446 8888",
    "sg:postcode":"S9A 3W2",
    "sg:province":"SK",
    "wof:name":"A Super 8 Motel",
    "wof:placetype":"venue"
},
  "geometry": {"coordinates":[-108.24073799999999,52.743614],"type":"Point"}
}