{
  "type": "Feature",
  "properties": {
    "iso:country":"CA",
    "sg:city":"High Prairie",
    "sg:classifiers":[
        {
            "category":"Wholesale",
            "subcategory":"Electrical",
            "type":"Manufacturing & Wholesale Goods"
        }
    ],
    "sg:phone":"+1 780 523 3200",
    "sg:postcode":"T0G 1E0",
    "sg:province":"AB",
    "sg:tags":[
        "fire",
        "equipment",
        "protection"
    ],
    "wof:name":"Save It Store",
    "wof:placetype":"venue"
},
  "geometry": {"coordinates":[-116.496070862,55.435836792],"type":"Point"}
}