{
  "type": "Feature",
  "properties": {
    "iso:country":"CA",
    "sg:city":"Edmonton",
    "sg:classifiers":[
        {
            "category":"Health Services",
            "subcategory":"Health Practitioner",
            "type":"Services"
        }
    ],
    "sg:phone":"+1 780 437 7414",
    "sg:postcode":"T6H 5K4",
    "sg:province":"AB",
    "sg:tags":[
        "counseling",
        "psychologist"
    ],
    "wof:name":"Matheson Counselling & Mdtn",
    "wof:placetype":"venue"
},
  "geometry": {"coordinates":[-113.578094482,53.4941749573],"type":"Point"}
}