{
  "type": "Feature",
  "properties": {
    "addr:full":"2733 6th Ave W Vancouver BC V6K 1W9",
    "addr:housenumber":"2733",
    "addr:postcode":"v6k 1w9",
    "addr:street":"6Th Ave W",
    "iso:country":"CA",
    "sg:address":"2733 6th Ave W",
    "sg:city":"Vancouver",
    "sg:classifiers":[
        {
            "category":"Professional",
            "subcategory":"Art Services",
            "type":"Services"
        }
    ],
    "sg:phone":"+1 604 322 6854",
    "sg:postcode":"V6K 1W9",
    "sg:province":"BC",
    "sg:tags":[
        "graphic",
        "designer"
    ],
    "wof:name":"Nouwens Graphic Arts Inc",
    "wof:placetype":"venue"
},
  "geometry": {"coordinates":[-123.16706085200001,49.2667694092],"type":"Point"}
}