{
  "type": "Feature",
  "properties": {
    "iso:country":"CA",
    "sg:address":"1135 Lakeshore Rd",
    "sg:city":"Sarnia",
    "sg:classifiers":[
        {
            "category":"Personal",
            "subcategory":"Beauty Salon",
            "type":"Services"
        }
    ],
    "sg:phone":"+1 519 542 4617",
    "sg:postcode":"N7V 2V5",
    "sg:province":"ON",
    "wof:name":"Lorraine's Hair Styling",
    "wof:placetype":"venue"
},
  "geometry": {"coordinates":[-82.366493,43.014351],"type":"Point"}
}