{
  "type": "Feature",
  "properties": {
    "addr:full":"200 Rue Cremazie O Quebec QC G1R 1X9",
    "addr:housenumber":"200",
    "addr:postcode":"g1r 1x9",
    "addr:street":"Rue Cremazie O",
    "iso:country":"CA",
    "sg:address":"200 Rue Cremazie O",
    "sg:city":"Quebec",
    "sg:classifiers":[
        {
            "category":"Shopping",
            "subcategory":"Computers & Home Electronics",
            "type":"Retail Goods"
        }
    ],
    "sg:phone":"+1 418 529 4471",
    "sg:postcode":"G1R 1X9",
    "sg:province":"QC",
    "sg:tags":[
        "radio",
        "television",
        "electronic",
        "equipment"
    ],
    "wof:name":"Multi Electronique Enr",
    "wof:placetype":"venue"
},
  "geometry": {"coordinates":[-71.2293395996,46.8038597107],"type":"Point"}
}