{
  "type": "Feature",
  "properties": {
    "addr:full":"611 Sundial Dr Orillia ON L3V 6K5",
    "addr:housenumber":"611",
    "addr:postcode":"l3v 6k5",
    "addr:street":"Sundial Dr",
    "iso:country":"CA",
    "sg:address":"611 Sundial Dr",
    "sg:city":"Orillia",
    "sg:classifiers":[
        {
            "category":"Autos & Motor Vehicles",
            "subcategory":"Automobile Sales",
            "type":"Retail Goods"
        }
    ],
    "sg:phone":"+1 705 325 4000",
    "sg:postcode":"L3V 6K5",
    "sg:province":"ON",
    "sg:tags":[
        "car",
        "dealer"
    ],
    "wof:name":"Sunrise Toyota",
    "wof:placetype":"venue"
},
  "geometry": {"coordinates":[-79.424667,44.638809],"type":"Point"}
}