{
  "type": "Feature",
  "properties": {
    "addr:full":"69 Grand Meadow Cres NW Edmonton AB T6L 1A3",
    "addr:housenumber":"69",
    "addr:postcode":"t6l 1a3",
    "addr:street":"Grand Meadow Cres Nw",
    "iso:country":"CA",
    "sg:address":"69 Grand Meadow Cres NW",
    "sg:city":"Edmonton",
    "sg:classifiers":[
        {
            "category":"Organizations",
            "subcategory":"Professional Association",
            "type":"Services"
        }
    ],
    "sg:phone":"+1 780 462 8879",
    "sg:postcode":"T6L 1A3",
    "sg:province":"AB",
    "wof:name":"Canadian Council of the Blind",
    "wof:placetype":"venue"
},
  "geometry": {"coordinates":[-113.431122,53.476467],"type":"Point"}
}