{
  "type": "Feature",
  "properties": {
    "addr:full":"Hwy 144 Dowling ON P0M 1R0",
    "addr:postcode":"p0m 1r0",
    "addr:street":"Hwy 144 Dowling",
    "iso:country":"CA",
    "sg:address":"Hwy 144",
    "sg:city":"Dowling",
    "sg:classifiers":[
        {
            "category":"Organizations",
            "subcategory":"Religious Organization",
            "type":"Services"
        }
    ],
    "sg:phone":"+1 705 855 3571",
    "sg:postcode":"P0M 1R0",
    "sg:province":"ON",
    "sg:tags":[
        "church"
    ],
    "wof:name":"Larchwood Bible Chapel",
    "wof:placetype":"venue"
},
  "geometry": {"coordinates":[-81.34623718260001,46.5859909058],"type":"Point"}
}