{
  "type": "Feature",
  "properties": {
    "addr:full":"26 Benson Ave Richmond Hill ON L4C 4E6",
    "addr:housenumber":"26",
    "addr:postcode":"l4c 4e6",
    "addr:street":"Benson Ave",
    "iso:country":"CA",
    "sg:address":"26 Benson Ave",
    "sg:city":"Richmond Hill",
    "sg:classifiers":[
        {
            "category":"Professional",
            "subcategory":"Management & Consulting",
            "type":"Services"
        }
    ],
    "sg:phone":"+1 905 737 0911",
    "sg:postcode":"L4C 4E6",
    "sg:province":"ON",
    "sg:tags":[
        "marketing",
        "consultant"
    ],
    "wof:name":"Innovagency Inc",
    "wof:placetype":"venue"
},
  "geometry": {"coordinates":[-79.440704,43.880325],"type":"Point"}
}