{
  "type": "Feature",
  "properties": {
    "iso:country":"CA",
    "sg:address":"111 Rue Child",
    "sg:city":"Coaticook",
    "sg:classifiers":[
        {
            "category":"Shopping",
            "subcategory":"Computers & Home Electronics",
            "type":"Retail Goods"
        }
    ],
    "sg:phone":"+1 819 849 3799",
    "sg:postcode":"J1A 2B2",
    "sg:province":"QC",
    "sg:tags":[
        "equipment",
        "dealer"
    ],
    "wof:name":"Coaticook Informatique Inc",
    "wof:placetype":"venue"
},
  "geometry": {"coordinates":[-71.80461120610001,45.133972168],"type":"Point"}
}