{
  "type": "Feature",
  "properties": {
    "addr:full":"1725 27 Ave NE Calgary AB T2E 7E1",
    "addr:housenumber":"1725",
    "addr:postcode":"t2e 7e1",
    "addr:street":"27 Ave Ne",
    "iso:country":"CA",
    "sg:address":"1725 27 Ave NE",
    "sg:city":"Calgary",
    "sg:classifiers":[
        {
            "category":"Building & Trades",
            "subcategory":"Electrical",
            "type":"Services"
        }
    ],
    "sg:phone":"+1 403 291 3303",
    "sg:postcode":"T2E 7E1",
    "sg:province":"AB",
    "sg:tags":[
        "electric",
        "contractor"
    ],
    "wof:name":"Custom Electric Ltd",
    "wof:placetype":"venue"
},
  "geometry": {"coordinates":[-114.018013,51.076759],"type":"Point"}
}