{
  "type": "Feature",
  "properties": {
    "addr:full":"340 Brooksbank Ave # 110 North Vancouver BC V7J 2C1",
    "addr:housenumber":"340",
    "addr:postcode":"v7j 2c1",
    "addr:street":"Brooksbank Ave # 110",
    "iso:country":"CA",
    "sg:address":"340 Brooksbank Ave # 110",
    "sg:city":"North Vancouver",
    "sg:classifiers":[
        {
            "category":"Home & Garden",
            "subcategory":"Building Materials",
            "type":"Retail Goods"
        }
    ],
    "sg:phone":"+1 604 903 4185",
    "sg:postcode":"V7J 2C1",
    "sg:province":"BC",
    "sg:tags":[
        "glass",
        "window",
        "plate"
    ],
    "wof:name":"Speedy Auto & Window Glass",
    "wof:placetype":"venue"
},
  "geometry": {"coordinates":[-123.04025300000001,49.308842],"type":"Point"}
}