{
  "type": "Feature",
  "properties": {
    "addr:full":"39 King St E Hagersville ON N0A 1H0",
    "addr:housenumber":"39",
    "addr:postcode":"n0a 1h0",
    "addr:street":"King St E",
    "iso:country":"CA",
    "sg:address":"39 King St E",
    "sg:city":"Hagersville",
    "sg:classifiers":[
        {
            "category":"Health Services",
            "subcategory":"Medical Lab",
            "type":"Services"
        }
    ],
    "sg:phone":"+1 905 768 3432",
    "sg:postcode":"N0A 1H0",
    "sg:province":"ON",
    "wof:name":"Denture Clinic",
    "wof:placetype":"venue"
},
  "geometry": {"coordinates":[-80.047562,42.960667],"type":"Point"}
}