{
  "type": "Feature",
  "properties": {
    "addr:full":"4819 45th St Hwy 11 E Rocky Mountain House AB T4T 1A9",
    "addr:housenumber":"4819",
    "addr:postcode":"t4t 1a9",
    "addr:street":"45Th St Hwy 11 E",
    "iso:country":"CA",
    "sg:address":"4819 45th St Hwy 11 E",
    "sg:city":"Rocky Mountain House",
    "sg:classifiers":[
        {
            "category":"Travel",
            "subcategory":"Hotels & Motels",
            "type":"Entertainment"
        }
    ],
    "sg:phone":"+1 403 845 2804",
    "sg:postcode":"T4T 1A9",
    "sg:province":"AB",
    "wof:name":"Walking Eagle Motor Inn",
    "wof:placetype":"venue"
},
  "geometry": {"coordinates":[-114.931236,52.37759],"type":"Point"}
}