{
  "type": "Feature",
  "properties": {
    "addr:full":"399 Sackville St Toronto ON M4X 1S6",
    "addr:housenumber":"399",
    "addr:postcode":"m4x 1s6",
    "addr:street":"Sackville St",
    "iso:country":"CA",
    "sg:address":"399 Sackville St",
    "sg:city":"Toronto",
    "sg:classifiers":[
        {
            "category":"Professional",
            "type":"Services"
        }
    ],
    "sg:phone":"+1 416 927 1501",
    "sg:postcode":"M4X 1S6",
    "sg:province":"ON",
    "sg:tags":[
        "art",
        "restoring"
    ],
    "wof:name":"Investors Art Svc Inc",
    "wof:placetype":"venue"
},
  "geometry": {"coordinates":[-79.36499000000001,43.665482],"type":"Point"}
}