{
  "type": "Feature",
  "properties": {
    "addr:full":"399 Boul Sainte-Madeleine Cap-DE-LA-Madeleine QC G8T 3M7",
    "addr:housenumber":"399",
    "addr:postcode":"g8t 3m7",
    "addr:street":"Boul Sainte-Madeleine",
    "iso:country":"CA",
    "sg:address":"399 Boul Sainte-Madeleine",
    "sg:city":"Cap-DE-LA-Madeleine",
    "sg:classifiers":[
        {
            "category":"Government",
            "subcategory":"Office",
            "type":"Public Place"
        }
    ],
    "sg:phone":"+1 819 375 7022",
    "sg:postcode":"G8T 3M7",
    "sg:province":"QC",
    "wof:name":"Quebec Societe DE L'Assurance",
    "wof:placetype":"venue"
},
  "geometry": {"coordinates":[-72.5051116943,46.3689727783],"type":"Point"}
}