{
  "type": "Feature",
  "properties": {
    "addr:full":"8 Country Rd L'Anse Au Clair NL A0K 3K0",
    "addr:housenumber":"8",
    "addr:postcode":"a0k 3k0",
    "addr:street":"Country Rd;Au",
    "iso:country":"CA",
    "sg:address":"8 Country Rd",
    "sg:city":"L'Anse Au Clair",
    "sg:classifiers":[
        {
            "category":"Shopping",
            "subcategory":"Gifts & Souvenirs",
            "type":"Retail Goods"
        }
    ],
    "sg:phone":"+1 709 931 2186",
    "sg:postcode":"A0K 3K0",
    "sg:province":"NL",
    "sg:tags":[
        "shop"
    ],
    "wof:name":"Moores Handicrafts",
    "wof:placetype":"venue"
},
  "geometry": {"coordinates":[-57.0641479492,51.4317092896],"type":"Point"}
}