{
  "type": "Feature",
  "properties": {
    "addr:full":"15 Phipps St Gore Bay ON P0P 1H0",
    "addr:housenumber":"15",
    "addr:postcode":"p0p 1h0",
    "addr:street":"Phipps St",
    "iso:country":"CA",
    "sg:address":"15 Phipps St",
    "sg:city":"Gore Bay",
    "sg:classifiers":[
        {
            "category":"Retail",
            "subcategory":"Auto Repair",
            "type":"Services"
        }
    ],
    "sg:phone":"+1 705 282 2091",
    "sg:postcode":"P0P 1H0",
    "sg:province":"ON",
    "sg:tags":[
        "body",
        "automobile",
        "painting"
    ],
    "wof:name":"Jewell's Collision Centre",
    "wof:placetype":"venue"
},
  "geometry": {"coordinates":[-82.46550000000001,45.917213],"type":"Point"}
}