{
  "type": "Feature",
  "properties": {
    "iso:country":"CA",
    "sg:address":"1981 Davenport Rd",
    "sg:city":"Toronto",
    "sg:classifiers":[
        {
            "category":"Shopping",
            "subcategory":"Pharmacy",
            "type":"Retail Goods"
        }
    ],
    "sg:phone":"+1 416 657 1500",
    "sg:postcode":"M6N 1C5",
    "sg:province":"ON",
    "wof:name":"Sky's Drug Store",
    "wof:placetype":"venue"
},
  "geometry": {"coordinates":[-79.4571609497,43.6700973511],"type":"Point"}
}