{
  "type": "Feature",
  "properties": {
    "addr:full":"Whitecourt AB T7S 1M2",
    "addr:postcode":"t7s 1m2",
    "iso:country":"CA",
    "sg:city":"Whitecourt",
    "sg:classifiers":[
        {
            "category":"Real Estate",
            "subcategory":"Real Estate Operator",
            "type":"Services"
        }
    ],
    "sg:phone":"+1 780 778 4341",
    "sg:postcode":"T7S 1M2",
    "sg:province":"AB",
    "sg:tags":[
        "apartment"
    ],
    "wof:name":"Valley Apartments",
    "wof:placetype":"venue"
},
  "geometry": {"coordinates":[-115.673721,54.141193],"type":"Point"}
}