{
  "type": "Feature",
  "properties": {
    "iso:country":"CA",
    "sg:city":"West Vancouver",
    "sg:classifiers":[
        {
            "category":"Wholesale",
            "subcategory":"Electrical",
            "type":"Manufacturing & Wholesale Goods"
        }
    ],
    "sg:phone":"+1 604 913 6662",
    "sg:postcode":"V7T 1E2",
    "sg:province":"BC",
    "sg:tags":[
        "sound",
        "equipment",
        "system"
    ],
    "wof:name":"Mothers Music",
    "wof:placetype":"venue"
},
  "geometry": {"coordinates":[-123.133781,49.32814],"type":"Point"}
}