{
  "type": "Feature",
  "properties": {
    "addr:full":"780 Landslide Rd Sault Ste Marie ON P6A 6J8",
    "addr:housenumber":"780",
    "addr:postcode":"p6a 6j8",
    "addr:street":"Landslide Rd",
    "iso:country":"CA",
    "sg:address":"780 Landslide Rd",
    "sg:city":"Sault Ste Marie",
    "sg:classifiers":[
        {
            "category":"Recreation",
            "type":"Entertainment"
        }
    ],
    "sg:phone":"+1 705 759 1920",
    "sg:postcode":"P6A 6J8",
    "sg:province":"ON",
    "sg:tags":[
        "hall",
        "auditorium"
    ],
    "wof:name":"Kinsmen Hall",
    "wof:placetype":"venue"
},
  "geometry": {"coordinates":[-84.27965500000001,46.589485],"type":"Point"}
}