{
  "type": "Feature",
  "properties": {
    "addr:full":"2055 Vallee Lourdes Dr Bathurst NB E2A 4P8",
    "addr:housenumber":"2055",
    "addr:postcode":"e2a 4p8",
    "addr:street":"Vallee Lourdes Dr",
    "iso:country":"CA",
    "sg:address":"2055 Vallee Lourdes Dr",
    "sg:city":"Bathurst",
    "sg:classifiers":[
        {
            "category":"Home & Garden",
            "subcategory":"Home Furnishings",
            "type":"Retail Goods"
        }
    ],
    "sg:phone":"+1 506 549 5070",
    "sg:postcode":"E2A 4P8",
    "sg:province":"NB",
    "sg:tags":[
        "convalescent",
        "fireplace",
        "nursing"
    ],
    "wof:name":"Foyer Notre Dame DE Lourdes",
    "wof:placetype":"venue"
},
  "geometry": {"coordinates":[-65.6893463135,47.6529846191],"type":"Point"}
}