{
  "type": "Feature",
  "properties": {
    "addr:full":"36 Mayfair Cres Brampton ON L6S 3N4",
    "addr:housenumber":"36",
    "addr:postcode":"l6s 3n4",
    "addr:street":"Mayfair Cres",
    "iso:country":"CA",
    "sg:address":"36 Mayfair Cres",
    "sg:city":"Brampton",
    "sg:classifiers":[
        {
            "category":"Building & Trades",
            "subcategory":"Plumbing",
            "type":"Services"
        }
    ],
    "sg:phone":"+1 905 793 5510",
    "sg:postcode":"L6S 3N4",
    "sg:province":"ON",
    "sg:tags":[
        "contractor"
    ],
    "wof:name":"Jenstan Plumbing & Heating CO",
    "wof:placetype":"venue"
},
  "geometry": {"coordinates":[-79.73603057859999,43.7306442261],"type":"Point"}
}