{
  "type": "Feature",
  "properties": {
    "addr:full":"Lac LA Biche AB T0A 2C0",
    "addr:postcode":"t0a 2c0",
    "iso:country":"CA",
    "sg:city":"Lac LA Biche",
    "sg:classifiers":[
        {
            "category":"Shopping",
            "subcategory":"Discount & Variety Stores",
            "type":"Retail Goods"
        }
    ],
    "sg:phone":"+1 780 623 2825",
    "sg:postcode":"T0A 2C0",
    "sg:province":"AB",
    "wof:name":"Lac LA Biche Dollar Store",
    "wof:placetype":"venue"
},
  "geometry": {"coordinates":[-111.980804443,54.7686309814],"type":"Point"}
}