{
  "type": "Feature",
  "properties": {
    "addr:full":"2940 Forest Glade Dr Windsor ON N8R 1L5",
    "addr:housenumber":"2940",
    "addr:postcode":"n8r 1l5",
    "addr:street":"Forest Glade Dr",
    "iso:country":"CA",
    "sg:address":"2940 Forest Glade Dr",
    "sg:city":"Windsor",
    "sg:classifiers":[
        {
            "category":"Organizations",
            "subcategory":"Religious Organization",
            "type":"Services"
        }
    ],
    "sg:phone":"+1 519 735 6023",
    "sg:postcode":"N8R 1L5",
    "sg:province":"ON",
    "sg:tags":[
        "church"
    ],
    "wof:name":"Parish of the Atonement Church",
    "wof:placetype":"venue"
},
  "geometry": {"coordinates":[-82.915657,42.309551],"type":"Point"}
}