{
  "type": "Feature",
  "properties": {
    "addr:full":"102 Doric Ave Nanaimo BC V9R 3N2",
    "addr:housenumber":"102",
    "addr:postcode":"v9r 3n2",
    "addr:street":"Doric Ave",
    "iso:country":"CA",
    "sg:address":"102 Doric Ave",
    "sg:city":"Nanaimo",
    "sg:classifiers":[
        {
            "category":"Professional",
            "subcategory":"Credit Reporting & Collection",
            "type":"Services"
        }
    ],
    "sg:phone":"+1 250 753 7729",
    "sg:postcode":"V9R 3N2",
    "sg:province":"BC",
    "sg:tags":[
        "agency"
    ],
    "wof:name":"J Mc Millan Bailiff & Cllctn",
    "wof:placetype":"venue"
},
  "geometry": {"coordinates":[-123.957886,49.169144],"type":"Point"}
}