{
  "type": "Feature",
  "properties": {
    "iso:country":"CA",
    "sg:address":"199 Rue Principale",
    "sg:city":"Les Coteaux",
    "sg:classifiers":[
        {
            "category":"Professional",
            "subcategory":"Management & Consulting",
            "type":"Services"
        }
    ],
    "sg:phone":"+1 450 267 1999",
    "sg:postcode":"J7X 1A1",
    "sg:province":"QC",
    "sg:tags":[
        "development",
        "international",
        "industrial",
        "consultant"
    ],
    "wof:name":"Regie Intermunicipale Du Canal",
    "wof:placetype":"venue"
},
  "geometry": {"coordinates":[-74.2091369629,45.2568016052],"type":"Point"}
}