{
  "type": "Feature",
  "properties": {
    "addr:full":"1538 22nd Ave E Vancouver BC V5N 2P1",
    "addr:housenumber":"1538",
    "addr:postcode":"v5n 2p1",
    "addr:street":"22Nd Ave E",
    "iso:country":"CA",
    "sg:address":"1538 22nd Ave E",
    "sg:city":"Vancouver",
    "sg:classifiers":[
        {
            "category":"Social Services",
            "type":"Services"
        }
    ],
    "sg:phone":"+1 604 875 8935",
    "sg:postcode":"V5N 2P1",
    "sg:province":"BC",
    "sg:tags":[
        "organization",
        "welfare"
    ],
    "wof:name":"Coast Foundation Society",
    "wof:placetype":"venue"
},
  "geometry": {"coordinates":[-123.07254791299999,49.2503623962],"type":"Point"}
}