{
  "type": "Feature",
  "properties": {
    "addr:full":"53 Jamieson Ave Orillia ON L3V 6H1",
    "addr:housenumber":"53",
    "addr:postcode":"l3v 6h1",
    "addr:street":"Jamieson Ave",
    "iso:country":"CA",
    "sg:address":"53 Jamieson Ave",
    "sg:city":"Orillia",
    "sg:classifiers":[
        {
            "category":"Building & Trades",
            "subcategory":"Plumbing",
            "type":"Services"
        }
    ],
    "sg:phone":"+1 705 326 5572",
    "sg:postcode":"L3V 6H1",
    "sg:province":"ON",
    "sg:tags":[
        "heating",
        "contractor"
    ],
    "wof:name":"Palmer's Heating & Air Cond",
    "wof:placetype":"venue"
},
  "geometry": {"coordinates":[-79.43497499999999,44.594288],"type":"Point"}
}