{
  "type": "Feature",
  "properties": {
    "addr:full":"5955 200 St Langley BC V3A 1N2",
    "addr:housenumber":"5955",
    "addr:postcode":"v3a 1n2",
    "addr:street":"200 St",
    "iso:country":"CA",
    "sg:address":"5955 200 St",
    "sg:city":"Langley",
    "sg:classifiers":[
        {
            "category":"Wholesale",
            "subcategory":"Machinery & Supplies",
            "type":"Manufacturing & Wholesale Goods"
        }
    ],
    "sg:phone":"+1 604 530 9701",
    "sg:postcode":"V3A 1N2",
    "sg:province":"BC",
    "sg:tags":[
        "equipment",
        "welding"
    ],
    "wof:name":"Air Liquide Canada",
    "wof:placetype":"venue"
},
  "geometry": {"coordinates":[-122.66877746599999,49.1104125977],"type":"Point"}
}