{
  "type": "Feature",
  "properties": {
    "iso:country":"CA",
    "sg:address":"2557 Maynard St",
    "sg:city":"Halifax",
    "sg:classifiers":[
        {
            "category":"Social Services",
            "subcategory":"Child Care",
            "type":"Services"
        }
    ],
    "sg:phone":"+1 902 423 4702",
    "sg:postcode":"B3K 3V6",
    "sg:province":"NS",
    "wof:name":"Halifax Developmental Pre-Schl",
    "wof:placetype":"venue"
},
  "geometry": {"coordinates":[-63.591839,44.655895],"type":"Point"}
}