{
  "type": "Feature",
  "properties": {
    "iso:country":"CA",
    "sg:city":"Edmonton",
    "sg:classifiers":[
        {
            "category":"Banks & Credit Unions",
            "subcategory":"Investment Brokerage",
            "type":"Services"
        }
    ],
    "sg:phone":"+1 780 429 6775",
    "sg:postcode":"T5H 3E8",
    "sg:province":"AB",
    "sg:tags":[
        "consultant",
        "planning",
        "financial"
    ],
    "wof:name":"Ron Graham & Assoc",
    "wof:placetype":"venue"
},
  "geometry": {"coordinates":[-113.51197052000001,53.5494689941],"type":"Point"}
}