{
  "type": "Feature",
  "properties": {
    "addr:full":"111 Rue Poirier Amos QC J9T 3R4",
    "addr:housenumber":"111",
    "addr:postcode":"j9t 3r4",
    "addr:street":"Rue Poirier",
    "iso:country":"CA",
    "sg:address":"111 Rue Poirier",
    "sg:city":"Amos",
    "sg:classifiers":[
        {
            "category":"Real Estate",
            "subcategory":"Real Estate Operator",
            "type":"Services"
        }
    ],
    "sg:phone":"+1 819 732 5090",
    "sg:postcode":"J9T 3R4",
    "sg:province":"QC",
    "sg:tags":[
        "apartment"
    ],
    "wof:name":"Immeubles Pins Vert Inc",
    "wof:placetype":"venue"
},
  "geometry": {"coordinates":[-78.10962677000001,48.5635643005],"type":"Point"}
}