{
  "type": "Feature",
  "properties": {
    "addr:full":"365 8th Conc Ruthven ON N0P 2G0",
    "addr:housenumber":"365",
    "addr:postcode":"n0p 2g0",
    "addr:street":"8Th Conc",
    "iso:country":"CA",
    "sg:address":"365 8th Conc",
    "sg:city":"Ruthven",
    "sg:classifiers":[
        {
            "category":"Building & Trades",
            "subcategory":"Plumbing",
            "type":"Services"
        }
    ],
    "sg:phone":"+1 519 326 4820",
    "sg:postcode":"N0P 2G0",
    "sg:province":"ON",
    "sg:tags":[
        "septic"
    ],
    "wof:name":"Cottam Sanitation",
    "wof:placetype":"venue"
},
  "geometry": {"coordinates":[-82.67202,42.051914],"type":"Point"}
}