{
  "type": "Feature",
  "properties": {
    "iso:country":"CA",
    "sg:address":"651 Boul Industriel",
    "sg:city":"Blainville",
    "sg:classifiers":[
        {
            "category":"Manufacturing",
            "subcategory":"Building Materials",
            "type":"Manufacturing & Wholesale Goods"
        }
    ],
    "sg:phone":"+1 450 435 6911",
    "sg:postcode":"J7C 3V3",
    "sg:province":"QC",
    "wof:name":"Distribution Can Wel Ltee",
    "wof:placetype":"venue"
},
  "geometry": {"coordinates":[-73.8544769287,45.6660614014],"type":"Point"}
}