{
  "type": "Feature",
  "properties": {
    "addr:full":"Brampton ON L6W 3R9",
    "addr:postcode":"l6w 3r9",
    "iso:country":"CA",
    "sg:city":"Brampton",
    "sg:classifiers":[
        {
            "category":"Shopping",
            "subcategory":"Crafts & Fabrics",
            "type":"Retail Goods"
        }
    ],
    "sg:phone":"+1 905 874 1564",
    "sg:postcode":"L6W 3R9",
    "sg:province":"ON",
    "sg:tags":[
        "shop",
        "machine",
        "sewing"
    ],
    "wof:name":"Brampton Sew 'N Serge Ctr",
    "wof:placetype":"venue"
},
  "geometry": {"coordinates":[-79.7246170044,43.6856155396],"type":"Point"}
}