{
  "type": "Feature",
  "properties": {
    "iso:country":"CA",
    "sg:address":"4324 Brisebois Dr NW",
    "sg:city":"Calgary",
    "sg:classifiers":[
        {
            "category":"Wholesale",
            "subcategory":"Electrical",
            "type":"Manufacturing & Wholesale Goods"
        }
    ],
    "sg:phone":"+1 403 269 2457",
    "sg:postcode":"T2L 2G2",
    "sg:province":"AB",
    "sg:tags":[
        "control"
    ],
    "wof:name":"Thelco Mechanical Svc Ltd",
    "wof:placetype":"venue"
},
  "geometry": {"coordinates":[-114.12953949,51.0921936035],"type":"Point"}
}