{
  "type": "Feature",
  "properties": {
    "addr:full":"1429 Chalice Cres Mississauga ON L5C 1S2",
    "addr:housenumber":"1429",
    "addr:postcode":"l5c 1s2",
    "addr:street":"Chalice Cres",
    "iso:country":"CA",
    "sg:address":"1429 Chalice Cres",
    "sg:city":"Mississauga",
    "sg:classifiers":[
        {
            "category":"Food & Beverages",
            "subcategory":"Specialty",
            "type":"Retail Goods"
        }
    ],
    "sg:phone":"+1 905 277 3704",
    "sg:postcode":"L5C 1S2",
    "sg:province":"ON",
    "sg:tags":[
        "health",
        "diet"
    ],
    "wof:name":"Shaklee Independent Distr",
    "wof:placetype":"venue"
},
  "geometry": {"coordinates":[-79.6660308838,43.5629348755],"type":"Point"}
}