{
  "type": "Feature",
  "properties": {
    "addr:full":"301 Frederick St Kitchener ON N2H 2N6",
    "addr:housenumber":"301",
    "addr:postcode":"n2h 2n6",
    "addr:street":"Frederick St",
    "iso:country":"CA",
    "sg:address":"301 Frederick St",
    "sg:city":"Kitchener",
    "sg:classifiers":[
        {
            "category":"Banks & Credit Unions",
            "subcategory":"Bank",
            "type":"Services"
        }
    ],
    "sg:phone":"+1 519 579 7526",
    "sg:postcode":"N2H 2N6",
    "sg:province":"ON",
    "sg:tags":[
        "financing",
        "bankruptcy",
        "trustee"
    ],
    "wof:name":"Credit & Debt Svc",
    "wof:placetype":"venue"
},
  "geometry": {"coordinates":[-80.4773483276,43.4558677673],"type":"Point"}
}