{
  "type": "Feature",
  "properties": {
    "addr:full":"Edmonton AB T5J 2W4",
    "addr:postcode":"t5j 2w4",
    "iso:country":"CA",
    "sg:city":"Edmonton",
    "sg:classifiers":[
        {
            "category":"Organizations",
            "subcategory":"Professional Association",
            "type":"Services"
        }
    ],
    "sg:phone":"+1 780 428 6146",
    "sg:postcode":"T5J 2W4",
    "sg:province":"AB",
    "wof:name":"Urban Development Institute",
    "wof:placetype":"venue"
},
  "geometry": {"coordinates":[-113.497749,53.541157],"type":"Point"}
}