{
  "type": "Feature",
  "properties": {
    "addr:full":"440 Pearl St Burlington ON L7R 2N1",
    "addr:housenumber":"440",
    "addr:postcode":"l7r 2n1",
    "addr:street":"Pearl St",
    "iso:country":"CA",
    "sg:address":"440 Pearl St",
    "sg:city":"Burlington",
    "sg:classifiers":[
        {
            "category":"Personal",
            "type":"Services"
        }
    ],
    "sg:phone":"+1 905 639 1440",
    "sg:postcode":"L7R 2N1",
    "sg:province":"ON",
    "sg:tags":[
        "yoga",
        "instruction",
        "program",
        "fitness",
        "exercise",
        "physical"
    ],
    "wof:name":"Four Forty Fitness For Women",
    "wof:placetype":"venue"
},
  "geometry": {"coordinates":[-79.79573059080001,43.3270797729],"type":"Point"}
}