{
  "type": "Feature",
  "properties": {
    "addr:full":"155 Ferndale Dr S Barrie ON L4N 6X9",
    "addr:housenumber":"155",
    "addr:postcode":"l4n 6x9",
    "addr:street":"Ferndale Dr S",
    "iso:country":"CA",
    "sg:address":"155 Ferndale Dr S",
    "sg:city":"Barrie",
    "sg:classifiers":[
        {
            "category":"Professional",
            "subcategory":"Computer Services",
            "type":"Services"
        }
    ],
    "sg:phone":"+1 705 733 7750",
    "sg:postcode":"L4N 6X9",
    "sg:province":"ON",
    "sg:tags":[
        "consultant"
    ],
    "wof:name":"Summerley Computer Systems Inc",
    "wof:placetype":"venue"
},
  "geometry": {"coordinates":[-79.7153549194,44.3593025208],"type":"Point"}
}