{
  "type": "Feature",
  "properties": {
    "addr:full":"45 Harbour Sq Toronto ON M5J 2G4",
    "addr:housenumber":"45",
    "addr:postcode":"m5j 2g4",
    "addr:street":"Harbour Sq",
    "iso:country":"CA",
    "sg:address":"45 Harbour Sq",
    "sg:city":"Toronto",
    "sg:classifiers":[
        {
            "category":"Recreation",
            "subcategory":"Marina",
            "type":"Entertainment"
        }
    ],
    "sg:phone":"+1 416 203 1055",
    "sg:postcode":"M5J 2G4",
    "sg:province":"ON",
    "sg:tags":[
        "repairing",
        "boat"
    ],
    "wof:name":"Toronto Island Marina",
    "wof:placetype":"venue"
},
  "geometry": {"coordinates":[-79.378883,43.640175],"type":"Point"}
}