{
  "type": "Feature",
  "properties": {
    "addr:full":"Calgary AB T2A 6W9",
    "addr:postcode":"t2a 6w9",
    "iso:country":"CA",
    "sg:city":"Calgary",
    "sg:classifiers":[
        {
            "category":"Professional",
            "subcategory":"Management & Consulting",
            "type":"Services"
        }
    ],
    "sg:phone":"+1 403 235 4007",
    "sg:postcode":"T2A 6W9",
    "sg:province":"AB",
    "sg:tags":[
        "consultant",
        "safety"
    ],
    "wof:name":"Moduspec",
    "wof:placetype":"venue"
},
  "geometry": {"coordinates":[-113.98932600000001,51.047443],"type":"Point"}
}