{
  "type": "Feature",
  "properties": {
    "addr:full":"8542 Hwy 97 S Quesnel BC V2J 6M4",
    "addr:housenumber":"8542",
    "addr:postcode":"v2j 6m4",
    "addr:street":"Hwy 97 S",
    "iso:country":"CA",
    "sg:address":"8542 Hwy 97 S",
    "sg:city":"Quesnel",
    "sg:classifiers":[
        {
            "category":"Retail",
            "subcategory":"Repair Shop",
            "type":"Services"
        }
    ],
    "sg:phone":"+1 250 747 8350",
    "sg:postcode":"V2J 6M4",
    "sg:province":"BC",
    "sg:tags":[
        "welding"
    ],
    "wof:name":"Glen's Welding & Fab",
    "wof:placetype":"venue"
},
  "geometry": {"coordinates":[-122.49508667000001,53.0151901245],"type":"Point"}
}