{
  "type": "Feature",
  "properties": {
    "addr:full":"416 Hwy 36 Lindsay ON K9V 4R3",
    "addr:housenumber":"416",
    "addr:postcode":"k9v 4r3",
    "addr:street":"Hwy 36",
    "iso:country":"CA",
    "sg:address":"416 Hwy 36",
    "sg:city":"Lindsay",
    "sg:classifiers":[
        {
            "category":"Social Services",
            "type":"Services"
        }
    ],
    "sg:phone":"+1 705 328 0949",
    "sg:postcode":"K9V 4R3",
    "sg:province":"ON",
    "sg:tags":[
        "organization",
        "welfare"
    ],
    "wof:name":"Moore Foster Homes",
    "wof:placetype":"venue"
},
  "geometry": {"coordinates":[-78.72268699999999,44.369144],"type":"Point"}
}