{
  "type": "Feature",
  "properties": {
    "iso:country":"CA",
    "sg:address":"265 Bernard Ave",
    "sg:city":"Kelowna",
    "sg:classifiers":[
        {
            "category":"Shopping",
            "subcategory":"Department Store",
            "type":"Retail Goods"
        }
    ],
    "sg:phone":"+1 250 763 1513",
    "sg:postcode":"V1Y 6N2",
    "sg:province":"BC",
    "sg:tags":[
        "shop"
    ],
    "wof:name":"Welk Mart",
    "wof:placetype":"venue"
},
  "geometry": {"coordinates":[-119.497497559,49.8861694336],"type":"Point"}
}