{
  "type": "Feature",
  "properties": {
    "addr:full":"Valcourt QC J0E 2L0",
    "addr:postcode":"j0e 2l0",
    "iso:country":"CA",
    "sg:city":"Valcourt",
    "sg:classifiers":[
        {
            "category":"Health Services",
            "subcategory":"Optometrist",
            "type":"Services"
        }
    ],
    "sg:phone":"+1 450 532 5552",
    "sg:postcode":"J0E 2L0",
    "sg:province":"QC",
    "wof:name":"Vision Expert",
    "wof:placetype":"venue"
},
  "geometry": {"coordinates":[-72.30861663819999,45.4885292053],"type":"Point"}
}