{
  "type": "Feature",
  "properties": {
    "addr:full":"1099 Kingston Rd Pickering ON L1V 1B5",
    "addr:housenumber":"1099",
    "addr:postcode":"l1v 1b5",
    "addr:street":"Kingston Rd",
    "iso:country":"CA",
    "sg:address":"1099 Kingston Rd",
    "sg:city":"Pickering",
    "sg:classifiers":[
        {
            "category":"Organizations",
            "subcategory":"Religious Organization",
            "type":"Services"
        }
    ],
    "sg:phone":"+1 905 420 9123",
    "sg:postcode":"L1V 1B5",
    "sg:province":"ON",
    "wof:name":"Christian Missionary Alliance",
    "wof:placetype":"venue"
},
  "geometry": {"coordinates":[-79.09833500000001,43.829014],"type":"Point"}
}