{
  "type": "Feature",
  "properties": {
    "addr:full":"14965 Stony Plain Rd NW Edmonton AB T5P 4W1",
    "addr:housenumber":"14965",
    "addr:postcode":"t5p 4w1",
    "addr:street":"Stony Plain Rd Nw",
    "iso:country":"CA",
    "sg:address":"14965 Stony Plain Rd NW",
    "sg:city":"Edmonton",
    "sg:classifiers":[
        {
            "category":"Health Services",
            "subcategory":"Doctor",
            "type":"Services"
        }
    ],
    "sg:phone":"+1 780 484 3931",
    "sg:postcode":"T5P 4W1",
    "sg:province":"AB",
    "sg:tags":[
        "dentist"
    ],
    "wof:name":"Zell, Merrill A DDS",
    "wof:placetype":"venue"
},
  "geometry": {"coordinates":[-113.580315,53.541191],"type":"Point"}
}