{
  "type": "Feature",
  "properties": {
    "iso:country":"CA",
    "sg:address":"315 Cambie St",
    "sg:city":"Vancouver",
    "sg:classifiers":[
        {
            "category":"Shopping",
            "subcategory":"Clothing, Apparel, & Fashions",
            "type":"Retail Goods"
        }
    ],
    "sg:phone":"+1 604 687 1908",
    "sg:postcode":"V6B 2N4",
    "sg:province":"BC",
    "sg:tags":[
        "designer"
    ],
    "wof:name":"Venus & Mars Universal Clthng",
    "wof:placetype":"venue"
},
  "geometry": {"coordinates":[-123.10942077599999,49.2833251953],"type":"Point"}
}