{
  "type": "Feature",
  "properties": {
    "addr:full":"Richmond BC V7E 3R3",
    "addr:postcode":"v7e 3r3",
    "iso:country":"CA",
    "sg:city":"Richmond",
    "sg:classifiers":[
        {
            "category":"Manufacturing",
            "subcategory":"Chemicals & Compounds",
            "type":"Manufacturing & Wholesale Goods"
        }
    ],
    "sg:phone":"+1 604 448 5577",
    "sg:postcode":"V7E 3R3",
    "sg:province":"BC",
    "sg:tags":[
        "cleaning"
    ],
    "wof:name":"R & P Distributing",
    "wof:placetype":"venue"
},
  "geometry": {"coordinates":[-123.154678,49.115524],"type":"Point"}
}