{
  "type": "Feature",
  "properties": {
    "addr:full":"713 Glencairn Ave North York ON M6B 1Z8",
    "addr:housenumber":"713",
    "addr:postcode":"m6b 1z8",
    "addr:street":"Glencairn Ave",
    "iso:country":"CA",
    "sg:address":"713 Glencairn Ave",
    "sg:city":"North York",
    "sg:classifiers":[
        {
            "category":"Organizations",
            "subcategory":"Religious Organization",
            "type":"Services"
        }
    ],
    "sg:phone":"+1 416 789 0124",
    "sg:postcode":"M6B 1Z8",
    "sg:province":"ON",
    "sg:tags":[
        "church"
    ],
    "wof:name":"Glencairn Baptist Church",
    "wof:placetype":"venue"
},
  "geometry": {"coordinates":[-79.4380874634,43.7100563049],"type":"Point"}
}