{
  "type": "Feature",
  "properties": {
    "addr:full":"180 1st Ave S Chesley ON N0G 1L0",
    "addr:housenumber":"180",
    "addr:postcode":"n0g 1l0",
    "addr:street":"1St Ave S Chesley",
    "iso:country":"CA",
    "sg:address":"180 1st Ave S",
    "sg:city":"Chesley",
    "sg:classifiers":[
        {
            "category":"Autos & Motor Vehicles",
            "subcategory":"Automobile Sales",
            "type":"Retail Goods"
        }
    ],
    "sg:phone":"+1 519 363 2572",
    "sg:postcode":"N0G 1L0",
    "sg:province":"ON",
    "sg:tags":[
        "cart"
    ],
    "wof:name":"Manny's Motorcycles & Acces",
    "wof:placetype":"venue"
},
  "geometry": {"coordinates":[-81.0946731567,44.2954864502],"type":"Point"}
}