{
  "type": "Feature",
  "properties": {
    "iso:country":"CA",
    "sg:address":"2885 Strata Crt",
    "sg:city":"Mississauga",
    "sg:classifiers":[
        {
            "category":"Shopping",
            "subcategory":"Catalog Store",
            "type":"Retail Goods"
        }
    ],
    "sg:phone":"+1 905 824 2786",
    "sg:postcode":"L5N 6K5",
    "sg:province":"ON",
    "sg:tags":[
        "mail",
        "order",
        "internet"
    ],
    "wof:name":"Grant Barrington & Sons Export",
    "wof:placetype":"venue"
},
  "geometry": {"coordinates":[-79.77736663819999,43.5954971313],"type":"Point"}
}