{
  "type": "Feature",
  "properties": {
    "addr:full":"2282 Ridge Ch Huntingdon QC J0S 1H0",
    "addr:housenumber":"2282",
    "addr:postcode":"j0s 1h0",
    "addr:street":"Ridge Ch",
    "iso:country":"CA",
    "sg:address":"2282 Ridge Ch",
    "sg:city":"Huntingdon",
    "sg:classifiers":[
        {
            "category":"Government",
            "subcategory":"Office",
            "type":"Public Place"
        }
    ],
    "sg:phone":"+1 450 264 3465",
    "sg:postcode":"J0S 1H0",
    "sg:province":"QC",
    "sg:tags":[
        "village"
    ],
    "wof:name":"Caserne D'Incendie",
    "wof:placetype":"venue"
},
  "geometry": {"coordinates":[-74.1729049683,45.0881462097],"type":"Point"}
}