{
  "type": "Feature",
  "properties": {
    "iso:country":"CA",
    "sg:city":"Blainville",
    "sg:classifiers":[
        {
            "category":"Manufacturing",
            "subcategory":"Tools & Machinery",
            "type":"Manufacturing & Wholesale Goods"
        }
    ],
    "sg:phone":"+1 450 430 4206",
    "sg:postcode":"J7C 2H5",
    "sg:province":"QC",
    "sg:tags":[
        "ventilating",
        "equipment"
    ],
    "wof:name":"Ferblanterie Val Royal Inc",
    "wof:placetype":"venue"
},
  "geometry": {"coordinates":[-73.851326,45.654778],"type":"Point"}
}