{
  "type": "Feature",
  "properties": {
    "addr:full":"85 South Edgeware Rd St Thomas ON N5P 2H7",
    "addr:housenumber":"85",
    "addr:postcode":"n5p 2h7",
    "addr:street":"South Edgeware Rd",
    "iso:country":"CA",
    "sg:address":"85 South Edgeware Rd",
    "sg:city":"St Thomas",
    "sg:classifiers":[
        {
            "category":"Health Services",
            "subcategory":"Health Practitioner",
            "type":"Services"
        }
    ],
    "sg:phone":"+1 519 633 7329",
    "sg:postcode":"N5P 2H7",
    "sg:province":"ON",
    "sg:tags":[
        "physiotherapist"
    ],
    "wof:name":"Spine & Joint Physiotherapy",
    "wof:placetype":"venue"
},
  "geometry": {"coordinates":[-81.17375183110001,42.7928924561],"type":"Point"}
}