{
  "type": "Feature",
  "properties": {
    "addr:full":"506 Burnside Rd W Victoria BC V8Z 1M5",
    "addr:housenumber":"506",
    "addr:postcode":"v8z 1m5",
    "addr:street":"Burnside Rd W",
    "iso:country":"CA",
    "sg:address":"506 Burnside Rd W",
    "sg:city":"Victoria",
    "sg:classifiers":[
        {
            "category":"Government",
            "subcategory":"Office",
            "type":"Public Place"
        }
    ],
    "sg:phone":"+1 250 363 0600",
    "sg:postcode":"V8Z 1M5",
    "sg:province":"BC",
    "wof:name":"Canada Natural Resources",
    "wof:placetype":"venue"
},
  "geometry": {"coordinates":[-123.37342099999999,48.444092],"type":"Point"}
}