{
  "type": "Feature",
  "properties": {
    "iso:country":"CA",
    "sg:address":"52 St Andrews St",
    "sg:city":"Antigonish",
    "sg:classifiers":[
        {
            "category":"Autos & Motor Vehicles",
            "subcategory":"Auto Supplies",
            "type":"Retail Goods"
        }
    ],
    "sg:phone":"+1 902 863 6111",
    "sg:postcode":"B2G 2H1",
    "sg:province":"NS",
    "sg:tags":[
        "automobile",
        "parts"
    ],
    "wof:name":"Napa Auto Parts",
    "wof:placetype":"venue"
},
  "geometry": {"coordinates":[-61.9831428528,45.6233177185],"type":"Point"}
}