{
  "type": "Feature",
  "properties": {
    "addr:full":"1667 Regional Rd 97 Freelton ON L0R 1K0",
    "addr:housenumber":"1667;97",
    "addr:postcode":"l0r 1k0",
    "addr:street":"Regional Rd",
    "iso:country":"CA",
    "sg:address":"1667 Regional Rd 97",
    "sg:city":"Freelton",
    "sg:classifiers":[
        {
            "category":"Government",
            "subcategory":"Office",
            "type":"Public Place"
        }
    ],
    "sg:phone":"+1 905 659 7715",
    "sg:postcode":"L0R 1K0",
    "sg:province":"ON",
    "sg:tags":[
        "campground",
        "village"
    ],
    "wof:name":"Valens Conservation Area",
    "wof:placetype":"venue"
},
  "geometry": {"coordinates":[-80.0391464233,43.4004554749],"type":"Point"}
}