{
  "type": "Feature",
  "properties": {
    "addr:full":"77 Queensway E Simcoe ON N3Y 4M5",
    "addr:housenumber":"77",
    "addr:postcode":"n3y 4m5",
    "addr:street":"Queensway E",
    "iso:country":"CA",
    "sg:address":"77 Queensway E",
    "sg:city":"Simcoe",
    "sg:classifiers":[
        {
            "category":"Restaurant",
            "type":"Food & Drink"
        }
    ],
    "sg:phone":"+1 519 426 8084",
    "sg:postcode":"N3Y 4M5",
    "sg:province":"ON",
    "wof:name":"Mc Donald's",
    "wof:placetype":"venue"
},
  "geometry": {"coordinates":[-80.2998352051,42.8474197388],"type":"Point"}
}