{
  "type": "Feature",
  "properties": {
    "addr:full":"5827 Main St Niagara Falls ON L2G 5Z6",
    "addr:housenumber":"5827",
    "addr:postcode":"l2g 5z6",
    "addr:street":"Main St",
    "iso:country":"CA",
    "sg:address":"5827 Main St",
    "sg:city":"Niagara Falls",
    "sg:classifiers":[
        {
            "category":"Health Services",
            "subcategory":"Doctor",
            "type":"Services"
        }
    ],
    "sg:phone":"+1 905 356 6924",
    "sg:postcode":"L2G 5Z6",
    "sg:province":"ON",
    "sg:tags":[
        "physician",
        "surgeon"
    ],
    "wof:name":"Hoh, K F MD",
    "wof:placetype":"venue"
},
  "geometry": {"coordinates":[-79.0930404663,43.0901298523],"type":"Point"}
}