{
  "type": "Feature",
  "properties": {
    "iso:country":"CA",
    "sg:address":"4269 Rue Saint-Denis",
    "sg:city":"Montreal",
    "sg:classifiers":[
        {
            "category":"Shopping",
            "subcategory":"Optical Goods",
            "type":"Retail Goods"
        }
    ],
    "sg:phone":"+1 514 985 0922",
    "sg:postcode":"H2J 2K9",
    "sg:province":"QC",
    "sg:tags":[
        "optician"
    ],
    "wof:name":"F Farhat Lunetterie",
    "wof:placetype":"venue"
},
  "geometry": {"coordinates":[-73.57917,45.52243],"type":"Point"}
}