{
  "type": "Feature",
  "properties": {
    "addr:full":"6253 Rue Sherbrooke O # A Montreal QC H4B 1M6",
    "addr:housenumber":"6253",
    "addr:postcode":"h4b 1m6",
    "addr:street":"Rue Sherbrooke O # A",
    "iso:country":"CA",
    "sg:address":"6253 Rue Sherbrooke O # A",
    "sg:city":"Montreal",
    "sg:classifiers":[
        {
            "category":"Personal",
            "subcategory":"Shoe Repair & Shine",
            "type":"Services"
        }
    ],
    "sg:phone":"+1 514 486 8562",
    "sg:postcode":"H4B 1M6",
    "sg:province":"QC",
    "sg:tags":[
        "repairing",
        "boot"
    ],
    "wof:name":"Elvis Shoe Repair & Valet Svc",
    "wof:placetype":"venue"
},
  "geometry": {"coordinates":[-73.545502,45.579266],"type":"Point"}
}