{
  "type": "Feature",
  "properties": {
    "addr:full":"55 Dundas St W Trenton ON K8V 3N9",
    "addr:housenumber":"55",
    "addr:postcode":"k8v 3n9",
    "addr:street":"Dundas St W",
    "iso:country":"CA",
    "sg:address":"55 Dundas St W",
    "sg:city":"Trenton",
    "sg:classifiers":[
        {
            "category":"Banks & Credit Unions",
            "subcategory":"Bank",
            "type":"Services"
        }
    ],
    "sg:phone":"+1 613 392 9216",
    "sg:postcode":"K8V 3N9",
    "sg:province":"ON",
    "wof:name":"Bank of Montreal",
    "wof:placetype":"venue"
},
  "geometry": {"coordinates":[-77.575928,44.101246],"type":"Point"}
}