{
  "type": "Feature",
  "properties": {
    "addr:full":"250 42 Ave SE Calgary AB T2G 1Y4",
    "addr:housenumber":"250",
    "addr:postcode":"t2g 1y4",
    "addr:street":"42 Ave Se",
    "iso:country":"CA",
    "sg:address":"250 42 Ave SE",
    "sg:city":"Calgary",
    "sg:classifiers":[
        {
            "category":"Building & Trades",
            "subcategory":"Electrical",
            "type":"Services"
        }
    ],
    "sg:phone":"+1 403 287 6026",
    "sg:postcode":"T2G 1Y4",
    "sg:province":"AB",
    "sg:tags":[
        "electric",
        "contractor"
    ],
    "wof:name":"Ber-Mac Electrical & Instrmntn",
    "wof:placetype":"venue"
},
  "geometry": {"coordinates":[-114.059319,51.016144],"type":"Point"}
}