{
  "type": "Feature",
  "properties": {
    "addr:full":"Woodbridge ON L4L 6C2",
    "addr:postcode":"l4l 6c2",
    "iso:country":"CA",
    "sg:city":"Woodbridge",
    "sg:classifiers":[
        {
            "category":"Manufacturing",
            "subcategory":"Glass & Minerals",
            "type":"Manufacturing & Wholesale Goods"
        }
    ],
    "sg:phone":"+1 905 850 5175",
    "sg:postcode":"L4L 6C2",
    "sg:province":"ON",
    "sg:tags":[
        "product",
        "marble"
    ],
    "wof:name":"Ariston Marble & Granite Ltd",
    "wof:placetype":"venue"
},
  "geometry": {"coordinates":[-79.5529632568,43.7868461609],"type":"Point"}
}