{
  "type": "Feature",
  "properties": {
    "addr:full":"399 Keele St Toronto ON M6P 2K9",
    "addr:housenumber":"399",
    "addr:postcode":"m6p 2k9",
    "addr:street":"Keele St",
    "iso:country":"CA",
    "sg:address":"399 Keele St",
    "sg:city":"Toronto",
    "sg:classifiers":[
        {
            "category":"Restaurant",
            "type":"Food & Drink"
        }
    ],
    "sg:phone":"+1 416 763 2827",
    "sg:postcode":"M6P 2K9",
    "sg:province":"ON",
    "wof:name":"Mantau Court Restaurant",
    "wof:placetype":"venue"
},
  "geometry": {"coordinates":[-79.46467590330001,43.6662139893],"type":"Point"}
}