{
  "type": "Feature",
  "properties": {
    "addr:full":"8 Oland Cres Halifax NS B3S 1C6",
    "addr:housenumber":"8",
    "addr:postcode":"b3s 1c6",
    "addr:street":"Oland Cres",
    "iso:country":"CA",
    "sg:address":"8 Oland Cres",
    "sg:city":"Halifax",
    "sg:classifiers":[
        {
            "category":"Manufacturing",
            "subcategory":"Printing",
            "type":"Manufacturing & Wholesale Goods"
        }
    ],
    "sg:phone":"+1 902 450 0508",
    "sg:postcode":"B3S 1C6",
    "sg:province":"NS",
    "sg:tags":[
        "printer"
    ],
    "wof:name":"Minuteman Press",
    "wof:placetype":"venue"
},
  "geometry": {"coordinates":[-63.6750411987,44.6474876404],"type":"Point"}
}