{
  "type": "Feature",
  "properties": {
    "addr:full":"559 222 Rte Valcourt QC J0E 2L0",
    "addr:housenumber":"222",
    "addr:postcode":"j0e 2l0",
    "addr:street":"Rte Valcourt",
    "iso:country":"CA",
    "sg:address":"559 222 Rte",
    "sg:city":"Valcourt",
    "sg:classifiers":[
        {
            "category":"Wholesale",
            "subcategory":"Auto Parts",
            "type":"Manufacturing & Wholesale Goods"
        }
    ],
    "sg:phone":"+1 450 532 4308",
    "sg:postcode":"J0E 2L0",
    "sg:province":"QC",
    "sg:tags":[
        "automobile",
        "rebuilt"
    ],
    "wof:name":"Groulx, Jacques",
    "wof:placetype":"venue"
},
  "geometry": {"coordinates":[-72.314956665,45.4933815002],"type":"Point"}
}