{
  "type": "Feature",
  "properties": {
    "addr:full":"2022 33 Ave SW Calgary AB T2T 1Z4",
    "addr:housenumber":"2022",
    "addr:postcode":"t2t 1z4",
    "addr:street":"33 Ave Sw",
    "iso:country":"CA",
    "sg:address":"2022 33 Ave SW",
    "sg:city":"Calgary",
    "sg:classifiers":[
        {
            "category":"Health Services",
            "subcategory":"Health Practitioner",
            "type":"Services"
        }
    ],
    "sg:phone":"+1 403 685 2893",
    "sg:postcode":"T2T 1Z4",
    "sg:province":"AB",
    "sg:tags":[
        "occupational",
        "therapist"
    ],
    "wof:name":"Kids Can",
    "wof:placetype":"venue"
},
  "geometry": {"coordinates":[-114.107674,51.02412],"type":"Point"}
}