{
  "type": "Feature",
  "properties": {
    "addr:full":"2175 Sheppard Ave E # 217 North York ON M2J 1W8",
    "addr:housenumber":"2175",
    "addr:postcode":"m2j 1w8",
    "addr:street":"Sheppard Ave E # 217",
    "iso:country":"CA",
    "sg:address":"2175 Sheppard Ave E # 217",
    "sg:city":"North York",
    "sg:classifiers":[
        {
            "category":"Banks & Credit Unions",
            "subcategory":"Bank",
            "type":"Services"
        }
    ],
    "sg:phone":"+1 416 499 6400",
    "sg:postcode":"M2J 1W8",
    "sg:province":"ON",
    "wof:name":"Scotiabank",
    "wof:placetype":"venue"
},
  "geometry": {"coordinates":[-79.3304443359,43.7748718262],"type":"Point"}
}