{
  "type": "Feature",
  "properties": {
    "addr:full":"511 Millway Ave Concord ON L4K 3V4",
    "addr:housenumber":"511",
    "addr:postcode":"l4k 3v4",
    "addr:street":"Millway Ave",
    "iso:country":"CA",
    "sg:address":"511 Millway Ave",
    "sg:city":"Concord",
    "sg:classifiers":[
        {
            "category":"Building & Trades",
            "subcategory":"Cleaning & Sanitation",
            "type":"Services"
        }
    ],
    "sg:phone":"+1 905 761 0932",
    "sg:postcode":"L4K 3V4",
    "sg:province":"ON",
    "sg:tags":[
        "maintenance",
        "contractor"
    ],
    "wof:name":"Gryphon Building Solutions Inc",
    "wof:placetype":"venue"
},
  "geometry": {"coordinates":[-79.529861,43.807106],"type":"Point"}
}