{
  "type": "Feature",
  "properties": {
    "addr:full":"RR 1 STN Main Bracebridge ON P1L 1W8",
    "addr:postcode":"p1l 1w8",
    "addr:street":"Rr 1 Stn Main",
    "iso:country":"CA",
    "sg:address":"RR 1 STN Main",
    "sg:city":"Bracebridge",
    "sg:classifiers":[
        {
            "category":"Building & Trades",
            "subcategory":"Cleaning & Sanitation",
            "type":"Services"
        }
    ],
    "sg:phone":"+1 705 644 1998",
    "sg:postcode":"P1L 1W8",
    "sg:province":"ON",
    "sg:tags":[
        "lawn",
        "property",
        "maintenance",
        "grounds"
    ],
    "wof:name":"Post Property Svc",
    "wof:placetype":"venue"
},
  "geometry": {"coordinates":[-79.288635,45.05558],"type":"Point"}
}