{
  "type": "Feature",
  "properties": {
    "addr:full":"48 King St W Dundas ON L9H 1T8",
    "addr:housenumber":"48",
    "addr:postcode":"l9h 1t8",
    "addr:street":"King St W",
    "iso:country":"CA",
    "sg:address":"48 King St W",
    "sg:city":"Dundas",
    "sg:classifiers":[
        {
            "category":"Restaurant",
            "type":"Food & Drink"
        }
    ],
    "sg:phone":"+1 905 627 5092",
    "sg:postcode":"L9H 1T8",
    "sg:province":"ON",
    "sg:tags":[
        "sandwich"
    ],
    "wof:name":"Super Submarine",
    "wof:placetype":"venue"
},
  "geometry": {"coordinates":[-79.955978,43.266266],"type":"Point"}
}