{
  "type": "Feature",
  "properties": {
    "addr:full":"1175 Rogers Way Kamloops BC V1S 1R5",
    "addr:housenumber":"1175",
    "addr:postcode":"bc v1s 1r5",
    "addr:street":"Rogers Way",
    "iso:country":"CA",
    "sg:address":"1175 Rogers Way",
    "sg:city":"Kamloops",
    "sg:classifiers":[
        {
            "category":"Travel",
            "subcategory":"Hotels & Motels",
            "type":"Entertainment"
        }
    ],
    "sg:phone":"+1 250 374 4144",
    "sg:postcode":"V1S 1R5",
    "sg:province":"BC",
    "wof:name":"Four Points Hotel Sheraton",
    "wof:placetype":"venue"
},
  "geometry": {"coordinates":[-120.368255615,50.6513061523],"type":"Point"}
}