{
  "type": "Feature",
  "properties": {
    "iso:country":"CA",
    "sg:address":"1236 Weber St E",
    "sg:city":"Kitchener",
    "sg:classifiers":[
        {
            "category":"Health Services",
            "subcategory":"Chiropractor",
            "type":"Services"
        }
    ],
    "sg:phone":"+1 519 894 3661",
    "sg:postcode":"N2A 1C3",
    "sg:province":"ON",
    "wof:name":"Kingsdale Chiropractic",
    "wof:placetype":"venue"
},
  "geometry": {"coordinates":[-80.44458,43.433666],"type":"Point"}
}