{
  "type": "Feature",
  "properties": {
    "addr:full":"400 Merganser Dr W Chestermere AB T1X 1K5",
    "addr:housenumber":"400",
    "addr:postcode":"t1x 1k5",
    "addr:street":"Merganser Dr W",
    "iso:country":"CA",
    "sg:address":"400 Merganser Dr W",
    "sg:city":"Chestermere",
    "sg:classifiers":[
        {
            "category":"Autos & Motor Vehicles",
            "subcategory":"Fuel & Gas Station",
            "type":"Retail Goods"
        }
    ],
    "sg:phone":"+1 403 235 9927",
    "sg:postcode":"T1X 1K5",
    "sg:province":"AB",
    "sg:tags":[
        "oil"
    ],
    "wof:name":"Gas Plus Inc",
    "wof:placetype":"venue"
},
  "geometry": {"coordinates":[-113.841553,51.036388],"type":"Point"}
}