{
  "type": "Feature",
  "properties": {
    "addr:full":"Vancouver BC V6K 2G3",
    "addr:postcode":"v6k 2g3",
    "iso:country":"CA",
    "sg:city":"Vancouver",
    "sg:classifiers":[
        {
            "category":"Travel",
            "subcategory":"Travel Agent",
            "type":"Entertainment"
        }
    ],
    "sg:phone":"+1 604 659 4150",
    "sg:postcode":"V6K 2G3",
    "sg:province":"BC",
    "sg:tags":[
        "agency",
        "bureau"
    ],
    "wof:name":"Travel Masters",
    "wof:placetype":"venue"
},
  "geometry": {"coordinates":[-123.16585499999999,49.263901],"type":"Point"}
}