{
  "type": "Feature",
  "properties": {
    "iso:country":"CA",
    "sg:address":"4439 Sumas St",
    "sg:city":"Burnaby",
    "sg:classifiers":[
        {
            "category":"Wholesale",
            "subcategory":"Electrical",
            "type":"Manufacturing & Wholesale Goods"
        }
    ],
    "sg:phone":"+1 604 294 4604",
    "sg:postcode":"V5C 6A4",
    "sg:province":"BC",
    "sg:tags":[
        "control",
        "electric",
        "motor"
    ],
    "wof:name":"Cesco Electrical Supply Ltd",
    "wof:placetype":"venue"
},
  "geometry": {"coordinates":[-123.00521850600001,49.2656669617],"type":"Point"}
}