{
  "type": "Feature",
  "properties": {
    "addr:full":"908 Pandora Ave Victoria BC V8V 3P3",
    "addr:housenumber":"908",
    "addr:postcode":"v8v 3p3",
    "addr:street":"Pandora Ave",
    "iso:country":"CA",
    "sg:address":"908 Pandora Ave",
    "sg:city":"Victoria",
    "sg:classifiers":[
        {
            "category":"Government",
            "subcategory":"Office",
            "type":"Public Place"
        }
    ],
    "sg:phone":"+1 250 356 8286",
    "sg:postcode":"V8V 3P3",
    "sg:province":"BC",
    "wof:name":"BC First Citizens Fund",
    "wof:placetype":"venue"
},
  "geometry": {"coordinates":[-123.35865,48.427612],"type":"Point"}
}