{
  "type": "Feature",
  "properties": {
    "addr:full":"648 14th St W North Vancouver BC V7M 1R2",
    "addr:housenumber":"648",
    "addr:postcode":"v7m 1r2",
    "addr:street":"14Th St W",
    "iso:country":"CA",
    "sg:address":"648 14th St W",
    "sg:city":"North Vancouver",
    "sg:classifiers":[
        {
            "category":"Wholesale",
            "subcategory":"Machinery & Supplies",
            "type":"Manufacturing & Wholesale Goods"
        }
    ],
    "sg:phone":"+1 604 291 6505",
    "sg:postcode":"V7M 1R2",
    "sg:province":"BC",
    "sg:tags":[
        "cargo",
        "container",
        "freight"
    ],
    "wof:name":"Black Swan Trucking",
    "wof:placetype":"venue"
},
  "geometry": {"coordinates":[-123.090492248,49.3213539124],"type":"Point"}
}