{
  "type": "Feature",
  "properties": {
    "addr:full":"415 42nd A St E Saskatoon SK S7K 0V4",
    "addr:housenumber":"415",
    "addr:postcode":"s7k 0v4",
    "addr:street":"42Nd A St E",
    "iso:country":"CA",
    "sg:address":"415 42nd A St E",
    "sg:city":"Saskatoon",
    "sg:classifiers":[
        {
            "category":"Building & Trades",
            "subcategory":"Electrical",
            "type":"Services"
        }
    ],
    "sg:phone":"+1 306 975 0101",
    "sg:postcode":"S7K 0V4",
    "sg:province":"SK",
    "sg:tags":[
        "electric",
        "contractor"
    ],
    "wof:name":"Amtech Electrical Ltd",
    "wof:placetype":"venue"
},
  "geometry": {"coordinates":[-106.66421508800001,52.1590614319],"type":"Point"}
}