{
  "type": "Feature",
  "properties": {
    "iso:country":"CA",
    "sg:city":"Brooks",
    "sg:classifiers":[
        {
            "category":"Wholesale",
            "subcategory":"Petroleum",
            "type":"Manufacturing & Wholesale Goods"
        }
    ],
    "sg:phone":"+1 403 362 2885",
    "sg:postcode":"T1R 1B9",
    "sg:province":"AB",
    "sg:tags":[
        "bulk",
        "oil",
        "gasoline"
    ],
    "wof:name":"Vauxhall CO-OP Brooks",
    "wof:placetype":"venue"
},
  "geometry": {"coordinates":[-111.890068054,50.5558547974],"type":"Point"}
}