{
  "type": "Feature",
  "properties": {
    "addr:full":"34 Main St St George Brant ON N0E 1N0",
    "addr:housenumber":"34",
    "addr:postcode":"n0e 1n0",
    "addr:street":"Main St",
    "iso:country":"CA",
    "sg:address":"34 Main St",
    "sg:city":"St George Brant",
    "sg:classifiers":[
        {
            "category":"Recreation",
            "type":"Entertainment"
        }
    ],
    "sg:phone":"+1 519 448 3753",
    "sg:postcode":"N0E 1N0",
    "sg:province":"ON",
    "sg:tags":[
        "hall",
        "auditorium"
    ],
    "wof:name":"St George Community Memorial",
    "wof:placetype":"venue"
},
  "geometry": {"coordinates":[-80.426659,43.10247],"type":"Point"}
}