{
  "type": "Feature",
  "properties": {
    "addr:full":"589 Fairway Rd S Kitchener ON N2C 1X4",
    "addr:housenumber":"589",
    "addr:postcode":"n2c 1x4",
    "addr:street":"Fairway Rd",
    "iso:country":"CA",
    "sg:address":"589 Fairway Rd S",
    "sg:city":"Kitchener",
    "sg:classifiers":[
        {
            "category":"Restaurant",
            "type":"Food & Drink"
        }
    ],
    "sg:phone":"+1 519 895 3888",
    "sg:postcode":"N2C 1X4",
    "sg:province":"ON",
    "wof:name":"Mr Sub",
    "wof:placetype":"venue"
},
  "geometry": {"coordinates":[-80.45013400000001,43.419632],"type":"Point"}
}