{
  "type": "Feature",
  "properties": {
    "addr:full":"5870 King Rd Nobleton ON L0G 1N0",
    "addr:housenumber":"5870",
    "addr:postcode":"l0g 1n0",
    "addr:street":"King Rd",
    "iso:country":"CA",
    "sg:address":"5870 King Rd",
    "sg:city":"Nobleton",
    "sg:classifiers":[
        {
            "category":"Retail",
            "subcategory":"Repair Shop",
            "type":"Services"
        }
    ],
    "sg:phone":"+1 905 859 4634",
    "sg:postcode":"L0G 1N0",
    "sg:province":"ON",
    "sg:tags":[
        "curtain",
        "upholsterer",
        "drapery"
    ],
    "wof:name":"Crupi's Interiors",
    "wof:placetype":"venue"
},
  "geometry": {"coordinates":[-79.64831542970001,43.9026565552],"type":"Point"}
}