{
  "type": "Feature",
  "properties": {
    "addr:full":"Sackville NB E4L 4P4",
    "addr:postcode":"e4l 4p4",
    "iso:country":"CA",
    "sg:city":"Sackville",
    "sg:classifiers":[
        {
            "category":"Building & Trades",
            "subcategory":"Construction",
            "type":"Services"
        }
    ],
    "sg:phone":"+1 506 536 1095",
    "sg:postcode":"E4L 4P4",
    "sg:province":"NB",
    "sg:tags":[
        "downspouts",
        "gutter",
        "contractor"
    ],
    "wof:name":"Tantramar Buildings Ltd",
    "wof:placetype":"venue"
},
  "geometry": {"coordinates":[-64.36745500000001,45.897163],"type":"Point"}
}