{
  "type": "Feature",
  "properties": {
    "iso:country":"CA",
    "sg:address":"6155 Tomken Rd # 8",
    "sg:city":"Mississauga",
    "sg:classifiers":[
        {
            "category":"Wholesale",
            "subcategory":"Electrical",
            "type":"Manufacturing & Wholesale Goods"
        }
    ],
    "sg:phone":"+1 905 565 0306",
    "sg:postcode":"L5T 1X3",
    "sg:province":"ON",
    "sg:tags":[
        "control",
        "security",
        "system"
    ],
    "wof:name":"Access Direct Sales Inc",
    "wof:placetype":"venue"
},
  "geometry": {"coordinates":[-79.662895,43.64946],"type":"Point"}
}