{
  "type": "Feature",
  "properties": {
    "addr:full":"2620 Eglinton Ave E Scarborough ON M1K 2S3",
    "addr:housenumber":"2620",
    "addr:postcode":"m1k 2s3",
    "addr:street":"Eglinton Ave E",
    "iso:country":"CA",
    "sg:address":"2620 Eglinton Ave E",
    "sg:city":"Scarborough",
    "sg:classifiers":[
        {
            "category":"Government",
            "subcategory":"Post Office",
            "type":"Public Place"
        }
    ],
    "sg:phone":"+1 416 261 7107",
    "sg:postcode":"M1K 2S3",
    "sg:province":"ON",
    "sg:tags":[
        "pharmacy"
    ],
    "wof:name":"Medical Centre Drugs Ltd",
    "wof:placetype":"venue"
},
  "geometry": {"coordinates":[-79.251648,43.736107],"type":"Point"}
}