{
  "type": "Feature",
  "properties": {
    "addr:full":"1290 Danforth Rd Scarborough ON M1J 3L9",
    "addr:housenumber":"1290",
    "addr:postcode":"m1j 3l9",
    "addr:street":"Danforth Rd",
    "iso:country":"CA",
    "sg:address":"1290 Danforth Rd",
    "sg:city":"Scarborough",
    "sg:classifiers":[
        {
            "category":"Health Services",
            "subcategory":"Nursing And Care Facility",
            "type":"Services"
        }
    ],
    "sg:phone":"+1 416 267 2737",
    "sg:postcode":"M1J 3L9",
    "sg:province":"ON",
    "sg:tags":[
        "home",
        "retirement",
        "community"
    ],
    "wof:name":"St David's Village",
    "wof:placetype":"venue"
},
  "geometry": {"coordinates":[-79.2456893921,43.7397537231],"type":"Point"}
}