{
  "type": "Feature",
  "properties": {
    "addr:full":"17 Erie St N Leamington ON N8H 2Z2",
    "addr:housenumber":"17",
    "addr:postcode":"n8h 2z2",
    "addr:street":"Erie St N",
    "iso:country":"CA",
    "sg:address":"17 Erie St N",
    "sg:city":"Leamington",
    "sg:classifiers":[
        {
            "category":"Real Estate",
            "subcategory":"Real Estate Agent",
            "type":"Services"
        }
    ],
    "sg:phone":"+1 519 326 3712",
    "sg:postcode":"N8H 2Z2",
    "sg:province":"ON",
    "wof:name":"Featherstone Realty Inc",
    "wof:placetype":"venue"
},
  "geometry": {"coordinates":[-82.599937,42.053558],"type":"Point"}
}