{
  "type": "Feature",
  "properties": {
    "addr:full":"307 Rue DE LA Lyre L'Epiphanie QC J5X 4C1",
    "addr:housenumber":"307",
    "addr:postcode":"j5x 4c1",
    "addr:street":"Rue De La Lyre L'Epiphanie",
    "iso:country":"CA",
    "sg:address":"307 Rue DE LA Lyre",
    "sg:city":"L'Epiphanie",
    "sg:classifiers":[
        {
            "category":"Building & Trades",
            "subcategory":"Construction",
            "type":"Services"
        }
    ],
    "sg:phone":"+1 450 588 7364",
    "sg:postcode":"J5X 4C1",
    "sg:province":"QC",
    "sg:tags":[
        "siding",
        "contractor"
    ],
    "wof:name":"Renovation C Gauthier Enr",
    "wof:placetype":"venue"
},
  "geometry": {"coordinates":[-73.495476,45.849964],"type":"Point"}
}