{
  "type": "Feature",
  "properties": {
    "addr:full":"76 Starrs Rd Yarmouth NS B5A 2T5",
    "addr:housenumber":"76",
    "addr:postcode":"b5a 2t5",
    "addr:street":"Starrs Rd",
    "iso:country":"CA",
    "sg:address":"76 Starrs Rd",
    "sg:city":"Yarmouth",
    "sg:classifiers":[
        {
            "category":"Personal",
            "subcategory":"Beauty Salon",
            "type":"Services"
        }
    ],
    "sg:phone":"+1 902 742 6108",
    "sg:postcode":"B5A 2T5",
    "sg:province":"NS",
    "wof:name":"Magicuts",
    "wof:placetype":"venue"
},
  "geometry": {"coordinates":[-66.09865600000001,43.841331],"type":"Point"}
}