{
  "type": "Feature",
  "properties": {
    "addr:full":"1050 Boul Henri-Bourassa E Montreal QC H2C 1G2",
    "addr:housenumber":"1050",
    "addr:postcode":"h2c 1g2",
    "addr:street":"Boul Henri-Bourassa E",
    "iso:country":"CA",
    "sg:address":"1050 Boul Henri-Bourassa E",
    "sg:city":"Montreal",
    "sg:classifiers":[
        {
            "category":"Health Services",
            "subcategory":"Medical Lab",
            "type":"Services"
        }
    ],
    "sg:phone":"+1 514 388 3216",
    "sg:postcode":"H2C 1G2",
    "sg:province":"QC",
    "wof:name":"Durette, Guy",
    "wof:placetype":"venue"
},
  "geometry": {"coordinates":[-73.66566467289999,45.5599708557],"type":"Point"}
}