{
  "type": "Feature",
  "properties": {
    "iso:country":"CA",
    "sg:city":"Abbotsford",
    "sg:classifiers":[
        {
            "category":"Personal",
            "subcategory":"Beauty Salon",
            "type":"Services"
        }
    ],
    "sg:phone":"+1 604 854 8343",
    "sg:postcode":"V2T 5E5",
    "sg:province":"BC",
    "wof:name":"Prince Hair & Beauty Salon",
    "wof:placetype":"venue"
},
  "geometry": {"coordinates":[-122.35939025899999,49.0543022156],"type":"Point"}
}