{
  "type": "Feature",
  "properties": {
    "addr:full":"Saint-Alphonse-DE-Granby QC J0E 2A0",
    "addr:postcode":"j0e 2a0",
    "iso:country":"CA",
    "sg:city":"Saint-Alphonse-DE-Granby",
    "sg:classifiers":[
        {
            "category":"Restaurant",
            "type":"Food & Drink"
        }
    ],
    "sg:phone":"+1 450 777 0280",
    "sg:postcode":"J0E 2A0",
    "sg:province":"QC",
    "wof:name":"Restaurant 68",
    "wof:placetype":"venue"
},
  "geometry": {"coordinates":[-72.783691,45.341576],"type":"Point"}
}