{
  "type": "Feature",
  "properties": {
    "addr:full":"Toronto ON M5M 1B2",
    "addr:postcode":"m5m 1b2",
    "iso:country":"CA",
    "sg:city":"Toronto",
    "sg:classifiers":[
        {
            "category":"Health Services",
            "subcategory":"Doctor",
            "type":"Services"
        }
    ],
    "sg:phone":"+1 416 789 7691",
    "sg:postcode":"M5M 1B2",
    "sg:province":"ON",
    "sg:tags":[
        "physician",
        "surgeon"
    ],
    "wof:name":"Voaden, Carol MD",
    "wof:placetype":"venue"
},
  "geometry": {"coordinates":[-79.413589,43.722847],"type":"Point"}
}