{
  "type": "Feature",
  "properties": {
    "addr:full":"514 Carlingview Dr Etobicoke ON M9W 5R3",
    "addr:housenumber":"514",
    "addr:postcode":"m9w 5r3",
    "addr:street":"Carlingview Dr",
    "iso:country":"CA",
    "sg:address":"514 Carlingview Dr",
    "sg:city":"Etobicoke",
    "sg:classifiers":[
        {
            "category":"Building & Trades",
            "subcategory":"Plumbing",
            "type":"Services"
        }
    ],
    "sg:phone":"+1 416 213 7495",
    "sg:postcode":"M9W 5R3",
    "sg:province":"ON",
    "sg:tags":[
        "conditioning",
        "air",
        "system",
        "contractor"
    ],
    "wof:name":"Agta Mechanical Ltd",
    "wof:placetype":"venue"
},
  "geometry": {"coordinates":[-79.603371,43.703747],"type":"Point"}
}