{
  "type": "Feature",
  "properties": {
    "addr:full":"555 1 Rue O Barraute QC J0Y 1A0",
    "addr:housenumber":"555 1",
    "addr:postcode":"j0y 1a0",
    "addr:street":"Rue O",
    "iso:country":"CA",
    "sg:address":"555 1 Rue O",
    "sg:city":"Barraute",
    "sg:classifiers":[
        {
            "category":"Social Services",
            "type":"Services"
        }
    ],
    "sg:phone":"+1 819 734 1354",
    "sg:postcode":"J0Y 1A0",
    "sg:province":"QC",
    "sg:tags":[
        "youth",
        "organization",
        "center"
    ],
    "wof:name":"Maison Des Jeunes DE Barraute",
    "wof:placetype":"venue"
},
  "geometry": {"coordinates":[-77.681969,48.516918],"type":"Point"}
}