{
  "type": "Feature",
  "properties": {
    "addr:full":"618 5 Ave SW Calgary AB T2P 0M7",
    "addr:housenumber":"618",
    "addr:postcode":"t2p 0m7",
    "addr:street":"5 Ave Sw",
    "iso:country":"CA",
    "sg:address":"618 5 Ave SW",
    "sg:city":"Calgary",
    "sg:classifiers":[
        {
            "category":"Travel",
            "subcategory":"Hotels & Motels",
            "type":"Entertainment"
        }
    ],
    "sg:phone":"+1 403 263 0520",
    "sg:postcode":"T2P 0M7",
    "sg:province":"AB",
    "wof:name":"Hawthorn Hotel & Suites",
    "wof:placetype":"venue"
},
  "geometry": {"coordinates":[-114.074226,51.048824],"type":"Point"}
}