{
  "type": "Feature",
  "properties": {
    "iso:country":"CA",
    "sg:address":"101 Longworth Ave",
    "sg:city":"Charlottetown",
    "sg:classifiers":[
        {
            "category":"Freight",
            "type":"Transportation"
        }
    ],
    "sg:phone":"+1 902 628 6683",
    "sg:postcode":"C1A 5A9",
    "sg:province":"PE",
    "sg:tags":[
        "mover",
        "commercial"
    ],
    "wof:name":"Jenkins Transfer Ltd",
    "wof:placetype":"venue"
},
  "geometry": {"coordinates":[-63.1240272522,46.2450561523],"type":"Point"}
}