{
  "type": "Feature",
  "properties": {
    "addr:full":"640 Boul Roberval O Longueuil QC J4L 3B7",
    "addr:housenumber":"640",
    "addr:postcode":"j4l 3b7",
    "addr:street":"Boul Roberval O",
    "iso:country":"CA",
    "sg:address":"640 Boul Roberval O",
    "sg:city":"Longueuil",
    "sg:classifiers":[
        {
            "category":"Building & Trades",
            "subcategory":"Electrical",
            "type":"Services"
        }
    ],
    "sg:phone":"+1 450 677 7124",
    "sg:postcode":"J4L 3B7",
    "sg:province":"QC",
    "sg:tags":[
        "electric",
        "contractor"
    ],
    "wof:name":"J-P Charbonneau Enr Elctrcn",
    "wof:placetype":"venue"
},
  "geometry": {"coordinates":[-73.443108,45.523861],"type":"Point"}
}