{
  "type": "Feature",
  "properties": {
    "addr:full":"E Barriere Lk Rd Barriere BC V0E 1E0",
    "addr:postcode":"bc v0e 1e0",
    "addr:street":"Lk Rd",
    "iso:country":"CA",
    "sg:address":"E Barriere Lk Rd",
    "sg:city":"Barriere",
    "sg:classifiers":[
        {
            "category":"Recreation",
            "type":"Entertainment"
        }
    ],
    "sg:phone":"+1 250 672 9633",
    "sg:postcode":"V0E 1E0",
    "sg:province":"BC",
    "sg:tags":[
        "carnival"
    ],
    "wof:name":"North Thompson Fall Fair",
    "wof:placetype":"venue"
},
  "geometry": {"coordinates":[-120.11826324499999,51.1966209412],"type":"Point"}
}