{
  "type": "Feature",
  "properties": {
    "iso:country":"CA",
    "sg:city":"Mississauga",
    "sg:classifiers":[
        {
            "category":"Professional",
            "subcategory":"Management & Consulting",
            "type":"Services"
        }
    ],
    "sg:phone":"+1 905 624 5846",
    "sg:postcode":"L4W 2M9",
    "sg:province":"ON",
    "sg:tags":[
        "consultant",
        "business"
    ],
    "wof:name":"H R Group",
    "wof:placetype":"venue"
},
  "geometry": {"coordinates":[-79.59944152830001,43.6324234009],"type":"Point"}
}