{
  "type": "Feature",
  "properties": {
    "addr:full":"48 Beckwith St N Smiths Falls ON K7A 2B3",
    "addr:housenumber":"48",
    "addr:postcode":"k7a 2b3",
    "addr:street":"Beckwith St N",
    "iso:country":"CA",
    "sg:address":"48 Beckwith St N",
    "sg:city":"Smiths Falls",
    "sg:classifiers":[
        {
            "category":"Restaurant",
            "type":"Food & Drink"
        }
    ],
    "sg:phone":"+1 613 284 1801",
    "sg:postcode":"K7A 2B3",
    "sg:province":"ON",
    "sg:tags":[
        "sandwich"
    ],
    "wof:name":"Subway Sandwiches & Salads",
    "wof:placetype":"venue"
},
  "geometry": {"coordinates":[-76.02146148680001,44.9012069702],"type":"Point"}
}