{
  "type": "Feature",
  "properties": {
    "addr:full":"5001 50th Ave Bonnyville AB T9N 2H5",
    "addr:housenumber":"5001",
    "addr:postcode":"t9n 2h5",
    "addr:street":"50Th Ave",
    "iso:country":"CA",
    "sg:address":"5001 50th Ave",
    "sg:city":"Bonnyville",
    "sg:classifiers":[
        {
            "category":"Food & Beverages",
            "subcategory":"Groceries & Convenience Stores",
            "type":"Retail Goods"
        }
    ],
    "sg:phone":"+1 780 826 3411",
    "sg:postcode":"T9N 2H5",
    "sg:province":"AB",
    "sg:tags":[
        "department",
        "grocer"
    ],
    "wof:name":"Brosseau's Dept Store Ltd",
    "wof:placetype":"venue"
},
  "geometry": {"coordinates":[-110.740128,54.268101],"type":"Point"}
}