{
  "type": "Feature",
  "properties": {
    "addr:full":"2235 Sheppard Avenue East Suite 1700 Toronto M2J 5B5",
    "addr:housenumber":"2235",
    "addr:postcode":"m2j 5b5",
    "addr:street":"Sheppard Avenue East Suite 1700",
    "iso:country":"CA",
    "sg:address":"2235 Sheppard Avenue East Suite 1700",
    "sg:city":"Toronto",
    "sg:classifiers":[
        {
            "category":"Professional",
            "subcategory":"Computer Services",
            "type":"Services"
        }
    ],
    "sg:postcode":"M2J 5B5",
    "sg:tags":[
        "authentication",
        "security"
    ],
    "sg:website":"http://diversinet.com",
    "wof:name":"Diversinet",
    "wof:placetype":"venue"
},
  "geometry": {"coordinates":[-79.32983,43.774927],"type":"Point"}
}