{
  "type": "Feature",
  "properties": {
    "addr:full":"21 Four Seasons Pl #400 Etobicoke ON M9B 6J8",
    "addr:housenumber":"21",
    "addr:postcode":"m9b 6j8",
    "addr:street":"Four Seasons Pl # 400",
    "iso:country":"CA",
    "sg:address":"21 Four Seasons Pl #400",
    "sg:city":"Etobicoke",
    "sg:classifiers":[
        {
            "category":"Professional",
            "type":"Services"
        }
    ],
    "sg:phone":"+1 416 695 4848",
    "sg:postcode":"M9B 6J8",
    "sg:province":"ON",
    "sg:tags":[
        "establishment",
        "trucking"
    ],
    "wof:name":"Clarke Logistics",
    "wof:placetype":"venue"
},
  "geometry": {"coordinates":[-79.56036400000001,43.647755],"type":"Point"}
}