{
  "type": "Feature",
  "properties": {
    "iso:country":"CA",
    "sg:address":"800 Benvenuto Ave",
    "sg:city":"Brentwood Bay",
    "sg:classifiers":[
        {
            "category":"Recreation",
            "type":"Entertainment"
        }
    ],
    "sg:phone":"+1 250 652 4422",
    "sg:postcode":"V8M 1J8",
    "sg:province":"BC",
    "sg:tags":[
        "provincial",
        "amusement",
        "parks"
    ],
    "wof:name":"Butchart Gardens Ltd",
    "wof:placetype":"venue"
},
  "geometry": {"coordinates":[-123.462722778,48.5637283325],"type":"Point"}
}