{
  "type": "Feature",
  "properties": {
    "addr:full":"1131 Wellington St W Ottawa ON K1Y 2Y6",
    "addr:housenumber":"1131",
    "addr:postcode":"k1y 2y6",
    "addr:street":"Wellington St W",
    "iso:country":"CA",
    "sg:address":"1131 Wellington St W",
    "sg:city":"Ottawa",
    "sg:classifiers":[
        {
            "category":"Shopping",
            "subcategory":"Tobacco",
            "type":"Retail Goods"
        }
    ],
    "sg:phone":"+1 613 728 5338",
    "sg:postcode":"K1Y 2Y6",
    "sg:province":"ON",
    "sg:tags":[
        "cigarette",
        "cigar",
        "dealer"
    ],
    "wof:name":"Malham's Smoke Shop",
    "wof:placetype":"venue"
},
  "geometry": {"coordinates":[-75.7266998291,45.4020271301],"type":"Point"}
}