{
  "type": "Feature",
  "properties": {
    "addr:full":"Lloydminster AB T9V 0K2",
    "addr:postcode":"t9v 0k2",
    "iso:country":"CA",
    "sg:city":"Lloydminster",
    "sg:classifiers":[
        {
            "category":"Professional",
            "subcategory":"Accounting & Tax Preparation",
            "type":"Services"
        }
    ],
    "sg:phone":"+1 780 875 1100",
    "sg:postcode":"T9V 0K2",
    "sg:province":"AB",
    "sg:tags":[
        "accountant"
    ],
    "wof:name":"Mac Donald, D W CA",
    "wof:placetype":"venue"
},
  "geometry": {"coordinates":[-110.005996704,53.2826499939],"type":"Point"}
}