{
  "type": "Feature",
  "properties": {
    "addr:full":"2354 Ch Lucerne Mont-Royal QC H3R 2J8",
    "addr:housenumber":"2354",
    "addr:postcode":"h3r 2j8",
    "addr:street":"Ch Lucerne",
    "iso:country":"CA",
    "sg:address":"2354 Ch Lucerne",
    "sg:city":"Mont-Royal",
    "sg:classifiers":[
        {
            "category":"Health Services",
            "subcategory":"Optometrist",
            "type":"Services"
        }
    ],
    "sg:phone":"+1 514 341 2020",
    "sg:postcode":"H3R 2J8",
    "sg:province":"QC",
    "wof:name":"Mes Yeux Tes Yeux",
    "wof:placetype":"venue"
},
  "geometry": {"coordinates":[-73.661484,45.507271],"type":"Point"}
}