{
  "type": "Feature",
  "properties": {
    "iso:country":"CA",
    "sg:address":"355 Smythe St",
    "sg:city":"Fredericton",
    "sg:classifiers":[
        {
            "category":"Professional",
            "subcategory":"Business Services",
            "type":"Services"
        }
    ],
    "sg:phone":"+1 506 452 1819",
    "sg:postcode":"E3B 4Y9",
    "sg:province":"NB",
    "sg:tags":[
        "fair",
        "show",
        "facility",
        "trade",
        "convention",
        "meeting"
    ],
    "wof:name":"Capital Exhibit Ctr",
    "wof:placetype":"venue"
},
  "geometry": {"coordinates":[-66.654625,45.960796],"type":"Point"}
}