{
  "type": "Feature",
  "properties": {
    "addr:full":"2464 Dundas St Burlington ON L7R 3X4",
    "addr:housenumber":"2464",
    "addr:postcode":"l7r 3x4",
    "addr:street":"Dundas St",
    "iso:country":"CA",
    "sg:address":"2464 Dundas St",
    "sg:city":"Burlington",
    "sg:classifiers":[
        {
            "category":"Organizations",
            "subcategory":"Religious Organization",
            "type":"Services"
        }
    ],
    "sg:phone":"+1 905 336 5164",
    "sg:postcode":"L7R 3X4",
    "sg:province":"ON",
    "sg:tags":[
        "church"
    ],
    "wof:name":"St John's Anglican Church",
    "wof:placetype":"venue"
},
  "geometry": {"coordinates":[-79.843468,43.374306],"type":"Point"}
}