{
  "type": "Feature",
  "properties": {
    "iso:country":"CA",
    "sg:address":"11431 76 Ave NW",
    "sg:city":"Edmonton",
    "sg:classifiers":[
        {
            "category":"Recreation",
            "type":"Entertainment"
        }
    ],
    "sg:phone":"+1 780 436 0977",
    "sg:postcode":"T6G 0K5",
    "sg:province":"AB",
    "sg:tags":[
        "martial",
        "arts",
        "instruction"
    ],
    "wof:name":"Karate-DO Goju-Kai",
    "wof:placetype":"venue"
},
  "geometry": {"coordinates":[-113.526939392,53.5121154785],"type":"Point"}
}