{
  "type": "Feature",
  "properties": {
    "addr:full":"440 Rue Saint-Jean Matane QC G4W 2H2",
    "addr:housenumber":"440",
    "addr:postcode":"g4w 2h2",
    "addr:street":"Rue Saint-Jean",
    "iso:country":"CA",
    "sg:address":"440 Rue Saint-Jean",
    "sg:city":"Matane",
    "sg:classifiers":[
        {
            "category":"Organizations",
            "subcategory":"Religious Organization",
            "type":"Services"
        }
    ],
    "sg:phone":"+1 418 562 3123",
    "sg:postcode":"G4W 2H2",
    "sg:province":"QC",
    "sg:tags":[
        "church"
    ],
    "wof:name":"Presbytere Bon Pasteur",
    "wof:placetype":"venue"
},
  "geometry": {"coordinates":[-67.54093899999999,48.842167],"type":"Point"}
}