{
  "type": "Feature",
  "properties": {
    "addr:full":"4811 Barriere Town Rd Barriere BC V0E 1E0",
    "addr:housenumber":"4811",
    "addr:postcode":"bc v0e 1e0",
    "addr:street":"Barriere Town Rd",
    "iso:country":"CA",
    "sg:address":"4811 Barriere Town Rd",
    "sg:city":"Barriere",
    "sg:classifiers":[
        {
            "category":"Education",
            "subcategory":"School",
            "type":"Public Place"
        }
    ],
    "sg:phone":"+1 250 672 9943",
    "sg:postcode":"V0E 1E0",
    "sg:province":"BC",
    "wof:name":"Barriere Secondary School",
    "wof:placetype":"venue"
},
  "geometry": {"coordinates":[-120.126671,51.188274],"type":"Point"}
}