{
  "type": "Feature",
  "properties": {
    "addr:full":"309 Rue Montcalm Chicoutimi QC G7J 2V1",
    "addr:housenumber":"309",
    "addr:postcode":"g7j 2v1",
    "addr:street":"Rue Montcalm",
    "iso:country":"CA",
    "sg:address":"309 Rue Montcalm",
    "sg:city":"Chicoutimi",
    "sg:classifiers":[
        {
            "category":"Health Services",
            "subcategory":"Doctor",
            "type":"Services"
        }
    ],
    "sg:phone":"+1 418 545 4211",
    "sg:postcode":"G7J 2V1",
    "sg:province":"QC",
    "sg:tags":[
        "physician",
        "clinic",
        "surgeon"
    ],
    "wof:name":"Clinique DE Medicine Familiale",
    "wof:placetype":"venue"
},
  "geometry": {"coordinates":[-71.071434021,48.4290313721],"type":"Point"}
}