{
  "type": "Feature",
  "properties": {
    "iso:country":"CA",
    "sg:address":"#117-1350 Ridgeway Drive",
    "sg:city":"Kelowna",
    "sg:classifiers":[
        {
            "category":"Professional",
            "subcategory":"Management & Consulting",
            "type":"Services"
        }
    ],
    "sg:postcode":"v1y 9t8",
    "sg:tags":[
        "web-design",
        "graphic-design",
        "design",
        "mobile-design",
        "marketing-services"
    ],
    "sg:website":"http://www.stickypages.ca",
    "wof:name":"StickyPages",
    "wof:placetype":"venue"
},
  "geometry": {"coordinates":[-119.4583914,49.8900432],"type":"Point"}
}