{
  "type": "Feature",
  "properties": {
    "addr:full":"5002 50th Ave Calmar AB T0C 0V0",
    "addr:housenumber":"5002",
    "addr:postcode":"t0c 0v0",
    "addr:street":"50Th Ave",
    "iso:country":"CA",
    "sg:address":"5002 50th Ave",
    "sg:city":"Calmar",
    "sg:classifiers":[
        {
            "category":"Shopping",
            "subcategory":"Pharmacy",
            "type":"Retail Goods"
        }
    ],
    "sg:phone":"+1 780 985 3142",
    "sg:postcode":"T0C 0V0",
    "sg:province":"AB",
    "wof:name":"Calmar Value Drug Mart",
    "wof:placetype":"venue"
},
  "geometry": {"coordinates":[-113.805671692,53.2651557922],"type":"Point"}
}