{
  "type": "Feature",
  "properties": {
    "addr:full":"790 Boul Charest E Quebec QC G1K 3J7",
    "addr:housenumber":"790",
    "addr:postcode":"g1k 3j7",
    "addr:street":"Boul Charest E",
    "iso:country":"CA",
    "sg:address":"790 Boul Charest E",
    "sg:city":"Quebec",
    "sg:classifiers":[
        {
            "category":"Retail",
            "subcategory":"Portrait Studio",
            "type":"Services"
        }
    ],
    "sg:phone":"+1 418 529 3000",
    "sg:postcode":"G1K 3J7",
    "sg:province":"QC",
    "sg:tags":[
        "photographer"
    ],
    "wof:name":"Ernest Rainville Photographe",
    "wof:placetype":"venue"
},
  "geometry": {"coordinates":[-71.21881103520001,46.8154563904],"type":"Point"}
}