{
  "type": "Feature",
  "properties": {
    "addr:full":"1015 Clark Dr Vancouver BC V5L 3K1",
    "addr:housenumber":"1015",
    "addr:postcode":"v5l 3k1",
    "addr:street":"Clark Dr",
    "iso:country":"CA",
    "sg:address":"1015 Clark Dr",
    "sg:city":"Vancouver",
    "sg:classifiers":[
        {
            "category":"Wholesale",
            "subcategory":"Home Furnishings",
            "type":"Manufacturing & Wholesale Goods"
        }
    ],
    "sg:phone":"+1 604 251 2401",
    "sg:postcode":"V5L 3K1",
    "sg:province":"BC",
    "sg:tags":[
        "curtain",
        "drapery"
    ],
    "wof:name":"Textile Trimmings",
    "wof:placetype":"venue"
},
  "geometry": {"coordinates":[-123.077392578,49.2756881714],"type":"Point"}
}