{
  "type": "Feature",
  "properties": {
    "iso:country":"CA",
    "sg:address":"2141 Kipling Ave # 8",
    "sg:city":"Etobicoke",
    "sg:classifiers":[
        {
            "category":"Government",
            "subcategory":"Post Office",
            "type":"Public Place"
        }
    ],
    "sg:phone":"+1 416 743 2251",
    "sg:postcode":"M9W 4K8",
    "sg:province":"ON",
    "wof:name":"Canada Post Corp",
    "wof:placetype":"venue"
},
  "geometry": {"coordinates":[-79.57019042970001,43.7193069458],"type":"Point"}
}