{
  "type": "Feature",
  "properties": {
    "addr:full":"Ottawa ON K1K 0R6",
    "addr:postcode":"k1k 0r6",
    "iso:country":"CA",
    "sg:city":"Ottawa",
    "sg:classifiers":[
        {
            "category":"Building & Trades",
            "subcategory":"Plumbing",
            "type":"Services"
        }
    ],
    "sg:phone":"+1 613 244 0633",
    "sg:postcode":"K1K 0R6",
    "sg:province":"ON",
    "sg:tags":[
        "air",
        "conditioning",
        "contractor",
        "system",
        "heating"
    ],
    "wof:name":"Ultimate Combustion Svc Inc",
    "wof:placetype":"venue"
},
  "geometry": {"coordinates":[-75.64782,45.445911],"type":"Point"}
}