{
  "type": "Feature",
  "properties": {
    "addr:full":"578 Yonge St Toronto ON M4Y 1Z3",
    "addr:housenumber":"578",
    "addr:postcode":"m4y 1z3",
    "addr:street":"Yonge St",
    "iso:country":"CA",
    "sg:address":"578 Yonge St",
    "sg:city":"Toronto",
    "sg:classifiers":[
        {
            "category":"Restaurant",
            "type":"Food & Drink"
        }
    ],
    "sg:phone":"+1 416 323 9819",
    "sg:postcode":"M4Y 1Z3",
    "sg:province":"ON",
    "wof:name":"Garlic Pepper Szechuan Cuisine",
    "wof:placetype":"venue"
},
  "geometry": {"coordinates":[-79.38484200000001,43.665119],"type":"Point"}
}