{
  "type": "Feature",
  "properties": {
    "iso:country":"CA",
    "sg:address":"70 Port Darlington Rd",
    "sg:city":"Bowmanville",
    "sg:classifiers":[
        {
            "category":"Recreation",
            "subcategory":"Marina",
            "type":"Entertainment"
        }
    ],
    "sg:phone":"+1 905 623 4925",
    "sg:postcode":"L1C 3K3",
    "sg:province":"ON",
    "wof:name":"Port Darlington Marina Hotel",
    "wof:placetype":"venue"
},
  "geometry": {"coordinates":[-78.66450500489999,43.8910102844],"type":"Point"}
}