{
  "type": "Feature",
  "properties": {
    "addr:full":"1 Railway Ave Ethelbert MB R0L 0T0",
    "addr:housenumber":"1",
    "addr:postcode":"r0l 0t0",
    "addr:street":"Railway Ave",
    "iso:country":"CA",
    "sg:address":"1 Railway Ave",
    "sg:city":"Ethelbert",
    "sg:classifiers":[
        {
            "category":"Food & Beverages",
            "subcategory":"Groceries & Convenience Stores",
            "type":"Retail Goods"
        }
    ],
    "sg:phone":"+1 204 742 3252",
    "sg:postcode":"R0L 0T0",
    "sg:province":"MB",
    "sg:tags":[
        "grocer"
    ],
    "wof:name":"Bird's Corner Store",
    "wof:placetype":"venue"
},
  "geometry": {"coordinates":[-100.39846,51.525059],"type":"Point"}
}