{
  "type": "Feature",
  "properties": {
    "addr:full":"1348 Rundle Rd Bowmanville ON L1C 3K3",
    "addr:housenumber":"1348",
    "addr:postcode":"l1c 3k3",
    "addr:street":"Rundle Rd",
    "iso:country":"CA",
    "sg:address":"1348 Rundle Rd",
    "sg:city":"Bowmanville",
    "sg:classifiers":[
        {
            "category":"Recreation",
            "type":"Entertainment"
        }
    ],
    "sg:phone":"+1 905 697 0397",
    "sg:postcode":"L1C 3K3",
    "sg:province":"ON",
    "sg:tags":[
        "martial",
        "arts",
        "instruction"
    ],
    "wof:name":"Ivens Shototkan Karate Club",
    "wof:placetype":"venue"
},
  "geometry": {"coordinates":[-78.68847700000001,43.913834],"type":"Point"}
}