{
  "type": "Feature",
  "properties": {
    "addr:full":"1595 Bedford Hwy # 224 Bedford NS B4A 3Y4",
    "addr:housenumber":"1595",
    "addr:postcode":"b4a 3y4",
    "addr:street":"Bedford Hwy # 224",
    "iso:country":"CA",
    "sg:address":"1595 Bedford Hwy # 224",
    "sg:city":"Bedford",
    "sg:classifiers":[
        {
            "category":"Autos & Motor Vehicles",
            "subcategory":"Auto Supplies",
            "type":"Retail Goods"
        }
    ],
    "sg:phone":"+1 902 835 1660",
    "sg:postcode":"B4A 3Y4",
    "sg:province":"NS",
    "sg:tags":[
        "automobile",
        "parts"
    ],
    "wof:name":"Canadian Tire",
    "wof:placetype":"venue"
},
  "geometry": {"coordinates":[-63.655972,44.73278],"type":"Point"}
}