{
  "type": "Feature",
  "properties": {
    "addr:full":"9495 Robson St Chilliwack BC V2P 4E4",
    "addr:housenumber":"9495",
    "addr:postcode":"v2p 4e4",
    "addr:street":"Robson St",
    "iso:country":"CA",
    "sg:address":"9495 Robson St",
    "sg:city":"Chilliwack",
    "sg:classifiers":[
        {
            "category":"Food & Beverages",
            "subcategory":"Specialty",
            "type":"Retail Goods"
        }
    ],
    "sg:phone":"+1 604 795 5845",
    "sg:postcode":"V2P 4E4",
    "sg:province":"BC",
    "sg:tags":[
        "vitamin"
    ],
    "wof:name":"Ecesis Enterprises",
    "wof:placetype":"venue"
},
  "geometry": {"coordinates":[-121.959045,49.174438],"type":"Point"}
}