{
  "type": "Feature",
  "properties": {
    "addr:full":"601 Rang DE LA Grande-Chaloupe Saint-Thomas QC J0K 3L0",
    "addr:housenumber":"601",
    "addr:postcode":"j0k 3l0",
    "addr:street":"Rang De La Grande-Chaloupe",
    "iso:country":"CA",
    "sg:address":"601 Rang DE LA Grande-Chaloupe",
    "sg:city":"Saint-Thomas",
    "sg:classifiers":[
        {
            "category":"Building & Trades",
            "subcategory":"Plumbing",
            "type":"Services"
        }
    ],
    "sg:phone":"+1 450 755 2467",
    "sg:postcode":"J0K 3L0",
    "sg:province":"QC",
    "sg:tags":[
        "septic"
    ],
    "wof:name":"Fosses Septiques Ste Julienne",
    "wof:placetype":"venue"
},
  "geometry": {"coordinates":[-73.365936,46.056534],"type":"Point"}
}