{
  "type": "Feature",
  "properties": {
    "addr:full":"2445 Boul DE Comporte LA Malbaie QC G5A 1N5",
    "addr:housenumber":"2445",
    "addr:postcode":"g5a 1n5",
    "addr:street":"Boul De Comporte",
    "iso:country":"CA",
    "sg:address":"2445 Boul DE Comporte",
    "sg:city":"LA Malbaie",
    "sg:classifiers":[
        {
            "category":"Freight",
            "type":"Transportation"
        }
    ],
    "sg:phone":"+1 418 439 3976",
    "sg:postcode":"G5A 1N5",
    "sg:province":"QC",
    "sg:tags":[
        "trucking"
    ],
    "wof:name":"Transporteurs En Vrac",
    "wof:placetype":"venue"
},
  "geometry": {"coordinates":[-70.197067,47.68224],"type":"Point"}
}