{
  "type": "Feature",
  "properties": {
    "addr:full":"59 Rexway Dr Georgetown ON L7G 1P9",
    "addr:housenumber":"59",
    "addr:postcode":"l7g 1p9",
    "addr:street":"Rexway Dr",
    "iso:country":"CA",
    "sg:address":"59 Rexway Dr",
    "sg:city":"Georgetown",
    "sg:classifiers":[
        {
            "category":"Social Services",
            "subcategory":"Child Care",
            "type":"Services"
        }
    ],
    "sg:phone":"+1 905 873 0486",
    "sg:postcode":"L7G 1P9",
    "sg:province":"ON",
    "wof:name":"Harrison School Age Programme",
    "wof:placetype":"venue"
},
  "geometry": {"coordinates":[-79.909576,43.646404],"type":"Point"}
}