{
  "type": "Feature",
  "properties": {
    "addr:full":"Montreal QC H2W 2R2",
    "addr:postcode":"h2w 2r2",
    "iso:country":"CA",
    "sg:city":"Montreal",
    "sg:classifiers":[
        {
            "category":"Professional",
            "subcategory":"Advertising",
            "type":"Services"
        }
    ],
    "sg:phone":"+1 514 908 2552",
    "sg:postcode":"H2W 2R2",
    "sg:province":"QC",
    "sg:tags":[
        "internet"
    ],
    "wof:name":"Askmen Com Solutions",
    "wof:placetype":"venue"
},
  "geometry": {"coordinates":[-73.5821838379,45.5181083679],"type":"Point"}
}