{
  "type": "Feature",
  "properties": {
    "addr:full":"35 Marine Dr Port Hope Simpson NL A0K 4E0",
    "addr:housenumber":"35",
    "addr:postcode":"a0k 4e0",
    "addr:street":"Marine Dr",
    "iso:country":"CA",
    "sg:address":"35 Marine Dr",
    "sg:city":"Port Hope Simpson",
    "sg:classifiers":[
        {
            "category":"Government",
            "subcategory":"Office",
            "type":"Public Place"
        }
    ],
    "sg:phone":"+1 709 960 0400",
    "sg:postcode":"A0K 4E0",
    "sg:province":"NL",
    "wof:name":"Newfoundland Forestry",
    "wof:placetype":"venue"
},
  "geometry": {"coordinates":[-56.335045,52.541763],"type":"Point"}
}