{
  "type": "Feature",
  "properties": {
    "addr:full":"242 Carbon Ave Bienfait SK S0C 0M0",
    "addr:housenumber":"242",
    "addr:postcode":"s0c 0m0",
    "addr:street":"Carbon Ave",
    "iso:country":"CA",
    "sg:address":"242 Carbon Ave",
    "sg:city":"Bienfait",
    "sg:classifiers":[
        {
            "category":"Recreation",
            "type":"Entertainment"
        }
    ],
    "sg:phone":"+1 306 388 2333",
    "sg:postcode":"S0C 0M0",
    "sg:province":"SK",
    "sg:tags":[
        "skating",
        "rink"
    ],
    "wof:name":"Bienfait Memorial Arena",
    "wof:placetype":"venue"
},
  "geometry": {"coordinates":[-102.806892,49.143147],"type":"Point"}
}