{
  "type": "Feature",
  "properties": {
    "iso:country":"CA",
    "sg:address":"137 Rue Gagnon",
    "sg:city":"Padoue",
    "sg:classifiers":[
        {
            "category":"Autos & Motor Vehicles",
            "subcategory":"Fuel & Gas Station",
            "type":"Retail Goods"
        }
    ],
    "sg:phone":"+1 418 775 8877",
    "sg:postcode":"G0J 1X0",
    "sg:province":"QC",
    "sg:tags":[
        "oil"
    ],
    "wof:name":"Service Plus Enr",
    "wof:placetype":"venue"
},
  "geometry": {"coordinates":[-67.9919052124,48.5764656067],"type":"Point"}
}