{
  "type": "Feature",
  "properties": {
    "addr:full":"Richmond BC V6X 3A5",
    "addr:postcode":"v6x 3a5",
    "iso:country":"CA",
    "sg:city":"Richmond",
    "sg:classifiers":[
        {
            "category":"Restaurant",
            "type":"Food & Drink"
        }
    ],
    "sg:phone":"+1 604 273 8208",
    "sg:postcode":"V6X 3A5",
    "sg:province":"BC",
    "wof:name":"Sun Sui Wah Seafood Restaurant",
    "wof:placetype":"venue"
},
  "geometry": {"coordinates":[-123.136177,49.177933],"type":"Point"}
}