{
  "type": "Feature",
  "properties": {
    "iso:country":"CA",
    "sg:address":"Clifflake Rd Hwy 105",
    "sg:city":"Perrault Falls",
    "sg:classifiers":[
        {
            "category":"Travel",
            "subcategory":"Hotels & Motels",
            "type":"Entertainment"
        }
    ],
    "sg:phone":"+1 807 529 6511",
    "sg:postcode":"P0V 2K0",
    "sg:province":"ON",
    "sg:tags":[
        "resort"
    ],
    "wof:name":"Lost Bay Resort",
    "wof:placetype":"venue"
},
  "geometry": {"coordinates":[-93.1197357178,50.3642539978],"type":"Point"}
}