{
  "type": "Feature",
  "properties": {
    "addr:full":"2770 Kennedy Rd Scarborough ON M1T 3J2",
    "addr:housenumber":"2770",
    "addr:postcode":"m1t 3j2",
    "addr:street":"Kennedy Rd",
    "iso:country":"CA",
    "sg:address":"2770 Kennedy Rd",
    "sg:city":"Scarborough",
    "sg:classifiers":[
        {
            "category":"Retail",
            "subcategory":"Animal Services",
            "type":"Services"
        }
    ],
    "sg:phone":"+1 416 292 1204",
    "sg:postcode":"M1T 3J2",
    "sg:province":"ON",
    "sg:tags":[
        "pet",
        "grooming",
        "washing"
    ],
    "wof:name":"Grooming Salon",
    "wof:placetype":"venue"
},
  "geometry": {"coordinates":[-79.2957611084,43.7999992371],"type":"Point"}
}