{
  "type": "Feature",
  "properties": {
    "addr:full":"2381 Hwy 34 Hawkesbury ON K6A 2R2",
    "addr:housenumber":"2381",
    "addr:postcode":"k6a 2r2",
    "addr:street":"Hwy 34",
    "iso:country":"CA",
    "sg:address":"2381 Hwy 34",
    "sg:city":"Hawkesbury",
    "sg:classifiers":[
        {
            "category":"Manufacturing",
            "subcategory":"Metals",
            "type":"Manufacturing & Wholesale Goods"
        }
    ],
    "sg:phone":"+1 613 632 2888",
    "sg:postcode":"K6A 2R2",
    "sg:province":"ON",
    "sg:tags":[
        "equipment",
        "tower",
        "satellite",
        "system"
    ],
    "wof:name":"Rcomm Radio Inc",
    "wof:placetype":"venue"
},
  "geometry": {"coordinates":[-74.61414337159999,45.6078948975],"type":"Point"}
}