{
  "type": "Feature",
  "properties": {
    "addr:full":"138 Queen St North Sydney NS B2A 1B1",
    "addr:housenumber":"138",
    "addr:postcode":"b2a 1b1",
    "addr:street":"Queen St",
    "iso:country":"CA",
    "sg:address":"138 Queen St",
    "sg:city":"North Sydney",
    "sg:classifiers":[
        {
            "category":"Restaurant",
            "type":"Food & Drink"
        }
    ],
    "sg:phone":"+1 902 794 4452",
    "sg:postcode":"B2A 1B1",
    "sg:province":"NS",
    "wof:name":"Bette's Kitchen",
    "wof:placetype":"venue"
},
  "geometry": {"coordinates":[-60.25465,46.204102],"type":"Point"}
}