{
  "type": "Feature",
  "properties": {
    "addr:full":"156 Taunton Rd W Oshawa ON L1G 3T3",
    "addr:housenumber":"156",
    "addr:postcode":"l1g 3t3",
    "addr:street":"Taunton Rd W",
    "iso:country":"CA",
    "sg:address":"156 Taunton Rd W",
    "sg:city":"Oshawa",
    "sg:classifiers":[
        {
            "category":"Professional",
            "subcategory":"Accounting & Tax Preparation",
            "type":"Services"
        }
    ],
    "sg:phone":"+1 905 579 6728",
    "sg:postcode":"L1G 3T3",
    "sg:province":"ON",
    "sg:tags":[
        "accountant",
        "return",
        "filing"
    ],
    "wof:name":"Gallery Tax & Accounting Svc",
    "wof:placetype":"venue"
},
  "geometry": {"coordinates":[-78.885383606,43.9316215515],"type":"Point"}
}