{
  "type": "Feature",
  "properties": {
    "addr:full":"430 Av Domaine Du Parc Chandler QC G0C 1K0",
    "addr:housenumber":"430",
    "addr:postcode":"g0c 1k0",
    "addr:street":"Av Domaine Du",
    "iso:country":"CA",
    "sg:address":"430 Av Domaine Du Parc",
    "sg:city":"Chandler",
    "sg:classifiers":[
        {
            "category":"Real Estate",
            "subcategory":"Real Estate Agent",
            "type":"Services"
        }
    ],
    "sg:phone":"+1 418 689 3838",
    "sg:postcode":"G0C 1K0",
    "sg:province":"QC",
    "sg:tags":[
        "management"
    ],
    "wof:name":"Office Municipal D'Habitation",
    "wof:placetype":"venue"
},
  "geometry": {"coordinates":[-64.68017578120001,48.3490104675],"type":"Point"}
}