{
  "type": "Feature",
  "properties": {
    "addr:full":"272 Torbay Rd St. John's NL A1A 4E1",
    "addr:housenumber":"272",
    "addr:postcode":"a1a 4e1",
    "addr:street":"Torbay Rd",
    "iso:country":"CA",
    "sg:address":"272 Torbay Rd",
    "sg:city":"St. John's",
    "sg:classifiers":[
        {
            "category":"Travel",
            "subcategory":"Travel Agent",
            "type":"Entertainment"
        }
    ],
    "sg:phone":"+1 709 739 5600",
    "sg:postcode":"A1A 4E1",
    "sg:province":"NL",
    "sg:tags":[
        "agency",
        "bureau"
    ],
    "wof:name":"Harvey's Travel",
    "wof:placetype":"venue"
},
  "geometry": {"coordinates":[-52.7111167908,47.598777771],"type":"Point"}
}