{
  "type": "Feature",
  "properties": {
    "addr:full":"5109 Trafalgar Rd Ballinafad ON N0B 1H0",
    "addr:housenumber":"5109",
    "addr:postcode":"n0b 1h0",
    "addr:street":"Trafalgar Rd",
    "iso:country":"CA",
    "sg:address":"5109 Trafalgar Rd",
    "sg:city":"Ballinafad",
    "sg:classifiers":[
        {
            "category":"Wholesale",
            "subcategory":"Machinery & Supplies",
            "type":"Manufacturing & Wholesale Goods"
        }
    ],
    "sg:phone":"+1 905 873 8502",
    "sg:postcode":"N0B 1H0",
    "sg:province":"ON",
    "sg:tags":[
        "equipment",
        "material",
        "handling",
        "welding"
    ],
    "wof:name":"Srt Contracting Ltd",
    "wof:placetype":"venue"
},
  "geometry": {"coordinates":[-79.985275,43.676022],"type":"Point"}
}