{
  "type": "Feature",
  "properties": {
    "addr:full":"275 Bank St # 301 Ottawa ON K2P 2L6",
    "addr:housenumber":"275",
    "addr:postcode":"k2p 2l6",
    "addr:street":"Bank St # 301",
    "iso:country":"CA",
    "sg:address":"275 Bank St # 301",
    "sg:city":"Ottawa",
    "sg:classifiers":[
        {
            "category":"Professional",
            "subcategory":"Business Services",
            "type":"Services"
        }
    ],
    "sg:phone":"+1 613 722 0106",
    "sg:postcode":"K2P 2L6",
    "sg:province":"ON",
    "sg:tags":[
        "interior",
        "consultant",
        "design",
        "decorator"
    ],
    "wof:name":"Susan Firestone Design Ltd",
    "wof:placetype":"venue"
},
  "geometry": {"coordinates":[-75.69641113279999,45.4156455994],"type":"Point"}
}