{
  "type": "Feature",
  "properties": {
    "addr:full":"87 Hespeler Ave Winnipeg MB R2L 0L2",
    "addr:housenumber":"87",
    "addr:postcode":"r2l 0l2",
    "addr:street":"Hespeler Ave",
    "iso:country":"CA",
    "sg:address":"87 Hespeler Ave",
    "sg:city":"Winnipeg",
    "sg:classifiers":[
        {
            "category":"Retail",
            "subcategory":"Auto Repair",
            "type":"Services"
        }
    ],
    "sg:phone":"+1 204 667 4705",
    "sg:postcode":"R2L 0L2",
    "sg:province":"MB",
    "sg:tags":[
        "repairing",
        "automobile"
    ],
    "wof:name":"Goertzen Auto Svc",
    "wof:placetype":"venue"
},
  "geometry": {"coordinates":[-97.121414,49.914627],"type":"Point"}
}