{
  "type": "Feature",
  "properties": {
    "addr:full":"225 Metcalfe St # B Ottawa ON K2P 1P9",
    "addr:housenumber":"225",
    "addr:postcode":"k2p 1p9",
    "addr:street":"Metcalfe St # B",
    "iso:country":"CA",
    "sg:address":"225 Metcalfe St # B",
    "sg:city":"Ottawa",
    "sg:classifiers":[
        {
            "category":"Restaurant",
            "type":"Food & Drink"
        }
    ],
    "sg:phone":"+1 613 235 2089",
    "sg:postcode":"K2P 1P9",
    "sg:province":"ON",
    "wof:name":"Kenson Kafe",
    "wof:placetype":"venue"
},
  "geometry": {"coordinates":[-75.69270299999999,45.417572],"type":"Point"}
}