{
  "type": "Feature",
  "properties": {
    "addr:full":"421 Av Sainte-Dorothee Louiseville QC J5V 1R2",
    "addr:postcode":"j5v 1r2",
    "addr:street":"421 Av Sainte-Dorothee",
    "iso:country":"CA",
    "sg:address":"421 Av Sainte-Dorothee",
    "sg:city":"Louiseville",
    "sg:classifiers":[
        {
            "category":"Building & Trades",
            "subcategory":"Construction",
            "type":"Services"
        }
    ],
    "sg:phone":"+1 819 228 3620",
    "sg:postcode":"J5V 1R2",
    "sg:province":"QC",
    "sg:tags":[
        "repairing",
        "remodeling",
        "contractor"
    ],
    "wof:name":"Construction A Pichette Inc",
    "wof:placetype":"venue"
},
  "geometry": {"coordinates":[-72.947303772,46.2537155151],"type":"Point"}
}