{
  "type": "Feature",
  "properties": {
    "addr:full":"9004 Yellowhead Trail NW Edmonton AB T5B 1G2",
    "addr:housenumber":"9004",
    "addr:postcode":"t5b 1g2",
    "addr:street":"Yellowhead Trail Nw",
    "iso:country":"CA",
    "sg:address":"9004 Yellowhead Trail NW",
    "sg:city":"Edmonton",
    "sg:classifiers":[
        {
            "category":"Farming",
            "subcategory":"Farm",
            "type":"Manufacturing & Wholesale Goods"
        }
    ],
    "sg:phone":"+1 780 998 3171",
    "sg:postcode":"T5B 1G2",
    "sg:province":"AB",
    "wof:name":"S V Half Diamond Ranch",
    "wof:placetype":"venue"
},
  "geometry": {"coordinates":[-113.47984314,53.5816192627],"type":"Point"}
}