{
  "type": "Feature",
  "properties": {
    "addr:full":"243 Henryvilla Dr Cambridge ON N3C 1B1",
    "addr:housenumber":"243",
    "addr:postcode":"n3c 1b1",
    "addr:street":"Henryvilla Dr",
    "iso:country":"CA",
    "sg:address":"243 Henryvilla Dr",
    "sg:city":"Cambridge",
    "sg:classifiers":[
        {
            "category":"Professional",
            "subcategory":"Accounting & Tax Preparation",
            "type":"Services"
        }
    ],
    "sg:phone":"+1 519 658 9813",
    "sg:postcode":"N3C 1B1",
    "sg:province":"ON",
    "sg:tags":[
        "accountant"
    ],
    "wof:name":"Maier, Barbara CA",
    "wof:placetype":"venue"
},
  "geometry": {"coordinates":[-80.311188,43.439449],"type":"Point"}
}