{
  "type": "Feature",
  "properties": {
    "addr:full":"50 Mumford Rd Lively ON P3Y 1L2",
    "addr:housenumber":"50",
    "addr:postcode":"p3y 1l2",
    "addr:street":"Mumford Rd",
    "iso:country":"CA",
    "sg:address":"50 Mumford Rd",
    "sg:city":"Lively",
    "sg:classifiers":[
        {
            "category":"Manufacturing",
            "subcategory":"Chemicals & Compounds",
            "type":"Manufacturing & Wholesale Goods"
        }
    ],
    "sg:phone":"+1 705 692 2959",
    "sg:postcode":"P3Y 1L2",
    "sg:province":"ON",
    "sg:tags":[
        "equipment",
        "industrial",
        "supply"
    ],
    "wof:name":"Reliable Industrial Supply",
    "wof:placetype":"venue"
},
  "geometry": {"coordinates":[-81.109871,46.43264],"type":"Point"}
}