{
  "type": "Feature",
  "properties": {
    "addr:full":"5418 Yonge St North York ON M2N 6X4",
    "addr:housenumber":"5418",
    "addr:postcode":"m2n 6x4",
    "addr:street":"Yonge St",
    "iso:country":"CA",
    "sg:address":"5418 Yonge St",
    "sg:city":"North York",
    "sg:classifiers":[
        {
            "category":"Food & Beverages",
            "subcategory":"Bakery",
            "type":"Retail Goods"
        }
    ],
    "sg:phone":"+1 416 733 9300",
    "sg:postcode":"M2N 6X4",
    "sg:province":"ON",
    "sg:tags":[
        "baker"
    ],
    "wof:name":"Jin Cheng Bakery Ltd",
    "wof:placetype":"venue"
},
  "geometry": {"coordinates":[-79.4147567749,43.775970459],"type":"Point"}
}