{
  "type": "Feature",
  "properties": {
    "addr:full":"365 Rue Racine E # 14 Chicoutimi QC G7H 1S8",
    "addr:housenumber":"365",
    "addr:postcode":"g7h 1s8",
    "addr:street":"Rue Racine E # 14",
    "iso:country":"CA",
    "sg:address":"365 Rue Racine E # 14",
    "sg:city":"Chicoutimi",
    "sg:classifiers":[
        {
            "category":"Professional",
            "subcategory":"Advertising",
            "type":"Services"
        }
    ],
    "sg:phone":"+1 418 549 2628",
    "sg:postcode":"G7H 1S8",
    "sg:province":"QC",
    "sg:tags":[
        "publicity"
    ],
    "wof:name":"Jacques Lemay Conception Grphq",
    "wof:placetype":"venue"
},
  "geometry": {"coordinates":[-71.05744900000001,48.427696],"type":"Point"}
}