{
  "type": "Feature",
  "properties": {
    "addr:full":"2525 36 St NE # K1 Calgary AB T1Y 5T4",
    "addr:housenumber":"2525",
    "addr:postcode":"t1y 5t4",
    "addr:street":"36 St Ne # K1",
    "iso:country":"CA",
    "sg:address":"2525 36 St NE # K1",
    "sg:city":"Calgary",
    "sg:classifiers":[
        {
            "category":"Shopping",
            "subcategory":"Jewelry",
            "type":"Retail Goods"
        }
    ],
    "sg:phone":"+1 403 293 0377",
    "sg:postcode":"T1Y 5T4",
    "sg:province":"AB",
    "sg:tags":[
        "watch"
    ],
    "wof:name":"Time Temptations",
    "wof:placetype":"venue"
},
  "geometry": {"coordinates":[-113.982177734,51.0741271973],"type":"Point"}
}