{
  "type": "Feature",
  "properties": {
    "addr:full":"529 Rue Principale Saint-Leonard-DE-Portneuf QC G0A 4A0",
    "addr:housenumber":"529",
    "addr:postcode":"g0a 4a0",
    "addr:street":"Rue Principale",
    "iso:country":"CA",
    "sg:address":"529 Rue Principale",
    "sg:city":"Saint-Leonard-DE-Portneuf",
    "sg:classifiers":[
        {
            "category":"Organizations",
            "subcategory":"Religious Organization",
            "type":"Services"
        }
    ],
    "sg:phone":"+1 418 337 2312",
    "sg:postcode":"G0A 4A0",
    "sg:province":"QC",
    "sg:tags":[
        "church"
    ],
    "wof:name":"Presbytere St-Leonard",
    "wof:placetype":"venue"
},
  "geometry": {"coordinates":[-71.90808868409999,46.8900413513],"type":"Point"}
}