{
  "type": "Feature",
  "properties": {
    "addr:full":"1938 Dewdney Ave Regina SK S4R 1G9",
    "addr:housenumber":"1938",
    "addr:postcode":"s4r 1g9",
    "addr:street":"Dewdney Ave",
    "iso:country":"CA",
    "sg:address":"1938 Dewdney Ave",
    "sg:city":"Regina",
    "sg:classifiers":[
        {
            "category":"Home & Garden",
            "subcategory":"Home Furnishings",
            "type":"Retail Goods"
        }
    ],
    "sg:phone":"+1 306 352 8601",
    "sg:postcode":"S4R 1G9",
    "sg:province":"SK",
    "sg:tags":[
        "shop",
        "made",
        "fabric",
        "drapery"
    ],
    "wof:name":"Fabricland",
    "wof:placetype":"venue"
},
  "geometry": {"coordinates":[-104.608543,50.45525],"type":"Point"}
}