{
  "type": "Feature",
  "properties": {
    "addr:full":"100 Av Des Pins E Montreal QC H2W 1N7",
    "addr:postcode":"h2w 1n7",
    "addr:street":"100 Av Des Pins E",
    "iso:country":"CA",
    "sg:address":"100 Av Des Pins E",
    "sg:city":"Montreal",
    "sg:classifiers":[
        {
            "category":"Cinema",
            "subcategory":"Movie Theater",
            "type":"Entertainment"
        }
    ],
    "sg:phone":"+1 514 845 7277",
    "sg:postcode":"H2W 1N7",
    "sg:province":"QC",
    "wof:name":"Theatre DE Quat'Sous",
    "wof:placetype":"venue"
},
  "geometry": {"coordinates":[-73.57418800000001,45.516026],"type":"Point"}
}