{
  "type": "Feature",
  "properties": {
    "addr:full":"284 Rue Temiscouata Riviere-Du-Loup QC G5R 2Y5",
    "addr:housenumber":"284",
    "addr:postcode":"g5r 2y5",
    "addr:street":"Rue Temiscouata Riviere-Du-Loup",
    "iso:country":"CA",
    "sg:address":"284 Rue Temiscouata",
    "sg:city":"Riviere-Du-Loup",
    "sg:classifiers":[
        {
            "category":"Freight",
            "type":"Transportation"
        }
    ],
    "sg:phone":"+1 418 867 3219",
    "sg:postcode":"G5R 2Y5",
    "sg:province":"QC",
    "sg:tags":[
        "trucking"
    ],
    "wof:name":"Transport Pettigrew Inc",
    "wof:placetype":"venue"
},
  "geometry": {"coordinates":[-69.513321,47.822296],"type":"Point"}
}