{
  "type": "Feature",
  "properties": {
    "addr:full":"Neepawa MB R0J 1H0",
    "addr:postcode":"r0j 1h0",
    "iso:country":"CA",
    "sg:city":"Neepawa",
    "sg:classifiers":[
        {
            "category":"Professional",
            "subcategory":"Lawyer & Legal Services",
            "type":"Services"
        }
    ],
    "sg:phone":"+1 204 476 2336",
    "sg:postcode":"R0J 1H0",
    "sg:province":"MB",
    "sg:tags":[
        "attorney"
    ],
    "wof:name":"Taylor Law Office",
    "wof:placetype":"venue"
},
  "geometry": {"coordinates":[-99.4650650024,50.2285041809],"type":"Point"}
}