{
  "type": "Feature",
  "properties": {
    "addr:full":"Calgary AB T2L 1K8",
    "addr:postcode":"t2l 1k8",
    "iso:country":"CA",
    "sg:city":"Calgary",
    "sg:classifiers":[
        {
            "category":"Health Services",
            "subcategory":"Medical Lab",
            "type":"Services"
        }
    ],
    "sg:phone":"+1 403 282 1225",
    "sg:postcode":"T2L 1K8",
    "sg:province":"AB",
    "wof:name":"Brentwood Village Denture Clnc",
    "wof:placetype":"venue"
},
  "geometry": {"coordinates":[-114.128761,51.086182],"type":"Point"}
}