{
  "type": "Feature",
  "properties": {
    "addr:full":"Prince George BC V2K 2X5",
    "addr:postcode":"v2k 2x5",
    "iso:country":"CA",
    "sg:city":"Prince George",
    "sg:classifiers":[
        {
            "category":"Autos & Motor Vehicles",
            "subcategory":"Motorcycle Sales",
            "type":"Retail Goods"
        }
    ],
    "sg:phone":"+1 250 563 7977",
    "sg:postcode":"V2K 2X5",
    "sg:province":"BC",
    "sg:tags":[
        "scooter"
    ],
    "wof:name":"B & B Custom Cycle",
    "wof:placetype":"venue"
},
  "geometry": {"coordinates":[-122.745087,53.91235],"type":"Point"}
}