{
  "type": "Feature",
  "properties": {
    "addr:full":"North York ON M1R 1P7",
    "addr:postcode":"m1r 1p7",
    "iso:country":"CA",
    "sg:city":"North York",
    "sg:classifiers":[
        {
            "category":"Restaurant",
            "type":"Food & Drink"
        }
    ],
    "sg:phone":"+1 416 288 8210",
    "sg:postcode":"M1R 1P7",
    "sg:province":"ON",
    "wof:name":"Chicken & Ribs Depot",
    "wof:placetype":"venue"
},
  "geometry": {"coordinates":[-79.30590100000001,43.732239],"type":"Point"}
}