{
  "type": "Feature",
  "properties": {
    "addr:full":"1252 Shawson Dr Mississauga ON L4W 1C3",
    "addr:housenumber":"1252",
    "addr:postcode":"l4w 1c3",
    "addr:street":"Shawson Dr",
    "iso:country":"CA",
    "sg:address":"1252 Shawson Dr",
    "sg:city":"Mississauga",
    "sg:classifiers":[
        {
            "category":"Autos & Motor Vehicles",
            "subcategory":"Automobile Sales",
            "type":"Retail Goods"
        }
    ],
    "sg:phone":"+1 905 564 4944",
    "sg:postcode":"L4W 1C3",
    "sg:province":"ON",
    "sg:tags":[
        "truck"
    ],
    "wof:name":"Universal Truck Sales Ltd",
    "wof:placetype":"venue"
},
  "geometry": {"coordinates":[-79.648399,43.64819],"type":"Point"}
}