{
  "type": "Feature",
  "properties": {
    "addr:full":"1777 Branchwood Pk Mississauga ON L4W 2E5",
    "addr:housenumber":"1777",
    "addr:postcode":"l4w 2e5",
    "addr:street":"Branchwood Pk",
    "iso:country":"CA",
    "sg:address":"1777 Branchwood Pk",
    "sg:city":"Mississauga",
    "sg:classifiers":[
        {
            "category":"Professional",
            "subcategory":"Business Services",
            "type":"Services"
        }
    ],
    "sg:phone":"+1 905 625 1451",
    "sg:postcode":"L4W 2E5",
    "sg:province":"ON",
    "sg:tags":[
        "drafting"
    ],
    "wof:name":"Z K Design & Drafting Svc Ltd",
    "wof:placetype":"venue"
},
  "geometry": {"coordinates":[-79.595406,43.632336],"type":"Point"}
}