{
  "type": "Feature",
  "properties": {
    "addr:full":"Port Borden PE C0B 1X0",
    "addr:postcode":"c0b 1x0",
    "iso:country":"CA",
    "sg:city":"Port Borden",
    "sg:classifiers":[
        {
            "category":"Shopping",
            "subcategory":"Gifts & Souvenirs",
            "type":"Retail Goods"
        }
    ],
    "sg:phone":"+1 902 437 6421",
    "sg:postcode":"C0B 1X0",
    "sg:province":"PE",
    "sg:tags":[
        "shop"
    ],
    "wof:name":"Official Island Store",
    "wof:placetype":"venue"
},
  "geometry": {"coordinates":[-63.6955184937,46.2549972534],"type":"Point"}
}