{
  "type": "Feature",
  "properties": {
    "iso:country":"CA",
    "sg:city":"Oakville",
    "sg:classifiers":[
        {
            "category":"Personal",
            "type":"Services"
        }
    ],
    "sg:phone":"+1 905 842 7249",
    "sg:postcode":"L6J 3C7",
    "sg:province":"ON",
    "sg:tags":[
        "electrolysis"
    ],
    "wof:name":"Natures Aesthetics",
    "wof:placetype":"venue"
},
  "geometry": {"coordinates":[-79.667175,43.446278],"type":"Point"}
}