{
  "type": "Feature",
  "properties": {
    "addr:full":"650 Rue Descartes Chicoutimi QC G7J 4H2",
    "addr:housenumber":"650",
    "addr:postcode":"g7j 4h2",
    "addr:street":"Rue Descartes",
    "iso:country":"CA",
    "sg:address":"650 Rue Descartes",
    "sg:city":"Chicoutimi",
    "sg:classifiers":[
        {
            "category":"Insurance",
            "subcategory":"Insurance Agent",
            "type":"Services"
        }
    ],
    "sg:phone":"+1 418 543 0496",
    "sg:postcode":"G7J 4H2",
    "sg:province":"QC",
    "sg:tags":[
        "consultant"
    ],
    "wof:name":"Services Conseils Ac-Gbs",
    "wof:placetype":"venue"
},
  "geometry": {"coordinates":[-71.091759,48.406952],"type":"Point"}
}