{
  "type": "Feature",
  "properties": {
    "addr:full":"734 Bank St Ottawa ON K1S 3V4",
    "addr:housenumber":"734",
    "addr:postcode":"k1s 3v4",
    "addr:street":"Bank St",
    "iso:country":"CA",
    "sg:address":"734 Bank St",
    "sg:city":"Ottawa",
    "sg:classifiers":[
        {
            "category":"Restaurant",
            "type":"Food & Drink"
        }
    ],
    "sg:phone":"+1 613 235 4740",
    "sg:postcode":"K1S 3V4",
    "sg:province":"ON",
    "sg:tags":[
        "shop",
        "coffee"
    ],
    "wof:name":"Morala Specialty Coffee",
    "wof:placetype":"venue"
},
  "geometry": {"coordinates":[-75.68914794920001,45.404083252],"type":"Point"}
}