{
  "type": "Feature",
  "properties": {
    "addr:full":"3924 Victoria Ave Vineland ON L0R 2C0",
    "addr:housenumber":"3924",
    "addr:postcode":"l0r 2c0",
    "addr:street":"Victoria Ave",
    "iso:country":"CA",
    "sg:address":"3924 Victoria Ave",
    "sg:city":"Vineland",
    "sg:classifiers":[
        {
            "category":"Personal",
            "subcategory":"Beauty Salon",
            "type":"Services"
        }
    ],
    "sg:phone":"+1 905 562 7206",
    "sg:postcode":"L0R 2C0",
    "sg:province":"ON",
    "wof:name":"House of Hair Design",
    "wof:placetype":"venue"
},
  "geometry": {"coordinates":[-79.39308200000001,43.152309],"type":"Point"}
}