{
  "type": "Feature",
  "properties": {
    "addr:full":"714 Central St Centreville NB E7K 2M5",
    "addr:housenumber":"714",
    "addr:postcode":"e7k 2m5",
    "addr:street":"Central St",
    "iso:country":"CA",
    "sg:address":"714 Central St",
    "sg:city":"Centreville",
    "sg:classifiers":[
        {
            "category":"Wholesale",
            "subcategory":"Machinery & Supplies",
            "type":"Manufacturing & Wholesale Goods"
        }
    ],
    "sg:phone":"+1 506 276 4591",
    "sg:postcode":"E7K 2M5",
    "sg:province":"NB",
    "sg:tags":[
        "farm",
        "equipment"
    ],
    "wof:name":"Centreville Equipment Ltd",
    "wof:placetype":"venue"
},
  "geometry": {"coordinates":[-67.711243,46.430885],"type":"Point"}
}