{
  "type": "Feature",
  "properties": {
    "addr:full":"63 John St Kingston ON K7K 1S8",
    "addr:housenumber":"63",
    "addr:postcode":"k7k 1s8",
    "addr:street":"John St",
    "iso:country":"CA",
    "sg:address":"63 John St",
    "sg:city":"Kingston",
    "sg:classifiers":[
        {
            "category":"Food & Beverages",
            "subcategory":"Groceries & Convenience Stores",
            "type":"Retail Goods"
        }
    ],
    "sg:phone":"+1 613 544 9808",
    "sg:postcode":"K7K 1S8",
    "sg:province":"ON",
    "wof:name":"Pat's Grocery",
    "wof:placetype":"venue"
},
  "geometry": {"coordinates":[-76.488602,44.238632],"type":"Point"}
}