{
  "type": "Feature",
  "properties": {
    "addr:full":"Vaudreuil-Dorion QC J7V 8P2",
    "addr:postcode":"j7v 8p2",
    "iso:country":"CA",
    "sg:city":"Vaudreuil-Dorion",
    "sg:classifiers":[
        {
            "category":"Professional",
            "subcategory":"Business Services",
            "type":"Services"
        }
    ],
    "sg:phone":"+1 450 967 0000",
    "sg:postcode":"J7V 8P2",
    "sg:province":"QC",
    "sg:tags":[
        "water",
        "equipment",
        "treatment",
        "softening"
    ],
    "wof:name":"Culligan DE Sud-Ouest Du Quebe",
    "wof:placetype":"venue"
},
  "geometry": {"coordinates":[-74.0438079834,45.3718528748],"type":"Point"}
}