{
  "type": "Feature",
  "properties": {
    "addr:full":"2245 Kennedy Rd Scarborough ON M1T 3G8",
    "addr:housenumber":"2245",
    "addr:postcode":"m1t 3g8",
    "addr:street":"Kennedy Rd",
    "iso:country":"CA",
    "sg:address":"2245 Kennedy Rd",
    "sg:city":"Scarborough",
    "sg:classifiers":[
        {
            "category":"Shopping",
            "subcategory":"Optical Goods",
            "type":"Retail Goods"
        }
    ],
    "sg:phone":"+1 416 292 8686",
    "sg:postcode":"M1T 3G8",
    "sg:province":"ON",
    "sg:tags":[
        "optician"
    ],
    "wof:name":"Hakim Optical Factory Outlet",
    "wof:placetype":"venue"
},
  "geometry": {"coordinates":[-79.2873916626,43.7821044922],"type":"Point"}
}