{
  "type": "Feature",
  "properties": {
    "addr:full":"25 Barnaby Dr #204 St Catharines ON L2S 3N9",
    "addr:housenumber":"25",
    "addr:postcode":"l2s 3n9",
    "addr:street":"Barnaby Dr # 204",
    "iso:country":"CA",
    "sg:address":"25 Barnaby Dr #204",
    "sg:city":"St Catharines",
    "sg:classifiers":[
        {
            "category":"Freight",
            "type":"Transportation"
        }
    ],
    "sg:phone":"+1 905 327 9775",
    "sg:postcode":"L2S 3N9",
    "sg:province":"ON",
    "sg:tags":[
        "delivery"
    ],
    "wof:name":"Reliable Deliveries",
    "wof:placetype":"venue"
},
  "geometry": {"coordinates":[-79.2611160278,43.1527709961],"type":"Point"}
}