{
  "type": "Feature",
  "properties": {
    "iso:country":"CA",
    "sg:address":"791 Rue Laval",
    "sg:city":"Casselman",
    "sg:classifiers":[
        {
            "category":"Building & Trades",
            "subcategory":"Construction",
            "type":"Services"
        }
    ],
    "sg:phone":"+1 613 764 0891",
    "sg:postcode":"K0A 1M0",
    "sg:province":"ON",
    "sg:tags":[
        "equipment",
        "computer",
        "rooms"
    ],
    "wof:name":"D P Environmental Svc",
    "wof:placetype":"venue"
},
  "geometry": {"coordinates":[-75.09432983400001,45.3134880066],"type":"Point"}
}