{
  "type": "Feature",
  "properties": {
    "iso:country":"CA",
    "sg:address":"RR 1 STN Main",
    "sg:city":"Georgetown",
    "sg:classifiers":[
        {
            "category":"Building & Trades",
            "subcategory":"Construction",
            "type":"Services"
        }
    ],
    "sg:phone":"+1 905 873 1127",
    "sg:postcode":"L7G 4S4",
    "sg:province":"ON",
    "sg:tags":[
        "general",
        "contractor"
    ],
    "wof:name":"Sye Vandermeer Construction",
    "wof:placetype":"venue"
},
  "geometry": {"coordinates":[-79.89888000489999,43.6500091553],"type":"Point"}
}