{
  "type": "Feature",
  "properties": {
    "addr:full":"1010 Alderson Ave Coquitlam BC V3K 1W1",
    "addr:housenumber":"1010",
    "addr:postcode":"v3k 1w1",
    "addr:street":"Alderson Ave",
    "iso:country":"CA",
    "sg:address":"1010 Alderson Ave",
    "sg:city":"Coquitlam",
    "sg:classifiers":[
        {
            "category":"Health Services",
            "subcategory":"Nursing And Care Facility",
            "type":"Services"
        }
    ],
    "sg:phone":"+1 604 937 5578",
    "sg:postcode":"V3K 1W1",
    "sg:province":"BC",
    "sg:tags":[
        "home",
        "retirement",
        "community"
    ],
    "wof:name":"Foyer Maillard",
    "wof:placetype":"venue"
},
  "geometry": {"coordinates":[-122.866524,49.239616],"type":"Point"}
}