{
  "type": "Feature",
  "properties": {
    "addr:full":"2049 Scarth St Regina SK S4P 2H5",
    "addr:housenumber":"2049",
    "addr:postcode":"s4p 2h5",
    "addr:street":"Scarth St",
    "iso:country":"CA",
    "sg:address":"2049 Scarth St",
    "sg:city":"Regina",
    "sg:classifiers":[
        {
            "category":"Organizations",
            "subcategory":"Religious Organization",
            "type":"Services"
        }
    ],
    "sg:phone":"+1 306 522 7422",
    "sg:postcode":"S4P 2H5",
    "sg:province":"SK",
    "sg:tags":[
        "church"
    ],
    "wof:name":"Blessed Sacrament Church",
    "wof:placetype":"venue"
},
  "geometry": {"coordinates":[-104.610626221,50.4463424683],"type":"Point"}
}