{
  "type": "Feature",
  "properties": {
    "addr:full":"Delta BC V3M 6K7",
    "addr:postcode":"v3m 6k7",
    "iso:country":"CA",
    "sg:city":"Delta",
    "sg:classifiers":[
        {
            "category":"Building & Trades",
            "subcategory":"Construction",
            "type":"Services"
        }
    ],
    "sg:phone":"+1 604 298 2434",
    "sg:postcode":"V3M 6K7",
    "sg:province":"BC",
    "sg:tags":[
        "fireproofing"
    ],
    "wof:name":"Alexander Installations Inc",
    "wof:placetype":"venue"
},
  "geometry": {"coordinates":[-122.95858,49.161541],"type":"Point"}
}