{
  "type": "Feature",
  "properties": {
    "addr:full":"156 Geneva St St Catharines ON L2R 4N9",
    "addr:housenumber":"156",
    "addr:postcode":"l2r 4n9",
    "addr:street":"Geneva St",
    "iso:country":"CA",
    "sg:address":"156 Geneva St",
    "sg:city":"St Catharines",
    "sg:classifiers":[
        {
            "category":"Shopping",
            "subcategory":"Clothing, Apparel, & Fashions",
            "type":"Retail Goods"
        }
    ],
    "sg:phone":"+1 905 984 4212",
    "sg:postcode":"L2R 4N9",
    "sg:province":"ON",
    "sg:tags":[
        "designer"
    ],
    "wof:name":"Nancy Clare Couturiere",
    "wof:placetype":"venue"
},
  "geometry": {"coordinates":[-79.2402801514,43.1690979004],"type":"Point"}
}