{
  "type": "Feature",
  "properties": {
    "addr:full":"119 Main St W Ethelbert MB R0L 0T0",
    "addr:housenumber":"119",
    "addr:postcode":"r0l 0t0",
    "addr:street":"Main St W Ethelbert",
    "iso:country":"CA",
    "sg:address":"119 Main St W",
    "sg:city":"Ethelbert",
    "sg:classifiers":[
        {
            "category":"Wholesale",
            "subcategory":"Groceries",
            "type":"Manufacturing & Wholesale Goods"
        }
    ],
    "sg:phone":"+1 204 742 3555",
    "sg:postcode":"R0L 0T0",
    "sg:province":"MB",
    "sg:tags":[
        "honey"
    ],
    "wof:name":"Podolski Honey Farms",
    "wof:placetype":"venue"
},
  "geometry": {"coordinates":[-100.39846,51.525059],"type":"Point"}
}