{
  "type": "Feature",
  "properties": {
    "iso:country":"CA",
    "sg:address":"2821 Huntington Pl",
    "sg:city":"Port Coquitlam",
    "sg:classifiers":[
        {
            "category":"Manufacturing",
            "subcategory":"Signs",
            "type":"Manufacturing & Wholesale Goods"
        }
    ],
    "sg:phone":"+1 604 941 2300",
    "sg:postcode":"V3C 4T3",
    "sg:province":"BC",
    "wof:name":"Classic Neon",
    "wof:placetype":"venue"
},
  "geometry": {"coordinates":[-122.793952942,49.2848854065],"type":"Point"}
}