{
  "type": "Feature",
  "properties": {
    "addr:full":"76 King St W Oshawa ON L1H 1A6",
    "addr:housenumber":"76",
    "addr:postcode":"l1h 1a6",
    "addr:street":"King St W",
    "iso:country":"CA",
    "sg:address":"76 King St W",
    "sg:city":"Oshawa",
    "sg:classifiers":[
        {
            "category":"Professional",
            "subcategory":"Accounting & Tax Preparation",
            "type":"Services"
        }
    ],
    "sg:phone":"+1 905 571 4423",
    "sg:postcode":"L1H 1A6",
    "sg:province":"ON",
    "sg:tags":[
        "accountant"
    ],
    "wof:name":"Clapp, Michael W CA",
    "wof:placetype":"venue"
},
  "geometry": {"coordinates":[-78.866699,43.897026],"type":"Point"}
}