{
  "type": "Feature",
  "properties": {
    "addr:full":"PO Box 39 Widewater AB T0G 2M0",
    "addr:housenumber":"po box 39",
    "addr:postcode":"t0g 2m0",
    "addr:street":"Widewater Ab",
    "iso:country":"CA",
    "sg:address":"PO Box 39",
    "sg:city":"Widewater",
    "sg:classifiers":[
        {
            "category":"Freight",
            "type":"Transportation"
        }
    ],
    "sg:phone":"+1 780 369 2191",
    "sg:postcode":"T0G 2M0",
    "sg:province":"AB",
    "sg:tags":[
        "trucking"
    ],
    "wof:name":"Ro-Bar Trucking Ltd",
    "wof:placetype":"venue"
},
  "geometry": {"coordinates":[-115.04830200000001,55.361191],"type":"Point"}
}