{
  "type": "Feature",
  "properties": {
    "iso:country":"CA",
    "sg:address":"1801 Broad St",
    "sg:city":"Regina",
    "sg:classifiers":[
        {
            "category":"Banks & Credit Unions",
            "subcategory":"Bank",
            "type":"Services"
        }
    ],
    "sg:phone":"+1 306 522 2694",
    "sg:postcode":"S4P 1X7",
    "sg:province":"SK",
    "sg:tags":[
        "cashing",
        "check"
    ],
    "wof:name":"Money Mart Cheque Cashing Ctr",
    "wof:placetype":"venue"
},
  "geometry": {"coordinates":[-104.60621643099999,50.4502029419],"type":"Point"}
}