{
  "type": "Feature",
  "properties": {
    "addr:full":"Williamsford ON N0H 2V0",
    "addr:postcode":"n0h 2v0",
    "iso:country":"CA",
    "sg:city":"Williamsford",
    "sg:classifiers":[
        {
            "category":"Home & Garden",
            "subcategory":"Hardware",
            "type":"Retail Goods"
        }
    ],
    "sg:phone":"+1 519 794 2034",
    "sg:postcode":"N0H 2V0",
    "sg:province":"ON",
    "wof:name":"Elliot's Hardware",
    "wof:placetype":"venue"
},
  "geometry": {"coordinates":[-80.87033081049999,44.3737411499],"type":"Point"}
}