{
  "type": "Feature",
  "properties": {
    "addr:full":"115 Adrian Cres Markham ON L3P 7B1",
    "addr:housenumber":"115",
    "addr:postcode":"l3p 7b1",
    "addr:street":"Adrian Cres",
    "iso:country":"CA",
    "sg:address":"115 Adrian Cres",
    "sg:city":"Markham",
    "sg:classifiers":[
        {
            "category":"Wholesale",
            "subcategory":"Office Equipment",
            "type":"Manufacturing & Wholesale Goods"
        }
    ],
    "sg:phone":"+1 905 472 8562",
    "sg:postcode":"L3P 7B1",
    "sg:province":"ON",
    "sg:tags":[
        "dictating",
        "machine",
        "supply"
    ],
    "wof:name":"Banfield Business Systems Ltd",
    "wof:placetype":"venue"
},
  "geometry": {"coordinates":[-79.287544,43.884026],"type":"Point"}
}