{
  "type": "Feature",
  "properties": {
    "addr:full":"212 Macdonnell St Kingston ON K7L 4C2",
    "addr:housenumber":"212",
    "addr:postcode":"k7l 4c2",
    "addr:street":"Macdonnell St",
    "iso:country":"CA",
    "sg:address":"212 Macdonnell St",
    "sg:city":"Kingston",
    "sg:classifiers":[
        {
            "category":"Retail",
            "subcategory":"Repair Shop",
            "type":"Services"
        }
    ],
    "sg:phone":"+1 613 544 0848",
    "sg:postcode":"K7L 4C2",
    "sg:province":"ON",
    "sg:tags":[
        "welding"
    ],
    "wof:name":"Mc Crady, James P",
    "wof:placetype":"venue"
},
  "geometry": {"coordinates":[-76.505241,44.231834],"type":"Point"}
}