{
  "type": "Feature",
  "properties": {
    "addr:full":"85 Rue DE LA Commune E Montreal QC H2Y 1J1",
    "addr:housenumber":"85",
    "addr:postcode":"h2y 1j1",
    "addr:street":"Rue De La Commune E",
    "iso:country":"CA",
    "sg:address":"85 Rue DE LA Commune E",
    "sg:city":"Montreal",
    "sg:classifiers":[
        {
            "category":"Professional",
            "subcategory":"Lawyer & Legal Services",
            "type":"Services"
        }
    ],
    "sg:phone":"+1 514 871 8385",
    "sg:postcode":"H2Y 1J1",
    "sg:province":"QC",
    "sg:tags":[
        "attorney"
    ],
    "wof:name":"Trudel & Johnston",
    "wof:placetype":"venue"
},
  "geometry": {"coordinates":[-73.5527496338,45.5065231323],"type":"Point"}
}