{
  "type": "Feature",
  "properties": {
    "iso:country":"CA",
    "sg:address":"85 Rue DE LA Commune E",
    "sg:city":"Montreal",
    "sg:classifiers":[
        {
            "category":"Professional",
            "subcategory":"Lawyer & Legal Services",
            "type":"Services"
        }
    ],
    "sg:phone":"+1 514 871 8385",
    "sg:postcode":"H2Y 1J1",
    "sg:province":"QC",
    "sg:tags":[
        "attorney"
    ],
    "wof:name":"Trudel & Johnston",
    "wof:placetype":"venue"
},
  "geometry": {"coordinates":[-73.5527496338,45.5065231323],"type":"Point"}
}