{
  "type": "Feature",
  "properties": {
    "iso:country":"CA",
    "sg:address":"555 Boul Dr.-Frederik-Philips",
    "sg:city":"Saint-Laurent",
    "sg:classifiers":[
        {
            "category":"Wholesale",
            "subcategory":"Computers",
            "type":"Manufacturing & Wholesale Goods"
        }
    ],
    "sg:phone":"+1 514 747 4646",
    "sg:postcode":"H4M 2X4",
    "sg:province":"QC",
    "sg:tags":[
        "communications",
        "datum"
    ],
    "wof:name":"Simpler Networks Inc",
    "wof:placetype":"venue"
},
  "geometry": {"coordinates":[-73.6916427612,45.4953193665],"type":"Point"}
}