{
  "type": "Feature",
  "properties": {
    "addr:full":"3275 Deziel Dr Windsor ON N8W 5A5",
    "addr:housenumber":"3275",
    "addr:postcode":"n8w 5a5",
    "addr:street":"Deziel Dr",
    "iso:country":"CA",
    "sg:address":"3275 Deziel Dr",
    "sg:city":"Windsor",
    "sg:classifiers":[
        {
            "category":"Manufacturing",
            "subcategory":"Tools & Machinery",
            "type":"Manufacturing & Wholesale Goods"
        }
    ],
    "sg:phone":"+1 519 948 5001",
    "sg:postcode":"N8W 5A5",
    "sg:province":"ON",
    "sg:tags":[
        "mold"
    ],
    "wof:name":"Components Manufacturing Ind",
    "wof:placetype":"venue"
},
  "geometry": {"coordinates":[-82.9693527222,42.2819099426],"type":"Point"}
}