{
  "type": "Feature",
  "properties": {
    "addr:full":"Dorval QC H9S 3H8",
    "addr:postcode":"h9s 3h8",
    "iso:country":"CA",
    "sg:city":"Dorval",
    "sg:classifiers":[
        {
            "category":"Health Services",
            "subcategory":"Health Practitioner",
            "type":"Services"
        }
    ],
    "sg:phone":"+1 514 633 1415",
    "sg:postcode":"H9S 3H8",
    "sg:province":"QC",
    "sg:tags":[
        "physiotherapist"
    ],
    "wof:name":"Physio Dorval",
    "wof:placetype":"venue"
},
  "geometry": {"coordinates":[-73.741112,45.444145],"type":"Point"}
}