{
  "type": "Feature",
  "properties": {
    "addr:full":"1226 Rue Bishop Montreal QC H3G 2E3",
    "addr:housenumber":"1226",
    "addr:postcode":"h3g 2e3",
    "addr:street":"Rue Bishop",
    "iso:country":"CA",
    "sg:address":"1226 Rue Bishop",
    "sg:city":"Montreal",
    "sg:classifiers":[
        {
            "category":"Real Estate",
            "subcategory":"Real Estate Agent",
            "type":"Services"
        }
    ],
    "sg:phone":"+1 514 861 7039",
    "sg:postcode":"H3G 2E3",
    "sg:province":"QC",
    "sg:tags":[
        "management"
    ],
    "wof:name":"Gestion Immobiliere Icon Ltee",
    "wof:placetype":"venue"
},
  "geometry": {"coordinates":[-73.575356,45.495941],"type":"Point"}
}