{
  "type": "Feature",
  "properties": {
    "addr:full":"800 Rue Rossiter Saint-Jean-Sur-Richelieu QC J3B 8J1",
    "addr:housenumber":"800",
    "addr:postcode":"j3b 8j1",
    "addr:street":"Rue Rossiter",
    "iso:country":"CA",
    "sg:address":"800 Rue Rossiter",
    "sg:city":"Saint-Jean-Sur-Richelieu",
    "sg:classifiers":[
        {
            "category":"Manufacturing",
            "subcategory":"Tools & Machinery",
            "type":"Manufacturing & Wholesale Goods"
        }
    ],
    "sg:phone":"+1 450 359 8800",
    "sg:postcode":"J3B 8J1",
    "sg:province":"QC",
    "sg:tags":[
        "machine",
        "sewing"
    ],
    "wof:name":"Landis-Letendre Ltee",
    "wof:placetype":"venue"
},
  "geometry": {"coordinates":[-73.2943267822,45.3262138367],"type":"Point"}
}