{
  "type": "Feature",
  "properties": {
    "addr:full":"Hull QC J8Z 2B4",
    "addr:postcode":"j8z 2b4",
    "iso:country":"CA",
    "sg:city":"Hull",
    "sg:classifiers":[
        {
            "category":"Retail",
            "subcategory":"Auto Repair",
            "type":"Services"
        }
    ],
    "sg:phone":"+1 819 595 8826",
    "sg:postcode":"J8Z 2B4",
    "sg:province":"QC",
    "sg:tags":[
        "repairing",
        "automobile"
    ],
    "wof:name":"L'Autopital",
    "wof:placetype":"venue"
},
  "geometry": {"coordinates":[-75.74276733400001,45.47290802],"type":"Point"}
}