{
  "type": "Feature",
  "properties": {
    "iso:country":"CA",
    "sg:city":"Burnaby",
    "sg:classifiers":[
        {
            "category":"Shopping",
            "subcategory":"Computers & Home Electronics",
            "type":"Retail Goods"
        }
    ],
    "sg:phone":"+1 604 437 6919",
    "sg:postcode":"V5J 1G1",
    "sg:province":"BC",
    "sg:tags":[
        "equipment",
        "dealer"
    ],
    "wof:name":"B C Compusolve Inc",
    "wof:placetype":"venue"
},
  "geometry": {"coordinates":[-122.9817276,49.2220497131],"type":"Point"}
}