{
  "type": "Feature",
  "properties": {
    "addr:full":"115 Bessemer Rd London ON N6E 1P9",
    "addr:housenumber":"115",
    "addr:postcode":"n6e 1p9",
    "addr:street":"Bessemer Rd",
    "iso:country":"CA",
    "sg:address":"115 Bessemer Rd",
    "sg:city":"London",
    "sg:classifiers":[
        {
            "category":"Autos & Motor Vehicles",
            "subcategory":"Auto Supplies",
            "type":"Retail Goods"
        }
    ],
    "sg:phone":"+1 519 681 2830",
    "sg:postcode":"N6E 1P9",
    "sg:province":"ON",
    "sg:tags":[
        "tire"
    ],
    "wof:name":"Don Mar Tire & Automotive Inc",
    "wof:placetype":"venue"
},
  "geometry": {"coordinates":[-81.2118988037,42.9324073792],"type":"Point"}
}