{
  "type": "Feature",
  "properties": {
    "addr:full":"Woodstock ON N4V 1C8",
    "addr:postcode":"n4v 1c8",
    "iso:country":"CA",
    "sg:city":"Woodstock",
    "sg:classifiers":[
        {
            "category":"Manufacturing",
            "subcategory":"Tools & Machinery",
            "type":"Manufacturing & Wholesale Goods"
        }
    ],
    "sg:phone":"+1 519 421 4416",
    "sg:postcode":"N4V 1C8",
    "sg:province":"ON",
    "sg:tags":[
        "machine",
        "shop"
    ],
    "wof:name":"Parkridge Machining",
    "wof:placetype":"venue"
},
  "geometry": {"coordinates":[-80.726967,43.109459],"type":"Point"}
}