{
  "type": "Feature",
  "properties": {
    "iso:country":"CA",
    "sg:address":"93 Russell Ave",
    "sg:city":"St Catharines",
    "sg:classifiers":[
        {
            "category":"Shopping",
            "subcategory":"Discount & Variety Stores",
            "type":"Retail Goods"
        }
    ],
    "sg:phone":"+1 905 688 8080",
    "sg:postcode":"L2R 1V8",
    "sg:province":"ON",
    "wof:name":"Russell Variety",
    "wof:placetype":"venue"
},
  "geometry": {"coordinates":[-79.2473526001,43.1703147888],"type":"Point"}
}