{
  "type": "Feature",
  "properties": {
    "addr:full":"581 Ch Pleasant Ridge Rogersville-Ouest NB E4Y 1A4",
    "addr:housenumber":"581",
    "addr:postcode":"e4y 1a4",
    "addr:street":"Ch Pleasant",
    "iso:country":"CA",
    "sg:address":"581 Ch Pleasant Ridge",
    "sg:city":"Rogersville-Ouest",
    "sg:classifiers":[
        {
            "category":"Retail",
            "subcategory":"Auto Repair",
            "type":"Services"
        }
    ],
    "sg:phone":"+1 506 775 2426",
    "sg:postcode":"E4Y 1A4",
    "sg:province":"NB",
    "sg:tags":[
        "repairing",
        "automobile"
    ],
    "wof:name":"Entreprises Lebel",
    "wof:placetype":"venue"
},
  "geometry": {"coordinates":[-65.478233,46.72477],"type":"Point"}
}