{
  "type": "Feature",
  "properties": {
    "addr:full":"421 Fifth Ave Matheson ON P0K 1N0",
    "addr:housenumber":"421",
    "addr:postcode":"p0k 1n0",
    "addr:street":"Fifth Ave",
    "iso:country":"CA",
    "sg:address":"421 Fifth Ave",
    "sg:city":"Matheson",
    "sg:classifiers":[
        {
            "category":"Shopping",
            "subcategory":"Gifts & Souvenirs",
            "type":"Retail Goods"
        }
    ],
    "sg:phone":"+1 705 273 2488",
    "sg:postcode":"P0K 1N0",
    "sg:province":"ON",
    "sg:tags":[
        "shop"
    ],
    "wof:name":"Northern Treasures",
    "wof:placetype":"venue"
},
  "geometry": {"coordinates":[-80.4654464722,48.5354194641],"type":"Point"}
}