{
  "type": "Feature",
  "properties": {
    "addr:full":"7885 Hwy 97 Vernon BC V1B 3R9",
    "addr:housenumber":"7885",
    "addr:postcode":"v1b 3r9",
    "addr:street":"Hwy 97",
    "iso:country":"CA",
    "sg:address":"7885 Hwy 97",
    "sg:city":"Vernon",
    "sg:classifiers":[
        {
            "category":"Food & Beverages",
            "subcategory":"Fruits & Vegetables",
            "type":"Retail Goods"
        }
    ],
    "sg:phone":"+1 250 545 2000",
    "sg:postcode":"V1B 3R9",
    "sg:province":"BC",
    "sg:tags":[
        "produce"
    ],
    "wof:name":"Pleasant Valley Fruit & Garden",
    "wof:placetype":"venue"
},
  "geometry": {"coordinates":[-119.273742676,50.2589797974],"type":"Point"}
}