{
  "type": "Feature",
  "properties": {
    "addr:full":"604 Centre St Bow Island AB T0K 0G0",
    "addr:housenumber":"604",
    "addr:postcode":"t0k 0g0",
    "addr:street":"Centre St",
    "iso:country":"CA",
    "sg:address":"604 Centre St",
    "sg:city":"Bow Island",
    "sg:classifiers":[
        {
            "category":"Professional",
            "subcategory":"Lawyer & Legal Services",
            "type":"Services"
        }
    ],
    "sg:phone":"+1 403 545 6666",
    "sg:postcode":"T0K 0G0",
    "sg:province":"AB",
    "sg:tags":[
        "attorney"
    ],
    "wof:name":"Stanley, Kirk F",
    "wof:placetype":"venue"
},
  "geometry": {"coordinates":[-111.37944,49.865559],"type":"Point"}
}