{
  "type": "Feature",
  "properties": {
    "addr:full":"6 Tippett Rd North York ON M3H 2V2",
    "addr:housenumber":"6",
    "addr:postcode":"m3h 2v2",
    "addr:street":"Tippett Rd",
    "iso:country":"CA",
    "sg:address":"6 Tippett Rd",
    "sg:city":"North York",
    "sg:classifiers":[
        {
            "category":"Manufacturing",
            "subcategory":"Jewelry",
            "type":"Manufacturing & Wholesale Goods"
        }
    ],
    "sg:phone":"+1 416 636 4040",
    "sg:postcode":"M3H 2V2",
    "sg:province":"ON",
    "wof:name":"Nathan Hennick Jewellery CO",
    "wof:placetype":"venue"
},
  "geometry": {"coordinates":[-79.4465255737,43.7322883606],"type":"Point"}
}