{
  "type": "Feature",
  "properties": {
    "addr:full":"9181 Rue Sainte-Claire Montreal QC H1L 6N4",
    "addr:housenumber":"9181",
    "addr:postcode":"h1l 6n4",
    "addr:street":"Rue Sainte-Claire",
    "iso:country":"CA",
    "sg:address":"9181 Rue Sainte-Claire",
    "sg:city":"Montreal",
    "sg:classifiers":[
        {
            "category":"Social Services",
            "subcategory":"Child Care",
            "type":"Services"
        }
    ],
    "sg:phone":"+1 514 351 1900",
    "sg:postcode":"H1L 6N4",
    "sg:province":"QC",
    "wof:name":"P'Tits Amis DE Savio Inc",
    "wof:placetype":"venue"
},
  "geometry": {"coordinates":[-73.521263,45.6077],"type":"Point"}
}