{
  "type": "Feature",
  "properties": {
    "addr:full":"874 Lapointe St Sudbury ON P3A 5N8",
    "addr:housenumber":"874",
    "addr:postcode":"p3a 5n8",
    "addr:street":"Lapointe St",
    "iso:country":"CA",
    "sg:address":"874 Lapointe St",
    "sg:city":"Sudbury",
    "sg:classifiers":[
        {
            "category":"Building & Trades",
            "subcategory":"Construction",
            "type":"Services"
        }
    ],
    "sg:phone":"+1 705 566 5702",
    "sg:postcode":"P3A 5N8",
    "sg:province":"ON",
    "sg:tags":[
        "general",
        "contractor"
    ],
    "wof:name":"Tesc Contracting Ltd",
    "wof:placetype":"venue"
},
  "geometry": {"coordinates":[-80.90933200000001,46.516483],"type":"Point"}
}