{
  "type": "Feature",
  "properties": {
    "iso:country":"CA",
    "sg:address":"245 Dixon Rd",
    "sg:city":"Etobicoke",
    "sg:classifiers":[
        {
            "category":"Professional",
            "subcategory":"Computer Services",
            "type":"Services"
        }
    ],
    "sg:phone":"+1 519 599 3388",
    "sg:postcode":"M9P 2M4",
    "sg:province":"ON",
    "sg:tags":[
        "internet"
    ],
    "wof:name":"Pricecheck Services Ltd",
    "wof:placetype":"venue"
},
  "geometry": {"coordinates":[-79.5449523926,43.697353363],"type":"Point"}
}