{
  "type": "Feature",
  "properties": {
    "iso:country":"CA",
    "sg:address":"3854 Rue Saint-Denis",
    "sg:city":"Montreal",
    "sg:classifiers":[
        {
            "category":"Shopping",
            "type":"Retail Goods"
        }
    ],
    "sg:phone":"+1 514 284 0192",
    "sg:postcode":"H2W 2M2",
    "sg:province":"QC",
    "sg:tags":[
        "picture",
        "frame"
    ],
    "wof:name":"Galerie Montreal Images",
    "wof:placetype":"venue"
},
  "geometry": {"coordinates":[-73.57357,45.519581],"type":"Point"}
}