{
  "type": "Feature",
  "properties": {
    "iso:country":"CA",
    "sg:address":"271 Nantucket Blvd",
    "sg:city":"Scarborough",
    "sg:classifiers":[
        {
            "category":"Wholesale",
            "subcategory":"Hardware",
            "type":"Manufacturing & Wholesale Goods"
        }
    ],
    "sg:phone":"+1 416 751 2000",
    "sg:postcode":"M1P 2P2",
    "sg:province":"ON",
    "sg:tags":[
        "parts",
        "refrigerating"
    ],
    "wof:name":"Frontier",
    "wof:placetype":"venue"
},
  "geometry": {"coordinates":[-79.2758407593,43.7605018616],"type":"Point"}
}