{
  "type": "Feature",
  "properties": {
    "addr:full":"PO Box 127 Neustadt ON N0G 2M0",
    "addr:housenumber":"po",
    "addr:postcode":"n0g 2m0",
    "addr:street":"Box 127",
    "iso:country":"CA",
    "sg:address":"PO Box 127",
    "sg:city":"Neustadt",
    "sg:classifiers":[
        {
            "category":"Organizations",
            "subcategory":"Religious Organization",
            "type":"Services"
        }
    ],
    "sg:phone":"+1 519 799 5398",
    "sg:postcode":"N0G 2M0",
    "sg:province":"ON",
    "sg:tags":[
        "church"
    ],
    "wof:name":"St Paul's Lutheran Church",
    "wof:placetype":"venue"
},
  "geometry": {"coordinates":[-81.002983,44.077305],"type":"Point"}
}