{
  "type": "Feature",
  "properties": {
    "iso:country":"CA",
    "sg:address":"233 Esplanade",
    "sg:city":"Sydney",
    "sg:classifiers":[
        {
            "category":"Restaurant",
            "type":"Food & Drink"
        }
    ],
    "sg:phone":"+1 902 562 7646",
    "sg:postcode":"B1P 1A6",
    "sg:province":"NS",
    "wof:name":"Governors Restaurant",
    "wof:placetype":"venue"
},
  "geometry": {"coordinates":[-60.19603,46.139565],"type":"Point"}
}