{
  "type": "Feature",
  "properties": {
    "addr:full":"645 Westmount Rd E Kitchener ON N2E 3S3",
    "addr:housenumber":"645",
    "addr:postcode":"n2e 3s3",
    "addr:street":"Westmount Rd E",
    "iso:country":"CA",
    "sg:address":"645 Westmount Rd E",
    "sg:city":"Kitchener",
    "sg:classifiers":[
        {
            "category":"Cinema",
            "subcategory":"Movie Rental",
            "type":"Entertainment"
        }
    ],
    "sg:phone":"+1 519 585 1118",
    "sg:postcode":"N2E 3S3",
    "sg:province":"ON",
    "sg:tags":[
        "leasing",
        "video",
        "disc",
        "tape"
    ],
    "wof:name":"Blockbuster",
    "wof:placetype":"venue"
},
  "geometry": {"coordinates":[-80.502151,43.42067],"type":"Point"}
}