{
  "type": "Feature",
  "properties": {
    "iso:country":"CA",
    "sg:address":"7911 128 St",
    "sg:city":"Surrey",
    "sg:classifiers":[
        {
            "category":"Manufacturing",
            "subcategory":"Tools & Machinery",
            "type":"Manufacturing & Wholesale Goods"
        }
    ],
    "sg:phone":"+1 604 591 6426",
    "sg:postcode":"V3W 4E7",
    "sg:province":"BC",
    "sg:tags":[
        "fan"
    ],
    "wof:name":"Longley Electric CO",
    "wof:placetype":"venue"
},
  "geometry": {"coordinates":[-122.86813354500001,49.146774292],"type":"Point"}
}