{
  "type": "Feature",
  "properties": {
    "addr:full":"301 Thorold Rd Welland ON L3C 6H5",
    "addr:housenumber":"301",
    "addr:postcode":"l3c 6h5",
    "addr:street":"Thorold Rd",
    "iso:country":"CA",
    "sg:address":"301 Thorold Rd",
    "sg:city":"Welland",
    "sg:classifiers":[
        {
            "category":"Restaurant",
            "type":"Food & Drink"
        }
    ],
    "sg:phone":"+1 905 734 8188",
    "sg:postcode":"L3C 6H5",
    "sg:province":"ON",
    "sg:tags":[
        "pizza"
    ],
    "wof:name":"Ever Fresh Pizza 2 For 1",
    "wof:placetype":"venue"
},
  "geometry": {"coordinates":[-79.2676620483,43.0035972595],"type":"Point"}
}