{
  "type": "Feature",
  "properties": {
    "addr:full":"400 Central Ave Fort Frances ON P9A 1X8",
    "addr:housenumber":"400",
    "addr:postcode":"p9a 1x8",
    "addr:street":"Central Ave",
    "iso:country":"CA",
    "sg:address":"400 Central Ave",
    "sg:city":"Fort Frances",
    "sg:classifiers":[
        {
            "category":"Government",
            "subcategory":"Office",
            "type":"Public Place"
        }
    ],
    "sg:phone":"+1 807 274 7566",
    "sg:postcode":"P9A 1X8",
    "sg:province":"ON",
    "wof:name":"Ontario Travel Information",
    "wof:placetype":"venue"
},
  "geometry": {"coordinates":[-93.40016199999999,48.609066],"type":"Point"}
}