{
  "type": "Feature",
  "properties": {
    "addr:full":"43 Main St W Beeton ON L0G 1A0",
    "addr:housenumber":"43",
    "addr:postcode":"l0g 1a0",
    "addr:street":"Main St W Beeton",
    "iso:country":"CA",
    "sg:address":"43 Main St W",
    "sg:city":"Beeton",
    "sg:classifiers":[
        {
            "category":"Retail",
            "subcategory":"Animal Services",
            "type":"Services"
        }
    ],
    "sg:phone":"+1 905 729 0077",
    "sg:postcode":"L0G 1A0",
    "sg:province":"ON",
    "sg:tags":[
        "pet",
        "grooming",
        "washing"
    ],
    "wof:name":"Beauty For the Beast",
    "wof:placetype":"venue"
},
  "geometry": {"coordinates":[-79.786407,44.078369],"type":"Point"}
}