{
  "type": "Feature",
  "properties": {
    "addr:full":"75 Watline Ave Mississauga ON L4Z 3E5",
    "addr:housenumber":"75",
    "addr:postcode":"l4z 3e5",
    "addr:street":"Watline Ave",
    "iso:country":"CA",
    "sg:address":"75 Watline Ave",
    "sg:city":"Mississauga",
    "sg:classifiers":[
        {
            "category":"Education",
            "subcategory":"Special Training",
            "type":"Public Place"
        }
    ],
    "sg:phone":"+1 905 502 5629",
    "sg:postcode":"L4Z 3E5",
    "sg:province":"ON",
    "sg:tags":[
        "tutoring"
    ],
    "wof:name":"Top Class Education Ctr",
    "wof:placetype":"venue"
},
  "geometry": {"coordinates":[-79.6707458496,43.6224250793],"type":"Point"}
}