{
  "type": "Feature",
  "properties": {
    "iso:country":"CA",
    "sg:address":"2 Lillian Ave",
    "sg:city":"Thornhill",
    "sg:classifiers":[
        {
            "category":"Shopping",
            "type":"Retail Goods"
        }
    ],
    "sg:phone":"+1 905 889 0344",
    "sg:postcode":"L3T 2J5",
    "sg:province":"ON",
    "sg:tags":[
        "trophy",
        "medal",
        "award"
    ],
    "wof:name":"Scooter Trophy CO",
    "wof:placetype":"venue"
},
  "geometry": {"coordinates":[-79.4133,43.807438],"type":"Point"}
}