{
  "type": "Feature",
  "properties": {
    "addr:full":"330 Nicol St Nanaimo BC V9R 4T4",
    "addr:housenumber":"330",
    "addr:postcode":"v9r 4t4",
    "addr:street":"Nicol St",
    "iso:country":"CA",
    "sg:address":"330 Nicol St",
    "sg:city":"Nanaimo",
    "sg:classifiers":[
        {
            "category":"Autos & Motor Vehicles",
            "subcategory":"Fuel & Gas Station",
            "type":"Retail Goods"
        }
    ],
    "sg:phone":"+1 250 754 3433",
    "sg:postcode":"V9R 4T4",
    "sg:province":"BC",
    "sg:tags":[
        "oil"
    ],
    "wof:name":"Malaspina Self-Serve",
    "wof:placetype":"venue"
},
  "geometry": {"coordinates":[-123.934181213,49.1557922363],"type":"Point"}
}