{
  "type": "Feature",
  "properties": {
    "addr:full":"7333 Edmonds St Burnaby BC V3N 1A7",
    "addr:housenumber":"7333",
    "addr:postcode":"v3n 1a7",
    "addr:street":"Edmonds St",
    "iso:country":"CA",
    "sg:address":"7333 Edmonds St",
    "sg:city":"Burnaby",
    "sg:classifiers":[
        {
            "category":"Personal",
            "subcategory":"Beauty Salon",
            "type":"Services"
        }
    ],
    "sg:phone":"+1 604 522 9131",
    "sg:postcode":"V3N 1A7",
    "sg:province":"BC",
    "wof:name":"Elaine's Coiffures",
    "wof:placetype":"venue"
},
  "geometry": {"coordinates":[-122.950615,49.219097],"type":"Point"}
}