{
  "type": "Feature",
  "properties": {
    "addr:full":"1224 34 Ave NE Calgary AB T2E 6L9",
    "addr:housenumber":"1224",
    "addr:postcode":"t2e 6l9",
    "addr:street":"34 Ave Ne",
    "iso:country":"CA",
    "sg:address":"1224 34 Ave NE",
    "sg:city":"Calgary",
    "sg:classifiers":[
        {
            "category":"Manufacturing",
            "subcategory":"Tools & Machinery",
            "type":"Manufacturing & Wholesale Goods"
        }
    ],
    "sg:phone":"+1 403 250 7060",
    "sg:postcode":"T2E 6L9",
    "sg:province":"AB",
    "sg:tags":[
        "equipment",
        "electric",
        "supply"
    ],
    "wof:name":"Electrical Wholesalers Ltd",
    "wof:placetype":"venue"
},
  "geometry": {"coordinates":[-114.032661,51.083691],"type":"Point"}
}