{
  "type": "Feature",
  "properties": {
    "addr:full":"Fisher River Fisher Branch MB R0C 0Z0",
    "addr:postcode":"r0c 0z0",
    "addr:street":"Fisher River Fisher Branch",
    "iso:country":"CA",
    "sg:address":"Fisher River",
    "sg:city":"Fisher Branch",
    "sg:classifiers":[
        {
            "category":"Government",
            "subcategory":"Office",
            "type":"Public Place"
        }
    ],
    "sg:phone":"+1 204 645 2626",
    "sg:postcode":"R0C 0Z0",
    "sg:province":"MB",
    "wof:name":"Manitoba Justice",
    "wof:placetype":"venue"
},
  "geometry": {"coordinates":[-97.618454,51.082603],"type":"Point"}
}