{
  "type": "Feature",
  "properties": {
    "addr:full":"541 Selkirk Ave Winnipeg MB R2W 2M8",
    "addr:housenumber":"541",
    "addr:postcode":"r2w 2m8",
    "addr:street":"Selkirk Ave",
    "iso:country":"CA",
    "sg:address":"541 Selkirk Ave",
    "sg:city":"Winnipeg",
    "sg:classifiers":[
        {
            "category":"Travel",
            "subcategory":"Hotels & Motels",
            "type":"Entertainment"
        }
    ],
    "sg:phone":"+1 204 586 4607",
    "sg:postcode":"R2W 2M8",
    "sg:province":"MB",
    "wof:name":"Merchants Hotel",
    "wof:placetype":"venue"
},
  "geometry": {"coordinates":[-97.14662199999999,49.916332],"type":"Point"}
}