{
  "type": "Feature",
  "properties": {
    "addr:full":"Surrey BC V3W 2N5",
    "addr:postcode":"v3w 2n5",
    "iso:country":"CA",
    "sg:city":"Surrey",
    "sg:classifiers":[
        {
            "category":"Professional",
            "subcategory":"Accounting & Tax Preparation",
            "type":"Services"
        }
    ],
    "sg:phone":"+1 604 599 3993",
    "sg:postcode":"V3W 2N5",
    "sg:province":"BC",
    "sg:tags":[
        "accountant"
    ],
    "wof:name":"Hiemstra, E G CA",
    "wof:placetype":"venue"
},
  "geometry": {"coordinates":[-122.867919922,49.1339607239],"type":"Point"}
}