{
  "type": "Feature",
  "properties": {
    "addr:full":"139 N Railway Ave Winkler MB R6W 4A5",
    "addr:housenumber":"139",
    "addr:postcode":"r6w 4a5",
    "addr:street":"N Railway Ave",
    "iso:country":"CA",
    "sg:address":"139 N Railway Ave",
    "sg:city":"Winkler",
    "sg:classifiers":[
        {
            "category":"Home & Garden",
            "subcategory":"Building Materials",
            "type":"Retail Goods"
        }
    ],
    "sg:phone":"+1 204 325 5319",
    "sg:postcode":"R6W 4A5",
    "sg:province":"MB",
    "sg:tags":[
        "lumber"
    ],
    "wof:name":"Canadian Lumber",
    "wof:placetype":"venue"
},
  "geometry": {"coordinates":[-97.93408966059999,49.184463501],"type":"Point"}
}