{
  "type": "Feature",
  "properties": {
    "addr:full":"292 Queen St S Bolton ON L7E 4Z5",
    "addr:housenumber":"292",
    "addr:postcode":"l7e 4z5",
    "addr:street":"Queen St S",
    "iso:country":"CA",
    "sg:address":"292 Queen St S",
    "sg:city":"Bolton",
    "sg:classifiers":[
        {
            "category":"Personal",
            "subcategory":"Beauty Salon",
            "type":"Services"
        }
    ],
    "sg:phone":"+1 905 951 6245",
    "sg:postcode":"L7E 4Z5",
    "sg:province":"ON",
    "wof:name":"Nice One Nail",
    "wof:placetype":"venue"
},
  "geometry": {"coordinates":[-79.73044586180001,43.8738937378],"type":"Point"}
}