{
  "type": "Feature",
  "properties": {
    "addr:full":"16 Cumberland St Toronto ON M4W 1J5",
    "addr:housenumber":"16",
    "addr:postcode":"m4w 1j5",
    "addr:street":"Cumberland St",
    "iso:country":"CA",
    "sg:address":"16 Cumberland St",
    "sg:city":"Toronto",
    "sg:classifiers":[
        {
            "category":"Personal",
            "subcategory":"Beauty Salon",
            "type":"Services"
        }
    ],
    "sg:phone":"+1 416 922 3179",
    "sg:postcode":"M4W 1J5",
    "sg:province":"ON",
    "wof:name":"Roman Empire Hair Stylists",
    "wof:placetype":"venue"
},
  "geometry": {"coordinates":[-79.387878,43.671093],"type":"Point"}
}