{
  "type": "Feature",
  "properties": {
    "addr:full":"Toronto ON M5J 2N7",
    "addr:postcode":"m5j 2n7",
    "iso:country":"CA",
    "sg:city":"Toronto",
    "sg:classifiers":[
        {
            "category":"Banks & Credit Unions",
            "subcategory":"Investment Brokerage",
            "type":"Services"
        }
    ],
    "sg:phone":"+1 416 363 8871",
    "sg:postcode":"M5J 2N7",
    "sg:province":"ON",
    "sg:tags":[
        "advisory",
        "financial"
    ],
    "wof:name":"Stuart Investment Management",
    "wof:placetype":"venue"
},
  "geometry": {"coordinates":[-79.38211800000001,43.646656],"type":"Point"}
}