{
  "type": "Feature",
  "properties": {
    "iso:country":"CA",
    "sg:address":"114 Main St",
    "sg:city":"Berwick",
    "sg:classifiers":[
        {
            "category":"Farming",
            "subcategory":"Farm",
            "type":"Manufacturing & Wholesale Goods"
        }
    ],
    "sg:phone":"+1 902 538 8446",
    "sg:postcode":"B0P 1E0",
    "sg:province":"NS",
    "wof:name":"Morse's Farm Ltd",
    "wof:placetype":"venue"
},
  "geometry": {"coordinates":[-64.7132492065,45.0485267639],"type":"Point"}
}