{
  "type": "Feature",
  "properties": {
    "addr:full":"1540 4th Line Ohsweken ON N0A 1M0",
    "addr:housenumber":"1540",
    "addr:postcode":"n0a 1m0",
    "addr:street":"4Th Line",
    "iso:country":"CA",
    "sg:address":"1540 4th Line",
    "sg:city":"Ohsweken",
    "sg:classifiers":[
        {
            "category":"Home & Garden",
            "subcategory":"Carpets & Floor Coverings",
            "type":"Retail Goods"
        }
    ],
    "sg:phone":"+1 519 445 2160",
    "sg:postcode":"N0A 1M0",
    "sg:province":"ON",
    "sg:tags":[
        "material",
        "rug"
    ],
    "wof:name":"Woody Thomas Flooring Ltd",
    "wof:placetype":"venue"
},
  "geometry": {"coordinates":[-80.13355300000001,43.074474],"type":"Point"}
}