{
  "type": "Feature",
  "properties": {
    "iso:country":"CA",
    "sg:address":"5137 Boul Decarie",
    "sg:city":"Montreal",
    "sg:classifiers":[
        {
            "category":"Home & Garden",
            "subcategory":"Household Appliances",
            "type":"Retail Goods"
        }
    ],
    "sg:phone":"+1 514 486 0544",
    "sg:postcode":"H3W 3C2",
    "sg:province":"QC",
    "sg:tags":[
        "sewing",
        "notion",
        "attachment"
    ],
    "wof:name":"Centre DE Couture Snowdon",
    "wof:placetype":"venue"
},
  "geometry": {"coordinates":[-73.629753,45.484303],"type":"Point"}
}