{
  "type": "Feature",
  "properties": {
    "iso:country":"CA",
    "sg:address":"1074 Westport Cres",
    "sg:city":"Mississauga",
    "sg:classifiers":[
        {
            "category":"Wholesale",
            "subcategory":"Construction Materials",
            "type":"Manufacturing & Wholesale Goods"
        }
    ],
    "sg:phone":"+1 905 670 3363",
    "sg:postcode":"L5T 1G1",
    "sg:province":"ON",
    "sg:tags":[
        "frame",
        "industrial",
        "door"
    ],
    "wof:name":"Upward Door Systems Inc",
    "wof:placetype":"venue"
},
  "geometry": {"coordinates":[-79.6610412598,43.6499481201],"type":"Point"}
}