{
  "type": "Feature",
  "properties": {
    "iso:country":"CA",
    "sg:address":"239 Manitoba Ave",
    "sg:city":"Selkirk",
    "sg:classifiers":[
        {
            "category":"Shopping",
            "subcategory":"Jewelry",
            "type":"Retail Goods"
        }
    ],
    "sg:phone":"+1 204 482 4229",
    "sg:postcode":"R1A 0Y4",
    "sg:province":"MB",
    "sg:tags":[
        "jeweler"
    ],
    "wof:name":"Gary's Gold",
    "wof:placetype":"venue"
},
  "geometry": {"coordinates":[-96.8704528809,50.1443786621],"type":"Point"}
}