{
  "type": "Feature",
  "properties": {
    "addr:full":"180 Bonnechere St E Eganville ON K0J 1T0",
    "addr:housenumber":"180",
    "addr:postcode":"k0j 1t0",
    "addr:street":"Bonnechere St E",
    "iso:country":"CA",
    "sg:address":"180 Bonnechere St E",
    "sg:city":"Eganville",
    "sg:classifiers":[
        {
            "category":"Building & Trades",
            "subcategory":"Plumbing",
            "type":"Services"
        }
    ],
    "sg:phone":"+1 613 628 2920",
    "sg:postcode":"K0J 1T0",
    "sg:province":"ON",
    "sg:tags":[
        "contractor"
    ],
    "wof:name":"Bimm Plumbing & Heating",
    "wof:placetype":"venue"
},
  "geometry": {"coordinates":[-77.10414123539999,45.5427742004],"type":"Point"}
}