{
  "type": "Feature",
  "properties": {
    "addr:full":"4808 49th Ave Yellowknife NT X1A 2N5",
    "addr:housenumber":"4808",
    "addr:postcode":"x1a 2n5",
    "addr:street":"49Th Ave",
    "iso:country":"CA",
    "sg:address":"4808 49th Ave",
    "sg:city":"Yellowknife",
    "sg:classifiers":[
        {
            "category":"Autos & Motor Vehicles",
            "subcategory":"Automobile Sales",
            "type":"Retail Goods"
        }
    ],
    "sg:phone":"+1 867 766 5000",
    "sg:postcode":"X1A 2N5",
    "sg:province":"NT",
    "sg:tags":[
        "car",
        "dealer"
    ],
    "wof:name":"Yellowknife Motors Ltd",
    "wof:placetype":"venue"
},
  "geometry": {"coordinates":[-114.372688294,62.4563980103],"type":"Point"}
}