{
  "type": "Feature",
  "properties": {
    "addr:full":"Saskatoon SK S7K 2B2",
    "addr:postcode":"s7k 2b2",
    "iso:country":"CA",
    "sg:city":"Saskatoon",
    "sg:classifiers":[
        {
            "category":"Shopping",
            "subcategory":"Music",
            "type":"Retail Goods"
        }
    ],
    "sg:phone":"+1 306 244 7090",
    "sg:postcode":"S7K 2B2",
    "sg:province":"SK",
    "sg:tags":[
        "compact",
        "record",
        "disc",
        "tape"
    ],
    "wof:name":"Vinyl Exchange",
    "wof:placetype":"venue"
},
  "geometry": {"coordinates":[-106.66340599999999,52.129223],"type":"Point"}
}