{
  "type": "Feature",
  "properties": {
    "addr:full":"13675 St Albert Trail NW Edmonton AB T5L 5E7",
    "addr:housenumber":"13675",
    "addr:postcode":"t5l 5e7",
    "addr:street":"St Albert Trail Nw",
    "iso:country":"CA",
    "sg:address":"13675 St Albert Trail NW",
    "sg:city":"Edmonton",
    "sg:classifiers":[
        {
            "category":"Restaurant",
            "type":"Food & Drink"
        }
    ],
    "sg:phone":"+1 780 455 5969",
    "sg:postcode":"T5L 5E7",
    "sg:province":"AB",
    "wof:name":"Subway Sandwiches & Salads",
    "wof:placetype":"venue"
},
  "geometry": {"coordinates":[-113.573357,53.598045],"type":"Point"}
}