{
  "type": "Feature",
  "properties": {
    "addr:full":"1299 Rue Beaubien E Montreal QC H2S 1V1",
    "addr:housenumber":"1299",
    "addr:postcode":"h2s 1v1",
    "addr:street":"Rue Beaubien E",
    "iso:country":"CA",
    "sg:address":"1299 Rue Beaubien E",
    "sg:city":"Montreal",
    "sg:classifiers":[
        {
            "category":"Shopping",
            "subcategory":"Pharmacy",
            "type":"Retail Goods"
        }
    ],
    "sg:phone":"+1 514 279 0088",
    "sg:postcode":"H2S 1V1",
    "sg:province":"QC",
    "wof:name":"Pharmacie Ly Giao",
    "wof:placetype":"venue"
},
  "geometry": {"coordinates":[-73.5997085571,45.5399398804],"type":"Point"}
}