{
  "type": "Feature",
  "properties": {
    "addr:full":"Winnipeg MB R3A 0A3",
    "addr:postcode":"r3a 0a3",
    "iso:country":"CA",
    "sg:city":"Winnipeg",
    "sg:classifiers":[
        {
            "category":"Social Services",
            "type":"Services"
        }
    ],
    "sg:phone":"+1 204 956 6560",
    "sg:postcode":"R3A 0A3",
    "sg:province":"MB",
    "sg:tags":[
        "clinic",
        "counselor",
        "marriage",
        "family"
    ],
    "wof:name":"Elizabeth Hill Counselling Ctr",
    "wof:placetype":"venue"
},
  "geometry": {"coordinates":[-97.1437,49.898212],"type":"Point"}
}