{
  "type": "Feature",
  "properties": {
    "addr:full":"20 7th St W Cornwall ON K6J 2X7",
    "addr:housenumber":"20",
    "addr:postcode":"k6j 2x7",
    "addr:street":"7Th St W",
    "iso:country":"CA",
    "sg:address":"20 7th St W",
    "sg:city":"Cornwall",
    "sg:classifiers":[
        {
            "category":"Retail",
            "subcategory":"Funeral Services",
            "type":"Services"
        }
    ],
    "sg:phone":"+1 613 932 8482",
    "sg:postcode":"K6J 2X7",
    "sg:province":"ON",
    "sg:tags":[
        "director"
    ],
    "wof:name":"Cornwall Funeral Home Ltd",
    "wof:placetype":"venue"
},
  "geometry": {"coordinates":[-74.73355865480001,45.025352478],"type":"Point"}
}