{
  "type": "Feature",
  "properties": {
    "addr:full":"436 Frontenac St Sault Ste Marie ON P6A 5K9",
    "addr:housenumber":"436",
    "addr:postcode":"p6a 5k9",
    "addr:street":"Frontenac St",
    "iso:country":"CA",
    "sg:address":"436 Frontenac St",
    "sg:city":"Sault Ste Marie",
    "sg:classifiers":[
        {
            "category":"Autos & Motor Vehicles",
            "subcategory":"Fuel & Gas Station",
            "type":"Retail Goods"
        }
    ],
    "sg:phone":"+1 705 945 6390",
    "sg:postcode":"P6A 5K9",
    "sg:province":"ON",
    "sg:tags":[
        "oil"
    ],
    "wof:name":"Sewell's Gas Bar",
    "wof:placetype":"venue"
},
  "geometry": {"coordinates":[-84.25134300000001,46.532459],"type":"Point"}
}