{
  "type": "Feature",
  "properties": {
    "addr:full":"225 Central Pky W Mississauga ON L5B 3J5",
    "addr:housenumber":"225",
    "addr:postcode":"l5b 3j5",
    "addr:street":"Central Pky W",
    "iso:country":"CA",
    "sg:address":"225 Central Pky W",
    "sg:city":"Mississauga",
    "sg:classifiers":[
        {
            "category":"Education",
            "subcategory":"School",
            "type":"Public Place"
        }
    ],
    "sg:phone":"+1 905 896 3665",
    "sg:postcode":"L5B 3J5",
    "sg:province":"ON",
    "wof:name":"Bishop Scalabrini School",
    "wof:placetype":"venue"
},
  "geometry": {"coordinates":[-79.634956,43.584503],"type":"Point"}
}