{
  "type": "Feature",
  "properties": {
    "iso:country":"CA",
    "sg:address":"754 Main St E",
    "sg:city":"Hamilton",
    "sg:classifiers":[
        {
            "category":"Restaurant",
            "type":"Food & Drink"
        }
    ],
    "sg:phone":"+1 905 549 1754",
    "sg:postcode":"L8M 1L1",
    "sg:province":"ON",
    "wof:name":"Big Top Restaurant",
    "wof:placetype":"venue"
},
  "geometry": {"coordinates":[-79.839722,43.247528],"type":"Point"}
}