{
  "type": "Feature",
  "properties": {
    "addr:full":"1 Williams Ave Main Brook NL A0K 3N0",
    "addr:housenumber":"1",
    "addr:postcode":"a0k 3n0",
    "addr:street":"Williams Ave",
    "iso:country":"CA",
    "sg:address":"1 Williams Ave",
    "sg:city":"Main Brook",
    "sg:classifiers":[
        {
            "category":"Wholesale",
            "subcategory":"Construction Materials",
            "type":"Manufacturing & Wholesale Goods"
        }
    ],
    "sg:phone":"+1 709 865 2120",
    "sg:postcode":"A0K 3N0",
    "sg:province":"NL",
    "sg:tags":[
        "lumber"
    ],
    "wof:name":"Coates Lumber CO",
    "wof:placetype":"venue"
},
  "geometry": {"coordinates":[-56.0192527771,51.1840324402],"type":"Point"}
}