{
  "type": "Feature",
  "properties": {
    "addr:full":"826 Regent Ave W Winnipeg MB R2C 3A8",
    "addr:housenumber":"826",
    "addr:postcode":"r2c 3a8",
    "addr:street":"Regent Ave W",
    "iso:country":"CA",
    "sg:address":"826 Regent Ave W",
    "sg:city":"Winnipeg",
    "sg:classifiers":[
        {
            "category":"Travel",
            "subcategory":"Hotels & Motels",
            "type":"Entertainment"
        }
    ],
    "sg:phone":"+1 204 224 1681",
    "sg:postcode":"R2C 3A8",
    "sg:province":"MB",
    "wof:name":"Canad Inns",
    "wof:placetype":"venue"
},
  "geometry": {"coordinates":[-97.027344,49.89502],"type":"Point"}
}