{
  "type": "Feature",
  "properties": {
    "addr:full":"1800 Vincent Massey Dr Cornwall ON K6H 5R6",
    "addr:housenumber":"1800",
    "addr:postcode":"k6h 5r6",
    "addr:street":"Vincent Massey Dr",
    "iso:country":"CA",
    "sg:address":"1800 Vincent Massey Dr",
    "sg:city":"Cornwall",
    "sg:classifiers":[
        {
            "category":"Wholesale",
            "subcategory":"Machinery & Supplies",
            "type":"Manufacturing & Wholesale Goods"
        }
    ],
    "sg:phone":"+1 613 938 7900",
    "sg:postcode":"K6H 5R6",
    "sg:province":"ON",
    "sg:tags":[
        "packaging"
    ],
    "wof:name":"Muller Manufacturing Ltd",
    "wof:placetype":"venue"
},
  "geometry": {"coordinates":[-74.77441399999999,45.031433],"type":"Point"}
}