{
  "type": "Feature",
  "properties": {
    "addr:full":"Ancaster ON L9G 4A8",
    "addr:postcode":"l9g 4a8",
    "iso:country":"CA",
    "sg:city":"Ancaster",
    "sg:classifiers":[
        {
            "category":"Health Services",
            "subcategory":"Doctor",
            "type":"Services"
        }
    ],
    "sg:phone":"+1 905 648 0247",
    "sg:postcode":"L9G 4A8",
    "sg:province":"ON",
    "sg:tags":[
        "dentist"
    ],
    "wof:name":"Gerend, Steven G DDS",
    "wof:placetype":"venue"
},
  "geometry": {"coordinates":[-79.97668457029999,43.2265472412],"type":"Point"}
}