{
  "type": "Feature",
  "properties": {
    "addr:full":"North York ON M9L 2S5",
    "addr:postcode":"m9l 2s5",
    "iso:country":"CA",
    "sg:city":"North York",
    "sg:classifiers":[
        {
            "category":"Manufacturing",
            "subcategory":"Jewelry",
            "type":"Manufacturing & Wholesale Goods"
        }
    ],
    "sg:phone":"+1 416 746 2351",
    "sg:postcode":"M9L 2S5",
    "sg:province":"ON",
    "wof:name":"Saro Jewellers",
    "wof:placetype":"venue"
},
  "geometry": {"coordinates":[-79.545586,43.766964],"type":"Point"}
}