{
  "type": "Feature",
  "properties": {
    "addr:full":"3415 8E Rue Saint-Prosper-DE-Dorchester QC G0M 1Y0",
    "addr:housenumber":"3415",
    "addr:postcode":"g0m 1y0",
    "addr:street":"8E Rue Saint-Prosper-De-Dorchester",
    "iso:country":"CA",
    "sg:address":"3415 8E Rue",
    "sg:city":"Saint-Prosper-DE-Dorchester",
    "sg:classifiers":[
        {
            "category":"Building & Trades",
            "subcategory":"Electrical",
            "type":"Services"
        }
    ],
    "sg:phone":"+1 418 594 8085",
    "sg:postcode":"G0M 1Y0",
    "sg:province":"QC",
    "sg:tags":[
        "electric",
        "contractor"
    ],
    "wof:name":"Installations Electriques Biss",
    "wof:placetype":"venue"
},
  "geometry": {"coordinates":[-70.497749,46.221554],"type":"Point"}
}