{
  "type": "Feature",
  "properties": {
    "addr:full":"2265 10 Ave SW Medicine Hat AB T1A 8G1",
    "addr:housenumber":"2265",
    "addr:postcode":"t1a 8g1",
    "addr:street":"10 Ave Sw",
    "iso:country":"CA",
    "sg:address":"2265 10 Ave SW",
    "sg:city":"Medicine Hat",
    "sg:classifiers":[
        {
            "category":"Wholesale",
            "subcategory":"Hardware",
            "type":"Manufacturing & Wholesale Goods"
        }
    ],
    "sg:phone":"+1 403 527 3226",
    "sg:postcode":"T1A 8G1",
    "sg:province":"AB",
    "sg:tags":[
        "furnace"
    ],
    "wof:name":"Ecco Heating Products Ltd",
    "wof:placetype":"venue"
},
  "geometry": {"coordinates":[-110.70961800000001,50.01812],"type":"Point"}
}