{
  "type": "Feature",
  "properties": {
    "addr:full":"645 47th Ave E Vancouver BC V5W 2B5",
    "addr:housenumber":"645",
    "addr:postcode":"v5w 2b5",
    "addr:street":"47Th Ave E",
    "iso:country":"CA",
    "sg:address":"645 47th Ave E",
    "sg:city":"Vancouver",
    "sg:classifiers":[
        {
            "category":"Organizations",
            "subcategory":"Religious Organization",
            "type":"Services"
        }
    ],
    "sg:phone":"+1 604 322 5657",
    "sg:postcode":"V5W 2B5",
    "sg:province":"BC",
    "sg:tags":[
        "church"
    ],
    "wof:name":"Lord's Love Church Society",
    "wof:placetype":"venue"
},
  "geometry": {"coordinates":[-123.09172821,49.227596283],"type":"Point"}
}