{
  "type": "Feature",
  "properties": {
    "addr:full":"2944 Ch Sullivan Sullivan QC J0Y 2N0",
    "addr:housenumber":"2944",
    "addr:postcode":"j0y 2n0",
    "addr:street":"Ch Sullivan",
    "iso:country":"CA",
    "sg:address":"2944 Ch Sullivan",
    "sg:city":"Sullivan",
    "sg:classifiers":[
        {
            "category":"Manufacturing",
            "subcategory":"Building Materials",
            "type":"Manufacturing & Wholesale Goods"
        }
    ],
    "sg:phone":"+1 819 874 8998",
    "sg:postcode":"J0Y 2N0",
    "sg:province":"QC",
    "wof:name":"Abiti-Bois",
    "wof:placetype":"venue"
},
  "geometry": {"coordinates":[-77.830803,48.122185],"type":"Point"}
}