{
  "type": "Feature",
  "properties": {
    "iso:country":"CA",
    "sg:address":"1134 Rue Sainte-Catherine O",
    "sg:city":"Montreal",
    "sg:classifiers":[
        {
            "category":"Restaurant",
            "type":"Food & Drink"
        }
    ],
    "sg:phone":"+1 514 866 8089",
    "sg:postcode":"H3B 1H4",
    "sg:province":"QC",
    "wof:name":"Restaurant Sheas",
    "wof:placetype":"venue"
},
  "geometry": {"coordinates":[-73.5565948486,45.5177078247],"type":"Point"}
}