{
  "type": "Feature",
  "properties": {
    "iso:country":"CA",
    "sg:address":"1325 Strathcona St",
    "sg:city":"Crossfield",
    "sg:classifiers":[
        {
            "category":"Organizations",
            "subcategory":"Religious Organization",
            "type":"Services"
        }
    ],
    "sg:phone":"+1 403 946 5651",
    "sg:postcode":"T0M 0S0",
    "sg:province":"AB",
    "sg:tags":[
        "church"
    ],
    "wof:name":"Crossfield Baptist Church",
    "wof:placetype":"venue"
},
  "geometry": {"coordinates":[-114.030166626,51.4297409058],"type":"Point"}
}