{
  "type": "Feature",
  "properties": {
    "addr:full":"8 Wilson St E Perth ON K7H 1L2",
    "addr:housenumber":"8",
    "addr:postcode":"k7h 1l2",
    "addr:street":"Wilson St E",
    "iso:country":"CA",
    "sg:address":"8 Wilson St E",
    "sg:city":"Perth",
    "sg:classifiers":[
        {
            "category":"Home & Garden",
            "subcategory":"Home Furnishings",
            "type":"Retail Goods"
        }
    ],
    "sg:phone":"+1 613 264 8752",
    "sg:postcode":"K7H 1L2",
    "sg:province":"ON",
    "sg:tags":[
        "linen"
    ],
    "wof:name":"Barb's Touch of Elegance",
    "wof:placetype":"venue"
},
  "geometry": {"coordinates":[-76.252235,44.899948],"type":"Point"}
}