{
  "type": "Feature",
  "properties": {
    "addr:full":"36 Home Ave Vankleek Hill ON K0B 1R0",
    "addr:housenumber":"36",
    "addr:postcode":"k0b 1r0",
    "addr:street":"Home Ave",
    "iso:country":"CA",
    "sg:address":"36 Home Ave",
    "sg:city":"Vankleek Hill",
    "sg:classifiers":[
        {
            "category":"Shopping",
            "type":"Retail Goods"
        }
    ],
    "sg:phone":"+1 613 678 5086",
    "sg:postcode":"K0B 1R0",
    "sg:province":"ON",
    "sg:tags":[
        "art",
        "gallery",
        "dealer"
    ],
    "wof:name":"Arbor Gallery",
    "wof:placetype":"venue"
},
  "geometry": {"coordinates":[-74.649422,45.520298],"type":"Point"}
}