{
  "type": "Feature",
  "properties": {
    "addr:full":"55558 Old Mill Line Vienna ON N0J 1Z0",
    "addr:housenumber":"55558",
    "addr:postcode":"n0j 1z0",
    "addr:street":"Old Mill Line",
    "iso:country":"CA",
    "sg:address":"55558 Old Mill Line",
    "sg:city":"Vienna",
    "sg:classifiers":[
        {
            "category":"Freight",
            "type":"Transportation"
        }
    ],
    "sg:phone":"+1 519 874 1335",
    "sg:postcode":"N0J 1Z0",
    "sg:province":"ON",
    "sg:tags":[
        "trucking"
    ],
    "wof:name":"Alan Soper Trucking Ltd",
    "wof:placetype":"venue"
},
  "geometry": {"coordinates":[-80.78585099999999,42.688744],"type":"Point"}
}