{
  "type": "Feature",
  "properties": {
    "addr:full":"3 Edgewater St Mahone Bay NS B0J 2E0",
    "addr:housenumber":"3",
    "addr:postcode":"b0j 2e0",
    "addr:street":"Edgewater St",
    "iso:country":"CA",
    "sg:address":"3 Edgewater St",
    "sg:city":"Mahone Bay",
    "sg:classifiers":[
        {
            "category":"Food & Beverages",
            "subcategory":"Bakery",
            "type":"Retail Goods"
        }
    ],
    "sg:phone":"+1 902 624 1420",
    "sg:postcode":"B0J 2E0",
    "sg:province":"NS",
    "sg:tags":[
        "baker"
    ],
    "wof:name":"Lahave Bakery",
    "wof:placetype":"venue"
},
  "geometry": {"coordinates":[-64.381935,44.449268],"type":"Point"}
}