{
  "type": "Feature",
  "properties": {
    "addr:full":"4261 Hwy 7 Norwood ON K0L 2V0",
    "addr:housenumber":"4261",
    "addr:postcode":"k0l 2v0",
    "addr:street":"Hwy 7",
    "iso:country":"CA",
    "sg:address":"4261 Hwy 7",
    "sg:city":"Norwood",
    "sg:classifiers":[
        {
            "category":"Restaurant",
            "type":"Food & Drink"
        }
    ],
    "sg:phone":"+1 705 639 2419",
    "sg:postcode":"K0L 2V0",
    "sg:province":"ON",
    "sg:tags":[
        "pizza"
    ],
    "wof:name":"Pizza LA Casa",
    "wof:placetype":"venue"
},
  "geometry": {"coordinates":[-77.9801101685,44.3818778992],"type":"Point"}
}