{
  "type": "Feature",
  "properties": {
    "addr:full":"3891 Rue Saint-Denis Montreal QC H2W 2M4",
    "addr:housenumber":"3891",
    "addr:postcode":"h2w 2m4",
    "addr:street":"Rue Saint-Denis",
    "iso:country":"CA",
    "sg:address":"3891 Rue Saint-Denis",
    "sg:city":"Montreal",
    "sg:classifiers":[
        {
            "category":"Arts & Performance",
            "subcategory":"Theater",
            "type":"Entertainment"
        }
    ],
    "sg:phone":"+1 514 845 6034",
    "sg:postcode":"H2W 2M4",
    "sg:province":"QC",
    "sg:tags":[
        "talent",
        "agency",
        "casting"
    ],
    "wof:name":"Productions Du Singe Bleu",
    "wof:placetype":"venue"
},
  "geometry": {"coordinates":[-73.573685,45.519951],"type":"Point"}
}