{
  "type": "Feature",
  "properties": {
    "iso:country":"CA",
    "sg:address":"533 Kingston Rd",
    "sg:city":"Pickering",
    "sg:classifiers":[
        {
            "category":"Travel",
            "subcategory":"Hotels & Motels",
            "type":"Entertainment"
        }
    ],
    "sg:phone":"+1 905 831 6200",
    "sg:postcode":"L1V 3N7",
    "sg:province":"ON",
    "wof:name":"Comfort Inn",
    "wof:placetype":"venue"
},
  "geometry": {"coordinates":[-79.122428894,43.8137168884],"type":"Point"}
}