{
  "type": "Feature",
  "properties": {
    "addr:full":"Saint-Barnabe-Sud QC J0H 1G0",
    "addr:postcode":"j0h 1g0",
    "iso:country":"CA",
    "sg:city":"Saint-Barnabe-Sud",
    "sg:classifiers":[
        {
            "category":"Retail",
            "subcategory":"Auto Repair",
            "type":"Services"
        }
    ],
    "sg:phone":"+1 450 792 3510",
    "sg:postcode":"J0H 1G0",
    "sg:province":"QC",
    "sg:tags":[
        "repairing",
        "automobile"
    ],
    "wof:name":"Suspension Yvon Leblanc Inc",
    "wof:placetype":"venue"
},
  "geometry": {"coordinates":[-72.9085159302,45.7413253784],"type":"Point"}
}