{
  "type": "Feature",
  "properties": {
    "addr:full":"North York ON M9M 2Y3",
    "addr:postcode":"m9m 2y3",
    "iso:country":"CA",
    "sg:city":"North York",
    "sg:classifiers":[
        {
            "category":"Retail",
            "subcategory":"Portrait Studio",
            "type":"Services"
        }
    ],
    "sg:phone":"+1 416 749 8480",
    "sg:postcode":"M9M 2Y3",
    "sg:province":"ON",
    "sg:tags":[
        "photographer"
    ],
    "wof:name":"Banga Photo & Portrait Studio",
    "wof:placetype":"venue"
},
  "geometry": {"coordinates":[-79.540459,43.75251],"type":"Point"}
}