{
  "type": "Feature",
  "properties": {
    "iso:country":"CA",
    "sg:address":"17002 90 Ave NW",
    "sg:city":"Edmonton",
    "sg:classifiers":[
        {
            "category":"Restaurant",
            "type":"Food & Drink"
        }
    ],
    "sg:phone":"+1 780 481 6822",
    "sg:postcode":"T5T 1L6",
    "sg:province":"AB",
    "wof:name":"Boston Pizza",
    "wof:placetype":"venue"
},
  "geometry": {"coordinates":[-113.61574554400001,53.524974823],"type":"Point"}
}