{
  "type": "Feature",
  "properties": {
    "iso:country":"CA",
    "sg:address":"4531 Sheppard Ave E # 200",
    "sg:city":"Scarborough",
    "sg:classifiers":[
        {
            "category":"Recreation",
            "type":"Entertainment"
        }
    ],
    "sg:phone":"+1 416 298 2888",
    "sg:postcode":"M1S 1V3",
    "sg:province":"ON",
    "sg:tags":[
        "parlor",
        "billiard"
    ],
    "wof:name":"Spot Billiard Lounge",
    "wof:placetype":"venue"
},
  "geometry": {"coordinates":[-79.26430511469999,43.7882995605],"type":"Point"}
}