{
  "type": "Feature",
  "properties": {
    "addr:full":"4997 Highway 7 Markham ON L3R 1N1",
    "addr:housenumber":"4997",
    "addr:postcode":"l3r 1n1",
    "addr:street":"Highway 7",
    "iso:country":"CA",
    "sg:address":"4997 Highway 7",
    "sg:city":"Markham",
    "sg:classifiers":[
        {
            "category":"Health Services",
            "subcategory":"Doctor",
            "type":"Services"
        }
    ],
    "sg:phone":"+1 905 470 1844",
    "sg:postcode":"L3R 1N1",
    "sg:province":"ON",
    "sg:tags":[
        "dentist"
    ],
    "wof:name":"Jacob, Victor DDS",
    "wof:placetype":"venue"
},
  "geometry": {"coordinates":[-79.33994300000001,43.856033],"type":"Point"}
}