{
  "type": "Feature",
  "properties": {
    "addr:full":"3805 Boul Cremazie E Montreal QC H1Z 4G7",
    "addr:housenumber":"3805",
    "addr:postcode":"h1z 4g7",
    "addr:street":"Boul Cremazie E",
    "iso:country":"CA",
    "sg:address":"3805 Boul Cremazie E",
    "sg:city":"Montreal",
    "sg:classifiers":[
        {
            "category":"Autos & Motor Vehicles",
            "subcategory":"Automobile Sales",
            "type":"Retail Goods"
        }
    ],
    "sg:phone":"+1 514 722 0505",
    "sg:postcode":"H1Z 4G7",
    "sg:province":"QC",
    "sg:tags":[
        "car",
        "dealer"
    ],
    "wof:name":"Oto Cremazie",
    "wof:placetype":"venue"
},
  "geometry": {"coordinates":[-73.60247039790001,45.5679168701],"type":"Point"}
}