{
  "type": "Feature",
  "properties": {
    "addr:full":"791 Somerset St W Ottawa ON K1R 6R3",
    "addr:housenumber":"791",
    "addr:postcode":"k1r 6r3",
    "addr:street":"Somerset St W",
    "iso:country":"CA",
    "sg:address":"791 Somerset St W",
    "sg:city":"Ottawa",
    "sg:classifiers":[
        {
            "category":"Food & Beverages",
            "subcategory":"Groceries & Convenience Stores",
            "type":"Retail Goods"
        }
    ],
    "sg:phone":"+1 613 230 7352",
    "sg:postcode":"K1R 6R3",
    "sg:province":"ON",
    "sg:tags":[
        "grocer"
    ],
    "wof:name":"Phuoc Loi Groceries",
    "wof:placetype":"venue"
},
  "geometry": {"coordinates":[-75.71040344239999,45.4097709656],"type":"Point"}
}