{
  "type": "Feature",
  "properties": {
    "iso:country":"CA",
    "sg:address":"1679 Kenworth St",
    "sg:city":"Thornhill",
    "sg:classifiers":[
        {
            "category":"Retail",
            "subcategory":"Repair Shop",
            "type":"Services"
        }
    ],
    "sg:phone":"+1 250 615 5807",
    "sg:postcode":"V8G 3Y4",
    "sg:province":"BC",
    "sg:tags":[
        "welding"
    ],
    "wof:name":"Nino's Arc & Spark",
    "wof:placetype":"venue"
},
  "geometry": {"coordinates":[-128.58009338400001,54.4941635132],"type":"Point"}
}