{
  "type": "Feature",
  "properties": {
    "addr:full":"2020 Boul DE Tadoussac Chicoutimi QC G7G 1K7",
    "addr:housenumber":"2020",
    "addr:postcode":"g7g 1k7",
    "addr:street":"Boul De Tadoussac",
    "iso:country":"CA",
    "sg:address":"2020 Boul DE Tadoussac",
    "sg:city":"Chicoutimi",
    "sg:classifiers":[
        {
            "category":"Health Services",
            "subcategory":"Medical Lab",
            "type":"Services"
        }
    ],
    "sg:phone":"+1 418 545 4155",
    "sg:postcode":"G7G 1K7",
    "sg:province":"QC",
    "sg:tags":[
        "laboratory"
    ],
    "wof:name":"Laboratories Dentaire Mj Inc",
    "wof:placetype":"venue"
},
  "geometry": {"coordinates":[-71.05950164790001,48.4414978027],"type":"Point"}
}