{
  "type": "Feature",
  "properties": {
    "addr:full":"Niagara Falls ON L2G 1J4",
    "addr:postcode":"l2g 1j4",
    "iso:country":"CA",
    "sg:city":"Niagara Falls",
    "sg:classifiers":[
        {
            "category":"Health Services",
            "subcategory":"Doctor",
            "type":"Services"
        }
    ],
    "sg:phone":"+1 905 356 1695",
    "sg:postcode":"L2G 1J4",
    "sg:province":"ON",
    "sg:tags":[
        "physician",
        "surgeon"
    ],
    "wof:name":"Brown, Ian MD",
    "wof:placetype":"venue"
},
  "geometry": {"coordinates":[-79.089012146,43.093334198],"type":"Point"}
}