{
  "type": "Feature",
  "properties": {
    "addr:full":"5007 50th Ave Olds AB T4H 1P5",
    "addr:housenumber":"5007",
    "addr:postcode":"t4h 1p5",
    "addr:street":"50Th Ave",
    "iso:country":"CA",
    "sg:address":"5007 50th Ave",
    "sg:city":"Olds",
    "sg:classifiers":[
        {
            "category":"Banks & Credit Unions",
            "subcategory":"Bank",
            "type":"Services"
        }
    ],
    "sg:phone":"+1 403 556 3368",
    "sg:postcode":"T4H 1P5",
    "sg:province":"AB",
    "wof:name":"Scotiabank",
    "wof:placetype":"venue"
},
  "geometry": {"coordinates":[-114.10511,51.791851],"type":"Point"}
}