{
  "type": "Feature",
  "properties": {
    "iso:country":"CA",
    "sg:city":"Victoria",
    "sg:classifiers":[
        {
            "category":"Professional",
            "subcategory":"Lawyer & Legal Services",
            "type":"Services"
        }
    ],
    "sg:phone":"+1 250 381 7321",
    "sg:postcode":"V8V 4X3",
    "sg:province":"BC",
    "sg:tags":[
        "attorney"
    ],
    "wof:name":"Anderson, Deborah H",
    "wof:placetype":"venue"
},
  "geometry": {"coordinates":[-123.358772,48.425507],"type":"Point"}
}