{
  "type": "Feature",
  "properties": {
    "addr:full":"391 Lyndock St Corunna ON N0N 1G0",
    "addr:housenumber":"391",
    "addr:postcode":"n0n 1g0",
    "addr:street":"Lyndock St",
    "iso:country":"CA",
    "sg:address":"391 Lyndock St",
    "sg:city":"Corunna",
    "sg:classifiers":[
        {
            "category":"Restaurant",
            "type":"Food & Drink"
        }
    ],
    "sg:phone":"+1 519 862 1172",
    "sg:postcode":"N0N 1G0",
    "sg:province":"ON",
    "wof:name":"Corunna Restaurant",
    "wof:placetype":"venue"
},
  "geometry": {"coordinates":[-82.453491,42.88929],"type":"Point"}
}