{
  "type": "Feature",
  "properties": {
    "iso:country":"CA",
    "sg:city":"Carcross",
    "sg:classifiers":[
        {
            "category":"Government",
            "subcategory":"Office",
            "type":"Public Place"
        }
    ],
    "sg:phone":"+1 867 821 4281",
    "sg:postcode":"Y0B 1B0",
    "sg:province":"YT",
    "wof:name":"Yukon Territorial Driving",
    "wof:placetype":"venue"
},
  "geometry": {"coordinates":[-134.699874878,60.1661987305],"type":"Point"}
}