{
  "type": "Feature",
  "properties": {
    "addr:full":"640 Simpson St Thunder Bay ON P7C 3J7",
    "addr:housenumber":"640",
    "addr:postcode":"p7c 3j7",
    "addr:street":"Simpson St",
    "iso:country":"CA",
    "sg:address":"640 Simpson St",
    "sg:city":"Thunder Bay",
    "sg:classifiers":[
        {
            "category":"Food & Beverages",
            "subcategory":"Bakery",
            "type":"Retail Goods"
        }
    ],
    "sg:phone":"+1 807 623 2344",
    "sg:postcode":"P7C 3J7",
    "sg:province":"ON",
    "sg:tags":[
        "baker"
    ],
    "wof:name":"European Bakery",
    "wof:placetype":"venue"
},
  "geometry": {"coordinates":[-89.235725,48.392769],"type":"Point"}
}