{
  "type": "Feature",
  "properties": {
    "iso:country":"CA",
    "sg:address":"67 Mowat Ave",
    "sg:city":"Toronto",
    "sg:classifiers":[
        {
            "category":"Arts & Performance",
            "subcategory":"Theater",
            "type":"Entertainment"
        }
    ],
    "sg:phone":"+1 416 537 0018",
    "sg:postcode":"M6K 3E3",
    "sg:province":"ON",
    "sg:tags":[
        "television",
        "program",
        "producer"
    ],
    "wof:name":"Studio One Productions Inc",
    "wof:placetype":"venue"
},
  "geometry": {"coordinates":[-79.425407,43.638077],"type":"Point"}
}