{
  "type": "Feature",
  "properties": {
    "addr:full":"Mississauga ON L5J 1K5",
    "addr:postcode":"l5j 1k5",
    "iso:country":"CA",
    "sg:city":"Mississauga",
    "sg:classifiers":[
        {
            "category":"Building & Trades",
            "subcategory":"Construction",
            "type":"Services"
        }
    ],
    "sg:phone":"+1 905 855 1544",
    "sg:postcode":"L5J 1K5",
    "sg:province":"ON",
    "sg:tags":[
        "designer",
        "general",
        "contractor",
        "dealer",
        "pool",
        "swimming"
    ],
    "wof:name":"Schneider Pools",
    "wof:placetype":"venue"
},
  "geometry": {"coordinates":[-79.6347579956,43.5067596436],"type":"Point"}
}