{
  "type": "Feature",
  "properties": {
    "addr:full":"4665 Central Pky E # 3 Mississauga ON L4Z 2V4",
    "addr:housenumber":"4665",
    "addr:postcode":"l4z 2v4",
    "addr:street":"Central Pky E # 3",
    "iso:country":"CA",
    "sg:address":"4665 Central Pky E # 3",
    "sg:city":"Mississauga",
    "sg:classifiers":[
        {
            "category":"Professional",
            "subcategory":"Business Services",
            "type":"Services"
        }
    ],
    "sg:phone":"+1 905 501 9447",
    "sg:postcode":"L4Z 2V4",
    "sg:province":"ON",
    "sg:tags":[
        "made",
        "shoes"
    ],
    "wof:name":"Mississauga Medical Shoe",
    "wof:placetype":"venue"
},
  "geometry": {"coordinates":[-79.64073944090001,43.6156425476],"type":"Point"}
}