{
  "type": "Feature",
  "properties": {
    "addr:full":"304 Willowgrove Cres Woodstock ON N4S 7N4",
    "addr:housenumber":"304",
    "addr:postcode":"n4s 7n4",
    "addr:street":"Willowgrove Cres",
    "iso:country":"CA",
    "sg:address":"304 Willowgrove Cres",
    "sg:city":"Woodstock",
    "sg:classifiers":[
        {
            "category":"Building & Trades",
            "subcategory":"Plumbing",
            "type":"Services"
        }
    ],
    "sg:phone":"+1 519 421 1416",
    "sg:postcode":"N4S 7N4",
    "sg:province":"ON",
    "sg:tags":[
        "contractor"
    ],
    "wof:name":"Bml Plumbing Svc",
    "wof:placetype":"venue"
},
  "geometry": {"coordinates":[-80.73657989500001,43.1440238953],"type":"Point"}
}