{
  "type": "Feature",
  "properties": {
    "addr:full":"1556 Docteur Camille Marcoux Blanc-Sablon QC G0G 1C0",
    "addr:housenumber":"1556",
    "addr:postcode":"g0g 1c0",
    "addr:street":"Docteur Camille Marcoux",
    "iso:country":"CA",
    "sg:address":"1556 Docteur Camille Marcoux",
    "sg:city":"Blanc-Sablon",
    "sg:classifiers":[
        {
            "category":"Home & Garden",
            "subcategory":"Furniture",
            "type":"Retail Goods"
        }
    ],
    "sg:phone":"+1 418 461 3200",
    "sg:postcode":"G0G 1C0",
    "sg:province":"QC",
    "wof:name":"North Shore Furniture Inc",
    "wof:placetype":"venue"
},
  "geometry": {"coordinates":[-57.153244,51.428188],"type":"Point"}
}