{
  "type": "Feature",
  "properties": {
    "addr:full":"2877 Ch DE Chambly Longueuil QC J4L 1M8",
    "addr:housenumber":"2877",
    "addr:postcode":"j4l 1m8",
    "addr:street":"Ch De Chambly",
    "iso:country":"CA",
    "sg:address":"2877 Ch DE Chambly",
    "sg:city":"Longueuil",
    "sg:classifiers":[
        {
            "category":"Shopping",
            "subcategory":"Pharmacy",
            "type":"Retail Goods"
        }
    ],
    "sg:phone":"+1 450 677 5221",
    "sg:postcode":"J4L 1M8",
    "sg:province":"QC",
    "wof:name":"Pharmaprix",
    "wof:placetype":"venue"
},
  "geometry": {"coordinates":[-73.4606628418,45.5208282471],"type":"Point"}
}