{
  "type": "Feature",
  "properties": {
    "addr:full":"Saint-Regis QC H0M 1A0",
    "addr:postcode":"h0m 1a0",
    "iso:country":"CA",
    "sg:city":"Saint-Regis",
    "sg:classifiers":[
        {
            "category":"Government",
            "subcategory":"Office",
            "type":"Public Place"
        }
    ],
    "sg:phone":"+1 613 575 1651",
    "sg:postcode":"H0M 1A0",
    "sg:province":"QC",
    "sg:tags":[
        "village"
    ],
    "wof:name":"St-Regis Angus Mitchell",
    "wof:placetype":"venue"
},
  "geometry": {"coordinates":[-74.6272735596,45.0011558533],"type":"Point"}
}