{
  "type": "Feature",
  "properties": {
    "addr:full":"800 Boul Grignon Saint-Jerome QC J7Y 2Y8",
    "addr:housenumber":"800",
    "addr:postcode":"j7y 2y8",
    "addr:street":"Boul Grignon Saint-Jerome",
    "iso:country":"CA",
    "sg:address":"800 Boul Grignon",
    "sg:city":"Saint-Jerome",
    "sg:classifiers":[
        {
            "category":"Food & Beverages",
            "subcategory":"Liquor & Beverages",
            "type":"Retail Goods"
        }
    ],
    "sg:phone":"+1 450 438 4662",
    "sg:postcode":"J7Y 2Y8",
    "sg:province":"QC",
    "sg:tags":[
        "store"
    ],
    "wof:name":"Saq",
    "wof:placetype":"venue"
},
  "geometry": {"coordinates":[-74.0140380859,45.791343689],"type":"Point"}
}