{
  "type": "Feature",
  "properties": {
    "addr:full":"249 King St Mattice ON P0L 1T0",
    "addr:housenumber":"249",
    "addr:postcode":"p0l 1t0",
    "addr:street":"King St",
    "iso:country":"CA",
    "sg:address":"249 King St",
    "sg:city":"Mattice",
    "sg:classifiers":[
        {
            "category":"Banks & Credit Unions",
            "subcategory":"Bank",
            "type":"Services"
        }
    ],
    "sg:phone":"+1 705 364 4441",
    "sg:postcode":"P0L 1T0",
    "sg:province":"ON",
    "wof:name":"Caisse Populaire DE Mattice",
    "wof:placetype":"venue"
},
  "geometry": {"coordinates":[-83.262421,49.612434],"type":"Point"}
}