{
  "type": "Feature",
  "properties": {
    "addr:full":"292 Queen St W Toronto ON M5V 2A1",
    "addr:housenumber":"292",
    "addr:postcode":"m5v 2a1",
    "addr:street":"Queen St W",
    "iso:country":"CA",
    "sg:address":"292 Queen St W",
    "sg:city":"Toronto",
    "sg:classifiers":[
        {
            "category":"Shopping",
            "subcategory":"Jewelry",
            "type":"Retail Goods"
        }
    ],
    "sg:phone":"+1 416 340 8579",
    "sg:postcode":"M5V 2A1",
    "sg:province":"ON",
    "sg:tags":[
        "watch"
    ],
    "wof:name":"Storm",
    "wof:placetype":"venue"
},
  "geometry": {"coordinates":[-79.3930892944,43.6495933533],"type":"Point"}
}