{
  "type": "Feature",
  "properties": {
    "addr:full":"204 Buffalo St Banff AB T1L 1H1",
    "addr:housenumber":"204",
    "addr:postcode":"t1l 1h1",
    "addr:street":"Buffalo St",
    "iso:country":"CA",
    "sg:address":"204 Buffalo St",
    "sg:city":"Banff",
    "sg:classifiers":[
        {
            "category":"Shopping",
            "type":"Retail Goods"
        }
    ],
    "sg:phone":"+1 403 762 2586",
    "sg:postcode":"T1L 1H1",
    "sg:province":"AB",
    "sg:tags":[
        "stamp",
        "collector",
        "for"
    ],
    "wof:name":"Canada Post Corp",
    "wof:placetype":"venue"
},
  "geometry": {"coordinates":[-115.57238006599999,51.1745147705],"type":"Point"}
}