{
  "type": "Feature",
  "properties": {
    "addr:full":"910 Boul Industriel Saint-Jean-Sur-Richelieu QC J3B 8J4",
    "addr:housenumber":"910",
    "addr:postcode":"j3b 8j4",
    "addr:street":"Boul Industriel",
    "iso:country":"CA",
    "sg:address":"910 Boul Industriel",
    "sg:city":"Saint-Jean-Sur-Richelieu",
    "sg:classifiers":[
        {
            "category":"Wholesale",
            "subcategory":"Electrical",
            "type":"Manufacturing & Wholesale Goods"
        }
    ],
    "sg:phone":"+1 450 346 1320",
    "sg:postcode":"J3B 8J4",
    "sg:province":"QC",
    "sg:tags":[
        "equipment",
        "electric",
        "supply"
    ],
    "wof:name":"Lumen",
    "wof:placetype":"venue"
},
  "geometry": {"coordinates":[-73.2897720337,45.3291397095],"type":"Point"}
}