{
  "type": "Feature",
  "properties": {
    "iso:country":"CA",
    "sg:city":"Repentigny",
    "sg:classifiers":[
        {
            "category":"Manufacturing",
            "subcategory":"Chemicals & Compounds",
            "type":"Manufacturing & Wholesale Goods"
        }
    ],
    "sg:phone":"+1 450 582 6662",
    "sg:postcode":"J5Y 1B7",
    "sg:province":"QC",
    "sg:tags":[
        "equipment",
        "hydroponics",
        "supply"
    ],
    "wof:name":"Pousse-Magique",
    "wof:placetype":"venue"
},
  "geometry": {"coordinates":[-73.422775,45.762344],"type":"Point"}
}