{
  "type": "Feature",
  "properties": {
    "addr:full":"15 Main St S Princeton ON N0J 1V0",
    "addr:housenumber":"15",
    "addr:postcode":"n0j 1v0",
    "addr:street":"Main St S",
    "iso:country":"CA",
    "sg:address":"15 Main St S",
    "sg:city":"Princeton",
    "sg:classifiers":[
        {
            "category":"Home & Garden",
            "subcategory":"Hardware",
            "type":"Retail Goods"
        }
    ],
    "sg:phone":"+1 519 458 4770",
    "sg:postcode":"N0J 1V0",
    "sg:province":"ON",
    "wof:name":"Sinden Feed & Seed Inc",
    "wof:placetype":"venue"
},
  "geometry": {"coordinates":[-80.527046,43.170319],"type":"Point"}
}