{
  "type": "Feature",
  "properties": {
    "addr:full":"7 Glenora Ave York ON M6C 3Y2",
    "addr:housenumber":"7",
    "addr:postcode":"m6c 3y2",
    "addr:street":"Glenora Ave",
    "iso:country":"CA",
    "sg:address":"7 Glenora Ave",
    "sg:city":"York",
    "sg:classifiers":[
        {
            "category":"Organizations",
            "subcategory":"Religious Organization",
            "type":"Services"
        }
    ],
    "sg:phone":"+1 416 656 0473",
    "sg:postcode":"M6C 3Y2",
    "sg:province":"ON",
    "sg:tags":[
        "church"
    ],
    "wof:name":"New Dawn Moravian Church",
    "wof:placetype":"venue"
},
  "geometry": {"coordinates":[-79.438637,43.691807],"type":"Point"}
}