{
  "type": "Feature",
  "properties": {
    "addr:full":"5319 48th Ave Fort Nelson BC V0C 1R0",
    "addr:housenumber":"5319",
    "addr:postcode":"bc v0c 1r0",
    "addr:street":"48Th Ave",
    "iso:country":"CA",
    "sg:address":"5319 48th Ave",
    "sg:city":"Fort Nelson",
    "sg:classifiers":[
        {
            "category":"Mining & Drilling",
            "type":"Manufacturing & Wholesale Goods"
        }
    ],
    "sg:phone":"+1 250 774 2833",
    "sg:postcode":"V0C 1R0",
    "sg:province":"BC",
    "sg:tags":[
        "field",
        "oil",
        "general",
        "contractor"
    ],
    "wof:name":"Tkb Oilfield Contracting Ltd",
    "wof:placetype":"venue"
},
  "geometry": {"coordinates":[-122.70811500000001,58.802071],"type":"Point"}
}