{
  "type": "Feature",
  "properties": {
    "addr:full":"13578 Fort Rd NW Edmonton AB T5A 1C5",
    "addr:housenumber":"13578",
    "addr:postcode":"t5a 1c5",
    "addr:street":"Fort Rd Nw",
    "iso:country":"CA",
    "sg:address":"13578 Fort Rd NW",
    "sg:city":"Edmonton",
    "sg:classifiers":[
        {
            "category":"Restaurant",
            "type":"Food & Drink"
        }
    ],
    "sg:phone":"+1 780 457 8855",
    "sg:postcode":"T5A 1C5",
    "sg:province":"AB",
    "wof:name":"Acqua Marina Italian Rstrnt",
    "wof:placetype":"venue"
},
  "geometry": {"coordinates":[-113.423241,53.598057],"type":"Point"}
}