{
  "type": "Feature",
  "properties": {
    "addr:full":"2458 23 Ave NE Calgary AB T2E 8J4",
    "addr:housenumber":"2458",
    "addr:postcode":"t2e 8j4",
    "addr:street":"23 Ave Ne",
    "iso:country":"CA",
    "sg:address":"2458 23 Ave NE",
    "sg:city":"Calgary",
    "sg:classifiers":[
        {
            "category":"Retail",
            "subcategory":"Auto Repair",
            "type":"Services"
        }
    ],
    "sg:phone":"+1 403 571 0920",
    "sg:postcode":"T2E 8J4",
    "sg:province":"AB",
    "sg:tags":[
        "repairing",
        "automobile"
    ],
    "wof:name":"Magikz Automotive Solutions",
    "wof:placetype":"venue"
},
  "geometry": {"coordinates":[-114.002838135,51.0733375549],"type":"Point"}
}