{
  "type": "Feature",
  "properties": {
    "addr:full":"85 Peninsula Rd Marathon ON P0T 2E0",
    "addr:housenumber":"85",
    "addr:postcode":"p0t 2e0",
    "addr:street":"Peninsula Rd",
    "iso:country":"CA",
    "sg:address":"85 Peninsula Rd",
    "sg:city":"Marathon",
    "sg:classifiers":[
        {
            "category":"Freight",
            "type":"Transportation"
        }
    ],
    "sg:phone":"+1 807 229 3433",
    "sg:postcode":"P0T 2E0",
    "sg:province":"ON",
    "sg:tags":[
        "bus",
        "line",
        "courier"
    ],
    "wof:name":"Greyhound Canada",
    "wof:placetype":"venue"
},
  "geometry": {"coordinates":[-86.375298,48.730305],"type":"Point"}
}