{
  "type": "Feature",
  "properties": {
    "addr:full":"625 Rue Chateaubriand Mont-Saint-Hilaire QC J3H 5X9",
    "addr:housenumber":"625",
    "addr:postcode":"j3h 5x9",
    "addr:street":"Rue Chateaubriand",
    "iso:country":"CA",
    "sg:address":"625 Rue Chateaubriand",
    "sg:city":"Mont-Saint-Hilaire",
    "sg:classifiers":[
        {
            "category":"Building & Trades",
            "subcategory":"Construction",
            "type":"Services"
        }
    ],
    "sg:phone":"+1 450 536 2776",
    "sg:postcode":"J3H 5X9",
    "sg:province":"QC",
    "sg:tags":[
        "stone",
        "pointing"
    ],
    "wof:name":"Gypsetec Inc",
    "wof:placetype":"venue"
},
  "geometry": {"coordinates":[-73.1728057861,45.5730247498],"type":"Point"}
}