{
  "type": "Feature",
  "properties": {
    "addr:full":"12005 25 Ave NW Edmonton AB T6J 4G6",
    "addr:housenumber":"12005",
    "addr:postcode":"t6j 4g6",
    "addr:street":"25 Ave Nw",
    "iso:country":"CA",
    "sg:address":"12005 25 Ave NW",
    "sg:city":"Edmonton",
    "sg:classifiers":[
        {
            "category":"Real Estate",
            "subcategory":"Real Estate Operator",
            "type":"Services"
        }
    ],
    "sg:phone":"+1 780 435 6074",
    "sg:postcode":"T6J 4G6",
    "sg:province":"AB",
    "sg:tags":[
        "apartment"
    ],
    "wof:name":"Blue Quill Gardens",
    "wof:placetype":"venue"
},
  "geometry": {"coordinates":[-113.537666,53.455738],"type":"Point"}
}