{
  "type": "Feature",
  "properties": {
    "addr:full":"39 Primrose Ave Toronto ON M6H 3V1",
    "addr:housenumber":"39",
    "addr:postcode":"m6h 3v1",
    "addr:street":"Primrose Ave",
    "iso:country":"CA",
    "sg:address":"39 Primrose Ave",
    "sg:city":"Toronto",
    "sg:classifiers":[
        {
            "category":"Building & Trades",
            "subcategory":"Construction",
            "type":"Services"
        }
    ],
    "sg:phone":"+1 416 532 7705",
    "sg:postcode":"M6H 3V1",
    "sg:province":"ON",
    "sg:tags":[
        "home",
        "improvement"
    ],
    "wof:name":"Demansou Construction Ltd",
    "wof:placetype":"venue"
},
  "geometry": {"coordinates":[-79.44467926030001,43.669002533],"type":"Point"}
}