{
  "type": "Feature",
  "properties": {
    "addr:full":"50 Av Dallaire Rouyn-Noranda QC J9X 4S7",
    "addr:postcode":"j9x 4s7",
    "addr:street":"50 Av Dallaire",
    "iso:country":"CA",
    "sg:address":"50 Av Dallaire",
    "sg:city":"Rouyn-Noranda",
    "sg:classifiers":[
        {
            "category":"Cinema",
            "subcategory":"Movie Rental",
            "type":"Entertainment"
        }
    ],
    "sg:phone":"+1 819 762 3456",
    "sg:postcode":"J9X 4S7",
    "sg:province":"QC",
    "sg:tags":[
        "leasing",
        "video",
        "disc",
        "tape"
    ],
    "wof:name":"Cine Video Club Rouyn",
    "wof:placetype":"venue"
},
  "geometry": {"coordinates":[-79.022705,48.241516],"type":"Point"}
}