{
  "type": "Feature",
  "properties": {
    "iso:country":"CA",
    "sg:address":"3201 122 Rte",
    "sg:city":"Saint-Cyrille-DE-Wendover",
    "sg:classifiers":[
        {
            "category":"Building & Trades",
            "subcategory":"Construction",
            "type":"Services"
        }
    ],
    "sg:phone":"+1 819 397 2206",
    "sg:postcode":"J1Z 1C2",
    "sg:province":"QC",
    "sg:tags":[
        "concrete",
        "contractor"
    ],
    "wof:name":"Fondations Herve Carpentier",
    "wof:placetype":"venue"
},
  "geometry": {"coordinates":[-72.4250259399,45.9324111938],"type":"Point"}
}