{
  "type": "Feature",
  "properties": {
    "iso:country":"CA",
    "sg:address":"1 Principale St E",
    "sg:city":"Verner",
    "sg:classifiers":[
        {
            "category":"Banks & Credit Unions",
            "subcategory":"Bank",
            "type":"Services"
        }
    ],
    "sg:phone":"+1 705 594 2388",
    "sg:postcode":"P0H 2M0",
    "sg:province":"ON",
    "wof:name":"Caisse Populaire DE Verner",
    "wof:placetype":"venue"
},
  "geometry": {"coordinates":[-80.1265640259,46.4112434387],"type":"Point"}
}