{
  "type": "Feature",
  "properties": {
    "addr:full":"8 College St Toronto ON M5G 1K2",
    "addr:housenumber":"8",
    "addr:postcode":"m5g 1k2",
    "addr:street":"College St",
    "iso:country":"CA",
    "sg:address":"8 College St",
    "sg:city":"Toronto",
    "sg:classifiers":[
        {
            "category":"Shopping",
            "subcategory":"Optical Goods",
            "type":"Retail Goods"
        }
    ],
    "sg:phone":"+1 416 922 4870",
    "sg:postcode":"M5G 1K2",
    "sg:province":"ON",
    "sg:tags":[
        "optician"
    ],
    "wof:name":"Economy Optical",
    "wof:placetype":"venue"
},
  "geometry": {"coordinates":[-79.38339999999999,43.661327],"type":"Point"}
}