{
  "type": "Feature",
  "properties": {
    "addr:full":"1262 Don Mills Rd North York ON M3B 2W7",
    "addr:housenumber":"1262",
    "addr:postcode":"m3b 2w7",
    "addr:street":"Don Mills Rd",
    "iso:country":"CA",
    "sg:address":"1262 Don Mills Rd",
    "sg:city":"North York",
    "sg:classifiers":[
        {
            "category":"Professional",
            "subcategory":"Testing Lab",
            "type":"Services"
        }
    ],
    "sg:phone":"+1 416 449 2166",
    "sg:postcode":"M3B 2W7",
    "sg:province":"ON",
    "sg:tags":[
        "laboratory"
    ],
    "wof:name":"Alpha Laboratories Inc",
    "wof:placetype":"venue"
},
  "geometry": {"coordinates":[-79.34549,43.743755],"type":"Point"}
}