{
  "type": "Feature",
  "properties": {
    "addr:full":"4701 Boul Robert Saint-Leonard QC H1R 3E6",
    "addr:housenumber":"4701",
    "addr:postcode":"h1r 3e6",
    "addr:street":"Boul Robert",
    "iso:country":"CA",
    "sg:address":"4701 Boul Robert",
    "sg:city":"Saint-Leonard",
    "sg:classifiers":[
        {
            "category":"Health Services",
            "subcategory":"Doctor",
            "type":"Services"
        }
    ],
    "sg:phone":"+1 514 323 4814",
    "sg:postcode":"H1R 3E6",
    "sg:province":"QC",
    "sg:tags":[
        "dentist"
    ],
    "wof:name":"Clinique Dentiare Alberico",
    "wof:placetype":"venue"
},
  "geometry": {"coordinates":[-73.6076965332,45.5820808411],"type":"Point"}
}