{
  "type": "Feature",
  "properties": {
    "addr:full":"1825 Riverside Dr North Vancouver BC V7H 1V8",
    "addr:housenumber":"1825",
    "addr:postcode":"v7h 1v8",
    "addr:street":"Riverside Dr",
    "iso:country":"CA",
    "sg:address":"1825 Riverside Dr",
    "sg:city":"North Vancouver",
    "sg:classifiers":[
        {
            "category":"Autos & Motor Vehicles",
            "subcategory":"Boat Sales",
            "type":"Retail Goods"
        }
    ],
    "sg:phone":"+1 604 929 5321",
    "sg:postcode":"V7H 1V8",
    "sg:province":"BC",
    "sg:tags":[
        "equipment",
        "supply"
    ],
    "wof:name":"Pacific Surface Drives Inc",
    "wof:placetype":"venue"
},
  "geometry": {"coordinates":[-123.011543274,49.3243942261],"type":"Point"}
}