{
  "type": "Feature",
  "properties": {
    "addr:full":"815 Broadway Ave Moosomin SK S0G 3N0",
    "addr:housenumber":"815",
    "addr:postcode":"s0g 3n0",
    "addr:street":"Broadway Ave",
    "iso:country":"CA",
    "sg:address":"815 Broadway Ave",
    "sg:city":"Moosomin",
    "sg:classifiers":[
        {
            "category":"Autos & Motor Vehicles",
            "subcategory":"Automobile Sales",
            "type":"Retail Goods"
        }
    ],
    "sg:phone":"+1 306 435 3313",
    "sg:postcode":"S0G 3N0",
    "sg:province":"SK",
    "sg:tags":[
        "car",
        "dealer"
    ],
    "wof:name":"Celebration Ford Sales Ltd",
    "wof:placetype":"venue"
},
  "geometry": {"coordinates":[-101.66712951700001,50.1444854736],"type":"Point"}
}