{
  "type": "Feature",
  "properties": {
    "addr:full":"50 King St London ON N6A 5L7",
    "addr:housenumber":"50",
    "addr:postcode":"n6a 5l7",
    "addr:street":"King St",
    "iso:country":"CA",
    "sg:address":"50 King St",
    "sg:city":"London",
    "sg:classifiers":[
        {
            "category":"Government",
            "subcategory":"Office",
            "type":"Public Place"
        }
    ],
    "sg:phone":"+1 519 663 5317",
    "sg:postcode":"N6A 5L7",
    "sg:province":"ON",
    "sg:tags":[
        "pathologist",
        "speech",
        "village"
    ],
    "wof:name":"Tyke Talk",
    "wof:placetype":"venue"
},
  "geometry": {"coordinates":[-81.253693,42.981392],"type":"Point"}
}