{
  "type": "Feature",
  "properties": {
    "addr:full":"1426 Boul Renaud Chicoutimi QC G7H 3P1",
    "addr:housenumber":"1426",
    "addr:postcode":"g7h 3p1",
    "addr:street":"Boul Renaud",
    "iso:country":"CA",
    "sg:address":"1426 Boul Renaud",
    "sg:city":"Chicoutimi",
    "sg:classifiers":[
        {
            "category":"Organizations",
            "subcategory":"Religious Organization",
            "type":"Services"
        }
    ],
    "sg:phone":"+1 418 549 5441",
    "sg:postcode":"G7H 3P1",
    "sg:province":"QC",
    "wof:name":"Myriam DE L'Esperance Svc",
    "wof:placetype":"venue"
},
  "geometry": {"coordinates":[-71.024230957,48.4328155518],"type":"Point"}
}