{
  "type": "Feature",
  "properties": {
    "iso:country":"CA",
    "sg:address":"2222 Queen St E",
    "sg:city":"Toronto",
    "sg:classifiers":[
        {
            "category":"Restaurant",
            "type":"Food & Drink"
        }
    ],
    "sg:phone":"+1 416 693 2221",
    "sg:postcode":"M4E 1E9",
    "sg:province":"ON",
    "wof:name":"Eric's Kitchen",
    "wof:placetype":"venue"
},
  "geometry": {"coordinates":[-79.2882156372,43.672668457],"type":"Point"}
}