{
  "type": "Feature",
  "properties": {
    "addr:full":"6711 Tecumseh Rd E Windsor ON N8T 3K7",
    "addr:housenumber":"6711",
    "addr:postcode":"n8t 3k7",
    "addr:street":"Tecumseh Rd E",
    "iso:country":"CA",
    "sg:address":"6711 Tecumseh Rd E",
    "sg:city":"Windsor",
    "sg:classifiers":[
        {
            "category":"Personal",
            "subcategory":"Beauty Salon",
            "type":"Services"
        }
    ],
    "sg:phone":"+1 519 945 2882",
    "sg:postcode":"N8T 3K7",
    "sg:province":"ON",
    "wof:name":"Fantastic Sam's",
    "wof:placetype":"venue"
},
  "geometry": {"coordinates":[-82.9441375732,42.3117675781],"type":"Point"}
}