{
  "type": "Feature",
  "properties": {
    "iso:country":"CA",
    "sg:address":"560 Anne St N",
    "sg:city":"Barrie",
    "sg:classifiers":[
        {
            "category":"Professional",
            "subcategory":"Accounting & Tax Preparation",
            "type":"Services"
        }
    ],
    "sg:phone":"+1 705 722 5294",
    "sg:postcode":"L4M 4S4",
    "sg:province":"ON",
    "sg:tags":[
        "accountant"
    ],
    "wof:name":"Superior Business Ctr Ltd",
    "wof:placetype":"venue"
},
  "geometry": {"coordinates":[-79.727165,44.40789],"type":"Point"}
}