{
  "type": "Feature",
  "properties": {
    "addr:full":"408 Erin Woods Dr SE Calgary AB T2B 3C5",
    "addr:housenumber":"408",
    "addr:postcode":"t2b 3c5",
    "addr:street":"Erin Woods Dr Se",
    "iso:country":"CA",
    "sg:address":"408 Erin Woods Dr SE",
    "sg:city":"Calgary",
    "sg:classifiers":[
        {
            "category":"Food & Beverages",
            "subcategory":"Liquor & Beverages",
            "type":"Retail Goods"
        }
    ],
    "sg:phone":"+1 403 235 3870",
    "sg:postcode":"T2B 3C5",
    "sg:province":"AB",
    "sg:tags":[
        "store"
    ],
    "wof:name":"Star Liquor Store",
    "wof:placetype":"venue"
},
  "geometry": {"coordinates":[-113.960747,51.024231],"type":"Point"}
}