{
  "type": "Feature",
  "properties": {
    "addr:full":"9276 Rue Boivin Lasalle QC H8R 2E7",
    "addr:housenumber":"9276",
    "addr:postcode":"h8r 2e7",
    "addr:street":"Rue Boivin",
    "iso:country":"CA",
    "sg:address":"9276 Rue Boivin",
    "sg:city":"Lasalle",
    "sg:classifiers":[
        {
            "category":"Retail",
            "subcategory":"Auto Repair",
            "type":"Services"
        }
    ],
    "sg:phone":"+1 514 364 6610",
    "sg:postcode":"H8R 2E7",
    "sg:province":"QC",
    "sg:tags":[
        "repairing",
        "automobile"
    ],
    "wof:name":"Reparations R Parise Enr",
    "wof:placetype":"venue"
},
  "geometry": {"coordinates":[-73.639763,45.423641],"type":"Point"}
}