{
  "type": "Feature",
  "properties": {
    "iso:country":"CA",
    "sg:address":"200 Windflower Gate # 700",
    "sg:city":"Woodbridge",
    "sg:classifiers":[
        {
            "category":"Home & Garden",
            "subcategory":"Home Furnishings",
            "type":"Retail Goods"
        }
    ],
    "sg:phone":"+1 905 856 6000",
    "sg:postcode":"L4L 9L3",
    "sg:province":"ON",
    "sg:tags":[
        "housewares"
    ],
    "wof:name":"Benix & CO",
    "wof:placetype":"venue"
},
  "geometry": {"coordinates":[-79.5572814941,43.7895202637],"type":"Point"}
}