{
  "type": "Feature",
  "properties": {
    "iso:country":"CA",
    "sg:address":"92 Lemarchant Rd",
    "sg:city":"St. John's",
    "sg:classifiers":[
        {
            "category":"Health Services",
            "subcategory":"Chiropractor",
            "type":"Services"
        }
    ],
    "sg:phone":"+1 709 753 3300",
    "sg:postcode":"A1C 2H2",
    "sg:province":"NL",
    "wof:name":"Alliance Chiropractic Clinic",
    "wof:placetype":"venue"
},
  "geometry": {"coordinates":[-52.7176933289,47.5611152649],"type":"Point"}
}