{
  "type": "Feature",
  "properties": {
    "addr:full":"720 Broadview Ave Toronto ON M4K 2P1",
    "addr:housenumber":"720",
    "addr:postcode":"m4k 2p1",
    "addr:street":"Broadview Ave",
    "iso:country":"CA",
    "sg:address":"720 Broadview Ave",
    "sg:city":"Toronto",
    "sg:classifiers":[
        {
            "category":"Food & Beverages",
            "subcategory":"Groceries & Convenience Stores",
            "type":"Retail Goods"
        }
    ],
    "sg:phone":"+1 416 778 8762",
    "sg:postcode":"M4K 2P1",
    "sg:province":"ON",
    "sg:tags":[
        "grocer"
    ],
    "wof:name":"Loblaws",
    "wof:placetype":"venue"
},
  "geometry": {"coordinates":[-79.358253,43.675419],"type":"Point"}
}