{
  "type": "Feature",
  "properties": {
    "iso:country":"CA",
    "sg:address":"340 Maclaren St",
    "sg:city":"Ottawa",
    "sg:classifiers":[
        {
            "category":"Shopping",
            "subcategory":"Computers & Home Electronics",
            "type":"Retail Goods"
        }
    ],
    "sg:phone":"+1 613 233 8783",
    "sg:postcode":"K2P 0M6",
    "sg:province":"ON",
    "sg:tags":[
        "software"
    ],
    "wof:name":"Truecontext Corp",
    "wof:placetype":"venue"
},
  "geometry": {"coordinates":[-75.6947402954,45.4150161743],"type":"Point"}
}