{
  "type": "Feature",
  "properties": {
    "addr:full":"1 Ron Maslin Way Kanata ON K2V 1A7",
    "addr:housenumber":"1",
    "addr:postcode":"k2v 1a7",
    "addr:street":"Ron Maslin Way",
    "iso:country":"CA",
    "sg:address":"1 Ron Maslin Way",
    "sg:city":"Kanata",
    "sg:classifiers":[
        {
            "category":"Government",
            "subcategory":"Office",
            "type":"Public Place"
        }
    ],
    "sg:phone":"+1 613 831 4435",
    "sg:postcode":"K2V 1A7",
    "sg:province":"ON",
    "sg:tags":[
        "village"
    ],
    "wof:name":"Salle DE Spectacle Ron Maslin",
    "wof:placetype":"venue"
},
  "geometry": {"coordinates":[-75.90088653559999,45.2953300476],"type":"Point"}
}