{
  "type": "Feature",
  "properties": {
    "addr:full":"177 Broadway E Vancouver BC V5T 1W1",
    "addr:housenumber":"177",
    "addr:postcode":"v5t 1w1",
    "addr:street":"Broadway E",
    "iso:country":"CA",
    "sg:address":"177 Broadway E",
    "sg:city":"Vancouver",
    "sg:classifiers":[
        {
            "category":"Personal",
            "subcategory":"Beauty Salon",
            "type":"Services"
        }
    ],
    "sg:phone":"+1 604 875 9435",
    "sg:postcode":"V5T 1W1",
    "sg:province":"BC",
    "wof:name":"Mine Style Source Inc",
    "wof:placetype":"venue"
},
  "geometry": {"coordinates":[-123.101517,49.263054],"type":"Point"}
}