{
  "type": "Feature",
  "properties": {
    "iso:country":"CA",
    "sg:address":"33 Hillhead Rd",
    "sg:city":"London",
    "sg:classifiers":[
        {
            "category":"Shopping",
            "subcategory":"Stationery & Office Supplies",
            "type":"Retail Goods"
        }
    ],
    "sg:phone":"+1 519 668 6480",
    "sg:postcode":"N6E 2P7",
    "sg:province":"ON",
    "sg:tags":[
        "educational",
        "material"
    ],
    "wof:name":"World Book Educational Prods",
    "wof:placetype":"venue"
},
  "geometry": {"coordinates":[-81.197311,42.940937],"type":"Point"}
}