{
  "type": "Feature",
  "properties": {
    "addr:full":"7730 Macleod Trail SE Calgary AB T2H 0L9",
    "addr:housenumber":"7730",
    "addr:postcode":"t2h 0l9",
    "addr:street":"Macleod Trail Se",
    "iso:country":"CA",
    "sg:address":"7730 Macleod Trail SE",
    "sg:city":"Calgary",
    "sg:classifiers":[
        {
            "category":"Restaurant",
            "type":"Food & Drink"
        }
    ],
    "sg:phone":"+1 403 252 0111",
    "sg:postcode":"T2H 0L9",
    "sg:province":"AB",
    "wof:name":"Tom's House of Pizza Ltd",
    "wof:placetype":"venue"
},
  "geometry": {"coordinates":[-114.070877075,50.9841766357],"type":"Point"}
}