{
  "type": "Feature",
  "properties": {
    "addr:full":"2876 Dundas St W Toronto ON M6P 1Y8",
    "addr:housenumber":"2876",
    "addr:postcode":"m6p 1y8",
    "addr:street":"Dundas St W",
    "iso:country":"CA",
    "sg:address":"2876 Dundas St W",
    "sg:city":"Toronto",
    "sg:classifiers":[
        {
            "category":"Health Services",
            "subcategory":"Optometrist",
            "type":"Services"
        }
    ],
    "sg:phone":"+1 416 763 2020",
    "sg:postcode":"M6P 1Y8",
    "sg:province":"ON",
    "wof:name":"Feldman, Brian S OD",
    "wof:placetype":"venue"
},
  "geometry": {"coordinates":[-79.465256,43.665546],"type":"Point"}
}