{
  "type": "Feature",
  "properties": {
    "addr:full":"3 Kilpper Dr South River ON P0A 1X0",
    "addr:housenumber":"3",
    "addr:postcode":"p0a 1x0",
    "addr:street":"Kilpper Dr",
    "iso:country":"CA",
    "sg:address":"3 Kilpper Dr",
    "sg:city":"South River",
    "sg:classifiers":[
        {
            "category":"Social Services",
            "type":"Services"
        }
    ],
    "sg:phone":"+1 705 386 2625",
    "sg:postcode":"P0A 1X0",
    "sg:province":"ON",
    "sg:tags":[
        "organization",
        "welfare"
    ],
    "wof:name":"Christian Horizons",
    "wof:placetype":"venue"
},
  "geometry": {"coordinates":[-79.3869400024,45.8454627991],"type":"Point"}
}