{
  "type": "Feature",
  "properties": {
    "iso:country":"CA",
    "sg:address":"809 Prince St",
    "sg:city":"Truro",
    "sg:classifiers":[
        {
            "category":"Food & Beverages",
            "subcategory":"Bakery",
            "type":"Retail Goods"
        }
    ],
    "sg:phone":"+1 902 895 1266",
    "sg:postcode":"B2N 1G7",
    "sg:province":"NS",
    "sg:tags":[
        "baker"
    ],
    "wof:name":"Fraser's Pastry Shop",
    "wof:placetype":"venue"
},
  "geometry": {"coordinates":[-63.2769622803,45.3648033142],"type":"Point"}
}