{
  "type": "Feature",
  "properties": {
    "addr:full":"24 Boudreau Rd St Albert AB T8N 6K3",
    "addr:housenumber":"24",
    "addr:postcode":"t8n 6k3",
    "addr:street":"Boudreau Rd St Albert",
    "iso:country":"CA",
    "sg:address":"24 Boudreau Rd",
    "sg:city":"St Albert",
    "sg:classifiers":[
        {
            "category":"Recreation",
            "subcategory":"Arcade",
            "type":"Entertainment"
        }
    ],
    "sg:phone":"+1 780 460 8092",
    "sg:postcode":"T8N 6K3",
    "sg:province":"AB",
    "sg:tags":[
        "casino"
    ],
    "wof:name":"Gold Dust Casino",
    "wof:placetype":"venue"
},
  "geometry": {"coordinates":[-113.57384491000001,53.6357536316],"type":"Point"}
}