{
  "type": "Feature",
  "properties": {
    "addr:full":"1845 Middleton Ave Brandon MB R7C 1A7",
    "addr:housenumber":"1845",
    "addr:postcode":"r7c 1a7",
    "addr:street":"Middleton Ave",
    "iso:country":"CA",
    "sg:address":"1845 Middleton Ave",
    "sg:city":"Brandon",
    "sg:classifiers":[
        {
            "category":"Food & Beverages",
            "subcategory":"Bakery",
            "type":"Retail Goods"
        }
    ],
    "sg:phone":"+1 204 726 0210",
    "sg:postcode":"R7C 1A7",
    "sg:province":"MB",
    "sg:tags":[
        "doughnut"
    ],
    "wof:name":"Tim Hortons",
    "wof:placetype":"venue"
},
  "geometry": {"coordinates":[-99.96199,49.887291],"type":"Point"}
}