{
  "type": "Feature",
  "properties": {
    "addr:full":"Berthierville QC J0K 1A0",
    "addr:postcode":"j0k 1a0",
    "iso:country":"CA",
    "sg:city":"Berthierville",
    "sg:classifiers":[
        {
            "category":"Health Services",
            "subcategory":"Nursing And Care Facility",
            "type":"Services"
        }
    ],
    "sg:phone":"+1 450 836 7533",
    "sg:postcode":"J0K 1A0",
    "sg:province":"QC",
    "sg:tags":[
        "home",
        "retirement",
        "community"
    ],
    "wof:name":"Seigneurie Berthelaise",
    "wof:placetype":"venue"
},
  "geometry": {"coordinates":[-73.18012237550001,46.0735549927],"type":"Point"}
}