{
  "type": "Feature",
  "properties": {
    "addr:full":"41 Dawson Rd Ste Anne MB R5H 1B7",
    "addr:housenumber":"41",
    "addr:postcode":"r5h 1b7",
    "addr:street":"Dawson Rd Ste",
    "iso:country":"CA",
    "sg:address":"41 Dawson Rd",
    "sg:city":"Ste Anne",
    "sg:classifiers":[
        {
            "category":"Building & Trades",
            "subcategory":"Construction",
            "type":"Services"
        }
    ],
    "sg:phone":"+1 204 422 8247",
    "sg:postcode":"R5H 1B7",
    "sg:province":"MB",
    "sg:tags":[
        "designer",
        "contractor",
        "concrete",
        "dealer",
        "pool",
        "swimming"
    ],
    "wof:name":"Natural Stone Arts",
    "wof:placetype":"venue"
},
  "geometry": {"coordinates":[-96.548447,49.658222],"type":"Point"}
}