{
  "type": "Feature",
  "properties": {
    "addr:full":"North York ON M9M 2W8",
    "addr:postcode":"m9m 2w8",
    "iso:country":"CA",
    "sg:city":"North York",
    "sg:classifiers":[
        {
            "category":"Shopping",
            "subcategory":"Clothing, Apparel, & Fashions",
            "type":"Retail Goods"
        }
    ],
    "sg:phone":"+1 416 741 0745",
    "sg:postcode":"M9M 2W8",
    "sg:province":"ON",
    "sg:tags":[
        "furnishing"
    ],
    "wof:name":"Top Line Fashions",
    "wof:placetype":"venue"
},
  "geometry": {"coordinates":[-79.54267120359999,43.7518997192],"type":"Point"}
}