{
  "type": "Feature",
  "properties": {
    "addr:full":"7224 50 St NW Edmonton AB T6B 2J8",
    "addr:housenumber":"7224",
    "addr:postcode":"t6b 2j8",
    "addr:street":"50 St Nw",
    "iso:country":"CA",
    "sg:address":"7224 50 St NW",
    "sg:city":"Edmonton",
    "sg:classifiers":[
        {
            "category":"Building & Trades",
            "subcategory":"Electrical",
            "type":"Services"
        }
    ],
    "sg:phone":"+1 780 466 5832",
    "sg:postcode":"T6B 2J8",
    "sg:province":"AB",
    "sg:tags":[
        "electric",
        "contractor"
    ],
    "wof:name":"Jatec Electric Ltd",
    "wof:placetype":"venue"
},
  "geometry": {"coordinates":[-113.418624878,53.5085220337],"type":"Point"}
}