{
  "type": "Feature",
  "properties": {
    "addr:full":"1133 Fort St Victoria BC V8V 3K9",
    "addr:housenumber":"1133",
    "addr:postcode":"v8v 3k9",
    "addr:street":"Fort St",
    "iso:country":"CA",
    "sg:address":"1133 Fort St",
    "sg:city":"Victoria",
    "sg:classifiers":[
        {
            "category":"Professional",
            "subcategory":"Lawyer & Legal Services",
            "type":"Services"
        }
    ],
    "sg:phone":"+1 250 361 1686",
    "sg:postcode":"V8V 3K9",
    "sg:province":"BC",
    "sg:tags":[
        "attorney"
    ],
    "wof:name":"Dennis Tr Murray Law Corp",
    "wof:placetype":"venue"
},
  "geometry": {"coordinates":[-123.352546692,48.423084259],"type":"Point"}
}