{
  "type": "Feature",
  "properties": {
    "addr:full":"1641 17th Ave Campbell River BC V9W 4L5",
    "addr:housenumber":"1641",
    "addr:postcode":"v9w 4l5",
    "addr:street":"17Th Ave",
    "iso:country":"CA",
    "sg:address":"1641 17th Ave",
    "sg:city":"Campbell River",
    "sg:classifiers":[
        {
            "category":"Manufacturing",
            "subcategory":"Tools & Machinery",
            "type":"Manufacturing & Wholesale Goods"
        }
    ],
    "sg:phone":"+1 250 287 7716",
    "sg:postcode":"V9W 4L5",
    "sg:province":"BC",
    "sg:tags":[
        "machine",
        "shop"
    ],
    "wof:name":"York Machine Shop",
    "wof:placetype":"venue"
},
  "geometry": {"coordinates":[-125.265427,50.031628],"type":"Point"}
}