{
  "type": "Feature",
  "properties": {
    "addr:full":"106 First Nation St Fort Mackay AB T0P 1C0",
    "addr:housenumber":"106",
    "addr:postcode":"t0p 1c0",
    "addr:street":"First Nation St",
    "iso:country":"CA",
    "sg:address":"106 First Nation St",
    "sg:city":"Fort Mackay",
    "sg:classifiers":[
        {
            "category":"Mining & Drilling",
            "type":"Manufacturing & Wholesale Goods"
        }
    ],
    "sg:phone":"+1 780 828 4302",
    "sg:postcode":"T0P 1C0",
    "sg:province":"AB",
    "sg:tags":[
        "field",
        "oil"
    ],
    "wof:name":"Fort Mc Kay Enterprises Ltd",
    "wof:placetype":"venue"
},
  "geometry": {"coordinates":[-111.47998,56.996014],"type":"Point"}
}