{
  "type": "Feature",
  "properties": {
    "addr:full":"1736 Av Jacques-Lemaistre Montreal QC H2M 2C6",
    "addr:housenumber":"1736",
    "addr:postcode":"h2m 2c6",
    "addr:street":"Av Jacques-Lemaistre",
    "iso:country":"CA",
    "sg:address":"1736 Av Jacques-Lemaistre",
    "sg:city":"Montreal",
    "sg:classifiers":[
        {
            "category":"Manufacturing",
            "subcategory":"Apparel",
            "type":"Manufacturing & Wholesale Goods"
        }
    ],
    "sg:phone":"+1 514 389 1420",
    "sg:postcode":"H2M 2C6",
    "sg:province":"QC",
    "sg:tags":[
        "clothing"
    ],
    "wof:name":"Odyssee 2001",
    "wof:placetype":"venue"
},
  "geometry": {"coordinates":[-73.64241,45.562389],"type":"Point"}
}