{
  "type": "Feature",
  "properties": {
    "addr:full":"Kingston Peninsula Rothesay NB E2E 5X4",
    "addr:postcode":"e2e 5x4",
    "addr:street":"Peninsula",
    "iso:country":"CA",
    "sg:address":"Kingston Peninsula",
    "sg:city":"Rothesay",
    "sg:classifiers":[
        {
            "category":"Retail",
            "subcategory":"Portrait Studio",
            "type":"Services"
        }
    ],
    "sg:phone":"+1 506 763 3816",
    "sg:postcode":"E2E 5X4",
    "sg:province":"NB",
    "sg:tags":[
        "photographer"
    ],
    "wof:name":"Beachwood Images Fine Phtgrphy",
    "wof:placetype":"venue"
},
  "geometry": {"coordinates":[-65.98616027830001,45.3942718506],"type":"Point"}
}