{
  "type": "Feature",
  "properties": {
    "iso:country":"CA",
    "sg:city":"Mississauga",
    "sg:classifiers":[
        {
            "category":"Health Services",
            "subcategory":"Clinic",
            "type":"Services"
        }
    ],
    "sg:phone":"+1 905 279 0344",
    "sg:postcode":"L4Y 4H5",
    "sg:province":"ON",
    "sg:tags":[
        "home"
    ],
    "wof:name":"Single Source Medical Products",
    "wof:placetype":"venue"
},
  "geometry": {"coordinates":[-79.593742,43.600124],"type":"Point"}
}