{
  "type": "Feature",
  "properties": {
    "addr:full":"70 Carson St Etobicoke ON M8W 3R9",
    "addr:housenumber":"70",
    "addr:postcode":"m8w 3r9",
    "addr:street":"Carson St",
    "iso:country":"CA",
    "sg:address":"70 Carson St",
    "sg:city":"Etobicoke",
    "sg:classifiers":[
        {
            "category":"Building & Trades",
            "subcategory":"Construction",
            "type":"Services"
        }
    ],
    "sg:phone":"+1 416 252 6622",
    "sg:postcode":"M8W 3R9",
    "sg:province":"ON",
    "sg:tags":[
        "general",
        "contractor"
    ],
    "wof:name":"Iron Will Installations",
    "wof:placetype":"venue"
},
  "geometry": {"coordinates":[-79.534637,43.602867],"type":"Point"}
}