{
  "type": "Feature",
  "properties": {
    "addr:full":"15 Boul Mountain Granby QC J2G 9M5",
    "addr:housenumber":"15",
    "addr:postcode":"j2g 9m5",
    "addr:street":"Boul Mountain",
    "iso:country":"CA",
    "sg:address":"15 Boul Mountain",
    "sg:city":"Granby",
    "sg:classifiers":[
        {
            "category":"Personal",
            "subcategory":"Beauty Salon",
            "type":"Services"
        }
    ],
    "sg:phone":"+1 450 375 2002",
    "sg:postcode":"J2G 9M5",
    "sg:province":"QC",
    "wof:name":"Bronzage U-Nic Xxvi",
    "wof:placetype":"venue"
},
  "geometry": {"coordinates":[-72.720199585,45.3997077942],"type":"Point"}
}