{
  "type": "Feature",
  "properties": {
    "addr:full":"457 Rue Laval Joliette QC J6E 5G9",
    "addr:housenumber":"457",
    "addr:postcode":"j6e 5g9",
    "addr:street":"Rue Laval",
    "iso:country":"CA",
    "sg:address":"457 Rue Laval",
    "sg:city":"Joliette",
    "sg:classifiers":[
        {
            "category":"Wholesale",
            "subcategory":"Office Equipment",
            "type":"Manufacturing & Wholesale Goods"
        }
    ],
    "sg:phone":"+1 450 756 4026",
    "sg:postcode":"J6E 5G9",
    "sg:province":"QC",
    "sg:tags":[
        "accounting",
        "bookkeeping",
        "system",
        "general"
    ],
    "wof:name":"Gesta Cooperative & Svc Techs",
    "wof:placetype":"venue"
},
  "geometry": {"coordinates":[-73.4330062866,46.0197105408],"type":"Point"}
}