{
  "type": "Feature",
  "properties": {
    "iso:country":"CA",
    "sg:address":"325 John St N",
    "sg:city":"Aylmer",
    "sg:classifiers":[
        {
            "category":"Autos & Motor Vehicles",
            "subcategory":"Automobile Sales",
            "type":"Retail Goods"
        }
    ],
    "sg:phone":"+1 519 773 9228",
    "sg:postcode":"N5H 2B6",
    "sg:province":"ON",
    "sg:tags":[
        "car",
        "dealer"
    ],
    "wof:name":"Dempsey Chrysler Jeep",
    "wof:placetype":"venue"
},
  "geometry": {"coordinates":[-80.9828033447,42.7778701782],"type":"Point"}
}