{
  "type": "Feature",
  "properties": {
    "addr:full":"239 Lottridge St Hamilton ON L8L 6W1",
    "addr:housenumber":"239",
    "addr:postcode":"l8l 6w1",
    "addr:street":"Lottridge St",
    "iso:country":"CA",
    "sg:address":"239 Lottridge St",
    "sg:city":"Hamilton",
    "sg:classifiers":[
        {
            "category":"Utilities",
            "subcategory":"Refuse",
            "type":"Services"
        }
    ],
    "sg:phone":"+1 905 545 2665",
    "sg:postcode":"L8L 6W1",
    "sg:province":"ON",
    "sg:tags":[
        "waste",
        "liquid",
        "removal"
    ],
    "wof:name":"Hotz Environmental Svc",
    "wof:placetype":"venue"
},
  "geometry": {"coordinates":[-79.8302078247,43.2581367493],"type":"Point"}
}