{
  "type": "Feature",
  "properties": {
    "iso:country":"CA",
    "sg:address":"3353 the Credit Woodlands # 2",
    "sg:city":"Mississauga",
    "sg:classifiers":[
        {
            "category":"Retail",
            "subcategory":"Photofinishing",
            "type":"Services"
        }
    ],
    "sg:phone":"+1 905 279 5353",
    "sg:postcode":"L5C 2K1",
    "sg:province":"ON",
    "sg:tags":[
        "photo",
        "pharmacy"
    ],
    "wof:name":"Woodland Village Pharmacy",
    "wof:placetype":"venue"
},
  "geometry": {"coordinates":[-79.65818023680001,43.5589370728],"type":"Point"}
}