{
  "type": "Feature",
  "properties": {
    "iso:country":"CA",
    "sg:city":"Oakville",
    "sg:classifiers":[
        {
            "category":"Shopping",
            "type":"Retail Goods"
        }
    ],
    "sg:phone":"+1 905 849 1977",
    "sg:postcode":"L6J 6X8",
    "sg:province":"ON",
    "sg:tags":[
        "pet",
        "food",
        "supply"
    ],
    "wof:name":"Pet Valu Discount Pet Foods",
    "wof:placetype":"venue"
},
  "geometry": {"coordinates":[-79.657112,43.478992],"type":"Point"}
}