{
  "type": "Feature",
  "properties": {
    "addr:full":"800 Latchford St Haileybury ON P0J 1K0",
    "addr:housenumber":"800",
    "addr:postcode":"p0j 1k0",
    "addr:street":"Latchford St",
    "iso:country":"CA",
    "sg:address":"800 Latchford St",
    "sg:city":"Haileybury",
    "sg:classifiers":[
        {
            "category":"Recreation",
            "type":"Entertainment"
        }
    ],
    "sg:phone":"+1 705 672 3455",
    "sg:postcode":"P0J 1K0",
    "sg:province":"ON",
    "sg:tags":[
        "course",
        "golf"
    ],
    "wof:name":"Haileybury Golf Club",
    "wof:placetype":"venue"
},
  "geometry": {"coordinates":[-79.638961792,47.4577445984],"type":"Point"}
}