{
  "type": "Feature",
  "properties": {
    "addr:full":"535 Imperial St S Massey ON P0P 1P0",
    "addr:housenumber":"535",
    "addr:postcode":"p0p 1p0",
    "addr:street":"Imperial St S",
    "iso:country":"CA",
    "sg:address":"535 Imperial St S",
    "sg:city":"Massey",
    "sg:classifiers":[
        {
            "category":"Organizations",
            "subcategory":"Religious Organization",
            "type":"Services"
        }
    ],
    "sg:phone":"+1 705 848 0346",
    "sg:postcode":"P0P 1P0",
    "sg:province":"ON",
    "sg:tags":[
        "church"
    ],
    "wof:name":"Zion Lutheran Church",
    "wof:placetype":"venue"
},
  "geometry": {"coordinates":[-82.07819366459999,46.2073135376],"type":"Point"}
}