{
  "type": "Feature",
  "properties": {
    "addr:full":"1414 Place Page Laval QC H7W 4L8",
    "addr:housenumber":"1414",
    "addr:postcode":"h7w 4l8",
    "addr:street":"Place Page",
    "iso:country":"CA",
    "sg:address":"1414 Place Page",
    "sg:city":"Laval",
    "sg:classifiers":[
        {
            "category":"Wholesale",
            "subcategory":"Metals & Minerals",
            "type":"Manufacturing & Wholesale Goods"
        }
    ],
    "sg:phone":"+1 450 681 2942",
    "sg:postcode":"H7W 4L8",
    "sg:province":"QC",
    "sg:tags":[
        "aluminum"
    ],
    "wof:name":"Margil Aluminium Enr",
    "wof:placetype":"venue"
},
  "geometry": {"coordinates":[-73.759972,45.538303],"type":"Point"}
}