{
  "type": "Feature",
  "properties": {
    "iso:country":"CA",
    "sg:address":"1200 Av DE Germain-Des-Pres",
    "sg:city":"Sainte-Foy",
    "sg:classifiers":[
        {
            "category":"Restaurant",
            "type":"Food & Drink"
        }
    ],
    "sg:phone":"+1 418 658 8780",
    "sg:postcode":"G1V 3M7",
    "sg:province":"QC",
    "wof:name":"Bistango",
    "wof:placetype":"venue"
},
  "geometry": {"coordinates":[-71.287964,46.769394],"type":"Point"}
}