{
  "type": "Feature",
  "properties": {
    "addr:full":"25 Rue Lakeview Saint-Bruno QC J3V 2L4",
    "addr:housenumber":"25",
    "addr:postcode":"j3v 2l4",
    "addr:street":"Rue Lakeview",
    "iso:country":"CA",
    "sg:address":"25 Rue Lakeview",
    "sg:city":"Saint-Bruno",
    "sg:classifiers":[
        {
            "category":"Organizations",
            "subcategory":"Religious Organization",
            "type":"Services"
        }
    ],
    "sg:phone":"+1 450 653 2312",
    "sg:postcode":"J3V 2L4",
    "sg:province":"QC",
    "sg:tags":[
        "church"
    ],
    "wof:name":"Mount Bruno United Church",
    "wof:placetype":"venue"
},
  "geometry": {"coordinates":[-71.67552185060001,48.4717712402],"type":"Point"}
}