{
  "type": "Feature",
  "properties": {
    "addr:full":"295 Hawthorne St Antigonish NS B2G 1B9",
    "addr:housenumber":"295",
    "addr:postcode":"b2g 1b9",
    "addr:street":"Hawthorne St",
    "iso:country":"CA",
    "sg:address":"295 Hawthorne St",
    "sg:city":"Antigonish",
    "sg:classifiers":[
        {
            "category":"Travel",
            "subcategory":"Hotels & Motels",
            "type":"Entertainment"
        }
    ],
    "sg:phone":"+1 902 863 0990",
    "sg:postcode":"B2G 1B9",
    "sg:province":"NS",
    "wof:name":"Valley View Motel",
    "wof:placetype":"venue"
},
  "geometry": {"coordinates":[-61.99427,45.622189],"type":"Point"}
}