{
  "type": "Feature",
  "properties": {
    "addr:full":"1700 Varsity Estates Dr NW Calgary AB T3B 2W9",
    "addr:housenumber":"1700",
    "addr:postcode":"t3b 2w9",
    "addr:street":"Varsity Estates Dr Nw",
    "iso:country":"CA",
    "sg:address":"1700 Varsity Estates Dr NW",
    "sg:city":"Calgary",
    "sg:classifiers":[
        {
            "category":"Manufacturing",
            "subcategory":"Tools & Machinery",
            "type":"Manufacturing & Wholesale Goods"
        }
    ],
    "sg:phone":"+1 403 247 9176",
    "sg:postcode":"T3B 2W9",
    "sg:province":"AB",
    "sg:tags":[
        "equipment",
        "system",
        "automation"
    ],
    "wof:name":"Quantum Electronic Systems",
    "wof:placetype":"venue"
},
  "geometry": {"coordinates":[-114.17208100000001,51.09766],"type":"Point"}
}