{
  "type": "Feature",
  "properties": {
    "iso:country":"CA",
    "sg:address":"1295 Ch DE Saint-Jean",
    "sg:city":"LA Prairie",
    "sg:classifiers":[
        {
            "category":"Building & Trades",
            "subcategory":"Plumbing",
            "type":"Services"
        }
    ],
    "sg:phone":"+1 450 444 7298",
    "sg:postcode":"J5R 2L8",
    "sg:province":"QC",
    "sg:tags":[
        "refrigeration",
        "contractor"
    ],
    "wof:name":"Refrigeration Gb",
    "wof:placetype":"venue"
},
  "geometry": {"coordinates":[-73.4761810303,45.4106330872],"type":"Point"}
}