{
  "type": "Feature",
  "properties": {
    "addr:full":"5168 Ladner Trunk Rd Delta BC V4K 1W3",
    "addr:housenumber":"5168",
    "addr:postcode":"v4k 1w3",
    "addr:street":"Ladner Trunk Rd",
    "iso:country":"CA",
    "sg:address":"5168 Ladner Trunk Rd",
    "sg:city":"Delta",
    "sg:classifiers":[
        {
            "category":"Health Services",
            "subcategory":"Optometrist",
            "type":"Services"
        }
    ],
    "sg:phone":"+1 604 946 6921",
    "sg:postcode":"V4K 1W3",
    "sg:province":"BC",
    "sg:tags":[
        "contact",
        "lense"
    ],
    "wof:name":"Susan Lu Optometric Corp",
    "wof:placetype":"venue"
},
  "geometry": {"coordinates":[-123.079879761,49.0900840759],"type":"Point"}
}