{
  "type": "Feature",
  "properties": {
    "addr:full":"3791 Rue DE LA Fabrique Jonquiere QC G7X 3P3",
    "addr:housenumber":"3791",
    "addr:postcode":"g7x 3p3",
    "addr:street":"Rue De La Fabrique",
    "iso:country":"CA",
    "sg:address":"3791 Rue DE LA Fabrique",
    "sg:city":"Jonquiere",
    "sg:classifiers":[
        {
            "category":"Social Services",
            "type":"Services"
        }
    ],
    "sg:phone":"+1 418 695 5949",
    "sg:postcode":"G7X 3P3",
    "sg:province":"QC",
    "sg:tags":[
        "organization",
        "welfare"
    ],
    "wof:name":"Habitations Partages Inc",
    "wof:placetype":"venue"
},
  "geometry": {"coordinates":[-71.2476272583,48.4072303772],"type":"Point"}
}