{
  "type": "Feature",
  "properties": {
    "iso:country":"CA",
    "sg:address":"747 Talbot Ave",
    "sg:city":"Winnipeg",
    "sg:classifiers":[
        {
            "category":"Shopping",
            "type":"Retail Goods"
        }
    ],
    "sg:phone":"+1 204 669 4289",
    "sg:postcode":"R2L 0S4",
    "sg:province":"MB",
    "sg:tags":[
        "wedding",
        "supply"
    ],
    "wof:name":"Picture Perfect Weddings",
    "wof:placetype":"venue"
},
  "geometry": {"coordinates":[-97.0884552002,49.904045105],"type":"Point"}
}