{
  "type": "Feature",
  "properties": {
    "addr:full":"1042 Topsail Rd Mount Pearl NL A1N 5E6",
    "addr:housenumber":"1042",
    "addr:postcode":"a1n 5e6",
    "addr:street":"Topsail Rd",
    "iso:country":"CA",
    "sg:address":"1042 Topsail Rd",
    "sg:city":"Mount Pearl",
    "sg:classifiers":[
        {
            "category":"Manufacturing",
            "subcategory":"Wood Products",
            "type":"Manufacturing & Wholesale Goods"
        }
    ],
    "sg:phone":"+1 709 745 6663",
    "sg:postcode":"A1N 5E6",
    "sg:province":"NL",
    "sg:tags":[
        "picture",
        "lamination"
    ],
    "wof:name":"Image Fusion Inc",
    "wof:placetype":"venue"
},
  "geometry": {"coordinates":[-52.811096,47.525604],"type":"Point"}
}