{
  "type": "Feature",
  "properties": {
    "addr:full":"1291 235 Rte Canton Bedford QC J0J 1A0",
    "addr:housenumber":"1291",
    "addr:postcode":"j0j 1a0",
    "addr:street":"235 Rte Canton",
    "iso:country":"CA",
    "sg:address":"1291 235 Rte",
    "sg:city":"Canton Bedford",
    "sg:classifiers":[
        {
            "category":"Wholesale",
            "subcategory":"Machinery & Supplies",
            "type":"Manufacturing & Wholesale Goods"
        }
    ],
    "sg:phone":"+1 450 248 3135",
    "sg:postcode":"J0J 1A0",
    "sg:province":"QC",
    "sg:tags":[
        "compressor",
        "gas"
    ],
    "wof:name":"Gdb Inc",
    "wof:placetype":"venue"
},
  "geometry": {"coordinates":[-72.98742675779999,45.1252937317],"type":"Point"}
}