{
  "type": "Feature",
  "properties": {
    "addr:full":"665 Davis Dr Newmarket ON L3Y 2R2",
    "addr:housenumber":"665",
    "addr:postcode":"l3y 2r2",
    "addr:street":"Davis Dr",
    "iso:country":"CA",
    "sg:address":"665 Davis Dr",
    "sg:city":"Newmarket",
    "sg:classifiers":[
        {
            "category":"Shopping",
            "type":"Retail Goods"
        }
    ],
    "sg:phone":"+1 905 953 9175",
    "sg:postcode":"L3Y 2R2",
    "sg:province":"ON",
    "sg:tags":[
        "equipment",
        "wine",
        "supply"
    ],
    "wof:name":"Tap & Vine Cellars",
    "wof:placetype":"venue"
},
  "geometry": {"coordinates":[-79.450050354,44.0617828369],"type":"Point"}
}