{
  "type": "Feature",
  "properties": {
    "addr:full":"5401 S Island Hwy Union Bay BC V0R 3B0",
    "addr:housenumber":"5401",
    "addr:postcode":"v0r 3b0",
    "addr:street":"S Island Hwy Union",
    "iso:country":"CA",
    "sg:address":"5401 S Island Hwy",
    "sg:city":"Union Bay",
    "sg:classifiers":[
        {
            "category":"Organizations",
            "subcategory":"Professional Association",
            "type":"Services"
        }
    ],
    "sg:phone":"+1 250 335 2500",
    "sg:postcode":"V0R 3B0",
    "sg:province":"BC",
    "wof:name":"Union Bay Community Club",
    "wof:placetype":"venue"
},
  "geometry": {"coordinates":[-124.888221741,49.5895385742],"type":"Point"}
}