{
  "type": "Feature",
  "properties": {
    "iso:country":"CA",
    "sg:address":"7070 Boul Perras",
    "sg:city":"Montreal",
    "sg:classifiers":[
        {
            "category":"Health Services",
            "subcategory":"Hospital",
            "type":"Services"
        }
    ],
    "sg:phone":"+1 514 323 7260",
    "sg:postcode":"H1E 1A4",
    "sg:province":"QC",
    "wof:name":"Hopital Riviere-Des-Prairies",
    "wof:placetype":"venue"
},
  "geometry": {"coordinates":[-73.616379,45.626205],"type":"Point"}
}