{
  "type": "Feature",
  "properties": {
    "addr:full":"Kelowna BC V1Y 8R4",
    "addr:postcode":"v1y 8r4",
    "iso:country":"CA",
    "sg:city":"Kelowna",
    "sg:classifiers":[
        {
            "category":"Real Estate",
            "subcategory":"Real Estate Agent",
            "type":"Services"
        }
    ],
    "sg:phone":"+1 250 770 1125",
    "sg:postcode":"V1Y 8R4",
    "sg:province":"BC",
    "wof:name":"Centre Group Commercial Realty",
    "wof:placetype":"venue"
},
  "geometry": {"coordinates":[-119.491241,49.886101],"type":"Point"}
}