{
  "type": "Feature",
  "properties": {
    "addr:full":"436 Limestone Cres North York ON M3J 2S4",
    "addr:housenumber":"436",
    "addr:postcode":"m3j 2s4",
    "addr:street":"Limestone Cres",
    "iso:country":"CA",
    "sg:address":"436 Limestone Cres",
    "sg:city":"North York",
    "sg:classifiers":[
        {
            "category":"Wholesale",
            "subcategory":"Medical Equipment & Supplies",
            "type":"Manufacturing & Wholesale Goods"
        }
    ],
    "sg:phone":"+1 416 665 6616",
    "sg:postcode":"M3J 2S4",
    "sg:province":"ON",
    "sg:tags":[
        "physician",
        "hospital",
        "surgeon"
    ],
    "wof:name":"Sigmacon Medical Products Ltd",
    "wof:placetype":"venue"
},
  "geometry": {"coordinates":[-79.485641,43.781429],"type":"Point"}
}