{
  "type": "Feature",
  "properties": {
    "addr:full":"St Peters NS B0E 3B0",
    "addr:postcode":"b0e 3b0",
    "iso:country":"CA",
    "sg:city":"St Peters",
    "sg:classifiers":[
        {
            "category":"Health Services",
            "subcategory":"Doctor",
            "type":"Services"
        }
    ],
    "sg:phone":"+1 902 535 2961",
    "sg:postcode":"B0E 3B0",
    "sg:province":"NS",
    "sg:tags":[
        "physician",
        "surgeon"
    ],
    "wof:name":"Potlotek Health Ctr",
    "wof:placetype":"venue"
},
  "geometry": {"coordinates":[-63.5875511169,44.7273788452],"type":"Point"}
}