{
  "type": "Feature",
  "properties": {
    "addr:full":"41 William St N Chatham ON N7M 4L3",
    "addr:housenumber":"41",
    "addr:postcode":"n7m 4l3",
    "addr:street":"William St N",
    "iso:country":"CA",
    "sg:address":"41 William St N",
    "sg:city":"Chatham",
    "sg:classifiers":[
        {
            "category":"Recreation",
            "type":"Entertainment"
        }
    ],
    "sg:phone":"+1 519 352 4324",
    "sg:postcode":"N7M 4L3",
    "sg:province":"ON",
    "sg:tags":[
        "club",
        "curling"
    ],
    "wof:name":"Chatham Granite Club",
    "wof:placetype":"venue"
},
  "geometry": {"coordinates":[-82.18170166020001,42.4061965942],"type":"Point"}
}