{
  "type": "Feature",
  "properties": {
    "addr:full":"1395 Knottwood Road East NW Edmonton AB T6K 2P5",
    "addr:housenumber":"1395",
    "addr:postcode":"t6k 2p5",
    "addr:street":"Knottwood Road East Nw",
    "iso:country":"CA",
    "sg:address":"1395 Knottwood Road East NW",
    "sg:city":"Edmonton",
    "sg:classifiers":[
        {
            "category":"Education",
            "subcategory":"School",
            "type":"Public Place"
        }
    ],
    "sg:phone":"+1 780 462 5112",
    "sg:postcode":"T6K 2P5",
    "sg:province":"AB",
    "wof:name":"Ekota Elementary School",
    "wof:placetype":"venue"
},
  "geometry": {"coordinates":[-113.441406,53.447739],"type":"Point"}
}