{
  "type": "Feature",
  "properties": {
    "iso:country":"CA",
    "sg:address":"7315 120 St",
    "sg:city":"Delta",
    "sg:classifiers":[
        {
            "category":"Shopping",
            "subcategory":"Stationery & Office Supplies",
            "type":"Retail Goods"
        }
    ],
    "sg:phone":"+1 604 501 7820",
    "sg:postcode":"V4C 6P5",
    "sg:province":"BC",
    "sg:tags":[
        "equipment",
        "computer",
        "dealer"
    ],
    "wof:name":"Staples",
    "wof:placetype":"venue"
},
  "geometry": {"coordinates":[-122.89057922400001,49.1360397339],"type":"Point"}
}