{
  "type": "Feature",
  "properties": {
    "addr:full":"2353 Weston Rd York ON M9N 1Z8",
    "addr:housenumber":"2353",
    "addr:postcode":"m9n 1z8",
    "addr:street":"Weston Rd",
    "iso:country":"CA",
    "sg:address":"2353 Weston Rd",
    "sg:city":"York",
    "sg:classifiers":[
        {
            "category":"Autos & Motor Vehicles",
            "subcategory":"Automobile Sales",
            "type":"Retail Goods"
        }
    ],
    "sg:phone":"+1 416 248 2291",
    "sg:postcode":"M9N 1Z8",
    "sg:province":"ON",
    "sg:tags":[
        "car",
        "dealer"
    ],
    "wof:name":"Weston Motors",
    "wof:placetype":"venue"
},
  "geometry": {"coordinates":[-79.531296,43.706165],"type":"Point"}
}