{
  "type": "Feature",
  "properties": {
    "addr:full":"1666 Victoria Park Ave North York ON M1R 1P7",
    "addr:housenumber":"1666",
    "addr:postcode":"m1r 1p7",
    "addr:street":"Victoria Park Ave",
    "iso:country":"CA",
    "sg:address":"1666 Victoria Park Ave",
    "sg:city":"North York",
    "sg:classifiers":[
        {
            "category":"Retail",
            "subcategory":"Laundry & Dry Cleaning",
            "type":"Services"
        }
    ],
    "sg:phone":"+1 416 759 9241",
    "sg:postcode":"M1R 1P7",
    "sg:province":"ON",
    "sg:tags":[
        "cleaners"
    ],
    "wof:name":"Princess Cleaners",
    "wof:placetype":"venue"
},
  "geometry": {"coordinates":[-79.305908,43.732159],"type":"Point"}
}