{
  "type": "Feature",
  "properties": {
    "iso:country":"CA",
    "sg:address":"1750 Av DE Vitre",
    "sg:city":"Quebec",
    "sg:classifiers":[
        {
            "category":"Shopping",
            "subcategory":"Pharmacy",
            "type":"Retail Goods"
        }
    ],
    "sg:phone":"+1 418 522 1561",
    "sg:postcode":"G1J 1Z6",
    "sg:province":"QC",
    "wof:name":"Pharmacie Philippe Moreau",
    "wof:placetype":"venue"
},
  "geometry": {"coordinates":[-71.22348,46.837017],"type":"Point"}
}