{
  "type": "Feature",
  "properties": {
    "addr:full":"1033 Rue DE LA Colombiere Saint-Jean-Chrysostome QC G6Z 2J4",
    "addr:housenumber":"1033",
    "addr:postcode":"g6z 2j4",
    "addr:street":"Rue De La Colombiere Saint-Jean-Chrysostome",
    "iso:country":"CA",
    "sg:address":"1033 Rue DE LA Colombiere",
    "sg:city":"Saint-Jean-Chrysostome",
    "sg:classifiers":[
        {
            "category":"Personal",
            "type":"Services"
        }
    ],
    "sg:phone":"+1 418 839 3660",
    "sg:postcode":"G6Z 2J4",
    "sg:province":"QC",
    "sg:tags":[
        "therapist",
        "massage"
    ],
    "wof:name":"Clinique DE Massotherapie",
    "wof:placetype":"venue"
},
  "geometry": {"coordinates":[-71.20027160639999,46.714099884],"type":"Point"}
}