{
  "type": "Feature",
  "properties": {
    "addr:full":"22550 Lougheed Hwy Maple Ridge BC V2X 2V1",
    "addr:housenumber":"22550",
    "addr:postcode":"v2x 2v1",
    "addr:street":"Lougheed Hwy",
    "iso:country":"CA",
    "sg:address":"22550 Lougheed Hwy",
    "sg:city":"Maple Ridge",
    "sg:classifiers":[
        {
            "category":"Personal",
            "subcategory":"Beauty Salon",
            "type":"Services"
        }
    ],
    "sg:phone":"+1 604 467 8578",
    "sg:postcode":"V2X 2V1",
    "sg:province":"BC",
    "wof:name":"Perimeters Salon",
    "wof:placetype":"venue"
},
  "geometry": {"coordinates":[-122.597595215,49.216960907],"type":"Point"}
}