{
  "type": "Feature",
  "properties": {
    "addr:full":"180 Bloor St W Toronto ON M5S 2V6",
    "addr:housenumber":"180",
    "addr:postcode":"m5s 2v6",
    "addr:street":"Bloor St W",
    "iso:country":"CA",
    "sg:address":"180 Bloor St W",
    "sg:city":"Toronto",
    "sg:classifiers":[
        {
            "category":"Health Services",
            "subcategory":"Doctor",
            "type":"Services"
        }
    ],
    "sg:phone":"+1 416 960 9129",
    "sg:postcode":"M5S 2V6",
    "sg:province":"ON",
    "sg:tags":[
        "physician",
        "surgeon"
    ],
    "wof:name":"Yanchyshyn, Gordon MD",
    "wof:placetype":"venue"
},
  "geometry": {"coordinates":[-79.39502,43.668659],"type":"Point"}
}