{
  "type": "Feature",
  "properties": {
    "addr:full":"10 Nordic Pl North York ON M3A 2H9",
    "addr:housenumber":"10",
    "addr:postcode":"m3a 2h9",
    "addr:street":"Nordic Pl",
    "iso:country":"CA",
    "sg:address":"10 Nordic Pl",
    "sg:city":"North York",
    "sg:classifiers":[
        {
            "category":"Real Estate",
            "subcategory":"Real Estate Agent",
            "type":"Services"
        }
    ],
    "sg:phone":"+1 416 445 4950",
    "sg:postcode":"M3A 2H9",
    "sg:province":"ON",
    "sg:tags":[
        "management"
    ],
    "wof:name":"Granite Property Management",
    "wof:placetype":"venue"
},
  "geometry": {"coordinates":[-79.32637800000001,43.741558],"type":"Point"}
}