{
  "type": "Feature",
  "properties": {
    "addr:full":"2904 Valleyvista Dr Coquitlam BC V3E 2P3",
    "addr:housenumber":"2904",
    "addr:postcode":"v3e 2p3",
    "addr:street":"Valleyvista Dr",
    "iso:country":"CA",
    "sg:address":"2904 Valleyvista Dr",
    "sg:city":"Coquitlam",
    "sg:classifiers":[
        {
            "category":"Communications",
            "subcategory":"Film & Video Production",
            "type":"Services"
        }
    ],
    "sg:phone":"+1 604 944 9454",
    "sg:postcode":"V3E 2P3",
    "sg:province":"BC",
    "sg:tags":[
        "taping"
    ],
    "wof:name":"Daystar Productions",
    "wof:placetype":"venue"
},
  "geometry": {"coordinates":[-122.800598145,49.2973175049],"type":"Point"}
}