{
  "type": "Feature",
  "properties": {
    "addr:full":"4807 Hwy 211 Bickerton West NS B0J 1A0",
    "addr:housenumber":"4807",
    "addr:postcode":"b0j 1a0",
    "addr:street":"Hwy 211 Bickerton West",
    "iso:country":"CA",
    "sg:address":"4807 Hwy 211",
    "sg:city":"Bickerton West",
    "sg:classifiers":[
        {
            "category":"Freight",
            "type":"Transportation"
        }
    ],
    "sg:phone":"+1 902 364 2002",
    "sg:postcode":"B0J 1A0",
    "sg:province":"NS",
    "sg:tags":[
        "trucking"
    ],
    "wof:name":"Kaiser Industrial & Marine Ltd",
    "wof:placetype":"venue"
},
  "geometry": {"coordinates":[-61.732460022,45.104057312],"type":"Point"}
}