{
  "type": "Feature",
  "properties": {
    "addr:full":"6762 52 Ave Red Deer AB T4N 4K9",
    "addr:housenumber":"6762",
    "addr:postcode":"t4n 4k9",
    "addr:street":"52 Ave",
    "iso:country":"CA",
    "sg:address":"6762 52 Ave",
    "sg:city":"Red Deer",
    "sg:phone":"+1 403 347 5850",
    "sg:postcode":"T4N 4K9",
    "sg:province":"AB",
    "sg:tags":[
        "lubricant",
        "lubricating",
        "compound"
    ],
    "wof:name":"Boss Lubricants",
    "wof:placetype":"venue"
},
  "geometry": {"coordinates":[-113.81711578399999,52.2908401489],"type":"Point"}
}