{
  "type": "Feature",
  "properties": {
    "addr:full":"64 Gordon St Guelph ON N1H 4H4",
    "addr:housenumber":"64",
    "addr:postcode":"n1h 4h4",
    "addr:street":"Gordon St",
    "iso:country":"CA",
    "sg:address":"64 Gordon St",
    "sg:city":"Guelph",
    "sg:classifiers":[
        {
            "category":"Building & Trades",
            "subcategory":"Electrical",
            "type":"Services"
        }
    ],
    "sg:phone":"+1 519 822 5480",
    "sg:postcode":"N1H 4H4",
    "sg:province":"ON",
    "sg:tags":[
        "electric",
        "motor",
        "contractor"
    ],
    "wof:name":"Schnurr Electric CO Ltd",
    "wof:placetype":"venue"
},
  "geometry": {"coordinates":[-80.245262,43.541096],"type":"Point"}
}