{
  "type": "Feature",
  "properties": {
    "addr:full":"285 Midwest Rd Scarborough ON M1P 3A6",
    "addr:housenumber":"285",
    "addr:postcode":"m1p 3a6",
    "addr:street":"Midwest Rd",
    "iso:country":"CA",
    "sg:address":"285 Midwest Rd",
    "sg:city":"Scarborough",
    "sg:classifiers":[
        {
            "category":"Manufacturing",
            "subcategory":"Apparel",
            "type":"Manufacturing & Wholesale Goods"
        }
    ],
    "sg:phone":"+1 416 751 7772",
    "sg:postcode":"M1P 3A6",
    "sg:province":"ON",
    "sg:tags":[
        "sportswear"
    ],
    "wof:name":"Guru Sportswear",
    "wof:placetype":"venue"
},
  "geometry": {"coordinates":[-79.27050800000001,43.759327],"type":"Point"}
}