{
  "type": "Feature",
  "properties": {
    "addr:full":"3430 Rte Saint-Leonard Shipshaw QC G7P 1G5",
    "addr:housenumber":"3430",
    "addr:postcode":"g7p 1g5",
    "addr:street":"Rte Saint-Leonard",
    "iso:country":"CA",
    "sg:address":"3430 Rte Saint-Leonard",
    "sg:city":"Shipshaw",
    "sg:classifiers":[
        {
            "category":"Building & Trades",
            "subcategory":"Construction",
            "type":"Services"
        }
    ],
    "sg:phone":"+1 418 695 3318",
    "sg:postcode":"G7P 1G5",
    "sg:province":"QC",
    "sg:tags":[
        "designer",
        "dealer",
        "pool",
        "swimming"
    ],
    "wof:name":"Piscines Pag",
    "wof:placetype":"venue"
},
  "geometry": {"coordinates":[-71.260193,48.45882],"type":"Point"}
}