{
  "type": "Feature",
  "properties": {
    "iso:country":"CA",
    "sg:city":"Concord",
    "sg:classifiers":[
        {
            "category":"Wholesale",
            "subcategory":"Machinery & Supplies",
            "type":"Manufacturing & Wholesale Goods"
        }
    ],
    "sg:phone":"+1 905 660 8818",
    "sg:postcode":"L4K 3R8",
    "sg:province":"ON",
    "sg:tags":[
        "equipment",
        "safety",
        "clothing"
    ],
    "wof:name":"Canrun Shoes Imports Ltd",
    "wof:placetype":"venue"
},
  "geometry": {"coordinates":[-79.484161,43.809792],"type":"Point"}
}