{
  "type": "Feature",
  "properties": {
    "addr:full":"Stettler AB T0C 2L2",
    "addr:postcode":"t0c 2l2",
    "iso:country":"CA",
    "sg:city":"Stettler",
    "sg:classifiers":[
        {
            "category":"Shopping",
            "subcategory":"Clothing, Apparel, & Fashions",
            "type":"Retail Goods"
        }
    ],
    "sg:phone":"+1 403 742 2211",
    "sg:postcode":"T0C 2L2",
    "sg:province":"AB",
    "sg:tags":[
        "furnishing"
    ],
    "wof:name":"John's Mens Wear",
    "wof:placetype":"venue"
},
  "geometry": {"coordinates":[-112.70539100000001,52.324749],"type":"Point"}
}