{
  "type": "Feature",
  "properties": {
    "addr:full":"383 Cannon St E Hamilton ON L8L 2C3",
    "addr:housenumber":"383",
    "addr:postcode":"l8l 2c3",
    "addr:street":"Cannon St E",
    "iso:country":"CA",
    "sg:address":"383 Cannon St E",
    "sg:city":"Hamilton",
    "sg:classifiers":[
        {
            "category":"Shopping",
            "type":"Retail Goods"
        }
    ],
    "sg:phone":"+1 905 523 4900",
    "sg:postcode":"L8L 2C3",
    "sg:province":"ON",
    "sg:tags":[
        "hearing",
        "equipment",
        "supply",
        "impaired",
        "aids"
    ],
    "wof:name":"Custom Earmold Laboratories",
    "wof:placetype":"venue"
},
  "geometry": {"coordinates":[-79.8505325317,43.2567825317],"type":"Point"}
}