{
  "type": "Feature",
  "properties": {
    "addr:full":"Eganville ON K0J 1T0",
    "addr:postcode":"k0j 1t0",
    "iso:country":"CA",
    "sg:city":"Eganville",
    "sg:classifiers":[
        {
            "category":"Wholesale",
            "subcategory":"Farm Supplies",
            "type":"Manufacturing & Wholesale Goods"
        }
    ],
    "sg:phone":"+1 613 628 2272",
    "sg:postcode":"K0J 1T0",
    "sg:province":"ON",
    "sg:tags":[
        "building",
        "material"
    ],
    "wof:name":"Eganville Country Depot",
    "wof:placetype":"venue"
},
  "geometry": {"coordinates":[-77.10090599999999,45.540077],"type":"Point"}
}