{
  "type": "Feature",
  "properties": {
    "addr:full":"Nakusp BC V0G 1R0",
    "addr:postcode":"v0g 1r0",
    "iso:country":"CA",
    "sg:city":"Nakusp",
    "sg:classifiers":[
        {
            "category":"Manufacturing",
            "subcategory":"Tools & Machinery",
            "type":"Manufacturing & Wholesale Goods"
        }
    ],
    "sg:phone":"+1 250 265 4740",
    "sg:postcode":"V0G 1R0",
    "sg:province":"BC",
    "sg:tags":[
        "equipment",
        "safety",
        "clothing"
    ],
    "wof:name":"Rainy Day Equipment",
    "wof:placetype":"venue"
},
  "geometry": {"coordinates":[-117.802032,50.238884],"type":"Point"}
}