{
  "type": "Feature",
  "properties": {
    "addr:full":"594 Montreal Rd Ottawa ON K1K 0T9",
    "addr:housenumber":"594",
    "addr:postcode":"k1k 0t9",
    "addr:street":"Montreal Rd",
    "iso:country":"CA",
    "sg:address":"594 Montreal Rd",
    "sg:city":"Ottawa",
    "sg:classifiers":[
        {
            "category":"Shopping",
            "subcategory":"Pharmacy",
            "type":"Retail Goods"
        }
    ],
    "sg:phone":"+1 613 749 4954",
    "sg:postcode":"K1K 0T9",
    "sg:province":"ON",
    "wof:name":"Pharma Plus Drugmart",
    "wof:placetype":"venue"
},
  "geometry": {"coordinates":[-75.643486,45.442066],"type":"Point"}
}