{
  "type": "Feature",
  "properties": {
    "addr:full":"1450 Kingston Rd #14 Pickering ON L1V 1C1",
    "addr:housenumber":"1450",
    "addr:postcode":"l1v 1c1",
    "addr:street":"Kingston Rd # 14",
    "iso:country":"CA",
    "sg:address":"1450 Kingston Rd #14",
    "sg:city":"Pickering",
    "sg:classifiers":[
        {
            "category":"Retail",
            "subcategory":"Veterinary Services",
            "type":"Services"
        }
    ],
    "sg:phone":"+1 905 420 1734",
    "sg:postcode":"L1V 1C1",
    "sg:province":"ON",
    "sg:tags":[
        "veterinarian"
    ],
    "wof:name":"Pickering Animal Hospital",
    "wof:placetype":"venue"
},
  "geometry": {"coordinates":[-79.083519,43.841434],"type":"Point"}
}