{
  "type": "Feature",
  "properties": {
    "addr:full":"Montreal QC H2W 1Z3",
    "addr:postcode":"h2w 1z3",
    "iso:country":"CA",
    "sg:city":"Montreal",
    "sg:classifiers":[
        {
            "category":"Organizations",
            "subcategory":"Professional Association",
            "type":"Services"
        }
    ],
    "sg:phone":"+1 514 499 1391",
    "sg:postcode":"H2W 1Z3",
    "sg:province":"QC",
    "wof:name":"Assn-Marketing Montreal Sctn",
    "wof:placetype":"venue"
},
  "geometry": {"coordinates":[-73.583748,45.518852],"type":"Point"}
}