{
  "type": "Feature",
  "properties": {
    "addr:full":"2050 Rue Beaudry Montreal QC H2L 3G3",
    "addr:housenumber":"2050",
    "addr:postcode":"h2l 3g3",
    "addr:street":"Rue Beaudry",
    "iso:country":"CA",
    "sg:address":"2050 Rue Beaudry",
    "sg:city":"Montreal",
    "sg:classifiers":[
        {
            "category":"Wholesale",
            "subcategory":"Photographic Equipment",
            "type":"Manufacturing & Wholesale Goods"
        }
    ],
    "sg:phone":"+1 514 844 8555",
    "sg:postcode":"H2L 3G3",
    "sg:province":"QC",
    "sg:tags":[
        "motion",
        "picture",
        "supply"
    ],
    "wof:name":"Lightworks Inc",
    "wof:placetype":"venue"
},
  "geometry": {"coordinates":[-73.56298828120001,45.5217933655],"type":"Point"}
}