{
  "type": "Feature",
  "properties": {
    "addr:full":"10 Suffolk St W Guelph ON N1H 2H8",
    "addr:housenumber":"10",
    "addr:postcode":"n1h 2h8",
    "addr:street":"Suffolk St W",
    "iso:country":"CA",
    "sg:address":"10 Suffolk St W",
    "sg:city":"Guelph",
    "sg:classifiers":[
        {
            "category":"Manufacturing",
            "subcategory":"Printing",
            "type":"Manufacturing & Wholesale Goods"
        }
    ],
    "sg:phone":"+1 519 766 4756",
    "sg:postcode":"N1H 2H8",
    "sg:province":"ON",
    "sg:tags":[
        "publisher"
    ],
    "wof:name":"Main Street Press",
    "wof:placetype":"venue"
},
  "geometry": {"coordinates":[-80.25467681879999,43.5472068787],"type":"Point"}
}