{
  "type": "Feature",
  "properties": {
    "iso:country":"CA",
    "sg:address":"1690 Rue Berlier",
    "sg:city":"Laval",
    "sg:classifiers":[
        {
            "category":"Manufacturing",
            "subcategory":"Paper Products",
            "type":"Manufacturing & Wholesale Goods"
        }
    ],
    "sg:phone":"+1 450 686 9595",
    "sg:postcode":"H7L 4A1",
    "sg:province":"QC",
    "sg:tags":[
        "bag"
    ],
    "wof:name":"Emballages Sara",
    "wof:placetype":"venue"
},
  "geometry": {"coordinates":[-73.744171,45.584145],"type":"Point"}
}