{
  "type": "Feature",
  "properties": {
    "addr:full":"8267 Boul Saint-Laurent Montreal QC H2P 2M1",
    "addr:housenumber":"8267",
    "addr:postcode":"h2p 2m1",
    "addr:street":"Boul Saint-Laurent",
    "iso:country":"CA",
    "sg:address":"8267 Boul Saint-Laurent",
    "sg:city":"Montreal",
    "sg:classifiers":[
        {
            "category":"Shopping",
            "subcategory":"Bicycles & Sporting Goods",
            "type":"Retail Goods"
        }
    ],
    "sg:phone":"+1 514 381 4399",
    "sg:postcode":"H2P 2M1",
    "sg:province":"QC",
    "wof:name":"Depot Du Plein-Air",
    "wof:placetype":"venue"
},
  "geometry": {"coordinates":[-73.6336593628,45.539806366],"type":"Point"}
}