{
  "type": "Feature",
  "properties": {
    "addr:full":"337 St. Paul St St Catharines ON L2R 3N1",
    "addr:housenumber":"337",
    "addr:postcode":"l2r 3n1",
    "addr:street":"St. Paul St",
    "iso:country":"CA",
    "sg:address":"337 St. Paul St",
    "sg:city":"St Catharines",
    "sg:classifiers":[
        {
            "category":"Home & Garden",
            "subcategory":"Garden Supply",
            "type":"Retail Goods"
        }
    ],
    "sg:phone":"+1 905 682 9948",
    "sg:postcode":"L2R 3N1",
    "sg:province":"ON",
    "sg:tags":[
        "cleaners",
        "lawn",
        "vacuum",
        "mower"
    ],
    "wof:name":"Sandham Electric Ltd",
    "wof:placetype":"venue"
},
  "geometry": {"coordinates":[-79.2417831421,43.160118103],"type":"Point"}
}