{
  "type": "Feature",
  "properties": {
    "addr:full":"Calgary AB T2P 1G2",
    "addr:postcode":"t2p 1g2",
    "iso:country":"CA",
    "sg:city":"Calgary",
    "sg:classifiers":[
        {
            "category":"Professional",
            "subcategory":"Management & Consulting",
            "type":"Services"
        }
    ],
    "sg:phone":"+1 403 266 1881",
    "sg:postcode":"T2P 1G2",
    "sg:province":"AB",
    "sg:tags":[
        "consultant",
        "training"
    ],
    "wof:name":"Amherst Consultants Ltd",
    "wof:placetype":"venue"
},
  "geometry": {"coordinates":[-114.071861,51.045666],"type":"Point"}
}