{
  "type": "Feature",
  "properties": {
    "addr:full":"12712 Boul Industriel Pointe-Aux-Trembles QC H1A 3V2",
    "addr:housenumber":"12712",
    "addr:postcode":"h1a 3v2",
    "addr:street":"Boul Industriel",
    "iso:country":"CA",
    "sg:address":"12712 Boul Industriel",
    "sg:city":"Pointe-Aux-Trembles",
    "sg:classifiers":[
        {
            "category":"Manufacturing",
            "subcategory":"Tools & Machinery",
            "type":"Manufacturing & Wholesale Goods"
        }
    ],
    "sg:phone":"+1 514 644 0009",
    "sg:postcode":"H1A 3V2",
    "sg:province":"QC",
    "sg:tags":[
        "machine",
        "shop"
    ],
    "wof:name":"A C Usinage Inc",
    "wof:placetype":"venue"
},
  "geometry": {"coordinates":[-73.5161972046,45.6550559998],"type":"Point"}
}