{
  "type": "Feature",
  "properties": {
    "addr:full":"4012 Route 105 Northampton NB E7N 1C9",
    "addr:housenumber":"4012",
    "addr:postcode":"e7n 1c9",
    "addr:street":"Route 105",
    "iso:country":"CA",
    "sg:address":"4012 Route 105",
    "sg:city":"Northampton",
    "sg:classifiers":[
        {
            "category":"Retail",
            "subcategory":"Portrait Studio",
            "type":"Services"
        }
    ],
    "sg:phone":"+1 506 328 8479",
    "sg:postcode":"E7N 1C9",
    "sg:province":"NB",
    "sg:tags":[
        "photographer"
    ],
    "wof:name":"Reflections Photography",
    "wof:placetype":"venue"
},
  "geometry": {"coordinates":[-67.5642318726,46.1254196167],"type":"Point"}
}