{
  "type": "Feature",
  "properties": {
    "addr:full":"44 Glenabbey Dr Courtice ON L1E 1B7",
    "addr:housenumber":"44",
    "addr:postcode":"l1e 1b7",
    "addr:street":"Glenabbey Dr",
    "iso:country":"CA",
    "sg:address":"44 Glenabbey Dr",
    "sg:city":"Courtice",
    "sg:classifiers":[
        {
            "category":"Organizations",
            "subcategory":"Religious Organization",
            "type":"Services"
        }
    ],
    "sg:phone":"+1 905 576 3584",
    "sg:postcode":"L1E 1B7",
    "sg:province":"ON",
    "sg:tags":[
        "church"
    ],
    "wof:name":"Eastern Slavic Conference Paoc",
    "wof:placetype":"venue"
},
  "geometry": {"coordinates":[-78.803093,43.894722],"type":"Point"}
}