{
  "type": "Feature",
  "properties": {
    "addr:full":"Notre-Dame-DE-L'Ile-Perrot QC J7V 7P2",
    "addr:postcode":"j7v 7p2",
    "iso:country":"CA",
    "sg:city":"Notre-Dame-DE-L'Ile-Perrot",
    "sg:classifiers":[
        {
            "category":"Building & Trades",
            "subcategory":"Construction",
            "type":"Services"
        }
    ],
    "sg:phone":"+1 514 453 5019",
    "sg:postcode":"J7V 7P2",
    "sg:province":"QC",
    "sg:tags":[
        "repairing",
        "remodeling",
        "contractor"
    ],
    "wof:name":"Construction Dorion Inc",
    "wof:placetype":"venue"
},
  "geometry": {"coordinates":[-73.95536800000001,45.393764],"type":"Point"}
}