{
  "type": "Feature",
  "properties": {
    "addr:full":"2219 2 St SW Calgary AB T2S 1S8",
    "addr:housenumber":"2219 2",
    "addr:postcode":"t2s 1s8",
    "addr:street":"St Sw",
    "iso:country":"CA",
    "sg:address":"2219 2 St SW",
    "sg:city":"Calgary",
    "sg:classifiers":[
        {
            "category":"Professional",
            "subcategory":"Art Services",
            "type":"Services"
        }
    ],
    "sg:phone":"+1 403 228 0167",
    "sg:postcode":"T2S 1S8",
    "sg:province":"AB",
    "sg:tags":[
        "graphic",
        "designer"
    ],
    "wof:name":"Humdinger Communications",
    "wof:placetype":"venue"
},
  "geometry": {"coordinates":[-114.06909942599999,51.0331001282],"type":"Point"}
}