{
  "type": "Feature",
  "properties": {
    "addr:full":"Guelph ON N1G 4S5",
    "addr:postcode":"n1g 4s5",
    "iso:country":"CA",
    "sg:city":"Guelph",
    "sg:classifiers":[
        {
            "category":"Personal",
            "subcategory":"Beauty Salon",
            "type":"Services"
        }
    ],
    "sg:phone":"+1 519 822 2086",
    "sg:postcode":"N1G 4S5",
    "sg:province":"ON",
    "wof:name":"Principessa Aesthetics",
    "wof:placetype":"venue"
},
  "geometry": {"coordinates":[-80.233437,43.519382],"type":"Point"}
}