{
  "type": "Feature",
  "properties": {
    "addr:full":"Vaudreuil-Dorion QC J7V 8P2",
    "addr:postcode":"j7v 8p2",
    "iso:country":"CA",
    "sg:city":"Vaudreuil-Dorion",
    "sg:classifiers":[
        {
            "category":"Building & Trades",
            "subcategory":"Construction",
            "type":"Services"
        }
    ],
    "sg:phone":"+1 450 424 4311",
    "sg:postcode":"J7V 8P2",
    "sg:province":"QC",
    "sg:tags":[
        "masonry",
        "waterproofing",
        "contractor"
    ],
    "wof:name":"Maconnerie Mar-Ge Inc",
    "wof:placetype":"venue"
},
  "geometry": {"coordinates":[-74.03555299999999,45.371449],"type":"Point"}
}