{
  "type": "Feature",
  "properties": {
    "addr:full":"1105 Rue Provost Lachine QC H8S 1N4",
    "addr:housenumber":"1105",
    "addr:postcode":"h8s 1n4",
    "addr:street":"Rue Provost",
    "iso:country":"CA",
    "sg:address":"1105 Rue Provost",
    "sg:city":"Lachine",
    "sg:classifiers":[
        {
            "category":"Wholesale",
            "subcategory":"Meat",
            "type":"Manufacturing & Wholesale Goods"
        }
    ],
    "sg:phone":"+1 514 637 5565",
    "sg:postcode":"H8S 1N4",
    "sg:province":"QC",
    "sg:tags":[
        "butchering"
    ],
    "wof:name":"Viandes Claude Chartier & Fils",
    "wof:placetype":"venue"
},
  "geometry": {"coordinates":[-73.674042,45.441837],"type":"Point"}
}