{
  "type": "Feature",
  "properties": {
    "addr:full":"8190 Bayview Ave Thornhill ON L3T 2S2",
    "addr:housenumber":"8190",
    "addr:postcode":"l3t 2s2",
    "addr:street":"Bayview Ave",
    "iso:country":"CA",
    "sg:address":"8190 Bayview Ave",
    "sg:city":"Thornhill",
    "sg:classifiers":[
        {
            "category":"Food & Beverages",
            "subcategory":"Groceries & Convenience Stores",
            "type":"Retail Goods"
        }
    ],
    "sg:phone":"+1 905 731 2300",
    "sg:postcode":"L3T 2S2",
    "sg:province":"ON",
    "sg:tags":[
        "grocer"
    ],
    "wof:name":"Food Basics",
    "wof:placetype":"venue"
},
  "geometry": {"coordinates":[-79.404442,43.831097],"type":"Point"}
}