{
  "type": "Feature",
  "properties": {
    "addr:full":"239 Pictou Rd Truro NS B2N 2S7",
    "addr:housenumber":"239",
    "addr:postcode":"b2n 2s7",
    "addr:street":"Pictou Rd",
    "iso:country":"CA",
    "sg:address":"239 Pictou Rd",
    "sg:city":"Truro",
    "sg:classifiers":[
        {
            "category":"Food & Beverages",
            "subcategory":"Liquor & Beverages",
            "type":"Retail Goods"
        }
    ],
    "sg:phone":"+1 902 895 6800",
    "sg:postcode":"B2N 2S7",
    "sg:province":"NS",
    "sg:tags":[
        "store"
    ],
    "wof:name":"Nova Scotia Liquor Commission",
    "wof:placetype":"venue"
},
  "geometry": {"coordinates":[-63.28904,45.36602],"type":"Point"}
}