{
  "type": "Feature",
  "properties": {
    "addr:full":"301 Brodie St S Thunder Bay ON P7E 1C4",
    "addr:housenumber":"301",
    "addr:postcode":"p7e 1c4",
    "addr:street":"Brodie St S",
    "iso:country":"CA",
    "sg:address":"301 Brodie St S",
    "sg:city":"Thunder Bay",
    "sg:classifiers":[
        {
            "category":"Restaurant",
            "type":"Food & Drink"
        }
    ],
    "sg:phone":"+1 807 623 1565",
    "sg:postcode":"P7E 1C4",
    "sg:province":"ON",
    "sg:tags":[
        "club",
        "night"
    ],
    "wof:name":"Inntowner Motor Hotel",
    "wof:placetype":"venue"
},
  "geometry": {"coordinates":[-89.24681091310001,48.3806838989],"type":"Point"}
}