{
  "type": "Feature",
  "properties": {
    "addr:full":"6233 Bathurst St North York ON M2R 2A5",
    "addr:housenumber":"6233",
    "addr:postcode":"m2r 2a5",
    "addr:street":"Bathurst St",
    "iso:country":"CA",
    "sg:address":"6233 Bathurst St",
    "sg:city":"North York",
    "sg:classifiers":[
        {
            "category":"Restaurant",
            "type":"Food & Drink"
        }
    ],
    "sg:phone":"+1 416 222 7727",
    "sg:postcode":"M2R 2A5",
    "sg:province":"ON",
    "wof:name":"Anton Restaurant",
    "wof:placetype":"venue"
},
  "geometry": {"coordinates":[-79.4452056885,43.791053772],"type":"Point"}
}