{
  "type": "Feature",
  "properties": {
    "addr:full":"784 Boul Arthur-Sauve Saint-Eustache QC J7R 4K3",
    "addr:housenumber":"784",
    "addr:postcode":"j7r 4k3",
    "addr:street":"Boul Arthur-Sauve",
    "iso:country":"CA",
    "sg:address":"784 Boul Arthur-Sauve",
    "sg:city":"Saint-Eustache",
    "sg:classifiers":[
        {
            "category":"Retail",
            "subcategory":"Auto Repair",
            "type":"Services"
        }
    ],
    "sg:phone":"+1 450 472 3151",
    "sg:postcode":"J7R 4K3",
    "sg:province":"QC",
    "sg:tags":[
        "repairing",
        "automobile"
    ],
    "wof:name":"Silencieux Belisle Inc",
    "wof:placetype":"venue"
},
  "geometry": {"coordinates":[-73.92141700000001,45.580837],"type":"Point"}
}