{
  "type": "Feature",
  "properties": {
    "addr:full":"514 Grand Ave Luseland SK S0L 2A0",
    "addr:housenumber":"514",
    "addr:postcode":"s0l 2a0",
    "addr:street":"Grand Ave",
    "iso:country":"CA",
    "sg:address":"514 Grand Ave",
    "sg:city":"Luseland",
    "sg:classifiers":[
        {
            "category":"Professional",
            "subcategory":"Accounting & Tax Preparation",
            "type":"Services"
        }
    ],
    "sg:phone":"+1 306 372 4557",
    "sg:postcode":"S0L 2A0",
    "sg:province":"SK",
    "sg:tags":[
        "accountant"
    ],
    "wof:name":"Hepting, Curtis",
    "wof:placetype":"venue"
},
  "geometry": {"coordinates":[-109.39123499999999,52.079819],"type":"Point"}
}