{
  "type": "Feature",
  "properties": {
    "addr:full":"1010 10 Ave SW Calgary AB T2R 1M4",
    "addr:housenumber":"1010",
    "addr:postcode":"t2r 1m4",
    "addr:street":"10 Ave Sw",
    "iso:country":"CA",
    "sg:address":"1010 10 Ave SW",
    "sg:city":"Calgary",
    "sg:classifiers":[
        {
            "category":"Government",
            "subcategory":"Fire Station",
            "type":"Public Place"
        }
    ],
    "sg:phone":"+1 403 264 1022",
    "sg:postcode":"T2R 1M4",
    "sg:province":"AB",
    "sg:tags":[
        "department"
    ],
    "wof:name":"Calgary Fire Dept",
    "wof:placetype":"venue"
},
  "geometry": {"coordinates":[-114.08429700000001,51.044048],"type":"Point"}
}