{
  "type": "Feature",
  "properties": {
    "addr:full":"478 Montee DE L'Eglise L'Ile-Bizard QC H9C 1G9",
    "addr:housenumber":"478",
    "addr:postcode":"h9c 1g9",
    "addr:street":"Montee De L'Eglise",
    "iso:country":"CA",
    "sg:address":"478 Montee DE L'Eglise",
    "sg:city":"L'Ile-Bizard",
    "sg:classifiers":[
        {
            "category":"Manufacturing",
            "subcategory":"Tools & Machinery",
            "type":"Manufacturing & Wholesale Goods"
        }
    ],
    "sg:phone":"+1 514 696 7396",
    "sg:postcode":"H9C 1G9",
    "sg:province":"QC",
    "sg:tags":[
        "machine",
        "shop"
    ],
    "wof:name":"Techno-Usinage Inc",
    "wof:placetype":"venue"
},
  "geometry": {"coordinates":[-73.88014221189999,45.4873886108],"type":"Point"}
}