{
  "type": "Feature",
  "properties": {
    "addr:full":"139 Crystal St Snow Lake MB R0B 1M0",
    "addr:housenumber":"139",
    "addr:postcode":"r0b 1m0",
    "addr:street":"Crystal St",
    "iso:country":"CA",
    "sg:address":"139 Crystal St",
    "sg:city":"Snow Lake",
    "sg:classifiers":[
        {
            "category":"Wholesale",
            "subcategory":"Machinery & Supplies",
            "type":"Manufacturing & Wholesale Goods"
        }
    ],
    "sg:phone":"+1 204 358 2170",
    "sg:postcode":"R0B 1M0",
    "sg:province":"MB",
    "sg:tags":[
        "equipment",
        "mining"
    ],
    "wof:name":"Atlas Copco Construction",
    "wof:placetype":"venue"
},
  "geometry": {"coordinates":[-100.015022278,54.8745231628],"type":"Point"}
}