{
  "type": "Feature",
  "properties": {
    "iso:country":"CA",
    "sg:address":"2600 John St # 126",
    "sg:city":"Markham",
    "sg:classifiers":[
        {
            "category":"Manufacturing",
            "subcategory":"Printing",
            "type":"Manufacturing & Wholesale Goods"
        }
    ],
    "sg:phone":"+1 905 415 1918",
    "sg:postcode":"L3R 3W3",
    "sg:province":"ON",
    "sg:tags":[
        "screen"
    ],
    "wof:name":"Apex Imaging Inc",
    "wof:placetype":"venue"
},
  "geometry": {"coordinates":[-79.361794,43.824341],"type":"Point"}
}