{
  "type": "Feature",
  "properties": {
    "addr:full":"519 Hugel Ave Midland ON L4R 1V8",
    "addr:housenumber":"519",
    "addr:postcode":"l4r 1v8",
    "addr:street":"Hugel Ave",
    "iso:country":"CA",
    "sg:address":"519 Hugel Ave",
    "sg:city":"Midland",
    "sg:classifiers":[
        {
            "category":"Health Services",
            "subcategory":"Doctor",
            "type":"Services"
        }
    ],
    "sg:phone":"+1 705 526 4041",
    "sg:postcode":"L4R 1V8",
    "sg:province":"ON",
    "sg:tags":[
        "clinic"
    ],
    "wof:name":"Robertson Denture Therapy Clnc",
    "wof:placetype":"venue"
},
  "geometry": {"coordinates":[-79.885536,44.749912],"type":"Point"}
}