{
  "type": "Feature",
  "properties": {
    "addr:full":"5637 Finch Ave E Scarborough ON M1B 5K9",
    "addr:housenumber":"5637",
    "addr:postcode":"m1b 5k9",
    "addr:street":"Finch Ave E",
    "iso:country":"CA",
    "sg:address":"5637 Finch Ave E",
    "sg:city":"Scarborough",
    "sg:classifiers":[
        {
            "category":"Home & Garden",
            "subcategory":"Carpets & Floor Coverings",
            "type":"Retail Goods"
        }
    ],
    "sg:phone":"+1 416 321 5220",
    "sg:postcode":"M1B 5K9",
    "sg:province":"ON",
    "sg:tags":[
        "bathroom",
        "remodeling",
        "rug"
    ],
    "wof:name":"Rapid Renovators CO Ltd",
    "wof:placetype":"venue"
},
  "geometry": {"coordinates":[-79.2396316528,43.8135986328],"type":"Point"}
}