{
  "type": "Feature",
  "properties": {
    "iso:country":"CA",
    "sg:city":"Bridgewater",
    "sg:classifiers":[
        {
            "category":"Restaurant",
            "type":"Food & Drink"
        }
    ],
    "sg:phone":"+1 902 543 2328",
    "sg:postcode":"B4V 3N2",
    "sg:province":"NS",
    "sg:tags":[
        "caterer"
    ],
    "wof:name":"Everything Nice Cafe-Catering",
    "wof:placetype":"venue"
},
  "geometry": {"coordinates":[-64.5137023926,44.383228302],"type":"Point"}
}