{
  "type": "Feature",
  "properties": {
    "addr:full":"374 Gregoire Dr Fort Mcmurray AB T9H 3R2",
    "addr:housenumber":"374",
    "addr:postcode":"t9h 3r2",
    "addr:street":"Gregoire Dr",
    "iso:country":"CA",
    "sg:address":"374 Gregoire Dr",
    "sg:city":"Fort Mcmurray",
    "sg:classifiers":[
        {
            "category":"Wholesale",
            "subcategory":"Machinery & Supplies",
            "type":"Manufacturing & Wholesale Goods"
        }
    ],
    "sg:phone":"+1 780 791 9513",
    "sg:postcode":"T9H 3R2",
    "sg:province":"AB",
    "sg:tags":[
        "equipment",
        "welding"
    ],
    "wof:name":"Praxair",
    "wof:placetype":"venue"
},
  "geometry": {"coordinates":[-111.348938,56.683727],"type":"Point"}
}