{
  "type": "Feature",
  "properties": {
    "iso:country":"CA",
    "sg:city":"Macamic",
    "sg:classifiers":[
        {
            "category":"Freight",
            "type":"Transportation"
        }
    ],
    "sg:phone":"+1 819 782 2704",
    "sg:postcode":"J0Z 2S0",
    "sg:province":"QC",
    "sg:tags":[
        "trucking"
    ],
    "wof:name":"Andre Daigle Construction Ltee",
    "wof:placetype":"venue"
},
  "geometry": {"coordinates":[-79.0000152588,48.7591705322],"type":"Point"}
}