{
  "type": "Feature",
  "properties": {
    "iso:country":"CA",
    "sg:city":"Vancouver",
    "sg:classifiers":[
        {
            "category":"Banks & Credit Unions",
            "subcategory":"Investment Brokerage",
            "type":"Services"
        }
    ],
    "sg:phone":"+1 604 684 1158",
    "sg:postcode":"V6C 2E8",
    "sg:province":"BC",
    "sg:tags":[
        "consultant",
        "planning",
        "financial"
    ],
    "wof:name":"Lemay Enterprises Financial",
    "wof:placetype":"venue"
},
  "geometry": {"coordinates":[-123.118171692,49.2851104736],"type":"Point"}
}