{
  "type": "Feature",
  "properties": {
    "addr:full":"1355 Mitchell St Victoria BC V8S 4P9",
    "addr:housenumber":"1355",
    "addr:postcode":"v8s 4p9",
    "addr:street":"Mitchell St",
    "iso:country":"CA",
    "sg:address":"1355 Mitchell St",
    "sg:city":"Victoria",
    "sg:classifiers":[
        {
            "category":"Organizations",
            "subcategory":"Religious Organization",
            "type":"Services"
        }
    ],
    "sg:phone":"+1 250 598 5021",
    "sg:postcode":"V8S 4P9",
    "sg:province":"BC",
    "sg:tags":[
        "church"
    ],
    "wof:name":"Oak Bay United Church",
    "wof:placetype":"venue"
},
  "geometry": {"coordinates":[-123.36451700000001,48.428314],"type":"Point"}
}