{
  "type": "Feature",
  "properties": {
    "addr:full":"462 Av Dorval Dorval QC H9S 3H7",
    "addr:postcode":"h9s 3h7",
    "addr:street":"462 Av Dorval",
    "iso:country":"CA",
    "sg:address":"462 Av Dorval",
    "sg:city":"Dorval",
    "sg:classifiers":[
        {
            "category":"Shopping",
            "subcategory":"Clothing, Apparel, & Fashions",
            "type":"Retail Goods"
        }
    ],
    "sg:phone":"+1 514 631 6812",
    "sg:postcode":"H9S 3H7",
    "sg:province":"QC",
    "sg:tags":[
        "infant",
        "wear"
    ],
    "wof:name":"Mini Vogue",
    "wof:placetype":"venue"
},
  "geometry": {"coordinates":[-73.741302,45.444946],"type":"Point"}
}