{
  "type": "Feature",
  "properties": {
    "addr:full":"6526 4 St NE Calgary AB T2K 6H2",
    "addr:housenumber":"6526 4",
    "addr:postcode":"t2k 6h2",
    "addr:street":"St Ne",
    "iso:country":"CA",
    "sg:address":"6526 4 St NE",
    "sg:city":"Calgary",
    "sg:classifiers":[
        {
            "category":"Health Services",
            "subcategory":"Doctor",
            "type":"Services"
        }
    ],
    "sg:phone":"+1 403 274 7040",
    "sg:postcode":"T2K 6H2",
    "sg:province":"AB",
    "sg:tags":[
        "dentist"
    ],
    "wof:name":"Mah, Wayman DDS",
    "wof:placetype":"venue"
},
  "geometry": {"coordinates":[-114.05652618400001,51.1110801697],"type":"Point"}
}