{
  "type": "Feature",
  "properties": {
    "iso:country":"CA",
    "sg:address":"10524 124 St NW",
    "sg:city":"Edmonton",
    "sg:classifiers":[
        {
            "category":"Wholesale",
            "subcategory":"Jewelry",
            "type":"Manufacturing & Wholesale Goods"
        }
    ],
    "sg:phone":"+1 780 452 8693",
    "sg:postcode":"T5N 1R9",
    "sg:province":"AB",
    "sg:tags":[
        "jeweler",
        "supply"
    ],
    "wof:name":"Edmonton Findings House",
    "wof:placetype":"venue"
},
  "geometry": {"coordinates":[-113.536118,53.548252],"type":"Point"}
}