{
  "type": "Feature",
  "properties": {
    "addr:full":"Yellowknife NT X1A 3T3",
    "addr:postcode":"x1a 3t3",
    "iso:country":"CA",
    "sg:city":"Yellowknife",
    "sg:classifiers":[
        {
            "category":"Wholesale",
            "subcategory":"Hardware",
            "type":"Manufacturing & Wholesale Goods"
        }
    ],
    "sg:phone":"+1 867 873 2711",
    "sg:postcode":"X1A 3T3",
    "sg:province":"NT",
    "sg:tags":[
        "plumbing",
        "fixture",
        "supply"
    ],
    "wof:name":"Emco Supply Frontier Mining",
    "wof:placetype":"venue"
},
  "geometry": {"coordinates":[-114.41378021200001,62.4632949829],"type":"Point"}
}