{
  "type": "Feature",
  "properties": {
    "addr:full":"420 Eddystone Ave North York ON M3N 1H7",
    "addr:housenumber":"420",
    "addr:postcode":"m3n 1h7",
    "addr:street":"Eddystone Ave",
    "iso:country":"CA",
    "sg:address":"420 Eddystone Ave",
    "sg:city":"North York",
    "sg:classifiers":[
        {
            "category":"Wholesale",
            "subcategory":"Machinery & Supplies",
            "type":"Manufacturing & Wholesale Goods"
        }
    ],
    "sg:phone":"+1 416 745 8247",
    "sg:postcode":"M3N 1H7",
    "sg:province":"ON",
    "sg:tags":[
        "equipment",
        "veterinarian"
    ],
    "wof:name":"Vet Link Ltd",
    "wof:placetype":"venue"
},
  "geometry": {"coordinates":[-79.5240020752,43.7473831177],"type":"Point"}
}