{
  "type": "Feature",
  "properties": {
    "iso:country":"CA",
    "sg:city":"Longueuil",
    "sg:classifiers":[
        {
            "category":"Health Services",
            "subcategory":"Doctor",
            "type":"Services"
        }
    ],
    "sg:phone":"+1 450 674 1504",
    "sg:postcode":"J4K 2T4",
    "sg:province":"QC",
    "sg:tags":[
        "clinic",
        "dentist"
    ],
    "wof:name":"Centre Dentaire Laporte",
    "wof:placetype":"venue"
},
  "geometry": {"coordinates":[-73.52252960209999,45.5253448486],"type":"Point"}
}