{
  "type": "Feature",
  "properties": {
    "addr:full":"10124 127 Ave NW Edmonton AB T5E 0B7",
    "addr:housenumber":"10124",
    "addr:postcode":"t5e 0b7",
    "addr:street":"127 Ave Nw",
    "iso:country":"CA",
    "sg:address":"10124 127 Ave NW",
    "sg:city":"Edmonton",
    "sg:classifiers":[
        {
            "category":"Retail",
            "subcategory":"Repair Shop",
            "type":"Services"
        }
    ],
    "sg:phone":"+1 780 476 9003",
    "sg:postcode":"T5E 0B7",
    "sg:province":"AB",
    "sg:tags":[
        "scooter",
        "motorcycle",
        "motor"
    ],
    "wof:name":"Leisure Cycle",
    "wof:placetype":"venue"
},
  "geometry": {"coordinates":[-113.494553,53.584938],"type":"Point"}
}