{
  "type": "Feature",
  "properties": {
    "addr:full":"13 Main St Sherbrooke NS B0J 3C0",
    "addr:housenumber":"13",
    "addr:postcode":"b0j 3c0",
    "addr:street":"Main St",
    "iso:country":"CA",
    "sg:address":"13 Main St",
    "sg:city":"Sherbrooke",
    "sg:classifiers":[
        {
            "category":"Education",
            "subcategory":"Library",
            "type":"Public Place"
        }
    ],
    "sg:phone":"+1 902 522 2180",
    "sg:postcode":"B0J 3C0",
    "sg:province":"NS",
    "wof:name":"Sherbrooke Library",
    "wof:placetype":"venue"
},
  "geometry": {"coordinates":[-61.9830322266,45.1418533325],"type":"Point"}
}