{
  "type": "Feature",
  "properties": {
    "addr:full":"130 Lepage Crt # 22 North York ON M3J 3J1",
    "addr:housenumber":"130",
    "addr:postcode":"m3j 3j1",
    "addr:street":"Lepage Crt # 22",
    "iso:country":"CA",
    "sg:address":"130 Lepage Crt # 22",
    "sg:city":"North York",
    "sg:classifiers":[
        {
            "category":"Autos & Motor Vehicles",
            "subcategory":"Automobile Sales",
            "type":"Retail Goods"
        }
    ],
    "sg:phone":"+1 416 633 7111",
    "sg:postcode":"M3J 3J1",
    "sg:province":"ON",
    "sg:tags":[
        "car",
        "dealer"
    ],
    "wof:name":"Ragtops Motorcar CO Inc",
    "wof:placetype":"venue"
},
  "geometry": {"coordinates":[-79.483231,43.759693],"type":"Point"}
}