{
  "type": "Feature",
  "properties": {
    "iso:country":"CA",
    "sg:address":"185 Pauline St",
    "sg:city":"Chelmsford",
    "sg:classifiers":[
        {
            "category":"Shopping",
            "type":"Retail Goods"
        }
    ],
    "sg:phone":"+1 705 855 5666",
    "sg:postcode":"P0M 1L0",
    "sg:province":"ON",
    "sg:tags":[
        "picture",
        "frame"
    ],
    "wof:name":"Frames By Day",
    "wof:placetype":"venue"
},
  "geometry": {"coordinates":[-81.188667,46.561512],"type":"Point"}
}