{
  "type": "Feature",
  "properties": {
    "addr:full":"2266 Keele St North York ON M6M 3Y9",
    "addr:housenumber":"2266",
    "addr:postcode":"m6m 3y9",
    "addr:street":"Keele St",
    "iso:country":"CA",
    "sg:address":"2266 Keele St",
    "sg:city":"North York",
    "sg:classifiers":[
        {
            "category":"Retail",
            "subcategory":"Laundry & Dry Cleaning",
            "type":"Services"
        }
    ],
    "sg:phone":"+1 416 247 0057",
    "sg:postcode":"M6M 3Y9",
    "sg:province":"ON",
    "sg:tags":[
        "cleaners"
    ],
    "wof:name":"Kleenest Cleaners",
    "wof:placetype":"venue"
},
  "geometry": {"coordinates":[-79.476799,43.702374],"type":"Point"}
}