{
  "type": "Feature",
  "properties": {
    "addr:full":"694 Ch Saint-Thomas Chicoutimi QC G7H 2R2",
    "addr:housenumber":"694",
    "addr:postcode":"g7h 2r2",
    "addr:street":"Ch Saint-Thomas",
    "iso:country":"CA",
    "sg:address":"694 Ch Saint-Thomas",
    "sg:city":"Chicoutimi",
    "sg:classifiers":[
        {
            "category":"Home & Garden",
            "subcategory":"Building Materials",
            "type":"Retail Goods"
        }
    ],
    "sg:phone":"+1 418 543 6383",
    "sg:postcode":"G7H 2R2",
    "sg:province":"QC",
    "sg:tags":[
        "glass",
        "window",
        "plate"
    ],
    "wof:name":"Pare-Brise Plus",
    "wof:placetype":"venue"
},
  "geometry": {"coordinates":[-71.0477981567,48.4160270691],"type":"Point"}
}