{
  "type": "Feature",
  "properties": {
    "addr:full":"184 Stephens St Thunder Bay ON P7A 2P3",
    "addr:housenumber":"184",
    "addr:postcode":"p7a 2p3",
    "addr:street":"Stephens St",
    "iso:country":"CA",
    "sg:address":"184 Stephens St",
    "sg:city":"Thunder Bay",
    "sg:classifiers":[
        {
            "category":"Manufacturing",
            "subcategory":"Metals",
            "type":"Manufacturing & Wholesale Goods"
        }
    ],
    "sg:phone":"+1 807 344 1162",
    "sg:postcode":"P7A 2P3",
    "sg:province":"ON",
    "sg:tags":[
        "windows"
    ],
    "wof:name":"Glass & Paint Clinic",
    "wof:placetype":"venue"
},
  "geometry": {"coordinates":[-89.204239,48.444881],"type":"Point"}
}