{
  "type": "Feature",
  "properties": {
    "iso:country":"CA",
    "sg:address":"17011 Headline Rd W",
    "sg:city":"Long Sault",
    "sg:classifiers":[
        {
            "category":"Retail",
            "subcategory":"Auto Repair",
            "type":"Services"
        }
    ],
    "sg:phone":"+1 613 933 2525",
    "sg:postcode":"K0C 1P0",
    "sg:province":"ON",
    "sg:tags":[
        "wrecker"
    ],
    "wof:name":"Cornwall Towing",
    "wof:placetype":"venue"
},
  "geometry": {"coordinates":[-74.89831542970001,45.0299835205],"type":"Point"}
}