{
  "type": "Feature",
  "properties": {
    "addr:full":"1559 Albuna Town Line Leamington ON N8H 4G1",
    "addr:housenumber":"1559",
    "addr:postcode":"n8h 4g1",
    "addr:street":"Albuna Town Line",
    "iso:country":"CA",
    "sg:address":"1559 Albuna Town Line",
    "sg:city":"Leamington",
    "sg:classifiers":[
        {
            "category":"Building & Trades",
            "subcategory":"Electrical",
            "type":"Services"
        }
    ],
    "sg:phone":"+1 519 326 9259",
    "sg:postcode":"N8H 4G1",
    "sg:province":"ON",
    "sg:tags":[
        "contractor",
        "electric",
        "heating"
    ],
    "wof:name":"Ciacelli Mechanical Contr Ltd",
    "wof:placetype":"venue"
},
  "geometry": {"coordinates":[-82.599716,42.054153],"type":"Point"}
}