{
  "type": "Feature",
  "properties": {
    "addr:full":"Toronto ON M5G 1T6",
    "addr:postcode":"m5g 1t6",
    "iso:country":"CA",
    "sg:city":"Toronto",
    "sg:classifiers":[
        {
            "category":"Professional",
            "subcategory":"Lawyer & Legal Services",
            "type":"Services"
        }
    ],
    "sg:phone":"+1 416 596 0722",
    "sg:postcode":"M5G 1T6",
    "sg:province":"ON",
    "sg:tags":[
        "attorney"
    ],
    "wof:name":"Valentine, Robert G",
    "wof:placetype":"venue"
},
  "geometry": {"coordinates":[-79.387703,43.654259],"type":"Point"}
}