{
  "type": "Feature",
  "properties": {
    "addr:full":"4 High St SE Calgary AB T2Z 3T8",
    "addr:housenumber":"4",
    "addr:postcode":"t2z 3t8",
    "addr:street":"High St Se",
    "iso:country":"CA",
    "sg:address":"4 High St SE",
    "sg:city":"Calgary",
    "sg:classifiers":[
        {
            "category":"Cinema",
            "subcategory":"Movie Rental",
            "type":"Entertainment"
        }
    ],
    "sg:phone":"+1 403 257 3773",
    "sg:postcode":"T2Z 3T8",
    "sg:province":"AB",
    "sg:tags":[
        "player",
        "recorder",
        "video",
        "leasing",
        "tape"
    ],
    "wof:name":"Blockbuster Video",
    "wof:placetype":"venue"
},
  "geometry": {"coordinates":[-113.960022,50.916061],"type":"Point"}
}