{
  "type": "Feature",
  "properties": {
    "addr:full":"6505 Vipond Dr Mississauga ON L5T 1J9",
    "addr:housenumber":"6505",
    "addr:postcode":"l5t 1j9",
    "addr:street":"Vipond Dr",
    "iso:country":"CA",
    "sg:address":"6505 Vipond Dr",
    "sg:city":"Mississauga",
    "sg:classifiers":[
        {
            "category":"Freight",
            "type":"Transportation"
        }
    ],
    "sg:phone":"+1 905 565 8877",
    "sg:postcode":"L5T 1J9",
    "sg:province":"ON",
    "sg:tags":[
        "trucking"
    ],
    "wof:name":"Bestway Cartage Ltd",
    "wof:placetype":"venue"
},
  "geometry": {"coordinates":[-79.66539,43.662128],"type":"Point"}
}