{
  "type": "Feature",
  "properties": {
    "addr:full":"4720 Old Scugog Rd RR 1 Bowmanville ON L1C 3K2",
    "addr:housenumber":"4720",
    "addr:postcode":"l1c 3k2",
    "addr:street":"Old Scugog Rd",
    "iso:country":"CA",
    "sg:address":"4720 Old Scugog Rd RR 1",
    "sg:city":"Bowmanville",
    "sg:classifiers":[
        {
            "category":"Professional",
            "subcategory":"Business Services",
            "type":"Services"
        }
    ],
    "sg:phone":"+1 905 263 2944",
    "sg:postcode":"L1C 3K2",
    "sg:province":"ON",
    "sg:tags":[
        "shop",
        "gift",
        "consultant",
        "design",
        "interior",
        "decorator"
    ],
    "wof:name":"Spruce Tree",
    "wof:placetype":"venue"
},
  "geometry": {"coordinates":[-78.732292,43.960438],"type":"Point"}
}