{
  "type": "Feature",
  "properties": {
    "addr:full":"556 Clendenan Ave Toronto ON M6P 2Y1",
    "addr:housenumber":"556",
    "addr:postcode":"m6p 2y1",
    "addr:street":"Clendenan Ave",
    "iso:country":"CA",
    "sg:address":"556 Clendenan Ave",
    "sg:city":"Toronto",
    "sg:classifiers":[
        {
            "category":"Health Services",
            "subcategory":"Clinic",
            "type":"Services"
        }
    ],
    "sg:phone":"+1 416 760 0058",
    "sg:postcode":"M6P 2Y1",
    "sg:province":"ON",
    "sg:tags":[
        "aid",
        "first"
    ],
    "wof:name":"Saje Health & Safety Cpr",
    "wof:placetype":"venue"
},
  "geometry": {"coordinates":[-79.4737701416,43.6663970947],"type":"Point"}
}