{
  "type": "Feature",
  "properties": {
    "addr:full":"157 Mountain St Hinton AB T7V 1M6",
    "addr:housenumber":"157",
    "addr:postcode":"t7v 1m6",
    "addr:street":"Mountain St",
    "iso:country":"CA",
    "sg:address":"157 Mountain St",
    "sg:city":"Hinton",
    "sg:classifiers":[
        {
            "category":"Food & Beverages",
            "subcategory":"Groceries & Convenience Stores",
            "type":"Retail Goods"
        }
    ],
    "sg:phone":"+1 780 865 2844",
    "sg:postcode":"T7V 1M6",
    "sg:province":"AB",
    "sg:tags":[
        "grocer"
    ],
    "wof:name":"West End Grocery",
    "wof:placetype":"venue"
},
  "geometry": {"coordinates":[-117.599861,53.393089],"type":"Point"}
}