{
  "type": "Feature",
  "properties": {
    "iso:country":"CA",
    "sg:address":"2501 Steeles Ave W",
    "sg:city":"North York",
    "sg:classifiers":[
        {
            "category":"Wholesale",
            "subcategory":"Non-durable Goods",
            "type":"Manufacturing & Wholesale Goods"
        }
    ],
    "sg:phone":"+1 416 650 0323",
    "sg:postcode":"M3J 2P1",
    "sg:province":"ON",
    "sg:tags":[
        "buckle"
    ],
    "wof:name":"Capitol Buttons CO Ltd",
    "wof:placetype":"venue"
},
  "geometry": {"coordinates":[-79.482749939,43.784160614],"type":"Point"}
}