{
  "type": "Feature",
  "properties": {
    "addr:full":"Sherwood Park AB T8H 1M1",
    "addr:postcode":"t8h 1m1",
    "iso:country":"CA",
    "sg:city":"Sherwood Park",
    "sg:classifiers":[
        {
            "category":"Restaurant",
            "type":"Food & Drink"
        }
    ],
    "sg:phone":"+1 780 449 2424",
    "sg:postcode":"T8H 1M1",
    "sg:province":"AB",
    "wof:name":"Willy's Place Dining Room",
    "wof:placetype":"venue"
},
  "geometry": {"coordinates":[-113.268951,53.567093],"type":"Point"}
}