{
  "type": "Feature",
  "properties": {
    "addr:full":"12 Bradwick Dr # 5 Concord ON L4K 3P6",
    "addr:housenumber":"12",
    "addr:postcode":"l4k 3p6",
    "addr:street":"Bradwick Dr # 5",
    "iso:country":"CA",
    "sg:address":"12 Bradwick Dr # 5",
    "sg:city":"Concord",
    "sg:classifiers":[
        {
            "category":"Wholesale",
            "subcategory":"Non-durable Goods",
            "type":"Manufacturing & Wholesale Goods"
        }
    ],
    "sg:phone":"+1 905 761 5261",
    "sg:postcode":"L4K 3P6",
    "sg:province":"ON",
    "sg:tags":[
        "advertising"
    ],
    "wof:name":"Event Marketing",
    "wof:placetype":"venue"
},
  "geometry": {"coordinates":[-79.483177,43.818317],"type":"Point"}
}