{
  "type": "Feature",
  "properties": {
    "addr:full":"1315 Rue Principale E Abbotsford QC J0E 1A0",
    "addr:housenumber":"1315",
    "addr:postcode":"j0e 1a0",
    "addr:street":"Rue Principale E",
    "iso:country":"CA",
    "sg:address":"1315 Rue Principale E",
    "sg:city":"Abbotsford",
    "sg:classifiers":[
        {
            "category":"Food & Beverages",
            "subcategory":"Fruits & Vegetables",
            "type":"Retail Goods"
        }
    ],
    "sg:phone":"+1 450 379 9393",
    "sg:postcode":"J0E 1A0",
    "sg:province":"QC",
    "sg:tags":[
        "produce"
    ],
    "wof:name":"Relais DE LA Pomme",
    "wof:placetype":"venue"
},
  "geometry": {"coordinates":[-72.86451721189999,45.4343109131],"type":"Point"}
}