{
  "type": "Feature",
  "properties": {
    "addr:full":"139 Valley Rd Wakefield QC J0X 3G0",
    "addr:housenumber":"139",
    "addr:postcode":"j0x 3g0",
    "addr:street":"Valley Rd",
    "iso:country":"CA",
    "sg:address":"139 Valley Rd",
    "sg:city":"Wakefield",
    "sg:classifiers":[
        {
            "category":"Retail",
            "subcategory":"Funeral Services",
            "type":"Services"
        }
    ],
    "sg:phone":"+1 819 459 1800",
    "sg:postcode":"J0X 3G0",
    "sg:province":"QC",
    "sg:tags":[
        "director"
    ],
    "wof:name":"Mc Garry Crematorium",
    "wof:placetype":"venue"
},
  "geometry": {"coordinates":[-75.932022,45.631081],"type":"Point"}
}