{
  "type": "Feature",
  "properties": {
    "addr:full":"2602 Quadra St Victoria BC V8T 4E4",
    "addr:housenumber":"2602",
    "addr:postcode":"v8t 4e4",
    "addr:street":"Quadra St",
    "iso:country":"CA",
    "sg:address":"2602 Quadra St",
    "sg:city":"Victoria",
    "sg:classifiers":[
        {
            "category":"Health Services",
            "subcategory":"Chiropractor",
            "type":"Services"
        }
    ],
    "sg:phone":"+1 250 386 8887",
    "sg:postcode":"V8T 4E4",
    "sg:province":"BC",
    "wof:name":"Mac Leod, Colin DC",
    "wof:placetype":"venue"
},
  "geometry": {"coordinates":[-123.358764648,48.4377441406],"type":"Point"}
}