{
  "type": "Feature",
  "properties": {
    "addr:full":"1253 St Clair Ave W Toronto ON M6E 1B8",
    "addr:housenumber":"1253",
    "addr:postcode":"m6e 1b8",
    "addr:street":"St Clair Ave W",
    "iso:country":"CA",
    "sg:address":"1253 St Clair Ave W",
    "sg:city":"Toronto",
    "sg:classifiers":[
        {
            "category":"Health Services",
            "subcategory":"Optometrist",
            "type":"Services"
        }
    ],
    "sg:phone":"+1 416 929 9133",
    "sg:postcode":"M6E 1B8",
    "sg:province":"ON",
    "wof:name":"Eng, Edmund OD",
    "wof:placetype":"venue"
},
  "geometry": {"coordinates":[-79.446327,43.677132],"type":"Point"}
}