{
  "type": "Feature",
  "properties": {
    "addr:full":"9 Main St Florenceville NB E7L 3G2",
    "addr:housenumber":"9",
    "addr:postcode":"e7l 3g2",
    "addr:street":"Main St",
    "iso:country":"CA",
    "sg:address":"9 Main St",
    "sg:city":"Florenceville",
    "sg:classifiers":[
        {
            "category":"Food & Beverages",
            "subcategory":"Groceries & Convenience Stores",
            "type":"Retail Goods"
        }
    ],
    "sg:phone":"+1 506 392 8844",
    "sg:postcode":"E7L 3G2",
    "sg:province":"NB",
    "sg:tags":[
        "grocer"
    ],
    "wof:name":"Carleton CO-Operative Ltd",
    "wof:placetype":"venue"
},
  "geometry": {"coordinates":[-67.609245,46.451981],"type":"Point"}
}