{
  "type": "Feature",
  "properties": {
    "addr:full":"42 South St Goderich ON N7A 3L5",
    "addr:housenumber":"42",
    "addr:postcode":"n7a 3l5",
    "addr:street":"South St",
    "iso:country":"CA",
    "sg:address":"42 South St",
    "sg:city":"Goderich",
    "sg:classifiers":[
        {
            "category":"Government",
            "subcategory":"Office",
            "type":"Public Place"
        }
    ],
    "sg:phone":"+1 519 524 2193",
    "sg:postcode":"N7A 3L5",
    "sg:province":"ON",
    "wof:name":"Ontario Correctional Svc",
    "wof:placetype":"venue"
},
  "geometry": {"coordinates":[-81.711349,43.741444],"type":"Point"}
}