{
  "type": "Feature",
  "properties": {
    "addr:full":"3222 Rue Beaubien E Montreal QC H1Y 1H7",
    "addr:housenumber":"3222",
    "addr:postcode":"h1y 1h7",
    "addr:street":"Rue Beaubien E",
    "iso:country":"CA",
    "sg:address":"3222 Rue Beaubien E",
    "sg:city":"Montreal",
    "sg:classifiers":[
        {
            "category":"Retail",
            "subcategory":"Laundry & Dry Cleaning",
            "type":"Services"
        }
    ],
    "sg:phone":"+1 514 722 7005",
    "sg:postcode":"H1Y 1H7",
    "sg:province":"QC",
    "sg:tags":[
        "cleaners"
    ],
    "wof:name":"Nettoyeur Multi'p",
    "wof:placetype":"venue"
},
  "geometry": {"coordinates":[-73.58641799999999,45.554623],"type":"Point"}
}