{
  "type": "Feature",
  "properties": {
    "addr:full":"3765 56 St Wetaskiwin AB T9A 3E7",
    "addr:housenumber":"3765",
    "addr:postcode":"t9a 3e7",
    "addr:street":"56 St",
    "iso:country":"CA",
    "sg:address":"3765 56 St",
    "sg:city":"Wetaskiwin",
    "sg:classifiers":[
        {
            "category":"Restaurant",
            "type":"Food & Drink"
        }
    ],
    "sg:phone":"+1 780 352 4511",
    "sg:postcode":"T9A 3E7",
    "sg:province":"AB",
    "wof:name":"Tasty Wok",
    "wof:placetype":"venue"
},
  "geometry": {"coordinates":[-113.38986969,52.9561691284],"type":"Point"}
}