{
  "type": "Feature",
  "properties": {
    "addr:full":"972 Clarkson Rd Mississauga ON L5J 2V7",
    "addr:housenumber":"972",
    "addr:postcode":"l5j 2v7",
    "addr:street":"Clarkson Rd",
    "iso:country":"CA",
    "sg:address":"972 Clarkson Rd",
    "sg:city":"Mississauga",
    "sg:classifiers":[
        {
            "category":"Professional",
            "subcategory":"Lawyer & Legal Services",
            "type":"Services"
        }
    ],
    "sg:phone":"+1 905 823 4400",
    "sg:postcode":"L5J 2V7",
    "sg:province":"ON",
    "sg:tags":[
        "attorney"
    ],
    "wof:name":"Garvey & Garvey Llp",
    "wof:placetype":"venue"
},
  "geometry": {"coordinates":[-79.6231918335,43.516166687],"type":"Point"}
}