{
  "type": "Feature",
  "properties": {
    "addr:full":"4667 Av Papineau Montreal QC H2H 1V4",
    "addr:housenumber":"4667",
    "addr:postcode":"h2h 1v4",
    "addr:street":"Av Papineau",
    "iso:country":"CA",
    "sg:address":"4667 Av Papineau",
    "sg:city":"Montreal",
    "sg:classifiers":[
        {
            "category":"Professional",
            "subcategory":"Research",
            "type":"Services"
        }
    ],
    "sg:phone":"+1 514 529 4004",
    "sg:postcode":"H2H 1V4",
    "sg:province":"QC",
    "sg:tags":[
        "market",
        "analysis"
    ],
    "wof:name":"Opinion Du Consommateur",
    "wof:placetype":"venue"
},
  "geometry": {"coordinates":[-73.5763702393,45.5339012146],"type":"Point"}
}