{
  "type": "Feature",
  "properties": {
    "addr:full":"9680 Rue Jeanne-Mance Montreal QC H3L 3B3",
    "addr:housenumber":"9680",
    "addr:postcode":"h3l 3b3",
    "addr:street":"Rue Jeanne-Mance",
    "iso:country":"CA",
    "sg:address":"9680 Rue Jeanne-Mance",
    "sg:city":"Montreal",
    "sg:classifiers":[
        {
            "category":"Manufacturing",
            "subcategory":"Printing",
            "type":"Manufacturing & Wholesale Goods"
        }
    ],
    "sg:phone":"+1 514 387 4548",
    "sg:postcode":"H3L 3B3",
    "sg:province":"QC",
    "sg:tags":[
        "printer"
    ],
    "wof:name":"Asty-Litho Ltd",
    "wof:placetype":"venue"
},
  "geometry": {"coordinates":[-73.65400699999999,45.53957],"type":"Point"}
}