{
  "type": "Feature",
  "properties": {
    "addr:full":"247 Lilac St Winnipeg MB R3M 2S2",
    "addr:housenumber":"247",
    "addr:postcode":"r3m 2s2",
    "addr:street":"Lilac St",
    "iso:country":"CA",
    "sg:address":"247 Lilac St",
    "sg:city":"Winnipeg",
    "sg:classifiers":[
        {
            "category":"Food & Beverages",
            "subcategory":"Groceries & Convenience Stores",
            "type":"Retail Goods"
        }
    ],
    "sg:phone":"+1 204 475 6638",
    "sg:postcode":"R3M 2S2",
    "sg:province":"MB",
    "sg:tags":[
        "grocer"
    ],
    "wof:name":"Foodfare Stores",
    "wof:placetype":"venue"
},
  "geometry": {"coordinates":[-97.157089,49.869797],"type":"Point"}
}