{
  "type": "Feature",
  "properties": {
    "addr:full":"2014 Bathurst St York ON M5P 3L1",
    "addr:housenumber":"2014",
    "addr:postcode":"m5p 3l1",
    "addr:street":"Bathurst St",
    "iso:country":"CA",
    "sg:address":"2014 Bathurst St",
    "sg:city":"York",
    "sg:classifiers":[
        {
            "category":"Shopping",
            "subcategory":"Jewelry",
            "type":"Retail Goods"
        }
    ],
    "sg:phone":"+1 416 785 4312",
    "sg:postcode":"M5P 3L1",
    "sg:province":"ON",
    "sg:tags":[
        "jeweler"
    ],
    "wof:name":"Joe Pro Jewellery Inc",
    "wof:placetype":"venue"
},
  "geometry": {"coordinates":[-79.4255981445,43.7007331848],"type":"Point"}
}