{
  "type": "Feature",
  "properties": {
    "addr:full":"85 Rue DE LA Polyvalente Charlesbourg QC G2N 1G7",
    "addr:housenumber":"85",
    "addr:postcode":"g2n 1g7",
    "addr:street":"Rue De La Polyvalente",
    "iso:country":"CA",
    "sg:address":"85 Rue DE LA Polyvalente",
    "sg:city":"Charlesbourg",
    "sg:classifiers":[
        {
            "category":"Professional",
            "subcategory":"Accounting & Tax Preparation",
            "type":"Services"
        }
    ],
    "sg:phone":"+1 418 849 5982",
    "sg:postcode":"G2N 1G7",
    "sg:province":"QC",
    "sg:tags":[
        "return",
        "filing"
    ],
    "wof:name":"Impot Deschenes",
    "wof:placetype":"venue"
},
  "geometry": {"coordinates":[-71.3310012817,46.9135055542],"type":"Point"}
}