{
  "type": "Feature",
  "properties": {
    "addr:full":"643 4E Av Saint-Romuald QC G6W 5M6",
    "addr:housenumber":"643",
    "addr:postcode":"g6w 5m6",
    "addr:street":"4E Av Saint-Romuald",
    "iso:country":"CA",
    "sg:address":"643 4E Av",
    "sg:city":"Saint-Romuald",
    "sg:classifiers":[
        {
            "category":"Bars & Pubs",
            "type":"Food & Drink"
        }
    ],
    "sg:phone":"+1 418 834 3257",
    "sg:postcode":"G6W 5M6",
    "sg:province":"QC",
    "sg:tags":[
        "lounge",
        "cocktail"
    ],
    "wof:name":"Bar L'Extase",
    "wof:placetype":"venue"
},
  "geometry": {"coordinates":[-71.240089,46.758121],"type":"Point"}
}