{
  "type": "Feature",
  "properties": {
    "addr:full":"568 Academy Rd Winnipeg MB R3N 0E3",
    "addr:housenumber":"568",
    "addr:postcode":"r3n 0e3",
    "addr:street":"Academy Rd",
    "iso:country":"CA",
    "sg:address":"568 Academy Rd",
    "sg:city":"Winnipeg",
    "sg:classifiers":[
        {
            "category":"Shopping",
            "subcategory":"Clothing, Apparel, & Fashions",
            "type":"Retail Goods"
        }
    ],
    "sg:phone":"+1 204 487 1681",
    "sg:postcode":"R3N 0E3",
    "sg:province":"MB",
    "wof:name":"Chestnut Lane Boutique",
    "wof:placetype":"venue"
},
  "geometry": {"coordinates":[-97.19807434080001,49.8741874695],"type":"Point"}
}