{
  "type": "Feature",
  "properties": {
    "addr:full":"Calgary AB T2K 3K2",
    "addr:postcode":"t2k 3k2",
    "iso:country":"CA",
    "sg:city":"Calgary",
    "sg:classifiers":[
        {
            "category":"Food & Beverages",
            "subcategory":"Liquor & Beverages",
            "type":"Retail Goods"
        }
    ],
    "sg:phone":"+1 403 284 2222",
    "sg:postcode":"T2K 3K2",
    "sg:province":"AB",
    "sg:tags":[
        "store"
    ],
    "wof:name":"Jag's Liquor Zone",
    "wof:placetype":"venue"
},
  "geometry": {"coordinates":[-114.09281900000001,51.08287],"type":"Point"}
}