{
  "type": "Feature",
  "properties": {
    "iso:country":"CA",
    "sg:address":"147 Main St E",
    "sg:city":"Milton",
    "sg:classifiers":[
        {
            "category":"Banks & Credit Unions",
            "subcategory":"Bank",
            "type":"Services"
        }
    ],
    "sg:phone":"+1 905 878 2321",
    "sg:postcode":"L9T 1N7",
    "sg:province":"ON",
    "wof:name":"Cibc",
    "wof:placetype":"venue"
},
  "geometry": {"coordinates":[-79.88468899999999,43.51194],"type":"Point"}
}