{
  "type": "Feature",
  "properties": {
    "addr:full":"1645 Rue King E Fleurimont QC J1G 5G7",
    "addr:housenumber":"1645",
    "addr:postcode":"j1g 5g7",
    "addr:street":"Rue King E Fleurimont",
    "iso:country":"CA",
    "sg:address":"1645 Rue King E",
    "sg:city":"Fleurimont",
    "sg:classifiers":[
        {
            "category":"Autos & Motor Vehicles",
            "subcategory":"Auto Supplies",
            "type":"Retail Goods"
        }
    ],
    "sg:phone":"+1 819 566 5991",
    "sg:postcode":"J1G 5G7",
    "sg:province":"QC",
    "sg:tags":[
        "repairing",
        "automobile",
        "parts"
    ],
    "wof:name":"Canadian Tire",
    "wof:placetype":"venue"
},
  "geometry": {"coordinates":[-71.851021,45.409111],"type":"Point"}
}