{
  "type": "Feature",
  "properties": {
    "addr:full":"1916 Queen St E Toronto ON M4L 1H5",
    "addr:housenumber":"1916",
    "addr:postcode":"m4l 1h5",
    "addr:street":"Queen St E",
    "iso:country":"CA",
    "sg:address":"1916 Queen St E",
    "sg:city":"Toronto",
    "sg:classifiers":[
        {
            "category":"Shopping",
            "subcategory":"Florist",
            "type":"Retail Goods"
        }
    ],
    "sg:phone":"+1 416 691 8185",
    "sg:postcode":"M4L 1H5",
    "sg:province":"ON",
    "wof:name":"Beachwood Flower Shop",
    "wof:placetype":"venue"
},
  "geometry": {"coordinates":[-79.30418396,43.669254303],"type":"Point"}
}