{
  "type": "Feature",
  "properties": {
    "addr:full":"207 Grand Ave E Chatham ON N7L 1W3",
    "addr:housenumber":"207",
    "addr:postcode":"n7l 1w3",
    "addr:street":"Grand Ave E",
    "iso:country":"CA",
    "sg:address":"207 Grand Ave E",
    "sg:city":"Chatham",
    "sg:classifiers":[
        {
            "category":"Building & Trades",
            "subcategory":"Construction",
            "type":"Services"
        }
    ],
    "sg:phone":"+1 519 351 3106",
    "sg:postcode":"N7L 1W3",
    "sg:province":"ON",
    "sg:tags":[
        "contractor"
    ],
    "wof:name":"Chatham Builders & Renovators",
    "wof:placetype":"venue"
},
  "geometry": {"coordinates":[-82.18493700000001,42.412228],"type":"Point"}
}