{
  "type": "Feature",
  "properties": {
    "addr:full":"3425 Harvester Rd Burlington ON L7N 3N1",
    "addr:housenumber":"3425",
    "addr:postcode":"l7n 3n1",
    "addr:street":"Harvester Rd",
    "iso:country":"CA",
    "sg:address":"3425 Harvester Rd",
    "sg:city":"Burlington",
    "sg:classifiers":[
        {
            "category":"Professional",
            "subcategory":"Computer Services",
            "type":"Services"
        }
    ],
    "sg:phone":"+1 905 639 8533",
    "sg:postcode":"L7N 3N1",
    "sg:province":"ON",
    "sg:tags":[
        "consultant"
    ],
    "wof:name":"Coyote Software Corp",
    "wof:placetype":"venue"
},
  "geometry": {"coordinates":[-79.7880706787,43.3603134155],"type":"Point"}
}