{
  "type": "Feature",
  "properties": {
    "addr:full":"Cranbrook BC V1C 3P6",
    "addr:postcode":"v1c 3p6",
    "iso:country":"CA",
    "sg:city":"Cranbrook",
    "sg:classifiers":[
        {
            "category":"Insurance",
            "subcategory":"Insurance Agent",
            "type":"Services"
        }
    ],
    "sg:phone":"+1 250 426 6651",
    "sg:postcode":"V1C 3P6",
    "sg:province":"BC",
    "sg:tags":[
        "adjuster"
    ],
    "wof:name":"Cunningham Lindsey Canada Ltd",
    "wof:placetype":"venue"
},
  "geometry": {"coordinates":[-115.767426,49.51226],"type":"Point"}
}