{
  "type": "Feature",
  "properties": {
    "addr:full":"Vancouver BC V6A 4C7",
    "addr:postcode":"v6a 4c7",
    "iso:country":"CA",
    "sg:city":"Vancouver",
    "sg:classifiers":[
        {
            "category":"Professional",
            "subcategory":"Detective & Security Services",
            "type":"Services"
        }
    ],
    "sg:phone":"+1 604 683 0621",
    "sg:postcode":"V6A 4C7",
    "sg:province":"BC",
    "sg:tags":[
        "guard",
        "patrol"
    ],
    "wof:name":"Protect Security Svc Ltd",
    "wof:placetype":"venue"
},
  "geometry": {"coordinates":[-123.098221,49.274311],"type":"Point"}
}