{
  "type": "Feature",
  "properties": {
    "addr:full":"Campbell River BC V9W 2Y1",
    "addr:postcode":"v9w 2y1",
    "iso:country":"CA",
    "sg:city":"Campbell River",
    "sg:classifiers":[
        {
            "category":"Shopping",
            "type":"Retail Goods"
        }
    ],
    "sg:phone":"+1 250 287 7405",
    "sg:postcode":"V9W 2Y1",
    "sg:province":"BC",
    "sg:tags":[
        "pet",
        "shop",
        "supply"
    ],
    "wof:name":"Dogwood Pet Mart",
    "wof:placetype":"venue"
},
  "geometry": {"coordinates":[-125.24723815900001,50.0116348267],"type":"Point"}
}