{
  "type": "Feature",
  "properties": {
    "addr:full":"64 Forest Ave Hamilton ON L8N 1X1",
    "addr:housenumber":"64",
    "addr:postcode":"l8n 1x1",
    "addr:street":"Forest Ave",
    "iso:country":"CA",
    "sg:address":"64 Forest Ave",
    "sg:city":"Hamilton",
    "sg:classifiers":[
        {
            "category":"Organizations",
            "subcategory":"Religious Organization",
            "type":"Services"
        }
    ],
    "sg:phone":"+1 905 527 3505",
    "sg:postcode":"L8N 1X1",
    "sg:province":"ON",
    "sg:tags":[
        "church"
    ],
    "wof:name":"Church of the Ascension",
    "wof:placetype":"venue"
},
  "geometry": {"coordinates":[-79.869644165,43.2497940063],"type":"Point"}
}