{
  "type": "Feature",
  "properties": {
    "addr:full":"1395 Lawrence Ave W North York ON M6L 1A4",
    "addr:housenumber":"1395",
    "addr:postcode":"m6l 1a4",
    "addr:street":"Lawrence Ave W",
    "iso:country":"CA",
    "sg:address":"1395 Lawrence Ave W",
    "sg:city":"North York",
    "sg:classifiers":[
        {
            "category":"Shopping",
            "subcategory":"Gifts & Souvenirs",
            "type":"Retail Goods"
        }
    ],
    "sg:phone":"+1 416 240 0706",
    "sg:postcode":"M6L 1A4",
    "sg:province":"ON",
    "sg:tags":[
        "shop"
    ],
    "wof:name":"Tender Thoughts",
    "wof:placetype":"venue"
},
  "geometry": {"coordinates":[-79.4771347046,43.7089118958],"type":"Point"}
}