{
  "type": "Feature",
  "properties": {
    "addr:full":"30 Barrieau St Miramichi NB E1N 4V3",
    "addr:housenumber":"30",
    "addr:postcode":"e1n 4v3",
    "addr:street":"Barrieau St",
    "iso:country":"CA",
    "sg:address":"30 Barrieau St",
    "sg:city":"Miramichi",
    "sg:classifiers":[
        {
            "category":"Recreation",
            "type":"Entertainment"
        }
    ],
    "sg:phone":"+1 506 622 0621",
    "sg:postcode":"E1N 4V3",
    "sg:province":"NB",
    "sg:tags":[
        "stable"
    ],
    "wof:name":"Double D Stables",
    "wof:placetype":"venue"
},
  "geometry": {"coordinates":[-65.51612854,46.9908714294],"type":"Point"}
}