{
  "type": "Feature",
  "properties": {
    "iso:country":"CA",
    "sg:address":"129 Boul Saint-Luc",
    "sg:city":"Saint-Luc",
    "sg:classifiers":[
        {
            "category":"Personal",
            "subcategory":"Beauty Salon",
            "type":"Services"
        }
    ],
    "sg:phone":"+1 450 349 4702",
    "sg:postcode":"J2W 1E1",
    "sg:province":"QC",
    "wof:name":"Salon Enr",
    "wof:placetype":"venue"
},
  "geometry": {"coordinates":[-73.278091,45.34108],"type":"Point"}
}