{
  "type": "Feature",
  "properties": {
    "addr:full":"15 Josephine Dr Hamilton ON L9B 1Z8",
    "addr:housenumber":"15",
    "addr:postcode":"l9b 1z8",
    "addr:street":"Josephine Dr",
    "iso:country":"CA",
    "sg:address":"15 Josephine Dr",
    "sg:city":"Hamilton",
    "sg:classifiers":[
        {
            "category":"Building & Trades",
            "subcategory":"Plumbing",
            "type":"Services"
        }
    ],
    "sg:phone":"+1 905 383 1823",
    "sg:postcode":"L9B 1Z8",
    "sg:province":"ON",
    "sg:tags":[
        "contractor"
    ],
    "wof:name":"Mc Connell Plumbing & Htg Ltd",
    "wof:placetype":"venue"
},
  "geometry": {"coordinates":[-79.873817,43.20549],"type":"Point"}
}