{
  "type": "Feature",
  "properties": {
    "iso:country":"CA",
    "sg:address":"50 Rue Rosedale",
    "sg:city":"Dollard-Des-Ormeaux",
    "sg:classifiers":[
        {
            "category":"Wholesale",
            "subcategory":"Non-durable Goods",
            "type":"Manufacturing & Wholesale Goods"
        }
    ],
    "sg:phone":"+1 514 624 5424",
    "sg:postcode":"H9G 1E1",
    "sg:province":"QC",
    "sg:tags":[
        "pet",
        "supply"
    ],
    "wof:name":"Produits Pour Animaux LA Niche",
    "wof:placetype":"venue"
},
  "geometry": {"coordinates":[-73.851051,45.469311],"type":"Point"}
}