{
  "type": "Feature",
  "properties": {
    "addr:full":"2 Rue D'Eglise Eel River Crossing NB E8E 1P6",
    "addr:housenumber":"2",
    "addr:postcode":"e8e 1p6",
    "addr:street":"Rue D'Eglise Eel River Crossing",
    "iso:country":"CA",
    "sg:address":"2 Rue D'Eglise",
    "sg:city":"Eel River Crossing",
    "sg:classifiers":[
        {
            "category":"Organizations",
            "subcategory":"Religious Organization",
            "type":"Services"
        }
    ],
    "sg:phone":"+1 506 826 2816",
    "sg:postcode":"E8E 1P6",
    "sg:province":"NB",
    "sg:tags":[
        "church"
    ],
    "wof:name":"St Trinite Catholic Church",
    "wof:placetype":"venue"
},
  "geometry": {"coordinates":[-66.4216918945,48.0162391663],"type":"Point"}
}