{
  "type": "Feature",
  "properties": {
    "addr:full":"New Westminster BC V3L 5B5",
    "addr:postcode":"v3l 5b5",
    "iso:country":"CA",
    "sg:city":"New Westminster",
    "sg:classifiers":[
        {
            "category":"Manufacturing",
            "subcategory":"Textiles",
            "type":"Manufacturing & Wholesale Goods"
        }
    ],
    "sg:phone":"+1 604 522 6745",
    "sg:postcode":"V3L 5B5",
    "sg:province":"BC",
    "sg:tags":[
        "upholsterer"
    ],
    "wof:name":"Nip & Tuck Interiors Ltd",
    "wof:placetype":"venue"
},
  "geometry": {"coordinates":[-122.912742615,49.2231941223],"type":"Point"}
}