{
  "type": "Feature",
  "properties": {
    "addr:full":"65 Mahon Ave North Vancouver BC V7M 2R3",
    "addr:housenumber":"65",
    "addr:postcode":"v7m 2r3",
    "addr:street":"Mahon Ave",
    "iso:country":"CA",
    "sg:address":"65 Mahon Ave",
    "sg:city":"North Vancouver",
    "sg:classifiers":[
        {
            "category":"Retail",
            "subcategory":"Auto Repair",
            "type":"Services"
        }
    ],
    "sg:phone":"+1 604 984 4566",
    "sg:postcode":"V7M 2R3",
    "sg:province":"BC",
    "sg:tags":[
        "repairing",
        "automobile"
    ],
    "wof:name":"City Auto",
    "wof:placetype":"venue"
},
  "geometry": {"coordinates":[-123.08524300000001,49.314358],"type":"Point"}
}