{
  "type": "Feature",
  "properties": {
    "addr:full":"9 Industrial Pky S Aurora ON L4G 3V9",
    "addr:housenumber":"9",
    "addr:postcode":"l4g 3v9",
    "addr:street":"Industrial Pky",
    "iso:country":"CA",
    "sg:address":"9 Industrial Pky S",
    "sg:city":"Aurora",
    "sg:classifiers":[
        {
            "category":"Shopping",
            "subcategory":"Computers & Home Electronics",
            "type":"Retail Goods"
        }
    ],
    "sg:phone":"+1 905 726 2853",
    "sg:postcode":"L4G 3V9",
    "sg:province":"ON",
    "sg:tags":[
        "training",
        "management",
        "software"
    ],
    "wof:name":"Strategic Transitions Inc",
    "wof:placetype":"venue"
},
  "geometry": {"coordinates":[-79.45626831049999,44.001209259],"type":"Point"}
}