{
  "type": "Feature",
  "properties": {
    "addr:full":"1591 10th Ave Fernie BC V0B 1M0",
    "addr:housenumber":"1591",
    "addr:postcode":"bc v0b 1m0",
    "addr:street":"10Th Ave",
    "iso:country":"CA",
    "sg:address":"1591 10th Ave",
    "sg:city":"Fernie",
    "sg:classifiers":[
        {
            "category":"Utilities",
            "subcategory":"Mobile Phone",
            "type":"Services"
        }
    ],
    "sg:phone":"+1 250 423 4160",
    "sg:postcode":"V0B 1M0",
    "sg:province":"BC",
    "sg:tags":[
        "telephone",
        "cellular"
    ],
    "wof:name":"Jrt Communications",
    "wof:placetype":"venue"
},
  "geometry": {"coordinates":[-115.06192,49.515915],"type":"Point"}
}