{
  "type": "Feature",
  "properties": {
    "addr:full":"4134 Dundas St W Etobicoke ON M8X 1X3",
    "addr:housenumber":"4134",
    "addr:postcode":"m8x 1x3",
    "addr:street":"Dundas St W",
    "iso:country":"CA",
    "sg:address":"4134 Dundas St W",
    "sg:city":"Etobicoke",
    "sg:classifiers":[
        {
            "category":"Travel",
            "subcategory":"Travel Agent",
            "type":"Entertainment"
        }
    ],
    "sg:phone":"+1 416 233 4601",
    "sg:postcode":"M8X 1X3",
    "sg:province":"ON",
    "sg:tags":[
        "agency",
        "bureau"
    ],
    "wof:name":"Pysanka Inc",
    "wof:placetype":"venue"
},
  "geometry": {"coordinates":[-79.5076293945,43.6618881226],"type":"Point"}
}