{
  "type": "Feature",
  "properties": {
    "iso:country":"CA",
    "sg:city":"Vermilion",
    "sg:classifiers":[
        {
            "category":"Personal",
            "subcategory":"Beauty Salon",
            "type":"Services"
        }
    ],
    "sg:phone":"+1 780 853 5447",
    "sg:postcode":"T9X 1G1",
    "sg:province":"AB",
    "wof:name":"Riverside Hair Design",
    "wof:placetype":"venue"
},
  "geometry": {"coordinates":[-110.835319519,53.3499794006],"type":"Point"}
}