{
  "type": "Feature",
  "properties": {
    "iso:country":"CA",
    "sg:city":"Thornhill",
    "sg:classifiers":[
        {
            "category":"Retail",
            "subcategory":"Veterinary Services",
            "type":"Services"
        }
    ],
    "sg:phone":"+1 905 731 3922",
    "sg:postcode":"L4J 3W1",
    "sg:province":"ON",
    "sg:tags":[
        "veterinarian"
    ],
    "wof:name":"Steeles Veterinary Svc",
    "wof:placetype":"venue"
},
  "geometry": {"coordinates":[-79.4468917847,43.7979354858],"type":"Point"}
}