{
  "type": "Feature",
  "properties": {
    "addr:full":"2 Primrose Blvd Sherwood Park AB T8H 1G2",
    "addr:housenumber":"2",
    "addr:postcode":"t8h 1g2",
    "addr:street":"Primrose Blvd",
    "iso:country":"CA",
    "sg:address":"2 Primrose Blvd",
    "sg:city":"Sherwood Park",
    "sg:classifiers":[
        {
            "category":"Organizations",
            "subcategory":"Religious Organization",
            "type":"Services"
        }
    ],
    "sg:phone":"+1 780 467 0337",
    "sg:postcode":"T8H 1G2",
    "sg:province":"AB",
    "sg:tags":[
        "church"
    ],
    "wof:name":"Good News Moravian Church",
    "wof:placetype":"venue"
},
  "geometry": {"coordinates":[-113.26269531200001,53.5463409424],"type":"Point"}
}