{
  "type": "Feature",
  "properties": {
    "addr:full":"3270 60 Ave NE Salmon Arm BC V1E 2A9",
    "addr:housenumber":"3270",
    "addr:postcode":"v1e 2a9",
    "addr:street":"60 Ave Ne",
    "iso:country":"CA",
    "sg:address":"3270 60 Ave NE",
    "sg:city":"Salmon Arm",
    "sg:classifiers":[
        {
            "category":"Organizations",
            "subcategory":"Religious Organization",
            "type":"Services"
        }
    ],
    "sg:phone":"+1 250 832 8936",
    "sg:postcode":"V1E 2A9",
    "sg:province":"BC",
    "sg:tags":[
        "church"
    ],
    "wof:name":"Seventh Day Adventist Church",
    "wof:placetype":"venue"
},
  "geometry": {"coordinates":[-119.25252500000001,50.743389],"type":"Point"}
}