{
  "type": "Feature",
  "properties": {
    "addr:full":"North York ON M3N 1Y4",
    "addr:postcode":"m3n 1y4",
    "iso:country":"CA",
    "sg:city":"North York",
    "sg:classifiers":[
        {
            "category":"Wholesale",
            "subcategory":"Electrical",
            "type":"Manufacturing & Wholesale Goods"
        }
    ],
    "sg:phone":"+1 416 667 9909",
    "sg:postcode":"M3N 1Y4",
    "sg:province":"ON",
    "sg:tags":[
        "equipment",
        "electronic",
        "supply"
    ],
    "wof:name":"Omega Electronic Inc",
    "wof:placetype":"venue"
},
  "geometry": {"coordinates":[-79.52919,43.760559],"type":"Point"}
}