{
  "type": "Feature",
  "properties": {
    "addr:full":"PO Box 5131 STN A Calgary AB T2H 1X3",
    "addr:housenumber":"po",
    "addr:postcode":"t2h 1x3",
    "addr:street":"Box 5131 Stn A",
    "iso:country":"CA",
    "sg:address":"PO Box 5131 STN A",
    "sg:city":"Calgary",
    "sg:classifiers":[
        {
            "category":"Shopping",
            "subcategory":"Bicycles & Sporting Goods",
            "type":"Retail Goods"
        }
    ],
    "sg:phone":"+1 403 294 1919",
    "sg:postcode":"T2H 1X3",
    "sg:province":"AB",
    "sg:tags":[
        "equipment",
        "playground"
    ],
    "wof:name":"Habitat Systems Inc",
    "wof:placetype":"venue"
},
  "geometry": {"coordinates":[-114.063194275,51.0450744629],"type":"Point"}
}