{
  "type": "Feature",
  "properties": {
    "addr:full":"12161 100 Ave Surrey BC V3V 2W7",
    "addr:housenumber":"12161",
    "addr:postcode":"v3v 2w7",
    "addr:street":"100 Ave",
    "iso:country":"CA",
    "sg:address":"12161 100 Ave",
    "sg:city":"Surrey",
    "sg:classifiers":[
        {
            "category":"Professional",
            "type":"Services"
        }
    ],
    "sg:phone":"+1 604 930 1788",
    "sg:postcode":"V3V 2W7",
    "sg:province":"BC",
    "sg:tags":[
        "meteorologist"
    ],
    "wof:name":"Air-Sea Research Ltd",
    "wof:placetype":"venue"
},
  "geometry": {"coordinates":[-122.88556699999999,49.184685],"type":"Point"}
}