{
  "type": "Feature",
  "properties": {
    "addr:full":"37 Rue Principale E Adstock QC G0N 1S0",
    "addr:housenumber":"37",
    "addr:postcode":"g0n 1s0",
    "addr:street":"Rue Principale E",
    "iso:country":"CA",
    "sg:address":"37 Rue Principale E",
    "sg:city":"Adstock",
    "sg:classifiers":[
        {
            "category":"Building & Trades",
            "subcategory":"Construction",
            "type":"Services"
        }
    ],
    "sg:phone":"+1 418 422 2355",
    "sg:postcode":"G0N 1S0",
    "sg:province":"QC",
    "sg:tags":[
        "cabinet",
        "maker",
        "woodworker"
    ],
    "wof:name":"Menuiserie St-Methode",
    "wof:placetype":"venue"
},
  "geometry": {"coordinates":[-71.074196,46.045609],"type":"Point"}
}