{
  "type": "Feature",
  "properties": {
    "addr:full":"1628 5th Line Ohsweken ON N0A 1M0",
    "addr:housenumber":"1628",
    "addr:postcode":"n0a 1m0",
    "addr:street":"5Th Line",
    "iso:country":"CA",
    "sg:address":"1628 5th Line",
    "sg:city":"Ohsweken",
    "sg:classifiers":[
        {
            "category":"Retail",
            "subcategory":"Auto Repair",
            "type":"Services"
        }
    ],
    "sg:phone":"+1 519 445 0182",
    "sg:postcode":"N0A 1M0",
    "sg:province":"ON",
    "sg:tags":[
        "wrecker"
    ],
    "wof:name":"Steve's Towing",
    "wof:placetype":"venue"
},
  "geometry": {"coordinates":[-80.11879730219999,43.0690460205],"type":"Point"}
}