{
  "type": "Feature",
  "properties": {
    "addr:full":"117 Allan Ave Saltcoats SK S0A 3R0",
    "addr:housenumber":"117",
    "addr:postcode":"s0a 3r0",
    "addr:street":"Allan Ave",
    "iso:country":"CA",
    "sg:address":"117 Allan Ave",
    "sg:city":"Saltcoats",
    "sg:classifiers":[
        {
            "category":"Education",
            "subcategory":"Library",
            "type":"Public Place"
        }
    ],
    "sg:phone":"+1 306 744 2911",
    "sg:postcode":"S0A 3R0",
    "sg:province":"SK",
    "wof:name":"Saltcoats Library",
    "wof:placetype":"venue"
},
  "geometry": {"coordinates":[-102.169204712,51.041229248],"type":"Point"}
}