{
  "type": "Feature",
  "properties": {
    "addr:full":"754 Northey Bay Rd Woodview ON K0L 3E0",
    "addr:housenumber":"754",
    "addr:postcode":"k0l 3e0",
    "addr:street":"Northey Bay Rd",
    "iso:country":"CA",
    "sg:address":"754 Northey Bay Rd",
    "sg:city":"Woodview",
    "sg:classifiers":[
        {
            "category":"Building & Trades",
            "subcategory":"Construction",
            "type":"Services"
        }
    ],
    "sg:phone":"+1 705 654 4312",
    "sg:postcode":"K0L 3E0",
    "sg:province":"ON",
    "sg:tags":[
        "contractor",
        "general"
    ],
    "wof:name":"Timberline Custom Homes",
    "wof:placetype":"venue"
},
  "geometry": {"coordinates":[-78.135178,44.592964],"type":"Point"}
}