{
  "type": "Feature",
  "properties": {
    "addr:full":"2227 Banff Trail NW Calgary AB T2M 4L2",
    "addr:housenumber":"2227",
    "addr:postcode":"t2m 4l2",
    "addr:street":"Banff Trail Nw",
    "iso:country":"CA",
    "sg:address":"2227 Banff Trail NW",
    "sg:city":"Calgary",
    "sg:classifiers":[
        {
            "category":"Travel",
            "subcategory":"Hotels & Motels",
            "type":"Entertainment"
        }
    ],
    "sg:phone":"+1 403 289 6600",
    "sg:postcode":"T2M 4L2",
    "sg:province":"AB",
    "wof:name":"Holiday Inn Express",
    "wof:placetype":"venue"
},
  "geometry": {"coordinates":[-114.11341899999999,51.067699],"type":"Point"}
}