{
  "type": "Feature",
  "properties": {
    "addr:full":"1321 Boul Saint-Joseph Quebec QC G2K 1G4",
    "addr:housenumber":"1321",
    "addr:postcode":"g2k 1g4",
    "addr:street":"Boul Saint-Joseph",
    "iso:country":"CA",
    "sg:address":"1321 Boul Saint-Joseph",
    "sg:city":"Quebec",
    "sg:classifiers":[
        {
            "category":"Retail",
            "subcategory":"Auto Repair",
            "type":"Services"
        }
    ],
    "sg:phone":"+1 418 628 3715",
    "sg:postcode":"G2K 1G4",
    "sg:province":"QC",
    "sg:tags":[
        "repairing",
        "automobile"
    ],
    "wof:name":"Garage Rene Gauthier Inc",
    "wof:placetype":"venue"
},
  "geometry": {"coordinates":[-71.28369903559999,46.8534698486],"type":"Point"}
}