{
  "type": "Feature",
  "properties": {
    "addr:full":"Ottawa ON K1V 1J5",
    "addr:postcode":"k1v 1j5",
    "iso:country":"CA",
    "sg:city":"Ottawa",
    "sg:classifiers":[
        {
            "category":"Shopping",
            "subcategory":"Pharmacy",
            "type":"Retail Goods"
        }
    ],
    "sg:phone":"+1 613 733 2283",
    "sg:postcode":"K1V 1J5",
    "sg:province":"ON",
    "wof:name":"Drug Store Pharmacy",
    "wof:placetype":"venue"
},
  "geometry": {"coordinates":[-75.6543273926,45.3575286865],"type":"Point"}
}