{
  "type": "Feature",
  "properties": {
    "addr:full":"PO Box 216 Wallace NS B0K 1Y0",
    "addr:housenumber":"po;216",
    "addr:postcode":"b0k 1y0",
    "addr:street":"Box",
    "iso:country":"CA",
    "sg:address":"PO Box 216",
    "sg:city":"Wallace",
    "sg:classifiers":[
        {
            "category":"Organizations",
            "subcategory":"Religious Organization",
            "type":"Services"
        }
    ],
    "sg:phone":"+1 902 257 2811",
    "sg:postcode":"B0K 1Y0",
    "sg:province":"NS",
    "sg:tags":[
        "church"
    ],
    "wof:name":"St Matthew Presbyterian Church",
    "wof:placetype":"venue"
},
  "geometry": {"coordinates":[-63.476177,45.813232],"type":"Point"}
}