{
  "type": "Feature",
  "properties": {
    "addr:full":"2943 10th Ave Port Alberni BC V9Y 2N5",
    "addr:housenumber":"2943",
    "addr:postcode":"v9y 2n5",
    "addr:street":"10Th Ave",
    "iso:country":"CA",
    "sg:address":"2943 10th Ave",
    "sg:city":"Port Alberni",
    "sg:classifiers":[
        {
            "category":"Food & Beverages",
            "subcategory":"Groceries & Convenience Stores",
            "type":"Retail Goods"
        }
    ],
    "sg:phone":"+1 250 723 3397",
    "sg:postcode":"V9Y 2N5",
    "sg:province":"BC",
    "sg:tags":[
        "grocer"
    ],
    "wof:name":"Quality Foods",
    "wof:placetype":"venue"
},
  "geometry": {"coordinates":[-124.797691345,49.2329101562],"type":"Point"}
}