{
  "type": "Feature",
  "properties": {
    "addr:full":"4535 Rg Desharnais Chesterville QC G0P 1J0",
    "addr:housenumber":"4535",
    "addr:postcode":"g0p 1j0",
    "addr:street":"Rg Desharnais",
    "iso:country":"CA",
    "sg:address":"4535 Rg Desharnais",
    "sg:city":"Chesterville",
    "sg:classifiers":[
        {
            "category":"Retail",
            "subcategory":"Veterinary Services",
            "type":"Services"
        }
    ],
    "sg:phone":"+1 819 382 9911",
    "sg:postcode":"G0P 1J0",
    "sg:province":"QC",
    "sg:tags":[
        "veterinarian"
    ],
    "wof:name":"Roux, Claudia",
    "wof:placetype":"venue"
},
  "geometry": {"coordinates":[-71.81076,45.991295],"type":"Point"}
}