{
  "type": "Feature",
  "properties": {
    "addr:full":"80 Toronto St Barrie ON L4N 1V2",
    "addr:housenumber":"80",
    "addr:postcode":"l4n 1v2",
    "addr:street":"Toronto St",
    "iso:country":"CA",
    "sg:address":"80 Toronto St",
    "sg:city":"Barrie",
    "sg:classifiers":[
        {
            "category":"Professional",
            "subcategory":"Art Services",
            "type":"Services"
        }
    ],
    "sg:phone":"+1 705 737 1792",
    "sg:postcode":"L4N 1V2",
    "sg:province":"ON",
    "sg:tags":[
        "photographer"
    ],
    "wof:name":"Amora Portrait Studio Ltd",
    "wof:placetype":"venue"
},
  "geometry": {"coordinates":[-79.694603,44.388973],"type":"Point"}
}