{
  "type": "Feature",
  "properties": {
    "addr:full":"Scarborough ON M1V 5H7",
    "addr:postcode":"m1v 5h7",
    "iso:country":"CA",
    "sg:city":"Scarborough",
    "sg:classifiers":[
        {
            "category":"Wholesale",
            "subcategory":"Electrical",
            "type":"Manufacturing & Wholesale Goods"
        }
    ],
    "sg:phone":"+1 416 609 8068",
    "sg:postcode":"M1V 5H7",
    "sg:province":"ON",
    "sg:tags":[
        "lighting",
        "fixture"
    ],
    "wof:name":"Mak Industrial Inc",
    "wof:placetype":"venue"
},
  "geometry": {"coordinates":[-79.2946853638,43.8033943176],"type":"Point"}
}