{
  "type": "Feature",
  "properties": {
    "addr:full":"2825 Longhill Rd Kelowna BC V1V 2G5",
    "addr:housenumber":"2825",
    "addr:postcode":"v1v 2g5",
    "addr:street":"Longhill Rd",
    "iso:country":"CA",
    "sg:address":"2825 Longhill Rd",
    "sg:city":"Kelowna",
    "sg:classifiers":[
        {
            "category":"Freight",
            "type":"Transportation"
        }
    ],
    "sg:phone":"+1 250 868 3380",
    "sg:postcode":"V1V 2G5",
    "sg:province":"BC",
    "sg:tags":[
        "excavating",
        "contractor",
        "trucking"
    ],
    "wof:name":"Grassmick's Excavating Ltd",
    "wof:placetype":"venue"
},
  "geometry": {"coordinates":[-119.410843,49.916283],"type":"Point"}
}