{
  "type": "Feature",
  "properties": {
    "addr:full":"Calgary AB T2P 1C2",
    "addr:postcode":"t2p 1c2",
    "iso:country":"CA",
    "sg:city":"Calgary",
    "sg:classifiers":[
        {
            "category":"Mining & Drilling",
            "type":"Manufacturing & Wholesale Goods"
        }
    ],
    "sg:phone":"+1 403 269 5111",
    "sg:postcode":"T2P 1C2",
    "sg:province":"AB",
    "sg:tags":[
        "field",
        "oil"
    ],
    "wof:name":"C-Tech Oilwell Tech Inc",
    "wof:placetype":"venue"
},
  "geometry": {"coordinates":[-114.068268,51.045826],"type":"Point"}
}