{
  "type": "Feature",
  "properties": {
    "addr:full":"Lachine QC H8T 1A4",
    "addr:postcode":"h8t 1a4",
    "iso:country":"CA",
    "sg:city":"Lachine",
    "sg:classifiers":[
        {
            "category":"Freight",
            "type":"Transportation"
        }
    ],
    "sg:phone":"+1 514 631 2880",
    "sg:postcode":"H8T 1A4",
    "sg:province":"QC",
    "sg:tags":[
        "shipping",
        "agent"
    ],
    "wof:name":"Odyssey Shipping Ltd",
    "wof:placetype":"venue"
},
  "geometry": {"coordinates":[-73.720001,45.463985],"type":"Point"}
}