{
  "type": "Feature",
  "properties": {
    "addr:full":"18 Av Sainte-Brigitte S Montmagny QC G5V 2X8",
    "addr:postcode":"g5v 2x8",
    "addr:street":"18 Av Sainte-Brigitte S Montmagny",
    "iso:country":"CA",
    "sg:address":"18 Av Sainte-Brigitte S",
    "sg:city":"Montmagny",
    "sg:classifiers":[
        {
            "category":"Organizations",
            "subcategory":"Professional Association",
            "type":"Services"
        }
    ],
    "sg:phone":"+1 418 248 3954",
    "sg:postcode":"G5V 2X8",
    "sg:province":"QC",
    "wof:name":"Festival DE L'Oie Blanche DE",
    "wof:placetype":"venue"
},
  "geometry": {"coordinates":[-70.5637588501,46.9805374146],"type":"Point"}
}