{
  "type": "Feature",
  "properties": {
    "addr:full":"2762 Highway 532 Searchmont ON P0S 1J0",
    "addr:housenumber":"2762",
    "addr:postcode":"p0s 1j0",
    "addr:street":"Highway 532",
    "iso:country":"CA",
    "sg:address":"2762 Highway 532",
    "sg:city":"Searchmont",
    "sg:classifiers":[
        {
            "category":"Travel",
            "subcategory":"Hotels & Motels",
            "type":"Entertainment"
        }
    ],
    "sg:phone":"+1 705 781 1003",
    "sg:postcode":"P0S 1J0",
    "sg:province":"ON",
    "sg:tags":[
        "tourist",
        "accommodation"
    ],
    "wof:name":"Wabos Trails End",
    "wof:placetype":"venue"
},
  "geometry": {"coordinates":[-84.05117,46.778107],"type":"Point"}
}