{
  "type": "Feature",
  "properties": {
    "addr:full":"693 Hamilton Rd London ON N5Z 1T5",
    "addr:housenumber":"693",
    "addr:postcode":"n5z 1t5",
    "addr:street":"Hamilton Rd",
    "iso:country":"CA",
    "sg:address":"693 Hamilton Rd",
    "sg:city":"London",
    "sg:classifiers":[
        {
            "category":"Shopping",
            "subcategory":"Discount & Variety Stores",
            "type":"Retail Goods"
        }
    ],
    "sg:phone":"+1 519 659 9202",
    "sg:postcode":"N5Z 1T5",
    "sg:province":"ON",
    "wof:name":"Mr Convenience Store",
    "wof:placetype":"venue"
},
  "geometry": {"coordinates":[-81.2068862915,42.9793548584],"type":"Point"}
}