{
  "type": "Feature",
  "properties": {
    "iso:country":"CA",
    "sg:address":"18140 107 Ave NW",
    "sg:city":"Edmonton",
    "sg:classifiers":[
        {
            "category":"Building & Trades",
            "subcategory":"Construction",
            "type":"Services"
        }
    ],
    "sg:phone":"+1 780 486 3666",
    "sg:postcode":"T5S 1K5",
    "sg:province":"AB",
    "sg:tags":[
        "home",
        "builder"
    ],
    "wof:name":"Reid-Built Homes",
    "wof:placetype":"venue"
},
  "geometry": {"coordinates":[-113.634475708,53.5534858704],"type":"Point"}
}