{
  "type": "Feature",
  "properties": {
    "addr:full":"430 Rue Mercier Mont-Laurier QC J9L 2W1",
    "addr:housenumber":"430",
    "addr:postcode":"j9l 2w1",
    "addr:street":"Rue Mercier",
    "iso:country":"CA",
    "sg:address":"430 Rue Mercier",
    "sg:city":"Mont-Laurier",
    "sg:classifiers":[
        {
            "category":"Personal",
            "subcategory":"Beauty Salon",
            "type":"Services"
        }
    ],
    "sg:phone":"+1 819 623 6252",
    "sg:postcode":"J9L 2W1",
    "sg:province":"QC",
    "sg:tags":[
        "manicuring"
    ],
    "wof:name":"Authentik Beaute",
    "wof:placetype":"venue"
},
  "geometry": {"coordinates":[-75.49639892579999,46.5519180298],"type":"Point"}
}