{
  "type": "Feature",
  "properties": {
    "addr:full":"40 Cassidy Rd Nepean ON K2H 6K1",
    "addr:housenumber":"40",
    "addr:postcode":"k2h 6k1",
    "addr:street":"Cassidy Rd",
    "iso:country":"CA",
    "sg:address":"40 Cassidy Rd",
    "sg:city":"Nepean",
    "sg:classifiers":[
        {
            "category":"Education",
            "subcategory":"School",
            "type":"Public Place"
        }
    ],
    "sg:phone":"+1 613 828 9101",
    "sg:postcode":"K2H 6K1",
    "sg:province":"ON",
    "wof:name":"Bell High School",
    "wof:placetype":"venue"
},
  "geometry": {"coordinates":[-75.80835,45.32692],"type":"Point"}
}