{
  "type": "Feature",
  "properties": {
    "addr:full":"337 Notre Dame St Belle River ON N0R 1A0",
    "addr:housenumber":"337",
    "addr:postcode":"n0r 1a0",
    "addr:street":"Notre Dame St",
    "iso:country":"CA",
    "sg:address":"337 Notre Dame St",
    "sg:city":"Belle River",
    "sg:classifiers":[
        {
            "category":"Food & Beverages",
            "subcategory":"Liquor & Beverages",
            "type":"Retail Goods"
        }
    ],
    "sg:phone":"+1 519 728 1550",
    "sg:postcode":"N0R 1A0",
    "sg:province":"ON",
    "sg:tags":[
        "store"
    ],
    "wof:name":"Liquor Control Board of Ont",
    "wof:placetype":"venue"
},
  "geometry": {"coordinates":[-82.69903600000001,42.292957],"type":"Point"}
}