{
  "type": "Feature",
  "properties": {
    "iso:country":"CA",
    "sg:address":"112 Calcite Rd",
    "sg:city":"Whitehorse",
    "sg:classifiers":[
        {
            "category":"Retail",
            "subcategory":"Auto Repair",
            "type":"Services"
        }
    ],
    "sg:phone":"+1 867 633 5659",
    "sg:postcode":"Y1A 2Z4",
    "sg:province":"YT",
    "sg:tags":[
        "repairing",
        "automobile"
    ],
    "wof:name":"Horsman Mechanical Ltd",
    "wof:placetype":"venue"
},
  "geometry": {"coordinates":[-135.07460022000001,60.7395515442],"type":"Point"}
}