{
  "type": "Feature",
  "properties": {
    "addr:full":"Weedon QC J0B 3J0",
    "addr:postcode":"j0b 3j0",
    "iso:country":"CA",
    "sg:city":"Weedon",
    "sg:classifiers":[
        {
            "category":"Manufacturing",
            "subcategory":"Motor Vehicles & Parts",
            "type":"Manufacturing & Wholesale Goods"
        }
    ],
    "sg:phone":"+1 819 877 2433",
    "sg:postcode":"J0B 3J0",
    "sg:province":"QC",
    "sg:tags":[
        "equipment",
        "truck"
    ],
    "wof:name":"Denis J-N Garage",
    "wof:placetype":"venue"
},
  "geometry": {"coordinates":[-71.4689483643,45.6992607117],"type":"Point"}
}