{
  "type": "Feature",
  "properties": {
    "addr:full":"62 Sheppard Ave W North York ON M2N 1M2",
    "addr:housenumber":"62",
    "addr:postcode":"m2n 1m2",
    "addr:street":"Sheppard Ave W",
    "iso:country":"CA",
    "sg:address":"62 Sheppard Ave W",
    "sg:city":"North York",
    "sg:classifiers":[
        {
            "category":"Professional",
            "subcategory":"Employment Agencies",
            "type":"Services"
        }
    ],
    "sg:phone":"+1 416 590 0008",
    "sg:postcode":"M2N 1M2",
    "sg:province":"ON",
    "sg:tags":[
        "opportunity"
    ],
    "wof:name":"Aspira Group",
    "wof:placetype":"venue"
},
  "geometry": {"coordinates":[-79.414314,43.760933],"type":"Point"}
}