{
  "type": "Feature",
  "properties": {
    "addr:full":"4553 Lakelse Ave Terrace BC V8G 1P7",
    "addr:housenumber":"4553",
    "addr:postcode":"v8g 1p7",
    "addr:street":"Lakelse Ave",
    "iso:country":"CA",
    "sg:address":"4553 Lakelse Ave",
    "sg:city":"Terrace",
    "sg:classifiers":[
        {
            "category":"Travel",
            "subcategory":"Travel Agent",
            "type":"Entertainment"
        }
    ],
    "sg:phone":"+1 250 635 2281",
    "sg:postcode":"V8G 1P7",
    "sg:province":"BC",
    "sg:tags":[
        "agency",
        "bureau"
    ],
    "wof:name":"Elan Travel",
    "wof:placetype":"venue"
},
  "geometry": {"coordinates":[-128.58457899999999,54.516247],"type":"Point"}
}