{
  "type": "Feature",
  "properties": {
    "iso:country":"CA",
    "sg:city":"Richmond",
    "sg:classifiers":[
        {
            "category":"Retail",
            "subcategory":"Auto Repair",
            "type":"Services"
        }
    ],
    "sg:phone":"+1 604 279 0123",
    "sg:postcode":"V6V 2R5",
    "sg:province":"BC",
    "sg:tags":[
        "repairing",
        "automobile"
    ],
    "wof:name":"Wan Chin",
    "wof:placetype":"venue"
},
  "geometry": {"coordinates":[-123.079063,49.193817],"type":"Point"}
}