{
  "type": "Feature",
  "properties": {
    "addr:full":"774 Somerset St W Ottawa ON K1R 6R2",
    "addr:housenumber":"774",
    "addr:postcode":"k1r 6r2",
    "addr:street":"Somerset St W",
    "iso:country":"CA",
    "sg:address":"774 Somerset St W",
    "sg:city":"Ottawa",
    "sg:classifiers":[
        {
            "category":"Restaurant",
            "type":"Food & Drink"
        }
    ],
    "sg:phone":"+1 613 237 8827",
    "sg:postcode":"K1R 6R2",
    "sg:province":"ON",
    "wof:name":"Royal Treasure Restaurant",
    "wof:placetype":"venue"
},
  "geometry": {"coordinates":[-75.709557,45.409897],"type":"Point"}
}