{
  "type": "Feature",
  "properties": {
    "addr:full":"4016 Central Ave Laird SK S0K 2H0",
    "addr:housenumber":"4016",
    "addr:postcode":"s0k 2h0",
    "addr:street":"Central Ave",
    "iso:country":"CA",
    "sg:address":"4016 Central Ave",
    "sg:city":"Laird",
    "sg:classifiers":[
        {
            "category":"Retail",
            "subcategory":"Auto Repair",
            "type":"Services"
        }
    ],
    "sg:phone":"+1 306 223 4223",
    "sg:postcode":"S0K 2H0",
    "sg:province":"SK",
    "sg:tags":[
        "repairing",
        "automobile"
    ],
    "wof:name":"Bev Hinz Automotive",
    "wof:placetype":"venue"
},
  "geometry": {"coordinates":[-106.590118,52.711208],"type":"Point"}
}