{
  "type": "Feature",
  "properties": {
    "addr:full":"28 Maclean Cres E Sedgewick AB T0B 4C0",
    "addr:housenumber":"28",
    "addr:postcode":"t0b 4c0",
    "addr:street":"Maclean Cres E",
    "iso:country":"CA",
    "sg:address":"28 Maclean Cres E",
    "sg:city":"Sedgewick",
    "sg:classifiers":[
        {
            "category":"Retail",
            "subcategory":"Laundry & Dry Cleaning",
            "type":"Services"
        }
    ],
    "sg:phone":"+1 780 384 3087",
    "sg:postcode":"T0B 4C0",
    "sg:province":"AB",
    "sg:tags":[
        "cleaners",
        "rug",
        "carpet"
    ],
    "wof:name":"Fancy Shine Auto & Carpet Care",
    "wof:placetype":"venue"
},
  "geometry": {"coordinates":[-111.69240600000001,52.779438],"type":"Point"}
}