{
  "type": "Feature",
  "properties": {
    "addr:full":"2804 Ch Des Quatre-Bourgeois Sainte-Foy QC G1V 1X7",
    "addr:postcode":"2804;g1v 1x7",
    "addr:street":"Ch Des Quatre-Bourgeois",
    "iso:country":"CA",
    "sg:address":"2804 Ch Des Quatre-Bourgeois",
    "sg:city":"Sainte-Foy",
    "sg:classifiers":[
        {
            "category":"Personal",
            "subcategory":"Beauty Salon",
            "type":"Services"
        }
    ],
    "sg:phone":"+1 418 651 1060",
    "sg:postcode":"G1V 1X7",
    "sg:province":"QC",
    "wof:name":"Salon DE Coiffure Christiane",
    "wof:placetype":"venue"
},
  "geometry": {"coordinates":[-71.297768,46.775673],"type":"Point"}
}