{
  "type": "Feature",
  "properties": {
    "iso:country":"CA",
    "sg:address":"44 Great Northern Rd",
    "sg:city":"Sault Ste Marie",
    "sg:classifiers":[
        {
            "category":"Shopping",
            "subcategory":"Music",
            "type":"Retail Goods"
        }
    ],
    "sg:phone":"+1 705 759 0218",
    "sg:postcode":"P6B 4Y5",
    "sg:province":"ON",
    "sg:tags":[
        "compact",
        "record",
        "disc",
        "tape"
    ],
    "wof:name":"C D Plus Partnership",
    "wof:placetype":"venue"
},
  "geometry": {"coordinates":[-84.31927490229999,46.5247497559],"type":"Point"}
}