{
  "type": "Feature",
  "properties": {
    "addr:full":"Surrey BC V4N 4E6",
    "addr:postcode":"v4n 4e6",
    "iso:country":"CA",
    "sg:city":"Surrey",
    "sg:classifiers":[
        {
            "category":"Building & Trades",
            "subcategory":"Construction",
            "type":"Services"
        }
    ],
    "sg:phone":"+1 604 882 1031",
    "sg:postcode":"V4N 4E6",
    "sg:province":"BC",
    "sg:tags":[
        "general",
        "contractor"
    ],
    "wof:name":"Tritech Industries Ltd",
    "wof:placetype":"venue"
},
  "geometry": {"coordinates":[-122.688064575,49.1737747192],"type":"Point"}
}