{
  "type": "Feature",
  "properties": {
    "iso:country":"CA",
    "sg:city":"Red Deer",
    "sg:classifiers":[
        {
            "category":"Insurance",
            "subcategory":"Insurance Agent",
            "type":"Services"
        }
    ],
    "sg:phone":"+1 403 347 9457",
    "sg:postcode":"T4N 6H8",
    "sg:province":"AB",
    "wof:name":"Andrusiak Financial Svc",
    "wof:placetype":"venue"
},
  "geometry": {"coordinates":[-113.815856934,52.2663574219],"type":"Point"}
}