{
  "type": "Feature",
  "properties": {
    "iso:country":"CA",
    "sg:city":"Fort Saskatchewan",
    "sg:classifiers":[
        {
            "category":"Building & Trades",
            "subcategory":"Construction",
            "type":"Services"
        }
    ],
    "sg:phone":"+1 780 992 0028",
    "sg:postcode":"T8L 3T8",
    "sg:province":"AB",
    "sg:tags":[
        "general",
        "contractor"
    ],
    "wof:name":"Gunther Construction Ltd",
    "wof:placetype":"venue"
},
  "geometry": {"coordinates":[-113.18427276600001,53.7028694153],"type":"Point"}
}