{
  "type": "Feature",
  "properties": {
    "addr:full":"3689 184 St Surrey BC V3S 0L5",
    "addr:housenumber":"3689",
    "addr:postcode":"v3s 0l5",
    "addr:street":"184 St",
    "iso:country":"CA",
    "sg:address":"3689 184 St",
    "sg:city":"Surrey",
    "sg:classifiers":[
        {
            "category":"Wholesale",
            "subcategory":"Fruits & Vegetables",
            "type":"Manufacturing & Wholesale Goods"
        }
    ],
    "sg:phone":"+1 604 576 2345",
    "sg:postcode":"V3S 0L5",
    "sg:province":"BC",
    "wof:name":"International Herbs Ltd",
    "wof:placetype":"venue"
},
  "geometry": {"coordinates":[-122.7135849,49.0686912537],"type":"Point"}
}