{
  "type": "Feature",
  "properties": {
    "addr:full":"2359 Royal Windsor Dr #13 Mississauga ON L5J 4S9",
    "addr:housenumber":"2359",
    "addr:postcode":"l5j 4s9",
    "addr:street":"Royal Windsor Dr # 13",
    "iso:country":"CA",
    "sg:address":"2359 Royal Windsor Dr #13",
    "sg:city":"Mississauga",
    "sg:classifiers":[
        {
            "category":"Freight",
            "type":"Transportation"
        }
    ],
    "sg:phone":"+1 905 855 1334",
    "sg:postcode":"L5J 4S9",
    "sg:province":"ON",
    "sg:tags":[
        "broker",
        "customs"
    ],
    "wof:name":"Traders Customs Brokerage",
    "wof:placetype":"venue"
},
  "geometry": {"coordinates":[-79.6380691528,43.5037193298],"type":"Point"}
}