{
  "type": "Feature",
  "properties": {
    "addr:full":"965 Dundas St W #201A Whitby ON L1P 1G8",
    "addr:housenumber":"965",
    "addr:postcode":"l1p 1g8",
    "addr:street":"Dundas St W # 201A",
    "iso:country":"CA",
    "sg:address":"965 Dundas St W #201A",
    "sg:city":"Whitby",
    "sg:classifiers":[
        {
            "category":"Social Services",
            "type":"Services"
        }
    ],
    "sg:phone":"+1 905 666 2622",
    "sg:postcode":"L1P 1G8",
    "sg:province":"ON",
    "sg:tags":[
        "counselor",
        "marriage",
        "family"
    ],
    "wof:name":"Trek Counselling Svc",
    "wof:placetype":"venue"
},
  "geometry": {"coordinates":[-78.96235656739999,43.8751831055],"type":"Point"}
}