{
  "type": "Feature",
  "properties": {
    "addr:full":"152 Kendall St Point Edward ON N7V 4G5",
    "addr:housenumber":"152",
    "addr:postcode":"n7v 4g5",
    "addr:street":"Kendall St",
    "iso:country":"CA",
    "sg:address":"152 Kendall St",
    "sg:city":"Point Edward",
    "sg:classifiers":[
        {
            "category":"Wholesale",
            "subcategory":"Furniture",
            "type":"Manufacturing & Wholesale Goods"
        }
    ],
    "sg:phone":"+1 519 336 4940",
    "sg:postcode":"N7V 4G5",
    "sg:province":"ON",
    "wof:name":"Manley's Stationery & Office",
    "wof:placetype":"venue"
},
  "geometry": {"coordinates":[-82.401985,42.994541],"type":"Point"}
}