{
  "type": "Feature",
  "properties": {
    "addr:full":"6 Quay Crt Hamilton ON L8W 1R2",
    "addr:housenumber":"6",
    "addr:postcode":"l8w 1r2",
    "addr:street":"Quay Crt",
    "iso:country":"CA",
    "sg:address":"6 Quay Crt",
    "sg:city":"Hamilton",
    "sg:classifiers":[
        {
            "category":"Building & Trades",
            "subcategory":"Construction",
            "type":"Services"
        }
    ],
    "sg:phone":"+1 905 548 0418",
    "sg:postcode":"L8W 1R2",
    "sg:province":"ON",
    "sg:tags":[
        "waterproofing",
        "contractor"
    ],
    "wof:name":"G & S Renovations",
    "wof:placetype":"venue"
},
  "geometry": {"coordinates":[-79.842361,43.202133],"type":"Point"}
}