{
  "type": "Feature",
  "properties": {
    "iso:country":"CA",
    "sg:address":"5255 Richmond Rd SW # 290",
    "sg:city":"Calgary",
    "sg:classifiers":[
        {
            "category":"Health Services",
            "subcategory":"Doctor",
            "type":"Services"
        }
    ],
    "sg:phone":"+1 403 246 2131",
    "sg:postcode":"T3E 7C4",
    "sg:province":"AB",
    "sg:tags":[
        "dentist"
    ],
    "wof:name":"Hennessy, James J DDS",
    "wof:placetype":"venue"
},
  "geometry": {"coordinates":[-114.162216187,51.0176429749],"type":"Point"}
}