{
  "type": "Feature",
  "properties": {
    "addr:full":"Brantford ON N3S 7S6",
    "addr:postcode":"n3s 7s6",
    "iso:country":"CA",
    "sg:city":"Brantford",
    "sg:classifiers":[
        {
            "category":"Real Estate",
            "subcategory":"Real Estate Operator",
            "type":"Services"
        }
    ],
    "sg:phone":"+1 519 751 0869",
    "sg:postcode":"N3S 7S6",
    "sg:province":"ON",
    "sg:tags":[
        "condominium"
    ],
    "wof:name":"Greystone Heights",
    "wof:placetype":"venue"
},
  "geometry": {"coordinates":[-80.23075900000001,43.147934],"type":"Point"}
}