{
  "type": "Feature",
  "properties": {
    "addr:full":"Mundare AB T0B 3H0",
    "addr:postcode":"t0b 3h0",
    "iso:country":"CA",
    "sg:city":"Mundare",
    "sg:classifiers":[
        {
            "category":"Wholesale",
            "subcategory":"Farm Supplies",
            "type":"Manufacturing & Wholesale Goods"
        }
    ],
    "sg:phone":"+1 780 764 8810",
    "sg:postcode":"T0B 3H0",
    "sg:province":"AB",
    "sg:tags":[
        "chemical",
        "agricultural",
        "greenhouse"
    ],
    "wof:name":"Agricore United",
    "wof:placetype":"venue"
},
  "geometry": {"coordinates":[-112.34474899999999,53.593143],"type":"Point"}
}