{
  "type": "Feature",
  "properties": {
    "addr:full":"1229 Cemetary Rd Queen Charlotte BC V0T 1S0",
    "addr:housenumber":"1229",
    "addr:postcode":"v0t 1s0",
    "addr:street":"Cemetary Rd",
    "iso:country":"CA",
    "sg:address":"1229 Cemetary Rd",
    "sg:city":"Queen Charlotte",
    "sg:classifiers":[
        {
            "category":"Government",
            "subcategory":"Office",
            "type":"Public Place"
        }
    ],
    "sg:phone":"+1 250 559 6200",
    "sg:postcode":"V0T 1S0",
    "sg:province":"BC",
    "wof:name":"BC Forests",
    "wof:placetype":"venue"
},
  "geometry": {"coordinates":[-132.114700317,53.2524757385],"type":"Point"}
}