{
  "type": "Feature",
  "properties": {
    "iso:country":"CA",
    "sg:address":"1100 Boul Maloney O",
    "sg:city":"Gatineau",
    "sg:classifiers":[
        {
            "category":"Food & Beverages",
            "subcategory":"Bakery",
            "type":"Retail Goods"
        }
    ],
    "sg:phone":"+1 819 561 6182",
    "sg:postcode":"J8T 6G3",
    "sg:province":"QC",
    "sg:tags":[
        "baker"
    ],
    "wof:name":"Mmmuffins",
    "wof:placetype":"venue"
},
  "geometry": {"coordinates":[-75.5879745483,45.492099762],"type":"Point"}
}