{
  "type": "Feature",
  "properties": {
    "addr:full":"3150 Boul DE Tracy Sorel-Tracy QC J3R 5M7",
    "addr:housenumber":"3150",
    "addr:postcode":"j3r 5m7",
    "addr:street":"Boul De Tracy",
    "iso:country":"CA",
    "sg:address":"3150 Boul DE Tracy",
    "sg:city":"Sorel-Tracy",
    "sg:classifiers":[
        {
            "category":"Retail",
            "subcategory":"Laundry & Dry Cleaning",
            "type":"Services"
        }
    ],
    "sg:phone":"+1 450 780 0862",
    "sg:postcode":"J3R 5M7",
    "sg:province":"QC",
    "sg:tags":[
        "cleaners"
    ],
    "wof:name":"Nettoyeur Michel Forget",
    "wof:placetype":"venue"
},
  "geometry": {"coordinates":[-73.156914,46.015369],"type":"Point"}
}