{
  "type": "Feature",
  "properties": {
    "iso:country":"CA",
    "sg:address":"601 6 Ave S",
    "sg:city":"Lethbridge",
    "sg:classifiers":[
        {
            "category":"Health Services",
            "subcategory":"Doctor",
            "type":"Services"
        }
    ],
    "sg:phone":"+1 403 328 6641",
    "sg:postcode":"T1J 0Z2",
    "sg:province":"AB",
    "sg:tags":[
        "physician",
        "surgeon"
    ],
    "wof:name":"Haig, Charlotte MD",
    "wof:placetype":"venue"
},
  "geometry": {"coordinates":[-112.836486816,49.6911964417],"type":"Point"}
}