{
  "type": "Feature",
  "properties": {
    "addr:full":"2108 Boul DE Tadoussac Chicoutimi QC G7G 1L1",
    "addr:housenumber":"2108",
    "addr:postcode":"g7g 1l1",
    "addr:street":"Boul De Tadoussac",
    "iso:country":"CA",
    "sg:address":"2108 Boul DE Tadoussac",
    "sg:city":"Chicoutimi",
    "sg:classifiers":[
        {
            "category":"Shopping",
            "subcategory":"Florist",
            "type":"Retail Goods"
        }
    ],
    "sg:phone":"+1 418 543 6980",
    "sg:postcode":"G7G 1L1",
    "sg:province":"QC",
    "wof:name":"Chicoutimi-Nord Fleuriste",
    "wof:placetype":"venue"
},
  "geometry": {"coordinates":[-71.061668,48.438534],"type":"Point"}
}