{
  "type": "Feature",
  "properties": {
    "iso:country":"CA",
    "sg:address":"100 Rue DE Vaudreuil",
    "sg:city":"Boucherville",
    "sg:classifiers":[
        {
            "category":"Wholesale",
            "subcategory":"Construction Materials",
            "type":"Manufacturing & Wholesale Goods"
        }
    ],
    "sg:phone":"+1 514 527 4581",
    "sg:postcode":"J4B 5G4",
    "sg:province":"QC",
    "sg:tags":[
        "building",
        "plywood",
        "veneer"
    ],
    "wof:name":"Commonwealth Plywood Cie Ltee",
    "wof:placetype":"venue"
},
  "geometry": {"coordinates":[-73.462425,45.5825],"type":"Point"}
}