{
  "type": "Feature",
  "properties": {
    "addr:full":"PO Box 51 Pakwaw Lake SK S0E 1G0",
    "addr:housenumber":"po box 51",
    "addr:postcode":"s0e 1g0",
    "iso:country":"CA",
    "sg:address":"PO Box 51",
    "sg:city":"Pakwaw Lake",
    "sg:classifiers":[
        {
            "category":"Health Services",
            "subcategory":"Doctor",
            "type":"Services"
        }
    ],
    "sg:phone":"+1 306 768 3617",
    "sg:postcode":"S0E 1G0",
    "sg:province":"SK",
    "sg:tags":[
        "physician",
        "surgeon"
    ],
    "wof:name":"Nipawin Health Ctr",
    "wof:placetype":"venue"
},
  "geometry": {"coordinates":[-102.622840881,53.4818916321],"type":"Point"}
}