{
  "type": "Feature",
  "properties": {
    "iso:country":"CA",
    "sg:city":"Trenton",
    "sg:classifiers":[
        {
            "category":"Building & Trades",
            "subcategory":"Construction",
            "type":"Services"
        }
    ],
    "sg:phone":"+1 613 392 8193",
    "sg:postcode":"K8V 5P7",
    "sg:province":"ON",
    "sg:tags":[
        "excavating",
        "tank",
        "septic",
        "contractor"
    ],
    "wof:name":"Cooney Excavating",
    "wof:placetype":"venue"
},
  "geometry": {"coordinates":[-77.5763092041,44.1011390686],"type":"Point"}
}