{
  "type": "Feature",
  "properties": {
    "addr:full":"2880 Temple Dr Windsor ON N8W 5J5",
    "addr:housenumber":"2880",
    "addr:postcode":"n8w 5j5",
    "addr:street":"Temple Dr",
    "iso:country":"CA",
    "sg:address":"2880 Temple Dr",
    "sg:city":"Windsor",
    "sg:classifiers":[
        {
            "category":"Professional",
            "subcategory":"Engineering",
            "type":"Services"
        }
    ],
    "sg:phone":"+1 519 945 1900",
    "sg:postcode":"N8W 5J5",
    "sg:province":"ON",
    "sg:tags":[
        "engineer"
    ],
    "wof:name":"G W Wolf Design & Engineering",
    "wof:placetype":"venue"
},
  "geometry": {"coordinates":[-82.9756317139,42.2887191772],"type":"Point"}
}