{
  "type": "Feature",
  "properties": {
    "addr:full":"1726 Dolphin Ave Kelowna BC V1Y 9R9",
    "addr:housenumber":"1726",
    "addr:postcode":"v1y 9r9",
    "addr:street":"Dolphin Ave",
    "iso:country":"CA",
    "sg:address":"1726 Dolphin Ave",
    "sg:city":"Kelowna",
    "sg:classifiers":[
        {
            "category":"Government",
            "subcategory":"Office",
            "type":"Public Place"
        }
    ],
    "sg:phone":"+1 250 717 2000",
    "sg:postcode":"V1Y 9R9",
    "sg:province":"BC",
    "wof:name":"B C Residential Tenancy Branch",
    "wof:placetype":"venue"
},
  "geometry": {"coordinates":[-119.460144,49.879387],"type":"Point"}
}