{
  "type": "Feature",
  "properties": {
    "addr:full":"1451 Rue Marois Thetford Mines QC G6G 6G2",
    "addr:housenumber":"1451",
    "addr:postcode":"g6g 6g2",
    "addr:street":"Rue Marois",
    "iso:country":"CA",
    "sg:address":"1451 Rue Marois",
    "sg:city":"Thetford Mines",
    "sg:classifiers":[
        {
            "category":"Personal",
            "subcategory":"Beauty Salon",
            "type":"Services"
        }
    ],
    "sg:phone":"+1 418 338 5044",
    "sg:postcode":"G6G 6G2",
    "sg:province":"QC",
    "wof:name":"Salon Chez Marc Enr",
    "wof:placetype":"venue"
},
  "geometry": {"coordinates":[-71.325333,46.102768],"type":"Point"}
}