{
  "type": "Feature",
  "properties": {
    "addr:full":"41 Av Des Erables Clair NB E7A 2B6",
    "addr:postcode":"e7a 2b6",
    "addr:street":"41 Av Des Erables",
    "iso:country":"CA",
    "sg:address":"41 Av Des Erables",
    "sg:city":"Clair",
    "sg:classifiers":[
        {
            "category":"Freight",
            "type":"Transportation"
        }
    ],
    "sg:phone":"+1 506 992 1818",
    "sg:postcode":"E7A 2B6",
    "sg:province":"NB",
    "sg:tags":[
        "trucking"
    ],
    "wof:name":"Ronald Hebert Trucking",
    "wof:placetype":"venue"
},
  "geometry": {"coordinates":[-68.60744476319999,47.2558822632],"type":"Point"}
}