{
  "type": "Feature",
  "properties": {
    "addr:full":"125 Rue Champoux Disraeli QC G0N 1E0",
    "addr:housenumber":"125",
    "addr:postcode":"g0n 1e0",
    "addr:street":"Rue Champoux Disraeli",
    "iso:country":"CA",
    "sg:address":"125 Rue Champoux",
    "sg:city":"Disraeli",
    "sg:classifiers":[
        {
            "category":"Food & Beverages",
            "subcategory":"Groceries & Convenience Stores",
            "type":"Retail Goods"
        }
    ],
    "sg:phone":"+1 418 449 4218",
    "sg:postcode":"G0N 1E0",
    "sg:province":"QC",
    "sg:tags":[
        "grocer"
    ],
    "wof:name":"Marche B Gagnon Inc Iga",
    "wof:placetype":"venue"
},
  "geometry": {"coordinates":[-71.359131,45.904751],"type":"Point"}
}