{
  "type": "Feature",
  "properties": {
    "addr:full":"Guelph ON N1G 4V9",
    "addr:postcode":"n1g 4v9",
    "iso:country":"CA",
    "sg:city":"Guelph",
    "sg:classifiers":[
        {
            "category":"Restaurant",
            "type":"Food & Drink"
        }
    ],
    "sg:phone":"+1 519 821 4448",
    "sg:postcode":"N1G 4V9",
    "sg:province":"ON",
    "sg:tags":[
        "pizza"
    ],
    "wof:name":"Gino's Pizza",
    "wof:placetype":"venue"
},
  "geometry": {"coordinates":[-80.23606872560001,43.5180168152],"type":"Point"}
}