{
  "type": "Feature",
  "properties": {
    "iso:country":"CA",
    "sg:city":"Lethbridge",
    "sg:classifiers":[
        {
            "category":"Airport",
            "type":"Transportation"
        }
    ],
    "sg:phone":"+1 403 327 4582",
    "sg:postcode":"T1J 3Y7",
    "sg:province":"AB",
    "sg:tags":[
        "aircraft",
        "maintenance"
    ],
    "wof:name":"Q L Aviation Svc Ltd",
    "wof:placetype":"venue"
},
  "geometry": {"coordinates":[-112.833740234,49.6938362122],"type":"Point"}
}