{
  "type": "Feature",
  "properties": {
    "addr:full":"32 Toulinquet St Twillingate NL A0G 4M0",
    "addr:housenumber":"32",
    "addr:postcode":"a0g 4m0",
    "addr:street":"Toulinquet St Twillingate",
    "iso:country":"CA",
    "sg:address":"32 Toulinquet St",
    "sg:city":"Twillingate",
    "sg:classifiers":[
        {
            "category":"Retail",
            "subcategory":"Auto Repair",
            "type":"Services"
        }
    ],
    "sg:phone":"+1 709 884 2533",
    "sg:postcode":"A0G 4M0",
    "sg:province":"NL",
    "sg:tags":[
        "repairing",
        "automobile"
    ],
    "wof:name":"Highway Service Ctr & Ultramar",
    "wof:placetype":"venue"
},
  "geometry": {"coordinates":[-54.775974,49.656921],"type":"Point"}
}