{
  "type": "Feature",
  "properties": {
    "addr:full":"5501 Tudor Glen St Albert AB T8N 3V4",
    "addr:housenumber":"5501",
    "addr:postcode":"t8n 3v4",
    "addr:street":"Tudor Glen",
    "iso:country":"CA",
    "sg:address":"5501 Tudor Glen",
    "sg:city":"St Albert",
    "sg:classifiers":[
        {
            "category":"Shopping",
            "subcategory":"Bicycles & Sporting Goods",
            "type":"Retail Goods"
        }
    ],
    "sg:phone":"+1 780 459 8212",
    "sg:postcode":"T8N 3V4",
    "sg:province":"AB",
    "sg:tags":[
        "engine"
    ],
    "wof:name":"B J's Fix-It Shop",
    "wof:placetype":"venue"
},
  "geometry": {"coordinates":[-113.627349853,53.633518219],"type":"Point"}
}