{
  "type": "Feature",
  "properties": {
    "iso:country":"CA",
    "sg:address":"218 Rue Des Commandeurs",
    "sg:city":"Rimouski",
    "sg:classifiers":[
        {
            "category":"Farming",
            "subcategory":"Farm & Veterinary Services",
            "type":"Manufacturing & Wholesale Goods"
        }
    ],
    "sg:phone":"+1 418 725 4845",
    "sg:postcode":"G5L 8L6",
    "sg:province":"QC",
    "sg:tags":[
        "insemination"
    ],
    "wof:name":"Insemination Artificielle",
    "wof:placetype":"venue"
},
  "geometry": {"coordinates":[-68.5769500732,48.4331130981],"type":"Point"}
}