{
  "type": "Feature",
  "properties": {
    "iso:country":"CA",
    "sg:address":"113 Cushman Rd",
    "sg:city":"St Catharines",
    "sg:classifiers":[
        {
            "category":"Autos & Motor Vehicles",
            "subcategory":"Boat Sales",
            "type":"Retail Goods"
        }
    ],
    "sg:phone":"+1 905 688 2661",
    "sg:postcode":"L2M 6S9",
    "sg:province":"ON",
    "sg:tags":[
        "equipment",
        "marine",
        "supply"
    ],
    "wof:name":"Seagulf Marine Industries Inc",
    "wof:placetype":"venue"
},
  "geometry": {"coordinates":[-79.199814,43.172653],"type":"Point"}
}