{
  "type": "Feature",
  "properties": {
    "addr:full":"Winnipeg MB R3B 0V3",
    "addr:postcode":"r3b 0v3",
    "iso:country":"CA",
    "sg:city":"Winnipeg",
    "sg:classifiers":[
        {
            "category":"Shopping",
            "subcategory":"Clothing, Apparel, & Fashions",
            "type":"Retail Goods"
        }
    ],
    "sg:phone":"+1 204 943 1723",
    "sg:postcode":"R3B 0V3",
    "sg:province":"MB",
    "sg:tags":[
        "tailor"
    ],
    "wof:name":"Manuel's Tailor Shop",
    "wof:placetype":"venue"
},
  "geometry": {"coordinates":[-97.13671100000001,49.896217],"type":"Point"}
}