{
  "type": "Feature",
  "properties": {
    "addr:full":"2200 Rue Mansfield Montreal QC H3A 3R8",
    "addr:housenumber":"2200",
    "addr:postcode":"h3a 3r8",
    "addr:street":"Rue Mansfield",
    "iso:country":"CA",
    "sg:address":"2200 Rue Mansfield",
    "sg:city":"Montreal",
    "sg:classifiers":[
        {
            "category":"Professional",
            "subcategory":"Business Services",
            "type":"Services"
        }
    ],
    "sg:phone":"+1 514 844 2000",
    "sg:postcode":"H3A 3R8",
    "sg:province":"QC",
    "sg:tags":[
        "convention",
        "meeting",
        "facility"
    ],
    "wof:name":"Centre Mont-Royal",
    "wof:placetype":"venue"
},
  "geometry": {"coordinates":[-73.5748825073,45.5028533936],"type":"Point"}
}