{
  "type": "Feature",
  "properties": {
    "addr:full":"4611 Maryvale Dr NE Calgary AB T2A 2T2",
    "addr:housenumber":"4611",
    "addr:postcode":"t2a 2t2",
    "addr:street":"Maryvale Dr Ne",
    "iso:country":"CA",
    "sg:address":"4611 Maryvale Dr NE",
    "sg:city":"Calgary",
    "sg:classifiers":[
        {
            "category":"Wholesale",
            "subcategory":"Apparel",
            "type":"Manufacturing & Wholesale Goods"
        }
    ],
    "sg:phone":"+1 403 235 4566",
    "sg:postcode":"T2A 2T2",
    "sg:province":"AB",
    "wof:name":"Selective Agency",
    "wof:placetype":"venue"
},
  "geometry": {"coordinates":[-113.967735,51.056473],"type":"Point"}
}