{
  "type": "Feature",
  "properties": {
    "addr:full":"3975 Jane St North York ON M3N 2K1",
    "addr:housenumber":"3975",
    "addr:postcode":"m3n 2k1",
    "addr:street":"Jane St",
    "iso:country":"CA",
    "sg:address":"3975 Jane St",
    "sg:city":"North York",
    "sg:classifiers":[
        {
            "category":"Shopping",
            "subcategory":"Pharmacy",
            "type":"Retail Goods"
        }
    ],
    "sg:phone":"+1 416 630 2553",
    "sg:postcode":"M3N 2K1",
    "sg:province":"ON",
    "wof:name":"Shoppers Drug Mart",
    "wof:placetype":"venue"
},
  "geometry": {"coordinates":[-79.5174942017,43.7569961548],"type":"Point"}
}