{
  "type": "Feature",
  "properties": {
    "iso:country":"CA",
    "sg:address":"529 Riverside Dr",
    "sg:city":"Peterborough",
    "sg:classifiers":[
        {
            "category":"Education",
            "subcategory":"Special Training",
            "type":"Public Place"
        }
    ],
    "sg:phone":"+1 705 876 7431",
    "sg:postcode":"K9J 3Y9",
    "sg:province":"ON",
    "sg:tags":[
        "instruction",
        "driving"
    ],
    "wof:name":"Achieve Safe Driving",
    "wof:placetype":"venue"
},
  "geometry": {"coordinates":[-78.32238,44.276436],"type":"Point"}
}