{
  "type": "Feature",
  "properties": {
    "iso:country":"CA",
    "sg:address":"377 Front St",
    "sg:city":"Belleville",
    "sg:classifiers":[
        {
            "category":"Retail",
            "subcategory":"Portrait Studio",
            "type":"Services"
        }
    ],
    "sg:phone":"+1 613 967 3823",
    "sg:postcode":"K8N 2Z9",
    "sg:province":"ON",
    "sg:tags":[
        "photographer"
    ],
    "wof:name":"Robert W House Photography",
    "wof:placetype":"venue"
},
  "geometry": {"coordinates":[-77.385597,44.167435],"type":"Point"}
}