{
  "type": "Feature",
  "properties": {
    "iso:country":"CA",
    "sg:address":"2312 16 Ave NW",
    "sg:city":"Calgary",
    "sg:classifiers":[
        {
            "category":"Restaurant",
            "type":"Food & Drink"
        }
    ],
    "sg:phone":"+1 403 284 9696",
    "sg:postcode":"T2M 0M5",
    "sg:province":"AB",
    "wof:name":"Phil's Restaurants",
    "wof:placetype":"venue"
},
  "geometry": {"coordinates":[-114.11320499999999,51.067276],"type":"Point"}
}