{
  "type": "Feature",
  "properties": {
    "addr:full":"Concord ON L4K 4Z5",
    "addr:postcode":"l4k 4z5",
    "iso:country":"CA",
    "sg:city":"Concord",
    "sg:classifiers":[
        {
            "category":"Wholesale",
            "subcategory":"Hardware",
            "type":"Manufacturing & Wholesale Goods"
        }
    ],
    "sg:phone":"+1 905 760 1527",
    "sg:postcode":"L4K 4Z5",
    "sg:province":"ON",
    "sg:tags":[
        "equipment",
        "heating",
        "system"
    ],
    "wof:name":"Thermal Hydronics Supply",
    "wof:placetype":"venue"
},
  "geometry": {"coordinates":[-79.53426399999999,43.801094],"type":"Point"}
}