{
  "type": "Feature",
  "properties": {
    "addr:full":"Montreal QC H2P 2Z6",
    "addr:postcode":"h2p 2z6",
    "iso:country":"CA",
    "sg:city":"Montreal",
    "sg:classifiers":[
        {
            "category":"Professional",
            "subcategory":"Lawyer & Legal Services",
            "type":"Services"
        }
    ],
    "sg:phone":"+1 514 271 1336",
    "sg:postcode":"H2P 2Z6",
    "sg:province":"QC",
    "sg:tags":[
        "attorney"
    ],
    "wof:name":"Turbide, Diane",
    "wof:placetype":"venue"
},
  "geometry": {"coordinates":[-73.63529200000001,45.540318],"type":"Point"}
}