{
  "type": "Feature",
  "properties": {
    "addr:full":"285 Massey Rd Guelph ON N1K 1B2",
    "addr:housenumber":"285",
    "addr:postcode":"n1k 1b2",
    "addr:street":"Massey Rd",
    "iso:country":"CA",
    "sg:address":"285 Massey Rd",
    "sg:city":"Guelph",
    "sg:classifiers":[
        {
            "category":"Manufacturing",
            "subcategory":"Tools & Machinery",
            "type":"Manufacturing & Wholesale Goods"
        }
    ],
    "sg:phone":"+1 519 763 0704",
    "sg:postcode":"N1K 1B2",
    "sg:province":"ON",
    "sg:tags":[
        "machine",
        "shop"
    ],
    "wof:name":"Spinic Manufacturing CO Ltd",
    "wof:placetype":"venue"
},
  "geometry": {"coordinates":[-80.304474,43.539032],"type":"Point"}
}