{
  "type": "Feature",
  "properties": {
    "addr:full":"2239 Granville St Vancouver BC V6H 3G1",
    "addr:housenumber":"2239",
    "addr:postcode":"v6h 3g1",
    "addr:street":"Granville St",
    "iso:country":"CA",
    "sg:address":"2239 Granville St",
    "sg:city":"Vancouver",
    "sg:classifiers":[
        {
            "category":"Personal",
            "subcategory":"Beauty Salon",
            "type":"Services"
        }
    ],
    "sg:phone":"+1 604 731 2411",
    "sg:postcode":"V6H 3G1",
    "sg:province":"BC",
    "sg:tags":[
        "barber"
    ],
    "wof:name":"Epoch Hair Design For Men Ltd",
    "wof:placetype":"venue"
},
  "geometry": {"coordinates":[-123.138702393,49.2658920288],"type":"Point"}
}