{
  "type": "Feature",
  "properties": {
    "addr:full":"Sherwood Park AB T8A 4N6",
    "addr:postcode":"t8a 4n6",
    "iso:country":"CA",
    "sg:city":"Sherwood Park",
    "sg:classifiers":[
        {
            "category":"Health Services",
            "subcategory":"Doctor",
            "type":"Services"
        }
    ],
    "sg:phone":"+1 780 467 8886",
    "sg:postcode":"T8A 4N6",
    "sg:province":"AB",
    "sg:tags":[
        "physician",
        "surgeon"
    ],
    "wof:name":"Gee, Edward MD",
    "wof:placetype":"venue"
},
  "geometry": {"coordinates":[-113.33575399999999,53.512943],"type":"Point"}
}