{
  "type": "Feature",
  "properties": {
    "addr:full":"1219 Ford St Thunder Bay ON P7E 2B7",
    "addr:housenumber":"1219",
    "addr:postcode":"p7e 2b7",
    "addr:street":"Ford St",
    "iso:country":"CA",
    "sg:address":"1219 Ford St",
    "sg:city":"Thunder Bay",
    "sg:classifiers":[
        {
            "category":"Organizations",
            "subcategory":"Religious Organization",
            "type":"Services"
        }
    ],
    "sg:phone":"+1 807 623 0021",
    "sg:postcode":"P7E 2B7",
    "sg:province":"ON",
    "sg:tags":[
        "church"
    ],
    "wof:name":"Westfort Baptist Church",
    "wof:placetype":"venue"
},
  "geometry": {"coordinates":[-89.2729873657,48.3680953979],"type":"Point"}
}