{
  "type": "Feature",
  "properties": {
    "addr:full":"1025 9 Ave SE Calgary AB T2G 0S8",
    "addr:housenumber":"1025",
    "addr:postcode":"t2g 0s8",
    "addr:street":"9 Ave Se",
    "iso:country":"CA",
    "sg:address":"1025 9 Ave SE",
    "sg:city":"Calgary",
    "sg:classifiers":[
        {
            "category":"Home & Garden",
            "subcategory":"Household Appliances",
            "type":"Retail Goods"
        }
    ],
    "sg:phone":"+1 403 269 3600",
    "sg:postcode":"T2G 0S8",
    "sg:province":"AB",
    "wof:name":"Calgary Home Appliance Ctr",
    "wof:placetype":"venue"
},
  "geometry": {"coordinates":[-114.037674,51.042355],"type":"Point"}
}