{
  "type": "Feature",
  "properties": {
    "addr:full":"507 Mount Pleasant Rd Toronto ON M4S 2L9",
    "addr:housenumber":"507",
    "addr:postcode":"m4s 2l9",
    "addr:street":"Mount Pleasant Rd",
    "iso:country":"CA",
    "sg:address":"507 Mount Pleasant Rd",
    "sg:city":"Toronto",
    "sg:classifiers":[
        {
            "category":"Restaurant",
            "type":"Food & Drink"
        }
    ],
    "sg:phone":"+1 416 488 0036",
    "sg:postcode":"M4S 2L9",
    "sg:province":"ON",
    "wof:name":"Bread & Butter",
    "wof:placetype":"venue"
},
  "geometry": {"coordinates":[-79.38725280760001,43.7015266418],"type":"Point"}
}