{
  "type": "Feature",
  "properties": {
    "addr:full":"683 Ouellette Ave Windsor ON N9A 4J4",
    "addr:housenumber":"683",
    "addr:postcode":"n9a 4j4",
    "addr:street":"Ouellette Ave",
    "iso:country":"CA",
    "sg:address":"683 Ouellette Ave",
    "sg:city":"Windsor",
    "sg:classifiers":[
        {
            "category":"Restaurant",
            "type":"Food & Drink"
        }
    ],
    "sg:phone":"+1 519 254 1300",
    "sg:postcode":"N9A 4J4",
    "sg:province":"ON",
    "wof:name":"Pasta Shop the Restaurant",
    "wof:placetype":"venue"
},
  "geometry": {"coordinates":[-83.0364,42.313084],"type":"Point"}
}