{
  "type": "Feature",
  "properties": {
    "addr:full":"Rocky Mountain House AB T4T 1A3",
    "addr:postcode":"t4t 1a3",
    "iso:country":"CA",
    "sg:city":"Rocky Mountain House",
    "sg:classifiers":[
        {
            "category":"Health Services",
            "subcategory":"Clinic",
            "type":"Services"
        }
    ],
    "sg:phone":"+1 403 845 3030",
    "sg:postcode":"T4T 1A3",
    "sg:province":"AB",
    "wof:name":"Rocky Community Health Ctr",
    "wof:placetype":"venue"
},
  "geometry": {"coordinates":[-114.91954,52.373386],"type":"Point"}
}