{
  "type": "Feature",
  "properties": {
    "addr:full":"5035 51st Ave Eckville AB T0M 0X0",
    "addr:housenumber":"5035",
    "addr:postcode":"t0m 0x0",
    "addr:street":"51St Ave",
    "iso:country":"CA",
    "sg:address":"5035 51st Ave",
    "sg:city":"Eckville",
    "sg:classifiers":[
        {
            "category":"Health Services",
            "subcategory":"Doctor",
            "type":"Services"
        }
    ],
    "sg:phone":"+1 403 746 2002",
    "sg:postcode":"T0M 0X0",
    "sg:province":"AB",
    "sg:tags":[
        "physician",
        "surgeon"
    ],
    "wof:name":"Eckville Medical Clinic",
    "wof:placetype":"venue"
},
  "geometry": {"coordinates":[-114.36882799999999,52.359959],"type":"Point"}
}