{
  "type": "Feature",
  "properties": {
    "addr:full":"Toronto ON M4S 1Z8",
    "addr:postcode":"m4s 1z8",
    "iso:country":"CA",
    "sg:city":"Toronto",
    "sg:classifiers":[
        {
            "category":"Personal",
            "subcategory":"Beauty Salon",
            "type":"Services"
        }
    ],
    "sg:phone":"+1 416 488 0311",
    "sg:postcode":"M4S 1Z8",
    "sg:province":"ON",
    "sg:tags":[
        "hair",
        "replacement"
    ],
    "wof:name":"Mr Jimmy's Hair Grooming Ltd",
    "wof:placetype":"venue"
},
  "geometry": {"coordinates":[-79.396973,43.700977],"type":"Point"}
}