{
  "type": "Feature",
  "properties": {
    "addr:full":"14611 131 Ave NW Edmonton AB T5L 4L8",
    "addr:housenumber":"14611",
    "addr:postcode":"t5l 4l8",
    "addr:street":"131 Ave Nw",
    "iso:country":"CA",
    "sg:address":"14611 131 Ave NW",
    "sg:city":"Edmonton",
    "sg:classifiers":[
        {
            "category":"Building & Trades",
            "subcategory":"Construction",
            "type":"Services"
        }
    ],
    "sg:phone":"+1 780 452 6464",
    "sg:postcode":"T5L 4L8",
    "sg:province":"AB",
    "sg:tags":[
        "resurfacing",
        "material",
        "laying",
        "refinishing",
        "floor"
    ],
    "wof:name":"Cfi Custom Floors Inc",
    "wof:placetype":"venue"
},
  "geometry": {"coordinates":[-113.572166,53.590263],"type":"Point"}
}