{
  "type": "Feature",
  "properties": {
    "addr:full":"383 Dawes Rd East York ON M4B 2E3",
    "addr:housenumber":"383",
    "addr:postcode":"m4b 2e3",
    "addr:street":"Dawes Rd",
    "iso:country":"CA",
    "sg:address":"383 Dawes Rd",
    "sg:city":"East York",
    "sg:classifiers":[
        {
            "category":"Organizations",
            "subcategory":"Religious Organization",
            "type":"Services"
        }
    ],
    "sg:phone":"+1 416 757 2633",
    "sg:postcode":"M4B 2E3",
    "sg:province":"ON",
    "sg:tags":[
        "church"
    ],
    "wof:name":"Dawes Road Gospel Church",
    "wof:placetype":"venue"
},
  "geometry": {"coordinates":[-79.296852,43.70126],"type":"Point"}
}