{
  "type": "Feature",
  "properties": {
    "addr:full":"532 1/2 Concession St Hamilton ON L8V 1A6",
    "addr:housenumber":"532 1 / 2",
    "addr:postcode":"l8v 1a6",
    "addr:street":"Concession St",
    "iso:country":"CA",
    "sg:address":"532 1/2 Concession St",
    "sg:city":"Hamilton",
    "sg:classifiers":[
        {
            "category":"Professional",
            "subcategory":"Management & Consulting",
            "type":"Services"
        }
    ],
    "sg:phone":"+1 905 574 4190",
    "sg:postcode":"L8V 1A6",
    "sg:province":"ON",
    "sg:tags":[
        "party",
        "planning",
        "clown"
    ],
    "wof:name":"Giggle's the Female Clown",
    "wof:placetype":"venue"
},
  "geometry": {"coordinates":[-79.85353851319999,43.2412033081],"type":"Point"}
}