{
  "type": "Feature",
  "properties": {
    "addr:full":"308 Highway 214 Elmsdale NS B2S 2K9",
    "addr:housenumber":"308",
    "addr:postcode":"b2s 2k9",
    "addr:street":"Highway 214",
    "iso:country":"CA",
    "sg:address":"308 Highway 214",
    "sg:city":"Elmsdale",
    "sg:classifiers":[
        {
            "category":"Health Services",
            "subcategory":"Optometrist",
            "type":"Services"
        }
    ],
    "sg:phone":"+1 902 883 2221",
    "sg:postcode":"B2S 2K9",
    "sg:province":"NS",
    "wof:name":"Elmsdale Vision Ctr",
    "wof:placetype":"venue"
},
  "geometry": {"coordinates":[-63.5046348572,44.9673805237],"type":"Point"}
}