{
  "type": "Feature",
  "properties": {
    "addr:full":"120 Dufferin St Alberton PE C0B 1B0",
    "addr:housenumber":"120",
    "addr:postcode":"c0b 1b0",
    "addr:street":"Dufferin St",
    "iso:country":"CA",
    "sg:address":"120 Dufferin St",
    "sg:city":"Alberton",
    "sg:classifiers":[
        {
            "category":"Social Services",
            "subcategory":"Adult Care",
            "type":"Services"
        }
    ],
    "sg:phone":"+1 902 853 3109",
    "sg:postcode":"C0B 1B0",
    "sg:province":"PE",
    "sg:tags":[
        "community",
        "facility"
    ],
    "wof:name":"Rev Wj Phillips Residence",
    "wof:placetype":"venue"
},
  "geometry": {"coordinates":[-64.063408,46.814697],"type":"Point"}
}