{
  "type": "Feature",
  "properties": {
    "addr:full":"233 Cloutierville Rd Smooth Rock Falls ON P0L 2B0",
    "addr:housenumber":"233",
    "addr:postcode":"p0l 2b0",
    "addr:street":"Cloutierville Rd",
    "iso:country":"CA",
    "sg:address":"233 Cloutierville Rd",
    "sg:city":"Smooth Rock Falls",
    "sg:classifiers":[
        {
            "category":"Freight",
            "type":"Transportation"
        }
    ],
    "sg:phone":"+1 705 338 2986",
    "sg:postcode":"P0L 2B0",
    "sg:province":"ON",
    "sg:tags":[
        "commercial",
        "storage"
    ],
    "wof:name":"G & L Storage",
    "wof:placetype":"venue"
},
  "geometry": {"coordinates":[-81.61996499999999,49.287563],"type":"Point"}
}