{
  "type": "Feature",
  "properties": {
    "addr:full":"PO Box 4428 STN E Ottawa ON K1S 5B4",
    "addr:housenumber":"po",
    "addr:postcode":"k1s 5b4",
    "addr:street":"Box 4428 Stn E",
    "iso:country":"CA",
    "sg:address":"PO Box 4428 STN E",
    "sg:city":"Ottawa",
    "sg:classifiers":[
        {
            "category":"Organizations",
            "subcategory":"Religious Organization",
            "type":"Services"
        }
    ],
    "sg:phone":"+1 613 770 3433",
    "sg:postcode":"K1S 5B4",
    "sg:province":"ON",
    "sg:tags":[
        "church"
    ],
    "wof:name":"St Mesrob Armenian Apos Church",
    "wof:placetype":"venue"
},
  "geometry": {"coordinates":[-75.691895,45.421501],"type":"Point"}
}