{
  "type": "Feature",
  "properties": {
    "addr:full":"321 Selkirk St S Outlook SK S0L 2N0",
    "addr:housenumber":"321",
    "addr:postcode":"s0l 2n0",
    "addr:street":"Selkirk St S Outlook",
    "iso:country":"CA",
    "sg:address":"321 Selkirk St S",
    "sg:city":"Outlook",
    "sg:classifiers":[
        {
            "category":"Retail",
            "subcategory":"Funeral Services",
            "type":"Services"
        }
    ],
    "sg:phone":"+1 306 867 8255",
    "sg:postcode":"S0L 2N0",
    "sg:province":"SK",
    "sg:tags":[
        "director"
    ],
    "wof:name":"Outlook Funeral Chapel",
    "wof:placetype":"venue"
},
  "geometry": {"coordinates":[-107.055335998,51.4860649109],"type":"Point"}
}