{
  "type": "Feature",
  "properties": {
    "addr:full":"190 Albert St N Regina SK S4R 3B9",
    "addr:housenumber":"190",
    "addr:postcode":"s4r 3b9",
    "addr:street":"Albert St N",
    "iso:country":"CA",
    "sg:address":"190 Albert St N",
    "sg:city":"Regina",
    "sg:classifiers":[
        {
            "category":"Retail",
            "subcategory":"Auto Repair",
            "type":"Services"
        }
    ],
    "sg:phone":"+1 306 791 7861",
    "sg:postcode":"S4R 3B9",
    "sg:province":"SK",
    "sg:tags":[
        "repairing",
        "automobile",
        "lubrication"
    ],
    "wof:name":"Mr Lube",
    "wof:placetype":"venue"
},
  "geometry": {"coordinates":[-104.618476868,50.4785766602],"type":"Point"}
}