{
  "type": "Feature",
  "properties": {
    "iso:country":"CA",
    "sg:address":"153 Macaleese Lane",
    "sg:city":"Moncton",
    "sg:classifiers":[
        {
            "category":"Manufacturing",
            "subcategory":"Lumber",
            "type":"Manufacturing & Wholesale Goods"
        }
    ],
    "sg:phone":"+1 506 859 8686",
    "sg:postcode":"E1A 3M2",
    "sg:province":"NB",
    "sg:tags":[
        "syrup",
        "maple",
        "sugar"
    ],
    "wof:name":"Sugar Shack Maple Products Ltd",
    "wof:placetype":"venue"
},
  "geometry": {"coordinates":[-64.7664260864,46.1172294617],"type":"Point"}
}