{
  "type": "Feature",
  "properties": {
    "iso:country":"CA",
    "sg:address":"160 Ch Industriel",
    "sg:city":"Gatineau",
    "sg:classifiers":[
        {
            "category":"Freight",
            "type":"Transportation"
        }
    ],
    "sg:phone":"+1 819 663 1460",
    "sg:postcode":"J8R 3N9",
    "sg:province":"QC",
    "sg:tags":[
        "commercial",
        "storage"
    ],
    "wof:name":"Alabri Enr Les Mini Entrepots",
    "wof:placetype":"venue"
},
  "geometry": {"coordinates":[-75.58335876460001,45.5132522583],"type":"Point"}
}