{
  "type": "Feature",
  "properties": {
    "addr:full":"6082 Tecumseh Rd E Windsor ON N8T 1E3",
    "addr:housenumber":"6082",
    "addr:postcode":"n8t 1e3",
    "addr:street":"Tecumseh Rd E",
    "iso:country":"CA",
    "sg:address":"6082 Tecumseh Rd E",
    "sg:city":"Windsor",
    "sg:classifiers":[
        {
            "category":"Restaurant",
            "type":"Food & Drink"
        }
    ],
    "sg:phone":"+1 519 948 7977",
    "sg:postcode":"N8T 1E3",
    "sg:province":"ON",
    "wof:name":"Sofos Submarine",
    "wof:placetype":"venue"
},
  "geometry": {"coordinates":[-82.952156,42.31044],"type":"Point"}
}