{
  "type": "Feature",
  "properties": {
    "iso:country":"CA",
    "sg:address":"126 George St",
    "sg:city":"Sutton West",
    "sg:classifiers":[
        {
            "category":"Personal",
            "type":"Services"
        }
    ],
    "sg:phone":"+1 905 722 0202",
    "sg:postcode":"L0E 1R0",
    "sg:province":"ON",
    "sg:tags":[
        "therapist",
        "massage"
    ],
    "wof:name":"Cedarwood Massage Therapy",
    "wof:placetype":"venue"
},
  "geometry": {"coordinates":[-79.3351593018,44.329334259],"type":"Point"}
}