{
  "type": "Feature",
  "properties": {
    "addr:full":"1 Railway St Moose Creek ON K0C 1W0",
    "addr:housenumber":"1",
    "addr:postcode":"k0c 1w0",
    "addr:street":"Railway St",
    "iso:country":"CA",
    "sg:address":"1 Railway St",
    "sg:city":"Moose Creek",
    "sg:classifiers":[
        {
            "category":"Wholesale",
            "subcategory":"Farm Supplies",
            "type":"Manufacturing & Wholesale Goods"
        }
    ],
    "sg:phone":"+1 613 538 2395",
    "sg:postcode":"K0C 1W0",
    "sg:province":"ON",
    "sg:tags":[
        "livestock"
    ],
    "wof:name":"Crp Theoret Farm & Livestock",
    "wof:placetype":"venue"
},
  "geometry": {"coordinates":[-74.9745559692,45.2597351074],"type":"Point"}
}