{
  "type": "Feature",
  "properties": {
    "addr:full":"Hubbards NS B0J 1T0",
    "addr:postcode":"b0j 1t0",
    "iso:country":"CA",
    "sg:city":"Hubbards",
    "sg:classifiers":[
        {
            "category":"Shopping",
            "subcategory":"Catalog Store",
            "type":"Retail Goods"
        }
    ],
    "sg:phone":"+1 902 857 9538",
    "sg:postcode":"B0J 1T0",
    "sg:province":"NS",
    "sg:tags":[
        "mail",
        "order",
        "internet"
    ],
    "wof:name":"Sears Canada Inc",
    "wof:placetype":"venue"
},
  "geometry": {"coordinates":[-64.05205535890001,44.6433143616],"type":"Point"}
}