{
  "type": "Feature",
  "properties": {
    "addr:full":"678 Rue Des Sagueneens Chicoutimi QC G7H 5X4",
    "addr:housenumber":"678",
    "addr:postcode":"g7h 5x4",
    "addr:street":"Rue Des Sagueneens",
    "iso:country":"CA",
    "sg:address":"678 Rue Des Sagueneens",
    "sg:city":"Chicoutimi",
    "sg:classifiers":[
        {
            "category":"Building & Trades",
            "subcategory":"Construction",
            "type":"Services"
        }
    ],
    "sg:phone":"+1 418 815 3383",
    "sg:postcode":"G7H 5X4",
    "sg:province":"QC",
    "sg:tags":[
        "contractor",
        "general"
    ],
    "wof:name":"Constructions Michel Tremblay",
    "wof:placetype":"venue"
},
  "geometry": {"coordinates":[-71.05072,48.401802],"type":"Point"}
}