{
  "type": "Feature",
  "properties": {
    "iso:country":"CA",
    "sg:address":"871 Belgrave Way",
    "sg:city":"Delta",
    "sg:classifiers":[
        {
            "category":"Wholesale",
            "subcategory":"Furniture",
            "type":"Manufacturing & Wholesale Goods"
        }
    ],
    "sg:phone":"+1 604 777 2871",
    "sg:postcode":"V3M 5R8",
    "sg:province":"BC",
    "wof:name":"Winner's Only",
    "wof:placetype":"venue"
},
  "geometry": {"coordinates":[-122.93893432599999,49.1768989563],"type":"Point"}
}