{
  "type": "Feature",
  "properties": {
    "addr:full":"1251 Yonge St Toronto ON M4T 1W6",
    "addr:housenumber":"1251",
    "addr:postcode":"m4t 1w6",
    "addr:street":"Yonge St",
    "iso:country":"CA",
    "sg:address":"1251 Yonge St",
    "sg:city":"Toronto",
    "sg:classifiers":[
        {
            "category":"Retail",
            "subcategory":"Laundry & Dry Cleaning",
            "type":"Services"
        }
    ],
    "sg:phone":"+1 416 920 6623",
    "sg:postcode":"M4T 1W6",
    "sg:province":"ON",
    "sg:tags":[
        "cleaners"
    ],
    "wof:name":"P D Custom Cleaners",
    "wof:placetype":"venue"
},
  "geometry": {"coordinates":[-79.392281,43.684097],"type":"Point"}
}