{
  "type": "Feature",
  "properties": {
    "addr:full":"11 Av Laflamme Pont-Rouge QC G3H 3E2",
    "addr:postcode":"g3h 3e2",
    "addr:street":"11 Av Laflamme",
    "iso:country":"CA",
    "sg:address":"11 Av Laflamme",
    "sg:city":"Pont-Rouge",
    "sg:classifiers":[
        {
            "category":"Manufacturing",
            "subcategory":"Metals",
            "type":"Manufacturing & Wholesale Goods"
        }
    ],
    "sg:phone":"+1 418 873 2470",
    "sg:postcode":"G3H 3E2",
    "sg:province":"QC",
    "sg:tags":[
        "shelter",
        "garage",
        "canopy",
        "temporary",
        "awning"
    ],
    "wof:name":"Auvent Pont-Rouge Inc",
    "wof:placetype":"venue"
},
  "geometry": {"coordinates":[-71.6930465698,46.755821228],"type":"Point"}
}