{
  "type": "Feature",
  "properties": {
    "addr:full":"45 Boul Bellerose E Laval QC H7K 1S5",
    "addr:housenumber":"45",
    "addr:postcode":"qc h7k 1s5",
    "addr:street":"Boul Bellerose E",
    "iso:country":"CA",
    "sg:address":"45 Boul Bellerose E",
    "sg:city":"Laval",
    "sg:classifiers":[
        {
            "category":"Bars & Pubs",
            "type":"Food & Drink"
        }
    ],
    "sg:phone":"+1 450 629 4593",
    "sg:postcode":"H7K 1S5",
    "sg:province":"QC",
    "sg:tags":[
        "lounge",
        "cocktail"
    ],
    "wof:name":"Cafe Du Monde Bistro Bar Inc",
    "wof:placetype":"venue"
},
  "geometry": {"coordinates":[-73.7335281372,45.6126441956],"type":"Point"}
}