{
  "type": "Feature",
  "properties": {
    "addr:full":"1501 Eastern Ave North Vancouver BC V7L 3G2",
    "addr:housenumber":"1501",
    "addr:postcode":"v7l 3g2",
    "addr:street":"Eastern Ave",
    "iso:country":"CA",
    "sg:address":"1501 Eastern Ave",
    "sg:city":"North Vancouver",
    "sg:classifiers":[
        {
            "category":"Health Services",
            "subcategory":"Doctor",
            "type":"Services"
        }
    ],
    "sg:phone":"+1 604 988 2555",
    "sg:postcode":"V7L 3G2",
    "sg:province":"BC",
    "sg:tags":[
        "dentist"
    ],
    "wof:name":"Aqua Dental Ctr",
    "wof:placetype":"venue"
},
  "geometry": {"coordinates":[-123.070892,49.322285],"type":"Point"}
}