{
  "type": "Feature",
  "properties": {
    "addr:full":"441 Brown St Wiarton ON N0H 2T0",
    "addr:housenumber":"441",
    "addr:postcode":"n0h 2t0",
    "addr:street":"Brown St",
    "iso:country":"CA",
    "sg:address":"441 Brown St",
    "sg:city":"Wiarton",
    "sg:classifiers":[
        {
            "category":"Organizations",
            "subcategory":"Religious Organization",
            "type":"Services"
        }
    ],
    "sg:phone":"+1 519 534 3456",
    "sg:postcode":"N0H 2T0",
    "sg:province":"ON",
    "sg:tags":[
        "church"
    ],
    "wof:name":"St Peter's Lutheran Church",
    "wof:placetype":"venue"
},
  "geometry": {"coordinates":[-81.136826,44.739532],"type":"Point"}
}