{
  "type": "Feature",
  "properties": {
    "addr:full":"37 Marchington Cir Scarborough ON M1R 3M6",
    "addr:housenumber":"37",
    "addr:postcode":"m1r 3m6",
    "addr:street":"Marchington Cir",
    "iso:country":"CA",
    "sg:address":"37 Marchington Cir",
    "sg:city":"Scarborough",
    "sg:classifiers":[
        {
            "category":"Social Services",
            "subcategory":"Child Care",
            "type":"Services"
        }
    ],
    "sg:phone":"+1 416 447 1059",
    "sg:postcode":"M1R 3M6",
    "sg:province":"ON",
    "sg:tags":[
        "kindergarten",
        "academic",
        "school"
    ],
    "wof:name":"Ellesmere Montessori School",
    "wof:placetype":"venue"
},
  "geometry": {"coordinates":[-79.30718231199999,43.7587127686],"type":"Point"}
}