{
  "type": "Feature",
  "properties": {
    "addr:full":"363 King George Hwy Miramichi NB E1V 1L2",
    "addr:housenumber":"363",
    "addr:postcode":"e1v 1l2",
    "addr:street":"King George Hwy",
    "iso:country":"CA",
    "sg:address":"363 King George Hwy",
    "sg:city":"Miramichi",
    "sg:classifiers":[
        {
            "category":"Wholesale",
            "subcategory":"Electrical",
            "type":"Manufacturing & Wholesale Goods"
        }
    ],
    "sg:phone":"+1 506 627 0988",
    "sg:postcode":"E1V 1L2",
    "sg:province":"NB",
    "sg:tags":[
        "equipment",
        "video"
    ],
    "wof:name":"Video Solutions",
    "wof:placetype":"venue"
},
  "geometry": {"coordinates":[-65.57781982420001,46.9867401123],"type":"Point"}
}