{
  "type": "Feature",
  "properties": {
    "addr:full":"41 Point Hope Pl Whitby ON L1N 9T2",
    "addr:housenumber":"41",
    "addr:postcode":"l1n 9t2",
    "addr:street":"Point Hope Pl",
    "iso:country":"CA",
    "sg:address":"41 Point Hope Pl",
    "sg:city":"Whitby",
    "sg:classifiers":[
        {
            "category":"Freight",
            "type":"Transportation"
        }
    ],
    "sg:phone":"+1 905 426 0202",
    "sg:postcode":"L1N 9T2",
    "sg:province":"ON",
    "sg:tags":[
        "mover"
    ],
    "wof:name":"Mc Gee Moving",
    "wof:placetype":"venue"
},
  "geometry": {"coordinates":[-78.95120199999999,43.858582],"type":"Point"}
}