{
  "type": "Feature",
  "properties": {
    "iso:country":"CA",
    "sg:address":"101 15th St E #204",
    "sg:city":"Prince Albert",
    "sg:classifiers":[
        {
            "category":"Social Services",
            "type":"Services"
        }
    ],
    "sg:phone":"+1 306 763 7243",
    "sg:postcode":"S6V 1G1",
    "sg:province":"SK",
    "sg:tags":[
        "counseling",
        "counselor",
        "marriage",
        "family"
    ],
    "wof:name":"Nistta Family & Art Therapy",
    "wof:placetype":"venue"
},
  "geometry": {"coordinates":[-105.750443,53.199303],"type":"Point"}
}