{
  "type": "Feature",
  "properties": {
    "iso:country":"CA",
    "sg:city":"Milton",
    "sg:classifiers":[
        {
            "category":"Retail",
            "subcategory":"Veterinary Services",
            "type":"Services"
        }
    ],
    "sg:phone":"+1 905 875 6888",
    "sg:postcode":"L9T 5E4",
    "sg:province":"ON",
    "sg:tags":[
        "veterinarian"
    ],
    "wof:name":"Hawkins Animal Hospital",
    "wof:placetype":"venue"
},
  "geometry": {"coordinates":[-79.862892,43.507294],"type":"Point"}
}