{
  "type": "Feature",
  "properties": {
    "iso:country":"CA",
    "sg:address":"1306 Boundary Rd",
    "sg:city":"Burnaby",
    "sg:classifiers":[
        {
            "category":"Wholesale",
            "subcategory":"Construction Materials",
            "type":"Manufacturing & Wholesale Goods"
        }
    ],
    "sg:phone":"+1 604 294 8116",
    "sg:postcode":"V5K 4T6",
    "sg:province":"BC",
    "sg:tags":[
        "glass",
        "product",
        "fiber",
        "plastic"
    ],
    "wof:name":"Coast Fiber-Tek Products Ltd",
    "wof:placetype":"venue"
},
  "geometry": {"coordinates":[-123.023368835,49.2729721069],"type":"Point"}
}