{
  "type": "Feature",
  "properties": {
    "addr:full":"85 Howard Pl Kitchener ON N2K 2Z4",
    "addr:housenumber":"85",
    "addr:postcode":"n2k 2z4",
    "addr:street":"Howard Pl",
    "iso:country":"CA",
    "sg:address":"85 Howard Pl",
    "sg:city":"Kitchener",
    "sg:classifiers":[
        {
            "category":"Building & Trades",
            "subcategory":"Landscaping Services",
            "type":"Services"
        }
    ],
    "sg:phone":"+1 519 744 2261",
    "sg:postcode":"N2K 2Z4",
    "sg:province":"ON",
    "sg:tags":[
        "landscape",
        "contractor"
    ],
    "wof:name":"Heritage Stoneworks Ltd",
    "wof:placetype":"venue"
},
  "geometry": {"coordinates":[-80.4644775391,43.4789237976],"type":"Point"}
}