{
  "type": "Feature",
  "properties": {
    "addr:full":"1819 Pembina Hwy Winnipeg MB R3T 2G6",
    "addr:housenumber":"1819",
    "addr:postcode":"r3t 2g6",
    "addr:street":"Pembina Hwy",
    "iso:country":"CA",
    "sg:address":"1819 Pembina Hwy",
    "sg:city":"Winnipeg",
    "sg:classifiers":[
        {
            "category":"Travel",
            "subcategory":"Hotels & Motels",
            "type":"Entertainment"
        }
    ],
    "sg:phone":"+1 204 269 6990",
    "sg:postcode":"R3T 2G6",
    "sg:province":"MB",
    "wof:name":"Capri Motel",
    "wof:placetype":"venue"
},
  "geometry": {"coordinates":[-97.15325900000001,49.823757],"type":"Point"}
}