{
  "type": "Feature",
  "properties": {
    "addr:full":"89 Steelcase Rd E Markham ON L3R 1E9",
    "addr:housenumber":"89",
    "addr:postcode":"l3r 1e9",
    "addr:street":"Steelcase Rd E",
    "iso:country":"CA",
    "sg:address":"89 Steelcase Rd E",
    "sg:city":"Markham",
    "sg:classifiers":[
        {
            "category":"Wholesale",
            "subcategory":"Electrical",
            "type":"Manufacturing & Wholesale Goods"
        }
    ],
    "sg:phone":"+1 905 948 0441",
    "sg:postcode":"L3R 1E9",
    "sg:province":"ON",
    "sg:tags":[
        "equipment",
        "electric",
        "supply"
    ],
    "wof:name":"Torbram Electric Supply",
    "wof:placetype":"venue"
},
  "geometry": {"coordinates":[-79.347458,43.820004],"type":"Point"}
}