{
  "type": "Feature",
  "properties": {
    "addr:full":"41 Poupore St Gogama ON P0M 1W0",
    "addr:housenumber":"41",
    "addr:postcode":"p0m 1w0",
    "addr:street":"Poupore St",
    "iso:country":"CA",
    "sg:address":"41 Poupore St",
    "sg:city":"Gogama",
    "sg:classifiers":[
        {
            "category":"Shopping",
            "subcategory":"Catalog Store",
            "type":"Retail Goods"
        }
    ],
    "sg:phone":"+1 705 894 2484",
    "sg:postcode":"P0M 1W0",
    "sg:province":"ON",
    "sg:tags":[
        "mail",
        "order",
        "internet"
    ],
    "wof:name":"Sears Canada Inc",
    "wof:placetype":"venue"
},
  "geometry": {"coordinates":[-81.724121,47.675491],"type":"Point"}
}