{
  "type": "Feature",
  "properties": {
    "addr:full":"1011 Manitoba Ave Selkirk MB R1A 3T7",
    "addr:housenumber":"1011",
    "addr:postcode":"r1a 3t7",
    "addr:street":"Manitoba Ave",
    "iso:country":"CA",
    "sg:address":"1011 Manitoba Ave",
    "sg:city":"Selkirk",
    "sg:classifiers":[
        {
            "category":"Autos & Motor Vehicles",
            "subcategory":"Automobile Sales",
            "type":"Retail Goods"
        }
    ],
    "sg:phone":"+1 204 482 4151",
    "sg:postcode":"R1A 3T7",
    "sg:province":"MB",
    "sg:tags":[
        "car",
        "dealer"
    ],
    "wof:name":"Selkirk Chrysler Ltd",
    "wof:placetype":"venue"
},
  "geometry": {"coordinates":[-96.89715576170001,50.1558113098],"type":"Point"}
}