{
  "type": "Feature",
  "properties": {
    "addr:full":"Surrey BC V4A 3A7",
    "addr:postcode":"v4a 3a7",
    "iso:country":"CA",
    "sg:city":"Surrey",
    "sg:classifiers":[
        {
            "category":"Real Estate",
            "subcategory":"Architect",
            "type":"Services"
        }
    ],
    "sg:phone":"+1 604 536 1600",
    "sg:postcode":"V4A 3A7",
    "sg:province":"BC",
    "wof:name":"Ankenman Associates Architects",
    "wof:placetype":"venue"
},
  "geometry": {"coordinates":[-122.880577,49.053219],"type":"Point"}
}