{
  "type": "Feature",
  "properties": {
    "addr:full":"72 Rue Saint-Louis Quebec QC G1R 3Z3",
    "addr:housenumber":"72",
    "addr:postcode":"g1r 3z3",
    "addr:street":"Rue Saint-Louis",
    "iso:country":"CA",
    "sg:address":"72 Rue Saint-Louis",
    "sg:city":"Quebec",
    "sg:classifiers":[
        {
            "category":"Travel",
            "subcategory":"Hotels & Motels",
            "type":"Entertainment"
        }
    ],
    "sg:phone":"+1 418 694 1905",
    "sg:postcode":"G1R 3Z3",
    "sg:province":"QC",
    "sg:tags":[
        "breakfast",
        "accommodation",
        "bed"
    ],
    "wof:name":"Hotel Maison Du General",
    "wof:placetype":"venue"
},
  "geometry": {"coordinates":[-71.2091369629,46.8108978271],"type":"Point"}
}