{
  "type": "Feature",
  "properties": {
    "addr:full":"Calgary AB T2P 3W2",
    "addr:postcode":"t2p 3w2",
    "iso:country":"CA",
    "sg:city":"Calgary",
    "sg:classifiers":[
        {
            "category":"Professional",
            "subcategory":"Engineering",
            "type":"Services"
        }
    ],
    "sg:phone":"+1 403 261 4720",
    "sg:postcode":"T2P 3W2",
    "sg:province":"AB",
    "sg:tags":[
        "engineer"
    ],
    "wof:name":"Trimble Engineering Assoc Ltd",
    "wof:placetype":"venue"
},
  "geometry": {"coordinates":[-114.078941345,51.0477561951],"type":"Point"}
}