{
  "type": "Feature",
  "properties": {
    "addr:full":"230 Boul Des Bois-Francs S Victoriaville QC G6P 4T1",
    "addr:housenumber":"230",
    "addr:postcode":"g6p 4t1",
    "addr:street":"Boul Des Bois-Francs S",
    "iso:country":"CA",
    "sg:address":"230 Boul Des Bois-Francs S",
    "sg:city":"Victoriaville",
    "sg:classifiers":[
        {
            "category":"Personal",
            "subcategory":"Beauty Salon",
            "type":"Services"
        }
    ],
    "sg:phone":"+1 819 758 9232",
    "sg:postcode":"G6P 4T1",
    "sg:province":"QC",
    "wof:name":"Coiffure Claire Soleil",
    "wof:placetype":"venue"
},
  "geometry": {"coordinates":[-71.944023,46.055096],"type":"Point"}
}