{
  "type": "Feature",
  "properties": {
    "addr:full":"10655 Rue L'Heureux Quebec QC G2A 2A3",
    "addr:housenumber":"10655",
    "addr:postcode":"g2a 2a3",
    "addr:street":"Rue L'Heureux",
    "iso:country":"CA",
    "sg:address":"10655 Rue L'Heureux",
    "sg:city":"Quebec",
    "sg:classifiers":[
        {
            "category":"Manufacturing",
            "subcategory":"Metals",
            "type":"Manufacturing & Wholesale Goods"
        }
    ],
    "sg:phone":"+1 418 845 3333",
    "sg:postcode":"G2A 2A3",
    "sg:province":"QC",
    "sg:tags":[
        "burglary",
        "heat",
        "protective",
        "robbery"
    ],
    "wof:name":"Mens-Tec Inc",
    "wof:placetype":"venue"
},
  "geometry": {"coordinates":[-71.2193527222,46.8127403259],"type":"Point"}
}