{
  "type": "Feature",
  "properties": {
    "iso:country":"CA",
    "sg:address":"445 Boul Arthur-Sauve",
    "sg:city":"Saint-Eustache",
    "sg:classifiers":[
        {
            "category":"Retail",
            "subcategory":"Auto Rental",
            "type":"Services"
        }
    ],
    "sg:phone":"+1 450 472 5664",
    "sg:postcode":"J7P 2B3",
    "sg:province":"QC",
    "sg:tags":[
        "renting",
        "automobile"
    ],
    "wof:name":"A Enterprise Location D'Autos",
    "wof:placetype":"venue"
},
  "geometry": {"coordinates":[-73.90603637700001,45.5658493042],"type":"Point"}
}