{
  "type": "Feature",
  "properties": {
    "addr:full":"Sharbot Lake ON K0H 2P0",
    "addr:postcode":"k0h 2p0",
    "iso:country":"CA",
    "sg:city":"Sharbot Lake",
    "sg:classifiers":[
        {
            "category":"Travel",
            "subcategory":"Hotels & Motels",
            "type":"Entertainment"
        }
    ],
    "sg:phone":"+1 613 279 3006",
    "sg:postcode":"K0H 2P0",
    "sg:province":"ON",
    "sg:tags":[
        "breakfast",
        "accommodation",
        "bed"
    ],
    "wof:name":"Rockhill Bed & Breakfast",
    "wof:placetype":"venue"
},
  "geometry": {"coordinates":[-76.6874008179,44.7715492249],"type":"Point"}
}