{
  "type": "Feature",
  "properties": {
    "addr:full":"513 Fildle Park Lane Shelburne ON L0N 1S2",
    "addr:housenumber":"513",
    "addr:postcode":"l0n 1s2",
    "addr:street":"Fildle Park Lane",
    "iso:country":"CA",
    "sg:address":"513 Fildle Park Lane",
    "sg:city":"Shelburne",
    "sg:classifiers":[
        {
            "category":"Building & Trades",
            "subcategory":"Construction",
            "type":"Services"
        }
    ],
    "sg:phone":"+1 519 925 3370",
    "sg:postcode":"L0N 1S2",
    "sg:province":"ON",
    "sg:tags":[
        "resurfacing",
        "laying",
        "refinishing",
        "floor"
    ],
    "wof:name":"Country Wood Floor Finishers",
    "wof:placetype":"venue"
},
  "geometry": {"coordinates":[-80.2010726929,44.0877151489],"type":"Point"}
}