{
  "type": "Feature",
  "properties": {
    "addr:full":"1440 Main St E Hamilton ON L8K 6M3",
    "addr:housenumber":"1440",
    "addr:postcode":"l8k 6m3",
    "addr:street":"Main St E",
    "iso:country":"CA",
    "sg:address":"1440 Main St E",
    "sg:city":"Hamilton",
    "sg:classifiers":[
        {
            "category":"Professional",
            "subcategory":"Business Services",
            "type":"Services"
        }
    ],
    "sg:phone":"+1 905 545 0442",
    "sg:postcode":"L8K 6M3",
    "sg:province":"ON",
    "sg:tags":[
        "arbitration",
        "attorney"
    ],
    "wof:name":"Mc Questen Legal & Cmnty Svc",
    "wof:placetype":"venue"
},
  "geometry": {"coordinates":[-79.808883667,43.2401199341],"type":"Point"}
}