{
  "type": "Feature",
  "properties": {
    "addr:full":"711 Concession St Hamilton ON L8V 1C3",
    "addr:housenumber":"711",
    "addr:postcode":"l8v 1c3",
    "addr:street":"Concession St",
    "iso:country":"CA",
    "sg:address":"711 Concession St",
    "sg:city":"Hamilton",
    "sg:classifiers":[
        {
            "category":"Health Services",
            "subcategory":"Health Practitioner",
            "type":"Services"
        }
    ],
    "sg:phone":"+1 905 527 4322",
    "sg:postcode":"L8V 1C3",
    "sg:province":"ON",
    "sg:tags":[
        "physiotherapist"
    ],
    "wof:name":"Fit For the Future",
    "wof:placetype":"venue"
},
  "geometry": {"coordinates":[-79.84440600000001,43.239079],"type":"Point"}
}