{
  "type": "Feature",
  "properties": {
    "addr:full":"6310 Rue Jean-Talon E Saint-Leonard QC H1S 1M8",
    "addr:housenumber":"6310",
    "addr:postcode":"h1s 1m8",
    "addr:street":"Rue Jean-Talon E",
    "iso:country":"CA",
    "sg:address":"6310 Rue Jean-Talon E",
    "sg:city":"Saint-Leonard",
    "sg:classifiers":[
        {
            "category":"Food & Beverages",
            "subcategory":"Groceries & Convenience Stores",
            "type":"Retail Goods"
        }
    ],
    "sg:phone":"+1 514 259 1882",
    "sg:postcode":"H1S 1M8",
    "sg:province":"QC",
    "wof:name":"Depanneur Ultra",
    "wof:placetype":"venue"
},
  "geometry": {"coordinates":[-73.57617999999999,45.590527],"type":"Point"}
}