{
  "type": "Feature",
  "properties": {
    "addr:full":"Grande Prairie AB T8V 7X7",
    "addr:postcode":"t8v 7x7",
    "iso:country":"CA",
    "sg:city":"Grande Prairie",
    "sg:classifiers":[
        {
            "category":"Organizations",
            "subcategory":"Professional Association",
            "type":"Services"
        }
    ],
    "sg:phone":"+1 780 532 3305",
    "sg:postcode":"T8V 7X7",
    "sg:province":"AB",
    "wof:name":"Canadian Paraplegic Assn",
    "wof:placetype":"venue"
},
  "geometry": {"coordinates":[-118.810593,55.168034],"type":"Point"}
}