{
  "type": "Feature",
  "properties": {
    "addr:full":"9611 Ferndale Rd Richmond BC V6Y 1X4",
    "addr:housenumber":"9611",
    "addr:postcode":"v6y 1x4",
    "addr:street":"Ferndale Rd",
    "iso:country":"CA",
    "sg:address":"9611 Ferndale Rd",
    "sg:city":"Richmond",
    "sg:classifiers":[
        {
            "category":"Building & Trades",
            "subcategory":"Landscaping Services",
            "type":"Services"
        }
    ],
    "sg:phone":"+1 604 273 0253",
    "sg:postcode":"V6Y 1X4",
    "sg:province":"BC",
    "sg:tags":[
        "landscape",
        "contractor"
    ],
    "wof:name":"Jade Landscaping & Gardening",
    "wof:placetype":"venue"
},
  "geometry": {"coordinates":[-123.118713,49.168777],"type":"Point"}
}