{
  "type": "Feature",
  "properties": {
    "addr:full":"2003 Ogilvie St S Prince George BC V2N 1X2",
    "addr:housenumber":"2003",
    "addr:postcode":"v2n 1x2",
    "addr:street":"Ogilvie St S",
    "iso:country":"CA",
    "sg:address":"2003 Ogilvie St S",
    "sg:city":"Prince George",
    "sg:phone":"+1 250 563 7959",
    "sg:postcode":"V2N 1X2",
    "sg:province":"BC",
    "sg:tags":[
        "scale"
    ],
    "wof:name":"Northern Scale",
    "wof:placetype":"venue"
},
  "geometry": {"coordinates":[-122.789452,53.905449],"type":"Point"}
}