{
  "type": "Feature",
  "properties": {
    "addr:full":"3185 Becker St Armstrong BC V0E 1B1",
    "addr:housenumber":"3185",
    "addr:postcode":"v0e 1b1",
    "addr:street":"Becker St",
    "iso:country":"CA",
    "sg:address":"3185 Becker St",
    "sg:city":"Armstrong",
    "sg:classifiers":[
        {
            "category":"Organizations",
            "subcategory":"Religious Organization",
            "type":"Services"
        }
    ],
    "sg:phone":"+1 250 546 9598",
    "sg:postcode":"V0E 1B1",
    "sg:province":"BC",
    "sg:tags":[
        "church"
    ],
    "wof:name":"First Baptist Church",
    "wof:placetype":"venue"
},
  "geometry": {"coordinates":[-119.197494507,50.4445991516],"type":"Point"}
}