{
  "type": "Feature",
  "properties": {
    "addr:full":"703 Gladstone Ave Toronto ON M6H 3J5",
    "addr:housenumber":"703",
    "addr:postcode":"m6h 3j5",
    "addr:street":"Gladstone Ave",
    "iso:country":"CA",
    "sg:address":"703 Gladstone Ave",
    "sg:city":"Toronto",
    "sg:classifiers":[
        {
            "category":"Freight",
            "type":"Transportation"
        }
    ],
    "sg:phone":"+1 416 533 4162",
    "sg:postcode":"M6H 3J5",
    "sg:province":"ON",
    "sg:tags":[
        "mover"
    ],
    "wof:name":"Apple Moving & Cartage",
    "wof:placetype":"venue"
},
  "geometry": {"coordinates":[-79.435913,43.66478],"type":"Point"}
}