{
  "type": "Feature",
  "properties": {
    "addr:full":"428 Rue Saint-Paul Le Gardeur QC J5Z 4H9",
    "addr:housenumber":"428",
    "addr:postcode":"j5z 4h9",
    "addr:street":"Rue Saint-Paul",
    "iso:country":"CA",
    "sg:address":"428 Rue Saint-Paul",
    "sg:city":"Le Gardeur",
    "sg:classifiers":[
        {
            "category":"Building & Trades",
            "subcategory":"Construction",
            "type":"Services"
        }
    ],
    "sg:phone":"+1 450 581 9533",
    "sg:postcode":"J5Z 4H9",
    "sg:province":"QC",
    "sg:tags":[
        "operating",
        "gate",
        "door",
        "devices",
        "contractor"
    ],
    "wof:name":"Entreprises Daunais Inc",
    "wof:placetype":"venue"
},
  "geometry": {"coordinates":[-73.48653400000001,45.760204],"type":"Point"}
}