{
  "type": "Feature",
  "properties": {
    "iso:country":"CA",
    "sg:address":"428 Rue Saint-Paul",
    "sg:city":"Le Gardeur",
    "sg:classifiers":[
        {
            "category":"Building & Trades",
            "subcategory":"Construction",
            "type":"Services"
        }
    ],
    "sg:phone":"+1 450 581 9533",
    "sg:postcode":"J5Z 4H9",
    "sg:province":"QC",
    "sg:tags":[
        "operating",
        "gate",
        "door",
        "devices",
        "contractor"
    ],
    "wof:name":"Entreprises Daunais Inc",
    "wof:placetype":"venue"
},
  "geometry": {"coordinates":[-73.486534,45.760204],"type":"Point"}
}