{
  "type": "Feature",
  "properties": {
    "addr:full":"427 Preston St Ottawa ON K1S 4N3",
    "addr:housenumber":"427",
    "addr:postcode":"k1s 4n3",
    "addr:street":"Preston St",
    "iso:country":"CA",
    "sg:address":"427 Preston St",
    "sg:city":"Ottawa",
    "sg:phone":"+1 613 231 7882",
    "sg:postcode":"K1S 4N3",
    "sg:province":"ON",
    "sg:tags":[
        "equipment",
        "register",
        "cash",
        "supply"
    ],
    "wof:name":"Azbar Inc",
    "wof:placetype":"venue"
},
  "geometry": {"coordinates":[-75.70882400000001,45.399853],"type":"Point"}
}