{
  "type": "Feature",
  "properties": {
    "iso:country":"CA",
    "sg:address":"260 St Patrick St",
    "sg:city":"Ottawa",
    "sg:classifiers":[
        {
            "category":"Real Estate",
            "subcategory":"Developer",
            "type":"Services"
        }
    ],
    "sg:phone":"+1 613 241 9410",
    "sg:postcode":"K1N 5K5",
    "sg:province":"ON",
    "sg:tags":[
        "company",
        "land"
    ],
    "wof:name":"Gestion Philips Inc",
    "wof:placetype":"venue"
},
  "geometry": {"coordinates":[-75.692299,45.430931],"type":"Point"}
}