{
  "type": "Feature",
  "properties": {
    "addr:full":"Lantzville BC V0R 2H0",
    "addr:postcode":"v0r 2h0",
    "iso:country":"CA",
    "sg:city":"Lantzville",
    "sg:classifiers":[
        {
            "category":"Retail",
            "subcategory":"Auto Repair",
            "type":"Services"
        }
    ],
    "sg:phone":"+1 250 754 8423",
    "sg:postcode":"V0R 2H0",
    "sg:province":"BC",
    "sg:tags":[
        "wrecker"
    ],
    "wof:name":"Affordable Towing",
    "wof:placetype":"venue"
},
  "geometry": {"coordinates":[-124.137657,49.247665],"type":"Point"}
}