{
  "type": "Feature",
  "properties": {
    "addr:full":"3478 John St S Sombra ON N0P 2H0",
    "addr:housenumber":"3478",
    "addr:postcode":"n0p 2h0",
    "addr:street":"John St S Sombra",
    "iso:country":"CA",
    "sg:address":"3478 John St S",
    "sg:city":"Sombra",
    "sg:classifiers":[
        {
            "category":"Wholesale",
            "subcategory":"Machinery & Supplies",
            "type":"Manufacturing & Wholesale Goods"
        }
    ],
    "sg:phone":"+1 519 892 3496",
    "sg:postcode":"N0P 2H0",
    "sg:province":"ON",
    "sg:tags":[
        "equipment",
        "oil",
        "well"
    ],
    "wof:name":"Lambton Pipe & Supply Ltd",
    "wof:placetype":"venue"
},
  "geometry": {"coordinates":[-82.47709655760001,42.7121810913],"type":"Point"}
}