{
  "type": "Feature",
  "properties": {
    "addr:full":"19498 92 Ave Surrey BC V4N 4G7",
    "addr:housenumber":"19498",
    "addr:postcode":"v4n 4g7",
    "addr:street":"92 Ave",
    "iso:country":"CA",
    "sg:address":"19498 92 Ave",
    "sg:city":"Surrey",
    "sg:classifiers":[
        {
            "category":"Retail",
            "subcategory":"Auto Repair",
            "type":"Services"
        }
    ],
    "sg:phone":"+1 604 888 3406",
    "sg:postcode":"V4N 4G7",
    "sg:province":"BC",
    "sg:tags":[
        "truck"
    ],
    "wof:name":"Finning Power Systems",
    "wof:placetype":"venue"
},
  "geometry": {"coordinates":[-122.682175,49.169994],"type":"Point"}
}