{
  "type": "Feature",
  "properties": {
    "addr:full":"345 Allen Ave Essex ON N8M 3G7",
    "addr:housenumber":"345",
    "addr:postcode":"n8m 3g7",
    "addr:street":"Allen Ave",
    "iso:country":"CA",
    "sg:address":"345 Allen Ave",
    "sg:city":"Essex",
    "sg:classifiers":[
        {
            "category":"Home & Garden",
            "subcategory":"Building Materials",
            "type":"Retail Goods"
        }
    ],
    "sg:phone":"+1 519 776 4121",
    "sg:postcode":"N8M 3G7",
    "sg:province":"ON",
    "sg:tags":[
        "door"
    ],
    "wof:name":"Mills Woodworking",
    "wof:placetype":"venue"
},
  "geometry": {"coordinates":[-82.833916,42.176743],"type":"Point"}
}