{
  "type": "Feature",
  "properties": {
    "addr:full":"6461 Metral Dr Nanaimo BC V9T 2L9",
    "addr:housenumber":"6461",
    "addr:postcode":"v9t 2l9",
    "addr:street":"Metral Dr",
    "iso:country":"CA",
    "sg:address":"6461 Metral Dr",
    "sg:city":"Nanaimo",
    "sg:classifiers":[
        {
            "category":"Home & Garden",
            "subcategory":"Furniture",
            "type":"Retail Goods"
        }
    ],
    "sg:phone":"+1 250 390 1737",
    "sg:postcode":"V9T 2L9",
    "sg:province":"BC",
    "wof:name":"Wosk Furniture Fashions",
    "wof:placetype":"venue"
},
  "geometry": {"coordinates":[-124.04437299999999,49.232372],"type":"Point"}
}