{
  "type": "Feature",
  "properties": {
    "iso:country":"CA",
    "sg:address":"2030 Meadowgate Blvd",
    "sg:city":"London",
    "sg:classifiers":[
        {
            "category":"Health Services",
            "subcategory":"Doctor",
            "type":"Services"
        }
    ],
    "sg:phone":"+1 519 649 2241",
    "sg:postcode":"N6M 1K1",
    "sg:province":"ON",
    "sg:tags":[
        "dentist"
    ],
    "wof:name":"Summerside Dental",
    "wof:placetype":"venue"
},
  "geometry": {"coordinates":[-81.1804885864,42.9631156921],"type":"Point"}
}