{
  "type": "Feature",
  "properties": {
    "addr:full":"PO Box 235 Eaglesham AB T0H 1H0",
    "addr:housenumber":"po",
    "addr:postcode":"t0h 1h0",
    "addr:street":"Box 235",
    "iso:country":"CA",
    "sg:address":"PO Box 235",
    "sg:city":"Eaglesham",
    "sg:classifiers":[
        {
            "category":"Building & Trades",
            "subcategory":"Construction",
            "type":"Services"
        }
    ],
    "sg:phone":"+1 780 359 2506",
    "sg:postcode":"T0H 1H0",
    "sg:province":"AB",
    "sg:tags":[
        "excavating",
        "contractor"
    ],
    "wof:name":"Leonard Despins Excavating",
    "wof:placetype":"venue"
},
  "geometry": {"coordinates":[-117.89444,55.786629],"type":"Point"}
}