{
  "type": "Feature",
  "properties": {
    "addr:full":"6580 4th Line Rd North Gower ON K0A 2T0",
    "addr:housenumber":"6580",
    "addr:postcode":"k0a 2t0",
    "addr:street":"4Th Line Rd",
    "iso:country":"CA",
    "sg:address":"6580 4th Line Rd",
    "sg:city":"North Gower",
    "sg:classifiers":[
        {
            "category":"Retail",
            "subcategory":"Auto Repair",
            "type":"Services"
        }
    ],
    "sg:phone":"+1 613 489 3882",
    "sg:postcode":"K0A 2T0",
    "sg:province":"ON",
    "sg:tags":[
        "repairing",
        "automobile"
    ],
    "wof:name":"Harrison's Garage",
    "wof:placetype":"venue"
},
  "geometry": {"coordinates":[-75.71765899659999,45.1325645447],"type":"Point"}
}