{
  "type": "Feature",
  "properties": {
    "addr:full":"100 Tempo Ave North York ON M2H 2N8",
    "addr:housenumber":"100",
    "addr:postcode":"m2h 2n8",
    "addr:street":"Tempo Ave",
    "iso:country":"CA",
    "sg:address":"100 Tempo Ave",
    "sg:city":"North York",
    "sg:classifiers":[
        {
            "category":"Professional",
            "subcategory":"Art Services",
            "type":"Services"
        }
    ],
    "sg:phone":"+1 416 493 4133",
    "sg:postcode":"M2H 2N8",
    "sg:province":"ON",
    "sg:tags":[
        "graphic",
        "designer"
    ],
    "wof:name":"Founder Technology Canada Corp",
    "wof:placetype":"venue"
},
  "geometry": {"coordinates":[-79.3410110474,43.8056755066],"type":"Point"}
}