{
  "type": "Feature",
  "properties": {
    "addr:full":"1262 Albert St Regina SK S4R 2R3",
    "addr:housenumber":"1262",
    "addr:postcode":"s4r 2r3",
    "addr:street":"Albert St",
    "iso:country":"CA",
    "sg:address":"1262 Albert St",
    "sg:city":"Regina",
    "sg:classifiers":[
        {
            "category":"Insurance",
            "subcategory":"Insurance Agent",
            "type":"Services"
        }
    ],
    "sg:phone":"+1 306 359 3331",
    "sg:postcode":"S4R 2R3",
    "sg:province":"SK",
    "wof:name":"Smiths' Insurance",
    "wof:placetype":"venue"
},
  "geometry": {"coordinates":[-104.618431,50.458908],"type":"Point"}
}