{
  "type": "Feature",
  "properties": {
    "addr:full":"168 Boul Du Portage-Des-Mousse Port-Cartier QC G5B 1E3",
    "addr:housenumber":"168",
    "addr:postcode":"g5b 1e3",
    "addr:street":"Boul Du Portage-Des-Mousse",
    "iso:country":"CA",
    "sg:address":"168 Boul Du Portage-Des-Mousse",
    "sg:city":"Port-Cartier",
    "sg:classifiers":[
        {
            "category":"Freight",
            "type":"Transportation"
        }
    ],
    "sg:phone":"+1 418 766 7094",
    "sg:postcode":"G5B 1E3",
    "sg:province":"QC",
    "sg:tags":[
        "trucking"
    ],
    "wof:name":"Transport Saguelac Inc",
    "wof:placetype":"venue"
},
  "geometry": {"coordinates":[-66.8302536011,50.0335083008],"type":"Point"}
}