{
  "type": "Feature",
  "properties": {
    "addr:full":"Scarborough ON M1B 3C6",
    "addr:postcode":"m1b 3c6",
    "iso:country":"CA",
    "sg:city":"Scarborough",
    "sg:classifiers":[
        {
            "category":"Social Services",
            "subcategory":"Job Training",
            "type":"Services"
        }
    ],
    "sg:phone":"+1 416 609 9622",
    "sg:postcode":"M1B 3C6",
    "sg:province":"ON",
    "sg:tags":[
        "employment"
    ],
    "wof:name":"Ymca",
    "wof:placetype":"venue"
},
  "geometry": {"coordinates":[-79.235527,43.789371],"type":"Point"}
}