{
  "type": "Feature",
  "properties": {
    "addr:full":"78 Maitland St Brantford ON N3S 6L3",
    "addr:housenumber":"78",
    "addr:postcode":"n3s 6l3",
    "addr:street":"Maitland St",
    "iso:country":"CA",
    "sg:address":"78 Maitland St",
    "sg:city":"Brantford",
    "sg:classifiers":[
        {
            "category":"Home & Garden",
            "subcategory":"Household Appliances",
            "type":"Retail Goods"
        }
    ],
    "sg:phone":"+1 519 753 2504",
    "sg:postcode":"N3S 6L3",
    "sg:province":"ON",
    "wof:name":"Gord's Pro Appliance Svc",
    "wof:placetype":"venue"
},
  "geometry": {"coordinates":[-80.246078,43.148266],"type":"Point"}
}