{
  "type": "Feature",
  "properties": {
    "addr:full":"624 Banner Ave North Bay ON P1A 1X8",
    "addr:housenumber":"624",
    "addr:postcode":"p1a 1x8",
    "addr:street":"Banner Ave",
    "iso:country":"CA",
    "sg:address":"624 Banner Ave",
    "sg:city":"North Bay",
    "sg:classifiers":[
        {
            "category":"Social Services",
            "type":"Services"
        }
    ],
    "sg:phone":"+1 705 472 4844",
    "sg:postcode":"P1A 1X8",
    "sg:province":"ON",
    "sg:tags":[
        "organization",
        "welfare"
    ],
    "wof:name":"Banner Residence",
    "wof:placetype":"venue"
},
  "geometry": {"coordinates":[-79.4427566528,46.2691993713],"type":"Point"}
}