{
  "type": "Feature",
  "properties": {
    "addr:full":"193 Eugene Rd North Bay ON P1B 8B8",
    "addr:housenumber":"193",
    "addr:postcode":"p1b 8b8",
    "addr:street":"Eugene Rd",
    "iso:country":"CA",
    "sg:address":"193 Eugene Rd",
    "sg:city":"North Bay",
    "sg:classifiers":[
        {
            "category":"Personal",
            "subcategory":"Beauty Salon",
            "type":"Services"
        }
    ],
    "sg:phone":"+1 705 472 0230",
    "sg:postcode":"P1B 8B8",
    "sg:province":"ON",
    "sg:tags":[
        "manicuring"
    ],
    "wof:name":"Mystique Nails",
    "wof:placetype":"venue"
},
  "geometry": {"coordinates":[-79.430305481,46.3275184631],"type":"Point"}
}