{
  "type": "Feature",
  "properties": {
    "addr:full":"1609 Av Saint-Nazaire Plessisville QC G6L 2J1",
    "addr:housenumber":"1609",
    "addr:postcode":"g6l 2j1",
    "addr:street":"Av Saint-Nazaire",
    "iso:country":"CA",
    "sg:address":"1609 Av Saint-Nazaire",
    "sg:city":"Plessisville",
    "sg:classifiers":[
        {
            "category":"Food & Beverages",
            "subcategory":"Groceries & Convenience Stores",
            "type":"Retail Goods"
        }
    ],
    "sg:phone":"+1 819 362 6269",
    "sg:postcode":"G6L 2J1",
    "sg:province":"QC",
    "sg:tags":[
        "grocer"
    ],
    "wof:name":"Epicerie Chez Ti-Mousse Enr",
    "wof:placetype":"venue"
},
  "geometry": {"coordinates":[-71.774467,46.219063],"type":"Point"}
}