{
  "type": "Feature",
  "properties": {
    "addr:full":"539 Prince St Truro NS B2N 1E8",
    "addr:housenumber":"539",
    "addr:postcode":"b2n 1e8",
    "addr:street":"Prince St",
    "iso:country":"CA",
    "sg:address":"539 Prince St",
    "sg:city":"Truro",
    "sg:classifiers":[
        {
            "category":"Health Services",
            "subcategory":"Doctor",
            "type":"Services"
        }
    ],
    "sg:phone":"+1 902 895 2882",
    "sg:postcode":"B2N 1E8",
    "sg:province":"NS",
    "sg:tags":[
        "dentist"
    ],
    "wof:name":"Mac Phee, Colin A DDS",
    "wof:placetype":"venue"
},
  "geometry": {"coordinates":[-63.2854347229,45.3657608032],"type":"Point"}
}