{
  "type": "Feature",
  "properties": {
    "addr:full":"8354 Boul Maurice-Duplessis Montreal QC H1E 3A3",
    "addr:housenumber":"8354",
    "addr:postcode":"h1e 3a3",
    "addr:street":"Boul Maurice-Duplessis",
    "iso:country":"CA",
    "sg:address":"8354 Boul Maurice-Duplessis",
    "sg:city":"Montreal",
    "sg:classifiers":[
        {
            "category":"Building & Trades",
            "subcategory":"Construction",
            "type":"Services"
        }
    ],
    "sg:phone":"+1 514 648 5063",
    "sg:postcode":"H1E 3A3",
    "sg:province":"QC",
    "sg:tags":[
        "downspouts",
        "gutter"
    ],
    "wof:name":"Renovation Pro Metal Enr",
    "wof:placetype":"venue"
},
  "geometry": {"coordinates":[-73.58363342289999,45.6356697083],"type":"Point"}
}