{
  "type": "Feature",
  "properties": {
    "addr:full":"1390 Boul Industriel Magog QC J1X 4V9",
    "addr:housenumber":"1390",
    "addr:postcode":"j1x 4v9",
    "addr:street":"Boul Industriel",
    "iso:country":"CA",
    "sg:address":"1390 Boul Industriel",
    "sg:city":"Magog",
    "sg:classifiers":[
        {
            "category":"Professional",
            "subcategory":"Business Services",
            "type":"Services"
        }
    ],
    "sg:phone":"+1 819 847 2925",
    "sg:postcode":"J1X 4V9",
    "sg:province":"QC",
    "sg:tags":[
        "water",
        "pump",
        "treatment"
    ],
    "wof:name":"H Fontaine Ltee",
    "wof:placetype":"venue"
},
  "geometry": {"coordinates":[-72.130714,45.272327],"type":"Point"}
}