{
  "type": "Feature",
  "properties": {
    "addr:full":"RR 1 Wellesley ON N0B 2T0",
    "addr:postcode":"n0b 2t0",
    "addr:street":"Rr 1",
    "iso:country":"CA",
    "sg:address":"RR 1",
    "sg:city":"Wellesley",
    "sg:classifiers":[
        {
            "category":"Building & Trades",
            "subcategory":"Construction",
            "type":"Services"
        }
    ],
    "sg:phone":"+1 519 656 2518",
    "sg:postcode":"N0B 2T0",
    "sg:province":"ON",
    "sg:tags":[
        "silo"
    ],
    "wof:name":"Country Thermal Gas",
    "wof:placetype":"venue"
},
  "geometry": {"coordinates":[-80.76454200000001,43.47665],"type":"Point"}
}