{
  "type": "Feature",
  "properties": {
    "addr:full":"Markham ON L3R 9X5",
    "addr:postcode":"l3r 9x5",
    "iso:country":"CA",
    "sg:city":"Markham",
    "sg:classifiers":[
        {
            "category":"Shopping",
            "type":"Retail Goods"
        }
    ],
    "sg:phone":"+1 905 940 8750",
    "sg:postcode":"L3R 9X5",
    "sg:province":"ON",
    "sg:tags":[
        "communication",
        "radio",
        "system",
        "cellular"
    ],
    "wof:name":"Go Wireless Inc",
    "wof:placetype":"venue"
},
  "geometry": {"coordinates":[-79.3264923096,43.8409233093],"type":"Point"}
}