{
  "type": "Feature",
  "properties": {
    "addr:full":"3956 Rue Ontario E Montreal QC H1W 1S9",
    "addr:housenumber":"3956",
    "addr:postcode":"h1w 1s9",
    "addr:street":"Rue Ontario E",
    "iso:country":"CA",
    "sg:address":"3956 Rue Ontario E",
    "sg:city":"Montreal",
    "sg:classifiers":[
        {
            "category":"Home & Garden",
            "subcategory":"Furniture",
            "type":"Retail Goods"
        }
    ],
    "sg:phone":"+1 514 526 0012",
    "sg:postcode":"H1W 1S9",
    "sg:province":"QC",
    "sg:tags":[
        "mattress",
        "futon"
    ],
    "wof:name":"Meubles Promenade Ontario",
    "wof:placetype":"venue"
},
  "geometry": {"coordinates":[-73.541763,45.549187],"type":"Point"}
}