{
  "type": "Feature",
  "properties": {
    "addr:full":"8 Second St Prescott ON K0E 1T0",
    "addr:housenumber":"8",
    "addr:postcode":"k0e 1t0",
    "addr:street":"Second St",
    "iso:country":"CA",
    "sg:address":"8 Second St",
    "sg:city":"Prescott",
    "sg:classifiers":[
        {
            "category":"Education",
            "subcategory":"School",
            "type":"Public Place"
        }
    ],
    "sg:phone":"+1 613 925 4183",
    "sg:postcode":"K0E 1T0",
    "sg:province":"ON",
    "wof:name":"South Edwardsburg Public Schl",
    "wof:placetype":"venue"
},
  "geometry": {"coordinates":[-75.518417,44.709419],"type":"Point"}
}