{
  "type": "Feature",
  "properties": {
    "addr:full":"441 Dewdney Ave Regina SK S4N 0G1",
    "addr:housenumber":"441",
    "addr:postcode":"s4n 0g1",
    "addr:street":"Dewdney Ave",
    "iso:country":"CA",
    "sg:address":"441 Dewdney Ave",
    "sg:city":"Regina",
    "sg:classifiers":[
        {
            "category":"Wholesale",
            "subcategory":"Machinery & Supplies",
            "type":"Manufacturing & Wholesale Goods"
        }
    ],
    "sg:phone":"+1 306 757 6775",
    "sg:postcode":"S4N 0G1",
    "sg:province":"SK",
    "sg:tags":[
        "belting"
    ],
    "wof:name":"B & T Rubber",
    "wof:placetype":"venue"
},
  "geometry": {"coordinates":[-104.587158,50.455021],"type":"Point"}
}