{
  "type": "Feature",
  "properties": {
    "addr:full":"Duncan BC V9L 3N9",
    "addr:postcode":"v9l 3n9",
    "iso:country":"CA",
    "sg:city":"Duncan",
    "sg:classifiers":[
        {
            "category":"Real Estate",
            "subcategory":"Real Estate Operator",
            "type":"Services"
        }
    ],
    "sg:phone":"+1 250 746 7241",
    "sg:postcode":"V9L 3N9",
    "sg:province":"BC",
    "sg:tags":[
        "apartment"
    ],
    "wof:name":"White House Apartments",
    "wof:placetype":"venue"
},
  "geometry": {"coordinates":[-123.696769714,48.7780303955],"type":"Point"}
}