{
  "type": "Feature",
  "properties": {
    "addr:full":"560 Conestoga Blvd Cambridge ON N1R 7P7",
    "addr:housenumber":"560",
    "addr:postcode":"n1r 7p7",
    "addr:street":"Conestoga Blvd",
    "iso:country":"CA",
    "sg:address":"560 Conestoga Blvd",
    "sg:city":"Cambridge",
    "sg:classifiers":[
        {
            "category":"Manufacturing",
            "subcategory":"Metals",
            "type":"Manufacturing & Wholesale Goods"
        }
    ],
    "sg:phone":"+1 519 621 7953",
    "sg:postcode":"N1R 7P7",
    "sg:province":"ON",
    "sg:tags":[
        "stamping"
    ],
    "wof:name":"A G Simpson CO Ltd",
    "wof:placetype":"venue"
},
  "geometry": {"coordinates":[-80.321854,43.40696],"type":"Point"}
}