{
  "type": "Feature",
  "properties": {
    "addr:full":"359 Coxwell Ave Toronto ON M4L 3B8",
    "addr:housenumber":"359",
    "addr:postcode":"m4l 3b8",
    "addr:street":"Coxwell Ave",
    "iso:country":"CA",
    "sg:address":"359 Coxwell Ave",
    "sg:city":"Toronto",
    "sg:classifiers":[
        {
            "category":"Retail",
            "subcategory":"Laundry & Dry Cleaning",
            "type":"Services"
        }
    ],
    "sg:phone":"+1 416 778 1693",
    "sg:postcode":"M4L 3B8",
    "sg:province":"ON",
    "sg:tags":[
        "cleaners"
    ],
    "wof:name":"Happy Cleaners",
    "wof:placetype":"venue"
},
  "geometry": {"coordinates":[-79.32019,43.675579],"type":"Point"}
}