{
  "type": "Feature",
  "properties": {
    "addr:full":"375 Industrial Dr Grand Forks BC V0H 1H0",
    "addr:housenumber":"375",
    "addr:postcode":"v0h 1h0",
    "addr:street":"Industrial Dr",
    "iso:country":"CA",
    "sg:address":"375 Industrial Dr",
    "sg:city":"Grand Forks",
    "sg:classifiers":[
        {
            "category":"Home & Garden",
            "subcategory":"Building Materials",
            "type":"Retail Goods"
        }
    ],
    "sg:phone":"+1 250 442 5507",
    "sg:postcode":"V0H 1H0",
    "sg:province":"BC",
    "sg:tags":[
        "truss"
    ],
    "wof:name":"Boundary Truss Inc",
    "wof:placetype":"venue"
},
  "geometry": {"coordinates":[-118.44326,49.032372],"type":"Point"}
}