{
  "type": "Feature",
  "properties": {
    "addr:full":"545 17 St SW Medicine Hat AB T1A 7W5",
    "addr:postcode":"545 17;t1a 7w5",
    "addr:street":"St Sw",
    "iso:country":"CA",
    "sg:address":"545 17 St SW",
    "sg:city":"Medicine Hat",
    "sg:classifiers":[
        {
            "category":"Home & Garden",
            "subcategory":"Building Materials",
            "type":"Retail Goods"
        }
    ],
    "sg:phone":"+1 403 526 6854",
    "sg:postcode":"T1A 7W5",
    "sg:province":"AB",
    "wof:name":"Windsor Plywood",
    "wof:placetype":"venue"
},
  "geometry": {"coordinates":[-110.699157715,50.0232925415],"type":"Point"}
}