{
  "type": "Feature",
  "properties": {
    "addr:full":"Victoria BC V8W 2B7",
    "addr:postcode":"v8w 2b7",
    "iso:country":"CA",
    "sg:city":"Victoria",
    "sg:classifiers":[
        {
            "category":"Professional",
            "subcategory":"Lawyer & Legal Services",
            "type":"Services"
        }
    ],
    "sg:phone":"+1 250 385 1383",
    "sg:postcode":"V8W 2B7",
    "sg:province":"BC",
    "sg:tags":[
        "attorney"
    ],
    "wof:name":"Salomon, Charlotte A",
    "wof:placetype":"venue"
},
  "geometry": {"coordinates":[-123.365921,48.422859],"type":"Point"}
}