{
  "type": "Feature",
  "properties": {
    "iso:country":"CA",
    "sg:address":"147 Rue Principale",
    "sg:city":"Saint-Cyprien",
    "sg:classifiers":[
        {
            "category":"Wholesale",
            "subcategory":"Meat",
            "type":"Manufacturing & Wholesale Goods"
        }
    ],
    "sg:phone":"+1 418 963 2255",
    "sg:postcode":"G0L 2P0",
    "sg:province":"QC",
    "sg:tags":[
        "grocer",
        "butchering"
    ],
    "wof:name":"Alimentation Dgc Caillouette",
    "wof:placetype":"venue"
},
  "geometry": {"coordinates":[-69.0207824707,47.8970375061],"type":"Point"}
}