{
  "type": "Feature",
  "properties": {
    "iso:country":"CA",
    "sg:address":"601 Aikins St",
    "sg:city":"Winnipeg",
    "sg:classifiers":[
        {
            "category":"Recreation",
            "type":"Entertainment"
        }
    ],
    "sg:phone":"+1 204 986 5518",
    "sg:postcode":"R2W 4J5",
    "sg:province":"MB",
    "sg:tags":[
        "center",
        "government"
    ],
    "wof:name":"Winnipeg St John's Leisure Ctr",
    "wof:placetype":"venue"
},
  "geometry": {"coordinates":[-97.1267166138,49.929977417],"type":"Point"}
}