{
  "type": "Feature",
  "properties": {
    "addr:full":"19 Britannia Ave Toronto ON M6N 3T6",
    "addr:housenumber":"19",
    "addr:postcode":"m6n 3t6",
    "addr:street":"Britannia Ave",
    "iso:country":"CA",
    "sg:address":"19 Britannia Ave",
    "sg:city":"Toronto",
    "sg:classifiers":[
        {
            "category":"Professional",
            "subcategory":"Business Services",
            "type":"Services"
        }
    ],
    "sg:phone":"+1 416 948 9025",
    "sg:postcode":"M6N 3T6",
    "sg:province":"ON",
    "sg:tags":[
        "packaging"
    ],
    "wof:name":"Straightway Equipment Svc",
    "wof:placetype":"venue"
},
  "geometry": {"coordinates":[-79.480728,43.669937],"type":"Point"}
}