{
  "type": "Feature",
  "properties": {
    "addr:full":"1466 5E Av Shawinigan-Sud QC G9P 1M3",
    "addr:housenumber":"1466",
    "addr:postcode":"g9p 1m3",
    "addr:street":"5E Av Shawinigan-Sud",
    "iso:country":"CA",
    "sg:address":"1466 5E Av",
    "sg:city":"Shawinigan-Sud",
    "sg:classifiers":[
        {
            "category":"Retail",
            "subcategory":"Auto Repair",
            "type":"Services"
        }
    ],
    "sg:phone":"+1 819 537 6687",
    "sg:postcode":"G9P 1M3",
    "sg:province":"QC",
    "sg:tags":[
        "repairing",
        "automobile",
        "tire"
    ],
    "wof:name":"Alignement Patenaude Inc",
    "wof:placetype":"venue"
},
  "geometry": {"coordinates":[-72.7498931885,46.523059845],"type":"Point"}
}