{
  "type": "Feature",
  "properties": {
    "addr:full":"3008 Maplewood Crt Coquitlam BC V3E 3P3",
    "addr:housenumber":"3008",
    "addr:postcode":"v3e 3p3",
    "addr:street":"Maplewood Crt",
    "iso:country":"CA",
    "sg:address":"3008 Maplewood Crt",
    "sg:city":"Coquitlam",
    "sg:classifiers":[
        {
            "category":"Retail",
            "subcategory":"Repair Shop",
            "type":"Services"
        }
    ],
    "sg:phone":"+1 604 468 2340",
    "sg:postcode":"V3E 3P3",
    "sg:province":"BC",
    "sg:tags":[
        "refinishing",
        "furniture"
    ],
    "wof:name":"Leather Doctor",
    "wof:placetype":"venue"
},
  "geometry": {"coordinates":[-122.793128967,49.3054504395],"type":"Point"}
}