{
  "type": "Feature",
  "properties": {
    "addr:full":"41 Kennings Cres Red Deer AB T4P 3M8",
    "addr:housenumber":"41",
    "addr:postcode":"t4p 3m8",
    "addr:street":"Kennings Cres",
    "iso:country":"CA",
    "sg:address":"41 Kennings Cres",
    "sg:city":"Red Deer",
    "sg:classifiers":[
        {
            "category":"Professional",
            "subcategory":"Business Services",
            "type":"Services"
        }
    ],
    "sg:phone":"+1 403 347 5749",
    "sg:postcode":"T4P 3M8",
    "sg:province":"AB",
    "sg:tags":[
        "auctioneer"
    ],
    "wof:name":"Rick Horn Auctions",
    "wof:placetype":"venue"
},
  "geometry": {"coordinates":[-113.819885,52.308472],"type":"Point"}
}