{
  "type": "Feature",
  "properties": {
    "addr:full":"70 Av Des Terrasses Laval QC H7H 1S8",
    "addr:postcode":"h7h 1s8",
    "addr:street":"70 Av Des Terrasses",
    "iso:country":"CA",
    "sg:address":"70 Av Des Terrasses",
    "sg:city":"Laval",
    "sg:classifiers":[
        {
            "category":"Home & Garden",
            "subcategory":"Garden Supply",
            "type":"Retail Goods"
        }
    ],
    "sg:phone":"+1 450 622 2746",
    "sg:postcode":"H7H 1S8",
    "sg:province":"QC",
    "sg:tags":[
        "nurseryman"
    ],
    "wof:name":"Pepiniere Des Terrasses",
    "wof:placetype":"venue"
},
  "geometry": {"coordinates":[-73.7733535767,45.6283798218],"type":"Point"}
}