{
  "type": "Feature",
  "properties": {
    "iso:country":"CA",
    "sg:address":"150 Tapscott Rd",
    "sg:city":"Scarborough",
    "sg:classifiers":[
        {
            "category":"Education",
            "subcategory":"School",
            "type":"Public Place"
        }
    ],
    "sg:phone":"+1 416 396 5892",
    "sg:postcode":"M1B 2L2",
    "sg:province":"ON",
    "wof:name":"Lester B Pearson Collegiate",
    "wof:placetype":"venue"
},
  "geometry": {"coordinates":[-79.224899292,43.8043670654],"type":"Point"}
}