{
  "type": "Feature",
  "properties": {
    "addr:full":"4015 Boul Saint-Laurent Montreal QC H2W 1Y4",
    "addr:housenumber":"4015",
    "addr:postcode":"h2w 1y4",
    "addr:street":"Boul Saint-Laurent",
    "iso:country":"CA",
    "sg:address":"4015 Boul Saint-Laurent",
    "sg:city":"Montreal",
    "sg:classifiers":[
        {
            "category":"Cinema",
            "subcategory":"Movie Theater",
            "type":"Entertainment"
        }
    ],
    "sg:phone":"+1 514 849 6227",
    "sg:postcode":"H2W 1Y4",
    "sg:province":"QC",
    "sg:tags":[
        "leasing",
        "video",
        "tape"
    ],
    "wof:name":"Cinema L'Amour-Xxx",
    "wof:placetype":"venue"
},
  "geometry": {"coordinates":[-73.578812,45.516888],"type":"Point"}
}