{
  "type": "Feature",
  "properties": {
    "addr:full":"2057 Dufferin St York ON M6E 3R3",
    "addr:housenumber":"2057",
    "addr:postcode":"m6e 3r3",
    "addr:street":"Dufferin St",
    "iso:country":"CA",
    "sg:address":"2057 Dufferin St",
    "sg:city":"York",
    "sg:classifiers":[
        {
            "category":"Food & Beverages",
            "subcategory":"Bakery",
            "type":"Retail Goods"
        }
    ],
    "sg:phone":"+1 416 656 0967",
    "sg:postcode":"M6E 3R3",
    "sg:province":"ON",
    "sg:tags":[
        "baker"
    ],
    "wof:name":"Nova Onda Churrasqueira & Bkry",
    "wof:placetype":"venue"
},
  "geometry": {"coordinates":[-79.446404,43.68671],"type":"Point"}
}