{
  "type": "Feature",
  "properties": {
    "addr:full":"10 Industrial Dr Sylvan Lake AB T4S 1P4",
    "addr:housenumber":"10",
    "addr:postcode":"t4s 1p4",
    "addr:street":"Industrial Dr",
    "iso:country":"CA",
    "sg:address":"10 Industrial Dr",
    "sg:city":"Sylvan Lake",
    "sg:classifiers":[
        {
            "category":"Retail",
            "subcategory":"Auto Repair",
            "type":"Services"
        }
    ],
    "sg:phone":"+1 403 887 2262",
    "sg:postcode":"T4S 1P4",
    "sg:province":"AB",
    "sg:tags":[
        "body",
        "automobile",
        "painting"
    ],
    "wof:name":"B & T Auto Body",
    "wof:placetype":"venue"
},
  "geometry": {"coordinates":[-114.071495,52.313267],"type":"Point"}
}