{
  "type": "Feature",
  "properties": {
    "addr:full":"102 Metcalfe St Elora ON N0B 1S0",
    "addr:housenumber":"102",
    "addr:postcode":"n0b 1s0",
    "addr:street":"Metcalfe St",
    "iso:country":"CA",
    "sg:address":"102 Metcalfe St",
    "sg:city":"Elora",
    "sg:classifiers":[
        {
            "category":"Shopping",
            "subcategory":"Gifts & Souvenirs",
            "type":"Retail Goods"
        }
    ],
    "sg:phone":"+1 519 846 8826",
    "sg:postcode":"N0B 1S0",
    "sg:province":"ON",
    "sg:tags":[
        "shop"
    ],
    "wof:name":"Wilde Thyme",
    "wof:placetype":"venue"
},
  "geometry": {"coordinates":[-80.4300994873,43.6822471619],"type":"Point"}
}