{
  "type": "Feature",
  "properties": {
    "addr:full":"PO Box 4057 STN Main Spruce Grove AB T7X 3B3",
    "addr:housenumber":"po",
    "addr:postcode":"4057;t7x 3b3",
    "addr:street":"Box;Stn Main",
    "iso:country":"CA",
    "sg:address":"PO Box 4057 STN Main",
    "sg:city":"Spruce Grove",
    "sg:classifiers":[
        {
            "category":"Building & Trades",
            "subcategory":"Construction",
            "type":"Services"
        }
    ],
    "sg:phone":"+1 780 962 3544",
    "sg:postcode":"T7X 3B3",
    "sg:province":"AB",
    "sg:tags":[
        "sewer",
        "contractor"
    ],
    "wof:name":"G S Holdings CO Ltd",
    "wof:placetype":"venue"
},
  "geometry": {"coordinates":[-113.901855469,53.5446357727],"type":"Point"}
}