{
  "type": "Feature",
  "properties": {
    "addr:full":"51 Breithaupt St Kitchener ON N2H 5G5",
    "addr:housenumber":"51",
    "addr:postcode":"n2h 5g5",
    "addr:street":"Breithaupt St",
    "iso:country":"CA",
    "sg:address":"51 Breithaupt St",
    "sg:city":"Kitchener",
    "sg:classifiers":[
        {
            "category":"Manufacturing",
            "subcategory":"Rubber & Plastics",
            "type":"Manufacturing & Wholesale Goods"
        }
    ],
    "sg:phone":"+1 519 579 1280",
    "sg:postcode":"N2H 5G5",
    "sg:province":"ON",
    "sg:tags":[
        "product"
    ],
    "wof:name":"Collins & Aikman",
    "wof:placetype":"venue"
},
  "geometry": {"coordinates":[-80.498817,43.454433],"type":"Point"}
}