{
  "type": "Feature",
  "properties": {
    "addr:full":"4 Rue Halle Sainte-Helene-DE-Breakeyville QC G0S 1E1",
    "addr:housenumber":"4",
    "addr:postcode":"g0s 1e1",
    "addr:street":"Rue Halle Sainte-Helene-De-Breakeyville",
    "iso:country":"CA",
    "sg:address":"4 Rue Halle",
    "sg:city":"Sainte-Helene-DE-Breakeyville",
    "sg:classifiers":[
        {
            "category":"Professional",
            "subcategory":"Computer Services",
            "type":"Services"
        }
    ],
    "sg:phone":"+1 418 832 5287",
    "sg:postcode":"G0S 1E1",
    "sg:province":"QC",
    "sg:tags":[
        "repair",
        "dealer",
        "equipment"
    ],
    "wof:name":"Techno-Info Enr",
    "wof:placetype":"venue"
},
  "geometry": {"coordinates":[-71.23686218260001,46.6905441284],"type":"Point"}
}