{
  "type": "Feature",
  "properties": {
    "addr:full":"129 Arran St Campbellton NB E3N 1M1",
    "addr:housenumber":"129",
    "addr:postcode":"e3n 1m1",
    "addr:street":"Arran St",
    "iso:country":"CA",
    "sg:address":"129 Arran St",
    "sg:city":"Campbellton",
    "sg:classifiers":[
        {
            "category":"Social Services",
            "type":"Services"
        }
    ],
    "sg:phone":"+1 506 753 4584",
    "sg:postcode":"E3N 1M1",
    "sg:province":"NB",
    "sg:tags":[
        "senior",
        "citizen"
    ],
    "wof:name":"Centre DE L'Amitie",
    "wof:placetype":"venue"
},
  "geometry": {"coordinates":[-66.678909,48.000359],"type":"Point"}
}