{
  "type": "Feature",
  "properties": {
    "addr:full":"452 Clareview Rd NW Edmonton AB T5A 4G6",
    "addr:housenumber":"452",
    "addr:postcode":"t5a 4g6",
    "addr:street":"Clareview Rd Nw",
    "iso:country":"CA",
    "sg:address":"452 Clareview Rd NW",
    "sg:city":"Edmonton",
    "sg:classifiers":[
        {
            "category":"Professional",
            "subcategory":"Computer Services",
            "type":"Services"
        }
    ],
    "sg:phone":"+1 780 413 7599",
    "sg:postcode":"T5A 4G6",
    "sg:province":"AB",
    "sg:tags":[
        "consultant"
    ],
    "wof:name":"Pixview",
    "wof:placetype":"venue"
},
  "geometry": {"coordinates":[-113.384498596,53.5926132202],"type":"Point"}
}