{
  "type": "Feature",
  "properties": {
    "addr:full":"5501 52 Ave Camrose AB T4V 0X7",
    "addr:housenumber":"5501",
    "addr:postcode":"t4v 0x7",
    "addr:street":"52 Ave",
    "iso:country":"CA",
    "sg:address":"5501 52 Ave",
    "sg:city":"Camrose",
    "sg:classifiers":[
        {
            "category":"Wholesale",
            "subcategory":"Scrap",
            "type":"Manufacturing & Wholesale Goods"
        }
    ],
    "sg:phone":"+1 780 672 4507",
    "sg:postcode":"T4V 0X7",
    "sg:province":"AB",
    "sg:tags":[
        "recycling",
        "can",
        "bottle",
        "depot"
    ],
    "wof:name":"Universal Bottle Depot",
    "wof:placetype":"venue"
},
  "geometry": {"coordinates":[-112.83440400000001,53.025784],"type":"Point"}
}