{
  "type": "Feature",
  "properties": {
    "addr:full":"2 Rue Du Buisson Pont-Rouge QC G3H 1X8",
    "addr:housenumber":"2",
    "addr:postcode":"g3h 1x8",
    "addr:street":"Rue Du Buisson",
    "iso:country":"CA",
    "sg:address":"2 Rue Du Buisson",
    "sg:city":"Pont-Rouge",
    "sg:classifiers":[
        {
            "category":"Professional",
            "subcategory":"Accounting & Tax Preparation",
            "type":"Services"
        }
    ],
    "sg:phone":"+1 418 873 4230",
    "sg:postcode":"G3H 1X8",
    "sg:province":"QC",
    "sg:tags":[
        "accountant"
    ],
    "wof:name":"Hardy, Jean Pierre",
    "wof:placetype":"venue"
},
  "geometry": {"coordinates":[-71.68798099999999,46.751263],"type":"Point"}
}