{
  "type": "Feature",
  "properties": {
    "iso:country":"CA",
    "sg:address":"1932 Ambassador Dr",
    "sg:city":"Windsor",
    "sg:classifiers":[
        {
            "category":"Professional",
            "subcategory":"Lawyer & Legal Services",
            "type":"Services"
        }
    ],
    "sg:phone":"+1 519 250 5138",
    "sg:postcode":"N9C 3R3",
    "sg:province":"ON",
    "sg:tags":[
        "naturalization",
        "immigration"
    ],
    "wof:name":"E Z Publications",
    "wof:placetype":"venue"
},
  "geometry": {"coordinates":[-83.055618,42.27985],"type":"Point"}
}