{
  "type": "Feature",
  "properties": {
    "addr:full":"778 Route 655 Waasis NB E3B 8V5",
    "addr:housenumber":"778",
    "addr:postcode":"e3b 8v5",
    "addr:street":"Route 655",
    "iso:country":"CA",
    "sg:address":"778 Route 655",
    "sg:city":"Waasis",
    "sg:classifiers":[
        {
            "category":"Retail",
            "subcategory":"Repair Shop",
            "type":"Services"
        }
    ],
    "sg:phone":"+1 506 446 4484",
    "sg:postcode":"E3B 8V5",
    "sg:province":"NB",
    "sg:tags":[
        "equipment",
        "electronic",
        "supply"
    ],
    "wof:name":"Mac Electronics",
    "wof:placetype":"venue"
},
  "geometry": {"coordinates":[-66.578636,45.828972],"type":"Point"}
}