{
  "type": "Feature",
  "properties": {
    "iso:country":"CA",
    "sg:city":"Burlington",
    "sg:classifiers":[
        {
            "category":"Food & Beverages",
            "subcategory":"Groceries & Convenience Stores",
            "type":"Retail Goods"
        }
    ],
    "sg:phone":"+1 905 637 3599",
    "sg:postcode":"L7L 1V2",
    "sg:province":"ON",
    "sg:tags":[
        "grocer"
    ],
    "wof:name":"Any Time Convenience",
    "wof:placetype":"venue"
},
  "geometry": {"coordinates":[-79.751724,43.36911],"type":"Point"}
}