{
  "type": "Feature",
  "properties": {
    "addr:full":"10425 Resthaven Dr Sidney BC V8L 3H4",
    "addr:housenumber":"10425",
    "addr:postcode":"v8l 3h4",
    "addr:street":"Resthaven Dr",
    "iso:country":"CA",
    "sg:address":"10425 Resthaven Dr",
    "sg:city":"Sidney",
    "sg:classifiers":[
        {
            "category":"Food & Beverages",
            "subcategory":"Groceries & Convenience Stores",
            "type":"Retail Goods"
        }
    ],
    "sg:phone":"+1 250 656 1140",
    "sg:postcode":"V8L 3H4",
    "sg:province":"BC",
    "sg:tags":[
        "grocer"
    ],
    "wof:name":"Resthaven Store",
    "wof:placetype":"venue"
},
  "geometry": {"coordinates":[-123.40846999999999,48.665073],"type":"Point"}
}