{
  "type": "Feature",
  "properties": {
    "addr:full":"5445 Boul Henri-Bourassa O Saint-Laurent QC H4R 1B7",
    "addr:housenumber":"5445",
    "addr:postcode":"h4r 1b7",
    "addr:street":"Boul Henri-Bourassa O",
    "iso:country":"CA",
    "sg:address":"5445 Boul Henri-Bourassa O",
    "sg:city":"Saint-Laurent",
    "sg:classifiers":[
        {
            "category":"Professional",
            "subcategory":"Computer Services",
            "type":"Services"
        }
    ],
    "sg:phone":"+1 514 334 4535",
    "sg:postcode":"H4R 1B7",
    "sg:province":"QC",
    "sg:tags":[
        "information",
        "system",
        "consultant"
    ],
    "wof:name":"Innologix",
    "wof:placetype":"venue"
},
  "geometry": {"coordinates":[-73.7125167847,45.5195846558],"type":"Point"}
}