{
  "type": "Feature",
  "properties": {
    "addr:full":"50 Alice St Waterford ON N0E 1Y0",
    "addr:housenumber":"50",
    "addr:postcode":"n0e 1y0",
    "addr:street":"Alice St",
    "iso:country":"CA",
    "sg:address":"50 Alice St",
    "sg:city":"Waterford",
    "sg:classifiers":[
        {
            "category":"Personal",
            "type":"Services"
        }
    ],
    "sg:phone":"+1 519 443 8118",
    "sg:postcode":"N0E 1Y0",
    "sg:province":"ON",
    "sg:tags":[
        "therapist",
        "massage"
    ],
    "wof:name":"Waterford Massage Therapy",
    "wof:placetype":"venue"
},
  "geometry": {"coordinates":[-80.29291499999999,42.934322],"type":"Point"}
}