{
  "type": "Feature",
  "properties": {
    "addr:full":"Saint-Pie QC J0H 1W0",
    "addr:postcode":"j0h 1w0",
    "iso:country":"CA",
    "sg:city":"Saint-Pie",
    "sg:classifiers":[
        {
            "category":"Real Estate",
            "subcategory":"Surveying",
            "type":"Services"
        }
    ],
    "sg:phone":"+1 450 771 9358",
    "sg:postcode":"J0H 1W0",
    "sg:province":"QC",
    "sg:tags":[
        "surveyor"
    ],
    "wof:name":"Bruno Ravenelle",
    "wof:placetype":"venue"
},
  "geometry": {"coordinates":[-72.90329699999999,45.501392],"type":"Point"}
}