{
  "type": "Feature",
  "properties": {
    "addr:full":"Okanagan Centre BC V4V 2J5",
    "addr:postcode":"v4v 2j5",
    "iso:country":"CA",
    "sg:city":"Okanagan Centre",
    "sg:classifiers":[
        {
            "category":"Utilities",
            "subcategory":"Water",
            "type":"Services"
        }
    ],
    "sg:phone":"+1 250 766 4486",
    "sg:postcode":"V4V 2J5",
    "sg:province":"BC",
    "sg:tags":[
        "company",
        "sewage"
    ],
    "wof:name":"Alto Utilities",
    "wof:placetype":"venue"
},
  "geometry": {"coordinates":[-119.45098114,50.0464019775],"type":"Point"}
}