{
  "type": "Feature",
  "properties": {
    "addr:full":"Nanaimo BC V9R 5N9",
    "addr:postcode":"v9r 5n9",
    "iso:country":"CA",
    "sg:city":"Nanaimo",
    "sg:classifiers":[
        {
            "category":"Social Services",
            "type":"Services"
        }
    ],
    "sg:phone":"+1 250 753 0999",
    "sg:postcode":"V9R 5N9",
    "sg:province":"BC",
    "sg:tags":[
        "organization",
        "welfare"
    ],
    "wof:name":"Island Deaf & Hard of Hearing",
    "wof:placetype":"venue"
},
  "geometry": {"coordinates":[-123.93486023,49.1604042053],"type":"Point"}
}