{
  "type": "Feature",
  "properties": {
    "addr:full":"175 Brentcliffe Rd East York ON M4G 3Z1",
    "addr:housenumber":"175",
    "addr:postcode":"m4g 3z1",
    "addr:street":"Brentcliffe Rd",
    "iso:country":"CA",
    "sg:address":"175 Brentcliffe Rd",
    "sg:city":"East York",
    "sg:classifiers":[
        {
            "category":"Social Services",
            "subcategory":"Job Training",
            "type":"Services"
        }
    ],
    "sg:phone":"+1 416 425 3930",
    "sg:postcode":"M4G 3Z1",
    "sg:province":"ON",
    "sg:tags":[
        "rehabilitation"
    ],
    "wof:name":"Centre For Addiction & Mental",
    "wof:placetype":"venue"
},
  "geometry": {"coordinates":[-79.36566925050001,43.7189407349],"type":"Point"}
}