{
  "type": "Feature",
  "properties": {
    "iso:country":"CA",
    "sg:address":"14019 Deer Ridge Dr SE",
    "sg:city":"Calgary",
    "sg:classifiers":[
        {
            "category":"Building & Trades",
            "subcategory":"Cleaning & Sanitation",
            "type":"Services"
        }
    ],
    "sg:phone":"+1 403 271 3616",
    "sg:postcode":"T2J 5R5",
    "sg:province":"AB",
    "sg:tags":[
        "janitor"
    ],
    "wof:name":"Norma Janitorial Svc",
    "wof:placetype":"venue"
},
  "geometry": {"coordinates":[-114.015914917,50.9284934998],"type":"Point"}
}