{
  "type": "Feature",
  "properties": {
    "addr:full":"35 Nanaimo River Rd Nanaimo BC V9X 1S5",
    "addr:housenumber":"35",
    "addr:postcode":"v9x 1s5",
    "addr:street":"Nanaimo River Rd",
    "iso:country":"CA",
    "sg:address":"35 Nanaimo River Rd",
    "sg:city":"Nanaimo",
    "sg:classifiers":[
        {
            "category":"Recreation",
            "type":"Entertainment"
        }
    ],
    "sg:phone":"+1 250 716 7874",
    "sg:postcode":"V9X 1S5",
    "sg:province":"BC",
    "sg:tags":[
        "center"
    ],
    "wof:name":"Bungy Zone",
    "wof:placetype":"venue"
},
  "geometry": {"coordinates":[-123.936157227,49.1642684937],"type":"Point"}
}