{
  "type": "Feature",
  "properties": {
    "addr:full":"5673 Main St Osgoode ON K0A 2W0",
    "addr:housenumber":"5673",
    "addr:postcode":"k0a 2w0",
    "addr:street":"Main St",
    "iso:country":"CA",
    "sg:address":"5673 Main St",
    "sg:city":"Osgoode",
    "sg:classifiers":[
        {
            "category":"Professional",
            "subcategory":"Accounting & Tax Preparation",
            "type":"Services"
        }
    ],
    "sg:phone":"+1 613 826 0862",
    "sg:postcode":"K0A 2W0",
    "sg:province":"ON",
    "sg:tags":[
        "accountant"
    ],
    "wof:name":"Thomson & CO",
    "wof:placetype":"venue"
},
  "geometry": {"coordinates":[-75.60092899999999,45.148819],"type":"Point"}
}