{
  "type": "Feature",
  "properties": {
    "iso:country":"CA",
    "sg:address":"300 Clarence St",
    "sg:city":"Brampton",
    "sg:classifiers":[
        {
            "category":"Wholesale",
            "subcategory":"Electrical",
            "type":"Manufacturing & Wholesale Goods"
        }
    ],
    "sg:phone":"+1 905 459 3321",
    "sg:postcode":"L6W 1T5",
    "sg:province":"ON",
    "sg:tags":[
        "generator"
    ],
    "wof:name":"Aggreko Inc",
    "wof:placetype":"venue"
},
  "geometry": {"coordinates":[-79.7315292358,43.6918258667],"type":"Point"}
}