{
  "type": "Feature",
  "properties": {
    "addr:full":"1308 5th Ave E Prince Albert SK S6V 2H7",
    "addr:housenumber":"1308",
    "addr:postcode":"s6v 2h7",
    "addr:street":"5Th Ave E",
    "iso:country":"CA",
    "sg:address":"1308 5th Ave E",
    "sg:city":"Prince Albert",
    "sg:classifiers":[
        {
            "category":"Real Estate",
            "subcategory":"Developer",
            "type":"Services"
        }
    ],
    "sg:phone":"+1 306 763 2455",
    "sg:postcode":"S6V 2H7",
    "sg:province":"SK",
    "sg:tags":[
        "cemetery"
    ],
    "wof:name":"St Mary's Cemetery",
    "wof:placetype":"venue"
},
  "geometry": {"coordinates":[-105.77315521200001,53.2173538208],"type":"Point"}
}