{
  "type": "Feature",
  "properties": {
    "addr:full":"650 Grande Allee E Quebec QC G1R 2K5",
    "addr:housenumber":"650",
    "addr:postcode":"g1r 2k5",
    "addr:street":"Grande Allee E",
    "iso:country":"CA",
    "sg:address":"650 Grande Allee E",
    "sg:city":"Quebec",
    "sg:classifiers":[
        {
            "category":"Restaurant",
            "type":"Food & Drink"
        }
    ],
    "sg:phone":"+1 418 529 9461",
    "sg:postcode":"G1R 2K5",
    "sg:province":"QC",
    "wof:name":"Restaurant Aux Vieux Canons",
    "wof:placetype":"venue"
},
  "geometry": {"coordinates":[-71.216331,46.806633],"type":"Point"}
}