{
  "type": "Feature",
  "properties": {
    "addr:full":"70 Grosvenor St Southampton ON N0H 2L0",
    "addr:housenumber":"70",
    "addr:postcode":"n0h 2l0",
    "addr:street":"Grosvenor St",
    "iso:country":"CA",
    "sg:address":"70 Grosvenor St",
    "sg:city":"Southampton",
    "sg:classifiers":[
        {
            "category":"Manufacturing",
            "subcategory":"Signs",
            "type":"Manufacturing & Wholesale Goods"
        }
    ],
    "sg:phone":"+1 519 797 5164",
    "sg:postcode":"N0H 2L0",
    "sg:province":"ON",
    "wof:name":"G W Signs",
    "wof:placetype":"venue"
},
  "geometry": {"coordinates":[-81.371544,44.498734],"type":"Point"}
}