{
  "type": "Feature",
  "properties": {
    "addr:full":"Campbell River BC V9W 2C7",
    "addr:postcode":"v9w 2c7",
    "iso:country":"CA",
    "sg:city":"Campbell River",
    "sg:classifiers":[
        {
            "category":"Shopping",
            "subcategory":"Clothing, Apparel, & Fashions",
            "type":"Retail Goods"
        }
    ],
    "sg:phone":"+1 250 287 7223",
    "sg:postcode":"V9W 2C7",
    "sg:province":"BC",
    "wof:name":"Suzanne's",
    "wof:placetype":"venue"
},
  "geometry": {"coordinates":[-125.245178223,50.0276679993],"type":"Point"}
}