{
  "type": "Feature",
  "properties": {
    "iso:country":"CA",
    "sg:city":"Saint-Jerome",
    "sg:classifiers":[
        {
            "category":"Health Services",
            "subcategory":"Health Practitioner",
            "type":"Services"
        }
    ],
    "sg:phone":"+1 450 432 1620",
    "sg:postcode":"J7Z 7E2",
    "sg:province":"QC",
    "sg:tags":[
        "psychologist"
    ],
    "wof:name":"Gaydos, Sylvie",
    "wof:placetype":"venue"
},
  "geometry": {"coordinates":[-74.00049591059999,45.7677764893],"type":"Point"}
}