{
  "type": "Feature",
  "properties": {
    "addr:full":"652 Lorne Ave E Stratford ON N5A 6S5",
    "addr:housenumber":"652",
    "addr:postcode":"n5a 6s5",
    "addr:street":"Lorne Ave E",
    "iso:country":"CA",
    "sg:address":"652 Lorne Ave E",
    "sg:city":"Stratford",
    "sg:classifiers":[
        {
            "category":"Autos & Motor Vehicles",
            "subcategory":"Automobile Sales",
            "type":"Retail Goods"
        }
    ],
    "sg:phone":"+1 519 273 0597",
    "sg:postcode":"N5A 6S5",
    "sg:province":"ON",
    "sg:tags":[
        "car",
        "dealer"
    ],
    "wof:name":"Art Marshall Motors",
    "wof:placetype":"venue"
},
  "geometry": {"coordinates":[-80.967979,43.352974],"type":"Point"}
}