{
  "type": "Feature",
  "properties": {
    "addr:full":"1972 Kipling Ave Etobicoke ON M9W 4J5",
    "addr:housenumber":"1972",
    "addr:postcode":"m9w 4j5",
    "addr:street":"Kipling Ave",
    "iso:country":"CA",
    "sg:address":"1972 Kipling Ave",
    "sg:city":"Etobicoke",
    "sg:classifiers":[
        {
            "category":"Retail",
            "subcategory":"Veterinary Services",
            "type":"Services"
        }
    ],
    "sg:phone":"+1 416 745 4700",
    "sg:postcode":"M9W 4J5",
    "sg:province":"ON",
    "sg:tags":[
        "veterinarian"
    ],
    "wof:name":"Etobicoke Veterinary Hospital",
    "wof:placetype":"venue"
},
  "geometry": {"coordinates":[-79.56530761720001,43.7083435059],"type":"Point"}
}