{
  "type": "Feature",
  "properties": {
    "addr:full":"24 Bruce St S Thornbury ON N0H 2P0",
    "addr:housenumber":"24",
    "addr:postcode":"n0h 2p0",
    "addr:street":"Bruce St S",
    "iso:country":"CA",
    "sg:address":"24 Bruce St S",
    "sg:city":"Thornbury",
    "sg:classifiers":[
        {
            "category":"Real Estate",
            "subcategory":"Real Estate Agent",
            "type":"Services"
        }
    ],
    "sg:phone":"+1 519 599 2136",
    "sg:postcode":"N0H 2P0",
    "sg:province":"ON",
    "wof:name":"Royal Lepage Locations North",
    "wof:placetype":"venue"
},
  "geometry": {"coordinates":[-80.4535980225,44.5615005493],"type":"Point"}
}