{
  "type": "Feature",
  "properties": {
    "addr:full":"24 Simmonds Dr # 1 Dartmouth NS B3B 1R3",
    "addr:housenumber":"24",
    "addr:postcode":"b3b 1r3",
    "addr:street":"Simmonds Dr # 1",
    "iso:country":"CA",
    "sg:address":"24 Simmonds Dr # 1",
    "sg:city":"Dartmouth",
    "sg:classifiers":[
        {
            "category":"Manufacturing",
            "subcategory":"Chemicals & Compounds",
            "type":"Manufacturing & Wholesale Goods"
        }
    ],
    "sg:phone":"+1 902 468 5868",
    "sg:postcode":"B3B 1R3",
    "sg:province":"NS",
    "sg:tags":[
        "treating",
        "heat",
        "metal"
    ],
    "wof:name":"Cooperheat-Mqs Canada Inc",
    "wof:placetype":"venue"
},
  "geometry": {"coordinates":[-63.596851,44.714817],"type":"Point"}
}