{
  "type": "Feature",
  "properties": {
    "addr:full":"814 2nd St W Cornwall ON K6J 1H6",
    "addr:housenumber":"814",
    "addr:postcode":"k6j 1h6",
    "addr:street":"2Nd St W",
    "iso:country":"CA",
    "sg:address":"814 2nd St W",
    "sg:city":"Cornwall",
    "sg:classifiers":[
        {
            "category":"Professional",
            "subcategory":"Testing Lab",
            "type":"Services"
        }
    ],
    "sg:phone":"+1 613 938 2521",
    "sg:postcode":"K6J 1H6",
    "sg:province":"ON",
    "sg:tags":[
        "soil",
        "engineer"
    ],
    "wof:name":"St Lawrence Testing & Insp CO",
    "wof:placetype":"venue"
},
  "geometry": {"coordinates":[-74.74812300000001,45.014771],"type":"Point"}
}