{
  "type": "Feature",
  "properties": {
    "addr:full":"955 Av DE Bourgogne Sainte-Foy QC G1X 3E5",
    "addr:postcode":"g1x 3e5",
    "addr:street":"955 Av De Bourgogne",
    "iso:country":"CA",
    "sg:address":"955 Av DE Bourgogne",
    "sg:city":"Sainte-Foy",
    "sg:classifiers":[
        {
            "category":"Health Services",
            "subcategory":"Health Practitioner",
            "type":"Services"
        }
    ],
    "sg:phone":"+1 418 658 8072",
    "sg:postcode":"G1X 3E5",
    "sg:province":"QC",
    "sg:tags":[
        "psychologist"
    ],
    "wof:name":"Psycho-Orientation",
    "wof:placetype":"venue"
},
  "geometry": {"coordinates":[-71.312073,46.767159],"type":"Point"}
}