{
  "type": "Feature",
  "properties": {
    "iso:country":"CA",
    "sg:address":"116 1st Ave W",
    "sg:city":"Leader",
    "sg:classifiers":[
        {
            "category":"Shopping",
            "subcategory":"Gifts & Souvenirs",
            "type":"Retail Goods"
        }
    ],
    "sg:phone":"+1 306 967 2511",
    "sg:postcode":"S0N 1H0",
    "sg:province":"SK",
    "sg:tags":[
        "shop",
        "pharmacy"
    ],
    "wof:name":"Stueck Pharmacy Ltd",
    "wof:placetype":"venue"
},
  "geometry": {"coordinates":[-109.536506653,50.8870353699],"type":"Point"}
}