{
  "type": "Feature",
  "properties": {
    "addr:full":"Fairgrounds Park St Killarney MB R0K 1G0",
    "addr:postcode":"r0k 1g0",
    "addr:street":"Park St",
    "iso:country":"CA",
    "sg:address":"Fairgrounds Park St",
    "sg:city":"Killarney",
    "sg:classifiers":[
        {
            "category":"Recreation",
            "type":"Entertainment"
        }
    ],
    "sg:phone":"+1 204 523 4301",
    "sg:postcode":"R0K 1G0",
    "sg:province":"MB",
    "sg:tags":[
        "club",
        "curling"
    ],
    "wof:name":"Killarney Curling Club Ltd",
    "wof:placetype":"venue"
},
  "geometry": {"coordinates":[-99.65715026860001,49.1804351807],"type":"Point"}
}