{
  "type": "Feature",
  "properties": {
    "addr:full":"1724 Snake Rd Burlington ON L7P 4Z3",
    "addr:housenumber":"1724",
    "addr:postcode":"l7p 4z3",
    "addr:street":"Snake Rd",
    "iso:country":"CA",
    "sg:address":"1724 Snake Rd",
    "sg:city":"Burlington",
    "sg:classifiers":[
        {
            "category":"Building & Trades",
            "subcategory":"Landscaping Services",
            "type":"Services"
        }
    ],
    "sg:phone":"+1 905 690 0314",
    "sg:postcode":"L7P 4Z3",
    "sg:province":"ON",
    "sg:tags":[
        "lawn",
        "maintenance",
        "grounds"
    ],
    "wof:name":"Springer's Lawn Maintenance",
    "wof:placetype":"venue"
},
  "geometry": {"coordinates":[-79.890907,43.313141],"type":"Point"}
}