{
  "type": "Feature",
  "properties": {
    "addr:full":"3235 Rue Adelaide Saint-Hubert QC J3Y 4W5",
    "addr:housenumber":"3235",
    "addr:postcode":"j3y 4w5",
    "addr:street":"Rue Adelaide",
    "iso:country":"CA",
    "sg:address":"3235 Rue Adelaide",
    "sg:city":"Saint-Hubert",
    "sg:classifiers":[
        {
            "category":"Building & Trades",
            "subcategory":"Construction",
            "type":"Services"
        }
    ],
    "sg:phone":"+1 450 678 5958",
    "sg:postcode":"J3Y 4W5",
    "sg:province":"QC",
    "sg:tags":[
        "foundation"
    ],
    "wof:name":"Construction Valois Inc",
    "wof:placetype":"venue"
},
  "geometry": {"coordinates":[-73.41892199999999,45.496403],"type":"Point"}
}