{
  "type": "Feature",
  "properties": {
    "addr:full":"1 Credit Union Dr North York ON M4A 2S6",
    "addr:housenumber":"1",
    "addr:postcode":"m4a 2s6",
    "addr:street":"Credit Union Dr",
    "iso:country":"CA",
    "sg:address":"1 Credit Union Dr",
    "sg:city":"North York",
    "sg:classifiers":[
        {
            "category":"Taxi",
            "type":"Transportation"
        }
    ],
    "sg:phone":"+1 416 751 5555",
    "sg:postcode":"M4A 2S6",
    "sg:province":"ON",
    "sg:tags":[
        "taxicab"
    ],
    "wof:name":"Beck Taxi Ltd",
    "wof:placetype":"venue"
},
  "geometry": {"coordinates":[-79.3180389404,43.7259979248],"type":"Point"}
}