{
  "type": "Feature",
  "properties": {
    "iso:country":"CA",
    "sg:address":"1026 Main St",
    "sg:city":"Carrot River",
    "sg:classifiers":[
        {
            "category":"Retail",
            "subcategory":"Self-service Laundry",
            "type":"Services"
        }
    ],
    "sg:phone":"+1 306 768 3878",
    "sg:postcode":"S0E 0L0",
    "sg:province":"SK",
    "wof:name":"Carrot River Laundromat",
    "wof:placetype":"venue"
},
  "geometry": {"coordinates":[-103.587532044,53.2833595276],"type":"Point"}
}