{
  "type": "Feature",
  "properties": {
    "addr:full":"8352 Mountain View Dr Whistler BC V0N 1B8",
    "addr:housenumber":"8352",
    "addr:postcode":"v0n 1b8",
    "addr:street":"Mountain View Dr",
    "iso:country":"CA",
    "sg:address":"8352 Mountain View Dr",
    "sg:city":"Whistler",
    "sg:classifiers":[
        {
            "category":"Building & Trades",
            "subcategory":"Construction",
            "type":"Services"
        }
    ],
    "sg:phone":"+1 604 932 4853",
    "sg:postcode":"V0N 1B8",
    "sg:province":"BC",
    "sg:tags":[
        "contractor",
        "general"
    ],
    "wof:name":"Currie Brothers Enterprises",
    "wof:placetype":"venue"
},
  "geometry": {"coordinates":[-122.969543457,50.1500892639],"type":"Point"}
}