{
  "type": "Feature",
  "properties": {
    "addr:full":"261 Rue Acadie Grande-Anse NB E8N 1B1",
    "addr:housenumber":"261",
    "addr:postcode":"e8n 1b1",
    "addr:street":"Rue Acadie",
    "iso:country":"CA",
    "sg:address":"261 Rue Acadie",
    "sg:city":"Grande-Anse",
    "sg:classifiers":[
        {
            "category":"Education",
            "subcategory":"School",
            "type":"Public Place"
        }
    ],
    "sg:phone":"+1 506 732 3200",
    "sg:postcode":"E8N 1B1",
    "sg:province":"NB",
    "wof:name":"Ecole Leandre-Le Gresley",
    "wof:placetype":"venue"
},
  "geometry": {"coordinates":[-65.18618011469999,47.811794281],"type":"Point"}
}