{
  "type": "Feature",
  "properties": {
    "addr:full":"362 Rte 138 Baie-Sainte-Catherine QC G0T 1A0",
    "addr:housenumber":"362",
    "addr:postcode":"g0t 1a0",
    "addr:street":"Rte 138 Baie-Sainte-Catherine",
    "iso:country":"CA",
    "sg:address":"362 Rte 138",
    "sg:city":"Baie-Sainte-Catherine",
    "sg:classifiers":[
        {
            "category":"Restaurant",
            "type":"Food & Drink"
        }
    ],
    "sg:phone":"+1 418 237 4018",
    "sg:postcode":"G0T 1A0",
    "sg:province":"QC",
    "wof:name":"Restaurant Le Baleineau",
    "wof:placetype":"venue"
},
  "geometry": {"coordinates":[-69.7264785767,48.1059150696],"type":"Point"}
}