{
  "type": "Feature",
  "properties": {
    "addr:full":"200 Broadway St #200 Tillsonburg ON N4G 5A7",
    "addr:housenumber":"200",
    "addr:postcode":"n4g 5a7",
    "addr:street":"Broadway St # 200",
    "iso:country":"CA",
    "sg:address":"200 Broadway St #200",
    "sg:city":"Tillsonburg",
    "sg:classifiers":[
        {
            "category":"Government",
            "subcategory":"Office",
            "type":"Public Place"
        }
    ],
    "sg:phone":"+1 519 842 6428",
    "sg:postcode":"N4G 5A7",
    "sg:province":"ON",
    "sg:tags":[
        "village"
    ],
    "wof:name":"Tillsonburg Treasurer's Office",
    "wof:placetype":"venue"
},
  "geometry": {"coordinates":[-80.7291641235,42.8621025085],"type":"Point"}
}