{
  "type": "Feature",
  "properties": {
    "addr:full":"143 Rue Maskinonge Saint-Gabriel-DE-Brandon QC J0K 2N0",
    "addr:housenumber":"143",
    "addr:postcode":"j0k 2n0",
    "addr:street":"Rue Maskinonge",
    "iso:country":"CA",
    "sg:address":"143 Rue Maskinonge",
    "sg:city":"Saint-Gabriel-DE-Brandon",
    "sg:classifiers":[
        {
            "category":"Food & Beverages",
            "subcategory":"Groceries & Convenience Stores",
            "type":"Retail Goods"
        }
    ],
    "sg:phone":"+1 450 835 7071",
    "sg:postcode":"J0K 2N0",
    "sg:province":"QC",
    "sg:tags":[
        "grocer"
    ],
    "wof:name":"Depanneur Yale",
    "wof:placetype":"venue"
},
  "geometry": {"coordinates":[-73.387336731,46.29712677],"type":"Point"}
}