{
  "type": "Feature",
  "properties": {
    "iso:country":"CA",
    "sg:address":"5050 Av Papineau",
    "sg:city":"Montreal",
    "sg:classifiers":[
        {
            "category":"Personal",
            "subcategory":"Beauty Salon",
            "type":"Services"
        }
    ],
    "sg:phone":"+1 514 528 9280",
    "sg:postcode":"H2H 1V8",
    "sg:province":"QC",
    "wof:name":"Salon DE Coiffure Ouellook",
    "wof:placetype":"venue"
},
  "geometry": {"coordinates":[-73.580406,45.535469],"type":"Point"}
}