{
  "type": "Feature",
  "properties": {
    "addr:full":"Ingersoll ON N5C 3J7",
    "addr:postcode":"n5c 3j7",
    "iso:country":"CA",
    "sg:city":"Ingersoll",
    "sg:classifiers":[
        {
            "category":"Manufacturing",
            "subcategory":"Metals",
            "type":"Manufacturing & Wholesale Goods"
        }
    ],
    "sg:phone":"+1 519 425 7555",
    "sg:postcode":"N5C 3J7",
    "sg:province":"ON",
    "sg:tags":[
        "welding"
    ],
    "wof:name":"M C & Sons Mfg Ltd",
    "wof:placetype":"venue"
},
  "geometry": {"coordinates":[-80.88385,43.038116],"type":"Point"}
}