{
  "type": "Feature",
  "properties": {
    "addr:full":"299 Bridge St Carleton Place ON K7C 3H7",
    "addr:housenumber":"299",
    "addr:postcode":"k7c 3h7",
    "addr:street":"Bridge St",
    "iso:country":"CA",
    "sg:address":"299 Bridge St",
    "sg:city":"Carleton Place",
    "sg:classifiers":[
        {
            "category":"Organizations",
            "subcategory":"Religious Organization",
            "type":"Services"
        }
    ],
    "sg:phone":"+1 613 257 1889",
    "sg:postcode":"K7C 3H7",
    "sg:province":"ON",
    "sg:tags":[
        "church"
    ],
    "wof:name":"Baptist Church",
    "wof:placetype":"venue"
},
  "geometry": {"coordinates":[-76.1499252319,45.1430740356],"type":"Point"}
}