{
  "type": "Feature",
  "properties": {
    "addr:full":"290 Edgepark Blvd NW Calgary AB T3A 4H4",
    "addr:housenumber":"290",
    "addr:postcode":"t3a 4h4",
    "addr:street":"Edgepark Blvd Nw",
    "iso:country":"CA",
    "sg:address":"290 Edgepark Blvd NW",
    "sg:city":"Calgary",
    "sg:classifiers":[
        {
            "category":"Social Services",
            "subcategory":"Child Care",
            "type":"Services"
        }
    ],
    "sg:phone":"+1 403 239 8311",
    "sg:postcode":"T3A 4H4",
    "sg:province":"AB",
    "sg:tags":[
        "kindergarten",
        "academic",
        "school",
        "montessori"
    ],
    "wof:name":"Unique Kids Preschool Inc",
    "wof:placetype":"venue"
},
  "geometry": {"coordinates":[-114.15712000000001,51.135128],"type":"Point"}
}