{
  "type": "Feature",
  "properties": {
    "addr:full":"Grande Cache AB T0E 0Y0",
    "addr:postcode":"t0e 0y0",
    "iso:country":"CA",
    "sg:city":"Grande Cache",
    "sg:classifiers":[
        {
            "category":"Recreation",
            "type":"Entertainment"
        }
    ],
    "sg:phone":"+1 780 827 5450",
    "sg:postcode":"T0E 0Y0",
    "sg:province":"AB",
    "sg:tags":[
        "guide"
    ],
    "wof:name":"Wild Blue Yonder Tours Ltd",
    "wof:placetype":"venue"
},
  "geometry": {"coordinates":[-119.116013,53.888275],"type":"Point"}
}