{
  "type": "Feature",
  "properties": {
    "addr:full":"830 Rue Notre-Dame Repentigny QC J5Y 1B8",
    "addr:housenumber":"830",
    "addr:postcode":"j5y 1b8",
    "addr:street":"Rue Notre-Dame",
    "iso:country":"CA",
    "sg:address":"830 Rue Notre-Dame",
    "sg:city":"Repentigny",
    "sg:phone":"+1 450 585 5255",
    "sg:postcode":"J5Y 1B8",
    "sg:province":"QC",
    "sg:tags":[
        "equipment",
        "supply"
    ],
    "wof:name":"A B Equipement",
    "wof:placetype":"venue"
},
  "geometry": {"coordinates":[-73.4223937988,45.7627220154],"type":"Point"}
}