{
  "type": "Feature",
  "properties": {
    "addr:full":"14 Rue Balmoral Morin-Heights QC J0R 1H0",
    "addr:housenumber":"14",
    "addr:postcode":"j0r 1h0",
    "addr:street":"Rue Balmoral",
    "iso:country":"CA",
    "sg:address":"14 Rue Balmoral",
    "sg:city":"Morin-Heights",
    "sg:classifiers":[
        {
            "category":"Building & Trades",
            "subcategory":"Construction",
            "type":"Services"
        }
    ],
    "sg:phone":"+1 450 226 7227",
    "sg:postcode":"J0R 1H0",
    "sg:province":"QC",
    "sg:tags":[
        "contractor"
    ],
    "wof:name":"Construction Belco Inc",
    "wof:placetype":"venue"
},
  "geometry": {"coordinates":[-74.2183227539,45.8989143372],"type":"Point"}
}