{
  "type": "Feature",
  "properties": {
    "addr:full":"128 Pitt St Cornwall ON K6J 3P4",
    "addr:housenumber":"128",
    "addr:postcode":"k6j 3p4",
    "addr:street":"Pitt St",
    "iso:country":"CA",
    "sg:address":"128 Pitt St",
    "sg:city":"Cornwall",
    "sg:classifiers":[
        {
            "category":"Restaurant",
            "type":"Food & Drink"
        }
    ],
    "sg:phone":"+1 613 933 5155",
    "sg:postcode":"K6J 3P4",
    "sg:province":"ON",
    "wof:name":"Jack Lee's Tavern Restaurant",
    "wof:placetype":"venue"
},
  "geometry": {"coordinates":[-74.72833300000001,45.017262],"type":"Point"}
}