{
  "type": "Feature",
  "properties": {
    "iso:country":"CA",
    "sg:address":"105 St. Peters Rd",
    "sg:city":"Charlottetown",
    "sg:classifiers":[
        {
            "category":"Retail",
            "subcategory":"Auto Repair",
            "type":"Services"
        }
    ],
    "sg:phone":"+1 902 892 4819",
    "sg:postcode":"C1A 5P1",
    "sg:province":"PE",
    "sg:tags":[
        "transmission"
    ],
    "wof:name":"Precision Transmission",
    "wof:placetype":"venue"
},
  "geometry": {"coordinates":[-63.121257782,46.2534217834],"type":"Point"}
}