{
  "type": "Feature",
  "properties": {
    "addr:full":"4926 50th St Cadogan AB T0B 0T0",
    "addr:housenumber":"4926",
    "addr:postcode":"t0b 0t0",
    "addr:street":"50Th St",
    "iso:country":"CA",
    "sg:address":"4926 50th St",
    "sg:city":"Cadogan",
    "sg:classifiers":[
        {
            "category":"Personal",
            "subcategory":"Beauty Salon",
            "type":"Services"
        }
    ],
    "sg:phone":"+1 780 753 2016",
    "sg:postcode":"T0B 0T0",
    "sg:province":"AB",
    "wof:name":"Karens Hair & Alpha Massage",
    "wof:placetype":"venue"
},
  "geometry": {"coordinates":[-110.45017199999999,52.319698],"type":"Point"}
}