{
  "type": "Feature",
  "properties": {
    "addr:full":"9712 153 Ave NW Edmonton AB T5X 5V2",
    "addr:housenumber":"9712",
    "addr:postcode":"t5x 5v2",
    "addr:street":"153 Ave Nw",
    "iso:country":"CA",
    "sg:address":"9712 153 Ave NW",
    "sg:city":"Edmonton",
    "sg:classifiers":[
        {
            "category":"Home & Garden",
            "subcategory":"Building Materials",
            "type":"Retail Goods"
        }
    ],
    "sg:phone":"+1 780 457 4646",
    "sg:postcode":"T5X 5V2",
    "sg:province":"AB",
    "sg:tags":[
        "paint"
    ],
    "wof:name":"Cloverdale Paint",
    "wof:placetype":"venue"
},
  "geometry": {"coordinates":[-113.493065,53.614262],"type":"Point"}
}