{
  "type": "Feature",
  "properties": {
    "addr:full":"Milverton ON N0K 1M0",
    "addr:postcode":"n0k 1m0",
    "iso:country":"CA",
    "sg:city":"Milverton",
    "sg:classifiers":[
        {
            "category":"Home & Garden",
            "subcategory":"Hardware",
            "type":"Retail Goods"
        }
    ],
    "sg:phone":"+1 519 595 8224",
    "sg:postcode":"N0K 1M0",
    "sg:province":"ON",
    "sg:tags":[
        "furniture"
    ],
    "wof:name":"Schneuker's Home Ctr",
    "wof:placetype":"venue"
},
  "geometry": {"coordinates":[-80.921936,43.566418],"type":"Point"}
}