{
  "type": "Feature",
  "properties": {
    "addr:full":"Valcourt QC J0E 2L0",
    "addr:postcode":"j0e 2l0",
    "iso:country":"CA",
    "sg:city":"Valcourt",
    "sg:classifiers":[
        {
            "category":"Wholesale",
            "subcategory":"Hardware",
            "type":"Manufacturing & Wholesale Goods"
        }
    ],
    "sg:phone":"+1 450 532 3131",
    "sg:postcode":"J0E 2L0",
    "sg:province":"QC",
    "sg:tags":[
        "nut",
        "bolt"
    ],
    "wof:name":"Specialty Bolt & Screw Inc",
    "wof:placetype":"venue"
},
  "geometry": {"coordinates":[-72.30201700000001,45.487324],"type":"Point"}
}