{
  "type": "Feature",
  "properties": {
    "addr:full":"Scarborough ON M1V 4Y6",
    "addr:postcode":"m1v 4y6",
    "iso:country":"CA",
    "sg:city":"Scarborough",
    "sg:classifiers":[
        {
            "category":"Manufacturing",
            "subcategory":"Paper Products",
            "type":"Manufacturing & Wholesale Goods"
        }
    ],
    "sg:phone":"+1 416 299 7766",
    "sg:postcode":"M1V 4Y6",
    "sg:province":"ON",
    "sg:tags":[
        "bag"
    ],
    "wof:name":"Multicolor Silk Printing Inc",
    "wof:placetype":"venue"
},
  "geometry": {"coordinates":[-79.25851400000001,43.812252],"type":"Point"}
}