{
  "type": "Feature",
  "properties": {
    "iso:country":"CA",
    "sg:address":"4101 Rue Sherbrooke E",
    "sg:city":"Montreal",
    "sg:classifiers":[
        {
            "category":"Government",
            "subcategory":"Office",
            "type":"Public Place"
        }
    ],
    "sg:phone":"+1 514 872 1400",
    "sg:postcode":"H1X 2B2",
    "sg:province":"QC",
    "sg:tags":[
        "village"
    ],
    "wof:name":"Montreal Jardin Botanique",
    "wof:placetype":"venue"
},
  "geometry": {"coordinates":[-73.5545883179,45.5565643311],"type":"Point"}
}