{
  "type": "Feature",
  "properties": {
    "addr:full":"Wickham QC J0C 1S0",
    "addr:postcode":"j0c 1s0",
    "iso:country":"CA",
    "sg:city":"Wickham",
    "sg:classifiers":[
        {
            "category":"Farming",
            "subcategory":"Aquatic Farm",
            "type":"Manufacturing & Wholesale Goods"
        }
    ],
    "sg:phone":"+1 819 398 6807",
    "sg:postcode":"J0C 1S0",
    "sg:province":"QC",
    "sg:tags":[
        "hatchery",
        "fish"
    ],
    "wof:name":"Couroir Boire & Freres",
    "wof:placetype":"venue"
},
  "geometry": {"coordinates":[-72.475692749,45.7456893921],"type":"Point"}
}