{
  "type": "Feature",
  "properties": {
    "addr:full":"1224 Rue Stanley Montreal QC H3B 2S7",
    "addr:housenumber":"1224",
    "addr:postcode":"h3b 2s7",
    "addr:street":"Rue Stanley",
    "iso:country":"CA",
    "sg:address":"1224 Rue Stanley",
    "sg:city":"Montreal",
    "sg:classifiers":[
        {
            "category":"Professional",
            "subcategory":"Management & Consulting",
            "type":"Services"
        }
    ],
    "sg:phone":"+1 514 875 7222",
    "sg:postcode":"H3B 2S7",
    "sg:province":"QC",
    "sg:tags":[
        "marketing",
        "consultant"
    ],
    "wof:name":"Eurosar Inc",
    "wof:placetype":"venue"
},
  "geometry": {"coordinates":[-73.572571,45.498707],"type":"Point"}
}