{
  "type": "Feature",
  "properties": {
    "iso:country":"CA",
    "sg:address":"9 Boul Ouellet",
    "sg:city":"Warwick",
    "sg:classifiers":[
        {
            "category":"Organizations",
            "subcategory":"Professional Association",
            "type":"Services"
        }
    ],
    "sg:phone":"+1 819 358 2222",
    "sg:postcode":"J0A 1M0",
    "sg:province":"QC",
    "sg:tags":[
        "club"
    ],
    "wof:name":"Club Aramis Warwick Inc",
    "wof:placetype":"venue"
},
  "geometry": {"coordinates":[-71.99881744379999,45.9451141357],"type":"Point"}
}