{
  "type": "Feature",
  "properties": {
    "iso:country":"CA",
    "sg:address":"4840 Wyandotte St E",
    "sg:city":"Windsor",
    "sg:classifiers":[
        {
            "category":"Restaurant",
            "type":"Food & Drink"
        }
    ],
    "sg:phone":"+1 519 944 0896",
    "sg:postcode":"N8Y 1H7",
    "sg:province":"ON",
    "wof:name":"Mc Donald's",
    "wof:placetype":"venue"
},
  "geometry": {"coordinates":[-82.9789199829,42.3267288208],"type":"Point"}
}