{
  "type": "Feature",
  "properties": {
    "addr:full":"Thompson MB R8N 1G1",
    "addr:postcode":"r8n 1g1",
    "iso:country":"CA",
    "sg:city":"Thompson",
    "sg:classifiers":[
        {
            "category":"Food & Beverages",
            "subcategory":"Specialty",
            "type":"Retail Goods"
        }
    ],
    "sg:phone":"+1 204 677 1141",
    "sg:postcode":"R8N 1G1",
    "sg:province":"MB",
    "sg:tags":[
        "health",
        "diet"
    ],
    "wof:name":"Herbal Healing",
    "wof:placetype":"venue"
},
  "geometry": {"coordinates":[-97.86537199999999,55.739029],"type":"Point"}
}