{
  "type": "Feature",
  "properties": {
    "addr:full":"6982 Main St Millbank ON N0K 1L0",
    "addr:housenumber":"6982",
    "addr:postcode":"n0k 1l0",
    "addr:street":"Main St",
    "iso:country":"CA",
    "sg:address":"6982 Main St",
    "sg:city":"Millbank",
    "sg:classifiers":[
        {
            "category":"Building & Trades",
            "subcategory":"Construction",
            "type":"Services"
        }
    ],
    "sg:phone":"+1 519 595 2053",
    "sg:postcode":"N0K 1L0",
    "sg:province":"ON",
    "sg:tags":[
        "concrete",
        "contractor"
    ],
    "wof:name":"Weickert & Meirowski Concrete",
    "wof:placetype":"venue"
},
  "geometry": {"coordinates":[-80.834557,43.57003],"type":"Point"}
}