{
  "type": "Feature",
  "properties": {
    "iso:country":"CA",
    "sg:address":"735 Boul Des Bois-Francs S",
    "sg:city":"Victoriaville",
    "sg:classifiers":[
        {
            "category":"Recreation",
            "type":"Entertainment"
        }
    ],
    "sg:phone":"+1 819 357 2097",
    "sg:postcode":"G6P 5W3",
    "sg:province":"QC",
    "sg:tags":[
        "center",
        "hall",
        "auditorium"
    ],
    "wof:name":"Centre Communautaire Inc",
    "wof:placetype":"venue"
},
  "geometry": {"coordinates":[-71.923866272,46.0430107117],"type":"Point"}
}