{
  "type": "Feature",
  "properties": {
    "addr:full":"1640 Ch D'Oka Deux-Montagnes QC J7R 1M9",
    "addr:postcode":"1640;j7r 1m9",
    "addr:street":"Ch D'Oka",
    "iso:country":"CA",
    "sg:address":"1640 Ch D'Oka",
    "sg:city":"Deux-Montagnes",
    "sg:classifiers":[
        {
            "category":"Cinema",
            "subcategory":"Movie Rental",
            "type":"Entertainment"
        }
    ],
    "sg:phone":"+1 450 491 2764",
    "sg:postcode":"J7R 1M9",
    "sg:province":"QC",
    "sg:tags":[
        "leasing",
        "video",
        "disc",
        "tape"
    ],
    "wof:name":"Club International Video-Film",
    "wof:placetype":"venue"
},
  "geometry": {"coordinates":[-73.89286800000001,45.541492],"type":"Point"}
}