{
  "type": "Feature",
  "properties": {
    "addr:full":"RR 4 Tottenham ON L0G 1W0",
    "addr:postcode":"l0g 1w0",
    "addr:street":"Rr 4 Tottenham",
    "iso:country":"CA",
    "sg:address":"RR 4",
    "sg:city":"Tottenham",
    "sg:classifiers":[
        {
            "category":"Professional",
            "subcategory":"Lawyer & Legal Services",
            "type":"Services"
        }
    ],
    "sg:phone":"+1 905 936 9902",
    "sg:postcode":"L0G 1W0",
    "sg:province":"ON",
    "sg:tags":[
        "attorney"
    ],
    "wof:name":"Aronovitch Macaulay & Rollo",
    "wof:placetype":"venue"
},
  "geometry": {"coordinates":[-79.80578613279999,44.0228767395],"type":"Point"}
}