{
  "type": "Feature",
  "properties": {
    "addr:full":"Quebec QC G2C 1T3",
    "addr:postcode":"qc g2c 1t3",
    "iso:country":"CA",
    "sg:city":"Quebec",
    "sg:classifiers":[
        {
            "category":"Wholesale",
            "subcategory":"Electrical",
            "type":"Manufacturing & Wholesale Goods"
        }
    ],
    "sg:phone":"+1 418 842 5114",
    "sg:postcode":"G2C 1T3",
    "sg:province":"QC",
    "sg:tags":[
        "control"
    ],
    "wof:name":"Regulvar Inc",
    "wof:placetype":"venue"
},
  "geometry": {"coordinates":[-71.316261,46.820419],"type":"Point"}
}