{
  "type": "Feature",
  "properties": {
    "addr:full":"7 Rue DE L'Eglise Sainte-Anne-DE-Madawaska NB E7E 1M2",
    "addr:housenumber":"7",
    "addr:postcode":"e7e 1m2",
    "addr:street":"Rue De L'Eglise",
    "iso:country":"CA",
    "sg:address":"7 Rue DE L'Eglise",
    "sg:city":"Sainte-Anne-DE-Madawaska",
    "sg:classifiers":[
        {
            "category":"Organizations",
            "subcategory":"Professional Association",
            "type":"Services"
        }
    ],
    "sg:phone":"+1 506 445 2539",
    "sg:postcode":"E7E 1M2",
    "sg:province":"NB",
    "wof:name":"Club DE L'Age D'Or",
    "wof:placetype":"venue"
},
  "geometry": {"coordinates":[-68.029259,47.245331],"type":"Point"}
}