{
  "type": "Feature",
  "properties": {
    "addr:full":"302 Rue DE LA Riviere Grandes-Bergeronnes QC G0T 1G0",
    "addr:housenumber":"302",
    "addr:postcode":"g0t 1g0",
    "addr:street":"Rue De La;Grandes-Bergeronnes",
    "iso:country":"CA",
    "sg:address":"302 Rue DE LA Riviere",
    "sg:city":"Grandes-Bergeronnes",
    "sg:classifiers":[
        {
            "category":"Travel",
            "subcategory":"Campground",
            "type":"Entertainment"
        }
    ],
    "sg:phone":"+1 418 232 6249",
    "sg:postcode":"G0T 1G0",
    "sg:province":"QC",
    "sg:tags":[
        "camp"
    ],
    "wof:name":"Explos-Nature",
    "wof:placetype":"venue"
},
  "geometry": {"coordinates":[-69.546944,48.24538],"type":"Point"}
}