{
  "type": "Feature",
  "properties": {
    "iso:country":"CA",
    "sg:city":"Richmond Hill",
    "sg:classifiers":[
        {
            "category":"Professional",
            "subcategory":"Engineering",
            "type":"Services"
        }
    ],
    "sg:phone":"+1 905 882 5445",
    "sg:postcode":"L4B 3M1",
    "sg:province":"ON",
    "sg:tags":[
        "engineer"
    ],
    "wof:name":"Enersys Engineering Group Ltd",
    "wof:placetype":"venue"
},
  "geometry": {"coordinates":[-79.3873596191,43.8472251892],"type":"Point"}
}