{
  "type": "Feature",
  "properties": {
    "iso:country":"CA",
    "sg:address":"3220 Silver King Rd",
    "sg:city":"Nelson",
    "sg:classifiers":[
        {
            "category":"Freight",
            "type":"Transportation"
        }
    ],
    "sg:phone":"+1 250 352 7990",
    "sg:postcode":"V1L 6Z7",
    "sg:province":"BC",
    "sg:tags":[
        "trucking"
    ],
    "wof:name":"Dave Weinrauch & Sons Trucking",
    "wof:placetype":"venue"
},
  "geometry": {"coordinates":[-117.29611969,49.4752883911],"type":"Point"}
}