{
  "type": "Feature",
  "properties": {
    "addr:full":"857 Lakeshore Rd E Mississauga ON L5E 1E2",
    "addr:housenumber":"857",
    "addr:postcode":"l5e 1e2",
    "addr:street":"Lakeshore Rd E",
    "iso:country":"CA",
    "sg:address":"857 Lakeshore Rd E",
    "sg:city":"Mississauga",
    "sg:classifiers":[
        {
            "category":"Retail",
            "subcategory":"Auto Repair",
            "type":"Services"
        }
    ],
    "sg:phone":"+1 905 278 5722",
    "sg:postcode":"L5E 1E2",
    "sg:province":"ON",
    "sg:tags":[
        "repairing",
        "automobile"
    ],
    "wof:name":"Cawthra Park Complete Car Care",
    "wof:placetype":"venue"
},
  "geometry": {"coordinates":[-79.56247711180001,43.5736198425],"type":"Point"}
}