{
  "type": "Feature",
  "properties": {
    "addr:full":"5107 50th St High Prairie AB T0G 1E0",
    "addr:housenumber":"5107",
    "addr:postcode":"t0g 1e0",
    "addr:street":"50Th St",
    "iso:country":"CA",
    "sg:address":"5107 50th St",
    "sg:city":"High Prairie",
    "sg:classifiers":[
        {
            "category":"Shopping",
            "subcategory":"Jewelry",
            "type":"Retail Goods"
        }
    ],
    "sg:phone":"+1 780 523 3730",
    "sg:postcode":"T0G 1E0",
    "sg:province":"AB",
    "sg:tags":[
        "jeweler"
    ],
    "wof:name":"Norm's Jewelry",
    "wof:placetype":"venue"
},
  "geometry": {"coordinates":[-116.495002747,55.4312057495],"type":"Point"}
}