{
  "type": "Feature",
  "properties": {
    "iso:country":"CA",
    "sg:city":"Vancouver",
    "sg:classifiers":[
        {
            "category":"Government",
            "subcategory":"Office",
            "type":"Public Place"
        }
    ],
    "sg:phone":"+1 604 666 2431",
    "sg:postcode":"V6C 1A1",
    "sg:province":"BC",
    "wof:name":"Canada Environmental Assess",
    "wof:placetype":"venue"
},
  "geometry": {"coordinates":[-123.114318848,49.2857208252],"type":"Point"}
}