{
  "type": "Feature",
  "properties": {
    "iso:country":"CA",
    "sg:address":"81 Alexander Blvd",
    "sg:city":"Jacksons Point",
    "sg:classifiers":[
        {
            "category":"Social Services",
            "type":"Services"
        }
    ],
    "sg:phone":"+1 905 722 4331",
    "sg:postcode":"L0E 1L0",
    "sg:province":"ON",
    "sg:tags":[
        "housing",
        "assistance"
    ],
    "wof:name":"Russion Orthodox Retirement",
    "wof:placetype":"venue"
},
  "geometry": {"coordinates":[-79.384766,44.317013],"type":"Point"}
}