{
  "type": "Feature",
  "properties": {
    "addr:full":"16 Aberdeen St Campbellton NB E3N 2J7",
    "addr:housenumber":"16",
    "addr:postcode":"e3n 2j7",
    "addr:street":"Aberdeen St",
    "iso:country":"CA",
    "sg:address":"16 Aberdeen St",
    "sg:city":"Campbellton",
    "sg:classifiers":[
        {
            "category":"Organizations",
            "subcategory":"Religious Organization",
            "type":"Services"
        }
    ],
    "sg:phone":"+1 506 753 3035",
    "sg:postcode":"E3N 2J7",
    "sg:province":"NB",
    "sg:tags":[
        "church"
    ],
    "wof:name":"First United Chr Campbellton",
    "wof:placetype":"venue"
},
  "geometry": {"coordinates":[-66.67422500000001,48.004097],"type":"Point"}
}