{
  "type": "Feature",
  "properties": {
    "addr:full":"20 Oxford St W London ON N6H 1P9",
    "addr:housenumber":"20",
    "addr:postcode":"n6h 1p9",
    "addr:street":"Oxford St W",
    "iso:country":"CA",
    "sg:address":"20 Oxford St W",
    "sg:city":"London",
    "sg:classifiers":[
        {
            "category":"Health Services",
            "subcategory":"Doctor",
            "type":"Services"
        }
    ],
    "sg:phone":"+1 519 434 1881",
    "sg:postcode":"N6H 1P9",
    "sg:province":"ON",
    "sg:tags":[
        "physician",
        "surgeon"
    ],
    "wof:name":"Yau, C Y MD",
    "wof:placetype":"venue"
},
  "geometry": {"coordinates":[-81.2622833252,42.9926071167],"type":"Point"}
}