{
  "type": "Feature",
  "properties": {
    "addr:full":"4708 Hastings St Burnaby BC V5C 2K7",
    "addr:housenumber":"4708",
    "addr:postcode":"v5c 2k7",
    "addr:street":"Hastings St",
    "iso:country":"CA",
    "sg:address":"4708 Hastings St",
    "sg:city":"Burnaby",
    "sg:classifiers":[
        {
            "category":"Retail",
            "subcategory":"Animal Services",
            "type":"Services"
        }
    ],
    "sg:phone":"+1 604 299 2990",
    "sg:postcode":"V5C 2K7",
    "sg:province":"BC",
    "sg:tags":[
        "pet",
        "grooming",
        "washing"
    ],
    "wof:name":"Haute Dog",
    "wof:placetype":"venue"
},
  "geometry": {"coordinates":[-122.996948,49.280785],"type":"Point"}
}