{
  "type": "Feature",
  "properties": {
    "addr:full":"4055 Malakwa Cemetery Rd Malakwa BC V0E 2J0",
    "addr:housenumber":"4055",
    "addr:postcode":"v0e 2j0",
    "addr:street":"Malakwa Cemetery Rd",
    "iso:country":"CA",
    "sg:address":"4055 Malakwa Cemetery Rd",
    "sg:city":"Malakwa",
    "sg:classifiers":[
        {
            "category":"Social Services",
            "subcategory":"Child Care",
            "type":"Services"
        }
    ],
    "sg:phone":"+1 250 836 5335",
    "sg:postcode":"V0E 2J0",
    "sg:province":"BC",
    "wof:name":"Malakwa Preschool",
    "wof:placetype":"venue"
},
  "geometry": {"coordinates":[-118.794456,50.937382],"type":"Point"}
}