{
  "type": "Feature",
  "properties": {
    "addr:full":"391 Sent Des Fougeres Sullivan QC J0Y 2N0",
    "addr:housenumber":"391",
    "addr:postcode":"j0y 2n0",
    "addr:street":"Sent Des Fougeres",
    "iso:country":"CA",
    "sg:address":"391 Sent Des Fougeres",
    "sg:city":"Sullivan",
    "sg:classifiers":[
        {
            "category":"Building & Trades",
            "subcategory":"Construction",
            "type":"Services"
        }
    ],
    "sg:phone":"+1 819 824 5443",
    "sg:postcode":"J0Y 2N0",
    "sg:province":"QC",
    "sg:tags":[
        "general",
        "contractor"
    ],
    "wof:name":"Construction Multiple Inc",
    "wof:placetype":"venue"
},
  "geometry": {"coordinates":[-77.819954,48.118614],"type":"Point"}
}