{
  "type": "Feature",
  "properties": {
    "addr:full":"Richmond Hill ON L4B 3V1",
    "addr:postcode":"l4b 3v1",
    "iso:country":"CA",
    "sg:city":"Richmond Hill",
    "sg:classifiers":[
        {
            "category":"Insurance",
            "subcategory":"Insurance Agent",
            "type":"Services"
        }
    ],
    "sg:phone":"+1 905 764 6575",
    "sg:postcode":"L4B 3V1",
    "sg:province":"ON",
    "wof:name":"Lora Cai Insurance Ltd",
    "wof:placetype":"venue"
},
  "geometry": {"coordinates":[-79.407623,43.844852],"type":"Point"}
}