{
  "type": "Feature",
  "properties": {
    "addr:full":"12 Hattie St Merlin ON N0P 1W0",
    "addr:housenumber":"12",
    "addr:postcode":"n0p 1w0",
    "addr:street":"Hattie St",
    "iso:country":"CA",
    "sg:address":"12 Hattie St",
    "sg:city":"Merlin",
    "sg:classifiers":[
        {
            "category":"Building & Trades",
            "subcategory":"Construction",
            "type":"Services"
        }
    ],
    "sg:phone":"+1 519 689 4692",
    "sg:postcode":"N0P 1W0",
    "sg:province":"ON",
    "sg:tags":[
        "well",
        "drilling"
    ],
    "wof:name":"Bradco Drilling Inc",
    "wof:placetype":"venue"
},
  "geometry": {"coordinates":[-82.2328414917,42.2399635315],"type":"Point"}
}