{
  "type": "Feature",
  "properties": {
    "iso:country":"CA",
    "sg:address":"1834 Hwy 3B",
    "sg:city":"Fruitvale",
    "sg:classifiers":[
        {
            "category":"Government",
            "subcategory":"Office",
            "type":"Public Place"
        }
    ],
    "sg:phone":"+1 250 367 6162",
    "sg:postcode":"V0G 1L0",
    "sg:province":"BC",
    "sg:tags":[
        "village"
    ],
    "wof:name":"Fruitvale Public Works",
    "wof:placetype":"venue"
},
  "geometry": {"coordinates":[-117.540481567,49.1169891357],"type":"Point"}
}