{
  "type": "Feature",
  "properties": {
    "iso:country":"CA",
    "sg:address":"32 James St E",
    "sg:city":"Orillia",
    "sg:classifiers":[
        {
            "category":"Shopping",
            "type":"Retail Goods"
        }
    ],
    "sg:phone":"+1 705 325 0847",
    "sg:postcode":"L3V 1L1",
    "sg:province":"ON",
    "sg:tags":[
        "cemetery",
        "monument"
    ],
    "wof:name":"Signature Memorials Ltd",
    "wof:placetype":"venue"
},
  "geometry": {"coordinates":[-79.40901184080001,44.5997924805],"type":"Point"}
}