{
  "type": "Feature",
  "properties": {
    "addr:full":"516 Rothesay Ave Saint John NB E2J 2C7",
    "addr:housenumber":"516",
    "addr:postcode":"e2j 2c7",
    "addr:street":"Rothesay Ave",
    "iso:country":"CA",
    "sg:address":"516 Rothesay Ave",
    "sg:city":"Saint John",
    "sg:classifiers":[
        {
            "category":"Retail",
            "subcategory":"Auto Rental",
            "type":"Services"
        }
    ],
    "sg:phone":"+1 506 633 4901",
    "sg:postcode":"E2J 2C7",
    "sg:province":"NB",
    "sg:tags":[
        "renting",
        "automobile"
    ],
    "wof:name":"Enterprise Rent-A-Car",
    "wof:placetype":"venue"
},
  "geometry": {"coordinates":[-66.029549,45.309319],"type":"Point"}
}