{
  "type": "Feature",
  "properties": {
    "addr:full":"369 George St N Peterborough ON K9H 3R2",
    "addr:housenumber":"369",
    "addr:postcode":"k9h 3r2",
    "addr:street":"George St N",
    "iso:country":"CA",
    "sg:address":"369 George St N",
    "sg:city":"Peterborough",
    "sg:classifiers":[
        {
            "category":"Food & Beverages",
            "subcategory":"Groceries & Convenience Stores",
            "type":"Retail Goods"
        }
    ],
    "sg:phone":"+1 705 749 5050",
    "sg:postcode":"K9H 3R2",
    "sg:province":"ON",
    "wof:name":"Downtown Dollar Convenience",
    "wof:placetype":"venue"
},
  "geometry": {"coordinates":[-78.32017500000001,44.305004],"type":"Point"}
}