{
  "type": "Feature",
  "properties": {
    "iso:country":"CA",
    "sg:city":"Vancouver",
    "sg:classifiers":[
        {
            "category":"Manufacturing",
            "subcategory":"Jewelry",
            "type":"Manufacturing & Wholesale Goods"
        }
    ],
    "sg:phone":"+1 604 687 4313",
    "sg:postcode":"V6Z 1N9",
    "sg:province":"BC",
    "wof:name":"George Adam Goldsmith Ltd",
    "wof:placetype":"venue"
},
  "geometry": {"coordinates":[-123.122841,49.280403],"type":"Point"}
}