{
  "type": "Feature",
  "properties": {
    "addr:full":"2435 Boul Du Royaume Jonquiere QC G7T 1A2",
    "addr:housenumber":"2435",
    "addr:postcode":"g7t 1a2",
    "addr:street":"Boul Du Royaume",
    "iso:country":"CA",
    "sg:address":"2435 Boul Du Royaume",
    "sg:city":"Jonquiere",
    "sg:classifiers":[
        {
            "category":"Home & Garden",
            "subcategory":"Building Materials",
            "type":"Retail Goods"
        }
    ],
    "sg:phone":"+1 418 548 8080",
    "sg:postcode":"G7T 1A2",
    "sg:province":"QC",
    "sg:tags":[
        "door"
    ],
    "wof:name":"Groupe Servi-Portes Ltee",
    "wof:placetype":"venue"
},
  "geometry": {"coordinates":[-71.157104,48.400951],"type":"Point"}
}