{
  "type": "Feature",
  "properties": {
    "addr:full":"41 Av DE Gaspe E Saint-Jean-Port-Joli QC G0R 3G0",
    "addr:postcode":"g0r 3g0",
    "addr:street":"41 Av De Gaspe E",
    "iso:country":"CA",
    "sg:address":"41 Av DE Gaspe E",
    "sg:city":"Saint-Jean-Port-Joli",
    "sg:classifiers":[
        {
            "category":"Travel",
            "subcategory":"Hotels & Motels",
            "type":"Entertainment"
        }
    ],
    "sg:phone":"+1 418 598 6774",
    "sg:postcode":"G0R 3G0",
    "sg:province":"QC",
    "sg:tags":[
        "breakfast",
        "inn",
        "bed",
        "accommodation"
    ],
    "wof:name":"Au Boise Joli",
    "wof:placetype":"venue"
},
  "geometry": {"coordinates":[-70.26839447019999,47.2165756226],"type":"Point"}
}