{
  "type": "Feature",
  "properties": {
    "addr:full":"3522 Marmac Cres Mississauga ON L5L 4Z9",
    "addr:housenumber":"3522",
    "addr:postcode":"l5l 4z9",
    "addr:street":"Marmac Cres",
    "iso:country":"CA",
    "sg:address":"3522 Marmac Cres",
    "sg:city":"Mississauga",
    "sg:classifiers":[
        {
            "category":"Building & Trades",
            "subcategory":"Construction",
            "type":"Services"
        }
    ],
    "sg:phone":"+1 905 569 3871",
    "sg:postcode":"L5L 4Z9",
    "sg:province":"ON",
    "sg:tags":[
        "general",
        "garbage",
        "collection",
        "contractor"
    ],
    "wof:name":"Westward General Contracting",
    "wof:placetype":"venue"
},
  "geometry": {"coordinates":[-79.6983947754,43.5254974365],"type":"Point"}
}