{
  "type": "Feature",
  "properties": {
    "addr:full":"5425 Hwy 93 Radium Hot Springs BC V0A 1M0",
    "addr:housenumber":"5425",
    "addr:postcode":"v0a 1m0",
    "addr:street":"Hwy 93",
    "iso:country":"CA",
    "sg:address":"5425 Hwy 93",
    "sg:city":"Radium Hot Springs",
    "sg:classifiers":[
        {
            "category":"Travel",
            "subcategory":"Hotels & Motels",
            "type":"Entertainment"
        }
    ],
    "sg:phone":"+1 250 347 9341",
    "sg:postcode":"V0A 1M0",
    "sg:province":"BC",
    "wof:name":"Radium Hot Springs Lodge",
    "wof:placetype":"venue"
},
  "geometry": {"coordinates":[-116.071472168,50.622379303],"type":"Point"}
}