{
  "type": "Feature",
  "properties": {
    "addr:full":"695 Main St E Hawkesbury ON K6A 1B3",
    "addr:housenumber":"695",
    "addr:postcode":"k6a 1b3",
    "addr:street":"Main St E",
    "iso:country":"CA",
    "sg:address":"695 Main St E",
    "sg:city":"Hawkesbury",
    "sg:classifiers":[
        {
            "category":"Food & Beverages",
            "subcategory":"Groceries & Convenience Stores",
            "type":"Retail Goods"
        }
    ],
    "sg:phone":"+1 613 632 3245",
    "sg:postcode":"K6A 1B3",
    "sg:province":"ON",
    "wof:name":"Depanneur Jo's",
    "wof:placetype":"venue"
},
  "geometry": {"coordinates":[-74.59947200000001,45.610596],"type":"Point"}
}