{
  "type": "Feature",
  "properties": {
    "addr:full":"2125 Rue Bellefeuille Trois-Rivieres QC G9A 3Z1",
    "addr:housenumber":"2125",
    "addr:postcode":"g9a 3z1",
    "addr:street":"Rue Bellefeuille Trois-Rivieres",
    "iso:country":"CA",
    "sg:address":"2125 Rue Bellefeuille",
    "sg:city":"Trois-Rivieres",
    "sg:classifiers":[
        {
            "category":"Autos & Motor Vehicles",
            "subcategory":"Fuel & Gas Station",
            "type":"Retail Goods"
        }
    ],
    "sg:phone":"+1 819 379 3285",
    "sg:postcode":"G9A 3Z1",
    "sg:province":"QC",
    "sg:tags":[
        "oil"
    ],
    "wof:name":"Olco",
    "wof:placetype":"venue"
},
  "geometry": {"coordinates":[-72.55252075200001,46.3378257751],"type":"Point"}
}