{
  "type": "Feature",
  "properties": {
    "addr:full":"Richmond BC V6V 3A1",
    "addr:postcode":"v6v 3a1",
    "iso:country":"CA",
    "sg:city":"Richmond",
    "sg:classifiers":[
        {
            "category":"Insurance",
            "subcategory":"Insurance Agent",
            "type":"Services"
        }
    ],
    "sg:phone":"+1 604 214 8745",
    "sg:postcode":"V6V 3A1",
    "sg:province":"BC",
    "sg:tags":[
        "consultant"
    ],
    "wof:name":"Booth Graham & Assoc Ltd",
    "wof:placetype":"venue"
},
  "geometry": {"coordinates":[-123.07199900000001,49.172344],"type":"Point"}
}