{
  "type": "Feature",
  "properties": {
    "addr:full":"337 Rue Moreault Rimouski QC G5L 1P4",
    "addr:housenumber":"337",
    "addr:postcode":"g5l 1p4",
    "addr:street":"Rue Moreault",
    "iso:country":"CA",
    "sg:address":"337 Rue Moreault",
    "sg:city":"Rimouski",
    "sg:classifiers":[
        {
            "category":"Government",
            "subcategory":"Office",
            "type":"Public Place"
        }
    ],
    "sg:phone":"+1 418 727 3750",
    "sg:postcode":"G5L 1P4",
    "sg:province":"QC",
    "wof:name":"Quebec Societe Immobiliere",
    "wof:placetype":"venue"
},
  "geometry": {"coordinates":[-68.516541,48.462032],"type":"Point"}
}