{
  "type": "Feature",
  "properties": {
    "addr:full":"66 Woodland Dr # 1 Hay River NT X0E 1G1",
    "addr:housenumber":"66",
    "addr:postcode":"x0e 1g1",
    "addr:street":"Woodland Dr # 1",
    "iso:country":"CA",
    "sg:address":"66 Woodland Dr # 1",
    "sg:city":"Hay River",
    "sg:classifiers":[
        {
            "category":"Utilities",
            "type":"Services"
        }
    ],
    "sg:phone":"+1 867 874 6879",
    "sg:postcode":"X0E 1G1",
    "sg:province":"NT",
    "sg:tags":[
        "company",
        "electric"
    ],
    "wof:name":"Northland Utilities Ltd",
    "wof:placetype":"venue"
},
  "geometry": {"coordinates":[-115.788917541,60.809135437],"type":"Point"}
}