{
  "type": "Feature",
  "properties": {
    "iso:country":"CA",
    "sg:address":"2065 Rue Parthenais",
    "sg:city":"Montreal",
    "sg:classifiers":[
        {
            "category":"Professional",
            "subcategory":"Research",
            "type":"Services"
        }
    ],
    "sg:phone":"+1 514 249 1488",
    "sg:postcode":"H2K 3T1",
    "sg:province":"QC",
    "sg:tags":[
        "environmental",
        "ecological"
    ],
    "wof:name":"Sol Air Eau Environnement",
    "wof:placetype":"venue"
},
  "geometry": {"coordinates":[-73.557144165,45.5301017761],"type":"Point"}
}