{
  "type": "Feature",
  "properties": {
    "addr:full":"8195 Rue Pascal-Gagnon Saint-Leonard QC H1P 1Y5",
    "addr:housenumber":"8195",
    "addr:postcode":"h1p 1y5",
    "addr:street":"Rue Pascal-Gagnon",
    "iso:country":"CA",
    "sg:address":"8195 Rue Pascal-Gagnon",
    "sg:city":"Saint-Leonard",
    "sg:classifiers":[
        {
            "category":"Manufacturing",
            "subcategory":"Metals",
            "type":"Manufacturing & Wholesale Goods"
        }
    ],
    "sg:phone":"+1 514 321 2432",
    "sg:postcode":"H1P 1Y5",
    "sg:province":"QC",
    "sg:tags":[
        "fastener"
    ],
    "wof:name":"Desormeau Industries Inc",
    "wof:placetype":"venue"
},
  "geometry": {"coordinates":[-73.5812,45.599598],"type":"Point"}
}