{
  "type": "Feature",
  "properties": {
    "addr:full":"241 Boul Labbe N Victoriaville QC G6P 1A7",
    "addr:housenumber":"241",
    "addr:postcode":"g6p 1a7",
    "addr:street":"Boul Labbe N",
    "iso:country":"CA",
    "sg:address":"241 Boul Labbe N",
    "sg:city":"Victoriaville",
    "sg:classifiers":[
        {
            "category":"Shopping",
            "subcategory":"Used Merchandise",
            "type":"Retail Goods"
        }
    ],
    "sg:phone":"+1 819 758 6777",
    "sg:postcode":"G6P 1A7",
    "sg:province":"QC",
    "sg:tags":[
        "building",
        "material"
    ],
    "wof:name":"Location Tg Enr",
    "wof:placetype":"venue"
},
  "geometry": {"coordinates":[-71.95068359379999,46.0687904358],"type":"Point"}
}