{
  "type": "Feature",
  "properties": {
    "addr:full":"320 5E Rue Quebec QC G1L 2R9",
    "addr:housenumber":"320",
    "addr:postcode":"g1l 2r9",
    "addr:street":"5E Rue Quebec",
    "iso:country":"CA",
    "sg:address":"320 5E Rue",
    "sg:city":"Quebec",
    "sg:classifiers":[
        {
            "category":"Building & Trades",
            "subcategory":"Construction",
            "type":"Services"
        }
    ],
    "sg:phone":"+1 418 524 3568",
    "sg:postcode":"G1L 2R9",
    "sg:province":"QC",
    "sg:tags":[
        "general",
        "contractor"
    ],
    "wof:name":"Quebechab Limitee",
    "wof:placetype":"venue"
},
  "geometry": {"coordinates":[-71.2262268066,46.8233909607],"type":"Point"}
}