{
  "type": "Feature",
  "properties": {
    "iso:country":"CA",
    "sg:city":"Calgary",
    "sg:classifiers":[
        {
            "category":"Retail",
            "subcategory":"Laundry & Dry Cleaning",
            "type":"Services"
        }
    ],
    "sg:phone":"+1 403 275 6337",
    "sg:postcode":"T3K 1J7",
    "sg:province":"AB",
    "sg:tags":[
        "cleaners"
    ],
    "wof:name":"Barker's Fine Dry Cleaning",
    "wof:placetype":"venue"
},
  "geometry": {"coordinates":[-114.071182251,51.1273765564],"type":"Point"}
}