{
  "type": "Feature",
  "properties": {
    "iso:country":"CA",
    "sg:address":"3522 19 St SW",
    "sg:city":"Calgary",
    "sg:classifiers":[
        {
            "category":"Education",
            "subcategory":"Dance Studio",
            "type":"Public Place"
        }
    ],
    "sg:phone":"+1 403 201 5519",
    "sg:postcode":"T2T 4X6",
    "sg:province":"AB",
    "sg:tags":[
        "instruction",
        "dancing"
    ],
    "wof:name":"Counterpoint Dance Academy",
    "wof:placetype":"venue"
},
  "geometry": {"coordinates":[-114.106186,51.022861],"type":"Point"}
}