{
  "type": "Feature",
  "properties": {
    "iso:country":"CA",
    "sg:city":"St. John's",
    "sg:classifiers":[
        {
            "category":"Health Services",
            "subcategory":"Health Practitioner",
            "type":"Services"
        }
    ],
    "sg:phone":"+1 709 738 5665",
    "sg:postcode":"A1E 1W6",
    "sg:province":"NL",
    "sg:tags":[
        "psychologist"
    ],
    "wof:name":"H Khalili & Assoc",
    "wof:placetype":"venue"
},
  "geometry": {"coordinates":[-58.5973587036,48.5482978821],"type":"Point"}
}