{
  "type": "Feature",
  "properties": {
    "iso:country":"CA",
    "sg:address":"2473 Thorn Lodge Dr",
    "sg:city":"Mississauga",
    "sg:classifiers":[
        {
            "category":"Organizations",
            "subcategory":"Religious Organization",
            "type":"Services"
        }
    ],
    "sg:phone":"+1 905 822 8132",
    "sg:postcode":"L5K 1K8",
    "sg:province":"ON",
    "sg:tags":[
        "church"
    ],
    "wof:name":"St Francis of Assisi Parish",
    "wof:placetype":"venue"
},
  "geometry": {"coordinates":[-79.6722335815,43.5273551941],"type":"Point"}
}