{
  "type": "Feature",
  "properties": {
    "addr:full":"104 13th St E Brandon MB R7A 5X8",
    "addr:housenumber":"104",
    "addr:postcode":"r7a 5x8",
    "addr:street":"13Th St E",
    "iso:country":"CA",
    "sg:address":"104 13th St E",
    "sg:city":"Brandon",
    "sg:classifiers":[
        {
            "category":"Building & Trades",
            "subcategory":"Construction",
            "type":"Services"
        }
    ],
    "sg:phone":"+1 204 726 4630",
    "sg:postcode":"R7A 5X8",
    "sg:province":"MB",
    "sg:tags":[
        "maker",
        "cabinet"
    ],
    "wof:name":"Heritage Woodworking",
    "wof:placetype":"venue"
},
  "geometry": {"coordinates":[-99.922462,49.848225],"type":"Point"}
}