{
  "type": "Feature",
  "properties": {
    "addr:full":"2486 Dunwin Dr Mississauga ON L5L 1J9",
    "addr:housenumber":"2486",
    "addr:postcode":"l5l 1j9",
    "addr:street":"Dunwin Dr",
    "iso:country":"CA",
    "sg:address":"2486 Dunwin Dr",
    "sg:city":"Mississauga",
    "sg:classifiers":[
        {
            "category":"Wholesale",
            "subcategory":"Electrical",
            "type":"Manufacturing & Wholesale Goods"
        }
    ],
    "sg:phone":"+1 905 828 7700",
    "sg:postcode":"L5L 1J9",
    "sg:province":"ON",
    "sg:tags":[
        "battery",
        "equipment",
        "charging"
    ],
    "wof:name":"Edison Source Norvik CO",
    "wof:placetype":"venue"
},
  "geometry": {"coordinates":[-79.680008,43.529938],"type":"Point"}
}