{
  "type": "Feature",
  "properties": {
    "addr:full":"Markham ON L3R 2M8",
    "addr:postcode":"l3r 2m8",
    "iso:country":"CA",
    "sg:city":"Markham",
    "sg:classifiers":[
        {
            "category":"Wholesale",
            "subcategory":"Electrical",
            "type":"Manufacturing & Wholesale Goods"
        }
    ],
    "sg:phone":"+1 905 479 0797",
    "sg:postcode":"L3R 2M8",
    "sg:province":"ON",
    "sg:tags":[
        "equipment",
        "electronic",
        "supply"
    ],
    "wof:name":"Btw Electronic Parts",
    "wof:placetype":"venue"
},
  "geometry": {"coordinates":[-79.34303300000001,43.823822],"type":"Point"}
}