{
  "type": "Feature",
  "properties": {
    "addr:full":"Calgary AB T2J 7A4",
    "addr:postcode":"t2j 7a4",
    "iso:country":"CA",
    "sg:city":"Calgary",
    "sg:classifiers":[
        {
            "category":"Restaurant",
            "type":"Food & Drink"
        }
    ],
    "sg:phone":"+1 403 271 7777",
    "sg:postcode":"T2J 7A4",
    "sg:province":"AB",
    "wof:name":"Boston Pizza",
    "wof:placetype":"venue"
},
  "geometry": {"coordinates":[-114.06822200000001,50.941975],"type":"Point"}
}