{
  "type": "Feature",
  "properties": {
    "addr:full":"Longueuil QC J4K 5G7",
    "addr:postcode":"j4k 5g7",
    "iso:country":"CA",
    "sg:city":"Longueuil",
    "sg:classifiers":[
        {
            "category":"Real Estate",
            "subcategory":"Real Estate Agent",
            "type":"Services"
        }
    ],
    "sg:phone":"+1 450 677 9297",
    "sg:postcode":"J4K 5G7",
    "sg:province":"QC",
    "sg:tags":[
        "appraiser"
    ],
    "wof:name":"Pierre Moreau & Assoc",
    "wof:placetype":"venue"
},
  "geometry": {"coordinates":[-73.5237121582,45.5234298706],"type":"Point"}
}