{
  "type": "Feature",
  "properties": {
    "addr:full":"100 Rue Goyer # 114 LA Prairie QC J5R 5G5",
    "addr:housenumber":"100",
    "addr:postcode":"j5r 5g5",
    "addr:street":"Rue Goyer # 114",
    "iso:country":"CA",
    "sg:address":"100 Rue Goyer # 114",
    "sg:city":"LA Prairie",
    "sg:classifiers":[
        {
            "category":"Shopping",
            "type":"Retail Goods"
        }
    ],
    "sg:phone":"+1 450 444 1733",
    "sg:postcode":"J5R 5G5",
    "sg:province":"QC",
    "sg:tags":[
        "leather",
        "clothes",
        "art",
        "gallery",
        "dealer"
    ],
    "wof:name":"Noah's Art",
    "wof:placetype":"venue"
},
  "geometry": {"coordinates":[-73.50216674799999,45.3985671997],"type":"Point"}
}