{
  "type": "Feature",
  "properties": {
    "addr:full":"648 103 Ave Dawson Creek BC V1G 2E8",
    "addr:housenumber":"103",
    "addr:postcode":"v1g 2e8",
    "addr:street":"Ave",
    "iso:country":"CA",
    "sg:address":"648 103 Ave",
    "sg:city":"Dawson Creek",
    "sg:classifiers":[
        {
            "category":"Cinema",
            "subcategory":"Movie Theater",
            "type":"Entertainment"
        }
    ],
    "sg:phone":"+1 250 782 7117",
    "sg:postcode":"V1G 2E8",
    "sg:province":"BC",
    "wof:name":"Center Cinema",
    "wof:placetype":"venue"
},
  "geometry": {"coordinates":[-120.219688416,55.7562294006],"type":"Point"}
}