{
  "type": "Feature",
  "properties": {
    "iso:country":"CA",
    "sg:city":"Coquitlam",
    "sg:classifiers":[
        {
            "category":"Health Services",
            "subcategory":"Health Practitioner",
            "type":"Services"
        }
    ],
    "sg:phone":"+1 604 526 1911",
    "sg:postcode":"V3K 6V7",
    "sg:province":"BC",
    "sg:tags":[
        "physiotherapist"
    ],
    "wof:name":"Excel Physiotherapy",
    "wof:placetype":"venue"
},
  "geometry": {"coordinates":[-122.852554321,49.238117218],"type":"Point"}
}