{
  "type": "Feature",
  "properties": {
    "addr:full":"4488 Chaple Rd Cardigan PE C0A 1G0",
    "addr:housenumber":"4488",
    "addr:postcode":"c0a 1g0",
    "addr:street":"Chaple Rd",
    "iso:country":"CA",
    "sg:address":"4488 Chaple Rd",
    "sg:city":"Cardigan",
    "sg:classifiers":[
        {
            "category":"Personal",
            "subcategory":"Beauty Salon",
            "type":"Services"
        }
    ],
    "sg:phone":"+1 902 583 2003",
    "sg:postcode":"C0A 1G0",
    "sg:province":"PE",
    "wof:name":"Vera's Beauty Salon",
    "wof:placetype":"venue"
},
  "geometry": {"coordinates":[-62.620144,46.235298],"type":"Point"}
}