{
  "type": "Feature",
  "properties": {
    "iso:country":"CA",
    "sg:address":"1053 Boul Saint-Laurent",
    "sg:city":"Montreal",
    "sg:classifiers":[
        {
            "category":"Restaurant",
            "type":"Food & Drink"
        }
    ],
    "sg:phone":"+1 514 875 8388",
    "sg:postcode":"H2Z 1J6",
    "sg:province":"QC",
    "wof:name":"Cite Imperial",
    "wof:placetype":"venue"
},
  "geometry": {"coordinates":[-73.560051,45.50832],"type":"Point"}
}