{
  "type": "Feature",
  "properties": {
    "addr:full":"925 Eagle Dr Kelowna BC V1Y 4S9",
    "addr:housenumber":"925",
    "addr:postcode":"v1y 4s9",
    "addr:street":"Eagle Dr",
    "iso:country":"CA",
    "sg:address":"925 Eagle Dr",
    "sg:city":"Kelowna",
    "sg:classifiers":[
        {
            "category":"Building & Trades",
            "subcategory":"Construction",
            "type":"Services"
        }
    ],
    "sg:phone":"+1 250 763 5057",
    "sg:postcode":"V1Y 4S9",
    "sg:province":"BC",
    "sg:tags":[
        "painter"
    ],
    "wof:name":"Okanagan Painting & Decor Ltd",
    "wof:placetype":"venue"
},
  "geometry": {"coordinates":[-119.44959299999999,49.899189],"type":"Point"}
}