{
  "type": "Feature",
  "properties": {
    "addr:full":"29 Main St Carrot River SK S0E 0L0",
    "addr:housenumber":"29",
    "addr:postcode":"s0e 0l0",
    "addr:street":"Main St",
    "iso:country":"CA",
    "sg:address":"29 Main St",
    "sg:city":"Carrot River",
    "sg:classifiers":[
        {
            "category":"Professional",
            "subcategory":"Accounting & Tax Preparation",
            "type":"Services"
        }
    ],
    "sg:phone":"+1 306 768 2838",
    "sg:postcode":"S0E 0L0",
    "sg:province":"SK",
    "sg:tags":[
        "bookkeeping",
        "general"
    ],
    "wof:name":"Jascal Bookkeeping",
    "wof:placetype":"venue"
},
  "geometry": {"coordinates":[-103.587532,53.28336],"type":"Point"}
}