{
  "type": "Feature",
  "properties": {
    "addr:full":"120 Clifford St Sarnia ON N7T 8C3",
    "addr:housenumber":"120",
    "addr:postcode":"n7t 8c3",
    "addr:street":"Clifford St",
    "iso:country":"CA",
    "sg:address":"120 Clifford St",
    "sg:city":"Sarnia",
    "sg:classifiers":[
        {
            "category":"Railroad",
            "type":"Transportation"
        }
    ],
    "sg:phone":"+1 519 383 6131",
    "sg:postcode":"N7T 8C3",
    "sg:province":"ON",
    "wof:name":"Csx Rail Transport",
    "wof:placetype":"venue"
},
  "geometry": {"coordinates":[-82.4177398682,42.9558906555],"type":"Point"}
}