{
  "type": "Feature",
  "properties": {
    "iso:country":"CA",
    "sg:address":"10 Adelaide St N",
    "sg:city":"Chatham",
    "sg:classifiers":[
        {
            "category":"Building & Trades",
            "subcategory":"Construction",
            "type":"Services"
        }
    ],
    "sg:phone":"+1 519 351 4221",
    "sg:postcode":"N7M 4K3",
    "sg:province":"ON",
    "wof:name":"Westhoek Construction Ltd",
    "wof:placetype":"venue"
},
  "geometry": {"coordinates":[-82.1803894043,42.4066390991],"type":"Point"}
}