{
  "type": "Feature",
  "properties": {
    "iso:country":"CA",
    "sg:address":"8934 Cavendish Rd",
    "sg:city":"Hunter River",
    "sg:classifiers":[
        {
            "category":"Food & Beverages",
            "subcategory":"Groceries & Convenience Stores",
            "type":"Retail Goods"
        }
    ],
    "sg:phone":"+1 902 963 2370",
    "sg:postcode":"C0A 1N0",
    "sg:province":"PE",
    "sg:tags":[
        "grocer"
    ],
    "wof:name":"Cavendish Tourist Mart",
    "wof:placetype":"venue"
},
  "geometry": {"coordinates":[-63.3431472778,46.3517608643],"type":"Point"}
}