{
  "type": "Feature",
  "properties": {
    "addr:full":"2236 Mcgarrigle Rd Nanaimo BC V9S 4M6",
    "addr:housenumber":"2236",
    "addr:postcode":"v9s 4m6",
    "addr:street":"Mcgarrigle Rd",
    "iso:country":"CA",
    "sg:address":"2236 Mcgarrigle Rd",
    "sg:city":"Nanaimo",
    "sg:classifiers":[
        {
            "category":"Retail",
            "subcategory":"Laundry & Dry Cleaning",
            "type":"Services"
        }
    ],
    "sg:phone":"+1 250 758 7522",
    "sg:postcode":"V9S 4M6",
    "sg:province":"BC",
    "sg:tags":[
        "cleaners"
    ],
    "wof:name":"Pressed For Time Dry Cleaning",
    "wof:placetype":"venue"
},
  "geometry": {"coordinates":[-123.982338,49.194157],"type":"Point"}
}