{
  "type": "Feature",
  "properties": {
    "addr:full":"570 Hood Rd Markham ON L3R 4G7",
    "addr:housenumber":"570",
    "addr:postcode":"l3r 4g7",
    "addr:street":"Hood Rd",
    "iso:country":"CA",
    "sg:address":"570 Hood Rd",
    "sg:city":"Markham",
    "sg:classifiers":[
        {
            "category":"Professional",
            "subcategory":"Engineering",
            "type":"Services"
        }
    ],
    "sg:phone":"+1 905 474 5059",
    "sg:postcode":"L3R 4G7",
    "sg:province":"ON",
    "sg:tags":[
        "engineer"
    ],
    "wof:name":"Kazdan & Lalji Structural",
    "wof:placetype":"venue"
},
  "geometry": {"coordinates":[-79.330223,43.834278],"type":"Point"}
}