{
  "type": "Feature",
  "properties": {
    "addr:full":"4 Dominion Cres Lakeside NS B3T 1M1",
    "addr:housenumber":"4",
    "addr:postcode":"b3t 1m1",
    "addr:street":"Dominion Cres",
    "iso:country":"CA",
    "sg:address":"4 Dominion Cres",
    "sg:city":"Lakeside",
    "sg:classifiers":[
        {
            "category":"Wholesale",
            "subcategory":"Meat",
            "type":"Manufacturing & Wholesale Goods"
        }
    ],
    "sg:phone":"+1 902 876 2356",
    "sg:postcode":"B3T 1M1",
    "sg:province":"NS",
    "sg:tags":[
        "product"
    ],
    "wof:name":"Eastern Meat Purveyors Ltd",
    "wof:placetype":"venue"
},
  "geometry": {"coordinates":[-63.690487,44.643112],"type":"Point"}
}