{
  "type": "Feature",
  "properties": {
    "addr:full":"368 Division St Kingston ON K7K 4A5",
    "addr:housenumber":"368",
    "addr:postcode":"k7k 4a5",
    "addr:street":"Division St",
    "iso:country":"CA",
    "sg:address":"368 Division St",
    "sg:city":"Kingston",
    "sg:classifiers":[
        {
            "category":"Food & Beverages",
            "subcategory":"Groceries & Convenience Stores",
            "type":"Retail Goods"
        }
    ],
    "sg:phone":"+1 613 544 9513",
    "sg:postcode":"K7K 4A5",
    "sg:province":"ON",
    "wof:name":"Division Street Market",
    "wof:placetype":"venue"
},
  "geometry": {"coordinates":[-76.4945449829,44.2393569946],"type":"Point"}
}