{
  "type": "Feature",
  "properties": {
    "addr:full":"Mississauga ON L5T 2B4",
    "addr:postcode":"l5t 2b4",
    "iso:country":"CA",
    "sg:city":"Mississauga",
    "sg:classifiers":[
        {
            "category":"Building & Trades",
            "subcategory":"Electrical",
            "type":"Services"
        }
    ],
    "sg:phone":"+1 905 564 4905",
    "sg:postcode":"L5T 2B4",
    "sg:province":"ON",
    "sg:tags":[
        "electric",
        "contractor"
    ],
    "wof:name":"Afonso Electrical Systems",
    "wof:placetype":"venue"
},
  "geometry": {"coordinates":[-79.6525344849,43.6560745239],"type":"Point"}
}