{
  "type": "Feature",
  "properties": {
    "addr:full":"905 Rue Saint-Jean-Baptiste Nicolet QC J3T 1W4",
    "addr:housenumber":"905",
    "addr:postcode":"j3t 1w4",
    "addr:street":"Rue Saint-Jean-Baptiste",
    "iso:country":"CA",
    "sg:address":"905 Rue Saint-Jean-Baptiste",
    "sg:city":"Nicolet",
    "sg:classifiers":[
        {
            "category":"Organizations",
            "subcategory":"Religious Organization",
            "type":"Services"
        }
    ],
    "sg:phone":"+1 819 293 4586",
    "sg:postcode":"J3T 1W4",
    "sg:province":"QC",
    "sg:tags":[
        "home",
        "rest"
    ],
    "wof:name":"Maison St-Joseph",
    "wof:placetype":"venue"
},
  "geometry": {"coordinates":[-72.6303939819,46.2325553894],"type":"Point"}
}