{
  "type": "Feature",
  "properties": {
    "addr:full":"Gimli MB R0C 1B1",
    "addr:postcode":"r0c 1b1",
    "iso:country":"CA",
    "sg:city":"Gimli",
    "sg:classifiers":[
        {
            "category":"Museum",
            "type":"Entertainment"
        }
    ],
    "sg:phone":"+1 204 642 4001",
    "sg:postcode":"R0C 1B1",
    "sg:province":"MB",
    "wof:name":"New Iceland Heritage Museum",
    "wof:placetype":"venue"
},
  "geometry": {"coordinates":[-96.98555755620001,50.6368598938],"type":"Point"}
}