{
  "type": "Feature",
  "properties": {
    "addr:full":"165 Terminal Ave Nanaimo BC V9R 5C6",
    "addr:housenumber":"165",
    "addr:postcode":"v9r 5c6",
    "addr:street":"Terminal Ave",
    "iso:country":"CA",
    "sg:address":"165 Terminal Ave",
    "sg:city":"Nanaimo",
    "sg:classifiers":[
        {
            "category":"Autos & Motor Vehicles",
            "subcategory":"Automobile Sales",
            "type":"Retail Goods"
        }
    ],
    "sg:phone":"+1 250 753 1099",
    "sg:postcode":"V9R 5C6",
    "sg:province":"BC",
    "sg:tags":[
        "car",
        "dealer"
    ],
    "wof:name":"South Side Motors Ltd",
    "wof:placetype":"venue"
},
  "geometry": {"coordinates":[-123.94016999999999,49.16777],"type":"Point"}
}