{
  "type": "Feature",
  "properties": {
    "iso:country":"CA",
    "sg:city":"Bloomfield",
    "sg:classifiers":[
        {
            "category":"Home & Garden",
            "subcategory":"Garden Supply",
            "type":"Retail Goods"
        }
    ],
    "sg:phone":"+1 613 393 3251",
    "sg:postcode":"K0K 1G0",
    "sg:province":"ON",
    "sg:tags":[
        "center",
        "landscape",
        "contractor"
    ],
    "wof:name":"Quinte Isles Landscaping",
    "wof:placetype":"venue"
},
  "geometry": {"coordinates":[-77.20988464360001,43.9882240295],"type":"Point"}
}