{
  "type": "Feature",
  "properties": {
    "addr:full":"986 Wall St Winnipeg MB R3G 2V3",
    "addr:housenumber":"986",
    "addr:postcode":"r3g 2v3",
    "addr:street":"Wall St",
    "iso:country":"CA",
    "sg:address":"986 Wall St",
    "sg:city":"Winnipeg",
    "sg:classifiers":[
        {
            "category":"Manufacturing",
            "subcategory":"Tools & Machinery",
            "type":"Manufacturing & Wholesale Goods"
        }
    ],
    "sg:phone":"+1 204 772 2481",
    "sg:postcode":"R3G 2V3",
    "sg:province":"MB",
    "sg:tags":[
        "automobile",
        "parts",
        "refrigeration",
        "supply"
    ],
    "wof:name":"Central Transport Refrign Ltd",
    "wof:placetype":"venue"
},
  "geometry": {"coordinates":[-97.18218231199999,49.8960647583],"type":"Point"}
}