{
  "type": "Feature",
  "properties": {
    "addr:full":"Vancouver BC V6C 1A1",
    "addr:postcode":"v6c 1a1",
    "iso:country":"CA",
    "sg:city":"Vancouver",
    "sg:classifiers":[
        {
            "category":"Restaurant",
            "type":"Food & Drink"
        }
    ],
    "sg:phone":"+1 604 689 9140",
    "sg:postcode":"V6C 1A1",
    "sg:province":"BC",
    "wof:name":"Charlie's Fish N' Chips",
    "wof:placetype":"venue"
},
  "geometry": {"coordinates":[-123.114318848,49.2857208252],"type":"Point"}
}