{
  "type": "Feature",
  "properties": {
    "addr:full":"334 Guelph St Georgetown ON L7G 4B5",
    "addr:housenumber":"334",
    "addr:postcode":"l7g 4b5",
    "addr:street":"Guelph St",
    "iso:country":"CA",
    "sg:address":"334 Guelph St",
    "sg:city":"Georgetown",
    "sg:classifiers":[
        {
            "category":"Wholesale",
            "subcategory":"Auto Parts",
            "type":"Manufacturing & Wholesale Goods"
        }
    ],
    "sg:phone":"+1 905 877 0143",
    "sg:postcode":"L7G 4B5",
    "sg:province":"ON",
    "sg:tags":[
        "body",
        "automobile",
        "shop"
    ],
    "wof:name":"Carquest",
    "wof:placetype":"venue"
},
  "geometry": {"coordinates":[-79.88715362550001,43.6492424011],"type":"Point"}
}