{
  "type": "Feature",
  "properties": {
    "addr:full":"28 Willow St Pictou NS B0K 1H0",
    "addr:housenumber":"28",
    "addr:postcode":"b0k 1h0",
    "addr:street":"Willow St",
    "iso:country":"CA",
    "sg:address":"28 Willow St",
    "sg:city":"Pictou",
    "sg:classifiers":[
        {
            "category":"Government",
            "subcategory":"Office",
            "type":"Public Place"
        }
    ],
    "sg:phone":"+1 902 485 4311",
    "sg:postcode":"B0K 1H0",
    "sg:province":"NS",
    "sg:tags":[
        "village"
    ],
    "wof:name":"Pictou County Municipal Clerk",
    "wof:placetype":"venue"
},
  "geometry": {"coordinates":[-62.7154350281,45.6771965027],"type":"Point"}
}