{
  "type": "Feature",
  "properties": {
    "addr:full":"Wapella SK S0G 4Z0",
    "addr:postcode":"s0g 4z0",
    "iso:country":"CA",
    "sg:city":"Wapella",
    "sg:classifiers":[
        {
            "category":"Travel",
            "subcategory":"Hotels & Motels",
            "type":"Entertainment"
        }
    ],
    "sg:phone":"+1 306 532 4253",
    "sg:postcode":"S0G 4Z0",
    "sg:province":"SK",
    "wof:name":"Hotel Commercial",
    "wof:placetype":"venue"
},
  "geometry": {"coordinates":[-101.96998600000001,50.260963],"type":"Point"}
}