{
  "type": "Feature",
  "properties": {
    "iso:country":"CA",
    "sg:address":"2950 Dundas St W",
    "sg:city":"Toronto",
    "sg:classifiers":[
        {
            "category":"Health Services",
            "subcategory":"Chiropractor",
            "type":"Services"
        }
    ],
    "sg:phone":"+1 416 766 6572",
    "sg:postcode":"M6P 1Y8",
    "sg:province":"ON",
    "wof:name":"Atlas Chiropractic",
    "wof:placetype":"venue"
},
  "geometry": {"coordinates":[-79.4678192139,43.6655845642],"type":"Point"}
}