{
  "type": "Feature",
  "properties": {
    "addr:full":"1411 Rue Peel Montreal QC H3A 1S5",
    "addr:housenumber":"1411",
    "addr:postcode":"h3a 1s5",
    "addr:street":"Rue Peel",
    "iso:country":"CA",
    "sg:address":"1411 Rue Peel",
    "sg:city":"Montreal",
    "sg:classifiers":[
        {
            "category":"Communications",
            "subcategory":"Radio Station",
            "type":"Services"
        }
    ],
    "sg:phone":"+1 514 877 6670",
    "sg:postcode":"H3A 1S5",
    "sg:province":"QC",
    "sg:tags":[
        "company",
        "broadcasting"
    ],
    "wof:name":"Telemedia Communications Inc",
    "wof:placetype":"venue"
},
  "geometry": {"coordinates":[-73.5729675293,45.5001907349],"type":"Point"}
}