{
  "type": "Feature",
  "properties": {
    "addr:full":"4902 Rue D'Amiens Montreal-Nord QC H1G 3E7",
    "addr:housenumber":"4902",
    "addr:postcode":"h1g 3e7",
    "addr:street":"Rue D'Amiens",
    "iso:country":"CA",
    "sg:address":"4902 Rue D'Amiens",
    "sg:city":"Montreal-Nord",
    "sg:classifiers":[
        {
            "category":"Food & Beverages",
            "subcategory":"Bakery",
            "type":"Retail Goods"
        }
    ],
    "sg:phone":"+1 514 325 7412",
    "sg:postcode":"H1G 3E7",
    "sg:province":"QC",
    "sg:tags":[
        "baker"
    ],
    "wof:name":"Boulangerie & Patisserie Amien",
    "wof:placetype":"venue"
},
  "geometry": {"coordinates":[-73.619247,45.597565],"type":"Point"}
}