{
  "type": "Feature",
  "properties": {
    "addr:full":"5491 Timberlea Blvd Mississauga ON L4W 2T6",
    "addr:housenumber":"5491",
    "addr:postcode":"l4w 2t6",
    "addr:street":"Timberlea Blvd",
    "iso:country":"CA",
    "sg:address":"5491 Timberlea Blvd",
    "sg:city":"Mississauga",
    "sg:classifiers":[
        {
            "category":"Professional",
            "subcategory":"Management & Consulting",
            "type":"Services"
        }
    ],
    "sg:phone":"+1 905 282 0977",
    "sg:postcode":"L4W 2T6",
    "sg:province":"ON",
    "sg:tags":[
        "project"
    ],
    "wof:name":"Northern Projects Inc",
    "wof:placetype":"venue"
},
  "geometry": {"coordinates":[-79.64729309080001,43.6338653564],"type":"Point"}
}