{
  "type": "Feature",
  "properties": {
    "addr:full":"1544 Pelham St N Fonthill ON L0S 1E0",
    "addr:housenumber":"1544",
    "addr:postcode":"l0s 1e0",
    "addr:street":"Pelham St N Fonthill",
    "iso:country":"CA",
    "sg:address":"1544 Pelham St N",
    "sg:city":"Fonthill",
    "sg:classifiers":[
        {
            "category":"Building & Trades",
            "subcategory":"Construction",
            "type":"Services"
        }
    ],
    "sg:phone":"+1 905 892 3146",
    "sg:postcode":"L0S 1E0",
    "sg:province":"ON",
    "sg:tags":[
        "equipment",
        "computer",
        "electric",
        "contractor"
    ],
    "wof:name":"House of Electronics",
    "wof:placetype":"venue"
},
  "geometry": {"coordinates":[-79.285652,43.047016],"type":"Point"}
}