{
  "type": "Feature",
  "properties": {
    "iso:country":"CA",
    "sg:city":"Vancouver",
    "sg:classifiers":[
        {
            "category":"Personal",
            "type":"Services"
        }
    ],
    "sg:phone":"+1 604 264 9921",
    "sg:postcode":"V6M 2B5",
    "sg:province":"BC",
    "sg:tags":[
        "therapist",
        "massage"
    ],
    "wof:name":"Arbutus Acupuncture & Massage",
    "wof:placetype":"venue"
},
  "geometry": {"coordinates":[-123.152839661,49.2336845398],"type":"Point"}
}