{
  "type": "Feature",
  "properties": {
    "addr:full":"8793 Cambie St Vancouver BC V6P 3J9",
    "addr:housenumber":"8793",
    "addr:postcode":"v6p 3j9",
    "addr:street":"Cambie St",
    "iso:country":"CA",
    "sg:address":"8793 Cambie St",
    "sg:city":"Vancouver",
    "sg:classifiers":[
        {
            "category":"Manufacturing",
            "subcategory":"Tools & Machinery",
            "type":"Manufacturing & Wholesale Goods"
        }
    ],
    "sg:phone":"+1 604 322 2979",
    "sg:postcode":"V6P 3J9",
    "sg:province":"BC",
    "sg:tags":[
        "body",
        "shop",
        "purifying",
        "automobile",
        "air",
        "equipment",
        "cleaning"
    ],
    "wof:name":"Island Clean Air Inc",
    "wof:placetype":"venue"
},
  "geometry": {"coordinates":[-123.11747,49.206581],"type":"Point"}
}