{
  "type": "Feature",
  "properties": {
    "addr:full":"50 Kenview Blvd Brampton ON L6T 5S8",
    "addr:housenumber":"50",
    "addr:postcode":"l6t 5s8",
    "addr:street":"Kenview Blvd",
    "iso:country":"CA",
    "sg:address":"50 Kenview Blvd",
    "sg:city":"Brampton",
    "sg:classifiers":[
        {
            "category":"Wholesale",
            "subcategory":"Home Furnishings",
            "type":"Manufacturing & Wholesale Goods"
        }
    ],
    "sg:phone":"+1 905 789 3755",
    "sg:postcode":"L6T 5S8",
    "sg:province":"ON",
    "sg:tags":[
        "rug",
        "carpet"
    ],
    "wof:name":"G E Scnier CO",
    "wof:placetype":"venue"
},
  "geometry": {"coordinates":[-79.64501199999999,43.73917],"type":"Point"}
}