{
  "type": "Feature",
  "properties": {
    "addr:full":"RR 1 Hepworth ON N0H 1P0",
    "addr:postcode":"n0h 1p0",
    "addr:street":"Rr 1 Hepworth",
    "iso:country":"CA",
    "sg:address":"RR 1",
    "sg:city":"Hepworth",
    "sg:classifiers":[
        {
            "category":"Home & Garden",
            "subcategory":"Garden Supply",
            "type":"Retail Goods"
        }
    ],
    "sg:phone":"+1 519 935 3186",
    "sg:postcode":"N0H 1P0",
    "sg:province":"ON",
    "sg:tags":[
        "nurseryman"
    ],
    "wof:name":"Everest Nurseries",
    "wof:placetype":"venue"
},
  "geometry": {"coordinates":[-81.131187,44.633793],"type":"Point"}
}