{
  "type": "Feature",
  "properties": {
    "iso:country":"CA",
    "sg:address":"2170 Av Bedard",
    "sg:city":"Saint-Lazare",
    "sg:classifiers":[
        {
            "category":"Building & Trades",
            "subcategory":"Construction",
            "type":"Services"
        }
    ],
    "sg:phone":"+1 450 424 2464",
    "sg:postcode":"J7T 2E5",
    "sg:province":"QC",
    "sg:tags":[
        "roofing",
        "contractor",
        "consultant"
    ],
    "wof:name":"Toiture Jps",
    "wof:placetype":"venue"
},
  "geometry": {"coordinates":[-74.1354217529,45.4183616638],"type":"Point"}
}