{
  "type": "Feature",
  "properties": {
    "addr:full":"Saint-Alphonse-DE-Caplan QC G0C 2V0",
    "addr:postcode":"g0c 2v0",
    "iso:country":"CA",
    "sg:city":"Saint-Alphonse-DE-Caplan",
    "sg:classifiers":[
        {
            "category":"Organizations",
            "subcategory":"Professional Association",
            "type":"Services"
        }
    ],
    "sg:phone":"+1 418 388 5582",
    "sg:postcode":"G0C 2V0",
    "sg:province":"QC",
    "wof:name":"Club DE Peche Au Saumon Le",
    "wof:placetype":"venue"
},
  "geometry": {"coordinates":[-65.67924499510001,48.1011810303],"type":"Point"}
}