{
  "type": "Feature",
  "properties": {
    "addr:full":"116 Industry St York ON M6M 4L8",
    "addr:housenumber":"116",
    "addr:postcode":"m6m 4l8",
    "addr:street":"Industry St",
    "iso:country":"CA",
    "sg:address":"116 Industry St",
    "sg:city":"York",
    "sg:classifiers":[
        {
            "category":"Social Services",
            "subcategory":"Child Care",
            "type":"Services"
        }
    ],
    "sg:phone":"+1 416 769 0830",
    "sg:postcode":"M6M 4L8",
    "sg:province":"ON",
    "sg:tags":[
        "organization",
        "welfare"
    ],
    "wof:name":"Learning Enrichment Foundation",
    "wof:placetype":"venue"
},
  "geometry": {"coordinates":[-79.4922790527,43.693195343],"type":"Point"}
}