{
  "type": "Feature",
  "properties": {
    "addr:full":"Ottawa ON K1R 7S8",
    "addr:postcode":"k1r 7s8",
    "iso:country":"CA",
    "sg:city":"Ottawa",
    "sg:classifiers":[
        {
            "category":"Health Services",
            "subcategory":"Health Practitioner",
            "type":"Services"
        }
    ],
    "sg:phone":"+1 613 563 9816",
    "sg:postcode":"K1R 7S8",
    "sg:province":"ON",
    "sg:tags":[
        "psychologist"
    ],
    "wof:name":"Meissner, John PhD",
    "wof:placetype":"venue"
},
  "geometry": {"coordinates":[-75.7057189941,45.4191207886],"type":"Point"}
}