{
  "type": "Feature",
  "properties": {
    "addr:full":"2142 41st Ave W Vancouver BC V6M 1Z1",
    "addr:housenumber":"2142",
    "addr:postcode":"v6m 1z1",
    "addr:street":"41St Ave W",
    "iso:country":"CA",
    "sg:address":"2142 41st Ave W",
    "sg:city":"Vancouver",
    "sg:classifiers":[
        {
            "category":"Home & Garden",
            "subcategory":"Home Furnishings",
            "type":"Retail Goods"
        }
    ],
    "sg:phone":"+1 604 263 7300",
    "sg:postcode":"V6M 1Z1",
    "sg:province":"BC",
    "sg:tags":[
        "linen"
    ],
    "wof:name":"Ed's Fine Linens",
    "wof:placetype":"venue"
},
  "geometry": {"coordinates":[-123.156807,49.234451],"type":"Point"}
}