{
  "type": "Feature",
  "properties": {
    "iso:country":"CA",
    "sg:city":"Toronto",
    "sg:classifiers":[
        {
            "category":"Mining & Drilling",
            "type":"Manufacturing & Wholesale Goods"
        }
    ],
    "sg:phone":"+1 416 361 0737",
    "sg:postcode":"M5H 3V5",
    "sg:province":"ON",
    "sg:tags":[
        "exploration",
        "mineral"
    ],
    "wof:name":"Gowest Amalgamated Resources",
    "wof:placetype":"venue"
},
  "geometry": {"coordinates":[-79.38139343260001,43.6506271362],"type":"Point"}
}