{
  "type": "Feature",
  "properties": {
    "iso:country":"CA",
    "sg:address":"49 Rue Notre Dame",
    "sg:city":"Cap-Chat",
    "sg:classifiers":[
        {
            "category":"Social Services",
            "type":"Services"
        }
    ],
    "sg:phone":"+1 418 786 5594",
    "sg:postcode":"G0J 1E0",
    "sg:province":"QC",
    "sg:tags":[
        "organization",
        "welfare"
    ],
    "wof:name":"Clsc Des Berges",
    "wof:placetype":"venue"
},
  "geometry": {"coordinates":[-66.6870422363,49.0973243713],"type":"Point"}
}