{
  "type": "Feature",
  "properties": {
    "addr:full":"15 Antares Dr # 3A Nepean ON K2E 7Y9",
    "addr:housenumber":"15;3a",
    "addr:postcode":"k2e 7y9",
    "addr:street":"Antares Dr #",
    "iso:country":"CA",
    "sg:address":"15 Antares Dr # 3A",
    "sg:city":"Nepean",
    "sg:classifiers":[
        {
            "category":"Retail",
            "subcategory":"Repair Shop",
            "type":"Services"
        }
    ],
    "sg:phone":"+1 613 225 9752",
    "sg:postcode":"K2E 7Y9",
    "sg:province":"ON",
    "sg:tags":[
        "refinishing",
        "furniture"
    ],
    "wof:name":"Installations Deliveries Plus",
    "wof:placetype":"venue"
},
  "geometry": {"coordinates":[-75.70649719239999,45.3351364136],"type":"Point"}
}