{
  "type": "Feature",
  "properties": {
    "addr:full":"Spedden AB T0A 3E0",
    "addr:postcode":"t0a 3e0",
    "iso:country":"CA",
    "sg:city":"Spedden",
    "sg:classifiers":[
        {
            "category":"Food & Beverages",
            "subcategory":"Groceries & Convenience Stores",
            "type":"Retail Goods"
        }
    ],
    "sg:phone":"+1 780 636 3514",
    "sg:postcode":"T0A 3E0",
    "sg:province":"AB",
    "sg:tags":[
        "grocer"
    ],
    "wof:name":"Cholak's Store",
    "wof:placetype":"venue"
},
  "geometry": {"coordinates":[-111.728340149,54.1759300232],"type":"Point"}
}