{
  "type": "Feature",
  "properties": {
    "addr:full":"4310 Fairview St Burlington ON L7L 4Y8",
    "addr:housenumber":"4310",
    "addr:postcode":"l7l 4y8",
    "addr:street":"Fairview St",
    "iso:country":"CA",
    "sg:address":"4310 Fairview St",
    "sg:city":"Burlington",
    "sg:classifiers":[
        {
            "category":"Organizations",
            "subcategory":"Religious Organization",
            "type":"Services"
        }
    ],
    "sg:phone":"+1 905 333 9856",
    "sg:postcode":"L7L 4Y8",
    "sg:province":"ON",
    "sg:tags":[
        "church"
    ],
    "wof:name":"Halton Mosque",
    "wof:placetype":"venue"
},
  "geometry": {"coordinates":[-79.76905059809999,43.3681373596],"type":"Point"}
}