{
  "type": "Feature",
  "properties": {
    "addr:full":"250 Boul Wilfrid-Hamel Quebec QC G1L 5A7",
    "addr:housenumber":"250",
    "addr:postcode":"g1l 5a7",
    "addr:street":"Boul Wilfrid-Hamel",
    "iso:country":"CA",
    "sg:address":"250 Boul Wilfrid-Hamel",
    "sg:city":"Quebec",
    "sg:classifiers":[
        {
            "category":"Sports & Exercise",
            "subcategory":"Race Track",
            "type":"Entertainment"
        }
    ],
    "sg:phone":"+1 418 524 5283",
    "sg:postcode":"G1L 5A7",
    "sg:province":"QC",
    "sg:tags":[
        "equipment",
        "supply"
    ],
    "wof:name":"Hippodrome DE Quebec",
    "wof:placetype":"venue"
},
  "geometry": {"coordinates":[-71.245598,46.826534],"type":"Point"}
}