{
  "type": "Feature",
  "properties": {
    "addr:full":"2 Meadow St Meadow Lake SK S9X 1M4",
    "addr:housenumber":"2",
    "addr:postcode":"s9x 1m4",
    "addr:street":"Meadow St",
    "iso:country":"CA",
    "sg:address":"2 Meadow St",
    "sg:city":"Meadow Lake",
    "sg:classifiers":[
        {
            "category":"Building & Trades",
            "subcategory":"Construction",
            "type":"Services"
        }
    ],
    "sg:phone":"+1 306 236 5990",
    "sg:postcode":"S9X 1M4",
    "sg:province":"SK",
    "sg:tags":[
        "maker",
        "cabinet"
    ],
    "wof:name":"Hebert's Woodworking",
    "wof:placetype":"venue"
},
  "geometry": {"coordinates":[-108.456481934,54.1198387146],"type":"Point"}
}