{
  "type": "Feature",
  "properties": {
    "iso:country":"CA",
    "sg:address":"205 Lakeshore Rd E",
    "sg:city":"Mississauga",
    "sg:classifiers":[
        {
            "category":"Shopping",
            "subcategory":"Department Store",
            "type":"Retail Goods"
        }
    ],
    "sg:phone":"+1 905 278 8047",
    "sg:postcode":"L5G 1G2",
    "sg:province":"ON",
    "sg:tags":[
        "variety"
    ],
    "wof:name":"Family Dollar Store",
    "wof:placetype":"venue"
},
  "geometry": {"coordinates":[-79.5786437988,43.55809021],"type":"Point"}
}