{
  "type": "Feature",
  "properties": {
    "addr:full":"Savant Lake ON P0V 2S0",
    "addr:postcode":"p0v 2s0",
    "addr:street":"Lake",
    "iso:country":"CA",
    "sg:city":"Savant Lake",
    "sg:classifiers":[
        {
            "category":"Education",
            "subcategory":"School",
            "type":"Public Place"
        }
    ],
    "sg:phone":"+1 807 584 2242",
    "sg:postcode":"P0V 2S0",
    "sg:province":"ON",
    "wof:name":"Savant Lake School",
    "wof:placetype":"venue"
},
  "geometry": {"coordinates":[-90.70960998539999,50.2464675903],"type":"Point"}
}