{
  "type": "Feature",
  "properties": {
    "addr:full":"52 Speers Rd Winnipeg MB R2J 1M3",
    "addr:housenumber":"52",
    "addr:postcode":"r2j 1m3",
    "addr:street":"Speers Rd",
    "iso:country":"CA",
    "sg:address":"52 Speers Rd",
    "sg:city":"Winnipeg",
    "sg:classifiers":[
        {
            "category":"Manufacturing",
            "subcategory":"Apparel",
            "type":"Manufacturing & Wholesale Goods"
        }
    ],
    "sg:phone":"+1 204 231 1390",
    "sg:postcode":"R2J 1M3",
    "sg:province":"MB",
    "sg:tags":[
        "flag",
        "sign"
    ],
    "wof:name":"Jade Sign Works",
    "wof:placetype":"venue"
},
  "geometry": {"coordinates":[-97.07266199999999,49.872185],"type":"Point"}
}