{
  "type": "Feature",
  "properties": {
    "addr:full":"832 Fennell Ave E Hamilton ON L8V 1V6",
    "addr:housenumber":"832",
    "addr:postcode":"l8v 1v6",
    "addr:street":"Fennell Ave E",
    "iso:country":"CA",
    "sg:address":"832 Fennell Ave E",
    "sg:city":"Hamilton",
    "sg:classifiers":[
        {
            "category":"Restaurant",
            "type":"Food & Drink"
        }
    ],
    "sg:phone":"+1 905 385 5882",
    "sg:postcode":"L8V 1V6",
    "sg:province":"ON",
    "sg:tags":[
        "parlor",
        "ice",
        "cream"
    ],
    "wof:name":"Dairy Queen",
    "wof:placetype":"venue"
},
  "geometry": {"coordinates":[-79.84702299999999,43.22971],"type":"Point"}
}