{
  "type": "Feature",
  "properties": {
    "iso:country":"CA",
    "sg:address":"7633 Rue Centrale",
    "sg:city":"Lasalle",
    "sg:classifiers":[
        {
            "category":"Home & Garden",
            "subcategory":"Building Materials",
            "type":"Retail Goods"
        }
    ],
    "sg:phone":"+1 514 364 1722",
    "sg:postcode":"H8P 1L1",
    "sg:province":"QC",
    "sg:tags":[
        "plumbing",
        "fixture",
        "supply"
    ],
    "wof:name":"Lambert Materiaux DE Plomberie",
    "wof:placetype":"venue"
},
  "geometry": {"coordinates":[-73.597794,45.431633],"type":"Point"}
}