{
  "type": "Feature",
  "properties": {
    "iso:country":"CA",
    "sg:address":"115 Rue Galt O",
    "sg:city":"Sherbrooke",
    "sg:classifiers":[
        {
            "category":"Organizations",
            "subcategory":"Community Association",
            "type":"Services"
        }
    ],
    "sg:phone":"+1 819 821 2233",
    "sg:postcode":"J1H 1X8",
    "sg:province":"QC",
    "sg:tags":[
        "second",
        "store",
        "hand"
    ],
    "wof:name":"Partage St-Francois",
    "wof:placetype":"venue"
},
  "geometry": {"coordinates":[-71.8868179321,45.3938827515],"type":"Point"}
}