{
  "type": "Feature",
  "properties": {
    "addr:full":"161 Rue DE Normandie Aylmer QC J9H 2R5",
    "addr:housenumber":"161",
    "addr:postcode":"j9h 2r5",
    "addr:street":"Rue De Normandie",
    "iso:country":"CA",
    "sg:address":"161 Rue DE Normandie",
    "sg:city":"Aylmer",
    "sg:classifiers":[
        {
            "category":"Shopping",
            "subcategory":"Computers & Home Electronics",
            "type":"Retail Goods"
        }
    ],
    "sg:phone":"+1 613 852 1780",
    "sg:postcode":"J9H 2R5",
    "sg:province":"QC",
    "sg:tags":[
        "parts",
        "supply"
    ],
    "wof:name":"Wray, Jeffrey",
    "wof:placetype":"venue"
},
  "geometry": {"coordinates":[-75.844872,45.394909],"type":"Point"}
}