{
  "type": "Feature",
  "properties": {
    "addr:full":"1155 Vanier Dr Mississauga ON L5H 3W9",
    "addr:housenumber":"1155",
    "addr:postcode":"l5h 3w9",
    "addr:street":"Vanier Dr",
    "iso:country":"CA",
    "sg:address":"1155 Vanier Dr",
    "sg:city":"Mississauga",
    "sg:classifiers":[
        {
            "category":"Professional",
            "subcategory":"Advertising",
            "type":"Services"
        }
    ],
    "sg:phone":"+1 905 274 7242",
    "sg:postcode":"L5H 3W9",
    "sg:province":"ON",
    "sg:tags":[
        "counselor"
    ],
    "wof:name":"Bridge Promotional Advertising",
    "wof:placetype":"venue"
},
  "geometry": {"coordinates":[-79.624123,43.542606],"type":"Point"}
}