{
  "type": "Feature",
  "properties": {
    "addr:full":"300 Boul Arthur-Sauve Saint-Eustache QC J7R 2J1",
    "addr:housenumber":"300",
    "addr:postcode":"j7r 2j1",
    "addr:street":"Boul Arthur-Sauve",
    "iso:country":"CA",
    "sg:address":"300 Boul Arthur-Sauve",
    "sg:city":"Saint-Eustache",
    "sg:classifiers":[
        {
            "category":"Shopping",
            "subcategory":"Shoes",
            "type":"Retail Goods"
        }
    ],
    "sg:phone":"+1 450 974 2074",
    "sg:postcode":"J7R 2J1",
    "sg:province":"QC",
    "wof:name":"Chaussures Yellow Ltee",
    "wof:placetype":"venue"
},
  "geometry": {"coordinates":[-73.899536,45.560867],"type":"Point"}
}