{
  "type": "Feature",
  "properties": {
    "addr:full":"Langley BC V3A 1N2",
    "addr:postcode":"v3a 1n2",
    "iso:country":"CA",
    "sg:city":"Langley",
    "sg:classifiers":[
        {
            "category":"Retail",
            "subcategory":"Auto Repair",
            "type":"Services"
        }
    ],
    "sg:phone":"+1 604 534 6644",
    "sg:postcode":"V3A 1N2",
    "sg:province":"BC",
    "sg:tags":[
        "repairing",
        "automobile"
    ],
    "wof:name":"A-1 Langley Import Repair Ltd",
    "wof:placetype":"venue"
},
  "geometry": {"coordinates":[-122.66877746599999,49.1107406616],"type":"Point"}
}