{
  "type": "Feature",
  "properties": {
    "addr:full":"10409 121 Ave NW Edmonton AB T5G 0T1",
    "addr:housenumber":"10409",
    "addr:postcode":"t5g 0t1",
    "addr:street":"121 Ave Nw",
    "iso:country":"CA",
    "sg:address":"10409 121 Ave NW",
    "sg:city":"Edmonton",
    "sg:classifiers":[
        {
            "category":"Health Services",
            "subcategory":"Medical Lab",
            "type":"Services"
        }
    ],
    "sg:phone":"+1 780 474 9031",
    "sg:postcode":"T5G 0T1",
    "sg:province":"AB",
    "sg:tags":[
        "laboratory"
    ],
    "wof:name":"Westwood Dental Laboratory Ltd",
    "wof:placetype":"venue"
},
  "geometry": {"coordinates":[-113.499771,53.575047],"type":"Point"}
}