{
  "type": "Feature",
  "properties": {
    "addr:full":"1221 Rue Crescent Montreal QC H3G 2B1",
    "addr:housenumber":"1221",
    "addr:postcode":"h3g 2b1",
    "addr:street":"Rue Crescent",
    "iso:country":"CA",
    "sg:address":"1221 Rue Crescent",
    "sg:city":"Montreal",
    "sg:classifiers":[
        {
            "category":"Shopping",
            "subcategory":"Books",
            "type":"Retail Goods"
        }
    ],
    "sg:phone":"+1 514 871 1402",
    "sg:postcode":"H3G 2B1",
    "sg:province":"QC",
    "sg:tags":[
        "comic"
    ],
    "wof:name":"Empire Comics Cards",
    "wof:placetype":"venue"
},
  "geometry": {"coordinates":[-73.5744934082,45.4967765808],"type":"Point"}
}