{
  "type": "Feature",
  "properties": {
    "addr:full":"1722 8th St E Saskatoon SK S7H 0T5",
    "addr:housenumber":"1722",
    "addr:postcode":"s7h 0t5",
    "addr:street":"8Th St E",
    "iso:country":"CA",
    "sg:address":"1722 8th St E",
    "sg:city":"Saskatoon",
    "sg:classifiers":[
        {
            "category":"Restaurant",
            "type":"Food & Drink"
        }
    ],
    "sg:phone":"+1 306 374 0505",
    "sg:postcode":"S7H 0T5",
    "sg:province":"SK",
    "sg:tags":[
        "parlor",
        "ice",
        "cream"
    ],
    "wof:name":"Dairy Queen",
    "wof:placetype":"venue"
},
  "geometry": {"coordinates":[-106.63047,52.114483],"type":"Point"}
}