{
  "type": "Feature",
  "properties": {
    "iso:country":"CA",
    "sg:address":"8781 Dale Rd # A",
    "sg:city":"Cobourg",
    "sg:classifiers":[
        {
            "category":"Wholesale",
            "subcategory":"Books, Periodicals, & Newspapers",
            "type":"Manufacturing & Wholesale Goods"
        }
    ],
    "sg:phone":"+1 905 372 6856",
    "sg:postcode":"K9A 4J9",
    "sg:province":"ON",
    "sg:tags":[
        "magazine"
    ],
    "wof:name":"Prologix",
    "wof:placetype":"venue"
},
  "geometry": {"coordinates":[-78.1677780151,43.9596061707],"type":"Point"}
}