{
  "type": "Feature",
  "properties": {
    "iso:country":"CA",
    "sg:address":"4053 Sheppard Ave E",
    "sg:city":"Scarborough",
    "sg:classifiers":[
        {
            "category":"Cinema",
            "subcategory":"Movie Rental",
            "type":"Entertainment"
        }
    ],
    "sg:phone":"+1 416 754 2500",
    "sg:postcode":"M1S 1S8",
    "sg:province":"ON",
    "sg:tags":[
        "leasing",
        "video",
        "disc",
        "tape"
    ],
    "wof:name":"Hot Time Adult Video",
    "wof:placetype":"venue"
},
  "geometry": {"coordinates":[-79.286277771,43.7835655212],"type":"Point"}
}