{
  "type": "Feature",
  "properties": {
    "addr:full":"Peterborough ON K9H 2W7",
    "addr:postcode":"k9h 2w7",
    "iso:country":"CA",
    "sg:city":"Peterborough",
    "sg:classifiers":[
        {
            "category":"Professional",
            "subcategory":"Computer Services",
            "type":"Services"
        }
    ],
    "sg:phone":"+1 705 745 4601",
    "sg:postcode":"K9H 2W7",
    "sg:province":"ON",
    "sg:tags":[
        "repair",
        "dealer",
        "equipment"
    ],
    "wof:name":"Benchmark Computers Inc",
    "wof:placetype":"venue"
},
  "geometry": {"coordinates":[-78.32763671879999,44.3095169067],"type":"Point"}
}