{
  "type": "Feature",
  "properties": {
    "addr:full":"37 Boul Renard O Gaspe QC G4X 5B2",
    "addr:housenumber":"37",
    "addr:postcode":"g4x 5b2",
    "addr:street":"Boul Renard O Gaspe",
    "iso:country":"CA",
    "sg:address":"37 Boul Renard O",
    "sg:city":"Gaspe",
    "sg:classifiers":[
        {
            "category":"Bars & Pubs",
            "type":"Food & Drink"
        }
    ],
    "sg:phone":"+1 418 269 5274",
    "sg:postcode":"G4X 5B2",
    "sg:province":"QC",
    "sg:tags":[
        "lounge",
        "cocktail"
    ],
    "wof:name":"Bar Rendez-Vous",
    "wof:placetype":"venue"
},
  "geometry": {"coordinates":[-64.398331,48.994858],"type":"Point"}
}