{
  "type": "Feature",
  "properties": {
    "addr:full":"603 22 Ave Nisku AB T9E 7X7",
    "addr:postcode":"603;t9e 7x7",
    "addr:street":"22 Ave",
    "iso:country":"CA",
    "sg:address":"603 22 Ave",
    "sg:city":"Nisku",
    "sg:classifiers":[
        {
            "category":"Professional",
            "type":"Services"
        }
    ],
    "sg:phone":"+1 780 955 2628",
    "sg:postcode":"T9E 7X7",
    "sg:province":"AB",
    "sg:tags":[
        "field",
        "oil",
        "establishment",
        "transportation"
    ],
    "wof:name":"Kam's Sand Coating Ltd",
    "wof:placetype":"venue"
},
  "geometry": {"coordinates":[-113.526459,53.342953],"type":"Point"}
}