{
  "type": "Feature",
  "properties": {
    "addr:full":"9505 118 Ave NW Edmonton AB T5G 0N8",
    "addr:housenumber":"9505",
    "addr:postcode":"t5g 0n8",
    "addr:street":"118 Ave Nw",
    "iso:country":"CA",
    "sg:address":"9505 118 Ave NW",
    "sg:city":"Edmonton",
    "sg:classifiers":[
        {
            "category":"Banks & Credit Unions",
            "subcategory":"Bank",
            "type":"Services"
        }
    ],
    "sg:phone":"+1 780 472 9329",
    "sg:postcode":"T5G 0N8",
    "sg:province":"AB",
    "sg:tags":[
        "cashing",
        "loan",
        "check"
    ],
    "wof:name":"Cash Store",
    "wof:placetype":"venue"
},
  "geometry": {"coordinates":[-113.487586975,53.5701828003],"type":"Point"}
}