{
  "type": "Feature",
  "properties": {
    "addr:full":"1053 Ch Du Fleuve Les Cedres QC J7T 1B7",
    "addr:postcode":"1053;j7t 1b7",
    "addr:street":"Ch Du Fleuve",
    "iso:country":"CA",
    "sg:address":"1053 Ch Du Fleuve",
    "sg:city":"Les Cedres",
    "sg:classifiers":[
        {
            "category":"Shopping",
            "subcategory":"Florist",
            "type":"Retail Goods"
        }
    ],
    "sg:phone":"+1 450 452 2081",
    "sg:postcode":"J7T 1B7",
    "sg:province":"QC",
    "wof:name":"Fleurs DE LA Rive Les Cedres",
    "wof:placetype":"venue"
},
  "geometry": {"coordinates":[-74.05416099999999,45.304569],"type":"Point"}
}