{
  "type": "Feature",
  "properties": {
    "addr:full":"805 Government St Victoria BC V8W 1W8",
    "addr:housenumber":"805",
    "addr:postcode":"v8w 1w8",
    "addr:street":"Government St",
    "iso:country":"CA",
    "sg:address":"805 Government St",
    "sg:city":"Victoria",
    "sg:classifiers":[
        {
            "category":"Restaurant",
            "type":"Food & Drink"
        }
    ],
    "sg:phone":"+1 250 382 8424",
    "sg:postcode":"V8W 1W8",
    "sg:province":"BC",
    "wof:name":"Sam's Deli",
    "wof:placetype":"venue"
},
  "geometry": {"coordinates":[-123.36816406200001,48.4228591919],"type":"Point"}
}