{
  "type": "Feature",
  "properties": {
    "addr:full":"803 Wood St Whitehorse YT Y1A 2G6",
    "addr:housenumber":"803",
    "addr:postcode":"y1a 2g6",
    "addr:street":"Wood St",
    "iso:country":"CA",
    "sg:address":"803 Wood St",
    "sg:city":"Whitehorse",
    "sg:classifiers":[
        {
            "category":"Professional",
            "subcategory":"Engineering",
            "type":"Services"
        }
    ],
    "sg:phone":"+1 867 393 3458",
    "sg:postcode":"Y1A 2G6",
    "sg:province":"YT",
    "sg:tags":[
        "engineer"
    ],
    "wof:name":"Vista Tek Ltd",
    "wof:placetype":"venue"
},
  "geometry": {"coordinates":[-135.06516999999999,60.719055],"type":"Point"}
}