{
  "type": "Feature",
  "properties": {
    "addr:full":"44 Court House Sq Goderich ON N7A 1M5",
    "addr:housenumber":"44",
    "addr:postcode":"n7a 1m5",
    "addr:street":"Court House Sq",
    "iso:country":"CA",
    "sg:address":"44 Court House Sq",
    "sg:city":"Goderich",
    "sg:classifiers":[
        {
            "category":"Banks & Credit Unions",
            "subcategory":"Bank",
            "type":"Services"
        }
    ],
    "sg:phone":"+1 519 524 4010",
    "sg:postcode":"N7A 1M5",
    "sg:province":"ON",
    "wof:name":"Scotiabank",
    "wof:placetype":"venue"
},
  "geometry": {"coordinates":[-81.71228000000001,43.742989],"type":"Point"}
}