{
  "type": "Feature",
  "properties": {
    "addr:full":"41 Keltic Dr Sydney NS B1S 1P4",
    "addr:housenumber":"41",
    "addr:postcode":"b1s 1p4",
    "addr:street":"Keltic Dr",
    "iso:country":"CA",
    "sg:address":"41 Keltic Dr",
    "sg:city":"Sydney",
    "sg:classifiers":[
        {
            "category":"Shopping",
            "subcategory":"Crafts & Fabrics",
            "type":"Retail Goods"
        }
    ],
    "sg:phone":"+1 902 539 5949",
    "sg:postcode":"B1S 1P4",
    "sg:province":"NS",
    "sg:tags":[
        "supply"
    ],
    "wof:name":"Moraff's Yarns & Crafts",
    "wof:placetype":"venue"
},
  "geometry": {"coordinates":[-60.2237014771,46.1100234985],"type":"Point"}
}