{
  "type": "Feature",
  "properties": {
    "iso:country":"CA",
    "sg:address":"603 Gerrard St E",
    "sg:city":"Toronto",
    "sg:classifiers":[
        {
            "category":"Food & Beverages",
            "subcategory":"Groceries & Convenience Stores",
            "type":"Retail Goods"
        }
    ],
    "sg:phone":"+1 416 778 6618",
    "sg:postcode":"M4M 1Y2",
    "sg:province":"ON",
    "sg:tags":[
        "grocer"
    ],
    "wof:name":"Ho Lee Supermarket",
    "wof:placetype":"venue"
},
  "geometry": {"coordinates":[-79.3515167236,43.6655387878],"type":"Point"}
}