{
  "type": "Feature",
  "properties": {
    "addr:full":"174 Asher Rd Kelowna BC V1X 3H6",
    "addr:housenumber":"174",
    "addr:postcode":"v1x 3h6",
    "addr:street":"Asher Rd",
    "iso:country":"CA",
    "sg:address":"174 Asher Rd",
    "sg:city":"Kelowna",
    "sg:classifiers":[
        {
            "category":"Shopping",
            "subcategory":"Used Merchandise",
            "type":"Retail Goods"
        }
    ],
    "sg:phone":"+1 250 491 3111",
    "sg:postcode":"V1X 3H6",
    "sg:province":"BC",
    "sg:tags":[
        "pawnbroker"
    ],
    "wof:name":"Asher Road Pawnbrokers",
    "wof:placetype":"venue"
},
  "geometry": {"coordinates":[-119.39141100000001,49.889973],"type":"Point"}
}