{
  "type": "Feature",
  "properties": {
    "addr:full":"3236 River St Alvinston ON N0N 1A0",
    "addr:housenumber":"3236",
    "addr:postcode":"n0n 1a0",
    "addr:street":"River St",
    "iso:country":"CA",
    "sg:address":"3236 River St",
    "sg:city":"Alvinston",
    "sg:classifiers":[
        {
            "category":"Government",
            "subcategory":"Office",
            "type":"Public Place"
        }
    ],
    "sg:phone":"+1 519 898 2173",
    "sg:postcode":"N0N 1A0",
    "sg:province":"ON",
    "sg:tags":[
        "municipality"
    ],
    "wof:name":"Alvinston Clerk's Office",
    "wof:placetype":"venue"
},
  "geometry": {"coordinates":[-81.86200714109999,42.8200073242],"type":"Point"}
}