{
  "type": "Feature",
  "properties": {
    "addr:full":"1 Cromer Ave Grand Falls-Windsor NL A2A 1W9",
    "addr:housenumber":"1",
    "addr:postcode":"a2a 1w9",
    "addr:street":"Cromer Ave",
    "iso:country":"CA",
    "sg:address":"1 Cromer Ave",
    "sg:city":"Grand Falls-Windsor",
    "sg:classifiers":[
        {
            "category":"Education",
            "subcategory":"Library",
            "type":"Public Place"
        }
    ],
    "sg:phone":"+1 709 489 2303",
    "sg:postcode":"A2A 1W9",
    "sg:province":"NL",
    "wof:name":"Grand Fall-Windsor Public Lbry",
    "wof:placetype":"venue"
},
  "geometry": {"coordinates":[-55.663158,48.938431],"type":"Point"}
}