{
  "type": "Feature",
  "properties": {
    "addr:full":"1020 Ch Des Anglais Mascouche QC J7L 3R7",
    "addr:postcode":"1020;j7l 3r7",
    "addr:street":"Ch Des Anglais",
    "iso:country":"CA",
    "sg:address":"1020 Ch Des Anglais",
    "sg:city":"Mascouche",
    "sg:classifiers":[
        {
            "category":"Sports & Exercise",
            "subcategory":"Golf",
            "type":"Entertainment"
        }
    ],
    "sg:phone":"+1 450 477 1411",
    "sg:postcode":"J7L 3R7",
    "sg:province":"QC",
    "sg:tags":[
        "course"
    ],
    "wof:name":"Mascouche Golf & Country Club",
    "wof:placetype":"venue"
},
  "geometry": {"coordinates":[-73.642662,45.74575],"type":"Point"}
}