{
  "type": "Feature",
  "properties": {
    "iso:country":"CA",
    "sg:address":"824 Cow Bay Rd",
    "sg:city":"Eastern Passage",
    "sg:classifiers":[
        {
            "category":"Wholesale",
            "subcategory":"Machinery & Supplies",
            "type":"Manufacturing & Wholesale Goods"
        }
    ],
    "sg:phone":"+1 902 465 4333",
    "sg:postcode":"B3G 1J8",
    "sg:province":"NS",
    "sg:tags":[
        "hydraulic",
        "lubricating",
        "system",
        "devices",
        "equipment"
    ],
    "wof:name":"Precision Hydraulics Ltd",
    "wof:placetype":"venue"
},
  "geometry": {"coordinates":[-63.454037,44.624355],"type":"Point"}
}