{
  "type": "Feature",
  "properties": {
    "addr:full":"Stayner ON L0M 1S0",
    "addr:postcode":"l0m 1s0",
    "iso:country":"CA",
    "sg:city":"Stayner",
    "sg:classifiers":[
        {
            "category":"Autos & Motor Vehicles",
            "subcategory":"Motorcycle Sales",
            "type":"Retail Goods"
        }
    ],
    "sg:phone":"+1 705 429 3822",
    "sg:postcode":"L0M 1S0",
    "sg:province":"ON",
    "sg:tags":[
        "scooter"
    ],
    "wof:name":"J & R Cycle",
    "wof:placetype":"venue"
},
  "geometry": {"coordinates":[-80.08947000000001,44.419765],"type":"Point"}
}