{
  "type": "Feature",
  "properties": {
    "addr:full":"344 Davenport Rd Toronto ON M5R 1K6",
    "addr:housenumber":"344",
    "addr:postcode":"m5r 1k6",
    "addr:street":"Davenport Rd",
    "iso:country":"CA",
    "sg:address":"344 Davenport Rd",
    "sg:city":"Toronto",
    "sg:classifiers":[
        {
            "category":"Shopping",
            "subcategory":"Clothing, Apparel, & Fashions",
            "type":"Retail Goods"
        }
    ],
    "sg:phone":"+1 416 515 9730",
    "sg:postcode":"M5R 1K6",
    "sg:province":"ON",
    "sg:tags":[
        "tailor"
    ],
    "wof:name":"Alteration Room",
    "wof:placetype":"venue"
},
  "geometry": {"coordinates":[-79.401611,43.675365],"type":"Point"}
}