{
  "type": "Feature",
  "properties": {
    "addr:full":"377 Burnhamthorpe Rd E Mississauga ON L5A 3Y1",
    "addr:housenumber":"377",
    "addr:postcode":"l5a 3y1",
    "addr:street":"Burnhamthorpe Rd E",
    "iso:country":"CA",
    "sg:address":"377 Burnhamthorpe Rd E",
    "sg:city":"Mississauga",
    "sg:classifiers":[
        {
            "category":"Shopping",
            "subcategory":"Pharmacy",
            "type":"Retail Goods"
        }
    ],
    "sg:phone":"+1 905 277 0379",
    "sg:postcode":"L5A 3Y1",
    "sg:province":"ON",
    "wof:name":"Pharma Plus Drugmart",
    "wof:placetype":"venue"
},
  "geometry": {"coordinates":[-79.6257476807,43.6017875671],"type":"Point"}
}