{
  "type": "Feature",
  "properties": {
    "iso:country":"CA",
    "sg:address":"1570 Av Du Pont S",
    "sg:city":"Alma",
    "sg:classifiers":[
        {
            "category":"Autos & Motor Vehicles",
            "subcategory":"Automobile Sales",
            "type":"Retail Goods"
        }
    ],
    "sg:phone":"+1 418 662 6695",
    "sg:postcode":"G8B 6N1",
    "sg:province":"QC",
    "sg:tags":[
        "car",
        "dealer"
    ],
    "wof:name":"Alma Ford",
    "wof:placetype":"venue"
},
  "geometry": {"coordinates":[-71.652153,48.52655],"type":"Point"}
}