{
  "type": "Feature",
  "properties": {
    "addr:full":"Etobicoke ON M9C 5J5",
    "addr:postcode":"m9c 5j5",
    "iso:country":"CA",
    "sg:city":"Etobicoke",
    "sg:classifiers":[
        {
            "category":"Health Services",
            "subcategory":"Clinic",
            "type":"Services"
        }
    ],
    "sg:phone":"+1 416 626 2222",
    "sg:postcode":"M9C 5J5",
    "sg:province":"ON",
    "sg:tags":[
        "home"
    ],
    "wof:name":"Etobicoke Community Care Ctr",
    "wof:placetype":"venue"
},
  "geometry": {"coordinates":[-79.567131,43.644756],"type":"Point"}
}