{
  "type": "Feature",
  "properties": {
    "addr:full":"967 Rue Sainte-Helene Longueuil QC J4K 3S1",
    "addr:housenumber":"967",
    "addr:postcode":"j4k 3s1",
    "addr:street":"Rue Sainte-Helene",
    "iso:country":"CA",
    "sg:address":"967 Rue Sainte-Helene",
    "sg:city":"Longueuil",
    "sg:classifiers":[
        {
            "category":"Health Services",
            "subcategory":"Medical Lab",
            "type":"Services"
        }
    ],
    "sg:phone":"+1 450 679 4643",
    "sg:postcode":"J4K 3S1",
    "sg:province":"QC",
    "wof:name":"Brochu, Dominique",
    "wof:placetype":"venue"
},
  "geometry": {"coordinates":[-73.504829,45.519985],"type":"Point"}
}