{
  "type": "Feature",
  "properties": {
    "addr:full":"640 River St Thunder Bay ON P7A 3S4",
    "addr:housenumber":"640",
    "addr:postcode":"p7a 3s4",
    "addr:street":"River St",
    "iso:country":"CA",
    "sg:address":"640 River St",
    "sg:city":"Thunder Bay",
    "sg:classifiers":[
        {
            "category":"Shopping",
            "subcategory":"Clothing, Apparel, & Fashions",
            "type":"Retail Goods"
        }
    ],
    "sg:phone":"+1 807 345 0831",
    "sg:postcode":"P7A 3S4",
    "sg:province":"ON",
    "wof:name":"Saan Stores Ltd",
    "wof:placetype":"venue"
},
  "geometry": {"coordinates":[-89.233513,48.448097],"type":"Point"}
}