{
  "type": "Feature",
  "properties": {
    "addr:full":"128 Dunlop St E Barrie ON L4M 1A4",
    "addr:housenumber":"128",
    "addr:postcode":"l4m 1a4",
    "addr:street":"Dunlop St E",
    "iso:country":"CA",
    "sg:address":"128 Dunlop St E",
    "sg:city":"Barrie",
    "sg:classifiers":[
        {
            "category":"Restaurant",
            "type":"Food & Drink"
        }
    ],
    "sg:phone":"+1 705 737 1821",
    "sg:postcode":"L4M 1A4",
    "sg:province":"ON",
    "wof:name":"Tara Indian Cuisine",
    "wof:placetype":"venue"
},
  "geometry": {"coordinates":[-79.68566894529999,44.3894271851],"type":"Point"}
}