{
  "type": "Feature",
  "properties": {
    "addr:full":"739 Riverside Rd Abbotsford BC V2S 7P6",
    "addr:housenumber":"739",
    "addr:postcode":"v2s 7p6",
    "addr:street":"Riverside Rd",
    "iso:country":"CA",
    "sg:address":"739 Riverside Rd",
    "sg:city":"Abbotsford",
    "sg:classifiers":[
        {
            "category":"Manufacturing",
            "subcategory":"Lumber",
            "type":"Manufacturing & Wholesale Goods"
        }
    ],
    "sg:phone":"+1 604 852 2218",
    "sg:postcode":"V2S 7P6",
    "sg:province":"BC",
    "wof:name":"Saran Cedar Ltd",
    "wof:placetype":"venue"
},
  "geometry": {"coordinates":[-122.271957398,49.0158500671],"type":"Point"}
}