{
  "type": "Feature",
  "properties": {
    "addr:full":"3929 Main St Niagara Falls ON L2G 6B7",
    "addr:housenumber":"3929",
    "addr:postcode":"l2g 6b7",
    "addr:street":"Main St",
    "iso:country":"CA",
    "sg:address":"3929 Main St",
    "sg:city":"Niagara Falls",
    "sg:classifiers":[
        {
            "category":"Retail",
            "subcategory":"Laundry & Dry Cleaning",
            "type":"Services"
        }
    ],
    "sg:phone":"+1 905 295 3294",
    "sg:postcode":"L2G 6B7",
    "sg:province":"ON",
    "sg:tags":[
        "cleaners",
        "rug",
        "carpet"
    ],
    "wof:name":"Double Action Carpet & Uphlstr",
    "wof:placetype":"venue"
},
  "geometry": {"coordinates":[-79.0545959473,43.0561332703],"type":"Point"}
}