{
  "type": "Feature",
  "properties": {
    "iso:country":"CA",
    "sg:address":"180 Rue Ouellette",
    "sg:city":"Marieville",
    "sg:classifiers":[
        {
            "category":"Manufacturing",
            "subcategory":"Printing",
            "type":"Manufacturing & Wholesale Goods"
        }
    ],
    "sg:phone":"+1 450 460 2105",
    "sg:postcode":"J3M 1A5",
    "sg:province":"QC",
    "sg:tags":[
        "bookbinder"
    ],
    "wof:name":"Reliures Rm Leduc & Cie",
    "wof:placetype":"venue"
},
  "geometry": {"coordinates":[-73.1684341431,45.4371185303],"type":"Point"}
}