{
  "type": "Feature",
  "properties": {
    "addr:full":"1190 Keith Ross Crt Oshawa ON L1H 7K4",
    "addr:housenumber":"1190",
    "addr:postcode":"l1h 7k4",
    "addr:street":"Keith Ross Crt",
    "iso:country":"CA",
    "sg:address":"1190 Keith Ross Crt",
    "sg:city":"Oshawa",
    "sg:classifiers":[
        {
            "category":"Education",
            "subcategory":"Special Training",
            "type":"Public Place"
        }
    ],
    "sg:phone":"+1 905 720 2831",
    "sg:postcode":"L1H 7K4",
    "sg:province":"ON",
    "sg:tags":[
        "aircraft",
        "school"
    ],
    "wof:name":"Durham Flight Ctr",
    "wof:placetype":"venue"
},
  "geometry": {"coordinates":[-78.859505,43.88868],"type":"Point"}
}