{
  "type": "Feature",
  "properties": {
    "addr:full":"201 Westheights Dr Kitchener ON N2N 1K2",
    "addr:housenumber":"201",
    "addr:postcode":"n2n 1k2",
    "addr:street":"Westheights Dr",
    "iso:country":"CA",
    "sg:address":"201 Westheights Dr",
    "sg:city":"Kitchener",
    "sg:classifiers":[
        {
            "category":"Home & Garden",
            "subcategory":"Garden Supply",
            "type":"Retail Goods"
        }
    ],
    "sg:phone":"+1 519 744 9921",
    "sg:postcode":"N2N 1K2",
    "sg:province":"ON",
    "sg:tags":[
        "sprinkler"
    ],
    "wof:name":"Reliable Rain Irrigation",
    "wof:placetype":"venue"
},
  "geometry": {"coordinates":[-80.5299072266,43.4235076904],"type":"Point"}
}