{
  "type": "Feature",
  "properties": {
    "iso:country":"CA",
    "sg:city":"Trois-Rivieres",
    "sg:classifiers":[
        {
            "category":"Manufacturing",
            "subcategory":"Apparel",
            "type":"Manufacturing & Wholesale Goods"
        }
    ],
    "sg:phone":"+1 819 378 5849",
    "sg:postcode":"G8Z 1J4",
    "sg:province":"QC",
    "sg:tags":[
        "clothing"
    ],
    "wof:name":"Confection R Hebert Ltee",
    "wof:placetype":"venue"
},
  "geometry": {"coordinates":[-72.54503631590001,46.3401794434],"type":"Point"}
}