{
  "type": "Feature",
  "properties": {
    "iso:country":"CA",
    "sg:city":"Dawson",
    "sg:classifiers":[
        {
            "category":"Shopping",
            "subcategory":"Department Store",
            "type":"Retail Goods"
        }
    ],
    "sg:phone":"+1 867 993 6683",
    "sg:postcode":"Y0B 1G0",
    "sg:province":"YT",
    "wof:name":"Ray of Sunshine Variety Store",
    "wof:placetype":"venue"
},
  "geometry": {"coordinates":[-139.43685913100001,64.0613327026],"type":"Point"}
}