{
  "type": "Feature",
  "properties": {
    "addr:full":"352 Main St Stonewall MB R0C 2Z0",
    "addr:housenumber":"352",
    "addr:postcode":"r0c 2z0",
    "addr:street":"Main St",
    "iso:country":"CA",
    "sg:address":"352 Main St",
    "sg:city":"Stonewall",
    "sg:classifiers":[
        {
            "category":"Farming",
            "subcategory":"Farm & Veterinary Services",
            "type":"Manufacturing & Wholesale Goods"
        }
    ],
    "sg:phone":"+1 204 467 4704",
    "sg:postcode":"R0C 2Z0",
    "sg:province":"MB",
    "sg:tags":[
        "control",
        "weed"
    ],
    "wof:name":"Rockwood Rosser Weed Control",
    "wof:placetype":"venue"
},
  "geometry": {"coordinates":[-97.3266296387,50.1346893311],"type":"Point"}
}