{
  "type": "Feature",
  "properties": {
    "iso:country":"CA",
    "sg:address":"612 S 12th St",
    "sg:city":"Golden",
    "sg:classifiers":[
        {
            "category":"Manufacturing",
            "subcategory":"Lumber",
            "type":"Manufacturing & Wholesale Goods"
        }
    ],
    "sg:phone":"+1 250 344 2264",
    "sg:postcode":"V0A 1H0",
    "sg:province":"BC",
    "sg:tags":[
        "forester"
    ],
    "wof:name":"Perrin Emerson Enterprises",
    "wof:placetype":"venue"
},
  "geometry": {"coordinates":[-116.97048950200001,51.2931671143],"type":"Point"}
}