{
  "type": "Feature",
  "properties": {
    "addr:full":"462 Rue St-Georges Manseau QC G0X 1V0",
    "addr:housenumber":"462",
    "addr:postcode":"g0x 1v0",
    "addr:street":"Rue St-Georges",
    "iso:country":"CA",
    "sg:address":"462 Rue St-Georges",
    "sg:city":"Manseau",
    "sg:classifiers":[
        {
            "category":"Social Services",
            "type":"Services"
        }
    ],
    "sg:phone":"+1 819 356 2010",
    "sg:postcode":"G0X 1V0",
    "sg:province":"QC",
    "sg:tags":[
        "organization",
        "welfare"
    ],
    "wof:name":"Carrefour Familial DE Manseau",
    "wof:placetype":"venue"
},
  "geometry": {"coordinates":[-72.00346374510001,46.3702659607],"type":"Point"}
}