{
  "type": "Feature",
  "properties": {
    "addr:full":"2205 Arch St Ottawa ON K1G 2H5",
    "addr:housenumber":"2205",
    "addr:postcode":"k1g 2h5",
    "addr:street":"Arch St",
    "iso:country":"CA",
    "sg:address":"2205 Arch St",
    "sg:city":"Ottawa",
    "sg:classifiers":[
        {
            "category":"Personal",
            "subcategory":"Beauty Salon",
            "type":"Services"
        }
    ],
    "sg:phone":"+1 613 731 5529",
    "sg:postcode":"K1G 2H5",
    "sg:province":"ON",
    "wof:name":"Canterbury Beauty Salon",
    "wof:placetype":"venue"
},
  "geometry": {"coordinates":[-75.630669,45.390522],"type":"Point"}
}