{
  "type": "Feature",
  "properties": {
    "addr:full":"1011 6 Ave SW Calgary AB T2P 0W1",
    "addr:housenumber":"1011",
    "addr:postcode":"t2p 0w1",
    "addr:street":"6 Ave Sw",
    "iso:country":"CA",
    "sg:address":"1011 6 Ave SW",
    "sg:city":"Calgary",
    "sg:classifiers":[
        {
            "category":"Government",
            "subcategory":"Office",
            "type":"Public Place"
        }
    ],
    "sg:phone":"+1 403 297 8080",
    "sg:postcode":"T2P 0W1",
    "sg:province":"AB",
    "wof:name":"Alberta Calgary Rocky View",
    "wof:placetype":"venue"
},
  "geometry": {"coordinates":[-114.084259,51.047916],"type":"Point"}
}