{
  "type": "Feature",
  "properties": {
    "addr:full":"2405 Scanlan St London ON N5W 6G9",
    "addr:housenumber":"2405",
    "addr:postcode":"n5w 6g9",
    "addr:street":"Scanlan St",
    "iso:country":"CA",
    "sg:address":"2405 Scanlan St",
    "sg:city":"London",
    "sg:classifiers":[
        {
            "category":"Retail",
            "subcategory":"Auto Repair",
            "type":"Services"
        }
    ],
    "sg:phone":"+1 519 455 3440",
    "sg:postcode":"N5W 6G9",
    "sg:province":"ON",
    "sg:tags":[
        "trailer"
    ],
    "wof:name":"Traction",
    "wof:placetype":"venue"
},
  "geometry": {"coordinates":[-81.137726,42.982643],"type":"Point"}
}