{
  "type": "Feature",
  "properties": {
    "addr:full":"Scarborough ON M1L 3G7",
    "addr:postcode":"m1l 3g7",
    "iso:country":"CA",
    "sg:city":"Scarborough",
    "sg:classifiers":[
        {
            "category":"Professional",
            "subcategory":"Management & Consulting",
            "type":"Services"
        }
    ],
    "sg:phone":"+1 416 757 7189",
    "sg:postcode":"M1L 3G7",
    "sg:province":"ON",
    "sg:tags":[
        "consultant",
        "business"
    ],
    "wof:name":"Ever Forestland Intl Mgmt Ltd",
    "wof:placetype":"venue"
},
  "geometry": {"coordinates":[-79.2889328003,43.7057151794],"type":"Point"}
}