{
  "type": "Feature",
  "properties": {
    "addr:full":"Scarborough ON M1P 3B2",
    "addr:postcode":"m1p 3b2",
    "iso:country":"CA",
    "sg:city":"Scarborough",
    "sg:classifiers":[
        {
            "category":"Manufacturing",
            "subcategory":"Motor Vehicles & Parts",
            "type":"Manufacturing & Wholesale Goods"
        }
    ],
    "sg:phone":"+1 416 752 6468",
    "sg:postcode":"M1P 3B2",
    "sg:province":"ON",
    "sg:tags":[
        "automobile",
        "supply"
    ],
    "wof:name":"Salmon Industries Limited",
    "wof:placetype":"venue"
},
  "geometry": {"coordinates":[-79.269241333,43.7560501099],"type":"Point"}
}