{
  "type": "Feature",
  "properties": {
    "addr:full":"10275 135 St Surrey BC V3T 4C3",
    "addr:housenumber":"10275",
    "addr:postcode":"v3t 4c3",
    "addr:street":"135 St",
    "iso:country":"CA",
    "sg:address":"10275 135 St",
    "sg:city":"Surrey",
    "sg:classifiers":[
        {
            "category":"Health Services",
            "subcategory":"Health Practitioner",
            "type":"Services"
        }
    ],
    "sg:phone":"+1 604 583 6088",
    "sg:postcode":"V3T 4C3",
    "sg:province":"BC",
    "sg:tags":[
        "physiotherapist",
        "rehabilitation"
    ],
    "wof:name":"Surrey Orthopaedic & Sports",
    "wof:placetype":"venue"
},
  "geometry": {"coordinates":[-122.84792299999999,49.18948],"type":"Point"}
}