{
  "type": "Feature",
  "properties": {
    "addr:full":"Portage LA Prairie MB R1N 3B9",
    "addr:postcode":"r1n 3b9",
    "iso:country":"CA",
    "sg:city":"Portage LA Prairie",
    "sg:classifiers":[
        {
            "category":"Freight",
            "type":"Transportation"
        }
    ],
    "sg:phone":"+1 204 239 8676",
    "sg:postcode":"R1N 3B9",
    "sg:province":"MB",
    "sg:tags":[
        "trucking"
    ],
    "wof:name":"Lark Transport",
    "wof:placetype":"venue"
},
  "geometry": {"coordinates":[-98.32972717289999,49.9737281799],"type":"Point"}
}