{
  "type": "Feature",
  "properties": {
    "addr:full":"Freshwater Pb NL A0B 1W0",
    "addr:postcode":"a0b 1w0",
    "iso:country":"CA",
    "sg:city":"Freshwater Pb",
    "sg:classifiers":[
        {
            "category":"Local Transit",
            "type":"Transportation"
        }
    ],
    "sg:phone":"+1 709 227 3808",
    "sg:postcode":"A0B 1W0",
    "sg:province":"NL",
    "sg:tags":[
        "ambulance"
    ],
    "wof:name":"Power's Ambulance Svc",
    "wof:placetype":"venue"
},
  "geometry": {"coordinates":[-53.9959220886,47.2723007202],"type":"Point"}
}