{
  "type": "Feature",
  "properties": {
    "addr:full":"Montebello QC J0V 1L0",
    "addr:postcode":"j0v 1l0",
    "iso:country":"CA",
    "sg:city":"Montebello",
    "sg:classifiers":[
        {
            "category":"Health Services",
            "subcategory":"Health Practitioner",
            "type":"Services"
        }
    ],
    "sg:phone":"+1 819 423 5765",
    "sg:postcode":"J0V 1L0",
    "sg:province":"QC",
    "sg:tags":[
        "psychologist"
    ],
    "wof:name":"Tremblay-Conlin, Madeleine",
    "wof:placetype":"venue"
},
  "geometry": {"coordinates":[-74.93905599999999,45.6502],"type":"Point"}
}