{
  "type": "Feature",
  "properties": {
    "addr:full":"PO Box 121 STN Main Okotoks AB T1S 1A4",
    "addr:housenumber":"po",
    "addr:postcode":"t1s 1a4",
    "addr:street":"Box 121 Stn Main Okotoks Ab",
    "iso:country":"CA",
    "sg:address":"PO Box 121 STN Main",
    "sg:city":"Okotoks",
    "sg:classifiers":[
        {
            "category":"Building & Trades",
            "subcategory":"Plumbing",
            "type":"Services"
        }
    ],
    "sg:phone":"+1 403 938 4628",
    "sg:postcode":"T1S 1A4",
    "sg:province":"AB",
    "sg:tags":[
        "contractor"
    ],
    "wof:name":"Alpine Plumbing Ltd",
    "wof:placetype":"venue"
},
  "geometry": {"coordinates":[-113.974937,50.725891],"type":"Point"}
}