{
  "type": "Feature",
  "properties": {
    "addr:full":"North York ON M6A 2H8",
    "addr:postcode":"m6a 2h8",
    "iso:country":"CA",
    "sg:city":"North York",
    "sg:classifiers":[
        {
            "category":"Professional",
            "subcategory":"Computer Services",
            "type":"Services"
        }
    ],
    "sg:phone":"+1 416 932 8132",
    "sg:postcode":"M6A 2H8",
    "sg:province":"ON",
    "sg:tags":[
        "internet"
    ],
    "wof:name":"Theoffice.com",
    "wof:placetype":"venue"
},
  "geometry": {"coordinates":[-79.43222,43.724716],"type":"Point"}
}