{
  "type": "Feature",
  "properties": {
    "addr:full":"Blainville QC J7C 2K9",
    "addr:postcode":"j7c 2k9",
    "iso:country":"CA",
    "sg:city":"Blainville",
    "sg:classifiers":[
        {
            "category":"Social Services",
            "subcategory":"Child Care",
            "type":"Services"
        }
    ],
    "sg:phone":"+1 450 433 7392",
    "sg:postcode":"J7C 2K9",
    "sg:province":"QC",
    "sg:tags":[
        "kindergarten",
        "academic",
        "school"
    ],
    "wof:name":"Prematernelle LA Petite Ecole",
    "wof:placetype":"venue"
},
  "geometry": {"coordinates":[-73.8744506836,45.670085907],"type":"Point"}
}