{
  "type": "Feature",
  "properties": {
    "addr:full":"491 Boul Edgar-Hebert Melocheville QC J0S 1J0",
    "addr:housenumber":"491",
    "addr:postcode":"j0s 1j0",
    "addr:street":"Boul Edgar-Hebert",
    "iso:country":"CA",
    "sg:address":"491 Boul Edgar-Hebert",
    "sg:city":"Melocheville",
    "sg:classifiers":[
        {
            "category":"Food & Beverages",
            "subcategory":"Groceries & Convenience Stores",
            "type":"Retail Goods"
        }
    ],
    "sg:phone":"+1 450 225 7877",
    "sg:postcode":"J0S 1J0",
    "sg:province":"QC",
    "wof:name":"Depanneur Melocheville",
    "wof:placetype":"venue"
},
  "geometry": {"coordinates":[-73.9663696289,45.3138237],"type":"Point"}
}