{
  "type": "Feature",
  "properties": {
    "iso:country":"CA",
    "sg:city":"Mont-Louis",
    "sg:classifiers":[
        {
            "category":"Communications",
            "subcategory":"Television Station",
            "type":"Services"
        }
    ],
    "sg:phone":"+1 418 797 2414",
    "sg:postcode":"G0E 1T0",
    "sg:province":"QC",
    "sg:tags":[
        "broadcasting",
        "co",
        "association"
    ],
    "wof:name":"Tele-Soleil Inc",
    "wof:placetype":"venue"
},
  "geometry": {"coordinates":[-65.7311096191,49.2291908264],"type":"Point"}
}