{
  "type": "Feature",
  "properties": {
    "addr:full":"44 Industrial Rd Victoria Harbour ON L0K 2A0",
    "addr:housenumber":"44",
    "addr:postcode":"l0k 2a0",
    "addr:street":"Industrial Rd",
    "iso:country":"CA",
    "sg:address":"44 Industrial Rd",
    "sg:city":"Victoria Harbour",
    "sg:classifiers":[
        {
            "category":"Manufacturing",
            "subcategory":"Tools & Machinery",
            "type":"Manufacturing & Wholesale Goods"
        }
    ],
    "sg:phone":"+1 705 534 0555",
    "sg:postcode":"L0K 2A0",
    "sg:province":"ON",
    "sg:tags":[
        "equipment",
        "electric"
    ],
    "wof:name":"Canadian Shunt Industries Ltd",
    "wof:placetype":"venue"
},
  "geometry": {"coordinates":[-79.763992,44.753704],"type":"Point"}
}