{
  "type": "Feature",
  "properties": {
    "addr:full":"1404 117 Rte Mont-Tremblant QC J8E 2X8",
    "addr:housenumber":"1404",
    "addr:postcode":"j8e 2x8",
    "addr:street":"117 Rte",
    "iso:country":"CA",
    "sg:address":"1404 117 Rte",
    "sg:city":"Mont-Tremblant",
    "sg:classifiers":[
        {
            "category":"Food & Beverages",
            "subcategory":"Groceries & Convenience Stores",
            "type":"Retail Goods"
        }
    ],
    "sg:phone":"+1 819 425 2560",
    "sg:postcode":"J8E 2X8",
    "sg:province":"QC",
    "sg:tags":[
        "video",
        "disc",
        "tape"
    ],
    "wof:name":"Depanneur Jean Telmosse",
    "wof:placetype":"venue"
},
  "geometry": {"coordinates":[-74.60168457029999,46.1183395386],"type":"Point"}
}