{
  "type": "Feature",
  "properties": {
    "addr:full":"8903 100 Ave Fort St John BC V1J 1X3",
    "addr:housenumber":"8903",
    "addr:postcode":"v1j 1x3",
    "addr:street":"100 Ave",
    "iso:country":"CA",
    "sg:address":"8903 100 Ave",
    "sg:city":"Fort St John",
    "sg:classifiers":[
        {
            "category":"Manufacturing",
            "subcategory":"Printing",
            "type":"Manufacturing & Wholesale Goods"
        }
    ],
    "sg:phone":"+1 250 785 1284",
    "sg:postcode":"V1J 1X3",
    "sg:province":"BC",
    "sg:tags":[
        "newspaper",
        "advertising"
    ],
    "wof:name":"Bargain Hunter",
    "wof:placetype":"venue"
},
  "geometry": {"coordinates":[-120.827217,56.24622],"type":"Point"}
}