{
  "type": "Feature",
  "properties": {
    "addr:full":"1 Parnell Ave Scarborough ON M1K 1B1",
    "addr:housenumber":"1",
    "addr:postcode":"m1k 1b1",
    "addr:street":"Parnell Ave",
    "iso:country":"CA",
    "sg:address":"1 Parnell Ave",
    "sg:city":"Scarborough",
    "sg:classifiers":[
        {
            "category":"Building & Trades",
            "subcategory":"Construction",
            "type":"Services"
        }
    ],
    "sg:phone":"+1 416 266 8851",
    "sg:postcode":"M1K 1B1",
    "sg:province":"ON",
    "sg:tags":[
        "maker",
        "cabinet"
    ],
    "wof:name":"Olympic Kitchens Inc",
    "wof:placetype":"venue"
},
  "geometry": {"coordinates":[-79.2645950317,43.7059402466],"type":"Point"}
}