{
  "type": "Feature",
  "properties": {
    "addr:full":"1552 Bayview Ave Toronto ON M4G 3B6",
    "addr:housenumber":"1552",
    "addr:postcode":"m4g 3b6",
    "addr:street":"Bayview Ave",
    "iso:country":"CA",
    "sg:address":"1552 Bayview Ave",
    "sg:city":"Toronto",
    "sg:classifiers":[
        {
            "category":"Professional",
            "subcategory":"Accounting & Tax Preparation",
            "type":"Services"
        }
    ],
    "sg:phone":"+1 416 932 8955",
    "sg:postcode":"M4G 3B6",
    "sg:province":"ON",
    "sg:tags":[
        "bookkeeping",
        "general"
    ],
    "wof:name":"Comprehensive Business Svc",
    "wof:placetype":"venue"
},
  "geometry": {"coordinates":[-79.3749847412,43.7049598694],"type":"Point"}
}