{
  "type": "Feature",
  "properties": {
    "addr:full":"121 Boul Notre-Dame Clermont QC G4A 1A3",
    "addr:housenumber":"121",
    "addr:postcode":"g4a 1a3",
    "addr:street":"Boul Notre-Dame",
    "iso:country":"CA",
    "sg:address":"121 Boul Notre-Dame",
    "sg:city":"Clermont",
    "sg:classifiers":[
        {
            "category":"Shopping",
            "subcategory":"Florist",
            "type":"Retail Goods"
        }
    ],
    "sg:phone":"+1 418 439 2441",
    "sg:postcode":"G4A 1A3",
    "sg:province":"QC",
    "wof:name":"Salon Quatre-Saisons",
    "wof:placetype":"venue"
},
  "geometry": {"coordinates":[-70.22515106199999,47.6915550232],"type":"Point"}
}