{
  "type": "Feature",
  "properties": {
    "iso:country":"CA",
    "sg:address":"365 Transport Rd",
    "sg:city":"Springfield",
    "sg:classifiers":[
        {
            "category":"Manufacturing",
            "subcategory":"Signs",
            "type":"Manufacturing & Wholesale Goods"
        }
    ],
    "sg:phone":"+1 204 224 5553",
    "sg:postcode":"R2C 2Z2",
    "sg:province":"MB",
    "wof:name":"Global Sign Concepts",
    "wof:placetype":"venue"
},
  "geometry": {"coordinates":[-96.97631072999999,49.9167366028],"type":"Point"}
}