{
  "type": "Feature",
  "properties": {
    "addr:full":"Dixon Rd Breadalbane PE C0A 1E0",
    "addr:postcode":"c0a 1e0",
    "addr:street":"Dixon Rd",
    "iso:country":"CA",
    "sg:address":"Dixon Rd",
    "sg:city":"Breadalbane",
    "sg:classifiers":[
        {
            "category":"Restaurant",
            "type":"Food & Drink"
        }
    ],
    "sg:phone":"+1 902 621 0002",
    "sg:postcode":"C0A 1E0",
    "sg:province":"PE",
    "wof:name":"Pei Maple Syrup CO",
    "wof:placetype":"venue"
},
  "geometry": {"coordinates":[-63.5032272339,46.3529891968],"type":"Point"}
}