{
  "type": "Feature",
  "properties": {
    "addr:full":"617 Jupiter Crt Sudbury ON P3E 5N1",
    "addr:housenumber":"617",
    "addr:postcode":"p3e 5n1",
    "addr:street":"Jupiter Crt",
    "iso:country":"CA",
    "sg:address":"617 Jupiter Crt",
    "sg:city":"Sudbury",
    "sg:classifiers":[
        {
            "category":"Building & Trades",
            "subcategory":"Construction",
            "type":"Services"
        }
    ],
    "sg:phone":"+1 705 522 6686",
    "sg:postcode":"P3E 5N1",
    "sg:province":"ON",
    "sg:tags":[
        "general",
        "contractor"
    ],
    "wof:name":"Nova Contracting",
    "wof:placetype":"venue"
},
  "geometry": {"coordinates":[-81.0128250122,46.4543495178],"type":"Point"}
}