{
  "type": "Feature",
  "properties": {
    "addr:full":"241 Rang Saint-Etienne N Sainte-Marie QC G6E 3A7",
    "addr:housenumber":"241",
    "addr:postcode":"g6e 3a7",
    "addr:street":"Rang Saint-Etienne N",
    "iso:country":"CA",
    "sg:address":"241 Rang Saint-Etienne N",
    "sg:city":"Sainte-Marie",
    "sg:classifiers":[
        {
            "category":"Building & Trades",
            "subcategory":"Construction",
            "type":"Services"
        }
    ],
    "sg:phone":"+1 418 387 3785",
    "sg:postcode":"G6E 3A7",
    "sg:province":"QC",
    "sg:tags":[
        "contractor"
    ],
    "wof:name":"Construction Jem",
    "wof:placetype":"venue"
},
  "geometry": {"coordinates":[-71.034324646,46.4375915527],"type":"Point"}
}