{
  "type": "Feature",
  "properties": {
    "iso:country":"CA",
    "sg:address":"211 Main St",
    "sg:city":"Saint John",
    "sg:classifiers":[
        {
            "category":"Organizations",
            "subcategory":"Religious Organization",
            "type":"Services"
        }
    ],
    "sg:phone":"+1 506 642 8060",
    "sg:postcode":"E2K 1H7",
    "sg:province":"NB",
    "sg:tags":[
        "church"
    ],
    "wof:name":"Main St Baptist Church",
    "wof:placetype":"venue"
},
  "geometry": {"coordinates":[-66.0821304321,45.2755699158],"type":"Point"}
}