{
  "type": "Feature",
  "properties": {
    "iso:country":"CA",
    "sg:address":"4141 Boul DE LA Grande-Allee",
    "sg:city":"Boisbriand",
    "sg:classifiers":[
        {
            "category":"Utilities",
            "subcategory":"Refuse",
            "type":"Services"
        }
    ],
    "sg:phone":"+1 450 435 2627",
    "sg:postcode":"J7H 1M7",
    "sg:province":"QC",
    "sg:tags":[
        "garbage",
        "collection"
    ],
    "wof:name":"Bfi Environnement",
    "wof:placetype":"venue"
},
  "geometry": {"coordinates":[-73.86521148680001,45.6332969666],"type":"Point"}
}