{
  "type": "Feature",
  "properties": {
    "addr:full":"33 Colborne St S Simcoe ON N3Y 4H2",
    "addr:housenumber":"33",
    "addr:postcode":"n3y 4h2",
    "addr:street":"Colborne St S",
    "iso:country":"CA",
    "sg:address":"33 Colborne St S",
    "sg:city":"Simcoe",
    "sg:classifiers":[
        {
            "category":"Restaurant",
            "type":"Food & Drink"
        }
    ],
    "sg:phone":"+1 519 426 4011",
    "sg:postcode":"N3Y 4H2",
    "sg:province":"ON",
    "sg:tags":[
        "pizza"
    ],
    "wof:name":"New Orleans Pizza",
    "wof:placetype":"venue"
},
  "geometry": {"coordinates":[-80.30587,42.836185],"type":"Point"}
}