{
  "type": "Feature",
  "properties": {
    "iso:country":"CA",
    "sg:address":"5519 Highway 6",
    "sg:city":"Winlaw",
    "sg:classifiers":[
        {
            "category":"Farming",
            "subcategory":"Aquatic Farm",
            "type":"Manufacturing & Wholesale Goods"
        }
    ],
    "sg:phone":"+1 250 226 7979",
    "sg:postcode":"V0G 2J0",
    "sg:province":"BC",
    "sg:tags":[
        "hatchery",
        "fish"
    ],
    "wof:name":"Silver Valley Trout Farm",
    "wof:placetype":"venue"
},
  "geometry": {"coordinates":[-117.498512268,49.6750488281],"type":"Point"}
}