{
  "type": "Feature",
  "properties": {
    "addr:full":"Calgary AB T3C 1S2",
    "addr:postcode":"t3c 1s2",
    "iso:country":"CA",
    "sg:city":"Calgary",
    "sg:classifiers":[
        {
            "category":"Personal",
            "subcategory":"Beauty Salon",
            "type":"Services"
        }
    ],
    "sg:phone":"+1 403 249 6661",
    "sg:postcode":"T3C 1S2",
    "sg:province":"AB",
    "wof:name":"David of Paris Westbrook",
    "wof:placetype":"venue"
},
  "geometry": {"coordinates":[-114.140923,51.041351],"type":"Point"}
}