{
  "type": "Feature",
  "properties": {
    "iso:country":"CA",
    "sg:address":"8420 Cambie Rd",
    "sg:city":"Richmond",
    "sg:classifiers":[
        {
            "category":"Retail",
            "subcategory":"Funeral Services",
            "type":"Services"
        }
    ],
    "sg:phone":"+1 604 273 3748",
    "sg:postcode":"V6X 1K1",
    "sg:province":"BC",
    "sg:tags":[
        "director"
    ],
    "wof:name":"Richmond Funeral Home",
    "wof:placetype":"venue"
},
  "geometry": {"coordinates":[-123.130302,49.184475],"type":"Point"}
}