{
  "type": "Feature",
  "properties": {
    "addr:full":"3857 Rue DE Mont-Royal Saint-Hubert QC J4T 2H2",
    "addr:housenumber":"3857",
    "addr:postcode":"j4t 2h2",
    "addr:street":"Rue De Mont-Royal",
    "iso:country":"CA",
    "sg:address":"3857 Rue DE Mont-Royal",
    "sg:city":"Saint-Hubert",
    "sg:classifiers":[
        {
            "category":"Organizations",
            "subcategory":"Professional Association",
            "type":"Services"
        }
    ],
    "sg:phone":"+1 450 676 9740",
    "sg:postcode":"J4T 2H2",
    "sg:province":"QC",
    "sg:tags":[
        "club"
    ],
    "wof:name":"Club Bel Age Inc",
    "wof:placetype":"venue"
},
  "geometry": {"coordinates":[-73.4693145752,45.4883041382],"type":"Point"}
}