{
  "type": "Feature",
  "properties": {
    "addr:full":"23 Prince Arthur Ave Toronto ON M5R 1B2",
    "addr:housenumber":"23",
    "addr:postcode":"m5r 1b2",
    "addr:street":"Prince Arthur Ave",
    "iso:country":"CA",
    "sg:address":"23 Prince Arthur Ave",
    "sg:city":"Toronto",
    "sg:classifiers":[
        {
            "category":"Organizations",
            "subcategory":"Professional Association",
            "type":"Services"
        }
    ],
    "sg:phone":"+1 416 922 2060",
    "sg:postcode":"M5R 1B2",
    "sg:province":"ON",
    "wof:name":"Women's Art Assn of Canada",
    "wof:placetype":"venue"
},
  "geometry": {"coordinates":[-79.396095,43.669468],"type":"Point"}
}