{
  "type": "Feature",
  "properties": {
    "iso:country":"CA",
    "sg:city":"Kelowna",
    "sg:classifiers":[
        {
            "category":"Building & Trades",
            "subcategory":"Construction",
            "type":"Services"
        }
    ],
    "sg:phone":"+1 250 769 5311",
    "sg:postcode":"V1Z 2S9",
    "sg:province":"BC",
    "sg:tags":[
        "general",
        "contractor"
    ],
    "wof:name":"Logan Contracting Ltd",
    "wof:placetype":"venue"
},
  "geometry": {"coordinates":[-119.571182251,49.8662071228],"type":"Point"}
}