{
  "type": "Feature",
  "properties": {
    "addr:full":"96 Atkinson Ave Moncton NB E1C 7S5",
    "addr:housenumber":"96",
    "addr:postcode":"e1c 7s5",
    "addr:street":"Atkinson Ave",
    "iso:country":"CA",
    "sg:address":"96 Atkinson Ave",
    "sg:city":"Moncton",
    "sg:classifiers":[
        {
            "category":"Building & Trades",
            "subcategory":"Electrical",
            "type":"Services"
        }
    ],
    "sg:phone":"+1 506 858 2274",
    "sg:postcode":"E1C 7S5",
    "sg:province":"NB",
    "sg:tags":[
        "electric",
        "contractor"
    ],
    "wof:name":"Cash Electric",
    "wof:placetype":"venue"
},
  "geometry": {"coordinates":[-64.818321,46.101414],"type":"Point"}
}