{
  "type": "Feature",
  "properties": {
    "iso:country":"CA",
    "sg:city":"Havre-Saint-Pierre",
    "sg:classifiers":[
        {
            "category":"Restaurant",
            "type":"Food & Drink"
        }
    ],
    "sg:phone":"+1 418 538 3070",
    "sg:postcode":"G0G 1P0",
    "sg:province":"QC",
    "wof:name":"Restaurant Chez Julie",
    "wof:placetype":"venue"
},
  "geometry": {"coordinates":[-63.6048164368,50.2439918518],"type":"Point"}
}