{
  "type": "Feature",
  "properties": {
    "addr:full":"Sault Ste Marie ON P6A 2A2",
    "addr:postcode":"p6a 2a2",
    "iso:country":"CA",
    "sg:city":"Sault Ste Marie",
    "sg:classifiers":[
        {
            "category":"Organizations",
            "subcategory":"Professional Association",
            "type":"Services"
        }
    ],
    "sg:phone":"+1 705 256 2335",
    "sg:postcode":"P6A 2A2",
    "sg:province":"ON",
    "wof:name":"Lung Association Algoma Dist",
    "wof:placetype":"venue"
},
  "geometry": {"coordinates":[-84.331161499,46.5101051331],"type":"Point"}
}