{
  "type": "Feature",
  "properties": {
    "iso:country":"CA",
    "sg:city":"Fort St John",
    "sg:classifiers":[
        {
            "category":"Building & Trades",
            "subcategory":"Construction",
            "type":"Services"
        }
    ],
    "sg:phone":"+1 250 785 5314",
    "sg:postcode":"V1J 4H6",
    "sg:province":"BC",
    "sg:tags":[
        "general",
        "contractor"
    ],
    "wof:name":"J & L Ness Ventures Ltd",
    "wof:placetype":"venue"
},
  "geometry": {"coordinates":[-120.847457886,56.2524642944],"type":"Point"}
}