{
  "type": "Feature",
  "properties": {
    "addr:full":"260 Stewart Green SW Calgary AB T3H 3C8",
    "addr:housenumber":"260",
    "addr:postcode":"t3h 3c8",
    "addr:street":"Stewart Green Sw",
    "iso:country":"CA",
    "sg:address":"260 Stewart Green SW",
    "sg:city":"Calgary",
    "sg:classifiers":[
        {
            "category":"Restaurant",
            "type":"Food & Drink"
        }
    ],
    "sg:phone":"+1 403 249 4445",
    "sg:postcode":"T3H 3C8",
    "sg:province":"AB",
    "wof:name":"Joey's Only Seafood",
    "wof:placetype":"venue"
},
  "geometry": {"coordinates":[-114.170326233,51.0150337219],"type":"Point"}
}