{
  "type": "Feature",
  "properties": {
    "iso:country":"CA",
    "sg:address":"5331 Hammond Bay Rd",
    "sg:city":"Nanaimo",
    "sg:classifiers":[
        {
            "category":"Professional",
            "subcategory":"Research",
            "type":"Services"
        }
    ],
    "sg:phone":"+1 250 758 2922",
    "sg:postcode":"V9T 5M9",
    "sg:province":"BC",
    "sg:tags":[
        "environmental",
        "ecological"
    ],
    "wof:name":"J C Lee & Assoc Ltd",
    "wof:placetype":"venue"
},
  "geometry": {"coordinates":[-124.000671387,49.2337875366],"type":"Point"}
}