{
  "type": "Feature",
  "properties": {
    "addr:full":"Viking AB T0B 4N0",
    "addr:postcode":"t0b 4n0",
    "iso:country":"CA",
    "sg:city":"Viking",
    "sg:classifiers":[
        {
            "category":"Building & Trades",
            "subcategory":"Construction",
            "type":"Services"
        }
    ],
    "sg:phone":"+1 780 336 2369",
    "sg:postcode":"T0B 4N0",
    "sg:province":"AB",
    "sg:tags":[
        "contractor"
    ],
    "wof:name":"J D Construction",
    "wof:placetype":"venue"
},
  "geometry": {"coordinates":[-111.783828735,53.0951271057],"type":"Point"}
}