{
  "type": "Feature",
  "properties": {
    "addr:full":"London ON N6E 3T1",
    "addr:postcode":"n6e 3t1",
    "iso:country":"CA",
    "sg:city":"London",
    "sg:classifiers":[
        {
            "category":"Shopping",
            "subcategory":"Clothing, Apparel, & Fashions",
            "type":"Retail Goods"
        }
    ],
    "sg:phone":"+1 519 668 6677",
    "sg:postcode":"N6E 3T1",
    "sg:province":"ON",
    "wof:name":"Jay Set Fashion Outlet",
    "wof:placetype":"venue"
},
  "geometry": {"coordinates":[-81.2188415527,42.9256134033],"type":"Point"}
}