{
  "type": "Feature",
  "properties": {
    "addr:full":"Gloucester ON K1B 3R5",
    "addr:postcode":"k1b 3r5",
    "iso:country":"CA",
    "sg:city":"Gloucester",
    "sg:classifiers":[
        {
            "category":"Wholesale",
            "subcategory":"Fruits & Vegetables",
            "type":"Manufacturing & Wholesale Goods"
        }
    ],
    "sg:phone":"+1 613 742 9999",
    "sg:postcode":"K1B 3R5",
    "sg:province":"ON",
    "wof:name":"Mac Artney Farms",
    "wof:placetype":"venue"
},
  "geometry": {"coordinates":[-75.62793000000001,45.41478],"type":"Point"}
}