{
  "type": "Feature",
  "properties": {
    "addr:full":"76 Rue Dufferin Salaberry-DE-Valleyfield QC J6S 1Y2",
    "addr:housenumber":"76",
    "addr:postcode":"j6s 1y2",
    "addr:street":"Rue Dufferin",
    "iso:country":"CA",
    "sg:address":"76 Rue Dufferin",
    "sg:city":"Salaberry-DE-Valleyfield",
    "sg:classifiers":[
        {
            "category":"Shopping",
            "subcategory":"Pharmacy",
            "type":"Retail Goods"
        }
    ],
    "sg:phone":"+1 450 371 3333",
    "sg:postcode":"J6S 1Y2",
    "sg:province":"QC",
    "wof:name":"Jean Coutu Pharmacy",
    "wof:placetype":"venue"
},
  "geometry": {"coordinates":[-74.12841033940001,45.2626914978],"type":"Point"}
}