{
  "type": "Feature",
  "properties": {
    "addr:full":"1919 52 St NW Calgary AB T3B 1C3",
    "addr:housenumber":"1919",
    "addr:postcode":"t3b 1c3",
    "addr:street":"52 St Nw",
    "iso:country":"CA",
    "sg:address":"1919 52 St NW",
    "sg:city":"Calgary",
    "sg:classifiers":[
        {
            "category":"Travel",
            "subcategory":"Hotels & Motels",
            "type":"Entertainment"
        }
    ],
    "sg:phone":"+1 403 247 1330",
    "sg:postcode":"T3B 1C3",
    "sg:province":"AB",
    "sg:tags":[
        "breakfast",
        "accommodation",
        "bed"
    ],
    "wof:name":"Along River Ridge 4 Star B & B",
    "wof:placetype":"venue"
},
  "geometry": {"coordinates":[-114.16830400000001,51.078865],"type":"Point"}
}