{
  "type": "Feature",
  "properties": {
    "iso:country":"CA",
    "sg:address":"224 Rue Principale",
    "sg:city":"Saint-Jules",
    "sg:classifiers":[
        {
            "category":"Shopping",
            "subcategory":"Bicycles & Sporting Goods",
            "type":"Retail Goods"
        }
    ],
    "sg:phone":"+1 418 397 8222",
    "sg:postcode":"G0N 1R0",
    "sg:province":"QC",
    "sg:tags":[
        "gun",
        "gunsmith"
    ],
    "wof:name":"Econo Sport",
    "wof:placetype":"venue"
},
  "geometry": {"coordinates":[-70.9411315918,46.2199401855],"type":"Point"}
}