{
  "type": "Feature",
  "properties": {
    "addr:full":"12500 Rue DE L'Avenir Mirabel QC J7J 2K3",
    "addr:housenumber":"12500",
    "addr:postcode":"j7j 2k3",
    "addr:street":"Rue De L'Avenir",
    "iso:country":"CA",
    "sg:address":"12500 Rue DE L'Avenir",
    "sg:city":"Mirabel",
    "sg:classifiers":[
        {
            "category":"Building & Trades",
            "subcategory":"Construction",
            "type":"Services"
        }
    ],
    "sg:phone":"+1 514 334 9620",
    "sg:postcode":"J7J 2K3",
    "sg:province":"QC",
    "sg:tags":[
        "insulation",
        "heat",
        "contractor"
    ],
    "wof:name":"B P St Laurent Inc",
    "wof:placetype":"venue"
},
  "geometry": {"coordinates":[-73.937172,45.691074],"type":"Point"}
}