{
  "type": "Feature",
  "properties": {
    "addr:full":"227 Rue Lafontaine Riviere-Du-Loup QC G5R 3A6",
    "addr:housenumber":"227",
    "addr:postcode":"g5r 3a6",
    "addr:street":"Rue Lafontaine",
    "iso:country":"CA",
    "sg:address":"227 Rue Lafontaine",
    "sg:city":"Riviere-Du-Loup",
    "sg:classifiers":[
        {
            "category":"Personal",
            "subcategory":"Beauty Salon",
            "type":"Services"
        }
    ],
    "sg:phone":"+1 418 862 7666",
    "sg:postcode":"G5R 3A6",
    "sg:province":"QC",
    "wof:name":"Institut DE Beaute Christine",
    "wof:placetype":"venue"
},
  "geometry": {"coordinates":[-69.53685,47.834629],"type":"Point"}
}