{
  "type": "Feature",
  "properties": {
    "addr:full":"Anderson Road NB E7G 4C5",
    "addr:postcode":"e7g 4c5",
    "addr:street":"Anderson Road",
    "iso:country":"CA",
    "sg:city":"Anderson Road",
    "sg:classifiers":[
        {
            "category":"Organizations",
            "subcategory":"Religious Organization",
            "type":"Services"
        }
    ],
    "sg:phone":"+1 506 356 1987",
    "sg:postcode":"E7G 4C5",
    "sg:province":"NB",
    "sg:tags":[
        "church"
    ],
    "wof:name":"St Theresa's Church",
    "wof:placetype":"venue"
},
  "geometry": {"coordinates":[-67.496956,46.866104],"type":"Point"}
}