{
  "type": "Feature",
  "properties": {
    "addr:full":"947 Falconbridge Rd Sudbury ON P3A 5K8",
    "addr:housenumber":"947",
    "addr:postcode":"p3a 5k8",
    "addr:street":"Falconbridge Rd",
    "iso:country":"CA",
    "sg:address":"947 Falconbridge Rd",
    "sg:city":"Sudbury",
    "sg:classifiers":[
        {
            "category":"Travel",
            "subcategory":"Hotels & Motels",
            "type":"Entertainment"
        }
    ],
    "sg:phone":"+1 705 524 2747",
    "sg:postcode":"P3A 5K8",
    "sg:province":"ON",
    "wof:name":"Solid Gold Vip Lounge",
    "wof:placetype":"venue"
},
  "geometry": {"coordinates":[-80.923744,46.517857],"type":"Point"}
}