{
  "type": "Feature",
  "properties": {
    "iso:country":"CA",
    "sg:address":"435 Rue Principale",
    "sg:city":"Boulanger",
    "sg:classifiers":[
        {
            "category":"Organizations",
            "subcategory":"Religious Organization",
            "type":"Services"
        }
    ],
    "sg:phone":"+1 418 276 3037",
    "sg:postcode":"G0W 1E0",
    "sg:province":"QC",
    "sg:tags":[
        "church"
    ],
    "wof:name":"Presbytere DE Ste Jeanne D'Arc",
    "wof:placetype":"venue"
},
  "geometry": {"coordinates":[-72.084869,48.864445],"type":"Point"}
}