{
  "type": "Feature",
  "properties": {
    "addr:full":"1161 98th St North Battleford SK S9A 0L7",
    "addr:housenumber":"1161",
    "addr:postcode":"s9a 0l7",
    "addr:street":"98Th St",
    "iso:country":"CA",
    "sg:address":"1161 98th St",
    "sg:city":"North Battleford",
    "sg:classifiers":[
        {
            "category":"Wholesale",
            "subcategory":"Tobacco Products",
            "type":"Manufacturing & Wholesale Goods"
        }
    ],
    "sg:phone":"+1 306 446 8300",
    "sg:postcode":"S9A 0L7",
    "sg:province":"SK",
    "sg:tags":[
        "cigarette",
        "cigar",
        "dealer"
    ],
    "wof:name":"Nor West Distributors Inc",
    "wof:placetype":"venue"
},
  "geometry": {"coordinates":[-108.302238,52.774502],"type":"Point"}
}