{
  "type": "Feature",
  "properties": {
    "addr:full":"211 Rue Saint-Andre Saint-Remi QC J0L 2L0",
    "addr:housenumber":"211",
    "addr:postcode":"j0l 2l0",
    "addr:street":"Rue Saint-Andre Saint-Remi",
    "iso:country":"CA",
    "sg:address":"211 Rue Saint-Andre",
    "sg:city":"Saint-Remi",
    "sg:classifiers":[
        {
            "category":"Bars & Pubs",
            "type":"Food & Drink"
        }
    ],
    "sg:phone":"+1 450 454 4956",
    "sg:postcode":"J0L 2L0",
    "sg:province":"QC",
    "wof:name":"Bar Jc Inc",
    "wof:placetype":"venue"
},
  "geometry": {"coordinates":[-73.610542,45.256184],"type":"Point"}
}