{
  "type": "Feature",
  "properties": {
    "addr:full":"494 Eastchester Ave E St Catharines ON L2M 6S3",
    "addr:housenumber":"494",
    "addr:postcode":"l2m 6s3",
    "addr:street":"Eastchester Ave E",
    "iso:country":"CA",
    "sg:address":"494 Eastchester Ave E",
    "sg:city":"St Catharines",
    "sg:classifiers":[
        {
            "category":"Home & Garden",
            "subcategory":"Carpets & Floor Coverings",
            "type":"Retail Goods"
        }
    ],
    "sg:phone":"+1 905 682 0107",
    "sg:postcode":"L2M 6S3",
    "sg:province":"ON",
    "sg:tags":[
        "material",
        "rug"
    ],
    "wof:name":"Carpet Emporium Inc",
    "wof:placetype":"venue"
},
  "geometry": {"coordinates":[-79.201004,43.170151],"type":"Point"}
}