{
  "type": "Feature",
  "properties": {
    "addr:full":"911 Lorne St # 1 Sudbury ON P3C 3J5",
    "addr:housenumber":"911",
    "addr:postcode":"p3c 3j5",
    "addr:street":"Lorne St # 1",
    "iso:country":"CA",
    "sg:address":"911 Lorne St # 1",
    "sg:city":"Sudbury",
    "sg:classifiers":[
        {
            "category":"Personal",
            "subcategory":"Beauty Salon",
            "type":"Services"
        }
    ],
    "sg:phone":"+1 705 671 2515",
    "sg:postcode":"P3C 3J5",
    "sg:province":"ON",
    "wof:name":"Ugo Barber & Hairstyling",
    "wof:placetype":"venue"
},
  "geometry": {"coordinates":[-81.02005,46.476498],"type":"Point"}
}