{
  "type": "Feature",
  "properties": {
    "iso:country":"CA",
    "sg:address":"245 Manitoba St",
    "sg:city":"Bracebridge",
    "sg:classifiers":[
        {
            "category":"Banks & Credit Unions",
            "subcategory":"Bank",
            "type":"Services"
        }
    ],
    "sg:phone":"+1 705 645 5213",
    "sg:postcode":"P1L 1S2",
    "sg:province":"ON",
    "wof:name":"Cibc",
    "wof:placetype":"venue"
},
  "geometry": {"coordinates":[-79.3181686401,45.0451278687],"type":"Point"}
}