{
  "type": "Feature",
  "properties": {
    "addr:full":"902 Centre St NE Calgary AB T2E 2P7",
    "addr:housenumber":"902",
    "addr:postcode":"t2e 2p7",
    "addr:street":"Centre St Ne",
    "iso:country":"CA",
    "sg:address":"902 Centre St NE",
    "sg:city":"Calgary",
    "sg:classifiers":[
        {
            "category":"Professional",
            "subcategory":"Computer Services",
            "type":"Services"
        }
    ],
    "sg:phone":"+1 403 219 3031",
    "sg:postcode":"T2E 2P7",
    "sg:province":"AB",
    "wof:name":"Dawson Technologies",
    "wof:placetype":"venue"
},
  "geometry": {"coordinates":[-114.04222106900001,51.0526733398],"type":"Point"}
}