{
  "type": "Feature",
  "properties": {
    "addr:full":"61 Saskatchewan Ave E Portage LA Prairie MB R1N 0L8",
    "addr:housenumber":"61",
    "addr:postcode":"r1n 0l8",
    "addr:street":"Saskatchewan Ave E",
    "iso:country":"CA",
    "sg:address":"61 Saskatchewan Ave E",
    "sg:city":"Portage LA Prairie",
    "sg:classifiers":[
        {
            "category":"Restaurant",
            "type":"Food & Drink"
        }
    ],
    "sg:phone":"+1 204 856 2468",
    "sg:postcode":"R1N 0L8",
    "sg:province":"MB",
    "sg:tags":[
        "shop",
        "coffee",
        "gift"
    ],
    "wof:name":"Grindstone Coffee CO",
    "wof:placetype":"venue"
},
  "geometry": {"coordinates":[-98.29047393800001,49.972946167],"type":"Point"}
}