{
  "type": "Feature",
  "properties": {
    "addr:full":"North York ON M3J 2C6",
    "addr:postcode":"m3j 2c6",
    "iso:country":"CA",
    "sg:city":"North York",
    "sg:classifiers":[
        {
            "category":"Retail",
            "subcategory":"Auto Repair",
            "type":"Services"
        }
    ],
    "sg:phone":"+1 416 638 1255",
    "sg:postcode":"M3J 2C6",
    "sg:province":"ON",
    "sg:tags":[
        "repairing",
        "automobile"
    ],
    "wof:name":"New Champagne Auto Repair Ont",
    "wof:placetype":"venue"
},
  "geometry": {"coordinates":[-79.473045,43.764938],"type":"Point"}
}