{
  "type": "Feature",
  "properties": {
    "addr:full":"Medicine Hat AB T1A 8E7",
    "addr:postcode":"t1a 8e7",
    "iso:country":"CA",
    "sg:city":"Medicine Hat",
    "sg:classifiers":[
        {
            "category":"Wholesale",
            "subcategory":"Electrical",
            "type":"Manufacturing & Wholesale Goods"
        }
    ],
    "sg:phone":"+1 403 529 2444",
    "sg:postcode":"T1A 8E7",
    "sg:province":"AB",
    "sg:tags":[
        "equipment",
        "electric",
        "supply"
    ],
    "wof:name":"Guillevin International CO",
    "wof:placetype":"venue"
},
  "geometry": {"coordinates":[-110.70469665500001,50.0184936523],"type":"Point"}
}