{
  "type": "Feature",
  "properties": {
    "addr:full":"Brockville ON K6V 5T4",
    "addr:postcode":"k6v 5t4",
    "iso:country":"CA",
    "sg:city":"Brockville",
    "sg:classifiers":[
        {
            "category":"Autos & Motor Vehicles",
            "subcategory":"Automobile Sales",
            "type":"Retail Goods"
        }
    ],
    "sg:phone":"+1 613 498 3366",
    "sg:postcode":"K6V 5T4",
    "sg:province":"ON",
    "sg:tags":[
        "car",
        "dealer"
    ],
    "wof:name":"Accent Auto Sales",
    "wof:placetype":"venue"
},
  "geometry": {"coordinates":[-75.68301391599999,44.5903892517],"type":"Point"}
}