{
  "type": "Feature",
  "properties": {
    "addr:full":"78 Glenwood Ave Sault Ste Marie ON P6A 4T7",
    "addr:housenumber":"78",
    "addr:postcode":"p6a 4t7",
    "addr:street":"Glenwood Ave",
    "iso:country":"CA",
    "sg:address":"78 Glenwood Ave",
    "sg:city":"Sault Ste Marie",
    "sg:classifiers":[
        {
            "category":"Professional",
            "subcategory":"Printing & Photocopies",
            "type":"Services"
        }
    ],
    "sg:phone":"+1 705 946 1222",
    "sg:postcode":"P6A 4T7",
    "sg:province":"ON",
    "sg:tags":[
        "printer",
        "duplicating",
        "copying"
    ],
    "wof:name":"Lamon's Printing Inc",
    "wof:placetype":"venue"
},
  "geometry": {"coordinates":[-84.26166499999999,46.521084],"type":"Point"}
}