{
  "type": "Feature",
  "properties": {
    "addr:full":"Elk Point AB T0A 1A0",
    "addr:postcode":"t0a 1a0",
    "iso:country":"CA",
    "sg:city":"Elk Point",
    "sg:classifiers":[
        {
            "category":"Professional",
            "subcategory":"Accounting & Tax Preparation",
            "type":"Services"
        }
    ],
    "sg:phone":"+1 780 724 3300",
    "sg:postcode":"T0A 1A0",
    "sg:province":"AB",
    "sg:tags":[
        "accountant"
    ],
    "wof:name":"Joly Mc Carthy & Dion",
    "wof:placetype":"venue"
},
  "geometry": {"coordinates":[-110.89663696300001,53.9011383057],"type":"Point"}
}