{
  "type": "Feature",
  "properties": {
    "addr:full":"1250 Bloor St W Toronto ON M6H 1N5",
    "addr:housenumber":"1250",
    "addr:postcode":"m6h 1n5",
    "addr:street":"Bloor St W",
    "iso:country":"CA",
    "sg:address":"1250 Bloor St W",
    "sg:city":"Toronto",
    "sg:classifiers":[
        {
            "category":"Personal",
            "subcategory":"Beauty Salon",
            "type":"Services"
        }
    ],
    "sg:phone":"+1 416 588 0632",
    "sg:postcode":"M6H 1N5",
    "sg:province":"ON",
    "wof:name":"Magic Touch Beauty Salon",
    "wof:placetype":"venue"
},
  "geometry": {"coordinates":[-79.44032300000001,43.65892],"type":"Point"}
}