{
  "type": "Feature",
  "properties": {
    "addr:full":"140 Roe Ave Gander NL A1V 1W5",
    "addr:housenumber":"140",
    "addr:postcode":"a1v 1w5",
    "addr:street":"Roe Ave",
    "iso:country":"CA",
    "sg:address":"140 Roe Ave",
    "sg:city":"Gander",
    "sg:classifiers":[
        {
            "category":"Freight",
            "type":"Transportation"
        }
    ],
    "sg:phone":"+1 709 256 2800",
    "sg:postcode":"A1V 1W5",
    "sg:province":"NL",
    "sg:tags":[
        "mover",
        "commercial"
    ],
    "wof:name":"Gander Self Storage Ltd",
    "wof:placetype":"venue"
},
  "geometry": {"coordinates":[-54.5949401855,48.9594841003],"type":"Point"}
}