{
  "type": "Feature",
  "properties": {
    "addr:full":"4708 50 Ave Drayton Valley AB T7A 1E1",
    "addr:housenumber":"4708",
    "addr:postcode":"t7a 1e1",
    "addr:street":"50 Ave",
    "iso:country":"CA",
    "sg:address":"4708 50 Ave",
    "sg:city":"Drayton Valley",
    "sg:classifiers":[
        {
            "category":"Organizations",
            "subcategory":"Religious Organization",
            "type":"Services"
        }
    ],
    "sg:phone":"+1 780 542 5254",
    "sg:postcode":"T7A 1E1",
    "sg:province":"AB",
    "sg:tags":[
        "church"
    ],
    "wof:name":"Catholic Institutions",
    "wof:placetype":"venue"
},
  "geometry": {"coordinates":[-114.97074890099999,53.2215881348],"type":"Point"}
}