{
  "type": "Feature",
  "properties": {
    "addr:full":"1018 Boul Saint-Laurent Montreal QC H2Z 1J3",
    "addr:housenumber":"1018",
    "addr:postcode":"h2z 1j3",
    "addr:street":"Boul Saint-Laurent",
    "iso:country":"CA",
    "sg:address":"1018 Boul Saint-Laurent",
    "sg:city":"Montreal",
    "sg:classifiers":[
        {
            "category":"Shopping",
            "subcategory":"Gifts & Souvenirs",
            "type":"Retail Goods"
        }
    ],
    "sg:phone":"+1 514 879 1234",
    "sg:postcode":"H2Z 1J3",
    "sg:province":"QC",
    "sg:tags":[
        "shop"
    ],
    "wof:name":"Shun Fat Trading",
    "wof:placetype":"venue"
},
  "geometry": {"coordinates":[-73.55954699999999,45.507767],"type":"Point"}
}