{
  "type": "Feature",
  "properties": {
    "addr:full":"4721 Lakelse Ave Terrace BC V8G 1R5",
    "addr:housenumber":"4721",
    "addr:postcode":"v8g 1r5",
    "addr:street":"Lakelse Ave",
    "iso:country":"CA",
    "sg:address":"4721 Lakelse Ave",
    "sg:city":"Terrace",
    "sg:classifiers":[
        {
            "category":"Shopping",
            "subcategory":"Bicycles & Sporting Goods",
            "type":"Retail Goods"
        }
    ],
    "sg:phone":"+1 250 635 9404",
    "sg:postcode":"V8G 1R5",
    "sg:province":"BC",
    "wof:name":"Ruins Board Shop",
    "wof:placetype":"venue"
},
  "geometry": {"coordinates":[-128.594512939,54.516872406],"type":"Point"}
}