{
  "type": "Feature",
  "properties": {
    "addr:full":"10109 125 St NW Edmonton AB T5N 1S7",
    "addr:housenumber":"10109",
    "addr:postcode":"t5n 1s7",
    "addr:street":"125 St Nw",
    "iso:country":"CA",
    "sg:address":"10109 125 St NW",
    "sg:city":"Edmonton",
    "sg:classifiers":[
        {
            "category":"Restaurant",
            "type":"Food & Drink"
        }
    ],
    "sg:phone":"+1 780 482 7577",
    "sg:postcode":"T5N 1S7",
    "sg:province":"AB",
    "wof:name":"Manor Cafe",
    "wof:placetype":"venue"
},
  "geometry": {"coordinates":[-113.53742200000001,53.542145],"type":"Point"}
}