{
  "type": "Feature",
  "properties": {
    "addr:full":"3544 Innes Rd Orleans ON K1C 1T1",
    "addr:housenumber":"3544",
    "addr:postcode":"k1c 1t1",
    "addr:street":"Innes Rd",
    "iso:country":"CA",
    "sg:address":"3544 Innes Rd",
    "sg:city":"Orleans",
    "sg:classifiers":[
        {
            "category":"Professional",
            "subcategory":"Accounting & Tax Preparation",
            "type":"Services"
        }
    ],
    "sg:phone":"+1 613 830 1050",
    "sg:postcode":"K1C 1T1",
    "sg:province":"ON",
    "sg:tags":[
        "accountant"
    ],
    "wof:name":"Poirier, John J CA",
    "wof:placetype":"venue"
},
  "geometry": {"coordinates":[-75.5233078003,45.4479904175],"type":"Point"}
}