{
  "type": "Feature",
  "properties": {
    "addr:full":"650 Georgia St W # 720 Vancouver BC V6B 6L7",
    "addr:housenumber":"650",
    "addr:postcode":"v6b 6l7",
    "addr:street":"Georgia St W # 720",
    "iso:country":"CA",
    "sg:address":"650 Georgia St W # 720",
    "sg:city":"Vancouver",
    "sg:classifiers":[
        {
            "category":"Banks & Credit Unions",
            "subcategory":"Investment Brokerage",
            "type":"Services"
        }
    ],
    "sg:phone":"+1 604 687 1027",
    "sg:postcode":"V6B 6L7",
    "sg:province":"BC",
    "sg:tags":[
        "consultant",
        "planning",
        "financial"
    ],
    "wof:name":"Partners in Planning Financial",
    "wof:placetype":"venue"
},
  "geometry": {"coordinates":[-123.117699,49.282082],"type":"Point"}
}