{
  "type": "Feature",
  "properties": {
    "addr:full":"Lorraine QC J6Z 3R8",
    "addr:postcode":"j6z 3r8",
    "iso:country":"CA",
    "sg:city":"Lorraine",
    "sg:classifiers":[
        {
            "category":"Health Services",
            "subcategory":"Doctor",
            "type":"Services"
        }
    ],
    "sg:phone":"+1 450 621 2099",
    "sg:postcode":"J6Z 3R8",
    "sg:province":"QC",
    "sg:tags":[
        "clinic",
        "chiropractor"
    ],
    "wof:name":"Clinique Chiropractique",
    "wof:placetype":"venue"
},
  "geometry": {"coordinates":[-73.7825088501,45.6657714844],"type":"Point"}
}