{
  "type": "Feature",
  "properties": {
    "addr:full":"8 Main St Sackville NB E4L 4A3",
    "addr:housenumber":"8",
    "addr:postcode":"e4l 4a3",
    "addr:street":"Main St",
    "iso:country":"CA",
    "sg:address":"8 Main St",
    "sg:city":"Sackville",
    "sg:classifiers":[
        {
            "category":"Organizations",
            "subcategory":"Professional Association",
            "type":"Services"
        }
    ],
    "sg:phone":"+1 506 364 8813",
    "sg:postcode":"E4L 4A3",
    "sg:province":"NB",
    "wof:name":"Red Cross Canadian Society",
    "wof:placetype":"venue"
},
  "geometry": {"coordinates":[-64.3716812134,45.8921394348],"type":"Point"}
}