{
  "type": "Feature",
  "properties": {
    "addr:full":"Etobicoke ON M9C 5N2",
    "addr:postcode":"m9c 5n2",
    "iso:country":"CA",
    "sg:city":"Etobicoke",
    "sg:classifiers":[
        {
            "category":"Health Services",
            "subcategory":"Doctor",
            "type":"Services"
        }
    ],
    "sg:phone":"+1 416 626 1538",
    "sg:postcode":"M9C 5N2",
    "sg:province":"ON",
    "sg:tags":[
        "physician",
        "surgeon"
    ],
    "wof:name":"Daya, M N MD",
    "wof:placetype":"venue"
},
  "geometry": {"coordinates":[-79.560181,43.608768],"type":"Point"}
}