{
  "type": "Feature",
  "properties": {
    "addr:full":"2001 16th Ave Campbell River BC V9W 8E8",
    "addr:housenumber":"2001",
    "addr:postcode":"v9w 8e8",
    "addr:street":"16Th Ave",
    "iso:country":"CA",
    "sg:address":"2001 16th Ave",
    "sg:city":"Campbell River",
    "sg:classifiers":[
        {
            "category":"Restaurant",
            "type":"Food & Drink"
        }
    ],
    "sg:phone":"+1 250 830 1466",
    "sg:postcode":"V9W 8E8",
    "sg:province":"BC",
    "wof:name":"Mc Donald's",
    "wof:placetype":"venue"
},
  "geometry": {"coordinates":[-125.273537,50.030724],"type":"Point"}
}