{
  "type": "Feature",
  "properties": {
    "iso:country":"CA",
    "sg:address":"1555 Main St W",
    "sg:city":"Hamilton",
    "sg:classifiers":[
        {
            "category":"Home & Garden",
            "subcategory":"Household Appliances",
            "type":"Retail Goods"
        }
    ],
    "sg:phone":"+1 905 529 7751",
    "sg:postcode":"L8S 1E6",
    "sg:province":"ON",
    "sg:tags":[
        "television",
        "radio"
    ],
    "wof:name":"Shanlin Tv & Appliances",
    "wof:placetype":"venue"
},
  "geometry": {"coordinates":[-79.9272155762,43.2573776245],"type":"Point"}
}