{
  "type": "Feature",
  "properties": {
    "addr:full":"139 Commercial Pk Tumbler Ridge BC V0C 2W0",
    "addr:housenumber":"139",
    "addr:postcode":"bc v0c 2w0",
    "addr:street":"Commercial Pk Tumbler Ridge",
    "iso:country":"CA",
    "sg:address":"139 Commercial Pk",
    "sg:city":"Tumbler Ridge",
    "sg:classifiers":[
        {
            "category":"Utilities",
            "subcategory":"Fuel Oil & Lpg",
            "type":"Services"
        }
    ],
    "sg:phone":"+1 250 242 4400",
    "sg:postcode":"V0C 2W0",
    "sg:province":"BC",
    "sg:tags":[
        "propane",
        "gas"
    ],
    "wof:name":"Joy Propane Ltd",
    "wof:placetype":"venue"
},
  "geometry": {"coordinates":[-120.99092865,55.1226005554],"type":"Point"}
}