{
  "type": "Feature",
  "properties": {
    "iso:country":"CA",
    "sg:address":"2053 Campbell Rd",
    "sg:city":"Kelowna",
    "sg:classifiers":[
        {
            "category":"Manufacturing",
            "subcategory":"Watercraft",
            "type":"Manufacturing & Wholesale Goods"
        }
    ],
    "sg:phone":"+1 250 769 7694",
    "sg:postcode":"V1Z 1S9",
    "sg:province":"BC",
    "sg:tags":[
        "barge"
    ],
    "wof:name":"Shoreline Pile Driving",
    "wof:placetype":"venue"
},
  "geometry": {"coordinates":[-119.524902,49.878105],"type":"Point"}
}