{
  "type": "Feature",
  "properties": {
    "addr:full":"101 Rue Grenier Charlemagne QC J5Z 4C6",
    "addr:housenumber":"101",
    "addr:postcode":"j5z 4c6",
    "addr:street":"Rue Grenier",
    "iso:country":"CA",
    "sg:address":"101 Rue Grenier",
    "sg:city":"Charlemagne",
    "sg:classifiers":[
        {
            "category":"Autos & Motor Vehicles",
            "subcategory":"Motorcycle Sales",
            "type":"Retail Goods"
        }
    ],
    "sg:phone":"+1 450 585 5224",
    "sg:postcode":"J5Z 4C6",
    "sg:province":"QC",
    "sg:tags":[
        "scooter"
    ],
    "wof:name":"Moto Repentigny Enr",
    "wof:placetype":"venue"
},
  "geometry": {"coordinates":[-73.488609,45.720478],"type":"Point"}
}