{
  "type": "Feature",
  "properties": {
    "addr:full":"3071 Babich St Abbotsford BC V2S 5W5",
    "addr:housenumber":"3071",
    "addr:postcode":"v2s 5w5",
    "addr:street":"Babich St",
    "iso:country":"CA",
    "sg:address":"3071 Babich St",
    "sg:city":"Abbotsford",
    "sg:classifiers":[
        {
            "category":"Social Services",
            "subcategory":"Child Care",
            "type":"Services"
        }
    ],
    "sg:phone":"+1 604 820 1240",
    "sg:postcode":"V2S 5W5",
    "sg:province":"BC",
    "wof:name":"Mission Montessori Preschool",
    "wof:placetype":"venue"
},
  "geometry": {"coordinates":[-122.300293,49.057945],"type":"Point"}
}