{
  "type": "Feature",
  "properties": {
    "addr:full":"742 Old Tecumseh Rd Belle River ON N0R 1A0",
    "addr:housenumber":"742",
    "addr:postcode":"n0r 1a0",
    "addr:street":"Old Tecumseh Rd",
    "iso:country":"CA",
    "sg:address":"742 Old Tecumseh Rd",
    "sg:city":"Belle River",
    "sg:classifiers":[
        {
            "category":"Manufacturing",
            "subcategory":"Wood Products",
            "type":"Manufacturing & Wholesale Goods"
        }
    ],
    "sg:phone":"+1 519 979 8275",
    "sg:postcode":"N0R 1A0",
    "sg:province":"ON",
    "sg:tags":[
        "picture",
        "frame"
    ],
    "wof:name":"Off the Wall Art & Framing",
    "wof:placetype":"venue"
},
  "geometry": {"coordinates":[-82.650856,42.296436],"type":"Point"}
}