{
  "type": "Feature",
  "properties": {
    "addr:full":"Richmond Hill ON L4B 1K6",
    "addr:postcode":"l4b 1k6",
    "iso:country":"CA",
    "sg:city":"Richmond Hill",
    "sg:classifiers":[
        {
            "category":"Wholesale",
            "subcategory":"Electrical",
            "type":"Manufacturing & Wholesale Goods"
        }
    ],
    "sg:phone":"+1 905 731 6892",
    "sg:postcode":"L4B 1K6",
    "sg:province":"ON",
    "sg:tags":[
        "control",
        "video",
        "security",
        "disc",
        "tape"
    ],
    "wof:name":"Video Solutions Inc",
    "wof:placetype":"venue"
},
  "geometry": {"coordinates":[-79.3933105469,43.8544807434],"type":"Point"}
}