{
  "type": "Feature",
  "properties": {
    "addr:full":"4114 Portage Rd Niagara Falls ON L2E 6A3",
    "addr:housenumber":"4114",
    "addr:postcode":"l2e 6a3",
    "addr:street":"Portage Rd",
    "iso:country":"CA",
    "sg:address":"4114 Portage Rd",
    "sg:city":"Niagara Falls",
    "sg:classifiers":[
        {
            "category":"Personal",
            "subcategory":"Beauty Salon",
            "type":"Services"
        }
    ],
    "sg:phone":"+1 905 374 6266",
    "sg:postcode":"L2E 6A3",
    "sg:province":"ON",
    "wof:name":"Studio 55 Hair Salon",
    "wof:placetype":"venue"
},
  "geometry": {"coordinates":[-79.098373,43.114559],"type":"Point"}
}