{
  "type": "Feature",
  "properties": {
    "addr:full":"49 Moore St Carleton Place ON K7C 2R3",
    "addr:housenumber":"49",
    "addr:postcode":"k7c 2r3",
    "addr:street":"Moore St",
    "iso:country":"CA",
    "sg:address":"49 Moore St",
    "sg:city":"Carleton Place",
    "sg:classifiers":[
        {
            "category":"Restaurant",
            "type":"Food & Drink"
        }
    ],
    "sg:phone":"+1 613 257 4000",
    "sg:postcode":"K7C 2R3",
    "sg:province":"ON",
    "wof:name":"Phil's Pizza",
    "wof:placetype":"venue"
},
  "geometry": {"coordinates":[-76.14072400000001,45.136799],"type":"Point"}
}