{
  "type": "Feature",
  "properties": {
    "addr:full":"Calgary AB T2P 1G3",
    "addr:postcode":"t2p 1g3",
    "iso:country":"CA",
    "sg:city":"Calgary",
    "sg:classifiers":[
        {
            "category":"Restaurant",
            "type":"Food & Drink"
        }
    ],
    "sg:phone":"+1 403 262 9993",
    "sg:postcode":"T2P 1G3",
    "sg:province":"AB",
    "wof:name":"Kites Again Dim Sum",
    "wof:placetype":"venue"
},
  "geometry": {"coordinates":[-114.072006,51.04567],"type":"Point"}
}