{
  "type": "Feature",
  "properties": {
    "addr:full":"1629 Fairfield Rd Victoria BC V8S 1G4",
    "addr:housenumber":"1629",
    "addr:postcode":"v8s 1g4",
    "addr:street":"Fairfield Rd",
    "iso:country":"CA",
    "sg:address":"1629 Fairfield Rd",
    "sg:city":"Victoria",
    "sg:classifiers":[
        {
            "category":"Real Estate",
            "subcategory":"Architect",
            "type":"Services"
        }
    ],
    "sg:phone":"+1 250 592 5593",
    "sg:postcode":"V8S 1G4",
    "sg:province":"BC",
    "wof:name":"Brian Tw Morris Architect",
    "wof:placetype":"venue"
},
  "geometry": {"coordinates":[-123.335503,48.412315],"type":"Point"}
}