{
  "type": "Feature",
  "properties": {
    "iso:country":"CA",
    "sg:address":"453 Wentworth St N",
    "sg:city":"Hamilton",
    "sg:classifiers":[
        {
            "category":"Building & Trades",
            "subcategory":"Construction",
            "type":"Services"
        }
    ],
    "sg:phone":"+1 905 527 0981",
    "sg:postcode":"L8L 5W7",
    "sg:province":"ON",
    "sg:tags":[
        "downspouts",
        "gutter"
    ],
    "wof:name":"Miller's Tin Shop",
    "wof:placetype":"venue"
},
  "geometry": {"coordinates":[-79.8436203003,43.2647857666],"type":"Point"}
}