{
  "type": "Feature",
  "properties": {
    "iso:country":"CA",
    "sg:address":"2870 White St",
    "sg:city":"Val Caron",
    "sg:classifiers":[
        {
            "category":"Building & Trades",
            "subcategory":"Plumbing",
            "type":"Services"
        }
    ],
    "sg:phone":"+1 705 673 8044",
    "sg:postcode":"P3N 1B2",
    "sg:province":"ON",
    "sg:tags":[
        "environmental",
        "ecological",
        "septic"
    ],
    "wof:name":"Herby Enterprises Ltd",
    "wof:placetype":"venue"
},
  "geometry": {"coordinates":[-81.031372,46.606873],"type":"Point"}
}