{
  "type": "Feature",
  "properties": {
    "addr:full":"431 Rue Des Capucines Sainte-Adele QC J8B 1W5",
    "addr:housenumber":"431",
    "addr:postcode":"j8b 1w5",
    "addr:street":"Rue Des Capucines Sainte-Adele",
    "iso:country":"CA",
    "sg:address":"431 Rue Des Capucines",
    "sg:city":"Sainte-Adele",
    "sg:classifiers":[
        {
            "category":"Health Services",
            "subcategory":"Nursing And Care Facility",
            "type":"Services"
        }
    ],
    "sg:phone":"+1 450 229 7877",
    "sg:postcode":"J8B 1W5",
    "sg:province":"QC",
    "sg:tags":[
        "home",
        "retirement",
        "community"
    ],
    "wof:name":"Residence Terrasses Capucines",
    "wof:placetype":"venue"
},
  "geometry": {"coordinates":[-74.1376876831,45.9553451538],"type":"Point"}
}