{
  "type": "Feature",
  "properties": {
    "addr:full":"3199 Dougall Ave Windsor ON N9E 1S5",
    "addr:housenumber":"3199",
    "addr:postcode":"n9e 1s5",
    "addr:street":"Dougall Ave",
    "iso:country":"CA",
    "sg:address":"3199 Dougall Ave",
    "sg:city":"Windsor",
    "sg:classifiers":[
        {
            "category":"Building & Trades",
            "subcategory":"Construction",
            "type":"Services"
        }
    ],
    "sg:phone":"+1 519 966 8100",
    "sg:postcode":"N9E 1S5",
    "sg:province":"ON",
    "sg:tags":[
        "home",
        "builder",
        "contractor"
    ],
    "wof:name":"Mastercraft Homes",
    "wof:placetype":"venue"
},
  "geometry": {"coordinates":[-83.01137542719999,42.268699646],"type":"Point"}
}