{
  "type": "Feature",
  "properties": {
    "addr:full":"1106 Queen St W Toronto ON M6J 1H9",
    "addr:housenumber":"1106",
    "addr:postcode":"m6j 1h9",
    "addr:street":"Queen St W",
    "iso:country":"CA",
    "sg:address":"1106 Queen St W",
    "sg:city":"Toronto",
    "sg:classifiers":[
        {
            "category":"Retail",
            "subcategory":"Car Wash",
            "type":"Services"
        }
    ],
    "sg:phone":"+1 416 530 0004",
    "sg:postcode":"M6J 1H9",
    "sg:province":"ON",
    "sg:tags":[
        "polishing",
        "washing"
    ],
    "wof:name":"Royal Car Wash",
    "wof:placetype":"venue"
},
  "geometry": {"coordinates":[-79.423027,43.643497],"type":"Point"}
}