{
  "type": "Feature",
  "properties": {
    "addr:full":"355 Pembina Ave E Winkler MB R6W 3N4",
    "addr:housenumber":"355",
    "addr:postcode":"r6w 3n4",
    "addr:street":"Pembina Ave E Winkler",
    "iso:country":"CA",
    "sg:address":"355 Pembina Ave E",
    "sg:city":"Winkler",
    "sg:classifiers":[
        {
            "category":"Building & Trades",
            "subcategory":"Construction",
            "type":"Services"
        }
    ],
    "sg:phone":"+1 204 325 4368",
    "sg:postcode":"R6W 3N4",
    "sg:province":"MB",
    "wof:name":"NU Steel Industries Ltd",
    "wof:placetype":"venue"
},
  "geometry": {"coordinates":[-97.923828,49.177937],"type":"Point"}
}