{
  "type": "Feature",
  "properties": {
    "addr:full":"8902 152 St Surrey BC V3R 4E4",
    "addr:housenumber":"8902",
    "addr:postcode":"v3r 4e4",
    "addr:street":"152 St",
    "iso:country":"CA",
    "sg:address":"8902 152 St",
    "sg:city":"Surrey",
    "sg:classifiers":[
        {
            "category":"Insurance",
            "subcategory":"Insurance Agent",
            "type":"Services"
        }
    ],
    "sg:phone":"+1 604 581 5566",
    "sg:postcode":"V3R 4E4",
    "sg:province":"BC",
    "wof:name":"Atkinson & Terry Insurance",
    "wof:placetype":"venue"
},
  "geometry": {"coordinates":[-122.80126190199999,49.1647071838],"type":"Point"}
}