{
  "type": "Feature",
  "properties": {
    "addr:full":"7 Rue Racine E Chicoutimi QC G7H 1P3",
    "addr:housenumber":"7",
    "addr:postcode":"g7h 1p3",
    "addr:street":"Rue Racine E",
    "iso:country":"CA",
    "sg:address":"7 Rue Racine E",
    "sg:city":"Chicoutimi",
    "sg:classifiers":[
        {
            "category":"Retail",
            "subcategory":"Auto Repair",
            "type":"Services"
        }
    ],
    "sg:phone":"+1 418 545 4952",
    "sg:postcode":"G7H 1P3",
    "sg:province":"QC",
    "sg:tags":[
        "repairing",
        "automobile",
        "wrecker"
    ],
    "wof:name":"Station Robert Gasse",
    "wof:placetype":"venue"
},
  "geometry": {"coordinates":[-71.068077,48.428154],"type":"Point"}
}