{
  "type": "Feature",
  "properties": {
    "addr:full":"129 Rue Barr Saint-Laurent QC H4T 1W6",
    "addr:housenumber":"129",
    "addr:postcode":"h4t 1w6",
    "addr:street":"Rue Barr",
    "iso:country":"CA",
    "sg:address":"129 Rue Barr",
    "sg:city":"Saint-Laurent",
    "sg:classifiers":[
        {
            "category":"Wholesale",
            "subcategory":"Non-durable Goods",
            "type":"Manufacturing & Wholesale Goods"
        }
    ],
    "sg:phone":"+1 514 345 1341",
    "sg:postcode":"H4T 1W6",
    "sg:province":"QC",
    "sg:tags":[
        "leather"
    ],
    "wof:name":"Lennox Charron Intl Inc",
    "wof:placetype":"venue"
},
  "geometry": {"coordinates":[-73.6917724609,45.4807014465],"type":"Point"}
}