{
  "type": "Feature",
  "properties": {
    "addr:full":"208 St Mary's River Dr Sault Ste Marie ON P6A 5V4",
    "addr:housenumber":"208",
    "addr:postcode":"p6a 5v4",
    "addr:street":"St Mary'S River Dr",
    "iso:country":"CA",
    "sg:address":"208 St Mary's River Dr",
    "sg:city":"Sault Ste Marie",
    "sg:classifiers":[
        {
            "category":"Restaurant",
            "type":"Food & Drink"
        }
    ],
    "sg:phone":"+1 705 945 6999",
    "sg:postcode":"P6A 5V4",
    "sg:province":"ON",
    "wof:name":"Bridge's Restaurant",
    "wof:placetype":"venue"
},
  "geometry": {"coordinates":[-84.252449,46.511875],"type":"Point"}
}