{
  "type": "Feature",
  "properties": {
    "iso:country":"CA",
    "sg:address":"37 Commo Rd",
    "sg:city":"Stewiacke",
    "sg:classifiers":[
        {
            "category":"Mining & Drilling",
            "type":"Manufacturing & Wholesale Goods"
        }
    ],
    "sg:phone":"+1 902 639 2343",
    "sg:postcode":"B0N 2J0",
    "sg:province":"NS",
    "sg:tags":[
        "diamond"
    ],
    "wof:name":"Logan Geotech Inc",
    "wof:placetype":"venue"
},
  "geometry": {"coordinates":[-63.356918335,45.1387634277],"type":"Point"}
}