{
  "type": "Feature",
  "properties": {
    "iso:country":"CA",
    "sg:address":"800 Franklin Blvd # A7",
    "sg:city":"Cambridge",
    "sg:classifiers":[
        {
            "category":"Personal",
            "subcategory":"Tanning Parlor",
            "type":"Services"
        }
    ],
    "sg:phone":"+1 519 622 0893",
    "sg:postcode":"N1R 7Z1",
    "sg:province":"ON",
    "sg:tags":[
        "salon"
    ],
    "wof:name":"Tan Unlimited",
    "wof:placetype":"venue"
},
  "geometry": {"coordinates":[-80.29907989500001,43.3803291321],"type":"Point"}
}