{
  "type": "Feature",
  "properties": {
    "addr:full":"Red Deer AB T4P 1M7",
    "addr:postcode":"t4p 1m7",
    "iso:country":"CA",
    "sg:city":"Red Deer",
    "sg:classifiers":[
        {
            "category":"Retail",
            "subcategory":"Veterinary Services",
            "type":"Services"
        }
    ],
    "sg:phone":"+1 403 343 7165",
    "sg:postcode":"T4P 1M7",
    "sg:province":"AB",
    "sg:tags":[
        "veterinarian"
    ],
    "wof:name":"Parkland Veterinary Hospital",
    "wof:placetype":"venue"
},
  "geometry": {"coordinates":[-113.813552856,52.3069992065],"type":"Point"}
}