{
  "type": "Feature",
  "properties": {
    "addr:full":"Thetford Mines QC G6G 2T9",
    "addr:postcode":"g6g 2t9",
    "iso:country":"CA",
    "sg:city":"Thetford Mines",
    "sg:classifiers":[
        {
            "category":"Building & Trades",
            "subcategory":"Plumbing",
            "type":"Services"
        }
    ],
    "sg:phone":"+1 418 334 0815",
    "sg:postcode":"G6G 2T9",
    "sg:province":"QC",
    "sg:tags":[
        "contractor"
    ],
    "wof:name":"Plomberie Lac As Inc",
    "wof:placetype":"venue"
},
  "geometry": {"coordinates":[-71.282875,46.104084],"type":"Point"}
}