{
  "type": "Feature",
  "properties": {
    "addr:full":"Niagara on the Lake ON L0S 1J0",
    "addr:postcode":"l0s 1j0",
    "iso:country":"CA",
    "sg:city":"Niagara on the Lake",
    "sg:classifiers":[
        {
            "category":"Freight",
            "type":"Transportation"
        }
    ],
    "sg:phone":"+1 905 262 0655",
    "sg:postcode":"L0S 1J0",
    "sg:province":"ON",
    "sg:tags":[
        "housewares",
        "broker",
        "customs"
    ],
    "wof:name":"Newport Customs Svc Inc",
    "wof:placetype":"venue"
},
  "geometry": {"coordinates":[-79.05819700000001,43.1796],"type":"Point"}
}