{
  "type": "Feature",
  "properties": {
    "addr:full":"New Westminster BC V3L 3A7",
    "addr:postcode":"v3l 3a7",
    "iso:country":"CA",
    "sg:city":"New Westminster",
    "sg:classifiers":[
        {
            "category":"Social Services",
            "type":"Services"
        }
    ],
    "sg:phone":"+1 604 525 9144",
    "sg:postcode":"V3L 3A7",
    "sg:province":"BC",
    "sg:tags":[
        "counselor",
        "marriage",
        "family"
    ],
    "wof:name":"Family Services of Greater Van",
    "wof:placetype":"venue"
},
  "geometry": {"coordinates":[-122.915382385,49.2094039917],"type":"Point"}
}