{
  "type": "Feature",
  "properties": {
    "addr:full":"Vancouver BC V6Z 2V2",
    "addr:postcode":"v6z 2v2",
    "iso:country":"CA",
    "sg:city":"Vancouver",
    "sg:classifiers":[
        {
            "category":"Shopping",
            "subcategory":"Computers & Home Electronics",
            "type":"Retail Goods"
        }
    ],
    "sg:phone":"+1 604 899 2064",
    "sg:postcode":"V6Z 2V2",
    "sg:province":"BC",
    "sg:tags":[
        "software"
    ],
    "wof:name":"Vortex Business Software Corp",
    "wof:placetype":"venue"
},
  "geometry": {"coordinates":[-123.12011,49.273022],"type":"Point"}
}