{
  "type": "Feature",
  "properties": {
    "iso:country":"CA",
    "sg:address":"590 Rue Notre-Dame",
    "sg:city":"Saint-Hugues",
    "sg:classifiers":[
        {
            "category":"Building & Trades",
            "subcategory":"Construction",
            "type":"Services"
        }
    ],
    "sg:phone":"+1 450 794 2409",
    "sg:postcode":"J0H 1N0",
    "sg:province":"QC",
    "sg:tags":[
        "excavating",
        "contractor"
    ],
    "wof:name":"Jean-Pierre Roy Excavation Inc",
    "wof:placetype":"venue"
},
  "geometry": {"coordinates":[-72.8623504639,45.796710968],"type":"Point"}
}