{
  "type": "Feature",
  "properties": {
    "addr:full":"7585 Duffs Rd Whitby ON L1M 1Z8",
    "addr:housenumber":"7585",
    "addr:postcode":"l1m 1z8",
    "addr:street":"Duffs Rd",
    "iso:country":"CA",
    "sg:address":"7585 Duffs Rd",
    "sg:city":"Whitby",
    "sg:classifiers":[
        {
            "category":"Wholesale",
            "subcategory":"Plants",
            "type":"Manufacturing & Wholesale Goods"
        }
    ],
    "sg:phone":"+1 905 655 4296",
    "sg:postcode":"L1M 1Z8",
    "sg:province":"ON",
    "wof:name":"Hotner Greenhouses",
    "wof:placetype":"venue"
},
  "geometry": {"coordinates":[-78.96459197999999,43.9810180664],"type":"Point"}
}