{
  "type": "Feature",
  "properties": {
    "iso:country":"CA",
    "sg:address":"2499 Boul Des Recollets",
    "sg:city":"Trois-Rivieres",
    "sg:classifiers":[
        {
            "category":"Building & Trades",
            "subcategory":"Construction",
            "type":"Services"
        }
    ],
    "sg:phone":"+1 819 378 2034",
    "sg:postcode":"G8Z 4G1",
    "sg:province":"QC",
    "sg:tags":[
        "tile",
        "dealer"
    ],
    "wof:name":"Ceramique Des Roches",
    "wof:placetype":"venue"
},
  "geometry": {"coordinates":[-72.578506,46.337559],"type":"Point"}
}