{
  "type": "Feature",
  "properties": {
    "addr:full":"Vancouver BC V6G 3G9",
    "addr:postcode":"v6g 3g9",
    "iso:country":"CA",
    "sg:city":"Vancouver",
    "sg:classifiers":[
        {
            "category":"Education",
            "subcategory":"Special Training",
            "type":"Public Place"
        }
    ],
    "sg:phone":"+1 604 331 0895",
    "sg:postcode":"V6G 3G9",
    "sg:province":"BC",
    "sg:tags":[
        "management"
    ],
    "wof:name":"Cascadian Consulting Group Inc",
    "wof:placetype":"venue"
},
  "geometry": {"coordinates":[-123.13314099999999,49.291573],"type":"Point"}
}