{
  "type": "Feature",
  "properties": {
    "addr:full":"4280 Main St Vancouver BC V5V 3P9",
    "addr:housenumber":"4280",
    "addr:postcode":"v5v 3p9",
    "addr:street":"Main St",
    "iso:country":"CA",
    "sg:address":"4280 Main St",
    "sg:city":"Vancouver",
    "sg:classifiers":[
        {
            "category":"Shopping",
            "subcategory":"Used Merchandise",
            "type":"Retail Goods"
        }
    ],
    "sg:phone":"+1 604 875 1434",
    "sg:postcode":"V5V 3P9",
    "sg:province":"BC",
    "sg:tags":[
        "antique"
    ],
    "wof:name":"Antique Market",
    "wof:placetype":"venue"
},
  "geometry": {"coordinates":[-123.100937,49.246773],"type":"Point"}
}