{
  "type": "Feature",
  "properties": {
    "addr:full":"810 Phillips St Portage LA Prairie MB R1N 3J9",
    "addr:housenumber":"810",
    "addr:postcode":"r1n 3j9",
    "addr:street":"Phillips St",
    "iso:country":"CA",
    "sg:address":"810 Phillips St",
    "sg:city":"Portage LA Prairie",
    "sg:classifiers":[
        {
            "category":"Professional",
            "subcategory":"Management & Consulting",
            "type":"Services"
        }
    ],
    "sg:phone":"+1 204 239 3150",
    "sg:postcode":"R1N 3J9",
    "sg:province":"MB",
    "sg:tags":[
        "food",
        "laboratory",
        "government"
    ],
    "wof:name":"Manitoba Food Development Ctr",
    "wof:placetype":"venue"
},
  "geometry": {"coordinates":[-98.27257537840001,49.9813652039],"type":"Point"}
}