{
  "type": "Feature",
  "properties": {
    "addr:full":"92 Boul Saint-Raymond Hull QC J8Y 1S7",
    "addr:housenumber":"92",
    "addr:postcode":"j8y 1s7",
    "addr:street":"Boul Saint-Raymond",
    "iso:country":"CA",
    "sg:address":"92 Boul Saint-Raymond",
    "sg:city":"Hull",
    "sg:classifiers":[
        {
            "category":"Health Services",
            "subcategory":"Hospital",
            "type":"Services"
        }
    ],
    "sg:phone":"+1 819 770 1622",
    "sg:postcode":"J8Y 1S7",
    "sg:province":"QC",
    "sg:tags":[
        "mental"
    ],
    "wof:name":"Envol Srt",
    "wof:placetype":"venue"
},
  "geometry": {"coordinates":[-75.74216461180001,45.4471054077],"type":"Point"}
}