{
  "type": "Feature",
  "properties": {
    "addr:full":"Saint-Jean-Chrysostome QC G6Z 2L2",
    "addr:postcode":"g6z 2l2",
    "iso:country":"CA",
    "sg:city":"Saint-Jean-Chrysostome",
    "sg:classifiers":[
        {
            "category":"Retail",
            "subcategory":"Auto Repair",
            "type":"Services"
        }
    ],
    "sg:phone":"+1 418 839 8585",
    "sg:postcode":"G6Z 2L2",
    "sg:province":"QC",
    "sg:tags":[
        "repairing",
        "automobile"
    ],
    "wof:name":"Garage Donald Belanger Inc",
    "wof:placetype":"venue"
},
  "geometry": {"coordinates":[-71.17961099999999,46.6982],"type":"Point"}
}