{
  "type": "Feature",
  "properties": {
    "iso:country":"CA",
    "sg:address":"33 Nora Crt",
    "sg:city":"Cambridge",
    "sg:classifiers":[
        {
            "category":"Building & Trades",
            "subcategory":"Construction",
            "type":"Services"
        }
    ],
    "sg:phone":"+1 519 658 5873",
    "sg:postcode":"N3C 3N1",
    "sg:province":"ON",
    "sg:tags":[
        "roofing",
        "contractor"
    ],
    "wof:name":"Britannica Roofing Inc",
    "wof:placetype":"venue"
},
  "geometry": {"coordinates":[-80.32150268549999,43.436794281],"type":"Point"}
}