{
  "type": "Feature",
  "properties": {
    "iso:country":"CA",
    "sg:address":"10006 101 St NW",
    "sg:city":"Edmonton",
    "sg:classifiers":[
        {
            "category":"Social Services",
            "subcategory":"Child Care",
            "type":"Services"
        }
    ],
    "sg:phone":"+1 780 498 5655",
    "sg:postcode":"T5J 0S1",
    "sg:province":"AB",
    "wof:name":"It's All About Kids",
    "wof:placetype":"venue"
},
  "geometry": {"coordinates":[-113.493942261,53.5397911072],"type":"Point"}
}