{
  "type": "Feature",
  "properties": {
    "addr:full":"674 Rue Victoria Sherbrooke QC J1H 3J5",
    "addr:housenumber":"674",
    "addr:postcode":"j1h 3j5",
    "addr:street":"Rue Victoria",
    "iso:country":"CA",
    "sg:address":"674 Rue Victoria",
    "sg:city":"Sherbrooke",
    "sg:classifiers":[
        {
            "category":"Personal",
            "subcategory":"Beauty Salon",
            "type":"Services"
        }
    ],
    "sg:phone":"+1 819 563 3211",
    "sg:postcode":"J1H 3J5",
    "sg:province":"QC",
    "wof:name":"Maison Louis Xv",
    "wof:placetype":"venue"
},
  "geometry": {"coordinates":[-71.905632,45.408615],"type":"Point"}
}