{
  "type": "Feature",
  "properties": {
    "addr:full":"2671 Eglinton Ave E Scarborough ON M1K 2S2",
    "addr:housenumber":"2671",
    "addr:postcode":"m1k 2s2",
    "addr:street":"Eglinton Ave E",
    "iso:country":"CA",
    "sg:address":"2671 Eglinton Ave E",
    "sg:city":"Scarborough",
    "sg:classifiers":[
        {
            "category":"Real Estate",
            "subcategory":"Real Estate Agent",
            "type":"Services"
        }
    ],
    "sg:phone":"+1 416 267 4601",
    "sg:postcode":"M1K 2S2",
    "sg:province":"ON",
    "wof:name":"William Mc Brien Ltd",
    "wof:placetype":"venue"
},
  "geometry": {"coordinates":[-79.2502670288,43.7361068726],"type":"Point"}
}