{
  "type": "Feature",
  "properties": {
    "iso:country":"CA",
    "sg:address":"4705 50 Ave",
    "sg:city":"Red Deer",
    "sg:classifiers":[
        {
            "category":"Home & Garden",
            "subcategory":"Carpets & Floor Coverings",
            "type":"Retail Goods"
        }
    ],
    "sg:phone":"+1 403 343 3128",
    "sg:postcode":"T4N 4A2",
    "sg:province":"AB",
    "sg:tags":[
        "dealer",
        "rug"
    ],
    "wof:name":"Sears Floor Covering Ctr",
    "wof:placetype":"venue"
},
  "geometry": {"coordinates":[-113.813995361,52.2669029236],"type":"Point"}
}