{
  "type": "Feature",
  "properties": {
    "iso:country":"CA",
    "sg:address":"915 Muskoka Beach Rd",
    "sg:city":"Gravenhurst",
    "sg:classifiers":[
        {
            "category":"Home & Garden",
            "subcategory":"Garden Supply",
            "type":"Retail Goods"
        }
    ],
    "sg:phone":"+1 705 687 8441",
    "sg:postcode":"P1P 1A5",
    "sg:province":"ON",
    "sg:tags":[
        "house",
        "bird",
        "feeder"
    ],
    "wof:name":"Chimney Facings Inc",
    "wof:placetype":"venue"
},
  "geometry": {"coordinates":[-79.37419128419999,44.9450683594],"type":"Point"}
}