{
  "type": "Feature",
  "properties": {
    "addr:full":"313 Main St Invermay SK S0A 1M0",
    "addr:housenumber":"313",
    "addr:postcode":"s0a 1m0",
    "addr:street":"Main St",
    "iso:country":"CA",
    "sg:address":"313 Main St",
    "sg:city":"Invermay",
    "sg:classifiers":[
        {
            "category":"Autos & Motor Vehicles",
            "subcategory":"Automobile Sales",
            "type":"Retail Goods"
        }
    ],
    "sg:phone":"+1 306 593 2177",
    "sg:postcode":"S0A 1M0",
    "sg:province":"SK",
    "sg:tags":[
        "car",
        "dealer"
    ],
    "wof:name":"Kam Auto Sales Ltd",
    "wof:placetype":"venue"
},
  "geometry": {"coordinates":[-103.15322113000001,51.8057937622],"type":"Point"}
}