{
  "type": "Feature",
  "properties": {
    "addr:full":"Rushoon NL A0E 2S0",
    "addr:postcode":"a0e 2s0",
    "iso:country":"CA",
    "sg:city":"Rushoon",
    "sg:classifiers":[
        {
            "category":"Government",
            "subcategory":"Office",
            "type":"Public Place"
        }
    ],
    "sg:phone":"+1 709 443 2572",
    "sg:postcode":"A0E 2S0",
    "sg:province":"NL",
    "sg:tags":[
        "village"
    ],
    "wof:name":"Rushoon Community Council",
    "wof:placetype":"venue"
},
  "geometry": {"coordinates":[-54.916203,47.367306],"type":"Point"}
}