{
  "type": "Feature",
  "properties": {
    "addr:full":"Red Deer AB T4N 2E9",
    "addr:postcode":"t4n 2e9",
    "iso:country":"CA",
    "sg:city":"Red Deer",
    "sg:classifiers":[
        {
            "category":"Professional",
            "subcategory":"Accounting & Tax Preparation",
            "type":"Services"
        }
    ],
    "sg:phone":"+1 403 346 8878",
    "sg:postcode":"T4N 2E9",
    "sg:province":"AB",
    "sg:tags":[
        "accountant"
    ],
    "wof:name":"Meyers Norris Penny",
    "wof:placetype":"venue"
},
  "geometry": {"coordinates":[-113.81220999999999,52.271984],"type":"Point"}
}