{
  "type": "Feature",
  "properties": {
    "addr:full":"32 North Park St Brantford ON N3R 4J6",
    "addr:housenumber":"32",
    "addr:postcode":"n3r 4j6",
    "addr:street":"North Park St",
    "iso:country":"CA",
    "sg:address":"32 North Park St",
    "sg:city":"Brantford",
    "sg:classifiers":[
        {
            "category":"Retail",
            "subcategory":"Car Wash",
            "type":"Services"
        }
    ],
    "sg:phone":"+1 519 752 3237",
    "sg:postcode":"N3R 4J6",
    "sg:province":"ON",
    "sg:tags":[
        "polishing",
        "washing"
    ],
    "wof:name":"Action Car Wash",
    "wof:placetype":"venue"
},
  "geometry": {"coordinates":[-80.2716598511,43.1551475525],"type":"Point"}
}