{
  "type": "Feature",
  "properties": {
    "addr:full":"3940 Moncton St Richmond BC V7E 3A6",
    "addr:housenumber":"3940",
    "addr:postcode":"v7e 3a6",
    "addr:street":"Moncton St",
    "iso:country":"CA",
    "sg:address":"3940 Moncton St",
    "sg:city":"Richmond",
    "sg:classifiers":[
        {
            "category":"Restaurant",
            "type":"Food & Drink"
        }
    ],
    "sg:phone":"+1 604 277 1812",
    "sg:postcode":"V7E 3A6",
    "sg:province":"BC",
    "wof:name":"Pat's Galley",
    "wof:placetype":"venue"
},
  "geometry": {"coordinates":[-123.18169403100001,49.1249732971],"type":"Point"}
}