{
  "type": "Feature",
  "properties": {
    "addr:full":"10023 88 Ave NW Edmonton AB T6E 2R6",
    "addr:housenumber":"10023",
    "addr:postcode":"t6e 2r6",
    "addr:street":"88 Ave Nw",
    "iso:country":"CA",
    "sg:address":"10023 88 Ave NW",
    "sg:city":"Edmonton",
    "sg:classifiers":[
        {
            "category":"Personal",
            "subcategory":"Beauty Salon",
            "type":"Services"
        }
    ],
    "sg:phone":"+1 780 433 7005",
    "sg:postcode":"T6E 2R6",
    "sg:province":"AB",
    "wof:name":"Ramona Le Blanc Salon",
    "wof:placetype":"venue"
},
  "geometry": {"coordinates":[-113.489395,53.523388],"type":"Point"}
}