{
  "type": "Feature",
  "properties": {
    "iso:country":"CA",
    "sg:address":"2810 Boul Pere-Lelievre",
    "sg:city":"Quebec",
    "sg:classifiers":[
        {
            "category":"Health Services",
            "subcategory":"Doctor",
            "type":"Services"
        }
    ],
    "sg:phone":"+1 418 688 8414",
    "sg:postcode":"G1P 2Y1",
    "sg:province":"QC",
    "sg:tags":[
        "clinic"
    ],
    "wof:name":"Clinique Medicale Duberger",
    "wof:placetype":"venue"
},
  "geometry": {"coordinates":[-71.3098373413,46.8127822876],"type":"Point"}
}