{
  "type": "Feature",
  "properties": {
    "addr:full":"4576 Yonge St #401 North York ON M2N 6N4",
    "addr:housenumber":"4576",
    "addr:postcode":"m2n 6n4",
    "addr:street":"Yonge St # 401",
    "iso:country":"CA",
    "sg:address":"4576 Yonge St #401",
    "sg:city":"North York",
    "sg:classifiers":[
        {
            "category":"Professional",
            "subcategory":"Accounting & Tax Preparation",
            "type":"Services"
        }
    ],
    "sg:phone":"+1 416 512 9077",
    "sg:postcode":"M2N 6N4",
    "sg:province":"ON",
    "sg:tags":[
        "consultant"
    ],
    "wof:name":"Hallmark Capital Corp",
    "wof:placetype":"venue"
},
  "geometry": {"coordinates":[-79.409744,43.756454],"type":"Point"}
}