{
  "type": "Feature",
  "properties": {
    "addr:full":"3000 Notre Dame Ave Winnipeg MB R3H 1B9",
    "addr:housenumber":"3000",
    "addr:postcode":"r3h 1b9",
    "addr:street":"Notre Dame Ave",
    "iso:country":"CA",
    "sg:address":"3000 Notre Dame Ave",
    "sg:city":"Winnipeg",
    "sg:classifiers":[
        {
            "category":"Building & Trades",
            "subcategory":"Construction",
            "type":"Services"
        }
    ],
    "sg:phone":"+1 204 694 7777",
    "sg:postcode":"R3H 1B9",
    "sg:province":"MB",
    "sg:tags":[
        "sandblasting"
    ],
    "wof:name":"Action Blast",
    "wof:placetype":"venue"
},
  "geometry": {"coordinates":[-97.21893300000001,49.916367],"type":"Point"}
}