{
  "type": "Feature",
  "properties": {
    "addr:full":"Val-Senneville QC J0Y 2P0",
    "addr:postcode":"j0y 2p0",
    "iso:country":"CA",
    "sg:city":"Val-Senneville",
    "sg:classifiers":[
        {
            "category":"Education",
            "subcategory":"Special Training",
            "type":"Public Place"
        }
    ],
    "sg:phone":"+1 819 824 5049",
    "sg:postcode":"J0Y 2P0",
    "sg:province":"QC",
    "sg:tags":[
        "school",
        "language"
    ],
    "wof:name":"Sur Mesure",
    "wof:placetype":"venue"
},
  "geometry": {"coordinates":[-73.9610443115,45.414604187],"type":"Point"}
}