{
  "type": "Feature",
  "properties": {
    "addr:full":"Port Robinson ON L0S 1K0",
    "addr:postcode":"l0s 1k0",
    "addr:street":"Port Robinson",
    "iso:country":"CA",
    "sg:city":"Port Robinson",
    "sg:classifiers":[
        {
            "category":"Wholesale",
            "subcategory":"Sporting Goods",
            "type":"Manufacturing & Wholesale Goods"
        }
    ],
    "sg:phone":"+1 905 384 0729",
    "sg:postcode":"L0S 1K0",
    "sg:province":"ON",
    "sg:tags":[
        "salon",
        "tanning"
    ],
    "wof:name":"Island Sun",
    "wof:placetype":"venue"
},
  "geometry": {"coordinates":[-79.208603,43.043148],"type":"Point"}
}