{
  "type": "Feature",
  "properties": {
    "addr:full":"474 W River Rd Hinton AB T7V 1X5",
    "addr:housenumber":"474",
    "addr:postcode":"t7v 1x5",
    "addr:street":"W River Rd",
    "iso:country":"CA",
    "sg:address":"474 W River Rd",
    "sg:city":"Hinton",
    "sg:classifiers":[
        {
            "category":"Freight",
            "type":"Transportation"
        }
    ],
    "sg:phone":"+1 780 865 4868",
    "sg:postcode":"T7V 1X5",
    "sg:province":"AB",
    "sg:tags":[
        "field",
        "oil",
        "trucking"
    ],
    "wof:name":"Dan Bailey Oilfield & Road",
    "wof:placetype":"venue"
},
  "geometry": {"coordinates":[-117.623093,53.391796],"type":"Point"}
}