{
  "type": "Feature",
  "properties": {
    "addr:full":"Pontypool ON L0A 1K0",
    "addr:postcode":"l0a 1k0",
    "iso:country":"CA",
    "sg:city":"Pontypool",
    "sg:classifiers":[
        {
            "category":"Freight",
            "type":"Transportation"
        }
    ],
    "sg:phone":"+1 705 277 3983",
    "sg:postcode":"L0A 1K0",
    "sg:province":"ON",
    "sg:tags":[
        "trucking"
    ],
    "wof:name":"Stewart Wood Transport Ltd",
    "wof:placetype":"venue"
},
  "geometry": {"coordinates":[-78.628265,44.099945],"type":"Point"}
}