{
  "type": "Feature",
  "properties": {
    "addr:full":"7089 Yonge St Thornhill ON L3T 2A7",
    "addr:housenumber":"7089",
    "addr:postcode":"l3t 2a7",
    "addr:street":"Yonge St",
    "iso:country":"CA",
    "sg:address":"7089 Yonge St",
    "sg:city":"Thornhill",
    "sg:classifiers":[
        {
            "category":"Retail",
            "subcategory":"Auto Rental",
            "type":"Services"
        }
    ],
    "sg:phone":"+1 905 731 4112",
    "sg:postcode":"L3T 2A7",
    "sg:province":"ON",
    "sg:tags":[
        "renting",
        "automobile"
    ],
    "wof:name":"Discount Car & Truck Rentals",
    "wof:placetype":"venue"
},
  "geometry": {"coordinates":[-79.4207,43.80069],"type":"Point"}
}