{
  "type": "Feature",
  "properties": {
    "addr:full":"405 Rue Marie-Anne E Montreal QC H2J 1Z9",
    "addr:housenumber":"405",
    "addr:postcode":"h2j 1z9",
    "addr:street":"Rue Marie-Anne E",
    "iso:country":"CA",
    "sg:address":"405 Rue Marie-Anne E",
    "sg:city":"Montreal",
    "sg:classifiers":[
        {
            "category":"Organizations",
            "subcategory":"Religious Organization",
            "type":"Services"
        }
    ],
    "sg:phone":"+1 514 288 4972",
    "sg:postcode":"H2J 1Z9",
    "sg:province":"QC",
    "sg:tags":[
        "church"
    ],
    "wof:name":"Eglise St Vladimir",
    "wof:placetype":"venue"
},
  "geometry": {"coordinates":[-73.58056640620001,45.5230636597],"type":"Point"}
}