{
  "type": "Feature",
  "properties": {
    "addr:full":"700 Main St S Sauble Beach ON N0H 2G0",
    "addr:housenumber":"700",
    "addr:postcode":"n0h 2g0",
    "addr:street":"Main St S Sauble Beach",
    "iso:country":"CA",
    "sg:address":"700 Main St S",
    "sg:city":"Sauble Beach",
    "sg:classifiers":[
        {
            "category":"Autos & Motor Vehicles",
            "subcategory":"Fuel & Gas Station",
            "type":"Retail Goods"
        }
    ],
    "sg:phone":"+1 519 422 2742",
    "sg:postcode":"N0H 2G0",
    "sg:province":"ON",
    "sg:tags":[
        "oil"
    ],
    "wof:name":"Sauble Beach Svc Ctr",
    "wof:placetype":"venue"
},
  "geometry": {"coordinates":[-81.25811767579999,44.6298408508],"type":"Point"}
}