{
  "type": "Feature",
  "properties": {
    "addr:full":"3163 Boul Des Sources Dollard-Des-Ormeaux QC H9B 1Z6",
    "addr:housenumber":"3163",
    "addr:postcode":"h9b 1z6",
    "addr:street":"Boul Des Sources",
    "iso:country":"CA",
    "sg:address":"3163 Boul Des Sources",
    "sg:city":"Dollard-Des-Ormeaux",
    "sg:classifiers":[
        {
            "category":"Home & Garden",
            "subcategory":"Household Appliances",
            "type":"Retail Goods"
        }
    ],
    "sg:phone":"+1 514 421 5395",
    "sg:postcode":"H9B 1Z6",
    "sg:province":"QC",
    "wof:name":"Corbeil Electromenagers",
    "wof:placetype":"venue"
},
  "geometry": {"coordinates":[-73.79521200000001,45.482754],"type":"Point"}
}