{
  "type": "Feature",
  "properties": {
    "addr:full":"128 Rainbow Rd Whitehorse YT Y1A 5K1",
    "addr:housenumber":"128",
    "addr:postcode":"y1a 5k1",
    "addr:street":"Rainbow Rd",
    "iso:country":"CA",
    "sg:address":"128 Rainbow Rd",
    "sg:city":"Whitehorse",
    "sg:classifiers":[
        {
            "category":"Building & Trades",
            "subcategory":"Cleaning & Sanitation",
            "type":"Services"
        }
    ],
    "sg:phone":"+1 867 668 2580",
    "sg:postcode":"Y1A 5K1",
    "sg:province":"YT",
    "sg:tags":[
        "janitor"
    ],
    "wof:name":"Crystal Services Window Clean",
    "wof:placetype":"venue"
},
  "geometry": {"coordinates":[-135.17132599999999,60.782856],"type":"Point"}
}