{
  "type": "Feature",
  "properties": {
    "addr:full":"228 Rte Principale Saint-Eusebe QC G0L 2Y0",
    "addr:housenumber":"228",
    "addr:postcode":"g0l 2y0",
    "addr:street":"Rte Principale",
    "iso:country":"CA",
    "sg:address":"228 Rte Principale",
    "sg:city":"Saint-Eusebe",
    "sg:classifiers":[
        {
            "category":"Education",
            "subcategory":"School",
            "type":"Public Place"
        }
    ],
    "sg:phone":"+1 418 899 2659",
    "sg:postcode":"G0L 2Y0",
    "sg:province":"QC",
    "wof:name":"Ecole St-Eusebe",
    "wof:placetype":"venue"
},
  "geometry": {"coordinates":[-68.908501,47.552097],"type":"Point"}
}