{
  "type": "Feature",
  "properties": {
    "addr:full":"1950 Boul Du Cure-Labelle Saint-Jerome QC J7Y 1S1",
    "addr:housenumber":"1950",
    "addr:postcode":"j7y 1s1",
    "addr:street":"Boul Du Cure-Labelle Saint-Jerome",
    "iso:country":"CA",
    "sg:address":"1950 Boul Du Cure-Labelle",
    "sg:city":"Saint-Jerome",
    "sg:classifiers":[
        {
            "category":"Shopping",
            "subcategory":"Music",
            "type":"Retail Goods"
        }
    ],
    "sg:phone":"+1 450 438 1944",
    "sg:postcode":"J7Y 1S1",
    "sg:province":"QC",
    "sg:tags":[
        "compact",
        "record",
        "disc",
        "tape"
    ],
    "wof:name":"Coin DE LA Musique",
    "wof:placetype":"venue"
},
  "geometry": {"coordinates":[-74.0089187622,45.7942886353],"type":"Point"}
}