{
  "type": "Feature",
  "properties": {
    "addr:full":"170 Boul Labelle Rosemere QC J7A 2H1",
    "addr:housenumber":"170",
    "addr:postcode":"j7a 2h1",
    "addr:street":"Boul Labelle",
    "iso:country":"CA",
    "sg:address":"170 Boul Labelle",
    "sg:city":"Rosemere",
    "sg:classifiers":[
        {
            "category":"Restaurant",
            "type":"Food & Drink"
        }
    ],
    "sg:phone":"+1 450 437 2840",
    "sg:postcode":"J7A 2H1",
    "sg:province":"QC",
    "wof:name":"Harvey's",
    "wof:placetype":"venue"
},
  "geometry": {"coordinates":[-73.8003082275,45.6226959229],"type":"Point"}
}