{
  "type": "Feature",
  "properties": {
    "addr:full":"710 Maple Ave Burlington ON L7S 1M6",
    "addr:housenumber":"710",
    "addr:postcode":"l7s 1m6",
    "addr:street":"Maple Ave",
    "iso:country":"CA",
    "sg:address":"710 Maple Ave",
    "sg:city":"Burlington",
    "sg:classifiers":[
        {
            "category":"Recreation",
            "type":"Entertainment"
        }
    ],
    "sg:phone":"+1 905 637 5774",
    "sg:postcode":"L7S 1M6",
    "sg:province":"ON",
    "sg:tags":[
        "instruction",
        "gymnastic"
    ],
    "wof:name":"Burlington Gymnastics Club",
    "wof:placetype":"venue"
},
  "geometry": {"coordinates":[-79.8138046265,43.3237075806],"type":"Point"}
}