{
  "type": "Feature",
  "properties": {
    "addr:full":"Concord ON L4K 2Y2",
    "addr:postcode":"l4k 2y2",
    "iso:country":"CA",
    "sg:city":"Concord",
    "sg:classifiers":[
        {
            "category":"Banks & Credit Unions",
            "subcategory":"Bank",
            "type":"Services"
        }
    ],
    "sg:phone":"+1 905 761 9373",
    "sg:postcode":"L4K 2Y2",
    "sg:province":"ON",
    "sg:tags":[
        "loan",
        "real estate"
    ],
    "wof:name":"Citi Financial Canada Inc",
    "wof:placetype":"venue"
},
  "geometry": {"coordinates":[-79.5260925293,43.7746276855],"type":"Point"}
}