{
  "type": "Feature",
  "properties": {
    "addr:full":"Port Rexton NL A0C 2H0",
    "addr:postcode":"a0c 2h0",
    "addr:street":"Port",
    "iso:country":"CA",
    "sg:city":"Port Rexton",
    "sg:classifiers":[
        {
            "category":"Insurance",
            "subcategory":"Insurance Agent",
            "type":"Services"
        }
    ],
    "sg:phone":"+1 709 464 3267",
    "sg:postcode":"A0C 2H0",
    "sg:province":"NL",
    "wof:name":"Wedgewood Insurance Ltd",
    "wof:placetype":"venue"
},
  "geometry": {"coordinates":[-53.325588,48.396557],"type":"Point"}
}