{
  "type": "Feature",
  "properties": {
    "addr:full":"202 28 Ave NE Calgary AB T2E 2B1",
    "addr:housenumber":"202",
    "addr:postcode":"t2e 2b1",
    "addr:street":"28 Ave Ne",
    "iso:country":"CA",
    "sg:address":"202 28 Ave NE",
    "sg:city":"Calgary",
    "sg:classifiers":[
        {
            "category":"Social Services",
            "subcategory":"Child Care",
            "type":"Services"
        }
    ],
    "sg:phone":"+1 403 277 3888",
    "sg:postcode":"T2E 2B1",
    "sg:province":"AB",
    "sg:tags":[
        "kindergarten",
        "academic",
        "school",
        "montessori"
    ],
    "wof:name":"St Paul's Pre-School",
    "wof:placetype":"venue"
},
  "geometry": {"coordinates":[-114.059624,51.077972],"type":"Point"}
}