{
  "type": "Feature",
  "properties": {
    "addr:full":"82 Appian Way Dartmouth NS B2X 3M4",
    "addr:housenumber":"82",
    "addr:postcode":"b2x 3m4",
    "addr:street":"Appian Way",
    "iso:country":"CA",
    "sg:address":"82 Appian Way",
    "sg:city":"Dartmouth",
    "sg:classifiers":[
        {
            "category":"Real Estate",
            "subcategory":"Architect",
            "type":"Services"
        }
    ],
    "sg:phone":"+1 902 462 7777",
    "sg:postcode":"B2X 3M4",
    "sg:province":"NS",
    "wof:name":"Richard Earle Architects Ltd",
    "wof:placetype":"venue"
},
  "geometry": {"coordinates":[-63.545212,44.703266],"type":"Point"}
}