{
  "type": "Feature",
  "properties": {
    "addr:full":"1 Hampton Rd Rothesay NB E2E 5K8",
    "addr:housenumber":"1",
    "addr:postcode":"e2e 5k8",
    "addr:street":"Hampton Rd",
    "iso:country":"CA",
    "sg:address":"1 Hampton Rd",
    "sg:city":"Rothesay",
    "sg:classifiers":[
        {
            "category":"Health Services",
            "subcategory":"Doctor",
            "type":"Services"
        }
    ],
    "sg:phone":"+1 506 849 5050",
    "sg:postcode":"E2E 5K8",
    "sg:province":"NB",
    "sg:tags":[
        "physician",
        "surgeon"
    ],
    "wof:name":"College of Physicians",
    "wof:placetype":"venue"
},
  "geometry": {"coordinates":[-65.9968414307,45.387348175],"type":"Point"}
}