{
  "type": "Feature",
  "properties": {
    "iso:country":"CA",
    "sg:address":"2762 Honey Harbour Rd",
    "sg:city":"Honey Harbour",
    "sg:classifiers":[
        {
            "category":"Recreation",
            "subcategory":"Marina",
            "type":"Entertainment"
        }
    ],
    "sg:phone":"+1 705 756 1662",
    "sg:postcode":"P0E 1E0",
    "sg:province":"ON",
    "sg:tags":[
        "dealer",
        "boat",
        "sales"
    ],
    "wof:name":"Jim Langley Marine",
    "wof:placetype":"venue"
},
  "geometry": {"coordinates":[-79.817237854,44.8707923889],"type":"Point"}
}