{
  "type": "Feature",
  "properties": {
    "addr:full":"158 Rue Nicholson Salaberry-DE-Valleyfield QC J6T 4N7",
    "addr:housenumber":"158",
    "addr:postcode":"j6t 4n7",
    "addr:street":"Rue Nicholson",
    "iso:country":"CA",
    "sg:address":"158 Rue Nicholson",
    "sg:city":"Salaberry-DE-Valleyfield",
    "sg:classifiers":[
        {
            "category":"Shopping",
            "subcategory":"Bicycles & Sporting Goods",
            "type":"Retail Goods"
        }
    ],
    "sg:phone":"+1 450 373 1450",
    "sg:postcode":"J6T 4N7",
    "sg:province":"QC",
    "wof:name":"Proshop L'Echappee",
    "wof:placetype":"venue"
},
  "geometry": {"coordinates":[-74.1288070679,45.2514533997],"type":"Point"}
}