{
  "type": "Feature",
  "properties": {
    "addr:full":"660 Rue Notre-Dame Saint-Sulpice QC J5W 3X2",
    "addr:housenumber":"660",
    "addr:postcode":"j5w 3x2",
    "addr:street":"Rue Notre-Dame",
    "iso:country":"CA",
    "sg:address":"660 Rue Notre-Dame",
    "sg:city":"Saint-Sulpice",
    "sg:classifiers":[
        {
            "category":"Restaurant",
            "type":"Food & Drink"
        }
    ],
    "sg:phone":"+1 450 589 6903",
    "sg:postcode":"J5W 3X2",
    "sg:province":"QC",
    "wof:name":"Restaurant LA Petite Marmite",
    "wof:placetype":"venue"
},
  "geometry": {"coordinates":[-73.37822723390001,45.8034172058],"type":"Point"}
}