{
  "type": "Feature",
  "properties": {
    "addr:full":"227 6E Av Dolbeau-Mistassini QC G8L 1X5",
    "addr:housenumber":"227",
    "addr:postcode":"g8l 1x5",
    "addr:street":"6E Av Dolbeau-Mistassini",
    "iso:country":"CA",
    "sg:address":"227 6E Av",
    "sg:city":"Dolbeau-Mistassini",
    "sg:classifiers":[
        {
            "category":"Wholesale",
            "subcategory":"Meat",
            "type":"Manufacturing & Wholesale Goods"
        }
    ],
    "sg:phone":"+1 418 276 4888",
    "sg:postcode":"G8L 1X5",
    "sg:province":"QC",
    "sg:tags":[
        "butchering"
    ],
    "wof:name":"Boucherie Francois Nadeau Enr",
    "wof:placetype":"venue"
},
  "geometry": {"coordinates":[-72.22985799999999,48.878468],"type":"Point"}
}