{
  "type": "Feature",
  "properties": {
    "iso:country":"CA",
    "sg:address":"289 Wellington St E",
    "sg:city":"Aurora",
    "sg:classifiers":[
        {
            "category":"Home & Garden",
            "subcategory":"Hardware",
            "type":"Retail Goods"
        }
    ],
    "sg:phone":"+1 905 727 4751",
    "sg:postcode":"L4G 6H6",
    "sg:province":"ON",
    "wof:name":"Aurora Home Hardware Ctr",
    "wof:placetype":"venue"
},
  "geometry": {"coordinates":[-79.451828,44.003006],"type":"Point"}
}