{
  "type": "Feature",
  "properties": {
    "addr:full":"432 Ontario St Newmarket ON L3Y 2K4",
    "addr:housenumber":"432",
    "addr:postcode":"l3y 2k4",
    "addr:street":"Ontario St",
    "iso:country":"CA",
    "sg:address":"432 Ontario St",
    "sg:city":"Newmarket",
    "sg:classifiers":[
        {
            "category":"Organizations",
            "subcategory":"Religious Organization",
            "type":"Services"
        }
    ],
    "sg:phone":"+1 905 898 4137",
    "sg:postcode":"L3Y 2K4",
    "sg:province":"ON",
    "sg:tags":[
        "church"
    ],
    "wof:name":"St John Crystosom Church",
    "wof:placetype":"venue"
},
  "geometry": {"coordinates":[-79.4600906372,44.057258606],"type":"Point"}
}