{
  "type": "Feature",
  "properties": {
    "iso:country":"CA",
    "sg:city":"Saint-Pie",
    "sg:classifiers":[
        {
            "category":"Manufacturing",
            "subcategory":"Furniture",
            "type":"Manufacturing & Wholesale Goods"
        }
    ],
    "sg:phone":"+1 450 772 2298",
    "sg:postcode":"J0H 1W0",
    "sg:province":"QC",
    "wof:name":"Creation Meubles Ac Inc",
    "wof:placetype":"venue"
},
  "geometry": {"coordinates":[-72.9003067017,45.5009307861],"type":"Point"}
}