{
  "type": "Feature",
  "properties": {
    "iso:country":"CA",
    "sg:city":"Mississauga",
    "sg:classifiers":[
        {
            "category":"Travel",
            "subcategory":"Travel Agent",
            "type":"Entertainment"
        }
    ],
    "sg:phone":"+1 905 238 2999",
    "sg:postcode":"L4W 5G6",
    "sg:province":"ON",
    "sg:tags":[
        "information",
        "tourist"
    ],
    "wof:name":"South American Tours Intl Inc",
    "wof:placetype":"venue"
},
  "geometry": {"coordinates":[-79.6140823364,43.6328887939],"type":"Point"}
}