{
  "type": "Feature",
  "properties": {
    "iso:country":"CA",
    "sg:address":"10 Elgin St",
    "sg:city":"St Thomas",
    "sg:classifiers":[
        {
            "category":"Retail",
            "subcategory":"Animal Services",
            "type":"Services"
        }
    ],
    "sg:phone":"+1 519 633 0204",
    "sg:postcode":"N5R 3L6",
    "sg:province":"ON",
    "sg:tags":[
        "pet",
        "grooming",
        "washing"
    ],
    "wof:name":"Yuppy Puppy",
    "wof:placetype":"venue"
},
  "geometry": {"coordinates":[-81.1985778809,42.7785873413],"type":"Point"}
}