{
  "type": "Feature",
  "properties": {
    "addr:full":"1350 16th St E Owen Sound ON N4K 6N7",
    "addr:housenumber":"1350",
    "addr:postcode":"n4k 6n7",
    "addr:street":"16Th St E",
    "iso:country":"CA",
    "sg:address":"1350 16th St E",
    "sg:city":"Owen Sound",
    "sg:classifiers":[
        {
            "category":"Personal",
            "subcategory":"Beauty Salon",
            "type":"Services"
        }
    ],
    "sg:phone":"+1 519 372 1616",
    "sg:postcode":"N4K 6N7",
    "sg:province":"ON",
    "wof:name":"Mastercut",
    "wof:placetype":"venue"
},
  "geometry": {"coordinates":[-80.92166137700001,44.5743026733],"type":"Point"}
}