{
  "type": "Feature",
  "properties": {
    "addr:full":"4309 Rue Hogan Montreal QC H2H 2N2",
    "addr:housenumber":"4309",
    "addr:postcode":"h2h 2n2",
    "addr:street":"Rue Hogan",
    "iso:country":"CA",
    "sg:address":"4309 Rue Hogan",
    "sg:city":"Montreal",
    "sg:classifiers":[
        {
            "category":"Manufacturing",
            "subcategory":"Paper Products",
            "type":"Manufacturing & Wholesale Goods"
        }
    ],
    "sg:phone":"+1 514 524 0742",
    "sg:postcode":"H2H 2N2",
    "sg:province":"QC",
    "sg:tags":[
        "printer"
    ],
    "wof:name":"Imprimerie Groupe Litho Inc",
    "wof:placetype":"venue"
},
  "geometry": {"coordinates":[-73.563919,45.539276],"type":"Point"}
}