{
  "type": "Feature",
  "properties": {
    "addr:full":"237 Barton St E # 704 Hamilton ON L8L 2X2",
    "addr:housenumber":"237;704",
    "addr:postcode":"l8l 2x2",
    "addr:street":"Barton St E #",
    "iso:country":"CA",
    "sg:address":"237 Barton St E # 704",
    "sg:city":"Hamilton",
    "sg:classifiers":[
        {
            "category":"Health Services",
            "subcategory":"Doctor",
            "type":"Services"
        }
    ],
    "sg:phone":"+1 905 522 0175",
    "sg:postcode":"L8L 2X2",
    "sg:province":"ON",
    "sg:tags":[
        "physician",
        "surgeon"
    ],
    "wof:name":"Lamy, Andre MD",
    "wof:placetype":"venue"
},
  "geometry": {"coordinates":[-79.85437,43.261387],"type":"Point"}
}