{
  "type": "Feature",
  "properties": {
    "addr:full":"170 Mill St Angus ON L0M 1B2",
    "addr:housenumber":"170",
    "addr:postcode":"l0m 1b2",
    "addr:street":"Mill St",
    "iso:country":"CA",
    "sg:address":"170 Mill St",
    "sg:city":"Angus",
    "sg:classifiers":[
        {
            "category":"Restaurant",
            "type":"Food & Drink"
        }
    ],
    "sg:phone":"+1 705 424 5584",
    "sg:postcode":"L0M 1B2",
    "sg:province":"ON",
    "sg:tags":[
        "caterer"
    ],
    "wof:name":"Kfc",
    "wof:placetype":"venue"
},
  "geometry": {"coordinates":[-79.887794,44.323963],"type":"Point"}
}