{
  "type": "Feature",
  "properties": {
    "addr:full":"15 Broadway St S Raymond AB T0K 2S0",
    "addr:housenumber":"15",
    "addr:postcode":"t0k 2s0",
    "addr:street":"Broadway St S Raymond",
    "iso:country":"CA",
    "sg:address":"15 Broadway St S",
    "sg:city":"Raymond",
    "sg:classifiers":[
        {
            "category":"Organizations",
            "subcategory":"Religious Organization",
            "type":"Services"
        }
    ],
    "sg:phone":"+1 403 752 3521",
    "sg:postcode":"T0K 2S0",
    "sg:province":"AB",
    "sg:tags":[
        "church"
    ],
    "wof:name":"Church of Jesus Christ of Lds",
    "wof:placetype":"venue"
},
  "geometry": {"coordinates":[-112.662010193,49.4608039856],"type":"Point"}
}