{
  "type": "Feature",
  "properties": {
    "addr:full":"733 Colborne St Brantford ON N3S 3R9",
    "addr:housenumber":"733",
    "addr:postcode":"n3s 3r9",
    "addr:street":"Colborne St",
    "iso:country":"CA",
    "sg:address":"733 Colborne St",
    "sg:city":"Brantford",
    "sg:classifiers":[
        {
            "category":"Travel",
            "subcategory":"Hotels & Motels",
            "type":"Entertainment"
        }
    ],
    "sg:phone":"+1 519 752 7013",
    "sg:postcode":"N3S 3R9",
    "sg:province":"ON",
    "sg:tags":[
        "breakfast",
        "accommodation",
        "bed"
    ],
    "wof:name":"Ava's Bed & Breakfast",
    "wof:placetype":"venue"
},
  "geometry": {"coordinates":[-80.23149100000001,43.142498],"type":"Point"}
}