{
  "type": "Feature",
  "properties": {
    "iso:country":"CA",
    "sg:address":"480 Kings Rd",
    "sg:city":"Sydney",
    "sg:classifiers":[
        {
            "category":"Travel",
            "subcategory":"Hotels & Motels",
            "type":"Entertainment"
        }
    ],
    "sg:phone":"+1 902 539 6750",
    "sg:postcode":"B1S 1A8",
    "sg:province":"NS",
    "wof:name":"Days Inn",
    "wof:placetype":"venue"
},
  "geometry": {"coordinates":[-60.2026939392,46.122303009],"type":"Point"}
}