{
  "type": "Feature",
  "properties": {
    "addr:full":"19677 Boul Gouin O Pierrefonds QC H9K 1B3",
    "addr:housenumber":"19677",
    "addr:postcode":"h9k 1b3",
    "addr:street":"Boul Gouin O",
    "iso:country":"CA",
    "sg:address":"19677 Boul Gouin O",
    "sg:city":"Pierrefonds",
    "sg:classifiers":[
        {
            "category":"Retail",
            "subcategory":"Auto Repair",
            "type":"Services"
        }
    ],
    "sg:phone":"+1 514 626 3083",
    "sg:postcode":"H9K 1B3",
    "sg:province":"QC",
    "sg:tags":[
        "body",
        "automobile",
        "painting"
    ],
    "wof:name":"A Rouleau Antirouille",
    "wof:placetype":"venue"
},
  "geometry": {"coordinates":[-73.913872,45.460739],"type":"Point"}
}