{
  "type": "Feature",
  "properties": {
    "addr:full":"PO Box 100 Kenosee Lake SK S0C 2S0",
    "addr:housenumber":"po",
    "addr:postcode":"s0c 2s0",
    "addr:street":"Box 100",
    "iso:country":"CA",
    "sg:address":"PO Box 100",
    "sg:city":"Kenosee Lake",
    "sg:classifiers":[
        {
            "category":"Travel",
            "subcategory":"Hotels & Motels",
            "type":"Entertainment"
        }
    ],
    "sg:phone":"+1 306 577 2110",
    "sg:postcode":"S0C 2S0",
    "sg:province":"SK",
    "sg:tags":[
        "resort"
    ],
    "wof:name":"Kenosee Cabins",
    "wof:placetype":"venue"
},
  "geometry": {"coordinates":[-102.28563690199999,49.8320007324],"type":"Point"}
}