{
  "type": "Feature",
  "properties": {
    "addr:full":"8765 Cariboo Pl Burnaby BC V3N 4T2",
    "addr:housenumber":"8765",
    "addr:postcode":"v3n 4t2",
    "addr:street":"Cariboo Pl",
    "iso:country":"CA",
    "sg:address":"8765 Cariboo Pl",
    "sg:city":"Burnaby",
    "sg:classifiers":[
        {
            "category":"Travel",
            "subcategory":"Hotels & Motels",
            "type":"Entertainment"
        }
    ],
    "sg:phone":"+1 604 420 1722",
    "sg:postcode":"V3N 4T2",
    "sg:province":"BC",
    "sg:tags":[
        "resort"
    ],
    "wof:name":"Burnaby Cariboo Rv Park Inc",
    "wof:placetype":"venue"
},
  "geometry": {"coordinates":[-122.91319300000001,49.248505],"type":"Point"}
}