{
  "type": "Feature",
  "properties": {
    "addr:full":"1650 Allee Du Marche Saint-Hyacinthe QC J2S 8E4",
    "addr:housenumber":"1650",
    "addr:postcode":"j2s 8e4",
    "addr:street":"Allee Du Marche",
    "iso:country":"CA",
    "sg:address":"1650 Allee Du Marche",
    "sg:city":"Saint-Hyacinthe",
    "sg:classifiers":[
        {
            "category":"Shopping",
            "subcategory":"Clothing, Apparel, & Fashions",
            "type":"Retail Goods"
        }
    ],
    "sg:phone":"+1 450 773 0986",
    "sg:postcode":"J2S 8E4",
    "sg:province":"QC",
    "sg:tags":[
        "infant",
        "wear",
        "boutique"
    ],
    "wof:name":"Boutique Fan-Fan Dodo",
    "wof:placetype":"venue"
},
  "geometry": {"coordinates":[-72.9460601807,45.6237983704],"type":"Point"}
}