{
  "type": "Feature",
  "properties": {
    "iso:country":"CA",
    "sg:city":"Edmonton",
    "sg:classifiers":[
        {
            "category":"Wholesale",
            "subcategory":"Construction Materials",
            "type":"Manufacturing & Wholesale Goods"
        }
    ],
    "sg:phone":"+1 780 444 7137",
    "sg:postcode":"T5P 4P4",
    "sg:province":"AB",
    "sg:tags":[
        "pallet",
        "skid"
    ],
    "wof:name":"Fortress Plastics Ltd",
    "wof:placetype":"venue"
},
  "geometry": {"coordinates":[-113.612548828,53.5476570129],"type":"Point"}
}