{
  "type": "Feature",
  "properties": {
    "addr:full":"Baie-Comeau QC G5C 1C5",
    "addr:postcode":"g5c 1c5",
    "iso:country":"CA",
    "sg:city":"Baie-Comeau",
    "sg:classifiers":[
        {
            "category":"Professional",
            "subcategory":"Management & Consulting",
            "type":"Services"
        }
    ],
    "sg:phone":"+1 418 589 5774",
    "sg:postcode":"G5C 1C5",
    "sg:province":"QC",
    "sg:tags":[
        "consultant",
        "recreation",
        "program"
    ],
    "wof:name":"Loisir & Sport Cote-Nord",
    "wof:placetype":"venue"
},
  "geometry": {"coordinates":[-68.25664500000001,49.200474],"type":"Point"}
}