{
  "type": "Feature",
  "properties": {
    "addr:full":"Abbotsford BC V2S 7M1",
    "addr:postcode":"v2s 7m1",
    "iso:country":"CA",
    "sg:city":"Abbotsford",
    "sg:classifiers":[
        {
            "category":"Professional",
            "subcategory":"Art Services",
            "type":"Services"
        }
    ],
    "sg:phone":"+1 604 850 2777",
    "sg:postcode":"V2S 7M1",
    "sg:province":"BC",
    "sg:tags":[
        "graphic",
        "printer",
        "designer"
    ],
    "wof:name":"Abbotsford Printing Inc",
    "wof:placetype":"venue"
},
  "geometry": {"coordinates":[-122.27288799999999,49.011696],"type":"Point"}
}