{
  "type": "Feature",
  "properties": {
    "addr:full":"310 Wellington St St Thomas ON N5R 2T1",
    "addr:housenumber":"310",
    "addr:postcode":"n5r 2t1",
    "addr:street":"Wellington St",
    "iso:country":"CA",
    "sg:address":"310 Wellington St",
    "sg:city":"St Thomas",
    "sg:classifiers":[
        {
            "category":"Shopping",
            "type":"Retail Goods"
        }
    ],
    "sg:phone":"+1 519 633 9955",
    "sg:postcode":"N5R 2T1",
    "sg:province":"ON",
    "sg:tags":[
        "wheel",
        "chair",
        "scooter"
    ],
    "wof:name":"Jewal International Inc",
    "wof:placetype":"venue"
},
  "geometry": {"coordinates":[-81.175217,42.774792],"type":"Point"}
}