{
  "type": "Feature",
  "properties": {
    "addr:full":"Victoria BC V9A 7N6",
    "addr:postcode":"v9a 7n6",
    "iso:country":"CA",
    "sg:city":"Victoria",
    "sg:classifiers":[
        {
            "category":"Health Services",
            "subcategory":"Doctor",
            "type":"Services"
        }
    ],
    "sg:phone":"+1 250 381 0028",
    "sg:postcode":"V9A 7N6",
    "sg:province":"BC",
    "sg:tags":[
        "dentist"
    ],
    "wof:name":"Dubois, Marie Nicol DDS",
    "wof:placetype":"venue"
},
  "geometry": {"coordinates":[-123.38125599999999,48.43261],"type":"Point"}
}