{
  "type": "Feature",
  "properties": {
    "iso:country":"CA",
    "sg:address":"158 Hanwell Rd",
    "sg:city":"Fredericton",
    "sg:classifiers":[
        {
            "category":"Real Estate",
            "subcategory":"Real Estate Operator",
            "type":"Services"
        }
    ],
    "sg:phone":"+1 506 452 1320",
    "sg:postcode":"E3B 9K7",
    "sg:province":"NB",
    "sg:tags":[
        "apartment"
    ],
    "wof:name":"Sunshine Terrace",
    "wof:placetype":"venue"
},
  "geometry": {"coordinates":[-66.6684417725,45.9607391357],"type":"Point"}
}