{
  "type": "Feature",
  "properties": {
    "addr:full":"Saskatoon SK S7N 3R3",
    "addr:postcode":"s7n 3r3",
    "iso:country":"CA",
    "sg:city":"Saskatoon",
    "sg:classifiers":[
        {
            "category":"Professional",
            "subcategory":"Engineering",
            "type":"Services"
        }
    ],
    "sg:phone":"+1 306 244 1303",
    "sg:postcode":"S7N 3R3",
    "sg:province":"SK",
    "sg:tags":[
        "engineer"
    ],
    "wof:name":"Ritenburg & Assoc Ltd",
    "wof:placetype":"venue"
},
  "geometry": {"coordinates":[-106.625778,52.142628],"type":"Point"}
}