{
  "type": "Feature",
  "properties": {
    "addr:full":"113 Leith St Thunder Bay ON P7C 1M7",
    "addr:housenumber":"113",
    "addr:postcode":"p7c 1m7",
    "addr:street":"Leith St",
    "iso:country":"CA",
    "sg:address":"113 Leith St",
    "sg:city":"Thunder Bay",
    "sg:classifiers":[
        {
            "category":"Taxi",
            "type":"Transportation"
        }
    ],
    "sg:phone":"+1 807 623 3423",
    "sg:postcode":"P7C 1M7",
    "sg:province":"ON",
    "sg:tags":[
        "delivery",
        "taxicab"
    ],
    "wof:name":"Lacey's Diamond Taxi",
    "wof:placetype":"venue"
},
  "geometry": {"coordinates":[-89.24211120610001,48.3859901428],"type":"Point"}
}