{
  "type": "Feature",
  "properties": {
    "addr:full":"234 Davenport Rd Toronto ON M5R 1J6",
    "addr:housenumber":"234",
    "addr:postcode":"m5r 1j6",
    "addr:street":"Davenport Rd",
    "iso:country":"CA",
    "sg:address":"234 Davenport Rd",
    "sg:city":"Toronto",
    "sg:classifiers":[
        {
            "category":"Professional",
            "subcategory":"Business Services",
            "type":"Services"
        }
    ],
    "sg:phone":"+1 416 928 2067",
    "sg:postcode":"M5R 1J6",
    "sg:province":"ON",
    "sg:tags":[
        "interior",
        "consultant",
        "design",
        "decorator"
    ],
    "wof:name":"Gluckstein Design Planning Inc",
    "wof:placetype":"venue"
},
  "geometry": {"coordinates":[-79.39785766599999,43.6746177673],"type":"Point"}
}