{
  "type": "Feature",
  "properties": {
    "addr:full":"10316 Jasper Ave NW Edmonton AB T5J 1Y7",
    "addr:housenumber":"10316",
    "addr:postcode":"t5j 1y7",
    "addr:street":"Jasper Ave Nw",
    "iso:country":"CA",
    "sg:address":"10316 Jasper Ave NW",
    "sg:city":"Edmonton",
    "sg:classifiers":[
        {
            "category":"Shopping",
            "subcategory":"Clothing, Apparel, & Fashions",
            "type":"Retail Goods"
        }
    ],
    "sg:phone":"+1 780 424 6335",
    "sg:postcode":"T5J 1Y7",
    "sg:province":"AB",
    "sg:tags":[
        "shop",
        "bridal"
    ],
    "wof:name":"Career Girl Bridal",
    "wof:placetype":"venue"
},
  "geometry": {"coordinates":[-113.497840881,53.5411567688],"type":"Point"}
}