{
  "type": "Feature",
  "properties": {
    "iso:country":"CA",
    "sg:address":"1175 Av Bernard",
    "sg:city":"Outremont",
    "sg:classifiers":[
        {
            "category":"Professional",
            "subcategory":"Accounting & Tax Preparation",
            "type":"Services"
        }
    ],
    "sg:phone":"+1 514 278 7557",
    "sg:postcode":"H2V 1V5",
    "sg:province":"QC",
    "sg:tags":[
        "accountant"
    ],
    "wof:name":"Rochette, Michel",
    "wof:placetype":"venue"
},
  "geometry": {"coordinates":[-73.608238,45.520916],"type":"Point"}
}