{
  "type": "Feature",
  "properties": {
    "addr:full":"4 Grandlea Cres Markham ON L3S 3V3",
    "addr:housenumber":"4",
    "addr:postcode":"l3s 3v3",
    "addr:street":"Grandlea Cres",
    "iso:country":"CA",
    "sg:address":"4 Grandlea Cres",
    "sg:city":"Markham",
    "sg:classifiers":[
        {
            "category":"Wholesale",
            "subcategory":"Non-durable Goods",
            "type":"Manufacturing & Wholesale Goods"
        }
    ],
    "sg:phone":"+1 905 201 6120",
    "sg:postcode":"L3S 3V3",
    "sg:province":"ON",
    "sg:tags":[
        "badge"
    ],
    "wof:name":"Romic Worldwide",
    "wof:placetype":"venue"
},
  "geometry": {"coordinates":[-79.24020400000001,43.855999],"type":"Point"}
}