{
  "type": "Feature",
  "properties": {
    "addr:full":"12633 Mile 52 Alaska Hwy Charlie Lake BC V0C 1H0",
    "addr:housenumber":"12633",
    "addr:postcode":"bc v0c 1h0",
    "addr:street":"Mile 52 Alaska Hwy",
    "iso:country":"CA",
    "sg:address":"12633 Mile 52 Alaska Hwy",
    "sg:city":"Charlie Lake",
    "sg:classifiers":[
        {
            "category":"Restaurant",
            "type":"Food & Drink"
        }
    ],
    "sg:phone":"+1 250 785 6148",
    "sg:postcode":"V0C 1H0",
    "sg:province":"BC",
    "sg:tags":[
        "caterer"
    ],
    "wof:name":"Independent Camp Svc Ltd",
    "wof:placetype":"venue"
},
  "geometry": {"coordinates":[-120.964912415,56.2806358337],"type":"Point"}
}