{
  "type": "Feature",
  "properties": {
    "addr:full":"1200 Front St Hearst ON P0L 1N0",
    "addr:housenumber":"1200",
    "addr:postcode":"p0l 1n0",
    "addr:street":"Front St",
    "iso:country":"CA",
    "sg:address":"1200 Front St",
    "sg:city":"Hearst",
    "sg:classifiers":[
        {
            "category":"Autos & Motor Vehicles",
            "subcategory":"Fuel & Gas Station",
            "type":"Retail Goods"
        }
    ],
    "sg:phone":"+1 705 362 4749",
    "sg:postcode":"P0L 1N0",
    "sg:province":"ON",
    "sg:tags":[
        "oil"
    ],
    "wof:name":"Shell Express",
    "wof:placetype":"venue"
},
  "geometry": {"coordinates":[-83.672569,49.69046],"type":"Point"}
}