{
  "type": "Feature",
  "properties": {
    "iso:country":"CA",
    "sg:address":"925 Arvin Ave",
    "sg:city":"Stoney Creek",
    "sg:classifiers":[
        {
            "category":"Wholesale",
            "subcategory":"Metals & Minerals",
            "type":"Manufacturing & Wholesale Goods"
        }
    ],
    "sg:phone":"+1 905 643 3535",
    "sg:postcode":"L8E 5N9",
    "sg:province":"ON",
    "sg:tags":[
        "steel",
        "warehouse"
    ],
    "wof:name":"Janco Steel Ltd",
    "wof:placetype":"venue"
},
  "geometry": {"coordinates":[-79.676392,43.219936],"type":"Point"}
}