{
  "type": "Feature",
  "properties": {
    "addr:full":"1644 Bayview Ave # 1004 Toronto ON M4G 3C2",
    "addr:housenumber":"1644",
    "addr:postcode":"m4g 3c2",
    "addr:street":"Bayview Ave # 1004",
    "iso:country":"CA",
    "sg:address":"1644 Bayview Ave # 1004",
    "sg:city":"Toronto",
    "sg:classifiers":[
        {
            "category":"Professional",
            "subcategory":"Business Services",
            "type":"Services"
        }
    ],
    "sg:phone":"+1 416 481 1886",
    "sg:postcode":"M4G 3C2",
    "sg:province":"ON",
    "sg:tags":[
        "lecture",
        "bureau",
        "seminar"
    ],
    "wof:name":"Achievers Choice Inc",
    "wof:placetype":"venue"
},
  "geometry": {"coordinates":[-79.375839,43.707073],"type":"Point"}
}