{
  "type": "Feature",
  "properties": {
    "addr:full":"Delta BC V3M 6Y9",
    "addr:postcode":"v3m 6y9",
    "iso:country":"CA",
    "sg:city":"Delta",
    "sg:classifiers":[
        {
            "category":"Wholesale",
            "subcategory":"Electrical",
            "type":"Manufacturing & Wholesale Goods"
        }
    ],
    "sg:phone":"+1 604 525 7940",
    "sg:postcode":"V3M 6Y9",
    "sg:province":"BC",
    "sg:tags":[
        "supply",
        "sign"
    ],
    "wof:name":"N D Graphic Products Ltd",
    "wof:placetype":"venue"
},
  "geometry": {"coordinates":[-122.96413421600001,49.1615257263],"type":"Point"}
}