{
  "type": "Feature",
  "properties": {
    "addr:full":"15 Rue Vittie Granby QC J2G 6N8",
    "addr:housenumber":"15",
    "addr:postcode":"j2g 6n8",
    "addr:street":"Rue Vittie",
    "iso:country":"CA",
    "sg:address":"15 Rue Vittie",
    "sg:city":"Granby",
    "sg:classifiers":[
        {
            "category":"Manufacturing",
            "subcategory":"Rubber & Plastics",
            "type":"Manufacturing & Wholesale Goods"
        }
    ],
    "sg:phone":"+1 450 372 5481",
    "sg:postcode":"J2G 6N8",
    "sg:province":"QC",
    "wof:name":"Bow Plastics Ltd",
    "wof:placetype":"venue"
},
  "geometry": {"coordinates":[-72.712952,45.394405],"type":"Point"}
}