{
  "type": "Feature",
  "properties": {
    "addr:full":"4369 Hwy 236 Kennetcook NS B0N 1P0",
    "addr:housenumber":"4369",
    "addr:postcode":"b0n 1p0",
    "addr:street":"Hwy 236",
    "iso:country":"CA",
    "sg:address":"4369 Hwy 236",
    "sg:city":"Kennetcook",
    "sg:classifiers":[
        {
            "category":"Education",
            "subcategory":"School",
            "type":"Public Place"
        }
    ],
    "sg:phone":"+1 902 362 3300",
    "sg:postcode":"B0N 1P0",
    "sg:province":"NS",
    "wof:name":"Hants North Rural High School",
    "wof:placetype":"venue"
},
  "geometry": {"coordinates":[-63.722279,45.17609],"type":"Point"}
}