{
  "type": "Feature",
  "properties": {
    "iso:country":"CA",
    "sg:address":"9108 Hwy 7",
    "sg:city":"Head of Jeddore",
    "sg:classifiers":[
        {
            "category":"Autos & Motor Vehicles",
            "subcategory":"Fuel & Gas Station",
            "type":"Retail Goods"
        }
    ],
    "sg:phone":"+1 902 889 2116",
    "sg:postcode":"B0J 1P0",
    "sg:province":"NS",
    "sg:tags":[
        "oil"
    ],
    "wof:name":"Baker's Bent Wrench Ultramar",
    "wof:placetype":"venue"
},
  "geometry": {"coordinates":[-63.071018219,44.7766494751],"type":"Point"}
}