{
  "type": "Feature",
  "properties": {
    "addr:full":"280 West Beaver Creek Rd #280 Richmond Hill ON L4B 3Z1",
    "addr:housenumber":"280;280",
    "addr:postcode":"l4b 3z1",
    "addr:street":"West Beaver Creek Rd #",
    "iso:country":"CA",
    "sg:address":"280 West Beaver Creek Rd #280",
    "sg:city":"Richmond Hill",
    "sg:classifiers":[
        {
            "category":"Shopping",
            "subcategory":"Pharmacy",
            "type":"Retail Goods"
        }
    ],
    "sg:phone":"+1 905 709 0778",
    "sg:postcode":"L4B 3Z1",
    "sg:province":"ON",
    "wof:name":"Jubilee Pharmacy",
    "wof:placetype":"venue"
},
  "geometry": {"coordinates":[-79.38705400000001,43.844688],"type":"Point"}
}