{
  "type": "Feature",
  "properties": {
    "iso:country":"CA",
    "sg:address":"530 Eastchester Ave E",
    "sg:city":"St Catharines",
    "sg:classifiers":[
        {
            "category":"Building & Trades",
            "subcategory":"Plumbing",
            "type":"Services"
        }
    ],
    "sg:phone":"+1 905 687 9033",
    "sg:postcode":"L2M 7P3",
    "sg:province":"ON",
    "sg:tags":[
        "contractor",
        "electric",
        "mechanical"
    ],
    "wof:name":"Black & Mc Donald Ltd",
    "wof:placetype":"venue"
},
  "geometry": {"coordinates":[-79.198647,43.17099],"type":"Point"}
}