{
  "type": "Feature",
  "properties": {
    "addr:full":"6646 Rue Saint-Denis Montreal QC H2S 2R9",
    "addr:housenumber":"6646",
    "addr:postcode":"h2s 2r9",
    "addr:street":"Rue Saint-Denis",
    "iso:country":"CA",
    "sg:address":"6646 Rue Saint-Denis",
    "sg:city":"Montreal",
    "sg:classifiers":[
        {
            "category":"Social Services",
            "type":"Services"
        }
    ],
    "sg:phone":"+1 514 273 7531",
    "sg:postcode":"H2S 2R9",
    "sg:province":"QC",
    "sg:tags":[
        "pregnancy",
        "counseling",
        "welfare",
        "organization",
        "information"
    ],
    "wof:name":"Serena Canada-Quebec",
    "wof:placetype":"venue"
},
  "geometry": {"coordinates":[-73.60748291020001,45.5349617004],"type":"Point"}
}