{
  "type": "Feature",
  "properties": {
    "addr:full":"700 Rue DE LA Gauchetiere O Montreal QC H3B 4L1",
    "addr:housenumber":"700",
    "addr:postcode":"h3b 4l1",
    "addr:street":"Rue De La Gauchetiere O",
    "iso:country":"CA",
    "sg:address":"700 Rue DE LA Gauchetiere O",
    "sg:city":"Montreal",
    "sg:classifiers":[
        {
            "category":"Professional",
            "subcategory":"Business Services",
            "type":"Services"
        }
    ],
    "sg:phone":"+1 514 875 9188",
    "sg:postcode":"H3B 4L1",
    "sg:province":"QC",
    "sg:tags":[
        "teleconferencing"
    ],
    "wof:name":"Darome Canada Inc",
    "wof:placetype":"venue"
},
  "geometry": {"coordinates":[-73.555244,45.513878],"type":"Point"}
}