{
  "type": "Feature",
  "properties": {
    "addr:full":"154 Maclaren St Ottawa ON K2P 0K9",
    "addr:housenumber":"154",
    "addr:postcode":"k2p 0k9",
    "addr:street":"Maclaren St",
    "iso:country":"CA",
    "sg:address":"154 Maclaren St",
    "sg:city":"Ottawa",
    "sg:classifiers":[
        {
            "category":"Real Estate",
            "subcategory":"Real Estate Agent",
            "type":"Services"
        }
    ],
    "sg:phone":"+1 613 237 8110",
    "sg:postcode":"K2P 0K9",
    "sg:province":"ON",
    "sg:tags":[
        "management"
    ],
    "wof:name":"E A Bourque Enterprises",
    "wof:placetype":"venue"
},
  "geometry": {"coordinates":[-75.68864440919999,45.4175453186],"type":"Point"}
}