{
  "type": "Feature",
  "properties": {
    "addr:full":"105 Av Legardeur Baie-Comeau QC G4Z 1E8",
    "addr:postcode":"g4z 1e8",
    "addr:street":"105 Av Legardeur",
    "iso:country":"CA",
    "sg:address":"105 Av Legardeur",
    "sg:city":"Baie-Comeau",
    "sg:classifiers":[
        {
            "category":"Education",
            "subcategory":"School",
            "type":"Public Place"
        }
    ],
    "sg:phone":"+1 418 296 6523",
    "sg:postcode":"G4Z 1E8",
    "sg:province":"QC",
    "wof:name":"Ecole Boisvert",
    "wof:placetype":"venue"
},
  "geometry": {"coordinates":[-68.1524810791,49.2210388184],"type":"Point"}
}