{
  "type": "Feature",
  "properties": {
    "addr:full":"5924 Boul Bourque Rock Forest QC J1N 1H3",
    "addr:housenumber":"5924",
    "addr:postcode":"j1n 1h3",
    "addr:street":"Boul Bourque",
    "iso:country":"CA",
    "sg:address":"5924 Boul Bourque",
    "sg:city":"Rock Forest",
    "sg:classifiers":[
        {
            "category":"Government",
            "subcategory":"Office",
            "type":"Public Place"
        }
    ],
    "sg:phone":"+1 819 864 7272",
    "sg:postcode":"J1N 1H3",
    "sg:province":"QC",
    "sg:tags":[
        "village"
    ],
    "wof:name":"Rock Forest Travaux Publics",
    "wof:placetype":"venue"
},
  "geometry": {"coordinates":[-72.01295471189999,45.3572921753],"type":"Point"}
}