{
  "type": "Feature",
  "properties": {
    "addr:full":"306 Jamieson Ave Picture Butte AB T0K 1V0",
    "addr:housenumber":"306",
    "addr:postcode":"t0k 1v0",
    "addr:street":"Jamieson Ave",
    "iso:country":"CA",
    "sg:address":"306 Jamieson Ave",
    "sg:city":"Picture Butte",
    "sg:classifiers":[
        {
            "category":"Restaurant",
            "type":"Food & Drink"
        }
    ],
    "sg:phone":"+1 403 732 4163",
    "sg:postcode":"T0K 1V0",
    "sg:province":"AB",
    "wof:name":"Picture Butte Restaurant",
    "wof:placetype":"venue"
},
  "geometry": {"coordinates":[-112.77819100000001,49.877438],"type":"Point"}
}