{
  "type": "Feature",
  "properties": {
    "addr:full":"169 St David St Mitchell ON N0K 1N0",
    "addr:housenumber":"169",
    "addr:postcode":"n0k 1n0",
    "addr:street":"St David St",
    "iso:country":"CA",
    "sg:address":"169 St David St",
    "sg:city":"Mitchell",
    "sg:classifiers":[
        {
            "category":"Government",
            "subcategory":"Office",
            "type":"Public Place"
        }
    ],
    "sg:phone":"+1 519 348 8429",
    "sg:postcode":"N0K 1N0",
    "sg:province":"ON",
    "sg:tags":[
        "village"
    ],
    "wof:name":"West Perth Dog Licensing",
    "wof:placetype":"venue"
},
  "geometry": {"coordinates":[-81.2002105713,43.4686164856],"type":"Point"}
}