{
  "type": "Feature",
  "properties": {
    "addr:full":"39 Vaughan St Ottawa ON K1M 1W9",
    "addr:housenumber":"39",
    "addr:postcode":"k1m 1w9",
    "addr:street":"Vaughan St",
    "iso:country":"CA",
    "sg:address":"39 Vaughan St",
    "sg:city":"Ottawa",
    "sg:classifiers":[
        {
            "category":"Professional",
            "subcategory":"Business Services",
            "type":"Services"
        }
    ],
    "sg:phone":"+1 613 742 6500",
    "sg:postcode":"K1M 1W9",
    "sg:province":"ON",
    "sg:tags":[
        "interior",
        "consultant",
        "design",
        "decorator"
    ],
    "wof:name":"Ecotope Inc",
    "wof:placetype":"venue"
},
  "geometry": {"coordinates":[-75.678619,45.440128],"type":"Point"}
}