{
  "type": "Feature",
  "properties": {
    "addr:full":"234 2nd St SW Altona MB R0G 0B0",
    "addr:housenumber":"234",
    "addr:postcode":"r0g 0b0",
    "addr:street":"2Nd St Sw",
    "iso:country":"CA",
    "sg:address":"234 2nd St SW",
    "sg:city":"Altona",
    "sg:classifiers":[
        {
            "category":"Building & Trades",
            "subcategory":"Construction",
            "type":"Services"
        }
    ],
    "sg:phone":"+1 204 324 8897",
    "sg:postcode":"R0G 0B0",
    "sg:province":"MB",
    "sg:tags":[
        "underground",
        "contractor",
        "trenching",
        "sewer"
    ],
    "wof:name":"John P Enns Construction Ltd",
    "wof:placetype":"venue"
},
  "geometry": {"coordinates":[-97.55609893800001,49.0986557007],"type":"Point"}
}