{
  "type": "Feature",
  "properties": {
    "addr:full":"Ottawa ON K1H 8N4",
    "addr:postcode":"k1h 8n4",
    "iso:country":"CA",
    "sg:city":"Ottawa",
    "sg:classifiers":[
        {
            "category":"Health Services",
            "subcategory":"Doctor",
            "type":"Services"
        }
    ],
    "sg:phone":"+1 613 721 2907",
    "sg:postcode":"K1H 8N4",
    "sg:province":"ON",
    "sg:tags":[
        "physician",
        "surgeon"
    ],
    "wof:name":"Shabib, Gihad MD",
    "wof:placetype":"venue"
},
  "geometry": {"coordinates":[-75.6721038818,45.3844718933],"type":"Point"}
}