{
  "type": "Feature",
  "properties": {
    "iso:country":"CA",
    "sg:address":"64 Buchanan Cres",
    "sg:city":"Brantford",
    "sg:classifiers":[
        {
            "category":"Organizations",
            "subcategory":"Religious Organization",
            "type":"Services"
        }
    ],
    "sg:phone":"+1 519 759 7581",
    "sg:postcode":"N3P 2A5",
    "sg:province":"ON",
    "sg:tags":[
        "church"
    ],
    "wof:name":"Christian Reformed Church",
    "wof:placetype":"venue"
},
  "geometry": {"coordinates":[-80.2442779541,43.1827507019],"type":"Point"}
}