{
  "type": "Feature",
  "properties": {
    "iso:country":"CA",
    "sg:address":"280 South Blair St",
    "sg:city":"Whitby",
    "sg:classifiers":[
        {
            "category":"Building & Trades",
            "subcategory":"Construction",
            "type":"Services"
        }
    ],
    "sg:phone":"+1 905 665 7788",
    "sg:postcode":"L1N 9N2",
    "sg:province":"ON",
    "sg:tags":[
        "sensitive",
        "deck",
        "material",
        "pressure",
        "restoration",
        "cleaning",
        "patio"
    ],
    "wof:name":"Label Supply",
    "wof:placetype":"venue"
},
  "geometry": {"coordinates":[-78.920448,43.853943],"type":"Point"}
}