{
  "type": "Feature",
  "properties": {
    "addr:full":"Montreal-Nord QC H1H 4J8",
    "addr:postcode":"h1h 4j8",
    "iso:country":"CA",
    "sg:city":"Montreal-Nord",
    "sg:classifiers":[
        {
            "category":"Manufacturing",
            "subcategory":"Tools & Machinery",
            "type":"Manufacturing & Wholesale Goods"
        }
    ],
    "sg:phone":"+1 514 325 0626",
    "sg:postcode":"H1H 4J8",
    "sg:province":"QC",
    "sg:tags":[
        "lamp"
    ],
    "wof:name":"Daniel Luminaire Inc",
    "wof:placetype":"venue"
},
  "geometry": {"coordinates":[-73.632904,45.581963],"type":"Point"}
}