{
  "type": "Feature",
  "properties": {
    "addr:full":"5524 Lawrence Ave E Scarborough ON M1C 3B2",
    "addr:housenumber":"5524",
    "addr:postcode":"m1c 3b2",
    "addr:street":"Lawrence Ave E",
    "iso:country":"CA",
    "sg:address":"5524 Lawrence Ave E",
    "sg:city":"Scarborough",
    "sg:classifiers":[
        {
            "category":"Professional",
            "subcategory":"Lawyer & Legal Services",
            "type":"Services"
        }
    ],
    "sg:phone":"+1 416 284 4749",
    "sg:postcode":"M1C 3B2",
    "sg:province":"ON",
    "sg:tags":[
        "attorney"
    ],
    "wof:name":"Tatham Pearson Llp",
    "wof:placetype":"venue"
},
  "geometry": {"coordinates":[-79.138992,43.779205],"type":"Point"}
}