{
  "type": "Feature",
  "properties": {
    "addr:full":"1368 Guildford Town Ctr Surrey BC V3R 7B7",
    "addr:housenumber":"1368",
    "addr:postcode":"v3r 7b7",
    "addr:street":"Guildford Town Ctr",
    "iso:country":"CA",
    "sg:address":"1368 Guildford Town Ctr",
    "sg:city":"Surrey",
    "sg:classifiers":[
        {
            "category":"Restaurant",
            "type":"Food & Drink"
        }
    ],
    "sg:phone":"+1 604 582 5853",
    "sg:postcode":"V3R 7B7",
    "sg:province":"BC",
    "wof:name":"Mr Sub",
    "wof:placetype":"venue"
},
  "geometry": {"coordinates":[-122.802055,49.188934],"type":"Point"}
}