{
  "type": "Feature",
  "properties": {
    "addr:full":"Courtenay BC V9N 1J3",
    "addr:postcode":"v9n 1j3",
    "iso:country":"CA",
    "sg:city":"Courtenay",
    "sg:classifiers":[
        {
            "category":"Shopping",
            "subcategory":"Bicycles & Sporting Goods",
            "type":"Retail Goods"
        }
    ],
    "sg:phone":"+1 250 897 1907",
    "sg:postcode":"V9N 1J3",
    "sg:province":"BC",
    "wof:name":"Onethirtythree",
    "wof:placetype":"venue"
},
  "geometry": {"coordinates":[-124.99646,49.691875],"type":"Point"}
}