{
  "type": "Feature",
  "properties": {
    "addr:full":"Dugald MB R0E 0K0",
    "addr:postcode":"r0e 0k0",
    "iso:country":"CA",
    "sg:city":"Dugald",
    "sg:classifiers":[
        {
            "category":"Retail",
            "subcategory":"Animal Services",
            "type":"Services"
        }
    ],
    "sg:phone":"+1 204 853 7796",
    "sg:postcode":"R0E 0K0",
    "sg:province":"MB",
    "sg:tags":[
        "pet",
        "boarding",
        "breeder",
        "dog",
        "sitting"
    ],
    "wof:name":"Masquerader Kennels",
    "wof:placetype":"venue"
},
  "geometry": {"coordinates":[-96.8401184082,49.8859062195],"type":"Point"}
}