{
  "type": "Feature",
  "properties": {
    "addr:full":"Stratford ON N5A 3W1",
    "addr:postcode":"n5a 3w1",
    "iso:country":"CA",
    "sg:city":"Stratford",
    "sg:classifiers":[
        {
            "category":"Building & Trades",
            "subcategory":"Construction",
            "type":"Services"
        }
    ],
    "sg:phone":"+1 519 273 1989",
    "sg:postcode":"N5A 3W1",
    "sg:province":"ON",
    "sg:tags":[
        "contractor",
        "general"
    ],
    "wof:name":"Feltz Design Build Ltd",
    "wof:placetype":"venue"
},
  "geometry": {"coordinates":[-80.968323,43.365185],"type":"Point"}
}