{
  "type": "Feature",
  "properties": {
    "iso:country":"CA",
    "sg:address":"30 Rue Dubois",
    "sg:city":"Saint-Eustache",
    "sg:classifiers":[
        {
            "category":"Building & Trades",
            "subcategory":"Construction",
            "type":"Services"
        }
    ],
    "sg:phone":"+1 450 623 7941",
    "sg:postcode":"J7P 4W9",
    "sg:province":"QC",
    "sg:tags":[
        "repairing",
        "contractor",
        "remodeling",
        "general"
    ],
    "wof:name":"Jean Lauzon & Fils Inc",
    "wof:placetype":"venue"
},
  "geometry": {"coordinates":[-73.910118103,45.5705375671],"type":"Point"}
}