{
  "type": "Feature",
  "properties": {
    "addr:full":"300 Lakeshore Rd E Oakville ON L6J 1J2",
    "addr:housenumber":"300",
    "addr:postcode":"l6j 1j2",
    "addr:street":"Lakeshore Rd E",
    "iso:country":"CA",
    "sg:address":"300 Lakeshore Rd E",
    "sg:city":"Oakville",
    "sg:classifiers":[
        {
            "category":"Personal",
            "subcategory":"Beauty Salon",
            "type":"Services"
        }
    ],
    "sg:phone":"+1 905 845 1888",
    "sg:postcode":"L6J 1J2",
    "sg:province":"ON",
    "wof:name":"Shears",
    "wof:placetype":"venue"
},
  "geometry": {"coordinates":[-79.66589355470001,43.4477005005],"type":"Point"}
}