{
  "type": "Feature",
  "properties": {
    "addr:full":"275 Rue Heriot Drummondville QC J2C 1K2",
    "addr:housenumber":"275",
    "addr:postcode":"j2c 1k2",
    "addr:street":"Rue Heriot",
    "iso:country":"CA",
    "sg:address":"275 Rue Heriot",
    "sg:city":"Drummondville",
    "sg:classifiers":[
        {
            "category":"Shopping",
            "subcategory":"Books",
            "type":"Retail Goods"
        }
    ],
    "sg:phone":"+1 819 472 3200",
    "sg:postcode":"J2C 1K2",
    "sg:province":"QC",
    "sg:tags":[
        "dealer"
    ],
    "wof:name":"Librairie LA Cle D'Or Boutique",
    "wof:placetype":"venue"
},
  "geometry": {"coordinates":[-72.487099,45.884037],"type":"Point"}
}