{
  "type": "Feature",
  "properties": {
    "addr:full":"50 Bastion Sq Victoria BC V8W 1J2",
    "addr:housenumber":"50",
    "addr:postcode":"v8w 1j2",
    "addr:street":"Bastion Sq",
    "iso:country":"CA",
    "sg:address":"50 Bastion Sq",
    "sg:city":"Victoria",
    "sg:classifiers":[
        {
            "category":"Restaurant",
            "type":"Food & Drink"
        }
    ],
    "sg:phone":"+1 250 361 9223",
    "sg:postcode":"V8W 1J2",
    "sg:province":"BC",
    "wof:name":"Re-Bar",
    "wof:placetype":"venue"
},
  "geometry": {"coordinates":[-123.368667602,48.4259338379],"type":"Point"}
}