{
  "type": "Feature",
  "properties": {
    "addr:full":"North York ON M3N 2V7",
    "addr:postcode":"m3n 2v7",
    "iso:country":"CA",
    "sg:city":"North York",
    "sg:classifiers":[
        {
            "category":"Health Services",
            "subcategory":"Doctor",
            "type":"Services"
        }
    ],
    "sg:phone":"+1 416 741 4844",
    "sg:postcode":"M3N 2V7",
    "sg:province":"ON",
    "sg:tags":[
        "dentist"
    ],
    "wof:name":"Lyon, Dennis F DDS",
    "wof:placetype":"venue"
},
  "geometry": {"coordinates":[-79.52304077150001,43.7560768127],"type":"Point"}
}