{
  "type": "Feature",
  "properties": {
    "iso:country":"CA",
    "sg:address":"2225 Ch Gascon",
    "sg:city":"Lachenaie",
    "sg:classifiers":[
        {
            "category":"Shopping",
            "subcategory":"Pharmacy",
            "type":"Retail Goods"
        }
    ],
    "sg:phone":"+1 450 471 2515",
    "sg:postcode":"J6X 4H3",
    "sg:province":"QC",
    "wof:name":"Jean Coutu",
    "wof:placetype":"venue"
},
  "geometry": {"coordinates":[-73.6647720337,45.7238197327],"type":"Point"}
}