{
  "type": "Feature",
  "properties": {
    "addr:full":"120 Woodstream Blvd Woodbridge ON L4L 7Z1",
    "addr:housenumber":"120",
    "addr:postcode":"l4l 7z1",
    "addr:street":"Woodstream Blvd",
    "iso:country":"CA",
    "sg:address":"120 Woodstream Blvd",
    "sg:city":"Woodbridge",
    "sg:classifiers":[
        {
            "category":"Retail",
            "subcategory":"Portrait Studio",
            "type":"Services"
        }
    ],
    "sg:phone":"+1 905 265 0009",
    "sg:postcode":"L4L 7Z1",
    "sg:province":"ON",
    "sg:tags":[
        "photographer"
    ],
    "wof:name":"Green Gecko Photography",
    "wof:placetype":"venue"
},
  "geometry": {"coordinates":[-79.60451500000001,43.774391],"type":"Point"}
}