{
  "type": "Feature",
  "properties": {
    "addr:full":"Edmonton AB T5H 0W2",
    "addr:postcode":"t5h 0w2",
    "iso:country":"CA",
    "sg:city":"Edmonton",
    "sg:classifiers":[
        {
            "category":"Autos & Motor Vehicles",
            "subcategory":"Auto Supplies",
            "type":"Retail Goods"
        }
    ],
    "sg:phone":"+1 780 414 1708",
    "sg:postcode":"T5H 0W2",
    "sg:province":"AB",
    "sg:tags":[
        "automobile",
        "parts"
    ],
    "wof:name":"Mei Lam Auto Inc",
    "wof:placetype":"venue"
},
  "geometry": {"coordinates":[-113.50129699999999,53.551521],"type":"Point"}
}