{
  "type": "Feature",
  "properties": {
    "iso:country":"CA",
    "sg:address":"14 23rd St E",
    "sg:city":"Saskatoon",
    "sg:classifiers":[
        {
            "category":"Shopping",
            "subcategory":"Hobbies, Toys, & Games",
            "type":"Retail Goods"
        }
    ],
    "sg:phone":"+1 306 664 8733",
    "sg:postcode":"S7K 0H5",
    "sg:province":"SK",
    "sg:tags":[
        "pottery",
        "equipment",
        "ceramic",
        "supply"
    ],
    "wof:name":"Tree",
    "wof:placetype":"venue"
},
  "geometry": {"coordinates":[-106.66941070599999,52.1316375732],"type":"Point"}
}