{
  "type": "Feature",
  "properties": {
    "addr:full":"386 Rue Hebert Mont-Laurier QC J9L 2X2",
    "addr:housenumber":"386",
    "addr:postcode":"j9l 2x2",
    "addr:street":"Rue Hebert",
    "iso:country":"CA",
    "sg:address":"386 Rue Hebert",
    "sg:city":"Mont-Laurier",
    "sg:classifiers":[
        {
            "category":"Organizations",
            "subcategory":"Professional Association",
            "type":"Services"
        }
    ],
    "sg:phone":"+1 819 623 6604",
    "sg:postcode":"J9L 2X2",
    "sg:province":"QC",
    "wof:name":"Manne Du Jour",
    "wof:placetype":"venue"
},
  "geometry": {"coordinates":[-75.49109649659999,46.5520858765],"type":"Point"}
}