{
  "type": "Feature",
  "properties": {
    "iso:country":"CA",
    "sg:address":"40 Birch St",
    "sg:city":"Lac Du Bonnet",
    "sg:classifiers":[
        {
            "category":"Building & Trades",
            "subcategory":"Plumbing",
            "type":"Services"
        }
    ],
    "sg:phone":"+1 204 345 2609",
    "sg:postcode":"R0E 1A0",
    "sg:province":"MB",
    "sg:tags":[
        "septic"
    ],
    "wof:name":"Rene's Septic Tank Cleaning",
    "wof:placetype":"venue"
},
  "geometry": {"coordinates":[-96.06196594239999,50.2516365051],"type":"Point"}
}