{
  "type": "Feature",
  "properties": {
    "iso:country":"CA",
    "sg:address":"17470 Av Saint-Louis # 5",
    "sg:city":"Saint-Hyacinthe",
    "sg:classifiers":[
        {
            "category":"Personal",
            "subcategory":"Beauty Salon",
            "type":"Services"
        }
    ],
    "sg:phone":"+1 450 771 6131",
    "sg:postcode":"J2T 3H1",
    "sg:province":"QC",
    "wof:name":"Salon Nuance",
    "wof:placetype":"venue"
},
  "geometry": {"coordinates":[-72.92505645750001,45.6184120178],"type":"Point"}
}