{
  "type": "Feature",
  "properties": {
    "addr:full":"4241 Briardale Rd Courtenay BC V9N 9R6",
    "addr:housenumber":"4241",
    "addr:postcode":"v9n 9r6",
    "addr:street":"Briardale Rd",
    "iso:country":"CA",
    "sg:address":"4241 Briardale Rd",
    "sg:city":"Courtenay",
    "sg:classifiers":[
        {
            "category":"Building & Trades",
            "subcategory":"Cleaning & Sanitation",
            "type":"Services"
        }
    ],
    "sg:phone":"+1 250 338 9714",
    "sg:postcode":"V9N 9R6",
    "sg:province":"BC",
    "sg:tags":[
        "janitor"
    ],
    "wof:name":"Above All Cleaning",
    "wof:placetype":"venue"
},
  "geometry": {"coordinates":[-124.993141174,49.6867218018],"type":"Point"}
}