{
  "type": "Feature",
  "properties": {
    "addr:full":"3225 Boul DE Tracy Sorel-Tracy QC J3R 5M7",
    "addr:housenumber":"3225",
    "addr:postcode":"j3r 5m7",
    "addr:street":"Boul De Tracy",
    "iso:country":"CA",
    "sg:address":"3225 Boul DE Tracy",
    "sg:city":"Sorel-Tracy",
    "sg:classifiers":[
        {
            "category":"Health Services",
            "subcategory":"Nursing And Care Facility",
            "type":"Services"
        }
    ],
    "sg:phone":"+1 450 746 8604",
    "sg:postcode":"J3R 5M7",
    "sg:province":"QC",
    "sg:tags":[
        "home",
        "retirement",
        "community",
        "rest"
    ],
    "wof:name":"Accueil Jardin Des Roses",
    "wof:placetype":"venue"
},
  "geometry": {"coordinates":[-73.1594543457,46.0149917603],"type":"Point"}
}