{
  "type": "Feature",
  "properties": {
    "addr:full":"11054 Sunrise Trl Pugwash NS B0K 1L0",
    "addr:housenumber":"11054",
    "addr:postcode":"b0k 1l0",
    "addr:street":"Sunrise Trl",
    "iso:country":"CA",
    "sg:address":"11054 Sunrise Trl",
    "sg:city":"Pugwash",
    "sg:classifiers":[
        {
            "category":"Travel",
            "subcategory":"Hotels & Motels",
            "type":"Entertainment"
        }
    ],
    "sg:phone":"+1 902 243 2727",
    "sg:postcode":"B0K 1L0",
    "sg:province":"NS",
    "wof:name":"Hillcrest Restaurant & Motel",
    "wof:placetype":"venue"
},
  "geometry": {"coordinates":[-63.6613349915,45.8495063782],"type":"Point"}
}