{
  "type": "Feature",
  "properties": {
    "addr:full":"Cambridge ON N1T 1J3",
    "addr:postcode":"n1t 1j3",
    "iso:country":"CA",
    "sg:city":"Cambridge",
    "sg:classifiers":[
        {
            "category":"Manufacturing",
            "subcategory":"Metals",
            "type":"Manufacturing & Wholesale Goods"
        }
    ],
    "sg:phone":"+1 519 622 3185",
    "sg:postcode":"N1T 1J3",
    "sg:province":"ON",
    "sg:tags":[
        "pipe",
        "sewer"
    ],
    "wof:name":"Underground Specialties",
    "wof:placetype":"venue"
},
  "geometry": {"coordinates":[-80.30122375489999,43.3974075317],"type":"Point"}
}