{
  "type": "Feature",
  "properties": {
    "addr:full":"454 Mcgill Dr Port Moody BC V3H 1T9",
    "addr:housenumber":"454",
    "addr:postcode":"v3h 1t9",
    "addr:street":"Mcgill Dr",
    "iso:country":"CA",
    "sg:address":"454 Mcgill Dr",
    "sg:city":"Port Moody",
    "sg:classifiers":[
        {
            "category":"Building & Trades",
            "subcategory":"Electrical",
            "type":"Services"
        }
    ],
    "sg:phone":"+1 604 931 7911",
    "sg:postcode":"V3H 1T9",
    "sg:province":"BC",
    "sg:tags":[
        "electric",
        "contractor"
    ],
    "wof:name":"Ramsay Electric Ltd",
    "wof:placetype":"venue"
},
  "geometry": {"coordinates":[-122.87346599999999,49.284992],"type":"Point"}
}