{
  "type": "Feature",
  "properties": {
    "addr:full":"5290 Route 11 Brantville NB E9H 1N4",
    "addr:housenumber":"5290",
    "addr:postcode":"e9h 1n4",
    "addr:street":"Route 11",
    "iso:country":"CA",
    "sg:address":"5290 Route 11",
    "sg:city":"Brantville",
    "sg:classifiers":[
        {
            "category":"Restaurant",
            "type":"Food & Drink"
        }
    ],
    "sg:phone":"+1 506 395 6734",
    "sg:postcode":"E9H 1N4",
    "sg:province":"NB",
    "wof:name":"Dixie Poulet Frit",
    "wof:placetype":"venue"
},
  "geometry": {"coordinates":[-65.016762,47.308434],"type":"Point"}
}