{
  "type": "Feature",
  "properties": {
    "addr:full":"195 Signal Rd Fort Mcmurray AB T9H 4Z9",
    "addr:housenumber":"195",
    "addr:postcode":"t9h 4z9",
    "addr:street":"Signal Rd",
    "iso:country":"CA",
    "sg:address":"195 Signal Rd",
    "sg:city":"Fort Mcmurray",
    "sg:classifiers":[
        {
            "category":"Organizations",
            "subcategory":"Religious Organization",
            "type":"Services"
        }
    ],
    "sg:phone":"+1 780 790 1114",
    "sg:postcode":"T9H 4Z9",
    "sg:province":"AB",
    "sg:tags":[
        "church"
    ],
    "wof:name":"St Thomas Anglican Church",
    "wof:placetype":"venue"
},
  "geometry": {"coordinates":[-111.42640686,56.7289123535],"type":"Point"}
}