{
  "type": "Feature",
  "properties": {
    "addr:full":"6849 Adera St Vancouver BC V6P 5C2",
    "addr:housenumber":"6849",
    "addr:postcode":"v6p 5c2",
    "addr:street":"Adera St",
    "iso:country":"CA",
    "sg:address":"6849 Adera St",
    "sg:city":"Vancouver",
    "sg:classifiers":[
        {
            "category":"Professional",
            "type":"Services"
        }
    ],
    "sg:phone":"+1 604 269 0827",
    "sg:postcode":"V6P 5C2",
    "sg:province":"BC",
    "sg:tags":[
        "actuary"
    ],
    "wof:name":"Christie Consulting Inc",
    "wof:placetype":"venue"
},
  "geometry": {"coordinates":[-123.143829346,49.223449707],"type":"Point"}
}