{
  "type": "Feature",
  "properties": {
    "addr:full":"6226 Boul Saint-Laurent Montreal QC H2S 3C2",
    "addr:housenumber":"6226",
    "addr:postcode":"h2s 3c2",
    "addr:street":"Boul Saint-Laurent",
    "iso:country":"CA",
    "sg:address":"6226 Boul Saint-Laurent",
    "sg:city":"Montreal",
    "sg:classifiers":[
        {
            "category":"Retail",
            "subcategory":"Auto Repair",
            "type":"Services"
        }
    ],
    "sg:phone":"+1 514 272 8888",
    "sg:postcode":"H2S 3C2",
    "sg:province":"QC",
    "sg:tags":[
        "repairing",
        "automobile"
    ],
    "wof:name":"Garage Vietnam Enr",
    "wof:placetype":"venue"
},
  "geometry": {"coordinates":[-73.6058731079,45.5288658142],"type":"Point"}
}