{
  "type": "Feature",
  "properties": {
    "addr:full":"9665 Trunk 8 Caledonia NS B0T 1B0",
    "addr:housenumber":"9665",
    "addr:postcode":"b0t 1b0",
    "addr:street":"Trunk 8",
    "iso:country":"CA",
    "sg:address":"9665 Trunk 8",
    "sg:city":"Caledonia",
    "sg:classifiers":[
        {
            "category":"Government",
            "subcategory":"Office",
            "type":"Public Place"
        }
    ],
    "sg:phone":"+1 902 682 2313",
    "sg:postcode":"B0T 1B0",
    "sg:province":"NS",
    "wof:name":"Nova Scotia Transportation",
    "wof:placetype":"venue"
},
  "geometry": {"coordinates":[-65.0296173096,44.3754196167],"type":"Point"}
}