{
  "type": "Feature",
  "properties": {
    "addr:full":"3328 Burnhamthorpe Rd W Oakville ON L6M 4H3",
    "addr:housenumber":"3328",
    "addr:postcode":"l6m 4h3",
    "addr:street":"Burnhamthorpe Rd W",
    "iso:country":"CA",
    "sg:address":"3328 Burnhamthorpe Rd W",
    "sg:city":"Oakville",
    "sg:classifiers":[
        {
            "category":"Building & Trades",
            "subcategory":"Electrical",
            "type":"Services"
        }
    ],
    "sg:phone":"+1 905 847 6504",
    "sg:postcode":"L6M 4H3",
    "sg:province":"ON",
    "sg:tags":[
        "electric",
        "contractor"
    ],
    "wof:name":"Lexsan Electric Inc",
    "wof:placetype":"venue"
},
  "geometry": {"coordinates":[-79.8035736084,43.4413986206],"type":"Point"}
}