{
  "type": "Feature",
  "properties": {
    "iso:country":"CA",
    "sg:address":"1915 Danforth Ave",
    "sg:city":"Toronto",
    "sg:classifiers":[
        {
            "category":"Professional",
            "subcategory":"Detective & Security Services",
            "type":"Services"
        }
    ],
    "sg:phone":"+1 416 690 2827",
    "sg:postcode":"M4C 1J5",
    "sg:province":"ON",
    "sg:tags":[
        "guard",
        "patrol"
    ],
    "wof:name":"Ontario Guard Svc Inc",
    "wof:placetype":"venue"
},
  "geometry": {"coordinates":[-79.3163528442,43.6847991943],"type":"Point"}
}