{
  "type": "Feature",
  "properties": {
    "iso:country":"CA",
    "sg:address":"53 Ontario St",
    "sg:city":"Toronto",
    "sg:classifiers":[
        {
            "category":"Communications",
            "subcategory":"Film & Video Production",
            "type":"Services"
        }
    ],
    "sg:phone":"+1 416 869 0420",
    "sg:postcode":"M5A 2V1",
    "sg:province":"ON",
    "sg:tags":[
        "motion",
        "picture",
        "studio",
        "producer"
    ],
    "wof:name":"Revolver",
    "wof:placetype":"venue"
},
  "geometry": {"coordinates":[-79.36614227290001,43.653011322],"type":"Point"}
}