{
  "type": "Feature",
  "properties": {
    "addr:full":"Pickering ON L1W 3N9",
    "addr:postcode":"l1w 3n9",
    "iso:country":"CA",
    "sg:city":"Pickering",
    "sg:classifiers":[
        {
            "category":"Wholesale",
            "subcategory":"Sporting Goods",
            "type":"Manufacturing & Wholesale Goods"
        }
    ],
    "sg:phone":"+1 905 428 6684",
    "sg:postcode":"L1W 3N9",
    "sg:province":"ON",
    "wof:name":"Durham Team & League Sports",
    "wof:placetype":"venue"
},
  "geometry": {"coordinates":[-79.0655136108,43.8353309631],"type":"Point"}
}