{
  "type": "Feature",
  "properties": {
    "iso:country":"CA",
    "sg:city":"Port Coquitlam",
    "sg:classifiers":[
        {
            "category":"Shopping",
            "subcategory":"Luggage & Leather Goods",
            "type":"Retail Goods"
        }
    ],
    "sg:phone":"+1 604 468 1166",
    "sg:postcode":"V3C 2M7",
    "sg:province":"BC",
    "sg:tags":[
        "motion",
        "picture",
        "case",
        "supply"
    ],
    "wof:name":"Clydesdale Custom Cases",
    "wof:placetype":"venue"
},
  "geometry": {"coordinates":[-122.762459,49.246002],"type":"Point"}
}