{
  "type": "Feature",
  "properties": {
    "addr:full":"894 Arnolds Bay Rd Mactier ON P0C 1H0",
    "addr:housenumber":"894",
    "addr:postcode":"p0c 1h0",
    "addr:street":"Arnolds Bay Rd",
    "iso:country":"CA",
    "sg:address":"894 Arnolds Bay Rd",
    "sg:city":"Mactier",
    "sg:classifiers":[
        {
            "category":"Travel",
            "subcategory":"Hotels & Motels",
            "type":"Entertainment"
        }
    ],
    "sg:phone":"+1 705 375 2081",
    "sg:postcode":"P0C 1H0",
    "sg:province":"ON",
    "sg:tags":[
        "cottage",
        "cabin"
    ],
    "wof:name":"Moon River Cottages",
    "wof:placetype":"venue"
},
  "geometry": {"coordinates":[-79.77039337159999,45.1369285583],"type":"Point"}
}