{
  "type": "Feature",
  "properties": {
    "addr:full":"188 Hymus Rd Scarborough ON M1L 2E1",
    "addr:housenumber":"188",
    "addr:postcode":"m1l 2e1",
    "addr:street":"Hymus Rd",
    "iso:country":"CA",
    "sg:address":"188 Hymus Rd",
    "sg:city":"Scarborough",
    "sg:classifiers":[
        {
            "category":"Retail",
            "subcategory":"Auto Repair",
            "type":"Services"
        }
    ],
    "sg:phone":"+1 416 759 9763",
    "sg:postcode":"M1L 2E1",
    "sg:province":"ON",
    "sg:tags":[
        "repairing",
        "automobile"
    ],
    "wof:name":"Toronto Brake",
    "wof:placetype":"venue"
},
  "geometry": {"coordinates":[-79.27858000000001,43.721001],"type":"Point"}
}