{
  "type": "Feature",
  "properties": {
    "addr:full":"Hamilton ON L8E 4V4",
    "addr:postcode":"l8e 4v4",
    "iso:country":"CA",
    "sg:city":"Hamilton",
    "sg:classifiers":[
        {
            "category":"Insurance",
            "subcategory":"Insurance Agent",
            "type":"Services"
        }
    ],
    "sg:phone":"+1 905 578 8045",
    "sg:postcode":"L8E 4V4",
    "sg:province":"ON",
    "wof:name":"Primerica Financial Svc",
    "wof:placetype":"venue"
},
  "geometry": {"coordinates":[-79.7611236572,43.2455558777],"type":"Point"}
}