{
  "type": "Feature",
  "properties": {
    "addr:full":"73 Downie St Stratford ON N5A 1W8",
    "addr:housenumber":"73",
    "addr:postcode":"n5a 1w8",
    "addr:street":"Downie St",
    "iso:country":"CA",
    "sg:address":"73 Downie St",
    "sg:city":"Stratford",
    "sg:classifiers":[
        {
            "category":"Banks & Credit Unions",
            "subcategory":"Bank",
            "type":"Services"
        }
    ],
    "sg:phone":"+1 519 271 4910",
    "sg:postcode":"N5A 1W8",
    "sg:province":"ON",
    "wof:name":"Bank of Montreal",
    "wof:placetype":"venue"
},
  "geometry": {"coordinates":[-80.981628418,43.369682312],"type":"Point"}
}