{
  "type": "Feature",
  "properties": {
    "addr:full":"575 Sackville Dr Lower Sackville NS B4C 2S4",
    "addr:housenumber":"575",
    "addr:postcode":"b4c 2s4",
    "addr:street":"Sackville Dr",
    "iso:country":"CA",
    "sg:address":"575 Sackville Dr",
    "sg:city":"Lower Sackville",
    "sg:classifiers":[
        {
            "category":"Retail",
            "subcategory":"Laundry & Dry Cleaning",
            "type":"Services"
        }
    ],
    "sg:phone":"+1 902 864 5854",
    "sg:postcode":"B4C 2S4",
    "sg:province":"NS",
    "sg:tags":[
        "cleaners",
        "rug",
        "carpet"
    ],
    "wof:name":"Metro Vacuum & Carpet Care",
    "wof:placetype":"venue"
},
  "geometry": {"coordinates":[-63.684723,44.767929],"type":"Point"}
}