{
  "type": "Feature",
  "properties": {
    "addr:full":"822 Eglinton Ave E East York ON M4G 2L1",
    "addr:housenumber":"822",
    "addr:postcode":"m4g 2l1",
    "addr:street":"Eglinton Ave E",
    "iso:country":"CA",
    "sg:address":"822 Eglinton Ave E",
    "sg:city":"East York",
    "sg:classifiers":[
        {
            "category":"Retail",
            "subcategory":"Repair Shop",
            "type":"Services"
        }
    ],
    "sg:phone":"+1 416 467 5858",
    "sg:postcode":"M4G 2L1",
    "sg:province":"ON",
    "sg:tags":[
        "upholsterer"
    ],
    "wof:name":"James Interiors",
    "wof:placetype":"venue"
},
  "geometry": {"coordinates":[-79.36618799999999,43.713436],"type":"Point"}
}