{
  "type": "Feature",
  "properties": {
    "addr:full":"Madeira Park BC V0N 2H0",
    "addr:postcode":"v0n 2h0",
    "iso:country":"CA",
    "sg:city":"Madeira Park",
    "sg:classifiers":[
        {
            "category":"Recreation",
            "type":"Entertainment"
        }
    ],
    "sg:phone":"+1 604 883 2612",
    "sg:postcode":"V0N 2H0",
    "sg:province":"BC",
    "sg:tags":[
        "government",
        "swimming"
    ],
    "wof:name":"Pender Harbour Aquatic Ctr",
    "wof:placetype":"venue"
},
  "geometry": {"coordinates":[-124.01795196499999,49.622215271],"type":"Point"}
}