{
  "type": "Feature",
  "properties": {
    "addr:full":"1515 Upper Sherman Ave Hamilton ON L8W 1C4",
    "addr:housenumber":"1515",
    "addr:postcode":"l8w 1c4",
    "addr:street":"Upper Sherman Ave",
    "iso:country":"CA",
    "sg:address":"1515 Upper Sherman Ave",
    "sg:city":"Hamilton",
    "sg:classifiers":[
        {
            "category":"Building & Trades",
            "subcategory":"Construction",
            "type":"Services"
        }
    ],
    "sg:phone":"+1 905 387 0333",
    "sg:postcode":"L8W 1C4",
    "sg:province":"ON",
    "sg:tags":[
        "home",
        "improvement"
    ],
    "wof:name":"Leuzzi & Sons Gen Contractors",
    "wof:placetype":"venue"
},
  "geometry": {"coordinates":[-79.861397,43.199612],"type":"Point"}
}