{
  "type": "Feature",
  "properties": {
    "addr:full":"139 Mckinnon Pl NE Calgary AB T2E 7B8",
    "addr:housenumber":"139",
    "addr:postcode":"t2e 7b8",
    "addr:street":"Mckinnon Pl Ne",
    "iso:country":"CA",
    "sg:address":"139 Mckinnon Pl NE",
    "sg:city":"Calgary",
    "sg:classifiers":[
        {
            "category":"Building & Trades",
            "subcategory":"Construction",
            "type":"Services"
        }
    ],
    "sg:phone":"+1 403 230 2020",
    "sg:postcode":"T2E 7B8",
    "sg:province":"AB",
    "sg:tags":[
        "underground",
        "trenching",
        "contractor"
    ],
    "wof:name":"NU Wave Backhoe & Trenching",
    "wof:placetype":"venue"
},
  "geometry": {"coordinates":[-114.00363900000001,51.055851],"type":"Point"}
}