{
  "type": "Feature",
  "properties": {
    "addr:full":"926 Hwy 6 Nakusp BC V0G 1R0",
    "addr:housenumber":"926",
    "addr:postcode":"v0g 1r0",
    "addr:street":"Hwy 6",
    "iso:country":"CA",
    "sg:address":"926 Hwy 6",
    "sg:city":"Nakusp",
    "sg:classifiers":[
        {
            "category":"Professional",
            "subcategory":"Accounting & Tax Preparation",
            "type":"Services"
        }
    ],
    "sg:phone":"+1 250 265 4051",
    "sg:postcode":"V0G 1R0",
    "sg:province":"BC",
    "sg:tags":[
        "return",
        "filing"
    ],
    "wof:name":"H & R Block Canada Inc",
    "wof:placetype":"venue"
},
  "geometry": {"coordinates":[-117.79536438,50.2381210327],"type":"Point"}
}