{
  "type": "Feature",
  "properties": {
    "addr:full":"901 Lansdowne St W Peterborough ON K9J 1Z5",
    "addr:housenumber":"901",
    "addr:postcode":"k9j 1z5",
    "addr:street":"Lansdowne St W",
    "iso:country":"CA",
    "sg:address":"901 Lansdowne St W",
    "sg:city":"Peterborough",
    "sg:classifiers":[
        {
            "category":"Home & Garden",
            "subcategory":"Garden Supply",
            "type":"Retail Goods"
        }
    ],
    "sg:phone":"+1 705 760 9766",
    "sg:postcode":"K9J 1Z5",
    "sg:province":"ON",
    "sg:tags":[
        "pet",
        "shop",
        "center"
    ],
    "wof:name":"Animalia",
    "wof:placetype":"venue"
},
  "geometry": {"coordinates":[-78.341003418,44.2828826904],"type":"Point"}
}