{
  "type": "Feature",
  "properties": {
    "addr:full":"2193 2nd Ave Whitehorse YT Y1A 3T8",
    "addr:housenumber":"2193",
    "addr:postcode":"y1a 3t8",
    "addr:street":"2Nd Ave",
    "iso:country":"CA",
    "sg:address":"2193 2nd Ave",
    "sg:city":"Whitehorse",
    "sg:classifiers":[
        {
            "category":"Restaurant",
            "type":"Food & Drink"
        }
    ],
    "sg:phone":"+1 867 393 3339",
    "sg:postcode":"Y1A 3T8",
    "sg:province":"YT",
    "sg:tags":[
        "pizza"
    ],
    "wof:name":"Domino's Pizza",
    "wof:placetype":"venue"
},
  "geometry": {"coordinates":[-135.05679321299999,60.7259101868],"type":"Point"}
}