{
  "type": "Feature",
  "properties": {
    "addr:full":"4350 Rue Rivard Montreal QC H2J 2M9",
    "addr:housenumber":"4350",
    "addr:postcode":"h2j 2m9",
    "addr:street":"Rue Rivard",
    "iso:country":"CA",
    "sg:address":"4350 Rue Rivard",
    "sg:city":"Montreal",
    "sg:classifiers":[
        {
            "category":"Personal",
            "subcategory":"Beauty Salon",
            "type":"Services"
        }
    ],
    "sg:phone":"+1 514 987 1645",
    "sg:postcode":"H2J 2M9",
    "sg:province":"QC",
    "wof:name":"Eliana Coiffure",
    "wof:placetype":"venue"
},
  "geometry": {"coordinates":[-73.5802688599,45.5234527588],"type":"Point"}
}