{
  "type": "Feature",
  "properties": {
    "addr:full":"18 Av Des Pruniers Sainte-Helene-DE-Breakeyville QC G0S 1E1",
    "addr:postcode":"g0s 1e1",
    "addr:street":"18 Av Des Pruniers Sainte-Helene-De-Breakeyville",
    "iso:country":"CA",
    "sg:address":"18 Av Des Pruniers",
    "sg:city":"Sainte-Helene-DE-Breakeyville",
    "sg:classifiers":[
        {
            "category":"Health Services",
            "subcategory":"Clinic",
            "type":"Services"
        }
    ],
    "sg:phone":"+1 418 832 4475",
    "sg:postcode":"G0S 1E1",
    "sg:province":"QC",
    "sg:tags":[
        "holistic",
        "practitioner"
    ],
    "wof:name":"Electro Bio Mag Inc",
    "wof:placetype":"venue"
},
  "geometry": {"coordinates":[-71.2252578735,46.6837692261],"type":"Point"}
}