{
  "type": "Feature",
  "properties": {
    "addr:full":"1367 Rue Des Champs-Elysees Chicoutimi QC G7H 6J2",
    "addr:housenumber":"1367",
    "addr:postcode":"g7h 6j2",
    "addr:street":"Rue Des Champs-Elysees",
    "iso:country":"CA",
    "sg:address":"1367 Rue Des Champs-Elysees",
    "sg:city":"Chicoutimi",
    "sg:classifiers":[
        {
            "category":"Insurance",
            "subcategory":"Insurance Agent",
            "type":"Services"
        }
    ],
    "sg:phone":"+1 418 543 3291",
    "sg:postcode":"G7H 6J2",
    "sg:province":"QC",
    "wof:name":"Promutuel Du Lac Au Fjord",
    "wof:placetype":"venue"
},
  "geometry": {"coordinates":[-71.05168914790001,48.4046096802],"type":"Point"}
}