{
  "type": "Feature",
  "properties": {
    "addr:full":"Vancouver BC V6E 3Z3",
    "addr:postcode":"v6e 3z3",
    "iso:country":"CA",
    "sg:city":"Vancouver",
    "sg:classifiers":[
        {
            "category":"Professional",
            "subcategory":"Business Services",
            "type":"Services"
        }
    ],
    "sg:phone":"+1 604 605 8400",
    "sg:postcode":"V6E 3Z3",
    "sg:province":"BC",
    "sg:tags":[
        "telemarketing"
    ],
    "wof:name":"Corporatel West",
    "wof:placetype":"venue"
},
  "geometry": {"coordinates":[-123.125336,49.286076],"type":"Point"}
}