{
  "type": "Feature",
  "properties": {
    "addr:full":"236 Arbour Glen Close NW Calgary AB T3G 3Y6",
    "addr:housenumber":"236",
    "addr:postcode":"t3g 3y6",
    "addr:street":"Arbour Glen Close Nw",
    "iso:country":"CA",
    "sg:address":"236 Arbour Glen Close NW",
    "sg:city":"Calgary",
    "sg:classifiers":[
        {
            "category":"Food & Beverages",
            "subcategory":"Dairy",
            "type":"Retail Goods"
        }
    ],
    "sg:phone":"+1 403 547 5601",
    "sg:postcode":"T3G 3Y6",
    "sg:province":"AB",
    "sg:tags":[
        "cheese"
    ],
    "wof:name":"Agropur",
    "wof:placetype":"venue"
},
  "geometry": {"coordinates":[-114.19204711899999,51.1368103027],"type":"Point"}
}