{
  "type": "Feature",
  "properties": {
    "iso:country":"CA",
    "sg:city":"Leduc",
    "sg:classifiers":[
        {
            "category":"Wholesale",
            "subcategory":"Machinery & Supplies",
            "type":"Manufacturing & Wholesale Goods"
        }
    ],
    "sg:phone":"+1 780 986 0666",
    "sg:postcode":"T9E 7B3",
    "sg:province":"AB",
    "sg:tags":[
        "equipment",
        "dairy"
    ],
    "wof:name":"Kneller's Sales and Svc",
    "wof:placetype":"venue"
},
  "geometry": {"coordinates":[-113.541946411,53.2728805542],"type":"Point"}
}