{
  "type": "Feature",
  "properties": {
    "iso:country":"CA",
    "sg:city":"Burnaby",
    "sg:classifiers":[
        {
            "category":"Personal",
            "subcategory":"Beauty Salon",
            "type":"Services"
        }
    ],
    "sg:phone":"+1 604 438 4944",
    "sg:postcode":"V5H 4G3",
    "sg:province":"BC",
    "wof:name":"Hair Fantasy",
    "wof:placetype":"venue"
},
  "geometry": {"coordinates":[-122.990005493,49.2245597839],"type":"Point"}
}