{
  "type": "Feature",
  "properties": {
    "addr:full":"57 Boul Kingsey Kingsey Falls QC J0A 1B0",
    "addr:housenumber":"57",
    "addr:postcode":"j0a 1b0",
    "addr:street":"Boul Kingsey",
    "iso:country":"CA",
    "sg:address":"57 Boul Kingsey",
    "sg:city":"Kingsey Falls",
    "sg:classifiers":[
        {
            "category":"Restaurant",
            "type":"Food & Drink"
        }
    ],
    "sg:phone":"+1 819 363 3825",
    "sg:postcode":"J0A 1B0",
    "sg:province":"QC",
    "sg:tags":[
        "banquet",
        "rooms"
    ],
    "wof:name":"Centre Communautaire",
    "wof:placetype":"venue"
},
  "geometry": {"coordinates":[-72.07028200000001,45.86171],"type":"Point"}
}