{
  "type": "Feature",
  "properties": {
    "addr:full":"3497 Juriet Rd Ladysmith BC V9G 1C7",
    "addr:housenumber":"3497",
    "addr:postcode":"v9g 1c7",
    "addr:street":"Juriet Rd",
    "iso:country":"CA",
    "sg:address":"3497 Juriet Rd",
    "sg:city":"Ladysmith",
    "sg:classifiers":[
        {
            "category":"Building & Trades",
            "subcategory":"Landscaping Services",
            "type":"Services"
        }
    ],
    "sg:phone":"+1 250 722 2125",
    "sg:postcode":"V9G 1C7",
    "sg:province":"BC",
    "sg:tags":[
        "lawn",
        "contractor",
        "landscape",
        "maintenance",
        "grounds"
    ],
    "wof:name":"Applelea Horticulture",
    "wof:placetype":"venue"
},
  "geometry": {"coordinates":[-123.820541382,48.9973564148],"type":"Point"}
}