{
  "type": "Feature",
  "properties": {
    "addr:full":"North York ON M2N 1T4",
    "addr:postcode":"m2n 1t4",
    "iso:country":"CA",
    "sg:city":"North York",
    "sg:classifiers":[
        {
            "category":"Professional",
            "subcategory":"Business Services",
            "type":"Services"
        }
    ],
    "sg:phone":"+1 416 224 8227",
    "sg:postcode":"M2N 1T4",
    "sg:province":"ON",
    "sg:tags":[
        "interior",
        "consultant",
        "design",
        "decorator"
    ],
    "wof:name":"David Lovett Design Consultant",
    "wof:placetype":"venue"
},
  "geometry": {"coordinates":[-79.4218215942,43.7615470886],"type":"Point"}
}