{
  "type": "Feature",
  "properties": {
    "addr:full":"427 Rue Principale Grenville QC J0V 1J0",
    "addr:housenumber":"427",
    "addr:postcode":"j0v 1j0",
    "addr:street":"Rue Principale",
    "iso:country":"CA",
    "sg:address":"427 Rue Principale",
    "sg:city":"Grenville",
    "sg:classifiers":[
        {
            "category":"Bars & Pubs",
            "type":"Food & Drink"
        }
    ],
    "sg:phone":"+1 819 242 3653",
    "sg:postcode":"J0V 1J0",
    "sg:province":"QC",
    "wof:name":"Bar Soumise",
    "wof:placetype":"venue"
},
  "geometry": {"coordinates":[-74.59577178959999,45.6226959229],"type":"Point"}
}