{
  "type": "Feature",
  "properties": {
    "addr:full":"11500 100 St # 1 Grande Prairie AB T8V 4C2",
    "addr:housenumber":"11500",
    "addr:postcode":"t8v 4c2",
    "addr:street":"100 St # 1",
    "iso:country":"CA",
    "sg:address":"11500 100 St # 1",
    "sg:city":"Grande Prairie",
    "sg:classifiers":[
        {
            "category":"Shopping",
            "subcategory":"Clothing, Apparel, & Fashions",
            "type":"Retail Goods"
        }
    ],
    "sg:phone":"+1 780 814 6199",
    "sg:postcode":"T8V 4C2",
    "sg:province":"AB",
    "sg:tags":[
        "jacket",
        "uniform"
    ],
    "wof:name":"Pro Sport Clothing CO",
    "wof:placetype":"venue"
},
  "geometry": {"coordinates":[-118.79499054,55.1843910217],"type":"Point"}
}