{
  "type": "Feature",
  "properties": {
    "addr:full":"260 Wharncliffe Rd S London ON N6J 2L4",
    "addr:housenumber":"260",
    "addr:postcode":"n6j 2l4",
    "addr:street":"Wharncliffe Rd",
    "iso:country":"CA",
    "sg:address":"260 Wharncliffe Rd S",
    "sg:city":"London",
    "sg:classifiers":[
        {
            "category":"Home & Garden",
            "subcategory":"Household Appliances",
            "type":"Retail Goods"
        }
    ],
    "sg:phone":"+1 519 439 9492",
    "sg:postcode":"N6J 2L4",
    "sg:province":"ON",
    "sg:tags":[
        "machine",
        "sewing"
    ],
    "wof:name":"Coolen's Sewing Machines",
    "wof:placetype":"venue"
},
  "geometry": {"coordinates":[-81.2615356445,42.9690322876],"type":"Point"}
}