{
  "type": "Feature",
  "properties": {
    "addr:full":"164 Starrs Rd Yarmouth NS B5A 4B6",
    "addr:housenumber":"164",
    "addr:postcode":"b5a 4b6",
    "addr:street":"Starrs Rd",
    "iso:country":"CA",
    "sg:address":"164 Starrs Rd",
    "sg:city":"Yarmouth",
    "sg:classifiers":[
        {
            "category":"Autos & Motor Vehicles",
            "subcategory":"Boat Sales",
            "type":"Retail Goods"
        }
    ],
    "sg:phone":"+1 902 742 5780",
    "sg:postcode":"B5A 4B6",
    "sg:province":"NS",
    "sg:tags":[
        "tackle",
        "equipment",
        "marine",
        "fishing",
        "supply"
    ],
    "wof:name":"Hydro Slave Marine Eqpt Ltd",
    "wof:placetype":"venue"
},
  "geometry": {"coordinates":[-66.09459699999999,43.839939],"type":"Point"}
}