{
  "type": "Feature",
  "properties": {
    "addr:full":"Fort St John BC V1J 2B8",
    "addr:postcode":"v1j 2b8",
    "iso:country":"CA",
    "sg:city":"Fort St John",
    "sg:classifiers":[
        {
            "category":"Shopping",
            "subcategory":"Used Merchandise",
            "type":"Retail Goods"
        }
    ],
    "sg:phone":"+1 250 785 2232",
    "sg:postcode":"V1J 2B8",
    "sg:province":"BC",
    "sg:tags":[
        "pawnbroker"
    ],
    "wof:name":"Express Pawn",
    "wof:placetype":"venue"
},
  "geometry": {"coordinates":[-120.854645,56.247692],"type":"Point"}
}