{
  "type": "Feature",
  "properties": {
    "iso:country":"CA",
    "sg:address":"623 Maitland St",
    "sg:city":"London",
    "sg:classifiers":[
        {
            "category":"Building & Trades",
            "subcategory":"Electrical",
            "type":"Services"
        }
    ],
    "sg:phone":"+1 519 432 7195",
    "sg:postcode":"N6B 3A1",
    "sg:province":"ON",
    "sg:tags":[
        "electric",
        "contractor"
    ],
    "wof:name":"J V Mc Donnell Electrical CO",
    "wof:placetype":"venue"
},
  "geometry": {"coordinates":[-81.2406082153,42.9940872192],"type":"Point"}
}