{
  "type": "Feature",
  "properties": {
    "addr:full":"945 Denman St Vancouver BC V6G 2M3",
    "addr:housenumber":"945",
    "addr:postcode":"v6g 2m3",
    "addr:street":"Denman St",
    "iso:country":"CA",
    "sg:address":"945 Denman St",
    "sg:city":"Vancouver",
    "sg:classifiers":[
        {
            "category":"Banks & Credit Unions",
            "subcategory":"Bank",
            "type":"Services"
        }
    ],
    "sg:phone":"+1 604 665 4189",
    "sg:postcode":"V6G 2M3",
    "sg:province":"BC",
    "wof:name":"Royal Bank Financial Group",
    "wof:placetype":"venue"
},
  "geometry": {"coordinates":[-123.138077,49.289951],"type":"Point"}
}