{
  "type": "Feature",
  "properties": {
    "addr:full":"Macdowall SK S0K 2S0",
    "addr:postcode":"s0k 2s0",
    "addr:street":"Macdowall",
    "iso:country":"CA",
    "sg:city":"Macdowall",
    "sg:classifiers":[
        {
            "category":"Organizations",
            "subcategory":"Professional Association",
            "type":"Services"
        }
    ],
    "sg:phone":"+1 306 922 8200",
    "sg:postcode":"S0K 2S0",
    "sg:province":"SK",
    "sg:tags":[
        "club"
    ],
    "wof:name":"Mac Dowall Lions Recreation",
    "wof:placetype":"venue"
},
  "geometry": {"coordinates":[-106.012535095,53.015335083],"type":"Point"}
}