{
  "type": "Feature",
  "properties": {
    "addr:full":"86 Conant St Oshawa ON L1H 3R4",
    "addr:housenumber":"86",
    "addr:postcode":"l1h 3r4",
    "addr:street":"Conant St",
    "iso:country":"CA",
    "sg:address":"86 Conant St",
    "sg:city":"Oshawa",
    "sg:classifiers":[
        {
            "category":"Education",
            "subcategory":"School",
            "type":"Public Place"
        }
    ],
    "sg:phone":"+1 905 723 0101",
    "sg:postcode":"L1H 3R4",
    "sg:province":"ON",
    "wof:name":"Canadian Conservatory of Music",
    "wof:placetype":"venue"
},
  "geometry": {"coordinates":[-78.851196,43.878113],"type":"Point"}
}