{
  "type": "Feature",
  "properties": {
    "iso:country":"CA",
    "sg:address":"2900 Woodroffe Ave",
    "sg:city":"Nepean",
    "sg:classifiers":[
        {
            "category":"Restaurant",
            "type":"Food & Drink"
        }
    ],
    "sg:phone":"+1 613 825 8254",
    "sg:postcode":"K2J 4G3",
    "sg:province":"ON",
    "sg:tags":[
        "pizza"
    ],
    "wof:name":"1 For 1 Pizza",
    "wof:placetype":"venue"
},
  "geometry": {"coordinates":[-75.7283630371,45.2929725647],"type":"Point"}
}