{
  "type": "Feature",
  "properties": {
    "addr:full":"272 Av Des Erables Brigham QC J2K 4C9",
    "addr:postcode":"j2k 4c9",
    "addr:street":"272 Av Des Erables",
    "iso:country":"CA",
    "sg:address":"272 Av Des Erables",
    "sg:city":"Brigham",
    "sg:classifiers":[
        {
            "category":"Travel",
            "subcategory":"Hotels & Motels",
            "type":"Entertainment"
        }
    ],
    "sg:phone":"+1 450 266 3446",
    "sg:postcode":"J2K 4C9",
    "sg:province":"QC",
    "sg:tags":[
        "inn"
    ],
    "wof:name":"Manoir Brigham",
    "wof:placetype":"venue"
},
  "geometry": {"coordinates":[-72.845398,45.246658],"type":"Point"}
}