{
  "type": "Feature",
  "properties": {
    "addr:full":"4 Adhemar Cusson Bedford QC J0J 1A0",
    "addr:housenumber":"4",
    "addr:postcode":"j0j 1a0",
    "addr:street":"Adhemar Cusson",
    "iso:country":"CA",
    "sg:address":"4 Adhemar Cusson",
    "sg:city":"Bedford",
    "sg:classifiers":[
        {
            "category":"Government",
            "subcategory":"Office",
            "type":"Public Place"
        }
    ],
    "sg:phone":"+1 450 248 3371",
    "sg:postcode":"J0J 1A0",
    "sg:province":"QC",
    "wof:name":"Quebec Bureau DE LA Publicite",
    "wof:placetype":"venue"
},
  "geometry": {"coordinates":[-72.985001,45.126041],"type":"Point"}
}