{
  "type": "Feature",
  "properties": {
    "addr:full":"961 Rue DE LA Clinique Senneterre QC J0Y 2M0",
    "addr:housenumber":"961",
    "addr:postcode":"j0y 2m0",
    "addr:street":"Rue De La Clinique",
    "iso:country":"CA",
    "sg:address":"961 Rue DE LA Clinique",
    "sg:city":"Senneterre",
    "sg:classifiers":[
        {
            "category":"Health Services",
            "subcategory":"Nursing And Care Facility",
            "type":"Services"
        }
    ],
    "sg:phone":"+1 819 737 2243",
    "sg:postcode":"J0Y 2M0",
    "sg:province":"QC",
    "sg:tags":[
        "organization",
        "social",
        "welfare"
    ],
    "wof:name":"Centre D'Fante Vallee DE L'Or",
    "wof:placetype":"venue"
},
  "geometry": {"coordinates":[-77.2520904541,48.3839607239],"type":"Point"}
}