{
  "type": "Feature",
  "properties": {
    "iso:country":"CA",
    "sg:address":"120 Inkerman St E",
    "sg:city":"Listowel",
    "sg:classifiers":[
        {
            "category":"Food & Beverages",
            "subcategory":"Specialty",
            "type":"Retail Goods"
        }
    ],
    "sg:phone":"+1 519 291 4920",
    "sg:postcode":"N4W 2L9",
    "sg:province":"ON",
    "sg:tags":[
        "health",
        "diet"
    ],
    "wof:name":"Pandora's Pantry",
    "wof:placetype":"venue"
},
  "geometry": {"coordinates":[-80.9521102905,43.7322425842],"type":"Point"}
}