{
  "type": "Feature",
  "properties": {
    "iso:country":"CA",
    "sg:address":"1405 Power Dam Dr",
    "sg:city":"Cornwall",
    "sg:classifiers":[
        {
            "category":"Building & Trades",
            "subcategory":"Equipment Rental",
            "type":"Services"
        }
    ],
    "sg:phone":"+1 613 938 8368",
    "sg:postcode":"K6H 5R6",
    "sg:province":"ON",
    "sg:tags":[
        "camping",
        "tent"
    ],
    "wof:name":"Lauzon Tent Rentals",
    "wof:placetype":"venue"
},
  "geometry": {"coordinates":[-74.7800445557,45.0202827454],"type":"Point"}
}