{
  "type": "Feature",
  "properties": {
    "addr:full":"1374 Rue Principale Saint-Boniface-DE-Shawinigan QC G0X 2L0",
    "addr:housenumber":"1374",
    "addr:postcode":"g0x 2l0",
    "addr:street":"Rue Principale",
    "iso:country":"CA",
    "sg:address":"1374 Rue Principale",
    "sg:city":"Saint-Boniface-DE-Shawinigan",
    "sg:classifiers":[
        {
            "category":"Government",
            "subcategory":"Office",
            "type":"Public Place"
        }
    ],
    "sg:phone":"+1 819 535 3141",
    "sg:postcode":"G0X 2L0",
    "sg:province":"QC",
    "sg:tags":[
        "village"
    ],
    "wof:name":"St-Boniface Station DE Pompage",
    "wof:placetype":"venue"
},
  "geometry": {"coordinates":[-72.811081,46.492287],"type":"Point"}
}