{
  "type": "Feature",
  "properties": {
    "addr:full":"6729 Hastings St Burnaby BC V5B 1S6",
    "addr:housenumber":"6729",
    "addr:postcode":"bc v5b 1s6",
    "addr:street":"Hastings St",
    "iso:country":"CA",
    "sg:address":"6729 Hastings St",
    "sg:city":"Burnaby",
    "sg:classifiers":[
        {
            "category":"Personal",
            "subcategory":"Beauty Salon",
            "type":"Services"
        }
    ],
    "sg:phone":"+1 604 298 9513",
    "sg:postcode":"V5B 1S6",
    "sg:province":"BC",
    "wof:name":"R & B Hair Design",
    "wof:placetype":"venue"
},
  "geometry": {"coordinates":[-122.964249,49.280491],"type":"Point"}
}