{
  "type": "Feature",
  "properties": {
    "iso:country":"CA",
    "sg:address":"11020 86 Ave NW",
    "sg:city":"Edmonton",
    "sg:classifiers":[
        {
            "category":"Organizations",
            "subcategory":"Community Association",
            "type":"Services"
        }
    ],
    "sg:phone":"+1 780 432 7373",
    "sg:postcode":"T6G 0W9",
    "sg:province":"AB",
    "sg:tags":[
        "sorority",
        "fraternity",
        "fraternal"
    ],
    "wof:name":"Delta Upsilon Fraternity",
    "wof:placetype":"venue"
},
  "geometry": {"coordinates":[-113.51573944099999,53.5221672058],"type":"Point"}
}