{
  "type": "Feature",
  "properties": {
    "addr:full":"408 Rue Lafleur Lachute QC J8H 1R3",
    "addr:housenumber":"408",
    "addr:postcode":"j8h 1r3",
    "addr:street":"Rue Lafleur",
    "iso:country":"CA",
    "sg:address":"408 Rue Lafleur",
    "sg:city":"Lachute",
    "sg:classifiers":[
        {
            "category":"Personal",
            "subcategory":"Beauty Salon",
            "type":"Services"
        }
    ],
    "sg:phone":"+1 450 562 2766",
    "sg:postcode":"J8H 1R3",
    "sg:province":"QC",
    "wof:name":"Salon Mimi",
    "wof:placetype":"venue"
},
  "geometry": {"coordinates":[-74.33768499999999,45.654827],"type":"Point"}
}