{
  "type": "Feature",
  "properties": {
    "addr:full":"36 Parkview Crt Sault Ste Marie ON P6B 6K6",
    "addr:housenumber":"36",
    "addr:postcode":"p6b 6k6",
    "addr:street":"Parkview Crt",
    "iso:country":"CA",
    "sg:address":"36 Parkview Crt",
    "sg:city":"Sault Ste Marie",
    "sg:classifiers":[
        {
            "category":"Building & Trades",
            "subcategory":"Construction",
            "type":"Services"
        }
    ],
    "sg:phone":"+1 705 949 6320",
    "sg:postcode":"P6B 6K6",
    "sg:province":"ON",
    "sg:tags":[
        "general",
        "contractor"
    ],
    "wof:name":"Jarrett Construction",
    "wof:placetype":"venue"
},
  "geometry": {"coordinates":[-84.293015,46.527435],"type":"Point"}
}