{
  "type": "Feature",
  "properties": {
    "addr:full":"6341 Boul Monk Montreal QC H4E 3H8",
    "addr:housenumber":"6341",
    "addr:postcode":"h4e 3h8",
    "addr:street":"Boul Monk",
    "iso:country":"CA",
    "sg:address":"6341 Boul Monk",
    "sg:city":"Montreal",
    "sg:classifiers":[
        {
            "category":"Shopping",
            "subcategory":"Bicycles & Sporting Goods",
            "type":"Retail Goods"
        }
    ],
    "sg:phone":"+1 514 767 0559",
    "sg:postcode":"H4E 3H8",
    "sg:province":"QC",
    "wof:name":"Eddy Bicycles Inc",
    "wof:placetype":"venue"
},
  "geometry": {"coordinates":[-73.595016,45.455265],"type":"Point"}
}