{
  "type": "Feature",
  "properties": {
    "addr:full":"1007 Fennell Ave E Hamilton ON L8T 1R1",
    "addr:housenumber":"1007",
    "addr:postcode":"l8t 1r1",
    "addr:street":"Fennell Ave E",
    "iso:country":"CA",
    "sg:address":"1007 Fennell Ave E",
    "sg:city":"Hamilton",
    "sg:classifiers":[
        {
            "category":"Retail",
            "subcategory":"Animal Services",
            "type":"Services"
        }
    ],
    "sg:phone":"+1 905 389 0778",
    "sg:postcode":"L8T 1R1",
    "sg:province":"ON",
    "sg:tags":[
        "pet",
        "grooming",
        "washing"
    ],
    "wof:name":"Canine Cottage",
    "wof:placetype":"venue"
},
  "geometry": {"coordinates":[-79.8364486694,43.2274665833],"type":"Point"}
}