{
  "type": "Feature",
  "properties": {
    "iso:country":"CA",
    "sg:address":"305 Rue Racine",
    "sg:city":"Loretteville",
    "sg:classifiers":[
        {
            "category":"Recreation",
            "type":"Entertainment"
        }
    ],
    "sg:phone":"+1 418 641 6122",
    "sg:postcode":"G2B 1E7",
    "sg:province":"QC",
    "sg:tags":[
        "center",
        "hall",
        "auditorium"
    ],
    "wof:name":"Loretteville Centres Communaut",
    "wof:placetype":"venue"
},
  "geometry": {"coordinates":[-71.3602676392,46.8510322571],"type":"Point"}
}