{
  "type": "Feature",
  "properties": {
    "addr:full":"2 Macquarrie Dr Exten Port Hawkesbury NS B9A 3A2",
    "addr:housenumber":"2",
    "addr:postcode":"b9a 3a2",
    "addr:street":"Macquarrie Dr Exten",
    "iso:country":"CA",
    "sg:address":"2 Macquarrie Dr Exten",
    "sg:city":"Port Hawkesbury",
    "sg:classifiers":[
        {
            "category":"Health Services",
            "subcategory":"Nursing And Care Facility",
            "type":"Services"
        }
    ],
    "sg:phone":"+1 902 625 1460",
    "sg:postcode":"B9A 3A2",
    "sg:province":"NS",
    "sg:tags":[
        "home",
        "convalescent"
    ],
    "wof:name":"Port Hawkesbury Nursing Home",
    "wof:placetype":"venue"
},
  "geometry": {"coordinates":[-61.354095459,45.6156654358],"type":"Point"}
}