{
  "type": "Feature",
  "properties": {
    "addr:full":"750 17th St West Vancouver BC V7V 3T3",
    "addr:housenumber":"750",
    "addr:postcode":"v7v 3t3",
    "addr:street":"17Th St",
    "iso:country":"CA",
    "sg:address":"750 17th St",
    "sg:city":"West Vancouver",
    "sg:classifiers":[
        {
            "category":"Government",
            "subcategory":"Office",
            "type":"Public Place"
        }
    ],
    "sg:phone":"+1 604 925 7020",
    "sg:postcode":"V7V 3T3",
    "sg:province":"BC",
    "sg:tags":[
        "village"
    ],
    "wof:name":"West Vancouver Engineering",
    "wof:placetype":"venue"
},
  "geometry": {"coordinates":[-123.160027,49.331154],"type":"Point"}
}