{
  "type": "Feature",
  "properties": {
    "addr:full":"4640 Circle Rd Montreal QC H3W 1Z1",
    "addr:housenumber":"4640",
    "addr:postcode":"h3w 1z1",
    "addr:street":"Circle Rd",
    "iso:country":"CA",
    "sg:address":"4640 Circle Rd",
    "sg:city":"Montreal",
    "sg:classifiers":[
        {
            "category":"Real Estate",
            "subcategory":"Real Estate Agent",
            "type":"Services"
        }
    ],
    "sg:phone":"+1 514 487 5669",
    "sg:postcode":"H3W 1Z1",
    "sg:province":"QC",
    "sg:tags":[
        "consultant"
    ],
    "wof:name":"Inspections Bpc",
    "wof:placetype":"venue"
},
  "geometry": {"coordinates":[-73.6204452515,45.4858627319],"type":"Point"}
}