{
  "type": "Feature",
  "properties": {
    "addr:full":"3295 Walker Rd Windsor ON N8W 3R7",
    "addr:housenumber":"3295",
    "addr:postcode":"n8w 3r7",
    "addr:street":"Walker Rd",
    "iso:country":"CA",
    "sg:address":"3295 Walker Rd",
    "sg:city":"Windsor",
    "sg:classifiers":[
        {
            "category":"Banks & Credit Unions",
            "subcategory":"Bank",
            "type":"Services"
        }
    ],
    "sg:phone":"+1 519 969 9370",
    "sg:postcode":"N8W 3R7",
    "sg:province":"ON",
    "wof:name":"Cibc",
    "wof:placetype":"venue"
},
  "geometry": {"coordinates":[-82.9793624878,42.2786254883],"type":"Point"}
}