{
  "type": "Feature",
  "properties": {
    "addr:full":"286 Panorama Hills Lane NW Calgary AB T3K 5H8",
    "addr:housenumber":"286",
    "addr:postcode":"t3k 5h8",
    "addr:street":"Panorama Hills Lane Nw",
    "iso:country":"CA",
    "sg:address":"286 Panorama Hills Lane NW",
    "sg:city":"Calgary",
    "sg:classifiers":[
        {
            "category":"Building & Trades",
            "subcategory":"Construction",
            "type":"Services"
        }
    ],
    "sg:phone":"+1 403 275 9555",
    "sg:postcode":"T3K 5H8",
    "sg:province":"AB",
    "sg:tags":[
        "skylight"
    ],
    "wof:name":"Calgary Construction Svc",
    "wof:placetype":"venue"
},
  "geometry": {"coordinates":[-114.068207,51.153347],"type":"Point"}
}