{
  "type": "Feature",
  "properties": {
    "addr:full":"St-Valerien QC J0H 2B0",
    "addr:postcode":"j0h 2b0",
    "iso:country":"CA",
    "sg:city":"St-Valerien",
    "sg:classifiers":[
        {
            "category":"Recreation",
            "type":"Entertainment"
        }
    ],
    "sg:phone":"+1 450 549 2663",
    "sg:postcode":"J0H 2B0",
    "sg:province":"QC",
    "sg:tags":[
        "center",
        "government"
    ],
    "wof:name":"St-Valerien Loisirs",
    "wof:placetype":"venue"
},
  "geometry": {"coordinates":[-68.66345200000001,48.339306],"type":"Point"}
}