{
  "type": "Feature",
  "properties": {
    "iso:country":"CA",
    "sg:city":"Edmonton",
    "sg:classifiers":[
        {
            "category":"Shopping",
            "subcategory":"Clothing, Apparel, & Fashions",
            "type":"Retail Goods"
        }
    ],
    "sg:phone":"+1 780 444 2117",
    "sg:postcode":"T5Z 2Y7",
    "sg:province":"AB",
    "wof:name":"Thriftys",
    "wof:placetype":"venue"
},
  "geometry": {"coordinates":[-113.476799011,53.6312904358],"type":"Point"}
}