{
  "type": "Feature",
  "properties": {
    "addr:full":"North York ON M6A 1E2",
    "addr:postcode":"m6a 1e2",
    "iso:country":"CA",
    "sg:city":"North York",
    "sg:classifiers":[
        {
            "category":"Building & Trades",
            "subcategory":"Construction",
            "type":"Services"
        }
    ],
    "sg:phone":"+1 416 782 2594",
    "sg:postcode":"M6A 1E2",
    "sg:province":"ON",
    "sg:tags":[
        "welding",
        "general",
        "contractor"
    ],
    "wof:name":"Mobile Welding",
    "wof:placetype":"venue"
},
  "geometry": {"coordinates":[-79.46888,43.71085],"type":"Point"}
}