{
  "type": "Feature",
  "properties": {
    "iso:country":"CA",
    "sg:address":"73 Water St N",
    "sg:city":"Cambridge",
    "sg:classifiers":[
        {
            "category":"Government",
            "subcategory":"Office",
            "type":"Public Place"
        }
    ],
    "sg:phone":"+1 519 740 5966",
    "sg:postcode":"N1R 7L6",
    "sg:province":"ON",
    "wof:name":"Ontario Parole & Probation",
    "wof:placetype":"venue"
},
  "geometry": {"coordinates":[-80.31517791749999,43.3617553711],"type":"Point"}
}