{
  "type": "Feature",
  "properties": {
    "addr:full":"671 Albert St Fredericton NB E3B 2C2",
    "addr:housenumber":"671",
    "addr:postcode":"e3b 2c2",
    "addr:street":"Albert St",
    "iso:country":"CA",
    "sg:address":"671 Albert St",
    "sg:city":"Fredericton",
    "sg:classifiers":[
        {
            "category":"Personal",
            "subcategory":"Beauty Salon",
            "type":"Services"
        }
    ],
    "sg:phone":"+1 506 455 1833",
    "sg:postcode":"E3B 2C2",
    "sg:province":"NB",
    "wof:name":"Phase 7 Hair Design",
    "wof:placetype":"venue"
},
  "geometry": {"coordinates":[-66.644661,45.95134],"type":"Point"}
}