{
  "type": "Feature",
  "properties": {
    "addr:full":"126 Wilson St E Ancaster ON L9G 2B7",
    "addr:housenumber":"126",
    "addr:postcode":"l9g 2b7",
    "addr:street":"Wilson St E",
    "iso:country":"CA",
    "sg:address":"126 Wilson St E",
    "sg:city":"Ancaster",
    "sg:classifiers":[
        {
            "category":"Social Services",
            "subcategory":"Child Care",
            "type":"Services"
        }
    ],
    "sg:phone":"+1 905 648 1838",
    "sg:postcode":"L9G 2B7",
    "sg:province":"ON",
    "wof:name":"Village Treehouse Childcare",
    "wof:placetype":"venue"
},
  "geometry": {"coordinates":[-79.98230743409999,43.220867157],"type":"Point"}
}