{
  "type": "Feature",
  "properties": {
    "iso:country":"CA",
    "sg:address":"9208 27 Ave NW",
    "sg:city":"Edmonton",
    "sg:classifiers":[
        {
            "category":"Manufacturing",
            "subcategory":"Metals",
            "type":"Manufacturing & Wholesale Goods"
        }
    ],
    "sg:phone":"+1 780 437 2334",
    "sg:postcode":"T6N 1B2",
    "sg:province":"AB",
    "sg:tags":[
        "valve"
    ],
    "wof:name":"Parval Equipment Ltd",
    "wof:placetype":"venue"
},
  "geometry": {"coordinates":[-113.471290588,53.4570541382],"type":"Point"}
}