{
  "type": "Feature",
  "properties": {
    "addr:full":"55 John St N Hamilton ON L8R 3M8",
    "addr:housenumber":"55",
    "addr:postcode":"l8r 3m8",
    "addr:street":"John St N",
    "iso:country":"CA",
    "sg:address":"55 John St N",
    "sg:city":"Hamilton",
    "sg:classifiers":[
        {
            "category":"Utilities",
            "subcategory":"Electric",
            "type":"Services"
        }
    ],
    "sg:phone":"+1 905 317 4781",
    "sg:postcode":"L8R 3M8",
    "sg:province":"ON",
    "sg:tags":[
        "company"
    ],
    "wof:name":"Hamilton Utilities Corp",
    "wof:placetype":"venue"
},
  "geometry": {"coordinates":[-79.8660583496,43.2574653625],"type":"Point"}
}