{
  "type": "Feature",
  "properties": {
    "addr:full":"420 Weber St N Waterloo ON N2L 4E7",
    "addr:housenumber":"420",
    "addr:postcode":"n2l 4e7",
    "addr:street":"Weber St N",
    "iso:country":"CA",
    "sg:address":"420 Weber St N",
    "sg:city":"Waterloo",
    "sg:classifiers":[
        {
            "category":"Real Estate",
            "subcategory":"Real Estate Agent",
            "type":"Services"
        }
    ],
    "sg:phone":"+1 519 745 6247",
    "sg:postcode":"N2L 4E7",
    "sg:province":"ON",
    "wof:name":"R P Krause Realty Corp",
    "wof:placetype":"venue"
},
  "geometry": {"coordinates":[-80.52855700000001,43.485222],"type":"Point"}
}