{
  "type": "Feature",
  "properties": {
    "addr:full":"191 1st St Nipigon ON P0T 2J0",
    "addr:housenumber":"191",
    "addr:postcode":"p0t 2j0",
    "addr:street":"1St St",
    "iso:country":"CA",
    "sg:address":"191 1st St",
    "sg:city":"Nipigon",
    "sg:classifiers":[
        {
            "category":"Autos & Motor Vehicles",
            "subcategory":"Auto Supplies",
            "type":"Retail Goods"
        }
    ],
    "sg:phone":"+1 807 887 3131",
    "sg:postcode":"P0T 2J0",
    "sg:province":"ON",
    "sg:tags":[
        "automobile",
        "parts"
    ],
    "wof:name":"Canadian Tire",
    "wof:placetype":"venue"
},
  "geometry": {"coordinates":[-88.28243999999999,49.020027],"type":"Point"}
}