{
  "type": "Feature",
  "properties": {
    "addr:full":"53 Yonge St Kingston ON K7M 6G4",
    "addr:housenumber":"53",
    "addr:postcode":"k7m 6g4",
    "addr:street":"Yonge St",
    "iso:country":"CA",
    "sg:address":"53 Yonge St",
    "sg:city":"Kingston",
    "sg:classifiers":[
        {
            "category":"Government",
            "subcategory":"Office",
            "type":"Public Place"
        }
    ],
    "sg:phone":"+1 613 544 9842",
    "sg:postcode":"K7M 6G4",
    "sg:province":"ON",
    "sg:tags":[
        "village"
    ],
    "wof:name":"Portsmouth Olympic Harbour",
    "wof:placetype":"venue"
},
  "geometry": {"coordinates":[-76.517921,44.218937],"type":"Point"}
}