{
  "type": "Feature",
  "properties": {
    "addr:full":"142 Colvin Cres Thornhill ON L4J 2R7",
    "addr:housenumber":"142",
    "addr:postcode":"l4j 2r7",
    "addr:street":"Colvin Cres",
    "iso:country":"CA",
    "sg:address":"142 Colvin Cres",
    "sg:city":"Thornhill",
    "sg:classifiers":[
        {
            "category":"Professional",
            "subcategory":"Accounting & Tax Preparation",
            "type":"Services"
        }
    ],
    "sg:phone":"+1 905 886 6567",
    "sg:postcode":"L4J 2R7",
    "sg:province":"ON",
    "sg:tags":[
        "bookkeeping",
        "general"
    ],
    "wof:name":"Bsm Accounting Svc",
    "wof:placetype":"venue"
},
  "geometry": {"coordinates":[-79.455505,43.797596],"type":"Point"}
}