{
  "type": "Feature",
  "properties": {
    "iso:country":"CA",
    "sg:address":"4144 99 St NW",
    "sg:city":"Edmonton",
    "sg:classifiers":[
        {
            "category":"Building & Trades",
            "subcategory":"Construction",
            "type":"Services"
        }
    ],
    "sg:phone":"+1 780 413 4847",
    "sg:postcode":"T6E 3N5",
    "sg:province":"AB",
    "sg:tags":[
        "resurfacing",
        "material",
        "laying",
        "refinishing",
        "floor"
    ],
    "wof:name":"Artison's Floor Fashions Ltd",
    "wof:placetype":"venue"
},
  "geometry": {"coordinates":[-113.486305,53.477497],"type":"Point"}
}