{
  "type": "Feature",
  "properties": {
    "addr:full":"2231 Banff Trail NW Calgary AB T2M 4L2",
    "addr:housenumber":"2231",
    "addr:postcode":"t2m 4l2",
    "addr:street":"Banff Trail Nw",
    "iso:country":"CA",
    "sg:address":"2231 Banff Trail NW",
    "sg:city":"Calgary",
    "sg:classifiers":[
        {
            "category":"Travel",
            "subcategory":"Hotels & Motels",
            "type":"Entertainment"
        }
    ],
    "sg:phone":"+1 403 289 1921",
    "sg:postcode":"T2M 4L2",
    "sg:province":"AB",
    "wof:name":"Econo Lodge Banff Trail",
    "wof:placetype":"venue"
},
  "geometry": {"coordinates":[-114.113472,51.067757],"type":"Point"}
}