{
  "type": "Feature",
  "properties": {
    "addr:full":"3225 Henderson Hwy East St Paul MB R2E 0J2",
    "addr:housenumber":"3225",
    "addr:postcode":"r2e 0j2",
    "addr:street":"Henderson Hwy",
    "iso:country":"CA",
    "sg:address":"3225 Henderson Hwy",
    "sg:city":"East St Paul",
    "sg:classifiers":[
        {
            "category":"Education",
            "subcategory":"School",
            "type":"Public Place"
        }
    ],
    "sg:phone":"+1 204 661 2500",
    "sg:postcode":"R2E 0J2",
    "sg:province":"MB",
    "wof:name":"Dr Fwl Hamilton School",
    "wof:placetype":"venue"
},
  "geometry": {"coordinates":[-97.0383224487,49.9933662415],"type":"Point"}
}