{
  "type": "Feature",
  "properties": {
    "addr:full":"8320 Boul Decarie Montreal QC H4P 2P5",
    "addr:housenumber":"8320",
    "addr:postcode":"h4p 2p5",
    "addr:street":"Boul Decarie",
    "iso:country":"CA",
    "sg:address":"8320 Boul Decarie",
    "sg:city":"Montreal",
    "sg:classifiers":[
        {
            "category":"Wholesale",
            "subcategory":"Apparel",
            "type":"Manufacturing & Wholesale Goods"
        }
    ],
    "sg:phone":"+1 514 735 1898",
    "sg:postcode":"H4P 2P5",
    "sg:province":"QC",
    "sg:tags":[
        "handbag"
    ],
    "wof:name":"Veneto Imports Ltd",
    "wof:placetype":"venue"
},
  "geometry": {"coordinates":[-73.662384,45.499828],"type":"Point"}
}