{
  "type": "Feature",
  "properties": {
    "addr:full":"5445 Lakeshore Rd Kelowna BC V1W 4S5",
    "addr:housenumber":"5445",
    "addr:postcode":"v1w 4s5",
    "addr:street":"Lakeshore Rd",
    "iso:country":"CA",
    "sg:address":"5445 Lakeshore Rd",
    "sg:city":"Kelowna",
    "sg:classifiers":[
        {
            "category":"Manufacturing",
            "subcategory":"Food",
            "type":"Manufacturing & Wholesale Goods"
        }
    ],
    "sg:phone":"+1 250 764 8866",
    "sg:postcode":"V1W 4S5",
    "sg:province":"BC",
    "sg:tags":[
        "winery"
    ],
    "wof:name":"Cedarcreek Estate Winery",
    "wof:placetype":"venue"
},
  "geometry": {"coordinates":[-119.54520416299999,49.7890777588],"type":"Point"}
}