{
  "type": "Feature",
  "properties": {
    "addr:full":"3229 Sparks St Terrace BC V8G 2T6",
    "addr:housenumber":"3229",
    "addr:postcode":"v8g 2t6",
    "addr:street":"Sparks St Terrace",
    "iso:country":"CA",
    "sg:address":"3229 Sparks St",
    "sg:city":"Terrace",
    "sg:classifiers":[
        {
            "category":"Organizations",
            "subcategory":"Religious Organization",
            "type":"Services"
        }
    ],
    "sg:phone":"+1 250 635 5520",
    "sg:postcode":"V8G 2T6",
    "sg:province":"BC",
    "sg:tags":[
        "church"
    ],
    "wof:name":"Lutheran Church Christ",
    "wof:placetype":"venue"
},
  "geometry": {"coordinates":[-128.592896,54.516014],"type":"Point"}
}