{
  "type": "Feature",
  "properties": {
    "addr:full":"1217 Glenora Dr London ON N5X 2P6",
    "addr:housenumber":"1217",
    "addr:postcode":"n5x 2p6",
    "addr:street":"Glenora Dr",
    "iso:country":"CA",
    "sg:address":"1217 Glenora Dr",
    "sg:city":"London",
    "sg:classifiers":[
        {
            "category":"Professional",
            "subcategory":"Accounting & Tax Preparation",
            "type":"Services"
        }
    ],
    "sg:phone":"+1 519 433 9595",
    "sg:postcode":"N5X 2P6",
    "sg:province":"ON",
    "sg:tags":[
        "accountant"
    ],
    "wof:name":"Ssy Lee Accounting",
    "wof:placetype":"venue"
},
  "geometry": {"coordinates":[-81.24608600000001,43.030865],"type":"Point"}
}