{
  "type": "Feature",
  "properties": {
    "iso:country":"CA",
    "sg:address":"112 Boul Colonia",
    "sg:city":"Repentigny",
    "sg:classifiers":[
        {
            "category":"Building & Trades",
            "subcategory":"Construction",
            "type":"Services"
        }
    ],
    "sg:phone":"+1 450 581 2173",
    "sg:postcode":"J6A 3R1",
    "sg:province":"QC",
    "sg:tags":[
        "plumbing",
        "sewer",
        "contractor"
    ],
    "wof:name":"Cote & Fils Enr",
    "wof:placetype":"venue"
},
  "geometry": {"coordinates":[-73.476997,45.729755],"type":"Point"}
}