{
  "type": "Feature",
  "properties": {
    "addr:full":"1330 Rue Volta Boucherville QC J4B 6G6",
    "addr:housenumber":"1330",
    "addr:postcode":"j4b 6g6",
    "addr:street":"Rue Volta",
    "iso:country":"CA",
    "sg:address":"1330 Rue Volta",
    "sg:city":"Boucherville",
    "sg:classifiers":[
        {
            "category":"Manufacturing",
            "subcategory":"Food",
            "type":"Manufacturing & Wholesale Goods"
        }
    ],
    "sg:phone":"+1 450 641 9090",
    "sg:postcode":"J4B 6G6",
    "sg:province":"QC",
    "sg:tags":[
        "colors",
        "pigment"
    ],
    "wof:name":"Kohnstamm Inc",
    "wof:placetype":"venue"
},
  "geometry": {"coordinates":[-73.440971,45.562916],"type":"Point"}
}