{
  "type": "Feature",
  "properties": {
    "addr:full":"2116 9 Ave S Lethbridge AB T1J 1X3",
    "addr:housenumber":"2116",
    "addr:postcode":"t1j 1x3",
    "addr:street":"9 Ave S",
    "iso:country":"CA",
    "sg:address":"2116 9 Ave S",
    "sg:city":"Lethbridge",
    "sg:classifiers":[
        {
            "category":"Building & Trades",
            "subcategory":"Construction",
            "type":"Services"
        }
    ],
    "sg:phone":"+1 403 327 2816",
    "sg:postcode":"T1J 1X3",
    "sg:province":"AB",
    "sg:tags":[
        "painter"
    ],
    "wof:name":"A & A Painting",
    "wof:placetype":"venue"
},
  "geometry": {"coordinates":[-112.81086731000001,49.6864929199],"type":"Point"}
}