{
  "type": "Feature",
  "properties": {
    "addr:full":"Richmond BC V7C 4R9",
    "addr:postcode":"v7c 4r9",
    "iso:country":"CA",
    "sg:city":"Richmond",
    "sg:classifiers":[
        {
            "category":"Professional",
            "subcategory":"Management & Consulting",
            "type":"Services"
        }
    ],
    "sg:phone":"+1 604 278 3538",
    "sg:postcode":"V7C 4R9",
    "sg:province":"BC",
    "sg:tags":[
        "aviation",
        "consultant"
    ],
    "wof:name":"Robert K Phillips Ltd",
    "wof:placetype":"venue"
},
  "geometry": {"coordinates":[-123.15845489500001,49.170539856],"type":"Point"}
}