{
  "type": "Feature",
  "properties": {
    "addr:full":"2728 Boul Du Cure-Labelle Prevost QC J0R 1T0",
    "addr:housenumber":"2728",
    "addr:postcode":"j0r 1t0",
    "addr:street":"Boul Du Cure-Labelle Prevost",
    "iso:country":"CA",
    "sg:address":"2728 Boul Du Cure-Labelle",
    "sg:city":"Prevost",
    "sg:classifiers":[
        {
            "category":"Retail",
            "subcategory":"Repair Shop",
            "type":"Services"
        }
    ],
    "sg:phone":"+1 450 224 2231",
    "sg:postcode":"J0R 1T0",
    "sg:province":"QC",
    "sg:tags":[
        "upholsterer"
    ],
    "wof:name":"Rembourrage Du Nord",
    "wof:placetype":"venue"
},
  "geometry": {"coordinates":[-74.06493377690001,45.8486480713],"type":"Point"}
}