{
  "type": "Feature",
  "properties": {
    "addr:full":"Les Eboulements QC G0A 2M0",
    "addr:postcode":"g0a 2m0",
    "iso:country":"CA",
    "sg:city":"Les Eboulements",
    "sg:classifiers":[
        {
            "category":"Professional",
            "subcategory":"Business Services",
            "type":"Services"
        }
    ],
    "sg:phone":"+1 418 635 1302",
    "sg:postcode":"G0A 2M0",
    "sg:province":"QC",
    "wof:name":"Textes Impeccables Inc",
    "wof:placetype":"venue"
},
  "geometry": {"coordinates":[-70.3170547485,47.4791564941],"type":"Point"}
}