{
  "type": "Feature",
  "properties": {
    "addr:full":"Jordan St Plumas MB R0J 1P0",
    "addr:postcode":"r0j 1p0",
    "addr:street":"Jordan St",
    "iso:country":"CA",
    "sg:address":"Jordan St",
    "sg:city":"Plumas",
    "sg:classifiers":[
        {
            "category":"Organizations",
            "subcategory":"Religious Organization",
            "type":"Services"
        }
    ],
    "sg:phone":"+1 204 386 2621",
    "sg:postcode":"R0J 1P0",
    "sg:province":"MB",
    "sg:tags":[
        "church"
    ],
    "wof:name":"Zion Lutheran Church",
    "wof:placetype":"venue"
},
  "geometry": {"coordinates":[-99.086365,50.384617],"type":"Point"}
}