{
  "type": "Feature",
  "properties": {
    "addr:full":"1398 Pembroke St W Pembroke ON K8A 7M3",
    "addr:housenumber":"1398",
    "addr:postcode":"k8a 7m3",
    "addr:street":"Pembroke St W",
    "iso:country":"CA",
    "sg:address":"1398 Pembroke St W",
    "sg:city":"Pembroke",
    "sg:classifiers":[
        {
            "category":"Autos & Motor Vehicles",
            "subcategory":"Automobile Sales",
            "type":"Retail Goods"
        }
    ],
    "sg:phone":"+1 613 735 0634",
    "sg:postcode":"K8A 7M3",
    "sg:province":"ON",
    "sg:tags":[
        "car",
        "dealer"
    ],
    "wof:name":"Lapointe Brothers Chrysler",
    "wof:placetype":"venue"
},
  "geometry": {"coordinates":[-77.15371704099999,45.8348808289],"type":"Point"}
}