{
  "type": "Feature",
  "properties": {
    "iso:country":"CA",
    "sg:address":"824 6 St SE",
    "sg:city":"Redcliff",
    "sg:classifiers":[
        {
            "category":"Retail",
            "subcategory":"Repair Shop",
            "type":"Services"
        }
    ],
    "sg:phone":"+1 403 548 2882",
    "sg:postcode":"T0J 2P0",
    "sg:province":"AB",
    "sg:tags":[
        "blacksmith"
    ],
    "wof:name":"Circle C Farrier Svc",
    "wof:placetype":"venue"
},
  "geometry": {"coordinates":[-110.780563355,50.0652885437],"type":"Point"}
}