{
  "type": "Feature",
  "properties": {
    "addr:full":"7420 Bren Rd Mississauga ON L4T 1H4",
    "addr:housenumber":"7420",
    "addr:postcode":"l4t 1h4",
    "addr:street":"Bren Rd",
    "iso:country":"CA",
    "sg:address":"7420 Bren Rd",
    "sg:city":"Mississauga",
    "sg:classifiers":[
        {
            "category":"Wholesale",
            "subcategory":"Meat",
            "type":"Manufacturing & Wholesale Goods"
        }
    ],
    "sg:phone":"+1 905 405 8833",
    "sg:postcode":"L4T 1H4",
    "sg:province":"ON",
    "sg:tags":[
        "broker"
    ],
    "wof:name":"Mtl Trading Inc",
    "wof:placetype":"venue"
},
  "geometry": {"coordinates":[-79.66091918950001,43.7058067322],"type":"Point"}
}