{
  "type": "Feature",
  "properties": {
    "addr:full":"206 Bank St Ottawa ON K2P 1W8",
    "addr:housenumber":"206",
    "addr:postcode":"k2p 1w8",
    "addr:street":"Bank St",
    "iso:country":"CA",
    "sg:address":"206 Bank St",
    "sg:city":"Ottawa",
    "sg:classifiers":[
        {
            "category":"Shopping",
            "subcategory":"Florist",
            "type":"Retail Goods"
        }
    ],
    "sg:phone":"+1 613 238 1430",
    "sg:postcode":"K2P 1W8",
    "sg:province":"ON",
    "wof:name":"Allen's Flowers By Les Estes",
    "wof:placetype":"venue"
},
  "geometry": {"coordinates":[-75.698364,45.417423],"type":"Point"}
}