{
  "type": "Feature",
  "properties": {
    "addr:full":"7887 49 Ave Red Deer AB T4P 2B4",
    "addr:housenumber":"7887",
    "addr:postcode":"t4p 2b4",
    "addr:street":"49 Ave",
    "iso:country":"CA",
    "sg:address":"7887 49 Ave",
    "sg:city":"Red Deer",
    "sg:classifiers":[
        {
            "category":"Professional",
            "subcategory":"Detective & Security Services",
            "type":"Services"
        }
    ],
    "sg:phone":"+1 403 314 5433",
    "sg:postcode":"T4P 2B4",
    "sg:province":"AB",
    "sg:tags":[
        "car",
        "armored"
    ],
    "wof:name":"Securicor Cash Svc",
    "wof:placetype":"venue"
},
  "geometry": {"coordinates":[-113.813827515,52.2885017395],"type":"Point"}
}