{
  "type": "Feature",
  "properties": {
    "iso:country":"CA",
    "sg:address":"5625 King Rd",
    "sg:city":"Nobleton",
    "sg:classifiers":[
        {
            "category":"Retail",
            "subcategory":"Auto Repair",
            "type":"Services"
        }
    ],
    "sg:phone":"+1 905 859 0817",
    "sg:postcode":"L0G 1N0",
    "sg:province":"ON",
    "sg:tags":[
        "wrecker"
    ],
    "wof:name":"King Road Auto Inc",
    "wof:placetype":"venue"
},
  "geometry": {"coordinates":[-79.6402359009,43.9040908813],"type":"Point"}
}