{
  "type": "Feature",
  "properties": {
    "addr:full":"883 Rang St Thomas Embrun ON K0A 1W0",
    "addr:housenumber":"883",
    "addr:postcode":"k0a 1w0",
    "addr:street":"Rang St Thomas",
    "iso:country":"CA",
    "sg:address":"883 Rang St Thomas",
    "sg:city":"Embrun",
    "sg:classifiers":[
        {
            "category":"Freight",
            "type":"Transportation"
        }
    ],
    "sg:phone":"+1 613 443 6697",
    "sg:postcode":"K0A 1W0",
    "sg:province":"ON",
    "sg:tags":[
        "mover"
    ],
    "wof:name":"Anthony's Demenagement",
    "wof:placetype":"venue"
},
  "geometry": {"coordinates":[-75.26976000000001,45.299595],"type":"Point"}
}