{
  "type": "Feature",
  "properties": {
    "addr:full":"3891 Ch Du Lac Saint-Norbert QC J0K 3C0",
    "addr:postcode":"3891;j0k 3c0",
    "addr:street":"Ch Du Lac",
    "iso:country":"CA",
    "sg:address":"3891 Ch Du Lac",
    "sg:city":"Saint-Norbert",
    "sg:classifiers":[
        {
            "category":"Manufacturing",
            "subcategory":"Tools & Machinery",
            "type":"Manufacturing & Wholesale Goods"
        }
    ],
    "sg:phone":"+1 450 835 9009",
    "sg:postcode":"J0K 3C0",
    "sg:province":"QC",
    "sg:tags":[
        "machine",
        "shop"
    ],
    "wof:name":"Atelier Mobile D'Usinage",
    "wof:placetype":"venue"
},
  "geometry": {"coordinates":[-73.332008,46.241745],"type":"Point"}
}