{
  "type": "Feature",
  "properties": {
    "addr:full":"5920 No. 2 Rd # 130 Richmond BC V7C 4R9",
    "addr:housenumber":"130",
    "addr:postcode":"5920;v7c 4r9",
    "addr:street":"2 Rd #",
    "iso:country":"CA",
    "sg:address":"5920 No. 2 Rd # 130",
    "sg:city":"Richmond",
    "sg:classifiers":[
        {
            "category":"Professional",
            "subcategory":"Business Services",
            "type":"Services"
        }
    ],
    "sg:phone":"+1 604 244 1672",
    "sg:postcode":"V7C 4R9",
    "sg:province":"BC",
    "sg:tags":[
        "event"
    ],
    "wof:name":"Zeco Inc",
    "wof:placetype":"venue"
},
  "geometry": {"coordinates":[-123.158455,49.17054],"type":"Point"}
}