{
  "type": "Feature",
  "properties": {
    "iso:country":"CA",
    "sg:address":"5359 Canotek Rd",
    "sg:city":"Gloucester",
    "sg:classifiers":[
        {
            "category":"Professional",
            "subcategory":"Business Services",
            "type":"Services"
        }
    ],
    "sg:phone":"+1 613 523 3672",
    "sg:postcode":"K1J 9E5",
    "sg:province":"ON",
    "sg:tags":[
        "equipment",
        "microfilming"
    ],
    "wof:name":"Wow Document Mgmt Svc",
    "wof:placetype":"venue"
},
  "geometry": {"coordinates":[-75.582321167,45.4566726685],"type":"Point"}
}