{
  "type": "Feature",
  "properties": {
    "iso:country":"CA",
    "sg:address":"950 Rue Mill",
    "sg:city":"Montreal",
    "sg:classifiers":[
        {
            "category":"Manufacturing",
            "subcategory":"Pet Food",
            "type":"Manufacturing & Wholesale Goods"
        }
    ],
    "sg:phone":"+1 514 846 8533",
    "sg:postcode":"H3C 1Y4",
    "sg:province":"QC",
    "sg:tags":[
        "flour",
        "mills"
    ],
    "wof:name":"Minoteries Adm",
    "wof:placetype":"venue"
},
  "geometry": {"coordinates":[-73.5511627197,45.4923782349],"type":"Point"}
}