{
  "type": "Feature",
  "properties": {
    "addr:full":"2927 Churchill Rd Falkland BC V0E 1W0",
    "addr:housenumber":"2927",
    "addr:postcode":"v0e 1w0",
    "addr:street":"Churchill Rd",
    "iso:country":"CA",
    "sg:address":"2927 Churchill Rd",
    "sg:city":"Falkland",
    "sg:classifiers":[
        {
            "category":"Building & Trades",
            "subcategory":"Construction",
            "type":"Services"
        }
    ],
    "sg:phone":"+1 250 379 2232",
    "sg:postcode":"V0E 1W0",
    "sg:province":"BC",
    "sg:tags":[
        "downspouts",
        "gutter"
    ],
    "wof:name":"J & S Gutter Systems",
    "wof:placetype":"venue"
},
  "geometry": {"coordinates":[-119.55555,50.501141],"type":"Point"}
}