{
  "type": "Feature",
  "properties": {
    "addr:full":"4000 Mainway Burlington ON L7M 4B9",
    "addr:housenumber":"4000",
    "addr:postcode":"l7m 4b9",
    "addr:street":"Mainway",
    "iso:country":"CA",
    "sg:address":"4000 Mainway",
    "sg:city":"Burlington",
    "sg:classifiers":[
        {
            "category":"Restaurant",
            "type":"Food & Drink"
        }
    ],
    "sg:phone":"+1 905 336 9232",
    "sg:postcode":"L7M 4B9",
    "sg:province":"ON",
    "wof:name":"Wendy's",
    "wof:placetype":"venue"
},
  "geometry": {"coordinates":[-79.795158,43.372116],"type":"Point"}
}