{
  "type": "Feature",
  "properties": {
    "addr:full":"297 Reeves St Port Hawkesbury NS B9A 2B6",
    "addr:housenumber":"297",
    "addr:postcode":"b9a 2b6",
    "addr:street":"Reeves St",
    "iso:country":"CA",
    "sg:address":"297 Reeves St",
    "sg:city":"Port Hawkesbury",
    "sg:classifiers":[
        {
            "category":"Restaurant",
            "type":"Food & Drink"
        }
    ],
    "sg:phone":"+1 902 625 1200",
    "sg:postcode":"B9A 2B6",
    "sg:province":"NS",
    "wof:name":"Subway Sandwiches & Salads",
    "wof:placetype":"venue"
},
  "geometry": {"coordinates":[-61.3584060669,45.6182479858],"type":"Point"}
}