{
  "type": "Feature",
  "properties": {
    "addr:full":"PO Box 293 Acme AB T0M 0A0",
    "addr:housenumber":"po",
    "addr:postcode":"t0m 0a0",
    "addr:street":"Box 293 Acme",
    "iso:country":"CA",
    "sg:address":"PO Box 293",
    "sg:city":"Acme",
    "sg:classifiers":[
        {
            "category":"Organizations",
            "subcategory":"Religious Organization",
            "type":"Services"
        }
    ],
    "sg:phone":"+1 403 546 3922",
    "sg:postcode":"T0M 0A0",
    "sg:province":"AB",
    "sg:tags":[
        "church"
    ],
    "wof:name":"Acme United Church",
    "wof:placetype":"venue"
},
  "geometry": {"coordinates":[-113.50789642300001,51.495765686],"type":"Point"}
}