{
  "type": "Feature",
  "properties": {
    "iso:country":"CA",
    "sg:address":"346 Poplar Bay",
    "sg:city":"Estevan",
    "sg:classifiers":[
        {
            "category":"Mining & Drilling",
            "type":"Manufacturing & Wholesale Goods"
        }
    ],
    "sg:phone":"+1 306 634 8500",
    "sg:postcode":"S4A 2C4",
    "sg:province":"SK",
    "sg:tags":[
        "oil",
        "well"
    ],
    "wof:name":"Lavoie Mobile Cleaning Ltd",
    "wof:placetype":"venue"
},
  "geometry": {"coordinates":[-102.976028442,49.1476173401],"type":"Point"}
}