{
  "type": "Feature",
  "properties": {
    "addr:full":"391 Adelaide St W Toronto ON M5V 1S6",
    "addr:housenumber":"391",
    "addr:postcode":"m5v 1s6",
    "addr:street":"Adelaide St W",
    "iso:country":"CA",
    "sg:address":"391 Adelaide St W",
    "sg:city":"Toronto",
    "sg:classifiers":[
        {
            "category":"Manufacturing",
            "subcategory":"Furniture",
            "type":"Manufacturing & Wholesale Goods"
        }
    ],
    "sg:phone":"+1 416 504 4551",
    "sg:postcode":"M5V 1S6",
    "sg:province":"ON",
    "sg:tags":[
        "fixture",
        "store"
    ],
    "wof:name":"William Prager Ltd",
    "wof:placetype":"venue"
},
  "geometry": {"coordinates":[-79.39653800000001,43.646408],"type":"Point"}
}