{
  "type": "Feature",
  "properties": {
    "addr:full":"Winnipeg MB R3T 5J7",
    "addr:postcode":"r3t 5j7",
    "iso:country":"CA",
    "sg:city":"Winnipeg",
    "sg:classifiers":[
        {
            "category":"Real Estate",
            "subcategory":"Real Estate Operator",
            "type":"Services"
        }
    ],
    "sg:phone":"+1 204 269 9509",
    "sg:postcode":"R3T 5J7",
    "sg:province":"MB",
    "sg:tags":[
        "apartment"
    ],
    "wof:name":"Bairdmore Estates",
    "wof:placetype":"venue"
},
  "geometry": {"coordinates":[-97.1590270996,49.7810211182],"type":"Point"}
}