{
  "type": "Feature",
  "properties": {
    "addr:full":"278 Boul Valcartier Loretteville QC G2A 2N1",
    "addr:housenumber":"278",
    "addr:postcode":"g2a 2n1",
    "addr:street":"Boul Valcartier",
    "iso:country":"CA",
    "sg:address":"278 Boul Valcartier",
    "sg:city":"Loretteville",
    "sg:classifiers":[
        {
            "category":"Travel",
            "subcategory":"Campground",
            "type":"Entertainment"
        }
    ],
    "sg:phone":"+1 418 843 1532",
    "sg:postcode":"G2A 2N1",
    "sg:province":"QC",
    "sg:tags":[
        "camp"
    ],
    "wof:name":"Camp Tekakwitha Inc",
    "wof:placetype":"venue"
},
  "geometry": {"coordinates":[-71.365639,46.857948],"type":"Point"}
}