{
  "type": "Feature",
  "properties": {
    "iso:country":"CA",
    "sg:address":"390 Av Brochu",
    "sg:city":"Sept-Iles",
    "sg:classifiers":[
        {
            "category":"Banks & Credit Unions",
            "subcategory":"Investment Brokerage",
            "type":"Services"
        }
    ],
    "sg:phone":"+1 418 968 4600",
    "sg:postcode":"G4R 2W6",
    "sg:province":"QC",
    "wof:name":"Bmo Nesbitt Burns Inc",
    "wof:placetype":"venue"
},
  "geometry": {"coordinates":[-66.3832015991,50.2049026489],"type":"Point"}
}