{
  "type": "Feature",
  "properties": {
    "addr:full":"92 John St N Hamilton ON L8R 1H6",
    "addr:housenumber":"92",
    "addr:postcode":"l8r 1h6",
    "addr:street":"John St N",
    "iso:country":"CA",
    "sg:address":"92 John St N",
    "sg:city":"Hamilton",
    "sg:classifiers":[
        {
            "category":"Education",
            "subcategory":"Special Training",
            "type":"Public Place"
        }
    ],
    "sg:phone":"+1 905 526 9470",
    "sg:postcode":"L8R 1H6",
    "sg:province":"ON",
    "sg:tags":[
        "instruction",
        "music"
    ],
    "wof:name":"Wow Studio",
    "wof:placetype":"venue"
},
  "geometry": {"coordinates":[-79.86529541020001,43.2583465576],"type":"Point"}
}