{
  "type": "Feature",
  "properties": {
    "iso:country":"CA",
    "sg:address":"1651 Park St",
    "sg:city":"Regina",
    "sg:classifiers":[
        {
            "category":"Manufacturing",
            "subcategory":"Printing",
            "type":"Manufacturing & Wholesale Goods"
        }
    ],
    "sg:phone":"+1 306 721 4111",
    "sg:postcode":"S4N 5A2",
    "sg:province":"SK",
    "sg:tags":[
        "printer"
    ],
    "wof:name":"Hi-Tech Printing & Copies Ltd",
    "wof:placetype":"venue"
},
  "geometry": {"coordinates":[-104.571975708,50.4526824951],"type":"Point"}
}