{
  "type": "Feature",
  "properties": {
    "addr:full":"Gatineau QC J8T 6G4",
    "addr:postcode":"j8t 6g4",
    "iso:country":"CA",
    "sg:city":"Gatineau",
    "sg:classifiers":[
        {
            "category":"Professional",
            "subcategory":"Lawyer & Legal Services",
            "type":"Services"
        }
    ],
    "sg:phone":"+1 819 568 9861",
    "sg:postcode":"J8T 6G4",
    "sg:province":"QC",
    "sg:tags":[
        "attorney"
    ],
    "wof:name":"Isabelle Patenaude Law Offices",
    "wof:placetype":"venue"
},
  "geometry": {"coordinates":[-75.710487,45.427853],"type":"Point"}
}