{
  "type": "Feature",
  "properties": {
    "addr:full":"400 Huron St Stratford ON N5A 5T5",
    "addr:housenumber":"400",
    "addr:postcode":"n5a 5t5",
    "addr:street":"Huron St",
    "iso:country":"CA",
    "sg:address":"400 Huron St",
    "sg:city":"Stratford",
    "sg:classifiers":[
        {
            "category":"Organizations",
            "subcategory":"Professional Association",
            "type":"Services"
        }
    ],
    "sg:phone":"+1 519 273 3450",
    "sg:postcode":"N5A 5T5",
    "sg:province":"ON",
    "wof:name":"West End Ctr",
    "wof:placetype":"venue"
},
  "geometry": {"coordinates":[-80.997147,43.378216],"type":"Point"}
}