{
  "type": "Feature",
  "properties": {
    "addr:full":"5740 Hillcrest Cres Niagara Falls ON L2J 2A7",
    "addr:housenumber":"5740",
    "addr:postcode":"l2j 2a7",
    "addr:street":"Hillcrest Cres",
    "iso:country":"CA",
    "sg:address":"5740 Hillcrest Cres",
    "sg:city":"Niagara Falls",
    "sg:classifiers":[
        {
            "category":"Social Services",
            "type":"Services"
        }
    ],
    "sg:phone":"+1 905 357 2380",
    "sg:postcode":"L2J 2A7",
    "sg:province":"ON",
    "sg:tags":[
        "organization",
        "welfare"
    ],
    "wof:name":"Childhood Asthma Foundation",
    "wof:placetype":"venue"
},
  "geometry": {"coordinates":[-79.090187,43.13343],"type":"Point"}
}