{
  "type": "Feature",
  "properties": {
    "addr:full":"1280 Aimco Blvd Mississauga ON L4W 1B2",
    "addr:housenumber":"1280",
    "addr:postcode":"l4w 1b2",
    "addr:street":"Aimco Blvd",
    "iso:country":"CA",
    "sg:address":"1280 Aimco Blvd",
    "sg:city":"Mississauga",
    "sg:classifiers":[
        {
            "category":"Wholesale",
            "subcategory":"Machinery & Supplies",
            "type":"Manufacturing & Wholesale Goods"
        }
    ],
    "sg:phone":"+1 905 624 9546",
    "sg:postcode":"L4W 1B2",
    "sg:province":"ON",
    "sg:tags":[
        "equipment",
        "industrial"
    ],
    "wof:name":"Windsor Factory Supply",
    "wof:placetype":"venue"
},
  "geometry": {"coordinates":[-79.6281661987,43.6349639893],"type":"Point"}
}