{
  "type": "Feature",
  "properties": {
    "addr:full":"Ottawa ON K1K 3B8",
    "addr:postcode":"k1k 3b8",
    "iso:country":"CA",
    "sg:city":"Ottawa",
    "sg:classifiers":[
        {
            "category":"Shopping",
            "subcategory":"Optical Goods",
            "type":"Retail Goods"
        }
    ],
    "sg:phone":"+1 613 747 7498",
    "sg:postcode":"K1K 3B8",
    "sg:province":"ON",
    "sg:tags":[
        "sun",
        "goggles",
        "sunglasses"
    ],
    "wof:name":"Sunglass Hut",
    "wof:placetype":"venue"
},
  "geometry": {"coordinates":[-75.63739013670001,45.4238433838],"type":"Point"}
}