{
  "type": "Feature",
  "properties": {
    "addr:full":"10303 Boul Perras Montreal QC H1C 2A3",
    "addr:housenumber":"10303",
    "addr:postcode":"h1c 2a3",
    "addr:street":"Boul Perras",
    "iso:country":"CA",
    "sg:address":"10303 Boul Perras",
    "sg:city":"Montreal",
    "sg:classifiers":[
        {
            "category":"Building & Trades",
            "subcategory":"Construction",
            "type":"Services"
        }
    ],
    "sg:phone":"+1 514 648 3690",
    "sg:postcode":"H1C 2A3",
    "sg:province":"QC",
    "sg:tags":[
        "resurfacing",
        "laying",
        "refinishing",
        "floor"
    ],
    "wof:name":"Sablage DE Planchers Renaud",
    "wof:placetype":"venue"
},
  "geometry": {"coordinates":[-73.5547866821,45.6647109985],"type":"Point"}
}