{
  "type": "Feature",
  "properties": {
    "addr:full":"161 Water St Summerside PE C1N 1B2",
    "addr:housenumber":"161",
    "addr:postcode":"c1n 1b2",
    "addr:street":"Water St",
    "iso:country":"CA",
    "sg:address":"161 Water St",
    "sg:city":"Summerside",
    "sg:classifiers":[
        {
            "category":"Retail",
            "subcategory":"Auto Repair",
            "type":"Services"
        }
    ],
    "sg:phone":"+1 902 436 6400",
    "sg:postcode":"C1N 1B2",
    "sg:province":"PE",
    "sg:tags":[
        "repairing",
        "automobile"
    ],
    "wof:name":"Meineke Discount Mufflers",
    "wof:placetype":"venue"
},
  "geometry": {"coordinates":[-63.786484,46.390858],"type":"Point"}
}