{
  "type": "Feature",
  "properties": {
    "addr:full":"836 Main Lillooet BC V0K 1V0",
    "addr:housenumber":"836",
    "addr:postcode":"v0k 1v0",
    "addr:street":"Main",
    "iso:country":"CA",
    "sg:address":"836 Main",
    "sg:city":"Lillooet",
    "sg:classifiers":[
        {
            "category":"Professional",
            "subcategory":"Accounting & Tax Preparation",
            "type":"Services"
        }
    ],
    "sg:phone":"+1 250 256 4411",
    "sg:postcode":"V0K 1V0",
    "sg:province":"BC",
    "sg:tags":[
        "accountant",
        "return",
        "filing"
    ],
    "wof:name":"H & R Block Canada Inc",
    "wof:placetype":"venue"
},
  "geometry": {"coordinates":[-121.93284606900001,50.6827888489],"type":"Point"}
}