{
  "type": "Feature",
  "properties": {
    "addr:full":"Quebec QC G1L 2W1",
    "addr:postcode":"g1l 2w1",
    "iso:country":"CA",
    "sg:city":"Quebec",
    "sg:classifiers":[
        {
            "category":"Social Services",
            "subcategory":"Job Training",
            "type":"Services"
        }
    ],
    "sg:phone":"+1 418 648 0044",
    "sg:postcode":"G1L 2W1",
    "sg:province":"QC",
    "sg:tags":[
        "employment",
        "resume"
    ],
    "wof:name":"Libre Emploi",
    "wof:placetype":"venue"
},
  "geometry": {"coordinates":[-71.226196,46.822845],"type":"Point"}
}