{
  "type": "Feature",
  "properties": {
    "addr:full":"3 2nd Ave SW Weyburn SK S4H 2J3",
    "addr:housenumber":"3",
    "addr:postcode":"s4h 2j3",
    "addr:street":"2Nd Ave Sw",
    "iso:country":"CA",
    "sg:address":"3 2nd Ave SW",
    "sg:city":"Weyburn",
    "sg:classifiers":[
        {
            "category":"Travel",
            "subcategory":"Hotels & Motels",
            "type":"Entertainment"
        }
    ],
    "sg:phone":"+1 306 842 4647",
    "sg:postcode":"S4H 2J3",
    "sg:province":"SK",
    "wof:name":"Motel 385",
    "wof:placetype":"venue"
},
  "geometry": {"coordinates":[-103.858368,49.65749],"type":"Point"}
}