{
  "type": "Feature",
  "properties": {
    "iso:country":"CA",
    "sg:address":"35 Cardico Dr",
    "sg:city":"Gormley",
    "sg:classifiers":[
        {
            "category":"Building & Trades",
            "subcategory":"Construction",
            "type":"Services"
        }
    ],
    "sg:phone":"+1 905 888 9777",
    "sg:postcode":"L0H 1G0",
    "sg:province":"ON",
    "sg:tags":[
        "paving",
        "contractor"
    ],
    "wof:name":"Mopal Construction",
    "wof:placetype":"venue"
},
  "geometry": {"coordinates":[-79.38485,43.954288],"type":"Point"}
}