{
  "type": "Feature",
  "properties": {
    "addr:full":"Richmond BC V6V 2W3",
    "addr:postcode":"v6v 2w3",
    "iso:country":"CA",
    "sg:city":"Richmond",
    "sg:classifiers":[
        {
            "category":"Wholesale",
            "subcategory":"Durable Goods & Equipment",
            "type":"Manufacturing & Wholesale Goods"
        }
    ],
    "sg:phone":"+1 604 270 0889",
    "sg:postcode":"V6V 2W3",
    "sg:province":"BC",
    "sg:tags":[
        "importer"
    ],
    "wof:name":"Century Trading CO Ltd",
    "wof:placetype":"venue"
},
  "geometry": {"coordinates":[-122.992622,49.169205],"type":"Point"}
}