{
  "type": "Feature",
  "properties": {
    "addr:full":"401 Knowlton Rd Knowlton QC J0E 1V0",
    "addr:housenumber":"401",
    "addr:postcode":"j0e 1v0",
    "addr:street":"Knowlton Rd",
    "iso:country":"CA",
    "sg:address":"401 Knowlton Rd",
    "sg:city":"Knowlton",
    "sg:classifiers":[
        {
            "category":"Health Services",
            "subcategory":"Nursing And Care Facility",
            "type":"Services"
        }
    ],
    "sg:phone":"+1 450 242 1621",
    "sg:postcode":"J0E 1V0",
    "sg:province":"QC",
    "sg:tags":[
        "home",
        "rest"
    ],
    "wof:name":"Maison Knowlton House Inc",
    "wof:placetype":"venue"
},
  "geometry": {"coordinates":[-72.52140799999999,45.216667],"type":"Point"}
}