{
  "type": "Feature",
  "properties": {
    "addr:full":"1704 61 St SE Calgary AB T2A 4V5",
    "addr:housenumber":"1704",
    "addr:postcode":"t2a 4v5",
    "addr:street":"61 St Se",
    "iso:country":"CA",
    "sg:address":"1704 61 St SE",
    "sg:city":"Calgary",
    "sg:classifiers":[
        {
            "category":"Bars & Pubs",
            "type":"Food & Drink"
        }
    ],
    "sg:phone":"+1 403 235 3232",
    "sg:postcode":"T2A 4V5",
    "sg:province":"AB",
    "wof:name":"Boddums Up Pub",
    "wof:placetype":"venue"
},
  "geometry": {"coordinates":[-113.942589,51.038757],"type":"Point"}
}