{
  "type": "Feature",
  "properties": {
    "addr:full":"119 Broadway Ave W Pilot Mound MB R0G 1P0",
    "addr:housenumber":"119",
    "addr:postcode":"r0g 1p0",
    "addr:street":"Broadway Ave W Pilot Mound",
    "iso:country":"CA",
    "sg:address":"119 Broadway Ave W",
    "sg:city":"Pilot Mound",
    "sg:classifiers":[
        {
            "category":"Professional",
            "subcategory":"Accounting & Tax Preparation",
            "type":"Services"
        }
    ],
    "sg:phone":"+1 204 825 2164",
    "sg:postcode":"R0G 1P0",
    "sg:province":"MB",
    "sg:tags":[
        "return",
        "filing"
    ],
    "wof:name":"Liberty Tax Svc",
    "wof:placetype":"venue"
},
  "geometry": {"coordinates":[-98.896072,49.202381],"type":"Point"}
}