{
  "type": "Feature",
  "properties": {
    "addr:full":"795 Giles Blvd E Windsor ON N9A 4E5",
    "addr:housenumber":"795",
    "addr:postcode":"n9a 4e5",
    "addr:street":"Giles Blvd E",
    "iso:country":"CA",
    "sg:address":"795 Giles Blvd E",
    "sg:city":"Windsor",
    "sg:classifiers":[
        {
            "category":"Social Services",
            "type":"Services"
        }
    ],
    "sg:phone":"+1 519 252 9696",
    "sg:postcode":"N9A 4E5",
    "sg:province":"ON",
    "sg:tags":[
        "organization",
        "welfare"
    ],
    "wof:name":"St Mary's Family Learning Ctr",
    "wof:placetype":"venue"
},
  "geometry": {"coordinates":[-83.020652771,42.3093147278],"type":"Point"}
}