{
  "type": "Feature",
  "properties": {
    "addr:full":"5 Rue Des Artisans Charlemagne QC J5Z 1B3",
    "addr:housenumber":"5",
    "addr:postcode":"j5z 1b3",
    "addr:street":"Rue Des Artisans",
    "iso:country":"CA",
    "sg:address":"5 Rue Des Artisans",
    "sg:city":"Charlemagne",
    "sg:classifiers":[
        {
            "category":"Building & Trades",
            "subcategory":"Electrical",
            "type":"Services"
        }
    ],
    "sg:phone":"+1 450 581 5085",
    "sg:postcode":"J5Z 1B3",
    "sg:province":"QC",
    "sg:tags":[
        "electric",
        "contractor"
    ],
    "wof:name":"C Latendresse Inc",
    "wof:placetype":"venue"
},
  "geometry": {"coordinates":[-73.4897079468,45.7261962891],"type":"Point"}
}