{
  "type": "Feature",
  "properties": {
    "addr:full":"21308 78 Ave Langley BC V2Y 2E9",
    "addr:housenumber":"21308",
    "addr:postcode":"v2y 2e9",
    "addr:street":"78 Ave",
    "iso:country":"CA",
    "sg:address":"21308 78 Ave",
    "sg:city":"Langley",
    "sg:classifiers":[
        {
            "category":"Building & Trades",
            "subcategory":"Construction",
            "type":"Services"
        }
    ],
    "sg:phone":"+1 604 513 1590",
    "sg:postcode":"V2Y 2E9",
    "sg:province":"BC",
    "sg:tags":[
        "general",
        "contractor"
    ],
    "wof:name":"Sure-Lok Builders Ltd",
    "wof:placetype":"venue"
},
  "geometry": {"coordinates":[-122.63140106199999,49.1438064575],"type":"Point"}
}