{
  "type": "Feature",
  "properties": {
    "addr:full":"572 Montreal Rd Ottawa ON K1K 0T9",
    "addr:housenumber":"572",
    "addr:postcode":"k1k 0t9",
    "addr:street":"Montreal Rd",
    "iso:country":"CA",
    "sg:address":"572 Montreal Rd",
    "sg:city":"Ottawa",
    "sg:classifiers":[
        {
            "category":"Shopping",
            "type":"Retail Goods"
        }
    ],
    "sg:phone":"+1 613 747 0515",
    "sg:postcode":"K1K 0T9",
    "sg:province":"ON",
    "sg:tags":[
        "equipment",
        "wine",
        "supply"
    ],
    "wof:name":"Wine Kitz",
    "wof:placetype":"venue"
},
  "geometry": {"coordinates":[-75.64399,45.441902],"type":"Point"}
}