{
  "type": "Feature",
  "properties": {
    "addr:full":"391 Rue Saint-Jean-Baptiste N Princeville QC G6L 5G3",
    "addr:housenumber":"391",
    "addr:postcode":"g6l 5g3",
    "addr:street":"Rue Saint-Jean-Baptiste N",
    "iso:country":"CA",
    "sg:address":"391 Rue Saint-Jean-Baptiste N",
    "sg:city":"Princeville",
    "sg:classifiers":[
        {
            "category":"Autos & Motor Vehicles",
            "subcategory":"Recreational Vehicle Sales",
            "type":"Retail Goods"
        }
    ],
    "sg:phone":"+1 819 364 5400",
    "sg:postcode":"G6L 5G3",
    "sg:province":"QC",
    "sg:tags":[
        "parts",
        "trailer"
    ],
    "wof:name":"Remeq Inc",
    "wof:placetype":"venue"
},
  "geometry": {"coordinates":[-71.88093600000001,46.177155],"type":"Point"}
}