{
  "type": "Feature",
  "properties": {
    "addr:full":"Tatamagouche NS B0K 1V0",
    "addr:postcode":"b0k 1v0",
    "iso:country":"CA",
    "sg:city":"Tatamagouche",
    "sg:classifiers":[
        {
            "category":"Retail",
            "subcategory":"Auto Repair",
            "type":"Services"
        }
    ],
    "sg:phone":"+1 902 657 3797",
    "sg:postcode":"B0K 1V0",
    "sg:province":"NS",
    "sg:tags":[
        "truck"
    ],
    "wof:name":"Aitchison Enterprises",
    "wof:placetype":"venue"
},
  "geometry": {"coordinates":[-63.291798,45.71233],"type":"Point"}
}