{
  "type": "Feature",
  "properties": {
    "iso:country":"CA",
    "sg:city":"Surrey",
    "sg:classifiers":[
        {
            "category":"Professional",
            "subcategory":"Accounting & Tax Preparation",
            "type":"Services"
        }
    ],
    "sg:phone":"+1 604 502 8574",
    "sg:postcode":"V3W 3N5",
    "sg:province":"BC",
    "sg:tags":[
        "accountant"
    ],
    "wof:name":"Lalani Accounting Svc",
    "wof:placetype":"venue"
},
  "geometry": {"coordinates":[-122.890167236,49.1586761475],"type":"Point"}
}