{
  "type": "Feature",
  "properties": {
    "iso:country":"CA",
    "sg:address":"11 Jacob Keffer Pky",
    "sg:city":"Concord",
    "sg:classifiers":[
        {
            "category":"Food & Beverages",
            "subcategory":"Bakery",
            "type":"Retail Goods"
        }
    ],
    "sg:phone":"+1 905 303 6936",
    "sg:postcode":"L4K 5N8",
    "sg:province":"ON",
    "sg:tags":[
        "doughnut"
    ],
    "wof:name":"Country Style Donuts",
    "wof:placetype":"venue"
},
  "geometry": {"coordinates":[-79.505669,43.836388],"type":"Point"}
}