{
  "type": "Feature",
  "properties": {
    "addr:full":"455 Rue Notre-Dame Montebello QC J0V 1L0",
    "addr:housenumber":"455",
    "addr:postcode":"j0v 1l0",
    "addr:street":"Rue Notre-Dame",
    "iso:country":"CA",
    "sg:address":"455 Rue Notre-Dame",
    "sg:city":"Montebello",
    "sg:classifiers":[
        {
            "category":"Wholesale",
            "subcategory":"Office Equipment",
            "type":"Manufacturing & Wholesale Goods"
        }
    ],
    "sg:phone":"+1 819 423 5097",
    "sg:postcode":"J0V 1L0",
    "sg:province":"QC",
    "sg:tags":[
        "accounting",
        "bookkeeping",
        "system"
    ],
    "wof:name":"Gestion Papineau",
    "wof:placetype":"venue"
},
  "geometry": {"coordinates":[-74.94612100000001,45.650185],"type":"Point"}
}