{
  "type": "Feature",
  "properties": {
    "iso:country":"CA",
    "sg:address":"1065 Sunningdale Rd E",
    "sg:city":"London",
    "sg:classifiers":[
        {
            "category":"Education",
            "subcategory":"School",
            "type":"Public Place"
        }
    ],
    "sg:phone":"+1 519 645 1318",
    "sg:postcode":"N5X 4B1",
    "sg:province":"ON",
    "wof:name":"Mother Teresa Ecole",
    "wof:placetype":"venue"
},
  "geometry": {"coordinates":[-81.252563,43.048935],"type":"Point"}
}