{
  "type": "Feature",
  "properties": {
    "addr:full":"1065 Sunningdale Rd E London ON N5X 4B1",
    "addr:housenumber":"1065",
    "addr:postcode":"n5x 4b1",
    "addr:street":"Sunningdale Rd E",
    "iso:country":"CA",
    "sg:address":"1065 Sunningdale Rd E",
    "sg:city":"London",
    "sg:classifiers":[
        {
            "category":"Education",
            "subcategory":"School",
            "type":"Public Place"
        }
    ],
    "sg:phone":"+1 519 645 1318",
    "sg:postcode":"N5X 4B1",
    "sg:province":"ON",
    "wof:name":"Mother Teresa Ecole",
    "wof:placetype":"venue"
},
  "geometry": {"coordinates":[-81.25256299999999,43.048935],"type":"Point"}
}