{
  "type": "Feature",
  "properties": {
    "addr:full":"Saint-Adolphe-D'Howard QC J0T 2B0",
    "addr:postcode":"j0t 2b0",
    "iso:country":"CA",
    "sg:city":"Saint-Adolphe-D'Howard",
    "sg:classifiers":[
        {
            "category":"Personal",
            "type":"Services"
        }
    ],
    "sg:phone":"+1 819 327 3390",
    "sg:postcode":"J0T 2B0",
    "sg:province":"QC",
    "sg:tags":[
        "therapist",
        "massage"
    ],
    "wof:name":"Corbeil, Johanne",
    "wof:placetype":"venue"
},
  "geometry": {"coordinates":[-74.630325,46.195099],"type":"Point"}
}