{
  "type": "Feature",
  "properties": {
    "addr:full":"293 East St S Sarnia ON N7T 3S1",
    "addr:housenumber":"293",
    "addr:postcode":"n7t 3s1",
    "addr:street":"East St S",
    "iso:country":"CA",
    "sg:address":"293 East St S",
    "sg:city":"Sarnia",
    "sg:classifiers":[
        {
            "category":"Restaurant",
            "type":"Food & Drink"
        }
    ],
    "sg:phone":"+1 519 336 7663",
    "sg:postcode":"N7T 3S1",
    "sg:province":"ON",
    "wof:name":"International Pancake & Brkfst",
    "wof:placetype":"venue"
},
  "geometry": {"coordinates":[-82.3871,42.963531],"type":"Point"}
}