{
  "type": "Feature",
  "properties": {
    "iso:country":"CA",
    "sg:address":"172 Lawlor Point",
    "sg:city":"Tangier",
    "sg:classifiers":[
        {
            "category":"Manufacturing",
            "subcategory":"Food",
            "type":"Manufacturing & Wholesale Goods"
        }
    ],
    "sg:phone":"+1 902 772 2366",
    "sg:postcode":"B0J 3H0",
    "sg:province":"NS",
    "sg:tags":[
        "product",
        "seafood",
        "fish",
        "prepared"
    ],
    "wof:name":"Ferguson's Lobster Pound",
    "wof:placetype":"venue"
},
  "geometry": {"coordinates":[-62.6985397339,44.8033485413],"type":"Point"}
}