{
  "type": "Feature",
  "properties": {
    "addr:full":"25 Rue Fleury O Montreal QC H3L 1S7",
    "addr:housenumber":"25",
    "addr:postcode":"h3l 1s7",
    "addr:street":"Rue Fleury O",
    "iso:country":"CA",
    "sg:address":"25 Rue Fleury O",
    "sg:city":"Montreal",
    "sg:classifiers":[
        {
            "category":"Retail",
            "subcategory":"Laundry & Dry Cleaning",
            "type":"Services"
        }
    ],
    "sg:phone":"+1 514 388 1168",
    "sg:postcode":"H3L 1S7",
    "sg:province":"QC",
    "sg:tags":[
        "cleaners"
    ],
    "wof:name":"Ahuntsic Nettoyeur Enrg",
    "wof:placetype":"venue"
},
  "geometry": {"coordinates":[-73.665306,45.548126],"type":"Point"}
}