{
  "type": "Feature",
  "properties": {
    "addr:full":"41 Citation Dr # 3 Concord ON L4K 2Y8",
    "addr:housenumber":"41",
    "addr:postcode":"l4k 2y8",
    "addr:street":"Citation Dr # 3",
    "iso:country":"CA",
    "sg:address":"41 Citation Dr # 3",
    "sg:city":"Concord",
    "sg:classifiers":[
        {
            "category":"Manufacturing",
            "subcategory":"Rubber & Plastics",
            "type":"Manufacturing & Wholesale Goods"
        }
    ],
    "sg:phone":"+1 905 660 3063",
    "sg:postcode":"L4K 2Y8",
    "sg:province":"ON",
    "wof:name":"Signature Plastics Inc",
    "wof:placetype":"venue"
},
  "geometry": {"coordinates":[-79.489655,43.823776],"type":"Point"}
}