{
  "type": "Feature",
  "properties": {
    "addr:full":"356 Rue Sherbrooke E Montreal QC H2X 1E6",
    "addr:housenumber":"356",
    "addr:postcode":"h2x 1e6",
    "addr:street":"Rue Sherbrooke E",
    "iso:country":"CA",
    "sg:address":"356 Rue Sherbrooke E",
    "sg:city":"Montreal",
    "sg:classifiers":[
        {
            "category":"Professional",
            "subcategory":"Management & Consulting",
            "type":"Services"
        }
    ],
    "sg:phone":"+1 514 948 0025",
    "sg:postcode":"H2X 1E6",
    "sg:province":"QC",
    "sg:tags":[
        "employee",
        "consultant",
        "benefit",
        "resource",
        "human"
    ],
    "wof:name":"Mc Kinnon Groupe Conseil Inc",
    "wof:placetype":"venue"
},
  "geometry": {"coordinates":[-73.5674819946,45.5164031982],"type":"Point"}
}