{
  "type": "Feature",
  "properties": {
    "addr:full":"82 Wellington St Stratford ON N5A 2L2",
    "addr:housenumber":"82",
    "addr:postcode":"n5a 2l2",
    "addr:street":"Wellington St",
    "iso:country":"CA",
    "sg:address":"82 Wellington St",
    "sg:city":"Stratford",
    "sg:classifiers":[
        {
            "category":"Restaurant",
            "type":"Food & Drink"
        }
    ],
    "sg:phone":"+1 519 273 4774",
    "sg:postcode":"N5A 2L2",
    "sg:province":"ON",
    "wof:name":"Let Them Eat Cake",
    "wof:placetype":"venue"
},
  "geometry": {"coordinates":[-80.98344400000001,43.369247],"type":"Point"}
}