{
  "type": "Feature",
  "properties": {
    "iso:country":"CA",
    "sg:address":"6403 Fraser St",
    "sg:city":"Vancouver",
    "sg:classifiers":[
        {
            "category":"Health Services",
            "subcategory":"Doctor",
            "type":"Services"
        }
    ],
    "sg:phone":"+1 604 325 1711",
    "sg:postcode":"V5W 3A6",
    "sg:province":"BC",
    "sg:tags":[
        "dentist"
    ],
    "wof:name":"Gill, K Tony Sing DDS",
    "wof:placetype":"venue"
},
  "geometry": {"coordinates":[-123.090843201,49.2264518738],"type":"Point"}
}