{
  "type": "Feature",
  "properties": {
    "iso:country":"CA",
    "sg:address":"8111 Kennedy Rd",
    "sg:city":"Markham",
    "sg:classifiers":[
        {
            "category":"Autos & Motor Vehicles",
            "subcategory":"Automobile Sales",
            "type":"Retail Goods"
        }
    ],
    "sg:phone":"+1 905 477 2212",
    "sg:postcode":"L3R 5M2",
    "sg:province":"ON",
    "sg:tags":[
        "car",
        "dealer"
    ],
    "wof:name":"Town & Country Bmw",
    "wof:placetype":"venue"
},
  "geometry": {"coordinates":[-79.306519,43.854427],"type":"Point"}
}