{
  "type": "Feature",
  "properties": {
    "iso:country":"CA",
    "sg:address":"14 Wilson Lake Cres",
    "sg:city":"Port Loring",
    "sg:classifiers":[
        {
            "category":"Food & Beverages",
            "subcategory":"Liquor & Beverages",
            "type":"Retail Goods"
        }
    ],
    "sg:phone":"+1 705 757 2880",
    "sg:postcode":"P0H 1Y0",
    "sg:province":"ON",
    "sg:tags":[
        "store"
    ],
    "wof:name":"Liquor Control Board of Ont",
    "wof:placetype":"venue"
},
  "geometry": {"coordinates":[-79.98682403559999,45.9141159058],"type":"Point"}
}