{
  "type": "Feature",
  "properties": {
    "iso:country":"CA",
    "sg:address":"1252 Michael St",
    "sg:city":"Gloucester",
    "sg:classifiers":[
        {
            "category":"Travel",
            "subcategory":"Hotels & Motels",
            "type":"Entertainment"
        }
    ],
    "sg:phone":"+1 613 744 2900",
    "sg:postcode":"K1J 7T1",
    "sg:province":"ON",
    "wof:name":"Comfort Inn",
    "wof:placetype":"venue"
},
  "geometry": {"coordinates":[-75.632195,45.421688],"type":"Point"}
}