{
  "type": "Feature",
  "properties": {
    "addr:full":"615 Rue Du L'Aeroport Labelle QC J0T 1H0",
    "addr:housenumber":"615",
    "addr:postcode":"j0t 1h0",
    "addr:street":"Rue Du L'Aeroport",
    "iso:country":"CA",
    "sg:address":"615 Rue Du L'Aeroport",
    "sg:city":"Labelle",
    "sg:classifiers":[
        {
            "category":"Freight",
            "type":"Transportation"
        }
    ],
    "sg:phone":"+1 819 686 2866",
    "sg:postcode":"J0T 1H0",
    "sg:province":"QC",
    "sg:tags":[
        "trucking"
    ],
    "wof:name":"Agregats DE Labelle Inc",
    "wof:placetype":"venue"
},
  "geometry": {"coordinates":[-74.7459487915,46.2807693481],"type":"Point"}
}