{
  "type": "Feature",
  "properties": {
    "addr:full":"90 Hastings St N Bancroft ON K0L 1C0",
    "addr:housenumber":"90",
    "addr:postcode":"k0l 1c0",
    "addr:street":"Hastings St N",
    "iso:country":"CA",
    "sg:address":"90 Hastings St N",
    "sg:city":"Bancroft",
    "sg:classifiers":[
        {
            "category":"Shopping",
            "subcategory":"Pharmacy",
            "type":"Retail Goods"
        }
    ],
    "sg:phone":"+1 613 332 4046",
    "sg:postcode":"K0L 1C0",
    "sg:province":"ON",
    "sg:tags":[
        "photo",
        "finishing"
    ],
    "wof:name":"Bancroft Ida Drug Mart",
    "wof:placetype":"venue"
},
  "geometry": {"coordinates":[-77.85497283940001,45.0590591431],"type":"Point"}
}