{
  "type": "Feature",
  "properties": {
    "addr:full":"394 County Road 27 Consecon ON K0K 1T0",
    "addr:housenumber":"394",
    "addr:postcode":"k0k 1t0",
    "addr:street":"County Road 27",
    "iso:country":"CA",
    "sg:address":"394 County Road 27",
    "sg:city":"Consecon",
    "sg:classifiers":[
        {
            "category":"Travel",
            "subcategory":"Campground",
            "type":"Entertainment"
        }
    ],
    "sg:phone":"+1 613 399 1979",
    "sg:postcode":"K0K 1T0",
    "sg:province":"ON",
    "wof:name":"Pleasant Bay Family Camp",
    "wof:placetype":"venue"
},
  "geometry": {"coordinates":[-77.5215,43.991421],"type":"Point"}
}