{
  "type": "Feature",
  "properties": {
    "iso:country":"CA",
    "sg:address":"3500 Laird Rd",
    "sg:city":"Mississauga",
    "sg:classifiers":[
        {
            "category":"Food & Beverages",
            "subcategory":"Fruits & Vegetables",
            "type":"Retail Goods"
        }
    ],
    "sg:phone":"+1 905 828 8280",
    "sg:postcode":"L5L 5Y4",
    "sg:province":"ON",
    "sg:tags":[
        "produce"
    ],
    "wof:name":"Pride Pak",
    "wof:placetype":"venue"
},
  "geometry": {"coordinates":[-79.6983337402,43.5167160034],"type":"Point"}
}