{
  "type": "Feature",
  "properties": {
    "iso:country":"CA",
    "sg:address":"6108 Centre St SE",
    "sg:city":"Calgary",
    "sg:classifiers":[
        {
            "category":"Shopping",
            "type":"Retail Goods"
        }
    ],
    "sg:phone":"+1 403 252 8282",
    "sg:postcode":"T2H 0C4",
    "sg:province":"AB",
    "sg:tags":[
        "plant",
        "flower",
        "tree",
        "artificial"
    ],
    "wof:name":"Silk Plant Warehouse",
    "wof:placetype":"venue"
},
  "geometry": {"coordinates":[-114.063598633,50.9975013733],"type":"Point"}
}