{
  "type": "Feature",
  "properties": {
    "addr:full":"9100 Yellowhead Trail NW Edmonton AB T5B 1G2",
    "addr:housenumber":"9100",
    "addr:postcode":"t5b 1g2",
    "addr:street":"Yellowhead Trail Nw",
    "iso:country":"CA",
    "sg:address":"9100 Yellowhead Trail NW",
    "sg:city":"Edmonton",
    "sg:classifiers":[
        {
            "category":"Manufacturing",
            "subcategory":"Metals",
            "type":"Manufacturing & Wholesale Goods"
        }
    ],
    "sg:phone":"+1 780 477 3521",
    "sg:postcode":"T5B 1G2",
    "sg:province":"AB",
    "sg:tags":[
        "plumbing",
        "fixture",
        "mirror"
    ],
    "wof:name":"City Glass & Supply Ltd",
    "wof:placetype":"venue"
},
  "geometry": {"coordinates":[-113.48114,53.581619],"type":"Point"}
}