{
  "type": "Feature",
  "properties": {
    "iso:country":"CA",
    "sg:address":"9100 Yellowhead Trail NW",
    "sg:city":"Edmonton",
    "sg:classifiers":[
        {
            "category":"Manufacturing",
            "subcategory":"Metals",
            "type":"Manufacturing & Wholesale Goods"
        }
    ],
    "sg:phone":"+1 780 477 3521",
    "sg:postcode":"T5B 1G2",
    "sg:province":"AB",
    "sg:tags":[
        "plumbing",
        "fixture",
        "mirror"
    ],
    "wof:name":"City Glass & Supply Ltd",
    "wof:placetype":"venue"
},
  "geometry": {"coordinates":[-113.48114,53.581619],"type":"Point"}
}