{
  "type": "Feature",
  "properties": {
    "addr:full":"414 College St Toronto ON M5T 1T3",
    "addr:housenumber":"414",
    "addr:postcode":"m5t 1t3",
    "addr:street":"College St",
    "iso:country":"CA",
    "sg:address":"414 College St",
    "sg:city":"Toronto",
    "sg:classifiers":[
        {
            "category":"Restaurant",
            "type":"Food & Drink"
        }
    ],
    "sg:phone":"+1 416 962 8888",
    "sg:postcode":"M5T 1T3",
    "sg:province":"ON",
    "wof:name":"Henry's Hunan Place Inc",
    "wof:placetype":"venue"
},
  "geometry": {"coordinates":[-79.406746,43.656765],"type":"Point"}
}