{
  "type": "Feature",
  "properties": {
    "addr:full":"Calgary AB T2R 1J5",
    "addr:postcode":"t2r 1j5",
    "iso:country":"CA",
    "sg:city":"Calgary",
    "sg:classifiers":[
        {
            "category":"Real Estate",
            "subcategory":"Surveying",
            "type":"Services"
        }
    ],
    "sg:phone":"+1 403 245 4711",
    "sg:postcode":"T2R 1J5",
    "sg:province":"AB",
    "sg:tags":[
        "surveyor"
    ],
    "wof:name":"Mc Elhanney Land Surveys Ltd",
    "wof:placetype":"venue"
},
  "geometry": {"coordinates":[-114.081588745,51.0440330505],"type":"Point"}
}