{
  "type": "Feature",
  "properties": {
    "addr:full":"Saint-Fulgence QC G0V 1S0",
    "addr:postcode":"g0v 1s0",
    "iso:country":"CA",
    "sg:city":"Saint-Fulgence",
    "sg:classifiers":[
        {
            "category":"Manufacturing",
            "subcategory":"Paper Products",
            "type":"Manufacturing & Wholesale Goods"
        }
    ],
    "sg:phone":"+1 418 674 2661",
    "sg:postcode":"G0V 1S0",
    "sg:province":"QC",
    "wof:name":"Abitibi-Consolidated Inc",
    "wof:placetype":"venue"
},
  "geometry": {"coordinates":[-70.717186,48.443363],"type":"Point"}
}