{
  "type": "Feature",
  "properties": {
    "addr:full":"69 Six Point Rd Etobicoke ON M8Z 2X3",
    "addr:housenumber":"69",
    "addr:postcode":"m8z 2x3",
    "addr:street":"Six Point Rd",
    "iso:country":"CA",
    "sg:address":"69 Six Point Rd",
    "sg:city":"Etobicoke",
    "sg:classifiers":[
        {
            "category":"Social Services",
            "subcategory":"Child Care",
            "type":"Services"
        }
    ],
    "sg:phone":"+1 416 231 8998",
    "sg:postcode":"M8Z 2X3",
    "sg:province":"ON",
    "wof:name":"Teddy Bear Educare",
    "wof:placetype":"venue"
},
  "geometry": {"coordinates":[-79.5241012573,43.6360359192],"type":"Point"}
}