{
  "type": "Feature",
  "properties": {
    "addr:full":"1244 Speers Rd Oakville ON L6L 2X4",
    "addr:housenumber":"1244",
    "addr:postcode":"l6l 2x4",
    "addr:street":"Speers Rd",
    "iso:country":"CA",
    "sg:address":"1244 Speers Rd",
    "sg:city":"Oakville",
    "sg:classifiers":[
        {
            "category":"Wholesale",
            "subcategory":"Machinery & Supplies",
            "type":"Manufacturing & Wholesale Goods"
        }
    ],
    "sg:phone":"+1 905 827 6695",
    "sg:postcode":"L6L 2X4",
    "sg:province":"ON",
    "sg:tags":[
        "equipment",
        "industrial"
    ],
    "wof:name":"Resolution Inplant Svc",
    "wof:placetype":"venue"
},
  "geometry": {"coordinates":[-79.7091293335,43.4268455505],"type":"Point"}
}