{
  "type": "Feature",
  "properties": {
    "addr:full":"PO Box 76 Milford Station NS B0N 1Y0",
    "addr:housenumber":"po box 76",
    "addr:postcode":"b0n 1y0",
    "addr:street":"Milford",
    "iso:country":"CA",
    "sg:address":"PO Box 76",
    "sg:city":"Milford Station",
    "sg:classifiers":[
        {
            "category":"Organizations",
            "subcategory":"Professional Association",
            "type":"Services"
        }
    ],
    "sg:phone":"+1 902 758 4257",
    "sg:postcode":"B0N 1Y0",
    "sg:province":"NS",
    "wof:name":"East Hants & District Chamber",
    "wof:placetype":"venue"
},
  "geometry": {"coordinates":[-63.438847,45.040562],"type":"Point"}
}