{
  "type": "Feature",
  "properties": {
    "addr:full":"975 Boul Saint-Joseph Drummondville QC J2C 2C4",
    "addr:housenumber":"975",
    "addr:postcode":"j2c 2c4",
    "addr:street":"Boul Saint-Joseph",
    "iso:country":"CA",
    "sg:address":"975 Boul Saint-Joseph",
    "sg:city":"Drummondville",
    "sg:classifiers":[
        {
            "category":"Wholesale",
            "subcategory":"Hardware",
            "type":"Manufacturing & Wholesale Goods"
        }
    ],
    "sg:phone":"+1 819 477 7711",
    "sg:postcode":"J2C 2C4",
    "sg:province":"QC",
    "wof:name":"Quincaillerie Le Seuil Inc",
    "wof:placetype":"venue"
},
  "geometry": {"coordinates":[-72.50759100000001,45.888912],"type":"Point"}
}