{
  "type": "Feature",
  "properties": {
    "addr:full":"PO Box 419 St Theresa Point MB R0B 1J0",
    "addr:housenumber":"po",
    "addr:postcode":"r0b 1j0",
    "addr:street":"Box 419;Theresa Point",
    "iso:country":"CA",
    "sg:address":"PO Box 419",
    "sg:city":"St Theresa Point",
    "sg:classifiers":[
        {
            "category":"Education",
            "subcategory":"College",
            "type":"Public Place"
        }
    ],
    "sg:phone":"+1 204 462 2266",
    "sg:postcode":"R0B 1J0",
    "sg:province":"MB",
    "sg:tags":[
        "academic",
        "school"
    ],
    "wof:name":"Buntep",
    "wof:placetype":"venue"
},
  "geometry": {"coordinates":[-94.844055,53.821236],"type":"Point"}
}