{
  "type": "Feature",
  "properties": {
    "iso:country":"CA",
    "sg:address":"110 18th St W",
    "sg:city":"Prince Albert",
    "sg:classifiers":[
        {
            "category":"Food & Beverages",
            "subcategory":"Meat & Fish",
            "type":"Retail Goods"
        }
    ],
    "sg:phone":"+1 306 764 5661",
    "sg:postcode":"S6V 3Z8",
    "sg:province":"SK",
    "wof:name":"Prince Albert Meat Market",
    "wof:placetype":"venue"
},
  "geometry": {"coordinates":[-105.75740051299999,53.1968612671],"type":"Point"}
}