{
  "type": "Feature",
  "properties": {
    "addr:full":"3593 Oliver Rd Murillo ON P0T 2G0",
    "addr:housenumber":"3593",
    "addr:postcode":"p0t 2g0",
    "addr:street":"Oliver Rd",
    "iso:country":"CA",
    "sg:address":"3593 Oliver Rd",
    "sg:city":"Murillo",
    "sg:classifiers":[
        {
            "category":"Shopping",
            "type":"Retail Goods"
        }
    ],
    "sg:phone":"+1 807 935 2389",
    "sg:postcode":"P0T 2G0",
    "sg:province":"ON",
    "sg:tags":[
        "water",
        "cooler",
        "fountain",
        "filter",
        "ice"
    ],
    "wof:name":"Arctic Ice Sales",
    "wof:placetype":"venue"
},
  "geometry": {"coordinates":[-89.50279999999999,48.41214],"type":"Point"}
}