{
  "type": "Feature",
  "properties": {
    "addr:full":"293 Rue Notre-Dame Nicolet QC J3T 1G2",
    "addr:housenumber":"293",
    "addr:postcode":"j3t 1g2",
    "addr:street":"Rue Notre-Dame",
    "iso:country":"CA",
    "sg:address":"293 Rue Notre-Dame",
    "sg:city":"Nicolet",
    "sg:classifiers":[
        {
            "category":"Food & Beverages",
            "subcategory":"Groceries & Convenience Stores",
            "type":"Retail Goods"
        }
    ],
    "sg:phone":"+1 819 293 4751",
    "sg:postcode":"J3T 1G2",
    "sg:province":"QC",
    "sg:tags":[
        "grocer"
    ],
    "wof:name":"J L Lafond Inc",
    "wof:placetype":"venue"
},
  "geometry": {"coordinates":[-72.61684417719999,46.2256965637],"type":"Point"}
}