{
  "type": "Feature",
  "properties": {
    "addr:full":"Nobel ON P0G 1G0",
    "addr:postcode":"p0g 1g0",
    "iso:country":"CA",
    "sg:city":"Nobel",
    "sg:classifiers":[
        {
            "category":"Government",
            "subcategory":"Office",
            "type":"Public Place"
        }
    ],
    "sg:phone":"+1 705 342 1685",
    "sg:postcode":"P0G 1G0",
    "sg:province":"ON",
    "sg:tags":[
        "village"
    ],
    "wof:name":"Carling Roads Department",
    "wof:placetype":"venue"
},
  "geometry": {"coordinates":[-80.092300415,45.4146690369],"type":"Point"}
}