{
  "type": "Feature",
  "properties": {
    "addr:full":"Erin ON N0B 1T0",
    "addr:postcode":"n0b 1t0",
    "iso:country":"CA",
    "sg:city":"Erin",
    "sg:classifiers":[
        {
            "category":"Health Services",
            "subcategory":"Doctor",
            "type":"Services"
        }
    ],
    "sg:phone":"+1 519 833 2946",
    "sg:postcode":"N0B 1T0",
    "sg:province":"ON",
    "sg:tags":[
        "clinic"
    ],
    "wof:name":"Erin Medical Chiropractic",
    "wof:placetype":"venue"
},
  "geometry": {"coordinates":[-80.0596084595,43.7630882263],"type":"Point"}
}