{
  "type": "Feature",
  "properties": {
    "addr:full":"5009 45 Ave Entwistle AB T0E 0S0",
    "addr:housenumber":"5009",
    "addr:postcode":"t0e 0s0",
    "addr:street":"45 Ave",
    "iso:country":"CA",
    "sg:address":"5009 45 Ave",
    "sg:city":"Entwistle",
    "sg:classifiers":[
        {
            "category":"Autos & Motor Vehicles",
            "subcategory":"Auto Supplies",
            "type":"Retail Goods"
        }
    ],
    "sg:phone":"+1 780 727 4442",
    "sg:postcode":"T0E 0S0",
    "sg:province":"AB",
    "sg:tags":[
        "tire"
    ],
    "wof:name":"OK Tire",
    "wof:placetype":"venue"
},
  "geometry": {"coordinates":[-114.99260700000001,53.587807],"type":"Point"}
}