{
  "type": "Feature",
  "properties": {
    "addr:full":"4500 Highway 7 # 210 Woodbridge ON L4L 4Y7",
    "addr:housenumber":"4500",
    "addr:postcode":"l4l 4y7",
    "addr:street":"Highway 7 # 210",
    "iso:country":"CA",
    "sg:address":"4500 Highway 7 # 210",
    "sg:city":"Woodbridge",
    "sg:classifiers":[
        {
            "category":"Professional",
            "subcategory":"Accounting & Tax Preparation",
            "type":"Services"
        }
    ],
    "sg:phone":"+1 905 851 7311",
    "sg:postcode":"L4L 4Y7",
    "sg:province":"ON",
    "sg:tags":[
        "accountant"
    ],
    "wof:name":"Voudouris & Zollo",
    "wof:placetype":"venue"
},
  "geometry": {"coordinates":[-79.59215500000001,43.785065],"type":"Point"}
}