{
  "type": "Feature",
  "properties": {
    "iso:country":"CA",
    "sg:address":"66 Rue DE L'Ermitage",
    "sg:city":"Saint-Jean-Port-Joli",
    "sg:classifiers":[
        {
            "category":"Retail",
            "subcategory":"Repair Shop",
            "type":"Services"
        }
    ],
    "sg:phone":"+1 418 598 3933",
    "sg:postcode":"G0R 3G0",
    "sg:province":"QC",
    "sg:tags":[
        "fabric",
        "upholsterer"
    ],
    "wof:name":"Rembourrage Belanger Enr",
    "wof:placetype":"venue"
},
  "geometry": {"coordinates":[-70.26676940919999,47.2121009827],"type":"Point"}
}