{
  "type": "Feature",
  "properties": {
    "addr:full":"Toronto ON M5H 3E5",
    "addr:postcode":"m5h 3e5",
    "iso:country":"CA",
    "sg:city":"Toronto",
    "sg:classifiers":[
        {
            "category":"Health Services",
            "subcategory":"Doctor",
            "type":"Services"
        }
    ],
    "sg:phone":"+1 416 977 6951",
    "sg:postcode":"M5H 3E5",
    "sg:province":"ON",
    "sg:tags":[
        "physician",
        "surgeon"
    ],
    "wof:name":"Copeland, Glenn MD",
    "wof:placetype":"venue"
},
  "geometry": {"coordinates":[-79.38681,43.65041],"type":"Point"}
}