{
  "type": "Feature",
  "properties": {
    "addr:full":"Hampstead QC H3X 1A6",
    "addr:postcode":"h3x 1a6",
    "iso:country":"CA",
    "sg:city":"Hampstead",
    "sg:classifiers":[
        {
            "category":"Government",
            "subcategory":"Office",
            "type":"Public Place"
        }
    ],
    "sg:phone":"+1 514 369 8280",
    "sg:postcode":"H3X 1A6",
    "sg:province":"QC",
    "sg:tags":[
        "village"
    ],
    "wof:name":"Hampstead Travaux Publics",
    "wof:placetype":"venue"
},
  "geometry": {"coordinates":[-73.6524276733,45.4869689941],"type":"Point"}
}