{
  "type": "Feature",
  "properties": {
    "iso:country":"CA",
    "sg:city":"Sainte-Foy",
    "sg:classifiers":[
        {
            "category":"Building & Trades",
            "subcategory":"Construction",
            "type":"Services"
        }
    ],
    "sg:phone":"+1 418 687 4848",
    "sg:postcode":"G1N 4L5",
    "sg:province":"QC",
    "sg:tags":[
        "elevator"
    ],
    "wof:name":"Otis Canada Inc",
    "wof:placetype":"venue"
},
  "geometry": {"coordinates":[-71.2724,46.797314],"type":"Point"}
}