{
  "type": "Feature",
  "properties": {
    "addr:full":"3893 Honey Locust Trail Mississauga ON L5N 6X4",
    "addr:housenumber":"3893",
    "addr:postcode":"l5n 6x4",
    "addr:street":"Honey Locust Trail",
    "iso:country":"CA",
    "sg:address":"3893 Honey Locust Trail",
    "sg:city":"Mississauga",
    "sg:classifiers":[
        {
            "category":"Shopping",
            "subcategory":"Computers & Home Electronics",
            "type":"Retail Goods"
        }
    ],
    "sg:phone":"+1 905 785 1982",
    "sg:postcode":"L5N 6X4",
    "sg:province":"ON",
    "sg:tags":[
        "equipment",
        "electronic",
        "supply"
    ],
    "wof:name":"Engineering Lab",
    "wof:placetype":"venue"
},
  "geometry": {"coordinates":[-79.77243,43.565887],"type":"Point"}
}