{
  "type": "Feature",
  "properties": {
    "iso:country":"CA",
    "sg:city":"Kingston",
    "sg:classifiers":[
        {
            "category":"Health Services",
            "subcategory":"Health Practitioner",
            "type":"Services"
        }
    ],
    "sg:phone":"+1 613 389 2350",
    "sg:postcode":"K7M 8M8",
    "sg:province":"ON",
    "sg:tags":[
        "therapist",
        "rehabilitation",
        "physical"
    ],
    "wof:name":"Limestone Health Consultants",
    "wof:placetype":"venue"
},
  "geometry": {"coordinates":[-76.5715332031,44.2490119934],"type":"Point"}
}