{
  "type": "Feature",
  "properties": {
    "addr:full":"26 Macdonald Rd Whitehorse YT Y1A 4L2",
    "addr:housenumber":"26",
    "addr:postcode":"y1a 4l2",
    "addr:street":"Macdonald Rd",
    "iso:country":"CA",
    "sg:address":"26 Macdonald Rd",
    "sg:city":"Whitehorse",
    "sg:classifiers":[
        {
            "category":"Retail",
            "subcategory":"Auto Repair",
            "type":"Services"
        }
    ],
    "sg:phone":"+1 867 667 2801",
    "sg:postcode":"Y1A 4L2",
    "sg:province":"YT",
    "sg:tags":[
        "repairing",
        "automobile"
    ],
    "wof:name":"Minute Muffler & Brake",
    "wof:placetype":"venue"
},
  "geometry": {"coordinates":[-135.146683,60.78175],"type":"Point"}
}