{
  "type": "Feature",
  "properties": {
    "addr:full":"Toronto ON M5V 2J6",
    "addr:postcode":"m5v 2j6",
    "iso:country":"CA",
    "sg:city":"Toronto",
    "sg:classifiers":[
        {
            "category":"Home & Garden",
            "subcategory":"Building Materials",
            "type":"Retail Goods"
        }
    ],
    "sg:phone":"+1 416 504 9706",
    "sg:postcode":"M5V 2J6",
    "sg:province":"ON",
    "sg:tags":[
        "leaded",
        "art",
        "gallery",
        "dealer"
    ],
    "wof:name":"Mimi Gellman Designs",
    "wof:placetype":"venue"
},
  "geometry": {"coordinates":[-79.3956832886,43.6463546753],"type":"Point"}
}