{
  "type": "Feature",
  "properties": {
    "iso:country":"CA",
    "sg:address":"25 Motherwell Cres",
    "sg:city":"Regina",
    "sg:classifiers":[
        {
            "category":"Professional",
            "subcategory":"Accounting & Tax Preparation",
            "type":"Services"
        }
    ],
    "sg:phone":"+1 306 522 1023",
    "sg:postcode":"S4S 3Z3",
    "sg:province":"SK",
    "sg:tags":[
        "accountant"
    ],
    "wof:name":"Lowthian, Sydney R CA",
    "wof:placetype":"venue"
},
  "geometry": {"coordinates":[-104.60482788100001,50.4225273132],"type":"Point"}
}