{
  "type": "Feature",
  "properties": {
    "addr:full":"210 Rutherford Rd S Brampton ON L6W 3J6",
    "addr:housenumber":"210",
    "addr:postcode":"l6w 3j6",
    "addr:street":"Rutherford Rd S",
    "iso:country":"CA",
    "sg:address":"210 Rutherford Rd S",
    "sg:city":"Brampton",
    "sg:classifiers":[
        {
            "category":"Retail",
            "subcategory":"Auto Repair",
            "type":"Services"
        }
    ],
    "sg:phone":"+1 905 452 3771",
    "sg:postcode":"L6W 3J6",
    "sg:province":"ON",
    "sg:tags":[
        "wrecker"
    ],
    "wof:name":"A & W Towing",
    "wof:placetype":"venue"
},
  "geometry": {"coordinates":[-79.73183400000001,43.691395],"type":"Point"}
}