{
  "type": "Feature",
  "properties": {
    "iso:country":"CA",
    "sg:address":"210 Rutherford Rd S",
    "sg:city":"Brampton",
    "sg:classifiers":[
        {
            "category":"Retail",
            "subcategory":"Auto Repair",
            "type":"Services"
        }
    ],
    "sg:phone":"+1 905 452 3771",
    "sg:postcode":"L6W 3J6",
    "sg:province":"ON",
    "sg:tags":[
        "wrecker"
    ],
    "wof:name":"A & W Towing",
    "wof:placetype":"venue"
},
  "geometry": {"coordinates":[-79.731834,43.691395],"type":"Point"}
}