{
  "type": "Feature",
  "properties": {
    "addr:full":"1810 Woodvale Ave Coquitlam BC V3J 3H4",
    "addr:housenumber":"1810",
    "addr:postcode":"v3j 3h4",
    "addr:street":"Woodvale Ave",
    "iso:country":"CA",
    "sg:address":"1810 Woodvale Ave",
    "sg:city":"Coquitlam",
    "sg:classifiers":[
        {
            "category":"Autos & Motor Vehicles",
            "subcategory":"Auto Supplies",
            "type":"Retail Goods"
        }
    ],
    "sg:phone":"+1 604 939 8661",
    "sg:postcode":"V3J 3H4",
    "sg:province":"BC",
    "sg:tags":[
        "equipment",
        "racing",
        "car",
        "automobile"
    ],
    "wof:name":"Jager Safety Equipment Inc",
    "wof:placetype":"venue"
},
  "geometry": {"coordinates":[-122.84335299999999,49.260563],"type":"Point"}
}