{
  "type": "Feature",
  "properties": {
    "addr:full":"Kitchener ON N2A 2Y5",
    "addr:postcode":"n2a 2y5",
    "iso:country":"CA",
    "sg:city":"Kitchener",
    "sg:classifiers":[
        {
            "category":"Shopping",
            "subcategory":"Florist",
            "type":"Retail Goods"
        }
    ],
    "sg:phone":"+1 519 893 1890",
    "sg:postcode":"N2A 2Y5",
    "sg:province":"ON",
    "wof:name":"Hiway Flowers",
    "wof:placetype":"venue"
},
  "geometry": {"coordinates":[-80.4371109009,43.4305877686],"type":"Point"}
}