{
  "type": "Feature",
  "properties": {
    "addr:full":"198 Mammoth Hall Trail Scarborough ON M1B 1R1",
    "addr:housenumber":"198",
    "addr:postcode":"m1b 1r1",
    "addr:street":"Mammoth Hall Trail",
    "iso:country":"CA",
    "sg:address":"198 Mammoth Hall Trail",
    "sg:city":"Scarborough",
    "sg:classifiers":[
        {
            "category":"Professional",
            "subcategory":"Management & Consulting",
            "type":"Services"
        }
    ],
    "sg:phone":"+1 416 335 7480",
    "sg:postcode":"M1B 1R1",
    "sg:province":"ON",
    "sg:tags":[
        "consultant",
        "business"
    ],
    "wof:name":"Nichols & Assoc",
    "wof:placetype":"venue"
},
  "geometry": {"coordinates":[-79.2285995483,43.8020362854],"type":"Point"}
}