{
  "type": "Feature",
  "properties": {
    "addr:full":"12608 Fort Rd NW Edmonton AB T5C 3C1",
    "addr:housenumber":"12608",
    "addr:postcode":"t5c 3c1",
    "addr:street":"Fort Rd Nw",
    "iso:country":"CA",
    "sg:address":"12608 Fort Rd NW",
    "sg:city":"Edmonton",
    "sg:classifiers":[
        {
            "category":"Retail",
            "subcategory":"Auto Repair",
            "type":"Services"
        }
    ],
    "sg:phone":"+1 780 456 2455",
    "sg:postcode":"T5C 3C1",
    "sg:province":"AB",
    "sg:tags":[
        "repairing",
        "automobile"
    ],
    "wof:name":"Bill's Auto Repair",
    "wof:placetype":"venue"
},
  "geometry": {"coordinates":[-113.44564099999999,53.584129],"type":"Point"}
}