{
  "type": "Feature",
  "properties": {
    "addr:full":"4852 Boul Des Sources Dollard-Des-Ormeaux QC H8Y 3C7",
    "addr:housenumber":"4852",
    "addr:postcode":"h8y 3c7",
    "addr:street":"Boul Des Sources",
    "iso:country":"CA",
    "sg:address":"4852 Boul Des Sources",
    "sg:city":"Dollard-Des-Ormeaux",
    "sg:classifiers":[
        {
            "category":"Food & Beverages",
            "subcategory":"Groceries & Convenience Stores",
            "type":"Retail Goods"
        }
    ],
    "sg:phone":"+1 514 421 0305",
    "sg:postcode":"H8Y 3C7",
    "sg:province":"QC",
    "sg:tags":[
        "grocer"
    ],
    "wof:name":"Apna Bazaar",
    "wof:placetype":"venue"
},
  "geometry": {"coordinates":[-73.8172836304,45.503692627],"type":"Point"}
}