{
  "type": "Feature",
  "properties": {
    "addr:full":"55 Snyder's Rd W Baden ON N3A 2M2",
    "addr:housenumber":"55",
    "addr:postcode":"n3a 2m2",
    "addr:street":"Snyder'S Rd W",
    "iso:country":"CA",
    "sg:address":"55 Snyder's Rd W",
    "sg:city":"Baden",
    "sg:classifiers":[
        {
            "category":"Food & Beverages",
            "subcategory":"Bakery",
            "type":"Retail Goods"
        }
    ],
    "sg:phone":"+1 519 634 5225",
    "sg:postcode":"N3A 2M2",
    "sg:province":"ON",
    "sg:tags":[
        "baker"
    ],
    "wof:name":"Teddy's Bakery",
    "wof:placetype":"venue"
},
  "geometry": {"coordinates":[-80.667969,43.402908],"type":"Point"}
}