{
  "type": "Feature",
  "properties": {
    "iso:country":"CA",
    "sg:address":"824 Dundas St W",
    "sg:city":"Toronto",
    "sg:classifiers":[
        {
            "category":"Home & Garden",
            "subcategory":"Furniture",
            "type":"Retail Goods"
        }
    ],
    "sg:phone":"+1 416 603 0346",
    "sg:postcode":"M6J 1V3",
    "sg:province":"ON",
    "wof:name":"31 Welcome Furniture Ltd",
    "wof:placetype":"venue"
},
  "geometry": {"coordinates":[-79.40930175779999,43.651763916],"type":"Point"}
}