{
  "type": "Feature",
  "properties": {
    "addr:full":"1414 Centre St NE Calgary AB T2E 2R9",
    "addr:housenumber":"1414",
    "addr:postcode":"t2e 2r9",
    "addr:street":"Centre St Ne",
    "iso:country":"CA",
    "sg:address":"1414 Centre St NE",
    "sg:city":"Calgary",
    "sg:classifiers":[
        {
            "category":"Shopping",
            "subcategory":"Bicycles & Sporting Goods",
            "type":"Retail Goods"
        }
    ],
    "sg:phone":"+1 403 277 3430",
    "sg:postcode":"T2E 2R9",
    "sg:province":"AB",
    "wof:name":"Calgary Cycle",
    "wof:placetype":"venue"
},
  "geometry": {"coordinates":[-114.060935974,51.0647468567],"type":"Point"}
}