{
  "type": "Feature",
  "properties": {
    "addr:full":"17010 90 Ave NW Edmonton AB T5T 1L6",
    "addr:housenumber":"17010",
    "addr:postcode":"t5t 1l6",
    "addr:street":"90 Ave Nw",
    "iso:country":"CA",
    "sg:address":"17010 90 Ave NW",
    "sg:city":"Edmonton",
    "sg:classifiers":[
        {
            "category":"Professional",
            "subcategory":"Business Services",
            "type":"Services"
        }
    ],
    "sg:phone":"+1 780 444 8855",
    "sg:postcode":"T5T 1L6",
    "sg:province":"AB",
    "sg:tags":[
        "interior",
        "consultant",
        "design",
        "decorator",
        "furniture"
    ],
    "wof:name":"Ethan Allen",
    "wof:placetype":"venue"
},
  "geometry": {"coordinates":[-113.61582199999999,53.524986],"type":"Point"}
}