{
  "type": "Feature",
  "properties": {
    "addr:full":"1220 Colonial Rd Navan ON K4B 1J4",
    "addr:housenumber":"1220",
    "addr:postcode":"k4b 1j4",
    "addr:street":"Colonial Rd",
    "iso:country":"CA",
    "sg:address":"1220 Colonial Rd",
    "sg:city":"Navan",
    "sg:classifiers":[
        {
            "category":"Food & Beverages",
            "subcategory":"Groceries & Convenience Stores",
            "type":"Retail Goods"
        }
    ],
    "sg:phone":"+1 613 835 3781",
    "sg:postcode":"K4B 1J4",
    "sg:province":"ON",
    "wof:name":"J T Bradley's Country Cnvnc",
    "wof:placetype":"venue"
},
  "geometry": {"coordinates":[-75.425629,45.42141],"type":"Point"}
}