{
  "type": "Feature",
  "properties": {
    "addr:full":"1440 Wellington Ave Winnipeg MB R3E 0K5",
    "addr:housenumber":"1440",
    "addr:postcode":"r3e 0k5",
    "addr:street":"Wellington Ave",
    "iso:country":"CA",
    "sg:address":"1440 Wellington Ave",
    "sg:city":"Winnipeg",
    "sg:classifiers":[
        {
            "category":"Home & Garden",
            "subcategory":"Carpets & Floor Coverings",
            "type":"Retail Goods"
        }
    ],
    "sg:phone":"+1 204 697 1337",
    "sg:postcode":"R3E 0K5",
    "sg:province":"MB",
    "sg:tags":[
        "dealer",
        "rug"
    ],
    "wof:name":"Studio Floor & Window Covering",
    "wof:placetype":"venue"
},
  "geometry": {"coordinates":[-97.19689200000001,49.901024],"type":"Point"}
}