{
  "type": "Feature",
  "properties": {
    "addr:full":"25 Main St Hantsport NS B0P 1P0",
    "addr:housenumber":"25",
    "addr:postcode":"b0p 1p0",
    "addr:street":"Main St",
    "iso:country":"CA",
    "sg:address":"25 Main St",
    "sg:city":"Hantsport",
    "sg:classifiers":[
        {
            "category":"Shopping",
            "subcategory":"Pharmacy",
            "type":"Retail Goods"
        }
    ],
    "sg:phone":"+1 902 684 9303",
    "sg:postcode":"B0P 1P0",
    "sg:province":"NS",
    "wof:name":"Cochrane Pharmacy Ltd",
    "wof:placetype":"venue"
},
  "geometry": {"coordinates":[-64.183891,45.064922],"type":"Point"}
}