{
  "type": "Feature",
  "properties": {
    "addr:full":"779 Prince St Truro NS B2N 1G7",
    "addr:housenumber":"779",
    "addr:postcode":"b2n 1g7",
    "addr:street":"Prince St",
    "iso:country":"CA",
    "sg:address":"779 Prince St",
    "sg:city":"Truro",
    "sg:classifiers":[
        {
            "category":"Professional",
            "subcategory":"Lawyer & Legal Services",
            "type":"Services"
        }
    ],
    "sg:phone":"+1 902 895 4417",
    "sg:postcode":"B2N 1G7",
    "sg:province":"NS",
    "sg:tags":[
        "attorney"
    ],
    "wof:name":"Begin, Alain J",
    "wof:placetype":"venue"
},
  "geometry": {"coordinates":[-63.277538,45.364803],"type":"Point"}
}