{
  "type": "Feature",
  "properties": {
    "iso:country":"CA",
    "sg:address":"409 Rideau St",
    "sg:city":"Kemptville",
    "sg:classifiers":[
        {
            "category":"Shopping",
            "type":"Retail Goods"
        }
    ],
    "sg:phone":"+1 613 258 9463",
    "sg:postcode":"K0G 1J0",
    "sg:province":"ON",
    "sg:tags":[
        "equipment",
        "wine",
        "supply"
    ],
    "wof:name":"Brewing Oasis Inc",
    "wof:placetype":"venue"
},
  "geometry": {"coordinates":[-75.650032,45.018757],"type":"Point"}
}