{
  "type": "Feature",
  "properties": {
    "addr:full":"Penticton BC V2A 8K3",
    "addr:postcode":"v2a 8k3",
    "iso:country":"CA",
    "sg:city":"Penticton",
    "sg:classifiers":[
        {
            "category":"Professional",
            "subcategory":"Business Services",
            "type":"Services"
        }
    ],
    "sg:phone":"+1 250 493 8951",
    "sg:postcode":"V2A 8K3",
    "sg:province":"BC",
    "sg:tags":[
        "diving",
        "instruction",
        "diver"
    ],
    "wof:name":"Oceantec Scuba Diving",
    "wof:placetype":"venue"
},
  "geometry": {"coordinates":[-119.593857,49.500229],"type":"Point"}
}