{
  "type": "Feature",
  "properties": {
    "addr:full":"2751 Plymouth Dr Oakville ON L6H 5R5",
    "addr:housenumber":"2751",
    "addr:postcode":"l6h 5r5",
    "addr:street":"Plymouth Dr",
    "iso:country":"CA",
    "sg:address":"2751 Plymouth Dr",
    "sg:city":"Oakville",
    "sg:classifiers":[
        {
            "category":"Manufacturing",
            "subcategory":"Metals",
            "type":"Manufacturing & Wholesale Goods"
        }
    ],
    "sg:phone":"+1 905 829 3660",
    "sg:postcode":"L6H 5R5",
    "sg:province":"ON",
    "sg:tags":[
        "stamping"
    ],
    "wof:name":"K Tool & Die CO Ltd",
    "wof:placetype":"venue"
},
  "geometry": {"coordinates":[-79.67743682859999,43.5084762573],"type":"Point"}
}