{
  "type": "Feature",
  "properties": {
    "iso:country":"CA",
    "sg:city":"Brampton",
    "sg:classifiers":[
        {
            "category":"Professional",
            "subcategory":"Engineering",
            "type":"Services"
        }
    ],
    "sg:phone":"+1 905 502 8533",
    "sg:postcode":"L6W 3V1",
    "sg:province":"ON",
    "sg:tags":[
        "engineer"
    ],
    "wof:name":"Terraprobe Limited",
    "wof:placetype":"venue"
},
  "geometry": {"coordinates":[-79.715851,43.684105],"type":"Point"}
}