{
  "type": "Feature",
  "properties": {
    "addr:full":"2860 Cruickshank St Abbotsford BC V2T 5M4",
    "addr:housenumber":"2860",
    "addr:postcode":"v2t 5m4",
    "addr:street":"Cruickshank St",
    "iso:country":"CA",
    "sg:address":"2860 Cruickshank St",
    "sg:city":"Abbotsford",
    "sg:classifiers":[
        {
            "category":"Building & Trades",
            "subcategory":"Equipment Rental",
            "type":"Services"
        }
    ],
    "sg:phone":"+1 604 855 9797",
    "sg:postcode":"V2T 5M4",
    "sg:province":"BC",
    "sg:tags":[
        "party",
        "supply"
    ],
    "wof:name":"Classic Party Rentals Ltd",
    "wof:placetype":"venue"
},
  "geometry": {"coordinates":[-122.32386,49.054253],"type":"Point"}
}