{
  "type": "Feature",
  "properties": {
    "addr:full":"354 Ch DE LA Grande-Cote Boisbriand QC J7G 1B1",
    "addr:housenumber":"354",
    "addr:postcode":"j7g 1b1",
    "addr:street":"Ch De La Grande-Cote",
    "iso:country":"CA",
    "sg:address":"354 Ch DE LA Grande-Cote",
    "sg:city":"Boisbriand",
    "sg:classifiers":[
        {
            "category":"Restaurant",
            "type":"Food & Drink"
        }
    ],
    "sg:phone":"+1 450 971 5151",
    "sg:postcode":"J7G 1B1",
    "sg:province":"QC",
    "wof:name":"Joes Restaurant",
    "wof:placetype":"venue"
},
  "geometry": {"coordinates":[-73.83317565919999,45.6076393127],"type":"Point"}
}