{
  "type": "Feature",
  "properties": {
    "iso:country":"CA",
    "sg:address":"2155 Northridge Dr",
    "sg:city":"Saskatoon",
    "sg:classifiers":[
        {
            "category":"Travel",
            "subcategory":"Hotels & Motels",
            "type":"Entertainment"
        }
    ],
    "sg:phone":"+1 306 934 1122",
    "sg:postcode":"S7L 6X6",
    "sg:province":"SK",
    "wof:name":"Comfort Inn",
    "wof:placetype":"venue"
},
  "geometry": {"coordinates":[-106.668015,52.159222],"type":"Point"}
}