{
  "type": "Feature",
  "properties": {
    "addr:full":"439 Rue Chasse Drummondville QC J2C 4E3",
    "addr:housenumber":"439",
    "addr:postcode":"j2c 4e3",
    "addr:street":"Rue Chasse",
    "iso:country":"CA",
    "sg:address":"439 Rue Chasse",
    "sg:city":"Drummondville",
    "sg:classifiers":[
        {
            "category":"Manufacturing",
            "subcategory":"Tools & Machinery",
            "type":"Manufacturing & Wholesale Goods"
        }
    ],
    "sg:phone":"+1 819 471 1349",
    "sg:postcode":"J2C 4E3",
    "sg:province":"QC",
    "sg:tags":[
        "water",
        "equipment",
        "works",
        "supply"
    ],
    "wof:name":"Amenagement Paysager Ctr",
    "wof:placetype":"venue"
},
  "geometry": {"coordinates":[-72.49865699999999,45.883003],"type":"Point"}
}