{
  "type": "Feature",
  "properties": {
    "iso:country":"CA",
    "sg:city":"North York",
    "sg:classifiers":[
        {
            "category":"Shopping",
            "subcategory":"Pharmacy",
            "type":"Retail Goods"
        }
    ],
    "sg:phone":"+1 416 222 0242",
    "sg:postcode":"M2N 6H7",
    "sg:province":"ON",
    "wof:name":"Triex International Inc",
    "wof:placetype":"venue"
},
  "geometry": {"coordinates":[-79.38832855219999,43.7666969299],"type":"Point"}
}