{
  "type": "Feature",
  "properties": {
    "addr:full":"807 Main St W Hamilton ON L8S 1A2",
    "addr:housenumber":"807",
    "addr:postcode":"l8s 1a2",
    "addr:street":"Main St W",
    "iso:country":"CA",
    "sg:address":"807 Main St W",
    "sg:city":"Hamilton",
    "sg:classifiers":[
        {
            "category":"Shopping",
            "subcategory":"Books",
            "type":"Retail Goods"
        }
    ],
    "sg:phone":"+1 905 522 9104",
    "sg:postcode":"L8S 1A2",
    "sg:province":"ON",
    "sg:tags":[
        "dealer"
    ],
    "wof:name":"Canadian Bible Society",
    "wof:placetype":"venue"
},
  "geometry": {"coordinates":[-79.8998260498,43.2593688965],"type":"Point"}
}