{
  "type": "Feature",
  "properties": {
    "addr:full":"Prince Rupert BC V8J 1L9",
    "addr:postcode":"v8j 1l9",
    "iso:country":"CA",
    "sg:city":"Prince Rupert",
    "sg:classifiers":[
        {
            "category":"Banks & Credit Unions",
            "subcategory":"Investment Brokerage",
            "type":"Services"
        }
    ],
    "sg:phone":"+1 250 622 2332",
    "sg:postcode":"V8J 1L9",
    "sg:province":"BC",
    "sg:tags":[
        "consultant",
        "planning",
        "financial",
        "business",
        "management"
    ],
    "wof:name":"Community Futures Dev Corp",
    "wof:placetype":"venue"
},
  "geometry": {"coordinates":[-130.32575988799999,54.311958313],"type":"Point"}
}