{
  "type": "Feature",
  "properties": {
    "addr:full":"390 Rideau St Ottawa ON K1N 5Y8",
    "addr:housenumber":"390",
    "addr:postcode":"k1n 5y8",
    "addr:street":"Rideau St",
    "iso:country":"CA",
    "sg:address":"390 Rideau St",
    "sg:city":"Ottawa",
    "sg:classifiers":[
        {
            "category":"Government",
            "subcategory":"Post Office",
            "type":"Public Place"
        }
    ],
    "sg:phone":"+1 613 789 1796",
    "sg:postcode":"K1N 5Y8",
    "sg:province":"ON",
    "sg:tags":[
        "pharmacy"
    ],
    "wof:name":"Pharmacie Rideau Pharmacy Ltd",
    "wof:placetype":"venue"
},
  "geometry": {"coordinates":[-75.68282318120001,45.4298439026],"type":"Point"}
}