{
  "type": "Feature",
  "properties": {
    "addr:full":"88 Broadway Corner Brook NL A2H 4C8",
    "addr:housenumber":"88",
    "addr:postcode":"a2h 4c8",
    "addr:street":"Broadway",
    "iso:country":"CA",
    "sg:address":"88 Broadway",
    "sg:city":"Corner Brook",
    "sg:classifiers":[
        {
            "category":"Home & Garden",
            "subcategory":"Building Materials",
            "type":"Retail Goods"
        }
    ],
    "sg:phone":"+1 709 634 7953",
    "sg:postcode":"A2H 4C8",
    "sg:province":"NL",
    "sg:tags":[
        "paint"
    ],
    "wof:name":"Glidden Paints",
    "wof:placetype":"venue"
},
  "geometry": {"coordinates":[-57.9556655884,48.9529151917],"type":"Point"}
}