{
  "type": "Feature",
  "properties": {
    "addr:full":"Scarborough ON M1N 4E4",
    "addr:postcode":"m1n 4e4",
    "iso:country":"CA",
    "sg:city":"Scarborough",
    "sg:classifiers":[
        {
            "category":"Social Services",
            "subcategory":"Job Training",
            "type":"Services"
        }
    ],
    "sg:phone":"+1 416 699 1700",
    "sg:postcode":"M1N 4E4",
    "sg:province":"ON",
    "sg:tags":[
        "physiotherapist",
        "rehabilitation"
    ],
    "wof:name":"Vicpark South Injury Rehab Ctr",
    "wof:placetype":"venue"
},
  "geometry": {"coordinates":[-79.282509,43.680984],"type":"Point"}
}