{
  "type": "Feature",
  "properties": {
    "addr:full":"Redcliff AB T0J 2P0",
    "addr:postcode":"t0j 2p0",
    "iso:country":"CA",
    "sg:city":"Redcliff",
    "sg:classifiers":[
        {
            "category":"Retail",
            "subcategory":"Auto Rental",
            "type":"Services"
        }
    ],
    "sg:phone":"+1 403 548 7555",
    "sg:postcode":"T0J 2P0",
    "sg:province":"AB",
    "sg:tags":[
        "renting",
        "truck",
        "leasing"
    ],
    "wof:name":"U-Haul CO Ltd",
    "wof:placetype":"venue"
},
  "geometry": {"coordinates":[-110.764801025,50.0746498108],"type":"Point"}
}