{
  "type": "Feature",
  "properties": {
    "addr:full":"Morden MB R6M 1V2",
    "addr:postcode":"r6m 1v2",
    "iso:country":"CA",
    "sg:city":"Morden",
    "sg:classifiers":[
        {
            "category":"Shopping",
            "subcategory":"Catalog Store",
            "type":"Retail Goods"
        }
    ],
    "sg:phone":"+1 204 822 5441",
    "sg:postcode":"R6M 1V2",
    "sg:province":"MB",
    "sg:tags":[
        "mail",
        "order",
        "internet"
    ],
    "wof:name":"Sears Canada Inc",
    "wof:placetype":"venue"
},
  "geometry": {"coordinates":[-98.098495,49.190056],"type":"Point"}
}