{
  "type": "Feature",
  "properties": {
    "addr:full":"445 County Rd 50 RR 1 Harrow ON N0R 1G0",
    "addr:housenumber":"445;50",
    "addr:postcode":"n0r 1g0",
    "addr:street":"County Rd;Rr 1",
    "iso:country":"CA",
    "sg:address":"445 County Rd 50 RR 1",
    "sg:city":"Harrow",
    "sg:classifiers":[
        {
            "category":"Travel",
            "subcategory":"Campground",
            "type":"Entertainment"
        }
    ],
    "sg:phone":"+1 519 738 2620",
    "sg:postcode":"N0R 1G0",
    "sg:province":"ON",
    "wof:name":"Ravine Cottages",
    "wof:placetype":"venue"
},
  "geometry": {"coordinates":[-82.91790771479999,42.0355262756],"type":"Point"}
}