{
  "type": "Feature",
  "properties": {
    "addr:full":"Saint-Jerome QC J7Z 4Z4",
    "addr:postcode":"j7z 4z4",
    "iso:country":"CA",
    "sg:city":"Saint-Jerome",
    "sg:classifiers":[
        {
            "category":"Home & Garden",
            "subcategory":"Building Materials",
            "type":"Retail Goods"
        }
    ],
    "sg:phone":"+1 450 438 7447",
    "sg:postcode":"J7Z 4Z4",
    "sg:province":"QC",
    "sg:tags":[
        "glass",
        "window",
        "plate"
    ],
    "wof:name":"Vitrerie Allen & Fils",
    "wof:placetype":"venue"
},
  "geometry": {"coordinates":[-74.001869,45.771744],"type":"Point"}
}