{
  "type": "Feature",
  "properties": {
    "addr:full":"1321 Rue Leger Saint-Timothee QC J6S 6C7",
    "addr:housenumber":"1321",
    "addr:postcode":"j6s 6c7",
    "addr:street":"Rue Leger Saint-Timothee",
    "iso:country":"CA",
    "sg:address":"1321 Rue Leger",
    "sg:city":"Saint-Timothee",
    "sg:classifiers":[
        {
            "category":"Social Services",
            "subcategory":"Child Care",
            "type":"Services"
        }
    ],
    "sg:phone":"+1 450 371 5937",
    "sg:postcode":"J6S 6C7",
    "sg:province":"QC",
    "wof:name":"Garderie Les Petits Bricoleurs",
    "wof:placetype":"venue"
},
  "geometry": {"coordinates":[-74.071609,45.276859],"type":"Point"}
}