{
  "type": "Feature",
  "properties": {
    "addr:full":"2078 Pasqua St Regina SK S4T 4L9",
    "addr:housenumber":"2078",
    "addr:postcode":"s4t 4l9",
    "addr:street":"Pasqua St",
    "iso:country":"CA",
    "sg:address":"2078 Pasqua St",
    "sg:city":"Regina",
    "sg:classifiers":[
        {
            "category":"Education",
            "subcategory":"School",
            "type":"Public Place"
        }
    ],
    "sg:phone":"+1 306 352 3601",
    "sg:postcode":"S4T 4L9",
    "sg:province":"SK",
    "wof:name":"Martin School of Dancing",
    "wof:placetype":"venue"
},
  "geometry": {"coordinates":[-104.641159,50.44593],"type":"Point"}
}