{
  "type": "Feature",
  "properties": {
    "addr:full":"1500 Boul Des Ruisseaux Mont-Laurier QC J9L 3G6",
    "addr:housenumber":"1500",
    "addr:postcode":"j9l 3g6",
    "addr:street":"Boul Des Ruisseaux",
    "iso:country":"CA",
    "sg:address":"1500 Boul Des Ruisseaux",
    "sg:city":"Mont-Laurier",
    "sg:classifiers":[
        {
            "category":"Autos & Motor Vehicles",
            "subcategory":"Automobile Sales",
            "type":"Retail Goods"
        }
    ],
    "sg:phone":"+1 819 623 7645",
    "sg:postcode":"J9L 3G6",
    "sg:province":"QC",
    "sg:tags":[
        "car",
        "dealer"
    ],
    "wof:name":"Auto Lepage",
    "wof:placetype":"venue"
},
  "geometry": {"coordinates":[-75.586716,46.557564],"type":"Point"}
}