{
  "type": "Feature",
  "properties": {
    "addr:full":"3080 Rue Saint-Prosper Saint-Hyacinthe QC J2S 2A4",
    "addr:housenumber":"3080",
    "addr:postcode":"j2s 2a4",
    "addr:street":"Rue Saint-Prosper",
    "iso:country":"CA",
    "sg:address":"3080 Rue Saint-Prosper",
    "sg:city":"Saint-Hyacinthe",
    "sg:classifiers":[
        {
            "category":"Wholesale",
            "subcategory":"Groceries",
            "type":"Manufacturing & Wholesale Goods"
        }
    ],
    "sg:phone":"+1 450 773 9944",
    "sg:postcode":"J2S 2A4",
    "sg:province":"QC",
    "sg:tags":[
        "baker"
    ],
    "wof:name":"Aliments Novali Foods Inc",
    "wof:placetype":"venue"
},
  "geometry": {"coordinates":[-72.964798,45.622482],"type":"Point"}
}