{
  "type": "Feature",
  "properties": {
    "addr:full":"6610 Boul Les Galeries-D'Anjou Anjou QC H1M 2T4",
    "addr:housenumber":"6610",
    "addr:postcode":"h1m 2t4",
    "addr:street":"Boul Les Galeries-D'Anjou",
    "iso:country":"CA",
    "sg:address":"6610 Boul Les Galeries-D'Anjou",
    "sg:city":"Anjou",
    "sg:classifiers":[
        {
            "category":"Taxi",
            "type":"Transportation"
        }
    ],
    "sg:phone":"+1 514 352 6000",
    "sg:postcode":"H1M 2T4",
    "sg:province":"QC",
    "sg:tags":[
        "taxicab"
    ],
    "wof:name":"CO-OP DE L'Est Taxi",
    "wof:placetype":"venue"
},
  "geometry": {"coordinates":[-73.538673,45.612267],"type":"Point"}
}