{
  "type": "Feature",
  "properties": {
    "addr:full":"10539 Kennedy Rd Gormley ON L0H 1G0",
    "addr:housenumber":"10539",
    "addr:postcode":"l0h 1g0",
    "addr:street":"Kennedy Rd",
    "iso:country":"CA",
    "sg:address":"10539 Kennedy Rd",
    "sg:city":"Gormley",
    "sg:classifiers":[
        {
            "category":"Farming",
            "subcategory":"Farm",
            "type":"Manufacturing & Wholesale Goods"
        }
    ],
    "sg:phone":"+1 905 887 1087",
    "sg:postcode":"L0H 1G0",
    "sg:province":"ON",
    "wof:name":"Forsythe Family Farms",
    "wof:placetype":"venue"
},
  "geometry": {"coordinates":[-79.3289718628,43.9378585815],"type":"Point"}
}