{
  "type": "Feature",
  "properties": {
    "addr:full":"56 Pennsylvania Ave Concord ON L4K 3V9",
    "addr:housenumber":"56",
    "addr:postcode":"l4k 3v9",
    "addr:street":"Pennsylvania Ave",
    "iso:country":"CA",
    "sg:address":"56 Pennsylvania Ave",
    "sg:city":"Concord",
    "sg:classifiers":[
        {
            "category":"Wholesale",
            "subcategory":"Machinery & Supplies",
            "type":"Manufacturing & Wholesale Goods"
        }
    ],
    "sg:phone":"+1 905 738 6918",
    "sg:postcode":"L4K 3V9",
    "sg:province":"ON",
    "sg:tags":[
        "salon",
        "beauty"
    ],
    "wof:name":"Rogers Agencies Inc",
    "wof:placetype":"venue"
},
  "geometry": {"coordinates":[-79.527924,43.803143],"type":"Point"}
}