{
  "type": "Feature",
  "properties": {
    "addr:full":"586 Champagne Dr North York ON M3J 2T9",
    "addr:housenumber":"586",
    "addr:postcode":"m3j 2t9",
    "addr:street":"Champagne Dr",
    "iso:country":"CA",
    "sg:address":"586 Champagne Dr",
    "sg:city":"North York",
    "sg:classifiers":[
        {
            "category":"Restaurant",
            "type":"Food & Drink"
        }
    ],
    "sg:phone":"+1 416 638 7911",
    "sg:postcode":"M3J 2T9",
    "sg:province":"ON",
    "wof:name":"Sandwich Garden Restaurant",
    "wof:placetype":"venue"
},
  "geometry": {"coordinates":[-79.4756011963,43.7646598816],"type":"Point"}
}