{
  "type": "Feature",
  "properties": {
    "addr:full":"5785 Av Victoria Montreal QC H3W 2R3",
    "addr:housenumber":"5785",
    "addr:postcode":"h3w 2r3",
    "addr:street":"Av Victoria",
    "iso:country":"CA",
    "sg:address":"5785 Av Victoria",
    "sg:city":"Montreal",
    "sg:classifiers":[
        {
            "category":"Professional",
            "subcategory":"Management & Consulting",
            "type":"Services"
        }
    ],
    "sg:phone":"+1 514 341 0303",
    "sg:postcode":"H3W 2R3",
    "sg:province":"QC",
    "sg:tags":[
        "consultant",
        "telecommunication"
    ],
    "wof:name":"Jervian Communications Inc",
    "wof:placetype":"venue"
},
  "geometry": {"coordinates":[-73.6343,45.493038],"type":"Point"}
}