{
  "type": "Feature",
  "properties": {
    "addr:full":"250 Taunton Rd E Oshawa ON L1G 7T1",
    "addr:housenumber":"250",
    "addr:postcode":"l1g 7t1",
    "addr:street":"Taunton Rd E",
    "iso:country":"CA",
    "sg:address":"250 Taunton Rd E",
    "sg:city":"Oshawa",
    "sg:classifiers":[
        {
            "category":"Shopping",
            "subcategory":"Music",
            "type":"Retail Goods"
        }
    ],
    "sg:phone":"+1 905 435 9989",
    "sg:postcode":"L1G 7T1",
    "sg:province":"ON",
    "sg:tags":[
        "compact",
        "record",
        "disc",
        "tape"
    ],
    "wof:name":"Deja Vu Discs",
    "wof:placetype":"venue"
},
  "geometry": {"coordinates":[-78.8703918457,43.9350013733],"type":"Point"}
}