{
  "type": "Feature",
  "properties": {
    "addr:full":"168 Muskoka Rd Bracebridge ON P1L 1H6",
    "addr:housenumber":"168",
    "addr:postcode":"p1l 1h6",
    "addr:street":"Muskoka Rd",
    "iso:country":"CA",
    "sg:address":"168 Muskoka Rd",
    "sg:city":"Bracebridge",
    "sg:classifiers":[
        {
            "category":"Organizations",
            "subcategory":"Professional Association",
            "type":"Services"
        }
    ],
    "sg:phone":"+1 705 645 8500",
    "sg:postcode":"P1L 1H6",
    "sg:province":"ON",
    "wof:name":"Royal Canadian Legion",
    "wof:placetype":"venue"
},
  "geometry": {"coordinates":[-79.3029708862,45.0365638733],"type":"Point"}
}