{
  "type": "Feature",
  "properties": {
    "iso:country":"CA",
    "sg:address":"3335 Woodward Blvd",
    "sg:city":"Windsor",
    "sg:classifiers":[
        {
            "category":"Organizations",
            "subcategory":"Religious Organization",
            "type":"Services"
        }
    ],
    "sg:phone":"+1 519 969 2731",
    "sg:postcode":"N8W 2Y7",
    "sg:province":"ON",
    "sg:tags":[
        "church"
    ],
    "wof:name":"St Christopher's Catholic Chr",
    "wof:placetype":"venue"
},
  "geometry": {"coordinates":[-82.982765,42.276119],"type":"Point"}
}