{
  "type": "Feature",
  "properties": {
    "iso:country":"CA",
    "sg:address":"594 Montee Du Moulin",
    "sg:city":"Laval",
    "sg:classifiers":[
        {
            "category":"Restaurant",
            "type":"Food & Drink"
        }
    ],
    "sg:phone":"+1 450 665 5757",
    "sg:postcode":"H7A 3R9",
    "sg:province":"QC",
    "wof:name":"Restaurant Le Belle Province",
    "wof:placetype":"venue"
},
  "geometry": {"coordinates":[-73.574966,45.669079],"type":"Point"}
}