{
  "type": "Feature",
  "properties": {
    "addr:full":"Courtenay BC V9N 7S7",
    "addr:postcode":"v9n 7s7",
    "iso:country":"CA",
    "sg:city":"Courtenay",
    "sg:classifiers":[
        {
            "category":"Wholesale",
            "subcategory":"Electrical",
            "type":"Manufacturing & Wholesale Goods"
        }
    ],
    "sg:phone":"+1 250 334 3148",
    "sg:postcode":"V9N 7S7",
    "sg:province":"BC",
    "sg:tags":[
        "equipment",
        "electric",
        "supply"
    ],
    "wof:name":"Westburne Supply BC Ltd",
    "wof:placetype":"venue"
},
  "geometry": {"coordinates":[-124.98426055900001,49.6696662903],"type":"Point"}
}