{
  "type": "Feature",
  "properties": {
    "addr:full":"847 Rue Cherrier Montreal QC H2L 1H6",
    "addr:housenumber":"847",
    "addr:postcode":"h2l 1h6",
    "addr:street":"Rue Cherrier",
    "iso:country":"CA",
    "sg:address":"847 Rue Cherrier",
    "sg:city":"Montreal",
    "sg:classifiers":[
        {
            "category":"Organizations",
            "subcategory":"Professional Association",
            "type":"Services"
        }
    ],
    "sg:phone":"+1 514 524 1970",
    "sg:postcode":"H2L 1H6",
    "sg:province":"QC",
    "wof:name":"Societe Quebecoise Pour LA",
    "wof:placetype":"venue"
},
  "geometry": {"coordinates":[-73.56809199999999,45.520477],"type":"Point"}
}