{
  "type": "Feature",
  "properties": {
    "addr:full":"102 1/2 Christina St S Sarnia ON N7T 2M6",
    "addr:housenumber":"102 1 / 2",
    "addr:postcode":"n7t 2m6",
    "addr:street":"Christina St S",
    "iso:country":"CA",
    "sg:address":"102 1/2 Christina St S",
    "sg:city":"Sarnia",
    "sg:classifiers":[
        {
            "category":"Organizations",
            "subcategory":"Professional Association",
            "type":"Services"
        }
    ],
    "sg:phone":"+1 519 344 8050",
    "sg:postcode":"N7T 2M6",
    "sg:province":"ON",
    "sg:tags":[
        "club"
    ],
    "wof:name":"Afac 403 Wing",
    "wof:placetype":"venue"
},
  "geometry": {"coordinates":[-82.40771484379999,42.9705810547],"type":"Point"}
}