{
  "type": "Feature",
  "properties": {
    "iso:country":"CA",
    "sg:address":"155 Main St",
    "sg:city":"Lillooet",
    "sg:classifiers":[
        {
            "category":"Shopping",
            "subcategory":"Department Store",
            "type":"Retail Goods"
        }
    ],
    "sg:phone":"+1 250 256 7555",
    "sg:postcode":"V0K 1V0",
    "sg:province":"BC",
    "wof:name":"Fields Stores",
    "wof:placetype":"venue"
},
  "geometry": {"coordinates":[-121.93284606900001,50.6827888489],"type":"Point"}
}