{
  "type": "Feature",
  "properties": {
    "addr:full":"1523 Cariboo Hwy S Williams Lake BC V2G 2W3",
    "addr:housenumber":"1523",
    "addr:postcode":"v2g 2w3",
    "addr:street":"Cariboo Hwy S Williams",
    "iso:country":"CA",
    "sg:address":"1523 Cariboo Hwy S",
    "sg:city":"Williams Lake",
    "sg:classifiers":[
        {
            "category":"Travel",
            "subcategory":"Hotels & Motels",
            "type":"Entertainment"
        }
    ],
    "sg:phone":"+1 250 392 4655",
    "sg:postcode":"V2G 2W3",
    "sg:province":"BC",
    "wof:name":"Valleyview Motel",
    "wof:placetype":"venue"
},
  "geometry": {"coordinates":[-122.111717224,52.1228065491],"type":"Point"}
}