{
  "type": "Feature",
  "properties": {
    "addr:full":"874 Eglinton Ave E East York ON M4G 2L1",
    "addr:housenumber":"874",
    "addr:postcode":"m4g 2l1",
    "addr:street":"Eglinton Ave E",
    "iso:country":"CA",
    "sg:address":"874 Eglinton Ave E",
    "sg:city":"East York",
    "sg:classifiers":[
        {
            "category":"Real Estate",
            "subcategory":"Real Estate Agent",
            "type":"Services"
        }
    ],
    "sg:phone":"+1 416 424 1300",
    "sg:postcode":"M4G 2L1",
    "sg:province":"ON",
    "wof:name":"Coldwell Banker Prpts Unltd Rl",
    "wof:placetype":"venue"
},
  "geometry": {"coordinates":[-79.365143,43.713657],"type":"Point"}
}