{
  "type": "Feature",
  "properties": {
    "addr:full":"Saint-Bonaventure QC J0C 1C0",
    "addr:postcode":"j0c 1c0",
    "iso:country":"CA",
    "sg:city":"Saint-Bonaventure",
    "sg:classifiers":[
        {
            "category":"Personal",
            "subcategory":"Beauty Salon",
            "type":"Services"
        }
    ],
    "sg:phone":"+1 819 396 2534",
    "sg:postcode":"J0C 1C0",
    "sg:province":"QC",
    "wof:name":"Athena Coiffure Esthetique",
    "wof:placetype":"venue"
},
  "geometry": {"coordinates":[-72.678116,45.961708],"type":"Point"}
}