{
  "type": "Feature",
  "properties": {
    "iso:country":"CA",
    "sg:address":"4709 Canal Rd",
    "sg:city":"Pender Island",
    "sg:classifiers":[
        {
            "category":"Travel",
            "subcategory":"Hotels & Motels",
            "type":"Entertainment"
        }
    ],
    "sg:phone":"+1 250 629 3353",
    "sg:postcode":"V0N 2M1",
    "sg:province":"BC",
    "sg:tags":[
        "resort"
    ],
    "wof:name":"Inn on Pender Island",
    "wof:placetype":"venue"
},
  "geometry": {"coordinates":[-123.275650024,48.770565033],"type":"Point"}
}