{
  "type": "Feature",
  "properties": {
    "addr:full":"9616 111 St Grande Prairie AB T8V 4E6",
    "addr:housenumber":"9616",
    "addr:postcode":"t8v 4e6",
    "addr:street":"111 St",
    "iso:country":"CA",
    "sg:address":"9616 111 St",
    "sg:city":"Grande Prairie",
    "sg:classifiers":[
        {
            "category":"Building & Trades",
            "subcategory":"Construction",
            "type":"Services"
        }
    ],
    "sg:phone":"+1 780 538 3665",
    "sg:postcode":"T8V 4E6",
    "sg:province":"AB",
    "sg:tags":[
        "general",
        "contractor"
    ],
    "wof:name":"Smash & Sons Contracting Ltd",
    "wof:placetype":"venue"
},
  "geometry": {"coordinates":[-118.82999420199999,55.1666374207],"type":"Point"}
}