{
  "type": "Feature",
  "properties": {
    "addr:full":"66 Clarkson Ave York ON M6E 2T6",
    "addr:housenumber":"66",
    "addr:postcode":"m6e 2t6",
    "addr:street":"Clarkson Ave",
    "iso:country":"CA",
    "sg:address":"66 Clarkson Ave",
    "sg:city":"York",
    "sg:classifiers":[
        {
            "category":"Building & Trades",
            "subcategory":"Plumbing",
            "type":"Services"
        }
    ],
    "sg:phone":"+1 416 787 1896",
    "sg:postcode":"M6E 2T6",
    "sg:province":"ON",
    "sg:tags":[
        "heating",
        "contractor"
    ],
    "wof:name":"Hulton Mechanical Svc Inc",
    "wof:placetype":"venue"
},
  "geometry": {"coordinates":[-79.462097168,43.6975288391],"type":"Point"}
}