{
  "type": "Feature",
  "properties": {
    "addr:full":"112 Humber Rd Corner Brook NL A2H 1E8",
    "addr:housenumber":"112",
    "addr:postcode":"a2h 1e8",
    "addr:street":"Humber Rd",
    "iso:country":"CA",
    "sg:address":"112 Humber Rd",
    "sg:city":"Corner Brook",
    "sg:classifiers":[
        {
            "category":"Education",
            "subcategory":"School",
            "type":"Public Place"
        }
    ],
    "sg:phone":"+1 709 634 1700",
    "sg:postcode":"A2H 1E8",
    "sg:province":"NL",
    "wof:name":"Immaculate Heart-Mary School",
    "wof:placetype":"venue"
},
  "geometry": {"coordinates":[-57.9313240051,48.9629516602],"type":"Point"}
}