{
  "type": "Feature",
  "properties": {
    "iso:country":"CA",
    "sg:city":"Saint-Philippe-DE-Neri",
    "sg:classifiers":[
        {
            "category":"Education",
            "subcategory":"Library",
            "type":"Public Place"
        }
    ],
    "sg:phone":"+1 418 498 3500",
    "sg:postcode":"G0L 4A0",
    "sg:province":"QC",
    "sg:tags":[
        "government"
    ],
    "wof:name":"Mont-Carmel Bibliotheque",
    "wof:placetype":"venue"
},
  "geometry": {"coordinates":[-69.883102417,47.4670753479],"type":"Point"}
}