{
  "type": "Feature",
  "properties": {
    "iso:country":"CA",
    "sg:address":"7250 Boul Taschereau # 74",
    "sg:city":"Brossard",
    "sg:classifiers":[
        {
            "category":"Shopping",
            "type":"Retail Goods"
        }
    ],
    "sg:phone":"+1 450 671 4744",
    "sg:postcode":"J4W 1M9",
    "sg:province":"QC",
    "sg:tags":[
        "telephone",
        "cellular"
    ],
    "wof:name":"Cellular Solution",
    "wof:placetype":"venue"
},
  "geometry": {"coordinates":[-73.4655456543,45.4619140625],"type":"Point"}
}