{
  "type": "Feature",
  "properties": {
    "addr:full":"20 Burnham Crt Grimsby ON L3M 5E9",
    "addr:housenumber":"20",
    "addr:postcode":"l3m 5e9",
    "addr:street":"Burnham Crt",
    "iso:country":"CA",
    "sg:address":"20 Burnham Crt",
    "sg:city":"Grimsby",
    "sg:classifiers":[
        {
            "category":"Wholesale",
            "subcategory":"Machinery & Supplies",
            "type":"Manufacturing & Wholesale Goods"
        }
    ],
    "sg:phone":"+1 905 945 7997",
    "sg:postcode":"L3M 5E9",
    "sg:province":"ON",
    "sg:tags":[
        "instrument",
        "surveying"
    ],
    "wof:name":"Centreline Precision Svc Inc",
    "wof:placetype":"venue"
},
  "geometry": {"coordinates":[-79.54280853269999,43.1967391968],"type":"Point"}
}