{
  "type": "Feature",
  "properties": {
    "addr:full":"North Bay ON P1B 4Z2",
    "addr:postcode":"p1b 4z2",
    "iso:country":"CA",
    "sg:city":"North Bay",
    "sg:classifiers":[
        {
            "category":"Health Services",
            "subcategory":"Doctor",
            "type":"Services"
        }
    ],
    "sg:phone":"+1 705 474 1500",
    "sg:postcode":"P1B 4Z2",
    "sg:province":"ON",
    "sg:tags":[
        "physician",
        "surgeon"
    ],
    "wof:name":"O'Donnell, J MD",
    "wof:placetype":"venue"
},
  "geometry": {"coordinates":[-79.46584320069999,46.332736969],"type":"Point"}
}