{
  "type": "Feature",
  "properties": {
    "addr:full":"102 Talbot St W Leamington ON N8H 1M8",
    "addr:housenumber":"102",
    "addr:postcode":"n8h 1m8",
    "addr:street":"Talbot St W",
    "iso:country":"CA",
    "sg:address":"102 Talbot St W",
    "sg:city":"Leamington",
    "sg:classifiers":[
        {
            "category":"Organizations",
            "subcategory":"Professional Association",
            "type":"Services"
        }
    ],
    "sg:phone":"+1 519 326 0595",
    "sg:postcode":"N8H 1M8",
    "sg:province":"ON",
    "sg:tags":[
        "counselor",
        "marriage",
        "family"
    ],
    "wof:name":"Lilyan M Sabga Counselling Svc",
    "wof:placetype":"venue"
},
  "geometry": {"coordinates":[-82.60477400000001,42.051731],"type":"Point"}
}