{
  "type": "Feature",
  "properties": {
    "addr:full":"2770 1E Av Notre-Dame-Des-Pins QC G0M 1K0",
    "addr:housenumber":"2770",
    "addr:postcode":"g0m 1k0",
    "addr:street":"1E Av Notre-Dame-Des-Pins",
    "iso:country":"CA",
    "sg:address":"2770 1E Av",
    "sg:city":"Notre-Dame-Des-Pins",
    "sg:classifiers":[
        {
            "category":"Organizations",
            "subcategory":"Religious Organization",
            "type":"Services"
        }
    ],
    "sg:phone":"+1 418 774 9110",
    "sg:postcode":"G0M 1K0",
    "sg:province":"QC",
    "sg:tags":[
        "church"
    ],
    "wof:name":"Fabrique Notre-Dame-Des-Pins",
    "wof:placetype":"venue"
},
  "geometry": {"coordinates":[-70.713448,46.184643],"type":"Point"}
}