{
  "type": "Feature",
  "properties": {
    "addr:full":"4377 Steeles Ave W North York ON M3N 1V7",
    "addr:housenumber":"4377",
    "addr:postcode":"m3n 1v7",
    "addr:street":"Steeles Ave W",
    "iso:country":"CA",
    "sg:address":"4377 Steeles Ave W",
    "sg:city":"North York",
    "sg:classifiers":[
        {
            "category":"Restaurant",
            "type":"Food & Drink"
        }
    ],
    "sg:phone":"+1 416 661 8989",
    "sg:postcode":"M3N 1V7",
    "sg:province":"ON",
    "wof:name":"Giorgio D Restaurant",
    "wof:placetype":"venue"
},
  "geometry": {"coordinates":[-79.53113555909999,43.7733306885],"type":"Point"}
}