{
  "type": "Feature",
  "properties": {
    "iso:country":"CA",
    "sg:address":"2840 58 Ave SE",
    "sg:city":"Calgary",
    "sg:classifiers":[
        {
            "category":"Freight",
            "type":"Transportation"
        }
    ],
    "sg:phone":"+1 403 236 8999",
    "sg:postcode":"T2C 0B3",
    "sg:province":"AB",
    "sg:tags":[
        "trucking"
    ],
    "wof:name":"East West Express Inc",
    "wof:placetype":"venue"
},
  "geometry": {"coordinates":[-113.995651,51.002251],"type":"Point"}
}