{
  "type": "Feature",
  "properties": {
    "addr:full":"400 Spence Ave Hawkesbury ON K6A 2Y3",
    "addr:housenumber":"400",
    "addr:postcode":"k6a 2y3",
    "addr:street":"Spence Ave",
    "iso:country":"CA",
    "sg:address":"400 Spence Ave",
    "sg:city":"Hawkesbury",
    "sg:classifiers":[
        {
            "category":"Shopping",
            "subcategory":"Department Store",
            "type":"Retail Goods"
        }
    ],
    "sg:phone":"+1 613 632 1273",
    "sg:postcode":"K6A 2Y3",
    "sg:province":"ON",
    "wof:name":"Hawkesbury Mall",
    "wof:placetype":"venue"
},
  "geometry": {"coordinates":[-74.611664,45.598534],"type":"Point"}
}