{
  "type": "Feature",
  "properties": {
    "addr:full":"Bancroft ON K0L 1C0",
    "addr:postcode":"k0l 1c0",
    "iso:country":"CA",
    "sg:city":"Bancroft",
    "sg:classifiers":[
        {
            "category":"Real Estate",
            "subcategory":"Real Estate Agent",
            "type":"Services"
        }
    ],
    "sg:phone":"+1 613 332 5500",
    "sg:postcode":"K0L 1C0",
    "sg:province":"ON",
    "wof:name":"Four Seasons Realty Ltd",
    "wof:placetype":"venue"
},
  "geometry": {"coordinates":[-77.862503,45.084663],"type":"Point"}
}