{
  "type": "Feature",
  "properties": {
    "iso:country":"CA",
    "sg:address":"253 Grand Ave W",
    "sg:city":"Chatham",
    "sg:classifiers":[
        {
            "category":"Professional",
            "subcategory":"Accounting & Tax Preparation",
            "type":"Services"
        }
    ],
    "sg:phone":"+1 519 351 1350",
    "sg:postcode":"N7L 1C3",
    "sg:province":"ON",
    "sg:tags":[
        "accountant"
    ],
    "wof:name":"Peterson, Murray CA",
    "wof:placetype":"venue"
},
  "geometry": {"coordinates":[-82.1988830566,42.402885437],"type":"Point"}
}