{
  "type": "Feature",
  "properties": {
    "addr:full":"105 118E Rue Shawinigan-Sud QC G9P 3E5",
    "addr:housenumber":"105",
    "addr:postcode":"g9p 3e5",
    "addr:street":"118E Rue Shawinigan-Sud",
    "iso:country":"CA",
    "sg:address":"105 118E Rue",
    "sg:city":"Shawinigan-Sud",
    "sg:classifiers":[
        {
            "category":"Health Services",
            "subcategory":"Nursing And Care Facility",
            "type":"Services"
        }
    ],
    "sg:phone":"+1 819 536 4291",
    "sg:postcode":"G9P 3E5",
    "sg:province":"QC",
    "sg:tags":[
        "home",
        "retirement",
        "community"
    ],
    "wof:name":"Residence Le Jardin DE Reves",
    "wof:placetype":"venue"
},
  "geometry": {"coordinates":[-72.7444610596,46.5236473083],"type":"Point"}
}