{
  "type": "Feature",
  "properties": {
    "addr:full":"437 Ch DE LA Cote Sud Boisbriand QC J7E 4H5",
    "addr:housenumber":"437",
    "addr:postcode":"j7e 4h5",
    "addr:street":"Ch De La Cote Sud",
    "iso:country":"CA",
    "sg:address":"437 Ch DE LA Cote Sud",
    "sg:city":"Boisbriand",
    "sg:classifiers":[
        {
            "category":"Building & Trades",
            "subcategory":"Construction",
            "type":"Services"
        }
    ],
    "sg:phone":"+1 450 433 8899",
    "sg:postcode":"J7E 4H5",
    "sg:province":"QC",
    "sg:tags":[
        "insulation",
        "heat",
        "contractor"
    ],
    "wof:name":"Atelier Isolation Unik",
    "wof:placetype":"venue"
},
  "geometry": {"coordinates":[-73.8996963501,45.629650116],"type":"Point"}
}