{
  "type": "Feature",
  "properties": {
    "addr:full":"3500 Rue Wellington Verdun QC H4G 1T3",
    "addr:housenumber":"3500",
    "addr:postcode":"h4g 1t3",
    "addr:street":"Rue Wellington",
    "iso:country":"CA",
    "sg:address":"3500 Rue Wellington",
    "sg:city":"Verdun",
    "sg:classifiers":[
        {
            "category":"Health Services",
            "subcategory":"Hospital",
            "type":"Services"
        }
    ],
    "sg:phone":"+1 514 761 5874",
    "sg:postcode":"H4G 1T3",
    "sg:province":"QC",
    "sg:tags":[
        "site",
        "reception",
        "wedding"
    ],
    "wof:name":"Centre D'Acceuil Real Morel",
    "wof:placetype":"venue"
},
  "geometry": {"coordinates":[-73.56554412840001,45.468585968],"type":"Point"}
}