{
  "type": "Feature",
  "properties": {
    "addr:full":"175 Mississaga St E Orillia ON L3V 1V8",
    "addr:housenumber":"175",
    "addr:postcode":"l3v 1v8",
    "addr:street":"Mississaga St E",
    "iso:country":"CA",
    "sg:address":"175 Mississaga St E",
    "sg:city":"Orillia",
    "sg:classifiers":[
        {
            "category":"Shopping",
            "subcategory":"Bicycles & Sporting Goods",
            "type":"Retail Goods"
        }
    ],
    "sg:phone":"+1 705 325 2461",
    "sg:postcode":"L3V 1V8",
    "sg:province":"ON",
    "wof:name":"Kahuna Surfshop",
    "wof:placetype":"venue"
},
  "geometry": {"coordinates":[-79.415222,44.609978],"type":"Point"}
}