{
  "type": "Feature",
  "properties": {
    "addr:full":"5351 46 Ave SE Salmon Arm BC V1E 1X2",
    "addr:housenumber":"5351",
    "addr:postcode":"v1e 1x2",
    "addr:street":"46 Ave Se",
    "iso:country":"CA",
    "sg:address":"5351 46 Ave SE",
    "sg:city":"Salmon Arm",
    "sg:classifiers":[
        {
            "category":"Freight",
            "type":"Transportation"
        }
    ],
    "sg:phone":"+1 250 833 1442",
    "sg:postcode":"V1E 1X2",
    "sg:province":"BC",
    "sg:tags":[
        "commercial",
        "storage"
    ],
    "wof:name":"Southside Storage & Leasing",
    "wof:placetype":"venue"
},
  "geometry": {"coordinates":[-119.223678589,50.6664009094],"type":"Point"}
}