{
  "type": "Feature",
  "properties": {
    "addr:full":"241 Norseman St Etobicoke ON M8Z 2R5",
    "addr:housenumber":"241",
    "addr:postcode":"m8z 2r5",
    "addr:street":"Norseman St",
    "iso:country":"CA",
    "sg:address":"241 Norseman St",
    "sg:city":"Etobicoke",
    "sg:classifiers":[
        {
            "category":"Retail",
            "subcategory":"Auto Repair",
            "type":"Services"
        }
    ],
    "sg:phone":"+1 416 231 2963",
    "sg:postcode":"M8Z 2R5",
    "sg:province":"ON",
    "sg:tags":[
        "lining",
        "brake"
    ],
    "wof:name":"Tapley Sales Canada",
    "wof:placetype":"venue"
},
  "geometry": {"coordinates":[-79.524353,43.63282],"type":"Point"}
}