{
  "type": "Feature",
  "properties": {
    "addr:full":"5750 Place Kubota Drummondville QC J2B 6V4",
    "addr:housenumber":"5750",
    "addr:postcode":"j2b 6v4",
    "addr:street":"Place Kubota",
    "iso:country":"CA",
    "sg:address":"5750 Place Kubota",
    "sg:city":"Drummondville",
    "sg:classifiers":[
        {
            "category":"Retail",
            "subcategory":"Auto Repair",
            "type":"Services"
        }
    ],
    "sg:phone":"+1 819 477 1171",
    "sg:postcode":"J2B 6V4",
    "sg:province":"QC",
    "sg:tags":[
        "transmission",
        "automobile",
        "repairing"
    ],
    "wof:name":"Transmission Pepin Inc",
    "wof:placetype":"venue"
},
  "geometry": {"coordinates":[-72.537941,45.893337],"type":"Point"}
}