{
  "type": "Feature",
  "properties": {
    "addr:full":"Chilliwack BC V2R 5P9",
    "addr:postcode":"v2r 5p9",
    "iso:country":"CA",
    "sg:city":"Chilliwack",
    "sg:classifiers":[
        {
            "category":"Shopping",
            "type":"Retail Goods"
        }
    ],
    "sg:phone":"+1 604 858 7813",
    "sg:postcode":"V2R 5P9",
    "sg:province":"BC",
    "sg:tags":[
        "supply",
        "art",
        "artist",
        "material",
        "gallery",
        "dealer"
    ],
    "wof:name":"Julie Anne's Art & Framing",
    "wof:placetype":"venue"
},
  "geometry": {"coordinates":[-121.957466126,49.1433296204],"type":"Point"}
}