{
  "type": "Feature",
  "properties": {
    "addr:full":"26456 Highway 62 Bancroft ON K0L 1C0",
    "addr:housenumber":"26456",
    "addr:postcode":"k0l 1c0",
    "addr:street":"Highway 62",
    "iso:country":"CA",
    "sg:address":"26456 Highway 62",
    "sg:city":"Bancroft",
    "sg:classifiers":[
        {
            "category":"Recreation",
            "type":"Entertainment"
        }
    ],
    "sg:phone":"+1 613 332 6125",
    "sg:postcode":"K0L 1C0",
    "sg:province":"ON",
    "sg:tags":[
        "center"
    ],
    "wof:name":"Old Hastings Snow Riders Inc",
    "wof:placetype":"venue"
},
  "geometry": {"coordinates":[-77.85334777830001,45.0565414429],"type":"Point"}
}