{
  "type": "Feature",
  "properties": {
    "addr:full":"1598 Queen St W Toronto ON M6R 1A8",
    "addr:housenumber":"1598",
    "addr:postcode":"m6r 1a8",
    "addr:street":"Queen St W",
    "iso:country":"CA",
    "sg:address":"1598 Queen St W",
    "sg:city":"Toronto",
    "sg:classifiers":[
        {
            "category":"Restaurant",
            "type":"Food & Drink"
        }
    ],
    "sg:phone":"+1 416 538 6292",
    "sg:postcode":"M6R 1A8",
    "sg:province":"ON",
    "sg:tags":[
        "caterer"
    ],
    "wof:name":"Canadian Caribbean Catering",
    "wof:placetype":"venue"
},
  "geometry": {"coordinates":[-79.44156599999999,43.639748],"type":"Point"}
}