{
  "type": "Feature",
  "properties": {
    "addr:full":"1000 Rue Dessaulles Saint-Hyacinthe QC J2S 8W1",
    "addr:housenumber":"1000",
    "addr:postcode":"j2s 8w1",
    "addr:street":"Rue Dessaulles",
    "iso:country":"CA",
    "sg:address":"1000 Rue Dessaulles",
    "sg:city":"Saint-Hyacinthe",
    "sg:classifiers":[
        {
            "category":"Professional",
            "subcategory":"Accounting & Tax Preparation",
            "type":"Services"
        }
    ],
    "sg:phone":"+1 450 774 9251",
    "sg:postcode":"J2S 8W1",
    "sg:province":"QC",
    "sg:tags":[
        "accountant"
    ],
    "wof:name":"Verrier Paquin Hebert",
    "wof:placetype":"venue"
},
  "geometry": {"coordinates":[-72.94506072999999,45.6280899048],"type":"Point"}
}