{
  "type": "Feature",
  "properties": {
    "addr:full":"27 Rue Du Petit-Champlain Quebec QC G1K 4H5",
    "addr:housenumber":"27",
    "addr:postcode":"g1k 4h5",
    "addr:street":"Rue Du Petit-Champlain",
    "iso:country":"CA",
    "sg:address":"27 Rue Du Petit-Champlain",
    "sg:city":"Quebec",
    "sg:classifiers":[
        {
            "category":"Shopping",
            "subcategory":"Gifts & Souvenirs",
            "type":"Retail Goods"
        }
    ],
    "sg:phone":"+1 418 692 1743",
    "sg:postcode":"G1K 4H5",
    "sg:province":"QC",
    "sg:tags":[
        "shop"
    ],
    "wof:name":"Boutique Pot-En-Ciel Enr",
    "wof:placetype":"venue"
},
  "geometry": {"coordinates":[-71.2033462524,46.8121147156],"type":"Point"}
}