{
  "type": "Feature",
  "properties": {
    "addr:full":"143 Commercial St Glace Bay NS B1A 3B9",
    "addr:housenumber":"143",
    "addr:postcode":"b1a 3b9",
    "addr:street":"Commercial St",
    "iso:country":"CA",
    "sg:address":"143 Commercial St",
    "sg:city":"Glace Bay",
    "sg:classifiers":[
        {
            "category":"Health Services",
            "subcategory":"Doctor",
            "type":"Services"
        }
    ],
    "sg:phone":"+1 902 842 0030",
    "sg:postcode":"B1A 3B9",
    "sg:province":"NS",
    "sg:tags":[
        "physician",
        "surgeon"
    ],
    "wof:name":"C K Butler Phsycian Inc",
    "wof:placetype":"venue"
},
  "geometry": {"coordinates":[-59.956387,46.196377],"type":"Point"}
}