{
  "type": "Feature",
  "properties": {
    "addr:full":"Calgary AB T2Z 4H5",
    "addr:postcode":"t2z 4h5",
    "iso:country":"CA",
    "sg:city":"Calgary",
    "sg:classifiers":[
        {
            "category":"Manufacturing",
            "subcategory":"Rubber & Plastics",
            "type":"Manufacturing & Wholesale Goods"
        }
    ],
    "sg:phone":"+1 403 236 7700",
    "sg:postcode":"T2Z 4H5",
    "sg:province":"AB",
    "sg:tags":[
        "product"
    ],
    "wof:name":"Plastic Works",
    "wof:placetype":"venue"
},
  "geometry": {"coordinates":[-113.972084,50.946037],"type":"Point"}
}