{
  "type": "Feature",
  "properties": {
    "addr:full":"Edson AB T7E 1V3",
    "addr:postcode":"t7e 1v3",
    "iso:country":"CA",
    "sg:city":"Edson",
    "sg:classifiers":[
        {
            "category":"Insurance",
            "subcategory":"Insurance Agent",
            "type":"Services"
        }
    ],
    "sg:phone":"+1 780 723 6045",
    "sg:postcode":"T7E 1V3",
    "sg:province":"AB",
    "wof:name":"Soltys Insurance Svc Ltd",
    "wof:placetype":"venue"
},
  "geometry": {"coordinates":[-116.43182373,53.5798072815],"type":"Point"}
}