{
  "type": "Feature",
  "properties": {
    "addr:full":"Standard AB T0J 3G0",
    "addr:postcode":"t0j 3g0",
    "iso:country":"CA",
    "sg:city":"Standard",
    "sg:classifiers":[
        {
            "category":"Retail",
            "subcategory":"Auto Repair",
            "type":"Services"
        }
    ],
    "sg:phone":"+1 403 644 3744",
    "sg:postcode":"T0J 3G0",
    "sg:province":"AB",
    "sg:tags":[
        "repairing",
        "automobile"
    ],
    "wof:name":"Reliable Motors",
    "wof:placetype":"venue"
},
  "geometry": {"coordinates":[-112.983223,51.109612],"type":"Point"}
}