{
  "type": "Feature",
  "properties": {
    "iso:country":"CA",
    "sg:address":"12850 96 Ave",
    "sg:city":"Surrey",
    "sg:classifiers":[
        {
            "category":"Food & Beverages",
            "subcategory":"Liquor & Beverages",
            "type":"Retail Goods"
        }
    ],
    "sg:phone":"+1 604 588 0711",
    "sg:postcode":"V3V 6A8",
    "sg:province":"BC",
    "sg:tags":[
        "store"
    ],
    "wof:name":"Liquor Stores-Government",
    "wof:placetype":"venue"
},
  "geometry": {"coordinates":[-122.866592407,49.1770477295],"type":"Point"}
}