{
  "type": "Feature",
  "properties": {
    "addr:full":"1222 Gladstone Ave Victoria BC V8T 1G6",
    "addr:housenumber":"1222",
    "addr:postcode":"v8t 1g6",
    "addr:street":"Gladstone Ave",
    "iso:country":"CA",
    "sg:address":"1222 Gladstone Ave",
    "sg:city":"Victoria",
    "sg:classifiers":[
        {
            "category":"Social Services",
            "subcategory":"Child Care",
            "type":"Services"
        }
    ],
    "sg:phone":"+1 250 384 2132",
    "sg:postcode":"V8T 1G6",
    "sg:province":"BC",
    "wof:name":"Springridge Early Childhood",
    "wof:placetype":"venue"
},
  "geometry": {"coordinates":[-123.349136352,48.4307556152],"type":"Point"}
}