{
  "type": "Feature",
  "properties": {
    "addr:full":"3150 St Mary's Rd Winnipeg MB R2N 4A8",
    "addr:housenumber":"3150",
    "addr:postcode":"r2n 4a8",
    "addr:street":"St Mary'S Rd",
    "iso:country":"CA",
    "sg:address":"3150 St Mary's Rd",
    "sg:city":"Winnipeg",
    "sg:classifiers":[
        {
            "category":"Retail",
            "subcategory":"Auto Repair",
            "type":"Services"
        }
    ],
    "sg:phone":"+1 204 257 2336",
    "sg:postcode":"R2N 4A8",
    "sg:province":"MB",
    "sg:tags":[
        "repairing",
        "automobile"
    ],
    "wof:name":"St Mary's Svc",
    "wof:placetype":"venue"
},
  "geometry": {"coordinates":[-97.1282196045,49.769733429],"type":"Point"}
}