{
  "type": "Feature",
  "properties": {
    "addr:full":"21 Betts Ave Yorkton SK S3N 1M1",
    "addr:housenumber":"21",
    "addr:postcode":"s3n 1m1",
    "addr:street":"Betts Ave",
    "iso:country":"CA",
    "sg:address":"21 Betts Ave",
    "sg:city":"Yorkton",
    "sg:classifiers":[
        {
            "category":"Restaurant",
            "type":"Food & Drink"
        }
    ],
    "sg:phone":"+1 306 782 0278",
    "sg:postcode":"S3N 1M1",
    "sg:province":"SK",
    "wof:name":"Wing's Restaurant",
    "wof:placetype":"venue"
},
  "geometry": {"coordinates":[-102.463852,51.210884],"type":"Point"}
}