{
  "type": "Feature",
  "properties": {
    "addr:full":"2111 Mccallum Rd Abbotsford BC V2S 3N7",
    "addr:housenumber":"2111",
    "addr:postcode":"v2s 3n7",
    "addr:street":"Mccallum Rd",
    "iso:country":"CA",
    "sg:address":"2111 Mccallum Rd",
    "sg:city":"Abbotsford",
    "sg:classifiers":[
        {
            "category":"Banks & Credit Unions",
            "subcategory":"Financial Services",
            "type":"Services"
        }
    ],
    "sg:phone":"+1 604 854 5358",
    "sg:postcode":"V2S 3N7",
    "sg:province":"BC",
    "sg:tags":[
        "company",
        "holding"
    ],
    "wof:name":"Forthright Holdings CO Ltd",
    "wof:placetype":"venue"
},
  "geometry": {"coordinates":[-122.293434143,49.0403518677],"type":"Point"}
}