{
  "type": "Feature",
  "properties": {
    "addr:full":"Toronto ON M5V 1W5",
    "addr:postcode":"m5v 1w5",
    "iso:country":"CA",
    "sg:city":"Toronto",
    "sg:classifiers":[
        {
            "category":"Professional",
            "subcategory":"Advertising",
            "type":"Services"
        }
    ],
    "sg:phone":"+1 416 506 9930",
    "sg:postcode":"M5V 1W5",
    "sg:province":"ON",
    "sg:tags":[
        "counselor"
    ],
    "wof:name":"Brainstorm Group",
    "wof:placetype":"venue"
},
  "geometry": {"coordinates":[-79.3900299072,43.6494140625],"type":"Point"}
}