{
  "type": "Feature",
  "properties": {
    "iso:country":"CA",
    "sg:address":"4388 112 Rte",
    "sg:city":"Ascot Corner",
    "sg:classifiers":[
        {
            "category":"Autos & Motor Vehicles",
            "subcategory":"Automobile Sales",
            "type":"Retail Goods"
        }
    ],
    "sg:phone":"+1 819 569 2575",
    "sg:postcode":"J0B 1A0",
    "sg:province":"QC",
    "sg:tags":[
        "truck"
    ],
    "wof:name":"Tardif Diesel Inc",
    "wof:placetype":"venue"
},
  "geometry": {"coordinates":[-71.8158187866,45.4323272705],"type":"Point"}
}