{
  "type": "Feature",
  "properties": {
    "addr:full":"2305 Mceown Ave Saskatoon SK S7J 2H1",
    "addr:housenumber":"2305",
    "addr:postcode":"s7j 2h1",
    "addr:street":"Mceown Ave",
    "iso:country":"CA",
    "sg:address":"2305 Mceown Ave",
    "sg:city":"Saskatoon",
    "sg:classifiers":[
        {
            "category":"Health Services",
            "subcategory":"Doctor",
            "type":"Services"
        }
    ],
    "sg:phone":"+1 306 374 1522",
    "sg:postcode":"S7J 2H1",
    "sg:province":"SK",
    "sg:tags":[
        "dentist"
    ],
    "wof:name":"Roberts, Cam DDS",
    "wof:placetype":"venue"
},
  "geometry": {"coordinates":[-106.617752,52.102207],"type":"Point"}
}