{
  "type": "Feature",
  "properties": {
    "addr:full":"199 Nicol St Nanaimo BC V9R 4T1",
    "addr:housenumber":"199",
    "addr:postcode":"v9r 4t1",
    "addr:street":"Nicol St",
    "iso:country":"CA",
    "sg:address":"199 Nicol St",
    "sg:city":"Nanaimo",
    "sg:classifiers":[
        {
            "category":"Autos & Motor Vehicles",
            "subcategory":"Fuel & Gas Station",
            "type":"Retail Goods"
        }
    ],
    "sg:phone":"+1 250 753 5352",
    "sg:postcode":"V9R 4T1",
    "sg:province":"BC",
    "sg:tags":[
        "oil"
    ],
    "wof:name":"Nicol Street Shell",
    "wof:placetype":"venue"
},
  "geometry": {"coordinates":[-123.933830261,49.158115387],"type":"Point"}
}