{
  "type": "Feature",
  "properties": {
    "addr:full":"Calgary AB T2C 4E4",
    "addr:postcode":"t2c 4e4",
    "iso:country":"CA",
    "sg:city":"Calgary",
    "sg:classifiers":[
        {
            "category":"Restaurant",
            "type":"Food & Drink"
        }
    ],
    "sg:phone":"+1 403 236 7000",
    "sg:postcode":"T2C 4E4",
    "sg:province":"AB",
    "wof:name":"Boston Pizza",
    "wof:placetype":"venue"
},
  "geometry": {"coordinates":[-114.015495,50.977055],"type":"Point"}
}