{
  "type": "Feature",
  "properties": {
    "addr:full":"2048 Front Rd Vittoria ON N0E 1W0",
    "addr:housenumber":"2048",
    "addr:postcode":"n0e 1w0",
    "addr:street":"Front Rd",
    "iso:country":"CA",
    "sg:address":"2048 Front Rd",
    "sg:city":"Vittoria",
    "sg:classifiers":[
        {
            "category":"Museum",
            "subcategory":"Botanical Garden",
            "type":"Entertainment"
        }
    ],
    "sg:phone":"+1 519 428 2637",
    "sg:postcode":"N0E 1W0",
    "sg:province":"ON",
    "sg:tags":[
        "zoo"
    ],
    "wof:name":"Canadian Raptor Conservancy",
    "wof:placetype":"venue"
},
  "geometry": {"coordinates":[-80.32357,42.76215],"type":"Point"}
}