{
  "type": "Feature",
  "properties": {
    "addr:full":"RR 4 Penetanguishene ON L9M 2H7",
    "addr:postcode":"l9m 2h7",
    "addr:street":"Rr 4",
    "iso:country":"CA",
    "sg:address":"RR 4",
    "sg:city":"Penetanguishene",
    "sg:classifiers":[
        {
            "category":"Building & Trades",
            "subcategory":"Plumbing",
            "type":"Services"
        }
    ],
    "sg:phone":"+1 705 533 2236",
    "sg:postcode":"L9M 2H7",
    "sg:province":"ON",
    "sg:tags":[
        "disposal",
        "system",
        "sewage",
        "septic"
    ],
    "wof:name":"Regional Sanitation Disposal",
    "wof:placetype":"venue"
},
  "geometry": {"coordinates":[-79.935356,44.76812],"type":"Point"}
}