{
  "type": "Feature",
  "properties": {
    "addr:full":"830 Fleury St Regina SK S4N 4W6",
    "addr:housenumber":"830",
    "addr:postcode":"s4n 4w6",
    "addr:street":"Fleury St",
    "iso:country":"CA",
    "sg:address":"830 Fleury St",
    "sg:city":"Regina",
    "sg:classifiers":[
        {
            "category":"Retail",
            "subcategory":"Auto Repair",
            "type":"Services"
        }
    ],
    "sg:phone":"+1 306 569 1122",
    "sg:postcode":"S4N 4W6",
    "sg:province":"SK",
    "sg:tags":[
        "spring"
    ],
    "wof:name":"Spring Service Ltd",
    "wof:placetype":"venue"
},
  "geometry": {"coordinates":[-104.577003,50.465004],"type":"Point"}
}