{
  "type": "Feature",
  "properties": {
    "addr:full":"2115 Urbana Rd NW Calgary AB T2N 4B9",
    "addr:housenumber":"2115",
    "addr:postcode":"t2n 4b9",
    "addr:street":"Urbana Rd Nw",
    "iso:country":"CA",
    "sg:address":"2115 Urbana Rd NW",
    "sg:city":"Calgary",
    "sg:classifiers":[
        {
            "category":"Organizations",
            "subcategory":"Religious Organization",
            "type":"Services"
        }
    ],
    "sg:phone":"+1 403 289 7172",
    "sg:postcode":"T2N 4B9",
    "sg:province":"AB",
    "sg:tags":[
        "church"
    ],
    "wof:name":"Foothills Mennonite Church",
    "wof:placetype":"venue"
},
  "geometry": {"coordinates":[-114.135338,51.071499],"type":"Point"}
}