{
  "type": "Feature",
  "properties": {
    "addr:full":"786 Rue Principale Sainte-Helene-DE-Bagot QC J0H 1M0",
    "addr:housenumber":"786",
    "addr:postcode":"j0h 1m0",
    "addr:street":"Rue Principale",
    "iso:country":"CA",
    "sg:address":"786 Rue Principale",
    "sg:city":"Sainte-Helene-DE-Bagot",
    "sg:classifiers":[
        {
            "category":"Education",
            "subcategory":"School",
            "type":"Public Place"
        }
    ],
    "sg:phone":"+1 450 791 2300",
    "sg:postcode":"J0H 1M0",
    "sg:province":"QC",
    "sg:tags":[
        "academic",
        "instruction",
        "music",
        "special"
    ],
    "wof:name":"Claude Paradis Ecole-Musique",
    "wof:placetype":"venue"
},
  "geometry": {"coordinates":[-72.73318500000001,45.72924],"type":"Point"}
}