{
  "type": "Feature",
  "properties": {
    "addr:full":"104 Church St Inverness NS B0E 1N0",
    "addr:housenumber":"104",
    "addr:postcode":"b0e 1n0",
    "addr:street":"Church St",
    "iso:country":"CA",
    "sg:address":"104 Church St",
    "sg:city":"Inverness",
    "sg:classifiers":[
        {
            "category":"Social Services",
            "subcategory":"Adult Care",
            "type":"Services"
        }
    ],
    "sg:phone":"+1 902 258 3115",
    "sg:postcode":"B0E 1N0",
    "sg:province":"NS",
    "sg:tags":[
        "community",
        "facility"
    ],
    "wof:name":"Cape Breton West Small Option",
    "wof:placetype":"venue"
},
  "geometry": {"coordinates":[-61.302666,46.230976],"type":"Point"}
}