{
  "type": "Feature",
  "properties": {
    "addr:full":"761 Av Du Parc Amos QC J9T 4M1",
    "addr:postcode":"j9t 4m1",
    "addr:street":"761 Av Du Parc Amos",
    "iso:country":"CA",
    "sg:address":"761 Av Du Parc",
    "sg:city":"Amos",
    "sg:classifiers":[
        {
            "category":"Wholesale",
            "subcategory":"Machinery & Supplies",
            "type":"Manufacturing & Wholesale Goods"
        }
    ],
    "sg:phone":"+1 819 732 8871",
    "sg:postcode":"J9T 4M1",
    "sg:province":"QC",
    "sg:tags":[
        "forestry",
        "machine",
        "shop",
        "timber"
    ],
    "wof:name":"Usinage Gn Roy Inc",
    "wof:placetype":"venue"
},
  "geometry": {"coordinates":[-78.127022,48.560837],"type":"Point"}
}