{
  "type": "Feature",
  "properties": {
    "addr:full":"Barrie ON L4M 5G1",
    "addr:postcode":"l4m 5g1",
    "iso:country":"CA",
    "sg:city":"Barrie",
    "sg:classifiers":[
        {
            "category":"Professional",
            "subcategory":"Engineering",
            "type":"Services"
        }
    ],
    "sg:phone":"+1 705 725 0242",
    "sg:postcode":"L4M 5G1",
    "sg:province":"ON",
    "sg:tags":[
        "engineer"
    ],
    "wof:name":"Gosse & Gilewicz Engrng Inc",
    "wof:placetype":"venue"
},
  "geometry": {"coordinates":[-79.677948,44.409729],"type":"Point"}
}