{
  "type": "Feature",
  "properties": {
    "iso:country":"CA",
    "sg:address":"1136 Devonshire Dr",
    "sg:city":"Regina",
    "sg:classifiers":[
        {
            "category":"Education",
            "subcategory":"Dance Studio",
            "type":"Public Place"
        }
    ],
    "sg:phone":"+1 306 781 6151",
    "sg:postcode":"S4X 3P2",
    "sg:province":"SK",
    "sg:tags":[
        "instruction",
        "dancing"
    ],
    "wof:name":"Dance Dimensions",
    "wof:placetype":"venue"
},
  "geometry": {"coordinates":[-104.67282104500001,50.4963264465],"type":"Point"}
}