{
  "type": "Feature",
  "properties": {
    "addr:full":"Lasalle QC H8P 2E1",
    "addr:postcode":"h8p 2e1",
    "iso:country":"CA",
    "sg:city":"Lasalle",
    "sg:classifiers":[
        {
            "category":"Building & Trades",
            "subcategory":"Electrical",
            "type":"Services"
        }
    ],
    "sg:phone":"+1 514 599 3563",
    "sg:postcode":"H8P 2E1",
    "sg:province":"QC",
    "sg:tags":[
        "electric",
        "contractor"
    ],
    "wof:name":"Dupuis Arsenault Electrique",
    "wof:placetype":"venue"
},
  "geometry": {"coordinates":[-73.591942,45.43317],"type":"Point"}
}