{
  "type": "Feature",
  "properties": {
    "addr:full":"1621 Mill St Revelstoke BC V0E 2S0",
    "addr:housenumber":"1621",
    "addr:postcode":"v0e 2s0",
    "addr:street":"Mill St",
    "iso:country":"CA",
    "sg:address":"1621 Mill St",
    "sg:city":"Revelstoke",
    "sg:classifiers":[
        {
            "category":"Manufacturing",
            "subcategory":"Lumber",
            "type":"Manufacturing & Wholesale Goods"
        }
    ],
    "sg:phone":"+1 250 837 2222",
    "sg:postcode":"V0E 2S0",
    "sg:province":"BC",
    "sg:tags":[
        "sawmill"
    ],
    "wof:name":"Downie Street Sawmills Ltd",
    "wof:placetype":"venue"
},
  "geometry": {"coordinates":[-118.199645996,50.9893188477],"type":"Point"}
}