{
  "type": "Feature",
  "properties": {
    "addr:full":"Salt Spring Island BC V8K 2R8",
    "addr:postcode":"v8k 2r8",
    "iso:country":"CA",
    "sg:city":"Salt Spring Island",
    "sg:classifiers":[
        {
            "category":"Personal",
            "type":"Services"
        }
    ],
    "sg:phone":"+1 250 537 9955",
    "sg:postcode":"V8K 2R8",
    "sg:province":"BC",
    "sg:tags":[
        "shopping"
    ],
    "wof:name":"Southern Golf Island Home",
    "wof:placetype":"venue"
},
  "geometry": {"coordinates":[-123.508652,48.861698],"type":"Point"}
}