{
  "type": "Feature",
  "properties": {
    "iso:country":"CA",
    "sg:city":"Oshawa",
    "sg:classifiers":[
        {
            "category":"Retail",
            "subcategory":"Auto Repair",
            "type":"Services"
        }
    ],
    "sg:phone":"+1 905 404 8395",
    "sg:postcode":"L1H 6L3",
    "sg:province":"ON",
    "sg:tags":[
        "truck"
    ],
    "wof:name":"Durham Truck Ctr",
    "wof:placetype":"venue"
},
  "geometry": {"coordinates":[-78.832283,43.882336],"type":"Point"}
}