{
  "type": "Feature",
  "properties": {
    "addr:full":"Medicine Hat AB T1B 1E3",
    "addr:postcode":"t1b 1e3",
    "iso:country":"CA",
    "sg:city":"Medicine Hat",
    "sg:classifiers":[
        {
            "category":"Personal",
            "subcategory":"Beauty Salon",
            "type":"Services"
        }
    ],
    "sg:phone":"+1 403 529 2250",
    "sg:postcode":"T1B 1E3",
    "sg:province":"AB",
    "wof:name":"Headline Hairstyling",
    "wof:placetype":"venue"
},
  "geometry": {"coordinates":[-110.66458129900001,50.0113105774],"type":"Point"}
}