{
  "type": "Feature",
  "properties": {
    "addr:full":"526 Frederick St Kitchener ON N2B 3R1",
    "addr:housenumber":"526",
    "addr:postcode":"n2b 3r1",
    "addr:street":"Frederick St",
    "iso:country":"CA",
    "sg:address":"526 Frederick St",
    "sg:city":"Kitchener",
    "sg:classifiers":[
        {
            "category":"Health Services",
            "subcategory":"Doctor",
            "type":"Services"
        }
    ],
    "sg:phone":"+1 519 578 4600",
    "sg:postcode":"N2B 3R1",
    "sg:province":"ON",
    "sg:tags":[
        "dentist"
    ],
    "wof:name":"Beaton, W Douglas DDS",
    "wof:placetype":"venue"
},
  "geometry": {"coordinates":[-80.4701538086,43.4593887329],"type":"Point"}
}