{
  "type": "Feature",
  "properties": {
    "addr:full":"7116 Kerr St Vancouver BC V5S 4W2",
    "addr:housenumber":"7116",
    "addr:postcode":"v5s 4w2",
    "addr:street":"Kerr St",
    "iso:country":"CA",
    "sg:address":"7116 Kerr St",
    "sg:city":"Vancouver",
    "sg:classifiers":[
        {
            "category":"Education",
            "subcategory":"Special Training",
            "type":"Public Place"
        }
    ],
    "sg:phone":"+1 604 434 7323",
    "sg:postcode":"V5S 4W2",
    "sg:province":"BC",
    "sg:tags":[
        "tutoring"
    ],
    "wof:name":"Sylvan Learning Ctr",
    "wof:placetype":"venue"
},
  "geometry": {"coordinates":[-123.041175842,49.2189788818],"type":"Point"}
}