{
  "type": "Feature",
  "properties": {
    "addr:full":"RR 2 Marmora ON K0K 2M0",
    "addr:postcode":"k0k 2m0",
    "addr:street":"Rr 2",
    "iso:country":"CA",
    "sg:address":"RR 2",
    "sg:city":"Marmora",
    "sg:classifiers":[
        {
            "category":"Government",
            "subcategory":"Office",
            "type":"Public Place"
        }
    ],
    "sg:phone":"+1 613 472 2172",
    "sg:postcode":"K0K 2M0",
    "sg:province":"ON",
    "sg:tags":[
        "village"
    ],
    "wof:name":"Deloro Municipal Office",
    "wof:placetype":"venue"
},
  "geometry": {"coordinates":[-77.6815567017,44.483089447],"type":"Point"}
}