{
  "type": "Feature",
  "properties": {
    "iso:country":"CA",
    "sg:address":"1207 Rue Antonio-Lemaire",
    "sg:city":"Chicoutimi",
    "sg:classifiers":[
        {
            "category":"Manufacturing",
            "subcategory":"Glass & Minerals",
            "type":"Manufacturing & Wholesale Goods"
        }
    ],
    "sg:phone":"+1 418 545 4200",
    "sg:postcode":"G7K 1J2",
    "sg:province":"QC",
    "sg:tags":[
        "refractory"
    ],
    "wof:name":"Groupe Refraco Inc",
    "wof:placetype":"venue"
},
  "geometry": {"coordinates":[-71.1121749878,48.3883285522],"type":"Point"}
}