{
  "type": "Feature",
  "properties": {
    "addr:full":"3222-02 Main Terminal # 300 Richmond BC V7B 1V1",
    "addr:housenumber":"3222-02",
    "addr:postcode":"v7b 1v1",
    "addr:street":"Main",
    "iso:country":"CA",
    "sg:address":"3222-02 Main Terminal # 300",
    "sg:city":"Richmond",
    "sg:classifiers":[
        {
            "category":"Manufacturing",
            "subcategory":"Food",
            "type":"Manufacturing & Wholesale Goods"
        }
    ],
    "sg:phone":"+1 604 270 8600",
    "sg:postcode":"V7B 1V1",
    "sg:province":"BC",
    "sg:tags":[
        "cocoa",
        "chocolate"
    ],
    "wof:name":"Rocky Mountain Chocolate Fctry",
    "wof:placetype":"venue"
},
  "geometry": {"coordinates":[-123.13651299999999,49.163174],"type":"Point"}
}