{
  "type": "Feature",
  "properties": {
    "addr:full":"Windsor ON N8Y 4T9",
    "addr:postcode":"n8y 4t9",
    "iso:country":"CA",
    "sg:city":"Windsor",
    "sg:classifiers":[
        {
            "category":"Health Services",
            "subcategory":"Doctor",
            "type":"Services"
        }
    ],
    "sg:phone":"+1 519 985 6988",
    "sg:postcode":"N8Y 4T9",
    "sg:province":"ON",
    "sg:tags":[
        "dentist"
    ],
    "wof:name":"Harvey, Cliff DDS",
    "wof:placetype":"venue"
},
  "geometry": {"coordinates":[-83.00056499999999,42.312077],"type":"Point"}
}