{
  "type": "Feature",
  "properties": {
    "addr:full":"Brampton ON L6T 5T1",
    "addr:postcode":"l6t 5t1",
    "iso:country":"CA",
    "sg:city":"Brampton",
    "sg:classifiers":[
        {
            "category":"Manufacturing",
            "subcategory":"Apparel",
            "type":"Manufacturing & Wholesale Goods"
        }
    ],
    "sg:phone":"+1 905 793 1330",
    "sg:postcode":"L6T 5T1",
    "sg:province":"ON",
    "sg:tags":[
        "clothing"
    ],
    "wof:name":"East West Fashion",
    "wof:placetype":"venue"
},
  "geometry": {"coordinates":[-79.6704330444,43.7222213745],"type":"Point"}
}