{
  "type": "Feature",
  "properties": {
    "addr:full":"3600 Rue Valiquette Saint-Laurent QC H4S 1X8",
    "addr:housenumber":"3600",
    "addr:postcode":"h4s 1x8",
    "addr:street":"Rue Valiquette",
    "iso:country":"CA",
    "sg:address":"3600 Rue Valiquette",
    "sg:city":"Saint-Laurent",
    "sg:classifiers":[
        {
            "category":"Building & Trades",
            "subcategory":"Plumbing",
            "type":"Services"
        }
    ],
    "sg:phone":"+1 514 332 2235",
    "sg:postcode":"H4S 1X8",
    "sg:province":"QC",
    "sg:tags":[
        "sheet",
        "work",
        "metal",
        "contractor"
    ],
    "wof:name":"Elva Metal Products Inc",
    "wof:placetype":"venue"
},
  "geometry": {"coordinates":[-73.75002288819999,45.5003623962],"type":"Point"}
}