{
  "type": "Feature",
  "properties": {
    "addr:full":"636 Rue Principale Saint-Jacques NB E7B 1Y4",
    "addr:housenumber":"636",
    "addr:postcode":"e7b 1y4",
    "addr:street":"Rue Principale",
    "iso:country":"CA",
    "sg:address":"636 Rue Principale",
    "sg:city":"Saint-Jacques",
    "sg:classifiers":[
        {
            "category":"Freight",
            "type":"Transportation"
        }
    ],
    "sg:phone":"+1 506 735 7238",
    "sg:postcode":"E7B 1Y4",
    "sg:province":"NB",
    "sg:tags":[
        "trucking"
    ],
    "wof:name":"Armour Transportation Systems",
    "wof:placetype":"venue"
},
  "geometry": {"coordinates":[-68.37744903559999,47.4183998108],"type":"Point"}
}