{
  "type": "Feature",
  "properties": {
    "addr:full":"180 Ch Des Patriotes Sorel-Tracy QC J3P 2L3",
    "addr:housenumber":"180",
    "addr:postcode":"j3p 2l3",
    "addr:street":"Ch Des Patriotes",
    "iso:country":"CA",
    "sg:address":"180 Ch Des Patriotes",
    "sg:city":"Sorel-Tracy",
    "sg:classifiers":[
        {
            "category":"Wholesale",
            "subcategory":"Machinery & Supplies",
            "type":"Manufacturing & Wholesale Goods"
        }
    ],
    "sg:phone":"+1 450 742 5648",
    "sg:postcode":"J3P 2L3",
    "sg:province":"QC",
    "sg:tags":[
        "contractor"
    ],
    "wof:name":"Marine International Dragagne",
    "wof:placetype":"venue"
},
  "geometry": {"coordinates":[-73.12097199999999,46.02879],"type":"Point"}
}