{
  "type": "Feature",
  "properties": {
    "addr:full":"901 1st Ave N Saskatoon SK S7K 1Y4",
    "addr:housenumber":"901",
    "addr:postcode":"s7k 1y4",
    "addr:street":"1St Ave N",
    "iso:country":"CA",
    "sg:address":"901 1st Ave N",
    "sg:city":"Saskatoon",
    "sg:classifiers":[
        {
            "category":"Professional",
            "subcategory":"Accounting & Tax Preparation",
            "type":"Services"
        }
    ],
    "sg:phone":"+1 306 975 0377",
    "sg:postcode":"S7K 1Y4",
    "sg:province":"SK",
    "sg:tags":[
        "return",
        "filing"
    ],
    "wof:name":"R Stevenson & Assoc",
    "wof:placetype":"venue"
},
  "geometry": {"coordinates":[-106.659622192,52.1412391663],"type":"Point"}
}