{
  "type": "Feature",
  "properties": {
    "addr:full":"42 Rue Du Parc Bouctouche NB E4S 3C5",
    "addr:housenumber":"42",
    "addr:postcode":"e4s 3c5",
    "addr:street":"Rue Du Parc",
    "iso:country":"CA",
    "sg:address":"42 Rue Du Parc",
    "sg:city":"Bouctouche",
    "sg:classifiers":[
        {
            "category":"Retail",
            "subcategory":"Animal Services",
            "type":"Services"
        }
    ],
    "sg:phone":"+1 506 743 8199",
    "sg:postcode":"E4S 3C5",
    "sg:province":"NB",
    "sg:tags":[
        "pet",
        "grooming",
        "washing"
    ],
    "wof:name":"Bouctouche Grooming & Pet",
    "wof:placetype":"venue"
},
  "geometry": {"coordinates":[-64.72510528559999,46.4739151001],"type":"Point"}
}