{
  "type": "Feature",
  "properties": {
    "addr:full":"53 Rue Renaud Repentigny QC J6A 6C1",
    "addr:housenumber":"53",
    "addr:postcode":"j6a 6c1",
    "addr:street":"Rue Renaud",
    "iso:country":"CA",
    "sg:address":"53 Rue Renaud",
    "sg:city":"Repentigny",
    "sg:classifiers":[
        {
            "category":"Social Services",
            "subcategory":"Child Care",
            "type":"Services"
        }
    ],
    "sg:phone":"+1 450 585 4086",
    "sg:postcode":"J6A 6C1",
    "sg:province":"QC",
    "wof:name":"Garderie Les P'Tits Bouts",
    "wof:placetype":"venue"
},
  "geometry": {"coordinates":[-73.439751,45.746613],"type":"Point"}
}