{
  "type": "Feature",
  "properties": {
    "addr:full":"78 Milltown Blvd St Stephen NB E3L 1G6",
    "addr:housenumber":"78",
    "addr:postcode":"e3l 1g6",
    "addr:street":"Milltown Blvd",
    "iso:country":"CA",
    "sg:address":"78 Milltown Blvd",
    "sg:city":"St Stephen",
    "sg:classifiers":[
        {
            "category":"Personal",
            "subcategory":"Beauty Salon",
            "type":"Services"
        }
    ],
    "sg:phone":"+1 506 466 4536",
    "sg:postcode":"E3L 1G6",
    "sg:province":"NB",
    "wof:name":"Talk of the Town",
    "wof:placetype":"venue"
},
  "geometry": {"coordinates":[-67.278229,45.192436],"type":"Point"}
}