{
  "type": "Feature",
  "properties": {
    "addr:full":"20 Heritage Rd # 12 Markham ON L3P 3P3",
    "addr:housenumber":"20",
    "addr:postcode":"l3p 3p3",
    "addr:street":"Heritage Rd # 12",
    "iso:country":"CA",
    "sg:address":"20 Heritage Rd # 12",
    "sg:city":"Markham",
    "sg:classifiers":[
        {
            "category":"Retail",
            "subcategory":"Auto Repair",
            "type":"Services"
        }
    ],
    "sg:phone":"+1 905 472 1115",
    "sg:postcode":"L3P 3P3",
    "sg:province":"ON",
    "sg:tags":[
        "body",
        "automobile",
        "painting"
    ],
    "wof:name":"Kkt Auto Collision Ltd",
    "wof:placetype":"venue"
},
  "geometry": {"coordinates":[-79.2799453735,43.8712158203],"type":"Point"}
}