{
  "type": "Feature",
  "properties": {
    "addr:full":"1473 Ch Principal Saint-Joseph-Du-Lac QC J0N 1M0",
    "addr:postcode":"1473;j0n 1m0",
    "addr:street":"Ch Principal",
    "iso:country":"CA",
    "sg:address":"1473 Ch Principal",
    "sg:city":"Saint-Joseph-Du-Lac",
    "sg:classifiers":[
        {
            "category":"Farming",
            "subcategory":"Orchard",
            "type":"Manufacturing & Wholesale Goods"
        }
    ],
    "sg:phone":"+1 450 491 7859",
    "sg:postcode":"J0N 1M0",
    "sg:province":"QC",
    "sg:tags":[
        "vegetable",
        "cider",
        "fruit",
        "mills"
    ],
    "wof:name":"Vergers Lafrance",
    "wof:placetype":"venue"
},
  "geometry": {"coordinates":[-74.0134429932,45.5416488647],"type":"Point"}
}