{
  "type": "Feature",
  "properties": {
    "addr:full":"Calgary AB T2A 2K2",
    "addr:postcode":"t2a 2k2",
    "iso:country":"CA",
    "sg:city":"Calgary",
    "sg:classifiers":[
        {
            "category":"Retail",
            "subcategory":"Laundry & Dry Cleaning",
            "type":"Services"
        }
    ],
    "sg:phone":"+1 403 235 3399",
    "sg:postcode":"T2A 2K2",
    "sg:province":"AB",
    "sg:tags":[
        "cleaners",
        "alteration"
    ],
    "wof:name":"Marlborough Alterations",
    "wof:placetype":"venue"
},
  "geometry": {"coordinates":[-113.979934692,51.0525283813],"type":"Point"}
}