{
  "type": "Feature",
  "properties": {
    "addr:full":"Stoney Creek ON L8E 5S7",
    "addr:postcode":"l8e 5s7",
    "iso:country":"CA",
    "sg:city":"Stoney Creek",
    "sg:classifiers":[
        {
            "category":"Wholesale",
            "subcategory":"Hardware",
            "type":"Manufacturing & Wholesale Goods"
        }
    ],
    "sg:phone":"+1 905 643 6600",
    "sg:postcode":"L8E 5S7",
    "sg:province":"ON",
    "sg:tags":[
        "tool"
    ],
    "wof:name":"Wera Tools Inc",
    "wof:placetype":"venue"
},
  "geometry": {"coordinates":[-79.69272613530001,43.2280769348],"type":"Point"}
}