{
  "type": "Feature",
  "properties": {
    "iso:country":"CA",
    "sg:address":"516 Brackley Point Rd",
    "sg:city":"Charlottetown",
    "sg:classifiers":[
        {
            "category":"Building & Trades",
            "subcategory":"Electrical",
            "type":"Services"
        }
    ],
    "sg:phone":"+1 902 368 1309",
    "sg:postcode":"C1E 1Z3",
    "sg:province":"PE",
    "sg:tags":[
        "electric",
        "contractor"
    ],
    "wof:name":"Jackson Electric Ltd",
    "wof:placetype":"venue"
},
  "geometry": {"coordinates":[-63.1395797729,46.291721344],"type":"Point"}
}