{
  "type": "Feature",
  "properties": {
    "addr:full":"Concord ON L4K 2G6",
    "addr:postcode":"l4k 2g6",
    "iso:country":"CA",
    "sg:city":"Concord",
    "sg:classifiers":[
        {
            "category":"Wholesale",
            "subcategory":"Machinery & Supplies",
            "type":"Manufacturing & Wholesale Goods"
        }
    ],
    "sg:phone":"+1 905 669 4500",
    "sg:postcode":"L4K 2G6",
    "sg:province":"ON",
    "sg:tags":[
        "valve"
    ],
    "wof:name":"Floval Equipment Ltd",
    "wof:placetype":"venue"
},
  "geometry": {"coordinates":[-79.49852,43.811069],"type":"Point"}
}