{
  "type": "Feature",
  "properties": {
    "addr:full":"300 Rossland Rd E Oshawa ON L1G 2X1",
    "addr:housenumber":"300",
    "addr:postcode":"l1g 2x1",
    "addr:street":"Rossland Rd E",
    "iso:country":"CA",
    "sg:address":"300 Rossland Rd E",
    "sg:city":"Oshawa",
    "sg:classifiers":[
        {
            "category":"Organizations",
            "subcategory":"Religious Organization",
            "type":"Services"
        }
    ],
    "sg:phone":"+1 905 433 2960",
    "sg:postcode":"L1G 2X1",
    "sg:province":"ON",
    "sg:tags":[
        "church"
    ],
    "wof:name":"Calvary Baptist Church",
    "wof:placetype":"venue"
},
  "geometry": {"coordinates":[-78.861076,43.91745],"type":"Point"}
}