{
  "type": "Feature",
  "properties": {
    "addr:full":"3138 Ch Sainte-Foy Sainte-Foy QC G1X 1R1",
    "addr:postcode":"3138;g1x 1r1",
    "addr:street":"Ch Sainte-Foy",
    "iso:country":"CA",
    "sg:address":"3138 Ch Sainte-Foy",
    "sg:city":"Sainte-Foy",
    "sg:classifiers":[
        {
            "category":"Personal",
            "subcategory":"Beauty Salon",
            "type":"Services"
        }
    ],
    "sg:phone":"+1 418 653 6011",
    "sg:postcode":"G1X 1R1",
    "sg:province":"QC",
    "wof:name":"Salon Abc DE LA Coiffure",
    "wof:placetype":"venue"
},
  "geometry": {"coordinates":[-71.2917633057,46.7692108154],"type":"Point"}
}