{
  "type": "Feature",
  "properties": {
    "iso:country":"CA",
    "sg:city":"Sainte-Marthe-Sur-Le-Lac",
    "sg:classifiers":[
        {
            "category":"Manufacturing",
            "subcategory":"Metals",
            "type":"Manufacturing & Wholesale Goods"
        }
    ],
    "sg:phone":"+1 450 491 0055",
    "sg:postcode":"J0N 1P0",
    "sg:province":"QC",
    "sg:tags":[
        "solder"
    ],
    "wof:name":"Soudure A Savard Inc",
    "wof:placetype":"venue"
},
  "geometry": {"coordinates":[-73.93236541749999,45.5292510986],"type":"Point"}
}