{
  "type": "Feature",
  "properties": {
    "addr:full":"32 Danforth Cres St Albert AB T8N 4W9",
    "addr:housenumber":"32",
    "addr:postcode":"t8n 4w9",
    "addr:street":"Danforth Cres",
    "iso:country":"CA",
    "sg:address":"32 Danforth Cres",
    "sg:city":"St Albert",
    "sg:classifiers":[
        {
            "category":"Building & Trades",
            "subcategory":"Construction",
            "type":"Services"
        }
    ],
    "sg:phone":"+1 780 459 3058",
    "sg:postcode":"T8N 4W9",
    "sg:province":"AB",
    "sg:tags":[
        "general",
        "contractor"
    ],
    "wof:name":"Sturgeonview Construction Ltd",
    "wof:placetype":"venue"
},
  "geometry": {"coordinates":[-113.64621699999999,53.651451],"type":"Point"}
}