{
  "type": "Feature",
  "properties": {
    "addr:full":"1632 Rue Lindsay Mont-Joli QC G5H 3A6",
    "addr:housenumber":"1632",
    "addr:postcode":"g5h 3a6",
    "addr:street":"Rue Lindsay",
    "iso:country":"CA",
    "sg:address":"1632 Rue Lindsay",
    "sg:city":"Mont-Joli",
    "sg:classifiers":[
        {
            "category":"Education",
            "subcategory":"School",
            "type":"Public Place"
        }
    ],
    "sg:phone":"+1 418 775 3328",
    "sg:postcode":"G5H 3A6",
    "sg:province":"QC",
    "wof:name":"Ecole Notre-Dame DE Lourdes",
    "wof:placetype":"venue"
},
  "geometry": {"coordinates":[-68.187927,48.584587],"type":"Point"}
}