{
  "type": "Feature",
  "properties": {
    "addr:full":"15 Ch Du Golf Saint-Gedeon QC G0W 2P0",
    "addr:housenumber":"15",
    "addr:postcode":"g0w 2p0",
    "addr:street":"Ch Du Golf Saint-Gedeon",
    "iso:country":"CA",
    "sg:address":"15 Ch Du Golf",
    "sg:city":"Saint-Gedeon",
    "sg:classifiers":[
        {
            "category":"Organizations",
            "subcategory":"Community Association",
            "type":"Services"
        }
    ],
    "sg:phone":"+1 418 487 3313",
    "sg:postcode":"G0W 2P0",
    "sg:province":"QC",
    "sg:tags":[
        "club",
        "course",
        "golf"
    ],
    "wof:name":"Club DE Golf Lac St-Jean Inc",
    "wof:placetype":"venue"
},
  "geometry": {"coordinates":[-71.776398,48.55397],"type":"Point"}
}