{
  "type": "Feature",
  "properties": {
    "addr:full":"York ON M9N 3V3",
    "addr:postcode":"m9n 3v3",
    "iso:country":"CA",
    "sg:city":"York",
    "sg:classifiers":[
        {
            "category":"Restaurant",
            "type":"Food & Drink"
        }
    ],
    "sg:phone":"+1 416 240 8326",
    "sg:postcode":"M9N 3V3",
    "sg:province":"ON",
    "wof:name":"Lawrence Park Restaurant",
    "wof:placetype":"venue"
},
  "geometry": {"coordinates":[-79.511612,43.701057],"type":"Point"}
}