{
  "type": "Feature",
  "properties": {
    "addr:full":"Masson-Angers QC J8M 1Y7",
    "addr:postcode":"j8m 1y7",
    "iso:country":"CA",
    "sg:city":"Masson-Angers",
    "sg:classifiers":[
        {
            "category":"Building & Trades",
            "subcategory":"Construction",
            "type":"Services"
        }
    ],
    "sg:phone":"+1 819 281 0836",
    "sg:postcode":"J8M 1Y7",
    "sg:province":"QC",
    "sg:tags":[
        "contractor"
    ],
    "wof:name":"Fondation Andre Constant",
    "wof:placetype":"venue"
},
  "geometry": {"coordinates":[-75.420791626,45.5565338135],"type":"Point"}
}