{
  "type": "Feature",
  "properties": {
    "addr:full":"226 Pacific Ave Saskatoon SK S7K 1N9",
    "addr:housenumber":"226",
    "addr:postcode":"s7k 1n9",
    "addr:street":"Pacific Ave",
    "iso:country":"CA",
    "sg:address":"226 Pacific Ave",
    "sg:city":"Saskatoon",
    "sg:classifiers":[
        {
            "category":"Manufacturing",
            "subcategory":"Retail Goods",
            "type":"Manufacturing & Wholesale Goods"
        }
    ],
    "sg:phone":"+1 306 244 5885",
    "sg:postcode":"S7K 1N9",
    "sg:province":"SK",
    "sg:tags":[
        "rubber",
        "stamp",
        "marking",
        "devices",
        "plastic"
    ],
    "wof:name":"Rose Marking Devices Ltd",
    "wof:placetype":"venue"
},
  "geometry": {"coordinates":[-106.667015076,52.1315536499],"type":"Point"}
}