{
  "type": "Feature",
  "properties": {
    "addr:full":"60 36E Av Bois-Des-Filion QC J6Z 2G6",
    "addr:housenumber":"60",
    "addr:postcode":"j6z 2g6",
    "addr:street":"36E Av Bois-Des-Filion",
    "iso:country":"CA",
    "sg:address":"60 36E Av",
    "sg:city":"Bois-Des-Filion",
    "sg:classifiers":[
        {
            "category":"Government",
            "subcategory":"Office",
            "type":"Public Place"
        }
    ],
    "sg:phone":"+1 450 621 1460",
    "sg:postcode":"J6Z 2G6",
    "sg:province":"QC",
    "sg:tags":[
        "village"
    ],
    "wof:name":"Bois Des Filion Hotel DE Ville",
    "wof:placetype":"venue"
},
  "geometry": {"coordinates":[-73.75769042970001,45.6676063538],"type":"Point"}
}