{
  "type": "Feature",
  "properties": {
    "addr:full":"70 King William St # 13 Huntsville ON P1H 2A5",
    "addr:housenumber":"70",
    "addr:postcode":"p1h 2a5",
    "addr:street":"King William St # 13",
    "iso:country":"CA",
    "sg:address":"70 King William St # 13",
    "sg:city":"Huntsville",
    "sg:classifiers":[
        {
            "category":"Shopping",
            "subcategory":"Clothing, Apparel, & Fashions",
            "type":"Retail Goods"
        }
    ],
    "sg:phone":"+1 705 788 0958",
    "sg:postcode":"P1H 2A5",
    "sg:province":"ON",
    "wof:name":"Cotton Ginny",
    "wof:placetype":"venue"
},
  "geometry": {"coordinates":[-79.20616099999999,45.333908],"type":"Point"}
}