{
  "type": "Feature",
  "properties": {
    "addr:full":"47 Clarence St #49 Ottawa ON K1N 9K1",
    "addr:housenumber":"47",
    "addr:postcode":"k1n 9k1",
    "addr:street":"Clarence St # 49",
    "iso:country":"CA",
    "sg:address":"47 Clarence St #49",
    "sg:city":"Ottawa",
    "sg:classifiers":[
        {
            "category":"Restaurant",
            "type":"Food & Drink"
        }
    ],
    "sg:phone":"+1 613 241 1343",
    "sg:postcode":"K1N 9K1",
    "sg:province":"ON",
    "wof:name":"Empire Grill",
    "wof:placetype":"venue"
},
  "geometry": {"coordinates":[-75.69407653810001,45.4287528992],"type":"Point"}
}