{
  "type": "Feature",
  "properties": {
    "addr:full":"810 Goderich St Port Elgin ON N0H 2C3",
    "addr:housenumber":"810",
    "addr:postcode":"n0h 2c3",
    "addr:street":"Goderich St",
    "iso:country":"CA",
    "sg:address":"810 Goderich St",
    "sg:city":"Port Elgin",
    "sg:classifiers":[
        {
            "category":"Social Services",
            "subcategory":"Child Care",
            "type":"Services"
        }
    ],
    "sg:phone":"+1 519 832 6230",
    "sg:postcode":"N0H 2C3",
    "sg:province":"ON",
    "wof:name":"Paddington Station Day Care",
    "wof:placetype":"venue"
},
  "geometry": {"coordinates":[-81.385231,44.441067],"type":"Point"}
}