{
  "type": "Feature",
  "properties": {
    "addr:full":"3067 Mainway Burlington ON L7M 1A1",
    "addr:housenumber":"3067",
    "addr:postcode":"l7m 1a1",
    "addr:street":"Mainway",
    "iso:country":"CA",
    "sg:address":"3067 Mainway",
    "sg:city":"Burlington",
    "sg:classifiers":[
        {
            "category":"Shopping",
            "subcategory":"Books",
            "type":"Retail Goods"
        }
    ],
    "sg:phone":"+1 905 319 9500",
    "sg:postcode":"L7M 1A1",
    "sg:province":"ON",
    "sg:tags":[
        "bible"
    ],
    "wof:name":"Bible League",
    "wof:placetype":"venue"
},
  "geometry": {"coordinates":[-79.808883667,43.3589286804],"type":"Point"}
}