{
  "type": "Feature",
  "properties": {
    "addr:full":"655 Garrison Rd Fort Erie ON L2A 1N5",
    "addr:housenumber":"655",
    "addr:postcode":"l2a 1n5",
    "addr:street":"Garrison Rd",
    "iso:country":"CA",
    "sg:address":"655 Garrison Rd",
    "sg:city":"Fort Erie",
    "sg:classifiers":[
        {
            "category":"Recreation",
            "type":"Entertainment"
        }
    ],
    "sg:phone":"+1 905 871 1277",
    "sg:postcode":"L2A 1N5",
    "sg:province":"ON",
    "sg:tags":[
        "bingo",
        "game"
    ],
    "wof:name":"Golden Nugget Bingo",
    "wof:placetype":"venue"
},
  "geometry": {"coordinates":[-78.9396820068,42.905216217],"type":"Point"}
}