{
  "type": "Feature",
  "properties": {
    "iso:country":"CA",
    "sg:address":"1660 Renfrew St",
    "sg:city":"Vancouver",
    "sg:classifiers":[
        {
            "category":"Restaurant",
            "type":"Food & Drink"
        }
    ],
    "sg:phone":"+1 604 255 6441",
    "sg:postcode":"V5K 4E1",
    "sg:province":"BC",
    "wof:name":"Osteria Napoli Restorante",
    "wof:placetype":"venue"
},
  "geometry": {"coordinates":[-123.043991089,49.2699279785],"type":"Point"}
}