{
  "type": "Feature",
  "properties": {
    "iso:country":"CA",
    "sg:city":"Burnaby",
    "sg:classifiers":[
        {
            "category":"Recreation",
            "subcategory":"Arcade",
            "type":"Entertainment"
        }
    ],
    "sg:phone":"+1 604 294 8084",
    "sg:postcode":"V5G 4L6",
    "sg:province":"BC",
    "sg:tags":[
        "amusement",
        "devices"
    ],
    "wof:name":"Thrill Time Entertainment Intl",
    "wof:placetype":"venue"
},
  "geometry": {"coordinates":[-122.99733734100001,49.2548446655],"type":"Point"}
}