{
  "type": "Feature",
  "properties": {
    "iso:country":"CA",
    "sg:address":"110 Coutts Bay Rd",
    "sg:city":"Rideau Ferry",
    "sg:classifiers":[
        {
            "category":"Recreation",
            "subcategory":"Marina",
            "type":"Entertainment"
        }
    ],
    "sg:phone":"+1 613 264 2628",
    "sg:postcode":"K0G 1W0",
    "sg:province":"ON",
    "wof:name":"Rideau Ferry Harbour",
    "wof:placetype":"venue"
},
  "geometry": {"coordinates":[-76.15808868409999,44.8526649475],"type":"Point"}
}