{
  "type": "Feature",
  "properties": {
    "addr:full":"438 Rue Principale Lachute QC J8H 1Y3",
    "addr:housenumber":"438",
    "addr:postcode":"j8h 1y3",
    "addr:street":"Rue Principale",
    "iso:country":"CA",
    "sg:address":"438 Rue Principale",
    "sg:city":"Lachute",
    "sg:classifiers":[
        {
            "category":"Sports & Exercise",
            "subcategory":"Bowling",
            "type":"Entertainment"
        }
    ],
    "sg:phone":"+1 450 562 6759",
    "sg:postcode":"J8H 1Y3",
    "sg:province":"QC",
    "sg:tags":[
        "center"
    ],
    "wof:name":"Belanger Pierre",
    "wof:placetype":"venue"
},
  "geometry": {"coordinates":[-74.337204,45.656319],"type":"Point"}
}