{
  "type": "Feature",
  "properties": {
    "addr:full":"238 2 Ave NE Medicine Hat AB T1A 6A1",
    "addr:housenumber":"238",
    "addr:postcode":"t1a 6a1",
    "addr:street":"2 Ave Ne",
    "iso:country":"CA",
    "sg:address":"238 2 Ave NE",
    "sg:city":"Medicine Hat",
    "sg:classifiers":[
        {
            "category":"Organizations",
            "subcategory":"Religious Organization",
            "type":"Services"
        }
    ],
    "sg:phone":"+1 403 526 2265",
    "sg:postcode":"T1A 6A1",
    "sg:province":"AB",
    "sg:tags":[
        "church"
    ],
    "wof:name":"St Patrick's Roman Catholic",
    "wof:placetype":"venue"
},
  "geometry": {"coordinates":[-110.680458069,50.0452728271],"type":"Point"}
}