{
  "type": "Feature",
  "properties": {
    "addr:full":"99 Shore Rd Florence NS B1Y 1R2",
    "addr:housenumber":"99",
    "addr:postcode":"b1y 1r2",
    "addr:street":"Shore Rd",
    "iso:country":"CA",
    "sg:address":"99 Shore Rd",
    "sg:city":"Florence",
    "sg:classifiers":[
        {
            "category":"Manufacturing",
            "subcategory":"Signs",
            "type":"Manufacturing & Wholesale Goods"
        }
    ],
    "sg:phone":"+1 902 736 2668",
    "sg:postcode":"B1Y 1R2",
    "sg:province":"NS",
    "wof:name":"Sketchline Design Signs",
    "wof:placetype":"venue"
},
  "geometry": {"coordinates":[-60.251663,46.264202],"type":"Point"}
}