{
  "type": "Feature",
  "properties": {
    "addr:full":"21 Ch Cocagne Sud Cocagne NB E4R 2J7",
    "addr:housenumber":"21",
    "addr:postcode":"e4r 2j7",
    "addr:street":"Ch Cocagne Sud",
    "iso:country":"CA",
    "sg:address":"21 Ch Cocagne Sud",
    "sg:city":"Cocagne",
    "sg:classifiers":[
        {
            "category":"Autos & Motor Vehicles",
            "subcategory":"Boat Sales",
            "type":"Retail Goods"
        }
    ],
    "sg:phone":"+1 506 576 9558",
    "sg:postcode":"E4R 2J7",
    "sg:province":"NB",
    "sg:tags":[
        "propeller"
    ],
    "wof:name":"Maritime Propeller Rebuilding",
    "wof:placetype":"venue"
},
  "geometry": {"coordinates":[-64.6160583496,46.3341026306],"type":"Point"}
}