{
  "type": "Feature",
  "properties": {
    "addr:full":"5992 Boul Des Hetres Shawinigan QC G9N 4W4",
    "addr:housenumber":"5992",
    "addr:postcode":"g9n 4w4",
    "addr:street":"Boul Des Hetres",
    "iso:country":"CA",
    "sg:address":"5992 Boul Des Hetres",
    "sg:city":"Shawinigan",
    "sg:classifiers":[
        {
            "category":"Retail",
            "subcategory":"Car Wash",
            "type":"Services"
        }
    ],
    "sg:phone":"+1 819 539 4800",
    "sg:postcode":"G9N 4W4",
    "sg:province":"QC",
    "sg:tags":[
        "polishing",
        "washing"
    ],
    "wof:name":"Lave-Auto Des Hetres",
    "wof:placetype":"venue"
},
  "geometry": {"coordinates":[-72.723427,46.574959],"type":"Point"}
}