{
  "type": "Feature",
  "properties": {
    "addr:full":"Penticton BC V2A 5K1",
    "addr:postcode":"v2a 5k1",
    "iso:country":"CA",
    "sg:city":"Penticton",
    "sg:classifiers":[
        {
            "category":"Shopping",
            "subcategory":"Used Merchandise",
            "type":"Retail Goods"
        }
    ],
    "sg:phone":"+1 250 492 4615",
    "sg:postcode":"V2A 5K1",
    "sg:province":"BC",
    "sg:tags":[
        "pawnbroker"
    ],
    "wof:name":"Mike's Pawnbrokers",
    "wof:placetype":"venue"
},
  "geometry": {"coordinates":[-119.594764709,49.501209259],"type":"Point"}
}