{
  "type": "Feature",
  "properties": {
    "iso:country":"CA",
    "sg:address":"2830 Agricola St",
    "sg:city":"Halifax",
    "sg:classifiers":[
        {
            "category":"Professional",
            "subcategory":"Lawyer & Legal Services",
            "type":"Services"
        }
    ],
    "sg:phone":"+1 ",
    "sg:postcode":"B3K 4E4",
    "sg:province":"NS",
    "sg:tags":[
        "attorney",
        "government"
    ],
    "wof:name":"Nova Scotia Legal Aid",
    "wof:placetype":"venue"
},
  "geometry": {"coordinates":[-63.5980644226,44.658416748],"type":"Point"}
}