{
  "type": "Feature",
  "properties": {
    "iso:country":"CA",
    "sg:address":"56 Queen St",
    "sg:city":"Port Hope",
    "sg:classifiers":[
        {
            "category":"Government",
            "subcategory":"Office",
            "type":"Public Place"
        }
    ],
    "sg:phone":"+1 905 885 2415",
    "sg:postcode":"L1A 3Z9",
    "sg:province":"ON",
    "sg:tags":[
        "village"
    ],
    "wof:name":"Port Hope Engineer",
    "wof:placetype":"venue"
},
  "geometry": {"coordinates":[-78.2929611206,43.9492263794],"type":"Point"}
}