{
  "type": "Feature",
  "properties": {
    "iso:country":"CA",
    "sg:address":"3988 Boul Saint-Charles",
    "sg:city":"Pierrefonds",
    "sg:classifiers":[
        {
            "category":"Wholesale",
            "subcategory":"Meat",
            "type":"Manufacturing & Wholesale Goods"
        }
    ],
    "sg:phone":"+1 514 620 6914",
    "sg:postcode":"H9H 3C6",
    "sg:province":"QC",
    "sg:tags":[
        "delicatessen",
        "product"
    ],
    "wof:name":"Bernoise",
    "wof:placetype":"venue"
},
  "geometry": {"coordinates":[-73.866989,45.460789],"type":"Point"}
}