{
  "type": "Feature",
  "properties": {
    "addr:full":"4372 Notre Dame St Harrowsmith ON K0H 1V0",
    "addr:housenumber":"4372",
    "addr:postcode":"k0h 1v0",
    "addr:street":"Notre Dame St",
    "iso:country":"CA",
    "sg:address":"4372 Notre Dame St",
    "sg:city":"Harrowsmith",
    "sg:classifiers":[
        {
            "category":"Retail",
            "subcategory":"Auto Repair",
            "type":"Services"
        }
    ],
    "sg:phone":"+1 613 372 1493",
    "sg:postcode":"K0H 1V0",
    "sg:province":"ON",
    "sg:tags":[
        "repairing",
        "automobile",
        "inspection"
    ],
    "wof:name":"Jim's Auto Svc",
    "wof:placetype":"venue"
},
  "geometry": {"coordinates":[-76.6668014526,44.4058074951],"type":"Point"}
}