{
  "type": "Feature",
  "properties": {
    "addr:full":"2910 Altamont Cres West Vancouver BC V7V 3C1",
    "addr:housenumber":"2910",
    "addr:postcode":"v7v 3c1",
    "addr:street":"Altamont Cres",
    "iso:country":"CA",
    "sg:address":"2910 Altamont Cres",
    "sg:city":"West Vancouver",
    "sg:classifiers":[
        {
            "category":"Building & Trades",
            "subcategory":"Landscaping Services",
            "type":"Services"
        }
    ],
    "sg:phone":"+1 604 922 0136",
    "sg:postcode":"V7V 3C1",
    "sg:province":"BC",
    "sg:tags":[
        "landscape",
        "contractor"
    ],
    "wof:name":"Greenscape Design",
    "wof:placetype":"venue"
},
  "geometry": {"coordinates":[-123.194138,49.344715],"type":"Point"}
}