{
  "type": "Feature",
  "properties": {
    "addr:full":"5017 53rd Ave High Prairie AB T0G 1E0",
    "addr:housenumber":"5017",
    "addr:postcode":"t0g 1e0",
    "addr:street":"53Rd Ave",
    "iso:country":"CA",
    "sg:address":"5017 53rd Ave",
    "sg:city":"High Prairie",
    "sg:classifiers":[
        {
            "category":"Banks & Credit Unions",
            "subcategory":"Bank",
            "type":"Services"
        }
    ],
    "sg:phone":"+1 780 536 2667",
    "sg:postcode":"T0G 1E0",
    "sg:province":"AB",
    "wof:name":"Caisse Horizon Credit Union",
    "wof:placetype":"venue"
},
  "geometry": {"coordinates":[-116.48042297400001,55.4328842163],"type":"Point"}
}