{
  "type": "Feature",
  "properties": {
    "addr:full":"301 Millway Ave Concord ON L4K 4T3",
    "addr:housenumber":"301",
    "addr:postcode":"l4k 4t3",
    "addr:street":"Millway Ave",
    "iso:country":"CA",
    "sg:address":"301 Millway Ave",
    "sg:city":"Concord",
    "sg:classifiers":[
        {
            "category":"Manufacturing",
            "subcategory":"Tools & Machinery",
            "type":"Manufacturing & Wholesale Goods"
        }
    ],
    "sg:phone":"+1 905 761 0808",
    "sg:postcode":"L4K 4T3",
    "sg:province":"ON",
    "sg:tags":[
        "machine",
        "shop"
    ],
    "wof:name":"Dellcom Industries",
    "wof:placetype":"venue"
},
  "geometry": {"coordinates":[-79.52840399999999,43.801331],"type":"Point"}
}