{
  "type": "Feature",
  "properties": {
    "iso:country":"CA",
    "sg:address":"108 College St",
    "sg:city":"Liverpool",
    "sg:classifiers":[
        {
            "category":"Social Services",
            "subcategory":"Child Care",
            "type":"Services"
        }
    ],
    "sg:phone":"+1 902 354 5088",
    "sg:postcode":"B0T 1K0",
    "sg:province":"NS",
    "wof:name":"Queen's Day Care Assoc",
    "wof:placetype":"venue"
},
  "geometry": {"coordinates":[-64.7058639526,44.0340042114],"type":"Point"}
}