{
  "type": "Feature",
  "properties": {
    "addr:full":"524 Rang Saint-Amable Saint-Barnabe-Sud QC J0H 1G0",
    "addr:housenumber":"524",
    "addr:postcode":"j0h 1g0",
    "addr:street":"Rang Saint-Amable Saint-Barnabe-Sud",
    "iso:country":"CA",
    "sg:address":"524 Rang Saint-Amable",
    "sg:city":"Saint-Barnabe-Sud",
    "sg:classifiers":[
        {
            "category":"Shopping",
            "type":"Retail Goods"
        }
    ],
    "sg:phone":"+1 450 792 3685",
    "sg:postcode":"J0H 1G0",
    "sg:province":"QC",
    "sg:tags":[
        "trophy",
        "engraver",
        "medal",
        "award"
    ],
    "wof:name":"Trophes Marcel Belisle Inc",
    "wof:placetype":"venue"
},
  "geometry": {"coordinates":[-72.92491912840001,45.7284736633],"type":"Point"}
}