{
  "type": "Feature",
  "properties": {
    "addr:full":"1256 Sedgewick Cres Oakville ON L6L 1X6",
    "addr:housenumber":"1256",
    "addr:postcode":"l6l 1x6",
    "addr:street":"Sedgewick Cres",
    "iso:country":"CA",
    "sg:address":"1256 Sedgewick Cres",
    "sg:city":"Oakville",
    "sg:classifiers":[
        {
            "category":"Social Services",
            "subcategory":"Child Care",
            "type":"Services"
        }
    ],
    "sg:phone":"+1 905 825 6264",
    "sg:postcode":"L6L 1X6",
    "sg:province":"ON",
    "wof:name":"Sedgewick Child Care Ctr",
    "wof:placetype":"venue"
},
  "geometry": {"coordinates":[-79.695847,43.415878],"type":"Point"}
}