{
  "type": "Feature",
  "properties": {
    "addr:full":"90 King St Woodville ON K0M 2T0",
    "addr:housenumber":"90",
    "addr:postcode":"k0m 2t0",
    "addr:street":"King St",
    "iso:country":"CA",
    "sg:address":"90 King St",
    "sg:city":"Woodville",
    "sg:classifiers":[
        {
            "category":"Shopping",
            "subcategory":"Pharmacy",
            "type":"Retail Goods"
        }
    ],
    "sg:phone":"+1 705 439 2844",
    "sg:postcode":"K0M 2T0",
    "sg:province":"ON",
    "wof:name":"Ben's Pharmacy",
    "wof:placetype":"venue"
},
  "geometry": {"coordinates":[-78.990234,44.39817],"type":"Point"}
}