{
  "type": "Feature",
  "properties": {
    "addr:full":"225 Talbot St St Thomas ON N5P 1B1",
    "addr:housenumber":"225",
    "addr:postcode":"n5p 1b1",
    "addr:street":"Talbot St",
    "iso:country":"CA",
    "sg:address":"225 Talbot St",
    "sg:city":"St Thomas",
    "sg:classifiers":[
        {
            "category":"Autos & Motor Vehicles",
            "subcategory":"Auto Supplies",
            "type":"Retail Goods"
        }
    ],
    "sg:phone":"+1 519 633 5253",
    "sg:postcode":"N5P 1B1",
    "sg:province":"ON",
    "sg:tags":[
        "automobile",
        "parts"
    ],
    "wof:name":"Bob Jones Auto Supply",
    "wof:placetype":"venue"
},
  "geometry": {"coordinates":[-81.20249200000001,42.779266],"type":"Point"}
}