{
  "type": "Feature",
  "properties": {
    "addr:full":"1036 Aberdeen St Hawkesbury ON K6A 1K5",
    "addr:housenumber":"1036",
    "addr:postcode":"k6a 1k5",
    "addr:street":"Aberdeen St",
    "iso:country":"CA",
    "sg:address":"1036 Aberdeen St",
    "sg:city":"Hawkesbury",
    "sg:classifiers":[
        {
            "category":"Manufacturing",
            "subcategory":"Paper Products",
            "type":"Manufacturing & Wholesale Goods"
        }
    ],
    "sg:phone":"+1 613 632 7096",
    "sg:postcode":"K6A 1K5",
    "sg:province":"ON",
    "sg:tags":[
        "tube",
        "collapsible"
    ],
    "wof:name":"Montebello Packaging",
    "wof:placetype":"venue"
},
  "geometry": {"coordinates":[-74.5955276489,45.6049461365],"type":"Point"}
}