{
  "type": "Feature",
  "properties": {
    "addr:full":"Fredericton NB E3B 1L7",
    "addr:postcode":"e3b 1l7",
    "iso:country":"CA",
    "sg:city":"Fredericton",
    "sg:classifiers":[
        {
            "category":"Real Estate",
            "subcategory":"Real Estate Operator",
            "type":"Services"
        }
    ],
    "sg:phone":"+1 506 454 2593",
    "sg:postcode":"E3B 1L7",
    "sg:province":"NB",
    "sg:tags":[
        "apartment"
    ],
    "wof:name":"Jeffrey Howard Real Estate CO",
    "wof:placetype":"venue"
},
  "geometry": {"coordinates":[-66.64701843260001,45.9593811035],"type":"Point"}
}