{
  "type": "Feature",
  "properties": {
    "addr:full":"1605 Av Du Pont S Alma QC G8B 6N3",
    "addr:housenumber":"1605",
    "addr:postcode":"g8b 6n3",
    "addr:street":"Av Du Pont S",
    "iso:country":"CA",
    "sg:address":"1605 Av Du Pont S",
    "sg:city":"Alma",
    "sg:classifiers":[
        {
            "category":"Manufacturing",
            "subcategory":"Metals",
            "type":"Manufacturing & Wholesale Goods"
        }
    ],
    "sg:phone":"+1 418 662 6436",
    "sg:postcode":"G8B 6N3",
    "sg:province":"QC",
    "sg:tags":[
        "equipment",
        "hose",
        "coupling",
        "hydraulic",
        "supply"
    ],
    "wof:name":"Hebdraulique Inc",
    "wof:placetype":"venue"
},
  "geometry": {"coordinates":[-71.652061,48.525791],"type":"Point"}
}