{
  "type": "Feature",
  "properties": {
    "addr:full":"836 Wallace Ave N Listowel ON N4W 1M4",
    "addr:housenumber":"836",
    "addr:postcode":"n4w 1m4",
    "addr:street":"Wallace Ave N",
    "iso:country":"CA",
    "sg:address":"836 Wallace Ave N",
    "sg:city":"Listowel",
    "sg:classifiers":[
        {
            "category":"Food & Beverages",
            "subcategory":"Bakery",
            "type":"Retail Goods"
        }
    ],
    "sg:phone":"+1 519 291 9990",
    "sg:postcode":"N4W 1M4",
    "sg:province":"ON",
    "sg:tags":[
        "doughnut"
    ],
    "wof:name":"Tim Hortons",
    "wof:placetype":"venue"
},
  "geometry": {"coordinates":[-80.94686900000001,43.73925],"type":"Point"}
}