{
  "type": "Feature",
  "properties": {
    "addr:full":"12121 118 Ave NW Edmonton AB T5L 4P1",
    "addr:housenumber":"12121",
    "addr:postcode":"t5l 4p1",
    "addr:street":"118 Ave Nw",
    "iso:country":"CA",
    "sg:address":"12121 118 Ave NW",
    "sg:city":"Edmonton",
    "sg:classifiers":[
        {
            "category":"Autos & Motor Vehicles",
            "subcategory":"Automobile Sales",
            "type":"Retail Goods"
        }
    ],
    "sg:phone":"+1 780 455 4000",
    "sg:postcode":"T5L 4P1",
    "sg:province":"AB",
    "sg:tags":[
        "car",
        "dealer"
    ],
    "wof:name":"Classic Motors Inc",
    "wof:placetype":"venue"
},
  "geometry": {"coordinates":[-113.53137207,53.5701065063],"type":"Point"}
}