{
  "type": "Feature",
  "properties": {
    "addr:full":"1325 Rue Maurice-Cullen # A Blainville QC J7C 4R1",
    "addr:housenumber":"1325",
    "addr:postcode":"j7c 4r1",
    "addr:street":"Rue Maurice-Cullen # A",
    "iso:country":"CA",
    "sg:address":"1325 Rue Maurice-Cullen # A",
    "sg:city":"Blainville",
    "sg:classifiers":[
        {
            "category":"Professional",
            "subcategory":"Business Services",
            "type":"Services"
        }
    ],
    "sg:phone":"+1 450 433 3530",
    "sg:postcode":"J7C 4R1",
    "sg:province":"QC",
    "sg:tags":[
        "paging",
        "answering"
    ],
    "wof:name":"M G Svc DE Reponse Enr",
    "wof:placetype":"venue"
},
  "geometry": {"coordinates":[-73.89678955079999,45.6901741028],"type":"Point"}
}