{
  "type": "Feature",
  "properties": {
    "addr:full":"633 Ritchie St Prince Rupert BC V8J 3S9",
    "addr:housenumber":"633",
    "addr:postcode":"v8j 3s9",
    "addr:street":"Ritchie St",
    "iso:country":"CA",
    "sg:address":"633 Ritchie St",
    "sg:city":"Prince Rupert",
    "sg:classifiers":[
        {
            "category":"Building & Trades",
            "subcategory":"Cleaning & Sanitation",
            "type":"Services"
        }
    ],
    "sg:phone":"+1 250 627 1223",
    "sg:postcode":"V8J 3S9",
    "sg:province":"BC",
    "sg:tags":[
        "janitor"
    ],
    "wof:name":"Abecia Cleaning Svc",
    "wof:placetype":"venue"
},
  "geometry": {"coordinates":[-130.33540300000001,54.302528],"type":"Point"}
}