{
  "type": "Feature",
  "properties": {
    "addr:full":"28280 Highway 48 Pefferlaw ON L0E 1N0",
    "addr:housenumber":"28280",
    "addr:postcode":"l0e 1n0",
    "addr:street":"Highway 48 Pefferlaw",
    "iso:country":"CA",
    "sg:address":"28280 Highway 48",
    "sg:city":"Pefferlaw",
    "sg:classifiers":[
        {
            "category":"Organizations",
            "subcategory":"Religious Organization",
            "type":"Services"
        }
    ],
    "sg:phone":"+1 705 437 3939",
    "sg:postcode":"L0E 1N0",
    "sg:province":"ON",
    "sg:tags":[
        "church"
    ],
    "wof:name":"Virginia United Church",
    "wof:placetype":"venue"
},
  "geometry": {"coordinates":[-79.19375599999999,44.311722],"type":"Point"}
}