{
  "type": "Feature",
  "properties": {
    "addr:full":"915 Rue Saint-Pierre Saint-Roch-DE-Richelieu QC J0L 2M0",
    "addr:housenumber":"915",
    "addr:postcode":"j0l 2m0",
    "addr:street":"Rue Saint-Pierre",
    "iso:country":"CA",
    "sg:address":"915 Rue Saint-Pierre",
    "sg:city":"Saint-Roch-DE-Richelieu",
    "sg:classifiers":[
        {
            "category":"Retail",
            "subcategory":"Funeral Services",
            "type":"Services"
        }
    ],
    "sg:phone":"+1 450 743 5566",
    "sg:postcode":"J0L 2M0",
    "sg:province":"QC",
    "sg:tags":[
        "director"
    ],
    "wof:name":"S Jacques & Fils Inc",
    "wof:placetype":"venue"
},
  "geometry": {"coordinates":[-73.157684,45.890476],"type":"Point"}
}