{
  "type": "Feature",
  "properties": {
    "addr:full":"1983 Rue Saint-Jean Plessisville QC G6L 1G9",
    "addr:housenumber":"1983",
    "addr:postcode":"g6l 1g9",
    "addr:street":"Rue Saint-Jean",
    "iso:country":"CA",
    "sg:address":"1983 Rue Saint-Jean",
    "sg:city":"Plessisville",
    "sg:classifiers":[
        {
            "category":"Health Services",
            "subcategory":"Nursing And Care Facility",
            "type":"Services"
        }
    ],
    "sg:phone":"+1 819 362 7069",
    "sg:postcode":"G6L 1G9",
    "sg:province":"QC",
    "sg:tags":[
        "home",
        "retirement",
        "community"
    ],
    "wof:name":"Residence St-Jean",
    "wof:placetype":"venue"
},
  "geometry": {"coordinates":[-71.77391799999999,46.226105],"type":"Point"}
}