{
  "type": "Feature",
  "properties": {
    "addr:full":"751 Gore Ave Vancouver BC V6A 2Z9",
    "addr:housenumber":"751",
    "addr:postcode":"v6a 2z9",
    "addr:street":"Gore Ave",
    "iso:country":"CA",
    "sg:address":"751 Gore Ave",
    "sg:city":"Vancouver",
    "sg:classifiers":[
        {
            "category":"Food & Beverages",
            "subcategory":"Meat & Fish",
            "type":"Retail Goods"
        }
    ],
    "sg:phone":"+1 604 681 8538",
    "sg:postcode":"V6A 2Z9",
    "sg:province":"BC",
    "wof:name":"Red Star Vegetable Fruit CO",
    "wof:placetype":"venue"
},
  "geometry": {"coordinates":[-123.09717559800001,49.2780570984],"type":"Point"}
}