{
  "type": "Feature",
  "properties": {
    "addr:full":"207 Granada Blvd Sherwood Park AB T8A 3R5",
    "addr:housenumber":"207",
    "addr:postcode":"t8a 3r5",
    "addr:street":"Granada Blvd",
    "iso:country":"CA",
    "sg:address":"207 Granada Blvd",
    "sg:city":"Sherwood Park",
    "sg:classifiers":[
        {
            "category":"Education",
            "subcategory":"School",
            "type":"Public Place"
        }
    ],
    "sg:phone":"+1 780 464 1711",
    "sg:postcode":"T8A 3R5",
    "sg:province":"AB",
    "wof:name":"Wes Hosford Elementary School",
    "wof:placetype":"venue"
},
  "geometry": {"coordinates":[-113.283646,53.528866],"type":"Point"}
}