{
  "type": "Feature",
  "properties": {
    "addr:full":"1040 Stewart Line Cavan ON L0A 1C0",
    "addr:housenumber":"1040",
    "addr:postcode":"l0a 1c0",
    "addr:street":"Stewart Line",
    "iso:country":"CA",
    "sg:address":"1040 Stewart Line",
    "sg:city":"Cavan",
    "sg:classifiers":[
        {
            "category":"Home & Garden",
            "subcategory":"Building Materials",
            "type":"Retail Goods"
        }
    ],
    "sg:phone":"+1 705 745 6363",
    "sg:postcode":"L0A 1C0",
    "sg:province":"ON",
    "sg:tags":[
        "windows"
    ],
    "wof:name":"World Magnetic Windows Mfg Inc",
    "wof:placetype":"venue"
},
  "geometry": {"coordinates":[-78.47023799999999,44.203602],"type":"Point"}
}