{
  "type": "Feature",
  "properties": {
    "addr:full":"1855 Smith St Regina SK S4P 2N5",
    "addr:housenumber":"1855",
    "addr:postcode":"s4p 2n5",
    "addr:street":"Smith St",
    "iso:country":"CA",
    "sg:address":"1855 Smith St",
    "sg:city":"Regina",
    "sg:classifiers":[
        {
            "category":"Social Services",
            "type":"Services"
        }
    ],
    "sg:phone":"+1 306 352 3500",
    "sg:postcode":"S4P 2N5",
    "sg:province":"SK",
    "sg:tags":[
        "organization",
        "welfare"
    ],
    "wof:name":"Regina Open Door Society",
    "wof:placetype":"venue"
},
  "geometry": {"coordinates":[-104.615005,50.449558],"type":"Point"}
}