{
  "type": "Feature",
  "properties": {
    "iso:country":"CA",
    "sg:address":"492 St Anne's Rd",
    "sg:city":"Winnipeg",
    "sg:classifiers":[
        {
            "category":"Shopping",
            "type":"Retail Goods"
        }
    ],
    "sg:phone":"+1 204 257 4044",
    "sg:postcode":"R2M 3E1",
    "sg:province":"MB",
    "sg:tags":[
        "pet",
        "food",
        "supply"
    ],
    "wof:name":"Best-West Pet Foods Inc",
    "wof:placetype":"venue"
},
  "geometry": {"coordinates":[-97.095879,49.843304],"type":"Point"}
}