{
  "type": "Feature",
  "properties": {
    "addr:full":"280 Spadina Ave # 2 Toronto ON M5T 3A5",
    "addr:housenumber":"280",
    "addr:postcode":"m5t 3a5",
    "addr:street":"Spadina Ave # 2",
    "iso:country":"CA",
    "sg:address":"280 Spadina Ave # 2",
    "sg:city":"Toronto",
    "sg:classifiers":[
        {
            "category":"Shopping",
            "subcategory":"Clothing, Apparel, & Fashions",
            "type":"Retail Goods"
        }
    ],
    "sg:phone":"+1 416 599 9343",
    "sg:postcode":"M5T 3A5",
    "sg:province":"ON",
    "wof:name":"J J's Boutique",
    "wof:placetype":"venue"
},
  "geometry": {"coordinates":[-79.39821600000001,43.652565],"type":"Point"}
}