{
  "type": "Feature",
  "properties": {
    "addr:full":"3610 Boul Saint-Jean Dollard-Des-Ormeaux QC H9G 1X1",
    "addr:housenumber":"3610",
    "addr:postcode":"h9g 1x1",
    "addr:street":"Boul Saint-Jean",
    "iso:country":"CA",
    "sg:address":"3610 Boul Saint-Jean",
    "sg:city":"Dollard-Des-Ormeaux",
    "sg:classifiers":[
        {
            "category":"Banks & Credit Unions",
            "subcategory":"Bank",
            "type":"Services"
        }
    ],
    "sg:phone":"+1 514 624 6700",
    "sg:postcode":"H9G 1X1",
    "sg:province":"QC",
    "wof:name":"Banque Royale",
    "wof:placetype":"venue"
},
  "geometry": {"coordinates":[-73.833504,45.471489],"type":"Point"}
}