{
  "type": "Feature",
  "properties": {
    "iso:country":"CA",
    "sg:address":"29 Mcewan Dr W",
    "sg:city":"Bolton",
    "sg:classifiers":[
        {
            "category":"Manufacturing",
            "subcategory":"Signs",
            "type":"Manufacturing & Wholesale Goods"
        }
    ],
    "sg:phone":"+1 905 857 8044",
    "sg:postcode":"L7E 1H4",
    "sg:province":"ON",
    "wof:name":"Wsi Sign Systems",
    "wof:placetype":"venue"
},
  "geometry": {"coordinates":[-79.711861,43.862148],"type":"Point"}
}