{
  "type": "Feature",
  "properties": {
    "addr:full":"Langley BC V2Y 1A2",
    "addr:postcode":"v2y 1a2",
    "iso:country":"CA",
    "sg:city":"Langley",
    "sg:classifiers":[
        {
            "category":"Travel",
            "subcategory":"Travel Agent",
            "type":"Entertainment"
        }
    ],
    "sg:phone":"+1 604 539 8840",
    "sg:postcode":"V2Y 1A2",
    "sg:province":"BC",
    "sg:tags":[
        "agency",
        "bureau"
    ],
    "wof:name":"Travel Cuts",
    "wof:placetype":"venue"
},
  "geometry": {"coordinates":[-122.668998718,49.1144294739],"type":"Point"}
}