{
  "type": "Feature",
  "properties": {
    "iso:country":"CA",
    "sg:address":"99 King St",
    "sg:city":"Dryden",
    "sg:classifiers":[
        {
            "category":"Food & Beverages",
            "subcategory":"Liquor & Beverages",
            "type":"Retail Goods"
        }
    ],
    "sg:phone":"+1 807 223 4029",
    "sg:postcode":"P8N 1C1",
    "sg:province":"ON",
    "sg:tags":[
        "store"
    ],
    "wof:name":"Liquor Control Board",
    "wof:placetype":"venue"
},
  "geometry": {"coordinates":[-92.8341217041,49.7844467163],"type":"Point"}
}