{
  "type": "Feature",
  "properties": {
    "addr:full":"341 Bison St Tugaske SK S0H 4B0",
    "addr:housenumber":"341",
    "addr:postcode":"s0h 4b0",
    "addr:street":"Bison St",
    "iso:country":"CA",
    "sg:address":"341 Bison St",
    "sg:city":"Tugaske",
    "sg:classifiers":[
        {
            "category":"Retail",
            "subcategory":"Repair Shop",
            "type":"Services"
        }
    ],
    "sg:phone":"+1 306 759 2042",
    "sg:postcode":"S0H 4B0",
    "sg:province":"SK",
    "sg:tags":[
        "instrument",
        "musical"
    ],
    "wof:name":"Timeless Instruments",
    "wof:placetype":"venue"
},
  "geometry": {"coordinates":[-106.286171,50.874844],"type":"Point"}
}