{
  "type": "Feature",
  "properties": {
    "addr:full":"Montreal QC H2W 2M7",
    "addr:postcode":"h2w 2m7",
    "iso:country":"CA",
    "sg:city":"Montreal",
    "sg:classifiers":[
        {
            "category":"Travel",
            "subcategory":"Travel Agent",
            "type":"Entertainment"
        }
    ],
    "sg:phone":"+1 514 279 5317",
    "sg:postcode":"H2W 2M7",
    "sg:province":"QC",
    "sg:tags":[
        "agency",
        "bureau"
    ],
    "wof:name":"Joie DE Voyage",
    "wof:placetype":"venue"
},
  "geometry": {"coordinates":[-73.57614100000001,45.521103],"type":"Point"}
}