{
  "type": "Feature",
  "properties": {
    "iso:country":"CA",
    "sg:city":"Montreal",
    "sg:classifiers":[
        {
            "category":"Travel",
            "subcategory":"Travel Agent",
            "type":"Entertainment"
        }
    ],
    "sg:phone":"+1 514 279 5317",
    "sg:postcode":"H2W 2M7",
    "sg:province":"QC",
    "sg:tags":[
        "agency",
        "bureau"
    ],
    "wof:name":"Joie DE Voyage",
    "wof:placetype":"venue"
},
  "geometry": {"coordinates":[-73.576141,45.521103],"type":"Point"}
}