{
  "type": "Feature",
  "properties": {
    "addr:full":"150 Rue Saint-Joseph E Quebec QC G1K 3A7",
    "addr:housenumber":"150",
    "addr:postcode":"g1k 3a7",
    "addr:street":"Rue Saint-Joseph E",
    "iso:country":"CA",
    "sg:address":"150 Rue Saint-Joseph E",
    "sg:city":"Quebec",
    "sg:classifiers":[
        {
            "category":"Organizations",
            "subcategory":"Non-profit Organization",
            "type":"Services"
        }
    ],
    "sg:phone":"+1 418 524 0320",
    "sg:postcode":"G1K 3A7",
    "sg:province":"QC",
    "sg:tags":[
        "info",
        "addiction",
        "abuse",
        "treatment",
        "drug"
    ],
    "wof:name":"Portage Quebec",
    "wof:placetype":"venue"
},
  "geometry": {"coordinates":[-71.2292251587,46.8128852844],"type":"Point"}
}