{
  "type": "Feature",
  "properties": {
    "addr:full":"5798 Hwy 9 Kincardine ON N2Z 2X5",
    "addr:housenumber":"5798",
    "addr:postcode":"n2z 2x5",
    "addr:street":"Hwy 9",
    "iso:country":"CA",
    "sg:address":"5798 Hwy 9",
    "sg:city":"Kincardine",
    "sg:classifiers":[
        {
            "category":"Organizations",
            "subcategory":"Religious Organization",
            "type":"Services"
        }
    ],
    "sg:phone":"+1 519 395 4466",
    "sg:postcode":"N2Z 2X5",
    "sg:province":"ON",
    "sg:tags":[
        "church"
    ],
    "wof:name":"Grace Lutheran Church",
    "wof:placetype":"venue"
},
  "geometry": {"coordinates":[-81.593102,44.166672],"type":"Point"}
}