{
  "type": "Feature",
  "properties": {
    "addr:full":"55 Patterson Rd Barrie ON L4N 3V9",
    "addr:housenumber":"55",
    "addr:postcode":"l4n 3v9",
    "addr:street":"Patterson Rd",
    "iso:country":"CA",
    "sg:address":"55 Patterson Rd",
    "sg:city":"Barrie",
    "sg:classifiers":[
        {
            "category":"Government",
            "subcategory":"Office",
            "type":"Public Place"
        }
    ],
    "sg:phone":"+1 705 722 7222",
    "sg:postcode":"L4N 3V9",
    "sg:province":"ON",
    "sg:tags":[
        "village"
    ],
    "wof:name":"Barrie Hydro",
    "wof:placetype":"venue"
},
  "geometry": {"coordinates":[-79.707787,44.366337],"type":"Point"}
}