{
  "type": "Feature",
  "properties": {
    "addr:full":"255 Woolwich St Guelph ON N1H 3V8",
    "addr:housenumber":"255",
    "addr:postcode":"n1h 3v8",
    "addr:street":"Woolwich St",
    "iso:country":"CA",
    "sg:address":"255 Woolwich St",
    "sg:city":"Guelph",
    "sg:classifiers":[
        {
            "category":"Organizations",
            "subcategory":"Religious Organization",
            "type":"Services"
        }
    ],
    "sg:phone":"+1 519 824 8230",
    "sg:postcode":"N1H 3V8",
    "sg:province":"ON",
    "sg:tags":[
        "church"
    ],
    "wof:name":"First Baptist Church",
    "wof:placetype":"venue"
},
  "geometry": {"coordinates":[-80.2557525635,43.5491333008],"type":"Point"}
}