{
  "type": "Feature",
  "properties": {
    "addr:full":"507 King St E Toronto ON M5A 1M3",
    "addr:housenumber":"507",
    "addr:postcode":"m5a 1m3",
    "addr:street":"King St E",
    "iso:country":"CA",
    "sg:address":"507 King St E",
    "sg:city":"Toronto",
    "sg:classifiers":[
        {
            "category":"Professional",
            "subcategory":"Business Services",
            "type":"Services"
        }
    ],
    "sg:phone":"+1 416 203 1339",
    "sg:postcode":"M5A 1M3",
    "sg:province":"ON",
    "sg:tags":[
        "recording",
        "studio"
    ],
    "wof:name":"Hive",
    "wof:placetype":"venue"
},
  "geometry": {"coordinates":[-79.35947400000001,43.654823],"type":"Point"}
}