{
  "type": "Feature",
  "properties": {
    "addr:full":"2475 Douglas Rd Burnaby BC V5C 5A9",
    "addr:housenumber":"2475",
    "addr:postcode":"v5c 5a9",
    "addr:street":"Douglas Rd",
    "iso:country":"CA",
    "sg:address":"2475 Douglas Rd",
    "sg:city":"Burnaby",
    "sg:classifiers":[
        {
            "category":"Wholesale",
            "subcategory":"Hardware",
            "type":"Manufacturing & Wholesale Goods"
        }
    ],
    "sg:phone":"+1 604 299 1212",
    "sg:postcode":"V5C 5A9",
    "sg:province":"BC",
    "sg:tags":[
        "fastener"
    ],
    "wof:name":"Acklands-Grainger Inc",
    "wof:placetype":"venue"
},
  "geometry": {"coordinates":[-122.98600768999999,49.2621917725],"type":"Point"}
}