{
  "type": "Feature",
  "properties": {
    "addr:full":"208 Conception Bay Hwy Bay Roberts NL A0A 1G0",
    "addr:housenumber":"208",
    "addr:postcode":"a0a 1g0",
    "addr:street":"Conception Bay Hwy Bay",
    "iso:country":"CA",
    "sg:address":"208 Conception Bay Hwy",
    "sg:city":"Bay Roberts",
    "sg:classifiers":[
        {
            "category":"Health Services",
            "subcategory":"Doctor",
            "type":"Services"
        }
    ],
    "sg:phone":"+1 709 834 1888",
    "sg:postcode":"A0A 1G0",
    "sg:province":"NL",
    "sg:tags":[
        "physician",
        "surgeon"
    ],
    "wof:name":"Shandera & Powell Family Med",
    "wof:placetype":"venue"
},
  "geometry": {"coordinates":[-53.282593,47.578079],"type":"Point"}
}