{
  "type": "Feature",
  "properties": {
    "addr:full":"Langley BC V3A 2W3",
    "addr:postcode":"v3a 2w3",
    "iso:country":"CA",
    "sg:city":"Langley",
    "sg:classifiers":[
        {
            "category":"Freight",
            "type":"Transportation"
        }
    ],
    "sg:phone":"+1 604 534 3549",
    "sg:postcode":"V3A 2W3",
    "sg:province":"BC",
    "sg:tags":[
        "broker",
        "agent"
    ],
    "wof:name":"Rite Way Freight Systems Ltd",
    "wof:placetype":"venue"
},
  "geometry": {"coordinates":[-122.666679382,49.0748405457],"type":"Point"}
}