{
  "type": "Feature",
  "properties": {
    "addr:full":"753 4th Ave Hope BC V0X 1L0",
    "addr:housenumber":"753",
    "addr:postcode":"v0x 1l0",
    "addr:street":"4Th Ave",
    "iso:country":"CA",
    "sg:address":"753 4th Ave",
    "sg:city":"Hope",
    "sg:classifiers":[
        {
            "category":"Retail",
            "subcategory":"Laundry & Dry Cleaning",
            "type":"Services"
        }
    ],
    "sg:phone":"+1 604 869 5381",
    "sg:postcode":"V0X 1L0",
    "sg:province":"BC",
    "sg:tags":[
        "cleaners"
    ],
    "wof:name":"Hope Dry Cleaners",
    "wof:placetype":"venue"
},
  "geometry": {"coordinates":[-121.440170288,49.3813476562],"type":"Point"}
}