{
  "type": "Feature",
  "properties": {
    "addr:full":"140 Argyle St S Caledonia ON N3W 1E5",
    "addr:housenumber":"140",
    "addr:postcode":"n3w 1e5",
    "addr:street":"Argyle St S",
    "iso:country":"CA",
    "sg:address":"140 Argyle St S",
    "sg:city":"Caledonia",
    "sg:classifiers":[
        {
            "category":"Autos & Motor Vehicles",
            "subcategory":"Automobile Sales",
            "type":"Retail Goods"
        }
    ],
    "sg:phone":"+1 905 765 4444",
    "sg:postcode":"N3W 1E5",
    "sg:province":"ON",
    "sg:tags":[
        "car",
        "dealer"
    ],
    "wof:name":"Winegard Motors Ltd",
    "wof:placetype":"venue"
},
  "geometry": {"coordinates":[-79.95574999999999,43.067955],"type":"Point"}
}