{
  "type": "Feature",
  "properties": {
    "addr:full":"422 Colborne St Brantford ON N3S 3N6",
    "addr:housenumber":"422",
    "addr:postcode":"n3s 3n6",
    "addr:street":"Colborne St",
    "iso:country":"CA",
    "sg:address":"422 Colborne St",
    "sg:city":"Brantford",
    "sg:classifiers":[
        {
            "category":"Shopping",
            "subcategory":"Musical Instruments",
            "type":"Retail Goods"
        }
    ],
    "sg:phone":"+1 519 752 3797",
    "sg:postcode":"N3S 3N6",
    "sg:province":"ON",
    "sg:tags":[
        "music",
        "dealer"
    ],
    "wof:name":"Brantford Music Ctr",
    "wof:placetype":"venue"
},
  "geometry": {"coordinates":[-80.254272,43.139282],"type":"Point"}
}