{
  "type": "Feature",
  "properties": {
    "addr:full":"33351 Richmond St Lucan ON N0M 2J0",
    "addr:housenumber":"33351",
    "addr:postcode":"n0m 2j0",
    "addr:street":"Richmond St",
    "iso:country":"CA",
    "sg:address":"33351 Richmond St",
    "sg:city":"Lucan",
    "sg:classifiers":[
        {
            "category":"Government",
            "subcategory":"Office",
            "type":"Public Place"
        }
    ],
    "sg:phone":"+1 519 227 4491",
    "sg:postcode":"N0M 2J0",
    "sg:province":"ON",
    "sg:tags":[
        "village"
    ],
    "wof:name":"Lucan Biddulph Clerk's Office",
    "wof:placetype":"venue"
},
  "geometry": {"coordinates":[-81.389397,43.181614],"type":"Point"}
}