{
  "type": "Feature",
  "properties": {
    "iso:country":"CA",
    "sg:address":"3034 Dundas St W",
    "sg:city":"Toronto",
    "sg:classifiers":[
        {
            "category":"Restaurant",
            "type":"Food & Drink"
        }
    ],
    "sg:phone":"+1 416 769 5460",
    "sg:postcode":"M6P 1Z3",
    "sg:province":"ON",
    "wof:name":"Curry Twist Restaurant",
    "wof:placetype":"venue"
},
  "geometry": {"coordinates":[-79.47054290769999,43.6655769348],"type":"Point"}
}