{
  "type": "Feature",
  "properties": {
    "addr:full":"Montreal-Nord QC H1G 2T6",
    "addr:postcode":"h1g 2t6",
    "iso:country":"CA",
    "sg:city":"Montreal-Nord",
    "sg:classifiers":[
        {
            "category":"Shopping",
            "subcategory":"Clothing, Apparel, & Fashions",
            "type":"Retail Goods"
        }
    ],
    "sg:phone":"+1 514 325 0904",
    "sg:postcode":"H1G 2T6",
    "sg:province":"QC",
    "sg:tags":[
        "handbag"
    ],
    "wof:name":"Bentley Leathers Inc",
    "wof:placetype":"venue"
},
  "geometry": {"coordinates":[-73.61732499999999,45.607395],"type":"Point"}
}