{
  "type": "Feature",
  "properties": {
    "addr:full":"Cheticamp NS B0E 1H0",
    "addr:postcode":"b0e 1h0",
    "iso:country":"CA",
    "sg:city":"Cheticamp",
    "sg:classifiers":[
        {
            "category":"Government",
            "subcategory":"Office",
            "type":"Public Place"
        }
    ],
    "sg:phone":"+1 902 224 1872",
    "sg:postcode":"B0E 1H0",
    "sg:province":"NS",
    "wof:name":"Nova Scotia Home Care Reg Ofc",
    "wof:placetype":"venue"
},
  "geometry": {"coordinates":[-61.009185791,46.6342811584],"type":"Point"}
}