{
  "type": "Feature",
  "properties": {
    "iso:country":"CA",
    "sg:address":"631 Rue Brassard",
    "sg:city":"Saint-Michel-Des-Saints",
    "sg:classifiers":[
        {
            "category":"Health Services",
            "subcategory":"Optometrist",
            "type":"Services"
        }
    ],
    "sg:phone":"+1 450 833 6900",
    "sg:postcode":"J0K 3B0",
    "sg:province":"QC",
    "sg:tags":[
        "clinic"
    ],
    "wof:name":"Centre Professionel St-Michel",
    "wof:placetype":"venue"
},
  "geometry": {"coordinates":[-73.916924,46.679455],"type":"Point"}
}