{
  "type": "Feature",
  "properties": {
    "iso:country":"CA",
    "sg:address":"215 Corvette Cres S",
    "sg:city":"Lethbridge",
    "sg:classifiers":[
        {
            "category":"Education",
            "subcategory":"School",
            "type":"Public Place"
        }
    ],
    "sg:phone":"+1 403 328 1201",
    "sg:postcode":"T1J 3X6",
    "sg:province":"AB",
    "wof:name":"General Stewart School",
    "wof:placetype":"venue"
},
  "geometry": {"coordinates":[-112.796966553,49.6930961609],"type":"Point"}
}