{
  "type": "Feature",
  "properties": {
    "iso:country":"CA",
    "sg:city":"Vanier",
    "sg:classifiers":[
        {
            "category":"Professional",
            "subcategory":"Management & Consulting",
            "type":"Services"
        }
    ],
    "sg:phone":"+1 613 742 7391",
    "sg:postcode":"K1L 8B4",
    "sg:province":"ON",
    "sg:tags":[
        "consultant",
        "school",
        "language",
        "business"
    ],
    "wof:name":"Institut Canadien DE Langues",
    "wof:placetype":"venue"
},
  "geometry": {"coordinates":[-75.6774139404,45.4385528564],"type":"Point"}
}