{
  "type": "Feature",
  "properties": {
    "addr:full":"2280 South Rd Gabriola BC V0R 1X7",
    "addr:housenumber":"2280",
    "addr:postcode":"v0r 1x7",
    "addr:street":"South Rd",
    "iso:country":"CA",
    "sg:address":"2280 South Rd",
    "sg:city":"Gabriola",
    "sg:classifiers":[
        {
            "category":"Home & Garden",
            "subcategory":"Garden Supply",
            "type":"Retail Goods"
        }
    ],
    "sg:phone":"+1 250 247 8728",
    "sg:postcode":"V0R 1X7",
    "sg:province":"BC",
    "sg:tags":[
        "nurseryman"
    ],
    "wof:name":"Wheelbarrel Nursery",
    "wof:placetype":"venue"
},
  "geometry": {"coordinates":[-123.75015999999999,49.134953],"type":"Point"}
}