{
  "type": "Feature",
  "properties": {
    "addr:full":"300 City Centre Dr Mississauga ON L5B 3C1",
    "addr:housenumber":"300",
    "addr:postcode":"l5b 3c1",
    "addr:street":"City Centre Dr",
    "iso:country":"CA",
    "sg:address":"300 City Centre Dr",
    "sg:city":"Mississauga",
    "sg:classifiers":[
        {
            "category":"Government",
            "subcategory":"Office",
            "type":"Public Place"
        }
    ],
    "sg:phone":"+1 905 615 3198",
    "sg:postcode":"L5B 3C1",
    "sg:province":"ON",
    "sg:tags":[
        "village"
    ],
    "wof:name":"Mississauga Birth Information",
    "wof:placetype":"venue"
},
  "geometry": {"coordinates":[-79.6433181763,43.5888252258],"type":"Point"}
}