{
  "type": "Feature",
  "properties": {
    "iso:country":"CA",
    "sg:city":"Brockville",
    "sg:classifiers":[
        {
            "category":"Health Services",
            "subcategory":"Hospital",
            "type":"Services"
        }
    ],
    "sg:phone":"+1 613 345 5645",
    "sg:postcode":"K6V 1S8",
    "sg:province":"ON",
    "wof:name":"Brockville General Hospital",
    "wof:placetype":"venue"
},
  "geometry": {"coordinates":[-75.6828460693,44.5961112976],"type":"Point"}
}