{
  "type": "Feature",
  "properties": {
    "addr:full":"2373 Hazen Rd NW Courtland ON N0J 1E0",
    "addr:housenumber":"2373",
    "addr:postcode":"n0j 1e0",
    "addr:street":"Hazen Rd Nw",
    "iso:country":"CA",
    "sg:address":"2373 Hazen Rd NW",
    "sg:city":"Courtland",
    "sg:classifiers":[
        {
            "category":"Wholesale",
            "subcategory":"Tobacco Products",
            "type":"Manufacturing & Wholesale Goods"
        }
    ],
    "sg:phone":"+1 519 875 2485",
    "sg:postcode":"N0J 1E0",
    "sg:province":"ON",
    "sg:tags":[
        "cigarette",
        "cigar",
        "dealer"
    ],
    "wof:name":"Lake Erie Farms Inc",
    "wof:placetype":"venue"
},
  "geometry": {"coordinates":[-80.64297500000001,42.841763],"type":"Point"}
}