{
  "type": "Feature",
  "properties": {
    "addr:full":"Surrey BC V3S 2A7",
    "addr:postcode":"v3s 2a7",
    "iso:country":"CA",
    "sg:city":"Surrey",
    "sg:classifiers":[
        {
            "category":"Manufacturing",
            "subcategory":"Paper Products",
            "type":"Manufacturing & Wholesale Goods"
        }
    ],
    "sg:phone":"+1 604 574 1469",
    "sg:postcode":"V3S 2A7",
    "sg:province":"BC",
    "sg:tags":[
        "label"
    ],
    "wof:name":"Label Resources Mfg Ltd",
    "wof:placetype":"venue"
},
  "geometry": {"coordinates":[-122.830215,49.105179],"type":"Point"}
}