{
  "type": "Feature",
  "properties": {
    "iso:country":"CA",
    "sg:address":"2375 Hwy 2",
    "sg:city":"Bowmanville",
    "sg:classifiers":[
        {
            "category":"Shopping",
            "subcategory":"Pharmacy",
            "type":"Retail Goods"
        }
    ],
    "sg:phone":"+1 905 623 0420",
    "sg:postcode":"L1C 5A3",
    "sg:province":"ON",
    "wof:name":"Drug Store Pharmacy",
    "wof:placetype":"venue"
},
  "geometry": {"coordinates":[-78.709777832,43.909412384],"type":"Point"}
}