{
  "type": "Feature",
  "properties": {
    "iso:country":"CA",
    "sg:address":"227 Rue Racine E",
    "sg:city":"Chicoutimi",
    "sg:classifiers":[
        {
            "category":"Government",
            "subcategory":"Office",
            "type":"Public Place"
        }
    ],
    "sg:phone":"+1 418 698 3636",
    "sg:postcode":"G7H 7B4",
    "sg:province":"QC",
    "wof:name":"Quebec Commission Des Droits",
    "wof:placetype":"venue"
},
  "geometry": {"coordinates":[-71.061852,48.427814],"type":"Point"}
}