{
  "type": "Feature",
  "properties": {
    "addr:full":"241 Horton St E London ON N6B 1L1",
    "addr:housenumber":"241",
    "addr:postcode":"n6b 1l1",
    "addr:street":"Horton St E",
    "iso:country":"CA",
    "sg:address":"241 Horton St E",
    "sg:city":"London",
    "sg:classifiers":[
        {
            "category":"Retail",
            "subcategory":"Auto Repair",
            "type":"Services"
        }
    ],
    "sg:phone":"+1 519 438 1330",
    "sg:postcode":"N6B 1L1",
    "sg:province":"ON",
    "sg:tags":[
        "repairing",
        "automobile"
    ],
    "wof:name":"Dominic's Auto Svc Inc",
    "wof:placetype":"venue"
},
  "geometry": {"coordinates":[-81.24421691889999,42.9796409607],"type":"Point"}
}