{
  "type": "Feature",
  "properties": {
    "addr:full":"16 School St Holland Landing ON L9N 1K9",
    "addr:housenumber":"16",
    "addr:postcode":"l9n 1k9",
    "addr:street":"School St",
    "iso:country":"CA",
    "sg:address":"16 School St",
    "sg:city":"Holland Landing",
    "sg:classifiers":[
        {
            "category":"Organizations",
            "subcategory":"Religious Organization",
            "type":"Services"
        }
    ],
    "sg:phone":"+1 905 853 0201",
    "sg:postcode":"L9N 1K9",
    "sg:province":"ON",
    "sg:tags":[
        "church"
    ],
    "wof:name":"Holland Landing United Church",
    "wof:placetype":"venue"
},
  "geometry": {"coordinates":[-79.489502,44.097149],"type":"Point"}
}