{
  "type": "Feature",
  "properties": {
    "addr:full":"18 Av Harrop Dorchester NB E4K 2X9",
    "addr:postcode":"e4k 2x9",
    "addr:street":"18 Av Harrop",
    "iso:country":"CA",
    "sg:address":"18 Av Harrop",
    "sg:city":"Dorchester",
    "sg:classifiers":[
        {
            "category":"Education",
            "subcategory":"School",
            "type":"Public Place"
        }
    ],
    "sg:phone":"+1 506 379 3000",
    "sg:postcode":"E4K 2X9",
    "sg:province":"NB",
    "wof:name":"Dorchester Consolidated School",
    "wof:placetype":"venue"
},
  "geometry": {"coordinates":[-64.514816,45.89624],"type":"Point"}
}