{
  "type": "Feature",
  "properties": {
    "addr:full":"111 Baig Blvd Moncton NB E1E 1C9",
    "addr:housenumber":"111",
    "addr:postcode":"e1e 1c9",
    "addr:street":"Baig Blvd",
    "iso:country":"CA",
    "sg:address":"111 Baig Blvd",
    "sg:city":"Moncton",
    "sg:classifiers":[
        {
            "category":"Autos & Motor Vehicles",
            "subcategory":"Automobile Sales",
            "type":"Retail Goods"
        }
    ],
    "sg:phone":"+1 506 853 6203",
    "sg:postcode":"E1E 1C9",
    "sg:province":"NB",
    "sg:tags":[
        "repairing",
        "car",
        "oil",
        "parts",
        "supply"
    ],
    "wof:name":"Mac Donald Pontiac Buick Ltd",
    "wof:placetype":"venue"
},
  "geometry": {"coordinates":[-64.81883999999999,46.075558],"type":"Point"}
}