{
  "type": "Feature",
  "properties": {
    "iso:country":"CA",
    "sg:address":"300 Av Sainte-Croix",
    "sg:city":"Saint-Laurent",
    "sg:classifiers":[
        {
            "category":"Shopping",
            "subcategory":"Pharmacy",
            "type":"Retail Goods"
        }
    ],
    "sg:phone":"+1 514 748 6644",
    "sg:postcode":"H4N 3K4",
    "sg:province":"QC",
    "wof:name":"Pharmacie Larry Yuskovitz",
    "wof:placetype":"venue"
},
  "geometry": {"coordinates":[-73.6674423218,45.5092430115],"type":"Point"}
}