{
  "type": "Feature",
  "properties": {
    "addr:full":"Surrey BC V3R 0R8",
    "addr:postcode":"v3r 0r8",
    "iso:country":"CA",
    "sg:city":"Surrey",
    "sg:classifiers":[
        {
            "category":"Social Services",
            "type":"Services"
        }
    ],
    "sg:phone":"+1 604 580 0112",
    "sg:postcode":"V3R 0R8",
    "sg:province":"BC",
    "sg:tags":[
        "organization",
        "welfare"
    ],
    "wof:name":"Vancouver Assn-Injured Mtrcycl",
    "wof:placetype":"venue"
},
  "geometry": {"coordinates":[-122.853683,49.213188],"type":"Point"}
}