{
  "type": "Feature",
  "properties": {
    "addr:full":"Leduc AB T9E 6Z6",
    "addr:postcode":"t9e 6z6",
    "iso:country":"CA",
    "sg:city":"Leduc",
    "sg:classifiers":[
        {
            "category":"Professional",
            "subcategory":"Lawyer & Legal Services",
            "type":"Services"
        }
    ],
    "sg:phone":"+1 780 986 8428",
    "sg:postcode":"T9E 6Z6",
    "sg:province":"AB",
    "sg:tags":[
        "attorney"
    ],
    "wof:name":"Zalapski & Pahl",
    "wof:placetype":"venue"
},
  "geometry": {"coordinates":[-113.552696,53.267311],"type":"Point"}
}