{
  "type": "Feature",
  "properties": {
    "addr:full":"2650 Rue Roussel Chicoutimi QC G7G 1Y4",
    "addr:housenumber":"2650",
    "addr:postcode":"g7g 1y4",
    "addr:street":"Rue Roussel",
    "iso:country":"CA",
    "sg:address":"2650 Rue Roussel",
    "sg:city":"Chicoutimi",
    "sg:classifiers":[
        {
            "category":"Freight",
            "type":"Transportation"
        }
    ],
    "sg:phone":"+1 418 693 0605",
    "sg:postcode":"G7G 1Y4",
    "sg:province":"QC",
    "sg:tags":[
        "commercial",
        "storage"
    ],
    "wof:name":"Remisage Select Enr",
    "wof:placetype":"venue"
},
  "geometry": {"coordinates":[-71.0798797607,48.4409103394],"type":"Point"}
}