{
  "type": "Feature",
  "properties": {
    "addr:full":"1717 Sunset Dr Bathurst NB E2A 4K8",
    "addr:housenumber":"1717",
    "addr:postcode":"e2a 4k8",
    "addr:street":"Sunset Dr",
    "iso:country":"CA",
    "sg:address":"1717 Sunset Dr",
    "sg:city":"Bathurst",
    "sg:classifiers":[
        {
            "category":"Retail",
            "subcategory":"Funeral Services",
            "type":"Services"
        }
    ],
    "sg:phone":"+1 506 546 4120",
    "sg:postcode":"E2A 4K8",
    "sg:province":"NB",
    "sg:tags":[
        "director"
    ],
    "wof:name":"Verret's Funeral Home & Chapel",
    "wof:placetype":"venue"
},
  "geometry": {"coordinates":[-65.69305419920001,47.6452445984],"type":"Point"}
}