{
  "type": "Feature",
  "properties": {
    "addr:full":"2119 101st Cres North Battleford SK S9A 1C2",
    "addr:housenumber":"2119",
    "addr:postcode":"s9a 1c2",
    "addr:street":"101St Cres",
    "iso:country":"CA",
    "sg:address":"2119 101st Cres",
    "sg:city":"North Battleford",
    "sg:classifiers":[
        {
            "category":"Health Services",
            "subcategory":"Clinic",
            "type":"Services"
        }
    ],
    "sg:phone":"+1 306 445 6681",
    "sg:postcode":"S9A 1C2",
    "sg:province":"SK",
    "sg:tags":[
        "home"
    ],
    "wof:name":"Prairie Villa Residence",
    "wof:placetype":"venue"
},
  "geometry": {"coordinates":[-108.29748499999999,52.789375],"type":"Point"}
}