{
  "type": "Feature",
  "properties": {
    "addr:full":"13230 126 Ave NW Edmonton AB T5L 3E1",
    "addr:housenumber":"13230",
    "addr:postcode":"t5l 3e1",
    "addr:street":"126 Ave Nw",
    "iso:country":"CA",
    "sg:address":"13230 126 Ave NW",
    "sg:city":"Edmonton",
    "sg:classifiers":[
        {
            "category":"Retail",
            "subcategory":"Auto Repair",
            "type":"Services"
        }
    ],
    "sg:phone":"+1 780 454 5530",
    "sg:postcode":"T5L 3E1",
    "sg:province":"AB",
    "sg:tags":[
        "repairing",
        "automobile",
        "wheel",
        "alignment"
    ],
    "wof:name":"Hi-Tech Alignment",
    "wof:placetype":"venue"
},
  "geometry": {"coordinates":[-113.555199,53.583107],"type":"Point"}
}