{
  "type": "Feature",
  "properties": {
    "addr:full":"Nepean ON K2G 6E2",
    "addr:postcode":"k2g 6e2",
    "iso:country":"CA",
    "sg:city":"Nepean",
    "sg:classifiers":[
        {
            "category":"Health Services",
            "subcategory":"Doctor",
            "type":"Services"
        }
    ],
    "sg:phone":"+1 613 225 3030",
    "sg:postcode":"K2G 6E2",
    "sg:province":"ON",
    "sg:tags":[
        "dentist"
    ],
    "wof:name":"Fyman, Dale S DDS",
    "wof:placetype":"venue"
},
  "geometry": {"coordinates":[-75.76889,45.348396],"type":"Point"}
}