{
  "type": "Feature",
  "properties": {
    "iso:country":"CA",
    "sg:address":"248 Locke St S",
    "sg:city":"Hamilton",
    "sg:classifiers":[
        {
            "category":"Food & Beverages",
            "subcategory":"Specialty",
            "type":"Retail Goods"
        }
    ],
    "sg:phone":"+1 905 525 3227",
    "sg:postcode":"L8P 4B9",
    "sg:province":"ON",
    "sg:tags":[
        "gourmet",
        "shop"
    ],
    "wof:name":"Elegant Pantry",
    "wof:placetype":"venue"
},
  "geometry": {"coordinates":[-79.88692474370001,43.2530708313],"type":"Point"}
}