{
  "type": "Feature",
  "properties": {
    "iso:country":"CA",
    "sg:address":"150 1 Ave Lac Vert",
    "sg:city":"Saint-Calixte",
    "sg:classifiers":[
        {
            "category":"Professional",
            "type":"Services"
        }
    ],
    "sg:phone":"+1 450 222 1177",
    "sg:postcode":"J0K 1Z0",
    "sg:province":"QC",
    "sg:tags":[
        "establishment",
        "publicity"
    ],
    "wof:name":"Publication Locale",
    "wof:placetype":"venue"
},
  "geometry": {"coordinates":[-73.9115066528,45.9920501709],"type":"Point"}
}