{
  "type": "Feature",
  "properties": {
    "addr:full":"8668 Sunrise Dr Chilliwack BC V2R 3J1",
    "addr:housenumber":"8668",
    "addr:postcode":"v2r 3j1",
    "addr:street":"Sunrise Dr",
    "iso:country":"CA",
    "sg:address":"8668 Sunrise Dr",
    "sg:city":"Chilliwack",
    "sg:classifiers":[
        {
            "category":"Recreation",
            "type":"Entertainment"
        }
    ],
    "sg:phone":"+1 604 795 6016",
    "sg:postcode":"V2R 3J1",
    "sg:province":"BC",
    "sg:tags":[
        "party",
        "fishing"
    ],
    "wof:name":"Discovery Charters & Tours",
    "wof:placetype":"venue"
},
  "geometry": {"coordinates":[-121.99623099999999,49.160931],"type":"Point"}
}