{
  "type": "Feature",
  "properties": {
    "addr:full":"115 Industrial Blvd #3 Napanee ON K7R 3Z1",
    "addr:housenumber":"115",
    "addr:postcode":"k7r 3z1",
    "addr:street":"Industrial Blvd # 3",
    "iso:country":"CA",
    "sg:address":"115 Industrial Blvd #3",
    "sg:city":"Napanee",
    "sg:classifiers":[
        {
            "category":"Government",
            "subcategory":"Office",
            "type":"Public Place"
        }
    ],
    "sg:phone":"+1 613 354 3522",
    "sg:postcode":"K7R 3Z1",
    "sg:province":"ON",
    "sg:tags":[
        "license"
    ],
    "wof:name":"Driver & Vehicle License Ofc",
    "wof:placetype":"venue"
},
  "geometry": {"coordinates":[-76.955383,44.260056],"type":"Point"}
}