{
  "type": "Feature",
  "properties": {
    "addr:full":"10365 Boul Saint-Laurent Montreal QC H3L 2P1",
    "addr:housenumber":"10365",
    "addr:postcode":"h3l 2p1",
    "addr:street":"Boul Saint-Laurent",
    "iso:country":"CA",
    "sg:address":"10365 Boul Saint-Laurent",
    "sg:city":"Montreal",
    "sg:classifiers":[
        {
            "category":"Professional",
            "subcategory":"Research",
            "type":"Services"
        }
    ],
    "sg:phone":"+1 514 389 9997",
    "sg:postcode":"H3L 2P1",
    "sg:province":"QC",
    "sg:tags":[
        "development",
        "laboratory"
    ],
    "wof:name":"Innovance Inc",
    "wof:placetype":"venue"
},
  "geometry": {"coordinates":[-73.6659622192,45.5489730835],"type":"Point"}
}