{
  "type": "Feature",
  "properties": {
    "addr:full":"609 Leola St Winnipeg MB R2C 1H8",
    "addr:housenumber":"609",
    "addr:postcode":"r2c 1h8",
    "addr:street":"Leola St",
    "iso:country":"CA",
    "sg:address":"609 Leola St",
    "sg:city":"Winnipeg",
    "sg:classifiers":[
        {
            "category":"Organizations",
            "subcategory":"Religious Organization",
            "type":"Services"
        }
    ],
    "sg:phone":"+1 204 222 0739",
    "sg:postcode":"R2C 1H8",
    "sg:province":"MB",
    "sg:tags":[
        "church"
    ],
    "wof:name":"Notre Dame DE L'Assomption",
    "wof:placetype":"venue"
},
  "geometry": {"coordinates":[-96.993668,49.897667],"type":"Point"}
}