{
  "type": "Feature",
  "properties": {
    "addr:full":"203 W 1st St Revelstoke BC V0E 2S0",
    "addr:housenumber":"203",
    "addr:postcode":"v0e 2s0",
    "addr:street":"W 1St St",
    "iso:country":"CA",
    "sg:address":"203 W 1st St",
    "sg:city":"Revelstoke",
    "sg:classifiers":[
        {
            "category":"Shopping",
            "subcategory":"Bicycles & Sporting Goods",
            "type":"Retail Goods"
        }
    ],
    "sg:phone":"+1 250 837 9453",
    "sg:postcode":"V0E 2S0",
    "sg:province":"BC",
    "wof:name":"Free Spirit Sports & Leisure",
    "wof:placetype":"venue"
},
  "geometry": {"coordinates":[-118.196281,50.999325],"type":"Point"}
}