{
  "type": "Feature",
  "properties": {
    "addr:full":"Calgary AB T2H 0T2",
    "addr:postcode":"t2h 0t2",
    "iso:country":"CA",
    "sg:city":"Calgary",
    "sg:classifiers":[
        {
            "category":"Retail",
            "subcategory":"Portrait Studio",
            "type":"Services"
        }
    ],
    "sg:phone":"+1 403 253 0200",
    "sg:postcode":"T2H 0T2",
    "sg:province":"AB",
    "sg:tags":[
        "photographer"
    ],
    "wof:name":"Images Unlimited",
    "wof:placetype":"venue"
},
  "geometry": {"coordinates":[-114.057007,50.992165],"type":"Point"}
}