{
  "type": "Feature",
  "properties": {
    "iso:country":"CA",
    "sg:address":"6465 Millcreek Dr",
    "sg:city":"Mississauga",
    "sg:classifiers":[
        {
            "category":"Personal",
            "type":"Services"
        }
    ],
    "sg:phone":"+1 905 813 4001",
    "sg:postcode":"L5N 5R3",
    "sg:province":"ON",
    "sg:tags":[
        "control",
        "weight"
    ],
    "wof:name":"Bernstein, S K",
    "wof:placetype":"venue"
},
  "geometry": {"coordinates":[-79.741562,43.590412],"type":"Point"}
}