{
  "type": "Feature",
  "properties": {
    "addr:full":"3111 Kennedy Rd Scarborough ON M1V 4Y1",
    "addr:housenumber":"3111",
    "addr:postcode":"m1v 4y1",
    "addr:street":"Kennedy Rd",
    "iso:country":"CA",
    "sg:address":"3111 Kennedy Rd",
    "sg:city":"Scarborough",
    "sg:classifiers":[
        {
            "category":"Building & Trades",
            "subcategory":"Construction",
            "type":"Services"
        }
    ],
    "sg:phone":"+1 416 321 2331",
    "sg:postcode":"M1V 4Y1",
    "sg:province":"ON",
    "sg:tags":[
        "home",
        "improvement"
    ],
    "wof:name":"Pang Ching Construction Dcrtn",
    "wof:placetype":"venue"
},
  "geometry": {"coordinates":[-79.30159759519999,43.8118362427],"type":"Point"}
}