{
  "type": "Feature",
  "properties": {
    "addr:full":"London ON N6A 5L9",
    "addr:postcode":"n6a 5l9",
    "iso:country":"CA",
    "sg:city":"London",
    "sg:classifiers":[
        {
            "category":"Real Estate",
            "subcategory":"Real Estate Operator",
            "type":"Services"
        }
    ],
    "sg:phone":"+1 519 667 0841",
    "sg:postcode":"N6A 5L9",
    "sg:province":"ON",
    "sg:tags":[
        "condominium"
    ],
    "wof:name":"Middlesex Condominium Corp",
    "wof:placetype":"venue"
},
  "geometry": {"coordinates":[-81.2547073364,42.9890174866],"type":"Point"}
}