{
  "type": "Feature",
  "properties": {
    "iso:country":"CA",
    "sg:city":"Vancouver",
    "sg:classifiers":[
        {
            "category":"Banks & Credit Unions",
            "subcategory":"Investment Brokerage",
            "type":"Services"
        }
    ],
    "sg:phone":"+1 604 684 7723",
    "sg:postcode":"V6B 6L7",
    "sg:province":"BC",
    "sg:tags":[
        "consultant",
        "planning",
        "financial"
    ],
    "wof:name":"Knights Financial Ltd",
    "wof:placetype":"venue"
},
  "geometry": {"coordinates":[-123.117699,49.282082],"type":"Point"}
}