{
  "type": "Feature",
  "properties": {
    "addr:full":"6939 Hastings St #6 Burnaby BC V5B 1S9",
    "addr:housenumber":"6939",
    "addr:postcode":"v5b 1s9",
    "addr:street":"Hastings St # 6",
    "iso:country":"CA",
    "sg:address":"6939 Hastings St #6",
    "sg:city":"Burnaby",
    "sg:classifiers":[
        {
            "category":"Home & Garden",
            "subcategory":"Hardware",
            "type":"Retail Goods"
        }
    ],
    "sg:phone":"+1 604 294 4474",
    "sg:postcode":"V5B 1S9",
    "sg:province":"BC",
    "sg:tags":[
        "saw"
    ],
    "wof:name":"Optibit Industries Inc",
    "wof:placetype":"venue"
},
  "geometry": {"coordinates":[-122.960647583,49.2802429199],"type":"Point"}
}