{
  "type": "Feature",
  "properties": {
    "iso:country":"CA",
    "sg:address":"12305 Boul Metropolitain E",
    "sg:city":"Pointe-Aux-Trembles",
    "sg:classifiers":[
        {
            "category":"Professional",
            "subcategory":"Management & Consulting",
            "type":"Services"
        }
    ],
    "sg:phone":"+1 514 351 5454",
    "sg:postcode":"H1B 5R3",
    "sg:province":"QC",
    "sg:tags":[
        "personnel",
        "consultant"
    ],
    "wof:name":"Service DE Personnel Riverain",
    "wof:placetype":"venue"
},
  "geometry": {"coordinates":[-73.5252456665,45.6522865295],"type":"Point"}
}