{
  "type": "Feature",
  "properties": {
    "addr:full":"1065 Danforth Ave Toronto ON M4J 1M1",
    "addr:housenumber":"1065",
    "addr:postcode":"m4j 1m1",
    "addr:street":"Danforth Ave",
    "iso:country":"CA",
    "sg:address":"1065 Danforth Ave",
    "sg:city":"Toronto",
    "sg:classifiers":[
        {
            "category":"Food & Beverages",
            "subcategory":"Groceries & Convenience Stores",
            "type":"Retail Goods"
        }
    ],
    "sg:phone":"+1 416 469 2069",
    "sg:postcode":"M4J 1M1",
    "sg:province":"ON",
    "sg:tags":[
        "butchering"
    ],
    "wof:name":"Motala Halal Meats & Grocery",
    "wof:placetype":"venue"
},
  "geometry": {"coordinates":[-79.33577,43.680595],"type":"Point"}
}