{
  "type": "Feature",
  "properties": {
    "addr:full":"Ottawa ON K1P 5P2",
    "addr:postcode":"k1p 5p2",
    "iso:country":"CA",
    "sg:city":"Ottawa",
    "sg:classifiers":[
        {
            "category":"Government",
            "subcategory":"Office",
            "type":"Public Place"
        }
    ],
    "sg:phone":"+1 613 996 0188",
    "sg:postcode":"K1P 5P2",
    "sg:province":"ON",
    "wof:name":"Consulting & Audit Canada",
    "wof:placetype":"venue"
},
  "geometry": {"coordinates":[-75.70305633540001,45.4194793701],"type":"Point"}
}