{
  "type": "Feature",
  "properties": {
    "iso:country":"CA",
    "sg:address":"77 Balsam Rd",
    "sg:city":"Snow Lake",
    "sg:classifiers":[
        {
            "category":"Government",
            "subcategory":"Office",
            "type":"Public Place"
        }
    ],
    "sg:phone":"+1 204 358 2392",
    "sg:postcode":"R0B 1M0",
    "sg:province":"MB",
    "wof:name":"Manitoba Labour",
    "wof:placetype":"venue"
},
  "geometry": {"coordinates":[-100.015022278,54.8745231628],"type":"Point"}
}