{
  "type": "Feature",
  "properties": {
    "iso:country":"CA",
    "sg:address":"525 Av Ogilvy",
    "sg:city":"Montreal",
    "sg:classifiers":[
        {
            "category":"Home & Garden",
            "subcategory":"Building Materials",
            "type":"Retail Goods"
        }
    ],
    "sg:phone":"+1 514 271 8132",
    "sg:postcode":"H3N 1M9",
    "sg:province":"QC",
    "sg:tags":[
        "paint"
    ],
    "wof:name":"Alex Paint Shop",
    "wof:placetype":"venue"
},
  "geometry": {"coordinates":[-73.625534,45.528927],"type":"Point"}
}