{
  "type": "Feature",
  "properties": {
    "addr:full":"260 Dalhousie St Ottawa ON K1N 7E4",
    "addr:housenumber":"260",
    "addr:postcode":"k1n 7e4",
    "addr:street":"Dalhousie St",
    "iso:country":"CA",
    "sg:address":"260 Dalhousie St",
    "sg:city":"Ottawa",
    "sg:classifiers":[
        {
            "category":"Professional",
            "type":"Services"
        }
    ],
    "sg:phone":"+1 613 747 1883",
    "sg:postcode":"K1N 7E4",
    "sg:province":"ON",
    "sg:tags":[
        "consultant",
        "computer",
        "establishment"
    ],
    "wof:name":"Despatie & Assoc Ltd",
    "wof:placetype":"venue"
},
  "geometry": {"coordinates":[-75.692795,45.430454],"type":"Point"}
}