{
  "type": "Feature",
  "properties": {
    "addr:full":"Calgary AB T2B 3M1",
    "addr:postcode":"t2b 3m1",
    "iso:country":"CA",
    "sg:city":"Calgary",
    "sg:classifiers":[
        {
            "category":"Wholesale",
            "subcategory":"Groceries",
            "type":"Manufacturing & Wholesale Goods"
        }
    ],
    "sg:phone":"+1 403 444 9300",
    "sg:postcode":"T2B 3M1",
    "sg:province":"AB",
    "sg:tags":[
        "coffee",
        "roasting"
    ],
    "wof:name":"Vittoria Reserve West Inc",
    "wof:placetype":"venue"
},
  "geometry": {"coordinates":[-113.99277499999999,51.01339],"type":"Point"}
}