{
  "type": "Feature",
  "properties": {
    "addr:full":"164 Douglas Woods Dr SE Calgary AB T2Z 2E4",
    "addr:housenumber":"164",
    "addr:postcode":"t2z 2e4",
    "addr:street":"Douglas Woods Dr Se",
    "iso:country":"CA",
    "sg:address":"164 Douglas Woods Dr SE",
    "sg:city":"Calgary",
    "sg:classifiers":[
        {
            "category":"Building & Trades",
            "subcategory":"Plumbing",
            "type":"Services"
        }
    ],
    "sg:phone":"+1 403 236 3266",
    "sg:postcode":"T2Z 2E4",
    "sg:province":"AB",
    "sg:tags":[
        "heating",
        "contractor"
    ],
    "wof:name":"Franko's Heating & Ac Ltd",
    "wof:placetype":"venue"
},
  "geometry": {"coordinates":[-113.99854999999999,50.946358],"type":"Point"}
}