{
  "type": "Feature",
  "properties": {
    "addr:full":"30 Mcewen Ave Ottawa ON K2B 5K8",
    "addr:housenumber":"30",
    "addr:postcode":"k2b 5k8",
    "addr:street":"Mcewen Ave",
    "iso:country":"CA",
    "sg:address":"30 Mcewen Ave",
    "sg:city":"Ottawa",
    "sg:classifiers":[
        {
            "category":"Real Estate",
            "subcategory":"Real Estate Operator",
            "type":"Services"
        }
    ],
    "sg:phone":"+1 613 820 4202",
    "sg:postcode":"K2B 5K8",
    "sg:province":"ON",
    "sg:tags":[
        "apartment"
    ],
    "wof:name":"Park West",
    "wof:placetype":"venue"
},
  "geometry": {"coordinates":[-75.78315000000001,45.371735],"type":"Point"}
}