{
  "type": "Feature",
  "properties": {
    "addr:full":"820 Grand River Rd W Grand River NS B0E 1M0",
    "addr:housenumber":"820",
    "addr:postcode":"b0e 1m0",
    "addr:street":"Grand River Rd W",
    "iso:country":"CA",
    "sg:address":"820 Grand River Rd W",
    "sg:city":"Grand River",
    "sg:classifiers":[
        {
            "category":"Travel",
            "subcategory":"Hotels & Motels",
            "type":"Entertainment"
        }
    ],
    "sg:phone":"+1 902 587 2410",
    "sg:postcode":"B0E 1M0",
    "sg:province":"NS",
    "sg:tags":[
        "tourist",
        "accommodation"
    ],
    "wof:name":"Indian Point Lodge Ltd",
    "wof:placetype":"venue"
},
  "geometry": {"coordinates":[-60.661331,45.64555],"type":"Point"}
}