{
  "type": "Feature",
  "properties": {
    "addr:full":"1644 Bob-O-Link Way Nanaimo BC V9S 2P8",
    "addr:housenumber":"1644",
    "addr:postcode":"v9s 2p8",
    "addr:street":"Bob-O-Link Way",
    "iso:country":"CA",
    "sg:address":"1644 Bob-O-Link Way",
    "sg:city":"Nanaimo",
    "sg:classifiers":[
        {
            "category":"Organizations",
            "subcategory":"Religious Organization",
            "type":"Services"
        }
    ],
    "sg:phone":"+1 250 758 7629",
    "sg:postcode":"V9S 2P8",
    "sg:province":"BC",
    "sg:tags":[
        "church"
    ],
    "wof:name":"Salvation Army",
    "wof:placetype":"venue"
},
  "geometry": {"coordinates":[-123.975266,49.187012],"type":"Point"}
}