{
  "type": "Feature",
  "properties": {
    "addr:full":"Vancouver BC V6B 6H5",
    "addr:postcode":"v6b 6h5",
    "iso:country":"CA",
    "sg:city":"Vancouver",
    "sg:phone":"+1 604 689 3719",
    "sg:postcode":"V6B 6H5",
    "sg:province":"BC",
    "sg:tags":[
        "transmission",
        "facsimile"
    ],
    "wof:name":"Informa Communications Corp",
    "wof:placetype":"venue"
},
  "geometry": {"coordinates":[-123.112877,49.283596],"type":"Point"}
}