{
  "type": "Feature",
  "properties": {
    "addr:full":"375 Boul DE Comporte LA Malbaie QC G5A 1H9",
    "addr:housenumber":"375",
    "addr:postcode":"g5a 1h9",
    "addr:street":"Boul De Comporte",
    "iso:country":"CA",
    "sg:address":"375 Boul DE Comporte",
    "sg:city":"LA Malbaie",
    "sg:classifiers":[
        {
            "category":"Shopping",
            "subcategory":"Tobacco",
            "type":"Retail Goods"
        }
    ],
    "sg:phone":"+1 418 665 4325",
    "sg:postcode":"G5A 1H9",
    "sg:province":"QC",
    "sg:tags":[
        "cigarette",
        "cigar",
        "dealer"
    ],
    "wof:name":"Tabagie Le Calumet Enr",
    "wof:placetype":"venue"
},
  "geometry": {"coordinates":[-70.14965100000001,47.646675],"type":"Point"}
}