{
  "type": "Feature",
  "properties": {
    "addr:full":"654 Park Ave Beausejour MB R0E 0C0",
    "addr:housenumber":"654",
    "addr:postcode":"r0e 0c0",
    "addr:street":"Park Ave",
    "iso:country":"CA",
    "sg:address":"654 Park Ave",
    "sg:city":"Beausejour",
    "sg:classifiers":[
        {
            "category":"Food & Beverages",
            "subcategory":"Groceries & Convenience Stores",
            "type":"Retail Goods"
        }
    ],
    "sg:phone":"+1 204 268 1475",
    "sg:postcode":"R0E 0C0",
    "sg:province":"MB",
    "wof:name":"Bergie's",
    "wof:placetype":"venue"
},
  "geometry": {"coordinates":[-96.512505,50.061745],"type":"Point"}
}