{
  "type": "Feature",
  "properties": {
    "addr:full":"Edmonton AB T5H 0X7",
    "addr:postcode":"t5h 0x7",
    "iso:country":"CA",
    "sg:city":"Edmonton",
    "sg:classifiers":[
        {
            "category":"Restaurant",
            "type":"Food & Drink"
        }
    ],
    "sg:phone":"+1 780 425 8912",
    "sg:postcode":"T5H 0X7",
    "sg:province":"AB",
    "wof:name":"Thanh Son Restaurant Ltd",
    "wof:placetype":"venue"
},
  "geometry": {"coordinates":[-113.510643,53.551544],"type":"Point"}
}