{
  "type": "Feature",
  "properties": {
    "addr:full":"149 Manitoba St Bracebridge ON P1L 2B7",
    "addr:housenumber":"149",
    "addr:postcode":"p1l 2b7",
    "addr:street":"Manitoba St",
    "iso:country":"CA",
    "sg:address":"149 Manitoba St",
    "sg:city":"Bracebridge",
    "sg:classifiers":[
        {
            "category":"Health Services",
            "subcategory":"Doctor",
            "type":"Services"
        }
    ],
    "sg:phone":"+1 705 645 4151",
    "sg:postcode":"P1L 2B7",
    "sg:province":"ON",
    "sg:tags":[
        "dentist"
    ],
    "wof:name":"Robson, Stuart DDS",
    "wof:placetype":"venue"
},
  "geometry": {"coordinates":[-79.31476600000001,45.043514],"type":"Point"}
}