{
  "type": "Feature",
  "properties": {
    "addr:full":"477 Mount Pleasant Rd # 105 Toronto ON M4S 2L9",
    "addr:housenumber":"477",
    "addr:postcode":"m4s 2l9",
    "addr:street":"Mount Pleasant Rd # 105",
    "iso:country":"CA",
    "sg:address":"477 Mount Pleasant Rd # 105",
    "sg:city":"Toronto",
    "sg:classifiers":[
        {
            "category":"Travel",
            "subcategory":"Travel Agent",
            "type":"Entertainment"
        }
    ],
    "sg:phone":"+1 416 489 8118",
    "sg:postcode":"M4S 2L9",
    "sg:province":"ON",
    "sg:tags":[
        "agency",
        "bureau"
    ],
    "wof:name":"Your Vacation Home",
    "wof:placetype":"venue"
},
  "geometry": {"coordinates":[-79.387047,43.701061],"type":"Point"}
}