{
  "type": "Feature",
  "properties": {
    "addr:full":"5421 Huron St Niagara Falls ON L2E 2K5",
    "addr:housenumber":"5421",
    "addr:postcode":"l2e 2k5",
    "addr:street":"Huron St",
    "iso:country":"CA",
    "sg:address":"5421 Huron St",
    "sg:city":"Niagara Falls",
    "sg:classifiers":[
        {
            "category":"Education",
            "subcategory":"School",
            "type":"Public Place"
        }
    ],
    "sg:phone":"+1 905 353 8654",
    "sg:postcode":"L2E 2K5",
    "sg:province":"ON",
    "sg:tags":[
        "academic",
        "special"
    ],
    "wof:name":"Brighter Futures Tutoring Svc",
    "wof:placetype":"venue"
},
  "geometry": {"coordinates":[-79.08452606199999,43.1060752869],"type":"Point"}
}