{
  "type": "Feature",
  "properties": {
    "addr:full":"2150 Av DE L'Hotel-DE-Ville Montreal QC H2X 3B3",
    "addr:housenumber":"2150",
    "addr:postcode":"h2x 3b3",
    "addr:street":"Av De L'Hotel-De-Ville",
    "iso:country":"CA",
    "sg:address":"2150 Av DE L'Hotel-DE-Ville",
    "sg:city":"Montreal",
    "sg:classifiers":[
        {
            "category":"Organizations",
            "subcategory":"Professional Association",
            "type":"Services"
        }
    ],
    "sg:phone":"+1 514 374 5818",
    "sg:postcode":"H2X 3B3",
    "sg:province":"QC",
    "sg:tags":[
        "charitable",
        "institution"
    ],
    "wof:name":"Logis Rose-Virginie",
    "wof:placetype":"venue"
},
  "geometry": {"coordinates":[-73.556549,45.509182],"type":"Point"}
}