{
  "type": "Feature",
  "properties": {
    "addr:full":"Crossfield AB T0M 0S0",
    "addr:postcode":"t0m 0s0",
    "iso:country":"CA",
    "sg:city":"Crossfield",
    "sg:classifiers":[
        {
            "category":"Retail",
            "subcategory":"Auto Repair",
            "type":"Services"
        }
    ],
    "sg:phone":"+1 403 946 4748",
    "sg:postcode":"T0M 0S0",
    "sg:province":"AB",
    "sg:tags":[
        "truck"
    ],
    "wof:name":"Rockyview Diesel",
    "wof:placetype":"venue"
},
  "geometry": {"coordinates":[-114.02761099999999,51.411968],"type":"Point"}
}