{
  "type": "Feature",
  "properties": {
    "addr:full":"5410 Deschene Rd Hanmer ON P3P 1R3",
    "addr:housenumber":"5410",
    "addr:postcode":"p3p 1r3",
    "addr:street":"Deschene Rd",
    "iso:country":"CA",
    "sg:address":"5410 Deschene Rd",
    "sg:city":"Hanmer",
    "sg:classifiers":[
        {
            "category":"Professional",
            "subcategory":"Business Services",
            "type":"Services"
        }
    ],
    "sg:phone":"+1 705 969 6333",
    "sg:postcode":"P3P 1R3",
    "sg:province":"ON",
    "sg:tags":[
        "inspection"
    ],
    "wof:name":"Total Crane & Assoc Svc Group",
    "wof:placetype":"venue"
},
  "geometry": {"coordinates":[-80.987694,46.677814],"type":"Point"}
}