{
  "type": "Feature",
  "properties": {
    "iso:country":"CA",
    "sg:address":"1447 Av Victoria",
    "sg:city":"Saint-Lambert",
    "sg:classifiers":[
        {
            "category":"Retail",
            "subcategory":"Laundry & Dry Cleaning",
            "type":"Services"
        }
    ],
    "sg:phone":"+1 450 671 7553",
    "sg:postcode":"J4R 1R5",
    "sg:province":"QC",
    "sg:tags":[
        "cleaners"
    ],
    "wof:name":"Nettoyeur Carol Inc",
    "wof:placetype":"venue"
},
  "geometry": {"coordinates":[-73.493270874,45.4899559021],"type":"Point"}
}