{
  "type": "Feature",
  "properties": {
    "addr:full":"416 Donald B Munro Dr Carp ON K0A 1L0",
    "addr:housenumber":"416",
    "addr:postcode":"k0a 1l0",
    "addr:street":"Donald B Munro Dr",
    "iso:country":"CA",
    "sg:address":"416 Donald B Munro Dr",
    "sg:city":"Carp",
    "sg:classifiers":[
        {
            "category":"Home & Garden",
            "subcategory":"Furniture",
            "type":"Retail Goods"
        }
    ],
    "sg:phone":"+1 613 839 3372",
    "sg:postcode":"K0A 1L0",
    "sg:province":"ON",
    "sg:tags":[
        "builder",
        "custom"
    ],
    "wof:name":"Spindler's Furniture",
    "wof:placetype":"venue"
},
  "geometry": {"coordinates":[-76.03465271,45.3444099426],"type":"Point"}
}