{
  "type": "Feature",
  "properties": {
    "addr:full":"2310 Av Ekers Mont-Royal QC H3S 1C5",
    "addr:housenumber":"2310",
    "addr:postcode":"h3s 1c5",
    "addr:street":"Av Ekers",
    "iso:country":"CA",
    "sg:address":"2310 Av Ekers",
    "sg:city":"Mont-Royal",
    "sg:classifiers":[
        {
            "category":"Professional",
            "subcategory":"Employment Agencies",
            "type":"Services"
        }
    ],
    "sg:phone":"+1 514 737 4019",
    "sg:postcode":"H3S 1C5",
    "sg:province":"QC",
    "wof:name":"Services DE Bar Jodan",
    "wof:placetype":"venue"
},
  "geometry": {"coordinates":[-73.628624,45.514568],"type":"Point"}
}