{
  "type": "Feature",
  "properties": {
    "addr:full":"3015 Winston Churchill Blvd Mississauga ON L5L 2V8",
    "addr:housenumber":"3015",
    "addr:postcode":"l5l 2v8",
    "addr:street":"Winston Churchill Blvd",
    "iso:country":"CA",
    "sg:address":"3015 Winston Churchill Blvd",
    "sg:city":"Mississauga",
    "sg:classifiers":[
        {
            "category":"Shopping",
            "subcategory":"Crafts & Fabrics",
            "type":"Retail Goods"
        }
    ],
    "sg:phone":"+1 905 828 9966",
    "sg:postcode":"L5L 2V8",
    "sg:province":"ON",
    "sg:tags":[
        "shop"
    ],
    "wof:name":"Fabricland Distributors",
    "wof:placetype":"venue"
},
  "geometry": {"coordinates":[-79.682114,43.52335],"type":"Point"}
}