{
  "type": "Feature",
  "properties": {
    "iso:country":"CA",
    "sg:address":"171 William St",
    "sg:city":"Palmerston",
    "sg:classifiers":[
        {
            "category":"Manufacturing",
            "subcategory":"Printing",
            "type":"Manufacturing & Wholesale Goods"
        }
    ],
    "sg:phone":"+1 519 343 2440",
    "sg:postcode":"N0G 2P0",
    "sg:province":"ON",
    "sg:tags":[
        "newspaper"
    ],
    "wof:name":"Minto Express",
    "wof:placetype":"venue"
},
  "geometry": {"coordinates":[-80.84954833979999,43.8334503174],"type":"Point"}
}