{
  "type": "Feature",
  "properties": {
    "iso:country":"CA",
    "sg:address":"131 Oakenwald Cres",
    "sg:city":"Mitchell",
    "sg:classifiers":[
        {
            "category":"Building & Trades",
            "subcategory":"Electrical",
            "type":"Services"
        }
    ],
    "sg:phone":"+1 204 346 0029",
    "sg:postcode":"R5G 1J2",
    "sg:province":"MB",
    "sg:tags":[
        "electric",
        "contractor"
    ],
    "wof:name":"Delta Electric",
    "wof:placetype":"venue"
},
  "geometry": {"coordinates":[-96.75798034669999,49.5320510864],"type":"Point"}
}