{
  "type": "Feature",
  "properties": {
    "iso:country":"CA",
    "sg:address":"1033 Heritage Blvd",
    "sg:city":"North Vancouver",
    "sg:classifiers":[
        {
            "category":"Shopping",
            "subcategory":"Computers & Home Electronics",
            "type":"Retail Goods"
        }
    ],
    "sg:phone":"+1 604 986 3022",
    "sg:postcode":"V7J 3G7",
    "sg:province":"BC",
    "sg:tags":[
        "television",
        "radio",
        "system"
    ],
    "wof:name":"Architectural Audio Video",
    "wof:placetype":"venue"
},
  "geometry": {"coordinates":[-123.014953613,49.3165283203],"type":"Point"}
}