{
  "type": "Feature",
  "properties": {
    "addr:full":"527 Rang Sainte-Helene Sainte-Helene-DE-Bagot QC J0H 1M0",
    "addr:housenumber":"527",
    "addr:postcode":"j0h 1m0",
    "addr:street":"Rang Sainte-Helene Sainte-Helene-De-Bagot",
    "iso:country":"CA",
    "sg:address":"527 Rang Sainte-Helene",
    "sg:city":"Sainte-Helene-DE-Bagot",
    "sg:classifiers":[
        {
            "category":"Freight",
            "type":"Transportation"
        }
    ],
    "sg:phone":"+1 450 791 2344",
    "sg:postcode":"J0H 1M0",
    "sg:province":"QC",
    "sg:tags":[
        "building",
        "house",
        "mover"
    ],
    "wof:name":"Royfer Inc",
    "wof:placetype":"venue"
},
  "geometry": {"coordinates":[-72.736069,45.731525],"type":"Point"}
}