{
  "type": "Feature",
  "properties": {
    "addr:full":"175 Queen St Port Perry ON L9L 1B8",
    "addr:housenumber":"175",
    "addr:postcode":"l9l 1b8",
    "addr:street":"Queen St",
    "iso:country":"CA",
    "sg:address":"175 Queen St",
    "sg:city":"Port Perry",
    "sg:classifiers":[
        {
            "category":"Home & Garden",
            "subcategory":"Hardware",
            "type":"Retail Goods"
        }
    ],
    "sg:phone":"+1 905 985 2674",
    "sg:postcode":"L9L 1B8",
    "sg:province":"ON",
    "wof:name":"Port Perry Home Hardware",
    "wof:placetype":"venue"
},
  "geometry": {"coordinates":[-78.9434509277,44.1051826477],"type":"Point"}
}