{
  "type": "Feature",
  "properties": {
    "addr:full":"700 Kingsway Vancouver BC V5V 3C1",
    "addr:housenumber":"700",
    "addr:postcode":"v5v 3c1",
    "addr:street":"Kingsway",
    "iso:country":"CA",
    "sg:address":"700 Kingsway",
    "sg:city":"Vancouver",
    "sg:classifiers":[
        {
            "category":"Social Services",
            "type":"Services"
        }
    ],
    "sg:phone":"+1 604 707 0222",
    "sg:postcode":"V5V 3C1",
    "sg:province":"BC",
    "sg:tags":[
        "community"
    ],
    "wof:name":"Link International Ministries",
    "wof:placetype":"venue"
},
  "geometry": {"coordinates":[-123.08921051,49.2563247681],"type":"Point"}
}