{
  "type": "Feature",
  "properties": {
    "iso:country":"CA",
    "sg:address":"623 Ferry Rd",
    "sg:city":"Winnipeg",
    "sg:classifiers":[
        {
            "category":"Shopping",
            "subcategory":"Bicycles & Sporting Goods",
            "type":"Retail Goods"
        }
    ],
    "sg:phone":"+1 204 783 9555",
    "sg:postcode":"R3H 0T5",
    "sg:province":"MB",
    "wof:name":"Wilderness Supply CO",
    "wof:placetype":"venue"
},
  "geometry": {"coordinates":[-97.217407,49.89296],"type":"Point"}
}