{
  "type": "Feature",
  "properties": {
    "addr:full":"935 St Clair Ave W Toronto ON M6C 1C7",
    "addr:housenumber":"935",
    "addr:postcode":"m6c 1c7",
    "addr:street":"St Clair Ave W",
    "iso:country":"CA",
    "sg:address":"935 St Clair Ave W",
    "sg:city":"Toronto",
    "sg:classifiers":[
        {
            "category":"Banks & Credit Unions",
            "subcategory":"Bank",
            "type":"Services"
        }
    ],
    "sg:phone":"+1 416 654 4333",
    "sg:postcode":"M6C 1C7",
    "sg:province":"ON",
    "wof:name":"Royal Bank Financial Group",
    "wof:placetype":"venue"
},
  "geometry": {"coordinates":[-79.4351654053,43.6795806885],"type":"Point"}
}