{
  "type": "Feature",
  "properties": {
    "addr:full":"2330 Rue Rachel E Montreal QC H2H 1R7",
    "addr:housenumber":"2330",
    "addr:postcode":"h2h 1r7",
    "addr:street":"Rue Rachel E",
    "iso:country":"CA",
    "sg:address":"2330 Rue Rachel E",
    "sg:city":"Montreal",
    "sg:classifiers":[
        {
            "category":"Recreation",
            "type":"Entertainment"
        }
    ],
    "sg:phone":"+1 514 872 3533",
    "sg:postcode":"H2H 1R7",
    "sg:province":"QC",
    "sg:tags":[
        "pool",
        "swimming"
    ],
    "wof:name":"Baldwin Piscines",
    "wof:placetype":"venue"
},
  "geometry": {"coordinates":[-73.5646362305,45.5353813171],"type":"Point"}
}