{
  "type": "Feature",
  "properties": {
    "addr:full":"603 Frank Trail Watson Lake YT Y0A 1C0",
    "addr:housenumber":"603",
    "addr:postcode":"y0a 1c0",
    "addr:street":"Frank Trail",
    "iso:country":"CA",
    "sg:address":"603 Frank Trail",
    "sg:city":"Watson Lake",
    "sg:classifiers":[
        {
            "category":"Food & Beverages",
            "subcategory":"Liquor & Beverages",
            "type":"Retail Goods"
        }
    ],
    "sg:phone":"+1 867 536 7311",
    "sg:postcode":"Y0A 1C0",
    "sg:province":"YT",
    "sg:tags":[
        "store"
    ],
    "wof:name":"Yukon Liquor Stores",
    "wof:placetype":"venue"
},
  "geometry": {"coordinates":[-128.714157105,60.0629348755],"type":"Point"}
}