{
  "type": "Feature",
  "properties": {
    "iso:country":"CA",
    "sg:address":"105 Nashdene Rd",
    "sg:city":"Scarborough",
    "sg:classifiers":[
        {
            "category":"Freight",
            "type":"Transportation"
        }
    ],
    "sg:phone":"+1 416 754 4778",
    "sg:postcode":"M1V 2W3",
    "sg:province":"ON",
    "sg:tags":[
        "automobile",
        "mover",
        "drive",
        "transporter"
    ],
    "wof:name":"Fast Vehicle Rail Trnsprtn",
    "wof:placetype":"venue"
},
  "geometry": {"coordinates":[-79.253441,43.818581],"type":"Point"}
}