{
  "type": "Feature",
  "properties": {
    "addr:full":"24 Thames Pl NW Calgary AB T2K 5L2",
    "addr:housenumber":"24",
    "addr:postcode":"t2k 5l2",
    "addr:street":"Thames Pl Nw",
    "iso:country":"CA",
    "sg:address":"24 Thames Pl NW",
    "sg:city":"Calgary",
    "sg:classifiers":[
        {
            "category":"Building & Trades",
            "subcategory":"Equipment Rental",
            "type":"Services"
        }
    ],
    "sg:phone":"+1 403 275 7549",
    "sg:postcode":"T2K 5L2",
    "sg:province":"AB",
    "sg:tags":[
        "computer",
        "leasing",
        "dealer"
    ],
    "wof:name":"Power Byte Solutions Inc",
    "wof:placetype":"venue"
},
  "geometry": {"coordinates":[-114.07891082800001,51.1066398621],"type":"Point"}
}