{
  "type": "Feature",
  "properties": {
    "iso:country":"CA",
    "sg:city":"Cap-DE-LA-Madeleine",
    "sg:classifiers":[
        {
            "category":"Sports & Exercise",
            "subcategory":"Bowling",
            "type":"Entertainment"
        }
    ],
    "sg:phone":"+1 819 379 6424",
    "sg:postcode":"G8T 7A4",
    "sg:province":"QC",
    "sg:tags":[
        "center"
    ],
    "wof:name":"Salle DE Quilles Chateaudun",
    "wof:placetype":"venue"
},
  "geometry": {"coordinates":[-72.5481872559,46.3846359253],"type":"Point"}
}