{
  "type": "Feature",
  "properties": {
    "iso:country":"CA",
    "sg:address":"9493 120 St",
    "sg:city":"Delta",
    "sg:classifiers":[
        {
            "category":"Restaurant",
            "type":"Food & Drink"
        }
    ],
    "sg:phone":"+1 604 581 7555",
    "sg:postcode":"V4C 6S3",
    "sg:province":"BC",
    "wof:name":"Porto Fino Restaurant Ltd",
    "wof:placetype":"venue"
},
  "geometry": {"coordinates":[-122.890365601,49.1753463745],"type":"Point"}
}