{
  "type": "Feature",
  "properties": {
    "addr:full":"15 Coral Springs Blvd NE Calgary AB T3J 4J1",
    "addr:housenumber":"15",
    "addr:postcode":"t3j 4j1",
    "addr:street":"Coral Springs Blvd Ne",
    "iso:country":"CA",
    "sg:address":"15 Coral Springs Blvd NE",
    "sg:city":"Calgary",
    "sg:classifiers":[
        {
            "category":"Banks & Credit Unions",
            "subcategory":"Investment Brokerage",
            "type":"Services"
        }
    ],
    "sg:phone":"+1 403 280 3465",
    "sg:postcode":"T3J 4J1",
    "sg:province":"AB",
    "sg:tags":[
        "stock",
        "broker",
        "bond"
    ],
    "wof:name":"Edward Jones",
    "wof:placetype":"venue"
},
  "geometry": {"coordinates":[-113.933655,51.09893],"type":"Point"}
}