{
  "type": "Feature",
  "properties": {
    "addr:full":"30 Earldown Dr Etobicoke ON M9R 2L3",
    "addr:housenumber":"30",
    "addr:postcode":"m9r 2l3",
    "addr:street":"Earldown Dr",
    "iso:country":"CA",
    "sg:address":"30 Earldown Dr",
    "sg:city":"Etobicoke",
    "sg:classifiers":[
        {
            "category":"Government",
            "subcategory":"Office",
            "type":"Public Place"
        }
    ],
    "sg:phone":"+1 416 392 5086",
    "sg:postcode":"M9R 2L3",
    "sg:province":"ON",
    "sg:tags":[
        "village"
    ],
    "wof:name":"Willowridge Child Care",
    "wof:placetype":"venue"
},
  "geometry": {"coordinates":[-79.57266235349999,43.6755523682],"type":"Point"}
}