{
  "type": "Feature",
  "properties": {
    "addr:full":"311 Jubilee Rd Muncey ON N0L 1Y0",
    "addr:housenumber":"311",
    "addr:postcode":"n0l 1y0",
    "addr:street":"Jubilee Rd",
    "iso:country":"CA",
    "sg:address":"311 Jubilee Rd",
    "sg:city":"Muncey",
    "sg:classifiers":[
        {
            "category":"Organizations",
            "subcategory":"Professional Association",
            "type":"Services"
        }
    ],
    "sg:phone":"+1 519 289 0777",
    "sg:postcode":"N0L 1Y0",
    "sg:province":"ON",
    "wof:name":"Anishinabek Educational Inst",
    "wof:placetype":"venue"
},
  "geometry": {"coordinates":[-81.4358673096,42.8198051453],"type":"Point"}
}