{
  "type": "Feature",
  "properties": {
    "addr:full":"5519 Yonge St North York ON M2N 5S3",
    "addr:housenumber":"5519",
    "addr:postcode":"m2n 5s3",
    "addr:street":"Yonge St",
    "iso:country":"CA",
    "sg:address":"5519 Yonge St",
    "sg:city":"North York",
    "sg:classifiers":[
        {
            "category":"Personal",
            "subcategory":"Beauty Salon",
            "type":"Services"
        }
    ],
    "sg:phone":"+1 416 225 1212",
    "sg:postcode":"M2N 5S3",
    "sg:province":"ON",
    "wof:name":"Atrium Hair Design",
    "wof:placetype":"venue"
},
  "geometry": {"coordinates":[-79.4149551392,43.7781829834],"type":"Point"}
}