{
  "type": "Feature",
  "properties": {
    "iso:country":"CA",
    "sg:address":"2145 Windsor St",
    "sg:city":"Halifax",
    "sg:classifiers":[
        {
            "category":"Organizations",
            "subcategory":"Religious Organization",
            "type":"Services"
        }
    ],
    "sg:phone":"+1 902 422 0042",
    "sg:postcode":"B3K 5B5",
    "sg:province":"NS",
    "sg:tags":[
        "church"
    ],
    "wof:name":"Atlantic Chan Buddhist Assn",
    "wof:placetype":"venue"
},
  "geometry": {"coordinates":[-63.5943489075,44.6494674683],"type":"Point"}
}