{
  "type": "Feature",
  "properties": {
    "iso:country":"CA",
    "sg:address":"710 Rue Bouvier # 102",
    "sg:city":"Quebec",
    "sg:classifiers":[
        {
            "category":"Wholesale",
            "subcategory":"Office Equipment",
            "type":"Manufacturing & Wholesale Goods"
        }
    ],
    "sg:phone":"+1 418 660 8060",
    "sg:postcode":"G2J 1C2",
    "sg:province":"QC",
    "sg:tags":[
        "machine",
        "duplicating",
        "copying"
    ],
    "wof:name":"Technimedias",
    "wof:placetype":"venue"
},
  "geometry": {"coordinates":[-71.273109,46.834042],"type":"Point"}
}