{
  "type": "Feature",
  "properties": {
    "addr:full":"250 Durham St Sturgis SK S0A 4A0",
    "addr:housenumber":"250",
    "addr:postcode":"s0a 4a0",
    "addr:street":"Durham St",
    "iso:country":"CA",
    "sg:address":"250 Durham St",
    "sg:city":"Sturgis",
    "sg:classifiers":[
        {
            "category":"Education",
            "subcategory":"School",
            "type":"Public Place"
        }
    ],
    "sg:phone":"+1 306 548 2103",
    "sg:postcode":"S0A 4A0",
    "sg:province":"SK",
    "wof:name":"Sturgis Composite High School",
    "wof:placetype":"venue"
},
  "geometry": {"coordinates":[-102.540848,51.938492],"type":"Point"}
}