{
  "type": "Feature",
  "properties": {
    "addr:full":"202 Sixth Ave New Westminster BC V3L 1T6",
    "addr:housenumber":"202",
    "addr:postcode":"v3l 1t6",
    "addr:street":"Sixth Ave",
    "iso:country":"CA",
    "sg:address":"202 Sixth Ave",
    "sg:city":"New Westminster",
    "sg:classifiers":[
        {
            "category":"Retail",
            "subcategory":"Auto Repair",
            "type":"Services"
        }
    ],
    "sg:phone":"+1 604 874 1103",
    "sg:postcode":"V3L 1T6",
    "sg:province":"BC",
    "sg:tags":[
        "brake"
    ],
    "wof:name":"Dependable Brake & Muffler",
    "wof:placetype":"venue"
},
  "geometry": {"coordinates":[-122.914215,49.216297],"type":"Point"}
}