{
  "type": "Feature",
  "properties": {
    "iso:country":"CA",
    "sg:city":"Prince George",
    "sg:classifiers":[
        {
            "category":"Wholesale",
            "subcategory":"Scrap",
            "type":"Manufacturing & Wholesale Goods"
        }
    ],
    "sg:phone":"+1 250 563 1040",
    "sg:postcode":"V2L 5R9",
    "sg:province":"BC",
    "sg:tags":[
        "recycling",
        "center"
    ],
    "wof:name":"Shred of Evidence",
    "wof:placetype":"venue"
},
  "geometry": {"coordinates":[-122.743873596,53.9150085449],"type":"Point"}
}