{
  "type": "Feature",
  "properties": {
    "addr:full":"701 Rue Fournier Saint-Jerome QC J7Z 4W6",
    "addr:housenumber":"701",
    "addr:postcode":"j7z 4w6",
    "addr:street":"Rue Fournier Saint-Jerome",
    "iso:country":"CA",
    "sg:address":"701 Rue Fournier",
    "sg:city":"Saint-Jerome",
    "sg:classifiers":[
        {
            "category":"Sports & Exercise",
            "subcategory":"Gym",
            "type":"Entertainment"
        }
    ],
    "sg:phone":"+1 450 431 4811",
    "sg:postcode":"J7Z 4W6",
    "sg:province":"QC",
    "sg:tags":[
        "club",
        "health",
        "studio",
        "gymnasium"
    ],
    "wof:name":"Gym",
    "wof:placetype":"venue"
},
  "geometry": {"coordinates":[-74.0007095337,45.7877578735],"type":"Point"}
}