{
  "type": "Feature",
  "properties": {
    "addr:full":"Elko BC V0B 1J0",
    "addr:postcode":"bc v0b 1j0",
    "iso:country":"CA",
    "sg:city":"Elko",
    "sg:classifiers":[
        {
            "category":"Organizations",
            "subcategory":"Community Association",
            "type":"Services"
        }
    ],
    "sg:phone":"+1 250 529 7748",
    "sg:postcode":"V0B 1J0",
    "sg:province":"BC",
    "sg:tags":[
        "fraternal"
    ],
    "wof:name":"Baynes Lake Lions Club",
    "wof:placetype":"venue"
},
  "geometry": {"coordinates":[-115.114914,49.301819],"type":"Point"}
}