{
  "type": "Feature",
  "properties": {
    "addr:full":"120 Horse Lake Rd 100 Mile House BC V0K 2E3",
    "addr:housenumber":"120",
    "addr:postcode":"v0k 2e3",
    "addr:street":"Horse Lake Rd",
    "iso:country":"CA",
    "sg:address":"120 Horse Lake Rd",
    "sg:city":"100 Mile House",
    "sg:classifiers":[
        {
            "category":"Organizations",
            "subcategory":"Religious Organization",
            "type":"Services"
        }
    ],
    "sg:phone":"+1 250 395 5159",
    "sg:postcode":"V0K 2E3",
    "sg:province":"BC",
    "sg:tags":[
        "church"
    ],
    "wof:name":"Christ the King Lutheran Chr",
    "wof:placetype":"venue"
},
  "geometry": {"coordinates":[-121.391159,51.314026],"type":"Point"}
}