{
  "type": "Feature",
  "properties": {
    "addr:full":"856 Av Lariviere Rouyn-Noranda QC J9X 4K4",
    "addr:postcode":"j9x 4k4",
    "addr:street":"856 Av Lariviere",
    "iso:country":"CA",
    "sg:address":"856 Av Lariviere",
    "sg:city":"Rouyn-Noranda",
    "sg:classifiers":[
        {
            "category":"Professional",
            "subcategory":"Business Services",
            "type":"Services"
        }
    ],
    "sg:phone":"+1 819 797 9275",
    "sg:postcode":"J9X 4K4",
    "sg:province":"QC",
    "sg:tags":[
        "water",
        "treatment"
    ],
    "wof:name":"Filtration Nord-Ouest Enr",
    "wof:placetype":"venue"
},
  "geometry": {"coordinates":[-79.00251,48.225491],"type":"Point"}
}