{
  "type": "Feature",
  "properties": {
    "addr:full":"1201 108E Av Saint-Georges-DE-Champlain QC G9T 5K4",
    "addr:housenumber":"1201",
    "addr:postcode":"g9t 5k4",
    "addr:street":"108E Av Saint-Georges-De-Champlain",
    "iso:country":"CA",
    "sg:address":"1201 108E Av",
    "sg:city":"Saint-Georges-DE-Champlain",
    "sg:classifiers":[
        {
            "category":"Retail",
            "subcategory":"Auto Repair",
            "type":"Services"
        }
    ],
    "sg:phone":"+1 819 538 3092",
    "sg:postcode":"G9T 5K4",
    "sg:province":"QC",
    "sg:tags":[
        "repairing",
        "automobile"
    ],
    "wof:name":"Garage Cloutier",
    "wof:placetype":"venue"
},
  "geometry": {"coordinates":[-72.34311676030001,46.4410400391],"type":"Point"}
}