{
  "type": "Feature",
  "properties": {
    "iso:country":"CA",
    "sg:address":"315 Pinnacle St",
    "sg:city":"Belleville",
    "sg:classifiers":[
        {
            "category":"Home & Garden",
            "subcategory":"Furniture",
            "type":"Retail Goods"
        }
    ],
    "sg:phone":"+1 613 962 6110",
    "sg:postcode":"K8N 3B3",
    "sg:province":"ON",
    "wof:name":"United Furniture Warehouse",
    "wof:placetype":"venue"
},
  "geometry": {"coordinates":[-77.3848571777,44.1693153381],"type":"Point"}
}