{
  "type": "Feature",
  "properties": {
    "addr:full":"1981 9 Ave NE Salmon Arm BC V1E 2L2",
    "addr:housenumber":"1981",
    "addr:postcode":"v1e 2l2",
    "addr:street":"9 Ave Ne",
    "iso:country":"CA",
    "sg:address":"1981 9 Ave NE",
    "sg:city":"Salmon Arm",
    "sg:classifiers":[
        {
            "category":"Organizations",
            "subcategory":"Religious Organization",
            "type":"Services"
        }
    ],
    "sg:phone":"+1 250 832 7282",
    "sg:postcode":"V1E 2L2",
    "sg:province":"BC",
    "sg:tags":[
        "church"
    ],
    "wof:name":"St Andrew's Presbyterian Chr",
    "wof:placetype":"venue"
},
  "geometry": {"coordinates":[-119.262550354,50.7064857483],"type":"Point"}
}