{
  "type": "Feature",
  "properties": {
    "addr:full":"3240 Mcgill Cres Prince George BC V2N 4J3",
    "addr:housenumber":"3240",
    "addr:postcode":"v2n 4j3",
    "addr:street":"Mcgill Cres",
    "iso:country":"CA",
    "sg:address":"3240 Mcgill Cres",
    "sg:city":"Prince George",
    "sg:classifiers":[
        {
            "category":"Health Services",
            "subcategory":"Clinic",
            "type":"Services"
        }
    ],
    "sg:phone":"+1 250 964 8676",
    "sg:postcode":"V2N 4J3",
    "sg:province":"BC",
    "sg:tags":[
        "hypnotherapy",
        "training",
        "sales"
    ],
    "wof:name":"Performance Institute",
    "wof:placetype":"venue"
},
  "geometry": {"coordinates":[-122.775803,53.869751],"type":"Point"}
}