{
  "type": "Feature",
  "properties": {
    "iso:country":"CA",
    "sg:city":"Oxdrift",
    "sg:classifiers":[
        {
            "category":"Government",
            "subcategory":"Fire Station",
            "type":"Public Place"
        }
    ],
    "sg:phone":"+1 807 937 7255",
    "sg:postcode":"P0V 2J0",
    "sg:province":"ON",
    "sg:tags":[
        "department"
    ],
    "wof:name":"Ontarion Service Base",
    "wof:placetype":"venue"
},
  "geometry": {"coordinates":[-93.01639556879999,49.8013496399],"type":"Point"}
}