{
  "type": "Feature",
  "properties": {
    "addr:full":"Surrey BC V3W 4M8",
    "addr:postcode":"v3w 4m8",
    "iso:country":"CA",
    "sg:city":"Surrey",
    "sg:classifiers":[
        {
            "category":"Manufacturing",
            "subcategory":"Glass & Minerals",
            "type":"Manufacturing & Wholesale Goods"
        }
    ],
    "sg:phone":"+1 604 597 3318",
    "sg:postcode":"V3W 4M8",
    "sg:province":"BC",
    "sg:tags":[
        "fabricator",
        "fiber"
    ],
    "wof:name":"John's Custom Fibreglass",
    "wof:placetype":"venue"
},
  "geometry": {"coordinates":[-122.85700225799999,49.1449508667],"type":"Point"}
}