{
  "type": "Feature",
  "properties": {
    "addr:full":"Etobicoke ON M9W 1G3",
    "addr:postcode":"m9w 1g3",
    "iso:country":"CA",
    "sg:city":"Etobicoke",
    "sg:classifiers":[
        {
            "category":"Manufacturing",
            "subcategory":"Furniture",
            "type":"Manufacturing & Wholesale Goods"
        }
    ],
    "sg:phone":"+1 416 241 5850",
    "sg:postcode":"M9W 1G3",
    "sg:province":"ON",
    "wof:name":"Furniture in Style",
    "wof:placetype":"venue"
},
  "geometry": {"coordinates":[-79.5697402954,43.7034645081],"type":"Point"}
}