{
  "type": "Feature",
  "properties": {
    "addr:full":"Montreal QC H3M 3E2",
    "addr:postcode":"h3m 3e2",
    "iso:country":"CA",
    "sg:city":"Montreal",
    "sg:classifiers":[
        {
            "category":"Insurance",
            "subcategory":"Insurance Agent",
            "type":"Services"
        }
    ],
    "sg:phone":"+1 514 333 7371",
    "sg:postcode":"H3M 3E2",
    "sg:province":"QC",
    "wof:name":"Richard Sauve Assurance Inc",
    "wof:placetype":"venue"
},
  "geometry": {"coordinates":[-73.6787185669,45.5368003845],"type":"Point"}
}