{
  "type": "Feature",
  "properties": {
    "addr:full":"26580 29 Ave Aldergrove BC V4W 3B3",
    "addr:housenumber":"26580",
    "addr:postcode":"v4w 3b3",
    "addr:street":"29 Ave",
    "iso:country":"CA",
    "sg:address":"26580 29 Ave",
    "sg:city":"Aldergrove",
    "sg:classifiers":[
        {
            "category":"Organizations",
            "subcategory":"Religious Organization",
            "type":"Services"
        }
    ],
    "sg:phone":"+1 604 856 5629",
    "sg:postcode":"V4W 3B3",
    "sg:province":"BC",
    "sg:tags":[
        "church"
    ],
    "wof:name":"Gospel Chapel",
    "wof:placetype":"venue"
},
  "geometry": {"coordinates":[-122.48790700000001,49.055283],"type":"Point"}
}