{
  "type": "Feature",
  "properties": {
    "addr:full":"840 Innisfil Beach Rd Innisfil ON L9S 2C3",
    "addr:housenumber":"840",
    "addr:postcode":"l9s 2c3",
    "addr:street":"Innisfil Beach Rd",
    "iso:country":"CA",
    "sg:address":"840 Innisfil Beach Rd",
    "sg:city":"Innisfil",
    "sg:classifiers":[
        {
            "category":"Restaurant",
            "type":"Food & Drink"
        }
    ],
    "sg:phone":"+1 705 431 0241",
    "sg:postcode":"L9S 2C3",
    "sg:province":"ON",
    "sg:tags":[
        "pizza"
    ],
    "wof:name":"241 Pizza",
    "wof:placetype":"venue"
},
  "geometry": {"coordinates":[-79.54207599999999,44.316341],"type":"Point"}
}