{
  "type": "Feature",
  "properties": {
    "addr:full":"520 Springbank Dr London ON N6J 1G8",
    "addr:housenumber":"520",
    "addr:postcode":"n6j 1g8",
    "addr:street":"Springbank Dr",
    "iso:country":"CA",
    "sg:address":"520 Springbank Dr",
    "sg:city":"London",
    "sg:classifiers":[
        {
            "category":"Health Services",
            "subcategory":"Chiropractor",
            "type":"Services"
        }
    ],
    "sg:phone":"+1 519 472 1800",
    "sg:postcode":"N6J 1G8",
    "sg:province":"ON",
    "wof:name":"Chiropractic Life Ctr",
    "wof:placetype":"venue"
},
  "geometry": {"coordinates":[-81.2894210815,42.9651985168],"type":"Point"}
}