{
  "type": "Feature",
  "properties": {
    "addr:full":"Rimouski QC G5L 8T7",
    "addr:postcode":"g5l 8t7",
    "iso:country":"CA",
    "sg:city":"Rimouski",
    "sg:classifiers":[
        {
            "category":"Organizations",
            "subcategory":"Professional Association",
            "type":"Services"
        }
    ],
    "sg:phone":"+1 418 724 5044",
    "sg:postcode":"G5L 8T7",
    "sg:province":"QC",
    "wof:name":"Syndicat Employes D'Execution",
    "wof:placetype":"venue"
},
  "geometry": {"coordinates":[-68.5276641846,48.451461792],"type":"Point"}
}