{
  "type": "Feature",
  "properties": {
    "addr:full":"Montreal QC H1Z 3A3",
    "addr:postcode":"h1z 3a3",
    "iso:country":"CA",
    "sg:city":"Montreal",
    "sg:classifiers":[
        {
            "category":"Manufacturing",
            "subcategory":"Signs",
            "type":"Manufacturing & Wholesale Goods"
        }
    ],
    "sg:phone":"+1 514 271 4555",
    "sg:postcode":"H1Z 3A3",
    "sg:province":"QC",
    "wof:name":"Enseignes Solution",
    "wof:placetype":"venue"
},
  "geometry": {"coordinates":[-73.622704,45.568172],"type":"Point"}
}