{
  "type": "Feature",
  "properties": {
    "addr:full":"1600 Aimco Blvd Mississauga ON L4W 1V1",
    "addr:housenumber":"1600",
    "addr:postcode":"l4w 1v1",
    "addr:street":"Aimco Blvd",
    "iso:country":"CA",
    "sg:address":"1600 Aimco Blvd",
    "sg:city":"Mississauga",
    "sg:classifiers":[
        {
            "category":"Health Services",
            "subcategory":"Medical Lab",
            "type":"Services"
        }
    ],
    "sg:phone":"+1 905 238 5281",
    "sg:postcode":"L4W 1V1",
    "sg:province":"ON",
    "sg:tags":[
        "laboratory"
    ],
    "wof:name":"Canadian Medical Laboratories",
    "wof:placetype":"venue"
},
  "geometry": {"coordinates":[-79.622208,43.640465],"type":"Point"}
}