{
  "type": "Feature",
  "properties": {
    "iso:country":"CA",
    "sg:address":"327 Boul Maloney E",
    "sg:city":"Gatineau",
    "sg:classifiers":[
        {
            "category":"Food & Beverages",
            "subcategory":"Bakery",
            "type":"Retail Goods"
        }
    ],
    "sg:phone":"+1 819 663 8000",
    "sg:postcode":"J8P 1E2",
    "sg:province":"QC",
    "sg:tags":[
        "doughnut"
    ],
    "wof:name":"Tim Hortons",
    "wof:placetype":"venue"
},
  "geometry": {"coordinates":[-75.644073,45.484566],"type":"Point"}
}