{
  "type": "Feature",
  "properties": {
    "addr:full":"4150 Boul DE Sainte-Adele Sainte-Adele QC J8B 2N7",
    "addr:housenumber":"4150",
    "addr:postcode":"j8b 2n7",
    "addr:street":"Boul De Sainte-Adele Sainte-Adele",
    "iso:country":"CA",
    "sg:address":"4150 Boul DE Sainte-Adele",
    "sg:city":"Sainte-Adele",
    "sg:classifiers":[
        {
            "category":"Home & Garden",
            "subcategory":"Garden Supply",
            "type":"Retail Goods"
        }
    ],
    "sg:phone":"+1 450 229 3265",
    "sg:postcode":"J8B 2N7",
    "sg:province":"QC",
    "sg:tags":[
        "nurseryman"
    ],
    "wof:name":"Jardinor Enr",
    "wof:placetype":"venue"
},
  "geometry": {"coordinates":[-74.13851200000001,45.954319],"type":"Point"}
}