{
  "type": "Feature",
  "properties": {
    "addr:full":"439 Hwy 11 Matheson ON P0K 1N0",
    "addr:housenumber":"439",
    "addr:postcode":"p0k 1n0",
    "addr:street":"Hwy 11 Matheson",
    "iso:country":"CA",
    "sg:address":"439 Hwy 11",
    "sg:city":"Matheson",
    "sg:classifiers":[
        {
            "category":"Restaurant",
            "type":"Food & Drink"
        }
    ],
    "sg:phone":"+1 705 273 2200",
    "sg:postcode":"P0K 1N0",
    "sg:province":"ON",
    "sg:tags":[
        "caterer"
    ],
    "wof:name":"Northern Delight Restaurant",
    "wof:placetype":"venue"
},
  "geometry": {"coordinates":[-80.5383148193,48.5377693176],"type":"Point"}
}