{
  "type": "Feature",
  "properties": {
    "addr:full":"830 Hanwell Rd # 6 Fredericton NB E3B 6A2",
    "addr:housenumber":"830",
    "addr:postcode":"e3b 6a2",
    "addr:street":"Hanwell Rd # 6",
    "iso:country":"CA",
    "sg:address":"830 Hanwell Rd # 6",
    "sg:city":"Fredericton",
    "sg:classifiers":[
        {
            "category":"Real Estate",
            "subcategory":"Developer",
            "type":"Services"
        }
    ],
    "sg:phone":"+1 506 451 1776",
    "sg:postcode":"E3B 6A2",
    "sg:province":"NB",
    "sg:tags":[
        "apartment"
    ],
    "wof:name":"Colpitts Developments Ltd",
    "wof:placetype":"venue"
},
  "geometry": {"coordinates":[-66.68524932859999,45.9530105591],"type":"Point"}
}