{
  "type": "Feature",
  "properties": {
    "addr:full":"Scarborough ON M1X 1A9",
    "addr:postcode":"m1x 1a9",
    "iso:country":"CA",
    "sg:city":"Scarborough",
    "sg:classifiers":[
        {
            "category":"Building & Trades",
            "subcategory":"Plumbing",
            "type":"Services"
        }
    ],
    "sg:phone":"+1 416 321 2001",
    "sg:postcode":"M1X 1A9",
    "sg:province":"ON",
    "sg:tags":[
        "contractor"
    ],
    "wof:name":"B Jackson Plumbing Ltd",
    "wof:placetype":"venue"
},
  "geometry": {"coordinates":[-79.23290299999999,43.818394],"type":"Point"}
}