{
  "type": "Feature",
  "properties": {
    "addr:full":"Laurel ON L0N 1L0",
    "addr:postcode":"l0n 1l0",
    "iso:country":"CA",
    "sg:city":"Laurel",
    "sg:classifiers":[
        {
            "category":"Building & Trades",
            "subcategory":"Construction",
            "type":"Services"
        }
    ],
    "sg:phone":"+1 519 941 2699",
    "sg:postcode":"L0N 1L0",
    "sg:province":"ON",
    "sg:tags":[
        "dry wall",
        "contractor"
    ],
    "wof:name":"Ewen Drywall",
    "wof:placetype":"venue"
},
  "geometry": {"coordinates":[-80.20975494379999,43.9520568848],"type":"Point"}
}