{
  "type": "Feature",
  "properties": {
    "iso:country":"CA",
    "sg:address":"351 Av Lariviere",
    "sg:city":"Rouyn-Noranda",
    "sg:classifiers":[
        {
            "category":"Insurance",
            "subcategory":"Insurance Agent",
            "type":"Services"
        }
    ],
    "sg:phone":"+1 819 762 0911",
    "sg:postcode":"J9X 4H5",
    "sg:province":"QC",
    "sg:tags":[
        "adjuster"
    ],
    "wof:name":"Evaluations Gerald Thiffault",
    "wof:placetype":"venue"
},
  "geometry": {"coordinates":[-79.0144271851,48.2331237793],"type":"Point"}
}