{
  "type": "Feature",
  "properties": {
    "addr:full":"4537 Aspdin Rd Rosseau ON P0C 1J0",
    "addr:housenumber":"4537",
    "addr:postcode":"p0c 1j0",
    "addr:street":"Aspdin Rd",
    "iso:country":"CA",
    "sg:address":"4537 Aspdin Rd",
    "sg:city":"Rosseau",
    "sg:classifiers":[
        {
            "category":"Retail",
            "subcategory":"Auto Repair",
            "type":"Services"
        }
    ],
    "sg:phone":"+1 705 732 1285",
    "sg:postcode":"P0C 1J0",
    "sg:province":"ON",
    "sg:tags":[
        "repairing",
        "automobile"
    ],
    "wof:name":"Automatic Transmission Spclty",
    "wof:placetype":"venue"
},
  "geometry": {"coordinates":[-79.63999938960001,45.257068634],"type":"Point"}
}