{
  "type": "Feature",
  "properties": {
    "addr:full":"3536 White Oak Rd London ON N6E 2Z9",
    "addr:housenumber":"3536",
    "addr:postcode":"n6e 2z9",
    "addr:street":"White Oak Rd",
    "iso:country":"CA",
    "sg:address":"3536 White Oak Rd",
    "sg:city":"London",
    "sg:classifiers":[
        {
            "category":"Autos & Motor Vehicles",
            "subcategory":"Auto Supplies",
            "type":"Retail Goods"
        }
    ],
    "sg:phone":"+1 519 685 7072",
    "sg:postcode":"N6E 2Z9",
    "sg:province":"ON",
    "sg:tags":[
        "automobile",
        "parts"
    ],
    "wof:name":"Battery Supply & Svc",
    "wof:placetype":"venue"
},
  "geometry": {"coordinates":[-81.24852,42.926975],"type":"Point"}
}