{
  "type": "Feature",
  "properties": {
    "addr:full":"191 Geary Ave Toronto ON M6H 2C1",
    "addr:housenumber":"191",
    "addr:postcode":"m6h 2c1",
    "addr:street":"Geary Ave",
    "iso:country":"CA",
    "sg:address":"191 Geary Ave",
    "sg:city":"Toronto",
    "sg:classifiers":[
        {
            "category":"Food & Beverages",
            "subcategory":"Bakery",
            "type":"Retail Goods"
        }
    ],
    "sg:phone":"+1 416 537 2993",
    "sg:postcode":"M6H 2C1",
    "sg:province":"ON",
    "sg:tags":[
        "baker"
    ],
    "wof:name":"Sunflower Bakery",
    "wof:placetype":"venue"
},
  "geometry": {"coordinates":[-79.4373092651,43.6697235107],"type":"Point"}
}