{
  "type": "Feature",
  "properties": {
    "addr:full":"113 Bowes St Parry Sound ON P2A 2L8",
    "addr:housenumber":"113",
    "addr:postcode":"p2a 2l8",
    "addr:street":"Bowes St",
    "iso:country":"CA",
    "sg:address":"113 Bowes St",
    "sg:city":"Parry Sound",
    "sg:classifiers":[
        {
            "category":"Food & Beverages",
            "subcategory":"Bakery",
            "type":"Retail Goods"
        }
    ],
    "sg:phone":"+1 705 746 7198",
    "sg:postcode":"P2A 2L8",
    "sg:province":"ON",
    "sg:tags":[
        "tea",
        "coffee",
        "doughnut"
    ],
    "wof:name":"Tim Hortons",
    "wof:placetype":"venue"
},
  "geometry": {"coordinates":[-80.01593017579999,45.3426475525],"type":"Point"}
}