{
  "type": "Feature",
  "properties": {
    "addr:full":"18 Rue Du Parc Mercier QC J6R 1E5",
    "addr:housenumber":"18",
    "addr:postcode":"j6r 1e5",
    "addr:street":"Rue Du Parc",
    "iso:country":"CA",
    "sg:address":"18 Rue Du Parc",
    "sg:city":"Mercier",
    "sg:classifiers":[
        {
            "category":"Arena",
            "subcategory":"Sports Club",
            "type":"Entertainment"
        }
    ],
    "sg:phone":"+1 450 699 4443",
    "sg:postcode":"J6R 1E5",
    "sg:province":"QC",
    "sg:tags":[
        "skating",
        "athletic",
        "stadium",
        "rink",
        "fields"
    ],
    "wof:name":"Centre Sportif Mercier Inc",
    "wof:placetype":"venue"
},
  "geometry": {"coordinates":[-73.74572000000001,45.313427],"type":"Point"}
}