{
  "type": "Feature",
  "properties": {
    "addr:full":"3091 Albion Rd N Ottawa ON K1V 9V9",
    "addr:housenumber":"3091",
    "addr:postcode":"k1v 9v9",
    "addr:street":"Albion Rd N",
    "iso:country":"CA",
    "sg:address":"3091 Albion Rd N",
    "sg:city":"Ottawa",
    "sg:classifiers":[
        {
            "category":"Manufacturing",
            "subcategory":"Metals",
            "type":"Manufacturing & Wholesale Goods"
        }
    ],
    "sg:phone":"+1 613 727 0529",
    "sg:postcode":"K1V 9V9",
    "sg:province":"ON",
    "sg:tags":[
        "finisher"
    ],
    "wof:name":"High Quality Paint Finishing",
    "wof:placetype":"venue"
},
  "geometry": {"coordinates":[-75.6510543823,45.3684158325],"type":"Point"}
}