{
  "type": "Feature",
  "properties": {
    "addr:full":"47 Norn Cres Markham ON L3S 2A9",
    "addr:housenumber":"47",
    "addr:postcode":"l3s 2a9",
    "addr:street":"Norn Cres",
    "iso:country":"CA",
    "sg:address":"47 Norn Cres",
    "sg:city":"Markham",
    "sg:classifiers":[
        {
            "category":"Building & Trades",
            "subcategory":"Electrical",
            "type":"Services"
        }
    ],
    "sg:phone":"+1 905 472 9116",
    "sg:postcode":"L3S 2A9",
    "sg:province":"ON",
    "sg:tags":[
        "electric",
        "contractor"
    ],
    "wof:name":"Wire Electric",
    "wof:placetype":"venue"
},
  "geometry": {"coordinates":[-79.27207199999999,43.832279],"type":"Point"}
}