{
  "type": "Feature",
  "properties": {
    "addr:full":"5102 46 St Vermilion AB T9X 1G5",
    "addr:housenumber":"5102",
    "addr:postcode":"t9x 1g5",
    "addr:street":"46 St",
    "iso:country":"CA",
    "sg:address":"5102 46 St",
    "sg:city":"Vermilion",
    "sg:classifiers":[
        {
            "category":"Education",
            "subcategory":"School",
            "type":"Public Place"
        }
    ],
    "sg:phone":"+1 780 853 4177",
    "sg:postcode":"T9X 1G5",
    "sg:province":"AB",
    "wof:name":"J R Robson School",
    "wof:placetype":"venue"
},
  "geometry": {"coordinates":[-110.840301514,53.3549842834],"type":"Point"}
}