{
  "type": "Feature",
  "properties": {
    "addr:full":"Banff AB T1L 1B5",
    "addr:postcode":"t1l 1b5",
    "iso:country":"CA",
    "sg:city":"Banff",
    "sg:classifiers":[
        {
            "category":"Retail",
            "subcategory":"Auto Repair",
            "type":"Services"
        }
    ],
    "sg:phone":"+1 403 762 5477",
    "sg:postcode":"T1L 1B5",
    "sg:province":"AB",
    "sg:tags":[
        "repairing",
        "automobile"
    ],
    "wof:name":"Banff Auto Ltd",
    "wof:placetype":"venue"
},
  "geometry": {"coordinates":[-115.558250427,51.1892852783],"type":"Point"}
}