{
  "type": "Feature",
  "properties": {
    "addr:full":"1020 Mcnicoll Ave # 400 Scarborough ON M1W 2J6",
    "addr:housenumber":"1020",
    "addr:postcode":"m1w 2j6",
    "addr:street":"Mcnicoll Ave # 400",
    "iso:country":"CA",
    "sg:address":"1020 Mcnicoll Ave # 400",
    "sg:city":"Scarborough",
    "sg:classifiers":[
        {
            "category":"Health Services",
            "subcategory":"Nursing And Care Facility",
            "type":"Services"
        }
    ],
    "sg:phone":"+1 416 497 3639",
    "sg:postcode":"M1W 2J6",
    "sg:province":"ON",
    "sg:tags":[
        "home",
        "retirement",
        "community"
    ],
    "wof:name":"German Speaking Seniors",
    "wof:placetype":"venue"
},
  "geometry": {"coordinates":[-79.3338851929,43.8043251038],"type":"Point"}
}