{
  "type": "Feature",
  "properties": {
    "iso:country":"CA",
    "sg:address":"649 3 St SE",
    "sg:city":"Medicine Hat",
    "sg:classifiers":[
        {
            "category":"Shopping",
            "subcategory":"Clothing, Apparel, & Fashions",
            "type":"Retail Goods"
        }
    ],
    "sg:phone":"+1 403 526 2544",
    "sg:postcode":"T1A 0H4",
    "sg:province":"AB",
    "sg:tags":[
        "furnishing"
    ],
    "wof:name":"Dell Rossi Men's Wear Ltd",
    "wof:placetype":"venue"
},
  "geometry": {"coordinates":[-110.6745224,50.0400390625],"type":"Point"}
}