{
  "type": "Feature",
  "properties": {
    "addr:full":"897 Dufferin St Woodstock ON N4S 1Y8",
    "addr:housenumber":"897",
    "addr:postcode":"n4s 1y8",
    "addr:street":"Dufferin St",
    "iso:country":"CA",
    "sg:address":"897 Dufferin St",
    "sg:city":"Woodstock",
    "sg:classifiers":[
        {
            "category":"Retail",
            "subcategory":"Repair Shop",
            "type":"Services"
        }
    ],
    "sg:phone":"+1 519 421 1591",
    "sg:postcode":"N4S 1Y8",
    "sg:province":"ON",
    "sg:tags":[
        "welding"
    ],
    "wof:name":"Brown's Welding",
    "wof:placetype":"venue"
},
  "geometry": {"coordinates":[-80.73732800000001,43.128208],"type":"Point"}
}