{
  "type": "Feature",
  "properties": {
    "iso:country":"CA",
    "sg:city":"Richmond Hill",
    "sg:classifiers":[
        {
            "category":"Shopping",
            "subcategory":"Shoes",
            "type":"Retail Goods"
        }
    ],
    "sg:phone":"+1 416 410 7867",
    "sg:postcode":"L4B 1M6",
    "sg:province":"ON",
    "sg:tags":[
        "rope",
        "shoe",
        "lace"
    ],
    "wof:name":"Braids & Laces Ltd",
    "wof:placetype":"venue"
},
  "geometry": {"coordinates":[-79.3898468018,43.8525390625],"type":"Point"}
}