{
  "type": "Feature",
  "properties": {
    "iso:country":"CA",
    "sg:address":"6430 Erin Mills Pky",
    "sg:city":"Mississauga",
    "sg:classifiers":[
        {
            "category":"Restaurant",
            "type":"Food & Drink"
        }
    ],
    "sg:phone":"+1 905 858 5849",
    "sg:postcode":"L5N 3P3",
    "sg:province":"ON",
    "wof:name":"Swiss Chalet Rotisserie/Grill",
    "wof:placetype":"venue"
},
  "geometry": {"coordinates":[-79.7424621582,43.5875854492],"type":"Point"}
}