{
  "type": "Feature",
  "properties": {
    "addr:full":"591 Chester Rd Delta BC V3M 6G7",
    "addr:housenumber":"591",
    "addr:postcode":"v3m 6g7",
    "addr:street":"Chester Rd",
    "iso:country":"CA",
    "sg:address":"591 Chester Rd",
    "sg:city":"Delta",
    "sg:classifiers":[
        {
            "category":"Manufacturing",
            "subcategory":"Motor Vehicles & Parts",
            "type":"Manufacturing & Wholesale Goods"
        }
    ],
    "sg:phone":"+1 604 526 6126",
    "sg:postcode":"V3M 6G7",
    "sg:province":"BC",
    "sg:tags":[
        "body",
        "truck"
    ],
    "wof:name":"Commercial Body Builders Ltd",
    "wof:placetype":"venue"
},
  "geometry": {"coordinates":[-122.94628906200001,49.1694602966],"type":"Point"}
}