{
  "type": "Feature",
  "properties": {
    "addr:full":"5002 46 St Stettler AB T0C 2L2",
    "addr:housenumber":"5002",
    "addr:postcode":"t0c 2l2",
    "addr:street":"46 St",
    "iso:country":"CA",
    "sg:address":"5002 46 St",
    "sg:city":"Stettler",
    "sg:classifiers":[
        {
            "category":"Building & Trades",
            "subcategory":"Electrical",
            "type":"Services"
        }
    ],
    "sg:phone":"+1 403 742 5111",
    "sg:postcode":"T0C 2L2",
    "sg:province":"AB",
    "sg:tags":[
        "electric",
        "contractor"
    ],
    "wof:name":"Ampko Electric Ltd",
    "wof:placetype":"venue"
},
  "geometry": {"coordinates":[-112.699524,52.326488],"type":"Point"}
}