{
  "type": "Feature",
  "properties": {
    "addr:full":"285 Bunting Rd St Catharines ON L2M 7T9",
    "addr:housenumber":"285",
    "addr:postcode":"l2m 7t9",
    "addr:street":"Bunting Rd",
    "iso:country":"CA",
    "sg:address":"285 Bunting Rd",
    "sg:city":"St Catharines",
    "sg:classifiers":[
        {
            "category":"Insurance",
            "subcategory":"Insurance Agent",
            "type":"Services"
        }
    ],
    "sg:phone":"+1 905 646 9216",
    "sg:postcode":"L2M 7T9",
    "sg:province":"ON",
    "wof:name":"K & B Insurance",
    "wof:placetype":"venue"
},
  "geometry": {"coordinates":[-79.2103500366,43.1774253845],"type":"Point"}
}