{
  "type": "Feature",
  "properties": {
    "addr:full":"1009 Highway 214 Belnan NS B2S 2R1",
    "addr:housenumber":"1009",
    "addr:postcode":"b2s 2r1",
    "addr:street":"Highway 214",
    "iso:country":"CA",
    "sg:address":"1009 Highway 214",
    "sg:city":"Belnan",
    "sg:classifiers":[
        {
            "category":"Retail",
            "subcategory":"Animal Services",
            "type":"Services"
        }
    ],
    "sg:phone":"+1 902 883 1494",
    "sg:postcode":"B2S 2R1",
    "sg:province":"NS",
    "sg:tags":[
        "pet",
        "boarding",
        "sitting"
    ],
    "wof:name":"Regalridge Kennel",
    "wof:placetype":"venue"
},
  "geometry": {"coordinates":[-63.5264892578,44.9946250916],"type":"Point"}
}