{
  "type": "Feature",
  "properties": {
    "iso:country":"CA",
    "sg:address":"84 Park Row",
    "sg:city":"Woodstock",
    "sg:classifiers":[
        {
            "category":"Building & Trades",
            "subcategory":"Construction",
            "type":"Services"
        }
    ],
    "sg:phone":"+1 519 537 3384",
    "sg:postcode":"N4S 1V8",
    "sg:province":"ON",
    "sg:tags":[
        "masonry",
        "contractor"
    ],
    "wof:name":"Ray's Masonry",
    "wof:placetype":"venue"
},
  "geometry": {"coordinates":[-80.77173614500001,43.1238594055],"type":"Point"}
}