{
  "type": "Feature",
  "properties": {
    "addr:full":"169 Bartley Dr North York ON M4A 1E7",
    "addr:housenumber":"169",
    "addr:postcode":"m4a 1e7",
    "addr:street":"Bartley Dr",
    "iso:country":"CA",
    "sg:address":"169 Bartley Dr",
    "sg:city":"North York",
    "sg:classifiers":[
        {
            "category":"Professional",
            "subcategory":"Advertising",
            "type":"Services"
        }
    ],
    "sg:phone":"+1 416 750 3222",
    "sg:postcode":"M4A 1E7",
    "sg:province":"ON",
    "sg:tags":[
        "mailing",
        "list"
    ],
    "wof:name":"Complete Mailing Svc",
    "wof:placetype":"venue"
},
  "geometry": {"coordinates":[-79.311363,43.721107],"type":"Point"}
}