{
  "type": "Feature",
  "properties": {
    "addr:full":"Dryden ON P8N 2W6",
    "addr:postcode":"p8n 2w6",
    "iso:country":"CA",
    "sg:city":"Dryden",
    "sg:classifiers":[
        {
            "category":"Building & Trades",
            "subcategory":"Construction",
            "type":"Services"
        }
    ],
    "sg:phone":"+1 807 223 7495",
    "sg:postcode":"P8N 2W6",
    "sg:province":"ON",
    "sg:tags":[
        "general",
        "contractor"
    ],
    "wof:name":"Gamble Contracting",
    "wof:placetype":"venue"
},
  "geometry": {"coordinates":[-92.823868,49.789886],"type":"Point"}
}