{
  "type": "Feature",
  "properties": {
    "addr:full":"Ottawa ON K1H 7X3",
    "addr:postcode":"k1h 7x3",
    "iso:country":"CA",
    "sg:city":"Ottawa",
    "sg:classifiers":[
        {
            "category":"Social Services",
            "type":"Services"
        }
    ],
    "sg:phone":"+1 613 736 5270",
    "sg:postcode":"K1H 7X3",
    "sg:province":"ON",
    "sg:tags":[
        "organization",
        "welfare"
    ],
    "wof:name":"Volunteer Ottawa",
    "wof:placetype":"venue"
},
  "geometry": {"coordinates":[-75.6767578125,45.3890304565],"type":"Point"}
}