{
  "type": "Feature",
  "properties": {
    "addr:full":"187 Henlow Bay Winnipeg MB R3Y 1G4",
    "addr:housenumber":"187",
    "addr:postcode":"r3y 1g4",
    "addr:street":"Henlow Bay",
    "iso:country":"CA",
    "sg:address":"187 Henlow Bay",
    "sg:city":"Winnipeg",
    "sg:classifiers":[
        {
            "category":"Organizations",
            "subcategory":"Religious Organization",
            "type":"Services"
        }
    ],
    "sg:phone":"+1 204 885 2125",
    "sg:postcode":"R3Y 1G4",
    "sg:province":"MB",
    "sg:tags":[
        "church"
    ],
    "wof:name":"Gull Lake Gospel Church",
    "wof:placetype":"venue"
},
  "geometry": {"coordinates":[-97.1910247803,49.8147201538],"type":"Point"}
}