{
  "type": "Feature",
  "properties": {
    "addr:full":"2411 Des Pruches Ave Orleans ON K1W 1K5",
    "addr:housenumber":"2411",
    "addr:postcode":"k1w 1k5",
    "addr:street":"Des Pruches Ave",
    "iso:country":"CA",
    "sg:address":"2411 Des Pruches Ave",
    "sg:city":"Orleans",
    "sg:classifiers":[
        {
            "category":"Retail",
            "subcategory":"Portrait Studio",
            "type":"Services"
        }
    ],
    "sg:phone":"+1 613 841 7766",
    "sg:postcode":"K1W 1K5",
    "sg:province":"ON",
    "sg:tags":[
        "photographer"
    ],
    "wof:name":"Ron Zeitlan Photo",
    "wof:placetype":"venue"
},
  "geometry": {"coordinates":[-75.52617600000001,45.434544],"type":"Point"}
}