{
  "type": "Feature",
  "properties": {
    "iso:country":"CA",
    "sg:address":"804 Ellice Ave",
    "sg:city":"Winnipeg",
    "sg:classifiers":[
        {
            "category":"Shopping",
            "subcategory":"Bicycles & Sporting Goods",
            "type":"Retail Goods"
        }
    ],
    "sg:phone":"+1 204 783 6458",
    "sg:postcode":"R3G 0B9",
    "sg:province":"MB",
    "sg:tags":[
        "pawnbroker"
    ],
    "wof:name":"Ellice Pawn Shop Inc",
    "wof:placetype":"venue"
},
  "geometry": {"coordinates":[-97.168388,49.893116],"type":"Point"}
}