{
  "type": "Feature",
  "properties": {
    "addr:full":"1396 Grand Lake Rd Sydney NS B1M 1A1",
    "addr:housenumber":"1396",
    "addr:postcode":"b1m 1a1",
    "addr:street":"Grand Lake Rd",
    "iso:country":"CA",
    "sg:address":"1396 Grand Lake Rd",
    "sg:city":"Sydney",
    "sg:classifiers":[
        {
            "category":"Travel",
            "subcategory":"Hotels & Motels",
            "type":"Entertainment"
        }
    ],
    "sg:phone":"+1 902 539 4375",
    "sg:postcode":"B1M 1A1",
    "sg:province":"NS",
    "wof:name":"Jacques Cartier Motel",
    "wof:placetype":"venue"
},
  "geometry": {"coordinates":[-60.0844497681,46.173248291],"type":"Point"}
}