{
  "type": "Feature",
  "properties": {
    "addr:full":"2526 Waverley Ave Vancouver BC V5S 4W1",
    "addr:housenumber":"2526",
    "addr:postcode":"v5s 4w1",
    "addr:street":"Waverley Ave",
    "iso:country":"CA",
    "sg:address":"2526 Waverley Ave",
    "sg:city":"Vancouver",
    "sg:classifiers":[
        {
            "category":"Social Services",
            "type":"Services"
        }
    ],
    "sg:phone":"+1 604 324 6257",
    "sg:postcode":"V5S 4W1",
    "sg:province":"BC",
    "sg:tags":[
        "home",
        "senior",
        "retirement",
        "community",
        "citizen"
    ],
    "wof:name":"Shannon Oaks",
    "wof:placetype":"venue"
},
  "geometry": {"coordinates":[-123.055649,49.226719],"type":"Point"}
}