{
  "type": "Feature",
  "properties": {
    "iso:country":"CA",
    "sg:address":"1056 Old Derry Rd",
    "sg:city":"Mississauga",
    "sg:classifiers":[
        {
            "category":"Autos & Motor Vehicles",
            "subcategory":"Fuel & Gas Station",
            "type":"Retail Goods"
        }
    ],
    "sg:phone":"+1 905 670 1337",
    "sg:postcode":"L5W 1A1",
    "sg:province":"ON",
    "sg:tags":[
        "oil"
    ],
    "wof:name":"Meadowvale Gas & Variety",
    "wof:placetype":"venue"
},
  "geometry": {"coordinates":[-79.728928,43.625885],"type":"Point"}
}