{
  "type": "Feature",
  "properties": {
    "iso:country":"CA",
    "sg:city":"Saanichton",
    "sg:classifiers":[
        {
            "category":"Building & Trades",
            "subcategory":"Plumbing",
            "type":"Services"
        }
    ],
    "sg:phone":"+1 250 652 6538",
    "sg:postcode":"V8M 1Z9",
    "sg:province":"BC",
    "sg:tags":[
        "ventilating",
        "conditioning",
        "contractor",
        "system",
        "air"
    ],
    "wof:name":"Elite Metal Works",
    "wof:placetype":"venue"
},
  "geometry": {"coordinates":[-123.41689300500001,48.595199585],"type":"Point"}
}