{
  "type": "Feature",
  "properties": {
    "iso:country":"CA",
    "sg:city":"Calgary",
    "sg:classifiers":[
        {
            "category":"Shopping",
            "type":"Retail Goods"
        }
    ],
    "sg:phone":"+1 403 238 2631",
    "sg:postcode":"T2W 2S8",
    "sg:province":"AB",
    "sg:tags":[
        "picture",
        "art",
        "gallery",
        "dealer"
    ],
    "wof:name":"Exploration Arts",
    "wof:placetype":"venue"
},
  "geometry": {"coordinates":[-114.077072144,50.9376792908],"type":"Point"}
}