{
  "type": "Feature",
  "properties": {
    "addr:full":"625 Manitou Rd SE Calgary AB T2G 4C2",
    "addr:housenumber":"625",
    "addr:postcode":"t2g 4c2",
    "addr:street":"Manitou Rd Se",
    "iso:country":"CA",
    "sg:address":"625 Manitou Rd SE",
    "sg:city":"Calgary",
    "sg:classifiers":[
        {
            "category":"Freight",
            "type":"Transportation"
        }
    ],
    "sg:phone":"+1 403 221 9270",
    "sg:postcode":"T2G 4C2",
    "sg:province":"AB",
    "sg:tags":[
        "delivery",
        "courier"
    ],
    "wof:name":"Greyhound Lines of Canada Ltd",
    "wof:placetype":"venue"
},
  "geometry": {"coordinates":[-114.051453,51.010387],"type":"Point"}
}