{
  "type": "Feature",
  "properties": {
    "addr:full":"427 Boul Bourque Omerville QC J1X 4G2",
    "addr:housenumber":"427",
    "addr:postcode":"j1x 4g2",
    "addr:street":"Boul Bourque",
    "iso:country":"CA",
    "sg:address":"427 Boul Bourque",
    "sg:city":"Omerville",
    "sg:classifiers":[
        {
            "category":"Autos & Motor Vehicles",
            "subcategory":"Automobile Sales",
            "type":"Retail Goods"
        }
    ],
    "sg:phone":"+1 819 843 8145",
    "sg:postcode":"J1X 4G2",
    "sg:province":"QC",
    "sg:tags":[
        "car",
        "dealer"
    ],
    "wof:name":"Nissan Magog Enr",
    "wof:placetype":"venue"
},
  "geometry": {"coordinates":[-72.1109085083,45.2912635803],"type":"Point"}
}