{
  "type": "Feature",
  "properties": {
    "addr:full":"457 Parliament St Toronto ON M5A 3A3",
    "addr:housenumber":"457",
    "addr:postcode":"m5a 3a3",
    "addr:street":"Parliament St",
    "iso:country":"CA",
    "sg:address":"457 Parliament St",
    "sg:city":"Toronto",
    "sg:classifiers":[
        {
            "category":"Food & Beverages",
            "subcategory":"Meat & Fish",
            "type":"Retail Goods"
        }
    ],
    "sg:phone":"+1 416 922 7389",
    "sg:postcode":"M5A 3A3",
    "sg:province":"ON",
    "sg:tags":[
        "seafood"
    ],
    "wof:name":"Halifax Fish Market",
    "wof:placetype":"venue"
},
  "geometry": {"coordinates":[-79.367493,43.663589],"type":"Point"}
}