{
  "type": "Feature",
  "properties": {
    "addr:full":"Carleton Place ON K7C 4M6",
    "addr:postcode":"k7c 4m6",
    "iso:country":"CA",
    "sg:city":"Carleton Place",
    "sg:classifiers":[
        {
            "category":"Food & Beverages",
            "subcategory":"Meat & Fish",
            "type":"Retail Goods"
        }
    ],
    "sg:phone":"+1 613 257 5782",
    "sg:postcode":"K7C 4M6",
    "sg:province":"ON",
    "sg:tags":[
        "frozen"
    ],
    "wof:name":"M & M Meat Shops",
    "wof:placetype":"venue"
},
  "geometry": {"coordinates":[-76.12902069090001,45.1301803589],"type":"Point"}
}