{
  "type": "Feature",
  "properties": {
    "addr:full":"245 Dixon Rd Etobicoke ON M9P 2M4",
    "addr:housenumber":"245",
    "addr:postcode":"m9p 2m4",
    "addr:street":"Dixon Rd",
    "iso:country":"CA",
    "sg:address":"245 Dixon Rd",
    "sg:city":"Etobicoke",
    "sg:classifiers":[
        {
            "category":"Personal",
            "subcategory":"Shoe Repair & Shine",
            "type":"Services"
        }
    ],
    "sg:phone":"+1 416 249 1047",
    "sg:postcode":"M9P 2M4",
    "sg:province":"ON",
    "sg:tags":[
        "repairing",
        "boot"
    ],
    "wof:name":"Moneysworth & Best",
    "wof:placetype":"venue"
},
  "geometry": {"coordinates":[-79.5449523926,43.697353363],"type":"Point"}
}