{
  "type": "Feature",
  "properties": {
    "iso:country":"CA",
    "sg:address":"5111 Bowness Rd NW",
    "sg:city":"Calgary",
    "sg:classifiers":[
        {
            "category":"Health Services",
            "subcategory":"Doctor",
            "type":"Services"
        }
    ],
    "sg:phone":"+1 403 286 6595",
    "sg:postcode":"T3B 4M9",
    "sg:province":"AB",
    "sg:tags":[
        "clinic"
    ],
    "wof:name":"Trans Canada Denture Clinic",
    "wof:placetype":"venue"
},
  "geometry": {"coordinates":[-114.167007446,51.0752677917],"type":"Point"}
}