{
  "type": "Feature",
  "properties": {
    "addr:full":"63 Talbot W Blenheim ON N0P 1A0",
    "addr:housenumber":"63",
    "addr:postcode":"n0p 1a0",
    "addr:street":"Talbot W",
    "iso:country":"CA",
    "sg:address":"63 Talbot W",
    "sg:city":"Blenheim",
    "sg:classifiers":[
        {
            "category":"Real Estate",
            "subcategory":"Real Estate Agent",
            "type":"Services"
        }
    ],
    "sg:phone":"+1 519 676 2022",
    "sg:postcode":"N0P 1A0",
    "sg:province":"ON",
    "wof:name":"Century 21 O'Brien Inc",
    "wof:placetype":"venue"
},
  "geometry": {"coordinates":[-81.99894714360001,42.3340187073],"type":"Point"}
}