{
  "type": "Feature",
  "properties": {
    "addr:full":"320 71st St E Saskatoon SK S7K 3J7",
    "addr:housenumber":"320",
    "addr:postcode":"s7k 3j7",
    "addr:street":"71St St E",
    "iso:country":"CA",
    "sg:address":"320 71st St E",
    "sg:city":"Saskatoon",
    "sg:classifiers":[
        {
            "category":"Manufacturing",
            "subcategory":"Metals",
            "type":"Manufacturing & Wholesale Goods"
        }
    ],
    "sg:phone":"+1 306 931 8737",
    "sg:postcode":"S7K 3J7",
    "sg:province":"SK",
    "sg:tags":[
        "scrap",
        "iron"
    ],
    "wof:name":"Hub City Iron & Metal",
    "wof:placetype":"venue"
},
  "geometry": {"coordinates":[-106.64653778100001,52.2020492554],"type":"Point"}
}