{
  "type": "Feature",
  "properties": {
    "addr:full":"584271 Beachville Beachville ON N0J 1A0",
    "addr:housenumber":"584271",
    "addr:postcode":"n0j 1a0",
    "addr:street":"Beachville",
    "iso:country":"CA",
    "sg:address":"584271 Beachville",
    "sg:city":"Beachville",
    "sg:classifiers":[
        {
            "category":"Home & Garden",
            "subcategory":"Garden Supply",
            "type":"Retail Goods"
        }
    ],
    "sg:phone":"+1 519 423 9798",
    "sg:postcode":"N0J 1A0",
    "sg:province":"ON",
    "sg:tags":[
        "lawn",
        "center",
        "maintenance",
        "grounds"
    ],
    "wof:name":"B & D Landscasping",
    "wof:placetype":"venue"
},
  "geometry": {"coordinates":[-80.84710699999999,43.070206],"type":"Point"}
}