{
  "type": "Feature",
  "properties": {
    "addr:full":"701 Rue Dubois Saint-Eustache QC J7P 3W1",
    "addr:housenumber":"701",
    "addr:postcode":"j7p 3w1",
    "addr:street":"Rue Dubois",
    "iso:country":"CA",
    "sg:address":"701 Rue Dubois",
    "sg:city":"Saint-Eustache",
    "sg:classifiers":[
        {
            "category":"Wholesale",
            "subcategory":"Motor Vehicles",
            "type":"Manufacturing & Wholesale Goods"
        }
    ],
    "sg:phone":"+1 450 472 1178",
    "sg:postcode":"J7P 3W1",
    "sg:province":"QC",
    "sg:tags":[
        "trailer"
    ],
    "wof:name":"Brucha Ventes & Locations Inc",
    "wof:placetype":"venue"
},
  "geometry": {"coordinates":[-73.871475,45.589928],"type":"Point"}
}