{
  "type": "Feature",
  "properties": {
    "addr:full":"35 9th St SW Portage LA Prairie MB R1N 2N5",
    "addr:housenumber":"35",
    "addr:postcode":"r1n 2n5",
    "addr:street":"9Th St Sw",
    "iso:country":"CA",
    "sg:address":"35 9th St SW",
    "sg:city":"Portage LA Prairie",
    "sg:classifiers":[
        {
            "category":"Home & Garden",
            "subcategory":"Garden Supply",
            "type":"Retail Goods"
        }
    ],
    "sg:phone":"+1 204 239 6132",
    "sg:postcode":"R1N 2N5",
    "sg:province":"MB",
    "sg:tags":[
        "center",
        "landscape",
        "contractor"
    ],
    "wof:name":"Prairie Blossom Garden Ctr",
    "wof:placetype":"venue"
},
  "geometry": {"coordinates":[-98.30315400000001,49.972885],"type":"Point"}
}