{
  "type": "Feature",
  "properties": {
    "iso:country":"CA",
    "sg:address":"2835 Sunningdale Rd E",
    "sg:city":"London",
    "sg:classifiers":[
        {
            "category":"Sports & Exercise",
            "subcategory":"Golf",
            "type":"Entertainment"
        }
    ],
    "sg:phone":"+1 519 661 4435",
    "sg:postcode":"N5X 3Y7",
    "sg:province":"ON",
    "sg:tags":[
        "course"
    ],
    "wof:name":"Fanshawe Golf Course",
    "wof:placetype":"venue"
},
  "geometry": {"coordinates":[-81.195930481,43.0655555725],"type":"Point"}
}