{
  "type": "Feature",
  "properties": {
    "iso:country":"CA",
    "sg:city":"High Prairie",
    "sg:classifiers":[
        {
            "category":"Health Services",
            "subcategory":"Nursing And Care Facility",
            "type":"Services"
        }
    ],
    "sg:phone":"+1 780 523 6470",
    "sg:postcode":"T0G 1E0",
    "sg:province":"AB",
    "sg:tags":[
        "home",
        "convalescent"
    ],
    "wof:name":"J B Wood Nursing Home",
    "wof:placetype":"venue"
},
  "geometry": {"coordinates":[-116.483680725,55.4347381592],"type":"Point"}
}