{
  "type": "Feature",
  "properties": {
    "iso:country":"CA",
    "sg:address":"77 Wellington St E",
    "sg:city":"Aurora",
    "sg:classifiers":[
        {
            "category":"Real Estate",
            "subcategory":"Real Estate Agent",
            "type":"Services"
        }
    ],
    "sg:phone":"+1 905 727 0271",
    "sg:postcode":"L4G 1H7",
    "sg:province":"ON",
    "wof:name":"Marsland Real Estate",
    "wof:placetype":"venue"
},
  "geometry": {"coordinates":[-79.463028,44.000511],"type":"Point"}
}