{
  "type": "Feature",
  "properties": {
    "addr:full":"77 Wellington St E Aurora ON L4G 1H7",
    "addr:housenumber":"77",
    "addr:postcode":"l4g 1h7",
    "addr:street":"Wellington St E",
    "iso:country":"CA",
    "sg:address":"77 Wellington St E",
    "sg:city":"Aurora",
    "sg:classifiers":[
        {
            "category":"Real Estate",
            "subcategory":"Real Estate Agent",
            "type":"Services"
        }
    ],
    "sg:phone":"+1 905 727 0271",
    "sg:postcode":"L4G 1H7",
    "sg:province":"ON",
    "wof:name":"Marsland Real Estate",
    "wof:placetype":"venue"
},
  "geometry": {"coordinates":[-79.46302799999999,44.000511],"type":"Point"}
}