{
  "type": "Feature",
  "properties": {
    "iso:country":"CA",
    "sg:address":"2021 Av Union #1150",
    "sg:city":"Montreal",
    "sg:classifiers":[
        {
            "category":"Insurance",
            "subcategory":"Insurance Agent",
            "type":"Services"
        }
    ],
    "sg:phone":"+1 514 284 9350",
    "sg:postcode":"H3A 2S9",
    "sg:province":"QC",
    "wof:name":"Jevco Insurance CO",
    "wof:placetype":"venue"
},
  "geometry": {"coordinates":[-73.571304,45.50494],"type":"Point"}
}