{
  "type": "Feature",
  "properties": {
    "addr:full":"350 Queensway Prince George BC V2L 5C3",
    "addr:housenumber":"350",
    "addr:postcode":"v2l 5c3",
    "addr:street":"Queensway",
    "iso:country":"CA",
    "sg:address":"350 Queensway",
    "sg:city":"Prince George",
    "sg:classifiers":[
        {
            "category":"Retail",
            "subcategory":"Repair Shop",
            "type":"Services"
        }
    ],
    "sg:phone":"+1 250 564 5462",
    "sg:postcode":"V2L 5C3",
    "sg:province":"BC",
    "sg:tags":[
        "range",
        "appliance"
    ],
    "wof:name":"Moore Appliance Repairs",
    "wof:placetype":"venue"
},
  "geometry": {"coordinates":[-122.74105835,53.9151382446],"type":"Point"}
}