{
  "type": "Feature",
  "properties": {
    "addr:full":"3791 Gibbins Rd Duncan BC V9L 6E8",
    "addr:housenumber":"3791",
    "addr:postcode":"v9l 6e8",
    "addr:street":"Gibbins Rd",
    "iso:country":"CA",
    "sg:address":"3791 Gibbins Rd",
    "sg:city":"Duncan",
    "sg:classifiers":[
        {
            "category":"Professional",
            "subcategory":"Accounting & Tax Preparation",
            "type":"Services"
        }
    ],
    "sg:phone":"+1 250 748 7777",
    "sg:postcode":"V9L 6E8",
    "sg:province":"BC",
    "sg:tags":[
        "accountant"
    ],
    "wof:name":"Cowichan Accounting",
    "wof:placetype":"venue"
},
  "geometry": {"coordinates":[-123.70738220200001,48.779094696],"type":"Point"}
}