{
  "type": "Feature",
  "properties": {
    "addr:full":"6 Rue DE L'Eveche E Rimouski QC G5L 1X4",
    "addr:housenumber":"6",
    "addr:postcode":"g5l 1x4",
    "addr:street":"Rue De L'Eveche E",
    "iso:country":"CA",
    "sg:address":"6 Rue DE L'Eveche E",
    "sg:city":"Rimouski",
    "sg:classifiers":[
        {
            "category":"Shopping",
            "subcategory":"Used Merchandise",
            "type":"Retail Goods"
        }
    ],
    "sg:phone":"+1 418 721 4444",
    "sg:postcode":"G5L 1X4",
    "sg:province":"QC",
    "sg:tags":[
        "flea",
        "market"
    ],
    "wof:name":"Achetons-Vendons",
    "wof:placetype":"venue"
},
  "geometry": {"coordinates":[-68.5217056274,48.4502677917],"type":"Point"}
}