{
  "type": "Feature",
  "properties": {
    "addr:full":"253 Woodlawn Rd W Guelph ON N1H 8J1",
    "addr:housenumber":"253",
    "addr:postcode":"n1h 8j1",
    "addr:street":"Woodlawn Rd W",
    "iso:country":"CA",
    "sg:address":"253 Woodlawn Rd W",
    "sg:city":"Guelph",
    "sg:classifiers":[
        {
            "category":"Shopping",
            "subcategory":"Bicycles & Sporting Goods",
            "type":"Retail Goods"
        }
    ],
    "sg:phone":"+1 519 767 6046",
    "sg:postcode":"N1H 8J1",
    "sg:province":"ON",
    "sg:tags":[
        "apparel",
        "bowling",
        "accessory"
    ],
    "wof:name":"J & B Pro Sports",
    "wof:placetype":"venue"
},
  "geometry": {"coordinates":[-80.29505899999999,43.552475],"type":"Point"}
}