{
  "type": "Feature",
  "properties": {
    "addr:full":"18 Parker Dr Simcoe ON N3Y 1A1",
    "addr:housenumber":"18",
    "addr:postcode":"n3y 1a1",
    "addr:street":"Parker Dr",
    "iso:country":"CA",
    "sg:address":"18 Parker Dr",
    "sg:city":"Simcoe",
    "sg:classifiers":[
        {
            "category":"Education",
            "subcategory":"School",
            "type":"Public Place"
        }
    ],
    "sg:phone":"+1 519 426 0688",
    "sg:postcode":"N3Y 1A1",
    "sg:province":"ON",
    "wof:name":"West Lynn Public School",
    "wof:placetype":"venue"
},
  "geometry": {"coordinates":[-80.2996292114,42.8210983276],"type":"Point"}
}