{
  "type": "Feature",
  "properties": {
    "addr:full":"2233 Stanley Ave Niagara Falls ON L2E 6S4",
    "addr:housenumber":"2233",
    "addr:postcode":"l2e 6s4",
    "addr:street":"Stanley Ave",
    "iso:country":"CA",
    "sg:address":"2233 Stanley Ave",
    "sg:city":"Niagara Falls",
    "sg:classifiers":[
        {
            "category":"Building & Trades",
            "subcategory":"Construction",
            "type":"Services"
        }
    ],
    "sg:phone":"+1 905 262 5492",
    "sg:postcode":"L2E 6S4",
    "sg:province":"ON",
    "sg:tags":[
        "contractor",
        "general"
    ],
    "wof:name":"Niacon Limited Construction CO",
    "wof:placetype":"venue"
},
  "geometry": {"coordinates":[-79.08740234379999,43.1396484375],"type":"Point"}
}