{
  "type": "Feature",
  "properties": {
    "addr:full":"63 High St W Moose Jaw SK S6H 1S4",
    "addr:housenumber":"63",
    "addr:postcode":"s6h 1s4",
    "addr:street":"High St W",
    "iso:country":"CA",
    "sg:address":"63 High St W",
    "sg:city":"Moose Jaw",
    "sg:classifiers":[
        {
            "category":"Shopping",
            "type":"Retail Goods"
        }
    ],
    "sg:phone":"+1 306 692 4644",
    "sg:postcode":"S6H 1S4",
    "sg:province":"SK",
    "sg:tags":[
        "equipment",
        "wine",
        "supply"
    ],
    "wof:name":"Moose Jaw Wine Cellar",
    "wof:placetype":"venue"
},
  "geometry": {"coordinates":[-105.536277771,50.3914299011],"type":"Point"}
}