{
  "type": "Feature",
  "properties": {
    "addr:full":"1632 6th Ave W Vancouver BC V6J 1R3",
    "addr:housenumber":"1632",
    "addr:postcode":"v6j 1r3",
    "addr:street":"6Th Ave W",
    "iso:country":"CA",
    "sg:address":"1632 6th Ave W",
    "sg:city":"Vancouver",
    "sg:classifiers":[
        {
            "category":"Professional",
            "subcategory":"Detective & Security Services",
            "type":"Services"
        }
    ],
    "sg:phone":"+1 604 886 9116",
    "sg:postcode":"V6J 1R3",
    "sg:province":"BC",
    "sg:tags":[
        "system"
    ],
    "wof:name":"Peninsula Alarm Systems Ltd",
    "wof:placetype":"venue"
},
  "geometry": {"coordinates":[-123.141762,49.266109],"type":"Point"}
}