{
  "type": "Feature",
  "properties": {
    "iso:country":"CA",
    "sg:address":"400 Manitoba St",
    "sg:city":"Bracebridge",
    "sg:classifiers":[
        {
            "category":"Travel",
            "subcategory":"Hotels & Motels",
            "type":"Entertainment"
        }
    ],
    "sg:phone":"+1 705 645 8755",
    "sg:postcode":"P1L 2C6",
    "sg:province":"ON",
    "wof:name":"Lofty Pines Motel",
    "wof:placetype":"venue"
},
  "geometry": {"coordinates":[-79.3237609863,45.0498313904],"type":"Point"}
}