{
  "type": "Feature",
  "properties": {
    "addr:full":"1029 Queen St E Toronto ON M4M 1K3",
    "addr:housenumber":"1029",
    "addr:postcode":"m4m 1k3",
    "addr:street":"Queen St E",
    "iso:country":"CA",
    "sg:address":"1029 Queen St E",
    "sg:city":"Toronto",
    "sg:classifiers":[
        {
            "category":"Professional",
            "subcategory":"Engineering",
            "type":"Services"
        }
    ],
    "sg:phone":"+1 416 778 6553",
    "sg:postcode":"M4M 1K3",
    "sg:province":"ON",
    "sg:tags":[
        "engineer"
    ],
    "wof:name":"G & M Technical Svc",
    "wof:placetype":"venue"
},
  "geometry": {"coordinates":[-79.33710499999999,43.661587],"type":"Point"}
}