{
  "type": "Feature",
  "properties": {
    "addr:full":"L'Ancienne-Lorette QC G2E 2Z3",
    "addr:postcode":"g2e 2z3",
    "iso:country":"CA",
    "sg:city":"L'Ancienne-Lorette",
    "sg:classifiers":[
        {
            "category":"Retail",
            "subcategory":"Repair Shop",
            "type":"Services"
        }
    ],
    "sg:phone":"+1 418 871 2424",
    "sg:postcode":"G2E 2Z3",
    "sg:province":"QC",
    "sg:tags":[
        "lock",
        "locksmith"
    ],
    "wof:name":"Serrurier 24 Sur 24 al Enr",
    "wof:placetype":"venue"
},
  "geometry": {"coordinates":[-71.3527832031,46.7974205017],"type":"Point"}
}