{
  "type": "Feature",
  "properties": {
    "addr:full":"1124 Boul Sainte-Foy Longueuil QC J4K 1W8",
    "addr:housenumber":"1124",
    "addr:postcode":"j4k 1w8",
    "addr:street":"Boul Sainte-Foy",
    "iso:country":"CA",
    "sg:address":"1124 Boul Sainte-Foy",
    "sg:city":"Longueuil",
    "sg:classifiers":[
        {
            "category":"Social Services",
            "type":"Services"
        }
    ],
    "sg:phone":"+1 450 679 0270",
    "sg:postcode":"J4K 1W8",
    "sg:province":"QC",
    "sg:tags":[
        "organization",
        "welfare"
    ],
    "wof:name":"Centres Jeunesse-LA Monteregie",
    "wof:placetype":"venue"
},
  "geometry": {"coordinates":[-73.49737548829999,45.5179023743],"type":"Point"}
}