{
  "type": "Feature",
  "properties": {
    "addr:full":"2072 Riverside Dr E Windsor ON N8Y 4S5",
    "addr:housenumber":"2072",
    "addr:postcode":"n8y 4s5",
    "addr:street":"Riverside Dr E",
    "iso:country":"CA",
    "sg:address":"2072 Riverside Dr E",
    "sg:city":"Windsor",
    "sg:classifiers":[
        {
            "category":"Manufacturing",
            "subcategory":"Food",
            "type":"Manufacturing & Wholesale Goods"
        }
    ],
    "sg:phone":"+1 519 254 5171",
    "sg:postcode":"N8Y 4S5",
    "sg:province":"ON",
    "sg:tags":[
        "distiller"
    ],
    "wof:name":"Hiram Walker & Sons Ltd",
    "wof:placetype":"venue"
},
  "geometry": {"coordinates":[-83.01252746580001,42.3259963989],"type":"Point"}
}