{
  "type": "Feature",
  "properties": {
    "addr:full":"Whitecourt AB T7S 1P1",
    "addr:postcode":"t7s 1p1",
    "iso:country":"CA",
    "sg:city":"Whitecourt",
    "sg:classifiers":[
        {
            "category":"Travel",
            "subcategory":"Hotels & Motels",
            "type":"Entertainment"
        }
    ],
    "sg:phone":"+1 780 778 2246",
    "sg:postcode":"T7S 1P1",
    "sg:province":"AB",
    "wof:name":"White-Kaps Motel",
    "wof:placetype":"venue"
},
  "geometry": {"coordinates":[-115.70787799999999,54.139435],"type":"Point"}
}