{
  "type": "Feature",
  "properties": {
    "iso:country":"CA",
    "sg:address":"385 Government Rd E",
    "sg:city":"Kapuskasing",
    "sg:classifiers":[
        {
            "category":"Manufacturing",
            "subcategory":"Tools & Machinery",
            "type":"Manufacturing & Wholesale Goods"
        }
    ],
    "sg:phone":"+1 705 335 6003",
    "sg:postcode":"P5N 2X7",
    "sg:province":"ON",
    "sg:tags":[
        "machine",
        "shop"
    ],
    "wof:name":"Kap Machine Shop & Welding Ltd",
    "wof:placetype":"venue"
},
  "geometry": {"coordinates":[-82.4198303223,49.4130516052],"type":"Point"}
}