{
  "type": "Feature",
  "properties": {
    "addr:full":"57 Cameron Rd SE Medicine Hat AB T1B 1J9",
    "addr:housenumber":"57",
    "addr:postcode":"t1b 1j9",
    "addr:street":"Cameron Rd Se",
    "iso:country":"CA",
    "sg:address":"57 Cameron Rd SE",
    "sg:city":"Medicine Hat",
    "sg:classifiers":[
        {
            "category":"Professional",
            "subcategory":"Accounting & Tax Preparation",
            "type":"Services"
        }
    ],
    "sg:phone":"+1 403 952 9112",
    "sg:postcode":"T1B 1J9",
    "sg:province":"AB",
    "sg:tags":[
        "bookkeeping",
        "general"
    ],
    "wof:name":"Christina Walcer Prof Bookkeep",
    "wof:placetype":"venue"
},
  "geometry": {"coordinates":[-110.640953064,50.0137252808],"type":"Point"}
}