{
  "type": "Feature",
  "properties": {
    "addr:full":"319 North Fraser Dr Quesnel BC V2J 1Y9",
    "addr:housenumber":"319",
    "addr:postcode":"v2j 1y9",
    "addr:street":"North Fraser Dr",
    "iso:country":"CA",
    "sg:address":"319 North Fraser Dr",
    "sg:city":"Quesnel",
    "sg:classifiers":[
        {
            "category":"Social Services",
            "type":"Services"
        }
    ],
    "sg:phone":"+1 250 992 8347",
    "sg:postcode":"V2J 1Y9",
    "sg:province":"BC",
    "sg:tags":[
        "organization",
        "welfare"
    ],
    "wof:name":"Quesnel Tillicum Society",
    "wof:placetype":"venue"
},
  "geometry": {"coordinates":[-122.502869,52.976555],"type":"Point"}
}