{
  "type": "Feature",
  "properties": {
    "addr:full":"9251 Yonge St #206 Richmond Hill ON L4C 9T3",
    "addr:housenumber":"9251;206",
    "addr:postcode":"l4c 9t3",
    "addr:street":"Yonge St #",
    "iso:country":"CA",
    "sg:address":"9251 Yonge St #206",
    "sg:city":"Richmond Hill",
    "sg:classifiers":[
        {
            "category":"Shopping",
            "subcategory":"Computers & Home Electronics",
            "type":"Retail Goods"
        }
    ],
    "sg:phone":"+1 905 709 9553",
    "sg:postcode":"L4C 9T3",
    "sg:province":"ON",
    "sg:tags":[
        "software"
    ],
    "wof:name":"Rayan Global Inc",
    "wof:placetype":"venue"
},
  "geometry": {"coordinates":[-79.43266300000001,43.852352],"type":"Point"}
}