{
  "type": "Feature",
  "properties": {
    "addr:full":"Woodbridge ON L4L 6E1",
    "addr:postcode":"l4l 6e1",
    "iso:country":"CA",
    "sg:city":"Woodbridge",
    "sg:classifiers":[
        {
            "category":"Wholesale",
            "subcategory":"Apparel",
            "type":"Manufacturing & Wholesale Goods"
        }
    ],
    "sg:phone":"+1 905 856 5289",
    "sg:postcode":"L4L 6E1",
    "sg:province":"ON",
    "sg:tags":[
        "sportswear"
    ],
    "wof:name":"Legacy Sportswear",
    "wof:placetype":"venue"
},
  "geometry": {"coordinates":[-79.5523986816,43.7850990295],"type":"Point"}
}