{
  "type": "Feature",
  "properties": {
    "addr:full":"2883 Broadway W Vancouver BC V6K 2G6",
    "addr:housenumber":"2883",
    "addr:postcode":"v6k 2g6",
    "addr:street":"Broadway W",
    "iso:country":"CA",
    "sg:address":"2883 Broadway W",
    "sg:city":"Vancouver",
    "sg:classifiers":[
        {
            "category":"Shopping",
            "subcategory":"News",
            "type":"Retail Goods"
        }
    ],
    "sg:phone":"+1 604 731 5180",
    "sg:postcode":"V6K 2G6",
    "sg:province":"BC",
    "sg:tags":[
        "magazine"
    ],
    "wof:name":"People's News & Magazines",
    "wof:placetype":"venue"
},
  "geometry": {"coordinates":[-123.169724,49.264183],"type":"Point"}
}