{
  "type": "Feature",
  "properties": {
    "iso:country":"CA",
    "sg:address":"499 Main St S # 168",
    "sg:city":"Brampton",
    "sg:classifiers":[
        {
            "category":"Home & Garden",
            "subcategory":"Home Furnishings",
            "type":"Retail Goods"
        }
    ],
    "sg:phone":"+1 905 457 2815",
    "sg:postcode":"L6Y 1N7",
    "sg:province":"ON",
    "sg:tags":[
        "linen"
    ],
    "wof:name":"Yeshne Bed & Bath",
    "wof:placetype":"venue"
},
  "geometry": {"coordinates":[-79.73579406739999,43.6675834656],"type":"Point"}
}