{
  "type": "Feature",
  "properties": {
    "addr:full":"103 Railway Ave W Arrowwood AB T0L 0B0",
    "addr:housenumber":"103",
    "addr:postcode":"t0l 0b0",
    "addr:street":"Railway Ave W Arrowwood",
    "iso:country":"CA",
    "sg:address":"103 Railway Ave W",
    "sg:city":"Arrowwood",
    "sg:classifiers":[
        {
            "category":"Shopping",
            "subcategory":"Hobbies, Toys, & Games",
            "type":"Retail Goods"
        }
    ],
    "sg:phone":"+1 403 534 0000",
    "sg:postcode":"T0L 0B0",
    "sg:province":"AB",
    "sg:tags":[
        "craft",
        "supply"
    ],
    "wof:name":"Oakes House",
    "wof:placetype":"venue"
},
  "geometry": {"coordinates":[-113.152733,50.737614],"type":"Point"}
}