{
  "type": "Feature",
  "properties": {
    "addr:full":"Banff AB T1L 1H1",
    "addr:postcode":"t1l 1h1",
    "iso:country":"CA",
    "sg:city":"Banff",
    "sg:classifiers":[
        {
            "category":"Professional",
            "subcategory":"Accounting & Tax Preparation",
            "type":"Services"
        }
    ],
    "sg:phone":"+1 403 762 8383",
    "sg:postcode":"T1L 1H1",
    "sg:province":"AB",
    "sg:tags":[
        "accountant"
    ],
    "wof:name":"Collins Barrow",
    "wof:placetype":"venue"
},
  "geometry": {"coordinates":[-115.570709228,51.1790313721],"type":"Point"}
}