{
  "type": "Feature",
  "properties": {
    "addr:full":"9608 Cameron St Burnaby BC V3J 1M2",
    "addr:housenumber":"9608",
    "addr:postcode":"v3j 1m2",
    "addr:street":"Cameron St",
    "iso:country":"CA",
    "sg:address":"9608 Cameron St",
    "sg:city":"Burnaby",
    "sg:classifiers":[
        {
            "category":"Banks & Credit Unions",
            "subcategory":"Bank",
            "type":"Services"
        }
    ],
    "sg:phone":"+1 604 421 3456",
    "sg:postcode":"V3J 1M2",
    "sg:province":"BC",
    "wof:name":"Greater Vancouver Comm Credit",
    "wof:placetype":"venue"
},
  "geometry": {"coordinates":[-122.89820899999999,49.253311],"type":"Point"}
}