{
  "type": "Feature",
  "properties": {
    "addr:full":"119 Brunswick St St George NB E5C 1A7",
    "addr:housenumber":"119",
    "addr:postcode":"e5c 1a7",
    "addr:street":"Brunswick St",
    "iso:country":"CA",
    "sg:address":"119 Brunswick St",
    "sg:city":"St George",
    "sg:classifiers":[
        {
            "category":"Retail",
            "subcategory":"Auto Repair",
            "type":"Services"
        }
    ],
    "sg:phone":"+1 506 755 3719",
    "sg:postcode":"E5C 1A7",
    "sg:province":"NB",
    "sg:tags":[
        "repairing",
        "automobile",
        "inspection"
    ],
    "wof:name":"Vance's Esso",
    "wof:placetype":"venue"
},
  "geometry": {"coordinates":[-66.830978,45.129318],"type":"Point"}
}