{
  "type": "Feature",
  "properties": {
    "addr:full":"1356 Weston Rd York ON M6M 4R8",
    "addr:housenumber":"1356",
    "addr:postcode":"m6m 4r8",
    "addr:street":"Weston Rd",
    "iso:country":"CA",
    "sg:address":"1356 Weston Rd",
    "sg:city":"York",
    "sg:classifiers":[
        {
            "category":"Restaurant",
            "type":"Food & Drink"
        }
    ],
    "sg:phone":"+1 416 245 3121",
    "sg:postcode":"M6M 4R8",
    "sg:province":"ON",
    "wof:name":"Fish Palace Restaurant",
    "wof:placetype":"venue"
},
  "geometry": {"coordinates":[-79.498878,43.690357],"type":"Point"}
}