{
  "type": "Feature",
  "properties": {
    "addr:full":"5991 Spring Garden Rd # 200 Halifax NS B3H 1Y6",
    "addr:housenumber":"5991",
    "addr:postcode":"b3h 1y6",
    "addr:street":"Spring Garden Rd # 200",
    "iso:country":"CA",
    "sg:address":"5991 Spring Garden Rd # 200",
    "sg:city":"Halifax",
    "sg:classifiers":[
        {
            "category":"Health Services",
            "subcategory":"Doctor",
            "type":"Services"
        }
    ],
    "sg:phone":"+1 902 423 7331",
    "sg:postcode":"B3H 1Y6",
    "sg:province":"NS",
    "sg:tags":[
        "dentist"
    ],
    "wof:name":"Paul Bourque Inc",
    "wof:placetype":"venue"
},
  "geometry": {"coordinates":[-63.5865364075,44.6405944824],"type":"Point"}
}