{
  "type": "Feature",
  "properties": {
    "addr:full":"301 Shirley St N Timmins ON P4R 1N5",
    "addr:housenumber":"301",
    "addr:postcode":"p4r 1n5",
    "addr:street":"Shirley St N",
    "iso:country":"CA",
    "sg:address":"301 Shirley St N",
    "sg:city":"Timmins",
    "sg:classifiers":[
        {
            "category":"Education",
            "subcategory":"School",
            "type":"Public Place"
        }
    ],
    "sg:phone":"+1 705 268 1333",
    "sg:postcode":"P4R 1N5",
    "sg:province":"ON",
    "wof:name":"Pavillon Renaissance",
    "wof:placetype":"venue"
},
  "geometry": {"coordinates":[-81.3786621094,48.4776916504],"type":"Point"}
}