{
  "type": "Feature",
  "properties": {
    "addr:full":"Montreal QC H2N 1E4",
    "addr:postcode":"h2n 1e4",
    "iso:country":"CA",
    "sg:city":"Montreal",
    "sg:classifiers":[
        {
            "category":"Manufacturing",
            "subcategory":"Apparel",
            "type":"Manufacturing & Wholesale Goods"
        }
    ],
    "sg:phone":"+1 514 387 6546",
    "sg:postcode":"H2N 1E4",
    "sg:province":"QC",
    "sg:tags":[
        "clothing"
    ],
    "wof:name":"Modes Red",
    "wof:placetype":"venue"
},
  "geometry": {"coordinates":[-73.65274047849999,45.5417327881],"type":"Point"}
}