{
  "type": "Feature",
  "properties": {
    "addr:full":"Barrhead AB T7N 1A3",
    "addr:postcode":"t7n 1a3",
    "iso:country":"CA",
    "sg:city":"Barrhead",
    "sg:classifiers":[
        {
            "category":"Insurance",
            "subcategory":"Insurance Agent",
            "type":"Services"
        }
    ],
    "sg:phone":"+1 780 674 2116",
    "sg:postcode":"T7N 1A3",
    "sg:province":"AB",
    "wof:name":"Stutchbury Insurance Inc",
    "wof:placetype":"venue"
},
  "geometry": {"coordinates":[-114.404022,54.120575],"type":"Point"}
}