{
  "type": "Feature",
  "properties": {
    "addr:full":"77 Mowat Ave Toronto ON M6K 3E3",
    "addr:housenumber":"77",
    "addr:postcode":"m6k 3e3",
    "addr:street":"Mowat Ave",
    "iso:country":"CA",
    "sg:address":"77 Mowat Ave",
    "sg:city":"Toronto",
    "sg:classifiers":[
        {
            "category":"Shopping",
            "subcategory":"Computers & Home Electronics",
            "type":"Retail Goods"
        }
    ],
    "sg:phone":"+1 416 538 0032",
    "sg:postcode":"M6K 3E3",
    "sg:province":"ON",
    "sg:tags":[
        "establishment",
        "software"
    ],
    "wof:name":"Adobe Systems Canada Inc",
    "wof:placetype":"venue"
},
  "geometry": {"coordinates":[-79.4255142212,43.6383743286],"type":"Point"}
}