{
  "type": "Feature",
  "properties": {
    "iso:country":"CA",
    "sg:address":"400 March Road",
    "sg:city":"Ottawa, ON",
    "sg:classifiers":[
        {
            "category":"Manufacturing",
            "subcategory":"Electronics",
            "type":"Manufacturing & Wholesale Goods"
        }
    ],
    "sg:postcode":"K2K 3H4",
    "sg:website":"http://www.enablence.com/",
    "wof:name":"Enablence Technologies",
    "wof:placetype":"venue"
},
  "geometry": {"coordinates":[-75.9124127,45.3393573],"type":"Point"}
}