{
  "type": "Feature",
  "properties": {
    "addr:full":"230 Hawker Rd Maple ON L6A 2R2",
    "addr:housenumber":"230",
    "addr:postcode":"l6a 2r2",
    "addr:street":"Hawker Rd",
    "iso:country":"CA",
    "sg:address":"230 Hawker Rd",
    "sg:city":"Maple",
    "sg:classifiers":[
        {
            "category":"Social Services",
            "subcategory":"Child Care",
            "type":"Services"
        }
    ],
    "sg:phone":"+1 905 303 2702",
    "sg:postcode":"L6A 2R2",
    "sg:province":"ON",
    "wof:name":"Maple Community of Child Care",
    "wof:placetype":"venue"
},
  "geometry": {"coordinates":[-79.52536000000001,43.843906],"type":"Point"}
}