{
  "type": "Feature",
  "properties": {
    "addr:full":"55 Morley St Hamilton ON L8H 3R8",
    "addr:housenumber":"55",
    "addr:postcode":"l8h 3r8",
    "addr:street":"Morley St",
    "iso:country":"CA",
    "sg:address":"55 Morley St",
    "sg:city":"Hamilton",
    "sg:classifiers":[
        {
            "category":"Building & Trades",
            "subcategory":"Construction",
            "type":"Services"
        }
    ],
    "sg:phone":"+1 905 547 5200",
    "sg:postcode":"L8H 3R8",
    "sg:province":"ON",
    "sg:tags":[
        "general",
        "contractor"
    ],
    "wof:name":"Barclay Constr Hamilton Ltd",
    "wof:placetype":"venue"
},
  "geometry": {"coordinates":[-79.782539,43.250458],"type":"Point"}
}