{
  "type": "Feature",
  "properties": {
    "addr:full":"2565 Portage Ave Winnipeg MB R3J 0P4",
    "addr:housenumber":"2565",
    "addr:postcode":"r3j 0p4",
    "addr:street":"Portage Ave",
    "iso:country":"CA",
    "sg:address":"2565 Portage Ave",
    "sg:city":"Winnipeg",
    "sg:classifiers":[
        {
            "category":"Banks & Credit Unions",
            "subcategory":"Bank",
            "type":"Services"
        }
    ],
    "sg:phone":"+1 204 958 8588",
    "sg:postcode":"R3J 0P4",
    "sg:province":"MB",
    "wof:name":"Assiniboine Credit Union",
    "wof:placetype":"venue"
},
  "geometry": {"coordinates":[-97.2632141113,49.8756752014],"type":"Point"}
}