{
  "type": "Feature",
  "properties": {
    "addr:full":"420 Rue Jean-Talon E Montreal QC H2R 1T5",
    "addr:housenumber":"420",
    "addr:postcode":"h2r 1t5",
    "addr:street":"Rue Jean-Talon E",
    "iso:country":"CA",
    "sg:address":"420 Rue Jean-Talon E",
    "sg:city":"Montreal",
    "sg:classifiers":[
        {
            "category":"Health Services",
            "subcategory":"Optometrist",
            "type":"Services"
        }
    ],
    "sg:phone":"+1 514 273 2222",
    "sg:postcode":"H2R 1T5",
    "sg:province":"QC",
    "wof:name":"Mazigi, Georges OD",
    "wof:placetype":"venue"
},
  "geometry": {"coordinates":[-73.61413574220001,45.5384292603],"type":"Point"}
}