{
  "type": "Feature",
  "properties": {
    "addr:full":"50 Everest St Hamilton ON L8W 2G9",
    "addr:housenumber":"50",
    "addr:postcode":"l8w 2g9",
    "addr:street":"Everest St",
    "iso:country":"CA",
    "sg:address":"50 Everest St",
    "sg:city":"Hamilton",
    "sg:classifiers":[
        {
            "category":"Building & Trades",
            "subcategory":"Cleaning & Sanitation",
            "type":"Services"
        }
    ],
    "sg:phone":"+1 905 388 8267",
    "sg:postcode":"L8W 2G9",
    "sg:province":"ON",
    "sg:tags":[
        "janitor"
    ],
    "wof:name":"Fantastic Building Cleaning CO",
    "wof:placetype":"venue"
},
  "geometry": {"coordinates":[-79.844658,43.191734],"type":"Point"}
}