{
  "type": "Feature",
  "properties": {
    "iso:country":"CA",
    "sg:address":"225 Montee DE Liesse",
    "sg:city":"Saint-Laurent",
    "sg:classifiers":[
        {
            "category":"Wholesale",
            "subcategory":"Electrical",
            "type":"Manufacturing & Wholesale Goods"
        }
    ],
    "sg:phone":"+1 514 738 2618",
    "sg:postcode":"H4T 1P5",
    "sg:province":"QC",
    "sg:tags":[
        "equipment",
        "electronic",
        "supply"
    ],
    "wof:name":"Microbrite Electric Sales Inc",
    "wof:placetype":"venue"
},
  "geometry": {"coordinates":[-73.703857,45.478268],"type":"Point"}
}