{
  "type": "Feature",
  "properties": {
    "addr:full":"Oakville ON L6L 5N9",
    "addr:postcode":"l6l 5n9",
    "iso:country":"CA",
    "sg:city":"Oakville",
    "sg:classifiers":[
        {
            "category":"Manufacturing",
            "subcategory":"Printing",
            "type":"Manufacturing & Wholesale Goods"
        }
    ],
    "sg:phone":"+1 905 825 2130",
    "sg:postcode":"L6L 5N9",
    "sg:province":"ON",
    "sg:tags":[
        "publisher"
    ],
    "wof:name":"Mosaic Press",
    "wof:placetype":"venue"
},
  "geometry": {"coordinates":[-79.7093200684,43.4266624451],"type":"Point"}
}