{
  "type": "Feature",
  "properties": {
    "addr:full":"2039 Drew St North Bay ON P1B 6R2",
    "addr:housenumber":"2039",
    "addr:postcode":"p1b 6r2",
    "addr:street":"Drew St",
    "iso:country":"CA",
    "sg:address":"2039 Drew St",
    "sg:city":"North Bay",
    "sg:classifiers":[
        {
            "category":"Freight",
            "type":"Transportation"
        }
    ],
    "sg:phone":"+1 705 474 8587",
    "sg:postcode":"P1B 6R2",
    "sg:province":"ON",
    "sg:tags":[
        "mover"
    ],
    "wof:name":"Richard's Delivery",
    "wof:placetype":"venue"
},
  "geometry": {"coordinates":[-79.445022583,46.318523407],"type":"Point"}
}