{
  "type": "Feature",
  "properties": {
    "addr:full":"Breslau ON N0B 1M0",
    "addr:postcode":"n0b 1m0",
    "iso:country":"CA",
    "sg:city":"Breslau",
    "sg:classifiers":[
        {
            "category":"Autos & Motor Vehicles",
            "subcategory":"Automobile Sales",
            "type":"Retail Goods"
        }
    ],
    "sg:phone":"+1 519 648 2921",
    "sg:postcode":"N0B 1M0",
    "sg:province":"ON",
    "sg:tags":[
        "equipment",
        "aircraft",
        "parts",
        "supply"
    ],
    "wof:name":"Kitchener Aero Avionics",
    "wof:placetype":"venue"
},
  "geometry": {"coordinates":[-80.386124,43.455811],"type":"Point"}
}