{
  "type": "Feature",
  "properties": {
    "addr:full":"247 Rue Dupont Pont-Rouge QC G3H 1P8",
    "addr:housenumber":"247",
    "addr:postcode":"g3h 1p8",
    "addr:street":"Rue Dupont",
    "iso:country":"CA",
    "sg:address":"247 Rue Dupont",
    "sg:city":"Pont-Rouge",
    "sg:classifiers":[
        {
            "category":"Retail",
            "subcategory":"Funeral Services",
            "type":"Services"
        }
    ],
    "sg:phone":"+1 418 873 2542",
    "sg:postcode":"G3H 1P8",
    "sg:province":"QC",
    "sg:tags":[
        "director"
    ],
    "wof:name":"Residence Funeraire C Charest",
    "wof:placetype":"venue"
},
  "geometry": {"coordinates":[-71.70032500000001,46.756283],"type":"Point"}
}