{
  "type": "Feature",
  "properties": {
    "addr:full":"440 Main St W Palmerston ON N0G 2P0",
    "addr:housenumber":"440",
    "addr:postcode":"n0g 2p0",
    "addr:street":"Main St W",
    "iso:country":"CA",
    "sg:address":"440 Main St W",
    "sg:city":"Palmerston",
    "sg:classifiers":[
        {
            "category":"Food & Beverages",
            "subcategory":"Liquor & Beverages",
            "type":"Retail Goods"
        }
    ],
    "sg:phone":"+1 519 343 2620",
    "sg:postcode":"N0G 2P0",
    "sg:province":"ON",
    "sg:tags":[
        "store"
    ],
    "wof:name":"Liquor Control Board of Ont",
    "wof:placetype":"venue"
},
  "geometry": {"coordinates":[-80.856918335,43.8331985474],"type":"Point"}
}