{
  "type": "Feature",
  "properties": {
    "addr:full":"Bowmanville ON L1C 1N1",
    "addr:postcode":"l1c 1n1",
    "iso:country":"CA",
    "sg:city":"Bowmanville",
    "sg:classifiers":[
        {
            "category":"Personal",
            "type":"Services"
        }
    ],
    "sg:phone":"+1 905 623 4884",
    "sg:postcode":"L1C 1N1",
    "sg:province":"ON",
    "sg:tags":[
        "therapist",
        "massage"
    ],
    "wof:name":"Natural Touch Therapies",
    "wof:placetype":"venue"
},
  "geometry": {"coordinates":[-78.687477,43.911671],"type":"Point"}
}