{
  "type": "Feature",
  "properties": {
    "addr:full":"1387 Cariboo Hwy Cache Creek BC V0K 1H0",
    "addr:housenumber":"1387",
    "addr:postcode":"v0k 1h0",
    "addr:street":"Cariboo Hwy",
    "iso:country":"CA",
    "sg:address":"1387 Cariboo Hwy",
    "sg:city":"Cache Creek",
    "sg:classifiers":[
        {
            "category":"Retail",
            "subcategory":"Repair Shop",
            "type":"Services"
        }
    ],
    "sg:phone":"+1 250 457 6566",
    "sg:postcode":"V0K 1H0",
    "sg:province":"BC",
    "sg:tags":[
        "welding"
    ],
    "wof:name":"B C Powerweld",
    "wof:placetype":"venue"
},
  "geometry": {"coordinates":[-121.325272,50.81036],"type":"Point"}
}