{
  "type": "Feature",
  "properties": {
    "addr:full":"2471 Mount Newton Cross Rd Saanichton BC V8M 2B7",
    "addr:housenumber":"2471",
    "addr:postcode":"v8m 2b7",
    "addr:street":"Mount Newton Cross Rd",
    "iso:country":"CA",
    "sg:address":"2471 Mount Newton Cross Rd",
    "sg:city":"Saanichton",
    "sg:classifiers":[
        {
            "category":"Autos & Motor Vehicles",
            "subcategory":"Fuel & Gas Station",
            "type":"Retail Goods"
        }
    ],
    "sg:phone":"+1 250 652 1153",
    "sg:postcode":"V8M 2B7",
    "sg:province":"BC",
    "sg:tags":[
        "oil"
    ],
    "wof:name":"Pat Bay Esso",
    "wof:placetype":"venue"
},
  "geometry": {"coordinates":[-123.416908264,48.5941696167],"type":"Point"}
}