{
  "type": "Feature",
  "properties": {
    "addr:full":"47 Water St S St Marys ON N4X 1C2",
    "addr:housenumber":"47",
    "addr:postcode":"n4x 1c2",
    "addr:street":"Water St S",
    "iso:country":"CA",
    "sg:address":"47 Water St S",
    "sg:city":"St Marys",
    "sg:classifiers":[
        {
            "category":"Insurance",
            "subcategory":"Insurance Agent",
            "type":"Services"
        }
    ],
    "sg:phone":"+1 519 284 3321",
    "sg:postcode":"N4X 1C2",
    "sg:province":"ON",
    "wof:name":"Stonetown Insurance",
    "wof:placetype":"venue"
},
  "geometry": {"coordinates":[-81.14312,43.258183],"type":"Point"}
}