{
  "type": "Feature",
  "properties": {
    "addr:full":"LA Crete AB T0H 2H0",
    "addr:postcode":"t0h 2h0",
    "iso:country":"CA",
    "sg:city":"LA Crete",
    "sg:classifiers":[
        {
            "category":"Social Services",
            "subcategory":"Child Care",
            "type":"Services"
        }
    ],
    "sg:phone":"+1 780 928 3323",
    "sg:postcode":"T0H 2H0",
    "sg:province":"AB",
    "sg:tags":[
        "kindergarten",
        "academic",
        "school",
        "montessori"
    ],
    "wof:name":"Brighter Future Society",
    "wof:placetype":"venue"
},
  "geometry": {"coordinates":[-116.40785200000001,58.195969],"type":"Point"}
}