{
  "type": "Feature",
  "properties": {
    "addr:full":"79 John Forsyth Rd Winnipeg MB R2N 1R3",
    "addr:housenumber":"79",
    "addr:postcode":"r2n 1r3",
    "addr:street":"John Forsyth Rd",
    "iso:country":"CA",
    "sg:address":"79 John Forsyth Rd",
    "sg:city":"Winnipeg",
    "sg:classifiers":[
        {
            "category":"Social Services",
            "subcategory":"Child Care",
            "type":"Services"
        }
    ],
    "sg:phone":"+1 204 256 4757",
    "sg:postcode":"R2N 1R3",
    "sg:province":"MB",
    "wof:name":"St Germain Day Care Inc",
    "wof:placetype":"venue"
},
  "geometry": {"coordinates":[-97.1008148193,49.8129959106],"type":"Point"}
}