{
  "type": "Feature",
  "properties": {
    "addr:full":"50 Rue Saint-Raphael LA Malbaie QC G5A 1X9",
    "addr:housenumber":"50",
    "addr:postcode":"g5a 1x9",
    "addr:street":"Rue Saint-Raphael",
    "iso:country":"CA",
    "sg:address":"50 Rue Saint-Raphael",
    "sg:city":"LA Malbaie",
    "sg:classifiers":[
        {
            "category":"Building & Trades",
            "subcategory":"Cleaning & Sanitation",
            "type":"Services"
        }
    ],
    "sg:phone":"+1 418 665 3847",
    "sg:postcode":"G5A 1X9",
    "sg:province":"QC",
    "sg:tags":[
        "fireplace",
        "chimney"
    ],
    "wof:name":"Ramoneurs Du Quebec Inc",
    "wof:placetype":"venue"
},
  "geometry": {"coordinates":[-70.119713,47.656551],"type":"Point"}
}