{
  "type": "Feature",
  "properties": {
    "addr:full":"250 Caribou St W Moose Jaw SK S6H 2J8",
    "addr:housenumber":"250",
    "addr:postcode":"s6h 2j8",
    "addr:street":"Caribou St W",
    "iso:country":"CA",
    "sg:address":"250 Caribou St W",
    "sg:city":"Moose Jaw",
    "sg:classifiers":[
        {
            "category":"Retail",
            "subcategory":"Auto Repair",
            "type":"Services"
        }
    ],
    "sg:phone":"+1 306 692 5545",
    "sg:postcode":"S6H 2J8",
    "sg:province":"SK",
    "sg:tags":[
        "body",
        "automobile",
        "painting"
    ],
    "wof:name":"Caribou Auto Body Ltd",
    "wof:placetype":"venue"
},
  "geometry": {"coordinates":[-105.54103088399999,50.3970184326],"type":"Point"}
}