{
  "type": "Feature",
  "properties": {
    "addr:full":"2184 Boul Sainte-Sophie Sainte-Sophie QC J5J 2P5",
    "addr:housenumber":"2184",
    "addr:postcode":"j5j 2p5",
    "addr:street":"Boul Sainte-Sophie",
    "iso:country":"CA",
    "sg:address":"2184 Boul Sainte-Sophie",
    "sg:city":"Sainte-Sophie",
    "sg:classifiers":[
        {
            "category":"Organizations",
            "subcategory":"Religious Organization",
            "type":"Services"
        }
    ],
    "sg:phone":"+1 450 565 1439",
    "sg:postcode":"J5J 2P5",
    "sg:province":"QC",
    "sg:tags":[
        "house",
        "retreat"
    ],
    "wof:name":"Villa Ste-Sophie Enr",
    "wof:placetype":"venue"
},
  "geometry": {"coordinates":[-73.89660644529999,45.8193588257],"type":"Point"}
}