{
  "type": "Feature",
  "properties": {
    "addr:full":"1202 Rue Frigon Shawinigan QC G9N 3Z4",
    "addr:housenumber":"1202",
    "addr:postcode":"g9n 3z4",
    "addr:street":"Rue Frigon",
    "iso:country":"CA",
    "sg:address":"1202 Rue Frigon",
    "sg:city":"Shawinigan",
    "sg:classifiers":[
        {
            "category":"Building & Trades",
            "subcategory":"Electrical",
            "type":"Services"
        }
    ],
    "sg:phone":"+1 819 539 5715",
    "sg:postcode":"G9N 3Z4",
    "sg:province":"QC",
    "sg:tags":[
        "electric",
        "contractor"
    ],
    "wof:name":"Shawinigan Electrique Inc",
    "wof:placetype":"venue"
},
  "geometry": {"coordinates":[-72.740891,46.558216],"type":"Point"}
}