{
  "type": "Feature",
  "properties": {
    "addr:full":"136 Rue Saint-Jacques Saint-Jacques QC J0K 2R0",
    "addr:housenumber":"136",
    "addr:postcode":"j0k 2r0",
    "addr:street":"Rue Saint-Jacques",
    "iso:country":"CA",
    "sg:address":"136 Rue Saint-Jacques",
    "sg:city":"Saint-Jacques",
    "sg:classifiers":[
        {
            "category":"Health Services",
            "subcategory":"Medical Lab",
            "type":"Services"
        }
    ],
    "sg:phone":"+1 450 839 3651",
    "sg:postcode":"J0K 2R0",
    "sg:province":"QC",
    "wof:name":"Berube, Marcel",
    "wof:placetype":"venue"
},
  "geometry": {"coordinates":[-73.572823,45.949837],"type":"Point"}
}