{
  "type": "Feature",
  "properties": {
    "iso:country":"CA",
    "sg:address":"5750 11 St SE",
    "sg:city":"Calgary",
    "sg:classifiers":[
        {
            "category":"Utilities",
            "subcategory":"Fuel Oil & Lpg",
            "type":"Services"
        }
    ],
    "sg:phone":"+1 403 243 7975",
    "sg:postcode":"T2H 2G1",
    "sg:province":"AB",
    "sg:tags":[
        "firewood"
    ],
    "wof:name":"Mc Kinnon Coal & Firewood",
    "wof:placetype":"venue"
},
  "geometry": {"coordinates":[-114.037048,51.004078],"type":"Point"}
}