{
  "type": "Feature",
  "properties": {
    "iso:country":"CA",
    "sg:city":"Windsor",
    "sg:classifiers":[
        {
            "category":"Insurance",
            "subcategory":"Insurance Agent",
            "type":"Services"
        }
    ],
    "sg:phone":"+1 902 798 3287",
    "sg:postcode":"B0N 2T0",
    "sg:province":"NS",
    "wof:name":"R A Gollan Insurance Svc",
    "wof:placetype":"venue"
},
  "geometry": {"coordinates":[-64.1289367676,44.9844474792],"type":"Point"}
}