{
  "type": "Feature",
  "properties": {
    "addr:full":"436 Rue Saint-Michel LA Tuque QC G9X 1C9",
    "addr:housenumber":"436",
    "addr:postcode":"g9x 1c9",
    "addr:street":"Rue Saint-Michel",
    "iso:country":"CA",
    "sg:address":"436 Rue Saint-Michel",
    "sg:city":"LA Tuque",
    "sg:classifiers":[
        {
            "category":"Manufacturing",
            "subcategory":"Metals",
            "type":"Manufacturing & Wholesale Goods"
        }
    ],
    "sg:phone":"+1 819 523 6131",
    "sg:postcode":"G9X 1C9",
    "sg:province":"QC",
    "sg:tags":[
        "energy",
        "electric",
        "solar",
        "contractor"
    ],
    "wof:name":"Melco Electrique Inc",
    "wof:placetype":"venue"
},
  "geometry": {"coordinates":[-72.77886199949999,47.4460983276],"type":"Point"}
}