{
  "type": "Feature",
  "properties": {
    "addr:full":"405 Enterprise Ave Kitimat BC V8C 2E3",
    "addr:housenumber":"405",
    "addr:postcode":"bc v8c 2e3",
    "addr:street":"Enterprise Ave",
    "iso:country":"CA",
    "sg:address":"405 Enterprise Ave",
    "sg:city":"Kitimat",
    "sg:classifiers":[
        {
            "category":"Autos & Motor Vehicles",
            "subcategory":"Automobile Sales",
            "type":"Retail Goods"
        }
    ],
    "sg:phone":"+1 250 632 6181",
    "sg:postcode":"V8C 2E3",
    "sg:province":"BC",
    "sg:tags":[
        "car",
        "dealer"
    ],
    "wof:name":"Snow Valley Ford Sales Ltd",
    "wof:placetype":"venue"
},
  "geometry": {"coordinates":[-128.68737793,54.0589065552],"type":"Point"}
}