{
  "type": "Feature",
  "properties": {
    "addr:full":"6591 Ch DE LA Cote-Des-Neiges Montreal QC H3S 2A5",
    "addr:postcode":"6591;h3s 2a5",
    "addr:street":"Ch De La Cote-Des-Neiges",
    "iso:country":"CA",
    "sg:address":"6591 Ch DE LA Cote-Des-Neiges",
    "sg:city":"Montreal",
    "sg:classifiers":[
        {
            "category":"Food & Beverages",
            "subcategory":"Bakery",
            "type":"Retail Goods"
        }
    ],
    "sg:phone":"+1 514 733 2769",
    "sg:postcode":"H3S 2A5",
    "sg:province":"QC",
    "sg:tags":[
        "baker"
    ],
    "wof:name":"Cantor Bakeries",
    "wof:placetype":"venue"
},
  "geometry": {"coordinates":[-73.6354751587,45.502456665],"type":"Point"}
}