{
  "type": "Feature",
  "properties": {
    "addr:full":"43 Chelsey Cir Charlottetown PE C1E 1E9",
    "addr:housenumber":"43",
    "addr:postcode":"c1e 1e9",
    "addr:street":"Chelsey Cir",
    "iso:country":"CA",
    "sg:address":"43 Chelsey Cir",
    "sg:city":"Charlottetown",
    "sg:classifiers":[
        {
            "category":"Building & Trades",
            "subcategory":"Landscaping Services",
            "type":"Services"
        }
    ],
    "sg:phone":"+1 902 892 7571",
    "sg:postcode":"C1E 1E9",
    "sg:province":"PE",
    "sg:tags":[
        "landscape",
        "contractor"
    ],
    "wof:name":"Louis Smith Landscape Contr",
    "wof:placetype":"venue"
},
  "geometry": {"coordinates":[-63.166519165,46.2564125061],"type":"Point"}
}