{
  "type": "Feature",
  "properties": {
    "addr:full":"240 Main St N Minnedosa MB R0J 1E0",
    "addr:housenumber":"240",
    "addr:postcode":"r0j 1e0",
    "addr:street":"Main St N",
    "iso:country":"CA",
    "sg:address":"240 Main St N",
    "sg:city":"Minnedosa",
    "sg:classifiers":[
        {
            "category":"Travel",
            "subcategory":"Hotels & Motels",
            "type":"Entertainment"
        }
    ],
    "sg:phone":"+1 204 867 2729",
    "sg:postcode":"R0J 1E0",
    "sg:province":"MB",
    "wof:name":"Gateway Motel",
    "wof:placetype":"venue"
},
  "geometry": {"coordinates":[-99.8387832642,50.253868103],"type":"Point"}
}