{
  "type": "Feature",
  "properties": {
    "addr:full":"18 Souris Ave NW Weyburn SK S4H 3M7",
    "addr:housenumber":"18",
    "addr:postcode":"s4h 3m7",
    "addr:street":"Souris Ave Nw",
    "iso:country":"CA",
    "sg:address":"18 Souris Ave NW",
    "sg:city":"Weyburn",
    "sg:classifiers":[
        {
            "category":"Government",
            "subcategory":"Office",
            "type":"Public Place"
        }
    ],
    "sg:phone":"+1 306 848 2440",
    "sg:postcode":"S4H 3M7",
    "sg:province":"SK",
    "wof:name":"Saskatchewan Highways Equip",
    "wof:placetype":"venue"
},
  "geometry": {"coordinates":[-103.858940124,49.6620635986],"type":"Point"}
}