{
  "type": "Feature",
  "properties": {
    "addr:full":"550 5E Ave Barraute QC J0Y 1A0",
    "addr:housenumber":"550",
    "addr:postcode":"j0y 1a0",
    "addr:street":"5E Ave",
    "iso:country":"CA",
    "sg:address":"550 5E Ave",
    "sg:city":"Barraute",
    "sg:classifiers":[
        {
            "category":"Personal",
            "subcategory":"Beauty Salon",
            "type":"Services"
        }
    ],
    "sg:phone":"+1 819 734 6040",
    "sg:postcode":"J0Y 1A0",
    "sg:province":"QC",
    "wof:name":"Salon Creation",
    "wof:placetype":"venue"
},
  "geometry": {"coordinates":[-77.638245,48.435524],"type":"Point"}
}