{
  "type": "Feature",
  "properties": {
    "iso:country":"CA",
    "sg:city":"Edmonton",
    "sg:classifiers":[
        {
            "category":"Health Services",
            "subcategory":"Nursing And Care Facility",
            "type":"Services"
        }
    ],
    "sg:phone":"+1 780 482 8992",
    "sg:postcode":"T5K 0L4",
    "sg:province":"AB",
    "sg:tags":[
        "home",
        "convalescent",
        "homemaker"
    ],
    "wof:name":"Arms Association-Residences",
    "wof:placetype":"venue"
},
  "geometry": {"coordinates":[-113.512398,53.540829],"type":"Point"}
}