{
  "type": "Feature",
  "properties": {
    "iso:country":"CA",
    "sg:address":"236 Cumming St",
    "sg:city":"Thunder Bay",
    "sg:classifiers":[
        {
            "category":"Sports & Exercise",
            "subcategory":"Bowling",
            "type":"Entertainment"
        }
    ],
    "sg:phone":"+1 807 622 2515",
    "sg:postcode":"P7C 1N7",
    "sg:province":"ON",
    "sg:tags":[
        "item",
        "boutique",
        "center"
    ],
    "wof:name":"Superior Bowladrome",
    "wof:placetype":"venue"
},
  "geometry": {"coordinates":[-89.244286,48.387119],"type":"Point"}
}