{
  "type": "Feature",
  "properties": {
    "addr:full":"7804 Yellowhead Trail NW Edmonton AB T5B 1G3",
    "addr:housenumber":"7804",
    "addr:postcode":"t5b 1g3",
    "addr:street":"Yellowhead Trail Nw",
    "iso:country":"CA",
    "sg:address":"7804 Yellowhead Trail NW",
    "sg:city":"Edmonton",
    "sg:classifiers":[
        {
            "category":"Wholesale",
            "subcategory":"Construction Materials",
            "type":"Manufacturing & Wholesale Goods"
        }
    ],
    "sg:phone":"+1 780 474 5491",
    "sg:postcode":"T5B 1G3",
    "sg:province":"AB",
    "sg:tags":[
        "equipment",
        "roofing",
        "supply"
    ],
    "wof:name":"Roofmart Alberta Inc",
    "wof:placetype":"venue"
},
  "geometry": {"coordinates":[-113.460953,53.582748],"type":"Point"}
}