{
  "type": "Feature",
  "properties": {
    "addr:full":"536 Chebucto St Baddeck NS B0E 1B0",
    "addr:housenumber":"536",
    "addr:postcode":"b0e 1b0",
    "addr:street":"Chebucto St",
    "iso:country":"CA",
    "sg:address":"536 Chebucto St",
    "sg:city":"Baddeck",
    "sg:classifiers":[
        {
            "category":"Restaurant",
            "type":"Food & Drink"
        }
    ],
    "sg:phone":"+1 902 295 2581",
    "sg:postcode":"B0E 1B0",
    "sg:province":"NS",
    "wof:name":"Bell-Buoy Restaurant",
    "wof:placetype":"venue"
},
  "geometry": {"coordinates":[-60.7473602295,46.1009674072],"type":"Point"}
}