{
  "type": "Feature",
  "properties": {
    "addr:full":"112 Main St Milestone SK S0G 3L0",
    "addr:housenumber":"112",
    "addr:postcode":"s0g 3l0",
    "addr:street":"Main St",
    "iso:country":"CA",
    "sg:address":"112 Main St",
    "sg:city":"Milestone",
    "sg:classifiers":[
        {
            "category":"Education",
            "subcategory":"Library",
            "type":"Public Place"
        }
    ],
    "sg:phone":"+1 306 436 2112",
    "sg:postcode":"S0G 3L0",
    "sg:province":"SK",
    "wof:name":"Milestone Library",
    "wof:placetype":"venue"
},
  "geometry": {"coordinates":[-104.517501831,49.9923248291],"type":"Point"}
}