{
  "type": "Feature",
  "properties": {
    "addr:full":"121 Kaiser William Ave Langenburg SK S0A 2A0",
    "addr:housenumber":"121",
    "addr:postcode":"s0a 2a0",
    "addr:street":"Kaiser William Ave",
    "iso:country":"CA",
    "sg:address":"121 Kaiser William Ave",
    "sg:city":"Langenburg",
    "sg:classifiers":[
        {
            "category":"Retail",
            "subcategory":"Repair Shop",
            "type":"Services"
        }
    ],
    "sg:phone":"+1 306 743 2651",
    "sg:postcode":"S0A 2A0",
    "sg:province":"SK",
    "sg:tags":[
        "video",
        "disc",
        "cassette",
        "tape"
    ],
    "wof:name":"Gala Home Video",
    "wof:placetype":"venue"
},
  "geometry": {"coordinates":[-101.695168,50.840549],"type":"Point"}
}