{
  "type": "Feature",
  "properties": {
    "addr:full":"10208 101 Ave Lac LA Biche AB T0A 2C0",
    "addr:housenumber":"10208",
    "addr:postcode":"t0a 2c0",
    "addr:street":"101 Ave",
    "iso:country":"CA",
    "sg:address":"10208 101 Ave",
    "sg:city":"Lac LA Biche",
    "sg:classifiers":[
        {
            "category":"Shopping",
            "subcategory":"Used Merchandise",
            "type":"Retail Goods"
        }
    ],
    "sg:phone":"+1 780 623 3300",
    "sg:postcode":"T0A 2C0",
    "sg:province":"AB",
    "sg:tags":[
        "pawnbroker"
    ],
    "wof:name":"Royal Pawn",
    "wof:placetype":"venue"
},
  "geometry": {"coordinates":[-111.97699,54.770329],"type":"Point"}
}