{
  "type": "Feature",
  "properties": {
    "iso:country":"CA",
    "sg:address":"2615 Northwood Terr",
    "sg:city":"Halifax",
    "sg:classifiers":[
        {
            "category":"Health Services",
            "subcategory":"Doctor",
            "type":"Services"
        }
    ],
    "sg:phone":"+1 902 423 6141",
    "sg:postcode":"B3K 3S5",
    "sg:province":"NS",
    "sg:tags":[
        "physician",
        "surgeon"
    ],
    "wof:name":"Sommers, Jack MD",
    "wof:placetype":"venue"
},
  "geometry": {"coordinates":[-63.592163,44.657078],"type":"Point"}
}