{
  "type": "Feature",
  "properties": {
    "iso:country":"CA",
    "sg:address":"349 Rue DE Dorval",
    "sg:city":"Gatineau",
    "sg:classifiers":[
        {
            "category":"Professional",
            "subcategory":"Accounting & Tax Preparation",
            "type":"Services"
        }
    ],
    "sg:phone":"+1 819 663 3999",
    "sg:postcode":"J8P 3M4",
    "sg:province":"QC",
    "sg:tags":[
        "bookkeeping",
        "general"
    ],
    "wof:name":"Karam Bookeeping Svc Reg",
    "wof:placetype":"venue"
},
  "geometry": {"coordinates":[-75.6422119141,45.4883918762],"type":"Point"}
}