{
  "type": "Feature",
  "properties": {
    "addr:full":"Terrace Bay ON P0T 2W0",
    "addr:postcode":"p0t 2w0",
    "iso:country":"CA",
    "sg:city":"Terrace Bay",
    "sg:classifiers":[
        {
            "category":"Shopping",
            "subcategory":"Gifts & Souvenirs",
            "type":"Retail Goods"
        }
    ],
    "sg:phone":"+1 807 825 1041",
    "sg:postcode":"P0T 2W0",
    "sg:province":"ON",
    "sg:tags":[
        "shop"
    ],
    "wof:name":"Hummingbird Haus",
    "wof:placetype":"venue"
},
  "geometry": {"coordinates":[-87.1021652222,48.7823829651],"type":"Point"}
}