{
  "type": "Feature",
  "properties": {
    "addr:full":"1275 Burrows Ave Winnipeg MB R2X 0B8",
    "addr:housenumber":"1275",
    "addr:postcode":"r2x 0b8",
    "addr:street":"Burrows Ave",
    "iso:country":"CA",
    "sg:address":"1275 Burrows Ave",
    "sg:city":"Winnipeg",
    "sg:classifiers":[
        {
            "category":"Health Services",
            "subcategory":"Nursing And Care Facility",
            "type":"Services"
        }
    ],
    "sg:phone":"+1 204 586 8541",
    "sg:postcode":"R2X 0B8",
    "sg:province":"MB",
    "sg:tags":[
        "personal",
        "home",
        "retirement",
        "community"
    ],
    "wof:name":"Fred Douglas Lodge",
    "wof:placetype":"venue"
},
  "geometry": {"coordinates":[-97.175301,49.929081],"type":"Point"}
}