{
  "type": "Feature",
  "properties": {
    "addr:full":"1835 Rue Ontario E Montreal QC H2K 1T6",
    "addr:housenumber":"1835",
    "addr:postcode":"h2k 1t6",
    "addr:street":"Rue Ontario E",
    "iso:country":"CA",
    "sg:address":"1835 Rue Ontario E",
    "sg:city":"Montreal",
    "sg:classifiers":[
        {
            "category":"Personal",
            "subcategory":"Tattoo Parlor",
            "type":"Services"
        }
    ],
    "sg:phone":"+1 514 521 5855",
    "sg:postcode":"H2K 1T6",
    "sg:province":"QC",
    "sg:tags":[
        "tattooing"
    ],
    "wof:name":"Tattoo Time",
    "wof:placetype":"venue"
},
  "geometry": {"coordinates":[-73.5591506958,45.5264205933],"type":"Point"}
}