{
  "type": "Feature",
  "properties": {
    "addr:full":"1912 Rue Principale LA Conception QC J0T 1M0",
    "addr:housenumber":"1912",
    "addr:postcode":"j0t 1m0",
    "addr:street":"Rue Principale",
    "iso:country":"CA",
    "sg:address":"1912 Rue Principale",
    "sg:city":"LA Conception",
    "sg:classifiers":[
        {
            "category":"Manufacturing",
            "subcategory":"Metals",
            "type":"Manufacturing & Wholesale Goods"
        }
    ],
    "sg:phone":"+1 819 686 3920",
    "sg:postcode":"J0T 1M0",
    "sg:province":"QC",
    "sg:tags":[
        "solder"
    ],
    "wof:name":"Entreprises DE Soudure Denis",
    "wof:placetype":"venue"
},
  "geometry": {"coordinates":[-74.697746,46.15136],"type":"Point"}
}