{
  "type": "Feature",
  "properties": {
    "addr:full":"Calgary AB T2P 4R5",
    "addr:postcode":"t2p 4r5",
    "iso:country":"CA",
    "sg:city":"Calgary",
    "sg:classifiers":[
        {
            "category":"Restaurant",
            "type":"Food & Drink"
        }
    ],
    "sg:phone":"+1 403 233 7885",
    "sg:postcode":"T2P 4R5",
    "sg:province":"AB",
    "wof:name":"Prego Cucina Italiana",
    "wof:placetype":"venue"
},
  "geometry": {"coordinates":[-114.06905365,51.0527839661],"type":"Point"}
}