{
  "type": "Feature",
  "properties": {
    "addr:full":"58 Elliott Dr Sussex NB E4E 2K3",
    "addr:housenumber":"58",
    "addr:postcode":"e4e 2k3",
    "addr:street":"Elliott Dr",
    "iso:country":"CA",
    "sg:address":"58 Elliott Dr",
    "sg:city":"Sussex",
    "sg:classifiers":[
        {
            "category":"Social Services",
            "type":"Services"
        }
    ],
    "sg:phone":"+1 506 432 2604",
    "sg:postcode":"E4E 2K3",
    "sg:province":"NB",
    "sg:tags":[
        "organization",
        "welfare"
    ],
    "wof:name":"Community Youth Svc Orgnztn",
    "wof:placetype":"venue"
},
  "geometry": {"coordinates":[-65.501099,45.717262],"type":"Point"}
}