{
  "type": "Feature",
  "properties": {
    "addr:full":"2615 Lancaster Rd #31 Ottawa ON K1B 5N2",
    "addr:housenumber":"2615",
    "addr:postcode":"k1b 5n2",
    "addr:street":"Lancaster Rd # 31",
    "iso:country":"CA",
    "sg:address":"2615 Lancaster Rd #31",
    "sg:city":"Ottawa",
    "sg:classifiers":[
        {
            "category":"Health Services",
            "subcategory":"Chiropractor",
            "type":"Services"
        }
    ],
    "sg:phone":"+1 613 737 4742",
    "sg:postcode":"K1B 5N2",
    "sg:province":"ON",
    "wof:name":"Ottawa Sport & Health Clinic",
    "wof:placetype":"venue"
},
  "geometry": {"coordinates":[-75.6117935181,45.399433136],"type":"Point"}
}