{
  "type": "Feature",
  "properties": {
    "addr:full":"137 Rue Jean-Poirier Boucherville QC J4B 5X8",
    "addr:housenumber":"137",
    "addr:postcode":"j4b 5x8",
    "addr:street":"Rue Jean-Poirier",
    "iso:country":"CA",
    "sg:address":"137 Rue Jean-Poirier",
    "sg:city":"Boucherville",
    "sg:classifiers":[
        {
            "category":"Building & Trades",
            "subcategory":"Construction",
            "type":"Services"
        }
    ],
    "sg:phone":"+1 450 641 6704",
    "sg:postcode":"J4B 5X8",
    "sg:province":"QC",
    "sg:tags":[
        "graphic",
        "builder",
        "designer",
        "patio",
        "deck"
    ],
    "wof:name":"Inforgraphie Richard Jean Inc",
    "wof:placetype":"venue"
},
  "geometry": {"coordinates":[-73.441757,45.619987],"type":"Point"}
}