{
  "type": "Feature",
  "properties": {
    "addr:full":"Scarborough ON M1H 3B9",
    "addr:postcode":"m1h 3b9",
    "iso:country":"CA",
    "sg:city":"Scarborough",
    "sg:classifiers":[
        {
            "category":"Food & Beverages",
            "subcategory":"Specialty",
            "type":"Retail Goods"
        }
    ],
    "sg:phone":"+1 416 431 9099",
    "sg:postcode":"M1H 3B9",
    "sg:province":"ON",
    "sg:tags":[
        "health",
        "diet"
    ],
    "wof:name":"Organic Planet Inc",
    "wof:placetype":"venue"
},
  "geometry": {"coordinates":[-79.242508,43.77721],"type":"Point"}
}