{
  "type": "Feature",
  "properties": {
    "addr:full":"2507 Boul Des Recollets Trois-Rivieres QC G8Z 4G1",
    "addr:housenumber":"2507",
    "addr:postcode":"g8z 4g1",
    "addr:street":"Boul Des Recollets Trois-Rivieres",
    "iso:country":"CA",
    "sg:address":"2507 Boul Des Recollets",
    "sg:city":"Trois-Rivieres",
    "sg:classifiers":[
        {
            "category":"Retail",
            "subcategory":"Car Wash",
            "type":"Services"
        }
    ],
    "sg:phone":"+1 819 693 7288",
    "sg:postcode":"G8Z 4G1",
    "sg:province":"QC",
    "sg:tags":[
        "polishing",
        "washing"
    ],
    "wof:name":"Lave-Auto Autopropp",
    "wof:placetype":"venue"
},
  "geometry": {"coordinates":[-72.578468,46.337528],"type":"Point"}
}