{
  "type": "Feature",
  "properties": {
    "addr:full":"Mount Hope ON L0R 1W0",
    "addr:postcode":"l0r 1w0",
    "iso:country":"CA",
    "sg:city":"Mount Hope",
    "sg:classifiers":[
        {
            "category":"Building & Trades",
            "subcategory":"Equipment Rental",
            "type":"Services"
        }
    ],
    "sg:phone":"+1 905 679 2400",
    "sg:postcode":"L0R 1W0",
    "sg:province":"ON",
    "sg:tags":[
        "aircraft",
        "leasing",
        "charter"
    ],
    "wof:name":"Jetport",
    "wof:placetype":"venue"
},
  "geometry": {"coordinates":[-79.92841339109999,43.1596755981],"type":"Point"}
}