{
  "type": "Feature",
  "properties": {
    "addr:full":"2184 Av Du Mont-Royal E Montreal QC H2H 1K3",
    "addr:housenumber":"2184",
    "addr:postcode":"h2h 1k3",
    "addr:street":"Av Du Mont-Royal E",
    "iso:country":"CA",
    "sg:address":"2184 Av Du Mont-Royal E",
    "sg:city":"Montreal",
    "sg:classifiers":[
        {
            "category":"Personal",
            "subcategory":"Tanning Parlor",
            "type":"Services"
        }
    ],
    "sg:phone":"+1 514 527 3939",
    "sg:postcode":"H2H 1K3",
    "sg:province":"QC",
    "sg:tags":[
        "salon"
    ],
    "wof:name":"Sol DE Plata",
    "wof:placetype":"venue"
},
  "geometry": {"coordinates":[-73.571136,45.536396],"type":"Point"}
}