{
  "type": "Feature",
  "properties": {
    "addr:full":"23 Ch Haendel Candiac QC J5R 1R7",
    "addr:housenumber":"23",
    "addr:postcode":"j5r 1r7",
    "addr:street":"Ch Haendel",
    "iso:country":"CA",
    "sg:address":"23 Ch Haendel",
    "sg:city":"Candiac",
    "sg:classifiers":[
        {
            "category":"Real Estate",
            "subcategory":"Real Estate Agent",
            "type":"Services"
        }
    ],
    "sg:phone":"+1 450 635 1104",
    "sg:postcode":"J5R 1R7",
    "sg:province":"QC",
    "sg:tags":[
        "authorities",
        "housing"
    ],
    "wof:name":"Patrice Rioux Logements",
    "wof:placetype":"venue"
},
  "geometry": {"coordinates":[-73.51708984379999,45.391330719],"type":"Point"}
}