{
  "type": "Feature",
  "properties": {
    "addr:full":"6471 Kister Rd Niagara Falls ON L2E 6X8",
    "addr:housenumber":"6471",
    "addr:postcode":"l2e 6x8",
    "addr:street":"Kister Rd",
    "iso:country":"CA",
    "sg:address":"6471 Kister Rd",
    "sg:city":"Niagara Falls",
    "sg:classifiers":[
        {
            "category":"Health Services",
            "subcategory":"Medical Lab",
            "type":"Services"
        }
    ],
    "sg:phone":"+1 905 354 1130",
    "sg:postcode":"L2E 6X8",
    "sg:province":"ON",
    "sg:tags":[
        "control",
        "pain"
    ],
    "wof:name":"United Medical Systems",
    "wof:placetype":"venue"
},
  "geometry": {"coordinates":[-79.093521,43.052505],"type":"Point"}
}