{
  "type": "Feature",
  "properties": {
    "iso:country":"CA",
    "sg:address":"3600 Av Marien",
    "sg:city":"Montreal-Est",
    "sg:classifiers":[
        {
            "category":"Wholesale",
            "subcategory":"Auto Parts",
            "type":"Manufacturing & Wholesale Goods"
        }
    ],
    "sg:phone":"+1 514 645 9279",
    "sg:postcode":"H1B 4W3",
    "sg:province":"QC",
    "sg:tags":[
        "automobile",
        "rebuilt"
    ],
    "wof:name":"Pieces D'Auto Bon Svc Inc",
    "wof:placetype":"venue"
},
  "geometry": {"coordinates":[-73.52280426030001,45.6377754211],"type":"Point"}
}