{
  "type": "Feature",
  "properties": {
    "addr:full":"690 32nd St E Prince Albert SK S6V 2W8",
    "addr:housenumber":"690",
    "addr:postcode":"s6v 2w8",
    "addr:street":"32Nd St",
    "iso:country":"CA",
    "sg:address":"690 32nd St E",
    "sg:city":"Prince Albert",
    "sg:classifiers":[
        {
            "category":"Government",
            "subcategory":"Office",
            "type":"Public Place"
        }
    ],
    "sg:phone":"+1 306 764 5348",
    "sg:postcode":"S6V 2W8",
    "sg:province":"SK",
    "sg:tags":[
        "village"
    ],
    "wof:name":"Raider Hockey Club Enr",
    "wof:placetype":"venue"
},
  "geometry": {"coordinates":[-105.772308,53.184227],"type":"Point"}
}