{
  "type": "Feature",
  "properties": {
    "addr:full":"15 Greenwood St Saint John NB E2N 1E1",
    "addr:housenumber":"15",
    "addr:postcode":"e2n 1e1",
    "addr:street":"Greenwood St",
    "iso:country":"CA",
    "sg:address":"15 Greenwood St",
    "sg:city":"Saint John",
    "sg:classifiers":[
        {
            "category":"Building & Trades",
            "subcategory":"Cleaning & Sanitation",
            "type":"Services"
        }
    ],
    "sg:phone":"+1 506 696 7292",
    "sg:postcode":"E2N 1E1",
    "sg:province":"NB",
    "sg:tags":[
        "fireplace",
        "chimney"
    ],
    "wof:name":"Chim Chimney Sweeps",
    "wof:placetype":"venue"
},
  "geometry": {"coordinates":[-65.948639,45.318943],"type":"Point"}
}