{
  "type": "Feature",
  "properties": {
    "addr:full":"155 London Rd Sarnia ON N7T 4V4",
    "addr:housenumber":"155",
    "addr:postcode":"n7t 4v4",
    "addr:street":"London Rd",
    "iso:country":"CA",
    "sg:address":"155 London Rd",
    "sg:city":"Sarnia",
    "sg:classifiers":[
        {
            "category":"Retail",
            "subcategory":"Auto Repair",
            "type":"Services"
        }
    ],
    "sg:phone":"+1 519 336 6460",
    "sg:postcode":"N7T 4V4",
    "sg:province":"ON",
    "sg:tags":[
        "repairing",
        "automobile"
    ],
    "wof:name":"Cameron Service",
    "wof:placetype":"venue"
},
  "geometry": {"coordinates":[-82.404579,42.978741],"type":"Point"}
}