{
  "type": "Feature",
  "properties": {
    "addr:full":"221 Viger Saint-Epiphane QC G0L 2X0",
    "addr:housenumber":"221",
    "addr:postcode":"g0l 2x0",
    "addr:street":"Viger Saint-Epiphane",
    "iso:country":"CA",
    "sg:address":"221 Viger",
    "sg:city":"Saint-Epiphane",
    "sg:classifiers":[
        {
            "category":"Manufacturing",
            "subcategory":"Lumber",
            "type":"Manufacturing & Wholesale Goods"
        }
    ],
    "sg:phone":"+1 418 862 8756",
    "sg:postcode":"G0L 2X0",
    "sg:province":"QC",
    "sg:tags":[
        "sawmill"
    ],
    "wof:name":"Pelletier, Renaldo",
    "wof:placetype":"venue"
},
  "geometry": {"coordinates":[-69.332649231,47.896572113],"type":"Point"}
}