{
  "type": "Feature",
  "properties": {
    "addr:full":"38 King St W Dundas ON L9H 1T7",
    "addr:housenumber":"38",
    "addr:postcode":"l9h 1t7",
    "addr:street":"King St W",
    "iso:country":"CA",
    "sg:address":"38 King St W",
    "sg:city":"Dundas",
    "sg:classifiers":[
        {
            "category":"Health Services",
            "subcategory":"Podiatrist",
            "type":"Services"
        }
    ],
    "sg:phone":"+1 905 628 5118",
    "sg:postcode":"L9H 1T7",
    "sg:province":"ON",
    "wof:name":"Smith, Pauline DPM",
    "wof:placetype":"venue"
},
  "geometry": {"coordinates":[-79.9554824829,43.2661781311],"type":"Point"}
}