{
  "type": "Feature",
  "properties": {
    "addr:full":"181 W Morland St Fredericton NB E3B 1K1",
    "addr:housenumber":"181",
    "addr:postcode":"e3b 1k1",
    "addr:street":"W Morland St",
    "iso:country":"CA",
    "sg:address":"181 W Morland St",
    "sg:city":"Fredericton",
    "sg:classifiers":[
        {
            "category":"Education",
            "subcategory":"Special Training",
            "type":"Public Place"
        }
    ],
    "sg:phone":"+1 506 458 9101",
    "sg:postcode":"E3B 1K1",
    "sg:province":"NB",
    "sg:tags":[
        "instruction",
        "driving"
    ],
    "wof:name":"Young Drivers of Canada",
    "wof:placetype":"venue"
},
  "geometry": {"coordinates":[-66.639122,45.96064],"type":"Point"}
}