{
  "type": "Feature",
  "properties": {
    "addr:full":"11960 Boul DE L'Acadie Montreal QC H3M 2T7",
    "addr:housenumber":"11960",
    "addr:postcode":"h3m 2t7",
    "addr:street":"Boul De L'Acadie",
    "iso:country":"CA",
    "sg:address":"11960 Boul DE L'Acadie",
    "sg:city":"Montreal",
    "sg:classifiers":[
        {
            "category":"Education",
            "subcategory":"School",
            "type":"Public Place"
        }
    ],
    "sg:phone":"+1 514 334 0057",
    "sg:postcode":"H3M 2T7",
    "sg:province":"QC",
    "wof:name":"Ecole Augustin Roscelli",
    "wof:placetype":"venue"
},
  "geometry": {"coordinates":[-73.3577804565,45.3339691162],"type":"Point"}
}