{
  "type": "Feature",
  "properties": {
    "iso:country":"CA",
    "sg:address":"10 Duke St",
    "sg:city":"Truro",
    "sg:classifiers":[
        {
            "category":"Health Services",
            "subcategory":"Doctor",
            "type":"Services"
        }
    ],
    "sg:phone":"+1 902 895 4937",
    "sg:postcode":"B2N 2A1",
    "sg:province":"NS",
    "sg:tags":[
        "dentist"
    ],
    "wof:name":"Layton Dentistry Inc",
    "wof:placetype":"venue"
},
  "geometry": {"coordinates":[-63.2871665955,45.3635063171],"type":"Point"}
}