{
  "type": "Feature",
  "properties": {
    "addr:full":"Halifax NS B3J 3K1",
    "addr:postcode":"ns b3j 3k1",
    "iso:country":"CA",
    "sg:city":"Halifax",
    "sg:classifiers":[
        {
            "category":"Travel",
            "subcategory":"Travel Agent",
            "type":"Entertainment"
        }
    ],
    "sg:phone":"+1 902 425 5500",
    "sg:postcode":"B3J 3K1",
    "sg:province":"NS",
    "sg:tags":[
        "agency",
        "steamship"
    ],
    "wof:name":"Seabridge Intl Shipping Inc",
    "wof:placetype":"venue"
},
  "geometry": {"coordinates":[-63.5757331848,44.6501235962],"type":"Point"}
}