{
  "type": "Feature",
  "properties": {
    "addr:full":"1240 Bay St Toronto ON M5R 2A7",
    "addr:housenumber":"1240",
    "addr:postcode":"m5r 2a7",
    "addr:street":"Bay St",
    "iso:country":"CA",
    "sg:address":"1240 Bay St",
    "sg:city":"Toronto",
    "sg:classifiers":[
        {
            "category":"Shopping",
            "subcategory":"Clothing, Apparel, & Fashions",
            "type":"Retail Goods"
        }
    ],
    "sg:phone":"+1 416 968 1096",
    "sg:postcode":"M5R 2A7",
    "sg:province":"ON",
    "sg:tags":[
        "dressmaker",
        "tailor"
    ],
    "wof:name":"Lucille Boutique",
    "wof:placetype":"venue"
},
  "geometry": {"coordinates":[-79.389893,43.670403],"type":"Point"}
}