{
  "type": "Feature",
  "properties": {
    "iso:country":"CA",
    "sg:address":"2354 Millstream Rd",
    "sg:city":"Victoria",
    "sg:classifiers":[
        {
            "category":"Freight",
            "type":"Transportation"
        }
    ],
    "sg:phone":"+1 250 478 6534",
    "sg:postcode":"V9B 3R3",
    "sg:province":"BC",
    "sg:tags":[
        "commercial",
        "storage"
    ],
    "wof:name":"Millstream Mini Storage",
    "wof:placetype":"venue"
},
  "geometry": {"coordinates":[-123.364517212,48.428314209],"type":"Point"}
}