{
  "type": "Feature",
  "properties": {
    "iso:country":"CA",
    "sg:address":"5771 Rue DE Marseille",
    "sg:city":"Montreal",
    "sg:classifiers":[
        {
            "category":"Home & Garden",
            "subcategory":"Hardware",
            "type":"Retail Goods"
        }
    ],
    "sg:phone":"+1 514 255 7472",
    "sg:postcode":"H1N 1K1",
    "sg:province":"QC",
    "wof:name":"Quincaillerie Paul Rivet Inc",
    "wof:placetype":"venue"
},
  "geometry": {"coordinates":[-73.543633,45.572823],"type":"Point"}
}