{
  "type": "Feature",
  "properties": {
    "addr:full":"1793 Portage Ave Winnipeg MB R3J 0E8",
    "addr:housenumber":"1793",
    "addr:postcode":"r3j 0e8",
    "addr:street":"Portage Ave",
    "iso:country":"CA",
    "sg:address":"1793 Portage Ave",
    "sg:city":"Winnipeg",
    "sg:classifiers":[
        {
            "category":"Retail",
            "subcategory":"Animal Services",
            "type":"Services"
        }
    ],
    "sg:phone":"+1 204 888 2266",
    "sg:postcode":"R3J 0E8",
    "sg:province":"MB",
    "sg:tags":[
        "shelter",
        "pet",
        "shop"
    ],
    "wof:name":"D'Arcy's Arc",
    "wof:placetype":"venue"
},
  "geometry": {"coordinates":[-97.212563,49.878948],"type":"Point"}
}