{
  "type": "Feature",
  "properties": {
    "addr:full":"19 Briggs Ave Nepean ON K2E 6W5",
    "addr:housenumber":"19",
    "addr:postcode":"k2e 6w5",
    "addr:street":"Briggs Ave",
    "iso:country":"CA",
    "sg:address":"19 Briggs Ave",
    "sg:city":"Nepean",
    "sg:classifiers":[
        {
            "category":"Organizations",
            "subcategory":"Religious Organization",
            "type":"Services"
        }
    ],
    "sg:phone":"+1 613 226 4427",
    "sg:postcode":"K2E 6W5",
    "sg:province":"ON",
    "sg:tags":[
        "church"
    ],
    "wof:name":"Iglesia Ni Christo",
    "wof:placetype":"venue"
},
  "geometry": {"coordinates":[-75.714539,45.324192],"type":"Point"}
}