{
  "type": "Feature",
  "properties": {
    "addr:full":"623 Aylmer Cres Kingston ON K7M 6K3",
    "addr:housenumber":"623",
    "addr:postcode":"k7m 6k3",
    "addr:street":"Aylmer Cres",
    "iso:country":"CA",
    "sg:address":"623 Aylmer Cres",
    "sg:city":"Kingston",
    "sg:classifiers":[
        {
            "category":"Personal",
            "subcategory":"Beauty Salon",
            "type":"Services"
        }
    ],
    "sg:phone":"+1 613 389 4147",
    "sg:postcode":"K7M 6K3",
    "sg:province":"ON",
    "wof:name":"Elisa's Hair Design",
    "wof:placetype":"venue"
},
  "geometry": {"coordinates":[-76.614777,44.242645],"type":"Point"}
}