{
  "type": "Feature",
  "properties": {
    "addr:full":"Etobicoke ON M9W 4P2",
    "addr:postcode":"m9w 4p2",
    "iso:country":"CA",
    "sg:city":"Etobicoke",
    "sg:classifiers":[
        {
            "category":"Autos & Motor Vehicles",
            "subcategory":"Automobile Sales",
            "type":"Retail Goods"
        }
    ],
    "sg:phone":"+1 416 747 9500",
    "sg:postcode":"M9W 4P2",
    "sg:province":"ON",
    "sg:tags":[
        "car",
        "dealer"
    ],
    "wof:name":"Zicar",
    "wof:placetype":"venue"
},
  "geometry": {"coordinates":[-79.574944,43.721066],"type":"Point"}
}