{
  "type": "Feature",
  "properties": {
    "iso:country":"CA",
    "sg:address":"9791 Buchanan Rd",
    "sg:city":"Coldstream",
    "sg:classifiers":[
        {
            "category":"Building & Trades",
            "subcategory":"Equipment Rental",
            "type":"Services"
        }
    ],
    "sg:phone":"+1 250 545 8020",
    "sg:postcode":"V1B 2X1",
    "sg:province":"BC",
    "sg:tags":[
        "crane"
    ],
    "wof:name":"Armstrong Crane & Rigging Inc",
    "wof:placetype":"venue"
},
  "geometry": {"coordinates":[-119.228279114,50.241771698],"type":"Point"}
}