{
  "type": "Feature",
  "properties": {
    "addr:full":"5460 Av Westminster Cote Saint-Luc QC H4X 2A5",
    "addr:housenumber":"5460",
    "addr:postcode":"h4x 2a5",
    "addr:street":"Av Westminster Cote",
    "iso:country":"CA",
    "sg:address":"5460 Av Westminster",
    "sg:city":"Cote Saint-Luc",
    "sg:classifiers":[
        {
            "category":"Retail",
            "subcategory":"Laundry & Dry Cleaning",
            "type":"Services"
        }
    ],
    "sg:phone":"+1 514 486 1234",
    "sg:postcode":"H4X 2A5",
    "sg:province":"QC",
    "sg:tags":[
        "cleaners"
    ],
    "wof:name":"Elio Cleaners",
    "wof:placetype":"venue"
},
  "geometry": {"coordinates":[-73.6613616943,45.4589271545],"type":"Point"}
}