{
  "type": "Feature",
  "properties": {
    "addr:full":"3174 King George Hwy Surrey BC V4P 1A2",
    "addr:housenumber":"3174",
    "addr:postcode":"v4p 1a2",
    "addr:street":"King George Hwy",
    "iso:country":"CA",
    "sg:address":"3174 King George Hwy",
    "sg:city":"Surrey",
    "sg:classifiers":[
        {
            "category":"Autos & Motor Vehicles",
            "subcategory":"Automobile Sales",
            "type":"Retail Goods"
        }
    ],
    "sg:phone":"+1 604 531 2916",
    "sg:postcode":"V4P 1A2",
    "sg:province":"BC",
    "sg:tags":[
        "car",
        "dealer"
    ],
    "wof:name":"Peace Arch Toyota",
    "wof:placetype":"venue"
},
  "geometry": {"coordinates":[-122.81075300000001,49.059666],"type":"Point"}
}