{
  "type": "Feature",
  "properties": {
    "iso:country":"CA",
    "sg:address":"18131 114 Ave NW",
    "sg:city":"Edmonton",
    "sg:classifiers":[
        {
            "category":"Wholesale",
            "subcategory":"Machinery & Supplies",
            "type":"Manufacturing & Wholesale Goods"
        }
    ],
    "sg:phone":"+1 780 486 6111",
    "sg:postcode":"T5S 1T8",
    "sg:province":"AB",
    "sg:tags":[
        "concrete",
        "equipment"
    ],
    "wof:name":"Sika Canada Inc",
    "wof:placetype":"venue"
},
  "geometry": {"coordinates":[-113.633850098,53.562953949],"type":"Point"}
}