{
  "type": "Feature",
  "properties": {
    "iso:country":"CA",
    "sg:address":"7730 18E Av",
    "sg:city":"Montreal",
    "sg:classifiers":[
        {
            "category":"Shopping",
            "subcategory":"Bicycles & Sporting Goods",
            "type":"Retail Goods"
        }
    ],
    "sg:phone":"+1 514 725 4735",
    "sg:postcode":"H2A 2N6",
    "sg:province":"QC",
    "sg:tags":[
        "horse",
        "furnishing"
    ],
    "wof:name":"Brodeur Sulky & Harness Mfg",
    "wof:placetype":"venue"
},
  "geometry": {"coordinates":[-73.600967,45.56699],"type":"Point"}
}