{
  "type": "Feature",
  "properties": {
    "addr:full":"15 Upton Rd Scarborough ON M1L 2C1",
    "addr:housenumber":"15",
    "addr:postcode":"m1l 2c1",
    "addr:street":"Upton Rd",
    "iso:country":"CA",
    "sg:address":"15 Upton Rd",
    "sg:city":"Scarborough",
    "sg:classifiers":[
        {
            "category":"Manufacturing",
            "subcategory":"Tools & Machinery",
            "type":"Manufacturing & Wholesale Goods"
        }
    ],
    "sg:phone":"+1 416 750 7726",
    "sg:postcode":"M1L 2C1",
    "sg:province":"ON",
    "sg:tags":[
        "die",
        "cutting"
    ],
    "wof:name":"Pam Inc",
    "wof:placetype":"venue"
},
  "geometry": {"coordinates":[-79.2824020386,43.7183570862],"type":"Point"}
}