{
  "type": "Feature",
  "properties": {
    "addr:full":"1890 20 Ave NE Salmon Arm BC V1E 2G3",
    "addr:housenumber":"1890",
    "addr:postcode":"v1e 2g3",
    "addr:street":"20 Ave Ne",
    "iso:country":"CA",
    "sg:address":"1890 20 Ave NE",
    "sg:city":"Salmon Arm",
    "sg:classifiers":[
        {
            "category":"Travel",
            "subcategory":"Hotels & Motels",
            "type":"Entertainment"
        }
    ],
    "sg:phone":"+1 250 833 1890",
    "sg:postcode":"V1E 2G3",
    "sg:province":"BC",
    "sg:tags":[
        "breakfast",
        "accommodation",
        "bed"
    ],
    "wof:name":"Tyn-Y-Coed B & B",
    "wof:placetype":"venue"
},
  "geometry": {"coordinates":[-119.262451,50.714283],"type":"Point"}
}