{
  "type": "Feature",
  "properties": {
    "addr:full":"22 King St Welland ON L3B 3H9",
    "addr:housenumber":"22",
    "addr:postcode":"l3b 3h9",
    "addr:street":"King St",
    "iso:country":"CA",
    "sg:address":"22 King St",
    "sg:city":"Welland",
    "sg:classifiers":[
        {
            "category":"Banks & Credit Unions",
            "subcategory":"Bank",
            "type":"Services"
        }
    ],
    "sg:phone":"+1 905 735 5653",
    "sg:postcode":"L3B 3H9",
    "sg:province":"ON",
    "wof:name":"Cibc",
    "wof:placetype":"venue"
},
  "geometry": {"coordinates":[-79.25052599999999,42.991253],"type":"Point"}
}