{
  "type": "Feature",
  "properties": {
    "addr:full":"990 Boul Saint-Jean Pointe-Claire QC H9R 5N9",
    "addr:housenumber":"990",
    "addr:postcode":"h9r 5n9",
    "addr:street":"Boul Saint-Jean",
    "iso:country":"CA",
    "sg:address":"990 Boul Saint-Jean",
    "sg:city":"Pointe-Claire",
    "sg:classifiers":[
        {
            "category":"Restaurant",
            "type":"Food & Drink"
        }
    ],
    "sg:phone":"+1 514 428 5550",
    "sg:postcode":"H9R 5N9",
    "sg:province":"QC",
    "sg:tags":[
        "shop",
        "coffee"
    ],
    "wof:name":"Second Cup",
    "wof:placetype":"venue"
},
  "geometry": {"coordinates":[-73.8314208984,45.4695625305],"type":"Point"}
}