{
  "type": "Feature",
  "properties": {
    "addr:full":"616 Main St Yarmouth NS B5A 1J9",
    "addr:housenumber":"616",
    "addr:postcode":"b5a 1j9",
    "addr:street":"Main St",
    "iso:country":"CA",
    "sg:address":"616 Main St",
    "sg:city":"Yarmouth",
    "sg:classifiers":[
        {
            "category":"Personal",
            "subcategory":"Beauty Salon",
            "type":"Services"
        }
    ],
    "sg:phone":"+1 902 742 7300",
    "sg:postcode":"B5A 1J9",
    "sg:province":"NS",
    "wof:name":"Salon 215",
    "wof:placetype":"venue"
},
  "geometry": {"coordinates":[-66.1141204834,43.8522033691],"type":"Point"}
}