{
  "type": "Feature",
  "properties": {
    "addr:full":"Trois-Rivieres-Ouest QC G9A 4N2",
    "addr:postcode":"g9a 4n2",
    "iso:country":"CA",
    "sg:city":"Trois-Rivieres-Ouest",
    "sg:classifiers":[
        {
            "category":"Restaurant",
            "type":"Food & Drink"
        }
    ],
    "sg:phone":"+1 819 694 7550",
    "sg:postcode":"G9A 4N2",
    "sg:province":"QC",
    "sg:tags":[
        "parlor",
        "ice",
        "cream"
    ],
    "wof:name":"Cremiere",
    "wof:placetype":"venue"
},
  "geometry": {"coordinates":[-72.56488,46.324368],"type":"Point"}
}