{
  "type": "Feature",
  "properties": {
    "addr:full":"Vancouver BC V6G 2A9",
    "addr:postcode":"v6g 2a9",
    "iso:country":"CA",
    "sg:city":"Vancouver",
    "sg:classifiers":[
        {
            "category":"Professional",
            "subcategory":"Computer Services",
            "type":"Services"
        }
    ],
    "sg:phone":"+1 604 682 4144",
    "sg:postcode":"V6G 2A9",
    "sg:province":"BC",
    "sg:tags":[
        "consultant",
        "designer"
    ],
    "wof:name":"Syndercom-Edi",
    "wof:placetype":"venue"
},
  "geometry": {"coordinates":[-123.134742737,49.2849617004],"type":"Point"}
}