{
  "type": "Feature",
  "properties": {
    "iso:country":"CA",
    "sg:city":"Markham",
    "sg:classifiers":[
        {
            "category":"Retail",
            "subcategory":"Auto Repair",
            "type":"Services"
        }
    ],
    "sg:phone":"+1 905 471 8473",
    "sg:postcode":"L3P 1W5",
    "sg:province":"ON",
    "sg:tags":[
        "repairing",
        "automobile"
    ],
    "wof:name":"Gus's Auto Svc",
    "wof:placetype":"venue"
},
  "geometry": {"coordinates":[-79.2779846191,43.8703041077],"type":"Point"}
}