{
  "type": "Feature",
  "properties": {
    "addr:full":"Stewiacke NS B0N 2J0",
    "addr:postcode":"b0n 2j0",
    "iso:country":"CA",
    "sg:city":"Stewiacke",
    "sg:classifiers":[
        {
            "category":"Restaurant",
            "type":"Food & Drink"
        }
    ],
    "sg:phone":"+1 902 639 2300",
    "sg:postcode":"B0N 2J0",
    "sg:province":"NS",
    "sg:tags":[
        "parlor",
        "ice",
        "cream"
    ],
    "wof:name":"Dairy Queen",
    "wof:placetype":"venue"
},
  "geometry": {"coordinates":[-63.366787,45.140221],"type":"Point"}
}