{
  "type": "Feature",
  "properties": {
    "iso:country":"CA",
    "sg:city":"Calgary",
    "sg:classifiers":[
        {
            "category":"Wholesale",
            "subcategory":"Electrical",
            "type":"Manufacturing & Wholesale Goods"
        }
    ],
    "sg:phone":"+1 403 269 2938",
    "sg:postcode":"T2R 1J8",
    "sg:province":"AB",
    "sg:tags":[
        "communications",
        "equipment"
    ],
    "wof:name":"Jasomi Network Inc",
    "wof:placetype":"venue"
},
  "geometry": {"coordinates":[-114.07434845,51.0428237915],"type":"Point"}
}