{
  "type": "Feature",
  "properties": {
    "addr:full":"Welland ON L3B 3W4",
    "addr:postcode":"l3b 3w4",
    "iso:country":"CA",
    "sg:city":"Welland",
    "sg:classifiers":[
        {
            "category":"Recreation",
            "type":"Entertainment"
        }
    ],
    "sg:phone":"+1 905 788 0322",
    "sg:postcode":"L3B 3W4",
    "sg:province":"ON",
    "sg:tags":[
        "bingo",
        "game"
    ],
    "wof:name":"Main St Bingo Palace",
    "wof:placetype":"venue"
},
  "geometry": {"coordinates":[-79.2497634888,42.9916915894],"type":"Point"}
}