{
  "type": "Feature",
  "properties": {
    "addr:full":"400 Route 430 #1 Big River NB E2A 6N6",
    "addr:housenumber":"400",
    "addr:postcode":"e2a 6n6",
    "addr:street":"Route 430 # 1 Big",
    "iso:country":"CA",
    "sg:address":"400 Route 430 #1",
    "sg:city":"Big River",
    "sg:classifiers":[
        {
            "category":"Real Estate",
            "subcategory":"Real Estate Operator",
            "type":"Services"
        }
    ],
    "sg:phone":"+1 506 548 9843",
    "sg:postcode":"E2A 6N6",
    "sg:province":"NB",
    "sg:tags":[
        "mall",
        "shopping",
        "center"
    ],
    "wof:name":"Chaleur Center Management",
    "wof:placetype":"venue"
},
  "geometry": {"coordinates":[-65.66407,47.580002],"type":"Point"}
}