{
  "type": "Feature",
  "properties": {
    "iso:country":"CA",
    "sg:address":"8505 Tecumseh Rd E",
    "sg:city":"Windsor",
    "sg:classifiers":[
        {
            "category":"Retail",
            "subcategory":"Auto Repair",
            "type":"Services"
        }
    ],
    "sg:phone":"+1 519 948 8111",
    "sg:postcode":"N8R 1A1",
    "sg:province":"ON",
    "sg:tags":[
        "repairing",
        "automobile"
    ],
    "wof:name":"Canadian Tire",
    "wof:placetype":"venue"
},
  "geometry": {"coordinates":[-82.932854,42.313923],"type":"Point"}
}