{
  "type": "Feature",
  "properties": {
    "addr:full":"285 Wilson St Sault Ste Marie ON P6B 2K6",
    "addr:housenumber":"285",
    "addr:postcode":"p6b 2k6",
    "addr:street":"Wilson St",
    "iso:country":"CA",
    "sg:address":"285 Wilson St",
    "sg:city":"Sault Ste Marie",
    "sg:classifiers":[
        {
            "category":"Travel",
            "subcategory":"Travel Agent",
            "type":"Entertainment"
        }
    ],
    "sg:phone":"+1 705 759 4796",
    "sg:postcode":"P6B 2K6",
    "sg:province":"ON",
    "sg:tags":[
        "agency",
        "bureau"
    ],
    "wof:name":"Sunshine Travel Club",
    "wof:placetype":"venue"
},
  "geometry": {"coordinates":[-84.331619,46.51815],"type":"Point"}
}