{
  "type": "Feature",
  "properties": {
    "addr:full":"Milton ON L9T 5B2",
    "addr:postcode":"l9t 5b2",
    "iso:country":"CA",
    "sg:city":"Milton",
    "sg:classifiers":[
        {
            "category":"Health Services",
            "subcategory":"Clinic",
            "type":"Services"
        }
    ],
    "sg:phone":"+1 905 875 1459",
    "sg:postcode":"L9T 5B2",
    "sg:province":"ON",
    "sg:tags":[
        "home",
        "first",
        "aid"
    ],
    "wof:name":"Canadian Red Cross Society",
    "wof:placetype":"venue"
},
  "geometry": {"coordinates":[-79.872574,43.520126],"type":"Point"}
}