{
  "type": "Feature",
  "properties": {
    "addr:full":"100 Mount Paul Way Kamloops BC V2C 5K9",
    "addr:housenumber":"100",
    "addr:postcode":"bc v2c 5k9",
    "addr:street":"Mount Paul Way",
    "iso:country":"CA",
    "sg:address":"100 Mount Paul Way",
    "sg:city":"Kamloops",
    "sg:classifiers":[
        {
            "category":"Building & Trades",
            "subcategory":"Construction",
            "type":"Services"
        }
    ],
    "sg:phone":"+1 250 374 0316",
    "sg:postcode":"V2C 5K9",
    "sg:province":"BC",
    "sg:tags":[
        "product",
        "asphalt"
    ],
    "wof:name":"Pounder Emulsions",
    "wof:placetype":"venue"
},
  "geometry": {"coordinates":[-120.324997,50.679161],"type":"Point"}
}