{
  "type": "Feature",
  "properties": {
    "addr:full":"6833 26 Ave NE Calgary AB T1Y 6M7",
    "addr:housenumber":"6833",
    "addr:postcode":"t1y 6m7",
    "addr:street":"26 Ave Ne",
    "iso:country":"CA",
    "sg:address":"6833 26 Ave NE",
    "sg:city":"Calgary",
    "sg:classifiers":[
        {
            "category":"Autos & Motor Vehicles",
            "subcategory":"Fuel & Gas Station",
            "type":"Retail Goods"
        }
    ],
    "sg:phone":"+1 403 293 6887",
    "sg:postcode":"T1Y 6M7",
    "sg:province":"AB",
    "sg:tags":[
        "oil"
    ],
    "wof:name":"Pineridge Husky",
    "wof:placetype":"venue"
},
  "geometry": {"coordinates":[-113.93596599999999,51.076008],"type":"Point"}
}