{
  "type": "Feature",
  "properties": {
    "addr:full":"1575 Upper Ottawa St Hamilton ON L8W 3E2",
    "addr:housenumber":"1575",
    "addr:postcode":"l8w 3e2",
    "addr:street":"Upper Ottawa St",
    "iso:country":"CA",
    "sg:address":"1575 Upper Ottawa St",
    "sg:city":"Hamilton",
    "sg:classifiers":[
        {
            "category":"Real Estate",
            "subcategory":"Real Estate Agent",
            "type":"Services"
        }
    ],
    "sg:phone":"+1 905 388 3244",
    "sg:postcode":"L8W 3E2",
    "sg:province":"ON",
    "wof:name":"Prudential Corona Realty",
    "wof:placetype":"venue"
},
  "geometry": {"coordinates":[-79.8440704346,43.1903915405],"type":"Point"}
}