{
  "type": "Feature",
  "properties": {
    "addr:full":"9941 Boul Des Hetres Shawinigan QC G9N 4Y2",
    "addr:housenumber":"9941",
    "addr:postcode":"g9n 4y2",
    "addr:street":"Boul Des Hetres",
    "iso:country":"CA",
    "sg:address":"9941 Boul Des Hetres",
    "sg:city":"Shawinigan",
    "sg:classifiers":[
        {
            "category":"Real Estate",
            "subcategory":"Real Estate Agent",
            "type":"Services"
        }
    ],
    "sg:phone":"+1 819 539 1144",
    "sg:postcode":"G9N 4Y2",
    "sg:province":"QC",
    "sg:tags":[
        "agency",
        "rental"
    ],
    "wof:name":"United Rentals",
    "wof:placetype":"venue"
},
  "geometry": {"coordinates":[-72.70987700000001,46.596706],"type":"Point"}
}