{
  "type": "Feature",
  "properties": {
    "addr:full":"Ottawa ON K1P 5A6",
    "addr:postcode":"k1p 5a6",
    "iso:country":"CA",
    "sg:city":"Ottawa",
    "sg:classifiers":[
        {
            "category":"Professional",
            "subcategory":"Research",
            "type":"Services"
        }
    ],
    "sg:phone":"+1 613 230 7135",
    "sg:postcode":"K1P 5A6",
    "sg:province":"ON",
    "sg:tags":[
        "economic",
        "analysis"
    ],
    "wof:name":"Global Economics Ltd",
    "wof:placetype":"venue"
},
  "geometry": {"coordinates":[-75.696938,45.423237],"type":"Point"}
}