{
  "type": "Feature",
  "properties": {
    "iso:country":"CA",
    "sg:city":"Kelowna",
    "sg:classifiers":[
        {
            "category":"Shopping",
            "subcategory":"Florist",
            "type":"Retail Goods"
        }
    ],
    "sg:phone":"+1 250 868 3009",
    "sg:postcode":"V1V 2J9",
    "sg:province":"BC",
    "sg:tags":[
        "grocer"
    ],
    "wof:name":"Iga",
    "wof:placetype":"venue"
},
  "geometry": {"coordinates":[-119.443435669,49.9153823853],"type":"Point"}
}