{
  "type": "Feature",
  "properties": {
    "addr:full":"Montreal QC H3B 3P9",
    "addr:postcode":"h3b 3p9",
    "iso:country":"CA",
    "sg:city":"Montreal",
    "sg:classifiers":[
        {
            "category":"Banks & Credit Unions",
            "subcategory":"Investment Brokerage",
            "type":"Services"
        }
    ],
    "sg:phone":"+1 514 392 7600",
    "sg:postcode":"H3B 3P9",
    "sg:province":"QC",
    "wof:name":"Cibc Wood Gundy Inc",
    "wof:placetype":"venue"
},
  "geometry": {"coordinates":[-73.5679702759,45.5018196106],"type":"Point"}
}