{
  "type": "Feature",
  "properties": {
    "addr:full":"22 Hardy Ave Grand Falls-Windsor NL A2A 2P9",
    "addr:housenumber":"22",
    "addr:postcode":"a2a 2p9",
    "addr:street":"Hardy Ave",
    "iso:country":"CA",
    "sg:address":"22 Hardy Ave",
    "sg:city":"Grand Falls-Windsor",
    "sg:classifiers":[
        {
            "category":"Wholesale",
            "subcategory":"Groceries",
            "type":"Manufacturing & Wholesale Goods"
        }
    ],
    "sg:phone":"+1 709 489 2299",
    "sg:postcode":"A2A 2P9",
    "sg:province":"NL",
    "sg:tags":[
        "confectionery",
        "candy"
    ],
    "wof:name":"Brown Derby Wholesale Ltd",
    "wof:placetype":"venue"
},
  "geometry": {"coordinates":[-55.627979,48.954788],"type":"Point"}
}