{
  "type": "Feature",
  "properties": {
    "addr:full":"1245 Reid St # 1 Richmond Hill ON L4B 1G4",
    "addr:housenumber":"1245",
    "addr:postcode":"l4b 1g4",
    "addr:street":"Reid St # 1",
    "iso:country":"CA",
    "sg:address":"1245 Reid St # 1",
    "sg:city":"Richmond Hill",
    "sg:classifiers":[
        {
            "category":"Manufacturing",
            "subcategory":"Tools & Machinery",
            "type":"Manufacturing & Wholesale Goods"
        }
    ],
    "sg:phone":"+1 905 707 6704",
    "sg:postcode":"L4B 1G4",
    "sg:province":"ON",
    "sg:tags":[
        "plastic"
    ],
    "wof:name":"W Amsler Equipment Inc",
    "wof:placetype":"venue"
},
  "geometry": {"coordinates":[-79.38769499999999,43.849628],"type":"Point"}
}