{
  "type": "Feature",
  "properties": {
    "addr:full":"1117 Grace St Regina SK S4T 5M6",
    "addr:housenumber":"1117",
    "addr:postcode":"s4t 5m6",
    "addr:street":"Grace St",
    "iso:country":"CA",
    "sg:address":"1117 Grace St",
    "sg:city":"Regina",
    "sg:classifiers":[
        {
            "category":"Building & Trades",
            "subcategory":"Construction",
            "type":"Services"
        }
    ],
    "sg:phone":"+1 306 949 8225",
    "sg:postcode":"S4T 5M6",
    "sg:province":"SK",
    "sg:tags":[
        "general",
        "contractor"
    ],
    "wof:name":"Xtreme Renovations",
    "wof:placetype":"venue"
},
  "geometry": {"coordinates":[-104.66091900000001,50.46056],"type":"Point"}
}