{
  "type": "Feature",
  "properties": {
    "iso:country":"CA",
    "sg:address":"1117 Grace St",
    "sg:city":"Regina",
    "sg:classifiers":[
        {
            "category":"Building & Trades",
            "subcategory":"Construction",
            "type":"Services"
        }
    ],
    "sg:phone":"+1 306 949 8225",
    "sg:postcode":"S4T 5M6",
    "sg:province":"SK",
    "sg:tags":[
        "general",
        "contractor"
    ],
    "wof:name":"Xtreme Renovations",
    "wof:placetype":"venue"
},
  "geometry": {"coordinates":[-104.660919,50.46056],"type":"Point"}
}