{
  "type": "Feature",
  "properties": {
    "addr:full":"6070 Rue Sherbrooke E Montreal QC H1N 1C1",
    "addr:housenumber":"6070",
    "addr:postcode":"h1n 1c1",
    "addr:street":"Rue Sherbrooke E",
    "iso:country":"CA",
    "sg:address":"6070 Rue Sherbrooke E",
    "sg:city":"Montreal",
    "sg:classifiers":[
        {
            "category":"Professional",
            "subcategory":"Lawyer & Legal Services",
            "type":"Services"
        }
    ],
    "sg:phone":"+1 514 495 8150",
    "sg:postcode":"H1N 1C1",
    "sg:province":"QC",
    "sg:tags":[
        "attorney"
    ],
    "wof:name":"Barnabe, Christiane",
    "wof:placetype":"venue"
},
  "geometry": {"coordinates":[-73.5457687378,45.5778121948],"type":"Point"}
}