{
  "type": "Feature",
  "properties": {
    "addr:full":"65 Stanleys Rd North Bay ON P1B 8G2",
    "addr:housenumber":"65",
    "addr:postcode":"p1b 8g2",
    "addr:street":"Stanleys Rd North",
    "iso:country":"CA",
    "sg:address":"65 Stanleys Rd",
    "sg:city":"North Bay",
    "sg:classifiers":[
        {
            "category":"Manufacturing",
            "subcategory":"Signs",
            "type":"Manufacturing & Wholesale Goods"
        }
    ],
    "sg:phone":"+1 705 495 4402",
    "sg:postcode":"P1B 8G2",
    "sg:province":"ON",
    "wof:name":"Lbg Signs",
    "wof:placetype":"venue"
},
  "geometry": {"coordinates":[-79.36163330079999,46.3799133301],"type":"Point"}
}