{
  "type": "Feature",
  "properties": {
    "iso:country":"CA",
    "sg:address":"505 Rue DE Castelnau E",
    "sg:city":"Montreal",
    "sg:classifiers":[
        {
            "category":"Shopping",
            "subcategory":"Computers & Home Electronics",
            "type":"Retail Goods"
        }
    ],
    "sg:phone":"+1 514 270 5100",
    "sg:postcode":"H2R 1R4",
    "sg:province":"QC",
    "sg:tags":[
        "equipment",
        "dealer"
    ],
    "wof:name":"Msb Innovation Inc",
    "wof:placetype":"venue"
},
  "geometry": {"coordinates":[-73.6169891357,45.5399093628],"type":"Point"}
}