{
  "type": "Feature",
  "properties": {
    "addr:full":"3150 Ash St Vancouver BC V5Z 3C9",
    "addr:housenumber":"3150",
    "addr:postcode":"v5z 3c9",
    "addr:street":"Ash St",
    "iso:country":"CA",
    "sg:address":"3150 Ash St",
    "sg:city":"Vancouver",
    "sg:classifiers":[
        {
            "category":"Shopping",
            "subcategory":"Hobbies, Toys, & Games",
            "type":"Retail Goods"
        }
    ],
    "sg:phone":"+1 604 872 8727",
    "sg:postcode":"V5Z 3C9",
    "sg:province":"BC",
    "sg:tags":[
        "supply"
    ],
    "wof:name":"Bingo Super J",
    "wof:placetype":"venue"
},
  "geometry": {"coordinates":[-123.11782074,49.2572517395],"type":"Point"}
}