{
  "type": "Feature",
  "properties": {
    "addr:full":"2798 Rang Saint-Pierre Chicoutimi QC G7H 5B3",
    "addr:housenumber":"2798",
    "addr:postcode":"g7h 5b3",
    "addr:street":"Rang Saint-Pierre",
    "iso:country":"CA",
    "sg:address":"2798 Rang Saint-Pierre",
    "sg:city":"Chicoutimi",
    "sg:classifiers":[
        {
            "category":"Building & Trades",
            "subcategory":"Cleaning & Sanitation",
            "type":"Services"
        }
    ],
    "sg:phone":"+1 418 549 3708",
    "sg:postcode":"G7H 5B3",
    "sg:province":"QC",
    "sg:tags":[
        "janitor",
        "steam"
    ],
    "wof:name":"Nettoyeur Ramsay Bernard",
    "wof:placetype":"venue"
},
  "geometry": {"coordinates":[-71.1341171265,48.3773269653],"type":"Point"}
}