{
  "type": "Feature",
  "properties": {
    "iso:country":"CA",
    "sg:city":"Saint-Antonin",
    "sg:classifiers":[
        {
            "category":"Building & Trades",
            "subcategory":"Plumbing",
            "type":"Services"
        }
    ],
    "sg:phone":"+1 418 867 4915",
    "sg:postcode":"G0L 2J0",
    "sg:province":"QC",
    "sg:tags":[
        "contractor"
    ],
    "wof:name":"Plomberie Damien Gagne Inc",
    "wof:placetype":"venue"
},
  "geometry": {"coordinates":[-69.4792022705,47.7612266541],"type":"Point"}
}