{
  "type": "Feature",
  "properties": {
    "iso:country":"CA",
    "sg:address":"2064 Sheppard Ave E",
    "sg:city":"North York",
    "sg:classifiers":[
        {
            "category":"Food & Beverages",
            "subcategory":"Groceries & Convenience Stores",
            "type":"Retail Goods"
        }
    ],
    "sg:phone":"+1 416 499 4850",
    "sg:postcode":"M2J 5B3",
    "sg:province":"ON",
    "sg:tags":[
        "grocer"
    ],
    "wof:name":"Marcy Fine Foods",
    "wof:placetype":"venue"
},
  "geometry": {"coordinates":[-79.33014678959999,43.7751083374],"type":"Point"}
}