{
  "type": "Feature",
  "properties": {
    "addr:full":"410 Rothesay Ave Saint John NB E2J 2C4",
    "addr:housenumber":"410",
    "addr:postcode":"e2j 2c4",
    "addr:street":"Rothesay Ave",
    "iso:country":"CA",
    "sg:address":"410 Rothesay Ave",
    "sg:city":"Saint John",
    "sg:classifiers":[
        {
            "category":"Autos & Motor Vehicles",
            "subcategory":"Automobile Sales",
            "type":"Retail Goods"
        }
    ],
    "sg:phone":"+1 506 633 7070",
    "sg:postcode":"E2J 2C4",
    "sg:province":"NB",
    "sg:tags":[
        "car",
        "dealer"
    ],
    "wof:name":"Saint John Toyota",
    "wof:placetype":"venue"
},
  "geometry": {"coordinates":[-66.035782,45.301678],"type":"Point"}
}