{
  "type": "Feature",
  "properties": {
    "addr:full":"Burlington ON L7M 1A6",
    "addr:postcode":"l7m 1a6",
    "iso:country":"CA",
    "sg:city":"Burlington",
    "sg:classifiers":[
        {
            "category":"Shopping",
            "subcategory":"Bicycles & Sporting Goods",
            "type":"Retail Goods"
        }
    ],
    "sg:phone":"+1 905 336 0821",
    "sg:postcode":"L7M 1A6",
    "sg:province":"ON",
    "sg:tags":[
        "equipment",
        "playground"
    ],
    "wof:name":"Timbertots",
    "wof:placetype":"venue"
},
  "geometry": {"coordinates":[-79.80165100000001,43.366047],"type":"Point"}
}