{
  "type": "Feature",
  "properties": {
    "addr:full":"Montreal QC H2Y 1T9",
    "addr:postcode":"h2y 1t9",
    "iso:country":"CA",
    "sg:city":"Montreal",
    "sg:classifiers":[
        {
            "category":"Wholesale",
            "subcategory":"Apparel",
            "type":"Manufacturing & Wholesale Goods"
        }
    ],
    "sg:phone":"+1 514 849 1287",
    "sg:postcode":"H2Y 1T9",
    "sg:province":"QC",
    "sg:tags":[
        "clothing"
    ],
    "wof:name":"Tri Cotage Des Vos Ges Canada",
    "wof:placetype":"venue"
},
  "geometry": {"coordinates":[-73.552696228,45.5096359253],"type":"Point"}
}