{
  "type": "Feature",
  "properties": {
    "addr:full":"2556 Sinclair Rd Victoria BC V8N 1B8",
    "addr:housenumber":"2556",
    "addr:postcode":"v8n 1b8",
    "addr:street":"Sinclair Rd",
    "iso:country":"CA",
    "sg:address":"2556 Sinclair Rd",
    "sg:city":"Victoria",
    "sg:classifiers":[
        {
            "category":"Real Estate",
            "subcategory":"Real Estate Agent",
            "type":"Services"
        }
    ],
    "sg:phone":"+1 250 477 1100",
    "sg:postcode":"V8N 1B8",
    "sg:province":"BC",
    "wof:name":"Queenswood Properties Ltd",
    "wof:placetype":"venue"
},
  "geometry": {"coordinates":[-123.364517212,48.428314209],"type":"Point"}
}