{
  "type": "Feature",
  "properties": {
    "addr:full":"Vancouver BC V6B 2S2",
    "addr:postcode":"v6b 2s2",
    "iso:country":"CA",
    "sg:city":"Vancouver",
    "sg:classifiers":[
        {
            "category":"Professional",
            "subcategory":"Art Services",
            "type":"Services"
        }
    ],
    "sg:phone":"+1 604 681 3377",
    "sg:postcode":"V6B 2S2",
    "sg:province":"BC",
    "sg:tags":[
        "graphic",
        "designer"
    ],
    "wof:name":"Barnstorm Creative Group Inc",
    "wof:placetype":"venue"
},
  "geometry": {"coordinates":[-123.121253967,49.2756538391],"type":"Point"}
}