{
  "type": "Feature",
  "properties": {
    "iso:country":"CA",
    "sg:address":"630 Garbally Rd",
    "sg:city":"Victoria",
    "sg:classifiers":[
        {
            "category":"Wholesale",
            "subcategory":"Farm Supplies",
            "type":"Manufacturing & Wholesale Goods"
        }
    ],
    "sg:phone":"+1 250 381 2281",
    "sg:postcode":"V8T 2K2",
    "sg:province":"BC",
    "sg:tags":[
        "equipment",
        "greenhouse"
    ],
    "wof:name":"Westgro Sales Inc",
    "wof:placetype":"venue"
},
  "geometry": {"coordinates":[-123.371002197,48.4408874512],"type":"Point"}
}