{
  "type": "Feature",
  "properties": {
    "addr:full":"4156 Eckert St Chilliwack BC V2R 5J6",
    "addr:postcode":"4156;v2r 5j6",
    "addr:street":"Eckert St",
    "iso:country":"CA",
    "sg:address":"4156 Eckert St",
    "sg:city":"Chilliwack",
    "sg:classifiers":[
        {
            "category":"Professional",
            "subcategory":"Accounting & Tax Preparation",
            "type":"Services"
        }
    ],
    "sg:phone":"+1 604 823 4711",
    "sg:postcode":"V2R 5J6",
    "sg:province":"BC",
    "sg:tags":[
        "bookkeeping",
        "general"
    ],
    "wof:name":"Lynda's Bookkeeping",
    "wof:placetype":"venue"
},
  "geometry": {"coordinates":[-122.056350708,49.0773200989],"type":"Point"}
}