{
  "type": "Feature",
  "properties": {
    "addr:full":"472 Rue Principale Saint-Donat-DE-Montcalm QC J0T 2C0",
    "addr:housenumber":"472",
    "addr:postcode":"j0t 2c0",
    "addr:street":"Rue Principale",
    "iso:country":"CA",
    "sg:address":"472 Rue Principale",
    "sg:city":"Saint-Donat-DE-Montcalm",
    "sg:classifiers":[
        {
            "category":"Real Estate",
            "subcategory":"Real Estate Agent",
            "type":"Services"
        }
    ],
    "sg:phone":"+1 819 424 2443",
    "sg:postcode":"J0T 2C0",
    "sg:province":"QC",
    "wof:name":"Capitale Saint-Donat",
    "wof:placetype":"venue"
},
  "geometry": {"coordinates":[-74.221245,46.318016],"type":"Point"}
}