{
  "type": "Feature",
  "properties": {
    "addr:full":"4135 Boul Sainte-Anne Beauport QC G1C 2H9",
    "addr:housenumber":"4135",
    "addr:postcode":"qc g1c 2h9",
    "addr:street":"Boul Sainte-Anne",
    "iso:country":"CA",
    "sg:address":"4135 Boul Sainte-Anne",
    "sg:city":"Beauport",
    "sg:classifiers":[
        {
            "category":"Freight",
            "type":"Transportation"
        }
    ],
    "sg:phone":"+1 418 661 6981",
    "sg:postcode":"G1C 2H9",
    "sg:province":"QC",
    "sg:tags":[
        "trucking"
    ],
    "wof:name":"Transport Lavoie Ltee",
    "wof:placetype":"venue"
},
  "geometry": {"coordinates":[-71.158737,46.873081],"type":"Point"}
}