{
  "type": "Feature",
  "properties": {
    "addr:full":"4204 12th Ave W Vancouver BC V6R 2P7",
    "addr:housenumber":"4204",
    "addr:postcode":"v6r 2p7",
    "addr:street":"12Th Ave W",
    "iso:country":"CA",
    "sg:address":"4204 12th Ave W",
    "sg:city":"Vancouver",
    "sg:classifiers":[
        {
            "category":"Professional",
            "subcategory":"Management & Consulting",
            "type":"Services"
        }
    ],
    "sg:phone":"+1 604 228 1948",
    "sg:postcode":"V6R 2P7",
    "sg:province":"BC",
    "sg:tags":[
        "consultant",
        "business"
    ],
    "wof:name":"Touchstone Management Conslnts",
    "wof:placetype":"venue"
},
  "geometry": {"coordinates":[-123.200447,49.261772],"type":"Point"}
}