{
  "type": "Feature",
  "properties": {
    "addr:full":"234 Rue Dufferin Sherbrooke QC J1H 4M2",
    "addr:housenumber":"234",
    "addr:postcode":"j1h 4m2",
    "addr:street":"Rue Dufferin",
    "iso:country":"CA",
    "sg:address":"234 Rue Dufferin",
    "sg:city":"Sherbrooke",
    "sg:classifiers":[
        {
            "category":"Personal",
            "type":"Services"
        }
    ],
    "sg:phone":"+1 819 563 0442",
    "sg:postcode":"J1H 4M2",
    "sg:province":"QC",
    "sg:tags":[
        "control",
        "weight"
    ],
    "wof:name":"Doucet, Marie I",
    "wof:placetype":"venue"
},
  "geometry": {"coordinates":[-71.89408874510001,45.4051589966],"type":"Point"}
}