{
  "type": "Feature",
  "properties": {
    "addr:full":"4453 99 St NW Edmonton AB T6E 5B6",
    "addr:housenumber":"4453",
    "addr:postcode":"t6e 5b6",
    "addr:street":"99 St Nw",
    "iso:country":"CA",
    "sg:address":"4453 99 St NW",
    "sg:city":"Edmonton",
    "sg:classifiers":[
        {
            "category":"Retail",
            "subcategory":"Repair Shop",
            "type":"Services"
        }
    ],
    "sg:phone":"+1 780 437 3800",
    "sg:postcode":"T6E 5B6",
    "sg:province":"AB",
    "sg:tags":[
        "radio",
        "television",
        "video"
    ],
    "wof:name":"Stereo City Svc",
    "wof:placetype":"venue"
},
  "geometry": {"coordinates":[-113.485794,53.482517],"type":"Point"}
}