{
  "type": "Feature",
  "properties": {
    "addr:full":"410 Rue Joseph-Nil-Claveau LA Baie QC G7B 4R6",
    "addr:housenumber":"410",
    "addr:postcode":"g7b 4r6",
    "addr:street":"Rue Joseph-Nil-Claveau",
    "iso:country":"CA",
    "sg:address":"410 Rue Joseph-Nil-Claveau",
    "sg:city":"LA Baie",
    "sg:classifiers":[
        {
            "category":"Building & Trades",
            "subcategory":"Construction",
            "type":"Services"
        }
    ],
    "sg:phone":"+1 418 544 1565",
    "sg:postcode":"G7B 4R6",
    "sg:province":"QC",
    "sg:tags":[
        "general",
        "contractor"
    ],
    "wof:name":"Constructions Real Houde Inc",
    "wof:placetype":"venue"
},
  "geometry": {"coordinates":[-70.90222930909999,48.3270263672],"type":"Point"}
}