{
  "type": "Feature",
  "properties": {
    "iso:country":"CA",
    "sg:address":"4362 Leader Lane",
    "sg:city":"Niagara Falls",
    "sg:classifiers":[
        {
            "category":"Recreation",
            "type":"Entertainment"
        }
    ],
    "sg:phone":"+1 905 991 8564",
    "sg:postcode":"L2E 2Z6",
    "sg:province":"ON",
    "sg:tags":[
        "bicycle"
    ],
    "wof:name":"Leisure Trails Bicycle Rentals",
    "wof:placetype":"venue"
},
  "geometry": {"coordinates":[-79.06503295900001,43.1148033142],"type":"Point"}
}