{
  "type": "Feature",
  "properties": {
    "addr:full":"39155 Westfield Blyth ON N0M 1H0",
    "addr:housenumber":"39155",
    "addr:postcode":"n0m 1h0",
    "addr:street":"Westfield",
    "iso:country":"CA",
    "sg:address":"39155 Westfield",
    "sg:city":"Blyth",
    "sg:classifiers":[
        {
            "category":"Retail",
            "subcategory":"Auto Repair",
            "type":"Services"
        }
    ],
    "sg:phone":"+1 519 523 4356",
    "sg:postcode":"N0M 1H0",
    "sg:province":"ON",
    "sg:tags":[
        "repairing",
        "automobile"
    ],
    "wof:name":"Dan's Auto Repair",
    "wof:placetype":"venue"
},
  "geometry": {"coordinates":[-81.4304351807,43.7350654602],"type":"Point"}
}