{
  "type": "Feature",
  "properties": {
    "iso:country":"CA",
    "sg:address":"143 Boul Evain E",
    "sg:city":"Evain",
    "sg:classifiers":[
        {
            "category":"Building & Trades",
            "subcategory":"Construction",
            "type":"Services"
        }
    ],
    "sg:phone":"+1 819 768 2337",
    "sg:postcode":"J0Z 1Y0",
    "sg:province":"QC",
    "sg:tags":[
        "refinishing",
        "floor",
        "laying",
        "cabinet",
        "equipment",
        "resurfacing",
        "kitchen"
    ],
    "wof:name":"Armoires Gibson Inc",
    "wof:placetype":"venue"
},
  "geometry": {"coordinates":[-79.2306976318,48.322769165],"type":"Point"}
}