{
  "type": "Feature",
  "properties": {
    "iso:country":"CA",
    "sg:address":"851 Route 10",
    "sg:city":"Noonan",
    "sg:classifiers":[
        {
            "category":"Organizations",
            "subcategory":"Religious Organization",
            "type":"Services"
        }
    ],
    "sg:phone":"+1 506 450 8380",
    "sg:postcode":"E3A 7H4",
    "sg:province":"NB",
    "sg:tags":[
        "church"
    ],
    "wof:name":"United Pentecostal Church",
    "wof:placetype":"venue"
},
  "geometry": {"coordinates":[-66.52565800000001,45.963711],"type":"Point"}
}