{
  "type": "Feature",
  "properties": {
    "addr:full":"12 Av Des Villas Orford QC J1X 6X3",
    "addr:postcode":"j1x 6x3",
    "addr:street":"12 Av Des Villas",
    "iso:country":"CA",
    "sg:address":"12 Av Des Villas",
    "sg:city":"Orford",
    "sg:classifiers":[
        {
            "category":"Real Estate",
            "subcategory":"Real Estate Operator",
            "type":"Services"
        }
    ],
    "sg:phone":"+1 819 868 2149",
    "sg:postcode":"J1X 6X3",
    "sg:province":"QC",
    "sg:tags":[
        "condominium"
    ],
    "wof:name":"Cedres D'Orford",
    "wof:placetype":"venue"
},
  "geometry": {"coordinates":[-72.1601257324,45.3101501465],"type":"Point"}
}