{
  "type": "Feature",
  "properties": {
    "addr:full":"Castlegar BC V1N 2W8",
    "addr:postcode":"v1n 2w8",
    "iso:country":"CA",
    "sg:city":"Castlegar",
    "sg:classifiers":[
        {
            "category":"Restaurant",
            "type":"Food & Drink"
        }
    ],
    "sg:phone":"+1 250 365 6444",
    "sg:postcode":"V1N 2W8",
    "sg:province":"BC",
    "wof:name":"Joey's Only Seafood Restaurant",
    "wof:placetype":"venue"
},
  "geometry": {"coordinates":[-117.65348053,49.295665741],"type":"Point"}
}