{
  "type": "Feature",
  "properties": {
    "addr:full":"North York ON M3M 2H7",
    "addr:postcode":"m3m 2h7",
    "iso:country":"CA",
    "sg:city":"North York",
    "sg:classifiers":[
        {
            "category":"Health Services",
            "subcategory":"Doctor",
            "type":"Services"
        }
    ],
    "sg:phone":"+1 416 633 3553",
    "sg:postcode":"M3M 2H7",
    "sg:province":"ON",
    "sg:tags":[
        "dentist"
    ],
    "wof:name":"Brown, S H DDS",
    "wof:placetype":"venue"
},
  "geometry": {"coordinates":[-79.486504,43.744514],"type":"Point"}
}