{
  "type": "Feature",
  "properties": {
    "addr:full":"Grande Prairie AB T8V 6Z1",
    "addr:postcode":"t8v 6z1",
    "iso:country":"CA",
    "sg:city":"Grande Prairie",
    "sg:classifiers":[
        {
            "category":"Shopping",
            "subcategory":"Clothing, Apparel, & Fashions",
            "type":"Retail Goods"
        }
    ],
    "sg:phone":"+1 780 539 7447",
    "sg:postcode":"T8V 6Z1",
    "sg:province":"AB",
    "wof:name":"Calista's",
    "wof:placetype":"venue"
},
  "geometry": {"coordinates":[-118.791404724,55.1855163574],"type":"Point"}
}