{
  "type": "Feature",
  "properties": {
    "addr:full":"Huntingdon QC J0S 1H0",
    "addr:postcode":"j0s 1h0",
    "iso:country":"CA",
    "sg:city":"Huntingdon",
    "sg:classifiers":[
        {
            "category":"Bars & Pubs",
            "type":"Food & Drink"
        }
    ],
    "sg:phone":"+1 450 264 6613",
    "sg:postcode":"J0S 1H0",
    "sg:province":"QC",
    "wof:name":"Brasserie Du Village",
    "wof:placetype":"venue"
},
  "geometry": {"coordinates":[-74.172752,45.087265],"type":"Point"}
}