{
  "type": "Feature",
  "properties": {
    "addr:full":"Clinton ON N0M 1L0",
    "addr:postcode":"n0m 1l0",
    "iso:country":"CA",
    "sg:city":"Clinton",
    "sg:classifiers":[
        {
            "category":"Government",
            "subcategory":"Office",
            "type":"Public Place"
        }
    ],
    "sg:phone":"+1 519 482 8612",
    "sg:postcode":"N0M 1L0",
    "sg:province":"ON",
    "wof:name":"Huron County Housing Corp",
    "wof:placetype":"venue"
},
  "geometry": {"coordinates":[-81.539680481,43.6265525818],"type":"Point"}
}