{
  "type": "Feature",
  "properties": {
    "addr:full":"3101 Boul Pere-Lelievre Quebec QC G1P 2Y3",
    "addr:housenumber":"3101",
    "addr:postcode":"g1p 2y3",
    "addr:street":"Boul Pere-Lelievre",
    "iso:country":"CA",
    "sg:address":"3101 Boul Pere-Lelievre",
    "sg:city":"Quebec",
    "sg:classifiers":[
        {
            "category":"Restaurant",
            "type":"Food & Drink"
        }
    ],
    "sg:phone":"+1 418 683 4434",
    "sg:postcode":"G1P 2Y3",
    "sg:province":"QC",
    "wof:name":"Pfk",
    "wof:placetype":"venue"
},
  "geometry": {"coordinates":[-71.313789,46.811893],"type":"Point"}
}