{
  "type": "Feature",
  "properties": {
    "addr:full":"241 39 Ave NE Calgary AB T2E 7E3",
    "addr:housenumber":"241",
    "addr:postcode":"t2e 7e3",
    "addr:street":"39 Ave Ne",
    "iso:country":"CA",
    "sg:address":"241 39 Ave NE",
    "sg:city":"Calgary",
    "sg:classifiers":[
        {
            "category":"Manufacturing",
            "subcategory":"Food",
            "type":"Manufacturing & Wholesale Goods"
        }
    ],
    "sg:phone":"+1 403 230 5837",
    "sg:postcode":"T2E 7E3",
    "sg:province":"AB",
    "sg:tags":[
        "grocer",
        "health"
    ],
    "wof:name":"Parkland Processors",
    "wof:placetype":"venue"
},
  "geometry": {"coordinates":[-114.058807,51.087616],"type":"Point"}
}