{
  "type": "Feature",
  "properties": {
    "addr:full":"300 Waverly Rd Bowmanville ON L1C 3K3",
    "addr:housenumber":"300",
    "addr:postcode":"l1c 3k3",
    "addr:street":"Waverly Rd",
    "iso:country":"CA",
    "sg:address":"300 Waverly Rd",
    "sg:city":"Bowmanville",
    "sg:classifiers":[
        {
            "category":"Food & Beverages",
            "subcategory":"Bakery",
            "type":"Retail Goods"
        }
    ],
    "sg:phone":"+1 905 623 6847",
    "sg:postcode":"L1C 3K3",
    "sg:province":"ON",
    "sg:tags":[
        "doughnut"
    ],
    "wof:name":"Skylight Donuts Drive Thru",
    "wof:placetype":"venue"
},
  "geometry": {"coordinates":[-78.69113900000001,43.898014],"type":"Point"}
}