{
  "type": "Feature",
  "properties": {
    "addr:full":"2151 Ontario St Vancouver BC V5T 2X1",
    "addr:housenumber":"2151",
    "addr:postcode":"v5t 2x1",
    "addr:street":"Ontario St",
    "iso:country":"CA",
    "sg:address":"2151 Ontario St",
    "sg:city":"Vancouver",
    "sg:classifiers":[
        {
            "category":"Manufacturing",
            "subcategory":"Printing",
            "type":"Manufacturing & Wholesale Goods"
        }
    ],
    "sg:phone":"+1 604 215 0828",
    "sg:postcode":"V5T 2X1",
    "sg:province":"BC",
    "sg:tags":[
        "printer"
    ],
    "wof:name":"Qualitime Printing CO Ltd",
    "wof:placetype":"venue"
},
  "geometry": {"coordinates":[-123.105003,49.266033],"type":"Point"}
}