{
  "type": "Feature",
  "properties": {
    "addr:full":"4231 Hazelbridge Way # 155 Richmond BC V6X 3L7",
    "addr:housenumber":"4231;155",
    "addr:postcode":"v6x 3l7",
    "addr:street":"Hazelbridge Way #",
    "iso:country":"CA",
    "sg:address":"4231 Hazelbridge Way # 155",
    "sg:city":"Richmond",
    "sg:classifiers":[
        {
            "category":"Utilities",
            "subcategory":"Mobile Phone",
            "type":"Services"
        }
    ],
    "sg:phone":"+1 604 231 8111",
    "sg:postcode":"V6X 3L7",
    "sg:province":"BC",
    "sg:tags":[
        "telephone",
        "cellular"
    ],
    "wof:name":"Genius Communications Ctr",
    "wof:placetype":"venue"
},
  "geometry": {"coordinates":[-123.13362100000001,49.182491],"type":"Point"}
}