{
  "type": "Feature",
  "properties": {
    "addr:full":"644 Baker St Nelson BC V1L 4J4",
    "addr:housenumber":"644",
    "addr:postcode":"bc v1l 4j4",
    "addr:street":"Baker St",
    "iso:country":"CA",
    "sg:address":"644 Baker St",
    "sg:city":"Nelson",
    "sg:classifiers":[
        {
            "category":"Shopping",
            "subcategory":"Department Store",
            "type":"Retail Goods"
        }
    ],
    "sg:phone":"+1 250 352 4644",
    "sg:postcode":"V1L 4J4",
    "sg:province":"BC",
    "sg:tags":[
        "shop",
        "variety"
    ],
    "wof:name":"Your Dollar Store With More",
    "wof:placetype":"venue"
},
  "geometry": {"coordinates":[-117.291878,49.492619],"type":"Point"}
}