{
  "type": "Feature",
  "properties": {
    "iso:country":"CA",
    "sg:city":"Vancouver",
    "sg:classifiers":[
        {
            "category":"Manufacturing",
            "subcategory":"Printing",
            "type":"Manufacturing & Wholesale Goods"
        }
    ],
    "sg:phone":"+1 604 325 8109",
    "sg:postcode":"V5Y 2V5",
    "sg:province":"BC",
    "sg:tags":[
        "newspaper"
    ],
    "wof:name":"Chinese-Canadian Press",
    "wof:placetype":"venue"
},
  "geometry": {"coordinates":[-123.111663818,49.2304611206],"type":"Point"}
}