{
  "type": "Feature",
  "properties": {
    "addr:full":"151 Trillium Dr Kitchener ON N2E 1W9",
    "addr:housenumber":"151",
    "addr:postcode":"n2e 1w9",
    "addr:street":"Trillium Dr",
    "iso:country":"CA",
    "sg:address":"151 Trillium Dr",
    "sg:city":"Kitchener",
    "sg:classifiers":[
        {
            "category":"Manufacturing",
            "subcategory":"Metals",
            "type":"Manufacturing & Wholesale Goods"
        }
    ],
    "sg:phone":"+1 519 893 1204",
    "sg:postcode":"N2E 1W9",
    "sg:province":"ON",
    "sg:tags":[
        "stamping"
    ],
    "wof:name":"Globe Stamping CO Ltd",
    "wof:placetype":"venue"
},
  "geometry": {"coordinates":[-80.4598770142,43.4014282227],"type":"Point"}
}