{
  "type": "Feature",
  "properties": {
    "addr:full":"111 Jasper St Maple Creek SK S0N 1N0",
    "addr:housenumber":"111",
    "addr:postcode":"s0n 1n0",
    "addr:street":"Jasper St",
    "iso:country":"CA",
    "sg:address":"111 Jasper St",
    "sg:city":"Maple Creek",
    "sg:classifiers":[
        {
            "category":"Home & Garden",
            "subcategory":"Hardware",
            "type":"Retail Goods"
        }
    ],
    "sg:phone":"+1 306 662 2144",
    "sg:postcode":"S0N 1N0",
    "sg:province":"SK",
    "sg:tags":[
        "saw"
    ],
    "wof:name":"Hodson Hardware CO Ltd",
    "wof:placetype":"venue"
},
  "geometry": {"coordinates":[-109.478645,49.909161],"type":"Point"}
}