{
  "type": "Feature",
  "properties": {
    "addr:full":"1603 Rue Fullum Montreal QC H2K 3M5",
    "addr:housenumber":"1603",
    "addr:postcode":"h2k 3m5",
    "addr:street":"Rue Fullum",
    "iso:country":"CA",
    "sg:address":"1603 Rue Fullum",
    "sg:city":"Montreal",
    "sg:classifiers":[
        {
            "category":"Food & Beverages",
            "subcategory":"Groceries & Convenience Stores",
            "type":"Retail Goods"
        }
    ],
    "sg:phone":"+1 514 526 2297",
    "sg:postcode":"H2K 3M5",
    "sg:province":"QC",
    "wof:name":"Depanneur Blanchette Enr",
    "wof:placetype":"venue"
},
  "geometry": {"coordinates":[-73.550224,45.528255],"type":"Point"}
}