{
  "type": "Feature",
  "properties": {
    "addr:full":"1312 Commercial Dr Vancouver BC V5L 3X6",
    "addr:housenumber":"1312",
    "addr:postcode":"v5l 3x6",
    "addr:street":"Commercial Dr",
    "iso:country":"CA",
    "sg:address":"1312 Commercial Dr",
    "sg:city":"Vancouver",
    "sg:classifiers":[
        {
            "category":"Shopping",
            "type":"Retail Goods"
        }
    ],
    "sg:phone":"+1 604 255 9513",
    "sg:postcode":"V5L 3X6",
    "sg:province":"BC",
    "sg:tags":[
        "art",
        "gallery",
        "dealer"
    ],
    "wof:name":"Doctor Vigari Gallery",
    "wof:placetype":"venue"
},
  "geometry": {"coordinates":[-123.06942749,49.2728271484],"type":"Point"}
}