{
  "type": "Feature",
  "properties": {
    "iso:country":"CA",
    "sg:address":"1061 Rue Saint-Alexandre # 600",
    "sg:city":"Montreal",
    "sg:classifiers":[
        {
            "category":"Wholesale",
            "subcategory":"Durable Goods & Equipment",
            "type":"Manufacturing & Wholesale Goods"
        }
    ],
    "sg:phone":"+1 514 286 2472",
    "sg:postcode":"H2Z 1P5",
    "sg:province":"QC",
    "sg:tags":[
        "recording",
        "record",
        "tape",
        "studio",
        "compact"
    ],
    "wof:name":"Magra Multi Media",
    "wof:placetype":"venue"
},
  "geometry": {"coordinates":[-73.5634613037,45.5034103394],"type":"Point"}
}