{
  "type": "Feature",
  "properties": {
    "addr:full":"4440 Cowley Cres Richmond BC V7B 1B8",
    "addr:housenumber":"4440",
    "addr:postcode":"v7b 1b8",
    "addr:street":"Cowley Cres",
    "iso:country":"CA",
    "sg:address":"4440 Cowley Cres",
    "sg:city":"Richmond",
    "sg:classifiers":[
        {
            "category":"Retail",
            "subcategory":"Auto Rental",
            "type":"Services"
        }
    ],
    "sg:phone":"+1 604 273 6572",
    "sg:postcode":"V7B 1B8",
    "sg:province":"BC",
    "sg:tags":[
        "renting",
        "automobile"
    ],
    "wof:name":"National Car Rental",
    "wof:placetype":"venue"
},
  "geometry": {"coordinates":[-123.17012,49.180622],"type":"Point"}
}