{
  "type": "Feature",
  "properties": {
    "addr:full":"Mississauga ON L4W 1T7",
    "addr:postcode":"l4w 1t7",
    "iso:country":"CA",
    "sg:city":"Mississauga",
    "sg:classifiers":[
        {
            "category":"Professional",
            "subcategory":"Business Services",
            "type":"Services"
        }
    ],
    "sg:phone":"+1 905 821 0007",
    "sg:postcode":"L4W 1T7",
    "sg:province":"ON",
    "sg:tags":[
        "agency",
        "paralegal",
        "collection"
    ],
    "wof:name":"Defend Paralegal & Financial",
    "wof:placetype":"venue"
},
  "geometry": {"coordinates":[-79.64195251460001,43.6541595459],"type":"Point"}
}