{
  "type": "Feature",
  "properties": {
    "iso:country":"CA",
    "sg:address":"4520 39 St",
    "sg:city":"Camrose",
    "sg:classifiers":[
        {
            "category":"Retail",
            "subcategory":"Auto Repair",
            "type":"Services"
        }
    ],
    "sg:phone":"+1 780 672 9998",
    "sg:postcode":"T4V 2N5",
    "sg:province":"AB",
    "sg:tags":[
        "repairing",
        "automobile"
    ],
    "wof:name":"Denz Auto Repair",
    "wof:placetype":"venue"
},
  "geometry": {"coordinates":[-112.80659484900001,53.0123100281],"type":"Point"}
}