{
  "type": "Feature",
  "properties": {
    "addr:full":"346 Rue Hubert Greenfield Park QC J4V 1S2",
    "addr:housenumber":"346",
    "addr:postcode":"j4v 1s2",
    "addr:street":"Rue Hubert;Park",
    "iso:country":"CA",
    "sg:address":"346 Rue Hubert",
    "sg:city":"Greenfield Park",
    "sg:classifiers":[
        {
            "category":"Restaurant",
            "type":"Food & Drink"
        }
    ],
    "sg:phone":"+1 450 671 1380",
    "sg:postcode":"J4V 1S2",
    "sg:province":"QC",
    "sg:tags":[
        "cafeteria"
    ],
    "wof:name":"Compass Group Canada Ltd",
    "wof:placetype":"venue"
},
  "geometry": {"coordinates":[-73.4869308472,45.488735199],"type":"Point"}
}