{
  "type": "Feature",
  "properties": {
    "addr:full":"48 Broadway Corner Brook NL A2H 4C4",
    "addr:housenumber":"48",
    "addr:postcode":"a2h 4c4",
    "addr:street":"Broadway",
    "iso:country":"CA",
    "sg:address":"48 Broadway",
    "sg:city":"Corner Brook",
    "sg:classifiers":[
        {
            "category":"Shopping",
            "subcategory":"Gifts & Souvenirs",
            "type":"Retail Goods"
        }
    ],
    "sg:phone":"+1 709 632 7878",
    "sg:postcode":"A2H 4C4",
    "sg:province":"NL",
    "sg:tags":[
        "shop"
    ],
    "wof:name":"Jennifer's Gift & Flower Shop",
    "wof:placetype":"venue"
},
  "geometry": {"coordinates":[-57.9533233643,48.9504776001],"type":"Point"}
}