{
  "type": "Feature",
  "properties": {
    "iso:country":"CA",
    "sg:address":"1109 17 Ave SW #303",
    "sg:city":"Calgary",
    "sg:classifiers":[
        {
            "category":"Real Estate",
            "subcategory":"Real Estate Agent",
            "type":"Services"
        }
    ],
    "sg:phone":"+1 403 229 2711",
    "sg:postcode":"T2T 5R9",
    "sg:province":"AB",
    "sg:tags":[
        "management"
    ],
    "wof:name":"Prosperity Management Svc",
    "wof:placetype":"venue"
},
  "geometry": {"coordinates":[-114.087646484,51.0376853943],"type":"Point"}
}