{
  "type": "Feature",
  "properties": {
    "addr:full":"10 Canso Rd Etobicoke ON M9W 4L8",
    "addr:housenumber":"10",
    "addr:postcode":"m9w 4l8",
    "addr:street":"Canso Rd",
    "iso:country":"CA",
    "sg:address":"10 Canso Rd",
    "sg:city":"Etobicoke",
    "sg:classifiers":[
        {
            "category":"Manufacturing",
            "subcategory":"Food",
            "type":"Manufacturing & Wholesale Goods"
        }
    ],
    "sg:phone":"+1 416 245 1555",
    "sg:postcode":"M9W 4L8",
    "sg:province":"ON",
    "sg:tags":[
        "product",
        "manufacturer"
    ],
    "wof:name":"China Brands Food Products",
    "wof:placetype":"venue"
},
  "geometry": {"coordinates":[-79.56744399999999,43.698223],"type":"Point"}
}