{
  "type": "Feature",
  "properties": {
    "iso:country":"CA",
    "sg:address":"226 Bond St E",
    "sg:city":"Oshawa",
    "sg:classifiers":[
        {
            "category":"Recreation",
            "type":"Entertainment"
        }
    ],
    "sg:phone":"+1 905 728 6281",
    "sg:postcode":"L1G 1B5",
    "sg:province":"ON",
    "sg:tags":[
        "club",
        "curling",
        "hall",
        "auditorium"
    ],
    "wof:name":"Oshawa Curling Club",
    "wof:placetype":"venue"
},
  "geometry": {"coordinates":[-78.8554763794,43.9005661011],"type":"Point"}
}