{
  "type": "Feature",
  "properties": {
    "addr:full":"221 Av DE LA Friche Dolbeau-Mistassini QC G8L 3A7",
    "addr:housenumber":"221",
    "addr:postcode":"g8l 3a7",
    "addr:street":"Av De La Friche",
    "iso:country":"CA",
    "sg:address":"221 Av DE LA Friche",
    "sg:city":"Dolbeau-Mistassini",
    "sg:classifiers":[
        {
            "category":"Food & Beverages",
            "subcategory":"Groceries & Convenience Stores",
            "type":"Retail Goods"
        }
    ],
    "sg:phone":"+1 418 276 6400",
    "sg:postcode":"G8L 3A7",
    "sg:province":"QC",
    "wof:name":"Depanneur Des Veterans",
    "wof:placetype":"venue"
},
  "geometry": {"coordinates":[-72.219635,48.864365],"type":"Point"}
}