{
  "type": "Feature",
  "properties": {
    "addr:full":"Laurierville QC G0S 1P0",
    "addr:postcode":"g0s 1p0",
    "iso:country":"CA",
    "sg:city":"Laurierville",
    "sg:classifiers":[
        {
            "category":"Manufacturing",
            "subcategory":"Leather Goods",
            "type":"Manufacturing & Wholesale Goods"
        }
    ],
    "sg:phone":"+1 819 365 4256",
    "sg:postcode":"G0S 1P0",
    "sg:province":"QC",
    "wof:name":"Cuirs Mario Inc",
    "wof:placetype":"venue"
},
  "geometry": {"coordinates":[-71.660538,46.299179],"type":"Point"}
}