{
  "type": "Feature",
  "properties": {
    "addr:full":"11237 Sussex Pl Delta BC V4E 2J8",
    "addr:housenumber":"11237",
    "addr:postcode":"v4e 2j8",
    "addr:street":"Sussex Pl",
    "iso:country":"CA",
    "sg:address":"11237 Sussex Pl",
    "sg:city":"Delta",
    "sg:classifiers":[
        {
            "category":"Building & Trades",
            "subcategory":"Electrical",
            "type":"Services"
        }
    ],
    "sg:phone":"+1 604 572 7513",
    "sg:postcode":"V4E 2J8",
    "sg:province":"BC",
    "sg:tags":[
        "electric",
        "contractor"
    ],
    "wof:name":"South Hill Electric Ltd",
    "wof:placetype":"venue"
},
  "geometry": {"coordinates":[-122.911598,49.128525],"type":"Point"}
}