{
  "type": "Feature",
  "properties": {
    "addr:full":"9737 197B St Langley BC V1M 3G3",
    "addr:housenumber":"9737",
    "addr:postcode":"v1m 3g3",
    "addr:street":"197B St",
    "iso:country":"CA",
    "sg:address":"9737 197B St",
    "sg:city":"Langley",
    "sg:classifiers":[
        {
            "category":"Retail",
            "subcategory":"Auto Repair",
            "type":"Services"
        }
    ],
    "sg:phone":"+1 604 888 8788",
    "sg:postcode":"V1M 3G3",
    "sg:province":"BC",
    "sg:tags":[
        "truck"
    ],
    "wof:name":"Truck West Ltd",
    "wof:placetype":"venue"
},
  "geometry": {"coordinates":[-122.65657043500001,49.1041221619],"type":"Point"}
}