{
  "type": "Feature",
  "properties": {
    "addr:full":"275 Alexander St Vancouver BC V6A 1C2",
    "addr:housenumber":"275",
    "addr:postcode":"v6a 1c2",
    "addr:street":"Alexander St",
    "iso:country":"CA",
    "sg:address":"275 Alexander St",
    "sg:city":"Vancouver",
    "sg:classifiers":[
        {
            "category":"Museum",
            "type":"Entertainment"
        }
    ],
    "sg:phone":"+1 604 602 7682",
    "sg:postcode":"V6A 1C2",
    "sg:province":"BC",
    "sg:tags":[
        "organization",
        "arts",
        "information"
    ],
    "wof:name":"Core Artist Live Work CO-OP",
    "wof:placetype":"venue"
},
  "geometry": {"coordinates":[-123.09833526600001,49.2842483521],"type":"Point"}
}