{
  "type": "Feature",
  "properties": {
    "addr:full":"438 Edward St Hearst ON P0L 1N0",
    "addr:housenumber":"438",
    "addr:postcode":"p0l 1n0",
    "addr:street":"Edward St",
    "iso:country":"CA",
    "sg:address":"438 Edward St",
    "sg:city":"Hearst",
    "sg:classifiers":[
        {
            "category":"Wholesale",
            "subcategory":"Hardware",
            "type":"Manufacturing & Wholesale Goods"
        }
    ],
    "sg:phone":"+1 705 362 5984",
    "sg:postcode":"P0L 1N0",
    "sg:province":"ON",
    "sg:tags":[
        "tool"
    ],
    "wof:name":"Mac Tools",
    "wof:placetype":"venue"
},
  "geometry": {"coordinates":[-83.65568500000001,49.684334],"type":"Point"}
}