{
  "type": "Feature",
  "properties": {
    "addr:full":"105 Applefield Dr Scarborough ON M1P 3Y5",
    "addr:housenumber":"105",
    "addr:postcode":"m1p 3y5",
    "addr:street":"Applefield Dr",
    "iso:country":"CA",
    "sg:address":"105 Applefield Dr",
    "sg:city":"Scarborough",
    "sg:classifiers":[
        {
            "category":"Professional",
            "type":"Services"
        }
    ],
    "sg:phone":"+1 416 757 0888",
    "sg:postcode":"M1P 3Y5",
    "sg:province":"ON",
    "sg:tags":[
        "product",
        "ceramic",
        "establishment"
    ],
    "wof:name":"Sheppard Pearl Decor Ctr",
    "wof:placetype":"venue"
},
  "geometry": {"coordinates":[-79.262131,43.767235],"type":"Point"}
}