{
  "type": "Feature",
  "properties": {
    "addr:full":"7000 Ch DE LA Cote-DE-Liesse Saint-Laurent QC H4T 1E7",
    "addr:postcode":"7000;h4t 1e7",
    "addr:street":"Ch De La Cote-De-Liesse",
    "iso:country":"CA",
    "sg:address":"7000 Ch DE LA Cote-DE-Liesse",
    "sg:city":"Saint-Laurent",
    "sg:classifiers":[
        {
            "category":"Travel",
            "subcategory":"Travel Agent",
            "type":"Entertainment"
        }
    ],
    "sg:phone":"+1 514 731 3338",
    "sg:postcode":"H4T 1E7",
    "sg:province":"QC",
    "sg:tags":[
        "agency",
        "bureau"
    ],
    "wof:name":"Agence DE Voyage Time",
    "wof:placetype":"venue"
},
  "geometry": {"coordinates":[-73.69864699999999,45.480022],"type":"Point"}
}