{
  "type": "Feature",
  "properties": {
    "iso:country":"CA",
    "sg:address":"9665 Bayview Ave # 31",
    "sg:city":"Richmond Hill",
    "sg:classifiers":[
        {
            "category":"Professional",
            "subcategory":"Accounting & Tax Preparation",
            "type":"Services"
        }
    ],
    "sg:phone":"+1 905 780 9751",
    "sg:postcode":"L4C 9V4",
    "sg:province":"ON",
    "sg:tags":[
        "accountant"
    ],
    "wof:name":"Chan & Chow Chartered Accts",
    "wof:placetype":"venue"
},
  "geometry": {"coordinates":[-79.413269043,43.8677444458],"type":"Point"}
}