{
  "type": "Feature",
  "properties": {
    "addr:full":"High Prairie AB T0G 1E0",
    "addr:postcode":"t0g 1e0",
    "iso:country":"CA",
    "sg:city":"High Prairie",
    "sg:classifiers":[
        {
            "category":"Education",
            "subcategory":"School",
            "type":"Public Place"
        }
    ],
    "sg:phone":"+1 780 523 4418",
    "sg:postcode":"T0G 1E0",
    "sg:province":"AB",
    "wof:name":"Prairie River Jr High School",
    "wof:placetype":"venue"
},
  "geometry": {"coordinates":[-116.482018,55.429859],"type":"Point"}
}