{
  "type": "Feature",
  "properties": {
    "addr:full":"2601 Mcnicoll Ave Scarborough ON M1V 5N8",
    "addr:housenumber":"2601",
    "addr:postcode":"m1v 5n8",
    "addr:street":"Mcnicoll Ave",
    "iso:country":"CA",
    "sg:address":"2601 Mcnicoll Ave",
    "sg:city":"Scarborough",
    "sg:classifiers":[
        {
            "category":"Organizations",
            "subcategory":"Religious Organization",
            "type":"Services"
        }
    ],
    "sg:phone":"+1 416 293 5552",
    "sg:postcode":"M1V 5N8",
    "sg:province":"ON",
    "sg:tags":[
        "church"
    ],
    "wof:name":"Rosewood Baptist Church",
    "wof:placetype":"venue"
},
  "geometry": {"coordinates":[-79.29034423829999,43.8145713806],"type":"Point"}
}