{
  "type": "Feature",
  "properties": {
    "addr:full":"2044 Rue Metcalfe Montreal QC H3A 1X8",
    "addr:housenumber":"2044",
    "addr:postcode":"h3a 1x8",
    "addr:street":"Rue Metcalfe",
    "iso:country":"CA",
    "sg:address":"2044 Rue Metcalfe",
    "sg:city":"Montreal",
    "sg:classifiers":[
        {
            "category":"Shopping",
            "subcategory":"Music",
            "type":"Retail Goods"
        }
    ],
    "sg:phone":"+1 514 844 8988",
    "sg:postcode":"H3A 1X8",
    "sg:province":"QC",
    "sg:tags":[
        "compact",
        "record",
        "disc",
        "tape"
    ],
    "wof:name":"Cheap Thrills",
    "wof:placetype":"venue"
},
  "geometry": {"coordinates":[-73.5749511719,45.5019340515],"type":"Point"}
}