{
  "type": "Feature",
  "properties": {
    "addr:full":"152 Boul St-Pierre O Caraquet NB E1W 1B6",
    "addr:housenumber":"152",
    "addr:postcode":"e1w 1b6",
    "addr:street":"Boul St-Pierre O",
    "iso:country":"CA",
    "sg:address":"152 Boul St-Pierre O",
    "sg:city":"Caraquet",
    "sg:classifiers":[
        {
            "category":"Retail",
            "subcategory":"Auto Repair",
            "type":"Services"
        }
    ],
    "sg:phone":"+1 506 727 2212",
    "sg:postcode":"E1W 1B6",
    "sg:province":"NB",
    "sg:tags":[
        "repairing",
        "automobile"
    ],
    "wof:name":"Esso",
    "wof:placetype":"venue"
},
  "geometry": {"coordinates":[-64.917351,47.7948],"type":"Point"}
}