{
  "type": "Feature",
  "properties": {
    "iso:country":"CA",
    "sg:address":"236 Rue Picard",
    "sg:city":"Sainte-Croix",
    "sg:classifiers":[
        {
            "category":"Health Services",
            "subcategory":"Nursing And Care Facility",
            "type":"Services"
        }
    ],
    "sg:phone":"+1 418 926 2808",
    "sg:postcode":"G0S 2H0",
    "sg:province":"QC",
    "sg:tags":[
        "home",
        "retirement",
        "community"
    ],
    "wof:name":"Cite Des Etoiles Inc",
    "wof:placetype":"venue"
},
  "geometry": {"coordinates":[-71.7369689941,46.6212234497],"type":"Point"}
}