{
  "type": "Feature",
  "properties": {
    "iso:country":"CA",
    "sg:address":"195 College Ave W",
    "sg:city":"Guelph",
    "sg:classifiers":[
        {
            "category":"Education",
            "subcategory":"School",
            "type":"Public Place"
        }
    ],
    "sg:phone":"+1 519 824 5760",
    "sg:postcode":"N1G 1S6",
    "sg:province":"ON",
    "wof:name":"College Avenue Public School",
    "wof:placetype":"venue"
},
  "geometry": {"coordinates":[-80.24453,43.523552],"type":"Point"}
}