{
  "type": "Feature",
  "properties": {
    "addr:full":"Lake Charlotte NS B0J 1Y0",
    "addr:postcode":"b0j 1y0",
    "iso:country":"CA",
    "sg:city":"Lake Charlotte",
    "sg:classifiers":[
        {
            "category":"Organizations",
            "subcategory":"Professional Association",
            "type":"Services"
        }
    ],
    "sg:phone":"+1 902 845 2501",
    "sg:postcode":"B0J 1Y0",
    "sg:province":"NS",
    "wof:name":"Memory Lane Heritage Village",
    "wof:placetype":"venue"
},
  "geometry": {"coordinates":[-62.943611145,44.7676734924],"type":"Point"}
}