{
  "type": "Feature",
  "properties": {
    "addr:full":"612 Windmill Rd Dartmouth NS B3B 1B5",
    "addr:housenumber":"612",
    "addr:postcode":"b3b 1b5",
    "addr:street":"Windmill Rd",
    "iso:country":"CA",
    "sg:address":"612 Windmill Rd",
    "sg:city":"Dartmouth",
    "sg:classifiers":[
        {
            "category":"Restaurant",
            "type":"Food & Drink"
        }
    ],
    "sg:phone":"+1 902 468 1059",
    "sg:postcode":"B3B 1B5",
    "sg:province":"NS",
    "wof:name":"Brewdebakers",
    "wof:placetype":"venue"
},
  "geometry": {"coordinates":[-63.602776,44.697048],"type":"Point"}
}