{
  "type": "Feature",
  "properties": {
    "addr:full":"PO Box 1080 Valleyview AB T0H 3N0",
    "addr:housenumber":"po;1080",
    "addr:postcode":"ab t0h 3n0",
    "addr:street":"Box",
    "iso:country":"CA",
    "sg:address":"PO Box 1080",
    "sg:city":"Valleyview",
    "sg:classifiers":[
        {
            "category":"Mining & Drilling",
            "type":"Manufacturing & Wholesale Goods"
        }
    ],
    "sg:phone":"+1 780 524 3341",
    "sg:postcode":"T0H 3N0",
    "sg:province":"AB",
    "sg:tags":[
        "company",
        "oil"
    ],
    "wof:name":"Burlington Resources Canada",
    "wof:placetype":"venue"
},
  "geometry": {"coordinates":[-117.27177399999999,55.068642],"type":"Point"}
}