{
  "type": "Feature",
  "properties": {
    "addr:full":"9011 Commercial St New Minas NS B4N 3E3",
    "addr:housenumber":"9011",
    "addr:postcode":"b4n 3e3",
    "addr:street":"Commercial St",
    "iso:country":"CA",
    "sg:address":"9011 Commercial St",
    "sg:city":"New Minas",
    "sg:classifiers":[
        {
            "category":"Retail",
            "subcategory":"Laundry & Dry Cleaning",
            "type":"Services"
        }
    ],
    "sg:phone":"+1 902 681 0189",
    "sg:postcode":"B4N 3E3",
    "sg:province":"NS",
    "sg:tags":[
        "cleaners"
    ],
    "wof:name":"Vail's Laundry & Cleaners",
    "wof:placetype":"venue"
},
  "geometry": {"coordinates":[-64.4593505859,45.0680274963],"type":"Point"}
}