{
  "type": "Feature",
  "properties": {
    "iso:country":"CA",
    "sg:address":"9250 Av Du Parc # 518",
    "sg:city":"Montreal",
    "sg:classifiers":[
        {
            "category":"Shopping",
            "subcategory":"Clothing, Apparel, & Fashions",
            "type":"Retail Goods"
        }
    ],
    "sg:phone":"+1 514 382 0190",
    "sg:postcode":"H2N 1Z2",
    "sg:province":"QC",
    "sg:tags":[
        "suspender",
        "belt"
    ],
    "wof:name":"Mil-Idee Accessoires",
    "wof:placetype":"venue"
},
  "geometry": {"coordinates":[-73.6539,45.537895],"type":"Point"}
}