{
  "type": "Feature",
  "properties": {
    "addr:full":"3253 Kofoed Dr Thornhill BC V8G 3P8",
    "addr:housenumber":"3253",
    "addr:postcode":"v8g 3p8",
    "addr:street":"Kofoed Dr",
    "iso:country":"CA",
    "sg:address":"3253 Kofoed Dr",
    "sg:city":"Thornhill",
    "sg:classifiers":[
        {
            "category":"Retail",
            "subcategory":"Auto Repair",
            "type":"Services"
        }
    ],
    "sg:phone":"+1 250 635 6488",
    "sg:postcode":"V8G 3P8",
    "sg:province":"BC",
    "sg:tags":[
        "repairing",
        "automobile"
    ],
    "wof:name":"Auto Choice Mechanical",
    "wof:placetype":"venue"
},
  "geometry": {"coordinates":[-128.54368600000001,54.517441],"type":"Point"}
}