{
  "type": "Feature",
  "properties": {
    "addr:full":"21 Regan Rd # I Brampton ON L7A 1C5",
    "addr:housenumber":"21",
    "addr:postcode":"l7a 1c5",
    "addr:street":"Regan Rd # I",
    "iso:country":"CA",
    "sg:address":"21 Regan Rd # I",
    "sg:city":"Brampton",
    "sg:classifiers":[
        {
            "category":"Professional",
            "subcategory":"Management & Consulting",
            "type":"Services"
        }
    ],
    "sg:phone":"+1 905 846 9425",
    "sg:postcode":"L7A 1C5",
    "sg:province":"ON",
    "sg:tags":[
        "pipe"
    ],
    "wof:name":"Pharma Processing",
    "wof:placetype":"venue"
},
  "geometry": {"coordinates":[-79.8022079468,43.7020187378],"type":"Point"}
}