{
  "type": "Feature",
  "properties": {
    "addr:full":"208 Sask Ave E Outlook SK S0L 2N0",
    "addr:housenumber":"208",
    "addr:postcode":"s0l 2n0",
    "addr:street":"Sask Ave E Outlook",
    "iso:country":"CA",
    "sg:address":"208 Sask Ave E",
    "sg:city":"Outlook",
    "sg:classifiers":[
        {
            "category":"Retail",
            "subcategory":"Portrait Studio",
            "type":"Services"
        }
    ],
    "sg:phone":"+1 306 867 9684",
    "sg:postcode":"S0L 2N0",
    "sg:province":"SK",
    "sg:tags":[
        "picture",
        "frame",
        "photography"
    ],
    "wof:name":"Creatively Speaking Photo",
    "wof:placetype":"venue"
},
  "geometry": {"coordinates":[-107.05843400000001,51.487324],"type":"Point"}
}