{
  "type": "Feature",
  "properties": {
    "addr:full":"Oakville ON L6L 6L4",
    "addr:postcode":"l6l 6l4",
    "iso:country":"CA",
    "sg:city":"Oakville",
    "sg:classifiers":[
        {
            "category":"Retail",
            "subcategory":"Repair Shop",
            "type":"Services"
        }
    ],
    "sg:phone":"+1 905 827 2681",
    "sg:postcode":"L6L 6L4",
    "sg:province":"ON",
    "sg:tags":[
        "upholsterer"
    ],
    "wof:name":"Baier's Custom Upholstery",
    "wof:placetype":"venue"
},
  "geometry": {"coordinates":[-79.73136901860001,43.4130630493],"type":"Point"}
}