{
  "type": "Feature",
  "properties": {
    "addr:full":"643 Seymour St Kamloops BC V2C 2H1",
    "addr:housenumber":"643",
    "addr:postcode":"bc v2c 2h1",
    "addr:street":"Seymour St",
    "iso:country":"CA",
    "sg:address":"643 Seymour St",
    "sg:city":"Kamloops",
    "sg:classifiers":[
        {
            "category":"Professional",
            "subcategory":"Accounting & Tax Preparation",
            "type":"Services"
        }
    ],
    "sg:phone":"+1 250 372 3833",
    "sg:postcode":"V2C 2H1",
    "sg:province":"BC",
    "sg:tags":[
        "accountant"
    ],
    "wof:name":"Hartwick & CO",
    "wof:placetype":"venue"
},
  "geometry": {"coordinates":[-120.325829,50.674782],"type":"Point"}
}