{
  "type": "Feature",
  "properties": {
    "iso:country":"CA",
    "sg:address":"1104 1 Ave NE",
    "sg:city":"Calgary",
    "sg:classifiers":[
        {
            "category":"Food & Beverages",
            "subcategory":"Groceries & Convenience Stores",
            "type":"Retail Goods"
        }
    ],
    "sg:phone":"+1 403 269 2381",
    "sg:postcode":"T2E 0C8",
    "sg:province":"AB",
    "sg:tags":[
        "grocer"
    ],
    "wof:name":"North East Grocery & Confect",
    "wof:placetype":"venue"
},
  "geometry": {"coordinates":[-114.03711699999999,51.053432],"type":"Point"}
}