{
  "type": "Feature",
  "properties": {
    "addr:full":"1859 Welch St North Vancouver BC V7P 1B7",
    "addr:housenumber":"1859",
    "addr:postcode":"v7p 1b7",
    "addr:street":"Welch St",
    "iso:country":"CA",
    "sg:address":"1859 Welch St",
    "sg:city":"North Vancouver",
    "sg:classifiers":[
        {
            "category":"Professional",
            "subcategory":"Detective & Security Services",
            "type":"Services"
        }
    ],
    "sg:phone":"+1 604 253 6664",
    "sg:postcode":"V7P 1B7",
    "sg:province":"BC",
    "sg:tags":[
        "system"
    ],
    "wof:name":"Omni Security Systems Ltd",
    "wof:placetype":"venue"
},
  "geometry": {"coordinates":[-123.119628906,49.317527771],"type":"Point"}
}