{
  "type": "Feature",
  "properties": {
    "addr:full":"Parrsboro NS B0M 1S0",
    "addr:postcode":"b0m 1s0",
    "iso:country":"CA",
    "sg:city":"Parrsboro",
    "sg:classifiers":[
        {
            "category":"Restaurant",
            "type":"Food & Drink"
        }
    ],
    "sg:phone":"+1 902 254 3488",
    "sg:postcode":"B0M 1S0",
    "sg:province":"NS",
    "wof:name":"Glooscap Restaurant & Lounge",
    "wof:placetype":"venue"
},
  "geometry": {"coordinates":[-64.32634,45.404499],"type":"Point"}
}