{
  "type": "Feature",
  "properties": {
    "addr:full":"263 Queen St Port Perry ON L9L 1B9",
    "addr:housenumber":"263",
    "addr:postcode":"l9l 1b9",
    "addr:street":"Queen St",
    "iso:country":"CA",
    "sg:address":"263 Queen St",
    "sg:city":"Port Perry",
    "sg:classifiers":[
        {
            "category":"Wholesale",
            "subcategory":"Meat",
            "type":"Manufacturing & Wholesale Goods"
        }
    ],
    "sg:phone":"+1 905 985 1456",
    "sg:postcode":"L9L 1B9",
    "sg:province":"ON",
    "sg:tags":[
        "butchering"
    ],
    "wof:name":"Herrington Quality Butchers",
    "wof:placetype":"venue"
},
  "geometry": {"coordinates":[-78.9455566406,44.1043624878],"type":"Point"}
}