{
  "type": "Feature",
  "properties": {
    "addr:full":"92 Thornhill Dr Dartmouth NS B3B 1S3",
    "addr:housenumber":"92",
    "addr:postcode":"b3b 1s3",
    "addr:street":"Thornhill Dr",
    "iso:country":"CA",
    "sg:address":"92 Thornhill Dr",
    "sg:city":"Dartmouth",
    "sg:classifiers":[
        {
            "category":"Manufacturing",
            "subcategory":"Glass & Minerals",
            "type":"Manufacturing & Wholesale Goods"
        }
    ],
    "sg:phone":"+1 902 468 2945",
    "sg:postcode":"B3B 1S3",
    "sg:province":"NS",
    "sg:tags":[
        "granite",
        "marble"
    ],
    "wof:name":"Nova Tile & Marble Ltd",
    "wof:placetype":"venue"
},
  "geometry": {"coordinates":[-63.592556,44.695427],"type":"Point"}
}