{
  "type": "Feature",
  "properties": {
    "addr:full":"354 King St Midland ON L4R 3M8",
    "addr:housenumber":"354",
    "addr:postcode":"l4r 3m8",
    "addr:street":"King St",
    "iso:country":"CA",
    "sg:address":"354 King St",
    "sg:city":"Midland",
    "sg:classifiers":[
        {
            "category":"Home & Garden",
            "subcategory":"Furniture",
            "type":"Retail Goods"
        }
    ],
    "sg:phone":"+1 705 526 3058",
    "sg:postcode":"L4R 3M8",
    "sg:province":"ON",
    "sg:tags":[
        "mattress"
    ],
    "wof:name":"Maurice Mattress World",
    "wof:placetype":"venue"
},
  "geometry": {"coordinates":[-79.8837051392,44.7476425171],"type":"Point"}
}