{
  "type": "Feature",
  "properties": {
    "addr:full":"Mississauga ON L4W 2K5",
    "addr:postcode":"l4w 2k5",
    "iso:country":"CA",
    "sg:city":"Mississauga",
    "sg:classifiers":[
        {
            "category":"Retail",
            "subcategory":"Auto Repair",
            "type":"Services"
        }
    ],
    "sg:phone":"+1 905 670 4545",
    "sg:postcode":"L4W 2K5",
    "sg:province":"ON",
    "sg:tags":[
        "trailer"
    ],
    "wof:name":"Britannia Trailer Svc",
    "wof:placetype":"venue"
},
  "geometry": {"coordinates":[-79.63555100000001,43.662354],"type":"Point"}
}