{
  "type": "Feature",
  "properties": {
    "iso:country":"CA",
    "sg:address":"2980 Rue Gagnon",
    "sg:city":"Trois-Rivieres-Ouest",
    "sg:classifiers":[
        {
            "category":"Manufacturing",
            "subcategory":"Food",
            "type":"Manufacturing & Wholesale Goods"
        }
    ],
    "sg:phone":"+1 819 378 7887",
    "sg:postcode":"G8Z 4H3",
    "sg:province":"QC",
    "sg:tags":[
        "product",
        "seafood",
        "fish",
        "prepared"
    ],
    "wof:name":"Delices DE LA Mer Inc",
    "wof:placetype":"venue"
},
  "geometry": {"coordinates":[-72.59326934809999,46.3322525024],"type":"Point"}
}