{
  "type": "Feature",
  "properties": {
    "addr:full":"2111 100th St Tisdale SK S0E 1T0",
    "addr:housenumber":"2111",
    "addr:postcode":"s0e 1t0",
    "addr:street":"100Th St",
    "iso:country":"CA",
    "sg:address":"2111 100th St",
    "sg:city":"Tisdale",
    "sg:classifiers":[
        {
            "category":"Retail",
            "subcategory":"Auto Repair",
            "type":"Services"
        }
    ],
    "sg:phone":"+1 306 873 5566",
    "sg:postcode":"S0E 1T0",
    "sg:province":"SK",
    "sg:tags":[
        "repairing",
        "automobile"
    ],
    "wof:name":"Randall Automotive",
    "wof:placetype":"venue"
},
  "geometry": {"coordinates":[-104.045059204,52.8570213318],"type":"Point"}
}