{
  "type": "Feature",
  "properties": {
    "addr:full":"130 Highland Dr Port Hope ON L1A 2A3",
    "addr:housenumber":"130",
    "addr:postcode":"l1a 2a3",
    "addr:street":"Highland Dr",
    "iso:country":"CA",
    "sg:address":"130 Highland Dr",
    "sg:city":"Port Hope",
    "sg:classifiers":[
        {
            "category":"Social Services",
            "subcategory":"Child Care",
            "type":"Services"
        }
    ],
    "sg:phone":"+1 905 885 2637",
    "sg:postcode":"L1A 2A3",
    "sg:province":"ON",
    "wof:name":"Ganaraska Child Care Ctr Inc",
    "wof:placetype":"venue"
},
  "geometry": {"coordinates":[-78.306084,43.957764],"type":"Point"}
}