{
  "type": "Feature",
  "properties": {
    "addr:full":"2660 Agricola St Halifax NS B3K 4C9",
    "addr:housenumber":"2660",
    "addr:postcode":"b3k 4c9",
    "addr:street":"Agricola St",
    "iso:country":"CA",
    "sg:address":"2660 Agricola St",
    "sg:city":"Halifax",
    "sg:classifiers":[
        {
            "category":"Shopping",
            "subcategory":"Clothing, Apparel, & Fashions",
            "type":"Retail Goods"
        }
    ],
    "sg:phone":"+1 902 454 4330",
    "sg:postcode":"B3K 4C9",
    "sg:province":"NS",
    "sg:tags":[
        "salvage",
        "surplus",
        "merchandise"
    ],
    "wof:name":"Army Navy Store",
    "wof:placetype":"venue"
},
  "geometry": {"coordinates":[-63.594967,44.656258],"type":"Point"}
}