{
  "type": "Feature",
  "properties": {
    "iso:country":"CA",
    "sg:address":"6304 129 Ave NW",
    "sg:city":"Edmonton",
    "sg:classifiers":[
        {
            "category":"Health Services",
            "subcategory":"Doctor",
            "type":"Services"
        }
    ],
    "sg:phone":"+1 780 478 1031",
    "sg:postcode":"T5A 0G1",
    "sg:province":"AB",
    "sg:tags":[
        "physician",
        "surgeon"
    ],
    "wof:name":"Toane, E Benjamin MD",
    "wof:placetype":"venue"
},
  "geometry": {"coordinates":[-113.43840789799999,53.587726593],"type":"Point"}
}