{
  "type": "Feature",
  "properties": {
    "addr:full":"Hamilton ON L8P 1L2",
    "addr:postcode":"l8p 1l2",
    "iso:country":"CA",
    "sg:city":"Hamilton",
    "sg:classifiers":[
        {
            "category":"Restaurant",
            "type":"Food & Drink"
        }
    ],
    "sg:phone":"+1 905 523 0240",
    "sg:postcode":"L8P 1L2",
    "sg:province":"ON",
    "sg:tags":[
        "cafe",
        "caterer"
    ],
    "wof:name":"Petit Cafe",
    "wof:placetype":"venue"
},
  "geometry": {"coordinates":[-79.870796,43.254784],"type":"Point"}
}