{
  "type": "Feature",
  "properties": {
    "addr:full":"1288 Highbury Ave N London ON N5Y 1B4",
    "addr:housenumber":"1288",
    "addr:postcode":"n5y 1b4",
    "addr:street":"Highbury Ave N",
    "iso:country":"CA",
    "sg:address":"1288 Highbury Ave N",
    "sg:city":"London",
    "sg:classifiers":[
        {
            "category":"Health Services",
            "subcategory":"Clinic",
            "type":"Services"
        }
    ],
    "sg:phone":"+1 519 453 7041",
    "sg:postcode":"N5Y 1B4",
    "sg:province":"ON",
    "sg:tags":[
        "holistic",
        "practitioner"
    ],
    "wof:name":"Get Well Stay Well",
    "wof:placetype":"venue"
},
  "geometry": {"coordinates":[-81.215675354,43.0205497742],"type":"Point"}
}