{
  "type": "Feature",
  "properties": {
    "iso:country":"CA",
    "sg:address":"66 Morrow Rd",
    "sg:city":"Barrie",
    "sg:classifiers":[
        {
            "category":"Wholesale",
            "subcategory":"Machinery & Supplies",
            "type":"Manufacturing & Wholesale Goods"
        }
    ],
    "sg:phone":"+1 705 733 3787",
    "sg:postcode":"L4N 3V8",
    "sg:province":"ON",
    "sg:tags":[
        "fuel",
        "equipment",
        "injection"
    ],
    "wof:name":"Derek's Diesel Svc Inc",
    "wof:placetype":"venue"
},
  "geometry": {"coordinates":[-79.70320129389999,44.3621177673],"type":"Point"}
}