{
  "type": "Feature",
  "properties": {
    "addr:full":"701 Queen St W Toronto ON M6J 1E6",
    "addr:housenumber":"701",
    "addr:postcode":"m6j 1e6",
    "addr:street":"Queen St W",
    "iso:country":"CA",
    "sg:address":"701 Queen St W",
    "sg:city":"Toronto",
    "sg:classifiers":[
        {
            "category":"Shopping",
            "subcategory":"Books",
            "type":"Retail Goods"
        }
    ],
    "sg:phone":"+1 416 504 7934",
    "sg:postcode":"M6J 1E6",
    "sg:province":"ON",
    "sg:tags":[
        "miscellaneous",
        "store"
    ],
    "wof:name":"Come As You Are",
    "wof:placetype":"venue"
},
  "geometry": {"coordinates":[-79.405632,43.646729],"type":"Point"}
}