{
  "type": "Feature",
  "properties": {
    "addr:full":"2656 Rue DE Cadillac Montreal QC H1N 2V3",
    "addr:housenumber":"2656",
    "addr:postcode":"h1n 2v3",
    "addr:street":"Rue De Cadillac",
    "iso:country":"CA",
    "sg:address":"2656 Rue DE Cadillac",
    "sg:city":"Montreal",
    "sg:classifiers":[
        {
            "category":"Food & Beverages",
            "subcategory":"Groceries & Convenience Stores",
            "type":"Retail Goods"
        }
    ],
    "sg:phone":"+1 514 259 3638",
    "sg:postcode":"H1N 2V3",
    "sg:province":"QC",
    "sg:tags":[
        "grocer"
    ],
    "wof:name":"Epicerie Gibeau Inc",
    "wof:placetype":"venue"
},
  "geometry": {"coordinates":[-73.5382843018,45.573928833],"type":"Point"}
}