{
  "type": "Feature",
  "properties": {
    "addr:full":"7020 Francis Rd # 110 Richmond BC V6Y 1A2",
    "addr:housenumber":"7020;110",
    "addr:postcode":"v6y 1a2",
    "addr:street":"Francis Rd #",
    "iso:country":"CA",
    "sg:address":"7020 Francis Rd # 110",
    "sg:city":"Richmond",
    "sg:classifiers":[
        {
            "category":"Retail",
            "subcategory":"Laundry & Dry Cleaning",
            "type":"Services"
        }
    ],
    "sg:phone":"+1 604 241 4304",
    "sg:postcode":"V6Y 1A2",
    "sg:province":"BC",
    "sg:tags":[
        "cleaners"
    ],
    "wof:name":"Chateau Quality Drycleaners",
    "wof:placetype":"venue"
},
  "geometry": {"coordinates":[-123.14716300000001,49.148094],"type":"Point"}
}