{
  "type": "Feature",
  "properties": {
    "addr:full":"9600 Rue Main Richibucto NB E4W 4E6",
    "addr:housenumber":"9600",
    "addr:postcode":"e4w 4e6",
    "addr:street":"Rue Main",
    "iso:country":"CA",
    "sg:address":"9600 Rue Main",
    "sg:city":"Richibucto",
    "sg:classifiers":[
        {
            "category":"Banks & Credit Unions",
            "subcategory":"Financial Services",
            "type":"Services"
        }
    ],
    "sg:phone":"+1 506 523 9283",
    "sg:postcode":"E4W 4E6",
    "sg:province":"NB",
    "sg:tags":[
        "franchising"
    ],
    "wof:name":"Pizza Shack Holdings Inc",
    "wof:placetype":"venue"
},
  "geometry": {"coordinates":[-64.875542,46.699299],"type":"Point"}
}