{
  "type": "Feature",
  "properties": {
    "addr:full":"850 23 Ave NW Edmonton AB T6T 1J1",
    "addr:postcode":"850;t6t 1j1",
    "addr:street":"23 Ave Nw",
    "iso:country":"CA",
    "sg:address":"850 23 Ave NW",
    "sg:city":"Edmonton",
    "sg:classifiers":[
        {
            "category":"Farming",
            "subcategory":"Nursery",
            "type":"Manufacturing & Wholesale Goods"
        }
    ],
    "sg:phone":"+1 780 440 3053",
    "sg:postcode":"T6T 1J1",
    "sg:province":"AB",
    "sg:tags":[
        "greenhouse"
    ],
    "wof:name":"Bonnie Doon Flowers Grdn Ctr",
    "wof:placetype":"venue"
},
  "geometry": {"coordinates":[-113.493469,53.453999],"type":"Point"}
}