{
  "type": "Feature",
  "properties": {
    "addr:full":"17 Hamilton St Bayfield ON N0M 1G0",
    "addr:housenumber":"17",
    "addr:postcode":"n0m 1g0",
    "addr:street":"Hamilton St",
    "iso:country":"CA",
    "sg:address":"17 Hamilton St",
    "sg:city":"Bayfield",
    "sg:classifiers":[
        {
            "category":"Building & Trades",
            "subcategory":"Plumbing",
            "type":"Services"
        }
    ],
    "sg:phone":"+1 519 565 2420",
    "sg:postcode":"N0M 1G0",
    "sg:province":"ON",
    "sg:tags":[
        "contractor"
    ],
    "wof:name":"Berard Wade Plumbing",
    "wof:placetype":"venue"
},
  "geometry": {"coordinates":[-81.7020111084,43.5548820496],"type":"Point"}
}