{
  "type": "Feature",
  "properties": {
    "iso:country":"CA",
    "sg:city":"Holstein",
    "sg:classifiers":[
        {
            "category":"Banks & Credit Unions",
            "subcategory":"Bank",
            "type":"Services"
        }
    ],
    "sg:phone":"+1 519 334 3460",
    "sg:postcode":"N0G 2A0",
    "sg:province":"ON",
    "wof:name":"Saugeen Community Credit Union",
    "wof:placetype":"venue"
},
  "geometry": {"coordinates":[-80.75997161870001,44.0601463318],"type":"Point"}
}