{
  "type": "Feature",
  "properties": {
    "addr:full":"507 Chebucto St Baddeck NS B0E 1B0",
    "addr:housenumber":"507",
    "addr:postcode":"b0e 1b0",
    "addr:street":"Chebucto St",
    "iso:country":"CA",
    "sg:address":"507 Chebucto St",
    "sg:city":"Baddeck",
    "sg:classifiers":[
        {
            "category":"Shopping",
            "subcategory":"Gifts & Souvenirs",
            "type":"Retail Goods"
        }
    ],
    "sg:phone":"+1 902 295 3424",
    "sg:postcode":"B0E 1B0",
    "sg:province":"NS",
    "sg:tags":[
        "shop"
    ],
    "wof:name":"Blue Heron Gift Shop",
    "wof:placetype":"venue"
},
  "geometry": {"coordinates":[-60.748856,46.101013],"type":"Point"}
}