{
  "type": "Feature",
  "properties": {
    "iso:country":"CA",
    "sg:address":"500 Rue Mcdougall",
    "sg:city":"Trois-Rivieres",
    "sg:classifiers":[
        {
            "category":"Retail",
            "subcategory":"Auto Repair",
            "type":"Services"
        }
    ],
    "sg:phone":"+1 819 378 0888",
    "sg:postcode":"G9A 2T3",
    "sg:province":"QC",
    "sg:tags":[
        "repairing",
        "automobile"
    ],
    "wof:name":"Mecanique Mc Dougall",
    "wof:placetype":"venue"
},
  "geometry": {"coordinates":[-72.547691,46.3368],"type":"Point"}
}