{
  "type": "Feature",
  "properties": {
    "iso:country":"CA",
    "sg:city":"Erin",
    "sg:classifiers":[
        {
            "category":"Shopping",
            "subcategory":"Computers & Home Electronics",
            "type":"Retail Goods"
        }
    ],
    "sg:phone":"+1 519 833 2900",
    "sg:postcode":"N0B 1T0",
    "sg:province":"ON",
    "sg:tags":[
        "equipment",
        "dealer"
    ],
    "wof:name":"Avax International",
    "wof:placetype":"venue"
},
  "geometry": {"coordinates":[-80.07666778559999,43.7815246582],"type":"Point"}
}