{
  "type": "Feature",
  "properties": {
    "addr:full":"Saskatoon SK S7K 4H9",
    "addr:postcode":"s7k 4h9",
    "iso:country":"CA",
    "sg:city":"Saskatoon",
    "sg:classifiers":[
        {
            "category":"Banks & Credit Unions",
            "subcategory":"Investment Brokerage",
            "type":"Services"
        }
    ],
    "sg:phone":"+1 306 665 3244",
    "sg:postcode":"S7K 4H9",
    "sg:province":"SK",
    "sg:tags":[
        "consultant",
        "planning",
        "financial"
    ],
    "wof:name":"Assante Financial Ltd",
    "wof:placetype":"venue"
},
  "geometry": {"coordinates":[-106.659957886,52.1247596741],"type":"Point"}
}