{
  "type": "Feature",
  "properties": {
    "addr:full":"Victoria BC V8P 2J9",
    "addr:postcode":"v8p 2j9",
    "iso:country":"CA",
    "sg:city":"Victoria",
    "sg:classifiers":[
        {
            "category":"Organizations",
            "subcategory":"Religious Organization",
            "type":"Services"
        }
    ],
    "sg:phone":"+1 250 384 7757",
    "sg:postcode":"V8P 2J9",
    "sg:province":"BC",
    "sg:tags":[
        "church"
    ],
    "wof:name":"St Peter's Anglican Church",
    "wof:placetype":"venue"
},
  "geometry": {"coordinates":[-123.364517212,48.428314209],"type":"Point"}
}