{
  "type": "Feature",
  "properties": {
    "addr:full":"Cassils Rd & 12 St W Brooks AB T1R 1C6",
    "addr:postcode":"ab t1r 1c6",
    "addr:street":"Cassils Rd & 12 St W Brooks",
    "iso:country":"CA",
    "sg:address":"Cassils Rd & 12 St W",
    "sg:city":"Brooks",
    "sg:classifiers":[
        {
            "category":"Retail",
            "subcategory":"Veterinary Services",
            "type":"Services"
        }
    ],
    "sg:phone":"+1 403 362 6876",
    "sg:postcode":"T1R 1C6",
    "sg:province":"AB",
    "sg:tags":[
        "veterinarian"
    ],
    "wof:name":"Brooks Veterinary Clinic",
    "wof:placetype":"venue"
},
  "geometry": {"coordinates":[-111.91976928699999,50.572101593],"type":"Point"}
}