{
  "type": "Feature",
  "properties": {
    "addr:full":"87 Canning St Lanark ON K0G 1K0",
    "addr:housenumber":"87",
    "addr:postcode":"k0g 1k0",
    "addr:street":"Canning St",
    "iso:country":"CA",
    "sg:address":"87 Canning St",
    "sg:city":"Lanark",
    "sg:classifiers":[
        {
            "category":"Personal",
            "subcategory":"Beauty Salon",
            "type":"Services"
        }
    ],
    "sg:phone":"+1 613 259 5610",
    "sg:postcode":"K0G 1K0",
    "sg:province":"ON",
    "wof:name":"Shirley's Beauty Nook",
    "wof:placetype":"venue"
},
  "geometry": {"coordinates":[-76.3635482788,45.0211029053],"type":"Point"}
}