{
  "type": "Feature",
  "properties": {
    "iso:country":"CA",
    "sg:city":"Medicine Hat",
    "sg:classifiers":[
        {
            "category":"Banks & Credit Unions",
            "subcategory":"Bank",
            "type":"Services"
        }
    ],
    "sg:phone":"+1 403 528 6145",
    "sg:postcode":"T1B 2R4",
    "sg:province":"AB",
    "wof:name":"Cibc",
    "wof:placetype":"venue"
},
  "geometry": {"coordinates":[-110.647041321,50.007183075],"type":"Point"}
}