{
  "type": "Feature",
  "properties": {
    "addr:full":"55 Main St Petitcodiac NB E4Z 4L9",
    "addr:housenumber":"55",
    "addr:postcode":"e4z 4l9",
    "addr:street":"Main St",
    "iso:country":"CA",
    "sg:address":"55 Main St",
    "sg:city":"Petitcodiac",
    "sg:classifiers":[
        {
            "category":"Shopping",
            "subcategory":"Catalog Store",
            "type":"Retail Goods"
        }
    ],
    "sg:phone":"+1 506 756 3323",
    "sg:postcode":"E4Z 4L9",
    "sg:province":"NB",
    "sg:tags":[
        "mail",
        "order",
        "internet"
    ],
    "wof:name":"Sears Canada Inc",
    "wof:placetype":"venue"
},
  "geometry": {"coordinates":[-65.17681899999999,45.930889],"type":"Point"}
}