{
  "type": "Feature",
  "properties": {
    "addr:full":"5343 Rue Sherbrooke O Montreal QC H4A 1V2",
    "addr:housenumber":"5343",
    "addr:postcode":"h4a 1v2",
    "addr:street":"Rue Sherbrooke O",
    "iso:country":"CA",
    "sg:address":"5343 Rue Sherbrooke O",
    "sg:city":"Montreal",
    "sg:classifiers":[
        {
            "category":"Shopping",
            "subcategory":"Clothing, Apparel, & Fashions",
            "type":"Retail Goods"
        }
    ],
    "sg:phone":"+1 514 488 1553",
    "sg:postcode":"H4A 1V2",
    "sg:province":"QC",
    "sg:tags":[
        "fur",
        "business"
    ],
    "wof:name":"Elite Suede",
    "wof:placetype":"venue"
},
  "geometry": {"coordinates":[-73.55192565919999,45.5695877075],"type":"Point"}
}