{
  "type": "Feature",
  "properties": {
    "addr:full":"Williams Lake BC V2G 3A7",
    "addr:postcode":"bc v2g 3a7",
    "iso:country":"CA",
    "sg:city":"Williams Lake",
    "sg:classifiers":[
        {
            "category":"Freight",
            "type":"Transportation"
        }
    ],
    "sg:phone":"+1 250 398 5984",
    "sg:postcode":"V2G 3A7",
    "sg:province":"BC",
    "sg:tags":[
        "trucking"
    ],
    "wof:name":"Delann Enterprises Ltd",
    "wof:placetype":"venue"
},
  "geometry": {"coordinates":[-122.12309999999999,52.114937],"type":"Point"}
}