{
  "type": "Feature",
  "properties": {
    "addr:full":"310 2nd Ave E Vancouver BC V5T 1C1",
    "addr:housenumber":"310",
    "addr:postcode":"v5t 1c1",
    "addr:street":"2Nd Ave E",
    "iso:country":"CA",
    "sg:address":"310 2nd Ave E",
    "sg:city":"Vancouver",
    "sg:classifiers":[
        {
            "category":"Retail",
            "subcategory":"Auto Repair",
            "type":"Services"
        }
    ],
    "sg:phone":"+1 604 876 9030",
    "sg:postcode":"V5T 1C1",
    "sg:province":"BC",
    "sg:tags":[
        "body",
        "automobile",
        "painting"
    ],
    "wof:name":"Dave Koby Collision",
    "wof:placetype":"venue"
},
  "geometry": {"coordinates":[-123.097824,49.267437],"type":"Point"}
}