{
  "type": "Feature",
  "properties": {
    "iso:country":"CA",
    "sg:address":"310 Neptune Cres",
    "sg:city":"London",
    "sg:classifiers":[
        {
            "category":"Wholesale",
            "subcategory":"Machinery & Supplies",
            "type":"Manufacturing & Wholesale Goods"
        }
    ],
    "sg:phone":"+1 519 451 7729",
    "sg:postcode":"N6M 1A1",
    "sg:province":"ON",
    "sg:tags":[
        "valve"
    ],
    "wof:name":"Crane Supply",
    "wof:placetype":"venue"
},
  "geometry": {"coordinates":[-81.137589,42.990349],"type":"Point"}
}