{
  "type": "Feature",
  "properties": {
    "addr:full":"310 Neptune Cres London ON N6M 1A1",
    "addr:housenumber":"310",
    "addr:postcode":"n6m 1a1",
    "addr:street":"Neptune Cres",
    "iso:country":"CA",
    "sg:address":"310 Neptune Cres",
    "sg:city":"London",
    "sg:classifiers":[
        {
            "category":"Wholesale",
            "subcategory":"Machinery & Supplies",
            "type":"Manufacturing & Wholesale Goods"
        }
    ],
    "sg:phone":"+1 519 451 7729",
    "sg:postcode":"N6M 1A1",
    "sg:province":"ON",
    "sg:tags":[
        "valve"
    ],
    "wof:name":"Crane Supply",
    "wof:placetype":"venue"
},
  "geometry": {"coordinates":[-81.13758900000001,42.990349],"type":"Point"}
}