{
  "type": "Feature",
  "properties": {
    "addr:full":"126 Industrial Rd Whitehorse YT Y1A 2T9",
    "addr:housenumber":"126",
    "addr:postcode":"y1a 2t9",
    "addr:street":"Industrial Rd",
    "iso:country":"CA",
    "sg:address":"126 Industrial Rd",
    "sg:city":"Whitehorse",
    "sg:classifiers":[
        {
            "category":"Wholesale",
            "subcategory":"Machinery & Supplies",
            "type":"Manufacturing & Wholesale Goods"
        }
    ],
    "sg:phone":"+1 867 667 6241",
    "sg:postcode":"Y1A 2T9",
    "sg:province":"YT",
    "sg:tags":[
        "equipment",
        "industrial",
        "clothing",
        "safety"
    ],
    "wof:name":"Yukon Explosives Ltd",
    "wof:placetype":"venue"
},
  "geometry": {"coordinates":[-135.07554626500001,60.7363357544],"type":"Point"}
}