{
  "type": "Feature",
  "properties": {
    "addr:full":"200 Saskatchewan Ave E Outlook SK S0L 2N0",
    "addr:housenumber":"200",
    "addr:postcode":"s0l 2n0",
    "addr:street":"Saskatchewan Ave E Outlook",
    "iso:country":"CA",
    "sg:address":"200 Saskatchewan Ave E",
    "sg:city":"Outlook",
    "sg:classifiers":[
        {
            "category":"Personal",
            "subcategory":"Beauty Salon",
            "type":"Services"
        }
    ],
    "sg:phone":"+1 306 867 8972",
    "sg:postcode":"S0L 2N0",
    "sg:province":"SK",
    "wof:name":"Cropper's Hair Designs",
    "wof:placetype":"venue"
},
  "geometry": {"coordinates":[-107.056808472,51.4881286621],"type":"Point"}
}