{
  "type": "Feature",
  "properties": {
    "addr:full":"1824 Rue Belanger Montreal QC H2G 1B4",
    "addr:housenumber":"1824",
    "addr:postcode":"h2g 1b4",
    "addr:street":"Rue Belanger",
    "iso:country":"CA",
    "sg:address":"1824 Rue Belanger",
    "sg:city":"Montreal",
    "sg:classifiers":[
        {
            "category":"Wholesale",
            "subcategory":"Meat",
            "type":"Manufacturing & Wholesale Goods"
        }
    ],
    "sg:phone":"+1 514 728 3681",
    "sg:postcode":"H2G 1B4",
    "sg:province":"QC",
    "sg:tags":[
        "butchering"
    ],
    "wof:name":"Viandes Mammola Inc",
    "wof:placetype":"venue"
},
  "geometry": {"coordinates":[-73.6031265259,45.5465812683],"type":"Point"}
}