{
  "type": "Feature",
  "properties": {
    "addr:full":"442 Bristol Rd W Mississauga ON L5R 2J6",
    "addr:housenumber":"442",
    "addr:postcode":"l5r 2j6",
    "addr:street":"Bristol Rd W",
    "iso:country":"CA",
    "sg:address":"442 Bristol Rd W",
    "sg:city":"Mississauga",
    "sg:classifiers":[
        {
            "category":"Real Estate",
            "subcategory":"Surveying",
            "type":"Services"
        }
    ],
    "sg:phone":"+1 905 890 9225",
    "sg:postcode":"L5R 2J6",
    "sg:province":"ON",
    "sg:tags":[
        "surveyor"
    ],
    "wof:name":"Tony Stauskas Surveying Inc",
    "wof:placetype":"venue"
},
  "geometry": {"coordinates":[-79.67029599999999,43.603897],"type":"Point"}
}