{
  "type": "Feature",
  "properties": {
    "addr:full":"2701 John St Markham ON L3R 2W5",
    "addr:housenumber":"2701",
    "addr:postcode":"l3r 2w5",
    "addr:street":"John St",
    "iso:country":"CA",
    "sg:address":"2701 John St",
    "sg:city":"Markham",
    "sg:classifiers":[
        {
            "category":"Manufacturing",
            "subcategory":"Electronics",
            "type":"Manufacturing & Wholesale Goods"
        }
    ],
    "sg:phone":"+1 905 479 9515",
    "sg:postcode":"L3R 2W5",
    "sg:province":"ON",
    "sg:tags":[
        "printed",
        "circuit",
        "etched"
    ],
    "wof:name":"Crest Circuit CO Ltd",
    "wof:placetype":"venue"
},
  "geometry": {"coordinates":[-79.35767364500001,43.8249092102],"type":"Point"}
}