{
  "type": "Feature",
  "properties": {
    "iso:country":"CA",
    "sg:address":"319 Worthington St E",
    "sg:city":"North Bay",
    "sg:classifiers":[
        {
            "category":"Health Services",
            "subcategory":"Doctor",
            "type":"Services"
        }
    ],
    "sg:phone":"+1 705 474 0655",
    "sg:postcode":"P1B 1H2",
    "sg:province":"ON",
    "sg:tags":[
        "dentist"
    ],
    "wof:name":"Family Dental Office",
    "wof:placetype":"venue"
},
  "geometry": {"coordinates":[-79.459305,46.308208],"type":"Point"}
}