{
  "type": "Feature",
  "properties": {
    "iso:country":"CA",
    "sg:address":"4570 Yonge St",
    "sg:city":"North York",
    "sg:classifiers":[
        {
            "category":"Real Estate",
            "subcategory":"Developer",
            "type":"Services"
        }
    ],
    "sg:phone":"+1 416 225 3345",
    "sg:postcode":"M2N 5L6",
    "sg:province":"ON",
    "sg:tags":[
        "cemetery",
        "mausoleum"
    ],
    "wof:name":"Forest Lawn Mausoleum",
    "wof:placetype":"venue"
},
  "geometry": {"coordinates":[-79.4097442627,43.7564544678],"type":"Point"}
}