{
  "type": "Feature",
  "properties": {
    "addr:full":"Toronto ON M6E 1B5",
    "addr:postcode":"m6e 1b5",
    "iso:country":"CA",
    "sg:city":"Toronto",
    "sg:classifiers":[
        {
            "category":"Health Services",
            "subcategory":"Optometrist",
            "type":"Services"
        }
    ],
    "sg:phone":"+1 416 656 3580",
    "sg:postcode":"M6E 1B5",
    "sg:province":"ON",
    "wof:name":"Militello, J OD",
    "wof:placetype":"venue"
},
  "geometry": {"coordinates":[-79.444275,43.677528],"type":"Point"}
}