{
  "type": "Feature",
  "properties": {
    "addr:full":"Two Hills AB T0B 4K0",
    "addr:postcode":"t0b 4k0",
    "iso:country":"CA",
    "sg:city":"Two Hills",
    "sg:classifiers":[
        {
            "category":"Shopping",
            "subcategory":"Catalog Store",
            "type":"Retail Goods"
        }
    ],
    "sg:phone":"+1 780 657 3355",
    "sg:postcode":"T0B 4K0",
    "sg:province":"AB",
    "sg:tags":[
        "mail",
        "order",
        "internet"
    ],
    "wof:name":"Sears Canada Inc",
    "wof:placetype":"venue"
},
  "geometry": {"coordinates":[-111.746665955,53.7160110474],"type":"Point"}
}