{
  "type": "Feature",
  "properties": {
    "addr:full":"58 Faywood Blvd North York ON M3H 2X2",
    "addr:housenumber":"58",
    "addr:postcode":"m3h 2x2",
    "addr:street":"Faywood Blvd",
    "iso:country":"CA",
    "sg:address":"58 Faywood Blvd",
    "sg:city":"North York",
    "sg:classifiers":[
        {
            "category":"Social Services",
            "type":"Services"
        }
    ],
    "sg:phone":"+1 416 398 4182",
    "sg:postcode":"M3H 2X2",
    "sg:province":"ON",
    "sg:tags":[
        "organization",
        "welfare"
    ],
    "wof:name":"Christian Horizons",
    "wof:placetype":"venue"
},
  "geometry": {"coordinates":[-79.447266,43.737411],"type":"Point"}
}