{
  "type": "Feature",
  "properties": {
    "addr:full":"6482 Chebucto Rd Halifax NS B3L 1L5",
    "addr:housenumber":"6482",
    "addr:postcode":"b3l 1l5",
    "addr:street":"Chebucto Rd",
    "iso:country":"CA",
    "sg:address":"6482 Chebucto Rd",
    "sg:city":"Halifax",
    "sg:classifiers":[
        {
            "category":"Autos & Motor Vehicles",
            "subcategory":"Fuel & Gas Station",
            "type":"Retail Goods"
        }
    ],
    "sg:phone":"+1 902 420 0311",
    "sg:postcode":"B3L 1L5",
    "sg:province":"NS",
    "sg:tags":[
        "oil"
    ],
    "wof:name":"Chebucto Road Ultramar",
    "wof:placetype":"venue"
},
  "geometry": {"coordinates":[-63.604889,44.648029],"type":"Point"}
}