{
  "type": "Feature",
  "properties": {
    "addr:full":"2980 Rue Diab Saint-Laurent QC H4S 1M7",
    "addr:housenumber":"2980",
    "addr:postcode":"h4s 1m7",
    "addr:street":"Rue Diab",
    "iso:country":"CA",
    "sg:address":"2980 Rue Diab",
    "sg:city":"Saint-Laurent",
    "sg:classifiers":[
        {
            "category":"Manufacturing",
            "subcategory":"Electronics",
            "type":"Manufacturing & Wholesale Goods"
        }
    ],
    "sg:phone":"+1 514 335 3434",
    "sg:postcode":"H4S 1M7",
    "sg:province":"QC",
    "sg:tags":[
        "semiconductor",
        "devices"
    ],
    "wof:name":"Progressive Technologies",
    "wof:placetype":"venue"
},
  "geometry": {"coordinates":[-73.750336,45.496231],"type":"Point"}
}