{
  "type": "Feature",
  "properties": {
    "addr:full":"256 Main St Cardston AB T0K 0K0",
    "addr:housenumber":"256",
    "addr:postcode":"t0k 0k0",
    "addr:street":"Main St",
    "iso:country":"CA",
    "sg:address":"256 Main St",
    "sg:city":"Cardston",
    "sg:classifiers":[
        {
            "category":"Home & Garden",
            "subcategory":"Building Materials",
            "type":"Retail Goods"
        }
    ],
    "sg:phone":"+1 403 653 3043",
    "sg:postcode":"T0K 0K0",
    "sg:province":"AB",
    "sg:tags":[
        "glass",
        "window",
        "plate"
    ],
    "wof:name":"Glass 2-U",
    "wof:placetype":"venue"
},
  "geometry": {"coordinates":[-113.301559,49.199917],"type":"Point"}
}