{
  "type": "Feature",
  "properties": {
    "addr:full":"7 Kelwood Dr Napanee ON K7R 4A1",
    "addr:housenumber":"7",
    "addr:postcode":"k7r 4a1",
    "addr:street":"Kelwood Dr",
    "iso:country":"CA",
    "sg:address":"7 Kelwood Dr",
    "sg:city":"Napanee",
    "sg:classifiers":[
        {
            "category":"Manufacturing",
            "subcategory":"Metals",
            "type":"Manufacturing & Wholesale Goods"
        }
    ],
    "sg:phone":"+1 613 354 6621",
    "sg:postcode":"K7R 4A1",
    "sg:province":"ON",
    "sg:tags":[
        "machine",
        "shop"
    ],
    "wof:name":"G T Machining & Fabricating",
    "wof:placetype":"venue"
},
  "geometry": {"coordinates":[-76.9580383301,44.2633476257],"type":"Point"}
}