{
  "type": "Feature",
  "properties": {
    "addr:full":"18 Jade Cres Woodbridge ON L4L 6L5",
    "addr:housenumber":"18",
    "addr:postcode":"l4l 6l5",
    "addr:street":"Jade Cres",
    "iso:country":"CA",
    "sg:address":"18 Jade Cres",
    "sg:city":"Woodbridge",
    "sg:classifiers":[
        {
            "category":"Building & Trades",
            "subcategory":"Construction",
            "type":"Services"
        }
    ],
    "sg:phone":"+1 905 850 1310",
    "sg:postcode":"L4L 6L5",
    "sg:province":"ON",
    "sg:tags":[
        "general",
        "contractor"
    ],
    "wof:name":"Gibert Construction Ltd",
    "wof:placetype":"venue"
},
  "geometry": {"coordinates":[-79.6188659668,43.7876167297],"type":"Point"}
}