{
  "type": "Feature",
  "properties": {
    "addr:full":"480 Fisher St North Bay ON P1B 9M9",
    "addr:housenumber":"480",
    "addr:postcode":"p1b 9m9",
    "addr:street":"Fisher St",
    "iso:country":"CA",
    "sg:address":"480 Fisher St",
    "sg:city":"North Bay",
    "sg:classifiers":[
        {
            "category":"Health Services",
            "subcategory":"Health Practitioner",
            "type":"Services"
        }
    ],
    "sg:phone":"+1 705 497 8788",
    "sg:postcode":"P1B 9M9",
    "sg:province":"ON",
    "sg:tags":[
        "physician"
    ],
    "wof:name":"Dmg Naturopathic Clinic",
    "wof:placetype":"venue"
},
  "geometry": {"coordinates":[-79.458679,46.30732],"type":"Point"}
}