{
  "type": "Feature",
  "properties": {
    "addr:full":"1076 Mccarty Cres Revelstoke BC V0E 2S1",
    "addr:housenumber":"1076",
    "addr:postcode":"v0e 2s1",
    "addr:street":"Mccarty Cres",
    "iso:country":"CA",
    "sg:address":"1076 Mccarty Cres",
    "sg:city":"Revelstoke",
    "sg:classifiers":[
        {
            "category":"Personal",
            "type":"Services"
        }
    ],
    "sg:phone":"+1 250 837 4134",
    "sg:postcode":"V0E 2S1",
    "sg:province":"BC",
    "sg:tags":[
        "electrolysis"
    ],
    "wof:name":"Electrolysis By Cynthia",
    "wof:placetype":"venue"
},
  "geometry": {"coordinates":[-118.19658699999999,50.977745],"type":"Point"}
}