{
  "type": "Feature",
  "properties": {
    "iso:country":"CA",
    "sg:city":"Victoria",
    "sg:classifiers":[
        {
            "category":"Shopping",
            "subcategory":"Clothing, Apparel, & Fashions",
            "type":"Retail Goods"
        }
    ],
    "sg:phone":"+1 250 381 1858",
    "sg:postcode":"V8W 3M9",
    "sg:province":"BC",
    "wof:name":"Garage Clothing CO",
    "wof:placetype":"venue"
},
  "geometry": {"coordinates":[-123.365524,48.425037],"type":"Point"}
}