{
  "type": "Feature",
  "properties": {
    "addr:full":"558 10th Ave Regina SK S4N 5P2",
    "addr:housenumber":"558",
    "addr:postcode":"s4n 5p2",
    "addr:street":"10Th Ave",
    "iso:country":"CA",
    "sg:address":"558 10th Ave",
    "sg:city":"Regina",
    "sg:classifiers":[
        {
            "category":"Shopping",
            "subcategory":"Jewelry",
            "type":"Retail Goods"
        }
    ],
    "sg:phone":"+1 306 522 3908",
    "sg:postcode":"S4N 5P2",
    "sg:province":"SK",
    "wof:name":"Jewellery Factory",
    "wof:placetype":"venue"
},
  "geometry": {"coordinates":[-104.588165283,50.4520301819],"type":"Point"}
}