{
  "type": "Feature",
  "properties": {
    "addr:full":"379 Parkridge Cres Oakville ON L6M 1A8",
    "addr:housenumber":"379",
    "addr:postcode":"l6m 1a8",
    "addr:street":"Parkridge Cres",
    "iso:country":"CA",
    "sg:address":"379 Parkridge Cres",
    "sg:city":"Oakville",
    "sg:classifiers":[
        {
            "category":"Food & Beverages",
            "subcategory":"Specialty",
            "type":"Retail Goods"
        }
    ],
    "sg:phone":"+1 905 465 4445",
    "sg:postcode":"L6M 1A8",
    "sg:province":"ON",
    "sg:tags":[
        "water",
        "bulk",
        "company"
    ],
    "wof:name":"Oak Hills Water Supply",
    "wof:placetype":"venue"
},
  "geometry": {"coordinates":[-79.7073898315,43.4444007874],"type":"Point"}
}