{
  "type": "Feature",
  "properties": {
    "addr:full":"21 Upper Centennial Pky S Stoney Creek ON L8J 3W2",
    "addr:housenumber":"21",
    "addr:postcode":"l8j 3w2",
    "addr:street":"Upper Centennial Pky S Stoney",
    "iso:country":"CA",
    "sg:address":"21 Upper Centennial Pky S",
    "sg:city":"Stoney Creek",
    "sg:classifiers":[
        {
            "category":"Shopping",
            "subcategory":"Florist",
            "type":"Retail Goods"
        }
    ],
    "sg:phone":"+1 905 662 7217",
    "sg:postcode":"L8J 3W2",
    "sg:province":"ON",
    "wof:name":"Fortinos House of Flowers",
    "wof:placetype":"venue"
},
  "geometry": {"coordinates":[-79.7756729126,43.1758270264],"type":"Point"}
}