{
  "type": "Feature",
  "properties": {
    "addr:full":"80 Rue Saint-Marc Louiseville QC J5V 2E6",
    "addr:housenumber":"80",
    "addr:postcode":"j5v 2e6",
    "addr:street":"Rue Saint-Marc",
    "iso:country":"CA",
    "sg:address":"80 Rue Saint-Marc",
    "sg:city":"Louiseville",
    "sg:classifiers":[
        {
            "category":"Food & Beverages",
            "subcategory":"Groceries & Convenience Stores",
            "type":"Retail Goods"
        }
    ],
    "sg:phone":"+1 819 228 2764",
    "sg:postcode":"J5V 2E6",
    "sg:province":"QC",
    "sg:tags":[
        "grocer"
    ],
    "wof:name":"Marche Emery & Fils Inc",
    "wof:placetype":"venue"
},
  "geometry": {"coordinates":[-72.9478759766,46.2567634583],"type":"Point"}
}