{
  "type": "Feature",
  "properties": {
    "addr:full":"Burlington ON L7N 3M6",
    "addr:postcode":"l7n 3m6",
    "iso:country":"CA",
    "sg:city":"Burlington",
    "sg:classifiers":[
        {
            "category":"Professional",
            "subcategory":"Research",
            "type":"Services"
        }
    ],
    "sg:phone":"+1 905 631 8489",
    "sg:postcode":"L7N 3M6",
    "sg:province":"ON",
    "sg:tags":[
        "environmental",
        "ecological"
    ],
    "wof:name":"Mc Kibbon Wakefield Inc",
    "wof:placetype":"venue"
},
  "geometry": {"coordinates":[-79.794365,43.359943],"type":"Point"}
}