{
  "type": "Feature",
  "properties": {
    "addr:full":"PO Box 463 Magrath AB T0K 1J0",
    "addr:housenumber":"po",
    "addr:postcode":"t0k 1j0",
    "addr:street":"Box 463 Magrath",
    "iso:country":"CA",
    "sg:address":"PO Box 463",
    "sg:city":"Magrath",
    "sg:classifiers":[
        {
            "category":"Building & Trades",
            "subcategory":"Construction",
            "type":"Services"
        }
    ],
    "sg:phone":"+1 403 758 6706",
    "sg:postcode":"T0K 1J0",
    "sg:province":"AB",
    "sg:tags":[
        "concrete",
        "contractor"
    ],
    "wof:name":"Marc's Concrete Ltd",
    "wof:placetype":"venue"
},
  "geometry": {"coordinates":[-112.86857605,49.4183807373],"type":"Point"}
}