{
  "type": "Feature",
  "properties": {
    "addr:full":"PO Box 26010 Rpo Terrace Hill Brantford ON N3R 7X4",
    "addr:housenumber":"po box",
    "addr:postcode":"26010;n3r 7x4",
    "addr:street":"Rpo",
    "iso:country":"CA",
    "sg:address":"PO Box 26010 Rpo Terrace Hill",
    "sg:city":"Brantford",
    "sg:classifiers":[
        {
            "category":"Organizations",
            "subcategory":"Non-profit Organization",
            "type":"Services"
        }
    ],
    "sg:phone":"+1 519 752 5981",
    "sg:postcode":"N3R 7X4",
    "sg:province":"ON",
    "sg:tags":[
        "addiction",
        "treatment",
        "center"
    ],
    "wof:name":"Alcoholics Anonymous",
    "wof:placetype":"venue"
},
  "geometry": {"coordinates":[-80.261742,43.141361],"type":"Point"}
}