{
  "type": "Feature",
  "properties": {
    "addr:full":"Ottawa ON K2C 0C7",
    "addr:postcode":"k2c 0c7",
    "iso:country":"CA",
    "sg:city":"Ottawa",
    "sg:classifiers":[
        {
            "category":"Wholesale",
            "subcategory":"Office Equipment",
            "type":"Manufacturing & Wholesale Goods"
        }
    ],
    "sg:phone":"+1 613 228 2251",
    "sg:postcode":"K2C 0C7",
    "sg:province":"ON",
    "sg:tags":[
        "return",
        "tax",
        "system",
        "preparation",
        "accounting",
        "bookkeeping",
        "filing"
    ],
    "wof:name":"A Plus Accounting & Consulting",
    "wof:placetype":"venue"
},
  "geometry": {"coordinates":[-75.75904800000001,45.353359],"type":"Point"}
}