{
  "type": "Feature",
  "properties": {
    "addr:full":"2055 20th Ave Prince George BC V2L 4V2",
    "addr:housenumber":"2055",
    "addr:postcode":"v2l 4v2",
    "addr:street":"20Th Ave",
    "iso:country":"CA",
    "sg:address":"2055 20th Ave",
    "sg:city":"Prince George",
    "sg:classifiers":[
        {
            "category":"Organizations",
            "subcategory":"Religious Organization",
            "type":"Services"
        }
    ],
    "sg:phone":"+1 250 563 1003",
    "sg:postcode":"V2L 4V2",
    "sg:province":"BC",
    "sg:tags":[
        "church"
    ],
    "wof:name":"Gateway Christian Ministries",
    "wof:placetype":"venue"
},
  "geometry": {"coordinates":[-122.773071,53.906078],"type":"Point"}
}