{
  "type": "Feature",
  "properties": {
    "addr:full":"2350 Av Du Colisee Quebec QC G1L 5A1",
    "addr:housenumber":"2350",
    "addr:postcode":"g1l 5a1",
    "addr:street":"Av Du Colisee",
    "iso:country":"CA",
    "sg:address":"2350 Av Du Colisee",
    "sg:city":"Quebec",
    "sg:classifiers":[
        {
            "category":"Social Services",
            "type":"Services"
        }
    ],
    "sg:phone":"+1 418 529 0015",
    "sg:postcode":"G1L 5A1",
    "sg:province":"QC",
    "sg:tags":[
        "organization",
        "welfare"
    ],
    "wof:name":"A A",
    "wof:placetype":"venue"
},
  "geometry": {"coordinates":[-71.24580400000001,46.832619],"type":"Point"}
}