{
  "type": "Feature",
  "properties": {
    "iso:country":"CA",
    "sg:address":"3908 49 St NW",
    "sg:city":"Edmonton",
    "sg:classifiers":[
        {
            "category":"Building & Trades",
            "subcategory":"Construction",
            "type":"Services"
        }
    ],
    "sg:phone":"+1 780 463 4109",
    "sg:postcode":"T6L 6E8",
    "sg:province":"AB",
    "sg:tags":[
        "maker",
        "cabinet"
    ],
    "wof:name":"Petersen Furniture Mfg Inc",
    "wof:placetype":"venue"
},
  "geometry": {"coordinates":[-113.415466309,53.4757194519],"type":"Point"}
}