{
  "type": "Feature",
  "properties": {
    "addr:full":"Victoriaville QC G6P 4A1",
    "addr:postcode":"g6p 4a1",
    "iso:country":"CA",
    "sg:city":"Victoriaville",
    "sg:classifiers":[
        {
            "category":"Personal",
            "type":"Services"
        }
    ],
    "sg:phone":"+1 819 350 8699",
    "sg:postcode":"G6P 4A1",
    "sg:province":"QC",
    "sg:tags":[
        "therapist",
        "massage"
    ],
    "wof:name":"Massotherapie LA Douce'Heure",
    "wof:placetype":"venue"
},
  "geometry": {"coordinates":[-71.954109,46.057446],"type":"Point"}
}