{
  "type": "Feature",
  "properties": {
    "addr:full":"22 Golden Blvd Welland ON L3B 1H4",
    "addr:housenumber":"22",
    "addr:postcode":"l3b 1h4",
    "addr:street":"Golden Blvd",
    "iso:country":"CA",
    "sg:address":"22 Golden Blvd",
    "sg:city":"Welland",
    "sg:classifiers":[
        {
            "category":"Organizations",
            "subcategory":"Religious Organization",
            "type":"Services"
        }
    ],
    "sg:phone":"+1 905 732 5046",
    "sg:postcode":"L3B 1H4",
    "sg:province":"ON",
    "sg:tags":[
        "church"
    ],
    "wof:name":"St Andrews the Apostle Rc Ch",
    "wof:placetype":"venue"
},
  "geometry": {"coordinates":[-79.229088,42.985577],"type":"Point"}
}