{
  "type": "Feature",
  "properties": {
    "addr:full":"3497 Kingsway Vancouver BC V5R 5L5",
    "addr:housenumber":"3497",
    "addr:postcode":"v5r 5l5",
    "addr:street":"Kingsway",
    "iso:country":"CA",
    "sg:address":"3497 Kingsway",
    "sg:city":"Vancouver",
    "sg:classifiers":[
        {
            "category":"Travel",
            "subcategory":"Travel Agent",
            "type":"Entertainment"
        }
    ],
    "sg:phone":"+1 604 451 0660",
    "sg:postcode":"V5R 5L5",
    "sg:province":"BC",
    "sg:tags":[
        "agency",
        "bureau"
    ],
    "wof:name":"Andes Travel Agency Inc",
    "wof:placetype":"venue"
},
  "geometry": {"coordinates":[-123.029563904,49.232131958],"type":"Point"}
}