{
  "type": "Feature",
  "properties": {
    "addr:full":"26 Rue Iberville Riviere-Du-Loup QC G5R 1G7",
    "addr:housenumber":"26",
    "addr:postcode":"g5r 1g7",
    "addr:street":"Rue Iberville Riviere-Du-Loup",
    "iso:country":"CA",
    "sg:address":"26 Rue Iberville",
    "sg:city":"Riviere-Du-Loup",
    "sg:classifiers":[
        {
            "category":"Professional",
            "subcategory":"Management & Consulting",
            "type":"Services"
        }
    ],
    "sg:phone":"+1 418 867 2853",
    "sg:postcode":"G5R 1G7",
    "sg:province":"QC",
    "sg:tags":[
        "communications",
        "advertising",
        "consultant"
    ],
    "wof:name":"Clic Communication",
    "wof:placetype":"venue"
},
  "geometry": {"coordinates":[-69.537476,47.839596],"type":"Point"}
}