{
  "type": "Feature",
  "properties": {
    "addr:full":"123 South Railway St E Macgregor MB R0H 0R0",
    "addr:housenumber":"123",
    "addr:postcode":"r0h 0r0",
    "addr:street":"South Railway St",
    "iso:country":"CA",
    "sg:address":"123 South Railway St E",
    "sg:city":"Macgregor",
    "sg:classifiers":[
        {
            "category":"Farming",
            "subcategory":"Farm & Veterinary Services",
            "type":"Manufacturing & Wholesale Goods"
        }
    ],
    "sg:phone":"+1 204 685 5685",
    "sg:postcode":"R0H 0R0",
    "sg:province":"MB",
    "sg:tags":[
        "product",
        "protection",
        "crop"
    ],
    "wof:name":"Munro Farm Supplies Ltd",
    "wof:placetype":"venue"
},
  "geometry": {"coordinates":[-98.779296875,49.965221405],"type":"Point"}
}