{
  "type": "Feature",
  "properties": {
    "addr:full":"Clinton ON N0M 1L0",
    "addr:postcode":"n0m 1l0",
    "iso:country":"CA",
    "sg:city":"Clinton",
    "sg:classifiers":[
        {
            "category":"Government",
            "subcategory":"Office",
            "type":"Public Place"
        }
    ],
    "sg:phone":"+1 519 482 5536",
    "sg:postcode":"N0M 1L0",
    "sg:province":"ON",
    "wof:name":"Ontario Safety & Vehicle Insp",
    "wof:placetype":"venue"
},
  "geometry": {"coordinates":[-81.536957,43.621487],"type":"Point"}
}