{
  "type": "Feature",
  "properties": {
    "addr:full":"251 Lemarchant Rd St. John's NL A1E 1P8",
    "addr:housenumber":"251",
    "addr:postcode":"a1e 1p8",
    "addr:street":"Lemarchant Rd",
    "iso:country":"CA",
    "sg:address":"251 Lemarchant Rd",
    "sg:city":"St. John's",
    "sg:classifiers":[
        {
            "category":"Health Services",
            "subcategory":"Doctor",
            "type":"Services"
        }
    ],
    "sg:phone":"+1 709 777 5151",
    "sg:postcode":"A1E 1P8",
    "sg:province":"NL",
    "sg:tags":[
        "physician",
        "surgeon"
    ],
    "wof:name":"Wells, Mary MD",
    "wof:placetype":"venue"
},
  "geometry": {"coordinates":[-52.72316,47.554203],"type":"Point"}
}