{
  "type": "Feature",
  "properties": {
    "iso:country":"CA",
    "sg:address":"104 Rue Bussiere",
    "sg:city":"Saint-Alphonse-DE-Granby",
    "sg:classifiers":[
        {
            "category":"Retail",
            "subcategory":"Auto Repair",
            "type":"Services"
        }
    ],
    "sg:phone":"+1 450 375 3720",
    "sg:postcode":"J0E 2A0",
    "sg:province":"QC",
    "sg:tags":[
        "repairing",
        "automobile",
        "tire"
    ],
    "wof:name":"Pneus Multi",
    "wof:placetype":"venue"
},
  "geometry": {"coordinates":[-72.7217712402,45.3979949951],"type":"Point"}
}