{
  "type": "Feature",
  "properties": {
    "iso:country":"CA",
    "sg:city":"Fleurimont",
    "sg:classifiers":[
        {
            "category":"Professional",
            "subcategory":"Testing Lab",
            "type":"Services"
        }
    ],
    "sg:phone":"+1 819 569 0436",
    "sg:postcode":"J1E 1C9",
    "sg:province":"QC",
    "sg:tags":[
        "x"
    ],
    "wof:name":"Rayon-X Ind Inc",
    "wof:placetype":"venue"
},
  "geometry": {"coordinates":[-71.8912887573,45.4230690002],"type":"Point"}
}