{
  "type": "Feature",
  "properties": {
    "addr:full":"2450 Boul Laurier Sainte-Foy QC G1V 2L1",
    "addr:housenumber":"2450",
    "addr:postcode":"g1v 2l1",
    "addr:street":"Boul Laurier",
    "iso:country":"CA",
    "sg:address":"2450 Boul Laurier",
    "sg:city":"Sainte-Foy",
    "sg:classifiers":[
        {
            "category":"Shopping",
            "subcategory":"Books",
            "type":"Retail Goods"
        }
    ],
    "sg:phone":"+1 418 651 4935",
    "sg:postcode":"G1V 2L1",
    "sg:province":"QC",
    "sg:tags":[
        "dealer"
    ],
    "wof:name":"Boutique Du Livre DE Ste-Foy",
    "wof:placetype":"venue"
},
  "geometry": {"coordinates":[-71.27625999999999,46.773705],"type":"Point"}
}