{
  "type": "Feature",
  "properties": {
    "addr:full":"4317 Gallant Ave North Vancouver BC V7G 2C1",
    "addr:housenumber":"4317",
    "addr:postcode":"v7g 2c1",
    "addr:street":"Gallant Ave",
    "iso:country":"CA",
    "sg:address":"4317 Gallant Ave",
    "sg:city":"North Vancouver",
    "sg:classifiers":[
        {
            "category":"Social Services",
            "subcategory":"Child Care",
            "type":"Services"
        }
    ],
    "sg:phone":"+1 604 924 1253",
    "sg:postcode":"V7G 2C1",
    "sg:province":"BC",
    "wof:name":"Mamalina's Montessori Prschl",
    "wof:placetype":"venue"
},
  "geometry": {"coordinates":[-122.95142364500001,49.3265953064],"type":"Point"}
}