{
  "type": "Feature",
  "properties": {
    "addr:full":"9815 Boul DE L'Acadie Montreal QC H4N 2W2",
    "addr:housenumber":"9815",
    "addr:postcode":"h4n 2w2",
    "addr:street":"Boul De L'Acadie",
    "iso:country":"CA",
    "sg:address":"9815 Boul DE L'Acadie",
    "sg:city":"Montreal",
    "sg:classifiers":[
        {
            "category":"Shopping",
            "subcategory":"Florist",
            "type":"Retail Goods"
        }
    ],
    "sg:phone":"+1 514 331 4584",
    "sg:postcode":"H4N 2W2",
    "sg:province":"QC",
    "wof:name":"Caprice Floral",
    "wof:placetype":"venue"
},
  "geometry": {"coordinates":[-73.3577804565,45.3339691162],"type":"Point"}
}