{
  "type": "Feature",
  "properties": {
    "iso:country":"CA",
    "sg:city":"Montreal",
    "sg:classifiers":[
        {
            "category":"Professional",
            "subcategory":"Advertising",
            "type":"Services"
        }
    ],
    "sg:phone":"+1 514 861 8989",
    "sg:postcode":"H3C 4L1",
    "sg:province":"QC",
    "sg:tags":[
        "publicity"
    ],
    "wof:name":"Pascal, Harold",
    "wof:placetype":"venue"
},
  "geometry": {"coordinates":[-73.5444488525,45.4969787598],"type":"Point"}
}