{
  "type": "Feature",
  "properties": {
    "addr:full":"93 Dufferin St Bridgewater NS B4V 2G4",
    "addr:housenumber":"93",
    "addr:postcode":"b4v 2g4",
    "addr:street":"Dufferin St",
    "iso:country":"CA",
    "sg:address":"93 Dufferin St",
    "sg:city":"Bridgewater",
    "sg:classifiers":[
        {
            "category":"Organizations",
            "subcategory":"Non-profit Organization",
            "type":"Services"
        }
    ],
    "sg:phone":"+1 902 354 5517",
    "sg:postcode":"B4V 2G4",
    "sg:province":"NS",
    "sg:tags":[
        "charitable",
        "institution"
    ],
    "wof:name":"Big Brothers Big Sisters Assn",
    "wof:placetype":"venue"
},
  "geometry": {"coordinates":[-64.51953899999999,44.37315],"type":"Point"}
}