{
  "type": "Feature",
  "properties": {
    "addr:full":"207 Lemarchant Rd St. John's NL A1C 2H5",
    "addr:housenumber":"207",
    "addr:postcode":"a1c 2h5",
    "addr:street":"Lemarchant Rd",
    "iso:country":"CA",
    "sg:address":"207 Lemarchant Rd",
    "sg:city":"St. John's",
    "sg:classifiers":[
        {
            "category":"Shopping",
            "subcategory":"Optical Goods",
            "type":"Retail Goods"
        }
    ],
    "sg:phone":"+1 709 579 3852",
    "sg:postcode":"A1C 2H5",
    "sg:province":"NL",
    "sg:tags":[
        "physician",
        "surgeon",
        "optician"
    ],
    "wof:name":"Optique Boutique",
    "wof:placetype":"venue"
},
  "geometry": {"coordinates":[-52.721634,47.555923],"type":"Point"}
}