{
  "type": "Feature",
  "properties": {
    "iso:country":"CA",
    "sg:address":"232 Miami River Dr",
    "sg:city":"Harrison Hot Springs",
    "sg:classifiers":[
        {
            "category":"Personal",
            "type":"Services"
        }
    ],
    "sg:phone":"+1 604 796 2696",
    "sg:postcode":"V0M 1K0",
    "sg:province":"BC",
    "sg:tags":[
        "therapist",
        "massage"
    ],
    "wof:name":"Dogwood Clinic of Massage",
    "wof:placetype":"venue"
},
  "geometry": {"coordinates":[-121.783195496,49.3004341125],"type":"Point"}
}