{
  "type": "Feature",
  "properties": {
    "iso:country":"CA",
    "sg:address":"640 Main St",
    "sg:city":"Canwood",
    "sg:classifiers":[
        {
            "category":"Retail",
            "subcategory":"Self-service Laundry",
            "type":"Services"
        }
    ],
    "sg:phone":"+1 306 468 2363",
    "sg:postcode":"S0J 0K0",
    "sg:province":"SK",
    "wof:name":"Judy's Billiard & Laundry",
    "wof:placetype":"venue"
},
  "geometry": {"coordinates":[-106.60481299999999,53.359676],"type":"Point"}
}