{
  "type": "Feature",
  "properties": {
    "addr:full":"686 Memorial Ave Qualicum Beach BC V9K 1S7",
    "addr:housenumber":"686",
    "addr:postcode":"v9k 1s7",
    "addr:street":"Memorial Ave",
    "iso:country":"CA",
    "sg:address":"686 Memorial Ave",
    "sg:city":"Qualicum Beach",
    "sg:classifiers":[
        {
            "category":"Banks & Credit Unions",
            "subcategory":"Bank",
            "type":"Services"
        }
    ],
    "sg:phone":"+1 250 752 4300",
    "sg:postcode":"V9K 1S7",
    "sg:province":"BC",
    "wof:name":"Cibc",
    "wof:placetype":"venue"
},
  "geometry": {"coordinates":[-124.44152800000001,49.347099],"type":"Point"}
}