{
  "type": "Feature",
  "properties": {
    "addr:full":"1110 Canterbury Dr SW Calgary AB T2W 3P5",
    "addr:housenumber":"1110",
    "addr:postcode":"t2w 3p5",
    "addr:street":"Canterbury Dr Sw",
    "iso:country":"CA",
    "sg:address":"1110 Canterbury Dr SW",
    "sg:city":"Calgary",
    "sg:classifiers":[
        {
            "category":"Food & Beverages",
            "subcategory":"Groceries & Convenience Stores",
            "type":"Retail Goods"
        }
    ],
    "sg:phone":"+1 403 281 4902",
    "sg:postcode":"T2W 3P5",
    "sg:province":"AB",
    "wof:name":"Mac's Convenience Stores Ltd",
    "wof:placetype":"venue"
},
  "geometry": {"coordinates":[-114.079803,50.936836],"type":"Point"}
}