{
  "type": "Feature",
  "properties": {
    "iso:country":"CA",
    "sg:address":"127 Esplanade W",
    "sg:city":"North Vancouver",
    "sg:classifiers":[
        {
            "category":"Shopping",
            "subcategory":"Clothing, Apparel, & Fashions",
            "type":"Retail Goods"
        }
    ],
    "sg:phone":"+1 604 985 9222",
    "sg:postcode":"V7M 1A1",
    "sg:province":"BC",
    "sg:tags":[
        "furnishing"
    ],
    "wof:name":"Paul Minichiello Intl Designs",
    "wof:placetype":"venue"
},
  "geometry": {"coordinates":[-123.080406,49.311333],"type":"Point"}
}