{
  "type": "Feature",
  "properties": {
    "iso:country":"CA",
    "sg:address":"183 Rue Pie-Xi",
    "sg:city":"Thetford Mines",
    "sg:classifiers":[
        {
            "category":"Government",
            "subcategory":"Office",
            "type":"Public Place"
        }
    ],
    "sg:phone":"+1 418 338 0181",
    "sg:postcode":"G6G 3N3",
    "sg:province":"QC",
    "wof:name":"Quebec Communication",
    "wof:placetype":"venue"
},
  "geometry": {"coordinates":[-71.30600738530001,46.0890045166],"type":"Point"}
}