{
  "type": "Feature",
  "properties": {
    "addr:full":"Lorraine QC J6Z 1T9",
    "addr:postcode":"j6z 1t9",
    "iso:country":"CA",
    "sg:city":"Lorraine",
    "sg:classifiers":[
        {
            "category":"Health Services",
            "subcategory":"Health Practitioner",
            "type":"Services"
        }
    ],
    "sg:phone":"+1 450 965 9531",
    "sg:postcode":"J6Z 1T9",
    "sg:province":"QC",
    "sg:tags":[
        "physiotherapist"
    ],
    "wof:name":"Chicoine, Louise",
    "wof:placetype":"venue"
},
  "geometry": {"coordinates":[-73.77741241459999,45.6638565063],"type":"Point"}
}