{
  "type": "Feature",
  "properties": {
    "addr:full":"274 Rue Bureau Trois-Rivieres QC G9A 2M7",
    "addr:housenumber":"274",
    "addr:postcode":"g9a 2m7",
    "addr:street":"Rue Bureau Trois-Rivieres",
    "iso:country":"CA",
    "sg:address":"274 Rue Bureau",
    "sg:city":"Trois-Rivieres",
    "sg:classifiers":[
        {
            "category":"Organizations",
            "subcategory":"Professional Association",
            "type":"Services"
        }
    ],
    "sg:phone":"+1 819 378 7888",
    "sg:postcode":"G9A 2M7",
    "sg:province":"QC",
    "sg:tags":[
        "consultant",
        "planning",
        "financial"
    ],
    "wof:name":"Acef DE LA Mauricie",
    "wof:placetype":"venue"
},
  "geometry": {"coordinates":[-72.544685,46.339283],"type":"Point"}
}