{
  "type": "Feature",
  "properties": {
    "addr:full":"9 Wellington St E Brampton ON L6W 1Y1",
    "addr:housenumber":"9",
    "addr:postcode":"l6w 1y1",
    "addr:street":"Wellington St E",
    "iso:country":"CA",
    "sg:address":"9 Wellington St E",
    "sg:city":"Brampton",
    "sg:classifiers":[
        {
            "category":"Government",
            "subcategory":"Office",
            "type":"Public Place"
        }
    ],
    "sg:phone":"+1 905 791 4055",
    "sg:postcode":"L6W 1Y1",
    "sg:province":"ON",
    "sg:tags":[
        "village"
    ],
    "wof:name":"Peel Heritage Complex",
    "wof:placetype":"venue"
},
  "geometry": {"coordinates":[-79.757561,43.685181],"type":"Point"}
}