{
  "type": "Feature",
  "properties": {
    "addr:full":"204 Main St Coleville SK S0L 0K0",
    "addr:housenumber":"204",
    "addr:postcode":"s0l 0k0",
    "addr:street":"Main St",
    "iso:country":"CA",
    "sg:address":"204 Main St",
    "sg:city":"Coleville",
    "sg:classifiers":[
        {
            "category":"Banks & Credit Unions",
            "subcategory":"Bank",
            "type":"Services"
        }
    ],
    "sg:phone":"+1 306 965 2232",
    "sg:postcode":"S0L 0K0",
    "sg:province":"SK",
    "wof:name":"Coleville Branch-Kindersley",
    "wof:placetype":"venue"
},
  "geometry": {"coordinates":[-109.246688843,51.7069015503],"type":"Point"}
}