{
  "type": "Feature",
  "properties": {
    "addr:full":"1248 St Clair Ave W Toronto ON M6E 1B7",
    "addr:housenumber":"1248",
    "addr:postcode":"m6e 1b7",
    "addr:street":"St Clair Ave W",
    "iso:country":"CA",
    "sg:address":"1248 St Clair Ave W",
    "sg:city":"Toronto",
    "sg:classifiers":[
        {
            "category":"Restaurant",
            "type":"Food & Drink"
        }
    ],
    "sg:phone":"+1 416 656 9266",
    "sg:postcode":"M6E 1B7",
    "sg:province":"ON",
    "wof:name":"International Sports Bar",
    "wof:placetype":"venue"
},
  "geometry": {"coordinates":[-79.4459762573,43.6774406433],"type":"Point"}
}