{
  "type": "Feature",
  "properties": {
    "iso:country":"CA",
    "sg:address":"48 Av Wolseley N",
    "sg:city":"Montreal-Ouest",
    "sg:classifiers":[
        {
            "category":"Building & Trades",
            "subcategory":"Plumbing",
            "type":"Services"
        }
    ],
    "sg:phone":"+1 514 481 0368",
    "sg:postcode":"H4X 1V5",
    "sg:province":"QC",
    "sg:tags":[
        "contractor"
    ],
    "wof:name":"Bertrand Durand Inc",
    "wof:placetype":"venue"
},
  "geometry": {"coordinates":[-73.646645,45.451786],"type":"Point"}
}