{
  "type": "Feature",
  "properties": {
    "addr:full":"Saskatoon SK S7H 0R8",
    "addr:postcode":"s7h 0r8",
    "iso:country":"CA",
    "sg:city":"Saskatoon",
    "sg:classifiers":[
        {
            "category":"Shopping",
            "subcategory":"Pharmacy",
            "type":"Retail Goods"
        }
    ],
    "sg:phone":"+1 306 244 1531",
    "sg:postcode":"S7H 0R8",
    "sg:province":"SK",
    "wof:name":"Earl's Pharmacy Ltd",
    "wof:placetype":"venue"
},
  "geometry": {"coordinates":[-106.647873,52.114445],"type":"Point"}
}