{
  "type": "Feature",
  "properties": {
    "addr:full":"229 Mackay St Pembroke ON K8A 1C3",
    "addr:housenumber":"229",
    "addr:postcode":"k8a 1c3",
    "addr:street":"Mackay St",
    "iso:country":"CA",
    "sg:address":"229 Mackay St",
    "sg:city":"Pembroke",
    "sg:classifiers":[
        {
            "category":"Banks & Credit Unions",
            "subcategory":"Investment Brokerage",
            "type":"Services"
        }
    ],
    "sg:phone":"+1 613 735 3442",
    "sg:postcode":"K8A 1C3",
    "sg:province":"ON",
    "sg:tags":[
        "consultant",
        "planning",
        "financial"
    ],
    "wof:name":"Investors Group Representative",
    "wof:placetype":"venue"
},
  "geometry": {"coordinates":[-77.11041299999999,45.825916],"type":"Point"}
}