{
  "type": "Feature",
  "properties": {
    "addr:full":"52 Eden Ave Markham ON L3R 8R7",
    "addr:housenumber":"52",
    "addr:postcode":"l3r 8r7",
    "addr:street":"Eden Ave",
    "iso:country":"CA",
    "sg:address":"52 Eden Ave",
    "sg:city":"Markham",
    "sg:classifiers":[
        {
            "category":"Building & Trades",
            "subcategory":"Construction",
            "type":"Services"
        }
    ],
    "sg:phone":"+1 905 470 7544",
    "sg:postcode":"L3R 8R7",
    "sg:province":"ON",
    "sg:tags":[
        "paving",
        "contractor"
    ],
    "wof:name":"Power Pack Paving Ltd",
    "wof:placetype":"venue"
},
  "geometry": {"coordinates":[-79.29496,43.839531],"type":"Point"}
}