{
  "type": "Feature",
  "properties": {
    "addr:full":"48 Darte Dr Welland ON L3B 5Y7",
    "addr:housenumber":"48",
    "addr:postcode":"l3b 5y7",
    "addr:street":"Darte Dr",
    "iso:country":"CA",
    "sg:address":"48 Darte Dr",
    "sg:city":"Welland",
    "sg:classifiers":[
        {
            "category":"Shopping",
            "type":"Retail Goods"
        }
    ],
    "sg:phone":"+1 905 735 1403",
    "sg:postcode":"L3B 5Y7",
    "sg:province":"ON",
    "sg:tags":[
        "spa",
        "hot",
        "tub",
        "pool",
        "swimming"
    ],
    "wof:name":"Blue Ocean Pools & Spas",
    "wof:placetype":"venue"
},
  "geometry": {"coordinates":[-79.26409099999999,42.962971],"type":"Point"}
}