{
  "type": "Feature",
  "properties": {
    "iso:country":"CA",
    "sg:address":"83 Edward St",
    "sg:city":"Stouffville",
    "sg:classifiers":[
        {
            "category":"Manufacturing",
            "subcategory":"Tools & Machinery",
            "type":"Manufacturing & Wholesale Goods"
        }
    ],
    "sg:phone":"+1 905 640 2976",
    "sg:postcode":"L4A 1A8",
    "sg:province":"ON",
    "sg:tags":[
        "die",
        "maker"
    ],
    "wof:name":"Royal Die Ltd",
    "wof:placetype":"venue"
},
  "geometry": {"coordinates":[-79.251511,43.972801],"type":"Point"}
}