{
  "type": "Feature",
  "properties": {
    "addr:full":"5836 Fieldon Rd Mississauga ON L5M 5K3",
    "addr:housenumber":"5836",
    "addr:postcode":"l5m 5k3",
    "addr:street":"Fieldon Rd",
    "iso:country":"CA",
    "sg:address":"5836 Fieldon Rd",
    "sg:city":"Mississauga",
    "sg:classifiers":[
        {
            "category":"Professional",
            "subcategory":"Computer Services",
            "type":"Services"
        }
    ],
    "sg:phone":"+1 905 567 3858",
    "sg:postcode":"L5M 5K3",
    "sg:province":"ON",
    "sg:tags":[
        "consultant"
    ],
    "wof:name":"Yuska & Assoc Ltd",
    "wof:placetype":"venue"
},
  "geometry": {"coordinates":[-79.7329711914,43.5719451904],"type":"Point"}
}