{
  "type": "Feature",
  "properties": {
    "addr:full":"100 3rd Ave NW Geraldton ON P0T 1M0",
    "addr:housenumber":"100",
    "addr:postcode":"p0t 1m0",
    "addr:street":"3Rd Ave Nw",
    "iso:country":"CA",
    "sg:address":"100 3rd Ave NW",
    "sg:city":"Geraldton",
    "sg:classifiers":[
        {
            "category":"Manufacturing",
            "subcategory":"Food",
            "type":"Manufacturing & Wholesale Goods"
        }
    ],
    "sg:phone":"+1 807 854 0147",
    "sg:postcode":"P0T 1M0",
    "sg:province":"ON",
    "sg:tags":[
        "baker",
        "product",
        "manufacturer"
    ],
    "wof:name":"Geraldton Bakeries",
    "wof:placetype":"venue"
},
  "geometry": {"coordinates":[-86.9498748779,49.7284965515],"type":"Point"}
}