{
  "type": "Feature",
  "properties": {
    "addr:full":"9807 102 St Fort Saskatchewan AB T8L 2C1",
    "addr:housenumber":"9807",
    "addr:postcode":"t8l 2c1",
    "addr:street":"102 St",
    "iso:country":"CA",
    "sg:address":"9807 102 St",
    "sg:city":"Fort Saskatchewan",
    "sg:classifiers":[
        {
            "category":"Professional",
            "subcategory":"Accounting & Tax Preparation",
            "type":"Services"
        }
    ],
    "sg:phone":"+1 780 998 5011",
    "sg:postcode":"T8L 2C1",
    "sg:province":"AB",
    "sg:tags":[
        "accountant"
    ],
    "wof:name":"Hotke, Paul CA",
    "wof:placetype":"venue"
},
  "geometry": {"coordinates":[-113.21064,53.709427],"type":"Point"}
}