{
  "type": "Feature",
  "properties": {
    "addr:full":"49 Lyngby Ave Dartmouth NS B3A 3V1",
    "addr:housenumber":"49",
    "addr:postcode":"b3a 3v1",
    "addr:street":"Lyngby Ave",
    "iso:country":"CA",
    "sg:address":"49 Lyngby Ave",
    "sg:city":"Dartmouth",
    "sg:classifiers":[
        {
            "category":"Education",
            "subcategory":"School",
            "type":"Public Place"
        }
    ],
    "sg:phone":"+1 902 464 2503",
    "sg:postcode":"B3A 3V1",
    "sg:province":"NS",
    "wof:name":"Crichton Park Elementary Schl",
    "wof:placetype":"venue"
},
  "geometry": {"coordinates":[-63.5645828247,44.6826820374],"type":"Point"}
}