{
  "type": "Feature",
  "properties": {
    "addr:full":"260 Water St Shelburne NS B0T 1W0",
    "addr:housenumber":"260",
    "addr:postcode":"b0t 1w0",
    "addr:street":"Water St",
    "iso:country":"CA",
    "sg:address":"260 Water St",
    "sg:city":"Shelburne",
    "sg:classifiers":[
        {
            "category":"Travel",
            "subcategory":"Hotels & Motels",
            "type":"Entertainment"
        }
    ],
    "sg:phone":"+1 902 875 2842",
    "sg:postcode":"B0T 1W0",
    "sg:province":"NS",
    "wof:name":"Mac Kenzie's Motel & Cottages",
    "wof:placetype":"venue"
},
  "geometry": {"coordinates":[-65.32409667970001,43.764251709],"type":"Point"}
}