{
  "type": "Feature",
  "properties": {
    "iso:country":"CA",
    "sg:city":"Scarborough",
    "sg:classifiers":[
        {
            "category":"Shopping",
            "subcategory":"Discount & Variety Stores",
            "type":"Retail Goods"
        }
    ],
    "sg:phone":"+1 416 282 9159",
    "sg:postcode":"M1E 1S4",
    "sg:province":"ON",
    "wof:name":"Hadfield Variety & Cleaners",
    "wof:placetype":"venue"
},
  "geometry": {"coordinates":[-79.1866607666,43.7535018921],"type":"Point"}
}