{
  "type": "Feature",
  "properties": {
    "addr:full":"2398 Algonquin Rd Sudbury ON P3E 5V1",
    "addr:housenumber":"2398",
    "addr:postcode":"p3e 5v1",
    "addr:street":"Algonquin Rd",
    "iso:country":"CA",
    "sg:address":"2398 Algonquin Rd",
    "sg:city":"Sudbury",
    "sg:classifiers":[
        {
            "category":"Manufacturing",
            "subcategory":"Buildings",
            "type":"Manufacturing & Wholesale Goods"
        }
    ],
    "sg:phone":"+1 705 522 7937",
    "sg:postcode":"P3E 5V1",
    "sg:province":"ON",
    "sg:tags":[
        "home",
        "log",
        "cabin"
    ],
    "wof:name":"J Robert Construction",
    "wof:placetype":"venue"
},
  "geometry": {"coordinates":[-80.9955444336,46.4399261475],"type":"Point"}
}