{
  "type": "Feature",
  "properties": {
    "addr:full":"9311 Boul Gouin O Montreal QC H4K 1C9",
    "addr:housenumber":"9311",
    "addr:postcode":"h4k 1c9",
    "addr:street":"Boul Gouin O",
    "iso:country":"CA",
    "sg:address":"9311 Boul Gouin O",
    "sg:city":"Montreal",
    "sg:classifiers":[
        {
            "category":"Retail",
            "subcategory":"Auto Repair",
            "type":"Services"
        }
    ],
    "sg:phone":"+1 514 331 3662",
    "sg:postcode":"H4K 1C9",
    "sg:province":"QC",
    "sg:tags":[
        "repairing",
        "automobile"
    ],
    "wof:name":"Auto-Pan",
    "wof:placetype":"venue"
},
  "geometry": {"coordinates":[-73.576401,45.657413],"type":"Point"}
}