{
  "type": "Feature",
  "properties": {
    "addr:full":"151 Jubilee St Duncan BC V9L 1W6",
    "addr:housenumber":"151",
    "addr:postcode":"v9l 1w6",
    "addr:street":"Jubilee St",
    "iso:country":"CA",
    "sg:address":"151 Jubilee St",
    "sg:city":"Duncan",
    "sg:classifiers":[
        {
            "category":"Retail",
            "subcategory":"Portrait Studio",
            "type":"Services"
        }
    ],
    "sg:phone":"+1 250 746 4341",
    "sg:postcode":"V9L 1W6",
    "sg:province":"BC",
    "sg:tags":[
        "photographer"
    ],
    "wof:name":"Paul Fletcher Photography",
    "wof:placetype":"venue"
},
  "geometry": {"coordinates":[-123.71068572999999,48.7781257629],"type":"Point"}
}