{
  "type": "Feature",
  "properties": {
    "addr:full":"Winnipeg MB R3C 4K5",
    "addr:postcode":"r3c 4k5",
    "iso:country":"CA",
    "sg:city":"Winnipeg",
    "sg:classifiers":[
        {
            "category":"Professional",
            "subcategory":"Accounting & Tax Preparation",
            "type":"Services"
        }
    ],
    "sg:phone":"+1 204 975 1634",
    "sg:postcode":"R3C 4K5",
    "sg:province":"MB",
    "sg:tags":[
        "consultant",
        "financial",
        "planning",
        "return",
        "filing"
    ],
    "wof:name":"Bieber Financial Svc Inc",
    "wof:placetype":"venue"
},
  "geometry": {"coordinates":[-97.1484222412,49.8890533447],"type":"Point"}
}