{
  "type": "Feature",
  "properties": {
    "addr:full":"286 Fitzroy St Summerside PE C1N 1J2",
    "addr:housenumber":"286",
    "addr:postcode":"c1n 1j2",
    "addr:street":"Fitzroy St",
    "iso:country":"CA",
    "sg:address":"286 Fitzroy St",
    "sg:city":"Summerside",
    "sg:classifiers":[
        {
            "category":"Real Estate",
            "subcategory":"Real Estate Agent",
            "type":"Services"
        }
    ],
    "sg:phone":"+1 902 888 3920",
    "sg:postcode":"C1N 1J2",
    "sg:province":"PE",
    "sg:tags":[
        "appraiser"
    ],
    "wof:name":"Habord Rogers & Assoc",
    "wof:placetype":"venue"
},
  "geometry": {"coordinates":[-63.791153,46.39291],"type":"Point"}
}