{
  "type": "Feature",
  "properties": {
    "addr:full":"570 Hermitage Rd NW Edmonton AB T5A 4N2",
    "addr:housenumber":"570",
    "addr:postcode":"t5a 4n2",
    "addr:street":"Hermitage Rd Nw",
    "iso:country":"CA",
    "sg:address":"570 Hermitage Rd NW",
    "sg:city":"Edmonton",
    "sg:classifiers":[
        {
            "category":"Social Services",
            "subcategory":"Child Care",
            "type":"Services"
        }
    ],
    "sg:phone":"+1 780 476 4201",
    "sg:postcode":"T5A 4N2",
    "sg:province":"AB",
    "wof:name":"Peter Pan Child Care Ctr",
    "wof:placetype":"venue"
},
  "geometry": {"coordinates":[-113.407188,53.586239],"type":"Point"}
}