{
  "type": "Feature",
  "properties": {
    "addr:full":"Peterborough ON K9H 3L9",
    "addr:postcode":"k9h 3l9",
    "iso:country":"CA",
    "sg:city":"Peterborough",
    "sg:classifiers":[
        {
            "category":"Organizations",
            "subcategory":"Professional Association",
            "type":"Services"
        }
    ],
    "sg:phone":"+1 705 742 7843",
    "sg:postcode":"K9H 3L9",
    "sg:province":"ON",
    "sg:tags":[
        "school"
    ],
    "wof:name":"Ontario English Catholic Assn",
    "wof:placetype":"venue"
},
  "geometry": {"coordinates":[-78.319176,44.306587],"type":"Point"}
}