{
  "type": "Feature",
  "properties": {
    "addr:full":"Kelowna BC V1Y 5V5",
    "addr:postcode":"v1y 5v5",
    "iso:country":"CA",
    "sg:city":"Kelowna",
    "sg:classifiers":[
        {
            "category":"Personal",
            "type":"Services"
        }
    ],
    "sg:phone":"+1 250 763 5757",
    "sg:postcode":"V1Y 5V5",
    "sg:province":"BC",
    "sg:tags":[
        "credit",
        "debt",
        "counseling"
    ],
    "wof:name":"Okanagan Credit Counsellors",
    "wof:placetype":"venue"
},
  "geometry": {"coordinates":[-119.457787,49.876736],"type":"Point"}
}