{
  "type": "Feature",
  "properties": {
    "addr:full":"Causapscal QC G0J 1J0",
    "addr:postcode":"g0j 1j0",
    "iso:country":"CA",
    "sg:city":"Causapscal",
    "sg:classifiers":[
        {
            "category":"Professional",
            "subcategory":"Employment Agencies",
            "type":"Services"
        }
    ],
    "sg:phone":"+1 418 756 6113",
    "sg:postcode":"G0J 1J0",
    "sg:province":"QC",
    "sg:tags":[
        "opportunity"
    ],
    "wof:name":"Centre DE LA Petite Enfance",
    "wof:placetype":"venue"
},
  "geometry": {"coordinates":[-67.22174835209999,48.3571968079],"type":"Point"}
}