{
  "type": "Feature",
  "properties": {
    "addr:full":"8599 Boul Maurice-Duplessis Montreal QC H1E 4H7",
    "addr:housenumber":"8599",
    "addr:postcode":"h1e 4h7",
    "addr:street":"Boul Maurice-Duplessis",
    "iso:country":"CA",
    "sg:address":"8599 Boul Maurice-Duplessis",
    "sg:city":"Montreal",
    "sg:classifiers":[
        {
            "category":"Banks & Credit Unions",
            "subcategory":"Bank",
            "type":"Services"
        }
    ],
    "sg:phone":"+1 514 394 5555",
    "sg:postcode":"H1E 4H7",
    "sg:province":"QC",
    "wof:name":"Banque Nationale Du Canada",
    "wof:placetype":"venue"
},
  "geometry": {"coordinates":[-73.5806732178,45.638458252],"type":"Point"}
}