{
  "type": "Feature",
  "properties": {
    "addr:full":"Surrey BC V4N 3R1",
    "addr:postcode":"v4n 3r1",
    "iso:country":"CA",
    "sg:city":"Surrey",
    "sg:classifiers":[
        {
            "category":"Professional",
            "subcategory":"Computer Services",
            "type":"Services"
        }
    ],
    "sg:phone":"+1 604 882 8854",
    "sg:postcode":"V4N 3R1",
    "sg:province":"BC",
    "sg:tags":[
        "repair"
    ],
    "wof:name":"Lasernetworks",
    "wof:placetype":"venue"
},
  "geometry": {"coordinates":[-122.70056200000001,49.176857],"type":"Point"}
}