{
  "type": "Feature",
  "properties": {
    "addr:full":"Bonnyville AB T9N 1Y4",
    "addr:postcode":"t9n 1y4",
    "iso:country":"CA",
    "sg:city":"Bonnyville",
    "sg:classifiers":[
        {
            "category":"Health Services",
            "subcategory":"Medical Lab",
            "type":"Services"
        }
    ],
    "sg:phone":"+1 780 826 4306",
    "sg:postcode":"T9N 1Y4",
    "sg:province":"AB",
    "wof:name":"Bonnyville Denture Svc Ltd",
    "wof:placetype":"venue"
},
  "geometry": {"coordinates":[-110.748970032,54.2678222656],"type":"Point"}
}