{
  "type": "Feature",
  "properties": {
    "addr:full":"2900 Tillicum Rd Victoria BC V9A 2A5",
    "addr:housenumber":"2900",
    "addr:postcode":"v9a 2a5",
    "addr:street":"Tillicum Rd",
    "iso:country":"CA",
    "sg:address":"2900 Tillicum Rd",
    "sg:city":"Victoria",
    "sg:classifiers":[
        {
            "category":"Restaurant",
            "type":"Food & Drink"
        }
    ],
    "sg:phone":"+1 250 386 1116",
    "sg:postcode":"V9A 2A5",
    "sg:province":"BC",
    "wof:name":"IL Greco Pizzeria",
    "wof:placetype":"venue"
},
  "geometry": {"coordinates":[-123.36451700000001,48.428314],"type":"Point"}
}