{
  "type": "Feature",
  "properties": {
    "addr:full":"1178 Ch Principal Saint-Joseph-Du-Lac QC J0N 1M0",
    "addr:housenumber":"1178",
    "addr:postcode":"j0n 1m0",
    "addr:street":"Ch Principal",
    "iso:country":"CA",
    "sg:address":"1178 Ch Principal",
    "sg:city":"Saint-Joseph-Du-Lac",
    "sg:classifiers":[
        {
            "category":"Retail",
            "subcategory":"Auto Repair",
            "type":"Services"
        }
    ],
    "sg:phone":"+1 450 472 9838",
    "sg:postcode":"J0N 1M0",
    "sg:province":"QC",
    "sg:tags":[
        "repairing",
        "automobile"
    ],
    "wof:name":"Garage Michel Lafrance",
    "wof:placetype":"venue"
},
  "geometry": {"coordinates":[-74.0095367432,45.5357818604],"type":"Point"}
}