{
  "type": "Feature",
  "properties": {
    "iso:country":"CA",
    "sg:address":"377 Simcoe St S",
    "sg:city":"Oshawa",
    "sg:classifiers":[
        {
            "category":"Education",
            "subcategory":"Special Training",
            "type":"Public Place"
        }
    ],
    "sg:phone":"+1 905 436 9402",
    "sg:postcode":"L1H 4J2",
    "sg:province":"ON",
    "sg:tags":[
        "instruction",
        "driving"
    ],
    "wof:name":"G2 Driving School",
    "wof:placetype":"venue"
},
  "geometry": {"coordinates":[-78.8589096069,43.8877639771],"type":"Point"}
}