{
  "type": "Feature",
  "properties": {
    "addr:full":"143 Boul Maple Chateauguay QC J6J 3R1",
    "addr:housenumber":"143",
    "addr:postcode":"j6j 3r1",
    "addr:street":"Boul Maple",
    "iso:country":"CA",
    "sg:address":"143 Boul Maple",
    "sg:city":"Chateauguay",
    "sg:classifiers":[
        {
            "category":"Personal",
            "subcategory":"Beauty Salon",
            "type":"Services"
        }
    ],
    "sg:phone":"+1 450 692 5515",
    "sg:postcode":"J6J 3R1",
    "sg:province":"QC",
    "wof:name":"Elixir Coiffure Esthetique",
    "wof:placetype":"venue"
},
  "geometry": {"coordinates":[-73.73100280760001,45.3664779663],"type":"Point"}
}