{
  "type": "Feature",
  "properties": {
    "addr:full":"14 Conway St Barrys Bay ON K0J 1B0",
    "addr:housenumber":"14",
    "addr:postcode":"k0j 1b0",
    "addr:street":"Conway St",
    "iso:country":"CA",
    "sg:address":"14 Conway St",
    "sg:city":"Barrys Bay",
    "sg:classifiers":[
        {
            "category":"Home & Garden",
            "subcategory":"Building Materials",
            "type":"Retail Goods"
        }
    ],
    "sg:phone":"+1 613 756 7066",
    "sg:postcode":"K0J 1B0",
    "sg:province":"ON",
    "sg:tags":[
        "door"
    ],
    "wof:name":"Madawaska Doors Inc",
    "wof:placetype":"venue"
},
  "geometry": {"coordinates":[-77.68189239500001,45.4889030457],"type":"Point"}
}