{
  "type": "Feature",
  "properties": {
    "addr:full":"447 Bernard Ave Kelowna BC V1Y 6N8",
    "addr:housenumber":"447",
    "addr:postcode":"v1y 6n8",
    "addr:street":"Bernard Ave",
    "iso:country":"CA",
    "sg:address":"447 Bernard Ave",
    "sg:city":"Kelowna",
    "sg:classifiers":[
        {
            "category":"Shopping",
            "subcategory":"Jewelry",
            "type":"Retail Goods"
        }
    ],
    "sg:phone":"+1 250 762 4274",
    "sg:postcode":"V1Y 6N8",
    "sg:province":"BC",
    "sg:tags":[
        "jeweler"
    ],
    "wof:name":"Wendt's",
    "wof:placetype":"venue"
},
  "geometry": {"coordinates":[-119.494347,49.886169],"type":"Point"}
}