{
  "type": "Feature",
  "properties": {
    "iso:country":"CA",
    "sg:address":"234 Rue Fleury O",
    "sg:city":"Montreal",
    "sg:classifiers":[
        {
            "category":"Restaurant",
            "type":"Food & Drink"
        }
    ],
    "sg:phone":"+1 514 387 1653",
    "sg:postcode":"H3L 1T7",
    "sg:province":"QC",
    "wof:name":"Chez France & Pietro Rstrnt",
    "wof:placetype":"venue"
},
  "geometry": {"coordinates":[-73.663452,45.550476],"type":"Point"}
}