{
  "type": "Feature",
  "properties": {
    "addr:full":"2328 Rue Ontario E Montreal QC H2K 1W1",
    "addr:housenumber":"2328",
    "addr:postcode":"h2k 1w1",
    "addr:street":"Rue Ontario E",
    "iso:country":"CA",
    "sg:address":"2328 Rue Ontario E",
    "sg:city":"Montreal",
    "sg:classifiers":[
        {
            "category":"Professional",
            "subcategory":"Lawyer & Legal Services",
            "type":"Services"
        }
    ],
    "sg:phone":"+1 514 527 8903",
    "sg:postcode":"H2K 1W1",
    "sg:province":"QC",
    "sg:tags":[
        "attorney"
    ],
    "wof:name":"Arsenault & Lemieux",
    "wof:placetype":"venue"
},
  "geometry": {"coordinates":[-73.554619,45.530621],"type":"Point"}
}