{
  "type": "Feature",
  "properties": {
    "addr:full":"17673 Rue Gowdridge Pierrefonds QC H9J 3L5",
    "addr:housenumber":"17673",
    "addr:postcode":"h9j 3l5",
    "addr:street":"Rue Gowdridge",
    "iso:country":"CA",
    "sg:address":"17673 Rue Gowdridge",
    "sg:city":"Pierrefonds",
    "sg:classifiers":[
        {
            "category":"Manufacturing",
            "subcategory":"Tools & Machinery",
            "type":"Manufacturing & Wholesale Goods"
        }
    ],
    "sg:phone":"+1 514 624 1520",
    "sg:postcode":"H9J 3L5",
    "sg:province":"QC",
    "sg:tags":[
        "equipment",
        "system",
        "automation"
    ],
    "wof:name":"Delta-Matic",
    "wof:placetype":"venue"
},
  "geometry": {"coordinates":[-73.8786849976,45.4554367065],"type":"Point"}
}