{
  "type": "Feature",
  "properties": {
    "addr:full":"Nepean ON K2E 7X1",
    "addr:postcode":"k2e 7x1",
    "iso:country":"CA",
    "sg:city":"Nepean",
    "sg:classifiers":[
        {
            "category":"Building & Trades",
            "subcategory":"Construction",
            "type":"Services"
        }
    ],
    "sg:phone":"+1 613 228 9620",
    "sg:postcode":"K2E 7X1",
    "sg:province":"ON",
    "sg:tags":[
        "dry wall",
        "contractor"
    ],
    "wof:name":"Croma Drywall Inc",
    "wof:placetype":"venue"
},
  "geometry": {"coordinates":[-75.708641,45.333065],"type":"Point"}
}