{
  "type": "Feature",
  "properties": {
    "addr:full":"134 Av Atwater Montreal QC H4C 2G3",
    "addr:postcode":"h4c 2g3",
    "addr:street":"134 Av Atwater",
    "iso:country":"CA",
    "sg:address":"134 Av Atwater",
    "sg:city":"Montreal",
    "sg:classifiers":[
        {
            "category":"Food & Beverages",
            "subcategory":"Dairy",
            "type":"Retail Goods"
        }
    ],
    "sg:phone":"+1 514 932 4653",
    "sg:postcode":"H4C 2G3",
    "sg:province":"QC",
    "sg:tags":[
        "cheese"
    ],
    "wof:name":"Fromagerie Du Marche Atwater",
    "wof:placetype":"venue"
},
  "geometry": {"coordinates":[-73.576171875,45.4796066284],"type":"Point"}
}