{
  "type": "Feature",
  "properties": {
    "addr:full":"2535 Blackwell St # 104A Ottawa ON K1B 4E4",
    "addr:housenumber":"2535",
    "addr:postcode":"k1b 4e4",
    "addr:street":"Blackwell St # 104A",
    "iso:country":"CA",
    "sg:address":"2535 Blackwell St # 104A",
    "sg:city":"Ottawa",
    "sg:classifiers":[
        {
            "category":"Retail",
            "subcategory":"Auto Repair",
            "type":"Services"
        }
    ],
    "sg:phone":"+1 613 741 7077",
    "sg:postcode":"K1B 4E4",
    "sg:province":"ON",
    "sg:tags":[
        "body",
        "automobile",
        "painting"
    ],
    "wof:name":"Oxford Paint & Collision Ctr",
    "wof:placetype":"venue"
},
  "geometry": {"coordinates":[-75.609528,45.405106],"type":"Point"}
}