{
  "type": "Feature",
  "properties": {
    "iso:country":"CA",
    "sg:address":"969 Rue Dufferin",
    "sg:city":"Canton-DE-Granby",
    "sg:classifiers":[
        {
            "category":"Retail",
            "subcategory":"Auto Repair",
            "type":"Services"
        }
    ],
    "sg:phone":"+1 450 372 9119",
    "sg:postcode":"J2G 9H8",
    "sg:province":"QC",
    "sg:tags":[
        "repairing",
        "automobile"
    ],
    "wof:name":"Garage Guy Royer Esso",
    "wof:placetype":"venue"
},
  "geometry": {"coordinates":[-72.7217712402,45.3979949951],"type":"Point"}
}