{
  "type": "Feature",
  "properties": {
    "addr:full":"431 Av Guerin Alma QC G8B 7J1",
    "addr:postcode":"g8b 7j1",
    "addr:street":"431 Av Guerin",
    "iso:country":"CA",
    "sg:address":"431 Av Guerin",
    "sg:city":"Alma",
    "sg:classifiers":[
        {
            "category":"Building & Trades",
            "subcategory":"Cleaning & Sanitation",
            "type":"Services"
        }
    ],
    "sg:phone":"+1 418 662 4068",
    "sg:postcode":"G8B 7J1",
    "sg:province":"QC",
    "sg:tags":[
        "janitor"
    ],
    "wof:name":"Maxi-Net Enrg",
    "wof:placetype":"venue"
},
  "geometry": {"coordinates":[-71.63533,48.555065],"type":"Point"}
}