{
  "type": "Feature",
  "properties": {
    "addr:full":"Napanee ON K7R 3L2",
    "addr:postcode":"k7r 3l2",
    "iso:country":"CA",
    "sg:city":"Napanee",
    "sg:classifiers":[
        {
            "category":"Retail",
            "subcategory":"Auto Repair",
            "type":"Services"
        }
    ],
    "sg:phone":"+1 613 388 2923",
    "sg:postcode":"K7R 3L2",
    "sg:province":"ON",
    "sg:tags":[
        "truck"
    ],
    "wof:name":"Town & Country Auto Body",
    "wof:placetype":"venue"
},
  "geometry": {"coordinates":[-76.951584,44.248325],"type":"Point"}
}