{
  "type": "Feature",
  "properties": {
    "addr:full":"81 Paramount Rd Winnipeg MB R2X 2W6",
    "addr:housenumber":"81",
    "addr:postcode":"r2x 2w6",
    "addr:street":"Paramount Rd",
    "iso:country":"CA",
    "sg:address":"81 Paramount Rd",
    "sg:city":"Winnipeg",
    "sg:classifiers":[
        {
            "category":"Manufacturing",
            "subcategory":"Rubber & Plastics",
            "type":"Manufacturing & Wholesale Goods"
        }
    ],
    "sg:phone":"+1 204 633 9256",
    "sg:postcode":"R2X 2W6",
    "sg:province":"MB",
    "sg:tags":[
        "product"
    ],
    "wof:name":"Johnston Industrial Plastics",
    "wof:placetype":"venue"
},
  "geometry": {"coordinates":[-97.192024,49.94849],"type":"Point"}
}