{
  "type": "Feature",
  "properties": {
    "addr:full":"15148 North Bluff Rd White Rock BC V4B 3E5",
    "addr:housenumber":"15148",
    "addr:postcode":"v4b 3e5",
    "addr:street":"North Bluff Rd",
    "iso:country":"CA",
    "sg:address":"15148 North Bluff Rd",
    "sg:city":"White Rock",
    "sg:classifiers":[
        {
            "category":"Travel",
            "subcategory":"Travel Agent",
            "type":"Entertainment"
        }
    ],
    "sg:phone":"+1 604 538 2111",
    "sg:postcode":"V4B 3E5",
    "sg:province":"BC",
    "sg:tags":[
        "agency",
        "bureau"
    ],
    "wof:name":"Uniglobe Travelex",
    "wof:placetype":"venue"
},
  "geometry": {"coordinates":[-122.802483,49.030987],"type":"Point"}
}