{
  "type": "Feature",
  "properties": {
    "iso:country":"CA",
    "sg:address":"8793 Commercial St",
    "sg:city":"New Minas",
    "sg:classifiers":[
        {
            "category":"Autos & Motor Vehicles",
            "subcategory":"Auto Supplies",
            "type":"Retail Goods"
        }
    ],
    "sg:phone":"+1 902 681 8944",
    "sg:postcode":"B4N 3C4",
    "sg:province":"NS",
    "sg:tags":[
        "automobile",
        "parts"
    ],
    "wof:name":"Napa Auto Parts",
    "wof:placetype":"venue"
},
  "geometry": {"coordinates":[-64.4718093872,45.0703811646],"type":"Point"}
}