{
  "type": "Feature",
  "properties": {
    "iso:country":"CA",
    "sg:address":"1106 Winnipeg St",
    "sg:city":"Regina",
    "sg:classifiers":[
        {
            "category":"Health Services",
            "subcategory":"Doctor",
            "type":"Services"
        }
    ],
    "sg:phone":"+1 306 543 7880",
    "sg:postcode":"S4R 1J6",
    "sg:province":"SK",
    "sg:tags":[
        "physician",
        "surgeon"
    ],
    "wof:name":"Logan, Dolores MD",
    "wof:placetype":"venue"
},
  "geometry": {"coordinates":[-104.595443726,50.4611587524],"type":"Point"}
}