{
  "type": "Feature",
  "properties": {
    "addr:full":"7115 Nesters Rd Whistler BC V0N 1B7",
    "addr:housenumber":"7115",
    "addr:postcode":"v0n 1b7",
    "addr:street":"Nesters Rd",
    "iso:country":"CA",
    "sg:address":"7115 Nesters Rd",
    "sg:city":"Whistler",
    "sg:classifiers":[
        {
            "category":"Travel",
            "subcategory":"Hotels & Motels",
            "type":"Entertainment"
        }
    ],
    "sg:phone":"+1 604 932 3113",
    "sg:postcode":"V0N 1B7",
    "sg:province":"BC",
    "sg:tags":[
        "breakfast",
        "accommodation",
        "bed"
    ],
    "wof:name":"Haus-Heidi-Pension Lodge",
    "wof:placetype":"venue"
},
  "geometry": {"coordinates":[-122.95871,50.124851],"type":"Point"}
}