{
  "type": "Feature",
  "properties": {
    "addr:full":"RR 1 Westerose AB T0C 2V0",
    "addr:postcode":"t0c 2v0",
    "addr:street":"Rr 1",
    "iso:country":"CA",
    "sg:address":"RR 1",
    "sg:city":"Westerose",
    "sg:classifiers":[
        {
            "category":"Organizations",
            "subcategory":"Religious Organization",
            "type":"Services"
        }
    ],
    "sg:phone":"+1 780 586 2719",
    "sg:postcode":"T0C 2V0",
    "sg:province":"AB",
    "sg:tags":[
        "church"
    ],
    "wof:name":"Battle Lake Community Baptist",
    "wof:placetype":"venue"
},
  "geometry": {"coordinates":[-114.018669128,52.9597511292],"type":"Point"}
}