{
  "type": "Feature",
  "properties": {
    "addr:full":"111 Rue Jean-Proulx Hull QC J8Z 1T4",
    "addr:housenumber":"111",
    "addr:postcode":"j8z 1t4",
    "addr:street":"Rue Jean-Proulx",
    "iso:country":"CA",
    "sg:address":"111 Rue Jean-Proulx",
    "sg:city":"Hull",
    "sg:classifiers":[
        {
            "category":"Local Transit",
            "type":"Transportation"
        }
    ],
    "sg:phone":"+1 819 770 3242",
    "sg:postcode":"J8Z 1T4",
    "sg:province":"QC",
    "sg:tags":[
        "line"
    ],
    "wof:name":"Societe-Transport-L'Outaouais",
    "wof:placetype":"venue"
},
  "geometry": {"coordinates":[-75.734978,45.466427],"type":"Point"}
}