{
  "type": "Feature",
  "properties": {
    "addr:full":"19 Pettipas Dr # F Dartmouth NS B3B 1K1",
    "addr:housenumber":"19",
    "addr:postcode":"b3b 1k1",
    "addr:street":"Pettipas Dr # F",
    "iso:country":"CA",
    "sg:address":"19 Pettipas Dr # F",
    "sg:city":"Dartmouth",
    "sg:classifiers":[
        {
            "category":"Retail",
            "subcategory":"Repair Shop",
            "type":"Services"
        }
    ],
    "sg:phone":"+1 902 468 4888",
    "sg:postcode":"B3B 1K1",
    "sg:province":"NS",
    "sg:tags":[
        "sharpening"
    ],
    "wof:name":"Deiter's Tool & Saw Svc",
    "wof:placetype":"venue"
},
  "geometry": {"coordinates":[-63.612293,44.710434],"type":"Point"}
}