{
  "type": "Feature",
  "properties": {
    "addr:full":"2114 14 Ave Wainwright AB T9W 1L2",
    "addr:housenumber":"2114",
    "addr:postcode":"t9w 1l2",
    "addr:street":"14 Ave",
    "iso:country":"CA",
    "sg:address":"2114 14 Ave",
    "sg:city":"Wainwright",
    "sg:classifiers":[
        {
            "category":"Travel",
            "subcategory":"Hotels & Motels",
            "type":"Entertainment"
        }
    ],
    "sg:phone":"+1 780 842 3371",
    "sg:postcode":"T9W 1L2",
    "sg:province":"AB",
    "wof:name":"Springs Motor Inn",
    "wof:placetype":"venue"
},
  "geometry": {"coordinates":[-110.84025573700001,52.8435325623],"type":"Point"}
}