{
  "type": "Feature",
  "properties": {
    "addr:full":"236 Avenue V N Saskatoon SK S7L 3E6",
    "addr:housenumber":"236",
    "addr:postcode":"s7l 3e6",
    "addr:street":"Avenue V N",
    "iso:country":"CA",
    "sg:address":"236 Avenue V N",
    "sg:city":"Saskatoon",
    "sg:classifiers":[
        {
            "category":"Education",
            "subcategory":"Special Training",
            "type":"Public Place"
        }
    ],
    "sg:phone":"+1 306 683 0888",
    "sg:postcode":"S7L 3E6",
    "sg:province":"SK",
    "sg:tags":[
        "instruction",
        "music"
    ],
    "wof:name":"Lions Band",
    "wof:placetype":"venue"
},
  "geometry": {"coordinates":[-106.70396423299999,52.1308670044],"type":"Point"}
}