{
  "type": "Feature",
  "properties": {
    "addr:full":"Peterborough ON K9J 6X9",
    "addr:postcode":"k9j 6x9",
    "iso:country":"CA",
    "sg:city":"Peterborough",
    "sg:classifiers":[
        {
            "category":"Food & Beverages",
            "subcategory":"Groceries & Convenience Stores",
            "type":"Retail Goods"
        }
    ],
    "sg:phone":"+1 705 295 6850",
    "sg:postcode":"K9J 6X9",
    "sg:province":"ON",
    "sg:tags":[
        "poultry"
    ],
    "wof:name":"Three Roads Farms Ltd",
    "wof:placetype":"venue"
},
  "geometry": {"coordinates":[-78.32131195069999,44.3007316589],"type":"Point"}
}