{
  "type": "Feature",
  "properties": {
    "addr:full":"560 Squier Pl Thunder Bay ON P7B 6M2",
    "addr:housenumber":"560",
    "addr:postcode":"p7b 6m2",
    "addr:street":"Squier Pl",
    "iso:country":"CA",
    "sg:address":"560 Squier Pl",
    "sg:city":"Thunder Bay",
    "sg:classifiers":[
        {
            "category":"Real Estate",
            "subcategory":"Developer",
            "type":"Services"
        }
    ],
    "sg:phone":"+1 807 345 1204",
    "sg:postcode":"P7B 6M2",
    "sg:province":"ON",
    "wof:name":"Tom Jones & Sons Ltd",
    "wof:placetype":"venue"
},
  "geometry": {"coordinates":[-89.2448806763,48.4177093506],"type":"Point"}
}