{
  "type": "Feature",
  "properties": {
    "iso:country":"CA",
    "sg:address":"250 Rang DE LA Montagne",
    "sg:city":"Rougemont",
    "sg:classifiers":[
        {
            "category":"Retail",
            "subcategory":"Auto Repair",
            "type":"Services"
        }
    ],
    "sg:phone":"+1 450 469 2252",
    "sg:postcode":"J0L 1M0",
    "sg:province":"QC",
    "sg:tags":[
        "repairing",
        "automobile"
    ],
    "wof:name":"Garage Real Barre Inc",
    "wof:placetype":"venue"
},
  "geometry": {"coordinates":[-73.083565,45.459068],"type":"Point"}
}