{
  "type": "Feature",
  "properties": {
    "addr:full":"11965 Hall St Maple Ridge BC V2X 5L9",
    "addr:housenumber":"11965",
    "addr:postcode":"v2x 5l9",
    "addr:street":"Hall St",
    "iso:country":"CA",
    "sg:address":"11965 Hall St",
    "sg:city":"Maple Ridge",
    "sg:classifiers":[
        {
            "category":"Cinema",
            "subcategory":"Movie Rental",
            "type":"Entertainment"
        }
    ],
    "sg:phone":"+1 604 463 3900",
    "sg:postcode":"V2X 5L9",
    "sg:province":"BC",
    "sg:tags":[
        "leasing",
        "video",
        "disc",
        "tape"
    ],
    "wof:name":"How To Video Inc",
    "wof:placetype":"venue"
},
  "geometry": {"coordinates":[-122.618858,49.220013],"type":"Point"}
}