{
  "type": "Feature",
  "properties": {
    "addr:full":"Burnaby BC V3N 4Z6",
    "addr:postcode":"v3n 4z6",
    "iso:country":"CA",
    "sg:city":"Burnaby",
    "sg:classifiers":[
        {
            "category":"Education",
            "subcategory":"School",
            "type":"Public Place"
        }
    ],
    "sg:phone":"+1 604 525 6056",
    "sg:postcode":"V3N 4Z6",
    "sg:province":"BC",
    "sg:tags":[
        "academic",
        "special"
    ],
    "wof:name":"Deaf Children's Society-BC",
    "wof:placetype":"venue"
},
  "geometry": {"coordinates":[-122.940392,49.223385],"type":"Point"}
}