{
  "type": "Feature",
  "properties": {
    "addr:full":"Grande Prairie AB T8V 0X6",
    "addr:postcode":"t8v 0x6",
    "iso:country":"CA",
    "sg:city":"Grande Prairie",
    "sg:classifiers":[
        {
            "category":"Health Services",
            "subcategory":"Doctor",
            "type":"Services"
        }
    ],
    "sg:phone":"+1 780 532 1380",
    "sg:postcode":"T8V 0X6",
    "sg:province":"AB",
    "sg:tags":[
        "dentist"
    ],
    "wof:name":"Syrota, Harvey D DDS",
    "wof:placetype":"venue"
},
  "geometry": {"coordinates":[-118.788956,55.171444],"type":"Point"}
}