{
  "type": "Feature",
  "properties": {
    "addr:full":"53431 Range Road 221 Ardrossan AB T8E 2K8",
    "addr:housenumber":"53431",
    "addr:postcode":"t8e 2k8",
    "addr:street":"Range Road 221",
    "iso:country":"CA",
    "sg:address":"53431 Range Road 221",
    "sg:city":"Ardrossan",
    "sg:classifiers":[
        {
            "category":"Retail",
            "subcategory":"Repair Shop",
            "type":"Services"
        }
    ],
    "sg:phone":"+1 780 922 3289",
    "sg:postcode":"T8E 2K8",
    "sg:province":"AB",
    "sg:tags":[
        "equipment",
        "electronic",
        "supply"
    ],
    "wof:name":"G-J Electronics",
    "wof:placetype":"venue"
},
  "geometry": {"coordinates":[-113.123268127,53.5699501038],"type":"Point"}
}