{
  "type": "Feature",
  "properties": {
    "addr:full":"1917 Columbia Gdns Fruitvale BC V0G 1L0",
    "addr:housenumber":"1917",
    "addr:postcode":"v0g 1l0",
    "addr:street":"Columbia Gdns",
    "iso:country":"CA",
    "sg:address":"1917 Columbia Gdns",
    "sg:city":"Fruitvale",
    "sg:classifiers":[
        {
            "category":"Organizations",
            "subcategory":"Religious Organization",
            "type":"Services"
        }
    ],
    "sg:phone":"+1 250 367 9809",
    "sg:postcode":"V0G 1L0",
    "sg:province":"BC",
    "sg:tags":[
        "church"
    ],
    "wof:name":"St Paul's United Church",
    "wof:placetype":"venue"
},
  "geometry": {"coordinates":[-117.54722595200001,49.1146469116],"type":"Point"}
}