{
  "type": "Feature",
  "properties": {
    "addr:full":"1620 Northside River Denys Rd River Denys NS B0E 2Y0",
    "addr:housenumber":"1620",
    "addr:postcode":"b0e 2y0",
    "addr:street":"Northside River Denys Rd",
    "iso:country":"CA",
    "sg:address":"1620 Northside River Denys Rd",
    "sg:city":"River Denys",
    "sg:classifiers":[
        {
            "category":"Shopping",
            "subcategory":"Discount & Variety Stores",
            "type":"Retail Goods"
        }
    ],
    "sg:phone":"+1 902 756 2780",
    "sg:postcode":"B0E 2Y0",
    "sg:province":"NS",
    "sg:tags":[
        "merchandise",
        "general"
    ],
    "wof:name":"Mac Leans General Store",
    "wof:placetype":"venue"
},
  "geometry": {"coordinates":[-61.176205,45.834587],"type":"Point"}
}