{
  "type": "Feature",
  "properties": {
    "addr:full":"100 Rue DE Grandmont Cap-DE-LA-Madeleine QC G8T 2P9",
    "addr:housenumber":"100",
    "addr:postcode":"g8t 2p9",
    "addr:street":"Rue De Grandmont",
    "iso:country":"CA",
    "sg:address":"100 Rue DE Grandmont",
    "sg:city":"Cap-DE-LA-Madeleine",
    "sg:classifiers":[
        {
            "category":"Food & Beverages",
            "subcategory":"Groceries & Convenience Stores",
            "type":"Retail Goods"
        }
    ],
    "sg:phone":"+1 819 372 1539",
    "sg:postcode":"G8T 2P9",
    "sg:province":"QC",
    "wof:name":"Depanneur DE Grandmont",
    "wof:placetype":"venue"
},
  "geometry": {"coordinates":[-72.5271453857,46.3701438904],"type":"Point"}
}