{
  "type": "Feature",
  "properties": {
    "addr:full":"5311 Segriff Dr Mississauga ON L5V 1N9",
    "addr:housenumber":"5311",
    "addr:postcode":"l5v 1n9",
    "addr:street":"Segriff Dr",
    "iso:country":"CA",
    "sg:address":"5311 Segriff Dr",
    "sg:city":"Mississauga",
    "sg:classifiers":[
        {
            "category":"Wholesale",
            "subcategory":"Durable Goods & Equipment",
            "type":"Manufacturing & Wholesale Goods"
        }
    ],
    "sg:phone":"+1 905 813 7252",
    "sg:postcode":"L5V 1N9",
    "sg:province":"ON",
    "sg:tags":[
        "exporter"
    ],
    "wof:name":"Jsc Engineering & Trading CO",
    "wof:placetype":"venue"
},
  "geometry": {"coordinates":[-79.6878128052,43.5896377563],"type":"Point"}
}