{
  "type": "Feature",
  "properties": {
    "addr:full":"PO Box 465 Watson Lake YT Y0A 1C0",
    "addr:housenumber":"po;465",
    "addr:postcode":"y0a 1c0",
    "addr:street":"Box",
    "iso:country":"CA",
    "sg:address":"PO Box 465",
    "sg:city":"Watson Lake",
    "sg:classifiers":[
        {
            "category":"Building & Trades",
            "subcategory":"Construction",
            "type":"Services"
        }
    ],
    "sg:phone":"+1 867 536 7524",
    "sg:postcode":"Y0A 1C0",
    "sg:province":"YT",
    "sg:tags":[
        "excavating",
        "contractor"
    ],
    "wof:name":"Joe's Bobcat Svc",
    "wof:placetype":"venue"
},
  "geometry": {"coordinates":[-128.714157105,60.0629348755],"type":"Point"}
}