{
  "type": "Feature",
  "properties": {
    "iso:country":"CA",
    "sg:address":"1089 Seneca Ave",
    "sg:city":"Mississauga",
    "sg:classifiers":[
        {
            "category":"Retail",
            "subcategory":"Repair Shop",
            "type":"Services"
        }
    ],
    "sg:phone":"+1 905 278 8129",
    "sg:postcode":"L5G 3X4",
    "sg:province":"ON",
    "sg:tags":[
        "restoring",
        "furniture"
    ],
    "wof:name":"Walser Furniture Refinishing",
    "wof:placetype":"venue"
},
  "geometry": {"coordinates":[-79.57670593260001,43.5636024475],"type":"Point"}
}