{
  "type": "Feature",
  "properties": {
    "iso:country":"CA",
    "sg:address":"174 Marlborough St",
    "sg:city":"Thunder Bay",
    "sg:classifiers":[
        {
            "category":"Education",
            "subcategory":"School",
            "type":"Public Place"
        }
    ],
    "sg:phone":"+1 807 345 1468",
    "sg:postcode":"P7B 4G4",
    "sg:province":"ON",
    "wof:name":"Ecole Gron Morgan Public Schl",
    "wof:placetype":"venue"
},
  "geometry": {"coordinates":[-89.2451324463,48.4341926575],"type":"Point"}
}