{
  "type": "Feature",
  "properties": {
    "addr:full":"3 Buckland Rd North York ON M3L 1V9",
    "addr:housenumber":"3",
    "addr:postcode":"m3l 1v9",
    "addr:street":"Buckland Rd",
    "iso:country":"CA",
    "sg:address":"3 Buckland Rd",
    "sg:city":"North York",
    "sg:classifiers":[
        {
            "category":"Building & Trades",
            "subcategory":"Plumbing",
            "type":"Services"
        }
    ],
    "sg:phone":"+1 416 740 5981",
    "sg:postcode":"M3L 1V9",
    "sg:province":"ON",
    "sg:tags":[
        "contractor"
    ],
    "wof:name":"Beny Plumbing & Heating",
    "wof:placetype":"venue"
},
  "geometry": {"coordinates":[-79.5018692017,43.7373657227],"type":"Point"}
}