{
  "type": "Feature",
  "properties": {
    "addr:full":"295 Alliance Rd # 1 Milton ON L9T 4W8",
    "addr:housenumber":"295",
    "addr:postcode":"l9t 4w8",
    "addr:street":"Alliance Rd # 1",
    "iso:country":"CA",
    "sg:address":"295 Alliance Rd # 1",
    "sg:city":"Milton",
    "sg:classifiers":[
        {
            "category":"Real Estate",
            "subcategory":"Real Estate Agent",
            "type":"Services"
        }
    ],
    "sg:phone":"+1 905 876 3336",
    "sg:postcode":"L9T 4W8",
    "sg:province":"ON",
    "sg:tags":[
        "management"
    ],
    "wof:name":"Lakeshore Management",
    "wof:placetype":"venue"
},
  "geometry": {"coordinates":[-79.892906189,43.5250968933],"type":"Point"}
}