{
  "type": "Feature",
  "properties": {
    "addr:full":"3308 Quesnel Hydraulic Rd Quesnel BC V2J 6N7",
    "addr:housenumber":"3308",
    "addr:postcode":"v2j 6n7",
    "addr:street":"Hydraulic Rd",
    "iso:country":"CA",
    "sg:address":"3308 Quesnel Hydraulic Rd",
    "sg:city":"Quesnel",
    "sg:classifiers":[
        {
            "category":"Retail",
            "subcategory":"Auto Repair",
            "type":"Services"
        }
    ],
    "sg:phone":"+1 250 747 1348",
    "sg:postcode":"V2J 6N7",
    "sg:province":"BC",
    "sg:tags":[
        "repairing",
        "automobile"
    ],
    "wof:name":"Terry's Auto Lab",
    "wof:placetype":"venue"
},
  "geometry": {"coordinates":[-122.423034668,52.9721107483],"type":"Point"}
}