{
  "type": "Feature",
  "properties": {
    "addr:full":"87 Main St Landmark MB R0A 0X0",
    "addr:housenumber":"87",
    "addr:postcode":"r0a 0x0",
    "addr:street":"Main St",
    "iso:country":"CA",
    "sg:address":"87 Main St",
    "sg:city":"Landmark",
    "sg:classifiers":[
        {
            "category":"Wholesale",
            "subcategory":"Hardware",
            "type":"Manufacturing & Wholesale Goods"
        }
    ],
    "sg:phone":"+1 204 355 4163",
    "sg:postcode":"R0A 0X0",
    "sg:province":"MB",
    "sg:tags":[
        "tool"
    ],
    "wof:name":"Landmark Auto Ctr",
    "wof:placetype":"venue"
},
  "geometry": {"coordinates":[-96.819969,49.664165],"type":"Point"}
}