{
  "type": "Feature",
  "properties": {
    "addr:full":"306 Boul Cremazie O Montreal QC H2P 1C6",
    "addr:housenumber":"306",
    "addr:postcode":"h2p 1c6",
    "addr:street":"Boul Cremazie O",
    "iso:country":"CA",
    "sg:address":"306 Boul Cremazie O",
    "sg:city":"Montreal",
    "sg:classifiers":[
        {
            "category":"Manufacturing",
            "subcategory":"Paper Products",
            "type":"Manufacturing & Wholesale Goods"
        }
    ],
    "sg:phone":"+1 514 385 6297",
    "sg:postcode":"H2P 1C6",
    "sg:province":"QC",
    "sg:tags":[
        "corrugated",
        "box",
        "fiber",
        "leasing",
        "renting",
        "solid",
        "truck"
    ],
    "wof:name":"U-Haul Cie Ltee",
    "wof:placetype":"venue"
},
  "geometry": {"coordinates":[-73.6393127441,45.5442733765],"type":"Point"}
}