{
  "type": "Feature",
  "properties": {
    "addr:full":"135 Rue Saint-Joseph E Quebec QC G1K 3A8",
    "addr:housenumber":"135",
    "addr:postcode":"g1k 3a8",
    "addr:street":"Rue Saint-Joseph E",
    "iso:country":"CA",
    "sg:address":"135 Rue Saint-Joseph E",
    "sg:city":"Quebec",
    "sg:classifiers":[
        {
            "category":"Shopping",
            "subcategory":"Florist",
            "type":"Retail Goods"
        }
    ],
    "sg:phone":"+1 418 524 5218",
    "sg:postcode":"G1K 3A8",
    "sg:province":"QC",
    "wof:name":"Au Salon Fleuri Inc",
    "wof:placetype":"venue"
},
  "geometry": {"coordinates":[-71.22923299999999,46.812584],"type":"Point"}
}