{
  "type": "Feature",
  "properties": {
    "addr:full":"19 Charlotte St Toronto ON M5V 2H5",
    "addr:housenumber":"19",
    "addr:postcode":"m5v 2h5",
    "addr:street":"Charlotte St",
    "iso:country":"CA",
    "sg:address":"19 Charlotte St",
    "sg:city":"Toronto",
    "sg:classifiers":[
        {
            "category":"Professional",
            "subcategory":"Employment Agencies",
            "type":"Services"
        }
    ],
    "sg:phone":"+1 416 593 7904",
    "sg:postcode":"M5V 2H5",
    "sg:province":"ON",
    "sg:tags":[
        "modeling"
    ],
    "wof:name":"W M Models",
    "wof:placetype":"venue"
},
  "geometry": {"coordinates":[-79.3938446045,43.646572113],"type":"Point"}
}