{
  "type": "Feature",
  "properties": {
    "iso:country":"CA",
    "sg:address":"2046 Avenue Rd",
    "sg:city":"North York",
    "sg:classifiers":[
        {
            "category":"Personal",
            "subcategory":"Beauty Salon",
            "type":"Services"
        }
    ],
    "sg:phone":"+1 416 483 7868",
    "sg:postcode":"M5M 4A6",
    "sg:province":"ON",
    "sg:tags":[
        "manicuring"
    ],
    "wof:name":"Kim's Nail Salon",
    "wof:placetype":"venue"
},
  "geometry": {"coordinates":[-79.420311,43.736088],"type":"Point"}
}