{
  "type": "Feature",
  "properties": {
    "addr:full":"462 Mcnicoll Ave North York ON M2H 2E1",
    "addr:housenumber":"462",
    "addr:postcode":"m2h 2e1",
    "addr:street":"Mcnicoll Ave",
    "iso:country":"CA",
    "sg:address":"462 Mcnicoll Ave",
    "sg:city":"North York",
    "sg:classifiers":[
        {
            "category":"Shopping",
            "subcategory":"Musical Instruments",
            "type":"Retail Goods"
        }
    ],
    "sg:phone":"+1 416 499 6122",
    "sg:postcode":"M2H 2E1",
    "sg:province":"ON",
    "wof:name":"House of Raga",
    "wof:placetype":"venue"
},
  "geometry": {"coordinates":[-79.340965271,43.8037261963],"type":"Point"}
}