{
  "type": "Feature",
  "properties": {
    "addr:full":"655 Adams St Regina SK S4N 6R7",
    "addr:housenumber":"655",
    "addr:postcode":"s4n 6r7",
    "addr:street":"Adams St",
    "iso:country":"CA",
    "sg:address":"655 Adams St",
    "sg:city":"Regina",
    "sg:classifiers":[
        {
            "category":"Building & Trades",
            "subcategory":"Construction",
            "type":"Services"
        }
    ],
    "sg:phone":"+1 306 537 6608",
    "sg:postcode":"S4N 6R7",
    "sg:province":"SK",
    "sg:tags":[
        "concrete",
        "waterproofing",
        "contractor"
    ],
    "wof:name":"Northern Tar & Tile Ltd",
    "wof:placetype":"venue"
},
  "geometry": {"coordinates":[-104.591393,50.468544],"type":"Point"}
}