{
  "type": "Feature",
  "properties": {
    "addr:full":"1177 Ridley Dr Burnaby BC V5A 2N7",
    "addr:housenumber":"1177",
    "addr:postcode":"v5a 2n7",
    "addr:street":"Ridley Dr",
    "iso:country":"CA",
    "sg:address":"1177 Ridley Dr",
    "sg:city":"Burnaby",
    "sg:classifiers":[
        {
            "category":"Building & Trades",
            "subcategory":"Plumbing",
            "type":"Services"
        }
    ],
    "sg:phone":"+1 604 420 2245",
    "sg:postcode":"V5A 2N7",
    "sg:province":"BC",
    "sg:tags":[
        "contractor"
    ],
    "wof:name":"Usinger Plumbing Heating & Gas",
    "wof:placetype":"venue"
},
  "geometry": {"coordinates":[-122.954086,49.27319],"type":"Point"}
}