{
  "type": "Feature",
  "properties": {
    "iso:country":"CA",
    "sg:address":"453 Brant St",
    "sg:city":"Burlington",
    "sg:classifiers":[
        {
            "category":"Shopping",
            "subcategory":"Shoes",
            "type":"Retail Goods"
        }
    ],
    "sg:phone":"+1 905 333 9229",
    "sg:postcode":"L7R 2G3",
    "sg:province":"ON",
    "wof:name":"What A Heel",
    "wof:placetype":"venue"
},
  "geometry": {"coordinates":[-79.799126,43.326771],"type":"Point"}
}