{
  "type": "Feature",
  "properties": {
    "addr:full":"3417 30 Ave Vernon BC V1T 2E3",
    "addr:housenumber":"3417",
    "addr:postcode":"v1t 2e3",
    "addr:street":"30 Ave",
    "iso:country":"CA",
    "sg:address":"3417 30 Ave",
    "sg:city":"Vernon",
    "sg:classifiers":[
        {
            "category":"Food & Beverages",
            "subcategory":"Groceries & Convenience Stores",
            "type":"Retail Goods"
        }
    ],
    "sg:phone":"+1 250 542 8008",
    "sg:postcode":"V1T 2E3",
    "sg:province":"BC",
    "sg:tags":[
        "pharmacy"
    ],
    "wof:name":"Canada Safeway Ltd",
    "wof:placetype":"venue"
},
  "geometry": {"coordinates":[-119.279465,50.26384],"type":"Point"}
}