{
  "type": "Feature",
  "properties": {
    "addr:full":"230 Main St W Port Colborne ON L3K 3V5",
    "addr:housenumber":"230",
    "addr:postcode":"l3k 3v5",
    "addr:street":"Main St W",
    "iso:country":"CA",
    "sg:address":"230 Main St W",
    "sg:city":"Port Colborne",
    "sg:classifiers":[
        {
            "category":"Restaurant",
            "type":"Food & Drink"
        }
    ],
    "sg:phone":"+1 905 835 6944",
    "sg:postcode":"L3K 3V5",
    "sg:province":"ON",
    "sg:tags":[
        "sandwich"
    ],
    "wof:name":"Subway Sandwiches & Salads",
    "wof:placetype":"venue"
},
  "geometry": {"coordinates":[-79.25309,42.899372],"type":"Point"}
}