{
  "type": "Feature",
  "properties": {
    "addr:full":"Calgary AB T2E 7Y2",
    "addr:postcode":"t2e 7y2",
    "iso:country":"CA",
    "sg:city":"Calgary",
    "sg:classifiers":[
        {
            "category":"Health Services",
            "subcategory":"Chiropractor",
            "type":"Services"
        }
    ],
    "sg:phone":"+1 403 230 0066",
    "sg:postcode":"T2E 7Y2",
    "sg:province":"AB",
    "wof:name":"On Centre Chiropractic",
    "wof:placetype":"venue"
},
  "geometry": {"coordinates":[-114.062637329,51.0670471191],"type":"Point"}
}