{
  "type": "Feature",
  "properties": {
    "addr:full":"31 Gordon Dr Charlottetown PE C1A 6B8",
    "addr:housenumber":"31",
    "addr:postcode":"c1a 6b8",
    "addr:street":"Gordon Dr",
    "iso:country":"CA",
    "sg:address":"31 Gordon Dr",
    "sg:city":"Charlottetown",
    "sg:classifiers":[
        {
            "category":"Government",
            "subcategory":"Office",
            "type":"Public Place"
        }
    ],
    "sg:phone":"+1 902 368 5282",
    "sg:postcode":"C1A 6B8",
    "sg:province":"PE",
    "wof:name":"Pei Land Policy",
    "wof:placetype":"venue"
},
  "geometry": {"coordinates":[-63.116318,46.259552],"type":"Point"}
}