{
  "type": "Feature",
  "properties": {
    "addr:full":"50 Rue Lapointe Clermont QC G4A 1A1",
    "addr:housenumber":"50",
    "addr:postcode":"g4a 1a1",
    "addr:street":"Rue Lapointe",
    "iso:country":"CA",
    "sg:address":"50 Rue Lapointe",
    "sg:city":"Clermont",
    "sg:classifiers":[
        {
            "category":"Education",
            "subcategory":"Library",
            "type":"Public Place"
        }
    ],
    "sg:phone":"+1 418 439 2903",
    "sg:postcode":"G4A 1A1",
    "sg:province":"QC",
    "sg:tags":[
        "government"
    ],
    "wof:name":"Clermont Bibliotheque Mncpl",
    "wof:placetype":"venue"
},
  "geometry": {"coordinates":[-70.22342681879999,47.6925048828],"type":"Point"}
}