{
  "type": "Feature",
  "properties": {
    "iso:country":"CA",
    "sg:city":"Richmond",
    "sg:classifiers":[
        {
            "category":"Shopping",
            "type":"Retail Goods"
        }
    ],
    "sg:phone":"+1 604 270 9965",
    "sg:postcode":"V6V 2L9",
    "sg:province":"BC",
    "sg:tags":[
        "equipment",
        "supply",
        "wine"
    ],
    "wof:name":"Bayou Brewing Club",
    "wof:placetype":"venue"
},
  "geometry": {"coordinates":[-123.080521,49.187248],"type":"Point"}
}