{
  "type": "Feature",
  "properties": {
    "iso:country":"CA",
    "sg:address":"3415 Plummer Ave",
    "sg:city":"New Waterford",
    "sg:classifiers":[
        {
            "category":"Shopping",
            "subcategory":"Pharmacy",
            "type":"Retail Goods"
        }
    ],
    "sg:phone":"+1 902 862 7105",
    "sg:postcode":"B1H 1Z2",
    "sg:province":"NS",
    "wof:name":"Lawton's Drugs",
    "wof:placetype":"venue"
},
  "geometry": {"coordinates":[-60.087296,46.249283],"type":"Point"}
}