{
  "type": "Feature",
  "properties": {
    "addr:full":"3654 Rue Saint-Denis Montreal QC H2X 3L7",
    "addr:housenumber":"3654",
    "addr:postcode":"h2x 3l7",
    "addr:street":"Rue Saint-Denis",
    "iso:country":"CA",
    "sg:address":"3654 Rue Saint-Denis",
    "sg:city":"Montreal",
    "sg:classifiers":[
        {
            "category":"Retail",
            "subcategory":"Laundry & Dry Cleaning",
            "type":"Services"
        }
    ],
    "sg:phone":"+1 514 844 4763",
    "sg:postcode":"H2X 3L7",
    "sg:province":"QC",
    "sg:tags":[
        "cleaners"
    ],
    "wof:name":"Nettoyeurs Daoust",
    "wof:placetype":"venue"
},
  "geometry": {"coordinates":[-73.5701751709,45.5181121826],"type":"Point"}
}