{
  "type": "Feature",
  "properties": {
    "addr:full":"11955 Rue Henry-Giffard Mirabel QC J7N 1G3",
    "addr:housenumber":"11955",
    "addr:postcode":"j7n 1g3",
    "addr:street":"Rue Henry-Giffard",
    "iso:country":"CA",
    "sg:address":"11955 Rue Henry-Giffard",
    "sg:city":"Mirabel",
    "sg:classifiers":[
        {
            "category":"Government",
            "subcategory":"Office",
            "type":"Public Place"
        }
    ],
    "sg:phone":"+1 450 476 3052",
    "sg:postcode":"J7N 1G3",
    "sg:province":"QC",
    "wof:name":"Canada Secteur Commercial",
    "wof:placetype":"venue"
},
  "geometry": {"coordinates":[-74.0483627319,45.6761856079],"type":"Point"}
}