{
  "type": "Feature",
  "properties": {
    "addr:full":"866 Autumnwood Dr Winnipeg MB R2J 1C1",
    "addr:housenumber":"866",
    "addr:postcode":"r2j 1c1",
    "addr:street":"Autumnwood Dr",
    "iso:country":"CA",
    "sg:address":"866 Autumnwood Dr",
    "sg:city":"Winnipeg",
    "sg:classifiers":[
        {
            "category":"Education",
            "subcategory":"School",
            "type":"Public Place"
        }
    ],
    "sg:phone":"+1 204 257 0609",
    "sg:postcode":"R2J 1C1",
    "sg:province":"MB",
    "wof:name":"Frontenac School",
    "wof:placetype":"venue"
},
  "geometry": {"coordinates":[-97.080871582,49.8671646118],"type":"Point"}
}