{
  "type": "Feature",
  "properties": {
    "iso:country":"CA",
    "sg:address":"831 Campbell Ave",
    "sg:city":"Ottawa",
    "sg:classifiers":[
        {
            "category":"Building & Trades",
            "subcategory":"Plumbing",
            "type":"Services"
        }
    ],
    "sg:phone":"+1 613 728 4780",
    "sg:postcode":"K2A 2C4",
    "sg:province":"ON",
    "sg:tags":[
        "contractor"
    ],
    "wof:name":"Thomas A Pegg Plumbing & Htg",
    "wof:placetype":"venue"
},
  "geometry": {"coordinates":[-75.749794,45.376762],"type":"Point"}
}