{
  "type": "Feature",
  "properties": {
    "addr:full":"831 Campbell Ave Ottawa ON K2A 2C4",
    "addr:housenumber":"831",
    "addr:postcode":"k2a 2c4",
    "addr:street":"Campbell Ave",
    "iso:country":"CA",
    "sg:address":"831 Campbell Ave",
    "sg:city":"Ottawa",
    "sg:classifiers":[
        {
            "category":"Building & Trades",
            "subcategory":"Plumbing",
            "type":"Services"
        }
    ],
    "sg:phone":"+1 613 728 4780",
    "sg:postcode":"K2A 2C4",
    "sg:province":"ON",
    "sg:tags":[
        "contractor"
    ],
    "wof:name":"Thomas A Pegg Plumbing & Htg",
    "wof:placetype":"venue"
},
  "geometry": {"coordinates":[-75.74979399999999,45.376762],"type":"Point"}
}