{
  "type": "Feature",
  "properties": {
    "iso:country":"CA",
    "sg:address":"1300 St. Peter Ave",
    "sg:city":"Bathurst",
    "sg:classifiers":[
        {
            "category":"Shopping",
            "subcategory":"Department Store",
            "type":"Retail Goods"
        }
    ],
    "sg:phone":"+1 506 546 7800",
    "sg:postcode":"E2A 3A6",
    "sg:province":"NB",
    "wof:name":"Sears Canada Inc",
    "wof:placetype":"venue"
},
  "geometry": {"coordinates":[-65.680153,47.639423],"type":"Point"}
}