{
  "type": "Feature",
  "properties": {
    "iso:country":"CA",
    "sg:address":"1072 Boul Des Laurentides",
    "sg:city":"Laval",
    "sg:classifiers":[
        {
            "category":"Home & Garden",
            "subcategory":"Building Materials",
            "type":"Retail Goods"
        }
    ],
    "sg:phone":"+1 450 663 9510",
    "sg:postcode":"H7G 2W1",
    "sg:province":"QC",
    "sg:tags":[
        "glass",
        "window",
        "plate"
    ],
    "wof:name":"Lebeau Vitres D'Autos",
    "wof:placetype":"venue"
},
  "geometry": {"coordinates":[-73.6991348267,45.5763511658],"type":"Point"}
}