{
  "type": "Feature",
  "properties": {
    "iso:country":"CA",
    "sg:city":"North Vancouver",
    "sg:classifiers":[
        {
            "category":"Home & Garden",
            "subcategory":"Home Furnishings",
            "type":"Retail Goods"
        }
    ],
    "sg:phone":"+1 604 986 5203",
    "sg:postcode":"V7P 1S3",
    "sg:province":"BC",
    "sg:tags":[
        "bathroom",
        "fixture",
        "accessory"
    ],
    "wof:name":"Ed's Linens",
    "wof:placetype":"venue"
},
  "geometry": {"coordinates":[-123.099129,49.322571],"type":"Point"}
}