{
  "type": "Feature",
  "properties": {
    "iso:country":"CA",
    "sg:city":"Hamilton",
    "sg:classifiers":[
        {
            "category":"Manufacturing",
            "subcategory":"Paper Products",
            "type":"Manufacturing & Wholesale Goods"
        }
    ],
    "sg:phone":"+1 905 575 3000",
    "sg:postcode":"L8W 3J6",
    "sg:province":"ON",
    "sg:tags":[
        "scanning",
        "code",
        "bar"
    ],
    "wof:name":"Barcode Canada",
    "wof:placetype":"venue"
},
  "geometry": {"coordinates":[-79.8405380249,43.1992111206],"type":"Point"}
}