{
  "type": "Feature",
  "properties": {
    "addr:full":"Calgary AB T2J 0P6",
    "addr:postcode":"t2j 0p6",
    "iso:country":"CA",
    "sg:city":"Calgary",
    "sg:classifiers":[
        {
            "category":"Shopping",
            "type":"Retail Goods"
        }
    ],
    "sg:phone":"+1 403 252 1846",
    "sg:postcode":"T2J 0P6",
    "sg:province":"AB",
    "sg:tags":[
        "miscellaneous",
        "store"
    ],
    "wof:name":"Love Boutique",
    "wof:placetype":"venue"
},
  "geometry": {"coordinates":[-114.071854,50.967178],"type":"Point"}
}