{
  "type": "Feature",
  "properties": {
    "addr:full":"808 Av Wiseman Outremont QC H2V 3L1",
    "addr:postcode":"h2v 3l1",
    "addr:street":"808 Av Wiseman",
    "iso:country":"CA",
    "sg:address":"808 Av Wiseman",
    "sg:city":"Outremont",
    "sg:classifiers":[
        {
            "category":"Building & Trades",
            "subcategory":"Plumbing",
            "type":"Services"
        }
    ],
    "sg:phone":"+1 514 272 6164",
    "sg:postcode":"H2V 3L1",
    "sg:province":"QC",
    "sg:tags":[
        "contractor"
    ],
    "wof:name":"Steve Plumbing & Heating",
    "wof:placetype":"venue"
},
  "geometry": {"coordinates":[-73.61531066889999,45.5203666687],"type":"Point"}
}