{
  "type": "Feature",
  "properties": {
    "addr:full":"1005 Martindale Rd Sudbury ON P3E 4J3",
    "addr:housenumber":"1005",
    "addr:postcode":"p3e 4j3",
    "addr:street":"Martindale Rd",
    "iso:country":"CA",
    "sg:address":"1005 Martindale Rd",
    "sg:city":"Sudbury",
    "sg:classifiers":[
        {
            "category":"Building & Trades",
            "subcategory":"Electrical",
            "type":"Services"
        }
    ],
    "sg:phone":"+1 705 669 0005",
    "sg:postcode":"P3E 4J3",
    "sg:province":"ON",
    "sg:tags":[
        "electric",
        "contractor"
    ],
    "wof:name":"Goliath Electrical Contracting",
    "wof:placetype":"venue"
},
  "geometry": {"coordinates":[-81.014526,46.471367],"type":"Point"}
}