{
  "type": "Feature",
  "properties": {
    "addr:full":"1881 Leslie St North York ON M3B 2M3",
    "addr:housenumber":"1881",
    "addr:postcode":"m3b 2m3",
    "addr:street":"Leslie St",
    "iso:country":"CA",
    "sg:address":"1881 Leslie St",
    "sg:city":"North York",
    "sg:classifiers":[
        {
            "category":"Retail",
            "subcategory":"Laundry & Dry Cleaning",
            "type":"Services"
        }
    ],
    "sg:phone":"+1 416 444 3592",
    "sg:postcode":"M3B 2M3",
    "sg:province":"ON",
    "sg:tags":[
        "cleaners"
    ],
    "wof:name":"Parkers Cleaners",
    "wof:placetype":"venue"
},
  "geometry": {"coordinates":[-79.3606262207,43.756690979],"type":"Point"}
}