{
  "type": "Feature",
  "properties": {
    "iso:country":"CA",
    "sg:address":"315 3E Rue",
    "sg:city":"Chibougamau",
    "sg:phone":"+1 418 748 6131",
    "sg:postcode":"G8P 1N4",
    "sg:province":"QC",
    "sg:tags":[
        "equipment",
        "utensil",
        "cooking",
        "supply"
    ],
    "wof:name":"Distributions Resto",
    "wof:placetype":"venue"
},
  "geometry": {"coordinates":[-74.3572311401,49.913860321],"type":"Point"}
}