{
  "type": "Feature",
  "properties": {
    "addr:full":"977 Eglinton Ave W York ON M6C 2C4",
    "addr:housenumber":"977",
    "addr:postcode":"m6c 2c4",
    "addr:street":"Eglinton Ave W",
    "iso:country":"CA",
    "sg:address":"977 Eglinton Ave W",
    "sg:city":"York",
    "sg:classifiers":[
        {
            "category":"Health Services",
            "subcategory":"Health Practitioner",
            "type":"Services"
        }
    ],
    "sg:phone":"+1 416 781 3945",
    "sg:postcode":"M6C 2C4",
    "sg:province":"ON",
    "sg:tags":[
        "physiotherapist"
    ],
    "wof:name":"York Physiotherapy & Rehab",
    "wof:placetype":"venue"
},
  "geometry": {"coordinates":[-79.42945899999999,43.700008],"type":"Point"}
}