{
  "type": "Feature",
  "properties": {
    "iso:country":"CA",
    "sg:address":"298 Rue Elm",
    "sg:city":"Saint-Lambert",
    "sg:classifiers":[
        {
            "category":"Personal",
            "type":"Services"
        }
    ],
    "sg:phone":"+1 450 672 7130",
    "sg:postcode":"J4P 1W3",
    "sg:province":"QC",
    "sg:tags":[
        "therapist",
        "massage"
    ],
    "wof:name":"Massage Ling Enr",
    "wof:placetype":"venue"
},
  "geometry": {"coordinates":[-73.51066589360001,45.4993934631],"type":"Point"}
}