{
  "type": "Feature",
  "properties": {
    "addr:full":"5851 Boul Cavendish Cote Saint-Luc QC H4W 2X8",
    "addr:housenumber":"5851",
    "addr:postcode":"h4w 2x8",
    "addr:street":"Boul Cavendish Cote",
    "iso:country":"CA",
    "sg:address":"5851 Boul Cavendish",
    "sg:city":"Cote Saint-Luc",
    "sg:classifiers":[
        {
            "category":"Education",
            "subcategory":"Library",
            "type":"Public Place"
        }
    ],
    "sg:phone":"+1 514 485 6900",
    "sg:postcode":"H4W 2X8",
    "sg:province":"QC",
    "wof:name":"Eleanor London Public Library",
    "wof:placetype":"venue"
},
  "geometry": {"coordinates":[-73.664879,45.477615],"type":"Point"}
}