{
  "type": "Feature",
  "properties": {
    "addr:full":"5775 Rue Jean-Talon E Saint-Leonard QC H1S 1M3",
    "addr:housenumber":"5775",
    "addr:postcode":"h1s 1m3",
    "addr:street":"Rue Jean-Talon E",
    "iso:country":"CA",
    "sg:address":"5775 Rue Jean-Talon E",
    "sg:city":"Saint-Leonard",
    "sg:classifiers":[
        {
            "category":"Wholesale",
            "subcategory":"Meat",
            "type":"Manufacturing & Wholesale Goods"
        }
    ],
    "sg:phone":"+1 514 899 7373",
    "sg:postcode":"H1S 1M3",
    "sg:province":"QC",
    "sg:tags":[
        "butchering"
    ],
    "wof:name":"Boucherie Timgad",
    "wof:placetype":"venue"
},
  "geometry": {"coordinates":[-73.580871582,45.5844459534],"type":"Point"}
}