{
  "type": "Feature",
  "properties": {
    "iso:country":"CA",
    "sg:address":"490 Eastchester Ave E",
    "sg:city":"St Catharines",
    "sg:classifiers":[
        {
            "category":"Manufacturing",
            "subcategory":"Metals",
            "type":"Manufacturing & Wholesale Goods"
        }
    ],
    "sg:phone":"+1 905 682 8338",
    "sg:postcode":"L2M 6S3",
    "sg:province":"ON",
    "sg:tags":[
        "steel"
    ],
    "wof:name":"Hingston Metal Fabricators Ltd",
    "wof:placetype":"venue"
},
  "geometry": {"coordinates":[-79.201225,43.170071],"type":"Point"}
}