{
  "type": "Feature",
  "properties": {
    "addr:full":"316 Manitoba St W Moose Jaw SK S6H 1R2",
    "addr:housenumber":"316",
    "addr:postcode":"s6h 1r2",
    "addr:street":"Manitoba St W",
    "iso:country":"CA",
    "sg:address":"316 Manitoba St W",
    "sg:city":"Moose Jaw",
    "sg:classifiers":[
        {
            "category":"Retail",
            "subcategory":"Auto Repair",
            "type":"Services"
        }
    ],
    "sg:phone":"+1 306 693 3511",
    "sg:postcode":"S6H 1R2",
    "sg:province":"SK",
    "sg:tags":[
        "repairing",
        "automobile",
        "tire"
    ],
    "wof:name":"Great West Tire Exchange",
    "wof:placetype":"venue"
},
  "geometry": {"coordinates":[-105.54270200000001,50.389816],"type":"Point"}
}