{
  "type": "Feature",
  "properties": {
    "addr:full":"Forest Grove BC V0K 1M0",
    "addr:postcode":"v0k 1m0",
    "iso:country":"CA",
    "sg:city":"Forest Grove",
    "sg:classifiers":[
        {
            "category":"Building & Trades",
            "subcategory":"Electrical",
            "type":"Services"
        }
    ],
    "sg:phone":"+1 250 397 2674",
    "sg:postcode":"V0K 1M0",
    "sg:province":"BC",
    "sg:tags":[
        "electric",
        "contractor"
    ],
    "wof:name":"Night Light Electrical",
    "wof:placetype":"venue"
},
  "geometry": {"coordinates":[-121.173500061,51.7117919922],"type":"Point"}
}