{
  "type": "Feature",
  "properties": {
    "addr:full":"129 Lily Ave Selkirk MB R1A 2A7",
    "addr:housenumber":"129",
    "addr:postcode":"r1a 2a7",
    "addr:street":"Lily Ave",
    "iso:country":"CA",
    "sg:address":"129 Lily Ave",
    "sg:city":"Selkirk",
    "sg:classifiers":[
        {
            "category":"Building & Trades",
            "subcategory":"Electrical",
            "type":"Services"
        }
    ],
    "sg:phone":"+1 204 482 5555",
    "sg:postcode":"R1A 2A7",
    "sg:province":"MB",
    "sg:tags":[
        "electric",
        "contractor"
    ],
    "wof:name":"Dale's Electric-Desco",
    "wof:placetype":"venue"
},
  "geometry": {"coordinates":[-96.86673,50.158379],"type":"Point"}
}