{
  "type": "Feature",
  "properties": {
    "iso:country":"CA",
    "sg:address":"301 Philip Rd",
    "sg:city":"Riverview",
    "sg:classifiers":[
        {
            "category":"Organizations",
            "subcategory":"Religious Organization",
            "type":"Services"
        }
    ],
    "sg:phone":"+1 506 387 3018",
    "sg:postcode":"E1B 2M1",
    "sg:province":"NB",
    "sg:tags":[
        "church"
    ],
    "wof:name":"Riverview Baptist Church Ofc",
    "wof:placetype":"venue"
},
  "geometry": {"coordinates":[-64.795532,46.064686],"type":"Point"}
}