{
  "type": "Feature",
  "properties": {
    "iso:country":"CA",
    "sg:address":"333 Av DE Dulwich",
    "sg:city":"Saint-Lambert",
    "sg:classifiers":[
        {
            "category":"Professional",
            "subcategory":"Business Services",
            "type":"Services"
        }
    ],
    "sg:phone":"+1 450 672 9602",
    "sg:postcode":"J4P 2Z2",
    "sg:province":"QC",
    "sg:tags":[
        "notary"
    ],
    "wof:name":"Lamarre, Elisabeth",
    "wof:placetype":"venue"
},
  "geometry": {"coordinates":[-73.5103607178,45.5098304749],"type":"Point"}
}