{
  "type": "Feature",
  "properties": {
    "addr:full":"Toronto ON M5H 2M5",
    "addr:postcode":"m5h 2m5",
    "iso:country":"CA",
    "sg:city":"Toronto",
    "sg:classifiers":[
        {
            "category":"Retail",
            "subcategory":"Portrait Studio",
            "type":"Services"
        }
    ],
    "sg:phone":"+1 416 363 7970",
    "sg:postcode":"M5H 2M5",
    "sg:province":"ON",
    "sg:tags":[
        "photographer"
    ],
    "wof:name":"Sooter's",
    "wof:placetype":"venue"
},
  "geometry": {"coordinates":[-79.381866,43.651711],"type":"Point"}
}