{
  "type": "Feature",
  "properties": {
    "addr:full":"11031 124 St NW Edmonton AB T5M 0J5",
    "addr:housenumber":"11031",
    "addr:postcode":"t5m 0j5",
    "addr:street":"124 St Nw",
    "iso:country":"CA",
    "sg:address":"11031 124 St NW",
    "sg:city":"Edmonton",
    "sg:classifiers":[
        {
            "category":"Organizations",
            "subcategory":"Community Association",
            "type":"Services"
        }
    ],
    "sg:phone":"+1 780 452 5794",
    "sg:postcode":"T5M 0J5",
    "sg:province":"AB",
    "sg:tags":[
        "club"
    ],
    "wof:name":"Canadian Progress Clubs",
    "wof:placetype":"venue"
},
  "geometry": {"coordinates":[-113.535751,53.557854],"type":"Point"}
}