{
  "type": "Feature",
  "properties": {
    "addr:full":"1670 Bayview Ave Toronto ON M4G 3C2",
    "addr:housenumber":"1670",
    "addr:postcode":"m4g 3c2",
    "addr:street":"Bayview Ave",
    "iso:country":"CA",
    "sg:address":"1670 Bayview Ave",
    "sg:city":"Toronto",
    "sg:classifiers":[
        {
            "category":"Professional",
            "subcategory":"Computer Services",
            "type":"Services"
        }
    ],
    "sg:phone":"+1 416 489 8041",
    "sg:postcode":"M4G 3C2",
    "sg:province":"ON",
    "sg:tags":[
        "internet"
    ],
    "wof:name":"Internet Shopping Catalogue",
    "wof:placetype":"venue"
},
  "geometry": {"coordinates":[-79.376045,43.707623],"type":"Point"}
}