{
  "type": "Feature",
  "properties": {
    "addr:full":"2710 Saratoga Pl Gloucester ON K1T 1Z2",
    "addr:housenumber":"2710",
    "addr:postcode":"k1t 1z2",
    "addr:street":"Saratoga Pl",
    "iso:country":"CA",
    "sg:address":"2710 Saratoga Pl",
    "sg:city":"Gloucester",
    "sg:classifiers":[
        {
            "category":"Real Estate",
            "subcategory":"Real Estate Operator",
            "type":"Services"
        }
    ],
    "sg:phone":"+1 613 729 4115",
    "sg:postcode":"K1T 1Z2",
    "sg:province":"ON",
    "sg:tags":[
        "apartment"
    ],
    "wof:name":"Ascot",
    "wof:placetype":"venue"
},
  "geometry": {"coordinates":[-75.647881,45.350182],"type":"Point"}
}