{
  "type": "Feature",
  "properties": {
    "addr:full":"Scarborough ON M1S 5C1",
    "addr:postcode":"m1s 5c1",
    "iso:country":"CA",
    "sg:city":"Scarborough",
    "sg:classifiers":[
        {
            "category":"Recreation",
            "type":"Entertainment"
        }
    ],
    "sg:phone":"+1 416 335 4588",
    "sg:postcode":"M1S 5C1",
    "sg:province":"ON",
    "sg:tags":[
        "martial",
        "arts",
        "instruction"
    ],
    "wof:name":"All Martial Arts Ctr",
    "wof:placetype":"venue"
},
  "geometry": {"coordinates":[-79.2766952515,43.7815246582],"type":"Point"}
}