{
  "type": "Feature",
  "properties": {
    "iso:country":"CA",
    "sg:address":"13551 Sparwood Pl",
    "sg:city":"Richmond",
    "sg:classifiers":[
        {
            "category":"Building & Trades",
            "subcategory":"Construction",
            "type":"Services"
        }
    ],
    "sg:phone":"+1 604 274 2792",
    "sg:postcode":"V6X 2C7",
    "sg:province":"BC",
    "sg:tags":[
        "excavating",
        "contractor",
        "topsoil"
    ],
    "wof:name":"A Little-Bit Deliveries",
    "wof:placetype":"venue"
},
  "geometry": {"coordinates":[-123.072463989,49.1707687378],"type":"Point"}
}