{
  "type": "Feature",
  "properties": {
    "addr:full":"6791 50 Ave # 10 Red Deer AB T4N 4C9",
    "addr:housenumber":"6791",
    "addr:postcode":"t4n 4c9",
    "addr:street":"50 Ave # 10",
    "iso:country":"CA",
    "sg:address":"6791 50 Ave # 10",
    "sg:city":"Red Deer",
    "sg:classifiers":[
        {
            "category":"Manufacturing",
            "subcategory":"Signs",
            "type":"Manufacturing & Wholesale Goods"
        }
    ],
    "sg:phone":"+1 403 340 2255",
    "sg:postcode":"T4N 4C9",
    "sg:province":"AB",
    "wof:name":"Signs Now",
    "wof:placetype":"venue"
},
  "geometry": {"coordinates":[-113.81326300000001,52.291721],"type":"Point"}
}