{
  "type": "Feature",
  "properties": {
    "iso:country":"CA",
    "sg:address":"500 158 Rte",
    "sg:city":"Saint-Thomas",
    "sg:classifiers":[
        {
            "category":"Building & Trades",
            "subcategory":"Construction",
            "type":"Services"
        }
    ],
    "sg:phone":"+1 450 759 1428",
    "sg:postcode":"J0K 3L0",
    "sg:province":"QC",
    "sg:tags":[
        "excavating",
        "contractor"
    ],
    "wof:name":"Entreprises Rene Vincent Inc",
    "wof:placetype":"venue"
},
  "geometry": {"coordinates":[-73.3608703613,46.0128173828],"type":"Point"}
}