{
  "type": "Feature",
  "properties": {
    "addr:full":"35921 Stoneridge Pl Abbotsford BC V3G 1L9",
    "addr:housenumber":"35921",
    "addr:postcode":"v3g 1l9",
    "addr:street":"Stoneridge Pl",
    "iso:country":"CA",
    "sg:address":"35921 Stoneridge Pl",
    "sg:city":"Abbotsford",
    "sg:classifiers":[
        {
            "category":"Building & Trades",
            "subcategory":"Construction",
            "type":"Services"
        }
    ],
    "sg:phone":"+1 604 504 7331",
    "sg:postcode":"V3G 1L9",
    "sg:province":"BC",
    "sg:tags":[
        "insulation",
        "heat",
        "contractor"
    ],
    "wof:name":"Fraser Valley Insualtion Svc",
    "wof:placetype":"venue"
},
  "geometry": {"coordinates":[-122.229782,49.04969],"type":"Point"}
}