{
  "type": "Feature",
  "properties": {
    "addr:full":"544 Rideau St Ottawa ON K1N 5Z8",
    "addr:housenumber":"544",
    "addr:postcode":"k1n 5z8",
    "addr:street":"Rideau St",
    "iso:country":"CA",
    "sg:address":"544 Rideau St",
    "sg:city":"Ottawa",
    "sg:classifiers":[
        {
            "category":"Restaurant",
            "type":"Food & Drink"
        }
    ],
    "sg:phone":"+1 613 789 4173",
    "sg:postcode":"K1N 5Z8",
    "sg:province":"ON",
    "wof:name":"Passage To India",
    "wof:placetype":"venue"
},
  "geometry": {"coordinates":[-75.677429,45.432076],"type":"Point"}
}