{
  "type": "Feature",
  "properties": {
    "addr:full":"44 Hawthorne Rd London ON N6G 2H5",
    "addr:housenumber":"44",
    "addr:postcode":"n6g 2h5",
    "addr:street":"Hawthorne Rd",
    "iso:country":"CA",
    "sg:address":"44 Hawthorne Rd",
    "sg:city":"London",
    "sg:classifiers":[
        {
            "category":"Education",
            "subcategory":"School",
            "type":"Public Place"
        }
    ],
    "sg:phone":"+1 519 452 8160",
    "sg:postcode":"N6G 2H5",
    "sg:province":"ON",
    "wof:name":"Emily Carr School",
    "wof:placetype":"venue"
},
  "geometry": {"coordinates":[-81.3124084473,43.0088577271],"type":"Point"}
}