{
  "type": "Feature",
  "properties": {
    "addr:full":"1274 Gerrard St E Toronto ON M4L 1Y7",
    "addr:housenumber":"1274",
    "addr:postcode":"m4l 1y7",
    "addr:street":"Gerrard St E",
    "iso:country":"CA",
    "sg:address":"1274 Gerrard St E",
    "sg:city":"Toronto",
    "sg:classifiers":[
        {
            "category":"Food & Beverages",
            "subcategory":"Groceries & Convenience Stores",
            "type":"Retail Goods"
        }
    ],
    "sg:phone":"+1 416 406 3673",
    "sg:postcode":"M4L 1Y7",
    "sg:province":"ON",
    "wof:name":"Daisy Mart",
    "wof:placetype":"venue"
},
  "geometry": {"coordinates":[-79.3278961182,43.6710243225],"type":"Point"}
}