{
  "type": "Feature",
  "properties": {
    "addr:full":"21 William St Paris ON N3L 1K9",
    "addr:housenumber":"21",
    "addr:postcode":"n3l 1k9",
    "addr:street":"William St",
    "iso:country":"CA",
    "sg:address":"21 William St",
    "sg:city":"Paris",
    "sg:classifiers":[
        {
            "category":"Shopping",
            "subcategory":"Used Merchandise",
            "type":"Retail Goods"
        }
    ],
    "sg:phone":"+1 519 442 1955",
    "sg:postcode":"N3L 1K9",
    "sg:province":"ON",
    "sg:tags":[
        "shop",
        "consignment"
    ],
    "wof:name":"Flashback",
    "wof:placetype":"venue"
},
  "geometry": {"coordinates":[-80.3853149414,43.1936264038],"type":"Point"}
}