{
  "type": "Feature",
  "properties": {
    "addr:full":"11 Alfred St E Wingham ON N0G 2W0",
    "addr:housenumber":"11",
    "addr:postcode":"n0g 2w0",
    "addr:street":"Alfred St E",
    "iso:country":"CA",
    "sg:address":"11 Alfred St E",
    "sg:city":"Wingham",
    "sg:classifiers":[
        {
            "category":"Retail",
            "subcategory":"Veterinary Services",
            "type":"Services"
        }
    ],
    "sg:phone":"+1 519 357 2471",
    "sg:postcode":"N0G 2W0",
    "sg:province":"ON",
    "sg:tags":[
        "veterinarian"
    ],
    "wof:name":"Strong, Alex E DVM",
    "wof:placetype":"venue"
},
  "geometry": {"coordinates":[-81.309799,43.889629],"type":"Point"}
}