{
  "type": "Feature",
  "properties": {
    "addr:full":"621 Mccowan Rd Scarborough ON M1J 1K2",
    "addr:housenumber":"621",
    "addr:postcode":"m1j 1k2",
    "addr:street":"Mccowan Rd",
    "iso:country":"CA",
    "sg:address":"621 Mccowan Rd",
    "sg:city":"Scarborough",
    "sg:classifiers":[
        {
            "category":"Wholesale",
            "subcategory":"Meat",
            "type":"Manufacturing & Wholesale Goods"
        }
    ],
    "sg:phone":"+1 416 431 0664",
    "sg:postcode":"M1J 1K2",
    "sg:province":"ON",
    "sg:tags":[
        "butchering"
    ],
    "wof:name":"M & B Meat",
    "wof:placetype":"venue"
},
  "geometry": {"coordinates":[-79.244286,43.753101],"type":"Point"}
}