{
  "type": "Feature",
  "properties": {
    "iso:country":"CA",
    "sg:address":"3733 Route 620",
    "sg:city":"Tay Creek",
    "sg:classifiers":[
        {
            "category":"Manufacturing",
            "subcategory":"Tools & Machinery",
            "type":"Manufacturing & Wholesale Goods"
        }
    ],
    "sg:phone":"+1 506 367 2005",
    "sg:postcode":"E6B 1K3",
    "sg:province":"NB",
    "sg:tags":[
        "equipment",
        "janitor"
    ],
    "wof:name":"Ricarda's Janitorial Svc",
    "wof:placetype":"venue"
},
  "geometry": {"coordinates":[-66.8219985962,46.2545318604],"type":"Point"}
}