{
  "type": "Feature",
  "properties": {
    "addr:full":"46 Rte Du Fleuve O Sainte-Luce QC G0K 1P0",
    "addr:housenumber":"46",
    "addr:postcode":"g0k 1p0",
    "addr:street":"Rte Du Fleuve O",
    "iso:country":"CA",
    "sg:address":"46 Rte Du Fleuve O",
    "sg:city":"Sainte-Luce",
    "sg:classifiers":[
        {
            "category":"Travel",
            "subcategory":"Hotels & Motels",
            "type":"Entertainment"
        }
    ],
    "sg:phone":"+1 418 739 4955",
    "sg:postcode":"G0K 1P0",
    "sg:province":"QC",
    "sg:tags":[
        "inn"
    ],
    "wof:name":"Auberge Ste-Luce",
    "wof:placetype":"venue"
},
  "geometry": {"coordinates":[-68.36097700000001,48.546543],"type":"Point"}
}