{
  "type": "Feature",
  "properties": {
    "addr:full":"170 Maplecrete Rd Concord ON L4K 2B6",
    "addr:housenumber":"170",
    "addr:postcode":"l4k 2b6",
    "addr:street":"Maplecrete Rd",
    "iso:country":"CA",
    "sg:address":"170 Maplecrete Rd",
    "sg:city":"Concord",
    "sg:classifiers":[
        {
            "category":"Retail",
            "subcategory":"Auto Repair",
            "type":"Services"
        }
    ],
    "sg:phone":"+1 905 738 0019",
    "sg:postcode":"L4K 2B6",
    "sg:province":"ON",
    "sg:tags":[
        "body",
        "automobile",
        "painting"
    ],
    "wof:name":"Triple Crown Auto Collision",
    "wof:placetype":"venue"
},
  "geometry": {"coordinates":[-79.521126,43.793491],"type":"Point"}
}