{
  "type": "Feature",
  "properties": {
    "iso:country":"CA",
    "sg:address":"5226 Stouffville Rd",
    "sg:city":"Stouffville",
    "sg:classifiers":[
        {
            "category":"Real Estate",
            "subcategory":"Real Estate Agent",
            "type":"Services"
        }
    ],
    "sg:phone":"+1 905 640 1200",
    "sg:postcode":"L4A 7X5",
    "sg:province":"ON",
    "wof:name":"Gallo Real Estate Ltd",
    "wof:placetype":"venue"
},
  "geometry": {"coordinates":[-79.282066,43.963711],"type":"Point"}
}