{
  "type": "Feature",
  "properties": {
    "addr:full":"3024 Falconbridge Hwy Garson ON P3L 1V1",
    "addr:housenumber":"3024",
    "addr:postcode":"p3l 1v1",
    "addr:street":"Falconbridge Hwy",
    "iso:country":"CA",
    "sg:address":"3024 Falconbridge Hwy",
    "sg:city":"Garson",
    "sg:classifiers":[
        {
            "category":"Travel",
            "subcategory":"Hotels & Motels",
            "type":"Entertainment"
        }
    ],
    "sg:phone":"+1 705 693 2727",
    "sg:postcode":"P3L 1V1",
    "sg:province":"ON",
    "wof:name":"Falcon Hotel",
    "wof:placetype":"venue"
},
  "geometry": {"coordinates":[-80.87665557859999,46.5492973328],"type":"Point"}
}