{
  "type": "Feature",
  "properties": {
    "addr:full":"225 2E Av O Weedon QC J0B 3J0",
    "addr:housenumber":"225",
    "addr:postcode":"j0b 3j0",
    "addr:street":"2E Av O",
    "iso:country":"CA",
    "sg:address":"225 2E Av O",
    "sg:city":"Weedon",
    "sg:classifiers":[
        {
            "category":"Government",
            "subcategory":"Office",
            "type":"Public Place"
        }
    ],
    "sg:phone":"+1 819 877 2155",
    "sg:postcode":"J0B 3J0",
    "sg:province":"QC",
    "sg:tags":[
        "union",
        "credit"
    ],
    "wof:name":"Caisses Desjardins-Weedon",
    "wof:placetype":"venue"
},
  "geometry": {"coordinates":[-71.4674,45.70034],"type":"Point"}
}