{
  "type": "Feature",
  "properties": {
    "iso:country":"CA",
    "sg:address":"25 Wingold Ave",
    "sg:city":"North York",
    "sg:classifiers":[
        {
            "category":"Building & Trades",
            "subcategory":"Construction",
            "type":"Services"
        }
    ],
    "sg:phone":"+1 416 787 4925",
    "sg:postcode":"M6B 1P8",
    "sg:province":"ON",
    "sg:tags":[
        "home",
        "bathroom",
        "remodeling",
        "improvement"
    ],
    "wof:name":"Lampert Renovations",
    "wof:placetype":"venue"
},
  "geometry": {"coordinates":[-79.454574585,43.7031974792],"type":"Point"}
}