{
  "type": "Feature",
  "properties": {
    "iso:country":"CA",
    "sg:address":"16621 83 Ave NW",
    "sg:city":"Edmonton",
    "sg:classifiers":[
        {
            "category":"Organizations",
            "subcategory":"Professional Association",
            "type":"Services"
        }
    ],
    "sg:phone":"+1 780 489 3903",
    "sg:postcode":"T5R 3V8",
    "sg:province":"AB",
    "wof:name":"Share",
    "wof:placetype":"venue"
},
  "geometry": {"coordinates":[-113.608642578,53.5163574219],"type":"Point"}
}