{
  "type": "Feature",
  "properties": {
    "addr:full":"Main St Dunville NL A0B 1S0",
    "addr:postcode":"a0b 1s0",
    "addr:street":"Main St",
    "iso:country":"CA",
    "sg:address":"Main St",
    "sg:city":"Dunville",
    "sg:classifiers":[
        {
            "category":"Food & Beverages",
            "subcategory":"Groceries & Convenience Stores",
            "type":"Retail Goods"
        }
    ],
    "sg:phone":"+1 709 227 2346",
    "sg:postcode":"A0B 1S0",
    "sg:province":"NL",
    "wof:name":"Gateway Mini Mart",
    "wof:placetype":"venue"
},
  "geometry": {"coordinates":[-53.873695,47.270329],"type":"Point"}
}