{
  "type": "Feature",
  "properties": {
    "addr:full":"Port Coquitlam BC V3C 6C1",
    "addr:postcode":"v3c 6c1",
    "iso:country":"CA",
    "sg:city":"Port Coquitlam",
    "sg:classifiers":[
        {
            "category":"Health Services",
            "subcategory":"Medical Lab",
            "type":"Services"
        }
    ],
    "sg:phone":"+1 604 941 5625",
    "sg:postcode":"V3C 6C1",
    "sg:province":"BC",
    "sg:tags":[
        "x"
    ],
    "wof:name":"Wilson X-Ray Ctr",
    "wof:placetype":"venue"
},
  "geometry": {"coordinates":[-122.777824,49.260979],"type":"Point"}
}