{
  "type": "Feature",
  "properties": {
    "addr:full":"Hudson QC J0P 1H0",
    "addr:postcode":"j0p 1h0",
    "iso:country":"CA",
    "sg:city":"Hudson",
    "sg:classifiers":[
        {
            "category":"Personal",
            "subcategory":"Beauty Salon",
            "type":"Services"
        }
    ],
    "sg:phone":"+1 450 458 1884",
    "sg:postcode":"J0P 1H0",
    "sg:province":"QC",
    "wof:name":"Centre DE Beaute Veronique I",
    "wof:placetype":"venue"
},
  "geometry": {"coordinates":[-74.14267,45.459293],"type":"Point"}
}