{
  "type": "Feature",
  "properties": {
    "iso:country":"CA",
    "sg:city":"Dundas",
    "sg:classifiers":[
        {
            "category":"Personal",
            "subcategory":"Beauty Salon",
            "type":"Services"
        }
    ],
    "sg:phone":"+1 905 662 2625",
    "sg:postcode":"L9H 5E1",
    "sg:province":"ON",
    "wof:name":"Angel Aesthetics",
    "wof:placetype":"venue"
},
  "geometry": {"coordinates":[-79.9523773193,43.2637786865],"type":"Point"}
}