{
  "type": "Feature",
  "properties": {
    "addr:full":"1830 Strasburg Rd Kitchener ON N2R 1E9",
    "addr:housenumber":"1830",
    "addr:postcode":"n2r 1e9",
    "addr:street":"Strasburg Rd",
    "iso:country":"CA",
    "sg:address":"1830 Strasburg Rd",
    "sg:city":"Kitchener",
    "sg:classifiers":[
        {
            "category":"Wholesale",
            "subcategory":"Machinery & Supplies",
            "type":"Manufacturing & Wholesale Goods"
        }
    ],
    "sg:phone":"+1 519 725 2400",
    "sg:postcode":"N2R 1E9",
    "sg:province":"ON",
    "sg:tags":[
        "cylinder",
        "hydraulic"
    ],
    "wof:name":"Ultra Metal Inc",
    "wof:placetype":"venue"
},
  "geometry": {"coordinates":[-80.466965,43.392868],"type":"Point"}
}