{
  "type": "Feature",
  "properties": {
    "iso:country":"CA",
    "sg:address":"100 3E Av",
    "sg:city":"Quebec",
    "sg:classifiers":[
        {
            "category":"Retail",
            "subcategory":"Auto Repair",
            "type":"Services"
        }
    ],
    "sg:phone":"+1 418 647 5965",
    "sg:postcode":"G1L 2V5",
    "sg:province":"QC",
    "sg:tags":[
        "repairing",
        "automobile"
    ],
    "wof:name":"Station DE Svc Dm Inc",
    "wof:placetype":"venue"
},
  "geometry": {"coordinates":[-71.224609375,46.8206672668],"type":"Point"}
}