{
  "type": "Feature",
  "properties": {
    "addr:full":"80 14th Ave Hanover ON N4N 3V9",
    "addr:housenumber":"80",
    "addr:postcode":"n4n 3v9",
    "addr:street":"14Th Ave",
    "iso:country":"CA",
    "sg:address":"80 14th Ave",
    "sg:city":"Hanover",
    "sg:classifiers":[
        {
            "category":"Wholesale",
            "subcategory":"Electrical",
            "type":"Manufacturing & Wholesale Goods"
        }
    ],
    "sg:phone":"+1 519 364 5055",
    "sg:postcode":"N4N 3V9",
    "sg:province":"ON",
    "sg:tags":[
        "communication",
        "radio",
        "system"
    ],
    "wof:name":"Hartman Electronics & Comms",
    "wof:placetype":"venue"
},
  "geometry": {"coordinates":[-81.017128,44.142769],"type":"Point"}
}