{
  "type": "Feature",
  "properties": {
    "addr:full":"865 Westney Rd S Ajax ON L1S 3M4",
    "addr:housenumber":"865",
    "addr:postcode":"l1s 3m4",
    "addr:street":"Westney Rd",
    "iso:country":"CA",
    "sg:address":"865 Westney Rd S",
    "sg:city":"Ajax",
    "sg:classifiers":[
        {
            "category":"Social Services",
            "type":"Services"
        }
    ],
    "sg:phone":"+1 905 427 8862",
    "sg:postcode":"L1S 3M4",
    "sg:province":"ON",
    "sg:tags":[
        "organization",
        "welfare"
    ],
    "wof:name":"Resource For Exceptional Child",
    "wof:placetype":"venue"
},
  "geometry": {"coordinates":[-79.02057647709999,43.8301239014],"type":"Point"}
}