{
  "type": "Feature",
  "properties": {
    "addr:full":"221 Ch Des Lots Saint-Gabriel-DE-Brandon QC J0K 2N0",
    "addr:housenumber":"221",
    "addr:postcode":"j0k 2n0",
    "addr:street":"Ch Des Lots",
    "iso:country":"CA",
    "sg:address":"221 Ch Des Lots",
    "sg:city":"Saint-Gabriel-DE-Brandon",
    "sg:classifiers":[
        {
            "category":"Retail",
            "subcategory":"Repair Shop",
            "type":"Services"
        }
    ],
    "sg:phone":"+1 450 835 7495",
    "sg:postcode":"J0K 2N0",
    "sg:province":"QC",
    "sg:tags":[
        "pump"
    ],
    "wof:name":"Systeme D'Eau Turcotte",
    "wof:placetype":"venue"
},
  "geometry": {"coordinates":[-73.3650131226,46.2905845642],"type":"Point"}
}