{
  "type": "Feature",
  "properties": {
    "addr:full":"306 Morice Ave Fort St James BC V0J 1P0",
    "addr:housenumber":"306",
    "addr:postcode":"v0j 1p0",
    "addr:street":"Morice Ave Fort St",
    "iso:country":"CA",
    "sg:address":"306 Morice Ave",
    "sg:city":"Fort St James",
    "sg:classifiers":[
        {
            "category":"Retail",
            "subcategory":"Auto Repair",
            "type":"Services"
        }
    ],
    "sg:phone":"+1 250 996 8711",
    "sg:postcode":"V0J 1P0",
    "sg:province":"BC",
    "sg:tags":[
        "repairing",
        "automobile"
    ],
    "wof:name":"Don's Repair Svc",
    "wof:placetype":"venue"
},
  "geometry": {"coordinates":[-124.25675200000001,54.444996],"type":"Point"}
}