{
  "type": "Feature",
  "properties": {
    "addr:full":"518 Lawrence Ave W North York ON M6A 1A1",
    "addr:housenumber":"518",
    "addr:postcode":"m6a 1a1",
    "addr:street":"Lawrence Ave W",
    "iso:country":"CA",
    "sg:address":"518 Lawrence Ave W",
    "sg:city":"North York",
    "sg:classifiers":[
        {
            "category":"Shopping",
            "subcategory":"Clothing, Apparel, & Fashions",
            "type":"Retail Goods"
        }
    ],
    "sg:phone":"+1 416 785 0330",
    "sg:postcode":"M6A 1A1",
    "sg:province":"ON",
    "wof:name":"Penningtons Superstore",
    "wof:placetype":"venue"
},
  "geometry": {"coordinates":[-79.4316253662,43.718963623],"type":"Point"}
}