{
  "type": "Feature",
  "properties": {
    "addr:full":"159 Ch Des Pionniers O L'Islet QC G0R 2B0",
    "addr:housenumber":"159",
    "addr:postcode":"g0r 2b0",
    "addr:street":"Ch Des Pionniers O",
    "iso:country":"CA",
    "sg:address":"159 Ch Des Pionniers O",
    "sg:city":"L'Islet",
    "sg:classifiers":[
        {
            "category":"Retail",
            "subcategory":"Auto Repair",
            "type":"Services"
        }
    ],
    "sg:phone":"+1 418 247 3731",
    "sg:postcode":"G0R 2B0",
    "sg:province":"QC",
    "sg:tags":[
        "repairing",
        "automobile"
    ],
    "wof:name":"Garage Rock Caron",
    "wof:placetype":"venue"
},
  "geometry": {"coordinates":[-70.331535,47.089802],"type":"Point"}
}