{
  "type": "Feature",
  "properties": {
    "addr:full":"Vancouver BC V6H 1E2",
    "addr:postcode":"v6h 1e2",
    "iso:country":"CA",
    "sg:city":"Vancouver",
    "sg:classifiers":[
        {
            "category":"Professional",
            "subcategory":"Lawyer & Legal Services",
            "type":"Services"
        }
    ],
    "sg:phone":"+1 604 688 1802",
    "sg:postcode":"V6H 1E2",
    "sg:province":"BC",
    "sg:tags":[
        "attorney"
    ],
    "wof:name":"Lawton, Stephanie",
    "wof:placetype":"venue"
},
  "geometry": {"coordinates":[-123.12789917000001,49.2635726929],"type":"Point"}
}