{
  "type": "Feature",
  "properties": {
    "iso:country":"CA",
    "sg:address":"1014 Rue King O",
    "sg:city":"Sherbrooke",
    "sg:classifiers":[
        {
            "category":"Personal",
            "type":"Services"
        }
    ],
    "sg:phone":"+1 819 346 8556",
    "sg:postcode":"J1H 1S2",
    "sg:province":"QC",
    "sg:tags":[
        "electrolysis"
    ],
    "wof:name":"Institut Mireille Dufault",
    "wof:placetype":"venue"
},
  "geometry": {"coordinates":[-71.86637878419999,45.4079360962],"type":"Point"}
}