{
  "type": "Feature",
  "properties": {
    "iso:country":"CA",
    "sg:address":"4650 Boul Decarie",
    "sg:city":"Montreal",
    "sg:classifiers":[
        {
            "category":"Retail",
            "subcategory":"Repair Shop",
            "type":"Services"
        }
    ],
    "sg:phone":"+1 514 489 2688",
    "sg:postcode":"H3X 2H5",
    "sg:province":"QC",
    "sg:tags":[
        "lock",
        "locksmith"
    ],
    "wof:name":"Serrurier Snowdon Locksmith",
    "wof:placetype":"venue"
},
  "geometry": {"coordinates":[-73.6246261597,45.4812164307],"type":"Point"}
}