{
  "type": "Feature",
  "properties": {
    "iso:country":"CA",
    "sg:city":"East York",
    "sg:classifiers":[
        {
            "category":"Travel",
            "subcategory":"Travel Agent",
            "type":"Entertainment"
        }
    ],
    "sg:phone":"+1 416 696 0036",
    "sg:postcode":"M4K 2S2",
    "sg:province":"ON",
    "sg:tags":[
        "agency",
        "bureau"
    ],
    "wof:name":"G V Travel Ltd",
    "wof:placetype":"venue"
},
  "geometry": {"coordinates":[-79.356812,43.685013],"type":"Point"}
}