{
  "type": "Feature",
  "properties": {
    "addr:full":"143 12E Av Drummondville QC J2B 2Y6",
    "addr:housenumber":"143",
    "addr:postcode":"j2b 2y6",
    "addr:street":"12E Av",
    "iso:country":"CA",
    "sg:address":"143 12E Av",
    "sg:city":"Drummondville",
    "sg:classifiers":[
        {
            "category":"Shopping",
            "subcategory":"Used Merchandise",
            "type":"Retail Goods"
        }
    ],
    "sg:phone":"+1 819 472 6188",
    "sg:postcode":"J2B 2Y6",
    "sg:province":"QC",
    "sg:tags":[
        "furniture"
    ],
    "wof:name":"Maison Du Chomeur",
    "wof:placetype":"venue"
},
  "geometry": {"coordinates":[-72.491364,45.869667],"type":"Point"}
}