{
  "type": "Feature",
  "properties": {
    "addr:full":"63 Medulla Ave Etobicoke ON M8Z 5L6",
    "addr:housenumber":"63",
    "addr:postcode":"m8z 5l6",
    "addr:street":"Medulla Ave",
    "iso:country":"CA",
    "sg:address":"63 Medulla Ave",
    "sg:city":"Etobicoke",
    "sg:classifiers":[
        {
            "category":"Manufacturing",
            "subcategory":"Metals",
            "type":"Manufacturing & Wholesale Goods"
        }
    ],
    "sg:phone":"+1 416 622 4595",
    "sg:postcode":"M8Z 5L6",
    "sg:province":"ON",
    "sg:tags":[
        "coating"
    ],
    "wof:name":"Spectrum Powder Coaters Ltd",
    "wof:placetype":"venue"
},
  "geometry": {"coordinates":[-79.546577,43.624447],"type":"Point"}
}