{
  "type": "Feature",
  "properties": {
    "iso:country":"CA",
    "sg:address":"475 329 Rte N",
    "sg:city":"Sainte-Agathe-Nord",
    "sg:classifiers":[
        {
            "category":"Home & Garden",
            "subcategory":"Building Materials",
            "type":"Retail Goods"
        }
    ],
    "sg:phone":"+1 819 326 2299",
    "sg:postcode":"J8C 2Z8",
    "sg:province":"QC",
    "sg:tags":[
        "lumber"
    ],
    "wof:name":"Renovation Ste-Agathe Inc",
    "wof:placetype":"venue"
},
  "geometry": {"coordinates":[-74.2838516235,46.0744743347],"type":"Point"}
}