{
  "type": "Feature",
  "properties": {
    "addr:full":"8431 Summer Pl Prince George BC V2K 4Z8",
    "addr:housenumber":"8431",
    "addr:postcode":"v2k 4z8",
    "addr:street":"Summer Pl",
    "iso:country":"CA",
    "sg:address":"8431 Summer Pl",
    "sg:city":"Prince George",
    "sg:classifiers":[
        {
            "category":"Building & Trades",
            "subcategory":"Construction",
            "type":"Services"
        }
    ],
    "sg:phone":"+1 250 562 7660",
    "sg:postcode":"V2K 4Z8",
    "sg:province":"BC",
    "sg:tags":[
        "insulation",
        "heat",
        "contractor"
    ],
    "wof:name":"Western Thermal Installation",
    "wof:placetype":"venue"
},
  "geometry": {"coordinates":[-122.870429993,53.9781455994],"type":"Point"}
}