{
  "type": "Feature",
  "properties": {
    "addr:full":"193 Queen St Port Perry ON L9L 1B9",
    "addr:housenumber":"193",
    "addr:postcode":"l9l 1b9",
    "addr:street":"Queen St",
    "iso:country":"CA",
    "sg:address":"193 Queen St",
    "sg:city":"Port Perry",
    "sg:classifiers":[
        {
            "category":"Insurance",
            "subcategory":"Insurance Agent",
            "type":"Services"
        }
    ],
    "sg:phone":"+1 905 985 7306",
    "sg:postcode":"L9L 1B9",
    "sg:province":"ON",
    "wof:name":"Emmerson Insurance Brokers Ltd",
    "wof:placetype":"venue"
},
  "geometry": {"coordinates":[-78.9438323975,44.1050376892],"type":"Point"}
}