{
  "type": "Feature",
  "properties": {
    "addr:full":"1142 Ch DE Chateau-Bigot Charlesbourg QC G2L 1G4",
    "addr:housenumber":"1142",
    "addr:postcode":"g2l 1g4",
    "addr:street":"Ch De Chateau-Bigot",
    "iso:country":"CA",
    "sg:address":"1142 Ch DE Chateau-Bigot",
    "sg:city":"Charlesbourg",
    "sg:classifiers":[
        {
            "category":"Professional",
            "subcategory":"Engineering",
            "type":"Services"
        }
    ],
    "sg:phone":"+1 514 246 2901",
    "sg:postcode":"G2L 1G4",
    "sg:province":"QC",
    "sg:tags":[
        "engineer"
    ],
    "wof:name":"Maurice Lebel Experts-Conseil",
    "wof:placetype":"venue"
},
  "geometry": {"coordinates":[-71.267799,46.888062],"type":"Point"}
}