{
  "type": "Feature",
  "properties": {
    "addr:full":"1485 Av Du Pont S Alma QC G8B 6N2",
    "addr:housenumber":"1485",
    "addr:postcode":"g8b 6n2",
    "addr:street":"Av Du Pont S",
    "iso:country":"CA",
    "sg:address":"1485 Av Du Pont S",
    "sg:city":"Alma",
    "sg:classifiers":[
        {
            "category":"Retail",
            "subcategory":"Auto Rental",
            "type":"Services"
        }
    ],
    "sg:phone":"+1 418 662 3799",
    "sg:postcode":"G8B 6N2",
    "sg:province":"QC",
    "sg:tags":[
        "renting",
        "automobile"
    ],
    "wof:name":"Entreprise Location D'Autos",
    "wof:placetype":"venue"
},
  "geometry": {"coordinates":[-71.651253,48.527615],"type":"Point"}
}