{
  "type": "Feature",
  "properties": {
    "addr:full":"3952 27E Av Shawinigan QC G9N 7Y1",
    "addr:housenumber":"3952",
    "addr:postcode":"g9n 7y1",
    "addr:street":"27E Av",
    "iso:country":"CA",
    "sg:address":"3952 27E Av",
    "sg:city":"Shawinigan",
    "sg:classifiers":[
        {
            "category":"Building & Trades",
            "subcategory":"Construction",
            "type":"Services"
        }
    ],
    "sg:phone":"+1 819 539 8251",
    "sg:postcode":"G9N 7Y1",
    "sg:province":"QC",
    "sg:tags":[
        "general",
        "contractor"
    ],
    "wof:name":"Excavation Claude Desaulniers",
    "wof:placetype":"venue"
},
  "geometry": {"coordinates":[-72.7417602539,46.5716362],"type":"Point"}
}