{
  "type": "Feature",
  "properties": {
    "addr:full":"390 Main St W Listowel ON N4W 1A5",
    "addr:housenumber":"390",
    "addr:postcode":"n4w 1a5",
    "addr:street":"Main St W",
    "iso:country":"CA",
    "sg:address":"390 Main St W",
    "sg:city":"Listowel",
    "sg:classifiers":[
        {
            "category":"Restaurant",
            "type":"Food & Drink"
        }
    ],
    "sg:phone":"+1 519 291 2989",
    "sg:postcode":"N4W 1A5",
    "sg:province":"ON",
    "wof:name":"Fiege's Fine Dining",
    "wof:placetype":"venue"
},
  "geometry": {"coordinates":[-80.95642100000001,43.732777],"type":"Point"}
}