{
  "type": "Feature",
  "properties": {
    "addr:full":"4161 50E Av Grand-Mere QC G9T 1A6",
    "addr:housenumber":"4161",
    "addr:postcode":"g9t 1a6",
    "addr:street":"50E Av Grand-Mere",
    "iso:country":"CA",
    "sg:address":"4161 50E Av",
    "sg:city":"Grand-Mere",
    "sg:classifiers":[
        {
            "category":"Manufacturing",
            "subcategory":"Electronics",
            "type":"Manufacturing & Wholesale Goods"
        }
    ],
    "sg:phone":"+1 819 538 3398",
    "sg:postcode":"G9T 1A6",
    "sg:province":"QC",
    "sg:tags":[
        "equipment",
        "electronic",
        "supply"
    ],
    "wof:name":"Hdi Technologies Inc",
    "wof:placetype":"venue"
},
  "geometry": {"coordinates":[-72.74141693120001,46.6107215881],"type":"Point"}
}