{
  "type": "Feature",
  "properties": {
    "addr:full":"29 Eastwood Dr Welland ON L3C 6W3",
    "addr:housenumber":"29",
    "addr:postcode":"l3c 6w3",
    "addr:street":"Eastwood Dr",
    "iso:country":"CA",
    "sg:address":"29 Eastwood Dr",
    "sg:city":"Welland",
    "sg:classifiers":[
        {
            "category":"Organizations",
            "subcategory":"Membership Organization",
            "type":"Services"
        }
    ],
    "sg:phone":"+1 905 732 9746",
    "sg:postcode":"L3C 6W3",
    "sg:province":"ON",
    "wof:name":"Boost",
    "wof:placetype":"venue"
},
  "geometry": {"coordinates":[-79.271523,43.016251],"type":"Point"}
}