{
  "type": "Feature",
  "properties": {
    "addr:full":"3663 Dutch Village Rd Halifax NS B3N 2T1",
    "addr:housenumber":"3663",
    "addr:postcode":"b3n 2t1",
    "addr:street":"Dutch Village Rd",
    "iso:country":"CA",
    "sg:address":"3663 Dutch Village Rd",
    "sg:city":"Halifax",
    "sg:classifiers":[
        {
            "category":"Social Services",
            "type":"Services"
        }
    ],
    "sg:phone":"+1 902 457 9622",
    "sg:postcode":"B3N 2T1",
    "sg:province":"NS",
    "sg:tags":[
        "youth",
        "organization",
        "center"
    ],
    "wof:name":"Ymca Newcomer Ctr",
    "wof:placetype":"venue"
},
  "geometry": {"coordinates":[-63.6317062378,44.6586380005],"type":"Point"}
}