{
  "type": "Feature",
  "properties": {
    "addr:full":"1525 Paris St # 105 Sudbury ON P3E 5K2",
    "addr:housenumber":"1525",
    "addr:postcode":"p3e 5k2",
    "addr:street":"Paris St # 105",
    "iso:country":"CA",
    "sg:address":"1525 Paris St # 105",
    "sg:city":"Sudbury",
    "sg:classifiers":[
        {
            "category":"Real Estate",
            "subcategory":"Real Estate Operator",
            "type":"Services"
        }
    ],
    "sg:phone":"+1 705 688 6059",
    "sg:postcode":"P3E 5K2",
    "sg:province":"ON",
    "sg:tags":[
        "apartment"
    ],
    "wof:name":"Banyan Apartments",
    "wof:placetype":"venue"
},
  "geometry": {"coordinates":[-81.000771,46.461151],"type":"Point"}
}