{
  "type": "Feature",
  "properties": {
    "addr:full":"2065 Petawawa Blvd Pembroke ON K8A 7G8",
    "addr:housenumber":"2065",
    "addr:postcode":"k8a 7g8",
    "addr:street":"Petawawa Blvd",
    "iso:country":"CA",
    "sg:address":"2065 Petawawa Blvd",
    "sg:city":"Pembroke",
    "sg:classifiers":[
        {
            "category":"Home & Garden",
            "subcategory":"Building Materials",
            "type":"Retail Goods"
        }
    ],
    "sg:phone":"+1 613 735 0631",
    "sg:postcode":"K8A 7G8",
    "sg:province":"ON",
    "sg:tags":[
        "mixed",
        "concrete"
    ],
    "wof:name":"Essroc Italcementi Group",
    "wof:placetype":"venue"
},
  "geometry": {"coordinates":[-77.112213,45.826481],"type":"Point"}
}