{
  "type": "Feature",
  "properties": {
    "addr:full":"45142 Laurelwood Pl Chilliwack BC V2R 1S8",
    "addr:housenumber":"45142",
    "addr:postcode":"v2r 1s8",
    "addr:street":"Laurelwood Pl",
    "iso:country":"CA",
    "sg:address":"45142 Laurelwood Pl",
    "sg:city":"Chilliwack",
    "sg:classifiers":[
        {
            "category":"Personal",
            "subcategory":"Beauty Salon",
            "type":"Services"
        }
    ],
    "sg:phone":"+1 604 858 2123",
    "sg:postcode":"V2R 1S8",
    "sg:province":"BC",
    "wof:name":"Victoria's Hair Design",
    "wof:placetype":"venue"
},
  "geometry": {"coordinates":[-121.975700378,49.1197128296],"type":"Point"}
}