{
  "type": "Feature",
  "properties": {
    "iso:country":"CA",
    "sg:address":"828 Eastern Ave",
    "sg:city":"Toronto",
    "sg:classifiers":[
        {
            "category":"Retail",
            "subcategory":"Car Wash",
            "type":"Services"
        }
    ],
    "sg:phone":"+1 416 366 9274",
    "sg:postcode":"M4L 1A1",
    "sg:province":"ON",
    "sg:tags":[
        "polishing",
        "washing"
    ],
    "wof:name":"Auto Wash Systems Canada Inc",
    "wof:placetype":"venue"
},
  "geometry": {"coordinates":[-79.3289108276,43.6617355347],"type":"Point"}
}