{
  "type": "Feature",
  "properties": {
    "iso:country":"CA",
    "sg:address":"500 Rue Deslauriers",
    "sg:city":"Saint-Laurent",
    "sg:classifiers":[
        {
            "category":"Manufacturing",
            "subcategory":"Food",
            "type":"Manufacturing & Wholesale Goods"
        }
    ],
    "sg:phone":"+1 514 642 0000",
    "sg:postcode":"H4N 1V8",
    "sg:province":"QC",
    "sg:tags":[
        "cocoa",
        "chocolate"
    ],
    "wof:name":"Deliska Tradition Inc",
    "wof:placetype":"venue"
},
  "geometry": {"coordinates":[-73.664795,45.524143],"type":"Point"}
}