{
  "type": "Feature",
  "properties": {
    "addr:full":"Salmon Arm BC V1E 1B5",
    "addr:postcode":"v1e 1b5",
    "iso:country":"CA",
    "sg:city":"Salmon Arm",
    "sg:classifiers":[
        {
            "category":"Personal",
            "subcategory":"Shoe Repair & Shine",
            "type":"Services"
        }
    ],
    "sg:phone":"+1 250 832 4525",
    "sg:postcode":"V1E 1B5",
    "sg:province":"BC",
    "sg:tags":[
        "repairing",
        "boot"
    ],
    "wof:name":"Cobbler Shoe Repair",
    "wof:placetype":"venue"
},
  "geometry": {"coordinates":[-119.28997039799999,50.6994972229],"type":"Point"}
}