{
  "type": "Feature",
  "properties": {
    "iso:country":"CA",
    "sg:city":"Ottawa",
    "sg:classifiers":[
        {
            "category":"Health Services",
            "subcategory":"Doctor",
            "type":"Services"
        }
    ],
    "sg:phone":"+1 613 233 9116",
    "sg:postcode":"K1R 6P6",
    "sg:province":"ON",
    "sg:tags":[
        "dentist"
    ],
    "wof:name":"Somerset Dental Ctr",
    "wof:placetype":"venue"
},
  "geometry": {"coordinates":[-75.707207,45.410686],"type":"Point"}
}