{
  "type": "Feature",
  "properties": {
    "addr:full":"Whiteway NL A0B 3L0",
    "addr:postcode":"a0b 3l0",
    "iso:country":"CA",
    "sg:city":"Whiteway",
    "sg:classifiers":[
        {
            "category":"Home & Garden",
            "subcategory":"Furniture",
            "type":"Retail Goods"
        }
    ],
    "sg:phone":"+1 709 588 2885",
    "sg:postcode":"A0B 3L0",
    "sg:province":"NL",
    "sg:tags":[
        "equipment",
        "kitchen",
        "cabinet"
    ],
    "wof:name":"R & R Kitchens",
    "wof:placetype":"venue"
},
  "geometry": {"coordinates":[-53.485451,47.665413],"type":"Point"}
}