{
  "type": "Feature",
  "properties": {
    "iso:country":"CA",
    "sg:address":"3 Rue Wilbrod",
    "sg:city":"Chateauguay",
    "sg:classifiers":[
        {
            "category":"Shopping",
            "subcategory":"Bicycles & Sporting Goods",
            "type":"Retail Goods"
        }
    ],
    "sg:phone":"+1 450 692 6451",
    "sg:postcode":"J6K 5C4",
    "sg:province":"QC",
    "sg:tags":[
        "supply"
    ],
    "wof:name":"Crepin Sports Inc",
    "wof:placetype":"venue"
},
  "geometry": {"coordinates":[-73.7482299805,45.3598136902],"type":"Point"}
}