{
  "type": "Feature",
  "properties": {
    "addr:full":"4033 Av DE L'Eau-Vive Charny QC G6X 1J2",
    "addr:housenumber":"4033",
    "addr:postcode":"g6x 1j2",
    "addr:street":"Av De L'Eau-Vive",
    "iso:country":"CA",
    "sg:address":"4033 Av DE L'Eau-Vive",
    "sg:city":"Charny",
    "sg:classifiers":[
        {
            "category":"Wholesale",
            "subcategory":"Medical Equipment & Supplies",
            "type":"Manufacturing & Wholesale Goods"
        }
    ],
    "sg:phone":"+1 418 832 6335",
    "sg:postcode":"G6X 1J2",
    "sg:province":"QC",
    "sg:tags":[
        "light",
        "tube",
        "microscope",
        "bulb"
    ],
    "wof:name":"Opti-Ressources Inc",
    "wof:placetype":"venue"
},
  "geometry": {"coordinates":[-71.26997375489999,46.7167701721],"type":"Point"}
}