{
  "type": "Feature",
  "properties": {
    "addr:full":"2880 Bayview Ave North York ON M2N 5K3",
    "addr:housenumber":"2880",
    "addr:postcode":"m2n 5k3",
    "addr:street":"Bayview Ave",
    "iso:country":"CA",
    "sg:address":"2880 Bayview Ave",
    "sg:city":"North York",
    "sg:classifiers":[
        {
            "category":"Organizations",
            "subcategory":"Non-profit Organization",
            "type":"Services"
        }
    ],
    "sg:phone":"+1 416 222 4448",
    "sg:postcode":"M2N 5K3",
    "sg:province":"ON",
    "sg:tags":[
        "disability"
    ],
    "wof:name":"North Yorkers For Disabled Inc",
    "wof:placetype":"venue"
},
  "geometry": {"coordinates":[-79.3883895874,43.7676391602],"type":"Point"}
}