{
  "type": "Feature",
  "properties": {
    "addr:full":"Red Deer County AB T4E 1B4",
    "addr:postcode":"t4e 1b4",
    "iso:country":"CA",
    "sg:city":"Red Deer County",
    "sg:classifiers":[
        {
            "category":"Building & Trades",
            "subcategory":"Equipment Rental",
            "type":"Services"
        }
    ],
    "sg:phone":"+1 403 342 5272",
    "sg:postcode":"T4E 1B4",
    "sg:province":"AB",
    "sg:tags":[
        "yard",
        "scaffolding"
    ],
    "wof:name":"Call Erection & Dismanteling",
    "wof:placetype":"venue"
},
  "geometry": {"coordinates":[-113.861328,52.283978],"type":"Point"}
}