{
  "type": "Feature",
  "properties": {
    "addr:full":"3528 Kingsway Vancouver BC V5R 5L7",
    "addr:housenumber":"3528",
    "addr:postcode":"v5r 5l7",
    "addr:street":"Kingsway",
    "iso:country":"CA",
    "sg:address":"3528 Kingsway",
    "sg:city":"Vancouver",
    "sg:classifiers":[
        {
            "category":"Shopping",
            "subcategory":"Musical Instruments",
            "type":"Retail Goods"
        }
    ],
    "sg:phone":"+1 604 437 1792",
    "sg:postcode":"V5R 5L7",
    "sg:province":"BC",
    "sg:tags":[
        "piano"
    ],
    "wof:name":"Piano Gallery",
    "wof:placetype":"venue"
},
  "geometry": {"coordinates":[-123.027687073,49.2319755554],"type":"Point"}
}