{
  "type": "Feature",
  "properties": {
    "addr:full":"Peers AB T0E 1W0",
    "addr:postcode":"t0e 1w0",
    "iso:country":"CA",
    "sg:city":"Peers",
    "sg:classifiers":[
        {
            "category":"Education",
            "subcategory":"School",
            "type":"Public Place"
        }
    ],
    "sg:phone":"+1 780 693 2186",
    "sg:postcode":"T0E 1W0",
    "sg:province":"AB",
    "wof:name":"Fulham School",
    "wof:placetype":"venue"
},
  "geometry": {"coordinates":[-115.99140930199999,53.6771850586],"type":"Point"}
}