{
  "type": "Feature",
  "properties": {
    "iso:country":"CA",
    "sg:address":"80 Rue Jean-Proulx",
    "sg:city":"Hull",
    "sg:classifiers":[
        {
            "category":"Professional",
            "subcategory":"Computer Services",
            "type":"Services"
        }
    ],
    "sg:phone":"+1 819 771 0011",
    "sg:postcode":"J8Z 1W1",
    "sg:province":"QC",
    "wof:name":"Versatel Networks",
    "wof:placetype":"venue"
},
  "geometry": {"coordinates":[-75.740685,45.46788],"type":"Point"}
}