{
  "type": "Feature",
  "properties": {
    "addr:full":"5301 Airport Rd S Richmond BC V7B 1B5",
    "addr:housenumber":"5301",
    "addr:postcode":"v7b 1b5",
    "addr:street":"Airport Rd",
    "iso:country":"CA",
    "sg:address":"5301 Airport Rd S",
    "sg:city":"Richmond",
    "sg:classifiers":[
        {
            "category":"Professional",
            "subcategory":"Testing Lab",
            "type":"Services"
        }
    ],
    "sg:phone":"+1 604 244 9699",
    "sg:postcode":"V7B 1B5",
    "sg:province":"BC",
    "wof:name":"Cantech Inspections Ltd",
    "wof:placetype":"venue"
},
  "geometry": {"coordinates":[-123.166161,49.180252],"type":"Point"}
}