{
  "type": "Feature",
  "properties": {
    "addr:full":"108 Main St Domremy SK S0K 1G0",
    "addr:housenumber":"108",
    "addr:postcode":"s0k 1g0",
    "addr:street":"Main St",
    "iso:country":"CA",
    "sg:address":"108 Main St",
    "sg:city":"Domremy",
    "sg:classifiers":[
        {
            "category":"Professional",
            "subcategory":"Research",
            "type":"Services"
        }
    ],
    "sg:phone":"+1 306 423 6100",
    "sg:postcode":"S0K 1G0",
    "sg:province":"SK",
    "sg:tags":[
        "environmental",
        "ecological"
    ],
    "wof:name":"Environmental Mgmt Group",
    "wof:placetype":"venue"
},
  "geometry": {"coordinates":[-105.73271200000001,52.789406],"type":"Point"}
}