{
  "type": "Feature",
  "properties": {
    "iso:country":"CA",
    "sg:address":"7275 Rapistan Crt",
    "sg:city":"Mississauga",
    "sg:classifiers":[
        {
            "category":"Manufacturing",
            "subcategory":"Tools & Machinery",
            "type":"Manufacturing & Wholesale Goods"
        }
    ],
    "sg:phone":"+1 905 542 2323",
    "sg:postcode":"L5N 5Z4",
    "sg:province":"ON",
    "sg:tags":[
        "control",
        "equipment",
        "electric"
    ],
    "wof:name":"Moeller Electric Inc",
    "wof:placetype":"venue"
},
  "geometry": {"coordinates":[-79.7658081055,43.6050186157],"type":"Point"}
}