{
  "type": "Feature",
  "properties": {
    "iso:country":"CA",
    "sg:address":"109 Rue Saint-Jean-Baptiste",
    "sg:city":"L'Isle-Verte",
    "sg:classifiers":[
        {
            "category":"Restaurant",
            "type":"Food & Drink"
        }
    ],
    "sg:phone":"+1 418 898 2769",
    "sg:postcode":"G0L 1K0",
    "sg:province":"QC",
    "wof:name":"Restaurant Cafe Chez Bedo",
    "wof:placetype":"venue"
},
  "geometry": {"coordinates":[-69.3341217041,48.0160713196],"type":"Point"}
}