{
  "type": "Feature",
  "properties": {
    "iso:country":"CA",
    "sg:address":"2 Westwyn Crt",
    "sg:city":"Brampton",
    "sg:classifiers":[
        {
            "category":"Home & Garden",
            "subcategory":"Household Appliances",
            "type":"Retail Goods"
        }
    ],
    "sg:phone":"+1 905 454 4013",
    "sg:postcode":"L6T 4T5",
    "sg:province":"ON",
    "sg:tags":[
        "pump"
    ],
    "wof:name":"York Fluid Controls",
    "wof:placetype":"venue"
},
  "geometry": {"coordinates":[-79.695045,43.686481],"type":"Point"}
}