{
  "type": "Feature",
  "properties": {
    "addr:full":"2 Westwyn Crt Brampton ON L6T 4T5",
    "addr:housenumber":"2",
    "addr:postcode":"l6t 4t5",
    "addr:street":"Westwyn Crt",
    "iso:country":"CA",
    "sg:address":"2 Westwyn Crt",
    "sg:city":"Brampton",
    "sg:classifiers":[
        {
            "category":"Home & Garden",
            "subcategory":"Household Appliances",
            "type":"Retail Goods"
        }
    ],
    "sg:phone":"+1 905 454 4013",
    "sg:postcode":"L6T 4T5",
    "sg:province":"ON",
    "sg:tags":[
        "pump"
    ],
    "wof:name":"York Fluid Controls",
    "wof:placetype":"venue"
},
  "geometry": {"coordinates":[-79.69504499999999,43.686481],"type":"Point"}
}