{
  "type": "Feature",
  "properties": {
    "addr:full":"2508 Rue Marie-Leneuf Trois-Rivieres QC G8Z 3T6",
    "addr:housenumber":"2508",
    "addr:postcode":"g8z 3t6",
    "addr:street":"Rue Marie-Leneuf Trois-Rivieres",
    "iso:country":"CA",
    "sg:address":"2508 Rue Marie-Leneuf",
    "sg:city":"Trois-Rivieres",
    "sg:classifiers":[
        {
            "category":"Health Services",
            "subcategory":"Health Practitioner",
            "type":"Services"
        }
    ],
    "sg:phone":"+1 819 375 9344",
    "sg:postcode":"G8Z 3T6",
    "sg:province":"QC",
    "sg:tags":[
        "psychologist"
    ],
    "wof:name":"Hebert, Ginette PhD",
    "wof:placetype":"venue"
},
  "geometry": {"coordinates":[-72.56295799999999,46.359764],"type":"Point"}
}