{
  "type": "Feature",
  "properties": {
    "addr:full":"Montreal QC H3B 2J9",
    "addr:postcode":"h3b 2j9",
    "iso:country":"CA",
    "sg:city":"Montreal",
    "sg:classifiers":[
        {
            "category":"Freight",
            "type":"Transportation"
        }
    ],
    "sg:phone":"+1 514 875 2335",
    "sg:postcode":"H3B 2J9",
    "sg:province":"QC",
    "sg:tags":[
        "cargo",
        "company",
        "containerized",
        "steamship"
    ],
    "wof:name":"Zim Compagnie Israelienne Ltee",
    "wof:placetype":"venue"
},
  "geometry": {"coordinates":[-73.55443572999999,45.5170631409],"type":"Point"}
}