{
  "type": "Feature",
  "properties": {
    "addr:full":"2682 Sperring Ave East St Paul MB R2E 1A3",
    "addr:housenumber":"2682",
    "addr:postcode":"r2e 1a3",
    "addr:street":"Sperring Ave",
    "iso:country":"CA",
    "sg:address":"2682 Sperring Ave",
    "sg:city":"East St Paul",
    "sg:classifiers":[
        {
            "category":"Building & Trades",
            "subcategory":"Construction",
            "type":"Services"
        }
    ],
    "sg:phone":"+1 204 661 9369",
    "sg:postcode":"R2E 1A3",
    "sg:province":"MB",
    "sg:tags":[
        "painter"
    ],
    "wof:name":"Ultra Painting & Decorating",
    "wof:placetype":"venue"
},
  "geometry": {"coordinates":[-97.0235443115,49.9590377808],"type":"Point"}
}