{
  "type": "Feature",
  "properties": {
    "iso:country":"CA",
    "sg:city":"Saint-Leonard",
    "sg:classifiers":[
        {
            "category":"Building & Trades",
            "subcategory":"Construction",
            "type":"Services"
        }
    ],
    "sg:phone":"+1 514 255 1314",
    "sg:postcode":"H1S 3E8",
    "sg:province":"QC",
    "sg:tags":[
        "general",
        "contractor"
    ],
    "wof:name":"Alcana Les Constructions Inc",
    "wof:placetype":"venue"
},
  "geometry": {"coordinates":[-73.575485,45.591808],"type":"Point"}
}