{
  "type": "Feature",
  "properties": {
    "iso:country":"CA",
    "sg:city":"Calgary",
    "sg:classifiers":[
        {
            "category":"Food & Beverages",
            "subcategory":"Bakery",
            "type":"Retail Goods"
        }
    ],
    "sg:phone":"+1 403 263 4882",
    "sg:postcode":"T2G 0B2",
    "sg:province":"AB",
    "sg:tags":[
        "baker"
    ],
    "wof:name":"Golden Happiness Bakery Ltd",
    "wof:placetype":"venue"
},
  "geometry": {"coordinates":[-114.062294006,51.0510406494],"type":"Point"}
}