{
  "type": "Feature",
  "properties": {
    "addr:full":"945 Boul Pierre-Bertrand Vanier QC G1M 2E8",
    "addr:housenumber":"945",
    "addr:postcode":"g1m 2e8",
    "addr:street":"Boul Pierre-Bertrand",
    "iso:country":"CA",
    "sg:address":"945 Boul Pierre-Bertrand",
    "sg:city":"Vanier",
    "sg:classifiers":[
        {
            "category":"Manufacturing",
            "subcategory":"Tools & Machinery",
            "type":"Manufacturing & Wholesale Goods"
        }
    ],
    "sg:phone":"+1 418 681 6177",
    "sg:postcode":"G1M 2E8",
    "sg:province":"QC",
    "sg:tags":[
        "machine",
        "shop"
    ],
    "wof:name":"Kelly Machinerie Inc",
    "wof:placetype":"venue"
},
  "geometry": {"coordinates":[-71.27514600000001,46.826721],"type":"Point"}
}