{
  "type": "Feature",
  "properties": {
    "addr:full":"635 St Clair Ave W Toronto ON M6C 1A7",
    "addr:housenumber":"635",
    "addr:postcode":"m6c 1a7",
    "addr:street":"St Clair Ave W",
    "iso:country":"CA",
    "sg:address":"635 St Clair Ave W",
    "sg:city":"Toronto",
    "sg:classifiers":[
        {
            "category":"Home & Garden",
            "subcategory":"Building Materials",
            "type":"Retail Goods"
        }
    ],
    "sg:phone":"+1 416 653 7477",
    "sg:postcode":"M6C 1A7",
    "sg:province":"ON",
    "sg:tags":[
        "paint"
    ],
    "wof:name":"Maple Paint & Wallpaper",
    "wof:placetype":"venue"
},
  "geometry": {"coordinates":[-79.4239273071,43.6819152832],"type":"Point"}
}