{
  "type": "Feature",
  "properties": {
    "addr:full":"1236 Yonge St Toronto ON M4T 1W3",
    "addr:housenumber":"1236",
    "addr:postcode":"m4t 1w3",
    "addr:street":"Yonge St",
    "iso:country":"CA",
    "sg:address":"1236 Yonge St",
    "sg:city":"Toronto",
    "sg:classifiers":[
        {
            "category":"Shopping",
            "subcategory":"Used Merchandise",
            "type":"Retail Goods"
        }
    ],
    "sg:phone":"+1 416 922 6784",
    "sg:postcode":"M4T 1W3",
    "sg:province":"ON",
    "sg:tags":[
        "antique"
    ],
    "wof:name":"Absolutely North",
    "wof:placetype":"venue"
},
  "geometry": {"coordinates":[-79.39202899999999,43.68264],"type":"Point"}
}