{
  "type": "Feature",
  "properties": {
    "addr:full":"9 Iroquois Rd Leamington ON N8H 3V7",
    "addr:housenumber":"9",
    "addr:postcode":"n8h 3v7",
    "addr:street":"Iroquois Rd",
    "iso:country":"CA",
    "sg:address":"9 Iroquois Rd",
    "sg:city":"Leamington",
    "sg:classifiers":[
        {
            "category":"Retail",
            "subcategory":"Auto Repair",
            "type":"Services"
        }
    ],
    "sg:phone":"+1 519 326 0356",
    "sg:postcode":"N8H 3V7",
    "sg:province":"ON",
    "sg:tags":[
        "body",
        "automobile",
        "painting"
    ],
    "wof:name":"Precision Collision & Rstrtn",
    "wof:placetype":"venue"
},
  "geometry": {"coordinates":[-82.5920791626,42.0333023071],"type":"Point"}
}