{
  "type": "Feature",
  "properties": {
    "addr:full":"6200 Edgar St Windsor ON N8S 2A6",
    "addr:housenumber":"6200",
    "addr:postcode":"n8s 2a6",
    "addr:street":"Edgar St",
    "iso:country":"CA",
    "sg:address":"6200 Edgar St",
    "sg:city":"Windsor",
    "sg:classifiers":[
        {
            "category":"Education",
            "subcategory":"School",
            "type":"Public Place"
        }
    ],
    "sg:phone":"+1 519 948 9481",
    "sg:postcode":"N8S 2A6",
    "sg:province":"ON",
    "wof:name":"Ecole George P Vanier",
    "wof:placetype":"venue"
},
  "geometry": {"coordinates":[-82.9587402344,42.3238449097],"type":"Point"}
}