{
  "type": "Feature",
  "properties": {
    "iso:country":"CA",
    "sg:city":"Surrey",
    "sg:classifiers":[
        {
            "category":"Retail",
            "subcategory":"Portrait Studio",
            "type":"Services"
        }
    ],
    "sg:phone":"+1 604 535 1666",
    "sg:postcode":"V4A 2J4",
    "sg:province":"BC",
    "sg:tags":[
        "photographer"
    ],
    "wof:name":"Gallery Creations",
    "wof:placetype":"venue"
},
  "geometry": {"coordinates":[-122.792366,49.045719],"type":"Point"}
}