{
  "type": "Feature",
  "properties": {
    "addr:full":"Nanaimo BC V9T 2H5",
    "addr:postcode":"v9t 2h5",
    "iso:country":"CA",
    "sg:city":"Nanaimo",
    "sg:classifiers":[
        {
            "category":"Insurance",
            "subcategory":"Insurance Agent",
            "type":"Services"
        }
    ],
    "sg:phone":"+1 250 751 1816",
    "sg:postcode":"V9T 2H5",
    "sg:province":"BC",
    "sg:tags":[
        "adjuster"
    ],
    "wof:name":"Brouwer Claims Canada & CO Ltd",
    "wof:placetype":"venue"
},
  "geometry": {"coordinates":[-124.029563904,49.211971283],"type":"Point"}
}