{
  "type": "Feature",
  "properties": {
    "addr:full":"180 Rue Saint-Lambert Salaberry-DE-Valleyfield QC J6T 1T7",
    "addr:housenumber":"180",
    "addr:postcode":"j6t 1t7",
    "addr:street":"Rue Saint-Lambert",
    "iso:country":"CA",
    "sg:address":"180 Rue Saint-Lambert",
    "sg:city":"Salaberry-DE-Valleyfield",
    "sg:classifiers":[
        {
            "category":"Building & Trades",
            "subcategory":"Electrical",
            "type":"Services"
        }
    ],
    "sg:phone":"+1 450 373 2733",
    "sg:postcode":"J6T 1T7",
    "sg:province":"QC",
    "sg:tags":[
        "electric",
        "contractor"
    ],
    "wof:name":"P G Electrique Inc",
    "wof:placetype":"venue"
},
  "geometry": {"coordinates":[-74.140106,45.251221],"type":"Point"}
}