{
  "type": "Feature",
  "properties": {
    "iso:country":"CA",
    "sg:address":"21 Ch DE L'Eglise",
    "sg:city":"Amos",
    "sg:classifiers":[
        {
            "category":"Organizations",
            "subcategory":"Religious Organization",
            "type":"Services"
        }
    ],
    "sg:phone":"+1 819 732 7985",
    "sg:postcode":"J9T 3A1",
    "sg:province":"QC",
    "sg:tags":[
        "church"
    ],
    "wof:name":"St Maurice Catholic Church",
    "wof:placetype":"venue"
},
  "geometry": {"coordinates":[-77.9860076904,48.6467971802],"type":"Point"}
}