{
  "type": "Feature",
  "properties": {
    "addr:full":"820 Willow St Truro NS B2N 6N7",
    "addr:housenumber":"820",
    "addr:postcode":"b2n 6n7",
    "addr:street":"Willow St",
    "iso:country":"CA",
    "sg:address":"820 Willow St",
    "sg:city":"Truro",
    "sg:classifiers":[
        {
            "category":"Organizations",
            "subcategory":"Professional Association",
            "type":"Services"
        }
    ],
    "sg:phone":"+1 902 897 9199",
    "sg:postcode":"B2N 6N7",
    "sg:province":"NS",
    "wof:name":"Millbrook Band Council",
    "wof:placetype":"venue"
},
  "geometry": {"coordinates":[-63.293167,45.33567],"type":"Point"}
}