{
  "type": "Feature",
  "properties": {
    "addr:full":"Mississauga ON L5T 1J6",
    "addr:postcode":"l5t 1j6",
    "iso:country":"CA",
    "sg:city":"Mississauga",
    "sg:classifiers":[
        {
            "category":"Building & Trades",
            "subcategory":"Construction",
            "type":"Services"
        }
    ],
    "sg:phone":"+1 416 674 7533",
    "sg:postcode":"L5T 1J6",
    "sg:province":"ON",
    "sg:tags":[
        "general",
        "contractor"
    ],
    "wof:name":"D I Construction CO",
    "wof:placetype":"venue"
},
  "geometry": {"coordinates":[-79.664207,43.651581],"type":"Point"}
}