{
  "type": "Feature",
  "properties": {
    "addr:full":"2019 Long Lake Rd Sudbury ON P3E 4M8",
    "addr:housenumber":"2019",
    "addr:postcode":"p3e 4m8",
    "addr:street":"Long Lake Rd",
    "iso:country":"CA",
    "sg:address":"2019 Long Lake Rd",
    "sg:city":"Sudbury",
    "sg:classifiers":[
        {
            "category":"Shopping",
            "subcategory":"Department Store",
            "type":"Retail Goods"
        }
    ],
    "sg:phone":"+1 705 522 5733",
    "sg:postcode":"P3E 4M8",
    "sg:province":"ON",
    "sg:tags":[
        "shop"
    ],
    "wof:name":"Dollarama",
    "wof:placetype":"venue"
},
  "geometry": {"coordinates":[-81.003494,46.451061],"type":"Point"}
}