{
  "type": "Feature",
  "properties": {
    "addr:full":"1238 Winnipeg St Regina SK S4R 1J6",
    "addr:housenumber":"1238",
    "addr:postcode":"s4r 1j6",
    "addr:street":"Winnipeg St",
    "iso:country":"CA",
    "sg:address":"1238 Winnipeg St",
    "sg:city":"Regina",
    "sg:classifiers":[
        {
            "category":"Manufacturing",
            "subcategory":"Tools & Machinery",
            "type":"Manufacturing & Wholesale Goods"
        }
    ],
    "sg:phone":"+1 306 781 6065",
    "sg:postcode":"S4R 1J6",
    "sg:province":"SK",
    "sg:tags":[
        "machine",
        "shop"
    ],
    "wof:name":"Pino Machine Shop Ltd",
    "wof:placetype":"venue"
},
  "geometry": {"coordinates":[-104.595451,50.459206],"type":"Point"}
}