{
  "type": "Feature",
  "properties": {
    "iso:country":"CA",
    "sg:address":"268 Rue Principale E",
    "sg:city":"Farnham",
    "sg:classifiers":[
        {
            "category":"Health Services",
            "subcategory":"Doctor",
            "type":"Services"
        }
    ],
    "sg:phone":"+1 450 293 3681",
    "sg:postcode":"J2N 1L6",
    "sg:province":"QC",
    "sg:tags":[
        "physician",
        "clinic",
        "surgeon"
    ],
    "wof:name":"Clinique Medicale Du Village",
    "wof:placetype":"venue"
},
  "geometry": {"coordinates":[-72.97732543950001,45.2841682434],"type":"Point"}
}