{
  "type": "Feature",
  "properties": {
    "addr:full":"5976 West Fraser Rd Quesnel BC V2J 6R2",
    "addr:housenumber":"5976",
    "addr:postcode":"v2j 6r2",
    "addr:street":"West Fraser Rd",
    "iso:country":"CA",
    "sg:address":"5976 West Fraser Rd",
    "sg:city":"Quesnel",
    "sg:classifiers":[
        {
            "category":"Education",
            "subcategory":"School",
            "type":"Public Place"
        }
    ],
    "sg:phone":"+1 250 747 8500",
    "sg:postcode":"V2J 6R2",
    "sg:province":"BC",
    "wof:name":"Narcosli Creek School",
    "wof:placetype":"venue"
},
  "geometry": {"coordinates":[-122.518417,52.96006],"type":"Point"}
}