{
  "type": "Feature",
  "properties": {
    "addr:full":"4150 4th Ave Whitehorse YT Y1A 1J2",
    "addr:housenumber":"4150",
    "addr:postcode":"y1a 1j2",
    "addr:street":"4Th Ave",
    "iso:country":"CA",
    "sg:address":"4150 4th Ave",
    "sg:city":"Whitehorse",
    "sg:classifiers":[
        {
            "category":"Real Estate",
            "subcategory":"Real Estate Agent",
            "type":"Services"
        }
    ],
    "sg:phone":"+1 867 668 3500",
    "sg:postcode":"Y1A 1J2",
    "sg:province":"YT",
    "wof:name":"Annau, Gary",
    "wof:placetype":"venue"
},
  "geometry": {"coordinates":[-135.058899,60.722122],"type":"Point"}
}