{
  "type": "Feature",
  "properties": {
    "addr:full":"Galloway BC V0B 1P0",
    "addr:postcode":"bc v0b 1p0",
    "iso:country":"CA",
    "sg:city":"Galloway",
    "sg:classifiers":[
        {
            "category":"Manufacturing",
            "subcategory":"Lumber",
            "type":"Manufacturing & Wholesale Goods"
        }
    ],
    "sg:phone":"+1 250 429 3496",
    "sg:postcode":"V0B 1P0",
    "sg:province":"BC",
    "wof:name":"Galloway Lumber CO Ltd",
    "wof:placetype":"venue"
},
  "geometry": {"coordinates":[-115.240906,49.371876],"type":"Point"}
}