{
  "type": "Feature",
  "properties": {
    "addr:full":"559 Boul Industriel Saint-Eustache QC J7R 6C3",
    "addr:housenumber":"559",
    "addr:postcode":"j7r 6c3",
    "addr:street":"Boul Industriel",
    "iso:country":"CA",
    "sg:address":"559 Boul Industriel",
    "sg:city":"Saint-Eustache",
    "sg:classifiers":[
        {
            "category":"Wholesale",
            "subcategory":"Electrical",
            "type":"Manufacturing & Wholesale Goods"
        }
    ],
    "sg:phone":"+1 450 491 0540",
    "sg:postcode":"J7R 6C3",
    "sg:province":"QC",
    "sg:tags":[
        "equipment",
        "electronic",
        "supply"
    ],
    "wof:name":"Triton Electronique Inc",
    "wof:placetype":"venue"
},
  "geometry": {"coordinates":[-73.92243999999999,45.557854],"type":"Point"}
}