{
  "type": "Feature",
  "properties": {
    "addr:full":"982 Rue Roger Canton-DE-Granby QC J2G 3A8",
    "addr:housenumber":"982",
    "addr:postcode":"j2g 3a8",
    "addr:street":"Rue Roger Canton-De-Granby",
    "iso:country":"CA",
    "sg:address":"982 Rue Roger",
    "sg:city":"Canton-DE-Granby",
    "sg:classifiers":[
        {
            "category":"Manufacturing",
            "subcategory":"Tools & Machinery",
            "type":"Manufacturing & Wholesale Goods"
        }
    ],
    "sg:phone":"+1 450 776 2628",
    "sg:postcode":"J2G 3A8",
    "sg:province":"QC",
    "sg:tags":[
        "control",
        "system",
        "automation"
    ],
    "wof:name":"Electrotech Automatisation Ind",
    "wof:placetype":"venue"
},
  "geometry": {"coordinates":[-72.7217712402,45.3979949951],"type":"Point"}
}