{
  "type": "Feature",
  "properties": {
    "addr:full":"22574 Fraser Hwy Langley BC V2Z 2T8",
    "addr:housenumber":"22574",
    "addr:postcode":"v2z 2t8",
    "addr:street":"Fraser Hwy",
    "iso:country":"CA",
    "sg:address":"22574 Fraser Hwy",
    "sg:city":"Langley",
    "sg:classifiers":[
        {
            "category":"Freight",
            "type":"Transportation"
        }
    ],
    "sg:phone":"+1 604 514 3440",
    "sg:postcode":"V2Z 2T8",
    "sg:province":"BC",
    "sg:tags":[
        "trucking"
    ],
    "wof:name":"Westside Transport Inc",
    "wof:placetype":"venue"
},
  "geometry": {"coordinates":[-122.5979,49.087948],"type":"Point"}
}