{
  "type": "Feature",
  "properties": {
    "addr:full":"9 Terrace Ave Flin Flon MB R8A 1S2",
    "addr:housenumber":"9",
    "addr:postcode":"r8a 1s2",
    "addr:street":"Terrace Ave",
    "iso:country":"CA",
    "sg:address":"9 Terrace Ave",
    "sg:city":"Flin Flon",
    "sg:classifiers":[
        {
            "category":"Social Services",
            "subcategory":"Child Care",
            "type":"Services"
        }
    ],
    "sg:phone":"+1 204 687 5117",
    "sg:postcode":"R8A 1S2",
    "sg:province":"MB",
    "wof:name":"Flin Flon Guidance Nursery",
    "wof:placetype":"venue"
},
  "geometry": {"coordinates":[-101.870826721,54.7652015686],"type":"Point"}
}