{
  "type": "Feature",
  "properties": {
    "addr:full":"106 Rte Du Cap # B Saint-Apollinaire QC G0S 2E0",
    "addr:housenumber":"106",
    "addr:postcode":"g0s 2e0",
    "addr:street":"Rte Du Cap # B Saint-Apollinaire",
    "iso:country":"CA",
    "sg:address":"106 Rte Du Cap # B",
    "sg:city":"Saint-Apollinaire",
    "sg:classifiers":[
        {
            "category":"Retail",
            "subcategory":"Auto Repair",
            "type":"Services"
        }
    ],
    "sg:phone":"+1 418 881 3410",
    "sg:postcode":"G0S 2E0",
    "sg:province":"QC",
    "sg:tags":[
        "repairing",
        "automobile",
        "rustproofing",
        "undercoating"
    ],
    "wof:name":"Garage Bolduc",
    "wof:placetype":"venue"
},
  "geometry": {"coordinates":[-71.4450759888,46.6349601746],"type":"Point"}
}