{
  "type": "Feature",
  "properties": {
    "addr:full":"Calgary AB T2E 6W3",
    "addr:postcode":"t2e 6w3",
    "iso:country":"CA",
    "sg:city":"Calgary",
    "sg:classifiers":[
        {
            "category":"Restaurant",
            "type":"Food & Drink"
        }
    ],
    "sg:phone":"+1 403 219 0961",
    "sg:postcode":"T2E 6W3",
    "sg:province":"AB",
    "wof:name":"New Berliner",
    "wof:placetype":"venue"
},
  "geometry": {"coordinates":[-114.00784299999999,51.083748],"type":"Point"}
}