{
  "type": "Feature",
  "properties": {
    "iso:country":"CA",
    "sg:address":"1166 3E Av",
    "sg:city":"Quebec",
    "sg:classifiers":[
        {
            "category":"Restaurant",
            "type":"Food & Drink"
        }
    ],
    "sg:phone":"+1 418 522 9988",
    "sg:postcode":"G1L 2X6",
    "sg:province":"QC",
    "wof:name":"Pizzedelic",
    "wof:placetype":"venue"
},
  "geometry": {"coordinates":[-71.2306442261,46.8276329041],"type":"Point"}
}