{
  "type": "Feature",
  "properties": {
    "addr:full":"Fitzroy Harbour ON K0A 1X0",
    "addr:postcode":"k0a 1x0",
    "iso:country":"CA",
    "sg:city":"Fitzroy Harbour",
    "sg:classifiers":[
        {
            "category":"Shopping",
            "subcategory":"Discount & Variety Stores",
            "type":"Retail Goods"
        }
    ],
    "sg:phone":"+1 613 623 3208",
    "sg:postcode":"K0A 1X0",
    "sg:province":"ON",
    "sg:tags":[
        "merchandise",
        "general"
    ],
    "wof:name":"Harbour Store",
    "wof:placetype":"venue"
},
  "geometry": {"coordinates":[-76.2154464722,45.4709854126],"type":"Point"}
}