{
  "type": "Feature",
  "properties": {
    "iso:country":"CA",
    "sg:address":"9275 Bayview Ave",
    "sg:city":"Richmond Hill",
    "sg:classifiers":[
        {
            "category":"Shopping",
            "subcategory":"Pharmacy",
            "type":"Retail Goods"
        }
    ],
    "sg:phone":"+1 905 886 6676",
    "sg:postcode":"L4C 9X4",
    "sg:province":"ON",
    "wof:name":"Shoppers Drug Mart",
    "wof:placetype":"venue"
},
  "geometry": {"coordinates":[-79.410789,43.857613],"type":"Point"}
}