{
  "type": "Feature",
  "properties": {
    "addr:full":"1451 River St Kamloops BC V2C 1Z1",
    "addr:housenumber":"1451",
    "addr:postcode":"bc v2c 1z1",
    "addr:street":"River St",
    "iso:country":"CA",
    "sg:address":"1451 River St",
    "sg:city":"Kamloops",
    "sg:classifiers":[
        {
            "category":"Retail",
            "subcategory":"Auto Repair",
            "type":"Services"
        }
    ],
    "sg:phone":"+1 250 374 5650",
    "sg:postcode":"V2C 1Z1",
    "sg:province":"BC",
    "sg:tags":[
        "body",
        "automobile",
        "painting"
    ],
    "wof:name":"Riverside Collision",
    "wof:placetype":"venue"
},
  "geometry": {"coordinates":[-120.305313,50.674923],"type":"Point"}
}