{
  "type": "Feature",
  "properties": {
    "iso:country":"CA",
    "sg:address":"2425 Rue Girard",
    "sg:city":"Trois-Rivieres",
    "sg:classifiers":[
        {
            "category":"Retail",
            "subcategory":"Auto Repair",
            "type":"Services"
        }
    ],
    "sg:phone":"+1 819 375 2421",
    "sg:postcode":"G8Z 2M3",
    "sg:province":"QC",
    "sg:tags":[
        "repairing",
        "automobile"
    ],
    "wof:name":"Garage Trudel & Fils Enrg",
    "wof:placetype":"venue"
},
  "geometry": {"coordinates":[-72.569061,46.338173],"type":"Point"}
}