{
  "type": "Feature",
  "properties": {
    "iso:country":"CA",
    "sg:city":"Ormstown",
    "sg:classifiers":[
        {
            "category":"Shopping",
            "subcategory":"Gifts & Souvenirs",
            "type":"Retail Goods"
        }
    ],
    "sg:phone":"+1 450 829 4170",
    "sg:postcode":"J0S 1K0",
    "sg:province":"QC",
    "sg:tags":[
        "balloon",
        "artist"
    ],
    "wof:name":"Party Plus",
    "wof:placetype":"venue"
},
  "geometry": {"coordinates":[-73.9836654663,45.1204490662],"type":"Point"}
}