{
  "type": "Feature",
  "properties": {
    "addr:full":"412 Av Perreault Sept-Iles QC G4R 1K5",
    "addr:postcode":"g4r 1k5",
    "addr:street":"412 Av Perreault Sept-Iles",
    "iso:country":"CA",
    "sg:address":"412 Av Perreault",
    "sg:city":"Sept-Iles",
    "sg:classifiers":[
        {
            "category":"Wholesale",
            "subcategory":"Hardware",
            "type":"Manufacturing & Wholesale Goods"
        }
    ],
    "sg:phone":"+1 418 962 5673",
    "sg:postcode":"G4R 1K5",
    "sg:province":"QC",
    "sg:tags":[
        "equipment",
        "refrigerating",
        "supply"
    ],
    "wof:name":"Lajoie Refrigeration Inc",
    "wof:placetype":"venue"
},
  "geometry": {"coordinates":[-66.368904,50.21389],"type":"Point"}
}