{
  "type": "Feature",
  "properties": {
    "addr:full":"160 Woodford Close SW Calgary AB T2W 6E2",
    "addr:housenumber":"160",
    "addr:postcode":"t2w 6e2",
    "addr:street":"Woodford Close Sw",
    "iso:country":"CA",
    "sg:address":"160 Woodford Close SW",
    "sg:city":"Calgary",
    "sg:classifiers":[
        {
            "category":"Building & Trades",
            "subcategory":"Cleaning & Sanitation",
            "type":"Services"
        }
    ],
    "sg:phone":"+1 403 238 0733",
    "sg:postcode":"T2W 6E2",
    "sg:province":"AB",
    "sg:tags":[
        "janitor"
    ],
    "wof:name":"Harmony Cleaning Svc Ltd",
    "wof:placetype":"venue"
},
  "geometry": {"coordinates":[-114.124573,50.947018],"type":"Point"}
}