{
  "type": "Feature",
  "properties": {
    "iso:country":"CA",
    "sg:address":"1746 Sandner Frontage Rd",
    "sg:city":"Christina Lake",
    "sg:classifiers":[
        {
            "category":"Health Services",
            "subcategory":"Doctor",
            "type":"Services"
        }
    ],
    "sg:phone":"+1 250 447 6262",
    "sg:postcode":"V0H 1E0",
    "sg:province":"BC",
    "sg:tags":[
        "clinic"
    ],
    "wof:name":"Christina Lake Medical Clinic",
    "wof:placetype":"venue"
},
  "geometry": {"coordinates":[-118.210235596,49.0524711609],"type":"Point"}
}