{
  "type": "Feature",
  "properties": {
    "addr:full":"228 Westmorland St Fredericton NB E3B 3L8",
    "addr:housenumber":"228",
    "addr:postcode":"e3b 3l8",
    "addr:street":"Westmorland St",
    "iso:country":"CA",
    "sg:address":"228 Westmorland St",
    "sg:city":"Fredericton",
    "sg:classifiers":[
        {
            "category":"Professional",
            "subcategory":"Accounting & Tax Preparation",
            "type":"Services"
        }
    ],
    "sg:phone":"+1 506 459 3815",
    "sg:postcode":"E3B 3L8",
    "sg:province":"NB",
    "sg:tags":[
        "accountant"
    ],
    "wof:name":"G M Accounting Svc Ltd",
    "wof:placetype":"venue"
},
  "geometry": {"coordinates":[-66.648033,45.960663],"type":"Point"}
}