{
  "type": "Feature",
  "properties": {
    "addr:full":"2351 Main St Val Caron ON P3N 1A9",
    "addr:housenumber":"2351",
    "addr:postcode":"p3n 1a9",
    "addr:street":"Main St",
    "iso:country":"CA",
    "sg:address":"2351 Main St",
    "sg:city":"Val Caron",
    "sg:classifiers":[
        {
            "category":"Home & Garden",
            "subcategory":"Carpets & Floor Coverings",
            "type":"Retail Goods"
        }
    ],
    "sg:phone":"+1 705 897 2048",
    "sg:postcode":"P3N 1A9",
    "sg:province":"ON",
    "sg:tags":[
        "resurfacing",
        "material",
        "laying",
        "refinishing"
    ],
    "wof:name":"Custom Hardwood Floors",
    "wof:placetype":"venue"
},
  "geometry": {"coordinates":[-81.035782,46.60939],"type":"Point"}
}