{
  "type": "Feature",
  "properties": {
    "iso:country":"CA",
    "sg:address":"9 Vancouver Dr",
    "sg:city":"Guelph",
    "sg:classifiers":[
        {
            "category":"Building & Trades",
            "subcategory":"Electrical",
            "type":"Services"
        }
    ],
    "sg:phone":"+1 519 823 8195",
    "sg:postcode":"N1E 2E7",
    "sg:province":"ON",
    "sg:tags":[
        "electric",
        "contractor"
    ],
    "wof:name":"Jones Electric",
    "wof:placetype":"venue"
},
  "geometry": {"coordinates":[-80.23997497560001,43.5596542358],"type":"Point"}
}