{
  "type": "Feature",
  "properties": {
    "iso:country":"CA",
    "sg:address":"3050 Portage Ave",
    "sg:city":"Winnipeg",
    "sg:classifiers":[
        {
            "category":"Retail",
            "subcategory":"Veterinary Services",
            "type":"Services"
        }
    ],
    "sg:phone":"+1 204 889 5570",
    "sg:postcode":"R3K 0Y1",
    "sg:province":"MB",
    "sg:tags":[
        "hospital",
        "veterinarian",
        "animal"
    ],
    "wof:name":"Assiniboia Animal Hospital",
    "wof:placetype":"venue"
},
  "geometry": {"coordinates":[-97.2816772461,49.8797416687],"type":"Point"}
}