{
  "type": "Feature",
  "properties": {
    "iso:country":"CA",
    "sg:address":"390 Moss St",
    "sg:city":"Victoria",
    "sg:classifiers":[
        {
            "category":"Food & Beverages",
            "subcategory":"Groceries & Convenience Stores",
            "type":"Retail Goods"
        }
    ],
    "sg:phone":"+1 250 386 6044",
    "sg:postcode":"V8V 4N1",
    "sg:province":"BC",
    "sg:tags":[
        "grocer"
    ],
    "wof:name":"Clare-Mart Foods Ltd",
    "wof:placetype":"venue"
},
  "geometry": {"coordinates":[-123.34909057599999,48.4149932861],"type":"Point"}
}