{
  "type": "Feature",
  "properties": {
    "addr:full":"74 Boulder Blvd Stony Plain AB T7Z 1V7",
    "addr:housenumber":"74",
    "addr:postcode":"t7z 1v7",
    "addr:street":"Boulder Blvd",
    "iso:country":"CA",
    "sg:address":"74 Boulder Blvd",
    "sg:city":"Stony Plain",
    "sg:classifiers":[
        {
            "category":"Travel",
            "subcategory":"Hotels & Motels",
            "type":"Entertainment"
        }
    ],
    "sg:phone":"+1 780 963 1161",
    "sg:postcode":"T7Z 1V7",
    "sg:province":"AB",
    "wof:name":"Travelodge Hotel Stony Plain",
    "wof:placetype":"venue"
},
  "geometry": {"coordinates":[-113.977577,53.542274],"type":"Point"}
}