{
  "type": "Feature",
  "properties": {
    "addr:full":"55 Rue Levesque E Sacre-Coeur-Saguenay QC G0T 1Y0",
    "addr:housenumber":"55",
    "addr:postcode":"g0t 1y0",
    "addr:street":"Rue Levesque E Sacre-Coeur-Saguenay",
    "iso:country":"CA",
    "sg:address":"55 Rue Levesque E",
    "sg:city":"Sacre-Coeur-Saguenay",
    "sg:classifiers":[
        {
            "category":"Organizations",
            "subcategory":"Religious Organization",
            "type":"Services"
        }
    ],
    "sg:phone":"+1 418 236 9227",
    "sg:postcode":"G0T 1Y0",
    "sg:province":"QC",
    "sg:tags":[
        "house",
        "retreat"
    ],
    "wof:name":"Pavillon Leopold Myrand",
    "wof:placetype":"venue"
},
  "geometry": {"coordinates":[-69.80059799999999,48.231564],"type":"Point"}
}