{
  "type": "Feature",
  "properties": {
    "addr:full":"1623 Wilson Ave North York ON M3L 1A5",
    "addr:housenumber":"1623",
    "addr:postcode":"m3l 1a5",
    "addr:street":"Wilson Ave",
    "iso:country":"CA",
    "sg:address":"1623 Wilson Ave",
    "sg:city":"North York",
    "sg:classifiers":[
        {
            "category":"Health Services",
            "subcategory":"Doctor",
            "type":"Services"
        }
    ],
    "sg:phone":"+1 416 244 5544",
    "sg:postcode":"M3L 1A5",
    "sg:province":"ON",
    "sg:tags":[
        "dentist"
    ],
    "wof:name":"Smile Magic Dental Clinic",
    "wof:placetype":"venue"
},
  "geometry": {"coordinates":[-79.513229,43.719791],"type":"Point"}
}