{
  "type": "Feature",
  "properties": {
    "addr:full":"376 Victoria St N Kitchener ON N2H 5E6",
    "addr:housenumber":"376",
    "addr:postcode":"n2h 5e6",
    "addr:street":"Victoria St N",
    "iso:country":"CA",
    "sg:address":"376 Victoria St N",
    "sg:city":"Kitchener",
    "sg:classifiers":[
        {
            "category":"Shopping",
            "type":"Retail Goods"
        }
    ],
    "sg:phone":"+1 519 743 6851",
    "sg:postcode":"N2H 5E6",
    "sg:province":"ON",
    "sg:tags":[
        "equipment",
        "wine",
        "supply"
    ],
    "wof:name":"Wine Kitz",
    "wof:placetype":"venue"
},
  "geometry": {"coordinates":[-80.481903,43.458935],"type":"Point"}
}