{
  "type": "Feature",
  "properties": {
    "addr:full":"6 Stanley Cres Red Deer AB T4N 0E9",
    "addr:housenumber":"6",
    "addr:postcode":"t4n 0e9",
    "addr:street":"Stanley Cres",
    "iso:country":"CA",
    "sg:address":"6 Stanley Cres",
    "sg:city":"Red Deer",
    "sg:classifiers":[
        {
            "category":"Professional",
            "subcategory":"Advertising",
            "type":"Services"
        }
    ],
    "sg:phone":"+1 403 347 9626",
    "sg:postcode":"T4N 0E9",
    "sg:province":"AB",
    "sg:tags":[
        "counselor"
    ],
    "wof:name":"Life in the Fax Lane",
    "wof:placetype":"venue"
},
  "geometry": {"coordinates":[-113.801132,52.250828],"type":"Point"}
}