{
  "type": "Feature",
  "properties": {
    "addr:full":"Vancouver BC V6E 4C4",
    "addr:postcode":"v6e 4c4",
    "iso:country":"CA",
    "sg:city":"Vancouver",
    "sg:classifiers":[
        {
            "category":"Wholesale",
            "subcategory":"Farm Supplies",
            "type":"Manufacturing & Wholesale Goods"
        }
    ],
    "sg:phone":"+1 604 646 6678",
    "sg:postcode":"V6E 4C4",
    "sg:province":"BC",
    "sg:tags":[
        "grain"
    ],
    "wof:name":"Harbour Grain Merchant Inc",
    "wof:placetype":"venue"
},
  "geometry": {"coordinates":[-123.123245,49.287487],"type":"Point"}
}