{
  "type": "Feature",
  "properties": {
    "addr:full":"405 Sackville Dr Lower Sackville NS B4C 2R9",
    "addr:housenumber":"405",
    "addr:postcode":"b4c 2r9",
    "addr:street":"Sackville Dr",
    "iso:country":"CA",
    "sg:address":"405 Sackville Dr",
    "sg:city":"Lower Sackville",
    "sg:classifiers":[
        {
            "category":"Health Services",
            "subcategory":"Doctor",
            "type":"Services"
        }
    ],
    "sg:phone":"+1 902 865 7555",
    "sg:postcode":"B4C 2R9",
    "sg:province":"NS",
    "sg:tags":[
        "physician",
        "surgeon"
    ],
    "wof:name":"Eye Exams",
    "wof:placetype":"venue"
},
  "geometry": {"coordinates":[-63.6762695312,44.7641906738],"type":"Point"}
}