{
  "type": "Feature",
  "properties": {
    "addr:full":"3224 28 St SW Calgary AB T3E 2J6",
    "addr:housenumber":"3224",
    "addr:postcode":"t3e 2j6",
    "addr:street":"28 St Sw",
    "iso:country":"CA",
    "sg:address":"3224 28 St SW",
    "sg:city":"Calgary",
    "sg:classifiers":[
        {
            "category":"Social Services",
            "subcategory":"Child Care",
            "type":"Services"
        }
    ],
    "sg:phone":"+1 403 217 5394",
    "sg:postcode":"T3E 2J6",
    "sg:province":"AB",
    "wof:name":"Calgary Family Day Homes",
    "wof:placetype":"venue"
},
  "geometry": {"coordinates":[-114.12786102299999,51.026134491],"type":"Point"}
}