{
  "type": "Feature",
  "properties": {
    "addr:full":"531 Rue Roussin Lac-Saint-Charles QC G3G 2C8",
    "addr:housenumber":"531",
    "addr:postcode":"g3g 2c8",
    "addr:street":"Rue Roussin Lac-Saint-Charles",
    "iso:country":"CA",
    "sg:address":"531 Rue Roussin",
    "sg:city":"Lac-Saint-Charles",
    "sg:classifiers":[
        {
            "category":"Wholesale",
            "subcategory":"Construction Materials",
            "type":"Manufacturing & Wholesale Goods"
        }
    ],
    "sg:phone":"+1 418 849 2808",
    "sg:postcode":"G3G 2C8",
    "sg:province":"QC",
    "sg:tags":[
        "fence"
    ],
    "wof:name":"Clotures Universelles Inc",
    "wof:placetype":"venue"
},
  "geometry": {"coordinates":[-71.3628082275,46.8923683167],"type":"Point"}
}