{
  "type": "Feature",
  "properties": {
    "iso:country":"CA",
    "sg:address":"196 Yorkshire Dr",
    "sg:city":"Newmarket",
    "sg:classifiers":[
        {
            "category":"Organizations",
            "subcategory":"Professional Association",
            "type":"Services"
        }
    ],
    "sg:phone":"+1 905 954 0730",
    "sg:postcode":"L3Y 6J7",
    "sg:province":"ON",
    "wof:name":"Canadian Home Builders Assn",
    "wof:placetype":"venue"
},
  "geometry": {"coordinates":[-79.472084,44.063709],"type":"Point"}
}