{
  "type": "Feature",
  "properties": {
    "addr:full":"196 Yorkshire Dr Newmarket ON L3Y 6J7",
    "addr:housenumber":"196",
    "addr:postcode":"l3y 6j7",
    "addr:street":"Yorkshire Dr",
    "iso:country":"CA",
    "sg:address":"196 Yorkshire Dr",
    "sg:city":"Newmarket",
    "sg:classifiers":[
        {
            "category":"Organizations",
            "subcategory":"Professional Association",
            "type":"Services"
        }
    ],
    "sg:phone":"+1 905 954 0730",
    "sg:postcode":"L3Y 6J7",
    "sg:province":"ON",
    "wof:name":"Canadian Home Builders Assn",
    "wof:placetype":"venue"
},
  "geometry": {"coordinates":[-79.472084,44.063709],"type":"Point"}
}