{
  "type": "Feature",
  "properties": {
    "addr:full":"17 Mcewan Dr W # 9 Bolton ON L7E 1H5",
    "addr:housenumber":"17",
    "addr:postcode":"l7e 1h5",
    "addr:street":"Mcewan Dr W # 9",
    "iso:country":"CA",
    "sg:address":"17 Mcewan Dr W # 9",
    "sg:city":"Bolton",
    "sg:classifiers":[
        {
            "category":"Recreation",
            "type":"Entertainment"
        }
    ],
    "sg:phone":"+1 905 857 0009",
    "sg:postcode":"L7E 1H5",
    "sg:province":"ON",
    "sg:tags":[
        "instruction",
        "gymnastic"
    ],
    "wof:name":"Bolton Gym Club",
    "wof:placetype":"venue"
},
  "geometry": {"coordinates":[-79.71209,43.86198],"type":"Point"}
}