{
  "type": "Feature",
  "properties": {
    "addr:full":"21 Station St Duncan BC V9L 1M2",
    "addr:housenumber":"21",
    "addr:postcode":"v9l 1m2",
    "addr:street":"Station St",
    "iso:country":"CA",
    "sg:address":"21 Station St",
    "sg:city":"Duncan",
    "sg:classifiers":[
        {
            "category":"Banks & Credit Unions",
            "subcategory":"Investment Brokerage",
            "type":"Services"
        }
    ],
    "sg:phone":"+1 250 715 2352",
    "sg:postcode":"V9L 1M2",
    "sg:province":"BC",
    "wof:name":"Bmo Nesbitt Burns Inc",
    "wof:placetype":"venue"
},
  "geometry": {"coordinates":[-123.707260132,48.7778205872],"type":"Point"}
}