{
  "type": "Feature",
  "properties": {
    "addr:full":"Mississauga ON L5T 1J2",
    "addr:postcode":"l5t 1j2",
    "iso:country":"CA",
    "sg:city":"Mississauga",
    "sg:classifiers":[
        {
            "category":"Shopping",
            "type":"Retail Goods"
        }
    ],
    "sg:phone":"+1 905 564 6446",
    "sg:postcode":"L5T 1J2",
    "sg:province":"ON",
    "sg:tags":[
        "awning",
        "canopy"
    ],
    "wof:name":"Somfy Canada",
    "wof:placetype":"venue"
},
  "geometry": {"coordinates":[-79.662971,43.65572],"type":"Point"}
}