{
  "type": "Feature",
  "properties": {
    "iso:country":"CA",
    "sg:address":"1550 Hall Ave",
    "sg:city":"Windsor",
    "sg:classifiers":[
        {
            "category":"Building & Trades",
            "subcategory":"Cleaning & Sanitation",
            "type":"Services"
        }
    ],
    "sg:phone":"+1 519 977 5241",
    "sg:postcode":"N8X 4R7",
    "sg:province":"ON",
    "sg:tags":[
        "janitor"
    ],
    "wof:name":"Active Janitorial",
    "wof:placetype":"venue"
},
  "geometry": {"coordinates":[-83.0092391968,42.305519104],"type":"Point"}
}