{
  "type": "Feature",
  "properties": {
    "addr:full":"243 Erie St Stratford ON N5A 2M9",
    "addr:housenumber":"243",
    "addr:postcode":"n5a 2m9",
    "addr:street":"Erie St",
    "iso:country":"CA",
    "sg:address":"243 Erie St",
    "sg:city":"Stratford",
    "sg:classifiers":[
        {
            "category":"Health Services",
            "subcategory":"Health Practitioner",
            "type":"Services"
        }
    ],
    "sg:phone":"+1 519 271 3490",
    "sg:postcode":"N5A 2M9",
    "sg:province":"ON",
    "sg:tags":[
        "midwife"
    ],
    "wof:name":"Stratford Midwives",
    "wof:placetype":"venue"
},
  "geometry": {"coordinates":[-80.987106,43.366104],"type":"Point"}
}