{
  "type": "Feature",
  "properties": {
    "iso:country":"CA",
    "sg:address":"66 Kenmount Rd # 302",
    "sg:city":"St. John's",
    "sg:classifiers":[
        {
            "category":"Marine",
            "type":"Transportation"
        }
    ],
    "sg:phone":"+1 709 576 3433",
    "sg:postcode":"A1B 3V7",
    "sg:province":"NL",
    "sg:tags":[
        "towing"
    ],
    "wof:name":"Comtug",
    "wof:placetype":"venue"
},
  "geometry": {"coordinates":[-52.7563705444,47.5582962036],"type":"Point"}
}