{
  "type": "Feature",
  "properties": {
    "iso:country":"CA",
    "sg:address":"463 Prince St",
    "sg:city":"Sydney",
    "sg:classifiers":[
        {
            "category":"Professional",
            "subcategory":"Lawyer & Legal Services",
            "type":"Services"
        }
    ],
    "sg:phone":"+1 902 564 6611",
    "sg:postcode":"B1P 5L6",
    "sg:province":"NS",
    "sg:tags":[
        "attorney"
    ],
    "wof:name":"Khattar, John G",
    "wof:placetype":"venue"
},
  "geometry": {"coordinates":[-60.1780014038,46.1406517029],"type":"Point"}
}