{
  "type": "Feature",
  "properties": {
    "addr:full":"88 Beaverbrook St Moncton NB E1C 9S7",
    "addr:housenumber":"88",
    "addr:postcode":"e1c 9s7",
    "addr:street":"Beaverbrook St",
    "iso:country":"CA",
    "sg:address":"88 Beaverbrook St",
    "sg:city":"Moncton",
    "sg:classifiers":[
        {
            "category":"Building & Trades",
            "subcategory":"Electrical",
            "type":"Services"
        }
    ],
    "sg:phone":"+1 506 857 2233",
    "sg:postcode":"E1C 9S7",
    "sg:province":"NB",
    "sg:tags":[
        "electric",
        "contractor"
    ],
    "wof:name":"Electrical & Refrigeration Svc",
    "wof:placetype":"venue"
},
  "geometry": {"coordinates":[-64.806274,46.09462],"type":"Point"}
}