{
  "type": "Feature",
  "properties": {
    "addr:full":"42206 Yarrow Central Rd Chilliwack BC V2R 5E4",
    "addr:postcode":"42206;v2r 5e4",
    "addr:street":"Central Rd",
    "iso:country":"CA",
    "sg:address":"42206 Yarrow Central Rd",
    "sg:city":"Chilliwack",
    "sg:classifiers":[
        {
            "category":"Banks & Credit Unions",
            "subcategory":"Bank",
            "type":"Services"
        }
    ],
    "sg:phone":"+1 604 703 7660",
    "sg:postcode":"V2R 5E4",
    "sg:province":"BC",
    "wof:name":"Envision Credit Union",
    "wof:placetype":"venue"
},
  "geometry": {"coordinates":[-122.05624400000001,49.081886],"type":"Point"}
}