{
  "type": "Feature",
  "properties": {
    "addr:full":"Sainte-Emelie-DE-L'Energie QC J0K 2K0",
    "addr:postcode":"j0k 2k0",
    "iso:country":"CA",
    "sg:city":"Sainte-Emelie-DE-L'Energie",
    "sg:classifiers":[
        {
            "category":"Recreation",
            "subcategory":"Amusement Park",
            "type":"Entertainment"
        }
    ],
    "sg:phone":"+1 450 886 5958",
    "sg:postcode":"J0K 2K0",
    "sg:province":"QC",
    "wof:name":"Loisirs Ste-Emelie Inc",
    "wof:placetype":"venue"
},
  "geometry": {"coordinates":[-70.604958,46.278858],"type":"Point"}
}