{
  "type": "Feature",
  "properties": {
    "addr:full":"2391 Trafalgar Rd Oakville ON L6H 6K7",
    "addr:housenumber":"2391",
    "addr:postcode":"l6h 6k7",
    "addr:street":"Trafalgar Rd",
    "iso:country":"CA",
    "sg:address":"2391 Trafalgar Rd",
    "sg:city":"Oakville",
    "sg:classifiers":[
        {
            "category":"Banks & Credit Unions",
            "subcategory":"Bank",
            "type":"Services"
        }
    ],
    "sg:phone":"+1 905 257 4810",
    "sg:postcode":"L6H 6K7",
    "sg:province":"ON",
    "wof:name":"Scotiabank",
    "wof:placetype":"venue"
},
  "geometry": {"coordinates":[-79.714546,43.484367],"type":"Point"}
}