{
  "type": "Feature",
  "properties": {
    "iso:country":"CA",
    "sg:address":"201 Selby St",
    "sg:city":"Nanaimo",
    "sg:classifiers":[
        {
            "category":"Professional",
            "subcategory":"Accounting & Tax Preparation",
            "type":"Services"
        }
    ],
    "sg:phone":"+1 250 755 7704",
    "sg:postcode":"V9R 2R2",
    "sg:province":"BC",
    "sg:tags":[
        "consultant",
        "return",
        "filing"
    ],
    "wof:name":"Liberty Tax Svc",
    "wof:placetype":"venue"
},
  "geometry": {"coordinates":[-123.943466187,49.1666526794],"type":"Point"}
}