{
  "type": "Feature",
  "properties": {
    "iso:country":"CA",
    "sg:address":"117 Main St",
    "sg:city":"Raymore",
    "sg:classifiers":[
        {
            "category":"Insurance",
            "subcategory":"Insurance Agent",
            "type":"Services"
        }
    ],
    "sg:phone":"+1 306 746 2944",
    "sg:postcode":"S0A 3J0",
    "sg:province":"SK",
    "wof:name":"Raymore Agencies Ltd",
    "wof:placetype":"venue"
},
  "geometry": {"coordinates":[-104.538025,51.409729],"type":"Point"}
}