{
  "type": "Feature",
  "properties": {
    "iso:country":"CA",
    "sg:address":"4419 Rue Beaubien E",
    "sg:city":"Montreal",
    "sg:classifiers":[
        {
            "category":"Retail",
            "subcategory":"Funeral Services",
            "type":"Services"
        }
    ],
    "sg:phone":"+1 514 527 4126",
    "sg:postcode":"H1T 1T2",
    "sg:province":"QC",
    "sg:tags":[
        "director"
    ],
    "wof:name":"Salon Funeraire T Sansregret",
    "wof:placetype":"venue"
},
  "geometry": {"coordinates":[-73.577133,45.5658],"type":"Point"}
}