{
  "type": "Feature",
  "properties": {
    "addr:full":"3172 Douglas St Victoria BC V8Z 3K5",
    "addr:housenumber":"3172",
    "addr:postcode":"v8z 3k5",
    "addr:street":"Douglas St",
    "iso:country":"CA",
    "sg:address":"3172 Douglas St",
    "sg:city":"Victoria",
    "sg:classifiers":[
        {
            "category":"Home & Garden",
            "subcategory":"Building Materials",
            "type":"Retail Goods"
        }
    ],
    "sg:phone":"+1 250 385 8794",
    "sg:postcode":"V8Z 3K5",
    "sg:province":"BC",
    "sg:tags":[
        "paint"
    ],
    "wof:name":"Mills Paint Sales Ltd",
    "wof:placetype":"venue"
},
  "geometry": {"coordinates":[-123.372108459,48.4468421936],"type":"Point"}
}