{
  "type": "Feature",
  "properties": {
    "iso:country":"CA",
    "sg:address":"293 Av Des Rosiers",
    "sg:city":"Blainville",
    "sg:classifiers":[
        {
            "category":"Wholesale",
            "subcategory":"Electrical",
            "type":"Manufacturing & Wholesale Goods"
        }
    ],
    "sg:phone":"+1 450 435 6273",
    "sg:postcode":"J7C 2Y8",
    "sg:province":"QC",
    "sg:tags":[
        "control",
        "burglary",
        "security",
        "protective",
        "robbery"
    ],
    "wof:name":"Alarmes & Comm Progix Ltee",
    "wof:placetype":"venue"
},
  "geometry": {"coordinates":[-73.8724365234,45.6621551514],"type":"Point"}
}