{
  "type": "Feature",
  "properties": {
    "addr:full":"4552 Redonda Ave Powell River BC V8A 3H4",
    "addr:postcode":"4552;powell;v8a 3h4",
    "addr:street":"Redonda Ave",
    "iso:country":"CA",
    "sg:address":"4552 Redonda Ave",
    "sg:city":"Powell River",
    "sg:classifiers":[
        {
            "category":"Cinema",
            "subcategory":"Movie Rental",
            "type":"Entertainment"
        }
    ],
    "sg:phone":"+1 604 485 2021",
    "sg:postcode":"V8A 3H4",
    "sg:province":"BC",
    "sg:tags":[
        "leasing",
        "video",
        "disc",
        "tape"
    ],
    "wof:name":"Arclen Video",
    "wof:placetype":"venue"
},
  "geometry": {"coordinates":[-124.51327499999999,49.840145],"type":"Point"}
}