{
  "type": "Feature",
  "properties": {
    "addr:full":"Surrey BC V3T 2Z3",
    "addr:postcode":"v3t 2z3",
    "iso:country":"CA",
    "sg:city":"Surrey",
    "sg:classifiers":[
        {
            "category":"Shopping",
            "subcategory":"Pharmacy",
            "type":"Retail Goods"
        }
    ],
    "sg:phone":"+1 604 589 4300",
    "sg:postcode":"V3T 2Z3",
    "sg:province":"BC",
    "wof:name":"Sandell Drug Mart",
    "wof:placetype":"venue"
},
  "geometry": {"coordinates":[-122.867515564,49.1884536743],"type":"Point"}
}