{
  "type": "Feature",
  "properties": {
    "addr:full":"380 St Andrew St W Fergus ON N1M 1N9",
    "addr:housenumber":"380",
    "addr:postcode":"n1m 1n9",
    "addr:street":"St Andrew St W",
    "iso:country":"CA",
    "sg:address":"380 St Andrew St W",
    "sg:city":"Fergus",
    "sg:classifiers":[
        {
            "category":"Education",
            "subcategory":"Dance Studio",
            "type":"Public Place"
        }
    ],
    "sg:phone":"+1 519 843 5040",
    "sg:postcode":"N1M 1N9",
    "sg:province":"ON",
    "sg:tags":[
        "dancing",
        "instruction",
        "program",
        "fitness",
        "exercise",
        "physical"
    ],
    "wof:name":"Grand River Dance Academy",
    "wof:placetype":"venue"
},
  "geometry": {"coordinates":[-80.379974,43.702763],"type":"Point"}
}