{
  "type": "Feature",
  "properties": {
    "iso:country":"CA",
    "sg:address":"331 Patrick St",
    "sg:city":"Sault Ste Marie",
    "sg:classifiers":[
        {
            "category":"Education",
            "subcategory":"School",
            "type":"Public Place"
        }
    ],
    "sg:phone":"+1 705 945 7140",
    "sg:postcode":"P6C 3Y9",
    "sg:province":"ON",
    "wof:name":"William Merriefield School",
    "wof:placetype":"venue"
},
  "geometry": {"coordinates":[-84.35321044920001,46.5335960388],"type":"Point"}
}