{
  "type": "Feature",
  "properties": {
    "addr:full":"Campbell River BC V9W 2C2",
    "addr:postcode":"v9w 2c2",
    "iso:country":"CA",
    "sg:city":"Campbell River",
    "sg:classifiers":[
        {
            "category":"Professional",
            "subcategory":"Lawyer & Legal Services",
            "type":"Services"
        }
    ],
    "sg:phone":"+1 250 830 0768",
    "sg:postcode":"V9W 2C2",
    "sg:province":"BC",
    "sg:tags":[
        "attorney"
    ],
    "wof:name":"Preston & CO",
    "wof:placetype":"venue"
},
  "geometry": {"coordinates":[-125.23994399999999,50.023499],"type":"Point"}
}