{
  "type": "Feature",
  "properties": {
    "addr:full":"204 Millbank Dr SW Calgary AB T2Y 2H9",
    "addr:housenumber":"204",
    "addr:postcode":"t2y 2h9",
    "addr:street":"Millbank Dr Sw",
    "iso:country":"CA",
    "sg:address":"204 Millbank Dr SW",
    "sg:city":"Calgary",
    "sg:classifiers":[
        {
            "category":"Professional",
            "subcategory":"Accounting & Tax Preparation",
            "type":"Services"
        }
    ],
    "sg:phone":"+1 403 256 4639",
    "sg:postcode":"T2Y 2H9",
    "sg:province":"AB",
    "sg:tags":[
        "accountant"
    ],
    "wof:name":"Aardvark Business Svc",
    "wof:placetype":"venue"
},
  "geometry": {"coordinates":[-114.08522000000001,50.915878],"type":"Point"}
}