{
  "type": "Feature",
  "properties": {
    "addr:full":"478 Highland Rd E Stoney Creek ON L8J 3G5",
    "addr:housenumber":"478",
    "addr:postcode":"l8j 3g5",
    "addr:street":"Highland Rd E",
    "iso:country":"CA",
    "sg:address":"478 Highland Rd E",
    "sg:city":"Stoney Creek",
    "sg:classifiers":[
        {
            "category":"Farming",
            "subcategory":"Farm",
            "type":"Manufacturing & Wholesale Goods"
        }
    ],
    "sg:phone":"+1 905 643 8443",
    "sg:postcode":"L8J 3G5",
    "sg:province":"ON",
    "wof:name":"Lincoln Mushroom Farm",
    "wof:placetype":"venue"
},
  "geometry": {"coordinates":[-79.73139999999999,43.170555],"type":"Point"}
}