{
  "type": "Feature",
  "properties": {
    "addr:full":"Hwy 2 & Hwy 34 Holland MB R0G 0X0",
    "addr:postcode":"r0g 0x0",
    "addr:street":"Hwy 2 & Hwy 34 Holland",
    "iso:country":"CA",
    "sg:address":"Hwy 2 & Hwy 34",
    "sg:city":"Holland",
    "sg:classifiers":[
        {
            "category":"Wholesale",
            "subcategory":"Machinery & Supplies",
            "type":"Manufacturing & Wholesale Goods"
        }
    ],
    "sg:phone":"+1 204 526 2740",
    "sg:postcode":"R0G 0X0",
    "sg:province":"MB",
    "sg:tags":[
        "farm",
        "equipment"
    ],
    "wof:name":"Drummond's Farm Svc Ltd",
    "wof:placetype":"venue"
},
  "geometry": {"coordinates":[-98.87776947019999,49.6007118225],"type":"Point"}
}