{
  "type": "Feature",
  "properties": {
    "addr:full":"32 Mckeen St Glace Bay NS B1A 5B9",
    "addr:housenumber":"32",
    "addr:postcode":"b1a 5b9",
    "addr:street":"Mckeen St",
    "iso:country":"CA",
    "sg:address":"32 Mckeen St",
    "sg:city":"Glace Bay",
    "sg:classifiers":[
        {
            "category":"Food & Beverages",
            "subcategory":"Groceries & Convenience Stores",
            "type":"Retail Goods"
        }
    ],
    "sg:phone":"+1 902 849 8093",
    "sg:postcode":"B1A 5B9",
    "sg:province":"NS",
    "wof:name":"Terry's Mc Keen Street Dairy",
    "wof:placetype":"venue"
},
  "geometry": {"coordinates":[-59.958015,46.19791],"type":"Point"}
}