{
  "type": "Feature",
  "properties": {
    "addr:full":"1442 King St E Kitchener ON N2G 2N7",
    "addr:housenumber":"1442",
    "addr:postcode":"n2g 2n7",
    "addr:street":"King St E",
    "iso:country":"CA",
    "sg:address":"1442 King St E",
    "sg:city":"Kitchener",
    "sg:classifiers":[
        {
            "category":"Health Services",
            "subcategory":"Chiropractor",
            "type":"Services"
        }
    ],
    "sg:phone":"+1 519 744 3582",
    "sg:postcode":"N2G 2N7",
    "sg:province":"ON",
    "wof:name":"Johannes Chiropractic Office",
    "wof:placetype":"venue"
},
  "geometry": {"coordinates":[-80.465805,43.439678],"type":"Point"}
}