{
  "type": "Feature",
  "properties": {
    "addr:full":"2419 Bellevue Ave # 108 West Vancouver BC V7V 4T4",
    "addr:housenumber":"2419",
    "addr:postcode":"v7v 4t4",
    "addr:street":"Bellevue Ave # 108",
    "iso:country":"CA",
    "sg:address":"2419 Bellevue Ave # 108",
    "sg:city":"West Vancouver",
    "sg:classifiers":[
        {
            "category":"Professional",
            "subcategory":"Business Services",
            "type":"Services"
        }
    ],
    "sg:phone":"+1 604 922 8585",
    "sg:postcode":"V7V 4T4",
    "sg:province":"BC",
    "sg:tags":[
        "drafting"
    ],
    "wof:name":"Antek Illustrations",
    "wof:placetype":"venue"
},
  "geometry": {"coordinates":[-123.18000793500001,49.3335838318],"type":"Point"}
}