{
  "type": "Feature",
  "properties": {
    "addr:full":"3700 Rue Du Campanile Sainte-Foy QC G1X 4G6",
    "addr:housenumber":"3700",
    "addr:postcode":"g1x 4g6",
    "addr:street":"Rue Du Campanile",
    "iso:country":"CA",
    "sg:address":"3700 Rue Du Campanile",
    "sg:city":"Sainte-Foy",
    "sg:classifiers":[
        {
            "category":"Professional",
            "subcategory":"Accounting & Tax Preparation",
            "type":"Services"
        }
    ],
    "sg:phone":"+1 418 575 8323",
    "sg:postcode":"G1X 4G6",
    "sg:province":"QC",
    "sg:tags":[
        "accountant"
    ],
    "wof:name":"Paquet, Tony",
    "wof:placetype":"venue"
},
  "geometry": {"coordinates":[-71.3329620361,46.7618103027],"type":"Point"}
}