{
  "type": "Feature",
  "properties": {
    "addr:full":"Lethbridge AB T1J 4M7",
    "addr:postcode":"t1j 4m7",
    "iso:country":"CA",
    "sg:city":"Lethbridge",
    "sg:classifiers":[
        {
            "category":"Shopping",
            "type":"Retail Goods"
        }
    ],
    "sg:phone":"+1 403 320 0095",
    "sg:postcode":"T1J 4M7",
    "sg:province":"AB",
    "sg:tags":[
        "pet",
        "shop"
    ],
    "wof:name":"Petland",
    "wof:placetype":"venue"
},
  "geometry": {"coordinates":[-112.833229065,49.698223114],"type":"Point"}
}