{
  "type": "Feature",
  "properties": {
    "addr:full":"35 N Railway St E Macgregor MB R0H 0R0",
    "addr:housenumber":"35",
    "addr:postcode":"r0h 0r0",
    "addr:street":"N Railway St",
    "iso:country":"CA",
    "sg:address":"35 N Railway St E",
    "sg:city":"Macgregor",
    "sg:classifiers":[
        {
            "category":"Travel",
            "subcategory":"Hotels & Motels",
            "type":"Entertainment"
        }
    ],
    "sg:phone":"+1 204 685 2066",
    "sg:postcode":"R0H 0R0",
    "sg:province":"MB",
    "wof:name":"Mac Gregor Hotel",
    "wof:placetype":"venue"
},
  "geometry": {"coordinates":[-98.779297,49.965221],"type":"Point"}
}