{
  "type": "Feature",
  "properties": {
    "addr:full":"1309 Pebble Rd Ottawa ON K1V 7R9",
    "addr:housenumber":"1309",
    "addr:postcode":"k1v 7r9",
    "addr:street":"Pebble Rd",
    "iso:country":"CA",
    "sg:address":"1309 Pebble Rd",
    "sg:city":"Ottawa",
    "sg:classifiers":[
        {
            "category":"Building & Trades",
            "subcategory":"Electrical",
            "type":"Services"
        }
    ],
    "sg:phone":"+1 613 731 3953",
    "sg:postcode":"K1V 7R9",
    "sg:province":"ON",
    "sg:tags":[
        "electric",
        "contractor"
    ],
    "wof:name":"Enertel Electric Ltd",
    "wof:placetype":"venue"
},
  "geometry": {"coordinates":[-75.6509399414,45.3604240417],"type":"Point"}
}