{
  "type": "Feature",
  "properties": {
    "addr:full":"Toronto ON M5N 1A1",
    "addr:postcode":"m5n 1a1",
    "iso:country":"CA",
    "sg:city":"Toronto",
    "sg:classifiers":[
        {
            "category":"Wholesale",
            "subcategory":"Electrical",
            "type":"Manufacturing & Wholesale Goods"
        }
    ],
    "sg:phone":"+1 416 482 4821",
    "sg:postcode":"M5N 1A1",
    "sg:province":"ON",
    "sg:tags":[
        "alarm",
        "burglar",
        "system"
    ],
    "wof:name":"Alarm Systems of Canada",
    "wof:placetype":"venue"
},
  "geometry": {"coordinates":[-79.4090270996,43.7043495178],"type":"Point"}
}