{
  "type": "Feature",
  "properties": {
    "iso:country":"CA",
    "sg:address":"72 Queensway Dr",
    "sg:city":"St Jacobs",
    "sg:classifiers":[
        {
            "category":"Education",
            "subcategory":"School",
            "type":"Public Place"
        }
    ],
    "sg:phone":"+1 519 664 2272",
    "sg:postcode":"N0B 2N0",
    "sg:province":"ON",
    "wof:name":"St Jacobs Public School",
    "wof:placetype":"venue"
},
  "geometry": {"coordinates":[-80.5554275513,43.5365943909],"type":"Point"}
}