{
  "type": "Feature",
  "properties": {
    "addr:full":"403 Bank St Ottawa ON K2P 1Y6",
    "addr:housenumber":"403",
    "addr:postcode":"k2p 1y6",
    "addr:street":"Bank St",
    "iso:country":"CA",
    "sg:address":"403 Bank St",
    "sg:city":"Ottawa",
    "sg:classifiers":[
        {
            "category":"Shopping",
            "subcategory":"Stationery & Office Supplies",
            "type":"Retail Goods"
        }
    ],
    "sg:phone":"+1 613 235 2525",
    "sg:postcode":"K2P 1Y6",
    "sg:province":"ON",
    "wof:name":"Staples Business Depot",
    "wof:placetype":"venue"
},
  "geometry": {"coordinates":[-75.69427490229999,45.4131011963],"type":"Point"}
}