{
  "type": "Feature",
  "properties": {
    "addr:full":"York ON M6M 5E2",
    "addr:postcode":"m6m 5e2",
    "iso:country":"CA",
    "sg:city":"York",
    "sg:classifiers":[
        {
            "category":"Social Services",
            "type":"Services"
        }
    ],
    "sg:phone":"+1 416 658 7720",
    "sg:postcode":"M6M 5E2",
    "sg:province":"ON",
    "sg:tags":[
        "organization",
        "welfare"
    ],
    "wof:name":"Access Apartments",
    "wof:placetype":"venue"
},
  "geometry": {"coordinates":[-79.46762099999999,43.69191],"type":"Point"}
}