{
  "type": "Feature",
  "properties": {
    "addr:full":"40 Churchill Cres St Thomas ON N5R 1N9",
    "addr:housenumber":"40",
    "addr:postcode":"n5r 1n9",
    "addr:street":"Churchill Cres",
    "iso:country":"CA",
    "sg:address":"40 Churchill Cres",
    "sg:city":"St Thomas",
    "sg:classifiers":[
        {
            "category":"Personal",
            "subcategory":"Beauty Salon",
            "type":"Services"
        }
    ],
    "sg:phone":"+1 519 631 2680",
    "sg:postcode":"N5R 1N9",
    "sg:province":"ON",
    "wof:name":"Plaza Beauty Salon",
    "wof:placetype":"venue"
},
  "geometry": {"coordinates":[-81.183418,42.766659],"type":"Point"}
}