{
  "type": "Feature",
  "properties": {
    "addr:full":"Brantford ON N3R 2W9",
    "addr:postcode":"n3r 2w9",
    "iso:country":"CA",
    "sg:city":"Brantford",
    "sg:classifiers":[
        {
            "category":"Health Services",
            "subcategory":"Doctor",
            "type":"Services"
        }
    ],
    "sg:phone":"+1 519 759 2590",
    "sg:postcode":"N3R 2W9",
    "sg:province":"ON",
    "sg:tags":[
        "dentist"
    ],
    "wof:name":"Mazzetti, Flaviano DDS",
    "wof:placetype":"venue"
},
  "geometry": {"coordinates":[-80.26256600000001,43.170002],"type":"Point"}
}