{
  "type": "Feature",
  "properties": {
    "addr:full":"12 Rue Tanguay Baie-Johan-Beetz QC G0G 1B0",
    "addr:housenumber":"12",
    "addr:postcode":"g0g 1b0",
    "addr:street":"Rue Tanguay",
    "iso:country":"CA",
    "sg:address":"12 Rue Tanguay",
    "sg:city":"Baie-Johan-Beetz",
    "sg:classifiers":[
        {
            "category":"Banks & Credit Unions",
            "subcategory":"Bank",
            "type":"Services"
        }
    ],
    "sg:phone":"+1 418 539 0155",
    "sg:postcode":"G0G 1B0",
    "sg:province":"QC",
    "wof:name":"Caisse Desjardins Baie-Johan",
    "wof:placetype":"venue"
},
  "geometry": {"coordinates":[-62.796932,50.307465],"type":"Point"}
}