{
  "type": "Feature",
  "properties": {
    "addr:full":"81 Prince St Charlottetown PE C1A 4R3",
    "addr:housenumber":"81",
    "addr:postcode":"c1a 4r3",
    "addr:street":"Prince St",
    "iso:country":"CA",
    "sg:address":"81 Prince St",
    "sg:city":"Charlottetown",
    "sg:classifiers":[
        {
            "category":"Organizations",
            "subcategory":"Non-profit Organization",
            "type":"Services"
        }
    ],
    "sg:phone":"+1 902 566 3523",
    "sg:postcode":"C1A 4R3",
    "sg:province":"PE",
    "sg:tags":[
        "charitable",
        "institution"
    ],
    "wof:name":"Pei Citizen Advocacy",
    "wof:placetype":"venue"
},
  "geometry": {"coordinates":[-63.1239013672,46.235244751],"type":"Point"}
}