{
  "type": "Feature",
  "properties": {
    "addr:full":"193 Rue Principale Saint-Jacques NB E7B 1W7",
    "addr:housenumber":"193",
    "addr:postcode":"e7b 1w7",
    "addr:street":"Rue Principale",
    "iso:country":"CA",
    "sg:address":"193 Rue Principale",
    "sg:city":"Saint-Jacques",
    "sg:classifiers":[
        {
            "category":"Shopping",
            "subcategory":"Computers & Home Electronics",
            "type":"Retail Goods"
        }
    ],
    "sg:phone":"+1 506 736 0909",
    "sg:postcode":"E7B 1W7",
    "sg:province":"NB",
    "sg:tags":[
        "equipment",
        "dealer"
    ],
    "wof:name":"Forest Cyberware Solutions",
    "wof:placetype":"venue"
},
  "geometry": {"coordinates":[-68.37744903559999,47.4183998108],"type":"Point"}
}