{
  "type": "Feature",
  "properties": {
    "addr:full":"182 Aqueduct St Welland ON L3C 1C4",
    "addr:housenumber":"182",
    "addr:postcode":"l3c 1c4",
    "addr:street":"Aqueduct St",
    "iso:country":"CA",
    "sg:address":"182 Aqueduct St",
    "sg:city":"Welland",
    "sg:classifiers":[
        {
            "category":"Education",
            "subcategory":"School",
            "type":"Public Place"
        }
    ],
    "sg:phone":"+1 905 734 7709",
    "sg:postcode":"L3C 1C4",
    "sg:province":"ON",
    "wof:name":"St Kevin's School",
    "wof:placetype":"venue"
},
  "geometry": {"coordinates":[-79.249634,42.999294],"type":"Point"}
}