{
  "type": "Feature",
  "properties": {
    "addr:full":"33 Highway 2 Leduc AB T9E 8B8",
    "addr:housenumber":"33",
    "addr:postcode":"t9e 8b8",
    "addr:street":"Highway 2",
    "iso:country":"CA",
    "sg:address":"33 Highway 2",
    "sg:city":"Leduc",
    "sg:classifiers":[
        {
            "category":"Autos & Motor Vehicles",
            "subcategory":"Recreational Vehicle Sales",
            "type":"Retail Goods"
        }
    ],
    "sg:phone":"+1 780 986 4674",
    "sg:postcode":"T9E 8B8",
    "sg:province":"AB",
    "wof:name":"Schwab Rv World Ltd",
    "wof:placetype":"venue"
},
  "geometry": {"coordinates":[-113.548568726,53.2593765259],"type":"Point"}
}