{
  "type": "Feature",
  "properties": {
    "addr:full":"21956 88 Ave Langley BC V1M 3S7",
    "addr:housenumber":"21956",
    "addr:postcode":"v1m 3s7",
    "addr:street":"88 Ave",
    "iso:country":"CA",
    "sg:address":"21956 88 Ave",
    "sg:city":"Langley",
    "sg:classifiers":[
        {
            "category":"Retail",
            "subcategory":"Auto Repair",
            "type":"Services"
        }
    ],
    "sg:phone":"+1 604 888 5555",
    "sg:postcode":"V1M 3S7",
    "sg:province":"BC",
    "sg:tags":[
        "automobile",
        "co",
        "drive",
        "transporter"
    ],
    "wof:name":"Pride Truck Delivery Ltd",
    "wof:placetype":"venue"
},
  "geometry": {"coordinates":[-122.615684509,49.1624488831],"type":"Point"}
}