{
  "type": "Feature",
  "properties": {
    "iso:country":"CA",
    "sg:address":"59 Av Principale",
    "sg:city":"Rouyn-Noranda",
    "sg:classifiers":[
        {
            "category":"Recreation",
            "type":"Entertainment"
        }
    ],
    "sg:phone":"+1 819 764 5997",
    "sg:postcode":"J9X 4P1",
    "sg:province":"QC",
    "sg:tags":[
        "bingo",
        "game"
    ],
    "wof:name":"Bingo Du Cuivre",
    "wof:placetype":"venue"
},
  "geometry": {"coordinates":[-79.01983642579999,48.2413063049],"type":"Point"}
}