{
  "type": "Feature",
  "properties": {
    "addr:full":"1522 Rue Sainte-Julie Trois-Rivieres QC G9A 1Y8",
    "addr:housenumber":"1522",
    "addr:postcode":"g9a 1y8",
    "addr:street":"Rue Sainte-Julie Trois-Rivieres",
    "iso:country":"CA",
    "sg:address":"1522 Rue Sainte-Julie",
    "sg:city":"Trois-Rivieres",
    "sg:classifiers":[
        {
            "category":"Health Services",
            "subcategory":"Nursing And Care Facility",
            "type":"Services"
        }
    ],
    "sg:phone":"+1 819 694 0451",
    "sg:postcode":"G9A 1Y8",
    "sg:province":"QC",
    "sg:tags":[
        "home",
        "retirement",
        "community",
        "rest"
    ],
    "wof:name":"Pavillon Belle Vie",
    "wof:placetype":"venue"
},
  "geometry": {"coordinates":[-72.5512390137,46.3526115417],"type":"Point"}
}