{
  "type": "Feature",
  "properties": {
    "addr:full":"65 Boullee St New Hamburg ON N3A 1E1",
    "addr:housenumber":"65",
    "addr:postcode":"n3a 1e1",
    "addr:street":"Boullee St",
    "iso:country":"CA",
    "sg:address":"65 Boullee St",
    "sg:city":"New Hamburg",
    "sg:classifiers":[
        {
            "category":"Organizations",
            "subcategory":"Community Association",
            "type":"Services"
        }
    ],
    "sg:phone":"+1 519 662 3770",
    "sg:postcode":"N3A 1E1",
    "sg:province":"ON",
    "sg:tags":[
        "club"
    ],
    "wof:name":"Royal Canadian Legion",
    "wof:placetype":"venue"
},
  "geometry": {"coordinates":[-80.7060241699,43.3773345947],"type":"Point"}
}