{
  "type": "Feature",
  "properties": {
    "addr:full":"1141 103rd St North Battleford SK S9A 1K5",
    "addr:housenumber":"1141",
    "addr:postcode":"s9a 1k5",
    "addr:street":"103Rd St",
    "iso:country":"CA",
    "sg:address":"1141 103rd St",
    "sg:city":"North Battleford",
    "sg:classifiers":[
        {
            "category":"Retail",
            "subcategory":"Portrait Studio",
            "type":"Services"
        }
    ],
    "sg:phone":"+1 306 445 5777",
    "sg:postcode":"S9A 1K5",
    "sg:province":"SK",
    "sg:tags":[
        "photography"
    ],
    "wof:name":"Viewpoint Photographic Design",
    "wof:placetype":"venue"
},
  "geometry": {"coordinates":[-108.29486084,52.774066925],"type":"Point"}
}