{
  "type": "Feature",
  "properties": {
    "addr:full":"10411 Yonge St Richmond Hill ON L4C 3C2",
    "addr:housenumber":"10411",
    "addr:postcode":"l4c 3c2",
    "addr:street":"Yonge St",
    "iso:country":"CA",
    "sg:address":"10411 Yonge St",
    "sg:city":"Richmond Hill",
    "sg:classifiers":[
        {
            "category":"Retail",
            "subcategory":"Auto Rental",
            "type":"Services"
        }
    ],
    "sg:phone":"+1 416 221 7575",
    "sg:postcode":"L4C 3C2",
    "sg:province":"ON",
    "sg:tags":[
        "renting",
        "automobile"
    ],
    "wof:name":"Advantage Car & Truck Rentals",
    "wof:placetype":"venue"
},
  "geometry": {"coordinates":[-79.4393539429,43.8812217712],"type":"Point"}
}