{
  "type": "Feature",
  "properties": {
    "addr:full":"2211 Wesbrook Mall Vancouver BC V6T 2B5",
    "addr:housenumber":"2211",
    "addr:postcode":"v6t 2b5",
    "addr:street":"Wesbrook Mall",
    "iso:country":"CA",
    "sg:address":"2211 Wesbrook Mall",
    "sg:city":"Vancouver",
    "sg:classifiers":[
        {
            "category":"Health Services",
            "subcategory":"Hospital",
            "type":"Services"
        }
    ],
    "sg:phone":"+1 604 822 7121",
    "sg:postcode":"V6T 2B5",
    "sg:province":"BC",
    "wof:name":"Ubc Hospital",
    "wof:placetype":"venue"
},
  "geometry": {"coordinates":[-123.24482727,49.26512146],"type":"Point"}
}