{
  "type": "Feature",
  "properties": {
    "addr:full":"1090 Don Mills Rd North York ON M3C 3R6",
    "addr:housenumber":"1090",
    "addr:postcode":"m3c 3r6",
    "addr:street":"Don Mills Rd",
    "iso:country":"CA",
    "sg:address":"1090 Don Mills Rd",
    "sg:city":"North York",
    "sg:classifiers":[
        {
            "category":"Manufacturing",
            "subcategory":"Printing",
            "type":"Manufacturing & Wholesale Goods"
        }
    ],
    "sg:phone":"+1 416 444 3637",
    "sg:postcode":"M3C 3R6",
    "sg:province":"ON",
    "sg:tags":[
        "multimedia"
    ],
    "wof:name":"Content Alive",
    "wof:placetype":"venue"
},
  "geometry": {"coordinates":[-79.343582,43.736717],"type":"Point"}
}