{
  "type": "Feature",
  "properties": {
    "addr:full":"439 Bell St Ingersoll ON N5C 3K1",
    "addr:housenumber":"439",
    "addr:postcode":"n5c 3k1",
    "addr:street":"Bell St",
    "iso:country":"CA",
    "sg:address":"439 Bell St",
    "sg:city":"Ingersoll",
    "sg:classifiers":[
        {
            "category":"Retail",
            "subcategory":"Auto Repair",
            "type":"Services"
        }
    ],
    "sg:phone":"+1 519 425 2146",
    "sg:postcode":"N5C 3K1",
    "sg:province":"ON",
    "sg:tags":[
        "repairing",
        "automobile"
    ],
    "wof:name":"Fast Lane",
    "wof:placetype":"venue"
},
  "geometry": {"coordinates":[-80.905151,43.041641],"type":"Point"}
}