{
  "type": "Feature",
  "properties": {
    "addr:full":"Sarnia ON N7T 7H2",
    "addr:postcode":"n7t 7h2",
    "iso:country":"CA",
    "sg:city":"Sarnia",
    "sg:classifiers":[
        {
            "category":"Building & Trades",
            "subcategory":"Construction",
            "type":"Services"
        }
    ],
    "sg:phone":"+1 519 542 6409",
    "sg:postcode":"N7T 7H2",
    "sg:province":"ON",
    "sg:tags":[
        "maker",
        "cabinet"
    ],
    "wof:name":"Met Woodworking",
    "wof:placetype":"venue"
},
  "geometry": {"coordinates":[-82.321404,42.98188],"type":"Point"}
}