{
  "type": "Feature",
  "properties": {
    "addr:full":"Blainville QC J7C 3M9",
    "addr:postcode":"j7c 3m9",
    "iso:country":"CA",
    "sg:city":"Blainville",
    "sg:classifiers":[
        {
            "category":"Banks & Credit Unions",
            "subcategory":"Bank",
            "type":"Services"
        }
    ],
    "sg:phone":"+1 450 433 2864",
    "sg:postcode":"J7C 3M9",
    "sg:province":"QC",
    "wof:name":"Cibc",
    "wof:placetype":"venue"
},
  "geometry": {"coordinates":[-73.886292,45.677395],"type":"Point"}
}