{
  "type": "Feature",
  "properties": {
    "addr:full":"3359 Rue Griffith Saint-Laurent QC H4T 1W5",
    "addr:housenumber":"3359",
    "addr:postcode":"h4t 1w5",
    "addr:street":"Rue Griffith",
    "iso:country":"CA",
    "sg:address":"3359 Rue Griffith",
    "sg:city":"Saint-Laurent",
    "sg:classifiers":[
        {
            "category":"Shopping",
            "type":"Retail Goods"
        }
    ],
    "sg:phone":"+1 514 737 3422",
    "sg:postcode":"H4T 1W5",
    "sg:province":"QC",
    "sg:tags":[
        "orthopedic",
        "appliance"
    ],
    "wof:name":"Sos Rehabilitation",
    "wof:placetype":"venue"
},
  "geometry": {"coordinates":[-73.69377900000001,45.489075],"type":"Point"}
}