{
  "type": "Feature",
  "properties": {
    "iso:country":"CA",
    "sg:address":"294 Rue Labelle",
    "sg:city":"Saint-Jerome",
    "sg:classifiers":[
        {
            "category":"Professional",
            "subcategory":"Business Services",
            "type":"Services"
        }
    ],
    "sg:phone":"+1 450 438 8540",
    "sg:postcode":"J7Z 5L1",
    "sg:province":"QC",
    "sg:tags":[
        "estate"
    ],
    "wof:name":"Lajeunesse, Anne",
    "wof:placetype":"venue"
},
  "geometry": {"coordinates":[-74.0046157837,45.7760238647],"type":"Point"}
}