{
  "type": "Feature",
  "properties": {
    "addr:full":"PO Box 95 Gillies Bay BC V0N 1W0",
    "addr:housenumber":"po box 95",
    "addr:postcode":"v0n 1w0",
    "iso:country":"CA",
    "sg:address":"PO Box 95",
    "sg:city":"Gillies Bay",
    "sg:classifiers":[
        {
            "category":"Airport",
            "type":"Transportation"
        }
    ],
    "sg:phone":"+1 604 486 7268",
    "sg:postcode":"V0N 1W0",
    "sg:province":"BC",
    "sg:tags":[
        "government"
    ],
    "wof:name":"Texada Island Airport",
    "wof:placetype":"venue"
},
  "geometry": {"coordinates":[-124.484840393,49.6774215698],"type":"Point"}
}