{
  "type": "Feature",
  "properties": {
    "addr:full":"945 Av Wolfe Sainte-Foy QC G1V 5B3",
    "addr:postcode":"g1v 5b3",
    "addr:street":"945 Av Wolfe",
    "iso:country":"CA",
    "sg:address":"945 Av Wolfe",
    "sg:city":"Sainte-Foy",
    "sg:classifiers":[
        {
            "category":"Education",
            "subcategory":"School",
            "type":"Public Place"
        }
    ],
    "sg:phone":"+1 418 652 2121",
    "sg:postcode":"G1V 5B3",
    "sg:province":"QC",
    "wof:name":"Commission Scolaire Decouvreur",
    "wof:placetype":"venue"
},
  "geometry": {"coordinates":[-71.294533,46.775578],"type":"Point"}
}