{
  "type": "Feature",
  "properties": {
    "iso:country":"CA",
    "sg:address":"1203 Lawrence Ave W",
    "sg:city":"North York",
    "sg:classifiers":[
        {
            "category":"Manufacturing",
            "subcategory":"Metals",
            "type":"Manufacturing & Wholesale Goods"
        }
    ],
    "sg:phone":"+1 416 787 6109",
    "sg:postcode":"M6A 1E2",
    "sg:province":"ON",
    "sg:tags":[
        "plating"
    ],
    "wof:name":"Superfinish CO Ltd",
    "wof:placetype":"venue"
},
  "geometry": {"coordinates":[-79.4681091309,43.7110099792],"type":"Point"}
}