{
  "type": "Feature",
  "properties": {
    "iso:country":"CA",
    "sg:address":"33952 Pine St",
    "sg:city":"Abbotsford",
    "sg:classifiers":[
        {
            "category":"Education",
            "subcategory":"School",
            "type":"Public Place"
        }
    ],
    "sg:phone":"+1 604 859 6726",
    "sg:postcode":"V2S 2P3",
    "sg:province":"BC",
    "wof:name":"Philip Sheffield Elementary",
    "wof:placetype":"venue"
},
  "geometry": {"coordinates":[-122.28503418,49.0511703491],"type":"Point"}
}