{
  "type": "Feature",
  "properties": {
    "iso:country":"CA",
    "sg:address":"3105 Rue Dessaulles",
    "sg:city":"Saint-Hyacinthe",
    "sg:classifiers":[
        {
            "category":"Food & Beverages",
            "subcategory":"Groceries & Convenience Stores",
            "type":"Retail Goods"
        }
    ],
    "sg:phone":"+1 450 773 8110",
    "sg:postcode":"J2S 2W1",
    "sg:province":"QC",
    "wof:name":"Couche-Tard",
    "wof:placetype":"venue"
},
  "geometry": {"coordinates":[-72.9609909058,45.6189537048],"type":"Point"}
}