{
  "type": "Feature",
  "properties": {
    "addr:full":"1505 1 Ave NW Airdrie AB T4B 2L9",
    "addr:housenumber":"1505",
    "addr:postcode":"t4b 2l9",
    "addr:street":"1 Ave Nw",
    "iso:country":"CA",
    "sg:address":"1505 1 Ave NW",
    "sg:city":"Airdrie",
    "sg:classifiers":[
        {
            "category":"Education",
            "subcategory":"School",
            "type":"Public Place"
        }
    ],
    "sg:phone":"+1 403 948 7030",
    "sg:postcode":"T4B 2L9",
    "sg:province":"AB",
    "wof:name":"Ralph Mc Call School",
    "wof:placetype":"venue"
},
  "geometry": {"coordinates":[-114.0338974,51.2926750183],"type":"Point"}
}