{
  "type": "Feature",
  "properties": {
    "addr:full":"2 Maclean Crt Port Hawkesbury NS B9A 3K2",
    "addr:housenumber":"2",
    "addr:postcode":"b9a 3k2",
    "addr:street":"Maclean Crt",
    "iso:country":"CA",
    "sg:address":"2 Maclean Crt",
    "sg:city":"Port Hawkesbury",
    "sg:classifiers":[
        {
            "category":"Manufacturing",
            "subcategory":"Printing",
            "type":"Manufacturing & Wholesale Goods"
        }
    ],
    "sg:phone":"+1 902 625 3300",
    "sg:postcode":"B9A 3K2",
    "sg:province":"NS",
    "sg:tags":[
        "newspaper"
    ],
    "wof:name":"Reporter",
    "wof:placetype":"venue"
},
  "geometry": {"coordinates":[-61.331715,45.617668],"type":"Point"}
}