{
  "type": "Feature",
  "properties": {
    "addr:full":"Edmonton AB T5K 2S6",
    "addr:postcode":"t5k 2s6",
    "iso:country":"CA",
    "sg:city":"Edmonton",
    "sg:classifiers":[
        {
            "category":"Professional",
            "subcategory":"Computer Services",
            "type":"Services"
        }
    ],
    "sg:phone":"+1 780 451 3089",
    "sg:postcode":"T5K 2S6",
    "sg:province":"AB",
    "sg:tags":[
        "consultant"
    ],
    "wof:name":"Cencomp Systems Solution Inc",
    "wof:placetype":"venue"
},
  "geometry": {"coordinates":[-113.517876,53.54166],"type":"Point"}
}