{
  "type": "Feature",
  "properties": {
    "addr:full":"Brampton ON L6V 1A9",
    "addr:postcode":"l6v 1a9",
    "iso:country":"CA",
    "sg:city":"Brampton",
    "sg:classifiers":[
        {
            "category":"Professional",
            "subcategory":"Lawyer & Legal Services",
            "type":"Services"
        }
    ],
    "sg:phone":"+1 905 453 3223",
    "sg:postcode":"L6V 1A9",
    "sg:province":"ON",
    "sg:tags":[
        "attorney"
    ],
    "wof:name":"Howick, David A L",
    "wof:placetype":"venue"
},
  "geometry": {"coordinates":[-79.75829299999999,43.687603],"type":"Point"}
}