{
  "type": "Feature",
  "properties": {
    "addr:full":"5240 Rumble St Burnaby BC V5J 2B6",
    "addr:housenumber":"5240",
    "addr:postcode":"v5j 2b6",
    "addr:street":"Rumble St",
    "iso:country":"CA",
    "sg:address":"5240 Rumble St",
    "sg:city":"Burnaby",
    "sg:classifiers":[
        {
            "category":"Restaurant",
            "type":"Food & Drink"
        }
    ],
    "sg:phone":"+1 604 438 1215",
    "sg:postcode":"V5J 2B6",
    "sg:province":"BC",
    "wof:name":"Jing Yuan Chinese Restaurant",
    "wof:placetype":"venue"
},
  "geometry": {"coordinates":[-122.987747192,49.2146224976],"type":"Point"}
}