{
  "type": "Feature",
  "properties": {
    "addr:full":"834 Appleby Line Burlington ON L7L 2Y7",
    "addr:housenumber":"834",
    "addr:postcode":"l7l 2y7",
    "addr:street":"Appleby Line",
    "iso:country":"CA",
    "sg:address":"834 Appleby Line",
    "sg:city":"Burlington",
    "sg:classifiers":[
        {
            "category":"Wholesale",
            "subcategory":"Scrap",
            "type":"Manufacturing & Wholesale Goods"
        }
    ],
    "sg:phone":"+1 905 639 9939",
    "sg:postcode":"L7L 2Y7",
    "sg:province":"ON",
    "sg:tags":[
        "metal",
        "iron"
    ],
    "wof:name":"Dominion Nickel Alloys Ltd",
    "wof:placetype":"venue"
},
  "geometry": {"coordinates":[-79.76664700000001,43.376652],"type":"Point"}
}