{
  "type": "Feature",
  "properties": {
    "iso:country":"CA",
    "sg:city":"Mississauga",
    "sg:classifiers":[
        {
            "category":"Wholesale",
            "subcategory":"Office Equipment",
            "type":"Manufacturing & Wholesale Goods"
        }
    ],
    "sg:phone":"+1 905 238 0818",
    "sg:postcode":"L4X 2T8",
    "sg:province":"ON",
    "sg:tags":[
        "accounting",
        "bookkeeping",
        "system"
    ],
    "wof:name":"M R Financial Svc",
    "wof:placetype":"venue"
},
  "geometry": {"coordinates":[-79.571083,43.621433],"type":"Point"}
}