{
  "type": "Feature",
  "properties": {
    "addr:full":"196 Rue Saint-Jacques Saint-Jacques QC J0K 2R0",
    "addr:housenumber":"196",
    "addr:postcode":"j0k 2r0",
    "addr:street":"Rue Saint-Jacques",
    "iso:country":"CA",
    "sg:address":"196 Rue Saint-Jacques",
    "sg:city":"Saint-Jacques",
    "sg:classifiers":[
        {
            "category":"Local Transit",
            "type":"Transportation"
        }
    ],
    "sg:phone":"+1 450 839 3611",
    "sg:postcode":"J0K 2R0",
    "sg:province":"QC",
    "sg:tags":[
        "bus",
        "line"
    ],
    "wof:name":"Autobus Laurin",
    "wof:placetype":"venue"
},
  "geometry": {"coordinates":[-73.575881958,45.9519348145],"type":"Point"}
}