{
  "type": "Feature",
  "properties": {
    "iso:country":"CA",
    "sg:address":"2485 Boul Sainte-Anne",
    "sg:city":"Quebec",
    "sg:classifiers":[
        {
            "category":"Shopping",
            "subcategory":"Shoes",
            "type":"Retail Goods"
        }
    ],
    "sg:phone":"+1 418 660 1530",
    "sg:postcode":"G1J 1Y4",
    "sg:province":"QC",
    "wof:name":"Naturalizer",
    "wof:placetype":"venue"
},
  "geometry": {"coordinates":[-71.215675354,46.8439407349],"type":"Point"}
}