{
  "type": "Feature",
  "properties": {
    "addr:full":"116 Lower Ganges Rd Salt Spring Island BC V8K 2S8",
    "addr:housenumber":"116",
    "addr:postcode":"v8k 2s8",
    "addr:street":"Lower Ganges Rd",
    "iso:country":"CA",
    "sg:address":"116 Lower Ganges Rd",
    "sg:city":"Salt Spring Island",
    "sg:classifiers":[
        {
            "category":"Food & Beverages",
            "subcategory":"Specialty",
            "type":"Retail Goods"
        }
    ],
    "sg:phone":"+1 250 537 2325",
    "sg:postcode":"V8K 2S8",
    "sg:province":"BC",
    "sg:tags":[
        "vitamin"
    ],
    "wof:name":"Salt Spring Natureworks",
    "wof:placetype":"venue"
},
  "geometry": {"coordinates":[-123.499985,48.852997],"type":"Point"}
}