{
  "type": "Feature",
  "properties": {
    "addr:full":"Calgary AB T2G 4R3",
    "addr:postcode":"t2g 4r3",
    "iso:country":"CA",
    "sg:city":"Calgary",
    "sg:classifiers":[
        {
            "category":"Home & Garden",
            "subcategory":"Home Furnishings",
            "type":"Retail Goods"
        }
    ],
    "sg:phone":"+1 403 243 3101",
    "sg:postcode":"T2G 4R3",
    "sg:province":"AB",
    "sg:tags":[
        "awning",
        "canopy",
        "lighting"
    ],
    "wof:name":"Sun Trend",
    "wof:placetype":"venue"
},
  "geometry": {"coordinates":[-114.066650391,51.0104293823],"type":"Point"}
}