{
  "type": "Feature",
  "properties": {
    "addr:full":"859 Hwy 6 N Millgrove ON L0R 1V0",
    "addr:housenumber":"859",
    "addr:postcode":"l0r 1v0",
    "addr:street":"Hwy 6 N",
    "iso:country":"CA",
    "sg:address":"859 Hwy 6 N",
    "sg:city":"Millgrove",
    "sg:classifiers":[
        {
            "category":"Retail",
            "subcategory":"Auto Repair",
            "type":"Services"
        }
    ],
    "sg:phone":"+1 905 689 4719",
    "sg:postcode":"L0R 1V0",
    "sg:province":"ON",
    "sg:tags":[
        "repairing",
        "automobile"
    ],
    "wof:name":"Safety Auto Svc",
    "wof:placetype":"venue"
},
  "geometry": {"coordinates":[-79.9506454468,43.3360137939],"type":"Point"}
}