{
  "type": "Feature",
  "properties": {
    "addr:full":"845 Rte Marie-Victorin Saint-Nicolas QC G7A 3S8",
    "addr:housenumber":"845",
    "addr:postcode":"g7a 3s8",
    "addr:street":"Rte Marie-Victorin",
    "iso:country":"CA",
    "sg:address":"845 Rte Marie-Victorin",
    "sg:city":"Saint-Nicolas",
    "sg:classifiers":[
        {
            "category":"Health Services",
            "subcategory":"Doctor",
            "type":"Services"
        }
    ],
    "sg:phone":"+1 418 831 1112",
    "sg:postcode":"G7A 3S8",
    "sg:province":"QC",
    "sg:tags":[
        "clinic",
        "dentist"
    ],
    "wof:name":"Clinique Dentaire Sandra",
    "wof:placetype":"venue"
},
  "geometry": {"coordinates":[-71.34831200000001,46.715527],"type":"Point"}
}