{
  "type": "Feature",
  "properties": {
    "addr:full":"8640 Glendon Dr Mount Brydges ON N0L 1W0",
    "addr:housenumber":"8640",
    "addr:postcode":"n0l 1w0",
    "addr:street":"Glendon Dr",
    "iso:country":"CA",
    "sg:address":"8640 Glendon Dr",
    "sg:city":"Mount Brydges",
    "sg:classifiers":[
        {
            "category":"Building & Trades",
            "subcategory":"Landscaping Services",
            "type":"Services"
        }
    ],
    "sg:phone":"+1 519 264 2346",
    "sg:postcode":"N0L 1W0",
    "sg:province":"ON",
    "sg:tags":[
        "landscape",
        "contractor"
    ],
    "wof:name":"Pinewood Horticultural Svc Inc",
    "wof:placetype":"venue"
},
  "geometry": {"coordinates":[-81.496574,42.909306],"type":"Point"}
}