{
  "type": "Feature",
  "properties": {
    "addr:full":"3514 Joseph Howe Dr Halifax NS B3L 4H7",
    "addr:housenumber":"3514",
    "addr:postcode":"b3l 4h7",
    "addr:street":"Joseph Howe Dr",
    "iso:country":"CA",
    "sg:address":"3514 Joseph Howe Dr",
    "sg:city":"Halifax",
    "sg:classifiers":[
        {
            "category":"Home & Garden",
            "subcategory":"Household Appliances",
            "type":"Retail Goods"
        }
    ],
    "sg:phone":"+1 902 455 8200",
    "sg:postcode":"B3L 4H7",
    "sg:province":"NS",
    "sg:tags":[
        "cleaners",
        "vacuum"
    ],
    "wof:name":"Electrolux Canada",
    "wof:placetype":"venue"
},
  "geometry": {"coordinates":[-63.6299476624,44.6555862427],"type":"Point"}
}