{
  "type": "Feature",
  "properties": {
    "addr:full":"115 Burrows Ave E Melfort SK S0E 1A0",
    "addr:housenumber":"115",
    "addr:postcode":"s0e 1a0",
    "addr:street":"Burrows Ave E Melfort",
    "iso:country":"CA",
    "sg:address":"115 Burrows Ave E",
    "sg:city":"Melfort",
    "sg:classifiers":[
        {
            "category":"Autos & Motor Vehicles",
            "subcategory":"Automobile Sales",
            "type":"Retail Goods"
        }
    ],
    "sg:phone":"+1 306 752 2886",
    "sg:postcode":"S0E 1A0",
    "sg:province":"SK",
    "sg:tags":[
        "car",
        "dealer"
    ],
    "wof:name":"Melody Motors Ltd",
    "wof:placetype":"venue"
},
  "geometry": {"coordinates":[-104.610214,52.860245],"type":"Point"}
}