{
  "type": "Feature",
  "properties": {
    "addr:full":"11440 29 St SE Calgary AB T2Z 3V5",
    "addr:housenumber":"11440",
    "addr:postcode":"t2z 3v5",
    "addr:street":"29 St Se",
    "iso:country":"CA",
    "sg:address":"11440 29 St SE",
    "sg:city":"Calgary",
    "sg:classifiers":[
        {
            "category":"Wholesale",
            "subcategory":"Scrap",
            "type":"Manufacturing & Wholesale Goods"
        }
    ],
    "sg:phone":"+1 403 203 0666",
    "sg:postcode":"T2Z 3V5",
    "sg:province":"AB",
    "sg:tags":[
        "recycling",
        "can",
        "bottle",
        "depot"
    ],
    "wof:name":"Deerfoot Bottle Depot Ltd",
    "wof:placetype":"venue"
},
  "geometry": {"coordinates":[-113.994576,50.952061],"type":"Point"}
}