{
  "type": "Feature",
  "properties": {
    "addr:full":"1938 Montreal Rd Gloucester ON K1J 6N2",
    "addr:housenumber":"1938",
    "addr:postcode":"k1j 6n2",
    "addr:street":"Montreal Rd",
    "iso:country":"CA",
    "sg:address":"1938 Montreal Rd",
    "sg:city":"Gloucester",
    "sg:classifiers":[
        {
            "category":"Retail",
            "subcategory":"Laundry & Dry Cleaning",
            "type":"Services"
        }
    ],
    "sg:phone":"+1 613 742 1847",
    "sg:postcode":"K1J 6N2",
    "sg:province":"ON",
    "sg:tags":[
        "cleaners"
    ],
    "wof:name":"Hill Cleaners",
    "wof:placetype":"venue"
},
  "geometry": {"coordinates":[-75.597183,45.445808],"type":"Point"}
}