{
  "type": "Feature",
  "properties": {
    "addr:full":"1229 King Rd King City ON L7B 1K5",
    "addr:housenumber":"1229",
    "addr:postcode":"l7b 1k5",
    "addr:street":"King Rd",
    "iso:country":"CA",
    "sg:address":"1229 King Rd",
    "sg:city":"King City",
    "sg:classifiers":[
        {
            "category":"Health Services",
            "subcategory":"Chiropractor",
            "type":"Services"
        }
    ],
    "sg:phone":"+1 905 773 5122",
    "sg:postcode":"L7B 1K5",
    "sg:province":"ON",
    "wof:name":"King City Natural Health Ctr",
    "wof:placetype":"venue"
},
  "geometry": {"coordinates":[-79.495895,43.935829],"type":"Point"}
}