{
  "type": "Feature",
  "properties": {
    "iso:country":"CA",
    "sg:address":"288 Princess St",
    "sg:city":"Winnipeg",
    "sg:classifiers":[
        {
            "category":"Wholesale",
            "subcategory":"Machinery & Supplies",
            "type":"Manufacturing & Wholesale Goods"
        }
    ],
    "sg:phone":"+1 204 947 1991",
    "sg:postcode":"R3B 1M3",
    "sg:province":"MB",
    "sg:tags":[
        "equipment",
        "motel",
        "hotel"
    ],
    "wof:name":"Westwin Food Equipment Ltd",
    "wof:placetype":"venue"
},
  "geometry": {"coordinates":[-97.138397,49.903805],"type":"Point"}
}