{
  "type": "Feature",
  "properties": {
    "addr:full":"1095 Ellis St Kelowna BC V1Y 1Z3",
    "addr:housenumber":"1095",
    "addr:postcode":"v1y 1z3",
    "addr:street":"Ellis St",
    "iso:country":"CA",
    "sg:address":"1095 Ellis St",
    "sg:city":"Kelowna",
    "sg:classifiers":[
        {
            "category":"Manufacturing",
            "subcategory":"Metals",
            "type":"Manufacturing & Wholesale Goods"
        }
    ],
    "sg:phone":"+1 250 762 2422",
    "sg:postcode":"V1Y 1Z3",
    "sg:province":"BC",
    "sg:tags":[
        "lumber",
        "dry wall",
        "contractor"
    ],
    "wof:name":"O K Builders Supplies Ltd",
    "wof:placetype":"venue"
},
  "geometry": {"coordinates":[-119.49336242699999,49.8955726624],"type":"Point"}
}