{
  "type": "Feature",
  "properties": {
    "addr:full":"91 Hospital Rd Sherbrooke NS B0J 3C0",
    "addr:housenumber":"91",
    "addr:postcode":"b0j 3c0",
    "addr:street":"Hospital Rd",
    "iso:country":"CA",
    "sg:address":"91 Hospital Rd",
    "sg:city":"Sherbrooke",
    "sg:classifiers":[
        {
            "category":"Health Services",
            "subcategory":"Doctor",
            "type":"Services"
        }
    ],
    "sg:phone":"+1 902 522 2275",
    "sg:postcode":"B0J 3C0",
    "sg:province":"NS",
    "sg:tags":[
        "physician",
        "surgeon"
    ],
    "wof:name":"St Mary's Medical Clinic",
    "wof:placetype":"venue"
},
  "geometry": {"coordinates":[-61.982254,45.146111],"type":"Point"}
}