{
  "type": "Feature",
  "properties": {
    "addr:full":"4266 Henderson Rd Milton ON L9T 2X5",
    "addr:housenumber":"4266",
    "addr:postcode":"l9t 2x5",
    "addr:street":"Henderson Rd",
    "iso:country":"CA",
    "sg:address":"4266 Henderson Rd",
    "sg:city":"Milton",
    "sg:classifiers":[
        {
            "category":"Building & Trades",
            "subcategory":"Landscaping Services",
            "type":"Services"
        }
    ],
    "sg:phone":"+1 905 878 2488",
    "sg:postcode":"L9T 2X5",
    "sg:province":"ON",
    "sg:tags":[
        "lawn",
        "contractor",
        "landscape",
        "maintenance",
        "grounds"
    ],
    "wof:name":"Henry's Lawn & Garden Mntnc",
    "wof:placetype":"venue"
},
  "geometry": {"coordinates":[-79.805305,43.456387],"type":"Point"}
}