{
  "type": "Feature",
  "properties": {
    "addr:full":"2886 Commercial Dr Vancouver BC V5N 4C6",
    "addr:housenumber":"2886",
    "addr:postcode":"v5n 4c6",
    "addr:street":"Commercial Dr",
    "iso:country":"CA",
    "sg:address":"2886 Commercial Dr",
    "sg:city":"Vancouver",
    "sg:classifiers":[
        {
            "category":"Retail",
            "subcategory":"Auto Repair",
            "type":"Services"
        }
    ],
    "sg:phone":"+1 604 872 8551",
    "sg:postcode":"V5N 4C6",
    "sg:province":"BC",
    "sg:tags":[
        "repairing",
        "automobile"
    ],
    "wof:name":"Grandview Tire & Auto Ctr",
    "wof:placetype":"venue"
},
  "geometry": {"coordinates":[-123.069633,49.258865],"type":"Point"}
}