{
  "type": "Feature",
  "properties": {
    "addr:full":"2404 Lake Shore Blvd W Etobicoke ON M8V 1C4",
    "addr:housenumber":"2404",
    "addr:postcode":"m8v 1c4",
    "addr:street":"Lake Shore Blvd W",
    "iso:country":"CA",
    "sg:address":"2404 Lake Shore Blvd W",
    "sg:city":"Etobicoke",
    "sg:classifiers":[
        {
            "category":"Home & Garden",
            "subcategory":"Hardware",
            "type":"Retail Goods"
        }
    ],
    "sg:phone":"+1 416 259 5111",
    "sg:postcode":"M8V 1C4",
    "sg:province":"ON",
    "wof:name":"Home Hardware Stores",
    "wof:placetype":"venue"
},
  "geometry": {"coordinates":[-79.488838,43.614864],"type":"Point"}
}