{
  "type": "Feature",
  "properties": {
    "addr:full":"Vancouver BC V5T 1S9",
    "addr:postcode":"v5t 1s9",
    "iso:country":"CA",
    "sg:city":"Vancouver",
    "sg:classifiers":[
        {
            "category":"Organizations",
            "subcategory":"Professional Association",
            "type":"Services"
        }
    ],
    "sg:phone":"+1 604 874 1741",
    "sg:postcode":"V5T 1S9",
    "sg:province":"BC",
    "wof:name":"Voice of the Cerebral Palsied",
    "wof:placetype":"venue"
},
  "geometry": {"coordinates":[-123.091454,49.263641],"type":"Point"}
}