{
  "type": "Feature",
  "properties": {
    "addr:full":"Leader SK S0N 1H0",
    "addr:postcode":"s0n 1h0",
    "addr:street":"Leader",
    "iso:country":"CA",
    "sg:city":"Leader",
    "sg:classifiers":[
        {
            "category":"Recreation",
            "type":"Entertainment"
        }
    ],
    "sg:phone":"+1 306 628 3256",
    "sg:postcode":"S0N 1H0",
    "sg:province":"SK",
    "sg:tags":[
        "course",
        "golf"
    ],
    "wof:name":"River Ridge Golf Club",
    "wof:placetype":"venue"
},
  "geometry": {"coordinates":[-109.536506653,50.8870353699],"type":"Point"}
}