{
  "type": "Feature",
  "properties": {
    "iso:country":"CA",
    "sg:address":"10807 82 Ave NW",
    "sg:city":"Edmonton",
    "sg:classifiers":[
        {
            "category":"Personal",
            "subcategory":"Beauty Salon",
            "type":"Services"
        }
    ],
    "sg:phone":"+1 780 413 3388",
    "sg:postcode":"T6E 2B2",
    "sg:province":"AB",
    "wof:name":"Captured Image Salon & Day Spa",
    "wof:placetype":"venue"
},
  "geometry": {"coordinates":[-113.509758,53.517834],"type":"Point"}
}