{
  "type": "Feature",
  "properties": {
    "addr:full":"Vancouver BC V6H 4C1",
    "addr:postcode":"v6h 4c1",
    "iso:country":"CA",
    "sg:city":"Vancouver",
    "sg:classifiers":[
        {
            "category":"Professional",
            "subcategory":"Lawyer & Legal Services",
            "type":"Services"
        }
    ],
    "sg:phone":"+1 604 734 4554",
    "sg:postcode":"V6H 4C1",
    "sg:province":"BC",
    "sg:tags":[
        "attorney"
    ],
    "wof:name":"Kerr Redekop Leinburd Boswell",
    "wof:placetype":"venue"
},
  "geometry": {"coordinates":[-123.134437561,49.2636795044],"type":"Point"}
}