{
  "type": "Feature",
  "properties": {
    "addr:full":"4035 Ogden Rd SE Calgary AB T2G 4N9",
    "addr:housenumber":"4035",
    "addr:postcode":"t2g 4n9",
    "addr:street":"Ogden Rd Se",
    "iso:country":"CA",
    "sg:address":"4035 Ogden Rd SE",
    "sg:city":"Calgary",
    "sg:classifiers":[
        {
            "category":"Freight",
            "type":"Transportation"
        }
    ],
    "sg:phone":"+1 403 640 9615",
    "sg:postcode":"T2G 4N9",
    "sg:province":"AB",
    "sg:tags":[
        "mover",
        "storage"
    ],
    "wof:name":"Beaver Moving & Storage Ltd",
    "wof:placetype":"venue"
},
  "geometry": {"coordinates":[-114.02874799999999,51.018326],"type":"Point"}
}