{
  "type": "Feature",
  "properties": {
    "addr:full":"146 Caribou Rd Channel-Port-Aux-Basques NL A0M 1C0",
    "addr:housenumber":"146",
    "addr:postcode":"a0m 1c0",
    "addr:street":"Caribou Rd",
    "iso:country":"CA",
    "sg:address":"146 Caribou Rd",
    "sg:city":"Channel-Port-Aux-Basques",
    "sg:classifiers":[
        {
            "category":"Travel",
            "subcategory":"Hotels & Motels",
            "type":"Entertainment"
        }
    ],
    "sg:phone":"+1 709 695 3500",
    "sg:postcode":"A0M 1C0",
    "sg:province":"NL",
    "wof:name":"St Christopher's Hotel",
    "wof:placetype":"venue"
},
  "geometry": {"coordinates":[-59.143604,47.581066],"type":"Point"}
}