{
  "type": "Feature",
  "properties": {
    "iso:country":"CA",
    "sg:address":"8 Rue Du Pere-Divet #9",
    "sg:city":"Sept-Iles",
    "sg:classifiers":[
        {
            "category":"Organizations",
            "subcategory":"Labor Organization",
            "type":"Services"
        }
    ],
    "sg:phone":"+1 418 968 3008",
    "sg:postcode":"G4R 3N2",
    "sg:province":"QC",
    "wof:name":"Fraternite Nationale Chrpntrs",
    "wof:placetype":"venue"
},
  "geometry": {"coordinates":[-66.38813018800001,50.2066383362],"type":"Point"}
}