{
  "type": "Feature",
  "properties": {
    "iso:country":"CA",
    "sg:address":"1975 Avenue Rd",
    "sg:city":"North York",
    "sg:classifiers":[
        {
            "category":"Shopping",
            "subcategory":"Clothing, Apparel, & Fashions",
            "type":"Retail Goods"
        }
    ],
    "sg:phone":"+1 416 489 1975",
    "sg:postcode":"M5M 4A3",
    "sg:province":"ON",
    "sg:tags":[
        "furnishing"
    ],
    "wof:name":"Brown's Short Man",
    "wof:placetype":"venue"
},
  "geometry": {"coordinates":[-79.4196090698,43.7346038818],"type":"Point"}
}