{
  "type": "Feature",
  "properties": {
    "iso:country":"CA",
    "sg:address":"9820 Main St",
    "sg:city":"Canning",
    "sg:classifiers":[
        {
            "category":"Wholesale",
            "subcategory":"Meat",
            "type":"Manufacturing & Wholesale Goods"
        }
    ],
    "sg:phone":"+1 902 582 3777",
    "sg:postcode":"B0P 1H0",
    "sg:province":"NS",
    "sg:tags":[
        "butchering"
    ],
    "wof:name":"Village Meat Store",
    "wof:placetype":"venue"
},
  "geometry": {"coordinates":[-64.431664,45.156918],"type":"Point"}
}