{
  "type": "Feature",
  "properties": {
    "addr:full":"495 Errol Rd W Sarnia ON N7V 2B8",
    "addr:housenumber":"495",
    "addr:postcode":"n7v 2b8",
    "addr:street":"Errol Rd W",
    "iso:country":"CA",
    "sg:address":"495 Errol Rd W",
    "sg:city":"Sarnia",
    "sg:classifiers":[
        {
            "category":"Real Estate",
            "subcategory":"Real Estate Operator",
            "type":"Services"
        }
    ],
    "sg:phone":"+1 519 332 6131",
    "sg:postcode":"N7V 2B8",
    "sg:province":"ON",
    "sg:tags":[
        "apartment"
    ],
    "wof:name":"Fairway Towers",
    "wof:placetype":"venue"
},
  "geometry": {"coordinates":[-82.395980835,42.990436554],"type":"Point"}
}