{
  "type": "Feature",
  "properties": {
    "addr:full":"101 Englemount Ave North York ON M6B 4L5",
    "addr:housenumber":"101",
    "addr:postcode":"m6b 4l5",
    "addr:street":"Englemount Ave",
    "iso:country":"CA",
    "sg:address":"101 Englemount Ave",
    "sg:city":"North York",
    "sg:classifiers":[
        {
            "category":"Education",
            "subcategory":"School",
            "type":"Public Place"
        }
    ],
    "sg:phone":"+1 416 395 2468",
    "sg:postcode":"M6B 4L5",
    "sg:province":"ON",
    "wof:name":"Glen Park Public School",
    "wof:placetype":"venue"
},
  "geometry": {"coordinates":[-79.4366760254,43.7134857178],"type":"Point"}
}