{
  "type": "Feature",
  "properties": {
    "addr:full":"1154 Lesperance Rd Windsor ON N8N 1X4",
    "addr:housenumber":"1154",
    "addr:postcode":"n8n 1x4",
    "addr:street":"Lesperance Rd",
    "iso:country":"CA",
    "sg:address":"1154 Lesperance Rd",
    "sg:city":"Windsor",
    "sg:classifiers":[
        {
            "category":"Restaurant",
            "type":"Food & Drink"
        }
    ],
    "sg:phone":"+1 519 735 3588",
    "sg:postcode":"N8N 1X4",
    "sg:province":"ON",
    "sg:tags":[
        "pizza"
    ],
    "wof:name":"Paul Castello's Pizza",
    "wof:placetype":"venue"
},
  "geometry": {"coordinates":[-83.033913,42.317822],"type":"Point"}
}