{
  "type": "Feature",
  "properties": {
    "addr:full":"8212 118 Ave NW Edmonton AB T5B 0S3",
    "addr:housenumber":"8212",
    "addr:postcode":"t5b 0s3",
    "addr:street":"118 Ave Nw",
    "iso:country":"CA",
    "sg:address":"8212 118 Ave NW",
    "sg:city":"Edmonton",
    "sg:classifiers":[
        {
            "category":"Social Services",
            "type":"Services"
        }
    ],
    "sg:phone":"+1 780 471 1122",
    "sg:postcode":"T5B 0S3",
    "sg:province":"AB",
    "sg:tags":[
        "counselor",
        "marriage",
        "family"
    ],
    "wof:name":"Catholic Social Svc",
    "wof:placetype":"venue"
},
  "geometry": {"coordinates":[-113.467598,53.570648],"type":"Point"}
}