{
  "type": "Feature",
  "properties": {
    "addr:full":"127 Curtis St St Thomas ON N5P 1J4",
    "addr:housenumber":"127",
    "addr:postcode":"n5p 1j4",
    "addr:street":"Curtis St",
    "iso:country":"CA",
    "sg:address":"127 Curtis St",
    "sg:city":"St Thomas",
    "sg:classifiers":[
        {
            "category":"Health Services",
            "subcategory":"Doctor",
            "type":"Services"
        }
    ],
    "sg:phone":"+1 519 631 1946",
    "sg:postcode":"N5P 1J4",
    "sg:province":"ON",
    "sg:tags":[
        "dentist"
    ],
    "wof:name":"Meadont",
    "wof:placetype":"venue"
},
  "geometry": {"coordinates":[-81.193741,42.779903],"type":"Point"}
}