{
  "type": "Feature",
  "properties": {
    "addr:full":"Calgary AB T2B 3P1",
    "addr:postcode":"t2b 3p1",
    "iso:country":"CA",
    "sg:city":"Calgary",
    "sg:classifiers":[
        {
            "category":"Wholesale",
            "subcategory":"Machinery & Supplies",
            "type":"Manufacturing & Wholesale Goods"
        }
    ],
    "sg:phone":"+1 403 236 7400",
    "sg:postcode":"T2B 3P1",
    "sg:province":"AB",
    "sg:tags":[
        "gasket"
    ],
    "wof:name":"Ags Group Inc",
    "wof:placetype":"venue"
},
  "geometry": {"coordinates":[-113.99884,51.014294],"type":"Point"}
}