{
  "type": "Feature",
  "properties": {
    "addr:full":"34 Simcoe St Barrie ON L4N 6T4",
    "addr:housenumber":"34",
    "addr:postcode":"l4n 6t4",
    "addr:street":"Simcoe St",
    "iso:country":"CA",
    "sg:address":"34 Simcoe St",
    "sg:city":"Barrie",
    "sg:classifiers":[
        {
            "category":"Social Services",
            "type":"Services"
        }
    ],
    "sg:phone":"+1 705 726 8861",
    "sg:postcode":"L4N 6T4",
    "sg:province":"ON",
    "sg:tags":[
        "organization",
        "welfare"
    ],
    "wof:name":"Kinark Child & Family Svc",
    "wof:placetype":"venue"
},
  "geometry": {"coordinates":[-79.69152832029999,44.3867835999],"type":"Point"}
}