{
  "type": "Feature",
  "properties": {
    "iso:country":"CA",
    "sg:address":"20 Airview Rd",
    "sg:city":"Etobicoke",
    "sg:classifiers":[
        {
            "category":"Home & Garden",
            "subcategory":"Building Materials",
            "type":"Retail Goods"
        }
    ],
    "sg:phone":"+1 416 742 0300",
    "sg:postcode":"M9W 4P2",
    "sg:province":"ON",
    "sg:tags":[
        "siding"
    ],
    "wof:name":"Gage Metal Cladding Ltd",
    "wof:placetype":"venue"
},
  "geometry": {"coordinates":[-79.57511901860001,43.7210617065],"type":"Point"}
}