{
  "type": "Feature",
  "properties": {
    "addr:full":"5739 Byrne Rd Burnaby BC V5J 3J1",
    "addr:housenumber":"5739",
    "addr:postcode":"v5j 3j1",
    "addr:street":"Byrne Rd",
    "iso:country":"CA",
    "sg:address":"5739 Byrne Rd",
    "sg:city":"Burnaby",
    "sg:classifiers":[
        {
            "category":"Retail",
            "subcategory":"Auto Repair",
            "type":"Services"
        }
    ],
    "sg:phone":"+1 604 439 0885",
    "sg:postcode":"V5J 3J1",
    "sg:province":"BC",
    "sg:tags":[
        "body",
        "automobile",
        "painting"
    ],
    "wof:name":"Fleetwood Auto Body",
    "wof:placetype":"venue"
},
  "geometry": {"coordinates":[-122.98030900000001,49.203037],"type":"Point"}
}