{
  "type": "Feature",
  "properties": {
    "addr:full":"1120 Devonshire Dr Regina SK S4X 3P2",
    "addr:housenumber":"1120",
    "addr:postcode":"s4x 3p2",
    "addr:street":"Devonshire Dr",
    "iso:country":"CA",
    "sg:address":"1120 Devonshire Dr",
    "sg:city":"Regina",
    "sg:classifiers":[
        {
            "category":"Personal",
            "type":"Services"
        }
    ],
    "sg:phone":"+1 306 775 0559",
    "sg:postcode":"S4X 3P2",
    "sg:province":"SK",
    "sg:tags":[
        "therapist",
        "massage"
    ],
    "wof:name":"Action Sports Remedial Massage",
    "wof:placetype":"venue"
},
  "geometry": {"coordinates":[-104.672813416,50.4961662292],"type":"Point"}
}