{
  "type": "Feature",
  "properties": {
    "addr:full":"301 North Railway St E Swift Current SK S9H 1C6",
    "addr:housenumber":"301",
    "addr:postcode":"s9h 1c6",
    "addr:street":"North Railway St E",
    "iso:country":"CA",
    "sg:address":"301 North Railway St E",
    "sg:city":"Swift Current",
    "sg:classifiers":[
        {
            "category":"Organizations",
            "subcategory":"Religious Organization",
            "type":"Services"
        }
    ],
    "sg:phone":"+1 306 773 3735",
    "sg:postcode":"S9H 1C6",
    "sg:province":"SK",
    "sg:tags":[
        "church"
    ],
    "wof:name":"Lifegiving Font Greek Orthodox",
    "wof:placetype":"venue"
},
  "geometry": {"coordinates":[-107.795959473,50.2820777893],"type":"Point"}
}