{
  "type": "Feature",
  "properties": {
    "iso:country":"CA",
    "sg:address":"23 E Lakeshore Rd",
    "sg:city":"St Malo",
    "sg:classifiers":[
        {
            "category":"Shopping",
            "subcategory":"Books",
            "type":"Retail Goods"
        }
    ],
    "sg:phone":"+1 204 347 5014",
    "sg:postcode":"R0A 1T0",
    "sg:province":"MB",
    "sg:tags":[
        "dealer"
    ],
    "wof:name":"Judith's Books",
    "wof:placetype":"venue"
},
  "geometry": {"coordinates":[-96.95025634770001,49.3160362244],"type":"Point"}
}