{
  "type": "Feature",
  "properties": {
    "addr:full":"67 Roche Killaloe ON K0J 2A0",
    "addr:housenumber":"67",
    "addr:postcode":"k0j 2a0",
    "addr:street":"Roche",
    "iso:country":"CA",
    "sg:address":"67 Roche",
    "sg:city":"Killaloe",
    "sg:classifiers":[
        {
            "category":"Travel",
            "subcategory":"Hotels & Motels",
            "type":"Entertainment"
        }
    ],
    "sg:phone":"+1 613 757 0950",
    "sg:postcode":"K0J 2A0",
    "sg:province":"ON",
    "sg:tags":[
        "reservation",
        "breakfast",
        "accommodation",
        "bed"
    ],
    "wof:name":"Annie's Inn",
    "wof:placetype":"venue"
},
  "geometry": {"coordinates":[-77.41961669920001,45.5645332336],"type":"Point"}
}