{
  "type": "Feature",
  "properties": {
    "addr:full":"30 Dover St Chatham ON N7L 1S6",
    "addr:housenumber":"30",
    "addr:postcode":"n7l 1s6",
    "addr:street":"Dover St",
    "iso:country":"CA",
    "sg:address":"30 Dover St",
    "sg:city":"Chatham",
    "sg:classifiers":[
        {
            "category":"Wholesale",
            "subcategory":"Hardware",
            "type":"Manufacturing & Wholesale Goods"
        }
    ],
    "sg:phone":"+1 519 352 7110",
    "sg:postcode":"N7L 1S6",
    "sg:province":"ON",
    "sg:tags":[
        "equipment",
        "heating",
        "system"
    ],
    "wof:name":"Mc Keough Supply Inc",
    "wof:placetype":"venue"
},
  "geometry": {"coordinates":[-82.18943,42.407387],"type":"Point"}
}