{
  "type": "Feature",
  "properties": {
    "iso:country":"CA",
    "sg:address":"3429 LA Grande-Allee",
    "sg:city":"Saint-Hubert",
    "sg:classifiers":[
        {
            "category":"Personal",
            "subcategory":"Tattoo Parlor",
            "type":"Services"
        }
    ],
    "sg:phone":"+1 450 445 0799",
    "sg:postcode":"J4T 2T4",
    "sg:province":"QC",
    "sg:tags":[
        "tattooing"
    ],
    "wof:name":"Tatouage Lgg Enr",
    "wof:placetype":"venue"
},
  "geometry": {"coordinates":[-73.473732,45.495113],"type":"Point"}
}