{
  "type": "Feature",
  "properties": {
    "addr:full":"2100 Av DE Marlowe Montreal QC H4A 3L5",
    "addr:housenumber":"2100",
    "addr:postcode":"h4a 3l5",
    "addr:street":"Av De Marlowe",
    "iso:country":"CA",
    "sg:address":"2100 Av DE Marlowe",
    "sg:city":"Montreal",
    "sg:classifiers":[
        {
            "category":"Health Services",
            "subcategory":"Doctor",
            "type":"Services"
        }
    ],
    "sg:phone":"+1 514 486 4980",
    "sg:postcode":"H4A 3L5",
    "sg:province":"QC",
    "sg:tags":[
        "physician",
        "surgeon"
    ],
    "wof:name":"Huglo, Evelyne MD",
    "wof:placetype":"venue"
},
  "geometry": {"coordinates":[-73.60623168950001,45.4744720459],"type":"Point"}
}