{
  "type": "Feature",
  "properties": {
    "addr:full":"Saint-Felicien QC G8K 1S7",
    "addr:postcode":"g8k 1s7",
    "iso:country":"CA",
    "sg:city":"Saint-Felicien",
    "sg:classifiers":[
        {
            "category":"Social Services",
            "type":"Services"
        }
    ],
    "sg:phone":"+1 418 630 3933",
    "sg:postcode":"G8K 1S7",
    "sg:province":"QC",
    "sg:tags":[
        "handicapped",
        "organization",
        "welfare"
    ],
    "wof:name":"Transport Adapte Pour Personne",
    "wof:placetype":"venue"
},
  "geometry": {"coordinates":[-72.4256744385,48.643245697],"type":"Point"}
}