{
  "type": "Feature",
  "properties": {
    "addr:full":"12528 93 Ave Surrey BC V3V 1K7",
    "addr:housenumber":"12528",
    "addr:postcode":"v3v 1k7",
    "addr:street":"93 Ave",
    "iso:country":"CA",
    "sg:address":"12528 93 Ave",
    "sg:city":"Surrey",
    "sg:classifiers":[
        {
            "category":"Professional",
            "subcategory":"Management & Consulting",
            "type":"Services"
        }
    ],
    "sg:phone":"+1 604 585 2119",
    "sg:postcode":"V3V 1K7",
    "sg:province":"BC",
    "sg:tags":[
        "aviation",
        "consultant"
    ],
    "wof:name":"Positronics Enterprises Ltd",
    "wof:placetype":"venue"
},
  "geometry": {"coordinates":[-122.875519,49.171635],"type":"Point"}
}