{
  "type": "Feature",
  "properties": {
    "iso:country":"CA",
    "sg:address":"177 Allard St",
    "sg:city":"Waterloo",
    "sg:classifiers":[
        {
            "category":"Building & Trades",
            "subcategory":"Construction",
            "type":"Services"
        }
    ],
    "sg:phone":"+1 450 539 3418",
    "sg:postcode":"J0E 2N0",
    "sg:province":"QC",
    "sg:tags":[
        "contractor"
    ],
    "wof:name":"Construction Paul-Andre Ares",
    "wof:placetype":"venue"
},
  "geometry": {"coordinates":[-72.5160980225,45.3435668945],"type":"Point"}
}